{
  "type": "Feature",
  "properties": {
    "addr:full":"Overtoom 73 Amsterdam North Holland 1054 HC",
    "addr:housenumber":"73",
    "addr:postcode":"1054 hc",
    "addr:street":"Overtoom",
    "iso:country":"NL",
    "sg:address":"Overtoom 73",
    "sg:city":"Amsterdam",
    "sg:classifiers":[
        {
            "category":"Communications",
            "subcategory":"Television Station",
            "type":"Services"
        }
    ],
    "sg:phone":"+31 20 412 0579",
    "sg:postcode":"1054 HC",
    "sg:province":"North Holland",
    "sg:tags":[
        "video",
        "audio",
        "verhuur"
    ],
    "wof:name":"Movie Center Videotheken",
    "wof:placetype":"venue"
},
  "geometry": {"coordinates":[4.87574,52.362648],"type":"Point"}
}