{
  "type": "Feature",
  "properties": {
    "addr:full":"Hoofdstraat 146 Sassenheim South Holland 2171 BL",
    "addr:housenumber":"146",
    "addr:postcode":"2171 bl",
    "addr:street":"Hoofdstraat",
    "iso:country":"NL",
    "sg:address":"Hoofdstraat 146",
    "sg:city":"Sassenheim",
    "sg:orig_category":"Kappers",
    "sg:phone":"+31 252 212 535",
    "sg:postcode":"2171 BL",
    "sg:province":"South Holland",
    "wof:name":"Avenue",
    "wof:placetype":"venue"
},
  "geometry": {"coordinates":[4.5166449547,52.2224006653],"type":"Point"}
}