{
  "type": "Feature",
  "properties": {
    "addr:full":"Burgemeester Vd Lelystr 11 Woudrichem Noord-Brabant 4285 BH",
    "addr:housenumber":"11",
    "addr:postcode":"4285 bh",
    "addr:street":"Burgemeester Vd Lelystr",
    "iso:country":"NL",
    "sg:address":"Burgemeester Vd Lelystr 11",
    "sg:city":"Woudrichem",
    "sg:orig_category":"Goederenvervoer Over De Weg",
    "sg:phone":"+31 6 53171695",
    "sg:postcode":"4285 BH",
    "sg:province":"Noord-Brabant",
    "wof:name":"Jbt",
    "wof:placetype":"venue"
},
  "geometry": {"coordinates":[5.000831,51.813404],"type":"Point"}
}