{
  "type": "Feature",
  "properties": {
    "iso:country":"NL",
    "sg:address":"Dorpsstr 1A",
    "sg:city":"Goirle",
    "sg:classifiers":[
        {
            "category":"Food & Beverages",
            "subcategory":"Candy",
            "type":"Retail Goods"
        }
    ],
    "sg:phone":"+31 13 534 2679",
    "sg:postcode":"5051 CH",
    "sg:province":"Noord-Brabant",
    "sg:tags":[
        "sport-",
        "en",
        "spelartikelen"
    ],
    "wof:name":"Wilkin",
    "wof:placetype":"venue"
},
  "geometry": {"coordinates":[5.066049,51.523182],"type":"Point"}
}