{
  "type": "Feature",
  "properties": {
    "addr:full":"Breedstr 99 Enkhuizen Noord-Holland 1601 KB",
    "addr:housenumber":"99",
    "addr:postcode":"1601 kb",
    "addr:street":"Breedstr",
    "iso:country":"NL",
    "sg:address":"Breedstr 99",
    "sg:city":"Enkhuizen",
    "sg:orig_category":"Onderhoudswerken",
    "sg:phone":"+31 6 53436256",
    "sg:postcode":"1601 KB",
    "sg:province":"Noord-Holland",
    "wof:name":"Desaunois",
    "wof:placetype":"venue"
},
  "geometry": {"coordinates":[5.2946,52.702431],"type":"Point"}
}