{
  "type": "Feature",
  "properties": {
    "addr:full":"Bosschendk 193 Oudenbosch Noord-Brabant 4731 DD",
    "addr:housenumber":"193",
    "addr:postcode":"4731 dd",
    "iso:country":"NL",
    "sg:address":"Bosschendk 193",
    "sg:city":"Oudenbosch",
    "sg:orig_category":"Bedrijfshuisvesting",
    "sg:phone":"+31 165 313 900",
    "sg:postcode":"4731 DD",
    "sg:province":"Noord-Brabant",
    "wof:name":"Handelscentr Oudenbosch",
    "wof:placetype":"venue"
},
  "geometry": {"coordinates":[4.551631,51.589581],"type":"Point"}
}