{
  "type": "Feature",
  "properties": {
    "iso:country":"NL",
    "sg:address":"Vd Dussenstr 4",
    "sg:city":"Geertruidenberg",
    "sg:orig_category":"Vertalers",
    "sg:phone":"+31 162 515 774",
    "sg:postcode":"4931 XT",
    "sg:province":"Noord-Brabant",
    "wof:name":"Neelissen & Van Paassen",
    "wof:placetype":"venue"
},
  "geometry": {"coordinates":[4.849791,51.70591],"type":"Point"}
}