{
  "type": "Feature",
  "properties": {
    "iso:country":"NL",
    "sg:address":"Brahmsstr 71",
    "sg:city":"Zevenaar",
    "sg:orig_category":"Adviesbureaus Bouwkunde",
    "sg:phone":"+31 316 524 863",
    "sg:postcode":"6904 DC",
    "sg:province":"Gelderland",
    "wof:name":"Jongh Bouwkundig Adviesbureau, De",
    "wof:placetype":"venue"
},
  "geometry": {"coordinates":[6.057038,51.927769],"type":"Point"}
}