{
  "type": "Feature",
  "properties": {
    "addr:full":"Postbus 2017 Sneek Provincie Friesland 8600 CA",
    "addr:housenumber":"2017",
    "addr:postcode":"8600 ca",
    "addr:street":"Postbus;Provincie Friesland",
    "iso:country":"NL",
    "sg:address":"Postbus 2017",
    "sg:city":"Sneek",
    "sg:orig_category":"Voetbalverenigingen",
    "sg:phone":"+31 515 427 307",
    "sg:postcode":"8600 CA",
    "sg:province":"Provincie Friesland",
    "wof:name":"Waterpoort Boys",
    "wof:placetype":"venue"
},
  "geometry": {"coordinates":[5.66197,53.033459],"type":"Point"}
}