{
  "type": "Feature",
  "properties": {
    "iso:country":"NL",
    "sg:address":"Van Ostadestraat 184",
    "sg:city":"Amsterdam",
    "sg:orig_category":"Glaszetten",
    "sg:phone":"+31 20 673 4512",
    "sg:postcode":"1072 TH",
    "sg:province":"North Holland",
    "wof:name":"Glasboetiek A.W. Ten Haaf Jr",
    "wof:placetype":"venue"
},
  "geometry": {"coordinates":[4.894206,52.352348],"type":"Point"}
}