{
  "type": "Feature",
  "properties": {
    "iso:country":"NL",
    "sg:address":"Hogeweg 8",
    "sg:city":"Deurne",
    "sg:orig_category":"Politie",
    "sg:phone":"+31 900 8844",
    "sg:postcode":"5751 KX",
    "sg:province":"North Brabant",
    "wof:name":"Politie Brabant Zuid-Oost Afdeling Deurne Asten So",
    "wof:placetype":"venue"
},
  "geometry": {"coordinates":[5.79516,51.461452],"type":"Point"}
}