{
  "type": "Feature",
  "properties": {
    "addr:full":"Steven Hoogendijkstraat 56 Rotterdam Zuid-Holland 3071 BW",
    "addr:housenumber":"56",
    "addr:postcode":"3071 bw",
    "addr:street":"Steven Hoogendijkstraat",
    "iso:country":"NL",
    "sg:address":"Steven Hoogendijkstraat 56",
    "sg:city":"Rotterdam",
    "sg:orig_category":"Kappers",
    "sg:phone":"+31 10 486 1116",
    "sg:postcode":"3071 BW",
    "sg:province":"Zuid-Holland",
    "wof:name":"Kapsalon Stieltjesplein",
    "wof:placetype":"venue"
},
  "geometry": {"coordinates":[4.5033707619,51.9104118347],"type":"Point"}
}