{
  "type": "Feature",
  "properties": {
    "addr:full":"Hoogdonksewg 4A Liessel Noord-Brabant 5757 PJ",
    "addr:housenumber":"4a",
    "addr:postcode":"5757 pj",
    "addr:street":"Hoogdonksewg",
    "iso:country":"NL",
    "sg:address":"Hoogdonksewg 4A",
    "sg:city":"Liessel",
    "sg:orig_category":"Tuinaanleg En -Onderhoud",
    "sg:phone":"+31 493 342 861",
    "sg:postcode":"5757 PJ",
    "sg:province":"Noord-Brabant",
    "wof:name":"Archituinen",
    "wof:placetype":"venue"
},
  "geometry": {"coordinates":[5.816467,51.428291],"type":"Point"}
}