{
  "type": "Feature",
  "properties": {
    "addr:full":"Portsmuiden 28 Amsterdam Noord-Holland 1046 AJ",
    "addr:housenumber":"28",
    "addr:postcode":"1046 aj",
    "addr:street":"Portsmuiden",
    "iso:country":"NL",
    "sg:address":"Portsmuiden 28",
    "sg:city":"Amsterdam",
    "sg:orig_category":"Daken And Skeletbouw",
    "sg:phone":"+31 20 611 3446",
    "sg:postcode":"1046 AJ",
    "sg:province":"Noord-Holland",
    "wof:name":"Dakdekkersbedrijf Buddingh Bv",
    "wof:placetype":"venue"
},
  "geometry": {"coordinates":[4.783203,52.390457],"type":"Point"}
}