{
  "type": "Feature",
  "properties": {
    "addr:full":"Lindelaan 20 Lelystad Flevoland 8224 KT",
    "addr:housenumber":"20",
    "addr:postcode":"8224 kt",
    "addr:street":"Lindelaan;Flevoland",
    "iso:country":"NL",
    "sg:address":"Lindelaan 20",
    "sg:city":"Lelystad",
    "sg:orig_category":"Overheidsdiensten",
    "sg:phone":"+31 320 274 911",
    "sg:postcode":"8224 KT",
    "sg:province":"Flevoland",
    "wof:name":"Waterschap Zuiderzeeland",
    "wof:placetype":"venue"
},
  "geometry": {"coordinates":[5.4807329178,52.511100769],"type":"Point"}
}