{
  "type": "Feature",
  "properties": {
    "addr:full":"Burgemeester Gilissenweg 44 Gennep Limburg 6591 ZR",
    "addr:housenumber":"44",
    "addr:postcode":"6591 zr",
    "addr:street":"Burgemeester Gilissenweg",
    "iso:country":"NL",
    "sg:address":"Burgemeester Gilissenweg 44",
    "sg:city":"Gennep",
    "sg:orig_category":"Boekhouders",
    "sg:phone":"+31 485 513 174",
    "sg:postcode":"6591 ZR",
    "sg:province":"Limburg",
    "wof:name":"L. Struik",
    "wof:placetype":"venue"
},
  "geometry": {"coordinates":[5.979127,51.68948],"type":"Point"}
}