{
  "type": "Feature",
  "properties": {
    "addr:full":"Spoorstr 3 Soest Utrecht 3761 AJ",
    "addr:housenumber":"3",
    "addr:postcode":"3761 aj",
    "addr:street":"Spoorstr",
    "iso:country":"NL",
    "sg:address":"Spoorstr 3",
    "sg:city":"Soest",
    "sg:orig_category":"Scholen Voor Basisonderwijs",
    "sg:phone":"+31 35 601 9975",
    "sg:postcode":"3761 AJ",
    "sg:province":"Utrecht",
    "wof:name":"Da Costa Prot Chr",
    "wof:placetype":"venue"
},
  "geometry": {"coordinates":[5.299625,52.183655],"type":"Point"}
}