{
  "type": "Feature",
  "properties": {
    "addr:full":"Waterdaal 3 Amersfoort Utrecht 3817 GV",
    "addr:housenumber":"3",
    "addr:postcode":"3817 gv",
    "addr:street":"Waterdaal",
    "iso:country":"NL",
    "sg:address":"Waterdaal 3",
    "sg:city":"Amersfoort",
    "sg:orig_category":"Scholen Voor Basisonderwijs",
    "sg:phone":"+31 33 461 4713",
    "sg:postcode":"3817 GV",
    "sg:province":"Utrecht",
    "wof:name":"Johannes Calvijn Reformatorisch",
    "wof:placetype":"venue"
},
  "geometry": {"coordinates":[5.386085,52.152325],"type":"Point"}
}