{
  "type": "Feature",
  "properties": {
    "addr:full":"Prinsenweide 13 Apeldoorn Gelderland 7317 BA",
    "addr:housenumber":"13",
    "addr:postcode":"7317 ba",
    "addr:street":"Prinsenweide;Gelderland",
    "iso:country":"NL",
    "sg:address":"Prinsenweide 13",
    "sg:city":"Apeldoorn",
    "sg:orig_category":"Koeltechniek",
    "sg:phone":"+31 55 521 5833",
    "sg:postcode":"7317 BA",
    "sg:province":"Gelderland",
    "wof:name":"Kmi Apeldoorn Bv",
    "wof:placetype":"venue"
},
  "geometry": {"coordinates":[5.971188,52.241184],"type":"Point"}
}