{
  "type": "Feature",
  "properties": {
    "addr:full":"Aalburgsestr 35 Wyk En Aalburg North Brabant 4261 BJ",
    "addr:housenumber":"35",
    "addr:postcode":"4261 bj",
    "addr:street":"Aalburgsestr",
    "iso:country":"NL",
    "sg:address":"Aalburgsestr 35",
    "sg:city":"Wyk En Aalburg",
    "sg:orig_category":"Montagebedrijven",
    "sg:phone":"+31 416 692 011",
    "sg:postcode":"4261 BJ",
    "sg:province":"North Brabant",
    "wof:name":"Arendse",
    "wof:placetype":"venue"
},
  "geometry": {"coordinates":[5.119152,51.753738],"type":"Point"}
}