{
  "type": "Feature",
  "properties": {
    "iso:country":"NL",
    "sg:address":"Conradstraat 8",
    "sg:city":"Amsterdam",
    "sg:orig_category":"Architecten",
    "sg:phone":"+31 20 320 8486",
    "sg:postcode":"1018 NG",
    "sg:province":"Noord-Holland",
    "wof:name":"Kruunenberg Van Der Erve Architecten",
    "wof:placetype":"venue"
},
  "geometry": {"coordinates":[4.9265,52.368687],"type":"Point"}
}