{
  "type": "Feature",
  "properties": {
    "addr:full":"Postbus 34 Gieten Provincie Drenthe 9460 AA",
    "addr:housenumber":"34",
    "addr:postcode":"9460 aa",
    "addr:street":"Postbus;Provincie Drenthe",
    "iso:country":"NL",
    "sg:address":"Postbus 34",
    "sg:city":"Gieten",
    "sg:orig_category":"Webdesign Bureaus",
    "sg:phone":"+31 592 300 679",
    "sg:postcode":"9460 AA",
    "sg:province":"Provincie Drenthe",
    "sg:website":"http://www.peppinfo.nl",
    "wof:name":"Peppinfo",
    "wof:placetype":"venue"
},
  "geometry": {"coordinates":[6.763879776,53.0058517456],"type":"Point"}
}