{
  "type": "Feature",
  "properties": {
    "addr:full":"De Pinnepot 6 Oostvoorne South Holland 3233 LP",
    "addr:housenumber":"6",
    "addr:postcode":"3233 lp",
    "addr:street":"De Pinnepot",
    "iso:country":"NL",
    "sg:address":"De Pinnepot 6",
    "sg:city":"Oostvoorne",
    "sg:orig_category":"Levensmiddelen- Grondstoffen - Fabrieken En Groothandel",
    "sg:phone":"+31 181 486 766",
    "sg:postcode":"3233 LP",
    "sg:province":"South Holland",
    "wof:name":"Dool Int Bv, Van Den",
    "wof:placetype":"venue"
},
  "geometry": {"coordinates":[4.116763,51.912338],"type":"Point"}
}