{
  "type": "Feature",
  "properties": {
    "addr:full":"Nicoline Swygmanstraat 59 Breda Noord-Brabant 4822 VD",
    "addr:housenumber":"59",
    "addr:postcode":"4822 vd",
    "addr:street":"Swygmanstraat",
    "iso:country":"NL",
    "sg:address":"Nicoline Swygmanstraat 59",
    "sg:city":"Breda",
    "sg:orig_category":"Boekhouders",
    "sg:phone":"+31 76 542 1647",
    "sg:postcode":"4822 VD",
    "sg:province":"Noord-Brabant",
    "wof:name":"D.L. Haegens",
    "wof:placetype":"venue"
},
  "geometry": {"coordinates":[4.728435,51.608635],"type":"Point"}
}