{
  "type": "Feature",
  "properties": {
    "iso:country":"NL",
    "sg:address":"Westkadijk 18",
    "sg:city":"Nijkerk Gld",
    "sg:orig_category":"Houten Verpakkingen Fab",
    "sg:phone":"+31 33 245 1941",
    "sg:postcode":"3861 MB",
    "sg:province":"Gelderland",
    "wof:name":"N. De Boer Bv",
    "wof:placetype":"venue"
},
  "geometry": {"coordinates":[5.479213,52.229321],"type":"Point"}
}