{
  "type": "Feature",
  "properties": {
    "addr:full":"Weerkruisln 97C Bennekom Gelderland 6721 BS",
    "addr:housenumber":"97c",
    "addr:postcode":"6721 bs",
    "addr:street":"Weerkruisln;Gelderland",
    "iso:country":"NL",
    "sg:address":"Weerkruisln 97C",
    "sg:city":"Bennekom",
    "sg:orig_category":"Loodgieters",
    "sg:phone":"+31 318 419 001",
    "sg:postcode":"6721 BS",
    "sg:province":"Gelderland",
    "wof:name":"Ginkel Bv, W Van",
    "wof:placetype":"venue"
},
  "geometry": {"coordinates":[5.675792,52.000942],"type":"Point"}
}