{
  "type": "Feature",
  "properties": {
    "addr:full":"Kerkweg 14 Schelluinen Zuid-Holland 4209 AE",
    "addr:housenumber":"14",
    "addr:postcode":"4209 ae",
    "addr:street":"Kerkweg",
    "iso:country":"NL",
    "sg:address":"Kerkweg 14",
    "sg:city":"Schelluinen",
    "sg:orig_category":"Verhuur Bouwmachines",
    "sg:phone":"+31 183 621 129",
    "sg:postcode":"4209 AE",
    "sg:province":"Zuid-Holland",
    "wof:name":"R. Sprong Grondverzet",
    "wof:placetype":"venue"
},
  "geometry": {"coordinates":[4.927148,51.843136],"type":"Point"}
}