{
  "type": "Feature",
  "properties": {
    "addr:full":"Mispelstr 18 S Gravenhage Zuid-Holland 2564 TR",
    "addr:housenumber":"18;gravenhage",
    "addr:postcode":"2564 tr",
    "addr:street":"Mispelstr;S",
    "iso:country":"NL",
    "sg:address":"Mispelstr 18",
    "sg:city":"S Gravenhage",
    "sg:orig_category":"Adviesbureaus Bedrijfsorganisatie",
    "sg:phone":"+31 6 54658978",
    "sg:postcode":"2564 TR",
    "sg:province":"Zuid-Holland",
    "sg:website":"http://www.mvmanagementsupport.nl",
    "wof:name":"Mv Management Support",
    "wof:placetype":"venue"
},
  "geometry": {"coordinates":[4.25946,52.06805],"type":"Point"}
}