{
  "type": "Feature",
  "properties": {
    "addr:full":"Prinses Beatrixlaan 34 Amerongen Utrecht 3958 XK",
    "addr:housenumber":"34",
    "addr:postcode":"3958 xk",
    "addr:street":"Prinses Beatrixlaan",
    "iso:country":"NL",
    "sg:address":"Prinses Beatrixlaan 34",
    "sg:city":"Amerongen",
    "sg:classifiers":[
        {
            "category":"Education",
            "subcategory":"Preschool",
            "type":"Public Place"
        }
    ],
    "sg:phone":"+31 343 452 466",
    "sg:postcode":"3958 XK",
    "sg:province":"Utrecht",
    "sg:tags":[
        "kleuteronderwijs",
        "basis-"
    ],
    "wof:name":"Cbs De Regenboog",
    "wof:placetype":"venue"
},
  "geometry": {"coordinates":[5.461498,52.003277],"type":"Point"}
}