{
  "type": "Feature",
  "properties": {
    "addr:full":"Dorpsstr 214 St Willebrord Noord-Brabant 4711 EN",
    "addr:housenumber":"214",
    "addr:postcode":"4711 en",
    "addr:street":"St",
    "iso:country":"NL",
    "sg:address":"Dorpsstr 214",
    "sg:city":"St Willebrord",
    "sg:orig_category":"Houtbewerking",
    "sg:phone":"+31 165 386 753",
    "sg:postcode":"4711 EN",
    "sg:province":"Noord-Brabant",
    "wof:name":"Jong, C De",
    "wof:placetype":"venue"
},
  "geometry": {"coordinates":[4.590881,51.555866],"type":"Point"}
}