{
  "type": "Feature",
  "properties": {
    "addr:full":"Huigsloterdk 238 Abbenes North Holland 2157 LN",
    "addr:housenumber":"238",
    "addr:postcode":"2157 ln",
    "iso:country":"NL",
    "sg:address":"Huigsloterdk 238",
    "sg:city":"Abbenes",
    "sg:orig_category":"Adviesbureaus Bedrijfsorganisatie",
    "sg:phone":"+31 252 545 100",
    "sg:postcode":"2157 LN",
    "sg:province":"North Holland",
    "wof:name":"Meer, Hans Van Der",
    "wof:placetype":"venue"
},
  "geometry": {"coordinates":[4.602271,52.215191],"type":"Point"}
}