{
  "type": "Feature",
  "properties": {
    "iso:country":"NL",
    "sg:address":"Danzigerkd 17",
    "sg:city":"Amsterdam",
    "sg:orig_category":"Grafisch Ontwerpers",
    "sg:phone":"+31 20 626 6233",
    "sg:postcode":"1013 AP",
    "sg:province":"Noord-Holland",
    "sg:website":"http://www.dedato.com",
    "wof:name":"Dedato Europe Bv",
    "wof:placetype":"venue"
},
  "geometry": {"coordinates":[4.893195,52.373119],"type":"Point"}
}