{
  "type": "Feature",
  "properties": {
    "addr:full":"Roermondsewg 66/D Weert Limburg 6004 AT",
    "addr:housenumber":"66 / d",
    "addr:postcode":"6004",
    "addr:street":"Roermondsewg",
    "iso:country":"NL",
    "sg:address":"Roermondsewg 66/D",
    "sg:city":"Weert",
    "sg:orig_category":"Automaterialen En Gereedschappen",
    "sg:phone":"+31 495 538 387",
    "sg:postcode":"6004 AT",
    "sg:province":"Limburg",
    "wof:name":"Vano",
    "wof:placetype":"venue"
},
  "geometry": {"coordinates":[5.721387,51.249218],"type":"Point"}
}