{
  "type": "Feature",
  "properties": {
    "addr:full":"Pastoorskuilenweg 4 Hoensbroek Limburg 6432 AC",
    "addr:housenumber":"4",
    "addr:postcode":"6432 ac",
    "addr:street":"Pastoorskuilenweg",
    "iso:country":"NL",
    "sg:address":"Pastoorskuilenweg 4",
    "sg:city":"Hoensbroek",
    "sg:orig_category":"Public Relationbureaus",
    "sg:phone":"+31 45 542 7469",
    "sg:postcode":"6432 AC",
    "sg:province":"Limburg",
    "wof:name":"Pr Actief",
    "wof:placetype":"venue"
},
  "geometry": {"coordinates":[5.922637,50.925636],"type":"Point"}
}