{
  "type": "Feature",
  "properties": {
    "addr:full":"Maastrichterln 13 Landgraaf Limburg 6374 VL",
    "addr:housenumber":"13",
    "addr:postcode":"6374 vl",
    "addr:street":"Maastrichterln",
    "iso:country":"NL",
    "sg:address":"Maastrichterln 13",
    "sg:city":"Landgraaf",
    "sg:orig_category":"Kappers",
    "sg:phone":"+31 45 531 2474",
    "sg:postcode":"6374 VL",
    "sg:province":"Limburg",
    "wof:name":"Meens",
    "wof:placetype":"venue"
},
  "geometry": {"coordinates":[6.041573,50.913082],"type":"Point"}
}