{
  "type": "Feature",
  "properties": {
    "iso:country":"NL",
    "sg:address":"Groot Ypelaardreef 16",
    "sg:city":"Breda",
    "sg:orig_category":"Autokeuringen",
    "sg:phone":"+31 76 565 6944",
    "sg:postcode":"4834 HD",
    "sg:province":"Noord-Brabant",
    "wof:name":"Jan Van Dooren Auto'S",
    "wof:placetype":"venue"
},
  "geometry": {"coordinates":[4.802289,51.574215],"type":"Point"}
}