{
  "type": "Feature",
  "properties": {
    "addr:full":"De Nederlanden 24 Noord Scharwoude Noord-Holland 1723 MG",
    "addr:housenumber":"24",
    "addr:postcode":"1723 mg",
    "addr:street":"De Nederlanden",
    "iso:country":"NL",
    "sg:address":"De Nederlanden 24",
    "sg:city":"Noord Scharwoude",
    "sg:orig_category":"Schilders",
    "sg:phone":"+31 226 315 632",
    "sg:postcode":"1723 MG",
    "sg:province":"Noord-Holland",
    "wof:name":"Coloury",
    "wof:placetype":"venue"
},
  "geometry": {"coordinates":[4.808708,52.701366],"type":"Point"}
}