{
  "type": "Feature",
  "properties": {
    "addr:full":"Ds Martin Luther Kingwg 68 Purmerend North Holland 1444 EE",
    "addr:housenumber":"68",
    "addr:postcode":"1444 ee",
    "addr:street":"Ds Martin Luther Kingwg",
    "iso:country":"NL",
    "sg:address":"Ds Martin Luther Kingwg 68",
    "sg:city":"Purmerend",
    "sg:orig_category":"Levende Dieren Gh",
    "sg:phone":"+31 299 429 525",
    "sg:postcode":"1444 EE",
    "sg:province":"North Holland",
    "wof:name":"R. Knaven",
    "wof:placetype":"venue"
},
  "geometry": {"coordinates":[4.966364,52.523125],"type":"Point"}
}