{
  "type": "Feature",
  "properties": {
    "iso:country":"NL",
    "sg:address":"Nw Zeelandwg 8-Z",
    "sg:city":"Amsterdam",
    "sg:orig_category":"Wasserijen",
    "sg:phone":"+31 20 619 9676",
    "sg:postcode":"1045 AL",
    "sg:province":"Noord-Holland",
    "wof:name":"Laundromatic Wasserij",
    "wof:placetype":"venue"
},
  "geometry": {"coordinates":[4.7939810753,52.4123497009],"type":"Point"}
}