{
  "type": "Feature",
  "properties": {
    "addr:full":"Burg V Fenemaplein 27 A Zandvoort North Holland 2042 TH",
    "addr:housenumber":"27 a",
    "addr:postcode":"2042 th",
    "addr:street":"Burg V Fenemaplein",
    "iso:country":"NL",
    "sg:address":"Burg V Fenemaplein 27 A",
    "sg:city":"Zandvoort",
    "sg:orig_category":"Fitnesscentra",
    "sg:phone":"+31 23 573 1289",
    "sg:postcode":"2042 TH",
    "sg:province":"North Holland",
    "wof:name":"Your Physic",
    "wof:placetype":"venue"
},
  "geometry": {"coordinates":[4.52729,52.370747],"type":"Point"}
}