{
  "type": "Feature",
  "properties": {
    "addr:full":"Buitenerf 123 Breda North Brabant 4824 HC",
    "addr:housenumber":"123",
    "addr:postcode":"4824 hc",
    "addr:street":"Buitenerf",
    "iso:country":"NL",
    "sg:address":"Buitenerf 123",
    "sg:city":"Breda",
    "sg:orig_category":"Diverse Grafische Activiteiten",
    "sg:phone":"+31 6 51670738",
    "sg:postcode":"4824 HC",
    "sg:province":"North Brabant",
    "wof:name":"Didesign & D",
    "wof:placetype":"venue"
},
  "geometry": {"coordinates":[4.7467,51.612679],"type":"Point"}
}