{
  "type": "Feature",
  "properties": {
    "addr:full":"Jan Stuytstraat 64 Haarlem Noord-Holland 2014 XL",
    "addr:housenumber":"64",
    "addr:postcode":"2014 xl",
    "addr:street":"Jan Stuytstraat",
    "iso:country":"NL",
    "sg:address":"Jan Stuytstraat 64",
    "sg:city":"Haarlem",
    "sg:orig_category":"Loodgieterswerk, Verwarming And Sanitaire Installaties",
    "sg:phone":"+31 6 24613950",
    "sg:postcode":"2014 XL",
    "sg:province":"Noord-Holland",
    "wof:name":"Van Den Berg Timmer & Onderhoud",
    "wof:placetype":"venue"
},
  "geometry": {"coordinates":[4.619291,52.376511],"type":"Point"}
}