{
  "type": "Feature",
  "properties": {
    "addr:full":"Voetboogstr 1B Amsterdam Noord-Holland 1012 XK",
    "addr:housenumber":"1b",
    "addr:postcode":"1012 xk",
    "addr:street":"Voetboogstr",
    "iso:country":"NL",
    "sg:address":"Voetboogstr 1B",
    "sg:city":"Amsterdam",
    "sg:orig_category":"Adviesbureaus Bedrijfsorganisatie",
    "sg:phone":"+31 20 623 7421",
    "sg:postcode":"1012 XK",
    "sg:province":"Noord-Holland",
    "wof:name":"Pol Bv, Van De",
    "wof:placetype":"venue"
},
  "geometry": {"coordinates":[4.890644,52.368729],"type":"Point"}
}