{
  "type": "Feature",
  "properties": {
    "addr:full":"F C Dondersstr 25 Utrecht Utrecht 3572 JB",
    "addr:housenumber":"25",
    "addr:postcode":"3572 jb",
    "addr:street":"F;Dondersstr",
    "iso:country":"NL",
    "sg:address":"F C Dondersstr 25",
    "sg:city":"Utrecht",
    "sg:orig_category":"Organisatiebureaus",
    "sg:phone":"+31 6 60543248",
    "sg:postcode":"3572 JB",
    "sg:province":"Utrecht",
    "wof:name":"Aediles",
    "wof:placetype":"venue"
},
  "geometry": {"coordinates":[5.1388511658,52.096912384],"type":"Point"}
}