{
  "type": "Feature",
  "properties": {
    "addr:full":"Pluympot 1 Delft Zuid-Holland 2611 LX",
    "addr:housenumber":"1",
    "addr:postcode":"2611 lx",
    "addr:street":"Pluympot",
    "iso:country":"NL",
    "sg:address":"Pluympot 1",
    "sg:city":"Delft",
    "sg:orig_category":"Drukkerijen",
    "sg:phone":"+31 15 214 2981",
    "sg:postcode":"2611 LX",
    "sg:province":"Zuid-Holland",
    "wof:name":"Tan Heck",
    "wof:placetype":"venue"
},
  "geometry": {"coordinates":[4.359433,52.013542],"type":"Point"}
}