{
  "type": "Feature",
  "properties": {
    "addr:full":"Maasdk 397 Veen Noord-Brabant 4264 AR",
    "addr:housenumber":"397",
    "addr:postcode":"4264",
    "addr:street":"Veen",
    "iso:country":"NL",
    "sg:address":"Maasdk 397",
    "sg:city":"Veen",
    "sg:orig_category":"Bloemen En Planten - Groothandel",
    "sg:phone":"+31 416 692 061",
    "sg:postcode":"4264 AR",
    "sg:province":"Noord-Brabant",
    "wof:name":"Wijk, Peter Van",
    "wof:placetype":"venue"
},
  "geometry": {"coordinates":[-92.131348,34.751888],"type":"Point"}
}