{
  "type": "Feature",
  "properties": {
    "iso:country":"NL",
    "sg:address":"Oogstplein 30",
    "sg:city":"Enschede",
    "sg:orig_category":"Kappers",
    "sg:phone":"+31 53 432 4994",
    "sg:postcode":"7545 HP",
    "sg:province":"Overijssel",
    "wof:name":"Haarstudio Benemonte",
    "wof:placetype":"venue"
},
  "geometry": {"coordinates":[6.8651418686,52.2118186951],"type":"Point"}
}