{
  "type": "Feature",
  "properties": {
    "iso:country":"NL",
    "sg:address":"Borgvlietsedreef 150",
    "sg:city":"Bergen Op Zoom",
    "sg:orig_category":"Bejaardeninstellingen And Serviceflats",
    "sg:phone":"+31 164 287 540",
    "sg:postcode":"4615 EJ",
    "sg:province":"North Brabant",
    "wof:name":"Stichting Serviceflat De Schelde",
    "wof:placetype":"venue"
},
  "geometry": {"coordinates":[4.28489,51.483524],"type":"Point"}
}