{
  "type": "Feature",
  "properties": {
    "addr:full":"Middenwg 221 Amsterdam Noord-Holland 1098 AN",
    "addr:housenumber":"221",
    "addr:postcode":"1098 an",
    "iso:country":"NL",
    "sg:address":"Middenwg 221",
    "sg:city":"Amsterdam",
    "sg:orig_category":"Webdesign Bureaus",
    "sg:phone":"+31 20 692 0541",
    "sg:postcode":"1098 AN",
    "sg:province":"Noord-Holland",
    "wof:name":"Allinone",
    "wof:placetype":"venue"
},
  "geometry": {"coordinates":[4.9372410774,52.34973526],"type":"Point"}
}