{
  "type": "Feature",
  "properties": {
    "iso:country":"NL",
    "sg:address":"Noorddammerweg 17",
    "sg:city":"Amstelveen",
    "sg:orig_category":"Loodgieterswerk, Verwarming And Sanitaire Installaties",
    "sg:phone":"+31 20 643 7071",
    "sg:postcode":"1187 CM",
    "sg:province":"Noord-Holland",
    "wof:name":"S & K",
    "wof:placetype":"venue"
},
  "geometry": {"coordinates":[4.832889,52.291946],"type":"Point"}
}