{
  "type": "Feature",
  "properties": {
    "addr:full":"Michelstraat 6 Zelhem Gelderland 7021 LV",
    "addr:housenumber":"6",
    "addr:postcode":"7021",
    "addr:street":"Michelstraat;Gelderland",
    "iso:country":"NL",
    "sg:address":"Michelstraat 6",
    "sg:city":"Zelhem",
    "sg:orig_category":"Loodgieterswerk, Verwarming And Sanitaire Installaties",
    "sg:phone":"+31 314 641 719",
    "sg:postcode":"7021 LV",
    "sg:province":"Gelderland",
    "wof:name":"Technisch Klussen Bedrijf Peter Kaak",
    "wof:placetype":"venue"
},
  "geometry": {"coordinates":[6.282005,52.010883],"type":"Point"}
}