{
  "type": "Feature",
  "properties": {
    "addr:full":"Ropsterwei 5 Oosternykerk Friesland 9137 RH",
    "addr:housenumber":"5",
    "addr:postcode":"9137 rh",
    "addr:street":"Ropsterwei",
    "iso:country":"NL",
    "sg:address":"Ropsterwei 5",
    "sg:city":"Oosternykerk",
    "sg:orig_category":"Architecten En Architectenbureaus",
    "sg:phone":"+31 519 241 550",
    "sg:postcode":"9137 RH",
    "sg:province":"Friesland",
    "wof:name":"Gunnar Daan, Doeke Van Wieren, Bv",
    "wof:placetype":"venue"
},
  "geometry": {"coordinates":[6.059543,53.373413],"type":"Point"}
}