{
  "type": "Feature",
  "properties": {
    "addr:full":"Jeroen Boschstraat 31 Oisterwijk North Brabant 5062 LD",
    "addr:housenumber":"31",
    "addr:postcode":"5062 ld",
    "addr:street":"Jeroen Boschstraat",
    "iso:country":"NL",
    "sg:address":"Jeroen Boschstraat 31",
    "sg:city":"Oisterwijk",
    "sg:orig_category":"Boekhouders",
    "sg:phone":"+31 13 528 3993",
    "sg:postcode":"5062 LD",
    "sg:province":"North Brabant",
    "wof:name":"Buro Voor Administraties F.W.Heiner",
    "wof:placetype":"venue"
},
  "geometry": {"coordinates":[5.188914,51.573803],"type":"Point"}
}