{
  "type": "Feature",
  "properties": {
    "addr:full":"Spoorstraat 15 Stadskanaal Groningen 9581 GA",
    "addr:housenumber":"15",
    "addr:postcode":"9581 ga",
    "addr:street":"Spoorstraat",
    "iso:country":"NL",
    "sg:address":"Spoorstraat 15",
    "sg:city":"Stadskanaal",
    "sg:orig_category":"Kampeerterreinen",
    "sg:phone":"+31 599 615 853",
    "sg:postcode":"9581 GA",
    "sg:province":"Groningen",
    "wof:name":"Mini-Camping 'T Nije Hof",
    "wof:placetype":"venue"
},
  "geometry": {"coordinates":[6.9430990219,52.9899978638],"type":"Point"}
}