{
  "type": "Feature",
  "properties": {
    "addr:full":"Baaiduinen 2 Terschelling Baaid Provincie Friesland 8884 HJ",
    "addr:housenumber":"2",
    "addr:postcode":"8884 hj",
    "addr:street":"Baaiduinen;Friesland",
    "iso:country":"NL",
    "sg:address":"Baaiduinen 2",
    "sg:city":"Terschelling Baaid",
    "sg:orig_category":"Vakantieverblijven",
    "sg:phone":"+31 562 448 664",
    "sg:postcode":"8884 HJ",
    "sg:province":"Provincie Friesland",
    "wof:name":"Atsma",
    "wof:placetype":"venue"
},
  "geometry": {"coordinates":[5.273395,53.376999],"type":"Point"}
}