{
  "type": "Feature",
  "properties": {
    "addr:full":"Nieuwstraat 57 Gilze North Brabant 5126 CB",
    "addr:housenumber":"57",
    "addr:postcode":"5126 cb",
    "addr:street":"Nieuwstraat",
    "iso:country":"NL",
    "sg:address":"Nieuwstraat 57",
    "sg:city":"Gilze",
    "sg:orig_category":"Boekhouders",
    "sg:phone":"+31 161 452 438",
    "sg:postcode":"5126 CB",
    "sg:province":"North Brabant",
    "wof:name":"Administratiekantoor En Belastingadviesburo Michie",
    "wof:placetype":"venue"
},
  "geometry": {"coordinates":[4.941986,51.54615],"type":"Point"}
}