{
  "type": "Feature",
  "properties": {
    "addr:full":"Satynbloem 67 Rotterdam Zuid-Holland 3068 JP",
    "addr:housenumber":"67",
    "addr:postcode":"3068 jp",
    "addr:street":"Satynbloem",
    "iso:country":"NL",
    "sg:address":"Satynbloem 67",
    "sg:city":"Rotterdam",
    "sg:orig_category":"Fotolaboratoria",
    "sg:phone":"+31 10 456 8866",
    "sg:postcode":"3068 JP",
    "sg:province":"Zuid-Holland",
    "wof:name":"Jg Bv",
    "wof:placetype":"venue"
},
  "geometry": {"coordinates":[4.532964,51.953476],"type":"Point"}
}