{
  "type": "Feature",
  "properties": {
    "addr:full":"Boulev De Wieling 4B Cadzand Zeeland 4506 JH",
    "addr:housenumber":"4b",
    "addr:postcode":"4506 jh",
    "addr:street":"Boulev De Wieling",
    "iso:country":"NL",
    "sg:address":"Boulev De Wieling 4B",
    "sg:city":"Cadzand",
    "sg:orig_category":"Discotheken",
    "sg:phone":"+31 117 396 073",
    "sg:postcode":"4506 JH",
    "sg:province":"Zeeland",
    "sg:website":"http://www.discojoy.nl",
    "wof:name":"Joy",
    "wof:placetype":"venue"
},
  "geometry": {"coordinates":[3.391363,51.37888],"type":"Point"}
}