{
  "type": "Feature",
  "properties": {
    "iso:country":"NL",
    "sg:address":"Rijksstraatweg 24",
    "sg:city":"Hellevoetsluis",
    "sg:orig_category":"Huishoudapparatuur, Televisies And Radio'S",
    "sg:phone":"+31 181 319 456",
    "sg:postcode":"3221 KA",
    "sg:province":"Zuid-Holland",
    "wof:name":"Vof Van Der Hoeven Audio/Video",
    "wof:placetype":"venue"
},
  "geometry": {"coordinates":[4.131573,51.833359],"type":"Point"}
}