{
  "type": "Feature",
  "properties": {
    "addr:full":"Turfstreek 272 Soest Utrecht 3766 HZ",
    "addr:housenumber":"272",
    "addr:postcode":"3766 hz",
    "addr:street":"Turfstreek",
    "iso:country":"NL",
    "sg:address":"Turfstreek 272",
    "sg:city":"Soest",
    "sg:orig_category":"Adviesbureaus Bouwkunde",
    "sg:phone":"+31 35 602 8718",
    "sg:postcode":"3766 HZ",
    "sg:province":"Utrecht",
    "wof:name":"Groosman, Gerard",
    "wof:placetype":"venue"
},
  "geometry": {"coordinates":[5.272887,52.16951],"type":"Point"}
}