{
  "type": "Feature",
  "properties": {
    "addr:full":"Obrechtstr 30 Zwolle Overijssel 8031 AZ",
    "addr:housenumber":"30",
    "addr:postcode":"8031 az",
    "addr:street":"Obrechtstr",
    "iso:country":"NL",
    "sg:address":"Obrechtstr 30",
    "sg:city":"Zwolle",
    "sg:orig_category":"Banden",
    "sg:phone":"+31 38 454 0445",
    "sg:postcode":"8031 AZ",
    "sg:province":"Overijssel",
    "sg:website":"http://www.kwik-fit.nl",
    "wof:name":"Kwik-Fit",
    "wof:placetype":"venue"
},
  "geometry": {"coordinates":[6.088296,52.522114],"type":"Point"}
}