{
  "type": "Feature",
  "properties": {
    "addr:full":"V Loostr 138 S Gravenhage Zuid-Holland 2582 XH",
    "addr:housenumber":"138;gravenhage",
    "addr:postcode":"2582 xh",
    "addr:street":"S",
    "iso:country":"NL",
    "sg:address":"V Loostr 138",
    "sg:city":"S Gravenhage",
    "sg:orig_category":"Glas, Porselein En Aardewerk",
    "sg:phone":"+31 70 358 7804",
    "sg:postcode":"2582 XH",
    "sg:province":"Zuid-Holland",
    "wof:name":"Stigter, B",
    "wof:placetype":"venue"
},
  "geometry": {"coordinates":[4.27852,52.092411],"type":"Point"}
}