{
  "type": "Feature",
  "properties": {
    "iso:country":"NL",
    "sg:address":"J Vermeerstr 46",
    "sg:city":"Zutphen",
    "sg:orig_category":"Verlichtingsartikelen - Fabrieken",
    "sg:phone":"+31 575 545 357",
    "sg:postcode":"7204 CN",
    "sg:province":"Gelderland",
    "wof:name":"Horst, G J",
    "wof:placetype":"venue"
},
  "geometry": {"coordinates":[-85.97782100000001,42.812248],"type":"Point"}
}