{
  "type": "Feature",
  "properties": {
    "addr:full":"Transportbaan 29 Winschoten Groningen 9672 BJ",
    "addr:housenumber":"29",
    "addr:postcode":"9672 bj",
    "addr:street":"Transportbaan",
    "iso:country":"NL",
    "sg:address":"Transportbaan 29",
    "sg:city":"Winschoten",
    "sg:orig_category":"Goederenvervoer Over De Weg",
    "sg:phone":"+31 597 413 856",
    "sg:postcode":"9672 BJ",
    "sg:province":"Groningen",
    "wof:name":"Drenth Transport Bv",
    "wof:placetype":"venue"
},
  "geometry": {"coordinates":[7.052341,53.147053],"type":"Point"}
}