{
  "type": "Feature",
  "properties": {
    "addr:full":"Haagstraat 26 Utrecht Utrecht 3581 SX",
    "addr:housenumber":"26",
    "addr:postcode":"3581 sx",
    "addr:street":"Haagstraat",
    "iso:country":"NL",
    "sg:address":"Haagstraat 26",
    "sg:city":"Utrecht",
    "sg:orig_category":"Goederenvervoer Over De Weg",
    "sg:phone":"+31 30 251 8336",
    "sg:postcode":"3581 SX",
    "sg:province":"Utrecht",
    "wof:name":"Peet'S Verhuisservice",
    "wof:placetype":"venue"
},
  "geometry": {"coordinates":[5.138353,52.0928],"type":"Point"}
}