{
  "type": "Feature",
  "properties": {
    "iso:country":"NL",
    "sg:address":"St Janstr 60",
    "sg:city":"Middelburg",
    "sg:orig_category":"Antiquiteiten",
    "sg:phone":"+31 118 624 260",
    "sg:postcode":"4331 KD",
    "sg:province":"Zeeland",
    "wof:name":"Heerlyckheid, De",
    "wof:placetype":"venue"
},
  "geometry": {"coordinates":[3.613961,51.496647],"type":"Point"}
}