{
  "type": "Feature",
  "properties": {
    "addr:full":"Schermerstraat 34 Haarlem Noord-Holland 2013 ET",
    "addr:housenumber":"34",
    "addr:postcode":"2013 et",
    "addr:street":"Schermerstraat",
    "iso:country":"NL",
    "sg:address":"Schermerstraat 34",
    "sg:city":"Haarlem",
    "sg:orig_category":"Public Relationbureaus",
    "sg:phone":"+31 23 542 2157",
    "sg:postcode":"2013 ET",
    "sg:province":"Noord-Holland",
    "wof:name":"Overmaat Communicatie-Advies",
    "wof:placetype":"venue"
},
  "geometry": {"coordinates":[4.625474,52.383381],"type":"Point"}
}