{
  "type": "Feature",
  "properties": {
    "addr:full":"Ruitersvaartseweg 38 Terheijden Noord-Brabant 4844 PJ",
    "addr:housenumber":"38",
    "addr:postcode":"4844 pj",
    "addr:street":"Ruitersvaartseweg",
    "iso:country":"NL",
    "sg:address":"Ruitersvaartseweg 38",
    "sg:city":"Terheijden",
    "sg:orig_category":"Juridische Dienstverlening",
    "sg:phone":"+31 76 593 3769",
    "sg:postcode":"4844 PJ",
    "sg:province":"Noord-Brabant",
    "wof:name":"Juridisch Adviesburo Mr. R.H. Donders",
    "wof:placetype":"venue"
},
  "geometry": {"coordinates":[4.755112,51.647423],"type":"Point"}
}