{
  "type": "Feature",
  "properties": {
    "iso:country":"NL",
    "sg:address":"Dorpsweg 124",
    "sg:city":"Twisk",
    "sg:orig_category":"Schilderwerk",
    "sg:phone":"+31 227 541 268",
    "sg:postcode":"1676 GH",
    "sg:province":"Noord-Holland",
    "wof:name":"Naastepad Schildersbedrijf",
    "wof:placetype":"venue"
},
  "geometry": {"coordinates":[5.06104,52.744186],"type":"Point"}
}