{
  "type": "Feature",
  "properties": {
    "addr:full":"Zandertje 30 Breskens Zeeland 4511 RH",
    "addr:housenumber":"30",
    "addr:postcode":"4511 rh",
    "addr:street":"Zandertje",
    "iso:country":"NL",
    "sg:address":"Zandertje 30",
    "sg:city":"Breskens",
    "sg:orig_category":"Kampeerterreinen",
    "sg:phone":"+31 117 381 428",
    "sg:postcode":"4511 RH",
    "sg:province":"Zeeland",
    "wof:name":"Camping Napoleonhoeve",
    "wof:placetype":"venue"
},
  "geometry": {"coordinates":[3.5152819157,51.4042358398],"type":"Point"}
}