{
  "type": "Feature",
  "properties": {
    "addr:full":"Hoenderhof 17 Delfzyl Groningen 9932 KK",
    "addr:housenumber":"17",
    "addr:postcode":"9932 kk",
    "addr:street":"Hoenderhof",
    "iso:country":"NL",
    "sg:address":"Hoenderhof 17",
    "sg:city":"Delfzyl",
    "sg:orig_category":"Facilitaire Dienstverlening",
    "sg:phone":"+31 596 681 199",
    "sg:postcode":"9932 KK",
    "sg:province":"Groningen",
    "wof:name":"Swint, John",
    "wof:placetype":"venue"
},
  "geometry": {"coordinates":[6.898349,53.316044],"type":"Point"}
}