{
  "type": "Feature",
  "properties": {
    "addr:full":"Spoordwarsstraat 6 Ijsselmuiden Overijssel 8271 RD",
    "addr:housenumber":"6",
    "addr:postcode":"8271 rd",
    "addr:street":"Spoordwarsstraat",
    "iso:country":"NL",
    "sg:address":"Spoordwarsstraat 6",
    "sg:city":"Ijsselmuiden",
    "sg:orig_category":"Autoreparatie And Auto-Onderhoud",
    "sg:phone":"+31 38 477 3376",
    "sg:postcode":"8271 RD",
    "sg:province":"Overijssel",
    "wof:name":"Clean Autopoetsbedrijf",
    "wof:placetype":"venue"
},
  "geometry": {"coordinates":[5.926329,52.55827],"type":"Point"}
}