{
  "type": "Feature",
  "properties": {
    "iso:country":"NL",
    "sg:address":"Hollantln 14",
    "sg:city":"Utrecht",
    "sg:orig_category":"Keukens",
    "sg:phone":"+31 30 288 8471",
    "sg:postcode":"3526 AM",
    "sg:province":"Utrecht",
    "sg:website":"http://www.brugman.nl",
    "wof:name":"Brugman",
    "wof:placetype":"venue"
},
  "geometry": {"coordinates":[5.104089,52.061699],"type":"Point"}
}