{
  "type": "Feature",
  "properties": {
    "addr:full":"Hollantln 14 Utrecht Utrecht 3526 AM",
    "addr:housenumber":"14",
    "addr:postcode":"3526",
    "addr:street":"Hollantln",
    "iso:country":"NL",
    "sg:address":"Hollantln 14",
    "sg:city":"Utrecht",
    "sg:orig_category":"Keukens",
    "sg:phone":"+31 30 288 8471",
    "sg:postcode":"3526 AM",
    "sg:province":"Utrecht",
    "sg:website":"http://www.brugman.nl",
    "wof:name":"Brugman",
    "wof:placetype":"venue"
},
  "geometry": {"coordinates":[5.104089,52.061699],"type":"Point"}
}