{
  "type": "Feature",
  "properties": {
    "iso:country":"NL",
    "sg:address":"Anklaarseweg 95 A",
    "sg:city":"Apeldoorn",
    "sg:orig_category":"Papier- And Kartonverpakkingen Fab",
    "sg:phone":"+31 55 533 0044",
    "sg:postcode":"7317 AS",
    "sg:province":"Gelderland",
    "wof:name":"Green Pack",
    "wof:placetype":"venue"
},
  "geometry": {"coordinates":[5.9708,52.235088],"type":"Point"}
}