{
  "type": "Feature",
  "properties": {
    "addr:full":"Anklaarseweg 95 A Apeldoorn Gelderland 7317 AS",
    "addr:housenumber":"95 a",
    "addr:postcode":"7317 as",
    "addr:street":"Anklaarseweg;Gelderland",
    "iso:country":"NL",
    "sg:address":"Anklaarseweg 95 A",
    "sg:city":"Apeldoorn",
    "sg:orig_category":"Papier- And Kartonverpakkingen Fab",
    "sg:phone":"+31 55 533 0044",
    "sg:postcode":"7317 AS",
    "sg:province":"Gelderland",
    "wof:name":"Green Pack",
    "wof:placetype":"venue"
},
  "geometry": {"coordinates":[5.9708,52.235088],"type":"Point"}
}