{
  "type": "Feature",
  "properties": {
    "addr:full":"Postbus 307 Baarle Nassau North Brabant 5110 AH",
    "addr:housenumber":"307",
    "addr:postcode":"5110 ah",
    "addr:street":"Postbus;Baarle Nassau",
    "iso:country":"NL",
    "sg:address":"Postbus 307",
    "sg:city":"Baarle Nassau",
    "sg:orig_category":"Voetbalverenigingen",
    "sg:phone":"+31 13 507 9696",
    "sg:postcode":"5110 AH",
    "sg:province":"North Brabant",
    "wof:name":"Gloria Uc",
    "wof:placetype":"venue"
},
  "geometry": {"coordinates":[4.92629,51.449741],"type":"Point"}
}