{
  "type": "Feature",
  "properties": {
    "iso:country":"NL",
    "sg:address":"J W Frisostr 116",
    "sg:city":"Sneek",
    "sg:orig_category":"Zonweringen",
    "sg:phone":"+31 515 415 190",
    "sg:postcode":"8606 XH",
    "sg:province":"Friesland",
    "wof:name":"Greidanus & Zn Zonwering",
    "wof:placetype":"venue"
},
  "geometry": {"coordinates":[5.668919,53.02496],"type":"Point"}
}