{
  "type": "Feature",
  "properties": {
    "addr:full":"Parallelstraat 67 (Westzijde) Rotterdam South Holland 3043 GM",
    "addr:housenumber":"67",
    "addr:postcode":"3043 gm",
    "addr:street":"Parallelstraat;Westzijde",
    "iso:country":"NL",
    "sg:address":"Parallelstraat 67 (Westzijde)",
    "sg:city":"Rotterdam",
    "sg:orig_category":"Autoreparatie And Auto-Onderhoud",
    "sg:phone":"+31 10 262 0802",
    "sg:postcode":"3043 GM",
    "sg:province":"South Holland",
    "sg:website":"http://www.carexpert.nl",
    "wof:name":"Car Expert",
    "wof:placetype":"venue"
},
  "geometry": {"coordinates":[4.423135,51.944004],"type":"Point"}
}