{
  "type": "Feature",
  "properties": {
    "addr:full":"Waterloostr 159 Rotterdam Zuid-Holland 3062 TM",
    "addr:housenumber":"159",
    "addr:postcode":"3062 tm",
    "iso:country":"NL",
    "sg:address":"Waterloostr 159",
    "sg:city":"Rotterdam",
    "sg:orig_category":"Onderhoudswerken",
    "sg:phone":"+31 10 414 1659",
    "sg:postcode":"3062 TM",
    "sg:province":"Zuid-Holland",
    "wof:name":"Rijnders, R",
    "wof:placetype":"venue"
},
  "geometry": {"coordinates":[4.513021,51.921329],"type":"Point"}
}