{
  "type": "Feature",
  "properties": {
    "addr:full":"Zuiderzeestrwg 209 Oldebroek Gelderland 8096 BJ",
    "addr:housenumber":"209",
    "addr:postcode":"8096 bj",
    "addr:street":"Gelderland",
    "iso:country":"NL",
    "sg:address":"Zuiderzeestrwg 209",
    "sg:city":"Oldebroek",
    "sg:orig_category":"Adviesbureaus Bedrijfsorganisatie",
    "sg:phone":"+31 525 631 379",
    "sg:postcode":"8096 BJ",
    "sg:province":"Gelderland",
    "wof:name":"Weerd En Partn, Van Der",
    "wof:placetype":"venue"
},
  "geometry": {"coordinates":[5.8934,52.445419],"type":"Point"}
}