{
  "type": "Feature",
  "properties": {
    "addr:full":"Burgemeester Mazairacln 123 Rosmalen Noord-Brabant 5242 AZ",
    "addr:housenumber":"123",
    "addr:postcode":"5242 az",
    "addr:street":"Burgemeester Mazairacln",
    "iso:country":"NL",
    "sg:address":"Burgemeester Mazairacln 123",
    "sg:city":"Rosmalen",
    "sg:orig_category":"Autokeuringen",
    "sg:phone":"+31 73 522 0310",
    "sg:postcode":"5242 AZ",
    "sg:province":"Noord-Brabant",
    "wof:name":"Jos Verhoeven Auto'S",
    "wof:placetype":"venue"
},
  "geometry": {"coordinates":[5.354356,51.710255],"type":"Point"}
}