{
  "type": "Feature",
  "properties": {
    "addr:full":"Haulerwg 62 Wolvega Friesland 8471 AM",
    "addr:housenumber":"62",
    "addr:postcode":"8471",
    "addr:street":"Haulerwg",
    "iso:country":"NL",
    "sg:address":"Haulerwg 62",
    "sg:city":"Wolvega",
    "sg:classifiers":[
        {
            "category":"Wholesale",
            "subcategory":"Meat",
            "type":"Manufacturing & Wholesale Goods"
        }
    ],
    "sg:phone":"+31 561 612 263",
    "sg:postcode":"8471 AM",
    "sg:province":"Friesland",
    "sg:tags":[
        "abattoir"
    ],
    "wof:name":"Feenstra Wolvega Bv",
    "wof:placetype":"venue"
},
  "geometry": {"coordinates":[5.995296,52.879898],"type":"Point"}
}