{
  "type": "Feature",
  "properties": {
    "addr:full":"De Sandery 5 Schoorl North Holland 1871 ER",
    "addr:housenumber":"5",
    "addr:postcode":"1871 er",
    "iso:country":"NL",
    "sg:address":"De Sandery 5",
    "sg:city":"Schoorl",
    "sg:orig_category":"Manueel Therapeuten",
    "sg:phone":"+31 72 509 2760",
    "sg:postcode":"1871 ER",
    "sg:province":"North Holland",
    "wof:name":"Praktijk Voor Fysiotherapie En Manuele Therapie",
    "wof:placetype":"venue"
},
  "geometry": {"coordinates":[4.691848,52.706627],"type":"Point"}
}