{
  "type": "Feature",
  "properties": {
    "addr:full":"Nw Keizersgr 22 Amsterdam North Holland 1018 DS",
    "addr:housenumber":"22",
    "addr:postcode":"1018 ds",
    "iso:country":"NL",
    "sg:address":"Nw Keizersgr 22",
    "sg:city":"Amsterdam",
    "sg:classifiers":[
        {
            "category":"Travel",
            "subcategory":"Hotels & Motels",
            "type":"Entertainment"
        }
    ],
    "sg:phone":"+31 20 626 0075",
    "sg:postcode":"1018 DS",
    "sg:province":"North Holland",
    "wof:name":"Synopsis",
    "wof:placetype":"venue"
},
  "geometry": {"coordinates":[4.903626,52.364483],"type":"Point"}
}