{
  "type": "Feature",
  "properties": {
    "addr:full":"Blankenweg 20 Bergen Op Zoom Noord-Brabant 4612 RC",
    "addr:housenumber":"20",
    "addr:postcode":"4612 rc",
    "addr:street":"Blankenweg",
    "iso:country":"NL",
    "sg:address":"Blankenweg 20",
    "sg:city":"Bergen Op Zoom",
    "sg:orig_category":"Displays, Showcards En Toonmaterialen",
    "sg:phone":"+31 164 662 660",
    "sg:postcode":"4612 RC",
    "sg:province":"Noord-Brabant",
    "sg:website":"http://www.hl-display.com",
    "wof:name":"Hl Nederland Bv",
    "wof:placetype":"venue"
},
  "geometry": {"coordinates":[4.26169,51.498947],"type":"Point"}
}