{
  "type": "Feature",
  "properties": {
    "iso:country":"NL",
    "sg:address":"Rododendronpln 6",
    "sg:city":"Rotterdam",
    "sg:orig_category":"Makelaars En Adviseurs Onroerende Goederen",
    "sg:phone":"+31 10 418 0515",
    "sg:postcode":"3053 ES",
    "sg:province":"South Holland",
    "sg:website":"http://www.spindlermakelaars.nl",
    "wof:name":"Spindler Nvm Makelaars",
    "wof:placetype":"venue"
},
  "geometry": {"coordinates":[4.472592,51.960117],"type":"Point"}
}