{
  "type": "Feature",
  "properties": {
    "addr:full":"Gedempte Biersloot 68 Vlaardingen South Holland 3131 HK",
    "addr:housenumber":"68",
    "addr:postcode":"3131 hk",
    "addr:street":"Gedempte Biersloot",
    "iso:country":"NL",
    "sg:address":"Gedempte Biersloot 68",
    "sg:city":"Vlaardingen",
    "sg:orig_category":"Fotostudio'S And Fotografen",
    "sg:phone":"+31 10 435 6881",
    "sg:postcode":"3131 HK",
    "sg:province":"South Holland",
    "wof:name":"Foto Studio Ronde",
    "wof:placetype":"venue"
},
  "geometry": {"coordinates":[4.341856,51.911259],"type":"Point"}
}