{
  "type": "Feature",
  "properties": {
    "addr:full":"Binnenwg 5 Twello Gelderland 7391 GK",
    "addr:housenumber":"5",
    "addr:postcode":"7391 gk",
    "addr:street":"Binnenwg;Gelderland",
    "iso:country":"NL",
    "sg:address":"Binnenwg 5",
    "sg:city":"Twello",
    "sg:orig_category":"Artsen - Huisartsen",
    "sg:phone":"+31 571 271 555",
    "sg:postcode":"7391 GK",
    "sg:province":"Gelderland",
    "wof:name":"Scholte & S P C Scholte-Talsma, A L",
    "wof:placetype":"venue"
},
  "geometry": {"coordinates":[6.107857,52.239452],"type":"Point"}
}