{
  "type": "Feature",
  "properties": {
    "iso:country":"NL",
    "sg:address":"Jol 1332",
    "sg:city":"Lelystad",
    "sg:orig_category":"Boeken En Tijdschriften",
    "sg:phone":"+31 320 244 143",
    "sg:postcode":"8243 EH",
    "sg:province":"Flevoland",
    "wof:name":"Komeet Vof, De",
    "wof:placetype":"venue"
},
  "geometry": {"coordinates":[5.446975,52.508324],"type":"Point"}
}