{
  "type": "Feature",
  "properties": {
    "iso:country":"NL",
    "sg:address":"Atalanta 11",
    "sg:city":"'S Gravendeel",
    "sg:orig_category":"Elektronische Bedrijfsinstallaties",
    "sg:phone":"+31 78 673 7206",
    "sg:postcode":"3295 PA",
    "sg:province":"Zuid-Holland",
    "wof:name":"Indusec Holland",
    "wof:placetype":"venue"
},
  "geometry": {"coordinates":[4.605798,51.786022],"type":"Point"}
}