{
  "type": "Feature",
  "properties": {
    "addr:full":"De Lytse Brekken 1 Follega Friesland 8535 XA",
    "addr:housenumber":"1",
    "addr:postcode":"8535 xa",
    "addr:street":"De Lytse Brekken",
    "iso:country":"NL",
    "sg:address":"De Lytse Brekken 1",
    "sg:city":"Follega",
    "sg:orig_category":"Hoefdierhouderijen",
    "sg:phone":"+31 513 432 659",
    "sg:postcode":"8535 XA",
    "sg:province":"Friesland",
    "wof:name":"Th. De Jong",
    "wof:placetype":"venue"
},
  "geometry": {"coordinates":[5.700924,52.898705],"type":"Point"}
}