{
  "type": "Feature",
  "properties": {
    "addr:full":"Hommerter Allee 1 Amstenrade Limburg 6436 AP",
    "addr:housenumber":"1",
    "addr:postcode":"6436 ap",
    "addr:street":"Hommerter Allee",
    "iso:country":"NL",
    "sg:address":"Hommerter Allee 1",
    "sg:city":"Amstenrade",
    "sg:classifiers":[
        {
            "category":"Professional",
            "subcategory":"Accounting & Tax Preparation",
            "type":"Services"
        }
    ],
    "sg:phone":"+31 46 442 5337",
    "sg:postcode":"6436 AP",
    "sg:province":"Limburg",
    "sg:tags":[
        "accountant",
        "en",
        "-kantoren",
        "register-"
    ],
    "wof:name":"Killaars Steeghs Groep",
    "wof:placetype":"venue"
},
  "geometry": {"coordinates":[5.924633,50.939323],"type":"Point"}
}