{
  "type": "Feature",
  "properties": {
    "addr:full":"Minderbroed Sngl 42 Roermond Limburg 6041 KK",
    "addr:housenumber":"42",
    "addr:postcode":"6041 kk",
    "addr:street":"Sngl",
    "iso:country":"NL",
    "sg:address":"Minderbroed Sngl 42",
    "sg:city":"Roermond",
    "sg:orig_category":"Accountants - Administratie- Consulenten En -Kantoren",
    "sg:phone":"+31 475 335 115",
    "sg:postcode":"6041 KK",
    "sg:province":"Limburg",
    "wof:name":"Fiscam Bv",
    "wof:placetype":"venue"
},
  "geometry": {"coordinates":[5.985228,51.191563],"type":"Point"}
}