{
  "type": "Feature",
  "properties": {
    "addr:full":"Herengracht 265 Amsterdam Noord-Holland 1016 BJ",
    "addr:housenumber":"265",
    "addr:postcode":"1016 bj",
    "addr:street":"Herengracht",
    "iso:country":"NL",
    "sg:address":"Herengracht 265",
    "sg:city":"Amsterdam",
    "sg:orig_category":"Kunst And Kunstenaarsbenodigdheden",
    "sg:phone":"+31 20 622 8766",
    "sg:postcode":"1016 BJ",
    "sg:province":"Noord-Holland",
    "wof:name":"Clubwear House",
    "wof:placetype":"venue"
},
  "geometry": {"coordinates":[4.887372,52.371616],"type":"Point"}
}