{
  "type": "Feature",
  "properties": {
    "addr:full":"Friesestraat 34 Coevorden Drenthe 7741 GW",
    "addr:housenumber":"34",
    "addr:postcode":"7741 gw",
    "addr:street":"Friesestraat",
    "iso:country":"NL",
    "sg:address":"Friesestraat 34",
    "sg:city":"Coevorden",
    "sg:orig_category":"Diverse Artikelen Fab",
    "sg:phone":"+31 524 519 501",
    "sg:postcode":"7741 GW",
    "sg:province":"Drenthe",
    "wof:name":"Kaarsen Kado-Atelier Het Ambacht",
    "wof:placetype":"venue"
},
  "geometry": {"coordinates":[6.738969,52.662083],"type":"Point"}
}