{
  "type": "Feature",
  "properties": {
    "addr:full":"Nachtegaallaan 2 Leende Noord-Brabant 5595 BK",
    "addr:housenumber":"2",
    "addr:postcode":"5595 bk",
    "addr:street":"Nachtegaallaan",
    "iso:country":"NL",
    "sg:address":"Nachtegaallaan 2",
    "sg:city":"Leende",
    "sg:orig_category":"Tandartsen",
    "sg:phone":"+31 40 206 1886",
    "sg:postcode":"5595 BK",
    "sg:province":"Noord-Brabant",
    "wof:name":"J.G.M. Loeffen",
    "wof:placetype":"venue"
},
  "geometry": {"coordinates":[5.542885,51.350861],"type":"Point"}
}