{
  "type": "Feature",
  "properties": {
    "addr:full":"Waterlooplein 19 Amsterdam Noord-Holland 1011 NV",
    "addr:housenumber":"19",
    "addr:postcode":"1011 nv",
    "addr:street":"Waterlooplein",
    "iso:country":"NL",
    "sg:address":"Waterlooplein 19",
    "sg:city":"Amsterdam",
    "sg:orig_category":"Juweliers",
    "sg:phone":"+31 20 423 0640",
    "sg:postcode":"1011 NV",
    "sg:province":"Noord-Holland",
    "wof:name":"Juwelier Ligtenberg Vof",
    "wof:placetype":"venue"
},
  "geometry": {"coordinates":[4.901181,52.368992],"type":"Point"}
}