{
  "type": "Feature",
  "properties": {
    "addr:full":"Hoefwg 6 Best Noord-Brabant 5684 ND",
    "addr:housenumber":"6",
    "addr:postcode":"5684 nd",
    "addr:street":"Hoefwg",
    "iso:country":"NL",
    "sg:address":"Hoefwg 6",
    "sg:city":"Best",
    "sg:orig_category":"Verzekeringen - Verzekeringskantoren",
    "sg:phone":"+31 499 390 176",
    "sg:postcode":"5684 ND",
    "sg:province":"Noord-Brabant",
    "wof:name":"Onderlinge Paardenverz Best",
    "wof:placetype":"venue"
},
  "geometry": {"coordinates":[-101.464676,31.19558],"type":"Point"}
}