{
  "type": "Feature",
  "properties": {
    "addr:full":"Hullenbergwg 3 Bennekom Gelderland 6721 AN",
    "addr:housenumber":"3",
    "addr:postcode":"6721 an",
    "addr:street":"Hullenbergwg;Gelderland",
    "iso:country":"NL",
    "sg:address":"Hullenbergwg 3",
    "sg:city":"Bennekom",
    "sg:orig_category":"Beeldende Kunstenaars",
    "sg:phone":"+31 318 414 218",
    "sg:postcode":"6721 AN",
    "sg:province":"Gelderland",
    "wof:name":"Hubbeling, B",
    "wof:placetype":"venue"
},
  "geometry": {"coordinates":[5.686734,51.996292],"type":"Point"}
}