{
  "type": "Feature",
  "properties": {
    "iso:country":"NL",
    "sg:address":"Lansinkstraat 42",
    "sg:city":"Haaksbergen",
    "sg:orig_category":"Medische Apparatuur And Prothesen Fab",
    "sg:phone":"+31 53 572 6936",
    "sg:postcode":"7481 JP",
    "sg:province":"NL.08",
    "wof:name":"Post Tandtechniek",
    "wof:placetype":"venue"
},
  "geometry": {"coordinates":[6.736743,52.156017],"type":"Point"}
}