{
  "type": "Feature",
  "properties": {
    "iso:country":"NL",
    "sg:address":"Nassaustraat 3A",
    "sg:city":"Bussum",
    "sg:orig_category":"Opticiens",
    "sg:phone":"+31 35 693 3306",
    "sg:postcode":"1404 CS",
    "sg:province":"North Holland",
    "wof:name":"Optiek Tom De Groot",
    "wof:placetype":"venue"
},
  "geometry": {"coordinates":[5.1618208885,52.275100708],"type":"Point"}
}