{
  "type": "Feature",
  "properties": {
    "addr:full":"St Maartenstr 53 Losser NL.08 7581 AK",
    "addr:housenumber":"53;nl.08",
    "addr:postcode":"7581 ak",
    "iso:country":"NL",
    "sg:address":"St Maartenstr 53",
    "sg:city":"Losser",
    "sg:orig_category":"Schoenen",
    "sg:phone":"+31 53 536 0382",
    "sg:postcode":"7581 AK",
    "sg:province":"NL.08",
    "wof:name":"Holtkamp",
    "wof:placetype":"venue"
},
  "geometry": {"coordinates":[7.006018,52.263569],"type":"Point"}
}