{
  "type": "Feature",
  "properties": {
    "addr:full":"Voorstraat 52 Poeldijk Zuid-Holland 2685 EN",
    "addr:housenumber":"52",
    "addr:postcode":"2685 en",
    "addr:street":"Voorstraat",
    "iso:country":"NL",
    "sg:address":"Voorstraat 52",
    "sg:city":"Poeldijk",
    "sg:orig_category":"Zuivelproducten",
    "sg:phone":"+31 174 244 055",
    "sg:postcode":"2685 EN",
    "sg:province":"Zuid-Holland",
    "wof:name":"Vof Gebroeders Van Der Valk",
    "wof:placetype":"venue"
},
  "geometry": {"coordinates":[4.218517,52.022518],"type":"Point"}
}