{
  "type": "Feature",
  "properties": {
    "addr:full":"V V Tot Voorststr 5 Vught North Brabant 5262 AL",
    "addr:housenumber":"5",
    "addr:postcode":"5262 al",
    "iso:country":"NL",
    "sg:address":"V V Tot Voorststr 5",
    "sg:city":"Vught",
    "sg:orig_category":"Kappers",
    "sg:phone":"+31 73 656 3980",
    "sg:postcode":"5262 AL",
    "sg:province":"North Brabant",
    "wof:name":"Lingg",
    "wof:placetype":"venue"
},
  "geometry": {"coordinates":[5.297663,51.660519],"type":"Point"}
}