{
  "type": "Feature",
  "properties": {
    "addr:full":"Goudsmitstr 1 Groenlo Gelderland 7141 AW",
    "addr:housenumber":"1",
    "addr:postcode":"7141 aw",
    "addr:street":"Goudsmitstr;Gelderland",
    "iso:country":"NL",
    "sg:address":"Goudsmitstr 1",
    "sg:city":"Groenlo",
    "sg:orig_category":"Koeriersdiensten",
    "sg:phone":"+31 544 466 233",
    "sg:postcode":"7141 AW",
    "sg:province":"Gelderland",
    "wof:name":"Achterhoek-Express",
    "wof:placetype":"venue"
},
  "geometry": {"coordinates":[6.615211,52.042427],"type":"Point"}
}