{
  "type": "Feature",
  "properties": {
    "addr:full":"Jannewekken 10 Zierikzee Zeeland 4301 HH",
    "addr:housenumber":"10",
    "addr:postcode":"4301 hh",
    "addr:street":"Jannewekken",
    "iso:country":"NL",
    "sg:address":"Jannewekken 10",
    "sg:city":"Zierikzee",
    "sg:orig_category":"Verenigingen En Stichtingen",
    "sg:phone":"+31 111 415 561",
    "sg:postcode":"4301 HH",
    "sg:province":"Zeeland",
    "sg:website":"http://www.arduin.nl",
    "wof:name":"Arduin, Sticht",
    "wof:placetype":"venue"
},
  "geometry": {"coordinates":[3.921585,51.652161],"type":"Point"}
}