{
  "type": "Feature",
  "properties": {
    "addr:full":"Eglantierbaan 4-6 Capelle Ad Yssel Zuid-Holland 2908 LV",
    "addr:housenumber":"4-6",
    "addr:postcode":"2908",
    "addr:street":"Eglantierbaan",
    "iso:country":"NL",
    "sg:address":"Eglantierbaan 4-6",
    "sg:city":"Capelle Ad Yssel",
    "sg:orig_category":"Oud Metaal",
    "sg:phone":"+31 10 442 4539",
    "sg:postcode":"2908 LV",
    "sg:province":"Zuid-Holland",
    "wof:name":"Meer, F N K Van Der",
    "wof:placetype":"venue"
},
  "geometry": {"coordinates":[4.5748739243,51.9572753906],"type":"Point"}
}