{
  "type": "Feature",
  "properties": {
    "addr:full":"2E Dorpsstr 38 Zeist Utrecht 3701 AB",
    "addr:housenumber":"38",
    "addr:postcode":"3701 ab",
    "addr:street":"2E Dorpsstr",
    "iso:country":"NL",
    "sg:address":"2E Dorpsstr 38",
    "sg:city":"Zeist",
    "sg:classifiers":[
        {
            "category":"Shopping",
            "subcategory":"Gifts & Souvenirs",
            "type":"Retail Goods"
        }
    ],
    "sg:phone":"+31 30 691 5885",
    "sg:postcode":"3701 AB",
    "sg:province":"Utrecht",
    "sg:tags":[
        "wens-",
        "en",
        "prentbriefkaarten"
    ],
    "wof:name":"Keyser, Han",
    "wof:placetype":"venue"
},
  "geometry": {"coordinates":[5.2392520905,52.081451416],"type":"Point"}
}