{
  "type": "Feature",
  "properties": {
    "addr:full":"Meerndk 92 De Meern Utrecht 3454 HT",
    "addr:housenumber":"92",
    "addr:postcode":"3454 ht",
    "addr:street":"Meerndk",
    "iso:country":"NL",
    "sg:address":"Meerndk 92",
    "sg:city":"De Meern",
    "sg:orig_category":"Afslankinstituten",
    "sg:phone":"+31 30 666 2322",
    "sg:postcode":"3454 HT",
    "sg:province":"Utrecht",
    "wof:name":"Voskuilen, Coby",
    "wof:placetype":"venue"
},
  "geometry": {"coordinates":[5.035164,52.078453],"type":"Point"}
}