{
  "type": "Feature",
  "properties": {
    "addr:full":"1E C Huygensstr 106 Amsterdam North Holland 1054 BZ",
    "addr:housenumber":"106",
    "addr:postcode":"1054 bz",
    "addr:street":"1E C Huygensstr",
    "iso:country":"NL",
    "sg:address":"1E C Huygensstr 106",
    "sg:city":"Amsterdam",
    "sg:orig_category":"Psychotherapeuten",
    "sg:phone":"+31 20 612 8773",
    "sg:postcode":"1054 BZ",
    "sg:province":"North Holland",
    "wof:name":"Frederiks, Drs A A",
    "wof:placetype":"venue"
},
  "geometry": {"coordinates":[4.875239,52.362366],"type":"Point"}
}