{
  "type": "Feature",
  "properties": {
    "addr:full":"Einsteinstraat 8 Dordrecht Zuid-Holland 3316 GG",
    "addr:housenumber":"8",
    "addr:postcode":"3316 gg",
    "addr:street":"Einsteinstraat",
    "iso:country":"NL",
    "sg:address":"Einsteinstraat 8",
    "sg:city":"Dordrecht",
    "sg:orig_category":"Verlichting And Huishoudartikelen",
    "sg:phone":"+31 78 654 0654",
    "sg:postcode":"3316 GG",
    "sg:province":"Zuid-Holland",
    "wof:name":"Nul Achthonderd 0800-Lighting",
    "wof:placetype":"venue"
},
  "geometry": {"coordinates":[4.636907,51.779251],"type":"Point"}
}