{
  "type": "Feature",
  "properties": {
    "addr:full":"J Vermeerstr 23 Maarssen Utrecht 3601 EL",
    "addr:housenumber":"23",
    "addr:postcode":"3601 el",
    "iso:country":"NL",
    "sg:address":"J Vermeerstr 23",
    "sg:city":"Maarssen",
    "sg:orig_category":"Postkantoren",
    "sg:phone":"+31 346 563 431",
    "sg:postcode":"3601 EL",
    "sg:province":"Utrecht",
    "sg:website":"http://www.postkantoor.nl",
    "wof:name":"Postkantoor",
    "wof:placetype":"venue"
},
  "geometry": {"coordinates":[5.041149,52.14262],"type":"Point"}
}