{
  "type": "Feature",
  "properties": {
    "addr:full":"Zwanebloem 28 Zuidhorn Groningen 9801 LC",
    "addr:housenumber":"28",
    "addr:postcode":"9801 lc",
    "addr:street":"Zwanebloem",
    "iso:country":"NL",
    "sg:address":"Zwanebloem 28",
    "sg:city":"Zuidhorn",
    "sg:orig_category":"Boekhouders",
    "sg:phone":"+31 594 507 085",
    "sg:postcode":"9801 LC",
    "sg:province":"Groningen",
    "wof:name":"Administraties Schriemer En Antonides",
    "wof:placetype":"venue"
},
  "geometry": {"coordinates":[6.392903,53.242683],"type":"Point"}
}