{
  "type": "Feature",
  "properties": {
    "addr:full":"Hoenderkamp 2 Emmen Provincie Drenthe 7812 VZ",
    "addr:housenumber":"2;7812",
    "addr:postcode":"vz",
    "addr:street":"Hoenderkamp;Provincie Drenthe",
    "iso:country":"NL",
    "sg:address":"Hoenderkamp 2",
    "sg:city":"Emmen",
    "sg:orig_category":"Banden",
    "sg:phone":"+31 591 659 300",
    "sg:postcode":"7812 VZ",
    "sg:province":"Provincie Drenthe",
    "sg:website":"http://www.kwik-fit.nl",
    "wof:name":"Kwik-Fit",
    "wof:placetype":"venue"
},
  "geometry": {"coordinates":[6.897247,52.77137],"type":"Point"}
}