{
  "type": "Feature",
  "properties": {
    "iso:country":"NL",
    "sg:address":"Timorstr 38",
    "sg:city":"Groningen",
    "sg:orig_category":"Vertaalbureaus",
    "sg:phone":"+31 50 571 6735",
    "sg:postcode":"9715 LH",
    "sg:province":"Groningen",
    "wof:name":"Matroos",
    "wof:placetype":"venue"
},
  "geometry": {"coordinates":[6.567789,53.234245],"type":"Point"}
}