{
  "type": "Feature",
  "properties": {
    "addr:full":"Baronielaan 73 Goirle North Brabant 5052 BX",
    "addr:housenumber":"73",
    "addr:postcode":"5052 bx",
    "addr:street":"Baronielaan",
    "iso:country":"NL",
    "sg:address":"Baronielaan 73",
    "sg:city":"Goirle",
    "sg:orig_category":"Voeding, Dranken And Tabak Gh",
    "sg:phone":"+31 13 534 3237",
    "sg:postcode":"5052 BX",
    "sg:province":"North Brabant",
    "wof:name":"De Wit Agenturen",
    "wof:placetype":"venue"
},
  "geometry": {"coordinates":[5.047723,51.528957],"type":"Point"}
}