{
  "type": "Feature",
  "properties": {
    "iso:country":"NL",
    "sg:address":"Tulpenstr 8",
    "sg:city":"Rynsburg",
    "sg:orig_category":"Kappers",
    "sg:phone":"+31 71 402 0762",
    "sg:postcode":"2231 GW",
    "sg:province":"Zuid-Holland",
    "wof:name":"Vierling, Paul",
    "wof:placetype":"venue"
},
  "geometry": {"coordinates":[4.443004,52.192493],"type":"Point"}
}