{
  "type": "Feature",
  "properties": {
    "addr:full":"Nieuwstad 82 Doetinchem Gelderland 7001 AE",
    "addr:housenumber":"82",
    "addr:postcode":"7001 ae",
    "addr:street":"Nieuwstad;Gelderland",
    "iso:country":"NL",
    "sg:address":"Nieuwstad 82",
    "sg:city":"Doetinchem",
    "sg:orig_category":"Miniaturen",
    "sg:phone":"+31 314 327 000",
    "sg:postcode":"7001 AE",
    "sg:province":"Gelderland",
    "wof:name":"Traffic",
    "wof:placetype":"venue"
},
  "geometry": {"coordinates":[6.290014,51.966309],"type":"Point"}
}