{
  "type": "Feature",
  "properties": {
    "addr:full":"Noordewierweg 143 Amersfoort Utrecht 3812 DD",
    "addr:housenumber":"143",
    "addr:postcode":"3812 dd",
    "addr:street":"Noordewierweg",
    "iso:country":"NL",
    "sg:address":"Noordewierweg 143",
    "sg:city":"Amersfoort",
    "sg:orig_category":"Timmerwerk Van Hout And Kunststof",
    "sg:phone":"+31 33 465 0571",
    "sg:postcode":"3812 DD",
    "sg:province":"Utrecht",
    "wof:name":"Bouwbedrijf Dorresteijn",
    "wof:placetype":"venue"
},
  "geometry": {"coordinates":[5.364254,52.160229],"type":"Point"}
}