{
  "type": "Feature",
  "properties": {
    "addr:full":"Stationsplein 2 Heerlen Limburg 6411 NE",
    "addr:housenumber":"2",
    "addr:postcode":"6411 ne",
    "addr:street":"Stationsplein",
    "iso:country":"NL",
    "sg:address":"Stationsplein 2",
    "sg:city":"Heerlen",
    "sg:orig_category":"Bloemen And Planten",
    "sg:phone":"+31 45 571 1155",
    "sg:postcode":"6411 NE",
    "sg:province":"Limburg",
    "wof:name":"Bloemenhandel Kerkvliet Vof",
    "wof:placetype":"venue"
},
  "geometry": {"coordinates":[5.975397,50.890255],"type":"Point"}
}