{
  "type": "Feature",
  "properties": {
    "addr:full":"Polderwg 7 Tiel Gelderland 4005 GA",
    "addr:housenumber":"7",
    "addr:postcode":"4005 ga",
    "addr:street":"Polderwg;Gelderland",
    "iso:country":"NL",
    "sg:address":"Polderwg 7",
    "sg:city":"Tiel",
    "sg:orig_category":"Filmstudio'S En -Productie",
    "sg:phone":"+31 344 570 212",
    "sg:postcode":"4005 GA",
    "sg:province":"Gelderland",
    "wof:name":"Olivier",
    "wof:placetype":"venue"
},
  "geometry": {"coordinates":[5.4479818344,51.8975563049],"type":"Point"}
}