{
  "type": "Feature",
  "properties": {
    "addr:full":"Wertstg 24 Kerkdriel Gelderland 5331 PE",
    "addr:housenumber":"24",
    "addr:postcode":"5331 pe",
    "addr:street":"Wertstg;Gelderland",
    "iso:country":"NL",
    "sg:address":"Wertstg 24",
    "sg:city":"Kerkdriel",
    "sg:orig_category":"Kaas",
    "sg:phone":"+31 418 633 384",
    "sg:postcode":"5331 PE",
    "sg:province":"Gelderland",
    "wof:name":"Jansen, B P J",
    "wof:placetype":"venue"
},
  "geometry": {"coordinates":[5.3277077675,51.7597885132],"type":"Point"}
}