{
  "type": "Feature",
  "properties": {
    "iso:country":"NL",
    "sg:address":"W Rosestr 4",
    "sg:city":"Eindhoven",
    "sg:orig_category":"Koeltechniek",
    "sg:phone":"+31 40 243 7616",
    "sg:postcode":"5622 GH",
    "sg:province":"Noord-Brabant",
    "sg:website":"http://www.vk-bv.nl",
    "wof:name":"Ven, Koeltechnisch Buro Van De",
    "wof:placetype":"venue"
},
  "geometry": {"coordinates":[5.466548,51.466026],"type":"Point"}
}