{
  "type": "Feature",
  "properties": {
    "addr:full":"Gerard Doustraat 119 Voorthuizen Gelderland 3781 EJ",
    "addr:housenumber":"119",
    "addr:postcode":"3781 ej",
    "addr:street":"Gerard Doustraat;Gelderland",
    "iso:country":"NL",
    "sg:address":"Gerard Doustraat 119",
    "sg:city":"Voorthuizen",
    "sg:orig_category":"Kappers",
    "sg:phone":"+31 342 473 373",
    "sg:postcode":"3781 EJ",
    "sg:province":"Gelderland",
    "wof:name":"Barbershop Henk",
    "wof:placetype":"venue"
},
  "geometry": {"coordinates":[5.6060461998,52.1879272461],"type":"Point"}
}