{
  "type": "Feature",
  "properties": {
    "addr:full":"De Kolk 30 Swifterbant Flevoland 8255 PE",
    "addr:housenumber":"30",
    "addr:postcode":"8255 pe",
    "addr:street":"De Kolk;Flevoland",
    "iso:country":"NL",
    "sg:address":"De Kolk 30",
    "sg:city":"Swifterbant",
    "sg:orig_category":"Diverse Bedrijfsinstallaties Gh",
    "sg:phone":"+31 321 322 918",
    "sg:postcode":"8255 PE",
    "sg:province":"Flevoland",
    "wof:name":"Vof Beerbaum Propermij",
    "wof:placetype":"venue"
},
  "geometry": {"coordinates":[5.648606,52.57262],"type":"Point"}
}