{
  "type": "Feature",
  "properties": {
    "addr:full":"Gebroken Meeldijk 54 Barendrecht Zuid-Holland 2991 VD",
    "addr:housenumber":"54",
    "addr:postcode":"2991 vd",
    "addr:street":"Gebroken Meeldijk",
    "iso:country":"NL",
    "sg:address":"Gebroken Meeldijk 54",
    "sg:city":"Barendrecht",
    "sg:orig_category":"Fruit And Groenten Gh",
    "sg:phone":"+31 180 693 939",
    "sg:postcode":"2991 VD",
    "sg:province":"Zuid-Holland",
    "wof:name":"Amaf Produce Bv",
    "wof:placetype":"venue"
},
  "geometry": {"coordinates":[4.558663,51.854511],"type":"Point"}
}