{
  "type": "Feature",
  "properties": {
    "iso:country":"NL",
    "sg:address":"Schryverstr 1",
    "sg:city":"Almere",
    "sg:orig_category":"Bibliotheken En Leeszalen Openbare",
    "sg:phone":"+31 36 548 6000",
    "sg:postcode":"1315 HW",
    "sg:province":"NL.",
    "sg:website":"http://www.bibliotheken-flevoland.nl",
    "wof:name":"Openbare Bibliotheek",
    "wof:placetype":"venue"
},
  "geometry": {"coordinates":[5.221869,52.372662],"type":"Point"}
}