{
  "type": "Feature",
  "properties": {
    "addr:full":"Kleingouw 92 Andyk Noord-Holland 1619 CG",
    "addr:housenumber":"92",
    "addr:postcode":"1619 cg",
    "addr:street":"Kleingouw",
    "iso:country":"NL",
    "sg:address":"Kleingouw 92",
    "sg:city":"Andyk",
    "sg:orig_category":"Vakantieverblijven",
    "sg:phone":"+31 228 592 626",
    "sg:postcode":"1619 CG",
    "sg:province":"Noord-Holland",
    "sg:website":"http://www.easyhome.nl",
    "wof:name":"Easyhome",
    "wof:placetype":"venue"
},
  "geometry": {"coordinates":[5.200143,52.741104],"type":"Point"}
}