{
  "type": "Feature",
  "properties": {
    "addr:full":"Emrikwg 48 Haarlem Noord-Holland 2031 BT",
    "addr:housenumber":"48",
    "addr:postcode":"2031 bt",
    "addr:street":"Emrikwg",
    "iso:country":"NL",
    "sg:address":"Emrikwg 48",
    "sg:city":"Haarlem",
    "sg:orig_category":"Orthopedische Artikelen - Fabrieken En Groothandel",
    "sg:phone":"+31 23 531 9427",
    "sg:postcode":"2031 BT",
    "sg:province":"Noord-Holland",
    "wof:name":"Bauerfeind Benelux Bv",
    "wof:placetype":"venue"
},
  "geometry": {"coordinates":[4.6617298126,52.3982505798],"type":"Point"}
}