{
  "type": "Feature",
  "properties": {
    "addr:full":"Javakade 568 Amsterdam Noord-Holland 1019 SE",
    "addr:housenumber":"568;1019",
    "addr:street":"Javakade;Se",
    "iso:country":"NL",
    "sg:address":"Javakade 568",
    "sg:city":"Amsterdam",
    "sg:orig_category":"Werving And Selectie Van Vast Personeel",
    "sg:phone":"+31 20 419 6101",
    "sg:postcode":"1019 SE",
    "sg:province":"Noord-Holland",
    "wof:name":"Asopos",
    "wof:placetype":"venue"
},
  "geometry": {"coordinates":[4.9264440536,52.3785705566],"type":"Point"}
}