{
  "type": "Feature",
  "properties": {
    "addr:full":"Verl Meidoornstr 57 Wezep Gelderland 8091 DM",
    "addr:housenumber":"57",
    "addr:postcode":"8091 dm",
    "iso:country":"NL",
    "sg:address":"Verl Meidoornstr 57",
    "sg:city":"Wezep",
    "sg:orig_category":"Fotopersbureaus",
    "sg:phone":"+31 6 53672548",
    "sg:postcode":"8091 DM",
    "sg:province":"Gelderland",
    "wof:name":"Fotopersbur",
    "wof:placetype":"venue"
},
  "geometry": {"coordinates":[6.011619,52.466061],"type":"Point"}
}