{
  "type": "Feature",
  "properties": {
    "addr:full":"Keenkestr 4 Gronsveld Limburg 6247 EJ",
    "addr:housenumber":"4",
    "addr:postcode":"6247 ej",
    "addr:street":"Keenkestr",
    "iso:country":"NL",
    "sg:address":"Keenkestr 4",
    "sg:city":"Gronsveld",
    "sg:orig_category":"Bloemen En Planten",
    "sg:phone":"+31 43 408 1990",
    "sg:postcode":"6247 EJ",
    "sg:province":"Limburg",
    "wof:name":"Scharnigg, G G J",
    "wof:placetype":"venue"
},
  "geometry": {"coordinates":[5.734439,50.809643],"type":"Point"}
}