{
  "type": "Feature",
  "properties": {
    "addr:full":"Muggenborch 25 Kapel Avezaath Gelderland 4013 CJ",
    "addr:housenumber":"25",
    "addr:postcode":"4013 cj",
    "addr:street":"Muggenborch",
    "iso:country":"NL",
    "sg:address":"Muggenborch 25",
    "sg:city":"Kapel Avezaath",
    "sg:orig_category":"Accountants - Administratie- Consulenten En -Kantoren",
    "sg:phone":"+31 344 661 840",
    "sg:postcode":"4013 CJ",
    "sg:province":"Gelderland",
    "wof:name":"Eck, G P H Van",
    "wof:placetype":"venue"
},
  "geometry": {"coordinates":[5.372835,51.881016],"type":"Point"}
}