{
  "type": "Feature",
  "properties": {
    "iso:country":"NL",
    "sg:address":"Maaseikstr 55",
    "sg:city":"Breda",
    "sg:orig_category":"Juweliers",
    "sg:phone":"+31 76 587 2910",
    "sg:postcode":"4826 LR",
    "sg:province":"Noord-Brabant",
    "wof:name":"Abc Goud & Zilversmederij",
    "wof:placetype":"venue"
},
  "geometry": {"coordinates":[4.78237,51.605888],"type":"Point"}
}