{
  "type": "Feature",
  "properties": {
    "addr:full":"Vijverstraat 5 Nieuwendijk Nb Noord-Brabant 4255 HE",
    "addr:housenumber":"5",
    "addr:postcode":"4255 he",
    "addr:street":"Vijverstraat",
    "iso:country":"NL",
    "sg:address":"Vijverstraat 5",
    "sg:city":"Nieuwendijk Nb",
    "sg:orig_category":"Kinderopvang Behalve Thuis",
    "sg:phone":"+31 183 403 276",
    "sg:postcode":"4255 HE",
    "sg:province":"Noord-Brabant",
    "wof:name":"Peuterspeelzaal Dombo",
    "wof:placetype":"venue"
},
  "geometry": {"coordinates":[4.924215,51.773941],"type":"Point"}
}