{
  "type": "Feature",
  "properties": {
    "addr:full":"Burg Magneestr 17 Bergeyk North Brabant 5571 HB",
    "addr:housenumber":"17",
    "addr:postcode":"5571 hb",
    "addr:street":"Burg;Bergeyk North",
    "iso:country":"NL",
    "sg:address":"Burg Magneestr 17",
    "sg:city":"Bergeyk",
    "sg:orig_category":"Kinderkleding",
    "sg:phone":"+31 497 550 325",
    "sg:postcode":"5571 HB",
    "sg:province":"North Brabant",
    "wof:name":"Robbedoes",
    "wof:placetype":"venue"
},
  "geometry": {"coordinates":[5.360135,51.323326],"type":"Point"}
}