{
  "type": "Feature",
  "properties": {
    "addr:full":"Het Rond 4 Zoetermeer Zuid-Holland 2711 BW",
    "addr:housenumber":"4",
    "addr:postcode":"2711 bw",
    "addr:street":"Het Rond",
    "iso:country":"NL",
    "sg:address":"Het Rond 4",
    "sg:city":"Zoetermeer",
    "sg:orig_category":"Kampeerartikelen",
    "sg:phone":"+31 79 331 0175",
    "sg:postcode":"2711 BW",
    "sg:province":"Zuid-Holland",
    "wof:name":"Bever",
    "wof:placetype":"venue"
},
  "geometry": {"coordinates":[4.4894828796,52.0614700317],"type":"Point"}
}