{
  "type": "Feature",
  "properties": {
    "addr:full":"Skuniadyk 2 Bakhuizen Friesland 8574 TR",
    "addr:housenumber":"2",
    "addr:postcode":"8574 tr",
    "addr:street":"Skuniadyk",
    "iso:country":"NL",
    "sg:address":"Skuniadyk 2",
    "sg:city":"Bakhuizen",
    "sg:orig_category":"Landbouwmachines Gh",
    "sg:phone":"+31 514 581 261",
    "sg:postcode":"8574 TR",
    "sg:province":"Friesland",
    "wof:name":"B S Dijkstra",
    "wof:placetype":"venue"
},
  "geometry": {"coordinates":[5.457908,52.865746],"type":"Point"}
}