{
  "type": "Feature",
  "properties": {
    "iso:country":"NL",
    "sg:address":"M L Kingstr 20",
    "sg:city":"S Gravenzande",
    "sg:orig_category":"Adviesbureaus Bedrijfsorganisatie",
    "sg:phone":"+31 174 280 328",
    "sg:postcode":"2694 AE",
    "sg:province":"Zuid-Holland",
    "wof:name":"Vandenende",
    "wof:placetype":"venue"
},
  "geometry": {"coordinates":[4.163731,52.006641],"type":"Point"}
}