{
  "type": "Feature",
  "properties": {
    "addr:full":"Koningstr 1 Naaldwyk Zuid-Holland 2671 JS",
    "addr:housenumber":"1",
    "addr:postcode":"2671 js",
    "addr:street":"Koningstr",
    "iso:country":"NL",
    "sg:address":"Koningstr 1",
    "sg:city":"Naaldwyk",
    "sg:orig_category":"Verf En Lak",
    "sg:phone":"+31 174 624 529",
    "sg:postcode":"2671 JS",
    "sg:province":"Zuid-Holland",
    "wof:name":"Trommel, Cees",
    "wof:placetype":"venue"
},
  "geometry": {"coordinates":[4.207718,51.992443],"type":"Point"}
}