{
  "type": "Feature",
  "properties": {
    "addr:full":"V H Goedhartln 385 Amstelveen North Holland 1181 KR",
    "addr:housenumber":"385",
    "addr:postcode":"1181 kr",
    "iso:country":"NL",
    "sg:address":"V H Goedhartln 385",
    "sg:city":"Amstelveen",
    "sg:orig_category":"Glazenwasserijen",
    "sg:phone":"+31 20 645 1831",
    "sg:postcode":"1181 KR",
    "sg:province":"North Holland",
    "wof:name":"Variant Bv Schoonmaakdiensten",
    "wof:placetype":"venue"
},
  "geometry": {"coordinates":[4.856945,52.303444],"type":"Point"}
}