{
  "type": "Feature",
  "properties": {
    "addr:full":"Arnolduspark 10 Hoofddorp North Holland 2132 CR",
    "addr:housenumber":"10",
    "addr:postcode":"2132 cr",
    "addr:street":"Arnolduspark",
    "iso:country":"NL",
    "sg:address":"Arnolduspark 10",
    "sg:city":"Hoofddorp",
    "sg:classifiers":[
        {
            "category":"Fast Food",
            "type":"Food & Drink"
        }
    ],
    "sg:phone":"+31 23 563 7193",
    "sg:postcode":"2132 CR",
    "sg:province":"North Holland",
    "sg:tags":[
        "afhaal",
        "restaurant"
    ],
    "sg:website":"http://wwwsenzubaru.nl",
    "wof:name":"Senbazuru",
    "wof:placetype":"venue"
},
  "geometry": {"coordinates":[4.705044,52.309235],"type":"Point"}
}