{
  "type": "Feature",
  "properties": {
    "addr:full":"V Voorststr 13C Huissen Gelderland 6851 LT",
    "addr:housenumber":"13c",
    "addr:postcode":"6851 lt",
    "addr:street":"Voorststr;Gelderland",
    "iso:country":"NL",
    "sg:address":"V Voorststr 13C",
    "sg:city":"Huissen",
    "sg:orig_category":"Adviesbureaus Bedrijfsorganisatie",
    "sg:phone":"+31 26 325 3783",
    "sg:postcode":"6851 LT",
    "sg:province":"Gelderland",
    "wof:name":"Continuo Bv",
    "wof:placetype":"venue"
},
  "geometry": {"coordinates":[5.940044,51.939777],"type":"Point"}
}