{
  "type": "Feature",
  "properties": {
    "addr:full":"Vleutstraat 14 Liempde Noord-Brabant 5298 NE",
    "addr:housenumber":"14;5298",
    "addr:postcode":"ne",
    "addr:street":"Vleutstraat",
    "iso:country":"NL",
    "sg:address":"Vleutstraat 14",
    "sg:city":"Liempde",
    "sg:orig_category":"Huishoudapparatuur, Televisies And Radio'S",
    "sg:phone":"+31 411 635 062",
    "sg:postcode":"5298 NE",
    "sg:province":"Noord-Brabant",
    "wof:name":"Dare-Tronics",
    "wof:placetype":"venue"
},
  "geometry": {"coordinates":[5.387049,51.556847],"type":"Point"}
}