{
  "type": "Feature",
  "properties": {
    "addr:full":"Maarten Mooystraat 38 Callantsoog North Holland 1759 XK",
    "addr:housenumber":"38",
    "addr:postcode":"1759 xk",
    "addr:street":"Maarten Mooystraat",
    "iso:country":"NL",
    "sg:address":"Maarten Mooystraat 38",
    "sg:city":"Callantsoog",
    "sg:classifiers":[
        {
            "category":"Shopping",
            "subcategory":"Gifts & Souvenirs",
            "type":"Retail Goods"
        }
    ],
    "sg:phone":"+31 224 581 216",
    "sg:postcode":"1759 XK",
    "sg:province":"North Holland",
    "sg:tags":[
        "geschenken"
    ],
    "wof:name":"Italie Design",
    "wof:placetype":"venue"
},
  "geometry": {"coordinates":[4.70249,52.835239],"type":"Point"}
}