{
  "type": "Feature",
  "properties": {
    "addr:full":"Makado Center 66 Alblasserdam South Holland 2951 EJ",
    "addr:housenumber":"66",
    "addr:postcode":"2951 ej",
    "iso:country":"NL",
    "sg:address":"Makado Center 66",
    "sg:city":"Alblasserdam",
    "sg:orig_category":"Huishoudelijke Apparaten En Artikelen",
    "sg:phone":"+31 78 699 0316",
    "sg:postcode":"2951 EJ",
    "sg:province":"South Holland",
    "wof:name":"Blokker Bv",
    "wof:placetype":"venue"
},
  "geometry": {"coordinates":[4.658493,51.86393],"type":"Point"}
}