{
  "type": "Feature",
  "properties": {
    "addr:full":"De Oude Veiling 82 Zwaag Noord-Holland 1689 AD",
    "addr:housenumber":"82",
    "addr:postcode":"1689 ad",
    "addr:street":"De Oude Veiling",
    "iso:country":"NL",
    "sg:address":"De Oude Veiling 82",
    "sg:city":"Zwaag",
    "sg:orig_category":"Verenigingen En Stichtingen",
    "sg:phone":"+31 229 244 000",
    "sg:postcode":"1689 AD",
    "sg:province":"Noord-Holland",
    "wof:name":"Ondernemers Club Westfriesland",
    "wof:placetype":"venue"
},
  "geometry": {"coordinates":[5.064629,52.661385],"type":"Point"}
}