{
  "type": "Feature",
  "properties": {
    "addr:full":"Tuinstr 155 Amsterdam Noord-Holland 1015 PB",
    "addr:housenumber":"155",
    "addr:postcode":"1015 pb",
    "iso:country":"NL",
    "sg:address":"Tuinstr 155",
    "sg:city":"Amsterdam",
    "sg:orig_category":"Vertaalbureaus",
    "sg:phone":"+31 20 625 7183",
    "sg:postcode":"1015 PB",
    "sg:province":"Noord-Holland",
    "wof:name":"Vox Et Lingua",
    "wof:placetype":"venue"
},
  "geometry": {"coordinates":[4.880965,52.376621],"type":"Point"}
}