{
  "type": "Feature",
  "properties": {
    "addr:full":"Maandereind 13 Ede Gld Gelderland 6711 AA",
    "addr:housenumber":"13",
    "addr:postcode":"6711 aa",
    "addr:street":"Maandereind;Gld Gelderland",
    "iso:country":"NL",
    "sg:address":"Maandereind 13",
    "sg:city":"Ede Gld",
    "sg:orig_category":"Boeken En Tijdschriften",
    "sg:phone":"+31 318 611 587",
    "sg:postcode":"6711 AA",
    "sg:province":"Gelderland",
    "wof:name":"Bron, De",
    "wof:placetype":"venue"
},
  "geometry": {"coordinates":[5.669699,52.043129],"type":"Point"}
}