{
  "type": "Feature",
  "properties": {
    "addr:full":"Zilvermeeuw 1 Almelo Overijssel 7609 PP",
    "addr:housenumber":"1",
    "addr:postcode":"7609 pp",
    "addr:street":"Zilvermeeuw",
    "iso:country":"NL",
    "sg:address":"Zilvermeeuw 1",
    "sg:city":"Almelo",
    "sg:orig_category":"Kappers",
    "sg:phone":"+31 546 851 497",
    "sg:postcode":"7609 PP",
    "sg:province":"Overijssel",
    "wof:name":"Haarmode Viola",
    "wof:placetype":"venue"
},
  "geometry": {"coordinates":[6.6416010857,52.3370361328],"type":"Point"}
}