{
  "type": "Feature",
  "properties": {
    "addr:full":"Enkweg 18 Velp Gld Gelderland 6881 MA",
    "addr:housenumber":"18",
    "addr:postcode":"6881 ma",
    "addr:street":"Enkweg;Gld Gelderland",
    "iso:country":"NL",
    "sg:address":"Enkweg 18",
    "sg:city":"Velp Gld",
    "sg:orig_category":"Architecten",
    "sg:phone":"+31 26 362 1742",
    "sg:postcode":"6881 MA",
    "sg:province":"Gelderland",
    "wof:name":"Term",
    "wof:placetype":"venue"
},
  "geometry": {"coordinates":[5.967555,52.000103],"type":"Point"}
}