{
  "type": "Feature",
  "properties": {
    "addr:full":"Biestkampwg 31 Rosmalen North Brabant 5249 JZ",
    "addr:housenumber":"31",
    "addr:postcode":"5249 jz",
    "addr:street":"Biestkampwg",
    "iso:country":"NL",
    "sg:address":"Biestkampwg 31",
    "sg:city":"Rosmalen",
    "sg:classifiers":[
        {
            "category":"Wholesale",
            "subcategory":"Motor Vehicles",
            "type":"Manufacturing & Wholesale Goods"
        }
    ],
    "sg:phone":"+31 73 521 0487",
    "sg:postcode":"5249 JZ",
    "sg:province":"North Brabant",
    "sg:tags":[
        "scooter",
        "en"
    ],
    "sg:website":"http://www.twinspecials.nl",
    "wof:name":"Twin Specials",
    "wof:placetype":"venue"
},
  "geometry": {"coordinates":[5.400227,51.724674],"type":"Point"}
}