{
  "type": "Feature",
  "properties": {
    "addr:full":"In De Betouwstraat 40 Nijmegen Gelderland 6511 GD",
    "addr:housenumber":"40",
    "addr:postcode":"6511 gd",
    "addr:street":"In De Betouwstraat;Gelderland",
    "iso:country":"NL",
    "sg:address":"In De Betouwstraat 40",
    "sg:city":"Nijmegen",
    "sg:orig_category":"Makelaars In Onroerend Goed",
    "sg:phone":"+31 24 323 2423",
    "sg:postcode":"6511 GD",
    "sg:province":"Gelderland",
    "wof:name":"Direkt Wonen Nijmegen",
    "wof:placetype":"venue"
},
  "geometry": {"coordinates":[5.859707,51.844036],"type":"Point"}
}