{
  "type": "Feature",
  "properties": {
    "iso:country":"NL",
    "sg:address":"Postbus 91",
    "sg:city":"Berkel Enschot",
    "sg:orig_category":"Verenigingen En Stichtingen",
    "sg:phone":"+31 13 533 5225",
    "sg:postcode":"5056 ZH",
    "sg:province":"Noord-Brabant",
    "wof:name":"Kreite, De",
    "wof:placetype":"venue"
},
  "geometry": {"coordinates":[5.136945,51.57674],"type":"Point"}
}