{
  "type": "Feature",
  "properties": {
    "addr:full":"Statenln 25A S Gravenhage South Holland 2582 GB",
    "addr:housenumber":"25a",
    "addr:postcode":"2582 gb",
    "addr:street":"Statenln;S Gravenhage",
    "iso:country":"NL",
    "sg:address":"Statenln 25A",
    "sg:city":"S Gravenhage",
    "sg:orig_category":"Homeopathie",
    "sg:phone":"+31 6 23337844",
    "sg:postcode":"2582 GB",
    "sg:province":"South Holland",
    "wof:name":"Statenlaan Homeopathie",
    "wof:placetype":"venue"
},
  "geometry": {"coordinates":[4.27852,52.092411],"type":"Point"}
}