{
  "type": "Feature",
  "properties": {
    "addr:full":"Hessenwg 323 Achterveld Utrecht 3791 PJ",
    "addr:housenumber":"323",
    "addr:postcode":"3791 pj",
    "addr:street":"Achterveld",
    "iso:country":"NL",
    "sg:address":"Hessenwg 323",
    "sg:city":"Achterveld",
    "sg:orig_category":"Postkantoren",
    "sg:phone":"+31 342 451 472",
    "sg:postcode":"3791 PJ",
    "sg:province":"Utrecht",
    "sg:website":"http://www.postkantoor.nl",
    "wof:name":"Postkantoor",
    "wof:placetype":"venue"
},
  "geometry": {"coordinates":[5.496022,52.134964],"type":"Point"}
}