{
  "type": "Feature",
  "properties": {
    "addr:full":"Gaast 19 Huizen North Holland 1274 AN",
    "addr:housenumber":"19",
    "addr:postcode":"1274 an",
    "addr:street":"Gaast",
    "iso:country":"NL",
    "sg:address":"Gaast 19",
    "sg:city":"Huizen",
    "sg:orig_category":"Film-, Tv- And Videoproductie",
    "sg:phone":"+31 35 523 1670",
    "sg:postcode":"1274 AN",
    "sg:province":"North Holland",
    "wof:name":"D.T. Stamate",
    "wof:placetype":"venue"
},
  "geometry": {"coordinates":[5.272843,52.303349],"type":"Point"}
}