{
  "type": "Feature",
  "properties": {
    "addr:full":"Meijelsedijk 28 Ospel Limburg 6035 RK",
    "addr:housenumber":"28",
    "addr:postcode":"6035 rk",
    "addr:street":"Meijelsedijk",
    "iso:country":"NL",
    "sg:address":"Meijelsedijk 28",
    "sg:city":"Ospel",
    "sg:orig_category":"Pluimveebedrijven En -Handelaren",
    "sg:phone":"+31 495 641 208",
    "sg:postcode":"6035 RK",
    "sg:province":"Limburg",
    "wof:name":"Beerens, M H",
    "wof:placetype":"venue"
},
  "geometry": {"coordinates":[-86.165451,34.620892],"type":"Point"}
}