{
  "type": "Feature",
  "properties": {
    "iso:country":"NL",
    "sg:address":"Zonstr 29",
    "sg:city":"Breda",
    "sg:orig_category":"Kinderkleding",
    "sg:phone":"+31 76 514 9826",
    "sg:postcode":"4818 NE",
    "sg:province":"Noord-Brabant",
    "wof:name":"Kinderkleermakerij, De",
    "wof:placetype":"venue"
},
  "geometry": {"coordinates":[4.77985,51.57637],"type":"Point"}
}