{
  "type": "Feature",
  "properties": {
    "addr:full":"Werenfriedplein 9 Elst Gld Gelderland 6661 EJ",
    "addr:housenumber":"9",
    "addr:postcode":"6661 ej",
    "addr:street":"Werenfriedplein;Gld Gelderland",
    "iso:country":"NL",
    "sg:address":"Werenfriedplein 9",
    "sg:city":"Elst Gld",
    "sg:orig_category":"Hout Gh",
    "sg:phone":"+31 481 372 701",
    "sg:postcode":"6661 EJ",
    "sg:province":"Gelderland",
    "wof:name":"Hubo Meuleman Vof",
    "wof:placetype":"venue"
},
  "geometry": {"coordinates":[5.842565,51.918617],"type":"Point"}
}