{
  "type": "Feature",
  "properties": {
    "addr:full":"Ptr Ullingsstr 1A Budel Schoot Noord-Brabant 6023 AM",
    "addr:housenumber":"1a",
    "addr:postcode":"6023",
    "iso:country":"NL",
    "sg:address":"Ptr Ullingsstr 1A",
    "sg:city":"Budel Schoot",
    "sg:orig_category":"Peuterspeelzalen",
    "sg:phone":"+31 495 492 972",
    "sg:postcode":"6023 AM",
    "sg:province":"Noord-Brabant",
    "wof:name":"Kruimelhoek, De",
    "wof:placetype":"venue"
},
  "geometry": {"coordinates":[5.565372,51.251801],"type":"Point"}
}