{
  "type": "Feature",
  "properties": {
    "iso:country":"NL",
    "sg:address":"Utrechtsestrwg 13",
    "sg:city":"Woerden",
    "sg:orig_category":"Juridische Adviseurs",
    "sg:phone":"+31 348 460 572",
    "sg:postcode":"3445 AL",
    "sg:province":"Utrecht",
    "wof:name":"Theunissen",
    "wof:placetype":"venue"
},
  "geometry": {"coordinates":[4.892011,52.087212],"type":"Point"}
}