{
  "type": "Feature",
  "properties": {
    "addr:full":"Beatrixstr 21 Den Helder Noord-Holland 1781 EM",
    "addr:housenumber":"21",
    "addr:postcode":"1781 em",
    "addr:street":"Beatrixstr",
    "iso:country":"NL",
    "sg:address":"Beatrixstr 21",
    "sg:city":"Den Helder",
    "sg:orig_category":"Non-Classified Establishments",
    "sg:phone":"+31 223 617 760",
    "sg:postcode":"1781 EM",
    "sg:province":"Noord-Holland",
    "wof:name":"Decork",
    "wof:placetype":"venue"
},
  "geometry": {"coordinates":[4.765232,52.957634],"type":"Point"}
}