{
  "type": "Feature",
  "properties": {
    "iso:country":"NL",
    "sg:address":"Iepenstraat 14",
    "sg:city":"Almere",
    "sg:orig_category":"Vertaal- And Tolkenbureaus",
    "sg:phone":"+31 36 523 1460",
    "sg:postcode":"1326 BA",
    "sg:province":"Flevoland",
    "wof:name":"It & C Support",
    "wof:placetype":"venue"
},
  "geometry": {"coordinates":[5.246145,52.374374],"type":"Point"}
}