{
  "type": "Feature",
  "properties": {
    "addr:full":"Abdissenln 84 Landgraaf Limburg 6374 BM",
    "addr:housenumber":"84",
    "addr:postcode":"6374 bm",
    "addr:street":"Abdissenln",
    "iso:country":"NL",
    "sg:address":"Abdissenln 84",
    "sg:city":"Landgraaf",
    "sg:orig_category":"Kappers",
    "sg:phone":"+31 45 532 2266",
    "sg:postcode":"6374 BM",
    "sg:province":"Limburg",
    "wof:name":"Hairwave",
    "wof:placetype":"venue"
},
  "geometry": {"coordinates":[6.0391411781,50.921459198],"type":"Point"}
}