{
  "type": "Feature",
  "properties": {
    "addr:full":"Gorredijksterweg 67 Jubbega Friesland 8411 KC",
    "addr:housenumber":"67",
    "addr:postcode":"8411 kc",
    "addr:street":"Gorredijksterweg",
    "iso:country":"NL",
    "sg:address":"Gorredijksterweg 67",
    "sg:city":"Jubbega",
    "sg:orig_category":"Bloemen And Planten Gh",
    "sg:phone":"+31 516 463 000",
    "sg:postcode":"8411 KC",
    "sg:province":"Friesland",
    "wof:name":"H.Post",
    "wof:placetype":"venue"
},
  "geometry": {"coordinates":[6.096458,52.985058],"type":"Point"}
}