{
  "type": "Feature",
  "properties": {
    "iso:country":"NL",
    "sg:address":"Hanenburgln 354",
    "sg:city":"S Gravenhage",
    "sg:orig_category":"Onroerende Goederen",
    "sg:phone":"+31 70 392 4817",
    "sg:postcode":"2565 HC",
    "sg:province":"Zuid-Holland",
    "wof:name":"Duynstaete Bv",
    "wof:placetype":"venue"
},
  "geometry": {"coordinates":[4.26129,52.076382],"type":"Point"}
}