{
  "type": "Feature",
  "properties": {
    "iso:country":"NL",
    "sg:address":"Parkwg 127",
    "sg:city":"Voorburg",
    "sg:orig_category":"Banken",
    "sg:phone":"+31 70 317 4174",
    "sg:postcode":"2271 AH",
    "sg:province":"Zuid-Holland",
    "sg:website":"http://www.rabobank.nl",
    "wof:name":"Rabobank",
    "wof:placetype":"venue"
},
  "geometry": {"coordinates":[4.365263,52.070595],"type":"Point"}
}