{
  "type": "Feature",
  "properties": {
    "addr:full":"Helicopterstraat 23 Amsterdam North Holland 1059 CE",
    "addr:housenumber":"23",
    "addr:postcode":"1059 ce",
    "addr:street":"Helicopterstraat",
    "iso:country":"NL",
    "sg:address":"Helicopterstraat 23",
    "sg:city":"Amsterdam",
    "sg:orig_category":"Loodgieterswerk, Verwarming And Sanitaire Installaties",
    "sg:phone":"+31 20 355 6500",
    "sg:postcode":"1059 CE",
    "sg:province":"North Holland",
    "wof:name":"Unica Installatietechniek Bv",
    "wof:placetype":"venue"
},
  "geometry": {"coordinates":[4.844873,52.340546],"type":"Point"}
}