{
  "type": "Feature",
  "properties": {
    "addr:full":"Doctor Erensstraat 4 Valkenburg Lb Limburg 6301 DX",
    "addr:housenumber":"4",
    "addr:postcode":"lb;6301 dx",
    "addr:street":"Doctor Erensstraat",
    "iso:country":"NL",
    "sg:address":"Doctor Erensstraat 4",
    "sg:city":"Valkenburg Lb",
    "sg:orig_category":"Opticiens",
    "sg:phone":"+31 43 601 3935",
    "sg:postcode":"6301 DX",
    "sg:province":"Limburg",
    "wof:name":"Vyghen Optiek",
    "wof:placetype":"venue"
},
  "geometry": {"coordinates":[5.8342270851,50.8647537231],"type":"Point"}
}