{
  "type": "Feature",
  "properties": {
    "addr:full":"Pres Kennedyln 715 Amsterdam North Holland 1079 MP",
    "addr:housenumber":"715",
    "addr:postcode":"1079 mp",
    "iso:country":"NL",
    "sg:address":"Pres Kennedyln 715",
    "sg:city":"Amsterdam",
    "sg:orig_category":"Verenigingen En Stichtingen",
    "sg:phone":"+31 20 661 1946",
    "sg:postcode":"1079 MP",
    "sg:province":"North Holland",
    "wof:name":"Vlieger Genootschap, Het",
    "wof:placetype":"venue"
},
  "geometry": {"coordinates":[4.89319,52.373119],"type":"Point"}
}