{
  "type": "Feature",
  "properties": {
    "addr:full":"Noordeinde 20 Landsmeer Noord-Holland 1121 AD",
    "addr:housenumber":"20",
    "addr:postcode":"1121 ad",
    "addr:street":"Noordeinde",
    "iso:country":"NL",
    "sg:address":"Noordeinde 20",
    "sg:city":"Landsmeer",
    "sg:orig_category":"Meubelen",
    "sg:phone":"+31 20 482 1479",
    "sg:postcode":"1121 AD",
    "sg:province":"Noord-Holland",
    "wof:name":"Walst Bv",
    "wof:placetype":"venue"
},
  "geometry": {"coordinates":[4.913803,52.441738],"type":"Point"}
}