{
  "type": "Feature",
  "properties": {
    "addr:full":"Hoefkestraat 17 Eindhoven North Brabant 5611 RK",
    "addr:housenumber":"17",
    "addr:postcode":"5611 rk",
    "addr:street":"Hoefkestraat",
    "iso:country":"NL",
    "sg:address":"Hoefkestraat 17",
    "sg:city":"Eindhoven",
    "sg:orig_category":"Autokeuringen",
    "sg:phone":"+31 40 211 2595",
    "sg:postcode":"5611 RK",
    "sg:province":"North Brabant",
    "wof:name":"Karting Service Slikker",
    "wof:placetype":"venue"
},
  "geometry": {"coordinates":[5.488661,51.432274],"type":"Point"}
}