{
  "type": "Feature",
  "properties": {
    "addr:full":"De Hennepe 218 Tiel Gelderland 4003 AK",
    "addr:housenumber":"218",
    "addr:postcode":"4003 ak",
    "addr:street":"De Hennepe;Gelderland",
    "iso:country":"NL",
    "sg:address":"De Hennepe 218",
    "sg:city":"Tiel",
    "sg:orig_category":"Stukadoorsbedrijven",
    "sg:phone":"+31 344 611 196",
    "sg:postcode":"4003 AK",
    "sg:province":"Gelderland",
    "wof:name":"Finishing Touch, The",
    "wof:placetype":"venue"
},
  "geometry": {"coordinates":[5.427664,51.899052],"type":"Point"}
}