{
  "type": "Feature",
  "properties": {
    "addr:full":"Sloterwg 342B Badhoevedorp North Holland 1171 VJ",
    "addr:housenumber":"342b",
    "addr:postcode":"1171 vj",
    "iso:country":"NL",
    "sg:address":"Sloterwg 342B",
    "sg:city":"Badhoevedorp",
    "sg:orig_category":"Onroerende Goederen",
    "sg:phone":"+31 20 449 3444",
    "sg:postcode":"1171 VJ",
    "sg:province":"North Holland",
    "sg:website":"http://www.koetenburg.nl",
    "wof:name":"Koetenburg Bv",
    "wof:placetype":"venue"
},
  "geometry": {"coordinates":[4.765021,52.32793],"type":"Point"}
}