{
  "type": "Feature",
  "properties": {
    "iso:country":"NL",
    "sg:address":"Liesselsewg 214",
    "sg:city":"Deurne",
    "sg:orig_category":"Oud Metaal",
    "sg:phone":"+31 493 312 764",
    "sg:postcode":"5753 PP",
    "sg:province":"Noord-Brabant",
    "wof:name":"Kuijpers, A",
    "wof:placetype":"venue"
},
  "geometry": {"coordinates":[5.8048992157,51.4381828308],"type":"Point"}
}