{
  "type": "Feature",
  "properties": {
    "addr:full":"De Krommert 27 Oosthuizen North Holland 1474 PN",
    "addr:housenumber":"27",
    "addr:postcode":"1474 pn",
    "addr:street":"De Krommert",
    "iso:country":"NL",
    "sg:address":"De Krommert 27",
    "sg:city":"Oosthuizen",
    "sg:orig_category":"Homeopathie",
    "sg:phone":"+31 299 403 470",
    "sg:postcode":"1474 PN",
    "sg:province":"North Holland",
    "wof:name":"Miedema Geertje",
    "wof:placetype":"venue"
},
  "geometry": {"coordinates":[4.99723,52.570892],"type":"Point"}
}