{
  "type": "Feature",
  "properties": {
    "addr:full":"Zijpe 13 Deurne Noord-Brabant 5751 ZP",
    "addr:housenumber":"13",
    "addr:postcode":"5751 zp",
    "addr:street":"Zijpe",
    "iso:country":"NL",
    "sg:address":"Zijpe 13",
    "sg:city":"Deurne",
    "sg:orig_category":"Autoreclame",
    "sg:phone":"+31 493 313 699",
    "sg:postcode":"5751 ZP",
    "sg:province":"Noord-Brabant",
    "wof:name":"Hugten Vof, Van",
    "wof:placetype":"venue"
},
  "geometry": {"coordinates":[5.809937,51.4548],"type":"Point"}
}