{
  "type": "Feature",
  "properties": {
    "addr:full":"Kleiwg 50 Gouda Zuid-Holland 2801 GH",
    "addr:housenumber":"50",
    "addr:postcode":"2801 gh",
    "addr:street":"Kleiwg",
    "iso:country":"NL",
    "sg:address":"Kleiwg 50",
    "sg:city":"Gouda",
    "sg:orig_category":"Sportschoenen - Winkels",
    "sg:phone":"+31 182 599 495",
    "sg:postcode":"2801 GH",
    "sg:province":"Zuid-Holland",
    "wof:name":"Coach Gouda Vof",
    "wof:placetype":"venue"
},
  "geometry": {"coordinates":[4.709893,52.013905],"type":"Point"}
}