{
  "type": "Feature",
  "properties": {
    "addr:full":"Pampuslaan 180 Weesp North Holland 1382 JS",
    "addr:housenumber":"180",
    "addr:postcode":"1382 js",
    "addr:street":"Pampuslaan",
    "iso:country":"NL",
    "sg:address":"Pampuslaan 180",
    "sg:city":"Weesp",
    "sg:orig_category":"Metaalbekleding And -Behandeling",
    "sg:phone":"+31 294 413 038",
    "sg:postcode":"1382 JS",
    "sg:province":"North Holland",
    "wof:name":"Machinefabriek J.H. Buitendijk Bv",
    "wof:placetype":"venue"
},
  "geometry": {"coordinates":[5.025066,52.315941],"type":"Point"}
}