{
  "type": "Feature",
  "properties": {
    "iso:country":"NL",
    "sg:address":"Kloosterkade 162",
    "sg:city":"Delft",
    "sg:classifiers":[
        {
            "category":"Fast Food",
            "type":"Food & Drink"
        }
    ],
    "sg:phone":"+31 15 256 0587",
    "sg:postcode":"2628 JG",
    "sg:province":"Zuid-Holland",
    "sg:tags":[
        "afhaal",
        "restaurant"
    ],
    "wof:name":"Snackbar 'T Oekie",
    "wof:placetype":"venue"
},
  "geometry": {"coordinates":[4.378222,52.005466],"type":"Point"}
}