{
  "type": "Feature",
  "properties": {
    "addr:full":"Zwanensngl 150 Velp Gld Gelderland 6883 GE",
    "addr:housenumber":"150",
    "addr:postcode":"6883",
    "addr:street":"Gld Gelderland",
    "iso:country":"NL",
    "sg:address":"Zwanensngl 150",
    "sg:city":"Velp Gld",
    "sg:orig_category":"Adviesbureaus Bouwkunde",
    "sg:phone":"+31 26 362 0031",
    "sg:postcode":"6883 GE",
    "sg:province":"Gelderland",
    "wof:name":"Stuiver, H",
    "wof:placetype":"venue"
},
  "geometry": {"coordinates":[5.97395,51.99601],"type":"Point"}
}