{
  "type": "Feature",
  "properties": {
    "addr:full":"Noorder Ij- En Zeeweg 2 Zaandam Noord-Holland 1505 HG",
    "addr:housenumber":"2",
    "addr:postcode":"1505 hg",
    "addr:street":"Noorder Ij En Zeeweg",
    "iso:country":"NL",
    "sg:address":"Noorder Ij- En Zeeweg 2",
    "sg:city":"Zaandam",
    "sg:orig_category":"Goederenvervoer Over De Weg",
    "sg:phone":"+31 75 615 8050",
    "sg:postcode":"1505 HG",
    "sg:province":"Noord-Holland",
    "wof:name":"Sitra Zaandam Bv",
    "wof:placetype":"venue"
},
  "geometry": {"coordinates":[4.854249,52.427773],"type":"Point"}
}