{
  "type": "Feature",
  "properties": {
    "addr:full":"Pr Hendrikstr 75-77 Breda Noord-Brabant 4835 PL",
    "addr:housenumber":"75-77",
    "addr:postcode":"breda;4835 pl",
    "iso:country":"NL",
    "sg:address":"Pr Hendrikstr 75-77",
    "sg:city":"Breda",
    "sg:orig_category":"Administratie- En Boekhoudkantoren",
    "sg:phone":"+31 76 561 4986",
    "sg:postcode":"4835 PL",
    "sg:province":"Noord-Brabant",
    "wof:name":"Brefin Administratiekantoor",
    "wof:placetype":"venue"
},
  "geometry": {"coordinates":[4.787201,51.572617],"type":"Point"}
}