{
  "type": "Feature",
  "properties": {
    "addr:full":"Kikkertstr 24 De Cocksdorp Noord-Holland 1795 AD",
    "addr:housenumber":"24",
    "addr:postcode":"1795 ad",
    "addr:street":"Kikkertstr",
    "iso:country":"NL",
    "sg:address":"Kikkertstr 24",
    "sg:city":"De Cocksdorp",
    "sg:classifiers":[
        {
            "category":"Travel",
            "subcategory":"Hotels & Motels",
            "type":"Entertainment"
        }
    ],
    "sg:phone":"+31 222 316 274",
    "sg:postcode":"1795 AD",
    "sg:province":"Noord-Holland",
    "wof:name":"Anker, 'T",
    "wof:placetype":"venue"
},
  "geometry": {"coordinates":[4.871929,53.156322],"type":"Point"}
}