{
  "type": "Feature",
  "properties": {
    "addr:full":"Pr Clausln 6 Badhoevedorp North Holland 1171 LD",
    "addr:housenumber":"6",
    "addr:postcode":"1171 ld",
    "iso:country":"NL",
    "sg:address":"Pr Clausln 6",
    "sg:city":"Badhoevedorp",
    "sg:orig_category":"Architecten En Architectenbureaus",
    "sg:phone":"+31 20 659 4119",
    "sg:postcode":"1171 LD",
    "sg:province":"North Holland",
    "wof:name":"Tecal Bv",
    "wof:placetype":"venue"
},
  "geometry": {"coordinates":[4.77827,52.338509],"type":"Point"}
}