{
  "type": "Feature",
  "properties": {
    "iso:country":"NL",
    "sg:address":"Buitenrustln 9",
    "sg:city":"Haarlem",
    "sg:orig_category":"Kinderopvang",
    "sg:phone":"+31 23 532 2436",
    "sg:postcode":"2012 BL",
    "sg:province":"Noord-Holland",
    "wof:name":"Dikkertje Dap",
    "wof:placetype":"venue"
},
  "geometry": {"coordinates":[4.638406,52.371544],"type":"Point"}
}