{
  "type": "Feature",
  "properties": {
    "addr:full":"Hadrianussingel 42 Beuningen Gld Gelderland 6642 AJ",
    "addr:housenumber":"42",
    "addr:postcode":"6642 aj",
    "addr:street":"Hadrianussingel",
    "iso:country":"NL",
    "sg:address":"Hadrianussingel 42",
    "sg:city":"Beuningen Gld",
    "sg:classifiers":[
        {
            "category":"Fast Food",
            "type":"Food & Drink"
        }
    ],
    "sg:phone":"+31 24 675 0508",
    "sg:postcode":"6642 AJ",
    "sg:province":"Gelderland",
    "sg:tags":[
        "afhaal",
        "restaurant"
    ],
    "wof:name":"Lotus Palace",
    "wof:placetype":"venue"
},
  "geometry": {"coordinates":[5.752261,51.8559],"type":"Point"}
}