{
  "type": "Feature",
  "properties": {
    "addr:full":"Postbus 139 Nieuwkoop South Holland 2420 AC",
    "addr:housenumber":"139",
    "addr:postcode":"2420 ac",
    "addr:street":"Postbus",
    "iso:country":"NL",
    "sg:address":"Postbus 139",
    "sg:city":"Nieuwkoop",
    "sg:orig_category":"Peuterspeelzalen",
    "sg:phone":"+31 172 573 314",
    "sg:postcode":"2420 AC",
    "sg:province":"South Holland",
    "wof:name":"Vijvertje, 'T",
    "wof:placetype":"venue"
},
  "geometry": {"coordinates":[4.778025,52.149162],"type":"Point"}
}