{
  "type": "Feature",
  "properties": {
    "addr:full":"Raadhuisstraat 51 Rucphen Noord-Brabant 4715 CC",
    "addr:housenumber":"51",
    "addr:postcode":"4715 cc",
    "addr:street":"Raadhuisstraat",
    "iso:country":"NL",
    "sg:address":"Raadhuisstraat 51",
    "sg:city":"Rucphen",
    "sg:classifiers":[
        {
            "category":"Fast Food",
            "type":"Food & Drink"
        }
    ],
    "sg:phone":"+31 165 341 661",
    "sg:postcode":"4715 CC",
    "sg:province":"Noord-Brabant",
    "sg:tags":[
        "afhaal",
        "restaurant"
    ],
    "wof:name":"T Voorhuys",
    "wof:placetype":"venue"
},
  "geometry": {"coordinates":[4.561067,51.532864],"type":"Point"}
}