{
  "type": "Feature",
  "properties": {
    "iso:country":"NL",
    "sg:address":"Breezyde 8",
    "sg:city":"Nieuwland",
    "sg:orig_category":"Elektrotechnische Installatiebureaus",
    "sg:phone":"+31 183 352 027",
    "sg:postcode":"4243 JM",
    "sg:province":"Zuid-Holland",
    "wof:name":"Groot, T De",
    "wof:placetype":"venue"
},
  "geometry": {"coordinates":[5.013928,51.901913],"type":"Point"}
}