{
  "type": "Feature",
  "properties": {
    "addr:full":"Dondersewg 8 Norg Provincie Drenthe 9331 BZ",
    "addr:housenumber":"8",
    "addr:postcode":"9331 bz",
    "addr:street":"Dondersewg;Provincie Drenthe",
    "iso:country":"NL",
    "sg:address":"Dondersewg 8",
    "sg:city":"Norg",
    "sg:orig_category":"Verzekeringen - Verzekeringskantoren",
    "sg:phone":"+31 592 612 884",
    "sg:postcode":"9331 BZ",
    "sg:province":"Provincie Drenthe",
    "sg:website":"http://www.dja.nl",
    "wof:name":"Jong, De",
    "wof:placetype":"venue"
},
  "geometry": {"coordinates":[6.477336,53.072609],"type":"Point"}
}