{
  "type": "Feature",
  "properties": {
    "addr:full":"Herungerberg 359 Venlo Limburg 5916 BC",
    "addr:housenumber":"359",
    "addr:postcode":"5916 bc",
    "addr:street":"Herungerberg",
    "iso:country":"NL",
    "sg:address":"Herungerberg 359",
    "sg:city":"Venlo",
    "sg:orig_category":"Accountants - Administratie- Consulenten En -Kantoren",
    "sg:phone":"+31 77 351 1478",
    "sg:postcode":"5916 BC",
    "sg:province":"Limburg",
    "wof:name":"Ligthuys En Rohmann",
    "wof:placetype":"venue"
},
  "geometry": {"coordinates":[6.206823,51.378613],"type":"Point"}
}