{
  "type": "Feature",
  "properties": {
    "addr:full":"Koepoortstr 40 Doesburg Gelderland 6981 AT",
    "addr:housenumber":"40",
    "addr:postcode":"6981",
    "addr:street":"Koepoortstr;Gelderland",
    "iso:country":"NL",
    "sg:address":"Koepoortstr 40",
    "sg:city":"Doesburg",
    "sg:orig_category":"Kunsthandel",
    "sg:phone":"+31 313 475 200",
    "sg:postcode":"6981 AT",
    "sg:province":"Gelderland",
    "sg:website":"http://www.kunsthandelnieuwenhuis.nl",
    "wof:name":"Nieuwenhuis, Kunsthandel J",
    "wof:placetype":"venue"
},
  "geometry": {"coordinates":[6.1331481934,52.0163879395],"type":"Point"}
}