{
  "type": "Feature",
  "properties": {
    "iso:country":"NL",
    "sg:address":"Aaldonksestraat 3",
    "sg:city":"Ottersum",
    "sg:orig_category":"Granen, Zaden And Diervoeders Gh",
    "sg:phone":"+31 485 518 170",
    "sg:postcode":"6595 NB",
    "sg:province":"Limburg",
    "wof:name":"B. Janssen",
    "wof:placetype":"venue"
},
  "geometry": {"coordinates":[5.985708,51.712379],"type":"Point"}
}