{
  "type": "Feature",
  "properties": {
    "iso:country":"NL",
    "sg:address":"Buitenveer 24",
    "sg:city":"Weesp",
    "sg:orig_category":"Watersportartikelen",
    "sg:phone":"+31 294 484 294",
    "sg:postcode":"1381 AD",
    "sg:province":"North Holland",
    "wof:name":"Weesper Watersport Winkel",
    "wof:placetype":"venue"
},
  "geometry": {"coordinates":[5.0381760597,52.3084526062],"type":"Point"}
}