{
  "type": "Feature",
  "properties": {
    "iso:country":"NL",
    "sg:address":"Moriaansewg O 76",
    "sg:city":"Hellevoetsluis",
    "sg:orig_category":"Meubelen",
    "sg:phone":"+31 181 323 735",
    "sg:postcode":"3223 AK",
    "sg:province":"Zuid-Holland",
    "wof:name":"Meubelaer, De",
    "wof:placetype":"venue"
},
  "geometry": {"coordinates":[4.13557,51.838455],"type":"Point"}
}