{
  "type": "Feature",
  "properties": {
    "addr:full":"Hazeldonk 6474 Breda Noord-Brabant 4836 LH",
    "addr:housenumber":"6474",
    "addr:postcode":"breda;4836 lh",
    "addr:street":"Hazeldonk",
    "iso:country":"NL",
    "sg:address":"Hazeldonk 6474",
    "sg:city":"Breda",
    "sg:classifiers":[
        {
            "category":"Building & Trades",
            "subcategory":"Electrical",
            "type":"Services"
        }
    ],
    "sg:phone":"+31 76 596 4649",
    "sg:postcode":"4836 LH",
    "sg:province":"Noord-Brabant",
    "sg:tags":[
        "distributor"
    ],
    "sg:website":"http://www.starsweets.com",
    "wof:name":"Starsweets Holl Bv",
    "wof:placetype":"venue"
},
  "geometry": {"coordinates":[4.744328,51.496899],"type":"Point"}
}