{
  "type": "Feature",
  "properties": {
    "iso:country":"NL",
    "sg:address":"Venneperhof 1C",
    "sg:city":"Nieuw Vennep",
    "sg:orig_category":"Broodjeszaken",
    "sg:phone":"+31 252 686 040",
    "sg:postcode":"2151 AW",
    "sg:province":"North Holland",
    "wof:name":"Plein 7",
    "wof:placetype":"venue"
},
  "geometry": {"coordinates":[4.631447,52.264057],"type":"Point"}
}