{
  "type": "Feature",
  "properties": {
    "addr:full":"Vlietwaard 319 Alkmaar Noord-Holland 1824 LM",
    "addr:housenumber":"319",
    "addr:postcode":"1824 lm",
    "addr:street":"Vlietwaard",
    "iso:country":"NL",
    "sg:address":"Vlietwaard 319",
    "sg:city":"Alkmaar",
    "sg:orig_category":"Schilders",
    "sg:phone":"+31 72 562 0194",
    "sg:postcode":"1824 LM",
    "sg:province":"Noord-Holland",
    "wof:name":"Stoop",
    "wof:placetype":"venue"
},
  "geometry": {"coordinates":[4.765897,52.64674],"type":"Point"}
}