{
  "type": "Feature",
  "properties": {
    "iso:country":"NL",
    "sg:address":"Hammarskjoldhof 10",
    "sg:city":"Utrecht",
    "sg:orig_category":"Opticiens",
    "sg:phone":"+31 30 293 1852",
    "sg:postcode":"3527 HE",
    "sg:province":"Utrecht",
    "wof:name":"Pearle Opticiens",
    "wof:placetype":"venue"
},
  "geometry": {"coordinates":[5.0938801765,52.0744171143],"type":"Point"}
}