{
  "type": "Feature",
  "properties": {
    "addr:full":"Hofcampwg 7 Wassenaar South Holland 2241 KD",
    "addr:housenumber":"7",
    "addr:postcode":"2241 kd",
    "addr:street":"Hofcampwg",
    "iso:country":"NL",
    "sg:address":"Hofcampwg 7",
    "sg:city":"Wassenaar",
    "sg:orig_category":"Artsen - Huisartsen",
    "sg:phone":"+31 70 511 2075",
    "sg:postcode":"2241 KD",
    "sg:province":"South Holland",
    "wof:name":"Tolingen, M H Van",
    "wof:placetype":"venue"
},
  "geometry": {"coordinates":[4.407047,52.1427],"type":"Point"}
}