{
  "type": "Feature",
  "properties": {
    "addr:full":"Schoolstr 18A Gieten Provincie Drenthe 9461 AB",
    "addr:housenumber":"18a",
    "addr:postcode":"9461 ab",
    "addr:street":"Schoolstr;Provincie Drenthe",
    "iso:country":"NL",
    "sg:address":"Schoolstr 18A",
    "sg:city":"Gieten",
    "sg:orig_category":"Projectontwikkeling",
    "sg:phone":"+31 592 543 179",
    "sg:postcode":"9461 AB",
    "sg:province":"Provincie Drenthe",
    "wof:name":"Svb",
    "wof:placetype":"venue"
},
  "geometry": {"coordinates":[6.766028,53.005672],"type":"Point"}
}