{
  "type": "Feature",
  "properties": {
    "iso:country":"NL",
    "sg:address":"Stuartweg 13",
    "sg:city":"Vianen Nb",
    "sg:orig_category":"Autokeuringen",
    "sg:phone":"+31 347 371 530",
    "sg:postcode":"4131 NH",
    "sg:province":"South Holland",
    "wof:name":"Autoschadeherstelbedrijf De Groot",
    "wof:placetype":"venue"
},
  "geometry": {"coordinates":[5.100631,51.985115],"type":"Point"}
}