{
  "type": "Feature",
  "properties": {
    "addr:full":"Achterstr 45 Helvoirt Noord-Brabant 5268 EA",
    "addr:housenumber":"45",
    "addr:postcode":"5268 ea",
    "addr:street":"Achterstr",
    "iso:country":"NL",
    "sg:address":"Achterstr 45",
    "sg:city":"Helvoirt",
    "sg:orig_category":"Piano'S",
    "sg:phone":"+31 411 641 245",
    "sg:postcode":"5268 EA",
    "sg:province":"Noord-Brabant",
    "sg:website":"http://www.vugtspiano.nl",
    "wof:name":"Vugts En Zn, Piano'S Fa H",
    "wof:placetype":"venue"
},
  "geometry": {"coordinates":[5.229054,51.631691],"type":"Point"}
}