{
  "type": "Feature",
  "properties": {
    "iso:country":"NL",
    "sg:address":"Noordlandsewg 70",
    "sg:city":"S Gravenzande",
    "sg:orig_category":"Bloemen En Planten",
    "sg:phone":"+31 174 412 041",
    "sg:postcode":"2691 KM",
    "sg:province":"South Holland",
    "wof:name":"Beekenkamp Ornamentals Bv",
    "wof:placetype":"venue"
},
  "geometry": {"coordinates":[4.143117,51.99651],"type":"Point"}
}