{
  "type": "Feature",
  "properties": {
    "addr:full":"Oudegr 133 Utrecht Utrecht 3511 AH",
    "addr:housenumber":"133",
    "addr:postcode":"3511 ah",
    "iso:country":"NL",
    "sg:address":"Oudegr 133",
    "sg:city":"Utrecht",
    "sg:orig_category":"Lijstenmakerijen",
    "sg:phone":"+31 30 231 5886",
    "sg:postcode":"3511 AH",
    "sg:province":"Utrecht",
    "sg:website":"http://www.homeinart.nl",
    "wof:name":"Uit De Kunst",
    "wof:placetype":"venue"
},
  "geometry": {"coordinates":[5.11745,52.091572],"type":"Point"}
}