{
  "type": "Feature",
  "properties": {
    "iso:country":"NL",
    "sg:address":"Gentiaansingel 5",
    "sg:city":"Jubbega",
    "sg:orig_category":"Overheidsdiensten",
    "sg:phone":"+31 516 461 804",
    "sg:postcode":"8411 VP",
    "sg:province":"Provincie Friesland",
    "wof:name":"De Stoater",
    "wof:placetype":"venue"
},
  "geometry": {"coordinates":[6.1261911392,53.0031661987],"type":"Point"}
}