{
  "type": "Feature",
  "properties": {
    "addr:full":"Visseringwg 40 Diemen North Holland 1112 AT",
    "addr:housenumber":"40",
    "addr:postcode":"1112",
    "addr:street":"Visseringwg",
    "iso:country":"NL",
    "sg:address":"Visseringwg 40",
    "sg:city":"Diemen",
    "sg:orig_category":"Drukkerijen",
    "sg:phone":"+31 20 398 0808",
    "sg:postcode":"1112 AT",
    "sg:province":"North Holland",
    "sg:website":"http://www.dijkman.nl",
    "wof:name":"Dijkman",
    "wof:placetype":"venue"
},
  "geometry": {"coordinates":[4.968397,52.332851],"type":"Point"}
}