{
  "type": "Feature",
  "properties": {
    "addr:full":"Wiekenplein 8A Heemstede Noord-Holland 2101 XS",
    "addr:housenumber":"8a",
    "addr:postcode":"2101 xs",
    "addr:street":"Wiekenplein",
    "iso:country":"NL",
    "sg:address":"Wiekenplein 8A",
    "sg:city":"Heemstede",
    "sg:orig_category":"Woningbouwverenigingen",
    "sg:phone":"+31 23 528 8036",
    "sg:postcode":"2101 XS",
    "sg:province":"Noord-Holland",
    "wof:name":"Woningstichting Op Eigen Wieken",
    "wof:placetype":"venue"
},
  "geometry": {"coordinates":[4.6194519997,52.3532142639],"type":"Point"}
}