{
  "type": "Feature",
  "properties": {
    "iso:country":"NL",
    "sg:address":"Voort 30",
    "sg:city":"Reusel",
    "sg:classifiers":[
        {
            "category":"Animal Shelter",
            "type":"Public Place"
        }
    ],
    "sg:phone":"+31 497 641 426",
    "sg:postcode":"5541 PH",
    "sg:province":"North Brabant",
    "sg:tags":[
        "kennel"
    ],
    "sg:website":"http://www.puppyfarm.nl",
    "wof:name":"Puppy Farm",
    "wof:placetype":"venue"
},
  "geometry": {"coordinates":[5.15105,51.362869],"type":"Point"}
}