{
  "type": "Feature",
  "properties": {
    "addr:full":"Kerkstraat 16 Strijen South Holland 3291 AL",
    "addr:housenumber":"16",
    "addr:postcode":"3291 al",
    "addr:street":"Kerkstraat",
    "iso:country":"NL",
    "sg:address":"Kerkstraat 16",
    "sg:city":"Strijen",
    "sg:orig_category":"Kappers",
    "sg:phone":"+31 78 674 1736",
    "sg:postcode":"3291 AL",
    "sg:province":"South Holland",
    "wof:name":"Dames- En Herenkapsalon Van Izerloo",
    "wof:placetype":"venue"
},
  "geometry": {"coordinates":[4.5531449318,51.7427940369],"type":"Point"}
}