{
  "type": "Feature",
  "properties": {
    "addr:full":"Stortenbekerstraat 205 'S Gravenhage South Holland 2525 SE",
    "addr:housenumber":"205 '",
    "addr:postcode":"2525 se",
    "addr:street":"Stortenbekerstraat",
    "iso:country":"NL",
    "sg:address":"Stortenbekerstraat 205",
    "sg:city":"'S Gravenhage",
    "sg:classifiers":[
        {
            "category":"Education",
            "subcategory":"Preschool",
            "type":"Public Place"
        }
    ],
    "sg:phone":"+31 70 388 3594",
    "sg:postcode":"2525 SE",
    "sg:province":"South Holland",
    "sg:tags":[
        "kleuteronderwijs",
        "basis-"
    ],
    "wof:name":"Het Spectrum",
    "wof:placetype":"venue"
},
  "geometry": {"coordinates":[4.303159,52.064476],"type":"Point"}
}