{
  "type": "Feature",
  "properties": {
    "addr:full":"Voorstr 12 Woerden Utrecht 3441 CL",
    "addr:housenumber":"12",
    "addr:postcode":"3441",
    "addr:street":"Voorstr",
    "iso:country":"NL",
    "sg:address":"Voorstr 12",
    "sg:city":"Woerden",
    "sg:orig_category":"Fietsen En Bromfietsen",
    "sg:phone":"+31 348 412 456",
    "sg:postcode":"3441 CL",
    "sg:province":"Utrecht",
    "wof:name":"Hans Voorn Tweewielercentrum",
    "wof:placetype":"venue"
},
  "geometry": {"coordinates":[4.88417,52.087292],"type":"Point"}
}