{
  "type": "Feature",
  "properties": {
    "addr:full":"Kathage 18 Wenum Wiesel Gelderland 7345 DN",
    "addr:housenumber":"18",
    "addr:postcode":"7345 dn",
    "addr:street":"Kathage",
    "iso:country":"NL",
    "sg:address":"Kathage 18",
    "sg:city":"Wenum Wiesel",
    "sg:orig_category":"Kermisexploitatie",
    "sg:phone":"+31 6 53117572",
    "sg:postcode":"7345 DN",
    "sg:province":"Gelderland",
    "wof:name":"D\u00f6renberg-Wegkamp Vof",
    "wof:placetype":"venue"
},
  "geometry": {"coordinates":[5.969207,52.24308],"type":"Point"}
}