{
  "type": "Feature",
  "properties": {
    "addr:full":"Plantage Middenlaan 25 Amsterdam Noord-Holland 1018 DB",
    "addr:housenumber":"25",
    "addr:postcode":"1018 db",
    "addr:street":"Plantage Middenlaan",
    "iso:country":"NL",
    "sg:address":"Plantage Middenlaan 25",
    "sg:city":"Amsterdam",
    "sg:orig_category":"Partycatering And -Organisatie",
    "sg:phone":"+31 20 420 6649",
    "sg:postcode":"1018 DB",
    "sg:province":"Noord-Holland",
    "wof:name":"Het Bourgondisch Genootschap",
    "wof:placetype":"venue"
},
  "geometry": {"coordinates":[4.910885,52.366924],"type":"Point"}
}