{
  "type": "Feature",
  "properties": {
    "addr:full":"Luxwoudestr 19 Tilburg Noord-Brabant 5045 XH",
    "addr:housenumber":"19",
    "addr:postcode":"5045 xh",
    "addr:street":"Luxwoudestr",
    "iso:country":"NL",
    "sg:address":"Luxwoudestr 19",
    "sg:city":"Tilburg",
    "sg:orig_category":"Metaalbewerking",
    "sg:phone":"+31 13 571 1571",
    "sg:postcode":"5045 XH",
    "sg:province":"Noord-Brabant",
    "wof:name":"Sufra",
    "wof:placetype":"venue"
},
  "geometry": {"coordinates":[4.9993,51.586037],"type":"Point"}
}