{
  "type": "Feature",
  "properties": {
    "addr:full":"Haarstr 41-43 Gorinchem South Holland 4201 JB",
    "addr:housenumber":"41-43",
    "addr:postcode":"4201 jb",
    "addr:street":"Haarstr",
    "iso:country":"NL",
    "sg:address":"Haarstr 41-43",
    "sg:city":"Gorinchem",
    "sg:orig_category":"Kappers",
    "sg:phone":"+31 183 631 517",
    "sg:postcode":"4201 JB",
    "sg:province":"South Holland",
    "wof:name":"Pulmans Salon, Harry",
    "wof:placetype":"venue"
},
  "geometry": {"coordinates":[4.974131,51.831978],"type":"Point"}
}