{
  "type": "Feature",
  "properties": {
    "addr:full":"Havermarkt 23A Breda Noord-Brabant 4811 WG",
    "addr:housenumber":"23a",
    "addr:postcode":"4811 wg",
    "addr:street":"Havermarkt",
    "iso:country":"NL",
    "sg:address":"Havermarkt 23A",
    "sg:city":"Breda",
    "sg:orig_category":"Broodjeszaken",
    "sg:phone":"+31 76 522 3006",
    "sg:postcode":"4811 WG",
    "sg:province":"Noord-Brabant",
    "wof:name":"Panach?",
    "wof:placetype":"venue"
},
  "geometry": {"coordinates":[4.773495,51.589088],"type":"Point"}
}