{
  "type": "Feature",
  "properties": {
    "addr:full":"Berghemsewg 104 Oss Virginia 5348 CL",
    "addr:housenumber":"104",
    "addr:postcode":"5348",
    "iso:country":"NL",
    "sg:address":"Berghemsewg 104",
    "sg:city":"Oss",
    "sg:orig_category":"Verenigingen En Stichtingen",
    "sg:phone":"+31 412 623 787",
    "sg:postcode":"5348 CL",
    "sg:province":"Virginia",
    "wof:name":"Huurders Belangen Oss, Ver",
    "wof:placetype":"venue"
},
  "geometry": {"coordinates":[-77.235214,38.312599],"type":"Point"}
}