{
  "type": "Feature",
  "properties": {
    "iso:country":"NL",
    "sg:address":"Mary Zeldenruststraat 59",
    "sg:city":"Hoofddorp",
    "sg:orig_category":"Vertaal- And Tolkenbureaus",
    "sg:phone":"+31 23 563 9307",
    "sg:postcode":"2135 JM",
    "sg:province":"Noord-Holland",
    "wof:name":"M.A. Mohiddin",
    "wof:placetype":"venue"
},
  "geometry": {"coordinates":[4.671274,52.297466],"type":"Point"}
}