{
  "type": "Feature",
  "properties": {
    "addr:full":"Stationsstr 11B Scheemda Groningen 9679 EA",
    "addr:housenumber":"11b",
    "addr:postcode":"9679 ea",
    "addr:street":"Stationsstr",
    "iso:country":"NL",
    "sg:address":"Stationsstr 11B",
    "sg:city":"Scheemda",
    "sg:orig_category":"Verenigingen En Stichtingen",
    "sg:phone":"+31 597 591 025",
    "sg:postcode":"9679 EA",
    "sg:province":"Groningen",
    "wof:name":"Grunneger Toal, Sticht",
    "wof:placetype":"venue"
},
  "geometry": {"coordinates":[6.971068,53.17482],"type":"Point"}
}