{
  "type": "Feature",
  "properties": {
    "addr:full":"Emmalaan 11 Harmelen Utrecht 3481 VB",
    "addr:housenumber":"11",
    "addr:postcode":"3481 vb",
    "addr:street":"Emmalaan",
    "iso:country":"NL",
    "sg:address":"Emmalaan 11",
    "sg:city":"Harmelen",
    "sg:orig_category":"Wegen And Sportterreinen",
    "sg:phone":"+31 348 441 677",
    "sg:postcode":"3481 VB",
    "sg:province":"Utrecht",
    "wof:name":"Aannemersbedrijf D. Huisman",
    "wof:placetype":"venue"
},
  "geometry": {"coordinates":[4.9615011215,52.0864181519],"type":"Point"}
}