{
  "type": "Feature",
  "properties": {
    "addr:full":"I Vorrinkstr 27 Culemborg Gelderland 4105 JA",
    "addr:housenumber":"27",
    "addr:postcode":"4105 ja",
    "addr:street":"Gelderland",
    "iso:country":"NL",
    "sg:address":"I Vorrinkstr 27",
    "sg:city":"Culemborg",
    "sg:orig_category":"Kantoor- En Secretariaatsservice",
    "sg:phone":"+31 345 544 610",
    "sg:postcode":"4105 JA",
    "sg:province":"Gelderland",
    "wof:name":"Instant Quality",
    "wof:placetype":"venue"
},
  "geometry": {"coordinates":[5.2214798927,51.9521751404],"type":"Point"}
}