{
  "type": "Feature",
  "properties": {
    "iso:country":"NL",
    "sg:address":"Weyerstr 6",
    "sg:city":"Boxmeer",
    "sg:orig_category":"Bejaarden - Verzorgingstehuizen",
    "sg:phone":"+31 485 573 879",
    "sg:postcode":"5831 JV",
    "sg:province":"Noord-Brabant",
    "wof:name":"Weyerdonck Steunpunt, De",
    "wof:placetype":"venue"
},
  "geometry": {"coordinates":[5.950357,51.646206],"type":"Point"}
}