{
  "type": "Feature",
  "properties": {
    "addr:full":"Westsngl 132 Goes Zeeland 4461 DR",
    "addr:housenumber":"132",
    "addr:postcode":"4461 dr",
    "iso:country":"NL",
    "sg:address":"Westsngl 132",
    "sg:city":"Goes",
    "sg:orig_category":"Adviesbureaus Beroeps-, School- And Studiekeuze",
    "sg:phone":"+31 113 230 548",
    "sg:postcode":"4461 DR",
    "sg:province":"Zeeland",
    "sg:website":"http://www.aobzn.nl",
    "wof:name":"Aob Zuid-Nederland",
    "wof:placetype":"venue"
},
  "geometry": {"coordinates":[-83.914169,39.768833],"type":"Point"}
}