{
  "type": "Feature",
  "properties": {
    "addr:full":"Vd Maesenstr 1 Heerlen Limburg 6411 LP",
    "addr:housenumber":"1",
    "addr:postcode":"6411 lp",
    "iso:country":"NL",
    "sg:address":"Vd Maesenstr 1",
    "sg:city":"Heerlen",
    "sg:orig_category":"Warenhuizen",
    "sg:phone":"+31 45 400 9966",
    "sg:postcode":"6411 LP",
    "sg:province":"Limburg",
    "wof:name":"Hema",
    "wof:placetype":"venue"
},
  "geometry": {"coordinates":[5.9769740105,50.8890838623],"type":"Point"}
}