{
  "type": "Feature",
  "properties": {
    "addr:full":"Shakespearezijde 3 Zoetermeer South Holland 2725 NP",
    "addr:housenumber":"3",
    "addr:postcode":"2725 np",
    "addr:street":"Shakespearezijde",
    "iso:country":"NL",
    "sg:address":"Shakespearezijde 3",
    "sg:city":"Zoetermeer",
    "sg:orig_category":"Boekhouders",
    "sg:phone":"+31 79 341 3043",
    "sg:postcode":"2725 NP",
    "sg:province":"South Holland",
    "wof:name":"Senator Administraties & Advies Bv",
    "wof:placetype":"venue"
},
  "geometry": {"coordinates":[4.497059,52.070591],"type":"Point"}
}