{
  "type": "Feature",
  "properties": {
    "addr:full":"Lambarenestraat 3 Delft Zuid-Holland 2622 DN",
    "addr:housenumber":"3",
    "addr:postcode":"2622 dn",
    "addr:street":"Lambarenestraat",
    "iso:country":"NL",
    "sg:address":"Lambarenestraat 3",
    "sg:city":"Delft",
    "sg:orig_category":"Elektronische Bedrijfsinstallaties",
    "sg:phone":"+31 15 256 8490",
    "sg:postcode":"2622 DN",
    "sg:province":"Zuid-Holland",
    "wof:name":"Inbraak, Preventie En Vertragende Maatregelen",
    "wof:placetype":"venue"
},
  "geometry": {"coordinates":[4.336924,51.98175],"type":"Point"}
}