{
  "type": "Feature",
  "properties": {
    "iso:country":"NL",
    "sg:address":"Nieuwe Steen 2",
    "sg:city":"Hoorn Nh",
    "sg:orig_category":"Makelaars In Onroerend Goed",
    "sg:phone":"+31 229 244 844",
    "sg:postcode":"1625 HV",
    "sg:province":"North Holland",
    "wof:name":"Abc Vastgoedbeheer",
    "wof:placetype":"venue"
},
  "geometry": {"coordinates":[5.063526,52.655064],"type":"Point"}
}