{
  "type": "Feature",
  "properties": {
    "iso:country":"NL",
    "sg:address":"Wendeling 90",
    "sg:city":"Emmen",
    "sg:orig_category":"Koeriersdiensten",
    "sg:phone":"+31 591 625 973",
    "sg:postcode":"7824 TJ",
    "sg:province":"Drenthe",
    "wof:name":"Unitrans Couriers",
    "wof:placetype":"venue"
},
  "geometry": {"coordinates":[6.92699,52.77795],"type":"Point"}
}