{
  "type": "Feature",
  "properties": {
    "addr:full":"Dreespassage 2 Alphen Aan Den Ryn Zuid-Holland 2406 DE",
    "addr:housenumber":"2",
    "addr:postcode":"2406 de",
    "addr:street":"Dreespassage;Aan Den Ryn",
    "iso:country":"NL",
    "sg:address":"Dreespassage 2",
    "sg:city":"Alphen Aan Den Ryn",
    "sg:orig_category":"Kinderkleding",
    "sg:phone":"+31 172 476 365",
    "sg:postcode":"2406 DE",
    "sg:province":"Zuid-Holland",
    "wof:name":"Cactus",
    "wof:placetype":"venue"
},
  "geometry": {"coordinates":[4.664575,52.130695],"type":"Point"}
}