{
  "type": "Feature",
  "properties": {
    "iso:country":"NL",
    "sg:address":"Haverstr Passage 7",
    "sg:city":"Enschede",
    "sg:orig_category":"Ontbijtservice",
    "sg:phone":"+31 53 431 8039",
    "sg:postcode":"7511 ET",
    "sg:province":"NL.08",
    "wof:name":"Delifrance",
    "wof:placetype":"venue"
},
  "geometry": {"coordinates":[6.897671,52.219776],"type":"Point"}
}