{
  "type": "Feature",
  "properties": {
    "iso:country":"NL",
    "sg:address":"Havenstr 43B",
    "sg:city":"Hilversum",
    "sg:orig_category":"Woninginrichting",
    "sg:phone":"+31 35 621 8975",
    "sg:postcode":"1211 KG",
    "sg:province":"Noord-Holland",
    "sg:website":"http://www.gooische-slaapspecialist.nl",
    "wof:name":"Gooische Slaapspecialist, De",
    "wof:placetype":"venue"
},
  "geometry": {"coordinates":[5.1694998741,52.2285652161],"type":"Point"}
}