{
  "type": "Feature",
  "properties": {
    "addr:full":"Zuiderzeestrwg 251 Oldebroek Gelderland 8096 BK",
    "addr:housenumber":"251",
    "addr:postcode":"8096 bk",
    "addr:street":"Gelderland",
    "iso:country":"NL",
    "sg:address":"Zuiderzeestrwg 251",
    "sg:city":"Oldebroek",
    "sg:orig_category":"Grondwerken",
    "sg:phone":"+31 525 631 480",
    "sg:postcode":"8096 BK",
    "sg:province":"Gelderland",
    "wof:name":"Besten, B Den",
    "wof:placetype":"venue"
},
  "geometry": {"coordinates":[5.8934,52.445419],"type":"Point"}
}