{
  "type": "Feature",
  "properties": {
    "addr:full":"Dkn V Baarsstr 8 Budel Noord-Brabant 6021 BH",
    "addr:housenumber":"8",
    "addr:postcode":"6021 bh",
    "addr:street":"Baarsstr",
    "iso:country":"NL",
    "sg:address":"Dkn V Baarsstr 8",
    "sg:city":"Budel",
    "sg:classifiers":[
        {
            "category":"Shopping",
            "subcategory":"Adult",
            "type":"Retail Goods"
        }
    ],
    "sg:phone":"+31 495 499 453",
    "sg:postcode":"6021 BH",
    "sg:province":"Noord-Brabant",
    "sg:tags":[
        "lingerie",
        "en",
        "tricotage"
    ],
    "wof:name":"Roses & Honey",
    "wof:placetype":"venue"
},
  "geometry": {"coordinates":[5.576494,51.274277],"type":"Point"}
}