{
  "type": "Feature",
  "properties": {
    "addr:full":"Dommelstr 30 Terneuzen Zeeland 4535 HB",
    "addr:housenumber":"30",
    "addr:postcode":"4535 hb",
    "addr:street":"Dommelstr",
    "iso:country":"NL",
    "sg:address":"Dommelstr 30",
    "sg:city":"Terneuzen",
    "sg:orig_category":"Verzekeringen - Verzekeringskantoren",
    "sg:phone":"+31 115 695 388",
    "sg:postcode":"4535 HB",
    "sg:province":"Zeeland",
    "wof:name":"Vermeulen",
    "wof:placetype":"venue"
},
  "geometry": {"coordinates":[3.86457,51.312283],"type":"Point"}
}