{
  "type": "Feature",
  "properties": {
    "addr:full":"Stuivezandsestr 5 Made California 4921 XP",
    "addr:housenumber":"5",
    "addr:postcode":"4921 xp",
    "addr:street":"Stuivezandsestr",
    "iso:country":"NL",
    "sg:address":"Stuivezandsestr 5",
    "sg:city":"Made",
    "sg:classifiers":[
        {
            "category":"Food & Beverages",
            "subcategory":"Bakery",
            "type":"Retail Goods"
        }
    ],
    "sg:phone":"+31 162 682 353",
    "sg:postcode":"4921 XP",
    "sg:province":"California",
    "sg:tags":[
        "brood",
        "en",
        "banket"
    ],
    "wof:name":"Westen Vof, L C J Van Der",
    "wof:placetype":"venue"
},
  "geometry": {"coordinates":[-120.101364,36.829536],"type":"Point"}
}