{
  "type": "Feature",
  "properties": {
    "addr:full":"Bosmanskamp 18 Geldermalsen Gelderland 4191 MV",
    "addr:housenumber":"18",
    "addr:postcode":"4191 mv",
    "addr:street":"Bosmanskamp;Gelderland",
    "iso:country":"NL",
    "sg:address":"Bosmanskamp 18",
    "sg:city":"Geldermalsen",
    "sg:orig_category":"Bakkerijmachines En -Gereedschappen",
    "sg:phone":"+31 345 473 984",
    "sg:postcode":"4191 MV",
    "sg:province":"Gelderland",
    "wof:name":"Rinc Europe Bv",
    "wof:placetype":"venue"
},
  "geometry": {"coordinates":[5.303068,51.873924],"type":"Point"}
}