{
  "type": "Feature",
  "properties": {
    "iso:country":"NL",
    "sg:address":"Stevinlaan 10",
    "sg:city":"Doetinchem",
    "sg:orig_category":"Bedrijfs- And Managementsconsultants",
    "sg:phone":"+31 314 325 262",
    "sg:postcode":"7002 HD",
    "sg:province":"Gelderland",
    "wof:name":"Adviesbureau Steenhuisen",
    "wof:placetype":"venue"
},
  "geometry": {"coordinates":[6.317128,51.972],"type":"Point"}
}