{
  "type": "Feature",
  "properties": {
    "iso:country":"NL",
    "sg:address":"Mathijs Heugenstraat 19",
    "sg:city":"Maastricht",
    "sg:orig_category":"Mobiele Service Aan Motorvoertuigen",
    "sg:phone":"+31 43 361 2758",
    "sg:postcode":"6227 AV",
    "sg:province":"Limburg",
    "wof:name":"G.W. Van Hooren",
    "wof:placetype":"venue"
},
  "geometry": {"coordinates":[5.725092,50.842876],"type":"Point"}
}