{
  "type": "Feature",
  "properties": {
    "addr:full":"Economiestr 12 Sittard Limburg 6135 KV",
    "addr:housenumber":"12",
    "addr:postcode":"6135 kv",
    "addr:street":"Economiestr",
    "iso:country":"NL",
    "sg:address":"Economiestr 12",
    "sg:city":"Sittard",
    "sg:orig_category":"Kappersbenodigdheden",
    "sg:phone":"+31 46 420 0470",
    "sg:postcode":"6135 KV",
    "sg:province":"Limburg",
    "wof:name":"Luca",
    "wof:placetype":"venue"
},
  "geometry": {"coordinates":[5.84128,50.996784],"type":"Point"}
}