{
  "type": "Feature",
  "properties": {
    "addr:full":"Utrechtsedwstr 28 A Amsterdam North Holland 1017 WG",
    "addr:housenumber":"28 a",
    "addr:postcode":"1017 wg",
    "addr:street":"Utrechtsedwstr",
    "iso:country":"NL",
    "sg:address":"Utrechtsedwstr 28 A",
    "sg:city":"Amsterdam",
    "sg:orig_category":"Beeldende Kunstenaars",
    "sg:phone":"+31 20 620 5010",
    "sg:postcode":"1017 WG",
    "sg:province":"North Holland",
    "wof:name":"Keulen, L Van",
    "wof:placetype":"venue"
},
  "geometry": {"coordinates":[4.897476,52.361034],"type":"Point"}
}