{
  "type": "Feature",
  "properties": {
    "addr:full":"Pr Beatrixln 5 Vlaardingen Zuid-Holland 3136 AD",
    "addr:housenumber":"5",
    "addr:postcode":"3136 ad",
    "iso:country":"NL",
    "sg:address":"Pr Beatrixln 5",
    "sg:city":"Vlaardingen",
    "sg:orig_category":"Adviesbureaus Economie",
    "sg:phone":"+31 10 474 1424",
    "sg:postcode":"3136 AD",
    "sg:province":"Zuid-Holland",
    "wof:name":"Vtc",
    "wof:placetype":"venue"
},
  "geometry": {"coordinates":[4.339151,51.930336],"type":"Point"}
}