{
  "type": "Feature",
  "properties": {
    "addr:full":"Groenstraat 2 A Hoogeloon Noord-Brabant 5528 NS",
    "addr:housenumber":"2 a",
    "addr:postcode":"5528 ns",
    "addr:street":"Groenstraat",
    "iso:country":"NL",
    "sg:address":"Groenstraat 2 A",
    "sg:city":"Hoogeloon",
    "sg:orig_category":"Hoefdierhouderijen",
    "sg:phone":"+31 497 682 057",
    "sg:postcode":"5528 NS",
    "sg:province":"Noord-Brabant",
    "wof:name":"Stal Burg Bv",
    "wof:placetype":"venue"
},
  "geometry": {"coordinates":[5.264848,51.4016],"type":"Point"}
}