{
  "type": "Feature",
  "properties": {
    "addr:full":"Geldersestr 2B Geldermalsen Gelderland 4191 BC",
    "addr:housenumber":"2b",
    "addr:postcode":"4191 bc",
    "addr:street":"Geldersestr;Gelderland",
    "iso:country":"NL",
    "sg:address":"Geldersestr 2B",
    "sg:city":"Geldermalsen",
    "sg:orig_category":"Drogisterijen",
    "sg:phone":"+31 345 574 869",
    "sg:postcode":"4191 BC",
    "sg:province":"Gelderland",
    "wof:name":"Kruidvat",
    "wof:placetype":"venue"
},
  "geometry": {"coordinates":[5.290205,51.883282],"type":"Point"}
}