{
  "type": "Feature",
  "properties": {
    "iso:country":"NL",
    "sg:address":"Vuurplaat 158",
    "sg:city":"Rotterdam",
    "sg:orig_category":"Apothekers",
    "sg:phone":"+31 10 486 3177",
    "sg:postcode":"3071 AR",
    "sg:province":"Zuid-Holland",
    "wof:name":"Apotheek Drogisterij De Vuurplaat",
    "wof:placetype":"venue"
},
  "geometry": {"coordinates":[-73.97101600000001,42.785419],"type":"Point"}
}