{
  "type": "Feature",
  "properties": {
    "addr:full":"Tarthorst 1221 Wageningen Gelderland 6708 HZ",
    "addr:housenumber":"1221",
    "addr:postcode":"6708 hz",
    "addr:street":"Tarthorst;Gelderland",
    "iso:country":"NL",
    "sg:address":"Tarthorst 1221",
    "sg:city":"Wageningen",
    "sg:orig_category":"Bloemen En Planten",
    "sg:phone":"+31 317 410 763",
    "sg:postcode":"6708 HZ",
    "sg:province":"Gelderland",
    "wof:name":"Tarthorst, De",
    "wof:placetype":"venue"
},
  "geometry": {"coordinates":[5.662959,51.978794],"type":"Point"}
}