{
  "type": "Feature",
  "properties": {
    "addr:full":"Marktstraat 22 Sneek Friesland 8601 CV",
    "addr:housenumber":"22",
    "addr:postcode":"8601 cv",
    "addr:street":"Marktstraat",
    "iso:country":"NL",
    "sg:address":"Marktstraat 22",
    "sg:city":"Sneek",
    "sg:orig_category":"Notarissen",
    "sg:phone":"+31 515 417 025",
    "sg:postcode":"8601 CV",
    "sg:province":"Friesland",
    "wof:name":"Notaris Mr. J.P.G. Mensen",
    "wof:placetype":"venue"
},
  "geometry": {"coordinates":[5.659477,53.032249],"type":"Point"}
}