{
  "type": "Feature",
  "properties": {
    "addr:full":"Rijksstraatweg 69 Sleeuwijk Noord-Brabant 4254 XB",
    "addr:housenumber":"69",
    "addr:postcode":"4254 xb",
    "addr:street":"Rijksstraatweg",
    "iso:country":"NL",
    "sg:address":"Rijksstraatweg 69",
    "sg:city":"Sleeuwijk",
    "sg:orig_category":"Meubelzaken, Woning- And Keukeninrichting",
    "sg:phone":"+31 183 303 311",
    "sg:postcode":"4254 XB",
    "sg:province":"Noord-Brabant",
    "wof:name":"Van Schuppen Wooncentrum Bv",
    "wof:placetype":"venue"
},
  "geometry": {"coordinates":[4.952836,51.810856],"type":"Point"}
}