{
  "type": "Feature",
  "properties": {
    "addr:full":"Kamervoort 2 Angeren Gelderland 6687 LA",
    "addr:housenumber":"2",
    "addr:postcode":"6687",
    "addr:street":"Kamervoort;Gelderland",
    "iso:country":"NL",
    "sg:address":"Kamervoort 2",
    "sg:city":"Angeren",
    "sg:orig_category":"Kappers",
    "sg:phone":"+31 26 325 8242",
    "sg:postcode":"6687 LA",
    "sg:province":"Gelderland",
    "wof:name":"Dave'S Hairstyling",
    "wof:placetype":"venue"
},
  "geometry": {"coordinates":[5.9517498016,51.9163513184],"type":"Point"}
}