{
  "type": "Feature",
  "properties": {
    "addr:full":"Frederik Van De Paltshof 16 Rhenen Utrecht 3911 LB",
    "addr:housenumber":"16",
    "addr:postcode":"3911 lb",
    "addr:street":"Frederik Van De Paltshof",
    "iso:country":"NL",
    "sg:address":"Frederik Van De Paltshof 16",
    "sg:city":"Rhenen",
    "sg:orig_category":"Banken And Kredietinstellingen",
    "sg:phone":"+31 317 612 424",
    "sg:postcode":"3911 LB",
    "sg:province":"Utrecht",
    "wof:name":"Gelders Utrechtse Spaarbank",
    "wof:placetype":"venue"
},
  "geometry": {"coordinates":[5.564954,51.957615],"type":"Point"}
}