{
  "type": "Feature",
  "properties": {
    "addr:full":"Haltestr 5 Zandvoort Noord-Holland 2042 LJ",
    "addr:housenumber":"5",
    "addr:postcode":"2042 lj",
    "addr:street":"Haltestr",
    "iso:country":"NL",
    "sg:address":"Haltestr 5",
    "sg:city":"Zandvoort",
    "sg:orig_category":"Opticiens",
    "sg:phone":"+31 23 571 2174",
    "sg:postcode":"2042 LJ",
    "sg:province":"Noord-Holland",
    "wof:name":"York",
    "wof:placetype":"venue"
},
  "geometry": {"coordinates":[4.5299491882,52.3723678589],"type":"Point"}
}