{
  "type": "Feature",
  "properties": {
    "addr:full":"Zenderseweg 44 Albergen Overijssel 7665 TN",
    "addr:housenumber":"44",
    "addr:postcode":"7665",
    "addr:street":"Zenderseweg",
    "iso:country":"NL",
    "sg:address":"Zenderseweg 44",
    "sg:city":"Albergen",
    "sg:orig_category":"Loodgieterswerk, Verwarming And Sanitaire Installaties",
    "sg:phone":"+31 546 441 480",
    "sg:postcode":"7665 TN",
    "sg:province":"Overijssel",
    "wof:name":"Afwerkingsbedrijf Kippers Bv",
    "wof:placetype":"venue"
},
  "geometry": {"coordinates":[6.759959,52.366272],"type":"Point"}
}