{
  "type": "Feature",
  "properties": {
    "addr:full":"Markerkant 1303D Almere Flevoland 1314 AL",
    "addr:housenumber":"1314",
    "addr:postcode":"al",
    "addr:street":"Markerkant 1303D;Flevoland",
    "iso:country":"NL",
    "sg:address":"Markerkant 1303D",
    "sg:city":"Almere",
    "sg:orig_category":"Hang- En Sluitwerk - Fabrieken En Groothandel",
    "sg:phone":"+31 36 530 5369",
    "sg:postcode":"1314 AL",
    "sg:province":"Flevoland",
    "wof:name":"Keyman Prod Int",
    "wof:placetype":"venue"
},
  "geometry": {"coordinates":[5.213485,52.384525],"type":"Point"}
}