{
  "type": "Feature",
  "properties": {
    "addr:full":"Hoogeveenseweg 4 Hazerswoude Dorp Zuid-Holland 2391 NR",
    "addr:housenumber":"4",
    "addr:postcode":"2391 nr",
    "addr:street":"Hoogeveenseweg",
    "iso:country":"NL",
    "sg:address":"Hoogeveenseweg 4",
    "sg:city":"Hazerswoude Dorp",
    "sg:orig_category":"Wegen And Sportterreinen",
    "sg:phone":"+31 79 341 0539",
    "sg:postcode":"2391 NR",
    "sg:province":"Zuid-Holland",
    "wof:name":"Aannemingsbedrijf Vermeulen Benthuizen Bv",
    "wof:placetype":"venue"
},
  "geometry": {"coordinates":[4.5638589859,52.0785560608],"type":"Point"}
}