{
  "type": "Feature",
  "properties": {
    "addr:full":"Middenstraat 8 Zuidlaren Drenthe 9471 GC",
    "addr:housenumber":"8",
    "addr:postcode":"9471 gc",
    "addr:street":"Middenstraat",
    "iso:country":"NL",
    "sg:address":"Middenstraat 8",
    "sg:city":"Zuidlaren",
    "sg:orig_category":"Kappers",
    "sg:phone":"+31 50 409 2302",
    "sg:postcode":"9471 GC",
    "sg:province":"Drenthe",
    "wof:name":"Haarstudio Els",
    "wof:placetype":"venue"
},
  "geometry": {"coordinates":[6.6851477623,53.0941162109],"type":"Point"}
}