{
  "type": "Feature",
  "properties": {
    "addr:full":"Prinsenstraat 43 Zaandam North Holland 1501 NS",
    "addr:housenumber":"43",
    "addr:postcode":"1501 ns",
    "addr:street":"Prinsenstraat",
    "iso:country":"NL",
    "sg:address":"Prinsenstraat 43",
    "sg:city":"Zaandam",
    "sg:orig_category":"Overheidsdiensten",
    "sg:phone":"+31 75 635 4905",
    "sg:postcode":"1501 NS",
    "sg:province":"North Holland",
    "wof:name":"De Doorbraak",
    "wof:placetype":"venue"
},
  "geometry": {"coordinates":[4.8306689262,52.4395332336],"type":"Point"}
}