{
  "type": "Feature",
  "properties": {
    "addr:full":"Roompotstr 1 Zierikzee Zeeland 4301 RE",
    "addr:housenumber":"1",
    "addr:postcode":"4301",
    "addr:street":"Roompotstr",
    "iso:country":"NL",
    "sg:address":"Roompotstr 1",
    "sg:city":"Zierikzee",
    "sg:orig_category":"Matrijzen",
    "sg:phone":"+31 111 415 037",
    "sg:postcode":"4301 RE",
    "sg:province":"Zeeland",
    "wof:name":"Vorma Bv",
    "wof:placetype":"venue"
},
  "geometry": {"coordinates":[3.92114,51.64465],"type":"Point"}
}