{
  "type": "Feature",
  "properties": {
    "addr:full":"Marconiweg 17 Hellevoetsluis South Holland 3225 LV",
    "addr:housenumber":"17",
    "addr:postcode":"3225",
    "addr:street":"Marconiweg",
    "iso:country":"NL",
    "sg:address":"Marconiweg 17",
    "sg:city":"Hellevoetsluis",
    "sg:orig_category":"Pompen And Compressoren Fab",
    "sg:phone":"+31 181 322 358",
    "sg:postcode":"3225 LV",
    "sg:province":"South Holland",
    "wof:name":"Cts Consultancies & Technical Services",
    "wof:placetype":"venue"
},
  "geometry": {"coordinates":[4.169206,51.840782],"type":"Point"}
}