{
  "type": "Feature",
  "properties": {
    "iso:country":"NL",
    "sg:address":"Bakkerswg 21-1",
    "sg:city":"Voorthuizen",
    "sg:orig_category":"Kaas",
    "sg:phone":"+31 342 473 125",
    "sg:postcode":"3781 GN",
    "sg:province":"Gelderland",
    "wof:name":"Hardon, J",
    "wof:placetype":"venue"
},
  "geometry": {"coordinates":[5.6122407913,52.1843528748],"type":"Point"}
}