{
  "type": "Feature",
  "properties": {
    "addr:full":"Arendstraat 20 Oosterhout Nb Noord-Brabant 4901 JK",
    "addr:housenumber":"20",
    "addr:postcode":"4901 jk",
    "addr:street":"Arendstraat",
    "iso:country":"NL",
    "sg:address":"Arendstraat 20",
    "sg:city":"Oosterhout Nb",
    "sg:orig_category":"Juweliers",
    "sg:phone":"+31 162 460 129",
    "sg:postcode":"4901 JK",
    "sg:province":"Noord-Brabant",
    "wof:name":"Het Juweliershuis",
    "wof:placetype":"venue"
},
  "geometry": {"coordinates":[4.858134,51.643921],"type":"Point"}
}