{
  "type": "Feature",
  "properties": {
    "addr:full":"Nescioplnts 11 Almere NL. 1321 BH",
    "addr:housenumber":"11",
    "addr:postcode":"1321 bh",
    "addr:street":"Nescioplnts;Nl.",
    "iso:country":"NL",
    "sg:address":"Nescioplnts 11",
    "sg:city":"Almere",
    "sg:orig_category":"Fotoreportages",
    "sg:phone":"+31 36 546 9343",
    "sg:postcode":"1321 BH",
    "sg:province":"NL.",
    "wof:name":"Riemersma, Anita",
    "wof:placetype":"venue"
},
  "geometry": {"coordinates":[5.18257,52.35714],"type":"Point"}
}