{
  "type": "Feature",
  "properties": {
    "iso:country":"NL",
    "sg:address":"Craneveldstr 24",
    "sg:city":"Venlo",
    "sg:orig_category":"Onderhoudswerken",
    "sg:phone":"+31 6 18871545",
    "sg:postcode":"5914 SJ",
    "sg:province":"Limburg",
    "wof:name":"Beerkens",
    "wof:placetype":"venue"
},
  "geometry": {"coordinates":[6.175676,51.376148],"type":"Point"}
}