{
  "type": "Feature",
  "properties": {
    "iso:country":"NL",
    "sg:address":"Damstraat 40",
    "sg:city":"Amsterdam",
    "sg:classifiers":[
        {
            "category":"Fast Food",
            "type":"Food & Drink"
        }
    ],
    "sg:phone":"+31 20 624 0411",
    "sg:postcode":"1012 JM",
    "sg:province":"Noord-Holland",
    "sg:tags":[
        "afhaal",
        "restaurant"
    ],
    "wof:name":"Grill Toby",
    "wof:placetype":"venue"
},
  "geometry": {"coordinates":[4.8952732086,52.3718795776],"type":"Point"}
}