{
  "type": "Feature",
  "properties": {
    "addr:full":"Brandstr 2 Sittard Limburg 6131 CT",
    "addr:housenumber":"2",
    "addr:postcode":"6131 ct",
    "addr:street":"Brandstr",
    "iso:country":"NL",
    "sg:address":"Brandstr 2",
    "sg:city":"Sittard",
    "sg:orig_category":"Boeken En Tijdschriften",
    "sg:phone":"+31 46 451 0555",
    "sg:postcode":"6131 CT",
    "sg:province":"Limburg",
    "wof:name":"Plantageboekhandel Het Boekhuis",
    "wof:placetype":"venue"
},
  "geometry": {"coordinates":[5.866499,50.998417],"type":"Point"}
}