{
  "type": "Feature",
  "properties": {
    "addr:full":"Vliegveldweg 59 Rotterdam Zuid-Holland 3043 NT",
    "addr:housenumber":"59",
    "addr:postcode":"3043 nt",
    "addr:street":"Vliegveldweg",
    "iso:country":"NL",
    "sg:address":"Vliegveldweg 59",
    "sg:city":"Rotterdam",
    "sg:orig_category":"Kappers",
    "sg:phone":"+31 10 415 0095",
    "sg:postcode":"3043 NT",
    "sg:province":"Zuid-Holland",
    "wof:name":"Dames- En Herenkapsalon Hairport",
    "wof:placetype":"venue"
},
  "geometry": {"coordinates":[4.4256629944,51.9469642639],"type":"Point"}
}