{
  "type": "Feature",
  "properties": {
    "addr:full":"Pampusstraat 28 Rijsenhout North Holland 1435 LJ",
    "addr:housenumber":"28",
    "addr:postcode":"1435 lj",
    "addr:street":"Pampusstraat",
    "iso:country":"NL",
    "sg:address":"Pampusstraat 28",
    "sg:city":"Rijsenhout",
    "sg:orig_category":"Kinderopvang Behalve Thuis",
    "sg:phone":"+31 297 326 565",
    "sg:postcode":"1435 LJ",
    "sg:province":"North Holland",
    "wof:name":"Gremlins Kinderdagverblijf",
    "wof:placetype":"venue"
},
  "geometry": {"coordinates":[4.710025,52.262016],"type":"Point"}
}