{
  "type": "Feature",
  "properties": {
    "iso:country":"NL",
    "sg:address":"Wielstr 14",
    "sg:city":"Geldrop",
    "sg:orig_category":"Bedrijfsopleidingen",
    "sg:phone":"+31 40 293 0901",
    "sg:postcode":"5664 HP",
    "sg:province":"Noord-Brabant",
    "wof:name":"Maan, Studio",
    "wof:placetype":"venue"
},
  "geometry": {"coordinates":[5.56235,51.422401],"type":"Point"}
}