{
  "type": "Feature",
  "properties": {
    "iso:country":"NL",
    "sg:address":"Cremerstr 36",
    "sg:city":"Haarlem",
    "sg:orig_category":"Modelbouw",
    "sg:phone":"+31 23 535 9596",
    "sg:postcode":"2032 KP",
    "sg:province":"North Holland",
    "sg:website":"http://www.jetenspeedmodels.nl",
    "wof:name":"Jet & Speed",
    "wof:placetype":"venue"
},
  "geometry": {"coordinates":[4.656273,52.379547],"type":"Point"}
}