{
  "type": "Feature",
  "properties": {
    "addr:full":"Grasmeent 50 Almere Flevoland 1357 JE",
    "addr:housenumber":"50",
    "addr:postcode":"1357 je",
    "addr:street":"Grasmeent;Flevoland",
    "iso:country":"NL",
    "sg:address":"Grasmeent 50",
    "sg:city":"Almere",
    "sg:orig_category":"Natuurvoeding En Reformartikelen - Fabrieken En Groothandel",
    "sg:phone":"+31 36 538 6924",
    "sg:postcode":"1357 JE",
    "sg:province":"Flevoland",
    "wof:name":"Ken-Ran",
    "wof:placetype":"venue"
},
  "geometry": {"coordinates":[5.241725,52.334068],"type":"Point"}
}