{
  "type": "Feature",
  "properties": {
    "addr:full":"Dwarstocht 1 Zaandam North Holland 1507 CH",
    "addr:housenumber":"1",
    "addr:postcode":"1507",
    "addr:street":"Dwarstocht",
    "iso:country":"NL",
    "sg:address":"Dwarstocht 1",
    "sg:city":"Zaandam",
    "sg:orig_category":"Verhuur Gereedschapsmachines And Gereedschappen",
    "sg:phone":"+31 75 670 5306",
    "sg:postcode":"1507 CH",
    "sg:province":"North Holland",
    "wof:name":"Canet Verhuurbedrijf Bv",
    "wof:placetype":"venue"
},
  "geometry": {"coordinates":[4.810093,52.426949],"type":"Point"}
}