{
  "type": "Feature",
  "properties": {
    "iso:country":"NL",
    "sg:address":"Tilburgseweg 6",
    "sg:city":"Moergestel",
    "sg:orig_category":"Meubelreparatie And -Restauratie",
    "sg:phone":"+31 13 513 2345",
    "sg:postcode":"5066 BV",
    "sg:province":"North Brabant",
    "wof:name":"J.M.H. Smits & Zoon",
    "wof:placetype":"venue"
},
  "geometry": {"coordinates":[5.176022,51.547089],"type":"Point"}
}