{
  "type": "Feature",
  "properties": {
    "addr:full":"Eerste Zeine 94 Waalwijk Noord-Brabant 5144 AL",
    "addr:housenumber":"94",
    "addr:postcode":"5144 al",
    "addr:street":"Eerste Zeine",
    "iso:country":"NL",
    "sg:address":"Eerste Zeine 94",
    "sg:city":"Waalwijk",
    "sg:orig_category":"Loodgieterswerk, Verwarming And Sanitaire Installaties",
    "sg:phone":"+31 416 340 792",
    "sg:postcode":"5144 AL",
    "sg:province":"Noord-Brabant",
    "wof:name":"Louis Zeegers Installatiebedrijf Vof",
    "wof:placetype":"venue"
},
  "geometry": {"coordinates":[5.07109,51.683762],"type":"Point"}
}