{
  "type": "Feature",
  "properties": {
    "addr:full":"Van Utrechtweg 67 Krimpen A/D Ijssel Zuid-Holland 2921 LN",
    "addr:housenumber":"67;a / d",
    "addr:postcode":"2921 ln",
    "addr:street":"Van Utrechtweg",
    "iso:country":"NL",
    "sg:address":"Van Utrechtweg 67",
    "sg:city":"Krimpen A/D Ijssel",
    "sg:orig_category":"Kantoor- And Schoolbenodigdheden Gh",
    "sg:phone":"+31 180 550 085",
    "sg:postcode":"2921 LN",
    "sg:province":"Zuid-Holland",
    "wof:name":"Handelsonderneming N. Bouwen Bv",
    "wof:placetype":"venue"
},
  "geometry": {"coordinates":[4.5771799088,51.9085083008],"type":"Point"}
}