{
  "type": "Feature",
  "properties": {
    "addr:full":"Hazelaarstraat 24 Waalwijk North Brabant 5143 BH",
    "addr:housenumber":"24",
    "addr:postcode":"5143 bh",
    "addr:street":"Hazelaarstraat",
    "iso:country":"NL",
    "sg:address":"Hazelaarstraat 24",
    "sg:city":"Waalwijk",
    "sg:orig_category":"Bloemen And Planten",
    "sg:phone":"+31 416 650 756",
    "sg:postcode":"5143 BH",
    "sg:province":"North Brabant",
    "wof:name":"Van Bladel Hydro Cultuur",
    "wof:placetype":"venue"
},
  "geometry": {"coordinates":[5.088535,51.683987],"type":"Point"}
}