{
  "type": "Feature",
  "properties": {
    "addr:full":"Keizerswaard 20 Rotterdam Zuid-Holland 3078 AM",
    "addr:housenumber":"20",
    "addr:postcode":"3078",
    "addr:street":"Keizerswaard",
    "iso:country":"NL",
    "sg:address":"Keizerswaard 20",
    "sg:city":"Rotterdam",
    "sg:classifiers":[
        {
            "category":"Food & Beverages",
            "subcategory":"Fruits & Vegetables",
            "type":"Retail Goods"
        }
    ],
    "sg:phone":"+31 10 479 1698",
    "sg:postcode":"3078 AM",
    "sg:province":"Zuid-Holland",
    "sg:tags":[
        "groenten"
    ],
    "wof:name":"De Goudreinet",
    "wof:placetype":"venue"
},
  "geometry": {"coordinates":[4.547104,51.886349],"type":"Point"}
}