{
  "type": "Feature",
  "properties": {
    "iso:country":"NL",
    "sg:address":"Zonnepln 12",
    "sg:city":"Bergen Op Zoom",
    "sg:orig_category":"Bloemen En Planten",
    "sg:phone":"+31 164 263 428",
    "sg:postcode":"4624 BC",
    "sg:province":"North Brabant",
    "wof:name":"Berry",
    "wof:placetype":"venue"
},
  "geometry": {"coordinates":[4.308577,51.485607],"type":"Point"}
}