{
  "type": "Feature",
  "properties": {
    "addr:full":"Kl Nullandstr 27A Kerkrade Limburg 6462 TA",
    "addr:housenumber":"27a",
    "addr:postcode":"6462 ta",
    "iso:country":"NL",
    "sg:address":"Kl Nullandstr 27A",
    "sg:city":"Kerkrade",
    "sg:orig_category":"Kunstgebitten",
    "sg:phone":"+31 45 545 7633",
    "sg:postcode":"6462 TA",
    "sg:province":"Limburg",
    "wof:name":"Rep-Dent Kerkrade, Tandprothesetechniek",
    "wof:placetype":"venue"
},
  "geometry": {"coordinates":[6.060967,50.854244],"type":"Point"}
}