{
  "type": "Feature",
  "properties": {
    "addr:full":"Postbus 1698 Leeuwarden Friesland 8901 BZ",
    "addr:housenumber":"1698",
    "addr:postcode":"8901 bz",
    "addr:street":"Postbus",
    "iso:country":"NL",
    "sg:address":"Postbus 1698",
    "sg:city":"Leeuwarden",
    "sg:orig_category":"Verenigingen En Stichtingen",
    "sg:phone":"+31 58 234 3131",
    "sg:postcode":"8901 BZ",
    "sg:province":"Friesland",
    "wof:name":"Bouw-Kunst, Sticht",
    "wof:placetype":"venue"
},
  "geometry": {"coordinates":[5.79143,53.203049],"type":"Point"}
}