{
  "type": "Feature",
  "properties": {
    "iso:country":"NL",
    "sg:address":"Axelsestraat 3",
    "sg:city":"Terneuzen",
    "sg:classifiers":[
        {
            "category":"Retail",
            "subcategory":"Photofinishing",
            "type":"Services"
        }
    ],
    "sg:phone":"+31 115 696 973",
    "sg:postcode":"4537 AA",
    "sg:province":"Zeeland",
    "sg:tags":[
        "foto",
        "film"
    ],
    "wof:name":"Croxdale Ltd H/O Studio Dieleman",
    "wof:placetype":"venue"
},
  "geometry": {"coordinates":[3.829276,51.334251],"type":"Point"}
}