{
  "type": "Feature",
  "properties": {
    "addr:full":"Fokke Bleekerstraat 8 Bussum Noord-Holland 1403 RZ",
    "addr:housenumber":"8",
    "addr:postcode":"1403 rz",
    "addr:street":"Fokke Bleekerstraat",
    "iso:country":"NL",
    "sg:address":"Fokke Bleekerstraat 8",
    "sg:city":"Bussum",
    "sg:orig_category":"Vertaal- And Tolkenbureaus",
    "sg:phone":"+31 35 693 5377",
    "sg:postcode":"1403 RZ",
    "sg:province":"Noord-Holland",
    "wof:name":"Luteijn Vertaalservice",
    "wof:placetype":"venue"
},
  "geometry": {"coordinates":[5.170271,52.266163],"type":"Point"}
}