{
  "type": "Feature",
  "properties": {
    "addr:full":"Bareveldstraat 27 Wildervank Groningen 9648 GV",
    "addr:housenumber":"27",
    "addr:postcode":"9648 gv",
    "addr:street":"Bareveldstraat",
    "iso:country":"NL",
    "sg:address":"Bareveldstraat 27",
    "sg:city":"Wildervank",
    "sg:orig_category":"Koeriersdiensten",
    "sg:phone":"+31 598 627 593",
    "sg:postcode":"9648 GV",
    "sg:province":"Groningen",
    "wof:name":"Jsl Transport",
    "wof:placetype":"venue"
},
  "geometry": {"coordinates":[6.84776,53.054707],"type":"Point"}
}