{
  "type": "Feature",
  "properties": {
    "addr:full":"Orlyplein 107 Amsterdam Noord-Holland 1043 DT",
    "addr:housenumber":"107",
    "addr:postcode":"1043 dt",
    "addr:street":"Orlyplein",
    "iso:country":"NL",
    "sg:address":"Orlyplein 107",
    "sg:city":"Amsterdam",
    "sg:orig_category":"Banken And Kredietinstellingen",
    "sg:phone":"+31 20 688 1213",
    "sg:postcode":"1043 DT",
    "sg:province":"Noord-Holland",
    "wof:name":"Gwk Banking & Tourist Services",
    "wof:placetype":"venue"
},
  "geometry": {"coordinates":[4.837185,52.389309],"type":"Point"}
}