{
  "type": "Feature",
  "properties": {
    "iso:country":"NL",
    "sg:address":"Plein 1953 No.54",
    "sg:city":"Rotterdam",
    "sg:orig_category":"Boekhandels",
    "sg:phone":"+31 10 480 5874",
    "sg:postcode":"3086 EE",
    "sg:province":"Zuid-Holland",
    "wof:name":"J C Van Der Wel",
    "wof:placetype":"venue"
},
  "geometry": {"coordinates":[4.469204,51.874344],"type":"Point"}
}