{
  "type": "Feature",
  "properties": {
    "addr:full":"Ryksstrwg 8 Den Hoorn Zh Zuid-Holland 2635 AC",
    "addr:housenumber":"8",
    "addr:postcode":"2635 ac",
    "addr:street":"Ryksstrwg",
    "iso:country":"NL",
    "sg:address":"Ryksstrwg 8",
    "sg:city":"Den Hoorn Zh",
    "sg:classifiers":[
        {
            "category":"Retail",
            "subcategory":"Auto Repair",
            "type":"Services"
        }
    ],
    "sg:phone":"+31 15 257 2643",
    "sg:postcode":"2635 AC",
    "sg:province":"Zuid-Holland",
    "sg:tags":[
        "garage"
    ],
    "wof:name":"Millenaar, H",
    "wof:placetype":"venue"
},
  "geometry": {"coordinates":[4.331055,51.99958],"type":"Point"}
}