{
  "type": "Feature",
  "properties": {
    "addr:full":"Allingawier 29 Grouw Friesland 9001 LP",
    "addr:housenumber":"29",
    "addr:postcode":"9001 lp",
    "addr:street":"Allingawier",
    "iso:country":"NL",
    "sg:address":"Allingawier 29",
    "sg:city":"Grouw",
    "sg:classifiers":[
        {
            "category":"Personal",
            "subcategory":"Nail Salon",
            "type":"Services"
        }
    ],
    "sg:phone":"+31 566 622 033",
    "sg:postcode":"9001 LP",
    "sg:province":"Friesland",
    "sg:tags":[
        "pedicure"
    ],
    "wof:name":"Laskewitz, Jante",
    "wof:placetype":"venue"
},
  "geometry": {"coordinates":[5.829963,53.090137],"type":"Point"}
}