{
  "type": "Feature",
  "properties": {
    "iso:country":"NL",
    "sg:address":"Thomsonstr 88",
    "sg:city":"Badhoevedorp",
    "sg:orig_category":"Organisatiebureaus",
    "sg:phone":"+31 20 659 7576",
    "sg:postcode":"1171 ZG",
    "sg:province":"Noord-Holland",
    "wof:name":"Ricardo Aziz",
    "wof:placetype":"venue"
},
  "geometry": {"coordinates":[4.7831630707,52.3441963196],"type":"Point"}
}