{
  "type": "Feature",
  "properties": {
    "addr:full":"Truffautstr 17 Almere Flevoland 1325 PR",
    "addr:housenumber":"17",
    "addr:postcode":"1325 pr",
    "addr:street":"Truffautstr;Flevoland",
    "iso:country":"NL",
    "sg:address":"Truffautstr 17",
    "sg:city":"Almere",
    "sg:orig_category":"Webdesign Bureaus",
    "sg:phone":"+31 36 537 3146",
    "sg:postcode":"1325 PR",
    "sg:province":"Flevoland",
    "sg:website":"http://www.tjeenkwillink.nl",
    "wof:name":"Tjeenk Willink",
    "wof:placetype":"venue"
},
  "geometry": {"coordinates":[5.2436718941,52.363067627],"type":"Point"}
}