{
  "type": "Feature",
  "properties": {
    "addr:full":"Kampwg 11 Doorn Utrecht 3941 HC",
    "addr:housenumber":"11",
    "addr:postcode":"3941 hc",
    "addr:street":"Kampwg",
    "iso:country":"NL",
    "sg:address":"Kampwg 11",
    "sg:city":"Doorn",
    "sg:orig_category":"Verzekeringen - Verzekeringskantoren",
    "sg:phone":"+31 343 413 020",
    "sg:postcode":"3941 HC",
    "sg:province":"Utrecht",
    "sg:website":"http://www.onstein.nl",
    "wof:name":"Onstein & Zoon Bv",
    "wof:placetype":"venue"
},
  "geometry": {"coordinates":[5.344466,52.035622],"type":"Point"}
}