{
  "type": "Feature",
  "properties": {
    "addr:full":"Steenpad 11 Willemstad Nb Noord-Brabant 4797 SG",
    "addr:housenumber":"11",
    "addr:postcode":"4797 sg",
    "addr:street":"Steenpad",
    "iso:country":"NL",
    "sg:address":"Steenpad 11",
    "sg:city":"Willemstad Nb",
    "sg:orig_category":"Werving And Selectie Van Tijdelijk Personeel And Uitzendkantoren",
    "sg:phone":"+31 168 477 177",
    "sg:postcode":"4797 SG",
    "sg:province":"Noord-Brabant",
    "wof:name":"Artifex Interim Bv",
    "wof:placetype":"venue"
},
  "geometry": {"coordinates":[4.4341731071,51.6761474609],"type":"Point"}
}