{
  "type": "Feature",
  "properties": {
    "iso:country":"NL",
    "sg:address":"Keizersgracht 635",
    "sg:city":"Amsterdam",
    "sg:orig_category":"Verzekerings- Maatschappijen",
    "sg:phone":"+31 20 530 4370",
    "sg:postcode":"1017 DS",
    "sg:province":"North Holland",
    "wof:name":"Gerling Namur Nv",
    "wof:placetype":"venue"
},
  "geometry": {"coordinates":[4.894306,52.363899],"type":"Point"}
}