{
  "type": "Feature",
  "properties": {
    "addr:full":"Basiswg 57 Amsterdam North Holland 1043 AN",
    "addr:housenumber":"57",
    "addr:postcode":"1043 an",
    "addr:street":"Basiswg",
    "iso:country":"NL",
    "sg:address":"Basiswg 57",
    "sg:city":"Amsterdam",
    "sg:orig_category":"Bedrijfskleding",
    "sg:phone":"+31 20 448 7333",
    "sg:postcode":"1043 AN",
    "sg:province":"North Holland",
    "wof:name":"Sga Bv",
    "wof:placetype":"venue"
},
  "geometry": {"coordinates":[4.826858,52.391171],"type":"Point"}
}