{
  "type": "Feature",
  "properties": {
    "addr:full":"Schietwilgsngl 2 Almere Flevoland 1326 EN",
    "addr:housenumber":"2",
    "addr:postcode":"1326 en",
    "addr:street":"Schietwilgsngl;Flevoland",
    "iso:country":"NL",
    "sg:address":"Schietwilgsngl 2",
    "sg:city":"Almere",
    "sg:orig_category":"Bejaarden - Verzorgingstehuizen",
    "sg:phone":"+31 36 535 7900",
    "sg:postcode":"1326 EN",
    "sg:province":"Flevoland",
    "wof:name":"Polderburen",
    "wof:placetype":"venue"
},
  "geometry": {"coordinates":[5.246232,52.372509],"type":"Point"}
}