{
  "type": "Feature",
  "properties": {
    "addr:full":"Dorpsstraat 224 Sint Willebrord North Brabant 4711 EN",
    "addr:housenumber":"224",
    "addr:postcode":"4711 en",
    "addr:street":"Dorpsstraat",
    "iso:country":"NL",
    "sg:address":"Dorpsstraat 224",
    "sg:city":"Sint Willebrord",
    "sg:classifiers":[
        {
            "category":"Fast Food",
            "type":"Food & Drink"
        }
    ],
    "sg:phone":"+31 165 387 285",
    "sg:postcode":"4711 EN",
    "sg:province":"North Brabant",
    "sg:tags":[
        "afhaal",
        "restaurant"
    ],
    "wof:name":"Shoarma De Pyramide",
    "wof:placetype":"venue"
},
  "geometry": {"coordinates":[4.590779,51.556194],"type":"Point"}
}