{
  "type": "Feature",
  "properties": {
    "addr:full":"Langstr 12 Geldrop Noord-Brabant 5664 GG",
    "addr:housenumber":"12",
    "addr:postcode":"5664 gg",
    "addr:street":"Langstr",
    "iso:country":"NL",
    "sg:address":"Langstr 12",
    "sg:city":"Geldrop",
    "sg:orig_category":"Handenarbeid",
    "sg:phone":"+31 40 286 3492",
    "sg:postcode":"5664 GG",
    "sg:province":"Noord-Brabant",
    "wof:name":"Winkeltje, 'T",
    "wof:placetype":"venue"
},
  "geometry": {"coordinates":[5.560361,51.421581],"type":"Point"}
}