{
  "type": "Feature",
  "properties": {
    "addr:full":"Korenbloemstr 2 Nieuwegein Utrecht 3434 EB",
    "addr:housenumber":"2",
    "addr:postcode":"3434 eb",
    "addr:street":"Korenbloemstr",
    "iso:country":"NL",
    "sg:address":"Korenbloemstr 2",
    "sg:city":"Nieuwegein",
    "sg:orig_category":"Bedrijfsopleidingen",
    "sg:phone":"+31 30 608 1805",
    "sg:postcode":"3434 EB",
    "sg:province":"Utrecht",
    "wof:name":"Sercon En Snijder Bv",
    "wof:placetype":"venue"
},
  "geometry": {"coordinates":[5.08668,52.008919],"type":"Point"}
}