{
  "type": "Feature",
  "properties": {
    "addr:full":"Kloosterpoort 1 Grootebroek North Holland 1613 EV",
    "addr:housenumber":"1",
    "addr:postcode":"1613 ev",
    "addr:street":"Kloosterpoort",
    "iso:country":"NL",
    "sg:address":"Kloosterpoort 1",
    "sg:city":"Grootebroek",
    "sg:orig_category":"Verloskundigen",
    "sg:phone":"+31 6 52066192",
    "sg:postcode":"1613 EV",
    "sg:province":"North Holland",
    "wof:name":"Klink, De",
    "wof:placetype":"venue"
},
  "geometry": {"coordinates":[5.223834,52.689636],"type":"Point"}
}