{
  "type": "Feature",
  "properties": {
    "addr:full":"Bisschopswetering 4 S Heerenbroek Overijssel 8275 AN",
    "addr:housenumber":"4",
    "addr:postcode":"8275 an",
    "addr:street":"Bisschopswetering;S Heerenbroek Overijssel",
    "iso:country":"NL",
    "sg:address":"Bisschopswetering 4",
    "sg:city":"S Heerenbroek",
    "sg:orig_category":"Kappers",
    "sg:phone":"+31 6 22329799",
    "sg:postcode":"8275 AN",
    "sg:province":"Overijssel",
    "wof:name":"Ilona Thuiskapster",
    "wof:placetype":"venue"
},
  "geometry": {"coordinates":[6.014480114,52.5357131958],"type":"Point"}
}