{
  "type": "Feature",
  "properties": {
    "addr:full":"Roggestr 7 Doesburg Gelderland 6981 BJ",
    "addr:housenumber":"7",
    "addr:postcode":"6981 bj",
    "addr:street":"Roggestr;Gelderland",
    "iso:country":"NL",
    "sg:address":"Roggestr 7",
    "sg:city":"Doesburg",
    "sg:orig_category":"Verenigingsgebouwen",
    "sg:phone":"+31 313 472 479",
    "sg:postcode":"6981 BJ",
    "sg:province":"Gelderland",
    "wof:name":"Maartenshuis, 'T",
    "wof:placetype":"venue"
},
  "geometry": {"coordinates":[6.133709,52.014767],"type":"Point"}
}