{
  "type": "Feature",
  "properties": {
    "addr:full":"Middenwg 15 Dirkshorn North Holland 1746 EA",
    "addr:housenumber":"15",
    "addr:postcode":"1746 ea",
    "addr:street":"Middenwg",
    "iso:country":"NL",
    "sg:address":"Middenwg 15",
    "sg:city":"Dirkshorn",
    "sg:orig_category":"Bloembollen - Groothandel",
    "sg:phone":"+31 224 551 309",
    "sg:postcode":"1746 EA",
    "sg:province":"North Holland",
    "wof:name":"Hoogland Bv",
    "wof:placetype":"venue"
},
  "geometry": {"coordinates":[4.790482,52.752773],"type":"Point"}
}