{
  "type": "Feature",
  "properties": {
    "addr:full":"Vanekerstraat 278 Enschede Overijssel 7523 HT",
    "addr:housenumber":"278",
    "addr:postcode":"7523 ht",
    "addr:street":"Vanekerstraat",
    "iso:country":"NL",
    "sg:address":"Vanekerstraat 278",
    "sg:city":"Enschede",
    "sg:orig_category":"Airconditioning And Ventilatie",
    "sg:phone":"+31 53 433 5129",
    "sg:postcode":"7523 HT",
    "sg:province":"Overijssel",
    "wof:name":"Henken Installatie Techniek Bv",
    "wof:placetype":"venue"
},
  "geometry": {"coordinates":[6.890719,52.242172],"type":"Point"}
}