{
  "type": "Feature",
  "properties": {
    "addr:full":"Griend 123 Diemen North Holland 1112 LA",
    "addr:housenumber":"123",
    "addr:postcode":"1112 la",
    "addr:street":"Griend",
    "iso:country":"NL",
    "sg:address":"Griend 123",
    "sg:city":"Diemen",
    "sg:orig_category":"Adviesbureaus Bouwkunde",
    "sg:phone":"+31 20 699 6503",
    "sg:postcode":"1112 LA",
    "sg:province":"North Holland",
    "sg:website":"http://www.adviesb2000.nl",
    "wof:name":"B2000",
    "wof:placetype":"venue"
},
  "geometry": {"coordinates":[4.945829,52.330219],"type":"Point"}
}