{
  "type": "Feature",
  "properties": {
    "addr:full":"Industriewg 46A Mydrecht Utrecht 3641 RM",
    "addr:housenumber":"46a;3641",
    "addr:street":"Industriewg;Rm",
    "iso:country":"NL",
    "sg:address":"Industriewg 46A",
    "sg:city":"Mydrecht",
    "sg:orig_category":"Fotoapparatuur En -Artikelen - Groothandel",
    "sg:phone":"+31 297 283 873",
    "sg:postcode":"3641 RM",
    "sg:province":"Utrecht",
    "wof:name":"Fodeco Ned Bv",
    "wof:placetype":"venue"
},
  "geometry": {"coordinates":[4.877313,52.206528],"type":"Point"}
}