{
  "type": "Feature",
  "properties": {
    "addr:full":"Bar G A Tindalstr 236 Amsterdam North Holland 1019 TZ",
    "addr:housenumber":"236",
    "addr:postcode":"1019 tz",
    "addr:street":"G",
    "iso:country":"NL",
    "sg:address":"Bar G A Tindalstr 236",
    "sg:city":"Amsterdam",
    "sg:orig_category":"Marktonderzoekbureaus",
    "sg:phone":"+31 20 419 0171",
    "sg:postcode":"1019 TZ",
    "sg:province":"North Holland",
    "sg:website":"http://www.alrightselect.nl",
    "wof:name":"Allround Select",
    "wof:placetype":"venue"
},
  "geometry": {"coordinates":[4.941392,52.373016],"type":"Point"}
}