{
  "type": "Feature",
  "properties": {
    "addr:full":"Onder De Wien 2 Haelen Limburg 6081 GC",
    "addr:housenumber":"2",
    "addr:postcode":"6081 gc",
    "addr:street":"Onder De Wien",
    "iso:country":"NL",
    "sg:address":"Onder De Wien 2",
    "sg:city":"Haelen",
    "sg:orig_category":"Algemene Werktuigbouw",
    "sg:phone":"+31 475 591 963",
    "sg:postcode":"6081 GC",
    "sg:province":"Limburg",
    "wof:name":"Van Den Beucken Lasbedrijf",
    "wof:placetype":"venue"
},
  "geometry": {"coordinates":[5.958405,51.236549],"type":"Point"}
}