{
  "type": "Feature",
  "properties": {
    "addr:full":"Kleinemeersterstr 78 Sappemeer Groningen 9611 JG",
    "addr:housenumber":"78",
    "addr:postcode":"9611 jg",
    "addr:street":"Kleinemeersterstr",
    "iso:country":"NL",
    "sg:address":"Kleinemeersterstr 78",
    "sg:city":"Sappemeer",
    "sg:orig_category":"Webdesign Bureaus",
    "sg:phone":"+31 598 399 681",
    "sg:postcode":"9611 JG",
    "sg:province":"Groningen",
    "sg:website":"http://www.bnbweb.nl",
    "wof:name":"Bnb",
    "wof:placetype":"venue"
},
  "geometry": {"coordinates":[6.7863149643,53.15858078],"type":"Point"}
}