{
  "type": "Feature",
  "properties": {
    "iso:country":"NL",
    "sg:address":"Hoendiep 97",
    "sg:city":"Groningen",
    "sg:orig_category":"Babyartikelen",
    "sg:phone":"+31 50 311 1363",
    "sg:postcode":"9718 TE",
    "sg:province":"Groningen",
    "sg:website":"http://www.beterbaby.nl",
    "wof:name":"Beter Baby",
    "wof:placetype":"venue"
},
  "geometry": {"coordinates":[6.543285,53.213638],"type":"Point"}
}