{
  "type": "Feature",
  "properties": {
    "addr:full":"Postbus 7001 Zoetermeer South Holland 2701 AA",
    "addr:housenumber":"7001",
    "addr:postcode":"2701 aa",
    "addr:street":"Postbus",
    "iso:country":"NL",
    "sg:address":"Postbus 7001",
    "sg:city":"Zoetermeer",
    "sg:orig_category":"Onderzoekbureaus",
    "sg:phone":"+31 79 341 4731",
    "sg:postcode":"2701 AA",
    "sg:province":"South Holland",
    "sg:website":"http://www.ioo.nl",
    "wof:name":"Ioo Bv",
    "wof:placetype":"venue"
},
  "geometry": {"coordinates":[4.49332,52.060501],"type":"Point"}
}