{
  "type": "Feature",
  "properties": {
    "addr:full":"Emmastr 2 Landgraaf Limburg 6373 HM",
    "addr:housenumber":"2",
    "addr:postcode":"6373 hm",
    "addr:street":"Emmastr",
    "iso:country":"NL",
    "sg:address":"Emmastr 2",
    "sg:city":"Landgraaf",
    "sg:orig_category":"Zalenverhuur",
    "sg:phone":"+31 45 531 2320",
    "sg:postcode":"6373 HM",
    "sg:province":"Limburg",
    "wof:name":"Trim Bourgogne",
    "wof:placetype":"venue"
},
  "geometry": {"coordinates":[6.032871,50.909904],"type":"Point"}
}