{
  "type": "Feature",
  "properties": {
    "addr:full":"Groen Blauwln 107 Zoetermeer South Holland 2718 GH",
    "addr:housenumber":"107",
    "addr:postcode":"2718 gh",
    "iso:country":"NL",
    "sg:address":"Groen Blauwln 107",
    "sg:city":"Zoetermeer",
    "sg:orig_category":"Bloemen En Planten",
    "sg:phone":"+31 15 256 2565",
    "sg:postcode":"2718 GH",
    "sg:province":"South Holland",
    "wof:name":"Robert",
    "wof:placetype":"venue"
},
  "geometry": {"coordinates":[4.494829,52.039772],"type":"Point"}
}