{
  "type": "Feature",
  "properties": {
    "addr:full":"Schepperijlaan 28 Winsum Gn Groningen 9951 BK",
    "addr:housenumber":"28",
    "addr:postcode":"gn;9951 bk",
    "addr:street":"Schepperijlaan",
    "iso:country":"NL",
    "sg:address":"Schepperijlaan 28",
    "sg:city":"Winsum Gn",
    "sg:orig_category":"Goederenvervoer Over De Weg",
    "sg:phone":"+31 595 441 805",
    "sg:postcode":"9951 BK",
    "sg:province":"Groningen",
    "wof:name":"Transportbedrijf L Noorman Vof",
    "wof:placetype":"venue"
},
  "geometry": {"coordinates":[6.52138,53.324783],"type":"Point"}
}