{
  "type": "Feature",
  "properties": {
    "iso:country":"NL",
    "sg:address":"Noord Ijsselkade 6",
    "sg:city":"Oudewater",
    "sg:orig_category":"Artiesten",
    "sg:phone":"+31 348 561 175",
    "sg:postcode":"3421 BD",
    "sg:province":"Utrecht",
    "wof:name":"Tulip Graphics",
    "wof:placetype":"venue"
},
  "geometry": {"coordinates":[4.869379,52.022816],"type":"Point"}
}