{
  "type": "Feature",
  "properties": {
    "iso:country":"NL",
    "sg:address":"Volkerakstraat 39",
    "sg:city":"'S Gravenhage",
    "sg:orig_category":"Autokeuringen",
    "sg:phone":"+31 70 383 9346",
    "sg:postcode":"2595 VD",
    "sg:province":"Zuid-Holland",
    "wof:name":"Garage J A Embregts",
    "wof:placetype":"venue"
},
  "geometry": {"coordinates":[4.333222,52.077168],"type":"Point"}
}