{
  "type": "Feature",
  "properties": {
    "iso:country":"NL",
    "sg:address":"Zilverlaan 30",
    "sg:city":"Groningen",
    "sg:orig_category":"Boekhouders",
    "sg:phone":"+31 50 577 6363",
    "sg:postcode":"9743 RK",
    "sg:province":"Groningen",
    "wof:name":"Administratiekantoor G Zuidema",
    "wof:placetype":"venue"
},
  "geometry": {"coordinates":[6.53258,53.220535],"type":"Point"}
}