{
  "type": "Feature",
  "properties": {
    "addr:full":"Formerum 81 Terschelling Formerum Friesland 8894 KC",
    "addr:housenumber":"81",
    "addr:postcode":"8894 kc",
    "addr:street":"Formerum",
    "iso:country":"NL",
    "sg:address":"Formerum 81",
    "sg:city":"Terschelling Formerum",
    "sg:orig_category":"Kampeerterreinen",
    "sg:phone":"+31 562 448 461",
    "sg:postcode":"8894 KC",
    "sg:province":"Friesland",
    "wof:name":"De Jonge Jan",
    "wof:placetype":"venue"
},
  "geometry": {"coordinates":[5.3137168884,53.39037323],"type":"Point"}
}