{
  "type": "Feature",
  "properties": {
    "addr:full":"Buitentocht 34 Leiderdorp South Holland 2353 VL",
    "addr:housenumber":"34",
    "addr:postcode":"2353 vl",
    "addr:street":"Buitentocht",
    "iso:country":"NL",
    "sg:address":"Buitentocht 34",
    "sg:city":"Leiderdorp",
    "sg:orig_category":"Loodgieterswerk, Verwarming And Sanitaire Installaties",
    "sg:phone":"+31 71 541 7418",
    "sg:postcode":"2353 VL",
    "sg:province":"South Holland",
    "wof:name":"J.J.M. Van Steenbergen",
    "wof:placetype":"venue"
},
  "geometry": {"coordinates":[4.529608,52.17062],"type":"Point"}
}