{
  "type": "Feature",
  "properties": {
    "addr:full":"Zuidstr 105 Westkapelle Zeeland 4361 AH",
    "addr:housenumber":"105",
    "addr:postcode":"4361 ah",
    "iso:country":"NL",
    "sg:address":"Zuidstr 105",
    "sg:city":"Westkapelle",
    "sg:classifiers":[
        {
            "category":"Travel",
            "subcategory":"Hotels & Motels",
            "type":"Entertainment"
        }
    ],
    "sg:phone":"+31 118 571 331",
    "sg:postcode":"4361 AH",
    "sg:province":"Zeeland",
    "wof:name":"Noordzeegalm",
    "wof:placetype":"venue"
},
  "geometry": {"coordinates":[3.439188,51.527325],"type":"Point"}
}