{
  "type": "Feature",
  "properties": {
    "addr:full":"Den Heuvel 112A Velp Gld Gelderland 6881 VH",
    "addr:housenumber":"112a",
    "addr:postcode":"6881 vh",
    "addr:street":"Den Heuvel;Gld Gelderland",
    "iso:country":"NL",
    "sg:address":"Den Heuvel 112A",
    "sg:city":"Velp Gld",
    "sg:classifiers":[
        {
            "category":"Real Estate",
            "subcategory":"Real Estate Operator",
            "type":"Services"
        }
    ],
    "sg:phone":"+31 26 362 1052",
    "sg:postcode":"6881 VH",
    "sg:province":"Gelderland",
    "sg:tags":[
        "appartementen",
        "en",
        "flat"
    ],
    "wof:name":"Heuvel, Den",
    "wof:placetype":"venue"
},
  "geometry": {"coordinates":[5.973882,51.994617],"type":"Point"}
}