{
  "type": "Feature",
  "properties": {
    "iso:country":"NL",
    "sg:address":"Brahmsstr 11",
    "sg:city":"Veenendaal",
    "sg:orig_category":"Verbouwingen",
    "sg:phone":"+31 318 610 640",
    "sg:postcode":"3906 BB",
    "sg:province":"Utrecht",
    "wof:name":"Dijkhuizen, G Van",
    "wof:placetype":"venue"
},
  "geometry": {"coordinates":[5.534867,52.034946],"type":"Point"}
}