{
  "type": "Feature",
  "properties": {
    "addr:full":"Gr Willemln 21 Vogelenzang North Holland 2114 DA",
    "addr:housenumber":"21",
    "addr:postcode":"2114 da",
    "addr:street":"Vogelenzang North",
    "iso:country":"NL",
    "sg:address":"Gr Willemln 21",
    "sg:city":"Vogelenzang",
    "sg:orig_category":"Verkoperen En Verbronzen",
    "sg:phone":"+31 6 55111110",
    "sg:postcode":"2114 DA",
    "sg:province":"North Holland",
    "wof:name":"Artisan Metals",
    "wof:placetype":"venue"
},
  "geometry": {"coordinates":[4.579401,52.319515],"type":"Point"}
}