{
  "type": "Feature",
  "properties": {
    "addr:full":"Levantkd 48 Amsterdam North Holland 1019 BG",
    "addr:housenumber":"48",
    "addr:postcode":"1019",
    "addr:street":"Levantkd",
    "iso:country":"NL",
    "sg:address":"Levantkd 48",
    "sg:city":"Amsterdam",
    "sg:orig_category":"Marktonderzoekbureaus",
    "sg:phone":"+31 20 419 7123",
    "sg:postcode":"1019 BG",
    "sg:province":"North Holland",
    "sg:website":"http://www.qrius.nl",
    "wof:name":"Qrius Bv",
    "wof:placetype":"venue"
},
  "geometry": {"coordinates":[4.939742,52.376163],"type":"Point"}
}