{
  "type": "Feature",
  "properties": {
    "iso:country":"NL",
    "sg:address":"Veldwg 21",
    "sg:city":"Rykevoort",
    "sg:classifiers":[
        {
            "category":"Retail",
            "subcategory":"Auto Repair",
            "type":"Services"
        }
    ],
    "sg:phone":"+31 485 371 744",
    "sg:postcode":"5447 BH",
    "sg:province":"Noord-Brabant",
    "sg:tags":[
        "garage"
    ],
    "sg:website":"http://www.garagehendriks.nl",
    "wof:name":"Hendriks",
    "wof:placetype":"venue"
},
  "geometry": {"coordinates":[5.89291,51.658749],"type":"Point"}
}