{
  "type": "Feature",
  "properties": {
    "addr:full":"Kortenaerstraat 1 Eindhoven Noord-Brabant 5612 GR",
    "addr:housenumber":"1",
    "addr:postcode":"5612",
    "addr:street":"Kortenaerstraat",
    "iso:country":"NL",
    "sg:address":"Kortenaerstraat 1",
    "sg:city":"Eindhoven",
    "sg:orig_category":"Visspeciaalzaken",
    "sg:phone":"+31 40 245 7931",
    "sg:postcode":"5612 GR",
    "sg:province":"Noord-Brabant",
    "wof:name":"Vof Vishandel Van Bakel",
    "wof:placetype":"venue"
},
  "geometry": {"coordinates":[5.469848,51.451733],"type":"Point"}
}