{
  "type": "Feature",
  "properties": {
    "iso:country":"NL",
    "sg:address":"Hengelder 22",
    "sg:city":"Zevenaar",
    "sg:orig_category":"Luchtvaartelektronica",
    "sg:phone":"+31 316 592 100",
    "sg:postcode":"6902 PA",
    "sg:province":"Gelderland",
    "sg:website":"http://www.schreiner-comp.com",
    "wof:name":"Schreiner",
    "wof:placetype":"venue"
},
  "geometry": {"coordinates":[6.095576,51.926552],"type":"Point"}
}