{
  "type": "Feature",
  "properties": {
    "addr:full":"Rivierensngl 326 Helmond Noord-Brabant 5704 KJ",
    "addr:housenumber":"326",
    "addr:postcode":"5704 kj",
    "iso:country":"NL",
    "sg:address":"Rivierensngl 326",
    "sg:city":"Helmond",
    "sg:orig_category":"Machineonderhoud En -Reparatie",
    "sg:phone":"+31 492 518 326",
    "sg:postcode":"5704 KJ",
    "sg:province":"Noord-Brabant",
    "wof:name":"Verberne Tech Dienstverlening",
    "wof:placetype":"venue"
},
  "geometry": {"coordinates":[5.69918,51.457249],"type":"Point"}
}