{
  "type": "Feature",
  "properties": {
    "addr:full":"Pluisheuvel 19 Best Noord-Brabant 5685 BK",
    "addr:housenumber":"19",
    "addr:postcode":"5685 bk",
    "addr:street":"Pluisheuvel",
    "iso:country":"NL",
    "sg:address":"Pluisheuvel 19",
    "sg:city":"Best",
    "sg:orig_category":"Verzekeringen",
    "sg:phone":"+31 499 311 292",
    "sg:postcode":"5685 BK",
    "sg:province":"Noord-Brabant",
    "wof:name":"C. Manders",
    "wof:placetype":"venue"
},
  "geometry": {"coordinates":[-101.618134,31.224251],"type":"Point"}
}