{
  "type": "Feature",
  "properties": {
    "addr:full":"L Delft 25 Middelburg Zeeland 4331 AK",
    "addr:housenumber":"25",
    "addr:postcode":"4331 ak",
    "addr:street":"L Delft",
    "iso:country":"NL",
    "sg:address":"L Delft 25",
    "sg:city":"Middelburg",
    "sg:orig_category":"Schoenen",
    "sg:phone":"+31 118 650 275",
    "sg:postcode":"4331 AK",
    "sg:province":"Zeeland",
    "wof:name":"Manfield",
    "wof:placetype":"venue"
},
  "geometry": {"coordinates":[3.613699,51.498352],"type":"Point"}
}