{
  "type": "Feature",
  "properties": {
    "iso:country":"NL",
    "sg:address":"W Royaardsstr 68",
    "sg:city":"Ryswyk Zh",
    "sg:classifiers":[
        {
            "category":"Personal",
            "subcategory":"Nail Salon",
            "type":"Services"
        }
    ],
    "sg:phone":"+31 70 394 2063",
    "sg:postcode":"2284 JL",
    "sg:province":"South Holland",
    "sg:tags":[
        "pedicure"
    ],
    "wof:name":"Willigen, F M Van",
    "wof:placetype":"venue"
},
  "geometry": {"coordinates":[4.31319,52.041302],"type":"Point"}
}