{
  "type": "Feature",
  "properties": {
    "addr:full":"Bellestein 49 Ede Gld Gelderland 6714 DP",
    "addr:housenumber":"49",
    "addr:postcode":"6714 dp",
    "addr:street":"Bellestein;Gld Gelderland",
    "iso:country":"NL",
    "sg:address":"Bellestein 49",
    "sg:city":"Ede Gld",
    "sg:orig_category":"Zuivelproducten",
    "sg:phone":"+31 318 639 442",
    "sg:postcode":"6714 DP",
    "sg:province":"Gelderland",
    "wof:name":"Fromage",
    "wof:placetype":"venue"
},
  "geometry": {"coordinates":[5.64459,52.042309],"type":"Point"}
}