{
  "type": "Feature",
  "properties": {
    "addr:full":"St Gotthard 10 Amstelveen North Holland 1186 EM",
    "addr:housenumber":"10",
    "addr:postcode":"1186 em",
    "addr:street":"St Gotthard",
    "iso:country":"NL",
    "sg:address":"St Gotthard 10",
    "sg:city":"Amstelveen",
    "sg:orig_category":"Product-Promotie",
    "sg:phone":"+31 20 645 7454",
    "sg:postcode":"1186 EM",
    "sg:province":"North Holland",
    "wof:name":"Sanugum",
    "wof:placetype":"venue"
},
  "geometry": {"coordinates":[4.865949,52.290546],"type":"Point"}
}