{
  "type": "Feature",
  "properties": {
    "iso:country":"NL",
    "sg:address":"Loggerwg 5",
    "sg:city":"Zwolle",
    "sg:orig_category":"Elektrotechnische Apparatuur - Fabrieken En Groothandel",
    "sg:phone":"+31 38 425 8425",
    "sg:postcode":"8042 PG",
    "sg:province":"NL.08",
    "sg:website":"http://www.technischeunie.com",
    "wof:name":"Technische Unie Bv",
    "wof:placetype":"venue"
},
  "geometry": {"coordinates":[6.050676,52.515419],"type":"Point"}
}