{
  "type": "Feature",
  "properties": {
    "addr:full":"Waalreseweg 17 Valkenswaard North Brabant 5554 HA",
    "addr:housenumber":"17",
    "addr:postcode":"5554 ha",
    "addr:street":"Waalreseweg",
    "iso:country":"NL",
    "sg:address":"Waalreseweg 17",
    "sg:city":"Valkenswaard",
    "sg:orig_category":"Partycatering And -Organisatie",
    "sg:phone":"+31 40 208 9324",
    "sg:postcode":"5554 HA",
    "sg:province":"North Brabant",
    "wof:name":"Fz Catering",
    "wof:placetype":"venue"
},
  "geometry": {"coordinates":[5.457215,51.351959],"type":"Point"}
}