{
  "type": "Feature",
  "properties": {
    "iso:country":"NL",
    "sg:address":"Verbindingsweg 10",
    "sg:city":"Epe",
    "sg:orig_category":"Bedrijfs- And Managementsconsultants",
    "sg:phone":"+31 570 510 912",
    "sg:postcode":"8161 CC",
    "sg:province":"Gelderland",
    "wof:name":"Schrover Interim Management",
    "wof:placetype":"venue"
},
  "geometry": {"coordinates":[5.985182,52.349014],"type":"Point"}
}