{
  "type": "Feature",
  "properties": {
    "addr:full":"De Hoven 102 Zwartemeer Drenthe 7894 BW",
    "addr:housenumber":"102",
    "addr:postcode":"7894 bw",
    "addr:street":"De Hoven",
    "iso:country":"NL",
    "sg:address":"De Hoven 102",
    "sg:city":"Zwartemeer",
    "sg:orig_category":"Metaalwerken",
    "sg:phone":"+31 591 316 380",
    "sg:postcode":"7894 BW",
    "sg:province":"Drenthe",
    "wof:name":"Prijs En Wanders Bv",
    "wof:placetype":"venue"
},
  "geometry": {"coordinates":[7.041621,52.716938],"type":"Point"}
}