{
  "type": "Feature",
  "properties": {
    "iso:country":"NL",
    "sg:address":"Bloemgr 300",
    "sg:city":"Amsterdam",
    "sg:orig_category":"Postkantoren",
    "sg:phone":"+31 20 624 7231",
    "sg:postcode":"1015 TV",
    "sg:province":"Noord-Holland",
    "sg:website":"http://www.postkantoor.nl",
    "wof:name":"Postkantoor",
    "wof:placetype":"venue"
},
  "geometry": {"coordinates":[4.877189,52.374096],"type":"Point"}
}