{
  "type": "Feature",
  "properties": {
    "addr:full":"Dorpsstraat 155 Harmelen Utrecht 3481 ED",
    "addr:housenumber":"155",
    "addr:postcode":"3481 ed",
    "addr:street":"Dorpsstraat",
    "iso:country":"NL",
    "sg:address":"Dorpsstraat 155",
    "sg:city":"Harmelen",
    "sg:orig_category":"Partycatering And -Organisatie",
    "sg:phone":"+31 348 443 184",
    "sg:postcode":"3481 ED",
    "sg:province":"Utrecht",
    "sg:website":"http://www.eten-van-emilie.nl",
    "wof:name":"Eve, Eten Van Emilie",
    "wof:placetype":"venue"
},
  "geometry": {"coordinates":[4.960137,52.090698],"type":"Point"}
}