{
  "type": "Feature",
  "properties": {
    "addr:full":"Business Pk Stein 302 Elsloo Lb BE.05 6181 MC",
    "addr:housenumber":"302;6181",
    "addr:street":"Business Pk Stein;Lb;Mc",
    "iso:country":"NL",
    "sg:address":"Business Pk Stein 302",
    "sg:city":"Elsloo Lb",
    "sg:orig_category":"Verhuur",
    "sg:phone":"+31 46 426 9100",
    "sg:postcode":"6181 MC",
    "sg:province":"BE.05",
    "sg:website":"http://www.storkmat.com",
    "wof:name":"Stork Materieel",
    "wof:placetype":"venue"
},
  "geometry": {"coordinates":[5.738695,50.960476],"type":"Point"}
}