{
  "type": "Feature",
  "properties": {
    "iso:country":"NL",
    "sg:address":"Werenfriedstraat 9",
    "sg:city":"Zieuwent",
    "sg:orig_category":"Verzekeringen",
    "sg:phone":"+31 544 351 461",
    "sg:postcode":"7136 LZ",
    "sg:province":"Gelderland",
    "wof:name":"Ass-Admin-Financieringsktr Th J Bekken",
    "wof:placetype":"venue"
},
  "geometry": {"coordinates":[6.517505,52.005566],"type":"Point"}
}