{
  "type": "Feature",
  "properties": {
    "iso:country":"NL",
    "sg:address":"Kon Wilhelminastr 20",
    "sg:city":"Nootdorp",
    "sg:orig_category":"Woningbouw- Verenigingen En -Stichtingen",
    "sg:phone":"+31 15 310 8877",
    "sg:postcode":"2631 CW",
    "sg:province":"Zuid-Holland",
    "wof:name":"Woningbouw Nootdorp, Sticht",
    "wof:placetype":"venue"
},
  "geometry": {"coordinates":[4.3943638802,52.0438461304],"type":"Point"}
}