{
  "type": "Feature",
  "properties": {
    "iso:country":"NL",
    "sg:address":"Nieuweweg 265",
    "sg:city":"Wijchen",
    "sg:orig_category":"Diverse Grafische Activiteiten",
    "sg:phone":"+31 24 641 2944",
    "sg:postcode":"6603 BN",
    "sg:province":"Gelderland",
    "wof:name":"Brainwave",
    "wof:placetype":"venue"
},
  "geometry": {"coordinates":[5.757906,51.80262],"type":"Point"}
}