{
  "type": "Feature",
  "properties": {
    "iso:country":"NL",
    "sg:address":"Schapenbrugstraat 4",
    "sg:city":"Heusden Gem Heusden",
    "sg:orig_category":"Fotostudio'S And Fotografen",
    "sg:phone":"+31 416 663 075",
    "sg:postcode":"5256 EH",
    "sg:province":"Noord-Brabant",
    "wof:name":"Fotostudio Lossie",
    "wof:placetype":"venue"
},
  "geometry": {"coordinates":[5.135764,51.732895],"type":"Point"}
}