{
  "type": "Feature",
  "properties": {
    "addr:full":"Postbus 20 Schoonoord Drenthe 7848 ZG",
    "addr:housenumber":"20",
    "addr:postcode":"7848 zg",
    "addr:street":"Postbus",
    "iso:country":"NL",
    "sg:address":"Postbus 20",
    "sg:city":"Schoonoord",
    "sg:orig_category":"Adviesbureaus Bedrijfsorganisatie",
    "sg:phone":"+31 591 382 370",
    "sg:postcode":"7848 ZG",
    "sg:province":"Drenthe",
    "wof:name":"Kesteren Vof, Van",
    "wof:placetype":"venue"
},
  "geometry": {"coordinates":[6.75755,52.845226],"type":"Point"}
}