{
  "type": "Feature",
  "properties": {
    "addr:full":"Schoolstraat 16 Krimpen A/D Lek Zuid-Holland 2931 GW",
    "addr:housenumber":"16;a / d",
    "addr:postcode":"2931 gw",
    "addr:street":"Schoolstraat",
    "iso:country":"NL",
    "sg:address":"Schoolstraat 16",
    "sg:city":"Krimpen A/D Lek",
    "sg:orig_category":"Bloemen And Planten",
    "sg:phone":"+31 180 511 563",
    "sg:postcode":"2931 GW",
    "sg:province":"Zuid-Holland",
    "wof:name":"J.M. Van Der Graaf Bloemen",
    "wof:placetype":"venue"
},
  "geometry": {"coordinates":[4.623801,51.892593],"type":"Point"}
}