{
  "type": "Feature",
  "properties": {
    "addr:full":"Willibrordusstraat 14 Riethoven North Brabant 5561 AX",
    "addr:housenumber":"14",
    "addr:postcode":"5561 ax",
    "addr:street":"Willibrordusstraat",
    "iso:country":"NL",
    "sg:address":"Willibrordusstraat 14",
    "sg:city":"Riethoven",
    "sg:orig_category":"Pompen And Compressoren Fab",
    "sg:phone":"+31 40 204 5269",
    "sg:postcode":"5561 AX",
    "sg:province":"North Brabant",
    "wof:name":"Tat",
    "wof:placetype":"venue"
},
  "geometry": {"coordinates":[5.388151,51.351772],"type":"Point"}
}