{
  "type": "Feature",
  "properties": {
    "addr:full":"Praam 253 Amstelveen North Holland 1186 TV",
    "addr:housenumber":"253",
    "addr:postcode":"1186 tv",
    "addr:street":"Praam",
    "iso:country":"NL",
    "sg:address":"Praam 253",
    "sg:city":"Amstelveen",
    "sg:orig_category":"Verlichting",
    "sg:phone":"+31 20 643 4886",
    "sg:postcode":"1186 TV",
    "sg:province":"North Holland",
    "wof:name":"Philektra",
    "wof:placetype":"venue"
},
  "geometry": {"coordinates":[4.860868,52.27943],"type":"Point"}
}