{
  "type": "Feature",
  "properties": {
    "addr:full":"Op Het Zant 8 Meyel Limburg 5768 HH",
    "addr:housenumber":"8",
    "addr:postcode":"5768 hh",
    "addr:street":"Op Het Zant",
    "iso:country":"NL",
    "sg:address":"Op Het Zant 8",
    "sg:city":"Meyel",
    "sg:orig_category":"Woninginrichting",
    "sg:phone":"+31 77 466 9025",
    "sg:postcode":"5768 HH",
    "sg:province":"Limburg",
    "wof:name":"Bakker, Tom",
    "wof:placetype":"venue"
},
  "geometry": {"coordinates":[5.8857588768,51.3442878723],"type":"Point"}
}