{
  "type": "Feature",
  "properties": {
    "iso:country":"NL",
    "sg:address":"Hartensewg 15",
    "sg:city":"Wageningen",
    "sg:orig_category":"Adviesbureaus Bedrijfsorganisatie",
    "sg:phone":"+31 317 420 293",
    "sg:postcode":"6705 BH",
    "sg:province":"Gelderland",
    "wof:name":"Putte & Partn, Organisatie Adv Vd",
    "wof:placetype":"venue"
},
  "geometry": {"coordinates":[5.70178,51.991405],"type":"Point"}
}