{
  "type": "Feature",
  "properties": {
    "addr:full":"2E Daalsedk 8 Utrecht Utrecht 3551 EJ",
    "addr:housenumber":"8",
    "addr:postcode":"3551 ej",
    "addr:street":"2E Daalsedk",
    "iso:country":"NL",
    "sg:address":"2E Daalsedk 8",
    "sg:city":"Utrecht",
    "sg:orig_category":"Verenigingen En Stichtingen",
    "sg:phone":"+31 30 235 8529",
    "sg:postcode":"3551 EJ",
    "sg:province":"Utrecht",
    "wof:name":"Bond Gepensioneerd Spoor & Trampers Bvg",
    "wof:placetype":"venue"
},
  "geometry": {"coordinates":[5.101048,52.09866],"type":"Point"}
}