{
  "type": "Feature",
  "properties": {
    "addr:full":"Armgardstr 15 Doesburg HR. 6981 HR",
    "addr:housenumber":"15",
    "addr:postcode":"6981 hr",
    "addr:street":"Armgardstr;Hr.",
    "iso:country":"NL",
    "sg:address":"Armgardstr 15",
    "sg:city":"Doesburg",
    "sg:orig_category":"Kinderopvang",
    "sg:phone":"+31 313 482 832",
    "sg:postcode":"6981 HR",
    "sg:province":"HR.",
    "wof:name":"Tombola",
    "wof:placetype":"venue"
},
  "geometry": {"coordinates":[15.40843,44.736759],"type":"Point"}
}