{
  "type": "Feature",
  "properties": {
    "addr:full":"De Sering 23 Boxmeer North Brabant 5831 RW",
    "addr:housenumber":"23",
    "addr:postcode":"5831 rw",
    "addr:street":"De Sering",
    "iso:country":"NL",
    "sg:address":"De Sering 23",
    "sg:city":"Boxmeer",
    "sg:orig_category":"Vertalers",
    "sg:phone":"+31 485 577 091",
    "sg:postcode":"5831 RW",
    "sg:province":"North Brabant",
    "wof:name":"Enckevort, E Van",
    "wof:placetype":"venue"
},
  "geometry": {"coordinates":[5.933352,51.655537],"type":"Point"}
}