{
  "type": "Feature",
  "properties": {
    "addr:full":"Grt Kerkstr 24-A Steenbergen Nb Noord-Brabant 4651 BB",
    "addr:housenumber":"24-a",
    "addr:postcode":"4651 bb",
    "iso:country":"NL",
    "sg:address":"Grt Kerkstr 24-A",
    "sg:city":"Steenbergen Nb",
    "sg:orig_category":"Verzekeringen - Verzekeringskantoren",
    "sg:phone":"+31 167 563 920",
    "sg:postcode":"4651 BB",
    "sg:province":"Noord-Brabant",
    "wof:name":"Peer Bv, Nico Van",
    "wof:placetype":"venue"
},
  "geometry": {"coordinates":[4.314555,51.585594],"type":"Point"}
}