{
  "type": "Feature",
  "properties": {
    "addr:full":"Rivieradreef 37 Haarlem Noord-Holland 2037 AE",
    "addr:housenumber":"37",
    "addr:postcode":"2037 ae",
    "addr:street":"Rivieradreef",
    "iso:country":"NL",
    "sg:address":"Rivieradreef 37",
    "sg:city":"Haarlem",
    "sg:orig_category":"Wasmachines En Wasdrogers",
    "sg:phone":"+31 23 536 5235",
    "sg:postcode":"2037 AE",
    "sg:province":"Noord-Holland",
    "wof:name":"Bcc",
    "wof:placetype":"venue"
},
  "geometry": {"coordinates":[4.6540551186,52.3585090637],"type":"Point"}
}