{
  "type": "Feature",
  "properties": {
    "addr:full":"Kortemeestraat 3 Bergen Op Zoom Noord-Brabant 4611 TK",
    "addr:housenumber":"3",
    "addr:postcode":"4611 tk",
    "addr:street":"Kortemeestraat",
    "iso:country":"NL",
    "sg:address":"Kortemeestraat 3",
    "sg:city":"Bergen Op Zoom",
    "sg:classifiers":[
        {
            "category":"Shopping",
            "subcategory":"Clothing, Apparel, & Fashions",
            "type":"Retail Goods"
        }
    ],
    "sg:phone":"+31 164 247 483",
    "sg:postcode":"4611 TK",
    "sg:province":"Noord-Brabant",
    "sg:tags":[
        "ondergoed",
        "lingerie"
    ],
    "wof:name":"Lingerie-Boetiek Erika",
    "wof:placetype":"venue"
},
  "geometry": {"coordinates":[4.285195,51.495415],"type":"Point"}
}