{
  "type": "Feature",
  "properties": {
    "addr:full":"Drielse Wetering 5 Kerkdriel Gelderland 5331 RK",
    "addr:housenumber":"5",
    "addr:postcode":"5331 rk",
    "addr:street":"Drielse Wetering;Gelderland",
    "iso:country":"NL",
    "sg:address":"Drielse Wetering 5",
    "sg:city":"Kerkdriel",
    "sg:orig_category":"Loodgieters",
    "sg:phone":"+31 418 633 107",
    "sg:postcode":"5331 RK",
    "sg:province":"Gelderland",
    "wof:name":"Kessel, A Van",
    "wof:placetype":"venue"
},
  "geometry": {"coordinates":[5.32954,51.767433],"type":"Point"}
}