{
  "type": "Feature",
  "properties": {
    "iso:country":"NL",
    "sg:address":"Drielse Wetering 5",
    "sg:city":"Kerkdriel",
    "sg:orig_category":"Loodgieters",
    "sg:phone":"+31 418 633 107",
    "sg:postcode":"5331 RK",
    "sg:province":"Gelderland",
    "wof:name":"Kessel, A Van",
    "wof:placetype":"venue"
},
  "geometry": {"coordinates":[5.32954,51.767433],"type":"Point"}
}