{
  "type": "Feature",
  "properties": {
    "addr:full":"Herenstraat 23 Hilversum North Holland 1211 BZ",
    "addr:housenumber":"23",
    "addr:postcode":"1211 bz",
    "addr:street":"Herenstraat",
    "iso:country":"NL",
    "sg:address":"Herenstraat 23",
    "sg:city":"Hilversum",
    "sg:orig_category":"Werving And Selectie Van Tijdelijk Personeel And Uitzendkantoren",
    "sg:phone":"+31 35 624 8645",
    "sg:postcode":"1211 BZ",
    "sg:province":"North Holland",
    "wof:name":"Kgu Bv",
    "wof:placetype":"venue"
},
  "geometry": {"coordinates":[5.1762800217,52.2237892151],"type":"Point"}
}