{
  "type": "Feature",
  "properties": {
    "addr:full":"Weiersloop 6 Assen Drenthe 9401 DZ",
    "addr:housenumber":"6",
    "addr:postcode":"9401 dz",
    "addr:street":"Weiersloop",
    "iso:country":"NL",
    "sg:address":"Weiersloop 6",
    "sg:city":"Assen",
    "sg:classifiers":[
        {
            "category":"Shopping",
            "subcategory":"Clothing, Apparel, & Fashions",
            "type":"Retail Goods"
        }
    ],
    "sg:phone":"+31 592 311 321",
    "sg:postcode":"9401 DZ",
    "sg:province":"Drenthe",
    "sg:tags":[
        "ondergoed",
        "lingerie"
    ],
    "wof:name":"Panty En Sokkenshop 'T Sokkie Vof",
    "wof:placetype":"venue"
},
  "geometry": {"coordinates":[6.560417,52.994343],"type":"Point"}
}