{
  "type": "Feature",
  "properties": {
    "addr:full":"Jekerwg 72A Maastricht Limburg 6212 GD",
    "addr:housenumber":"72a",
    "addr:postcode":"6212 gd",
    "addr:street":"Jekerwg",
    "iso:country":"NL",
    "sg:address":"Jekerwg 72A",
    "sg:city":"Maastricht",
    "sg:orig_category":"Adviesbureaus Personeel",
    "sg:phone":"+31 43 326 3778",
    "sg:postcode":"6212 GD",
    "sg:province":"Limburg",
    "wof:name":"Proflex",
    "wof:placetype":"venue"
},
  "geometry": {"coordinates":[5.68508,50.84042],"type":"Point"}
}