{
  "type": "Feature",
  "properties": {
    "addr:full":"Postbus 786 Haarlem North Holland 2003 RT",
    "addr:housenumber":"786",
    "addr:postcode":"2003 rt",
    "addr:street":"Postbus",
    "iso:country":"NL",
    "sg:address":"Postbus 786",
    "sg:city":"Haarlem",
    "sg:orig_category":"Kantoorartikelen",
    "sg:phone":"+31 23 524 2517",
    "sg:postcode":"2003 RT",
    "sg:province":"North Holland",
    "wof:name":"Veldhuis Projektinrichting",
    "wof:placetype":"venue"
},
  "geometry": {"coordinates":[4.642250061,52.3805618286],"type":"Point"}
}