{
  "type": "Feature",
  "properties": {
    "iso:country":"NL",
    "sg:address":"J P Gouverneurlaan 30",
    "sg:city":"Sassenheim",
    "sg:orig_category":"Notarissen",
    "sg:phone":"+31 252 215 550",
    "sg:postcode":"2171 ER",
    "sg:province":"South Holland",
    "wof:name":"Notariskantoor Dirven & Schrama",
    "wof:placetype":"venue"
},
  "geometry": {"coordinates":[4.522504,52.224865],"type":"Point"}
}