{
  "type": "Feature",
  "properties": {
    "addr:full":"Concourslaan 92 Hoofddorp Noord-Holland 2132 DK",
    "addr:housenumber":"92",
    "addr:postcode":"2132 dk",
    "addr:street":"Concourslaan",
    "iso:country":"NL",
    "sg:address":"Concourslaan 92",
    "sg:city":"Hoofddorp",
    "sg:orig_category":"Werving And Selectie Van Tijdelijk Personeel And Uitzendkantoren",
    "sg:phone":"+31 23 561 7776",
    "sg:postcode":"2132 DK",
    "sg:province":"Noord-Holland",
    "wof:name":"Uitzendbureau Start",
    "wof:placetype":"venue"
},
  "geometry": {"coordinates":[4.6939630508,52.3030509949],"type":"Point"}
}