{
  "type": "Feature",
  "properties": {
    "addr:full":"Noordsngl 32 Sprundel North Brabant 4714 HB",
    "addr:housenumber":"32",
    "addr:postcode":"4714 hb",
    "addr:street":"Noordsngl",
    "iso:country":"NL",
    "sg:address":"Noordsngl 32",
    "sg:city":"Sprundel",
    "sg:orig_category":"Warmtetechniek",
    "sg:phone":"+31 165 350 408",
    "sg:postcode":"4714 HB",
    "sg:province":"North Brabant",
    "wof:name":"Deijkers Gloeitechniek",
    "wof:placetype":"venue"
},
  "geometry": {"coordinates":[4.6010451317,51.5382652283],"type":"Point"}
}