{
  "type": "Feature",
  "properties": {
    "iso:country":"NL",
    "sg:address":"Buurmalsenstr 1",
    "sg:city":"Tiel",
    "sg:orig_category":"Werving En Selectie",
    "sg:phone":"+31 344 632 111",
    "sg:postcode":"4006 BB",
    "sg:province":"Gelderland",
    "sg:website":"http://www.intersales.nl",
    "wof:name":"Creyf'S Intersales",
    "wof:placetype":"venue"
},
  "geometry": {"coordinates":[5.4204859734,51.8791732788],"type":"Point"}
}