{
  "type": "Feature",
  "properties": {
    "addr:full":"Zijlweg 66 Haarlem Noord-Holland 2013 DK",
    "addr:housenumber":"66",
    "addr:postcode":"2013 dk",
    "addr:street":"Zijlweg",
    "iso:country":"NL",
    "sg:address":"Zijlweg 66",
    "sg:city":"Haarlem",
    "sg:classifiers":[
        {
            "category":"Retail",
            "subcategory":"Photofinishing",
            "type":"Services"
        }
    ],
    "sg:phone":"+31 23 542 4759",
    "sg:postcode":"2013 DK",
    "sg:province":"Noord-Holland",
    "sg:tags":[
        "foto",
        "film"
    ],
    "wof:name":"Combi City",
    "wof:placetype":"venue"
},
  "geometry": {"coordinates":[4.625606,52.384644],"type":"Point"}
}