{
  "type": "Feature",
  "properties": {
    "addr:full":"Bronovolaan 5 'S Gravenhage Zuid-Holland 2597 AX",
    "addr:housenumber":"5 '",
    "addr:postcode":"2597 ax",
    "addr:street":"Bronovolaan",
    "iso:country":"NL",
    "sg:address":"Bronovolaan 5",
    "sg:city":"'S Gravenhage",
    "sg:orig_category":"Kappers",
    "sg:phone":"+31 70 324 6380",
    "sg:postcode":"2597 AX",
    "sg:province":"Zuid-Holland",
    "wof:name":"Bronovoshop",
    "wof:placetype":"venue"
},
  "geometry": {"coordinates":[4.3174772263,52.1018676758],"type":"Point"}
}