{
  "type": "Feature",
  "properties": {
    "addr:full":"Nassaulaan 24 Bussum Noord-Holland 1404 CP",
    "addr:housenumber":"24",
    "addr:postcode":"1404 cp",
    "addr:street":"Nassaulaan",
    "iso:country":"NL",
    "sg:address":"Nassaulaan 24",
    "sg:city":"Bussum",
    "sg:orig_category":"Voeding, Dranken And Tabak Gh",
    "sg:phone":"+31 35 692 0960",
    "sg:postcode":"1404 CP",
    "sg:province":"Noord-Holland",
    "wof:name":"Klein Distributions",
    "wof:placetype":"venue"
},
  "geometry": {"coordinates":[5.162263,52.274967],"type":"Point"}
}