{
  "type": "Feature",
  "properties": {
    "iso:country":"NL",
    "sg:address":"Havikveld 67",
    "sg:city":"Zoetermeer",
    "sg:orig_category":"Administratie- En Boekhoudkantoren",
    "sg:phone":"+31 79 331 6945",
    "sg:postcode":"2727 AB",
    "sg:province":"Zuid-Holland",
    "wof:name":"Bregonje",
    "wof:placetype":"venue"
},
  "geometry": {"coordinates":[4.507491,52.069748],"type":"Point"}
}