{
  "type": "Feature",
  "properties": {
    "addr:full":"Leeuwenln 16 S Graveland North Holland 1243 KB",
    "addr:housenumber":"16",
    "addr:postcode":"1243 kb",
    "addr:street":"Leeuwenln;S Graveland North",
    "iso:country":"NL",
    "sg:address":"Leeuwenln 16",
    "sg:city":"S Graveland",
    "sg:orig_category":"Fotostudio'S",
    "sg:phone":"+31 35 656 4412",
    "sg:postcode":"1243 KB",
    "sg:province":"North Holland",
    "sg:website":"http://www.tobiasreymond.nl",
    "wof:name":"Reymond Bv, Tobias",
    "wof:placetype":"venue"
},
  "geometry": {"coordinates":[5.132315,52.235859],"type":"Point"}
}