{
  "type": "Feature",
  "properties": {
    "addr:full":"Meester Kesperweg 54 Ridderkerk South Holland 2982 RR",
    "addr:housenumber":"54",
    "addr:postcode":"2982 rr",
    "addr:street":"Meester Kesperweg",
    "iso:country":"NL",
    "sg:address":"Meester Kesperweg 54",
    "sg:city":"Ridderkerk",
    "sg:orig_category":"Boekhouders",
    "sg:phone":"+31 180 427 180",
    "sg:postcode":"2982 RR",
    "sg:province":"South Holland",
    "wof:name":"G M Van Luijk",
    "wof:placetype":"venue"
},
  "geometry": {"coordinates":[4.593619,51.872173],"type":"Point"}
}