{
  "type": "Feature",
  "properties": {
    "addr:full":"Easter Omwei 36 Hardegaryp Friesland 9254 GN",
    "addr:housenumber":"36",
    "addr:postcode":"9254 gn",
    "addr:street":"Easter Omwei",
    "iso:country":"NL",
    "sg:address":"Easter Omwei 36",
    "sg:city":"Hardegaryp",
    "sg:orig_category":"Administratie- En Boekhoudkantoren",
    "sg:phone":"+31 511 474 348",
    "sg:postcode":"9254 GN",
    "sg:province":"Friesland",
    "wof:name":"Hardegarijp",
    "wof:placetype":"venue"
},
  "geometry": {"coordinates":[5.944636,53.21302],"type":"Point"}
}