{
  "type": "Feature",
  "properties": {
    "addr:full":"Vuurboetsplein 7 Vlieland Provincie Friesland 8899 AP",
    "addr:housenumber":"7",
    "addr:postcode":"8899 ap",
    "addr:street":"Vuurboetsplein;Friesland",
    "iso:country":"NL",
    "sg:address":"Vuurboetsplein 7",
    "sg:city":"Vlieland",
    "sg:classifiers":[
        {
            "category":"Education",
            "subcategory":"Preschool",
            "type":"Public Place"
        }
    ],
    "sg:phone":"+31 562 451 581",
    "sg:postcode":"8899 AP",
    "sg:province":"Provincie Friesland",
    "sg:tags":[
        "kleuteronderwijs",
        "basis-"
    ],
    "wof:name":"Openbare Basisschool De Zeester",
    "wof:placetype":"venue"
},
  "geometry": {"coordinates":[5.060834,53.294987],"type":"Point"}
}