{
  "type": "Feature",
  "properties": {
    "addr:full":"Churchillwg 5 Wageningen Gelderland 6707 JA",
    "addr:housenumber":"5",
    "addr:postcode":"6707 ja",
    "addr:street":"Churchillwg;Gelderland",
    "iso:country":"NL",
    "sg:address":"Churchillwg 5",
    "sg:city":"Wageningen",
    "sg:orig_category":"Bedrijfsopleidingen",
    "sg:phone":"+31 317 425 134",
    "sg:postcode":"6707 JA",
    "sg:province":"Gelderland",
    "sg:website":"http://www.trainersopleiding.nl",
    "wof:name":"Kb&K",
    "wof:placetype":"venue"
},
  "geometry": {"coordinates":[5.668948,51.970261],"type":"Point"}
}