{
  "type": "Feature",
  "properties": {
    "addr:full":"Sluisplateau 31 Wemeldinge Zeeland 4424 BK",
    "addr:housenumber":"31",
    "addr:postcode":"4424 bk",
    "addr:street":"Sluisplateau",
    "iso:country":"NL",
    "sg:address":"Sluisplateau 31",
    "sg:city":"Wemeldinge",
    "sg:orig_category":"Jachthavens - Jachtwerven",
    "sg:phone":"+31 113 622 093",
    "sg:postcode":"4424 BK",
    "sg:province":"Zeeland",
    "wof:name":"Wemeldinge Bv",
    "wof:placetype":"venue"
},
  "geometry": {"coordinates":[4.004525,51.514038],"type":"Point"}
}