{
  "type": "Feature",
  "properties": {
    "addr:full":"Weth Rebelln 87 Barneveld Gelderland 3771 KA",
    "addr:housenumber":"87",
    "addr:postcode":"3771 ka",
    "addr:street":"Weth Rebelln;Gelderland",
    "iso:country":"NL",
    "sg:address":"Weth Rebelln 87",
    "sg:city":"Barneveld",
    "sg:orig_category":"Feestartikelen",
    "sg:phone":"+31 342 493 195",
    "sg:postcode":"3771 KA",
    "sg:province":"Gelderland",
    "sg:website":"http://www.ronnies-feest.tk",
    "wof:name":"Ronnies Feest En Promotie Supplies",
    "wof:placetype":"venue"
},
  "geometry": {"coordinates":[5.582306,52.150078],"type":"Point"}
}