{
  "type": "Feature",
  "properties": {
    "iso:country":"NL",
    "sg:address":"P Calandln 124",
    "sg:city":"Amsterdam",
    "sg:orig_category":"Fietsen En Bromfietsen",
    "sg:phone":"+31 20 619 5627",
    "sg:postcode":"1068 NR",
    "sg:province":"Noord-Holland",
    "wof:name":"Heng Xing",
    "wof:placetype":"venue"
},
  "geometry": {"coordinates":[4.811352,52.354458],"type":"Point"}
}