{
  "type": "Feature",
  "properties": {
    "addr:full":"Haarlemmerstraat 175 Amsterdam Noord-Holland 1013 EP",
    "addr:housenumber":"175",
    "addr:postcode":"1013 ep",
    "addr:street":"Haarlemmerstraat",
    "iso:country":"NL",
    "sg:address":"Haarlemmerstraat 175",
    "sg:city":"Amsterdam",
    "sg:classifiers":[
        {
            "category":"Fast Food",
            "type":"Food & Drink"
        }
    ],
    "sg:phone":"+31 20 626 4650",
    "sg:postcode":"1013 EP",
    "sg:province":"Noord-Holland",
    "sg:tags":[
        "afhaal",
        "restaurant"
    ],
    "wof:name":"Snackbar De Snackcorner",
    "wof:placetype":"venue"
},
  "geometry": {"coordinates":[4.88956,52.381168],"type":"Point"}
}