{
  "type": "Feature",
  "properties": {
    "addr:full":"Meidoornln 33 Roermond Limburg 6042 HA",
    "addr:housenumber":"33",
    "addr:postcode":"6042 ha",
    "addr:street":"Meidoornln",
    "iso:country":"NL",
    "sg:address":"Meidoornln 33",
    "sg:city":"Roermond",
    "sg:orig_category":"Ventilatiesystemen",
    "sg:phone":"+31 475 325 922",
    "sg:postcode":"6042 HA",
    "sg:province":"Limburg",
    "wof:name":"Sieg Bv",
    "wof:placetype":"venue"
},
  "geometry": {"coordinates":[6.005629,51.196255],"type":"Point"}
}