{
  "type": "Feature",
  "properties": {
    "addr:full":"Achterbaan 82 Huizen Noord-Holland 1271 TZ",
    "addr:housenumber":"82",
    "addr:postcode":"1271 tz",
    "addr:street":"Achterbaan",
    "iso:country":"NL",
    "sg:address":"Achterbaan 82",
    "sg:city":"Huizen",
    "sg:orig_category":"Musea",
    "sg:phone":"+31 35 525 0223",
    "sg:postcode":"1271 TZ",
    "sg:province":"Noord-Holland",
    "wof:name":"Huizermuseum Het Schoutenhuis, Het",
    "wof:placetype":"venue"
},
  "geometry": {"coordinates":[5.234322,52.300091],"type":"Point"}
}