{
  "type": "Feature",
  "properties": {
    "iso:country":"NL",
    "sg:address":"Verryn Stuartlaan 28",
    "sg:city":"Rijswijk Zh",
    "sg:orig_category":"Metaalwerken",
    "sg:phone":"+31 70 399 0675",
    "sg:postcode":"2288 EL",
    "sg:province":"Zuid-Holland",
    "wof:name":"Sun Gard Heat & Light Conditioning Bv",
    "wof:placetype":"venue"
},
  "geometry": {"coordinates":[4.334414,52.041122],"type":"Point"}
}