{
  "type": "Feature",
  "properties": {
    "addr:full":"Lindtsedijk 62 Zwijndrecht Zuid-Holland 3336 LE",
    "addr:housenumber":"62",
    "addr:postcode":"3336 le",
    "addr:street":"Lindtsedijk",
    "iso:country":"NL",
    "sg:address":"Lindtsedijk 62",
    "sg:city":"Zwijndrecht",
    "sg:orig_category":"Autoschade- Herstelbedrijven",
    "sg:phone":"+31 78 610 1707",
    "sg:postcode":"3336 LE",
    "sg:province":"Zuid-Holland",
    "wof:name":"Autoschade Goudswaard Vof",
    "wof:placetype":"venue"
},
  "geometry": {"coordinates":[4.618424,51.811531],"type":"Point"}
}