{
  "type": "Feature",
  "properties": {
    "addr:full":"Madoerastr 4 S Gravenhage South Holland 2585 VB",
    "addr:housenumber":"4",
    "addr:postcode":"2585 vb",
    "addr:street":"Madoerastr;S Gravenhage",
    "iso:country":"NL",
    "sg:address":"Madoerastr 4",
    "sg:city":"S Gravenhage",
    "sg:orig_category":"Loodgieters",
    "sg:phone":"+31 70 355 2743",
    "sg:postcode":"2585 VB",
    "sg:province":"South Holland",
    "wof:name":"Kersbergen, Erik",
    "wof:placetype":"venue"
},
  "geometry": {"coordinates":[4.29777,52.094799],"type":"Point"}
}