{
  "type": "Feature",
  "properties": {
    "addr:full":"Doelenstraat 21 Gouda Zuid-Holland 2801 PW",
    "addr:housenumber":"21",
    "addr:postcode":"2801 pw",
    "addr:street":"Doelenstraat",
    "iso:country":"NL",
    "sg:address":"Doelenstraat 21",
    "sg:city":"Gouda",
    "sg:orig_category":"Binnenhuisarchitecten",
    "sg:phone":"+31 182 524 308",
    "sg:postcode":"2801 PW",
    "sg:province":"Zuid-Holland",
    "wof:name":"De Langen Design",
    "wof:placetype":"venue"
},
  "geometry": {"coordinates":[4.715033,52.009472],"type":"Point"}
}