{
  "type": "Feature",
  "properties": {
    "iso:country":"NL",
    "sg:address":"Doelenstraat 21",
    "sg:city":"Gouda",
    "sg:orig_category":"Binnenhuisarchitecten",
    "sg:phone":"+31 182 524 308",
    "sg:postcode":"2801 PW",
    "sg:province":"Zuid-Holland",
    "wof:name":"De Langen Design",
    "wof:placetype":"venue"
},
  "geometry": {"coordinates":[4.715033,52.009472],"type":"Point"}
}