{
  "type": "Feature",
  "properties": {
    "iso:country":"NL",
    "sg:address":"Waterstraat 209",
    "sg:city":"Nijmegen",
    "sg:classifiers":[
        {
            "category":"Food & Beverages",
            "subcategory":"Fruits & Vegetables",
            "type":"Retail Goods"
        }
    ],
    "sg:phone":"+31 24 377 5825",
    "sg:postcode":"6541 TJ",
    "sg:province":"Gelderland",
    "sg:tags":[
        "groenten"
    ],
    "wof:name":"Jan Cleijne",
    "wof:placetype":"venue"
},
  "geometry": {"coordinates":[5.843424,51.85128],"type":"Point"}
}