{
  "type": "Feature",
  "properties": {
    "addr:full":"Dorpsstraat 59 Zevenhuizen Zh Zuid-Holland 2761 AA",
    "addr:housenumber":"59",
    "addr:postcode":"2761 aa",
    "addr:street":"Dorpsstraat",
    "iso:country":"NL",
    "sg:address":"Dorpsstraat 59",
    "sg:city":"Zevenhuizen Zh",
    "sg:classifiers":[
        {
            "category":"Communications",
            "subcategory":"Television Station",
            "type":"Services"
        }
    ],
    "sg:phone":"+31 180 633 608",
    "sg:postcode":"2761 AA",
    "sg:province":"Zuid-Holland",
    "sg:tags":[
        "video",
        "audio",
        "verhuur"
    ],
    "wof:name":"Videotheek Zevenhuizen",
    "wof:placetype":"venue"
},
  "geometry": {"coordinates":[4.582325,52.010204],"type":"Point"}
}