{
  "type": "Feature",
  "properties": {
    "iso:country":"NL",
    "sg:address":"Rutgerinkdk 3",
    "sg:city":"Neede",
    "sg:orig_category":"Scholen Voor Basisonderwijs",
    "sg:phone":"+31 545 291 050",
    "sg:postcode":"7161 EW",
    "sg:province":"California",
    "wof:name":"Ari?ns Rk, Dr",
    "wof:placetype":"venue"
},
  "geometry": {"coordinates":[-121.31706200000001,38.299633],"type":"Point"}
}