{
  "type": "Feature",
  "properties": {
    "addr:full":"Kr Esse 4A Waddinxveen Zuid-Holland 2741 KP",
    "addr:housenumber":"4a",
    "addr:postcode":"2741 kp",
    "addr:street":"Kr Esse",
    "iso:country":"NL",
    "sg:address":"Kr Esse 4A",
    "sg:city":"Waddinxveen",
    "sg:orig_category":"Meubelen - Fabrieken En Groothandel",
    "sg:phone":"+31 182 612 092",
    "sg:postcode":"2741 KP",
    "sg:province":"Zuid-Holland",
    "wof:name":"Hogenelst Bv",
    "wof:placetype":"venue"
},
  "geometry": {"coordinates":[4.66164,52.041519],"type":"Point"}
}