{
  "type": "Feature",
  "properties": {
    "addr:full":"Voorstr 40 Katwyk Zh South Holland 2225 ER",
    "addr:housenumber":"40;zh",
    "addr:postcode":"2225 er",
    "addr:street":"Voorstr",
    "iso:country":"NL",
    "sg:address":"Voorstr 40",
    "sg:city":"Katwyk Zh",
    "sg:orig_category":"Beveiliging",
    "sg:phone":"+31 71 401 3341",
    "sg:postcode":"2225 ER",
    "sg:province":"South Holland",
    "wof:name":"Freke Inbraakbeveiliging",
    "wof:placetype":"venue"
},
  "geometry": {"coordinates":[4.397248,52.203651],"type":"Point"}
}