{
  "type": "Feature",
  "properties": {
    "iso:country":"NL",
    "sg:address":"Koolmees 43",
    "sg:city":"Hoorn Nh",
    "sg:orig_category":"Bedrijfs- And Managementsconsultants",
    "sg:phone":"+31 229 234 155",
    "sg:postcode":"1628 AT",
    "sg:province":"Noord-Holland",
    "wof:name":"Ridecon Bv",
    "wof:placetype":"venue"
},
  "geometry": {"coordinates":[5.08029,52.653477],"type":"Point"}
}