{
  "type": "Feature",
  "properties": {
    "addr:full":"Nikkelstraat 1 Lelystad NL. 8211 AJ",
    "addr:housenumber":"1",
    "addr:postcode":"8211 aj",
    "addr:street":"Nikkelstraat;Nl.",
    "iso:country":"NL",
    "sg:address":"Nikkelstraat 1",
    "sg:city":"Lelystad",
    "sg:orig_category":"Metaalwerken",
    "sg:phone":"+31 320 242 678",
    "sg:postcode":"8211 AJ",
    "sg:province":"NL.",
    "wof:name":"In Den Haak",
    "wof:placetype":"venue"
},
  "geometry": {"coordinates":[5.522408,52.544254],"type":"Point"}
}