{
  "type": "Feature",
  "properties": {
    "addr:full":"Beneluxln 16 Middelburg Zeeland 4334 GJ",
    "addr:housenumber":"16",
    "addr:postcode":"4334 gj",
    "addr:street":"Beneluxln",
    "iso:country":"NL",
    "sg:address":"Beneluxln 16",
    "sg:city":"Middelburg",
    "sg:orig_category":"Peuterspeelzalen",
    "sg:phone":"+31 118 615 345",
    "sg:postcode":"4334 GJ",
    "sg:province":"Zeeland",
    "wof:name":"Speeltreintje",
    "wof:placetype":"venue"
},
  "geometry": {"coordinates":[3.596647,51.504539],"type":"Point"}
}