{
  "type": "Feature",
  "properties": {
    "iso:country":"NL",
    "sg:address":"Lindenhof 26",
    "sg:city":"Malden",
    "sg:orig_category":"Openbaar Vervoer",
    "sg:phone":"+31 24 358 3553",
    "sg:postcode":"6581 PS",
    "sg:province":"Gelderland",
    "wof:name":"Buurtbus",
    "wof:placetype":"venue"
},
  "geometry": {"coordinates":[5.8644161224,51.7806472778],"type":"Point"}
}