{
  "type": "Feature",
  "properties": {
    "iso:country":"NL",
    "sg:address":"Westeinde 90A",
    "sg:city":"Enkhuizen",
    "sg:orig_category":"Verzekeringen - Verzekeringskantoren",
    "sg:phone":"+31 228 322 407",
    "sg:postcode":"1601 BL",
    "sg:province":"North Holland",
    "wof:name":"Enkhuizen Adviesgroep",
    "wof:placetype":"venue"
},
  "geometry": {"coordinates":[5.266888,52.700699],"type":"Point"}
}