{
  "type": "Feature",
  "properties": {
    "addr:full":"Schaepmanstr 11 Venlo Limburg 5921 CK",
    "addr:housenumber":"11",
    "addr:postcode":"5921 ck",
    "addr:street":"Schaepmanstr",
    "iso:country":"NL",
    "sg:address":"Schaepmanstr 11",
    "sg:city":"Venlo",
    "sg:orig_category":"Grafisch Ontwerpers",
    "sg:phone":"+31 77 464 2683",
    "sg:postcode":"5921 CK",
    "sg:province":"Limburg",
    "wof:name":"Cr-Design",
    "wof:placetype":"venue"
},
  "geometry": {"coordinates":[6.143231,51.364956],"type":"Point"}
}