{
  "type": "Feature",
  "properties": {
    "addr:full":"Middelwg 11-13 Opmeer North Holland 1716 KB",
    "addr:housenumber":"11-13",
    "addr:postcode":"1716 kb",
    "iso:country":"NL",
    "sg:address":"Middelwg 11-13",
    "sg:city":"Opmeer",
    "sg:orig_category":"Kunststof Ramen",
    "sg:phone":"+31 226 360 400",
    "sg:postcode":"1716 KB",
    "sg:province":"North Holland",
    "sg:website":"http://www.schipperkozijnen.nl",
    "wof:name":"Schipper Kozijnen Bv",
    "wof:placetype":"venue"
},
  "geometry": {"coordinates":[4.944089,52.710499],"type":"Point"}
}