{
  "type": "Feature",
  "properties": {
    "iso:country":"NL",
    "sg:address":"Castellum 1",
    "sg:city":"Cuijk",
    "sg:orig_category":"Musea And Historische Gebouwen",
    "sg:phone":"+31 485 330 181",
    "sg:postcode":"5431 EM",
    "sg:province":"Noord-Brabant",
    "wof:name":"Museum Ceuclum",
    "wof:placetype":"venue"
},
  "geometry": {"coordinates":[5.883348,51.728828],"type":"Point"}
}