{
  "type": "Feature",
  "properties": {
    "addr:full":"G Doupln 6 Amsterdam Noord-Holland 1072 VE",
    "addr:housenumber":"6",
    "addr:postcode":"1072",
    "addr:street":"Ve",
    "iso:country":"NL",
    "sg:address":"G Doupln 6",
    "sg:city":"Amsterdam",
    "sg:orig_category":"Verf En Lak",
    "sg:phone":"+31 20 679 0942",
    "sg:postcode":"1072 VE",
    "sg:province":"Noord-Holland",
    "wof:name":"Univerf-Colorite Verf- & Glasspecialisten",
    "wof:placetype":"venue"
},
  "geometry": {"coordinates":[4.89253,52.355869],"type":"Point"}
}