{
  "type": "Feature",
  "properties": {
    "iso:country":"NL",
    "sg:address":"Boerhaavelaan 20",
    "sg:city":"Zoetermeer",
    "sg:orig_category":"Elektronische Bedrijfsinstallaties",
    "sg:phone":"+31 79 320 3320",
    "sg:postcode":"2713 HX",
    "sg:province":"Zuid-Holland",
    "wof:name":"Teclion Bv",
    "wof:placetype":"venue"
},
  "geometry": {"coordinates":[4.477226,52.048779],"type":"Point"}
}