{
  "type": "Feature",
  "properties": {
    "addr:full":"Bezuidenhoutsewg 265E S Gravenhage South Holland 2594 AN",
    "addr:housenumber":"265e s",
    "addr:postcode":"2594 an",
    "addr:street":"Bezuidenhoutsewg",
    "iso:country":"NL",
    "sg:address":"Bezuidenhoutsewg 265E",
    "sg:city":"S Gravenhage",
    "sg:orig_category":"Plasticverwerking - Apparaten En Benodigdheden",
    "sg:phone":"+31 70 381 7158",
    "sg:postcode":"2594 AN",
    "sg:province":"South Holland",
    "wof:name":"Murman Bv",
    "wof:placetype":"venue"
},
  "geometry": {"coordinates":[4.317415,52.083992],"type":"Point"}
}