{
  "type": "Feature",
  "properties": {
    "addr:full":"Billitonstr 81 Groningen Groningen 9715 ER",
    "addr:housenumber":"81",
    "addr:postcode":"9715 er",
    "addr:street":"Billitonstr",
    "iso:country":"NL",
    "sg:address":"Billitonstr 81",
    "sg:city":"Groningen",
    "sg:orig_category":"Verenigingsgebouwen",
    "sg:phone":"+31 50 579 0070",
    "sg:postcode":"9715 ER",
    "sg:province":"Groningen",
    "wof:name":"Booib",
    "wof:placetype":"venue"
},
  "geometry": {"coordinates":[6.56566,53.231873],"type":"Point"}
}