{
  "type": "Feature",
  "properties": {
    "addr:full":"Korenbloemstr 6 Rosmalen Noord-Brabant 5241 BV",
    "addr:housenumber":"6",
    "addr:postcode":"5241 bv",
    "addr:street":"Korenbloemstr",
    "iso:country":"NL",
    "sg:address":"Korenbloemstr 6",
    "sg:city":"Rosmalen",
    "sg:orig_category":"Lasbedrijven",
    "sg:phone":"+31 6 22517540",
    "sg:postcode":"5241 BV",
    "sg:province":"Noord-Brabant",
    "wof:name":"Almilas",
    "wof:placetype":"venue"
},
  "geometry": {"coordinates":[5.357704,51.717384],"type":"Point"}
}