{
  "type": "Feature",
  "properties": {
    "addr:full":"Burgemeester Bootstraat 1 Varsseveld Gelderland 7051 BJ",
    "addr:housenumber":"1",
    "addr:postcode":"7051 bj",
    "addr:street":"Burgemeester Bootstraat;Gelderland",
    "iso:country":"NL",
    "sg:address":"Burgemeester Bootstraat 1",
    "sg:city":"Varsseveld",
    "sg:orig_category":"Boekhouders",
    "sg:phone":"+31 315 230 070",
    "sg:postcode":"7051 BJ",
    "sg:province":"Gelderland",
    "wof:name":"H.J. Ten Brinke Beheer Bv Administratie Kantoor",
    "wof:placetype":"venue"
},
  "geometry": {"coordinates":[6.457211,51.938747],"type":"Point"}
}