{
  "type": "Feature",
  "properties": {
    "addr:full":"Gemeentewg 40 Staphorst Overijssel 7951 CN",
    "addr:housenumber":"40",
    "addr:postcode":"7951 cn",
    "addr:street":"Gemeentewg",
    "iso:country":"NL",
    "sg:address":"Gemeentewg 40",
    "sg:city":"Staphorst",
    "sg:orig_category":"Koelkasten",
    "sg:phone":"+31 522 462 625",
    "sg:postcode":"7951 CN",
    "sg:province":"Overijssel",
    "wof:name":"Talen",
    "wof:placetype":"venue"
},
  "geometry": {"coordinates":[6.205218,52.644665],"type":"Point"}
}