{
  "type": "Feature",
  "properties": {
    "addr:full":"Postbus 335 Katwyk Zh South Holland 2220 AH",
    "addr:housenumber":"335;zh",
    "addr:postcode":"2220 ah",
    "addr:street":"Postbus",
    "iso:country":"NL",
    "sg:address":"Postbus 335",
    "sg:city":"Katwyk Zh",
    "sg:orig_category":"Verenigingen En Stichtingen",
    "sg:phone":"+31 71 403 0462",
    "sg:postcode":"2220 AH",
    "sg:province":"South Holland",
    "wof:name":"Katwijk Vv",
    "wof:placetype":"venue"
},
  "geometry": {"coordinates":[4.42057,52.187599],"type":"Point"}
}