{
  "type": "Feature",
  "properties": {
    "addr:full":"Oudlaan 40 Naaldwijk Zuid-Holland 2672 AN",
    "addr:housenumber":"40",
    "addr:postcode":"2672 an",
    "addr:street":"Oudlaan",
    "iso:country":"NL",
    "sg:address":"Oudlaan 40",
    "sg:city":"Naaldwijk",
    "sg:orig_category":"Metaalwerken",
    "sg:phone":"+31 174 627 116",
    "sg:postcode":"2672 AN",
    "sg:province":"Zuid-Holland",
    "wof:name":"J.P.A. Van Der Ven",
    "wof:placetype":"venue"
},
  "geometry": {"coordinates":[4.217135,51.996986],"type":"Point"}
}