{
  "type": "Feature",
  "properties": {
    "addr:full":"Kerkstraat 23 Groot Ammers Zuid-Holland 2964 BT",
    "addr:housenumber":"23",
    "addr:postcode":"2964 bt",
    "addr:street":"Kerkstraat;Groot Ammers",
    "iso:country":"NL",
    "sg:address":"Kerkstraat 23",
    "sg:city":"Groot Ammers",
    "sg:orig_category":"Kappers",
    "sg:phone":"+31 184 669 000",
    "sg:postcode":"2964 BT",
    "sg:province":"Zuid-Holland",
    "wof:name":"Kapsalon Nelleke Dames & Herenkapsalon",
    "wof:placetype":"venue"
},
  "geometry": {"coordinates":[4.8185629845,51.9230766296],"type":"Point"}
}