{
  "type": "Feature",
  "properties": {
    "iso:country":"NL",
    "sg:address":"Groenmarkt 153",
    "sg:city":"Dordrecht",
    "sg:orig_category":"Bibliotheken And Openbare Archieven",
    "sg:phone":"+31 78 613 0077",
    "sg:postcode":"3311 BD",
    "sg:province":"Zuid-Holland",
    "wof:name":"Stichting Verenigde Openbare Bibliotheken Dordrech",
    "wof:placetype":"venue"
},
  "geometry": {"coordinates":[4.664957,51.814449],"type":"Point"}
}