{
  "type": "Feature",
  "properties": {
    "iso:country":"NL",
    "sg:address":"F D Rooseveltln 24",
    "sg:city":"Eindhoven",
    "sg:orig_category":"Vertaalbureaus",
    "sg:phone":"+31 40 292 6532",
    "sg:postcode":"5625 PA",
    "sg:province":"Noord-Brabant",
    "wof:name":"Campman",
    "wof:placetype":"venue"
},
  "geometry": {"coordinates":[5.47419,51.471748],"type":"Point"}
}