{
  "type": "Feature",
  "properties": {
    "addr:full":"Dautzenbergstraat 39 Heerlen Limburg 6411 LA",
    "addr:housenumber":"39",
    "addr:postcode":"6411 la",
    "addr:street":"Dautzenbergstraat",
    "iso:country":"NL",
    "sg:address":"Dautzenbergstraat 39",
    "sg:city":"Heerlen",
    "sg:orig_category":"Damesmodezaken",
    "sg:phone":"+31 45 571 5806",
    "sg:postcode":"6411 LA",
    "sg:province":"Limburg",
    "wof:name":"Modehuis H.J. Teheux-Baks Bv",
    "wof:placetype":"venue"
},
  "geometry": {"coordinates":[5.977374,50.888245],"type":"Point"}
}