{
  "type": "Feature",
  "properties": {
    "iso:country":"NL",
    "sg:address":"Dreef 37",
    "sg:city":"Made",
    "sg:orig_category":"Geluidsinstallaties - Verhuur",
    "sg:phone":"+31 162 670 376",
    "sg:postcode":"4921 ZA",
    "sg:province":"Noord-Brabant",
    "wof:name":"Casey",
    "wof:placetype":"venue"
},
  "geometry": {"coordinates":[-119.86702699999999,36.934589],"type":"Point"}
}