{
  "type": "Feature",
  "properties": {
    "addr:full":"Amstelveensewg 282 Amsterdam Noord-Holland 1075 XW",
    "addr:housenumber":"282",
    "addr:postcode":"1075 xw",
    "iso:country":"NL",
    "sg:address":"Amstelveensewg 282",
    "sg:city":"Amsterdam",
    "sg:orig_category":"Zonnebank- En Solariumcentra",
    "sg:phone":"+31 20 662 9955",
    "sg:postcode":"1075 XW",
    "sg:province":"Noord-Holland",
    "wof:name":"Sarino",
    "wof:placetype":"venue"
},
  "geometry": {"coordinates":[4.857175,52.348324],"type":"Point"}
}