{
  "type": "Feature",
  "properties": {
    "iso:country":"NL",
    "sg:address":"Kampdykln 60",
    "sg:city":"Vught",
    "sg:orig_category":"Adviesbureaus Economie",
    "sg:phone":"+31 73 657 9363",
    "sg:postcode":"5263 CK",
    "sg:province":"Noord-Brabant",
    "wof:name":"Final Trust Financial Planning",
    "wof:placetype":"venue"
},
  "geometry": {"coordinates":[5.286228,51.669949],"type":"Point"}
}