{
  "type": "Feature",
  "properties": {
    "addr:full":"Klopschouw 8A Oss Virginia 5345 RL",
    "addr:housenumber":"8a",
    "addr:postcode":"5345 rl",
    "addr:street":"Klopschouw",
    "iso:country":"NL",
    "sg:address":"Klopschouw 8A",
    "sg:city":"Oss",
    "sg:orig_category":"Meubelen - Fabrieken En Groothandel",
    "sg:phone":"+31 412 627 951",
    "sg:postcode":"5345 RL",
    "sg:province":"Virginia",
    "wof:name":"Rowan, De",
    "wof:placetype":"venue"
},
  "geometry": {"coordinates":[-77.235214,38.312599],"type":"Point"}
}