{
  "type": "Feature",
  "properties": {
    "addr:full":"Roelenengwg 118 Voorthuizen Gelderland 3781 BD",
    "addr:housenumber":"118",
    "addr:postcode":"3781 bd",
    "addr:street":"Gelderland",
    "iso:country":"NL",
    "sg:address":"Roelenengwg 118",
    "sg:city":"Voorthuizen",
    "sg:orig_category":"Machinefabrieken",
    "sg:phone":"+31 342 492 620",
    "sg:postcode":"3781 BD",
    "sg:province":"Gelderland",
    "wof:name":"Solid Service",
    "wof:placetype":"venue"
},
  "geometry": {"coordinates":[5.615229,52.189693],"type":"Point"}
}