{
  "type": "Feature",
  "properties": {
    "addr:full":"Plevierwg 51 Apeldoorn Gelderland 7331 BZ",
    "addr:housenumber":"51",
    "addr:postcode":"7331 bz",
    "addr:street":"Plevierwg;Gelderland",
    "iso:country":"NL",
    "sg:address":"Plevierwg 51",
    "sg:city":"Apeldoorn",
    "sg:orig_category":"Autoreclame",
    "sg:phone":"+31 55 543 1197",
    "sg:postcode":"7331 BZ",
    "sg:province":"Gelderland",
    "sg:website":"http://come.to/airbrushing",
    "wof:name":"Mario",
    "wof:placetype":"venue"
},
  "geometry": {"coordinates":[5.9595,52.20084],"type":"Point"}
}