{
  "type": "Feature",
  "properties": {
    "iso:country":"NL",
    "sg:address":"Grindwg 200",
    "sg:city":"Scherpenzeel Fr",
    "sg:orig_category":"Fietsen En Bromfietsen Onderdelen - Fabr. En Grooth",
    "sg:phone":"+31 561 481 233",
    "sg:postcode":"8483 JK",
    "sg:province":"Friesland",
    "sg:website":"http://www.dutch-perfect.nl",
    "wof:name":"Hunneman Import Bv",
    "wof:placetype":"venue"
},
  "geometry": {"coordinates":[5.874874,52.832119],"type":"Point"}
}