{
  "type": "Feature",
  "properties": {
    "addr:full":"Wiidswal 2 Oudehaske Friesland 8465 PV",
    "addr:housenumber":"2",
    "addr:postcode":"8465 pv",
    "addr:street":"Wiidswal",
    "iso:country":"NL",
    "sg:address":"Wiidswal 2",
    "sg:city":"Oudehaske",
    "sg:orig_category":"Onderhoudswerken",
    "sg:phone":"+31 513 677 200",
    "sg:postcode":"8465 PV",
    "sg:province":"Friesland",
    "wof:name":"Oudehaske",
    "wof:placetype":"venue"
},
  "geometry": {"coordinates":[5.868465,52.956856],"type":"Point"}
}