{
  "type": "Feature",
  "properties": {
    "iso:country":"NL",
    "sg:address":"Balistraat 104",
    "sg:city":"Amsterdam",
    "sg:orig_category":"Politie",
    "sg:phone":"+31 900 8844",
    "sg:postcode":"1094 JT",
    "sg:province":"Noord-Holland",
    "wof:name":"Politie Amsterdam Amstelland Wijkteam Balistraat",
    "wof:placetype":"venue"
},
  "geometry": {"coordinates":[4.937115,52.363018],"type":"Point"}
}