{
  "type": "Feature",
  "properties": {
    "addr:full":"Lieshoutsedijk 29 Sint Oedenrode North Brabant 5491 RV",
    "addr:housenumber":"29",
    "addr:postcode":"5491 rv",
    "addr:street":"Lieshoutsedijk;Sint Oedenrode",
    "iso:country":"NL",
    "sg:address":"Lieshoutsedijk 29",
    "sg:city":"Sint Oedenrode",
    "sg:orig_category":"Metaalbekleding And -Behandeling",
    "sg:phone":"+31 413 475 391",
    "sg:postcode":"5491 RV",
    "sg:province":"North Brabant",
    "wof:name":"E.E.M. Van De Sande",
    "wof:placetype":"venue"
},
  "geometry": {"coordinates":[5.500307,51.568436],"type":"Point"}
}