{
  "type": "Feature",
  "properties": {
    "addr:full":"Landjuweel 12 Veenendaal Utrecht 3905 PG",
    "addr:housenumber":"12",
    "addr:postcode":"3905 pg",
    "addr:street":"Landjuweel",
    "iso:country":"NL",
    "sg:address":"Landjuweel 12",
    "sg:city":"Veenendaal",
    "sg:orig_category":"Projectontwikkeling",
    "sg:phone":"+31 318 524 141",
    "sg:postcode":"3905 PG",
    "sg:province":"Utrecht",
    "wof:name":"Midden Ned Bv",
    "wof:placetype":"venue"
},
  "geometry": {"coordinates":[5.551064,52.040394],"type":"Point"}
}