{
  "type": "Feature",
  "properties": {
    "iso:country":"NL",
    "sg:address":"A G Wyerswg 10",
    "sg:city":"Wekerom",
    "sg:orig_category":"Administratie- En Boekhoudkantoren",
    "sg:phone":"+31 318 461 686",
    "sg:postcode":"6733 AS",
    "sg:province":"Gelderland",
    "wof:name":"Janssen, D",
    "wof:placetype":"venue"
},
  "geometry": {"coordinates":[5.71421,52.111546],"type":"Point"}
}