{
  "type": "Feature",
  "properties": {
    "addr:full":"A G Wyerswg 10 Wekerom Gelderland 6733 AS",
    "addr:housenumber":"10",
    "addr:postcode":"6733 as",
    "addr:street":"A;Wyerswg;Gelderland",
    "iso:country":"NL",
    "sg:address":"A G Wyerswg 10",
    "sg:city":"Wekerom",
    "sg:orig_category":"Administratie- En Boekhoudkantoren",
    "sg:phone":"+31 318 461 686",
    "sg:postcode":"6733 AS",
    "sg:province":"Gelderland",
    "wof:name":"Janssen, D",
    "wof:placetype":"venue"
},
  "geometry": {"coordinates":[5.71421,52.111546],"type":"Point"}
}