{
  "type": "Feature",
  "properties": {
    "iso:country":"NL",
    "sg:address":"Touwbaan 67",
    "sg:city":"Vlaardingen",
    "sg:orig_category":"Waterbehandeling En Waterzuiverings- Systemen",
    "sg:phone":"+31 10 435 0250",
    "sg:postcode":"3134 MD",
    "sg:province":"South Holland",
    "wof:name":"Aqua Best",
    "wof:placetype":"venue"
},
  "geometry": {"coordinates":[4.3500452042,51.9058494568],"type":"Point"}
}