{
  "type": "Feature",
  "properties": {
    "iso:country":"NL",
    "sg:address":"Valkeniersngl 73",
    "sg:city":"Rosmalen",
    "sg:orig_category":"Autorijscholen",
    "sg:phone":"+31 73 612 4747",
    "sg:postcode":"5241 JD",
    "sg:province":"Noord-Brabant",
    "wof:name":"Hazendonk, Verkeersschool Van",
    "wof:placetype":"venue"
},
  "geometry": {"coordinates":[5.364569,51.718582],"type":"Point"}
}