{
  "type": "Feature",
  "properties": {
    "addr:full":"De Hoefsmid 13 Heiloo Noord-Holland 1851 PZ",
    "addr:housenumber":"13",
    "addr:postcode":"1851 pz",
    "addr:street":"De Hoefsmid",
    "iso:country":"NL",
    "sg:address":"De Hoefsmid 13",
    "sg:city":"Heiloo",
    "sg:orig_category":"Fotostudio'S And Fotografen",
    "sg:phone":"+31 72 532 0500",
    "sg:postcode":"1851 PZ",
    "sg:province":"Noord-Holland",
    "wof:name":"Foto En Grafi Beeldvisie",
    "wof:placetype":"venue"
},
  "geometry": {"coordinates":[4.71765,52.592136],"type":"Point"}
}