{
  "type": "Feature",
  "properties": {
    "iso:country":"NL",
    "sg:address":"Marconistr 7C",
    "sg:city":"Tiel",
    "sg:orig_category":"Houtgroothandel",
    "sg:phone":"+31 344 613 957",
    "sg:postcode":"4004 JM",
    "sg:province":"Gelderland",
    "sg:website":"http://www.debetuwe.net",
    "wof:name":"Betuwe, De",
    "wof:placetype":"venue"
},
  "geometry": {"coordinates":[5.433836,51.906242],"type":"Point"}
}