{
  "type": "Feature",
  "properties": {
    "addr:full":"Hogenkampseweg 26 Renkum Gelderland 6871 JP",
    "addr:housenumber":"26",
    "addr:postcode":"6871 jp",
    "addr:street":"Hogenkampseweg;Gelderland",
    "iso:country":"NL",
    "sg:address":"Hogenkampseweg 26",
    "sg:city":"Renkum",
    "sg:orig_category":"Verhuur Audiovisuele Apparatuur",
    "sg:phone":"+31 317 312 332",
    "sg:postcode":"6871 JP",
    "sg:province":"Gelderland",
    "wof:name":"Wavru",
    "wof:placetype":"venue"
},
  "geometry": {"coordinates":[5.734288,51.97908],"type":"Point"}
}