{
  "type": "Feature",
  "properties": {
    "addr:full":"Handelswg 33-35 Westknollendam Noord-Holland 1525 RG",
    "addr:housenumber":"33-35",
    "addr:postcode":"1525 rg",
    "addr:street":"Westknollendam",
    "iso:country":"NL",
    "sg:address":"Handelswg 33-35",
    "sg:city":"Westknollendam",
    "sg:orig_category":"Bedrijfsmechanisatie En -Automatisering",
    "sg:phone":"+31 75 616 9077",
    "sg:postcode":"1525 RG",
    "sg:province":"Noord-Holland",
    "wof:name":"Compulutions Bv",
    "wof:placetype":"venue"
},
  "geometry": {"coordinates":[4.777844,52.516209],"type":"Point"}
}