{
  "type": "Feature",
  "properties": {
    "addr:full":"Moerheimstraat 78 Dedemsvaart NL.08 7701 CG",
    "addr:housenumber":"78;nl.08",
    "addr:postcode":"7701 cg",
    "addr:street":"Moerheimstraat",
    "iso:country":"NL",
    "sg:address":"Moerheimstraat 78",
    "sg:city":"Dedemsvaart",
    "sg:orig_category":"Bloemen And Planten",
    "sg:phone":"+31 523 612 345",
    "sg:postcode":"7701 CG",
    "sg:province":"NL.08",
    "wof:name":"Moerheim Plantenwinkel",
    "wof:placetype":"venue"
},
  "geometry": {"coordinates":[6.464305,52.600727],"type":"Point"}
}