{
  "type": "Feature",
  "properties": {
    "addr:full":"Stationswg 72 Maasbracht Limburg 6051 KL",
    "addr:housenumber":"72",
    "addr:postcode":"6051 kl",
    "addr:street":"Stationswg",
    "iso:country":"NL",
    "sg:address":"Stationswg 72",
    "sg:city":"Maasbracht",
    "sg:orig_category":"Bloemen En Planten",
    "sg:phone":"+31 475 465 793",
    "sg:postcode":"6051 KL",
    "sg:province":"Limburg",
    "wof:name":"Linssen, Fa",
    "wof:placetype":"venue"
},
  "geometry": {"coordinates":[5.918426,51.144711],"type":"Point"}
}