{
  "type": "Feature",
  "properties": {
    "iso:country":"NL",
    "sg:address":"Bornhemweg 2",
    "sg:city":"Oudenbosch",
    "sg:classifiers":[
        {
            "category":"Shopping",
            "subcategory":"Bicycles & Sporting Goods",
            "type":"Retail Goods"
        }
    ],
    "sg:phone":"+31 165 313 707",
    "sg:postcode":"4731 KD",
    "sg:province":"Noord-Brabant",
    "sg:tags":[
        "sport-",
        "kampeerartikelen"
    ],
    "wof:name":"Vof Octopus",
    "wof:placetype":"venue"
},
  "geometry": {"coordinates":[4.530801,51.59129],"type":"Point"}
}