{
  "type": "Feature",
  "properties": {
    "addr:full":"Selenakker 30 Tilburg Noord-Brabant 5047 TP",
    "addr:housenumber":"30",
    "addr:postcode":"5047 tp",
    "addr:street":"Selenakker",
    "iso:country":"NL",
    "sg:address":"Selenakker 30",
    "sg:city":"Tilburg",
    "sg:orig_category":"Verhuur",
    "sg:phone":"+31 13 572 1366",
    "sg:postcode":"5047 TP",
    "sg:province":"Noord-Brabant",
    "sg:website":"http://www.boels.nl",
    "wof:name":"Boels Tilburg",
    "wof:placetype":"venue"
},
  "geometry": {"coordinates":[5.028538,51.588966],"type":"Point"}
}