{
  "type": "Feature",
  "properties": {
    "addr:full":"Van Bronckhorststraat 1 Heemskerk Noord-Holland 1962 TV",
    "addr:housenumber":"1",
    "addr:postcode":"1962 tv",
    "addr:street":"Van Bronckhorststraat",
    "iso:country":"NL",
    "sg:address":"Van Bronckhorststraat 1",
    "sg:city":"Heemskerk",
    "sg:orig_category":"Kinderopvang Behalve Thuis",
    "sg:phone":"+31 251 253 054",
    "sg:postcode":"1962 TV",
    "sg:province":"Noord-Holland",
    "wof:name":"Naschoolse Opvang Het Vogelnest",
    "wof:placetype":"venue"
},
  "geometry": {"coordinates":[4.684505,52.510342],"type":"Point"}
}