{
  "type": "Feature",
  "properties": {
    "addr:full":"V Stuartln 21 Ryswyk Zh Zuid-Holland 2288 EK",
    "addr:housenumber":"21",
    "addr:postcode":"2288 ek",
    "addr:street":"Ryswyk",
    "iso:country":"NL",
    "sg:address":"V Stuartln 21",
    "sg:city":"Ryswyk Zh",
    "sg:orig_category":"Knipseldiensten",
    "sg:phone":"+31 70 309 7242",
    "sg:postcode":"2288 EK",
    "sg:province":"Zuid-Holland",
    "sg:website":"http://www.antal-clipping.nl",
    "wof:name":"Antal Clipping Bv",
    "wof:placetype":"venue"
},
  "geometry": {"coordinates":[4.32436,52.037251],"type":"Point"}
}