{
  "type": "Feature",
  "properties": {
    "addr:full":"Leliestr 8 Lisse Zuid-Holland 2161 XK",
    "addr:housenumber":"8",
    "addr:postcode":"2161 xk",
    "addr:street":"Leliestr",
    "iso:country":"NL",
    "sg:address":"Leliestr 8",
    "sg:city":"Lisse",
    "sg:orig_category":"Parketvloeren",
    "sg:phone":"+31 252 428 010",
    "sg:postcode":"2161 XK",
    "sg:province":"Zuid-Holland",
    "wof:name":"Meskers Vof",
    "wof:placetype":"venue"
},
  "geometry": {"coordinates":[4.563311,52.256359],"type":"Point"}
}