{
  "type": "Feature",
  "properties": {
    "addr:full":"Vryburgln 39 Uitgeest Noord-Holland 1911 SE",
    "addr:housenumber":"39",
    "addr:postcode":"1911 se",
    "addr:street":"Vryburgln",
    "iso:country":"NL",
    "sg:address":"Vryburgln 39",
    "sg:city":"Uitgeest",
    "sg:orig_category":"Schilders",
    "sg:phone":"+31 251 320 409",
    "sg:postcode":"1911 SE",
    "sg:province":"Noord-Holland",
    "wof:name":"Cor Zeeuw",
    "wof:placetype":"venue"
},
  "geometry": {"coordinates":[4.705775,52.528172],"type":"Point"}
}