{
  "type": "Feature",
  "properties": {
    "addr:full":"Lindsterln 46 Marum Groningen 9363 XB",
    "addr:housenumber":"46",
    "addr:postcode":"9363 xb",
    "addr:street":"Lindsterln",
    "iso:country":"NL",
    "sg:address":"Lindsterln 46",
    "sg:city":"Marum",
    "sg:orig_category":"Arbo- En Bedrijfsgezondheids- Diensten",
    "sg:phone":"+31 594 643 733",
    "sg:postcode":"9363 XB",
    "sg:province":"Groningen",
    "wof:name":"Interventie",
    "wof:placetype":"venue"
},
  "geometry": {"coordinates":[6.268128,53.137589],"type":"Point"}
}