{
  "type": "Feature",
  "properties": {
    "addr:full":"Elzenhof 22 Zoeterwoude Zuid-Holland 2382 EV",
    "addr:housenumber":"22",
    "addr:postcode":"2382 ev",
    "addr:street":"Elzenhof",
    "iso:country":"NL",
    "sg:address":"Elzenhof 22",
    "sg:city":"Zoeterwoude",
    "sg:classifiers":[
        {
            "category":"Utilities",
            "subcategory":"Cable",
            "type":"Services"
        }
    ],
    "sg:phone":"+31 71 589 4446",
    "sg:postcode":"2382 EV",
    "sg:province":"Zuid-Holland",
    "sg:tags":[
        "masseur",
        "en",
        "heilgymnasten"
    ],
    "sg:website":"http://www.welcome-massage.nl",
    "wof:name":"Welcome Massagepraktijk",
    "wof:placetype":"venue"
},
  "geometry": {"coordinates":[4.520824,52.142563],"type":"Point"}
}