{
  "type": "Feature",
  "properties": {
    "addr:full":"Rechte Zandwg 26A Dordrecht South Holland 3319 GR",
    "addr:housenumber":"26a",
    "addr:postcode":"3319",
    "addr:street":"Zandwg",
    "iso:country":"NL",
    "sg:address":"Rechte Zandwg 26A",
    "sg:city":"Dordrecht",
    "sg:orig_category":"Kappers",
    "sg:phone":"+31 78 616 1871",
    "sg:postcode":"3319 GR",
    "sg:province":"South Holland",
    "wof:name":"Frederique Intercoiffure",
    "wof:placetype":"venue"
},
  "geometry": {"coordinates":[4.7052221298,51.7958641052],"type":"Point"}
}