{
  "type": "Feature",
  "properties": {
    "addr:full":"Bronkhorststr 43-45 Leiden Zuid-Holland 2316 SZ",
    "addr:housenumber":"43-45",
    "addr:postcode":"2316 sz",
    "iso:country":"NL",
    "sg:address":"Bronkhorststr 43-45",
    "sg:city":"Leiden",
    "sg:orig_category":"Artsen - Huisartsen",
    "sg:phone":"+31 71 521 2025",
    "sg:postcode":"2316 SZ",
    "sg:province":"Zuid-Holland",
    "wof:name":"Bakker, M",
    "wof:placetype":"venue"
},
  "geometry": {"coordinates":[4.496218,52.165337],"type":"Point"}
}