{
  "type": "Feature",
  "properties": {
    "addr:full":"Zeedk 17 Dordrecht Zuid-Holland 3329 LC",
    "addr:housenumber":"17",
    "addr:postcode":"3329 lc",
    "addr:street":"Zeedk",
    "iso:country":"NL",
    "sg:address":"Zeedk 17",
    "sg:city":"Dordrecht",
    "sg:orig_category":"Sportverenigingen En Ontspannings- Verenigingen",
    "sg:phone":"+31 78 621 0705",
    "sg:postcode":"3329 LC",
    "sg:province":"Zuid-Holland",
    "wof:name":"Dajaks Kano-Ver",
    "wof:placetype":"venue"
},
  "geometry": {"coordinates":[4.757092,51.790367],"type":"Point"}
}