{
  "type": "Feature",
  "properties": {
    "addr:full":"Zandsestr 11 Bemmel Gelderland 6681 KB",
    "addr:housenumber":"11",
    "addr:postcode":"6681 kb",
    "addr:street":"Zandsestr;Gelderland",
    "iso:country":"NL",
    "sg:address":"Zandsestr 11",
    "sg:city":"Bemmel",
    "sg:orig_category":"Bloemen En Planten - Groothandel",
    "sg:phone":"+31 481 450 545",
    "sg:postcode":"6681 KB",
    "sg:province":"Gelderland",
    "wof:name":"Hendriks Cv, G J",
    "wof:placetype":"venue"
},
  "geometry": {"coordinates":[5.880128,51.881622],"type":"Point"}
}