{
  "type": "Feature",
  "properties": {
    "addr:full":"Kooikersweg 7 Grave Louisiana 5361 VA",
    "addr:housenumber":"7",
    "addr:postcode":"5361",
    "addr:street":"Kooikersweg;Louisiana",
    "iso:country":"NL",
    "sg:address":"Kooikersweg 7",
    "sg:city":"Grave",
    "sg:orig_category":"Glaszetten",
    "sg:phone":"+31 486 477 600",
    "sg:postcode":"5361 VA",
    "sg:province":"Louisiana",
    "wof:name":"Derks Schilders Bv",
    "wof:placetype":"venue"
},
  "geometry": {"coordinates":[-92.151741,32.929253],"type":"Point"}
}