{
  "type": "Feature",
  "properties": {
    "iso:country":"NL",
    "sg:address":"Apeldoornseln 318",
    "sg:city":"S Gravenhage",
    "sg:orig_category":"Opticiens",
    "sg:phone":"+31 70 364 8113",
    "sg:postcode":"2573 LZ",
    "sg:province":"Zuid-Holland",
    "wof:name":"Optiek In",
    "wof:placetype":"venue"
},
  "geometry": {"coordinates":[4.2843999863,52.0649108887],"type":"Point"}
}