{
  "type": "Feature",
  "properties": {
    "addr:full":"Netwerk 59 Purmerend North Holland 1446 WS",
    "addr:housenumber":"59",
    "addr:postcode":"1446 ws",
    "addr:street":"Netwerk",
    "iso:country":"NL",
    "sg:address":"Netwerk 59",
    "sg:city":"Purmerend",
    "sg:orig_category":"Metaalwerken",
    "sg:phone":"+31 299 460 445",
    "sg:postcode":"1446 WS",
    "sg:province":"North Holland",
    "wof:name":"Glasfolie Suncontrol Bv",
    "wof:placetype":"venue"
},
  "geometry": {"coordinates":[5.00376,52.51133],"type":"Point"}
}