{
  "type": "Feature",
  "properties": {
    "iso:country":"NL",
    "sg:address":"Rechtstr 89B",
    "sg:city":"Maastricht",
    "sg:orig_category":"Banken",
    "sg:phone":"+31 43 350 0885",
    "sg:postcode":"6221 EH",
    "sg:province":"Limburg",
    "wof:name":"Fgh Nv",
    "wof:placetype":"venue"
},
  "geometry": {"coordinates":[5.698502,50.847664],"type":"Point"}
}