{
  "type": "Feature",
  "properties": {
    "iso:country":"NL",
    "sg:address":"Breeweer 3",
    "sg:city":"Ouderkerk Ad Yssel",
    "sg:orig_category":"Montagebedrijven",
    "sg:phone":"+31 180 681 410",
    "sg:postcode":"2935 CA",
    "sg:province":"Zuid-Holland",
    "wof:name":"Boer, R",
    "wof:placetype":"venue"
},
  "geometry": {"coordinates":[4.642139,51.965771],"type":"Point"}
}