{
  "type": "Feature",
  "properties": {
    "addr:full":"Flevolaan 39 Huizen Noord-Holland 1272 PB",
    "addr:housenumber":"39",
    "addr:postcode":"1272 pb",
    "addr:street":"Flevolaan",
    "iso:country":"NL",
    "sg:address":"Flevolaan 39",
    "sg:city":"Huizen",
    "sg:orig_category":"Zalenexploitatie",
    "sg:phone":"+31 35 692 0790",
    "sg:postcode":"1272 PB",
    "sg:province":"Noord-Holland",
    "wof:name":"De Plankeniers",
    "wof:placetype":"venue"
},
  "geometry": {"coordinates":[5.196223,52.288666],"type":"Point"}
}