{
  "type": "Feature",
  "properties": {
    "addr:full":"Duinwg 32 Noordwyk Zh Zuid-Holland 2204 AV",
    "addr:housenumber":"32",
    "addr:postcode":"2204 av",
    "addr:street":"Duinwg",
    "iso:country":"NL",
    "sg:address":"Duinwg 32",
    "sg:city":"Noordwyk Zh",
    "sg:orig_category":"Bloemen En Planten - Groothandel",
    "sg:phone":"+31 71 361 0993",
    "sg:postcode":"2204 AV",
    "sg:province":"Zuid-Holland",
    "wof:name":"Baduplant Bv",
    "wof:placetype":"venue"
},
  "geometry": {"coordinates":[4.4477,52.234261],"type":"Point"}
}