{
  "type": "Feature",
  "properties": {
    "addr:full":"Zeilmakerstr 17 Assen Drenthe 9403 VA",
    "addr:housenumber":"17",
    "addr:postcode":"9403",
    "addr:street":"Zeilmakerstr",
    "iso:country":"NL",
    "sg:address":"Zeilmakerstr 17",
    "sg:city":"Assen",
    "sg:orig_category":"Schilders",
    "sg:phone":"+31 592 372 888",
    "sg:postcode":"9403 VA",
    "sg:province":"Drenthe",
    "wof:name":"Dijkstra Assen Bv",
    "wof:placetype":"venue"
},
  "geometry": {"coordinates":[6.578604,53.012138],"type":"Point"}
}