{
  "type": "Feature",
  "properties": {
    "addr:full":"Stobbenbroekerweg 16 Raalte Overijssel 8101 NT",
    "addr:housenumber":"16",
    "addr:postcode":"8101 nt",
    "addr:street":"Stobbenbroekerweg",
    "iso:country":"NL",
    "sg:address":"Stobbenbroekerweg 16",
    "sg:city":"Raalte",
    "sg:orig_category":"Huizensloop And Bouwrijp Maken",
    "sg:phone":"+31 572 352 250",
    "sg:postcode":"8101 NT",
    "sg:province":"Overijssel",
    "wof:name":"Hoogeboom Raalte Bv",
    "wof:placetype":"venue"
},
  "geometry": {"coordinates":[6.2515,52.397266],"type":"Point"}
}