{
  "type": "Feature",
  "properties": {
    "iso:country":"NL",
    "sg:address":"Tenelenwg 28",
    "sg:city":"Voerendaal",
    "sg:orig_category":"Kinderkleding",
    "sg:phone":"+31 45 575 1112",
    "sg:postcode":"6367 VV",
    "sg:province":"Limburg",
    "wof:name":"Oki Doki",
    "wof:placetype":"venue"
},
  "geometry": {"coordinates":[5.924097,50.882919],"type":"Point"}
}