{
  "type": "Feature",
  "properties": {
    "addr:full":"Voetboogstr 63Hg Amsterdam North Holland 1012 XL",
    "addr:postcode":"1012 xl",
    "iso:country":"NL",
    "sg:address":"Voetboogstr 63Hg",
    "sg:city":"Amsterdam",
    "sg:orig_category":"Webdesign Bureaus",
    "sg:phone":"+31 20 428 1660",
    "sg:postcode":"1012 XL",
    "sg:province":"North Holland",
    "wof:name":"Spoorenberg Com",
    "wof:placetype":"venue"
},
  "geometry": {"coordinates":[4.8910398483,52.3677597046],"type":"Point"}
}