{
  "type": "Feature",
  "properties": {
    "addr:full":"G J Van Heekstr 237 Enschede NL.08 7521 EE",
    "addr:housenumber":"237",
    "addr:postcode":"7521 ee",
    "addr:street":"G J",
    "iso:country":"NL",
    "sg:address":"G J Van Heekstr 237",
    "sg:city":"Enschede",
    "sg:orig_category":"Cafetaria'S",
    "sg:phone":"+31 53 433 2194",
    "sg:postcode":"7521 EE",
    "sg:province":"NL.08",
    "wof:name":"Twekkelerveld",
    "wof:placetype":"venue"
},
  "geometry": {"coordinates":[6.858663,52.229443],"type":"Point"}
}