{
  "type": "Feature",
  "properties": {
    "iso:country":"NL",
    "sg:address":"Kerkbuurt 156",
    "sg:city":"Sliedrecht",
    "sg:orig_category":"Verenigingen En Stichtingen",
    "sg:phone":"+31 184 412 510",
    "sg:postcode":"3361 BM",
    "sg:province":"Zuid-Holland",
    "wof:name":"Crescendo",
    "wof:placetype":"venue"
},
  "geometry": {"coordinates":[4.770646,51.822552],"type":"Point"}
}