{
  "type": "Feature",
  "properties": {
    "addr:full":"Kleiwegstr 24 Gouda South Holland 2801 GM",
    "addr:housenumber":"24",
    "addr:postcode":"2801 gm",
    "addr:street":"Kleiwegstr",
    "iso:country":"NL",
    "sg:address":"Kleiwegstr 24",
    "sg:city":"Gouda",
    "sg:orig_category":"Verf En Lak",
    "sg:phone":"+31 182 516 252",
    "sg:postcode":"2801 GM",
    "sg:province":"South Holland",
    "wof:name":"Natte, Henk",
    "wof:placetype":"venue"
},
  "geometry": {"coordinates":[4.708815,52.014103],"type":"Point"}
}