{
  "type": "Feature",
  "properties": {
    "iso:country":"NL",
    "sg:address":"Kleiwegstr 24",
    "sg:city":"Gouda",
    "sg:orig_category":"Verf En Lak",
    "sg:phone":"+31 182 516 252",
    "sg:postcode":"2801 GM",
    "sg:province":"South Holland",
    "wof:name":"Natte, Henk",
    "wof:placetype":"venue"
},
  "geometry": {"coordinates":[4.708815,52.014103],"type":"Point"}
}