{
  "type": "Feature",
  "properties": {
    "addr:full":"Brusselsestr 148 Maastricht Limburg 6211 PJ",
    "addr:housenumber":"148",
    "addr:postcode":"6211 pj",
    "iso:country":"NL",
    "sg:address":"Brusselsestr 148",
    "sg:city":"Maastricht",
    "sg:orig_category":"Kantoor- En Bedrijfsmeubelen",
    "sg:phone":"+31 43 325 7600",
    "sg:postcode":"6211 PJ",
    "sg:province":"Limburg",
    "wof:name":"Manderveld Bv",
    "wof:placetype":"venue"
},
  "geometry": {"coordinates":[5.6788787842,50.8496208191],"type":"Point"}
}