{
  "type": "Feature",
  "properties": {
    "addr:full":"Collendoorn 11 Losser NL.08 7581 RH",
    "addr:housenumber":"11;nl.08",
    "addr:postcode":"7581 rh",
    "addr:street":"Collendoorn",
    "iso:country":"NL",
    "sg:address":"Collendoorn 11",
    "sg:city":"Losser",
    "sg:orig_category":"Bedrijfskleding",
    "sg:phone":"+31 53 434 9088",
    "sg:postcode":"7581 RH",
    "sg:province":"NL.08",
    "wof:name":"J En B",
    "wof:placetype":"venue"
},
  "geometry": {"coordinates":[7.002397,52.270836],"type":"Point"}
}