{
  "type": "Feature",
  "properties": {
    "addr:full":"Korenmolenwg 35 Bleiswyk South Holland 2665 CH",
    "addr:housenumber":"35",
    "addr:postcode":"2665",
    "addr:street":"Korenmolenwg",
    "iso:country":"NL",
    "sg:address":"Korenmolenwg 35",
    "sg:city":"Bleiswyk",
    "sg:orig_category":"Autorijscholen",
    "sg:phone":"+31 10 521 7003",
    "sg:postcode":"2665 CH",
    "sg:province":"South Holland",
    "wof:name":"Kerklaan, H",
    "wof:placetype":"venue"
},
  "geometry": {"coordinates":[4.542118,52.016075],"type":"Point"}
}