{
  "type": "Feature",
  "properties": {
    "addr:full":"V Myrlaerstr 34 Meerlo Limburg 5864 BN",
    "addr:housenumber":"34",
    "addr:postcode":"5864 bn",
    "iso:country":"NL",
    "sg:address":"V Myrlaerstr 34",
    "sg:city":"Meerlo",
    "sg:orig_category":"Verpakkingsmachines",
    "sg:phone":"+31 478 690 990",
    "sg:postcode":"5864 BN",
    "sg:province":"Limburg",
    "wof:name":"Meepak",
    "wof:placetype":"venue"
},
  "geometry": {"coordinates":[6.087518,51.513844],"type":"Point"}
}