{
  "type": "Feature",
  "properties": {
    "addr:full":"Bergsestr 3 Huybergen Noord-Brabant 4635 BS",
    "addr:housenumber":"3",
    "addr:postcode":"4635 bs",
    "addr:street":"Bergsestr",
    "iso:country":"NL",
    "sg:address":"Bergsestr 3",
    "sg:city":"Huybergen",
    "sg:orig_category":"Kappers",
    "sg:phone":"+31 164 643 080",
    "sg:postcode":"4635 BS",
    "sg:province":"Noord-Brabant",
    "wof:name":"Pascal",
    "wof:placetype":"venue"
},
  "geometry": {"coordinates":[4.37635,51.433132],"type":"Point"}
}