{
  "type": "Feature",
  "properties": {
    "iso:country":"NL",
    "sg:address":"Spoorln 10",
    "sg:city":"Capelle Ad Yssel",
    "sg:orig_category":"Artiesten/Gezelschappen",
    "sg:phone":"+31 10 458 0853",
    "sg:postcode":"2908 BG",
    "sg:province":"Zuid-Holland",
    "sg:website":"http://home.planet.nl/~think.twice",
    "wof:name":"Twice",
    "wof:placetype":"venue"
},
  "geometry": {"coordinates":[4.5846,51.923401],"type":"Point"}
}