{
  "type": "Feature",
  "properties": {
    "addr:full":"Bolscher Landen 25 Bornerbroek Overijssel 7627 NP",
    "addr:housenumber":"25",
    "addr:postcode":"7627 np",
    "addr:street":"Bolscher Landen",
    "iso:country":"NL",
    "sg:address":"Bolscher Landen 25",
    "sg:city":"Bornerbroek",
    "sg:orig_category":"Granen, Zaden And Diervoeders Gh",
    "sg:phone":"+31 74 384 1693",
    "sg:postcode":"7627 NP",
    "sg:province":"Overijssel",
    "wof:name":"W.H.M. Zegger",
    "wof:placetype":"venue"
},
  "geometry": {"coordinates":[6.670556,52.311077],"type":"Point"}
}