{
  "type": "Feature",
  "properties": {
    "iso:country":"NL",
    "sg:address":"Hofstr 13",
    "sg:city":"Aalten",
    "sg:orig_category":"Notarissen En Notariskantoren",
    "sg:phone":"+31 543 474 468",
    "sg:postcode":"7121 DM",
    "sg:province":"Gelderland",
    "wof:name":"Mulder & Brinkman, Notarispraktijk",
    "wof:placetype":"venue"
},
  "geometry": {"coordinates":[6.584145,51.926159],"type":"Point"}
}