{
  "type": "Feature",
  "properties": {
    "addr:full":"Klimopstraat 48 'S Gravenhage South Holland 2565 VK",
    "addr:housenumber":"48",
    "addr:postcode":"2565 vk",
    "addr:street":"Klimopstraat;' S Gravenhage",
    "iso:country":"NL",
    "sg:address":"Klimopstraat 48",
    "sg:city":"'S Gravenhage",
    "sg:orig_category":"Woningbouwverenigingen",
    "sg:phone":"+31 70 356 1753",
    "sg:postcode":"2565 VK",
    "sg:province":"South Holland",
    "wof:name":"Coop Woningbouwver Tuinstadwyk Daal & Be",
    "wof:placetype":"venue"
},
  "geometry": {"coordinates":[4.2617540359,52.0762252808],"type":"Point"}
}