{
  "type": "Feature",
  "properties": {
    "addr:full":"Hobbe Van Baerdtstraat 6 Joure Provincie Friesland 8501 CX",
    "addr:housenumber":"6",
    "addr:postcode":"8501 cx",
    "addr:street":"Hobbe Van Baerdtstraat;Provincie Friesland",
    "iso:country":"NL",
    "sg:address":"Hobbe Van Baerdtstraat 6",
    "sg:city":"Joure",
    "sg:orig_category":"Fitnesscentra",
    "sg:phone":"+31 513 417 566",
    "sg:postcode":"8501 CX",
    "sg:province":"Provincie Friesland",
    "wof:name":"Sportschool Keep Fit",
    "wof:placetype":"venue"
},
  "geometry": {"coordinates":[5.794034,52.96751],"type":"Point"}
}