{
  "type": "Feature",
  "properties": {
    "addr:full":"Galery 1 Beuningen Gld Gelderland 6641 PA",
    "addr:housenumber":"1",
    "addr:postcode":"6641 pa",
    "addr:street":"Galery",
    "iso:country":"NL",
    "sg:address":"Galery 1",
    "sg:city":"Beuningen Gld",
    "sg:orig_category":"Loodgieters",
    "sg:phone":"+31 24 675 0770",
    "sg:postcode":"6641 PA",
    "sg:province":"Gelderland",
    "wof:name":"Sommeren, J Van",
    "wof:placetype":"venue"
},
  "geometry": {"coordinates":[5.76956,51.85955],"type":"Point"}
}