{
  "type": "Feature",
  "properties": {
    "addr:full":"Tjalk 45 Schipluiden Zuid-Holland 2636 DA",
    "addr:housenumber":"45",
    "addr:postcode":"2636 da",
    "addr:street":"Tjalk",
    "iso:country":"NL",
    "sg:address":"Tjalk 45",
    "sg:city":"Schipluiden",
    "sg:orig_category":"Administratie- En Boekhoudkantoren",
    "sg:phone":"+31 15 380 8072",
    "sg:postcode":"2636 DA",
    "sg:province":"Zuid-Holland",
    "wof:name":"Bol Bv, T",
    "wof:placetype":"venue"
},
  "geometry": {"coordinates":[4.312383,51.97823],"type":"Point"}
}