{
  "type": "Feature",
  "properties": {
    "addr:full":"Landsteinerhof 60 Hoogeveen Drenthe 7908 BC",
    "addr:housenumber":"60",
    "addr:postcode":"7908 bc",
    "addr:street":"Landsteinerhof",
    "iso:country":"NL",
    "sg:address":"Landsteinerhof 60",
    "sg:city":"Hoogeveen",
    "sg:orig_category":"Verenigingen En Stichtingen",
    "sg:phone":"+31 528 268 924",
    "sg:postcode":"7908 BC",
    "sg:province":"Drenthe",
    "wof:name":"Rover Reizigersver",
    "wof:placetype":"venue"
},
  "geometry": {"coordinates":[6.455223,52.721737],"type":"Point"}
}