{
  "type": "Feature",
  "properties": {
    "addr:full":"Stapelovenwg 4 Helmond North Brabant 5708 JW",
    "addr:housenumber":"4",
    "addr:postcode":"5708 jw",
    "addr:street":"Stapelovenwg",
    "iso:country":"NL",
    "sg:address":"Stapelovenwg 4",
    "sg:city":"Helmond",
    "sg:orig_category":"Kappersbenodigdheden",
    "sg:phone":"+31 492 590 401",
    "sg:postcode":"5708 JW",
    "sg:province":"North Brabant",
    "wof:name":"Hair Mission Ned Bv",
    "wof:placetype":"venue"
},
  "geometry": {"coordinates":[5.627897,51.476231],"type":"Point"}
}