{
  "type": "Feature",
  "properties": {
    "addr:full":"Zadelmaker 58 Alphen A/D Rijn Zuid-Holland 2401 PH",
    "addr:housenumber":"58;2401",
    "addr:street":"Zadelmaker",
    "iso:country":"NL",
    "sg:address":"Zadelmaker 58",
    "sg:city":"Alphen A/D Rijn",
    "sg:orig_category":"Goederenvervoer Over De Weg",
    "sg:phone":"+31 172 419 093",
    "sg:postcode":"2401 PH",
    "sg:province":"Zuid-Holland",
    "wof:name":"U & U Transport",
    "wof:placetype":"venue"
},
  "geometry": {"coordinates":[4.653874,52.154514],"type":"Point"}
}