{
  "type": "Feature",
  "properties": {
    "addr:full":"Kasteel Stapelenstraat 2 Tilburg Noord-Brabant 5037 HR",
    "addr:housenumber":"2",
    "addr:postcode":"5037 hr",
    "addr:street":"Kasteel Stapelenstraat",
    "iso:country":"NL",
    "sg:address":"Kasteel Stapelenstraat 2",
    "sg:city":"Tilburg",
    "sg:orig_category":"Verzekeringen",
    "sg:phone":"+31 13 467 2851",
    "sg:postcode":"5037 HR",
    "sg:province":"Noord-Brabant",
    "wof:name":"Schol, Roerend En Onroerend Goed Service",
    "wof:placetype":"venue"
},
  "geometry": {"coordinates":[5.049387,51.560673],"type":"Point"}
}