{
  "type": "Feature",
  "properties": {
    "addr:full":"Markt 35 Panningen Limburg 5981 AP",
    "addr:housenumber":"35",
    "addr:postcode":"5981 ap",
    "addr:street":"Markt",
    "iso:country":"NL",
    "sg:address":"Markt 35",
    "sg:city":"Panningen",
    "sg:orig_category":"Administratie- En Boekhoudkantoren",
    "sg:phone":"+31 77 307 1791",
    "sg:postcode":"5981 AP",
    "sg:province":"Limburg",
    "wof:name":"Leenders",
    "wof:placetype":"venue"
},
  "geometry": {"coordinates":[5.981042,51.328899],"type":"Point"}
}