{
  "type": "Feature",
  "properties": {
    "addr:full":"Groenezoom 155 Rotterdam Zuid-Holland 3075 GC",
    "addr:housenumber":"155",
    "addr:postcode":"3075 gc",
    "addr:street":"Groenezoom",
    "iso:country":"NL",
    "sg:address":"Groenezoom 155",
    "sg:city":"Rotterdam",
    "sg:orig_category":"Kappers",
    "sg:phone":"+31 10 419 5041",
    "sg:postcode":"3075 GC",
    "sg:province":"Zuid-Holland",
    "wof:name":"Kapsalon M Poot",
    "wof:placetype":"venue"
},
  "geometry": {"coordinates":[4.5156359673,51.8857650757],"type":"Point"}
}