{
  "type": "Feature",
  "properties": {
    "iso:country":"NL",
    "sg:address":"Vlielandstr 48",
    "sg:city":"Zaandam",
    "sg:orig_category":"Lasbedrijven",
    "sg:phone":"+31 75 617 0082",
    "sg:postcode":"1506 ZK",
    "sg:province":"North Holland",
    "wof:name":"Fabel, C E",
    "wof:placetype":"venue"
},
  "geometry": {"coordinates":[4.807365,52.454254],"type":"Point"}
}