{
  "type": "Feature",
  "properties": {
    "addr:full":"Middenweg 4 Lisse North Holland 2161 LR",
    "addr:housenumber":"4",
    "addr:postcode":"2161 lr",
    "addr:street":"Middenweg",
    "iso:country":"NL",
    "sg:address":"Middenweg 4",
    "sg:city":"Lisse",
    "sg:orig_category":"Bloemen And Planten",
    "sg:phone":"+31 252 219 015",
    "sg:postcode":"2161 LR",
    "sg:province":"North Holland",
    "wof:name":"Limaplant Bv",
    "wof:placetype":"venue"
},
  "geometry": {"coordinates":[4.556859,52.240498],"type":"Point"}
}