{
  "type": "Feature",
  "properties": {
    "iso:country":"NL",
    "sg:address":"F Kupperstr 5",
    "sg:city":"Amsterdam",
    "sg:orig_category":"Kappers",
    "sg:phone":"+31 20 619 1734",
    "sg:postcode":"1068 KL",
    "sg:province":"Noord-Holland",
    "wof:name":"Eig Ostermann, H T J Van",
    "wof:placetype":"venue"
},
  "geometry": {"coordinates":[4.8164100647,52.3527183533],"type":"Point"}
}