{
  "type": "Feature",
  "properties": {
    "addr:full":"Leuvensestraat 85 Den Haag Zuid-Holland 2587 GD",
    "addr:housenumber":"85",
    "addr:postcode":"2587 gd",
    "addr:street":"Leuvensestraat",
    "iso:country":"NL",
    "sg:address":"Leuvensestraat 85",
    "sg:city":"Den Haag",
    "sg:orig_category":"Verzekeringen",
    "sg:phone":"+31 70 354 5505",
    "sg:postcode":"2587 GD",
    "sg:province":"Zuid-Holland",
    "wof:name":"Leuvass Assurantien",
    "wof:placetype":"venue"
},
  "geometry": {"coordinates":[4.295167,52.108921],"type":"Point"}
}