{
  "type": "Feature",
  "properties": {
    "iso:country":"NL",
    "sg:address":"Zwart Janstr 72",
    "sg:city":"Rotterdam",
    "sg:orig_category":"Zonnebank- En Solariumcentra",
    "sg:phone":"+31 10 265 2388",
    "sg:postcode":"3035 AV",
    "sg:province":"South Holland",
    "sg:website":"http://www.sundays.nl",
    "wof:name":"Sunday",
    "wof:placetype":"venue"
},
  "geometry": {"coordinates":[4.477911,51.933308],"type":"Point"}
}