{
  "type": "Feature",
  "properties": {
    "addr:full":"Gebbelsweg 14 Ospel Alabama 6035 EA",
    "addr:housenumber":"14",
    "addr:postcode":"6035 ea",
    "addr:street":"Gebbelsweg",
    "iso:country":"NL",
    "sg:address":"Gebbelsweg 14",
    "sg:city":"Ospel",
    "sg:orig_category":"Metaalbekleding And -Behandeling",
    "sg:phone":"+31 495 631 993",
    "sg:postcode":"6035 EA",
    "sg:province":"Alabama",
    "wof:name":"Vof Van Meel-Vaes",
    "wof:placetype":"venue"
},
  "geometry": {"coordinates":[-86.165451,34.620892],"type":"Point"}
}