{
  "type": "Feature",
  "properties": {
    "addr:full":"Van Baerlestraat 18Bg Amsterdam Noord-Holland 1071 AW",
    "addr:housenumber":"18bg",
    "addr:postcode":"1071 aw",
    "addr:street":"Van Baerlestraat",
    "iso:country":"NL",
    "sg:address":"Van Baerlestraat 18Bg",
    "sg:city":"Amsterdam",
    "sg:orig_category":"Damesmodezaken",
    "sg:phone":"+31 20 400 4743",
    "sg:postcode":"1071 AW",
    "sg:province":"Noord-Holland",
    "wof:name":"Morgan Fashion",
    "wof:placetype":"venue"
},
  "geometry": {"coordinates":[4.877361,52.359482],"type":"Point"}
}