{
  "type": "Feature",
  "properties": {
    "addr:full":"Van Ghertstraat 14 Rijen North Brabant 5121 HZ",
    "addr:housenumber":"14",
    "addr:postcode":"5121 hz",
    "addr:street":"Van Ghertstraat",
    "iso:country":"NL",
    "sg:address":"Van Ghertstraat 14",
    "sg:city":"Rijen",
    "sg:orig_category":"Koeriersdiensten",
    "sg:phone":"+31 161 227 386",
    "sg:postcode":"5121 HZ",
    "sg:province":"North Brabant",
    "wof:name":"J. V.D. Velden Snel- En Koeriersdiensten",
    "wof:placetype":"venue"
},
  "geometry": {"coordinates":[4.9138,51.595112],"type":"Point"}
}