{
  "type": "Feature",
  "properties": {
    "iso:country":"NL",
    "sg:address":"Van Ghertstraat 14",
    "sg:city":"Rijen",
    "sg:orig_category":"Koeriersdiensten",
    "sg:phone":"+31 161 227 386",
    "sg:postcode":"5121 HZ",
    "sg:province":"North Brabant",
    "wof:name":"J. V.D. Velden Snel- En Koeriersdiensten",
    "wof:placetype":"venue"
},
  "geometry": {"coordinates":[4.9138,51.595112],"type":"Point"}
}