{
  "type": "Feature",
  "properties": {
    "addr:full":"Provenierssngl 11 Rotterdam Zuid-Holland 3033 ED",
    "addr:housenumber":"11",
    "addr:postcode":"3033 ed",
    "addr:street":"Provenierssngl",
    "iso:country":"NL",
    "sg:address":"Provenierssngl 11",
    "sg:city":"Rotterdam",
    "sg:orig_category":"Architecten En Architectenbureaus",
    "sg:phone":"+31 10 465 1680",
    "sg:postcode":"3033 ED",
    "sg:province":"Zuid-Holland",
    "wof:name":"L\u00fcthi En Niclaes",
    "wof:placetype":"venue"
},
  "geometry": {"coordinates":[4.472616,51.928261],"type":"Point"}
}