{
  "type": "Feature",
  "properties": {
    "addr:full":"Handelstr 11 Leerdam Zuid-Holland 4143 HT",
    "addr:housenumber":"11",
    "addr:postcode":"4143 ht",
    "addr:street":"Handelstr",
    "iso:country":"NL",
    "sg:address":"Handelstr 11",
    "sg:city":"Leerdam",
    "sg:orig_category":"Kaasgroothandel",
    "sg:phone":"+31 345 639 900",
    "sg:postcode":"4143 HT",
    "sg:province":"Zuid-Holland",
    "wof:name":"Frico",
    "wof:placetype":"venue"
},
  "geometry": {"coordinates":[5.1047720909,51.8985328674],"type":"Point"}
}