{
  "type": "Feature",
  "properties": {
    "addr:full":"Lytwg 307 Oegstgeest South Holland 2341 HB",
    "addr:housenumber":"307",
    "addr:postcode":"2341 hb",
    "iso:country":"NL",
    "sg:address":"Lytwg 307",
    "sg:city":"Oegstgeest",
    "sg:orig_category":"Vertalers",
    "sg:phone":"+31 71 576 3378",
    "sg:postcode":"2341 HB",
    "sg:province":"South Holland",
    "wof:name":"Bos, Drs D Van Den",
    "wof:placetype":"venue"
},
  "geometry": {"coordinates":[4.468242,52.176617],"type":"Point"}
}