{
  "type": "Feature",
  "properties": {
    "iso:country":"NL",
    "sg:address":"Putseln 115A",
    "sg:city":"Rotterdam",
    "sg:orig_category":"Kappers",
    "sg:phone":"+31 10 484 9873",
    "sg:postcode":"3072 CD",
    "sg:province":"Zuid-Holland",
    "wof:name":"Asena",
    "wof:placetype":"venue"
},
  "geometry": {"coordinates":[4.490049839,51.9025001526],"type":"Point"}
}