{
  "type": "Feature",
  "properties": {
    "addr:full":"Gendringseweg 2 Azewijn Gelderland 7045 AR",
    "addr:housenumber":"2",
    "addr:postcode":"7045",
    "addr:street":"Gendringseweg;Gelderland",
    "iso:country":"NL",
    "sg:address":"Gendringseweg 2",
    "sg:city":"Azewijn",
    "sg:orig_category":"Fietshandelaren",
    "sg:phone":"+31 314 651 220",
    "sg:postcode":"7045 AR",
    "sg:province":"Gelderland",
    "wof:name":"H.B. Overbeek Vof",
    "wof:placetype":"venue"
},
  "geometry": {"coordinates":[6.309609,51.887634],"type":"Point"}
}