{
  "type": "Feature",
  "properties": {
    "addr:full":"Bredaseweg 88 Tilburg Noord-Brabant 5038 NH",
    "addr:housenumber":"88",
    "addr:postcode":"5038 nh",
    "addr:street":"Bredaseweg",
    "iso:country":"NL",
    "sg:address":"Bredaseweg 88",
    "sg:city":"Tilburg",
    "sg:orig_category":"Kappers",
    "sg:phone":"+31 13 542 5154",
    "sg:postcode":"5038 NH",
    "sg:province":"Noord-Brabant",
    "wof:name":"Avangi Hairfashion",
    "wof:placetype":"venue"
},
  "geometry": {"coordinates":[5.0761418343,51.55519104],"type":"Point"}
}