{
  "type": "Feature",
  "properties": {
    "addr:full":"Ged Hantumervaart 14 Dokkum Provincie Friesland 9101 AW",
    "addr:housenumber":"14",
    "addr:postcode":"9101 aw",
    "addr:street":"Hantumervaart;Provincie Friesland",
    "iso:country":"NL",
    "sg:address":"Ged Hantumervaart 14",
    "sg:city":"Dokkum",
    "sg:orig_category":"Onderhoudswerken",
    "sg:phone":"+31 519 292 292",
    "sg:postcode":"9101 AW",
    "sg:province":"Provincie Friesland",
    "wof:name":"Postma, Anne",
    "wof:placetype":"venue"
},
  "geometry": {"coordinates":[5.991331,53.326729],"type":"Point"}
}