{
  "type": "Feature",
  "properties": {
    "iso:country":"NL",
    "sg:address":"Panamakade 114",
    "sg:city":"Amsterdam",
    "sg:orig_category":"Adviesbureaus Bedrijfsorganisatie",
    "sg:phone":"+31 20 685 3200",
    "sg:postcode":"1019 AX",
    "sg:province":"North Holland",
    "sg:website":"http://www.effective-management.nl",
    "wof:name":"Effective Management Consultancy",
    "wof:placetype":"venue"
},
  "geometry": {"coordinates":[4.943643,52.372772],"type":"Point"}
}