{
  "type": "Feature",
  "properties": {
    "addr:full":"Molenstraat 17 Buitenpost Pennsylvania 9285 PA",
    "addr:housenumber":"17",
    "addr:postcode":"9285 pa",
    "addr:street":"Molenstraat",
    "iso:country":"NL",
    "sg:address":"Molenstraat 17",
    "sg:city":"Buitenpost",
    "sg:classifiers":[
        {
            "category":"Education",
            "subcategory":"Preschool",
            "type":"Public Place"
        }
    ],
    "sg:phone":"+31 511 542 225",
    "sg:postcode":"9285 PA",
    "sg:province":"Pennsylvania",
    "sg:tags":[
        "kleuteronderwijs",
        "basis-"
    ],
    "wof:name":"Gereformeerde Basisschool De Fontein",
    "wof:placetype":"venue"
},
  "geometry": {"coordinates":[-77.604507,40.99464],"type":"Point"}
}