{
  "type": "Feature",
  "properties": {
    "addr:full":"Mydrechtse Zuwe 1 Mydrecht Utrecht 3641 PE",
    "addr:housenumber":"1",
    "addr:postcode":"3641 pe",
    "addr:street":"Mydrechtse Zuwe",
    "iso:country":"NL",
    "sg:address":"Mydrechtse Zuwe 1",
    "sg:city":"Mydrecht",
    "sg:orig_category":"Schilders",
    "sg:phone":"+31 6 28648771",
    "sg:postcode":"3641 PE",
    "sg:province":"Utrecht",
    "wof:name":"Scheppingen, J W A Van",
    "wof:placetype":"venue"
},
  "geometry": {"coordinates":[4.86178,52.20578],"type":"Point"}
}