{
  "type": "Feature",
  "properties": {
    "iso:country":"NL",
    "sg:address":"Hortensialaan 3",
    "sg:city":"Groningen",
    "sg:classifiers":[
        {
            "category":"Fast Food",
            "type":"Food & Drink"
        }
    ],
    "sg:phone":"+31 50 312 5978",
    "sg:postcode":"9713 KG",
    "sg:province":"Groningen",
    "sg:tags":[
        "afhaal",
        "restaurant"
    ],
    "wof:name":"H Bats",
    "wof:placetype":"venue"
},
  "geometry": {"coordinates":[6.584413,53.222122],"type":"Point"}
}