{
  "type": "Feature",
  "properties": {
    "addr:full":"Laan Van Orden 8 Apeldoorn Gelderland 7312 KJ",
    "addr:housenumber":"8",
    "addr:postcode":"7312 kj",
    "addr:street":"Laan Van Orden;Gelderland",
    "iso:country":"NL",
    "sg:address":"Laan Van Orden 8",
    "sg:city":"Apeldoorn",
    "sg:orig_category":"Loodgieterswerk, Verwarming And Sanitaire Installaties",
    "sg:phone":"+31 55 356 0355",
    "sg:postcode":"7312 KJ",
    "sg:province":"Gelderland",
    "wof:name":"Van Dam Installatietechniek Bv",
    "wof:placetype":"venue"
},
  "geometry": {"coordinates":[5.93747,52.203812],"type":"Point"}
}