{
  "type": "Feature",
  "properties": {
    "addr:full":"Helene Swarthlaan 80 Groningen Groningen 9721 TX",
    "addr:housenumber":"80",
    "addr:postcode":"9721 tx",
    "addr:street":"Helene Swarthlaan",
    "iso:country":"NL",
    "sg:address":"Helene Swarthlaan 80",
    "sg:city":"Groningen",
    "sg:orig_category":"Juridische Dienstverlening",
    "sg:phone":"+31 50 526 5033",
    "sg:postcode":"9721 TX",
    "sg:province":"Groningen",
    "wof:name":"Dijkhuizen Consultancy",
    "wof:placetype":"venue"
},
  "geometry": {"coordinates":[6.568057,53.191097],"type":"Point"}
}