{
  "type": "Feature",
  "properties": {
    "addr:full":"Albrecht Durerstraat 29 Amsterdam Noord-Holland 1077 LV",
    "addr:housenumber":"29",
    "addr:postcode":"1077",
    "addr:street":"Durerstraat",
    "iso:country":"NL",
    "sg:address":"Albrecht Durerstraat 29",
    "sg:city":"Amsterdam",
    "sg:orig_category":"Parfum And Cosmetica Gh",
    "sg:phone":"+31 20 662 9452",
    "sg:postcode":"1077 LV",
    "sg:province":"Noord-Holland",
    "wof:name":"Handelsonderneming Cabet",
    "wof:placetype":"venue"
},
  "geometry": {"coordinates":[4.876049,52.348488],"type":"Point"}
}