{
  "type": "Feature",
  "properties": {
    "addr:full":"Zernikestr 3 Eindhoven North Brabant 5612 HZ",
    "addr:housenumber":"3",
    "addr:postcode":"5612 hz",
    "addr:street":"Zernikestr",
    "iso:country":"NL",
    "sg:address":"Zernikestr 3",
    "sg:city":"Eindhoven",
    "sg:orig_category":"Ministeries En Overheidsinstellingen",
    "sg:phone":"+31 40 265 7657",
    "sg:postcode":"5612 HZ",
    "sg:province":"North Brabant",
    "wof:name":"Rijkswaterstaat Meetkundige Dienst",
    "wof:placetype":"venue"
},
  "geometry": {"coordinates":[5.469883,51.445965],"type":"Point"}
}