{
  "type": "Feature",
  "properties": {
    "iso:country":"NL",
    "sg:address":"Grt Peel 77",
    "sg:city":"Diemen",
    "sg:orig_category":"Partycatering And -Organisatie",
    "sg:phone":"+31 20 416 6490",
    "sg:postcode":"1112 KE",
    "sg:province":"Noord-Holland",
    "wof:name":"R & D Partyservice",
    "wof:placetype":"venue"
},
  "geometry": {"coordinates":[4.944899,52.329872],"type":"Point"}
}