{
  "type": "Feature",
  "properties": {
    "iso:country":"NL",
    "sg:address":"Te Winkelmarke 16",
    "sg:city":"Zwolle",
    "sg:orig_category":"Diverse Grafische Activiteiten",
    "sg:phone":"+31 38 466 1335",
    "sg:postcode":"8016 MP",
    "sg:province":"NL.08",
    "wof:name":"A.M. Biel",
    "wof:placetype":"venue"
},
  "geometry": {"coordinates":[6.108384,52.476814],"type":"Point"}
}