{
  "type": "Feature",
  "properties": {
    "iso:country":"NL",
    "sg:address":"Eenrumerwg 4",
    "sg:city":"Baflo",
    "sg:orig_category":"Levensmiddelen- Grondstoffen - Fabrieken En Groothandel",
    "sg:phone":"+31 595 422 724",
    "sg:postcode":"9953 TD",
    "sg:province":"Groningen",
    "wof:name":"Vries Bv, J",
    "wof:placetype":"venue"
},
  "geometry": {"coordinates":[6.509836,53.36375],"type":"Point"}
}