{
  "type": "Feature",
  "properties": {
    "addr:full":"Noordweg 97 Pijnacker South Holland 2641 ZA",
    "addr:housenumber":"97",
    "addr:postcode":"2641",
    "addr:street":"Noordweg",
    "iso:country":"NL",
    "sg:address":"Noordweg 97",
    "sg:city":"Pijnacker",
    "sg:orig_category":"Benzinestations And Brandstoffen",
    "sg:phone":"+31 15 369 2508",
    "sg:postcode":"2641 ZA",
    "sg:province":"South Holland",
    "wof:name":"Shell",
    "wof:placetype":"venue"
},
  "geometry": {"coordinates":[4.41976,52.029488],"type":"Point"}
}