{
  "type": "Feature",
  "properties": {
    "addr:full":"Johan Dijkstrasingel 2 Winsum Gn Groningen 9951 MR",
    "addr:housenumber":"2",
    "addr:postcode":"gn;9951 mr",
    "addr:street":"Johan Dijkstrasingel",
    "iso:country":"NL",
    "sg:address":"Johan Dijkstrasingel 2",
    "sg:city":"Winsum Gn",
    "sg:orig_category":"Kappers",
    "sg:phone":"+31 595 444 055",
    "sg:postcode":"9951 MR",
    "sg:province":"Groningen",
    "wof:name":"Dameskappersbedrijf Geke Weelink",
    "wof:placetype":"venue"
},
  "geometry": {"coordinates":[6.5268478394,53.3333015442],"type":"Point"}
}