{
  "type": "Feature",
  "properties": {
    "addr:full":"Lichtenvoordsestr 44 Aalten Gelderland 7121 RA",
    "addr:housenumber":"44",
    "addr:postcode":"7121 ra",
    "addr:street":"Lichtenvoordsestr;Gelderland",
    "iso:country":"NL",
    "sg:address":"Lichtenvoordsestr 44",
    "sg:city":"Aalten",
    "sg:orig_category":"Zalenverhuur",
    "sg:phone":"+31 543 472 551",
    "sg:postcode":"7121 RA",
    "sg:province":"Gelderland",
    "wof:name":"Noorden, 'T",
    "wof:placetype":"venue"
},
  "geometry": {"coordinates":[6.582458,51.933701],"type":"Point"}
}