{
  "type": "Feature",
  "properties": {
    "addr:full":"Echelpoelweg 17 Weerselo Overijssel 7595 KA",
    "addr:housenumber":"17",
    "addr:postcode":"7595 ka",
    "addr:street":"Echelpoelweg",
    "iso:country":"NL",
    "sg:address":"Echelpoelweg 17",
    "sg:city":"Weerselo",
    "sg:orig_category":"Autokeuringen",
    "sg:phone":"+31 541 661 046",
    "sg:postcode":"7595 KA",
    "sg:province":"Overijssel",
    "wof:name":"H.G.F. Boswerger",
    "wof:placetype":"venue"
},
  "geometry": {"coordinates":[6.842381,52.357151],"type":"Point"}
}