{
  "type": "Feature",
  "properties": {
    "iso:country":"NL",
    "sg:address":"Molenstraat 223",
    "sg:city":"Helmond",
    "sg:orig_category":"Verplichte Sociale Verzekeringen",
    "sg:phone":"+31 492 522 377",
    "sg:postcode":"5701 KE",
    "sg:province":"Noord-Brabant",
    "wof:name":"Cz Groep Zorgverzekeringen Servicekantoor Helmond",
    "wof:placetype":"venue"
},
  "geometry": {"coordinates":[5.658064,51.478718],"type":"Point"}
}