{
  "type": "Feature",
  "properties": {
    "addr:full":"D C Meesstr 88 Spykenisse Zuid-Holland 3201 RA",
    "addr:housenumber":"88",
    "addr:postcode":"3201 ra",
    "addr:street":"D C Meesstr",
    "iso:country":"NL",
    "sg:address":"D C Meesstr 88",
    "sg:city":"Spykenisse",
    "sg:orig_category":"Bestratingen",
    "sg:phone":"+31 181 626 613",
    "sg:postcode":"3201 RA",
    "sg:province":"Zuid-Holland",
    "wof:name":"Klinker, De",
    "wof:placetype":"venue"
},
  "geometry": {"coordinates":[4.333203,51.847317],"type":"Point"}
}