{
  "type": "Feature",
  "properties": {
    "addr:full":"Voorterweg 168 Eindhoven North Brabant 5611 TT",
    "addr:housenumber":"168",
    "addr:postcode":"5611 tt",
    "addr:street":"Voorterweg",
    "iso:country":"NL",
    "sg:address":"Voorterweg 168",
    "sg:city":"Eindhoven",
    "sg:classifiers":[
        {
            "category":"Fast Food",
            "type":"Food & Drink"
        }
    ],
    "sg:phone":"+31 40 212 3466",
    "sg:postcode":"5611 TT",
    "sg:province":"North Brabant",
    "sg:tags":[
        "afhaal",
        "restaurant"
    ],
    "wof:name":"Iris",
    "wof:placetype":"venue"
},
  "geometry": {"coordinates":[5.492771,51.433556],"type":"Point"}
}