{
  "type": "Feature",
  "properties": {
    "addr:full":"Noordstr 17 Axel England 4571 GB",
    "addr:housenumber":"17",
    "addr:postcode":"4571 gb",
    "addr:street":"Noordstr;England",
    "iso:country":"NL",
    "sg:address":"Noordstr 17",
    "sg:city":"Axel",
    "sg:orig_category":"Juweliers",
    "sg:phone":"+31 115 564 813",
    "sg:postcode":"4571 GB",
    "sg:province":"England",
    "wof:name":"Maridiam",
    "wof:placetype":"venue"
},
  "geometry": {"coordinates":[-2.23218,54.313919],"type":"Point"}
}