{
  "type": "Feature",
  "properties": {
    "iso:country":"NL",
    "sg:address":"Noordstr 17",
    "sg:city":"Axel",
    "sg:orig_category":"Juweliers",
    "sg:phone":"+31 115 564 813",
    "sg:postcode":"4571 GB",
    "sg:province":"England",
    "wof:name":"Maridiam",
    "wof:placetype":"venue"
},
  "geometry": {"coordinates":[-2.23218,54.313919],"type":"Point"}
}