{
  "type": "Feature",
  "properties": {
    "addr:full":"Dorpsstraat 25/A Vleuten Utrecht 3451 BJ",
    "addr:housenumber":"25 / a",
    "addr:postcode":"3451 bj",
    "addr:street":"Dorpsstraat",
    "iso:country":"NL",
    "sg:address":"Dorpsstraat 25/A",
    "sg:city":"Vleuten",
    "sg:orig_category":"Meubelzaken, Woning- And Keukeninrichting",
    "sg:phone":"+31 30 677 2742",
    "sg:postcode":"3451 BJ",
    "sg:province":"Utrecht",
    "wof:name":"Slaapplaneet/Tele Tapijt",
    "wof:placetype":"venue"
},
  "geometry": {"coordinates":[5.007642,52.107582],"type":"Point"}
}