{
  "type": "Feature",
  "properties": {
    "iso:country":"NL",
    "sg:address":"Tupolevlaan 42",
    "sg:city":"Schiphol-Rijk",
    "sg:orig_category":"Koeriersdiensten",
    "sg:phone":"+31 20 653 6747",
    "sg:postcode":"1119 NZ",
    "sg:province":"Noord-Holland",
    "wof:name":"Transport Pf Cv",
    "wof:placetype":"venue"
},
  "geometry": {"coordinates":[4.757205,52.281868],"type":"Point"}
}