{
  "type": "Feature",
  "properties": {
    "iso:country":"NL",
    "sg:address":"Sperwerpad 3",
    "sg:city":"Voorschoten",
    "sg:orig_category":"Onderhoud And Reparatie Kantoorapparatuur",
    "sg:phone":"+31 71 561 1265",
    "sg:postcode":"2251 PE",
    "sg:province":"South Holland",
    "wof:name":"Eric De Stoppelaar Computers",
    "wof:placetype":"venue"
},
  "geometry": {"coordinates":[4.44797,52.120667],"type":"Point"}
}