{
  "type": "Feature",
  "properties": {
    "addr:full":"Ryksstrwg 90 Hellevoetsluis South Holland 3223 KB",
    "addr:housenumber":"90",
    "addr:postcode":"3223 kb",
    "addr:street":"Ryksstrwg",
    "iso:country":"NL",
    "sg:address":"Ryksstrwg 90",
    "sg:city":"Hellevoetsluis",
    "sg:orig_category":"Kunstgebitten",
    "sg:phone":"+31 181 316 143",
    "sg:postcode":"3223 KB",
    "sg:province":"South Holland",
    "wof:name":"Grave, De",
    "wof:placetype":"venue"
},
  "geometry": {"coordinates":[4.14703,51.830406],"type":"Point"}
}