{
  "type": "Feature",
  "properties": {
    "addr:full":"Nieuwez Voorburgw 332 Amsterdam Noord-Holland 1012 RW",
    "addr:housenumber":"332",
    "addr:postcode":"1012 rw",
    "iso:country":"NL",
    "sg:address":"Nieuwez Voorburgw 332",
    "sg:city":"Amsterdam",
    "sg:orig_category":"Gelegenheidskleding",
    "sg:phone":"+31 20 330 5734",
    "sg:postcode":"1012 RW",
    "sg:province":"Noord-Holland",
    "sg:website":"http://www.skintighk.nl",
    "wof:name":"Wastelandware, De",
    "wof:placetype":"venue"
},
  "geometry": {"coordinates":[4.889145,52.369499],"type":"Point"}
}