{
  "type": "Feature",
  "properties": {
    "addr:full":"Bergenstr 3 Raamsdonk North Brabant 4944 XE",
    "addr:housenumber":"3",
    "addr:postcode":"4944 xe",
    "addr:street":"Bergenstr",
    "iso:country":"NL",
    "sg:address":"Bergenstr 3",
    "sg:city":"Raamsdonk",
    "sg:orig_category":"Belastingconsulenten/ Belastingadviseurs",
    "sg:phone":"+31 162 513 061",
    "sg:postcode":"4944 XE",
    "sg:province":"North Brabant",
    "wof:name":"D'Haene, J",
    "wof:placetype":"venue"
},
  "geometry": {"coordinates":[4.90495,51.686352],"type":"Point"}
}