{
  "type": "Feature",
  "properties": {
    "addr:full":"A V Ostadeln 122 Utrecht Utrecht 3583 AM",
    "addr:housenumber":"122",
    "addr:postcode":"3583",
    "addr:street":"A;Ostadeln",
    "iso:country":"NL",
    "sg:address":"A V Ostadeln 122",
    "sg:city":"Utrecht",
    "sg:orig_category":"Pensioenfondsen",
    "sg:phone":"+31 30 251 1519",
    "sg:postcode":"3583 AM",
    "sg:province":"Utrecht",
    "wof:name":"Co-Op Pensioenfonds",
    "wof:placetype":"venue"
},
  "geometry": {"coordinates":[5.14371,52.086601],"type":"Point"}
}