{
  "type": "Feature",
  "properties": {
    "addr:full":"Ratelaar 14 Boskoop Zuid-Holland 2771 RH",
    "addr:housenumber":"14",
    "addr:postcode":"2771 rh",
    "addr:street":"Ratelaar",
    "iso:country":"NL",
    "sg:address":"Ratelaar 14",
    "sg:city":"Boskoop",
    "sg:orig_category":"Kappers",
    "sg:phone":"+31 172 216 066",
    "sg:postcode":"2771 RH",
    "sg:province":"Zuid-Holland",
    "wof:name":"H.J. Stolk-Hofland",
    "wof:placetype":"venue"
},
  "geometry": {"coordinates":[4.6382808685,52.0718154907],"type":"Point"}
}