{
  "type": "Feature",
  "properties": {
    "addr:full":"Oude Zwolsewg 149A Wenum Wiesel Gelderland 7345 DG",
    "addr:housenumber":"149a",
    "addr:postcode":"7345 dg",
    "addr:street":"Oude Zwolsewg",
    "iso:country":"NL",
    "sg:address":"Oude Zwolsewg 149A",
    "sg:city":"Wenum Wiesel",
    "sg:classifiers":[
        {
            "category":"Retail",
            "subcategory":"Auto Repair",
            "type":"Services"
        }
    ],
    "sg:phone":"+31 55 312 1254",
    "sg:postcode":"7345 DG",
    "sg:province":"Gelderland",
    "sg:tags":[
        "garage"
    ],
    "sg:website":"http://www.autohennekes.nl",
    "wof:name":"Hennekes Autobedrijf",
    "wof:placetype":"venue"
},
  "geometry": {"coordinates":[5.964136,52.255074],"type":"Point"}
}