{
  "type": "Feature",
  "properties": {
    "iso:country":"NL",
    "sg:address":"Kasteel 2",
    "sg:city":"Coevorden",
    "sg:orig_category":"Banken And Kredietinstellingen",
    "sg:phone":"+31 524 597 666",
    "sg:postcode":"7741 GD",
    "sg:province":"Provincie Drenthe",
    "wof:name":"Rabobank",
    "wof:placetype":"venue"
},
  "geometry": {"coordinates":[6.741811,52.661671],"type":"Point"}
}