{
  "type": "Feature",
  "properties": {
    "addr:full":"Kasteel 2 Coevorden Provincie Drenthe 7741 GD",
    "addr:housenumber":"2",
    "addr:postcode":"7741 gd",
    "addr:street":"Kasteel;Provincie Drenthe",
    "iso:country":"NL",
    "sg:address":"Kasteel 2",
    "sg:city":"Coevorden",
    "sg:orig_category":"Banken And Kredietinstellingen",
    "sg:phone":"+31 524 597 666",
    "sg:postcode":"7741 GD",
    "sg:province":"Provincie Drenthe",
    "wof:name":"Rabobank",
    "wof:placetype":"venue"
},
  "geometry": {"coordinates":[6.741811,52.661671],"type":"Point"}
}