{
  "type": "Feature",
  "properties": {
    "iso:country":"NL",
    "sg:address":"Stationsweg 140",
    "sg:city":"Barendrecht",
    "sg:orig_category":"Fruit And Groenten Gh",
    "sg:phone":"+31 180 612 732",
    "sg:postcode":"2991 VN",
    "sg:province":"Zuid-Holland",
    "wof:name":"B.A. Gouman",
    "wof:placetype":"venue"
},
  "geometry": {"coordinates":[4.54064,51.853176],"type":"Point"}
}