{
  "type": "Feature",
  "properties": {
    "addr:full":"Paltzerwg 199 Den Dolder Utrecht 3734 CL",
    "addr:housenumber":"199",
    "addr:postcode":"3734",
    "iso:country":"NL",
    "sg:address":"Paltzerwg 199",
    "sg:city":"Den Dolder",
    "sg:orig_category":"Adviesbureaus Financieel",
    "sg:phone":"+31 30 255 1697",
    "sg:postcode":"3734 CL",
    "sg:province":"Utrecht",
    "wof:name":"Tsp",
    "wof:placetype":"venue"
},
  "geometry": {"coordinates":[5.232741,52.136044],"type":"Point"}
}