{
  "type": "Feature",
  "properties": {
    "addr:full":"Kossinkwg 2 Winterswyk Gelderland 7105 CA",
    "addr:housenumber":"2",
    "addr:postcode":"7105 ca",
    "addr:street":"Kossinkwg;Gelderland",
    "iso:country":"NL",
    "sg:address":"Kossinkwg 2",
    "sg:city":"Winterswyk",
    "sg:classifiers":[
        {
            "category":"Real Estate",
            "subcategory":"Real Estate Operator",
            "type":"Services"
        }
    ],
    "sg:phone":"+31 543 562 421",
    "sg:postcode":"7105 CA",
    "sg:province":"Gelderland",
    "sg:tags":[
        "appartementen",
        "en",
        "flat"
    ],
    "wof:name":"Tenkink, A P",
    "wof:placetype":"venue"
},
  "geometry": {"coordinates":[-119.270203,37.271832],"type":"Point"}
}