{
  "type": "Feature",
  "properties": {
    "addr:full":"Maaspoort 6 Weert Limburg 6001 BP",
    "addr:housenumber":"6",
    "addr:postcode":"6001 bp",
    "addr:street":"Maaspoort",
    "iso:country":"NL",
    "sg:address":"Maaspoort 6",
    "sg:city":"Weert",
    "sg:orig_category":"Kampeerartikelen",
    "sg:phone":"+31 495 547 434",
    "sg:postcode":"6001 BP",
    "sg:province":"Limburg",
    "wof:name":"Bob'S Adventure Store",
    "wof:placetype":"venue"
},
  "geometry": {"coordinates":[5.7100639343,51.2519989014],"type":"Point"}
}