{
  "type": "Feature",
  "properties": {
    "addr:full":"Kluyverweg 1 Delft Zuid-Holland 2629 HS",
    "addr:housenumber":"1",
    "addr:postcode":"2629 hs",
    "addr:street":"Kluyverweg",
    "iso:country":"NL",
    "sg:address":"Kluyverweg 1",
    "sg:city":"Delft",
    "sg:orig_category":"Organisaties And Verenigingen",
    "sg:phone":"+31 15 278 5215",
    "sg:postcode":"2629 HS",
    "sg:province":"Zuid-Holland",
    "wof:name":"Eurovia Delft",
    "wof:placetype":"venue"
},
  "geometry": {"coordinates":[4.3771901131,51.9901351929],"type":"Point"}
}