{
  "type": "Feature",
  "properties": {
    "addr:full":"Stationstr 32 Baexem Limburg 6095 BS",
    "addr:housenumber":"32",
    "addr:postcode":"6095 bs",
    "addr:street":"Stationstr",
    "iso:country":"NL",
    "sg:address":"Stationstr 32",
    "sg:city":"Baexem",
    "sg:orig_category":"Pluimveebedrijven En -Handelaren",
    "sg:phone":"+31 475 451 678",
    "sg:postcode":"6095 BS",
    "sg:province":"Limburg",
    "wof:name":"Horne, L Van",
    "wof:placetype":"venue"
},
  "geometry": {"coordinates":[5.886116,51.238117],"type":"Point"}
}