{
  "type": "Feature",
  "properties": {
    "addr:full":"Rijnweide 26 Cothen Utrecht 3945 BR",
    "addr:housenumber":"26",
    "addr:postcode":"3945 br",
    "addr:street":"Rijnweide",
    "iso:country":"NL",
    "sg:address":"Rijnweide 26",
    "sg:city":"Cothen",
    "sg:orig_category":"Architecten",
    "sg:phone":"+31 343 561 478",
    "sg:postcode":"3945 BR",
    "sg:province":"Utrecht",
    "wof:name":"A.C.M. Van Der Wielen Architektenburo",
    "wof:placetype":"venue"
},
  "geometry": {"coordinates":[5.306351,51.999374],"type":"Point"}
}