{
  "type": "Feature",
  "properties": {
    "iso:country":"NL",
    "sg:address":"Lepelaarstraat 10",
    "sg:city":"Wijchen",
    "sg:orig_category":"Kappers",
    "sg:phone":"+31 24 641 3510",
    "sg:postcode":"6601 DJ",
    "sg:province":"Gelderland",
    "wof:name":"Dames- En Herenkapsalon J.A.M. Smits",
    "wof:placetype":"venue"
},
  "geometry": {"coordinates":[5.7282419205,51.8145980835],"type":"Point"}
}