{
  "type": "Feature",
  "properties": {
    "addr:full":"Boulevard 1945 505 Enschede Noord-Holland 7511 AD",
    "addr:housenumber":"505",
    "addr:postcode":"7511 ad",
    "addr:street":"Boulevard 1945",
    "iso:country":"NL",
    "sg:address":"Boulevard 1945 505",
    "sg:city":"Enschede",
    "sg:orig_category":"Bejaardeninstellingen And Serviceflats",
    "sg:phone":"+31 53 431 1068",
    "sg:postcode":"7511 AD",
    "sg:province":"Noord-Holland",
    "wof:name":"Stichting Zorgpalet",
    "wof:placetype":"venue"
},
  "geometry": {"coordinates":[6.90476,52.216591],"type":"Point"}
}