{
  "type": "Feature",
  "properties": {
    "addr:full":"Maagdenburgstr 9 Deventer NL.08 7421 ZA",
    "addr:housenumber":"9;nl.08",
    "addr:postcode":"7421",
    "addr:street":"Maagdenburgstr",
    "iso:country":"NL",
    "sg:address":"Maagdenburgstr 9",
    "sg:city":"Deventer",
    "sg:orig_category":"Displays, Showcards En Toonmaterialen",
    "sg:phone":"+31 570 698 911",
    "sg:postcode":"7421 ZA",
    "sg:province":"NL.08",
    "wof:name":"Kappa Zedek Bv",
    "wof:placetype":"venue"
},
  "geometry": {"coordinates":[6.218175,52.239254],"type":"Point"}
}