{
  "type": "Feature",
  "properties": {
    "iso:country":"NL",
    "sg:address":"Kerkln 18",
    "sg:city":"Ermelo",
    "sg:orig_category":"Antiquiteiten",
    "sg:phone":"+31 6 23372373",
    "sg:postcode":"3851 JV",
    "sg:province":"Gelderland",
    "wof:name":"Pompoen, De",
    "wof:placetype":"venue"
},
  "geometry": {"coordinates":[5.63146,52.297852],"type":"Point"}
}