{
  "type": "Feature",
  "properties": {
    "addr:full":"Thorbeckeln 10 Barneveld Gelderland 3771 EG",
    "addr:housenumber":"10",
    "addr:postcode":"3771 eg",
    "addr:street":"Thorbeckeln;Gelderland",
    "iso:country":"NL",
    "sg:address":"Thorbeckeln 10",
    "sg:city":"Barneveld",
    "sg:orig_category":"Adviesbureaus Bedrijfsorganisatie",
    "sg:phone":"+31 342 423 941",
    "sg:postcode":"3771 EG",
    "sg:province":"Gelderland",
    "wof:name":"Morsink",
    "wof:placetype":"venue"
},
  "geometry": {"coordinates":[5.588843,52.141216],"type":"Point"}
}