{
  "type": "Feature",
  "properties": {
    "addr:full":"Paleisstr 135 Amsterdam Noord-Holland 1012 ZL",
    "addr:housenumber":"135",
    "addr:postcode":"1012 zl",
    "iso:country":"NL",
    "sg:address":"Paleisstr 135",
    "sg:city":"Amsterdam",
    "sg:orig_category":"Boeken En Tijdschriften",
    "sg:phone":"+31 20 623 5142",
    "sg:postcode":"1012 ZL",
    "sg:province":"Noord-Holland",
    "wof:name":"Vrolijk",
    "wof:placetype":"venue"
},
  "geometry": {"coordinates":[4.8898,52.372231],"type":"Point"}
}