{
  "type": "Feature",
  "properties": {
    "iso:country":"NL",
    "sg:address":"Belgieln 9",
    "sg:city":"Hazerswoude Dorp",
    "sg:orig_category":"Koel- En Vrieshuizen",
    "sg:phone":"+31 172 611 513",
    "sg:postcode":"2391 PH",
    "sg:province":"South Holland",
    "sg:website":"http://www.dammeslaban.nl",
    "wof:name":"Dammas Laban",
    "wof:placetype":"venue"
},
  "geometry": {"coordinates":[4.59104,52.097099],"type":"Point"}
}