{
  "type": "Feature",
  "properties": {
    "addr:full":"Goudenregenstraat 40 Papendrecht Zuid-Holland 3353 VA",
    "addr:housenumber":"40",
    "addr:postcode":"3353",
    "addr:street":"Goudenregenstraat",
    "iso:country":"NL",
    "sg:address":"Goudenregenstraat 40",
    "sg:city":"Papendrecht",
    "sg:classifiers":[
        {
            "category":"Fast Food",
            "type":"Food & Drink"
        }
    ],
    "sg:phone":"+31 78 641 1040",
    "sg:postcode":"3353 VA",
    "sg:province":"Zuid-Holland",
    "sg:tags":[
        "afhaal",
        "restaurant"
    ],
    "wof:name":"Snacky",
    "wof:placetype":"venue"
},
  "geometry": {"coordinates":[4.691766,51.829311],"type":"Point"}
}