{
  "type": "Feature",
  "properties": {
    "iso:country":"NL",
    "sg:address":"Kleiwg 95A",
    "sg:city":"Rotterdam",
    "sg:classifiers":[
        {
            "category":"Shopping",
            "subcategory":"Gifts & Souvenirs",
            "type":"Retail Goods"
        }
    ],
    "sg:phone":"+31 10 422 2202",
    "sg:postcode":"3051 GK",
    "sg:province":"Zuid-Holland",
    "sg:tags":[
        "wens-",
        "en",
        "prentbriefkaarten"
    ],
    "wof:name":"Verdoorn, J B",
    "wof:placetype":"venue"
},
  "geometry": {"coordinates":[4.4794387817,51.9453964233],"type":"Point"}
}