{
  "type": "Feature",
  "properties": {
    "iso:country":"NL",
    "sg:address":"Gerard Boedijnstraat 9",
    "sg:city":"Kerkrade",
    "sg:orig_category":"Paramedische Behandelingen",
    "sg:phone":"+31 45 545 9818",
    "sg:postcode":"6461 CX",
    "sg:province":"Limburg",
    "wof:name":"Spee Podotherapie",
    "wof:placetype":"venue"
},
  "geometry": {"coordinates":[6.067228,50.862427],"type":"Point"}
}