{
  "type": "Feature",
  "properties": {
    "addr:full":"Groenedk 21 Dordrecht Zuid-Holland 3311 DB",
    "addr:housenumber":"21",
    "addr:postcode":"3311 db",
    "addr:street":"Groenedk",
    "iso:country":"NL",
    "sg:address":"Groenedk 21",
    "sg:city":"Dordrecht",
    "sg:orig_category":"Journalisten Freelance",
    "sg:phone":"+31 78 648 9589",
    "sg:postcode":"3311 DB",
    "sg:province":"Zuid-Holland",
    "wof:name":"Hanneke Kijlstra",
    "wof:placetype":"venue"
},
  "geometry": {"coordinates":[4.680232,51.813732],"type":"Point"}
}