{
  "type": "Feature",
  "properties": {
    "iso:country":"NL",
    "sg:address":"Zijhuizen 1",
    "sg:city":"Haarlem",
    "sg:orig_category":"Meubelzaken, Woning- And Keukeninrichting",
    "sg:phone":"+31 23 531 1976",
    "sg:postcode":"2011 NA",
    "sg:province":"North Holland",
    "wof:name":"Wim Kraakman Licht En Interieurarchitekt",
    "wof:placetype":"venue"
},
  "geometry": {"coordinates":[4.634227,52.385582],"type":"Point"}
}