{
  "type": "Feature",
  "properties": {
    "addr:full":"Valkwg 6 Sliedrecht Zuid-Holland 3362 GH",
    "addr:housenumber":"6",
    "addr:postcode":"3362 gh",
    "addr:street":"Valkwg",
    "iso:country":"NL",
    "sg:address":"Valkwg 6",
    "sg:city":"Sliedrecht",
    "sg:orig_category":"Fitnesscentra",
    "sg:phone":"+31 184 410 206",
    "sg:postcode":"3362 GH",
    "sg:province":"Zuid-Holland",
    "wof:name":"Fitness En Beauty Palace",
    "wof:placetype":"venue"
},
  "geometry": {"coordinates":[4.789244,51.824535],"type":"Point"}
}