{
  "type": "Feature",
  "properties": {
    "addr:full":"Houtse Heuvel 3 Den Hout Nb Noord-Brabant 4911 AT",
    "addr:housenumber":"3",
    "addr:postcode":"4911",
    "addr:street":"Houtse Heuvel",
    "iso:country":"NL",
    "sg:address":"Houtse Heuvel 3",
    "sg:city":"Den Hout Nb",
    "sg:orig_category":"Scholen Voor Basisonderwijs",
    "sg:phone":"+31 162 455 472",
    "sg:postcode":"4911 AT",
    "sg:province":"Noord-Brabant",
    "wof:name":"Achthoek Rk, De",
    "wof:placetype":"venue"
},
  "geometry": {"coordinates":[4.812081,51.658325],"type":"Point"}
}