{
  "type": "Feature",
  "properties": {
    "iso:country":"NL",
    "sg:address":"Houtse Heuvel 3",
    "sg:city":"Den Hout Nb",
    "sg:orig_category":"Scholen Voor Basisonderwijs",
    "sg:phone":"+31 162 455 472",
    "sg:postcode":"4911 AT",
    "sg:province":"Noord-Brabant",
    "wof:name":"Achthoek Rk, De",
    "wof:placetype":"venue"
},
  "geometry": {"coordinates":[4.812081,51.658325],"type":"Point"}
}