{
  "type": "Feature",
  "properties": {
    "addr:full":"Noordlangeweg 19 Kats Zeeland 4485 PK",
    "addr:housenumber":"19",
    "addr:postcode":"4485 pk",
    "addr:street":"Noordlangeweg",
    "iso:country":"NL",
    "sg:address":"Noordlangeweg 19",
    "sg:city":"Kats",
    "sg:orig_category":"Kampeerterreinen",
    "sg:phone":"+31 113 695 680",
    "sg:postcode":"4485 PK",
    "sg:province":"Zeeland",
    "wof:name":"Mini-Camping Weizicht",
    "wof:placetype":"venue"
},
  "geometry": {"coordinates":[3.8612699509,51.5809516907],"type":"Point"}
}