{
  "type": "Feature",
  "properties": {
    "iso:country":"NL",
    "sg:address":"Jan Weitkamplaan 7",
    "sg:city":"Hardenberg",
    "sg:orig_category":"Bloemen And Planten",
    "sg:phone":"+31 523 267 877",
    "sg:postcode":"7772 SC",
    "sg:province":"Overijssel",
    "wof:name":"Plantage-Oost",
    "wof:placetype":"venue"
},
  "geometry": {"coordinates":[6.631093,52.570286],"type":"Point"}
}