{
  "type": "Feature",
  "properties": {
    "iso:country":"NL",
    "sg:address":"Schoolstraat 17",
    "sg:city":"Nieuwerbrug",
    "sg:orig_category":"Goederenvervoer Over De Weg",
    "sg:phone":"+31 348 688 862",
    "sg:postcode":"2415 AM",
    "sg:province":"Zuid-Holland",
    "wof:name":"Transportbedrijf Hans De With",
    "wof:placetype":"venue"
},
  "geometry": {"coordinates":[4.820569,52.076824],"type":"Point"}
}