{
  "type": "Feature",
  "properties": {
    "addr:full":"Duindoornstr 60 Almelo NL.08 7601 ER",
    "addr:housenumber":"60;nl.08",
    "addr:postcode":"7601 er",
    "addr:street":"Duindoornstr",
    "iso:country":"NL",
    "sg:address":"Duindoornstr 60",
    "sg:city":"Almelo",
    "sg:classifiers":[
        {
            "category":"Personal",
            "subcategory":"Nail Salon",
            "type":"Services"
        }
    ],
    "sg:phone":"+31 546 811 588",
    "sg:postcode":"7601 ER",
    "sg:province":"NL.08",
    "sg:tags":[
        "pedicure"
    ],
    "wof:name":"Korte, H C",
    "wof:placetype":"venue"
},
  "geometry": {"coordinates":[6.675035,52.342258],"type":"Point"}
}