{
  "type": "Feature",
  "properties": {
    "addr:full":"Kl Kerkstr 2 Hoogeveen Drenthe 7902 CN",
    "addr:housenumber":"2",
    "addr:postcode":"7902 cn",
    "iso:country":"NL",
    "sg:address":"Kl Kerkstr 2",
    "sg:city":"Hoogeveen",
    "sg:orig_category":"Muziekinstrumenten En Bladmuziek",
    "sg:phone":"+31 528 234 512",
    "sg:postcode":"7902 CN",
    "sg:province":"Drenthe",
    "sg:website":"HTTP://www.freetimemusic.org",
    "wof:name":"Free Time Music",
    "wof:placetype":"venue"
},
  "geometry": {"coordinates":[6.479956,52.725464],"type":"Point"}
}