{
  "type": "Feature",
  "properties": {
    "addr:full":"Heistr 110 Helmond Noord-Brabant 5701 HR",
    "addr:housenumber":"110",
    "addr:postcode":"5701 hr",
    "iso:country":"NL",
    "sg:address":"Heistr 110",
    "sg:city":"Helmond",
    "sg:orig_category":"Gordijnen",
    "sg:phone":"+31 492 538 408",
    "sg:postcode":"5701 HR",
    "sg:province":"Noord-Brabant",
    "wof:name":"Gordijnenhuis Vof, Het",
    "wof:placetype":"venue"
},
  "geometry": {"coordinates":[5.660766,51.483303],"type":"Point"}
}