{
  "type": "Feature",
  "properties": {
    "iso:country":"NL",
    "sg:address":"Oude Kerkstraat 28",
    "sg:city":"Duizel",
    "sg:orig_category":"Meubelreparatie And -Restauratie",
    "sg:phone":"+31 497 516 295",
    "sg:postcode":"5525 AV",
    "sg:province":"Noord-Brabant",
    "wof:name":"Henk Kox Meubelstoffering Vof",
    "wof:placetype":"venue"
},
  "geometry": {"coordinates":[5.294217,51.368195],"type":"Point"}
}