{
  "type": "Feature",
  "properties": {
    "iso:country":"NL",
    "sg:address":"Refelingse Erven 122",
    "sg:city":"Nuenen",
    "sg:orig_category":"Kantoor- En Secretariaatsservice",
    "sg:phone":"+31 40 284 5392",
    "sg:postcode":"5672 TH",
    "sg:province":"North Brabant",
    "wof:name":"Multi-Mate",
    "wof:placetype":"venue"
},
  "geometry": {"coordinates":[5.5575881004,51.4644241333],"type":"Point"}
}