{
  "type": "Feature",
  "properties": {
    "iso:country":"NL",
    "sg:address":"Zutfensestr 99",
    "sg:city":"S Gravenhage",
    "sg:orig_category":"Grafisch Ontwerpers",
    "sg:phone":"+31 70 350 6011",
    "sg:postcode":"2587 TN",
    "sg:province":"South Holland",
    "sg:website":"http://www.xs4all.nl/~bdj",
    "wof:name":"Jong Lambert, De",
    "wof:placetype":"venue"
},
  "geometry": {"coordinates":[4.29118,52.112942],"type":"Point"}
}