{
  "type": "Feature",
  "properties": {
    "iso:country":"NL",
    "sg:address":"Energieweg 7",
    "sg:city":"Hapert",
    "sg:orig_category":"Metaalbekleding And -Behandeling",
    "sg:phone":"+31 497 384 252",
    "sg:postcode":"5527 AH",
    "sg:province":"North Brabant",
    "wof:name":"Van Mook Graveertechnieken Bv",
    "wof:placetype":"venue"
},
  "geometry": {"coordinates":[5.270093,51.37093],"type":"Point"}
}