{
  "type": "Feature",
  "properties": {
    "addr:full":"Schimmelpenninckstraat 5 Drunen Noord-Brabant 5151 CL",
    "addr:housenumber":"5",
    "addr:postcode":"5151",
    "addr:street":"Schimmelpenninckstraat",
    "iso:country":"NL",
    "sg:address":"Schimmelpenninckstraat 5",
    "sg:city":"Drunen",
    "sg:orig_category":"Metaalwerken",
    "sg:phone":"+31 416 320 599",
    "sg:postcode":"5151 CL",
    "sg:province":"Noord-Brabant",
    "wof:name":"De Kanter Systeem- En Interieurbouw",
    "wof:placetype":"venue"
},
  "geometry": {"coordinates":[5.133452,51.682808],"type":"Point"}
}