{
  "type": "Feature",
  "properties": {
    "addr:full":"Hullenwg 6 Roden Provincie Drenthe 9301 ZD",
    "addr:housenumber":"6",
    "addr:postcode":"9301 zd",
    "addr:street":"Hullenwg;Provincie Drenthe",
    "iso:country":"NL",
    "sg:address":"Hullenwg 6",
    "sg:city":"Roden",
    "sg:orig_category":"Vakantieverblijven",
    "sg:phone":"+31 50 501 8125",
    "sg:postcode":"9301 ZD",
    "sg:province":"Provincie Drenthe",
    "sg:website":"http://www.drentnet.nl",
    "wof:name":"Hullen Vof, De",
    "wof:placetype":"venue"
},
  "geometry": {"coordinates":[6.432945,53.137001],"type":"Point"}
}