{
  "type": "Feature",
  "properties": {
    "addr:full":"I Vorrinkstr 29 Culemborg Gelderland 4105 JA",
    "addr:housenumber":"29",
    "addr:postcode":"4105 ja",
    "addr:street":"Gelderland",
    "iso:country":"NL",
    "sg:address":"I Vorrinkstr 29",
    "sg:city":"Culemborg",
    "sg:orig_category":"Facilitaire Dienstverlening",
    "sg:phone":"+31 345 533 170",
    "sg:postcode":"4105 JA",
    "sg:province":"Gelderland",
    "sg:website":"http://www.vertas.nl",
    "wof:name":"Vertas",
    "wof:placetype":"venue"
},
  "geometry": {"coordinates":[5.22148,51.952175],"type":"Point"}
}