{
  "type": "Feature",
  "properties": {
    "addr:full":"Geerdinkswg 3939 Hengelo Ov NL.08 7555 DG",
    "addr:housenumber":"3939",
    "addr:postcode":"7555 dg",
    "addr:street":"Ov",
    "iso:country":"NL",
    "sg:address":"Geerdinkswg 3939",
    "sg:city":"Hengelo Ov",
    "sg:orig_category":"Podotherapeuten",
    "sg:phone":"+31 74 242 5313",
    "sg:postcode":"7555 DG",
    "sg:province":"NL.08",
    "wof:name":"Thoma, B G M",
    "wof:placetype":"venue"
},
  "geometry": {"coordinates":[6.77656,52.2682],"type":"Point"}
}