{
  "type": "Feature",
  "properties": {
    "addr:full":"Ceintuurbaan 5A Huizen North Holland 1271 BE",
    "addr:housenumber":"5a",
    "addr:postcode":"1271",
    "addr:street":"Ceintuurbaan",
    "iso:country":"NL",
    "sg:address":"Ceintuurbaan 5A",
    "sg:city":"Huizen",
    "sg:orig_category":"Verzekeringen - Verzekeringskantoren",
    "sg:phone":"+31 35 525 9490",
    "sg:postcode":"1271 BE",
    "sg:province":"North Holland",
    "wof:name":"Hart & Teeuwissen, 'T",
    "wof:placetype":"venue"
},
  "geometry": {"coordinates":[5.232732,52.296864],"type":"Point"}
}