{
  "type": "Feature",
  "properties": {
    "addr:full":"Scharreveld 54 Haarlem Noord-Holland 2036 BE",
    "addr:housenumber":"54",
    "addr:postcode":"2036",
    "addr:street":"Scharreveld",
    "iso:country":"NL",
    "sg:address":"Scharreveld 54",
    "sg:city":"Haarlem",
    "sg:orig_category":"Boekhouders",
    "sg:phone":"+31 23 535 2606",
    "sg:postcode":"2036 BE",
    "sg:province":"Noord-Holland",
    "wof:name":"Administratiekantoor Blokker",
    "wof:placetype":"venue"
},
  "geometry": {"coordinates":[4.655636,52.352718],"type":"Point"}
}