{
  "type": "Feature",
  "properties": {
    "iso:country":"NL",
    "sg:address":"Willemsparkweg 181",
    "sg:city":"Amsterdam",
    "sg:orig_category":"Fietsen En Bromfietsen",
    "sg:phone":"+31 20 662 2380",
    "sg:postcode":"1071 HA",
    "sg:province":"Noord-Holland",
    "wof:name":"Jan Van Wijk",
    "wof:placetype":"venue"
},
  "geometry": {"coordinates":[4.870102,52.355724],"type":"Point"}
}