{
  "type": "Feature",
  "properties": {
    "addr:full":"Willemsparkweg 181 Amsterdam Noord-Holland 1071 HA",
    "addr:housenumber":"181",
    "addr:postcode":"1071 ha",
    "addr:street":"Willemsparkweg",
    "iso:country":"NL",
    "sg:address":"Willemsparkweg 181",
    "sg:city":"Amsterdam",
    "sg:orig_category":"Fietsen En Bromfietsen",
    "sg:phone":"+31 20 662 2380",
    "sg:postcode":"1071 HA",
    "sg:province":"Noord-Holland",
    "wof:name":"Jan Van Wijk",
    "wof:placetype":"venue"
},
  "geometry": {"coordinates":[4.870102,52.355724],"type":"Point"}
}