{
  "type": "Feature",
  "properties": {
    "addr:full":"Heliconwg 40-A Leeuwarden Friesland 8914 AT",
    "addr:housenumber":"40-a",
    "addr:postcode":"8914",
    "addr:street":"Heliconwg",
    "iso:country":"NL",
    "sg:address":"Heliconwg 40-A",
    "sg:city":"Leeuwarden",
    "sg:orig_category":"Autorijscholen",
    "sg:phone":"+31 58 213 5420",
    "sg:postcode":"8914 AT",
    "sg:province":"Friesland",
    "sg:website":"http://www.vandijk.to",
    "wof:name":"Dijk, Verkeersschool Van",
    "wof:placetype":"venue"
},
  "geometry": {"coordinates":[5.775307,53.202629],"type":"Point"}
}