{
  "type": "Feature",
  "properties": {
    "addr:full":"Hoofdweg 13 Klijndijk Drenthe 7871 TB",
    "addr:housenumber":"13",
    "addr:postcode":"7871 tb",
    "addr:street":"Hoofdweg",
    "iso:country":"NL",
    "sg:address":"Hoofdweg 13",
    "sg:city":"Klijndijk",
    "sg:orig_category":"Aannemers Woningbouw",
    "sg:phone":"+31 591 513 476",
    "sg:postcode":"7871 TB",
    "sg:province":"Drenthe",
    "wof:name":"Hendriks H.",
    "wof:placetype":"venue"
},
  "geometry": {"coordinates":[6.853096,52.835217],"type":"Point"}
}