{
  "type": "Feature",
  "properties": {
    "addr:full":"Ds Vd Kraanplnts 20 Bunnik Utrecht 3981 GN",
    "addr:housenumber":"20",
    "addr:postcode":"3981 gn",
    "addr:street":"Ds Vd Kraanplnts",
    "iso:country":"NL",
    "sg:address":"Ds Vd Kraanplnts 20",
    "sg:city":"Bunnik",
    "sg:orig_category":"Adviesbureaus Bedrijfsorganisatie",
    "sg:phone":"+31 30 657 1811",
    "sg:postcode":"3981 GN",
    "sg:province":"Utrecht",
    "wof:name":"Okapi",
    "wof:placetype":"venue"
},
  "geometry": {"coordinates":[5.19958,52.067097],"type":"Point"}
}