{
  "type": "Feature",
  "properties": {
    "addr:full":"Barrevoetestr 14A Haarlem Noord-Holland 2011 WP",
    "addr:housenumber":"14a",
    "addr:postcode":"2011 wp",
    "addr:street":"Barrevoetestr",
    "iso:country":"NL",
    "sg:address":"Barrevoetestr 14A",
    "sg:city":"Haarlem",
    "sg:orig_category":"Kunstgebitten",
    "sg:phone":"+31 23 531 4416",
    "sg:postcode":"2011 WP",
    "sg:province":"Noord-Holland",
    "wof:name":"Merkelbag Tandprothetische Praktijk",
    "wof:placetype":"venue"
},
  "geometry": {"coordinates":[4.630552,52.379887],"type":"Point"}
}