{
  "type": "Feature",
  "properties": {
    "addr:full":"Nw Keizersgr 58-Ii Amsterdam North Holland 1018 DT",
    "addr:housenumber":"58-ii",
    "addr:postcode":"1018 dt",
    "addr:street":"Keizersgr",
    "iso:country":"NL",
    "sg:address":"Nw Keizersgr 58-Ii",
    "sg:city":"Amsterdam",
    "sg:orig_category":"Psychotherapeuten",
    "sg:phone":"+31 20 470 8821",
    "sg:postcode":"1018 DT",
    "sg:province":"North Holland",
    "wof:name":"Michel, A H",
    "wof:placetype":"venue"
},
  "geometry": {"coordinates":[4.893195,52.373119],"type":"Point"}
}