{
  "type": "Feature",
  "properties": {
    "iso:country":"NL",
    "sg:address":"Loosduinsewg 15",
    "sg:city":"S Gravenhage",
    "sg:orig_category":"Verenigingen En Stichtingen",
    "sg:phone":"+31 70 346 5810",
    "sg:postcode":"2571 AA",
    "sg:province":"Zuid-Holland",
    "wof:name":"Vshg",
    "wof:placetype":"venue"
},
  "geometry": {"coordinates":[4.29037,52.06884],"type":"Point"}
}