{
  "type": "Feature",
  "properties": {
    "addr:full":"Stationsstraat 18 Drunen North Brabant 5151 HB",
    "addr:housenumber":"18",
    "addr:postcode":"5151 hb",
    "addr:street":"Stationsstraat",
    "iso:country":"NL",
    "sg:address":"Stationsstraat 18",
    "sg:city":"Drunen",
    "sg:orig_category":"Baby- And Kinderkleding",
    "sg:phone":"+31 416 372 206",
    "sg:postcode":"5151 HB",
    "sg:province":"North Brabant",
    "wof:name":"Boerenbond",
    "wof:placetype":"venue"
},
  "geometry": {"coordinates":[5.131863,51.689388],"type":"Point"}
}