{
  "type": "Feature",
  "properties": {
    "iso:country":"NL",
    "sg:address":"Stroombaan 6",
    "sg:city":"Amstelveen",
    "sg:orig_category":"Administratie- En Boekhoudkantoren",
    "sg:phone":"+31 20 426 3530",
    "sg:postcode":"1181 VX",
    "sg:province":"North Holland",
    "wof:name":"Admiprofs Bv",
    "wof:placetype":"venue"
},
  "geometry": {"coordinates":[4.869537,52.302402],"type":"Point"}
}