{
  "type": "Feature",
  "properties": {
    "addr:full":"Schuitenhuisstraat 5 Amsterdam Noord-Holland 1069 WK",
    "addr:housenumber":"5",
    "addr:postcode":"1069 wk",
    "addr:street":"Schuitenhuisstraat",
    "iso:country":"NL",
    "sg:address":"Schuitenhuisstraat 5",
    "sg:city":"Amsterdam",
    "sg:classifiers":[
        {
            "category":"Education",
            "subcategory":"Preschool",
            "type":"Public Place"
        }
    ],
    "sg:phone":"+31 20 619 0268",
    "sg:postcode":"1069 WK",
    "sg:province":"Noord-Holland",
    "sg:tags":[
        "kleuteronderwijs",
        "basis-"
    ],
    "wof:name":"Dr. W.A. Visser 'T Hooftschool",
    "wof:placetype":"venue"
},
  "geometry": {"coordinates":[4.786471,52.35788],"type":"Point"}
}