{
  "type": "Feature",
  "properties": {
    "addr:full":"Postbus 1030 Mydrecht Utrecht 3640 BA",
    "addr:postcode":"1030;3640 ba",
    "addr:street":"Postbus;Mydrecht",
    "iso:country":"NL",
    "sg:address":"Postbus 1030",
    "sg:city":"Mydrecht",
    "sg:orig_category":"Kinderopvang",
    "sg:phone":"+31 297 214 436",
    "sg:postcode":"3640 BA",
    "sg:province":"Utrecht",
    "sg:website":"http://www.kidsfirst.nl",
    "wof:name":"Kids First Kinderopvang",
    "wof:placetype":"venue"
},
  "geometry": {"coordinates":[4.86584,52.2075],"type":"Point"}
}