{
  "type": "Feature",
  "properties": {
    "addr:full":"Koudenhorn 54-56 Haarlem North Holland 2011 JD",
    "addr:housenumber":"54-56",
    "addr:postcode":"2011 jd",
    "addr:street":"Koudenhorn",
    "iso:country":"NL",
    "sg:address":"Koudenhorn 54-56",
    "sg:city":"Haarlem",
    "sg:orig_category":"Autoradio'S",
    "sg:phone":"+31 23 531 6778",
    "sg:postcode":"2011 JD",
    "sg:province":"North Holland",
    "wof:name":"Snijders",
    "wof:placetype":"venue"
},
  "geometry": {"coordinates":[4.642487,52.382339],"type":"Point"}
}