{
  "type": "Feature",
  "properties": {
    "iso:country":"NL",
    "sg:address":"V S V Ysseltstr 8",
    "sg:city":"Boxmeer",
    "sg:orig_category":"Logopedisten",
    "sg:phone":"+31 485 541 976",
    "sg:postcode":"5831 HD",
    "sg:province":"Noord-Brabant",
    "wof:name":"Martens, Antoinette",
    "wof:placetype":"venue"
},
  "geometry": {"coordinates":[5.950357,51.646206],"type":"Point"}
}