{
  "type": "Feature",
  "properties": {
    "addr:full":"Lindendreef 4 Vlaardingen Zuid-Holland 3137 CM",
    "addr:housenumber":"4",
    "addr:postcode":"3137 cm",
    "addr:street":"Lindendreef",
    "iso:country":"NL",
    "sg:address":"Lindendreef 4",
    "sg:city":"Vlaardingen",
    "sg:orig_category":"Hypotheken And Hypotheekbanken",
    "sg:phone":"+31 10 474 5055",
    "sg:postcode":"3137 CM",
    "sg:province":"Zuid-Holland",
    "wof:name":"Lensvelt",
    "wof:placetype":"venue"
},
  "geometry": {"coordinates":[4.34375,51.938442],"type":"Point"}
}