{
  "type": "Feature",
  "properties": {
    "addr:full":"Stationstraat 6 Steijl Limburg 5935 RA",
    "addr:housenumber":"6",
    "addr:postcode":"5935 ra",
    "addr:street":"Stationstraat",
    "iso:country":"NL",
    "sg:address":"Stationstraat 6",
    "sg:city":"Steijl",
    "sg:orig_category":"Autokeuringen",
    "sg:phone":"+31 77 373 0220",
    "sg:postcode":"5935 RA",
    "sg:province":"Limburg",
    "wof:name":"S. Koopmans Auto'S",
    "wof:placetype":"venue"
},
  "geometry": {"coordinates":[6.12579,51.335209],"type":"Point"}
}