{
  "type": "Feature",
  "properties": {
    "addr:full":"Dr H P Bremmerstr 54 S Gravenhage Zuid-Holland 2552 MJ",
    "addr:housenumber":"54;gravenhage",
    "addr:postcode":"2552 mj",
    "addr:street":"Dr;S",
    "iso:country":"NL",
    "sg:address":"Dr H P Bremmerstr 54",
    "sg:city":"S Gravenhage",
    "sg:orig_category":"Geluidsinstallaties",
    "sg:phone":"+31 70 397 4680",
    "sg:postcode":"2552 MJ",
    "sg:province":"Zuid-Holland",
    "wof:name":"What'S Watt",
    "wof:placetype":"venue"
},
  "geometry": {"coordinates":[4.24958,52.053631],"type":"Point"}
}