{
  "type": "Feature",
  "properties": {
    "addr:full":"Buitengrave 12 Dordrecht Zuid-Holland 3317 MH",
    "addr:housenumber":"12",
    "addr:postcode":"3317 mh",
    "addr:street":"Buitengrave",
    "iso:country":"NL",
    "sg:address":"Buitengrave 12",
    "sg:city":"Dordrecht",
    "sg:orig_category":"Adviesbureaus Automatisering",
    "sg:phone":"+31 78 618 9903",
    "sg:postcode":"3317 MH",
    "sg:province":"Zuid-Holland",
    "wof:name":"Procyon",
    "wof:placetype":"venue"
},
  "geometry": {"coordinates":[4.65886,51.78006],"type":"Point"}
}