{
  "type": "Feature",
  "properties": {
    "addr:full":"Aalsvoort 41 Lochem Gelderland 7241 MA",
    "addr:housenumber":"41",
    "addr:postcode":"7241 ma",
    "addr:street":"Aalsvoort;Gelderland",
    "iso:country":"NL",
    "sg:address":"Aalsvoort 41",
    "sg:city":"Lochem",
    "sg:orig_category":"Loodgieters",
    "sg:phone":"+31 573 251 008",
    "sg:postcode":"7241 MA",
    "sg:province":"Gelderland",
    "wof:name":"Dijkerman & Lammers Bv",
    "wof:placetype":"venue"
},
  "geometry": {"coordinates":[6.385707,52.168129],"type":"Point"}
}