{
  "type": "Feature",
  "properties": {
    "addr:full":"Laarderheerd 4 Weert Limburg 6003 PB",
    "addr:housenumber":"4",
    "addr:postcode":"6003 pb",
    "addr:street":"Laarderheerd",
    "iso:country":"NL",
    "sg:address":"Laarderheerd 4",
    "sg:city":"Weert",
    "sg:orig_category":"Kantoorapparatuur Gh",
    "sg:phone":"+31 495 534 842",
    "sg:postcode":"6003 PB",
    "sg:province":"Limburg",
    "wof:name":"Retail Supplies J.F.P. Van Goor",
    "wof:placetype":"venue"
},
  "geometry": {"coordinates":[5.7050361633,51.2765579224],"type":"Point"}
}