{
  "type": "Feature",
  "properties": {
    "addr:full":"Clematisstr 53 Breda Noord-Brabant 4814 JX",
    "addr:housenumber":"53",
    "addr:postcode":"4814 jx",
    "addr:street":"Clematisstr",
    "iso:country":"NL",
    "sg:address":"Clematisstr 53",
    "sg:city":"Breda",
    "sg:orig_category":"Kappers",
    "sg:phone":"+31 76 521 5571",
    "sg:postcode":"4814 JX",
    "sg:province":"Noord-Brabant",
    "wof:name":"Leidner, Haarstudio",
    "wof:placetype":"venue"
},
  "geometry": {"coordinates":[4.753193,51.587261],"type":"Point"}
}