{
  "type": "Feature",
  "properties": {
    "iso:country":"NL",
    "sg:address":"Horthoekerweg 31",
    "sg:city":"Oene",
    "sg:orig_category":"Levende Dieren Gh",
    "sg:phone":"+31 578 641 387",
    "sg:postcode":"8167 LV",
    "sg:province":"Nevada",
    "wof:name":"Veehandel W. Telintel",
    "wof:placetype":"venue"
},
  "geometry": {"coordinates":[-115.139748,36.171848],"type":"Point"}
}