{
  "type": "Feature",
  "properties": {
    "addr:full":"De Hoefsmid 26 St Michielsgestel North Brabant 5272 RK",
    "addr:housenumber":"26",
    "addr:postcode":"5272 rk",
    "addr:street":"De Hoefsmid",
    "iso:country":"NL",
    "sg:address":"De Hoefsmid 26",
    "sg:city":"St Michielsgestel",
    "sg:orig_category":"Adviesbureaus Bouwkunde",
    "sg:phone":"+31 73 553 0617",
    "sg:postcode":"5272 RK",
    "sg:province":"North Brabant",
    "wof:name":"Bfb Linea",
    "wof:placetype":"venue"
},
  "geometry": {"coordinates":[5.360409,51.6483],"type":"Point"}
}