{
  "type": "Feature",
  "properties": {
    "addr:full":"Kerkstraat 18 Almere Flevoland 1354 AB",
    "addr:housenumber":"18",
    "addr:postcode":"1354 ab",
    "addr:street":"Kerkstraat;Flevoland",
    "iso:country":"NL",
    "sg:address":"Kerkstraat 18",
    "sg:city":"Almere",
    "sg:orig_category":"Marktonderzoekbureaus",
    "sg:phone":"+31 36 531 4604",
    "sg:postcode":"1354 AB",
    "sg:province":"Flevoland",
    "wof:name":"Veldwerk Organisatie Mobil Centre Bv",
    "wof:placetype":"venue"
},
  "geometry": {"coordinates":[5.219687,52.335464],"type":"Point"}
}