{
  "type": "Feature",
  "properties": {
    "iso:country":"NL",
    "sg:address":"Postbus 14",
    "sg:city":"Wekerom",
    "sg:orig_category":"Verenigingsgebouwen",
    "sg:phone":"+31 318 462 044",
    "sg:postcode":"6733 ZG",
    "sg:province":"Gelderland",
    "wof:name":"Kastanjehof, De",
    "wof:placetype":"venue"
},
  "geometry": {"coordinates":[5.71421,52.111546],"type":"Point"}
}