{
  "type": "Feature",
  "properties": {
    "addr:full":"Hoofdstraat 46 Veenendaal Utrecht 3901 AR",
    "addr:housenumber":"46",
    "addr:postcode":"3901",
    "addr:street":"Hoofdstraat",
    "iso:country":"NL",
    "sg:address":"Hoofdstraat 46",
    "sg:city":"Veenendaal",
    "sg:orig_category":"Herenmodezaken",
    "sg:phone":"+31 318 548 027",
    "sg:postcode":"3901 AR",
    "sg:province":"Utrecht",
    "wof:name":"Van Os Herenmode",
    "wof:placetype":"venue"
},
  "geometry": {"coordinates":[5.556221,52.027271],"type":"Point"}
}