{
  "type": "Feature",
  "properties": {
    "addr:full":"Heisterberg 53 Hoensbroek Limburg 6431 JB",
    "addr:housenumber":"53",
    "addr:postcode":"6431 jb",
    "addr:street":"Heisterberg",
    "iso:country":"NL",
    "sg:address":"Heisterberg 53",
    "sg:city":"Hoensbroek",
    "sg:classifiers":[
        {
            "category":"Fast Food",
            "type":"Food & Drink"
        }
    ],
    "sg:phone":"+31 45 522 4509",
    "sg:postcode":"6431 JB",
    "sg:province":"Limburg",
    "sg:tags":[
        "afhaal",
        "restaurant"
    ],
    "wof:name":"Cafetaria De Heister",
    "wof:placetype":"venue"
},
  "geometry": {"coordinates":[5.937239,50.927017],"type":"Point"}
}