{
  "type": "Feature",
  "properties": {
    "addr:full":"P Sipmawei 7 Leeuwarden Provincie Friesland 8915 DZ",
    "addr:housenumber":"7",
    "addr:postcode":"8915 dz",
    "addr:street":"P Sipmawei;Provincie Friesland",
    "iso:country":"NL",
    "sg:address":"P Sipmawei 7",
    "sg:city":"Leeuwarden",
    "sg:orig_category":"Kappers",
    "sg:phone":"+31 58 215 5479",
    "sg:postcode":"8915 DZ",
    "sg:province":"Provincie Friesland",
    "sg:website":"http://www.kapsalon-kingma.com",
    "wof:name":"Kingma Gemengde Kapsalon",
    "wof:placetype":"venue"
},
  "geometry": {"coordinates":[5.7681698799,53.2080116272],"type":"Point"}
}