{
  "type": "Feature",
  "properties": {
    "addr:full":"Bikolaan 189 Delft Zuid-Holland 2622 GS",
    "addr:housenumber":"189",
    "addr:postcode":"2622 gs",
    "addr:street":"Bikolaan",
    "iso:country":"NL",
    "sg:address":"Bikolaan 189",
    "sg:city":"Delft",
    "sg:orig_category":"Postkantoren",
    "sg:phone":"+31 15 262 1453",
    "sg:postcode":"2622 GS",
    "sg:province":"Zuid-Holland",
    "wof:name":"Postkantoor",
    "wof:placetype":"venue"
},
  "geometry": {"coordinates":[4.345732,51.982006],"type":"Point"}
}