{
  "type": "Feature",
  "properties": {
    "addr:full":"Smidsweg 19 Bathmen Overijssel 7437 CC",
    "addr:housenumber":"19",
    "addr:postcode":"7437 cc",
    "addr:street":"Smidsweg",
    "iso:country":"NL",
    "sg:address":"Smidsweg 19",
    "sg:city":"Bathmen",
    "sg:orig_category":"Goederenvervoer Over De Weg",
    "sg:phone":"+31 570 543 253",
    "sg:postcode":"7437 CC",
    "sg:province":"Overijssel",
    "wof:name":"Jab Transport",
    "wof:placetype":"venue"
},
  "geometry": {"coordinates":[6.291225,52.250408],"type":"Point"}
}