{
  "type": "Feature",
  "properties": {
    "addr:full":"Roosendaalsebaan 9 Schyf Noord-Brabant 4721 SH",
    "addr:housenumber":"9",
    "addr:postcode":"4721 sh",
    "addr:street":"Roosendaalsebaan",
    "iso:country":"NL",
    "sg:address":"Roosendaalsebaan 9",
    "sg:city":"Schyf",
    "sg:orig_category":"Parketvloeren",
    "sg:phone":"+31 165 342 630",
    "sg:postcode":"4721 SH",
    "sg:province":"Noord-Brabant",
    "wof:name":"Hooydonk, A Van",
    "wof:placetype":"venue"
},
  "geometry": {"coordinates":[4.553681,51.49889],"type":"Point"}
}