{
  "type": "Feature",
  "properties": {
    "addr:full":"Bennenbroekstr 48 Someren North Brabant 5712 BM",
    "addr:housenumber":"48",
    "addr:postcode":"5712 bm",
    "addr:street":"Bennenbroekstr",
    "iso:country":"NL",
    "sg:address":"Bennenbroekstr 48",
    "sg:city":"Someren",
    "sg:orig_category":"Pluimveebedrijven En -Handelaren",
    "sg:phone":"+31 493 492 461",
    "sg:postcode":"5712 BM",
    "sg:province":"North Brabant",
    "wof:name":"Laar & Couperus Bv, Van De",
    "wof:placetype":"venue"
},
  "geometry": {"coordinates":[5.734194,51.351318],"type":"Point"}
}