{
  "type": "Feature",
  "properties": {
    "addr:full":"Kruisberg 46 Meerssen Limburg 6231 RK",
    "addr:housenumber":"46",
    "addr:postcode":"6231 rk",
    "addr:street":"Kruisberg",
    "iso:country":"NL",
    "sg:address":"Kruisberg 46",
    "sg:city":"Meerssen",
    "sg:orig_category":"Keukens",
    "sg:phone":"+31 43 364 2535",
    "sg:postcode":"6231 RK",
    "sg:province":"Limburg",
    "sg:website":"http://www.zambon-design.nl",
    "wof:name":"Zambon",
    "wof:placetype":"venue"
},
  "geometry": {"coordinates":[5.743599,50.892773],"type":"Point"}
}