{
  "type": "Feature",
  "properties": {
    "iso:country":"NL",
    "sg:address":"Fazantstr 7",
    "sg:city":"Wieringerwerf",
    "sg:orig_category":"Postkantoren",
    "sg:phone":"+31 227 600 237",
    "sg:postcode":"1771 CP",
    "sg:province":"North Holland",
    "sg:website":"http://www.postkantoor.nl",
    "wof:name":"Postkantoor",
    "wof:placetype":"venue"
},
  "geometry": {"coordinates":[5.023933,52.854286],"type":"Point"}
}