{
  "type": "Feature",
  "properties": {
    "addr:full":"Portus 2 Poortugaal Zuid-Holland 3176 TG",
    "addr:housenumber":"2",
    "addr:postcode":"3176 tg",
    "addr:street":"Portus",
    "iso:country":"NL",
    "sg:address":"Portus 2",
    "sg:city":"Poortugaal",
    "sg:orig_category":"Administratie- En Boekhoudkantoren",
    "sg:phone":"+31 10 483 0405",
    "sg:postcode":"3176 TG",
    "sg:province":"Zuid-Holland",
    "wof:name":"Cepas",
    "wof:placetype":"venue"
},
  "geometry": {"coordinates":[4.399179,51.862396],"type":"Point"}
}