{
  "type": "Feature",
  "properties": {
    "addr:full":"Helmstr 3 Maastricht Limburg 6211 TA",
    "addr:housenumber":"3",
    "addr:postcode":"6211 ta",
    "addr:street":"Helmstr",
    "iso:country":"NL",
    "sg:address":"Helmstr 3",
    "sg:city":"Maastricht",
    "sg:orig_category":"Warenhuizen",
    "sg:phone":"+31 43 351 0289",
    "sg:postcode":"6211 TA",
    "sg:province":"Limburg",
    "wof:name":"Xenos Bv",
    "wof:placetype":"venue"
},
  "geometry": {"coordinates":[5.689330101,50.8503761292],"type":"Point"}
}