{
  "type": "Feature",
  "properties": {
    "iso:country":"NL",
    "sg:address":"Willibrorduslaan 94",
    "sg:city":"Valkenswaard",
    "sg:orig_category":"Kinderopvang Behalve Thuis",
    "sg:phone":"+31 40 204 4339",
    "sg:postcode":"5552 HE",
    "sg:province":"North Brabant",
    "wof:name":"Kinderopvang De Horizon",
    "wof:placetype":"venue"
},
  "geometry": {"coordinates":[5.45566,51.358612],"type":"Point"}
}