{
  "type": "Feature",
  "properties": {
    "addr:full":"Pres Kennedyln 783 Amsterdam Noord-Holland 1079 MS",
    "addr:housenumber":"783",
    "addr:postcode":"1079 ms",
    "iso:country":"NL",
    "sg:address":"Pres Kennedyln 783",
    "sg:city":"Amsterdam",
    "sg:orig_category":"Autoverhuur",
    "sg:phone":"+31 20 644 3684",
    "sg:postcode":"1079 MS",
    "sg:province":"Noord-Holland",
    "sg:website":"http://www.avis.nl",
    "wof:name":"Avis Autoverhuur",
    "wof:placetype":"venue"
},
  "geometry": {"coordinates":[4.89319,52.373119],"type":"Point"}
}