{
  "type": "Feature",
  "properties": {
    "addr:full":"Kerkstr 76 Wognum Noord-Holland 1687 AT",
    "addr:housenumber":"76",
    "addr:postcode":"1687",
    "addr:street":"Kerkstr",
    "iso:country":"NL",
    "sg:address":"Kerkstr 76",
    "sg:city":"Wognum",
    "sg:orig_category":"Logopedisten",
    "sg:phone":"+31 229 573 237",
    "sg:postcode":"1687 AT",
    "sg:province":"Noord-Holland",
    "wof:name":"Logopediepraktijk Wognum",
    "wof:placetype":"venue"
},
  "geometry": {"coordinates":[5.019371,52.686836],"type":"Point"}
}