{
  "type": "Feature",
  "properties": {
    "addr:full":"Verwulft 2 Haarlem Noord-Holland 2011 GJ",
    "addr:housenumber":"2",
    "addr:postcode":"2011 gj",
    "addr:street":"Verwulft",
    "iso:country":"NL",
    "sg:address":"Verwulft 2",
    "sg:city":"Haarlem",
    "sg:orig_category":"Fotolaboratoria",
    "sg:phone":"+31 23 531 3390",
    "sg:postcode":"2011 GJ",
    "sg:province":"Noord-Holland",
    "wof:name":"Super Photo",
    "wof:placetype":"venue"
},
  "geometry": {"coordinates":[4.633076,52.379478],"type":"Point"}
}