{
  "type": "Feature",
  "properties": {
    "addr:full":"Begoniasingel 118 Geleen Limburg 6163 BG",
    "addr:housenumber":"118",
    "addr:postcode":"6163",
    "addr:street":"Begoniasingel",
    "iso:country":"NL",
    "sg:address":"Begoniasingel 118",
    "sg:city":"Geleen",
    "sg:orig_category":"Verzekeringen",
    "sg:phone":"+31 46 475 4444",
    "sg:postcode":"6163 BG",
    "sg:province":"Limburg",
    "wof:name":"Assurantiekantoor Meessen",
    "wof:placetype":"venue"
},
  "geometry": {"coordinates":[5.818773,50.986656],"type":"Point"}
}