{
  "type": "Feature",
  "properties": {
    "addr:full":"Nieuwewg 34 Oostwold Scheemda Groningen 9682 RM",
    "addr:housenumber":"34",
    "addr:postcode":"9682 rm",
    "addr:street":"Nieuwewg",
    "iso:country":"NL",
    "sg:address":"Nieuwewg 34",
    "sg:city":"Oostwold Scheemda",
    "sg:orig_category":"Koffie- En Theehuizen",
    "sg:phone":"+31 597 551 383",
    "sg:postcode":"9682 RM",
    "sg:province":"Groningen",
    "wof:name":"Tuinfleur",
    "wof:placetype":"venue"
},
  "geometry": {"coordinates":[7.056375,53.192356],"type":"Point"}
}