{
  "type": "Feature",
  "properties": {
    "addr:full":"Vondelstraat 16 'S Hertogenbosch Noord-Brabant 5216 HJ",
    "addr:housenumber":"16",
    "addr:postcode":"5216 hj",
    "addr:street":"Vondelstraat;' S",
    "iso:country":"NL",
    "sg:address":"Vondelstraat 16",
    "sg:city":"'S Hertogenbosch",
    "sg:orig_category":"Wasserettes And Stomerijen",
    "sg:phone":"+31 73 613 3562",
    "sg:postcode":"5216 HJ",
    "sg:province":"Noord-Brabant",
    "wof:name":"Vof Wassalon Zuid",
    "wof:placetype":"venue"
},
  "geometry": {"coordinates":[5.3245310783,51.6842536926],"type":"Point"}
}