{
  "type": "Feature",
  "properties": {
    "addr:full":"Ln Op Zuid 908 Rotterdam South Holland 3071 AC",
    "addr:housenumber":"908",
    "addr:postcode":"3071 ac",
    "addr:street":"Ln Op Zuid",
    "iso:country":"NL",
    "sg:address":"Ln Op Zuid 908",
    "sg:city":"Rotterdam",
    "sg:orig_category":"Kinderopvang",
    "sg:phone":"+31 10 423 2592",
    "sg:postcode":"3071 AC",
    "sg:province":"South Holland",
    "wof:name":"Bimbola",
    "wof:placetype":"venue"
},
  "geometry": {"coordinates":[4.501649,51.904911],"type":"Point"}
}