{
  "type": "Feature",
  "properties": {
    "addr:full":"Calsln 100 Gouda Zuid-Holland 2804 RT",
    "addr:housenumber":"100",
    "addr:postcode":"2804 rt",
    "iso:country":"NL",
    "sg:address":"Calsln 100",
    "sg:city":"Gouda",
    "sg:orig_category":"Scholen Voor Algemeen Voortgezet Onderwijs",
    "sg:phone":"+31 182 538 468",
    "sg:postcode":"2804 RT",
    "sg:province":"Zuid-Holland",
    "wof:name":"Brug Chr Svo Lom, De",
    "wof:placetype":"venue"
},
  "geometry": {"coordinates":[4.710715,52.010006],"type":"Point"}
}