{
  "type": "Feature",
  "properties": {
    "addr:full":"Hoofdstr 62 B Hoogeloon North Brabant 5528 AK",
    "addr:housenumber":"62 b",
    "addr:postcode":"5528 ak",
    "addr:street":"Hoofdstr",
    "iso:country":"NL",
    "sg:address":"Hoofdstr 62 B",
    "sg:city":"Hoogeloon",
    "sg:orig_category":"Schilders",
    "sg:phone":"+31 497 644 027",
    "sg:postcode":"5528 AK",
    "sg:province":"North Brabant",
    "wof:name":"Antonius, Schildersbedrijf",
    "wof:placetype":"venue"
},
  "geometry": {"coordinates":[5.266848,51.398201],"type":"Point"}
}