{
  "type": "Feature",
  "properties": {
    "addr:full":"V Z V Nyeveltstr 285 Wassenaar South Holland 2242 LJ",
    "addr:housenumber":"285",
    "addr:postcode":"2242 lj",
    "addr:street":"V Z V Nyeveltstr",
    "iso:country":"NL",
    "sg:address":"V Z V Nyeveltstr 285",
    "sg:city":"Wassenaar",
    "sg:orig_category":"Onroerende Goederen",
    "sg:phone":"+31 70 511 9110",
    "sg:postcode":"2242 LJ",
    "sg:province":"South Holland",
    "wof:name":"Brouwers Bv",
    "wof:placetype":"venue"
},
  "geometry": {"coordinates":[4.393863,52.14307],"type":"Point"}
}