{
  "type": "Feature",
  "properties": {
    "iso:country":"NL",
    "sg:address":"V Raveschotstr 1A",
    "sg:city":"Sprang Capelle",
    "sg:orig_category":"Antiquiteiten",
    "sg:phone":"+31 416 314 003",
    "sg:postcode":"5161 AX",
    "sg:province":"Noord-Brabant",
    "wof:name":"Hans Brokx",
    "wof:placetype":"venue"
},
  "geometry": {"coordinates":[5.02336,51.670841],"type":"Point"}
}