{
  "type": "Feature",
  "properties": {
    "iso:country":"NL",
    "sg:address":"Koningsdiep 29",
    "sg:city":"Brielle",
    "sg:orig_category":"Babyartikelen",
    "sg:phone":"+31 181 472 672",
    "sg:postcode":"3232 PG",
    "sg:province":"South Holland",
    "sg:website":"http://www.babybasket.nl",
    "wof:name":"Baby Basket Service",
    "wof:placetype":"venue"
},
  "geometry": {"coordinates":[4.176331,51.895199],"type":"Point"}
}