{
  "type": "Feature",
  "properties": {
    "addr:full":"Dykplan 4 Steenbergen Nb Noord-Brabant 4651 GT",
    "addr:housenumber":"4",
    "addr:postcode":"4651 gt",
    "addr:street":"Dykplan",
    "iso:country":"NL",
    "sg:address":"Dykplan 4",
    "sg:city":"Steenbergen Nb",
    "sg:orig_category":"Adviesbureaus Bedrijfsorganisatie",
    "sg:phone":"+31 167 540 248",
    "sg:postcode":"4651 GT",
    "sg:province":"Noord-Brabant",
    "sg:website":"http://www.himountain.nl",
    "wof:name":"Himountain",
    "wof:placetype":"venue"
},
  "geometry": {"coordinates":[4.314555,51.585594],"type":"Point"}
}