{
  "type": "Feature",
  "properties": {
    "addr:full":"Weyerkeswg 3 Weert Limburg 6003 PW",
    "addr:housenumber":"3",
    "addr:postcode":"6003 pw",
    "addr:street":"Weyerkeswg",
    "iso:country":"NL",
    "sg:address":"Weyerkeswg 3",
    "sg:city":"Weert",
    "sg:orig_category":"Hoefsmederijen",
    "sg:phone":"+31 495 533 869",
    "sg:postcode":"6003 PW",
    "sg:province":"Limburg",
    "wof:name":"Bocken, J A M",
    "wof:placetype":"venue"
},
  "geometry": {"coordinates":[5.677967,51.271812],"type":"Point"}
}