{
  "type": "Feature",
  "properties": {
    "addr:full":"Singelpark 3 Odijk Utrecht 3984 NC",
    "addr:housenumber":"3",
    "addr:postcode":"3984 nc",
    "addr:street":"Singelpark",
    "iso:country":"NL",
    "sg:address":"Singelpark 3",
    "sg:city":"Odijk",
    "sg:orig_category":"Politie",
    "sg:phone":"+31 900 8844",
    "sg:postcode":"3984 NC",
    "sg:province":"Utrecht",
    "wof:name":"Politie Regio Utrecht District Binnensticht",
    "wof:placetype":"venue"
},
  "geometry": {"coordinates":[5.226226,52.055481],"type":"Point"}
}