{
  "type": "Feature",
  "properties": {
    "addr:full":"Ternatestraat 16 Delft Zuid-Holland 2612 BD",
    "addr:housenumber":"16",
    "addr:postcode":"2612 bd",
    "addr:street":"Ternatestraat",
    "iso:country":"NL",
    "sg:address":"Ternatestraat 16",
    "sg:city":"Delft",
    "sg:orig_category":"Boekhouders",
    "sg:phone":"+31 15 212 3856",
    "sg:postcode":"2612 BD",
    "sg:province":"Zuid-Holland",
    "wof:name":"A K De Bruin",
    "wof:placetype":"venue"
},
  "geometry": {"coordinates":[4.353989,52.022682],"type":"Point"}
}