{
  "type": "Feature",
  "properties": {
    "addr:full":"Fultonstraat 4 Vlaardingen Zuid-Holland 3133 KH",
    "addr:housenumber":"4",
    "addr:postcode":"3133 kh",
    "addr:street":"Fultonstraat",
    "iso:country":"NL",
    "sg:address":"Fultonstraat 4",
    "sg:city":"Vlaardingen",
    "sg:orig_category":"Diverse Grafische Activiteiten",
    "sg:phone":"+31 10 460 0922",
    "sg:postcode":"3133 KH",
    "sg:province":"Zuid-Holland",
    "wof:name":"Zeefdrukkerij Triomf Bv",
    "wof:placetype":"venue"
},
  "geometry": {"coordinates":[4.311483,51.903816],"type":"Point"}
}