{
  "type": "Feature",
  "properties": {
    "iso:country":"NL",
    "sg:address":"Steenweg 7",
    "sg:city":"Wessem",
    "sg:orig_category":"Verlichting And Huishoudartikelen",
    "sg:phone":"+31 475 561 694",
    "sg:postcode":"6019 AW",
    "sg:province":"Limburg",
    "wof:name":"Vof Woninginrichting Maessen",
    "wof:placetype":"venue"
},
  "geometry": {"coordinates":[5.881049,51.158951],"type":"Point"}
}