{
  "type": "Feature",
  "properties": {
    "addr:full":"Hoofdstr 147A Posterholt Limburg 6061 CC",
    "addr:housenumber":"147a",
    "addr:postcode":"6061 cc",
    "iso:country":"NL",
    "sg:address":"Hoofdstr 147A",
    "sg:city":"Posterholt",
    "sg:orig_category":"Postkantoren",
    "sg:phone":"+31 475 401 210",
    "sg:postcode":"6061 CC",
    "sg:province":"Limburg",
    "sg:website":"http://www.postkantoor.nl",
    "wof:name":"Postkantoor",
    "wof:placetype":"venue"
},
  "geometry": {"coordinates":[6.037516,51.118652],"type":"Point"}
}