{
  "type": "Feature",
  "properties": {
    "addr:full":"O Nassaupln 8 Krimpen Aan De Lek South Holland 2931 CV",
    "addr:housenumber":"8",
    "addr:postcode":"2931 cv",
    "iso:country":"NL",
    "sg:address":"O Nassaupln 8",
    "sg:city":"Krimpen Aan De Lek",
    "sg:orig_category":"Kappers",
    "sg:phone":"+31 180 514 589",
    "sg:postcode":"2931 CV",
    "sg:province":"South Holland",
    "wof:name":"Jack",
    "wof:placetype":"venue"
},
  "geometry": {"coordinates":[4.6294031143,51.8936653137],"type":"Point"}
}