{
  "type": "Feature",
  "properties": {
    "iso:country":"NL",
    "sg:address":"Smaragdstraat 8",
    "sg:city":"Ede Gld",
    "sg:classifiers":[
        {
            "category":"Professional",
            "subcategory":"Accounting & Tax Preparation",
            "type":"Services"
        }
    ],
    "sg:phone":"+31 318 618 045",
    "sg:postcode":"6713 TJ",
    "sg:province":"Gelderland",
    "sg:tags":[
        "accountant"
    ],
    "wof:name":"Administratiekantoor C.J.A. Ooijendijk",
    "wof:placetype":"venue"
},
  "geometry": {"coordinates":[5.663941,52.041683],"type":"Point"}
}