{
  "type": "Feature",
  "properties": {
    "addr:full":"Oranjeln 52 Rozenburg Zh Zuid-Holland 3181 HA",
    "addr:housenumber":"52",
    "addr:postcode":"zh;3181 ha",
    "addr:street":"Oranjeln",
    "iso:country":"NL",
    "sg:address":"Oranjeln 52",
    "sg:city":"Rozenburg Zh",
    "sg:orig_category":"Loodgieters",
    "sg:phone":"+31 181 212 866",
    "sg:postcode":"3181 HA",
    "sg:province":"Zuid-Holland",
    "wof:name":"Noordzij Rozenburg Bv, Piet",
    "wof:placetype":"venue"
},
  "geometry": {"coordinates":[4.241977,51.901974],"type":"Point"}
}