{
  "type": "Feature",
  "properties": {
    "addr:full":"Parallelwg 17 Coevorden Drenthe 7741 KA",
    "addr:housenumber":"17",
    "addr:postcode":"7741 ka",
    "addr:street":"Parallelwg",
    "iso:country":"NL",
    "sg:address":"Parallelwg 17",
    "sg:city":"Coevorden",
    "sg:orig_category":"Meubelen",
    "sg:phone":"+31 524 515 708",
    "sg:postcode":"7741 KA",
    "sg:province":"Drenthe",
    "wof:name":"Kastenman, De",
    "wof:placetype":"venue"
},
  "geometry": {"coordinates":[6.734907,52.661667],"type":"Point"}
}