{
  "type": "Feature",
  "properties": {
    "addr:full":"Keizersdijk 19 Raamsdonksveer Noord-Brabant 4941 GC",
    "addr:housenumber":"19",
    "addr:postcode":"4941 gc",
    "addr:street":"Keizersdijk",
    "iso:country":"NL",
    "sg:address":"Keizersdijk 19",
    "sg:city":"Raamsdonksveer",
    "sg:classifiers":[
        {
            "category":"Bakery",
            "type":"Food & Drink"
        }
    ],
    "sg:phone":"+31 162 512 894",
    "sg:postcode":"4941 GC",
    "sg:province":"Noord-Brabant",
    "sg:tags":[
        "brood",
        "banket"
    ],
    "wof:name":"Edwin Broeders",
    "wof:placetype":"venue"
},
  "geometry": {"coordinates":[4.873843,51.696846],"type":"Point"}
}