{
  "type": "Feature",
  "properties": {
    "addr:full":"Veeartsenystr 141 Utrecht Utrecht 3572 DD",
    "addr:housenumber":"141",
    "addr:postcode":"3572 dd",
    "iso:country":"NL",
    "sg:address":"Veeartsenystr 141",
    "sg:city":"Utrecht",
    "sg:orig_category":"Loopbaanbegeleiding",
    "sg:phone":"+31 30 271 3571",
    "sg:postcode":"3572 DD",
    "sg:province":"Utrecht",
    "wof:name":"Op Koers",
    "wof:placetype":"venue"
},
  "geometry": {"coordinates":[5.137774,52.097282],"type":"Point"}
}