{
  "type": "Feature",
  "properties": {
    "addr:full":"Jachtfjild 11 Tietjerk Provincie Friesland 9255 JL",
    "addr:housenumber":"11",
    "addr:postcode":"9255 jl",
    "addr:street":"Jachtfjild;Provincie Friesland",
    "iso:country":"NL",
    "sg:address":"Jachtfjild 11",
    "sg:city":"Tietjerk",
    "sg:orig_category":"Administratie- En Boekhoudkantoren",
    "sg:phone":"+31 511 432 365",
    "sg:postcode":"9255 JL",
    "sg:province":"Provincie Friesland",
    "wof:name":"Administr Service",
    "wof:placetype":"venue"
},
  "geometry": {"coordinates":[5.896325,53.197521],"type":"Point"}
}