{
  "type": "Feature",
  "properties": {
    "iso:country":"NL",
    "sg:address":"Steutenwg 85A",
    "sg:city":"Nederweert Eind",
    "sg:orig_category":"Metaalbewerking",
    "sg:phone":"+31 495 632 530",
    "sg:postcode":"6034 SC",
    "sg:province":"Limburg",
    "wof:name":"Gog, Van",
    "wof:placetype":"venue"
},
  "geometry": {"coordinates":[5.787264,51.276524],"type":"Point"}
}