{
  "type": "Feature",
  "properties": {
    "addr:full":"Zeemansstraat 58 Zaandam Noord-Holland 1506 CV",
    "addr:housenumber":"58",
    "addr:postcode":"1506 cv",
    "addr:street":"Zeemansstraat",
    "iso:country":"NL",
    "sg:address":"Zeemansstraat 58",
    "sg:city":"Zaandam",
    "sg:orig_category":"Werving And Selectie Van Tijdelijk Personeel And Uitzendkantoren",
    "sg:phone":"+31 75 650 1050",
    "sg:postcode":"1506 CV",
    "sg:province":"Noord-Holland",
    "wof:name":"Pdz Uitzendburo Beheer Bv",
    "wof:placetype":"venue"
},
  "geometry": {"coordinates":[4.8200011253,52.4406394958],"type":"Point"}
}