{
  "type": "Feature",
  "properties": {
    "addr:full":"Oosterstreek 64 Oosterstreek Friesland 8388 NE",
    "addr:housenumber":"64",
    "addr:postcode":"8388 ne",
    "addr:street":"Oosterstreek",
    "iso:country":"NL",
    "sg:address":"Oosterstreek 64",
    "sg:city":"Oosterstreek",
    "sg:classifiers":[
        {
            "category":"Sports & Exercise",
            "subcategory":"Stables",
            "type":"Entertainment"
        }
    ],
    "sg:phone":"+31 561 433 819",
    "sg:postcode":"8388 NE",
    "sg:province":"Friesland",
    "sg:tags":[
        "maneges"
    ],
    "wof:name":"Schimmelhoeve, De",
    "wof:placetype":"venue"
},
  "geometry": {"coordinates":[6.163235,52.898422],"type":"Point"}
}