{
  "type": "Feature",
  "properties": {
    "addr:full":"Cannenburgerwg 63 A Ankeveen Noord-Holland 1244 RH",
    "addr:housenumber":"63 a",
    "addr:postcode":"1244 rh",
    "addr:street":"Cannenburgerwg",
    "iso:country":"NL",
    "sg:address":"Cannenburgerwg 63 A",
    "sg:city":"Ankeveen",
    "sg:classifiers":[
        {
            "category":"Professional",
            "subcategory":"Accounting & Tax Preparation",
            "type":"Services"
        }
    ],
    "sg:phone":"+31 35 656 6242",
    "sg:postcode":"1244 RH",
    "sg:province":"Noord-Holland",
    "sg:tags":[
        "accountant",
        "en",
        "-kantoren",
        "register-"
    ],
    "sg:website":"http://www.m-l.nl",
    "wof:name":"Ml Bv",
    "wof:placetype":"venue"
},
  "geometry": {"coordinates":[5.119665,52.258595],"type":"Point"}
}