{
  "type": "Feature",
  "properties": {
    "iso:country":"NL",
    "sg:address":"Van Walbekestraat 3",
    "sg:city":"Heeten",
    "sg:orig_category":"Loodgieterswerk, Verwarming And Sanitaire Installaties",
    "sg:phone":"+31 572 382 566",
    "sg:postcode":"8111 BG",
    "sg:province":"Burgas",
    "wof:name":"Anwe Polyform Heeten Vof",
    "wof:placetype":"venue"
},
  "geometry": {"coordinates":[27.294701,42.503601],"type":"Point"}
}