{
  "type": "Feature",
  "properties": {
    "iso:country":"NL",
    "sg:address":"Platinastraat 20",
    "sg:city":"Zoetermeer",
    "sg:orig_category":"Metaalbekleding And -Behandeling",
    "sg:phone":"+31 79 361 4929",
    "sg:postcode":"2718 RZ",
    "sg:province":"Zuid-Holland",
    "wof:name":"Combifit International Bv",
    "wof:placetype":"venue"
},
  "geometry": {"coordinates":[4.505604,52.038261],"type":"Point"}
}