{
  "type": "Feature",
  "properties": {
    "addr:full":"Doelweyk 9 Nieuw Beyerland South Holland 3264 AC",
    "addr:housenumber":"9",
    "addr:postcode":"3264 ac",
    "addr:street":"Doelweyk;Nieuw Beyerland",
    "iso:country":"NL",
    "sg:address":"Doelweyk 9",
    "sg:city":"Nieuw Beyerland",
    "sg:orig_category":"Kappers",
    "sg:phone":"+31 186 692 515",
    "sg:postcode":"3264 AC",
    "sg:province":"South Holland",
    "wof:name":"Brigitte",
    "wof:placetype":"venue"
},
  "geometry": {"coordinates":[4.3376779556,51.8139076233],"type":"Point"}
}