{
  "type": "Feature",
  "properties": {
    "addr:full":"Peuleyen 208 Waddinxveen Zuid-Holland 2742 ES",
    "addr:housenumber":"208",
    "addr:postcode":"2742 es",
    "addr:street":"Peuleyen",
    "iso:country":"NL",
    "sg:address":"Peuleyen 208",
    "sg:city":"Waddinxveen",
    "sg:orig_category":"Autorijscholen",
    "sg:phone":"+31 6 22374132",
    "sg:postcode":"2742 ES",
    "sg:province":"Zuid-Holland",
    "wof:name":"Mimpen, M J M",
    "wof:placetype":"venue"
},
  "geometry": {"coordinates":[4.64341,52.053558],"type":"Point"}
}