{
  "type": "Feature",
  "properties": {
    "addr:full":"Vd Lynstr 9 Alkmaar Noord-Holland 1817 EH",
    "addr:housenumber":"9",
    "addr:postcode":"1817 eh",
    "iso:country":"NL",
    "sg:address":"Vd Lynstr 9",
    "sg:city":"Alkmaar",
    "sg:orig_category":"Hulpverlening Sociaal",
    "sg:phone":"+31 72 514 3939",
    "sg:postcode":"1817 EH",
    "sg:province":"Noord-Holland",
    "wof:name":"Kardeel Centraal Bureau",
    "wof:placetype":"venue"
},
  "geometry": {"coordinates":[4.746258,52.634361],"type":"Point"}
}