{
  "type": "Feature",
  "properties": {
    "addr:full":"Hordijk 242 Rotterdam South Holland 3079 DL",
    "addr:housenumber":"242",
    "addr:postcode":"3079 dl",
    "addr:street":"Hordijk",
    "iso:country":"NL",
    "sg:address":"Hordijk 242",
    "sg:city":"Rotterdam",
    "sg:orig_category":"Benzinestations And Brandstoffen",
    "sg:phone":"+31 10 483 6873",
    "sg:postcode":"3079 DL",
    "sg:province":"South Holland",
    "wof:name":"Benzinestation L C Zwaal",
    "wof:placetype":"venue"
},
  "geometry": {"coordinates":[4.543027,51.873924],"type":"Point"}
}