{
  "type": "Feature",
  "properties": {
    "addr:full":"Zwijndrechtsestraat 40 Rotterdam South Holland 3073 RN",
    "addr:housenumber":"40",
    "addr:postcode":"3073 rn",
    "addr:street":"Zwijndrechtsestraat",
    "iso:country":"NL",
    "sg:address":"Zwijndrechtsestraat 40",
    "sg:city":"Rotterdam",
    "sg:orig_category":"Artiestenbureaus",
    "sg:phone":"+31 10 423 2729",
    "sg:postcode":"3073 RN",
    "sg:province":"South Holland",
    "wof:name":"Destiny",
    "wof:placetype":"venue"
},
  "geometry": {"coordinates":[4.505147,51.893345],"type":"Point"}
}