{
  "type": "Feature",
  "properties": {
    "addr:full":"Ossendk 43 Langeveen Overijssel 7679 VD",
    "addr:housenumber":"43",
    "addr:postcode":"7679 vd",
    "addr:street":"Ossendk",
    "iso:country":"NL",
    "sg:address":"Ossendk 43",
    "sg:city":"Langeveen",
    "sg:orig_category":"Lasbedrijven",
    "sg:phone":"+31 546 681 585",
    "sg:postcode":"7679 VD",
    "sg:province":"Overijssel",
    "wof:name":"Krola",
    "wof:placetype":"venue"
},
  "geometry": {"coordinates":[6.717308,52.453083],"type":"Point"}
}