{
  "type": "Feature",
  "properties": {
    "addr:full":"Driehuizerkerkweg 87 Driehuis Nh Noord-Holland 1985 HA",
    "addr:housenumber":"87",
    "addr:postcode":"1985 ha",
    "addr:street":"Driehuizerkerkweg",
    "iso:country":"NL",
    "sg:address":"Driehuizerkerkweg 87",
    "sg:city":"Driehuis Nh",
    "sg:orig_category":"Huishoudapparatuur, Televisies And Radio'S",
    "sg:phone":"+31 255 515 736",
    "sg:postcode":"1985 HA",
    "sg:province":"Noord-Holland",
    "wof:name":"Firma Krijnen & Zoon",
    "wof:placetype":"venue"
},
  "geometry": {"coordinates":[4.636547,52.447563],"type":"Point"}
}