{
  "type": "Feature",
  "properties": {
    "addr:full":"Wilhelminastraat 56 Amsterdam Noord-Holland 1054 WK",
    "addr:housenumber":"56",
    "addr:postcode":"1054 wk",
    "addr:street":"Wilhelminastraat",
    "iso:country":"NL",
    "sg:address":"Wilhelminastraat 56",
    "sg:city":"Amsterdam",
    "sg:orig_category":"Bedrijfs- And Managementsconsultants",
    "sg:phone":"+31 20 612 3409",
    "sg:postcode":"1054 WK",
    "sg:province":"Noord-Holland",
    "wof:name":"Tielen Gellings",
    "wof:placetype":"venue"
},
  "geometry": {"coordinates":[4.865176,52.362202],"type":"Point"}
}