{
  "type": "Feature",
  "properties": {
    "addr:full":"Hoogstraat 23 Montfort Limburg 6065 BA",
    "addr:housenumber":"23",
    "addr:postcode":"6065 ba",
    "addr:street":"Hoogstraat",
    "iso:country":"NL",
    "sg:address":"Hoogstraat 23",
    "sg:city":"Montfort",
    "sg:orig_category":"Banken And Kredietinstellingen",
    "sg:phone":"+31 475 541 410",
    "sg:postcode":"6065 BA",
    "sg:province":"Limburg",
    "wof:name":"Postkantoor",
    "wof:placetype":"venue"
},
  "geometry": {"coordinates":[5.951622,51.124596],"type":"Point"}
}