{
  "type": "Feature",
  "properties": {
    "addr:full":"Hg Zandschel 7 Kaatsheuvel North Brabant 5171 TH",
    "addr:housenumber":"7",
    "addr:postcode":"5171 th",
    "addr:street":"Zandschel",
    "iso:country":"NL",
    "sg:address":"Hg Zandschel 7",
    "sg:city":"Kaatsheuvel",
    "sg:orig_category":"Onderhoudswerken",
    "sg:phone":"+31 416 276 192",
    "sg:postcode":"5171 TH",
    "sg:province":"North Brabant",
    "wof:name":"Rooij, A W De",
    "wof:placetype":"venue"
},
  "geometry": {"coordinates":[5.00729,51.661198],"type":"Point"}
}