{
  "type": "Feature",
  "properties": {
    "addr:full":"Esweg 4 Erm Drenthe 7843 PA",
    "addr:housenumber":"4",
    "addr:postcode":"7843 pa",
    "addr:street":"Esweg",
    "iso:country":"NL",
    "sg:address":"Esweg 4",
    "sg:city":"Erm",
    "sg:orig_category":"Architecten",
    "sg:phone":"+31 591 361 885",
    "sg:postcode":"7843 PA",
    "sg:province":"Drenthe",
    "wof:name":"Ingenieurs- En Architectengroep Advikon",
    "wof:placetype":"venue"
},
  "geometry": {"coordinates":[-74.90799,38.980587],"type":"Point"}
}