{
  "type": "Feature",
  "properties": {
    "addr:full":"Bredasewg 152 Oosterhout Nb Noord-Brabant 4904 SC",
    "addr:housenumber":"152",
    "addr:postcode":"4904 sc",
    "iso:country":"NL",
    "sg:address":"Bredasewg 152",
    "sg:city":"Oosterhout Nb",
    "sg:classifiers":[
        {
            "category":"Sports & Exercise",
            "subcategory":"Stables",
            "type":"Entertainment"
        }
    ],
    "sg:phone":"+31 162 454 835",
    "sg:postcode":"4904 SC",
    "sg:province":"Noord-Brabant",
    "sg:tags":[
        "maneges"
    ],
    "wof:name":"Oosterhoutse Hoeve, De",
    "wof:placetype":"venue"
},
  "geometry": {"coordinates":[4.836144,51.626163],"type":"Point"}
}