{
  "type": "Feature",
  "properties": {
    "addr:full":"Javastraat 33 Nijmegen Gelderland 6524 LT",
    "addr:housenumber":"33",
    "addr:postcode":"6524 lt",
    "addr:street":"Javastraat;Gelderland",
    "iso:country":"NL",
    "sg:address":"Javastraat 33",
    "sg:city":"Nijmegen",
    "sg:orig_category":"Krantenuitgeverijen",
    "sg:phone":"+31 24 322 9030",
    "sg:postcode":"6524 LT",
    "sg:province":"Gelderland",
    "wof:name":"Uitgeverij Bandijk Boeken",
    "wof:placetype":"venue"
},
  "geometry": {"coordinates":[5.862391,51.83659],"type":"Point"}
}