{
  "type": "Feature",
  "properties": {
    "addr:full":"Mommerstg 5 Haarsteeg Noord-Brabant 5254 VK",
    "addr:housenumber":"5",
    "addr:postcode":"5254 vk",
    "addr:street":"Mommerstg",
    "iso:country":"NL",
    "sg:address":"Mommerstg 5",
    "sg:city":"Haarsteeg",
    "sg:orig_category":"Bloemen En Planten - Verhuur",
    "sg:phone":"+31 73 511 7182",
    "sg:postcode":"5254 VK",
    "sg:province":"Noord-Brabant",
    "wof:name":"Art-Nivo",
    "wof:placetype":"venue"
},
  "geometry": {"coordinates":[5.205765,51.706615],"type":"Point"}
}