{
  "type": "Feature",
  "properties": {
    "iso:country":"NL",
    "sg:address":"Mommerstg 5",
    "sg:city":"Haarsteeg",
    "sg:orig_category":"Bloemen En Planten - Verhuur",
    "sg:phone":"+31 73 511 7182",
    "sg:postcode":"5254 VK",
    "sg:province":"Noord-Brabant",
    "wof:name":"Art-Nivo",
    "wof:placetype":"venue"
},
  "geometry": {"coordinates":[5.205765,51.706615],"type":"Point"}
}