{
  "type": "Feature",
  "properties": {
    "iso:country":"NL",
    "sg:address":"V Leeuwenstr 31",
    "sg:city":"Boxtel",
    "sg:orig_category":"Kantoor- En Interieurbeplanting",
    "sg:phone":"+31 6 51596418",
    "sg:postcode":"5281 GM",
    "sg:province":"North Brabant",
    "wof:name":"Blauwe Lelie, De",
    "wof:placetype":"venue"
},
  "geometry": {"coordinates":[5.3227748871,51.591594696],"type":"Point"}
}