{
  "type": "Feature",
  "properties": {
    "iso:country":"NL",
    "sg:address":"Ellendk 3A",
    "sg:city":"Heikant",
    "sg:orig_category":"Grafisch Ontwerpers",
    "sg:phone":"+31 114 315 352",
    "sg:postcode":"4566 BE",
    "sg:province":"Zeeland",
    "wof:name":"Megabite",
    "wof:placetype":"venue"
},
  "geometry": {"coordinates":[4.035743,51.25087],"type":"Point"}
}