{
  "type": "Feature",
  "properties": {
    "iso:country":"NL",
    "sg:address":"Broekhovensewg 245",
    "sg:city":"Tilburg",
    "sg:orig_category":"Cafetaria'S",
    "sg:phone":"+31 13 543 7307",
    "sg:postcode":"5022 CC",
    "sg:province":"North Brabant",
    "wof:name":"Marian",
    "wof:placetype":"venue"
},
  "geometry": {"coordinates":[5.09468,51.543331],"type":"Point"}
}