{
  "type": "Feature",
  "properties": {
    "addr:full":"Nieuwendammerdk 250B Amsterdam Noord-Holland 1025 LW",
    "addr:housenumber":"250b",
    "addr:postcode":"1025 lw",
    "iso:country":"NL",
    "sg:address":"Nieuwendammerdk 250B",
    "sg:city":"Amsterdam",
    "sg:orig_category":"Grafisch Ontwerpers",
    "sg:phone":"+31 20 632 0257",
    "sg:postcode":"1025 LW",
    "sg:province":"Noord-Holland",
    "wof:name":"Sloot, R",
    "wof:placetype":"venue"
},
  "geometry": {"coordinates":[4.9331,52.391609],"type":"Point"}
}