{
  "type": "Feature",
  "properties": {
    "addr:full":"Symfoniestr 204 Nymegen Tennessee 6544 TN",
    "addr:housenumber":"204",
    "addr:postcode":"6544",
    "addr:street":"Nymegen Tennessee",
    "iso:country":"NL",
    "sg:address":"Symfoniestr 204",
    "sg:city":"Nymegen",
    "sg:orig_category":"Verenigingsgebouwen",
    "sg:phone":"+31 24 377 2460",
    "sg:postcode":"6544 TN",
    "sg:province":"Tennessee",
    "wof:name":"Schalmei, De",
    "wof:placetype":"venue"
},
  "geometry": {"coordinates":[-85.978554,35.83062],"type":"Point"}
}