{
  "type": "Feature",
  "properties": {
    "addr:full":"Eindje De Rondte 3 Kruiningen Zeeland 4416 CP",
    "addr:housenumber":"3",
    "addr:postcode":"4416 cp",
    "addr:street":"Eindje De Rondte",
    "iso:country":"NL",
    "sg:address":"Eindje De Rondte 3",
    "sg:city":"Kruiningen",
    "sg:classifiers":[
        {
            "category":"Professional",
            "subcategory":"Accounting & Tax Preparation",
            "type":"Services"
        }
    ],
    "sg:phone":"+31 113 383 112",
    "sg:postcode":"4416 CP",
    "sg:province":"Zeeland",
    "sg:tags":[
        "accountant"
    ],
    "wof:name":"Van De Velde Accountancy Bv",
    "wof:placetype":"venue"
},
  "geometry": {"coordinates":[4.0332,51.447292],"type":"Point"}
}