{
  "type": "Feature",
  "properties": {
    "addr:full":"Kerkstr 6 Zevenaar Gelderland 6901 AB",
    "addr:housenumber":"6",
    "addr:postcode":"6901 ab",
    "addr:street":"Kerkstr",
    "iso:country":"NL",
    "sg:address":"Kerkstr 6",
    "sg:city":"Zevenaar",
    "sg:orig_category":"Orthopedisch Schoeisel",
    "sg:phone":"+31 316 523 374",
    "sg:postcode":"6901 AB",
    "sg:province":"Gelderland",
    "wof:name":"Hoevers, W",
    "wof:placetype":"venue"
},
  "geometry": {"coordinates":[6.0768780708,51.9316177368],"type":"Point"}
}