{
  "type": "Feature",
  "properties": {
    "addr:full":"Hommelsewg 213 Arnhem Gelderland 6821 LG",
    "addr:housenumber":"213",
    "addr:postcode":"6821 lg",
    "iso:country":"NL",
    "sg:address":"Hommelsewg 213",
    "sg:city":"Arnhem",
    "sg:orig_category":"Fotoreportages",
    "sg:phone":"+31 26 442 6600",
    "sg:postcode":"6821 LG",
    "sg:province":"Gelderland",
    "wof:name":"Rutgers, Kees",
    "wof:placetype":"venue"
},
  "geometry": {"coordinates":[5.916128,51.990028],"type":"Point"}
}