{
  "type": "Feature",
  "properties": {
    "addr:full":"Wouwbaan 79 Hoogerheide Noord-Brabant 4631 KL",
    "addr:housenumber":"79",
    "addr:postcode":"4631 kl",
    "addr:street":"Wouwbaan",
    "iso:country":"NL",
    "sg:address":"Wouwbaan 79",
    "sg:city":"Hoogerheide",
    "sg:orig_category":"Motoren - Onderdelen",
    "sg:phone":"+31 164 612 146",
    "sg:postcode":"4631 KL",
    "sg:province":"Noord-Brabant",
    "sg:website":"http://www.racing-bikes.nl",
    "wof:name":"Racing Bikes",
    "wof:placetype":"venue"
},
  "geometry": {"coordinates":[4.327826,51.428089],"type":"Point"}
}