{
  "type": "Feature",
  "properties": {
    "iso:country":"NL",
    "sg:address":"Tongerloseweg 12",
    "sg:city":"Diessen",
    "sg:orig_category":"Technische Studies And Onderzoek",
    "sg:phone":"+31 13 504 2013",
    "sg:postcode":"5087 KX",
    "sg:province":"Noord-Brabant",
    "wof:name":"Van Dal Trading",
    "wof:placetype":"venue"
},
  "geometry": {"coordinates":[5.17989,51.462727],"type":"Point"}
}