{
  "type": "Feature",
  "properties": {
    "addr:full":"Houtstr 25 Klimmen Limburg 6343 BJ",
    "addr:housenumber":"25",
    "addr:postcode":"6343 bj",
    "addr:street":"Houtstr",
    "iso:country":"NL",
    "sg:address":"Houtstr 25",
    "sg:city":"Klimmen",
    "sg:orig_category":"Verenigingsgebouwen",
    "sg:phone":"+31 45 405 2628",
    "sg:postcode":"6343 BJ",
    "sg:province":"Limburg",
    "wof:name":"Op D'R Plats, Gemeenschapshuis",
    "wof:placetype":"venue"
},
  "geometry": {"coordinates":[5.882016,50.875877],"type":"Point"}
}