{
  "type": "Feature",
  "properties": {
    "addr:full":"Spaarnwouderweg 1175 Vijfhuizen Noord-Holland 2141 BN",
    "addr:housenumber":"1175",
    "addr:postcode":"vijfhuizen;2141 bn",
    "addr:street":"Spaarnwouderweg",
    "iso:country":"NL",
    "sg:address":"Spaarnwouderweg 1175",
    "sg:city":"Vijfhuizen",
    "sg:orig_category":"Metaalafval, Schrootrecycling And Sloperijen",
    "sg:phone":"+31 23 536 5202",
    "sg:postcode":"2141 BN",
    "sg:province":"Noord-Holland",
    "wof:name":"Autosloperij Alladin",
    "wof:placetype":"venue"
},
  "geometry": {"coordinates":[4.697459,52.375584],"type":"Point"}
}