{
  "type": "Feature",
  "properties": {
    "addr:full":"Utrechtsestraat 10 Arnhem Gelderland 6811 LX",
    "addr:housenumber":"10",
    "addr:postcode":"6811 lx",
    "addr:street":"Utrechtsestraat",
    "iso:country":"NL",
    "sg:address":"Utrechtsestraat 10",
    "sg:city":"Arnhem",
    "sg:orig_category":"Beroepsorganisaties",
    "sg:phone":"+31 26 443 3438",
    "sg:postcode":"6811 LX",
    "sg:province":"Gelderland",
    "wof:name":"Vereniging Hoger Personeel Akzo",
    "wof:placetype":"venue"
},
  "geometry": {"coordinates":[5.899773,51.98344],"type":"Point"}
}