{
  "type": "Feature",
  "properties": {
    "addr:full":"Ijsselstraat 11 Oss Virginia 5347 KG",
    "addr:housenumber":"11",
    "addr:postcode":"5347 kg",
    "addr:street":"Ijsselstraat",
    "iso:country":"NL",
    "sg:address":"Ijsselstraat 11",
    "sg:city":"Oss",
    "sg:orig_category":"Werving And Selectie Van Tijdelijk Personeel And Uitzendkantoren",
    "sg:phone":"+31 412 450 441",
    "sg:postcode":"5347 KG",
    "sg:province":"Virginia",
    "wof:name":"Simplicity Bv",
    "wof:placetype":"venue"
},
  "geometry": {"coordinates":[-77.2352142334,38.3125991821],"type":"Point"}
}