{
  "type": "Feature",
  "properties": {
    "addr:full":"Hulsterweg 75 Kloosterzande Zeeland 4587 LG",
    "addr:housenumber":"75",
    "addr:postcode":"4587 lg",
    "addr:street":"Hulsterweg",
    "iso:country":"NL",
    "sg:address":"Hulsterweg 75",
    "sg:city":"Kloosterzande",
    "sg:orig_category":"Metaalbekleding And -Behandeling",
    "sg:phone":"+31 114 683 030",
    "sg:postcode":"4587 LG",
    "sg:province":"Zeeland",
    "wof:name":"Bormstaal Holding Bv",
    "wof:placetype":"venue"
},
  "geometry": {"coordinates":[4.023665,51.360165],"type":"Point"}
}