{
  "type": "Feature",
  "properties": {
    "addr:full":"Sluisstraat 63 Someren Noord-Brabant 5712 BE",
    "addr:housenumber":"63",
    "addr:postcode":"5712",
    "addr:street":"Sluisstraat",
    "iso:country":"NL",
    "sg:address":"Sluisstraat 63",
    "sg:city":"Someren",
    "sg:orig_category":"Metaalwerken",
    "sg:phone":"+31 493 492 395",
    "sg:postcode":"5712 BE",
    "sg:province":"Noord-Brabant",
    "wof:name":"Firma C. Geraerts",
    "wof:placetype":"venue"
},
  "geometry": {"coordinates":[5.739636,51.353497],"type":"Point"}
}