{
  "type": "Feature",
  "properties": {
    "addr:full":"Koningstr 15 Sassenheim South Holland 2171 DD",
    "addr:housenumber":"15",
    "addr:postcode":"2171 dd",
    "addr:street":"Koningstr",
    "iso:country":"NL",
    "sg:address":"Koningstr 15",
    "sg:city":"Sassenheim",
    "sg:orig_category":"Accountants - Administratie- Consulenten En -Kantoren",
    "sg:phone":"+31 252 217 199",
    "sg:postcode":"2171 DD",
    "sg:province":"South Holland",
    "wof:name":"Tewarie En Partners",
    "wof:placetype":"venue"
},
  "geometry": {"coordinates":[4.51467,52.221073],"type":"Point"}
}