{
  "type": "Feature",
  "properties": {
    "addr:full":"Middelwg 13A Numansdorp Zuid-Holland 3281 KH",
    "addr:housenumber":"13a",
    "addr:postcode":"3281 kh",
    "addr:street":"Middelwg",
    "iso:country":"NL",
    "sg:address":"Middelwg 13A",
    "sg:city":"Numansdorp",
    "sg:orig_category":"Havenbedrijven",
    "sg:phone":"+31 186 654 325",
    "sg:postcode":"3281 KH",
    "sg:province":"Zuid-Holland",
    "wof:name":"Adv Schaft Bv",
    "wof:placetype":"venue"
},
  "geometry": {"coordinates":[4.441282,51.73468],"type":"Point"}
}