{
  "type": "Feature",
  "properties": {
    "iso:country":"NL",
    "sg:address":"Postbus 132",
    "sg:city":"Delfzyl",
    "sg:orig_category":"Scholen Voor Basisonderwijs",
    "sg:phone":"+31 596 680 501",
    "sg:postcode":"9930 AC",
    "sg:province":"Groningen",
    "wof:name":"Vore Cbs, De",
    "wof:placetype":"venue"
},
  "geometry": {"coordinates":[6.92738,53.331291],"type":"Point"}
}