{
  "type": "Feature",
  "properties": {
    "addr:full":"Kabelrijs 27 Sint Pancras Noord-Holland 1834 EV",
    "addr:housenumber":"27",
    "addr:street":"Kabelrijs",
    "iso:country":"NL",
    "sg:address":"Kabelrijs 27",
    "sg:city":"Sint Pancras",
    "sg:orig_category":"Verzekeringen",
    "sg:phone":"+31 72 564 2906",
    "sg:postcode":"1834 EV",
    "sg:province":"Noord-Holland",
    "wof:name":"Assurantiekantoor J.J. De Wit",
    "wof:placetype":"venue"
},
  "geometry": {"coordinates":[4.789441,52.664772],"type":"Point"}
}