{
  "type": "Feature",
  "properties": {
    "iso:country":"NL",
    "sg:address":"Postbus 34",
    "sg:city":"Rheden",
    "sg:orig_category":"Jachthavens - Jachtwerven",
    "sg:phone":"+31 26 495 3293",
    "sg:postcode":"6990 AA",
    "sg:province":"Gelderland",
    "wof:name":"Engel Wsv, De",
    "wof:placetype":"venue"
},
  "geometry": {"coordinates":[6.03264,52.002544],"type":"Point"}
}