{
  "type": "Feature",
  "properties": {
    "addr:full":"Verlengde Stationsstraat 83 Zwaagwesteinde Provincie Friesland 9271 CC",
    "addr:housenumber":"83",
    "addr:postcode":"9271 cc",
    "addr:street":"Verlengde Stationsstraat;Provincie Friesland",
    "iso:country":"NL",
    "sg:address":"Verlengde Stationsstraat 83",
    "sg:city":"Zwaagwesteinde",
    "sg:orig_category":"Kappers",
    "sg:phone":"+31 511 444 200",
    "sg:postcode":"9271 CC",
    "sg:province":"Provincie Friesland",
    "wof:name":"Kapsalon Fantastique",
    "wof:placetype":"venue"
},
  "geometry": {"coordinates":[6.0410509109,53.2614936829],"type":"Point"}
}