{
  "type": "Feature",
  "properties": {
    "iso:country":"NL",
    "sg:address":"Kalverstraat 64",
    "sg:city":"Amsterdam",
    "sg:orig_category":"Herenmodezaken",
    "sg:phone":"+31 20 626 6353",
    "sg:postcode":"1012 PG",
    "sg:province":"North Holland",
    "wof:name":"Yank'S Clothing Company",
    "wof:placetype":"venue"
},
  "geometry": {"coordinates":[4.891619,52.370972],"type":"Point"}
}