{
  "type": "Feature",
  "properties": {
    "addr:full":"Kalverstraat 64 Amsterdam North Holland 1012 PG",
    "addr:housenumber":"64",
    "addr:postcode":"1012 pg",
    "addr:street":"Kalverstraat",
    "iso:country":"NL",
    "sg:address":"Kalverstraat 64",
    "sg:city":"Amsterdam",
    "sg:orig_category":"Herenmodezaken",
    "sg:phone":"+31 20 626 6353",
    "sg:postcode":"1012 PG",
    "sg:province":"North Holland",
    "wof:name":"Yank'S Clothing Company",
    "wof:placetype":"venue"
},
  "geometry": {"coordinates":[4.891619,52.370972],"type":"Point"}
}