{
  "type": "Feature",
  "properties": {
    "iso:country":"NL",
    "sg:address":"Donkersln 2A",
    "sg:city":"Harkstede",
    "sg:orig_category":"Webdesign Bureaus",
    "sg:phone":"+31 50 404 2796",
    "sg:postcode":"9617 AN",
    "sg:province":"Groningen",
    "wof:name":"Vestigo",
    "wof:placetype":"venue"
},
  "geometry": {"coordinates":[6.6938900948,53.2125663757],"type":"Point"}
}