{
  "type": "Feature",
  "properties": {
    "addr:full":"Waaier 15 Leimuiden Zuid-Holland 2451 VV",
    "addr:housenumber":"15",
    "addr:postcode":"2451 vv",
    "addr:street":"Waaier",
    "iso:country":"NL",
    "sg:address":"Waaier 15",
    "sg:city":"Leimuiden",
    "sg:orig_category":"Kantoorbenodigdheden",
    "sg:phone":"+31 172 602 261",
    "sg:postcode":"2451 VV",
    "sg:province":"Zuid-Holland",
    "sg:website":"http://www.hijdra.com",
    "wof:name":"All Office Hijdra",
    "wof:placetype":"venue"
},
  "geometry": {"coordinates":[4.6822590828,52.2234573364],"type":"Point"}
}