{
  "type": "Feature",
  "properties": {
    "iso:country":"NL",
    "sg:address":"Motorkade 7F",
    "sg:city":"Amsterdam",
    "sg:orig_category":"Goederenvervoer Over De Weg",
    "sg:phone":"+31 20 637 2273",
    "sg:postcode":"1021 JR",
    "sg:province":"Noord-Holland",
    "wof:name":"Olympuk Amsterdam",
    "wof:placetype":"venue"
},
  "geometry": {"coordinates":[4.919393,52.384743],"type":"Point"}
}