{
  "type": "Feature",
  "properties": {
    "addr:full":"Lubitschstr 22 Almere Flevoland 1325 RW",
    "addr:housenumber":"22;1325",
    "addr:street":"Lubitschstr;Flevoland;Rw",
    "iso:country":"NL",
    "sg:address":"Lubitschstr 22",
    "sg:city":"Almere",
    "sg:orig_category":"Vertalers",
    "sg:phone":"+31 36 535 3048",
    "sg:postcode":"1325 RW",
    "sg:province":"Flevoland",
    "sg:website":"http://www.hippolingo.myweb.nl",
    "wof:name":"Hippolingo",
    "wof:placetype":"venue"
},
  "geometry": {"coordinates":[5.248109,52.359898],"type":"Point"}
}