{
  "type": "Feature",
  "properties": {
    "iso:country":"NL",
    "sg:address":"Haagsebosweg 49",
    "sg:city":"Enschede",
    "sg:orig_category":"Levende Dieren Gh",
    "sg:phone":"+31 53 538 1363",
    "sg:postcode":"7525 PP",
    "sg:province":"NL.08",
    "wof:name":"H.A. Bloemen",
    "wof:placetype":"venue"
},
  "geometry": {"coordinates":[6.95619,52.259659],"type":"Point"}
}