{
  "type": "Feature",
  "properties": {
    "addr:full":"Van Welderenstraat 114 Nijmegen Gelderland 6511 MT",
    "addr:housenumber":"114",
    "addr:postcode":"6511",
    "addr:street":"Van Welderenstraat;Gelderland;Mt",
    "iso:country":"NL",
    "sg:address":"Van Welderenstraat 114",
    "sg:city":"Nijmegen",
    "sg:classifiers":[
        {
            "category":"Retail",
            "subcategory":"Storage",
            "type":"Services"
        }
    ],
    "sg:phone":"+31 24 322 7654",
    "sg:postcode":"6511 MT",
    "sg:province":"Gelderland",
    "sg:tags":[
        "opslag",
        "bewaring"
    ],
    "wof:name":"Combo Nijmegen Bv",
    "wof:placetype":"venue"
},
  "geometry": {"coordinates":[5.8621959686,51.8429031372],"type":"Point"}
}