{
  "type": "Feature",
  "properties": {
    "iso:country":"NL",
    "sg:address":"Grote Marktstraat 58",
    "sg:city":"'S Gravenhage",
    "sg:orig_category":"Drogisterijen",
    "sg:phone":"+31 70 392 4647",
    "sg:postcode":"2511 BJ",
    "sg:province":"Zuid-Holland",
    "wof:name":"Le Drugstore Spuihof",
    "wof:placetype":"venue"
},
  "geometry": {"coordinates":[4.31393,52.077366],"type":"Point"}
}