{
  "type": "Feature",
  "properties": {
    "addr:full":"Sperwerstr 97 Arnhem Gelderland 6823 DL",
    "addr:housenumber":"97",
    "addr:postcode":"6823 dl",
    "addr:street":"Sperwerstr",
    "iso:country":"NL",
    "sg:address":"Sperwerstr 97",
    "sg:city":"Arnhem",
    "sg:orig_category":"Scholen Voor Basisonderwijs",
    "sg:phone":"+31 26 443 2857",
    "sg:postcode":"6823 DL",
    "sg:province":"Gelderland",
    "wof:name":"Vlindertuin, De",
    "wof:placetype":"venue"
},
  "geometry": {"coordinates":[5.936202,52.003963],"type":"Point"}
}