{
  "type": "Feature",
  "properties": {
    "addr:full":"Schilperoortstr 70B Rotterdam South Holland 3082 SX",
    "addr:housenumber":"70b",
    "addr:postcode":"3082 sx",
    "addr:street":"Schilperoortstr",
    "iso:country":"NL",
    "sg:address":"Schilperoortstr 70B",
    "sg:city":"Rotterdam",
    "sg:orig_category":"Webdesign Bureaus",
    "sg:phone":"+31 10 495 4705",
    "sg:postcode":"3082 SX",
    "sg:province":"South Holland",
    "sg:website":"http://www.unreal-rotterdam.nl",
    "wof:name":"Unreal",
    "wof:placetype":"venue"
},
  "geometry": {"coordinates":[4.4674711227,51.8907470703],"type":"Point"}
}