{
  "type": "Feature",
  "properties": {
    "addr:full":"Breestraat 175 Leiden Zuid-Holland 2311 CP",
    "addr:housenumber":"175",
    "addr:postcode":"2311 cp",
    "addr:street":"Breestraat",
    "iso:country":"NL",
    "sg:address":"Breestraat 175",
    "sg:city":"Leiden",
    "sg:classifiers":[
        {
            "category":"Shopping",
            "subcategory":"Gifts & Souvenirs",
            "type":"Retail Goods"
        }
    ],
    "sg:phone":"+31 71 512 5466",
    "sg:postcode":"2311 CP",
    "sg:province":"Zuid-Holland",
    "sg:tags":[
        "geschenken"
    ],
    "wof:name":"Niets Vergeten Kadowinkel",
    "wof:placetype":"venue"
},
  "geometry": {"coordinates":[4.492706,52.156353],"type":"Point"}
}