{
  "type": "Feature",
  "properties": {
    "addr:full":"Groene Tuin 147 Rotterdam Zuid-Holland 3078 KD",
    "addr:housenumber":"147",
    "addr:postcode":"3078 kd",
    "addr:street":"Groene Tuin",
    "iso:country":"NL",
    "sg:address":"Groene Tuin 147",
    "sg:city":"Rotterdam",
    "sg:orig_category":"Verloskundigen",
    "sg:phone":"+31 10 482 7806",
    "sg:postcode":"3078 KD",
    "sg:province":"Zuid-Holland",
    "wof:name":"Rinnert & Schenk",
    "wof:placetype":"venue"
},
  "geometry": {"coordinates":[4.550079,51.890957],"type":"Point"}
}