{
  "type": "Feature",
  "properties": {
    "addr:full":"Rustenburgerstraat 380 Amsterdam North Holland 1072 HG",
    "addr:housenumber":"380",
    "addr:postcode":"1072 hg",
    "addr:street":"Rustenburgerstraat",
    "iso:country":"NL",
    "sg:address":"Rustenburgerstraat 380",
    "sg:city":"Amsterdam",
    "sg:orig_category":"Kappers",
    "sg:phone":"+31 20 679 3224",
    "sg:postcode":"1072 HG",
    "sg:province":"North Holland",
    "wof:name":"Kapsalon Hair Care",
    "wof:placetype":"venue"
},
  "geometry": {"coordinates":[4.891933918,52.3516426086],"type":"Point"}
}