{
  "type": "Feature",
  "properties": {
    "addr:full":"Eerste Van Der Helststr 27 Amsterdam North Holland 1073 AC",
    "addr:housenumber":"27",
    "addr:postcode":"1073 ac",
    "addr:street":"Eerste Van Der Helststr",
    "iso:country":"NL",
    "sg:address":"Eerste Van Der Helststr 27",
    "sg:city":"Amsterdam",
    "sg:orig_category":"Wasserettes And Stomerijen",
    "sg:phone":"+31 20 671 1033",
    "sg:postcode":"1073 AC",
    "sg:province":"North Holland",
    "wof:name":"Was Snelservice A R S",
    "wof:placetype":"venue"
},
  "geometry": {"coordinates":[4.893032074,52.3558807373],"type":"Point"}
}