{
  "type": "Feature",
  "properties": {
    "addr:full":"Amstelveenseweg 77 Amsterdam Noord-Holland 1075 VW",
    "addr:housenumber":"77",
    "addr:postcode":"1075 vw",
    "addr:street":"Amstelveenseweg",
    "iso:country":"NL",
    "sg:address":"Amstelveenseweg 77",
    "sg:city":"Amsterdam",
    "sg:orig_category":"Boekhandels",
    "sg:phone":"+31 20 662 0809",
    "sg:postcode":"1075 VW",
    "sg:province":"Noord-Holland",
    "wof:name":"Bv Kantoorboekhandel V/H Gebroeders Wint",
    "wof:placetype":"venue"
},
  "geometry": {"coordinates":[4.85608,52.353382],"type":"Point"}
}