{
  "type": "Feature",
  "properties": {
    "addr:full":"Oudestreek 25 Zevenhuizen Gn Groningen 9354 AD",
    "addr:housenumber":"25;gn",
    "addr:postcode":"9354 ad",
    "addr:street":"Oudestreek",
    "iso:country":"NL",
    "sg:address":"Oudestreek 25",
    "sg:city":"Zevenhuizen Gn",
    "sg:orig_category":"Montagebedrijven",
    "sg:phone":"+31 594 632 254",
    "sg:postcode":"9354 AD",
    "sg:province":"Groningen",
    "wof:name":"Kombuis, De",
    "wof:placetype":"venue"
},
  "geometry": {"coordinates":[6.34386,53.118912],"type":"Point"}
}