{
  "type": "Feature",
  "properties": {
    "addr:full":"Azaleastr 21 Terneuzen Zeeland 4537 RA",
    "addr:housenumber":"21",
    "addr:postcode":"4537 ra",
    "addr:street":"Azaleastr",
    "iso:country":"NL",
    "sg:address":"Azaleastr 21",
    "sg:city":"Terneuzen",
    "sg:orig_category":"Scheepssleep- En Duwvaart",
    "sg:phone":"+31 6 53684117",
    "sg:postcode":"4537 RA",
    "sg:province":"Zeeland",
    "wof:name":"Arends Van Den Ouden Vof",
    "wof:placetype":"venue"
},
  "geometry": {"coordinates":[3.830859,51.329647],"type":"Point"}
}