{
  "type": "Feature",
  "properties": {
    "addr:full":"Kuyperln 50 Uithoorn North Holland 1421 VS",
    "addr:housenumber":"50",
    "addr:postcode":"1421 vs",
    "addr:street":"Kuyperln",
    "iso:country":"NL",
    "sg:address":"Kuyperln 50",
    "sg:city":"Uithoorn",
    "sg:orig_category":"Scholen Voor Basisonderwijs",
    "sg:phone":"+31 297 521 447",
    "sg:postcode":"1421 VS",
    "sg:province":"North Holland",
    "wof:name":"Regenboog, De",
    "wof:placetype":"venue"
},
  "geometry": {"coordinates":[4.828947,52.233421],"type":"Point"}
}