{
  "type": "Feature",
  "properties": {
    "addr:full":"Koningin Emmakade 91 'S Gravenhage Zuid-Holland 2518 RM",
    "addr:housenumber":"91",
    "addr:postcode":"2518 rm",
    "addr:street":"Koningin Emmakade;' S",
    "iso:country":"NL",
    "sg:address":"Koningin Emmakade 91",
    "sg:city":"'S Gravenhage",
    "sg:orig_category":"Huishoudapparatuur, Televisies And Radio'S",
    "sg:phone":"+31 70 363 6154",
    "sg:postcode":"2518 RM",
    "sg:province":"Zuid-Holland",
    "wof:name":"Techn Servicebur F L Van Esveld",
    "wof:placetype":"venue"
},
  "geometry": {"coordinates":[4.290305,52.079563],"type":"Point"}
}