{
  "type": "Feature",
  "properties": {
    "addr:full":"Stationsstraat 40 Maastricht Limburg 6221 BR",
    "addr:housenumber":"40",
    "addr:postcode":"6221 br",
    "addr:street":"Stationsstraat",
    "iso:country":"NL",
    "sg:address":"Stationsstraat 40",
    "sg:city":"Maastricht",
    "sg:orig_category":"Bloemen And Planten",
    "sg:phone":"+31 43 325 2625",
    "sg:postcode":"6221 BR",
    "sg:province":"Limburg",
    "wof:name":"De Rozengaard",
    "wof:placetype":"venue"
},
  "geometry": {"coordinates":[5.702679,50.849808],"type":"Point"}
}