{
  "type": "Feature",
  "properties": {
    "addr:full":"Watercipresstraat 1 Almere Flevoland 1326 CE",
    "addr:housenumber":"1",
    "addr:postcode":"1326 ce",
    "addr:street":"Watercipresstraat;Flevoland",
    "iso:country":"NL",
    "sg:address":"Watercipresstraat 1",
    "sg:city":"Almere",
    "sg:orig_category":"Paramedische Behandelingen",
    "sg:phone":"+31 36 535 7700",
    "sg:postcode":"1326 CE",
    "sg:province":"Flevoland",
    "wof:name":"Gezondheidscentrum Parkwijk",
    "wof:placetype":"venue"
},
  "geometry": {"coordinates":[5.24408,52.374523],"type":"Point"}
}