{
  "type": "Feature",
  "properties": {
    "addr:full":"J Glyniswg 50A Heerhugowaard North Holland 1702 PD",
    "addr:housenumber":"50a",
    "addr:postcode":"1702 pd",
    "iso:country":"NL",
    "sg:address":"J Glyniswg 50A",
    "sg:city":"Heerhugowaard",
    "sg:orig_category":"Land- En Tuinbouw - Loonbedrijven",
    "sg:phone":"+31 72 571 0344",
    "sg:postcode":"1702 PD",
    "sg:province":"North Holland",
    "wof:name":"Mol, A A",
    "wof:placetype":"venue"
},
  "geometry": {"coordinates":[4.855883,52.656414],"type":"Point"}
}