{
  "type": "Feature",
  "properties": {
    "addr:full":"Gerstdijk 15 Helmond Noord-Brabant 5704 RG",
    "addr:housenumber":"15",
    "addr:postcode":"5704 rg",
    "addr:street":"Gerstdijk",
    "iso:country":"NL",
    "sg:address":"Gerstdijk 15",
    "sg:city":"Helmond",
    "sg:orig_category":"Houtverwerking",
    "sg:phone":"+31 492 531 919",
    "sg:postcode":"5704 RG",
    "sg:province":"Noord-Brabant",
    "wof:name":"Houtindustrie Mevo Bv",
    "wof:placetype":"venue"
},
  "geometry": {"coordinates":[5.69585,51.444962],"type":"Point"}
}