{
  "type": "Feature",
  "properties": {
    "addr:full":"Rykswg 202 Ryen Noord-Brabant 5121 RC",
    "addr:housenumber":"202",
    "addr:postcode":"5121 rc",
    "iso:country":"NL",
    "sg:address":"Rykswg 202",
    "sg:city":"Ryen",
    "sg:classifiers":[
        {
            "category":"Travel",
            "subcategory":"Hotels & Motels",
            "type":"Entertainment"
        }
    ],
    "sg:phone":"+31 161 224 318",
    "sg:postcode":"5121 RC",
    "sg:province":"Noord-Brabant",
    "sg:website":"http://www.cigogne.nl",
    "wof:name":"Cigogne, La",
    "wof:placetype":"venue"
},
  "geometry": {"coordinates":[4.9197,51.588017],"type":"Point"}
}