{
  "type": "Feature",
  "properties": {
    "addr:full":"Burg Boreelstr 13 Haarlem North Holland 2013 BT",
    "addr:housenumber":"13",
    "addr:postcode":"2013 bt",
    "addr:street":"Burg",
    "iso:country":"NL",
    "sg:address":"Burg Boreelstr 13",
    "sg:city":"Haarlem",
    "sg:orig_category":"Journalisten Freelance",
    "sg:phone":"+31 23 531 8360",
    "sg:postcode":"2013 BT",
    "sg:province":"North Holland",
    "wof:name":"Koppeschaar, C E",
    "wof:placetype":"venue"
},
  "geometry": {"coordinates":[4.629472,52.384995],"type":"Point"}
}