{
  "type": "Feature",
  "properties": {
    "addr:full":"Oostkd 46 Huizen Noord-Holland 1274 ND",
    "addr:housenumber":"46",
    "addr:postcode":"1274 nd",
    "addr:street":"Oostkd",
    "iso:country":"NL",
    "sg:address":"Oostkd 46",
    "sg:city":"Huizen",
    "sg:orig_category":"Fietsen En Bromfietsen",
    "sg:phone":"+31 35 526 6601",
    "sg:postcode":"1274 ND",
    "sg:province":"Noord-Holland",
    "sg:website":"http://www.donshop.nl",
    "wof:name":"Don Shop",
    "wof:placetype":"venue"
},
  "geometry": {"coordinates":[5.23421,52.29504],"type":"Point"}
}