{
  "type": "Feature",
  "properties": {
    "addr:full":"Goejanverwelle 11 Hekendorp Utrecht 3467 PN",
    "addr:housenumber":"11",
    "addr:postcode":"3467 pn",
    "addr:street":"Goejanverwelle",
    "iso:country":"NL",
    "sg:address":"Goejanverwelle 11",
    "sg:city":"Hekendorp",
    "sg:orig_category":"Pleziervaartuigen And Reparatie",
    "sg:phone":"+31 182 502 534",
    "sg:postcode":"3467 PN",
    "sg:province":"Utrecht",
    "wof:name":"Van Der Wolf Jachtbouw",
    "wof:placetype":"venue"
},
  "geometry": {"coordinates":[4.809392,52.014759],"type":"Point"}
}