{
  "type": "Feature",
  "properties": {
    "addr:full":"Oudegracht 109 Utrecht Utrecht 3511 AG",
    "addr:housenumber":"109",
    "addr:postcode":"3511",
    "addr:street":"Oudegracht",
    "iso:country":"NL",
    "sg:address":"Oudegracht 109",
    "sg:city":"Utrecht",
    "sg:classifiers":[
        {
            "category":"Shopping",
            "subcategory":"Gifts & Souvenirs",
            "type":"Retail Goods"
        }
    ],
    "sg:phone":"+31 30 234 0112",
    "sg:postcode":"3511 AG",
    "sg:province":"Utrecht",
    "sg:tags":[
        "geschenken"
    ],
    "wof:name":"Grants Gifts Bv",
    "wof:placetype":"venue"
},
  "geometry": {"coordinates":[5.115405,52.088932],"type":"Point"}
}