{
  "type": "Feature",
  "properties": {
    "addr:full":"Klokpoort 53 Leiden Zuid-Holland 2312 CX",
    "addr:housenumber":"53",
    "addr:postcode":"2312 cx",
    "addr:street":"Klokpoort",
    "iso:country":"NL",
    "sg:address":"Klokpoort 53",
    "sg:city":"Leiden",
    "sg:orig_category":"Non-Classified Establishments",
    "sg:phone":"+31 71 522 6138",
    "sg:postcode":"2312 CX",
    "sg:province":"Zuid-Holland",
    "sg:website":"http://www.decork.nl",
    "wof:name":"D?cork De Kurkspeciaalzaak",
    "wof:placetype":"venue"
},
  "geometry": {"coordinates":[4.498177,52.162685],"type":"Point"}
}