{
  "type": "Feature",
  "properties": {
    "addr:full":"Zuivelstr 35 Bergen Op Zoom Noord-Brabant 4611 PE",
    "addr:housenumber":"35",
    "addr:postcode":"4611 pe",
    "addr:street":"Zuivelstr",
    "iso:country":"NL",
    "sg:address":"Zuivelstr 35",
    "sg:city":"Bergen Op Zoom",
    "sg:orig_category":"Huishoudelijke Apparaten En Artikelen",
    "sg:phone":"+31 164 211 058",
    "sg:postcode":"4611 PE",
    "sg:province":"Noord-Brabant",
    "wof:name":"Blokker Nv",
    "wof:placetype":"venue"
},
  "geometry": {"coordinates":[4.289033,51.495178],"type":"Point"}
}