{
  "type": "Feature",
  "properties": {
    "iso:country":"NL",
    "sg:address":"Constantijn Huygensstr 44",
    "sg:city":"Haarlem",
    "sg:orig_category":"Loodgieterswerk, Verwarming And Sanitaire Installaties",
    "sg:phone":"+31 23 538 1270",
    "sg:postcode":"2026 XX",
    "sg:province":"Noord-Holland",
    "wof:name":"P.H. Van Oppen",
    "wof:placetype":"venue"
},
  "geometry": {"coordinates":[4.652238,52.41758],"type":"Point"}
}