{
  "type": "Feature",
  "properties": {
    "iso:country":"NL",
    "sg:address":"Ns Plein 27",
    "sg:city":"Tilburg",
    "sg:orig_category":"Kappers",
    "sg:phone":"+31 13 542 6218",
    "sg:postcode":"5014 DB",
    "sg:province":"North Brabant",
    "wof:name":"Avant Garde Haar- En Huidverzorging",
    "wof:placetype":"venue"
},
  "geometry": {"coordinates":[5.092656,51.560829],"type":"Point"}
}