{
  "type": "Feature",
  "properties": {
    "iso:country":"NL",
    "sg:address":"Beukenln 36",
    "sg:city":"Soest",
    "sg:orig_category":"Adviesbureaus Bedrijfsorganisatie",
    "sg:phone":"+31 35 582 2730",
    "sg:postcode":"3762 AJ",
    "sg:province":"Utrecht",
    "wof:name":"Marcommit Bv",
    "wof:placetype":"venue"
},
  "geometry": {"coordinates":[5.288006,52.176853],"type":"Point"}
}