{
  "type": "Feature",
  "properties": {
    "addr:full":"Lindenhoutseweg 45 Nijmegen Gelderland 6545 AH",
    "addr:housenumber":"45",
    "addr:postcode":"6545 ah",
    "addr:street":"Lindenhoutseweg;Gelderland",
    "iso:country":"NL",
    "sg:address":"Lindenhoutseweg 45",
    "sg:city":"Nijmegen",
    "sg:orig_category":"Kunststofverpakkingen Fab",
    "sg:phone":"+31 24 371 0111",
    "sg:postcode":"6545 AH",
    "sg:province":"Gelderland",
    "wof:name":"Sealed Air Bv",
    "wof:placetype":"venue"
},
  "geometry": {"coordinates":[5.809825,51.844528],"type":"Point"}
}