{
  "type": "Feature",
  "properties": {
    "addr:full":"Speerstraat 6 Amsterdam North Holland 1076 XN",
    "addr:housenumber":"6",
    "addr:postcode":"1076 xn",
    "addr:street":"Speerstraat",
    "iso:country":"NL",
    "sg:address":"Speerstraat 6",
    "sg:city":"Amsterdam",
    "sg:classifiers":[
        {
            "category":"Education",
            "subcategory":"Preschool",
            "type":"Public Place"
        }
    ],
    "sg:phone":"+31 20 671 9739",
    "sg:postcode":"1076 XN",
    "sg:province":"North Holland",
    "sg:tags":[
        "kleuteronderwijs",
        "basis-"
    ],
    "wof:name":"Elout Van Soeterwoudeschool",
    "wof:placetype":"venue"
},
  "geometry": {"coordinates":[4.862324,52.34911],"type":"Point"}
}