{
  "type": "Feature",
  "properties": {
    "addr:full":"Bogortuin 109 Amsterdam Noord-Holland 1019 PE",
    "addr:housenumber":"109",
    "addr:postcode":"1019 pe",
    "addr:street":"Bogortuin",
    "iso:country":"NL",
    "sg:address":"Bogortuin 109",
    "sg:city":"Amsterdam",
    "sg:orig_category":"Binnenhuisarchitectuur",
    "sg:phone":"+31 20 623 2624",
    "sg:postcode":"1019 PE",
    "sg:province":"Noord-Holland",
    "wof:name":"Vos, Wim De",
    "wof:placetype":"venue"
},
  "geometry": {"coordinates":[4.933963,52.377396],"type":"Point"}
}