{
  "type": "Feature",
  "properties": {
    "addr:full":"Nassau Odijckstraat 12 'S Gravenhage Zuid-Holland 2596 AH",
    "addr:housenumber":"12",
    "addr:postcode":"2596 ah",
    "addr:street":"Nassau Odijckstraat;' S",
    "iso:country":"NL",
    "sg:address":"Nassau Odijckstraat 12",
    "sg:city":"'S Gravenhage",
    "sg:orig_category":"Public Relationbureaus",
    "sg:phone":"+31 70 328 0537",
    "sg:postcode":"2596 AH",
    "sg:province":"Zuid-Holland",
    "wof:name":"Lammerts Van Bueren Projectorganisatie",
    "wof:placetype":"venue"
},
  "geometry": {"coordinates":[4.315053,52.089016],"type":"Point"}
}