{
  "type": "Feature",
  "properties": {
    "addr:full":"Oosterdk 89 Sneek Provincie Friesland 8601 BS",
    "addr:housenumber":"89",
    "addr:postcode":"provincie;8601 bs",
    "addr:street":"Oosterdk",
    "iso:country":"NL",
    "sg:address":"Oosterdk 89",
    "sg:city":"Sneek",
    "sg:orig_category":"Verlichting",
    "sg:phone":"+31 515 412 874",
    "sg:postcode":"8601 BS",
    "sg:province":"Provincie Friesland",
    "wof:name":"Boer Licht, De",
    "wof:placetype":"venue"
},
  "geometry": {"coordinates":[5.664994,53.03384],"type":"Point"}
}