{
  "type": "Feature",
  "properties": {
    "iso:country":"NL",
    "sg:address":"Stationsstraat 12",
    "sg:city":"Twello",
    "sg:orig_category":"Zuivelproducten",
    "sg:phone":"+31 571 275 616",
    "sg:postcode":"7391 EK",
    "sg:province":"Gelderland",
    "wof:name":"Leida'S Kaasboetiek",
    "wof:placetype":"venue"
},
  "geometry": {"coordinates":[6.102842,52.237457],"type":"Point"}
}