{
  "type": "Feature",
  "properties": {
    "iso:country":"NL",
    "sg:address":"Koenestr 53A",
    "sg:city":"Amerongen",
    "sg:orig_category":"Afzuiginstallaties",
    "sg:phone":"+31 343 456 844",
    "sg:postcode":"3958 XE",
    "sg:province":"Utrecht",
    "wof:name":"Keulen, Van",
    "wof:placetype":"venue"
},
  "geometry": {"coordinates":[5.462574,52.003208],"type":"Point"}
}