{
  "type": "Feature",
  "properties": {
    "iso:country":"NL",
    "sg:address":"Luntersewg 25",
    "sg:city":"Ede",
    "sg:orig_category":"Pluimveebedrijven En -Handelaren",
    "sg:phone":"+31 318 610 425",
    "sg:postcode":"6718 WB",
    "sg:province":"Gelderland",
    "wof:name":"Boekhout",
    "wof:placetype":"venue"
},
  "geometry": {"coordinates":[5.642707,52.057793],"type":"Point"}
}