{
  "type": "Feature",
  "properties": {
    "addr:full":"Wilde Wingerdln 259 Gouda South Holland 2803 WB",
    "addr:housenumber":"259",
    "addr:postcode":"2803 wb",
    "iso:country":"NL",
    "sg:address":"Wilde Wingerdln 259",
    "sg:city":"Gouda",
    "sg:orig_category":"Verenigingen En Stichtingen",
    "sg:phone":"+31 182 531 616",
    "sg:postcode":"2803 WB",
    "sg:province":"South Holland",
    "wof:name":"Gouds Seniorenwerk En Hulpdienst, Sticht",
    "wof:placetype":"venue"
},
  "geometry": {"coordinates":[4.693963,52.023811],"type":"Point"}
}