{
  "type": "Feature",
  "properties": {
    "iso:country":"NL",
    "sg:address":"Nieuwestad 73",
    "sg:city":"Leeuwarden",
    "sg:orig_category":"Herenmodezaken",
    "sg:phone":"+31 58 212 0444",
    "sg:postcode":"8911 CK",
    "sg:province":"Friesland",
    "wof:name":"First Man - J. Wijnia En Zoon",
    "wof:placetype":"venue"
},
  "geometry": {"coordinates":[5.793384,53.201221],"type":"Point"}
}