{
  "type": "Feature",
  "properties": {
    "iso:country":"NL",
    "sg:address":"Langestraat 155",
    "sg:city":"Klazienaveen",
    "sg:orig_category":"Hypotheken And Hypotheekbanken",
    "sg:phone":"+31 591 315 504",
    "sg:postcode":"7891 GK",
    "sg:province":"Drenthe",
    "wof:name":"Heidinga Assurantien",
    "wof:placetype":"venue"
},
  "geometry": {"coordinates":[6.998573,52.724167],"type":"Point"}
}