{
  "type": "Feature",
  "properties": {
    "addr:full":"Jachthavenwg 50 Venlo Limburg 5928 NT",
    "addr:housenumber":"50",
    "addr:postcode":"5928 nt",
    "addr:street":"Jachthavenwg",
    "iso:country":"NL",
    "sg:address":"Jachthavenwg 50",
    "sg:city":"Venlo",
    "sg:orig_category":"Sportverenigingen En Ontspannings- Verenigingen",
    "sg:phone":"+31 77 382 3820",
    "sg:postcode":"5928 NT",
    "sg:province":"Limburg",
    "wof:name":"Maas Watersportver, De",
    "wof:placetype":"venue"
},
  "geometry": {"coordinates":[6.14644,51.389629],"type":"Point"}
}