{
  "type": "Feature",
  "properties": {
    "addr:full":"Boelekd 109 Gouda Zuid-Holland 2806 AG",
    "addr:housenumber":"109",
    "addr:postcode":"2806",
    "iso:country":"NL",
    "sg:address":"Boelekd 109",
    "sg:city":"Gouda",
    "sg:orig_category":"Kunststoffen - Fabrieken En Groothandel",
    "sg:phone":"+31 182 504 204",
    "sg:postcode":"2806 AG",
    "sg:province":"Zuid-Holland",
    "wof:name":"Vds",
    "wof:placetype":"venue"
},
  "geometry": {"coordinates":[4.710715,52.010006],"type":"Point"}
}