{
  "type": "Feature",
  "properties": {
    "addr:full":"De Veken 106 Opmeer Noord-Holland 1716 KG",
    "addr:housenumber":"106",
    "addr:postcode":"1716 kg",
    "addr:street":"De Veken",
    "iso:country":"NL",
    "sg:address":"De Veken 106",
    "sg:city":"Opmeer",
    "sg:orig_category":"Noten",
    "sg:phone":"+31 226 359 906",
    "sg:postcode":"1716 KG",
    "sg:province":"Noord-Holland",
    "wof:name":"Westfriesche Pindabranderij, De",
    "wof:placetype":"venue"
},
  "geometry": {"coordinates":[4.954695,52.70644],"type":"Point"}
}