{
  "type": "Feature",
  "properties": {
    "addr:full":"Mathenesserln 184 Rotterdam South Holland 3015 CM",
    "addr:housenumber":"184",
    "addr:postcode":"3015 cm",
    "iso:country":"NL",
    "sg:address":"Mathenesserln 184",
    "sg:city":"Rotterdam",
    "sg:orig_category":"Verenigingen En Stichtingen",
    "sg:phone":"+31 10 436 1900",
    "sg:postcode":"3015 CM",
    "sg:province":"South Holland",
    "wof:name":"Onder Dak",
    "wof:placetype":"venue"
},
  "geometry": {"coordinates":[4.466514,51.914509],"type":"Point"}
}