{
  "type": "Feature",
  "properties": {
    "iso:country":"NL",
    "sg:address":"Erasmusstraat 92",
    "sg:city":"Amersfoort",
    "sg:orig_category":"Autokeuringen",
    "sg:phone":"+31 33 455 2906",
    "sg:postcode":"3822 BH",
    "sg:province":"Utrecht",
    "wof:name":"Peter Thiel Schade Auto'S",
    "wof:placetype":"venue"
},
  "geometry": {"coordinates":[5.408838,52.178497],"type":"Point"}
}