{
  "type": "Feature",
  "properties": {
    "addr:full":"J P Broekhovenstr 11C Elburg Gelderland 8081 HB",
    "addr:housenumber":"11c",
    "addr:postcode":"8081 hb",
    "addr:street":"J P Broekhovenstr;Gelderland",
    "iso:country":"NL",
    "sg:address":"J P Broekhovenstr 11C",
    "sg:city":"Elburg",
    "sg:orig_category":"Kansspelen",
    "sg:phone":"+31 525 680 001",
    "sg:postcode":"8081 HB",
    "sg:province":"Gelderland",
    "sg:website":"http://www.hbtrading.nl",
    "wof:name":"H & B Trading",
    "wof:placetype":"venue"
},
  "geometry": {"coordinates":[5.8305721283,52.4536514282],"type":"Point"}
}