{
  "type": "Feature",
  "properties": {
    "addr:full":"Gebroken Meeldijk 56 Barendrecht Zuid-Holland 2991 VD",
    "addr:housenumber":"56",
    "addr:postcode":"2991 vd",
    "addr:street":"Gebroken Meeldijk",
    "iso:country":"NL",
    "sg:address":"Gebroken Meeldijk 56",
    "sg:city":"Barendrecht",
    "sg:classifiers":[
        {
            "category":"Food & Beverages",
            "subcategory":"Fruits & Vegetables",
            "type":"Retail Goods"
        }
    ],
    "sg:phone":"+31 180 612 577",
    "sg:postcode":"2991 VD",
    "sg:province":"Zuid-Holland",
    "sg:tags":[
        "groenten"
    ],
    "wof:name":"Levensmiddelenbedrijf Vano",
    "wof:placetype":"venue"
},
  "geometry": {"coordinates":[4.558592,51.854443],"type":"Point"}
}