{
  "type": "Feature",
  "properties": {
    "addr:full":"Wagenaarstr 42 Zwyndrecht Zuid-Holland 3335 XK",
    "addr:housenumber":"42",
    "addr:postcode":"3335 xk",
    "addr:street":"Wagenaarstr",
    "iso:country":"NL",
    "sg:address":"Wagenaarstr 42",
    "sg:city":"Zwyndrecht",
    "sg:orig_category":"Kantoorbenodigdheden - Fabrieken En Groothandel",
    "sg:phone":"+31 78 610 1927",
    "sg:postcode":"3335 XK",
    "sg:province":"Zuid-Holland",
    "wof:name":"Sloot, J H Van Der",
    "wof:placetype":"venue"
},
  "geometry": {"coordinates":[4.6071200371,51.8278388977],"type":"Point"}
}