{
  "type": "Feature",
  "properties": {
    "addr:full":"Wethouder De Joodestraat 1 Woudrichem Noord-Brabant 4285 CC",
    "addr:housenumber":"1",
    "addr:postcode":"4285 cc",
    "addr:street":"Wethouder De Joodestraat",
    "iso:country":"NL",
    "sg:address":"Wethouder De Joodestraat 1",
    "sg:city":"Woudrichem",
    "sg:classifiers":[
        {
            "category":"Fast Food",
            "type":"Food & Drink"
        }
    ],
    "sg:phone":"+31 183 304 868",
    "sg:postcode":"4285 CC",
    "sg:province":"Noord-Brabant",
    "sg:tags":[
        "afhaal",
        "restaurant"
    ],
    "wof:name":"Cafetaria 'T Rond",
    "wof:placetype":"venue"
},
  "geometry": {"coordinates":[4.998791,51.810883],"type":"Point"}
}