{
  "type": "Feature",
  "properties": {
    "addr:full":"Eenlandswg 29 Halsteren North Brabant 4661 LH",
    "addr:housenumber":"29",
    "addr:postcode":"4661 lh",
    "addr:street":"Eenlandswg",
    "iso:country":"NL",
    "sg:address":"Eenlandswg 29",
    "sg:city":"Halsteren",
    "sg:orig_category":"Psychotherapeuten",
    "sg:phone":"+31 164 681 622",
    "sg:postcode":"4661 LH",
    "sg:province":"North Brabant",
    "wof:name":"Emmy Mul",
    "wof:placetype":"venue"
},
  "geometry": {"coordinates":[4.275578,51.524738],"type":"Point"}
}