{
  "type": "Feature",
  "properties": {
    "addr:full":"Stroyenborchdreef 12 Utrecht Utrecht 3562 GN",
    "addr:housenumber":"12",
    "addr:postcode":"3562 gn",
    "addr:street":"Stroyenborchdreef",
    "iso:country":"NL",
    "sg:address":"Stroyenborchdreef 12",
    "sg:city":"Utrecht",
    "sg:orig_category":"Verenigingsgebouwen",
    "sg:phone":"+31 30 263 4022",
    "sg:postcode":"3562 GN",
    "sg:province":"Utrecht",
    "wof:name":"Einstein",
    "wof:placetype":"venue"
},
  "geometry": {"coordinates":[5.116246,52.120949],"type":"Point"}
}