{
  "type": "Feature",
  "properties": {
    "addr:full":"O Nassaustr 12 Leeuwarden Provincie Friesland 8933 BR",
    "addr:housenumber":"12",
    "addr:postcode":"8933 br",
    "addr:street":"Provincie Friesland",
    "iso:country":"NL",
    "sg:address":"O Nassaustr 12",
    "sg:city":"Leeuwarden",
    "sg:orig_category":"Vakantieverblijven",
    "sg:phone":"+31 58 215 9154",
    "sg:postcode":"8933 BR",
    "sg:province":"Provincie Friesland",
    "sg:website":"http://www.alpicasa.nl",
    "wof:name":"Alpicasa Vakantiewoningen",
    "wof:placetype":"venue"
},
  "geometry": {"coordinates":[5.807752,53.198624],"type":"Point"}
}