{
  "type": "Feature",
  "properties": {
    "addr:full":"Mauritsstraat 7 Hilversum Noord-Holland 1211 KE",
    "addr:housenumber":"7",
    "addr:postcode":"1211 ke",
    "addr:street":"Mauritsstraat",
    "iso:country":"NL",
    "sg:address":"Mauritsstraat 7",
    "sg:city":"Hilversum",
    "sg:orig_category":"Schilderwerk",
    "sg:phone":"+31 35 621 6839",
    "sg:postcode":"1211 KE",
    "sg:province":"Noord-Holland",
    "wof:name":"Reinders",
    "wof:placetype":"venue"
},
  "geometry": {"coordinates":[5.167358,52.220066],"type":"Point"}
}