{
  "type": "Feature",
  "properties": {
    "addr:full":"V A V Wyckln 1 Oldebroek Gelderland 8096 AE",
    "addr:housenumber":"1",
    "addr:postcode":"8096 ae",
    "addr:street":"V A V Wyckln;Gelderland",
    "iso:country":"NL",
    "sg:address":"V A V Wyckln 1",
    "sg:city":"Oldebroek",
    "sg:orig_category":"Koffers En Tassen - Fabrieken En Groothandel",
    "sg:phone":"+31 525 633 073",
    "sg:postcode":"8096 AE",
    "sg:province":"Gelderland",
    "wof:name":"Alpian",
    "wof:placetype":"venue"
},
  "geometry": {"coordinates":[5.8934,52.445419],"type":"Point"}
}