{
  "type": "Feature",
  "properties": {
    "addr:full":"Koningstraat 73 Apeldoorn Gelderland 7315 HV",
    "addr:housenumber":"73",
    "addr:postcode":"7315 hv",
    "addr:street":"Koningstraat;Gelderland",
    "iso:country":"NL",
    "sg:address":"Koningstraat 73",
    "sg:city":"Apeldoorn",
    "sg:orig_category":"Artsen And Specialisten",
    "sg:phone":"+31 55 521 8022",
    "sg:postcode":"7315 HV",
    "sg:province":"Gelderland",
    "wof:name":"J. Houtman En R Verdonk",
    "wof:placetype":"venue"
},
  "geometry": {"coordinates":[5.955444,52.234573],"type":"Point"}
}