{
  "type": "Feature",
  "properties": {
    "addr:full":"Zijdwerk 20 Wervershoof Noord-Holland 1693 NZ",
    "addr:housenumber":"20",
    "addr:postcode":"1693 nz",
    "addr:street":"Zijdwerk",
    "iso:country":"NL",
    "sg:address":"Zijdwerk 20",
    "sg:city":"Wervershoof",
    "sg:orig_category":"Huisdierenvoer Fab",
    "sg:phone":"+31 228 583 130",
    "sg:postcode":"1693 NZ",
    "sg:province":"Noord-Holland",
    "wof:name":"K. Doeve Dierenvoeders",
    "wof:placetype":"venue"
},
  "geometry": {"coordinates":[170.36663799999999,-43.587711],"type":"Point"}
}