{
  "type": "Feature",
  "properties": {
    "addr:full":"De Messenmaker 6 Veldhoven Noord-Brabant 5506 CG",
    "addr:housenumber":"6",
    "addr:postcode":"5506 cg",
    "addr:street":"De Messenmaker",
    "iso:country":"NL",
    "sg:address":"De Messenmaker 6",
    "sg:city":"Veldhoven",
    "sg:classifiers":[
        {
            "category":"Education",
            "subcategory":"Preschool",
            "type":"Public Place"
        }
    ],
    "sg:phone":"+31 40 253 3566",
    "sg:postcode":"5506 CG",
    "sg:province":"Noord-Brabant",
    "sg:tags":[
        "kleuteronderwijs",
        "basis-"
    ],
    "wof:name":"Peuterspeelzaal 'T Sterretje",
    "wof:placetype":"venue"
},
  "geometry": {"coordinates":[5.387155,51.417152],"type":"Point"}
}