{
  "type": "Feature",
  "properties": {
    "addr:full":"Samsonweg 2 Wormerveer North Holland 1521 RC",
    "addr:housenumber":"2",
    "addr:postcode":"1521 rc",
    "addr:street":"Samsonweg",
    "iso:country":"NL",
    "sg:address":"Samsonweg 2",
    "sg:city":"Wormerveer",
    "sg:orig_category":"Goederenvervoer Over De Weg",
    "sg:phone":"+31 75 631 1311",
    "sg:postcode":"1521 RC",
    "sg:province":"North Holland",
    "wof:name":"H. Nijboer Verhuis- En Transportbedrijf Bv",
    "wof:placetype":"venue"
},
  "geometry": {"coordinates":[4.784357,52.503277],"type":"Point"}
}