{
  "type": "Feature",
  "properties": {
    "addr:full":"Kerkln 12 Akersloot Noord-Holland 1921 BL",
    "addr:housenumber":"12",
    "addr:postcode":"1921 bl",
    "addr:street":"Kerkln",
    "iso:country":"NL",
    "sg:address":"Kerkln 12",
    "sg:city":"Akersloot",
    "sg:orig_category":"Huisbrand- En Industrieolie",
    "sg:phone":"+31 251 312 301",
    "sg:postcode":"1921 BL",
    "sg:province":"Noord-Holland",
    "wof:name":"Verduin, H P",
    "wof:placetype":"venue"
},
  "geometry": {"coordinates":[4.734425,52.56197],"type":"Point"}
}