{
  "type": "Feature",
  "properties": {
    "addr:full":"Schalk Burgerstraat 25 'S Gravenhage South Holland 2572 TN",
    "addr:housenumber":"25",
    "addr:postcode":"2572",
    "addr:street":"Schalk Burgerstraat;' S Gravenhage",
    "iso:country":"NL",
    "sg:address":"Schalk Burgerstraat 25",
    "sg:city":"'S Gravenhage",
    "sg:orig_category":"Werving And Selectie Van Tijdelijk Personeel And Uitzendkantoren",
    "sg:phone":"+31 70 362 0086",
    "sg:postcode":"2572 TN",
    "sg:province":"South Holland",
    "wof:name":"Dingol",
    "wof:placetype":"venue"
},
  "geometry": {"coordinates":[4.293241024,52.067779541],"type":"Point"}
}