{
  "type": "Feature",
  "properties": {
    "iso:country":"NL",
    "sg:address":"Wikkeweg 3",
    "sg:city":"Apeldoorn",
    "sg:orig_category":"Schoonheidssalons",
    "sg:phone":"+31 55 323 1730",
    "sg:postcode":"7325 WE",
    "sg:province":"Gelderland",
    "wof:name":"Schoonheidssalon Bonnie Ten Damme",
    "wof:placetype":"venue"
},
  "geometry": {"coordinates":[6.020601,52.228237],"type":"Point"}
}