{
  "type": "Feature",
  "properties": {
    "addr:full":"Riouwln 40 Vlaardingen South Holland 3131 NL",
    "addr:housenumber":"40",
    "addr:postcode":"3131 nl",
    "addr:street":"Riouwln",
    "iso:country":"NL",
    "sg:address":"Riouwln 40",
    "sg:city":"Vlaardingen",
    "sg:orig_category":"Artsen - Huisartsen",
    "sg:phone":"+31 10 434 2081",
    "sg:postcode":"3131 NL",
    "sg:province":"South Holland",
    "wof:name":"Slagter, G",
    "wof:placetype":"venue"
},
  "geometry": {"coordinates":[4.340359,51.910442],"type":"Point"}
}