{
  "type": "Feature",
  "properties": {
    "addr:full":"Wilde Wingerd 7 Helmond Noord-Brabant 5708 DC",
    "addr:housenumber":"7",
    "addr:postcode":"5708",
    "addr:street":"Wilde Wingerd",
    "iso:country":"NL",
    "sg:address":"Wilde Wingerd 7",
    "sg:city":"Helmond",
    "sg:orig_category":"Adviesbureaus Bedrijfsorganisatie",
    "sg:phone":"+31 492 529 059",
    "sg:postcode":"5708 DC",
    "sg:province":"Noord-Brabant",
    "wof:name":"Modderkolk Bv",
    "wof:placetype":"venue"
},
  "geometry": {"coordinates":[5.611197,51.484829],"type":"Point"}
}