{
  "type": "Feature",
  "properties": {
    "addr:full":"Stationsstr 23 Oosterwolde Fr Friesland 8431 ET",
    "addr:housenumber":"23",
    "addr:postcode":"8431 et",
    "addr:street":"Stationsstr",
    "iso:country":"NL",
    "sg:address":"Stationsstr 23",
    "sg:city":"Oosterwolde Fr",
    "sg:orig_category":"Makelaars En Adviseurs Onroerende Goederen",
    "sg:phone":"+31 516 520 470",
    "sg:postcode":"8431 ET",
    "sg:province":"Friesland",
    "sg:website":"http://www.makelaardijbijlsma.nl",
    "wof:name":"Bijlsma Vof",
    "wof:placetype":"venue"
},
  "geometry": {"coordinates":[6.290997,52.989319],"type":"Point"}
}