{
  "type": "Feature",
  "properties": {
    "iso:country":"NL",
    "sg:address":"Cloosterstraat 48",
    "sg:city":"Kloosterzande",
    "sg:orig_category":"Paramedische Behandelingen",
    "sg:phone":"+31 114 681 163",
    "sg:postcode":"4587 CD",
    "sg:province":"Zeeland",
    "wof:name":"Logopedie Prakt",
    "wof:placetype":"venue"
},
  "geometry": {"coordinates":[4.016277,51.367424],"type":"Point"}
}