{
  "type": "Feature",
  "properties": {
    "addr:full":"Grietsestraat 33 Zevenaar Gelderland 6901 GR",
    "addr:housenumber":"33",
    "addr:postcode":"6901",
    "addr:street":"Grietsestraat",
    "iso:country":"NL",
    "sg:address":"Grietsestraat 33",
    "sg:city":"Zevenaar",
    "sg:orig_category":"Herenmodezaken",
    "sg:phone":"+31 316 332 589",
    "sg:postcode":"6901 GR",
    "sg:province":"Gelderland",
    "wof:name":"Vof Jansen Mannenmode",
    "wof:placetype":"venue"
},
  "geometry": {"coordinates":[6.077177,51.930199],"type":"Point"}
}