{
  "type": "Feature",
  "properties": {
    "addr:full":"De Zeis 76 Apeldoorn Gelderland 7335 KC",
    "addr:housenumber":"76",
    "addr:postcode":"7335 kc",
    "addr:street":"De Zeis;Gelderland",
    "iso:country":"NL",
    "sg:address":"De Zeis 76",
    "sg:city":"Apeldoorn",
    "sg:orig_category":"Goudsmeden En Zilversmeden",
    "sg:phone":"+31 55 542 3794",
    "sg:postcode":"7335 KC",
    "sg:province":"Gelderland",
    "wof:name":"Noordberger, C J",
    "wof:placetype":"venue"
},
  "geometry": {"coordinates":[5.958562,52.200855],"type":"Point"}
}