{
  "type": "Feature",
  "properties": {
    "addr:full":"Molenbeekstraat 10 Voerendaal Limburg 6367 XX",
    "addr:housenumber":"10",
    "addr:postcode":"6367 xx",
    "addr:street":"Molenbeekstraat",
    "iso:country":"NL",
    "sg:address":"Molenbeekstraat 10",
    "sg:city":"Voerendaal",
    "sg:orig_category":"Artsen And Specialisten",
    "sg:phone":"+31 45 575 0945",
    "sg:postcode":"6367 XX",
    "sg:province":"Limburg",
    "wof:name":"Drs. L.A.E. De Vooght",
    "wof:placetype":"venue"
},
  "geometry": {"coordinates":[5.92583,50.88401],"type":"Point"}
}