{
  "type": "Feature",
  "properties": {
    "addr:full":"Schoolstraat 1 Grathem Limburg 6096 AS",
    "addr:housenumber":"1",
    "addr:postcode":"6096 as",
    "addr:street":"Schoolstraat",
    "iso:country":"NL",
    "sg:address":"Schoolstraat 1",
    "sg:city":"Grathem",
    "sg:classifiers":[
        {
            "category":"Education",
            "subcategory":"Preschool",
            "type":"Public Place"
        }
    ],
    "sg:phone":"+31 475 459 008",
    "sg:postcode":"6096 AS",
    "sg:province":"Limburg",
    "sg:tags":[
        "kleuteronderwijs",
        "basis-"
    ],
    "wof:name":"Jenaplan Basisschool De Klink",
    "wof:placetype":"venue"
},
  "geometry": {"coordinates":[5.858997,51.192986],"type":"Point"}
}