{
  "type": "Feature",
  "properties": {
    "addr:full":"Peperstr 7 Valkenswaard Noord-Brabant 5554 EG",
    "addr:housenumber":"7",
    "addr:postcode":"5554 eg",
    "addr:street":"Peperstr",
    "iso:country":"NL",
    "sg:address":"Peperstr 7",
    "sg:city":"Valkenswaard",
    "sg:orig_category":"Verzekeringen - Verzekeringskantoren",
    "sg:phone":"+31 40 207 5626",
    "sg:postcode":"5554 EG",
    "sg:province":"Noord-Brabant",
    "wof:name":"Wijk En Partn, Van",
    "wof:placetype":"venue"
},
  "geometry": {"coordinates":[5.459562,51.3493],"type":"Point"}
}