{
  "type": "Feature",
  "properties": {
    "addr:full":"Vyfhuizenberg 117 Roosendaal Noord-Brabant 4708 AJ",
    "addr:housenumber":"117",
    "addr:postcode":"4708 aj",
    "addr:street":"Vyfhuizenberg",
    "iso:country":"NL",
    "sg:address":"Vyfhuizenberg 117",
    "sg:city":"Roosendaal",
    "sg:orig_category":"Bedrijfsmechanisatie En -Automatisering",
    "sg:phone":"+31 165 553 528",
    "sg:postcode":"4708 AJ",
    "sg:province":"Noord-Brabant",
    "wof:name":"Blanche Bv",
    "wof:placetype":"venue"
},
  "geometry": {"coordinates":[4.444015,51.519337],"type":"Point"}
}