{
  "type": "Feature",
  "properties": {
    "iso:country":"NL",
    "sg:address":"Vyfhuizenberg 117",
    "sg:city":"Roosendaal",
    "sg:orig_category":"Bedrijfsmechanisatie En -Automatisering",
    "sg:phone":"+31 165 553 528",
    "sg:postcode":"4708 AJ",
    "sg:province":"Noord-Brabant",
    "wof:name":"Blanche Bv",
    "wof:placetype":"venue"
},
  "geometry": {"coordinates":[4.444015,51.519337],"type":"Point"}
}