{
  "type": "Feature",
  "properties": {
    "addr:full":"L Davidsstr 152 Almere Flevoland 1311 LW",
    "addr:housenumber":"152",
    "addr:postcode":"1311 lw",
    "addr:street":"Flevoland",
    "iso:country":"NL",
    "sg:address":"L Davidsstr 152",
    "sg:city":"Almere",
    "sg:orig_category":"Adviesbureaus Bouwkunde",
    "sg:phone":"+31 36 546 5473",
    "sg:postcode":"1311 LW",
    "sg:province":"Flevoland",
    "wof:name":"Waltje",
    "wof:placetype":"venue"
},
  "geometry": {"coordinates":[5.179974,52.370354],"type":"Point"}
}