{
  "type": "Feature",
  "properties": {
    "addr:full":"Buitenwatersloot 318 Delft Zuid-Holland 2614 GR",
    "addr:housenumber":"318",
    "addr:postcode":"2614",
    "addr:street":"Buitenwatersloot",
    "iso:country":"NL",
    "sg:address":"Buitenwatersloot 318",
    "sg:city":"Delft",
    "sg:orig_category":"Boekhouders",
    "sg:phone":"+31 15 214 2355",
    "sg:postcode":"2614 GR",
    "sg:province":"Zuid-Holland",
    "wof:name":"Berkien Administratiebureau Delft Bv",
    "wof:placetype":"venue"
},
  "geometry": {"coordinates":[4.343418,52.004063],"type":"Point"}
}