{
  "type": "Feature",
  "properties": {
    "addr:full":"Voorstr 10 Fynaart Noord-Brabant 4793 EV",
    "addr:housenumber":"10",
    "addr:postcode":"4793 ev",
    "addr:street":"Voorstr",
    "iso:country":"NL",
    "sg:address":"Voorstr 10",
    "sg:city":"Fynaart",
    "sg:orig_category":"Boekhandels",
    "sg:phone":"+31 168 462 694",
    "sg:postcode":"4793 EV",
    "sg:province":"Noord-Brabant",
    "wof:name":"Boekhoven Vof",
    "wof:placetype":"venue"
},
  "geometry": {"coordinates":[4.467011,51.634895],"type":"Point"}
}