{
  "type": "Feature",
  "properties": {
    "addr:full":"Boomstraat 25 Terschelling West Provincie Friesland 8881 BS",
    "addr:housenumber":"25",
    "addr:postcode":"8881 bs",
    "addr:street":"Boomstraat;Friesland",
    "iso:country":"NL",
    "sg:address":"Boomstraat 25",
    "sg:city":"Terschelling West",
    "sg:orig_category":"Bloemen And Planten",
    "sg:phone":"+31 562 443 058",
    "sg:postcode":"8881 BS",
    "sg:province":"Provincie Friesland",
    "wof:name":"Lotus Petite Fleur",
    "wof:placetype":"venue"
},
  "geometry": {"coordinates":[5.215838,53.360481],"type":"Point"}
}