{
  "type": "Feature",
  "properties": {
    "addr:full":"Zesakkerlaan 1 Overasselt Gelderland 6611 AZ",
    "addr:housenumber":"1",
    "addr:postcode":"6611",
    "addr:street":"Zesakkerlaan;Gelderland",
    "iso:country":"NL",
    "sg:address":"Zesakkerlaan 1",
    "sg:city":"Overasselt",
    "sg:orig_category":"Verzekeringen",
    "sg:phone":"+31 24 622 2112",
    "sg:postcode":"6611 AZ",
    "sg:province":"Gelderland",
    "wof:name":"3Theo Bekkers Assurantie Advies Kantoor",
    "wof:placetype":"venue"
},
  "geometry": {"coordinates":[-111.93034400000001,34.168091],"type":"Point"}
}