{
  "type": "Feature",
  "properties": {
    "addr:full":"Hekerbeek 21 Geleen Limburg 6166 HW",
    "addr:housenumber":"21",
    "addr:postcode":"6166 hw",
    "addr:street":"Hekerbeek",
    "iso:country":"NL",
    "sg:address":"Hekerbeek 21",
    "sg:city":"Geleen",
    "sg:orig_category":"Verzekeringen - Verzekeringskantoren",
    "sg:phone":"+31 46 423 1994",
    "sg:postcode":"6166 HW",
    "sg:province":"Limburg",
    "wof:name":"M & S Bv",
    "wof:placetype":"venue"
},
  "geometry": {"coordinates":[5.839395,50.976082],"type":"Point"}
}