{
  "type": "Feature",
  "properties": {
    "addr:full":"Klompenmakerstraat 10 Ridderkerk South Holland 2984 BB",
    "addr:housenumber":"10",
    "addr:postcode":"2984 bb",
    "addr:street":"Klompenmakerstraat",
    "iso:country":"NL",
    "sg:address":"Klompenmakerstraat 10",
    "sg:city":"Ridderkerk",
    "sg:orig_category":"Elektronische Bedrijfsinstallaties",
    "sg:phone":"+31 180 481 184",
    "sg:postcode":"2984 BB",
    "sg:province":"South Holland",
    "wof:name":"Zegers Bv",
    "wof:placetype":"venue"
},
  "geometry": {"coordinates":[4.616542,51.879021],"type":"Point"}
}