{
  "type": "Feature",
  "properties": {
    "addr:full":"Nieuwstr 6A Velp Gld Gelderland 6881 SL",
    "addr:housenumber":"6a",
    "addr:postcode":"6881 sl",
    "addr:street":"Nieuwstr;Gld Gelderland",
    "iso:country":"NL",
    "sg:address":"Nieuwstr 6A",
    "sg:city":"Velp Gld",
    "sg:orig_category":"Kantoor- En Interieurbeplanting",
    "sg:phone":"+31 26 361 1485",
    "sg:postcode":"6881 SL",
    "sg:province":"Gelderland",
    "wof:name":"Kooyker, J",
    "wof:placetype":"venue"
},
  "geometry": {"coordinates":[5.9726691246,51.9951248169],"type":"Point"}
}