{
  "type": "Feature",
  "properties": {
    "addr:full":"Couperusstraat 9 Zuidbroek Groningen 9636 DC",
    "addr:housenumber":"9",
    "addr:postcode":"9636",
    "addr:street":"Couperusstraat",
    "iso:country":"NL",
    "sg:address":"Couperusstraat 9",
    "sg:city":"Zuidbroek",
    "sg:orig_category":"Boekhouders",
    "sg:phone":"+31 598 451 900",
    "sg:postcode":"9636 DC",
    "sg:province":"Groningen",
    "wof:name":"Raad Zuidbroek",
    "wof:placetype":"venue"
},
  "geometry": {"coordinates":[6.860658,53.16024],"type":"Point"}
}