{
  "type": "Feature",
  "properties": {
    "iso:country":"NL",
    "sg:address":"Horst 1504",
    "sg:city":"Lelystad",
    "sg:orig_category":"Schilders",
    "sg:phone":"+31 320 224 647",
    "sg:postcode":"8225 LH",
    "sg:province":"Flevoland",
    "wof:name":"Damen Schilderwerken",
    "wof:placetype":"venue"
},
  "geometry": {"coordinates":[5.499856,52.50222],"type":"Point"}
}