{
  "type": "Feature",
  "properties": {
    "addr:full":"De Run 5601 Veldhoven Noord-Brabant 5504 DK",
    "addr:housenumber":"5601",
    "addr:postcode":"5504 dk",
    "addr:street":"De Run",
    "iso:country":"NL",
    "sg:address":"De Run 5601",
    "sg:city":"Veldhoven",
    "sg:orig_category":"Paramedische Behandelingen",
    "sg:phone":"+31 40 230 8408",
    "sg:postcode":"5504 DK",
    "sg:province":"Noord-Brabant",
    "wof:name":"Stichting Thuiszorg Kempenstreek",
    "wof:placetype":"venue"
},
  "geometry": {"coordinates":[5.407685,51.406216],"type":"Point"}
}