{
  "type": "Feature",
  "properties": {
    "addr:full":"Zutphensestrwg 17A Velp Gld Gelderland 6881 WN",
    "addr:housenumber":"17a",
    "addr:postcode":"6881 wn",
    "addr:street":"Zutphensestrwg;Gld Gelderland",
    "iso:country":"NL",
    "sg:address":"Zutphensestrwg 17A",
    "sg:city":"Velp Gld",
    "sg:orig_category":"Psychotherapeuten",
    "sg:phone":"+31 26 442 0789",
    "sg:postcode":"6881 WN",
    "sg:province":"Gelderland",
    "wof:name":"Dabrowski, H P",
    "wof:placetype":"venue"
},
  "geometry": {"coordinates":[5.983144,51.997562],"type":"Point"}
}