{
  "type": "Feature",
  "properties": {
    "addr:full":"Regent Smitsstr 36 St Michielsgestel Noord-Brabant 5272 BE",
    "addr:housenumber":"36",
    "addr:postcode":"5272",
    "addr:street":"St Michielsgestel",
    "iso:country":"NL",
    "sg:address":"Regent Smitsstr 36",
    "sg:city":"St Michielsgestel",
    "sg:orig_category":"Adviesbureaus Bouwkunde",
    "sg:phone":"+31 73 551 7371",
    "sg:postcode":"5272 BE",
    "sg:province":"Noord-Brabant",
    "wof:name":"Wens",
    "wof:placetype":"venue"
},
  "geometry": {"coordinates":[5.360136,51.638706],"type":"Point"}
}