{
  "type": "Feature",
  "properties": {
    "addr:full":"Ryksstrwg 159A Leersum Utrecht 3956 CL",
    "addr:housenumber":"159a",
    "addr:postcode":"3956",
    "addr:street":"Leersum",
    "iso:country":"NL",
    "sg:address":"Ryksstrwg 159A",
    "sg:city":"Leersum",
    "sg:orig_category":"Verzekeringen - Verzekeringskantoren",
    "sg:phone":"+31 343 454 714",
    "sg:postcode":"3956 CL",
    "sg:province":"Utrecht",
    "wof:name":"Deur Assuranti\u00ebn",
    "wof:placetype":"venue"
},
  "geometry": {"coordinates":[5.43237,52.010792],"type":"Point"}
}