{
  "type": "Feature",
  "properties": {
    "addr:full":"Burg Falkenawg 25 Heerenveen Friesland 8442 KX",
    "addr:housenumber":"25",
    "addr:postcode":"8442 kx",
    "addr:street":"Burg",
    "iso:country":"NL",
    "sg:address":"Burg Falkenawg 25",
    "sg:city":"Heerenveen",
    "sg:orig_category":"Verzekeringen - Verzekeringskantoren",
    "sg:phone":"+31 513 628 989",
    "sg:postcode":"8442 KX",
    "sg:province":"Friesland",
    "wof:name":"Bilijam Assuranti\u00ebn",
    "wof:placetype":"venue"
},
  "geometry": {"coordinates":[5.928118,52.956169],"type":"Point"}
}