{
  "type": "Feature",
  "properties": {
    "addr:full":"Oranjeln 2 Waddinxveen South Holland 2741 ER",
    "addr:housenumber":"2",
    "addr:postcode":"2741 er",
    "addr:street":"Oranjeln",
    "iso:country":"NL",
    "sg:address":"Oranjeln 2",
    "sg:city":"Waddinxveen",
    "sg:orig_category":"Autorijscholen",
    "sg:phone":"+31 182 640 442",
    "sg:postcode":"2741 ER",
    "sg:province":"South Holland",
    "wof:name":"Tricom Bv",
    "wof:placetype":"venue"
},
  "geometry": {"coordinates":[4.658575,52.045715],"type":"Point"}
}