{
  "type": "Feature",
  "properties": {
    "addr:full":"Wittebrem 22 Rotterdam Zuid-Holland 3068 TM",
    "addr:housenumber":"22",
    "addr:postcode":"3068 tm",
    "addr:street":"Wittebrem",
    "iso:country":"NL",
    "sg:address":"Wittebrem 22",
    "sg:city":"Rotterdam",
    "sg:orig_category":"Webdesign Bureaus",
    "sg:phone":"+31 10 456 3546",
    "sg:postcode":"3068 TM",
    "sg:province":"Zuid-Holland",
    "wof:name":"Slash Design",
    "wof:placetype":"venue"
},
  "geometry": {"coordinates":[4.5574297905,51.9621124268],"type":"Point"}
}