{
  "type": "Feature",
  "properties": {
    "addr:full":"Postbus 16415 Amsterdam Limburg 1001 RM",
    "addr:housenumber":"16415",
    "addr:postcode":"1001 rm",
    "addr:street":"Postbus",
    "iso:country":"NL",
    "sg:address":"Postbus 16415",
    "sg:city":"Amsterdam",
    "sg:orig_category":"Evenementenverzorging",
    "sg:phone":"+31 20 639 0064",
    "sg:postcode":"1001 RM",
    "sg:province":"Limburg",
    "wof:name":"Amstel, Aan De",
    "wof:placetype":"venue"
},
  "geometry": {"coordinates":[4.89319,52.373119],"type":"Point"}
}