{
  "type": "Feature",
  "properties": {
    "addr:full":"Voorstr 41-43 Zwolle Overijssel 8011 MK",
    "addr:housenumber":"41-43",
    "addr:postcode":"8011",
    "iso:country":"NL",
    "sg:address":"Voorstr 41-43",
    "sg:city":"Zwolle",
    "sg:orig_category":"Antiquiteiten",
    "sg:phone":"+31 38 421 8572",
    "sg:postcode":"8011 MK",
    "sg:province":"Overijssel",
    "wof:name":"Anno 1666",
    "wof:placetype":"venue"
},
  "geometry": {"coordinates":[6.088738,52.512566],"type":"Point"}
}