{
  "type": "Feature",
  "properties": {
    "addr:full":"Korvelsewg 108C Tilburg North Brabant 5025 JK",
    "addr:housenumber":"108c",
    "addr:postcode":"5025 jk",
    "addr:street":"Korvelsewg",
    "iso:country":"NL",
    "sg:address":"Korvelsewg 108C",
    "sg:city":"Tilburg",
    "sg:orig_category":"Herenkleding",
    "sg:phone":"+31 315 448 180",
    "sg:postcode":"5025 JK",
    "sg:province":"North Brabant",
    "wof:name":"Duka",
    "wof:placetype":"venue"
},
  "geometry": {"coordinates":[5.075383,51.551193],"type":"Point"}
}