{
  "type": "Feature",
  "properties": {
    "iso:country":"NL",
    "sg:address":"Korvelsewg 108C",
    "sg:city":"Tilburg",
    "sg:orig_category":"Herenkleding",
    "sg:phone":"+31 315 448 180",
    "sg:postcode":"5025 JK",
    "sg:province":"North Brabant",
    "wof:name":"Duka",
    "wof:placetype":"venue"
},
  "geometry": {"coordinates":[5.075383,51.551193],"type":"Point"}
}