{
  "type": "Feature",
  "properties": {
    "addr:full":"Bekenlaan 66 Woerden Utrecht 3448 XD",
    "addr:housenumber":"66",
    "addr:postcode":"3448 xd",
    "addr:street":"Bekenlaan",
    "iso:country":"NL",
    "sg:address":"Bekenlaan 66",
    "sg:city":"Woerden",
    "sg:orig_category":"Bedrijfs- And Managementsconsultants",
    "sg:phone":"+31 348 425 604",
    "sg:postcode":"3448 XD",
    "sg:province":"Utrecht",
    "wof:name":"Bmp Blom Managementadvies & Projectuitvo",
    "wof:placetype":"venue"
},
  "geometry": {"coordinates":[4.869444,52.074581],"type":"Point"}
}