{
  "type": "Feature",
  "properties": {
    "addr:full":"Nissewg 4 Kruiningen Zeeland 4416 PK",
    "addr:housenumber":"4",
    "addr:postcode":"4416 pk",
    "addr:street":"Nissewg",
    "iso:country":"NL",
    "sg:address":"Nissewg 4",
    "sg:city":"Kruiningen",
    "sg:orig_category":"Koel- En Vrieshuizen",
    "sg:phone":"+31 113 382 000",
    "sg:postcode":"4416 PK",
    "sg:province":"Zeeland",
    "wof:name":"Zoomweg Zeeland Bv",
    "wof:placetype":"venue"
},
  "geometry": {"coordinates":[4.034001,51.459061],"type":"Point"}
}