{
  "type": "Feature",
  "properties": {
    "addr:full":"Grasryk 9 Amsterdam Noord-Holland 1068 BS",
    "addr:housenumber":"9",
    "addr:postcode":"1068 bs",
    "addr:street":"Grasryk",
    "iso:country":"NL",
    "sg:address":"Grasryk 9",
    "sg:city":"Amsterdam",
    "sg:orig_category":"Voetbalverenigingen",
    "sg:phone":"+31 20 610 1567",
    "sg:postcode":"1068 BS",
    "sg:province":"Noord-Holland",
    "wof:name":"Apgs",
    "wof:placetype":"venue"
},
  "geometry": {"coordinates":[4.80813,52.35844],"type":"Point"}
}