{
  "type": "Feature",
  "properties": {
    "iso:country":"NL",
    "sg:address":"Rudolf Dieselweg 3",
    "sg:city":"Venlo",
    "sg:orig_category":"Papieren Kantoorbenodigdheden Fab",
    "sg:phone":"+31 77 382 9191",
    "sg:postcode":"5928 RA",
    "sg:province":"Limburg",
    "wof:name":"High Speed Envelope Bv",
    "wof:placetype":"venue"
},
  "geometry": {"coordinates":[6.161549,51.378075],"type":"Point"}
}