{
  "type": "Feature",
  "properties": {
    "addr:full":"Holevoetplein 284 Scherpenzeel Gld Utrecht 3925 CA",
    "addr:housenumber":"284",
    "addr:postcode":"3925 ca",
    "addr:street":"Holevoetplein;Gld",
    "iso:country":"NL",
    "sg:address":"Holevoetplein 284",
    "sg:city":"Scherpenzeel Gld",
    "sg:orig_category":"Huishoudapparatuur, Televisies And Radio'S",
    "sg:phone":"+31 33 277 8648",
    "sg:postcode":"3925 CA",
    "sg:province":"Utrecht",
    "wof:name":"Van Den Brink Witgoed Vof",
    "wof:placetype":"venue"
},
  "geometry": {"coordinates":[5.481423,52.078918],"type":"Point"}
}