{
  "type": "Feature",
  "properties": {
    "addr:full":"Kievit 5 Zuid-Scharwoude Noord-Holland 1722 HE",
    "addr:housenumber":"5",
    "addr:postcode":"1722 he",
    "addr:street":"Kievit",
    "iso:country":"NL",
    "sg:address":"Kievit 5",
    "sg:city":"Zuid-Scharwoude",
    "sg:orig_category":"Boekhouders",
    "sg:phone":"+31 226 341 829",
    "sg:postcode":"1722 HE",
    "sg:province":"Noord-Holland",
    "wof:name":"J.P. Hoedjes",
    "wof:placetype":"venue"
},
  "geometry": {"coordinates":[4.814591,52.688251],"type":"Point"}
}