{
  "type": "Feature",
  "properties": {
    "addr:full":"Rosmolenstraat 15 Sittard Limburg 6131 HW",
    "addr:housenumber":"15",
    "addr:postcode":"6131 hw",
    "addr:street":"Rosmolenstraat",
    "iso:country":"NL",
    "sg:address":"Rosmolenstraat 15",
    "sg:city":"Sittard",
    "sg:orig_category":"Werving And Selectie Van Tijdelijk Personeel And Uitzendkantoren",
    "sg:phone":"+31 46 451 9988",
    "sg:postcode":"6131 HW",
    "sg:province":"Limburg",
    "wof:name":"Randstad",
    "wof:placetype":"venue"
},
  "geometry": {"coordinates":[5.8692641258,50.9966697693],"type":"Point"}
}