{
  "type": "Feature",
  "properties": {
    "addr:full":"Irenestraat 4 Elst Ut Utrecht 3921 BJ",
    "addr:housenumber":"4",
    "addr:postcode":"ut;3921 bj",
    "addr:street":"Irenestraat",
    "iso:country":"NL",
    "sg:address":"Irenestraat 4",
    "sg:city":"Elst Ut",
    "sg:orig_category":"Goederenvervoer Over De Weg",
    "sg:phone":"+31 318 471 478",
    "sg:postcode":"3921 BJ",
    "sg:province":"Utrecht",
    "wof:name":"Fa. Transportbedrijf Gebr. Van Erven",
    "wof:placetype":"venue"
},
  "geometry": {"coordinates":[5.50231,51.985077],"type":"Point"}
}