{
  "type": "Feature",
  "properties": {
    "addr:full":"Haalmansweg 2 Lochem Gelderland 7241 CP",
    "addr:housenumber":"2",
    "addr:postcode":"7241 cp",
    "addr:street":"Haalmansweg;Gelderland",
    "iso:country":"NL",
    "sg:address":"Haalmansweg 2",
    "sg:city":"Lochem",
    "sg:orig_category":"Farmaceutische Producten Gh",
    "sg:phone":"+31 573 258 808",
    "sg:postcode":"7241 CP",
    "sg:province":"Gelderland",
    "wof:name":"Wellform Bv",
    "wof:placetype":"venue"
},
  "geometry": {"coordinates":[6.408813,52.16404],"type":"Point"}
}