{
  "type": "Feature",
  "properties": {
    "addr:full":"Bosdrift 98A Hilversum Noord-Holland 1215 AN",
    "addr:housenumber":"98a",
    "addr:postcode":"1215 an",
    "addr:street":"Bosdrift",
    "iso:country":"NL",
    "sg:address":"Bosdrift 98A",
    "sg:city":"Hilversum",
    "sg:orig_category":"Omroep",
    "sg:phone":"+31 35 698 2773",
    "sg:postcode":"1215 AN",
    "sg:province":"Noord-Holland",
    "sg:website":"http://www.radio192.nl",
    "wof:name":"Radio I92/Gooiland Bv",
    "wof:placetype":"venue"
},
  "geometry": {"coordinates":[5.1695,52.228565],"type":"Point"}
}