{
  "type": "Feature",
  "properties": {
    "iso:country":"NL",
    "sg:address":"Kerkstr 22",
    "sg:city":"Loon Op Zand",
    "sg:classifiers":[
        {
            "category":"Food & Beverages",
            "subcategory":"Bakery",
            "type":"Retail Goods"
        }
    ],
    "sg:phone":"+31 416 363 119",
    "sg:postcode":"5175 BB",
    "sg:province":"Noord-Brabant",
    "sg:tags":[
        "pizza"
    ],
    "wof:name":"Aspendos",
    "wof:placetype":"venue"
},
  "geometry": {"coordinates":[5.076348,51.627399],"type":"Point"}
}