{
  "type": "Feature",
  "properties": {
    "addr:full":"Wielewaalln 16 Leiderdorp Zuid-Holland 2352 EW",
    "addr:housenumber":"16",
    "addr:postcode":"2352 ew",
    "addr:street":"Wielewaalln",
    "iso:country":"NL",
    "sg:address":"Wielewaalln 16",
    "sg:city":"Leiderdorp",
    "sg:orig_category":"Voegwerken",
    "sg:phone":"+31 71 589 6387",
    "sg:postcode":"2352 EW",
    "sg:province":"Zuid-Holland",
    "sg:website":"http://www.hannaart-breidenbach.nl",
    "wof:name":"Hannaart & Breidenbach",
    "wof:placetype":"venue"
},
  "geometry": {"coordinates":[4.534218,52.156174],"type":"Point"}
}