{
  "type": "Feature",
  "properties": {
    "addr:full":"Van Eedenlaan 27 Roosendaal North Brabant 4707 LA",
    "addr:housenumber":"27",
    "addr:postcode":"4707 la",
    "addr:street":"Van Eedenlaan",
    "iso:country":"NL",
    "sg:address":"Van Eedenlaan 27",
    "sg:city":"Roosendaal",
    "sg:orig_category":"Kantoor- And Schoolbenodigdheden Gh",
    "sg:phone":"+31 165 537 399",
    "sg:postcode":"4707 LA",
    "sg:province":"North Brabant",
    "wof:name":"Speciaal Drukwerk Janssen",
    "wof:placetype":"venue"
},
  "geometry": {"coordinates":[4.4594831467,51.5128440857],"type":"Point"}
}