{
  "type": "Feature",
  "properties": {
    "iso:country":"NL",
    "sg:address":"Brinkstraat 33",
    "sg:city":"Denekamp",
    "sg:orig_category":"Visspeciaalzaken",
    "sg:phone":"+31 541 353 393",
    "sg:postcode":"7591 DM",
    "sg:province":"Overijssel",
    "wof:name":"Vishandel 'T Graotke",
    "wof:placetype":"venue"
},
  "geometry": {"coordinates":[7.004165,52.376942],"type":"Point"}
}