{
  "type": "Feature",
  "properties": {
    "addr:full":"Rozengr 22 Amsterdam North Holland 1016 NC",
    "addr:housenumber":"22",
    "addr:postcode":"1016 nc",
    "addr:street":"Rozengr",
    "iso:country":"NL",
    "sg:address":"Rozengr 22",
    "sg:city":"Amsterdam",
    "sg:classifiers":[
        {
            "category":"Food & Beverages",
            "subcategory":"Fruits & Vegetables",
            "type":"Retail Goods"
        }
    ],
    "sg:phone":"+31 20 626 5981",
    "sg:postcode":"1016 NC",
    "sg:province":"North Holland",
    "sg:tags":[
        "en",
        "groenten"
    ],
    "wof:name":"Ensink",
    "wof:placetype":"venue"
},
  "geometry": {"coordinates":[4.882009,52.373856],"type":"Point"}
}