{
  "type": "Feature",
  "properties": {
    "addr:full":"Visserstraat 50 Aalsmeer Noord-Holland 1431 GJ",
    "addr:housenumber":"50",
    "addr:postcode":"1431 gj",
    "addr:street":"Visserstraat",
    "iso:country":"NL",
    "sg:address":"Visserstraat 50",
    "sg:city":"Aalsmeer",
    "sg:orig_category":"Technische Studies And Onderzoek",
    "sg:phone":"+31 297 320 651",
    "sg:postcode":"1431 GJ",
    "sg:province":"Noord-Holland",
    "wof:name":"M + P Raadgevende Ingenieurs Bv",
    "wof:placetype":"venue"
},
  "geometry": {"coordinates":[4.773787,52.25769],"type":"Point"}
}