{
  "type": "Feature",
  "properties": {
    "addr:full":"Tweede Vooruitgangstraat 12 Haarlem North Holland 2032 NJ",
    "addr:housenumber":"12",
    "addr:postcode":"2032 nj",
    "addr:street":"Tweede Vooruitgangstraat",
    "iso:country":"NL",
    "sg:address":"Tweede Vooruitgangstraat 12",
    "sg:city":"Haarlem",
    "sg:orig_category":"Loodgieterswerk, Verwarming And Sanitaire Installaties",
    "sg:phone":"+31 23 536 0069",
    "sg:postcode":"2032 NJ",
    "sg:province":"North Holland",
    "wof:name":"J.W. Hansma",
    "wof:placetype":"venue"
},
  "geometry": {"coordinates":[4.649398,52.379768],"type":"Point"}
}