{
  "type": "Feature",
  "properties": {
    "addr:full":"Bokkerijder 12 Bergeyk North Brabant 5571 MX",
    "addr:housenumber":"12",
    "addr:postcode":"5571 mx",
    "addr:street":"Bokkerijder",
    "iso:country":"NL",
    "sg:address":"Bokkerijder 12",
    "sg:city":"Bergeyk",
    "sg:orig_category":"Verhuisdiensten",
    "sg:phone":"+31 497 575 484",
    "sg:postcode":"5571 MX",
    "sg:province":"North Brabant",
    "wof:name":"Bots Ras Verhuis En Transportbedrijf",
    "wof:placetype":"venue"
},
  "geometry": {"coordinates":[5.337321,51.319012],"type":"Point"}
}