{
  "type": "Feature",
  "properties": {
    "addr:full":"De Werf 27-29 S Gravenhage South Holland 2544 EH",
    "addr:housenumber":"27-29",
    "addr:postcode":"2544 eh",
    "addr:street":"De Werf;S Gravenhage",
    "iso:country":"NL",
    "sg:address":"De Werf 27-29",
    "sg:city":"S Gravenhage",
    "sg:orig_category":"Projectinrichting",
    "sg:phone":"+31 70 329 6323",
    "sg:postcode":"2544 EH",
    "sg:province":"South Holland",
    "wof:name":"Aviso Bv",
    "wof:placetype":"venue"
},
  "geometry": {"coordinates":[4.25157,52.039551],"type":"Point"}
}