{
  "type": "Feature",
  "properties": {
    "iso:country":"NL",
    "sg:address":"Hasselterdk 35-1",
    "sg:city":"Zwolle",
    "sg:orig_category":"Oud Metaal",
    "sg:phone":"+31 38 422 5416",
    "sg:postcode":"8043 PD",
    "sg:province":"NL.08",
    "wof:name":"Wolters",
    "wof:placetype":"venue"
},
  "geometry": {"coordinates":[6.0692739487,52.5228691101],"type":"Point"}
}