{
  "type": "Feature",
  "properties": {
    "addr:full":"Lorentzstr 479 Zandvoort Noord-Holland 2041 RR",
    "addr:housenumber":"479",
    "addr:postcode":"2041 rr",
    "addr:street":"Zandvoort",
    "iso:country":"NL",
    "sg:address":"Lorentzstr 479",
    "sg:city":"Zandvoort",
    "sg:orig_category":"Onderhoudswerken",
    "sg:phone":"+31 6 53871394",
    "sg:postcode":"2041 RR",
    "sg:province":"Noord-Holland",
    "wof:name":"Dijkstra Onderhoudsbedrijf",
    "wof:placetype":"venue"
},
  "geometry": {"coordinates":[4.551919,52.380619],"type":"Point"}
}