{
  "type": "Feature",
  "properties": {
    "addr:full":"Ootmarsumseweg 35 Albergen NL.08 7665 RV",
    "addr:housenumber":"35;nl.08",
    "addr:postcode":"7665 rv",
    "addr:street":"Ootmarsumseweg",
    "iso:country":"NL",
    "sg:address":"Ootmarsumseweg 35",
    "sg:city":"Albergen",
    "sg:orig_category":"Autokeuringen",
    "sg:phone":"+31 546 441 345",
    "sg:postcode":"7665 RV",
    "sg:province":"NL.08",
    "wof:name":"Autohandel Theo Sonder",
    "wof:placetype":"venue"
},
  "geometry": {"coordinates":[6.734242,52.372524],"type":"Point"}
}