{
  "type": "Feature",
  "properties": {
    "iso:country":"NL",
    "sg:address":"Nadorstwg 8",
    "sg:city":"Middelburg",
    "sg:orig_category":"Beeldende Kunstenaars",
    "sg:phone":"+31 118 635 088",
    "sg:postcode":"4333 AM",
    "sg:province":"Zeeland",
    "wof:name":"Breel, Anne",
    "wof:placetype":"venue"
},
  "geometry": {"coordinates":[3.617114,51.508598],"type":"Point"}
}