{
  "type": "Feature",
  "properties": {
    "addr:full":"Nadorstwg 8 Middelburg Zeeland 4333 AM",
    "addr:housenumber":"8",
    "addr:postcode":"4333",
    "addr:street":"Nadorstwg",
    "iso:country":"NL",
    "sg:address":"Nadorstwg 8",
    "sg:city":"Middelburg",
    "sg:orig_category":"Beeldende Kunstenaars",
    "sg:phone":"+31 118 635 088",
    "sg:postcode":"4333 AM",
    "sg:province":"Zeeland",
    "wof:name":"Breel, Anne",
    "wof:placetype":"venue"
},
  "geometry": {"coordinates":[3.617114,51.508598],"type":"Point"}
}