{
  "type": "Feature",
  "properties": {
    "iso:country":"NL",
    "sg:address":"Palmenhage 34",
    "sg:city":"Stadskanaal",
    "sg:orig_category":"Makelaars In Onroerend Goed",
    "sg:phone":"+31 599 651 186",
    "sg:postcode":"9501 TT",
    "sg:province":"Groningen",
    "wof:name":"D. Kloen",
    "wof:placetype":"venue"
},
  "geometry": {"coordinates":[6.96448,52.984615],"type":"Point"}
}