{
  "type": "Feature",
  "properties": {
    "addr:full":"Plantagewg 70 Alblasserdam Zuid-Holland 2951 VH",
    "addr:housenumber":"70",
    "addr:postcode":"2951 vh",
    "addr:street":"Plantagewg",
    "iso:country":"NL",
    "sg:address":"Plantagewg 70",
    "sg:city":"Alblasserdam",
    "sg:orig_category":"Binnenhuisarchitectuur",
    "sg:phone":"+31 78 691 2471",
    "sg:postcode":"2951 VH",
    "sg:province":"Zuid-Holland",
    "wof:name":"Vlist, Van Der",
    "wof:placetype":"venue"
},
  "geometry": {"coordinates":[4.662483,51.864273],"type":"Point"}
}