{
  "type": "Feature",
  "properties": {
    "iso:country":"NL",
    "sg:address":"Werfwg 79",
    "sg:city":"Lelystad",
    "sg:orig_category":"Plafonds",
    "sg:phone":"+31 320 264 177",
    "sg:postcode":"8243 PG",
    "sg:province":"Flevoland",
    "wof:name":"Plafond Advies Bureau",
    "wof:placetype":"venue"
},
  "geometry": {"coordinates":[5.431554,52.496861],"type":"Point"}
}