{
  "type": "Feature",
  "properties": {
    "addr:full":"Steenstr 69 Boxmeer Noord-Brabant 5831 JC",
    "addr:housenumber":"69",
    "addr:postcode":"5831 jc",
    "addr:street":"Steenstr",
    "iso:country":"NL",
    "sg:address":"Steenstr 69",
    "sg:city":"Boxmeer",
    "sg:orig_category":"Huishoudelijke Apparaten En Artikelen",
    "sg:phone":"+31 485 576 650",
    "sg:postcode":"5831 JC",
    "sg:province":"Noord-Brabant",
    "wof:name":"Blokker",
    "wof:placetype":"venue"
},
  "geometry": {"coordinates":[5.950378,51.647758],"type":"Point"}
}