{
  "type": "Feature",
  "properties": {
    "addr:full":"Noordeind 5 Emmen Drenthe 7815 PA",
    "addr:housenumber":"5",
    "addr:postcode":"7815 pa",
    "addr:street":"Noordeind",
    "iso:country":"NL",
    "sg:address":"Noordeind 5",
    "sg:city":"Emmen",
    "sg:orig_category":"Advocaten En Advocatenkantoren",
    "sg:phone":"+31 591 610 880",
    "sg:postcode":"7815 PA",
    "sg:province":"Drenthe",
    "wof:name":"Buisman Advocaten",
    "wof:placetype":"venue"
},
  "geometry": {"coordinates":[6.890863,52.789261],"type":"Point"}
}