{
  "type": "Feature",
  "properties": {
    "addr:full":"Het Rond 8 Zoetermeer Zuid-Holland 2711 BW",
    "addr:housenumber":"8",
    "addr:postcode":"2711 bw",
    "addr:street":"Het Rond",
    "iso:country":"NL",
    "sg:address":"Het Rond 8",
    "sg:city":"Zoetermeer",
    "sg:orig_category":"Werving And Selectie Van Tijdelijk Personeel And Uitzendkantoren",
    "sg:phone":"+31 79 342 7769",
    "sg:postcode":"2711 BW",
    "sg:province":"Zuid-Holland",
    "wof:name":"Randstad Bv",
    "wof:placetype":"venue"
},
  "geometry": {"coordinates":[4.4895000458,52.0614547729],"type":"Point"}
}