{
  "type": "Feature",
  "properties": {
    "addr:full":"Buitentuin 88 Zaltbommel Gelderland 5301 WN",
    "addr:housenumber":"88",
    "addr:postcode":"5301 wn",
    "addr:street":"Buitentuin;Gelderland",
    "iso:country":"NL",
    "sg:address":"Buitentuin 88",
    "sg:city":"Zaltbommel",
    "sg:orig_category":"Adviesbureaus Bedrijfsorganisatie",
    "sg:phone":"+31 418 510 440",
    "sg:postcode":"5301 WN",
    "sg:province":"Gelderland",
    "wof:name":"Mossou",
    "wof:placetype":"venue"
},
  "geometry": {"coordinates":[5.236107,51.80619],"type":"Point"}
}