{
  "type": "Feature",
  "properties": {
    "addr:full":"Sloterkd 188Hs Amsterdam Noord-Holland 1059 EC",
    "addr:housenumber":"188hs",
    "addr:postcode":"1059 ec",
    "addr:street":"Sloterkd",
    "iso:country":"NL",
    "sg:address":"Sloterkd 188Hs",
    "sg:city":"Amsterdam",
    "sg:orig_category":"Vertalers",
    "sg:phone":"+31 20 670 3633",
    "sg:postcode":"1059 EC",
    "sg:province":"Noord-Holland",
    "wof:name":"Anglo Dutch Vertaalbureau",
    "wof:placetype":"venue"
},
  "geometry": {"coordinates":[4.84673,52.344818],"type":"Point"}
}