{
  "type": "Feature",
  "properties": {
    "addr:full":"Past V Beugenstr 50 Oisterwyk North Brabant 5061 CS",
    "addr:housenumber":"50",
    "addr:postcode":"5061 cs",
    "addr:street":"Past;Beugenstr",
    "iso:country":"NL",
    "sg:address":"Past V Beugenstr 50",
    "sg:city":"Oisterwyk",
    "sg:orig_category":"Woninginrichting",
    "sg:phone":"+31 13 528 4870",
    "sg:postcode":"5061 CS",
    "sg:province":"North Brabant",
    "wof:name":"Slaapcenter Oisterwijk",
    "wof:placetype":"venue"
},
  "geometry": {"coordinates":[5.1820998192,51.5765304565],"type":"Point"}
}