{
  "type": "Feature",
  "properties": {
    "addr:full":"Ekersdijk 83 Enschede Overijssel 7534 AZ",
    "addr:housenumber":"83",
    "addr:postcode":"7534 az",
    "addr:street":"Ekersdijk",
    "iso:country":"NL",
    "sg:address":"Ekersdijk 83",
    "sg:city":"Enschede",
    "sg:orig_category":"Verhuur Bouwmachines",
    "sg:phone":"+31 53 461 2918",
    "sg:postcode":"7534 AZ",
    "sg:province":"Overijssel",
    "wof:name":"Nijboer-Glanerbrug Machine- En Gereedsch",
    "wof:placetype":"venue"
},
  "geometry": {"coordinates":[6.94961,52.214581],"type":"Point"}
}