{
  "type": "Feature",
  "properties": {
    "iso:country":"NL",
    "sg:address":"Eglantierhof 1-3",
    "sg:city":"Leidschendam",
    "sg:orig_category":"Warenhuizen",
    "sg:phone":"+31 70 320 9210",
    "sg:postcode":"2262 AS",
    "sg:province":"Zuid-Holland",
    "wof:name":"V & D",
    "wof:placetype":"venue"
},
  "geometry": {"coordinates":[4.3848791122,52.0897979736],"type":"Point"}
}