{
  "type": "Feature",
  "properties": {
    "iso:country":"NL",
    "sg:address":"Wapenveldestraat 65",
    "sg:city":"'S Gravenhage",
    "sg:orig_category":"Loodgieterswerk, Verwarming And Sanitaire Installaties",
    "sg:phone":"+31 70 345 3771",
    "sg:postcode":"2573 BH",
    "sg:province":"Zuid-Holland",
    "wof:name":"Loodg Bedr W Th Vd Aa & Zn",
    "wof:placetype":"venue"
},
  "geometry": {"coordinates":[4.283739,52.062553],"type":"Point"}
}