{
  "type": "Feature",
  "properties": {
    "addr:full":"Meenthof 36 Kortenhoef Noord-Holland 1241 CZ",
    "addr:housenumber":"36",
    "addr:postcode":"1241",
    "addr:street":"Meenthof",
    "iso:country":"NL",
    "sg:address":"Meenthof 36",
    "sg:city":"Kortenhoef",
    "sg:orig_category":"Dierenspeciaalzaken",
    "sg:phone":"+31 35 656 9334",
    "sg:postcode":"1241 CZ",
    "sg:province":"Noord-Holland",
    "wof:name":"Dierenspeciaalzaak Dobey De Beeretuin",
    "wof:placetype":"venue"
},
  "geometry": {"coordinates":[5.112546,52.240231],"type":"Point"}
}