{
  "type": "Feature",
  "properties": {
    "addr:full":"Vlijtseweg 77 A Apeldoorn Gelderland 7317 AE",
    "addr:housenumber":"77 a",
    "addr:postcode":"7317 ae",
    "addr:street":"Vlijtseweg;Gelderland",
    "iso:country":"NL",
    "sg:address":"Vlijtseweg 77 A",
    "sg:city":"Apeldoorn",
    "sg:orig_category":"Diverse Consumentenartikelen Gh",
    "sg:phone":"+31 55 522 3944",
    "sg:postcode":"7317 AE",
    "sg:province":"Gelderland",
    "wof:name":"Rovac Kooien & Volieres",
    "wof:placetype":"venue"
},
  "geometry": {"coordinates":[5.970225,52.22113],"type":"Point"}
}