{
  "type": "Feature",
  "properties": {
    "addr:full":"Past Huybenpln 25 Panningen Limburg 5981 BH",
    "addr:housenumber":"25",
    "addr:postcode":"5981 bh",
    "iso:country":"NL",
    "sg:address":"Past Huybenpln 25",
    "sg:city":"Panningen",
    "sg:orig_category":"Kaas",
    "sg:phone":"+31 77 307 9270",
    "sg:postcode":"5981 BH",
    "sg:province":"Limburg",
    "wof:name":"Tebben Bv, J",
    "wof:placetype":"venue"
},
  "geometry": {"coordinates":[5.9792428017,51.3276634216],"type":"Point"}
}