{
  "type": "Feature",
  "properties": {
    "addr:full":"Bergwg 57 Veenendaal Utrecht 3904 HM",
    "addr:housenumber":"57",
    "addr:postcode":"3904 hm",
    "addr:street":"Bergwg",
    "iso:country":"NL",
    "sg:address":"Bergwg 57",
    "sg:city":"Veenendaal",
    "sg:orig_category":"Administratie- En Boekhoudkantoren",
    "sg:phone":"+31 318 550 162",
    "sg:postcode":"3904 HM",
    "sg:province":"Utrecht",
    "wof:name":"Jong, De",
    "wof:placetype":"venue"
},
  "geometry": {"coordinates":[5.539038,52.013371],"type":"Point"}
}