{
  "type": "Feature",
  "properties": {
    "addr:full":"Emmastraat 7 Wellerlooi Limburg 5856 CD",
    "addr:housenumber":"7",
    "addr:postcode":"5856 cd",
    "addr:street":"Emmastraat",
    "iso:country":"NL",
    "sg:address":"Emmastraat 7",
    "sg:city":"Wellerlooi",
    "sg:orig_category":"Bloemen- And Plantenteelt",
    "sg:phone":"+31 478 502 705",
    "sg:postcode":"5856 CD",
    "sg:province":"Limburg",
    "wof:name":"Vof Boom- En Roz.K./-Hand.Mij. Seuren-Ma",
    "wof:placetype":"venue"
},
  "geometry": {"coordinates":[6.16391,51.542946],"type":"Point"}
}