{
  "type": "Feature",
  "properties": {
    "addr:full":"Kerkstr 28 Wehe Den Hoorn Groningen 9964 AD",
    "addr:housenumber":"28",
    "addr:postcode":"9964 ad",
    "addr:street":"Kerkstr;Den Hoorn",
    "iso:country":"NL",
    "sg:address":"Kerkstr 28",
    "sg:city":"Wehe Den Hoorn",
    "sg:orig_category":"Oud Metaal",
    "sg:phone":"+31 595 571 359",
    "sg:postcode":"9964 AD",
    "sg:province":"Groningen",
    "wof:name":"Pol",
    "wof:placetype":"venue"
},
  "geometry": {"coordinates":[6.4163379669,53.3590049744],"type":"Point"}
}