{
  "type": "Feature",
  "properties": {
    "addr:full":"Koninginneduinweg 5 Bloemendaal Noord-Holland 2061 AM",
    "addr:housenumber":"5",
    "addr:postcode":"2061",
    "addr:street":"Koninginneduinweg",
    "iso:country":"NL",
    "sg:address":"Koninginneduinweg 5",
    "sg:city":"Bloemendaal",
    "sg:orig_category":"Film-, Tv- And Videoproductie",
    "sg:phone":"+31 23 526 0840",
    "sg:postcode":"2061 AM",
    "sg:province":"Noord-Holland",
    "wof:name":"Lalita Media",
    "wof:placetype":"venue"
},
  "geometry": {"coordinates":[4.606134,52.407917],"type":"Point"}
}