{
  "type": "Feature",
  "properties": {
    "iso:country":"NL",
    "sg:address":"Akkermolenwg 17",
    "sg:city":"Zundert",
    "sg:orig_category":"Sportverenigingen En Ontspannings- Verenigingen",
    "sg:phone":"+31 76 597 5332",
    "sg:postcode":"4881 BL",
    "sg:province":"Noord-Brabant",
    "wof:name":"Dja Atletiekver",
    "wof:placetype":"venue"
},
  "geometry": {"coordinates":[4.668467,51.479656],"type":"Point"}
}