{
  "type": "Feature",
  "properties": {
    "iso:country":"NL",
    "sg:address":"Jan Vermeerlaan 82",
    "sg:city":"Roosendaal",
    "sg:orig_category":"Metaalwerken",
    "sg:phone":"+31 165 554 417",
    "sg:postcode":"4703 LC",
    "sg:province":"Noord-Brabant",
    "wof:name":"Cj - Plafonds",
    "wof:placetype":"venue"
},
  "geometry": {"coordinates":[4.443038,51.540394],"type":"Point"}
}