{
  "type": "Feature",
  "properties": {
    "iso:country":"NL",
    "sg:address":"Mr Nelissenstr 26",
    "sg:city":"Beltrum",
    "sg:orig_category":"Kappers",
    "sg:phone":"+31 544 481 206",
    "sg:postcode":"7156 MD",
    "sg:province":"Gelderland",
    "wof:name":"Scharenborg",
    "wof:placetype":"venue"
},
  "geometry": {"coordinates":[6.563325,52.067696],"type":"Point"}
}