{
  "type": "Feature",
  "properties": {
    "addr:full":"Eikenln 247 Alphen Aan Den Ryn Zuid-Holland 2404 BP",
    "addr:housenumber":"247",
    "addr:postcode":"2404 bp",
    "addr:street":"Aan Den Ryn",
    "iso:country":"NL",
    "sg:address":"Eikenln 247",
    "sg:city":"Alphen Aan Den Ryn",
    "sg:orig_category":"Verzekeringen - Verzekeringskantoren",
    "sg:phone":"+31 172 472 991",
    "sg:postcode":"2404 BP",
    "sg:province":"Zuid-Holland",
    "wof:name":"Vdh",
    "wof:placetype":"venue"
},
  "geometry": {"coordinates":[4.658921,52.12719],"type":"Point"}
}