{
  "type": "Feature",
  "properties": {
    "iso:country":"NL",
    "sg:address":"Punterweg 41",
    "sg:city":"Maastricht",
    "sg:orig_category":"Kantoorapparatuur Gh",
    "sg:phone":"+31 43 352 5100",
    "sg:postcode":"6222 NW",
    "sg:province":"Limburg",
    "wof:name":"Aci Adam Bv",
    "wof:placetype":"venue"
},
  "geometry": {"coordinates":[5.7104592323,50.8758888245],"type":"Point"}
}