{
  "type": "Feature",
  "properties": {
    "addr:full":"Anna De Waalhoeve 13 Waddinxveen South Holland 2743 HT",
    "addr:housenumber":"13",
    "addr:postcode":"2743 ht",
    "addr:street":"Anna De Waalhoeve",
    "iso:country":"NL",
    "sg:address":"Anna De Waalhoeve 13",
    "sg:city":"Waddinxveen",
    "sg:orig_category":"Boekhouders",
    "sg:phone":"+31 182 614 818",
    "sg:postcode":"2743 HT",
    "sg:province":"South Holland",
    "wof:name":"R. Westmaas",
    "wof:placetype":"venue"
},
  "geometry": {"coordinates":[4.634005,52.036633],"type":"Point"}
}