{
  "type": "Feature",
  "properties": {
    "iso:country":"NL",
    "sg:address":"Paterswoldsewg 112B",
    "sg:city":"Groningen",
    "sg:orig_category":"Meubelmakerijen",
    "sg:phone":"+31 50 313 7359",
    "sg:postcode":"9727 BJ",
    "sg:province":"Groningen",
    "wof:name":"Tisa",
    "wof:placetype":"venue"
},
  "geometry": {"coordinates":[6.557557,53.208874],"type":"Point"}
}