{
  "type": "Feature",
  "properties": {
    "addr:full":"Sara Mansveltweg 15 Wolfheze Gelderland 6874 CB",
    "addr:housenumber":"15",
    "addr:postcode":"6874 cb",
    "addr:street":"Sara Mansveltweg;Gelderland",
    "iso:country":"NL",
    "sg:address":"Sara Mansveltweg 15",
    "sg:city":"Wolfheze",
    "sg:orig_category":"Fitnesscentra",
    "sg:phone":"+31 26 482 2716",
    "sg:postcode":"6874 CB",
    "sg:province":"Gelderland",
    "wof:name":"Sportschool In Beweging",
    "wof:placetype":"venue"
},
  "geometry": {"coordinates":[5.795166,52.006256],"type":"Point"}
}