{
  "type": "Feature",
  "properties": {
    "addr:full":"Munterstraat 32 Schiedam South Holland 3123 PN",
    "addr:housenumber":"32",
    "addr:postcode":"3123 pn",
    "addr:street":"Munterstraat",
    "iso:country":"NL",
    "sg:address":"Munterstraat 32",
    "sg:city":"Schiedam",
    "sg:orig_category":"Diverse Grafische Activiteiten",
    "sg:phone":"+31 10 470 9635",
    "sg:postcode":"3123 PN",
    "sg:province":"South Holland",
    "wof:name":"J.M.N. Emmerik",
    "wof:placetype":"venue"
},
  "geometry": {"coordinates":[4.362014,51.945053],"type":"Point"}
}