{
  "type": "Feature",
  "properties": {
    "addr:full":"Zwarteweg 1 Heerde Gelderland 8181 PD",
    "addr:housenumber":"1",
    "addr:postcode":"8181 pd",
    "addr:street":"Zwarteweg;Gelderland",
    "iso:country":"NL",
    "sg:address":"Zwarteweg 1",
    "sg:city":"Heerde",
    "sg:orig_category":"Huizensloop And Bouwrijp Maken",
    "sg:phone":"+31 578 692 064",
    "sg:postcode":"8181 PD",
    "sg:province":"Gelderland",
    "wof:name":"Lagemaat Sloopwerken Bv",
    "wof:placetype":"venue"
},
  "geometry": {"coordinates":[6.015168,52.374538],"type":"Point"}
}