{
  "type": "Feature",
  "properties": {
    "iso:country":"NL",
    "sg:address":"J T Cremerln 87",
    "sg:city":"Santpoort Noord",
    "sg:orig_category":"Vertaalbureaus",
    "sg:phone":"+31 23 549 2288",
    "sg:postcode":"2071 SM",
    "sg:province":"Noord-Holland",
    "wof:name":"More Traductions, Le",
    "wof:placetype":"venue"
},
  "geometry": {"coordinates":[-121.95871,39.780125],"type":"Point"}
}