{
  "type": "Feature",
  "properties": {
    "addr:full":"J T Cremerln 87 Santpoort Noord Noord-Holland 2071 SM",
    "addr:housenumber":"87",
    "addr:postcode":"2071 sm",
    "addr:street":"Santpoort",
    "iso:country":"NL",
    "sg:address":"J T Cremerln 87",
    "sg:city":"Santpoort Noord",
    "sg:orig_category":"Vertaalbureaus",
    "sg:phone":"+31 23 549 2288",
    "sg:postcode":"2071 SM",
    "sg:province":"Noord-Holland",
    "wof:name":"More Traductions, Le",
    "wof:placetype":"venue"
},
  "geometry": {"coordinates":[-121.95871,39.780125],"type":"Point"}
}