{
  "type": "Feature",
  "properties": {
    "addr:full":"Montalbaendreef 2 Utrecht Utrecht 3562 LC",
    "addr:housenumber":"2",
    "addr:postcode":"3562 lc",
    "addr:street":"Montalbaendreef",
    "iso:country":"NL",
    "sg:address":"Montalbaendreef 2",
    "sg:city":"Utrecht",
    "sg:orig_category":"Boekenuitgeverijen",
    "sg:phone":"+31 30 265 0630",
    "sg:postcode":"3562 LC",
    "sg:province":"Utrecht",
    "wof:name":"Boeknet Nederlandse Internetboekhandel",
    "wof:placetype":"venue"
},
  "geometry": {"coordinates":[5.111946,52.111443],"type":"Point"}
}