{
  "type": "Feature",
  "properties": {
    "iso:country":"NL",
    "sg:address":"Maarssenbroeksedk 11",
    "sg:city":"Utrecht",
    "sg:orig_category":"Airconditioning",
    "sg:phone":"+31 30 241 6850",
    "sg:postcode":"3542 DL",
    "sg:province":"Utrecht",
    "sg:website":"http://www.apac.nl",
    "wof:name":"Apac Groep",
    "wof:placetype":"venue"
},
  "geometry": {"coordinates":[5.043174,52.122631],"type":"Point"}
}