{
  "type": "Feature",
  "properties": {
    "addr:full":"Gemini 71 Lemmer Friesland 8531 NS",
    "addr:housenumber":"71",
    "addr:postcode":"8531 ns",
    "addr:street":"Gemini",
    "iso:country":"NL",
    "sg:address":"Gemini 71",
    "sg:city":"Lemmer",
    "sg:orig_category":"Koelkasten - Verhuur",
    "sg:phone":"+31 514 564 231",
    "sg:postcode":"8531 NS",
    "sg:province":"Friesland",
    "wof:name":"Famsmit",
    "wof:placetype":"venue"
},
  "geometry": {"coordinates":[5.698755,52.853729],"type":"Point"}
}