{
  "type": "Feature",
  "properties": {
    "addr:full":"West Breukelderweg 2 Bennekom Gelderland 6721 MR",
    "addr:housenumber":"2",
    "addr:postcode":"6721 mr",
    "addr:street":"West Breukelderweg;Gelderland",
    "iso:country":"NL",
    "sg:address":"West Breukelderweg 2",
    "sg:city":"Bennekom",
    "sg:orig_category":"Diverse Artikelen Fab",
    "sg:phone":"+31 318 413 032",
    "sg:postcode":"6721 MR",
    "sg:province":"Gelderland",
    "wof:name":"Polux",
    "wof:placetype":"venue"
},
  "geometry": {"coordinates":[5.672292,52.010689],"type":"Point"}
}