{
  "type": "Feature",
  "properties": {
    "addr:full":"De Klip 37 Koedyk North Holland 1831 AL",
    "addr:housenumber":"37",
    "addr:postcode":"1831 al",
    "addr:street":"De Klip;North",
    "iso:country":"NL",
    "sg:address":"De Klip 37",
    "sg:city":"Koedyk",
    "sg:orig_category":"Parketvloeren",
    "sg:phone":"+31 72 561 5701",
    "sg:postcode":"1831 AL",
    "sg:province":"North Holland",
    "wof:name":"Tigro",
    "wof:placetype":"venue"
},
  "geometry": {"coordinates":[4.756096,52.671261],"type":"Point"}
}