{
  "type": "Feature",
  "properties": {
    "addr:full":"Klaverblad 49 Anna Paulowna Noord-Holland 1761 HB",
    "addr:housenumber":"49",
    "addr:postcode":"1761 hb",
    "addr:street":"Klaverblad",
    "iso:country":"NL",
    "sg:address":"Klaverblad 49",
    "sg:city":"Anna Paulowna",
    "sg:orig_category":"Waterbehandeling En Waterzuiverings- Systemen",
    "sg:phone":"+31 223 533 248",
    "sg:postcode":"1761 HB",
    "sg:province":"Noord-Holland",
    "sg:website":"http://www.plentistic.com",
    "wof:name":"Plentistic Holland Bv",
    "wof:placetype":"venue"
},
  "geometry": {"coordinates":[4.8207249641,52.8651771545],"type":"Point"}
}