{
  "type": "Feature",
  "properties": {
    "addr:full":"Sluissestr 11 Maasbommel North Brabant 6627 KR",
    "addr:housenumber":"11",
    "addr:postcode":"6627 kr",
    "addr:street":"Sluissestr",
    "iso:country":"NL",
    "sg:address":"Sluissestr 11",
    "sg:city":"Maasbommel",
    "sg:orig_category":"Loonbedrijven",
    "sg:phone":"+31 487 542 757",
    "sg:postcode":"6627 KR",
    "sg:province":"North Brabant",
    "wof:name":"Hermans, C G M",
    "wof:placetype":"venue"
},
  "geometry": {"coordinates":[5.534482,51.820831],"type":"Point"}
}