{
  "type": "Feature",
  "properties": {
    "iso:country":"NL",
    "sg:address":"Raadhuisln 26",
    "sg:city":"Rockanje",
    "sg:orig_category":"Kappers",
    "sg:phone":"+31 181 401 951",
    "sg:postcode":"3235 AP",
    "sg:province":"Zuid-Holland",
    "wof:name":"Klok",
    "wof:placetype":"venue"
},
  "geometry": {"coordinates":[4.070745,51.870178],"type":"Point"}
}