{
  "type": "Feature",
  "properties": {
    "iso:country":"NL",
    "sg:address":"Weteringkade 67",
    "sg:city":"'S Gravenhage",
    "sg:orig_category":"Verzekeringen",
    "sg:phone":"+31 70 385 6703",
    "sg:postcode":"2515 AL",
    "sg:province":"Zuid-Holland",
    "wof:name":"Assurantiekantoor G. Bakker Bv",
    "wof:placetype":"venue"
},
  "geometry": {"coordinates":[4.32715,52.07394],"type":"Point"}
}