{
  "type": "Feature",
  "properties": {
    "addr:full":"Postbus 8 Wyk Aan Zee Noord-Holland 1949 ZG",
    "addr:housenumber":"8",
    "addr:postcode":"zee;1949 zg",
    "addr:street":"Postbus",
    "iso:country":"NL",
    "sg:address":"Postbus 8",
    "sg:city":"Wyk Aan Zee",
    "sg:orig_category":"Bodemsanering",
    "sg:phone":"+31 23 549 1600",
    "sg:postcode":"1949 ZG",
    "sg:province":"Noord-Holland",
    "wof:name":"Someren, Van",
    "wof:placetype":"venue"
},
  "geometry": {"coordinates":[4.59469,52.491989],"type":"Point"}
}