{
  "type": "Feature",
  "properties": {
    "addr:full":"Motorstr 9 Rotterdam Zuid-Holland 3083 AP",
    "addr:housenumber":"9",
    "addr:postcode":"3083 ap",
    "addr:street":"Motorstr",
    "iso:country":"NL",
    "sg:address":"Motorstr 9",
    "sg:city":"Rotterdam",
    "sg:orig_category":"Orthopedische Artikelen",
    "sg:phone":"+31 10 493 3200",
    "sg:postcode":"3083 AP",
    "sg:province":"Zuid-Holland",
    "sg:website":"http://www.livit.nl",
    "wof:name":"Livit",
    "wof:placetype":"venue"
},
  "geometry": {"coordinates":[4.4947209358,51.8879089355],"type":"Point"}
}