{
  "type": "Feature",
  "properties": {
    "addr:full":"Emmastraat 33 Sneek Provincie Friesland 8601 GK",
    "addr:housenumber":"33",
    "addr:postcode":"8601 gk",
    "addr:street":"Emmastraat;Provincie Friesland",
    "iso:country":"NL",
    "sg:address":"Emmastraat 33",
    "sg:city":"Sneek",
    "sg:orig_category":"Muziekinstrumenten",
    "sg:phone":"+31 515 421 409",
    "sg:postcode":"8601 GK",
    "sg:province":"Provincie Friesland",
    "wof:name":"Pianotechniek Van Dieren",
    "wof:placetype":"venue"
},
  "geometry": {"coordinates":[5.65477,53.032703],"type":"Point"}
}