{
  "type": "Feature",
  "properties": {
    "addr:full":"Rijksstraatweg 126 Haarlem Noord-Holland 2022 DE",
    "addr:housenumber":"126",
    "addr:postcode":"2022 de",
    "addr:street":"Rijksstraatweg",
    "iso:country":"NL",
    "sg:address":"Rijksstraatweg 126",
    "sg:city":"Haarlem",
    "sg:orig_category":"Huishoudapparatuur, Televisies And Radio'S",
    "sg:phone":"+31 23 538 0420",
    "sg:postcode":"2022 DE",
    "sg:province":"Noord-Holland",
    "wof:name":"Radiotv Knol Vof",
    "wof:placetype":"venue"
},
  "geometry": {"coordinates":[4.648582,52.404747],"type":"Point"}
}