{
  "type": "Feature",
  "properties": {
    "addr:full":"Tulpenstraat 8 Rijnsburg South Holland 2231 GW",
    "addr:housenumber":"8",
    "addr:postcode":"2231 gw",
    "addr:street":"Tulpenstraat",
    "iso:country":"NL",
    "sg:address":"Tulpenstraat 8",
    "sg:city":"Rijnsburg",
    "sg:orig_category":"Kappers",
    "sg:phone":"+31 71 402 0762",
    "sg:postcode":"2231 GW",
    "sg:province":"South Holland",
    "wof:name":"Paul Vierling Haarcreaties",
    "wof:placetype":"venue"
},
  "geometry": {"coordinates":[4.443004,52.192493],"type":"Point"}
}