{
  "type": "Feature",
  "properties": {
    "addr:full":"Snoekenveen 1011 Spijkenisse Noord-Holland 3205 CL",
    "addr:housenumber":"1011",
    "addr:postcode":"3205",
    "addr:street":"Snoekenveen",
    "iso:country":"NL",
    "sg:address":"Snoekenveen 1011",
    "sg:city":"Spijkenisse",
    "sg:orig_category":"Paramedische Behandelingen",
    "sg:phone":"+31 181 640 919",
    "sg:postcode":"3205 CL",
    "sg:province":"Noord-Holland",
    "wof:name":"Verloskundige N C Schaasberg",
    "wof:placetype":"venue"
},
  "geometry": {"coordinates":[4.349378,51.834068],"type":"Point"}
}