{
  "type": "Feature",
  "properties": {
    "addr:full":"Bliek 155 Ridderkerk South Holland 2986 SG",
    "addr:housenumber":"155",
    "addr:postcode":"2986 sg",
    "addr:street":"Bliek",
    "iso:country":"NL",
    "sg:address":"Bliek 155",
    "sg:city":"Ridderkerk",
    "sg:classifiers":[
        {
            "category":"Recreation",
            "subcategory":"Dog Park",
            "type":"Entertainment"
        }
    ],
    "sg:phone":"+31 6 53530630",
    "sg:postcode":"2986 SG",
    "sg:province":"South Holland",
    "sg:tags":[
        "chauffeur",
        "met",
        "autoverhuur"
    ],
    "sg:website":"http://www.limodrive.nl",
    "wof:name":"Limodrive Nl",
    "wof:placetype":"venue"
},
  "geometry": {"coordinates":[4.625399,51.863731],"type":"Point"}
}