{
  "type": "Feature",
  "properties": {
    "iso:country":"NL",
    "sg:address":"Vogelzangstg 9",
    "sg:city":"Noordlaren",
    "sg:orig_category":"Facilitaire Dienstverlening",
    "sg:phone":"+31 50 403 1985",
    "sg:postcode":"9479 TE",
    "sg:province":"Groningen",
    "sg:website":"http://www.nonagon.nl",
    "wof:name":"Nonagon",
    "wof:placetype":"venue"
},
  "geometry": {"coordinates":[6.65268,53.132622],"type":"Point"}
}