{
  "type": "Feature",
  "properties": {
    "addr:full":"Hoofdstr 151A Epe Gelderland 8162 AE",
    "addr:housenumber":"151a",
    "addr:postcode":"8162 ae",
    "addr:street":"Gelderland",
    "iso:country":"NL",
    "sg:address":"Hoofdstr 151A",
    "sg:city":"Epe",
    "sg:orig_category":"Schoonheidsinstituten",
    "sg:phone":"+31 578 570 474",
    "sg:postcode":"8162 AE",
    "sg:province":"Gelderland",
    "wof:name":"Face, Schoonheidssalon",
    "wof:placetype":"venue"
},
  "geometry": {"coordinates":[5.983192,52.342758],"type":"Point"}
}