{
  "type": "Feature",
  "properties": {
    "iso:country":"NL",
    "sg:address":"Langeland 34",
    "sg:city":"S Gravenhage",
    "sg:orig_category":"Kappers",
    "sg:phone":"+31 70 364 5458",
    "sg:postcode":"2548 WE",
    "sg:province":"South Holland",
    "wof:name":"Steen, Els Van Der",
    "wof:placetype":"venue"
},
  "geometry": {"coordinates":[4.2901,52.029888],"type":"Point"}
}