{
  "type": "Feature",
  "properties": {
    "addr:full":"Postweg 88 Lunteren Gelderland 6741 ML",
    "addr:housenumber":"88",
    "addr:postcode":"6741 ml",
    "addr:street":"Postweg;Gelderland",
    "iso:country":"NL",
    "sg:address":"Postweg 88",
    "sg:city":"Lunteren",
    "sg:orig_category":"Autokeuringen",
    "sg:phone":"+31 318 482 791",
    "sg:postcode":"6741 ML",
    "sg:province":"Gelderland",
    "wof:name":"G.J. Van Harn",
    "wof:placetype":"venue"
},
  "geometry": {"coordinates":[5.605289,52.086567],"type":"Point"}
}