{
  "type": "Feature",
  "properties": {
    "addr:full":"Mijnheerkensweg 29 Roermond Limburg 6041 TA",
    "addr:housenumber":"29",
    "addr:postcode":"6041 ta",
    "addr:street":"Mijnheerkensweg",
    "iso:country":"NL",
    "sg:address":"Mijnheerkensweg 29",
    "sg:city":"Roermond",
    "sg:orig_category":"Hout Gh",
    "sg:phone":"+31 475 464 444",
    "sg:postcode":"6041 TA",
    "sg:province":"Limburg",
    "wof:name":"Willamette Europe Ltd",
    "wof:placetype":"venue"
},
  "geometry": {"coordinates":[6.001274,51.204533],"type":"Point"}
}