{
  "type": "Feature",
  "properties": {
    "addr:full":"Vd Woertstr 27 S Gravenhage South Holland 2597 PJ",
    "addr:housenumber":"27",
    "addr:postcode":"2597 pj",
    "addr:street":"S Gravenhage",
    "iso:country":"NL",
    "sg:address":"Vd Woertstr 27",
    "sg:city":"S Gravenhage",
    "sg:orig_category":"Verenigingen En Stichtingen",
    "sg:phone":"+31 70 324 8743",
    "sg:postcode":"2597 PJ",
    "sg:province":"South Holland",
    "wof:name":"Ex Oriente Lux",
    "wof:placetype":"venue"
},
  "geometry": {"coordinates":[4.31817,52.11031],"type":"Point"}
}