{
  "type": "Feature",
  "properties": {
    "addr:full":"Hoekerwg 9 Zwolle Overijssel 8042 PH",
    "addr:housenumber":"9",
    "addr:postcode":"8042",
    "addr:street":"Hoekerwg",
    "iso:country":"NL",
    "sg:address":"Hoekerwg 9",
    "sg:city":"Zwolle",
    "sg:orig_category":"Autoverhuur",
    "sg:phone":"+31 38 421 8000",
    "sg:postcode":"8042 PH",
    "sg:province":"Overijssel",
    "sg:website":"http://www.kav.nl",
    "wof:name":"Kav",
    "wof:placetype":"venue"
},
  "geometry": {"coordinates":[6.052145,52.513493],"type":"Point"}
}