{
  "type": "Feature",
  "properties": {
    "addr:full":"Brouwerystr 14 Oostburg Zeeland 4501 CP",
    "addr:housenumber":"14",
    "addr:postcode":"4501 cp",
    "addr:street":"Brouwerystr",
    "iso:country":"NL",
    "sg:address":"Brouwerystr 14",
    "sg:city":"Oostburg",
    "sg:orig_category":"Fietsen En Bromfietsen",
    "sg:phone":"+31 117 452 440",
    "sg:postcode":"4501 CP",
    "sg:province":"Zeeland",
    "wof:name":"Jansen, A",
    "wof:placetype":"venue"
},
  "geometry": {"coordinates":[3.492293,51.328056],"type":"Point"}
}