{
  "type": "Feature",
  "properties": {
    "addr:full":"Arnhemsebovenwg 239 Driebergen Rysenb Utrecht 3971 MG",
    "addr:housenumber":"239",
    "addr:postcode":"3971 mg",
    "addr:street":"Driebergen Rysenb",
    "iso:country":"NL",
    "sg:address":"Arnhemsebovenwg 239",
    "sg:city":"Driebergen Rysenb",
    "sg:classifiers":[
        {
            "category":"Home & Garden",
            "subcategory":"Hardware",
            "type":"Retail Goods"
        }
    ],
    "sg:phone":"+31 343 516 399",
    "sg:postcode":"3971 MG",
    "sg:province":"Utrecht",
    "sg:tags":[
        "machine",
        "houtbewerking",
        "-"
    ],
    "wof:name":"Rhenen, Van",
    "wof:placetype":"venue"
},
  "geometry": {"coordinates":[5.296499,52.057014],"type":"Point"}
}