{
  "type": "Feature",
  "properties": {
    "addr:full":"De Kuiper 8 Heeze North Brabant 5591 MZ",
    "addr:housenumber":"8",
    "addr:postcode":"5591 mz",
    "addr:street":"De Kuiper",
    "iso:country":"NL",
    "sg:address":"De Kuiper 8",
    "sg:city":"Heeze",
    "sg:orig_category":"Beautyfarms And Sauna'S",
    "sg:phone":"+31 40 226 4606",
    "sg:postcode":"5591 MZ",
    "sg:province":"North Brabant",
    "wof:name":"Schoonheidssalon Nordy",
    "wof:placetype":"venue"
},
  "geometry": {"coordinates":[5.564447,51.38467],"type":"Point"}
}