{
  "type": "Feature",
  "properties": {
    "iso:country":"NL",
    "sg:address":"Oldenoord 81",
    "sg:city":"Rotterdam",
    "sg:classifiers":[
        {
            "category":"Education",
            "subcategory":"Preschool",
            "type":"Public Place"
        }
    ],
    "sg:phone":"+31 10 482 9188",
    "sg:postcode":"3079 KG",
    "sg:province":"Zuid-Holland",
    "sg:tags":[
        "kleuteronderwijs",
        "basis-"
    ],
    "wof:name":"Openbare Basisschool De Kubus",
    "wof:placetype":"venue"
},
  "geometry": {"coordinates":[4.557213,51.880089],"type":"Point"}
}