{
  "type": "Feature",
  "properties": {
    "addr:full":"De Pleatsen 5 Makkum Fr Friesland 8754 KE",
    "addr:housenumber":"5",
    "addr:postcode":"8754 ke",
    "addr:street":"De Pleatsen",
    "iso:country":"NL",
    "sg:address":"De Pleatsen 5",
    "sg:city":"Makkum Fr",
    "sg:orig_category":"Voeding, Dranken And Tabak Gh",
    "sg:phone":"+31 515 430 154",
    "sg:postcode":"8754 KE",
    "sg:province":"Friesland",
    "wof:name":"Selak Import - Export",
    "wof:placetype":"venue"
},
  "geometry": {"coordinates":[5.406712,53.063572],"type":"Point"}
}