{
  "type": "Feature",
  "properties": {
    "addr:full":"Karreveld 1A Koudekerke Zeeland 4371 GA",
    "addr:housenumber":"1a",
    "addr:postcode":"4371 ga",
    "addr:street":"Karreveld",
    "iso:country":"NL",
    "sg:address":"Karreveld 1A",
    "sg:city":"Koudekerke",
    "sg:orig_category":"Projectontwikkeling",
    "sg:phone":"+31 118 555 900",
    "sg:postcode":"4371 GA",
    "sg:province":"Zeeland",
    "wof:name":"Koningshof Bv",
    "wof:placetype":"venue"
},
  "geometry": {"coordinates":[3.556318,51.485332],"type":"Point"}
}