{
  "type": "Feature",
  "properties": {
    "addr:full":"Nassaupk 67 Lisse Zuid-Holland 2161 KL",
    "addr:housenumber":"67",
    "addr:postcode":"2161 kl",
    "addr:street":"Nassaupk",
    "iso:country":"NL",
    "sg:address":"Nassaupk 67",
    "sg:city":"Lisse",
    "sg:orig_category":"Schilders",
    "sg:phone":"+31 252 674 343",
    "sg:postcode":"2161 KL",
    "sg:province":"Zuid-Holland",
    "wof:name":"Beek, Van",
    "wof:placetype":"venue"
},
  "geometry": {"coordinates":[4.563436,52.261677],"type":"Point"}
}