{
  "type": "Feature",
  "properties": {
    "iso:country":"NL",
    "sg:address":"Weimarstraat 322",
    "sg:city":"'S Gravenhage",
    "sg:orig_category":"Kappers",
    "sg:phone":"+31 70 364 3876",
    "sg:postcode":"2562 HT",
    "sg:province":"South Holland",
    "wof:name":"Living Colors",
    "wof:placetype":"venue"
},
  "geometry": {"coordinates":[4.27701,52.073269],"type":"Point"}
}