{
  "type": "Feature",
  "properties": {
    "iso:country":"NL",
    "sg:address":"Zeeburgerpad 44A",
    "sg:city":"Amsterdam",
    "sg:orig_category":"Horecabenodigdheden",
    "sg:phone":"+31 20 693 4098",
    "sg:postcode":"1019 AA",
    "sg:province":"Noord-Holland",
    "wof:name":"Ca?Ro Agabi",
    "wof:placetype":"venue"
},
  "geometry": {"coordinates":[4.936631,52.367004],"type":"Point"}
}