{
  "type": "Feature",
  "properties": {
    "addr:full":"Jan Willem Frisostraat 64 Delft Zuid-Holland 2628 TS",
    "addr:housenumber":"64",
    "addr:postcode":"2628 ts",
    "addr:street":"Jan Willem Frisostraat",
    "iso:country":"NL",
    "sg:address":"Jan Willem Frisostraat 64",
    "sg:city":"Delft",
    "sg:orig_category":"Geluidsopnamen",
    "sg:phone":"+31 15 256 9852",
    "sg:postcode":"2628 TS",
    "sg:province":"Zuid-Holland",
    "wof:name":"Van Eekelen",
    "wof:placetype":"venue"
},
  "geometry": {"coordinates":[4.37672,52.007431],"type":"Point"}
}