{
  "type": "Feature",
  "properties": {
    "addr:full":"Scheelenstr 151 Simpelveld Limburg 6369 VW",
    "addr:housenumber":"151",
    "addr:postcode":"6369 vw",
    "iso:country":"NL",
    "sg:address":"Scheelenstr 151",
    "sg:city":"Simpelveld",
    "sg:orig_category":"Kappers",
    "sg:phone":"+31 6 21271817",
    "sg:postcode":"6369 VW",
    "sg:province":"Limburg",
    "wof:name":"Ellen",
    "wof:placetype":"venue"
},
  "geometry": {"coordinates":[5.9755158424,50.8336257935],"type":"Point"}
}