{
  "type": "Feature",
  "properties": {
    "iso:country":"NL",
    "sg:address":"Stadsring 63",
    "sg:city":"Amersfoort",
    "sg:orig_category":"Makelaars En Adviseurs Onroerende Goederen",
    "sg:phone":"+31 33 465 5655",
    "sg:postcode":"3811 HN",
    "sg:province":"Utrecht",
    "wof:name":"Walles & Van Heel",
    "wof:placetype":"venue"
},
  "geometry": {"coordinates":[5.38321,52.154701],"type":"Point"}
}