{
  "type": "Feature",
  "properties": {
    "addr:full":"Kalslagerring 13 Nieuw Vennep Noord-Holland 2151 TA",
    "addr:housenumber":"13",
    "addr:postcode":"2151 ta",
    "addr:street":"Kalslagerring;Nieuw Vennep",
    "iso:country":"NL",
    "sg:address":"Kalslagerring 13",
    "sg:city":"Nieuw Vennep",
    "sg:orig_category":"Verenigingen En Stichtingen",
    "sg:phone":"+31 252 621 591",
    "sg:postcode":"2151 TA",
    "sg:province":"Noord-Holland",
    "wof:name":"Schakel, Sticht De",
    "wof:placetype":"venue"
},
  "geometry": {"coordinates":[4.619998,52.262054],"type":"Point"}
}