{
  "type": "Feature",
  "properties": {
    "iso:country":"NL",
    "sg:address":"Essenlaan 4",
    "sg:city":"Bloemendaal",
    "sg:orig_category":"Beautyfarms And Sauna'S",
    "sg:phone":"+31 23 527 5175",
    "sg:postcode":"2061 GB",
    "sg:province":"Noord-Holland",
    "wof:name":"Jhr. Drs. C.S. Dedel",
    "wof:placetype":"venue"
},
  "geometry": {"coordinates":[4.622906,52.400925],"type":"Point"}
}