{
  "type": "Feature",
  "properties": {
    "iso:country":"NL",
    "sg:address":"Monsterseweg 24",
    "sg:city":"'S-Gravenzande",
    "sg:orig_category":"Bloemen En Planten",
    "sg:phone":"+31 174 440 610",
    "sg:postcode":"2691 JG",
    "sg:province":"Zuid-Holland",
    "sg:website":"http://www.antonvanbaalen.nl",
    "wof:name":"Anton Van Baalen Bedrijven",
    "wof:placetype":"venue"
},
  "geometry": {"coordinates":[4.15652,52.007847],"type":"Point"}
}