{
  "type": "Feature",
  "properties": {
    "addr:full":"Vredenveld 78 Emmen Drenthe 7824 CJ",
    "addr:housenumber":"78",
    "addr:postcode":"7824 cj",
    "addr:street":"Vredenveld",
    "iso:country":"NL",
    "sg:address":"Vredenveld 78",
    "sg:city":"Emmen",
    "sg:orig_category":"Scholen Voor Basisonderwijs",
    "sg:phone":"+31 591 622 409",
    "sg:postcode":"7824 CJ",
    "sg:province":"Drenthe",
    "sg:website":"http://www.twiespan.f2s.com",
    "wof:name":"Twiespan, 'T",
    "wof:placetype":"venue"
},
  "geometry": {"coordinates":[6.922396,52.782001],"type":"Point"}
}