{
  "type": "Feature",
  "properties": {
    "addr:full":"F Schurerstr 6 Hengelo Overijssel 7552 MB",
    "addr:housenumber":"6",
    "addr:postcode":"7552 mb",
    "addr:street":"Schurerstr",
    "iso:country":"NL",
    "sg:address":"F Schurerstr 6",
    "sg:city":"Hengelo",
    "sg:classifiers":[
        {
            "category":"Personal",
            "subcategory":"Nail Salon",
            "type":"Services"
        }
    ],
    "sg:phone":"+31 74 243 9991",
    "sg:postcode":"7552 MB",
    "sg:province":"Overijssel",
    "sg:tags":[
        "pedicure"
    ],
    "wof:name":"Lassche-De Jong, Y",
    "wof:placetype":"venue"
},
  "geometry": {"coordinates":[6.82641,52.262615],"type":"Point"}
}