{
  "type": "Feature",
  "properties": {
    "addr:full":"Boschstraat 88 Breda North Brabant 4811 GJ",
    "addr:housenumber":"88",
    "addr:postcode":"4811 gj",
    "addr:street":"Boschstraat",
    "iso:country":"NL",
    "sg:address":"Boschstraat 88",
    "sg:city":"Breda",
    "sg:orig_category":"Drukkerijen And Copyshops",
    "sg:phone":"+31 76 521 2248",
    "sg:postcode":"4811 GJ",
    "sg:province":"North Brabant",
    "wof:name":"Planitas Bv",
    "wof:placetype":"venue"
},
  "geometry": {"coordinates":[4.782981,51.590565],"type":"Point"}
}