{
  "type": "Feature",
  "properties": {
    "addr:full":"Stoopln 4 Dordrecht Zuid-Holland 3311 DM",
    "addr:housenumber":"4",
    "addr:postcode":"3311 dm",
    "addr:street":"Stoopln",
    "iso:country":"NL",
    "sg:address":"Stoopln 4",
    "sg:city":"Dordrecht",
    "sg:orig_category":"Makelaars En Adviseurs Onroerende Goederen",
    "sg:phone":"+31 78 631 4878",
    "sg:postcode":"3311 DM",
    "sg:province":"Zuid-Holland",
    "wof:name":"Rest, Van De",
    "wof:placetype":"venue"
},
  "geometry": {"coordinates":[4.68025,51.81245],"type":"Point"}
}