{
  "type": "Feature",
  "properties": {
    "addr:full":"De Feart 79 Ureterp Friesland 9247 CL",
    "addr:housenumber":"79",
    "addr:postcode":"9247",
    "addr:street":"De Feart",
    "iso:country":"NL",
    "sg:address":"De Feart 79",
    "sg:city":"Ureterp",
    "sg:orig_category":"Daken And Skeletbouw",
    "sg:phone":"+31 512 303 932",
    "sg:postcode":"9247 CL",
    "sg:province":"Friesland",
    "wof:name":"Beuckens Dak- & Zinkwerken",
    "wof:placetype":"venue"
},
  "geometry": {"coordinates":[6.164682,53.107883],"type":"Point"}
}