{
  "type": "Feature",
  "properties": {
    "iso:country":"NL",
    "sg:address":"Brouwerijstraat 11",
    "sg:city":"Koudekerke",
    "sg:orig_category":"Zuivelproducten",
    "sg:phone":"+31 118 552 299",
    "sg:postcode":"4371 EJ",
    "sg:province":"Zeeland",
    "wof:name":"Zuivelhandel L Oste",
    "wof:placetype":"venue"
},
  "geometry": {"coordinates":[3.555979,51.482327],"type":"Point"}
}