{
  "type": "Feature",
  "properties": {
    "iso:country":"NL",
    "sg:address":"Nederveenweg 16",
    "sg:city":"Sprang-Capelle",
    "sg:orig_category":"Loodgieterswerk, Verwarming And Sanitaire Installaties",
    "sg:phone":"+31 416 313 105",
    "sg:postcode":"5161 PA",
    "sg:province":"North Brabant",
    "wof:name":"Breman Zuid Bv",
    "wof:placetype":"venue"
},
  "geometry": {"coordinates":[4.982649,51.69474],"type":"Point"}
}