{
  "type": "Feature",
  "properties": {
    "addr:full":"Kerkstr 70 Huizen North Holland 1271 RM",
    "addr:housenumber":"70",
    "addr:postcode":"1271 rm",
    "addr:street":"Kerkstr",
    "iso:country":"NL",
    "sg:address":"Kerkstr 70",
    "sg:city":"Huizen",
    "sg:orig_category":"Artsen - Huisartsen",
    "sg:phone":"+31 35 525 6444",
    "sg:postcode":"1271 RM",
    "sg:province":"North Holland",
    "sg:website":"http://www.groepspraktijkhuizen.nl",
    "wof:name":"Groepspraktijk Huizen",
    "wof:placetype":"venue"
},
  "geometry": {"coordinates":[5.238987,52.298405],"type":"Point"}
}