{
  "type": "Feature",
  "properties": {
    "addr:full":"Wolstraat 8 Haarlem Noord-Holland 2011 ZA",
    "addr:housenumber":"8",
    "addr:postcode":"2011",
    "addr:street":"Wolstraat",
    "iso:country":"NL",
    "sg:address":"Wolstraat 8",
    "sg:city":"Haarlem",
    "sg:orig_category":"Fotostudio'S And Fotografen",
    "sg:phone":"+31 23 531 7220",
    "sg:postcode":"2011 ZA",
    "sg:province":"Noord-Holland",
    "wof:name":"Fotografie Powilleit Inga",
    "wof:placetype":"venue"
},
  "geometry": {"coordinates":[-82.312515,33.415298],"type":"Point"}
}