{
  "type": "Feature",
  "properties": {
    "addr:full":"Emdenstr 7 Deventer Overijssel 7418 BR",
    "addr:housenumber":"7",
    "addr:postcode":"7418 br",
    "addr:street":"Emdenstr",
    "iso:country":"NL",
    "sg:address":"Emdenstr 7",
    "sg:city":"Deventer",
    "sg:orig_category":"Verhuizingen",
    "sg:phone":"+31 570 633 044",
    "sg:postcode":"7418 BR",
    "sg:province":"Overijssel",
    "sg:website":"http://www.veldhoen.com",
    "wof:name":"Veldhoen Bv, T",
    "wof:placetype":"venue"
},
  "geometry": {"coordinates":[6.198715,52.24184],"type":"Point"}
}