{
  "type": "Feature",
  "properties": {
    "addr:full":"Noordeindseweg 3 Berkel En Rodenrijs Zuid-Holland 2651 CV",
    "addr:housenumber":"3",
    "addr:postcode":"2651 cv",
    "addr:street":"Noordeindseweg",
    "iso:country":"NL",
    "sg:address":"Noordeindseweg 3",
    "sg:city":"Berkel En Rodenrijs",
    "sg:orig_category":"Bedrijfs- And Managementsconsultants",
    "sg:phone":"+31 10 519 0851",
    "sg:postcode":"2651 CV",
    "sg:province":"Zuid-Holland",
    "wof:name":"Implex Theta Bv",
    "wof:placetype":"venue"
},
  "geometry": {"coordinates":[4.478176,51.995663],"type":"Point"}
}