{
  "type": "Feature",
  "properties": {
    "addr:full":"Past Gilisstr 30 Ryen Noord-Brabant 5121 CE",
    "addr:housenumber":"30",
    "addr:postcode":"5121 ce",
    "iso:country":"NL",
    "sg:address":"Past Gilisstr 30",
    "sg:city":"Ryen",
    "sg:orig_category":"Fitnesscentra",
    "sg:phone":"+31 161 226 394",
    "sg:postcode":"5121 CE",
    "sg:province":"Noord-Brabant",
    "sg:website":"http://www.indoorfitness.nl",
    "wof:name":"Indoor Fitness",
    "wof:placetype":"venue"
},
  "geometry": {"coordinates":[4.9197,51.588017],"type":"Point"}
}