{
  "type": "Feature",
  "properties": {
    "addr:full":"Hollandsch Diep 69 Capelle A/D Ijssel Zuid-Holland 2904 EP",
    "addr:housenumber":"69;a / d",
    "addr:postcode":"2904 ep",
    "addr:street":"Hollandsch Diep",
    "iso:country":"NL",
    "sg:address":"Hollandsch Diep 69",
    "sg:city":"Capelle A/D Ijssel",
    "sg:orig_category":"Kantoorartikelen",
    "sg:phone":"+31 10 451 4565",
    "sg:postcode":"2904 EP",
    "sg:province":"Zuid-Holland",
    "wof:name":"J Willebrands Automatisering",
    "wof:placetype":"venue"
},
  "geometry": {"coordinates":[4.6025300026,51.9369430542],"type":"Point"}
}