{
  "type": "Feature",
  "properties": {
    "addr:full":"Enterwg 13A Wierden NL.08 7642 NB",
    "addr:housenumber":"13a;nl.08",
    "addr:postcode":"7642 nb",
    "addr:street":"Enterwg",
    "iso:country":"NL",
    "sg:address":"Enterwg 13A",
    "sg:city":"Wierden",
    "sg:orig_category":"Bloemen En Planten",
    "sg:phone":"+31 547 382 540",
    "sg:postcode":"7642 NB",
    "sg:province":"NL.08",
    "wof:name":"Ans",
    "wof:placetype":"venue"
},
  "geometry": {"coordinates":[6.572451,52.330746],"type":"Point"}
}