{
  "type": "Feature",
  "properties": {
    "addr:full":"Opwg 90B Schoonhoven Zuid-Holland 2871 NG",
    "addr:housenumber":"90b",
    "addr:postcode":"2871 ng",
    "addr:street":"Opwg",
    "iso:country":"NL",
    "sg:address":"Opwg 90B",
    "sg:city":"Schoonhoven",
    "sg:orig_category":"Parkeersystemen",
    "sg:phone":"+31 182 381 224",
    "sg:postcode":"2871 NG",
    "sg:province":"Zuid-Holland",
    "wof:name":"Scanton Bv",
    "wof:placetype":"venue"
},
  "geometry": {"coordinates":[4.841312,51.956261],"type":"Point"}
}