{
  "type": "Feature",
  "properties": {
    "addr:full":"Ambachtsweg 16 Utrecht Utrecht 3542 DG",
    "addr:housenumber":"16",
    "addr:postcode":"3542 dg",
    "addr:street":"Ambachtsweg",
    "iso:country":"NL",
    "sg:address":"Ambachtsweg 16",
    "sg:city":"Utrecht",
    "sg:orig_category":"Kantoorapparatuur Gh",
    "sg:phone":"+31 30 241 6364",
    "sg:postcode":"3542 DG",
    "sg:province":"Utrecht",
    "wof:name":"Asis Nederland Bv",
    "wof:placetype":"venue"
},
  "geometry": {"coordinates":[5.0458450317,52.1223564148],"type":"Point"}
}