{
  "type": "Feature",
  "properties": {
    "addr:full":"Doctor Welfferweg 86 Westbroek Utrecht 3615 AR",
    "addr:housenumber":"86",
    "addr:postcode":"3615",
    "addr:street":"Doctor Welfferweg",
    "iso:country":"NL",
    "sg:address":"Doctor Welfferweg 86",
    "sg:city":"Westbroek",
    "sg:orig_category":"Bedrijfs- And Managementsconsultants",
    "sg:phone":"+31 346 281 190",
    "sg:postcode":"3615 AR",
    "sg:province":"Utrecht",
    "wof:name":"Syscon",
    "wof:placetype":"venue"
},
  "geometry": {"coordinates":[-58.874729,-24.81008],"type":"Point"}
}