{
  "type": "Feature",
  "properties": {
    "addr:full":"Postbus 30 Schoonhoven Zuid-Holland 2870 AA",
    "addr:housenumber":"30",
    "addr:postcode":"2870 aa",
    "addr:street":"Postbus",
    "iso:country":"NL",
    "sg:address":"Postbus 30",
    "sg:city":"Schoonhoven",
    "sg:orig_category":"Hek- En Rasterwerken",
    "sg:phone":"+31 900 8212427",
    "sg:postcode":"2870 AA",
    "sg:province":"Zuid-Holland",
    "sg:website":"http://www.abchekwerk.nl",
    "wof:name":"Abc Hekwerk Rijnmond",
    "wof:placetype":"venue"
},
  "geometry": {"coordinates":[4.85103,51.946453],"type":"Point"}
}