{
  "type": "Feature",
  "properties": {
    "addr:full":"Boombergln 71A Hilversum Noord-Holland 1217 RP",
    "addr:housenumber":"71a",
    "addr:postcode":"1217 rp",
    "addr:street":"Boombergln",
    "iso:country":"NL",
    "sg:address":"Boombergln 71A",
    "sg:city":"Hilversum",
    "sg:orig_category":"Hydrocultuur",
    "sg:phone":"+31 35 624 7285",
    "sg:postcode":"1217 RP",
    "sg:province":"Noord-Holland",
    "wof:name":"Peter Van Herwijnen",
    "wof:placetype":"venue"
},
  "geometry": {"coordinates":[5.165774,52.227066],"type":"Point"}
}