{
  "type": "Feature",
  "properties": {
    "addr:full":"Oude Haven 64 Nijmegen Gelderland 6511 XH",
    "addr:housenumber":"64",
    "addr:postcode":"6511 xh",
    "addr:street":"Oude Haven;Gelderland",
    "iso:country":"NL",
    "sg:address":"Oude Haven 64",
    "sg:city":"Nijmegen",
    "sg:orig_category":"Public Relationbureaus",
    "sg:phone":"+31 24 323 8830",
    "sg:postcode":"6511 XH",
    "sg:province":"Gelderland",
    "wof:name":"Walraven P.O.P.",
    "wof:placetype":"venue"
},
  "geometry": {"coordinates":[5.860212,51.849545],"type":"Point"}
}