{
  "type": "Feature",
  "properties": {
    "addr:full":"R Hartpln 320 Amsterdam Noord-Holland 1071 TT",
    "addr:housenumber":"320",
    "addr:postcode":"1071 tt",
    "iso:country":"NL",
    "sg:address":"R Hartpln 320",
    "sg:city":"Amsterdam",
    "sg:orig_category":"Psychotherapeuten",
    "sg:phone":"+31 20 672 2558",
    "sg:postcode":"1071 TT",
    "sg:province":"Noord-Holland",
    "wof:name":"Hypnose Praktijk",
    "wof:placetype":"venue"
},
  "geometry": {"coordinates":[4.882397,52.352612],"type":"Point"}
}