{
  "type": "Feature",
  "properties": {
    "addr:full":"Voorheuvel 3 Zeist Utrecht 3701 JA",
    "addr:housenumber":"3",
    "addr:postcode":"3701 ja",
    "addr:street":"Voorheuvel",
    "iso:country":"NL",
    "sg:address":"Voorheuvel 3",
    "sg:city":"Zeist",
    "sg:orig_category":"Herenmodezaken",
    "sg:phone":"+31 30 692 4674",
    "sg:postcode":"3701 JA",
    "sg:province":"Utrecht",
    "wof:name":"Duetz Kleding Bv",
    "wof:placetype":"venue"
},
  "geometry": {"coordinates":[5.239469,52.086514],"type":"Point"}
}