{
  "type": "Feature",
  "properties": {
    "addr:full":"Leidsestraatweg 225 Woerden Utrecht 3443 BT",
    "addr:housenumber":"225",
    "addr:postcode":"3443 bt",
    "addr:street":"Leidsestraatweg",
    "iso:country":"NL",
    "sg:address":"Leidsestraatweg 225",
    "sg:city":"Woerden",
    "sg:orig_category":"Verhuur Voertuigen Behalve Auto'S",
    "sg:phone":"+31 348 421 345",
    "sg:postcode":"3443 BT",
    "sg:province":"Utrecht",
    "wof:name":"H. Mostert Aanhangwagens En Magazijnstellingen",
    "wof:placetype":"venue"
},
  "geometry": {"coordinates":[4.865584,52.085873],"type":"Point"}
}