{
  "type": "Feature",
  "properties": {
    "addr:full":"Badweg 20 Gorredijk Friesland 8401 BL",
    "addr:housenumber":"20",
    "addr:postcode":"8401 bl",
    "addr:street":"Badweg",
    "iso:country":"NL",
    "sg:address":"Badweg 20",
    "sg:city":"Gorredijk",
    "sg:orig_category":"Autokeuringen",
    "sg:phone":"+31 513 462 845",
    "sg:postcode":"8401 BL",
    "sg:province":"Friesland",
    "wof:name":"Automobielbedrijf A. Fransen",
    "wof:placetype":"venue"
},
  "geometry": {"coordinates":[6.058314,53.002476],"type":"Point"}
}