{
  "type": "Feature",
  "properties": {
    "addr:full":"Stek 4 Dordrecht Zuid-Holland 3311 XS",
    "addr:housenumber":"4",
    "addr:postcode":"3311 xs",
    "addr:street":"Stek",
    "iso:country":"NL",
    "sg:address":"Stek 4",
    "sg:city":"Dordrecht",
    "sg:orig_category":"Loodgieters",
    "sg:phone":"+31 78 614 8690",
    "sg:postcode":"3311 XS",
    "sg:province":"Zuid-Holland",
    "wof:name":"Schelt, Van",
    "wof:placetype":"venue"
},
  "geometry": {"coordinates":[4.673467,51.815678],"type":"Point"}
}