{
  "type": "Feature",
  "properties": {
    "addr:full":"Torenstr 2 S Gravenhage Zuid-Holland 2513 BS",
    "addr:housenumber":"2;gravenhage",
    "addr:postcode":"2513 bs",
    "addr:street":"Torenstr;S",
    "iso:country":"NL",
    "sg:address":"Torenstr 2",
    "sg:city":"S Gravenhage",
    "sg:orig_category":"Kampeerartikelen",
    "sg:phone":"+31 70 346 4673",
    "sg:postcode":"2513 BS",
    "sg:province":"Zuid-Holland",
    "wof:name":"Track & Trail",
    "wof:placetype":"venue"
},
  "geometry": {"coordinates":[4.3033900261,52.0784416199],"type":"Point"}
}