{
  "type": "Feature",
  "properties": {
    "addr:full":"Marcellienstr 17 Geleen Limburg 6166 CP",
    "addr:housenumber":"17",
    "addr:postcode":"6166 cp",
    "addr:street":"Marcellienstr",
    "iso:country":"NL",
    "sg:address":"Marcellienstr 17",
    "sg:city":"Geleen",
    "sg:classifiers":[
        {
            "category":"Food & Beverages",
            "subcategory":"Fruits & Vegetables",
            "type":"Retail Goods"
        }
    ],
    "sg:phone":"+31 46 474 3548",
    "sg:postcode":"6166 CP",
    "sg:province":"Limburg",
    "sg:tags":[
        "en",
        "groenten"
    ],
    "wof:name":"Vallen Vof, J",
    "wof:placetype":"venue"
},
  "geometry": {"coordinates":[5.841926,50.971672],"type":"Point"}
}