{
  "type": "Feature",
  "properties": {
    "iso:country":"NL",
    "sg:address":"Deventerwg 9",
    "sg:city":"Harderwyk",
    "sg:orig_category":"Kantoormachines",
    "sg:phone":"+31 341 462 080",
    "sg:postcode":"3843 GA",
    "sg:province":"Georgia",
    "sg:website":"http://www.wuestman.nl",
    "wof:name":"Wuestman, Kantoorwereld",
    "wof:placetype":"venue"
},
  "geometry": {"coordinates":[-83.2229309082,32.6781311035],"type":"Point"}
}