{
  "type": "Feature",
  "properties": {
    "addr:full":"Kremerstr 14 Bergen Op Zoom Noord-Brabant 4611 TR",
    "addr:housenumber":"14",
    "addr:postcode":"4611 tr",
    "addr:street":"Kremerstr",
    "iso:country":"NL",
    "sg:address":"Kremerstr 14",
    "sg:city":"Bergen Op Zoom",
    "sg:orig_category":"Poeliers",
    "sg:phone":"+31 164 254 342",
    "sg:postcode":"4611 TR",
    "sg:province":"Noord-Brabant",
    "sg:website":"http://www.poelier.com",
    "wof:name":"Schrauwen",
    "wof:placetype":"venue"
},
  "geometry": {"coordinates":[4.287085,51.495358],"type":"Point"}
}