{
  "type": "Feature",
  "properties": {
    "iso:country":"NL",
    "sg:address":"Hoofdwg 26",
    "sg:city":"Capelle Ad Yssel",
    "sg:orig_category":"Lasapparaten En Benodigdheden",
    "sg:phone":"+31 10 458 2877",
    "sg:postcode":"2908 LC",
    "sg:province":"South Holland",
    "sg:website":"http://www.unidare.nl",
    "wof:name":"Unidare Benelux Bv",
    "wof:placetype":"venue"
},
  "geometry": {"coordinates":[4.577893,51.956711],"type":"Point"}
}