{
  "type": "Feature",
  "properties": {
    "addr:full":"Warmenbossenwg 7 Schoonloo Drenthe 9443 TN",
    "addr:housenumber":"7",
    "addr:postcode":"9443",
    "addr:street":"Warmenbossenwg",
    "iso:country":"NL",
    "sg:address":"Warmenbossenwg 7",
    "sg:city":"Schoonloo",
    "sg:orig_category":"Groepsaccommodaties",
    "sg:phone":"+31 592 501 511",
    "sg:postcode":"9443 TN",
    "sg:province":"Drenthe",
    "sg:website":"http://www.warmebossen.nl",
    "wof:name":"Warme Bossen Camping/Kampeerboerderij, De",
    "wof:placetype":"venue"
},
  "geometry": {"coordinates":[-85.978554,35.83062],"type":"Point"}
}