{
  "type": "Feature",
  "properties": {
    "addr:full":"Kolonievaart 3 Huis Ter Heide Dr Drenthe 9336 TC",
    "addr:housenumber":"3",
    "addr:postcode":"9336 tc",
    "addr:street":"Kolonievaart;Ter Heide Dr",
    "iso:country":"NL",
    "sg:address":"Kolonievaart 3",
    "sg:city":"Huis Ter Heide Dr",
    "sg:orig_category":"Kampeerterreinen",
    "sg:phone":"+31 592 388 269",
    "sg:postcode":"9336 TC",
    "sg:province":"Drenthe",
    "wof:name":"De Schuilhoeve",
    "wof:placetype":"venue"
},
  "geometry": {"coordinates":[6.4692821503,53.018371582],"type":"Point"}
}