{
  "type": "Feature",
  "properties": {
    "addr:full":"Sint Jacobsstraat 9 Leeuwarden Provincie Friesland 8911 HR",
    "addr:housenumber":"9",
    "addr:postcode":"8911 hr",
    "addr:street":"Sint Jacobsstraat;Provincie Friesland",
    "iso:country":"NL",
    "sg:address":"Sint Jacobsstraat 9",
    "sg:city":"Leeuwarden",
    "sg:classifiers":[
        {
            "category":"Shopping",
            "subcategory":"Gifts & Souvenirs",
            "type":"Retail Goods"
        }
    ],
    "sg:phone":"+31 58 216 3130",
    "sg:postcode":"8911 HR",
    "sg:province":"Provincie Friesland",
    "sg:tags":[
        "geschenken"
    ],
    "wof:name":"Frappant, Hebbers En Krijgers",
    "wof:placetype":"venue"
},
  "geometry": {"coordinates":[5.796455,53.201366],"type":"Point"}
}