{
  "type": "Feature",
  "properties": {
    "addr:full":"Vlamoven 5A/B/C/D Delfzyl Groningen 9934 ND",
    "addr:housenumber":"5a / b / c;d",
    "addr:postcode":"9934 nd",
    "addr:street":"Vlamoven;/",
    "iso:country":"NL",
    "sg:address":"Vlamoven 5A/B/C/D",
    "sg:city":"Delfzyl",
    "sg:orig_category":"Omroep",
    "sg:phone":"+31 596 620 185",
    "sg:postcode":"9934 ND",
    "sg:province":"Groningen",
    "wof:name":"Radio Delfzicht",
    "wof:placetype":"venue"
},
  "geometry": {"coordinates":[6.903212,53.331192],"type":"Point"}
}