{
  "type": "Feature",
  "properties": {
    "addr:full":"Glaslaan 34 Nieuw Buinen Drenthe 9521 GG",
    "addr:housenumber":"34",
    "addr:postcode":"buinen;9521 gg",
    "addr:street":"Glaslaan",
    "iso:country":"NL",
    "sg:address":"Glaslaan 34",
    "sg:city":"Nieuw Buinen",
    "sg:orig_category":"Schilderwerk",
    "sg:phone":"+31 599 651 975",
    "sg:postcode":"9521 GG",
    "sg:province":"Drenthe",
    "wof:name":"N. Huiting",
    "wof:placetype":"venue"
},
  "geometry": {"coordinates":[6.967499,52.965923],"type":"Point"}
}