{
  "type": "Feature",
  "properties": {
    "addr:full":"Douwemastrjitte 14 Jirnsum Friesland 9011 VS",
    "addr:housenumber":"14",
    "addr:postcode":"9011 vs",
    "addr:street":"Douwemastrjitte",
    "iso:country":"NL",
    "sg:address":"Douwemastrjitte 14",
    "sg:city":"Jirnsum",
    "sg:classifiers":[
        {
            "category":"Education",
            "subcategory":"Preschool",
            "type":"Public Place"
        }
    ],
    "sg:phone":"+31 566 601 646",
    "sg:postcode":"9011 VS",
    "sg:province":"Friesland",
    "sg:tags":[
        "kleuteronderwijs",
        "basis-"
    ],
    "wof:name":"Openbare Basisschool It Tredde Ste",
    "wof:placetype":"venue"
},
  "geometry": {"coordinates":[5.79287,53.081409],"type":"Point"}
}