{
  "type": "Feature",
  "properties": {
    "iso:country":"NL",
    "sg:address":"Veluwelaan 45",
    "sg:city":"Heerenveen",
    "sg:classifiers":[
        {
            "category":"Education",
            "subcategory":"Preschool",
            "type":"Public Place"
        }
    ],
    "sg:phone":"+31 513 633 788",
    "sg:postcode":"8443 AJ",
    "sg:province":"Friesland",
    "sg:tags":[
        "kleuteronderwijs",
        "basis-"
    ],
    "wof:name":"Jenaplanschool De Bernebrege",
    "wof:placetype":"venue"
},
  "geometry": {"coordinates":[5.936142,52.947021],"type":"Point"}
}