{
  "type": "Feature",
  "properties": {
    "addr:full":"Marktstr 22 Uden North Brabant 5401 GH",
    "addr:housenumber":"22",
    "addr:postcode":"5401 gh",
    "addr:street":"Marktstr",
    "iso:country":"NL",
    "sg:address":"Marktstr 22",
    "sg:city":"Uden",
    "sg:orig_category":"Warenhuizen",
    "sg:phone":"+31 413 262 146",
    "sg:postcode":"5401 GH",
    "sg:province":"North Brabant",
    "wof:name":"Hema",
    "wof:placetype":"venue"
},
  "geometry": {"coordinates":[5.613817215,51.6576118469],"type":"Point"}
}