{
  "type": "Feature",
  "properties": {
    "addr:full":"Voornestraat 60 Eindhoven North Brabant 5628 JG",
    "addr:housenumber":"60",
    "addr:postcode":"5628 jg",
    "addr:street":"Voornestraat",
    "iso:country":"NL",
    "sg:address":"Voornestraat 60",
    "sg:city":"Eindhoven",
    "sg:orig_category":"Goederenvervoer Over De Weg",
    "sg:phone":"+31 40 242 1609",
    "sg:postcode":"5628 JG",
    "sg:province":"North Brabant",
    "wof:name":"Frank Transport",
    "wof:placetype":"venue"
},
  "geometry": {"coordinates":[5.46896,51.481186],"type":"Point"}
}