{
  "type": "Feature",
  "properties": {
    "addr:full":"Klaasstr 37 Venlo Limburg 5911 JN",
    "addr:housenumber":"37",
    "addr:postcode":"5911 jn",
    "addr:street":"Klaasstr",
    "iso:country":"NL",
    "sg:address":"Klaasstr 37",
    "sg:city":"Venlo",
    "sg:orig_category":"Boeken En Tijdschriften",
    "sg:phone":"+31 77 351 9411",
    "sg:postcode":"5911 JN",
    "sg:province":"Limburg",
    "wof:name":"Kortooms, The",
    "wof:placetype":"venue"
},
  "geometry": {"coordinates":[6.17048,51.368622],"type":"Point"}
}