{
  "type": "Feature",
  "properties": {
    "addr:full":"Waardsedijk 100 Snelrewaard Utrecht 3425 TH",
    "addr:housenumber":"100",
    "addr:postcode":"3425 th",
    "addr:street":"Waardsedijk",
    "iso:country":"NL",
    "sg:address":"Waardsedijk 100",
    "sg:city":"Snelrewaard",
    "sg:orig_category":"Goederenvervoer Over De Weg",
    "sg:phone":"+31 348 564 120",
    "sg:postcode":"3425 TH",
    "sg:province":"Utrecht",
    "wof:name":"Transportbedrijf J.W. Muys",
    "wof:placetype":"venue"
},
  "geometry": {"coordinates":[4.880134,52.021431],"type":"Point"}
}