{
  "type": "Feature",
  "properties": {
    "addr:full":"Langenhorst 245 Rotterdam South Holland 3085 HE",
    "addr:housenumber":"245",
    "addr:postcode":"3085 he",
    "addr:street":"Langenhorst",
    "iso:country":"NL",
    "sg:address":"Langenhorst 245",
    "sg:city":"Rotterdam",
    "sg:orig_category":"Bloemen And Planten",
    "sg:phone":"+31 10 480 4305",
    "sg:postcode":"3085 HE",
    "sg:province":"South Holland",
    "wof:name":"De Plantenbeurs W.C. De Poter",
    "wof:placetype":"venue"
},
  "geometry": {"coordinates":[4.49423,51.874199],"type":"Point"}
}