{
  "type": "Feature",
  "properties": {
    "addr:full":"Goorseweg 39 Diepenheim NL.08 7478 BC",
    "addr:housenumber":"39;nl.08",
    "addr:postcode":"7478 bc",
    "addr:street":"Goorseweg",
    "iso:country":"NL",
    "sg:address":"Goorseweg 39",
    "sg:city":"Diepenheim",
    "sg:orig_category":"Autokeuringen",
    "sg:phone":"+31 547 351 796",
    "sg:postcode":"7478 BC",
    "sg:province":"NL.08",
    "wof:name":"A.L. Bauhuis",
    "wof:placetype":"venue"
},
  "geometry": {"coordinates":[6.56063,52.20042],"type":"Point"}
}