{
  "type": "Feature",
  "properties": {
    "iso:country":"NL",
    "sg:address":"Kruidenlaan 282",
    "sg:city":"Nijverdal",
    "sg:orig_category":"Paramedische Behandelingen",
    "sg:phone":"+31 548 616 602",
    "sg:postcode":"7443 JV",
    "sg:province":"Overijssel",
    "wof:name":"E.V.M. Hegeman",
    "wof:placetype":"venue"
},
  "geometry": {"coordinates":[6.483491,52.376312],"type":"Point"}
}