{
  "type": "Feature",
  "properties": {
    "addr:full":"Europaln N 16B Budel North Brabant 6021 EH",
    "addr:housenumber":"16b",
    "addr:postcode":"6021 eh",
    "addr:street":"N",
    "iso:country":"NL",
    "sg:address":"Europaln N 16B",
    "sg:city":"Budel",
    "sg:orig_category":"Omroep",
    "sg:phone":"+31 495 495 678",
    "sg:postcode":"6021 EH",
    "sg:province":"North Brabant",
    "wof:name":"Cranendonck Radio",
    "wof:placetype":"venue"
},
  "geometry": {"coordinates":[5.576494,51.274277],"type":"Point"}
}