{
  "type": "Feature",
  "properties": {
    "addr:full":"Boomgaardwg 7 Odijk Utrecht 3984 KG",
    "addr:housenumber":"7",
    "addr:postcode":"3984 kg",
    "addr:street":"Boomgaardwg",
    "iso:country":"NL",
    "sg:address":"Boomgaardwg 7",
    "sg:city":"Odijk",
    "sg:orig_category":"Apotheken",
    "sg:phone":"+31 30 656 7711",
    "sg:postcode":"3984 KG",
    "sg:province":"Utrecht",
    "wof:name":"Steeg Bv, In De",
    "wof:placetype":"venue"
},
  "geometry": {"coordinates":[5.233961,52.050789],"type":"Point"}
}