{
  "type": "Feature",
  "properties": {
    "addr:full":"Stationsweg 32 Wadenoijen Gelderland 4014 NC",
    "addr:housenumber":"32",
    "addr:postcode":"4014 nc",
    "addr:street":"Stationsweg;Gelderland",
    "iso:country":"NL",
    "sg:address":"Stationsweg 32",
    "sg:city":"Wadenoijen",
    "sg:orig_category":"Loodgieterswerk, Verwarming And Sanitaire Installaties",
    "sg:phone":"+31 344 662 013",
    "sg:postcode":"4014 NC",
    "sg:province":"Gelderland",
    "wof:name":"G. Vermasen",
    "wof:placetype":"venue"
},
  "geometry": {"coordinates":[5.352854,51.869194],"type":"Point"}
}