{
  "type": "Feature",
  "properties": {
    "addr:full":"Mr Moddermanstr 3 Winschoten Groningen 9671 AG",
    "addr:housenumber":"3",
    "addr:postcode":"9671",
    "iso:country":"NL",
    "sg:address":"Mr Moddermanstr 3",
    "sg:city":"Winschoten",
    "sg:orig_category":"Baggerwerken",
    "sg:phone":"+31 597 471 220",
    "sg:postcode":"9671 AG",
    "sg:province":"Groningen",
    "sg:website":"http://www.musing.nl",
    "wof:name":"M?sing Bv",
    "wof:placetype":"venue"
},
  "geometry": {"coordinates":[7.033235,53.141117],"type":"Point"}
}