{
  "type": "Feature",
  "properties": {
    "addr:full":"Julialaantje 26 Rijswijk Zh Zuid-Holland 2283 TB",
    "addr:housenumber":"26",
    "addr:postcode":"zh;2283 tb",
    "addr:street":"Julialaantje",
    "iso:country":"NL",
    "sg:address":"Julialaantje 26",
    "sg:city":"Rijswijk Zh",
    "sg:orig_category":"Overheidsdiensten",
    "sg:phone":"+31 70 399 9580",
    "sg:postcode":"2283 TB",
    "sg:province":"Zuid-Holland",
    "wof:name":"Don Bosco Jongerencentrum",
    "wof:placetype":"venue"
},
  "geometry": {"coordinates":[4.3235459328,52.0524139404],"type":"Point"}
}