{
  "type": "Feature",
  "properties": {
    "iso:country":"NL",
    "sg:address":"Willem Van Nassaulaan 6",
    "sg:city":"'S Hertogenbosch",
    "sg:orig_category":"Vertaal- And Tolkenbureaus",
    "sg:phone":"+31 73 613 6991",
    "sg:postcode":"5212 TA",
    "sg:province":"Noord-Brabant",
    "wof:name":"Portugees Vertaalburo A Esperanca",
    "wof:placetype":"venue"
},
  "geometry": {"coordinates":[5.308339,51.696636],"type":"Point"}
}