{
  "type": "Feature",
  "properties": {
    "iso:country":"NL",
    "sg:address":"Houtrustweg 108",
    "sg:city":"'S Gravenhage",
    "sg:orig_category":"Fitnesscentra",
    "sg:phone":"+31 70 363 4348",
    "sg:postcode":"2566 GJ",
    "sg:province":"South Holland",
    "wof:name":"Caesar Sport'S Health Clubs",
    "wof:placetype":"venue"
},
  "geometry": {"coordinates":[4.269557,52.087234],"type":"Point"}
}