{
  "type": "Feature",
  "properties": {
    "addr:full":"Houtrustweg 108 'S Gravenhage South Holland 2566 GJ",
    "addr:housenumber":"108 '",
    "addr:postcode":"2566 gj",
    "addr:street":"Houtrustweg",
    "iso:country":"NL",
    "sg:address":"Houtrustweg 108",
    "sg:city":"'S Gravenhage",
    "sg:orig_category":"Fitnesscentra",
    "sg:phone":"+31 70 363 4348",
    "sg:postcode":"2566 GJ",
    "sg:province":"South Holland",
    "wof:name":"Caesar Sport'S Health Clubs",
    "wof:placetype":"venue"
},
  "geometry": {"coordinates":[4.269557,52.087234],"type":"Point"}
}