{
  "type": "Feature",
  "properties": {
    "addr:full":"Langestraat 28 Amersfoort Utrecht 3811 AH",
    "addr:housenumber":"28",
    "addr:postcode":"3811 ah",
    "addr:street":"Langestraat",
    "iso:country":"NL",
    "sg:address":"Langestraat 28",
    "sg:city":"Amersfoort",
    "sg:classifiers":[
        {
            "category":"Shopping",
            "subcategory":"Clothing, Apparel, & Fashions",
            "type":"Retail Goods"
        }
    ],
    "sg:phone":"+31 33 465 7575",
    "sg:postcode":"3811 AH",
    "sg:province":"Utrecht",
    "sg:tags":[
        "ondergoed",
        "lingerie"
    ],
    "wof:name":"Jambelle Beenmode",
    "wof:placetype":"venue"
},
  "geometry": {"coordinates":[5.386085,52.152325],"type":"Point"}
}