{
  "type": "Feature",
  "properties": {
    "addr:full":"Engelsestraat 11 Leeuwarden Provincie Friesland 8913 BE",
    "addr:housenumber":"11",
    "addr:postcode":"8913",
    "addr:street":"Engelsestraat;Provincie Friesland",
    "iso:country":"NL",
    "sg:address":"Engelsestraat 11",
    "sg:city":"Leeuwarden",
    "sg:orig_category":"Bloemen And Planten",
    "sg:phone":"+31 58 213 4319",
    "sg:postcode":"8913 BE",
    "sg:province":"Provincie Friesland",
    "wof:name":"Bloembinderij De Witte Lelie",
    "wof:placetype":"venue"
},
  "geometry": {"coordinates":[5.782709,53.203613],"type":"Point"}
}