{
  "type": "Feature",
  "properties": {
    "iso:country":"NL",
    "sg:address":"Stroeerwg 46",
    "sg:city":"Stroe",
    "sg:orig_category":"Verhuur",
    "sg:phone":"+31 342 443 129",
    "sg:postcode":"3776 MJ",
    "sg:province":"Gelderland",
    "wof:name":"Kruif, De",
    "wof:placetype":"venue"
},
  "geometry": {"coordinates":[5.678774,52.177025],"type":"Point"}
}