{
  "type": "Feature",
  "properties": {
    "addr:full":"Montfortstraat 1 Hoensbroek Limburg 6433 JG",
    "addr:housenumber":"1",
    "addr:postcode":"6433 jg",
    "addr:street":"Montfortstraat",
    "iso:country":"NL",
    "sg:address":"Montfortstraat 1",
    "sg:city":"Hoensbroek",
    "sg:classifiers":[
        {
            "category":"Fast Food",
            "type":"Food & Drink"
        }
    ],
    "sg:phone":"+31 45 522 0852",
    "sg:postcode":"6433 JG",
    "sg:province":"Limburg",
    "sg:tags":[
        "afhaal",
        "restaurant"
    ],
    "wof:name":"Friture Montfort",
    "wof:placetype":"venue"
},
  "geometry": {"coordinates":[5.932104,50.908646],"type":"Point"}
}