{
  "type": "Feature",
  "properties": {
    "iso:country":"NL",
    "sg:address":"Hoofdwg 12",
    "sg:city":"Klyndyk",
    "sg:orig_category":"Land- En Tuinbouw - Mechanisatie",
    "sg:phone":"+31 591 513 613",
    "sg:postcode":"7871 TB",
    "sg:province":"Drenthe",
    "wof:name":"Meijering",
    "wof:placetype":"venue"
},
  "geometry": {"coordinates":[6.852678,52.835075],"type":"Point"}
}