{
  "type": "Feature",
  "properties": {
    "addr:full":"Hg Bothofstr 138A Enschede NL.08 7511 ZE",
    "addr:housenumber":"138a",
    "addr:postcode":"7511 ze",
    "iso:country":"NL",
    "sg:address":"Hg Bothofstr 138A",
    "sg:city":"Enschede",
    "sg:orig_category":"Belastingconsulenten/ Belastingadviseurs",
    "sg:phone":"+31 53 433 3322",
    "sg:postcode":"7511 ZE",
    "sg:province":"NL.08",
    "wof:name":"Vos, J H",
    "wof:placetype":"venue"
},
  "geometry": {"coordinates":[6.90743,52.222683],"type":"Point"}
}