{
  "type": "Feature",
  "properties": {
    "addr:full":"Zuidlaarderweg 97 Annen Drenthe 9468 AD",
    "addr:housenumber":"97",
    "addr:postcode":"9468 ad",
    "addr:street":"Zuidlaarderweg",
    "iso:country":"NL",
    "sg:address":"Zuidlaarderweg 97",
    "sg:city":"Annen",
    "sg:orig_category":"Artiestenbureaus",
    "sg:phone":"+31 592 273 002",
    "sg:postcode":"9468 AD",
    "sg:province":"Drenthe",
    "wof:name":"De Flierefluiter Marionettentheater",
    "wof:placetype":"venue"
},
  "geometry": {"coordinates":[-79.253815,33.471233],"type":"Point"}
}