{
  "type": "Feature",
  "properties": {
    "addr:full":"Meenteweg 56 Schildwolde Groningen 9626 BJ",
    "addr:housenumber":"56",
    "addr:postcode":"9626 bj",
    "addr:street":"Meenteweg",
    "iso:country":"NL",
    "sg:address":"Meenteweg 56",
    "sg:city":"Schildwolde",
    "sg:classifiers":[
        {
            "category":"Bars & Pubs",
            "type":"Food & Drink"
        }
    ],
    "sg:phone":"+31 598 422 772",
    "sg:postcode":"9626 BJ",
    "sg:province":"Groningen",
    "wof:name":"Cafetaria-Pub Fiddler'S Green",
    "wof:placetype":"venue"
},
  "geometry": {"coordinates":[6.8097128868,53.2373390198],"type":"Point"}
}