{
  "type": "Feature",
  "properties": {
    "addr:full":"Voorthuizerwg 3 Nykerk Gld Gelderland 3862 PZ",
    "addr:housenumber":"3",
    "addr:postcode":"3862 pz",
    "addr:street":"Voorthuizerwg;Gld Gelderland",
    "iso:country":"NL",
    "sg:address":"Voorthuizerwg 3",
    "sg:city":"Nykerk Gld",
    "sg:orig_category":"Kaas",
    "sg:phone":"+31 342 473 566",
    "sg:postcode":"3862 PZ",
    "sg:province":"Gelderland",
    "wof:name":"Kaasspecialist, De",
    "wof:placetype":"venue"
},
  "geometry": {"coordinates":[5.6080260277,52.1977920532],"type":"Point"}
}