{
  "type": "Feature",
  "properties": {
    "addr:full":"Hoofdwg 74 Harkstede Groningen 9617 AJ",
    "addr:housenumber":"74",
    "addr:postcode":"9617 aj",
    "addr:street":"Hoofdwg",
    "iso:country":"NL",
    "sg:address":"Hoofdwg 74",
    "sg:city":"Harkstede",
    "sg:orig_category":"Kappers",
    "sg:phone":"+31 50 404 1800",
    "sg:postcode":"9617 AJ",
    "sg:province":"Groningen",
    "wof:name":"Knipstee, De",
    "wof:placetype":"venue"
},
  "geometry": {"coordinates":[6.695661,53.212757],"type":"Point"}
}