{
  "type": "Feature",
  "properties": {
    "addr:full":"N Maesstr 25 Schagen Noord-Holland 1741 KP",
    "addr:housenumber":"25",
    "addr:postcode":"1741 kp",
    "addr:street":"N;Schagen",
    "iso:country":"NL",
    "sg:address":"N Maesstr 25",
    "sg:city":"Schagen",
    "sg:orig_category":"Verbouwingen",
    "sg:phone":"+31 224 296 050",
    "sg:postcode":"1741 KP",
    "sg:province":"Noord-Holland",
    "wof:name":"Plukker, F J L",
    "wof:placetype":"venue"
},
  "geometry": {"coordinates":[4.80148,52.793285],"type":"Point"}
}