{
  "type": "Feature",
  "properties": {
    "addr:full":"Nassaustraat 22 Bussum Noord-Holland 1404 CT",
    "addr:housenumber":"22",
    "addr:postcode":"1404 ct",
    "addr:street":"Nassaustraat",
    "iso:country":"NL",
    "sg:address":"Nassaustraat 22",
    "sg:city":"Bussum",
    "sg:classifiers":[
        {
            "category":"Shopping",
            "subcategory":"Clothing, Apparel, & Fashions",
            "type":"Retail Goods"
        }
    ],
    "sg:phone":"+31 35 691 0564",
    "sg:postcode":"1404 CT",
    "sg:province":"Noord-Holland",
    "sg:tags":[
        "ondergoed",
        "lingerie"
    ],
    "wof:name":"Rivo",
    "wof:placetype":"venue"
},
  "geometry": {"coordinates":[5.161548,52.27565],"type":"Point"}
}