{
  "type": "Feature",
  "properties": {
    "iso:country":"NL",
    "sg:address":"C Schuytstr 16",
    "sg:city":"Amsterdam",
    "sg:orig_category":"Onroerende Goederen",
    "sg:phone":"+31 20 679 7838",
    "sg:postcode":"1071 JH",
    "sg:province":"North Holland",
    "sg:website":"http://www.nieuwpoort.nl",
    "wof:name":"Nieuwpoort Van Hees, Van",
    "wof:placetype":"venue"
},
  "geometry": {"coordinates":[4.87084,52.355495],"type":"Point"}
}