{
  "type": "Feature",
  "properties": {
    "addr:full":"Plompetorengr 12 Utrecht Utrecht 3512 CD",
    "addr:housenumber":"12",
    "addr:postcode":"3512 cd",
    "addr:street":"Plompetorengr",
    "iso:country":"NL",
    "sg:address":"Plompetorengr 12",
    "sg:city":"Utrecht",
    "sg:orig_category":"Kinderopvang",
    "sg:phone":"+31 30 232 8441",
    "sg:postcode":"3512 CD",
    "sg:province":"Utrecht",
    "wof:name":"Blauwe Zwaan, De",
    "wof:placetype":"venue"
},
  "geometry": {"coordinates":[5.123276,52.095955],"type":"Point"}
}