{
  "type": "Feature",
  "properties": {
    "iso:country":"NL",
    "sg:address":"Oranjeweg 1",
    "sg:city":"Oosterbeek",
    "sg:orig_category":"Vakantiehuizen",
    "sg:phone":"+31 26 339 0322",
    "sg:postcode":"6861 BK",
    "sg:province":"Gelderland",
    "wof:name":"Ullver'S Bemiddelingen",
    "wof:placetype":"venue"
},
  "geometry": {"coordinates":[5.830887,51.98978],"type":"Point"}
}