{
  "type": "Feature",
  "properties": {
    "addr:full":"Benesserlaan 244 Uitgeest Noord-Holland 1911 VJ",
    "addr:housenumber":"244",
    "addr:postcode":"1911 vj",
    "addr:street":"Benesserlaan",
    "iso:country":"NL",
    "sg:address":"Benesserlaan 244",
    "sg:city":"Uitgeest",
    "sg:orig_category":"Loodgieterswerk, Verwarming And Sanitaire Installaties",
    "sg:phone":"+31 251 313 421",
    "sg:postcode":"1911 VJ",
    "sg:province":"Noord-Holland",
    "wof:name":"Pim",
    "wof:placetype":"venue"
},
  "geometry": {"coordinates":[4.707624,52.534191],"type":"Point"}
}