{
  "type": "Feature",
  "properties": {
    "iso:country":"NL",
    "sg:address":"Grotestr 84",
    "sg:city":"Tegelen",
    "sg:orig_category":"Fotoreportages",
    "sg:phone":"+31 77 373 2371",
    "sg:postcode":"5931 CX",
    "sg:province":"Limburg",
    "wof:name":"Heuijerjans, Ellen",
    "wof:placetype":"venue"
},
  "geometry": {"coordinates":[6.135597,51.342381],"type":"Point"}
}