{
  "type": "Feature",
  "properties": {
    "iso:country":"NL",
    "sg:address":"Postbus 91",
    "sg:city":"Voorthuizen",
    "sg:orig_category":"Omroep",
    "sg:phone":"+31 342 478 432",
    "sg:postcode":"3780 BB",
    "sg:province":"Gelderland",
    "wof:name":"Trans World Radio Ned",
    "wof:placetype":"venue"
},
  "geometry": {"coordinates":[5.60713,52.18708],"type":"Point"}
}