{
  "type": "Feature",
  "properties": {
    "addr:full":"Stadsring 191 Amersfoort Utrecht 3817 BA",
    "addr:housenumber":"191",
    "addr:postcode":"3817 ba",
    "addr:street":"Stadsring",
    "iso:country":"NL",
    "sg:address":"Stadsring 191",
    "sg:city":"Amersfoort",
    "sg:orig_category":"Pensioenen",
    "sg:phone":"+31 33 479 8798",
    "sg:postcode":"3817 BA",
    "sg:province":"Utrecht",
    "wof:name":"Stork",
    "wof:placetype":"venue"
},
  "geometry": {"coordinates":[5.392571,52.153076],"type":"Point"}
}