{
  "type": "Feature",
  "properties": {
    "addr:full":"Daalderwg 8 Zaandam North Holland 1507 DT",
    "addr:housenumber":"8",
    "addr:postcode":"1507 dt",
    "addr:street":"Daalderwg",
    "iso:country":"NL",
    "sg:address":"Daalderwg 8",
    "sg:city":"Zaandam",
    "sg:orig_category":"Verzekeringen - Verzekeringskantoren",
    "sg:phone":"+31 75 631 9380",
    "sg:postcode":"1507 DT",
    "sg:province":"North Holland",
    "sg:website":"http://www.smart-adviesgroep.nl",
    "wof:name":"Smart Bv",
    "wof:placetype":"venue"
},
  "geometry": {"coordinates":[4.791253,52.427547],"type":"Point"}
}