{
  "type": "Feature",
  "properties": {
    "iso:country":"NL",
    "sg:address":"Daalderwg 8",
    "sg:city":"Zaandam",
    "sg:orig_category":"Verzekeringen - Verzekeringskantoren",
    "sg:phone":"+31 75 631 9380",
    "sg:postcode":"1507 DT",
    "sg:province":"North Holland",
    "sg:website":"http://www.smart-adviesgroep.nl",
    "wof:name":"Smart Bv",
    "wof:placetype":"venue"
},
  "geometry": {"coordinates":[4.791253,52.427547],"type":"Point"}
}