{
  "type": "Feature",
  "properties": {
    "addr:full":"Stationsstr 62A Ermelo Gelderland 3851 NJ",
    "addr:housenumber":"62a",
    "addr:postcode":"3851",
    "addr:street":"Stationsstr;Gelderland",
    "iso:country":"NL",
    "sg:address":"Stationsstr 62A",
    "sg:city":"Ermelo",
    "sg:classifiers":[
        {
            "category":"Food & Beverages",
            "subcategory":"Bakery",
            "type":"Retail Goods"
        }
    ],
    "sg:phone":"+31 341 554 373",
    "sg:postcode":"3851 NJ",
    "sg:province":"Gelderland",
    "sg:tags":[
        "pizza"
    ],
    "wof:name":"Ritza",
    "wof:placetype":"venue"
},
  "geometry": {"coordinates":[5.62301,52.300282],"type":"Point"}
}