{
  "type": "Feature",
  "properties": {
    "addr:full":"Nagelerstraat 5 Emmeloord Flevoland 8301 XE",
    "addr:housenumber":"5",
    "addr:postcode":"8301 xe",
    "addr:street":"Nagelerstraat;Flevoland",
    "iso:country":"NL",
    "sg:address":"Nagelerstraat 5",
    "sg:city":"Emmeloord",
    "sg:orig_category":"Webdesign Bureaus",
    "sg:phone":"+31 527 617 004",
    "sg:postcode":"8301 XE",
    "sg:province":"Flevoland",
    "sg:website":"http://www.atlantisfuturemedia.nl",
    "wof:name":"Atlantis Future Media",
    "wof:placetype":"venue"
},
  "geometry": {"coordinates":[5.7541699409,52.7089996338],"type":"Point"}
}