{
  "type": "Feature",
  "properties": {
    "addr:full":"Simpelhuisstr 14 Middelburg Zeeland 4331 PH",
    "addr:housenumber":"14",
    "addr:postcode":"4331",
    "addr:street":"Simpelhuisstr",
    "iso:country":"NL",
    "sg:address":"Simpelhuisstr 14",
    "sg:city":"Middelburg",
    "sg:orig_category":"Schoonheidsinstituten",
    "sg:phone":"+31 118 674 493",
    "sg:postcode":"4331 PH",
    "sg:province":"Zeeland",
    "wof:name":"Marnel Jeras Skin Care",
    "wof:placetype":"venue"
},
  "geometry": {"coordinates":[3.609515,51.499046],"type":"Point"}
}