{
  "type": "Feature",
  "properties": {
    "addr:full":"Cabralstr 34 Amsterdam North Holland 1057 CH",
    "addr:housenumber":"34",
    "addr:postcode":"1057",
    "addr:street":"Cabralstr",
    "iso:country":"NL",
    "sg:address":"Cabralstr 34",
    "sg:city":"Amsterdam",
    "sg:classifiers":[
        {
            "category":"Food & Beverages",
            "subcategory":"Fruits & Vegetables",
            "type":"Retail Goods"
        }
    ],
    "sg:phone":"+31 20 616 4101",
    "sg:postcode":"1057 CH",
    "sg:province":"North Holland",
    "sg:tags":[
        "en",
        "groenten"
    ],
    "wof:name":"Anavatan",
    "wof:placetype":"venue"
},
  "geometry": {"coordinates":[4.852255,52.369331],"type":"Point"}
}