{
  "type": "Feature",
  "properties": {
    "addr:full":"Sluisje 12 Vreeland Utrecht 3633 AC",
    "addr:housenumber":"12",
    "addr:postcode":"3633 ac",
    "addr:street":"Sluisje;Vreeland",
    "iso:country":"NL",
    "sg:address":"Sluisje 12",
    "sg:city":"Vreeland",
    "sg:orig_category":"Diverse Bedrijfsinstallaties Gh",
    "sg:phone":"+31 294 234 278",
    "sg:postcode":"3633 AC",
    "sg:province":"Utrecht",
    "wof:name":"Albin-Nederland Bv",
    "wof:placetype":"venue"
},
  "geometry": {"coordinates":[-76.68330400000001,39.705425],"type":"Point"}
}