{
  "type": "Feature",
  "properties": {
    "addr:full":"Heersdk 9 Oirschot Noord-Brabant 5688 NW",
    "addr:housenumber":"9",
    "addr:postcode":"5688 nw",
    "addr:street":"Heersdk",
    "iso:country":"NL",
    "sg:address":"Heersdk 9",
    "sg:city":"Oirschot",
    "sg:orig_category":"Magazijninrichtingen",
    "sg:phone":"+31 499 575 258",
    "sg:postcode":"5688 NW",
    "sg:province":"Noord-Brabant",
    "wof:name":"Bresser Best Magazijninventaris",
    "wof:placetype":"venue"
},
  "geometry": {"coordinates":[5.337213,51.499805],"type":"Point"}
}