{
  "type": "Feature",
  "properties": {
    "iso:country":"NL",
    "sg:address":"Jonge Voolwg 12",
    "sg:city":"Wormerveer",
    "sg:orig_category":"Babyartikelen",
    "sg:phone":"+31 75 687 7122",
    "sg:postcode":"1521 RJ",
    "sg:province":"North Holland",
    "sg:website":"http://www.kidsjoy.nl",
    "wof:name":"Kidsjoy",
    "wof:placetype":"venue"
},
  "geometry": {"coordinates":[4.782914,52.507179],"type":"Point"}
}