{
  "type": "Feature",
  "properties": {
    "addr:full":"Albert Cuypstraat 58 Amsterdam Noord-Holland 1072 CV",
    "addr:housenumber":"58",
    "addr:postcode":"1072 cv",
    "addr:street":"Albert Cuypstraat",
    "iso:country":"NL",
    "sg:address":"Albert Cuypstraat 58",
    "sg:city":"Amsterdam",
    "sg:classifiers":[
        {
            "category":"Fast Food",
            "type":"Food & Drink"
        }
    ],
    "sg:phone":"+31 20 671 4930",
    "sg:postcode":"1072 CV",
    "sg:province":"Noord-Holland",
    "sg:tags":[
        "afhaal",
        "restaurant"
    ],
    "wof:name":"Cambodja City",
    "wof:placetype":"venue"
},
  "geometry": {"coordinates":[4.88957,52.354664],"type":"Point"}
}