{
  "type": "Feature",
  "properties": {
    "addr:full":"Langstraat 160 Wassenaar South Holland 2242 JZ",
    "addr:housenumber":"160",
    "addr:postcode":"2242 jz",
    "addr:street":"Langstraat",
    "iso:country":"NL",
    "sg:address":"Langstraat 160",
    "sg:city":"Wassenaar",
    "sg:orig_category":"Huishoudapparatuur, Televisies And Radio'S",
    "sg:phone":"+31 70 511 5101",
    "sg:postcode":"2242 JZ",
    "sg:province":"South Holland",
    "wof:name":"Odemaere Radio En Televisie",
    "wof:placetype":"venue"
},
  "geometry": {"coordinates":[4.395205,52.142815],"type":"Point"}
}