{
  "type": "Feature",
  "properties": {
    "addr:full":"Julianastraat 68 Hoogkarspel Noord-Holland 1616 CL",
    "addr:housenumber":"68",
    "addr:postcode":"1616",
    "addr:street":"Julianastraat",
    "iso:country":"NL",
    "sg:address":"Julianastraat 68",
    "sg:city":"Hoogkarspel",
    "sg:orig_category":"Meubelzaken, Woning- And Keukeninrichting",
    "sg:phone":"+31 228 567 525",
    "sg:postcode":"1616 CL",
    "sg:province":"Noord-Holland",
    "wof:name":"Janze Zitmeubelhoezen",
    "wof:placetype":"venue"
},
  "geometry": {"coordinates":[5.181287,52.691135],"type":"Point"}
}