{
  "type": "Feature",
  "properties": {
    "addr:full":"Koraalrood 28 Zoetermeer South Holland 2718 SC",
    "addr:housenumber":"28",
    "addr:postcode":"2718 sc",
    "addr:street":"Koraalrood",
    "iso:country":"NL",
    "sg:address":"Koraalrood 28",
    "sg:city":"Zoetermeer",
    "sg:orig_category":"Accountants - Administratie- Consulenten En -Kantoren",
    "sg:phone":"+31 79 331 5545",
    "sg:postcode":"2718 SC",
    "sg:province":"South Holland",
    "wof:name":"Duijnisveld Bv",
    "wof:placetype":"venue"
},
  "geometry": {"coordinates":[4.502669,52.040886],"type":"Point"}
}