{
  "type": "Feature",
  "properties": {
    "addr:full":"Menninckstraat 4 'S Gravenhage Zuid-Holland 2583 BR",
    "addr:housenumber":"4 '",
    "addr:postcode":"2583 br",
    "addr:street":"Menninckstraat",
    "iso:country":"NL",
    "sg:address":"Menninckstraat 4",
    "sg:city":"'S Gravenhage",
    "sg:orig_category":"Hout Gh",
    "sg:phone":"+31 70 358 9092",
    "sg:postcode":"2583 BR",
    "sg:province":"Zuid-Holland",
    "wof:name":"Hout Van Wout",
    "wof:placetype":"venue"
},
  "geometry": {"coordinates":[4.26787,52.095291],"type":"Point"}
}