{
  "type": "Feature",
  "properties": {
    "addr:full":"Sportstraat 50 Roosendaal North Brabant 4708 AT",
    "addr:housenumber":"50",
    "addr:postcode":"4708",
    "addr:street":"Sportstraat",
    "iso:country":"NL",
    "sg:address":"Sportstraat 50",
    "sg:city":"Roosendaal",
    "sg:orig_category":"Kinderopvang Behalve Thuis",
    "sg:phone":"+31 165 557 175",
    "sg:postcode":"4708 AT",
    "sg:province":"North Brabant",
    "wof:name":"Kinderdagverblijf Dribbel",
    "wof:placetype":"venue"
},
  "geometry": {"coordinates":[4.441744,51.527485],"type":"Point"}
}