{
  "type": "Feature",
  "properties": {
    "addr:full":"Ringdijk 396 Ridderkerk South Holland 2983 GS",
    "addr:housenumber":"396",
    "addr:postcode":"2983 gs",
    "addr:street":"Ringdijk",
    "iso:country":"NL",
    "sg:address":"Ringdijk 396",
    "sg:city":"Ridderkerk",
    "sg:orig_category":"Verhuur Bouwmachines",
    "sg:phone":"+31 180 418 209",
    "sg:postcode":"2983 GS",
    "sg:province":"South Holland",
    "wof:name":"Altena Electrotechnisch Bedrijf",
    "wof:placetype":"venue"
},
  "geometry": {"coordinates":[4.615753,51.8853],"type":"Point"}
}