{
  "type": "Feature",
  "properties": {
    "addr:full":"Quadoelenwg 27A Oosterwolde Fr Friesland 8431 LN",
    "addr:housenumber":"27a",
    "addr:postcode":"8431 ln",
    "addr:street":"Quadoelenwg",
    "iso:country":"NL",
    "sg:address":"Quadoelenwg 27A",
    "sg:city":"Oosterwolde Fr",
    "sg:orig_category":"Schilders",
    "sg:phone":"+31 516 514 002",
    "sg:postcode":"8431 LN",
    "sg:province":"Friesland",
    "wof:name":"Schildersgilde Friesland Bv",
    "wof:placetype":"venue"
},
  "geometry": {"coordinates":[6.290361,52.991653],"type":"Point"}
}