{
  "type": "Feature",
  "properties": {
    "addr:full":"Iepenln 40 Eindhoven Noord-Brabant 5616 NS",
    "addr:housenumber":"40",
    "addr:postcode":"5616 ns",
    "addr:street":"Iepenln",
    "iso:country":"NL",
    "sg:address":"Iepenln 40",
    "sg:city":"Eindhoven",
    "sg:orig_category":"Verenigingsgebouwen",
    "sg:phone":"+31 40 251 4675",
    "sg:postcode":"5616 NS",
    "sg:province":"Noord-Brabant",
    "wof:name":"Bellefort, 'T",
    "wof:placetype":"venue"
},
  "geometry": {"coordinates":[5.461528,51.440788],"type":"Point"}
}