{
  "type": "Feature",
  "properties": {
    "addr:full":"Kerklaan 19 Ermelo Gelderland 3851 JV",
    "addr:housenumber":"19",
    "addr:postcode":"3851 jv",
    "addr:street":"Kerklaan;Gelderland",
    "iso:country":"NL",
    "sg:address":"Kerklaan 19",
    "sg:city":"Ermelo",
    "sg:orig_category":"Kappers",
    "sg:phone":"+31 341 553 296",
    "sg:postcode":"3851 JV",
    "sg:province":"Gelderland",
    "wof:name":"Dameskapsalon Lisette",
    "wof:placetype":"venue"
},
  "geometry": {"coordinates":[5.6158480644,52.2984924316],"type":"Point"}
}