{
  "type": "Feature",
  "properties": {
    "addr:full":"Professor Molkenboerstr 20 Nijmegen Gelderland 6524 RP",
    "addr:housenumber":"20",
    "addr:postcode":"6524",
    "addr:street":"Professor Molkenboerstr;Gelderland",
    "iso:country":"NL",
    "sg:address":"Professor Molkenboerstr 20",
    "sg:city":"Nijmegen",
    "sg:orig_category":"Kappers",
    "sg:phone":"+31 24 322 1016",
    "sg:postcode":"6524 RP",
    "sg:province":"Gelderland",
    "wof:name":"Johnny'S Hairstyling",
    "wof:placetype":"venue"
},
  "geometry": {"coordinates":[5.8679847717,51.8300590515],"type":"Point"}
}