{
  "type": "Feature",
  "properties": {
    "addr:full":"Puntenburgerln 102 Amersfoort Utrecht 3812 CG",
    "addr:housenumber":"102",
    "addr:postcode":"3812 cg",
    "iso:country":"NL",
    "sg:address":"Puntenburgerln 102",
    "sg:city":"Amersfoort",
    "sg:orig_category":"Kappers",
    "sg:phone":"+31 33 465 6490",
    "sg:postcode":"3812 CG",
    "sg:province":"Utrecht",
    "wof:name":"Puntenburg",
    "wof:placetype":"venue"
},
  "geometry": {"coordinates":[5.375137,52.158394],"type":"Point"}
}