{
  "type": "Feature",
  "properties": {
    "addr:full":"Kl Brabant 49 Vught North Brabant 5262 RL",
    "addr:housenumber":"49",
    "addr:postcode":"5262 rl",
    "addr:street":"Brabant",
    "iso:country":"NL",
    "sg:address":"Kl Brabant 49",
    "sg:city":"Vught",
    "sg:orig_category":"Schoonheidsinstituten",
    "sg:phone":"+31 73 656 7995",
    "sg:postcode":"5262 RL",
    "sg:province":"North Brabant",
    "wof:name":"Wolfs-De Gruijter, D H M",
    "wof:placetype":"venue"
},
  "geometry": {"coordinates":[5.293801,51.637871],"type":"Point"}
}