{
  "type": "Feature",
  "properties": {
    "iso:country":"NL",
    "sg:address":"Marktstr 10",
    "sg:city":"Meppel",
    "sg:orig_category":"Zalenverhuur",
    "sg:phone":"+31 522 251 185",
    "sg:postcode":"7941 KR",
    "sg:province":"Drenthe",
    "wof:name":"Markthal",
    "wof:placetype":"venue"
},
  "geometry": {"coordinates":[6.195799,52.697826],"type":"Point"}
}