{
  "type": "Feature",
  "properties": {
    "addr:full":"Billitonstraat 37 Enschede Overijssel 7512 BT",
    "addr:housenumber":"37",
    "addr:postcode":"7512 bt",
    "addr:street":"Billitonstraat",
    "iso:country":"NL",
    "sg:address":"Billitonstraat 37",
    "sg:city":"Enschede",
    "sg:orig_category":"Goederenvervoer Over De Weg",
    "sg:phone":"+31 53 434 2106",
    "sg:postcode":"7512 BT",
    "sg:province":"Overijssel",
    "wof:name":"Vermeer Internationale Transporten",
    "wof:placetype":"venue"
},
  "geometry": {"coordinates":[6.894017,52.212471],"type":"Point"}
}