{
  "type": "Feature",
  "properties": {
    "addr:full":"August Allebeplein 20 Amsterdam Noord-Holland 1062 AC",
    "addr:housenumber":"20",
    "addr:postcode":"1062 ac",
    "iso:country":"NL",
    "sg:address":"August Allebeplein 20",
    "sg:city":"Amsterdam",
    "sg:orig_category":"Kappers",
    "sg:phone":"+31 20 615 4404",
    "sg:postcode":"1062 AC",
    "sg:province":"Noord-Holland",
    "wof:name":"Snijders Coiffures",
    "wof:placetype":"venue"
},
  "geometry": {"coordinates":[4.837432,52.363659],"type":"Point"}
}