{
  "type": "Feature",
  "properties": {
    "addr:full":"Baaneweer 4 Sliedrecht South Holland 3363 XA",
    "addr:housenumber":"4",
    "addr:postcode":"3363 xa",
    "addr:street":"Baaneweer",
    "iso:country":"NL",
    "sg:address":"Baaneweer 4",
    "sg:city":"Sliedrecht",
    "sg:orig_category":"Verenigingen En Stichtingen",
    "sg:phone":"+31 184 419 650",
    "sg:postcode":"3363 XA",
    "sg:province":"South Holland",
    "wof:name":"Lotuskring Zuid-Holland Oost",
    "wof:placetype":"venue"
},
  "geometry": {"coordinates":[4.752023,51.827278],"type":"Point"}
}