{
  "type": "Feature",
  "properties": {
    "iso:country":"NL",
    "sg:address":"Dordtsestraatweg 69",
    "sg:city":"Rotterdam",
    "sg:orig_category":"Loodgieterswerk, Verwarming And Sanitaire Installaties",
    "sg:phone":"+31 10 486 6398",
    "sg:postcode":"3083 AD",
    "sg:province":"Zuid-Holland",
    "wof:name":"P.M. Eijfferts",
    "wof:placetype":"venue"
},
  "geometry": {"coordinates":[4.497291,51.887272],"type":"Point"}
}