{
  "type": "Feature",
  "properties": {
    "addr:full":"Pr Bernhardln 191 Veenendaal Utrecht 3905 JC",
    "addr:housenumber":"191",
    "addr:postcode":"3905 jc",
    "iso:country":"NL",
    "sg:address":"Pr Bernhardln 191",
    "sg:city":"Veenendaal",
    "sg:orig_category":"Verzekeringen - Verzekeringskantoren",
    "sg:phone":"+31 318 519 055",
    "sg:postcode":"3905 JC",
    "sg:province":"Utrecht",
    "wof:name":"Doesburg Bv, Van",
    "wof:placetype":"venue"
},
  "geometry": {"coordinates":[5.55418,52.024902],"type":"Point"}
}