{
  "type": "Feature",
  "properties": {
    "addr:full":"Virulypln 15 Rotterdam Zuid-Holland 3022 ZJ",
    "addr:housenumber":"15",
    "addr:postcode":"3022 zj",
    "addr:street":"Virulypln",
    "iso:country":"NL",
    "sg:address":"Virulypln 15",
    "sg:city":"Rotterdam",
    "sg:orig_category":"Verlichting",
    "sg:phone":"+31 10 244 9979",
    "sg:postcode":"3022 ZJ",
    "sg:province":"Zuid-Holland",
    "wof:name":"Quack & Compagnon",
    "wof:placetype":"venue"
},
  "geometry": {"coordinates":[4.451166,51.919979],"type":"Point"}
}