{
  "type": "Feature",
  "properties": {
    "addr:full":"Geertruidenbergp 26 Arnhem Gelderland 6844 DM",
    "addr:housenumber":"26",
    "addr:postcode":"6844 dm",
    "addr:street":"Geertruidenbergp",
    "iso:country":"NL",
    "sg:address":"Geertruidenbergp 26",
    "sg:city":"Arnhem",
    "sg:orig_category":"Graniet-, Granito- En Terrazzowerken",
    "sg:phone":"+31 26 389 1434",
    "sg:postcode":"6844 DM",
    "sg:province":"Gelderland",
    "sg:website":"http://www.granito-terrazzo.nl",
    "wof:name":"Mendels Terrazzo",
    "wof:placetype":"venue"
},
  "geometry": {"coordinates":[5.854564,51.948479],"type":"Point"}
}