{
  "type": "Feature",
  "properties": {
    "addr:full":"Buitendraaiery 33 Amsterdam Noord-Holland 1021 NM",
    "addr:housenumber":"33",
    "addr:postcode":"1021",
    "addr:street":"Buitendraaiery",
    "iso:country":"NL",
    "sg:address":"Buitendraaiery 33",
    "sg:city":"Amsterdam",
    "sg:orig_category":"Beeldende Kunstenaars",
    "sg:phone":"+31 20 634 3513",
    "sg:postcode":"1021 NM",
    "sg:province":"Noord-Holland",
    "wof:name":"Heesters, J M",
    "wof:placetype":"venue"
},
  "geometry": {"coordinates":[4.915884,52.381889],"type":"Point"}
}