{
  "type": "Feature",
  "properties": {
    "addr:full":"Nettelhorst 68 Ede Gld Gelderland 6714 ME",
    "addr:housenumber":"68",
    "addr:postcode":"6714 me",
    "addr:street":"Nettelhorst;Gld Gelderland",
    "iso:country":"NL",
    "sg:address":"Nettelhorst 68",
    "sg:city":"Ede Gld",
    "sg:orig_category":"Binnenhuisarchitectuur",
    "sg:phone":"+31 318 621 130",
    "sg:postcode":"6714 ME",
    "sg:province":"Gelderland",
    "wof:name":"Boeve, G",
    "wof:placetype":"venue"
},
  "geometry": {"coordinates":[5.637532,52.047626],"type":"Point"}
}