{
  "type": "Feature",
  "properties": {
    "addr:full":"Thornerweg 2 Wessem Limburg 6019 CA",
    "addr:housenumber":"2",
    "addr:postcode":"6019 ca",
    "addr:street":"Thornerweg",
    "iso:country":"NL",
    "sg:address":"Thornerweg 2",
    "sg:city":"Wessem",
    "sg:orig_category":"Kinderopvang Behalve Thuis",
    "sg:phone":"+31 475 562 727",
    "sg:postcode":"6019 CA",
    "sg:province":"Limburg",
    "wof:name":"Medisch Kleuterdagverblijf 'T Brogske",
    "wof:placetype":"venue"
},
  "geometry": {"coordinates":[5.878132,51.160892],"type":"Point"}
}