{
  "type": "Feature",
  "properties": {
    "iso:country":"NL",
    "sg:address":"Raadhuisstr 2",
    "sg:city":"Waspik",
    "sg:orig_category":"Postkantoren",
    "sg:phone":"+31 416 311 225",
    "sg:postcode":"5165 CH",
    "sg:province":"Noord-Brabant",
    "sg:website":"http://www.postkantoor.nl",
    "wof:name":"Postkantoor",
    "wof:placetype":"venue"
},
  "geometry": {"coordinates":[8.22414,46.813091],"type":"Point"}
}