{
  "type": "Feature",
  "properties": {
    "addr:full":"Maaskantje 50 Den Dungen Noord-Brabant 5271 XH",
    "addr:housenumber":"50",
    "addr:postcode":"5271 xh",
    "addr:street":"Maaskantje",
    "iso:country":"NL",
    "sg:address":"Maaskantje 50",
    "sg:city":"Den Dungen",
    "sg:orig_category":"Verhuur Audiovisuele Apparatuur",
    "sg:phone":"+31 73 594 1830",
    "sg:postcode":"5271 XH",
    "sg:province":"Noord-Brabant",
    "wof:name":"Trax Licht En Geluidstechniek",
    "wof:placetype":"venue"
},
  "geometry": {"coordinates":[5.35092,51.638424],"type":"Point"}
}