{
  "type": "Feature",
  "properties": {
    "addr:full":"Postbus 6537 Nymegen Gelderland 6503 GA",
    "addr:housenumber":"6537",
    "addr:postcode":"6503 ga",
    "addr:street":"Postbus;Gelderland",
    "iso:country":"NL",
    "sg:address":"Postbus 6537",
    "sg:city":"Nymegen",
    "sg:orig_category":"Psychologen",
    "sg:phone":"+31 481 465 565",
    "sg:postcode":"6503 GA",
    "sg:province":"Gelderland",
    "wof:name":"Psych Expertisebureau Nijmegen",
    "wof:placetype":"venue"
},
  "geometry": {"coordinates":[-83.222931,32.678131],"type":"Point"}
}