{
  "type": "Feature",
  "properties": {
    "addr:full":"Weenahof 10 Amsterdam Noord-Holland 1083 JE",
    "addr:housenumber":"10",
    "addr:postcode":"1083 je",
    "addr:street":"Weenahof",
    "iso:country":"NL",
    "sg:address":"Weenahof 10",
    "sg:city":"Amsterdam",
    "sg:orig_category":"Adviesbureaus Bedrijfsorganisatie",
    "sg:phone":"+31 20 644 6016",
    "sg:postcode":"1083 JE",
    "sg:province":"Noord-Holland",
    "wof:name":"Mijnders",
    "wof:placetype":"venue"
},
  "geometry": {"coordinates":[4.882505,52.33382],"type":"Point"}
}