{
  "type": "Feature",
  "properties": {
    "addr:full":"Vd Parrastr 44 S Gravenhage South Holland 2595 RB",
    "addr:housenumber":"44",
    "addr:postcode":"2595 rb",
    "addr:street":"S Gravenhage",
    "iso:country":"NL",
    "sg:address":"Vd Parrastr 44",
    "sg:city":"S Gravenhage",
    "sg:orig_category":"Poppen En Poppenhuismaterialen",
    "sg:phone":"+31 70 347 4820",
    "sg:postcode":"2595 RB",
    "sg:province":"South Holland",
    "wof:name":"Bernie",
    "wof:placetype":"venue"
},
  "geometry": {"coordinates":[4.33507,52.081421],"type":"Point"}
}