{
  "type": "Feature",
  "properties": {
    "addr:full":"Bevrydingspln 42 Leiden Zuid-Holland 2321 BX",
    "addr:housenumber":"42",
    "addr:postcode":"2321 bx",
    "addr:street":"Bevrydingspln",
    "iso:country":"NL",
    "sg:address":"Bevrydingspln 42",
    "sg:city":"Leiden",
    "sg:orig_category":"Kappers",
    "sg:phone":"+31 71 528 1404",
    "sg:postcode":"2321 BX",
    "sg:province":"Zuid-Holland",
    "wof:name":"Euro Hair",
    "wof:placetype":"venue"
},
  "geometry": {"coordinates":[4.4767827988,52.1469230652],"type":"Point"}
}