{
  "type": "Feature",
  "properties": {
    "addr:full":"Paramasiebaan 13 Ameide Zuid-Holland 4233 EX",
    "addr:housenumber":"13",
    "addr:postcode":"4233 ex",
    "addr:street":"Paramasiebaan",
    "iso:country":"NL",
    "sg:address":"Paramasiebaan 13",
    "sg:city":"Ameide",
    "sg:orig_category":"Banken",
    "sg:phone":"+31 184 667 788",
    "sg:postcode":"4233 EX",
    "sg:province":"Zuid-Holland",
    "sg:website":"http://www.rabobank.nl",
    "wof:name":"Rabobank",
    "wof:placetype":"venue"
},
  "geometry": {"coordinates":[4.961535,51.955288],"type":"Point"}
}