{
  "type": "Feature",
  "properties": {
    "iso:country":"NL",
    "sg:address":"Postbus 449",
    "sg:city":"Schiedam",
    "sg:orig_category":"Adviesbureaus Bouwkunde",
    "sg:phone":"+31 10 462 1895",
    "sg:postcode":"3100 AK",
    "sg:province":"Zuid-Holland",
    "wof:name":"Keemink Vastgoed Inspectarium Bv",
    "wof:placetype":"venue"
},
  "geometry": {"coordinates":[4.39816,51.918449],"type":"Point"}
}