{
  "type": "Feature",
  "properties": {
    "addr:full":"Graafseweg 145 'S Hertogenbosch Noord-Brabant 5213 AD",
    "addr:housenumber":"145 ' s",
    "addr:postcode":"5213 ad",
    "addr:street":"Graafseweg",
    "iso:country":"NL",
    "sg:address":"Graafseweg 145",
    "sg:city":"'S Hertogenbosch",
    "sg:classifiers":[
        {
            "category":"Fast Food",
            "type":"Food & Drink"
        }
    ],
    "sg:phone":"+31 73 614 5578",
    "sg:postcode":"5213 AD",
    "sg:province":"Noord-Brabant",
    "sg:tags":[
        "afhaal",
        "restaurant"
    ],
    "wof:name":"Da Lino",
    "wof:placetype":"venue"
},
  "geometry": {"coordinates":[5.322993,51.694794],"type":"Point"}
}