{
  "type": "Feature",
  "properties": {
    "addr:full":"Postbus 56941 Amsterdam Gelderland 1040 AX",
    "addr:housenumber":"56941",
    "addr:postcode":"1040 ax",
    "addr:street":"Postbus",
    "iso:country":"NL",
    "sg:address":"Postbus 56941",
    "sg:city":"Amsterdam",
    "sg:orig_category":"Hulpverlening Sociaal",
    "sg:phone":"+31 20 688 5272",
    "sg:postcode":"1040 AX",
    "sg:province":"Gelderland",
    "wof:name":"Koerdische Rode Halve Maan Nederland",
    "wof:placetype":"venue"
},
  "geometry": {"coordinates":[4.89205,52.37355],"type":"Point"}
}