{
  "type": "Feature",
  "properties": {
    "iso:country":"NL",
    "sg:address":"Postbus 56941",
    "sg:city":"Amsterdam",
    "sg:orig_category":"Hulpverlening Sociaal",
    "sg:phone":"+31 20 688 5272",
    "sg:postcode":"1040 AX",
    "sg:province":"Gelderland",
    "wof:name":"Koerdische Rode Halve Maan Nederland",
    "wof:placetype":"venue"
},
  "geometry": {"coordinates":[4.89205,52.37355],"type":"Point"}
}