{
  "type": "Feature",
  "properties": {
    "iso:country":"NL",
    "sg:address":"Dukdalf 1B",
    "sg:city":"Wyk By Duurstede",
    "sg:orig_category":"Kunstgebitten",
    "sg:phone":"+31 343 578 787",
    "sg:postcode":"3961 LA",
    "sg:province":"Utrecht",
    "sg:website":"http://www.ont.nl",
    "wof:name":"Engelbrecht",
    "wof:placetype":"venue"
},
  "geometry": {"coordinates":[5.327503,51.973885],"type":"Point"}
}