{
  "type": "Feature",
  "properties": {
    "addr:full":"Eikerplein 3 Kerkrade Limburg 6465 BS",
    "addr:housenumber":"3",
    "addr:postcode":"6465 bs",
    "addr:street":"Eikerplein",
    "iso:country":"NL",
    "sg:address":"Eikerplein 3",
    "sg:city":"Kerkrade",
    "sg:classifiers":[
        {
            "category":"Fast Food",
            "type":"Food & Drink"
        }
    ],
    "sg:phone":"+31 45 541 5777",
    "sg:postcode":"6465 BS",
    "sg:province":"Limburg",
    "sg:tags":[
        "afhaal",
        "restaurant"
    ],
    "wof:name":"Friture De Gracht",
    "wof:placetype":"venue"
},
  "geometry": {"coordinates":[6.022593,50.849869],"type":"Point"}
}