{
  "type": "Feature",
  "properties": {
    "addr:full":"Awg 13 Groningen Groningen 9718 CT",
    "addr:housenumber":"13",
    "addr:postcode":"9718 ct",
    "addr:street":"Awg",
    "iso:country":"NL",
    "sg:address":"Awg 13",
    "sg:city":"Groningen",
    "sg:orig_category":"Kantoor- En Secretariaatsservice",
    "sg:phone":"+31 50 850 8000",
    "sg:postcode":"9718 CT",
    "sg:province":"Groningen",
    "sg:website":"http://www.alterego.nl",
    "wof:name":"Alter Ego",
    "wof:placetype":"venue"
},
  "geometry": {"coordinates":[6.5747151375,53.2171440125],"type":"Point"}
}