{
  "type": "Feature",
  "properties": {
    "addr:full":"Meteorenstraat 94 Emmeloord Flevoland 8303 BB",
    "addr:housenumber":"94",
    "addr:postcode":"8303 bb",
    "addr:street":"Meteorenstraat;Flevoland",
    "iso:country":"NL",
    "sg:address":"Meteorenstraat 94",
    "sg:city":"Emmeloord",
    "sg:orig_category":"Verhuur Diversen",
    "sg:phone":"+31 527 619 194",
    "sg:postcode":"8303 BB",
    "sg:province":"Flevoland",
    "wof:name":"Fs Lighting",
    "wof:placetype":"venue"
},
  "geometry": {"coordinates":[5.737572,52.7033],"type":"Point"}
}