{
  "type": "Feature",
  "properties": {
    "addr:full":"Voorstr 21 Fynaart Noord-Brabant 4793 ET",
    "addr:housenumber":"21",
    "addr:postcode":"4793 et",
    "addr:street":"Voorstr",
    "iso:country":"NL",
    "sg:address":"Voorstr 21",
    "sg:city":"Fynaart",
    "sg:orig_category":"Drogisterijen",
    "sg:phone":"+31 168 462 443",
    "sg:postcode":"4793 ET",
    "sg:province":"Noord-Brabant",
    "wof:name":"Da",
    "wof:placetype":"venue"
},
  "geometry": {"coordinates":[4.46705,51.635269],"type":"Point"}
}