{
  "type": "Feature",
  "properties": {
    "iso:country":"NL",
    "sg:address":"Voorstr 21",
    "sg:city":"Fynaart",
    "sg:orig_category":"Drogisterijen",
    "sg:phone":"+31 168 462 443",
    "sg:postcode":"4793 ET",
    "sg:province":"Noord-Brabant",
    "wof:name":"Da",
    "wof:placetype":"venue"
},
  "geometry": {"coordinates":[4.46705,51.635269],"type":"Point"}
}