{
  "type": "Feature",
  "properties": {
    "iso:country":"NL",
    "sg:address":"Zuidbroek 177",
    "sg:city":"Bergambacht",
    "sg:orig_category":"Timmerwerken",
    "sg:phone":"+31 182 367 575",
    "sg:postcode":"2861 LL",
    "sg:province":"Zuid-Holland",
    "wof:name":"Slingerland Timmerbedrijf",
    "wof:placetype":"venue"
},
  "geometry": {"coordinates":[4.718951,51.936115],"type":"Point"}
}