{
  "type": "Feature",
  "properties": {
    "addr:full":"Havenstraat 17 Nijkerk Gld Gelderland 3861 VS",
    "addr:housenumber":"17",
    "addr:postcode":"3861",
    "addr:street":"Havenstraat;Gld Gelderland",
    "iso:country":"NL",
    "sg:address":"Havenstraat 17",
    "sg:city":"Nijkerk Gld",
    "sg:orig_category":"Makelaars In Onroerend Goed",
    "sg:phone":"+31 33 245 4242",
    "sg:postcode":"3861 VS",
    "sg:province":"Gelderland",
    "wof:name":"Assurantiekantoor Aart Van De Bor",
    "wof:placetype":"venue"
},
  "geometry": {"coordinates":[5.476898,52.225792],"type":"Point"}
}