{
  "type": "Feature",
  "properties": {
    "iso:country":"NL",
    "sg:address":"Ospelsewg 4",
    "sg:city":"Nederweert",
    "sg:orig_category":"Verloskundigen",
    "sg:phone":"+31 495 633 920",
    "sg:postcode":"6031 AK",
    "sg:province":"Limburg",
    "wof:name":"El Haddad, B",
    "wof:placetype":"venue"
},
  "geometry": {"coordinates":[5.758093,51.284039],"type":"Point"}
}