{
  "type": "Feature",
  "properties": {
    "addr:full":"Emdenmeen 24 Harderwijk Gelderland 3844 EC",
    "addr:housenumber":"24",
    "addr:postcode":"3844 ec",
    "addr:street":"Emdenmeen;Gelderland",
    "iso:country":"NL",
    "sg:address":"Emdenmeen 24",
    "sg:city":"Harderwijk",
    "sg:orig_category":"Verzekeringen",
    "sg:phone":"+31 341 414 658",
    "sg:postcode":"3844 EC",
    "sg:province":"Gelderland",
    "wof:name":"G.A.L. Moossdorff",
    "wof:placetype":"venue"
},
  "geometry": {"coordinates":[5.612692,52.343254],"type":"Point"}
}