{
  "type": "Feature",
  "properties": {
    "addr:full":"Boxtelsewg 45 Liempde Noord-Brabant 5298 VA",
    "addr:housenumber":"45",
    "addr:postcode":"5298",
    "addr:street":"Boxtelsewg",
    "iso:country":"NL",
    "sg:address":"Boxtelsewg 45",
    "sg:city":"Liempde",
    "sg:orig_category":"Kappers",
    "sg:phone":"+31 411 631 996",
    "sg:postcode":"5298 VA",
    "sg:province":"Noord-Brabant",
    "wof:name":"Peijnenburg, M",
    "wof:placetype":"venue"
},
  "geometry": {"coordinates":[5.36649,51.5746],"type":"Point"}
}