{
  "type": "Feature",
  "properties": {
    "addr:full":"Fazantstr 175 Enschede Overijssel 7523 DP",
    "addr:housenumber":"175",
    "addr:postcode":"7523 dp",
    "iso:country":"NL",
    "sg:address":"Fazantstr 175",
    "sg:city":"Enschede",
    "sg:classifiers":[
        {
            "category":"Farming",
            "subcategory":"Fish & Marine Products",
            "type":"Manufacturing & Wholesale Goods"
        }
    ],
    "sg:phone":"+31 53 433 0647",
    "sg:postcode":"7523 DP",
    "sg:province":"Overijssel",
    "sg:tags":[
        "vi"
    ],
    "wof:name":"Brandaris, De",
    "wof:placetype":"venue"
},
  "geometry": {"coordinates":[6.890205,52.235012],"type":"Point"}
}