{
  "type": "Feature",
  "properties": {
    "iso:country":"NL",
    "sg:address":"Honingerdijk 35",
    "sg:city":"Rotterdam",
    "sg:orig_category":"Advocaten And Juridische Adviseurs",
    "sg:phone":"+31 10 452 3204",
    "sg:postcode":"3063 AJ",
    "sg:province":"Zuid-Holland",
    "wof:name":"Advocatenkantoor Mr. G. Laurman",
    "wof:placetype":"venue"
},
  "geometry": {"coordinates":[4.51762,51.917252],"type":"Point"}
}