{
  "type": "Feature",
  "properties": {
    "addr:full":"Weerdingerkan Nz 48 Nieuw Weerdinge Drenthe 7831 HD",
    "addr:housenumber":"48",
    "addr:postcode":"7831 hd",
    "addr:street":"Nz;Nieuw Weerdinge",
    "iso:country":"NL",
    "sg:address":"Weerdingerkan Nz 48",
    "sg:city":"Nieuw Weerdinge",
    "sg:orig_category":"Hek- En Rasterwerken",
    "sg:phone":"+31 591 352 186",
    "sg:postcode":"7831 HD",
    "sg:province":"Drenthe",
    "sg:website":"http://www.home.wanadoo.nl/l.vander.heide/index.html",
    "wof:name":"Heide, Siersmederij V/D",
    "wof:placetype":"venue"
},
  "geometry": {"coordinates":[6.961288,52.847679],"type":"Point"}
}