{
  "type": "Feature",
  "properties": {
    "addr:full":"Mauritslaan 42 Poeldijk Zuid-Holland 2685 VA",
    "addr:housenumber":"42",
    "addr:postcode":"2685",
    "addr:street":"Mauritslaan",
    "iso:country":"NL",
    "sg:address":"Mauritslaan 42",
    "sg:city":"Poeldijk",
    "sg:orig_category":"Metaalwerken",
    "sg:phone":"+31 174 247 097",
    "sg:postcode":"2685 VA",
    "sg:province":"Zuid-Holland",
    "wof:name":"J Greeve",
    "wof:placetype":"venue"
},
  "geometry": {"coordinates":[4.216464,52.025707],"type":"Point"}
}