{
  "type": "Feature",
  "properties": {
    "addr:full":"Peschstr 43 Geleen Limburg 6166 CS",
    "addr:housenumber":"43",
    "addr:postcode":"6166 cs",
    "addr:street":"Peschstr",
    "iso:country":"NL",
    "sg:address":"Peschstr 43",
    "sg:city":"Geleen",
    "sg:orig_category":"Bloemen En Planten",
    "sg:phone":"+31 46 474 7249",
    "sg:postcode":"6166 CS",
    "sg:province":"Limburg",
    "wof:name":"Loos, Harry",
    "wof:placetype":"venue"
},
  "geometry": {"coordinates":[5.842088,50.970676],"type":"Point"}
}