{
  "type": "Feature",
  "properties": {
    "addr:full":"Klein Dorregeest 4 Akersloot Noord-Holland 1921 HA",
    "addr:housenumber":"4",
    "addr:postcode":"1921 ha",
    "addr:street":"Klein Dorregeest",
    "iso:country":"NL",
    "sg:address":"Klein Dorregeest 4",
    "sg:city":"Akersloot",
    "sg:orig_category":"Artiesten",
    "sg:phone":"+31 251 312 092",
    "sg:postcode":"1921 HA",
    "sg:province":"Noord-Holland",
    "wof:name":"P. Zonneveld",
    "wof:placetype":"venue"
},
  "geometry": {"coordinates":[4.72576,52.54747],"type":"Point"}
}