{
  "type": "Feature",
  "properties": {
    "addr:full":"T Sant 12 Wijk Bij Duurstede Utrecht 3962 TB",
    "addr:housenumber":"12",
    "addr:postcode":"3962 tb",
    "addr:street":"T Sant",
    "iso:country":"NL",
    "sg:address":"T Sant 12",
    "sg:city":"Wijk Bij Duurstede",
    "sg:orig_category":"Paramedische Behandelingen",
    "sg:phone":"+31 343 591 174",
    "sg:postcode":"3962 TB",
    "sg:province":"Utrecht",
    "wof:name":"J M Van Olphen-Van Mervennee",
    "wof:placetype":"venue"
},
  "geometry": {"coordinates":[5.348871,51.977921],"type":"Point"}
}