{
  "type": "Feature",
  "properties": {
    "addr:full":"Zandhei 44 Veldhoven Noord-Brabant 5508 WT",
    "addr:housenumber":"44",
    "addr:postcode":"5508 wt",
    "addr:street":"Zandhei",
    "iso:country":"NL",
    "sg:address":"Zandhei 44",
    "sg:city":"Veldhoven",
    "sg:orig_category":"Pensioenen",
    "sg:phone":"+31 40 254 1340",
    "sg:postcode":"5508 WT",
    "sg:province":"Noord-Brabant",
    "wof:name":"Graaf, Mr W C M De",
    "wof:placetype":"venue"
},
  "geometry": {"coordinates":[5.40213,51.427223],"type":"Point"}
}