{
  "type": "Feature",
  "properties": {
    "addr:full":"Leermosstr 7 Almere NL. 1314 MS",
    "addr:housenumber":"7",
    "addr:postcode":"1314",
    "addr:street":"Leermosstr;Nl.",
    "iso:country":"NL",
    "sg:address":"Leermosstr 7",
    "sg:city":"Almere",
    "sg:orig_category":"Kappers",
    "sg:phone":"+31 36 533 0474",
    "sg:postcode":"1314 MS",
    "sg:province":"NL.",
    "wof:name":"Hellen",
    "wof:placetype":"venue"
},
  "geometry": {"coordinates":[5.2098650932,52.3830833435],"type":"Point"}
}