{
  "type": "Feature",
  "properties": {
    "addr:full":"Zuidereinde 156 S Graveland Noord-Holland 1243 KN",
    "addr:housenumber":"156",
    "addr:postcode":"1243 kn",
    "addr:street":"Zuidereinde;S Graveland",
    "iso:country":"NL",
    "sg:address":"Zuidereinde 156",
    "sg:city":"S Graveland",
    "sg:orig_category":"Kantoor- En Bedrijfsmeubelen",
    "sg:phone":"+31 35 656 3225",
    "sg:postcode":"1243 KN",
    "sg:province":"Noord-Holland",
    "sg:website":"http://www.interni.nl",
    "wof:name":"Int?rni International Interiors Bv",
    "wof:placetype":"venue"
},
  "geometry": {"coordinates":[5.1218528748,52.2280311584],"type":"Point"}
}