{
  "type": "Feature",
  "properties": {
    "addr:full":"Krabbescheerstr 1 Lisserbroek Noord-Holland 2165 XG",
    "addr:housenumber":"1",
    "addr:postcode":"2165 xg",
    "addr:street":"Krabbescheerstr",
    "iso:country":"NL",
    "sg:address":"Krabbescheerstr 1",
    "sg:city":"Lisserbroek",
    "sg:orig_category":"Peuterspeelzalen",
    "sg:phone":"+31 252 415 887",
    "sg:postcode":"2165 XG",
    "sg:province":"Noord-Holland",
    "wof:name":"Broekjes, De",
    "wof:placetype":"venue"
},
  "geometry": {"coordinates":[4.572476,52.259457],"type":"Point"}
}