{
  "type": "Feature",
  "properties": {
    "addr:full":"Milhezerwg 78 Deurne North Brabant 5752 PL",
    "addr:housenumber":"78",
    "addr:postcode":"5752 pl",
    "addr:street":"Milhezerwg",
    "iso:country":"NL",
    "sg:address":"Milhezerwg 78",
    "sg:city":"Deurne",
    "sg:orig_category":"Bloemen En Planten",
    "sg:phone":"+31 493 316 622",
    "sg:postcode":"5752 PL",
    "sg:province":"North Brabant",
    "wof:name":"Berkers, P H",
    "wof:placetype":"venue"
},
  "geometry": {"coordinates":[5.797797,51.482128],"type":"Point"}
}