{
  "type": "Feature",
  "properties": {
    "addr:full":"Marathon 6 Hilversum Noord-Holland 1213 PK",
    "addr:housenumber":"6",
    "addr:postcode":"1213 pk",
    "addr:street":"Marathon",
    "iso:country":"NL",
    "sg:address":"Marathon 6",
    "sg:city":"Hilversum",
    "sg:orig_category":"Openbaar Vervoer",
    "sg:phone":"+31 35 625 1600",
    "sg:postcode":"1213 PK",
    "sg:province":"Noord-Holland",
    "sg:website":"http://www.connexxion.nl",
    "wof:name":"Connexxion",
    "wof:placetype":"venue"
},
  "geometry": {"coordinates":[5.1930232048,52.2109336853],"type":"Point"}
}