{
  "type": "Feature",
  "properties": {
    "addr:full":"Wulfaertstraat 16 Goes Zeeland 4461 HS",
    "addr:housenumber":"16",
    "addr:postcode":"4461 hs",
    "addr:street":"Wulfaertstraat",
    "iso:country":"NL",
    "sg:address":"Wulfaertstraat 16",
    "sg:city":"Goes",
    "sg:orig_category":"Loodgieterswerk, Verwarming And Sanitaire Installaties",
    "sg:phone":"+31 113 223 258",
    "sg:postcode":"4461 HS",
    "sg:province":"Zeeland",
    "wof:name":"J.W. Struijcken Services",
    "wof:placetype":"venue"
},
  "geometry": {"coordinates":[-83.914169,39.768833],"type":"Point"}
}