{
  "type": "Feature",
  "properties": {
    "addr:full":"Noordeinde 171 Almere Flevoland 1334 AP",
    "addr:housenumber":"171",
    "addr:postcode":"1334 ap",
    "addr:street":"Noordeinde;Flevoland",
    "iso:country":"NL",
    "sg:address":"Noordeinde 171",
    "sg:city":"Almere",
    "sg:classifiers":[
        {
            "category":"Restaurant",
            "type":"Food & Drink"
        }
    ],
    "sg:phone":"+31 36 532 2051",
    "sg:postcode":"1334 AP",
    "sg:province":"Flevoland",
    "wof:name":"Vietnamees",
    "wof:placetype":"venue"
},
  "geometry": {"coordinates":[5.277507,52.394882],"type":"Point"}
}