{
  "type": "Feature",
  "properties": {
    "iso:country":"NL",
    "sg:address":"Noordeinde 171",
    "sg:city":"Almere",
    "sg:classifiers":[
        {
            "category":"Restaurant",
            "type":"Food & Drink"
        }
    ],
    "sg:phone":"+31 36 532 2051",
    "sg:postcode":"1334 AP",
    "sg:province":"Flevoland",
    "wof:name":"Vietnamees",
    "wof:placetype":"venue"
},
  "geometry": {"coordinates":[5.277507,52.394882],"type":"Point"}
}