{
  "type": "Feature",
  "properties": {
    "iso:country":"NL",
    "sg:address":"Herengracht 25",
    "sg:city":"Weesp",
    "sg:orig_category":"Kappers",
    "sg:phone":"+31 294 414 014",
    "sg:postcode":"1382 AG",
    "sg:province":"Noord-Holland",
    "wof:name":"J. Van Der Hooft",
    "wof:placetype":"venue"
},
  "geometry": {"coordinates":[5.0396780968,52.3088798523],"type":"Point"}
}