{
  "type": "Feature",
  "properties": {
    "iso:country":"NL",
    "sg:address":"Venkant 11",
    "sg:city":"St Michielsgestel",
    "sg:orig_category":"Kermisexploitatie",
    "sg:phone":"+31 73 551 6488",
    "sg:postcode":"5271 SP",
    "sg:province":"North Brabant",
    "wof:name":"Westelaken, B Van De",
    "wof:placetype":"venue"
},
  "geometry": {"coordinates":[5.360489,51.648827],"type":"Point"}
}