{
  "type": "Feature",
  "properties": {
    "addr:full":"A V Leeuwenhoekln 22 Hengelo Ov Overijssel 7555 BJ",
    "addr:housenumber":"22",
    "addr:postcode":"7555 bj",
    "addr:street":"A;Leeuwenhoekln;Ov",
    "iso:country":"NL",
    "sg:address":"A V Leeuwenhoekln 22",
    "sg:city":"Hengelo Ov",
    "sg:orig_category":"Verenigingen En Stichtingen",
    "sg:phone":"+31 74 243 9997",
    "sg:postcode":"7555 BJ",
    "sg:province":"Overijssel",
    "wof:name":"Wladimir Byzantijnskoor",
    "wof:placetype":"venue"
},
  "geometry": {"coordinates":[6.78971,52.266331],"type":"Point"}
}