{
  "type": "Feature",
  "properties": {
    "addr:full":"Willem Barentszkade 15 Terschelling West Friesland 8881 BC",
    "addr:housenumber":"15",
    "addr:postcode":"8881 bc",
    "addr:street":"Willem Barentszkade",
    "iso:country":"NL",
    "sg:address":"Willem Barentszkade 15",
    "sg:city":"Terschelling West",
    "sg:orig_category":"Watersport-, Sport- And Kampeerbenodigdheden Verhuur",
    "sg:phone":"+31 562 442 178",
    "sg:postcode":"8881 BC",
    "sg:province":"Friesland",
    "wof:name":"W.L. Zeelen Rijwielverhuur Bv",
    "wof:placetype":"venue"
},
  "geometry": {"coordinates":[5.2155199051,53.3576545715],"type":"Point"}
}