{
  "type": "Feature",
  "properties": {
    "iso:country":"NL",
    "sg:address":"Monnickenmeer 3",
    "sg:city":"Monnickendam",
    "sg:orig_category":"Landbouwmachines Gh",
    "sg:phone":"+31 299 653 989",
    "sg:postcode":"1141 PB",
    "sg:province":"Noord-Holland",
    "wof:name":"K.P. Reijnders",
    "wof:placetype":"venue"
},
  "geometry": {"coordinates":[5.016871,52.454788],"type":"Point"}
}