{
  "type": "Feature",
  "properties": {
    "addr:full":"Pastoor Van De Plaatstr 21 Rijpwetering Zuid-Holland 2375 AE",
    "addr:housenumber":"21",
    "addr:postcode":"2375 ae",
    "addr:street":"Pastoor Van De Plaatstr",
    "iso:country":"NL",
    "sg:address":"Pastoor Van De Plaatstr 21",
    "sg:city":"Rijpwetering",
    "sg:orig_category":"Verzekeringen",
    "sg:phone":"+31 71 501 8096",
    "sg:postcode":"2375 AE",
    "sg:province":"Zuid-Holland",
    "wof:name":"Adviesburo Montanus",
    "wof:placetype":"venue"
},
  "geometry": {"coordinates":[4.584683,52.191895],"type":"Point"}
}