{
  "type": "Feature",
  "properties": {
    "iso:country":"NL",
    "sg:address":"Oudedijk 245",
    "sg:city":"Rotterdam",
    "sg:orig_category":"Loodgieterswerk, Verwarming And Sanitaire Installaties",
    "sg:phone":"+31 10 452 2393",
    "sg:postcode":"3061 AH",
    "sg:province":"Zuid-Holland",
    "wof:name":"L.C. Vermeulen",
    "wof:placetype":"venue"
},
  "geometry": {"coordinates":[4.506391,51.929024],"type":"Point"}
}