{
  "type": "Feature",
  "properties": {
    "iso:country":"NL",
    "sg:address":"Kanaalstr 9",
    "sg:city":"Werkendam",
    "sg:orig_category":"Keukens",
    "sg:phone":"+31 183 689 211",
    "sg:postcode":"4251 ZS",
    "sg:province":"North Brabant",
    "sg:website":"http://www.vandijkkeukens.nl",
    "wof:name":"Dijk, Van",
    "wof:placetype":"venue"
},
  "geometry": {"coordinates":[4.892422,51.809551],"type":"Point"}
}