{
  "type": "Feature",
  "properties": {
    "addr:full":"Boschstr 82A Maastricht Limburg 6211 AZ",
    "addr:housenumber":"82a",
    "addr:postcode":"6211 az",
    "addr:street":"Boschstr",
    "iso:country":"NL",
    "sg:address":"Boschstr 82A",
    "sg:city":"Maastricht",
    "sg:orig_category":"Wasserijen",
    "sg:phone":"+31 43 325 0959",
    "sg:postcode":"6211 AZ",
    "sg:province":"Limburg",
    "wof:name":"Huysmans",
    "wof:placetype":"venue"
},
  "geometry": {"coordinates":[5.6900749207,50.8530273438],"type":"Point"}
}