{
  "type": "Feature",
  "properties": {
    "addr:full":"Hessenwg 125 Stoutenburg Utrecht 3835 PH",
    "addr:housenumber":"125",
    "addr:postcode":"3835",
    "addr:street":"Stoutenburg",
    "iso:country":"NL",
    "sg:address":"Hessenwg 125",
    "sg:city":"Stoutenburg",
    "sg:orig_category":"Kantoor- En Interieurbeplanting",
    "sg:phone":"+31 33 495 2326",
    "sg:postcode":"3835 PH",
    "sg:province":"Utrecht",
    "sg:website":"http://www.ottovisser.nl",
    "wof:name":"Visser, Otto",
    "wof:placetype":"venue"
},
  "geometry": {"coordinates":[5.4380288124,52.1511535645],"type":"Point"}
}