{
  "type": "Feature",
  "properties": {
    "iso:country":"NL",
    "sg:address":"Hoofdstraat 190",
    "sg:city":"Hoogezand",
    "sg:orig_category":"Meubelzaken, Woning- And Keukeninrichting",
    "sg:phone":"+31 598 394 815",
    "sg:postcode":"9601 EM",
    "sg:province":"Groningen",
    "wof:name":"Schoonveld Interieur Bv",
    "wof:placetype":"venue"
},
  "geometry": {"coordinates":[6.767934,53.163464],"type":"Point"}
}