{
  "type": "Feature",
  "properties": {
    "addr:full":"Dennendk 12 Warnsveld Gelderland 7231 RD",
    "addr:housenumber":"12",
    "addr:postcode":"7231",
    "addr:street":"Dennendk;Gelderland;Rd",
    "iso:country":"NL",
    "sg:address":"Dennendk 12",
    "sg:city":"Warnsveld",
    "sg:orig_category":"Groepsaccommodaties",
    "sg:phone":"+31 575 551 378",
    "sg:postcode":"7231 RD",
    "sg:province":"Gelderland",
    "wof:name":"Wagenvoort, W",
    "wof:placetype":"venue"
},
  "geometry": {"coordinates":[6.283721,52.125965],"type":"Point"}
}