{
  "type": "Feature",
  "properties": {
    "addr:full":"Noordvliet 149 Maassluis South Holland 3142 CL",
    "addr:housenumber":"149",
    "addr:postcode":"3142",
    "addr:street":"Noordvliet",
    "iso:country":"NL",
    "sg:address":"Noordvliet 149",
    "sg:city":"Maassluis",
    "sg:orig_category":"Schilderwerk",
    "sg:phone":"+31 10 591 8021",
    "sg:postcode":"3142 CL",
    "sg:province":"South Holland",
    "wof:name":"Schildersbedrijf W.L. Boer",
    "wof:placetype":"venue"
},
  "geometry": {"coordinates":[4.262179,51.925041],"type":"Point"}
}