{
  "type": "Feature",
  "properties": {
    "iso:country":"NL",
    "sg:address":"Noorderkampwg 20",
    "sg:city":"Wapenveld",
    "sg:orig_category":"Adviesbureaus Bedrijfsorganisatie",
    "sg:phone":"+31 38 447 0977",
    "sg:postcode":"8191 JH",
    "sg:province":"Gelderland",
    "wof:name":"Basalt Bv",
    "wof:placetype":"venue"
},
  "geometry": {"coordinates":[6.064274,52.445961],"type":"Point"}
}