{
  "type": "Feature",
  "properties": {
    "addr:full":"Keurenplein 1 Amsterdam Noord-Holland 1069 CD",
    "addr:housenumber":"1",
    "addr:postcode":"1069 cd",
    "addr:street":"Keurenplein",
    "iso:country":"NL",
    "sg:address":"Keurenplein 1",
    "sg:city":"Amsterdam",
    "sg:orig_category":"Fotografische And Optische Artikelen Gh",
    "sg:phone":"+31 20 410 6900",
    "sg:postcode":"1069 CD",
    "sg:province":"Noord-Holland",
    "wof:name":"Bv Nederlandse Optische Industrie Enot",
    "wof:placetype":"venue"
},
  "geometry": {"coordinates":[4.7844781876,52.3611450195],"type":"Point"}
}