{
  "type": "Feature",
  "properties": {
    "addr:full":"Van Egmondlaan 14 Wateringen Zuid-Holland 2291 RT",
    "addr:housenumber":"14",
    "addr:postcode":"2291 rt",
    "addr:street":"Van Egmondlaan",
    "iso:country":"NL",
    "sg:address":"Van Egmondlaan 14",
    "sg:city":"Wateringen",
    "sg:orig_category":"Metaalbekleding And -Behandeling",
    "sg:phone":"+31 174 294 469",
    "sg:postcode":"2291 RT",
    "sg:province":"Zuid-Holland",
    "wof:name":"J.H.A. V.D. Valk",
    "wof:placetype":"venue"
},
  "geometry": {"coordinates":[4.274912,52.025883],"type":"Point"}
}