{
  "type": "Feature",
  "properties": {
    "addr:full":"Schaaksport 100 Groningen Groningen 9728 PG",
    "addr:housenumber":"100",
    "addr:postcode":"9728 pg",
    "addr:street":"Schaaksport",
    "iso:country":"NL",
    "sg:address":"Schaaksport 100",
    "sg:city":"Groningen",
    "sg:orig_category":"Omroep",
    "sg:phone":"+31 50 526 1608",
    "sg:postcode":"9728 PG",
    "sg:province":"Groningen",
    "wof:name":"Senioren Omroep, Stich Reg",
    "wof:placetype":"venue"
},
  "geometry": {"coordinates":[6.560388,53.19194],"type":"Point"}
}