{
  "type": "Feature",
  "properties": {
    "iso:country":"NL",
    "sg:address":"Raadhuispln 6",
    "sg:city":"Panningen",
    "sg:orig_category":"Zoetwaren - Winkels",
    "sg:phone":"+31 77 307 2130",
    "sg:postcode":"5981 AT",
    "sg:province":"Limburg",
    "wof:name":"Zoetelaar, De",
    "wof:placetype":"venue"
},
  "geometry": {"coordinates":[5.981089,51.328056],"type":"Point"}
}