{
  "type": "Feature",
  "properties": {
    "addr:full":"Langestr 50 Alkmaar Noord-Holland 1811 JJ",
    "addr:housenumber":"50",
    "addr:postcode":"1811 jj",
    "addr:street":"Langestr",
    "iso:country":"NL",
    "sg:address":"Langestr 50",
    "sg:city":"Alkmaar",
    "sg:orig_category":"Boeken En Tijdschriften",
    "sg:phone":"+31 72 511 6596",
    "sg:postcode":"1811 JJ",
    "sg:province":"Noord-Holland",
    "wof:name":"Boekenvoordeel Bv",
    "wof:placetype":"venue"
},
  "geometry": {"coordinates":[4.746258,52.634361],"type":"Point"}
}