{
  "type": "Feature",
  "properties": {
    "addr:full":"Haya V Someren-Downerstr 5 Amsterdam Noord-Holland 1067 WP",
    "addr:housenumber":"5",
    "addr:postcode":"1067 wp",
    "addr:street":"Someren-Downerstr",
    "iso:country":"NL",
    "sg:address":"Haya V Someren-Downerstr 5",
    "sg:city":"Amsterdam",
    "sg:orig_category":"Diverse Grafische Activiteiten",
    "sg:phone":"+31 20 614 7202",
    "sg:postcode":"1067 WP",
    "sg:province":"Noord-Holland",
    "wof:name":"I.N.L. Bijman",
    "wof:placetype":"venue"
},
  "geometry": {"coordinates":[4.791023,52.382881],"type":"Point"}
}