{
  "type": "Feature",
  "properties": {
    "addr:full":"Emmapln 16 Schiedam Zuid-Holland 3112 DC",
    "addr:housenumber":"16",
    "addr:postcode":"3112",
    "addr:street":"Emmapln",
    "iso:country":"NL",
    "sg:address":"Emmapln 16",
    "sg:city":"Schiedam",
    "sg:orig_category":"Video - Faciliteiten En Producties",
    "sg:phone":"+31 10 246 0926",
    "sg:postcode":"3112 DC",
    "sg:province":"Zuid-Holland",
    "sg:website":"http://www.kustersdigitalevideoproducties.nl",
    "wof:name":"Kusters Digitale Videoproducties",
    "wof:placetype":"venue"
},
  "geometry": {"coordinates":[4.403127,51.917034],"type":"Point"}
}