{
  "type": "Feature",
  "properties": {
    "addr:full":"Lepelblad 111 Purmerend Noord-Holland 1441 VH",
    "addr:housenumber":"111",
    "addr:postcode":"1441 vh",
    "addr:street":"Lepelblad",
    "iso:country":"NL",
    "sg:address":"Lepelblad 111",
    "sg:city":"Purmerend",
    "sg:orig_category":"Adviesbureaus Chemische Techniek",
    "sg:phone":"+31 299 429 118",
    "sg:postcode":"1441 VH",
    "sg:province":"Noord-Holland",
    "sg:website":"http://www.rnd-coordinatie.mypage.org",
    "wof:name":"Malssen, Van",
    "wof:placetype":"venue"
},
  "geometry": {"coordinates":[4.958434,52.493484],"type":"Point"}
}