{
  "type": "Feature",
  "properties": {
    "iso:country":"NL",
    "sg:address":"Traay 19",
    "sg:city":"Driebergen-Rijsenburg",
    "sg:orig_category":"Juweliers",
    "sg:phone":"+31 343 513 756",
    "sg:postcode":"3971 GB",
    "sg:province":"Utrecht",
    "wof:name":"E J Van Benschop",
    "wof:placetype":"venue"
},
  "geometry": {"coordinates":[5.283711,52.052437],"type":"Point"}
}