{
  "type": "Feature",
  "properties": {
    "addr:full":"Tuinstraat 47 Amsterdam North Holland 1015 NX",
    "addr:housenumber":"47",
    "addr:postcode":"1015 nx",
    "addr:street":"Tuinstraat",
    "iso:country":"NL",
    "sg:address":"Tuinstraat 47",
    "sg:city":"Amsterdam",
    "sg:orig_category":"Loodgieterswerk, Verwarming And Sanitaire Installaties",
    "sg:phone":"+31 20 624 6873",
    "sg:postcode":"1015 NX",
    "sg:province":"North Holland",
    "wof:name":"B. Van Amerongen",
    "wof:placetype":"venue"
},
  "geometry": {"coordinates":[4.884197,52.377319],"type":"Point"}
}