{
  "type": "Feature",
  "properties": {
    "iso:country":"NL",
    "sg:address":"Assendorperstr 100",
    "sg:city":"Zwolle",
    "sg:orig_category":"Juweliers",
    "sg:phone":"+31 38 421 6928",
    "sg:postcode":"8012 CC",
    "sg:province":"Overijssel",
    "wof:name":"Kale, A",
    "wof:placetype":"venue"
},
  "geometry": {"coordinates":[6.101415,52.506359],"type":"Point"}
}