{
  "type": "Feature",
  "properties": {
    "addr:full":"Boelewerf 2 Ridderkerk South Holland 2987 VD",
    "addr:housenumber":"2",
    "addr:postcode":"2987 vd",
    "addr:street":"Boelewerf",
    "iso:country":"NL",
    "sg:address":"Boelewerf 2",
    "sg:city":"Ridderkerk",
    "sg:orig_category":"Meubelen - Fabrieken En Groothandel",
    "sg:phone":"+31 180 414 245",
    "sg:postcode":"2987 VD",
    "sg:province":"South Holland",
    "wof:name":"Rijnmond Meubel Bv",
    "wof:placetype":"venue"
},
  "geometry": {"coordinates":[4.578559,51.900898],"type":"Point"}
}