{
  "type": "Feature",
  "properties": {
    "iso:country":"NL",
    "sg:address":"Steenovenweg 12",
    "sg:city":"Montfoort",
    "sg:orig_category":"Glaszetten",
    "sg:phone":"+31 348 471 116",
    "sg:postcode":"3417 XR",
    "sg:province":"Utrecht",
    "wof:name":"Verheul Trappen",
    "wof:placetype":"venue"
},
  "geometry": {"coordinates":[4.941086,52.045033],"type":"Point"}
}