{
  "type": "Feature",
  "properties": {
    "addr:full":"Steenovenweg 12 Montfoort Utrecht 3417 XR",
    "addr:housenumber":"12",
    "addr:postcode":"3417 xr",
    "addr:street":"Steenovenweg",
    "iso:country":"NL",
    "sg:address":"Steenovenweg 12",
    "sg:city":"Montfoort",
    "sg:orig_category":"Glaszetten",
    "sg:phone":"+31 348 471 116",
    "sg:postcode":"3417 XR",
    "sg:province":"Utrecht",
    "wof:name":"Verheul Trappen",
    "wof:placetype":"venue"
},
  "geometry": {"coordinates":[4.941086,52.045033],"type":"Point"}
}