{
  "type": "Feature",
  "properties": {
    "addr:full":"Tudderenderweg 46 Sittard North Rhine-Westphalia 6137 CG",
    "addr:housenumber":"46",
    "addr:postcode":"6137 cg",
    "addr:street":"Tudderenderweg",
    "iso:country":"NL",
    "sg:address":"Tudderenderweg 46",
    "sg:city":"Sittard",
    "sg:orig_category":"Overheidsdiensten",
    "sg:phone":"+31 46 452 2399",
    "sg:postcode":"6137 CG",
    "sg:province":"North Rhine-Westphalia",
    "wof:name":"Don Bosco",
    "wof:placetype":"venue"
},
  "geometry": {"coordinates":[5.8803491592,51.0020065308],"type":"Point"}
}