{
  "type": "Feature",
  "properties": {
    "addr:full":"Dr. Schaepmanlaan 23A Roosendaal Noord-Brabant 4702 GT",
    "addr:housenumber":"23a",
    "addr:postcode":"4702 gt",
    "addr:street":"Dr. Schaepmanlaan",
    "iso:country":"NL",
    "sg:address":"Dr. Schaepmanlaan 23A",
    "sg:city":"Roosendaal",
    "sg:orig_category":"Visspeciaalzaken",
    "sg:phone":"+31 165 532 013",
    "sg:postcode":"4702 GT",
    "sg:province":"Noord-Brabant",
    "wof:name":"Kaviaar Viswinkel",
    "wof:placetype":"venue"
},
  "geometry": {"coordinates":[4.471663,51.535038],"type":"Point"}
}