{
  "type": "Feature",
  "properties": {
    "addr:full":"Burgemeester Timansweg 4 'S Heerenhoek Zeeland 4453 CM",
    "addr:housenumber":"4 '",
    "addr:postcode":"4453 cm",
    "addr:street":"Burgemeester Timansweg",
    "iso:country":"NL",
    "sg:address":"Burgemeester Timansweg 4",
    "sg:city":"'S Heerenhoek",
    "sg:orig_category":"Kappers",
    "sg:phone":"+31 113 352 630",
    "sg:postcode":"4453 CM",
    "sg:province":"Zeeland",
    "wof:name":"Studio Dzjell",
    "wof:placetype":"venue"
},
  "geometry": {"coordinates":[3.767445,51.453465],"type":"Point"}
}