{
  "type": "Feature",
  "properties": {
    "addr:full":"Hoffmannln 403 Tilburg Noord-Brabant 5011 WH",
    "addr:housenumber":"403",
    "addr:postcode":"5011 wh",
    "addr:street":"Tilburg",
    "iso:country":"NL",
    "sg:address":"Hoffmannln 403",
    "sg:city":"Tilburg",
    "sg:orig_category":"Grafologen",
    "sg:phone":"+31 13 456 2203",
    "sg:postcode":"5011 WH",
    "sg:province":"Noord-Brabant",
    "wof:name":"Linden, M Van Der",
    "wof:placetype":"venue"
},
  "geometry": {"coordinates":[5.106271,51.554928],"type":"Point"}
}