{
  "type": "Feature",
  "properties": {
    "addr:full":"Molendk 25 Wolphaartsdyk Zeeland 4471 BN",
    "addr:housenumber":"25",
    "addr:postcode":"4471 bn",
    "addr:street":"Molendk;Zeeland",
    "iso:country":"NL",
    "sg:address":"Molendk 25",
    "sg:city":"Wolphaartsdyk",
    "sg:orig_category":"Meel - Fabrieken En Groothandel",
    "sg:phone":"+31 113 581 226",
    "sg:postcode":"4471 BN",
    "sg:province":"Zeeland",
    "wof:name":"Visser, J De",
    "wof:placetype":"venue"
},
  "geometry": {"coordinates":[3.817013,51.529663],"type":"Point"}
}