{
  "type": "Feature",
  "properties": {
    "addr:full":"Wilhelminapk 46 Utrecht Utrecht 3581 NL",
    "addr:housenumber":"46",
    "addr:postcode":"3581 nl",
    "addr:street":"Wilhelminapk",
    "iso:country":"NL",
    "sg:address":"Wilhelminapk 46",
    "sg:city":"Utrecht",
    "sg:orig_category":"Werving En Selectie",
    "sg:phone":"+31 30 220 9787",
    "sg:postcode":"3581 NL",
    "sg:province":"Utrecht",
    "sg:website":"http://www.crmpeople.nl",
    "wof:name":"Crm People",
    "wof:placetype":"venue"
},
  "geometry": {"coordinates":[5.1382288933,52.0865402222],"type":"Point"}
}