{
  "type": "Feature",
  "properties": {
    "addr:full":"Julianaln 15 Etten Leur Noord-Brabant 4872 BC",
    "addr:housenumber":"15",
    "addr:postcode":"4872 bc",
    "addr:street":"Julianaln",
    "iso:country":"NL",
    "sg:address":"Julianaln 15",
    "sg:city":"Etten Leur",
    "sg:orig_category":"Beeldende Kunstenaars",
    "sg:phone":"+31 76 503 2290",
    "sg:postcode":"4872 BC",
    "sg:province":"Noord-Brabant",
    "wof:name":"Spaan, Atelier Annemarie",
    "wof:placetype":"venue"
},
  "geometry": {"coordinates":[4.645348,51.572353],"type":"Point"}
}