{
  "type": "Feature",
  "properties": {
    "iso:country":"NL",
    "sg:address":"Cluselaan 20",
    "sg:city":"Eindhoven",
    "sg:orig_category":"Diverse Grafische Activiteiten",
    "sg:phone":"+31 40 248 6351",
    "sg:postcode":"5627 DC",
    "sg:province":"Noord-Brabant",
    "wof:name":"Muizenissen",
    "wof:placetype":"venue"
},
  "geometry": {"coordinates":[5.440005,51.484562],"type":"Point"}
}