{
  "type": "Feature",
  "properties": {
    "addr:full":"Deltaplein 71 'S Gravenhage South Holland 2554 EE",
    "addr:housenumber":"71",
    "addr:postcode":"2554 ee",
    "addr:street":"Deltaplein;' S Gravenhage",
    "iso:country":"NL",
    "sg:address":"Deltaplein 71",
    "sg:city":"'S Gravenhage",
    "sg:orig_category":"Metalen And Ertsen Gh",
    "sg:phone":"+31 70 323 8578",
    "sg:postcode":"2554 EE",
    "sg:province":"South Holland",
    "wof:name":"Awelco Benelux Bv",
    "wof:placetype":"venue"
},
  "geometry": {"coordinates":[4.220788,52.068222],"type":"Point"}
}