{
  "type": "Feature",
  "properties": {
    "iso:country":"NL",
    "sg:address":"Mr Troelstrastr 32",
    "sg:city":"Vlaardingen",
    "sg:orig_category":"Journalisten Freelance",
    "sg:phone":"+31 10 435 6417",
    "sg:postcode":"3131 HS",
    "sg:province":"South Holland",
    "wof:name":"Lugt, D G Van Der",
    "wof:placetype":"venue"
},
  "geometry": {"coordinates":[4.339441,51.914024],"type":"Point"}
}