{
  "type": "Feature",
  "properties": {
    "addr:full":"Beneluxwg 37 Oosterhout Nb North Brabant 4904 SJ",
    "addr:housenumber":"37;nb",
    "addr:postcode":"4904",
    "addr:street":"Beneluxwg",
    "iso:country":"NL",
    "sg:address":"Beneluxwg 37",
    "sg:city":"Oosterhout Nb",
    "sg:orig_category":"Grafische Machines",
    "sg:phone":"+31 162 472 471",
    "sg:postcode":"4904 SJ",
    "sg:province":"North Brabant",
    "wof:name":"Qi Press Controls",
    "wof:placetype":"venue"
},
  "geometry": {"coordinates":[4.866536,51.624878],"type":"Point"}
}