{
  "type": "Feature",
  "properties": {
    "iso:country":"NL",
    "sg:address":"Hoogeinde 21",
    "sg:city":"Tricht",
    "sg:orig_category":"Honden- En Kattentrimsalons",
    "sg:phone":"+31 345 535 447",
    "sg:postcode":"4196 JN",
    "sg:province":"Gelderland",
    "wof:name":"Lugtigheid, G H J",
    "wof:placetype":"venue"
},
  "geometry": {"coordinates":[5.275072,51.891727],"type":"Point"}
}