{
  "type": "Feature",
  "properties": {
    "addr:full":"Kapelstr 43 Heeze North Brabant 5591 HD",
    "addr:housenumber":"43",
    "addr:postcode":"5591 hd",
    "addr:street":"Kapelstr",
    "iso:country":"NL",
    "sg:address":"Kapelstr 43",
    "sg:city":"Heeze",
    "sg:orig_category":"Glas, Porselein En Aardewerk",
    "sg:phone":"+31 40 226 1359",
    "sg:postcode":"5591 HD",
    "sg:province":"North Brabant",
    "wof:name":"Vingerhoets",
    "wof:placetype":"venue"
},
  "geometry": {"coordinates":[5.580339,51.381886],"type":"Point"}
}