{
  "type": "Feature",
  "properties": {
    "addr:full":"V Beethovenln 15 Nieuwerkerk Yssel South Holland 2912 VK",
    "addr:housenumber":"15",
    "addr:postcode":"2912 vk",
    "iso:country":"NL",
    "sg:address":"V Beethovenln 15",
    "sg:city":"Nieuwerkerk Yssel",
    "sg:classifiers":[
        {
            "category":"Personal",
            "subcategory":"Nail Salon",
            "type":"Services"
        }
    ],
    "sg:phone":"+31 180 315 190",
    "sg:postcode":"2912 VK",
    "sg:province":"South Holland",
    "sg:tags":[
        "pedicure"
    ],
    "wof:name":"Tilburg, L C Van",
    "wof:placetype":"venue"
},
  "geometry": {"coordinates":[4.6028,51.963692],"type":"Point"}
}