{
  "type": "Feature",
  "properties": {
    "iso:country":"NL",
    "sg:address":"Nissewg 4",
    "sg:city":"Kruiningen",
    "sg:classifiers":[
        {
            "category":"Retail",
            "subcategory":"Storage",
            "type":"Services"
        }
    ],
    "sg:phone":"+31 113 322 355",
    "sg:postcode":"4416 PK",
    "sg:province":"Zeeland",
    "sg:tags":[
        "op-",
        "en",
        "overslagbedrijven"
    ],
    "wof:name":"Continental Stevedoring",
    "wof:placetype":"venue"
},
  "geometry": {"coordinates":[4.034001,51.459061],"type":"Point"}
}