{
  "type": "Feature",
  "properties": {
    "iso:country":"NL",
    "sg:address":"Sloterkd 184",
    "sg:city":"Amsterdam",
    "sg:classifiers":[
        {
            "category":"Retail",
            "subcategory":"Auto Repair",
            "type":"Services"
        }
    ],
    "sg:phone":"+31 20 617 7522",
    "sg:postcode":"1059 EC",
    "sg:province":"Noord-Holland",
    "sg:tags":[
        "garage"
    ],
    "wof:name":"Leeuw, Garagebedrijf De",
    "wof:placetype":"venue"
},
  "geometry": {"coordinates":[4.84673,52.344818],"type":"Point"}
}