{
  "type": "Feature",
  "properties": {
    "addr:full":"Uitwierderwg 23 Delfzyl Groningen 9933 GH",
    "addr:housenumber":"23",
    "addr:postcode":"9933 gh",
    "addr:street":"Uitwierderwg",
    "iso:country":"NL",
    "sg:address":"Uitwierderwg 23",
    "sg:city":"Delfzyl",
    "sg:classifiers":[
        {
            "category":"Wholesale",
            "subcategory":"Meat",
            "type":"Manufacturing & Wholesale Goods"
        }
    ],
    "sg:phone":"+31 596 616 203",
    "sg:postcode":"9933 GH",
    "sg:province":"Groningen",
    "sg:tags":[
        "hang-",
        "sluitwerk",
        "en"
    ],
    "wof:name":"Sls Safety Lock Systems",
    "wof:placetype":"venue"
},
  "geometry": {"coordinates":[6.924345,53.334431],"type":"Point"}
}