{
  "type": "Feature",
  "properties": {
    "addr:full":"Eize Bosstraat 15 Drachten Friesland 9203 SN",
    "addr:housenumber":"15",
    "addr:postcode":"9203 sn",
    "addr:street":"Eize Bosstraat",
    "iso:country":"NL",
    "sg:address":"Eize Bosstraat 15",
    "sg:city":"Drachten",
    "sg:orig_category":"Technische Studies And Onderzoek",
    "sg:phone":"+31 512 513 840",
    "sg:postcode":"9203 SN",
    "sg:province":"Friesland",
    "wof:name":"M. Van Lelyveld",
    "wof:placetype":"venue"
},
  "geometry": {"coordinates":[6.091973,53.103642],"type":"Point"}
}