{
  "type": "Feature",
  "properties": {
    "addr:full":"Holterwg 59 Colmschate NL.08 7429 AE",
    "addr:housenumber":"59;nl.08",
    "addr:postcode":"7429 ae",
    "addr:street":"Holterwg",
    "iso:country":"NL",
    "sg:address":"Holterwg 59",
    "sg:city":"Colmschate",
    "sg:orig_category":"Kappers",
    "sg:phone":"+31 570 650 845",
    "sg:postcode":"7429 AE",
    "sg:province":"NL.08",
    "wof:name":"Lange, Bert De",
    "wof:placetype":"venue"
},
  "geometry": {"coordinates":[6.216112,52.24876],"type":"Point"}
}