{
  "type": "Feature",
  "properties": {
    "addr:full":"Lievevrouwestraat 2 Bergen Op Zoom North Brabant 4611 JK",
    "addr:housenumber":"2",
    "addr:postcode":"4611 jk",
    "addr:street":"Lievevrouwestraat",
    "iso:country":"NL",
    "sg:address":"Lievevrouwestraat 2",
    "sg:city":"Bergen Op Zoom",
    "sg:orig_category":"Fotostudio'S And Fotografen",
    "sg:phone":"+31 164 235 807",
    "sg:postcode":"4611 JK",
    "sg:province":"North Brabant",
    "wof:name":"Fotolino",
    "wof:placetype":"venue"
},
  "geometry": {"coordinates":[4.28502,51.495239],"type":"Point"}
}