{
  "type": "Feature",
  "properties": {
    "iso:country":"NL",
    "sg:address":"Blokland 125",
    "sg:city":"Montfoort",
    "sg:orig_category":"Kantoorbenodigdheden",
    "sg:phone":"+31 348 470 656",
    "sg:postcode":"3417 MR",
    "sg:province":"Utrecht",
    "sg:website":"http://www.kokkantoorservice.nl",
    "wof:name":"Kok Kantoorservice",
    "wof:placetype":"venue"
},
  "geometry": {"coordinates":[4.9501152039,52.0300102234],"type":"Point"}
}