{
  "type": "Feature",
  "properties": {
    "iso:country":"NL",
    "sg:address":"Molenstraat 29",
    "sg:city":"Helden",
    "sg:orig_category":"Kappers",
    "sg:phone":"+31 77 306 0081",
    "sg:postcode":"5988 EN",
    "sg:province":"Illinois",
    "wof:name":"Kapsalon Figaro",
    "wof:placetype":"venue"
},
  "geometry": {"coordinates":[-89.4168395996,41.772731781],"type":"Point"}
}