{
  "type": "Feature",
  "properties": {
    "addr:full":"Magazynwg 8 Best Noord-Brabant 5683 CW",
    "addr:housenumber":"8",
    "addr:postcode":"5683 cw",
    "addr:street":"Magazynwg",
    "iso:country":"NL",
    "sg:address":"Magazynwg 8",
    "sg:city":"Best",
    "sg:classifiers":[
        {
            "category":"Building & Trades",
            "subcategory":"Electrical",
            "type":"Services"
        }
    ],
    "sg:phone":"+31 499 330 009",
    "sg:postcode":"5683 CW",
    "sg:province":"Noord-Brabant",
    "sg:tags":[
        "distributor"
    ],
    "sg:website":"http://www.dynamic-support.com",
    "wof:name":"Dynamic Support Logistics Ltd",
    "wof:placetype":"venue"
},
  "geometry": {"coordinates":[-101.464592,31.19754],"type":"Point"}
}