{
  "type": "Feature",
  "properties": {
    "addr:full":"Tussenwater 3 Rotterdam Zuid-Holland 3024 RL",
    "addr:housenumber":"3",
    "addr:postcode":"3024 rl",
    "addr:street":"Tussenwater",
    "iso:country":"NL",
    "sg:address":"Tussenwater 3",
    "sg:city":"Rotterdam",
    "sg:orig_category":"Architecten",
    "sg:phone":"+31 10 425 9199",
    "sg:postcode":"3024 RL",
    "sg:province":"Zuid-Holland",
    "wof:name":"Coop Vereniging Maaswerk Architekten Ua",
    "wof:placetype":"venue"
},
  "geometry": {"coordinates":[4.449157,51.907452],"type":"Point"}
}