{
  "type": "Feature",
  "properties": {
    "addr:full":"Westeinde 382 Vriezenveen Overijssel 7671 CN",
    "addr:housenumber":"382",
    "addr:postcode":"7671 cn",
    "addr:street":"Westeinde",
    "iso:country":"NL",
    "sg:address":"Westeinde 382",
    "sg:city":"Vriezenveen",
    "sg:orig_category":"Metaalwerken",
    "sg:phone":"+31 546 564 932",
    "sg:postcode":"7671 CN",
    "sg:province":"Overijssel",
    "wof:name":"Jls",
    "wof:placetype":"venue"
},
  "geometry": {"coordinates":[6.612695,52.408195],"type":"Point"}
}