{
  "type": "Feature",
  "properties": {
    "iso:country":"NL",
    "sg:address":"De Gouwe 22",
    "sg:city":"Dronten",
    "sg:orig_category":"Luchtbehandelings- Apparaten",
    "sg:phone":"+31 321 313 194",
    "sg:postcode":"8253 PA",
    "sg:province":"Flevoland",
    "wof:name":"Aircleaning Service",
    "wof:placetype":"venue"
},
  "geometry": {"coordinates":[5.698135,52.539417],"type":"Point"}
}