{
  "type": "Feature",
  "properties": {
    "addr:full":"Slotlaan 164 Zeist Utrecht 3701 GS",
    "addr:housenumber":"164",
    "addr:postcode":"3701 gs",
    "addr:street":"Slotlaan",
    "iso:country":"NL",
    "sg:address":"Slotlaan 164",
    "sg:city":"Zeist",
    "sg:orig_category":"Huishoudapparatuur, Televisies And Radio'S",
    "sg:phone":"+31 30 692 0685",
    "sg:postcode":"3701 GS",
    "sg:province":"Utrecht",
    "wof:name":"Duiker Steenweg Electronics Bv",
    "wof:placetype":"venue"
},
  "geometry": {"coordinates":[5.244208,52.085518],"type":"Point"}
}