{
  "type": "Feature",
  "properties": {
    "iso:country":"NL",
    "sg:address":"Bizetstr 33",
    "sg:city":"Numansdorp",
    "sg:classifiers":[
        {
            "category":"Personal",
            "subcategory":"Nail Salon",
            "type":"Services"
        }
    ],
    "sg:phone":"+31 186 652 657",
    "sg:postcode":"3281 TR",
    "sg:province":"Zuid-Holland",
    "sg:tags":[
        "pedicure"
    ],
    "wof:name":"Vlegaard-De Groot, P E J",
    "wof:placetype":"venue"
},
  "geometry": {"coordinates":[4.431882,51.734528],"type":"Point"}
}