{
  "type": "Feature",
  "properties": {
    "addr:full":"Nw Ryn 49 Leiden Zuid-Holland 2312 JH",
    "addr:housenumber":"49",
    "addr:postcode":"2312 jh",
    "addr:street":"Nw Ryn",
    "iso:country":"NL",
    "sg:address":"Nw Ryn 49",
    "sg:city":"Leiden",
    "sg:orig_category":"Broodjeszaken",
    "sg:phone":"+31 71 514 4646",
    "sg:postcode":"2312 JH",
    "sg:province":"Zuid-Holland",
    "wof:name":"Jeruzalem",
    "wof:placetype":"venue"
},
  "geometry": {"coordinates":[4.49463,52.154572],"type":"Point"}
}