{
  "type": "Feature",
  "properties": {
    "addr:full":"Kalverstr 15 Amsterdam Noord-Holland 1012 NX",
    "addr:housenumber":"15",
    "addr:postcode":"1012 nx",
    "addr:street":"Kalverstr",
    "iso:country":"NL",
    "sg:address":"Kalverstr 15",
    "sg:city":"Amsterdam",
    "sg:orig_category":"Sportschoenen - Winkels",
    "sg:phone":"+31 20 622 0951",
    "sg:postcode":"1012 NX",
    "sg:province":"Noord-Holland",
    "sg:website":"http://www.footlocker.com",
    "wof:name":"Footlocker",
    "wof:placetype":"venue"
},
  "geometry": {"coordinates":[4.892162,52.372074],"type":"Point"}
}