{
  "type": "Feature",
  "properties": {
    "addr:full":"Trampad 23 Sprang Capelle North Brabant 5161 HK",
    "addr:housenumber":"23",
    "addr:postcode":"5161 hk",
    "addr:street":"Trampad",
    "iso:country":"NL",
    "sg:address":"Trampad 23",
    "sg:city":"Sprang Capelle",
    "sg:orig_category":"Metaalbewerking",
    "sg:phone":"+31 6 18053335",
    "sg:postcode":"5161 HK",
    "sg:province":"North Brabant",
    "wof:name":"Bolasco",
    "wof:placetype":"venue"
},
  "geometry": {"coordinates":[5.018875,51.670189],"type":"Point"}
}