{
  "type": "Feature",
  "properties": {
    "addr:full":"Dr Lelykd 22A S Gravenhage Zuid-Holland 2583 CM",
    "addr:housenumber":"22a;gravenhage",
    "addr:postcode":"2583 cm",
    "addr:street":"S",
    "iso:country":"NL",
    "sg:address":"Dr Lelykd 22A",
    "sg:city":"S Gravenhage",
    "sg:orig_category":"Kantoor- En Secretariaatsservice",
    "sg:phone":"+31 70 416 1718",
    "sg:postcode":"2583 CM",
    "sg:province":"Zuid-Holland",
    "wof:name":"Harbour Business Center",
    "wof:placetype":"venue"
},
  "geometry": {"coordinates":[4.2552599907,52.0912399292],"type":"Point"}
}