{
  "type": "Feature",
  "properties": {
    "addr:full":"Borgvlietsedreef 95 Bergen Op Zoom Noord-Brabant 4615 EB",
    "addr:housenumber":"95",
    "addr:postcode":"4615 eb",
    "addr:street":"Borgvlietsedreef",
    "iso:country":"NL",
    "sg:address":"Borgvlietsedreef 95",
    "sg:city":"Bergen Op Zoom",
    "sg:orig_category":"Administratie- En Boekhoudkantoren",
    "sg:phone":"+31 164 253 918",
    "sg:postcode":"4615 EB",
    "sg:province":"Noord-Brabant",
    "wof:name":"Haast, P",
    "wof:placetype":"venue"
},
  "geometry": {"coordinates":[4.286016,51.485561],"type":"Point"}
}