{
  "type": "Feature",
  "properties": {
    "addr:full":"Esdoornln 5 Castricum Noord-Holland 1901 SC",
    "addr:housenumber":"5",
    "addr:postcode":"1901 sc",
    "addr:street":"Esdoornln",
    "iso:country":"NL",
    "sg:address":"Esdoornln 5",
    "sg:city":"Castricum",
    "sg:orig_category":"Schilders",
    "sg:phone":"+31 251 671 661",
    "sg:postcode":"1901 SC",
    "sg:province":"Noord-Holland",
    "wof:name":"Logchies Intercolour Bv",
    "wof:placetype":"venue"
},
  "geometry": {"coordinates":[4.660369,52.554146],"type":"Point"}
}