{
  "type": "Feature",
  "properties": {
    "iso:country":"NL",
    "sg:address":"De Iisbaan 2",
    "sg:city":"Wommels",
    "sg:orig_category":"Fietsen En Bromfietsen",
    "sg:phone":"+31 515 332 565",
    "sg:postcode":"8731 DW",
    "sg:province":"Friesland",
    "wof:name":"Jong, De",
    "wof:placetype":"venue"
},
  "geometry": {"coordinates":[5.591516,53.116714],"type":"Point"}
}