{
  "type": "Feature",
  "properties": {
    "iso:country":"NL",
    "sg:address":"Demmerik 98",
    "sg:city":"Vinkeveen",
    "sg:orig_category":"Schilderwerk",
    "sg:phone":"+31 297 263 265",
    "sg:postcode":"3645 EE",
    "sg:province":"Utrecht",
    "wof:name":"C H W Versteegh",
    "wof:placetype":"venue"
},
  "geometry": {"coordinates":[4.93173,52.204391],"type":"Point"}
}