{
  "type": "Feature",
  "properties": {
    "addr:full":"Ketsheuvel 50 'S Hertogenbosch Noord-Brabant 5231 PT",
    "addr:housenumber":"50",
    "addr:postcode":"5231 pt",
    "addr:street":"Ketsheuvel;' S",
    "iso:country":"NL",
    "sg:address":"Ketsheuvel 50",
    "sg:city":"'S Hertogenbosch",
    "sg:orig_category":"Overheidsdiensten",
    "sg:phone":"+31 73 642 2669",
    "sg:postcode":"5231 PT",
    "sg:province":"Noord-Brabant",
    "wof:name":"Nico Schuurmanshuis",
    "wof:placetype":"venue"
},
  "geometry": {"coordinates":[5.3062748909,51.7054672241],"type":"Point"}
}