{
  "type": "Feature",
  "properties": {
    "iso:country":"NL",
    "sg:address":"Oude Vismarkt 15",
    "sg:city":"Culemborg",
    "sg:classifiers":[
        {
            "category":"Food & Beverages",
            "subcategory":"Fruits & Vegetables",
            "type":"Retail Goods"
        }
    ],
    "sg:phone":"+31 345 512 363",
    "sg:postcode":"4101 CA",
    "sg:province":"Gelderland",
    "sg:tags":[
        "groenten"
    ],
    "wof:name":"P Op Den Kelder",
    "wof:placetype":"venue"
},
  "geometry": {"coordinates":[5.2246,51.958637],"type":"Point"}
}