{
  "type": "Feature",
  "properties": {
    "iso:country":"NL",
    "sg:address":"Harlingerstr 7",
    "sg:city":"Heerhugowaard",
    "sg:orig_category":"Schilders",
    "sg:phone":"+31 72 534 8439",
    "sg:postcode":"1704 BT",
    "sg:province":"Noord-Holland",
    "wof:name":"Ijdema",
    "wof:placetype":"venue"
},
  "geometry": {"coordinates":[4.854042,52.707394],"type":"Point"}
}