{
  "type": "Feature",
  "properties": {
    "addr:full":"Hoofdstraat 6 Leiderdorp South Holland 2351 AJ",
    "addr:housenumber":"6",
    "addr:postcode":"2351 aj",
    "addr:street":"Hoofdstraat",
    "iso:country":"NL",
    "sg:address":"Hoofdstraat 6",
    "sg:city":"Leiderdorp",
    "sg:orig_category":"Sportprijzen, Postzegels And Munten",
    "sg:phone":"+31 71 541 2266",
    "sg:postcode":"2351 AJ",
    "sg:province":"South Holland",
    "wof:name":"Vof C.P.Th. Bos",
    "wof:placetype":"venue"
},
  "geometry": {"coordinates":[4.522663,52.151707],"type":"Point"}
}