{
  "type": "Feature",
  "properties": {
    "addr:full":"Nieuwstraat 173 Spijkenisse South Holland 3201 EE",
    "addr:housenumber":"173",
    "addr:postcode":"3201 ee",
    "addr:street":"Nieuwstraat",
    "iso:country":"NL",
    "sg:address":"Nieuwstraat 173",
    "sg:city":"Spijkenisse",
    "sg:orig_category":"Juweliers",
    "sg:phone":"+31 181 610 578",
    "sg:postcode":"3201 EE",
    "sg:province":"South Holland",
    "wof:name":"Luigi Lucardi",
    "wof:placetype":"venue"
},
  "geometry": {"coordinates":[4.325045,51.849525],"type":"Point"}
}