{
  "type": "Feature",
  "properties": {
    "iso:country":"NL",
    "sg:address":"Primulastraat 14",
    "sg:city":"Oldenzaal",
    "sg:orig_category":"Verzekeringen",
    "sg:phone":"+31 541 532 390",
    "sg:postcode":"7572 AS",
    "sg:province":"Overijssel",
    "wof:name":"Schasfoort Assurantie- En Hypotheek Adviseurs",
    "wof:placetype":"venue"
},
  "geometry": {"coordinates":[6.918423,52.312778],"type":"Point"}
}