{
  "type": "Feature",
  "properties": {
    "iso:country":"NL",
    "sg:address":"Bierkade 9",
    "sg:city":"Blokzijl",
    "sg:orig_category":"Banken And Kredietinstellingen",
    "sg:phone":"+31 527 291 731",
    "sg:postcode":"8356 DH",
    "sg:province":"NL.08",
    "wof:name":"Rabobank",
    "wof:placetype":"venue"
},
  "geometry": {"coordinates":[5.959215,52.727409],"type":"Point"}
}