{
  "type": "Feature",
  "properties": {
    "iso:country":"NL",
    "sg:address":"Talesiuspark 1",
    "sg:city":"Spaarndam",
    "sg:classifiers":[
        {
            "category":"Professional",
            "subcategory":"Accounting & Tax Preparation",
            "type":"Services"
        }
    ],
    "sg:phone":"+31 23 537 6742",
    "sg:postcode":"2064 LJ",
    "sg:province":"Noord-Holland",
    "sg:tags":[
        "accountant"
    ],
    "wof:name":"Accountantskantoor Kuhlman",
    "wof:placetype":"venue"
},
  "geometry": {"coordinates":[4.690351,52.416271],"type":"Point"}
}