{
  "type": "Feature",
  "properties": {
    "addr:full":"L Nering 54 Emmeloord Flevoland 8302 ED",
    "addr:housenumber":"54",
    "addr:postcode":"8302 ed",
    "addr:street":"Nering;Flevoland",
    "iso:country":"NL",
    "sg:address":"L Nering 54",
    "sg:city":"Emmeloord",
    "sg:orig_category":"Warenhuizen",
    "sg:phone":"+31 527 614 412",
    "sg:postcode":"8302 ED",
    "sg:province":"Flevoland",
    "wof:name":"Hema",
    "wof:placetype":"venue"
},
  "geometry": {"coordinates":[5.757212162,52.711227417],"type":"Point"}
}