{
  "type": "Feature",
  "properties": {
    "addr:full":"Maatkampstr 42 Epe Gelderland 8162 WX",
    "addr:housenumber":"42",
    "addr:postcode":"8162 wx",
    "addr:street":"Maatkampstr;Gelderland",
    "iso:country":"NL",
    "sg:address":"Maatkampstr 42",
    "sg:city":"Epe",
    "sg:orig_category":"Glazenwasserijen",
    "sg:phone":"+31 578 614 509",
    "sg:postcode":"8162 WX",
    "sg:province":"Gelderland",
    "wof:name":"Lava Vetri",
    "wof:placetype":"venue"
},
  "geometry": {"coordinates":[5.977684,52.342636],"type":"Point"}
}