{
  "type": "Feature",
  "properties": {
    "addr:full":"Dalkruidstraat 21 Rotterdam Zuid-Holland 3053 DE",
    "addr:housenumber":"21",
    "addr:postcode":"3053 de",
    "addr:street":"Dalkruidstraat",
    "iso:country":"NL",
    "sg:address":"Dalkruidstraat 21",
    "sg:city":"Rotterdam",
    "sg:orig_category":"Muziekinstrumenten",
    "sg:phone":"+31 10 422 1918",
    "sg:postcode":"3053 DE",
    "sg:province":"Zuid-Holland",
    "wof:name":"J Bouman",
    "wof:placetype":"venue"
},
  "geometry": {"coordinates":[4.467528,51.96059],"type":"Point"}
}