{
  "type": "Feature",
  "properties": {
    "iso:country":"NL",
    "sg:address":"Viljoenstraat 26",
    "sg:city":"'S Gravenhage",
    "sg:orig_category":"Boekhouders",
    "sg:phone":"+31 70 389 0058",
    "sg:postcode":"2572 PE",
    "sg:province":"Zuid-Holland",
    "wof:name":"M J Brinkman-Tebbenhoff",
    "wof:placetype":"venue"
},
  "geometry": {"coordinates":[4.2939,52.062199],"type":"Point"}
}