{
  "type": "Feature",
  "properties": {
    "addr:full":"Hengelosestraat 585 Enschede Overijssel 7521 AG",
    "addr:housenumber":"585",
    "addr:postcode":"7521",
    "addr:street":"Hengelosestraat",
    "iso:country":"NL",
    "sg:address":"Hengelosestraat 585",
    "sg:city":"Enschede",
    "sg:orig_category":"Bedrijfs- And Werkgeversorganisaties",
    "sg:phone":"+31 53 484 9849",
    "sg:postcode":"7521 AG",
    "sg:province":"Overijssel",
    "wof:name":"Kamer Van Koophandel Voor De Veluwe En Twente",
    "wof:placetype":"venue"
},
  "geometry": {"coordinates":[6.8495,52.237587],"type":"Point"}
}