{
  "type": "Feature",
  "properties": {
    "iso:country":"NL",
    "sg:address":"Bisschop Van Munsterstr 18",
    "sg:city":"Borculo",
    "sg:orig_category":"Kappers",
    "sg:phone":"+31 545 273 764",
    "sg:postcode":"7271 WT",
    "sg:province":"Gelderland",
    "wof:name":"Gerry Dollekamp",
    "wof:placetype":"venue"
},
  "geometry": {"coordinates":[6.5213489532,52.1208648682],"type":"Point"}
}