{
  "type": "Feature",
  "properties": {
    "addr:full":"Gasthuisvest 23 Haarlem North Holland 2011 ET",
    "addr:housenumber":"23",
    "addr:postcode":"2011 et",
    "addr:street":"Gasthuisvest",
    "iso:country":"NL",
    "sg:address":"Gasthuisvest 23",
    "sg:city":"Haarlem",
    "sg:orig_category":"Beeldende Kunstenaars",
    "sg:phone":"+31 23 542 3739",
    "sg:postcode":"2011 ET",
    "sg:province":"North Holland",
    "wof:name":"Johnson, P A",
    "wof:placetype":"venue"
},
  "geometry": {"coordinates":[4.632642,52.376278],"type":"Point"}
}