{
  "type": "Feature",
  "properties": {
    "addr:full":"Postbus 16 Spijkenisse 3200 AA",
    "addr:housenumber":"16",
    "addr:postcode":"3200 aa",
    "addr:street":"Postbus",
    "iso:country":"NL",
    "sg:address":"Postbus 16",
    "sg:city":"Spijkenisse",
    "sg:orig_category":"Verzekeringen - Verzekeringskantoren",
    "sg:phone":"+31 181 646 984",
    "sg:postcode":"3200 AA",
    "wof:name":"West-Nederland",
    "wof:placetype":"venue"
},
  "geometry": {"coordinates":[4.325045,51.849525],"type":"Point"}
}