{
  "type": "Feature",
  "properties": {
    "addr:full":"P Paaltjenspad 5 Foudgum Friesland 9154 BD",
    "addr:housenumber":"5",
    "addr:postcode":"9154 bd",
    "addr:street":"P Paaltjenspad",
    "iso:country":"NL",
    "sg:address":"P Paaltjenspad 5",
    "sg:city":"Foudgum",
    "sg:orig_category":"Begrafenisverzorging",
    "sg:phone":"+31 519 296 152",
    "sg:postcode":"9154 BD",
    "sg:province":"Friesland",
    "wof:name":"Reitsma, Jetske",
    "wof:placetype":"venue"
},
  "geometry": {"coordinates":[5.941495,53.345783],"type":"Point"}
}