{
  "type": "Feature",
  "properties": {
    "addr:full":"Barchemsewg 59 Lochem Gelderland 7241 JC",
    "addr:housenumber":"59",
    "addr:postcode":"7241 jc",
    "addr:street":"Barchemsewg;Gelderland",
    "iso:country":"NL",
    "sg:address":"Barchemsewg 59",
    "sg:city":"Lochem",
    "sg:orig_category":"Kantoorbenodigdheden",
    "sg:phone":"+31 573 250 696",
    "sg:postcode":"7241 JC",
    "sg:province":"Gelderland",
    "wof:name":"Roussac Olympia",
    "wof:placetype":"venue"
},
  "geometry": {"coordinates":[6.41898489,52.1519241333],"type":"Point"}
}