{
  "type": "Feature",
  "properties": {
    "addr:full":"Weth I Hutstr 28 Leek Groningen 9351 RG",
    "addr:housenumber":"28",
    "addr:postcode":"9351 rg",
    "addr:street":"Weth I Hutstr",
    "iso:country":"NL",
    "sg:address":"Weth I Hutstr 28",
    "sg:city":"Leek",
    "sg:orig_category":"Scholen Voor Basisonderwijs",
    "sg:phone":"+31 594 514 607",
    "sg:postcode":"9351 RG",
    "sg:province":"Groningen",
    "wof:name":"Tweemaster Openb, De",
    "wof:placetype":"venue"
},
  "geometry": {"coordinates":[6.392695,53.162521],"type":"Point"}
}