{
  "type": "Feature",
  "properties": {
    "addr:full":"Prinsenstraat 27 Haarsteeg Noord-Brabant 5254 JB",
    "addr:housenumber":"27",
    "addr:postcode":"5254 jb",
    "addr:street":"Prinsenstraat",
    "iso:country":"NL",
    "sg:address":"Prinsenstraat 27",
    "sg:city":"Haarsteeg",
    "sg:orig_category":"Goederenvervoer Over De Weg",
    "sg:phone":"+31 73 511 8867",
    "sg:postcode":"5254 JB",
    "sg:province":"Noord-Brabant",
    "wof:name":"L.F. Bax",
    "wof:placetype":"venue"
},
  "geometry": {"coordinates":[5.199276,51.712048],"type":"Point"}
}