{
  "type": "Feature",
  "properties": {
    "addr:full":"Dorpsstraat 60 Lunteren Gelderland 6741 AM",
    "addr:housenumber":"60",
    "addr:postcode":"6741",
    "addr:street":"Dorpsstraat;Gelderland",
    "iso:country":"NL",
    "sg:address":"Dorpsstraat 60",
    "sg:city":"Lunteren",
    "sg:classifiers":[
        {
            "category":"Fast Food",
            "type":"Food & Drink"
        }
    ],
    "sg:phone":"+31 318 483 423",
    "sg:postcode":"6741 AM",
    "sg:province":"Gelderland",
    "sg:tags":[
        "afhaal",
        "restaurant"
    ],
    "wof:name":"Restaurant Pizzeria Sakara",
    "wof:placetype":"venue"
},
  "geometry": {"coordinates":[5.620694,52.084808],"type":"Point"}
}