{
  "type": "Feature",
  "properties": {
    "iso:country":"NL",
    "sg:address":"Grevelingen 12",
    "sg:city":"Zwijndrecht",
    "sg:orig_category":"Overheidsdiensten",
    "sg:phone":"+31 78 612 1820",
    "sg:postcode":"3332 VA",
    "sg:province":"Zuid-Holland",
    "wof:name":"Handelsonderneming P. Van Herk Vof",
    "wof:placetype":"venue"
},
  "geometry": {"coordinates":[4.6655859947,51.822353363],"type":"Point"}
}