{
  "type": "Feature",
  "properties": {
    "addr:full":"Wieringerwaardstraat 29 Amsterdam North Holland 1024 HB",
    "addr:housenumber":"29",
    "addr:postcode":"1024 hb",
    "addr:street":"Wieringerwaardstraat",
    "iso:country":"NL",
    "sg:address":"Wieringerwaardstraat 29",
    "sg:city":"Amsterdam",
    "sg:orig_category":"Goederenvervoer Over De Weg",
    "sg:phone":"+31 20 494 0297",
    "sg:postcode":"1024 HB",
    "sg:province":"North Holland",
    "wof:name":"Cito Sneltransporten",
    "wof:placetype":"venue"
},
  "geometry": {"coordinates":[4.956608,52.39439],"type":"Point"}
}