{
  "type": "Feature",
  "properties": {
    "iso:country":"NL",
    "sg:address":"Hoofdstraat 7",
    "sg:city":"'T Zandt Gn",
    "sg:orig_category":"Autokeuringen",
    "sg:phone":"+31 596 581 312",
    "sg:postcode":"9915 PA",
    "sg:province":"Groningen",
    "wof:name":"Garage K J Van Der Berg",
    "wof:placetype":"venue"
},
  "geometry": {"coordinates":[6.776466,53.361923],"type":"Point"}
}