{
  "type": "Feature",
  "properties": {
    "iso:country":"NL",
    "sg:address":"Deukelven 36",
    "sg:city":"Heemskerk",
    "sg:orig_category":"Administratie- En Boekhoudkantoren",
    "sg:phone":"+31 251 234 940",
    "sg:postcode":"1963 SP",
    "sg:province":"Noord-Holland",
    "wof:name":"Go'S Office",
    "wof:placetype":"venue"
},
  "geometry": {"coordinates":[-48.635078,-22.5149],"type":"Point"}
}