{
  "type": "Feature",
  "properties": {
    "addr:full":"Postbus 366 'S-Hertogenbosch 5201 AJ",
    "addr:housenumber":"366",
    "addr:postcode":"5201 aj",
    "addr:street":"Postbus",
    "iso:country":"NL",
    "sg:address":"Postbus 366",
    "sg:city":"'S-Hertogenbosch",
    "sg:classifiers":[
        {
            "category":"Shopping",
            "subcategory":"News",
            "type":"Retail Goods"
        }
    ],
    "sg:phone":"+31 73 622 0269",
    "sg:postcode":"5201 AJ",
    "sg:tags":[
        "maandbladen",
        "en",
        "week-"
    ],
    "wof:name":"Bazuin, De",
    "wof:placetype":"venue"
},
  "geometry": {"coordinates":[5.304210186,51.6892204285],"type":"Point"}
}