{
  "type": "Feature",
  "properties": {
    "addr:full":"Gasthuisgraaf 13 Sittard Limburg 6136 KS",
    "addr:housenumber":"13",
    "addr:postcode":"6136 ks",
    "addr:street":"Gasthuisgraaf",
    "iso:country":"NL",
    "sg:address":"Gasthuisgraaf 13",
    "sg:city":"Sittard",
    "sg:orig_category":"Verpakkingen En Verpakkingsmaterialen",
    "sg:phone":"+31 46 451 2906",
    "sg:postcode":"6136 KS",
    "sg:province":"Limburg",
    "wof:name":"Schiffeleers Bv",
    "wof:placetype":"venue"
},
  "geometry": {"coordinates":[5.871495,51.015503],"type":"Point"}
}