{
  "type": "Feature",
  "properties": {
    "addr:full":"Tamboerstraat 4 Goirle Noord-Brabant 5051 JP",
    "addr:housenumber":"4",
    "addr:postcode":"5051 jp",
    "addr:street":"Tamboerstraat",
    "iso:country":"NL",
    "sg:address":"Tamboerstraat 4",
    "sg:city":"Goirle",
    "sg:classifiers":[
        {
            "category":"Education",
            "subcategory":"Preschool",
            "type":"Public Place"
        }
    ],
    "sg:phone":"+31 13 534 2263",
    "sg:postcode":"5051 JP",
    "sg:province":"Noord-Brabant",
    "sg:tags":[
        "kleuteronderwijs",
        "basis-"
    ],
    "wof:name":"Basisschool De Heibloem",
    "wof:placetype":"venue"
},
  "geometry": {"coordinates":[5.054018,51.518661],"type":"Point"}
}