{
  "type": "Feature",
  "properties": {
    "addr:full":"Haarensewg 49 Oisterwyk North Brabant 5061 VJ",
    "addr:housenumber":"49",
    "addr:postcode":"5061 vj",
    "addr:street":"Haarensewg",
    "iso:country":"NL",
    "sg:address":"Haarensewg 49",
    "sg:city":"Oisterwyk",
    "sg:orig_category":"Oldtimers",
    "sg:phone":"+31 13 528 4997",
    "sg:postcode":"5061 VJ",
    "sg:province":"North Brabant",
    "sg:website":"http://www.porscheclassics.nl",
    "wof:name":"Berry Smits",
    "wof:placetype":"venue"
},
  "geometry": {"coordinates":[5.201864,51.587021],"type":"Point"}
}