{
  "type": "Feature",
  "properties": {
    "addr:full":"Slotermeerlaan 152 Amsterdam North Holland 1063 JW",
    "addr:housenumber":"152",
    "addr:postcode":"1063 jw",
    "addr:street":"Slotermeerlaan",
    "iso:country":"NL",
    "sg:address":"Slotermeerlaan 152",
    "sg:city":"Amsterdam",
    "sg:orig_category":"Woningbouwverenigingen",
    "sg:phone":"+31 20 506 2100",
    "sg:postcode":"1063 JW",
    "sg:province":"North Holland",
    "wof:name":"Bouwvereniging Rochdale",
    "wof:placetype":"venue"
},
  "geometry": {"coordinates":[4.8220381737,52.3830566406],"type":"Point"}
}