{
  "type": "Feature",
  "properties": {
    "addr:full":"Slauerhofflaan 17 Raamsdonksveer Noord-Brabant 4942 DK",
    "addr:housenumber":"17",
    "addr:postcode":"4942 dk",
    "addr:street":"Slauerhofflaan",
    "iso:country":"NL",
    "sg:address":"Slauerhofflaan 17",
    "sg:city":"Raamsdonksveer",
    "sg:orig_category":"Kappers",
    "sg:phone":"+31 162 517 215",
    "sg:postcode":"4942 DK",
    "sg:province":"Noord-Brabant",
    "wof:name":"Astrid",
    "wof:placetype":"venue"
},
  "geometry": {"coordinates":[4.8722090721,51.702545166],"type":"Point"}
}