{
  "type": "Feature",
  "properties": {
    "addr:full":"Slotmansweg 3 Eibergen Gelderland 7152 AC",
    "addr:housenumber":"3",
    "addr:postcode":"7152 ac",
    "addr:street":"Slotmansweg;Gelderland",
    "iso:country":"NL",
    "sg:address":"Slotmansweg 3",
    "sg:city":"Eibergen",
    "sg:classifiers":[
        {
            "category":"Professional",
            "subcategory":"Accounting & Tax Preparation",
            "type":"Services"
        }
    ],
    "sg:phone":"+31 545 473 201",
    "sg:postcode":"7152 AC",
    "sg:province":"Gelderland",
    "sg:tags":[
        "accountant"
    ],
    "wof:name":"Accountantskantoor Drs. H. Jansen",
    "wof:placetype":"venue"
},
  "geometry": {"coordinates":[6.669879,52.115517],"type":"Point"}
}