{
  "type": "Feature",
  "properties": {
    "addr:full":"Tamboerstr 38B Rotterdam Zuid-Holland 3034 PW",
    "addr:housenumber":"38b",
    "addr:postcode":"3034 pw",
    "addr:street":"Tamboerstr",
    "iso:country":"NL",
    "sg:address":"Tamboerstr 38B",
    "sg:city":"Rotterdam",
    "sg:classifiers":[
        {
            "category":"Retail",
            "subcategory":"Auto Repair",
            "type":"Services"
        }
    ],
    "sg:phone":"+31 10 411 5374",
    "sg:postcode":"3034 PW",
    "sg:province":"Zuid-Holland",
    "sg:tags":[
        "garage"
    ],
    "wof:name":"Brug, Garage De",
    "wof:placetype":"venue"
},
  "geometry": {"coordinates":[4.496083,51.933041],"type":"Point"}
}