{
  "type": "Feature",
  "properties": {
    "addr:full":"De Goorn 72A De Goorn Noord-Holland 1648 JS",
    "addr:housenumber":"72a",
    "addr:postcode":"1648 js",
    "addr:street":"De Goorn",
    "iso:country":"NL",
    "sg:address":"De Goorn 72A",
    "sg:city":"De Goorn",
    "sg:orig_category":"Artsen - Huisartsen",
    "sg:phone":"+31 229 542 808",
    "sg:postcode":"1648 JS",
    "sg:province":"Noord-Holland",
    "sg:website":"http://www.hagrowk.nl",
    "wof:name":"Bemmel, M D Van",
    "wof:placetype":"venue"
},
  "geometry": {"coordinates":[4.94819,52.630638],"type":"Point"}
}