{
  "type": "Feature",
  "properties": {
    "addr:full":"Oudkerkseweg 20 Giessenburg Zuid-Holland 3381 KR",
    "addr:housenumber":"20",
    "addr:postcode":"3381 kr",
    "addr:street":"Oudkerkseweg",
    "iso:country":"NL",
    "sg:address":"Oudkerkseweg 20",
    "sg:city":"Giessenburg",
    "sg:orig_category":"Overheidsdiensten",
    "sg:phone":"+31 184 651 407",
    "sg:postcode":"3381 KR",
    "sg:province":"Zuid-Holland",
    "wof:name":"De Oude School",
    "wof:placetype":"venue"
},
  "geometry": {"coordinates":[4.8670320511,51.8445167542],"type":"Point"}
}