{
  "type": "Feature",
  "properties": {
    "addr:full":"P C Hooftlaan 50 Soest Utrecht 3768 GT",
    "addr:housenumber":"50",
    "addr:postcode":"3768 gt",
    "addr:street":"P C Hooftlaan",
    "iso:country":"NL",
    "sg:address":"P C Hooftlaan 50",
    "sg:city":"Soest",
    "sg:orig_category":"Boekhouders",
    "sg:phone":"+31 35 603 3834",
    "sg:postcode":"3768 GT",
    "sg:province":"Utrecht",
    "wof:name":"Dekker Administratie En Belastingen",
    "wof:placetype":"venue"
},
  "geometry": {"coordinates":[5.309159,52.160866],"type":"Point"}
}