{
  "type": "Feature",
  "properties": {
    "addr:full":"Biarritzplein 15 Eindhoven North Brabant 5627 LE",
    "addr:housenumber":"15",
    "addr:postcode":"5627 le",
    "addr:street":"Biarritzplein",
    "iso:country":"NL",
    "sg:address":"Biarritzplein 15",
    "sg:city":"Eindhoven",
    "sg:classifiers":[
        {
            "category":"Fast Food",
            "type":"Food & Drink"
        }
    ],
    "sg:phone":"+31 40 241 8750",
    "sg:postcode":"5627 LE",
    "sg:province":"North Brabant",
    "sg:tags":[
        "afhaal",
        "restaurant"
    ],
    "wof:name":"Mangerie Biarritz",
    "wof:placetype":"venue"
},
  "geometry": {"coordinates":[5.448701,51.482841],"type":"Point"}
}