{
  "type": "Feature",
  "properties": {
    "addr:full":"Jan Van Der Heijdenstr 27 Oud Beijerland Zuid-Holland 3261 LE",
    "addr:housenumber":"27",
    "addr:postcode":"3261 le",
    "addr:street":"Jan Van Der Heijdenstr;Oud Beijerland",
    "iso:country":"NL",
    "sg:address":"Jan Van Der Heijdenstr 27",
    "sg:city":"Oud Beijerland",
    "sg:orig_category":"Waterbeheer",
    "sg:phone":"+31 186 631 500",
    "sg:postcode":"3261 LE",
    "sg:province":"Zuid-Holland",
    "wof:name":"Waterbedrijf Europoort Nv",
    "wof:placetype":"venue"
},
  "geometry": {"coordinates":[4.4370560646,51.827129364],"type":"Point"}
}