{
  "type": "Feature",
  "properties": {
    "addr:full":"Koperslagerstr 5 Zwolle Overijssel 8043 EL",
    "addr:housenumber":"5",
    "addr:postcode":"8043 el",
    "addr:street":"Koperslagerstr",
    "iso:country":"NL",
    "sg:address":"Koperslagerstr 5",
    "sg:city":"Zwolle",
    "sg:orig_category":"Adviesbureaus Bedrijfsorganisatie",
    "sg:phone":"+31 38 460 3495",
    "sg:postcode":"8043 EL",
    "sg:province":"Overijssel",
    "sg:website":"http://www.clickadvies.nl",
    "wof:name":"Click Advies",
    "wof:placetype":"venue"
},
  "geometry": {"coordinates":[6.062003,52.536415],"type":"Point"}
}