{
  "type": "Feature",
  "properties": {
    "addr:full":"Stromarkt 25-26 Deventer Overijssel 7411 PK",
    "addr:housenumber":"25-26",
    "addr:postcode":"7411 pk",
    "addr:street":"Stromarkt",
    "iso:country":"NL",
    "sg:address":"Stromarkt 25-26",
    "sg:city":"Deventer",
    "sg:orig_category":"Biljartzalen",
    "sg:phone":"+31 570 643 931",
    "sg:postcode":"7411 PK",
    "sg:province":"Overijssel",
    "wof:name":"Poolroom Biljartcentrum, The",
    "wof:placetype":"venue"
},
  "geometry": {"coordinates":[6.154981,52.253059],"type":"Point"}
}