{
  "type": "Feature",
  "properties": {
    "iso:country":"NL",
    "sg:address":"Ten Katestraat 2",
    "sg:city":"Amsterdam",
    "sg:orig_category":"Meubelzaken, Woning- And Keukeninrichting",
    "sg:phone":"+31 20 683 8894",
    "sg:postcode":"1053 CE",
    "sg:province":"Noord-Holland",
    "wof:name":"Henk En Bep",
    "wof:placetype":"venue"
},
  "geometry": {"coordinates":[4.866027,52.367981],"type":"Point"}
}