{
  "type": "Feature",
  "properties": {
    "addr:full":"Ten Katestraat 2 Amsterdam Noord-Holland 1053 CE",
    "addr:housenumber":"2",
    "addr:postcode":"1053 ce",
    "addr:street":"Ten Katestraat",
    "iso:country":"NL",
    "sg:address":"Ten Katestraat 2",
    "sg:city":"Amsterdam",
    "sg:orig_category":"Meubelzaken, Woning- And Keukeninrichting",
    "sg:phone":"+31 20 683 8894",
    "sg:postcode":"1053 CE",
    "sg:province":"Noord-Holland",
    "wof:name":"Henk En Bep",
    "wof:placetype":"venue"
},
  "geometry": {"coordinates":[4.866027,52.367981],"type":"Point"}
}