{
  "type": "Feature",
  "properties": {
    "addr:full":"P Krugerstr 88 Vlissingen Zeeland 4381 WH",
    "addr:housenumber":"88",
    "addr:postcode":"4381 wh",
    "iso:country":"NL",
    "sg:address":"P Krugerstr 88",
    "sg:city":"Vlissingen",
    "sg:orig_category":"Kappers",
    "sg:phone":"+31 118 412 139",
    "sg:postcode":"4381 WH",
    "sg:province":"Zeeland",
    "wof:name":"Morsheim Kapsalon",
    "wof:placetype":"venue"
},
  "geometry": {"coordinates":[3.570975,51.448196],"type":"Point"}
}