{
  "type": "Feature",
  "properties": {
    "addr:full":"Marinierswg 1 Rotterdam South Holland 3011 NB",
    "addr:housenumber":"1",
    "addr:postcode":"3011 nb",
    "addr:street":"Marinierswg",
    "iso:country":"NL",
    "sg:address":"Marinierswg 1",
    "sg:city":"Rotterdam",
    "sg:orig_category":"Woninginrichting",
    "sg:phone":"+31 10 240 9379",
    "sg:postcode":"3011 NB",
    "sg:province":"South Holland",
    "wof:name":"Binnen, Van",
    "wof:placetype":"venue"
},
  "geometry": {"coordinates":[4.4885568619,51.9242324829],"type":"Point"}
}