{
  "type": "Feature",
  "properties": {
    "addr:full":"Parkhaven 7 Stellendam South Holland 3251 BK",
    "addr:housenumber":"7",
    "addr:postcode":"3251 bk",
    "addr:street":"Parkhaven",
    "iso:country":"NL",
    "sg:address":"Parkhaven 7",
    "sg:city":"Stellendam",
    "sg:orig_category":"Oud Metaal",
    "sg:phone":"+31 187 492 807",
    "sg:postcode":"3251 BK",
    "sg:province":"South Holland",
    "wof:name":"Netten, W",
    "wof:placetype":"venue"
},
  "geometry": {"coordinates":[4.0327949524,51.8054084778],"type":"Point"}
}