{
  "type": "Feature",
  "properties": {
    "addr:full":"Sint Pieterstraat 37 Middelburg Zeeland 4331 EV",
    "addr:housenumber":"37",
    "addr:postcode":"4331 ev",
    "addr:street":"Sint Pieterstraat",
    "iso:country":"NL",
    "sg:address":"Sint Pieterstraat 37",
    "sg:city":"Middelburg",
    "sg:orig_category":"Fotostudio'S And Fotografen",
    "sg:phone":"+31 118 616 120",
    "sg:postcode":"4331 EV",
    "sg:province":"Zeeland",
    "wof:name":"Anda Van Riet",
    "wof:placetype":"venue"
},
  "geometry": {"coordinates":[3.616059,51.50066],"type":"Point"}
}