{
  "type": "Feature",
  "properties": {
    "addr:full":"Suikerbakkerstraat 40 Hoogvliet Rt South Holland 3194 AK",
    "addr:housenumber":"40",
    "addr:postcode":"3194 ak",
    "addr:street":"Suikerbakkerstraat;Rt South",
    "iso:country":"NL",
    "sg:address":"Suikerbakkerstraat 40",
    "sg:city":"Hoogvliet Rt",
    "sg:classifiers":[
        {
            "category":"Professional",
            "subcategory":"Accounting & Tax Preparation",
            "type":"Services"
        }
    ],
    "sg:phone":"+31 10 416 4377",
    "sg:postcode":"3194 AK",
    "sg:province":"South Holland",
    "sg:tags":[
        "accountant"
    ],
    "wof:name":"Van Kempen Van Vuren & Partners Bv Acc &",
    "wof:placetype":"venue"
},
  "geometry": {"coordinates":[4.377634,51.868523],"type":"Point"}
}