{
  "type": "Feature",
  "properties": {
    "addr:full":"Wakkerendk 4/A Eemnes Utrecht 3755 DC",
    "addr:housenumber":"4 / a",
    "addr:postcode":"3755",
    "addr:street":"Wakkerendk",
    "iso:country":"NL",
    "sg:address":"Wakkerendk 4/A",
    "sg:city":"Eemnes",
    "sg:orig_category":"Adviesbureaus Personeel",
    "sg:phone":"+31 35 531 4337",
    "sg:postcode":"3755 DC",
    "sg:province":"Utrecht",
    "wof:name":"Bbos",
    "wof:placetype":"venue"
},
  "geometry": {"coordinates":[5.266767,52.252247],"type":"Point"}
}