{
  "type": "Feature",
  "properties": {
    "addr:full":"Visser 25 Deurne Noord-Brabant 5751 BL",
    "addr:housenumber":"25",
    "addr:postcode":"5751 bl",
    "addr:street":"Visser",
    "iso:country":"NL",
    "sg:address":"Visser 25",
    "sg:city":"Deurne",
    "sg:orig_category":"Bedrijfsmechanisatie En -Automatisering",
    "sg:phone":"+31 493 351 020",
    "sg:postcode":"5751 BL",
    "sg:province":"Noord-Brabant",
    "wof:name":"Snijder",
    "wof:placetype":"venue"
},
  "geometry": {"coordinates":[5.792727,51.465103],"type":"Point"}
}