{
  "type": "Feature",
  "properties": {
    "addr:full":"Strandplevier 28 Bergen Op Zoom Noord-Brabant 4617 JN",
    "addr:housenumber":"28",
    "addr:postcode":"4617 jn",
    "addr:street":"Strandplevier",
    "iso:country":"NL",
    "sg:address":"Strandplevier 28",
    "sg:city":"Bergen Op Zoom",
    "sg:orig_category":"Keukens",
    "sg:phone":"+31 164 606 066",
    "sg:postcode":"4617 JN",
    "sg:province":"Noord-Brabant",
    "wof:name":"Belde, Jasper",
    "wof:placetype":"venue"
},
  "geometry": {"coordinates":[4.26558,51.479126],"type":"Point"}
}