{
  "type": "Feature",
  "properties": {
    "addr:full":"Donkerstraat 45 Harderwijk Gelderland 3841 CB",
    "addr:housenumber":"45",
    "addr:postcode":"3841 cb",
    "addr:street":"Donkerstraat;Gelderland",
    "iso:country":"NL",
    "sg:address":"Donkerstraat 45",
    "sg:city":"Harderwijk",
    "sg:orig_category":"Discountwinkels",
    "sg:phone":"+31 341 434 862",
    "sg:postcode":"3841 CB",
    "sg:province":"Gelderland",
    "wof:name":"Zeeman Textielsupers",
    "wof:placetype":"venue"
},
  "geometry": {"coordinates":[5.617588,52.349293],"type":"Point"}
}