{
  "type": "Feature",
  "properties": {
    "addr:full":"Margrietstr 3 Groesbeek Gelderland 6561 WS",
    "addr:housenumber":"3",
    "addr:postcode":"6561 ws",
    "addr:street":"Margrietstr;Gelderland",
    "iso:country":"NL",
    "sg:address":"Margrietstr 3",
    "sg:city":"Groesbeek",
    "sg:orig_category":"Parketvloeren",
    "sg:phone":"+31 24 397 4944",
    "sg:postcode":"6561 WS",
    "sg:province":"Gelderland",
    "wof:name":"Lema Vof",
    "wof:placetype":"venue"
},
  "geometry": {"coordinates":[5.924893,51.783985],"type":"Point"}
}