{
  "type": "Feature",
  "properties": {
    "addr:full":"Handelswg 15 Emmen Drenthe 7826 TC",
    "addr:housenumber":"15",
    "addr:postcode":"7826 tc",
    "addr:street":"Handelswg",
    "iso:country":"NL",
    "sg:address":"Handelswg 15",
    "sg:city":"Emmen",
    "sg:orig_category":"Kantoor- En Bedrijfsmeubelen - Fabrieken En Groothandel",
    "sg:phone":"+31 591 622 500",
    "sg:postcode":"7826 TC",
    "sg:province":"Drenthe",
    "wof:name":"Delmar Bv, De",
    "wof:placetype":"venue"
},
  "geometry": {"coordinates":[6.9521222115,52.776473999],"type":"Point"}
}