{
  "type": "Feature",
  "properties": {
    "iso:country":"NL",
    "sg:address":"Voltastr 21",
    "sg:city":"Purmerend",
    "sg:orig_category":"Verzekeringen - Verzekeringskantoren",
    "sg:phone":"+31 299 415 954",
    "sg:postcode":"1446 VA",
    "sg:province":"North Holland",
    "wof:name":"Attentiv",
    "wof:placetype":"venue"
},
  "geometry": {"coordinates":[5.002637,52.515823],"type":"Point"}
}