{
  "type": "Feature",
  "properties": {
    "addr:full":"Voltastr 21 Purmerend North Holland 1446 VA",
    "addr:housenumber":"21",
    "addr:postcode":"1446",
    "addr:street":"Voltastr",
    "iso:country":"NL",
    "sg:address":"Voltastr 21",
    "sg:city":"Purmerend",
    "sg:orig_category":"Verzekeringen - Verzekeringskantoren",
    "sg:phone":"+31 299 415 954",
    "sg:postcode":"1446 VA",
    "sg:province":"North Holland",
    "wof:name":"Attentiv",
    "wof:placetype":"venue"
},
  "geometry": {"coordinates":[5.002637,52.515823],"type":"Point"}
}