{
  "type": "Feature",
  "properties": {
    "addr:full":"West 33 Hoorn Nh North Holland 1621 AT",
    "addr:housenumber":"33",
    "addr:postcode":"1621",
    "addr:street":"West;Nh North",
    "iso:country":"NL",
    "sg:address":"West 33",
    "sg:city":"Hoorn Nh",
    "sg:classifiers":[
        {
            "category":"Fast Food",
            "type":"Food & Drink"
        }
    ],
    "sg:phone":"+31 229 270 608",
    "sg:postcode":"1621 AT",
    "sg:province":"North Holland",
    "sg:tags":[
        "afhaal",
        "restaurant"
    ],
    "wof:name":"Sphinx Ii",
    "wof:placetype":"venue"
},
  "geometry": {"coordinates":[5.058585,52.638733],"type":"Point"}
}