{
  "type": "Feature",
  "properties": {
    "addr:full":"Daalakkerswg 8 Eindhoven North Brabant 5641 JA",
    "addr:housenumber":"8",
    "addr:postcode":"5641 ja",
    "addr:street":"Daalakkerswg",
    "iso:country":"NL",
    "sg:address":"Daalakkerswg 8",
    "sg:city":"Eindhoven",
    "sg:orig_category":"Machinefabrieken",
    "sg:phone":"+31 40 282 9922",
    "sg:postcode":"5641 JA",
    "sg:province":"North Brabant",
    "sg:website":"http://www.sim.storkgroup.com",
    "wof:name":"Stork",
    "wof:placetype":"venue"
},
  "geometry": {"coordinates":[5.523125,51.447018],"type":"Point"}
}