{
  "type": "Feature",
  "properties": {
    "addr:full":"Raadhuisstraat 9 Enschede NL.08 7511 HJ",
    "addr:housenumber":"9",
    "addr:postcode":"7511 hj",
    "addr:street":"Raadhuisstraat",
    "iso:country":"NL",
    "sg:address":"Raadhuisstraat 9",
    "sg:city":"Enschede",
    "sg:orig_category":"Schoenen",
    "sg:phone":"+31 53 432 3419",
    "sg:postcode":"7511 HJ",
    "sg:province":"NL.08",
    "wof:name":"Manfield Bv",
    "wof:placetype":"venue"
},
  "geometry": {"coordinates":[6.896499,52.218609],"type":"Point"}
}