{
  "type": "Feature",
  "properties": {
    "addr:full":"Monteverdiln 202 Zwolle NL.08 8031 DW",
    "addr:housenumber":"202",
    "addr:postcode":"8031 dw",
    "iso:country":"NL",
    "sg:address":"Monteverdiln 202",
    "sg:city":"Zwolle",
    "sg:orig_category":"Scholen Voor Basisonderwijs",
    "sg:phone":"+31 38 454 0744",
    "sg:postcode":"8031 DW",
    "sg:province":"NL.08",
    "wof:name":"Carillon Prot Chr, Het",
    "wof:placetype":"venue"
},
  "geometry": {"coordinates":[6.090213,52.522987],"type":"Point"}
}