{
  "type": "Feature",
  "properties": {
    "addr:full":"Markt 1 Linne Maine 6067 BS",
    "addr:housenumber":"1",
    "addr:postcode":"6067 bs",
    "addr:street":"Markt",
    "iso:country":"NL",
    "sg:address":"Markt 1",
    "sg:city":"Linne",
    "sg:orig_category":"Verenigingsgebouwen",
    "sg:phone":"+31 475 462 633",
    "sg:postcode":"6067 BS",
    "sg:province":"Maine",
    "wof:name":"Pool, De",
    "wof:placetype":"venue"
},
  "geometry": {"coordinates":[-67.840874,46.241039],"type":"Point"}
}