{
  "type": "Feature",
  "properties": {
    "addr:full":"Raadhuisstraat 1 Beilen Drenthe 9411 NA",
    "addr:housenumber":"1",
    "addr:postcode":"9411 na",
    "addr:street":"Raadhuisstraat",
    "iso:country":"NL",
    "sg:address":"Raadhuisstraat 1",
    "sg:city":"Beilen",
    "sg:classifiers":[
        {
            "category":"Retail",
            "subcategory":"Photofinishing",
            "type":"Services"
        }
    ],
    "sg:phone":"+31 593 522 136",
    "sg:postcode":"9411 NA",
    "sg:province":"Drenthe",
    "sg:tags":[
        "foto",
        "film"
    ],
    "wof:name":"Fotoplus Marloes Vof",
    "wof:placetype":"venue"
},
  "geometry": {"coordinates":[6.515167,52.859516],"type":"Point"}
}