{
  "type": "Feature",
  "properties": {
    "addr:full":"Stationshal 7 Utrecht Utrecht 3511 CE",
    "addr:housenumber":"7",
    "addr:postcode":"3511 ce",
    "addr:street":"Stationshal",
    "iso:country":"NL",
    "sg:address":"Stationshal 7",
    "sg:city":"Utrecht",
    "sg:classifiers":[
        {
            "category":"Fast Food",
            "type":"Food & Drink"
        }
    ],
    "sg:phone":"+31 30 670 1220",
    "sg:postcode":"3511 CE",
    "sg:province":"Utrecht",
    "sg:tags":[
        "afhaal",
        "restaurant"
    ],
    "wof:name":"Tiny Tokyo",
    "wof:placetype":"venue"
},
  "geometry": {"coordinates":[5.10982,52.089252],"type":"Point"}
}