{
  "type": "Feature",
  "properties": {
    "addr:full":"Lessingln 107 Utrecht Utrecht 3533 AV",
    "addr:housenumber":"107",
    "addr:postcode":"3533 av",
    "iso:country":"NL",
    "sg:address":"Lessingln 107",
    "sg:city":"Utrecht",
    "sg:orig_category":"Journalisten Freelance",
    "sg:phone":"+31 30 294 2419",
    "sg:postcode":"3533 AV",
    "sg:province":"Utrecht",
    "wof:name":"Kreugel, G A",
    "wof:placetype":"venue"
},
  "geometry": {"coordinates":[5.082804,52.087681],"type":"Point"}
}