{
  "type": "Feature",
  "properties": {
    "addr:full":"Korenstraat 27 Apeldoorn Gelderland 7311 LM",
    "addr:housenumber":"27",
    "addr:postcode":"7311 lm",
    "addr:street":"Korenstraat;Gelderland",
    "iso:country":"NL",
    "sg:address":"Korenstraat 27",
    "sg:city":"Apeldoorn",
    "sg:orig_category":"Erotische Etablissementen",
    "sg:phone":"+31 55 521 6493",
    "sg:postcode":"7311 LM",
    "sg:province":"Gelderland",
    "wof:name":"Sexcentrum Apeldoorn",
    "wof:placetype":"venue"
},
  "geometry": {"coordinates":[5.960386,52.21447],"type":"Point"}
}