{
  "type": "Feature",
  "properties": {
    "addr:full":"Ter Apelkanaal Oost 113 Ter Apelkanaal Groningen 9563 RE",
    "addr:housenumber":"113",
    "addr:postcode":"9563 re",
    "addr:street":"Ter Apelkanaal Oost;Ter",
    "iso:country":"NL",
    "sg:address":"Ter Apelkanaal Oost 113",
    "sg:city":"Ter Apelkanaal",
    "sg:classifiers":[
        {
            "category":"Education",
            "subcategory":"Preschool",
            "type":"Public Place"
        }
    ],
    "sg:phone":"+31 599 416 425",
    "sg:postcode":"9563 RE",
    "sg:province":"Groningen",
    "sg:tags":[
        "kleuteronderwijs",
        "basis-"
    ],
    "wof:name":"Openbare Basisschool De Klimop",
    "wof:placetype":"venue"
},
  "geometry": {"coordinates":[7.048549,52.912231],"type":"Point"}
}