{
  "type": "Feature",
  "properties": {
    "addr:full":"A Het Verguld Harnas 6 'S Hertogenbosch North Brabant 5211 HL",
    "addr:housenumber":"6 ' s",
    "addr:postcode":"5211 hl",
    "addr:street":"A;Verguld Harnas;Hertogenbosch",
    "iso:country":"NL",
    "sg:address":"A Het Verguld Harnas 6",
    "sg:city":"'S Hertogenbosch",
    "sg:classifiers":[
        {
            "category":"Fast Food",
            "type":"Food & Drink"
        }
    ],
    "sg:phone":"+31 73 614 1389",
    "sg:postcode":"5211 HL",
    "sg:province":"North Brabant",
    "sg:tags":[
        "afhaal",
        "restaurant"
    ],
    "wof:name":"De Passanterie",
    "wof:placetype":"venue"
},
  "geometry": {"coordinates":[5.29302,51.683041],"type":"Point"}
}