{
  "type": "Feature",
  "properties": {
    "iso:country":"NL",
    "sg:address":"Prins Mauritsstraat 35",
    "sg:city":"Maassluis",
    "sg:orig_category":"Antiekzaken",
    "sg:phone":"+31 10 592 2620",
    "sg:postcode":"3143 LL",
    "sg:province":"Zuid-Holland",
    "wof:name":"Varro",
    "wof:placetype":"venue"
},
  "geometry": {"coordinates":[4.25687,51.916794],"type":"Point"}
}