{
  "type": "Feature",
  "properties": {
    "iso:country":"NL",
    "sg:address":"Steenwg Op Zevendonk 69",
    "sg:city":"Turnhout",
    "sg:orig_category":"Beveiliging",
    "sg:phone":"+31 14437999",
    "sg:postcode":"B-23 00",
    "sg:website":"http://www.maasbeveiligingstechniek.be",
    "wof:name":"Maas Beveiligingstechniek",
    "wof:placetype":"venue"
},
  "geometry": {"coordinates":[4.950275,51.317551],"type":"Point"}
}