{
  "type": "Feature",
  "properties": {
    "addr:full":"Vogelzangsekd 11 Lopik Utrecht 3411 JS",
    "addr:housenumber":"11",
    "addr:postcode":"3411 js",
    "addr:street":"Vogelzangsekd",
    "iso:country":"NL",
    "sg:address":"Vogelzangsekd 11",
    "sg:city":"Lopik",
    "sg:orig_category":"Onderhoudswerken",
    "sg:phone":"+31 348 551 738",
    "sg:postcode":"3411 JS",
    "sg:province":"Utrecht",
    "wof:name":"Renes, C",
    "wof:placetype":"venue"
},
  "geometry": {"coordinates":[4.969197,51.977524],"type":"Point"}
}