{
  "type": "Feature",
  "properties": {
    "iso:country":"NL",
    "sg:address":"Hellendoornsewg 8-10",
    "sg:city":"Marienheem",
    "sg:orig_category":"Fietsen En Bromfietsen",
    "sg:phone":"+31 572 351 839",
    "sg:postcode":"8106 AJ",
    "sg:province":"Overijssel",
    "wof:name":"Kruiper, Fa",
    "wof:placetype":"venue"
},
  "geometry": {"coordinates":[6.322795,52.38216],"type":"Point"}
}