{
  "type": "Feature",
  "properties": {
    "addr:full":"Spuipad 23 Stellendam Zuid-Holland 3251 LS",
    "addr:housenumber":"23",
    "addr:postcode":"3251 ls",
    "addr:street":"Spuipad",
    "iso:country":"NL",
    "sg:address":"Spuipad 23",
    "sg:city":"Stellendam",
    "sg:orig_category":"Autokeuringen",
    "sg:phone":"+31 187 603 841",
    "sg:postcode":"3251 LS",
    "sg:province":"Zuid-Holland",
    "wof:name":"Noordijk Mobiele Car Cleaning",
    "wof:placetype":"venue"
},
  "geometry": {"coordinates":[4.028769,51.80719],"type":"Point"}
}