{
  "type": "Feature",
  "properties": {
    "addr:full":"Brink 27 Roden Drenthe 9301 JK",
    "addr:housenumber":"27",
    "addr:postcode":"9301 jk",
    "addr:street":"Brink",
    "iso:country":"NL",
    "sg:address":"Brink 27",
    "sg:city":"Roden",
    "sg:classifiers":[
        {
            "category":"Travel",
            "subcategory":"Hotels & Motels",
            "type":"Entertainment"
        }
    ],
    "sg:phone":"+31 50 501 9021",
    "sg:postcode":"9301 JK",
    "sg:province":"Drenthe",
    "sg:website":"http://www.hotelonderdelinden.nl",
    "wof:name":"Onder De Linden",
    "wof:placetype":"venue"
},
  "geometry": {"coordinates":[6.432336,53.134892],"type":"Point"}
}