{
  "type": "Feature",
  "properties": {
    "addr:full":"Groene Kruisstraat 30 Kerkrade Limburg 6466 LM",
    "addr:housenumber":"30",
    "addr:postcode":"6466 lm",
    "addr:street":"Groene Kruisstraat",
    "iso:country":"NL",
    "sg:address":"Groene Kruisstraat 30",
    "sg:city":"Kerkrade",
    "sg:orig_category":"Kappers",
    "sg:phone":"+31 45 541 7628",
    "sg:postcode":"6466 LM",
    "sg:province":"Limburg",
    "wof:name":"Marlene",
    "wof:placetype":"venue"
},
  "geometry": {"coordinates":[6.0221,50.855362],"type":"Point"}
}