{
  "type": "Feature",
  "properties": {
    "addr:full":"H Loonstrastr 18 Jistrum Friesland 9258 CZ",
    "addr:housenumber":"18",
    "addr:postcode":"9258",
    "iso:country":"NL",
    "sg:address":"H Loonstrastr 18",
    "sg:city":"Jistrum",
    "sg:orig_category":"Paardensport",
    "sg:phone":"+31 512 472 988",
    "sg:postcode":"9258 CZ",
    "sg:province":"Friesland",
    "wof:name":"Midwoud, A Van",
    "wof:placetype":"venue"
},
  "geometry": {"coordinates":[15.47527,49.803791],"type":"Point"}
}