{
  "type": "Feature",
  "properties": {
    "iso:country":"NL",
    "sg:address":"Elektronwg 34",
    "sg:city":"Utrecht",
    "sg:orig_category":"Horecabenodigdheden",
    "sg:phone":"+31 30 241 0400",
    "sg:postcode":"3542 AC",
    "sg:province":"Utrecht",
    "wof:name":"Helal",
    "wof:placetype":"venue"
},
  "geometry": {"coordinates":[5.074515,52.099182],"type":"Point"}
}