{
  "type": "Feature",
  "properties": {
    "addr:full":"Past. Van Haarenstraat 15-17 Veghel Noord-Brabant 5464 VD",
    "addr:housenumber":"15-17",
    "addr:postcode":"veghel;5464 vd",
    "addr:street":"Past. Van Haarenstraat",
    "iso:country":"NL",
    "sg:address":"Past. Van Haarenstraat 15-17",
    "sg:city":"Veghel",
    "sg:orig_category":"Meubelzaken, Woning- And Keukeninrichting",
    "sg:phone":"+31 413 366 076",
    "sg:postcode":"5464 VD",
    "sg:province":"Noord-Brabant",
    "wof:name":"Eurobed",
    "wof:placetype":"venue"
},
  "geometry": {"coordinates":[5.578838,51.632336],"type":"Point"}
}