{
  "type": "Feature",
  "properties": {
    "iso:country":"NL",
    "sg:address":"Spielehorst 6",
    "sg:city":"Enschede",
    "sg:orig_category":"Oldtimers",
    "sg:phone":"+31 53 432 6588",
    "sg:postcode":"7531 ER",
    "sg:province":"Overijssel",
    "wof:name":"Renault 4 Club Ned",
    "wof:placetype":"venue"
},
  "geometry": {"coordinates":[6.928125,52.224899],"type":"Point"}
}