{
  "type": "Feature",
  "properties": {
    "iso:country":"NL",
    "sg:address":"Marktstraat 23",
    "sg:city":"Wierden",
    "sg:orig_category":"Bloemen And Planten",
    "sg:phone":"+31 546 575 427",
    "sg:postcode":"7642 AK",
    "sg:province":"Overijssel",
    "wof:name":"De Bloemenschuur",
    "wof:placetype":"venue"
},
  "geometry": {"coordinates":[6.59029,52.3577],"type":"Point"}
}