{
  "type": "Feature",
  "properties": {
    "addr:full":"Aucubastr 3 S Gravenhage Zuid-Holland 2565 XD",
    "addr:housenumber":"3;gravenhage",
    "addr:postcode":"2565 xd",
    "addr:street":"Aucubastr;S",
    "iso:country":"NL",
    "sg:address":"Aucubastr 3",
    "sg:city":"S Gravenhage",
    "sg:orig_category":"Scholen Voor Basisonderwijs",
    "sg:phone":"+31 70 363 4509",
    "sg:postcode":"2565 XD",
    "sg:province":"Zuid-Holland",
    "sg:website":"http://www.hoftad.net/bontevlinder",
    "wof:name":"Bonte Vlinder Sbo, De",
    "wof:placetype":"venue"
},
  "geometry": {"coordinates":[4.26129,52.076382],"type":"Point"}
}