{
  "type": "Feature",
  "properties": {
    "addr:full":"Z Havenwg 20 Hengelo Ov NL.08 7554 RR",
    "addr:housenumber":"20",
    "addr:postcode":"7554 rr",
    "addr:street":"Ov",
    "iso:country":"NL",
    "sg:address":"Z Havenwg 20",
    "sg:city":"Hengelo Ov",
    "sg:orig_category":"Dierenvoeder - Fabrieken",
    "sg:phone":"+31 74 291 7061",
    "sg:postcode":"7554 RR",
    "sg:province":"NL.08",
    "sg:website":"http://www.schoutenproducts.com",
    "wof:name":"Schouten Industries Bv",
    "wof:placetype":"venue"
},
  "geometry": {"coordinates":[6.741497,52.212124],"type":"Point"}
}