{
  "type": "Feature",
  "properties": {
    "iso:country":"NL",
    "sg:address":"H Lodeizenstr 28",
    "sg:city":"Groningen",
    "sg:orig_category":"Zonnebanken En Solarium-Installaties",
    "sg:phone":"+31 50 579 0568",
    "sg:postcode":"9745 DS",
    "sg:province":"Groningen",
    "sg:website":"http://www.go.to/bootsma",
    "wof:name":"Bootsma, Zonnehemelverhuur",
    "wof:placetype":"venue"
},
  "geometry": {"coordinates":[6.513081,53.223747],"type":"Point"}
}