{
  "type": "Feature",
  "properties": {
    "addr:full":"L Voren 30 Eersel Noord-Brabant 5521 DD",
    "addr:housenumber":"30",
    "addr:postcode":"5521 dd",
    "addr:street":"L Voren",
    "iso:country":"NL",
    "sg:address":"L Voren 30",
    "sg:city":"Eersel",
    "sg:orig_category":"Wegenbouw",
    "sg:phone":"+31 497 512 792",
    "sg:postcode":"5521 DD",
    "sg:province":"Noord-Brabant",
    "wof:name":"Webo Bv",
    "wof:placetype":"venue"
},
  "geometry": {"coordinates":[5.3152709007,51.3656234741],"type":"Point"}
}