{
  "type": "Feature",
  "properties": {
    "addr:full":"Utrechtse Veer 31 Leiden Zuid-Holland 2311 ND",
    "addr:housenumber":"31",
    "addr:postcode":"2311 nd",
    "addr:street":"Utrechtse Veer",
    "iso:country":"NL",
    "sg:address":"Utrechtse Veer 31",
    "sg:city":"Leiden",
    "sg:orig_category":"Biljartzalen",
    "sg:phone":"+31 71 512 0057",
    "sg:postcode":"2311 ND",
    "sg:province":"Zuid-Holland",
    "sg:website":"http://www.desnookerij.nl",
    "wof:name":"Snookerij, De",
    "wof:placetype":"venue"
},
  "geometry": {"coordinates":[4.501926,52.155743],"type":"Point"}
}