{
  "type": "Feature",
  "properties": {
    "iso:country":"NL",
    "sg:address":"Beuklaan 16",
    "sg:city":"Pijnacker",
    "sg:orig_category":"Huizensloop And Bouwrijp Maken",
    "sg:phone":"+31 15 369 3976",
    "sg:postcode":"2641 AT",
    "sg:province":"Zuid-Holland",
    "wof:name":"M.C. Verhoef",
    "wof:placetype":"venue"
},
  "geometry": {"coordinates":[4.428792,52.021587],"type":"Point"}
}