{
  "type": "Feature",
  "properties": {
    "addr:full":"Tjaskerlaan 38 Rotterdam Zuid-Holland 3052 HR",
    "addr:housenumber":"38",
    "addr:postcode":"3052 hr",
    "addr:street":"Tjaskerlaan",
    "iso:country":"NL",
    "sg:address":"Tjaskerlaan 38",
    "sg:city":"Rotterdam",
    "sg:orig_category":"Binnenhuisarchitecten",
    "sg:phone":"+31 10 418 9436",
    "sg:postcode":"3052 HR",
    "sg:province":"Zuid-Holland",
    "wof:name":"D.M. Andeweg",
    "wof:placetype":"venue"
},
  "geometry": {"coordinates":[4.475566,51.954727],"type":"Point"}
}