{
  "type": "Feature",
  "properties": {
    "addr:full":"De Wissel 17B St Annaparochie Friesland 9076 PT",
    "addr:housenumber":"17b",
    "addr:postcode":"9076 pt",
    "addr:street":"De Wissel;St",
    "iso:country":"NL",
    "sg:address":"De Wissel 17B",
    "sg:city":"St Annaparochie",
    "sg:orig_category":"Autoschade- Herstelbedrijven",
    "sg:phone":"+31 518 491 515",
    "sg:postcode":"9076 PT",
    "sg:province":"Friesland",
    "sg:website":"http://www.autoschade-faber.nl",
    "wof:name":"Faber Vof, Richard",
    "wof:placetype":"venue"
},
  "geometry": {"coordinates":[5.65766,53.27393],"type":"Point"}
}