{
  "type": "Feature",
  "properties": {
    "addr:full":"Wilhelminalaan 25 Sassenheim South Holland 2171 CS",
    "addr:housenumber":"25",
    "addr:postcode":"2171 cs",
    "addr:street":"Wilhelminalaan",
    "iso:country":"NL",
    "sg:address":"Wilhelminalaan 25",
    "sg:city":"Sassenheim",
    "sg:orig_category":"Overheidsdiensten",
    "sg:phone":"+31 252 242 242",
    "sg:postcode":"2171 CS",
    "sg:province":"South Holland",
    "wof:name":"Gemeente Sassenheim",
    "wof:placetype":"venue"
},
  "geometry": {"coordinates":[4.5188598633,52.2271118164],"type":"Point"}
}