{
  "type": "Feature",
  "properties": {
    "addr:full":"Eglantierln 203 Apeldoorn Gelderland 7329 AP",
    "addr:housenumber":"203",
    "addr:postcode":"7329 ap",
    "addr:street":"Gelderland",
    "iso:country":"NL",
    "sg:address":"Eglantierln 203",
    "sg:city":"Apeldoorn",
    "sg:orig_category":"Verenigingsgebouwen",
    "sg:phone":"+31 55 542 5951",
    "sg:postcode":"7329 AP",
    "sg:province":"Gelderland",
    "wof:name":"Jejocema, Sticht",
    "wof:placetype":"venue"
},
  "geometry": {"coordinates":[6.004568,52.19315],"type":"Point"}
}