{
  "type": "Feature",
  "properties": {
    "addr:full":"Iendrachtsngl 9 Opeinde Provincie Friesland 9218 PM",
    "addr:housenumber":"9",
    "addr:postcode":"9218 pm",
    "addr:street":"Iendrachtsngl;Provincie Friesland",
    "iso:country":"NL",
    "sg:address":"Iendrachtsngl 9",
    "sg:city":"Opeinde",
    "sg:orig_category":"Grasdrogerijen",
    "sg:phone":"+31 512 371 256",
    "sg:postcode":"9218 PM",
    "sg:province":"Provincie Friesland",
    "wof:name":"Groenvoer Opeinde Friesland Bv",
    "wof:placetype":"venue"
},
  "geometry": {"coordinates":[6.057847,53.136986],"type":"Point"}
}