{
  "type": "Feature",
  "properties": {
    "addr:full":"Koningsstr 19 Hilversum North Holland 1211 NJ",
    "addr:housenumber":"19",
    "addr:postcode":"1211 nj",
    "addr:street":"Koningsstr",
    "iso:country":"NL",
    "sg:address":"Koningsstr 19",
    "sg:city":"Hilversum",
    "sg:orig_category":"Wasmachines En Wasdrogers",
    "sg:phone":"+31 35 624 8457",
    "sg:postcode":"1211 NJ",
    "sg:province":"North Holland",
    "wof:name":"Miele Speciaalzaak",
    "wof:placetype":"venue"
},
  "geometry": {"coordinates":[5.1770219803,52.220413208],"type":"Point"}
}