{
  "type": "Feature",
  "properties": {
    "iso:country":"NL",
    "sg:address":"L Springerln 27",
    "sg:city":"Groningen",
    "sg:orig_category":"Vakorganisaties",
    "sg:phone":"+31 50 311 0222",
    "sg:postcode":"9727 KB",
    "sg:province":"Groningen",
    "wof:name":"Fnv Kiem",
    "wof:placetype":"venue"
},
  "geometry": {"coordinates":[6.555041,53.203285],"type":"Point"}
}