{
  "type": "Feature",
  "properties": {
    "addr:full":"Brusselstr 63 Breda Noord-Brabant 4826 NH",
    "addr:housenumber":"63",
    "addr:postcode":"4826 nh",
    "addr:street":"Brusselstr",
    "iso:country":"NL",
    "sg:address":"Brusselstr 63",
    "sg:city":"Breda",
    "sg:orig_category":"Verzekeringen - Verzekeringskantoren",
    "sg:phone":"+31 76 587 2748",
    "sg:postcode":"4826 NH",
    "sg:province":"Noord-Brabant",
    "wof:name":"Sluis, Van Der",
    "wof:placetype":"venue"
},
  "geometry": {"coordinates":[4.783719,51.608799],"type":"Point"}
}