{
  "type": "Feature",
  "properties": {
    "addr:full":"Zoggelsestraat 7 Heesch Noord-Brabant 5384 LL",
    "addr:housenumber":"7",
    "addr:postcode":"5384 ll",
    "addr:street":"Zoggelsestraat",
    "iso:country":"NL",
    "sg:address":"Zoggelsestraat 7",
    "sg:city":"Heesch",
    "sg:orig_category":"Metaalvrije Afvalrecycling",
    "sg:phone":"+31 412 455 228",
    "sg:postcode":"5384 LL",
    "sg:province":"Noord-Brabant",
    "wof:name":"Reisswolf Heesch Bv",
    "wof:placetype":"venue"
},
  "geometry": {"coordinates":[5.5156,51.727325],"type":"Point"}
}