{
  "type": "Feature",
  "properties": {
    "addr:full":"Loosduinsekade 179 'S Gravenhage Zuid-Holland 2571 BW",
    "addr:housenumber":"179 '",
    "addr:postcode":"2571 bw",
    "addr:street":"Loosduinsekade",
    "iso:country":"NL",
    "sg:address":"Loosduinsekade 179",
    "sg:city":"'S Gravenhage",
    "sg:orig_category":"Platenmaatschappijen",
    "sg:phone":"+31 70 345 5596",
    "sg:postcode":"2571 BW",
    "sg:province":"Zuid-Holland",
    "wof:name":"Hemon-Panfluitconservatorium",
    "wof:placetype":"venue"
},
  "geometry": {"coordinates":[4.286145,52.070934],"type":"Point"}
}