{
  "type": "Feature",
  "properties": {
    "addr:full":"Kerkstr 45 Berkel Enschot North Brabant 5056 AB",
    "addr:housenumber":"45",
    "addr:postcode":"5056 ab",
    "addr:street":"Kerkstr;Enschot",
    "iso:country":"NL",
    "sg:address":"Kerkstr 45",
    "sg:city":"Berkel Enschot",
    "sg:orig_category":"Autorijscholen",
    "sg:phone":"+31 13 533 3408",
    "sg:postcode":"5056 AB",
    "sg:province":"North Brabant",
    "wof:name":"Kleijngeld, Rijschool",
    "wof:placetype":"venue"
},
  "geometry": {"coordinates":[5.137825,51.575916],"type":"Point"}
}