{
  "type": "Feature",
  "properties": {
    "iso:country":"NL",
    "sg:address":"Willemskade 18",
    "sg:city":"Rotterdam",
    "sg:orig_category":"Ambassades And Consulaten",
    "sg:phone":"+31 10 411 1540",
    "sg:postcode":"3016 DL",
    "sg:province":"Zuid-Holland",
    "wof:name":"Consulaat Generaal Van Portugal",
    "wof:placetype":"venue"
},
  "geometry": {"coordinates":[4.481476,51.908768],"type":"Point"}
}