{
  "type": "Feature",
  "properties": {
    "addr:full":"Pr Hendrikstr 95 Breda Noord-Brabant 4835 PL",
    "addr:housenumber":"95",
    "addr:postcode":"4835 pl",
    "iso:country":"NL",
    "sg:address":"Pr Hendrikstr 95",
    "sg:city":"Breda",
    "sg:orig_category":"Schilders",
    "sg:phone":"+31 76 565 2718",
    "sg:postcode":"4835 PL",
    "sg:province":"Noord-Brabant",
    "sg:website":"http://www.petercolbethschilderwerken.nl",
    "wof:name":"Colbeth, Schilderwerken Peter",
    "wof:placetype":"venue"
},
  "geometry": {"coordinates":[4.788445,51.57238],"type":"Point"}
}