{
  "type": "Feature",
  "properties": {
    "addr:full":"M P Lindostr 4 Utrecht Utrecht 3532 XE",
    "addr:housenumber":"4",
    "addr:postcode":"3532 xe",
    "addr:street":"Lindostr",
    "iso:country":"NL",
    "sg:address":"M P Lindostr 4",
    "sg:city":"Utrecht",
    "sg:orig_category":"Kappers",
    "sg:phone":"+31 30 271 1918",
    "sg:postcode":"3532 XE",
    "sg:province":"Utrecht",
    "sg:website":"http://www.haarstylistencollege.nl",
    "wof:name":"Haarstylisten College",
    "wof:placetype":"venue"
},
  "geometry": {"coordinates":[5.1032190323,52.0941696167],"type":"Point"}
}