{
  "type": "Feature",
  "properties": {
    "addr:full":"Hoofdstr 17 Voorthuizen Gelderland 3781 AA",
    "addr:housenumber":"17",
    "addr:postcode":"3781 aa",
    "addr:street":"Hoofdstr;Gelderland",
    "iso:country":"NL",
    "sg:address":"Hoofdstr 17",
    "sg:city":"Voorthuizen",
    "sg:orig_category":"Grafmonumenten",
    "sg:phone":"+31 342 473 994",
    "sg:postcode":"3781 AA",
    "sg:province":"Gelderland",
    "wof:name":"Veluwehof Bv",
    "wof:placetype":"venue"
},
  "geometry": {"coordinates":[5.589758,52.181015],"type":"Point"}
}