{
  "type": "Feature",
  "properties": {
    "iso:country":"NL",
    "sg:address":"Industrieterrein 24",
    "sg:city":"Panningen",
    "sg:orig_category":"Airconditioning",
    "sg:phone":"+31 77 308 7200",
    "sg:postcode":"5981 NK",
    "sg:province":"Limburg",
    "wof:name":"Gti Koudetechniek Bv",
    "wof:placetype":"venue"
},
  "geometry": {"coordinates":[5.984843,51.335785],"type":"Point"}
}