{
  "type": "Feature",
  "properties": {
    "addr:full":"Nieuweweg 1 Tripscompagnie Groningen 9633 TD",
    "addr:housenumber":"1",
    "addr:postcode":"9633 td",
    "addr:street":"Nieuweweg",
    "iso:country":"NL",
    "sg:address":"Nieuweweg 1",
    "sg:city":"Tripscompagnie",
    "sg:orig_category":"Overheidsdiensten",
    "sg:phone":"+31 598 626 107",
    "sg:postcode":"9633 TD",
    "sg:province":"Groningen",
    "wof:name":"Nooitgedacht",
    "wof:placetype":"venue"
},
  "geometry": {"coordinates":[6.8245677948,53.1380348206],"type":"Point"}
}