{
  "type": "Feature",
  "properties": {
    "addr:full":"Ringwei 5 Drachten Friesland 9201 GT",
    "addr:housenumber":"5",
    "addr:postcode":"9201 gt",
    "addr:street":"Ringwei",
    "iso:country":"NL",
    "sg:address":"Ringwei 5",
    "sg:city":"Drachten",
    "sg:orig_category":"Wegenbouw",
    "sg:phone":"+31 512 540 866",
    "sg:postcode":"9201 GT",
    "sg:province":"Friesland",
    "wof:name":"Goa Noord",
    "wof:placetype":"venue"
},
  "geometry": {"coordinates":[6.0969910622,53.1187896729],"type":"Point"}
}