{
  "type": "Feature",
  "properties": {
    "iso:country":"NL",
    "sg:address":"Vyzelstr 24 Poli Enkhuizen",
    "sg:city":"Enkhuizen",
    "sg:orig_category":"Poliklinieken",
    "sg:phone":"+31 228 312 345",
    "sg:postcode":"1601 NK",
    "sg:province":"North Holland",
    "wof:name":"Polikliniek Enkhuizen",
    "wof:placetype":"venue"
},
  "geometry": {"coordinates":[5.2900848389,52.7036743164],"type":"Point"}
}