{
  "type": "Feature",
  "properties": {
    "iso:country":"NL",
    "sg:address":"Geldropseweg 126 C",
    "sg:city":"Eindhoven",
    "sg:orig_category":"Wasserettes And Stomerijen",
    "sg:phone":"+31 40 213 0411",
    "sg:postcode":"5611 SM",
    "sg:province":"North Brabant",
    "wof:name":"Palthe Stomerijen Bv",
    "wof:placetype":"venue"
},
  "geometry": {"coordinates":[5.4918789864,51.4323158264],"type":"Point"}
}