{
  "type": "Feature",
  "properties": {
    "addr:full":"Stadhouderskd 12 Amsterdam Noord-Holland 1054 ES",
    "addr:housenumber":"12",
    "addr:postcode":"1054 es",
    "addr:street":"Stadhouderskd",
    "iso:country":"NL",
    "sg:address":"Stadhouderskd 12",
    "sg:city":"Amsterdam",
    "sg:orig_category":"Kappers",
    "sg:phone":"+31 20 589 8869",
    "sg:postcode":"1054 ES",
    "sg:province":"Noord-Holland",
    "wof:name":"Hair By Trudy",
    "wof:placetype":"venue"
},
  "geometry": {"coordinates":[4.8685698509,52.3614082336],"type":"Point"}
}