{
  "type": "Feature",
  "properties": {
    "addr:full":"De Ruijterstraat 4 Lisse North Holland 2161 TB",
    "addr:housenumber":"4",
    "addr:postcode":"2161 tb",
    "addr:street":"De Ruijterstraat",
    "iso:country":"NL",
    "sg:address":"De Ruijterstraat 4",
    "sg:city":"Lisse",
    "sg:classifiers":[
        {
            "category":"Fast Food",
            "type":"Food & Drink"
        }
    ],
    "sg:phone":"+31 252 412 735",
    "sg:postcode":"2161 TB",
    "sg:province":"North Holland",
    "sg:tags":[
        "afhaal",
        "restaurant"
    ],
    "wof:name":"King Lao",
    "wof:placetype":"venue"
},
  "geometry": {"coordinates":[4.564844,52.259617],"type":"Point"}
}