{
  "type": "Feature",
  "properties": {
    "addr:full":"Amatist 45 Heerhugowaard Noord-Holland 1703 AR",
    "addr:housenumber":"45",
    "addr:postcode":"1703",
    "addr:street":"Amatist",
    "iso:country":"NL",
    "sg:address":"Amatist 45",
    "sg:city":"Heerhugowaard",
    "sg:orig_category":"Autorijscholen",
    "sg:phone":"+31 72 571 6108",
    "sg:postcode":"1703 AR",
    "sg:province":"Noord-Holland",
    "wof:name":"Brummel, H",
    "wof:placetype":"venue"
},
  "geometry": {"coordinates":[4.819535,52.65802],"type":"Point"}
}