{
  "type": "Feature",
  "properties": {
    "iso:country":"NL",
    "sg:address":"T Ei 1",
    "sg:city":"Lochem",
    "sg:orig_category":"Architecten En Architectenbureaus",
    "sg:phone":"+31 573 222 180",
    "sg:postcode":"7241 AK",
    "sg:province":"Gelderland",
    "wof:name":"Maas Bv",
    "wof:placetype":"venue"
},
  "geometry": {"coordinates":[6.416901,52.161076],"type":"Point"}
}