{
  "type": "Feature",
  "properties": {
    "addr:full":"Diependaalsedk 76 Maarssen Utrecht 3601 GM",
    "addr:housenumber":"76",
    "addr:postcode":"3601 gm",
    "addr:street":"Diependaalsedk",
    "iso:country":"NL",
    "sg:address":"Diependaalsedk 76",
    "sg:city":"Maarssen",
    "sg:orig_category":"Adviesbureaus Bedrijfsorganisatie",
    "sg:phone":"+31 346 575 353",
    "sg:postcode":"3601 GM",
    "sg:province":"Utrecht",
    "sg:website":"http://www.natural.nl",
    "wof:name":"Natural Management Bv",
    "wof:placetype":"venue"
},
  "geometry": {"coordinates":[5.036601,52.14785],"type":"Point"}
}