{
  "type": "Feature",
  "properties": {
    "addr:full":"Van Lumeystraat 51 'S Gravenhage Zuid-Holland 2581 XB",
    "addr:housenumber":"51",
    "addr:postcode":"2581 xb",
    "addr:street":"Van Lumeystraat;' S",
    "iso:country":"NL",
    "sg:address":"Van Lumeystraat 51",
    "sg:city":"'S Gravenhage",
    "sg:orig_category":"Juridische Dienstverlening",
    "sg:phone":"+31 70 355 1682",
    "sg:postcode":"2581 XB",
    "sg:province":"Zuid-Holland",
    "wof:name":"Stordiau Adv",
    "wof:placetype":"venue"
},
  "geometry": {"coordinates":[4.270879,52.089436],"type":"Point"}
}