{
  "type": "Feature",
  "properties": {
    "addr:full":"Van Breestraat 67 Amsterdam Noord-Holland 1071 ZG",
    "addr:housenumber":"67",
    "addr:postcode":"1071 zg",
    "addr:street":"Van Breestraat",
    "iso:country":"NL",
    "sg:address":"Van Breestraat 67",
    "sg:city":"Amsterdam",
    "sg:orig_category":"Artsen And Specialisten",
    "sg:phone":"+31 20 673 4820",
    "sg:postcode":"1071 ZG",
    "sg:province":"Noord-Holland",
    "wof:name":"Instituut Voor Psychotherapie",
    "wof:placetype":"venue"
},
  "geometry": {"coordinates":[4.875424,52.356449],"type":"Point"}
}