{
  "type": "Feature",
  "properties": {
    "iso:country":"NL",
    "sg:address":"Den Texstraat 29",
    "sg:city":"Amsterdam",
    "sg:orig_category":"Werving And Selectie Van Vast Personeel",
    "sg:phone":"+31 20 622 7387",
    "sg:postcode":"1017 XX",
    "sg:province":"Noord-Holland",
    "wof:name":"B & F Loopbaanadviesbureau",
    "wof:placetype":"venue"
},
  "geometry": {"coordinates":[4.8946270943,52.358997345],"type":"Point"}
}