{
  "type": "Feature",
  "properties": {
    "addr:full":"Zandstraat 59 Veenendaal Utrecht 3901 CK",
    "addr:housenumber":"59",
    "addr:postcode":"3901 ck",
    "addr:street":"Zandstraat",
    "iso:country":"NL",
    "sg:address":"Zandstraat 59",
    "sg:city":"Veenendaal",
    "sg:orig_category":"Paramedische Behandelingen",
    "sg:phone":"+31 318 544 100",
    "sg:postcode":"3901 CK",
    "sg:province":"Utrecht",
    "wof:name":"Cmd Zuid Oost Utrecht",
    "wof:placetype":"venue"
},
  "geometry": {"coordinates":[5.553418,52.029068],"type":"Point"}
}