{
  "type": "Feature",
  "properties": {
    "addr:full":"Hoorn 99 Alphen Aan Den Ryn Zuid-Holland 2404 HH",
    "addr:housenumber":"99",
    "addr:postcode":"2404 hh",
    "addr:street":"Hoorn;Aan Den Ryn",
    "iso:country":"NL",
    "sg:address":"Hoorn 99",
    "sg:city":"Alphen Aan Den Ryn",
    "sg:orig_category":"Onroerende Goederen",
    "sg:phone":"+31 172 417 036",
    "sg:postcode":"2404 HH",
    "sg:province":"Zuid-Holland",
    "wof:name":"Hoorn 99 Bv",
    "wof:placetype":"venue"
},
  "geometry": {"coordinates":[4.633767,52.138828],"type":"Point"}
}