{
  "type": "Feature",
  "properties": {
    "iso:country":"NL",
    "sg:address":"Karstr 10",
    "sg:city":"Bemmel",
    "sg:orig_category":"Woningbouw- Verenigingen En -Stichtingen",
    "sg:phone":"+31 900 4444555",
    "sg:postcode":"6681 LA",
    "sg:province":"Gelderland",
    "sg:website":"http://www.LingewaardWonen.nl",
    "wof:name":"Lingewaard",
    "wof:placetype":"venue"
},
  "geometry": {"coordinates":[5.9055452347,51.8963928223],"type":"Point"}
}