{
  "type": "Feature",
  "properties": {
    "iso:country":"NL",
    "sg:address":"Nr 2",
    "sg:city":"Huins",
    "sg:orig_category":"Fotojournalisten Freelance",
    "sg:phone":"+31 517 341 400",
    "sg:postcode":"8832 KB",
    "sg:province":"Friesland",
    "wof:name":"Spectrum, Fotografie",
    "wof:placetype":"venue"
},
  "geometry": {"coordinates":[5.666855,53.159821],"type":"Point"}
}