{
  "type": "Feature",
  "properties": {
    "addr:full":"Leeghwaterstr 6 Arnhem Gelderland 6827 AP",
    "addr:housenumber":"6",
    "addr:postcode":"6827 ap",
    "addr:street":"Leeghwaterstr",
    "iso:country":"NL",
    "sg:address":"Leeghwaterstr 6",
    "sg:city":"Arnhem",
    "sg:orig_category":"Oud Metaal",
    "sg:phone":"+31 26 361 5534",
    "sg:postcode":"6827 AP",
    "sg:province":"Gelderland",
    "wof:name":"Houtum Bv, Van",
    "wof:placetype":"venue"
},
  "geometry": {"coordinates":[5.9236121178,51.973690033],"type":"Point"}
}