{
  "type": "Feature",
  "properties": {
    "addr:full":"Hazenakkerweg 12 Kessel Lb Limburg 5995 RM",
    "addr:housenumber":"12",
    "addr:postcode":"lb;5995 rm",
    "addr:street":"Hazenakkerweg",
    "iso:country":"NL",
    "sg:address":"Hazenakkerweg 12",
    "sg:city":"Kessel Lb",
    "sg:orig_category":"Verhuur Diversen",
    "sg:phone":"+31 77 462 1713",
    "sg:postcode":"5995 RM",
    "sg:province":"Limburg",
    "wof:name":"Sturme - Smedts",
    "wof:placetype":"venue"
},
  "geometry": {"coordinates":[6.04692,51.301208],"type":"Point"}
}