{
  "type": "Feature",
  "properties": {
    "addr:full":"Willemstr 47 Roosendaal North Brabant 4701 HB",
    "addr:housenumber":"47",
    "addr:postcode":"4701 hb",
    "addr:street":"Willemstr",
    "iso:country":"NL",
    "sg:address":"Willemstr 47",
    "sg:city":"Roosendaal",
    "sg:orig_category":"Kappers",
    "sg:phone":"+31 6 18701752",
    "sg:postcode":"4701 HB",
    "sg:province":"North Brabant",
    "wof:name":"Renate'S Knip Express",
    "wof:placetype":"venue"
},
  "geometry": {"coordinates":[4.465573,51.534225],"type":"Point"}
}