{
  "type": "Feature",
  "properties": {
    "addr:full":"Pasteurstr 36 A Leiden Zuid-Holland 2316 BW",
    "addr:housenumber":"36 a",
    "addr:postcode":"2316 bw",
    "addr:street":"Pasteurstr",
    "iso:country":"NL",
    "sg:address":"Pasteurstr 36 A",
    "sg:city":"Leiden",
    "sg:orig_category":"Administratie- En Boekhoudkantoren",
    "sg:phone":"+31 71 523 6074",
    "sg:postcode":"2316 BW",
    "sg:province":"Zuid-Holland",
    "wof:name":"Karin Scheele",
    "wof:placetype":"venue"
},
  "geometry": {"coordinates":[4.491494,52.166336],"type":"Point"}
}