{
  "type": "Feature",
  "properties": {
    "addr:full":"Nieuwendk 213 Amsterdam Noord-Holland 1012 MH",
    "addr:housenumber":"213",
    "addr:postcode":"1012 mh",
    "iso:country":"NL",
    "sg:address":"Nieuwendk 213",
    "sg:city":"Amsterdam",
    "sg:orig_category":"Schoenen",
    "sg:phone":"+31 20 624 8114",
    "sg:postcode":"1012 MH",
    "sg:province":"Noord-Holland",
    "wof:name":"Haren Bv, Van",
    "wof:placetype":"venue"
},
  "geometry": {"coordinates":[4.893546,52.374294],"type":"Point"}
}