{
  "type": "Feature",
  "properties": {
    "addr:full":"Nieuwstraat 23 Woerden Utrecht 3441 EA",
    "addr:housenumber":"23",
    "addr:postcode":"3441 ea",
    "addr:street":"Nieuwstraat",
    "iso:country":"NL",
    "sg:address":"Nieuwstraat 23",
    "sg:city":"Woerden",
    "sg:orig_category":"Kappers",
    "sg:phone":"+31 348 424 631",
    "sg:postcode":"3441 EA",
    "sg:province":"Utrecht",
    "wof:name":"Action Haarmode",
    "wof:placetype":"venue"
},
  "geometry": {"coordinates":[4.8366317749,52.1139984131],"type":"Point"}
}