{
  "type": "Feature",
  "properties": {
    "addr:full":"Snekertrekwg 25 Leeuwarden Friesland 8912 AA",
    "addr:housenumber":"25",
    "addr:postcode":"8912 aa",
    "addr:street":"Snekertrekwg",
    "iso:country":"NL",
    "sg:address":"Snekertrekwg 25",
    "sg:city":"Leeuwarden",
    "sg:orig_category":"Woninginrichting",
    "sg:phone":"+31 58 212 1800",
    "sg:postcode":"8912 AA",
    "sg:province":"Friesland",
    "wof:name":"Kwantum",
    "wof:placetype":"venue"
},
  "geometry": {"coordinates":[5.7851829529,53.1969070435],"type":"Point"}
}