{
  "type": "Feature",
  "properties": {
    "iso:country":"NL",
    "sg:address":"Bakkersbergwg 7",
    "sg:city":"Roosendaal",
    "sg:orig_category":"Kinderopvang",
    "sg:phone":"+31 165 569 111",
    "sg:postcode":"4706 PD",
    "sg:province":"Noord-Brabant",
    "wof:name":"Stegel, Mkd De",
    "wof:placetype":"venue"
},
  "geometry": {"coordinates":[4.50491,51.540882],"type":"Point"}
}