{
  "type": "Feature",
  "properties": {
    "addr:full":"Bookholtln 21 Losser NL.08 7581 BB",
    "addr:housenumber":"21;nl.08",
    "addr:postcode":"7581 bb",
    "addr:street":"Bookholtln",
    "iso:country":"NL",
    "sg:address":"Bookholtln 21",
    "sg:city":"Losser",
    "sg:orig_category":"Verenigingsgebouwen",
    "sg:phone":"+31 53 538 1044",
    "sg:postcode":"7581 BB",
    "sg:province":"NL.08",
    "wof:name":"Tukkershoes, 'T",
    "wof:placetype":"venue"
},
  "geometry": {"coordinates":[7.005806,52.261173],"type":"Point"}
}