{
  "type": "Feature",
  "properties": {
    "addr:full":"Den Akker 2 Voorthuizen Gelderland 3781 MC",
    "addr:housenumber":"2;3781",
    "addr:street":"Den Akker;Gelderland;Mc",
    "iso:country":"NL",
    "sg:address":"Den Akker 2",
    "sg:city":"Voorthuizen",
    "sg:orig_category":"Antiquiteiten - Restauratie",
    "sg:phone":"+31 342 471 273",
    "sg:postcode":"3781 MC",
    "sg:province":"Gelderland",
    "wof:name":"Koenders, M C J",
    "wof:placetype":"venue"
},
  "geometry": {"coordinates":[5.56251,52.175228],"type":"Point"}
}