{
  "type": "Feature",
  "properties": {
    "iso:country":"NL",
    "sg:address":"Kerkstr 22",
    "sg:city":"Ysselstein Ut",
    "sg:orig_category":"Fietsen En Bromfietsen",
    "sg:phone":"+31 30 688 1296",
    "sg:postcode":"3401 CN",
    "sg:province":"Utrecht",
    "sg:website":"http://www.roodenburgbiketotaal.nl",
    "wof:name":"Roodenburg Bike Totaal",
    "wof:placetype":"venue"
},
  "geometry": {"coordinates":[5.045391,52.019997],"type":"Point"}
}