{
  "type": "Feature",
  "properties": {
    "iso:country":"NL",
    "sg:address":"Stuijvenburchstraat 7",
    "sg:city":"Eerbeek",
    "sg:orig_category":"Goederenvervoer Over De Weg",
    "sg:phone":"+31 313 652 635",
    "sg:postcode":"6961 DP",
    "sg:province":"Gelderland",
    "wof:name":"Van Driel Transport",
    "wof:placetype":"venue"
},
  "geometry": {"coordinates":[6.070016,52.104],"type":"Point"}
}