{
  "type": "Feature",
  "properties": {
    "addr:full":"Stuijvenburchstraat 7 Eerbeek Gelderland 6961 DP",
    "addr:housenumber":"7",
    "addr:postcode":"6961 dp",
    "addr:street":"Stuijvenburchstraat;Gelderland",
    "iso:country":"NL",
    "sg:address":"Stuijvenburchstraat 7",
    "sg:city":"Eerbeek",
    "sg:orig_category":"Goederenvervoer Over De Weg",
    "sg:phone":"+31 313 652 635",
    "sg:postcode":"6961 DP",
    "sg:province":"Gelderland",
    "wof:name":"Van Driel Transport",
    "wof:placetype":"venue"
},
  "geometry": {"coordinates":[6.070016,52.104],"type":"Point"}
}