{
  "type": "Feature",
  "properties": {
    "addr:full":"F V Eedenhove 19 Nieuwegein Utrecht 3438 PV",
    "addr:housenumber":"19",
    "addr:postcode":"3438 pv",
    "addr:street":"Eedenhove",
    "iso:country":"NL",
    "sg:address":"F V Eedenhove 19",
    "sg:city":"Nieuwegein",
    "sg:orig_category":"Autopoetsbedrijven",
    "sg:phone":"+31 6 29535257",
    "sg:postcode":"3438 PV",
    "sg:province":"Utrecht",
    "wof:name":"New Car Cleaning",
    "wof:placetype":"venue"
},
  "geometry": {"coordinates":[5.082197,52.027325],"type":"Point"}
}