{
  "type": "Feature",
  "properties": {
    "addr:full":"Sonsbeeksingel 101 Arnhem Gelderland 6822 BJ",
    "addr:housenumber":"101",
    "addr:postcode":"6822 bj",
    "addr:street":"Sonsbeeksingel",
    "iso:country":"NL",
    "sg:address":"Sonsbeeksingel 101",
    "sg:city":"Arnhem",
    "sg:classifiers":[
        {
            "category":"Bars & Pubs",
            "type":"Food & Drink"
        }
    ],
    "sg:phone":"+31 26 443 5934",
    "sg:postcode":"6822 BJ",
    "sg:province":"Gelderland",
    "wof:name":"Thc",
    "wof:placetype":"venue"
},
  "geometry": {"coordinates":[5.914623,51.986088],"type":"Point"}
}