{
  "type": "Feature",
  "properties": {
    "addr:full":"Fortstr 4 Woudrichem Noord-Brabant 4285 XZ",
    "addr:housenumber":"4",
    "addr:postcode":"4285 xz",
    "addr:street":"Fortstr",
    "iso:country":"NL",
    "sg:address":"Fortstr 4",
    "sg:city":"Woudrichem",
    "sg:orig_category":"Adviesbureaus Beveiliging",
    "sg:phone":"+31 183 303 828",
    "sg:postcode":"4285 XZ",
    "sg:province":"Noord-Brabant",
    "wof:name":"Pid",
    "wof:placetype":"venue"
},
  "geometry": {"coordinates":[4.993137,51.814522],"type":"Point"}
}