{
  "type": "Feature",
  "properties": {
    "addr:full":"Wisselwg 1 Almere NL. 1314 CA",
    "addr:housenumber":"1",
    "addr:postcode":"1314 ca",
    "addr:street":"Wisselwg;Nl.",
    "iso:country":"NL",
    "sg:address":"Wisselwg 1",
    "sg:city":"Almere",
    "sg:orig_category":"Luchtfotografie",
    "sg:phone":"+31 36 530 8000",
    "sg:postcode":"1314 CA",
    "sg:province":"NL.",
    "wof:name":"Oranjewoud Bv",
    "wof:placetype":"venue"
},
  "geometry": {"coordinates":[5.214169,52.375107],"type":"Point"}
}