{
  "type": "Feature",
  "properties": {
    "addr:full":"De Meent 2 Hilversum Noord-Holland 1218 CB",
    "addr:housenumber":"2",
    "addr:postcode":"1218 cb",
    "addr:street":"De Meent",
    "iso:country":"NL",
    "sg:address":"De Meent 2",
    "sg:city":"Hilversum",
    "sg:classifiers":[
        {
            "category":"Education",
            "subcategory":"Preschool",
            "type":"Public Place"
        }
    ],
    "sg:phone":"+31 35 691 2446",
    "sg:postcode":"1218 CB",
    "sg:province":"Noord-Holland",
    "sg:tags":[
        "kleuteronderwijs",
        "basis-"
    ],
    "wof:name":"Daltonschool De Meent",
    "wof:placetype":"venue"
},
  "geometry": {"coordinates":[5.13748,52.27047],"type":"Point"}
}