{
  "type": "Feature",
  "properties": {
    "addr:full":"Tynaarlosestr 21 Vries Drenthe 9481 AA",
    "addr:housenumber":"21",
    "addr:postcode":"9481 aa",
    "addr:street":"Tynaarlosestr",
    "iso:country":"NL",
    "sg:address":"Tynaarlosestr 21",
    "sg:city":"Vries",
    "sg:orig_category":"Houtindustrie",
    "sg:phone":"+31 592 542 371",
    "sg:postcode":"9481 AA",
    "sg:province":"Drenthe",
    "wof:name":"Piet Van Der Vinne",
    "wof:placetype":"venue"
},
  "geometry": {"coordinates":[-85.944946,42.811916],"type":"Point"}
}