{
  "type": "Feature",
  "properties": {
    "addr:full":"Suderskarren 10 Drachten Provincie Friesland 9203 TG",
    "addr:housenumber":"10;9203",
    "addr:postcode":"tg",
    "addr:street":"Suderskarren;Provincie Friesland",
    "iso:country":"NL",
    "sg:address":"Suderskarren 10",
    "sg:city":"Drachten",
    "sg:orig_category":"Projectontwikkeling",
    "sg:phone":"+31 512 520 635",
    "sg:postcode":"9203 TG",
    "sg:province":"Provincie Friesland",
    "wof:name":"Keuning Bv",
    "wof:placetype":"venue"
},
  "geometry": {"coordinates":[6.092126,53.078182],"type":"Point"}
}