{
  "type": "Feature",
  "properties": {
    "iso:country":"NL",
    "sg:address":"Dykstr 10",
    "sg:city":"Sprang Capelle",
    "sg:orig_category":"Plafonds",
    "sg:phone":"+31 416 276 100",
    "sg:postcode":"5161 BV",
    "sg:province":"North Brabant",
    "wof:name":"Jansen Afbouw",
    "wof:placetype":"venue"
},
  "geometry": {"coordinates":[5.02336,51.670841],"type":"Point"}
}