{
  "type": "Feature",
  "properties": {
    "addr:full":"K Zylstr 1 Haarlem Noord-Holland 2011 TN",
    "addr:housenumber":"1",
    "addr:postcode":"2011",
    "addr:street":"Zylstr",
    "iso:country":"NL",
    "sg:address":"K Zylstr 1",
    "sg:city":"Haarlem",
    "sg:orig_category":"Verhuizingen",
    "sg:phone":"+31 23 534 1387",
    "sg:postcode":"2011 TN",
    "sg:province":"Noord-Holland",
    "wof:name":"Wit, Aad De",
    "wof:placetype":"venue"
},
  "geometry": {"coordinates":[4.642253,52.380562],"type":"Point"}
}