{
  "type": "Feature",
  "properties": {
    "addr:full":"Rykswg 57-B Nuland Noord-Brabant 5391 LJ",
    "addr:housenumber":"57-b",
    "addr:postcode":"5391 lj",
    "addr:street":"Rykswg",
    "iso:country":"NL",
    "sg:address":"Rykswg 57-B",
    "sg:city":"Nuland",
    "sg:orig_category":"Kantoor- En Bedrijfsmeubelen",
    "sg:phone":"+31 73 522 1266",
    "sg:postcode":"5391 LJ",
    "sg:province":"Noord-Brabant",
    "sg:website":"http://www.kantoormeubelen.com",
    "wof:name":"Ton Wooning",
    "wof:placetype":"venue"
},
  "geometry": {"coordinates":[5.4469809532,51.7227210999],"type":"Point"}
}