{
  "type": "Feature",
  "properties": {
    "iso:country":"NL",
    "sg:address":"Adelaertstraat 1",
    "sg:city":"Eindhoven",
    "sg:orig_category":"Kappers",
    "sg:phone":"+31 40 241 6626",
    "sg:postcode":"5625 HC",
    "sg:province":"North Brabant",
    "wof:name":"Kapsalon Mia",
    "wof:placetype":"venue"
},
  "geometry": {"coordinates":[5.4688138962,51.4744758606],"type":"Point"}
}