{
  "type": "Feature",
  "properties": {
    "addr:full":"Adelaertstraat 1 Eindhoven North Brabant 5625 HC",
    "addr:housenumber":"1",
    "addr:postcode":"5625 hc",
    "addr:street":"Adelaertstraat",
    "iso:country":"NL",
    "sg:address":"Adelaertstraat 1",
    "sg:city":"Eindhoven",
    "sg:orig_category":"Kappers",
    "sg:phone":"+31 40 241 6626",
    "sg:postcode":"5625 HC",
    "sg:province":"North Brabant",
    "wof:name":"Kapsalon Mia",
    "wof:placetype":"venue"
},
  "geometry": {"coordinates":[5.4688138962,51.4744758606],"type":"Point"}
}