{
  "type": "Feature",
  "properties": {
    "addr:full":"Vlasstr 11 Someren Noord-Brabant 5712 RP",
    "addr:housenumber":"11",
    "addr:postcode":"5712 rp",
    "addr:street":"Vlasstr",
    "iso:country":"NL",
    "sg:address":"Vlasstr 11",
    "sg:city":"Someren",
    "sg:orig_category":"Administratie- En Boekhoudkantoren",
    "sg:phone":"+31 493 491 699",
    "sg:postcode":"5712 RP",
    "sg:province":"Noord-Brabant",
    "wof:name":"Eijk Bv, Van",
    "wof:placetype":"venue"
},
  "geometry": {"coordinates":[5.718696,51.364273],"type":"Point"}
}