{
  "type": "Feature",
  "properties": {
    "iso:country":"NL",
    "sg:address":"Werfpad 2",
    "sg:city":"'S Hertogenbosch",
    "sg:orig_category":"Meubelzaken, Woning- And Keukeninrichting",
    "sg:phone":"+31 73 691 0211",
    "sg:postcode":"5212 VJ",
    "sg:province":"Noord-Brabant",
    "wof:name":"Beter Bed",
    "wof:placetype":"venue"
},
  "geometry": {"coordinates":[5.302475,51.697289],"type":"Point"}
}