{
  "type": "Feature",
  "properties": {
    "addr:full":"Loevenhoutsedijk 54 Utrecht Utrecht 3552 XE",
    "addr:housenumber":"54",
    "addr:postcode":"3552 xe",
    "addr:street":"Loevenhoutsedijk",
    "iso:country":"NL",
    "sg:address":"Loevenhoutsedijk 54",
    "sg:city":"Utrecht",
    "sg:orig_category":"Juridische Dienstverlening",
    "sg:phone":"+31 30 294 8662",
    "sg:postcode":"3552 XE",
    "sg:province":"Utrecht",
    "wof:name":"Adviesbureau Sab",
    "wof:placetype":"venue"
},
  "geometry": {"coordinates":[5.109326,52.107243],"type":"Point"}
}