{
  "type": "Feature",
  "properties": {
    "addr:full":"Aalsvoort 60 Lochem Gelderland 7241 MA",
    "addr:housenumber":"60",
    "addr:postcode":"7241 ma",
    "addr:street":"Aalsvoort;Gelderland",
    "iso:country":"NL",
    "sg:address":"Aalsvoort 60",
    "sg:city":"Lochem",
    "sg:orig_category":"Metaalbekleding And -Behandeling",
    "sg:phone":"+31 573 251 258",
    "sg:postcode":"7241 MA",
    "sg:province":"Gelderland",
    "wof:name":"Metaaldraaierij Eggink",
    "wof:placetype":"venue"
},
  "geometry": {"coordinates":[6.385481,52.169014],"type":"Point"}
}