{
  "type": "Feature",
  "properties": {
    "addr:full":"S Hartstr 1 Zaandam Noord-Holland 1507 WX",
    "addr:housenumber":"1",
    "addr:postcode":"1507 wx",
    "iso:country":"NL",
    "sg:address":"S Hartstr 1",
    "sg:city":"Zaandam",
    "sg:orig_category":"Voetbalverenigingen",
    "sg:phone":"+31 20 569 2271",
    "sg:postcode":"1507 WX",
    "sg:province":"Noord-Holland",
    "wof:name":"Kondo Budjang",
    "wof:placetype":"venue"
},
  "geometry": {"coordinates":[4.798445,52.448307],"type":"Point"}
}