{
  "type": "Feature",
  "properties": {
    "addr:full":"Theems 31 S Gravenhage 2491 BR",
    "addr:housenumber":"31",
    "addr:postcode":"2491 br",
    "addr:street":"Theems;S Gravenhage",
    "iso:country":"NL",
    "sg:address":"Theems 31",
    "sg:city":"S Gravenhage",
    "sg:orig_category":"Liften - Onderhoud En Reparatie",
    "sg:phone":"+31 70 320 1477",
    "sg:postcode":"2491 BR",
    "sg:website":"http://www.vandeelenliften.nl",
    "wof:name":"Deelen Bv, Van",
    "wof:placetype":"venue"
},
  "geometry": {"coordinates":[4.38382,52.065289],"type":"Point"}
}