{
  "type": "Feature",
  "properties": {
    "iso:country":"NL",
    "sg:address":"Senecaln 10",
    "sg:city":"Venlo",
    "sg:orig_category":"Schoonheidsinstituten",
    "sg:phone":"+31 77 387 2517",
    "sg:postcode":"5926 SL",
    "sg:province":"Limburg",
    "wof:name":"Jacobs, Nicole",
    "wof:placetype":"venue"
},
  "geometry": {"coordinates":[6.128113,51.357544],"type":"Point"}
}