{
  "type": "Feature",
  "properties": {
    "addr:full":"Ringwg Randenb 110 Loc St Elisabeth Amersfoort Utrecht 3816 CP",
    "addr:housenumber":"110",
    "addr:postcode":"3816 cp",
    "addr:street":"Loc St",
    "iso:country":"NL",
    "sg:address":"Ringwg Randenb 110 Loc St Elisabeth",
    "sg:city":"Amersfoort",
    "sg:orig_category":"Ziekenhuizen, Sanatoria, Verpleeghuizen",
    "sg:phone":"+31 33 422 2345",
    "sg:postcode":"3816 CP",
    "sg:province":"Utrecht",
    "wof:name":"Eemland Zks",
    "wof:placetype":"venue"
},
  "geometry": {"coordinates":[5.386085,52.152325],"type":"Point"}
}