{
  "type": "Feature",
  "properties": {
    "addr:full":"Minkmaatstr 44 Enschede NL.08 7514 EC",
    "addr:housenumber":"44",
    "addr:postcode":"7514 ec",
    "addr:street":"Minkmaatstr",
    "iso:country":"NL",
    "sg:address":"Minkmaatstr 44",
    "sg:city":"Enschede",
    "sg:orig_category":"Homeopathie",
    "sg:phone":"+31 53 433 7533",
    "sg:postcode":"7514 EC",
    "sg:province":"NL.08",
    "wof:name":"Heuvelink, W T M",
    "wof:placetype":"venue"
},
  "geometry": {"coordinates":[6.901873,52.226215],"type":"Point"}
}