{
  "type": "Feature",
  "properties": {
    "addr:full":"Julianaplein 122 Den Helder Noord-Holland 1781 HE",
    "addr:housenumber":"122",
    "addr:postcode":"1781 he",
    "addr:street":"Julianaplein",
    "iso:country":"NL",
    "sg:address":"Julianaplein 122",
    "sg:city":"Den Helder",
    "sg:orig_category":"Banken And Kredietinstellingen",
    "sg:phone":"+31 223 673 100",
    "sg:postcode":"1781 HE",
    "sg:province":"Noord-Holland",
    "wof:name":"Rabobank",
    "wof:placetype":"venue"
},
  "geometry": {"coordinates":[4.760525,52.958302],"type":"Point"}
}