{
  "type": "Feature",
  "properties": {
    "addr:full":"Zonneln 13 Hilversum Noord-Holland 1217 ND",
    "addr:housenumber":"13",
    "addr:postcode":"1217 nd",
    "addr:street":"Zonneln",
    "iso:country":"NL",
    "sg:address":"Zonneln 13",
    "sg:city":"Hilversum",
    "sg:orig_category":"Adviesbureaus Bedrijfsorganisatie",
    "sg:phone":"+31 35 622 0402",
    "sg:postcode":"1217 ND",
    "sg:province":"Noord-Holland",
    "wof:name":"Kayuga Bv",
    "wof:placetype":"venue"
},
  "geometry": {"coordinates":[5.1695,52.228565],"type":"Point"}
}