{
  "type": "Feature",
  "properties": {
    "addr:full":"Heuvelwg 3 Zoetermeer South Holland 2716 DZ",
    "addr:housenumber":"3",
    "addr:postcode":"2716 dz",
    "addr:street":"Heuvelwg",
    "iso:country":"NL",
    "sg:address":"Heuvelwg 3",
    "sg:city":"Zoetermeer",
    "sg:orig_category":"Golfbanen",
    "sg:phone":"+31 79 320 3130",
    "sg:postcode":"2716 DZ",
    "sg:province":"South Holland",
    "wof:name":"Burggolf Zoetermeer Bv",
    "wof:placetype":"venue"
},
  "geometry": {"coordinates":[4.440111,52.05426],"type":"Point"}
}