{
  "type": "Feature",
  "properties": {
    "addr:full":"Postbus 189 Diemen North Holland 1110 AD",
    "addr:housenumber":"189",
    "addr:postcode":"1110 ad",
    "addr:street":"Postbus",
    "iso:country":"NL",
    "sg:address":"Postbus 189",
    "sg:city":"Diemen",
    "sg:orig_category":"Voetbalverenigingen",
    "sg:phone":"+31 20 600 0882",
    "sg:postcode":"1110 AD",
    "sg:province":"North Holland",
    "wof:name":"Diemen Sv",
    "wof:placetype":"venue"
},
  "geometry": {"coordinates":[4.964805,52.34132],"type":"Point"}
}