{
  "type": "Feature",
  "properties": {
    "addr:full":"Van De Spiegelstraat 13 'S Gravenhage Zuid-Holland 2518 ES",
    "addr:housenumber":"13",
    "addr:postcode":"2518 es",
    "addr:street":"Van De Spiegelstraat;' S",
    "iso:country":"NL",
    "sg:address":"Van De Spiegelstraat 13",
    "sg:city":"'S Gravenhage",
    "sg:orig_category":"Artsen And Specialisten",
    "sg:phone":"+31 70 364 2211",
    "sg:postcode":"2518 ES",
    "sg:province":"Zuid-Holland",
    "wof:name":"J.J.B.M. Nouwens",
    "wof:placetype":"venue"
},
  "geometry": {"coordinates":[4.296673,52.084602],"type":"Point"}
}