{
  "type": "Feature",
  "properties": {
    "iso:country":"NL",
    "sg:address":"De Oude Veiling 86",
    "sg:city":"Zwaag",
    "sg:orig_category":"Boekhandels",
    "sg:phone":"+31 229 245 450",
    "sg:postcode":"1689 AD",
    "sg:province":"Noord-Holland",
    "wof:name":"Media Expresse",
    "wof:placetype":"venue"
},
  "geometry": {"coordinates":[5.065083,52.660583],"type":"Point"}
}