{
  "type": "Feature",
  "properties": {
    "addr:full":"Pilotenstraat 36 Den Dungen North Brabant 5275 BC",
    "addr:housenumber":"36",
    "addr:postcode":"5275 bc",
    "addr:street":"Pilotenstraat",
    "iso:country":"NL",
    "sg:address":"Pilotenstraat 36",
    "sg:city":"Den Dungen",
    "sg:orig_category":"Kappers",
    "sg:phone":"+31 73 594 3086",
    "sg:postcode":"5275 BC",
    "sg:province":"North Brabant",
    "wof:name":"Kapsalon Leonardo",
    "wof:placetype":"venue"
},
  "geometry": {"coordinates":[5.3745560646,51.6678657532],"type":"Point"}
}