{
  "type": "Feature",
  "properties": {
    "addr:full":"Fernhoutstraat 9 Ede Gld Gelderland 6717 MD",
    "addr:housenumber":"9",
    "addr:postcode":"6717",
    "addr:street":"Fernhoutstraat;Gld Gelderland",
    "iso:country":"NL",
    "sg:address":"Fernhoutstraat 9",
    "sg:city":"Ede Gld",
    "sg:orig_category":"Paramedische Behandelingen",
    "sg:phone":"+31 318 621 538",
    "sg:postcode":"6717 MD",
    "sg:province":"Gelderland",
    "wof:name":"G.T. Mastwijk",
    "wof:placetype":"venue"
},
  "geometry": {"coordinates":[5.655701,52.021641],"type":"Point"}
}