{
  "type": "Feature",
  "properties": {
    "addr:full":"Nw Ebbingestr 27 Groningen Groningen 9712 ND",
    "addr:housenumber":"27",
    "addr:postcode":"9712 nd",
    "iso:country":"NL",
    "sg:address":"Nw Ebbingestr 27",
    "sg:city":"Groningen",
    "sg:orig_category":"Kappers",
    "sg:phone":"+31 50 318 7716",
    "sg:postcode":"9712 ND",
    "sg:province":"Groningen",
    "wof:name":"Maress, Hairstyling",
    "wof:placetype":"venue"
},
  "geometry": {"coordinates":[6.56421,53.223232],"type":"Point"}
}