{
  "type": "Feature",
  "properties": {
    "addr:full":"Infirmeriestr 6-8 Rotterdam South Holland 3063 EP",
    "addr:housenumber":"6-8",
    "addr:postcode":"3063 ep",
    "addr:street":"Infirmeriestr",
    "iso:country":"NL",
    "sg:address":"Infirmeriestr 6-8",
    "sg:city":"Rotterdam",
    "sg:orig_category":"Verenigingen En Stichtingen",
    "sg:phone":"+31 10 453 5777",
    "sg:postcode":"3063 EP",
    "sg:province":"South Holland",
    "wof:name":"Rsv Sanctus Laurentius",
    "wof:placetype":"venue"
},
  "geometry": {"coordinates":[4.502673,51.92197],"type":"Point"}
}