{
  "type": "Feature",
  "properties": {
    "addr:full":"Hengelolaan 191/D Den Haag Zuid-Holland 2545 JG",
    "addr:housenumber":"191 / d",
    "addr:postcode":"2545 jg",
    "addr:street":"Hengelolaan",
    "iso:country":"NL",
    "sg:address":"Hengelolaan 191/D",
    "sg:city":"Den Haag",
    "sg:orig_category":"Fysiotherapeuten",
    "sg:phone":"+31 70 367 9422",
    "sg:postcode":"2545 JG",
    "sg:province":"Zuid-Holland",
    "wof:name":"Samson Maatwerk Bv",
    "wof:placetype":"venue"
},
  "geometry": {"coordinates":[4.272632,52.050003],"type":"Point"}
}