{
  "type": "Feature",
  "properties": {
    "addr:full":"Burg Roelenwg 31 Zwolle NL.08 8031 ES",
    "addr:housenumber":"31",
    "addr:postcode":"8031 es",
    "addr:street":"Burg",
    "iso:country":"NL",
    "sg:address":"Burg Roelenwg 31",
    "sg:city":"Zwolle",
    "sg:orig_category":"Werving En Selectie",
    "sg:phone":"+31 38 422 3548",
    "sg:postcode":"8031 ES",
    "sg:province":"NL.08",
    "sg:website":"http://www.hj.nl",
    "wof:name":"Hj Bv",
    "wof:placetype":"venue"
},
  "geometry": {"coordinates":[6.0847821236,52.5177764893],"type":"Point"}
}