{
  "type": "Feature",
  "properties": {
    "addr:full":"De Wel 1416 Hoevelaken Gelderland 3871 MV",
    "addr:housenumber":"1416",
    "addr:postcode":"3871 mv",
    "addr:street":"De Wel;Gelderland",
    "iso:country":"NL",
    "sg:address":"De Wel 1416",
    "sg:city":"Hoevelaken",
    "sg:orig_category":"Adviesbureaus Verzekeringen",
    "sg:phone":"+31 33 258 0460",
    "sg:postcode":"3871 MV",
    "sg:province":"Gelderland",
    "wof:name":"D & O Bv, Bur",
    "wof:placetype":"venue"
},
  "geometry": {"coordinates":[5.46516,52.166672],"type":"Point"}
}