{
  "type": "Feature",
  "properties": {
    "addr:full":"Raadhuisstr 55 Hoogerheide North Brabant 4631 NB",
    "addr:housenumber":"55",
    "addr:postcode":"4631 nb",
    "addr:street":"Raadhuisstr",
    "iso:country":"NL",
    "sg:address":"Raadhuisstr 55",
    "sg:city":"Hoogerheide",
    "sg:orig_category":"Belastingconsulenten/ Belastingadviseurs",
    "sg:phone":"+31 164 613 162",
    "sg:postcode":"4631 NB",
    "sg:province":"North Brabant",
    "wof:name":"Burgt-Daalmans, Van De",
    "wof:placetype":"venue"
},
  "geometry": {"coordinates":[4.321887,51.426601],"type":"Point"}
}