{
  "type": "Feature",
  "properties": {
    "addr:full":"Stuwmeer 130 Houten Utrecht 3994 HS",
    "addr:housenumber":"130",
    "addr:postcode":"3994 hs",
    "addr:street":"Stuwmeer",
    "iso:country":"NL",
    "sg:address":"Stuwmeer 130",
    "sg:city":"Houten",
    "sg:orig_category":"Schilders",
    "sg:phone":"+31 30 634 2887",
    "sg:postcode":"3994 HS",
    "sg:province":"Utrecht",
    "wof:name":"Mks",
    "wof:placetype":"venue"
},
  "geometry": {"coordinates":[5.196055,52.019711],"type":"Point"}
}