{
  "type": "Feature",
  "properties": {
    "addr:full":"Secr Varkevisserstr 335 Katwijk Zh Zuid-Holland 2225 LD",
    "addr:housenumber":"335",
    "addr:postcode":"2225 ld",
    "iso:country":"NL",
    "sg:address":"Secr Varkevisserstr 335",
    "sg:city":"Katwijk Zh",
    "sg:classifiers":[
        {
            "category":"Fast Food",
            "type":"Food & Drink"
        }
    ],
    "sg:phone":"+31 71 407 1931",
    "sg:postcode":"2225 LD",
    "sg:province":"Zuid-Holland",
    "sg:tags":[
        "afhaal",
        "restaurant"
    ],
    "wof:name":"T Anker",
    "wof:placetype":"venue"
},
  "geometry": {"coordinates":[4.40577,52.200565],"type":"Point"}
}