{
  "type": "Feature",
  "properties": {
    "addr:full":"Zuidkd 2 Veghel Noord-Brabant 5462 CD",
    "addr:housenumber":"2",
    "addr:postcode":"5462 cd",
    "addr:street":"Zuidkd",
    "iso:country":"NL",
    "sg:address":"Zuidkd 2",
    "sg:city":"Veghel",
    "sg:orig_category":"Administratie- En Boekhoudkantoren",
    "sg:phone":"+31 413 365 780",
    "sg:postcode":"5462 CD",
    "sg:province":"Noord-Brabant",
    "wof:name":"Amwa",
    "wof:placetype":"venue"
},
  "geometry": {"coordinates":[5.528348,51.61729],"type":"Point"}
}