{
  "type": "Feature",
  "properties": {
    "addr:full":"Nyverdalsestr 27/B Wierden Overijssel 7642 AA",
    "addr:housenumber":"27 / b",
    "addr:postcode":"7642 aa",
    "addr:street":"Nyverdalsestr",
    "iso:country":"NL",
    "sg:address":"Nyverdalsestr 27/B",
    "sg:city":"Wierden",
    "sg:classifiers":[
        {
            "category":"Food & Beverages",
            "subcategory":"Bakery",
            "type":"Retail Goods"
        }
    ],
    "sg:phone":"+31 546 575 654",
    "sg:postcode":"7642 AA",
    "sg:province":"Overijssel",
    "sg:tags":[
        "pizza"
    ],
    "wof:name":"Rivi\u00e8ra, La",
    "wof:placetype":"venue"
},
  "geometry": {"coordinates":[6.580354,52.360081],"type":"Point"}
}