{
  "type": "Feature",
  "properties": {
    "addr:full":"Dostojevskisngl 151 Amsterdam Zuidoost North Holland 1102 XL",
    "addr:housenumber":"151",
    "addr:postcode":"1102 xl",
    "iso:country":"NL",
    "sg:address":"Dostojevskisngl 151",
    "sg:city":"Amsterdam Zuidoost",
    "sg:orig_category":"Autorijscholen",
    "sg:phone":"+31 20 695 9522",
    "sg:postcode":"1102 XL",
    "sg:province":"North Holland",
    "sg:website":"http://www.rijschool-first.com",
    "wof:name":"First Autorijschool",
    "wof:placetype":"venue"
},
  "geometry": {"coordinates":[4.947921,52.324066],"type":"Point"}
}