{
  "type": "Feature",
  "properties": {
    "addr:full":"Diezerstr 111 Zwolle NL.08 8011 RE",
    "addr:housenumber":"111",
    "addr:postcode":"8011",
    "iso:country":"NL",
    "sg:address":"Diezerstr 111",
    "sg:city":"Zwolle",
    "sg:orig_category":"Dameskleding",
    "sg:phone":"+31 38 386 9964",
    "sg:postcode":"8011 RE",
    "sg:province":"NL.08",
    "wof:name":"Factory",
    "wof:placetype":"venue"
},
  "geometry": {"coordinates":[6.098314,52.513542],"type":"Point"}
}