{
  "type": "Feature",
  "properties": {
    "addr:full":"Hoofdstr 61 Terheyden Noord-Brabant 4844 CB",
    "addr:housenumber":"61",
    "addr:postcode":"4844 cb",
    "addr:street":"Hoofdstr",
    "iso:country":"NL",
    "sg:address":"Hoofdstr 61",
    "sg:city":"Terheyden",
    "sg:orig_category":"Postkantoren",
    "sg:phone":"+31 76 593 1320",
    "sg:postcode":"4844 CB",
    "sg:province":"Noord-Brabant",
    "sg:website":"http://www.postkantoor.nl",
    "wof:name":"Postkantoor",
    "wof:placetype":"venue"
},
  "geometry": {"coordinates":[4.754773,51.641182],"type":"Point"}
}