{
  "type": "Feature",
  "properties": {
    "addr:full":"Dalmatie 46 Leusden Utrecht 3831 EG",
    "addr:housenumber":"46",
    "addr:postcode":"3831 eg",
    "addr:street":"Dalmatie",
    "iso:country":"NL",
    "sg:address":"Dalmatie 46",
    "sg:city":"Leusden",
    "sg:orig_category":"Adviesbureaus Bedrijfsorganisatie",
    "sg:phone":"+31 33 432 0048",
    "sg:postcode":"3831 EG",
    "sg:province":"Utrecht",
    "wof:name":"Wieren, Van",
    "wof:placetype":"venue"
},
  "geometry": {"coordinates":[5.43449,52.134151],"type":"Point"}
}