{
  "type": "Feature",
  "properties": {
    "iso:country":"NL",
    "sg:address":"Nyhoffln 35",
    "sg:city":"Veenendaal",
    "sg:orig_category":"Schilders",
    "sg:phone":"+31 318 512 986",
    "sg:postcode":"3906 EV",
    "sg:province":"Utrecht",
    "wof:name":"Bruin, M De",
    "wof:placetype":"venue"
},
  "geometry": {"coordinates":[5.55418,52.024902],"type":"Point"}
}