{
  "type": "Feature",
  "properties": {
    "addr:full":"Apollowg 11 Moerdyk Noord-Brabant 4782 SB",
    "addr:housenumber":"11",
    "addr:postcode":"4782 sb",
    "addr:street":"Apollowg",
    "iso:country":"NL",
    "sg:address":"Apollowg 11",
    "sg:city":"Moerdyk",
    "sg:orig_category":"Heftrucks",
    "sg:phone":"+31 168 380 110",
    "sg:postcode":"4782 SB",
    "sg:province":"Noord-Brabant",
    "wof:name":"Crepa Reyners Bv",
    "wof:placetype":"venue"
},
  "geometry": {"coordinates":[4.605904,51.689396],"type":"Point"}
}