{
  "type": "Feature",
  "properties": {
    "addr:full":"T Naeffstr 12 Rotterdam South Holland 3069 WS",
    "addr:housenumber":"12",
    "addr:postcode":"3069 ws",
    "iso:country":"NL",
    "sg:address":"T Naeffstr 12",
    "sg:city":"Rotterdam",
    "sg:orig_category":"Honden- En Kattentrimsalons",
    "sg:phone":"+31 10 421 4899",
    "sg:postcode":"3069 WS",
    "sg:province":"South Holland",
    "wof:name":"Pasha",
    "wof:placetype":"venue"
},
  "geometry": {"coordinates":[4.567108,51.965706],"type":"Point"}
}