{
  "type": "Feature",
  "properties": {
    "iso:country":"NL",
    "sg:address":"Industriewg 33-37",
    "sg:city":"Zoetermeer",
    "sg:orig_category":"Kasregisters",
    "sg:phone":"+31 79 316 6799",
    "sg:postcode":"2712 LA",
    "sg:province":"Zuid-Holland",
    "sg:website":"http://www.wbrand.nl",
    "wof:name":"Brand, W",
    "wof:placetype":"venue"
},
  "geometry": {"coordinates":[4.51078,52.047771],"type":"Point"}
}