{
  "type": "Feature",
  "properties": {
    "addr:full":"St Annapln 3 Oudenbosch Noord-Brabant 4731 HN",
    "addr:housenumber":"3",
    "addr:postcode":"4731 hn",
    "iso:country":"NL",
    "sg:address":"St Annapln 3",
    "sg:city":"Oudenbosch",
    "sg:orig_category":"Bibliotheken En Leeszalen Openbare",
    "sg:phone":"+31 165 313 287",
    "sg:postcode":"4731 HN",
    "sg:province":"Noord-Brabant",
    "wof:name":"Openb Bibliotheek",
    "wof:placetype":"venue"
},
  "geometry": {"coordinates":[4.529664,51.589806],"type":"Point"}
}