{
  "type": "Feature",
  "properties": {
    "addr:full":"Twuyverwg 49 St Pancras North Holland 1834 AB",
    "addr:housenumber":"49",
    "addr:postcode":"1834 ab",
    "addr:street":"Twuyverwg",
    "iso:country":"NL",
    "sg:address":"Twuyverwg 49",
    "sg:city":"St Pancras",
    "sg:orig_category":"Metselwerken",
    "sg:phone":"+31 72 564 3153",
    "sg:postcode":"1834 AB",
    "sg:province":"North Holland",
    "wof:name":"Louwen Bv, Metselbedrijf Gebr",
    "wof:placetype":"venue"
},
  "geometry": {"coordinates":[4.792744,52.665539],"type":"Point"}
}