{
  "type": "Feature",
  "properties": {
    "addr:full":"Nieuweweg 62 Wormer Noord-Holland 1531 AG",
    "addr:housenumber":"62",
    "addr:postcode":"1531",
    "addr:street":"Nieuweweg",
    "iso:country":"NL",
    "sg:address":"Nieuweweg 62",
    "sg:city":"Wormer",
    "sg:orig_category":"Muziekinstrumenten",
    "sg:phone":"+31 75 642 1682",
    "sg:postcode":"1531 AG",
    "sg:province":"Noord-Holland",
    "wof:name":"Ron Meyjes Pianotechniek",
    "wof:placetype":"venue"
},
  "geometry": {"coordinates":[4.799772,52.493732],"type":"Point"}
}