{
  "type": "Feature",
  "properties": {
    "iso:country":"NL",
    "sg:address":"Azaleastr 40/A",
    "sg:city":"Rotterdam",
    "sg:orig_category":"Adviesbureaus Bedrijfsorganisatie",
    "sg:phone":"+31 10 418 8114",
    "sg:postcode":"3051 TG",
    "sg:province":"Zuid-Holland",
    "wof:name":"Vlugt, J J M Van Der",
    "wof:placetype":"venue"
},
  "geometry": {"coordinates":[4.47369,51.94273],"type":"Point"}
}