{
  "type": "Feature",
  "properties": {
    "addr:full":"Vryheidsln 12 Delft South Holland 2625 RD",
    "addr:housenumber":"12",
    "addr:postcode":"2625 rd",
    "addr:street":"Vryheidsln",
    "iso:country":"NL",
    "sg:address":"Vryheidsln 12",
    "sg:city":"Delft",
    "sg:orig_category":"Kappers",
    "sg:phone":"+31 15 257 1421",
    "sg:postcode":"2625 RD",
    "sg:province":"South Holland",
    "wof:name":"Headline, Haarmode",
    "wof:placetype":"venue"
},
  "geometry": {"coordinates":[4.3418397903,51.992351532],"type":"Point"}
}