{
  "type": "Feature",
  "properties": {
    "addr:full":"Badwg 22 Doetinchem Gelderland 7004 GV",
    "addr:housenumber":"22",
    "addr:postcode":"7004 gv",
    "addr:street":"Badwg;Gelderland",
    "iso:country":"NL",
    "sg:address":"Badwg 22",
    "sg:city":"Doetinchem",
    "sg:orig_category":"Onroerende Goederen",
    "sg:phone":"+31 314 391 352",
    "sg:postcode":"7004 GV",
    "sg:province":"Gelderland",
    "wof:name":"Sandt Bv, Van Der",
    "wof:placetype":"venue"
},
  "geometry": {"coordinates":[6.317563,51.955345],"type":"Point"}
}