{
  "type": "Feature",
  "properties": {
    "iso:country":"NL",
    "sg:address":"De Havik 52",
    "sg:city":"Denekamp",
    "sg:orig_category":"Prefabconstructies",
    "sg:phone":"+31 541 353 330",
    "sg:postcode":"7591 JT",
    "sg:province":"NL.08",
    "wof:name":"Denekamp Bv",
    "wof:placetype":"venue"
},
  "geometry": {"coordinates":[7.006727,52.386829],"type":"Point"}
}