{
  "type": "Feature",
  "properties": {
    "addr:full":"Kerkstr 16 Bergeyk North Brabant 5571 CK",
    "addr:housenumber":"16",
    "addr:postcode":"5571 ck",
    "addr:street":"Kerkstr",
    "iso:country":"NL",
    "sg:address":"Kerkstr 16",
    "sg:city":"Bergeyk",
    "sg:orig_category":"Beeldende Kunstenaars",
    "sg:phone":"+31 497 550 545",
    "sg:postcode":"5571 CK",
    "sg:province":"North Brabant",
    "wof:name":"Verhoeven, Harry",
    "wof:placetype":"venue"
},
  "geometry": {"coordinates":[5.361618,51.321262],"type":"Point"}
}