{
  "type": "Feature",
  "properties": {
    "addr:full":"O Vlisterdk 14 Vlist Zuid-Holland 2855 AC",
    "addr:housenumber":"14",
    "addr:postcode":"2855 ac",
    "iso:country":"NL",
    "sg:address":"O Vlisterdk 14",
    "sg:city":"Vlist",
    "sg:orig_category":"Grondwerken",
    "sg:phone":"+31 182 501 271",
    "sg:postcode":"2855 AC",
    "sg:province":"Zuid-Holland",
    "wof:name":"Marco Spruit",
    "wof:placetype":"venue"
},
  "geometry": {"coordinates":[4.827385,51.971668],"type":"Point"}
}