{
  "type": "Feature",
  "properties": {
    "addr:full":"Zuideinde 412 Amsterdam Noord-Holland 1035 PR",
    "addr:housenumber":"412",
    "addr:postcode":"1035 pr",
    "addr:street":"Zuideinde",
    "iso:country":"NL",
    "sg:address":"Zuideinde 412",
    "sg:city":"Amsterdam",
    "sg:orig_category":"Juweliers",
    "sg:phone":"+31 20 633 5134",
    "sg:postcode":"1035 PR",
    "sg:province":"Noord-Holland",
    "wof:name":"E. Th. Rosenbaum Juwelier",
    "wof:placetype":"venue"
},
  "geometry": {"coordinates":[4.895329,52.417393],"type":"Point"}
}