{
  "type": "Feature",
  "properties": {
    "iso:country":"NL",
    "sg:address":"De Weyver 6",
    "sg:city":"Hoogwoud",
    "sg:orig_category":"Mensendieck - Oefentherapeuten",
    "sg:phone":"+31 226 351 839",
    "sg:postcode":"1718 MS",
    "sg:province":"Noord-Holland",
    "wof:name":"Br\u00fchl Mensendieck Oefentherapeut",
    "wof:placetype":"venue"
},
  "geometry": {"coordinates":[4.936716,52.708294],"type":"Point"}
}