{
  "type": "Feature",
  "properties": {
    "addr:full":"Riethovensewg 14 Steensel Noord-Brabant 5524 BB",
    "addr:housenumber":"14",
    "addr:postcode":"5524 bb",
    "addr:street":"Riethovensewg",
    "iso:country":"NL",
    "sg:address":"Riethovensewg 14",
    "sg:city":"Steensel",
    "sg:orig_category":"Koeltechniek",
    "sg:phone":"+31 497 515 715",
    "sg:postcode":"5524 BB",
    "sg:province":"Noord-Brabant",
    "wof:name":"Renders",
    "wof:placetype":"venue"
},
  "geometry": {"coordinates":[5.356593,51.377338],"type":"Point"}
}