{
  "type": "Feature",
  "properties": {
    "addr:full":"Jan Van Gentstraat 36 Petten North Holland 1755 PC",
    "addr:housenumber":"36",
    "addr:postcode":"1755 pc",
    "addr:street":"Jan Van Gentstraat",
    "iso:country":"NL",
    "sg:address":"Jan Van Gentstraat 36",
    "sg:city":"Petten",
    "sg:orig_category":"Kappers",
    "sg:phone":"+31 226 381 244",
    "sg:postcode":"1755 PC",
    "sg:province":"North Holland",
    "wof:name":"A. Ridderhof",
    "wof:placetype":"venue"
},
  "geometry": {"coordinates":[4.6587891579,52.7677574158],"type":"Point"}
}