{
  "type": "Feature",
  "properties": {
    "addr:full":"Limburglaan 25 Maastricht Limburg 6229 GA",
    "addr:housenumber":"25",
    "addr:postcode":"6229 ga",
    "addr:street":"Limburglaan",
    "iso:country":"NL",
    "sg:address":"Limburglaan 25",
    "sg:city":"Maastricht",
    "sg:orig_category":"Waterbeheer",
    "sg:phone":"+31 43 880 8088",
    "sg:postcode":"6229 GA",
    "sg:province":"Limburg",
    "wof:name":"Nv Waterleidingmaatschappij Limburg",
    "wof:placetype":"venue"
},
  "geometry": {"coordinates":[5.703523159,50.8369064331],"type":"Point"}
}