{
  "type": "Feature",
  "properties": {
    "addr:full":"Bloemendijk 24 Dinteloord Noord-Brabant 4671 PN",
    "addr:housenumber":"24",
    "addr:postcode":"4671 pn",
    "addr:street":"Bloemendijk",
    "iso:country":"NL",
    "sg:address":"Bloemendijk 24",
    "sg:city":"Dinteloord",
    "sg:orig_category":"Verhuur Bouwmachines",
    "sg:phone":"+31 167 522 479",
    "sg:postcode":"4671 PN",
    "sg:province":"Noord-Brabant",
    "wof:name":"A P Schyvenaars",
    "wof:placetype":"venue"
},
  "geometry": {"coordinates":[4.338779,51.623131],"type":"Point"}
}