{
  "type": "Feature",
  "properties": {
    "addr:full":"J S Bachln 135 Leidschendam South Holland 2264 WD",
    "addr:housenumber":"135",
    "addr:postcode":"2264 wd",
    "iso:country":"NL",
    "sg:address":"J S Bachln 135",
    "sg:city":"Leidschendam",
    "sg:orig_category":"Architecten En Architectenbureaus",
    "sg:phone":"+31 70 320 9268",
    "sg:postcode":"2264 WD",
    "sg:province":"South Holland",
    "wof:name":"Kokshoorn, Paul",
    "wof:placetype":"venue"
},
  "geometry": {"coordinates":[4.393446,52.084591],"type":"Point"}
}