{
  "type": "Feature",
  "properties": {
    "addr:full":"Churchillln 70 Helmond North Brabant 5705 BK",
    "addr:housenumber":"70",
    "addr:postcode":"5705 bk",
    "addr:street":"Churchillln",
    "iso:country":"NL",
    "sg:address":"Churchillln 70",
    "sg:city":"Helmond",
    "sg:orig_category":"Heftrucks",
    "sg:phone":"+31 492 528 476",
    "sg:postcode":"5705 BK",
    "sg:province":"North Brabant",
    "sg:website":"http://www.vvl.nl",
    "wof:name":"Vakopleiding Vervoer & Logistiek Regio Zuid-Oost",
    "wof:placetype":"venue"
},
  "geometry": {"coordinates":[5.658284,51.482239],"type":"Point"}
}