{
  "type": "Feature",
  "properties": {
    "addr:full":"Oude Zwolseweg 5 Hoge Hexel Overijssel 7645 AZ",
    "addr:housenumber":"5",
    "addr:postcode":"7645 az",
    "addr:street":"Oude Zwolseweg",
    "iso:country":"NL",
    "sg:address":"Oude Zwolseweg 5",
    "sg:city":"Hoge Hexel",
    "sg:orig_category":"Levende Dieren Gh",
    "sg:phone":"+31 546 573 772",
    "sg:postcode":"7645 AZ",
    "sg:province":"Overijssel",
    "wof:name":"Veehandel J.H. Wolters",
    "wof:placetype":"venue"
},
  "geometry": {"coordinates":[6.560789,52.397072],"type":"Point"}
}