{
  "type": "Feature",
  "properties": {
    "addr:full":"Kayersdijk 95 Apeldoorn Gelderland 7332 AM",
    "addr:housenumber":"95",
    "addr:postcode":"7332",
    "addr:street":"Kayersdijk;Gelderland",
    "iso:country":"NL",
    "sg:address":"Kayersdijk 95",
    "sg:city":"Apeldoorn",
    "sg:orig_category":"Verhuur Catering-, Feest- En Evenementbenodigdheden",
    "sg:phone":"+31 55 533 3151",
    "sg:postcode":"7332 AM",
    "sg:province":"Gelderland",
    "wof:name":"Apeldoornse Tent- En Zeilmakerij",
    "wof:placetype":"venue"
},
  "geometry": {"coordinates":[5.979763,52.198322],"type":"Point"}
}