{
  "type": "Feature",
  "properties": {
    "iso:country":"NL",
    "sg:address":"Oorgat 23A",
    "sg:city":"Edam",
    "sg:orig_category":"Jachthavens - Jachtwerven",
    "sg:phone":"+31 299 372 762",
    "sg:postcode":"1135 CP",
    "sg:province":"Noord-Holland",
    "wof:name":"Jachtscheepswerf Edam",
    "wof:placetype":"venue"
},
  "geometry": {"coordinates":[5.059504,52.513969],"type":"Point"}
}