{
  "type": "Feature",
  "properties": {
    "iso:country":"NL",
    "sg:address":"Frederik Hendrikstraat 115A",
    "sg:city":"Delft",
    "sg:orig_category":"Meubelreparatie And -Restauratie",
    "sg:phone":"+31 15 262 1393",
    "sg:postcode":"2628 TA",
    "sg:province":"South Holland",
    "wof:name":"Dyas Fine Art",
    "wof:placetype":"venue"
},
  "geometry": {"coordinates":[4.374903,52.007679],"type":"Point"}
}