{
  "type": "Feature",
  "properties": {
    "addr:full":"Lindenlaan 6 Staphorst Overijssel 7951 BV",
    "addr:housenumber":"6",
    "addr:postcode":"7951 bv",
    "addr:street":"Lindenlaan",
    "iso:country":"NL",
    "sg:address":"Lindenlaan 6",
    "sg:city":"Staphorst",
    "sg:orig_category":"Bloemen And Planten",
    "sg:phone":"+31 522 461 937",
    "sg:postcode":"7951 BV",
    "sg:province":"Overijssel",
    "wof:name":"Firma Liberty Bloemen",
    "wof:placetype":"venue"
},
  "geometry": {"coordinates":[6.20717,52.647995],"type":"Point"}
}