{
  "type": "Feature",
  "properties": {
    "addr:full":"Hoofdstr 99 Noordwyk Zh Zuid-Holland 2202 EW",
    "addr:housenumber":"99",
    "addr:postcode":"2202 ew",
    "addr:street":"Hoofdstr",
    "iso:country":"NL",
    "sg:address":"Hoofdstr 99",
    "sg:city":"Noordwyk Zh",
    "sg:orig_category":"Postkantoren",
    "sg:phone":"+31 71 361 6661",
    "sg:postcode":"2202 EW",
    "sg:province":"Zuid-Holland",
    "sg:website":"http://www.postkantoor.nl",
    "wof:name":"Postkantoor",
    "wof:placetype":"venue"
},
  "geometry": {"coordinates":[4.431251,52.243408],"type":"Point"}
}