{
  "type": "Feature",
  "properties": {
    "iso:country":"NL",
    "sg:address":"Parallelwg W 37",
    "sg:city":"Culemborg",
    "sg:orig_category":"Meubelen - Fabrieken En Groothandel",
    "sg:phone":"+31 345 513 979",
    "sg:postcode":"4107 NA",
    "sg:province":"Gelderland",
    "wof:name":"Jonkman",
    "wof:placetype":"venue"
},
  "geometry": {"coordinates":[5.22976,51.942913],"type":"Point"}
}