{
  "type": "Feature",
  "properties": {
    "addr:full":"Hoofdstraat 40 Sint Jansteen Salta 4564 AR",
    "addr:housenumber":"40",
    "addr:postcode":"4564",
    "addr:street":"Hoofdstraat;Salta",
    "iso:country":"NL",
    "sg:address":"Hoofdstraat 40",
    "sg:city":"Sint Jansteen",
    "sg:orig_category":"Kappers",
    "sg:phone":"+31 114 312 922",
    "sg:postcode":"4564 AR",
    "sg:province":"Salta",
    "wof:name":"Kapsalon F.P.S. Van De Wiele",
    "wof:placetype":"venue"
},
  "geometry": {"coordinates":[-63.7905082703,-22.3614692688],"type":"Point"}
}