{
  "type": "Feature",
  "properties": {
    "addr:full":"Loskd 9 Middelburg Zeeland 4331 HV",
    "addr:housenumber":"9",
    "addr:postcode":"4331 hv",
    "addr:street":"Loskd",
    "iso:country":"NL",
    "sg:address":"Loskd 9",
    "sg:city":"Middelburg",
    "sg:orig_category":"Dameskleding",
    "sg:phone":"+31 118 623 246",
    "sg:postcode":"4331 HV",
    "sg:province":"Zeeland",
    "wof:name":"Eszeth",
    "wof:placetype":"venue"
},
  "geometry": {"coordinates":[3.609615,51.495415],"type":"Point"}
}