{
  "type": "Feature",
  "properties": {
    "addr:full":"Buitendams 33 Hardinxveld Giessend Zuid-Holland 3371 BA",
    "addr:housenumber":"33;giessend",
    "addr:postcode":"3371 ba",
    "addr:street":"Buitendams",
    "iso:country":"NL",
    "sg:address":"Buitendams 33",
    "sg:city":"Hardinxveld Giessend",
    "sg:orig_category":"Kappers",
    "sg:phone":"+31 184 670 474",
    "sg:postcode":"3371 BA",
    "sg:province":"Zuid-Holland",
    "wof:name":"Dameskapsalon Ockers",
    "wof:placetype":"venue"
},
  "geometry": {"coordinates":[4.8324432373,51.8274688721],"type":"Point"}
}