{
  "type": "Feature",
  "properties": {
    "addr:full":"F Halsplnts 10 Voorschoten Zuid-Holland 2251 XJ",
    "addr:housenumber":"10",
    "addr:postcode":"2251 xj",
    "iso:country":"NL",
    "sg:address":"F Halsplnts 10",
    "sg:city":"Voorschoten",
    "sg:orig_category":"Verenigingsgebouwen",
    "sg:phone":"+31 71 561 4016",
    "sg:postcode":"2251 XJ",
    "sg:province":"Zuid-Holland",
    "wof:name":"Groene Kikker, De",
    "wof:placetype":"venue"
},
  "geometry": {"coordinates":[4.44429,52.124825],"type":"Point"}
}