{
  "type": "Feature",
  "properties": {
    "iso:country":"NL",
    "sg:address":"Buitenplein 82",
    "sg:city":"Amstelveen",
    "sg:classifiers":[
        {
            "category":"Fast Food",
            "type":"Food & Drink"
        }
    ],
    "sg:phone":"+31 20 441 7539",
    "sg:postcode":"1181 ZE",
    "sg:province":"Noord-Holland",
    "sg:tags":[
        "afhaal",
        "restaurant"
    ],
    "wof:name":"Mcdonald'S Restaurant",
    "wof:placetype":"venue"
},
  "geometry": {"coordinates":[4.863326,52.30175],"type":"Point"}
}