{
  "type": "Feature",
  "properties": {
    "addr:full":"Kruiswg 482 Hoofddorp Noord-Holland 2132 LA",
    "addr:housenumber":"482",
    "addr:postcode":"2132 la",
    "iso:country":"NL",
    "sg:address":"Kruiswg 482",
    "sg:city":"Hoofddorp",
    "sg:orig_category":"Projectontwikkeling",
    "sg:phone":"+31 23 561 5372",
    "sg:postcode":"2132 LA",
    "sg:province":"Noord-Holland",
    "sg:website":"http://www.meerschip.nl",
    "wof:name":"Meerschip Bv",
    "wof:placetype":"venue"
},
  "geometry": {"coordinates":[4.71434,52.292171],"type":"Point"}
}