{
  "type": "Feature",
  "properties": {
    "addr:full":"Emmastr 33 Alkmaar North Holland 1814 DM",
    "addr:housenumber":"33",
    "addr:postcode":"1814 dm",
    "addr:street":"Emmastr",
    "iso:country":"NL",
    "sg:address":"Emmastr 33",
    "sg:city":"Alkmaar",
    "sg:orig_category":"Adviesbureaus Bouwkunde",
    "sg:phone":"+31 72 515 3241",
    "sg:postcode":"1814 DM",
    "sg:province":"North Holland",
    "wof:name":"Luijn, Van",
    "wof:placetype":"venue"
},
  "geometry": {"coordinates":[4.741917,52.626553],"type":"Point"}
}