{
  "type": "Feature",
  "properties": {
    "addr:full":"Regenboogstraat 39 Zierikzee Zeeland 4301 BS",
    "addr:housenumber":"39",
    "addr:postcode":"4301 bs",
    "addr:street":"Regenboogstraat",
    "iso:country":"NL",
    "sg:address":"Regenboogstraat 39",
    "sg:city":"Zierikzee",
    "sg:orig_category":"Pleziervaartuigen And Reparatie",
    "sg:phone":"+31 111 414 929",
    "sg:postcode":"4301 BS",
    "sg:province":"Zeeland",
    "wof:name":"Multiconsult",
    "wof:placetype":"venue"
},
  "geometry": {"coordinates":[3.912857,51.648537],"type":"Point"}
}