{
  "type": "Feature",
  "properties": {
    "addr:full":"Ter Leedeln 13 Sassenheim Zuid-Holland 2172 JK",
    "addr:housenumber":"13",
    "addr:postcode":"2172 jk",
    "iso:country":"NL",
    "sg:address":"Ter Leedeln 13",
    "sg:city":"Sassenheim",
    "sg:orig_category":"Grafische Bedrijven",
    "sg:phone":"+31 252 225 888",
    "sg:postcode":"2172 JK",
    "sg:province":"Zuid-Holland",
    "sg:website":"http://www.siriusb.nl",
    "wof:name":"Sirius-B",
    "wof:placetype":"venue"
},
  "geometry": {"coordinates":[4.5302758217,52.2307510376],"type":"Point"}
}