{
  "type": "Feature",
  "properties": {
    "addr:full":"Professor Dr Dorgelolaan 36 Eindhoven Noord-Brabant 5613 AM",
    "addr:housenumber":"36",
    "addr:postcode":"5613",
    "addr:street":"Professor Dr Dorgelolaan",
    "iso:country":"NL",
    "sg:address":"Professor Dr Dorgelolaan 36",
    "sg:city":"Eindhoven",
    "sg:orig_category":"Banken And Kredietinstellingen",
    "sg:phone":"+31 40 246 6122",
    "sg:postcode":"5613 AM",
    "sg:province":"Noord-Brabant",
    "wof:name":"Meespierson Nv",
    "wof:placetype":"venue"
},
  "geometry": {"coordinates":[5.49399,51.445595],"type":"Point"}
}