{
  "type": "Feature",
  "properties": {
    "addr:full":"Kapelstraat 1 Wageningen Gelderland 6701 DD",
    "addr:housenumber":"1",
    "addr:postcode":"6701 dd",
    "addr:street":"Kapelstraat;Gelderland",
    "iso:country":"NL",
    "sg:address":"Kapelstraat 1",
    "sg:city":"Wageningen",
    "sg:orig_category":"Damesmodezaken",
    "sg:phone":"+31 317 411 614",
    "sg:postcode":"6701 DD",
    "sg:province":"Gelderland",
    "wof:name":"Boutique Chapelle",
    "wof:placetype":"venue"
},
  "geometry": {"coordinates":[5.663209,51.965466],"type":"Point"}
}