{
  "type": "Feature",
  "properties": {
    "addr:full":"Marevista 36 Noordwyk Zh Zuid-Holland 2202 BX",
    "addr:housenumber":"36",
    "addr:postcode":"2202 bx",
    "addr:street":"Marevista",
    "iso:country":"NL",
    "sg:address":"Marevista 36",
    "sg:city":"Noordwyk Zh",
    "sg:orig_category":"Adviesbureaus Economie",
    "sg:phone":"+31 71 361 9852",
    "sg:postcode":"2202 BX",
    "sg:province":"Zuid-Holland",
    "wof:name":"Bemolt Bv",
    "wof:placetype":"venue"
},
  "geometry": {"coordinates":[4.435614,52.248837],"type":"Point"}
}