{
  "type": "Feature",
  "properties": {
    "addr:full":"Hellingwg 192 S Gravenhage South Holland 2583 DX",
    "addr:housenumber":"192",
    "addr:postcode":"2583 dx",
    "addr:street":"S Gravenhage",
    "iso:country":"NL",
    "sg:address":"Hellingwg 192",
    "sg:city":"S Gravenhage",
    "sg:orig_category":"Sportverenigingen En Ontspannings- Verenigingen",
    "sg:phone":"+31 70 354 9696",
    "sg:postcode":"2583 DX",
    "sg:province":"South Holland",
    "wof:name":"Afrit Scheveningen, De",
    "wof:placetype":"venue"
},
  "geometry": {"coordinates":[4.25526,52.09124],"type":"Point"}
}