{
  "type": "Feature",
  "properties": {
    "addr:full":"Welgelegenwg 19 Apeldoorn Gelderland 7321 AV",
    "addr:housenumber":"19",
    "addr:postcode":"7321 av",
    "addr:street":"Welgelegenwg;Gelderland",
    "iso:country":"NL",
    "sg:address":"Welgelegenwg 19",
    "sg:city":"Apeldoorn",
    "sg:orig_category":"Fietsen En Bromfietsen",
    "sg:phone":"+31 55 366 4583",
    "sg:postcode":"7321 AV",
    "sg:province":"Gelderland",
    "wof:name":"Os, E Van",
    "wof:placetype":"venue"
},
  "geometry": {"coordinates":[5.977169,52.214302],"type":"Point"}
}