{
  "type": "Feature",
  "properties": {
    "addr:full":"Piccolopad 9 Dongen Noord-Brabant 5101 AD",
    "addr:housenumber":"9",
    "addr:postcode":"5101 ad",
    "addr:street":"Piccolopad",
    "iso:country":"NL",
    "sg:address":"Piccolopad 9",
    "sg:city":"Dongen",
    "sg:orig_category":"Antiquiteiten - Restauratie",
    "sg:phone":"+31 162 320 840",
    "sg:postcode":"5101 AD",
    "sg:province":"Noord-Brabant",
    "wof:name":"Biezen, Evelien Van",
    "wof:placetype":"venue"
},
  "geometry": {"coordinates":[4.93351,51.626541],"type":"Point"}
}