{
  "type": "Feature",
  "properties": {
    "iso:country":"NL",
    "sg:address":"Markt 44",
    "sg:city":"Brouwershaven",
    "sg:orig_category":"Visspeciaalzaken",
    "sg:phone":"+31 111 692 163",
    "sg:postcode":"4318 AH",
    "sg:province":"Zeeland",
    "wof:name":"Van Beveren'S Vishandel",
    "wof:placetype":"venue"
},
  "geometry": {"coordinates":[3.913226,51.725422],"type":"Point"}
}