{
  "type": "Feature",
  "properties": {
    "addr:full":"Schoolwg 16 Nunspeet Gelderland 8071 BC",
    "addr:housenumber":"16",
    "addr:postcode":"8071 bc",
    "addr:street":"Schoolwg;Gelderland",
    "iso:country":"NL",
    "sg:address":"Schoolwg 16",
    "sg:city":"Nunspeet",
    "sg:orig_category":"Adviesbureaus Werktuigbouwkunde",
    "sg:phone":"+31 341 252 541",
    "sg:postcode":"8071 BC",
    "sg:province":"Gelderland",
    "wof:name":"Veteco",
    "wof:placetype":"venue"
},
  "geometry": {"coordinates":[5.788766,52.374393],"type":"Point"}
}