{
  "type": "Feature",
  "properties": {
    "addr:full":"Iersestr 15 Nieuwerkerk Yssel Zuid-Holland 2912 TH",
    "addr:housenumber":"15",
    "addr:postcode":"2912 th",
    "addr:street":"Iersestr",
    "iso:country":"NL",
    "sg:address":"Iersestr 15",
    "sg:city":"Nieuwerkerk Yssel",
    "sg:orig_category":"Fitnesscentra",
    "sg:phone":"+31 180 321 544",
    "sg:postcode":"2912 TH",
    "sg:province":"Zuid-Holland",
    "sg:website":"http://www.achmeahealthcenters.nl",
    "wof:name":"Achmea Healthcenter",
    "wof:placetype":"venue"
},
  "geometry": {"coordinates":[4.602494,51.962234],"type":"Point"}
}