{
  "type": "Feature",
  "properties": {
    "iso:country":"NL",
    "sg:address":"Stadhouderslaan 1",
    "sg:city":"Vlaardingen",
    "sg:classifiers":[
        {
            "category":"Education",
            "subcategory":"Preschool",
            "type":"Public Place"
        }
    ],
    "sg:phone":"+31 10 474 8192",
    "sg:postcode":"3136 BK",
    "sg:province":"South Holland",
    "sg:tags":[
        "kleuteronderwijs",
        "basis-"
    ],
    "wof:name":"Obs Klimop",
    "wof:placetype":"venue"
},
  "geometry": {"coordinates":[4.350951,51.926273],"type":"Point"}
}