{
  "type": "Feature",
  "properties": {
    "iso:country":"NL",
    "sg:address":"Duisterestr 6",
    "sg:city":"Epe",
    "sg:orig_category":"Bestratingen",
    "sg:phone":"+31 578 612 833",
    "sg:postcode":"8162 GL",
    "sg:province":"Gelderland",
    "wof:name":"Vos & Zn",
    "wof:placetype":"venue"
},
  "geometry": {"coordinates":[5.973393,52.353504],"type":"Point"}
}