{
  "type": "Feature",
  "properties": {
    "iso:country":"NL",
    "sg:address":"E. Goldmanweg 4B",
    "sg:city":"Tilburg",
    "sg:orig_category":"Werving And Selectie Van Tijdelijk Personeel And Uitzendkantoren",
    "sg:phone":"+31 13 466 6530",
    "sg:postcode":"5032 MN",
    "sg:province":"North Brabant",
    "wof:name":"Randstad Transportdiensten",
    "wof:placetype":"venue"
},
  "geometry": {"coordinates":[5.0403079987,51.5373306274],"type":"Point"}
}