{
  "type": "Feature",
  "properties": {
    "addr:full":"Beneden Zandpad 15 Middelharnis South Holland 3241 GA",
    "addr:housenumber":"15",
    "addr:postcode":"3241 ga",
    "addr:street":"Beneden Zandpad",
    "iso:country":"NL",
    "sg:address":"Beneden Zandpad 15",
    "sg:city":"Middelharnis",
    "sg:orig_category":"Koffie- En Theehuizen",
    "sg:phone":"+31 187 482 507",
    "sg:postcode":"3241 GA",
    "sg:province":"South Holland",
    "wof:name":"Bienefelt, J P",
    "wof:placetype":"venue"
},
  "geometry": {"coordinates":[4.157658,51.760448],"type":"Point"}
}