{
  "type": "Feature",
  "properties": {
    "addr:full":"Payglop 9 Alkmaar Noord-Holland 1811 HM",
    "addr:housenumber":"9",
    "addr:postcode":"1811 hm",
    "addr:street":"Payglop",
    "iso:country":"NL",
    "sg:address":"Payglop 9",
    "sg:city":"Alkmaar",
    "sg:orig_category":"Boekhandels",
    "sg:phone":"+31 72 520 2232",
    "sg:postcode":"1811 HM",
    "sg:province":"Noord-Holland",
    "wof:name":"Witte Boekenmarkt, De",
    "wof:placetype":"venue"
},
  "geometry": {"coordinates":[4.748524,52.630684],"type":"Point"}
}