{
  "type": "Feature",
  "properties": {
    "addr:full":"Oceanenwg 2 Amsterdam North Holland 1047 BB",
    "addr:housenumber":"2",
    "addr:postcode":"1047 bb",
    "addr:street":"Oceanenwg",
    "iso:country":"NL",
    "sg:address":"Oceanenwg 2",
    "sg:city":"Amsterdam",
    "sg:orig_category":"Verf En Lak - Fabrieken En Groothandel",
    "sg:phone":"+31 20 407 5100",
    "sg:postcode":"1047 BB",
    "sg:province":"North Holland",
    "sg:website":"http://www.sigmacoatings.com",
    "wof:name":"Sigma Bv",
    "wof:placetype":"venue"
},
  "geometry": {"coordinates":[4.762203,52.407833],"type":"Point"}
}