{
  "type": "Feature",
  "properties": {
    "addr:full":"Grt Markt 17 Almere Flevoland 1315 JA",
    "addr:housenumber":"17",
    "addr:postcode":"1315 ja",
    "addr:street":"Markt;Flevoland",
    "iso:country":"NL",
    "sg:address":"Grt Markt 17",
    "sg:city":"Almere",
    "sg:orig_category":"Adviesbureaus Beroeps-, School- And Studiekeuze",
    "sg:phone":"+31 30 233 0144",
    "sg:postcode":"1315 JA",
    "sg:province":"Flevoland",
    "wof:name":"Boa",
    "wof:placetype":"venue"
},
  "geometry": {"coordinates":[5.21998,52.374531],"type":"Point"}
}