{
  "type": "Feature",
  "properties": {
    "iso:country":"NL",
    "sg:address":"Steenovenweg 5",
    "sg:city":"Deurne",
    "sg:orig_category":"Metaalwerken",
    "sg:phone":"+31 493 314 382",
    "sg:postcode":"5753 AJ",
    "sg:province":"Noord-Brabant",
    "wof:name":"P. Linders",
    "wof:placetype":"venue"
},
  "geometry": {"coordinates":[5.783017,51.454689],"type":"Point"}
}