{
  "type": "Feature",
  "properties": {
    "addr:full":"Ridder Hoenstraat 203 Hoensbroek Limburg 6433 EE",
    "addr:housenumber":"203",
    "addr:postcode":"6433 ee",
    "addr:street":"Ridder Hoenstraat",
    "iso:country":"NL",
    "sg:address":"Ridder Hoenstraat 203",
    "sg:city":"Hoensbroek",
    "sg:orig_category":"Fotostudio'S And Fotografen",
    "sg:phone":"+31 45 521 0584",
    "sg:postcode":"6433 EE",
    "sg:province":"Limburg",
    "wof:name":"Exposure",
    "wof:placetype":"venue"
},
  "geometry": {"coordinates":[5.925645,50.913559],"type":"Point"}
}