{
  "type": "Feature",
  "properties": {
    "iso:country":"NL",
    "sg:address":"Drietorensweg 29",
    "sg:city":"Ens",
    "sg:orig_category":"Public Relationbureaus",
    "sg:phone":"+31 527 251 056",
    "sg:postcode":"8307 PC",
    "sg:province":"Flevoland",
    "wof:name":"Newbizz Bv",
    "wof:placetype":"venue"
},
  "geometry": {"coordinates":[5.84457,52.629356],"type":"Point"}
}