{
  "type": "Feature",
  "properties": {
    "addr:full":"Baronielaan 59 Breda Noord-Brabant 4818 PC",
    "addr:housenumber":"59",
    "addr:postcode":"4818 pc",
    "addr:street":"Baronielaan",
    "iso:country":"NL",
    "sg:address":"Baronielaan 59",
    "sg:city":"Breda",
    "sg:orig_category":"Kantoor- And Schoolbenodigdheden Gh",
    "sg:phone":"+31 76 531 7317",
    "sg:postcode":"4818 PC",
    "sg:province":"Noord-Brabant",
    "wof:name":"Stevens Paper & Board Bv",
    "wof:placetype":"venue"
},
  "geometry": {"coordinates":[4.7770371437,51.5765228271],"type":"Point"}
}