{
  "type": "Feature",
  "properties": {
    "addr:full":"Asterstr 58 Den Helder Noord-Holland 1782 LR",
    "addr:housenumber":"58",
    "addr:postcode":"1782 lr",
    "addr:street":"Asterstr",
    "iso:country":"NL",
    "sg:address":"Asterstr 58",
    "sg:city":"Den Helder",
    "sg:orig_category":"Horeca-Inrichtingen En -Uitrustingen",
    "sg:phone":"+31 223 619 759",
    "sg:postcode":"1782 LR",
    "sg:province":"Noord-Holland",
    "wof:name":"Hordiver",
    "wof:placetype":"venue"
},
  "geometry": {"coordinates":[4.761588,52.948177],"type":"Point"}
}