{
  "type": "Feature",
  "properties": {
    "addr:full":"V Stolbergwg 4 Veendam Groningen 9641 HL",
    "addr:housenumber":"4",
    "addr:postcode":"9641 hl",
    "addr:street":"Stolbergwg",
    "iso:country":"NL",
    "sg:address":"V Stolbergwg 4",
    "sg:city":"Veendam",
    "sg:orig_category":"Verpakkingen En Verpakkingsmaterialen",
    "sg:phone":"+31 598 613 674",
    "sg:postcode":"9641 HL",
    "sg:province":"Groningen",
    "wof:name":"Rooze & Zn",
    "wof:placetype":"venue"
},
  "geometry": {"coordinates":[6.880442,53.106426],"type":"Point"}
}