{
  "type": "Feature",
  "properties": {
    "addr:full":"W Boothstr 205 Haarlem Noord-Holland 2037 SH",
    "addr:housenumber":"205",
    "addr:postcode":"2037 sh",
    "addr:street":"W",
    "iso:country":"NL",
    "sg:address":"W Boothstr 205",
    "sg:city":"Haarlem",
    "sg:orig_category":"Hoefsmederijen",
    "sg:phone":"+31 23 535 5600",
    "sg:postcode":"2037 SH",
    "sg:province":"Noord-Holland",
    "wof:name":"Beers, Ronald",
    "wof:placetype":"venue"
},
  "geometry": {"coordinates":[4.662571,52.355198],"type":"Point"}
}