{
  "type": "Feature",
  "properties": {
    "addr:full":"De Weid 9 Velserbroek Noord-Holland 1991 ES",
    "addr:housenumber":"9",
    "addr:postcode":"1991 es",
    "addr:street":"De Weid",
    "iso:country":"NL",
    "sg:address":"De Weid 9",
    "sg:city":"Velserbroek",
    "sg:orig_category":"Open Haarden",
    "sg:phone":"+31 23 534 1687",
    "sg:postcode":"1991 ES",
    "sg:province":"Noord-Holland",
    "wof:name":"Deja-Vu",
    "wof:placetype":"venue"
},
  "geometry": {"coordinates":[4.662476,52.437096],"type":"Point"}
}