{
  "type": "Feature",
  "properties": {
    "addr:full":"Leidsevaart 344 Haarlem North Holland 2014 HK",
    "addr:housenumber":"344",
    "addr:postcode":"2014 hk",
    "addr:street":"Leidsevaart",
    "iso:country":"NL",
    "sg:address":"Leidsevaart 344",
    "sg:city":"Haarlem",
    "sg:classifiers":[
        {
            "category":"Manufacturing",
            "subcategory":"Motor Vehicles & Parts",
            "type":"Manufacturing & Wholesale Goods"
        }
    ],
    "sg:phone":"+31 23 524 6207",
    "sg:postcode":"2014 HK",
    "sg:province":"North Holland",
    "sg:tags":[
        "verhuur",
        "scooter",
        "en",
        "-"
    ],
    "sg:website":"http://www.avis.nl",
    "wof:name":"All Rent",
    "wof:placetype":"venue"
},
  "geometry": {"coordinates":[4.617828,52.370983],"type":"Point"}
}