{
  "type": "Feature",
  "properties": {
    "addr:full":"Stouweweg 7 Zwartsluis NL.08 8064 PD",
    "addr:housenumber":"7;nl.08",
    "addr:postcode":"8064 pd",
    "addr:street":"Stouweweg",
    "iso:country":"NL",
    "sg:address":"Stouweweg 7",
    "sg:city":"Zwartsluis",
    "sg:orig_category":"Verbouwingen",
    "sg:phone":"+31 38 386 9752",
    "sg:postcode":"8064 PD",
    "sg:province":"NL.08",
    "wof:name":"Gelder, Van",
    "wof:placetype":"venue"
},
  "geometry": {"coordinates":[6.089895,52.644482],"type":"Point"}
}