{
  "type": "Feature",
  "properties": {
    "addr:full":"Marktveld 3 Nieuw Beijerland Zuid-Holland 3264 AL",
    "addr:housenumber":"3",
    "addr:postcode":"3264 al",
    "addr:street":"Marktveld;Beijerland",
    "iso:country":"NL",
    "sg:address":"Marktveld 3",
    "sg:city":"Nieuw Beijerland",
    "sg:orig_category":"Verlichting And Huishoudartikelen",
    "sg:phone":"+31 186 691 376",
    "sg:postcode":"3264 AL",
    "sg:province":"Zuid-Holland",
    "wof:name":"Gez Nobel",
    "wof:placetype":"venue"
},
  "geometry": {"coordinates":[4.336077,51.812107],"type":"Point"}
}