{
  "type": "Feature",
  "properties": {
    "addr:full":"De Sitterln 18 Leiden Zuid-Holland 2313 TN",
    "addr:housenumber":"18",
    "addr:postcode":"2313",
    "iso:country":"NL",
    "sg:address":"De Sitterln 18",
    "sg:city":"Leiden",
    "sg:orig_category":"Artsen - Huisartsen",
    "sg:phone":"+31 71 513 2877",
    "sg:postcode":"2313 TN",
    "sg:province":"Zuid-Holland",
    "wof:name":"Fogelberg, E K",
    "wof:placetype":"venue"
},
  "geometry": {"coordinates":[4.49463,52.154572],"type":"Point"}
}