{
  "type": "Feature",
  "properties": {
    "iso:country":"NL",
    "sg:address":"Postpad 1",
    "sg:city":"Oosterbeek",
    "sg:orig_category":"Kinderopvang",
    "sg:phone":"+31 26 333 3651",
    "sg:postcode":"6862 CM",
    "sg:province":"Gelderland",
    "wof:name":"Dol-Fijn",
    "wof:placetype":"venue"
},
  "geometry": {"coordinates":[5.840935,51.982265],"type":"Point"}
}