{
  "type": "Feature",
  "properties": {
    "addr:full":"Mastenbroekw 2 Weert Limburg 6006 PT",
    "addr:housenumber":"2",
    "addr:postcode":"6006 pt",
    "addr:street":"Mastenbroekw",
    "iso:country":"NL",
    "sg:address":"Mastenbroekw 2",
    "sg:city":"Weert",
    "sg:orig_category":"Bedrijfsorganisaties",
    "sg:phone":"+31 495 584 990",
    "sg:postcode":"6006 PT",
    "sg:province":"Limburg",
    "sg:website":"http://www.isidorus.nl",
    "wof:name":"Isidorus Bv",
    "wof:placetype":"venue"
},
  "geometry": {"coordinates":[5.689795,51.22662],"type":"Point"}
}