{
  "type": "Feature",
  "properties": {
    "addr:full":"Overhoven 39 Sittard Limburg 6136 EA",
    "addr:housenumber":"39",
    "addr:postcode":"6136 ea",
    "addr:street":"Overhoven",
    "iso:country":"NL",
    "sg:address":"Overhoven 39",
    "sg:city":"Sittard",
    "sg:orig_category":"Drogisterijen",
    "sg:phone":"+31 46 451 0047",
    "sg:postcode":"6136 EA",
    "sg:province":"Limburg",
    "wof:name":"Kurvers-Kremers",
    "wof:placetype":"venue"
},
  "geometry": {"coordinates":[5.867124,51.004593],"type":"Point"}
}