{
  "type": "Feature",
  "properties": {
    "addr:full":"Burg Vd Loostr 1A Berg En Terblyt Limburg 6325 BW",
    "addr:housenumber":"1a",
    "addr:postcode":"6325 bw",
    "addr:street":"Burg;Berg",
    "iso:country":"NL",
    "sg:address":"Burg Vd Loostr 1A",
    "sg:city":"Berg En Terblyt",
    "sg:orig_category":"Banken",
    "sg:phone":"+31 43 604 1879",
    "sg:postcode":"6325 BW",
    "sg:province":"Limburg",
    "wof:name":"Cvb Bank Berg En Terblijt",
    "wof:placetype":"venue"
},
  "geometry": {"coordinates":[5.810365,50.857407],"type":"Point"}
}