{
  "type": "Feature",
  "properties": {
    "addr:full":"Copernicusstr 8A Weert Limburg 6003 DE",
    "addr:housenumber":"8a",
    "addr:postcode":"6003 de",
    "addr:street":"Copernicusstr",
    "iso:country":"NL",
    "sg:address":"Copernicusstr 8A",
    "sg:city":"Weert",
    "sg:orig_category":"Hefwerktuigen",
    "sg:phone":"+31 495 525 504",
    "sg:postcode":"6003 DE",
    "sg:province":"Limburg",
    "sg:website":"http://www.stork.com",
    "wof:name":"Stork Bv",
    "wof:placetype":"venue"
},
  "geometry": {"coordinates":[5.734737,51.273811],"type":"Point"}
}