{
  "type": "Feature",
  "properties": {
    "iso:country":"NL",
    "sg:address":"Communicatiewg 13",
    "sg:city":"Mydrecht",
    "sg:orig_category":"Sanitaire Artikelen",
    "sg:phone":"+31 297 366 066",
    "sg:postcode":"3641 SG",
    "sg:province":"Utrecht",
    "sg:website":"http://www.sanidiscount.com",
    "wof:name":"Sani Discount Bv",
    "wof:placetype":"venue"
},
  "geometry": {"coordinates":[4.882752,52.212521],"type":"Point"}
}