{
  "type": "Feature",
  "properties": {
    "iso:country":"NL",
    "sg:address":"Groenstr 2",
    "sg:city":"Soerendonk",
    "sg:orig_category":"Metaalgroothandel",
    "sg:phone":"+31 495 591 287",
    "sg:postcode":"6027 PW",
    "sg:province":"Noord-Brabant",
    "wof:name":"Verbruggen Vof",
    "wof:placetype":"venue"
},
  "geometry": {"coordinates":[5.572907,51.303722],"type":"Point"}
}