{
  "type": "Feature",
  "properties": {
    "addr:full":"V Galenstr 46 Zaak Den Helder Noord-Holland 1782 EW",
    "addr:housenumber":"46",
    "addr:postcode":"1782 ew",
    "addr:street":"Zaak",
    "iso:country":"NL",
    "sg:address":"V Galenstr 46 Zaak",
    "sg:city":"Den Helder",
    "sg:classifiers":[
        {
            "category":"Farming",
            "subcategory":"Fish & Marine Products",
            "type":"Manufacturing & Wholesale Goods"
        }
    ],
    "sg:phone":"+31 223 612 908",
    "sg:postcode":"1782 EW",
    "sg:province":"Noord-Holland",
    "sg:tags":[
        "vi"
    ],
    "wof:name":"Noordzee",
    "wof:placetype":"venue"
},
  "geometry": {"coordinates":[4.758825,52.958191],"type":"Point"}
}