{
  "type": "Feature",
  "properties": {
    "iso:country":"NL",
    "sg:address":"Holendrechterweg 55",
    "sg:city":"Ouderkerk A/D Amstel",
    "sg:orig_category":"Farmaceutische Producten Gh",
    "sg:phone":"+31 20 496 8377",
    "sg:postcode":"1191 KX",
    "sg:province":"North Holland",
    "wof:name":"Jos Geijsel Sportfit",
    "wof:placetype":"venue"
},
  "geometry": {"coordinates":[4.922208,52.281586],"type":"Point"}
}