{
  "type": "Feature",
  "properties": {
    "iso:country":"NL",
    "sg:address":"Bosuillaan 3",
    "sg:city":"Bilthoven",
    "sg:orig_category":"Boekhouders",
    "sg:phone":"+31 30 228 5986",
    "sg:postcode":"3722 XC",
    "sg:province":"Utrecht",
    "wof:name":"Accountant En Administratie- Consulent G.M. Hehenk",
    "wof:placetype":"venue"
},
  "geometry": {"coordinates":[5.214049,52.130142],"type":"Point"}
}