{
  "type": "Feature",
  "properties": {
    "addr:full":"Kampwg 2 Doorn Utrecht 3941 HH",
    "addr:housenumber":"2",
    "addr:postcode":"3941 hh",
    "addr:street":"Kampwg",
    "iso:country":"NL",
    "sg:address":"Kampwg 2",
    "sg:city":"Doorn",
    "sg:orig_category":"Makelaars En Adviseurs Onroerende Goederen",
    "sg:phone":"+31 343 412 841",
    "sg:postcode":"3941 HH",
    "sg:province":"Utrecht",
    "wof:name":"Vellinga Bv",
    "wof:placetype":"venue"
},
  "geometry": {"coordinates":[5.344287,52.036419],"type":"Point"}
}