{
  "type": "Feature",
  "properties": {
    "iso:country":"NL",
    "sg:address":"Bloemstede 254",
    "sg:city":"Maarssen",
    "sg:orig_category":"Koeriersdiensten",
    "sg:phone":"+31 6 22779695",
    "sg:postcode":"3608 VK",
    "sg:province":"Utrecht",
    "wof:name":"Cvm",
    "wof:placetype":"venue"
},
  "geometry": {"coordinates":[5.034688,52.127682],"type":"Point"}
}