{
  "type": "Feature",
  "properties": {
    "iso:country":"NL",
    "sg:address":"Meester J C Buhrmannlaan 72",
    "sg:city":"Weesp",
    "sg:orig_category":"Beursorganisaties And Standbouw",
    "sg:phone":"+31 294 410 318",
    "sg:postcode":"1381 GN",
    "sg:province":"Noord-Holland",
    "wof:name":"Puchberger Reklame & Display",
    "wof:placetype":"venue"
},
  "geometry": {"coordinates":[5.052326,52.300491],"type":"Point"}
}