{
  "type": "Feature",
  "properties": {
    "iso:country":"NL",
    "sg:address":"Frederikstr 61",
    "sg:city":"Groningen",
    "sg:orig_category":"Cafetaria'S",
    "sg:phone":"+31 50 314 4422",
    "sg:postcode":"9724 KB",
    "sg:province":"Groningen",
    "wof:name":"Meeuw, De",
    "wof:placetype":"venue"
},
  "geometry": {"coordinates":[6.579714,53.210186],"type":"Point"}
}