{
  "type": "Feature",
  "properties": {
    "iso:country":"NL",
    "sg:address":"Nw Keizersgr 494",
    "sg:city":"Amsterdam",
    "sg:orig_category":"Fotografie Reclame En Mode",
    "sg:phone":"+31 20 623 0228",
    "sg:postcode":"1018 VG",
    "sg:province":"North Holland",
    "wof:name":"Meijer, Sibrand",
    "wof:placetype":"venue"
},
  "geometry": {"coordinates":[4.909263,52.365288],"type":"Point"}
}