{
  "type": "Feature",
  "properties": {
    "addr:full":"V Hornstr 1A Boxtel North Brabant 5282 NA",
    "addr:housenumber":"1a",
    "addr:postcode":"5282 na",
    "addr:street":"Hornstr",
    "iso:country":"NL",
    "sg:address":"V Hornstr 1A",
    "sg:city":"Boxtel",
    "sg:orig_category":"Fotoreportages",
    "sg:phone":"+31 411 682 874",
    "sg:postcode":"5282 NA",
    "sg:province":"North Brabant",
    "sg:website":"http://www.studiomystica.nl",
    "wof:name":"Mystica, Studio",
    "wof:placetype":"venue"
},
  "geometry": {"coordinates":[5.322775,51.591595],"type":"Point"}
}