{
  "type": "Feature",
  "properties": {
    "addr:full":"Kalverstraat 151 Amsterdam North Holland 1012 XB",
    "addr:housenumber":"151",
    "addr:postcode":"1012 xb",
    "addr:street":"Kalverstraat",
    "iso:country":"NL",
    "sg:address":"Kalverstraat 151",
    "sg:city":"Amsterdam",
    "sg:orig_category":"Herenmodezaken",
    "sg:phone":"+31 20 623 5665",
    "sg:postcode":"1012 XB",
    "sg:province":"North Holland",
    "wof:name":"Arrow Store",
    "wof:placetype":"venue"
},
  "geometry": {"coordinates":[4.89137,52.368713],"type":"Point"}
}