{
  "type": "Feature",
  "properties": {
    "addr:full":"Leidseweg 193 Utrecht Utrecht 3533 HD",
    "addr:housenumber":"193",
    "addr:postcode":"3533 hd",
    "addr:street":"Leidseweg",
    "iso:country":"NL",
    "sg:address":"Leidseweg 193",
    "sg:city":"Utrecht",
    "sg:orig_category":"Boekhouders",
    "sg:phone":"+31 30 293 3039",
    "sg:postcode":"3533 HD",
    "sg:province":"Utrecht",
    "wof:name":"M Jongerius",
    "wof:placetype":"venue"
},
  "geometry": {"coordinates":[5.089829,52.082779],"type":"Point"}
}