{
  "type": "Feature",
  "properties": {
    "iso:country":"NL",
    "sg:address":"Schiedamsewg 12A",
    "sg:city":"Rotterdam",
    "sg:orig_category":"Beeldende Kunstenaars",
    "sg:phone":"+31 6 24997264",
    "sg:postcode":"3025 AA",
    "sg:province":"Zuid-Holland",
    "wof:name":"Luijk, Nadia Van",
    "wof:placetype":"venue"
},
  "geometry": {"coordinates":[4.447649,51.909676],"type":"Point"}
}