{
  "type": "Feature",
  "properties": {
    "addr:full":"De Wylch 7 Bergum Friesland 9251 PB",
    "addr:housenumber":"7",
    "addr:postcode":"9251 pb",
    "addr:street":"De Wylch",
    "iso:country":"NL",
    "sg:address":"De Wylch 7",
    "sg:city":"Bergum",
    "sg:orig_category":"Adviesbureaus",
    "sg:phone":"+31 511 465 433",
    "sg:postcode":"9251 PB",
    "sg:province":"Friesland",
    "wof:name":"Ista Trade",
    "wof:placetype":"venue"
},
  "geometry": {"coordinates":[6.004194,53.189789],"type":"Point"}
}