{
  "type": "Feature",
  "properties": {
    "addr:full":"Rechter Rottekd 349 Rotterdam Zuid-Holland 3032 XG",
    "addr:housenumber":"349",
    "addr:postcode":"3032 xg",
    "iso:country":"NL",
    "sg:address":"Rechter Rottekd 349",
    "sg:city":"Rotterdam",
    "sg:orig_category":"Psychotherapeuten",
    "sg:phone":"+31 10 465 4159",
    "sg:postcode":"3032 XG",
    "sg:province":"Zuid-Holland",
    "wof:name":"Corbeth",
    "wof:placetype":"venue"
},
  "geometry": {"coordinates":[4.483982,51.927483],"type":"Point"}
}