{
  "type": "Feature",
  "properties": {
    "addr:full":"Eindhovenseweg 13 Valkenswaard Noord-Brabant 5554 AA",
    "addr:housenumber":"13",
    "addr:postcode":"5554 aa",
    "addr:street":"Eindhovenseweg",
    "iso:country":"NL",
    "sg:address":"Eindhovenseweg 13",
    "sg:city":"Valkenswaard",
    "sg:classifiers":[
        {
            "category":"Shopping",
            "subcategory":"Clothing, Apparel, & Fashions",
            "type":"Retail Goods"
        }
    ],
    "sg:phone":"+31 40 201 5502",
    "sg:postcode":"5554 AA",
    "sg:province":"Noord-Brabant",
    "sg:tags":[
        "ondergoed",
        "lingerie"
    ],
    "wof:name":"Livera Van Gennip",
    "wof:placetype":"venue"
},
  "geometry": {"coordinates":[5.459213,51.351646],"type":"Point"}
}