{
  "type": "Feature",
  "properties": {
    "addr:full":"Dracht 17 Heerenveen Provincie Friesland 8442 BJ",
    "addr:housenumber":"17",
    "addr:postcode":"8442 bj",
    "addr:street":"Dracht;Provincie Friesland",
    "iso:country":"NL",
    "sg:address":"Dracht 17",
    "sg:city":"Heerenveen",
    "sg:classifiers":[
        {
            "category":"Shopping",
            "subcategory":"Adult",
            "type":"Retail Goods"
        }
    ],
    "sg:phone":"+31 513 622 595",
    "sg:postcode":"8442 BJ",
    "sg:province":"Provincie Friesland",
    "sg:tags":[
        "lingerie",
        "en",
        "tricotage"
    ],
    "wof:name":"Monsma",
    "wof:placetype":"venue"
},
  "geometry": {"coordinates":[5.924501,52.958813],"type":"Point"}
}