{
  "type": "Feature",
  "properties": {
    "addr:full":"Leegstraat 16 Winssen Gelderland 6645 BC",
    "addr:housenumber":"16",
    "addr:postcode":"6645 bc",
    "addr:street":"Leegstraat;Gelderland",
    "iso:country":"NL",
    "sg:address":"Leegstraat 16",
    "sg:city":"Winssen",
    "sg:orig_category":"Diverse Consumentenartikelen Gh",
    "sg:phone":"+31 487 523 343",
    "sg:postcode":"6645 BC",
    "sg:province":"Gelderland",
    "wof:name":"Emipol Trading Inc.",
    "wof:placetype":"venue"
},
  "geometry": {"coordinates":[5.700791,51.875343],"type":"Point"}
}