{
  "type": "Feature",
  "properties": {
    "addr:full":"Raadhuisstraat 102 Hoogerheide Noord-Brabant 4631 NJ",
    "addr:housenumber":"102",
    "addr:postcode":"4631 nj",
    "addr:street":"Raadhuisstraat",
    "iso:country":"NL",
    "sg:address":"Raadhuisstraat 102",
    "sg:city":"Hoogerheide",
    "sg:orig_category":"Herenmodezaken",
    "sg:phone":"+31 164 620 308",
    "sg:postcode":"4631 NJ",
    "sg:province":"Noord-Brabant",
    "wof:name":"Henri'S Men Shop",
    "wof:placetype":"venue"
},
  "geometry": {"coordinates":[4.323194,51.424553],"type":"Point"}
}