{
  "type": "Feature",
  "properties": {
    "addr:full":"Burg Dryberwg 12 Hardegaryp Friesland 9254 BJ",
    "addr:housenumber":"12",
    "addr:postcode":"9254 bj",
    "addr:street":"Burg;Hardegaryp Friesland",
    "iso:country":"NL",
    "sg:address":"Burg Dryberwg 12",
    "sg:city":"Hardegaryp",
    "sg:orig_category":"Bloemen En Planten",
    "sg:phone":"+31 511 474 335",
    "sg:postcode":"9254 BJ",
    "sg:province":"Friesland",
    "wof:name":"Frans",
    "wof:placetype":"venue"
},
  "geometry": {"coordinates":[5.94131,53.215366],"type":"Point"}
}