{
  "type": "Feature",
  "properties": {
    "iso:country":"NL",
    "sg:address":"Rector Heuvelsstraat 4",
    "sg:city":"Helmond",
    "sg:classifiers":[
        {
            "category":"Education",
            "subcategory":"Preschool",
            "type":"Public Place"
        }
    ],
    "sg:phone":"+31 492 511 604",
    "sg:postcode":"5704 AN",
    "sg:province":"Noord-Brabant",
    "sg:tags":[
        "kleuteronderwijs",
        "basis-"
    ],
    "wof:name":"Basisschool De Korenaar",
    "wof:placetype":"venue"
},
  "geometry": {"coordinates":[5.69885,51.46035],"type":"Point"}
}