{
  "type": "Feature",
  "properties": {
    "addr:full":"Emmaln 2 Etten Leur Noord-Brabant 4872 CA",
    "addr:housenumber":"2",
    "addr:postcode":"4872 ca",
    "addr:street":"Emmaln",
    "iso:country":"NL",
    "sg:address":"Emmaln 2",
    "sg:city":"Etten Leur",
    "sg:classifiers":[
        {
            "category":"Real Estate",
            "subcategory":"Real Estate Operator",
            "type":"Services"
        }
    ],
    "sg:phone":"+31 76 503 4888",
    "sg:postcode":"4872 CA",
    "sg:province":"Noord-Brabant",
    "sg:tags":[
        "appartementen",
        "en",
        "flat"
    ],
    "wof:name":"Vitalis",
    "wof:placetype":"venue"
},
  "geometry": {"coordinates":[4.649096,51.577057],"type":"Point"}
}