{
  "type": "Feature",
  "properties": {
    "addr:full":"Dasseburcht 21 Zeewolde Flevoland 3892 WB",
    "addr:housenumber":"21",
    "addr:postcode":"3892 wb",
    "addr:street":"Dasseburcht;Flevoland",
    "iso:country":"NL",
    "sg:address":"Dasseburcht 21",
    "sg:city":"Zeewolde",
    "sg:orig_category":"Afslankinstituten",
    "sg:phone":"+31 36 522 1158",
    "sg:postcode":"3892 WB",
    "sg:province":"Flevoland",
    "wof:name":"Healthy Business",
    "wof:placetype":"venue"
},
  "geometry": {"coordinates":[5.535267,52.321804],"type":"Point"}
}