{
  "type": "Feature",
  "properties": {
    "addr:full":"Joannaplnts 1 Goes Ohio 4462 AV",
    "addr:housenumber":"1",
    "addr:postcode":"4462 av",
    "addr:street":"Joannaplnts",
    "iso:country":"NL",
    "sg:address":"Joannaplnts 1",
    "sg:city":"Goes",
    "sg:orig_category":"Bejaarden - Verzorgingstehuizen",
    "sg:phone":"+31 113 216 878",
    "sg:postcode":"4462 AV",
    "sg:province":"Ohio",
    "sg:website":"http://www.terweel.nl",
    "wof:name":"Weel, Stichting Ter",
    "wof:placetype":"venue"
},
  "geometry": {"coordinates":[-83.914169,39.768833],"type":"Point"}
}