{
  "type": "Feature",
  "properties": {
    "iso:country":"NL",
    "sg:address":"Kerkln 85",
    "sg:city":"Ryswyk Zh",
    "sg:orig_category":"Verzekeringen - Verzekeringskantoren",
    "sg:phone":"+31 70 390 9782",
    "sg:postcode":"2282 CG",
    "sg:province":"South Holland",
    "sg:website":"http://www.roben.nl",
    "wof:name":"Roben",
    "wof:placetype":"venue"
},
  "geometry": {"coordinates":[4.33694,52.056503],"type":"Point"}
}