{
  "type": "Feature",
  "properties": {
    "addr:full":"Blokland 118 Montfoort Utrecht 3417 MR",
    "addr:housenumber":"118",
    "addr:postcode":"3417 mr",
    "addr:street":"Blokland",
    "iso:country":"NL",
    "sg:address":"Blokland 118",
    "sg:city":"Montfoort",
    "sg:classifiers":[
        {
            "category":"Food & Beverages",
            "subcategory":"Candy",
            "type":"Retail Goods"
        }
    ],
    "sg:phone":"+31 348 472 016",
    "sg:postcode":"3417 MR",
    "sg:province":"Utrecht",
    "sg:tags":[
        "sport-",
        "en",
        "spelartikelen"
    ],
    "wof:name":"Verkaik Ltd, E",
    "wof:placetype":"venue"
},
  "geometry": {"coordinates":[4.943329,52.02121],"type":"Point"}
}