{
  "type": "Feature",
  "properties": {
    "addr:full":"Vonderstr 3 Someren Noord-Brabant 5712 NK",
    "addr:housenumber":"3",
    "addr:postcode":"5712 nk",
    "addr:street":"Vonderstr",
    "iso:country":"NL",
    "sg:address":"Vonderstr 3",
    "sg:city":"Someren",
    "sg:orig_category":"Zonne-Energie",
    "sg:phone":"+31 493 496 788",
    "sg:postcode":"5712 NK",
    "sg:province":"Noord-Brabant",
    "sg:website":"http://www.nuropa.nl",
    "wof:name":"Nuropa",
    "wof:placetype":"venue"
},
  "geometry": {"coordinates":[5.730251,51.359165],"type":"Point"}
}