{
  "type": "Feature",
  "properties": {
    "iso:country":"NL",
    "sg:address":"Grotestr 25",
    "sg:city":"Tubbergen",
    "sg:orig_category":"Opticiens",
    "sg:phone":"+31 546 622 873",
    "sg:postcode":"7651 CG",
    "sg:province":"Overijssel",
    "wof:name":"Haasewinkel",
    "wof:placetype":"venue"
},
  "geometry": {"coordinates":[6.7818012238,52.4058265686],"type":"Point"}
}