{
  "type": "Feature",
  "properties": {
    "addr:full":"Roselaarplein 30 Roosendaal North Brabant 4701 BR",
    "addr:housenumber":"30",
    "addr:postcode":"4701 br",
    "addr:street":"Roselaarplein",
    "iso:country":"NL",
    "sg:address":"Roselaarplein 30",
    "sg:city":"Roosendaal",
    "sg:classifiers":[
        {
            "category":"Fast Food",
            "type":"Food & Drink"
        }
    ],
    "sg:phone":"+31 165 558 814",
    "sg:postcode":"4701 BR",
    "sg:province":"North Brabant",
    "sg:tags":[
        "afhaal",
        "restaurant"
    ],
    "wof:name":"Snack Express",
    "wof:placetype":"venue"
},
  "geometry": {"coordinates":[4.453396,51.531506],"type":"Point"}
}