{
  "type": "Feature",
  "properties": {
    "addr:full":"Haven 33 Schoonhoven South Holland 2871 CK",
    "addr:housenumber":"33",
    "addr:postcode":"2871 ck",
    "addr:street":"Haven",
    "iso:country":"NL",
    "sg:address":"Haven 33",
    "sg:city":"Schoonhoven",
    "sg:orig_category":"Orthopedische Artikelen",
    "sg:phone":"+31 182 382 405",
    "sg:postcode":"2871 CK",
    "sg:province":"South Holland",
    "wof:name":"T?Th-Elsenaar, N",
    "wof:placetype":"venue"
},
  "geometry": {"coordinates":[4.8520479202,51.9450874329],"type":"Point"}
}