{
  "type": "Feature",
  "properties": {
    "addr:full":"Brouwersdk 83 Dordrecht Zuid-Holland 3314 GH",
    "addr:housenumber":"83",
    "addr:postcode":"3314 gh",
    "addr:street":"Brouwersdk",
    "iso:country":"NL",
    "sg:address":"Brouwersdk 83",
    "sg:city":"Dordrecht",
    "sg:orig_category":"Psychologen",
    "sg:phone":"+31 78 631 4746",
    "sg:postcode":"3314 GH",
    "sg:province":"Zuid-Holland",
    "wof:name":"Veen Stakelbeek, Drs M A",
    "wof:placetype":"venue"
},
  "geometry": {"coordinates":[4.657344,51.803352],"type":"Point"}
}