{
  "type": "Feature",
  "properties": {
    "addr:full":"Kreeftstr 42 Rotterdam South Holland 3067 JV",
    "addr:housenumber":"42",
    "addr:postcode":"3067 jv",
    "addr:street":"Kreeftstr",
    "iso:country":"NL",
    "sg:address":"Kreeftstr 42",
    "sg:city":"Rotterdam",
    "sg:orig_category":"Drogisterijen",
    "sg:phone":"+31 10 421 3530",
    "sg:postcode":"3067 JV",
    "sg:province":"South Holland",
    "wof:name":"Farma Bv",
    "wof:placetype":"venue"
},
  "geometry": {"coordinates":[4.554896,51.946594],"type":"Point"}
}