{
  "type": "Feature",
  "properties": {
    "addr:full":"Nic Barnhoornweg 12 Noordwijk Zh Zuid-Holland 2202 JB",
    "addr:housenumber":"12",
    "addr:postcode":"2202 jb",
    "iso:country":"NL",
    "sg:address":"Nic Barnhoornweg 12",
    "sg:city":"Noordwijk Zh",
    "sg:orig_category":"Kappers",
    "sg:phone":"+31 71 361 4642",
    "sg:postcode":"2202 JB",
    "sg:province":"Zuid-Holland",
    "wof:name":"Kapsalon Nuance Coiffures",
    "wof:placetype":"venue"
},
  "geometry": {"coordinates":[4.4325900078,52.2447776794],"type":"Point"}
}