{
  "type": "Feature",
  "properties": {
    "addr:full":"Bussumerstr 60 Hilversum Noord-Holland 1211 BL",
    "addr:housenumber":"60",
    "addr:postcode":"1211 bl",
    "addr:street":"Bussumerstr",
    "iso:country":"NL",
    "sg:address":"Bussumerstr 60",
    "sg:city":"Hilversum",
    "sg:orig_category":"Verenigingen En Stichtingen",
    "sg:phone":"+31 35 628 4984",
    "sg:postcode":"1211 BL",
    "sg:province":"Noord-Holland",
    "wof:name":"Ics",
    "wof:placetype":"venue"
},
  "geometry": {"coordinates":[5.173447,52.225529],"type":"Point"}
}