{
  "type": "Feature",
  "properties": {
    "addr:full":"T Noord 6 Tzum Friesland 8804 NC",
    "addr:housenumber":"6",
    "addr:postcode":"8804 nc",
    "addr:street":"T Noord",
    "iso:country":"NL",
    "sg:address":"T Noord 6",
    "sg:city":"Tzum",
    "sg:orig_category":"Levende Dieren Gh",
    "sg:phone":"+31 517 452 386",
    "sg:postcode":"8804 NC",
    "sg:province":"Friesland",
    "wof:name":"D. Palma",
    "wof:placetype":"venue"
},
  "geometry": {"coordinates":[5.567209,53.162922],"type":"Point"}
}