{
  "type": "Feature",
  "properties": {
    "addr:full":"Veewg 5 Schinnen Limburg 6365 CV",
    "addr:housenumber":"5",
    "addr:postcode":"6365 cv",
    "addr:street":"Veewg",
    "iso:country":"NL",
    "sg:address":"Veewg 5",
    "sg:city":"Schinnen",
    "sg:orig_category":"Onderhoudswerken",
    "sg:phone":"+31 46 443 2141",
    "sg:postcode":"6365 CV",
    "sg:province":"Limburg",
    "wof:name":"Goessens Bv",
    "wof:placetype":"venue"
},
  "geometry": {"coordinates":[5.875037,50.940445],"type":"Point"}
}