{
  "type": "Feature",
  "properties": {
    "addr:full":"Bredestraat 13 Rotterdam Zuid-Holland 3011 RB",
    "addr:housenumber":"13",
    "addr:postcode":"3011 rb",
    "addr:street":"Bredestraat",
    "iso:country":"NL",
    "sg:address":"Bredestraat 13",
    "sg:city":"Rotterdam",
    "sg:orig_category":"Overheidsdiensten",
    "sg:phone":"+31 10 414 0733",
    "sg:postcode":"3011 RB",
    "sg:province":"Zuid-Holland",
    "wof:name":"Stadsdriehoek Wijkorgaan",
    "wof:placetype":"venue"
},
  "geometry": {"coordinates":[4.4909567833,51.923576355],"type":"Point"}
}