{
  "type": "Feature",
  "properties": {
    "iso:country":"NL",
    "sg:address":"Molenbeekstr 22",
    "sg:city":"Roosendaal",
    "sg:orig_category":"Video - Faciliteiten En Producties",
    "sg:phone":"+31 165 559 375",
    "sg:postcode":"4703 BG",
    "sg:province":"Noord-Brabant",
    "wof:name":"Holland Screen Vof",
    "wof:placetype":"venue"
},
  "geometry": {"coordinates":[4.448274,51.530979],"type":"Point"}
}