{
  "type": "Feature",
  "properties": {
    "addr:full":"Goudenregenstraat 2 Woerden Utrecht 3442 HG",
    "addr:housenumber":"2",
    "addr:postcode":"3442 hg",
    "addr:street":"Goudenregenstraat",
    "iso:country":"NL",
    "sg:address":"Goudenregenstraat 2",
    "sg:city":"Woerden",
    "sg:classifiers":[
        {
            "category":"Education",
            "subcategory":"Preschool",
            "type":"Public Place"
        }
    ],
    "sg:phone":"+31 348 416 079",
    "sg:postcode":"3442 HG",
    "sg:province":"Utrecht",
    "sg:tags":[
        "kleuteronderwijs",
        "basis-"
    ],
    "wof:name":"Christelijke Basisschool Willem Van Oranje",
    "wof:placetype":"venue"
},
  "geometry": {"coordinates":[4.874183,52.083878],"type":"Point"}
}