{
  "type": "Feature",
  "properties": {
    "addr:full":"Beukenln 10 Garderen Gelderland 3886 AE",
    "addr:housenumber":"10",
    "addr:postcode":"3886 ae",
    "addr:street":"Beukenln;Gelderland",
    "iso:country":"NL",
    "sg:address":"Beukenln 10",
    "sg:city":"Garderen",
    "sg:orig_category":"Schilders",
    "sg:phone":"+31 577 462 790",
    "sg:postcode":"3886 AE",
    "sg:province":"Gelderland",
    "wof:name":"Beek, A Van",
    "wof:placetype":"venue"
},
  "geometry": {"coordinates":[5.713984,52.229527],"type":"Point"}
}