{
  "type": "Feature",
  "properties": {
    "iso:country":"NL",
    "sg:address":"Westhavenkade 29",
    "sg:city":"Vlaardingen",
    "sg:orig_category":"Diverse Bedrijfsinstallaties Gh",
    "sg:phone":"+31 10 434 7276",
    "sg:postcode":"3131 AD",
    "sg:province":"Zuid-Holland",
    "wof:name":"Handelsonderneming Faas",
    "wof:placetype":"venue"
},
  "geometry": {"coordinates":[4.34455,51.907242],"type":"Point"}
}