{
  "type": "Feature",
  "properties": {
    "iso:country":"NL",
    "sg:address":"Haarlemmerstraat 63",
    "sg:city":"Leiden",
    "sg:orig_category":"Opticiens",
    "sg:phone":"+31 71 514 5121",
    "sg:postcode":"2312 DL",
    "sg:province":"South Holland",
    "wof:name":"Hans Anders Opticiens",
    "wof:placetype":"venue"
},
  "geometry": {"coordinates":[4.4880709648,52.1608963013],"type":"Point"}
}