{
  "type": "Feature",
  "properties": {
    "addr:full":"Dorpsstr 57 Kloosterhaar NL.08 7694 AB",
    "addr:housenumber":"57;nl.08",
    "addr:postcode":"7694 ab",
    "addr:street":"Dorpsstr",
    "iso:country":"NL",
    "sg:address":"Dorpsstr 57",
    "sg:city":"Kloosterhaar",
    "sg:orig_category":"Keukens",
    "sg:phone":"+31 523 242 134",
    "sg:postcode":"7694 AB",
    "sg:province":"NL.08",
    "wof:name":"Olthoff, Klaas",
    "wof:placetype":"venue"
},
  "geometry": {"coordinates":[6.676352,52.497421],"type":"Point"}
}