{
  "type": "Feature",
  "properties": {
    "addr:full":"Ln V Chartroise 174 Utrecht Utrecht 3552 EZ",
    "addr:housenumber":"174",
    "addr:postcode":"3552 ez",
    "addr:street":"Ln;Chartroise",
    "iso:country":"NL",
    "sg:address":"Ln V Chartroise 174",
    "sg:city":"Utrecht",
    "sg:orig_category":"Galeries",
    "sg:phone":"+31 30 244 0840",
    "sg:postcode":"3552 EZ",
    "sg:province":"Utrecht",
    "wof:name":"Pavlovsky",
    "wof:placetype":"venue"
},
  "geometry": {"coordinates":[5.09806,52.108589],"type":"Point"}
}