{
  "type": "Feature",
  "properties": {
    "addr:full":"Boterdiep Wz 6 Bedum Groningen 9781 EH",
    "addr:housenumber":"6",
    "addr:postcode":"9781 eh",
    "addr:street":"Boterdiep Wz",
    "iso:country":"NL",
    "sg:address":"Boterdiep Wz 6",
    "sg:city":"Bedum",
    "sg:orig_category":"Boekenuitgeverijen",
    "sg:phone":"+31 50 301 3515",
    "sg:postcode":"9781 EH",
    "sg:province":"Groningen",
    "wof:name":"Mp Media Bv",
    "wof:placetype":"venue"
},
  "geometry": {"coordinates":[6.6007008553,53.3018989563],"type":"Point"}
}