{
  "type": "Feature",
  "properties": {
    "iso:country":"NL",
    "sg:address":"Prof Elemastr 24",
    "sg:city":"Emmen",
    "sg:orig_category":"Autorijscholen",
    "sg:phone":"+31 591 649 105",
    "sg:postcode":"7815 EM",
    "sg:province":"Drenthe",
    "wof:name":"Hondsrug, De",
    "wof:placetype":"venue"
},
  "geometry": {"coordinates":[6.893443,52.80143],"type":"Point"}
}