{
  "type": "Feature",
  "properties": {
    "addr:full":"Singelstraat 16 Leeuwarden Provincie Friesland 8917 BK",
    "addr:housenumber":"16",
    "addr:postcode":"8917 bk",
    "addr:street":"Singelstraat;Provincie Friesland",
    "iso:country":"NL",
    "sg:address":"Singelstraat 16",
    "sg:city":"Leeuwarden",
    "sg:orig_category":"Metaalbekleding And -Behandeling",
    "sg:phone":"+31 58 212 2975",
    "sg:postcode":"8917 BK",
    "sg:province":"Provincie Friesland",
    "wof:name":"Slijpinrichting De Eestroom",
    "wof:placetype":"venue"
},
  "geometry": {"coordinates":[5.793365,53.206734],"type":"Point"}
}