{
  "type": "Feature",
  "properties": {
    "addr:full":"Ten Katestraat 63 Haarlem Noord-Holland 2032 ZN",
    "addr:housenumber":"63",
    "addr:postcode":"2032 zn",
    "addr:street":"Ten Katestraat",
    "iso:country":"NL",
    "sg:address":"Ten Katestraat 63",
    "sg:city":"Haarlem",
    "sg:orig_category":"Loodgieterswerk, Verwarming And Sanitaire Installaties",
    "sg:phone":"+31 23 540 4370",
    "sg:postcode":"2032 ZN",
    "sg:province":"Noord-Holland",
    "wof:name":"F. Olyhoek",
    "wof:placetype":"venue"
},
  "geometry": {"coordinates":[4.656826,52.376667],"type":"Point"}
}