{
  "type": "Feature",
  "properties": {
    "addr:full":"Stationsstr 19 Appingedam Groningen 9901 BL",
    "addr:housenumber":"19",
    "addr:postcode":"9901 bl",
    "addr:street":"Stationsstr",
    "iso:country":"NL",
    "sg:address":"Stationsstr 19",
    "sg:city":"Appingedam",
    "sg:orig_category":"Kappers",
    "sg:phone":"+31 596 622 482",
    "sg:postcode":"9901 BL",
    "sg:province":"Groningen",
    "wof:name":"Hoff",
    "wof:placetype":"venue"
},
  "geometry": {"coordinates":[6.8591160774,53.3225288391],"type":"Point"}
}