{
  "type": "Feature",
  "properties": {
    "iso:country":"NL",
    "sg:address":"Industriewg 2",
    "sg:city":"Deventer",
    "sg:orig_category":"Architecten En Architectenbureaus",
    "sg:phone":"+31 570 634 649",
    "sg:postcode":"7418 CE",
    "sg:province":"Overijssel",
    "sg:website":"http://www.abog.nl",
    "wof:name":"Abog Bv",
    "wof:placetype":"venue"
},
  "geometry": {"coordinates":[6.169358,52.249855],"type":"Point"}
}