{
  "type": "Feature",
  "properties": {
    "addr:full":"G Doustr 124 Zutphen Gelderland 7204 EX",
    "addr:housenumber":"124",
    "addr:postcode":"7204 ex",
    "addr:street":"Gelderland",
    "iso:country":"NL",
    "sg:address":"G Doustr 124",
    "sg:city":"Zutphen",
    "sg:orig_category":"Boeken En Tijdschriften",
    "sg:phone":"+31 575 511 973",
    "sg:postcode":"7204 EX",
    "sg:province":"Gelderland",
    "wof:name":"Ijssel, De",
    "wof:placetype":"venue"
},
  "geometry": {"coordinates":[6.215271,52.13728],"type":"Point"}
}