{
  "type": "Feature",
  "properties": {
    "addr:full":"Ellertsveld 11 Lelystad Flevoland 8245 CD",
    "addr:housenumber":"11",
    "addr:postcode":"8245 cd",
    "addr:street":"Ellertsveld;Flevoland",
    "iso:country":"NL",
    "sg:address":"Ellertsveld 11",
    "sg:city":"Lelystad",
    "sg:orig_category":"Administratie- En Boekhoudkantoren",
    "sg:phone":"+31 320 218 046",
    "sg:postcode":"8245 CD",
    "sg:province":"Flevoland",
    "wof:name":"Boekhouderij, De",
    "wof:placetype":"venue"
},
  "geometry": {"coordinates":[5.464111,52.496494],"type":"Point"}
}