{
  "type": "Feature",
  "properties": {
    "addr:full":"Boonkamp 19 Ammerzoden Gelderland 5324 EZ",
    "addr:housenumber":"19",
    "addr:postcode":"5324 ez",
    "addr:street":"Boonkamp;Gelderland",
    "iso:country":"NL",
    "sg:address":"Boonkamp 19",
    "sg:city":"Ammerzoden",
    "sg:orig_category":"Fruit And Groenten Gh",
    "sg:phone":"+31 73 599 1446",
    "sg:postcode":"5324 EZ",
    "sg:province":"Gelderland",
    "wof:name":"M.A.M. Fraaye",
    "wof:placetype":"venue"
},
  "geometry": {"coordinates":[5.214257,51.749786],"type":"Point"}
}