{
  "type": "Feature",
  "properties": {
    "iso:country":"NL",
    "sg:address":"W Vd Zaanstr 1",
    "sg:city":"Hellevoetsluis",
    "sg:orig_category":"Administratie- En Boekhoudkantoren",
    "sg:phone":"+31 181 320 345",
    "sg:postcode":"3223 SN",
    "sg:province":"Zuid-Holland",
    "wof:name":"Compdata",
    "wof:placetype":"venue"
},
  "geometry": {"coordinates":[4.145761,51.839539],"type":"Point"}
}