{
  "type": "Feature",
  "properties": {
    "addr:full":"Hoefwg 31 Bleiswyk South Holland 2665 CB",
    "addr:housenumber":"31",
    "addr:postcode":"2665 cb",
    "addr:street":"Hoefwg",
    "iso:country":"NL",
    "sg:address":"Hoefwg 31",
    "sg:city":"Bleiswyk",
    "sg:orig_category":"Binnenhuisarchitectuur",
    "sg:phone":"+31 10 521 6188",
    "sg:postcode":"2665 CB",
    "sg:province":"South Holland",
    "wof:name":"Biemond",
    "wof:placetype":"venue"
},
  "geometry": {"coordinates":[4.53205,52.014267],"type":"Point"}
}