{
  "type": "Feature",
  "properties": {
    "iso:country":"NL",
    "sg:address":"Broekpolderln 17",
    "sg:city":"Honselersdyk",
    "sg:orig_category":"Loonbedrijven",
    "sg:phone":"+31 174 626 593",
    "sg:postcode":"2675 LJ",
    "sg:province":"South Holland",
    "wof:name":"Boekestijn, P",
    "wof:placetype":"venue"
},
  "geometry": {"coordinates":[4.238759,51.993603],"type":"Point"}
}