{
  "type": "Feature",
  "properties": {
    "addr:full":"Repelstraat 1 Nieuw Vennep North Holland 2151 BN",
    "addr:housenumber":"1",
    "addr:postcode":"2151 bn",
    "addr:street":"Repelstraat;Nieuw Vennep North",
    "iso:country":"NL",
    "sg:address":"Repelstraat 1",
    "sg:city":"Nieuw Vennep",
    "sg:classifiers":[
        {
            "category":"Professional",
            "subcategory":"Accounting & Tax Preparation",
            "type":"Services"
        }
    ],
    "sg:phone":"+31 252 673 033",
    "sg:postcode":"2151 BN",
    "sg:province":"North Holland",
    "sg:tags":[
        "accountant"
    ],
    "wof:name":"P.A. Van Der Linden Bv",
    "wof:placetype":"venue"
},
  "geometry": {"coordinates":[4.624529,52.268208],"type":"Point"}
}