{
  "type": "Feature",
  "properties": {
    "addr:full":"Waterstraat 74-78 Delfzijl Groningen 9934 AX",
    "addr:housenumber":"74-78",
    "addr:postcode":"9934 ax",
    "addr:street":"Waterstraat",
    "iso:country":"NL",
    "sg:address":"Waterstraat 74-78",
    "sg:city":"Delfzijl",
    "sg:classifiers":[
        {
            "category":"Travel",
            "subcategory":"Hotels & Motels",
            "type":"Entertainment"
        }
    ],
    "sg:phone":"+31 596 618 771",
    "sg:postcode":"9934 AX",
    "sg:province":"Groningen",
    "wof:name":"Hotel Du Bastion",
    "wof:placetype":"venue"
},
  "geometry": {"coordinates":[6.925131,53.333134],"type":"Point"}
}