{
  "type": "Feature",
  "properties": {
    "addr:full":"Kerkstraat 88 Ulft Gelderland 7071 WZ",
    "addr:housenumber":"88",
    "addr:postcode":"7071 wz",
    "addr:street":"Kerkstraat;Gelderland",
    "iso:country":"NL",
    "sg:address":"Kerkstraat 88",
    "sg:city":"Ulft",
    "sg:orig_category":"Discountwinkels",
    "sg:phone":"+31 315 640 461",
    "sg:postcode":"7071 WZ",
    "sg:province":"Gelderland",
    "wof:name":"Ter Stal Textiel Bv",
    "wof:placetype":"venue"
},
  "geometry": {"coordinates":[6.383311,51.890934],"type":"Point"}
}