{
  "type": "Feature",
  "properties": {
    "addr:full":"Folkingestraat 47 Groningen Groningen 9711 JV",
    "addr:housenumber":"47",
    "addr:postcode":"9711 jv",
    "addr:street":"Folkingestraat",
    "iso:country":"NL",
    "sg:address":"Folkingestraat 47",
    "sg:city":"Groningen",
    "sg:classifiers":[
        {
            "category":"Shopping",
            "subcategory":"Gifts & Souvenirs",
            "type":"Retail Goods"
        }
    ],
    "sg:phone":"+31 50 589 2951",
    "sg:postcode":"9711 JV",
    "sg:province":"Groningen",
    "sg:tags":[
        "geschenken"
    ],
    "wof:name":"La Lanza",
    "wof:placetype":"venue"
},
  "geometry": {"coordinates":[6.564745,53.215309],"type":"Point"}
}