{
  "type": "Feature",
  "properties": {
    "addr:full":"Baarleseweg 38 Alphen Nb Noord-Brabant 5131 BC",
    "addr:housenumber":"38",
    "addr:postcode":"5131 bc",
    "addr:street":"Baarleseweg",
    "iso:country":"NL",
    "sg:address":"Baarleseweg 38",
    "sg:city":"Alphen Nb",
    "sg:orig_category":"Boekhouders",
    "sg:phone":"+31 13 508 1947",
    "sg:postcode":"5131 BC",
    "sg:province":"Noord-Brabant",
    "wof:name":"Administratiekantoor M. Veroude",
    "wof:placetype":"venue"
},
  "geometry": {"coordinates":[4.952483,51.474579],"type":"Point"}
}