{
  "type": "Feature",
  "properties": {
    "addr:full":"Anthonetta Kuijlstraat 122 Rotterdam Centrum South Holland 3066 GS",
    "addr:housenumber":"122",
    "addr:postcode":"3066 gs",
    "addr:street":"Anthonetta Kuijlstraat",
    "iso:country":"NL",
    "sg:address":"Anthonetta Kuijlstraat 122",
    "sg:city":"Rotterdam Centrum",
    "sg:orig_category":"Autokeuringen",
    "sg:phone":"+31 10 220 5080",
    "sg:postcode":"3066 GS",
    "sg:province":"South Holland",
    "wof:name":"Adkol",
    "wof:placetype":"venue"
},
  "geometry": {"coordinates":[4.540823,51.929588],"type":"Point"}
}