{
  "type": "Feature",
  "properties": {
    "iso:country":"NL",
    "sg:address":"Dorpstr 38",
    "sg:city":"Heumen",
    "sg:orig_category":"Peuterspeelzalen",
    "sg:phone":"+31 24 358 6448",
    "sg:postcode":"6582 AN",
    "sg:province":"Gelderland",
    "wof:name":"Drie Turfjes Hoog",
    "wof:placetype":"venue"
},
  "geometry": {"coordinates":[5.842125,51.764256],"type":"Point"}
}