{
  "type": "Feature",
  "properties": {
    "iso:country":"NL",
    "sg:address":"Heeghstr 74",
    "sg:city":"Didam",
    "sg:classifiers":[
        {
            "category":"Home & Garden",
            "subcategory":"Hardware",
            "type":"Retail Goods"
        }
    ],
    "sg:phone":"+31 316 224 540",
    "sg:postcode":"6942 PG",
    "sg:province":"Gelderland",
    "sg:tags":[
        "machine",
        "-",
        "metaalbewerking"
    ],
    "wof:name":"Machimpex Bv",
    "wof:placetype":"venue"
},
  "geometry": {"coordinates":[6.152763,51.94138],"type":"Point"}
}