{
  "type": "Feature",
  "properties": {
    "addr:full":"Boeijerstraat 18 Bruinisse Zeeland 4311 EW",
    "addr:housenumber":"18",
    "addr:postcode":"4311 ew",
    "addr:street":"Boeijerstraat",
    "iso:country":"NL",
    "sg:address":"Boeijerstraat 18",
    "sg:city":"Bruinisse",
    "sg:orig_category":"Rijscholen",
    "sg:phone":"+31 111 481 613",
    "sg:postcode":"4311 EW",
    "sg:province":"Zeeland",
    "wof:name":"Autorijschool Bruinisse",
    "wof:placetype":"venue"
},
  "geometry": {"coordinates":[4.088734,51.661255],"type":"Point"}
}