{
  "type": "Feature",
  "properties": {
    "iso:country":"NL",
    "sg:address":"Nieuwstraat 21",
    "sg:city":"Hoorn Nh",
    "sg:orig_category":"Bloemen And Planten",
    "sg:phone":"+31 229 214 802",
    "sg:postcode":"1621 EA",
    "sg:province":"Noord-Holland",
    "wof:name":"Vok Jong Bloemen En Planten",
    "wof:placetype":"venue"
},
  "geometry": {"coordinates":[5.059936,52.641331],"type":"Point"}
}