{
  "type": "Feature",
  "properties": {
    "iso:country":"NL",
    "sg:address":"Hoefbladstr 46",
    "sg:city":"Alphen Aan Den Ryn",
    "sg:orig_category":"Scholen Voor Basisonderwijs",
    "sg:phone":"+31 172 443 009",
    "sg:postcode":"2403 VB",
    "sg:province":"Zuid-Holland",
    "wof:name":"Ridderspoor",
    "wof:placetype":"venue"
},
  "geometry": {"coordinates":[4.687307,52.145664],"type":"Point"}
}