{
  "type": "Feature",
  "properties": {
    "iso:country":"NL",
    "sg:address":"Brugakker 5879",
    "sg:city":"Zeist",
    "sg:orig_category":"Binnenhuisarchitecten",
    "sg:phone":"+31 30 695 1451",
    "sg:postcode":"3704 MX",
    "sg:province":"Utrecht",
    "wof:name":"Ruijssenaars Architecten (B.N.A.) Bv",
    "wof:placetype":"venue"
},
  "geometry": {"coordinates":[5.210062,52.082447],"type":"Point"}
}