{
  "type": "Feature",
  "properties": {
    "addr:full":"Nieuwe Ebbingestraat 13 Groningen Groningen 9712 NC",
    "addr:housenumber":"13",
    "addr:postcode":"9712 nc",
    "addr:street":"Nieuwe Ebbingestraat",
    "iso:country":"NL",
    "sg:address":"Nieuwe Ebbingestraat 13",
    "sg:city":"Groningen",
    "sg:orig_category":"Glaszetten",
    "sg:phone":"+31 50 313 0041",
    "sg:postcode":"9712 NC",
    "sg:province":"Groningen",
    "sg:website":"http://www.scoot.nl/doornbos",
    "wof:name":"Colors@Home Doornbos",
    "wof:placetype":"venue"
},
  "geometry": {"coordinates":[6.564723,53.222755],"type":"Point"}
}