{
  "type": "Feature",
  "properties": {
    "addr:full":"Burg Vd Munnikstr 20 Loppersum Groningen 9919 AN",
    "addr:housenumber":"20",
    "addr:postcode":"9919 an",
    "addr:street":"Burg",
    "iso:country":"NL",
    "sg:address":"Burg Vd Munnikstr 20",
    "sg:city":"Loppersum",
    "sg:orig_category":"Paramedische Behandelingen",
    "sg:phone":"+31 596 620 120",
    "sg:postcode":"9919 AN",
    "sg:province":"Groningen",
    "wof:name":"Logopedische Praktijk J.E. Sprang",
    "wof:placetype":"venue"
},
  "geometry": {"coordinates":[6.743999,53.332386],"type":"Point"}
}