{
  "type": "Feature",
  "properties": {
    "addr:full":"Lg Boog 12 Amersfoort Utrecht 3824 EG",
    "addr:housenumber":"12",
    "addr:postcode":"3824 eg",
    "addr:street":"Lg Boog",
    "iso:country":"NL",
    "sg:address":"Lg Boog 12",
    "sg:city":"Amersfoort",
    "sg:classifiers":[
        {
            "category":"Food & Beverages",
            "subcategory":"Bakery",
            "type":"Retail Goods"
        }
    ],
    "sg:phone":"+31 33 457 1122",
    "sg:postcode":"3824 EG",
    "sg:province":"Utrecht",
    "sg:tags":[
        "pizza"
    ],
    "wof:name":"Casa Mia",
    "wof:placetype":"venue"
},
  "geometry": {"coordinates":[5.37541,52.199226],"type":"Point"}
}