{
  "type": "Feature",
  "properties": {
    "addr:full":"Stationswg 94 Gorredyk Friesland 8401 DT",
    "addr:housenumber":"94",
    "addr:postcode":"8401 dt",
    "addr:street":"Stationswg",
    "iso:country":"NL",
    "sg:address":"Stationswg 94",
    "sg:city":"Gorredyk",
    "sg:orig_category":"Sauna'S",
    "sg:phone":"+31 513 461 482",
    "sg:postcode":"8401 DT",
    "sg:province":"Friesland",
    "sg:website":"http://www.saunastate.nl",
    "wof:name":"Saunastate.Nl",
    "wof:placetype":"venue"
},
  "geometry": {"coordinates":[6.06818,53.012768],"type":"Point"}
}