{
  "type": "Feature",
  "properties": {
    "addr:full":"Grootzeil 14 Zeewolde Flevoland 3891 KH",
    "addr:housenumber":"14",
    "addr:postcode":"3891 kh",
    "addr:street":"Grootzeil;Flevoland",
    "iso:country":"NL",
    "sg:address":"Grootzeil 14",
    "sg:city":"Zeewolde",
    "sg:orig_category":"Airconditioning",
    "sg:phone":"+31 36 522 0279",
    "sg:postcode":"3891 KH",
    "sg:province":"Flevoland",
    "wof:name":"Articcool, Int Luchtbehandeling",
    "wof:placetype":"venue"
},
  "geometry": {"coordinates":[5.52654,52.337746],"type":"Point"}
}