{
  "type": "Feature",
  "properties": {
    "iso:country":"NL",
    "sg:address":"Veerhaven 12",
    "sg:city":"Rotterdam",
    "sg:orig_category":"Kappers",
    "sg:phone":"+31 10 436 3932",
    "sg:postcode":"3016 CJ",
    "sg:province":"Zuid-Holland",
    "wof:name":"De Kapper Aan De Maas",
    "wof:placetype":"venue"
},
  "geometry": {"coordinates":[4.4779920578,51.9070243835],"type":"Point"}
}