{
  "type": "Feature",
  "properties": {
    "addr:full":"Stationswg 108 S Gravenhage South Holland 2515 BR",
    "addr:housenumber":"108",
    "addr:postcode":"2515 br",
    "addr:street":"S Gravenhage",
    "iso:country":"NL",
    "sg:address":"Stationswg 108",
    "sg:city":"S Gravenhage",
    "sg:orig_category":"Pruiken",
    "sg:phone":"+31 70 380 7267",
    "sg:postcode":"2515 BR",
    "sg:province":"South Holland",
    "wof:name":"Black & Beautiful",
    "wof:placetype":"venue"
},
  "geometry": {"coordinates":[4.31741,52.083988],"type":"Point"}
}