{
  "type": "Feature",
  "properties": {
    "addr:full":"Verzetstr 104 Vriezenveen Overijssel 7671 GN",
    "addr:housenumber":"104",
    "addr:postcode":"7671 gn",
    "iso:country":"NL",
    "sg:address":"Verzetstr 104",
    "sg:city":"Vriezenveen",
    "sg:classifiers":[
        {
            "category":"Retail",
            "subcategory":"Auto Repair",
            "type":"Services"
        }
    ],
    "sg:phone":"+31 546 563 891",
    "sg:postcode":"7671 GN",
    "sg:province":"Overijssel",
    "sg:tags":[
        "garage"
    ],
    "sg:website":"http://www.autobedrijf-zomer.nl",
    "wof:name":"Zomer, M",
    "wof:placetype":"venue"
},
  "geometry": {"coordinates":[6.605592,52.402908],"type":"Point"}
}