{
  "type": "Feature",
  "properties": {
    "addr:full":"G Metsuln 36 Alkmaar Noord-Holland 1816 EP",
    "addr:housenumber":"36",
    "addr:postcode":"1816 ep",
    "iso:country":"NL",
    "sg:address":"G Metsuln 36",
    "sg:city":"Alkmaar",
    "sg:orig_category":"Scholen Voor Basisonderwijs",
    "sg:phone":"+31 72 512 1006",
    "sg:postcode":"1816 EP",
    "sg:province":"Noord-Holland",
    "wof:name":"Driemaster Rk, De",
    "wof:placetype":"venue"
},
  "geometry": {"coordinates":[4.746258,52.634361],"type":"Point"}
}