{
  "type": "Feature",
  "properties": {
    "addr:full":"Stuvesande 78 Terneuzen Zeeland 4532 MH",
    "addr:housenumber":"78",
    "addr:postcode":"4532 mh",
    "addr:street":"Stuvesande",
    "iso:country":"NL",
    "sg:address":"Stuvesande 78",
    "sg:city":"Terneuzen",
    "sg:orig_category":"Bedrijfs- And Managementsconsultants",
    "sg:phone":"+31 115 648 813",
    "sg:postcode":"4532 MH",
    "sg:province":"Zeeland",
    "wof:name":"J.L.C.M. Gremmen",
    "wof:placetype":"venue"
},
  "geometry": {"coordinates":[3.838787,51.33588],"type":"Point"}
}