{
  "type": "Feature",
  "properties": {
    "addr:full":"Steenenstraat 24 Oud Beijerland Zuid-Holland 3262 JM",
    "addr:housenumber":"24",
    "addr:postcode":"3262 jm",
    "addr:street":"Steenenstraat;Oud Beijerland",
    "iso:country":"NL",
    "sg:address":"Steenenstraat 24",
    "sg:city":"Oud Beijerland",
    "sg:orig_category":"Bibliotheken And Openbare Archieven",
    "sg:phone":"+31 186 615 365",
    "sg:postcode":"3262 JM",
    "sg:province":"Zuid-Holland",
    "wof:name":"Speelotheek De Sprinter",
    "wof:placetype":"venue"
},
  "geometry": {"coordinates":[4.415244,51.821404],"type":"Point"}
}