{
  "type": "Feature",
  "properties": {
    "addr:full":"Oscar Romerolaan 3 Hilversum North Holland 1216 TJ",
    "addr:housenumber":"3",
    "addr:postcode":"1216 tj",
    "addr:street":"Oscar Romerolaan",
    "iso:country":"NL",
    "sg:address":"Oscar Romerolaan 3",
    "sg:city":"Hilversum",
    "sg:orig_category":"Film-, Tv- And Videoproductie",
    "sg:phone":"+31 35 625 2700",
    "sg:postcode":"1216 TJ",
    "sg:province":"North Holland",
    "wof:name":"Sentinel Bv Compact Discs",
    "wof:placetype":"venue"
},
  "geometry": {"coordinates":[5.144016,52.211071],"type":"Point"}
}