{
  "type": "Feature",
  "properties": {
    "addr:full":"Groenhof 25 Almere Flevoland 1352 AB",
    "addr:housenumber":"25",
    "addr:postcode":"1352 ab",
    "addr:street":"Groenhof;Flevoland",
    "iso:country":"NL",
    "sg:address":"Groenhof 25",
    "sg:city":"Almere",
    "sg:orig_category":"Accountants - Administratie- Consulenten En -Kantoren",
    "sg:phone":"+31 36 540 0070",
    "sg:postcode":"1352 AB",
    "sg:province":"Flevoland",
    "sg:website":"http://www.fabaconsult.nl",
    "wof:name":"Faba Consult",
    "wof:placetype":"venue"
},
  "geometry": {"coordinates":[5.218649,52.343075],"type":"Point"}
}