{
  "type": "Feature",
  "properties": {
    "iso:country":"NL",
    "sg:address":"Zweeloerstraat 1",
    "sg:city":"Noord Sleen",
    "sg:orig_category":"Zalenexploitatie",
    "sg:phone":"+31 591 361 778",
    "sg:postcode":"7846 TE",
    "sg:province":"Provincie Drenthe",
    "wof:name":"Galerie Geert W. Smegen",
    "wof:placetype":"venue"
},
  "geometry": {"coordinates":[6.794164,52.793453],"type":"Point"}
}