{
  "type": "Feature",
  "properties": {
    "addr:full":"Linge 36 Tilburg Noord-Brabant 5032 EW",
    "addr:housenumber":"36",
    "addr:postcode":"5032 ew",
    "addr:street":"Linge",
    "iso:country":"NL",
    "sg:address":"Linge 36",
    "sg:city":"Tilburg",
    "sg:classifiers":[
        {
            "category":"Retail",
            "subcategory":"Auto Repair",
            "type":"Services"
        }
    ],
    "sg:phone":"+31 13 468 1373",
    "sg:postcode":"5032 EW",
    "sg:province":"Noord-Brabant",
    "sg:tags":[
        "garage"
    ],
    "wof:name":"Wensveen, J A P Van",
    "wof:placetype":"venue"
},
  "geometry": {"coordinates":[5.052549,51.547508],"type":"Point"}
}