{
  "type": "Feature",
  "properties": {
    "addr:full":"Mesdaglaan 3 Maassluis Zuid-Holland 3141 HE",
    "addr:housenumber":"3",
    "addr:postcode":"3141 he",
    "addr:street":"Mesdaglaan",
    "iso:country":"NL",
    "sg:address":"Mesdaglaan 3",
    "sg:city":"Maassluis",
    "sg:orig_category":"Kappers",
    "sg:phone":"+31 10 591 0478",
    "sg:postcode":"3141 HE",
    "sg:province":"Zuid-Holland",
    "wof:name":"Herenkapsalon Kardien",
    "wof:placetype":"venue"
},
  "geometry": {"coordinates":[4.2608838081,51.9182739258],"type":"Point"}
}