{
  "type": "Feature",
  "properties": {
    "iso:country":"NL",
    "sg:address":"Baden Powellweg 2",
    "sg:city":"Ijsselstein Ut",
    "sg:orig_category":"Begrafenisondernemers",
    "sg:phone":"+31 30 688 1353",
    "sg:postcode":"3401 RR",
    "sg:province":"Utrecht",
    "wof:name":"Begrafenis En Crematie Isselheemuitvaartv",
    "wof:placetype":"venue"
},
  "geometry": {"coordinates":[5.05009,52.016979],"type":"Point"}
}