{
  "type": "Feature",
  "properties": {
    "addr:full":"Raadhuispln 53 Krimpen Ad Yssel South Holland 2922 AG",
    "addr:housenumber":"53",
    "addr:postcode":"2922",
    "addr:street":"Raadhuispln;Yssel",
    "iso:country":"NL",
    "sg:address":"Raadhuispln 53",
    "sg:city":"Krimpen Ad Yssel",
    "sg:orig_category":"Opticiens",
    "sg:phone":"+31 180 515 053",
    "sg:postcode":"2922 AG",
    "sg:province":"South Holland",
    "sg:website":"http://www.pearle.nl",
    "wof:name":"Pearle",
    "wof:placetype":"venue"
},
  "geometry": {"coordinates":[4.5904169083,51.9144668579],"type":"Point"}
}