{
  "type": "Feature",
  "properties": {
    "addr:full":"Ropsterwei 10 Oosternykerk Provincie Friesland 9137 RH",
    "addr:housenumber":"10",
    "addr:postcode":"9137 rh",
    "addr:street":"Ropsterwei;Provincie Friesland",
    "iso:country":"NL",
    "sg:address":"Ropsterwei 10",
    "sg:city":"Oosternykerk",
    "sg:orig_category":"Verf En Lak",
    "sg:phone":"+31 519 241 492",
    "sg:postcode":"9137 RH",
    "sg:province":"Provincie Friesland",
    "wof:name":"Walda",
    "wof:placetype":"venue"
},
  "geometry": {"coordinates":[6.056982,53.377167],"type":"Point"}
}