{
  "type": "Feature",
  "properties": {
    "addr:full":"Sluis 5 Giesbeek Gelderland 6987 BZ",
    "addr:housenumber":"5",
    "addr:postcode":"6987 bz",
    "addr:street":"Sluis;Gelderland",
    "iso:country":"NL",
    "sg:address":"Sluis 5",
    "sg:city":"Giesbeek",
    "sg:orig_category":"Medische Apparatuur And Prothesen Fab",
    "sg:phone":"+31 313 632 977",
    "sg:postcode":"6987 BZ",
    "sg:province":"Gelderland",
    "wof:name":"Dental Lab Jan Mulder",
    "wof:placetype":"venue"
},
  "geometry": {"coordinates":[6.074306,51.99585],"type":"Point"}
}