{
  "type": "Feature",
  "properties": {
    "addr:full":"Voltastraat 16A Roosendaal North Brabant 4702 PC",
    "addr:housenumber":"16a",
    "addr:postcode":"4702 pc",
    "addr:street":"Voltastraat",
    "iso:country":"NL",
    "sg:address":"Voltastraat 16A",
    "sg:city":"Roosendaal",
    "sg:orig_category":"Kappers",
    "sg:phone":"+31 165 398 511",
    "sg:postcode":"4702 PC",
    "sg:province":"North Brabant",
    "wof:name":"Diala",
    "wof:placetype":"venue"
},
  "geometry": {"coordinates":[4.4773421288,51.5414505005],"type":"Point"}
}