{
  "type": "Feature",
  "properties": {
    "addr:full":"Struik 12 Schimmert Limburg 6333 BP",
    "addr:housenumber":"12",
    "addr:postcode":"6333 bp",
    "addr:street":"Struik",
    "iso:country":"NL",
    "sg:address":"Struik 12",
    "sg:city":"Schimmert",
    "sg:orig_category":"Fotostudio'S And Fotografen",
    "sg:phone":"+31 45 404 1773",
    "sg:postcode":"6333 BP",
    "sg:province":"Limburg",
    "wof:name":"Foto Lou Zeegers",
    "wof:placetype":"venue"
},
  "geometry": {"coordinates":[5.82908,50.907455],"type":"Point"}
}