{
  "type": "Feature",
  "properties": {
    "iso:country":"NL",
    "sg:address":"Leidsegr 3",
    "sg:city":"Amsterdam",
    "sg:orig_category":"Vertalers",
    "sg:phone":"+31 20 620 3715",
    "sg:postcode":"1017 NA",
    "sg:province":"North Holland",
    "wof:name":"Warendorf, Mr H C S",
    "wof:placetype":"venue"
},
  "geometry": {"coordinates":[4.886537,52.367214],"type":"Point"}
}