{
  "type": "Feature",
  "properties": {
    "iso:country":"NL",
    "sg:address":"Nieuwstad 11",
    "sg:city":"Wehe Den Hoorn",
    "sg:orig_category":"Technische Studies And Onderzoek",
    "sg:phone":"+31 595 577 017",
    "sg:postcode":"9964 AM",
    "sg:province":"Groningen",
    "wof:name":"Onderwater, Milieu-Educatie En Communica",
    "wof:placetype":"venue"
},
  "geometry": {"coordinates":[6.418129,53.360126],"type":"Point"}
}