{
  "type": "Feature",
  "properties": {
    "addr:full":"Nyverheidswg 9 Den Helder North Holland 1785 AA",
    "addr:housenumber":"9",
    "addr:postcode":"1785 aa",
    "addr:street":"Nyverheidswg",
    "iso:country":"NL",
    "sg:address":"Nyverheidswg 9",
    "sg:city":"Den Helder",
    "sg:orig_category":"On- Offshore",
    "sg:phone":"+31 223 631 324",
    "sg:postcode":"1785 AA",
    "sg:province":"North Holland",
    "wof:name":"Zuiderstrand Sb Bv",
    "wof:placetype":"venue"
},
  "geometry": {"coordinates":[4.771383,52.947018],"type":"Point"}
}