{
  "type": "Feature",
  "properties": {
    "iso:country":"NL",
    "sg:address":"Prins Hendrikkade 97",
    "sg:city":"Amsterdam",
    "sg:classifiers":[
        {
            "category":"Fast Food",
            "type":"Food & Drink"
        }
    ],
    "sg:phone":"+31 20 622 9218",
    "sg:postcode":"1011 AG",
    "sg:province":"Noord-Holland",
    "sg:tags":[
        "afhaal",
        "restaurant"
    ],
    "wof:name":"Snackbar Centraal 97 A",
    "wof:placetype":"venue"
},
  "geometry": {"coordinates":[4.902715,52.375957],"type":"Point"}
}