{
  "type": "Feature",
  "properties": {
    "addr:full":"Wilhelminastraat 64 Asten North Brabant 5721 KK",
    "addr:housenumber":"64",
    "addr:postcode":"5721 kk",
    "addr:street":"Wilhelminastraat",
    "iso:country":"NL",
    "sg:address":"Wilhelminastraat 64",
    "sg:city":"Asten",
    "sg:orig_category":"Huisdierenfokkers",
    "sg:phone":"+31 493 696 087",
    "sg:postcode":"5721 KK",
    "sg:province":"North Brabant",
    "wof:name":"Nederlandse Cairn Terrier Club",
    "wof:placetype":"venue"
},
  "geometry": {"coordinates":[5.738868,51.39949],"type":"Point"}
}