{
  "type": "Feature",
  "properties": {
    "iso:country":"NL",
    "sg:address":"Nw Bussummerwg 76",
    "sg:city":"Huizen",
    "sg:orig_category":"Adviesbureaus Bedrijfsorganisatie",
    "sg:phone":"+31 35 523 3591",
    "sg:postcode":"1272 CK",
    "sg:province":"Noord-Holland",
    "wof:name":"Bruijn, De",
    "wof:placetype":"venue"
},
  "geometry": {"coordinates":[5.22372,52.29459],"type":"Point"}
}