{
  "type": "Feature",
  "properties": {
    "addr:full":"Ds Boersmastr 16 Elim Drenthe 7916 RH",
    "addr:housenumber":"16",
    "addr:postcode":"7916 rh",
    "addr:street":"Ds Boersmastr",
    "iso:country":"NL",
    "sg:address":"Ds Boersmastr 16",
    "sg:city":"Elim",
    "sg:orig_category":"Bibliotheken En Leeszalen Openbare",
    "sg:phone":"+31 528 352 010",
    "sg:postcode":"7916 RH",
    "sg:province":"Drenthe",
    "wof:name":"Openb Bibliotheek",
    "wof:placetype":"venue"
},
  "geometry": {"coordinates":[6.578884,52.680794],"type":"Point"}
}