{
  "type": "Feature",
  "properties": {
    "addr:full":"V L V Pabststr 205 Arnhem Gelderland 6814 HG",
    "addr:housenumber":"205",
    "addr:postcode":"6814 hg",
    "addr:street":"V L V Pabststr",
    "iso:country":"NL",
    "sg:address":"V L V Pabststr 205",
    "sg:city":"Arnhem",
    "sg:orig_category":"Kappers",
    "sg:phone":"+31 26 442 0677",
    "sg:postcode":"6814 HG",
    "sg:province":"Gelderland",
    "wof:name":"Arjo",
    "wof:placetype":"venue"
},
  "geometry": {"coordinates":[5.9045848846,51.9855194092],"type":"Point"}
}