{
  "type": "Feature",
  "properties": {
    "addr:full":"Langegr 24 Maarssen Utrecht 3601 AH",
    "addr:housenumber":"24",
    "addr:postcode":"3601 ah",
    "addr:street":"Langegr",
    "iso:country":"NL",
    "sg:address":"Langegr 24",
    "sg:city":"Maarssen",
    "sg:orig_category":"Homeopathie",
    "sg:phone":"+31 346 573 685",
    "sg:postcode":"3601 AH",
    "sg:province":"Utrecht",
    "wof:name":"Veldhuizen & Nagel, Van",
    "wof:placetype":"venue"
},
  "geometry": {"coordinates":[5.042254,52.141628],"type":"Point"}
}