{
  "type": "Feature",
  "properties": {
    "addr:full":"Den Brielstr 24 Amsterdam North Holland 1055 RV",
    "addr:housenumber":"24",
    "addr:postcode":"1055 rv",
    "iso:country":"NL",
    "sg:address":"Den Brielstr 24",
    "sg:city":"Amsterdam",
    "sg:orig_category":"Jachthavens - Jachtwerven",
    "sg:phone":"+31 20 682 2901",
    "sg:postcode":"1055 RV",
    "sg:province":"North Holland",
    "wof:name":"Staverno",
    "wof:placetype":"venue"
},
  "geometry": {"coordinates":[4.859705,52.382656],"type":"Point"}
}