{
  "type": "Feature",
  "properties": {
    "addr:full":"Van Sminiaweg 11 Haskerdijken Friesland 8468 MD",
    "addr:housenumber":"11",
    "addr:postcode":"8468",
    "addr:street":"Van Sminiaweg",
    "iso:country":"NL",
    "sg:address":"Van Sminiaweg 11",
    "sg:city":"Haskerdijken",
    "sg:orig_category":"Autokeuringen",
    "sg:phone":"+31 566 652 670",
    "sg:postcode":"8468 MD",
    "sg:province":"Friesland",
    "wof:name":"Friesland Montage",
    "wof:placetype":"venue"
},
  "geometry": {"coordinates":[5.868471,53.023029],"type":"Point"}
}