{
  "type": "Feature",
  "properties": {
    "addr:full":"H Verheesln 70 Boxtel North Brabant 5283 CW",
    "addr:housenumber":"70",
    "addr:postcode":"5283 cw",
    "iso:country":"NL",
    "sg:address":"H Verheesln 70",
    "sg:city":"Boxtel",
    "sg:orig_category":"Bedrijfsopleidingen",
    "sg:phone":"+31 411 678 991",
    "sg:postcode":"5283 CW",
    "sg:province":"North Brabant",
    "wof:name":"Hest, Astrid Van",
    "wof:placetype":"venue"
},
  "geometry": {"coordinates":[5.322775,51.591595],"type":"Point"}
}