{
  "type": "Feature",
  "properties": {
    "addr:full":"Generaal Snijdersstraat 54 Helmond Noord-Brabant 5703 GT",
    "addr:housenumber":"54",
    "addr:postcode":"5703 gt",
    "addr:street":"Generaal Snijdersstraat",
    "iso:country":"NL",
    "sg:address":"Generaal Snijdersstraat 54",
    "sg:city":"Helmond",
    "sg:orig_category":"Bedrijfs- And Managementsconsultants",
    "sg:phone":"+31 492 538 053",
    "sg:postcode":"5703 GT",
    "sg:province":"Noord-Brabant",
    "wof:name":"Van Gastel Consultants",
    "wof:placetype":"venue"
},
  "geometry": {"coordinates":[5.679615,51.481998],"type":"Point"}
}