{
  "type": "Feature",
  "properties": {
    "iso:country":"NL",
    "sg:address":"Bergstr 7",
    "sg:city":"Wageningen",
    "sg:orig_category":"Kappers",
    "sg:phone":"+31 317 415 150",
    "sg:postcode":"6701 AB",
    "sg:province":"Gelderland",
    "wof:name":"Joelle",
    "wof:placetype":"venue"
},
  "geometry": {"coordinates":[5.6609759331,51.9643554688],"type":"Point"}
}