{
  "type": "Feature",
  "properties": {
    "iso:country":"NL",
    "sg:address":"Prinsegracht 55",
    "sg:city":"'S Gravenhage",
    "sg:orig_category":"Metaalwerken",
    "sg:phone":"+31 70 380 1834",
    "sg:postcode":"2512 EX",
    "sg:province":"Zuid-Holland",
    "wof:name":"Fa Smit & De Ridder",
    "wof:placetype":"venue"
},
  "geometry": {"coordinates":[4.304244,52.074013],"type":"Point"}
}