{
  "type": "Feature",
  "properties": {
    "addr:full":"Hoevelakerveenweg 14 Hoevelaken Gelderland 3871 KK",
    "addr:housenumber":"14",
    "addr:postcode":"3871 kk",
    "addr:street":"Hoevelakerveenweg;Gelderland",
    "iso:country":"NL",
    "sg:address":"Hoevelakerveenweg 14",
    "sg:city":"Hoevelaken",
    "sg:orig_category":"Begrafenisondernemers",
    "sg:phone":"+31 33 257 1816",
    "sg:postcode":"3871 KK",
    "sg:province":"Gelderland",
    "wof:name":"Dierenbegraafplaats Klaverweide",
    "wof:placetype":"venue"
},
  "geometry": {"coordinates":[5.455435,52.189274],"type":"Point"}
}