{
  "type": "Feature",
  "properties": {
    "iso:country":"NL",
    "sg:address":"Leyensteinstr 5",
    "sg:city":"Kerkdriel",
    "sg:orig_category":"Woninginrichting",
    "sg:phone":"+31 418 632 175",
    "sg:postcode":"5331 CS",
    "sg:province":"Gelderland",
    "wof:name":"Bijl-De Bie, Woninginrichting Fa",
    "wof:placetype":"venue"
},
  "geometry": {"coordinates":[5.336689949,51.7712440491],"type":"Point"}
}