{
  "type": "Feature",
  "properties": {
    "addr:full":"Oude Markt 26 Stadskanaal Groningen 9501 VK",
    "addr:housenumber":"26",
    "addr:postcode":"9501 vk",
    "addr:street":"Oude Markt",
    "iso:country":"NL",
    "sg:address":"Oude Markt 26",
    "sg:city":"Stadskanaal",
    "sg:orig_category":"Werving And Selectie Van Tijdelijk Personeel And Uitzendkantoren",
    "sg:phone":"+31 599 610 055",
    "sg:postcode":"9501 VK",
    "sg:province":"Groningen",
    "wof:name":"Randstad",
    "wof:placetype":"venue"
},
  "geometry": {"coordinates":[6.95439291,52.987739563],"type":"Point"}
}