{
  "type": "Feature",
  "properties": {
    "addr:full":"Rengelinkweg 4 Aalten Gelderland 7122 JW",
    "addr:housenumber":"4",
    "addr:postcode":"7122 jw",
    "addr:street":"Rengelinkweg;Gelderland",
    "iso:country":"NL",
    "sg:address":"Rengelinkweg 4",
    "sg:city":"Aalten",
    "sg:orig_category":"Verhuur Landbouwmachines",
    "sg:phone":"+31 543 466 363",
    "sg:postcode":"7122 JW",
    "sg:province":"Gelderland",
    "wof:name":"Hoftijzer Bv Aalten",
    "wof:placetype":"venue"
},
  "geometry": {"coordinates":[6.525464,51.893501],"type":"Point"}
}