{
  "type": "Feature",
  "properties": {
    "addr:full":"Koperslagersstr 22 Sneek Provincie Friesland 8601 WL",
    "addr:housenumber":"22",
    "addr:postcode":"provincie;8601 wl",
    "addr:street":"Koperslagersstr",
    "iso:country":"NL",
    "sg:address":"Koperslagersstr 22",
    "sg:city":"Sneek",
    "sg:orig_category":"Kantoor- En Bedrijfsmeubelen - Fabrieken En Groothandel",
    "sg:phone":"+31 515 412 730",
    "sg:postcode":"8601 WL",
    "sg:province":"Provincie Friesland",
    "wof:name":"Valk Bv, De",
    "wof:placetype":"venue"
},
  "geometry": {"coordinates":[5.6313247681,53.0281944275],"type":"Point"}
}