{
  "type": "Feature",
  "properties": {
    "addr:full":"Parkln 2 Groningen Groningen 9724 AL",
    "addr:housenumber":"2",
    "addr:postcode":"9724 al",
    "addr:street":"Parkln",
    "iso:country":"NL",
    "sg:address":"Parkln 2",
    "sg:city":"Groningen",
    "sg:orig_category":"Administratie- En Boekhoudkantoren",
    "sg:phone":"+31 50 313 2918",
    "sg:postcode":"9724 AL",
    "sg:province":"Groningen",
    "wof:name":"K\u00fchl, M A C",
    "wof:placetype":"venue"
},
  "geometry": {"coordinates":[6.57675,53.211639],"type":"Point"}
}