{
  "type": "Feature",
  "properties": {
    "addr:full":"Emmakd 60 Boskoop Zuid-Holland 2771 VA",
    "addr:housenumber":"60",
    "addr:postcode":"2771",
    "addr:street":"Emmakd",
    "iso:country":"NL",
    "sg:address":"Emmakd 60",
    "sg:city":"Boskoop",
    "sg:orig_category":"Vertaalbureaus",
    "sg:phone":"+31 172 215 856",
    "sg:postcode":"2771 VA",
    "sg:province":"Zuid-Holland",
    "sg:website":"http://www.perfectenglish.nl",
    "wof:name":"Perfect English",
    "wof:placetype":"venue"
},
  "geometry": {"coordinates":[4.65922,52.074268],"type":"Point"}
}