{
  "type": "Feature",
  "properties": {
    "iso:country":"NL",
    "sg:address":"Domselaerstraat 108/1",
    "sg:city":"Amsterdam",
    "sg:orig_category":"Glaszetten",
    "sg:phone":"+31 20 663 8784",
    "sg:postcode":"1093 MA",
    "sg:province":"North Holland",
    "wof:name":"Glasatelier Renee Weyand",
    "wof:placetype":"venue"
},
  "geometry": {"coordinates":[4.928323,52.359955],"type":"Point"}
}