{
  "type": "Feature",
  "properties": {
    "addr:full":"Burgemeester Doornlaan 19 Zwijndrecht South Holland 3331 BB",
    "addr:housenumber":"19",
    "addr:postcode":"3331 bb",
    "addr:street":"Burgemeester Doornlaan",
    "iso:country":"NL",
    "sg:address":"Burgemeester Doornlaan 19",
    "sg:city":"Zwijndrecht",
    "sg:orig_category":"Loodgieterswerk, Verwarming And Sanitaire Installaties",
    "sg:phone":"+31 78 619 1264",
    "sg:postcode":"3331 BB",
    "sg:province":"South Holland",
    "wof:name":"R.P.S. V.D. Werken",
    "wof:placetype":"venue"
},
  "geometry": {"coordinates":[4.643843,51.818069],"type":"Point"}
}