{
  "type": "Feature",
  "properties": {
    "iso:country":"NL",
    "sg:address":"I Gerhardtstr 9",
    "sg:city":"Almere",
    "sg:orig_category":"Autorijscholen",
    "sg:phone":"+31 6 44712272",
    "sg:postcode":"1321 PR",
    "sg:province":"Flevoland",
    "wof:name":"Adam",
    "wof:placetype":"venue"
},
  "geometry": {"coordinates":[5.18257,52.35714],"type":"Point"}
}