{
  "type": "Feature",
  "properties": {
    "addr:full":"Bestsewg 2 Liempde Noord-Brabant 5298 LN",
    "addr:housenumber":"2",
    "addr:postcode":"5298 ln",
    "addr:street":"Bestsewg",
    "iso:country":"NL",
    "sg:address":"Bestsewg 2",
    "sg:city":"Liempde",
    "sg:orig_category":"Modellenbureaus En Modellen Freelance",
    "sg:phone":"+31 411 633 333",
    "sg:postcode":"5298 LN",
    "sg:province":"Noord-Brabant",
    "wof:name":"Schellen, Andr\u00e9",
    "wof:placetype":"venue"
},
  "geometry": {"coordinates":[5.367479,51.548584],"type":"Point"}
}