{
  "type": "Feature",
  "properties": {
    "addr:full":"Bentinckstraat 48 'S Gravenhage Zuid-Holland 2582 SX",
    "addr:housenumber":"48",
    "addr:postcode":"2582 sx",
    "addr:street":"Bentinckstraat;' S",
    "iso:country":"NL",
    "sg:address":"Bentinckstraat 48",
    "sg:city":"'S Gravenhage",
    "sg:orig_category":"Geluidsopnamen",
    "sg:phone":"+31 70 351 4609",
    "sg:postcode":"2582 SX",
    "sg:province":"Zuid-Holland",
    "wof:name":"Studio Clock",
    "wof:placetype":"venue"
},
  "geometry": {"coordinates":[4.278479,52.093666],"type":"Point"}
}