{
  "type": "Feature",
  "properties": {
    "addr:full":"Kaap Hoornstroom 12 Huizen Noord-Holland 1271 EL",
    "addr:housenumber":"12;1271",
    "addr:postcode":"el",
    "addr:street":"Kaap Hoornstroom",
    "iso:country":"NL",
    "sg:address":"Kaap Hoornstroom 12",
    "sg:city":"Huizen",
    "sg:orig_category":"Airconditioning",
    "sg:phone":"+31 35 526 8898",
    "sg:postcode":"1271 EL",
    "sg:province":"Noord-Holland",
    "sg:website":"http://www.hofstee-porsche.nl",
    "wof:name":"Hofstee, P",
    "wof:placetype":"venue"
},
  "geometry": {"coordinates":[5.248367,52.307804],"type":"Point"}
}