{
  "type": "Feature",
  "properties": {
    "addr:full":"Asserstr 46 Norg Provincie Drenthe 9331 JD",
    "addr:housenumber":"46",
    "addr:postcode":"9331 jd",
    "addr:street":"Asserstr;Provincie Drenthe",
    "iso:country":"NL",
    "sg:address":"Asserstr 46",
    "sg:city":"Norg",
    "sg:orig_category":"Verhuizingen",
    "sg:phone":"+31 592 612 262",
    "sg:postcode":"9331 JD",
    "sg:province":"Provincie Drenthe",
    "wof:name":"Kregel Norg Bv",
    "wof:placetype":"venue"
},
  "geometry": {"coordinates":[6.458285,53.061073],"type":"Point"}
}