{
  "type": "Feature",
  "properties": {
    "addr:full":"Schiedamseweg 2 Vlaardingen South Holland 3134 BJ",
    "addr:housenumber":"2",
    "addr:postcode":"3134 bj",
    "addr:street":"Schiedamseweg",
    "iso:country":"NL",
    "sg:address":"Schiedamseweg 2",
    "sg:city":"Vlaardingen",
    "sg:orig_category":"Werving And Selectie Van Tijdelijk Personeel And Uitzendkantoren",
    "sg:phone":"+31 10 460 2666",
    "sg:postcode":"3134 BJ",
    "sg:province":"South Holland",
    "wof:name":"Start",
    "wof:placetype":"venue"
},
  "geometry": {"coordinates":[4.3454508781,51.9092445374],"type":"Point"}
}