{
  "type": "Feature",
  "properties": {
    "addr:full":"Stranwei 15 Makkum Fr Friesland 8754 HA",
    "addr:housenumber":"15",
    "addr:postcode":"8754 ha",
    "addr:street":"Stranwei",
    "iso:country":"NL",
    "sg:address":"Stranwei 15",
    "sg:city":"Makkum Fr",
    "sg:orig_category":"Jachthavens - Jachtwerven",
    "sg:phone":"+31 515 231 628",
    "sg:postcode":"8754 HA",
    "sg:province":"Friesland",
    "wof:name":"Aquatel",
    "wof:placetype":"venue"
},
  "geometry": {"coordinates":[5.397804,53.051483],"type":"Point"}
}