{
  "type": "Feature",
  "properties": {
    "addr:full":"Middendam 2 Alphen Gld Gelderland 6626 AG",
    "addr:housenumber":"2",
    "addr:postcode":"6626",
    "addr:street":"Middendam;Gld Gelderland",
    "iso:country":"NL",
    "sg:address":"Middendam 2",
    "sg:city":"Alphen Gld",
    "sg:orig_category":"Verhuur Audiovisuele Apparatuur",
    "sg:phone":"+31 487 561 647",
    "sg:postcode":"6626 AG",
    "sg:province":"Gelderland",
    "wof:name":"Bye Bye Sound",
    "wof:placetype":"venue"
},
  "geometry": {"coordinates":[5.470872,51.821587],"type":"Point"}
}