{
  "type": "Feature",
  "properties": {
    "addr:full":"Beekstr 86 Arnhem Gelderland 6811 DZ",
    "addr:housenumber":"86",
    "addr:postcode":"6811 dz",
    "addr:street":"Beekstr",
    "iso:country":"NL",
    "sg:address":"Beekstr 86",
    "sg:city":"Arnhem",
    "sg:orig_category":"Parketvloeren",
    "sg:phone":"+31 26 389 4800",
    "sg:postcode":"6811 DZ",
    "sg:province":"Gelderland",
    "sg:website":"http://www.overgoorparket.nl",
    "wof:name":"Overgoor, Parket",
    "wof:placetype":"venue"
},
  "geometry": {"coordinates":[5.911037,51.9813],"type":"Point"}
}