{
  "type": "Feature",
  "properties": {
    "addr:full":"Ridderhofstraat 32 Kwadendamme Zeeland 4434 AP",
    "addr:housenumber":"32",
    "addr:postcode":"4434 ap",
    "addr:street":"Ridderhofstraat",
    "iso:country":"NL",
    "sg:address":"Ridderhofstraat 32",
    "sg:city":"Kwadendamme",
    "sg:orig_category":"Loodgieters- And Verwarmingsmateriaal Gh",
    "sg:phone":"+31 113 649 817",
    "sg:postcode":"4434 AP",
    "sg:province":"Zeeland",
    "wof:name":"Servon",
    "wof:placetype":"venue"
},
  "geometry": {"coordinates":[3.877063,51.43491],"type":"Point"}
}