{
  "type": "Feature",
  "properties": {
    "iso:country":"NL",
    "sg:address":"Schooldwarsweg 17",
    "sg:city":"Austerlitz",
    "sg:orig_category":"Schilderwerk",
    "sg:phone":"+31 343 491 490",
    "sg:postcode":"3711 BM",
    "sg:province":"Utrecht",
    "wof:name":"Albert Aalten Schilders Bv",
    "wof:placetype":"venue"
},
  "geometry": {"coordinates":[5.314193,52.07946],"type":"Point"}
}