{
  "type": "Feature",
  "properties": {
    "addr:full":"Hengelosestraat 237 Enschede NL.08 7521 AC",
    "addr:housenumber":"237",
    "addr:postcode":"7521 ac",
    "addr:street":"Hengelosestraat",
    "iso:country":"NL",
    "sg:address":"Hengelosestraat 237",
    "sg:city":"Enschede",
    "sg:orig_category":"Autokeuringen",
    "sg:phone":"+31 53 435 7084",
    "sg:postcode":"7521 AC",
    "sg:province":"NL.08",
    "wof:name":"Kroonband Bv",
    "wof:placetype":"venue"
},
  "geometry": {"coordinates":[6.873741,52.228786],"type":"Point"}
}