{
  "type": "Feature",
  "properties": {
    "iso:country":"NL",
    "sg:address":"Zoutmanstraat 2",
    "sg:city":"'S Gravenhage",
    "sg:orig_category":"Fotolaboratoria",
    "sg:phone":"+31 70 345 9805",
    "sg:postcode":"2518 GP",
    "sg:province":"Zuid-Holland",
    "wof:name":"Best Price Foto'S",
    "wof:placetype":"venue"
},
  "geometry": {"coordinates":[4.29348,52.080318],"type":"Point"}
}