{
  "type": "Feature",
  "properties": {
    "iso:country":"NL",
    "sg:address":"Noordeinde 52",
    "sg:city":"S Gravenhage",
    "sg:orig_category":"Kappers",
    "sg:phone":"+31 70 365 5153",
    "sg:postcode":"2514 GJ",
    "sg:province":"Zuid-Holland",
    "sg:website":"http://www.studiojollygood.nl",
    "wof:name":"Jolly Good, Studio",
    "wof:placetype":"venue"
},
  "geometry": {"coordinates":[4.3093500137,52.084148407],"type":"Point"}
}