{
  "type": "Feature",
  "properties": {
    "addr:full":"Grt Spuistr 30-38 Dordrecht Zuid-Holland 3311 GE",
    "addr:housenumber":"30-38",
    "addr:postcode":"3311",
    "iso:country":"NL",
    "sg:address":"Grt Spuistr 30-38",
    "sg:city":"Dordrecht",
    "sg:orig_category":"Kantoor- En Bedrijfsmeubelen",
    "sg:phone":"+31 78 614 0933",
    "sg:postcode":"3311 GE",
    "sg:province":"Zuid-Holland",
    "sg:website":"http://www.holster.nl",
    "wof:name":"Holster Kantoorverzorging",
    "wof:placetype":"venue"
},
  "geometry": {"coordinates":[4.6640758514,51.8128700256],"type":"Point"}
}