{
  "type": "Feature",
  "properties": {
    "addr:full":"Cingelstr 2A Breda Noord-Brabant 4811 MC",
    "addr:housenumber":"2a;4811",
    "addr:postcode":"mc",
    "addr:street":"Cingelstr",
    "iso:country":"NL",
    "sg:address":"Cingelstr 2A",
    "sg:city":"Breda",
    "sg:orig_category":"Beeldende Kunstenaars",
    "sg:phone":"+31 76 514 3341",
    "sg:postcode":"4811 MC",
    "sg:province":"Noord-Brabant",
    "wof:name":"Cotrotsos, E",
    "wof:placetype":"venue"
},
  "geometry": {"coordinates":[4.774579,51.590008],"type":"Point"}
}