{
  "type": "Feature",
  "properties": {
    "addr:full":"Kerklaan 63 De Lier Zuid-Holland 2678 ST",
    "addr:housenumber":"63",
    "addr:postcode":"2678 st",
    "addr:street":"Kerklaan",
    "iso:country":"NL",
    "sg:address":"Kerklaan 63",
    "sg:city":"De Lier",
    "sg:orig_category":"Bloemen And Planten Gh",
    "sg:phone":"+31 174 517 609",
    "sg:postcode":"2678 ST",
    "sg:province":"Zuid-Holland",
    "wof:name":"Handelsmaatschappij P.J. Luyendijk Bv",
    "wof:placetype":"venue"
},
  "geometry": {"coordinates":[4.246268,51.980881],"type":"Point"}
}