{
  "type": "Feature",
  "properties": {
    "addr:full":"Zyperstr 60 Alkmaar North Holland 1823 CX",
    "addr:housenumber":"60",
    "addr:postcode":"1823 cx",
    "addr:street":"Zyperstr",
    "iso:country":"NL",
    "sg:address":"Zyperstr 60",
    "sg:city":"Alkmaar",
    "sg:orig_category":"Loodgieters",
    "sg:phone":"+31 72 511 4930",
    "sg:postcode":"1823 CX",
    "sg:province":"North Holland",
    "sg:website":"http://www.hoflandalkmaar.nl",
    "wof:name":"Hofland Installatiebedrijf",
    "wof:placetype":"venue"
},
  "geometry": {"coordinates":[4.76043,52.638321],"type":"Point"}
}