{
  "type": "Feature",
  "properties": {
    "addr:full":"Westerstraat 37- 39 Enkhuizen Noord-Holland 1601 AB",
    "addr:housenumber":"37 39",
    "addr:postcode":"1601 ab",
    "addr:street":"Westerstraat",
    "iso:country":"NL",
    "sg:address":"Westerstraat 37- 39",
    "sg:city":"Enkhuizen",
    "sg:orig_category":"Huishoudapparatuur, Televisies And Radio'S",
    "sg:phone":"+31 228 315 544",
    "sg:postcode":"1601 AB",
    "sg:province":"Noord-Holland",
    "wof:name":"De Wit",
    "wof:placetype":"venue"
},
  "geometry": {"coordinates":[5.292125,52.70422],"type":"Point"}
}