{
  "type": "Feature",
  "properties": {
    "iso:country":"NL",
    "sg:address":"Impuls 49",
    "sg:city":"Purmerend",
    "sg:classifiers":[
        {
            "category":"Professional",
            "subcategory":"Accounting & Tax Preparation",
            "type":"Services"
        }
    ],
    "sg:phone":"+31 299 667 101",
    "sg:postcode":"1446 WC",
    "sg:province":"Noord-Holland",
    "sg:tags":[
        "accountant"
    ],
    "wof:name":"Accountantskantoor Aa Renout Bv",
    "wof:placetype":"venue"
},
  "geometry": {"coordinates":[5.00657,52.511162],"type":"Point"}
}