{
  "type": "Feature",
  "properties": {
    "iso:country":"NL",
    "sg:address":"Koninginneln 48",
    "sg:city":"Groningen",
    "sg:orig_category":"Hengelsportartikelen",
    "sg:phone":"+31 50 313 7517",
    "sg:postcode":"9717 BW",
    "sg:province":"Baden-W\u00fcrttemberg",
    "wof:name":"Hofstra, B",
    "wof:placetype":"venue"
},
  "geometry": {"coordinates":[10.06394,49.188332],"type":"Point"}
}