{
  "type": "Feature",
  "properties": {
    "addr:full":"Sportln 404 S Gravenhage Zuid-Holland 2566 MA",
    "addr:housenumber":"404;gravenhage",
    "addr:postcode":"2566 ma",
    "addr:street":"S",
    "iso:country":"NL",
    "sg:address":"Sportln 404",
    "sg:city":"S Gravenhage",
    "sg:orig_category":"Woningbouw- Verenigingen En -Stichtingen",
    "sg:phone":"+31 70 363 1292",
    "sg:postcode":"2566 MA",
    "sg:province":"Zuid-Holland",
    "wof:name":"Segbroekhof Co\u00f7P",
    "wof:placetype":"venue"
},
  "geometry": {"coordinates":[4.2555298805,52.0791282654],"type":"Point"}
}