{
  "type": "Feature",
  "properties": {
    "addr:full":"Linnaeuswg 21 Ysselstein Ut Utrecht 3401 MS",
    "addr:housenumber":"21",
    "addr:postcode":"3401 ms",
    "addr:street":"Linnaeuswg",
    "iso:country":"NL",
    "sg:address":"Linnaeuswg 21",
    "sg:city":"Ysselstein Ut",
    "sg:orig_category":"Machineonderhoud En -Reparatie",
    "sg:phone":"+31 6 22378365",
    "sg:postcode":"3401 MS",
    "sg:province":"Utrecht",
    "sg:website":"http://www.dehaantechnics.nl",
    "wof:name":"Haan Technics & Services, W De",
    "wof:placetype":"venue"
},
  "geometry": {"coordinates":[5.054631,52.016602],"type":"Point"}
}