{
  "type": "Feature",
  "properties": {
    "iso:country":"NL",
    "sg:address":"Schiekd 31E",
    "sg:city":"Rotterdam",
    "sg:orig_category":"Bejaarden - Verzorgingstehuizen",
    "sg:phone":"+31 10 467 5099",
    "sg:postcode":"3033 BB",
    "sg:province":"Zuid-Holland",
    "wof:name":"Heulbrug",
    "wof:placetype":"venue"
},
  "geometry": {"coordinates":[4.46912,51.927521],"type":"Point"}
}