{
  "type": "Feature",
  "properties": {
    "iso:country":"NL",
    "sg:address":"Parallelwg O 31",
    "sg:city":"Valkenswaard",
    "sg:orig_category":"Adviesbureaus",
    "sg:phone":"+31 40 204 4466",
    "sg:postcode":"5555 XA",
    "sg:province":"Noord-Brabant",
    "wof:name":"Personeelsplus Bv",
    "wof:placetype":"venue"
},
  "geometry": {"coordinates":[5.466762,51.344738],"type":"Point"}
}