{
  "type": "Feature",
  "properties": {
    "addr:full":"Torenstraat 32 Castricum Noord-Holland 1901 EE",
    "addr:housenumber":"32",
    "addr:postcode":"1901 ee",
    "addr:street":"Torenstraat",
    "iso:country":"NL",
    "sg:address":"Torenstraat 32",
    "sg:city":"Castricum",
    "sg:orig_category":"Opticiens",
    "sg:phone":"+31 251 652 238",
    "sg:postcode":"1901 EE",
    "sg:province":"Noord-Holland",
    "wof:name":"Bossinade Optiek Bv",
    "wof:placetype":"venue"
},
  "geometry": {"coordinates":[4.6637001038,52.5489196777],"type":"Point"}
}