{
  "type": "Feature",
  "properties": {
    "addr:full":"Isseltseveld 2A Amersfoort Utrecht 3812 LH",
    "addr:housenumber":"2a",
    "addr:postcode":"3812 lh",
    "addr:street":"Isseltseveld",
    "iso:country":"NL",
    "sg:address":"Isseltseveld 2A",
    "sg:city":"Amersfoort",
    "sg:orig_category":"Kinderopvang Behalve Thuis",
    "sg:phone":"+31 33 465 4295",
    "sg:postcode":"3812 LH",
    "sg:province":"Utrecht",
    "wof:name":"Buitenschoolse Opvang Ratel",
    "wof:placetype":"venue"
},
  "geometry": {"coordinates":[5.356341,52.161076],"type":"Point"}
}