{
  "type": "Feature",
  "properties": {
    "addr:full":"Bijleveldsingel 13 Nijmegen Gelderland 6521 AM",
    "addr:housenumber":"13",
    "addr:postcode":"6521",
    "addr:street":"Bijleveldsingel;Gelderland",
    "iso:country":"NL",
    "sg:address":"Bijleveldsingel 13",
    "sg:city":"Nijmegen",
    "sg:orig_category":"Verzekeringen",
    "sg:phone":"+31 24 323 0366",
    "sg:postcode":"6521 AM",
    "sg:province":"Gelderland",
    "wof:name":"Jurgens Assurantien Nijmegen Bv",
    "wof:placetype":"venue"
},
  "geometry": {"coordinates":[5.869918,51.842575],"type":"Point"}
}