{
  "type": "Feature",
  "properties": {
    "addr:full":"Zeelsterstraat 80 Eindhoven Noord-Brabant 5652 EL",
    "addr:housenumber":"80",
    "addr:postcode":"5652 el",
    "addr:street":"Zeelsterstraat",
    "iso:country":"NL",
    "sg:address":"Zeelsterstraat 80",
    "sg:city":"Eindhoven",
    "sg:orig_category":"Banken And Kredietinstellingen",
    "sg:phone":"+31 40 251 3811",
    "sg:postcode":"5652 EL",
    "sg:province":"Noord-Brabant",
    "wof:name":"Abn Amro",
    "wof:placetype":"venue"
},
  "geometry": {"coordinates":[5.443737,51.438251],"type":"Point"}
}