{
  "type": "Feature",
  "properties": {
    "iso:country":"NL",
    "sg:address":"Bermwg 394",
    "sg:city":"Capelle Ad Yssel",
    "sg:orig_category":"Loonbedrijven",
    "sg:phone":"+31 10 451 5093",
    "sg:postcode":"2907 LC",
    "sg:province":"Zuid-Holland",
    "wof:name":"Haag, P J",
    "wof:placetype":"venue"
},
  "geometry": {"coordinates":[4.58487,51.94006],"type":"Point"}
}