{
  "type": "Feature",
  "properties": {
    "iso:country":"NL",
    "sg:address":"Jufferstraat 4",
    "sg:city":"Zaandam",
    "sg:orig_category":"Boekhouders",
    "sg:phone":"+31 75 659 0909",
    "sg:postcode":"1508 EB",
    "sg:province":"Noord-Holland",
    "wof:name":"Stichting Welsaen",
    "wof:placetype":"venue"
},
  "geometry": {"coordinates":[4.817031,52.459385],"type":"Point"}
}