{
  "type": "Feature",
  "properties": {
    "addr:full":"Waterbies 77 Leeuwarden Friesland 8935 PG",
    "addr:housenumber":"77",
    "addr:postcode":"8935 pg",
    "addr:street":"Waterbies",
    "iso:country":"NL",
    "sg:address":"Waterbies 77",
    "sg:city":"Leeuwarden",
    "sg:orig_category":"Verenigingen En Stichtingen",
    "sg:phone":"+31 58 288 0667",
    "sg:postcode":"8935 PG",
    "sg:province":"Friesland",
    "wof:name":"Scouting Regio Frysl\u00e2n",
    "wof:placetype":"venue"
},
  "geometry": {"coordinates":[5.836248,53.190876],"type":"Point"}
}