{
  "type": "Feature",
  "properties": {
    "iso:country":"NL",
    "sg:address":"Vosstr 31",
    "sg:city":"Hall",
    "sg:orig_category":"Adviesbureaus Bouwkunde",
    "sg:phone":"+31 313 656 240",
    "sg:postcode":"6964 BB",
    "sg:province":"Montana",
    "wof:name":"Edm",
    "wof:placetype":"venue"
},
  "geometry": {"coordinates":[-113.196388,46.589054],"type":"Point"}
}