{
  "type": "Feature",
  "properties": {
    "addr:full":"Gravenstr 85 Alphen Aan Den Ryn South Holland 2405 ZD",
    "addr:housenumber":"85",
    "addr:postcode":"2405 zd",
    "addr:street":"Gravenstr;Aan Den Ryn",
    "iso:country":"NL",
    "sg:address":"Gravenstr 85",
    "sg:city":"Alphen Aan Den Ryn",
    "sg:orig_category":"Beveiliging",
    "sg:phone":"+31 172 424 185",
    "sg:postcode":"2405 ZD",
    "sg:province":"South Holland",
    "sg:website":"http://www.osr-security.nl",
    "wof:name":"Osr, Security",
    "wof:placetype":"venue"
},
  "geometry": {"coordinates":[4.669079,52.11919],"type":"Point"}
}