{
  "type": "Feature",
  "properties": {
    "addr:full":"Prinsenstraat 52 Zaandam Noord-Holland 1501 NV",
    "addr:housenumber":"52",
    "addr:postcode":"1501 nv",
    "addr:street":"Prinsenstraat",
    "iso:country":"NL",
    "sg:address":"Prinsenstraat 52",
    "sg:city":"Zaandam",
    "sg:orig_category":"Kappers",
    "sg:phone":"+31 75 631 5018",
    "sg:postcode":"1501 NV",
    "sg:province":"Noord-Holland",
    "sg:website":"http://www.newhairexperience.nl",
    "wof:name":"New Hair Experience",
    "wof:placetype":"venue"
},
  "geometry": {"coordinates":[4.830841,52.439434],"type":"Point"}
}