{
  "type": "Feature",
  "properties": {
    "addr:full":"St Isidoorstr 26 Heibloem Limburg 6089 NG",
    "addr:housenumber":"26",
    "addr:postcode":"6089 ng",
    "addr:street":"Heibloem Limburg",
    "iso:country":"NL",
    "sg:address":"St Isidoorstr 26",
    "sg:city":"Heibloem",
    "sg:orig_category":"Manueel Therapeuten",
    "sg:phone":"+31 475 495 125",
    "sg:postcode":"6089 NG",
    "sg:province":"Limburg",
    "wof:name":"Eidolon",
    "wof:placetype":"venue"
},
  "geometry": {"coordinates":[5.896518,51.300686],"type":"Point"}
}