{
  "type": "Feature",
  "properties": {
    "addr:full":"Brinkweg 48 Heino Minnesota 8141 NH",
    "addr:housenumber":"48",
    "addr:postcode":"8141 nh",
    "addr:street":"Brinkweg;Minnesota",
    "iso:country":"NL",
    "sg:address":"Brinkweg 48",
    "sg:city":"Heino",
    "sg:orig_category":"Beroepsorganisaties",
    "sg:phone":"+31 572 391 965",
    "sg:postcode":"8141 NH",
    "sg:province":"Minnesota",
    "wof:name":"Onderwijsbonden Cnv",
    "wof:placetype":"venue"
},
  "geometry": {"coordinates":[-95.398735,46.498905],"type":"Point"}
}