{
  "type": "Feature",
  "properties": {
    "iso:country":"NL",
    "sg:address":"Middendijk 66",
    "sg:city":"Nijbroek",
    "sg:orig_category":"Huizensloop And Bouwrijp Maken",
    "sg:phone":"+31 571 291 624",
    "sg:postcode":"7397 NE",
    "sg:province":"Gelderland",
    "wof:name":"Vof W.B. Mekelenkamp",
    "wof:placetype":"venue"
},
  "geometry": {"coordinates":[6.060241,52.309399],"type":"Point"}
}