{
  "type": "Feature",
  "properties": {
    "iso:country":"NL",
    "sg:address":"Arenberglaan 370",
    "sg:city":"Breda",
    "sg:orig_category":"Diverse Grafische Activiteiten",
    "sg:phone":"+31 76 541 7131",
    "sg:postcode":"4822 ZS",
    "sg:province":"North Brabant",
    "wof:name":"Marq",
    "wof:placetype":"venue"
},
  "geometry": {"coordinates":[4.72941,51.604843],"type":"Point"}
}