{
  "type": "Feature",
  "properties": {
    "addr:full":"Korte Noorderweg 22 Hilversum Noord-Holland 1221 NB",
    "addr:housenumber":"22",
    "addr:postcode":"1221 nb",
    "addr:street":"Korte Noorderweg",
    "iso:country":"NL",
    "sg:address":"Korte Noorderweg 22",
    "sg:city":"Hilversum",
    "sg:orig_category":"Kantoorartikelen",
    "sg:phone":"+31 35 683 3229",
    "sg:postcode":"1221 NB",
    "sg:province":"Noord-Holland",
    "wof:name":"Ida Verstege",
    "wof:placetype":"venue"
},
  "geometry": {"coordinates":[5.181219101,52.2282752991],"type":"Point"}
}