{
  "type": "Feature",
  "properties": {
    "iso:country":"NL",
    "sg:address":"Klinkenhof 10",
    "sg:city":"Meerssen",
    "sg:orig_category":"Elektronische Informatie- Systemen Off-Line",
    "sg:phone":"+31 43 362 5422",
    "sg:postcode":"6231 BA",
    "sg:province":"Limburg",
    "wof:name":"Edro",
    "wof:placetype":"venue"
},
  "geometry": {"coordinates":[5.740132,50.878609],"type":"Point"}
}