{
  "type": "Feature",
  "properties": {
    "iso:country":"NL",
    "sg:address":"Industriestraat 67",
    "sg:city":"Haaksbergen",
    "sg:orig_category":"Voeding, Dranken And Tabak Gh",
    "sg:phone":"+31 53 572 2705",
    "sg:postcode":"7482 EW",
    "sg:province":"Overijssel",
    "wof:name":"Bv Sperwer Oost",
    "wof:placetype":"venue"
},
  "geometry": {"coordinates":[6.72262,52.152233],"type":"Point"}
}