{
  "type": "Feature",
  "properties": {
    "addr:full":"Beethovenln 203 Tilburg Noord-Brabant 5011 LG",
    "addr:housenumber":"203",
    "addr:postcode":"5011 lg",
    "addr:street":"Tilburg",
    "iso:country":"NL",
    "sg:address":"Beethovenln 203",
    "sg:city":"Tilburg",
    "sg:orig_category":"Begrafenisverzorging",
    "sg:phone":"+31 13 455 3379",
    "sg:postcode":"5011 LG",
    "sg:province":"Noord-Brabant",
    "wof:name":"Bijnen",
    "wof:placetype":"venue"
},
  "geometry": {"coordinates":[5.08836,51.584732],"type":"Point"}
}