{
  "type": "Feature",
  "properties": {
    "addr:full":"Damloper 69 Oosterhout Nb Noord-Brabant 4902 CE",
    "addr:housenumber":"69",
    "addr:postcode":"4902 ce",
    "addr:street":"Damloper",
    "iso:country":"NL",
    "sg:address":"Damloper 69",
    "sg:city":"Oosterhout Nb",
    "sg:orig_category":"Glasdecoratie",
    "sg:phone":"+31 162 471 670",
    "sg:postcode":"4902 CE",
    "sg:province":"Noord-Brabant",
    "wof:name":"Gloasshop, De",
    "wof:placetype":"venue"
},
  "geometry": {"coordinates":[4.84039,51.640602],"type":"Point"}
}