{
  "type": "Feature",
  "properties": {
    "iso:country":"NL",
    "sg:address":"Past Hoekstr 2",
    "sg:city":"Groesbeek",
    "sg:orig_category":"Administratie- En Boekhoudkantoren",
    "sg:phone":"+31 24 397 5735",
    "sg:postcode":"6562 GB",
    "sg:province":"Gelderland",
    "wof:name":"Janssen",
    "wof:placetype":"venue"
},
  "geometry": {"coordinates":[5.938986,51.758278],"type":"Point"}
}