{
  "type": "Feature",
  "properties": {
    "addr:full":"V Hortastr 5 Amersfoort Utrecht 3822 VM",
    "addr:housenumber":"5",
    "addr:postcode":"3822 vm",
    "addr:street":"Hortastr",
    "iso:country":"NL",
    "sg:address":"V Hortastr 5",
    "sg:city":"Amersfoort",
    "sg:orig_category":"Adviesbureaus Bedrijfsorganisatie",
    "sg:phone":"+31 33 456 2675",
    "sg:postcode":"3822 VM",
    "sg:province":"Utrecht",
    "wof:name":"Bart Siermann Bv",
    "wof:placetype":"venue"
},
  "geometry": {"coordinates":[5.39704,52.180801],"type":"Point"}
}