{
  "type": "Feature",
  "properties": {
    "addr:full":"Raadhuisstr 12 Oudorp Nh Noord-Holland 1829 BV",
    "addr:housenumber":"12",
    "addr:postcode":"1829 bv",
    "addr:street":"Raadhuisstr",
    "iso:country":"NL",
    "sg:address":"Raadhuisstr 12",
    "sg:city":"Oudorp Nh",
    "sg:orig_category":"Bedrijfsopleidingen",
    "sg:phone":"+31 72 562 0852",
    "sg:postcode":"1829 BV",
    "sg:province":"Noord-Holland",
    "wof:name":"Aguja Flecha Vof",
    "wof:placetype":"venue"
},
  "geometry": {"coordinates":[4.774813,52.630238],"type":"Point"}
}