{
  "type": "Feature",
  "properties": {
    "addr:full":"Waterhoen 23 Mydrecht Utrecht 3641 TP",
    "addr:housenumber":"23;3641",
    "addr:street":"Waterhoen;Tp",
    "iso:country":"NL",
    "sg:address":"Waterhoen 23",
    "sg:city":"Mydrecht",
    "sg:orig_category":"Schilders",
    "sg:phone":"+31 297 256 825",
    "sg:postcode":"3641 TP",
    "sg:province":"Utrecht",
    "wof:name":"Molenaar, G",
    "wof:placetype":"venue"
},
  "geometry": {"coordinates":[4.849755,52.201641],"type":"Point"}
}