{
  "type": "Feature",
  "properties": {
    "iso:country":"NL",
    "sg:address":"Antillenwg 10",
    "sg:city":"Mill",
    "sg:orig_category":"Nachtclubs",
    "sg:phone":"+31 485 454 597",
    "sg:postcode":"5451 GK",
    "sg:province":"Noord-Brabant",
    "wof:name":"Can-Can",
    "wof:placetype":"venue"
},
  "geometry": {"coordinates":[-98.988472,44.25444],"type":"Point"}
}