{
  "type": "Feature",
  "properties": {
    "iso:country":"NL",
    "sg:address":"Kloosring 87",
    "sg:city":"Oud Beyerland",
    "sg:orig_category":"Bedrijfsopleidingen",
    "sg:phone":"+31 186 625 519",
    "sg:postcode":"3261 SG",
    "sg:province":"South Holland",
    "wof:name":"Maritime Positioning",
    "wof:placetype":"venue"
},
  "geometry": {"coordinates":[4.43064,51.819118],"type":"Point"}
}