{
  "type": "Feature",
  "properties": {
    "addr:full":"Zuidpln 113C Rayonkant Zuid West Rotterdam South Holland 3083 CN",
    "addr:housenumber":"113c rayonkant",
    "addr:postcode":"3083 cn",
    "addr:street":"Zuidpln;West",
    "iso:country":"NL",
    "sg:address":"Zuidpln 113C Rayonkant Zuid West",
    "sg:city":"Rotterdam",
    "sg:orig_category":"Vakorganisaties",
    "sg:phone":"+31 10 486 3900",
    "sg:postcode":"3083 CN",
    "sg:province":"South Holland",
    "sg:website":"http://www.aob.nl",
    "wof:name":"Aob",
    "wof:placetype":"venue"
},
  "geometry": {"coordinates":[4.48606,51.887791],"type":"Point"}
}