{
  "type": "Feature",
  "properties": {
    "addr:full":"Dr Bolkesteinstr 88 Hoofddorp Noord-Holland 2132 JV",
    "addr:housenumber":"88",
    "addr:postcode":"2132 jv",
    "iso:country":"NL",
    "sg:address":"Dr Bolkesteinstr 88",
    "sg:city":"Hoofddorp",
    "sg:orig_category":"Verhuizingen",
    "sg:phone":"+31 6 22800016",
    "sg:postcode":"2132 JV",
    "sg:province":"Noord-Holland",
    "wof:name":"Spaan",
    "wof:placetype":"venue"
},
  "geometry": {"coordinates":[4.697988,52.306572],"type":"Point"}
}