{
  "type": "Feature",
  "properties": {
    "addr:full":"Koloniewg 8 Soest Utrecht 3768 EX",
    "addr:housenumber":"8",
    "addr:postcode":"3768 ex",
    "addr:street":"Koloniewg",
    "iso:country":"NL",
    "sg:address":"Koloniewg 8",
    "sg:city":"Soest",
    "sg:orig_category":"Bloemen En Planten",
    "sg:phone":"+31 35 601 1783",
    "sg:postcode":"3768 EX",
    "sg:province":"Utrecht",
    "wof:name":"Brink & Co, J Van Den",
    "wof:placetype":"venue"
},
  "geometry": {"coordinates":[5.305801,52.168255],"type":"Point"}
}