{
  "type": "Feature",
  "properties": {
    "iso:country":"NL",
    "sg:address":"Escamplaan 1975",
    "sg:city":"'S Gravenhage",
    "sg:orig_category":"Kinderopvang Behalve Thuis",
    "sg:phone":"+31 70 397 6659",
    "sg:postcode":"2547 EZ",
    "sg:province":"Noord-Holland",
    "wof:name":"Peuterspeelzaal Kareltje",
    "wof:placetype":"venue"
},
  "geometry": {"coordinates":[4.26694,52.061771],"type":"Point"}
}