{
  "type": "Feature",
  "properties": {
    "addr:full":"A V Nassaustr 22 S Gravenzande South Holland 2691 GM",
    "addr:housenumber":"22",
    "addr:postcode":"2691 gm",
    "addr:street":"A;Nassaustr;S Gravenzande",
    "iso:country":"NL",
    "sg:address":"A V Nassaustr 22",
    "sg:city":"S Gravenzande",
    "sg:orig_category":"Projectontwikkeling",
    "sg:phone":"+31 174 413 167",
    "sg:postcode":"2691 GM",
    "sg:province":"South Holland",
    "wof:name":"Hoogenboom-Wolf, S G",
    "wof:placetype":"venue"
},
  "geometry": {"coordinates":[4.16946,51.994629],"type":"Point"}
}