{
  "type": "Feature",
  "properties": {
    "iso:country":"NL",
    "sg:address":"Noordereinde 40A",
    "sg:city":"S Graveland",
    "sg:orig_category":"Antiquiteiten",
    "sg:phone":"+31 35 656 5079",
    "sg:postcode":"1243 JH",
    "sg:province":"Noord-Holland",
    "wof:name":"Ratatouille",
    "wof:placetype":"venue"
},
  "geometry": {"coordinates":[5.12143,52.247784],"type":"Point"}
}