{
  "type": "Feature",
  "properties": {
    "addr:full":"Noordereinde 40A S Graveland Noord-Holland 1243 JH",
    "addr:housenumber":"40a",
    "addr:postcode":"1243 jh",
    "addr:street":"Noordereinde;S Graveland",
    "iso:country":"NL",
    "sg:address":"Noordereinde 40A",
    "sg:city":"S Graveland",
    "sg:orig_category":"Antiquiteiten",
    "sg:phone":"+31 35 656 5079",
    "sg:postcode":"1243 JH",
    "sg:province":"Noord-Holland",
    "wof:name":"Ratatouille",
    "wof:placetype":"venue"
},
  "geometry": {"coordinates":[5.12143,52.247784],"type":"Point"}
}