{
  "type": "Feature",
  "properties": {
    "addr:full":"Groenoord 422 Alphen Aan Den Ryn South Holland 2401 AP",
    "addr:housenumber":"422",
    "addr:postcode":"2401 ap",
    "addr:street":"Groenoord;Aan Den Ryn",
    "iso:country":"NL",
    "sg:address":"Groenoord 422",
    "sg:city":"Alphen Aan Den Ryn",
    "sg:orig_category":"Ongediertebestrijding En Ontsmetting",
    "sg:phone":"+31 172 444 906",
    "sg:postcode":"2401 AP",
    "sg:province":"South Holland",
    "wof:name":"Vermeulen, A G",
    "wof:placetype":"venue"
},
  "geometry": {"coordinates":[4.656571,52.145161],"type":"Point"}
}