{
  "type": "Feature",
  "properties": {
    "addr:full":"Chrysantstr 11 S Gravenzande South Holland 2691 LP",
    "addr:housenumber":"11",
    "addr:postcode":"2691 lp",
    "addr:street":"Chrysantstr;S Gravenzande",
    "iso:country":"NL",
    "sg:address":"Chrysantstr 11",
    "sg:city":"S Gravenzande",
    "sg:orig_category":"Kassenonderhoud",
    "sg:phone":"+31 174 422 905",
    "sg:postcode":"2691 LP",
    "sg:province":"South Holland",
    "wof:name":"Egr",
    "wof:placetype":"venue"
},
  "geometry": {"coordinates":[4.180012,51.981731],"type":"Point"}
}