{
  "type": "Feature",
  "properties": {
    "addr:full":"Vredebest 10 Gouda Zuid-Holland 2801 AS",
    "addr:housenumber":"10",
    "addr:postcode":"2801 as",
    "addr:street":"Vredebest",
    "iso:country":"NL",
    "sg:address":"Vredebest 10",
    "sg:city":"Gouda",
    "sg:orig_category":"Verzekeringen - Verzekeringskantoren",
    "sg:phone":"+31 182 348 887",
    "sg:postcode":"2801 AS",
    "sg:province":"Zuid-Holland",
    "sg:website":"http://www.accesnet.nl/univehgv",
    "wof:name":"Univ\u00e9",
    "wof:placetype":"venue"
},
  "geometry": {"coordinates":[4.709284,52.015942],"type":"Point"}
}