{
  "type": "Feature",
  "properties": {
    "iso:country":"NL",
    "sg:address":"Bosln 35",
    "sg:city":"Appelscha",
    "sg:orig_category":"Kappers",
    "sg:phone":"+31 516 433 394",
    "sg:postcode":"8426 EG",
    "sg:province":"Friesland",
    "wof:name":"Bronshof, Ria",
    "wof:placetype":"venue"
},
  "geometry": {"coordinates":[6.3390479088,52.9548797607],"type":"Point"}
}