{
  "type": "Feature",
  "properties": {
    "addr:full":"Hidalgoweg 2 Leeuwarden Friesland 8938 BA",
    "addr:housenumber":"2",
    "addr:postcode":"8938 ba",
    "addr:street":"Hidalgoweg",
    "iso:country":"NL",
    "sg:address":"Hidalgoweg 2",
    "sg:city":"Leeuwarden",
    "sg:orig_category":"Voeding, Dranken And Tabak Gh",
    "sg:phone":"+31 58 284 4044",
    "sg:postcode":"8938 BA",
    "sg:province":"Friesland",
    "wof:name":"Lukas Klamer Bv",
    "wof:placetype":"venue"
},
  "geometry": {"coordinates":[5.858448,53.195469],"type":"Point"}
}