{
  "type": "Feature",
  "properties": {
    "addr:full":"Rydersstr 11A T Veld Noord-Holland 1735 GA",
    "addr:housenumber":"11a",
    "addr:postcode":"1735 ga",
    "addr:street":"Rydersstr",
    "iso:country":"NL",
    "sg:address":"Rydersstr 11A",
    "sg:city":"T Veld",
    "sg:orig_category":"Adviesbureaus Bedrijfsorganisatie",
    "sg:phone":"+31 226 422 421",
    "sg:postcode":"1735 GA",
    "sg:province":"Noord-Holland",
    "wof:name":"Molen, Ria Van Der",
    "wof:placetype":"venue"
},
  "geometry": {"coordinates":[4.849047,52.735283],"type":"Point"}
}