{
  "type": "Feature",
  "properties": {
    "addr:full":"Wolfhorn 2 Eelde Drenthe 9761 BC",
    "addr:housenumber":"2",
    "addr:postcode":"9761 bc",
    "addr:street":"Wolfhorn",
    "iso:country":"NL",
    "sg:address":"Wolfhorn 2",
    "sg:city":"Eelde",
    "sg:orig_category":"Kappers",
    "sg:phone":"+31 50 309 1808",
    "sg:postcode":"9761 BC",
    "sg:province":"Drenthe",
    "wof:name":"Maison Ellen",
    "wof:placetype":"venue"
},
  "geometry": {"coordinates":[6.569089,53.137978],"type":"Point"}
}