{
  "type": "Feature",
  "properties": {
    "iso:country":"NL",
    "sg:address":"Herestr 2",
    "sg:city":"Grypskerk",
    "sg:orig_category":"Makelaars En Adviseurs Onroerende Goederen",
    "sg:phone":"+31 594 212 556",
    "sg:postcode":"9843 AK",
    "sg:province":"Groningen",
    "sg:website":"http://www.steller-verzekeringen.nl",
    "wof:name":"Steller",
    "wof:placetype":"venue"
},
  "geometry": {"coordinates":[6.310302,53.263493],"type":"Point"}
}