{
  "type": "Feature",
  "properties": {
    "addr:full":"F Halsln 1 Waalwyk Noord-Brabant 5143 GJ",
    "addr:housenumber":"1",
    "addr:postcode":"5143 gj",
    "addr:street":"Halsln",
    "iso:country":"NL",
    "sg:address":"F Halsln 1",
    "sg:city":"Waalwyk",
    "sg:orig_category":"Adviesbureaus Bedrijfsorganisatie",
    "sg:phone":"+31 416 341 741",
    "sg:postcode":"5143 GJ",
    "sg:province":"Noord-Brabant",
    "wof:name":"Daal Bv, H Van",
    "wof:placetype":"venue"
},
  "geometry": {"coordinates":[5.09139,51.680408],"type":"Point"}
}