{
  "type": "Feature",
  "properties": {
    "addr:full":"Kromstr 116 Oss Noord-Brabant 5345 AE",
    "addr:housenumber":"116",
    "addr:postcode":"5345 ae",
    "iso:country":"NL",
    "sg:address":"Kromstr 116",
    "sg:city":"Oss",
    "sg:orig_category":"Adviesbureaus",
    "sg:phone":"+31 412 691 765",
    "sg:postcode":"5345 AE",
    "sg:province":"Noord-Brabant",
    "wof:name":"Exrogo Bv",
    "wof:placetype":"venue"
},
  "geometry": {"coordinates":[-77.235214,38.312599],"type":"Point"}
}