{
  "type": "Feature",
  "properties": {
    "addr:full":"Oirschotsebaan 36 Oisterwijk North Brabant 5062 TG",
    "addr:housenumber":"36",
    "addr:postcode":"5062 tg",
    "addr:street":"Oirschotsebaan",
    "iso:country":"NL",
    "sg:address":"Oirschotsebaan 36",
    "sg:city":"Oisterwijk",
    "sg:orig_category":"Meubelzaken, Woning- And Keukeninrichting",
    "sg:phone":"+31 13 513 3662",
    "sg:postcode":"5062 TG",
    "sg:province":"North Brabant",
    "wof:name":"Antonis",
    "wof:placetype":"venue"
},
  "geometry": {"coordinates":[5.238788,51.534103],"type":"Point"}
}