{
  "type": "Feature",
  "properties": {
    "addr:full":"Karel Doormanstraat 70 Groenlo Gelderland 7141 WH",
    "addr:housenumber":"70",
    "addr:postcode":"7141 wh",
    "addr:street":"Karel Doormanstraat;Gelderland",
    "iso:country":"NL",
    "sg:address":"Karel Doormanstraat 70",
    "sg:city":"Groenlo",
    "sg:orig_category":"Antiekzaken",
    "sg:phone":"+31 544 463 954",
    "sg:postcode":"7141 WH",
    "sg:province":"Gelderland",
    "wof:name":"Corantiek",
    "wof:placetype":"venue"
},
  "geometry": {"coordinates":[6.600181,52.043945],"type":"Point"}
}