{
  "type": "Feature",
  "properties": {
    "iso:country":"NL",
    "sg:address":"Teugsewg 8",
    "sg:city":"Teuge",
    "sg:classifiers":[
        {
            "category":"Retail",
            "subcategory":"Auto Repair",
            "type":"Services"
        }
    ],
    "sg:phone":"+31 55 323 1494",
    "sg:postcode":"7395 SG",
    "sg:province":"Gelderland",
    "sg:tags":[
        "garage"
    ],
    "sg:website":"http://www.weijers.nl",
    "wof:name":"Weijers Autobedrijf",
    "wof:placetype":"venue"
},
  "geometry": {"coordinates":[6.039676,52.232792],"type":"Point"}
}