{
  "type": "Feature",
  "properties": {
    "addr:full":"Kanaaldk 1 Weesp Noord-Holland 1383 ND",
    "addr:housenumber":"1",
    "addr:postcode":"1383 nd",
    "addr:street":"Kanaaldk",
    "iso:country":"NL",
    "sg:address":"Kanaaldk 1",
    "sg:city":"Weesp",
    "sg:orig_category":"Kinderopvang",
    "sg:phone":"+31 294 419 260",
    "sg:postcode":"1383 ND",
    "sg:province":"Noord-Holland",
    "wof:name":"Boerderij, De",
    "wof:placetype":"venue"
},
  "geometry": {"coordinates":[5.022725,52.284351],"type":"Point"}
}