{
  "type": "Feature",
  "properties": {
    "iso:country":"NL",
    "sg:address":"Aalsterveld 76",
    "sg:city":"Beuningen Gld",
    "sg:orig_category":"Fotostudio'S And Fotografen",
    "sg:phone":"+31 24 677 6511",
    "sg:postcode":"6641 SE",
    "sg:province":"Gelderland",
    "wof:name":"Air Inspection Holland",
    "wof:placetype":"venue"
},
  "geometry": {"coordinates":[5.75434,51.864887],"type":"Point"}
}