{
  "type": "Feature",
  "properties": {
    "addr:full":"Marsstraat 27 Haarlem North Holland 2024 GA",
    "addr:housenumber":"27",
    "addr:postcode":"2024 ga",
    "addr:street":"Marsstraat",
    "iso:country":"NL",
    "sg:address":"Marsstraat 27",
    "sg:city":"Haarlem",
    "sg:orig_category":"Verenigingen En Stichtingen",
    "sg:phone":"+31 23 526 6144",
    "sg:postcode":"2024 GA",
    "sg:province":"North Holland",
    "wof:name":"Meer Bewegen Nrd-Holland, Sticht",
    "wof:placetype":"venue"
},
  "geometry": {"coordinates":[4.641431,52.405907],"type":"Point"}
}