{
  "type": "Feature",
  "properties": {
    "addr:full":"Baai 82 Etten Leur Noord-Brabant 4871 BC",
    "addr:housenumber":"82",
    "addr:postcode":"4871 bc",
    "addr:street":"Baai",
    "iso:country":"NL",
    "sg:address":"Baai 82",
    "sg:city":"Etten Leur",
    "sg:classifiers":[
        {
            "category":"Personal",
            "subcategory":"Nail Salon",
            "type":"Services"
        }
    ],
    "sg:phone":"+31 76 502 1000",
    "sg:postcode":"4871 BC",
    "sg:province":"Noord-Brabant",
    "sg:tags":[
        "pedicure"
    ],
    "wof:name":"Pedizon",
    "wof:placetype":"venue"
},
  "geometry": {"coordinates":[4.645066,51.583427],"type":"Point"}
}