{
  "type": "Feature",
  "properties": {
    "addr:full":"Ernest Hendrickxstraat 1 Breda Noord-Brabant 4827 CD",
    "addr:housenumber":"1",
    "addr:postcode":"4827 cd",
    "addr:street":"Ernest Hendrickxstraat",
    "iso:country":"NL",
    "sg:address":"Ernest Hendrickxstraat 1",
    "sg:city":"Breda",
    "sg:orig_category":"Juridische Dienstverlening",
    "sg:phone":"+31 76 587 7685",
    "sg:postcode":"4827 CD",
    "sg:province":"Noord-Brabant",
    "wof:name":"Jurosport",
    "wof:placetype":"venue"
},
  "geometry": {"coordinates":[4.801434,51.611542],"type":"Point"}
}