{
  "type": "Feature",
  "properties": {
    "addr:full":"Schoonoortstraat 40 Velsen-Noord North Holland 1951 CC",
    "addr:housenumber":"40",
    "addr:postcode":"1951 cc",
    "addr:street":"Schoonoortstraat",
    "iso:country":"NL",
    "sg:address":"Schoonoortstraat 40",
    "sg:city":"Velsen-Noord",
    "sg:orig_category":"Loodgieterswerk, Verwarming And Sanitaire Installaties",
    "sg:phone":"+31 251 228 366",
    "sg:postcode":"1951 CC",
    "sg:province":"North Holland",
    "wof:name":"Installatiebedrijf M.A. Schipper",
    "wof:placetype":"venue"
},
  "geometry": {"coordinates":[4.647087,52.469547],"type":"Point"}
}