{
  "type": "Feature",
  "properties": {
    "addr:full":"Europaweg 76 Schoonebeek Drenthe 7761 AJ",
    "addr:housenumber":"76",
    "addr:postcode":"7761 aj",
    "addr:street":"Europaweg",
    "iso:country":"NL",
    "sg:address":"Europaweg 76",
    "sg:city":"Schoonebeek",
    "sg:orig_category":"Glaszetten",
    "sg:phone":"+31 524 531 188",
    "sg:postcode":"7761 AJ",
    "sg:province":"Drenthe",
    "wof:name":"Doevendans Schilderswerken Bv",
    "wof:placetype":"venue"
},
  "geometry": {"coordinates":[6.892666,52.659298],"type":"Point"}
}