{
  "type": "Feature",
  "properties": {
    "addr:full":"Pr Margrietln 39 Wezep Gelderland 8091 AV",
    "addr:housenumber":"39",
    "addr:postcode":"8091 av",
    "iso:country":"NL",
    "sg:address":"Pr Margrietln 39",
    "sg:city":"Wezep",
    "sg:orig_category":"Loopbaanbegeleiding",
    "sg:phone":"+31 38 376 5628",
    "sg:postcode":"8091 AV",
    "sg:province":"Gelderland",
    "sg:website":"http://www.bureau-inbalans.nl",
    "wof:name":"In Balans",
    "wof:placetype":"venue"
},
  "geometry": {"coordinates":[5.996179,52.449257],"type":"Point"}
}