{
  "type": "Feature",
  "properties": {
    "addr:full":"Randwg 6A Culemborg Gelderland 4104 AC",
    "addr:housenumber":"6a",
    "addr:postcode":"4104 ac",
    "addr:street":"Randwg;Gelderland",
    "iso:country":"NL",
    "sg:address":"Randwg 6A",
    "sg:city":"Culemborg",
    "sg:orig_category":"Automaterialen En Gereedschappen",
    "sg:phone":"+31 345 532 122",
    "sg:postcode":"4104 AC",
    "sg:province":"Gelderland",
    "sg:website":"http://www.brezan.nl",
    "wof:name":"Brezan",
    "wof:placetype":"venue"
},
  "geometry": {"coordinates":[5.220801,51.945171],"type":"Point"}
}