{
  "type": "Feature",
  "properties": {
    "iso:country":"NL",
    "sg:address":"Zuideinde 8C",
    "sg:city":"Zevenhuizen Zh",
    "sg:orig_category":"Bloemen And Planten Gh",
    "sg:phone":"+31 180 631 789",
    "sg:postcode":"2761 DA",
    "sg:province":"Zuid-Holland",
    "wof:name":"Sota Zuideinde Bv",
    "wof:placetype":"venue"
},
  "geometry": {"coordinates":[4.587702,52.002789],"type":"Point"}
}