{
  "type": "Feature",
  "properties": {
    "addr:full":"Dirk De Raetlaan 60 Wassenaar Zuid-Holland 2241 RH",
    "addr:housenumber":"60",
    "addr:postcode":"2241 rh",
    "addr:street":"Dirk De Raetlaan",
    "iso:country":"NL",
    "sg:address":"Dirk De Raetlaan 60",
    "sg:city":"Wassenaar",
    "sg:orig_category":"Verhuur Catering-, Feest- En Evenementbenodigdheden",
    "sg:phone":"+31 70 511 1433",
    "sg:postcode":"2241 RH",
    "sg:province":"Zuid-Holland",
    "wof:name":"J A Vd Velde",
    "wof:placetype":"venue"
},
  "geometry": {"coordinates":[4.403543,52.15271],"type":"Point"}
}