{
  "type": "Feature",
  "properties": {
    "addr:full":"Oldengaerde 31 Almelo Overijssel 7608 AP",
    "addr:housenumber":"31",
    "addr:postcode":"7608 ap",
    "addr:street":"Oldengaerde",
    "iso:country":"NL",
    "sg:address":"Oldengaerde 31",
    "sg:city":"Almelo",
    "sg:orig_category":"Adviesbureaus Bedrijfsorganisatie",
    "sg:phone":"+31 546 863 498",
    "sg:postcode":"7608 AP",
    "sg:province":"Overijssel",
    "wof:name":"Sloten, Van",
    "wof:placetype":"venue"
},
  "geometry": {"coordinates":[6.686633,52.382324],"type":"Point"}
}