{
  "type": "Feature",
  "properties": {
    "addr:full":"Bromelia 2 Nootdorp Zuid-Holland 2631 VK",
    "addr:housenumber":"2",
    "addr:postcode":"2631 vk",
    "addr:street":"Bromelia",
    "iso:country":"NL",
    "sg:address":"Bromelia 2",
    "sg:city":"Nootdorp",
    "sg:orig_category":"Administratie- En Boekhoudkantoren",
    "sg:phone":"+31 15 310 7946",
    "sg:postcode":"2631 VK",
    "sg:province":"Zuid-Holland",
    "wof:name":"French Bv",
    "wof:placetype":"venue"
},
  "geometry": {"coordinates":[4.404982,52.03912],"type":"Point"}
}