{
  "type": "Feature",
  "properties": {
    "iso:country":"NL",
    "sg:address":"J F Kellywg 4",
    "sg:city":"Ulvenhout",
    "sg:orig_category":"Architecten En Architectenbureaus",
    "sg:phone":"+31 76 565 5950",
    "sg:postcode":"4851 SX",
    "sg:province":"Noord-Brabant",
    "wof:name":"Evers, Architectenbureau",
    "wof:placetype":"venue"
},
  "geometry": {"coordinates":[4.798011,51.539761],"type":"Point"}
}