{
  "type": "Feature",
  "properties": {
    "addr:full":"Verheeskade 327 'S-Gravenhage Zuid-Holland 2521 DE",
    "addr:housenumber":"327",
    "addr:postcode":"s-gravenhage;2521 de",
    "addr:street":"Verheeskade",
    "iso:country":"NL",
    "sg:address":"Verheeskade 327",
    "sg:city":"'S-Gravenhage",
    "sg:orig_category":"Opslag Inboedels",
    "sg:phone":"+31 70 305 3180",
    "sg:postcode":"2521 DE",
    "sg:province":"Zuid-Holland",
    "sg:website":"http://www.shurgard.nl",
    "wof:name":"Shurgard Den Haag",
    "wof:placetype":"venue"
},
  "geometry": {"coordinates":[4.3178172112,52.062953949],"type":"Point"}
}