{
  "type": "Feature",
  "properties": {
    "addr:full":"Raadhuisstraat 16 Amsterdam Noord-Holland 1016 DE",
    "addr:housenumber":"16;1016",
    "addr:postcode":"de",
    "addr:street":"Raadhuisstraat",
    "iso:country":"NL",
    "sg:address":"Raadhuisstraat 16",
    "sg:city":"Amsterdam",
    "sg:orig_category":"Feestartikelen",
    "sg:phone":"+31 20 624 6886",
    "sg:postcode":"1016 DE",
    "sg:province":"Noord-Holland",
    "sg:website":"http://www.louiswittenburg.nl",
    "wof:name":"Louis Wittenburg",
    "wof:placetype":"venue"
},
  "geometry": {"coordinates":[4.888125,52.373432],"type":"Point"}
}