{
  "type": "Feature",
  "properties": {
    "addr:full":"Klein Brabant 19 Vught Noord-Brabant 5262 RK",
    "addr:housenumber":"19",
    "addr:postcode":"5262 rk",
    "addr:street":"Klein Brabant",
    "iso:country":"NL",
    "sg:address":"Klein Brabant 19",
    "sg:city":"Vught",
    "sg:orig_category":"Verzekeringen",
    "sg:phone":"+31 73 656 4499",
    "sg:postcode":"5262 RK",
    "sg:province":"Noord-Brabant",
    "wof:name":"H. Bossong Assurantiekantoor Zuid",
    "wof:placetype":"venue"
},
  "geometry": {"coordinates":[5.291074,51.637676],"type":"Point"}
}