{
  "type": "Feature",
  "properties": {
    "addr:full":"De Breelaan 9 Amerongen Utrecht 3958 EE",
    "addr:housenumber":"9",
    "addr:postcode":"3958 ee",
    "addr:street":"De Breelaan",
    "iso:country":"NL",
    "sg:address":"De Breelaan 9",
    "sg:city":"Amerongen",
    "sg:orig_category":"Goederenvervoer Over De Weg",
    "sg:phone":"+31 343 453 484",
    "sg:postcode":"3958 EE",
    "sg:province":"Utrecht",
    "wof:name":"A. Van Eck",
    "wof:placetype":"venue"
},
  "geometry": {"coordinates":[5.463485,52.002213],"type":"Point"}
}