{
  "type": "Feature",
  "properties": {
    "addr:full":"Musketiersveld 225 Apeldoorn Gelderland 7327 GT",
    "addr:housenumber":"225",
    "addr:postcode":"7327 gt",
    "addr:street":"Musketiersveld;Gelderland",
    "iso:country":"NL",
    "sg:address":"Musketiersveld 225",
    "sg:city":"Apeldoorn",
    "sg:orig_category":"Grafisch Ontwerpers",
    "sg:phone":"+31 55 541 7699",
    "sg:postcode":"7327 GT",
    "sg:province":"Gelderland",
    "wof:name":"Eisink, D",
    "wof:placetype":"venue"
},
  "geometry": {"coordinates":[6.001595,52.187279],"type":"Point"}
}