{
  "type": "Feature",
  "properties": {
    "addr:full":"Burenpolderweg 30A Yerseke Zeeland 4401 KX",
    "addr:housenumber":"30a",
    "addr:postcode":"4401 kx",
    "addr:street":"Burenpolderweg",
    "iso:country":"NL",
    "sg:address":"Burenpolderweg 30A",
    "sg:city":"Yerseke",
    "sg:orig_category":"Kampeerterreinen",
    "sg:phone":"+31 113 571 860",
    "sg:postcode":"4401 KX",
    "sg:province":"Zeeland",
    "wof:name":"Camping Zon En Zee",
    "wof:placetype":"venue"
},
  "geometry": {"coordinates":[4.0529718399,51.498550415],"type":"Point"}
}