{
  "type": "Feature",
  "properties": {
    "addr:full":"Singel 457 Amsterdam Noord-Holland 1012 WP",
    "addr:housenumber":"457",
    "addr:postcode":"1012 wp",
    "addr:street":"Singel",
    "iso:country":"NL",
    "sg:address":"Singel 457",
    "sg:city":"Amsterdam",
    "sg:orig_category":"Herenkleding",
    "sg:phone":"+31 20 427 7842",
    "sg:postcode":"1012 WP",
    "sg:province":"Noord-Holland",
    "wof:name":"Hugo Boss Store",
    "wof:placetype":"venue"
},
  "geometry": {"coordinates":[4.891188,52.367294],"type":"Point"}
}