{
  "type": "Feature",
  "properties": {
    "addr:full":"Gildenstr 47 Doetinchem Gelderland 7005 BL",
    "addr:housenumber":"47",
    "addr:postcode":"7005 bl",
    "addr:street":"Gildenstr;Gelderland",
    "iso:country":"NL",
    "sg:address":"Gildenstr 47",
    "sg:city":"Doetinchem",
    "sg:orig_category":"Verf En Lak - Fabrieken En Groothandel",
    "sg:phone":"+31 314 361 040",
    "sg:postcode":"7005 BL",
    "sg:province":"Gelderland",
    "wof:name":"Habeco Bv, 1",
    "wof:placetype":"venue"
},
  "geometry": {"coordinates":[6.301784,51.949493],"type":"Point"}
}