{
  "type": "Feature",
  "properties": {
    "addr:full":"Noordstraat 28 Axel Zeeland 4571 GD",
    "addr:housenumber":"28",
    "addr:postcode":"4571 gd",
    "addr:street":"Noordstraat",
    "iso:country":"NL",
    "sg:address":"Noordstraat 28",
    "sg:city":"Axel",
    "sg:orig_category":"Herenmodezaken",
    "sg:phone":"+31 115 561 920",
    "sg:postcode":"4571 GD",
    "sg:province":"Zeeland",
    "wof:name":"Landgraaf",
    "wof:placetype":"venue"
},
  "geometry": {"coordinates":[3.907686,51.26627],"type":"Point"}
}