{
  "type": "Feature",
  "properties": {
    "addr:full":"Statenln 105 Ryen North Brabant 5121 HC",
    "addr:housenumber":"105",
    "addr:postcode":"5121 hc",
    "iso:country":"NL",
    "sg:address":"Statenln 105",
    "sg:city":"Ryen",
    "sg:orig_category":"Kinderopvang",
    "sg:phone":"+31 161 220 704",
    "sg:postcode":"5121 HC",
    "sg:province":"North Brabant",
    "wof:name":"Skoebidoe",
    "wof:placetype":"venue"
},
  "geometry": {"coordinates":[4.9197,51.588017],"type":"Point"}
}