{
  "type": "Feature",
  "properties": {
    "addr:full":"Ln V Meerdervoort 172 S Gravenhage Zuid-Holland 2517 BH",
    "addr:housenumber":"172;gravenhage",
    "addr:postcode":"2517 bh",
    "addr:street":"Ln;Meerdervoort;S",
    "iso:country":"NL",
    "sg:address":"Ln V Meerdervoort 172",
    "sg:city":"S Gravenhage",
    "sg:orig_category":"Adviesbureaus Bedrijfsorganisatie",
    "sg:phone":"+31 70 360 7814",
    "sg:postcode":"2517 BH",
    "sg:province":"Zuid-Holland",
    "wof:name":"Bsh",
    "wof:placetype":"venue"
},
  "geometry": {"coordinates":[4.28708,52.08667],"type":"Point"}
}