{
  "type": "Feature",
  "properties": {
    "addr:full":"Hangenwg 2 Huizen North Holland 1271 KA",
    "addr:housenumber":"2",
    "addr:postcode":"1271 ka",
    "addr:street":"Hangenwg",
    "iso:country":"NL",
    "sg:address":"Hangenwg 2",
    "sg:city":"Huizen",
    "sg:orig_category":"Kaas",
    "sg:phone":"+31 35 526 9597",
    "sg:postcode":"1271 KA",
    "sg:province":"North Holland",
    "wof:name":"Jan Ren?",
    "wof:placetype":"venue"
},
  "geometry": {"coordinates":[5.2399249077,52.2964935303],"type":"Point"}
}