{
  "type": "Feature",
  "properties": {
    "iso:country":"NL",
    "sg:address":"Maurick 50",
    "sg:city":"Hillegom",
    "sg:orig_category":"Autorijscholen",
    "sg:phone":"+31 252 520 887",
    "sg:postcode":"2181 LC",
    "sg:province":"Zuid-Holland",
    "wof:name":"Lippens Autorijschool, J",
    "wof:placetype":"venue"
},
  "geometry": {"coordinates":[4.591885,52.297569],"type":"Point"}
}