{
  "type": "Feature",
  "properties": {
    "addr:full":"Hobbemaplein 14 Drunen Noord-Brabant 5151 SL",
    "addr:housenumber":"14",
    "addr:postcode":"5151 sl",
    "addr:street":"Hobbemaplein",
    "iso:country":"NL",
    "sg:address":"Hobbemaplein 14",
    "sg:city":"Drunen",
    "sg:orig_category":"Technische Studies And Onderzoek",
    "sg:phone":"+31 416 379 391",
    "sg:postcode":"5151 SL",
    "sg:province":"Noord-Brabant",
    "wof:name":"Mateco Nv",
    "wof:placetype":"venue"
},
  "geometry": {"coordinates":[5.141431,51.683762],"type":"Point"}
}