{
  "type": "Feature",
  "properties": {
    "iso:country":"NL",
    "sg:address":"Allersmaweg 17",
    "sg:city":"Godlinze",
    "sg:orig_category":"Overheidsdiensten",
    "sg:phone":"+31 596 581 902",
    "sg:postcode":"9908 PD",
    "sg:province":"Groningen",
    "wof:name":"Vinkenhorst",
    "wof:placetype":"venue"
},
  "geometry": {"coordinates":[6.8120980263,53.3728904724],"type":"Point"}
}