{
  "type": "Feature",
  "properties": {
    "addr:full":"De Maas 2 Best Texas 5684 PL",
    "addr:housenumber":"2",
    "addr:postcode":"5684 pl",
    "addr:street":"De Maas",
    "iso:country":"NL",
    "sg:address":"De Maas 2",
    "sg:city":"Best",
    "sg:classifiers":[
        {
            "category":"Travel",
            "subcategory":"Hotels & Motels",
            "type":"Entertainment"
        }
    ],
    "sg:phone":"+31 499 390 100",
    "sg:postcode":"5684 PL",
    "sg:province":"Texas",
    "sg:website":"http://www.nh-hotels.com",
    "wof:name":"Nh Best",
    "wof:placetype":"venue"
},
  "geometry": {"coordinates":[-101.45208700000001,31.191275],"type":"Point"}
}