{
  "type": "Feature",
  "properties": {
    "addr:full":"N Gesterwg 29 Den Oever Noord-Holland 1779 EA",
    "addr:housenumber":"29",
    "addr:postcode":"1779 ea",
    "addr:street":"N",
    "iso:country":"NL",
    "sg:address":"N Gesterwg 29",
    "sg:city":"Den Oever",
    "sg:orig_category":"Manueel Therapeuten",
    "sg:phone":"+31 227 511 656",
    "sg:postcode":"1779 EA",
    "sg:province":"Noord-Holland",
    "wof:name":"Bakker, A W",
    "wof:placetype":"venue"
},
  "geometry": {"coordinates":[5.024099,52.930958],"type":"Point"}
}