{
  "type": "Feature",
  "properties": {
    "addr:full":"De Sonman 9 Moergestel North Brabant 5066 GJ",
    "addr:housenumber":"9",
    "addr:postcode":"5066 gj",
    "addr:street":"De Sonman",
    "iso:country":"NL",
    "sg:address":"De Sonman 9",
    "sg:city":"Moergestel",
    "sg:orig_category":"Autokeuringen",
    "sg:phone":"+31 13 513 3537",
    "sg:postcode":"5066 GJ",
    "sg:province":"North Brabant",
    "wof:name":"Donkers Autoschade",
    "wof:placetype":"venue"
},
  "geometry": {"coordinates":[5.177446,51.537586],"type":"Point"}
}