{
  "type": "Feature",
  "properties": {
    "addr:full":"Anna Van Burenlaan 22 Alphen A/D Rijn South Holland 2404 GM",
    "addr:housenumber":"22",
    "addr:postcode":"2404 gm",
    "addr:street":"Anna Van Burenlaan",
    "iso:country":"NL",
    "sg:address":"Anna Van Burenlaan 22",
    "sg:city":"Alphen A/D Rijn",
    "sg:orig_category":"Kinderopvang Behalve Thuis",
    "sg:phone":"+31 172 494 151",
    "sg:postcode":"2404 GM",
    "sg:province":"South Holland",
    "wof:name":"Katrijn Kinderdagverblijf",
    "wof:placetype":"venue"
},
  "geometry": {"coordinates":[4.654014,52.133038],"type":"Point"}
}