{
  "type": "Feature",
  "properties": {
    "addr:full":"J V Gelderstr 11 Hellevoetsluis South Holland 3223 SC",
    "addr:housenumber":"11",
    "addr:postcode":"3223 sc",
    "addr:street":"J;Gelderstr",
    "iso:country":"NL",
    "sg:address":"J V Gelderstr 11",
    "sg:city":"Hellevoetsluis",
    "sg:orig_category":"Verzekeringen - Verzekeringskantoren",
    "sg:phone":"+31 181 323 220",
    "sg:postcode":"3223 SC",
    "sg:province":"South Holland",
    "wof:name":"Staetelande Adviesgroep",
    "wof:placetype":"venue"
},
  "geometry": {"coordinates":[4.14703,51.830406],"type":"Point"}
}