{
  "type": "Feature",
  "properties": {
    "iso:country":"NL",
    "sg:address":"Stationswg 3",
    "sg:city":"Groningen",
    "sg:classifiers":[
        {
            "category":"Education",
            "subcategory":"Special Training",
            "type":"Public Place"
        }
    ],
    "sg:phone":"+31 50 588 8666",
    "sg:postcode":"9726 AC",
    "sg:province":"Groningen",
    "sg:tags":[
        "expertise"
    ],
    "wof:name":"Risk Consultants Bv",
    "wof:placetype":"venue"
},
  "geometry": {"coordinates":[6.569485,53.211884],"type":"Point"}
}