{
  "type": "Feature",
  "properties": {
    "iso:country":"NL",
    "sg:address":"Galvanistraat 10",
    "sg:city":"Heerhugowaard",
    "sg:orig_category":"Goederenvervoer Over De Weg",
    "sg:phone":"+31 72 572 2413",
    "sg:postcode":"1704 ST",
    "sg:province":"Noord-Holland",
    "wof:name":"D Kuiper - Kraanverhuur En Transport",
    "wof:placetype":"venue"
},
  "geometry": {"coordinates":[4.837869,52.687992],"type":"Point"}
}