{
  "type": "Feature",
  "properties": {
    "addr:full":"De Hennepe 523 Tiel Gelderland 4003 BH",
    "addr:housenumber":"523",
    "addr:postcode":"4003 bh",
    "addr:street":"De Hennepe;Gelderland",
    "iso:country":"NL",
    "sg:address":"De Hennepe 523",
    "sg:city":"Tiel",
    "sg:orig_category":"Loodgieterswerk, Verwarming And Sanitaire Installaties",
    "sg:phone":"+31 6 21586461",
    "sg:postcode":"4003 BH",
    "sg:province":"Gelderland",
    "wof:name":"Pons",
    "wof:placetype":"venue"
},
  "geometry": {"coordinates":[5.433615,51.89851],"type":"Point"}
}