{
  "type": "Feature",
  "properties": {
    "addr:full":"De Schans 20 Leek Groningen 9351 AZ",
    "addr:housenumber":"20",
    "addr:postcode":"9351 az",
    "addr:street":"De Schans",
    "iso:country":"NL",
    "sg:address":"De Schans 20",
    "sg:city":"Leek",
    "sg:orig_category":"Bloemen And Planten",
    "sg:phone":"+31 594 514 007",
    "sg:postcode":"9351 AZ",
    "sg:province":"Groningen",
    "wof:name":"Topfleur",
    "wof:placetype":"venue"
},
  "geometry": {"coordinates":[6.390986,53.161324],"type":"Point"}
}