{
  "type": "Feature",
  "properties": {
    "iso:country":"NL",
    "sg:address":"Nw Ebbingestr 40",
    "sg:city":"Groningen",
    "sg:orig_category":"Horloges En Klokken",
    "sg:phone":"+31 50 312 9055",
    "sg:postcode":"9712 NL",
    "sg:province":"Groningen",
    "wof:name":"Gabry'S Klokken",
    "wof:placetype":"venue"
},
  "geometry": {"coordinates":[6.563655,53.223347],"type":"Point"}
}