{
  "type": "Feature",
  "properties": {
    "addr:full":"Damwg 53 Zwartebroek Gelderland 3785 LJ",
    "addr:housenumber":"53;lj",
    "addr:postcode":"3785",
    "addr:street":"Damwg;Gelderland",
    "iso:country":"NL",
    "sg:address":"Damwg 53",
    "sg:city":"Zwartebroek",
    "sg:orig_category":"Levensmiddelen - Fabrieken En Groothandel",
    "sg:phone":"+31 342 461 232",
    "sg:postcode":"3785 LJ",
    "sg:province":"Gelderland",
    "wof:name":"Veen Zwartebroek Bv, Van",
    "wof:placetype":"venue"
},
  "geometry": {"coordinates":[5.499048,52.183079],"type":"Point"}
}