{
  "type": "Feature",
  "properties": {
    "addr:full":"Zoete Inval 8 Breda Noord-Brabant 4815 HK",
    "addr:housenumber":"8",
    "addr:postcode":"4815 hk",
    "addr:street":"Zoete Inval",
    "iso:country":"NL",
    "sg:address":"Zoete Inval 8",
    "sg:city":"Breda",
    "sg:classifiers":[
        {
            "category":"Retail",
            "subcategory":"Storage",
            "type":"Services"
        }
    ],
    "sg:phone":"+31 76 530 6100",
    "sg:postcode":"4815 HK",
    "sg:province":"Noord-Brabant",
    "sg:tags":[
        "opslag",
        "bewaring"
    ],
    "wof:name":"Fedex Supply Chain Services",
    "wof:placetype":"venue"
},
  "geometry": {"coordinates":[4.7607522011,51.5962333679],"type":"Point"}
}