{
  "type": "Feature",
  "properties": {
    "addr:full":"De Tuinen 35 Naaldwyk Zuid-Holland 2671 NX",
    "addr:housenumber":"35",
    "addr:postcode":"2671 nx",
    "addr:street":"De Tuinen",
    "iso:country":"NL",
    "sg:address":"De Tuinen 35",
    "sg:city":"Naaldwyk",
    "sg:orig_category":"Juweliers",
    "sg:phone":"+31 174 670 687",
    "sg:postcode":"2671 NX",
    "sg:province":"Zuid-Holland",
    "wof:name":"Lucardi",
    "wof:placetype":"venue"
},
  "geometry": {"coordinates":[4.205063,51.992676],"type":"Point"}
}