{
  "type": "Feature",
  "properties": {
    "iso:country":"NL",
    "sg:address":"Molenstr 15",
    "sg:city":"Rosmalen",
    "sg:orig_category":"Verloskundigen",
    "sg:phone":"+31 73 521 0764",
    "sg:postcode":"5242 HA",
    "sg:province":"Noord-Brabant",
    "wof:name":"Helvoirt, B Van",
    "wof:placetype":"venue"
},
  "geometry": {"coordinates":[5.361439,51.711178],"type":"Point"}
}