{
  "type": "Feature",
  "properties": {
    "addr:full":"Zelhorstwg 11 Vinkenbuurt NL.08 7739 PN",
    "addr:housenumber":"11;nl.08",
    "addr:postcode":"7739 pn",
    "addr:street":"Zelhorstwg",
    "iso:country":"NL",
    "sg:address":"Zelhorstwg 11",
    "sg:city":"Vinkenbuurt",
    "sg:orig_category":"Loonbedrijven",
    "sg:phone":"+31 523 649 380",
    "sg:postcode":"7739 PN",
    "sg:province":"NL.08",
    "wof:name":"Heetebrij, Fa",
    "wof:placetype":"venue"
},
  "geometry": {"coordinates":[6.357519,52.585033],"type":"Point"}
}