{
  "type": "Feature",
  "properties": {
    "addr:full":"Protonstr 9 Groningen Groningen 9743 AL",
    "addr:housenumber":"9",
    "addr:postcode":"9743 al",
    "addr:street":"Protonstr",
    "iso:country":"NL",
    "sg:address":"Protonstr 9",
    "sg:city":"Groningen",
    "sg:orig_category":"Horeca-Inrichtingen En -Uitrustingen",
    "sg:phone":"+31 50 318 1600",
    "sg:postcode":"9743 AL",
    "sg:province":"Groningen",
    "wof:name":"Hakvoort Noord Bv",
    "wof:placetype":"venue"
},
  "geometry": {"coordinates":[6.53499,53.215508],"type":"Point"}
}