{
  "type": "Feature",
  "properties": {
    "addr:full":"A Diepenbrockstr 7B Amersfoort Utrecht 3816 PJ",
    "addr:housenumber":"7b",
    "addr:postcode":"3816 pj",
    "iso:country":"NL",
    "sg:address":"A Diepenbrockstr 7B",
    "sg:city":"Amersfoort",
    "sg:orig_category":"Video - Faciliteiten En Producties",
    "sg:phone":"+31 33 472 1223",
    "sg:postcode":"3816 PJ",
    "sg:province":"Utrecht",
    "wof:name":"Sefthoen",
    "wof:placetype":"venue"
},
  "geometry": {"coordinates":[5.403746,52.154053],"type":"Point"}
}