{
  "type": "Feature",
  "properties": {
    "iso:country":"NL",
    "sg:address":"Burg Hoffmanpln 58A",
    "sg:city":"Rotterdam",
    "sg:orig_category":"Elektronica - Ontwikkeling En Groothandel",
    "sg:phone":"+31 10 414 1904",
    "sg:postcode":"3071 XM",
    "sg:province":"Zuid-Holland",
    "wof:name":"Digitron",
    "wof:placetype":"venue"
},
  "geometry": {"coordinates":[4.493995,51.912643],"type":"Point"}
}