{
  "type": "Feature",
  "properties": {
    "addr:full":"Terletstraat 141 Amsterdam Zuidoost North Holland 1107 RN",
    "addr:housenumber":"141",
    "addr:postcode":"1107 rn",
    "addr:street":"Terletstraat",
    "iso:country":"NL",
    "sg:address":"Terletstraat 141",
    "sg:city":"Amsterdam Zuidoost",
    "sg:orig_category":"Binnenhuisarchitecten",
    "sg:phone":"+31 20 697 0150",
    "sg:postcode":"1107 RN",
    "sg:province":"North Holland",
    "wof:name":"E. Gorter",
    "wof:placetype":"venue"
},
  "geometry": {"coordinates":[4.973287,52.294014],"type":"Point"}
}