{
  "type": "Feature",
  "properties": {
    "iso:country":"NL",
    "sg:address":"Dr V Deenwg 68",
    "sg:city":"Zwolle",
    "sg:orig_category":"Arbo- En Bedrijfsgezondheids- Diensten",
    "sg:phone":"+31 38 452 6540",
    "sg:postcode":"8025 BD",
    "sg:province":"Overijssel",
    "wof:name":"Laic Zwolle",
    "wof:placetype":"venue"
},
  "geometry": {"coordinates":[6.12659,52.51054],"type":"Point"}
}