{
  "type": "Feature",
  "properties": {
    "addr:full":"Markt 19 Eindhoven Noord-Brabant 5611 EC",
    "addr:housenumber":"19",
    "addr:postcode":"5611 ec",
    "addr:street":"Markt",
    "iso:country":"NL",
    "sg:address":"Markt 19",
    "sg:city":"Eindhoven",
    "sg:classifiers":[
        {
            "category":"Fast Food",
            "type":"Food & Drink"
        }
    ],
    "sg:phone":"+31 40 244 5858",
    "sg:postcode":"5611 EC",
    "sg:province":"Noord-Brabant",
    "sg:tags":[
        "afhaal",
        "restaurant"
    ],
    "wof:name":"Cafetaria Le Marche",
    "wof:placetype":"venue"
},
  "geometry": {"coordinates":[5.478201,51.439014],"type":"Point"}
}