{
  "type": "Feature",
  "properties": {
    "addr:full":"Stormpolderdk 4-C Krimpen Ad Yssel Zuid-Holland 2921 LL",
    "addr:housenumber":"4-c;2921",
    "addr:postcode":"ll",
    "addr:street":"Stormpolderdk",
    "iso:country":"NL",
    "sg:address":"Stormpolderdk 4-C",
    "sg:city":"Krimpen Ad Yssel",
    "sg:orig_category":"Woninginrichting",
    "sg:phone":"+31 180 554 890",
    "sg:postcode":"2921 LL",
    "sg:province":"Zuid-Holland",
    "sg:website":"http://www.verschoor-tapijt.nl",
    "wof:name":"Verschoor, W & E",
    "wof:placetype":"venue"
},
  "geometry": {"coordinates":[4.5800051689,51.9104309082],"type":"Point"}
}