{
  "type": "Feature",
  "properties": {
    "addr:full":"Achterweg 11 Noordwijk Zh South Holland 2201 AH",
    "addr:housenumber":"11",
    "addr:postcode":"zh;2201 ah",
    "addr:street":"Achterweg",
    "iso:country":"NL",
    "sg:address":"Achterweg 11",
    "sg:city":"Noordwijk Zh",
    "sg:orig_category":"Overheidsdiensten",
    "sg:phone":"+31 71 361 4290",
    "sg:postcode":"2201 AH",
    "sg:province":"South Holland",
    "wof:name":"Hoogheemraadschap Van Rijnland",
    "wof:placetype":"venue"
},
  "geometry": {"coordinates":[4.4477038383,52.2342681885],"type":"Point"}
}