{
  "type": "Feature",
  "properties": {
    "addr:full":"Klappolder 105 Bleiswijk South Holland 2665 LP",
    "addr:housenumber":"105",
    "addr:postcode":"2665 lp",
    "addr:street":"Klappolder",
    "iso:country":"NL",
    "sg:address":"Klappolder 105",
    "sg:city":"Bleiswijk",
    "sg:orig_category":"Fruit And Groenten Gh",
    "sg:phone":"+31 10 521 8477",
    "sg:postcode":"2665 LP",
    "sg:province":"South Holland",
    "wof:name":"K. Olieman Export Bv",
    "wof:placetype":"venue"
},
  "geometry": {"coordinates":[4.541719,52.028095],"type":"Point"}
}