{
  "type": "Feature",
  "properties": {
    "addr:full":"Past Doensstr 5 Bavel Noord-Brabant 4854 CP",
    "addr:housenumber":"5",
    "addr:postcode":"4854 cp",
    "iso:country":"NL",
    "sg:address":"Past Doensstr 5",
    "sg:city":"Bavel",
    "sg:orig_category":"Peuterspeelzalen",
    "sg:phone":"+31 161 432 557",
    "sg:postcode":"4854 CP",
    "sg:province":"Noord-Brabant",
    "wof:name":"Humpie Dumpie",
    "wof:placetype":"venue"
},
  "geometry": {"coordinates":[4.832036,51.56723],"type":"Point"}
}