{
  "type": "Feature",
  "properties": {
    "iso:country":"NL",
    "sg:address":"Kon Wilhelminapln 13",
    "sg:city":"Amsterdam",
    "sg:orig_category":"Mode Artikelen Dames En Heren - Fabrieken En Groothandel",
    "sg:phone":"+31 20 617 9592",
    "sg:postcode":"1062 HH",
    "sg:province":"Noord-Holland",
    "wof:name":"Robako Bv",
    "wof:placetype":"venue"
},
  "geometry": {"coordinates":[4.840918,52.354782],"type":"Point"}
}