{
  "type": "Feature",
  "properties": {
    "addr:full":"Vermeerstr 35 Zoetermeer Zuid-Holland 2712 SR",
    "addr:housenumber":"35",
    "addr:postcode":"2712 sr",
    "addr:street":"Vermeerstr",
    "iso:country":"NL",
    "sg:address":"Vermeerstr 35",
    "sg:city":"Zoetermeer",
    "sg:orig_category":"Woningstoffeerders",
    "sg:phone":"+31 79 316 0055",
    "sg:postcode":"2712 SR",
    "sg:province":"Zuid-Holland",
    "wof:name":"Windmeijer, W G",
    "wof:placetype":"venue"
},
  "geometry": {"coordinates":[4.4998631477,52.0502853394],"type":"Point"}
}