{
  "type": "Feature",
  "properties": {
    "iso:country":"NL",
    "sg:address":"Het Rond 6",
    "sg:city":"Zeist",
    "sg:orig_category":"Postkantoren",
    "sg:phone":"+31 30 692 3284",
    "sg:postcode":"3701 HS",
    "sg:province":"Utrecht",
    "sg:website":"http://www.postkantoor.nl",
    "wof:name":"Postkantoor",
    "wof:placetype":"venue"
},
  "geometry": {"coordinates":[5.238363,52.081306],"type":"Point"}
}