{
  "type": "Feature",
  "properties": {
    "addr:full":"Nieuwe Steen 1 Hoorn Nh Noord-Holland 1625 HV",
    "addr:housenumber":"1",
    "addr:postcode":"1625 hv",
    "addr:street":"Nieuwe Steen",
    "iso:country":"NL",
    "sg:address":"Nieuwe Steen 1",
    "sg:city":"Hoorn Nh",
    "sg:orig_category":"Overheidsdiensten",
    "sg:phone":"+31 229 252 200",
    "sg:postcode":"1625 HV",
    "sg:province":"Noord-Holland",
    "wof:name":"Sector Maatschappelijke Aangelegenheden",
    "wof:placetype":"venue"
},
  "geometry": {"coordinates":[5.0656700134,52.6545715332],"type":"Point"}
}