{
  "type": "Feature",
  "properties": {
    "addr:full":"Gudumholm 42 Hoofddorp Noord-Holland 2133 HH",
    "addr:housenumber":"42",
    "addr:postcode":"2133 hh",
    "addr:street":"Gudumholm",
    "iso:country":"NL",
    "sg:address":"Gudumholm 42",
    "sg:city":"Hoofddorp",
    "sg:orig_category":"Bedrijfsopleidingen",
    "sg:phone":"+31 23 562 9513",
    "sg:postcode":"2133 HH",
    "sg:province":"Noord-Holland",
    "wof:name":"Blom, Jasper",
    "wof:placetype":"venue"
},
  "geometry": {"coordinates":[4.668601,52.312382],"type":"Point"}
}