{
  "type": "Feature",
  "properties": {
    "addr:full":"Wierdensewg 18 Vriezenveen Overijssel 7671 JK",
    "addr:housenumber":"18",
    "addr:postcode":"7671 jk",
    "addr:street":"Wierdensewg",
    "iso:country":"NL",
    "sg:address":"Wierdensewg 18",
    "sg:city":"Vriezenveen",
    "sg:orig_category":"Accountants - Administratie- Consulenten En -Kantoren",
    "sg:phone":"+31 546 564 545",
    "sg:postcode":"7671 JK",
    "sg:province":"Overijssel",
    "wof:name":"Jong & Laan, De",
    "wof:placetype":"venue"
},
  "geometry": {"coordinates":[6.601541,52.401333],"type":"Point"}
}