{
  "type": "Feature",
  "properties": {
    "addr:full":"Eikesngl 17 Drachten Friesland 9203 NW",
    "addr:housenumber":"17",
    "addr:postcode":"9203 nw",
    "addr:street":"Eikesngl",
    "iso:country":"NL",
    "sg:address":"Eikesngl 17",
    "sg:city":"Drachten",
    "sg:orig_category":"Fotojournalisten Freelance",
    "sg:phone":"+31 512 546 521",
    "sg:postcode":"9203 NW",
    "sg:province":"Friesland",
    "wof:name":"Wilstra, Willem",
    "wof:placetype":"venue"
},
  "geometry": {"coordinates":[6.098565,53.102871],"type":"Point"}
}