{
  "type": "Feature",
  "properties": {
    "iso:country":"NL",
    "sg:address":"Randerstr 34A",
    "sg:city":"Diepenveen",
    "sg:classifiers":[
        {
            "category":"Sports & Exercise",
            "subcategory":"Stables",
            "type":"Entertainment"
        }
    ],
    "sg:phone":"+31 570 592 957",
    "sg:postcode":"7431 PS",
    "sg:province":"Overijssel",
    "sg:tags":[
        "maneges"
    ],
    "wof:name":"Veldhuus",
    "wof:placetype":"venue"
},
  "geometry": {"coordinates":[6.156725,52.301018],"type":"Point"}
}