{
  "type": "Feature",
  "properties": {
    "addr:full":"Hertogstraat 1 Nijmegen Gelderland 6511 RV",
    "addr:housenumber":"1",
    "addr:postcode":"6511 rv",
    "addr:street":"Hertogstraat;Gelderland",
    "iso:country":"NL",
    "sg:address":"Hertogstraat 1",
    "sg:city":"Nijmegen",
    "sg:classifiers":[
        {
            "category":"Travel",
            "subcategory":"Hotels & Motels",
            "type":"Entertainment"
        }
    ],
    "sg:phone":"+31 24 322 0498",
    "sg:postcode":"6511 RV",
    "sg:province":"Gelderland",
    "wof:name":"City-Park Hotel",
    "wof:placetype":"venue"
},
  "geometry": {"coordinates":[5.869243,51.846432],"type":"Point"}
}