{
  "type": "Feature",
  "properties": {
    "iso:country":"NL",
    "sg:address":"Nieuwe Ebbingestraat 102",
    "sg:city":"Groningen",
    "sg:orig_category":"Verlichting And Huishoudartikelen",
    "sg:phone":"+31 50 313 2137",
    "sg:postcode":"9712 NP",
    "sg:province":"Groningen",
    "wof:name":"Blokker",
    "wof:placetype":"venue"
},
  "geometry": {"coordinates":[6.561047,53.225899],"type":"Point"}
}