{
  "type": "Feature",
  "properties": {
    "iso:country":"NL",
    "sg:address":"Bosberg 8",
    "sg:city":"Borculo",
    "sg:orig_category":"Oldtimers",
    "sg:phone":"+31 545 294 435",
    "sg:postcode":"7271 LG",
    "sg:province":"Gelderland",
    "wof:name":"Citro Classique",
    "wof:placetype":"venue"
},
  "geometry": {"coordinates":[6.534966,52.123379],"type":"Point"}
}