{
  "type": "Feature",
  "properties": {
    "iso:country":"NL",
    "sg:address":"Hoonaartstr 70",
    "sg:city":"Hellevoetsluis",
    "sg:orig_category":"Verzekeringen - Verzekeringskantoren",
    "sg:phone":"+31 181 312 143",
    "sg:postcode":"3222 CL",
    "sg:province":"South Holland",
    "wof:name":"Sintmaartensdijk, Van",
    "wof:placetype":"venue"
},
  "geometry": {"coordinates":[4.131279,51.836266],"type":"Point"}
}