{
  "type": "Feature",
  "properties": {
    "addr:full":"O L Vrouwepln 16 Maastricht Limburg 6211 HE",
    "addr:housenumber":"16",
    "addr:postcode":"6211 he",
    "addr:street":"O",
    "iso:country":"NL",
    "sg:address":"O L Vrouwepln 16",
    "sg:city":"Maastricht",
    "sg:orig_category":"Kopieerservice",
    "sg:phone":"+31 43 325 7505",
    "sg:postcode":"6211 HE",
    "sg:province":"Limburg",
    "wof:name":"Kopi\u00eberder, De",
    "wof:placetype":"venue"
},
  "geometry": {"coordinates":[5.693809,50.846951],"type":"Point"}
}