{
  "type": "Feature",
  "properties": {
    "iso:country":"NL",
    "sg:address":"Dorpsstr 62",
    "sg:city":"Benthuizen",
    "sg:orig_category":"Hengelsportartikelen - Fabrieken En Groothandel",
    "sg:phone":"+31 79 361 8229",
    "sg:postcode":"2731 AR",
    "sg:province":"Zuid-Holland",
    "wof:name":"Omega",
    "wof:placetype":"venue"
},
  "geometry": {"coordinates":[4.541441,52.077271],"type":"Point"}
}