{
  "type": "Feature",
  "properties": {
    "addr:full":"De Beemden 1 Liempde Noord-Brabant 5298 VT",
    "addr:housenumber":"1",
    "addr:postcode":"5298",
    "addr:street":"De Beemden",
    "iso:country":"NL",
    "sg:address":"De Beemden 1",
    "sg:city":"Liempde",
    "sg:orig_category":"Verzekeringen - Verzekeringskantoren",
    "sg:phone":"+31 411 631 536",
    "sg:postcode":"5298 VT",
    "sg:province":"Noord-Brabant",
    "wof:name":"Savante",
    "wof:placetype":"venue"
},
  "geometry": {"coordinates":[5.359342,51.5774],"type":"Point"}
}