{
  "type": "Feature",
  "properties": {
    "addr:full":"Blauwkapelsewg 123 Utrecht Utrecht 3572 KE",
    "addr:housenumber":"123",
    "addr:postcode":"3572 ke",
    "iso:country":"NL",
    "sg:address":"Blauwkapelsewg 123",
    "sg:city":"Utrecht",
    "sg:orig_category":"Autorijscholen",
    "sg:phone":"+31 30 272 1545",
    "sg:postcode":"3572 KE",
    "sg:province":"Utrecht",
    "wof:name":"Randstad",
    "wof:placetype":"venue"
},
  "geometry": {"coordinates":[5.130328,52.102577],"type":"Point"}
}