{
  "type": "Feature",
  "properties": {
    "addr:full":"Wolphaertsbocht 296 Rotterdam South Holland 3081 KR",
    "addr:housenumber":"296",
    "addr:postcode":"3081 kr",
    "addr:street":"Wolphaertsbocht",
    "iso:country":"NL",
    "sg:address":"Wolphaertsbocht 296",
    "sg:city":"Rotterdam",
    "sg:classifiers":[
        {
            "category":"Fast Food",
            "type":"Food & Drink"
        }
    ],
    "sg:phone":"+31 10 484 6936",
    "sg:postcode":"3081 KR",
    "sg:province":"South Holland",
    "sg:tags":[
        "afhaal",
        "restaurant"
    ],
    "wof:name":"Snackbar Birsen",
    "wof:placetype":"venue"
},
  "geometry": {"coordinates":[4.479641,51.892216],"type":"Point"}
}