{
  "type": "Feature",
  "properties": {
    "addr:full":"Ketelstraat 101 'S Gravenhage South Holland 2516 VN",
    "addr:housenumber":"101 '",
    "addr:postcode":"2516 vn",
    "addr:street":"Ketelstraat",
    "iso:country":"NL",
    "sg:address":"Ketelstraat 101",
    "sg:city":"'S Gravenhage",
    "sg:classifiers":[
        {
            "category":"Education",
            "subcategory":"Preschool",
            "type":"Public Place"
        }
    ],
    "sg:phone":"+31 70 415 2531",
    "sg:postcode":"2516 VN",
    "sg:province":"South Holland",
    "sg:tags":[
        "kleuteronderwijs",
        "basis-"
    ],
    "wof:name":"Openbare Basisschool De Kameleon",
    "wof:placetype":"venue"
},
  "geometry": {"coordinates":[4.337957,52.062778],"type":"Point"}
}