{
  "type": "Feature",
  "properties": {
    "addr:full":"Grenswg 1 Siebengewald North Rhine-Westphalia 5853 EN",
    "addr:housenumber":"1",
    "addr:postcode":"5853 en",
    "addr:street":"Grenswg",
    "iso:country":"NL",
    "sg:address":"Grenswg 1",
    "sg:city":"Siebengewald",
    "sg:orig_category":"Grondwerken",
    "sg:phone":"+31 485 441 871",
    "sg:postcode":"5853 EN",
    "sg:province":"North Rhine-Westphalia",
    "wof:name":"Hees, Van",
    "wof:placetype":"venue"
},
  "geometry": {"coordinates":[6.060649,51.665161],"type":"Point"}
}