{
  "type": "Feature",
  "properties": {
    "addr:full":"Achtergracht 2 Amsterdam Noord-Holland 1017 WP",
    "addr:housenumber":"2",
    "addr:postcode":"1017 wp",
    "addr:street":"Achtergracht",
    "iso:country":"NL",
    "sg:address":"Achtergracht 2",
    "sg:city":"Amsterdam",
    "sg:orig_category":"Kinderopvang Behalve Thuis",
    "sg:phone":"+31 20 622 1417",
    "sg:postcode":"1017 WP",
    "sg:province":"Noord-Holland",
    "wof:name":"Kinderdagverblijf Zon St Uk",
    "wof:placetype":"venue"
},
  "geometry": {"coordinates":[4.901412,52.361027],"type":"Point"}
}