{
  "type": "Feature",
  "properties": {
    "addr:full":"Baarnsche Dijk 21 Baarn Utrecht 3741 LP",
    "addr:housenumber":"21",
    "addr:postcode":"3741 lp",
    "addr:street":"Baarnsche Dijk",
    "iso:country":"NL",
    "sg:address":"Baarnsche Dijk 21",
    "sg:city":"Baarn",
    "sg:orig_category":"Diverse Grafische Activiteiten",
    "sg:phone":"+31 35 541 4222",
    "sg:postcode":"3741 LP",
    "sg:province":"Utrecht",
    "wof:name":"Pre Press Bv",
    "wof:placetype":"venue"
},
  "geometry": {"coordinates":[5.300673,52.217987],"type":"Point"}
}