{
  "type": "Feature",
  "properties": {
    "addr:full":"P De Gorterstr 2 Rosmalen Noord-Brabant 5248 NS",
    "addr:housenumber":"2",
    "addr:postcode":"5248 ns",
    "addr:street":"P;Gorterstr",
    "iso:country":"NL",
    "sg:address":"P De Gorterstr 2",
    "sg:city":"Rosmalen",
    "sg:orig_category":"Verenigingen En Stichtingen",
    "sg:phone":"+31 73 521 1215",
    "sg:postcode":"5248 NS",
    "sg:province":"Noord-Brabant",
    "wof:name":"Vluchtelingenwerk Azc Rosmalen, Sticht",
    "wof:placetype":"venue"
},
  "geometry": {"coordinates":[5.375843,51.704525],"type":"Point"}
}