{
  "type": "Feature",
  "properties": {
    "addr:full":"Boerestreek 41 Ureterp Friesland 9247 CB",
    "addr:housenumber":"41",
    "addr:postcode":"9247 cb",
    "addr:street":"Boerestreek",
    "iso:country":"NL",
    "sg:address":"Boerestreek 41",
    "sg:city":"Ureterp",
    "sg:orig_category":"Warenhuizen",
    "sg:phone":"+31 512 301 431",
    "sg:postcode":"9247 CB",
    "sg:province":"Friesland",
    "wof:name":"Firma Dijk",
    "wof:placetype":"venue"
},
  "geometry": {"coordinates":[6.1903138161,53.0951271057],"type":"Point"}
}