{
  "type": "Feature",
  "properties": {
    "addr:full":"Keizersdk 71 Raamsdonksveer Noord-Brabant 4941 GD",
    "addr:housenumber":"71",
    "addr:postcode":"4941 gd",
    "addr:street":"Keizersdk",
    "iso:country":"NL",
    "sg:address":"Keizersdk 71",
    "sg:city":"Raamsdonksveer",
    "sg:orig_category":"Woninginrichting",
    "sg:phone":"+31 162 512 833",
    "sg:postcode":"4941 GD",
    "sg:province":"Noord-Brabant",
    "wof:name":"Decorette",
    "wof:placetype":"venue"
},
  "geometry": {"coordinates":[4.872262001,51.6984863281],"type":"Point"}
}