{
  "type": "Feature",
  "properties": {
    "iso:country":"NL",
    "sg:address":"Helmersstr 11",
    "sg:city":"Zandvoort",
    "sg:orig_category":"Verzekeringen - Verzekeringskantoren",
    "sg:phone":"+31 23 571 2150",
    "sg:postcode":"2041 PE",
    "sg:province":"Noord-Holland",
    "wof:name":"Zandvoortse Verzekering Service",
    "wof:placetype":"venue"
},
  "geometry": {"coordinates":[4.537983,52.375912],"type":"Point"}
}