{
  "type": "Feature",
  "properties": {
    "iso:country":"NL",
    "sg:address":"Stationstraat 282",
    "sg:city":"Nuth",
    "sg:classifiers":[
        {
            "category":"Retail",
            "subcategory":"Photofinishing",
            "type":"Services"
        }
    ],
    "sg:phone":"+31 45 524 1238",
    "sg:postcode":"6361 BH",
    "sg:province":"Limburg",
    "sg:tags":[
        "foto",
        "film"
    ],
    "wof:name":"Vinken & Rade Vakfotografie",
    "wof:placetype":"venue"
},
  "geometry": {"coordinates":[5.885999,50.918785],"type":"Point"}
}