{
  "type": "Feature",
  "properties": {
    "iso:country":"NL",
    "sg:address":"Kattebos 83",
    "sg:city":"Heerenveen",
    "sg:orig_category":"Verhuur Audiovisuele Apparatuur",
    "sg:phone":"+31 513 615 191",
    "sg:postcode":"8446 CP",
    "sg:province":"Friesland",
    "wof:name":"Frans Wajon Professionele Geluidstechniek",
    "wof:placetype":"venue"
},
  "geometry": {"coordinates":[5.914472,52.950195],"type":"Point"}
}