{
  "type": "Feature",
  "properties": {
    "addr:full":"Noorddammerwg 76A Amstelveen Noord-Holland 1187 ZT",
    "addr:housenumber":"76a",
    "addr:postcode":"1187 zt",
    "addr:street":"Noorddammerwg",
    "iso:country":"NL",
    "sg:address":"Noorddammerwg 76A",
    "sg:city":"Amstelveen",
    "sg:orig_category":"Bloemen En Planten - Groothandel",
    "sg:phone":"+31 20 645 8419",
    "sg:postcode":"1187 ZT",
    "sg:province":"Noord-Holland",
    "wof:name":"Meilland Selectie Bv",
    "wof:placetype":"venue"
},
  "geometry": {"coordinates":[4.820715,52.274921],"type":"Point"}
}