{
  "type": "Feature",
  "properties": {
    "addr:full":"Wyenwg 145 Brunssum Limburg 6446 AK",
    "addr:housenumber":"145",
    "addr:postcode":"6446 ak",
    "addr:street":"Brunssum Limburg",
    "iso:country":"NL",
    "sg:address":"Wyenwg 145",
    "sg:city":"Brunssum",
    "sg:orig_category":"Kappers",
    "sg:phone":"+31 45 521 4551",
    "sg:postcode":"6446 AK",
    "sg:province":"Limburg",
    "wof:name":"Kitty",
    "wof:placetype":"venue"
},
  "geometry": {"coordinates":[5.9702329636,50.9433021545],"type":"Point"}
}