{
  "type": "Feature",
  "properties": {
    "addr:full":"Westerweg 73 Heiloo Noord-Holland 1852 AA",
    "addr:housenumber":"73",
    "addr:postcode":"1852 aa",
    "addr:street":"Westerweg",
    "iso:country":"NL",
    "sg:address":"Westerweg 73",
    "sg:city":"Heiloo",
    "sg:orig_category":"Kantoorartikelen",
    "sg:phone":"+31 72 533 8277",
    "sg:postcode":"1852 AA",
    "sg:province":"Noord-Holland",
    "wof:name":"C. Becker",
    "wof:placetype":"venue"
},
  "geometry": {"coordinates":[4.7080540657,52.6086502075],"type":"Point"}
}