{
  "type": "Feature",
  "properties": {
    "addr:full":"Rozenstraat 41 Zeist Utrecht 3702 VM",
    "addr:housenumber":"41",
    "addr:postcode":"3702 vm",
    "addr:street":"Rozenstraat",
    "iso:country":"NL",
    "sg:address":"Rozenstraat 41",
    "sg:city":"Zeist",
    "sg:classifiers":[
        {
            "category":"Fast Food",
            "type":"Food & Drink"
        }
    ],
    "sg:phone":"+31 30 691 8220",
    "sg:postcode":"3702 VM",
    "sg:province":"Utrecht",
    "sg:tags":[
        "afhaal",
        "restaurant"
    ],
    "wof:name":"Cafetaria De Corner",
    "wof:placetype":"venue"
},
  "geometry": {"coordinates":[5.237225,52.089634],"type":"Point"}
}