{
  "type": "Feature",
  "properties": {
    "addr:full":"Vinkenburgstraat 9 Utrecht Utrecht 3512 AA",
    "addr:housenumber":"9",
    "addr:postcode":"3512 aa",
    "addr:street":"Vinkenburgstraat",
    "iso:country":"NL",
    "sg:address":"Vinkenburgstraat 9",
    "sg:city":"Utrecht",
    "sg:orig_category":"Kappers",
    "sg:phone":"+31 30 231 8749",
    "sg:postcode":"3512 AA",
    "sg:province":"Utrecht",
    "wof:name":"Haarstudio Bobby'S",
    "wof:placetype":"venue"
},
  "geometry": {"coordinates":[5.1179909706,52.0922088623],"type":"Point"}
}