{
  "type": "Feature",
  "properties": {
    "addr:full":"G V Prinstererstr 186 Vlaardingen South Holland 3131 GJ",
    "addr:housenumber":"186",
    "addr:postcode":"3131 gj",
    "addr:street":"V Prinstererstr",
    "iso:country":"NL",
    "sg:address":"G V Prinstererstr 186",
    "sg:city":"Vlaardingen",
    "sg:orig_category":"Fotografie Reclame En Mode",
    "sg:phone":"+31 10 460 3773",
    "sg:postcode":"3131 GJ",
    "sg:province":"South Holland",
    "sg:website":"http://www.glamourphoto.nl",
    "wof:name":"Gelder, Anthony Van",
    "wof:placetype":"venue"
},
  "geometry": {"coordinates":[4.340359,51.910442],"type":"Point"}
}