{
  "type": "Feature",
  "properties": {
    "addr:full":"Amersfoortsewg 205 Uddel Gelderland 3888 NM",
    "addr:housenumber":"205",
    "addr:postcode":"3888",
    "addr:street":"Gelderland",
    "iso:country":"NL",
    "sg:address":"Amersfoortsewg 205",
    "sg:city":"Uddel",
    "sg:orig_category":"Motorzagen",
    "sg:phone":"+31 577 456 561",
    "sg:postcode":"3888 NM",
    "sg:province":"Gelderland",
    "sg:website":"http://www.poelbosbouw.nl",
    "wof:name":"Poel",
    "wof:placetype":"venue"
},
  "geometry": {"coordinates":[5.808656,52.22205],"type":"Point"}
}