{
  "type": "Feature",
  "properties": {
    "addr:full":"Leigraaf 48 Twello Gelderland 7391 AL",
    "addr:housenumber":"48",
    "addr:postcode":"7391",
    "addr:street":"Leigraaf;Gelderland",
    "iso:country":"NL",
    "sg:address":"Leigraaf 48",
    "sg:city":"Twello",
    "sg:orig_category":"Autokeuringen",
    "sg:phone":"+31 571 272 342",
    "sg:postcode":"7391 AL",
    "sg:province":"Gelderland",
    "wof:name":"Hans Bakker",
    "wof:placetype":"venue"
},
  "geometry": {"coordinates":[6.088427,52.221272],"type":"Point"}
}