{
  "type": "Feature",
  "properties": {
    "addr:full":"Ruigebol 11 Koog Aan De Zaan Noord-Holland 1541 WS",
    "addr:housenumber":"11",
    "addr:postcode":"1541 ws",
    "addr:street":"Ruigebol",
    "iso:country":"NL",
    "sg:address":"Ruigebol 11",
    "sg:city":"Koog Aan De Zaan",
    "sg:orig_category":"Autorijscholen",
    "sg:phone":"+31 75 615 6104",
    "sg:postcode":"1541 WS",
    "sg:province":"Noord-Holland",
    "sg:website":"http://www.westerkoog.nu",
    "wof:name":"Westerkoog, Autorijschool",
    "wof:placetype":"venue"
},
  "geometry": {"coordinates":[4.795108,52.457657],"type":"Point"}
}