{
  "type": "Feature",
  "properties": {
    "addr:full":"Asschatterwg 223 Leusden Utrecht 3831 JP",
    "addr:housenumber":"223",
    "addr:postcode":"3831 jp",
    "iso:country":"NL",
    "sg:address":"Asschatterwg 223",
    "sg:city":"Leusden",
    "sg:orig_category":"Loonbedrijven",
    "sg:phone":"+31 6 22970077",
    "sg:postcode":"3831 JP",
    "sg:province":"Utrecht",
    "wof:name":"Kruyf, M De",
    "wof:placetype":"venue"
},
  "geometry": {"coordinates":[5.471774,52.130096],"type":"Point"}
}