{
  "type": "Feature",
  "properties": {
    "addr:full":"Muntpln 3 Nieuwegein Utrecht 3437 AN",
    "addr:housenumber":"3",
    "addr:postcode":"3437 an",
    "addr:street":"Muntpln",
    "iso:country":"NL",
    "sg:address":"Muntpln 3",
    "sg:city":"Nieuwegein",
    "sg:orig_category":"Hoortoestellen",
    "sg:phone":"+31 30 605 3236",
    "sg:postcode":"3437 AN",
    "sg:province":"Utrecht",
    "wof:name":"Hoon, De",
    "wof:placetype":"venue"
},
  "geometry": {"coordinates":[5.078252,52.041039],"type":"Point"}
}