{
  "type": "Feature",
  "properties": {
    "addr:full":"Deltastraat 76 Almere Flevoland 1353 BS",
    "addr:housenumber":"76",
    "addr:postcode":"1353 bs",
    "addr:street":"Deltastraat;Flevoland",
    "iso:country":"NL",
    "sg:address":"Deltastraat 76",
    "sg:city":"Almere",
    "sg:orig_category":"Binnenvaart",
    "sg:phone":"+31 36 531 7284",
    "sg:postcode":"1353 BS",
    "sg:province":"Flevoland",
    "wof:name":"Party Rederij Tisset",
    "wof:placetype":"venue"
},
  "geometry": {"coordinates":[5.217591,52.333733],"type":"Point"}
}