{
  "type": "Feature",
  "properties": {
    "addr:full":"Schiekd 133-52 Rotterdam Zuid-Holland 3033 BL",
    "addr:housenumber":"133-52",
    "addr:postcode":"3033 bl",
    "addr:street":"Schiekd",
    "iso:country":"NL",
    "sg:address":"Schiekd 133-52",
    "sg:city":"Rotterdam",
    "sg:orig_category":"Adviesbureaus Bouwkunde",
    "sg:phone":"+31 10 467 2448",
    "sg:postcode":"3033 BL",
    "sg:province":"Zuid-Holland",
    "wof:name":"Descon",
    "wof:placetype":"venue"
},
  "geometry": {"coordinates":[4.46912,51.927521],"type":"Point"}
}