{
  "type": "Feature",
  "properties": {
    "addr:full":"Maasburg 40 Cuijk Noord-Brabant 5431 BR",
    "addr:housenumber":"40",
    "addr:postcode":"5431 br",
    "addr:street":"Maasburg",
    "iso:country":"NL",
    "sg:address":"Maasburg 40",
    "sg:city":"Cuijk",
    "sg:classifiers":[
        {
            "category":"Fast Food",
            "type":"Food & Drink"
        }
    ],
    "sg:phone":"+31 485 316 724",
    "sg:postcode":"5431 BR",
    "sg:province":"Noord-Brabant",
    "sg:tags":[
        "afhaal",
        "restaurant"
    ],
    "wof:name":"Cafetaria Chez Wiellie",
    "wof:placetype":"venue"
},
  "geometry": {"coordinates":[5.879392,51.729424],"type":"Point"}
}