{
  "type": "Feature",
  "properties": {
    "addr:full":"Boterdijk 172 De Kwakel North Holland 1424 NM",
    "addr:housenumber":"172",
    "addr:postcode":"1424",
    "addr:street":"Boterdijk",
    "iso:country":"NL",
    "sg:address":"Boterdijk 172",
    "sg:city":"De Kwakel",
    "sg:orig_category":"Wegen And Sportterreinen",
    "sg:phone":"+31 297 560 310",
    "sg:postcode":"1424 NM",
    "sg:province":"North Holland",
    "wof:name":"Kraanverhuurbedrijf R. Kok",
    "wof:placetype":"venue"
},
  "geometry": {"coordinates":[4.7987837791,52.2405929565],"type":"Point"}
}