{
  "type": "Feature",
  "properties": {
    "addr:full":"Ryksstrwg 95 Haarlem North Holland 2024 DB",
    "addr:housenumber":"95",
    "addr:postcode":"2024 db",
    "addr:street":"Ryksstrwg",
    "iso:country":"NL",
    "sg:address":"Ryksstrwg 95",
    "sg:city":"Haarlem",
    "sg:orig_category":"Binnenhuisarchitectuur",
    "sg:phone":"+31 23 551 2397",
    "sg:postcode":"2024 DB",
    "sg:province":"North Holland",
    "wof:name":"Xid",
    "wof:placetype":"venue"
},
  "geometry": {"coordinates":[4.63761,52.40593],"type":"Point"}
}