{
  "type": "Feature",
  "properties": {
    "addr:full":"Nieuw Baarnstraat 99 Baarn Utrecht 3743 BP",
    "addr:housenumber":"99",
    "addr:postcode":"3743 bp",
    "addr:street":"Nieuw Baarnstraat",
    "iso:country":"NL",
    "sg:address":"Nieuw Baarnstraat 99",
    "sg:city":"Baarn",
    "sg:orig_category":"Geluidsopnamen",
    "sg:phone":"+31 35 543 1991",
    "sg:postcode":"3743 BP",
    "sg:province":"Utrecht",
    "wof:name":"Zomba Music Holdings Bv",
    "wof:placetype":"venue"
},
  "geometry": {"coordinates":[5.282085,52.214287],"type":"Point"}
}