{
  "type": "Feature",
  "properties": {
    "addr:full":"Van Coehoornstraat 22 Venlo Limburg 5916 PH",
    "addr:housenumber":"22",
    "addr:postcode":"5916",
    "addr:street":"Van Coehoornstraat",
    "iso:country":"NL",
    "sg:address":"Van Coehoornstraat 22",
    "sg:city":"Venlo",
    "sg:orig_category":"Meubelzaken, Woning- And Keukeninrichting",
    "sg:phone":"+31 77 351 8053",
    "sg:postcode":"5916 PH",
    "sg:province":"Limburg",
    "wof:name":"Camare B.V.",
    "wof:placetype":"venue"
},
  "geometry": {"coordinates":[6.186942,51.387714],"type":"Point"}
}