{
  "type": "Feature",
  "properties": {
    "iso:country":"NL",
    "sg:address":"Gildestr 27A",
    "sg:city":"Holthees",
    "sg:orig_category":"Peuterspeelzalen",
    "sg:phone":"+31 478 630 089",
    "sg:postcode":"5824 AA",
    "sg:province":"North Brabant",
    "wof:name":"Rakkertjes, De",
    "wof:placetype":"venue"
},
  "geometry": {"coordinates":[6.003008,51.573673],"type":"Point"}
}