{
  "type": "Feature",
  "properties": {
    "addr:full":"Weg En Land 10 Bergschenhoek Zuid-Holland 2661 DB",
    "addr:housenumber":"10",
    "addr:postcode":"2661 db",
    "addr:street":"Weg En Land",
    "iso:country":"NL",
    "sg:address":"Weg En Land 10",
    "sg:city":"Bergschenhoek",
    "sg:orig_category":"Autokeuringen",
    "sg:phone":"+31 10 521 4444",
    "sg:postcode":"2661 DB",
    "sg:province":"Zuid-Holland",
    "wof:name":"Van Den Bogerd Transporten Bv",
    "wof:placetype":"venue"
},
  "geometry": {"coordinates":[4.499757,51.978264],"type":"Point"}
}