{
  "type": "Feature",
  "properties": {
    "iso:country":"NL",
    "sg:address":"Gootepad 19",
    "sg:city":"Brielle",
    "sg:classifiers":[
        {
            "category":"Personal",
            "subcategory":"Nail Salon",
            "type":"Services"
        }
    ],
    "sg:phone":"+31 181 417 015",
    "sg:postcode":"3232 GL",
    "sg:province":"Zuid-Holland",
    "sg:tags":[
        "pedicure"
    ],
    "wof:name":"Woudenberg-Kroon, J J",
    "wof:placetype":"venue"
},
  "geometry": {"coordinates":[4.166699,51.892563],"type":"Point"}
}