{
  "type": "Feature",
  "properties": {
    "addr:full":"Stationsplein 2 Schiedam South Holland 3112 HJ",
    "addr:housenumber":"2",
    "addr:postcode":"3112 hj",
    "addr:street":"Stationsplein",
    "iso:country":"NL",
    "sg:address":"Stationsplein 2",
    "sg:city":"Schiedam",
    "sg:orig_category":"Technische Studies And Onderzoek",
    "sg:phone":"+31 10 208 8888",
    "sg:postcode":"3112 HJ",
    "sg:province":"South Holland",
    "wof:name":"Kh- Engineering Bv",
    "wof:placetype":"venue"
},
  "geometry": {"coordinates":[4.39816,51.918472],"type":"Point"}
}