{
  "type": "Feature",
  "properties": {
    "iso:country":"NL",
    "sg:address":"Postbus 2527",
    "sg:city":"Haarlem",
    "sg:orig_category":"Adviesbureaus Automatisering",
    "sg:phone":"+31 23 539 0128",
    "sg:postcode":"2002 RA",
    "sg:province":"Noord-Holland",
    "wof:name":"Cnsi",
    "wof:placetype":"venue"
},
  "geometry": {"coordinates":[4.64225,52.380562],"type":"Point"}
}