{
  "type": "Feature",
  "properties": {
    "iso:country":"NL",
    "sg:address":"Sliedrechtstraat 52",
    "sg:city":"Rotterdam",
    "sg:orig_category":"Honden- En Kattentrimsalons",
    "sg:phone":"+31 10 481 5297",
    "sg:postcode":"3086 JN",
    "sg:province":"South Holland",
    "wof:name":"Snoopy",
    "wof:placetype":"venue"
},
  "geometry": {"coordinates":[4.471541,51.871696],"type":"Point"}
}