{
  "type": "Feature",
  "properties": {
    "addr:full":"Orinoco 5 Amstelveen Noord-Holland 1186 HV",
    "addr:housenumber":"5",
    "addr:postcode":"1186 hv",
    "addr:street":"Orinoco",
    "iso:country":"NL",
    "sg:address":"Orinoco 5",
    "sg:city":"Amstelveen",
    "sg:orig_category":"Psychologen",
    "sg:phone":"+31 20 647 8064",
    "sg:postcode":"1186 HV",
    "sg:province":"Noord-Holland",
    "wof:name":"Szab\u00f3-D\u00e9k\u00e1ny, Drs M",
    "wof:placetype":"venue"
},
  "geometry": {"coordinates":[4.871122,52.285404],"type":"Point"}
}