{
  "type": "Feature",
  "properties": {
    "addr:full":"Carre 66 Tilburg Noord-Brabant 5017 JE",
    "addr:housenumber":"66",
    "addr:postcode":"5017 je",
    "addr:street":"Carre",
    "iso:country":"NL",
    "sg:address":"Carre 66",
    "sg:city":"Tilburg",
    "sg:orig_category":"Beeldende Kunstenaars",
    "sg:phone":"+31 13 543 5334",
    "sg:postcode":"5017 JE",
    "sg:province":"Noord-Brabant",
    "wof:name":"Kalypso",
    "wof:placetype":"venue"
},
  "geometry": {"coordinates":[5.102586,51.558887],"type":"Point"}
}