{
  "type": "Feature",
  "properties": {
    "addr:full":"Achterom 1 Delft Zuid-Holland 2611 PL",
    "addr:housenumber":"1",
    "addr:postcode":"2611 pl",
    "addr:street":"Achterom",
    "iso:country":"NL",
    "sg:address":"Achterom 1",
    "sg:city":"Delft",
    "sg:orig_category":"Fotozaken",
    "sg:phone":"+31 15 212 3010",
    "sg:postcode":"2611 PL",
    "sg:province":"Zuid-Holland",
    "wof:name":"Deko Bv",
    "wof:placetype":"venue"
},
  "geometry": {"coordinates":[4.361209,52.006187],"type":"Point"}
}