{
  "type": "Feature",
  "properties": {
    "addr:full":"Diamant 11 Mydrecht Utrecht 3641 XR",
    "addr:housenumber":"11;3641",
    "addr:street":"Diamant;Xr",
    "iso:country":"NL",
    "sg:address":"Diamant 11",
    "sg:city":"Mydrecht",
    "sg:orig_category":"Peuterspeelzalen",
    "sg:phone":"+31 297 284 741",
    "sg:postcode":"3641 XR",
    "sg:province":"Utrecht",
    "wof:name":"Klein Duimpje, Sticht",
    "wof:placetype":"venue"
},
  "geometry": {"coordinates":[4.86178,52.20578],"type":"Point"}
}