{
  "type": "Feature",
  "properties": {
    "addr:full":"Schepenbergwg 26 Amsterdam Zuidoost North Holland 1105 AT",
    "addr:housenumber":"26",
    "addr:postcode":"1105",
    "addr:street":"Schepenbergwg",
    "iso:country":"NL",
    "sg:address":"Schepenbergwg 26",
    "sg:city":"Amsterdam Zuidoost",
    "sg:orig_category":"Autopoetsbedrijven",
    "sg:phone":"+31 20 409 4326",
    "sg:postcode":"1105 AT",
    "sg:province":"North Holland",
    "wof:name":"B'Na",
    "wof:placetype":"venue"
},
  "geometry": {"coordinates":[4.944319,52.295448],"type":"Point"}
}