{
  "type": "Feature",
  "properties": {
    "addr:full":"Ambachtswg 7 Huizen North Holland 1271 AL",
    "addr:housenumber":"7",
    "addr:postcode":"1271 al",
    "addr:street":"Ambachtswg",
    "iso:country":"NL",
    "sg:address":"Ambachtswg 7",
    "sg:city":"Huizen",
    "sg:orig_category":"Verf En Lak - Fabrieken En Groothandel",
    "sg:phone":"+31 35 525 1749",
    "sg:postcode":"1271 AL",
    "sg:province":"North Holland",
    "wof:name":"Phoenix",
    "wof:placetype":"venue"
},
  "geometry": {"coordinates":[5.2417,52.301079],"type":"Point"}
}