{
  "type": "Feature",
  "properties": {
    "addr:full":"Nieuwkuikseweg 6A Helvoirt Noord-Brabant 5268 LE",
    "addr:housenumber":"6a",
    "addr:postcode":"5268 le",
    "addr:street":"Nieuwkuikseweg",
    "iso:country":"NL",
    "sg:address":"Nieuwkuikseweg 6A",
    "sg:city":"Helvoirt",
    "sg:orig_category":"Huizensloop And Bouwrijp Maken",
    "sg:phone":"+31 411 642 075",
    "sg:postcode":"5268 LE",
    "sg:province":"Noord-Brabant",
    "wof:name":"E. Gubbels",
    "wof:placetype":"venue"
},
  "geometry": {"coordinates":[5.21557,51.661942],"type":"Point"}
}