{
  "type": "Feature",
  "properties": {
    "iso:country":"NL",
    "sg:address":"Barestraat 2D",
    "sg:city":"Groningen",
    "sg:orig_category":"Architecten",
    "sg:phone":"+31 50 526 1775",
    "sg:postcode":"9725 CP",
    "sg:province":"Groningen",
    "wof:name":"R.C. Stoian",
    "wof:placetype":"venue"
},
  "geometry": {"coordinates":[6.571944,53.209087],"type":"Point"}
}