{
  "type": "Feature",
  "properties": {
    "addr:full":"Verbindingswg 24 Musselkanaal Groningen 9581 TH",
    "addr:housenumber":"24",
    "addr:postcode":"9581 th",
    "addr:street":"Verbindingswg",
    "iso:country":"NL",
    "sg:address":"Verbindingswg 24",
    "sg:city":"Musselkanaal",
    "sg:orig_category":"Journalisten Freelance",
    "sg:phone":"+31 599 454 815",
    "sg:postcode":"9581 TH",
    "sg:province":"Groningen",
    "wof:name":"Textfree",
    "wof:placetype":"venue"
},
  "geometry": {"coordinates":[7.007427,52.956139],"type":"Point"}
}