{
  "type": "Feature",
  "properties": {
    "addr:full":"Akkerstraat 12 Heusden Gem Heusden North Brabant 5256 NM",
    "addr:housenumber":"12",
    "addr:postcode":"5256",
    "addr:street":"Akkerstraat",
    "iso:country":"NL",
    "sg:address":"Akkerstraat 12",
    "sg:city":"Heusden Gem Heusden",
    "sg:orig_category":"Boekhouders",
    "sg:phone":"+31 416 661 742",
    "sg:postcode":"5256 NM",
    "sg:province":"North Brabant",
    "wof:name":"Administratiekantoor A. De Wilt",
    "wof:placetype":"venue"
},
  "geometry": {"coordinates":[5.154845,51.730778],"type":"Point"}
}