{
  "type": "Feature",
  "properties": {
    "iso:country":"NL",
    "sg:address":"Dykstr 5",
    "sg:city":"Franeker",
    "sg:orig_category":"Adviesbureaus Bedrijfsorganisatie",
    "sg:phone":"+31 517 390 038",
    "sg:postcode":"8801 LR",
    "sg:province":"Friesland",
    "sg:website":"HTTP://www.bureaudebok.nl",
    "wof:name":"Bok, De",
    "wof:placetype":"venue"
},
  "geometry": {"coordinates":[5.538215,53.18536],"type":"Point"}
}