{
  "type": "Feature",
  "properties": {
    "iso:country":"NL",
    "sg:address":"Zaaren 73",
    "sg:city":"Rijen",
    "sg:orig_category":"Loodgieterswerk, Verwarming And Sanitaire Installaties",
    "sg:phone":"+31 161 225 406",
    "sg:postcode":"5122 GH",
    "sg:province":"Noord-Brabant",
    "wof:name":"Klufran",
    "wof:placetype":"venue"
},
  "geometry": {"coordinates":[4.927531,51.596008],"type":"Point"}
}