{
  "type": "Feature",
  "properties": {
    "addr:full":"Luikstr 1 Etten Leur North Brabant 4871 ZN",
    "addr:housenumber":"1",
    "addr:postcode":"4871 zn",
    "addr:street":"Luikstr",
    "iso:country":"NL",
    "sg:address":"Luikstr 1",
    "sg:city":"Etten Leur",
    "sg:orig_category":"Accountants - Administratie- Consulenten En -Kantoren",
    "sg:phone":"+31 76 501 4002",
    "sg:postcode":"4871 ZN",
    "sg:province":"North Brabant",
    "wof:name":"Poppelaars",
    "wof:placetype":"venue"
},
  "geometry": {"coordinates":[4.644554,51.580341],"type":"Point"}
}