{
  "type": "Feature",
  "properties": {
    "iso:country":"NL",
    "sg:address":"Vendelierskamp 9",
    "sg:city":"Vianen Nb",
    "sg:orig_category":"Voetbalverenigingen",
    "sg:phone":"+31 485 314 923",
    "sg:postcode":"5434 SM",
    "sg:province":"North Brabant",
    "wof:name":"Desm",
    "wof:placetype":"venue"
},
  "geometry": {"coordinates":[5.858729,51.719044],"type":"Point"}
}