{
  "type": "Feature",
  "properties": {
    "iso:country":"NL",
    "sg:address":"Bredasewg 26A",
    "sg:city":"Terheyden",
    "sg:orig_category":"Milieu",
    "sg:phone":"+31 76 593 4124",
    "sg:postcode":"4844 CL",
    "sg:province":"North Brabant",
    "wof:name":"Rasenberg Bv",
    "wof:placetype":"venue"
},
  "geometry": {"coordinates":[4.764511,51.634819],"type":"Point"}
}