{
  "type": "Feature",
  "properties": {
    "addr:full":"Kruyskamp 44 Oldenzaal Overijssel 7576 ER",
    "addr:housenumber":"44",
    "addr:postcode":"7576 er",
    "addr:street":"Kruyskamp",
    "iso:country":"NL",
    "sg:address":"Kruyskamp 44",
    "sg:city":"Oldenzaal",
    "sg:orig_category":"Hypotheken",
    "sg:phone":"+31 541 294 231",
    "sg:postcode":"7576 ER",
    "sg:province":"Overijssel",
    "wof:name":"Roeloffzen",
    "wof:placetype":"venue"
},
  "geometry": {"coordinates":[6.899474,52.313362],"type":"Point"}
}