{
  "type": "Feature",
  "properties": {
    "iso:country":"NL",
    "sg:address":"Dorpsstr 77",
    "sg:city":"Nyeveen",
    "sg:classifiers":[
        {
            "category":"Retail",
            "subcategory":"Auto Repair",
            "type":"Services"
        }
    ],
    "sg:phone":"+31 522 491 449",
    "sg:postcode":"7948 BM",
    "sg:province":"Drenthe",
    "sg:tags":[
        "garage"
    ],
    "sg:website":"http://www.janschutautos.nl",
    "wof:name":"Schut Auto'S, Jan",
    "wof:placetype":"venue"
},
  "geometry": {"coordinates":[6.160105,52.725842],"type":"Point"}
}