{
  "type": "Feature",
  "properties": {
    "addr:full":"Boeijerstraat 14 De Rijp Noord-Holland 1483 TH",
    "addr:housenumber":"14",
    "addr:postcode":"1483 th",
    "addr:street":"Boeijerstraat",
    "iso:country":"NL",
    "sg:address":"Boeijerstraat 14",
    "sg:city":"De Rijp",
    "sg:classifiers":[
        {
            "category":"Education",
            "subcategory":"Preschool",
            "type":"Public Place"
        }
    ],
    "sg:phone":"+31 299 673 396",
    "sg:postcode":"1483 TH",
    "sg:province":"Noord-Holland",
    "sg:tags":[
        "kleuteronderwijs",
        "basis-"
    ],
    "wof:name":"Openbare Basisschool De Tweemaster",
    "wof:placetype":"venue"
},
  "geometry": {"coordinates":[4.84165,52.555408],"type":"Point"}
}