{
  "type": "Feature",
  "properties": {
    "iso:country":"NL",
    "sg:address":"Lingedk 95",
    "sg:city":"Wadenoyen",
    "sg:orig_category":"Webdesign Bureaus",
    "sg:phone":"+31 344 621 977",
    "sg:postcode":"4014 MD",
    "sg:province":"Gelderland",
    "wof:name":"Jared",
    "wof:placetype":"venue"
},
  "geometry": {"coordinates":[5.3732299805,51.8733558655],"type":"Point"}
}