{
  "type": "Feature",
  "properties": {
    "iso:country":"NL",
    "sg:address":"Stadhuispln 10",
    "sg:city":"Gorinchem",
    "sg:orig_category":"Verzekeringen - Verzekeringskantoren",
    "sg:phone":"+31 183 691 666",
    "sg:postcode":"4205 AX",
    "sg:province":"Zuid-Holland",
    "wof:name":"Brand Lugtenburg Koster",
    "wof:placetype":"venue"
},
  "geometry": {"coordinates":[4.964804,51.832027],"type":"Point"}
}