{
  "type": "Feature",
  "properties": {
    "addr:full":"Hofpassage 9 Enschede Overijssel 7511 HZ",
    "addr:housenumber":"9",
    "addr:postcode":"7511 hz",
    "addr:street":"Hofpassage",
    "iso:country":"NL",
    "sg:address":"Hofpassage 9",
    "sg:city":"Enschede",
    "sg:orig_category":"Damesmodezaken",
    "sg:phone":"+31 53 430 3363",
    "sg:postcode":"7511 HZ",
    "sg:province":"Overijssel",
    "wof:name":"Boetiek 32 Enschede Bv",
    "wof:placetype":"venue"
},
  "geometry": {"coordinates":[6.898419,52.219147],"type":"Point"}
}