{
  "type": "Feature",
  "properties": {
    "iso:country":"NL",
    "sg:address":"Parelvissersstr 201 Het Zevenhuis",
    "sg:city":"Apeldoorn",
    "sg:orig_category":"Verenigingsgebouwen",
    "sg:phone":"+31 55 366 3983",
    "sg:postcode":"7323 BM",
    "sg:province":"Gelderland",
    "wof:name":"Zevenhuis, Het",
    "wof:placetype":"venue"
},
  "geometry": {"coordinates":[5.99607,52.235001],"type":"Point"}
}