{
  "type": "Feature",
  "properties": {
    "iso:country":"NL",
    "sg:address":"Torenstr 7",
    "sg:city":"Velsen Zuid",
    "sg:orig_category":"Beeldende Kunstenaars",
    "sg:phone":"+31 255 518 051",
    "sg:postcode":"1981 BC",
    "sg:province":"British Columbia",
    "wof:name":"Kunstenaarscollectief Velsen",
    "wof:placetype":"venue"
},
  "geometry": {"coordinates":[-126.555511,54.485668],"type":"Point"}
}