{
  "type": "Feature",
  "properties": {
    "iso:country":"NL",
    "sg:address":"Riemtale 11",
    "sg:city":"Maasland",
    "sg:orig_category":"Verenigingen En Stichtingen",
    "sg:phone":"+31 10 591 9141",
    "sg:postcode":"3155 ND",
    "sg:province":"Zuid-Holland",
    "wof:name":"Maasland Gospel Management, Sticht",
    "wof:placetype":"venue"
},
  "geometry": {"coordinates":[4.275688,51.933777],"type":"Point"}
}