{
  "type": "Feature",
  "properties": {
    "addr:full":"Nieuwe Rijn 7 Leiden Zuid-Holland 2312 JB",
    "addr:housenumber":"7",
    "addr:postcode":"2312 jb",
    "addr:street":"Nieuwe Rijn",
    "iso:country":"NL",
    "sg:address":"Nieuwe Rijn 7",
    "sg:city":"Leiden",
    "sg:orig_category":"Juweliers",
    "sg:phone":"+31 71 514 0461",
    "sg:postcode":"2312 JB",
    "sg:province":"Zuid-Holland",
    "wof:name":"Sieraad 2000",
    "wof:placetype":"venue"
},
  "geometry": {"coordinates":[4.491722,52.158859],"type":"Point"}
}