{
  "type": "Feature",
  "properties": {
    "addr:full":"Rijksweg 69 Ten Boer Groningen 9791 AA",
    "addr:housenumber":"69",
    "addr:postcode":"boer;9791 aa",
    "addr:street":"Rijksweg",
    "iso:country":"NL",
    "sg:address":"Rijksweg 69",
    "sg:city":"Ten Boer",
    "sg:orig_category":"Verzekeringen",
    "sg:phone":"+31 50 525 1234",
    "sg:postcode":"9791 AA",
    "sg:province":"Groningen",
    "wof:name":"Assurantie- En Adviesbureau Hoekstra",
    "wof:placetype":"venue"
},
  "geometry": {"coordinates":[6.705305,53.27795],"type":"Point"}
}