{
  "type": "Feature",
  "properties": {
    "addr:full":"Eksterdreef 111 Waddinxveen South Holland 2743 EC",
    "addr:housenumber":"111",
    "addr:postcode":"2743 ec",
    "addr:street":"Eksterdreef",
    "iso:country":"NL",
    "sg:address":"Eksterdreef 111",
    "sg:city":"Waddinxveen",
    "sg:orig_category":"Marktonderzoekbureaus",
    "sg:phone":"+31 182 632 165",
    "sg:postcode":"2743 EC",
    "sg:province":"South Holland",
    "wof:name":"Adviesbureau Drs. H. Breimer",
    "wof:placetype":"venue"
},
  "geometry": {"coordinates":[4.64414,52.038345],"type":"Point"}
}