{
  "type": "Feature",
  "properties": {
    "addr:full":"A V Leeuwenhoekwg 8 Alphen Aan Den Ryn South Holland 2408 AM",
    "addr:housenumber":"8",
    "addr:postcode":"2408",
    "addr:street":"A;Leeuwenhoekwg;Aan Den Ryn",
    "iso:country":"NL",
    "sg:address":"A V Leeuwenhoekwg 8",
    "sg:city":"Alphen Aan Den Ryn",
    "sg:orig_category":"Verenigingen En Stichtingen",
    "sg:phone":"+31 172 476 241",
    "sg:postcode":"2408 AM",
    "sg:province":"South Holland",
    "wof:name":"Functiewaardering Wegvervoer, Sticht",
    "wof:placetype":"venue"
},
  "geometry": {"coordinates":[4.65273,52.120281],"type":"Point"}
}