{
  "type": "Feature",
  "properties": {
    "addr:full":"Monikesstr 9 Venray Limburg 5801 RZ",
    "addr:housenumber":"9",
    "addr:postcode":"5801 rz",
    "addr:street":"Monikesstr",
    "iso:country":"NL",
    "sg:address":"Monikesstr 9",
    "sg:city":"Venray",
    "sg:orig_category":"Adviesbureaus Bedrijfsorganisatie",
    "sg:phone":"+31 478 512 580",
    "sg:postcode":"5801 RZ",
    "sg:province":"Limburg",
    "wof:name":"Berhitu, A J",
    "wof:placetype":"venue"
},
  "geometry": {"coordinates":[5.965474,51.521198],"type":"Point"}
}