{
  "type": "Feature",
  "properties": {
    "addr:full":"Sagenstraat 7 Veldhoven Noord-Brabant 5503 ET",
    "addr:housenumber":"7",
    "addr:postcode":"5503 et",
    "addr:street":"Sagenstraat",
    "iso:country":"NL",
    "sg:address":"Sagenstraat 7",
    "sg:city":"Veldhoven",
    "sg:orig_category":"Metaalbekleding And -Behandeling",
    "sg:phone":"+31 40 254 6690",
    "sg:postcode":"5503 ET",
    "sg:province":"Noord-Brabant",
    "wof:name":"Van Vlokhoven",
    "wof:placetype":"venue"
},
  "geometry": {"coordinates":[5.415797,51.416374],"type":"Point"}
}