{
  "type": "Feature",
  "properties": {
    "addr:full":"Vd Burchstr 42 Hoofddorp Noord-Holland 2132 RN",
    "addr:housenumber":"42",
    "addr:postcode":"2132 rn",
    "iso:country":"NL",
    "sg:address":"Vd Burchstr 42",
    "sg:city":"Hoofddorp",
    "sg:orig_category":"Accountants - Administratie- Consulenten En -Kantoren",
    "sg:phone":"+31 23 565 5610",
    "sg:postcode":"2132 RN",
    "sg:province":"Noord-Holland",
    "wof:name":"Noord, Van",
    "wof:placetype":"venue"
},
  "geometry": {"coordinates":[4.69296,52.305393],"type":"Point"}
}