{
  "type": "Feature",
  "properties": {
    "addr:full":"Lang Gr 16 Maastricht Limburg 6211 JG",
    "addr:housenumber":"16",
    "addr:postcode":"6211 jg",
    "addr:street":"Lang Gr",
    "iso:country":"NL",
    "sg:address":"Lang Gr 16",
    "sg:city":"Maastricht",
    "sg:orig_category":"Adviesbureaus Gezondheidszorg",
    "sg:phone":"+31 43 325 4164",
    "sg:postcode":"6211 JG",
    "sg:province":"Limburg",
    "wof:name":"Koch",
    "wof:placetype":"venue"
},
  "geometry": {"coordinates":[5.691075,50.845795],"type":"Point"}
}