{
  "type": "Feature",
  "properties": {
    "addr:full":"Maaskd 14 Venlo Limburg 5911 EW",
    "addr:housenumber":"14",
    "addr:postcode":"5911 ew",
    "addr:street":"Maaskd",
    "iso:country":"NL",
    "sg:address":"Maaskd 14",
    "sg:city":"Venlo",
    "sg:orig_category":"Boeken En Tijdschriften",
    "sg:phone":"+31 77 354 9597",
    "sg:postcode":"5911 EW",
    "sg:province":"Limburg",
    "wof:name":"Climax",
    "wof:placetype":"venue"
},
  "geometry": {"coordinates":[6.17286,51.372421],"type":"Point"}
}