{
  "type": "Feature",
  "properties": {
    "iso:country":"NL",
    "sg:address":"Dr M V Drielpln 2",
    "sg:city":"Ochten",
    "sg:orig_category":"Zalenverhuur",
    "sg:phone":"+31 344 641 222",
    "sg:postcode":"4051 AX",
    "sg:province":"Gelderland",
    "sg:website":"HTTP://www.devicary.nl",
    "wof:name":"Vicary, De",
    "wof:placetype":"venue"
},
  "geometry": {"coordinates":[5.56602,51.90736],"type":"Point"}
}