{
  "type": "Feature",
  "properties": {
    "addr:full":"Zeestraat 60 Beverwijk North Holland 1942 AS",
    "addr:housenumber":"60",
    "addr:postcode":"1942 as",
    "addr:street":"Zeestraat",
    "iso:country":"NL",
    "sg:address":"Zeestraat 60",
    "sg:city":"Beverwijk",
    "sg:orig_category":"Werving And Selectie Van Tijdelijk Personeel And Uitzendkantoren",
    "sg:phone":"+31 251 218 484",
    "sg:postcode":"1942 AS",
    "sg:province":"North Holland",
    "wof:name":"Ferro",
    "wof:placetype":"venue"
},
  "geometry": {"coordinates":[4.6524701118,52.4820098877],"type":"Point"}
}