{
  "type": "Feature",
  "properties": {
    "addr:full":"Najaarswg 2 Enschede Overijssel 7532 SK",
    "addr:housenumber":"2",
    "addr:street":"Najaarswg;7532",
    "iso:country":"NL",
    "sg:address":"Najaarswg 2",
    "sg:city":"Enschede",
    "sg:orig_category":"Zeefdrukkerijen",
    "sg:phone":"+31 53 461 5815",
    "sg:postcode":"7532 SK",
    "sg:province":"Overijssel",
    "wof:name":"Meer-Print, Van Der",
    "wof:placetype":"venue"
},
  "geometry": {"coordinates":[6.957396,52.225338],"type":"Point"}
}