{
  "type": "Feature",
  "properties": {
    "addr:full":"Solwerderstraat 48 Appingedam Groningen 9901 BE",
    "addr:housenumber":"48",
    "addr:postcode":"9901",
    "addr:street":"Solwerderstraat",
    "iso:country":"NL",
    "sg:address":"Solwerderstraat 48",
    "sg:city":"Appingedam",
    "sg:classifiers":[
        {
            "category":"Bakery",
            "type":"Food & Drink"
        }
    ],
    "sg:phone":"+31 596 680 707",
    "sg:postcode":"9901 BE",
    "sg:province":"Groningen",
    "sg:tags":[
        "brood",
        "banket"
    ],
    "wof:name":"Kwaliteits Banketbakkerij H. Koenen",
    "wof:placetype":"venue"
},
  "geometry": {"coordinates":[6.860233,53.321625],"type":"Point"}
}