{
  "type": "Feature",
  "properties": {
    "addr:full":"Wijk 2 2 Urk Flevoland 8321 EP",
    "addr:housenumber":"2",
    "addr:postcode":"8321 ep",
    "addr:street":"Wijk 2;Flevoland",
    "iso:country":"NL",
    "sg:address":"Wijk 2 2",
    "sg:city":"Urk",
    "sg:orig_category":"Musea And Historische Gebouwen",
    "sg:phone":"+31 527 683 262",
    "sg:postcode":"8321 EP",
    "sg:province":"Flevoland",
    "wof:name":"Museum Het Oude Raadhuis",
    "wof:placetype":"venue"
},
  "geometry": {"coordinates":[5.592915,52.660725],"type":"Point"}
}