{
  "type": "Feature",
  "properties": {
    "addr:full":"Hoofdstraat 113 Meppel Drenthe 7941 AE",
    "addr:housenumber":"113",
    "addr:postcode":"7941 ae",
    "addr:street":"Hoofdstraat",
    "iso:country":"NL",
    "sg:address":"Hoofdstraat 113",
    "sg:city":"Meppel",
    "sg:orig_category":"Verlichting And Huishoudartikelen",
    "sg:phone":"+31 522 240 858",
    "sg:postcode":"7941 AE",
    "sg:province":"Drenthe",
    "wof:name":"Vof Roodbergen & Wilts",
    "wof:placetype":"venue"
},
  "geometry": {"coordinates":[6.196295,52.699615],"type":"Point"}
}