{
  "type": "Feature",
  "properties": {
    "addr:full":"Hoofdstr 94 Hoogezand Groningen 9601 EL",
    "addr:housenumber":"94",
    "addr:postcode":"9601 el",
    "addr:street":"Hoofdstr",
    "iso:country":"NL",
    "sg:address":"Hoofdstr 94",
    "sg:city":"Hoogezand",
    "sg:orig_category":"Kappers",
    "sg:phone":"+31 598 399 972",
    "sg:postcode":"9601 EL",
    "sg:province":"Groningen",
    "wof:name":"Humphrey Hair Design",
    "wof:placetype":"venue"
},
  "geometry": {"coordinates":[6.7609858513,53.1634788513],"type":"Point"}
}