{
  "type": "Feature",
  "properties": {
    "addr:full":"J Evertsenstr 43 Amsterdam North Holland 1057 BN",
    "addr:housenumber":"43",
    "addr:postcode":"1057 bn",
    "iso:country":"NL",
    "sg:address":"J Evertsenstr 43",
    "sg:city":"Amsterdam",
    "sg:orig_category":"Fietsen En Bromfietsen",
    "sg:phone":"+31 20 618 8604",
    "sg:postcode":"1057 BN",
    "sg:province":"North Holland",
    "sg:website":"http://www.alechkar.nl",
    "wof:name":"Lechkar, A",
    "wof:placetype":"venue"
},
  "geometry": {"coordinates":[4.856124,52.370926],"type":"Point"}
}