{
  "type": "Feature",
  "properties": {
    "addr:full":"Stadhoudersmol Wg 19 Apeldoorn Gelderland 7317 AV",
    "addr:housenumber":"19",
    "addr:postcode":"7317 av",
    "addr:street":"Wg;Gelderland",
    "iso:country":"NL",
    "sg:address":"Stadhoudersmol Wg 19",
    "sg:city":"Apeldoorn",
    "sg:orig_category":"Verenigingen En Stichtingen",
    "sg:phone":"+31 55 506 2733",
    "sg:postcode":"7317 AV",
    "sg:province":"Gelderland",
    "sg:website":"http://www.nvvo.nl",
    "wof:name":"Nvvo",
    "wof:placetype":"venue"
},
  "geometry": {"coordinates":[5.969548,52.236897],"type":"Point"}
}