{
  "type": "Feature",
  "properties": {
    "addr:full":"Stroinksbleekwg 10 D Enschede NL.08 7523 ZL",
    "addr:housenumber":"10 d",
    "addr:postcode":"7523 zl",
    "addr:street":"Stroinksbleekwg",
    "iso:country":"NL",
    "sg:address":"Stroinksbleekwg 10 D",
    "sg:city":"Enschede",
    "sg:orig_category":"Meubelmakerijen",
    "sg:phone":"+31 53 435 1748",
    "sg:postcode":"7523 ZL",
    "sg:province":"NL.08",
    "wof:name":"Brongers",
    "wof:placetype":"venue"
},
  "geometry": {"coordinates":[6.895224,52.234253],"type":"Point"}
}