{
  "type": "Feature",
  "properties": {
    "addr:full":"Burg V Tuyllln 10 Zeist Utrecht 3707 CW",
    "addr:housenumber":"10",
    "addr:postcode":"3707 cw",
    "addr:street":"Burg V Tuyllln",
    "iso:country":"NL",
    "sg:address":"Burg V Tuyllln 10",
    "sg:city":"Zeist",
    "sg:orig_category":"Mensendieck - Oefentherapeuten",
    "sg:phone":"+31 30 692 2815",
    "sg:postcode":"3707 CW",
    "sg:province":"Utrecht",
    "wof:name":"Eysbouts-Jonker, G",
    "wof:placetype":"venue"
},
  "geometry": {"coordinates":[5.24387,52.08548],"type":"Point"}
}