{
  "type": "Feature",
  "properties": {
    "addr:full":"C Jolstr 115 S Gravenhage Zuid-Holland 2584 EP",
    "addr:housenumber":"115;gravenhage",
    "addr:postcode":"2584 ep",
    "addr:street":"S",
    "iso:country":"NL",
    "sg:address":"C Jolstr 115",
    "sg:city":"S Gravenhage",
    "sg:orig_category":"Adviesbureaus Bedrijfsorganisatie",
    "sg:phone":"+31 70 358 7513",
    "sg:postcode":"2584 EP",
    "sg:province":"Zuid-Holland",
    "wof:name":"Gelder",
    "wof:placetype":"venue"
},
  "geometry": {"coordinates":[4.28131,52.103199],"type":"Point"}
}