{
  "type": "Feature",
  "properties": {
    "addr:full":"Orleanshof 34 Eindhoven North Brabant 5627 LP",
    "addr:housenumber":"34",
    "addr:postcode":"5627 lp",
    "addr:street":"Orleanshof",
    "iso:country":"NL",
    "sg:address":"Orleanshof 34",
    "sg:city":"Eindhoven",
    "sg:orig_category":"Vertaal- And Tolkenbureaus",
    "sg:phone":"+31 40 241 3844",
    "sg:postcode":"5627 LP",
    "sg:province":"North Brabant",
    "wof:name":"J G Gerbranda",
    "wof:placetype":"venue"
},
  "geometry": {"coordinates":[5.447048,51.484444],"type":"Point"}
}