{
  "type": "Feature",
  "properties": {
    "iso:country":"NL",
    "sg:address":"Orleanshof 34",
    "sg:city":"Eindhoven",
    "sg:orig_category":"Vertaal- And Tolkenbureaus",
    "sg:phone":"+31 40 241 3844",
    "sg:postcode":"5627 LP",
    "sg:province":"North Brabant",
    "wof:name":"J G Gerbranda",
    "wof:placetype":"venue"
},
  "geometry": {"coordinates":[5.447048,51.484444],"type":"Point"}
}