{
  "type": "Feature",
  "properties": {
    "addr:full":"Tjalkstraat 31 Eindhoven Noord-Brabant 5616 KB",
    "addr:housenumber":"31",
    "addr:postcode":"5616 kb",
    "addr:street":"Tjalkstraat",
    "iso:country":"NL",
    "sg:address":"Tjalkstraat 31",
    "sg:city":"Eindhoven",
    "sg:orig_category":"Binnenhuisarchitecten",
    "sg:phone":"+31 40 257 5606",
    "sg:postcode":"5616 KB",
    "sg:province":"Noord-Brabant",
    "wof:name":"J.M.P. Van Och",
    "wof:placetype":"venue"
},
  "geometry": {"coordinates":[5.452996,51.439442],"type":"Point"}
}