{
  "type": "Feature",
  "properties": {
    "iso:country":"NL",
    "sg:address":"De Kuil 6",
    "sg:city":"Uitgeest",
    "sg:orig_category":"Verlichting And Huishoudartikelen",
    "sg:phone":"+31 251 313 407",
    "sg:postcode":"1911 TP",
    "sg:province":"Noord-Holland",
    "wof:name":"Woninginrichting Oosterwal Bv",
    "wof:placetype":"venue"
},
  "geometry": {"coordinates":[4.704034,52.525909],"type":"Point"}
}