{
  "type": "Feature",
  "properties": {
    "addr:full":"Kasterenln 13 Tilburg North Brabant 5045 RA",
    "addr:housenumber":"13",
    "addr:postcode":"5045 ra",
    "addr:street":"Kasterenln",
    "iso:country":"NL",
    "sg:address":"Kasterenln 13",
    "sg:city":"Tilburg",
    "sg:orig_category":"Keukens",
    "sg:phone":"+31 13 456 5674",
    "sg:postcode":"5045 RA",
    "sg:province":"North Brabant",
    "wof:name":"Frank Keukenmontage",
    "wof:placetype":"venue"
},
  "geometry": {"coordinates":[5.002497,51.576542],"type":"Point"}
}