{
  "type": "Feature",
  "properties": {
    "addr:full":"Boezembocht 23 Rotterdam South Holland 3034 KA",
    "addr:housenumber":"23",
    "addr:postcode":"3034 ka",
    "addr:street":"Boezembocht",
    "iso:country":"NL",
    "sg:address":"Boezembocht 23",
    "sg:city":"Rotterdam",
    "sg:orig_category":"Metalen And Ertsen Gh",
    "sg:phone":"+31 10 413 2960",
    "sg:postcode":"3034 KA",
    "sg:province":"South Holland",
    "wof:name":"Bv Nickel Refining And Trading Niref",
    "wof:placetype":"venue"
},
  "geometry": {"coordinates":[4.493529,51.941204],"type":"Point"}
}