{
  "type": "Feature",
  "properties": {
    "addr:full":"Boeyer 26 Volendam Noord-Holland 1132 GR",
    "addr:housenumber":"26",
    "addr:postcode":"1132",
    "addr:street":"Boeyer",
    "iso:country":"NL",
    "sg:address":"Boeyer 26",
    "sg:city":"Volendam",
    "sg:orig_category":"Schilders",
    "sg:phone":"+31 299 368 331",
    "sg:postcode":"1132 GR",
    "sg:province":"Noord-Holland",
    "wof:name":"Evert Jan, Schildersbedrijf",
    "wof:placetype":"venue"
},
  "geometry": {"coordinates":[5.05583,52.501999],"type":"Point"}
}