{
  "type": "Feature",
  "properties": {
    "addr:full":"Vlasakker 2 Oudewater Utrecht 3421 JR",
    "addr:housenumber":"2",
    "addr:postcode":"3421 jr",
    "addr:street":"Vlasakker",
    "iso:country":"NL",
    "sg:address":"Vlasakker 2",
    "sg:city":"Oudewater",
    "sg:orig_category":"Public Relationbureaus",
    "sg:phone":"+31 348 562 632",
    "sg:postcode":"3421 JR",
    "sg:province":"Utrecht",
    "wof:name":"Vof Trend Consultants",
    "wof:placetype":"venue"
},
  "geometry": {"coordinates":[4.871398,52.030334],"type":"Point"}
}