{
  "type": "Feature",
  "properties": {
    "iso:country":"NL",
    "sg:address":"Spaansewg 8",
    "sg:city":"Rotterdam",
    "sg:orig_category":"Verenigingen En Stichtingen",
    "sg:phone":"+31 10 415 4140",
    "sg:postcode":"3028 HW",
    "sg:province":"Zuid-Holland",
    "wof:name":"Stedepost",
    "wof:placetype":"venue"
},
  "geometry": {"coordinates":[4.428954,51.918907],"type":"Point"}
}