{
  "type": "Feature",
  "properties": {
    "addr:full":"Lage Barakken 2 Maastricht Limburg 6221 CJ",
    "addr:housenumber":"2",
    "addr:postcode":"6221 cj",
    "addr:street":"Lage Barakken",
    "iso:country":"NL",
    "sg:address":"Lage Barakken 2",
    "sg:city":"Maastricht",
    "sg:orig_category":"Artsen And Specialisten",
    "sg:phone":"+31 43 321 4087",
    "sg:postcode":"6221 CJ",
    "sg:province":"Limburg",
    "wof:name":"Advies- En Bemiddelingsbureau Kemeling",
    "wof:placetype":"venue"
},
  "geometry": {"coordinates":[5.699986,50.850361],"type":"Point"}
}