{
  "type": "Feature",
  "properties": {
    "addr:full":"Beeldschermwg 5-9 Amersfoort Utrecht 3821 AH",
    "addr:housenumber":"5-9",
    "addr:postcode":"3821 ah",
    "addr:street":"Beeldschermwg",
    "iso:country":"NL",
    "sg:address":"Beeldschermwg 5-9",
    "sg:city":"Amersfoort",
    "sg:orig_category":"Offsetmateriaal",
    "sg:phone":"+31 33 455 7501",
    "sg:postcode":"3821 AH",
    "sg:province":"Utrecht",
    "wof:name":"Beijersbergen & Partners Bv",
    "wof:placetype":"venue"
},
  "geometry": {"coordinates":[5.417625,52.17849],"type":"Point"}
}