{
  "type": "Feature",
  "properties": {
    "addr:full":"Polderwg 92 Amsterdam North Holland 1093 KP",
    "addr:housenumber":"92",
    "addr:postcode":"1093 kp",
    "addr:street":"Polderwg",
    "iso:country":"NL",
    "sg:address":"Polderwg 92",
    "sg:city":"Amsterdam",
    "sg:orig_category":"Vertaalbureaus",
    "sg:phone":"+31 20 622 9749",
    "sg:postcode":"1093 KP",
    "sg:province":"North Holland",
    "wof:name":"Holland Bombay",
    "wof:placetype":"venue"
},
  "geometry": {"coordinates":[4.928607,52.35743],"type":"Point"}
}