{
  "type": "Feature",
  "properties": {
    "addr:full":"Sperwerstr 14 Wychen BD.70 6601 BD",
    "addr:housenumber":"14",
    "addr:postcode":"6601",
    "addr:street":"Sperwerstr;Bd",
    "iso:country":"NL",
    "sg:address":"Sperwerstr 14",
    "sg:city":"Wychen",
    "sg:orig_category":"Autorijscholen",
    "sg:phone":"+31 24 641 3860",
    "sg:postcode":"6601 BD",
    "sg:province":"BD.70",
    "wof:name":"Loet & Roland Van Perlo",
    "wof:placetype":"venue"
},
  "geometry": {"coordinates":[89.21734600000001,23.945801],"type":"Point"}
}