{
  "type": "Feature",
  "properties": {
    "addr:full":"Hengelosestr 57 Haaksbergen NL.08 7482 AB",
    "addr:housenumber":"57;nl.08",
    "addr:postcode":"7482 ab",
    "addr:street":"Hengelosestr",
    "iso:country":"NL",
    "sg:address":"Hengelosestr 57",
    "sg:city":"Haaksbergen",
    "sg:orig_category":"Onderhoudswerken",
    "sg:phone":"+31 53 572 1673",
    "sg:postcode":"7482 AB",
    "sg:province":"NL.08",
    "wof:name":"Broekkamp, R H J",
    "wof:placetype":"venue"
},
  "geometry": {"coordinates":[6.739573,52.178009],"type":"Point"}
}