{
  "type": "Feature",
  "properties": {
    "addr:full":"Lingedk 86 Geldermalsen Gelderland 4191 VH",
    "addr:housenumber":"86",
    "addr:postcode":"4191 vh",
    "addr:street":"Lingedk;Gelderland",
    "iso:country":"NL",
    "sg:address":"Lingedk 86",
    "sg:city":"Geldermalsen",
    "sg:orig_category":"Journalisten Freelance",
    "sg:phone":"+31 345 574 115",
    "sg:postcode":"4191 VH",
    "sg:province":"Gelderland",
    "wof:name":"Wwtb",
    "wof:placetype":"venue"
},
  "geometry": {"coordinates":[5.316329,51.88821],"type":"Point"}
}