{
  "type": "Feature",
  "properties": {
    "iso:country":"NL",
    "sg:address":"L Vyverberg 12",
    "sg:city":"S Gravenhage",
    "sg:orig_category":"Ambassades/Consulaten",
    "sg:phone":"+31 70 312 3456",
    "sg:postcode":"2513 AC",
    "sg:province":"Zuid-Holland",
    "wof:name":"Belgi\u00eb Ambassade Van",
    "wof:placetype":"venue"
},
  "geometry": {"coordinates":[4.30339,52.078442],"type":"Point"}
}