{
  "type": "Feature",
  "properties": {
    "iso:country":"NL",
    "sg:address":"Handelsln 9",
    "sg:city":"Uden",
    "sg:orig_category":"Bedden En Matrassen",
    "sg:phone":"+31 413 331 349",
    "sg:postcode":"5405 AE",
    "sg:province":"North Brabant",
    "wof:name":"Dorma?l Bv",
    "wof:placetype":"venue"
},
  "geometry": {"coordinates":[5.618265,51.657413],"type":"Point"}
}