{
  "type": "Feature",
  "properties": {
    "iso:country":"NL",
    "sg:address":"De Schans 1908",
    "sg:city":"Lelystad",
    "sg:orig_category":"Boekhouders",
    "sg:phone":"+31 320 220 993",
    "sg:postcode":"8231 KM",
    "sg:province":"NL.",
    "wof:name":"Administratie Verzorging Joko",
    "wof:placetype":"venue"
},
  "geometry": {"coordinates":[5.47369,52.514961],"type":"Point"}
}