{
  "type": "Feature",
  "properties": {
    "addr:full":"Blankenburgerstraat 23 Haaksbergen Overijssel 7481 EA",
    "addr:housenumber":"23",
    "addr:postcode":"7481 ea",
    "addr:street":"Blankenburgerstraat",
    "iso:country":"NL",
    "sg:address":"Blankenburgerstraat 23",
    "sg:city":"Haaksbergen",
    "sg:orig_category":"Drukkerijen And Copyshops",
    "sg:phone":"+31 53 572 1352",
    "sg:postcode":"7481 EA",
    "sg:province":"Overijssel",
    "wof:name":"Drukkerij Van Ooijen",
    "wof:placetype":"venue"
},
  "geometry": {"coordinates":[6.742577,52.156227],"type":"Point"}
}