{
  "type": "Feature",
  "properties": {
    "addr:full":"Beeklaan 277 'S Gravenhage South Holland 2562 AH",
    "addr:housenumber":"277 '",
    "addr:postcode":"2562 ah",
    "addr:street":"Beeklaan",
    "iso:country":"NL",
    "sg:address":"Beeklaan 277",
    "sg:city":"'S Gravenhage",
    "sg:classifiers":[
        {
            "category":"Communications",
            "subcategory":"Television Station",
            "type":"Services"
        }
    ],
    "sg:phone":"+31 70 360 5414",
    "sg:postcode":"2562 AH",
    "sg:province":"South Holland",
    "sg:tags":[
        "video",
        "audio",
        "verhuur"
    ],
    "wof:name":"Ram'S Film",
    "wof:placetype":"venue"
},
  "geometry": {"coordinates":[4.279974,52.075806],"type":"Point"}
}