{
  "type": "Feature",
  "properties": {
    "iso:country":"NL",
    "sg:address":"Z Spierdykerwg 18",
    "sg:city":"De Goorn",
    "sg:orig_category":"Bloemen En Planten - Groothandel",
    "sg:phone":"+31 229 541 283",
    "sg:postcode":"1648 LA",
    "sg:province":"Noord-Holland",
    "wof:name":"Nieuwendijk, Erwin",
    "wof:placetype":"venue"
},
  "geometry": {"coordinates":[4.945473,52.630692],"type":"Point"}
}