{
  "type": "Feature",
  "properties": {
    "addr:full":"Friesestrwg 191 Groningen Groningen 9743 AC",
    "addr:housenumber":"191",
    "addr:postcode":"9743 ac",
    "iso:country":"NL",
    "sg:address":"Friesestrwg 191",
    "sg:city":"Groningen",
    "sg:orig_category":"Bodemonderzoek",
    "sg:phone":"+31 50 303 9300",
    "sg:postcode":"9743 AC",
    "sg:province":"Groningen",
    "wof:name":"Sialtech Praktische Milieutechniek",
    "wof:placetype":"venue"
},
  "geometry": {"coordinates":[6.5306,53.22348],"type":"Point"}
}