{
  "type": "Feature",
  "properties": {
    "addr:full":"Schoolstr 46 Bergum Friesland 9251 EC",
    "addr:housenumber":"46",
    "addr:postcode":"9251 ec",
    "addr:street":"Schoolstr",
    "iso:country":"NL",
    "sg:address":"Schoolstr 46",
    "sg:city":"Bergum",
    "sg:orig_category":"Boeken En Tijdschriften",
    "sg:phone":"+31 511 463 737",
    "sg:postcode":"9251 EC",
    "sg:province":"Friesland",
    "wof:name":"Boekhandel Bergum",
    "wof:placetype":"venue"
},
  "geometry": {"coordinates":[5.99145,53.192455],"type":"Point"}
}