{
  "type": "Feature",
  "properties": {
    "addr:full":"In De Cramer 164 Heerlen Limburg 6412 PM",
    "addr:housenumber":"164",
    "addr:postcode":"6412 pm",
    "addr:street":"In De Cramer",
    "iso:country":"NL",
    "sg:address":"In De Cramer 164",
    "sg:city":"Heerlen",
    "sg:orig_category":"Verlichting And Huishoudartikelen",
    "sg:phone":"+31 45 575 4203",
    "sg:postcode":"6412 PM",
    "sg:province":"Limburg",
    "wof:name":"Leenbakker",
    "wof:placetype":"venue"
},
  "geometry": {"coordinates":[5.942777,50.900288],"type":"Point"}
}