{
  "type": "Feature",
  "properties": {
    "addr:full":"Meerwg 14 Bennebroek Noord-Holland 2121 VA",
    "addr:housenumber":"14",
    "addr:postcode":"2121",
    "addr:street":"Meerwg",
    "iso:country":"NL",
    "sg:address":"Meerwg 14",
    "sg:city":"Bennebroek",
    "sg:orig_category":"Machineonderhoud En -Reparatie",
    "sg:phone":"+31 23 584 9008",
    "sg:postcode":"2121 VA",
    "sg:province":"Noord-Holland",
    "wof:name":"Griekspoor",
    "wof:placetype":"venue"
},
  "geometry": {"coordinates":[4.603369,52.319893],"type":"Point"}
}