{
  "type": "Feature",
  "properties": {
    "iso:country":"NL",
    "sg:address":"C Houtmanstr 21",
    "sg:city":"Utrecht",
    "sg:orig_category":"Advocaten En Advocatenkantoren",
    "sg:phone":"+31 30 275 8999",
    "sg:postcode":"3572 LT",
    "sg:province":"Utrecht",
    "sg:website":"http://www.vanderlindenadvocaten.nl",
    "wof:name":"Linden Advocatenkantoor, Van Der",
    "wof:placetype":"venue"
},
  "geometry": {"coordinates":[5.142099,52.09903],"type":"Point"}
}