{
  "type": "Feature",
  "properties": {
    "iso:country":"NL",
    "sg:address":"Vughterstr 39-B",
    "sg:city":"S Hertogenbosch",
    "sg:orig_category":"Mode-Artikelen Dames En Heren",
    "sg:phone":"+31 73 690 0480",
    "sg:postcode":"5211 EX",
    "sg:province":"North Brabant",
    "wof:name":"Gruijter, Hans De",
    "wof:placetype":"venue"
},
  "geometry": {"coordinates":[5.301011,51.687416],"type":"Point"}
}