{
  "type": "Feature",
  "properties": {
    "addr:full":"Minstreelstr 2 Rotterdam Zuid-Holland 3051 PK",
    "addr:housenumber":"2",
    "addr:postcode":"3051 pk",
    "addr:street":"Minstreelstr",
    "iso:country":"NL",
    "sg:address":"Minstreelstr 2",
    "sg:city":"Rotterdam",
    "sg:orig_category":"Belastingconsulenten/ Belastingadviseurs",
    "sg:phone":"+31 10 211 2080",
    "sg:postcode":"3051 PK",
    "sg:province":"Zuid-Holland",
    "sg:website":"http://www.veurtjes-katz.com",
    "wof:name":"Veurtjes & Katz",
    "wof:placetype":"venue"
},
  "geometry": {"coordinates":[4.482834,51.94392],"type":"Point"}
}