{
  "type": "Feature",
  "properties": {
    "addr:full":"Katendrechtse Lagedijk 235 Rotterdam Zuid-Holland 3083 GC",
    "addr:housenumber":"235",
    "addr:postcode":"3083 gc",
    "addr:street":"Katendrechtse Lagedijk",
    "iso:country":"NL",
    "sg:address":"Katendrechtse Lagedijk 235",
    "sg:city":"Rotterdam",
    "sg:classifiers":[
        {
            "category":"Fast Food",
            "type":"Food & Drink"
        }
    ],
    "sg:phone":"+31 10 480 7206",
    "sg:postcode":"3083 GC",
    "sg:province":"Zuid-Holland",
    "sg:tags":[
        "afhaal",
        "restaurant"
    ],
    "wof:name":"Pizzeria Piccolino",
    "wof:placetype":"venue"
},
  "geometry": {"coordinates":[4.478315,51.890678],"type":"Point"}
}