{
  "type": "Feature",
  "properties": {
    "iso:country":"NL",
    "sg:address":"Cederlaan 31",
    "sg:city":"Rijswijk Zh",
    "sg:orig_category":"Boekhouders",
    "sg:phone":"+31 70 399 2747",
    "sg:postcode":"2282 KC",
    "sg:province":"South Holland",
    "wof:name":"M P Van Blyswyk",
    "wof:placetype":"venue"
},
  "geometry": {"coordinates":[4.341668,52.049999],"type":"Point"}
}