{
  "type": "Feature",
  "properties": {
    "iso:country":"NL",
    "sg:address":"Oostermaatweg 4A",
    "sg:city":"Vriezenveen",
    "sg:orig_category":"Zuivelproducten",
    "sg:phone":"+31 546 561 366",
    "sg:postcode":"7671 RN",
    "sg:province":"NL.08",
    "wof:name":"J. Holland",
    "wof:placetype":"venue"
},
  "geometry": {"coordinates":[6.659113,52.396675],"type":"Point"}
}