{
  "type": "Feature",
  "properties": {
    "addr:full":"Oostermaatweg 4A Vriezenveen NL.08 7671 RN",
    "addr:housenumber":"4a;nl.08",
    "addr:postcode":"7671 rn",
    "addr:street":"Oostermaatweg",
    "iso:country":"NL",
    "sg:address":"Oostermaatweg 4A",
    "sg:city":"Vriezenveen",
    "sg:orig_category":"Zuivelproducten",
    "sg:phone":"+31 546 561 366",
    "sg:postcode":"7671 RN",
    "sg:province":"NL.08",
    "wof:name":"J. Holland",
    "wof:placetype":"venue"
},
  "geometry": {"coordinates":[6.659113,52.396675],"type":"Point"}
}