{
  "type": "Feature",
  "properties": {
    "addr:full":"Alexander Battalaan 65 Maastricht Limburg 6221 CC",
    "addr:housenumber":"65",
    "addr:postcode":"6221 cc",
    "addr:street":"Alexander Battalaan",
    "iso:country":"NL",
    "sg:address":"Alexander Battalaan 65",
    "sg:city":"Maastricht",
    "sg:orig_category":"Advocaten And Juridische Adviseurs",
    "sg:phone":"+31 43 325 4258",
    "sg:postcode":"6221 CC",
    "sg:province":"Limburg",
    "wof:name":"Advokatenkantoor Wyck",
    "wof:placetype":"venue"
},
  "geometry": {"coordinates":[5.704147,50.848518],"type":"Point"}
}