{
  "type": "Feature",
  "properties": {
    "addr:full":"Wulk 1 Noordwijk Zh Zuid-Holland 2201 VH",
    "addr:housenumber":"1",
    "addr:postcode":"2201 vh",
    "addr:street":"Wulk",
    "iso:country":"NL",
    "sg:address":"Wulk 1",
    "sg:city":"Noordwijk Zh",
    "sg:orig_category":"Loodgieterswerk, Verwarming And Sanitaire Installaties",
    "sg:phone":"+31 71 361 1294",
    "sg:postcode":"2201 VH",
    "sg:province":"Zuid-Holland",
    "wof:name":"F. Onverwagt",
    "wof:placetype":"venue"
},
  "geometry": {"coordinates":[4.443433,52.228016],"type":"Point"}
}