{
  "type": "Feature",
  "properties": {
    "addr:full":"Zanddijk 7 Dordrecht Zuid-Holland 3329 LB",
    "addr:housenumber":"7",
    "addr:postcode":"3329 lb",
    "addr:street":"Zanddijk",
    "iso:country":"NL",
    "sg:address":"Zanddijk 7",
    "sg:city":"Dordrecht",
    "sg:orig_category":"Huizensloop And Bouwrijp Maken",
    "sg:phone":"+31 78 618 1775",
    "sg:postcode":"3329 LB",
    "sg:province":"Zuid-Holland",
    "wof:name":"De Zanddijk",
    "wof:placetype":"venue"
},
  "geometry": {"coordinates":[4.662037,51.757244],"type":"Point"}
}