{
  "type": "Feature",
  "properties": {
    "addr:full":"Oude Moerstraatsebaan 1 Bergen Op Zoom Noord-Brabant 4614 RN",
    "addr:housenumber":"1",
    "addr:postcode":"4614 rn",
    "addr:street":"Oude Moerstraatsebaan",
    "iso:country":"NL",
    "sg:address":"Oude Moerstraatsebaan 1",
    "sg:city":"Bergen Op Zoom",
    "sg:orig_category":"Pompen And Compressoren Fab",
    "sg:phone":"+31 164 254 522",
    "sg:postcode":"4614 RN",
    "sg:province":"Noord-Brabant",
    "wof:name":"Hydrosan Bv",
    "wof:placetype":"venue"
},
  "geometry": {"coordinates":[4.299539,51.507221],"type":"Point"}
}