{
  "type": "Feature",
  "properties": {
    "addr:full":"Bennekelstr 15 Eindhoven Noord-Brabant 5654 DB",
    "addr:housenumber":"15",
    "addr:postcode":"5654 db",
    "addr:street":"Bennekelstr",
    "iso:country":"NL",
    "sg:address":"Bennekelstr 15",
    "sg:city":"Eindhoven",
    "sg:orig_category":"Babyartikelen",
    "sg:phone":"+31 40 246 0646",
    "sg:postcode":"5654 DB",
    "sg:province":"Noord-Brabant",
    "sg:website":"http://www.babyboardrent.nl",
    "wof:name":"Baby Boardrent",
    "wof:placetype":"venue"
},
  "geometry": {"coordinates":[5.462173,51.422695],"type":"Point"}
}