{
  "type": "Feature",
  "properties": {
    "addr:full":"Postbus 239 Zoetermeer Zuid-Holland 2700 AE",
    "addr:housenumber":"239",
    "addr:postcode":"2700 ae",
    "addr:street":"Postbus",
    "iso:country":"NL",
    "sg:address":"Postbus 239",
    "sg:city":"Zoetermeer",
    "sg:orig_category":"Adviesbureaus Marketing",
    "sg:phone":"+31 79 331 9873",
    "sg:postcode":"2700 AE",
    "sg:province":"Zuid-Holland",
    "wof:name":"Double Vision Projects",
    "wof:placetype":"venue"
},
  "geometry": {"coordinates":[4.48892,52.06308],"type":"Point"}
}