{
  "type": "Feature",
  "properties": {
    "addr:full":"Wildekampseweg 15 Wapenveld Gelderland 8191 BP",
    "addr:housenumber":"15",
    "addr:postcode":"8191 bp",
    "addr:street":"Wildekampseweg;Gelderland",
    "iso:country":"NL",
    "sg:address":"Wildekampseweg 15",
    "sg:city":"Wapenveld",
    "sg:orig_category":"Kantoorartikelen",
    "sg:phone":"+31 38 447 8439",
    "sg:postcode":"8191 BP",
    "sg:province":"Gelderland",
    "wof:name":"H. Van Rijssen",
    "wof:placetype":"venue"
},
  "geometry": {"coordinates":[6.0736289024,52.4300270081],"type":"Point"}
}