{
  "type": "Feature",
  "properties": {
    "addr:full":"Boomgaardweg 6 Geervliet Zuid-Holland 3211 AC",
    "addr:housenumber":"6",
    "addr:postcode":"3211 ac",
    "addr:street":"Boomgaardweg",
    "iso:country":"NL",
    "sg:address":"Boomgaardweg 6",
    "sg:city":"Geervliet",
    "sg:classifiers":[
        {
            "category":"Education",
            "subcategory":"Preschool",
            "type":"Public Place"
        }
    ],
    "sg:phone":"+31 181 661 675",
    "sg:postcode":"3211 AC",
    "sg:province":"Zuid-Holland",
    "sg:tags":[
        "kleuteronderwijs",
        "basis-"
    ],
    "wof:name":"Obs Markenburg",
    "wof:placetype":"venue"
},
  "geometry": {"coordinates":[4.26321,51.8615],"type":"Point"}
}