{
  "type": "Feature",
  "properties": {
    "addr:full":"Gentiaan 4 Oldebroek Gelderland 8096 XX",
    "addr:housenumber":"4",
    "addr:postcode":"8096 xx",
    "addr:street":"Gentiaan;Gelderland",
    "iso:country":"NL",
    "sg:address":"Gentiaan 4",
    "sg:city":"Oldebroek",
    "sg:orig_category":"Machineonderhoud En -Reparatie",
    "sg:phone":"+31 525 633 321",
    "sg:postcode":"8096 XX",
    "sg:province":"Gelderland",
    "wof:name":"Norel, Van",
    "wof:placetype":"venue"
},
  "geometry": {"coordinates":[5.902243,52.441257],"type":"Point"}
}