{
  "type": "Feature",
  "properties": {
    "iso:country":"NL",
    "sg:address":"Zeestraat 142",
    "sg:city":"Beverwijk",
    "sg:orig_category":"Verpakkingsmachines Fab",
    "sg:phone":"+31 251 272 088",
    "sg:postcode":"1942 AX",
    "sg:province":"Noord-Holland",
    "wof:name":"Zwager Techniek",
    "wof:placetype":"venue"
},
  "geometry": {"coordinates":[4.64614,52.483158],"type":"Point"}
}