{
  "type": "Feature",
  "properties": {
    "iso:country":"NL",
    "sg:address":"Grote Kerkplein 15",
    "sg:city":"Zwolle",
    "sg:orig_category":"Overheidsdiensten",
    "sg:phone":"+31 38 498 9111",
    "sg:postcode":"8011 PK",
    "sg:province":"Overijssel",
    "wof:name":"Gemeente Zwolle",
    "wof:placetype":"venue"
},
  "geometry": {"coordinates":[6.0923480988,52.5113258362],"type":"Point"}
}