{
  "type": "Feature",
  "properties": {
    "iso:country":"NL",
    "sg:address":"Beulkstr 5-7",
    "sg:city":"Wechelderzande",
    "sg:orig_category":"Houtgroothandel",
    "sg:phone":"+31 33091450",
    "sg:postcode":"B-22 75",
    "sg:website":"http://www.helsenhout.be",
    "wof:name":"Helsen Houtbedrijf",
    "wof:placetype":"venue"
},
  "geometry": {"coordinates":[4.78596,51.264091],"type":"Point"}
}