{
  "type": "Feature",
  "properties": {
    "iso:country":"NL",
    "sg:address":"Plantagewg 17",
    "sg:city":"Alblasserdam",
    "sg:orig_category":"Kappers",
    "sg:phone":"+31 78 691 4281",
    "sg:postcode":"2951 GN",
    "sg:province":"Zuid-Holland",
    "wof:name":"Pico Bello",
    "wof:placetype":"venue"
},
  "geometry": {"coordinates":[4.660931,51.862148],"type":"Point"}
}