{
  "type": "Feature",
  "properties": {
    "addr:full":"Herengr 495 Amsterdam North Holland 1017 BT",
    "addr:housenumber":"495",
    "addr:postcode":"1017 bt",
    "iso:country":"NL",
    "sg:address":"Herengr 495",
    "sg:city":"Amsterdam",
    "sg:orig_category":"Adviesbureaus Bedrijfsorganisatie",
    "sg:phone":"+31 20 528 7322",
    "sg:postcode":"1017 BT",
    "sg:province":"North Holland",
    "sg:website":"http://www.upstreamconsulting.nl",
    "wof:name":"Upstream Consulting",
    "wof:placetype":"venue"
},
  "geometry": {"coordinates":[4.891268,52.365677],"type":"Point"}
}