{
  "type": "Feature",
  "properties": {
    "addr:full":"Duivendijk 4 Nuenen Noord-Brabant 5672 AD",
    "addr:housenumber":"4",
    "addr:postcode":"5672 ad",
    "addr:street":"Duivendijk",
    "iso:country":"NL",
    "sg:address":"Duivendijk 4",
    "sg:city":"Nuenen",
    "sg:orig_category":"Meubelzaken, Woning- And Keukeninrichting",
    "sg:phone":"+31 40 283 6057",
    "sg:postcode":"5672 AD",
    "sg:province":"Noord-Brabant",
    "wof:name":"Goossens Meubelen Bv",
    "wof:placetype":"venue"
},
  "geometry": {"coordinates":[5.537351,51.467735],"type":"Point"}
}