{
  "type": "Feature",
  "properties": {
    "addr:full":"Hoofdstr 62 Veenendaal Utrecht 3901 AS",
    "addr:housenumber":"62",
    "addr:postcode":"3901 as",
    "addr:street":"Hoofdstr",
    "iso:country":"NL",
    "sg:address":"Hoofdstr 62",
    "sg:city":"Veenendaal",
    "sg:orig_category":"Dameskleding",
    "sg:phone":"+31 318 540 444",
    "sg:postcode":"3901 AS",
    "sg:province":"Utrecht",
    "wof:name":"Fan Fan La Tulipe",
    "wof:placetype":"venue"
},
  "geometry": {"coordinates":[5.556438,52.027576],"type":"Point"}
}