{
  "type": "Feature",
  "properties": {
    "addr:full":"Marconistr 16 Rotterdam Zuid-Holland 3029 AK",
    "addr:housenumber":"16",
    "addr:postcode":"3029 ak",
    "addr:street":"Marconistr",
    "iso:country":"NL",
    "sg:address":"Marconistr 16",
    "sg:city":"Rotterdam",
    "sg:orig_category":"Verzekerings- Maatschappijen",
    "sg:phone":"+31 10 448 3050",
    "sg:postcode":"3029 AK",
    "sg:province":"Zuid-Holland",
    "wof:name":"Bishopsgate Schadeverzekering Nv",
    "wof:placetype":"venue"
},
  "geometry": {"coordinates":[4.428163,51.912334],"type":"Point"}
}