{
  "type": "Feature",
  "properties": {
    "addr:full":"A Paulownastr 27 S Gravenhage South Holland 2518 BA",
    "addr:housenumber":"27",
    "addr:postcode":"2518 ba",
    "addr:street":"S Gravenhage",
    "iso:country":"NL",
    "sg:address":"A Paulownastr 27",
    "sg:city":"S Gravenhage",
    "sg:orig_category":"Kunsthandel",
    "sg:phone":"+31 70 363 7192",
    "sg:postcode":"2518 BA",
    "sg:province":"South Holland",
    "sg:website":"http://www.artonline.nl/kunsthandel/elshout",
    "wof:name":"Elshout J A P Van Den",
    "wof:placetype":"venue"
},
  "geometry": {"coordinates":[4.29348,52.080318],"type":"Point"}
}