{
  "type": "Feature",
  "properties": {
    "addr:full":"Pettelaarpk 22 S Hertogenbosch Noord-Brabant 5216 PD",
    "addr:housenumber":"22",
    "addr:postcode":"5216 pd",
    "addr:street":"Pettelaarpk;S",
    "iso:country":"NL",
    "sg:address":"Pettelaarpk 22",
    "sg:city":"S Hertogenbosch",
    "sg:orig_category":"Adviesbureaus Bedrijfsorganisatie",
    "sg:phone":"+31 73 613 6003",
    "sg:postcode":"5216 PD",
    "sg:province":"Noord-Brabant",
    "wof:name":"Geerts",
    "wof:placetype":"venue"
},
  "geometry": {"coordinates":[5.333878,51.679329],"type":"Point"}
}