{
  "type": "Feature",
  "properties": {
    "addr:full":"W.A. Scholtenstraat 22 Groningen Groningen 9712  K",
    "addr:housenumber":"22;9712",
    "addr:postcode":"k",
    "addr:street":"W.A. Scholtenstraat",
    "iso:country":"NL",
    "sg:address":"W.A. Scholtenstraat 22",
    "sg:city":"Groningen",
    "sg:orig_category":"Loodgieterswerk, Verwarming And Sanitaire Installaties",
    "sg:phone":"+31 50 318 2277",
    "sg:postcode":"9712  K",
    "sg:province":"Groningen",
    "wof:name":"Brakel Installateurs",
    "wof:placetype":"venue"
},
  "geometry": {"coordinates":[6.569616,53.223251],"type":"Point"}
}