{
  "type": "Feature",
  "properties": {
    "addr:full":"Voorstraat 28 Harlingen Provincie Friesland 8861 BL",
    "addr:housenumber":"28",
    "addr:postcode":"8861 bl",
    "addr:street":"Voorstraat;Provincie Friesland",
    "iso:country":"NL",
    "sg:address":"Voorstraat 28",
    "sg:city":"Harlingen",
    "sg:orig_category":"Discountwinkels",
    "sg:phone":"+31 517 430 499",
    "sg:postcode":"8861 BL",
    "sg:province":"Provincie Friesland",
    "wof:name":"Bentex",
    "wof:placetype":"venue"
},
  "geometry": {"coordinates":[5.417577,53.174801],"type":"Point"}
}