{
  "type": "Feature",
  "properties": {
    "addr:full":"Windmolen 14/A Almelo Overijssel 7609 NN",
    "addr:housenumber":"14 / a",
    "addr:postcode":"7609 nn",
    "addr:street":"Windmolen",
    "iso:country":"NL",
    "sg:address":"Windmolen 14/A",
    "sg:city":"Almelo",
    "sg:classifiers":[
        {
            "category":"Manufacturing",
            "subcategory":"Metals",
            "type":"Manufacturing & Wholesale Goods"
        }
    ],
    "sg:phone":"+31 546 815 065",
    "sg:postcode":"7609 NN",
    "sg:province":"Overijssel",
    "sg:tags":[
        "aluminium"
    ],
    "sg:website":"http://www.mkproducts.nl",
    "wof:name":"Mk Products",
    "wof:placetype":"venue"
},
  "geometry": {"coordinates":[6.652458,52.337269],"type":"Point"}
}