{
  "type": "Feature",
  "properties": {
    "addr:full":"Winschoterwg 1 Groningen Groningen 9723 CG",
    "addr:housenumber":"1",
    "addr:postcode":"9723 cg",
    "addr:street":"Winschoterwg",
    "iso:country":"NL",
    "sg:address":"Winschoterwg 1",
    "sg:city":"Groningen",
    "sg:orig_category":"Vuilnisafvoer",
    "sg:phone":"+31 50 541 6633",
    "sg:postcode":"9723 CG",
    "sg:province":"Groningen",
    "wof:name":"Stainkoeln, De",
    "wof:placetype":"venue"
},
  "geometry": {"coordinates":[6.62808,53.194241],"type":"Point"}
}