{
  "type": "Feature",
  "properties": {
    "iso:country":"NL",
    "sg:address":"Van Toulon Vd Koogwg 2",
    "sg:city":"Oosterbeek",
    "sg:orig_category":"Herenmodezaken",
    "sg:phone":"+31 26 333 2184",
    "sg:postcode":"6862 EC",
    "sg:province":"Gelderland",
    "wof:name":"Harold Van De Ven Mannenmode",
    "wof:placetype":"venue"
},
  "geometry": {"coordinates":[5.845034,51.986801],"type":"Point"}
}