{
  "type": "Feature",
  "properties": {
    "iso:country":"NL",
    "sg:address":"Wieken 70",
    "sg:city":"Schaijk",
    "sg:orig_category":"Marktonderzoekbureaus",
    "sg:phone":"+31 486 462 202",
    "sg:postcode":"5374 JW",
    "sg:province":"North Brabant",
    "wof:name":"Th.J.M. Platenburg",
    "wof:placetype":"venue"
},
  "geometry": {"coordinates":[5.628508,51.74033],"type":"Point"}
}