{
  "type": "Feature",
  "properties": {
    "addr:full":"Deukelven 95 Heemskerk Noord-Holland 1963 SN",
    "addr:housenumber":"95",
    "addr:postcode":"1963 sn",
    "addr:street":"Deukelven",
    "iso:country":"NL",
    "sg:address":"Deukelven 95",
    "sg:city":"Heemskerk",
    "sg:orig_category":"Kinderopvang Behalve Thuis",
    "sg:phone":"+31 251 255 421",
    "sg:postcode":"1963 SN",
    "sg:province":"Noord-Holland",
    "wof:name":"Naschoolse Opvang De Blauwe Reiger",
    "wof:placetype":"venue"
},
  "geometry": {"coordinates":[4.69104,52.51186],"type":"Point"}
}