{
  "type": "Feature",
  "properties": {
    "iso:country":"NL",
    "sg:address":"Pieter Lieftinckweg 14",
    "sg:city":"Zaandam",
    "sg:orig_category":"Diverse Grafische Activiteiten",
    "sg:phone":"+31 75 670 3948",
    "sg:postcode":"1505 HX",
    "sg:province":"Noord-Holland",
    "wof:name":"Boekbinderij Van Waarden Bv",
    "wof:placetype":"venue"
},
  "geometry": {"coordinates":[4.841205,52.428593],"type":"Point"}
}