{
  "type": "Feature",
  "properties": {
    "addr:full":"Hoofdstraat 112 Posterholt Limburg 6061 CG",
    "addr:housenumber":"112",
    "addr:postcode":"6061 cg",
    "addr:street":"Hoofdstraat",
    "iso:country":"NL",
    "sg:address":"Hoofdstraat 112",
    "sg:city":"Posterholt",
    "sg:orig_category":"Kappers",
    "sg:phone":"+31 475 403 338",
    "sg:postcode":"6061 CG",
    "sg:province":"Limburg",
    "wof:name":"Nix Haarmode A.A.W.H. Smitz",
    "wof:placetype":"venue"
},
  "geometry": {"coordinates":[6.03599,51.121819],"type":"Point"}
}