{
  "type": "Feature",
  "properties": {
    "addr:full":"Struikheide 54 Heerenveen Friesland 8445 SE",
    "addr:housenumber":"54",
    "addr:postcode":"8445 se",
    "addr:street":"Struikheide",
    "iso:country":"NL",
    "sg:address":"Struikheide 54",
    "sg:city":"Heerenveen",
    "sg:orig_category":"Meubelen - Fabrieken En Groothandel",
    "sg:phone":"+31 513 682 684",
    "sg:postcode":"8445 SE",
    "sg:province":"Friesland",
    "sg:website":"http://www.new-id.nl",
    "wof:name":"New Id",
    "wof:placetype":"venue"
},
  "geometry": {"coordinates":[5.934939,52.936436],"type":"Point"}
}