{
  "type": "Feature",
  "properties": {
    "addr:full":"Noorderstat Str 34 Groningen Groningen 9717 KP",
    "addr:housenumber":"34",
    "addr:postcode":"9717 kp",
    "addr:street":"Str",
    "iso:country":"NL",
    "sg:address":"Noorderstat Str 34",
    "sg:city":"Groningen",
    "sg:orig_category":"Beeldende Kunstenaars",
    "sg:phone":"+31 50 312 5634",
    "sg:postcode":"9717 KP",
    "sg:province":"Groningen",
    "sg:website":"http://www.lizettemveenhuizen.artolive.com",
    "wof:name":"Veenhuizen, Lizette M",
    "wof:placetype":"venue"
},
  "geometry": {"coordinates":[6.559332,53.22871],"type":"Point"}
}