{
  "type": "Feature",
  "properties": {
    "addr:full":"Ritzema Bosstraat 6 Nieuw Vennep Noord-Holland 2152 XG",
    "addr:housenumber":"6",
    "addr:postcode":"2152 xg",
    "addr:street":"Ritzema Bosstraat;Nieuw Vennep",
    "iso:country":"NL",
    "sg:address":"Ritzema Bosstraat 6",
    "sg:city":"Nieuw Vennep",
    "sg:orig_category":"Zuivelproducten And Spijsoli?n Gh",
    "sg:phone":"+31 252 674 936",
    "sg:postcode":"2152 XG",
    "sg:province":"Noord-Holland",
    "wof:name":"P.M. Smit",
    "wof:placetype":"venue"
},
  "geometry": {"coordinates":[4.631996,52.266869],"type":"Point"}
}