{
  "type": "Feature",
  "properties": {
    "addr:full":"Dokter Slotstraat 2 Nieuw Lekkerland Zuid-Holland 2957 AJ",
    "addr:housenumber":"2",
    "addr:postcode":"2957 aj",
    "addr:street":"Dokter Slotstraat",
    "iso:country":"NL",
    "sg:address":"Dokter Slotstraat 2",
    "sg:city":"Nieuw Lekkerland",
    "sg:orig_category":"Verzekeringen",
    "sg:phone":"+31 184 681 641",
    "sg:postcode":"2957 AJ",
    "sg:province":"Zuid-Holland",
    "wof:name":"Assurantiekantoor Dekker Cv",
    "wof:placetype":"venue"
},
  "geometry": {"coordinates":[4.689243,51.888779],"type":"Point"}
}