{
  "type": "Feature",
  "properties": {
    "addr:full":"Hoofdweg 110 Midwolda Groningen 9681 AK",
    "addr:housenumber":"110",
    "addr:postcode":"9681 ak",
    "addr:street":"Hoofdweg",
    "iso:country":"NL",
    "sg:address":"Hoofdweg 110",
    "sg:city":"Midwolda",
    "sg:orig_category":"Banken And Kredietinstellingen",
    "sg:phone":"+31 597 551 440",
    "sg:postcode":"9681 AK",
    "sg:province":"Groningen",
    "wof:name":"Postagentschap Midwolda",
    "wof:placetype":"venue"
},
  "geometry": {"coordinates":[7.002424,53.193485],"type":"Point"}
}