{
  "type": "Feature",
  "properties": {
    "addr:full":"Karveelweg 9 Maastricht Limburg 6222 NJ",
    "addr:housenumber":"9",
    "addr:postcode":"6222 nj",
    "addr:street":"Karveelweg",
    "iso:country":"NL",
    "sg:address":"Karveelweg 9",
    "sg:city":"Maastricht",
    "sg:orig_category":"Diverse Bedrijfsinstallaties Gh",
    "sg:phone":"+31 43 352 5050",
    "sg:postcode":"6222 NJ",
    "sg:province":"Limburg",
    "wof:name":"Abs Pompen Bv",
    "wof:placetype":"venue"
},
  "geometry": {"coordinates":[5.707062,50.873863],"type":"Point"}
}