{
  "type": "Feature",
  "properties": {
    "addr:full":"De Wyer 1 Hapert Noord-Brabant 5527 EA",
    "addr:housenumber":"1",
    "addr:postcode":"5527 ea",
    "iso:country":"NL",
    "sg:address":"De Wyer 1",
    "sg:city":"Hapert",
    "sg:orig_category":"Notarissen En Notariskantoren",
    "sg:phone":"+31 497 383 250",
    "sg:postcode":"5527 EA",
    "sg:province":"Noord-Brabant",
    "wof:name":"Voskuijlen, Mr J H M Van",
    "wof:placetype":"venue"
},
  "geometry": {"coordinates":[5.258786,51.352222],"type":"Point"}
}