{
  "type": "Feature",
  "properties": {
    "addr:full":"Boterdiep 9 Rotterdam Zuid-Holland 3077 AW",
    "addr:housenumber":"9",
    "addr:postcode":"3077 aw",
    "addr:street":"Boterdiep",
    "iso:country":"NL",
    "sg:address":"Boterdiep 9",
    "sg:city":"Rotterdam",
    "sg:orig_category":"Schilderwerk",
    "sg:phone":"+31 10 483 2373",
    "sg:postcode":"3077 AW",
    "sg:province":"Zuid-Holland",
    "wof:name":"Schildersbedrijf M.C. Stinis Bv",
    "wof:placetype":"venue"
},
  "geometry": {"coordinates":[4.529772,51.895882],"type":"Point"}
}