{
  "type": "Feature",
  "properties": {
    "addr:full":"Amperestr 13 Nunspeet Gelderland 8071 PH",
    "addr:housenumber":"13",
    "addr:postcode":"8071",
    "addr:street":"Amperestr;Gelderland",
    "iso:country":"NL",
    "sg:address":"Amperestr 13",
    "sg:city":"Nunspeet",
    "sg:orig_category":"Gordijnstoffen - Fabrieken En Groothandel",
    "sg:phone":"+31 341 260 424",
    "sg:postcode":"8071 PH",
    "sg:province":"Gelderland",
    "wof:name":"Curdes Bv",
    "wof:placetype":"venue"
},
  "geometry": {"coordinates":[5.765745,52.36673],"type":"Point"}
}