{
  "type": "Feature",
  "properties": {
    "addr:full":"Scheperswg 6A Breukelen Ut Utrecht 3621 JK",
    "addr:housenumber":"6a",
    "addr:postcode":"3621 jk",
    "addr:street":"Scheperswg",
    "iso:country":"NL",
    "sg:address":"Scheperswg 6A",
    "sg:city":"Breukelen Ut",
    "sg:orig_category":"Scholen Voor Algemeen Voortgezet Onderwijs",
    "sg:phone":"+31 346 258 060",
    "sg:postcode":"3621 JK",
    "sg:province":"Utrecht",
    "wof:name":"Broklede Reg Scholengem",
    "wof:placetype":"venue"
},
  "geometry": {"coordinates":[4.995445,52.177624],"type":"Point"}
}