{
  "type": "Feature",
  "properties": {
    "addr:full":"Raiffeisenstr 24 St Annaland Zeeland 4697 CG",
    "addr:housenumber":"24",
    "addr:postcode":"4697 cg",
    "addr:street":"Raiffeisenstr",
    "iso:country":"NL",
    "sg:address":"Raiffeisenstr 24",
    "sg:city":"St Annaland",
    "sg:orig_category":"Banken",
    "sg:phone":"+31 166 658 100",
    "sg:postcode":"4697 CG",
    "sg:province":"Zeeland",
    "sg:website":"http://www.rabobank.nl",
    "wof:name":"Rabobank",
    "wof:placetype":"venue"
},
  "geometry": {"coordinates":[4.101047,51.597675],"type":"Point"}
}