{
  "type": "Feature",
  "properties": {
    "addr:full":"Walstro 15 Nootdorp Zuid-Holland 2631 SE",
    "addr:housenumber":"15",
    "addr:postcode":"2631 se",
    "addr:street":"Walstro",
    "iso:country":"NL",
    "sg:address":"Walstro 15",
    "sg:city":"Nootdorp",
    "sg:orig_category":"Webdesign Bureaus",
    "sg:phone":"+31 6 24539942",
    "sg:postcode":"2631 SE",
    "sg:province":"Zuid-Holland",
    "sg:website":"http://www.cdwdesign.nl",
    "wof:name":"Cdw",
    "wof:placetype":"venue"
},
  "geometry": {"coordinates":[4.3992629051,52.040512085],"type":"Point"}
}