{
  "type": "Feature",
  "properties": {
    "addr:full":"Burgemeester Elsenlaan 15 Rijswijk Zh Zuid-Holland 2282 NA",
    "addr:housenumber":"15",
    "addr:postcode":"zh;2282 na",
    "addr:street":"Burgemeester Elsenlaan",
    "iso:country":"NL",
    "sg:address":"Burgemeester Elsenlaan 15",
    "sg:city":"Rijswijk Zh",
    "sg:orig_category":"Autokeuringen",
    "sg:phone":"+31 70 399 2798",
    "sg:postcode":"2282 NA",
    "sg:province":"Zuid-Holland",
    "wof:name":"Shell",
    "wof:placetype":"venue"
},
  "geometry": {"coordinates":[4.328275,52.051586],"type":"Point"}
}