{
  "type": "Feature",
  "properties": {
    "iso:country":"NL",
    "sg:address":"Robbertsmatenstr 15",
    "sg:city":"Elburg",
    "sg:orig_category":"Metaaldraaierijen",
    "sg:phone":"+31 525 681 988",
    "sg:postcode":"8081 HL",
    "sg:province":"Gelderland",
    "wof:name":"Ardesch Bv",
    "wof:placetype":"venue"
},
  "geometry": {"coordinates":[5.834733,52.455654],"type":"Point"}
}