{
  "type": "Feature",
  "properties": {
    "addr:full":"Zomerdykstr 18 Amsterdam Noord-Holland 1079 XB",
    "addr:housenumber":"18",
    "addr:postcode":"1079 xb",
    "addr:street":"Zomerdykstr",
    "iso:country":"NL",
    "sg:address":"Zomerdykstr 18",
    "sg:city":"Amsterdam",
    "sg:orig_category":"Beeldende Kunstenaars",
    "sg:phone":"+31 20 644 5130",
    "sg:postcode":"1079 XB",
    "sg:province":"Noord-Holland",
    "wof:name":"Jorna, J H",
    "wof:placetype":"venue"
},
  "geometry": {"coordinates":[4.904076,52.342503],"type":"Point"}
}