{
  "type": "Feature",
  "properties": {
    "addr:full":"Postbus 73 Moergestel North Brabant 5066 ZH",
    "addr:housenumber":"73",
    "addr:postcode":"5066 zh",
    "addr:street":"Postbus",
    "iso:country":"NL",
    "sg:address":"Postbus 73",
    "sg:city":"Moergestel",
    "sg:orig_category":"Voetbalverenigingen",
    "sg:phone":"+31 13 513 0469",
    "sg:postcode":"5066 ZH",
    "sg:province":"North Brabant",
    "wof:name":"Audacia",
    "wof:placetype":"venue"
},
  "geometry": {"coordinates":[5.183641,51.545498],"type":"Point"}
}