{
  "type": "Feature",
  "properties": {
    "iso:country":"NL",
    "sg:address":"Pliniusstraat 12",
    "sg:city":"Heerlen",
    "sg:orig_category":"Bouwmaterialen Gh",
    "sg:phone":"+31 45 571 0661",
    "sg:postcode":"6417 TR",
    "sg:province":"Limburg",
    "wof:name":"Altintas Imp-Exp",
    "wof:placetype":"venue"
},
  "geometry": {"coordinates":[5.977679,50.87709],"type":"Point"}
}