{
  "type": "Feature",
  "properties": {
    "addr:full":"Driewegpln 5 Gouda Zuid-Holland 2805 HV",
    "addr:housenumber":"5",
    "addr:postcode":"2805 hv",
    "addr:street":"Driewegpln",
    "iso:country":"NL",
    "sg:address":"Driewegpln 5",
    "sg:city":"Gouda",
    "sg:orig_category":"Kappers",
    "sg:phone":"+31 182 515 225",
    "sg:postcode":"2805 HV",
    "sg:province":"Zuid-Holland",
    "wof:name":"Helfteren, T Van",
    "wof:placetype":"venue"
},
  "geometry": {"coordinates":[4.7237467766,52.0220527649],"type":"Point"}
}