{
  "type": "Feature",
  "properties": {
    "addr:full":"De Tempelier 15 Aarle Rixtel Noord-Brabant 5735 JG",
    "addr:housenumber":"15",
    "addr:postcode":"5735 jg",
    "addr:street":"De Tempelier",
    "iso:country":"NL",
    "sg:address":"De Tempelier 15",
    "sg:city":"Aarle Rixtel",
    "sg:orig_category":"Verzekeringen - Verzekeringskantoren",
    "sg:phone":"+31 492 386 133",
    "sg:postcode":"5735 JG",
    "sg:province":"Noord-Brabant",
    "wof:name":"Relou, A J",
    "wof:placetype":"venue"
},
  "geometry": {"coordinates":[5.6453518867,51.5074043274],"type":"Point"}
}