{
  "type": "Feature",
  "properties": {
    "addr:full":"Rouaanstr 11 Groningen Groningen 9723 CA",
    "addr:housenumber":"11",
    "addr:postcode":"9723 ca",
    "addr:street":"Rouaanstr",
    "iso:country":"NL",
    "sg:address":"Rouaanstr 11",
    "sg:city":"Groningen",
    "sg:orig_category":"Grondwerken",
    "sg:phone":"+31 50 313 1038",
    "sg:postcode":"9723 CA",
    "sg:province":"Groningen",
    "wof:name":"Rump Bv",
    "wof:placetype":"venue"
},
  "geometry": {"coordinates":[6.602081,53.198734],"type":"Point"}
}