{
  "type": "Feature",
  "properties": {
    "addr:full":"Zuidlarenstr 10 S Gravenhage Zuid-Holland 2545 VX",
    "addr:housenumber":"10 s",
    "addr:postcode":"2545 vx",
    "addr:street":"Zuidlarenstr",
    "iso:country":"NL",
    "sg:address":"Zuidlarenstr 10",
    "sg:city":"S Gravenhage",
    "sg:orig_category":"Scholen: Hoger Beroepsonderwijs",
    "sg:phone":"+31 70 308 8383",
    "sg:postcode":"2545 VX",
    "sg:province":"Zuid-Holland",
    "sg:website":"http://www.mon3aan.nl",
    "wof:name":"Mondriaan Stadscollege Voor Educatie",
    "wof:placetype":"venue"
},
  "geometry": {"coordinates":[4.27049,52.05093],"type":"Point"}
}