{
  "type": "Feature",
  "properties": {
    "addr:full":"De Clinge 38 Noordbroek Groningen 9635 CJ",
    "addr:housenumber":"38",
    "addr:postcode":"9635 cj",
    "addr:street":"De Clinge",
    "iso:country":"NL",
    "sg:address":"De Clinge 38",
    "sg:city":"Noordbroek",
    "sg:orig_category":"Schilders",
    "sg:phone":"+31 598 452 557",
    "sg:postcode":"9635 CJ",
    "sg:province":"Groningen",
    "wof:name":"Blaauw",
    "wof:placetype":"venue"
},
  "geometry": {"coordinates":[6.87411,53.19289],"type":"Point"}
}