{
  "type": "Feature",
  "properties": {
    "addr:full":"Kennemerln 39 Ymuiden North Holland 1972 EG",
    "addr:housenumber":"39",
    "addr:postcode":"1972 eg",
    "addr:street":"Kennemerln",
    "iso:country":"NL",
    "sg:address":"Kennemerln 39",
    "sg:city":"Ymuiden",
    "sg:orig_category":"Zonweringen",
    "sg:phone":"+31 255 531 324",
    "sg:postcode":"1972 EG",
    "sg:province":"North Holland",
    "wof:name":"Bonlite",
    "wof:placetype":"venue"
},
  "geometry": {"coordinates":[4.605057,52.460835],"type":"Point"}
}