{
  "type": "Feature",
  "properties": {
    "addr:full":"Lange Stoep 7 Lekkerkerk South Holland 2941 AE",
    "addr:housenumber":"7",
    "addr:postcode":"2941 ae",
    "addr:street":"Lange Stoep",
    "iso:country":"NL",
    "sg:address":"Lange Stoep 7",
    "sg:city":"Lekkerkerk",
    "sg:orig_category":"Bloemen And Planten",
    "sg:phone":"+31 180 661 497",
    "sg:postcode":"2941 AE",
    "sg:province":"South Holland",
    "wof:name":"Fa A. Van Der Graaf & Co",
    "wof:placetype":"venue"
},
  "geometry": {"coordinates":[4.683046,51.895],"type":"Point"}
}