{
  "type": "Feature",
  "properties": {
    "addr:full":"Rijksweg 116 Malden Gelderland 6581 ES",
    "addr:housenumber":"116",
    "addr:postcode":"6581 es",
    "addr:street":"Rijksweg;Gelderland",
    "iso:country":"NL",
    "sg:address":"Rijksweg 116",
    "sg:city":"Malden",
    "sg:classifiers":[
        {
            "category":"Fast Food",
            "type":"Food & Drink"
        }
    ],
    "sg:phone":"+31 24 358 5318",
    "sg:postcode":"6581 ES",
    "sg:province":"Gelderland",
    "sg:tags":[
        "afhaal",
        "restaurant"
    ],
    "wof:name":"Grillroom Jeruzalem Of Gold",
    "wof:placetype":"venue"
},
  "geometry": {"coordinates":[5.851491,51.783325],"type":"Point"}
}