{
  "type": "Feature",
  "properties": {
    "iso:country":"NL",
    "sg:address":"Achter De Hoven 213",
    "sg:city":"Leeuwarden",
    "sg:orig_category":"Geluidsopnamen",
    "sg:phone":"+31 58 216 1778",
    "sg:postcode":"8933 CL",
    "sg:province":"Friesland",
    "wof:name":"Cryptic Recording Studio",
    "wof:placetype":"venue"
},
  "geometry": {"coordinates":[5.81023,53.196251],"type":"Point"}
}