{
  "type": "Feature",
  "properties": {
    "iso:country":"NL",
    "sg:address":"E C De Greefhof 8",
    "sg:city":"Garderen",
    "sg:orig_category":"Onderhoudswerken",
    "sg:phone":"+31 577 460 850",
    "sg:postcode":"3886 KK",
    "sg:province":"Gelderland",
    "wof:name":"Heus, De",
    "wof:placetype":"venue"
},
  "geometry": {"coordinates":[5.713639,52.234756],"type":"Point"}
}