{
  "type": "Feature",
  "properties": {
    "addr:full":"E C De Greefhof 8 Garderen Gelderland 3886 KK",
    "addr:housenumber":"8",
    "addr:postcode":"3886 kk",
    "addr:street":"Greefhof;Gelderland",
    "iso:country":"NL",
    "sg:address":"E C De Greefhof 8",
    "sg:city":"Garderen",
    "sg:orig_category":"Onderhoudswerken",
    "sg:phone":"+31 577 460 850",
    "sg:postcode":"3886 KK",
    "sg:province":"Gelderland",
    "wof:name":"Heus, De",
    "wof:placetype":"venue"
},
  "geometry": {"coordinates":[5.713639,52.234756],"type":"Point"}
}