{
  "type": "Feature",
  "properties": {
    "addr:full":"Noorddammerlaan 124 Amstelveen Noord-Holland 1187 AG",
    "addr:housenumber":"124",
    "addr:postcode":"1187",
    "addr:street":"Noorddammerlaan",
    "iso:country":"NL",
    "sg:address":"Noorddammerlaan 124",
    "sg:city":"Amstelveen",
    "sg:orig_category":"Boekhouders",
    "sg:phone":"+31 20 545 6010",
    "sg:postcode":"1187 AG",
    "sg:province":"Noord-Holland",
    "wof:name":"Adfiscass Bv",
    "wof:placetype":"venue"
},
  "geometry": {"coordinates":[4.835453,52.293407],"type":"Point"}
}