{
  "type": "Feature",
  "properties": {
    "iso:country":"NL",
    "sg:address":"Kloosterlaan 27",
    "sg:city":"Winschoten",
    "sg:orig_category":"Kappers",
    "sg:phone":"+31 597 416 384",
    "sg:postcode":"9675 JL",
    "sg:province":"Groningen",
    "wof:name":"Kapsalon Karre",
    "wof:placetype":"venue"
},
  "geometry": {"coordinates":[7.0203938484,53.1604156494],"type":"Point"}
}