{
  "type": "Feature",
  "properties": {
    "iso:country":"NL",
    "sg:address":"Slachthuiskd 30",
    "sg:city":"Almelo",
    "sg:orig_category":"Keukens",
    "sg:phone":"+31 546 852 258",
    "sg:postcode":"7602 CV",
    "sg:province":"Overijssel",
    "wof:name":"Bovrie",
    "wof:placetype":"venue"
},
  "geometry": {"coordinates":[6.640881,52.366459],"type":"Point"}
}