{
  "type": "Feature",
  "properties": {
    "addr:full":"Fuik 50 Monnickendam North Holland 1141 CK",
    "addr:housenumber":"50",
    "addr:postcode":"1141 ck",
    "addr:street":"Fuik",
    "iso:country":"NL",
    "sg:address":"Fuik 50",
    "sg:city":"Monnickendam",
    "sg:orig_category":"Loodgieterswerk, Verwarming And Sanitaire Installaties",
    "sg:phone":"+31 299 655 213",
    "sg:postcode":"1141 CK",
    "sg:province":"North Holland",
    "wof:name":"J. Poel",
    "wof:placetype":"venue"
},
  "geometry": {"coordinates":[5.028514,52.450222],"type":"Point"}
}