{
  "type": "Feature",
  "properties": {
    "addr:full":"De Bolder 55 Drachten Friesland 9206 AP",
    "addr:housenumber":"55",
    "addr:postcode":"9206 ap",
    "addr:street":"De Bolder",
    "iso:country":"NL",
    "sg:address":"De Bolder 55",
    "sg:city":"Drachten",
    "sg:orig_category":"Verhuur Catering-, Feest- En Evenementbenodigdheden",
    "sg:phone":"+31 512 523 818",
    "sg:postcode":"9206 AP",
    "sg:province":"Friesland",
    "wof:name":"Hoogpak",
    "wof:placetype":"venue"
},
  "geometry": {"coordinates":[6.070512,53.116241],"type":"Point"}
}