{
  "type": "Feature",
  "properties": {
    "iso:country":"NL",
    "sg:address":"De Heurne 59",
    "sg:city":"Enschede",
    "sg:orig_category":"Natuurvoeding En Reformartikelen",
    "sg:phone":"+31 53 431 7099",
    "sg:postcode":"7511 GS",
    "sg:province":"Overijssel",
    "sg:website":"http://www.denatuurwinkel.nl",
    "wof:name":"Natuurwinkel, De",
    "wof:placetype":"venue"
},
  "geometry": {"coordinates":[6.899076,52.221889],"type":"Point"}
}