{
  "type": "Feature",
  "properties": {
    "addr:full":"Koopmansplein 1 Assen Drenthe 9401 EL",
    "addr:housenumber":"1",
    "addr:postcode":"9401 el",
    "addr:street":"Koopmansplein",
    "iso:country":"NL",
    "sg:address":"Koopmansplein 1",
    "sg:city":"Assen",
    "sg:classifiers":[
        {
            "category":"Shopping",
            "subcategory":"Gifts & Souvenirs",
            "type":"Retail Goods"
        }
    ],
    "sg:phone":"+31 592 317 055",
    "sg:postcode":"9401 EL",
    "sg:province":"Drenthe",
    "sg:tags":[
        "geschenken"
    ],
    "wof:name":"Hema",
    "wof:placetype":"venue"
},
  "geometry": {"coordinates":[6.559849,52.995041],"type":"Point"}
}