{
  "type": "Feature",
  "properties": {
    "addr:full":"Kromhoutln 1 Haarlem North Holland 2033 WJ",
    "addr:housenumber":"1",
    "addr:postcode":"2033 wj",
    "addr:street":"Kromhoutln",
    "iso:country":"NL",
    "sg:address":"Kromhoutln 1",
    "sg:city":"Haarlem",
    "sg:orig_category":"Video - Faciliteiten En Producties",
    "sg:phone":"+31 23 536 4424",
    "sg:postcode":"2033 WJ",
    "sg:province":"North Holland",
    "sg:website":"http://www.ctl.nl",
    "wof:name":"Ctl, Video Group",
    "wof:placetype":"venue"
},
  "geometry": {"coordinates":[4.662813,52.380035],"type":"Point"}
}