{
  "type": "Feature",
  "properties": {
    "addr:full":"Postbus 50 Rhenen Utrecht 3910 AB",
    "addr:housenumber":"50",
    "addr:postcode":"3910 ab",
    "addr:street":"Postbus",
    "iso:country":"NL",
    "sg:address":"Postbus 50",
    "sg:city":"Rhenen",
    "sg:orig_category":"Pompen",
    "sg:phone":"+31 317 620 095",
    "sg:postcode":"3910 AB",
    "sg:province":"Utrecht",
    "wof:name":"All Pumps Holland Bv",
    "wof:placetype":"venue"
},
  "geometry": {"coordinates":[5.567005,51.957603],"type":"Point"}
}