{
  "type": "Feature",
  "properties": {
    "addr:full":"Rodenryseln 74 Rotterdam South Holland 3037 XH",
    "addr:housenumber":"74",
    "addr:postcode":"3037 xh",
    "addr:street":"Rodenryseln",
    "iso:country":"NL",
    "sg:address":"Rodenryseln 74",
    "sg:city":"Rotterdam",
    "sg:orig_category":"Kinderopvang",
    "sg:phone":"+31 10 265 2636",
    "sg:postcode":"3037 XH",
    "sg:province":"South Holland",
    "wof:name":"Laddertje, Het",
    "wof:placetype":"venue"
},
  "geometry": {"coordinates":[4.4744,51.934601],"type":"Point"}
}