{
  "type": "Feature",
  "properties": {
    "addr:full":"Brouwerijdreef 26 Valkenswaard Noord-Brabant 5551 VB",
    "addr:housenumber":"26",
    "addr:postcode":"5551 vb",
    "addr:street":"Brouwerijdreef",
    "iso:country":"NL",
    "sg:address":"Brouwerijdreef 26",
    "sg:city":"Valkenswaard",
    "sg:orig_category":"Marktonderzoekbureaus",
    "sg:phone":"+31 40 201 9119",
    "sg:postcode":"5551 VB",
    "sg:province":"Noord-Brabant",
    "wof:name":"Knoop H.H.P.",
    "wof:placetype":"venue"
},
  "geometry": {"coordinates":[5.427535,51.351025],"type":"Point"}
}