{
  "type": "Feature",
  "properties": {
    "addr:full":"Helvoirtsestraat 6 Helvoirt North Brabant 5268 BB",
    "addr:housenumber":"6",
    "addr:postcode":"5268 bb",
    "addr:street":"Helvoirtsestraat",
    "iso:country":"NL",
    "sg:address":"Helvoirtsestraat 6",
    "sg:city":"Helvoirt",
    "sg:orig_category":"Organisaties And Verenigingen",
    "sg:phone":"+31 411 641 304",
    "sg:postcode":"5268 BB",
    "sg:province":"North Brabant",
    "wof:name":"Ultimate Events B.V.",
    "wof:placetype":"venue"
},
  "geometry": {"coordinates":[5.2236428261,51.6440544128],"type":"Point"}
}