{
  "type": "Feature",
  "properties": {
    "addr:full":"Tjalk 19 Hoorn Nh Noord-Holland 1625 EB",
    "addr:housenumber":"19",
    "addr:postcode":"1625 eb",
    "addr:street":"Tjalk",
    "iso:country":"NL",
    "sg:address":"Tjalk 19",
    "sg:city":"Hoorn Nh",
    "sg:orig_category":"Plafonds",
    "sg:phone":"+31 229 234 791",
    "sg:postcode":"1625 EB",
    "sg:province":"Noord-Holland",
    "wof:name":"Kever Afbouw",
    "wof:placetype":"venue"
},
  "geometry": {"coordinates":[5.058061,52.6609],"type":"Point"}
}