{
  "type": "Feature",
  "properties": {
    "addr:full":"Leywg 595K S Gravenhage South Holland 2545 GH",
    "addr:housenumber":"595k s",
    "addr:postcode":"2545 gh",
    "addr:street":"Leywg",
    "iso:country":"NL",
    "sg:address":"Leywg 595K",
    "sg:city":"S Gravenhage",
    "sg:orig_category":"Opticiens",
    "sg:phone":"+31 70 321 0771",
    "sg:postcode":"2545 GH",
    "sg:province":"South Holland",
    "sg:website":"http://www.hansanders.nl",
    "wof:name":"Hans Anders",
    "wof:placetype":"venue"
},
  "geometry": {"coordinates":[4.2704901695,52.0509300232],"type":"Point"}
}