{
  "type": "Feature",
  "properties": {
    "addr:full":"Zuidplasstraat 6 Moerkapelle Zuid-Holland 2751 GN",
    "addr:housenumber":"6",
    "addr:postcode":"2751 gn",
    "addr:street":"Zuidplasstraat",
    "iso:country":"NL",
    "sg:address":"Zuidplasstraat 6",
    "sg:city":"Moerkapelle",
    "sg:orig_category":"Bedrijfsinventaris Gh",
    "sg:phone":"+31 79 593 1494",
    "sg:postcode":"2751 GN",
    "sg:province":"Zuid-Holland",
    "wof:name":"Hayashi Europe Bv",
    "wof:placetype":"venue"
},
  "geometry": {"coordinates":[4.58109,52.042564],"type":"Point"}
}