{
  "type": "Feature",
  "properties": {
    "iso:country":"NL",
    "sg:address":"Maliebaan 12",
    "sg:city":"Arcen",
    "sg:orig_category":"Psychotherapeuten",
    "sg:phone":"+31 77 473 1887",
    "sg:postcode":"5944 BL",
    "sg:province":"Limburg",
    "wof:name":"Schreuder, Drs J W L",
    "wof:placetype":"venue"
},
  "geometry": {"coordinates":[6.189568,51.475262],"type":"Point"}
}