{
  "type": "Feature",
  "properties": {
    "addr:full":"Flevowg 9E Leiden Zuid-Holland 2318 BZ",
    "addr:housenumber":"9e",
    "addr:postcode":"2318 bz",
    "addr:street":"Flevowg",
    "iso:country":"NL",
    "sg:address":"Flevowg 9E",
    "sg:city":"Leiden",
    "sg:classifiers":[
        {
            "category":"Retail",
            "subcategory":"Auto Repair",
            "type":"Services"
        }
    ],
    "sg:phone":"+31 71 521 6430",
    "sg:postcode":"2318 BZ",
    "sg:province":"Zuid-Holland",
    "sg:tags":[
        "garage"
    ],
    "wof:name":"Ok Auto",
    "wof:placetype":"venue"
},
  "geometry": {"coordinates":[4.498298,52.175938],"type":"Point"}
}