{
  "type": "Feature",
  "properties": {
    "addr:full":"Spoordonkseweg 28 Oirschot Noord-Brabant 5688 KD",
    "addr:housenumber":"28",
    "addr:postcode":"5688 kd",
    "addr:street":"Spoordonkseweg",
    "iso:country":"NL",
    "sg:address":"Spoordonkseweg 28",
    "sg:city":"Oirschot",
    "sg:orig_category":"Fietshandelaren",
    "sg:phone":"+31 499 571 231",
    "sg:postcode":"5688 KD",
    "sg:province":"Noord-Brabant",
    "wof:name":"Smetsers Oirschot",
    "wof:placetype":"venue"
},
  "geometry": {"coordinates":[5.301813,51.50856],"type":"Point"}
}