{
  "type": "Feature",
  "properties": {
    "iso:country":"NL",
    "sg:address":"Pastoor Bruggemanlaan 33",
    "sg:city":"Oosterbeek",
    "sg:orig_category":"Banken And Kredietinstellingen",
    "sg:phone":"+31 26 334 4544",
    "sg:postcode":"6861 GR",
    "sg:province":"Gelderland",
    "wof:name":"Rabobank",
    "wof:placetype":"venue"
},
  "geometry": {"coordinates":[5.843885,51.988747],"type":"Point"}
}