{
  "type": "Feature",
  "properties": {
    "iso:country":"NL",
    "sg:address":"Kempenlandstraat 26",
    "sg:city":"Oisterwijk",
    "sg:orig_category":"Autokeuringen",
    "sg:phone":"+31 13 521 7405",
    "sg:postcode":"5061 XR",
    "sg:province":"Noord-Brabant",
    "wof:name":"Spierings",
    "wof:placetype":"venue"
},
  "geometry": {"coordinates":[5.2096571922,51.5834236145],"type":"Point"}
}