{
  "type": "Feature",
  "properties": {
    "iso:country":"NL",
    "sg:address":"Strandweg 21",
    "sg:city":"'S Gravenhage",
    "sg:classifiers":[
        {
            "category":"Fast Food",
            "type":"Food & Drink"
        }
    ],
    "sg:phone":"+31 70 323 8537",
    "sg:postcode":"2586 JK",
    "sg:province":"South Holland",
    "sg:tags":[
        "afhaal",
        "restaurant"
    ],
    "wof:name":"Strandtent De Flamengo'S",
    "wof:placetype":"venue"
},
  "geometry": {"coordinates":[4.280269,52.113224],"type":"Point"}
}