{
  "type": "Feature",
  "properties": {
    "addr:full":"Markt 51 'S Hertogenbosch North Brabant 5211 JW",
    "addr:housenumber":"51",
    "addr:postcode":"5211 jw",
    "addr:street":"Markt;' S Hertogenbosch",
    "iso:country":"NL",
    "sg:address":"Markt 51",
    "sg:city":"'S Hertogenbosch",
    "sg:classifiers":[
        {
            "category":"Fast Food",
            "type":"Food & Drink"
        }
    ],
    "sg:phone":"+31 73 692 6926",
    "sg:postcode":"5211 JW",
    "sg:province":"North Brabant",
    "sg:tags":[
        "afhaal",
        "restaurant"
    ],
    "wof:name":"De Leeuwenborgh",
    "wof:placetype":"venue"
},
  "geometry": {"coordinates":[5.30394,51.689423],"type":"Point"}
}