{
  "type": "Feature",
  "properties": {
    "iso:country":"NL",
    "sg:address":"Markt 22",
    "sg:city":"Lochem",
    "sg:orig_category":"Fotoreportages",
    "sg:phone":"+31 573 257 135",
    "sg:postcode":"7241 AA",
    "sg:province":"Gelderland",
    "wof:name":"Hans Makkink, Fotografie",
    "wof:placetype":"venue"
},
  "geometry": {"coordinates":[6.415802,52.161793],"type":"Point"}
}