{
  "type": "Feature",
  "properties": {
    "addr:full":"Heuvelenweg 6 Dwingeloo Drenthe 7991 CK",
    "addr:housenumber":"6",
    "addr:postcode":"7991 ck",
    "addr:street":"Heuvelenweg",
    "iso:country":"NL",
    "sg:address":"Heuvelenweg 6",
    "sg:city":"Dwingeloo",
    "sg:orig_category":"Bloemen And Planten",
    "sg:phone":"+31 521 593 254",
    "sg:postcode":"7991 CK",
    "sg:province":"Drenthe",
    "wof:name":"T Stiggeltien",
    "wof:placetype":"venue"
},
  "geometry": {"coordinates":[6.362956,52.833649],"type":"Point"}
}