{
  "type": "Feature",
  "properties": {
    "iso:country":"NL",
    "sg:address":"Korenmolenweg 41",
    "sg:city":"Bleiswijk",
    "sg:orig_category":"Boekhouders",
    "sg:phone":"+31 10 521 6604",
    "sg:postcode":"2665 CH",
    "sg:province":"Zuid-Holland",
    "wof:name":"C. Van Der Leek",
    "wof:placetype":"venue"
},
  "geometry": {"coordinates":[4.543422,52.01585],"type":"Point"}
}