{
  "type": "Feature",
  "properties": {
    "addr:full":"Franciscuswg 227 Hilversum Noord-Holland 1216 SE",
    "addr:housenumber":"227",
    "addr:postcode":"hilversum;1216 se",
    "iso:country":"NL",
    "sg:address":"Franciscuswg 227",
    "sg:city":"Hilversum",
    "sg:orig_category":"Lederwaren - Fabrieken En Groothandel",
    "sg:phone":"+31 35 621 2757",
    "sg:postcode":"1216 SE",
    "sg:province":"Noord-Holland",
    "wof:name":"Arwa Bv",
    "wof:placetype":"venue"
},
  "geometry": {"coordinates":[5.147476,52.214634],"type":"Point"}
}