{
  "type": "Feature",
  "properties": {
    "addr:full":"Tolstr 43 Meerkerk South Holland 4231 BB",
    "addr:housenumber":"43",
    "addr:postcode":"4231 bb",
    "addr:street":"Tolstr",
    "iso:country":"NL",
    "sg:address":"Tolstr 43",
    "sg:city":"Meerkerk",
    "sg:orig_category":"Kappers",
    "sg:phone":"+31 183 352 283",
    "sg:postcode":"4231 BB",
    "sg:province":"South Holland",
    "wof:name":"Trudy En Arien",
    "wof:placetype":"venue"
},
  "geometry": {"coordinates":[5.000788,51.921597],"type":"Point"}
}