{
  "type": "Feature",
  "properties": {
    "addr:full":"Boulev De Wieling 49 Cadzand Zeeland 4506 JK",
    "addr:housenumber":"49",
    "addr:postcode":"4506 jk",
    "addr:street":"Boulev De Wieling",
    "iso:country":"NL",
    "sg:address":"Boulev De Wieling 49",
    "sg:city":"Cadzand",
    "sg:classifiers":[
        {
            "category":"Travel",
            "subcategory":"Hotels & Motels",
            "type":"Entertainment"
        }
    ],
    "sg:phone":"+31 117 392 110",
    "sg:postcode":"4506 JK",
    "sg:province":"Zeeland",
    "sg:website":"http://www.strandhotel-cadzand.nl",
    "wof:name":"Strandhotel",
    "wof:placetype":"venue"
},
  "geometry": {"coordinates":[3.391363,51.37888],"type":"Point"}
}