{
  "type": "Feature",
  "properties": {
    "addr:full":"De Grt Ekker 13 Bladel North Brabant 5531 DW",
    "addr:housenumber":"13",
    "addr:postcode":"5531 dw",
    "addr:street":"Ekker",
    "iso:country":"NL",
    "sg:address":"De Grt Ekker 13",
    "sg:city":"Bladel",
    "sg:orig_category":"Kinderkleding",
    "sg:phone":"+31 497 384 649",
    "sg:postcode":"5531 DW",
    "sg:province":"North Brabant",
    "wof:name":"Janssen, M A A",
    "wof:placetype":"venue"
},
  "geometry": {"coordinates":[5.222949,51.3741],"type":"Point"}
}