{
  "type": "Feature",
  "properties": {
    "iso:country":"NL",
    "sg:address":"Stadhoudersln 1A",
    "sg:city":"Schiedam",
    "sg:orig_category":"Onderhoudswerken",
    "sg:phone":"+31 10 426 6730",
    "sg:postcode":"3116 HK",
    "sg:province":"South Holland",
    "wof:name":"Kapoen, Gebr",
    "wof:placetype":"venue"
},
  "geometry": {"coordinates":[4.39816,51.918472],"type":"Point"}
}