{
  "type": "Feature",
  "properties": {
    "addr:full":"Singel 376 Amsterdam Noord-Holland 1016 AH",
    "addr:housenumber":"376",
    "addr:postcode":"1016 ah",
    "addr:street":"Singel",
    "iso:country":"NL",
    "sg:address":"Singel 376",
    "sg:city":"Amsterdam",
    "sg:orig_category":"Kalligrafische Ateliers",
    "sg:phone":"+31 20 623 9690",
    "sg:postcode":"1016 AH",
    "sg:province":"Noord-Holland",
    "wof:name":"Ger De Vries Kalligraaf",
    "wof:placetype":"venue"
},
  "geometry": {"coordinates":[4.8874502182,52.3695755005],"type":"Point"}
}