{
  "type": "Feature",
  "properties": {
    "addr:full":"Middelberg 7 Veldhoven Noord-Brabant 5508 DM",
    "addr:housenumber":"7",
    "addr:postcode":"5508 dm",
    "addr:street":"Middelberg",
    "iso:country":"NL",
    "sg:address":"Middelberg 7",
    "sg:city":"Veldhoven",
    "sg:orig_category":"Keramische Producten Fab",
    "sg:phone":"+31 40 253 6486",
    "sg:postcode":"5508 DM",
    "sg:province":"Noord-Brabant",
    "wof:name":"3Pottenbakkerij J.T.",
    "wof:placetype":"venue"
},
  "geometry": {"coordinates":[5.383846,51.42424],"type":"Point"}
}