{
  "type": "Feature",
  "properties": {
    "addr:full":"Melkpad 61 Zeeland Noord-Brabant 5411 GD",
    "addr:housenumber":"61",
    "addr:postcode":"5411 gd",
    "addr:street":"Melkpad",
    "iso:country":"NL",
    "sg:address":"Melkpad 61",
    "sg:city":"Zeeland",
    "sg:orig_category":"Betonijzervlechten",
    "sg:phone":"+31 6 16604238",
    "sg:postcode":"5411 GD",
    "sg:province":"Noord-Brabant",
    "wof:name":"Mentzij, J",
    "wof:placetype":"venue"
},
  "geometry": {"coordinates":[5.678726,51.701332],"type":"Point"}
}