{
  "type": "Feature",
  "properties": {
    "addr:full":"Burgwal 14 Bunschoten Spakenb Utrecht 3752 XA",
    "addr:housenumber":"14",
    "addr:postcode":"3752 xa",
    "addr:street":"Burgwal",
    "iso:country":"NL",
    "sg:address":"Burgwal 14",
    "sg:city":"Bunschoten Spakenb",
    "sg:orig_category":"Fotoreportages",
    "sg:phone":"+31 33 298 0734",
    "sg:postcode":"3752 XA",
    "sg:province":"Utrecht",
    "wof:name":"Oosterom, Wendy Van",
    "wof:placetype":"venue"
},
  "geometry": {"coordinates":[5.370129,52.237495],"type":"Point"}
}