{
  "type": "Feature",
  "properties": {
    "addr:full":"Koperwiek 71 Capelle Ad Yssel South Holland 2903 AD",
    "addr:housenumber":"71",
    "addr:postcode":"2903 ad",
    "addr:street":"Koperwiek;Yssel",
    "iso:country":"NL",
    "sg:address":"Koperwiek 71",
    "sg:city":"Capelle Ad Yssel",
    "sg:orig_category":"Herenkleding",
    "sg:phone":"+31 10 450 3282",
    "sg:postcode":"2903 AD",
    "sg:province":"South Holland",
    "wof:name":"Adam",
    "wof:placetype":"venue"
},
  "geometry": {"coordinates":[4.589116,51.929993],"type":"Point"}
}