{
  "type": "Feature",
  "properties": {
    "addr:full":"Van Eysingalaan 333 Utrecht Utrecht 3527 VK",
    "addr:housenumber":"333",
    "addr:postcode":"3527 vk",
    "addr:street":"Van Eysingalaan",
    "iso:country":"NL",
    "sg:address":"Van Eysingalaan 333",
    "sg:city":"Utrecht",
    "sg:classifiers":[
        {
            "category":"Fast Food",
            "type":"Food & Drink"
        }
    ],
    "sg:phone":"+31 30 293 3690",
    "sg:postcode":"3527 VK",
    "sg:province":"Utrecht",
    "sg:tags":[
        "afhaal",
        "restaurant"
    ],
    "wof:name":"De Molen",
    "wof:placetype":"venue"
},
  "geometry": {"coordinates":[5.095351,52.079445],"type":"Point"}
}