{
  "type": "Feature",
  "properties": {
    "addr:full":"Koepoortstraat 16 Middelburg Zeeland 4331 SL",
    "addr:housenumber":"16",
    "addr:postcode":"4331 sl",
    "addr:street":"Koepoortstraat",
    "iso:country":"NL",
    "sg:address":"Koepoortstraat 16",
    "sg:city":"Middelburg",
    "sg:orig_category":"Geluidsopnamen",
    "sg:phone":"+31 118 642 842",
    "sg:postcode":"4331 SL",
    "sg:province":"Zeeland",
    "wof:name":"Van Der Heijden",
    "wof:placetype":"venue"
},
  "geometry": {"coordinates":[3.618351,51.502846],"type":"Point"}
}