{
  "type": "Feature",
  "properties": {
    "addr:full":"Huntstr 2 Sittard Limburg 6135 CP",
    "addr:housenumber":"2",
    "addr:postcode":"6135 cp",
    "addr:street":"Huntstr",
    "iso:country":"NL",
    "sg:address":"Huntstr 2",
    "sg:city":"Sittard",
    "sg:classifiers":[
        {
            "category":"Retail",
            "subcategory":"Auto Repair",
            "type":"Services"
        }
    ],
    "sg:phone":"+31 46 451 3510",
    "sg:postcode":"6135 CP",
    "sg:province":"Limburg",
    "sg:tags":[
        "garage"
    ],
    "wof:name":"Rosbak, Jim",
    "wof:placetype":"venue"
},
  "geometry": {"coordinates":[5.852334,51.007561],"type":"Point"}
}