{
  "type": "Feature",
  "properties": {
    "addr:full":"Ingenieur D S Tuijnmanwg 4B Vianen Zh South Holland 4131 PN",
    "addr:housenumber":"s;4b",
    "addr:postcode":"zh;4131 pn",
    "addr:street":"Ingenieur D",
    "iso:country":"NL",
    "sg:address":"Ingenieur D S Tuijnmanwg 4B",
    "sg:city":"Vianen Zh",
    "sg:orig_category":"Juridische Dienstverlening",
    "sg:phone":"+31 347 357 075",
    "sg:postcode":"4131 PN",
    "sg:province":"South Holland",
    "wof:name":"Legal House Bv",
    "wof:placetype":"venue"
},
  "geometry": {"coordinates":[5.107021,51.987518],"type":"Point"}
}