{
  "type": "Feature",
  "properties": {
    "addr:full":"Biarritzpln 37 Eindhoven Noord-Brabant 5627 LE",
    "addr:housenumber":"37",
    "addr:postcode":"5627 le",
    "addr:street":"Biarritzpln",
    "iso:country":"NL",
    "sg:address":"Biarritzpln 37",
    "sg:city":"Eindhoven",
    "sg:orig_category":"Fotoreportages",
    "sg:phone":"+31 40 242 4262",
    "sg:postcode":"5627 LE",
    "sg:province":"Noord-Brabant",
    "wof:name":"Klaassens, Ton",
    "wof:placetype":"venue"
},
  "geometry": {"coordinates":[5.449241,51.483112],"type":"Point"}
}