{
  "type": "Feature",
  "properties": {
    "addr:full":"Jupiter 11 Veldhoven Noord-Brabant 5505 NT",
    "addr:housenumber":"11",
    "addr:postcode":"5505 nt",
    "addr:street":"Jupiter",
    "iso:country":"NL",
    "sg:address":"Jupiter 11",
    "sg:city":"Veldhoven",
    "sg:orig_category":"Daken And Skeletbouw",
    "sg:phone":"+31 40 254 2681",
    "sg:postcode":"5505 NT",
    "sg:province":"Noord-Brabant",
    "wof:name":"Bhfw",
    "wof:placetype":"venue"
},
  "geometry": {"coordinates":[5.388028,51.409645],"type":"Point"}
}