{
  "type": "Feature",
  "properties": {
    "addr:full":"Lijzij 112 Huizen Noord-Holland 1276 GN",
    "addr:housenumber":"112",
    "addr:postcode":"1276 gn",
    "addr:street":"Lijzij",
    "iso:country":"NL",
    "sg:address":"Lijzij 112",
    "sg:city":"Huizen",
    "sg:orig_category":"Fotostudio'S And Fotografen",
    "sg:phone":"+31 35 524 2354",
    "sg:postcode":"1276 GN",
    "sg:province":"Noord-Holland",
    "wof:name":"Caesar A Wille Fotostudio",
    "wof:placetype":"venue"
},
  "geometry": {"coordinates":[5.248718,52.288166],"type":"Point"}
}