{
  "type": "Feature",
  "properties": {
    "addr:full":"Europaweg 71 Schoonebeek Drenthe 7761 AA",
    "addr:housenumber":"71",
    "addr:postcode":"7761 aa",
    "addr:street":"Europaweg",
    "iso:country":"NL",
    "sg:address":"Europaweg 71",
    "sg:city":"Schoonebeek",
    "sg:orig_category":"Bloemen And Planten",
    "sg:phone":"+31 524 525 142",
    "sg:postcode":"7761 AA",
    "sg:province":"Drenthe",
    "wof:name":"Bloemboutique Marianne Van Oenen",
    "wof:placetype":"venue"
},
  "geometry": {"coordinates":[6.892674,52.659046],"type":"Point"}
}