{
  "type": "Feature",
  "properties": {
    "addr:full":"Markerkant 1521B Almere Flevoland 1314 AV",
    "addr:housenumber":"1314",
    "addr:postcode":"av",
    "addr:street":"Markerkant 1521B;Flevoland",
    "iso:country":"NL",
    "sg:address":"Markerkant 1521B",
    "sg:city":"Almere",
    "sg:classifiers":[
        {
            "category":"Retail",
            "subcategory":"Auto Repair",
            "type":"Services"
        }
    ],
    "sg:phone":"+31 36 530 6700",
    "sg:postcode":"1314 AV",
    "sg:province":"Flevoland",
    "sg:tags":[
        "garage"
    ],
    "wof:name":"Arie",
    "wof:placetype":"venue"
},
  "geometry": {"coordinates":[5.2154,52.379723],"type":"Point"}
}