{
  "type": "Feature",
  "properties": {
    "iso:country":"NL",
    "sg:address":"Ketelwg 63C",
    "sg:city":"Papendrecht",
    "sg:orig_category":"Automaterialen En Gereedschappen",
    "sg:phone":"+31 78 615 4355",
    "sg:postcode":"3356 LD",
    "sg:province":"Zuid-Holland",
    "wof:name":"Rijwa Automaterialen Bv",
    "wof:placetype":"venue"
},
  "geometry": {"coordinates":[4.728068,51.82843],"type":"Point"}
}