{
  "type": "Feature",
  "properties": {
    "addr:full":"Veenendaalpln 154 Amsterdam Zuidoost North Holland 1106 CS",
    "addr:housenumber":"154",
    "addr:postcode":"1106 cs",
    "iso:country":"NL",
    "sg:address":"Veenendaalpln 154",
    "sg:city":"Amsterdam Zuidoost",
    "sg:orig_category":"Marktonderzoekbureaus",
    "sg:phone":"+31 20 691 4504",
    "sg:postcode":"1106 CS",
    "sg:province":"North Holland",
    "wof:name":"Innerview",
    "wof:placetype":"venue"
},
  "geometry": {"coordinates":[4.985049,52.300571],"type":"Point"}
}