{
  "type": "Feature",
  "properties": {
    "addr:full":"Mercatorpln 94 Amsterdam Noord-Holland 1056 CL",
    "addr:housenumber":"94",
    "addr:postcode":"1056",
    "addr:street":"Mercatorpln",
    "iso:country":"NL",
    "sg:address":"Mercatorpln 94",
    "sg:city":"Amsterdam",
    "sg:orig_category":"Opticiens",
    "sg:phone":"+31 20 689 3572",
    "sg:postcode":"1056 CL",
    "sg:province":"Noord-Holland",
    "wof:name":"Pearle",
    "wof:placetype":"venue"
},
  "geometry": {"coordinates":[4.8506360054,52.3703193665],"type":"Point"}
}