{
  "type": "Feature",
  "properties": {
    "addr:full":"Frobenstr 7 Rotterdam South Holland 3045 RD",
    "addr:housenumber":"7",
    "addr:postcode":"3045 rd",
    "addr:street":"Frobenstr",
    "iso:country":"NL",
    "sg:address":"Frobenstr 7",
    "sg:city":"Rotterdam",
    "sg:orig_category":"Fotografie Reclame En Mode",
    "sg:phone":"+31 10 418 5000",
    "sg:postcode":"3045 RD",
    "sg:province":"South Holland",
    "wof:name":"Fotowerk Bv",
    "wof:placetype":"venue"
},
  "geometry": {"coordinates":[4.46311,51.947628],"type":"Point"}
}