{
  "type": "Feature",
  "properties": {
    "iso:country":"NL",
    "sg:address":"Krugerstr 5A",
    "sg:city":"Amsterdam",
    "sg:orig_category":"Mensendieck - Oefentherapeuten",
    "sg:phone":"+31 20 694 7289",
    "sg:postcode":"1091 LB",
    "sg:province":"Noord-Holland",
    "wof:name":"Transvaalbuurt, Praktijk",
    "wof:placetype":"venue"
},
  "geometry": {"coordinates":[4.91921,52.353455],"type":"Point"}
}