{
  "type": "Feature",
  "properties": {
    "addr:full":"Herenln 2 Zeist Utrecht 3701 AT",
    "addr:housenumber":"2",
    "addr:postcode":"3701",
    "addr:street":"Herenln",
    "iso:country":"NL",
    "sg:address":"Herenln 2",
    "sg:city":"Zeist",
    "sg:orig_category":"Verenigingen En Stichtingen",
    "sg:phone":"+31 30 695 7816",
    "sg:postcode":"3701 AT",
    "sg:province":"Utrecht",
    "wof:name":"Nederlandse Ver Aannemers Markeringswerken",
    "wof:placetype":"venue"
},
  "geometry": {"coordinates":[5.241167,52.082363],"type":"Point"}
}