{
  "type": "Feature",
  "properties": {
    "addr:full":"T De Jagerdreef 4 Utrecht Utrecht 3561 JK",
    "addr:housenumber":"4",
    "addr:postcode":"3561 jk",
    "addr:street":"T De Jagerdreef",
    "iso:country":"NL",
    "sg:address":"T De Jagerdreef 4",
    "sg:city":"Utrecht",
    "sg:orig_category":"Autorijscholen",
    "sg:phone":"+31 30 266 2148",
    "sg:postcode":"3561 JK",
    "sg:province":"Utrecht",
    "wof:name":"Angena, Rijschool",
    "wof:placetype":"venue"
},
  "geometry": {"coordinates":[5.11832,52.110027],"type":"Point"}
}