{
  "type": "Feature",
  "properties": {
    "iso:country":"NL",
    "sg:address":"Gamanderweerd 10",
    "sg:city":"Maastricht",
    "sg:orig_category":"Schilders",
    "sg:phone":"+31 43 367 2485",
    "sg:postcode":"6229 TW",
    "sg:province":"Limburg",
    "wof:name":"Stones",
    "wof:placetype":"venue"
},
  "geometry": {"coordinates":[5.70932,50.831093],"type":"Point"}
}