{
  "type": "Feature",
  "properties": {
    "addr:full":"J V Gaesbeekln 5 Driebergen Rysenb Utrecht 3971 BR",
    "addr:housenumber":"5",
    "addr:postcode":"3971 br",
    "addr:street":"J;Gaesbeekln;Rysenb",
    "iso:country":"NL",
    "sg:address":"J V Gaesbeekln 5",
    "sg:city":"Driebergen Rysenb",
    "sg:orig_category":"Adviesbureaus Bedrijfsorganisatie",
    "sg:phone":"+31 343 533 219",
    "sg:postcode":"3971 BR",
    "sg:province":"Utrecht",
    "wof:name":"Vandenhil",
    "wof:placetype":"venue"
},
  "geometry": {"coordinates":[5.30052,52.065571],"type":"Point"}
}