{
  "type": "Feature",
  "properties": {
    "addr:full":"Smalle Themaat 30 Vleuten Utrecht 3451 SW",
    "addr:housenumber":"30",
    "addr:postcode":"3451 sw",
    "addr:street":"Smalle Themaat",
    "iso:country":"NL",
    "sg:address":"Smalle Themaat 30",
    "sg:city":"Vleuten",
    "sg:orig_category":"Modeontwerpen",
    "sg:phone":"+31 30 677 0639",
    "sg:postcode":"3451 SW",
    "sg:province":"Utrecht",
    "wof:name":"Ultimate",
    "wof:placetype":"venue"
},
  "geometry": {"coordinates":[5.022221,52.112106],"type":"Point"}
}