{
  "type": "Feature",
  "properties": {
    "addr:full":"Tesschenmacherstr 43 Deventer Overijssel 7415 CS",
    "addr:housenumber":"43",
    "addr:postcode":"7415 cs",
    "addr:street":"Tesschenmacherstr",
    "iso:country":"NL",
    "sg:address":"Tesschenmacherstr 43",
    "sg:city":"Deventer",
    "sg:orig_category":"Adviesbureaus Bedrijfsorganisatie",
    "sg:phone":"+31 570 676 740",
    "sg:postcode":"7415 CS",
    "sg:province":"Overijssel",
    "wof:name":"Provim",
    "wof:placetype":"venue"
},
  "geometry": {"coordinates":[6.168688,52.263973],"type":"Point"}
}