{
  "type": "Feature",
  "properties": {
    "iso:country":"NL",
    "sg:address":"Strickledeweg 54",
    "sg:city":"Rotterdam",
    "sg:orig_category":"Boekhandels",
    "sg:phone":"+31 10 462 7477",
    "sg:postcode":"3044 EK",
    "sg:province":"Zuid-Holland",
    "wof:name":"Academic Book Import",
    "wof:placetype":"venue"
},
  "geometry": {"coordinates":[4.410511,51.929546],"type":"Point"}
}