{
  "type": "Feature",
  "properties": {
    "iso:country":"NL",
    "sg:address":"Henegouwerln 118",
    "sg:city":"Rotterdam",
    "sg:orig_category":"Grafisch Ontwerpers",
    "sg:phone":"+31 10 233 1720",
    "sg:postcode":"3014 CG",
    "sg:province":"Zuid-Holland",
    "wof:name":"Typography & Other Serous Matters",
    "wof:placetype":"venue"
},
  "geometry": {"coordinates":[4.478455,51.922836],"type":"Point"}
}