{
  "type": "Feature",
  "properties": {
    "iso:country":"NL",
    "sg:address":"Breestr 50",
    "sg:city":"Leiden",
    "sg:orig_category":"Verenigingen En Stichtingen",
    "sg:phone":"+31 71 514 9241",
    "sg:postcode":"2311 CS",
    "sg:province":"Zuid-Holland",
    "wof:name":"Minerva Leidse Studentenver",
    "wof:placetype":"venue"
},
  "geometry": {"coordinates":[4.487866,52.159897],"type":"Point"}
}