{
  "type": "Feature",
  "properties": {
    "addr:full":"Van Der Glasstraat 14 Bergen Op Zoom Noord-Brabant 4614 VK",
    "addr:housenumber":"14",
    "addr:postcode":"4614 vk",
    "addr:street":"Van Der Glasstraat",
    "iso:country":"NL",
    "sg:address":"Van Der Glasstraat 14",
    "sg:city":"Bergen Op Zoom",
    "sg:orig_category":"Loopbaanbegeleiding",
    "sg:phone":"+31 164 249 460",
    "sg:postcode":"4614 VK",
    "sg:province":"Noord-Brabant",
    "wof:name":"Integra",
    "wof:placetype":"venue"
},
  "geometry": {"coordinates":[4.297786,51.504574],"type":"Point"}
}