{
  "type": "Feature",
  "properties": {
    "addr:full":"Bachln 118 Terneuzen Zeeland 4536 GE",
    "addr:housenumber":"118",
    "addr:postcode":"4536",
    "iso:country":"NL",
    "sg:address":"Bachln 118",
    "sg:city":"Terneuzen",
    "sg:orig_category":"Vertalers",
    "sg:phone":"+31 115 619 724",
    "sg:postcode":"4536 GE",
    "sg:province":"Zeeland",
    "wof:name":"Andrade Figueiredo",
    "wof:placetype":"venue"
},
  "geometry": {"coordinates":[3.827559,51.338146],"type":"Point"}
}