{
  "type": "Feature",
  "properties": {
    "addr:full":"Patrijsstraat 1 Zundert Noord-Brabant 4881 WS",
    "addr:housenumber":"1",
    "addr:postcode":"4881 ws",
    "addr:street":"Patrijsstraat",
    "iso:country":"NL",
    "sg:address":"Patrijsstraat 1",
    "sg:city":"Zundert",
    "sg:orig_category":"Kappers",
    "sg:phone":"+31 76 597 5491",
    "sg:postcode":"4881 WS",
    "sg:province":"Noord-Brabant",
    "wof:name":"Kapsalon Hilde",
    "wof:placetype":"venue"
},
  "geometry": {"coordinates":[4.6515069008,51.46692276],"type":"Point"}
}