{
  "type": "Feature",
  "properties": {
    "addr:full":"Kapberg 14 Wognum North Holland 1687 TD",
    "addr:housenumber":"14",
    "addr:postcode":"1687 td",
    "addr:street":"Kapberg",
    "iso:country":"NL",
    "sg:address":"Kapberg 14",
    "sg:city":"Wognum",
    "sg:orig_category":"Adviesbureaus",
    "sg:phone":"+31 229 573 485",
    "sg:postcode":"1687 TD",
    "sg:province":"North Holland",
    "wof:name":"Lcc",
    "wof:placetype":"venue"
},
  "geometry": {"coordinates":[5.019696,52.68158],"type":"Point"}
}