{
  "type": "Feature",
  "properties": {
    "addr:full":"Heidestr 44 Ham B--3 94",
    "addr:housenumber":"44;94",
    "addr:street":"Heidestr;B--3",
    "iso:country":"NL",
    "sg:address":"Heidestr 44",
    "sg:city":"Ham",
    "sg:orig_category":"Watersportartikelen",
    "sg:phone":"+31 13676224",
    "sg:postcode":"B--3 94",
    "sg:website":"http://www.piranha-racing.com",
    "wof:name":"Jet-Ski Piranha-Racing",
    "wof:placetype":"venue"
},
  "geometry": {"coordinates":[-3.0827488899,50.8067016602],"type":"Point"}
}