{
  "type": "Feature",
  "properties": {
    "addr:full":"Hoefyzer 56 Loenen Ad Vecht Utrecht 3632 WD",
    "addr:housenumber":"56",
    "addr:postcode":"3632 wd",
    "addr:street":"Hoefyzer;Vecht",
    "iso:country":"NL",
    "sg:address":"Hoefyzer 56",
    "sg:city":"Loenen Ad Vecht",
    "sg:orig_category":"Adviesbureaus Bedrijfsorganisatie",
    "sg:phone":"+31 294 237 506",
    "sg:postcode":"3632 WD",
    "sg:province":"Utrecht",
    "wof:name":"Dijk Loenen Bv, J Van",
    "wof:placetype":"venue"
},
  "geometry": {"coordinates":[5.021896,52.209732],"type":"Point"}
}