{
  "type": "Feature",
  "properties": {
    "addr:full":"S Prinsensngl 19 Maasland South Holland 3155 VK",
    "addr:housenumber":"19",
    "addr:postcode":"3155 vk",
    "addr:street":"Maasland",
    "iso:country":"NL",
    "sg:address":"S Prinsensngl 19",
    "sg:city":"Maasland",
    "sg:orig_category":"Wereldwinkels",
    "sg:phone":"+31 10 591 3849",
    "sg:postcode":"3155 VK",
    "sg:province":"South Holland",
    "wof:name":"Wereldwinkel",
    "wof:placetype":"venue"
},
  "geometry": {"coordinates":[4.266356945,51.9366264343],"type":"Point"}
}