{
  "type": "Feature",
  "properties": {
    "addr:full":"Antwerpsestrwg 99 Bergen Op Zoom Noord-Brabant 4615 AM",
    "addr:housenumber":"99",
    "addr:postcode":"4615",
    "addr:street":"Antwerpsestrwg",
    "iso:country":"NL",
    "sg:address":"Antwerpsestrwg 99",
    "sg:city":"Bergen Op Zoom",
    "sg:orig_category":"Montagebedrijven",
    "sg:phone":"+31 164 266 102",
    "sg:postcode":"4615 AM",
    "sg:province":"Noord-Brabant",
    "wof:name":"Berg, Kees Van Den",
    "wof:placetype":"venue"
},
  "geometry": {"coordinates":[4.291044,51.486343],"type":"Point"}
}