{
  "type": "Feature",
  "properties": {
    "addr:full":"Kieskoel 23 Landgraaf Limburg 6371 DB",
    "addr:housenumber":"23",
    "addr:postcode":"6371 db",
    "addr:street":"Kieskoel",
    "iso:country":"NL",
    "sg:address":"Kieskoel 23",
    "sg:city":"Landgraaf",
    "sg:orig_category":"Woningbouw- Verenigingen En -Stichtingen",
    "sg:phone":"+31 45 531 9765",
    "sg:postcode":"6371 DB",
    "sg:province":"Limburg",
    "wof:name":"Woonplaats, De",
    "wof:placetype":"venue"
},
  "geometry": {"coordinates":[6.0183749199,50.9012985229],"type":"Point"}
}