{
  "type": "Feature",
  "properties": {
    "addr:full":"Printer 29 Coevorden Provincie Drenthe 7741 ME",
    "addr:housenumber":"29",
    "addr:postcode":"7741 me",
    "addr:street":"Printer;Provincie Drenthe",
    "iso:country":"NL",
    "sg:address":"Printer 29",
    "sg:city":"Coevorden",
    "sg:orig_category":"Wintersportkleding En -Artikelen",
    "sg:phone":"+31 524 513 182",
    "sg:postcode":"7741 ME",
    "sg:province":"Provincie Drenthe",
    "sg:website":"http://www.petstra.nl",
    "wof:name":"Petstra Caravaning-Ski",
    "wof:placetype":"venue"
},
  "geometry": {"coordinates":[6.7239489555,52.665096283],"type":"Point"}
}