{
  "type": "Feature",
  "properties": {
    "iso:country":"NL",
    "sg:address":"A.W. Lipsstraat 17",
    "sg:city":"Oud Beijerland",
    "sg:orig_category":"Metaalbekleding And -Behandeling",
    "sg:phone":"+31 186 621 722",
    "sg:postcode":"3262 GA",
    "sg:province":"Zuid-Holland",
    "wof:name":"J. Koppelaar",
    "wof:placetype":"venue"
},
  "geometry": {"coordinates":[4.402012,51.81926],"type":"Point"}
}