{
  "type": "Feature",
  "properties": {
    "addr:full":"Bilderdykstr 118 Amsterdam North Holland 1053 KZ",
    "addr:housenumber":"118",
    "addr:postcode":"1053 kz",
    "iso:country":"NL",
    "sg:address":"Bilderdykstr 118",
    "sg:city":"Amsterdam",
    "sg:orig_category":"Webdesign Bureaus",
    "sg:phone":"+31 20 689 0809",
    "sg:postcode":"1053 KZ",
    "sg:province":"North Holland",
    "sg:website":"http://www.page-design.nl",
    "wof:name":"Page Design Nederland",
    "wof:placetype":"venue"
},
  "geometry": {"coordinates":[4.8710198402,52.3684539795],"type":"Point"}
}