{
  "type": "Feature",
  "properties": {
    "addr:full":"Gerard Doulaan 2 Vlissingen Zeeland 4382 RA",
    "addr:housenumber":"2",
    "addr:postcode":"4382 ra",
    "addr:street":"Gerard Doulaan",
    "iso:country":"NL",
    "sg:address":"Gerard Doulaan 2",
    "sg:city":"Vlissingen",
    "sg:orig_category":"Loodgieterswerk, Verwarming And Sanitaire Installaties",
    "sg:phone":"+31 118 416 585",
    "sg:postcode":"4382 RA",
    "sg:province":"Zeeland",
    "wof:name":"Loodgieters- En Verwarmingsbedrijf Nijhu",
    "wof:placetype":"venue"
},
  "geometry": {"coordinates":[3.572516,51.453594],"type":"Point"}
}