{
  "type": "Feature",
  "properties": {
    "addr:full":"Appelbes 10 Leiden Zuid-Holland 2318 AK",
    "addr:housenumber":"10",
    "addr:postcode":"2318 ak",
    "addr:street":"Appelbes",
    "iso:country":"NL",
    "sg:address":"Appelbes 10",
    "sg:city":"Leiden",
    "sg:orig_category":"Wijnkoperijen En -Groothandel",
    "sg:phone":"+31 71 523 5600",
    "sg:postcode":"2318 AK",
    "sg:province":"Zuid-Holland",
    "sg:website":"http://www.xs4all.nl~jorissen",
    "wof:name":"Jorissen, H",
    "wof:placetype":"venue"
},
  "geometry": {"coordinates":[4.4979100227,52.1776924133],"type":"Point"}
}