{
  "type": "Feature",
  "properties": {
    "iso:country":"NL",
    "sg:address":"Liebergerwg 75",
    "sg:city":"Hilversum",
    "sg:orig_category":"Onderhoudswerken",
    "sg:phone":"+31 35 685 2748",
    "sg:postcode":"1221 JR",
    "sg:province":"Noord-Holland",
    "wof:name":"Withake, R P",
    "wof:placetype":"venue"
},
  "geometry": {"coordinates":[5.191245,52.222733],"type":"Point"}
}