{
  "type": "Feature",
  "properties": {
    "iso:country":"NL",
    "sg:address":"Hoogstraat 51",
    "sg:city":"Werkendam",
    "sg:orig_category":"Werving And Selectie Van Vast Personeel",
    "sg:phone":"+31 183 505 777",
    "sg:postcode":"4251 CJ",
    "sg:province":"North Brabant",
    "wof:name":"C. Bik",
    "wof:placetype":"venue"
},
  "geometry": {"coordinates":[4.8953170776,51.8083724976],"type":"Point"}
}