{
  "type": "Feature",
  "properties": {
    "addr:full":"Lynbaansgr 317 Amsterdam Noord-Holland 1017 WZ",
    "addr:housenumber":"317",
    "addr:postcode":"1017 wz",
    "iso:country":"NL",
    "sg:address":"Lynbaansgr 317",
    "sg:city":"Amsterdam",
    "sg:orig_category":"Galeries",
    "sg:phone":"+31 20 638 0480",
    "sg:postcode":"1017 WZ",
    "sg:province":"Noord-Holland",
    "wof:name":"Akinci",
    "wof:placetype":"venue"
},
  "geometry": {"coordinates":[4.891958,52.360233],"type":"Point"}
}