{
  "type": "Feature",
  "properties": {
    "addr:full":"Pruimendijk 354 Ridderkerk Zuid-Holland 2989 AR",
    "addr:housenumber":"354",
    "addr:postcode":"2989",
    "addr:street":"Pruimendijk",
    "iso:country":"NL",
    "sg:address":"Pruimendijk 354",
    "sg:city":"Ridderkerk",
    "sg:orig_category":"Verzekeringen",
    "sg:phone":"+31 78 682 1800",
    "sg:postcode":"2989 AR",
    "sg:province":"Zuid-Holland",
    "wof:name":"Adviesburo Peter Van Leeuwen Bv",
    "wof:placetype":"venue"
},
  "geometry": {"coordinates":[4.640167,51.854458],"type":"Point"}
}