{
  "type": "Feature",
  "properties": {
    "iso:country":"NL",
    "sg:address":"Karolusstr 14A",
    "sg:city":"Oosterhout Nb",
    "sg:orig_category":"Veiligheidsuitrusting En -Kleding",
    "sg:phone":"+31 162 486 400",
    "sg:postcode":"4903 RJ",
    "sg:province":"North Brabant",
    "sg:website":"http://www.vandeputteinternational.com",
    "wof:name":"Vandeputte",
    "wof:placetype":"venue"
},
  "geometry": {"coordinates":[4.88181,51.61956],"type":"Point"}
}