{
  "type": "Feature",
  "properties": {
    "addr:full":"Coudorp 23 Nieuwdorp Zld Zeeland 4455 AH",
    "addr:housenumber":"23",
    "addr:postcode":"4455 ah",
    "addr:street":"Coudorp",
    "iso:country":"NL",
    "sg:address":"Coudorp 23",
    "sg:city":"Nieuwdorp Zld",
    "sg:orig_category":"Grondboringen En Bronbemalingen",
    "sg:phone":"+31 113 670 310",
    "sg:postcode":"4455 AH",
    "sg:province":"Zeeland",
    "wof:name":"Reinders-Wessemius Bv",
    "wof:placetype":"venue"
},
  "geometry": {"coordinates":[3.743731,51.468761],"type":"Point"}
}