{
  "type": "Feature",
  "properties": {
    "addr:full":"Slotermeerln 119-123 Amsterdam North Holland 1063 JN",
    "addr:housenumber":"119-123",
    "addr:postcode":"1063 jn",
    "iso:country":"NL",
    "sg:address":"Slotermeerln 119-123",
    "sg:city":"Amsterdam",
    "sg:orig_category":"Meubelen",
    "sg:phone":"+31 20 613 4486",
    "sg:postcode":"1063 JN",
    "sg:province":"North Holland",
    "wof:name":"Jos Kop Meubelen Bv",
    "wof:placetype":"venue"
},
  "geometry": {"coordinates":[4.820625,52.380375],"type":"Point"}
}