{
  "type": "Feature",
  "properties": {
    "iso:country":"NL",
    "sg:address":"Middenwg 23",
    "sg:city":"Huizen",
    "sg:orig_category":"Hoortoestellen",
    "sg:phone":"+31 35 523 3062",
    "sg:postcode":"1271 AS",
    "sg:province":"Noord-Holland",
    "sg:website":"http://www.beterhoren.nl",
    "wof:name":"Beter Horen",
    "wof:placetype":"venue"
},
  "geometry": {"coordinates":[5.236987,52.297886],"type":"Point"}
}