{
  "type": "Feature",
  "properties": {
    "addr:full":"Landstr 15A Groningen Groningen 9714 GP",
    "addr:housenumber":"15a",
    "addr:postcode":"9714 gp",
    "addr:street":"Landstr",
    "iso:country":"NL",
    "sg:address":"Landstr 15A",
    "sg:city":"Groningen",
    "sg:orig_category":"Koeriersdiensten",
    "sg:phone":"+31 50 573 1811",
    "sg:postcode":"9714 GP",
    "sg:province":"Groningen",
    "wof:name":"Mertens",
    "wof:placetype":"venue"
},
  "geometry": {"coordinates":[6.574033,53.230179],"type":"Point"}
}