{
  "type": "Feature",
  "properties": {
    "addr:full":"Tussendiepen 25 Drachten Provincie Friesland 9206 AA",
    "addr:housenumber":"25",
    "addr:postcode":"9206 aa",
    "addr:street":"Tussendiepen;Provincie Friesland",
    "iso:country":"NL",
    "sg:address":"Tussendiepen 25",
    "sg:city":"Drachten",
    "sg:orig_category":"Zoetwaren - Fabrieken En Groothandel",
    "sg:phone":"+31 512 513 905",
    "sg:postcode":"9206 AA",
    "sg:province":"Provincie Friesland",
    "wof:name":"Metz Bv, De",
    "wof:placetype":"venue"
},
  "geometry": {"coordinates":[6.073389,53.106232],"type":"Point"}
}