{
  "type": "Feature",
  "properties": {
    "addr:full":"Nieuwsteeg 27 Hoorn Nh Noord-Holland 1621 EC",
    "addr:housenumber":"27",
    "addr:postcode":"1621 ec",
    "addr:street":"Nieuwsteeg",
    "iso:country":"NL",
    "sg:address":"Nieuwsteeg 27",
    "sg:city":"Hoorn Nh",
    "sg:orig_category":"Verlichting And Huishoudartikelen",
    "sg:phone":"+31 229 215 224",
    "sg:postcode":"1621 EC",
    "sg:province":"Noord-Holland",
    "wof:name":"Stam Verlichting Bv",
    "wof:placetype":"venue"
},
  "geometry": {"coordinates":[5.058371,52.641354],"type":"Point"}
}