{
  "type": "Feature",
  "properties": {
    "iso:country":"NL",
    "sg:address":"Stationsstraat 55",
    "sg:city":"Elsloo Lb",
    "sg:orig_category":"Rijscholen",
    "sg:phone":"+31 46 437 5124",
    "sg:postcode":"6181 AE",
    "sg:province":"Limburg",
    "wof:name":"Autorijschool Bours",
    "wof:placetype":"venue"
},
  "geometry": {"coordinates":[5.769564,50.946823],"type":"Point"}
}