{
  "type": "Feature",
  "properties": {
    "addr:full":"Goudenregenplein 67 'S Gravenhage South Holland 2565 GK",
    "addr:housenumber":"67",
    "addr:postcode":"2565 gk",
    "addr:street":"Goudenregenplein;' S Gravenhage",
    "iso:country":"NL",
    "sg:address":"Goudenregenplein 67",
    "sg:city":"'S Gravenhage",
    "sg:classifiers":[
        {
            "category":"Bars & Pubs",
            "type":"Food & Drink"
        }
    ],
    "sg:phone":"+31 70 360 6586",
    "sg:postcode":"2565 GK",
    "sg:province":"South Holland",
    "wof:name":"Coffeeshop Mikelly",
    "wof:placetype":"venue"
},
  "geometry": {"coordinates":[4.263399,52.076187],"type":"Point"}
}