{
  "type": "Feature",
  "properties": {
    "addr:full":"Johannes Poststraat 412 Soest Utrecht 3762 VX",
    "addr:housenumber":"412",
    "addr:postcode":"3762 vx",
    "addr:street":"Johannes Poststraat",
    "iso:country":"NL",
    "sg:address":"Johannes Poststraat 412",
    "sg:city":"Soest",
    "sg:orig_category":"Handelsbemiddeling Textiel And Lederwaren",
    "sg:phone":"+31 35 602 4141",
    "sg:postcode":"3762 VX",
    "sg:province":"Utrecht",
    "wof:name":"Jac. C. Witte Textielagenturen",
    "wof:placetype":"venue"
},
  "geometry": {"coordinates":[5.281731,52.172527],"type":"Point"}
}