{
  "type": "Feature",
  "properties": {
    "addr:full":"Vivaldistr 5 Twello Gelderland 7391 ST",
    "addr:housenumber":"5",
    "addr:postcode":"7391 st",
    "addr:street":"Vivaldistr;Gelderland",
    "iso:country":"NL",
    "sg:address":"Vivaldistr 5",
    "sg:city":"Twello",
    "sg:orig_category":"Voetbalverenigingen",
    "sg:phone":"+31 571 274 458",
    "sg:postcode":"7391 ST",
    "sg:province":"Gelderland",
    "wof:name":"Avanti",
    "wof:placetype":"venue"
},
  "geometry": {"coordinates":[6.102384,52.228554],"type":"Point"}
}