{
  "type": "Feature",
  "properties": {
    "addr:full":"Korianderhof 47 Barendrecht Zuid-Holland 2991 HD",
    "addr:housenumber":"47",
    "addr:postcode":"2991 hd",
    "addr:street":"Korianderhof",
    "iso:country":"NL",
    "sg:address":"Korianderhof 47",
    "sg:city":"Barendrecht",
    "sg:orig_category":"Elektrotechnische Installatiebureaus",
    "sg:phone":"+31 180 629 028",
    "sg:postcode":"2991 HD",
    "sg:province":"Zuid-Holland",
    "wof:name":"Groen, R",
    "wof:placetype":"venue"
},
  "geometry": {"coordinates":[4.546994,51.855034],"type":"Point"}
}