{
  "type": "Feature",
  "properties": {
    "iso:country":"NL",
    "sg:address":"Watermunt 14",
    "sg:city":"Mierlo",
    "sg:orig_category":"Adviesbureaus Bedrijfsorganisatie",
    "sg:phone":"+31 492 592 371",
    "sg:postcode":"5731 TE",
    "sg:province":"Noord-Brabant",
    "wof:name":"Upall Cons",
    "wof:placetype":"venue"
},
  "geometry": {"coordinates":[5.625031,51.439377],"type":"Point"}
}