{
  "type": "Feature",
  "properties": {
    "addr:full":"Amsteldk N 116 Amstelveen Noord-Holland 1183 TJ",
    "addr:housenumber":"116",
    "addr:postcode":"1183 tj",
    "addr:street":"N",
    "iso:country":"NL",
    "sg:address":"Amsteldk N 116",
    "sg:city":"Amstelveen",
    "sg:orig_category":"Yoga-Instituten",
    "sg:phone":"+31 20 616 0232",
    "sg:postcode":"1183 TJ",
    "sg:province":"Noord-Holland",
    "wof:name":"Kreyenbroek, Sonja",
    "wof:placetype":"venue"
},
  "geometry": {"coordinates":[4.908245,52.318264],"type":"Point"}
}