{
  "type": "Feature",
  "properties": {
    "addr:full":"Vlietskade 7004 Arkel Gelderland 4241 WR",
    "addr:housenumber":"7004",
    "addr:postcode":"4241",
    "addr:street":"Vlietskade;Gelderland",
    "iso:country":"NL",
    "sg:address":"Vlietskade 7004",
    "sg:city":"Arkel",
    "sg:classifiers":[
        {
            "category":"Recreation",
            "subcategory":"Amusement Park",
            "type":"Entertainment"
        }
    ],
    "sg:phone":"+31 183 567 050",
    "sg:postcode":"4241 WR",
    "sg:province":"Gelderland",
    "wof:name":"Holland Indoor Karting Arkel Bv",
    "wof:placetype":"venue"
},
  "geometry": {"coordinates":[4.992002,51.866608],"type":"Point"}
}