{
  "type": "Feature",
  "properties": {
    "addr:full":"Beneluxln 1000A Utrecht Utrecht 3526 KK",
    "addr:housenumber":"1000a",
    "addr:postcode":"3526 kk",
    "iso:country":"NL",
    "sg:address":"Beneluxln 1000A",
    "sg:city":"Utrecht",
    "sg:orig_category":"Boekbinderijen",
    "sg:phone":"+31 30 289 6908",
    "sg:postcode":"3526 KK",
    "sg:province":"Utrecht",
    "sg:website":"http://www.publicard-vandoorn.nl",
    "wof:name":"Doorn Boekbinderij Bv, Van",
    "wof:placetype":"venue"
},
  "geometry": {"coordinates":[5.109135,52.067242],"type":"Point"}
}