{
  "type": "Feature",
  "properties": {
    "addr:full":"Vd Borchln 14 Breda Noord-Brabant 4835 KM",
    "addr:housenumber":"14",
    "addr:postcode":"4835 km",
    "iso:country":"NL",
    "sg:address":"Vd Borchln 14",
    "sg:city":"Breda",
    "sg:orig_category":"Tekstschrijversters",
    "sg:phone":"+31 76 561 0463",
    "sg:postcode":"4835 KM",
    "sg:province":"Noord-Brabant",
    "wof:name":"Marecom",
    "wof:placetype":"venue"
},
  "geometry": {"coordinates":[4.78509,51.569248],"type":"Point"}
}