{
  "type": "Feature",
  "properties": {
    "addr:full":"Trompstr 33 Ymuiden Noord-Holland 1971 AA",
    "addr:housenumber":"33",
    "addr:postcode":"1971 aa",
    "addr:street":"Trompstr",
    "iso:country":"NL",
    "sg:address":"Trompstr 33",
    "sg:city":"Ymuiden",
    "sg:orig_category":"Verhuur",
    "sg:phone":"+31 255 511 463",
    "sg:postcode":"1971 AA",
    "sg:province":"Noord-Holland",
    "wof:name":"Tromp",
    "wof:placetype":"venue"
},
  "geometry": {"coordinates":[4.624218,52.462509],"type":"Point"}
}