{
  "type": "Feature",
  "properties": {
    "addr:full":"Vliegertsdk 18 Grashoek Limburg 5985 PD",
    "addr:housenumber":"18",
    "addr:postcode":"5985 pd",
    "addr:street":"Vliegertsdk",
    "iso:country":"NL",
    "sg:address":"Vliegertsdk 18",
    "sg:city":"Grashoek",
    "sg:orig_category":"Zuivel - Fabrieken",
    "sg:phone":"+31 77 307 6161",
    "sg:postcode":"5985 PD",
    "sg:province":"Limburg",
    "wof:name":"Engelen, Gebr",
    "wof:placetype":"venue"
},
  "geometry": {"coordinates":[5.9513,51.365215],"type":"Point"}
}