{
  "type": "Feature",
  "properties": {
    "iso:country":"NL",
    "sg:address":"Vliegertsdk 18",
    "sg:city":"Grashoek",
    "sg:orig_category":"Zuivel - Fabrieken",
    "sg:phone":"+31 77 307 6161",
    "sg:postcode":"5985 PD",
    "sg:province":"Limburg",
    "wof:name":"Engelen, Gebr",
    "wof:placetype":"venue"
},
  "geometry": {"coordinates":[5.9513,51.365215],"type":"Point"}
}