{
  "type": "Feature",
  "properties": {
    "iso:country":"NL",
    "sg:address":"Sarphatipark 5",
    "sg:city":"Amsterdam",
    "sg:orig_category":"Binnenhuisarchitecten",
    "sg:phone":"+31 20 470 1036",
    "sg:postcode":"1073 CN",
    "sg:province":"Noord-Holland",
    "wof:name":"Faber Interieurbouw & Design",
    "wof:placetype":"venue"
},
  "geometry": {"coordinates":[4.894215,52.354767],"type":"Point"}
}