{
  "type": "Feature",
  "properties": {
    "addr:full":"Frankenslag 14D S Gravenhage South Holland 2582 HR",
    "addr:housenumber":"14d",
    "addr:postcode":"2582 hr",
    "addr:street":"Frankenslag;S Gravenhage",
    "iso:country":"NL",
    "sg:address":"Frankenslag 14D",
    "sg:city":"S Gravenhage",
    "sg:orig_category":"Fotografie Reclame En Mode",
    "sg:phone":"+31 70 323 9925",
    "sg:postcode":"2582 HR",
    "sg:province":"South Holland",
    "wof:name":"Zwier, Egbert",
    "wof:placetype":"venue"
},
  "geometry": {"coordinates":[4.27852,52.092411],"type":"Point"}
}