{
  "type": "Feature",
  "properties": {
    "iso:country":"NL",
    "sg:address":"Haarlemmerstraat 74",
    "sg:city":"Hillegom",
    "sg:orig_category":"Boekenuitgeverijen",
    "sg:phone":"+31 23 584 6757",
    "sg:postcode":"2181 HD",
    "sg:province":"Zuid-Holland",
    "wof:name":"Uitgeverij Zonnebloem Bv",
    "wof:placetype":"venue"
},
  "geometry": {"coordinates":[4.58865,52.313381],"type":"Point"}
}