{
  "type": "Feature",
  "properties": {
    "addr:full":"Oudegr 284 Utrecht Utrecht 3511 NW",
    "addr:housenumber":"284",
    "addr:postcode":"3511 nw",
    "iso:country":"NL",
    "sg:address":"Oudegr 284",
    "sg:city":"Utrecht",
    "sg:classifiers":[
        {
            "category":"Shopping",
            "subcategory":"Gifts & Souvenirs",
            "type":"Retail Goods"
        }
    ],
    "sg:phone":"+31 30 234 3343",
    "sg:postcode":"3511 NW",
    "sg:province":"Utrecht",
    "sg:tags":[
        "wens-",
        "en",
        "prentbriefkaarten"
    ],
    "wof:name":"Groeten Uit, Postcardshop",
    "wof:placetype":"venue"
},
  "geometry": {"coordinates":[5.1154050827,52.0889320374],"type":"Point"}
}