{
  "type": "Feature",
  "properties": {
    "addr:full":"T Goylaan 100 Utrecht Utrecht 3525 AK",
    "addr:housenumber":"100",
    "addr:postcode":"3525 ak",
    "addr:street":"T Goylaan",
    "iso:country":"NL",
    "sg:address":"T Goylaan 100",
    "sg:city":"Utrecht",
    "sg:orig_category":"Kappers",
    "sg:phone":"+31 30 288 0943",
    "sg:postcode":"3525 AK",
    "sg:province":"Utrecht",
    "wof:name":"Ton De Bruyn Haarverzorging",
    "wof:placetype":"venue"
},
  "geometry": {"coordinates":[5.121399,52.066139],"type":"Point"}
}