{
  "type": "Feature",
  "properties": {
    "iso:country":"NL",
    "sg:address":"Beukemastraat 44",
    "sg:city":"Hoogeveen",
    "sg:classifiers":[
        {
            "category":"Education",
            "subcategory":"Preschool",
            "type":"Public Place"
        }
    ],
    "sg:phone":"+31 528 267 382",
    "sg:postcode":"7906 AN",
    "sg:province":"Provincie Drenthe",
    "sg:tags":[
        "kleuteronderwijs",
        "basis-"
    ],
    "wof:name":"Johannes Calvijnschool",
    "wof:placetype":"venue"
},
  "geometry": {"coordinates":[6.4806,52.716785],"type":"Point"}
}