{
  "type": "Feature",
  "properties": {
    "addr:full":"Abbestederwg 7 Callantsoog Noord-Holland 1759 NA",
    "addr:housenumber":"7",
    "addr:postcode":"1759 na",
    "addr:street":"Abbestederwg",
    "iso:country":"NL",
    "sg:address":"Abbestederwg 7",
    "sg:city":"Callantsoog",
    "sg:classifiers":[
        {
            "category":"Personal",
            "subcategory":"Nail Salon",
            "type":"Services"
        }
    ],
    "sg:phone":"+31 224 581 862",
    "sg:postcode":"1759 NA",
    "sg:province":"Noord-Holland",
    "sg:tags":[
        "pedicure"
    ],
    "wof:name":"Sijnesael, Inge",
    "wof:placetype":"venue"
},
  "geometry": {"coordinates":[4.695618,52.840199],"type":"Point"}
}