{
  "type": "Feature",
  "properties": {
    "addr:full":"Passage 10 Valkenswaard North Brabant 5554 AH",
    "addr:housenumber":"10",
    "addr:postcode":"5554 ah",
    "addr:street":"Passage",
    "iso:country":"NL",
    "sg:address":"Passage 10",
    "sg:city":"Valkenswaard",
    "sg:orig_category":"Verlichting And Huishoudartikelen",
    "sg:phone":"+31 40 201 6244",
    "sg:postcode":"5554 AH",
    "sg:province":"North Brabant",
    "wof:name":"Lumiere",
    "wof:placetype":"venue"
},
  "geometry": {"coordinates":[5.458852,51.352104],"type":"Point"}
}