{
  "type": "Feature",
  "properties": {
    "iso:country":"NL",
    "sg:address":"De Watersnip 7",
    "sg:city":"St Michielsgestel",
    "sg:orig_category":"Adviesbureaus Bedrijfsorganisatie",
    "sg:phone":"+31 73 551 6255",
    "sg:postcode":"5271 LG",
    "sg:province":"North Brabant",
    "wof:name":"Insight Int Bv",
    "wof:placetype":"venue"
},
  "geometry": {"coordinates":[5.363877,51.644459],"type":"Point"}
}