{
  "type": "Feature",
  "properties": {
    "addr:full":"Nimbus 8 Hellevoetsluis Zuid-Holland 3225 VM",
    "addr:housenumber":"8",
    "addr:postcode":"3225 vm",
    "addr:street":"Nimbus",
    "iso:country":"NL",
    "sg:address":"Nimbus 8",
    "sg:city":"Hellevoetsluis",
    "sg:orig_category":"Keukens",
    "sg:phone":"+31 181 310 701",
    "sg:postcode":"3225 VM",
    "sg:province":"Zuid-Holland",
    "wof:name":"Unibehr",
    "wof:placetype":"venue"
},
  "geometry": {"coordinates":[4.163565,51.835064],"type":"Point"}
}