{
  "type": "Feature",
  "properties": {
    "addr:full":"Zaanenlaan 11 Haarlem Noord-Holland 2023 SH",
    "addr:housenumber":"11",
    "addr:postcode":"2023 sh",
    "addr:street":"Zaanenlaan",
    "iso:country":"NL",
    "sg:address":"Zaanenlaan 11",
    "sg:city":"Haarlem",
    "sg:orig_category":"Verzekeringen",
    "sg:phone":"+31 23 526 2808",
    "sg:postcode":"2023 SH",
    "sg:province":"Noord-Holland",
    "wof:name":"Willemse Business Services Haarlem Bv",
    "wof:placetype":"venue"
},
  "geometry": {"coordinates":[4.643928,52.401348],"type":"Point"}
}