{
  "type": "Feature",
  "properties": {
    "addr:full":"Oyense Benedendk 26 Oyen Noord-Brabant 5394 LT",
    "addr:housenumber":"26",
    "addr:postcode":"5394 lt",
    "addr:street":"Oyen",
    "iso:country":"NL",
    "sg:address":"Oyense Benedendk 26",
    "sg:city":"Oyen",
    "sg:orig_category":"Adviesbureaus Elektrotechniek",
    "sg:phone":"+31 412 492 889",
    "sg:postcode":"5394 LT",
    "sg:province":"Noord-Brabant",
    "wof:name":"Etab Oyen",
    "wof:placetype":"venue"
},
  "geometry": {"coordinates":[-96.055939,42.820534],"type":"Point"}
}