{
  "type": "Feature",
  "properties": {
    "addr:full":"Jan Thomeelaan 24 Delft Zuid-Holland 2625 DV",
    "addr:housenumber":"24",
    "addr:postcode":"2625 dv",
    "addr:street":"Thomeelaan",
    "iso:country":"NL",
    "sg:address":"Jan Thomeelaan 24",
    "sg:city":"Delft",
    "sg:classifiers":[
        {
            "category":"Professional",
            "subcategory":"Accounting & Tax Preparation",
            "type":"Services"
        }
    ],
    "sg:phone":"+31 15 262 4633",
    "sg:postcode":"2625 DV",
    "sg:province":"Zuid-Holland",
    "sg:tags":[
        "accountant"
    ],
    "wof:name":"P.H. Van Velzen Consultancy",
    "wof:placetype":"venue"
},
  "geometry": {"coordinates":[4.333757,51.995491],"type":"Point"}
}