{
  "type": "Feature",
  "properties": {
    "iso:country":"NL",
    "sg:address":"Bloemerstraat 38",
    "sg:city":"Nijmegen",
    "sg:orig_category":"Film-, Tv- And Videoproductie",
    "sg:phone":"+31 24 323 2988",
    "sg:postcode":"6511 EK",
    "sg:province":"Gelderland",
    "wof:name":"Videoproduktiebedrijf P.J.M. Versleijen",
    "wof:placetype":"venue"
},
  "geometry": {"coordinates":[5.860463,51.844753],"type":"Point"}
}