{
  "type": "Feature",
  "properties": {
    "addr:full":"Traay 35 Driebergen Rysenb Utrecht 3971 GB",
    "addr:housenumber":"35",
    "addr:postcode":"3971 gb",
    "addr:street":"Traay;Rysenb",
    "iso:country":"NL",
    "sg:address":"Traay 35",
    "sg:city":"Driebergen Rysenb",
    "sg:orig_category":"Boeken En Tijdschriften",
    "sg:phone":"+31 343 517 362",
    "sg:postcode":"3971 GB",
    "sg:province":"Utrecht",
    "sg:website":"http://www.nieskens.nl",
    "wof:name":"Nieskens",
    "wof:placetype":"venue"
},
  "geometry": {"coordinates":[5.284294,52.05265],"type":"Point"}
}