{
  "type": "Feature",
  "properties": {
    "addr:full":"Doormanstr 14 A/B Capelle Ad Yssel South Holland 2901 AJ",
    "addr:housenumber":"14 a / b;2901",
    "addr:postcode":"aj",
    "addr:street":"Doormanstr;Yssel",
    "iso:country":"NL",
    "sg:address":"Doormanstr 14 A/B",
    "sg:city":"Capelle Ad Yssel",
    "sg:orig_category":"Opticiens",
    "sg:phone":"+31 10 279 9869",
    "sg:postcode":"2901 AJ",
    "sg:province":"South Holland",
    "wof:name":"Eyes Design",
    "wof:placetype":"venue"
},
  "geometry": {"coordinates":[4.564260006,51.9169807434],"type":"Point"}
}