{
  "type": "Feature",
  "properties": {
    "addr:full":"Stationsweg 49 Wezep Gelderland 8091 AB",
    "addr:housenumber":"49",
    "addr:postcode":"8091 ab",
    "addr:street":"Stationsweg",
    "iso:country":"NL",
    "sg:address":"Stationsweg 49",
    "sg:city":"Wezep",
    "sg:orig_category":"Boekenuitgeverijen",
    "sg:phone":"+31 38 376 3390",
    "sg:postcode":"8091 AB",
    "sg:province":"Gelderland",
    "wof:name":"Drukkerij Bredewold",
    "wof:placetype":"venue"
},
  "geometry": {"coordinates":[5.99585,52.460045],"type":"Point"}
}