{
  "type": "Feature",
  "properties": {
    "iso:country":"NL",
    "sg:address":"Industriewg 20",
    "sg:city":"Berkel En Rodenrys",
    "sg:orig_category":"Machinefabrieken",
    "sg:phone":"+31 10 512 0600",
    "sg:postcode":"2651 BD",
    "sg:province":"South Holland",
    "wof:name":"Cupedo & Zn, J G N",
    "wof:placetype":"venue"
},
  "geometry": {"coordinates":[4.456897,51.978905],"type":"Point"}
}