{
  "type": "Feature",
  "properties": {
    "addr:full":"Bruggeln 8B Appelscha Provincie Friesland 8426 BE",
    "addr:housenumber":"8b",
    "addr:postcode":"8426",
    "addr:street":"Bruggeln;Provincie Friesland",
    "iso:country":"NL",
    "sg:address":"Bruggeln 8B",
    "sg:city":"Appelscha",
    "sg:orig_category":"Verzekeringen - Verzekeringskantoren",
    "sg:phone":"+31 516 431 403",
    "sg:postcode":"8426 BE",
    "sg:province":"Provincie Friesland",
    "wof:name":"Koelma, J",
    "wof:placetype":"venue"
},
  "geometry": {"coordinates":[6.339048,52.95488],"type":"Point"}
}