{
  "type": "Feature",
  "properties": {
    "addr:full":"Gildewg 2 Nootdorp Zuid-Holland 2632 BA",
    "addr:housenumber":"2",
    "addr:postcode":"2632 ba",
    "addr:street":"Gildewg",
    "iso:country":"NL",
    "sg:address":"Gildewg 2",
    "sg:city":"Nootdorp",
    "sg:orig_category":"Partyservice",
    "sg:phone":"+31 15 310 9180",
    "sg:postcode":"2632 BA",
    "sg:province":"Zuid-Holland",
    "sg:website":"http://www.wittepaard.nl",
    "wof:name":"Witte Paard, Het",
    "wof:placetype":"venue"
},
  "geometry": {"coordinates":[4.403076,52.052223],"type":"Point"}
}