{
  "type": "Feature",
  "properties": {
    "addr:full":"Pln Welgelegen 2 Krimpen Aan De Lek Zuid-Holland 2931 HG",
    "addr:housenumber":"2",
    "addr:postcode":"lek;2931 hg",
    "iso:country":"NL",
    "sg:address":"Pln Welgelegen 2",
    "sg:city":"Krimpen Aan De Lek",
    "sg:orig_category":"Meubelstoffering",
    "sg:phone":"+31 180 550 623",
    "sg:postcode":"2931 HG",
    "sg:province":"Zuid-Holland",
    "wof:name":"Deurzen, C M W Van",
    "wof:placetype":"venue"
},
  "geometry": {"coordinates":[4.626837,51.891792],"type":"Point"}
}