{
  "type": "Feature",
  "properties": {
    "addr:full":"Burg V Hooffln 67 Veldhoven Noord-Brabant 5503 BK",
    "addr:housenumber":"67",
    "addr:postcode":"5503 bk",
    "addr:street":"Burg V Hooffln",
    "iso:country":"NL",
    "sg:address":"Burg V Hooffln 67",
    "sg:city":"Veldhoven",
    "sg:classifiers":[
        {
            "category":"Food & Beverages",
            "subcategory":"Bakery",
            "type":"Retail Goods"
        }
    ],
    "sg:phone":"+31 40 255 6636",
    "sg:postcode":"5503 BK",
    "sg:province":"Noord-Brabant",
    "sg:tags":[
        "pizza"
    ],
    "sg:website":"http://www.dominos.nl",
    "wof:name":"Domino",
    "wof:placetype":"venue"
},
  "geometry": {"coordinates":[5.404554,51.421745],"type":"Point"}
}