{
  "type": "Feature",
  "properties": {
    "iso:country":"NL",
    "sg:address":"J Catsstr 5",
    "sg:city":"Voorburg",
    "sg:classifiers":[
        {
            "category":"Personal",
            "subcategory":"Nail Salon",
            "type":"Services"
        }
    ],
    "sg:phone":"+31 70 386 6934",
    "sg:postcode":"2274 GS",
    "sg:province":"Zuid-Holland",
    "sg:tags":[
        "pedicure"
    ],
    "wof:name":"Paridaens, C M B",
    "wof:placetype":"venue"
},
  "geometry": {"coordinates":[4.350976,52.075314],"type":"Point"}
}