{
  "type": "Feature",
  "properties": {
    "iso:country":"NL",
    "sg:address":"De Linde 13",
    "sg:city":"Ouderkerk A/D Ijssel",
    "sg:orig_category":"Binnenhuisarchitecten",
    "sg:phone":"+31 180 681 959",
    "sg:postcode":"2935 SH",
    "sg:province":"Zuid-Holland",
    "wof:name":"Interieur Architektuur S.I. Pitti",
    "wof:placetype":"venue"
},
  "geometry": {"coordinates":[4.634108,51.932316],"type":"Point"}
}