{
  "type": "Feature",
  "properties": {
    "addr:full":"De Linde 13 Ouderkerk A/D Ijssel Zuid-Holland 2935 SH",
    "addr:housenumber":"13;a / d;2935",
    "addr:postcode":"sh",
    "addr:street":"De Linde",
    "iso:country":"NL",
    "sg:address":"De Linde 13",
    "sg:city":"Ouderkerk A/D Ijssel",
    "sg:orig_category":"Binnenhuisarchitecten",
    "sg:phone":"+31 180 681 959",
    "sg:postcode":"2935 SH",
    "sg:province":"Zuid-Holland",
    "wof:name":"Interieur Architektuur S.I. Pitti",
    "wof:placetype":"venue"
},
  "geometry": {"coordinates":[4.634108,51.932316],"type":"Point"}
}