{
  "type": "Feature",
  "properties": {
    "addr:full":"Van Boshuizenstraat 119 Amsterdam Zuid North Holland 1083 AS",
    "addr:housenumber":"119",
    "addr:postcode":"1083 as",
    "addr:street":"Van Boshuizenstraat;Holland",
    "iso:country":"NL",
    "sg:address":"Van Boshuizenstraat 119",
    "sg:city":"Amsterdam Zuid",
    "sg:orig_category":"Bedrijfs- And Managementsconsultants",
    "sg:phone":"+31 20 642 5122",
    "sg:postcode":"1083 AS",
    "sg:province":"North Holland",
    "wof:name":"Personeelsadviesbureau Jeanette Schouten",
    "wof:placetype":"venue"
},
  "geometry": {"coordinates":[4.886651,52.324684],"type":"Point"}
}