{
  "type": "Feature",
  "properties": {
    "addr:full":"Ambachtsstraat 6 Terneuzen Zeeland 4538 AW",
    "addr:housenumber":"6",
    "addr:postcode":"4538 aw",
    "addr:street":"Ambachtsstraat",
    "iso:country":"NL",
    "sg:address":"Ambachtsstraat 6",
    "sg:city":"Terneuzen",
    "sg:orig_category":"Wegen And Sportterreinen",
    "sg:phone":"+31 115 618 256",
    "sg:postcode":"4538 AW",
    "sg:province":"Zeeland",
    "wof:name":"Aannemersbedrijf 'T Gilde Bv",
    "wof:placetype":"venue"
},
  "geometry": {"coordinates":[3.8506169319,51.3073120117],"type":"Point"}
}