{
  "type": "Feature",
  "properties": {
    "addr:full":"Peschstr 32A Geleen Limburg 6166 CT",
    "addr:housenumber":"32a",
    "addr:postcode":"6166 ct",
    "addr:street":"Peschstr",
    "iso:country":"NL",
    "sg:address":"Peschstr 32A",
    "sg:city":"Geleen",
    "sg:orig_category":"Organisatiebureaus",
    "sg:phone":"+31 6 18449083",
    "sg:postcode":"6166 CT",
    "sg:province":"Limburg",
    "sg:website":"http://www.greengx.com",
    "wof:name":"Green Galaxy",
    "wof:placetype":"venue"
},
  "geometry": {"coordinates":[5.8432488441,50.9703330994],"type":"Point"}
}