{
  "type": "Feature",
  "properties": {
    "addr:full":"Stadhoudersplein 1 Alphen A/D Rijn Zuid-Holland 2404 BE",
    "addr:housenumber":"1",
    "addr:postcode":"2404",
    "addr:street":"Stadhoudersplein",
    "iso:country":"NL",
    "sg:address":"Stadhoudersplein 1",
    "sg:city":"Alphen A/D Rijn",
    "sg:orig_category":"Verzekeringen",
    "sg:phone":"+31 172 424 011",
    "sg:postcode":"2404 BE",
    "sg:province":"Zuid-Holland",
    "wof:name":"Verda Verzekeringen Bv",
    "wof:placetype":"venue"
},
  "geometry": {"coordinates":[4.655566,52.134964],"type":"Point"}
}