{
  "type": "Feature",
  "properties": {
    "iso:country":"NL",
    "sg:address":"Sittarderwg 79B",
    "sg:city":"Heerlen",
    "sg:orig_category":"Wijnkoperijen En -Groothandel",
    "sg:phone":"+31 45 572 9701",
    "sg:postcode":"6412 CC",
    "sg:province":"Limburg",
    "sg:website":"http://www.roncohenwijnen.com",
    "wof:name":"Cohen Bv, Ron",
    "wof:placetype":"venue"
},
  "geometry": {"coordinates":[5.9752187729,50.8935432434],"type":"Point"}
}