{
  "type": "Feature",
  "properties": {
    "iso:country":"NL",
    "sg:address":"Noordeinde 148",
    "sg:city":"Landsmeer",
    "sg:orig_category":"Bedrijfsinventaris Gh",
    "sg:phone":"+31 20 482 3866",
    "sg:postcode":"1121 AM",
    "sg:province":"Noord-Holland",
    "wof:name":"Vof Th. Maeijer En Zonen",
    "wof:placetype":"venue"
},
  "geometry": {"coordinates":[4.914545,52.435867],"type":"Point"}
}