{
  "type": "Feature",
  "properties": {
    "iso:country":"NL",
    "sg:address":"Castenrayseweg 14",
    "sg:city":"Oirlo",
    "sg:orig_category":"Loodgieterswerk, Verwarming And Sanitaire Installaties",
    "sg:phone":"+31 478 571 941",
    "sg:postcode":"5808 AG",
    "sg:province":"Limburg",
    "wof:name":"Versleijen Agri Bv",
    "wof:placetype":"venue"
},
  "geometry": {"coordinates":[6.041828,51.502571],"type":"Point"}
}