{
  "type": "Feature",
  "properties": {
    "addr:full":"De Wetstr 2 Arnhem Gelderland 6814 AP",
    "addr:housenumber":"2",
    "addr:postcode":"6814 ap",
    "iso:country":"NL",
    "sg:address":"De Wetstr 2",
    "sg:city":"Arnhem",
    "sg:orig_category":"Koeriersdiensten",
    "sg:phone":"+31 26 442 2865",
    "sg:postcode":"6814 AP",
    "sg:province":"Gelderland",
    "wof:name":"Arnhem Express",
    "wof:placetype":"venue"
},
  "geometry": {"coordinates":[5.908813,51.98634],"type":"Point"}
}