{
  "type": "Feature",
  "properties": {
    "addr:full":"Veilingweg 4 Zandeweer Groningen 9997 PC",
    "addr:housenumber":"4",
    "addr:postcode":"9997 pc",
    "addr:street":"Veilingweg",
    "iso:country":"NL",
    "sg:address":"Veilingweg 4",
    "sg:city":"Zandeweer",
    "sg:orig_category":"Kappers",
    "sg:phone":"+31 595 431 367",
    "sg:postcode":"9997 PC",
    "sg:province":"Groningen",
    "wof:name":"C J De Vos",
    "wof:placetype":"venue"
},
  "geometry": {"coordinates":[6.6821780205,53.3883781433],"type":"Point"}
}