{
  "type": "Feature",
  "properties": {
    "addr:full":"Herenstr 25 Raalte Overijssel 8102 CN",
    "addr:housenumber":"25",
    "addr:postcode":"8102 cn",
    "addr:street":"Herenstr",
    "iso:country":"NL",
    "sg:address":"Herenstr 25",
    "sg:city":"Raalte",
    "sg:orig_category":"Zoetwaren - Winkels",
    "sg:phone":"+31 572 358 838",
    "sg:postcode":"8102 CN",
    "sg:province":"Overijssel",
    "wof:name":"Jamin",
    "wof:placetype":"venue"
},
  "geometry": {"coordinates":[6.275134,52.386505],"type":"Point"}
}