{
  "type": "Feature",
  "properties": {
    "addr:full":"Schoolpad 8 Berkel En Rodenrijs South Holland 2651 TM",
    "addr:housenumber":"8",
    "addr:postcode":"2651 tm",
    "addr:street":"Schoolpad",
    "iso:country":"NL",
    "sg:address":"Schoolpad 8",
    "sg:city":"Berkel En Rodenrijs",
    "sg:classifiers":[
        {
            "category":"Education",
            "subcategory":"Preschool",
            "type":"Public Place"
        }
    ],
    "sg:phone":"+31 10 511 3280",
    "sg:postcode":"2651 TM",
    "sg:province":"South Holland",
    "sg:tags":[
        "kleuteronderwijs",
        "basis-"
    ],
    "wof:name":"Evert Kuilema Basisschool",
    "wof:placetype":"venue"
},
  "geometry": {"coordinates":[4.486812,52.000736],"type":"Point"}
}