{
  "type": "Feature",
  "properties": {
    "iso:country":"NL",
    "sg:address":"Hammerstraat 48",
    "sg:city":"Epe",
    "sg:orig_category":"Diverse Grafische Activiteiten",
    "sg:phone":"+31 578 676 200",
    "sg:postcode":"8161 PH",
    "sg:province":"Gelderland",
    "wof:name":"Zeefdrukkerij Decoprint Bv",
    "wof:placetype":"venue"
},
  "geometry": {"coordinates":[5.999332,52.345234],"type":"Point"}
}