{
  "type": "Feature",
  "properties": {
    "iso:country":"NL",
    "sg:address":"Kraneweg 19",
    "sg:city":"Groningen",
    "sg:orig_category":"Advocaten And Juridische Adviseurs",
    "sg:phone":"+31 50 314 2142",
    "sg:postcode":"9718 JD",
    "sg:province":"Groningen",
    "wof:name":"Van Dijk Advocaten",
    "wof:placetype":"venue"
},
  "geometry": {"coordinates":[6.553722,53.218086],"type":"Point"}
}