{
  "type": "Feature",
  "properties": {
    "addr:full":"Hollenhof 4 Wamel Gelderland 6659 BC",
    "addr:housenumber":"4",
    "addr:postcode":"6659 bc",
    "addr:street":"Hollenhof;Gelderland",
    "iso:country":"NL",
    "sg:address":"Hollenhof 4",
    "sg:city":"Wamel",
    "sg:orig_category":"Loodgieterswerk, Verwarming And Sanitaire Installaties",
    "sg:phone":"+31 487 501 381",
    "sg:postcode":"6659 BC",
    "sg:province":"Gelderland",
    "wof:name":"G.M.A.J. Pompen",
    "wof:placetype":"venue"
},
  "geometry": {"coordinates":[5.471849,51.880356],"type":"Point"}
}