{
  "type": "Feature",
  "properties": {
    "iso:country":"NL",
    "sg:address":"Jagersheuvelstr 36A",
    "sg:city":"S Hertogenbosch",
    "sg:orig_category":"Autopoetsbedrijven",
    "sg:phone":"+31 73 621 4719",
    "sg:postcode":"5222 BJ",
    "sg:province":"Noord-Brabant",
    "wof:name":"Hepo Car Cleaning",
    "wof:placetype":"venue"
},
  "geometry": {"coordinates":[5.280802,51.696327],"type":"Point"}
}