{
  "type": "Feature",
  "properties": {
    "addr:full":"Margrietstraat 43 Mierlo North Brabant 5731 BN",
    "addr:housenumber":"43",
    "addr:postcode":"5731 bn",
    "addr:street":"Margrietstraat",
    "iso:country":"NL",
    "sg:address":"Margrietstraat 43",
    "sg:city":"Mierlo",
    "sg:classifiers":[
        {
            "category":"Retail",
            "subcategory":"Photofinishing",
            "type":"Services"
        }
    ],
    "sg:phone":"+31 492 661 960",
    "sg:postcode":"5731 BN",
    "sg:province":"North Brabant",
    "sg:tags":[
        "foto",
        "film"
    ],
    "wof:name":"Combifoto Dries Van Bergeijk",
    "wof:placetype":"venue"
},
  "geometry": {"coordinates":[5.619225,51.441963],"type":"Point"}
}