{
  "type": "Feature",
  "properties": {
    "addr:full":"Sloetmarke 37 Zwolle NL.08 8016 CJ",
    "addr:housenumber":"37",
    "addr:postcode":"8016",
    "addr:street":"Sloetmarke;Cj",
    "iso:country":"NL",
    "sg:address":"Sloetmarke 37",
    "sg:city":"Zwolle",
    "sg:orig_category":"Schoonheidssalons",
    "sg:phone":"+31 38 465 6910",
    "sg:postcode":"8016 CJ",
    "sg:province":"NL.08",
    "wof:name":"Annelies Koopman",
    "wof:placetype":"venue"
},
  "geometry": {"coordinates":[6.100663,52.483871],"type":"Point"}
}