{
  "type": "Feature",
  "properties": {
    "addr:full":"Postbus 123 Didam Gelderland 6940 AA",
    "addr:housenumber":"123",
    "addr:postcode":"6940 aa",
    "addr:street":"Postbus;Gelderland",
    "iso:country":"NL",
    "sg:address":"Postbus 123",
    "sg:city":"Didam",
    "sg:orig_category":"Fitnesscentra",
    "sg:phone":"+31 6 53236877",
    "sg:postcode":"6940 AA",
    "sg:province":"Gelderland",
    "wof:name":"Vivid",
    "wof:placetype":"venue"
},
  "geometry": {"coordinates":[6.129,51.942871],"type":"Point"}
}