{
  "type": "Feature",
  "properties": {
    "addr:full":"Norenberg 42 Veldhoven Noord-Brabant 5508 DK",
    "addr:housenumber":"42",
    "addr:postcode":"5508 dk",
    "addr:street":"Norenberg",
    "iso:country":"NL",
    "sg:address":"Norenberg 42",
    "sg:city":"Veldhoven",
    "sg:orig_category":"Metaalwerken",
    "sg:phone":"+31 40 253 7608",
    "sg:postcode":"5508 DK",
    "sg:province":"Noord-Brabant",
    "wof:name":"Wima Stucadoorswerken Bv",
    "wof:placetype":"venue"
},
  "geometry": {"coordinates":[5.385942,51.425434],"type":"Point"}
}