{
  "type": "Feature",
  "properties": {
    "addr:full":"Helftheuvelwg 47 S Hertogenbosch Noord-Brabant 5222 AV",
    "addr:housenumber":"47",
    "addr:postcode":"5222 av",
    "addr:street":"Helftheuvelwg;S Hertogenbosch",
    "iso:country":"NL",
    "sg:address":"Helftheuvelwg 47",
    "sg:city":"S Hertogenbosch",
    "sg:orig_category":"Accountants - Administratie- Consulenten En -Kantoren",
    "sg:phone":"+31 73 621 7115",
    "sg:postcode":"5222 AV",
    "sg:province":"Noord-Brabant",
    "wof:name":"Accadi",
    "wof:placetype":"venue"
},
  "geometry": {"coordinates":[5.270372,51.700161],"type":"Point"}
}