{
  "type": "Feature",
  "properties": {
    "addr:full":"Pekelharingswg 3 Deventer NL.08 7414 KM",
    "addr:housenumber":"3;nl.08",
    "addr:street":"Pekelharingswg;7414 Km",
    "iso:country":"NL",
    "sg:address":"Pekelharingswg 3",
    "sg:city":"Deventer",
    "sg:classifiers":[
        {
            "category":"Personal",
            "subcategory":"Nail Salon",
            "type":"Services"
        }
    ],
    "sg:phone":"+31 570 643 010",
    "sg:postcode":"7414 KM",
    "sg:province":"NL.08",
    "sg:tags":[
        "pedicure"
    ],
    "wof:name":"Jonkers, Solange",
    "wof:placetype":"venue"
},
  "geometry": {"coordinates":[6.128682,52.274128],"type":"Point"}
}