{
  "type": "Feature",
  "properties": {
    "addr:full":"Kam Onneswg 39 Bussum Noord-Holland 1402 EC",
    "addr:housenumber":"39",
    "addr:postcode":"1402 ec",
    "iso:country":"NL",
    "sg:address":"Kam Onneswg 39",
    "sg:city":"Bussum",
    "sg:orig_category":"Schoonheidsinstituten",
    "sg:phone":"+31 35 693 8166",
    "sg:postcode":"1402 EC",
    "sg:province":"Noord-Holland",
    "sg:website":"http://www.maryfaberhuidverzorging.nl",
    "wof:name":"Faber, Mary",
    "wof:placetype":"venue"
},
  "geometry": {"coordinates":[5.182296,52.272743],"type":"Point"}
}