{
  "type": "Feature",
  "properties": {
    "addr:full":"Postbus 12819 Amsterdam Zuidoost North Holland 1100 AV",
    "addr:housenumber":"12819",
    "addr:postcode":"1100 av",
    "addr:street":"Postbus",
    "iso:country":"NL",
    "sg:address":"Postbus 12819",
    "sg:city":"Amsterdam Zuidoost",
    "sg:orig_category":"Onroerende Goederen",
    "sg:phone":"+31 20 600 4808",
    "sg:postcode":"1100 AV",
    "sg:province":"North Holland",
    "sg:website":"http://www.filsanbv.nl",
    "wof:name":"Filsan Bv",
    "wof:placetype":"venue"
},
  "geometry": {"coordinates":[4.95131,52.316158],"type":"Point"}
}