{
  "type": "Feature",
  "properties": {
    "addr:full":"Orlyplein 101 Amsterdam Noord-Holland 1043 DT",
    "addr:housenumber":"101",
    "addr:postcode":"1043 dt",
    "addr:street":"Orlyplein",
    "iso:country":"NL",
    "sg:address":"Orlyplein 101",
    "sg:city":"Amsterdam",
    "sg:orig_category":"Bloemen And Planten",
    "sg:phone":"+31 20 686 8622",
    "sg:postcode":"1043 DT",
    "sg:province":"Noord-Holland",
    "wof:name":"Bloemenkiosk Henk Bout Vof",
    "wof:placetype":"venue"
},
  "geometry": {"coordinates":[4.837213,52.389404],"type":"Point"}
}