{
  "type": "Feature",
  "properties": {
    "iso:country":"NL",
    "sg:address":"Langs De Baan 110",
    "sg:city":"Hoogvliet Rt",
    "sg:orig_category":"Adviesbureaus Bedrijfsorganisatie",
    "sg:phone":"+31 10 472 5500",
    "sg:postcode":"3191 TP",
    "sg:province":"South Holland",
    "wof:name":"Quality & Risk Management",
    "wof:placetype":"venue"
},
  "geometry": {"coordinates":[4.365443,51.860744],"type":"Point"}
}