{
  "type": "Feature",
  "properties": {
    "addr:full":"Langs De Baan 110 Hoogvliet Rt South Holland 3191 TP",
    "addr:housenumber":"110",
    "addr:postcode":"3191 tp",
    "addr:street":"Langs De Baan;Rt South",
    "iso:country":"NL",
    "sg:address":"Langs De Baan 110",
    "sg:city":"Hoogvliet Rt",
    "sg:orig_category":"Adviesbureaus Bedrijfsorganisatie",
    "sg:phone":"+31 10 472 5500",
    "sg:postcode":"3191 TP",
    "sg:province":"South Holland",
    "wof:name":"Quality & Risk Management",
    "wof:placetype":"venue"
},
  "geometry": {"coordinates":[4.365443,51.860744],"type":"Point"}
}