{
  "type": "Feature",
  "properties": {
    "iso:country":"NL",
    "sg:address":"Heliconw 40A",
    "sg:city":"Leeuwarden",
    "sg:orig_category":"Margarine, Olie En Vet - Industrie",
    "sg:phone":"+31 58 212 0012",
    "sg:postcode":"8914 AT",
    "sg:province":"Provincie Friesland",
    "wof:name":"Bellmar Bv",
    "wof:placetype":"venue"
},
  "geometry": {"coordinates":[5.775307,53.202629],"type":"Point"}
}