{
  "type": "Feature",
  "properties": {
    "addr:full":"Winkelcentrum Coevering 24 Geldrop Noord-Brabant 5665 GA",
    "addr:housenumber":"24",
    "addr:postcode":"5665 ga",
    "addr:street":"Winkelcentrum Coevering",
    "iso:country":"NL",
    "sg:address":"Winkelcentrum Coevering 24",
    "sg:city":"Geldrop",
    "sg:orig_category":"Zuivelproducten",
    "sg:phone":"+31 40 285 4953",
    "sg:postcode":"5665 GA",
    "sg:province":"Noord-Brabant",
    "wof:name":"T Kaaspunt",
    "wof:placetype":"venue"
},
  "geometry": {"coordinates":[5.574491,51.417072],"type":"Point"}
}