{
  "type": "Feature",
  "properties": {
    "addr:full":"Enschedesestr 29 Hengelo Ov Overijssel 7551 EH",
    "addr:housenumber":"29",
    "addr:postcode":"7551 eh",
    "addr:street":"Enschedesestr;Ov",
    "iso:country":"NL",
    "sg:address":"Enschedesestr 29",
    "sg:city":"Hengelo Ov",
    "sg:orig_category":"Kappers",
    "sg:phone":"+31 74 291 0231",
    "sg:postcode":"7551 EH",
    "sg:province":"Overijssel",
    "wof:name":"Jos",
    "wof:placetype":"venue"
},
  "geometry": {"coordinates":[6.7954120636,52.2646026611],"type":"Point"}
}