{
  "type": "Feature",
  "properties": {
    "addr:full":"Kalverstr 9 Amsterdam Noord-Holland 1012 NX",
    "addr:housenumber":"9",
    "addr:postcode":"1012 nx",
    "addr:street":"Kalverstr",
    "iso:country":"NL",
    "sg:address":"Kalverstr 9",
    "sg:city":"Amsterdam",
    "sg:orig_category":"Bijouterie?n",
    "sg:phone":"+31 20 620 5681",
    "sg:postcode":"1012 NX",
    "sg:province":"Noord-Holland",
    "wof:name":"Bon Dia",
    "wof:placetype":"venue"
},
  "geometry": {"coordinates":[4.892256,52.372337],"type":"Point"}
}