{
  "type": "Feature",
  "properties": {
    "addr:full":"Ptr Vd Elsenstr 12 S Hertogenbosch North Brabant 5213 CD",
    "addr:housenumber":"12",
    "addr:postcode":"ptr;5213 cd",
    "addr:street":"S Hertogenbosch",
    "iso:country":"NL",
    "sg:address":"Ptr Vd Elsenstr 12",
    "sg:city":"S Hertogenbosch",
    "sg:classifiers":[
        {
            "category":"Professional",
            "subcategory":"Accounting & Tax Preparation",
            "type":"Services"
        }
    ],
    "sg:phone":"+31 73 612 5363",
    "sg:postcode":"5213 CD",
    "sg:province":"North Brabant",
    "sg:tags":[
        "accountant",
        "en",
        "-kantoren",
        "register-"
    ],
    "wof:name":"Verhoeven Bv",
    "wof:placetype":"venue"
},
  "geometry": {"coordinates":[5.328047,51.696323],"type":"Point"}
}