{
  "type": "Feature",
  "properties": {
    "addr:full":"Zuiderwouder Dorpsstraat 15 Zuiderwoude Noord-Holland 1153 PB",
    "addr:housenumber":"15",
    "addr:postcode":"1153 pb",
    "addr:street":"Zuiderwouder Dorpsstraat",
    "iso:country":"NL",
    "sg:address":"Zuiderwouder Dorpsstraat 15",
    "sg:city":"Zuiderwoude",
    "sg:orig_category":"Pleziervaartuigen And Reparatie",
    "sg:phone":"+31 20 403 3763",
    "sg:postcode":"1153 PB",
    "sg:province":"Noord-Holland",
    "wof:name":"G Verstoep Scheepstimmerwerken",
    "wof:placetype":"venue"
},
  "geometry": {"coordinates":[5.035044,52.431885],"type":"Point"}
}