{
  "type": "Feature",
  "properties": {
    "addr:full":"Vossenlaan 5 Bosch En Duin Utrecht 3735 KM",
    "addr:housenumber":"5",
    "addr:postcode":"en duin;3735 km",
    "addr:street":"Vossenlaan",
    "iso:country":"NL",
    "sg:address":"Vossenlaan 5",
    "sg:city":"Bosch En Duin",
    "sg:orig_category":"Verzekeringen",
    "sg:phone":"+31 30 692 4404",
    "sg:postcode":"3735 KM",
    "sg:province":"Utrecht",
    "wof:name":"Hufen Assurantien Bv",
    "wof:placetype":"venue"
},
  "geometry": {"coordinates":[5.23998,52.123264],"type":"Point"}
}