{
  "type": "Feature",
  "properties": {
    "addr:full":"Slootweg 2 Schoonhoven South Holland 2871 RP",
    "addr:housenumber":"2",
    "addr:postcode":"2871 rp",
    "addr:street":"Slootweg",
    "iso:country":"NL",
    "sg:address":"Slootweg 2",
    "sg:city":"Schoonhoven",
    "sg:orig_category":"Loodgieterswerk, Verwarming And Sanitaire Installaties",
    "sg:phone":"+31 182 384 116",
    "sg:postcode":"2871 RP",
    "sg:province":"South Holland",
    "wof:name":"Tuithof Installatietechniek Vof",
    "wof:placetype":"venue"
},
  "geometry": {"coordinates":[4.862842,51.947445],"type":"Point"}
}