{
  "type": "Feature",
  "properties": {
    "addr:full":"Oudestr 2 Neede California 7161 DW",
    "addr:housenumber":"2",
    "addr:postcode":"7161 dw",
    "addr:street":"Oudestr",
    "iso:country":"NL",
    "sg:address":"Oudestr 2",
    "sg:city":"Neede",
    "sg:orig_category":"Kappers",
    "sg:phone":"+31 545 291 682",
    "sg:postcode":"7161 DW",
    "sg:province":"California",
    "wof:name":"Janet",
    "wof:placetype":"venue"
},
  "geometry": {"coordinates":[-121.3170623779,38.2996330261],"type":"Point"}
}