{
  "type": "Feature",
  "properties": {
    "iso:country":"NL",
    "sg:address":"Hassinkweg 19",
    "sg:city":"Hengelo Ov",
    "sg:orig_category":"Technische Studies And Onderzoek",
    "sg:phone":"+31 74 291 5151",
    "sg:postcode":"7556 BV",
    "sg:province":"Overijssel",
    "wof:name":"Proftech Bv",
    "wof:placetype":"venue"
},
  "geometry": {"coordinates":[6.773186,52.280254],"type":"Point"}
}