{
  "type": "Feature",
  "properties": {
    "iso:country":"NL",
    "sg:address":"Bunschotenweg 123",
    "sg:city":"Rotterdam",
    "sg:orig_category":"Werving And Selectie Van Tijdelijk Personeel And Uitzendkantoren",
    "sg:phone":"+31 10 429 2844",
    "sg:postcode":"3089 KB",
    "sg:province":"South Holland",
    "wof:name":"Verwaard Handelsonderneming Bv",
    "wof:placetype":"venue"
},
  "geometry": {"coordinates":[4.4145960808,51.8883323669],"type":"Point"}
}