{
  "type": "Feature",
  "properties": {
    "addr:full":"Gerard Doustraat 1 Amsterdam North Holland 1072 VG",
    "addr:housenumber":"1",
    "addr:postcode":"1072 vg",
    "addr:street":"Gerard Doustraat",
    "iso:country":"NL",
    "sg:address":"Gerard Doustraat 1",
    "sg:city":"Amsterdam",
    "sg:orig_category":"Public Relationbureaus",
    "sg:phone":"+31 20 679 9984",
    "sg:postcode":"1072 VG",
    "sg:province":"North Holland",
    "wof:name":"H.W.G. Leenders",
    "wof:placetype":"venue"
},
  "geometry": {"coordinates":[4.887313,52.355385],"type":"Point"}
}