{
  "type": "Feature",
  "properties": {
    "addr:full":"Postbus 22603 Amsterdam Zuidoost District of Columbia 1100 DC",
    "addr:postcode":"22603;1100",
    "addr:street":"Postbus",
    "iso:country":"NL",
    "sg:address":"Postbus 22603",
    "sg:city":"Amsterdam Zuidoost",
    "sg:classifiers":[
        {
            "category":"Professional",
            "subcategory":"Printing & Photocopies",
            "type":"Services"
        }
    ],
    "sg:phone":"+31 20 642 1987",
    "sg:postcode":"1100 DC",
    "sg:province":"District of Columbia",
    "sg:tags":[
        "printer"
    ],
    "sg:website":"http://www.canoncenteramsterdam.nl",
    "wof:name":"Canon Center",
    "wof:placetype":"venue"
},
  "geometry": {"coordinates":[-77.01458700000001,38.8937],"type":"Point"}
}