{
  "type": "Feature",
  "properties": {
    "iso:country":"NL",
    "sg:address":"Resedastraat 56",
    "sg:city":"Alblasserdam",
    "sg:orig_category":"Loodgieterswerk, Verwarming And Sanitaire Installaties",
    "sg:phone":"+31 78 693 0709",
    "sg:postcode":"2951 BX",
    "sg:province":"Zuid-Holland",
    "wof:name":"T. Penning",
    "wof:placetype":"venue"
},
  "geometry": {"coordinates":[4.660336,51.869877],"type":"Point"}
}