{
  "type": "Feature",
  "properties": {
    "addr:full":"O Voorstr 34 Oud Beyerland South Holland 3262 JE",
    "addr:housenumber":"34",
    "addr:postcode":"3262 je",
    "addr:street":"Oud Beyerland",
    "iso:country":"NL",
    "sg:address":"O Voorstr 34",
    "sg:city":"Oud Beyerland",
    "sg:orig_category":"Warenhuizen",
    "sg:phone":"+31 186 617 877",
    "sg:postcode":"3262 JE",
    "sg:province":"South Holland",
    "wof:name":"Hema",
    "wof:placetype":"venue"
},
  "geometry": {"coordinates":[4.4170098305,51.8230438232],"type":"Point"}
}