{
  "type": "Feature",
  "properties": {
    "iso:country":"NL",
    "sg:address":"Waterlandln 50 Fil",
    "sg:city":"Purmerend",
    "sg:orig_category":"Bibliotheken En Leeszalen Openbare",
    "sg:phone":"+31 299 433 323",
    "sg:postcode":"1441 MP",
    "sg:province":"Noord-Holland",
    "sg:website":"http://www.hollandnet.nl",
    "wof:name":"Openb Bibliotheek",
    "wof:placetype":"venue"
},
  "geometry": {"coordinates":[4.94793,52.507607],"type":"Point"}
}