{
  "type": "Feature",
  "properties": {
    "addr:full":"Schoolstr 14 Koewacht Zeeland 4576 AB",
    "addr:housenumber":"14",
    "addr:postcode":"4576 ab",
    "addr:street":"Schoolstr",
    "iso:country":"NL",
    "sg:address":"Schoolstr 14",
    "sg:city":"Koewacht",
    "sg:orig_category":"Kappers",
    "sg:phone":"+31 114 361 274",
    "sg:postcode":"4576 AB",
    "sg:province":"Zeeland",
    "wof:name":"Vermeulen, Karolien",
    "wof:placetype":"venue"
},
  "geometry": {"coordinates":[3.975756,51.225967],"type":"Point"}
}