{
  "type": "Feature",
  "properties": {
    "iso:country":"NL",
    "sg:address":"Heulweg 15",
    "sg:city":"Rijswijk Zh",
    "sg:orig_category":"Chemische Producten Gh",
    "sg:phone":"+31 15 219 0011",
    "sg:postcode":"2288 GP",
    "sg:province":"Zuid-Holland",
    "wof:name":"Perspect Nederland Bv",
    "wof:placetype":"venue"
},
  "geometry": {"coordinates":[4.337394,52.029884],"type":"Point"}
}