{
  "type": "Feature",
  "properties": {
    "addr:full":"Nijverheidsstraat 11 Noordwolde Fr Friesland 8391 AH",
    "addr:housenumber":"11",
    "addr:postcode":"8391 ah",
    "addr:street":"Nijverheidsstraat",
    "iso:country":"NL",
    "sg:address":"Nijverheidsstraat 11",
    "sg:city":"Noordwolde Fr",
    "sg:orig_category":"Hout Gh",
    "sg:phone":"+31 561 432 606",
    "sg:postcode":"8391 AH",
    "sg:province":"Friesland",
    "wof:name":"Handelsonderneming Wi-Ot",
    "wof:placetype":"venue"
},
  "geometry": {"coordinates":[6.140317,52.893864],"type":"Point"}
}