{
  "type": "Feature",
  "properties": {
    "iso:country":"NL",
    "sg:address":"Wegedoornpage 1",
    "sg:city":"Breda",
    "sg:orig_category":"Scholen Voor Basisonderwijs",
    "sg:phone":"+31 76 521 6105",
    "sg:postcode":"4814 TZ",
    "sg:province":"North Brabant",
    "wof:name":"Boomgaard, De",
    "wof:placetype":"venue"
},
  "geometry": {"coordinates":[4.748977,51.588779],"type":"Point"}
}