{
  "type": "Feature",
  "properties": {
    "addr:full":"Arnhemsebovenwg 28 Driebergen Rysenb Utrecht 3971 MK",
    "addr:housenumber":"28",
    "addr:postcode":"3971",
    "addr:street":"Arnhemsebovenwg;Rysenb",
    "iso:country":"NL",
    "sg:address":"Arnhemsebovenwg 28",
    "sg:city":"Driebergen Rysenb",
    "sg:orig_category":"Administratie- En Boekhoudkantoren",
    "sg:phone":"+31 343 518 219",
    "sg:postcode":"3971 MK",
    "sg:province":"Utrecht",
    "wof:name":"Bleijenberg Administratie- En Adviesburo",
    "wof:placetype":"venue"
},
  "geometry": {"coordinates":[5.292316,52.058109],"type":"Point"}
}