{
  "type": "Feature",
  "properties": {
    "addr:full":"Herengr 66 Amsterdam Noord-Holland 1015 BR",
    "addr:housenumber":"66",
    "addr:postcode":"1015 br",
    "addr:street":"Herengr",
    "iso:country":"NL",
    "sg:address":"Herengr 66",
    "sg:city":"Amsterdam",
    "sg:classifiers":[
        {
            "category":"Professional",
            "subcategory":"Management & Consulting",
            "type":"Services"
        }
    ],
    "sg:phone":"+31 20 421 4781",
    "sg:postcode":"1015 BR",
    "sg:province":"Noord-Holland",
    "sg:tags":[
        "relation",
        "adviesbureaus",
        "public"
    ],
    "wof:name":"Pkd",
    "wof:placetype":"venue"
},
  "geometry": {"coordinates":[4.889917,52.377537],"type":"Point"}
}