{
  "type": "Feature",
  "properties": {
    "addr:full":"De Horsterkamp 8 Vorden Gelderland 7251 AZ",
    "addr:housenumber":"8",
    "addr:postcode":"7251",
    "addr:street":"De Horsterkamp;Gelderland",
    "iso:country":"NL",
    "sg:address":"De Horsterkamp 8",
    "sg:city":"Vorden",
    "sg:orig_category":"Overheidsdiensten",
    "sg:phone":"+31 575 557 474",
    "sg:postcode":"7251 AZ",
    "sg:province":"Gelderland",
    "wof:name":"Gemeente Vorden",
    "wof:placetype":"venue"
},
  "geometry": {"coordinates":[6.3222107887,52.1010017395],"type":"Point"}
}