{
  "type": "Feature",
  "properties": {
    "addr:full":"Kon Wilhelminakd 265 Ymuiden Noord-Holland 1975 GL",
    "addr:housenumber":"265",
    "addr:postcode":"1975 gl",
    "addr:street":"Kon;Ymuiden Noord-Holland",
    "iso:country":"NL",
    "sg:address":"Kon Wilhelminakd 265",
    "sg:city":"Ymuiden",
    "sg:orig_category":"Zalenverhuur",
    "sg:phone":"+31 255 510 919",
    "sg:postcode":"1975 GL",
    "sg:province":"Noord-Holland",
    "wof:name":"Rank, De",
    "wof:placetype":"venue"
},
  "geometry": {"coordinates":[4.604136,52.462654],"type":"Point"}
}