{
  "type": "Feature",
  "properties": {
    "addr:full":"Dorpsstraat 13 Gapinge Zeeland 4352 AA",
    "addr:housenumber":"13",
    "addr:postcode":"4352 aa",
    "addr:street":"Dorpsstraat",
    "iso:country":"NL",
    "sg:address":"Dorpsstraat 13",
    "sg:city":"Gapinge",
    "sg:orig_category":"Levende Dieren Gh",
    "sg:phone":"+31 118 591 740",
    "sg:postcode":"4352 AA",
    "sg:province":"Zeeland",
    "wof:name":"A H S Commelin",
    "wof:placetype":"venue"
},
  "geometry": {"coordinates":[3.627094,51.544682],"type":"Point"}
}