{
  "type": "Feature",
  "properties": {
    "iso:country":"NL",
    "sg:address":"Oude Beekbergerwg 168",
    "sg:city":"Apeldoorn",
    "sg:orig_category":"Waterbehandeling En Waterzuiverings- Systemen",
    "sg:phone":"+31 55 533 3115",
    "sg:postcode":"7333 AJ",
    "sg:province":"Gelderland",
    "wof:name":"Water Techniek Nederland",
    "wof:placetype":"venue"
},
  "geometry": {"coordinates":[5.9697871208,52.1924819946],"type":"Point"}
}