{
  "type": "Feature",
  "properties": {
    "addr:full":"Willinkplein 30 Emmen Provincie Drenthe 7811 DD",
    "addr:housenumber":"30",
    "addr:postcode":"7811 dd",
    "addr:street":"Willinkplein;Provincie Drenthe",
    "iso:country":"NL",
    "sg:address":"Willinkplein 30",
    "sg:city":"Emmen",
    "sg:classifiers":[
        {
            "category":"Retail",
            "subcategory":"Photofinishing",
            "type":"Services"
        }
    ],
    "sg:phone":"+31 591 616 610",
    "sg:postcode":"7811 DD",
    "sg:province":"Provincie Drenthe",
    "sg:tags":[
        "foto",
        "film"
    ],
    "wof:name":"Fotox",
    "wof:placetype":"venue"
},
  "geometry": {"coordinates":[6.893085,52.781406],"type":"Point"}
}