{
  "type": "Feature",
  "properties": {
    "iso:country":"NL",
    "sg:address":"Ln V Het Kwekebos 358-360",
    "sg:city":"Emmen",
    "sg:orig_category":"Manueel Therapeuten",
    "sg:phone":"+31 591 622 967",
    "sg:postcode":"7823 LP",
    "sg:province":"Provincie Drenthe",
    "wof:name":"Kloosterman, J R",
    "wof:placetype":"venue"
},
  "geometry": {"coordinates":[6.945142,52.796509],"type":"Point"}
}