{
  "type": "Feature",
  "properties": {
    "addr:full":"Dorpsveld 8 Berlicum Nb Noord-Brabant 5258 MB",
    "addr:housenumber":"8",
    "addr:postcode":"5258 mb",
    "addr:street":"Dorpsveld",
    "iso:country":"NL",
    "sg:address":"Dorpsveld 8",
    "sg:city":"Berlicum Nb",
    "sg:orig_category":"Metselwerken",
    "sg:phone":"+31 73 503 1337",
    "sg:postcode":"5258 MB",
    "sg:province":"Noord-Brabant",
    "wof:name":"Aa & Van De Laar, Van Der",
    "wof:placetype":"venue"
},
  "geometry": {"coordinates":[5.396638,51.675537],"type":"Point"}
}