{
  "type": "Feature",
  "properties": {
    "addr:full":"Terschellingkd 9 Woerden Utrecht 3446 BK",
    "addr:housenumber":"9",
    "addr:postcode":"3446 bk",
    "addr:street":"Terschellingkd",
    "iso:country":"NL",
    "sg:address":"Terschellingkd 9",
    "sg:city":"Woerden",
    "sg:orig_category":"Logopedisten",
    "sg:phone":"+31 348 434 627",
    "sg:postcode":"3446 BK",
    "sg:province":"Utrecht",
    "wof:name":"Logopedisten Maatschap Woerden",
    "wof:placetype":"venue"
},
  "geometry": {"coordinates":[4.903562,52.084549],"type":"Point"}
}