{
  "type": "Feature",
  "properties": {
    "addr:full":"Noordzyde 123 Gasselternyv Mond Drenthe 9515 PD",
    "addr:housenumber":"123",
    "addr:postcode":"9515 pd",
    "addr:street":"Gasselternyv Mond",
    "iso:country":"NL",
    "sg:address":"Noordzyde 123",
    "sg:city":"Gasselternyv Mond",
    "sg:orig_category":"Kampeerartikelen",
    "sg:phone":"+31 599 613 946",
    "sg:postcode":"9515 PD",
    "sg:province":"Drenthe",
    "sg:website":"http://www.tevelde.nl",
    "wof:name":"Velde, Tentenmakerij & Campingshop",
    "wof:placetype":"venue"
},
  "geometry": {"coordinates":[-108.9166107178,32.2604904175],"type":"Point"}
}