{
  "type": "Feature",
  "properties": {
    "addr:full":"De Drift 1A Drachten Friesland 9203 GG",
    "addr:housenumber":"1a",
    "addr:postcode":"9203 gg",
    "addr:street":"De Drift",
    "iso:country":"NL",
    "sg:address":"De Drift 1A",
    "sg:city":"Drachten",
    "sg:orig_category":"Adviesbureaus",
    "sg:phone":"+31 512 549 905",
    "sg:postcode":"9203 GG",
    "sg:province":"Friesland",
    "wof:name":"Time Bv",
    "wof:placetype":"venue"
},
  "geometry": {"coordinates":[6.10109,53.104771],"type":"Point"}
}