{
  "type": "Feature",
  "properties": {
    "addr:full":"Veenwal 15B Hoevelaken Gelderland 3871 KE",
    "addr:housenumber":"15b",
    "addr:postcode":"3871 ke",
    "addr:street":"Veenwal;Gelderland",
    "iso:country":"NL",
    "sg:address":"Veenwal 15B",
    "sg:city":"Hoevelaken",
    "sg:orig_category":"Letselschadespecialisten",
    "sg:phone":"+31 33 253 7200",
    "sg:postcode":"3871 KE",
    "sg:province":"Gelderland",
    "sg:website":"http://www.kloppenburgbv.nl",
    "wof:name":"Kloppenburg Bv",
    "wof:placetype":"venue"
},
  "geometry": {"coordinates":[5.460189,52.177254],"type":"Point"}
}