{
  "type": "Feature",
  "properties": {
    "addr:full":"Julianastr 30 Wissenkerke Zeeland 4491 GB",
    "addr:housenumber":"30",
    "addr:postcode":"4491 gb",
    "addr:street":"Julianastr",
    "iso:country":"NL",
    "sg:address":"Julianastr 30",
    "sg:city":"Wissenkerke",
    "sg:orig_category":"Scholen Voor Basisonderwijs",
    "sg:phone":"+31 113 371 463",
    "sg:postcode":"4491 GB",
    "sg:province":"Zeeland",
    "wof:name":"Vliete Openb, De",
    "wof:placetype":"venue"
},
  "geometry": {"coordinates":[3.745503,51.583538],"type":"Point"}
}