{
  "type": "Feature",
  "properties": {
    "addr:full":"Delflandplein 20 Amsterdam Noord-Holland 1062 HR",
    "addr:housenumber":"20",
    "addr:postcode":"1062 hr",
    "addr:street":"Delflandplein",
    "iso:country":"NL",
    "sg:address":"Delflandplein 20",
    "sg:city":"Amsterdam",
    "sg:orig_category":"Wasserettes And Stomerijen",
    "sg:phone":"+31 20 614 0671",
    "sg:postcode":"1062 HR",
    "sg:province":"Noord-Holland",
    "wof:name":"Quality Service",
    "wof:placetype":"venue"
},
  "geometry": {"coordinates":[4.8402409554,52.3497886658],"type":"Point"}
}