{
  "type": "Feature",
  "properties": {
    "addr:full":"Postbus 241 Veenendaal Utrecht 3900 AE",
    "addr:housenumber":"241",
    "addr:postcode":"3900 ae",
    "addr:street":"Postbus",
    "iso:country":"NL",
    "sg:address":"Postbus 241",
    "sg:city":"Veenendaal",
    "sg:orig_category":"Metaalbekleding And -Behandeling",
    "sg:phone":"+31 318 557 611",
    "sg:postcode":"3900 AE",
    "sg:province":"Utrecht",
    "wof:name":"Dmg Benelux Bv",
    "wof:placetype":"venue"
},
  "geometry": {"coordinates":[5.55418,52.024902],"type":"Point"}
}