{
  "type": "Feature",
  "properties": {
    "addr:full":"Meenthof 16 Kortenhoef Noord-Holland 1241 CP",
    "addr:housenumber":"16",
    "addr:postcode":"1241 cp",
    "addr:street":"Meenthof",
    "iso:country":"NL",
    "sg:address":"Meenthof 16",
    "sg:city":"Kortenhoef",
    "sg:orig_category":"Verloskundigen",
    "sg:phone":"+31 35 656 1613",
    "sg:postcode":"1241 CP",
    "sg:province":"Noord-Holland",
    "wof:name":"Verloskundigenprakt 'S-Graveland-Kortenhoef-Vreeland",
    "wof:placetype":"venue"
},
  "geometry": {"coordinates":[5.112409,52.239941],"type":"Point"}
}