{
  "type": "Feature",
  "properties": {
    "addr:full":"Wilmersdorf 44A Apeldoorn Gelderland 7327 AC",
    "addr:housenumber":"44a",
    "addr:postcode":"7327 ac",
    "addr:street":"Wilmersdorf;Gelderland",
    "iso:country":"NL",
    "sg:address":"Wilmersdorf 44A",
    "sg:city":"Apeldoorn",
    "sg:orig_category":"Bedrijfskleding",
    "sg:phone":"+31 55 599 9860",
    "sg:postcode":"7327 AC",
    "sg:province":"Gelderland",
    "sg:website":"http://www.snickers-workwear.nl",
    "wof:name":"Snickers Original Bv",
    "wof:placetype":"venue"
},
  "geometry": {"coordinates":[5.99154,52.185398],"type":"Point"}
}