{
  "type": "Feature",
  "properties": {
    "addr:full":"Dorpsstraat 51 Maasdam Zuid-Holland 3299 BB",
    "addr:housenumber":"51",
    "addr:postcode":"3299 bb",
    "addr:street":"Dorpsstraat",
    "iso:country":"NL",
    "sg:address":"Dorpsstraat 51",
    "sg:city":"Maasdam",
    "sg:orig_category":"Wasserettes And Stomerijen",
    "sg:phone":"+31 78 676 4024",
    "sg:postcode":"3299 BB",
    "sg:province":"Zuid-Holland",
    "wof:name":"Van Alphen Stomerijen",
    "wof:placetype":"venue"
},
  "geometry": {"coordinates":[4.5570511818,51.7835159302],"type":"Point"}
}