{
  "type": "Feature",
  "properties": {
    "addr:full":"Vogelplein 2 'S Hertogenbosch North Brabant 5212 VK",
    "addr:housenumber":"2 ' s",
    "addr:postcode":"5212 vk",
    "addr:street":"Vogelplein;Hertogenbosch",
    "iso:country":"NL",
    "sg:address":"Vogelplein 2",
    "sg:city":"'S Hertogenbosch",
    "sg:orig_category":"Pleziervaartuigen And Reparatie",
    "sg:phone":"+31 73 613 2030",
    "sg:postcode":"5212 VK",
    "sg:province":"North Brabant",
    "wof:name":"Gebr. Beekmans Roestvaststaal Bv",
    "wof:placetype":"venue"
},
  "geometry": {"coordinates":[5.29901,51.699085],"type":"Point"}
}