{
  "type": "Feature",
  "properties": {
    "iso:country":"NL",
    "sg:address":"Doelenstr 5",
    "sg:city":"Schoonhoven",
    "sg:orig_category":"Bloemen En Planten",
    "sg:phone":"+31 182 382 608",
    "sg:postcode":"2871 CW",
    "sg:province":"South Holland",
    "wof:name":"Marianne",
    "wof:placetype":"venue"
},
  "geometry": {"coordinates":[4.852982,51.946804],"type":"Point"}
}