{
  "type": "Feature",
  "properties": {
    "addr:full":"Lijsterbesstraat 2 Enkhuizen Noord-Holland 1602 SE",
    "addr:housenumber":"2;1602",
    "addr:street":"Lijsterbesstraat;Se",
    "iso:country":"NL",
    "sg:address":"Lijsterbesstraat 2",
    "sg:city":"Enkhuizen",
    "sg:orig_category":"Bejaardeninstellingen And Serviceflats",
    "sg:phone":"+31 228 313 144",
    "sg:postcode":"1602 SE",
    "sg:province":"Noord-Holland",
    "wof:name":"De Omring Overvest",
    "wof:placetype":"venue"
},
  "geometry": {"coordinates":[5.279792,52.708534],"type":"Point"}
}