{
  "type": "Feature",
  "properties": {
    "addr:full":"St Jacobsstr 12 Utrecht Utrecht 3511 BS",
    "addr:housenumber":"12",
    "addr:postcode":"3511 bs",
    "iso:country":"NL",
    "sg:address":"St Jacobsstr 12",
    "sg:city":"Utrecht",
    "sg:orig_category":"Woninginrichting",
    "sg:phone":"+31 30 234 0201",
    "sg:postcode":"3511 BS",
    "sg:province":"Utrecht",
    "wof:name":"Koot",
    "wof:placetype":"venue"
},
  "geometry": {"coordinates":[5.1143388748,52.09425354],"type":"Point"}
}