{
  "type": "Feature",
  "properties": {
    "addr:full":"Smidstr 27 Rynsburg Zuid-Holland 2231 EK",
    "addr:housenumber":"27",
    "addr:postcode":"2231 ek",
    "addr:street":"Smidstr",
    "iso:country":"NL",
    "sg:address":"Smidstr 27",
    "sg:city":"Rynsburg",
    "sg:orig_category":"Scholen Voor Basisonderwijs",
    "sg:phone":"+31 71 408 2869",
    "sg:postcode":"2231 EK",
    "sg:province":"Zuid-Holland",
    "wof:name":"Emma, Kon",
    "wof:placetype":"venue"
},
  "geometry": {"coordinates":[4.446897,52.190098],"type":"Point"}
}