{
  "type": "Feature",
  "properties": {
    "addr:full":"Brouwketel 1 Huissen Gelderland 6851 ZX",
    "addr:housenumber":"1",
    "addr:postcode":"6851 zx",
    "addr:street":"Brouwketel;Gelderland",
    "iso:country":"NL",
    "sg:address":"Brouwketel 1",
    "sg:city":"Huissen",
    "sg:orig_category":"Loodgieterswerk, Verwarming And Sanitaire Installaties",
    "sg:phone":"+31 26 325 5005",
    "sg:postcode":"6851 ZX",
    "sg:province":"Gelderland",
    "wof:name":"Th.A.P. Hubers",
    "wof:placetype":"venue"
},
  "geometry": {"coordinates":[5.967681,51.923313],"type":"Point"}
}