{
  "type": "Feature",
  "properties": {
    "addr:full":"Amsterdamseweg 421 Amstelveen North Holland 1181 BP",
    "addr:housenumber":"421",
    "addr:postcode":"1181 bp",
    "addr:street":"Amsterdamseweg",
    "iso:country":"NL",
    "sg:address":"Amsterdamseweg 421",
    "sg:city":"Amstelveen",
    "sg:orig_category":"Banken And Kredietinstellingen",
    "sg:phone":"+31 20 643 1378",
    "sg:postcode":"1181 BP",
    "sg:province":"North Holland",
    "wof:name":"Abn Amro",
    "wof:placetype":"venue"
},
  "geometry": {"coordinates":[4.856613,52.315628],"type":"Point"}
}