{
  "type": "Feature",
  "properties": {
    "addr:full":"Beitelstr 8A Hengelo Ov Overijssel 7556 NB",
    "addr:housenumber":"8a",
    "addr:postcode":"7556 nb",
    "addr:street":"Beitelstr;Ov",
    "iso:country":"NL",
    "sg:address":"Beitelstr 8A",
    "sg:city":"Hengelo Ov",
    "sg:orig_category":"Projectinrichting",
    "sg:phone":"+31 74 243 1769",
    "sg:postcode":"7556 NB",
    "sg:province":"Overijssel",
    "wof:name":"Eerde, P Van",
    "wof:placetype":"venue"
},
  "geometry": {"coordinates":[6.809053,52.280857],"type":"Point"}
}