{
  "type": "Feature",
  "properties": {
    "addr:full":"Hengelosewg 4 Zelhem Gelderland 7021 ZT",
    "addr:housenumber":"4",
    "addr:postcode":"7021 zt",
    "addr:street":"Hengelosewg;Gelderland",
    "iso:country":"NL",
    "sg:address":"Hengelosewg 4",
    "sg:city":"Zelhem",
    "sg:orig_category":"Hypotheken",
    "sg:phone":"+31 314 620 956",
    "sg:postcode":"7021 ZT",
    "sg:province":"Gelderland",
    "sg:website":"http://www.hypotheekadvieszelhem.nl",
    "wof:name":"Hypotheek Adviesbureau Zelhem Bv",
    "wof:placetype":"venue"
},
  "geometry": {"coordinates":[6.294927,52.003761],"type":"Point"}
}