{
  "type": "Feature",
  "properties": {
    "addr:full":"Dobbeweg 30 Voorschoten Zuid-Holland 2254 AG",
    "addr:housenumber":"30",
    "addr:postcode":"2254",
    "addr:street":"Dobbeweg",
    "iso:country":"NL",
    "sg:address":"Dobbeweg 30",
    "sg:city":"Voorschoten",
    "sg:orig_category":"Verhuisdiensten",
    "sg:phone":"+31 800 0242222",
    "sg:postcode":"2254 AG",
    "sg:province":"Zuid-Holland",
    "wof:name":"Internationaal Meubeltransport H. Tipker Bv",
    "wof:placetype":"venue"
},
  "geometry": {"coordinates":[4.434578,52.129837],"type":"Point"}
}