{
  "type": "Feature",
  "properties": {
    "iso:country":"NL",
    "sg:address":"Pollux 35",
    "sg:city":"Hoogeveen",
    "sg:orig_category":"Gehandicapteninformatie",
    "sg:phone":"+31 528 278 029",
    "sg:postcode":"7904 KM",
    "sg:province":"Drenthe",
    "wof:name":"Pollux, De",
    "wof:placetype":"venue"
},
  "geometry": {"coordinates":[6.518273,52.726158],"type":"Point"}
}