{
  "type": "Feature",
  "properties": {
    "addr:full":"Sportlaan 7 Marum Groningen 9363 GM",
    "addr:housenumber":"7",
    "addr:postcode":"9363 gm",
    "addr:street":"Sportlaan",
    "iso:country":"NL",
    "sg:address":"Sportlaan 7",
    "sg:city":"Marum",
    "sg:orig_category":"Diverse Grafische Activiteiten",
    "sg:phone":"+31 594 643 619",
    "sg:postcode":"9363 GM",
    "sg:province":"Groningen",
    "wof:name":"Idk Buro Voor Grafische Vormgeving",
    "wof:placetype":"venue"
},
  "geometry": {"coordinates":[6.2568,53.144321],"type":"Point"}
}