{
  "type": "Feature",
  "properties": {
    "iso:country":"NL",
    "sg:address":"Oostwoud Dorpsstr 48",
    "sg:city":"Oostwoud",
    "sg:orig_category":"Adviesbureaus Bouwkosten",
    "sg:phone":"+31 229 201 509",
    "sg:postcode":"1678 HG",
    "sg:province":"Noord-Holland",
    "sg:website":"http://www.laan-bka.nl",
    "wof:name":"Laan, T M",
    "wof:placetype":"venue"
},
  "geometry": {"coordinates":[5.083525,52.724773],"type":"Point"}
}