{
  "type": "Feature",
  "properties": {
    "addr:full":"St Walburgispln 45 Arnhem Gelderland 6811 BZ",
    "addr:housenumber":"45",
    "addr:postcode":"6811 bz",
    "iso:country":"NL",
    "sg:address":"St Walburgispln 45",
    "sg:city":"Arnhem",
    "sg:orig_category":"Verenigingsgebouwen",
    "sg:phone":"+31 26 443 2819",
    "sg:postcode":"6811 BZ",
    "sg:province":"Gelderland",
    "wof:name":"Walburg",
    "wof:placetype":"venue"
},
  "geometry": {"coordinates":[5.912737,51.978981],"type":"Point"}
}