{
  "type": "Feature",
  "properties": {
    "addr:full":"Breusterstraat 45 Eijsden Limburg 6245 EH",
    "addr:housenumber":"45",
    "addr:postcode":"6245 eh",
    "addr:street":"Breusterstraat",
    "iso:country":"NL",
    "sg:address":"Breusterstraat 45",
    "sg:city":"Eijsden",
    "sg:orig_category":"Banken And Kredietinstellingen",
    "sg:phone":"+31 43 409 7100",
    "sg:postcode":"6245 EH",
    "sg:province":"Limburg",
    "wof:name":"Rabobank",
    "wof:placetype":"venue"
},
  "geometry": {"coordinates":[5.709597,50.777523],"type":"Point"}
}