{
  "type": "Feature",
  "properties": {
    "addr:full":"Markeweg 9 Valthermond Provincie Drenthe 7876 TJ",
    "addr:housenumber":"9",
    "addr:postcode":"7876 tj",
    "addr:street":"Markeweg;Provincie Drenthe",
    "iso:country":"NL",
    "sg:address":"Markeweg 9",
    "sg:city":"Valthermond",
    "sg:orig_category":"Pluimveehouderijen",
    "sg:phone":"+31 599 417 738",
    "sg:postcode":"7876 TJ",
    "sg:province":"Provincie Drenthe",
    "wof:name":"J. Jongbloed",
    "wof:placetype":"venue"
},
  "geometry": {"coordinates":[7.011861,52.905956],"type":"Point"}
}