{
  "type": "Feature",
  "properties": {
    "addr:full":"Vrouwe Huisjeswg 1 Mynsheerenland Zuid-Holland 3271 LX",
    "addr:housenumber":"1",
    "addr:postcode":"3271 lx",
    "addr:street":"Vrouwe Huisjeswg",
    "iso:country":"NL",
    "sg:address":"Vrouwe Huisjeswg 1",
    "sg:city":"Mynsheerenland",
    "sg:orig_category":"Hondenscholen",
    "sg:phone":"+31 78 676 4357",
    "sg:postcode":"3271 LX",
    "sg:province":"Zuid-Holland",
    "wof:name":"Hoeksche Waard, Kynologencl",
    "wof:placetype":"venue"
},
  "geometry": {"coordinates":[4.517112,51.801476],"type":"Point"}
}