{
  "type": "Feature",
  "properties": {
    "addr:full":"Johan Frisostraat 2 Sint Oedenrode Noord-Brabant 5491 HX",
    "addr:housenumber":"2;oedenrode",
    "addr:postcode":"5491 hx",
    "addr:street":"Johan Frisostraat",
    "iso:country":"NL",
    "sg:address":"Johan Frisostraat 2",
    "sg:city":"Sint Oedenrode",
    "sg:orig_category":"Glaszetten",
    "sg:phone":"+31 413 476 293",
    "sg:postcode":"5491 HX",
    "sg:province":"Noord-Brabant",
    "wof:name":"Glaszettersbedrijf Harrie Van Erp Vof",
    "wof:placetype":"venue"
},
  "geometry": {"coordinates":[5.455847,51.571793],"type":"Point"}
}