{
  "type": "Feature",
  "properties": {
    "addr:full":"C V Maarssenpln 8 Diemen Noord-Holland 1111 JE",
    "addr:housenumber":"8",
    "addr:postcode":"1111 je",
    "addr:street":"V Maarssenpln",
    "iso:country":"NL",
    "sg:address":"C V Maarssenpln 8",
    "sg:city":"Diemen",
    "sg:orig_category":"Huishoudelijke Apparaten En Artikelen",
    "sg:phone":"+31 20 416 0867",
    "sg:postcode":"1111 JE",
    "sg:province":"Noord-Holland",
    "wof:name":"Blokker Bv",
    "wof:placetype":"venue"
},
  "geometry": {"coordinates":[4.964805,52.34132],"type":"Point"}
}