{
  "type": "Feature",
  "properties": {
    "addr:full":"Hoogte Kadk 108R Amsterdam North Holland 1018 BS",
    "addr:housenumber":"108r",
    "addr:postcode":"1018 bs",
    "addr:street":"Hoogte Kadk",
    "iso:country":"NL",
    "sg:address":"Hoogte Kadk 108R",
    "sg:city":"Amsterdam",
    "sg:orig_category":"Adviesbureaus Bedrijfsorganisatie",
    "sg:phone":"+31 20 627 2812",
    "sg:postcode":"1018 BS",
    "sg:province":"North Holland",
    "wof:name":"Marco Luirink",
    "wof:placetype":"venue"
},
  "geometry": {"coordinates":[4.915891,52.368988],"type":"Point"}
}