{
  "type": "Feature",
  "properties": {
    "addr:full":"St Josephstr 65 Bergen Op Zoom North Brabant 4611 MK",
    "addr:housenumber":"65",
    "addr:postcode":"4611",
    "iso:country":"NL",
    "sg:address":"St Josephstr 65",
    "sg:city":"Bergen Op Zoom",
    "sg:orig_category":"Vakorganisaties",
    "sg:phone":"+31 164 264 000",
    "sg:postcode":"4611 MK",
    "sg:province":"North Brabant",
    "sg:website":"http://www.fnv.nl/",
    "wof:name":"Fnv",
    "wof:placetype":"venue"
},
  "geometry": {"coordinates":[4.29057,51.49332],"type":"Point"}
}