{
  "type": "Feature",
  "properties": {
    "iso:country":"NL",
    "sg:address":"Kruiswg 15",
    "sg:city":"Utrecht",
    "sg:orig_category":"Hulpverlening Sociaal",
    "sg:phone":"+31 30 223 2033",
    "sg:postcode":"3513 CS",
    "sg:province":"Utrecht",
    "wof:name":"Vervolghuis Psychiatrie",
    "wof:placetype":"venue"
},
  "geometry": {"coordinates":[5.109453,52.097542],"type":"Point"}
}