{
  "type": "Feature",
  "properties": {
    "addr:full":"Kerkstr 149 Weert Limburg 6006 KM",
    "addr:housenumber":"149",
    "addr:street":"Weert Limburg 6006 Km",
    "iso:country":"NL",
    "sg:address":"Kerkstr 149",
    "sg:city":"Weert",
    "sg:orig_category":"Binnenhuisarchitectuur",
    "sg:phone":"+31 495 540 511",
    "sg:postcode":"6006 KM",
    "sg:province":"Limburg",
    "wof:name":"Rademakers, Interieurontwerp",
    "wof:placetype":"venue"
},
  "geometry": {"coordinates":[5.703781,51.255016],"type":"Point"}
}