{
  "type": "Feature",
  "properties": {
    "addr:full":"Ranonkel 2 Barendrecht Zuid-Holland 2992 VS",
    "addr:housenumber":"2",
    "addr:postcode":"2992 vs",
    "addr:street":"Ranonkel",
    "iso:country":"NL",
    "sg:address":"Ranonkel 2",
    "sg:city":"Barendrecht",
    "sg:orig_category":"Verzekeringen",
    "sg:phone":"+31 180 611 206",
    "sg:postcode":"2992 VS",
    "sg:province":"Zuid-Holland",
    "wof:name":"M.N.A. Assurantien",
    "wof:placetype":"venue"
},
  "geometry": {"coordinates":[4.531564,51.853729],"type":"Point"}
}