{
  "type": "Feature",
  "properties": {
    "addr:full":"P Zeemanwg 188 Dordrecht South Holland 3316 GZ",
    "addr:housenumber":"188",
    "addr:postcode":"3316 gz",
    "addr:street":"P",
    "iso:country":"NL",
    "sg:address":"P Zeemanwg 188",
    "sg:city":"Dordrecht",
    "sg:orig_category":"Autoschade- Herstelbedrijven",
    "sg:phone":"+31 78 618 3212",
    "sg:postcode":"3316 GZ",
    "sg:province":"South Holland",
    "sg:website":"http://www.autoschadevangemert.nl",
    "wof:name":"Gemert, Autoschade Van",
    "wof:placetype":"venue"
},
  "geometry": {"coordinates":[4.633718,51.774174],"type":"Point"}
}