{
  "type": "Feature",
  "properties": {
    "addr:full":"Oosterwoldseweg 2 Oldeberkoop Pennsylvania 8421 PA",
    "addr:housenumber":"2",
    "addr:postcode":"8421 pa",
    "addr:street":"Oosterwoldseweg",
    "iso:country":"NL",
    "sg:address":"Oosterwoldseweg 2",
    "sg:city":"Oldeberkoop",
    "sg:orig_category":"Verzekeringen",
    "sg:phone":"+31 516 451 379",
    "sg:postcode":"8421 PA",
    "sg:province":"Pennsylvania",
    "wof:name":"Brouwer'S Assurantiekantoor",
    "wof:placetype":"venue"
},
  "geometry": {"coordinates":[-77.604507,40.99464],"type":"Point"}
}