{
  "type": "Feature",
  "properties": {
    "addr:full":"Oerseweg 19 Ulft Gelderland 7071 PP",
    "addr:housenumber":"19",
    "addr:postcode":"7071 pp",
    "addr:street":"Oerseweg;Gelderland",
    "iso:country":"NL",
    "sg:address":"Oerseweg 19",
    "sg:city":"Ulft",
    "sg:orig_category":"Autokeuringen",
    "sg:phone":"+31 315 684 141",
    "sg:postcode":"7071 PP",
    "sg:province":"Gelderland",
    "wof:name":"Vtk Autoschade En Autoreparatie",
    "wof:placetype":"venue"
},
  "geometry": {"coordinates":[6.367849,51.901165],"type":"Point"}
}