{
  "type": "Feature",
  "properties": {
    "addr:full":"Hoofdwg 129 Zegveld Utrecht 3474 JC",
    "addr:housenumber":"129",
    "addr:postcode":"3474 jc",
    "addr:street":"Zegveld",
    "iso:country":"NL",
    "sg:address":"Hoofdwg 129",
    "sg:city":"Zegveld",
    "sg:orig_category":"Betonijzervlechten",
    "sg:phone":"+31 348 691 377",
    "sg:postcode":"3474 JC",
    "sg:province":"Utrecht",
    "wof:name":"Mutalis",
    "wof:placetype":"venue"
},
  "geometry": {"coordinates":[4.843788,52.110214],"type":"Point"}
}