{
  "type": "Feature",
  "properties": {
    "iso:country":"NL",
    "sg:address":"Havenweg 16",
    "sg:city":"Nieuwdorp Zld",
    "sg:orig_category":"Artsen And Specialisten",
    "sg:phone":"+31 113 612 327",
    "sg:postcode":"4455 AP",
    "sg:province":"Zeeland",
    "wof:name":"Huisartsenpraktijk",
    "wof:placetype":"venue"
},
  "geometry": {"coordinates":[3.736954,51.47102],"type":"Point"}
}