{
  "type": "Feature",
  "properties": {
    "addr:full":"Regentesseln 5 Baarn Utrecht 3744 MB",
    "addr:housenumber":"5",
    "addr:postcode":"3744 mb",
    "addr:street":"Regentesseln",
    "iso:country":"NL",
    "sg:address":"Regentesseln 5",
    "sg:city":"Baarn",
    "sg:orig_category":"Accountants - Administratie- Consulenten En -Kantoren",
    "sg:phone":"+31 35 543 0434",
    "sg:postcode":"3744 MB",
    "sg:province":"Utrecht",
    "wof:name":"Msas Bv",
    "wof:placetype":"venue"
},
  "geometry": {"coordinates":[5.267246,52.211082],"type":"Point"}
}