{
  "type": "Feature",
  "properties": {
    "addr:full":"Farmsumerwg 132 Appingedam Groningen 9902 BW",
    "addr:housenumber":"132",
    "addr:postcode":"9902 bw",
    "addr:street":"Appingedam",
    "iso:country":"NL",
    "sg:address":"Farmsumerwg 132",
    "sg:city":"Appingedam",
    "sg:orig_category":"Woninginrichting",
    "sg:phone":"+31 596 680 222",
    "sg:postcode":"9902 BW",
    "sg:province":"Groningen",
    "wof:name":"Kwantum",
    "wof:placetype":"venue"
},
  "geometry": {"coordinates":[6.8797688484,53.3194580078],"type":"Point"}
}