{
  "type": "Feature",
  "properties": {
    "iso:country":"NL",
    "sg:address":"Zuiderhaven 6A",
    "sg:city":"Harlingen",
    "sg:orig_category":"Grafisch Ontwerpers",
    "sg:phone":"+31 517 418 580",
    "sg:postcode":"8861 XB",
    "sg:province":"Provincie Friesland",
    "wof:name":"Jukkema Bno Ontwerpstudio",
    "wof:placetype":"venue"
},
  "geometry": {"coordinates":[5.413086,53.174549],"type":"Point"}
}