{
  "type": "Feature",
  "properties": {
    "addr:full":"Nachtegaalln 16B Bilthoven Utrecht 3722 AB",
    "addr:housenumber":"16b",
    "addr:postcode":"3722 ab",
    "addr:street":"Nachtegaalln",
    "iso:country":"NL",
    "sg:address":"Nachtegaalln 16B",
    "sg:city":"Bilthoven",
    "sg:orig_category":"Hoortoestellen",
    "sg:phone":"+31 30 228 3862",
    "sg:postcode":"3722 AB",
    "sg:province":"Utrecht",
    "wof:name":"Beter Horen",
    "wof:placetype":"venue"
},
  "geometry": {"coordinates":[5.205421,52.128616],"type":"Point"}
}