{
  "type": "Feature",
  "properties": {
    "addr:full":"Van Baerlestraat 57Hs Amsterdam Noord-Holland 1071 AR",
    "addr:housenumber":"57hs",
    "addr:postcode":"1071",
    "addr:street":"Van Baerlestraat",
    "iso:country":"NL",
    "sg:address":"Van Baerlestraat 57Hs",
    "sg:city":"Amsterdam",
    "sg:orig_category":"Farmaceutische Producten Gh",
    "sg:phone":"+31 20 670 1672",
    "sg:postcode":"1071 AR",
    "sg:province":"Noord-Holland",
    "wof:name":"Pharmodontal Nederland Bv",
    "wof:placetype":"venue"
},
  "geometry": {"coordinates":[-94.58503,38.350479],"type":"Point"}
}