{
  "type": "Feature",
  "properties": {
    "addr:full":"Noorder Parallelweg 15 Ede Gld Gelderland 6713 KN",
    "addr:housenumber":"15",
    "addr:postcode":"6713 kn",
    "addr:street":"Noorder Parallelweg;Gld Gelderland",
    "iso:country":"NL",
    "sg:address":"Noorder Parallelweg 15",
    "sg:city":"Ede Gld",
    "sg:orig_category":"Fitnesscentra",
    "sg:phone":"+31 318 639 092",
    "sg:postcode":"6713 KN",
    "sg:province":"Gelderland",
    "wof:name":"Sportschool Louwerse",
    "wof:placetype":"venue"
},
  "geometry": {"coordinates":[5.650267,52.032204],"type":"Point"}
}