{
  "type": "Feature",
  "properties": {
    "addr:full":"Kuyperstr 41 Bunschoten Spakenb Utrecht 3752 BC",
    "addr:housenumber":"41",
    "addr:postcode":"3752 bc",
    "addr:street":"Kuyperstr",
    "iso:country":"NL",
    "sg:address":"Kuyperstr 41",
    "sg:city":"Bunschoten Spakenb",
    "sg:orig_category":"Projectontwikkeling",
    "sg:phone":"+31 33 298 6937",
    "sg:postcode":"3752 BC",
    "sg:province":"Utrecht",
    "wof:name":"Koops",
    "wof:placetype":"venue"
},
  "geometry": {"coordinates":[5.373884,52.252083],"type":"Point"}
}