{
  "type": "Feature",
  "properties": {
    "addr:full":"Tressenplaats 17 Groningen Groningen 9722 XC",
    "addr:housenumber":"17",
    "addr:postcode":"9722 xc",
    "addr:street":"Tressenplaats",
    "iso:country":"NL",
    "sg:address":"Tressenplaats 17",
    "sg:city":"Groningen",
    "sg:orig_category":"Bibliotheken And Openbare Archieven",
    "sg:phone":"+31 50 526 9452",
    "sg:postcode":"9722 XC",
    "sg:province":"Groningen",
    "wof:name":"Theosofische Vereniging Nederland",
    "wof:placetype":"venue"
},
  "geometry": {"coordinates":[6.580681,53.200005],"type":"Point"}
}