{
  "type": "Feature",
  "properties": {
    "iso:country":"NL",
    "sg:address":"De Zwemmer 7",
    "sg:city":"Leeuwarden",
    "sg:orig_category":"Watersport-, Sport- And Kampeerbenodigdheden Verhuur",
    "sg:phone":"+31 58 280 0034",
    "sg:postcode":"8939 CA",
    "sg:province":"Friesland",
    "wof:name":"Watersportbedrijf De Vries",
    "wof:placetype":"venue"
},
  "geometry": {"coordinates":[5.837667942,53.1855354309],"type":"Point"}
}