{
  "type": "Feature",
  "properties": {
    "addr:full":"Van Oestendestraat 23D Rotterdam Zuid-Holland 3083 MD",
    "addr:housenumber":"23d",
    "addr:postcode":"3083",
    "addr:street":"Van Oestendestraat",
    "iso:country":"NL",
    "sg:address":"Van Oestendestraat 23D",
    "sg:city":"Rotterdam",
    "sg:orig_category":"Autokeuringen",
    "sg:phone":"+31 10 484 2061",
    "sg:postcode":"3083 MD",
    "sg:province":"Zuid-Holland",
    "wof:name":"Isra",
    "wof:placetype":"venue"
},
  "geometry": {"coordinates":[4.476971,51.891472],"type":"Point"}
}