{
  "type": "Feature",
  "properties": {
    "iso:country":"NL",
    "sg:address":"Achtersloot 194",
    "sg:city":"Ijsselstein Ut",
    "sg:orig_category":"Granen, Zaden And Diervoeders Gh",
    "sg:phone":"+31 348 473 762",
    "sg:postcode":"3401 NZ",
    "sg:province":"Utrecht",
    "wof:name":"J.A.J. Verkleij",
    "wof:placetype":"venue"
},
  "geometry": {"coordinates":[5.020972,52.037724],"type":"Point"}
}