{
  "type": "Feature",
  "properties": {
    "addr:full":"Julianastraat 85 Dedemsvaart NL.08 7701 GK",
    "addr:housenumber":"85;nl.08",
    "addr:postcode":"7701 gk",
    "addr:street":"Julianastraat",
    "iso:country":"NL",
    "sg:address":"Julianastraat 85",
    "sg:city":"Dedemsvaart",
    "sg:orig_category":"Huishoudapparatuur, Televisies And Radio'S",
    "sg:phone":"+31 523 615 394",
    "sg:postcode":"7701 GK",
    "sg:province":"NL.08",
    "wof:name":"Mds",
    "wof:placetype":"venue"
},
  "geometry": {"coordinates":[6.457838,52.604179],"type":"Point"}
}