{
  "type": "Feature",
  "properties": {
    "iso:country":"NL",
    "sg:address":"Griendtsveenstraat 80",
    "sg:city":"Erica",
    "sg:orig_category":"Kappers",
    "sg:phone":"+31 591 301 949",
    "sg:postcode":"7887 TK",
    "sg:province":"Drenthe",
    "wof:name":"Kapsalon Rita",
    "wof:placetype":"venue"
},
  "geometry": {"coordinates":[6.9493441582,52.6778297424],"type":"Point"}
}