{
  "type": "Feature",
  "properties": {
    "addr:full":"Everdenberg 21 Oosterhout Nb Noord-Brabant 4902 TT",
    "addr:housenumber":"21",
    "addr:postcode":"4902 tt",
    "addr:street":"Everdenberg",
    "iso:country":"NL",
    "sg:address":"Everdenberg 21",
    "sg:city":"Oosterhout Nb",
    "sg:orig_category":"Verlichtingsartikelen - Groothandel",
    "sg:phone":"+31 162 522 446",
    "sg:postcode":"4902 TT",
    "sg:province":"Noord-Brabant",
    "sg:website":"http://www.bailey.nl/",
    "wof:name":"Bailey Bv",
    "wof:placetype":"venue"
},
  "geometry": {"coordinates":[4.885623,51.633732],"type":"Point"}
}