{
  "type": "Feature",
  "properties": {
    "addr:full":"Stationsstr 28/30 Kesteren Gelderland 4041 CJ",
    "addr:housenumber":"28 / 30",
    "addr:postcode":"4041 cj",
    "addr:street":"Stationsstr;Gelderland",
    "iso:country":"NL",
    "sg:address":"Stationsstr 28/30",
    "sg:city":"Kesteren",
    "sg:orig_category":"Gehandicapteninformatie",
    "sg:phone":"+31 488 483 322",
    "sg:postcode":"4041 CJ",
    "sg:province":"Gelderland",
    "wof:name":"Schutse, De",
    "wof:placetype":"venue"
},
  "geometry": {"coordinates":[5.579859,51.932529],"type":"Point"}
}