{
  "type": "Feature",
  "properties": {
    "addr:full":"Gubbelstraat 16 Maastricht Limburg 6211 CE",
    "addr:housenumber":"16",
    "addr:postcode":"6211 ce",
    "addr:street":"Gubbelstraat",
    "iso:country":"NL",
    "sg:address":"Gubbelstraat 16",
    "sg:city":"Maastricht",
    "sg:orig_category":"Binnenhuisarchitecten",
    "sg:phone":"+31 43 325 4570",
    "sg:postcode":"6211 CE",
    "sg:province":"Limburg",
    "wof:name":"Grummer Interieur Bv",
    "wof:placetype":"venue"
},
  "geometry": {"coordinates":[5.69284,50.852295],"type":"Point"}
}