{
  "type": "Feature",
  "properties": {
    "addr:full":"Kruisherenborch 31 Rosmalen North Brabant 5241 KK",
    "addr:housenumber":"31",
    "addr:postcode":"5241 kk",
    "addr:street":"Kruisherenborch",
    "iso:country":"NL",
    "sg:address":"Kruisherenborch 31",
    "sg:city":"Rosmalen",
    "sg:orig_category":"Grafisch Ontwerpers",
    "sg:phone":"+31 73 523 6937",
    "sg:postcode":"5241 KK",
    "sg:province":"North Brabant",
    "wof:name":"Leeuwen, Pieter Van",
    "wof:placetype":"venue"
},
  "geometry": {"coordinates":[5.3579,51.722729],"type":"Point"}
}