{
  "type": "Feature",
  "properties": {
    "iso:country":"NL",
    "sg:address":"Twekkeler Es 28",
    "sg:city":"Enschede",
    "sg:orig_category":"Kunststoffen- Verwerkende Industrie",
    "sg:phone":"+31 53 432 1962",
    "sg:postcode":"7547 SM",
    "sg:province":"Overijssel",
    "wof:name":"Interplastics Holland Bv",
    "wof:placetype":"venue"
},
  "geometry": {"coordinates":[6.83954,52.220699],"type":"Point"}
}