{
  "type": "Feature",
  "properties": {
    "iso:country":"NL",
    "sg:address":"Schooldwwg 19",
    "sg:city":"Austerlitz",
    "sg:orig_category":"Kappers",
    "sg:phone":"+31 343 491 238",
    "sg:postcode":"3711 BM",
    "sg:province":"Utrecht",
    "wof:name":"Stevens",
    "wof:placetype":"venue"
},
  "geometry": {"coordinates":[5.315293,52.079029],"type":"Point"}
}