{
  "type": "Feature",
  "properties": {
    "addr:full":"Maldivenwg 108 Almere Flevoland 1339 RV",
    "addr:housenumber":"108",
    "addr:postcode":"1339 rv",
    "addr:street":"Flevoland",
    "iso:country":"NL",
    "sg:address":"Maldivenwg 108",
    "sg:city":"Almere",
    "sg:orig_category":"Homeopathie",
    "sg:phone":"+31 36 535 2829",
    "sg:postcode":"1339 RV",
    "sg:province":"Flevoland",
    "wof:name":"Koert, Hilde",
    "wof:placetype":"venue"
},
  "geometry": {"coordinates":[5.312805,52.397877],"type":"Point"}
}