{
  "type": "Feature",
  "properties": {
    "addr:full":"Balderikstr 17 Utrecht Utrecht 3553 BA",
    "addr:housenumber":"17",
    "addr:postcode":"3553 ba",
    "addr:street":"Balderikstr",
    "iso:country":"NL",
    "sg:address":"Balderikstr 17",
    "sg:city":"Utrecht",
    "sg:orig_category":"Fotografie Reclame En Mode",
    "sg:phone":"+31 30 244 3846",
    "sg:postcode":"3553 BA",
    "sg:province":"Utrecht",
    "wof:name":"Eddy Elderman",
    "wof:placetype":"venue"
},
  "geometry": {"coordinates":[5.090551,52.110264],"type":"Point"}
}