{
  "type": "Feature",
  "properties": {
    "addr:full":"Kon Julianaln 200 Voorburg Zuid-Holland 2274 JP",
    "addr:housenumber":"200",
    "addr:postcode":"2274 jp",
    "addr:street":"Kon",
    "iso:country":"NL",
    "sg:address":"Kon Julianaln 200",
    "sg:city":"Voorburg",
    "sg:orig_category":"Kopieerservice",
    "sg:phone":"+31 70 369 1692",
    "sg:postcode":"2274 JP",
    "sg:province":"Zuid-Holland",
    "sg:website":"http://www.printer.nl",
    "wof:name":"Printer, The",
    "wof:placetype":"venue"
},
  "geometry": {"coordinates":[4.353286,52.076946],"type":"Point"}
}