{
  "type": "Feature",
  "properties": {
    "iso:country":"NL",
    "sg:address":"Kerkraderweg 19",
    "sg:city":"Heerlen",
    "sg:orig_category":"Kappers",
    "sg:phone":"+31 45 541 3447",
    "sg:postcode":"6416 CC",
    "sg:province":"Limburg",
    "wof:name":"Coiffure Raymond",
    "wof:placetype":"venue"
},
  "geometry": {"coordinates":[5.9954171181,50.8844184875],"type":"Point"}
}