{
  "type": "Feature",
  "properties": {
    "iso:country":"NL",
    "sg:address":"Fjord 145",
    "sg:city":"Lelystad",
    "sg:orig_category":"Architecten En Architectenbureaus",
    "sg:phone":"+31 320 245 557",
    "sg:postcode":"8224 DJ",
    "sg:province":"Flevoland",
    "wof:name":"Rabius, Bur",
    "wof:placetype":"venue"
},
  "geometry": {"coordinates":[5.487075,52.514664],"type":"Point"}
}