{
  "type": "Feature",
  "properties": {
    "iso:country":"NL",
    "sg:address":"Bovenboer 31",
    "sg:city":"Veeningen",
    "sg:orig_category":"Montagebedrijven",
    "sg:phone":"+31 528 391 493",
    "sg:postcode":"7924 PT",
    "sg:province":"Provincie Drenthe",
    "wof:name":"Kms",
    "wof:placetype":"venue"
},
  "geometry": {"coordinates":[6.369455,52.66856],"type":"Point"}
}