{
  "type": "Feature",
  "properties": {
    "addr:full":"Bovenboer 31 Veeningen Provincie Drenthe 7924 PT",
    "addr:housenumber":"31",
    "addr:postcode":"7924",
    "addr:street":"Bovenboer;Pt",
    "iso:country":"NL",
    "sg:address":"Bovenboer 31",
    "sg:city":"Veeningen",
    "sg:orig_category":"Montagebedrijven",
    "sg:phone":"+31 528 391 493",
    "sg:postcode":"7924 PT",
    "sg:province":"Provincie Drenthe",
    "wof:name":"Kms",
    "wof:placetype":"venue"
},
  "geometry": {"coordinates":[6.369455,52.66856],"type":"Point"}
}