{
  "type": "Feature",
  "properties": {
    "iso:country":"NL",
    "sg:address":"Postweg 117",
    "sg:city":"De Cocksdorp",
    "sg:orig_category":"Levende Dieren Gh",
    "sg:phone":"+31 222 311 753",
    "sg:postcode":"1795 JL",
    "sg:province":"North Holland",
    "wof:name":"P C Bouthoorn",
    "wof:placetype":"venue"
},
  "geometry": {"coordinates":[4.827051,53.118668],"type":"Point"}
}