{
  "type": "Feature",
  "properties": {
    "iso:country":"NL",
    "sg:address":"Beyerlandseln 10",
    "sg:city":"Rotterdam",
    "sg:orig_category":"Biljartzalen",
    "sg:phone":"+31 10 432 1176",
    "sg:postcode":"3074 EJ",
    "sg:province":"Zuid-Holland",
    "wof:name":"Linker Maasoever",
    "wof:placetype":"venue"
},
  "geometry": {"coordinates":[4.51149,51.89608],"type":"Point"}
}