{
  "type": "Feature",
  "properties": {
    "addr:full":"Oudeland 128 Zwyndrecht Zuid-Holland 3335 VJ",
    "addr:housenumber":"128",
    "addr:postcode":"3335 vj",
    "addr:street":"Oudeland",
    "iso:country":"NL",
    "sg:address":"Oudeland 128",
    "sg:city":"Zwyndrecht",
    "sg:orig_category":"Fietsen En Bromfietsen",
    "sg:phone":"+31 78 610 1310",
    "sg:postcode":"3335 VJ",
    "sg:province":"Zuid-Holland",
    "wof:name":"Gulden Fietsen Vof",
    "wof:placetype":"venue"
},
  "geometry": {"coordinates":[4.60712,51.827839],"type":"Point"}
}