{
  "type": "Feature",
  "properties": {
    "addr:full":"Binnenwg 73 Heemstede Noord-Holland 2101 JD",
    "addr:housenumber":"73",
    "addr:postcode":"2101 jd",
    "addr:street":"Binnenwg",
    "iso:country":"NL",
    "sg:address":"Binnenwg 73",
    "sg:city":"Heemstede",
    "sg:orig_category":"Beveiliging",
    "sg:phone":"+31 23 528 0490",
    "sg:postcode":"2101 JD",
    "sg:province":"Noord-Holland",
    "sg:website":"http://www.meer-sleutelservice.nl",
    "wof:name":"Meer Sleutelservice Van Der",
    "wof:placetype":"venue"
},
  "geometry": {"coordinates":[4.621356,52.352657],"type":"Point"}
}