{
  "type": "Feature",
  "properties": {
    "addr:full":"De Horzak 61 Oss Noord-Brabant 5347 JA",
    "addr:housenumber":"61",
    "addr:postcode":"5347 ja",
    "addr:street":"De Horzak",
    "iso:country":"NL",
    "sg:address":"De Horzak 61",
    "sg:city":"Oss",
    "sg:orig_category":"Accountants - Administratie- Consulenten En -Kantoren",
    "sg:phone":"+31 412 657 275",
    "sg:postcode":"5347 JA",
    "sg:province":"Noord-Brabant",
    "wof:name":"Gaal Accountantskantoor, Van",
    "wof:placetype":"venue"
},
  "geometry": {"coordinates":[-93.432076,45.066154],"type":"Point"}
}