{
  "type": "Feature",
  "properties": {
    "iso:country":"NL",
    "sg:address":"Kruisstr 36",
    "sg:city":"Tilburg",
    "sg:orig_category":"Psychotherapeuten",
    "sg:phone":"+31 13 580 1188",
    "sg:postcode":"5014 HT",
    "sg:province":"Noord-Brabant",
    "wof:name":"Meulenkamp",
    "wof:placetype":"venue"
},
  "geometry": {"coordinates":[5.150421,51.592369],"type":"Point"}
}