{
  "type": "Feature",
  "properties": {
    "addr:full":"Evertsenstr 69C Leiden Zuid-Holland 2315 SK",
    "addr:housenumber":"69c",
    "addr:street":"Evertsenstr;2315",
    "iso:country":"NL",
    "sg:address":"Evertsenstr 69C",
    "sg:city":"Leiden",
    "sg:orig_category":"Kunstenaars- Benodigdheden",
    "sg:phone":"+31 71 522 2681",
    "sg:postcode":"2315 SK",
    "sg:province":"Zuid-Holland",
    "wof:name":"Polymetaal",
    "wof:placetype":"venue"
},
  "geometry": {"coordinates":[4.508164,52.157143],"type":"Point"}
}