{
  "type": "Feature",
  "properties": {
    "addr:full":"Hollewg 30 Scherpenzeel Gld Gelderland 3925 LW",
    "addr:housenumber":"30",
    "addr:postcode":"3925 lw",
    "addr:street":"Hollewg;Gld Gelderland",
    "iso:country":"NL",
    "sg:address":"Hollewg 30",
    "sg:city":"Scherpenzeel Gld",
    "sg:classifiers":[
        {
            "category":"Retail",
            "subcategory":"Auto Repair",
            "type":"Services"
        }
    ],
    "sg:phone":"+31 33 277 9900",
    "sg:postcode":"3925 LW",
    "sg:province":"Gelderland",
    "sg:tags":[
        "garage"
    ],
    "wof:name":"Broekhuis Tts",
    "wof:placetype":"venue"
},
  "geometry": {"coordinates":[5.501958,52.079559],"type":"Point"}
}