{
  "type": "Feature",
  "properties": {
    "iso:country":"NL",
    "sg:address":"De Hooge Hoek 5",
    "sg:city":"Renswoude",
    "sg:orig_category":"Lasbedrijven",
    "sg:phone":"+31 318 574 479",
    "sg:postcode":"3927 GG",
    "sg:province":"Utrecht",
    "sg:website":"http://www.maas-gerritsen.nl",
    "wof:name":"Gerritsen Bv",
    "wof:placetype":"venue"
},
  "geometry": {"coordinates":[5.536477,52.078892],"type":"Point"}
}