{
  "type": "Feature",
  "properties": {
    "addr:full":"Grt Kerkstr 30 Harlingen Friesland 8861 EK",
    "addr:housenumber":"30",
    "addr:postcode":"8861 ek",
    "iso:country":"NL",
    "sg:address":"Grt Kerkstr 30",
    "sg:city":"Harlingen",
    "sg:orig_category":"Antiquiteiten",
    "sg:phone":"+31 517 414 807",
    "sg:postcode":"8861 EK",
    "sg:province":"Friesland",
    "wof:name":"Koperen Bel, De",
    "wof:placetype":"venue"
},
  "geometry": {"coordinates":[5.420929,53.173481],"type":"Point"}
}