{
  "type": "Feature",
  "properties": {
    "addr:full":"Bennebroekerdijk 205 Cruquius North Holland 2142 LD",
    "addr:housenumber":"205",
    "addr:postcode":"2142 ld",
    "addr:street":"Bennebroekerdijk",
    "iso:country":"NL",
    "sg:address":"Bennebroekerdijk 205",
    "sg:city":"Cruquius",
    "sg:orig_category":"Autokeuringen",
    "sg:phone":"+31 23 529 3588",
    "sg:postcode":"2142 LD",
    "sg:province":"North Holland",
    "wof:name":"Dymo Track Motortechniek Bv",
    "wof:placetype":"venue"
},
  "geometry": {"coordinates":[4.622989,52.334187],"type":"Point"}
}