{
  "type": "Feature",
  "properties": {
    "iso:country":"NL",
    "sg:address":"Hendrik Van Viandenstr 18",
    "sg:city":"Achterveld",
    "sg:orig_category":"Kappers",
    "sg:phone":"+31 342 451 123",
    "sg:postcode":"3791 AV",
    "sg:province":"Gelderland",
    "wof:name":"D.M.L. Doornekamp",
    "wof:placetype":"venue"
},
  "geometry": {"coordinates":[5.4932999611,52.1389312744],"type":"Point"}
}