{
  "type": "Feature",
  "properties": {
    "addr:full":"Smedestr 5 Fil Haarlem Noord-Holland 2011 RE",
    "addr:housenumber":"5 fil",
    "addr:postcode":"2011 re",
    "addr:street":"Smedestr",
    "iso:country":"NL",
    "sg:address":"Smedestr 5 Fil",
    "sg:city":"Haarlem",
    "sg:orig_category":"Warenhuizen",
    "sg:phone":"+31 23 531 9332",
    "sg:postcode":"2011 RE",
    "sg:province":"Noord-Holland",
    "wof:name":"Hema",
    "wof:placetype":"venue"
},
  "geometry": {"coordinates":[4.6422529221,52.3805618286],"type":"Point"}
}