{
  "type": "Feature",
  "properties": {
    "addr:full":"Midstraat 13 Joure Friesland 8501 AC",
    "addr:housenumber":"13",
    "addr:postcode":"8501 ac",
    "addr:street":"Midstraat",
    "iso:country":"NL",
    "sg:address":"Midstraat 13",
    "sg:city":"Joure",
    "sg:orig_category":"Visspeciaalzaken",
    "sg:phone":"+31 513 417 547",
    "sg:postcode":"8501 AC",
    "sg:province":"Friesland",
    "wof:name":"Het Urker Vispaleis",
    "wof:placetype":"venue"
},
  "geometry": {"coordinates":[5.792589,52.969082],"type":"Point"}
}