{
  "type": "Feature",
  "properties": {
    "addr:full":"L Tiendewg 53 Gouda South Holland 2801 KE",
    "addr:housenumber":"53",
    "addr:postcode":"2801 ke",
    "iso:country":"NL",
    "sg:address":"L Tiendewg 53",
    "sg:city":"Gouda",
    "sg:orig_category":"Wasmachines En Wasdrogers",
    "sg:phone":"+31 182 689 010",
    "sg:postcode":"2801 KE",
    "sg:province":"South Holland",
    "wof:name":"Dernee Bv, Rob",
    "wof:placetype":"venue"
},
  "geometry": {"coordinates":[4.7136659622,52.0118331909],"type":"Point"}
}