{
  "type": "Feature",
  "properties": {
    "iso:country":"NL",
    "sg:address":"Pampusln 68",
    "sg:city":"Weesp",
    "sg:orig_category":"Administratie- En Boekhoudkantoren",
    "sg:phone":"+31 294 419 452",
    "sg:postcode":"1382 JR",
    "sg:province":"Noord-Holland",
    "wof:name":"Bedeco",
    "wof:placetype":"venue"
},
  "geometry": {"coordinates":[5.03828,52.308315],"type":"Point"}
}