{
  "type": "Feature",
  "properties": {
    "addr:full":"Paukenslag 21 Klaaswaal Zuid-Holland 3286 TD",
    "addr:housenumber":"21",
    "addr:postcode":"3286 td",
    "addr:street":"Paukenslag",
    "iso:country":"NL",
    "sg:address":"Paukenslag 21",
    "sg:city":"Klaaswaal",
    "sg:orig_category":"Nagelstudio'S",
    "sg:phone":"+31 186 575 025",
    "sg:postcode":"3286 TD",
    "sg:province":"Zuid-Holland",
    "wof:name":"Jeanette",
    "wof:placetype":"venue"
},
  "geometry": {"coordinates":[4.453293,51.773159],"type":"Point"}
}