{
  "type": "Feature",
  "properties": {
    "iso:country":"NL",
    "sg:address":"Haarlemmerwg 201",
    "sg:city":"Amsterdam",
    "sg:orig_category":"Meubelen",
    "sg:phone":"+31 20 686 2244",
    "sg:postcode":"1051 LD",
    "sg:province":"Noord-Holland",
    "wof:name":"Westerpark",
    "wof:placetype":"venue"
},
  "geometry": {"coordinates":[4.87059,52.385265],"type":"Point"}
}