{
  "type": "Feature",
  "properties": {
    "iso:country":"NL",
    "sg:address":"Egelwier 8",
    "sg:city":"Leusden",
    "sg:orig_category":"Psychologen",
    "sg:phone":"+31 33 494 2765",
    "sg:postcode":"3831 ZJ",
    "sg:province":"Utrecht",
    "wof:name":"Psychologische En Pedagogische Praktijk",
    "wof:placetype":"venue"
},
  "geometry": {"coordinates":[5.441486,52.129208],"type":"Point"}
}