{
  "type": "Feature",
  "properties": {
    "addr:full":"Koelhuisstr 25 Huissen Gelderland 6851 NB",
    "addr:housenumber":"25",
    "addr:postcode":"6851 nb",
    "addr:street":"Koelhuisstr;Gelderland",
    "iso:country":"NL",
    "sg:address":"Koelhuisstr 25",
    "sg:city":"Huissen",
    "sg:orig_category":"Koeriersdiensten",
    "sg:phone":"+31 26 325 2536",
    "sg:postcode":"6851 NB",
    "sg:province":"Gelderland",
    "wof:name":"Sonny Express",
    "wof:placetype":"venue"
},
  "geometry": {"coordinates":[5.935935,51.931507],"type":"Point"}
}