{
  "type": "Feature",
  "properties": {
    "addr:full":"Spoordreef 41 Almere Flevoland 1315 GK",
    "addr:housenumber":"41",
    "addr:postcode":"1315 gk",
    "addr:street":"Spoordreef;Flevoland",
    "iso:country":"NL",
    "sg:address":"Spoordreef 41",
    "sg:city":"Almere",
    "sg:orig_category":"Hypotheken",
    "sg:phone":"+31 36 530 0636",
    "sg:postcode":"1315 GK",
    "sg:province":"Flevoland",
    "sg:website":"http://www.almere.hypotheekshop.nl/360",
    "wof:name":"Hypotheekshop, De",
    "wof:placetype":"venue"
},
  "geometry": {"coordinates":[5.216207,52.371239],"type":"Point"}
}