{
  "type": "Feature",
  "properties": {
    "iso:country":"NL",
    "sg:address":"St.- Antoniusstraat 29",
    "sg:city":"De Mortel",
    "sg:classifiers":[
        {
            "category":"Fast Food",
            "type":"Food & Drink"
        }
    ],
    "sg:phone":"+31 492 361 258",
    "sg:postcode":"5425 VD",
    "sg:province":"North Brabant",
    "sg:tags":[
        "afhaal",
        "restaurant"
    ],
    "wof:name":"De Koperen Hoorn",
    "wof:placetype":"venue"
},
  "geometry": {"coordinates":[5.707731,51.541412],"type":"Point"}
}