{
  "type": "Feature",
  "properties": {
    "addr:full":"St.- Antoniusstraat 29 De Mortel North Brabant 5425 VD",
    "addr:housenumber":"29",
    "addr:postcode":"5425 vd",
    "addr:street":"St. Antoniusstraat",
    "iso:country":"NL",
    "sg:address":"St.- Antoniusstraat 29",
    "sg:city":"De Mortel",
    "sg:classifiers":[
        {
            "category":"Fast Food",
            "type":"Food & Drink"
        }
    ],
    "sg:phone":"+31 492 361 258",
    "sg:postcode":"5425 VD",
    "sg:province":"North Brabant",
    "sg:tags":[
        "afhaal",
        "restaurant"
    ],
    "wof:name":"De Koperen Hoorn",
    "wof:placetype":"venue"
},
  "geometry": {"coordinates":[5.707731,51.541412],"type":"Point"}
}