{
  "type": "Feature",
  "properties": {
    "addr:full":"Hans Memlinglaan 22 Bilthoven Utrecht 3723 WJ",
    "addr:housenumber":"22",
    "addr:postcode":"3723 wj",
    "addr:street":"Hans Memlinglaan",
    "iso:country":"NL",
    "sg:address":"Hans Memlinglaan 22",
    "sg:city":"Bilthoven",
    "sg:orig_category":"Public Relationbureaus",
    "sg:phone":"+31 30 228 1226",
    "sg:postcode":"3723 WJ",
    "sg:province":"Utrecht",
    "wof:name":"Denkidee Bv",
    "wof:placetype":"venue"
},
  "geometry": {"coordinates":[5.192119,52.130333],"type":"Point"}
}