{
  "type": "Feature",
  "properties": {
    "addr:full":"Koekoeksbloem 22 Uithoorn Noord-Holland 1422 KP",
    "addr:housenumber":"22",
    "addr:postcode":"1422 kp",
    "addr:street":"Koekoeksbloem",
    "iso:country":"NL",
    "sg:address":"Koekoeksbloem 22",
    "sg:city":"Uithoorn",
    "sg:orig_category":"Bedrijfs- And Managementsconsultants",
    "sg:phone":"+31 297 569 766",
    "sg:postcode":"1422 KP",
    "sg:province":"Noord-Holland",
    "wof:name":"Archituur - Organisatiebegeleiding",
    "wof:placetype":"venue"
},
  "geometry": {"coordinates":[4.822114,52.252575],"type":"Point"}
}