{
  "type": "Feature",
  "properties": {
    "iso:country":"NL",
    "sg:address":"Koekoeksbloem 22",
    "sg:city":"Uithoorn",
    "sg:orig_category":"Bedrijfs- And Managementsconsultants",
    "sg:phone":"+31 297 569 766",
    "sg:postcode":"1422 KP",
    "sg:province":"Noord-Holland",
    "wof:name":"Archituur - Organisatiebegeleiding",
    "wof:placetype":"venue"
},
  "geometry": {"coordinates":[4.822114,52.252575],"type":"Point"}
}