{
  "type": "Feature",
  "properties": {
    "addr:full":"Paasloregel 47 Willemsoord Overijssel 8338 SV",
    "addr:housenumber":"47",
    "addr:postcode":"8338 sv",
    "addr:street":"Paasloregel",
    "iso:country":"NL",
    "sg:address":"Paasloregel 47",
    "sg:city":"Willemsoord",
    "sg:orig_category":"Oldtimers",
    "sg:phone":"+31 521 588 342",
    "sg:postcode":"8338 SV",
    "sg:province":"Overijssel",
    "wof:name":"Algra",
    "wof:placetype":"venue"
},
  "geometry": {"coordinates":[6.050374,52.82127],"type":"Point"}
}