{
  "type": "Feature",
  "properties": {
    "addr:full":"Broekwg 4 Venray Limburg 5804 BH",
    "addr:housenumber":"4",
    "addr:postcode":"5804 bh",
    "addr:street":"Broekwg",
    "iso:country":"NL",
    "sg:address":"Broekwg 4",
    "sg:city":"Venray",
    "sg:orig_category":"Kermisexploitatie",
    "sg:phone":"+31 478 510 086",
    "sg:postcode":"5804 BH",
    "sg:province":"Limburg",
    "wof:name":"Geven, H A",
    "wof:placetype":"venue"
},
  "geometry": {"coordinates":[5.969201,51.534084],"type":"Point"}
}