{
  "type": "Feature",
  "properties": {
    "addr:full":"Breukkruid 1 Veenendaal Utrecht 3903 GP",
    "addr:housenumber":"1",
    "addr:postcode":"3903 gp",
    "addr:street":"Breukkruid",
    "iso:country":"NL",
    "sg:address":"Breukkruid 1",
    "sg:city":"Veenendaal",
    "sg:orig_category":"Bevestigingsmaterialen",
    "sg:phone":"+31 318 526 977",
    "sg:postcode":"3903 GP",
    "sg:province":"Utrecht",
    "wof:name":"Rotadrill Gmbh",
    "wof:placetype":"venue"
},
  "geometry": {"coordinates":[5.554758,52.003517],"type":"Point"}
}