{
  "type": "Feature",
  "properties": {
    "addr:full":"Raambrug 1 Bladel Noord-Brabant 5531 AG",
    "addr:housenumber":"1",
    "addr:postcode":"5531",
    "addr:street":"Raambrug",
    "iso:country":"NL",
    "sg:address":"Raambrug 1",
    "sg:city":"Bladel",
    "sg:orig_category":"Accountants - Administratie- Consulenten En -Kantoren",
    "sg:phone":"+31 497 382 624",
    "sg:postcode":"5531 AG",
    "sg:province":"Noord-Brabant",
    "wof:name":"Rekenarsenaal, Het",
    "wof:placetype":"venue"
},
  "geometry": {"coordinates":[5.205198,51.360191],"type":"Point"}
}