{
  "type": "Feature",
  "properties": {
    "addr:full":"Rynstr 81 Woerden Utrecht 3441 BS",
    "addr:housenumber":"81",
    "addr:postcode":"3441 bs",
    "addr:street":"Rynstr",
    "iso:country":"NL",
    "sg:address":"Rynstr 81",
    "sg:city":"Woerden",
    "sg:orig_category":"Bijouterie?n",
    "sg:phone":"+31 348 500 506",
    "sg:postcode":"3441 BS",
    "sg:province":"Utrecht",
    "wof:name":"Kaia",
    "wof:placetype":"venue"
},
  "geometry": {"coordinates":[4.887371,52.085117],"type":"Point"}
}