{
  "type": "Feature",
  "properties": {
    "addr:full":"Paradijsstr 4 Sittard Limburg 6131 JB",
    "addr:housenumber":"4",
    "addr:postcode":"6131 jb",
    "addr:street":"Paradijsstr",
    "iso:country":"NL",
    "sg:address":"Paradijsstr 4",
    "sg:city":"Sittard",
    "sg:orig_category":"Zoetwaren - Winkels",
    "sg:phone":"+31 46 452 9116",
    "sg:postcode":"6131 JB",
    "sg:province":"Limburg",
    "wof:name":"Drop Inn",
    "wof:placetype":"venue"
},
  "geometry": {"coordinates":[5.869191,50.996597],"type":"Point"}
}