{
  "type": "Feature",
  "properties": {
    "addr:full":"Melis Stokelaan 1/By 'S Gravenhage South Holland 2533 CM",
    "addr:housenumber":"1 / by",
    "addr:postcode":"2533 cm",
    "addr:street":"Melis Stokelaan",
    "iso:country":"NL",
    "sg:address":"Melis Stokelaan 1/By",
    "sg:city":"'S Gravenhage",
    "sg:classifiers":[
        {
            "category":"Fast Food",
            "type":"Food & Drink"
        }
    ],
    "sg:phone":"+31 70 389 6496",
    "sg:postcode":"2533 CM",
    "sg:province":"South Holland",
    "sg:tags":[
        "afhaal",
        "restaurant"
    ],
    "wof:name":"Snackkiosk Miranda",
    "wof:placetype":"venue"
},
  "geometry": {"coordinates":[4.289636,52.051498],"type":"Point"}
}