{
  "type": "Feature",
  "properties": {
    "addr:full":"Papiermakerstr 1 Wormer North Holland 1531 NA",
    "addr:housenumber":"1",
    "addr:postcode":"1531 na",
    "addr:street":"Papiermakerstr",
    "iso:country":"NL",
    "sg:address":"Papiermakerstr 1",
    "sg:city":"Wormer",
    "sg:orig_category":"Woningbouw- Verenigingen En -Stichtingen",
    "sg:phone":"+31 75 642 6421",
    "sg:postcode":"1531 NA",
    "sg:province":"North Holland",
    "sg:website":"http://www.wbvwormer.nl",
    "wof:name":"Woning Stichting Wormer",
    "wof:placetype":"venue"
},
  "geometry": {"coordinates":[4.8120150566,52.4905853271],"type":"Point"}
}