{
  "type": "Feature",
  "properties": {
    "addr:full":"Zwaluwwg 64 Enkhuizen North Holland 1602 NV",
    "addr:housenumber":"64",
    "addr:postcode":"1602 nv",
    "addr:street":"Zwaluwwg",
    "iso:country":"NL",
    "sg:address":"Zwaluwwg 64",
    "sg:city":"Enkhuizen",
    "sg:orig_category":"Lasbedrijven",
    "sg:phone":"+31 228 320 103",
    "sg:postcode":"1602 NV",
    "sg:province":"North Holland",
    "wof:name":"Orij",
    "wof:placetype":"venue"
},
  "geometry": {"coordinates":[5.276247,52.715237],"type":"Point"}
}