{
  "type": "Feature",
  "properties": {
    "addr:full":"Randijk 5 Nieuwegein Utrecht 3435 PC",
    "addr:housenumber":"5",
    "addr:postcode":"3435 pc",
    "addr:street":"Randijk",
    "iso:country":"NL",
    "sg:address":"Randijk 5",
    "sg:city":"Nieuwegein",
    "sg:orig_category":"Parfum And Cosmetica Gh",
    "sg:phone":"+31 30 603 6059",
    "sg:postcode":"3435 PC",
    "sg:province":"Utrecht",
    "wof:name":"M. Mooren",
    "wof:placetype":"venue"
},
  "geometry": {"coordinates":[5.079608,52.023567],"type":"Point"}
}