{
  "type": "Feature",
  "properties": {
    "iso:country":"NL",
    "sg:address":"Randijk 5",
    "sg:city":"Nieuwegein",
    "sg:orig_category":"Parfum And Cosmetica Gh",
    "sg:phone":"+31 30 603 6059",
    "sg:postcode":"3435 PC",
    "sg:province":"Utrecht",
    "wof:name":"M. Mooren",
    "wof:placetype":"venue"
},
  "geometry": {"coordinates":[5.079608,52.023567],"type":"Point"}
}