{
  "type": "Feature",
  "properties": {
    "addr:full":"Keuningsweg 15 De Wilp Gn Groningen 9367 TB",
    "addr:housenumber":"15",
    "addr:postcode":"gn;9367 tb",
    "addr:street":"Keuningsweg",
    "iso:country":"NL",
    "sg:address":"Keuningsweg 15",
    "sg:city":"De Wilp Gn",
    "sg:orig_category":"Levende Dieren Gh",
    "sg:phone":"+31 594 641 767",
    "sg:postcode":"9367 TB",
    "sg:province":"Groningen",
    "wof:name":"U Veenema",
    "wof:placetype":"venue"
},
  "geometry": {"coordinates":[6.279076,53.120121],"type":"Point"}
}