{
  "type": "Feature",
  "properties": {
    "addr:full":"Concertwg 9 Alphen Aan Den Ryn Zuid-Holland 2402 JG",
    "addr:housenumber":"9",
    "addr:postcode":"2402 jg",
    "addr:street":"Concertwg;Aan Den Ryn",
    "iso:country":"NL",
    "sg:address":"Concertwg 9",
    "sg:city":"Alphen Aan Den Ryn",
    "sg:orig_category":"Fotozaken",
    "sg:phone":"+31 172 440 305",
    "sg:postcode":"2402 JG",
    "sg:province":"Zuid-Holland",
    "wof:name":"Foto Print Service Alphen",
    "wof:placetype":"venue"
},
  "geometry": {"coordinates":[4.659797,52.148712],"type":"Point"}
}