{
  "type": "Feature",
  "properties": {
    "addr:full":"Eikbergseweg 1 Bavel North Brabant 4854 NH",
    "addr:housenumber":"1",
    "addr:postcode":"4854 nh",
    "addr:street":"Eikbergseweg",
    "iso:country":"NL",
    "sg:address":"Eikbergseweg 1",
    "sg:city":"Bavel",
    "sg:orig_category":"Autokeuringen",
    "sg:phone":"+31 161 431 705",
    "sg:postcode":"4854 NH",
    "sg:province":"North Brabant",
    "wof:name":"Van Gestel Autoschade",
    "wof:placetype":"venue"
},
  "geometry": {"coordinates":[4.839468,51.561844],"type":"Point"}
}