{
  "type": "Feature",
  "properties": {
    "addr:full":"Slinge 574 Rotterdam Zuid-Holland 3086 EW",
    "addr:housenumber":"574",
    "addr:postcode":"3086 ew",
    "addr:street":"Slinge",
    "iso:country":"NL",
    "sg:address":"Slinge 574",
    "sg:city":"Rotterdam",
    "sg:orig_category":"Huishoudelijke Apparaten En Artikelen",
    "sg:phone":"+31 10 293 7105",
    "sg:postcode":"3086 EW",
    "sg:province":"Zuid-Holland",
    "wof:name":"Blokker Bv",
    "wof:placetype":"venue"
},
  "geometry": {"coordinates":[4.469753,51.874569],"type":"Point"}
}