{
  "type": "Feature",
  "properties": {
    "iso:country":"NL",
    "sg:address":"Lagedk 12",
    "sg:city":"Enter",
    "sg:classifiers":[
        {
            "category":"Education",
            "subcategory":"Special Training",
            "type":"Public Place"
        }
    ],
    "sg:phone":"+31 547 383 816",
    "sg:postcode":"7468 EZ",
    "sg:province":"Overijssel",
    "sg:tags":[
        "expertise"
    ],
    "wof:name":"Kraats & Blanken, Van Der",
    "wof:placetype":"venue"
},
  "geometry": {"coordinates":[-76.841904,40.463078],"type":"Point"}
}