{
  "type": "Feature",
  "properties": {
    "iso:country":"NL",
    "sg:address":"Mastbosstr 96",
    "sg:city":"Breda",
    "sg:orig_category":"Kappers",
    "sg:phone":"+31 6 22264010",
    "sg:postcode":"4813 GV",
    "sg:province":"North Brabant",
    "wof:name":"Bo Cheveux",
    "wof:placetype":"venue"
},
  "geometry": {"coordinates":[4.7426848412,51.5701370239],"type":"Point"}
}