{
  "type": "Feature",
  "properties": {
    "addr:full":"C Debussystr 169 S Gravenhage Zuid-Holland 2551 ZW",
    "addr:housenumber":"169;gravenhage",
    "addr:postcode":"2551 zw",
    "addr:street":"S",
    "iso:country":"NL",
    "sg:address":"C Debussystr 169",
    "sg:city":"S Gravenhage",
    "sg:orig_category":"Schilders",
    "sg:phone":"+31 70 323 2920",
    "sg:postcode":"2551 ZW",
    "sg:province":"Zuid-Holland",
    "wof:name":"Wessels, Martin",
    "wof:placetype":"venue"
},
  "geometry": {"coordinates":[4.23775,52.058601],"type":"Point"}
}