{
  "type": "Feature",
  "properties": {
    "iso:country":"NL",
    "sg:address":"Nicolaaswg 42",
    "sg:city":"Utrecht",
    "sg:classifiers":[
        {
            "category":"Retail",
            "subcategory":"Auto Repair",
            "type":"Services"
        }
    ],
    "sg:phone":"+31 30 251 6164",
    "sg:postcode":"3581 VJ",
    "sg:province":"Utrecht",
    "sg:tags":[
        "garage"
    ],
    "wof:name":"Wind Vof, Garage Van Der",
    "wof:placetype":"venue"
},
  "geometry": {"coordinates":[5.13737,52.087051],"type":"Point"}
}