{
  "type": "Feature",
  "properties": {
    "addr:full":"Pascalwg 10 Elst Gld Gelderland 6662 NX",
    "addr:housenumber":"10",
    "addr:postcode":"6662 nx",
    "addr:street":"Pascalwg;Gld Gelderland",
    "iso:country":"NL",
    "sg:address":"Pascalwg 10",
    "sg:city":"Elst Gld",
    "sg:orig_category":"Pompen - Revisie",
    "sg:phone":"+31 481 377 904",
    "sg:postcode":"6662 NX",
    "sg:province":"Gelderland",
    "sg:website":"http://www.croonen-pompen.nl",
    "wof:name":"Croonen, J A",
    "wof:placetype":"venue"
},
  "geometry": {"coordinates":[5.865815,51.913544],"type":"Point"}
}