{
  "type": "Feature",
  "properties": {
    "addr:full":"Kruisweg 35 Herkenbosch Limburg 6075 AL",
    "addr:housenumber":"35",
    "addr:postcode":"6075 al",
    "addr:street":"Kruisweg",
    "iso:country":"NL",
    "sg:address":"Kruisweg 35",
    "sg:city":"Herkenbosch",
    "sg:orig_category":"Bloemen And Planten Gh",
    "sg:phone":"+31 475 534 381",
    "sg:postcode":"6075 AL",
    "sg:province":"Limburg",
    "wof:name":"G. Minkenberg-Meijers Land- En Tuinbouwbenodigdhed",
    "wof:placetype":"venue"
},
  "geometry": {"coordinates":[6.054422,51.151558],"type":"Point"}
}