{
  "type": "Feature",
  "properties": {
    "addr:full":"Mauritskade 37 'S Gravenhage Zuid-Holland 2514 HE",
    "addr:housenumber":"37",
    "addr:postcode":"2514 he",
    "addr:street":"Mauritskade;' S",
    "iso:country":"NL",
    "sg:address":"Mauritskade 37",
    "sg:city":"'S Gravenhage",
    "sg:orig_category":"Werving And Selectie Van Vast Personeel",
    "sg:phone":"+31 70 364 0929",
    "sg:postcode":"2514 HE",
    "sg:province":"Zuid-Holland",
    "wof:name":"Toplink",
    "wof:placetype":"venue"
},
  "geometry": {"coordinates":[4.308465004,52.085105896],"type":"Point"}
}