{
  "type": "Feature",
  "properties": {
    "addr:full":"Varkenmarkt 61 Dordrecht South Holland 3311 BR",
    "addr:housenumber":"61",
    "addr:postcode":"3311 br",
    "addr:street":"Varkenmarkt",
    "iso:country":"NL",
    "sg:address":"Varkenmarkt 61",
    "sg:city":"Dordrecht",
    "sg:orig_category":"Autokeuringen",
    "sg:phone":"+31 78 631 6750",
    "sg:postcode":"3311 BR",
    "sg:province":"South Holland",
    "wof:name":"K.F. Bolger",
    "wof:placetype":"venue"
},
  "geometry": {"coordinates":[4.664647,51.815815],"type":"Point"}
}