{
  "type": "Feature",
  "properties": {
    "addr:full":"Zirkoon 11 Venlo Limburg 5912 SW",
    "addr:housenumber":"11",
    "addr:postcode":"5912 sw",
    "addr:street":"Zirkoon",
    "iso:country":"NL",
    "sg:address":"Zirkoon 11",
    "sg:city":"Venlo",
    "sg:orig_category":"Partycatering And -Organisatie",
    "sg:phone":"+31 77 351 7280",
    "sg:postcode":"5912 SW",
    "sg:province":"Limburg",
    "wof:name":"Paul Scheelings Party Catering & Surprise Ontbijt",
    "wof:placetype":"venue"
},
  "geometry": {"coordinates":[6.168422,51.353786],"type":"Point"}
}