{
  "type": "Feature",
  "properties": {
    "iso:country":"NL",
    "sg:address":"Westerhuisweg 10",
    "sg:city":"Harskamp",
    "sg:orig_category":"Autokeuringen",
    "sg:phone":"+31 318 461 307",
    "sg:postcode":"6732 GK",
    "sg:province":"Gelderland",
    "wof:name":"Garagebedrijf H. V. Roekel",
    "wof:placetype":"venue"
},
  "geometry": {"coordinates":[5.700707,52.133808],"type":"Point"}
}