{
  "type": "Feature",
  "properties": {
    "addr:full":"Ankerkd 31 Maastricht Limburg 6222 NL",
    "addr:housenumber":"31",
    "addr:postcode":"6222 nl",
    "addr:street":"Ankerkd",
    "iso:country":"NL",
    "sg:address":"Ankerkd 31",
    "sg:city":"Maastricht",
    "sg:classifiers":[
        {
            "category":"Retail",
            "subcategory":"Storage",
            "type":"Services"
        }
    ],
    "sg:phone":"+31 43 352 9898",
    "sg:postcode":"6222 NL",
    "sg:province":"Limburg",
    "sg:tags":[
        "op-",
        "en",
        "overslagbedrijven"
    ],
    "sg:website":"http://www.cws-bv.nl",
    "wof:name":"Chemical Warehouses And Services Bv",
    "wof:placetype":"venue"
},
  "geometry": {"coordinates":[5.71695,50.87904],"type":"Point"}
}