{
  "type": "Feature",
  "properties": {
    "addr:full":"Kornoelje 1 Tiel Gelderland 4007 TP",
    "addr:housenumber":"1",
    "addr:postcode":"4007",
    "addr:street":"Kornoelje;Gelderland",
    "iso:country":"NL",
    "sg:address":"Kornoelje 1",
    "sg:city":"Tiel",
    "sg:classifiers":[
        {
            "category":"Education",
            "subcategory":"Preschool",
            "type":"Public Place"
        }
    ],
    "sg:phone":"+31 344 632 604",
    "sg:postcode":"4007 TP",
    "sg:province":"Gelderland",
    "sg:tags":[
        "kleuteronderwijs",
        "basis-"
    ],
    "wof:name":"De Waayer Openbare Basisschool",
    "wof:placetype":"venue"
},
  "geometry": {"coordinates":[5.39976,51.87072],"type":"Point"}
}