{
  "type": "Feature",
  "properties": {
    "iso:country":"NL",
    "sg:address":"Kl Zonnedauw 9",
    "sg:city":"Velserbroek",
    "sg:orig_category":"Administratie- En Boekhoudkantoren",
    "sg:phone":"+31 23 539 2323",
    "sg:postcode":"1991 HS",
    "sg:province":"Noord-Holland",
    "wof:name":"Facet",
    "wof:placetype":"venue"
},
  "geometry": {"coordinates":[101.707611,3.1501],"type":"Point"}
}