{
  "type": "Feature",
  "properties": {
    "addr:full":"Parkwykln 108 Almere Flevoland 1326 DT",
    "addr:housenumber":"108",
    "addr:postcode":"1326 dt",
    "addr:street":"Flevoland",
    "iso:country":"NL",
    "sg:address":"Parkwykln 108",
    "sg:city":"Almere",
    "sg:orig_category":"Verzekeringen - Verzekeringskantoren",
    "sg:phone":"+31 36 537 8184",
    "sg:postcode":"1326 DT",
    "sg:province":"Flevoland",
    "wof:name":"Ruiter, C H De",
    "wof:placetype":"venue"
},
  "geometry": {"coordinates":[5.24996,52.368961],"type":"Point"}
}