{
  "type": "Feature",
  "properties": {
    "iso:country":"NL",
    "sg:address":"A V Nesstr 2",
    "sg:city":"S Hertogenbosch",
    "sg:orig_category":"Vertaalbureaus",
    "sg:phone":"+31 73 610 0599",
    "sg:postcode":"5224 GB",
    "sg:province":"North Brabant",
    "sg:website":"http://home.planet.nl/~yelpa000/",
    "wof:name":"Russisch Vertaalbureau",
    "wof:placetype":"venue"
},
  "geometry": {"coordinates":[5.25958,51.698631],"type":"Point"}
}