{
  "type": "Feature",
  "properties": {
    "iso:country":"NL",
    "sg:address":"Nabuccostr 12",
    "sg:city":"Amersfoort",
    "sg:orig_category":"Orthopedagogen",
    "sg:phone":"+31 33 472 9728",
    "sg:postcode":"3816 TS",
    "sg:province":"Utrecht",
    "wof:name":"Dijck, Ellen Van",
    "wof:placetype":"venue"
},
  "geometry": {"coordinates":[5.4116520882,52.1502494812],"type":"Point"}
}