{
  "type": "Feature",
  "properties": {
    "addr:full":"Molenstraat 114 Helmond Noord-Brabant 5701 KJ",
    "addr:housenumber":"114",
    "addr:postcode":"5701 kj",
    "addr:street":"Molenstraat",
    "iso:country":"NL",
    "sg:address":"Molenstraat 114",
    "sg:city":"Helmond",
    "sg:orig_category":"Vertaal- And Tolkenbureaus",
    "sg:phone":"+31 492 545 072",
    "sg:postcode":"5701 KJ",
    "sg:province":"Noord-Brabant",
    "wof:name":"Multitext Helmond",
    "wof:placetype":"venue"
},
  "geometry": {"coordinates":[5.664235,51.478619],"type":"Point"}
}