{
  "type": "Feature",
  "properties": {
    "addr:full":"Ridderlaan 4 Utrecht Utrecht 3523 HT",
    "addr:housenumber":"4",
    "addr:postcode":"3523 ht",
    "addr:street":"Ridderlaan",
    "iso:country":"NL",
    "sg:address":"Ridderlaan 4",
    "sg:city":"Utrecht",
    "sg:classifiers":[
        {
            "category":"Education",
            "subcategory":"Preschool",
            "type":"Public Place"
        }
    ],
    "sg:phone":"+31 30 288 1655",
    "sg:postcode":"3523 HT",
    "sg:province":"Utrecht",
    "sg:tags":[
        "kleuteronderwijs",
        "basis-"
    ],
    "wof:name":"Prot Chr Basisschool J.W. Van De Meene",
    "wof:placetype":"venue"
},
  "geometry": {"coordinates":[5.127713,52.069035],"type":"Point"}
}