{
  "type": "Feature",
  "properties": {
    "addr:full":"Gerstveld 1 Bergschenhoek South Holland 2661 VM",
    "addr:housenumber":"1",
    "addr:postcode":"2661 vm",
    "addr:street":"Gerstveld",
    "iso:country":"NL",
    "sg:address":"Gerstveld 1",
    "sg:city":"Bergschenhoek",
    "sg:orig_category":"Milieu",
    "sg:phone":"+31 10 522 4164",
    "sg:postcode":"2661 VM",
    "sg:province":"South Holland",
    "wof:name":"Reclaim Systems",
    "wof:placetype":"venue"
},
  "geometry": {"coordinates":[4.493118,51.989231],"type":"Point"}
}