{
  "type": "Feature",
  "properties": {
    "addr:full":"Zwedenburg 82 S Gravenhage South Holland 2591 BH",
    "addr:housenumber":"82",
    "addr:postcode":"2591 bh",
    "addr:street":"Zwedenburg;S Gravenhage",
    "iso:country":"NL",
    "sg:address":"Zwedenburg 82",
    "sg:city":"S Gravenhage",
    "sg:orig_category":"Verzekeringen - Verzekeringskantoren",
    "sg:phone":"+31 70 385 6108",
    "sg:postcode":"2591 BH",
    "sg:province":"South Holland",
    "wof:name":"Plesman",
    "wof:placetype":"venue"
},
  "geometry": {"coordinates":[4.3639,52.09351],"type":"Point"}
}