{
  "type": "Feature",
  "properties": {
    "addr:full":"Leeuwte 61 Sint Jansklooster NL.08 8326 AB",
    "addr:housenumber":"61",
    "addr:postcode":"nl.08 8326 ab",
    "addr:street":"Leeuwte",
    "iso:country":"NL",
    "sg:address":"Leeuwte 61",
    "sg:city":"Sint Jansklooster",
    "sg:orig_category":"Levende Dieren Gh",
    "sg:phone":"+31 527 246 502",
    "sg:postcode":"8326 AB",
    "sg:province":"NL.08",
    "wof:name":"Vof Veehandelsbedrijf Naberman",
    "wof:placetype":"venue"
},
  "geometry": {"coordinates":[5.997694,52.68782],"type":"Point"}
}