{
  "type": "Feature",
  "properties": {
    "addr:full":"Keizersgr 328 Amsterdam North Holland 1016 EZ",
    "addr:housenumber":"328",
    "addr:postcode":"1016 ez",
    "iso:country":"NL",
    "sg:address":"Keizersgr 328",
    "sg:city":"Amsterdam",
    "sg:orig_category":"Makelaars En Adviseurs Onroerende Goederen",
    "sg:phone":"+31 20 622 2922",
    "sg:postcode":"1016 EZ",
    "sg:province":"North Holland",
    "wof:name":"Havik & Havik, Makelaars O/G",
    "wof:placetype":"venue"
},
  "geometry": {"coordinates":[4.884143,52.370041],"type":"Point"}
}