{
  "type": "Feature",
  "properties": {
    "iso:country":"NL",
    "sg:address":"Kervelsewg 14",
    "sg:city":"Hengelo Gld",
    "sg:orig_category":"Betonwerken",
    "sg:phone":"+31 6 53558131",
    "sg:postcode":"7255 BG",
    "sg:province":"Gelderland",
    "wof:name":"Kok Vof",
    "wof:placetype":"venue"
},
  "geometry": {"coordinates":[6.306351,52.053139],"type":"Point"}
}