{
  "type": "Feature",
  "properties": {
    "addr:full":"Kasteel Kessenichstraat 5 Roermond Limburg 6043 XZ",
    "addr:housenumber":"5",
    "addr:postcode":"6043 xz",
    "addr:street":"Kasteel Kessenichstraat",
    "iso:country":"NL",
    "sg:address":"Kasteel Kessenichstraat 5",
    "sg:city":"Roermond",
    "sg:orig_category":"Bedrijfs- And Managementsconsultants",
    "sg:phone":"+31 475 328 932",
    "sg:postcode":"6043 XZ",
    "sg:province":"Limburg",
    "wof:name":"Bureau Olav J.M.J. Moonen",
    "wof:placetype":"venue"
},
  "geometry": {"coordinates":[6.009346,51.188354],"type":"Point"}
}