{
  "type": "Feature",
  "properties": {
    "addr:full":"Negen-Novemberweg 19 Venlo Limburg 5916 LD",
    "addr:housenumber":"19",
    "addr:postcode":"5916 ld",
    "addr:street":"Negen-Novemberweg",
    "iso:country":"NL",
    "sg:address":"Negen-Novemberweg 19",
    "sg:city":"Venlo",
    "sg:orig_category":"Bloemen And Planten Gh",
    "sg:phone":"+31 77 320 0410",
    "sg:postcode":"5916 LD",
    "sg:province":"Limburg",
    "wof:name":"Zuiderplant Bv",
    "wof:placetype":"venue"
},
  "geometry": {"coordinates":[6.208611,51.381035],"type":"Point"}
}