{
  "type": "Feature",
  "properties": {
    "addr:full":"Vyzelstr 19 Arnhem Gelderland 6811 ET",
    "addr:housenumber":"19",
    "addr:postcode":"6811 et",
    "addr:street":"Vyzelstr",
    "iso:country":"NL",
    "sg:address":"Vyzelstr 19",
    "sg:city":"Arnhem",
    "sg:orig_category":"Huishoudelijke Apparaten En Artikelen",
    "sg:phone":"+31 26 351 4142",
    "sg:postcode":"6811 ET",
    "sg:province":"Gelderland",
    "wof:name":"Blokker Bv",
    "wof:placetype":"venue"
},
  "geometry": {"coordinates":[5.907506,51.981499],"type":"Point"}
}