{
  "type": "Feature",
  "properties": {
    "addr:full":"Raadhuisstraat 22 Vorden Gelderland 7251 AB",
    "addr:housenumber":"22",
    "addr:postcode":"7251 ab",
    "addr:street":"Raadhuisstraat;Gelderland",
    "iso:country":"NL",
    "sg:address":"Raadhuisstraat 22",
    "sg:city":"Vorden",
    "sg:orig_category":"Boekhouders",
    "sg:phone":"+31 575 551 455",
    "sg:postcode":"7251 AB",
    "sg:province":"Gelderland",
    "wof:name":"Administratie- En Belastingadv Robbers & Partners",
    "wof:placetype":"venue"
},
  "geometry": {"coordinates":[6.311778,52.102684],"type":"Point"}
}