{
  "type": "Feature",
  "properties": {
    "addr:full":"Rodenbachstr 17 S Gravenhage Zuid-Holland 2523 JH",
    "addr:housenumber":"17;gravenhage",
    "addr:postcode":"2523 jh",
    "addr:street":"Rodenbachstr;S",
    "iso:country":"NL",
    "sg:address":"Rodenbachstr 17",
    "sg:city":"S Gravenhage",
    "sg:orig_category":"Kisten - Fabrieken En Groothandel",
    "sg:phone":"+31 182 644 440",
    "sg:postcode":"2523 JH",
    "sg:province":"Zuid-Holland",
    "wof:name":"Aad Zuidwijk",
    "wof:placetype":"venue"
},
  "geometry": {"coordinates":[4.31927,52.056469],"type":"Point"}
}