{
  "type": "Feature",
  "properties": {
    "iso:country":"NL",
    "sg:address":"De Beente 66A",
    "sg:city":"Maastricht",
    "sg:orig_category":"Postkantoren",
    "sg:phone":"+31 43 367 2273",
    "sg:postcode":"6229 AV",
    "sg:province":"Limburg",
    "sg:website":"http://www.postkantoor.nl",
    "wof:name":"Postkantoor",
    "wof:placetype":"venue"
},
  "geometry": {"coordinates":[5.704172,50.831581],"type":"Point"}
}