{
  "type": "Feature",
  "properties": {
    "addr:full":"J V Galenstr 76 Amsterdam Noord-Holland 1056 CC",
    "addr:housenumber":"76",
    "addr:postcode":"1056 cc",
    "addr:street":"J;Galenstr",
    "iso:country":"NL",
    "sg:address":"J V Galenstr 76",
    "sg:city":"Amsterdam",
    "sg:orig_category":"Meubelmakerijen",
    "sg:phone":"+31 20 612 4236",
    "sg:postcode":"1056 CC",
    "sg:province":"Noord-Holland",
    "wof:name":"Abc Huis",
    "wof:placetype":"venue"
},
  "geometry": {"coordinates":[4.85478,52.373699],"type":"Point"}
}