{
  "type": "Feature",
  "properties": {
    "addr:full":"Pr Hendrikkd 176 Amsterdam North Holland 1011 TC",
    "addr:housenumber":"176",
    "addr:postcode":"1011 tc",
    "iso:country":"NL",
    "sg:address":"Pr Hendrikkd 176",
    "sg:city":"Amsterdam",
    "sg:orig_category":"Psychotechniek",
    "sg:phone":"+31 20 489 1253",
    "sg:postcode":"1011 TC",
    "sg:province":"North Holland",
    "wof:name":"Mind At Work",
    "wof:placetype":"venue"
},
  "geometry": {"coordinates":[4.910191,52.371559],"type":"Point"}
}