{
  "type": "Feature",
  "properties": {
    "addr:full":"Fazant 8 Sprang-Capelle Noord-Brabant 5161 SC",
    "addr:housenumber":"8",
    "addr:postcode":"5161 sc",
    "addr:street":"Fazant",
    "iso:country":"NL",
    "sg:address":"Fazant 8",
    "sg:city":"Sprang-Capelle",
    "sg:orig_category":"Begrafenisondernemers",
    "sg:phone":"+31 416 275 342",
    "sg:postcode":"5161 SC",
    "sg:province":"Noord-Brabant",
    "wof:name":"Begrafenisvereniging De Laatste Eer",
    "wof:placetype":"venue"
},
  "geometry": {"coordinates":[5.0171,51.673206],"type":"Point"}
}