{
  "type": "Feature",
  "properties": {
    "addr:full":"Anjelierstr 123A Heerlen Limburg 6414 ES",
    "addr:housenumber":"123a",
    "addr:postcode":"6414 es",
    "iso:country":"NL",
    "sg:address":"Anjelierstr 123A",
    "sg:city":"Heerlen",
    "sg:orig_category":"Automaterialen En Gereedschappen",
    "sg:phone":"+31 45 523 2916",
    "sg:postcode":"6414 ES",
    "sg:province":"Limburg",
    "wof:name":"El\u00f6",
    "wof:placetype":"venue"
},
  "geometry": {"coordinates":[5.970539,50.923859],"type":"Point"}
}