{
  "type": "Feature",
  "properties": {
    "addr:full":"Postbus 168 De Meern Utrecht 3454 ZK",
    "addr:housenumber":"168",
    "addr:postcode":"3454",
    "addr:street":"Postbus",
    "iso:country":"NL",
    "sg:address":"Postbus 168",
    "sg:city":"De Meern",
    "sg:orig_category":"Organisatiebureaus",
    "sg:phone":"+31 30 666 6358",
    "sg:postcode":"3454 ZK",
    "sg:province":"Utrecht",
    "wof:name":"Exhibition Company, The",
    "wof:placetype":"venue"
},
  "geometry": {"coordinates":[5.0375199318,52.0789833069],"type":"Point"}
}