{
  "type": "Feature",
  "properties": {
    "addr:full":"Industriestr 74A Haaksbergen Overijssel 7482 EX",
    "addr:housenumber":"74a",
    "addr:postcode":"7482 ex",
    "addr:street":"Industriestr",
    "iso:country":"NL",
    "sg:address":"Industriestr 74A",
    "sg:city":"Haaksbergen",
    "sg:orig_category":"Grafmonumenten",
    "sg:phone":"+31 53 574 3902",
    "sg:postcode":"7482 EX",
    "sg:province":"Overijssel",
    "sg:website":"http://www.rustenburgnatuursteen.nl",
    "wof:name":"Rustenburg",
    "wof:placetype":"venue"
},
  "geometry": {"coordinates":[6.724756,52.152447],"type":"Point"}
}