{
  "type": "Feature",
  "properties": {
    "iso:country":"NL",
    "sg:address":"Kortestraat 22",
    "sg:city":"Arnhem",
    "sg:orig_category":"Kappers",
    "sg:phone":"+31 26 442 1408",
    "sg:postcode":"6811 EP",
    "sg:province":"Gelderland",
    "wof:name":"Miranda'S Hairstyling",
    "wof:placetype":"venue"
},
  "geometry": {"coordinates":[5.905065,51.981026],"type":"Point"}
}