{
  "type": "Feature",
  "properties": {
    "addr:full":"Palmstr 79 Amsterdam North Holland 1015 HP",
    "addr:housenumber":"79",
    "addr:postcode":"1015 hp",
    "addr:street":"Palmstr",
    "iso:country":"NL",
    "sg:address":"Palmstr 79",
    "sg:city":"Amsterdam",
    "sg:orig_category":"Parketvloeren",
    "sg:phone":"+31 20 625 2544",
    "sg:postcode":"1015 HP",
    "sg:province":"North Holland",
    "wof:name":"Gelderblom",
    "wof:placetype":"venue"
},
  "geometry": {"coordinates":[4.882764,52.381371],"type":"Point"}
}