{
  "type": "Feature",
  "properties": {
    "addr:full":"Kap Nausstr 33 Venlo Limburg 5915 BA",
    "addr:housenumber":"33",
    "addr:postcode":"5915 ba",
    "iso:country":"NL",
    "sg:address":"Kap Nausstr 33",
    "sg:city":"Venlo",
    "sg:orig_category":"Fotoreportages",
    "sg:phone":"+31 77 351 3284",
    "sg:postcode":"5915 BA",
    "sg:province":"Limburg",
    "wof:name":"Stefels",
    "wof:placetype":"venue"
},
  "geometry": {"coordinates":[6.181645,51.356457],"type":"Point"}
}