{
  "type": "Feature",
  "properties": {
    "addr:full":"Maandereind 14 Ede Gld Gelderland 6711 AC",
    "addr:housenumber":"14",
    "addr:postcode":"6711 ac",
    "addr:street":"Maandereind;Gld Gelderland",
    "iso:country":"NL",
    "sg:address":"Maandereind 14",
    "sg:city":"Ede Gld",
    "sg:orig_category":"Goederenvervoer Over De Weg",
    "sg:phone":"+31 318 617 062",
    "sg:postcode":"6711 AC",
    "sg:province":"Gelderland",
    "wof:name":"Jeroen De Jong Internationaal Transport",
    "wof:placetype":"venue"
},
  "geometry": {"coordinates":[5.669317,52.043274],"type":"Point"}
}