{
  "type": "Feature",
  "properties": {
    "addr:full":"Uitheying 4 Lemmer Friesland 8531 XJ",
    "addr:housenumber":"4",
    "addr:postcode":"8531 xj",
    "addr:street":"Uitheying",
    "iso:country":"NL",
    "sg:address":"Uitheying 4",
    "sg:city":"Lemmer",
    "sg:orig_category":"Straalbedrijven",
    "sg:phone":"+31 514 566 121",
    "sg:postcode":"8531 XJ",
    "sg:province":"Friesland",
    "wof:name":"Hardstraal Bv",
    "wof:placetype":"venue"
},
  "geometry": {"coordinates":[5.712385,52.844051],"type":"Point"}
}