{
  "type": "Feature",
  "properties": {
    "addr:full":"Nispensestraat 65 Roosendaal Noord-Brabant 4701 CT",
    "addr:housenumber":"65",
    "addr:postcode":"4701 ct",
    "addr:street":"Nispensestraat",
    "iso:country":"NL",
    "sg:address":"Nispensestraat 65",
    "sg:city":"Roosendaal",
    "sg:orig_category":"Hypotheken And Hypotheekbanken",
    "sg:phone":"+31 165 555 330",
    "sg:postcode":"4701 CT",
    "sg:province":"Noord-Brabant",
    "wof:name":"Hypotheek Visie Roosendaal",
    "wof:placetype":"venue"
},
  "geometry": {"coordinates":[4.459116,51.529636],"type":"Point"}
}