{
  "type": "Feature",
  "properties": {
    "addr:full":"Lutkenieuwstr 5 Groningen Groningen 9712 AW",
    "addr:housenumber":"5",
    "addr:postcode":"9712 aw",
    "addr:street":"Lutkenieuwstr",
    "iso:country":"NL",
    "sg:address":"Lutkenieuwstr 5",
    "sg:city":"Groningen",
    "sg:orig_category":"Kappers",
    "sg:phone":"+31 50 360 0318",
    "sg:postcode":"9712 AW",
    "sg:province":"Groningen",
    "wof:name":"D'Ukkie",
    "wof:placetype":"venue"
},
  "geometry": {"coordinates":[6.561560154,53.216960907],"type":"Point"}
}