{
  "type": "Feature",
  "properties": {
    "addr:full":"Grote Noord 8 Hoorn Nh North Holland 1621 KJ",
    "addr:housenumber":"8",
    "addr:postcode":"1621 kj",
    "addr:street":"Grote Noord;Nh North",
    "iso:country":"NL",
    "sg:address":"Grote Noord 8",
    "sg:city":"Hoorn Nh",
    "sg:orig_category":"Huishoudapparatuur, Televisies And Radio'S",
    "sg:phone":"+31 229 214 171",
    "sg:postcode":"1621 KJ",
    "sg:province":"North Holland",
    "wof:name":"Expert Moeijes & Hartog",
    "wof:placetype":"venue"
},
  "geometry": {"coordinates":[5.058657,52.639771],"type":"Point"}
}