{
  "type": "Feature",
  "properties": {
    "iso:country":"NL",
    "sg:address":"M Planckstr 5",
    "sg:city":"Ede Gld",
    "sg:orig_category":"Verpakkingen En Verpakkingsmaterialen",
    "sg:phone":"+31 318 664 664",
    "sg:postcode":"6716 BD",
    "sg:province":"Gelderland",
    "sg:website":"http://www.tcplasticum.nl",
    "wof:name":"Cate Plasticum Ede Bv, Ten",
    "wof:placetype":"venue"
},
  "geometry": {"coordinates":[5.62593,52.033653],"type":"Point"}
}