{
  "type": "Feature",
  "properties": {
    "addr:full":"Hoofdstraat 26 Meppel Provincie Drenthe 7941 AG",
    "addr:housenumber":"26",
    "addr:postcode":"7941",
    "addr:street":"Hoofdstraat;Provincie Drenthe",
    "iso:country":"NL",
    "sg:address":"Hoofdstraat 26",
    "sg:city":"Meppel",
    "sg:orig_category":"Wasserettes, Stomerijen And Reiniging",
    "sg:phone":"+31 522 244 066",
    "sg:postcode":"7941 AG",
    "sg:province":"Provincie Drenthe",
    "wof:name":"Stomerij Meinen",
    "wof:placetype":"venue"
},
  "geometry": {"coordinates":[6.1962947845,52.6996154785],"type":"Point"}
}