{
  "type": "Feature",
  "properties": {
    "iso:country":"NL",
    "sg:address":"Midstr 119",
    "sg:city":"Joure",
    "sg:orig_category":"Elektrotechnische Installatiebureaus",
    "sg:phone":"+31 513 410 678",
    "sg:postcode":"8501 AJ",
    "sg:province":"Friesland",
    "wof:name":"Boer, Fa Gebroeders De",
    "wof:placetype":"venue"
},
  "geometry": {"coordinates":[5.796785,52.9669],"type":"Point"}
}