{
  "type": "Feature",
  "properties": {
    "addr:full":"Hommelseweg 221 Arnhem Gelderland 6821 LG",
    "addr:housenumber":"221",
    "addr:postcode":"6821 lg",
    "addr:street":"Hommelseweg",
    "iso:country":"NL",
    "sg:address":"Hommelseweg 221",
    "sg:city":"Arnhem",
    "sg:orig_category":"Verlichting And Huishoudartikelen",
    "sg:phone":"+31 26 445 5111",
    "sg:postcode":"6821 LG",
    "sg:province":"Gelderland",
    "wof:name":"Gordijnenhal Malle Marietje",
    "wof:placetype":"venue"
},
  "geometry": {"coordinates":[5.916247,51.990181],"type":"Point"}
}