{
  "type": "Feature",
  "properties": {
    "iso:country":"NL",
    "sg:address":"Rivierdijk 635",
    "sg:city":"Hardinxveld Giessend",
    "sg:orig_category":"Daken And Skeletbouw",
    "sg:phone":"+31 184 617 977",
    "sg:postcode":"3371 EE",
    "sg:province":"Zuid-Holland",
    "wof:name":"Bbs Dakbedekkingen Bv",
    "wof:placetype":"venue"
},
  "geometry": {"coordinates":[4.847365,51.821388],"type":"Point"}
}