{
  "type": "Feature",
  "properties": {
    "addr:full":"Zwartsluisje 113 Zuid Beyerland South Holland 3284 LM",
    "addr:housenumber":"113",
    "addr:postcode":"3284 lm",
    "addr:street":"Zwartsluisje;Beyerland",
    "iso:country":"NL",
    "sg:address":"Zwartsluisje 113",
    "sg:city":"Zuid Beyerland",
    "sg:orig_category":"Loodgieters",
    "sg:phone":"+31 186 691 538",
    "sg:postcode":"3284 LM",
    "sg:province":"South Holland",
    "wof:name":"Boot, Fa",
    "wof:placetype":"venue"
},
  "geometry": {"coordinates":[4.324849,51.776588],"type":"Point"}
}