{
  "type": "Feature",
  "properties": {
    "addr:full":"Boeierstr 77 Purmerend North Holland 1443 EE",
    "addr:housenumber":"77",
    "addr:postcode":"1443 ee",
    "addr:street":"Boeierstr",
    "iso:country":"NL",
    "sg:address":"Boeierstr 77",
    "sg:city":"Purmerend",
    "sg:orig_category":"Verenigingen En Stichtingen",
    "sg:phone":"+31 299 428 504",
    "sg:postcode":"1443 EE",
    "sg:province":"North Holland",
    "wof:name":"Boeier, De",
    "wof:placetype":"venue"
},
  "geometry": {"coordinates":[4.969232,52.51128],"type":"Point"}
}