{
  "type": "Feature",
  "properties": {
    "addr:full":"Bos En Lommerwg 236 Amsterdam Noord-Holland 1055 EJ",
    "addr:housenumber":"236",
    "addr:postcode":"1055 ej",
    "addr:street":"Bos En Lommerwg",
    "iso:country":"NL",
    "sg:address":"Bos En Lommerwg 236",
    "sg:city":"Amsterdam",
    "sg:orig_category":"Kappers",
    "sg:phone":"+31 20 686 7059",
    "sg:postcode":"1055 EJ",
    "sg:province":"Noord-Holland",
    "wof:name":"Sabina'S",
    "wof:placetype":"venue"
},
  "geometry": {"coordinates":[4.849569,52.37891],"type":"Point"}
}