{
  "type": "Feature",
  "properties": {
    "addr:full":"Dam 13 Schiedam Zuid-Holland 3111 BC",
    "addr:housenumber":"13",
    "addr:postcode":"3111 bc",
    "addr:street":"Dam",
    "iso:country":"NL",
    "sg:address":"Dam 13",
    "sg:city":"Schiedam",
    "sg:orig_category":"Kappers",
    "sg:phone":"+31 10 273 0606",
    "sg:postcode":"3111 BC",
    "sg:province":"Zuid-Holland",
    "wof:name":"Mary'S Haarmode",
    "wof:placetype":"venue"
},
  "geometry": {"coordinates":[4.39816,51.918472],"type":"Point"}
}