{
  "type": "Feature",
  "properties": {
    "addr:full":"Dorpstraat 137 Luyksgestel North Brabant 5575 AG",
    "addr:housenumber":"137",
    "addr:postcode":"5575",
    "addr:street":"Dorpstraat",
    "iso:country":"NL",
    "sg:address":"Dorpstraat 137",
    "sg:city":"Luyksgestel",
    "sg:classifiers":[
        {
            "category":"Fast Food",
            "type":"Food & Drink"
        }
    ],
    "sg:phone":"+31 497 542 607",
    "sg:postcode":"5575 AG",
    "sg:province":"North Brabant",
    "sg:tags":[
        "afhaal",
        "restaurant"
    ],
    "wof:name":"Cafetaria Beeks",
    "wof:placetype":"venue"
},
  "geometry": {"coordinates":[5.316601,51.285099],"type":"Point"}
}