{
  "type": "Feature",
  "properties": {
    "addr:full":"Langewg 10 Middelharnis Zuid-Holland 3241 KA",
    "addr:housenumber":"10",
    "addr:postcode":"3241 ka",
    "addr:street":"Langewg",
    "iso:country":"NL",
    "sg:address":"Langewg 10",
    "sg:city":"Middelharnis",
    "sg:orig_category":"Postkantoren",
    "sg:phone":"+31 187 482 220",
    "sg:postcode":"3241 KA",
    "sg:province":"Zuid-Holland",
    "sg:website":"http://www.postkantoor.nl",
    "wof:name":"Postkantoor",
    "wof:placetype":"venue"
},
  "geometry": {"coordinates":[4.154987,51.760281],"type":"Point"}
}