{
  "type": "Feature",
  "properties": {
    "addr:full":"Postbus 367 Zwolle Louisiana 8000 AJ",
    "addr:housenumber":"367",
    "addr:postcode":"8000 aj",
    "addr:street":"Postbus;Louisiana",
    "iso:country":"NL",
    "sg:address":"Postbus 367",
    "sg:city":"Zwolle",
    "sg:orig_category":"Verenigingen En Stichtingen",
    "sg:phone":"+31 38 423 7619",
    "sg:postcode":"8000 AJ",
    "sg:province":"Louisiana",
    "wof:name":"Zwolsche Reddingsbrigade",
    "wof:placetype":"venue"
},
  "geometry": {"coordinates":[-93.643631,31.632046],"type":"Point"}
}