{
  "type": "Feature",
  "properties": {
    "iso:country":"NL",
    "sg:address":"Virulylaan 15",
    "sg:city":"Leidschendam",
    "sg:orig_category":"Boekhouders",
    "sg:phone":"+31 70 414 0009",
    "sg:postcode":"2267 BR",
    "sg:province":"Zuid-Holland",
    "wof:name":"Admin & Belast Advbur Wll Tabbers",
    "wof:placetype":"venue"
},
  "geometry": {"coordinates":[4.356747,52.058086],"type":"Point"}
}