{
  "type": "Feature",
  "properties": {
    "iso:country":"NL",
    "sg:address":"Warmenhovenstr 51",
    "sg:city":"Ymuiden",
    "sg:orig_category":"Zonweringen",
    "sg:phone":"+31 6 53941095",
    "sg:postcode":"1972 EB",
    "sg:province":"North Holland",
    "wof:name":"Wassink, T",
    "wof:placetype":"venue"
},
  "geometry": {"coordinates":[4.608312,52.460896],"type":"Point"}
}