{
  "type": "Feature",
  "properties": {
    "iso:country":"NL",
    "sg:address":"Azaleaduin 17",
    "sg:city":"Leiden",
    "sg:orig_category":"Loodgieterswerk, Verwarming And Sanitaire Installaties",
    "sg:phone":"+31 71 521 0866",
    "sg:postcode":"2318 XL",
    "sg:province":"Zuid-Holland",
    "wof:name":"Roest Warmteservice",
    "wof:placetype":"venue"
},
  "geometry": {"coordinates":[4.508496,52.182346],"type":"Point"}
}