{
  "type": "Feature",
  "properties": {
    "addr:full":"Schere 7 Rotterdam Zuid-Holland 3085 DT",
    "addr:housenumber":"7",
    "addr:postcode":"3085 dt",
    "addr:street":"Schere",
    "iso:country":"NL",
    "sg:address":"Schere 7",
    "sg:city":"Rotterdam",
    "sg:orig_category":"Wolartikelen En Breiwol",
    "sg:phone":"+31 10 481 0307",
    "sg:postcode":"3085 DT",
    "sg:province":"Zuid-Holland",
    "wof:name":"Jacqueline Handwerkstudio",
    "wof:placetype":"venue"
},
  "geometry": {"coordinates":[4.4939107895,51.8753547668],"type":"Point"}
}