{
  "type": "Feature",
  "properties": {
    "addr:full":"Biss Zwysenstr 77 Tilburg Noord-Brabant 5021 KA",
    "addr:housenumber":"77",
    "addr:postcode":"5021 ka",
    "iso:country":"NL",
    "sg:address":"Biss Zwysenstr 77",
    "sg:city":"Tilburg",
    "sg:orig_category":"Geluidsinstallaties - Verhuur",
    "sg:phone":"+31 13 536 3510",
    "sg:postcode":"5021 KA",
    "sg:province":"Noord-Brabant",
    "wof:name":"Hans V/D Ven",
    "wof:placetype":"venue"
},
  "geometry": {"coordinates":[5.09061,51.548569],"type":"Point"}
}