{
  "type": "Feature",
  "properties": {
    "addr:full":"Sloterweg 1052 Amsterdam Noord-Holland 1066 CT",
    "addr:housenumber":"1052",
    "addr:postcode":"1066 ct",
    "addr:street":"Sloterweg",
    "iso:country":"NL",
    "sg:address":"Sloterweg 1052",
    "sg:city":"Amsterdam",
    "sg:orig_category":"Drukkerijen And Copyshops",
    "sg:phone":"+31 20 617 9313",
    "sg:postcode":"1066 CT",
    "sg:province":"Noord-Holland",
    "wof:name":"Drukkerij Webbers",
    "wof:placetype":"venue"
},
  "geometry": {"coordinates":[4.805407,52.341492],"type":"Point"}
}