{
  "type": "Feature",
  "properties": {
    "addr:full":"Herenwal 75 Heerenveen Friesland 8441 BC",
    "addr:housenumber":"75",
    "addr:postcode":"8441 bc",
    "addr:street":"Herenwal",
    "iso:country":"NL",
    "sg:address":"Herenwal 75",
    "sg:city":"Heerenveen",
    "sg:orig_category":"Goederenvervoer Over De Weg",
    "sg:phone":"+31 513 610 659",
    "sg:postcode":"8441 BC",
    "sg:province":"Friesland",
    "wof:name":"Minkes Transport",
    "wof:placetype":"venue"
},
  "geometry": {"coordinates":[5.916643,52.962624],"type":"Point"}
}