{
  "type": "Feature",
  "properties": {
    "addr:full":"Kamp 3910 Lelystad NL. 8225 HJ",
    "addr:postcode":"3910;8225 hj",
    "addr:street":"Kamp;Nl.",
    "iso:country":"NL",
    "sg:address":"Kamp 3910",
    "sg:city":"Lelystad",
    "sg:orig_category":"Webdesign Bureaus",
    "sg:phone":"+31 320 232 621",
    "sg:postcode":"8225 HJ",
    "sg:province":"NL.",
    "wof:name":"Creatiefwebmaatwerk",
    "wof:placetype":"venue"
},
  "geometry": {"coordinates":[5.4877500534,52.5026473999],"type":"Point"}
}