{
  "type": "Feature",
  "properties": {
    "iso:country":"NL",
    "sg:address":"Pr Willem-Alexandersngl 28",
    "sg:city":"Beesd",
    "sg:orig_category":"Goederenvervoer Over De Weg",
    "sg:phone":"+31 345 683 210",
    "sg:postcode":"4153 BJ",
    "sg:province":"Gelderland",
    "wof:name":"Transport- En Opslagbedrijf R. Sneepels",
    "wof:placetype":"venue"
},
  "geometry": {"coordinates":[5.19254,51.889385],"type":"Point"}
}