{
  "type": "Feature",
  "properties": {
    "addr:full":"Marktstr 17 Naarden North Holland 1411 CX",
    "addr:housenumber":"17",
    "addr:postcode":"1411 cx",
    "addr:street":"Marktstr",
    "iso:country":"NL",
    "sg:address":"Marktstr 17",
    "sg:city":"Naarden",
    "sg:orig_category":"Kunstbemiddeling",
    "sg:phone":"+31 35 678 0220",
    "sg:postcode":"1411 CX",
    "sg:province":"North Holland",
    "wof:name":"Portret, Het",
    "wof:placetype":"venue"
},
  "geometry": {"coordinates":[5.163013,52.295853],"type":"Point"}
}