{
  "type": "Feature",
  "properties": {
    "iso:country":"NL",
    "sg:address":"Oyense Bovendk 5",
    "sg:city":"Oyen",
    "sg:orig_category":"Bejaarden - Verzorgingstehuizen",
    "sg:phone":"+31 412 492 408",
    "sg:postcode":"5394 AJ",
    "sg:province":"Noord-Brabant",
    "wof:name":"Zorg Voor Ouderen Maasland, Sticht",
    "wof:placetype":"venue"
},
  "geometry": {"coordinates":[-96.055939,42.820534],"type":"Point"}
}