{
  "type": "Feature",
  "properties": {
    "addr:full":"Kalverstraat 183 Amsterdam Noord-Holland 1012 XC",
    "addr:housenumber":"183",
    "addr:postcode":"1012 xc",
    "addr:street":"Kalverstraat",
    "iso:country":"NL",
    "sg:address":"Kalverstraat 183",
    "sg:city":"Amsterdam",
    "sg:orig_category":"Warenhuizen",
    "sg:phone":"+31 20 626 2162",
    "sg:postcode":"1012 XC",
    "sg:province":"Noord-Holland",
    "wof:name":"Maison De Bonneterie Bv",
    "wof:placetype":"venue"
},
  "geometry": {"coordinates":[4.8918418884,52.3679618835],"type":"Point"}
}