{
  "type": "Feature",
  "properties": {
    "addr:full":"Teteringsedk 28 Breda Noord-Brabant 4817 MG",
    "addr:housenumber":"28",
    "addr:postcode":"4817 mg",
    "addr:street":"Teteringsedk",
    "iso:country":"NL",
    "sg:address":"Teteringsedk 28",
    "sg:city":"Breda",
    "sg:orig_category":"Video - Faciliteiten En Producties",
    "sg:phone":"+31 76 522 4402",
    "sg:postcode":"4817 MG",
    "sg:province":"Noord-Brabant",
    "wof:name":"Hi-Fi Video Breda",
    "wof:placetype":"venue"
},
  "geometry": {"coordinates":[4.792719,51.594139],"type":"Point"}
}