{
  "type": "Feature",
  "properties": {
    "addr:full":"Postbus 23051 Rotterdam South Holland 3001 KB",
    "addr:housenumber":"23051",
    "addr:postcode":"3001 kb",
    "addr:street":"Postbus",
    "iso:country":"NL",
    "sg:address":"Postbus 23051",
    "sg:city":"Rotterdam",
    "sg:orig_category":"Verenigingen En Stichtingen",
    "sg:phone":"+31 10 206 8650",
    "sg:postcode":"3001 KB",
    "sg:province":"South Holland",
    "wof:name":"Rotterdams Indicatieorgaan, Sticht",
    "wof:placetype":"venue"
},
  "geometry": {"coordinates":[4.47075,51.922619],"type":"Point"}
}