{
  "type": "Feature",
  "properties": {
    "iso:country":"NL",
    "sg:address":"Hazelaarstr 31",
    "sg:city":"Woerden",
    "sg:orig_category":"Onderhoudswerken",
    "sg:phone":"+31 348 430 981",
    "sg:postcode":"3442 EM",
    "sg:province":"South Holland",
    "wof:name":"Broek, D Van Den",
    "wof:placetype":"venue"
},
  "geometry": {"coordinates":[4.875179,52.082077],"type":"Point"}
}