{
  "type": "Feature",
  "properties": {
    "iso:country":"NL",
    "sg:address":"S Vd Kolkstr 10",
    "sg:city":"Utrecht",
    "sg:orig_category":"Psychotherapeuten",
    "sg:phone":"+31 30 232 2731",
    "sg:postcode":"3511 HS",
    "sg:province":"Utrecht",
    "sg:website":"http://www.praktijkvoorpsychodrama.nl",
    "wof:name":"Praktijk Voor Psychodrama",
    "wof:placetype":"venue"
},
  "geometry": {"coordinates":[5.115405,52.088932],"type":"Point"}
}