{
  "type": "Feature",
  "properties": {
    "addr:full":"Stationstr 5 Boxtel North Brabant 5281 GA",
    "addr:housenumber":"5",
    "addr:postcode":"5281 ga",
    "addr:street":"Stationstr",
    "iso:country":"NL",
    "sg:address":"Stationstr 5",
    "sg:city":"Boxtel",
    "sg:orig_category":"Opticiens",
    "sg:phone":"+31 411 672 033",
    "sg:postcode":"5281 GA",
    "sg:province":"North Brabant",
    "wof:name":"Rens Doms, De Brillenshop",
    "wof:placetype":"venue"
},
  "geometry": {"coordinates":[5.3237261772,51.5881919861],"type":"Point"}
}