{
  "type": "Feature",
  "properties": {
    "addr:full":"Leidsestr 61 Amsterdam Noord-Holland 1017 NX",
    "addr:housenumber":"61",
    "addr:postcode":"1017 nx",
    "addr:street":"Leidsestr",
    "iso:country":"NL",
    "sg:address":"Leidsestr 61",
    "sg:city":"Amsterdam",
    "sg:orig_category":"Bijouterie?n - Fabrieken En Groothandel",
    "sg:phone":"+31 20 618 5311",
    "sg:postcode":"1017 NX",
    "sg:province":"Noord-Holland",
    "sg:website":"http://www.rodrigootazu.com",
    "wof:name":"Otazu",
    "wof:placetype":"venue"
},
  "geometry": {"coordinates":[4.885322,52.365349],"type":"Point"}
}