{
  "type": "Feature",
  "properties": {
    "iso:country":"NL",
    "sg:address":"Antillenstraat 20",
    "sg:city":"Amsterdam",
    "sg:orig_category":"Boekhouders",
    "sg:phone":"+31 20 616 1707",
    "sg:postcode":"1058 HB",
    "sg:province":"North Holland",
    "wof:name":"M & R Horeca Bv",
    "wof:placetype":"venue"
},
  "geometry": {"coordinates":[4.851322,52.359543],"type":"Point"}
}