{
  "type": "Feature",
  "properties": {
    "addr:full":"Rynzichtwg 153 Oegstgeest South Holland 2342 AZ",
    "addr:housenumber":"153",
    "addr:postcode":"2342 az",
    "iso:country":"NL",
    "sg:address":"Rynzichtwg 153",
    "sg:city":"Oegstgeest",
    "sg:orig_category":"Adviesbureaus Bouwkunde",
    "sg:phone":"+31 71 517 1642",
    "sg:postcode":"2342 AZ",
    "sg:province":"South Holland",
    "wof:name":"Zijlstra",
    "wof:placetype":"venue"
},
  "geometry": {"coordinates":[4.453048,52.178551],"type":"Point"}
}