{
  "type": "Feature",
  "properties": {
    "addr:full":"Venedien 25 Purmerend North Holland 1441 AK",
    "addr:housenumber":"25",
    "addr:postcode":"1441 ak",
    "addr:street":"Venedien",
    "iso:country":"NL",
    "sg:address":"Venedien 25",
    "sg:city":"Purmerend",
    "sg:orig_category":"Architecten En Architectenbureaus",
    "sg:phone":"+31 299 439 993",
    "sg:postcode":"1441 AK",
    "sg:province":"North Holland",
    "wof:name":"Rietvink Architecten Bv",
    "wof:placetype":"venue"
},
  "geometry": {"coordinates":[4.948546,52.510696],"type":"Point"}
}