{
  "type": "Feature",
  "properties": {
    "addr:full":"Slinge 600 Rotterdam Zuid-Holland 3086 EX",
    "addr:housenumber":"600",
    "addr:postcode":"3086 ex",
    "addr:street":"Slinge",
    "iso:country":"NL",
    "sg:address":"Slinge 600",
    "sg:city":"Rotterdam",
    "sg:orig_category":"Woningbureaus",
    "sg:phone":"+31 10 217 9090",
    "sg:postcode":"3086 EX",
    "sg:province":"Zuid-Holland",
    "wof:name":"Oke",
    "wof:placetype":"venue"
},
  "geometry": {"coordinates":[4.4686079025,51.8747024536],"type":"Point"}
}