{
  "type": "Feature",
  "properties": {
    "addr:full":"Doelenplein 6 Delft Zuid-Holland 2611 BP",
    "addr:housenumber":"6",
    "addr:postcode":"2611 bp",
    "addr:street":"Doelenplein",
    "iso:country":"NL",
    "sg:address":"Doelenplein 6",
    "sg:city":"Delft",
    "sg:orig_category":"Architecten",
    "sg:phone":"+31 15 212 0110",
    "sg:postcode":"2611 BP",
    "sg:province":"Zuid-Holland",
    "wof:name":"Dp6 Architectuurstudio Bv",
    "wof:placetype":"venue"
},
  "geometry": {"coordinates":[4.359456,52.014297],"type":"Point"}
}