{
  "type": "Feature",
  "properties": {
    "addr:full":"Havenstraat 197 Rotterdam Zuid-Holland 3024 SK",
    "addr:housenumber":"197",
    "addr:street":"Havenstraat;3024",
    "iso:country":"NL",
    "sg:address":"Havenstraat 197",
    "sg:city":"Rotterdam",
    "sg:orig_category":"Overheidsdiensten",
    "sg:phone":"+31 10 476 0847",
    "sg:postcode":"3024 SK",
    "sg:province":"Zuid-Holland",
    "wof:name":"Buurthuis De Helling",
    "wof:placetype":"venue"
},
  "geometry": {"coordinates":[4.4521870613,51.9058189392],"type":"Point"}
}