{
  "type": "Feature",
  "properties": {
    "addr:full":"Axelsestr 156 Terneuzen Zeeland 4537 AS",
    "addr:housenumber":"156",
    "addr:postcode":"4537 as",
    "iso:country":"NL",
    "sg:address":"Axelsestr 156",
    "sg:city":"Terneuzen",
    "sg:orig_category":"Drukkerijen",
    "sg:phone":"+31 115 613 072",
    "sg:postcode":"4537 AS",
    "sg:province":"Zeeland",
    "wof:name":"Bareman Bv",
    "wof:placetype":"venue"
},
  "geometry": {"coordinates":[3.835331,51.328392],"type":"Point"}
}