{
  "type": "Feature",
  "properties": {
    "addr:full":"Lagewg 11 Burgh Haamstede Zeeland 4328 RR",
    "addr:housenumber":"11",
    "addr:postcode":"4328 rr",
    "addr:street":"Lagewg;Haamstede",
    "iso:country":"NL",
    "sg:address":"Lagewg 11",
    "sg:city":"Burgh Haamstede",
    "sg:orig_category":"Vakantieverblijven",
    "sg:phone":"+31 111 654 447",
    "sg:postcode":"4328 RR",
    "sg:province":"Zeeland",
    "wof:name":"Zeester",
    "wof:placetype":"venue"
},
  "geometry": {"coordinates":[3.712323,51.675587],"type":"Point"}
}