{
  "type": "Feature",
  "properties": {
    "addr:full":"A H G Fokkerstr 28 Assen Drenthe 9403 AP",
    "addr:housenumber":"28",
    "addr:postcode":"9403 ap",
    "addr:street":"A",
    "iso:country":"NL",
    "sg:address":"A H G Fokkerstr 28",
    "sg:city":"Assen",
    "sg:classifiers":[
        {
            "category":"Retail",
            "subcategory":"Auto Repair",
            "type":"Services"
        }
    ],
    "sg:phone":"+31 592 313 181",
    "sg:postcode":"9403 AP",
    "sg:province":"Drenthe",
    "sg:tags":[
        "garage"
    ],
    "wof:name":"Tappel Bv, H J",
    "wof:placetype":"venue"
},
  "geometry": {"coordinates":[6.58091,53.006443],"type":"Point"}
}