{
  "type": "Feature",
  "properties": {
    "addr:full":"L Spaanderln 25 Volendam North Holland 1132 BP",
    "addr:housenumber":"25",
    "addr:postcode":"1132 bp",
    "iso:country":"NL",
    "sg:address":"L Spaanderln 25",
    "sg:city":"Volendam",
    "sg:orig_category":"Administratie- En Boekhoudkantoren",
    "sg:phone":"+31 299 321 650",
    "sg:postcode":"1132 BP",
    "sg:province":"North Holland",
    "wof:name":"Keizer, Th",
    "wof:placetype":"venue"
},
  "geometry": {"coordinates":[5.053201,52.495964],"type":"Point"}
}