{
  "type": "Feature",
  "properties": {
    "addr:full":"Tesselschadestr 5 Barneveld Gelderland 3771 ZC",
    "addr:housenumber":"5",
    "addr:postcode":"3771 zc",
    "addr:street":"Tesselschadestr;Gelderland",
    "iso:country":"NL",
    "sg:address":"Tesselschadestr 5",
    "sg:city":"Barneveld",
    "sg:orig_category":"Schilders",
    "sg:phone":"+31 342 423 883",
    "sg:postcode":"3771 ZC",
    "sg:province":"Gelderland",
    "wof:name":"Dokke",
    "wof:placetype":"venue"
},
  "geometry": {"coordinates":[5.568554,52.141567],"type":"Point"}
}