{
  "type": "Feature",
  "properties": {
    "iso:country":"NL",
    "sg:address":"Laurillardlaan 29",
    "sg:city":"Bilthoven",
    "sg:orig_category":"Boekenuitgeverijen",
    "sg:phone":"+31 30 228 8147",
    "sg:postcode":"3723 DL",
    "sg:province":"Utrecht",
    "wof:name":"Mundt Print & Bookmarketing",
    "wof:placetype":"venue"
},
  "geometry": {"coordinates":[5.214688,52.134254],"type":"Point"}
}