{
  "type": "Feature",
  "properties": {
    "addr:full":"Roskam 17 Berlicum Nb Noord-Brabant 5258 JE",
    "addr:housenumber":"17",
    "addr:postcode":"5258 je",
    "addr:street":"Roskam",
    "iso:country":"NL",
    "sg:address":"Roskam 17",
    "sg:city":"Berlicum Nb",
    "sg:orig_category":"Kinderopvang Behalve Thuis",
    "sg:phone":"+31 73 503 3302",
    "sg:postcode":"5258 JE",
    "sg:province":"Noord-Brabant",
    "wof:name":"T Beertjeshuis Kinderopvang",
    "wof:placetype":"venue"
},
  "geometry": {"coordinates":[5.401422,51.674568],"type":"Point"}
}