{
  "type": "Feature",
  "properties": {
    "iso:country":"NL",
    "sg:address":"Spechtln 24",
    "sg:city":"Leidschendam",
    "sg:orig_category":"Petrochemische Industrie",
    "sg:phone":"+31 70 306 5400",
    "sg:postcode":"2261 BL",
    "sg:province":"Zuid-Holland",
    "wof:name":"Upts Nederland Bv",
    "wof:placetype":"venue"
},
  "geometry": {"coordinates":[4.389408,52.09737],"type":"Point"}
}