{
  "type": "Feature",
  "properties": {
    "iso:country":"NL",
    "sg:address":"Dolderstr 8",
    "sg:city":"Wageningen",
    "sg:orig_category":"Verenigingen En Stichtingen",
    "sg:phone":"+31 317 425 999",
    "sg:postcode":"6706 JE",
    "sg:province":"Gelderland",
    "sg:website":"http://www.bergrace.nl",
    "wof:name":"Berg Tot Berg Race, Sticht Van",
    "wof:placetype":"venue"
},
  "geometry": {"coordinates":[5.67278,51.977371],"type":"Point"}
}