{
  "type": "Feature",
  "properties": {
    "iso:country":"NL",
    "sg:address":"Hefswalsterwg 19",
    "sg:city":"Uithuizermeeden",
    "sg:classifiers":[
        {
            "category":"Retail",
            "subcategory":"Auto Repair",
            "type":"Services"
        }
    ],
    "sg:phone":"+31 595 412 553",
    "sg:postcode":"9982 TP",
    "sg:province":"Groningen",
    "sg:tags":[
        "garage"
    ],
    "wof:name":"Sietsema Bv",
    "wof:placetype":"venue"
},
  "geometry": {"coordinates":[6.739822,53.42503],"type":"Point"}
}