{
  "type": "Feature",
  "properties": {
    "addr:full":"Rauwenhoffstraat 39 Rotterdam Zuid-Holland 3022 RL",
    "addr:housenumber":"39",
    "addr:postcode":"3022 rl",
    "addr:street":"Rauwenhoffstraat",
    "iso:country":"NL",
    "sg:address":"Rauwenhoffstraat 39",
    "sg:city":"Rotterdam",
    "sg:orig_category":"Overheidsdiensten",
    "sg:phone":"+31 10 478 0773",
    "sg:postcode":"3022 RL",
    "sg:province":"Zuid-Holland",
    "wof:name":"St Wimasanga",
    "wof:placetype":"venue"
},
  "geometry": {"coordinates":[4.4468588829,51.9177856445],"type":"Point"}
}