{
  "type": "Feature",
  "properties": {
    "addr:full":"Wolphaertsbocht 62 Rotterdam Zuid-Holland 3082 AP",
    "addr:housenumber":"62",
    "addr:postcode":"3082 ap",
    "addr:street":"Wolphaertsbocht",
    "iso:country":"NL",
    "sg:address":"Wolphaertsbocht 62",
    "sg:city":"Rotterdam",
    "sg:orig_category":"Kappers",
    "sg:phone":"+31 10 429 5126",
    "sg:postcode":"3082 AP",
    "sg:province":"Zuid-Holland",
    "wof:name":"J M Minderman",
    "wof:placetype":"venue"
},
  "geometry": {"coordinates":[4.4691371918,51.8934211731],"type":"Point"}
}