{
  "type": "Feature",
  "properties": {
    "addr:full":"Burg Neetstr 6-8 Ouderkerk Ad Yssel Zuid-Holland 2935 BB",
    "addr:housenumber":"6-8",
    "addr:postcode":"2935 bb",
    "addr:street":"Burg",
    "iso:country":"NL",
    "sg:address":"Burg Neetstr 6-8",
    "sg:city":"Ouderkerk Ad Yssel",
    "sg:orig_category":"Bejaarden - Verzorgingstehuizen",
    "sg:phone":"+31 180 681 778",
    "sg:postcode":"2935 BB",
    "sg:province":"Zuid-Holland",
    "wof:name":"Geerestein",
    "wof:placetype":"venue"
},
  "geometry": {"coordinates":[4.637585,51.932926],"type":"Point"}
}