{
  "type": "Feature",
  "properties": {
    "addr:full":"Peperstraat 9 Beverwijk Noord-Holland 1941 GA",
    "addr:housenumber":"9",
    "addr:postcode":"1941 ga",
    "addr:street":"Peperstraat",
    "iso:country":"NL",
    "sg:address":"Peperstraat 9",
    "sg:city":"Beverwijk",
    "sg:orig_category":"Meubelzaken, Woning- And Keukeninrichting",
    "sg:phone":"+31 251 215 777",
    "sg:postcode":"1941 GA",
    "sg:province":"Noord-Holland",
    "wof:name":"Hollandivani",
    "wof:placetype":"venue"
},
  "geometry": {"coordinates":[-83.222931,32.678131],"type":"Point"}
}