{
  "type": "Feature",
  "properties": {
    "addr:full":"Westerstraat 96 Amsterdam Noord-Holland 1015 MN",
    "addr:housenumber":"96",
    "addr:postcode":"1015 mn",
    "addr:street":"Westerstraat",
    "iso:country":"NL",
    "sg:address":"Westerstraat 96",
    "sg:city":"Amsterdam",
    "sg:orig_category":"Boekenuitgeverijen",
    "sg:phone":"+31 20 626 8509",
    "sg:postcode":"1015 MN",
    "sg:province":"Noord-Holland",
    "wof:name":"Boekhandel Het Griekse Eiland",
    "wof:placetype":"venue"
},
  "geometry": {"coordinates":[4.883754,52.378674],"type":"Point"}
}