{
  "type": "Feature",
  "properties": {
    "iso:country":"NL",
    "sg:address":"Westerstraat 96",
    "sg:city":"Amsterdam",
    "sg:orig_category":"Boekenuitgeverijen",
    "sg:phone":"+31 20 626 8509",
    "sg:postcode":"1015 MN",
    "sg:province":"Noord-Holland",
    "wof:name":"Boekhandel Het Griekse Eiland",
    "wof:placetype":"venue"
},
  "geometry": {"coordinates":[4.883754,52.378674],"type":"Point"}
}