{
  "type": "Feature",
  "properties": {
    "addr:full":"Noordereinde 70 'S Graveland Noord-Holland 1243 JJ",
    "addr:housenumber":"70",
    "addr:postcode":"1243 jj",
    "addr:street":"Noordereinde;' S",
    "iso:country":"NL",
    "sg:address":"Noordereinde 70",
    "sg:city":"'S Graveland",
    "sg:orig_category":"Metaalwerken",
    "sg:phone":"+31 35 656 3565",
    "sg:postcode":"1243 JJ",
    "sg:province":"Noord-Holland",
    "wof:name":"D.J. De Gooijer",
    "wof:placetype":"venue"
},
  "geometry": {"coordinates":[5.123869,52.25843],"type":"Point"}
}