{
  "type": "Feature",
  "properties": {
    "iso:country":"NL",
    "sg:address":"Weitjeswg 12",
    "sg:city":"Brakel",
    "sg:orig_category":"Architecten En Architectenbureaus",
    "sg:phone":"+31 418 671 944",
    "sg:postcode":"5306 XW",
    "sg:province":"Gelderland",
    "wof:name":"Zwanziger Bv",
    "wof:placetype":"venue"
},
  "geometry": {"coordinates":[5.087712,51.81464],"type":"Point"}
}