{
  "type": "Feature",
  "properties": {
    "addr:full":"Dionestr 12 Oudorp Nh Noord-Holland 1829 CB",
    "addr:housenumber":"12",
    "addr:postcode":"1829 cb",
    "addr:street":"Dionestr",
    "iso:country":"NL",
    "sg:address":"Dionestr 12",
    "sg:city":"Oudorp Nh",
    "sg:orig_category":"Administratie- En Boekhoudkantoren",
    "sg:phone":"+31 72 512 1330",
    "sg:postcode":"1829 CB",
    "sg:province":"Noord-Holland",
    "wof:name":"Hoet, A J C",
    "wof:placetype":"venue"
},
  "geometry": {"coordinates":[4.7761888504,52.6302719116],"type":"Point"}
}