{
  "type": "Feature",
  "properties": {
    "addr:full":"Frankenthalerstr 6 Breda Noord-Brabant 4816 KA",
    "addr:housenumber":"6",
    "addr:postcode":"4816 ka",
    "addr:street":"Frankenthalerstr",
    "iso:country":"NL",
    "sg:address":"Frankenthalerstr 6",
    "sg:city":"Breda",
    "sg:orig_category":"Verenigingen En Stichtingen",
    "sg:phone":"+31 76 571 1983",
    "sg:postcode":"4816 KA",
    "sg:province":"Noord-Brabant",
    "wof:name":"Schweitzer, Scouting A",
    "wof:placetype":"venue"
},
  "geometry": {"coordinates":[4.801391,51.597813],"type":"Point"}
}