{
  "type": "Feature",
  "properties": {
    "addr:full":"Titus Brandsmastraat 15 Brunssum Limburg 6441 LD",
    "addr:housenumber":"15",
    "addr:postcode":"6441 ld",
    "addr:street":"Titus Brandsmastraat",
    "iso:country":"NL",
    "sg:address":"Titus Brandsmastraat 15",
    "sg:city":"Brunssum",
    "sg:orig_category":"Huizensloop And Bouwrijp Maken",
    "sg:phone":"+31 45 525 3016",
    "sg:postcode":"6441 LD",
    "sg:province":"Limburg",
    "wof:name":"Leo Rutten Bv",
    "wof:placetype":"venue"
},
  "geometry": {"coordinates":[5.956116,50.953758],"type":"Point"}
}