{
  "type": "Feature",
  "properties": {
    "addr:full":"A Kuylstr 63 Rotterdam Zuid-Holland 3066 GS",
    "addr:housenumber":"63",
    "addr:postcode":"3066 gs",
    "iso:country":"NL",
    "sg:address":"A Kuylstr 63",
    "sg:city":"Rotterdam",
    "sg:orig_category":"Modellenbureaus En Modellen Freelance",
    "sg:phone":"+31 10 209 6409",
    "sg:postcode":"3066 GS",
    "sg:province":"Zuid-Holland",
    "sg:website":"http://www.xyloniteenjoyment.nl",
    "wof:name":"Xylonite Enjoyment",
    "wof:placetype":"venue"
},
  "geometry": {"coordinates":[4.55005,51.934711],"type":"Point"}
}