{
  "type": "Feature",
  "properties": {
    "iso:country":"NL",
    "sg:address":"Stephensonstr 23",
    "sg:city":"Hoogeveen",
    "sg:orig_category":"Wasmachines En Wasdrogers",
    "sg:phone":"+31 528 262 036",
    "sg:postcode":"7903 AS",
    "sg:province":"Provincie Drenthe",
    "wof:name":"Expert",
    "wof:placetype":"venue"
},
  "geometry": {"coordinates":[6.5121240616,52.7292861938],"type":"Point"}
}