{
  "type": "Feature",
  "properties": {
    "addr:full":"Bronckhorststraat 6 Amsterdam North Holland 1071 WR",
    "addr:housenumber":"6",
    "addr:postcode":"1071 wr",
    "addr:street":"Bronckhorststraat",
    "iso:country":"NL",
    "sg:address":"Bronckhorststraat 6",
    "sg:city":"Amsterdam",
    "sg:orig_category":"Fotostudio'S And Fotografen",
    "sg:phone":"+31 20 679 2582",
    "sg:postcode":"1071 WR",
    "sg:province":"North Holland",
    "wof:name":"Andy Tan Bv",
    "wof:placetype":"venue"
},
  "geometry": {"coordinates":[4.881261,52.353218],"type":"Point"}
}