{
  "type": "Feature",
  "properties": {
    "addr:full":"Provincialewg 196 Opende Groningen 9865 TB",
    "addr:housenumber":"196",
    "addr:postcode":"9865 tb",
    "iso:country":"NL",
    "sg:address":"Provincialewg 196",
    "sg:city":"Opende",
    "sg:orig_category":"Bruidskleding",
    "sg:phone":"+31 594 659 090",
    "sg:postcode":"9865 TB",
    "sg:province":"Groningen",
    "sg:website":"http://www.interindex.nl/eringa.htm",
    "wof:name":"Bert Eringa",
    "wof:placetype":"venue"
},
  "geometry": {"coordinates":[6.228557,53.177433],"type":"Point"}
}