{
  "type": "Feature",
  "properties": {
    "iso:country":"NL",
    "sg:address":"Zevenwouden 220-222",
    "sg:city":"Utrecht",
    "sg:orig_category":"Postkantoren",
    "sg:phone":"+31 30 289 4891",
    "sg:postcode":"3524 CX",
    "sg:province":"Utrecht",
    "sg:website":"http://www.postkantoor.nl",
    "wof:name":"Postkantoor",
    "wof:placetype":"venue"
},
  "geometry": {"coordinates":[5.137144,52.06509],"type":"Point"}
}