{
  "type": "Feature",
  "properties": {
    "addr:full":"M H Trompstr 28 Roodeschool Groningen 9983 PP",
    "addr:housenumber":"28",
    "addr:postcode":"9983 pp",
    "addr:street":"M",
    "iso:country":"NL",
    "sg:address":"M H Trompstr 28",
    "sg:city":"Roodeschool",
    "sg:orig_category":"Autorijscholen",
    "sg:phone":"+31 595 412 237",
    "sg:postcode":"9983 PP",
    "sg:province":"Groningen",
    "wof:name":"Leest-Bakker Bv, Van Der",
    "wof:placetype":"venue"
},
  "geometry": {"coordinates":[6.766248,53.421696],"type":"Point"}
}