{
  "type": "Feature",
  "properties": {
    "addr:full":"Wilgenlaan 10 Aalsmeer Noord-Holland 1431 HT",
    "addr:housenumber":"10",
    "addr:postcode":"1431 ht",
    "addr:street":"Wilgenlaan",
    "iso:country":"NL",
    "sg:address":"Wilgenlaan 10",
    "sg:city":"Aalsmeer",
    "sg:orig_category":"Bedrijfsinventaris Gh",
    "sg:phone":"+31 297 321 347",
    "sg:postcode":"1431 HT",
    "sg:province":"Noord-Holland",
    "wof:name":"Cees Van Bergen Design",
    "wof:placetype":"venue"
},
  "geometry": {"coordinates":[4.763255,52.266632],"type":"Point"}
}