{
  "type": "Feature",
  "properties": {
    "addr:full":"Reinier De Graafweg 1 Delft Zuid-Holland 2625 AD",
    "addr:housenumber":"1",
    "addr:postcode":"2625 ad",
    "addr:street":"Reinier De Graafweg",
    "iso:country":"NL",
    "sg:address":"Reinier De Graafweg 1",
    "sg:city":"Delft",
    "sg:orig_category":"Medische Apparatuur And Prothesen Fab",
    "sg:phone":"+31 15 262 8215",
    "sg:postcode":"2625 AD",
    "sg:province":"Zuid-Holland",
    "wof:name":"Den Blanken Hoortechnisch Centrum",
    "wof:placetype":"venue"
},
  "geometry": {"coordinates":[4.340929,51.998741],"type":"Point"}
}