{
  "type": "Feature",
  "properties": {
    "addr:full":"St Adriaanstr 1 Goes Zeeland 4461 JC",
    "addr:housenumber":"1",
    "addr:postcode":"4461 jc",
    "iso:country":"NL",
    "sg:address":"St Adriaanstr 1",
    "sg:city":"Goes",
    "sg:orig_category":"Verlichting",
    "sg:phone":"+31 113 250 669",
    "sg:postcode":"4461 JC",
    "sg:province":"Zeeland",
    "wof:name":"Licht-Formule Design",
    "wof:placetype":"venue"
},
  "geometry": {"coordinates":[-83.914169,39.768833],"type":"Point"}
}