{
  "type": "Feature",
  "properties": {
    "addr:full":"Oude Telgterweg 123 Ermelo Gelderland 3851 EB",
    "addr:housenumber":"123",
    "addr:postcode":"3851 eb",
    "addr:street":"Oude Telgterweg;Gelderland",
    "iso:country":"NL",
    "sg:address":"Oude Telgterweg 123",
    "sg:city":"Ermelo",
    "sg:orig_category":"Verlichting And Huishoudartikelen",
    "sg:phone":"+31 341 551 405",
    "sg:postcode":"3851 EB",
    "sg:province":"Gelderland",
    "wof:name":"G. Hey",
    "wof:placetype":"venue"
},
  "geometry": {"coordinates":[5.614053,52.294518],"type":"Point"}
}