{
  "type": "Feature",
  "properties": {
    "iso:country":"NL",
    "sg:address":"Gandhiweg 54",
    "sg:city":"Gouda",
    "sg:orig_category":"Technische Studies And Onderzoek",
    "sg:phone":"+31 182 521 991",
    "sg:postcode":"2807 RH",
    "sg:province":"South Holland",
    "wof:name":"Uptime",
    "wof:placetype":"venue"
},
  "geometry": {"coordinates":[4.754487,52.006012],"type":"Point"}
}