{
  "type": "Feature",
  "properties": {
    "iso:country":"NL",
    "sg:address":"Korvelseweg 132",
    "sg:city":"Tilburg",
    "sg:classifiers":[
        {
            "category":"Food & Beverages",
            "subcategory":"Fruits & Vegetables",
            "type":"Retail Goods"
        }
    ],
    "sg:phone":"+31 13 543 4430",
    "sg:postcode":"5025 JL",
    "sg:province":"North Brabant",
    "sg:tags":[
        "groenten"
    ],
    "wof:name":"Jan Timmermans",
    "wof:placetype":"venue"
},
  "geometry": {"coordinates":[5.073297,51.550835],"type":"Point"}
}