{
  "type": "Feature",
  "properties": {
    "addr:full":"Meidoornstr 9 Duivendrecht Noord-Holland 1115 BE",
    "addr:housenumber":"9",
    "addr:postcode":"1115",
    "addr:street":"Meidoornstr",
    "iso:country":"NL",
    "sg:address":"Meidoornstr 9",
    "sg:city":"Duivendrecht",
    "sg:orig_category":"Koeltechniek",
    "sg:phone":"+31 20 698 1862",
    "sg:postcode":"1115 BE",
    "sg:province":"Noord-Holland",
    "wof:name":"Gofrigo Bv",
    "wof:placetype":"venue"
},
  "geometry": {"coordinates":[4.939892,52.326508],"type":"Point"}
}