{
  "type": "Feature",
  "properties": {
    "addr:full":"Zeilweg 12 Lelystad NL. 8243 PK",
    "addr:housenumber":"12",
    "addr:postcode":"8243 pk",
    "addr:street":"Zeilweg;Nl.",
    "iso:country":"NL",
    "sg:address":"Zeilweg 12",
    "sg:city":"Lelystad",
    "sg:orig_category":"Kantoor- And Schoolbenodigdheden Gh",
    "sg:phone":"+31 320 260 369",
    "sg:postcode":"8243 PK",
    "sg:province":"NL.",
    "wof:name":"Hollandse Rondkartonnage Bv",
    "wof:placetype":"venue"
},
  "geometry": {"coordinates":[5.4336161613,52.499546051],"type":"Point"}
}