{
  "type": "Feature",
  "properties": {
    "addr:full":"Grasmeent 69 Hilversum Noord-Holland 1218 AE",
    "addr:housenumber":"69",
    "addr:postcode":"1218 ae",
    "addr:street":"Grasmeent",
    "iso:country":"NL",
    "sg:address":"Grasmeent 69",
    "sg:city":"Hilversum",
    "sg:orig_category":"Vertaal- And Tolkenbureaus",
    "sg:phone":"+31 35 691 3195",
    "sg:postcode":"1218 AE",
    "sg:province":"Noord-Holland",
    "wof:name":"Geurtsen Vertaal Circuit",
    "wof:placetype":"venue"
},
  "geometry": {"coordinates":[5.138141,52.275681],"type":"Point"}
}