{
  "type": "Feature",
  "properties": {
    "addr:full":"Oostelijke Handelskade 17 Amsterdam Noord-Holland 1019 BL",
    "addr:housenumber":"17;1019",
    "addr:postcode":"bl",
    "addr:street":"Oostelijke Handelskade",
    "iso:country":"NL",
    "sg:address":"Oostelijke Handelskade 17",
    "sg:city":"Amsterdam",
    "sg:orig_category":"Meubelreparatie And -Restauratie",
    "sg:phone":"+31 20 421 1033",
    "sg:postcode":"1019 BL",
    "sg:province":"Noord-Holland",
    "wof:name":"Pakhuis Amsterdam",
    "wof:placetype":"venue"
},
  "geometry": {"coordinates":[4.932476,52.374683],"type":"Point"}
}