{
  "type": "Feature",
  "properties": {
    "addr:full":"Loodsgr 55 'T Juttersjong Den Helder Noord-Holland 1781 KN",
    "addr:housenumber":"55",
    "addr:postcode":"1781 kn",
    "addr:street":"Loodsgr;' T",
    "iso:country":"NL",
    "sg:address":"Loodsgr 55 'T Juttersjong",
    "sg:city":"Den Helder",
    "sg:orig_category":"Verenigingen En Stichtingen",
    "sg:phone":"+31 223 618 075",
    "sg:postcode":"1781 KN",
    "sg:province":"Noord-Holland",
    "wof:name":"Juttersjong, Ver 'T",
    "wof:placetype":"venue"
},
  "geometry": {"coordinates":[4.79429,52.949692],"type":"Point"}
}