{
  "type": "Feature",
  "properties": {
    "iso:country":"NL",
    "sg:address":"Lengwg 80",
    "sg:city":"Hoogvliet Rt",
    "sg:orig_category":"Kunstgebitten",
    "sg:phone":"+31 10 216 2258",
    "sg:postcode":"3192 BL",
    "sg:province":"Zuid-Holland",
    "wof:name":"Fair Dent, Tandprothetisch Centrum",
    "wof:placetype":"venue"
},
  "geometry": {"coordinates":[4.358388,51.856293],"type":"Point"}
}