{
  "type": "Feature",
  "properties": {
    "addr:full":"Dopheidestraat 86 Lisserbroek North Holland 2165 VS",
    "addr:housenumber":"86",
    "addr:postcode":"2165 vs",
    "addr:street":"Dopheidestraat",
    "iso:country":"NL",
    "sg:address":"Dopheidestraat 86",
    "sg:city":"Lisserbroek",
    "sg:orig_category":"Fitnesscentra",
    "sg:phone":"+31 252 418 207",
    "sg:postcode":"2165 VS",
    "sg:province":"North Holland",
    "wof:name":"Kagerplas",
    "wof:placetype":"venue"
},
  "geometry": {"coordinates":[4.57335,52.254936],"type":"Point"}
}