{
  "type": "Feature",
  "properties": {
    "iso:country":"NL",
    "sg:address":"Steur 1",
    "sg:city":"Ridderkerk",
    "sg:orig_category":"Verlichtingsartikelen - Groothandel",
    "sg:phone":"+31 180 431 953",
    "sg:postcode":"2986 SH",
    "sg:province":"South Holland",
    "wof:name":"Geth",
    "wof:placetype":"venue"
},
  "geometry": {"coordinates":[4.624882,51.86348],"type":"Point"}
}