{
  "type": "Feature",
  "properties": {
    "addr:full":"Korte Mare 8 Leiden Zuid-Holland 2312 NN",
    "addr:housenumber":"8",
    "addr:postcode":"2312 nn",
    "addr:street":"Korte Mare",
    "iso:country":"NL",
    "sg:address":"Korte Mare 8",
    "sg:city":"Leiden",
    "sg:classifiers":[
        {
            "category":"Bars & Pubs",
            "type":"Food & Drink"
        }
    ],
    "sg:phone":"+31 71 522 6137",
    "sg:postcode":"2312 NN",
    "sg:province":"Zuid-Holland",
    "wof:name":"Malabata",
    "wof:placetype":"venue"
},
  "geometry": {"coordinates":[4.489895,52.163937],"type":"Point"}
}