{
  "type": "Feature",
  "properties": {
    "addr:full":"Heistr 117 Sprang Capelle Noord-Brabant 5161 GC",
    "addr:housenumber":"117",
    "addr:postcode":"5161 gc",
    "iso:country":"NL",
    "sg:address":"Heistr 117",
    "sg:city":"Sprang Capelle",
    "sg:orig_category":"Melktransporten",
    "sg:phone":"+31 416 275 570",
    "sg:postcode":"5161 GC",
    "sg:province":"Noord-Brabant",
    "wof:name":"Versteeg, J",
    "wof:placetype":"venue"
},
  "geometry": {"coordinates":[5.000724,51.675987],"type":"Point"}
}