{
  "type": "Feature",
  "properties": {
    "addr:full":"J Luykenstr 37 Amsterdam Noord-Holland 1071 CL",
    "addr:housenumber":"37",
    "addr:postcode":"1071",
    "iso:country":"NL",
    "sg:address":"J Luykenstr 37",
    "sg:city":"Amsterdam",
    "sg:classifiers":[
        {
            "category":"Travel",
            "subcategory":"Hotels & Motels",
            "type":"Entertainment"
        }
    ],
    "sg:phone":"+31 20 679 0976",
    "sg:postcode":"1071 CL",
    "sg:province":"Noord-Holland",
    "sg:website":"http://www.fita.nl",
    "wof:name":"Fita",
    "wof:placetype":"venue"
},
  "geometry": {"coordinates":[4.879614,52.359177],"type":"Point"}
}