{
  "type": "Feature",
  "properties": {
    "iso:country":"NL",
    "sg:address":"Nieuwstr 13-15",
    "sg:city":"Hansweert",
    "sg:orig_category":"Bloemen En Planten",
    "sg:phone":"+31 113 382 122",
    "sg:postcode":"4417 AE",
    "sg:province":"Zeeland",
    "wof:name":"Helianthus",
    "wof:placetype":"venue"
},
  "geometry": {"coordinates":[4.004915,51.448357],"type":"Point"}
}