{
  "type": "Feature",
  "properties": {
    "addr:full":"2E Haagstr 1 Helmond Noord-Brabant 5707 VJ",
    "addr:housenumber":"1",
    "addr:postcode":"5707 vj",
    "addr:street":"2E Haagstr",
    "iso:country":"NL",
    "sg:address":"2E Haagstr 1",
    "sg:city":"Helmond",
    "sg:orig_category":"Verenigingen En Stichtingen",
    "sg:phone":"+31 492 529 084",
    "sg:postcode":"5707 VJ",
    "sg:province":"Noord-Brabant",
    "wof:name":"West-Side, Jeugdhonk",
    "wof:placetype":"venue"
},
  "geometry": {"coordinates":[5.642957,51.474377],"type":"Point"}
}