{
  "type": "Feature",
  "properties": {
    "addr:full":"Winkelc Woensel 78D Eindhoven Noord-Brabant 5625 AD",
    "addr:housenumber":"78d",
    "addr:postcode":"5625 ad",
    "addr:street":"Winkelc Woensel",
    "iso:country":"NL",
    "sg:address":"Winkelc Woensel 78D",
    "sg:city":"Eindhoven",
    "sg:orig_category":"Kappers",
    "sg:phone":"+31 40 248 1819",
    "sg:postcode":"5625 AD",
    "sg:province":"Noord-Brabant",
    "wof:name":"Clementine, Haarmode",
    "wof:placetype":"venue"
},
  "geometry": {"coordinates":[5.4774451256,51.4706459045],"type":"Point"}
}