{
  "type": "Feature",
  "properties": {
    "iso:country":"NL",
    "sg:address":"Brigidastr 6",
    "sg:city":"Bavel",
    "sg:orig_category":"Kaas",
    "sg:phone":"+31 161 432 827",
    "sg:postcode":"4854 CT",
    "sg:province":"Noord-Brabant",
    "wof:name":"Kaashuis Bavel",
    "wof:placetype":"venue"
},
  "geometry": {"coordinates":[4.8296952248,51.5653343201],"type":"Point"}
}