{
  "type": "Feature",
  "properties": {
    "addr:full":"Mechelenln 4G Eindhoven Noord-Brabant 5628 VG",
    "addr:housenumber":"4g",
    "addr:postcode":"5628 vg",
    "addr:street":"Mechelenln",
    "iso:country":"NL",
    "sg:address":"Mechelenln 4G",
    "sg:city":"Eindhoven",
    "sg:orig_category":"Verenigingen En Stichtingen",
    "sg:phone":"+31 40 241 0207",
    "sg:postcode":"5628 VG",
    "sg:province":"Noord-Brabant",
    "wof:name":"Aquarius",
    "wof:placetype":"venue"
},
  "geometry": {"coordinates":[5.482857,51.48119],"type":"Point"}
}