{
  "type": "Feature",
  "properties": {
    "iso:country":"NL",
    "sg:address":"Beekerheide 41A",
    "sg:city":"Beek En Donk",
    "sg:orig_category":"Gordijnen",
    "sg:phone":"+31 492 463 876",
    "sg:postcode":"5741 HB",
    "sg:province":"Noord-Brabant",
    "wof:name":"Doratex",
    "wof:placetype":"venue"
},
  "geometry": {"coordinates":[5.642421,51.526592],"type":"Point"}
}