{
  "type": "Feature",
  "properties": {
    "addr:full":"Industrieweg 4 Bedum Groningen 9781 AC",
    "addr:housenumber":"4",
    "addr:postcode":"9781 ac",
    "addr:street":"Industrieweg",
    "iso:country":"NL",
    "sg:address":"Industrieweg 4",
    "sg:city":"Bedum",
    "sg:orig_category":"Boekenuitgeverijen",
    "sg:phone":"+31 50 301 2144",
    "sg:postcode":"9781 AC",
    "sg:province":"Groningen",
    "wof:name":"Profiel Bv",
    "wof:placetype":"venue"
},
  "geometry": {"coordinates":[6.596307,53.298073],"type":"Point"}
}