{
  "type": "Feature",
  "properties": {
    "addr:full":"Zuiderparkln 72 S Gravenhage South Holland 2574 HM",
    "addr:housenumber":"72",
    "addr:postcode":"2574 hm",
    "addr:street":"Zuiderparkln;S Gravenhage",
    "iso:country":"NL",
    "sg:address":"Zuiderparkln 72",
    "sg:city":"S Gravenhage",
    "sg:orig_category":"Koffie- En Theehuizen",
    "sg:phone":"+31 70 427 2007",
    "sg:postcode":"2574 HM",
    "sg:province":"South Holland",
    "wof:name":"Greetje",
    "wof:placetype":"venue"
},
  "geometry": {"coordinates":[4.277523,52.064205],"type":"Point"}
}