{
  "type": "Feature",
  "properties": {
    "addr:full":"Schiedamsewg 60A Rotterdam Zuid-Holland 3025 AD",
    "addr:housenumber":"60a",
    "addr:postcode":"3025 ad",
    "addr:street":"Schiedamsewg",
    "iso:country":"NL",
    "sg:address":"Schiedamsewg 60A",
    "sg:city":"Rotterdam",
    "sg:orig_category":"Kappersbenodigdheden",
    "sg:phone":"+31 10 466 4154",
    "sg:postcode":"3025 AD",
    "sg:province":"Zuid-Holland",
    "sg:website":"http://www.intertexbv.nl",
    "wof:name":"Intertex, Bv",
    "wof:placetype":"venue"
},
  "geometry": {"coordinates":[4.445073,51.909863],"type":"Point"}
}