{
  "type": "Feature",
  "properties": {
    "addr:full":"Beekseweg 3 Didam Gelderland 6942 JC",
    "addr:housenumber":"3",
    "addr:postcode":"6942 jc",
    "addr:street":"Beekseweg;Gelderland",
    "iso:country":"NL",
    "sg:address":"Beekseweg 3",
    "sg:city":"Didam",
    "sg:orig_category":"Diverse Bedrijfsinstallaties Gh",
    "sg:phone":"+31 316 292 929",
    "sg:postcode":"6942 JC",
    "sg:province":"Gelderland",
    "wof:name":"Rensa Technisch Handelsbureau Bv",
    "wof:placetype":"venue"
},
  "geometry": {"coordinates":[6.144582,51.933624],"type":"Point"}
}