{
  "type": "Feature",
  "properties": {
    "addr:full":"Drogteropslagen 62 Drogteropslagen Drenthe 7705 PJ",
    "addr:housenumber":"62",
    "addr:postcode":"7705 pj",
    "addr:street":"Drogteropslagen",
    "iso:country":"NL",
    "sg:address":"Drogteropslagen 62",
    "sg:city":"Drogteropslagen",
    "sg:orig_category":"Granen, Zaden And Diervoeders Gh",
    "sg:phone":"+31 523 612 480",
    "sg:postcode":"7705 PJ",
    "sg:province":"Drenthe",
    "wof:name":"W.J. Huzen",
    "wof:placetype":"venue"
},
  "geometry": {"coordinates":[6.511306,52.618938],"type":"Point"}
}