{
  "type": "Feature",
  "properties": {
    "addr:full":"Kanaalstr 20 Hengelo Ov Overijssel 7553 GP",
    "addr:housenumber":"20",
    "addr:postcode":"7553 gp",
    "addr:street":"Kanaalstr;Ov",
    "iso:country":"NL",
    "sg:address":"Kanaalstr 20",
    "sg:city":"Hengelo Ov",
    "sg:orig_category":"Betonmortel",
    "sg:phone":"+31 74 249 3333",
    "sg:postcode":"7553 GP",
    "sg:province":"Overijssel",
    "sg:website":"http://www.betoncentrale.nl",
    "wof:name":"Betoncentrale Twenthe Bv",
    "wof:placetype":"venue"
},
  "geometry": {"coordinates":[6.773117,52.25024],"type":"Point"}
}