{
  "type": "Feature",
  "properties": {
    "addr:full":"Stammerdk 5 Diemen North Holland 1112 AA",
    "addr:housenumber":"5",
    "addr:postcode":"1112 aa",
    "addr:street":"Stammerdk",
    "iso:country":"NL",
    "sg:address":"Stammerdk 5",
    "sg:city":"Diemen",
    "sg:orig_category":"Autoruiten",
    "sg:phone":"+31 20 632 2871",
    "sg:postcode":"1112 AA",
    "sg:province":"North Holland",
    "wof:name":"Aa, Autoruitenservice Amsterdam",
    "wof:placetype":"venue"
},
  "geometry": {"coordinates":[4.980675,52.332214],"type":"Point"}
}