{
  "type": "Feature",
  "properties": {
    "addr:full":"Grondzijl 4 Groningen Groningen 9731 DG",
    "addr:housenumber":"4",
    "addr:postcode":"9731 dg",
    "addr:street":"Grondzijl",
    "iso:country":"NL",
    "sg:address":"Grondzijl 4",
    "sg:city":"Groningen",
    "sg:orig_category":"Airconditioning And Ventilatie",
    "sg:phone":"+31 50 549 4006",
    "sg:postcode":"9731 DG",
    "sg:province":"Groningen",
    "wof:name":"Cley Installateurs Vof",
    "wof:placetype":"venue"
},
  "geometry": {"coordinates":[6.591707,53.236122],"type":"Point"}
}