{
  "type": "Feature",
  "properties": {
    "addr:full":"Irenestr 17 Overloon North Brabant 5825 CA",
    "addr:housenumber":"17",
    "addr:postcode":"5825 ca",
    "addr:street":"Irenestr",
    "iso:country":"NL",
    "sg:address":"Irenestr 17",
    "sg:city":"Overloon",
    "sg:classifiers":[
        {
            "category":"Personal",
            "subcategory":"Nail Salon",
            "type":"Services"
        }
    ],
    "sg:phone":"+31 478 641 322",
    "sg:postcode":"5825 CA",
    "sg:province":"North Brabant",
    "sg:tags":[
        "pedicure"
    ],
    "wof:name":"Jacobs, Wilma",
    "wof:placetype":"venue"
},
  "geometry": {"coordinates":[5.94325,51.570797],"type":"Point"}
}