{
  "type": "Feature",
  "properties": {
    "addr:full":"Wyksestr 3 Wyk En Aalburg Gelderland 4261 TV",
    "addr:housenumber":"3",
    "addr:postcode":"4261 tv",
    "addr:street":"Wyksestr",
    "iso:country":"NL",
    "sg:address":"Wyksestr 3",
    "sg:city":"Wyk En Aalburg",
    "sg:orig_category":"Jachthavens - Jachtwerven",
    "sg:phone":"+31 416 696 238",
    "sg:postcode":"4261 TV",
    "sg:province":"Gelderland",
    "wof:name":"Vandenenden Bv",
    "wof:placetype":"venue"
},
  "geometry": {"coordinates":[5.13042,51.755196],"type":"Point"}
}