{
  "type": "Feature",
  "properties": {
    "addr:full":"Paijensweg 1 Nijmegen Gelderland 6523 MB",
    "addr:housenumber":"1",
    "addr:postcode":"6523 mb",
    "addr:street":"Paijensweg;Gelderland",
    "iso:country":"NL",
    "sg:address":"Paijensweg 1",
    "sg:city":"Nijmegen",
    "sg:orig_category":"Public Relationbureaus",
    "sg:phone":"+31 24 381 2345",
    "sg:postcode":"6523 MB",
    "sg:province":"Gelderland",
    "wof:name":"Reclameburo Brouwer & Partners Nijmegen Bv",
    "wof:placetype":"venue"
},
  "geometry": {"coordinates":[5.901128,51.828671],"type":"Point"}
}