{
  "type": "Feature",
  "properties": {
    "addr:full":"Noordweg 412 Middelburg Zeeland 4333 KL",
    "addr:housenumber":"412",
    "addr:postcode":"4333 kl",
    "addr:street":"Noordweg",
    "iso:country":"NL",
    "sg:address":"Noordweg 412",
    "sg:city":"Middelburg",
    "sg:orig_category":"Effectenmakelaars And Fondsenbeheer",
    "sg:phone":"+31 118 616 860",
    "sg:postcode":"4333 KL",
    "sg:province":"Zeeland",
    "wof:name":"Aura International Bv",
    "wof:placetype":"venue"
},
  "geometry": {"coordinates":[3.60594,51.522171],"type":"Point"}
}