{
  "type": "Feature",
  "properties": {
    "addr:full":"Schoolstr 29 Aerdt Gelderland 6913 AC",
    "addr:housenumber":"29",
    "addr:postcode":"6913 ac",
    "addr:street":"Schoolstr;Gelderland",
    "iso:country":"NL",
    "sg:address":"Schoolstr 29",
    "sg:city":"Aerdt",
    "sg:orig_category":"Scholen Voor Basisonderwijs",
    "sg:phone":"+31 316 247 413",
    "sg:postcode":"6913 AC",
    "sg:province":"Gelderland",
    "wof:name":"Driehoek Openb, De",
    "wof:placetype":"venue"
},
  "geometry": {"coordinates":[6.084909,51.893684],"type":"Point"}
}