{
  "type": "Feature",
  "properties": {
    "addr:full":"De Martinet 12 Deurne Noord-Brabant 5751 KS",
    "addr:housenumber":"12",
    "addr:postcode":"5751 ks",
    "addr:street":"De Martinet",
    "iso:country":"NL",
    "sg:address":"De Martinet 12",
    "sg:city":"Deurne",
    "sg:orig_category":"Schoenen",
    "sg:phone":"+31 493 312 523",
    "sg:postcode":"5751 KS",
    "sg:province":"Noord-Brabant",
    "wof:name":"Bukkems",
    "wof:placetype":"venue"
},
  "geometry": {"coordinates":[5.795296,51.462536],"type":"Point"}
}