{
  "type": "Feature",
  "properties": {
    "addr:full":"De Scheren 8 Lelystad Flevoland 8212 EA",
    "addr:housenumber":"8",
    "addr:postcode":"8212 ea",
    "addr:street":"De Scheren;Flevoland",
    "iso:country":"NL",
    "sg:address":"De Scheren 8",
    "sg:city":"Lelystad",
    "sg:orig_category":"Adviesbureaus",
    "sg:phone":"+31 320 222 569",
    "sg:postcode":"8212 EA",
    "sg:province":"Flevoland",
    "wof:name":"Overwater",
    "wof:placetype":"venue"
},
  "geometry": {"coordinates":[5.49588,52.507076],"type":"Point"}
}