{
  "type": "Feature",
  "properties": {
    "iso:country":"NL",
    "sg:address":"Ijwg 763",
    "sg:city":"Hoofddorp",
    "sg:classifiers":[
        {
            "category":"Personal",
            "subcategory":"Nail Salon",
            "type":"Services"
        }
    ],
    "sg:phone":"+31 23 558 1446",
    "sg:postcode":"2131 LR",
    "sg:province":"Noord-Holland",
    "sg:tags":[
        "pedicure"
    ],
    "wof:name":"Krijger-Van Dijk, A",
    "wof:placetype":"venue"
},
  "geometry": {"coordinates":[4.698339,52.337547],"type":"Point"}
}