{
  "type": "Feature",
  "properties": {
    "addr:full":"Rozenbergerweg 2 'T Harde Gelderland 8084 PG",
    "addr:housenumber":"2",
    "addr:postcode":"8084 pg",
    "addr:street":"Rozenbergerweg",
    "iso:country":"NL",
    "sg:address":"Rozenbergerweg 2",
    "sg:city":"'T Harde",
    "sg:orig_category":"Goederenvervoer Over De Weg",
    "sg:phone":"+31 525 685 779",
    "sg:postcode":"8084 PG",
    "sg:province":"Gelderland",
    "wof:name":"A. Van Spijkeren",
    "wof:placetype":"venue"
},
  "geometry": {"coordinates":[5.871002,52.427975],"type":"Point"}
}