{
  "type": "Feature",
  "properties": {
    "addr:full":"Beverveen 486 Spykenisse Zuid-Holland 3205 AN",
    "addr:housenumber":"486",
    "addr:postcode":"3205 an",
    "addr:street":"Beverveen",
    "iso:country":"NL",
    "sg:address":"Beverveen 486",
    "sg:city":"Spykenisse",
    "sg:orig_category":"Administratie- En Boekhoudkantoren",
    "sg:phone":"+31 181 640 621",
    "sg:postcode":"3205 AN",
    "sg:province":"Zuid-Holland",
    "wof:name":"Pas Peters Administratie Service",
    "wof:placetype":"venue"
},
  "geometry": {"coordinates":[4.334235,51.835365],"type":"Point"}
}