{
  "type": "Feature",
  "properties": {
    "addr:full":"Nam Wg 23 Dalerveen Provincie Drenthe 7755 PT",
    "addr:postcode":"7755",
    "addr:street":"Provincie Drenthe;Pt",
    "iso:country":"NL",
    "sg:address":"Nam Wg 23",
    "sg:city":"Dalerveen",
    "sg:orig_category":"Fotoreportages",
    "sg:phone":"+31 524 221 374",
    "sg:postcode":"7755 PT",
    "sg:province":"Provincie Drenthe",
    "wof:name":"Benting, H R D",
    "wof:placetype":"venue"
},
  "geometry": {"coordinates":[6.819655,52.684029],"type":"Point"}
}