{
  "type": "Feature",
  "properties": {
    "iso:country":"NL",
    "sg:address":"Ruusbroecstraat 88",
    "sg:city":"Breda",
    "sg:orig_category":"Verpakkingsmachines Fab",
    "sg:phone":"+31 76 521 4504",
    "sg:postcode":"4819 GE",
    "sg:province":"Noord-Brabant",
    "wof:name":"Stokla Techniek",
    "wof:placetype":"venue"
},
  "geometry": {"coordinates":[4.764879,51.576275],"type":"Point"}
}