{
  "type": "Feature",
  "properties": {
    "iso:country":"NL",
    "sg:address":"Zuivelwg 2",
    "sg:city":"Zelhem",
    "sg:orig_category":"Kinderopvang",
    "sg:phone":"+31 314 623 022",
    "sg:postcode":"7021 CS",
    "sg:province":"Gelderland",
    "wof:name":"Yunio",
    "wof:placetype":"venue"
},
  "geometry": {"coordinates":[6.352749,52.004517],"type":"Point"}
}