{
  "type": "Feature",
  "properties": {
    "iso:country":"NL",
    "sg:address":"Vegelinswg 6",
    "sg:city":"Joure",
    "sg:orig_category":"Muziekscholen",
    "sg:phone":"+31 513 417 555",
    "sg:postcode":"8501 BA",
    "sg:province":"Provincie Friesland",
    "wof:name":"Toanh\u00fbs, Skv It",
    "wof:placetype":"venue"
},
  "geometry": {"coordinates":[5.793356,52.972294],"type":"Point"}
}