{
  "type": "Feature",
  "properties": {
    "addr:full":"Hovenstr 7 Maastricht Limburg 6227 ST",
    "addr:housenumber":"7",
    "addr:postcode":"6227 st",
    "addr:street":"Hovenstr",
    "iso:country":"NL",
    "sg:address":"Hovenstr 7",
    "sg:city":"Maastricht",
    "sg:orig_category":"Kaasgroothandel",
    "sg:phone":"+31 43 361 1209",
    "sg:postcode":"6227 ST",
    "sg:province":"Limburg",
    "wof:name":"Geelen Vof, J P",
    "wof:placetype":"venue"
},
  "geometry": {"coordinates":[5.7256698608,50.8379516602],"type":"Point"}
}