{
  "type": "Feature",
  "properties": {
    "addr:full":"De Kolk 21 Surhuisterveen Friesland 9231 CV",
    "addr:housenumber":"21",
    "addr:postcode":"9231 cv",
    "addr:street":"De Kolk",
    "iso:country":"NL",
    "sg:address":"De Kolk 21",
    "sg:city":"Surhuisterveen",
    "sg:orig_category":"Damesmodezaken",
    "sg:phone":"+31 512 361 276",
    "sg:postcode":"9231 CV",
    "sg:province":"Friesland",
    "wof:name":"Modehuis Van Der Lijn Bv",
    "wof:placetype":"venue"
},
  "geometry": {"coordinates":[6.165457,53.182384],"type":"Point"}
}