{
  "type": "Feature",
  "properties": {
    "addr:full":"5 Meipln 128 Leiden Zuid-Holland 2321 BS",
    "addr:housenumber":"5;128",
    "addr:postcode":"2321 bs",
    "addr:street":"Meipln",
    "iso:country":"NL",
    "sg:address":"5 Meipln 128",
    "sg:city":"Leiden",
    "sg:orig_category":"Fietsen En Bromfietsen",
    "sg:phone":"+31 71 576 6026",
    "sg:postcode":"2321 BS",
    "sg:province":"Zuid-Holland",
    "wof:name":"Polanen Rijwiel- En Bromfietshandel, Van",
    "wof:placetype":"venue"
},
  "geometry": {"coordinates":[4.480106,52.147549],"type":"Point"}
}