{
  "type": "Feature",
  "properties": {
    "addr:full":"Heesterln 17 Groningen Groningen 9713 NV",
    "addr:housenumber":"17",
    "addr:postcode":"9713 nv",
    "addr:street":"Heesterln",
    "iso:country":"NL",
    "sg:address":"Heesterln 17",
    "sg:city":"Groningen",
    "sg:orig_category":"Grafisch Ontwerpers",
    "sg:phone":"+31 50 313 8830",
    "sg:postcode":"9713 NV",
    "sg:province":"Groningen",
    "wof:name":"Rapper, Y De",
    "wof:placetype":"venue"
},
  "geometry": {"coordinates":[6.574715,53.217144],"type":"Point"}
}