{
  "type": "Feature",
  "properties": {
    "addr:full":"Dalmatie 40 Leusden Utrecht 3831 EG",
    "addr:housenumber":"40",
    "addr:postcode":"3831 eg",
    "addr:street":"Dalmatie",
    "iso:country":"NL",
    "sg:address":"Dalmatie 40",
    "sg:city":"Leusden",
    "sg:orig_category":"Graveerbedrijven",
    "sg:phone":"+31 33 432 1945",
    "sg:postcode":"3831 EG",
    "sg:province":"Utrecht",
    "wof:name":"Calligraphics",
    "wof:placetype":"venue"
},
  "geometry": {"coordinates":[5.434278,52.134235],"type":"Point"}
}