{
  "type": "Feature",
  "properties": {
    "addr:full":"T Klif 4 Urk Flevoland 8321 KG",
    "addr:housenumber":"4",
    "addr:postcode":"8321 kg",
    "addr:street":"T Klif;Flevoland",
    "iso:country":"NL",
    "sg:address":"T Klif 4",
    "sg:city":"Urk",
    "sg:orig_category":"Verlichting And Huishoudartikelen",
    "sg:phone":"+31 527 688 397",
    "sg:postcode":"8321 KG",
    "sg:province":"Flevoland",
    "wof:name":"Marskramer",
    "wof:placetype":"venue"
},
  "geometry": {"coordinates":[5.599911,52.661327],"type":"Point"}
}