{
  "type": "Feature",
  "properties": {
    "iso:country":"NL",
    "sg:address":"Nyverheidswg 4",
    "sg:city":"Putten",
    "sg:orig_category":"Parketvloeren",
    "sg:phone":"+31 341 355 400",
    "sg:postcode":"3881 LA",
    "sg:province":"Gelderland",
    "sg:website":"http://www.mmh.nl",
    "wof:name":"Meuleman",
    "wof:placetype":"venue"
},
  "geometry": {"coordinates":[5.580013,52.267448],"type":"Point"}
}