{
  "type": "Feature",
  "properties": {
    "addr:full":"Stationsstr 51 Koog Aan De Zaan Noord-Holland 1541 LG",
    "addr:housenumber":"51",
    "addr:postcode":"1541 lg",
    "addr:street":"Stationsstr",
    "iso:country":"NL",
    "sg:address":"Stationsstr 51",
    "sg:city":"Koog Aan De Zaan",
    "sg:orig_category":"Antiquiteiten - Restauratie",
    "sg:phone":"+31 75 622 2568",
    "sg:postcode":"1541 LG",
    "sg:province":"Noord-Holland",
    "wof:name":"Antiques Collectors, The",
    "wof:placetype":"venue"
},
  "geometry": {"coordinates":[4.808357,52.469303],"type":"Point"}
}