{
  "type": "Feature",
  "properties": {
    "addr:full":"Kameraarsweide 3 Nieuwegein Utrecht 3437 CB",
    "addr:housenumber":"3",
    "addr:postcode":"3437 cb",
    "addr:street":"Kameraarsweide",
    "iso:country":"NL",
    "sg:address":"Kameraarsweide 3",
    "sg:city":"Nieuwegein",
    "sg:orig_category":"Boekhouders",
    "sg:phone":"+31 30 603 2256",
    "sg:postcode":"3437 CB",
    "sg:province":"Utrecht",
    "wof:name":"Patz Administraties",
    "wof:placetype":"venue"
},
  "geometry": {"coordinates":[5.071746,52.041203],"type":"Point"}
}