{
  "type": "Feature",
  "properties": {
    "addr:full":"Palladiostr 9 Rotterdam South Holland 3066 AH",
    "addr:housenumber":"9",
    "addr:postcode":"3066 ah",
    "addr:street":"Palladiostr",
    "iso:country":"NL",
    "sg:address":"Palladiostr 9",
    "sg:city":"Rotterdam",
    "sg:orig_category":"Verzekeringen - Verzekeringskantoren",
    "sg:phone":"+31 10 286 2733",
    "sg:postcode":"3066 AH",
    "sg:province":"South Holland",
    "sg:website":"http://www.tensurance.nl",
    "wof:name":"Tensurance",
    "wof:placetype":"venue"
},
  "geometry": {"coordinates":[4.550986,51.938789],"type":"Point"}
}