{
  "type": "Feature",
  "properties": {
    "addr:full":"P V Aschstr 1 Rotterdam Zuid-Holland 3043 RE",
    "addr:housenumber":"1",
    "addr:postcode":"3043 re",
    "addr:street":"Aschstr",
    "iso:country":"NL",
    "sg:address":"P V Aschstr 1",
    "sg:city":"Rotterdam",
    "sg:orig_category":"Scholen Voor Basisonderwijs",
    "sg:phone":"+31 10 437 1476",
    "sg:postcode":"3043 RE",
    "sg:province":"Zuid-Holland",
    "wof:name":"Startbaan Overschie",
    "wof:placetype":"venue"
},
  "geometry": {"coordinates":[4.42887,51.943211],"type":"Point"}
}