{
  "type": "Feature",
  "properties": {
    "addr:full":"Schoenmakerij 1B Zevenbergen Noord-Brabant 4762 AS",
    "addr:housenumber":"1b",
    "addr:postcode":"4762 as",
    "addr:street":"Schoenmakerij",
    "iso:country":"NL",
    "sg:address":"Schoenmakerij 1B",
    "sg:city":"Zevenbergen",
    "sg:orig_category":"Kantoor- En Bedrijfsmeubelen",
    "sg:phone":"+31 168 371 110",
    "sg:postcode":"4762 AS",
    "sg:province":"Noord-Brabant",
    "wof:name":"Rokus",
    "wof:placetype":"venue"
},
  "geometry": {"coordinates":[4.6209878922,51.6459617615],"type":"Point"}
}