{
  "type": "Feature",
  "properties": {
    "addr:full":"Oude Haven 73 Barendrecht Zuid-Holland 2992 BK",
    "addr:housenumber":"73",
    "addr:postcode":"2992 bk",
    "addr:street":"Oude Haven",
    "iso:country":"NL",
    "sg:address":"Oude Haven 73",
    "sg:city":"Barendrecht",
    "sg:orig_category":"Meubelzaken, Woning- And Keukeninrichting",
    "sg:phone":"+31 180 619 267",
    "sg:postcode":"2992 BK",
    "sg:province":"Zuid-Holland",
    "wof:name":"J.D. Jongenotter",
    "wof:placetype":"venue"
},
  "geometry": {"coordinates":[4.532222,51.857224],"type":"Point"}
}