{
  "type": "Feature",
  "properties": {
    "addr:full":"Prins Hendrikstraat 41 Raamsdonksveer Noord-Brabant 4941 JT",
    "addr:housenumber":"41",
    "addr:postcode":"4941 jt",
    "addr:street":"Prins Hendrikstraat",
    "iso:country":"NL",
    "sg:address":"Prins Hendrikstraat 41",
    "sg:city":"Raamsdonksveer",
    "sg:orig_category":"Woningbouwverenigingen",
    "sg:phone":"+31 162 513 391",
    "sg:postcode":"4941 JT",
    "sg:province":"Noord-Brabant",
    "wof:name":"Woningbouwvereniging Volksbelang",
    "wof:placetype":"venue"
},
  "geometry": {"coordinates":[4.87458992,51.6957740784],"type":"Point"}
}