{
  "type": "Feature",
  "properties": {
    "iso:country":"NL",
    "sg:address":"Prins Clausstraat 75",
    "sg:city":"Haarlem",
    "sg:orig_category":"Geluidsopnamen",
    "sg:phone":"+31 23 532 3024",
    "sg:postcode":"2012 KW",
    "sg:province":"Noord-Holland",
    "wof:name":"Studio 75 Music Productions",
    "wof:placetype":"venue"
},
  "geometry": {"coordinates":[4.621186,52.37188],"type":"Point"}
}