{
  "type": "Feature",
  "properties": {
    "addr:full":"Laan Van Meerdervoort 3 'S Gravenhage Zuid-Holland 2517 AA",
    "addr:housenumber":"3 '",
    "addr:postcode":"2517 aa",
    "addr:street":"Laan Van Meerdervoort",
    "iso:country":"NL",
    "sg:address":"Laan Van Meerdervoort 3",
    "sg:city":"'S Gravenhage",
    "sg:orig_category":"Antiekzaken",
    "sg:phone":"+31 70 365 1346",
    "sg:postcode":"2517 AA",
    "sg:province":"Zuid-Holland",
    "wof:name":"Prix D-Amis",
    "wof:placetype":"venue"
},
  "geometry": {"coordinates":[4.299571,52.08651],"type":"Point"}
}