{
  "type": "Feature",
  "properties": {
    "addr:full":"Hogenakkerstr 30 Weert Limburg 6002 BB",
    "addr:housenumber":"30",
    "addr:postcode":"6002 bb",
    "addr:street":"Hogenakkerstr",
    "iso:country":"NL",
    "sg:address":"Hogenakkerstr 30",
    "sg:city":"Weert",
    "sg:orig_category":"Banden",
    "sg:phone":"+31 495 524 117",
    "sg:postcode":"6002 BB",
    "sg:province":"Limburg",
    "wof:name":"Loos, Van",
    "wof:placetype":"venue"
},
  "geometry": {"coordinates":[5.684722,51.258083],"type":"Point"}
}