{
  "type": "Feature",
  "properties": {
    "iso:country":"NL",
    "sg:address":"Visseringln 14",
    "sg:city":"Ryswyk Zh",
    "sg:orig_category":"Opslag Inboedels",
    "sg:phone":"+31 70 307 6120",
    "sg:postcode":"2288 ER",
    "sg:province":"South Holland",
    "sg:website":"http://www.shurgard.nl",
    "wof:name":"Shurgard Rijswijk",
    "wof:placetype":"venue"
},
  "geometry": {"coordinates":[4.3243598938,52.0372505188],"type":"Point"}
}