{
  "type": "Feature",
  "properties": {
    "addr:full":"Postbus 547 Leeuwarden Provincie Friesland 8901 BH",
    "addr:housenumber":"547",
    "addr:postcode":"8901 bh",
    "addr:street":"Postbus;Provincie Friesland",
    "iso:country":"NL",
    "sg:address":"Postbus 547",
    "sg:city":"Leeuwarden",
    "sg:orig_category":"Voetbalverenigingen",
    "sg:phone":"+31 58 213 5516",
    "sg:postcode":"8901 BH",
    "sg:province":"Provincie Friesland",
    "sg:website":"http://come.to/cambuurls",
    "wof:name":"Cambuur Leeuwarden Bvo",
    "wof:placetype":"venue"
},
  "geometry": {"coordinates":[5.79143,53.203049],"type":"Point"}
}