{
  "type": "Feature",
  "properties": {
    "addr:full":"Kampstraat 4 Geleen Limburg 6163 HG",
    "addr:housenumber":"4",
    "addr:postcode":"6163 hg",
    "addr:street":"Kampstraat",
    "iso:country":"NL",
    "sg:address":"Kampstraat 4",
    "sg:city":"Geleen",
    "sg:orig_category":"Airconditioning And Ventilatie",
    "sg:phone":"+31 46 423 5800",
    "sg:postcode":"6163 HG",
    "sg:province":"Limburg",
    "wof:name":"Jos Smeets Luchtbehandeling Bv",
    "wof:placetype":"venue"
},
  "geometry": {"coordinates":[5.816747,50.977787],"type":"Point"}
}