{
  "type": "Feature",
  "properties": {
    "addr:full":"Curacao 22 Apeldoorn Gelderland 7332 BM",
    "addr:housenumber":"22",
    "addr:postcode":"7332 bm",
    "addr:street":"Curacao;Gelderland",
    "iso:country":"NL",
    "sg:address":"Curacao 22",
    "sg:city":"Apeldoorn",
    "sg:orig_category":"Lichtreclame",
    "sg:phone":"+31 55 542 3933",
    "sg:postcode":"7332 BM",
    "sg:province":"Gelderland",
    "sg:website":"http://www.cl.nl",
    "wof:name":"Cijfers & Letters Bv",
    "wof:placetype":"venue"
},
  "geometry": {"coordinates":[5.986798,52.18351],"type":"Point"}
}