{
  "type": "Feature",
  "properties": {
    "iso:country":"NL",
    "sg:address":"Benedenrywg 180",
    "sg:city":"Ridderkerk",
    "sg:classifiers":[
        {
            "category":"Retail",
            "subcategory":"Auto Repair",
            "type":"Services"
        }
    ],
    "sg:phone":"+31 180 413 033",
    "sg:postcode":"2987 VB",
    "sg:province":"Zuid-Holland",
    "sg:tags":[
        "garage"
    ],
    "wof:name":"Kwawegen Ridderkerk Bv, Van",
    "wof:placetype":"venue"
},
  "geometry": {"coordinates":[4.585886,51.893429],"type":"Point"}
}