{
  "type": "Feature",
  "properties": {
    "addr:full":"Coenecoop 630 Waddinxveen South Holland 2741 PV",
    "addr:housenumber":"630",
    "addr:postcode":"2741 pv",
    "addr:street":"Coenecoop",
    "iso:country":"NL",
    "sg:address":"Coenecoop 630",
    "sg:city":"Waddinxveen",
    "sg:orig_category":"Papier - Fabrieken En Groothandel",
    "sg:phone":"+31 182 572 855",
    "sg:postcode":"2741 PV",
    "sg:province":"South Holland",
    "wof:name":"Dorgelo Bv",
    "wof:placetype":"venue"
},
  "geometry": {"coordinates":[4.650439,52.024975],"type":"Point"}
}