{
  "type": "Feature",
  "properties": {
    "iso:country":"NL",
    "sg:address":"Voorsterweg 60",
    "sg:city":"Zwolle",
    "sg:orig_category":"Hout Gh",
    "sg:phone":"+31 38 421 5175",
    "sg:postcode":"8042 AD",
    "sg:province":"NL.08",
    "wof:name":"Houthandel G. Van Dijk En Zn Zwolle Bv",
    "wof:placetype":"venue"
},
  "geometry": {"coordinates":[6.046581,52.526596],"type":"Point"}
}