{
  "type": "Feature",
  "properties": {
    "addr:full":"Kerkwg 12A Haarle Gem Hellend Overijssel 7448 AD",
    "addr:housenumber":"12a",
    "addr:postcode":"7448 ad",
    "addr:street":"Kerkwg;Overijssel",
    "iso:country":"NL",
    "sg:address":"Kerkwg 12A",
    "sg:city":"Haarle Gem Hellend",
    "sg:orig_category":"Kappers",
    "sg:phone":"+31 548 595 281",
    "sg:postcode":"7448 AD",
    "sg:province":"Overijssel",
    "wof:name":"Schaartje, Het",
    "wof:placetype":"venue"
},
  "geometry": {"coordinates":[6.382222,52.359516],"type":"Point"}
}