{
  "type": "Feature",
  "properties": {
    "addr:full":"Pr W Alexanderstr 20 Baambrugge Utrecht 1396 KC",
    "addr:housenumber":"20",
    "addr:postcode":"1396 kc",
    "addr:street":"W;Baambrugge",
    "iso:country":"NL",
    "sg:address":"Pr W Alexanderstr 20",
    "sg:city":"Baambrugge",
    "sg:orig_category":"Poppen - Reparatie",
    "sg:phone":"+31 294 293 015",
    "sg:postcode":"1396 KC",
    "sg:province":"Utrecht",
    "wof:name":"Pimpernel",
    "wof:placetype":"venue"
},
  "geometry": {"coordinates":[4.986344,52.245441],"type":"Point"}
}