{
  "type": "Feature",
  "properties": {
    "addr:full":"De Bleker 27 Veldhoven Noord-Brabant 5506 BA",
    "addr:housenumber":"27",
    "addr:postcode":"5506 ba",
    "addr:street":"De Bleker",
    "iso:country":"NL",
    "sg:address":"De Bleker 27",
    "sg:city":"Veldhoven",
    "sg:orig_category":"Psychologen",
    "sg:phone":"+31 40 253 8046",
    "sg:postcode":"5506 BA",
    "sg:province":"Noord-Brabant",
    "wof:name":"Michielsen-Bos, Ilka",
    "wof:placetype":"venue"
},
  "geometry": {"coordinates":[5.387715,51.419987],"type":"Point"}
}