{
  "type": "Feature",
  "properties": {
    "addr:full":"Postbus 5014 Deventer NL.08 7400 GC",
    "addr:postcode":"5014;nl.08 7400 gc",
    "addr:street":"Postbus",
    "iso:country":"NL",
    "sg:address":"Postbus 5014",
    "sg:city":"Deventer",
    "sg:orig_category":"Bejaarden - Verzorgingstehuizen",
    "sg:phone":"+31 570 655 550",
    "sg:postcode":"7400 GC",
    "sg:province":"NL.08",
    "sg:website":"http://www.zorggroepsolis.nl",
    "wof:name":"Solis Stichting, Zorggroep",
    "wof:placetype":"venue"
},
  "geometry": {"coordinates":[6.15984,52.25354],"type":"Point"}
}