{
  "type": "Feature",
  "properties": {
    "iso:country":"NL",
    "sg:address":"Postbus 5014",
    "sg:city":"Deventer",
    "sg:orig_category":"Bejaarden - Verzorgingstehuizen",
    "sg:phone":"+31 570 655 550",
    "sg:postcode":"7400 GC",
    "sg:province":"NL.08",
    "sg:website":"http://www.zorggroepsolis.nl",
    "wof:name":"Solis Stichting, Zorggroep",
    "wof:placetype":"venue"
},
  "geometry": {"coordinates":[6.15984,52.25354],"type":"Point"}
}