{
  "type": "Feature",
  "properties": {
    "addr:full":"Julianastraat 22 Purmerend Noord-Holland 1441 EP",
    "addr:housenumber":"22",
    "addr:postcode":"1441 ep",
    "addr:street":"Julianastraat",
    "iso:country":"NL",
    "sg:address":"Julianastraat 22",
    "sg:city":"Purmerend",
    "sg:orig_category":"Medische Apparatuur And Prothesen Fab",
    "sg:phone":"+31 299 470 327",
    "sg:postcode":"1441 EP",
    "sg:province":"Noord-Holland",
    "wof:name":"Purmerdent Bv",
    "wof:placetype":"venue"
},
  "geometry": {"coordinates":[4.947517,52.506245],"type":"Point"}
}