{
  "type": "Feature",
  "properties": {
    "addr:full":"Europaplein 8 Gennep Limburg 6591 AV",
    "addr:housenumber":"8",
    "addr:postcode":"6591 av",
    "addr:street":"Europaplein",
    "iso:country":"NL",
    "sg:address":"Europaplein 8",
    "sg:city":"Gennep",
    "sg:orig_category":"Boekhouders",
    "sg:phone":"+31 485 361 623",
    "sg:postcode":"6591 AV",
    "sg:province":"Limburg",
    "wof:name":"Financieel En Fiscaal Buro Unicum",
    "wof:placetype":"venue"
},
  "geometry": {"coordinates":[5.971388,51.697845],"type":"Point"}
}