{
  "type": "Feature",
  "properties": {
    "addr:full":"Flevolaan 41 Naarden Noord-Holland 1411 KC",
    "addr:housenumber":"41",
    "addr:postcode":"1411 kc",
    "addr:street":"Flevolaan",
    "iso:country":"NL",
    "sg:address":"Flevolaan 41",
    "sg:city":"Naarden",
    "sg:orig_category":"Geluidsopnamen",
    "sg:phone":"+31 35 695 8411",
    "sg:postcode":"1411 KC",
    "sg:province":"Noord-Holland",
    "wof:name":"Studio Oud-Bussem Bv",
    "wof:placetype":"venue"
},
  "geometry": {"coordinates":[5.194775,52.286087],"type":"Point"}
}