{
  "type": "Feature",
  "properties": {
    "addr:full":"Putterln 30 Bilthoven Utrecht 3722 WH",
    "addr:housenumber":"30",
    "addr:postcode":"3722 wh",
    "addr:street":"Putterln",
    "iso:country":"NL",
    "sg:address":"Putterln 30",
    "sg:city":"Bilthoven",
    "sg:orig_category":"Koel- En Vriestransporten",
    "sg:phone":"+31 30 229 3208",
    "sg:postcode":"3722 WH",
    "sg:province":"Utrecht",
    "wof:name":"Slagmaat Bv, Van",
    "wof:placetype":"venue"
},
  "geometry": {"coordinates":[5.21093,52.121498],"type":"Point"}
}