{
  "type": "Feature",
  "properties": {
    "addr:full":"Prins Hendrikweg 10 Bennekom Gelderland 6721 AD",
    "addr:housenumber":"10",
    "addr:postcode":"6721 ad",
    "addr:street":"Prins Hendrikweg;Gelderland",
    "iso:country":"NL",
    "sg:address":"Prins Hendrikweg 10",
    "sg:city":"Bennekom",
    "sg:orig_category":"Diverse Consumentenartikelen Gh",
    "sg:phone":"+31 318 430 008",
    "sg:postcode":"6721 AD",
    "sg:province":"Gelderland",
    "wof:name":"Toots Trading Vof",
    "wof:placetype":"venue"
},
  "geometry": {"coordinates":[5.689111,52.002773],"type":"Point"}
}