{
  "type": "Feature",
  "properties": {
    "addr:full":"V Haestrechtsngl 86 S Hertogenbosch Noord-Brabant 5237 SK",
    "addr:housenumber":"86",
    "addr:street":"S Hertogenbosch;5237",
    "iso:country":"NL",
    "sg:address":"V Haestrechtsngl 86",
    "sg:city":"S Hertogenbosch",
    "sg:orig_category":"Nagelstudio'S",
    "sg:phone":"+31 73 614 7144",
    "sg:postcode":"5237 SK",
    "sg:province":"Noord-Brabant",
    "wof:name":"Andreas",
    "wof:placetype":"venue"
},
  "geometry": {"coordinates":[5.2886,51.730911],"type":"Point"}
}