{
  "type": "Feature",
  "properties": {
    "addr:full":"Heikantstraat 50 Someren Noord-Brabant 5712 GS",
    "addr:housenumber":"50",
    "addr:postcode":"5712 gs",
    "addr:street":"Heikantstraat",
    "iso:country":"NL",
    "sg:address":"Heikantstraat 50",
    "sg:city":"Someren",
    "sg:orig_category":"Vertaal- And Tolkenbureaus",
    "sg:phone":"+31 493 490 050",
    "sg:postcode":"5712 GS",
    "sg:province":"Noord-Brabant",
    "wof:name":"Drs W Van Lierop",
    "wof:placetype":"venue"
},
  "geometry": {"coordinates":[5.695842,51.373383],"type":"Point"}
}