{
  "type": "Feature",
  "properties": {
    "addr:full":"Dokter Stolteweg 52A Zwolle Overijssel 8025 AX",
    "addr:housenumber":"52a",
    "addr:postcode":"8025 ax",
    "addr:street":"Dokter Stolteweg",
    "iso:country":"NL",
    "sg:address":"Dokter Stolteweg 52A",
    "sg:city":"Zwolle",
    "sg:orig_category":"Bloemen And Planten Gh",
    "sg:phone":"+31 38 453 0671",
    "sg:postcode":"8025 AX",
    "sg:province":"Overijssel",
    "wof:name":"Nevema Bv",
    "wof:placetype":"venue"
},
  "geometry": {"coordinates":[6.121334,52.515507],"type":"Point"}
}