{
  "type": "Feature",
  "properties": {
    "addr:full":"Elritsstr 123 Hoogvliet Rt Zuid-Holland 3192 CC",
    "addr:housenumber":"123",
    "addr:postcode":"rt;3192 cc",
    "iso:country":"NL",
    "sg:address":"Elritsstr 123",
    "sg:city":"Hoogvliet Rt",
    "sg:orig_category":"Organisatiebureaus",
    "sg:phone":"+31 10 438 4566",
    "sg:postcode":"3192 CC",
    "sg:province":"Zuid-Holland",
    "wof:name":"Hkk",
    "wof:placetype":"venue"
},
  "geometry": {"coordinates":[4.3611941338,51.855884552],"type":"Point"}
}