{
  "type": "Feature",
  "properties": {
    "iso:country":"NL",
    "sg:address":"Elritsstr 123",
    "sg:city":"Hoogvliet Rt",
    "sg:orig_category":"Organisatiebureaus",
    "sg:phone":"+31 10 438 4566",
    "sg:postcode":"3192 CC",
    "sg:province":"Zuid-Holland",
    "wof:name":"Hkk",
    "wof:placetype":"venue"
},
  "geometry": {"coordinates":[4.3611941338,51.855884552],"type":"Point"}
}