{
  "type": "Feature",
  "properties": {
    "iso:country":"NL",
    "sg:address":"Handelsweg 6",
    "sg:city":"Alphen A/D Rijn",
    "sg:orig_category":"Chemische Producten Gh",
    "sg:phone":"+31 172 436 361",
    "sg:postcode":"2404 CD",
    "sg:province":"South Holland",
    "wof:name":"Mavom Bv",
    "wof:placetype":"venue"
},
  "geometry": {"coordinates":[4.642635,52.131332],"type":"Point"}
}