{
  "type": "Feature",
  "properties": {
    "addr:full":"Populierenlaan 23 Oirsbeek Limburg 6438 GK",
    "addr:housenumber":"23",
    "addr:postcode":"6438 gk",
    "addr:street":"Populierenlaan",
    "iso:country":"NL",
    "sg:address":"Populierenlaan 23",
    "sg:city":"Oirsbeek",
    "sg:orig_category":"Film-, Tv- And Videoproductie",
    "sg:phone":"+31 46 442 5381",
    "sg:postcode":"6438 GK",
    "sg:province":"Limburg",
    "wof:name":"P.G.G. Eggen",
    "wof:placetype":"venue"
},
  "geometry": {"coordinates":[5.902848,50.949696],"type":"Point"}
}