{
  "type": "Feature",
  "properties": {
    "addr:full":"L V Deysseldreef 41 Goirle Noord-Brabant 5051 GT",
    "addr:housenumber":"41",
    "addr:postcode":"5051 gt",
    "addr:street":"L V Deysseldreef",
    "iso:country":"NL",
    "sg:address":"L V Deysseldreef 41",
    "sg:city":"Goirle",
    "sg:orig_category":"Kantoor- En Secretariaatsservice",
    "sg:phone":"+31 13 534 7446",
    "sg:postcode":"5051 GT",
    "sg:province":"Noord-Brabant",
    "wof:name":"Aanhef Secretariaatsservices",
    "wof:placetype":"venue"
},
  "geometry": {"coordinates":[5.0678877831,51.5186233521],"type":"Point"}
}