{
  "type": "Feature",
  "properties": {
    "addr:full":"Kennedydreef 103 Ede Gld Gelderland 6716 CG",
    "addr:housenumber":"103",
    "addr:postcode":"6716 cg",
    "addr:street":"Kennedydreef;Gld Gelderland",
    "iso:country":"NL",
    "sg:address":"Kennedydreef 103",
    "sg:city":"Ede Gld",
    "sg:orig_category":"Webdesign Bureaus",
    "sg:phone":"+31 6 15185081",
    "sg:postcode":"6716 CG",
    "sg:province":"Gelderland",
    "sg:website":"http://www.maximumwebdesign.nl",
    "wof:name":"Maximum",
    "wof:placetype":"venue"
},
  "geometry": {"coordinates":[5.6418647766,52.0232696533],"type":"Point"}
}