{
  "type": "Feature",
  "properties": {
    "addr:full":"J Ligthartstr 2 Tiel Gelderland 4003 DH",
    "addr:housenumber":"2",
    "addr:postcode":"4003 dh",
    "addr:street":"Gelderland",
    "iso:country":"NL",
    "sg:address":"J Ligthartstr 2",
    "sg:city":"Tiel",
    "sg:orig_category":"Product-Promotie",
    "sg:phone":"+31 344 611 020",
    "sg:postcode":"4003 DH",
    "sg:province":"Gelderland",
    "wof:name":"Vip",
    "wof:placetype":"venue"
},
  "geometry": {"coordinates":[5.404326,51.893204],"type":"Point"}
}