{
  "type": "Feature",
  "properties": {
    "addr:full":"Laat 227 Alkmaar Noord-Holland 1811 EH",
    "addr:housenumber":"227",
    "addr:postcode":"1811 eh",
    "addr:street":"Laat",
    "iso:country":"NL",
    "sg:address":"Laat 227",
    "sg:city":"Alkmaar",
    "sg:orig_category":"Dameskleding",
    "sg:phone":"+31 72 520 0922",
    "sg:postcode":"1811 EH",
    "sg:province":"Noord-Holland",
    "wof:name":"Esprit",
    "wof:placetype":"venue"
},
  "geometry": {"coordinates":[4.74425,52.631115],"type":"Point"}
}