{
  "type": "Feature",
  "properties": {
    "addr:full":"St. Ignatiusstraat 225 Breda Noord-Brabant 4817 KJ",
    "addr:housenumber":"225",
    "addr:postcode":"4817 kj",
    "addr:street":"St. Ignatiusstraat",
    "iso:country":"NL",
    "sg:address":"St. Ignatiusstraat 225",
    "sg:city":"Breda",
    "sg:orig_category":"Kappers",
    "sg:phone":"+31 76 514 0143",
    "sg:postcode":"4817 KJ",
    "sg:province":"Noord-Brabant",
    "wof:name":"Dames En Herenkapsalon Hair",
    "wof:placetype":"venue"
},
  "geometry": {"coordinates":[4.8019170761,51.5913200378],"type":"Point"}
}