{
  "type": "Feature",
  "properties": {
    "addr:full":"Graslaan 97 Arnhem Gelderland 6833 CE",
    "addr:housenumber":"97",
    "addr:postcode":"6833 ce",
    "addr:street":"Graslaan",
    "iso:country":"NL",
    "sg:address":"Graslaan 97",
    "sg:city":"Arnhem",
    "sg:classifiers":[
        {
            "category":"Education",
            "subcategory":"Preschool",
            "type":"Public Place"
        }
    ],
    "sg:phone":"+31 26 321 8471",
    "sg:postcode":"6833 CE",
    "sg:province":"Gelderland",
    "sg:tags":[
        "kleuteronderwijs",
        "basis-"
    ],
    "wof:name":"Burgemeester De Monchyschool",
    "wof:placetype":"venue"
},
  "geometry": {"coordinates":[5.916033,51.967567],"type":"Point"}
}