{
  "type": "Feature",
  "properties": {
    "addr:full":"Vergtwg 18 Zaltbommel Gelderland 5301 TG",
    "addr:housenumber":"18",
    "addr:postcode":"5301 tg",
    "addr:street":"Vergtwg;Gelderland",
    "iso:country":"NL",
    "sg:address":"Vergtwg 18",
    "sg:city":"Zaltbommel",
    "sg:orig_category":"Acupunctuur",
    "sg:phone":"+31 418 512 662",
    "sg:postcode":"5301 TG",
    "sg:province":"Gelderland",
    "wof:name":"Schmidt, M M",
    "wof:placetype":"venue"
},
  "geometry": {"coordinates":[5.248815,51.806152],"type":"Point"}
}