{
  "type": "Feature",
  "properties": {
    "addr:full":"Ged Wyde Wyk 16 Kerkenveld Drenthe 7926 TW",
    "addr:housenumber":"16",
    "addr:postcode":"7926 tw",
    "addr:street":"Wyk",
    "iso:country":"NL",
    "sg:address":"Ged Wyde Wyk 16",
    "sg:city":"Kerkenveld",
    "sg:orig_category":"Loonbedrijven",
    "sg:phone":"+31 528 361 453",
    "sg:postcode":"7926 TW",
    "sg:province":"Drenthe",
    "wof:name":"Jonkman, Kees",
    "wof:placetype":"venue"
},
  "geometry": {"coordinates":[6.500275,52.667984],"type":"Point"}
}