{
  "type": "Feature",
  "properties": {
    "addr:full":"Willem Barentszweg 18 Venlo Limburg 5928 LM",
    "addr:housenumber":"18",
    "addr:postcode":"5928 lm",
    "addr:street":"Willem Barentszweg",
    "iso:country":"NL",
    "sg:address":"Willem Barentszweg 18",
    "sg:city":"Venlo",
    "sg:orig_category":"Metaalbekleding And -Behandeling",
    "sg:phone":"+31 77 396 7865",
    "sg:postcode":"5928 LM",
    "sg:province":"Limburg",
    "wof:name":"Ventool Slijptechniek Bv",
    "wof:placetype":"venue"
},
  "geometry": {"coordinates":[6.087938,51.390484],"type":"Point"}
}