{
  "type": "Feature",
  "properties": {
    "iso:country":"NL",
    "sg:address":"Turfstraat 39",
    "sg:city":"Zutphen",
    "sg:classifiers":[
        {
            "category":"Retail",
            "subcategory":"Photofinishing",
            "type":"Services"
        }
    ],
    "sg:phone":"+31 575 513 069",
    "sg:postcode":"7201 KE",
    "sg:province":"Gelderland",
    "sg:tags":[
        "foto",
        "film"
    ],
    "wof:name":"Foto Video Hans Drent",
    "wof:placetype":"venue"
},
  "geometry": {"coordinates":[6.196281,52.142757],"type":"Point"}
}