{
  "type": "Feature",
  "properties": {
    "addr:full":"A V Solmsstr 38 Groningen Groningen 9717 AP",
    "addr:housenumber":"38",
    "addr:postcode":"9717 ap",
    "addr:street":"A;Solmsstr",
    "iso:country":"NL",
    "sg:address":"A V Solmsstr 38",
    "sg:city":"Groningen",
    "sg:orig_category":"Vertalers",
    "sg:phone":"+31 50 360 3070",
    "sg:postcode":"9717 AP",
    "sg:province":"Groningen",
    "wof:name":"Nynke",
    "wof:placetype":"venue"
},
  "geometry": {"coordinates":[6.574715,53.217144],"type":"Point"}
}