{
  "type": "Feature",
  "properties": {
    "addr:full":"Herenwg 50 Ankeveen Noord-Holland 1244 PW",
    "addr:housenumber":"50",
    "addr:postcode":"1244 pw",
    "addr:street":"Herenwg",
    "iso:country":"NL",
    "sg:address":"Herenwg 50",
    "sg:city":"Ankeveen",
    "sg:orig_category":"Pottenbakkerijen",
    "sg:phone":"+31 35 656 5055",
    "sg:postcode":"1244 PW",
    "sg:province":"Noord-Holland",
    "wof:name":"Herenweg, Pottenbakkerij",
    "wof:placetype":"venue"
},
  "geometry": {"coordinates":[5.110417,52.251247],"type":"Point"}
}