{
  "type": "Feature",
  "properties": {
    "addr:full":"Dorpstraat 50 Lopik Utrecht 3411 AG",
    "addr:housenumber":"50",
    "addr:postcode":"3411",
    "addr:street":"Dorpstraat",
    "iso:country":"NL",
    "sg:address":"Dorpstraat 50",
    "sg:city":"Lopik",
    "sg:orig_category":"Woningbouwverenigingen",
    "sg:phone":"+31 348 553 232",
    "sg:postcode":"3411 AG",
    "sg:province":"Utrecht",
    "wof:name":"Woningbouwvereniging Lopik",
    "wof:placetype":"venue"
},
  "geometry": {"coordinates":[4.9434399605,51.9744796753],"type":"Point"}
}