{
  "type": "Feature",
  "properties": {
    "addr:full":"Postbus 4401 Velden Zeeland 5940 AA",
    "addr:housenumber":"4401",
    "addr:postcode":"5940 aa",
    "addr:street":"Postbus",
    "iso:country":"NL",
    "sg:address":"Postbus 4401",
    "sg:city":"Velden",
    "sg:orig_category":"Voetbalverenigingen",
    "sg:phone":"+31 6 20349038",
    "sg:postcode":"5940 AA",
    "sg:province":"Zeeland",
    "wof:name":"Ivo",
    "wof:placetype":"venue"
},
  "geometry": {"coordinates":[6.16551,51.414509],"type":"Point"}
}