{
  "type": "Feature",
  "properties": {
    "iso:country":"NL",
    "sg:address":"Dr Kantersln 222",
    "sg:city":"Grave",
    "sg:orig_category":"Winkelinrichting",
    "sg:phone":"+31 486 432 626",
    "sg:postcode":"5361 NL",
    "sg:province":"Noord-Brabant",
    "sg:website":"http://www.m51.nl",
    "wof:name":"M 51",
    "wof:placetype":"venue"
},
  "geometry": {"coordinates":[5.7502989769,51.7539253235],"type":"Point"}
}