{
  "type": "Feature",
  "properties": {
    "addr:full":"S Buysingstr 14 Leiden Zuid-Holland 2332 VW",
    "addr:housenumber":"14",
    "addr:postcode":"2332 vw",
    "iso:country":"NL",
    "sg:address":"S Buysingstr 14",
    "sg:city":"Leiden",
    "sg:orig_category":"Organisatiebureaus",
    "sg:phone":"+31 71 576 1175",
    "sg:postcode":"2332 VW",
    "sg:province":"Zuid-Holland",
    "wof:name":"Kempff",
    "wof:placetype":"venue"
},
  "geometry": {"coordinates":[4.4662361145,52.1588401794],"type":"Point"}
}