{
  "type": "Feature",
  "properties": {
    "addr:full":"Bijlestaal 64 Broek Op Langedijk Noord-Holland 1721 PW",
    "addr:housenumber":"64",
    "addr:postcode":"1721 pw",
    "addr:street":"Bijlestaal",
    "iso:country":"NL",
    "sg:address":"Bijlestaal 64",
    "sg:city":"Broek Op Langedijk",
    "sg:orig_category":"Beautyfarms And Sauna'S",
    "sg:phone":"+31 226 320 800",
    "sg:postcode":"1721 PW",
    "sg:province":"Noord-Holland",
    "wof:name":"Schoonheidssalon Face To Face",
    "wof:placetype":"venue"
},
  "geometry": {"coordinates":[4.792429,52.675892],"type":"Point"}
}