{
  "type": "Feature",
  "properties": {
    "iso:country":"NL",
    "sg:address":"Berkenheg 3",
    "sg:city":"Meyel",
    "sg:orig_category":"Stukadoorsbedrijven",
    "sg:phone":"+31 77 466 2942",
    "sg:postcode":"5768 PB",
    "sg:province":"Limburg",
    "wof:name":"Giel Schijven",
    "wof:placetype":"venue"
},
  "geometry": {"coordinates":[5.88575,51.34428],"type":"Point"}
}