{
  "type": "Feature",
  "properties": {
    "iso:country":"NL",
    "sg:address":"Bedryfswg 13",
    "sg:city":"Nymegen",
    "sg:orig_category":"Autoschade- Herstelbedrijven",
    "sg:phone":"+31 24 378 1995",
    "sg:postcode":"6541 DC",
    "sg:province":"Gelderland",
    "wof:name":"Geenacker",
    "wof:placetype":"venue"
},
  "geometry": {"coordinates":[-77.01458700000001,38.8937],"type":"Point"}
}