{
  "type": "Feature",
  "properties": {
    "iso:country":"NL",
    "sg:address":"Maarheezerweg 5",
    "sg:city":"Budel",
    "sg:orig_category":"Begrafenisondernemers",
    "sg:phone":"+31 495 491 459",
    "sg:postcode":"6021 CN",
    "sg:province":"North Brabant",
    "wof:name":"Uitvaartverzorging Vos",
    "wof:placetype":"venue"
},
  "geometry": {"coordinates":[5.58134,51.278564],"type":"Point"}
}