{
  "type": "Feature",
  "properties": {
    "addr:full":"A V Diemenstr 4A Culemborg Gelderland 4104 AE",
    "addr:housenumber":"4a",
    "addr:postcode":"4104 ae",
    "addr:street":"A V Diemenstr;Gelderland",
    "iso:country":"NL",
    "sg:address":"A V Diemenstr 4A",
    "sg:city":"Culemborg",
    "sg:orig_category":"Meubelen - Fabrieken En Groothandel",
    "sg:phone":"+31 345 530 639",
    "sg:postcode":"4104 AE",
    "sg:province":"Gelderland",
    "wof:name":"Thema Meubel Culemborg",
    "wof:placetype":"venue"
},
  "geometry": {"coordinates":[5.22148,51.952175],"type":"Point"}
}