{
  "type": "Feature",
  "properties": {
    "addr:full":"Sprangseweg 2 Waalwijk Noord-Brabant 5144 NV",
    "addr:housenumber":"2",
    "addr:postcode":"5144 nv",
    "addr:street":"Sprangseweg",
    "iso:country":"NL",
    "sg:address":"Sprangseweg 2",
    "sg:city":"Waalwijk",
    "sg:orig_category":"Fitnesscentra",
    "sg:phone":"+31 416 561 730",
    "sg:postcode":"5144 NV",
    "sg:province":"Noord-Brabant",
    "wof:name":"Ontspanningcentrum De Spoorlijn",
    "wof:placetype":"venue"
},
  "geometry": {"coordinates":[5.050821,51.681858],"type":"Point"}
}