{
  "type": "Feature",
  "properties": {
    "iso:country":"NL",
    "sg:address":"Lijsterstraat 26",
    "sg:city":"Groot Ammers",
    "sg:orig_category":"Begrafenisondernemers",
    "sg:phone":"+31 184 661 793",
    "sg:postcode":"2964 CD",
    "sg:province":"Zuid-Holland",
    "wof:name":"Uitvaartverzorging Annet Verheij",
    "wof:placetype":"venue"
},
  "geometry": {"coordinates":[4.825895,51.925255],"type":"Point"}
}