{
  "type": "Feature",
  "properties": {
    "addr:full":"Koekoeksedk 11A Zevenbergen Noord-Brabant 4761 RG",
    "addr:housenumber":"11a",
    "addr:postcode":"4761 rg",
    "addr:street":"Koekoeksedk",
    "iso:country":"NL",
    "sg:address":"Koekoeksedk 11A",
    "sg:city":"Zevenbergen",
    "sg:orig_category":"Machineonderhoud En -Reparatie",
    "sg:phone":"+31 168 328 979",
    "sg:postcode":"4761 RG",
    "sg:province":"Noord-Brabant",
    "wof:name":"Tbk Vof",
    "wof:placetype":"venue"
},
  "geometry": {"coordinates":[4.6087040901,51.6544380188],"type":"Point"}
}