{
  "type": "Feature",
  "properties": {
    "addr:full":"Nieuwehuizen 7 Assen Provincie Drenthe 9401 JS",
    "addr:housenumber":"7",
    "addr:postcode":"9401 js",
    "addr:street":"Nieuwehuizen;Provincie Drenthe",
    "iso:country":"NL",
    "sg:address":"Nieuwehuizen 7",
    "sg:city":"Assen",
    "sg:classifiers":[
        {
            "category":"Retail",
            "subcategory":"Photofinishing",
            "type":"Services"
        }
    ],
    "sg:phone":"+31 592 318 415",
    "sg:postcode":"9401 JS",
    "sg:province":"Provincie Drenthe",
    "sg:tags":[
        "foto",
        "film"
    ],
    "wof:name":"Foto Hilbink-Vennink",
    "wof:placetype":"venue"
},
  "geometry": {"coordinates":[6.563391,52.995495],"type":"Point"}
}