{
  "type": "Feature",
  "properties": {
    "addr:full":"Marktstr 2931 Zevenaar Gelderland 6901 AK",
    "addr:housenumber":"2931",
    "addr:postcode":"6901 ak",
    "iso:country":"NL",
    "sg:address":"Marktstr 2931",
    "sg:city":"Zevenaar",
    "sg:orig_category":"Boeken En Tijdschriften",
    "sg:phone":"+31 316 524 970",
    "sg:postcode":"6901 AK",
    "sg:province":"Gelderland",
    "wof:name":"Rebers",
    "wof:placetype":"venue"
},
  "geometry": {"coordinates":[6.07604,51.92709],"type":"Point"}
}