{
  "type": "Feature",
  "properties": {
    "addr:full":"Waterkers 11 Kockengen Utrecht 3628 NH",
    "addr:housenumber":"11",
    "addr:postcode":"3628 nh",
    "addr:street":"Waterkers",
    "iso:country":"NL",
    "sg:address":"Waterkers 11",
    "sg:city":"Kockengen",
    "sg:orig_category":"Bodemonderzoek",
    "sg:phone":"+31 346 241 900",
    "sg:postcode":"3628 NH",
    "sg:province":"Utrecht",
    "wof:name":"Verhoeven, M J C",
    "wof:placetype":"venue"
},
  "geometry": {"coordinates":[4.955674,52.15049],"type":"Point"}
}