{
  "type": "Feature",
  "properties": {
    "addr:full":"Kerkstr 25 Zaltbommel Gelderland 5301 EG",
    "addr:housenumber":"25",
    "addr:postcode":"5301 eg",
    "addr:street":"Kerkstr;Gelderland",
    "iso:country":"NL",
    "sg:address":"Kerkstr 25",
    "sg:city":"Zaltbommel",
    "sg:orig_category":"Tekstschrijversters",
    "sg:phone":"+31 418 512 979",
    "sg:postcode":"5301 EG",
    "sg:province":"Gelderland",
    "sg:website":"http://www.tekstperfect.nl",
    "wof:name":"Tekstperfect",
    "wof:placetype":"venue"
},
  "geometry": {"coordinates":[5.250964,51.813248],"type":"Point"}
}