{
  "type": "Feature",
  "properties": {
    "iso:country":"NL",
    "sg:address":"Hoogemierdseweg 2",
    "sg:city":"Lage Mierde",
    "sg:orig_category":"Banken And Kredietinstellingen",
    "sg:phone":"+31 497 650 100",
    "sg:postcode":"5094 AA",
    "sg:province":"Noord-Brabant",
    "wof:name":"Rabobank",
    "wof:placetype":"venue"
},
  "geometry": {"coordinates":[5.148596,51.405754],"type":"Point"}
}