{
  "type": "Feature",
  "properties": {
    "addr:full":"Graaf Florisweg 17 Nieuwerbrug South Holland 2415 AB",
    "addr:housenumber":"17",
    "addr:postcode":"2415 ab",
    "addr:street":"Graaf Florisweg;Nieuwerbrug South",
    "iso:country":"NL",
    "sg:address":"Graaf Florisweg 17",
    "sg:city":"Nieuwerbrug",
    "sg:orig_category":"Banken And Kredietinstellingen",
    "sg:phone":"+31 348 688 477",
    "sg:postcode":"2415 AB",
    "sg:province":"South Holland",
    "wof:name":"J C M Kompier-Vergeer",
    "wof:placetype":"venue"
},
  "geometry": {"coordinates":[4.812645,52.07732],"type":"Point"}
}