{
  "type": "Feature",
  "properties": {
    "addr:full":"Binnenhof 5 Vriezenveen NL.08 7671 GN",
    "addr:housenumber":"5;nl.08",
    "addr:postcode":"7671 gn",
    "addr:street":"Binnenhof",
    "iso:country":"NL",
    "sg:address":"Binnenhof 5",
    "sg:city":"Vriezenveen",
    "sg:orig_category":"Autokeuringen",
    "sg:phone":"+31 546 567 630",
    "sg:postcode":"7671 GN",
    "sg:province":"NL.08",
    "wof:name":"Reemeij",
    "wof:placetype":"venue"
},
  "geometry": {"coordinates":[6.619891,52.408096],"type":"Point"}
}