{
  "type": "Feature",
  "properties": {
    "addr:full":"Wagewg 17 Alkmaar Noord-Holland 1811 MK",
    "addr:housenumber":"17",
    "addr:postcode":"1811",
    "addr:street":"Wagewg",
    "iso:country":"NL",
    "sg:address":"Wagewg 17",
    "sg:city":"Alkmaar",
    "sg:classifiers":[
        {
            "category":"Retail",
            "subcategory":"Auto Repair",
            "type":"Services"
        }
    ],
    "sg:phone":"+31 72 512 5250",
    "sg:postcode":"1811 MK",
    "sg:province":"Noord-Holland",
    "sg:tags":[
        "garage"
    ],
    "wof:name":"Tools, E R",
    "wof:placetype":"venue"
},
  "geometry": {"coordinates":[4.755818,52.629982],"type":"Point"}
}