{
  "type": "Feature",
  "properties": {
    "addr:full":"Juraln 31 Son Noord-Brabant 5691 JC",
    "addr:housenumber":"31",
    "addr:postcode":"5691 jc",
    "addr:street":"Juraln",
    "iso:country":"NL",
    "sg:address":"Juraln 31",
    "sg:city":"Son",
    "sg:orig_category":"Beeldende Kunstenaars",
    "sg:phone":"+31 499 473 420",
    "sg:postcode":"5691 JC",
    "sg:province":"Noord-Brabant",
    "wof:name":"Laan, Jacqueline Van Der",
    "wof:placetype":"venue"
},
  "geometry": {"coordinates":[-101.937622,35.189621],"type":"Point"}
}