{
  "type": "Feature",
  "properties": {
    "addr:full":"W Elsschothove 39 Nieuwegein Utrecht 3437 BM",
    "addr:housenumber":"39",
    "addr:postcode":"3437 bm",
    "addr:street":"W Elsschothove",
    "iso:country":"NL",
    "sg:address":"W Elsschothove 39",
    "sg:city":"Nieuwegein",
    "sg:orig_category":"Administratie- En Boekhoudkantoren",
    "sg:phone":"+31 30 603 4256",
    "sg:postcode":"3437 BM",
    "sg:province":"Utrecht",
    "wof:name":"Henan",
    "wof:placetype":"venue"
},
  "geometry": {"coordinates":[5.072563,52.054058],"type":"Point"}
}