{
  "type": "Feature",
  "properties": {
    "addr:full":"T Spil 1 Monnickendam North Holland 1141 SB",
    "addr:housenumber":"1",
    "addr:postcode":"1141 sb",
    "addr:street":"T Spil",
    "iso:country":"NL",
    "sg:address":"T Spil 1",
    "sg:city":"Monnickendam",
    "sg:orig_category":"Overheidsdiensten",
    "sg:phone":"+31 299 650 560",
    "sg:postcode":"1141 SB",
    "sg:province":"North Holland",
    "wof:name":"Sociaal Cultureel Centrum De Bolder",
    "wof:placetype":"venue"
},
  "geometry": {"coordinates":[5.0358190536,52.4500732422],"type":"Point"}
}