{
  "type": "Feature",
  "properties": {
    "iso:country":"NL",
    "sg:address":"Brusselstraat 63",
    "sg:city":"Breda",
    "sg:orig_category":"Verzekeringen",
    "sg:phone":"+31 76 587 2748",
    "sg:postcode":"4826 NH",
    "sg:province":"North Brabant",
    "wof:name":"Van Der Sluis Assurantien",
    "wof:placetype":"venue"
},
  "geometry": {"coordinates":[4.783719,51.608799],"type":"Point"}
}