{
  "type": "Feature",
  "properties": {
    "addr:full":"Amsteldijk 166/7 Amsterdam Noord-Holland 1079 LH",
    "addr:housenumber":"166 / 7",
    "addr:postcode":"1079 lh",
    "addr:street":"Amsteldijk",
    "iso:country":"NL",
    "sg:address":"Amsteldijk 166/7",
    "sg:city":"Amsterdam",
    "sg:orig_category":"Werving And Selectie Van Vast Personeel",
    "sg:phone":"+31 20 442 0686",
    "sg:postcode":"1079 LH",
    "sg:province":"Noord-Holland",
    "sg:website":"http://www.cobtul.nl",
    "wof:name":"Cobben & Van Tulder",
    "wof:placetype":"venue"
},
  "geometry": {"coordinates":[4.9126291275,52.3438796997],"type":"Point"}
}