{
  "type": "Feature",
  "properties": {
    "addr:full":"Maldenhof 40 Amsterdam Zuidoost North Holland 1106 ER",
    "addr:housenumber":"40",
    "addr:postcode":"1106 er",
    "addr:street":"Maldenhof",
    "iso:country":"NL",
    "sg:address":"Maldenhof 40",
    "sg:city":"Amsterdam Zuidoost",
    "sg:orig_category":"Levensmiddelen - Fabrieken En Groothandel",
    "sg:phone":"+31 20 696 2383",
    "sg:postcode":"1106 ER",
    "sg:province":"North Holland",
    "wof:name":"Swaan, De",
    "wof:placetype":"venue"
},
  "geometry": {"coordinates":[4.963816,52.303844],"type":"Point"}
}