{
  "type": "Feature",
  "properties": {
    "addr:full":"Molenstraat 123 Apeldoorn Gelderland 7321 BD",
    "addr:housenumber":"123",
    "addr:postcode":"7321 bd",
    "addr:street":"Molenstraat;Gelderland",
    "iso:country":"NL",
    "sg:address":"Molenstraat 123",
    "sg:city":"Apeldoorn",
    "sg:orig_category":"Diverse Bedrijfsinstallaties Gh",
    "sg:phone":"+31 55 366 6173",
    "sg:postcode":"7321 BD",
    "sg:province":"Gelderland",
    "wof:name":"Ton Middelink Industrie- En Handelsonderneming Vof",
    "wof:placetype":"venue"
},
  "geometry": {"coordinates":[5.978538,52.212452],"type":"Point"}
}