{
  "type": "Feature",
  "properties": {
    "addr:full":"Voorstraat 83 Harlingen Friesland 8861 BH",
    "addr:housenumber":"83",
    "addr:postcode":"8861 bh",
    "addr:street":"Voorstraat",
    "iso:country":"NL",
    "sg:address":"Voorstraat 83",
    "sg:city":"Harlingen",
    "sg:orig_category":"Wasserettes And Stomerijen",
    "sg:phone":"+31 517 414 353",
    "sg:postcode":"8861 BH",
    "sg:province":"Friesland",
    "wof:name":"De Kostumerie",
    "wof:placetype":"venue"
},
  "geometry": {"coordinates":[5.4203748703,53.1747703552],"type":"Point"}
}