{
  "type": "Feature",
  "properties": {
    "addr:full":"Marcellusstr 1A Noordwyk Zh Zuid-Holland 2201 NA",
    "addr:housenumber":"1a",
    "addr:postcode":"2201 na",
    "addr:street":"Marcellusstr",
    "iso:country":"NL",
    "sg:address":"Marcellusstr 1A",
    "sg:city":"Noordwyk Zh",
    "sg:orig_category":"Meubelstoffering",
    "sg:phone":"+31 6 53526318",
    "sg:postcode":"2201 NA",
    "sg:province":"Zuid-Holland",
    "wof:name":"Hermans Paul",
    "wof:placetype":"venue"
},
  "geometry": {"coordinates":[4.447704,52.234268],"type":"Point"}
}