{
  "type": "Feature",
  "properties": {
    "addr:full":"Oranjekade 7 Haarlem North Holland 2011 VC",
    "addr:housenumber":"7",
    "addr:postcode":"2011 vc",
    "addr:street":"Oranjekade",
    "iso:country":"NL",
    "sg:address":"Oranjekade 7",
    "sg:city":"Haarlem",
    "sg:orig_category":"Diverse Grafische Activiteiten",
    "sg:phone":"+31 23 531 6762",
    "sg:postcode":"2011 VC",
    "sg:province":"North Holland",
    "wof:name":"& Studio Evers Bv.",
    "wof:placetype":"venue"
},
  "geometry": {"coordinates":[4.626464,52.379295],"type":"Point"}
}