{
  "type": "Feature",
  "properties": {
    "addr:full":"Geertje Wagemansstraat 16 Rotterdam South Holland 3065 GG",
    "addr:housenumber":"16",
    "addr:postcode":"3065 gg",
    "addr:street":"Geertje Wagemansstraat",
    "iso:country":"NL",
    "sg:address":"Geertje Wagemansstraat 16",
    "sg:city":"Rotterdam",
    "sg:orig_category":"Elektronische Bedrijfsinstallaties",
    "sg:phone":"+31 10 447 3022",
    "sg:postcode":"3065 GG",
    "sg:province":"South Holland",
    "wof:name":"Cdr Bv",
    "wof:placetype":"venue"
},
  "geometry": {"coordinates":[4.549549,51.927128],"type":"Point"}
}