{
  "type": "Feature",
  "properties": {
    "addr:full":"Kwartelstraat 1 Breda Noord-Brabant 4815 GG",
    "addr:housenumber":"1",
    "addr:postcode":"4815 gg",
    "addr:street":"Kwartelstraat",
    "iso:country":"NL",
    "sg:address":"Kwartelstraat 1",
    "sg:city":"Breda",
    "sg:orig_category":"Bedrijfsinventaris Gh",
    "sg:phone":"+31 76 571 2617",
    "sg:postcode":"4815 GG",
    "sg:province":"Noord-Brabant",
    "wof:name":"De Etalagemaker",
    "wof:placetype":"venue"
},
  "geometry": {"coordinates":[4.774946,51.597713],"type":"Point"}
}