{
  "type": "Feature",
  "properties": {
    "addr:full":"Ziekerstraat 65 Nijmegen Gelderland 6511 LE",
    "addr:housenumber":"65",
    "addr:postcode":"6511 le",
    "addr:street":"Ziekerstraat;Gelderland",
    "iso:country":"NL",
    "sg:address":"Ziekerstraat 65",
    "sg:city":"Nijmegen",
    "sg:classifiers":[
        {
            "category":"Retail",
            "subcategory":"Photofinishing",
            "type":"Services"
        }
    ],
    "sg:phone":"+31 24 323 0550",
    "sg:postcode":"6511 LE",
    "sg:province":"Gelderland",
    "sg:tags":[
        "foto",
        "film"
    ],
    "wof:name":"Super Photo Kral Fotoshop",
    "wof:placetype":"venue"
},
  "geometry": {"coordinates":[5.865207,51.844364],"type":"Point"}
}