{
  "type": "Feature",
  "properties": {
    "iso:country":"NL",
    "sg:address":"Stationstr 1",
    "sg:city":"Meerssen",
    "sg:orig_category":"Juweliers",
    "sg:phone":"+31 43 364 2569",
    "sg:postcode":"6231 CK",
    "sg:province":"Limburg",
    "wof:name":"Riand",
    "wof:placetype":"venue"
},
  "geometry": {"coordinates":[5.752171,50.883217],"type":"Point"}
}