{
  "type": "Feature",
  "properties": {
    "addr:full":"Posthuisstr 26 Tegelen Limburg 5931 EN",
    "addr:housenumber":"26",
    "addr:postcode":"5931 en",
    "addr:street":"Posthuisstr",
    "iso:country":"NL",
    "sg:address":"Posthuisstr 26",
    "sg:city":"Tegelen",
    "sg:orig_category":"Verzekeringen - Verzekeringskantoren",
    "sg:phone":"+31 77 373 0772",
    "sg:postcode":"5931 EN",
    "sg:province":"Limburg",
    "wof:name":"Hamans",
    "wof:placetype":"venue"
},
  "geometry": {"coordinates":[6.134597,51.342415],"type":"Point"}
}