{
  "type": "Feature",
  "properties": {
    "addr:full":"Dorpstraat 22 Grathem Limburg 6096 AJ",
    "addr:housenumber":"22",
    "addr:postcode":"6096 aj",
    "addr:street":"Dorpstraat",
    "iso:country":"NL",
    "sg:address":"Dorpstraat 22",
    "sg:city":"Grathem",
    "sg:orig_category":"Kappers",
    "sg:phone":"+31 475 451 654",
    "sg:postcode":"6096 AJ",
    "sg:province":"Limburg",
    "wof:name":"J.C.P. Zentjens",
    "wof:placetype":"venue"
},
  "geometry": {"coordinates":[5.8590011597,51.1924324036],"type":"Point"}
}