{
  "type": "Feature",
  "properties": {
    "addr:full":"Cruquiuswg 86 Amsterdam North Holland 1019 AJ",
    "addr:housenumber":"86",
    "addr:postcode":"1019 aj",
    "addr:street":"Cruquiuswg",
    "iso:country":"NL",
    "sg:address":"Cruquiuswg 86",
    "sg:city":"Amsterdam",
    "sg:orig_category":"Autoschade- Herstelbedrijven",
    "sg:phone":"+31 20 668 2630",
    "sg:postcode":"1019 AJ",
    "sg:province":"North Holland",
    "sg:website":"http://www.autoschadedrenth.nl",
    "wof:name":"Drenth Bv, Autoschade",
    "wof:placetype":"venue"
},
  "geometry": {"coordinates":[4.947822,52.36853],"type":"Point"}
}