{
  "type": "Feature",
  "properties": {
    "addr:full":"Heilaarstr 196 Breda North Brabant 4814 NR",
    "addr:housenumber":"196",
    "addr:postcode":"4814 nr",
    "iso:country":"NL",
    "sg:address":"Heilaarstr 196",
    "sg:city":"Breda",
    "sg:orig_category":"Makelaars En Adviseurs Onroerende Goederen",
    "sg:phone":"+31 76 522 7194",
    "sg:postcode":"4814 NR",
    "sg:province":"North Brabant",
    "sg:website":"http://www.lambregtsensweep.nl",
    "wof:name":"Lambregts & Sweep Makelaardij",
    "wof:placetype":"venue"
},
  "geometry": {"coordinates":[4.73632,51.586391],"type":"Point"}
}