{
  "type": "Feature",
  "properties": {
    "addr:full":"Schipperswal 5 Roermond Limburg 6041 TC",
    "addr:housenumber":"5",
    "addr:postcode":"6041 tc",
    "addr:street":"Schipperswal",
    "iso:country":"NL",
    "sg:address":"Schipperswal 5",
    "sg:city":"Roermond",
    "sg:orig_category":"Weegbruggen",
    "sg:phone":"+31 475 384 142",
    "sg:postcode":"6041 TC",
    "sg:province":"Limburg",
    "wof:name":"Kalle En Bakker",
    "wof:placetype":"venue"
},
  "geometry": {"coordinates":[5.9850177765,51.2008628845],"type":"Point"}
}