{
  "type": "Feature",
  "properties": {
    "addr:full":"Eendrachtswg 49C Rotterdam Zuid-Holland 3012 LD",
    "addr:housenumber":"49c",
    "addr:postcode":"3012 ld",
    "addr:street":"Eendrachtswg",
    "iso:country":"NL",
    "sg:address":"Eendrachtswg 49C",
    "sg:city":"Rotterdam",
    "sg:orig_category":"Loopbaanbegeleiding",
    "sg:phone":"+31 10 213 0789",
    "sg:postcode":"3012 LD",
    "sg:province":"Zuid-Holland",
    "wof:name":"Ackerman, E J",
    "wof:placetype":"venue"
},
  "geometry": {"coordinates":[4.476148,51.913952],"type":"Point"}
}