{
  "type": "Feature",
  "properties": {
    "iso:country":"NL",
    "sg:address":"Postbus 76520",
    "sg:city":"Amsterdam",
    "sg:orig_category":"Geluidsinstallaties",
    "sg:phone":"+31 20 470 5044",
    "sg:postcode":"1070 HC",
    "sg:province":"Noord-Holland",
    "sg:website":"http://www.hifinesse.nl",
    "wof:name":"Hifinesse",
    "wof:placetype":"venue"
},
  "geometry": {"coordinates":[4.89205,52.37355],"type":"Point"}
}