{
  "type": "Feature",
  "properties": {
    "iso:country":"NL",
    "sg:address":"Gerwensewg 50",
    "sg:city":"Helmond",
    "sg:orig_category":"Autoschade- Herstelbedrijven",
    "sg:phone":"+31 492 538 255",
    "sg:postcode":"5708 EK",
    "sg:province":"North Brabant",
    "wof:name":"Alards",
    "wof:placetype":"venue"
},
  "geometry": {"coordinates":[5.609358,51.485638],"type":"Point"}
}