{
  "type": "Feature",
  "properties": {
    "addr:full":"Newtonlaan 53 Utrecht Utrecht 3584 BP",
    "addr:housenumber":"53",
    "addr:postcode":"3584 bp",
    "addr:street":"Newtonlaan",
    "iso:country":"NL",
    "sg:address":"Newtonlaan 53",
    "sg:city":"Utrecht",
    "sg:classifiers":[
        {
            "category":"Professional",
            "subcategory":"Accounting & Tax Preparation",
            "type":"Services"
        }
    ],
    "sg:phone":"+31 30 252 1344",
    "sg:postcode":"3584 BP",
    "sg:province":"Utrecht",
    "sg:tags":[
        "accountant"
    ],
    "wof:name":"Accountantskantoor Van Herwijnen & Co",
    "wof:placetype":"venue"
},
  "geometry": {"coordinates":[5.149285,52.090801],"type":"Point"}
}