{
  "type": "Feature",
  "properties": {
    "iso:country":"NL",
    "sg:address":"Bellestein 61G",
    "sg:city":"Ede Gld",
    "sg:orig_category":"Manueel Therapeuten",
    "sg:phone":"+31 318 641 810",
    "sg:postcode":"6714 DP",
    "sg:province":"Gelderland",
    "wof:name":"Kropman, J C",
    "wof:placetype":"venue"
},
  "geometry": {"coordinates":[5.644543,52.042328],"type":"Point"}
}