{
  "type": "Feature",
  "properties": {
    "iso:country":"NL",
    "sg:address":"Utrechtsestraat 40",
    "sg:city":"Arnhem",
    "sg:orig_category":"Overheidsdiensten",
    "sg:phone":"+31 26 352 2211",
    "sg:postcode":"6811 LZ",
    "sg:province":"Gelderland",
    "wof:name":"Cadans",
    "wof:placetype":"venue"
},
  "geometry": {"coordinates":[5.897465229,51.983833313],"type":"Point"}
}