{
  "type": "Feature",
  "properties": {
    "iso:country":"NL",
    "sg:address":"Heklanden 69",
    "sg:city":"Assen",
    "sg:orig_category":"Administratie- En Boekhoudkantoren",
    "sg:phone":"+31 592 344 098",
    "sg:postcode":"9407 PL",
    "sg:province":"Drenthe",
    "wof:name":"Mulder",
    "wof:placetype":"venue"
},
  "geometry": {"coordinates":[6.562931,53.021378],"type":"Point"}
}