{
  "type": "Feature",
  "properties": {
    "addr:full":"Hoofdstr 143 Ryen Noord-Brabant 5121 JD",
    "addr:housenumber":"143",
    "addr:postcode":"5121 jd",
    "iso:country":"NL",
    "sg:address":"Hoofdstr 143",
    "sg:city":"Ryen",
    "sg:orig_category":"Glasindustrie?n",
    "sg:phone":"+31 161 220 278",
    "sg:postcode":"5121 JD",
    "sg:province":"Noord-Brabant",
    "sg:website":"http://www.contour-glas.nl",
    "wof:name":"Contour, Glasbuigerij",
    "wof:placetype":"venue"
},
  "geometry": {"coordinates":[4.9197,51.588017],"type":"Point"}
}