{
  "type": "Feature",
  "properties": {
    "addr:full":"Rijnzathe 8 De Meern Utrecht 3454 PV",
    "addr:housenumber":"8",
    "addr:postcode":"3454 pv",
    "addr:street":"Rijnzathe",
    "iso:country":"NL",
    "sg:address":"Rijnzathe 8",
    "sg:city":"De Meern",
    "sg:orig_category":"Overheidsdiensten",
    "sg:phone":"+31 30 669 7033",
    "sg:postcode":"3454 PV",
    "sg:province":"Utrecht",
    "wof:name":"Anvr Federatie",
    "wof:placetype":"venue"
},
  "geometry": {"coordinates":[5.0517911911,52.0716629028],"type":"Point"}
}