{
  "type": "Feature",
  "properties": {
    "addr:full":"Klanderij 132 Enschede Overijssel 7511 HT",
    "addr:housenumber":"132",
    "addr:postcode":"7511 ht",
    "addr:street":"Klanderij",
    "iso:country":"NL",
    "sg:address":"Klanderij 132",
    "sg:city":"Enschede",
    "sg:orig_category":"Kappers",
    "sg:phone":"+31 53 430 7373",
    "sg:postcode":"7511 HT",
    "sg:province":"Overijssel",
    "wof:name":"Madame & Monsieur Coiffure",
    "wof:placetype":"venue"
},
  "geometry": {"coordinates":[6.898461,52.218227],"type":"Point"}
}