{
  "type": "Feature",
  "properties": {
    "addr:full":"Mozartln 280 S Gravenhage Zuid-Holland 2555 KZ",
    "addr:housenumber":"280;gravenhage",
    "addr:postcode":"2555 kz",
    "addr:street":"S",
    "iso:country":"NL",
    "sg:address":"Mozartln 280",
    "sg:city":"S Gravenhage",
    "sg:orig_category":"Bejaarden - Verzorgingstehuizen",
    "sg:phone":"+31 70 890 9100",
    "sg:postcode":"2555 KZ",
    "sg:province":"Zuid-Holland",
    "sg:website":"http://www.tabitha-haaglanden.nl",
    "wof:name":"Tabitha",
    "wof:placetype":"venue"
},
  "geometry": {"coordinates":[4.2417,52.06638],"type":"Point"}
}