{
  "type": "Feature",
  "properties": {
    "iso:country":"NL",
    "sg:address":"Boulevard Paulus Loot 17",
    "sg:city":"Zandvoort",
    "sg:classifiers":[
        {
            "category":"Fast Food",
            "type":"Food & Drink"
        }
    ],
    "sg:phone":"+31 23 571 8178",
    "sg:postcode":"2042 AD",
    "sg:province":"Noord-Holland",
    "sg:tags":[
        "afhaal",
        "restaurant"
    ],
    "wof:name":"La Rondine",
    "wof:placetype":"venue"
},
  "geometry": {"coordinates":[4.523374,52.370148],"type":"Point"}
}