{
  "type": "Feature",
  "properties": {
    "addr:full":"Bettoweg 21 Schiedam Zuid-Holland 3125 AB",
    "addr:housenumber":"21",
    "addr:postcode":"3125 ab",
    "addr:street":"Bettoweg",
    "iso:country":"NL",
    "sg:address":"Bettoweg 21",
    "sg:city":"Schiedam",
    "sg:orig_category":"Diverse Bedrijfsinstallaties Gh",
    "sg:phone":"+31 10 437 4677",
    "sg:postcode":"3125 AB",
    "sg:province":"Zuid-Holland",
    "wof:name":"Air Trading Rotterdam Bv",
    "wof:placetype":"venue"
},
  "geometry": {"coordinates":[4.410696,51.925102],"type":"Point"}
}