{
  "type": "Feature",
  "properties": {
    "addr:full":"Oostersngl 36A Culemborg Gelderland 4101 GH",
    "addr:housenumber":"36a",
    "addr:postcode":"4101 gh",
    "addr:street":"Oostersngl;Gelderland",
    "iso:country":"NL",
    "sg:address":"Oostersngl 36A",
    "sg:city":"Culemborg",
    "sg:orig_category":"Psychotherapeuten",
    "sg:phone":"+31 345 515 669",
    "sg:postcode":"4101 GH",
    "sg:province":"Gelderland",
    "wof:name":"Sinnema, Dr G",
    "wof:placetype":"venue"
},
  "geometry": {"coordinates":[5.22148,51.952175],"type":"Point"}
}