{
  "type": "Feature",
  "properties": {
    "addr:full":"Noorderhaven 64 Groningen Groningen 9712 VM",
    "addr:housenumber":"64",
    "addr:postcode":"9712 vm",
    "addr:street":"Noorderhaven",
    "iso:country":"NL",
    "sg:address":"Noorderhaven 64",
    "sg:city":"Groningen",
    "sg:orig_category":"Adviesbureaus Bedrijfsorganisatie",
    "sg:phone":"+31 50 313 0203",
    "sg:postcode":"9712 VM",
    "sg:province":"Groningen",
    "sg:website":"http://www.vanraad.nl",
    "wof:name":"Raad Consults, Van",
    "wof:placetype":"venue"
},
  "geometry": {"coordinates":[6.557671,53.21925],"type":"Point"}
}