{
  "type": "Feature",
  "properties": {
    "addr:full":"Mercuriuswg 3A Zutphen Gelderland 7202 BS",
    "addr:housenumber":"3a",
    "addr:postcode":"7202 bs",
    "addr:street":"Mercuriuswg;Gelderland",
    "iso:country":"NL",
    "sg:address":"Mercuriuswg 3A",
    "sg:city":"Zutphen",
    "sg:orig_category":"Verf En Lak - Fabrieken En Groothandel",
    "sg:phone":"+31 575 515 213",
    "sg:postcode":"7202 BS",
    "sg:province":"Gelderland",
    "wof:name":"Zutphen",
    "wof:placetype":"venue"
},
  "geometry": {"coordinates":[6.198002,52.153034],"type":"Point"}
}