{
  "type": "Feature",
  "properties": {
    "addr:full":"Iseoplnts 24 Amsterdam Noord-Holland 1060 PW",
    "addr:housenumber":"24",
    "addr:postcode":"1060 pw",
    "addr:street":"Iseoplnts",
    "iso:country":"NL",
    "sg:address":"Iseoplnts 24",
    "sg:city":"Amsterdam",
    "sg:orig_category":"Journalisten Freelance",
    "sg:phone":"+31 20 667 2501",
    "sg:postcode":"1060 PW",
    "sg:province":"Noord-Holland",
    "wof:name":"Emous",
    "wof:placetype":"venue"
},
  "geometry": {"coordinates":[4.77754,52.34988],"type":"Point"}
}