{
  "type": "Feature",
  "properties": {
    "addr:full":"St Odulphusstr 69 Bakhuizen Provincie Friesland 8574 SZ",
    "addr:housenumber":"69",
    "addr:postcode":"8574 sz",
    "addr:street":"Provincie Friesland",
    "iso:country":"NL",
    "sg:address":"St Odulphusstr 69",
    "sg:city":"Bakhuizen",
    "sg:orig_category":"Verenigingsgebouwen",
    "sg:phone":"+31 514 581 259",
    "sg:postcode":"8574 SZ",
    "sg:province":"Provincie Friesland",
    "wof:name":"Gearte, Mfc De",
    "wof:placetype":"venue"
},
  "geometry": {"coordinates":[5.45547,52.868912],"type":"Point"}
}