{
  "type": "Feature",
  "properties": {
    "addr:full":"Lijnbaan 66 Zoetermeer Zuid-Holland 2728 AK",
    "addr:housenumber":"66",
    "addr:postcode":"2728 ak",
    "addr:street":"Lijnbaan",
    "iso:country":"NL",
    "sg:address":"Lijnbaan 66",
    "sg:city":"Zoetermeer",
    "sg:orig_category":"Glaszetten",
    "sg:phone":"+31 79 342 1294",
    "sg:postcode":"2728 AK",
    "sg:province":"Zuid-Holland",
    "wof:name":"Keller",
    "wof:placetype":"venue"
},
  "geometry": {"coordinates":[4.516846,52.075809],"type":"Point"}
}