{
  "type": "Feature",
  "properties": {
    "addr:full":"Choorstraat 50 Delft Zuid-Holland 2611 JH",
    "addr:housenumber":"50",
    "addr:postcode":"2611 jh",
    "addr:street":"Choorstraat",
    "iso:country":"NL",
    "sg:address":"Choorstraat 50",
    "sg:city":"Delft",
    "sg:classifiers":[
        {
            "category":"Fast Food",
            "type":"Food & Drink"
        }
    ],
    "sg:phone":"+31 15 212 5022",
    "sg:postcode":"2611 JH",
    "sg:province":"Zuid-Holland",
    "sg:tags":[
        "afhaal",
        "restaurant"
    ],
    "wof:name":"Indonesisch Restaurant Redjeki",
    "wof:placetype":"venue"
},
  "geometry": {"coordinates":[4.358463,52.013294],"type":"Point"}
}