{
  "type": "Feature",
  "properties": {
    "addr:full":"Biestsestraat 20 Biest Houtakker Noord-Brabant 5084 HE",
    "addr:housenumber":"20",
    "addr:postcode":"5084 he",
    "addr:street":"Biestsestraat",
    "iso:country":"NL",
    "sg:address":"Biestsestraat 20",
    "sg:city":"Biest Houtakker",
    "sg:orig_category":"Banken And Kredietinstellingen",
    "sg:phone":"+31 13 505 8505",
    "sg:postcode":"5084 HE",
    "sg:province":"Noord-Brabant",
    "wof:name":"Rabobank",
    "wof:placetype":"venue"
},
  "geometry": {"coordinates":[5.160023,51.507191],"type":"Point"}
}