{
  "type": "Feature",
  "properties": {
    "iso:country":"NL",
    "sg:address":"Raadhuisstr 29",
    "sg:city":"Heemstede",
    "sg:orig_category":"Wereldwinkels",
    "sg:phone":"+31 23 529 1770",
    "sg:postcode":"2101 HC",
    "sg:province":"Noord-Holland",
    "wof:name":"Wereldwinkel Heemstede",
    "wof:placetype":"venue"
},
  "geometry": {"coordinates":[4.6203079224,52.3478813171],"type":"Point"}
}