{
  "type": "Feature",
  "properties": {
    "addr:full":"Jachtln 14 Ede Gld Gelderland 6713 KM",
    "addr:housenumber":"14",
    "addr:street":"Jachtln;Gld Gelderland 6713 Km",
    "iso:country":"NL",
    "sg:address":"Jachtln 14",
    "sg:city":"Ede Gld",
    "sg:orig_category":"Scholen Voor Algemeen Voortgezet Onderwijs",
    "sg:phone":"+31 318 630 414",
    "sg:postcode":"6713 KM",
    "sg:province":"Gelderland",
    "wof:name":"Pallas Athene Coll",
    "wof:placetype":"venue"
},
  "geometry": {"coordinates":[5.667675,52.044979],"type":"Point"}
}