{
  "type": "Feature",
  "properties": {
    "addr:full":"Oostburgsestr 36 Zuidzande Zeeland 4505 AC",
    "addr:housenumber":"36",
    "addr:postcode":"4505 ac",
    "addr:street":"Oostburgsestr",
    "iso:country":"NL",
    "sg:address":"Oostburgsestr 36",
    "sg:city":"Zuidzande",
    "sg:orig_category":"Woninginrichting",
    "sg:phone":"+31 117 441 010",
    "sg:postcode":"4505 AC",
    "sg:province":"Zeeland",
    "sg:website":"http://www.evenkijken.nl",
    "wof:name":"Even Kijken, Meubelhuis",
    "wof:placetype":"venue"
},
  "geometry": {"coordinates":[3.4592680931,51.3365898132],"type":"Point"}
}