{
  "type": "Feature",
  "properties": {
    "addr:full":"Vliersingel 90 Deurne Noord-Brabant 5754 DS",
    "addr:housenumber":"90",
    "addr:postcode":"5754 ds",
    "addr:street":"Vliersingel",
    "iso:country":"NL",
    "sg:address":"Vliersingel 90",
    "sg:city":"Deurne",
    "sg:orig_category":"Loodgieterswerk, Verwarming And Sanitaire Installaties",
    "sg:phone":"+31 493 320 123",
    "sg:postcode":"5754 DS",
    "sg:province":"Noord-Brabant",
    "wof:name":"E.M.A.F. Van Veghel-Daniels",
    "wof:placetype":"venue"
},
  "geometry": {"coordinates":[5.808625,51.470325],"type":"Point"}
}