{
  "type": "Feature",
  "properties": {
    "addr:full":"Haaksbergsewg 42 Neede Gelderland 7161 BK",
    "addr:housenumber":"42",
    "addr:postcode":"7161 bk",
    "addr:street":"Haaksbergsewg;Gelderland",
    "iso:country":"NL",
    "sg:address":"Haaksbergsewg 42",
    "sg:city":"Neede",
    "sg:orig_category":"Antiquiteiten",
    "sg:phone":"+31 6 53271835",
    "sg:postcode":"7161 BK",
    "sg:province":"Gelderland",
    "sg:website":"HTTP://www.maporte.nl",
    "wof:name":"Maporte Huis En Hof",
    "wof:placetype":"venue"
},
  "geometry": {"coordinates":[-121.31706200000001,38.299633],"type":"Point"}
}