{
  "type": "Feature",
  "properties": {
    "addr:full":"Verheydenstraat 3 Raalte NL.08 8101 BK",
    "addr:housenumber":"3;nl.08",
    "addr:postcode":"8101 bk",
    "addr:street":"Verheydenstraat",
    "iso:country":"NL",
    "sg:address":"Verheydenstraat 3",
    "sg:city":"Raalte",
    "sg:orig_category":"Huishoudapparatuur, Televisies And Radio'S",
    "sg:phone":"+31 572 351 919",
    "sg:postcode":"8101 BK",
    "sg:province":"NL.08",
    "wof:name":"J.J. Kleinherenbrink",
    "wof:placetype":"venue"
},
  "geometry": {"coordinates":[6.271669,52.383759],"type":"Point"}
}