{
  "type": "Feature",
  "properties": {
    "addr:full":"Langstr 133 Venray Limburg 5801 AC",
    "addr:housenumber":"133",
    "addr:postcode":"5801 ac",
    "iso:country":"NL",
    "sg:address":"Langstr 133",
    "sg:city":"Venray",
    "sg:orig_category":"Bloemen En Planten",
    "sg:phone":"+31 478 588 585",
    "sg:postcode":"5801 AC",
    "sg:province":"Limburg",
    "wof:name":"Intratuin Venray",
    "wof:placetype":"venue"
},
  "geometry": {"coordinates":[5.965206,51.514603],"type":"Point"}
}