{
  "type": "Feature",
  "properties": {
    "addr:full":"Klopperman 4 Wateringen Zuid-Holland 2292 JD",
    "addr:housenumber":"4",
    "addr:postcode":"2292 jd",
    "addr:street":"Klopperman",
    "iso:country":"NL",
    "sg:address":"Klopperman 4",
    "sg:city":"Wateringen",
    "sg:orig_category":"Natuurvoeding En Reformartikelen - Fabrieken En Groothandel",
    "sg:phone":"+31 174 226 288",
    "sg:postcode":"2292 JD",
    "sg:province":"Zuid-Holland",
    "sg:website":"http://www.fitshape.com",
    "wof:name":"Fitshape Bv",
    "wof:placetype":"venue"
},
  "geometry": {"coordinates":[4.297774,52.014011],"type":"Point"}
}