{
  "type": "Feature",
  "properties": {
    "addr:full":"Peursumseweg 19 Giessenburg South Holland 3381 KT",
    "addr:housenumber":"19",
    "addr:postcode":"3381 kt",
    "addr:street":"Peursumseweg",
    "iso:country":"NL",
    "sg:address":"Peursumseweg 19",
    "sg:city":"Giessenburg",
    "sg:orig_category":"Banken And Kredietinstellingen",
    "sg:phone":"+31 184 657 500",
    "sg:postcode":"3381 KT",
    "sg:province":"South Holland",
    "wof:name":"Rabobank",
    "wof:placetype":"venue"
},
  "geometry": {"coordinates":[4.889529,51.853359],"type":"Point"}
}