{
  "type": "Feature",
  "properties": {
    "iso:country":"NL",
    "sg:address":"Kapittelwg 271",
    "sg:city":"Hilversum",
    "sg:orig_category":"Drogisterijen",
    "sg:phone":"+31 35 624 8229",
    "sg:postcode":"1216 HZ",
    "sg:province":"Noord-Holland",
    "sg:website":"http://www.drogisterijeva.nl",
    "wof:name":"Eva Da-Drogist",
    "wof:placetype":"venue"
},
  "geometry": {"coordinates":[5.14043,52.215481],"type":"Point"}
}