{
  "type": "Feature",
  "properties": {
    "addr:full":"Molenstr 32 Uitgeest Noord-Holland 1911 DA",
    "addr:housenumber":"32",
    "addr:postcode":"1911 da",
    "addr:street":"Molenstr",
    "iso:country":"NL",
    "sg:address":"Molenstr 32",
    "sg:city":"Uitgeest",
    "sg:orig_category":"Metaalbewerking",
    "sg:phone":"+31 251 310 119",
    "sg:postcode":"1911 DA",
    "sg:province":"Noord-Holland",
    "wof:name":"Arrow Technics",
    "wof:placetype":"venue"
},
  "geometry": {"coordinates":[4.719593,52.534172],"type":"Point"}
}