{
  "type": "Feature",
  "properties": {
    "addr:full":"Nw Almersdorperwg 12 Middenmeer North Holland 1775 RC",
    "addr:housenumber":"12",
    "addr:postcode":"1775 rc",
    "iso:country":"NL",
    "sg:address":"Nw Almersdorperwg 12",
    "sg:city":"Middenmeer",
    "sg:orig_category":"Bloemen En Planten - Decoratie",
    "sg:phone":"+31 227 656 252",
    "sg:postcode":"1775 RC",
    "sg:province":"North Holland",
    "wof:name":"Binderij, De",
    "wof:placetype":"venue"
},
  "geometry": {"coordinates":[5.020123,52.778931],"type":"Point"}
}