{
  "type": "Feature",
  "properties": {
    "iso:country":"NL",
    "sg:address":"Rollostr 75",
    "sg:city":"Rotterdam",
    "sg:orig_category":"Verenigingsgebouwen",
    "sg:phone":"+31 10 429 0202",
    "sg:postcode":"3084 PM",
    "sg:province":"South Holland",
    "wof:name":"Wielewaal, Activiteiten Centr",
    "wof:placetype":"venue"
},
  "geometry": {"coordinates":[4.460537,51.879436],"type":"Point"}
}