{
  "type": "Feature",
  "properties": {
    "addr:full":"Rembrandtweg 146 Amstelveen Noord-Holland 1181 GX",
    "addr:housenumber":"146",
    "addr:postcode":"1181 gx",
    "addr:street":"Rembrandtweg",
    "iso:country":"NL",
    "sg:address":"Rembrandtweg 146",
    "sg:city":"Amstelveen",
    "sg:orig_category":"Meubelzaken, Woning- And Keukeninrichting",
    "sg:phone":"+31 20 641 7116",
    "sg:postcode":"1181 GX",
    "sg:province":"Noord-Holland",
    "wof:name":"Art D'Interieur Annes",
    "wof:placetype":"venue"
},
  "geometry": {"coordinates":[4.862153,52.305279],"type":"Point"}
}