{
  "type": "Feature",
  "properties": {
    "addr:full":"Amstelplein 71 Uithoorn Noord-Holland 1421 SB",
    "addr:housenumber":"71",
    "addr:postcode":"1421 sb",
    "addr:street":"Amstelplein",
    "iso:country":"NL",
    "sg:address":"Amstelplein 71",
    "sg:city":"Uithoorn",
    "sg:orig_category":"Zuivelproducten And Spijsoli?n Gh",
    "sg:phone":"+31 297 567 001",
    "sg:postcode":"1421 SB",
    "sg:province":"Noord-Holland",
    "wof:name":"Den Hollander Kaasmarkt",
    "wof:placetype":"venue"
},
  "geometry": {"coordinates":[4.828221,52.232597],"type":"Point"}
}