{
  "type": "Feature",
  "properties": {
    "iso:country":"NL",
    "sg:address":"Galicie 2",
    "sg:city":"Leusden",
    "sg:orig_category":"Binnenhuisarchitecten",
    "sg:phone":"+31 33 495 2023",
    "sg:postcode":"3831 JD",
    "sg:province":"Utrecht",
    "wof:name":"Md-Design",
    "wof:placetype":"venue"
},
  "geometry": {"coordinates":[5.434205,52.136543],"type":"Point"}
}