{
  "type": "Feature",
  "properties": {
    "addr:full":"Papeln 2 Voorschoten South Holland 2252 EJ",
    "addr:housenumber":"2",
    "addr:postcode":"2252 ej",
    "addr:street":"Papeln",
    "iso:country":"NL",
    "sg:address":"Papeln 2",
    "sg:city":"Voorschoten",
    "sg:classifiers":[
        {
            "category":"Retail",
            "subcategory":"Auto Repair",
            "type":"Services"
        }
    ],
    "sg:phone":"+31 71 561 4242",
    "sg:postcode":"2252 EJ",
    "sg:province":"South Holland",
    "sg:tags":[
        "garage"
    ],
    "wof:name":"Placar, Auto",
    "wof:placetype":"venue"
},
  "geometry": {"coordinates":[4.44429,52.124825],"type":"Point"}
}