{
  "type": "Feature",
  "properties": {
    "addr:full":"Westelykedwwg 4 Hoofdplaat Zeeland 4513 KJ",
    "addr:housenumber":"4",
    "addr:postcode":"4513 kj",
    "addr:street":"Westelykedwwg",
    "iso:country":"NL",
    "sg:address":"Westelykedwwg 4",
    "sg:city":"Hoofdplaat",
    "sg:orig_category":"Kappers",
    "sg:phone":"+31 117 348 060",
    "sg:postcode":"4513 KJ",
    "sg:province":"Zeeland",
    "wof:name":"Ang?le",
    "wof:placetype":"venue"
},
  "geometry": {"coordinates":[3.6054999828,51.3795394897],"type":"Point"}
}