{
  "type": "Feature",
  "properties": {
    "addr:full":"Burg Struykstr 1 Dordrecht Zuid-Holland 3319 CD",
    "addr:housenumber":"1",
    "addr:postcode":"3319 cd",
    "addr:street":"Burg Struykstr",
    "iso:country":"NL",
    "sg:address":"Burg Struykstr 1",
    "sg:city":"Dordrecht",
    "sg:orig_category":"Fotoreportages",
    "sg:phone":"+31 78 616 5252",
    "sg:postcode":"3319 CD",
    "sg:province":"Zuid-Holland",
    "wof:name":"Machiel, Mol",
    "wof:placetype":"venue"
},
  "geometry": {"coordinates":[4.701594,51.79771],"type":"Point"}
}