{
  "type": "Feature",
  "properties": {
    "addr:full":"Westenesscherstr 56 Emmen Drenthe 7814 TA",
    "addr:housenumber":"56",
    "addr:postcode":"7814 ta",
    "addr:street":"Westenesscherstr",
    "iso:country":"NL",
    "sg:address":"Westenesscherstr 56",
    "sg:city":"Emmen",
    "sg:orig_category":"Kunsthandel",
    "sg:phone":"+31 591 640 147",
    "sg:postcode":"7814 TA",
    "sg:province":"Drenthe",
    "wof:name":"Lange, De",
    "wof:placetype":"venue"
},
  "geometry": {"coordinates":[6.883987,52.785522],"type":"Point"}
}