{
  "type": "Feature",
  "properties": {
    "iso:country":"NL",
    "sg:address":"Dominee T O Hylkemaweg 30",
    "sg:city":"Giethoorn",
    "sg:orig_category":"Kappers",
    "sg:phone":"+31 521 361 233",
    "sg:postcode":"8355 CE",
    "sg:province":"NL.08",
    "wof:name":"W R Broer",
    "wof:placetype":"venue"
},
  "geometry": {"coordinates":[6.084824,52.722389],"type":"Point"}
}