{
  "type": "Feature",
  "properties": {
    "addr:full":"Kivitsln 9C Oisterwyk Noord-Brabant 5062 AA",
    "addr:housenumber":"9c",
    "addr:postcode":"5062 aa",
    "addr:street":"Kivitsln",
    "iso:country":"NL",
    "sg:address":"Kivitsln 9C",
    "sg:city":"Oisterwyk",
    "sg:orig_category":"Artiesten/Gezelschappen",
    "sg:phone":"+31 13 528 3140",
    "sg:postcode":"5062 AA",
    "sg:province":"Noord-Brabant",
    "wof:name":"Kreater Produkties Bv",
    "wof:placetype":"venue"
},
  "geometry": {"coordinates":[5.20733,51.556389],"type":"Point"}
}