{
  "type": "Feature",
  "properties": {
    "addr:full":"Egelshoek 8 Hilversum Noord-Holland 1213 RD",
    "addr:housenumber":"8",
    "addr:postcode":"1213 rd",
    "addr:street":"Egelshoek",
    "iso:country":"NL",
    "sg:address":"Egelshoek 8",
    "sg:city":"Hilversum",
    "sg:orig_category":"Autosloperijen En Autodemontagebedrijven",
    "sg:phone":"+31 35 577 1586",
    "sg:postcode":"1213 RD",
    "sg:province":"Noord-Holland",
    "wof:name":"Mercedes",
    "wof:placetype":"venue"
},
  "geometry": {"coordinates":[5.148841,52.181744],"type":"Point"}
}