{
  "type": "Feature",
  "properties": {
    "iso:country":"NL",
    "sg:address":"Venuslaan 209",
    "sg:city":"Eindhoven",
    "sg:orig_category":"Zalenexploitatie",
    "sg:phone":"+31 40 241 3000",
    "sg:postcode":"5632 HD",
    "sg:province":"North Brabant",
    "wof:name":"Heyster-Art Kunstuitleen",
    "wof:placetype":"venue"
},
  "geometry": {"coordinates":[5.488639,51.468967],"type":"Point"}
}