{
  "type": "Feature",
  "properties": {
    "iso:country":"NL",
    "sg:address":"Van Goyenlaan 17",
    "sg:city":"Bilthoven",
    "sg:orig_category":"Verzekeringen",
    "sg:phone":"+31 30 229 2640",
    "sg:postcode":"3723 GN",
    "sg:province":"Utrecht",
    "wof:name":"Mpa Actuariaat & Automatisering",
    "wof:placetype":"venue"
},
  "geometry": {"coordinates":[5.210863,52.140934],"type":"Point"}
}