{
  "type": "Feature",
  "properties": {
    "iso:country":"NL",
    "sg:address":"Muldershof 45",
    "sg:city":"Zevenaar",
    "sg:orig_category":"Wasserettes And Stomerijen",
    "sg:phone":"+31 316 331 604",
    "sg:postcode":"6901 GZ",
    "sg:province":"Gelderland",
    "wof:name":"Kwaliteitsstomerij Teunissen",
    "wof:placetype":"venue"
},
  "geometry": {"coordinates":[6.0766859055,51.9304237366],"type":"Point"}
}