{
  "type": "Feature",
  "properties": {
    "iso:country":"NL",
    "sg:address":"Dorpstraat 46",
    "sg:city":"Ulvenhout",
    "sg:orig_category":"Public Relationbureaus",
    "sg:phone":"+31 161 493 141",
    "sg:postcode":"4851 CM",
    "sg:province":"Noord-Brabant",
    "wof:name":"Cat",
    "wof:placetype":"venue"
},
  "geometry": {"coordinates":[4.796924,51.551857],"type":"Point"}
}