{
  "type": "Feature",
  "properties": {
    "addr:full":"Oude Doelenstraat 18 Amsterdam Noord-Holland 1012 ED",
    "addr:housenumber":"18",
    "addr:postcode":"1012 ed",
    "addr:street":"Oude Doelenstraat",
    "iso:country":"NL",
    "sg:address":"Oude Doelenstraat 18",
    "sg:city":"Amsterdam",
    "sg:orig_category":"Visspeciaalzaken",
    "sg:phone":"+31 20 622 1284",
    "sg:postcode":"1012 ED",
    "sg:province":"Noord-Holland",
    "wof:name":"Jan Hendriks",
    "wof:placetype":"venue"
},
  "geometry": {"coordinates":[4.89653,52.371498],"type":"Point"}
}