{
  "type": "Feature",
  "properties": {
    "addr:full":"Walenburgerweg 90 Rotterdam South Holland 3033 AH",
    "addr:housenumber":"90",
    "addr:postcode":"3033 ah",
    "addr:street":"Walenburgerweg",
    "iso:country":"NL",
    "sg:address":"Walenburgerweg 90",
    "sg:city":"Rotterdam",
    "sg:orig_category":"Film-, Tv- And Videoproductie",
    "sg:phone":"+31 10 465 4481",
    "sg:postcode":"3033 AH",
    "sg:province":"South Holland",
    "wof:name":"Doing",
    "wof:placetype":"venue"
},
  "geometry": {"coordinates":[4.466005,51.927906],"type":"Point"}
}