{
  "type": "Feature",
  "properties": {
    "addr:full":"Gr Ottoln 15 Oosterbeek Gelderland 6861 BS",
    "addr:housenumber":"15",
    "addr:postcode":"6861 bs",
    "addr:street":"Gelderland",
    "iso:country":"NL",
    "sg:address":"Gr Ottoln 15",
    "sg:city":"Oosterbeek",
    "sg:orig_category":"Vertaalbureaus",
    "sg:phone":"+31 26 339 0261",
    "sg:postcode":"6861 BS",
    "sg:province":"Gelderland",
    "wof:name":"Cressie",
    "wof:placetype":"venue"
},
  "geometry": {"coordinates":[5.83106,51.994411],"type":"Point"}
}