{
  "type": "Feature",
  "properties": {
    "addr:full":"Liedekerkestr 138 Budel Dorplein Noord-Brabant 6024 AK",
    "addr:housenumber":"138",
    "addr:postcode":"6024 ak",
    "iso:country":"NL",
    "sg:address":"Liedekerkestr 138",
    "sg:city":"Budel Dorplein",
    "sg:orig_category":"Verhuur",
    "sg:phone":"+31 495 518 550",
    "sg:postcode":"6024 AK",
    "sg:province":"Noord-Brabant",
    "wof:name":"Kroezen",
    "wof:placetype":"venue"
},
  "geometry": {"coordinates":[5.58446,51.233139],"type":"Point"}
}