{
  "type": "Feature",
  "properties": {
    "addr:full":"Verbreepk 10A Benthuizen South Holland 2731 BR",
    "addr:housenumber":"10a",
    "addr:postcode":"2731 br",
    "addr:street":"Verbreepk",
    "iso:country":"NL",
    "sg:address":"Verbreepk 10A",
    "sg:city":"Benthuizen",
    "sg:classifiers":[
        {
            "category":"Shopping",
            "subcategory":"Gifts & Souvenirs",
            "type":"Retail Goods"
        }
    ],
    "sg:phone":"+31 79 346 0969",
    "sg:postcode":"2731 BR",
    "sg:province":"South Holland",
    "sg:tags":[
        "wens-",
        "en",
        "prentbriefkaarten"
    ],
    "wof:name":"Pos-Kaart",
    "wof:placetype":"venue"
},
  "geometry": {"coordinates":[4.5571198463,52.0755386353],"type":"Point"}
}