{
  "type": "Feature",
  "properties": {
    "addr:full":"H Consciencestr 49 Venlo Limburg 5921 AR",
    "addr:housenumber":"49",
    "addr:postcode":"5921",
    "iso:country":"NL",
    "sg:address":"H Consciencestr 49",
    "sg:city":"Venlo",
    "sg:orig_category":"Boekhandels",
    "sg:phone":"+31 77 382 8739",
    "sg:postcode":"5921 AR",
    "sg:province":"Limburg",
    "wof:name":"Media Expresse",
    "wof:placetype":"venue"
},
  "geometry": {"coordinates":[-97.445908,46.48592],"type":"Point"}
}