{
  "type": "Feature",
  "properties": {
    "iso:country":"NL",
    "sg:address":"Jan Tinbergenstraat 3",
    "sg:city":"Reeuwijk",
    "sg:orig_category":"Autokeuringen",
    "sg:phone":"+31 182 392 350",
    "sg:postcode":"2811 DZ",
    "sg:province":"South Holland",
    "wof:name":"Automobielbedrijf Ton De Wit Bv",
    "wof:placetype":"venue"
},
  "geometry": {"coordinates":[4.716562,52.040901],"type":"Point"}
}