{
  "type": "Feature",
  "properties": {
    "iso:country":"NL",
    "sg:address":"Rietgorsstraat 73",
    "sg:city":"Aalsmeer",
    "sg:orig_category":"Elektronische Bedrijfsinstallaties",
    "sg:phone":"+31 297 322 833",
    "sg:postcode":"1431 VV",
    "sg:province":"Noord-Holland",
    "wof:name":"A.T.S. Beveiligingen",
    "wof:placetype":"venue"
},
  "geometry": {"coordinates":[4.761334,52.255795],"type":"Point"}
}