{
  "type": "Feature",
  "properties": {
    "addr:full":"Oostkerkpln 16 Middelburg Zeeland 4331 TL",
    "addr:housenumber":"16",
    "addr:postcode":"4331 tl",
    "addr:street":"Oostkerkpln",
    "iso:country":"NL",
    "sg:address":"Oostkerkpln 16",
    "sg:city":"Middelburg",
    "sg:orig_category":"Onroerende Goederen",
    "sg:phone":"+31 118 614 363",
    "sg:postcode":"4331 TL",
    "sg:province":"Zeeland",
    "wof:name":"Looff Bv, De",
    "wof:placetype":"venue"
},
  "geometry": {"coordinates":[3.620244,51.502842],"type":"Point"}
}