{
  "type": "Feature",
  "properties": {
    "addr:full":"V Schootenstr 23 Breda North Brabant 4835 CJ",
    "addr:housenumber":"23",
    "addr:postcode":"4835 cj",
    "iso:country":"NL",
    "sg:address":"V Schootenstr 23",
    "sg:city":"Breda",
    "sg:orig_category":"Fotojournalisten Freelance",
    "sg:phone":"+31 76 560 1022",
    "sg:postcode":"4835 CJ",
    "sg:province":"North Brabant",
    "wof:name":"Schr\u00f6der, Caroline",
    "wof:placetype":"venue"
},
  "geometry": {"coordinates":[4.78509,51.569248],"type":"Point"}
}