{
  "type": "Feature",
  "properties": {
    "addr:full":"Weezenhof 2055 Nijmegen Gelderland 6536 JK",
    "addr:housenumber":"2055",
    "addr:postcode":"6536 jk",
    "addr:street":"Weezenhof;Gelderland",
    "iso:country":"NL",
    "sg:address":"Weezenhof 2055",
    "sg:city":"Nijmegen",
    "sg:orig_category":"Handelsbemiddeling Textiel And Lederwaren",
    "sg:phone":"+31 24 345 2574",
    "sg:postcode":"6536 JK",
    "sg:province":"Gelderland",
    "wof:name":"K.J. Smit",
    "wof:placetype":"venue"
},
  "geometry": {"coordinates":[5.80219,51.800388],"type":"Point"}
}