{
  "type": "Feature",
  "properties": {
    "iso:country":"NL",
    "sg:address":"Kleiwegstr 15",
    "sg:city":"Gouda",
    "sg:orig_category":"Kappers",
    "sg:phone":"+31 182 521 860",
    "sg:postcode":"2801 GL",
    "sg:province":"South Holland",
    "wof:name":"Jup?, La",
    "wof:placetype":"venue"
},
  "geometry": {"coordinates":[4.7093009949,52.0139961243],"type":"Point"}
}