{
  "type": "Feature",
  "properties": {
    "iso:country":"NL",
    "sg:address":"Brasemsloot 11",
    "sg:city":"Zoetermeer",
    "sg:orig_category":"Diverse Opleidingen And Onderwijs",
    "sg:phone":"+31 79 341 1090",
    "sg:postcode":"2724 EL",
    "sg:province":"Zuid-Holland",
    "wof:name":"Ehbo & Bhv Opleidingen",
    "wof:placetype":"venue"
},
  "geometry": {"coordinates":[4.512795,52.06324],"type":"Point"}
}