{
  "type": "Feature",
  "properties": {
    "addr:full":"St Mariastr 132A Rotterdam South Holland 3014 SR",
    "addr:housenumber":"132a",
    "addr:postcode":"3014 sr",
    "iso:country":"NL",
    "sg:address":"St Mariastr 132A",
    "sg:city":"Rotterdam",
    "sg:orig_category":"Verenigingen En Stichtingen",
    "sg:phone":"+31 10 436 4975",
    "sg:postcode":"3014 SR",
    "sg:province":"South Holland",
    "wof:name":"So Mi Tan, Sticht",
    "wof:placetype":"venue"
},
  "geometry": {"coordinates":[4.468504,51.918518],"type":"Point"}
}