{
  "type": "Feature",
  "properties": {
    "iso:country":"NL",
    "sg:address":"Broekhovensewg 56",
    "sg:city":"Tilburg",
    "sg:orig_category":"Nagelstudio'S",
    "sg:phone":"+31 13 536 1312",
    "sg:postcode":"5021 LG",
    "sg:province":"North Brabant",
    "wof:name":"Linda",
    "wof:placetype":"venue"
},
  "geometry": {"coordinates":[5.090949,51.54731],"type":"Point"}
}