{
  "type": "Feature",
  "properties": {
    "addr:full":"Ster Bastion 49 Velserbroek BE.04 1991 WE",
    "addr:housenumber":"49;be.04",
    "addr:postcode":"1991 we",
    "addr:street":"Ster Bastion",
    "iso:country":"NL",
    "sg:address":"Ster Bastion 49",
    "sg:city":"Velserbroek",
    "sg:orig_category":"Zuivelproducten",
    "sg:phone":"+31 23 539 1106",
    "sg:postcode":"1991 WE",
    "sg:province":"BE.04",
    "wof:name":"Lujo",
    "wof:placetype":"venue"
},
  "geometry": {"coordinates":[5.9741,50.46162],"type":"Point"}
}