{
  "type": "Feature",
  "properties": {
    "addr:full":"Ekenrooisestraat 57 Waalre Noord-Brabant 5583 TD",
    "addr:housenumber":"57",
    "addr:postcode":"5583 td",
    "addr:street":"Ekenrooisestraat",
    "iso:country":"NL",
    "sg:address":"Ekenrooisestraat 57",
    "sg:city":"Waalre",
    "sg:orig_category":"Artsen And Specialisten",
    "sg:phone":"+31 40 221 6237",
    "sg:postcode":"5583 TD",
    "sg:province":"Noord-Brabant",
    "wof:name":"Huisartsenpraktijk F.L.M. Van Stiphout",
    "wof:placetype":"venue"
},
  "geometry": {"coordinates":[5.486315,51.392742],"type":"Point"}
}