{
  "type": "Feature",
  "properties": {
    "iso:country":"NL",
    "sg:address":"Burgemeester Posweg 46",
    "sg:city":"Brakel",
    "sg:classifiers":[
        {
            "category":"Education",
            "subcategory":"Preschool",
            "type":"Public Place"
        }
    ],
    "sg:phone":"+31 418 677 180",
    "sg:postcode":"5306 GE",
    "sg:province":"Gelderland",
    "sg:tags":[
        "kleuteronderwijs",
        "basis-"
    ],
    "wof:name":"D.W. Van Dam Van Brakelschool",
    "wof:placetype":"venue"
},
  "geometry": {"coordinates":[5.092053,51.818203],"type":"Point"}
}