{
  "type": "Feature",
  "properties": {
    "iso:country":"NL",
    "sg:address":"De Wetering 85",
    "sg:city":"Oosterhout Nb",
    "sg:orig_category":"Autopoetsbedrijven",
    "sg:phone":"+31 162 462 226",
    "sg:postcode":"4906 CT",
    "sg:province":"Noord-Brabant",
    "wof:name":"Dongen Vof, Van",
    "wof:placetype":"venue"
},
  "geometry": {"coordinates":[4.84302,51.65432],"type":"Point"}
}