{
  "type": "Feature",
  "properties": {
    "addr:full":"Frederiksplein 51 Amsterdam North Holland 1017 XL",
    "addr:housenumber":"51",
    "addr:postcode":"1017 xl",
    "addr:street":"Frederiksplein",
    "iso:country":"NL",
    "sg:address":"Frederiksplein 51",
    "sg:city":"Amsterdam",
    "sg:orig_category":"Film-, Tv- And Videoproductie",
    "sg:phone":"+31 20 624 5580",
    "sg:postcode":"1017 XL",
    "sg:province":"North Holland",
    "wof:name":"De Levita Productions Bv",
    "wof:placetype":"venue"
},
  "geometry": {"coordinates":[4.901295,52.360088],"type":"Point"}
}