{
  "type": "Feature",
  "properties": {
    "addr:full":"N V Eybenln 11 Driebergen Rysenb Utrecht 3972 GT",
    "addr:housenumber":"11",
    "addr:postcode":"3972 gt",
    "addr:street":"N V Eybenln;Rysenb",
    "iso:country":"NL",
    "sg:address":"N V Eybenln 11",
    "sg:city":"Driebergen Rysenb",
    "sg:orig_category":"Verzekeringen - Verzekeringskantoren",
    "sg:phone":"+31 343 514 535",
    "sg:postcode":"3972 GT",
    "sg:province":"Utrecht",
    "wof:name":"Sticht, Het",
    "wof:placetype":"venue"
},
  "geometry": {"coordinates":[5.283655,52.051552],"type":"Point"}
}