{
  "type": "Feature",
  "properties": {
    "addr:full":"Zuidenveld 109 Assen Provincie Drenthe 9406 LK",
    "addr:housenumber":"109",
    "addr:postcode":"9406 lk",
    "addr:street":"Zuidenveld;Provincie Drenthe",
    "iso:country":"NL",
    "sg:address":"Zuidenveld 109",
    "sg:city":"Assen",
    "sg:orig_category":"Adviesbureaus Bedrijfsorganisatie",
    "sg:phone":"+31 6 18766841",
    "sg:postcode":"9406 LK",
    "sg:province":"Provincie Drenthe",
    "sg:website":"http://www.gastronomischadviesburo.nl",
    "wof:name":"Gastronomisch Adviesburo",
    "wof:placetype":"venue"
},
  "geometry": {"coordinates":[6.547242,53.005787],"type":"Point"}
}