{
  "type": "Feature",
  "properties": {
    "iso:country":"NL",
    "sg:address":"Brinkstraat 17",
    "sg:city":"Beilen",
    "sg:orig_category":"Herenmodezaken",
    "sg:phone":"+31 593 522 677",
    "sg:postcode":"9411 KJ",
    "sg:province":"Provincie Drenthe",
    "wof:name":"Modecentrum Ten Oever Bv",
    "wof:placetype":"venue"
},
  "geometry": {"coordinates":[6.513789,52.859325],"type":"Point"}
}