{
  "type": "Feature",
  "properties": {
    "addr:full":"Heikantsestr 60 Oosteind Noord-Brabant 4909 BR",
    "addr:housenumber":"60",
    "addr:postcode":"4909 br",
    "addr:street":"Heikantsestr",
    "iso:country":"NL",
    "sg:address":"Heikantsestr 60",
    "sg:city":"Oosteind",
    "sg:orig_category":"Verzekeringen - Verzekeringskantoren",
    "sg:phone":"+31 162 423 063",
    "sg:postcode":"4909 BR",
    "sg:province":"Noord-Brabant",
    "wof:name":"Rooij, Van",
    "wof:placetype":"venue"
},
  "geometry": {"coordinates":[4.90524,51.646793],"type":"Point"}
}