{
  "type": "Feature",
  "properties": {
    "addr:full":"Kerkstraat 6 Poortugaal South Holland 3171 GG",
    "addr:housenumber":"6",
    "addr:postcode":"3171 gg",
    "addr:street":"Kerkstraat",
    "iso:country":"NL",
    "sg:address":"Kerkstraat 6",
    "sg:city":"Poortugaal",
    "sg:orig_category":"Kappers",
    "sg:phone":"+31 10 501 7949",
    "sg:postcode":"3171 GG",
    "sg:province":"South Holland",
    "wof:name":"Dameskapsalon Ageeth",
    "wof:placetype":"venue"
},
  "geometry": {"coordinates":[4.3888759613,51.8572654724],"type":"Point"}
}