{
  "type": "Feature",
  "properties": {
    "addr:full":"Fritz Conijnstraat 32 Amsterdam Noord-Holland 1063 CE",
    "addr:housenumber":"32",
    "addr:postcode":"1063 ce",
    "addr:street":"Fritz Conijnstraat",
    "iso:country":"NL",
    "sg:address":"Fritz Conijnstraat 32",
    "sg:city":"Amsterdam",
    "sg:orig_category":"Meubelreparatie And -Restauratie",
    "sg:phone":"+31 20 611 3083",
    "sg:postcode":"1063 CE",
    "sg:province":"Noord-Holland",
    "wof:name":"Meubelstoffeerderij Verheyen",
    "wof:placetype":"venue"
},
  "geometry": {"coordinates":[4.836075,52.384148],"type":"Point"}
}