{
  "type": "Feature",
  "properties": {
    "addr:full":"Kerkstr 1 Vriezenveen NL.08 7671 HE",
    "addr:housenumber":"1;nl.08",
    "addr:postcode":"7671 he",
    "addr:street":"Kerkstr",
    "iso:country":"NL",
    "sg:address":"Kerkstr 1",
    "sg:city":"Vriezenveen",
    "sg:orig_category":"Makelaars En Adviseurs Onroerende Goederen",
    "sg:phone":"+31 546 565 758",
    "sg:postcode":"7671 HE",
    "sg:province":"NL.08",
    "sg:website":"http://www.wemekamp-makelaars.nl",
    "wof:name":"Wemekamp Bv",
    "wof:placetype":"venue"
},
  "geometry": {"coordinates":[6.626411,52.411106],"type":"Point"}
}