{
  "type": "Feature",
  "properties": {
    "addr:full":"Splinterln 7 Leiderdorp Zuid-Holland 2352 SB",
    "addr:housenumber":"7",
    "addr:postcode":"2352 sb",
    "addr:street":"Splinterln",
    "iso:country":"NL",
    "sg:address":"Splinterln 7",
    "sg:city":"Leiderdorp",
    "sg:orig_category":"Bloemen En Planten",
    "sg:phone":"+31 71 541 3270",
    "sg:postcode":"2352 SB",
    "sg:province":"Zuid-Holland",
    "wof:name":"Jean-Marie",
    "wof:placetype":"venue"
},
  "geometry": {"coordinates":[4.516484,52.161304],"type":"Point"}
}