{
  "type": "Feature",
  "properties": {
    "addr:full":"Van Weerden Poelmanweg 21 Soest Utrecht 3768 MN",
    "addr:housenumber":"21",
    "addr:postcode":"3768 mn",
    "addr:street":"Van Weerden Poelmanweg",
    "iso:country":"NL",
    "sg:address":"Van Weerden Poelmanweg 21",
    "sg:city":"Soest",
    "sg:orig_category":"Farmaceutische Producten Gh",
    "sg:phone":"+31 35 603 0043",
    "sg:postcode":"3768 MN",
    "sg:province":"Utrecht",
    "wof:name":"Spina - Bac Holland",
    "wof:placetype":"venue"
},
  "geometry": {"coordinates":[5.295589,52.141754],"type":"Point"}
}