{
  "type": "Feature",
  "properties": {
    "addr:full":"Rekhemseweg 49 Doetinchem Gelderland 7004 HA",
    "addr:housenumber":"49",
    "addr:postcode":"7004 ha",
    "addr:street":"Rekhemseweg;Gelderland",
    "iso:country":"NL",
    "sg:address":"Rekhemseweg 49",
    "sg:city":"Doetinchem",
    "sg:orig_category":"Vertaal- And Tolkenbureaus",
    "sg:phone":"+31 314 325 804",
    "sg:postcode":"7004 HA",
    "sg:province":"Gelderland",
    "wof:name":"P.G.A. Admiraal",
    "wof:placetype":"venue"
},
  "geometry": {"coordinates":[6.320858,51.953773],"type":"Point"}
}