{
  "type": "Feature",
  "properties": {
    "addr:full":"Ootmarsumsestr 273 Almelo Overijssel 7603 AD",
    "addr:housenumber":"273",
    "addr:postcode":"7603 ad",
    "iso:country":"NL",
    "sg:address":"Ootmarsumsestr 273",
    "sg:city":"Almelo",
    "sg:orig_category":"Verzekeringen - Verzekeringskantoren",
    "sg:phone":"+31 546 872 014",
    "sg:postcode":"7603 AD",
    "sg:province":"Overijssel",
    "wof:name":"Leeuwenkamp, Van",
    "wof:placetype":"venue"
},
  "geometry": {"coordinates":[6.682625,52.367828],"type":"Point"}
}