{
  "type": "Feature",
  "properties": {
    "iso:country":"NL",
    "sg:address":"Groenendaal 8",
    "sg:city":"Tiel",
    "sg:orig_category":"Medische And Orthopedische Artikelen",
    "sg:phone":"+31 344 634 102",
    "sg:postcode":"4003 EL",
    "sg:province":"Gelderland",
    "wof:name":"Vof J.W.G. Husselson-J.J.S. Husselson-V.",
    "wof:placetype":"venue"
},
  "geometry": {"coordinates":[5.420605,51.897469],"type":"Point"}
}