{
  "type": "Feature",
  "properties": {
    "iso:country":"NL",
    "sg:address":"Paletplein 6",
    "sg:city":"Tilburg",
    "sg:orig_category":"Bedden En Matrassen",
    "sg:phone":"+31 13 532 1100",
    "sg:postcode":"5044 JB",
    "sg:province":"Noord-Brabant",
    "wof:name":"Luybregts",
    "wof:placetype":"venue"
},
  "geometry": {"coordinates":[5.039351,51.576134],"type":"Point"}
}