{
  "type": "Feature",
  "properties": {
    "addr:full":"Holpryp 6 Tzum Friesland 8804 RZ",
    "addr:housenumber":"6",
    "addr:postcode":"8804 rz",
    "addr:street":"Holpryp",
    "iso:country":"NL",
    "sg:address":"Holpryp 6",
    "sg:city":"Tzum",
    "sg:orig_category":"Loodgieters",
    "sg:phone":"+31 517 452 430",
    "sg:postcode":"8804 RZ",
    "sg:province":"Friesland",
    "wof:name":"Genee, Installatiebedrijf",
    "wof:placetype":"venue"
},
  "geometry": {"coordinates":[5.541833,53.163761],"type":"Point"}
}