{
  "type": "Feature",
  "properties": {
    "iso:country":"NL",
    "sg:address":"Dam 27",
    "sg:city":"Middelburg",
    "sg:orig_category":"Kappers",
    "sg:phone":"+31 118 634 940",
    "sg:postcode":"4331 GE",
    "sg:province":"Zeeland",
    "wof:name":"Kim",
    "wof:placetype":"venue"
},
  "geometry": {"coordinates":[3.6179280281,51.5009231567],"type":"Point"}
}