{
  "type": "Feature",
  "properties": {
    "addr:full":"Hg Ryndk 199 Zoeterwoude Zuid-Holland 2382 AK",
    "addr:housenumber":"199",
    "addr:postcode":"2382 ak",
    "iso:country":"NL",
    "sg:address":"Hg Ryndk 199",
    "sg:city":"Zoeterwoude",
    "sg:orig_category":"Meubelen",
    "sg:phone":"+31 71 541 3616",
    "sg:postcode":"2382 AK",
    "sg:province":"Zuid-Holland",
    "wof:name":"Nagtegaal Glasmeubelen",
    "wof:placetype":"venue"
},
  "geometry": {"coordinates":[4.524844,52.144672],"type":"Point"}
}