{
  "type": "Feature",
  "properties": {
    "addr:full":"H\u00e4ndelhof 5 Alphen Aan Den Ryn Zuid-Holland 2402 GT",
    "addr:housenumber":"5",
    "addr:postcode":"2402 gt",
    "addr:street":"Haendelhof;Aan Den Ryn",
    "iso:country":"NL",
    "sg:address":"H\u00e4ndelhof 5",
    "sg:city":"Alphen Aan Den Ryn",
    "sg:orig_category":"Adviesbureaus Bouwkunde",
    "sg:phone":"+31 172 419 704",
    "sg:postcode":"2402 GT",
    "sg:province":"Zuid-Holland",
    "wof:name":"Tip",
    "wof:placetype":"venue"
},
  "geometry": {"coordinates":[4.672339,52.146984],"type":"Point"}
}