{
  "type": "Feature",
  "properties": {
    "addr:full":"Ellermanstr 27 Amsterdam North Holland 1099 BZ",
    "addr:housenumber":"27",
    "addr:postcode":"1099 bz",
    "addr:street":"Ellermanstr",
    "iso:country":"NL",
    "sg:address":"Ellermanstr 27",
    "sg:city":"Amsterdam",
    "sg:orig_category":"Levensmiddelen - Fabrieken En Groothandel",
    "sg:phone":"+31 20 692 9299",
    "sg:postcode":"1099 BZ",
    "sg:province":"North Holland",
    "wof:name":"Hocorn Bv",
    "wof:placetype":"venue"
},
  "geometry": {"coordinates":[4.92998,52.326878],"type":"Point"}
}