{
  "type": "Feature",
  "properties": {
    "addr:full":"Kerkstraat 3 Vught Noord-Brabant 5261 CP",
    "addr:housenumber":"3",
    "addr:postcode":"5261 cp",
    "addr:street":"Kerkstraat",
    "iso:country":"NL",
    "sg:address":"Kerkstraat 3",
    "sg:city":"Vught",
    "sg:orig_category":"Binnenhuisarchitecten",
    "sg:phone":"+31 73 656 4689",
    "sg:postcode":"5261 CP",
    "sg:province":"Noord-Brabant",
    "wof:name":"Studio Heijckmann Bv",
    "wof:placetype":"venue"
},
  "geometry": {"coordinates":[5.297663,51.660519],"type":"Point"}
}