{
  "type": "Feature",
  "properties": {
    "addr:full":"Faunalaan 77 Driebergen-Rijsenburg Utrecht 3972 PP",
    "addr:housenumber":"77",
    "addr:postcode":"3972 pp",
    "addr:street":"Faunalaan",
    "iso:country":"NL",
    "sg:address":"Faunalaan 77",
    "sg:city":"Driebergen-Rijsenburg",
    "sg:orig_category":"Kappers",
    "sg:phone":"+31 343 513 282",
    "sg:postcode":"3972 PP",
    "sg:province":"Utrecht",
    "wof:name":"Haarverzorging Marjan Van Garderen",
    "wof:placetype":"venue"
},
  "geometry": {"coordinates":[5.2620229721,52.0516281128],"type":"Point"}
}