{
  "type": "Feature",
  "properties": {
    "addr:full":"Achillesstr 115 Amsterdam Noord-Holland 1076 RA",
    "addr:housenumber":"115",
    "addr:postcode":"1076 ra",
    "iso:country":"NL",
    "sg:address":"Achillesstr 115",
    "sg:city":"Amsterdam",
    "sg:orig_category":"Wijnkoperijen En -Groothandel",
    "sg:phone":"+31 6 24244333",
    "sg:postcode":"1076 RA",
    "sg:province":"Noord-Holland",
    "wof:name":"Visa Versa Bv",
    "wof:placetype":"venue"
},
  "geometry": {"coordinates":[4.8650650978,52.3438720703],"type":"Point"}
}