{
  "type": "Feature",
  "properties": {
    "addr:full":"Kapellerln 19 Roermond Limburg 6041 JB",
    "addr:housenumber":"19",
    "addr:postcode":"6041 jb",
    "addr:street":"Kapellerln",
    "iso:country":"NL",
    "sg:address":"Kapellerln 19",
    "sg:city":"Roermond",
    "sg:orig_category":"Adviesbureaus Bedrijfsorganisatie",
    "sg:phone":"+31 475 420 378",
    "sg:postcode":"6041 JB",
    "sg:province":"Limburg",
    "sg:website":"http://www.bothmer.nl",
    "wof:name":"Bothmer",
    "wof:placetype":"venue"
},
  "geometry": {"coordinates":[5.991103,51.189888],"type":"Point"}
}