{
  "type": "Feature",
  "properties": {
    "addr:full":"Dorpsstr 21 Zwartewaal Zuid-Holland 3238 BA",
    "addr:housenumber":"21",
    "addr:postcode":"3238 ba",
    "addr:street":"Dorpsstr",
    "iso:country":"NL",
    "sg:address":"Dorpsstr 21",
    "sg:city":"Zwartewaal",
    "sg:orig_category":"Bloemen En Planten",
    "sg:phone":"+31 181 664 086",
    "sg:postcode":"3238 BA",
    "sg:province":"Zuid-Holland",
    "wof:name":"Vier Seizoenen, De",
    "wof:placetype":"venue"
},
  "geometry": {"coordinates":[4.223274,51.882069],"type":"Point"}
}