{
  "type": "Feature",
  "properties": {
    "addr:full":"Parallelwg 73 S Gravenhage South Holland 2525 ND",
    "addr:housenumber":"73",
    "addr:postcode":"2525 nd",
    "addr:street":"Parallelwg;S Gravenhage",
    "iso:country":"NL",
    "sg:address":"Parallelwg 73",
    "sg:city":"S Gravenhage",
    "sg:orig_category":"Onderhoudswerken",
    "sg:phone":"+31 70 402 3612",
    "sg:postcode":"2525 ND",
    "sg:province":"South Holland",
    "wof:name":"Kmd Vof",
    "wof:placetype":"venue"
},
  "geometry": {"coordinates":[4.30248,52.062462],"type":"Point"}
}