{
  "type": "Feature",
  "properties": {
    "iso:country":"NL",
    "sg:address":"Ysselstr 12",
    "sg:city":"Oss",
    "sg:orig_category":"Oldtimers",
    "sg:phone":"+31 412 651 412",
    "sg:postcode":"5347 KG",
    "sg:province":"Noord-Brabant",
    "wof:name":"Leur, Van",
    "wof:placetype":"venue"
},
  "geometry": {"coordinates":[-77.235214,38.312599],"type":"Point"}
}