{
  "type": "Feature",
  "properties": {
    "addr:full":"Laan Van Nieuw Guinea 107 Utrecht Utrecht 3531 JG",
    "addr:housenumber":"107",
    "addr:postcode":"3531 jg",
    "addr:street":"Laan Van Nieuw Guinea",
    "iso:country":"NL",
    "sg:address":"Laan Van Nieuw Guinea 107",
    "sg:city":"Utrecht",
    "sg:orig_category":"Fietshandelaren",
    "sg:phone":"+31 30 293 0635",
    "sg:postcode":"3531 JG",
    "sg:province":"Utrecht",
    "wof:name":"Henny Gouka Tweewieler Service",
    "wof:placetype":"venue"
},
  "geometry": {"coordinates":[5.085586,52.09367],"type":"Point"}
}