{
  "type": "Feature",
  "properties": {
    "iso:country":"NL",
    "sg:address":"Woensdrechtstraat 17",
    "sg:city":"Rotterdam",
    "sg:orig_category":"Verhuur Diversen",
    "sg:phone":"+31 10 418 6333",
    "sg:postcode":"3045 PZ",
    "sg:province":"South Holland",
    "wof:name":"Reri Evenementen",
    "wof:placetype":"venue"
},
  "geometry": {"coordinates":[4.453513,51.95216],"type":"Point"}
}