{
  "type": "Feature",
  "properties": {
    "addr:full":"Noorderwg 3 Nes Ameland Friesland 9163 HR",
    "addr:housenumber":"3",
    "addr:postcode":"9163 hr",
    "addr:street":"Noorderwg",
    "iso:country":"NL",
    "sg:address":"Noorderwg 3",
    "sg:city":"Nes Ameland",
    "sg:classifiers":[
        {
            "category":"Travel",
            "subcategory":"Hotels & Motels",
            "type":"Entertainment"
        }
    ],
    "sg:phone":"+31 519 542 165",
    "sg:postcode":"9163 HR",
    "sg:province":"Friesland",
    "wof:name":"Molenzicht, Hotel Pension",
    "wof:placetype":"venue"
},
  "geometry": {"coordinates":[5.774603,53.446957],"type":"Point"}
}