{
  "type": "Feature",
  "properties": {
    "addr:full":"Heezerenbosch 3 Heeze North Brabant 5591 TA",
    "addr:housenumber":"3",
    "addr:postcode":"5591 ta",
    "addr:street":"Heezerenbosch",
    "iso:country":"NL",
    "sg:address":"Heezerenbosch 3",
    "sg:city":"Heeze",
    "sg:orig_category":"Muziekinstrumenten",
    "sg:phone":"+31 40 226 4408",
    "sg:postcode":"5591 TA",
    "sg:province":"North Brabant",
    "wof:name":"Vanderaa Accordeons",
    "wof:placetype":"venue"
},
  "geometry": {"coordinates":[5.554551,51.374062],"type":"Point"}
}