{
  "type": "Feature",
  "properties": {
    "addr:full":"Rode Landsweg 3 Doornspijk Gelderland 8085 SL",
    "addr:housenumber":"3",
    "addr:postcode":"8085 sl",
    "addr:street":"Rode Landsweg;Gelderland",
    "iso:country":"NL",
    "sg:address":"Rode Landsweg 3",
    "sg:city":"Doornspijk",
    "sg:classifiers":[
        {
            "category":"Recreation",
            "subcategory":"Amusement Park",
            "type":"Entertainment"
        }
    ],
    "sg:phone":"+31 525 661 160",
    "sg:postcode":"8085 SL",
    "sg:province":"Gelderland",
    "wof:name":"Ijsvereniging Doornspijk",
    "wof:placetype":"venue"
},
  "geometry": {"coordinates":[5.815134,52.414352],"type":"Point"}
}