{
  "type": "Feature",
  "properties": {
    "addr:full":"Langendijk 3 Gorinchem Zuid-Holland 4201 CE",
    "addr:housenumber":"3",
    "addr:postcode":"4201 ce",
    "addr:street":"Langendijk",
    "iso:country":"NL",
    "sg:address":"Langendijk 3",
    "sg:city":"Gorinchem",
    "sg:orig_category":"Meubelzaken, Woning- And Keukeninrichting",
    "sg:phone":"+31 183 635 679",
    "sg:postcode":"4201 CE",
    "sg:province":"Zuid-Holland",
    "wof:name":"Aquadonk",
    "wof:placetype":"venue"
},
  "geometry": {"coordinates":[4.97651,51.829998],"type":"Point"}
}