{
  "type": "Feature",
  "properties": {
    "addr:full":"Dalveen 17 Wateringen Zuid-Holland 2291 NG",
    "addr:housenumber":"17",
    "addr:postcode":"2291 ng",
    "addr:street":"Dalveen",
    "iso:country":"NL",
    "sg:address":"Dalveen 17",
    "sg:city":"Wateringen",
    "sg:orig_category":"Betonboringen",
    "sg:phone":"+31 174 297 568",
    "sg:postcode":"2291 NG",
    "sg:province":"Zuid-Holland",
    "wof:name":"Zuyderwijk, A",
    "wof:placetype":"venue"
},
  "geometry": {"coordinates":[4.280481,52.018578],"type":"Point"}
}