{
  "type": "Feature",
  "properties": {
    "iso:country":"NL",
    "sg:address":"Burg Vd Klokkenln 31",
    "sg:city":"Waalwyk",
    "sg:orig_category":"Artiesten/Gezelschappen",
    "sg:phone":"+31 416 344 663",
    "sg:postcode":"5141 EE",
    "sg:province":"Noord-Brabant",
    "wof:name":"Jo Ko & Kobus",
    "wof:placetype":"venue"
},
  "geometry": {"coordinates":[5.062876,51.689789],"type":"Point"}
}