{
  "type": "Feature",
  "properties": {
    "addr:full":"St Janshof 1 Baarle Nassau Noord-Brabant 5111 VV",
    "addr:housenumber":"1",
    "addr:postcode":"5111 vv",
    "addr:street":"St Janshof",
    "iso:country":"NL",
    "sg:address":"St Janshof 1",
    "sg:city":"Baarle Nassau",
    "sg:orig_category":"Huidtherapeuten",
    "sg:phone":"+31 13 507 5178",
    "sg:postcode":"5111 VV",
    "sg:province":"Noord-Brabant",
    "wof:name":"Gelton-Hamaker, J B",
    "wof:placetype":"venue"
},
  "geometry": {"coordinates":[4.928495,51.445312],"type":"Point"}
}