{
  "type": "Feature",
  "properties": {
    "addr:full":"Beethovenlaan 25 Voorthuizen Gelderland 3781 TL",
    "addr:housenumber":"25",
    "addr:postcode":"3781 tl",
    "addr:street":"Beethovenlaan;Gelderland",
    "iso:country":"NL",
    "sg:address":"Beethovenlaan 25",
    "sg:city":"Voorthuizen",
    "sg:orig_category":"Loodgieterswerk, Verwarming And Sanitaire Installaties",
    "sg:phone":"+31 342 473 510",
    "sg:postcode":"3781 TL",
    "sg:province":"Gelderland",
    "wof:name":"Vof Baatenburg Bouwhulp",
    "wof:placetype":"venue"
},
  "geometry": {"coordinates":[5.604518,52.183681],"type":"Point"}
}