{
  "type": "Feature",
  "properties": {
    "addr:full":"Postbus 2768 Utrecht Utrecht 3500 GT",
    "addr:housenumber":"2768",
    "addr:postcode":"3500 gt",
    "addr:street":"Postbus",
    "iso:country":"NL",
    "sg:address":"Postbus 2768",
    "sg:city":"Utrecht",
    "sg:orig_category":"Verenigingen En Stichtingen",
    "sg:phone":"+31 30 239 4500",
    "sg:postcode":"3500 GT",
    "sg:province":"Utrecht",
    "wof:name":"Raad Voor Accreditatie",
    "wof:placetype":"venue"
},
  "geometry": {"coordinates":[5.12289,52.091],"type":"Point"}
}