{
  "type": "Feature",
  "properties": {
    "iso:country":"NL",
    "sg:address":"Ruysdaellaan 8",
    "sg:city":"Bilthoven",
    "sg:orig_category":"Makelaars In Onroerend Goed",
    "sg:phone":"+31 30 228 4456",
    "sg:postcode":"3723 CC",
    "sg:province":"Utrecht",
    "wof:name":"Francissen Bv",
    "wof:placetype":"venue"
},
  "geometry": {"coordinates":[5.207401,52.13475],"type":"Point"}
}