{
  "type": "Feature",
  "properties": {
    "addr:full":"Scheldekade 3 Breskens Zeeland 4511 AV",
    "addr:housenumber":"3",
    "addr:postcode":"4511 av",
    "addr:street":"Scheldekade",
    "iso:country":"NL",
    "sg:address":"Scheldekade 3",
    "sg:city":"Breskens",
    "sg:classifiers":[
        {
            "category":"Fast Food",
            "type":"Food & Drink"
        }
    ],
    "sg:phone":"+31 117 382 788",
    "sg:postcode":"4511 AV",
    "sg:province":"Zeeland",
    "sg:tags":[
        "afhaal",
        "restaurant"
    ],
    "wof:name":"Cafetaria Snackbar De Boemerang",
    "wof:placetype":"venue"
},
  "geometry": {"coordinates":[3.571098,51.393795],"type":"Point"}
}