{
  "type": "Feature",
  "properties": {
    "addr:full":"Oude Terborgseweg 263 Doetinchem Gelderland 7004 GZ",
    "addr:housenumber":"263",
    "addr:postcode":"7004 gz",
    "addr:street":"Oude Terborgseweg;Gelderland",
    "iso:country":"NL",
    "sg:address":"Oude Terborgseweg 263",
    "sg:city":"Doetinchem",
    "sg:orig_category":"Autokeuringen",
    "sg:phone":"+31 314 343 411",
    "sg:postcode":"7004 GZ",
    "sg:province":"Gelderland",
    "wof:name":"Rozeboom Banden",
    "wof:placetype":"venue"
},
  "geometry": {"coordinates":[6.310095,51.946629],"type":"Point"}
}