{
  "type": "Feature",
  "properties": {
    "iso:country":"NL",
    "sg:address":"Oude Terborgseweg 263",
    "sg:city":"Doetinchem",
    "sg:orig_category":"Autokeuringen",
    "sg:phone":"+31 314 343 411",
    "sg:postcode":"7004 GZ",
    "sg:province":"Gelderland",
    "wof:name":"Rozeboom Banden",
    "wof:placetype":"venue"
},
  "geometry": {"coordinates":[6.310095,51.946629],"type":"Point"}
}