{
  "type": "Feature",
  "properties": {
    "iso:country":"NL",
    "sg:address":"Van Der Werffstraat 14",
    "sg:city":"Eindhoven",
    "sg:orig_category":"Overheidsdiensten",
    "sg:phone":"+31 40 243 1154",
    "sg:postcode":"5622 KB",
    "sg:province":"North Brabant",
    "wof:name":"De Werf",
    "wof:placetype":"venue"
},
  "geometry": {"coordinates":[5.4651432037,51.4628181458],"type":"Point"}
}