{
  "type": "Feature",
  "properties": {
    "iso:country":"NL",
    "sg:address":"Dokter Schepelstraat 2",
    "sg:city":"Gulpen",
    "sg:orig_category":"Kunst And Kunstenaarsbenodigdheden",
    "sg:phone":"+31 43 450 4030",
    "sg:postcode":"6271 GE",
    "sg:province":"Limburg",
    "wof:name":"R. Plum",
    "wof:placetype":"venue"
},
  "geometry": {"coordinates":[5.88823,50.817841],"type":"Point"}
}