{
  "type": "Feature",
  "properties": {
    "addr:full":"Stadhoudersweg 104 Rotterdam Zuid-Holland 3039 CK",
    "addr:housenumber":"104",
    "addr:postcode":"3039 ck",
    "addr:street":"Stadhoudersweg",
    "iso:country":"NL",
    "sg:address":"Stadhoudersweg 104",
    "sg:city":"Rotterdam",
    "sg:orig_category":"Kappers",
    "sg:phone":"+31 10 466 3121",
    "sg:postcode":"3039 CK",
    "sg:province":"Zuid-Holland",
    "wof:name":"J & J Hairsaloon",
    "wof:placetype":"venue"
},
  "geometry": {"coordinates":[4.4599871635,51.930519104],"type":"Point"}
}