{
  "type": "Feature",
  "properties": {
    "addr:full":"Arena 300 Hilversum Noord-Holland 1213 NW",
    "addr:housenumber":"300;1213",
    "addr:postcode":"nw",
    "addr:street":"Arena",
    "iso:country":"NL",
    "sg:address":"Arena 300",
    "sg:city":"Hilversum",
    "sg:orig_category":"Luchtbehandelings- Apparaten",
    "sg:phone":"+31 35 693 0773",
    "sg:postcode":"1213 NW",
    "sg:province":"Noord-Holland",
    "sg:website":"http://www.smokefreesystems.com",
    "wof:name":"Smoke Free Systems",
    "wof:placetype":"venue"
},
  "geometry": {"coordinates":[5.189833,52.214588],"type":"Point"}
}