{
  "type": "Feature",
  "properties": {
    "addr:full":"Zesstedenwg 81 Grootebroek Noord-Holland 1613 JB",
    "addr:housenumber":"81",
    "addr:postcode":"1613 jb",
    "addr:street":"Zesstedenwg",
    "iso:country":"NL",
    "sg:address":"Zesstedenwg 81",
    "sg:city":"Grootebroek",
    "sg:orig_category":"Handwerkartikelen",
    "sg:phone":"+31 228 515 611",
    "sg:postcode":"1613 JB",
    "sg:province":"Noord-Holland",
    "wof:name":"Veltrop Shop",
    "wof:placetype":"venue"
},
  "geometry": {"coordinates":[5.22764,52.697224],"type":"Point"}
}