{
  "type": "Feature",
  "properties": {
    "addr:full":"Haansberg 66 Etten-Leur North Brabant 4874 NL",
    "addr:housenumber":"66",
    "addr:postcode":"4874 nl",
    "addr:street":"Haansberg",
    "iso:country":"NL",
    "sg:address":"Haansberg 66",
    "sg:city":"Etten-Leur",
    "sg:orig_category":"Bloemen And Planten",
    "sg:phone":"+31 76 501 5608",
    "sg:postcode":"4874 NL",
    "sg:province":"North Brabant",
    "wof:name":"Plantenkwekerij De Haansberg Vof",
    "wof:placetype":"venue"
},
  "geometry": {"coordinates":[4.631537,51.583523],"type":"Point"}
}