{
  "type": "Feature",
  "properties": {
    "addr:full":"Westerdorpsstr 105A Hoevelaken Gelderland 3871 AW",
    "addr:housenumber":"105a",
    "addr:postcode":"3871 aw",
    "addr:street":"Gelderland",
    "iso:country":"NL",
    "sg:address":"Westerdorpsstr 105A",
    "sg:city":"Hoevelaken",
    "sg:orig_category":"Verzekeringen - Verzekeringskantoren",
    "sg:phone":"+31 33 253 4170",
    "sg:postcode":"3871 AW",
    "sg:province":"Gelderland",
    "sg:website":"http://www.pluspunt.com",
    "wof:name":"Pluspunt",
    "wof:placetype":"venue"
},
  "geometry": {"coordinates":[5.44013,52.173302],"type":"Point"}
}