{
  "type": "Feature",
  "properties": {
    "addr:full":"Lagewg 1A Velp Nb North Brabant 5363 TN",
    "addr:housenumber":"1a;nb",
    "addr:postcode":"5363",
    "addr:street":"Lagewg",
    "iso:country":"NL",
    "sg:address":"Lagewg 1A",
    "sg:city":"Velp Nb",
    "sg:orig_category":"Autopoetsbedrijven",
    "sg:phone":"+31 486 474 451",
    "sg:postcode":"5363 TN",
    "sg:province":"North Brabant",
    "wof:name":"P & P Autopoetscentrale",
    "wof:placetype":"venue"
},
  "geometry": {"coordinates":[5.723006,51.759251],"type":"Point"}
}