{
  "type": "Feature",
  "properties": {
    "iso:country":"NL",
    "sg:address":"Hortensiastraat 29",
    "sg:city":"Zwolle",
    "sg:orig_category":"Kantoorartikelen",
    "sg:phone":"+31 38 422 1188",
    "sg:postcode":"8013 AA",
    "sg:province":"Overijssel",
    "wof:name":"Dick Noteboom Audio Video",
    "wof:placetype":"venue"
},
  "geometry": {"coordinates":[6.1090297699,52.5004768372],"type":"Point"}
}