{
  "type": "Feature",
  "properties": {
    "addr:full":"Nwe Deventerw 99 Zwolle NL.08 8014 AE",
    "addr:housenumber":"99",
    "addr:postcode":"8014 ae",
    "iso:country":"NL",
    "sg:address":"Nwe Deventerw 99",
    "sg:city":"Zwolle",
    "sg:orig_category":"Artsen - Huisartsen",
    "sg:phone":"+31 38 465 0111",
    "sg:postcode":"8014 AE",
    "sg:province":"NL.08",
    "wof:name":"Es, H Van",
    "wof:placetype":"venue"
},
  "geometry": {"coordinates":[6.088738,52.512566],"type":"Point"}
}