{
  "type": "Feature",
  "properties": {
    "iso:country":"NL",
    "sg:address":"Leidekkerstr 6",
    "sg:city":"Ridderkerk",
    "sg:orig_category":"Hek- En Rasterwerken",
    "sg:phone":"+31 180 481 818",
    "sg:postcode":"2984 AV",
    "sg:province":"Zuid-Holland",
    "sg:website":"http://www.heras.nl",
    "wof:name":"Heras Nederland Bv",
    "wof:placetype":"venue"
},
  "geometry": {"coordinates":[4.609801,51.877068],"type":"Point"}
}