{
  "type": "Feature",
  "properties": {
    "addr:full":"Schaapsdrift 115 Arnhem Gelderland 6824 GR",
    "addr:housenumber":"115",
    "addr:postcode":"6824",
    "addr:street":"Schaapsdrift",
    "iso:country":"NL",
    "sg:address":"Schaapsdrift 115",
    "sg:city":"Arnhem",
    "sg:orig_category":"Fietshandelaren",
    "sg:phone":"+31 26 361 3671",
    "sg:postcode":"6824 GR",
    "sg:province":"Gelderland",
    "wof:name":"A V.D. Kamp",
    "wof:placetype":"venue"
},
  "geometry": {"coordinates":[5.942683,51.987846],"type":"Point"}
}