{
  "type": "Feature",
  "properties": {
    "addr:full":"Diepenveenstraat 15 Tilburg Noord-Brabant 5043 JL",
    "addr:housenumber":"15",
    "addr:postcode":"5043 jl",
    "addr:street":"Diepenveenstraat",
    "iso:country":"NL",
    "sg:address":"Diepenveenstraat 15",
    "sg:city":"Tilburg",
    "sg:orig_category":"Boekhouders",
    "sg:phone":"+31 13 570 1727",
    "sg:postcode":"5043 JL",
    "sg:province":"Noord-Brabant",
    "wof:name":"B & L Belasting En Lonen",
    "wof:placetype":"venue"
},
  "geometry": {"coordinates":[5.016419,51.575397],"type":"Point"}
}