{
  "type": "Feature",
  "properties": {
    "addr:full":"Kamperfoelielaan 39 Bosch En Duin Utrecht 3735 KR",
    "addr:housenumber":"39",
    "addr:postcode":"en duin;3735 kr",
    "addr:street":"Kamperfoelielaan",
    "iso:country":"NL",
    "sg:address":"Kamperfoelielaan 39",
    "sg:city":"Bosch En Duin",
    "sg:classifiers":[
        {
            "category":"Professional",
            "subcategory":"Accounting & Tax Preparation",
            "type":"Services"
        }
    ],
    "sg:phone":"+31 30 225 0478",
    "sg:postcode":"3735 KR",
    "sg:province":"Utrecht",
    "sg:tags":[
        "accountant"
    ],
    "wof:name":"Accountantskantoor H.J. Sprong Bv",
    "wof:placetype":"venue"
},
  "geometry": {"coordinates":[5.234853,52.134373],"type":"Point"}
}