{
  "type": "Feature",
  "properties": {
    "addr:full":"Pijlijserstraat 113 Tilburg Noord-Brabant 5041 KD",
    "addr:housenumber":"113",
    "addr:postcode":"5041 kd",
    "addr:street":"Pijlijserstraat",
    "iso:country":"NL",
    "sg:address":"Pijlijserstraat 113",
    "sg:city":"Tilburg",
    "sg:orig_category":"Autokeuringen",
    "sg:phone":"+31 13 542 4022",
    "sg:postcode":"5041 KD",
    "sg:province":"Noord-Brabant",
    "wof:name":"L H G M Schults",
    "wof:placetype":"venue"
},
  "geometry": {"coordinates":[5.070506,51.562412],"type":"Point"}
}