{
  "type": "Feature",
  "properties": {
    "addr:full":"Majeurstr 3 Hellevoetsluis Zuid-Holland 3223 PD",
    "addr:housenumber":"3",
    "addr:postcode":"3223 pd",
    "addr:street":"Majeurstr",
    "iso:country":"NL",
    "sg:address":"Majeurstr 3",
    "sg:city":"Hellevoetsluis",
    "sg:orig_category":"Grondwerken",
    "sg:phone":"+31 6 22932786",
    "sg:postcode":"3223 PD",
    "sg:province":"Zuid-Holland",
    "wof:name":"Looij, M",
    "wof:placetype":"venue"
},
  "geometry": {"coordinates":[4.161854,51.843681],"type":"Point"}
}