{
  "type": "Feature",
  "properties": {
    "iso:country":"NL",
    "sg:address":"Korenmarkt 12",
    "sg:city":"Hoorn Nh",
    "sg:orig_category":"Organisatiebureaus",
    "sg:phone":"+31 229 278 588",
    "sg:postcode":"1621 BG",
    "sg:province":"North Holland",
    "wof:name":"Hoekenga, Ing M G",
    "wof:placetype":"venue"
},
  "geometry": {"coordinates":[5.0627589226,52.6388053894],"type":"Point"}
}