{
  "type": "Feature",
  "properties": {
    "addr:full":"Willem Joseph V Ghentstr 19 Hellevoetsluis South Holland 3223 RH",
    "addr:housenumber":"19",
    "addr:postcode":"3223 rh",
    "addr:street":"Willem Joseph V Ghentstr",
    "iso:country":"NL",
    "sg:address":"Willem Joseph V Ghentstr 19",
    "sg:city":"Hellevoetsluis",
    "sg:orig_category":"Boekhouders",
    "sg:phone":"+31 181 390 026",
    "sg:postcode":"3223 RH",
    "sg:province":"South Holland",
    "wof:name":"Administratiekantoor Ravi",
    "wof:placetype":"venue"
},
  "geometry": {"coordinates":[4.148541,51.845032],"type":"Point"}
}