{
  "type": "Feature",
  "properties": {
    "addr:full":"Brink 66 Deventer NL.08 7411 BW",
    "addr:housenumber":"66;nl.08",
    "addr:postcode":"7411 bw",
    "addr:street":"Brink",
    "iso:country":"NL",
    "sg:address":"Brink 66",
    "sg:city":"Deventer",
    "sg:orig_category":"Kappers",
    "sg:phone":"+31 570 613 333",
    "sg:postcode":"7411 BW",
    "sg:province":"NL.08",
    "wof:name":"Kapsalon Ellen Klein Koerkamp",
    "wof:placetype":"venue"
},
  "geometry": {"coordinates":[6.1592741013,52.2512588501],"type":"Point"}
}