{
  "type": "Feature",
  "properties": {
    "iso:country":"NL",
    "sg:address":"T Kieftenland 52",
    "sg:city":"Limmen",
    "sg:orig_category":"Webdesign Bureaus",
    "sg:phone":"+31 72 505 2794",
    "sg:postcode":"1906 WG",
    "sg:province":"Noord-Holland",
    "sg:website":"http://www.xtra-webdesign.nl",
    "wof:name":"Xtra",
    "wof:placetype":"venue"
},
  "geometry": {"coordinates":[4.7053308487,52.5688285828],"type":"Point"}
}