{
  "type": "Feature",
  "properties": {
    "addr:full":"N Ysseldk 107 Ysselstein Ut Utrecht 3402 PG",
    "addr:housenumber":"107",
    "addr:postcode":"3402 pg",
    "addr:street":"N;Ysselstein",
    "iso:country":"NL",
    "sg:address":"N Ysseldk 107",
    "sg:city":"Ysselstein Ut",
    "sg:orig_category":"Adviesbureaus Bedrijfsorganisatie",
    "sg:phone":"+31 30 687 6406",
    "sg:postcode":"3402 PG",
    "sg:province":"Utrecht",
    "wof:name":"Power Of 4 Bv",
    "wof:placetype":"venue"
},
  "geometry": {"coordinates":[5.0281,52.02663],"type":"Point"}
}