{
  "type": "Feature",
  "properties": {
    "addr:full":"Haringvlietstr 50 Arnhem Gelderland 6826 ED",
    "addr:housenumber":"50",
    "addr:postcode":"6826 ed",
    "addr:street":"Haringvlietstr",
    "iso:country":"NL",
    "sg:address":"Haringvlietstr 50",
    "sg:city":"Arnhem",
    "sg:orig_category":"Verenigingen En Stichtingen",
    "sg:phone":"+31 26 361 8655",
    "sg:postcode":"6826 ED",
    "sg:province":"Gelderland",
    "sg:website":"http://www.jongerencentrumpush.nl",
    "wof:name":"Push Jongerencentrum",
    "wof:placetype":"venue"
},
  "geometry": {"coordinates":[5.941798,51.981647],"type":"Point"}
}