{
  "type": "Feature",
  "properties": {
    "addr:full":"Kosmonaut 24A Amersfoort Utrecht 3824 MK",
    "addr:housenumber":"24a",
    "addr:postcode":"3824",
    "addr:street":"Kosmonaut",
    "iso:country":"NL",
    "sg:address":"Kosmonaut 24A",
    "sg:city":"Amersfoort",
    "sg:orig_category":"Wijnkoperijen En -Groothandel",
    "sg:phone":"+31 33 476 6000",
    "sg:postcode":"3824 MK",
    "sg:province":"Utrecht",
    "wof:name":"Grammont",
    "wof:placetype":"venue"
},
  "geometry": {"coordinates":[5.3923997879,52.1987304688],"type":"Point"}
}