{
  "type": "Feature",
  "properties": {
    "addr:full":"Verwersdk 102-104 Delft Zuid-Holland 2611 NK",
    "addr:housenumber":"102-104",
    "addr:postcode":"2611 nk",
    "addr:street":"Delft",
    "iso:country":"NL",
    "sg:address":"Verwersdk 102-104",
    "sg:city":"Delft",
    "sg:orig_category":"Verenigingen En Stichtingen",
    "sg:phone":"+31 15 212 1516",
    "sg:postcode":"2611 NK",
    "sg:province":"Zuid-Holland",
    "wof:name":"Soc Novum",
    "wof:placetype":"venue"
},
  "geometry": {"coordinates":[4.357521,52.014847],"type":"Point"}
}