{
  "type": "Feature",
  "properties": {
    "addr:full":"Schiedamsewg 35 Rotterdam Zuid-Holland 3026 AC",
    "addr:housenumber":"35",
    "addr:postcode":"3026 ac",
    "addr:street":"Schiedamsewg",
    "iso:country":"NL",
    "sg:address":"Schiedamsewg 35",
    "sg:city":"Rotterdam",
    "sg:orig_category":"Publiciteitsbureaus",
    "sg:phone":"+31 10 476 7991",
    "sg:postcode":"3026 AC",
    "sg:province":"Zuid-Holland",
    "wof:name":"Diamond Juwelier Sw",
    "wof:placetype":"venue"
},
  "geometry": {"coordinates":[4.446912,51.910027],"type":"Point"}
}