{
  "type": "Feature",
  "properties": {
    "iso:country":"NL",
    "sg:address":"Westfriesedk 160",
    "sg:city":"Kolhorn",
    "sg:orig_category":"Organisatiebureaus",
    "sg:phone":"+31 224 533 060",
    "sg:postcode":"1767 CV",
    "sg:province":"North Holland",
    "wof:name":"Ager Bovum Bv",
    "wof:placetype":"venue"
},
  "geometry": {"coordinates":[4.8899002075,52.7900810242],"type":"Point"}
}