{
  "type": "Feature",
  "properties": {
    "addr:full":"Herenstraat 24 Rijswijk Zh Zuid-Holland 2282 BT",
    "addr:housenumber":"24",
    "addr:postcode":"zh;2282 bt",
    "addr:street":"Herenstraat",
    "iso:country":"NL",
    "sg:address":"Herenstraat 24",
    "sg:city":"Rijswijk Zh",
    "sg:orig_category":"Diverse Grafische Activiteiten",
    "sg:phone":"+31 70 415 1575",
    "sg:postcode":"2282 BT",
    "sg:province":"Zuid-Holland",
    "wof:name":"Nocliches Bv",
    "wof:placetype":"venue"
},
  "geometry": {"coordinates":[4.336248,52.056419],"type":"Point"}
}