{
  "type": "Feature",
  "properties": {
    "addr:full":"De Nieuwe Haven 35 Hardenberg Overijssel 7772 BC",
    "addr:housenumber":"35",
    "addr:postcode":"7772 bc",
    "addr:street":"De Nieuwe Haven",
    "iso:country":"NL",
    "sg:address":"De Nieuwe Haven 35",
    "sg:city":"Hardenberg",
    "sg:orig_category":"Mobiele Service Aan Motorvoertuigen",
    "sg:phone":"+31 523 261 448",
    "sg:postcode":"7772 BC",
    "sg:province":"Overijssel",
    "wof:name":"Oostenbrink Goverts Kraanverhuur",
    "wof:placetype":"venue"
},
  "geometry": {"coordinates":[6.629237,52.559006],"type":"Point"}
}