{
  "type": "Feature",
  "properties": {
    "addr:full":"Koestr 13 Maastricht Limburg 6211 HR",
    "addr:housenumber":"13",
    "addr:postcode":"6211 hr",
    "addr:street":"Koestr",
    "iso:country":"NL",
    "sg:address":"Koestr 13",
    "sg:city":"Maastricht",
    "sg:orig_category":"Cafetaria'S",
    "sg:phone":"+31 43 325 6533",
    "sg:postcode":"6211 HR",
    "sg:province":"Limburg",
    "wof:name":"Santorini",
    "wof:placetype":"venue"
},
  "geometry": {"coordinates":[5.692957,50.846607],"type":"Point"}
}