{
  "type": "Feature",
  "properties": {
    "addr:full":"Ambonstr 28A Groningen Groningen 9715 HD",
    "addr:housenumber":"28a",
    "addr:postcode":"9715 hd",
    "addr:street":"Ambonstr",
    "iso:country":"NL",
    "sg:address":"Ambonstr 28A",
    "sg:city":"Groningen",
    "sg:orig_category":"Webdesign Bureaus",
    "sg:phone":"+31 50 577 8236",
    "sg:postcode":"9715 HD",
    "sg:province":"Groningen",
    "wof:name":"Ihost",
    "wof:placetype":"venue"
},
  "geometry": {"coordinates":[6.5674757957,53.2310142517],"type":"Point"}
}