{
  "type": "Feature",
  "properties": {
    "addr:full":"Schoonoordstr 37 Rotterdam South Holland 3036 XG",
    "addr:housenumber":"37",
    "addr:postcode":"3036 xg",
    "addr:street":"Schoonoordstr",
    "iso:country":"NL",
    "sg:address":"Schoonoordstr 37",
    "sg:city":"Rotterdam",
    "sg:orig_category":"Juridische Adviseurs",
    "sg:phone":"+31 10 467 8062",
    "sg:postcode":"3036 XG",
    "sg:province":"South Holland",
    "wof:name":"Inter Iura",
    "wof:placetype":"venue"
},
  "geometry": {"coordinates":[4.477967,51.936718],"type":"Point"}
}