{
  "type": "Feature",
  "properties": {
    "addr:full":"Borndiep 49 Capelle A/D Ijssel Zuid-Holland 2904 RA",
    "addr:housenumber":"49;a / d",
    "addr:postcode":"2904 ra",
    "addr:street":"Borndiep",
    "iso:country":"NL",
    "sg:address":"Borndiep 49",
    "sg:city":"Capelle A/D Ijssel",
    "sg:orig_category":"Diverse Grafische Activiteiten",
    "sg:phone":"+31 10 458 5135",
    "sg:postcode":"2904 RA",
    "sg:province":"Zuid-Holland",
    "wof:name":"J.O. V.D. Herik",
    "wof:placetype":"venue"
},
  "geometry": {"coordinates":[4.60789,51.932671],"type":"Point"}
}