{
  "type": "Feature",
  "properties": {
    "addr:full":"Kennemerbeek 4 Zaandam North Holland 1509 EL",
    "addr:housenumber":"4",
    "addr:postcode":"1509 el",
    "addr:street":"Kennemerbeek",
    "iso:country":"NL",
    "sg:address":"Kennemerbeek 4",
    "sg:city":"Zaandam",
    "sg:orig_category":"Verzekeringen - Verzekeringskantoren",
    "sg:phone":"+31 75 616 7138",
    "sg:postcode":"1509 EL",
    "sg:province":"North Holland",
    "wof:name":"Schoenmaker En Zn, Fa C H",
    "wof:placetype":"venue"
},
  "geometry": {"coordinates":[4.835585,52.469353],"type":"Point"}
}