{
  "type": "Feature",
  "properties": {
    "iso:country":"NL",
    "sg:address":"Kennemerbeek 4",
    "sg:city":"Zaandam",
    "sg:orig_category":"Verzekeringen - Verzekeringskantoren",
    "sg:phone":"+31 75 616 7138",
    "sg:postcode":"1509 EL",
    "sg:province":"North Holland",
    "wof:name":"Schoenmaker En Zn, Fa C H",
    "wof:placetype":"venue"
},
  "geometry": {"coordinates":[4.835585,52.469353],"type":"Point"}
}