{
  "type": "Feature",
  "properties": {
    "addr:full":"Duinwg 6 Noordlaren Groningen 9479 TM",
    "addr:housenumber":"6",
    "addr:postcode":"9479 tm",
    "addr:street":"Duinwg",
    "iso:country":"NL",
    "sg:address":"Duinwg 6",
    "sg:city":"Noordlaren",
    "sg:orig_category":"Vakantieverblijven",
    "sg:phone":"+31 50 409 1634",
    "sg:postcode":"9479 TM",
    "sg:province":"Groningen",
    "wof:name":"Hondsrug, De",
    "wof:placetype":"venue"
},
  "geometry": {"coordinates":[6.650892,53.118271],"type":"Point"}
}