{
  "type": "Feature",
  "properties": {
    "iso:country":"NL",
    "sg:address":"Haverakker 2",
    "sg:city":"Wezep",
    "sg:orig_category":"Autorijscholen",
    "sg:phone":"+31 38 376 1820",
    "sg:postcode":"8091 NW",
    "sg:province":"Gelderland",
    "wof:name":"Middelkoop, J",
    "wof:placetype":"venue"
},
  "geometry": {"coordinates":[5.988725,52.457314],"type":"Point"}
}