{
  "type": "Feature",
  "properties": {
    "iso:country":"NL",
    "sg:address":"Beukenhof 56",
    "sg:city":"Lelystad",
    "sg:orig_category":"Bedrijfsopleidingen",
    "sg:phone":"+31 320 215 967",
    "sg:postcode":"8212 EB",
    "sg:province":"Flevoland",
    "sg:website":"http://www.optio.nl",
    "wof:name":"Optio Ned Bv",
    "wof:placetype":"venue"
},
  "geometry": {"coordinates":[5.49847,52.509567],"type":"Point"}
}