{
  "type": "Feature",
  "properties": {
    "addr:full":"Wilhelminaln 39 Thorn Limburg 6017 BA",
    "addr:housenumber":"39",
    "addr:postcode":"6017 ba",
    "addr:street":"Wilhelminaln",
    "iso:country":"NL",
    "sg:address":"Wilhelminaln 39",
    "sg:city":"Thorn",
    "sg:orig_category":"Houtgroothandel",
    "sg:phone":"+31 475 561 237",
    "sg:postcode":"6017 BA",
    "sg:province":"Limburg",
    "sg:website":"http://www.parren.nl",
    "wof:name":"Parren Houthandel",
    "wof:placetype":"venue"
},
  "geometry": {"coordinates":[5.837406,51.164082],"type":"Point"}
}