{
  "type": "Feature",
  "properties": {
    "iso:country":"NL",
    "sg:address":"C V Maasdykstr 59",
    "sg:city":"Utrecht",
    "sg:orig_category":"Gehandicapteninformatie",
    "sg:phone":"+31 30 244 2949",
    "sg:postcode":"3555 VM",
    "sg:province":"Utrecht",
    "wof:name":"Zand, 'T",
    "wof:placetype":"venue"
},
  "geometry": {"coordinates":[5.07365,52.119228],"type":"Point"}
}