{
  "type": "Feature",
  "properties": {
    "addr:full":"Chopinln 83 Doorwerth Gelderland 6865 EZ",
    "addr:housenumber":"83",
    "addr:postcode":"6865 ez",
    "addr:street":"Chopinln;Gelderland",
    "iso:country":"NL",
    "sg:address":"Chopinln 83",
    "sg:city":"Doorwerth",
    "sg:orig_category":"Loopbaanbegeleiding",
    "sg:phone":"+31 26 445 3120",
    "sg:postcode":"6865 EZ",
    "sg:province":"Gelderland",
    "sg:website":"http://www.carriereprofs.nl",
    "wof:name":"Carri\u00e8re Profs",
    "wof:placetype":"venue"
},
  "geometry": {"coordinates":[5.793784,51.983936],"type":"Point"}
}