{
  "type": "Feature",
  "properties": {
    "iso:country":"NL",
    "sg:address":"Fresiastraat 7",
    "sg:city":"Naaldwijk",
    "sg:orig_category":"Technische Studies And Onderzoek",
    "sg:phone":"+31 174 621 290",
    "sg:postcode":"2671 KS",
    "sg:province":"South Holland",
    "wof:name":"Van Staalduinen Techniek Bv",
    "wof:placetype":"venue"
},
  "geometry": {"coordinates":[4.213212,51.99015],"type":"Point"}
}