{
  "type": "Feature",
  "properties": {
    "addr:full":"Surinamestr 27B S Gravenhage Zuid-Holland 2585 GH",
    "addr:housenumber":"27b;gravenhage",
    "addr:postcode":"2585 gh",
    "addr:street":"Surinamestr;S",
    "iso:country":"NL",
    "sg:address":"Surinamestr 27B",
    "sg:city":"S Gravenhage",
    "sg:orig_category":"Wijnkoperijen En -Groothandel",
    "sg:phone":"+31 70 362 7559",
    "sg:postcode":"2585 GH",
    "sg:province":"Zuid-Holland",
    "sg:website":"http://www.vinovetro.nl",
    "wof:name":"Vino & Vetro",
    "wof:placetype":"venue"
},
  "geometry": {"coordinates":[4.2977700233,52.0947990417],"type":"Point"}
}