{
  "type": "Feature",
  "properties": {
    "addr:full":"Strijpsestraat 52 Eindhoven North Brabant 5616 GR",
    "addr:housenumber":"52",
    "addr:postcode":"5616",
    "addr:street":"Strijpsestraat",
    "iso:country":"NL",
    "sg:address":"Strijpsestraat 52",
    "sg:city":"Eindhoven",
    "sg:orig_category":"Verzekeringen",
    "sg:phone":"+31 40 257 0444",
    "sg:postcode":"5616 GR",
    "sg:province":"North Brabant",
    "wof:name":"J & S Bemiddeling",
    "wof:placetype":"venue"
},
  "geometry": {"coordinates":[5.460776,51.438854],"type":"Point"}
}