{
  "type": "Feature",
  "properties": {
    "iso:country":"NL",
    "sg:address":"Kerkstr 23A",
    "sg:city":"Eemnes",
    "sg:orig_category":"Fietsen En Bromfietsen",
    "sg:phone":"+31 35 538 3535",
    "sg:postcode":"3755 CK",
    "sg:province":"Utrecht",
    "wof:name":"Liersen",
    "wof:placetype":"venue"
},
  "geometry": {"coordinates":[5.264872,52.251968],"type":"Point"}
}