{
  "type": "Feature",
  "properties": {
    "addr:full":"T Woud 49D Kant Brielle Zuid-Holland 3232 LN",
    "addr:housenumber":"49d",
    "addr:postcode":"3232 ln",
    "addr:street":"T Woud",
    "iso:country":"NL",
    "sg:address":"T Woud 49D Kant",
    "sg:city":"Brielle",
    "sg:orig_category":"Agenturen En Commissiehandel",
    "sg:phone":"+31 181 410 700",
    "sg:postcode":"3232 LN",
    "sg:province":"Zuid-Holland",
    "wof:name":"Wolff & Company Bv, J",
    "wof:placetype":"venue"
},
  "geometry": {"coordinates":[4.167875,51.90406],"type":"Point"}
}