{
  "type": "Feature",
  "properties": {
    "addr:full":"Julianastraat 88 Moerkapelle South Holland 2751 GA",
    "addr:housenumber":"88",
    "addr:postcode":"2751 ga",
    "addr:street":"Julianastraat",
    "iso:country":"NL",
    "sg:address":"Julianastraat 88",
    "sg:city":"Moerkapelle",
    "sg:orig_category":"Goederenvervoer Over De Weg",
    "sg:phone":"+31 79 593 1712",
    "sg:postcode":"2751 GA",
    "sg:province":"South Holland",
    "wof:name":"C J Bakker Transport",
    "wof:placetype":"venue"
},
  "geometry": {"coordinates":[4.587528,52.044243],"type":"Point"}
}