{
  "type": "Feature",
  "properties": {
    "addr:full":"Spui 186 S Gravenhage South Holland 2511 BW",
    "addr:housenumber":"186",
    "addr:postcode":"2511 bw",
    "addr:street":"Spui;S Gravenhage",
    "iso:country":"NL",
    "sg:address":"Spui 186",
    "sg:city":"S Gravenhage",
    "sg:orig_category":"Juridische Adviseurs",
    "sg:phone":"+31 70 346 0974",
    "sg:postcode":"2511 BW",
    "sg:province":"South Holland",
    "sg:website":"http://www.iji.nl",
    "wof:name":"Int Juridisch Instituut",
    "wof:placetype":"venue"
},
  "geometry": {"coordinates":[4.31627,52.07896],"type":"Point"}
}