{
  "type": "Feature",
  "properties": {
    "addr:full":"Kerkstr 21 Zwartsluis Overijssel 8064 DM",
    "addr:housenumber":"21",
    "addr:postcode":"8064 dm",
    "addr:street":"Kerkstr",
    "iso:country":"NL",
    "sg:address":"Kerkstr 21",
    "sg:city":"Zwartsluis",
    "sg:orig_category":"Fietsen En Bromfietsen",
    "sg:phone":"+31 38 386 8112",
    "sg:postcode":"8064 DM",
    "sg:province":"Overijssel",
    "wof:name":"Maandag'S Rijwielhandel",
    "wof:placetype":"venue"
},
  "geometry": {"coordinates":[6.071681,52.640305],"type":"Point"}
}