{
  "type": "Feature",
  "properties": {
    "addr:full":"Hoeksekd 84 Bergschenhoek South Holland 2661 GL",
    "addr:housenumber":"84",
    "addr:postcode":"2661 gl",
    "addr:street":"Hoeksekd",
    "iso:country":"NL",
    "sg:address":"Hoeksekd 84",
    "sg:city":"Bergschenhoek",
    "sg:orig_category":"Grondwerken",
    "sg:phone":"+31 10 521 4170",
    "sg:postcode":"2661 GL",
    "sg:province":"South Holland",
    "wof:name":"Benschop, C L",
    "wof:placetype":"venue"
},
  "geometry": {"coordinates":[4.500133,51.989536],"type":"Point"}
}