{
  "type": "Feature",
  "properties": {
    "addr:full":"Marnixkade 74 Amsterdam Noord-Holland 1015 ZD",
    "addr:housenumber":"74",
    "addr:postcode":"1015 zd",
    "addr:street":"Marnixkade",
    "iso:country":"NL",
    "sg:address":"Marnixkade 74",
    "sg:city":"Amsterdam",
    "sg:orig_category":"Krantenuitgeverijen",
    "sg:phone":"+31 20 624 0829",
    "sg:postcode":"1015 ZD",
    "sg:province":"Noord-Holland",
    "wof:name":"Asi",
    "wof:placetype":"venue"
},
  "geometry": {"coordinates":[4.878682,52.378559],"type":"Point"}
}