{
  "type": "Feature",
  "properties": {
    "iso:country":"NL",
    "sg:address":"Zanddijk 5",
    "sg:city":"Oostvoorne",
    "sg:orig_category":"Watersportartikelen",
    "sg:phone":"+31 181 487 960",
    "sg:postcode":"3233 XJ",
    "sg:province":"Zuid-Holland",
    "sg:website":"http://www.geijsman-watersport.nl",
    "wof:name":"Geijsman Bv",
    "wof:placetype":"venue"
},
  "geometry": {"coordinates":[4.1067471504,51.9237594604],"type":"Point"}
}