{
  "type": "Feature",
  "properties": {
    "addr:full":"Glanerbeekwg 3 Glane Overijssel 7585 PJ",
    "addr:housenumber":"3",
    "addr:postcode":"7585 pj",
    "addr:street":"Glanerbeekwg",
    "iso:country":"NL",
    "sg:address":"Glanerbeekwg 3",
    "sg:city":"Glane",
    "sg:orig_category":"Honden- En Kattentrimsalons",
    "sg:phone":"+31 53 461 0730",
    "sg:postcode":"7585 PJ",
    "sg:province":"Overijssel",
    "wof:name":"Baake, Femke",
    "wof:placetype":"venue"
},
  "geometry": {"coordinates":[6.993921,52.229042],"type":"Point"}
}