{
  "type": "Feature",
  "properties": {
    "addr:full":"Bredaseweg 24 Baarle Nassau Noord-Brabant 5111 GD",
    "addr:housenumber":"24",
    "addr:postcode":"5111 gd",
    "addr:street":"Bredaseweg",
    "iso:country":"NL",
    "sg:address":"Bredaseweg 24",
    "sg:city":"Baarle Nassau",
    "sg:orig_category":"Huisdierenfokkers",
    "sg:phone":"+31 13 507 8585",
    "sg:postcode":"5111 GD",
    "sg:province":"Noord-Brabant",
    "wof:name":"Of Jack'S Paradise",
    "wof:placetype":"venue"
},
  "geometry": {"coordinates":[4.909901,51.461857],"type":"Point"}
}