{
  "type": "Feature",
  "properties": {
    "addr:full":"Landweringstr 112 Sittard Limburg 6133 AJ",
    "addr:housenumber":"112",
    "addr:postcode":"6133 aj",
    "addr:street":"Sittard Limburg",
    "iso:country":"NL",
    "sg:address":"Landweringstr 112",
    "sg:city":"Sittard",
    "sg:orig_category":"Peuterspeelzalen",
    "sg:phone":"+31 46 452 0792",
    "sg:postcode":"6133 AJ",
    "sg:province":"Limburg",
    "wof:name":"Ukkepuk, Sticht",
    "wof:placetype":"venue"
},
  "geometry": {"coordinates":[5.857472,50.990524],"type":"Point"}
}