{
  "type": "Feature",
  "properties": {
    "iso:country":"NL",
    "sg:address":"Zeekampln 10",
    "sg:city":"Heiloo",
    "sg:orig_category":"Adviesbureaus Bedrijfsorganisatie",
    "sg:phone":"+31 72 533 7138",
    "sg:postcode":"1851 XG",
    "sg:province":"Noord-Holland",
    "wof:name":"Astra Consult",
    "wof:placetype":"venue"
},
  "geometry": {"coordinates":[4.700188,52.595985],"type":"Point"}
}