{
  "type": "Feature",
  "properties": {
    "iso:country":"NL",
    "sg:address":"Grindzuigerstr 9",
    "sg:city":"Almere",
    "sg:orig_category":"Organisatiebureaus",
    "sg:phone":"+31 36 546 8099",
    "sg:postcode":"1333 MS",
    "sg:province":"NL.",
    "wof:name":"Bakker & Partn",
    "wof:placetype":"venue"
},
  "geometry": {"coordinates":[5.2690038681,52.4062385559],"type":"Point"}
}