{
  "type": "Feature",
  "properties": {
    "addr:full":"Richterswg 3A Enschede Overijssel 7521 BV",
    "addr:housenumber":"3a",
    "addr:postcode":"7521 bv",
    "addr:street":"Richterswg",
    "iso:country":"NL",
    "sg:address":"Richterswg 3A",
    "sg:city":"Enschede",
    "sg:orig_category":"Horecabenodigdheden",
    "sg:phone":"+31 53 433 6079",
    "sg:postcode":"7521 BV",
    "sg:province":"Overijssel",
    "wof:name":"Gouden Ambacht",
    "wof:placetype":"venue"
},
  "geometry": {"coordinates":[6.877931,52.223095],"type":"Point"}
}