{
  "type": "Feature",
  "properties": {
    "iso:country":"NL",
    "sg:address":"Voordijk 25",
    "sg:city":"Sint Hubert",
    "sg:orig_category":"Paramedische Behandelingen",
    "sg:phone":"+31 485 454 328",
    "sg:postcode":"5454 GB",
    "sg:province":"North Brabant",
    "wof:name":"Pvg Bemiddelingsburo Voor Kraamzorg",
    "wof:placetype":"venue"
},
  "geometry": {"coordinates":[5.808062,51.681969],"type":"Point"}
}