{
  "type": "Feature",
  "properties": {
    "addr:full":"Voordijk 25 Sint Hubert North Brabant 5454 GB",
    "addr:housenumber":"25",
    "addr:postcode":"5454 gb",
    "addr:street":"Voordijk",
    "iso:country":"NL",
    "sg:address":"Voordijk 25",
    "sg:city":"Sint Hubert",
    "sg:orig_category":"Paramedische Behandelingen",
    "sg:phone":"+31 485 454 328",
    "sg:postcode":"5454 GB",
    "sg:province":"North Brabant",
    "wof:name":"Pvg Bemiddelingsburo Voor Kraamzorg",
    "wof:placetype":"venue"
},
  "geometry": {"coordinates":[5.808062,51.681969],"type":"Point"}
}