{
  "type": "Feature",
  "properties": {
    "addr:full":"Hoofdwg W 12-14 Nieuwolda Groningen 9944 EB",
    "addr:postcode":"9944 eb",
    "addr:street":"W 12-14 Nieuwolda",
    "iso:country":"NL",
    "sg:address":"Hoofdwg W 12-14",
    "sg:city":"Nieuwolda",
    "sg:orig_category":"Grondwerken",
    "sg:phone":"+31 596 541 481",
    "sg:postcode":"9944 EB",
    "sg:province":"Groningen",
    "wof:name":"Borgje, Het",
    "wof:placetype":"venue"
},
  "geometry": {"coordinates":[6.962799,53.235962],"type":"Point"}
}