{
  "type": "Feature",
  "properties": {
    "addr:full":"Mosselenbuurt 16 Bergen Nh North Holland 1861 CA",
    "addr:housenumber":"16",
    "addr:postcode":"1861 ca",
    "addr:street":"Mosselenbuurt",
    "iso:country":"NL",
    "sg:address":"Mosselenbuurt 16",
    "sg:city":"Bergen Nh",
    "sg:orig_category":"Onroerende Goederen",
    "sg:phone":"+31 72 581 4901",
    "sg:postcode":"1861 CA",
    "sg:province":"North Holland",
    "wof:name":"Villabella International Bv",
    "wof:placetype":"venue"
},
  "geometry": {"coordinates":[4.686583,52.664791],"type":"Point"}
}