{
  "type": "Feature",
  "properties": {
    "addr:full":"Lagedykerwg 1 Schagen North Holland 1742 NB",
    "addr:housenumber":"1",
    "addr:postcode":"1742 nb",
    "addr:street":"Lagedykerwg",
    "iso:country":"NL",
    "sg:address":"Lagedykerwg 1",
    "sg:city":"Schagen",
    "sg:orig_category":"Meubelen",
    "sg:phone":"+31 224 216 227",
    "sg:postcode":"1742 NB",
    "sg:province":"North Holland",
    "sg:website":"http://www.fizzyliving.nl",
    "wof:name":"Fizzy",
    "wof:placetype":"venue"
},
  "geometry": {"coordinates":[4.787359,52.790508],"type":"Point"}
}