{
  "type": "Feature",
  "properties": {
    "iso:country":"NL",
    "sg:address":"Bennebroekerln 35A",
    "sg:city":"Bennebroek",
    "sg:orig_category":"Muziekinstrumenten En Bladmuziek",
    "sg:phone":"+31 23 584 9003",
    "sg:postcode":"2121 GR",
    "sg:province":"Noord-Holland",
    "wof:name":"Otja",
    "wof:placetype":"venue"
},
  "geometry": {"coordinates":[4.595839,52.31955],"type":"Point"}
}