{
  "type": "Feature",
  "properties": {
    "addr:full":"De Tinneweide 159 Veenendaal Utrecht 3901 KJ",
    "addr:housenumber":"159",
    "addr:postcode":"3901 kj",
    "addr:street":"De Tinneweide",
    "iso:country":"NL",
    "sg:address":"De Tinneweide 159",
    "sg:city":"Veenendaal",
    "sg:orig_category":"Hijswerktuigen",
    "sg:phone":"+31 318 548 950",
    "sg:postcode":"3901 KJ",
    "sg:province":"Utrecht",
    "wof:name":"Telemat Bv",
    "wof:placetype":"venue"
},
  "geometry": {"coordinates":[5.563406,52.018906],"type":"Point"}
}