{
  "type": "Feature",
  "properties": {
    "iso:country":"NL",
    "sg:address":"Koekoekstraat 43",
    "sg:city":"Tegelen",
    "sg:orig_category":"Verhuur Catering-, Feest- En Evenementbenodigdheden",
    "sg:phone":"+31 77 373 7262",
    "sg:postcode":"5931 LP",
    "sg:province":"Limburg",
    "wof:name":"Vullings Verhuur",
    "wof:placetype":"venue"
},
  "geometry": {"coordinates":[6.14586,51.341061],"type":"Point"}
}