{
  "type": "Feature",
  "properties": {
    "iso:country":"NL",
    "sg:address":"Kloosterstr 17",
    "sg:city":"Doesburg",
    "sg:orig_category":"Bejaarden - Verzorgingstehuizen",
    "sg:phone":"+31 313 610 600",
    "sg:postcode":"6981 CC",
    "sg:province":"Gelderland",
    "wof:name":"Elisabeth, Sticht",
    "wof:placetype":"venue"
},
  "geometry": {"coordinates":[6.133128,52.013042],"type":"Point"}
}