{
  "type": "Feature",
  "properties": {
    "addr:full":"Dierenriemstr 152 Groningen Groningen 9742 AK",
    "addr:housenumber":"152",
    "addr:postcode":"9742 ak",
    "iso:country":"NL",
    "sg:address":"Dierenriemstr 152",
    "sg:city":"Groningen",
    "sg:orig_category":"Wolartikelen En Breiwol",
    "sg:phone":"+31 50 577 3760",
    "sg:postcode":"9742 AK",
    "sg:province":"Groningen",
    "wof:name":"Sajet",
    "wof:placetype":"venue"
},
  "geometry": {"coordinates":[6.5443291664,53.2298851013],"type":"Point"}
}