{
  "type": "Feature",
  "properties": {
    "addr:full":"Rapenburgerstraat 109 Amsterdam Noord-Holland 1011 VL",
    "addr:housenumber":"109",
    "addr:postcode":"1011 vl",
    "addr:street":"Rapenburgerstraat",
    "iso:country":"NL",
    "sg:address":"Rapenburgerstraat 109",
    "sg:city":"Amsterdam",
    "sg:classifiers":[
        {
            "category":"Professional",
            "subcategory":"Accounting & Tax Preparation",
            "type":"Services"
        }
    ],
    "sg:phone":"+31 20 638 1881",
    "sg:postcode":"1011 VL",
    "sg:province":"Noord-Holland",
    "sg:tags":[
        "accountant"
    ],
    "wof:name":"Registeraccountants Mock & Partners",
    "wof:placetype":"venue"
},
  "geometry": {"coordinates":[4.906954,52.368629],"type":"Point"}
}