{
  "type": "Feature",
  "properties": {
    "iso:country":"NL",
    "sg:address":"Postbus 19153",
    "sg:city":"Rotterdam",
    "sg:orig_category":"Organisatiebureaus",
    "sg:phone":"+31 10 404 8422",
    "sg:postcode":"3001 BD",
    "sg:province":"Friesland",
    "sg:website":"http://www.ducos.com",
    "wof:name":"Ducos Acr",
    "wof:placetype":"venue"
},
  "geometry": {"coordinates":[4.470749855,51.922618866],"type":"Point"}
}