{
  "type": "Feature",
  "properties": {
    "iso:country":"NL",
    "sg:address":"Souvereinstraat 15",
    "sg:city":"Oosterhout Nb",
    "sg:orig_category":"Loodgieterswerk, Verwarming And Sanitaire Installaties",
    "sg:phone":"+31 162 424 460",
    "sg:postcode":"4903 RH",
    "sg:province":"North Brabant",
    "wof:name":"Hadeha",
    "wof:placetype":"venue"
},
  "geometry": {"coordinates":[4.882118,51.624001],"type":"Point"}
}