{
  "type": "Feature",
  "properties": {
    "addr:full":"Lange Amerikaweg 73 Apeldoorn Gelderland 7332 BP",
    "addr:housenumber":"73",
    "addr:postcode":"7332 bp",
    "addr:street":"Lange Amerikaweg;Gelderland",
    "iso:country":"NL",
    "sg:address":"Lange Amerikaweg 73",
    "sg:city":"Apeldoorn",
    "sg:orig_category":"Hypotheken",
    "sg:phone":"+31 55 533 0339",
    "sg:postcode":"7332 BP",
    "sg:province":"Gelderland",
    "sg:website":"http://www.huis-hypotheek.nl",
    "wof:name":"Huis & Hypotheek",
    "wof:placetype":"venue"
},
  "geometry": {"coordinates":[5.986007,52.18005],"type":"Point"}
}