{
  "type": "Feature",
  "properties": {
    "addr:full":"Laan Van Malkenschoten 95 Apeldoorn Gelderland 7333 NP",
    "addr:housenumber":"95",
    "addr:postcode":"7333 np",
    "addr:street":"Laan Van Malkenschoten;Gelderland",
    "iso:country":"NL",
    "sg:address":"Laan Van Malkenschoten 95",
    "sg:city":"Apeldoorn",
    "sg:orig_category":"Pompen And Compressoren Fab",
    "sg:phone":"+31 55 541 1255",
    "sg:postcode":"7333 NP",
    "sg:province":"Gelderland",
    "wof:name":"Bv Machinefabriek Vremac",
    "wof:placetype":"venue"
},
  "geometry": {"coordinates":[5.97945,52.179897],"type":"Point"}
}