{
  "type": "Feature",
  "properties": {
    "iso:country":"NL",
    "sg:address":"Leidsestraat 32",
    "sg:city":"Amsterdam",
    "sg:orig_category":"Kantoorartikelen",
    "sg:phone":"+31 20 422 0452",
    "sg:postcode":"1017 PB",
    "sg:province":"North Holland",
    "wof:name":"Carto Studio Bv",
    "wof:placetype":"venue"
},
  "geometry": {"coordinates":[4.8868169785,52.3663024902],"type":"Point"}
}