{
  "type": "Feature",
  "properties": {
    "addr:full":"Park Oosterspaarn 42 Haarlem Noord-Holland 2036 MB",
    "addr:housenumber":"42",
    "addr:postcode":"2036 mb",
    "addr:street":"Park Oosterspaarn",
    "iso:country":"NL",
    "sg:address":"Park Oosterspaarn 42",
    "sg:city":"Haarlem",
    "sg:orig_category":"Boekhouders",
    "sg:phone":"+31 23 533 2106",
    "sg:postcode":"2036 MB",
    "sg:province":"Noord-Holland",
    "wof:name":"Bedrijfsadm.- En Belastingadv. Buro De Groot",
    "wof:placetype":"venue"
},
  "geometry": {"coordinates":[4.644918,52.35059],"type":"Point"}
}