{
  "type": "Feature",
  "properties": {
    "addr:full":"Pr Irenewg 30 Geldermalsen Gelderland 4191 XC",
    "addr:housenumber":"30",
    "addr:postcode":"4191 xc",
    "addr:street":"Gelderland",
    "iso:country":"NL",
    "sg:address":"Pr Irenewg 30",
    "sg:city":"Geldermalsen",
    "sg:orig_category":"Glazenwasserijen",
    "sg:phone":"+31 345 570 806",
    "sg:postcode":"4191 XC",
    "sg:province":"Gelderland",
    "sg:website":"http://www.betuwegids.net/wilruton",
    "wof:name":"Wilruton",
    "wof:placetype":"venue"
},
  "geometry": {"coordinates":[5.299264,51.882965],"type":"Point"}
}