{
  "type": "Feature",
  "properties": {
    "addr:full":"Floresstraat 5 Haarlem North Holland 2022 BB",
    "addr:housenumber":"5",
    "addr:postcode":"2022 bb",
    "addr:street":"Floresstraat",
    "iso:country":"NL",
    "sg:address":"Floresstraat 5",
    "sg:city":"Haarlem",
    "sg:classifiers":[
        {
            "category":"Fast Food",
            "type":"Food & Drink"
        }
    ],
    "sg:phone":"+31 23 525 5731",
    "sg:postcode":"2022 BB",
    "sg:province":"North Holland",
    "sg:tags":[
        "afhaal",
        "restaurant"
    ],
    "wof:name":"Brouwer Snacks",
    "wof:placetype":"venue"
},
  "geometry": {"coordinates":[4.644967,52.399326],"type":"Point"}
}