{
  "type": "Feature",
  "properties": {
    "addr:full":"Heuningstraat 24 Ochten Gelderland 4051 CB",
    "addr:housenumber":"24",
    "addr:postcode":"4051 cb",
    "addr:street":"Heuningstraat;Gelderland",
    "iso:country":"NL",
    "sg:address":"Heuningstraat 24",
    "sg:city":"Ochten",
    "sg:orig_category":"Fruit And Groenten Gh",
    "sg:phone":"+31 344 642 797",
    "sg:postcode":"4051 CB",
    "sg:province":"Gelderland",
    "wof:name":"Leccius De Ridder Fruitexploitatiemij. B",
    "wof:placetype":"venue"
},
  "geometry": {"coordinates":[5.550958,51.912228],"type":"Point"}
}