{
  "type": "Feature",
  "properties": {
    "addr:full":"Bukkumweg 3 Hilvarenbeek Noord-Brabant 5081 CT",
    "addr:housenumber":"3",
    "addr:postcode":"5081 ct",
    "addr:street":"Bukkumweg",
    "iso:country":"NL",
    "sg:address":"Bukkumweg 3",
    "sg:city":"Hilvarenbeek",
    "sg:orig_category":"Diverse Bedrijfsinstallaties Gh",
    "sg:phone":"+31 13 505 1763",
    "sg:postcode":"5081 CT",
    "sg:province":"Noord-Brabant",
    "wof:name":"Henri Dudar",
    "wof:placetype":"venue"
},
  "geometry": {"coordinates":[5.143343,51.486637],"type":"Point"}
}