{
  "type": "Feature",
  "properties": {
    "iso:country":"NL",
    "sg:address":"J Verfaillewg 20A",
    "sg:city":"Den Helder",
    "sg:orig_category":"Bloemen En Planten",
    "sg:phone":"+31 223 613 857",
    "sg:postcode":"1783 BB",
    "sg:province":"North Holland",
    "wof:name":"Witte Huis, Het",
    "wof:placetype":"venue"
},
  "geometry": {"coordinates":[4.742456,52.950199],"type":"Point"}
}