{
  "type": "Feature",
  "properties": {
    "addr:full":"Hoefstraat 26 Macharen North Brabant 5367 AP",
    "addr:housenumber":"26",
    "addr:postcode":"5367 ap",
    "addr:street":"Hoefstraat",
    "iso:country":"NL",
    "sg:address":"Hoefstraat 26",
    "sg:city":"Macharen",
    "sg:orig_category":"Partycatering And -Organisatie",
    "sg:phone":"+31 412 492 540",
    "sg:postcode":"5367 AP",
    "sg:province":"North Brabant",
    "wof:name":"Donkers Catering",
    "wof:placetype":"venue"
},
  "geometry": {"coordinates":[5.546843,51.804089],"type":"Point"}
}