{
  "type": "Feature",
  "properties": {
    "addr:full":"Hoofdstr 95 Grootegast Groningen 9861 AC",
    "addr:housenumber":"95",
    "addr:postcode":"9861 ac",
    "addr:street":"Hoofdstr",
    "iso:country":"NL",
    "sg:address":"Hoofdstr 95",
    "sg:city":"Grootegast",
    "sg:orig_category":"Verzekeringen - Verzekeringskantoren",
    "sg:phone":"+31 594 612 345",
    "sg:postcode":"9861 AC",
    "sg:province":"Groningen",
    "wof:name":"Univ\u00e9 Westerkwartier",
    "wof:placetype":"venue"
},
  "geometry": {"coordinates":[6.278224,53.21376],"type":"Point"}
}