{
  "type": "Feature",
  "properties": {
    "addr:full":"Beeldsnydersdreef 201 Maastricht Limburg 6216 EA",
    "addr:housenumber":"201",
    "addr:postcode":"6216 ea",
    "iso:country":"NL",
    "sg:address":"Beeldsnydersdreef 201",
    "sg:city":"Maastricht",
    "sg:orig_category":"Peuterspeelzalen",
    "sg:phone":"+31 43 347 4310",
    "sg:postcode":"6216 EA",
    "sg:province":"Limburg",
    "wof:name":"Wesly, Emile",
    "wof:placetype":"venue"
},
  "geometry": {"coordinates":[5.668958,50.845116],"type":"Point"}
}