{
  "type": "Feature",
  "properties": {
    "addr:full":"Koningstraat 75 Beverwijk Noord-Holland 1941 BB",
    "addr:housenumber":"75",
    "addr:postcode":"1941 bb",
    "addr:street":"Koningstraat",
    "iso:country":"NL",
    "sg:address":"Koningstraat 75",
    "sg:city":"Beverwijk",
    "sg:orig_category":"Organisaties And Verenigingen",
    "sg:phone":"+31 251 224 084",
    "sg:postcode":"1941 BB",
    "sg:province":"Noord-Holland",
    "wof:name":"Kunstuitleen Sbk Ijmond Noord",
    "wof:placetype":"venue"
},
  "geometry": {"coordinates":[4.6566529274,52.4823036194],"type":"Point"}
}