{
  "type": "Feature",
  "properties": {
    "iso:country":"NL",
    "sg:address":"Eendrachtstr 6C",
    "sg:city":"Apeldoorn",
    "sg:orig_category":"Adviesbureaus Bedrijfsorganisatie",
    "sg:phone":"+31 55 540 2108",
    "sg:postcode":"7335 CH",
    "sg:province":"Gelderland",
    "sg:website":"http://www.stbma.nl",
    "wof:name":"Business Management Alliance",
    "wof:placetype":"venue"
},
  "geometry": {"coordinates":[5.958439,52.200356],"type":"Point"}
}