{
  "type": "Feature",
  "properties": {
    "iso:country":"NL",
    "sg:address":"Billitonstraat 45",
    "sg:city":"Dordrecht",
    "sg:orig_category":"Huishoudapparatuur, Televisies And Radio'S",
    "sg:phone":"+31 78 618 2690",
    "sg:postcode":"3312 SB",
    "sg:province":"Zuid-Holland",
    "wof:name":"F.A. Van Driel",
    "wof:placetype":"venue"
},
  "geometry": {"coordinates":[4.684984,51.809425],"type":"Point"}
}