{
  "type": "Feature",
  "properties": {
    "iso:country":"NL",
    "sg:address":"Koningin Wilhelminaplein 1",
    "sg:city":"Amsterdam",
    "sg:orig_category":"Handelsbemiddeling Textiel And Lederwaren",
    "sg:phone":"+31 20 617 0189",
    "sg:postcode":"1062 HG",
    "sg:province":"Noord-Holland",
    "wof:name":"Jos Bles Mode Bv",
    "wof:placetype":"venue"
},
  "geometry": {"coordinates":[4.840995,52.355759],"type":"Point"}
}