{
  "type": "Feature",
  "properties": {
    "addr:full":"Demer 44 Eindhoven Noord-Brabant 5611 AS",
    "addr:housenumber":"44",
    "addr:postcode":"5611 as",
    "addr:street":"Demer",
    "iso:country":"NL",
    "sg:address":"Demer 44",
    "sg:city":"Eindhoven",
    "sg:orig_category":"Kappers",
    "sg:phone":"+31 40 243 5073",
    "sg:postcode":"5611 AS",
    "sg:province":"Noord-Brabant",
    "wof:name":"Kapsalon Christiaan Brankaert",
    "wof:placetype":"venue"
},
  "geometry": {"coordinates":[5.4770669937,51.4396438599],"type":"Point"}
}