{
  "type": "Feature",
  "properties": {
    "addr:full":"Slobeend 5 Nieuw Lekkerland Zuid-Holland 2957 NG",
    "addr:housenumber":"5",
    "addr:postcode":"2957 ng",
    "addr:street":"Slobeend",
    "iso:country":"NL",
    "sg:address":"Slobeend 5",
    "sg:city":"Nieuw Lekkerland",
    "sg:orig_category":"Administratie- En Boekhoudkantoren",
    "sg:phone":"+31 184 682 054",
    "sg:postcode":"2957 NG",
    "sg:province":"Zuid-Holland",
    "wof:name":"Plaat, Chr Van Der",
    "wof:placetype":"venue"
},
  "geometry": {"coordinates":[4.67497,51.886974],"type":"Point"}
}