{
  "type": "Feature",
  "properties": {
    "iso:country":"NL",
    "sg:address":"Zebraspoor 69",
    "sg:city":"Maarssen",
    "sg:orig_category":"Administratie- En Boekhoudkantoren",
    "sg:phone":"+31 346 560 693",
    "sg:postcode":"3605 GD",
    "sg:province":"Utrecht",
    "wof:name":"Postmus Administratie",
    "wof:placetype":"venue"
},
  "geometry": {"coordinates":[5.019846,52.142651],"type":"Point"}
}