{
  "type": "Feature",
  "properties": {
    "addr:full":"Haagbeukln 26 Amstelveen Noord-Holland 1185 KL",
    "addr:housenumber":"26",
    "addr:postcode":"1185 kl",
    "addr:street":"Haagbeukln",
    "iso:country":"NL",
    "sg:address":"Haagbeukln 26",
    "sg:city":"Amstelveen",
    "sg:orig_category":"Beeldende Kunstenaars",
    "sg:phone":"+31 20 641 1892",
    "sg:postcode":"1185 KL",
    "sg:province":"Noord-Holland",
    "wof:name":"Gerritse, K",
    "wof:placetype":"venue"
},
  "geometry": {"coordinates":[4.849605,52.29393],"type":"Point"}
}