{
  "type": "Feature",
  "properties": {
    "iso:country":"NL",
    "sg:address":"St Servaaskloost 38",
    "sg:city":"Maastricht",
    "sg:orig_category":"Kunsthandel",
    "sg:phone":"+31 43 325 4383",
    "sg:postcode":"6211 TE",
    "sg:province":"Limburg",
    "wof:name":"Blauwe Olifant, De",
    "wof:placetype":"venue"
},
  "geometry": {"coordinates":[5.687392,50.847183],"type":"Point"}
}