{
  "type": "Feature",
  "properties": {
    "addr:full":"D Twee Gebroeders 134A Drachten Provincie Friesland 9207 CJ",
    "addr:housenumber":"134a",
    "addr:postcode":"9207 cj",
    "addr:street":"Twee Gebroeders;Provincie Friesland",
    "iso:country":"NL",
    "sg:address":"D Twee Gebroeders 134A",
    "sg:city":"Drachten",
    "sg:orig_category":"Verenigingen En Stichtingen",
    "sg:phone":"+31 512 516 867",
    "sg:postcode":"9207 CJ",
    "sg:province":"Provincie Friesland",
    "wof:name":"Trekharmonika Friesland",
    "wof:placetype":"venue"
},
  "geometry": {"coordinates":[6.081789,53.116859],"type":"Point"}
}