{
  "type": "Feature",
  "properties": {
    "addr:full":"Willemsplein 16 Arnhem Gelderland 6811 KB",
    "addr:housenumber":"16",
    "addr:postcode":"6811 kb",
    "addr:street":"Willemsplein",
    "iso:country":"NL",
    "sg:address":"Willemsplein 16",
    "sg:city":"Arnhem",
    "sg:orig_category":"Werving And Selectie Van Tijdelijk Personeel And Uitzendkantoren",
    "sg:phone":"+31 26 442 6928",
    "sg:postcode":"6811 KB",
    "sg:province":"Gelderland",
    "wof:name":"Nederrijn Bv",
    "wof:placetype":"venue"
},
  "geometry": {"coordinates":[5.9034080505,51.9832649231],"type":"Point"}
}