{
  "type": "Feature",
  "properties": {
    "iso:country":"NL",
    "sg:address":"De Wip 5",
    "sg:city":"Hilvarenbeek",
    "sg:orig_category":"Medische And Orthopedische Artikelen",
    "sg:phone":"+31 13 505 3766",
    "sg:postcode":"5081 PV",
    "sg:province":"North Brabant",
    "wof:name":"Pedicure Otten-Van Sluysveld",
    "wof:placetype":"venue"
},
  "geometry": {"coordinates":[5.140275,51.490814],"type":"Point"}
}