{
  "type": "Feature",
  "properties": {
    "addr:full":"Wittemerweg 10 Eys Limburg 6287 AB",
    "addr:housenumber":"10",
    "addr:postcode":"6287 ab",
    "addr:street":"Wittemerweg",
    "iso:country":"NL",
    "sg:address":"Wittemerweg 10",
    "sg:city":"Eys",
    "sg:orig_category":"Diverse Consumentenartikelen Gh",
    "sg:phone":"+31 43 451 1666",
    "sg:postcode":"6287 AB",
    "sg:province":"Limburg",
    "wof:name":"Myth And Magic",
    "wof:placetype":"venue"
},
  "geometry": {"coordinates":[5.934232,50.824997],"type":"Point"}
}