{
  "type": "Feature",
  "properties": {
    "addr:full":"Linkensweg 31 Oss Virginia 5341 CA",
    "addr:housenumber":"31",
    "addr:postcode":"5341 ca",
    "addr:street":"Linkensweg",
    "iso:country":"NL",
    "sg:address":"Linkensweg 31",
    "sg:city":"Oss",
    "sg:orig_category":"Diverse Bedrijfsinstallaties Gh",
    "sg:phone":"+31 412 630 684",
    "sg:postcode":"5341 CA",
    "sg:province":"Virginia",
    "wof:name":"Verkoopcombinatie Van Hoogstraten",
    "wof:placetype":"venue"
},
  "geometry": {"coordinates":[-77.235214,38.312599],"type":"Point"}
}