{
  "type": "Feature",
  "properties": {
    "iso:country":"NL",
    "sg:address":"Dorpsstraat 91",
    "sg:city":"Oostknollendam",
    "sg:orig_category":"Pleziervaartuigen And Reparatie",
    "sg:phone":"+31 75 642 6332",
    "sg:postcode":"1534 NE",
    "sg:province":"Noord-Holland",
    "wof:name":"Scheepswerf Zwart",
    "wof:placetype":"venue"
},
  "geometry": {"coordinates":[4.790327,52.517746],"type":"Point"}
}