{
  "type": "Feature",
  "properties": {
    "addr:full":"Kromsteeg 3 Kerkdriel Gelderland 5331 AH",
    "addr:housenumber":"3",
    "addr:postcode":"5331 ah",
    "addr:street":"Kromsteeg;Gelderland",
    "iso:country":"NL",
    "sg:address":"Kromsteeg 3",
    "sg:city":"Kerkdriel",
    "sg:classifiers":[
        {
            "category":"Fast Food",
            "type":"Food & Drink"
        }
    ],
    "sg:phone":"+31 418 631 454",
    "sg:postcode":"5331 AH",
    "sg:province":"Gelderland",
    "sg:tags":[
        "afhaal",
        "restaurant"
    ],
    "wof:name":"New City",
    "wof:placetype":"venue"
},
  "geometry": {"coordinates":[5.3341,51.773239],"type":"Point"}
}