{
  "type": "Feature",
  "properties": {
    "addr:full":"Rozenstr 13 Poeldyk Zuid-Holland 2685 XS",
    "addr:housenumber":"13",
    "addr:postcode":"2685 xs",
    "addr:street":"Rozenstr",
    "iso:country":"NL",
    "sg:address":"Rozenstr 13",
    "sg:city":"Poeldyk",
    "sg:orig_category":"Onderhoudswerken",
    "sg:phone":"+31 174 240 625",
    "sg:postcode":"2685 XS",
    "sg:province":"Zuid-Holland",
    "wof:name":"Tamerus, A",
    "wof:placetype":"venue"
},
  "geometry": {"coordinates":[4.218561,52.024471],"type":"Point"}
}