{
  "type": "Feature",
  "properties": {
    "addr:full":"Ptr Willemsplnts 1B Meyel Limburg 5768 CK",
    "addr:housenumber":"1b",
    "addr:postcode":"5768 ck",
    "addr:street":"Willemsplnts",
    "iso:country":"NL",
    "sg:address":"Ptr Willemsplnts 1B",
    "sg:city":"Meyel",
    "sg:orig_category":"Verhuur",
    "sg:phone":"+31 77 466 3963",
    "sg:postcode":"5768 CK",
    "sg:province":"Limburg",
    "wof:name":"Rene Teeuwen, Frituurwagenverhuur",
    "wof:placetype":"venue"
},
  "geometry": {"coordinates":[5.885759,51.344288],"type":"Point"}
}