{
  "type": "Feature",
  "properties": {
    "iso:country":"NL",
    "sg:address":"Oude Zwolseweg 127",
    "sg:city":"Wenum Wiesel",
    "sg:orig_category":"Zuivelproducten",
    "sg:phone":"+31 55 312 1695",
    "sg:postcode":"7345 BE",
    "sg:province":"Gelderland",
    "wof:name":"Zuivelhandel Henk Gerritsen",
    "wof:placetype":"venue"
},
  "geometry": {"coordinates":[5.962247,52.251682],"type":"Point"}
}