{
  "type": "Feature",
  "properties": {
    "addr:full":"World Trade Center, Amsterdam Airport, Tower B, 10Th Fl. Schiphol Blvd. 217 1118 Noord-Holland BH A MS",
    "addr:housenumber":"217",
    "addr:postcode":"1118",
    "addr:street":"10Th Fl. Schiphol Blvd.;A",
    "iso:country":"NL",
    "sg:address":"World Trade Center, Amsterdam Airport, Tower B, 10Th Fl. Schiphol Blvd. 217",
    "sg:city":"1118",
    "sg:classifiers":[
        {
            "category":"Industrial Area",
            "type":"Public Place"
        }
    ],
    "sg:phone":"+31 3120460429",
    "sg:postcode":"BH A MS",
    "sg:province":"Noord-Holland",
    "sg:tags":[
        "large",
        "private"
    ],
    "sg:website":"www.cnh.com",
    "wof:name":"Cnh Global N.V.",
    "wof:placetype":"venue"
},
  "geometry": {"coordinates":[4.753868,52.306507],"type":"Point"}
}