{
  "type": "Feature",
  "properties": {
    "addr:full":"Kaaistraat 27 Steenbergen Nb North Brabant 4651 BL",
    "addr:housenumber":"27;nb",
    "addr:postcode":"4651 bl",
    "addr:street":"Kaaistraat",
    "iso:country":"NL",
    "sg:address":"Kaaistraat 27",
    "sg:city":"Steenbergen Nb",
    "sg:orig_category":"Wasserettes And Stomerijen",
    "sg:phone":"+31 167 565 044",
    "sg:postcode":"4651 BL",
    "sg:province":"North Brabant",
    "wof:name":"Van Alphen Stomerij",
    "wof:placetype":"venue"
},
  "geometry": {"coordinates":[4.3163480759,51.5865364075],"type":"Point"}
}