{
  "type": "Feature",
  "properties": {
    "addr:full":"F Bolstr 12 Alkmaar North Holland 1816 CV",
    "addr:housenumber":"12",
    "addr:postcode":"1816 cv",
    "iso:country":"NL",
    "sg:address":"F Bolstr 12",
    "sg:city":"Alkmaar",
    "sg:orig_category":"Onderhoudswerken",
    "sg:phone":"+31 72 512 1466",
    "sg:postcode":"1816 CV",
    "sg:province":"North Holland",
    "wof:name":"Verbeem, M W M",
    "wof:placetype":"venue"
},
  "geometry": {"coordinates":[4.746258,52.634361],"type":"Point"}
}