{
  "type": "Feature",
  "properties": {
    "addr:full":"Winterhaarweg 177 Enschede NL.08 7547 PT",
    "addr:housenumber":"177",
    "addr:postcode":"7547",
    "addr:street":"Winterhaarweg;Pt",
    "iso:country":"NL",
    "sg:address":"Winterhaarweg 177",
    "sg:city":"Enschede",
    "sg:orig_category":"Glaszetten",
    "sg:phone":"+31 53 428 2124",
    "sg:postcode":"7547 PT",
    "sg:province":"NL.08",
    "wof:name":"All Glas Veldman",
    "wof:placetype":"venue"
},
  "geometry": {"coordinates":[6.810101,52.210247],"type":"Point"}
}