{
  "type": "Feature",
  "properties": {
    "addr:full":"Postbus 317 Hengelo Ov NL.08 7550 AH",
    "addr:housenumber":"317",
    "addr:postcode":"7550 ah",
    "addr:street":"Postbus;Ov",
    "iso:country":"NL",
    "sg:address":"Postbus 317",
    "sg:city":"Hengelo Ov",
    "sg:orig_category":"Beeldende Kunstenaars",
    "sg:phone":"+31 74 291 8443",
    "sg:postcode":"7550 AH",
    "sg:province":"NL.08",
    "wof:name":"Ateliers 93",
    "wof:placetype":"venue"
},
  "geometry": {"coordinates":[6.78971,52.266331],"type":"Point"}
}