{
  "type": "Feature",
  "properties": {
    "addr:full":"Pluto 45 Den Helder North Holland 1785 AP",
    "addr:housenumber":"45",
    "addr:postcode":"1785 ap",
    "addr:street":"Pluto",
    "iso:country":"NL",
    "sg:address":"Pluto 45",
    "sg:city":"Den Helder",
    "sg:classifiers":[
        {
            "category":"Retail",
            "subcategory":"Storage",
            "type":"Services"
        }
    ],
    "sg:phone":"+31 223 668 956",
    "sg:postcode":"1785 AP",
    "sg:province":"North Holland",
    "sg:tags":[
        "op-",
        "en",
        "overslagbedrijven"
    ],
    "wof:name":"Kooiman",
    "wof:placetype":"venue"
},
  "geometry": {"coordinates":[4.776077,52.946301],"type":"Point"}
}