{
  "type": "Feature",
  "properties": {
    "addr:full":"Postbus 41 Teteringen Noord-Brabant 4847 ZG",
    "addr:housenumber":"41",
    "addr:postcode":"4847 zg",
    "addr:street":"Postbus",
    "iso:country":"NL",
    "sg:address":"Postbus 41",
    "sg:city":"Teteringen",
    "sg:orig_category":"Luchtverontreinigings- Bestrijding",
    "sg:phone":"+31 76 581 0076",
    "sg:postcode":"4847 ZG",
    "sg:province":"Noord-Brabant",
    "wof:name":"Vision Engineers",
    "wof:placetype":"venue"
},
  "geometry": {"coordinates":[4.814294,51.610271],"type":"Point"}
}