{
  "type": "Feature",
  "properties": {
    "addr:full":"Vecht 4 Rotterdam Zuid-Holland 3068 TX",
    "addr:housenumber":"4",
    "addr:postcode":"3068 tx",
    "addr:street":"Vecht",
    "iso:country":"NL",
    "sg:address":"Vecht 4",
    "sg:city":"Rotterdam",
    "sg:orig_category":"Onderhoudswerken",
    "sg:phone":"+31 10 456 2490",
    "sg:postcode":"3068 TX",
    "sg:province":"Zuid-Holland",
    "wof:name":"Roco",
    "wof:placetype":"venue"
},
  "geometry": {"coordinates":[4.564712,51.96035],"type":"Point"}
}