{
  "type": "Feature",
  "properties": {
    "iso:country":"NL",
    "sg:address":"Ribbelthorst 15",
    "sg:city":"Enschede",
    "sg:classifiers":[
        {
            "category":"Professional",
            "subcategory":"Accounting & Tax Preparation",
            "type":"Services"
        }
    ],
    "sg:phone":"+31 53 433 0193",
    "sg:postcode":"7531 GA",
    "sg:province":"Overijssel",
    "sg:tags":[
        "accountant"
    ],
    "wof:name":"Administratiebureau Lunter",
    "wof:placetype":"venue"
},
  "geometry": {"coordinates":[6.923419,52.22583],"type":"Point"}
}