{
  "type": "Feature",
  "properties": {
    "iso:country":"NL",
    "sg:address":"Herman Heijermanshove 29",
    "sg:city":"Nieuwegein",
    "sg:orig_category":"Loodgieterswerk, Verwarming And Sanitaire Installaties",
    "sg:phone":"+31 30 602 1701",
    "sg:postcode":"3438 HA",
    "sg:province":"Utrecht",
    "wof:name":"Klus En Montagebedrijf Bert Peek",
    "wof:placetype":"venue"
},
  "geometry": {"coordinates":[5.087216,52.053017],"type":"Point"}
}