{
  "type": "Feature",
  "properties": {
    "addr:full":"Lysterwg 41 Hengelo Ov NL.08 7557 PL",
    "addr:housenumber":"41",
    "addr:postcode":"7557 pl",
    "addr:street":"Lysterwg;Ov",
    "iso:country":"NL",
    "sg:address":"Lysterwg 41",
    "sg:city":"Hengelo Ov",
    "sg:orig_category":"Beeldende Kunstenaars",
    "sg:phone":"+31 74 243 0527",
    "sg:postcode":"7557 PL",
    "sg:province":"NL.08",
    "wof:name":"Piekartz, R Van",
    "wof:placetype":"venue"
},
  "geometry": {"coordinates":[6.78971,52.266331],"type":"Point"}
}