{
  "type": "Feature",
  "properties": {
    "addr:full":"Bredasewg 496 Tilburg North Brabant 5036 NB",
    "addr:housenumber":"496",
    "addr:postcode":"5036 nb",
    "iso:country":"NL",
    "sg:address":"Bredasewg 496",
    "sg:city":"Tilburg",
    "sg:orig_category":"Melktransporten",
    "sg:phone":"+31 13 463 1316",
    "sg:postcode":"5036 NB",
    "sg:province":"North Brabant",
    "wof:name":"Vermeer, M G M",
    "wof:placetype":"venue"
},
  "geometry": {"coordinates":[5.031829,51.559399],"type":"Point"}
}