{
  "type": "Feature",
  "properties": {
    "addr:full":"Nyverheidswg 15 Zuidwolde Dr Drenthe 7921 JH",
    "addr:housenumber":"15",
    "addr:postcode":"7921 jh",
    "addr:street":"Nyverheidswg;Dr",
    "iso:country":"NL",
    "sg:address":"Nyverheidswg 15",
    "sg:city":"Zuidwolde Dr",
    "sg:orig_category":"Pluimveebedrijven En -Handelaren",
    "sg:phone":"+31 528 372 929",
    "sg:postcode":"7921 JH",
    "sg:province":"Drenthe",
    "wof:name":"Haanstra Bv",
    "wof:placetype":"venue"
},
  "geometry": {"coordinates":[6.42853,52.67675],"type":"Point"}
}