{
  "type": "Feature",
  "properties": {
    "iso:country":"NL",
    "sg:address":"Kathodeweg 3",
    "sg:city":"Hoorn Nh",
    "sg:orig_category":"Glaszetten",
    "sg:phone":"+31 229 247 234",
    "sg:postcode":"1627 LK",
    "sg:province":"North Holland",
    "wof:name":"Caresse Glas Design",
    "wof:placetype":"venue"
},
  "geometry": {"coordinates":[5.102277,52.637093],"type":"Point"}
}