{
  "type": "Feature",
  "properties": {
    "addr:full":"Valkenaarstr 63 Huizen North Holland 1271 TK",
    "addr:housenumber":"63",
    "addr:postcode":"1271 tk",
    "addr:street":"Valkenaarstr",
    "iso:country":"NL",
    "sg:address":"Valkenaarstr 63",
    "sg:city":"Huizen",
    "sg:orig_category":"Webdesign Bureaus",
    "sg:phone":"+31 35 525 3444",
    "sg:postcode":"1271 TK",
    "sg:province":"North Holland",
    "sg:website":"http://www.lorentdesign.nl",
    "wof:name":"Lorent, Peter",
    "wof:placetype":"venue"
},
  "geometry": {"coordinates":[5.2394971848,52.2988433838],"type":"Point"}
}