{
  "type": "Feature",
  "properties": {
    "addr:full":"Cantharel 1 Amersfoort Utrecht 3823 XE",
    "addr:housenumber":"1",
    "addr:postcode":"3823 xe",
    "addr:street":"Cantharel",
    "iso:country":"NL",
    "sg:address":"Cantharel 1",
    "sg:city":"Amersfoort",
    "sg:orig_category":"Beautyfarms And Sauna'S",
    "sg:phone":"+31 33 456 2176",
    "sg:postcode":"3823 XE",
    "sg:province":"Utrecht",
    "wof:name":"R.A. Schippers",
    "wof:placetype":"venue"
},
  "geometry": {"coordinates":[5.392894,52.185871],"type":"Point"}
}