{
  "type": "Feature",
  "properties": {
    "addr:full":"Dennenweg 166 Enschede Overijssel 7545 WL",
    "addr:housenumber":"166",
    "addr:postcode":"7545 wl",
    "addr:street":"Dennenweg",
    "iso:country":"NL",
    "sg:address":"Dennenweg 166",
    "sg:city":"Enschede",
    "sg:classifiers":[
        {
            "category":"Fast Food",
            "type":"Food & Drink"
        }
    ],
    "sg:phone":"+31 53 432 1200",
    "sg:postcode":"7545 WL",
    "sg:province":"Overijssel",
    "sg:tags":[
        "afhaal",
        "restaurant"
    ],
    "wof:name":"Cafetaria De Instuif",
    "wof:placetype":"venue"
},
  "geometry": {"coordinates":[6.872962,52.21381],"type":"Point"}
}