{
  "type": "Feature",
  "properties": {
    "addr:full":"Steenwg 55 Sittard Limburg 6131 BD",
    "addr:housenumber":"55",
    "addr:postcode":"6131 bd",
    "addr:street":"Steenwg",
    "iso:country":"NL",
    "sg:address":"Steenwg 55",
    "sg:city":"Sittard",
    "sg:orig_category":"Kinderkleding",
    "sg:phone":"+31 46 411 1032",
    "sg:postcode":"6131 BD",
    "sg:province":"Limburg",
    "wof:name":"Enano",
    "wof:placetype":"venue"
},
  "geometry": {"coordinates":[5.862553,51.00066],"type":"Point"}
}