{
  "type": "Feature",
  "properties": {
    "addr:full":"Botsestr 45E Kekerdom Gelderland 6579 JA",
    "addr:housenumber":"45e",
    "addr:postcode":"6579 ja",
    "addr:street":"Botsestr;Gelderland",
    "iso:country":"NL",
    "sg:address":"Botsestr 45E",
    "sg:city":"Kekerdom",
    "sg:orig_category":"Hek- En Rasterwerken",
    "sg:phone":"+31 481 432 161",
    "sg:postcode":"6579 JA",
    "sg:province":"Gelderland",
    "wof:name":"Meijs",
    "wof:placetype":"venue"
},
  "geometry": {"coordinates":[6.021267,51.864777],"type":"Point"}
}