{
  "type": "Feature",
  "properties": {
    "addr:full":"Tuyll V Serooskerkenpln 36 Amsterdam Noord-Holland 1076 NB",
    "addr:housenumber":"36",
    "addr:postcode":"1076 nb",
    "addr:street":"Serooskerkenpln",
    "iso:country":"NL",
    "sg:address":"Tuyll V Serooskerkenpln 36",
    "sg:city":"Amsterdam",
    "sg:orig_category":"Goederenvervoer Over De Weg",
    "sg:phone":"+31 20 664 8022",
    "sg:postcode":"1076 NB",
    "sg:province":"Noord-Holland",
    "wof:name":"Transportbedrijf Esmeijer",
    "wof:placetype":"venue"
},
  "geometry": {"coordinates":[4.85812,52.344231],"type":"Point"}
}