{
  "type": "Feature",
  "properties": {
    "iso:country":"NL",
    "sg:address":"Boompjes 55",
    "sg:city":"Rotterdam",
    "sg:orig_category":"Verenigingen En Stichtingen",
    "sg:phone":"+31 10 412 1960",
    "sg:postcode":"3011 XB",
    "sg:province":"Zuid-Holland",
    "wof:name":"Vut Tankstationbranche, Sticht",
    "wof:placetype":"venue"
},
  "geometry": {"coordinates":[4.48958,51.916317],"type":"Point"}
}