{
  "type": "Feature",
  "properties": {
    "addr:full":"Beltmolen 28 Mydrecht Utrecht 3642 CB",
    "addr:housenumber":"28;3642",
    "addr:postcode":"cb",
    "addr:street":"Beltmolen",
    "iso:country":"NL",
    "sg:address":"Beltmolen 28",
    "sg:city":"Mydrecht",
    "sg:orig_category":"Vertaalbureaus",
    "sg:phone":"+31 297 255 076",
    "sg:postcode":"3642 CB",
    "sg:province":"Utrecht",
    "wof:name":"Emerald Arr",
    "wof:placetype":"venue"
},
  "geometry": {"coordinates":[4.863153,52.198177],"type":"Point"}
}