{
  "type": "Feature",
  "properties": {
    "addr:full":"Reedk 101D Mynsheerenland South Holland 3271 LK",
    "addr:housenumber":"101d",
    "addr:postcode":"3271 lk",
    "addr:street":"Reedk",
    "iso:country":"NL",
    "sg:address":"Reedk 101D",
    "sg:city":"Mynsheerenland",
    "sg:orig_category":"Oldtimers",
    "sg:phone":"+31 186 605 560",
    "sg:postcode":"3271 LK",
    "sg:province":"South Holland",
    "wof:name":"Autorevisie Heinenoord",
    "wof:placetype":"venue"
},
  "geometry": {"coordinates":[4.48532,51.810555],"type":"Point"}
}