{
  "type": "Feature",
  "properties": {
    "iso:country":"NL",
    "sg:address":"Van Weedestraat 215",
    "sg:city":"Soest",
    "sg:orig_category":"Huishoudapparatuur, Televisies And Radio'S",
    "sg:phone":"+31 35 603 3038",
    "sg:postcode":"3761 CD",
    "sg:province":"Utrecht",
    "wof:name":"Modern Electronics",
    "wof:placetype":"venue"
},
  "geometry": {"coordinates":[5.294352,52.186497],"type":"Point"}
}