{
  "type": "Feature",
  "properties": {
    "addr:full":"Voorstad 59A Goes Zeeland 4461 KL",
    "addr:housenumber":"59a",
    "addr:postcode":"4461 kl",
    "addr:street":"Voorstad",
    "iso:country":"NL",
    "sg:address":"Voorstad 59A",
    "sg:city":"Goes",
    "sg:orig_category":"Lasbedrijven",
    "sg:phone":"+31 6 22685759",
    "sg:postcode":"4461 KL",
    "sg:province":"Zeeland",
    "wof:name":"Bel, Van Der",
    "wof:placetype":"venue"
},
  "geometry": {"coordinates":[-83.914169,39.768833],"type":"Point"}
}