{
  "type": "Feature",
  "properties": {
    "addr:full":"Geldersekd 112 Amsterdam North Holland 1012 BN",
    "addr:housenumber":"112",
    "addr:postcode":"1012 bn",
    "iso:country":"NL",
    "sg:address":"Geldersekd 112",
    "sg:city":"Amsterdam",
    "sg:orig_category":"Kappers",
    "sg:phone":"+31 20 625 6566",
    "sg:postcode":"1012 BN",
    "sg:province":"North Holland",
    "wof:name":"Langeweg, P",
    "wof:placetype":"venue"
},
  "geometry": {"coordinates":[4.893195,52.373119],"type":"Point"}
}