{
  "type": "Feature",
  "properties": {
    "addr:full":"Kattenburg 21 Druten Gelderland 6651 AL",
    "addr:housenumber":"21",
    "addr:postcode":"6651 al",
    "addr:street":"Kattenburg",
    "iso:country":"NL",
    "sg:address":"Kattenburg 21",
    "sg:city":"Druten",
    "sg:orig_category":"Kappers",
    "sg:phone":"+31 487 516 196",
    "sg:postcode":"6651 AL",
    "sg:province":"Gelderland",
    "wof:name":"Fa. Herenhaarmode La Vie",
    "wof:placetype":"venue"
},
  "geometry": {"coordinates":[5.6110649109,51.892074585],"type":"Point"}
}