{
  "type": "Feature",
  "properties": {
    "addr:full":"Jacob Barneveldstraat 22 Linschoten Utrecht 3461 GA",
    "addr:housenumber":"22",
    "addr:postcode":"3461 ga",
    "addr:street":"Jacob Barneveldstraat",
    "iso:country":"NL",
    "sg:address":"Jacob Barneveldstraat 22",
    "sg:city":"Linschoten",
    "sg:classifiers":[
        {
            "category":"Communications",
            "subcategory":"Television Station",
            "type":"Services"
        }
    ],
    "sg:phone":"+31 348 411 233",
    "sg:postcode":"3461 GA",
    "sg:province":"Utrecht",
    "sg:tags":[
        "video",
        "audio",
        "verhuur"
    ],
    "wof:name":"Forto Cajo",
    "wof:placetype":"venue"
},
  "geometry": {"coordinates":[4.916921,52.063381],"type":"Point"}
}