{
  "type": "Feature",
  "properties": {
    "addr:full":"Prinsengr 1009 Amsterdam Noord-Holland 1017 KN",
    "addr:housenumber":"1009",
    "addr:postcode":"1017 kn",
    "iso:country":"NL",
    "sg:address":"Prinsengr 1009",
    "sg:city":"Amsterdam",
    "sg:orig_category":"Verenigingen En Stichtingen",
    "sg:phone":"+31 20 420 5379",
    "sg:postcode":"1017 KN",
    "sg:province":"Noord-Holland",
    "wof:name":"Wig, Sticht",
    "wof:placetype":"venue"
},
  "geometry": {"coordinates":[4.894156,52.362137],"type":"Point"}
}