{
  "type": "Feature",
  "properties": {
    "addr:full":"Statenstr 9 Sas Van Gent Zeeland 4551 VV",
    "addr:housenumber":"9",
    "addr:postcode":"4551 vv",
    "addr:street":"Statenstr",
    "iso:country":"NL",
    "sg:address":"Statenstr 9",
    "sg:city":"Sas Van Gent",
    "sg:orig_category":"Voetbalverenigingen",
    "sg:phone":"+31 115 453 741",
    "sg:postcode":"4551 VV",
    "sg:province":"Zeeland",
    "wof:name":"Corn Boys",
    "wof:placetype":"venue"
},
  "geometry": {"coordinates":[3.789265,51.231991],"type":"Point"}
}