{
  "type": "Feature",
  "properties": {
    "iso:country":"NL",
    "sg:address":"Mathenesserln 370A",
    "sg:city":"Rotterdam",
    "sg:orig_category":"Adviesbureaus Bedrijfsorganisatie",
    "sg:phone":"+31 10 244 0299",
    "sg:postcode":"3023 HB",
    "sg:province":"Zuid-Holland",
    "wof:name":"Meurisse",
    "wof:placetype":"venue"
},
  "geometry": {"coordinates":[4.452136,51.913315],"type":"Point"}
}