{
  "type": "Feature",
  "properties": {
    "addr:full":"Breestraat 1 Delft Zuid-Holland 2611 CB",
    "addr:housenumber":"1",
    "addr:postcode":"2611 cb",
    "addr:street":"Breestraat",
    "iso:country":"NL",
    "sg:address":"Breestraat 1",
    "sg:city":"Delft",
    "sg:classifiers":[
        {
            "category":"Travel",
            "subcategory":"Hotels & Motels",
            "type":"Entertainment"
        }
    ],
    "sg:phone":"+31 15 215 7133",
    "sg:postcode":"2611 CB",
    "sg:province":"Zuid-Holland",
    "wof:name":"Hotel Les Compagnons Grand Canal",
    "wof:placetype":"venue"
},
  "geometry": {"coordinates":[4.359463,52.007591],"type":"Point"}
}