{
  "type": "Feature",
  "properties": {
    "addr:full":"Penitentenstr 9E Weert Limburg 6001 VX",
    "addr:housenumber":"9e",
    "addr:postcode":"6001 vx",
    "addr:street":"Penitentenstr",
    "iso:country":"NL",
    "sg:address":"Penitentenstr 9E",
    "sg:city":"Weert",
    "sg:orig_category":"Grafische Materialen",
    "sg:phone":"+31 495 550 409",
    "sg:postcode":"6001 VX",
    "sg:province":"Limburg",
    "sg:website":"http://www.vegra.de",
    "wof:name":"Vegra Benelux Bv",
    "wof:placetype":"venue"
},
  "geometry": {"coordinates":[5.698237,51.255108],"type":"Point"}
}