{
  "type": "Feature",
  "properties": {
    "addr:full":"Amsteldk N 82 Uithoorn Noord-Holland 1422 XX",
    "addr:housenumber":"82",
    "addr:postcode":"1422 xx",
    "addr:street":"N",
    "iso:country":"NL",
    "sg:address":"Amsteldk N 82",
    "sg:city":"Uithoorn",
    "sg:orig_category":"Onderhoudswerken",
    "sg:phone":"+31 297 532 461",
    "sg:postcode":"1422 XX",
    "sg:province":"Noord-Holland",
    "wof:name":"Chuckie",
    "wof:placetype":"venue"
},
  "geometry": {"coordinates":[4.849022,52.239925],"type":"Point"}
}