{
  "type": "Feature",
  "properties": {
    "addr:full":"Het Laar 5A Maarheeze Noord-Brabant 6026 RX",
    "addr:housenumber":"5a",
    "addr:postcode":"6026 rx",
    "addr:street":"Het Laar",
    "iso:country":"NL",
    "sg:address":"Het Laar 5A",
    "sg:city":"Maarheeze",
    "sg:orig_category":"Pluimveehouderijen",
    "sg:phone":"+31 495 594 232",
    "sg:postcode":"6026 RX",
    "sg:province":"Noord-Brabant",
    "wof:name":"H.G.M. Timmermans",
    "wof:placetype":"venue"
},
  "geometry": {"coordinates":[5.613336,51.301586],"type":"Point"}
}