{
  "type": "Feature",
  "properties": {
    "addr:full":"Waardstr 107 Leiden Zuid-Holland 2315 SB",
    "addr:housenumber":"107",
    "addr:postcode":"2315 sb",
    "iso:country":"NL",
    "sg:address":"Waardstr 107",
    "sg:city":"Leiden",
    "sg:orig_category":"Houtgroothandel",
    "sg:phone":"+31 71 522 6151",
    "sg:postcode":"2315 SB",
    "sg:province":"Zuid-Holland",
    "wof:name":"Jongeneel Leiden Bv",
    "wof:placetype":"venue"
},
  "geometry": {"coordinates":[4.50767,52.15984],"type":"Point"}
}