{
  "type": "Feature",
  "properties": {
    "addr:full":"Grotestr 99 Venray Limburg 5801 BE",
    "addr:housenumber":"99",
    "addr:postcode":"5801",
    "addr:street":"Grotestr",
    "iso:country":"NL",
    "sg:address":"Grotestr 99",
    "sg:city":"Venray",
    "sg:orig_category":"Warenhuizen",
    "sg:phone":"+31 900 9800",
    "sg:postcode":"5801 BE",
    "sg:province":"Limburg",
    "wof:name":"Kijkshop",
    "wof:placetype":"venue"
},
  "geometry": {"coordinates":[5.9756698608,51.5247993469],"type":"Point"}
}