{
  "type": "Feature",
  "properties": {
    "addr:full":"Westerwerf 28 Uitgeest Noord-Holland 1911 JA",
    "addr:housenumber":"28",
    "addr:postcode":"1911 ja",
    "addr:street":"Westerwerf",
    "iso:country":"NL",
    "sg:address":"Westerwerf 28",
    "sg:city":"Uitgeest",
    "sg:orig_category":"Mode Artikelen Dames En Heren - Fabrieken En Groothandel",
    "sg:phone":"+31 251 316 238",
    "sg:postcode":"1911 JA",
    "sg:province":"Noord-Holland",
    "sg:website":"http://www.sunsetint.nl",
    "wof:name":"Sunset Int Bv",
    "wof:placetype":"venue"
},
  "geometry": {"coordinates":[4.718609,52.538101],"type":"Point"}
}