{
  "type": "Feature",
  "properties": {
    "addr:full":"Wallenburg 47 Zeist Utrecht 3707 AP",
    "addr:housenumber":"47",
    "addr:postcode":"3707 ap",
    "addr:street":"Wallenburg",
    "iso:country":"NL",
    "sg:address":"Wallenburg 47",
    "sg:city":"Zeist",
    "sg:orig_category":"Bloemen And Planten",
    "sg:phone":"+31 30 691 9847",
    "sg:postcode":"3707 AP",
    "sg:province":"Utrecht",
    "wof:name":"Briljant Boeket",
    "wof:placetype":"venue"
},
  "geometry": {"coordinates":[5.257633,52.102573],"type":"Point"}
}