{
  "type": "Feature",
  "properties": {
    "iso:country":"NL",
    "sg:address":"Arkwg 34",
    "sg:city":"Mierlo",
    "sg:classifiers":[
        {
            "category":"Sports & Exercise",
            "subcategory":"Stables",
            "type":"Entertainment"
        }
    ],
    "sg:phone":"+31 492 660 880",
    "sg:postcode":"5731 PD",
    "sg:province":"North Brabant",
    "sg:tags":[
        "maneges"
    ],
    "sg:website":"http://www.denieuweark.nl",
    "wof:name":"Nieuwe Ark, Manege De",
    "wof:placetype":"venue"
},
  "geometry": {"coordinates":[5.631039,51.451672],"type":"Point"}
}