{
  "type": "Feature",
  "properties": {
    "addr:full":"De Brinken 43 Veenendaal Utrecht 3901 KV",
    "addr:housenumber":"43",
    "addr:postcode":"3901 kv",
    "addr:street":"De Brinken",
    "iso:country":"NL",
    "sg:address":"De Brinken 43",
    "sg:city":"Veenendaal",
    "sg:orig_category":"Administratie- En Boekhoudkantoren",
    "sg:phone":"+31 318 550 779",
    "sg:postcode":"3901 KV",
    "sg:province":"Utrecht",
    "wof:name":"Ardonne, J",
    "wof:placetype":"venue"
},
  "geometry": {"coordinates":[5.560608,52.018814],"type":"Point"}
}