{
  "type": "Feature",
  "properties": {
    "addr:full":"Duitslandstr 11 Ysselstein Ut Utrecht 3402 TJ",
    "addr:housenumber":"11",
    "addr:postcode":"3402 tj",
    "addr:street":"Duitslandstr",
    "iso:country":"NL",
    "sg:address":"Duitslandstr 11",
    "sg:city":"Ysselstein Ut",
    "sg:orig_category":"Scholen Voor Basisonderwijs",
    "sg:phone":"+31 30 688 2725",
    "sg:postcode":"3402 TJ",
    "sg:province":"Utrecht",
    "wof:name":"Paulussch Rk",
    "wof:placetype":"venue"
},
  "geometry": {"coordinates":[5.055547,52.022717],"type":"Point"}
}