{
  "type": "Feature",
  "properties": {
    "addr:full":"De Mossel 2 Noord Scharwoude Noord-Holland 1723 HZ",
    "addr:housenumber":"2",
    "addr:postcode":"1723 hz",
    "addr:street":"De Mossel",
    "iso:country":"NL",
    "sg:address":"De Mossel 2",
    "sg:city":"Noord Scharwoude",
    "sg:orig_category":"Koel- En Vrieshuizen",
    "sg:phone":"+31 226 314 260",
    "sg:postcode":"1723 HZ",
    "sg:province":"Noord-Holland",
    "wof:name":"Veldboer Bv, J",
    "wof:placetype":"venue"
},
  "geometry": {"coordinates":[4.80945,52.705383],"type":"Point"}
}