{
  "type": "Feature",
  "properties": {
    "iso:country":"NL",
    "sg:address":"R Ketellapperstr 29",
    "sg:city":"Zandvoort",
    "sg:orig_category":"Autoschade- Herstelbedrijven",
    "sg:phone":"+31 23 573 5800",
    "sg:postcode":"2041 EL",
    "sg:province":"Noord-Holland",
    "wof:name":"Car Wizard",
    "wof:placetype":"venue"
},
  "geometry": {"coordinates":[4.53431,52.376953],"type":"Point"}
}