{
  "type": "Feature",
  "properties": {
    "addr:full":"R Ketellapperstr 29 Zandvoort Noord-Holland 2041 EL",
    "addr:housenumber":"29;2041",
    "addr:postcode":"el",
    "addr:street":"Zandvoort",
    "iso:country":"NL",
    "sg:address":"R Ketellapperstr 29",
    "sg:city":"Zandvoort",
    "sg:orig_category":"Autoschade- Herstelbedrijven",
    "sg:phone":"+31 23 573 5800",
    "sg:postcode":"2041 EL",
    "sg:province":"Noord-Holland",
    "wof:name":"Car Wizard",
    "wof:placetype":"venue"
},
  "geometry": {"coordinates":[4.53431,52.376953],"type":"Point"}
}