{
  "type": "Feature",
  "properties": {
    "addr:full":"Oude Kleiwg 87 Rotterdam South Holland 3043 LE",
    "addr:housenumber":"87",
    "addr:postcode":"3043 le",
    "addr:street":"Oude Kleiwg",
    "iso:country":"NL",
    "sg:address":"Oude Kleiwg 87",
    "sg:city":"Rotterdam",
    "sg:orig_category":"Verloskundigen",
    "sg:phone":"+31 10 465 7733",
    "sg:postcode":"3043 LE",
    "sg:province":"South Holland",
    "wof:name":"Maal, E I Vd",
    "wof:placetype":"venue"
},
  "geometry": {"coordinates":[4.444594,51.937912],"type":"Point"}
}