{
  "type": "Feature",
  "properties": {
    "addr:full":"Beekstr 43 Weert Limburg 6001 GG",
    "addr:housenumber":"43",
    "addr:postcode":"6001 gg",
    "addr:street":"Beekstr",
    "iso:country":"NL",
    "sg:address":"Beekstr 43",
    "sg:city":"Weert",
    "sg:orig_category":"Verlichting",
    "sg:phone":"+31 495 524 190",
    "sg:postcode":"6001 GG",
    "sg:province":"Limburg",
    "wof:name":"Louw Van Der Zanden, De",
    "wof:placetype":"venue"
},
  "geometry": {"coordinates":[5.705546,51.255562],"type":"Point"}
}