{
  "type": "Feature",
  "properties": {
    "iso:country":"NL",
    "sg:address":"Zwolsewg 148",
    "sg:city":"Balkbrug",
    "sg:orig_category":"Bloemen En Planten",
    "sg:phone":"+31 523 656 861",
    "sg:postcode":"7707 AM",
    "sg:province":"Overijssel",
    "wof:name":"Brinkman",
    "wof:placetype":"venue"
},
  "geometry": {"coordinates":[6.358936,52.596684],"type":"Point"}
}