{
  "type": "Feature",
  "properties": {
    "addr:full":"Tiendwg 41 Leerdam Zuid-Holland 4142 EH",
    "addr:housenumber":"41",
    "addr:postcode":"4142 eh",
    "addr:street":"Tiendwg",
    "iso:country":"NL",
    "sg:address":"Tiendwg 41",
    "sg:city":"Leerdam",
    "sg:orig_category":"Behangselpapier En Wandbekleding",
    "sg:phone":"+31 345 632 266",
    "sg:postcode":"4142 EH",
    "sg:province":"Zuid-Holland",
    "sg:website":"http://www.decohome.nl",
    "wof:name":"Deco Home",
    "wof:placetype":"venue"
},
  "geometry": {"coordinates":[5.081939,51.88776],"type":"Point"}
}