{
  "type": "Feature",
  "properties": {
    "addr:full":"Abbestederwg 22B Callantsoog North Holland 1759 NB",
    "addr:housenumber":"22b",
    "addr:postcode":"1759 nb",
    "addr:street":"Abbestederwg",
    "iso:country":"NL",
    "sg:address":"Abbestederwg 22B",
    "sg:city":"Callantsoog",
    "sg:orig_category":"Voetbalverenigingen",
    "sg:phone":"+31 224 582 149",
    "sg:postcode":"1759 NB",
    "sg:province":"North Holland",
    "wof:name":"Callantsoog",
    "wof:placetype":"venue"
},
  "geometry": {"coordinates":[4.698269,52.840931],"type":"Point"}
}