{
  "type": "Feature",
  "properties": {
    "iso:country":"NL",
    "sg:address":"Louwersplein 41",
    "sg:city":"Hendrik Ido Ambacht",
    "sg:orig_category":"Kappers",
    "sg:phone":"+31 78 682 1811",
    "sg:postcode":"3343 RC",
    "sg:province":"Zuid-Holland",
    "wof:name":"Monroe",
    "wof:placetype":"venue"
},
  "geometry": {"coordinates":[4.63611,51.838341],"type":"Point"}
}