{
  "type": "Feature",
  "properties": {
    "addr:full":"Schoolstraat 27 'S Hertogenbosch Noord-Brabant 5221 AB",
    "addr:housenumber":"27",
    "addr:postcode":"5221 ab",
    "addr:street":"Schoolstraat;' S",
    "iso:country":"NL",
    "sg:address":"Schoolstraat 27",
    "sg:city":"'S Hertogenbosch",
    "sg:orig_category":"Juridische Dienstverlening",
    "sg:phone":"+31 73 631 1390",
    "sg:postcode":"5221 AB",
    "sg:province":"Noord-Brabant",
    "wof:name":"Arie J. Van Buytene",
    "wof:placetype":"venue"
},
  "geometry": {"coordinates":[5.269372,51.721725],"type":"Point"}
}