{
  "type": "Feature",
  "properties": {
    "addr:full":"Rozemaryn 59 Dronten Flevoland 8252 CV",
    "addr:housenumber":"59",
    "addr:postcode":"8252 cv",
    "addr:street":"Rozemaryn;Flevoland",
    "iso:country":"NL",
    "sg:address":"Rozemaryn 59",
    "sg:city":"Dronten",
    "sg:orig_category":"Adviesbureaus Bedrijfsorganisatie",
    "sg:phone":"+31 321 334 168",
    "sg:postcode":"8252 CV",
    "sg:province":"Flevoland",
    "sg:website":"http://www.provisionairs.nl",
    "wof:name":"Provisionairs",
    "wof:placetype":"venue"
},
  "geometry": {"coordinates":[5.72121,52.51062],"type":"Point"}
}