{
  "type": "Feature",
  "properties": {
    "addr:full":"Jellen 12 Sneek Provincie Friesland 8603 DK",
    "addr:housenumber":"12",
    "addr:postcode":"8603 dk",
    "addr:street":"Jellen;Provincie Friesland",
    "iso:country":"NL",
    "sg:address":"Jellen 12",
    "sg:city":"Sneek",
    "sg:orig_category":"Video - Faciliteiten En Producties",
    "sg:phone":"+31 515 423 576",
    "sg:postcode":"8603 DK",
    "sg:province":"Provincie Friesland",
    "wof:name":"Bok",
    "wof:placetype":"venue"
},
  "geometry": {"coordinates":[5.668884,53.042999],"type":"Point"}
}