{
  "type": "Feature",
  "properties": {
    "addr:full":"Violier 12 Haelen Limburg 6081 CD",
    "addr:housenumber":"12",
    "addr:postcode":"6081 cd",
    "addr:street":"Violier",
    "iso:country":"NL",
    "sg:address":"Violier 12",
    "sg:city":"Haelen",
    "sg:orig_category":"Grafisch Ontwerpers",
    "sg:phone":"+31 475 591 078",
    "sg:postcode":"6081 CD",
    "sg:province":"Limburg",
    "wof:name":"Idesign",
    "wof:placetype":"venue"
},
  "geometry": {"coordinates":[5.949389,51.233749],"type":"Point"}
}