{
  "type": "Feature",
  "properties": {
    "iso:country":"NL",
    "sg:address":"Harderwijkerweg 246",
    "sg:city":"Ermelo",
    "sg:orig_category":"Kampeerterreinen",
    "sg:phone":"+31 341 417 637",
    "sg:postcode":"3852 AL",
    "sg:province":"Gelderland",
    "wof:name":"Camping Klavertje Vier",
    "wof:placetype":"venue"
},
  "geometry": {"coordinates":[5.6214699745,52.3251037598],"type":"Point"}
}