{
  "type": "Feature",
  "properties": {
    "iso:country":"NL",
    "sg:address":"Vlietwg 58",
    "sg:city":"Leiden",
    "sg:classifiers":[
        {
            "category":"Retail",
            "subcategory":"Auto Repair",
            "type":"Services"
        }
    ],
    "sg:phone":"+31 71 576 7175",
    "sg:postcode":"2323 LE",
    "sg:province":"Zuid-Holland",
    "sg:tags":[
        "garage"
    ],
    "wof:name":"Lagerberg, C P",
    "wof:placetype":"venue"
},
  "geometry": {"coordinates":[4.481646,52.137779],"type":"Point"}
}