{
  "type": "Feature",
  "properties": {
    "addr:full":"Provincialeweg 33 Heiligerlee Groningen 9677 PA",
    "addr:housenumber":"33",
    "addr:postcode":"9677 pa",
    "addr:street":"Provincialeweg",
    "iso:country":"NL",
    "sg:address":"Provincialeweg 33",
    "sg:city":"Heiligerlee",
    "sg:classifiers":[
        {
            "category":"Education",
            "subcategory":"Preschool",
            "type":"Public Place"
        }
    ],
    "sg:phone":"+31 597 423 447",
    "sg:postcode":"9677 PA",
    "sg:province":"Groningen",
    "sg:tags":[
        "kleuteronderwijs",
        "basis-"
    ],
    "wof:name":"Christelijke Basisschool Mons Sinai",
    "wof:placetype":"venue"
},
  "geometry": {"coordinates":[7.005846,53.155769],"type":"Point"}
}