{
  "type": "Feature",
  "properties": {
    "addr:full":"Geermanstraat 48 Geesteren NL.08 7678 BK",
    "addr:housenumber":"48;nl.08",
    "addr:postcode":"7678 bk",
    "addr:street":"Geermanstraat",
    "iso:country":"NL",
    "sg:address":"Geermanstraat 48",
    "sg:city":"Geesteren",
    "sg:orig_category":"Wegen And Sportterreinen",
    "sg:phone":"+31 546 632 010",
    "sg:postcode":"7678 BK",
    "sg:province":"NL.08",
    "wof:name":"Minkjan Bestratingen",
    "wof:placetype":"venue"
},
  "geometry": {"coordinates":[6.7411761284,52.4233665466],"type":"Point"}
}