{
  "type": "Feature",
  "properties": {
    "addr:full":"Natriumweg 7 Amersfoort Utrecht 3812 PV",
    "addr:housenumber":"7",
    "addr:postcode":"3812 pv",
    "addr:street":"Natriumweg",
    "iso:country":"NL",
    "sg:address":"Natriumweg 7",
    "sg:city":"Amersfoort",
    "sg:orig_category":"Film-, Tv- And Videoproductie",
    "sg:phone":"+31 33 456 5888",
    "sg:postcode":"3812 PV",
    "sg:province":"Utrecht",
    "wof:name":"Video Productions At",
    "wof:placetype":"venue"
},
  "geometry": {"coordinates":[5.364291,52.167198],"type":"Point"}
}