{
  "type": "Feature",
  "properties": {
    "addr:full":"Raadhuisstraat 1 A3 Beilen Provincie Drenthe 9411 NA",
    "addr:housenumber":"1 a3",
    "addr:postcode":"9411 na",
    "addr:street":"Raadhuisstraat;Provincie Drenthe",
    "iso:country":"NL",
    "sg:address":"Raadhuisstraat 1 A3",
    "sg:city":"Beilen",
    "sg:orig_category":"Juweliers",
    "sg:phone":"+31 593 526 241",
    "sg:postcode":"9411 NA",
    "sg:province":"Provincie Drenthe",
    "wof:name":"Michal",
    "wof:placetype":"venue"
},
  "geometry": {"coordinates":[6.516025,52.857738],"type":"Point"}
}