{
  "type": "Feature",
  "properties": {
    "addr:full":"Drapeniersdonk 147 Apeldoorn Gelderland 7326 AH",
    "addr:housenumber":"147",
    "addr:postcode":"7326 ah",
    "addr:street":"Drapeniersdonk;Gelderland",
    "iso:country":"NL",
    "sg:address":"Drapeniersdonk 147",
    "sg:city":"Apeldoorn",
    "sg:orig_category":"Beeldende Kunstenaars",
    "sg:phone":"+31 55 541 1001",
    "sg:postcode":"7326 AH",
    "sg:province":"Gelderland",
    "wof:name":"Man In 'T Veld, P",
    "wof:placetype":"venue"
},
  "geometry": {"coordinates":[6.001261,52.204121],"type":"Point"}
}