{
  "type": "Feature",
  "properties": {
    "addr:full":"Bleijenburg 180 De Lier South Holland 2678 BD",
    "addr:housenumber":"180",
    "addr:postcode":"2678 bd",
    "addr:street":"Bleijenburg",
    "iso:country":"NL",
    "sg:address":"Bleijenburg 180",
    "sg:city":"De Lier",
    "sg:orig_category":"Verzekeringen",
    "sg:phone":"+31 174 513 315",
    "sg:postcode":"2678 BD",
    "sg:province":"South Holland",
    "wof:name":"Beishuizen Verzekeringen",
    "wof:placetype":"venue"
},
  "geometry": {"coordinates":[4.24951,51.978657],"type":"Point"}
}