{
  "type": "Feature",
  "properties": {
    "iso:country":"NL",
    "sg:address":"Bleijenburg 180",
    "sg:city":"De Lier",
    "sg:orig_category":"Verzekeringen",
    "sg:phone":"+31 174 513 315",
    "sg:postcode":"2678 BD",
    "sg:province":"South Holland",
    "wof:name":"Beishuizen Verzekeringen",
    "wof:placetype":"venue"
},
  "geometry": {"coordinates":[4.24951,51.978657],"type":"Point"}
}