{
  "type": "Feature",
  "properties": {
    "iso:country":"NL",
    "sg:address":"Utrechtseweg 8",
    "sg:city":"Renswoude",
    "sg:orig_category":"Kantoorartikelen",
    "sg:phone":"+31 318 571 906",
    "sg:postcode":"3927 AV",
    "sg:province":"Utrecht",
    "wof:name":"Handelsonderneming Van Tuijl",
    "wof:placetype":"venue"
},
  "geometry": {"coordinates":[5.5332608223,52.0754890442],"type":"Point"}
}