{
  "type": "Feature",
  "properties": {
    "addr:full":"Bisschopshoeve 31 Breda Noord-Brabant 4817 PR",
    "addr:housenumber":"31",
    "addr:postcode":"4817 pr",
    "addr:street":"Bisschopshoeve",
    "iso:country":"NL",
    "sg:address":"Bisschopshoeve 31",
    "sg:city":"Breda",
    "sg:orig_category":"Kappers",
    "sg:phone":"+31 76 587 4707",
    "sg:postcode":"4817 PR",
    "sg:province":"Noord-Brabant",
    "wof:name":"W. Drabbe-Hakkens",
    "wof:placetype":"venue"
},
  "geometry": {"coordinates":[4.823808,51.591087],"type":"Point"}
}