{
  "type": "Feature",
  "properties": {
    "addr:full":"Broekseln 1B Bergambacht South Holland 2861 GG",
    "addr:housenumber":"1b",
    "addr:postcode":"2861 gg",
    "addr:street":"Broekseln",
    "iso:country":"NL",
    "sg:address":"Broekseln 1B",
    "sg:city":"Bergambacht",
    "sg:orig_category":"Metselwerken",
    "sg:phone":"+31 182 353 522",
    "sg:postcode":"2861 GG",
    "sg:province":"South Holland",
    "wof:name":"Nobel Bv, B",
    "wof:placetype":"venue"
},
  "geometry": {"coordinates":[4.783119,51.936462],"type":"Point"}
}