{
  "type": "Feature",
  "properties": {
    "addr:full":"S. Abrahamsestraat 81 Meteren Gelderland 4194 RD",
    "addr:housenumber":"81",
    "addr:postcode":"4194",
    "addr:street":"S. Abrahamsestraat;Gelderland;Rd",
    "iso:country":"NL",
    "sg:address":"S. Abrahamsestraat 81",
    "sg:city":"Meteren",
    "sg:orig_category":"Goederenvervoer Over De Weg",
    "sg:phone":"+31 345 570 049",
    "sg:postcode":"4194 RD",
    "sg:province":"Gelderland",
    "wof:name":"Bouwens Transport",
    "wof:placetype":"venue"
},
  "geometry": {"coordinates":[5.284524,51.871567],"type":"Point"}
}