{
  "type": "Feature",
  "properties": {
    "iso:country":"NL",
    "sg:address":"J V Arkelstr 55",
    "sg:city":"Utrecht",
    "sg:orig_category":"Verenigingsgebouwen",
    "sg:phone":"+31 30 289 4469",
    "sg:postcode":"3523 VE",
    "sg:province":"Utrecht",
    "wof:name":"Wijkwinkel Hoograven",
    "wof:placetype":"venue"
},
  "geometry": {"coordinates":[5.12632,52.072041],"type":"Point"}
}