{
  "type": "Feature",
  "properties": {
    "addr:full":"Frans Halsstraat 162 'S Gravenhage South Holland 2525 XD",
    "addr:housenumber":"162 '",
    "addr:postcode":"2525 xd",
    "addr:street":"Frans Halsstraat",
    "iso:country":"NL",
    "sg:address":"Frans Halsstraat 162",
    "sg:city":"'S Gravenhage",
    "sg:orig_category":"Werving And Selectie Van Tijdelijk Personeel And Uitzendkantoren",
    "sg:phone":"+31 70 389 5219",
    "sg:postcode":"2525 XD",
    "sg:province":"South Holland",
    "wof:name":"Europa",
    "wof:placetype":"venue"
},
  "geometry": {"coordinates":[4.3086681366,52.0628890991],"type":"Point"}
}