{
  "type": "Feature",
  "properties": {
    "addr:full":"Catharynesngl 100 Utrecht Utrecht 3511 GV",
    "addr:housenumber":"100",
    "addr:postcode":"3511 gv",
    "iso:country":"NL",
    "sg:address":"Catharynesngl 100",
    "sg:city":"Utrecht",
    "sg:orig_category":"Makelaars En Adviseurs Onroerende Goederen",
    "sg:phone":"+31 30 231 5186",
    "sg:postcode":"3511 GV",
    "sg:province":"Utrecht",
    "sg:website":"http://www.lauteslager.nl",
    "wof:name":"Lauteslager Makelaars Bv",
    "wof:placetype":"venue"
},
  "geometry": {"coordinates":[5.120187,52.082317],"type":"Point"}
}