{
  "type": "Feature",
  "properties": {
    "iso:country":"NL",
    "sg:address":"Raadhuisplein 24",
    "sg:city":"Rozenburg Zh",
    "sg:orig_category":"Banken And Kredietinstellingen",
    "sg:phone":"+31 181 246 400",
    "sg:postcode":"3181 CG",
    "sg:province":"Zuid-Holland",
    "wof:name":"Rabobank",
    "wof:placetype":"venue"
},
  "geometry": {"coordinates":[4.249541,51.905293],"type":"Point"}
}