{
  "type": "Feature",
  "properties": {
    "addr:full":"Nieuwstr 67 De Bilt Utrecht 3732 DH",
    "addr:housenumber":"67",
    "addr:postcode":"3732 dh",
    "addr:street":"Nieuwstr",
    "iso:country":"NL",
    "sg:address":"Nieuwstr 67",
    "sg:city":"De Bilt",
    "sg:orig_category":"Parketvloeren",
    "sg:phone":"+31 30 221 7010",
    "sg:postcode":"3732 DH",
    "sg:province":"Utrecht",
    "sg:website":"http://www.gildenhuis.nl",
    "wof:name":"Gildenhuis De Bilt, Het",
    "wof:placetype":"venue"
},
  "geometry": {"coordinates":[5.181418,52.107044],"type":"Point"}
}