{
  "type": "Feature",
  "properties": {
    "addr:full":"Ln V Westenenk 44 Apeldoorn Gelderland 7336 AZ",
    "addr:housenumber":"44",
    "addr:postcode":"7336",
    "addr:street":"Ln;Westenenk;Gelderland",
    "iso:country":"NL",
    "sg:address":"Ln V Westenenk 44",
    "sg:city":"Apeldoorn",
    "sg:orig_category":"Verhuizingen",
    "sg:phone":"+31 55 543 1653",
    "sg:postcode":"7336 AZ",
    "sg:province":"Gelderland",
    "wof:name":"Asselt & Zn Bv, Van",
    "wof:placetype":"venue"
},
  "geometry": {"coordinates":[5.941423,52.194984],"type":"Point"}
}