{
  "type": "Feature",
  "properties": {
    "addr:full":"Lebretwg 27 Oosterbeek Gelderland 6861 ZV",
    "addr:housenumber":"27",
    "addr:postcode":"6861 zv",
    "addr:street":"Lebretwg;Gelderland",
    "iso:country":"NL",
    "sg:address":"Lebretwg 27",
    "sg:city":"Oosterbeek",
    "sg:orig_category":"Autorijscholen",
    "sg:phone":"+31 26 334 1236",
    "sg:postcode":"6861 ZV",
    "sg:province":"Gelderland",
    "wof:name":"Vogel, W",
    "wof:placetype":"venue"
},
  "geometry": {"coordinates":[5.846624,51.988708],"type":"Point"}
}