{
  "type": "Feature",
  "properties": {
    "addr:full":"Simon Stevinweg 17 Hilversum North Holland 1221 AC",
    "addr:housenumber":"17",
    "addr:postcode":"1221 ac",
    "addr:street":"Simon Stevinweg",
    "iso:country":"NL",
    "sg:address":"Simon Stevinweg 17",
    "sg:city":"Hilversum",
    "sg:orig_category":"Loodgieterswerk, Verwarming And Sanitaire Installaties",
    "sg:phone":"+31 35 685 5278",
    "sg:postcode":"1221 AC",
    "sg:province":"North Holland",
    "wof:name":"Afbouw A.C. Spakman",
    "wof:placetype":"venue"
},
  "geometry": {"coordinates":[5.179324,52.230797],"type":"Point"}
}