{
  "type": "Feature",
  "properties": {
    "iso:country":"NL",
    "sg:address":"P Gabrielstr 14",
    "sg:city":"Deurne",
    "sg:orig_category":"Autoschade- Herstelbedrijven",
    "sg:phone":"+31 493 311 063",
    "sg:postcode":"5753 DG",
    "sg:province":"Noord-Brabant",
    "wof:name":"Munsters Bv",
    "wof:placetype":"venue"
},
  "geometry": {"coordinates":[5.790711,51.461773],"type":"Point"}
}