{
  "type": "Feature",
  "properties": {
    "addr:full":"Zuster Hennekeplein 25 Rotterdam Zuid-Holland 3033 BW",
    "addr:housenumber":"25",
    "addr:postcode":"3033 bw",
    "addr:street":"Zuster Hennekeplein",
    "iso:country":"NL",
    "sg:address":"Zuster Hennekeplein 25",
    "sg:city":"Rotterdam",
    "sg:orig_category":"Diverse Grafische Activiteiten",
    "sg:phone":"+31 10 265 2996",
    "sg:postcode":"3033 BW",
    "sg:province":"Zuid-Holland",
    "wof:name":"Frame Grafisch En Ruimtelijk Ontwerp",
    "wof:placetype":"venue"
},
  "geometry": {"coordinates":[4.474048,51.926628],"type":"Point"}
}