{
  "type": "Feature",
  "properties": {
    "addr:full":"Nieuwe Veer 114 Streefkerk South Holland 2959 AN",
    "addr:housenumber":"114",
    "addr:postcode":"2959 an",
    "addr:street":"Nieuwe Veer",
    "iso:country":"NL",
    "sg:address":"Nieuwe Veer 114",
    "sg:city":"Streefkerk",
    "sg:orig_category":"Aanvullende Diensten Watertransport",
    "sg:phone":"+31 184 681 873",
    "sg:postcode":"2959 AN",
    "sg:province":"South Holland",
    "wof:name":"Jachthaven Lekzicht",
    "wof:placetype":"venue"
},
  "geometry": {"coordinates":[4.746154,51.902344],"type":"Point"}
}