{
  "type": "Feature",
  "properties": {
    "addr:full":"Karrestraat 19 Breda Noord-Brabant 4811 WT",
    "addr:housenumber":"19",
    "addr:postcode":"4811 wt",
    "addr:street":"Karrestraat",
    "iso:country":"NL",
    "sg:address":"Karrestraat 19",
    "sg:city":"Breda",
    "sg:orig_category":"Schoenen",
    "sg:phone":"+31 76 520 1323",
    "sg:postcode":"4811 WT",
    "sg:province":"Noord-Brabant",
    "wof:name":"Fooks",
    "wof:placetype":"venue"
},
  "geometry": {"coordinates":[4.775708,51.587608],"type":"Point"}
}