{
  "type": "Feature",
  "properties": {
    "iso:country":"NL",
    "sg:address":"De Wetering 5",
    "sg:city":"Oosterhout Nb",
    "sg:orig_category":"Kermisexploitatie",
    "sg:phone":"+31 162 455 038",
    "sg:postcode":"4906 CT",
    "sg:province":"North Brabant",
    "wof:name":"Kouwelaar & Zoon Bv",
    "wof:placetype":"venue"
},
  "geometry": {"coordinates":[4.845248,51.653709],"type":"Point"}
}