{
  "type": "Feature",
  "properties": {
    "addr:full":"Laan Van Westenenk 12 Apeldoorn Gelderland 7336 AZ",
    "addr:housenumber":"12",
    "addr:postcode":"7336",
    "addr:street":"Laan Van Westenenk;Gelderland",
    "iso:country":"NL",
    "sg:address":"Laan Van Westenenk 12",
    "sg:city":"Apeldoorn",
    "sg:orig_category":"Krantenuitgeverijen",
    "sg:phone":"+31 55 539 0222",
    "sg:postcode":"7336 AZ",
    "sg:province":"Gelderland",
    "wof:name":"Reformatorisch Dagblad Bv",
    "wof:placetype":"venue"
},
  "geometry": {"coordinates":[5.936183,52.191883],"type":"Point"}
}