{
  "type": "Feature",
  "properties": {
    "addr:full":"Atalanta 55 Zeewolde Flevoland 3892 EB",
    "addr:housenumber":"55",
    "addr:postcode":"3892 eb",
    "addr:street":"Atalanta;Flevoland",
    "iso:country":"NL",
    "sg:address":"Atalanta 55",
    "sg:city":"Zeewolde",
    "sg:orig_category":"Boeken En Tijdschriften",
    "sg:phone":"+31 6 22419155",
    "sg:postcode":"3892 EB",
    "sg:province":"Flevoland",
    "sg:website":"http://www.dekinderboekenshop.nl",
    "wof:name":"Kinderboekenshop Nl, De",
    "wof:placetype":"venue"
},
  "geometry": {"coordinates":[5.545175,52.320721],"type":"Point"}
}