{
  "type": "Feature",
  "properties": {
    "addr:full":"Jan Weitkamplaan 8 K Hardenberg Overijssel 7772 SE",
    "addr:housenumber":"8 k",
    "addr:postcode":"7772 se",
    "addr:street":"Jan Weitkamplaan",
    "iso:country":"NL",
    "sg:address":"Jan Weitkamplaan 8 K",
    "sg:city":"Hardenberg",
    "sg:orig_category":"Koeriersdiensten",
    "sg:phone":"+31 523 271 556",
    "sg:postcode":"7772 SE",
    "sg:province":"Overijssel",
    "wof:name":"Sneldienst Hardenberg",
    "wof:placetype":"venue"
},
  "geometry": {"coordinates":[6.6228837967,52.575340271],"type":"Point"}
}