{
  "type": "Feature",
  "properties": {
    "iso:country":"NL",
    "sg:address":"Begynenhof 28",
    "sg:city":"Molenhoek Lb",
    "sg:orig_category":"Psychologen",
    "sg:phone":"+31 24 358 3998",
    "sg:postcode":"6584 CW",
    "sg:province":"Limburg",
    "wof:name":"Oosterbaan, H J A",
    "wof:placetype":"venue"
},
  "geometry": {"coordinates":[5.877718,51.772072],"type":"Point"}
}