{
  "type": "Feature",
  "properties": {
    "iso:country":"NL",
    "sg:address":"Hamerstraat 1",
    "sg:city":"Amsterdam",
    "sg:orig_category":"Autoreparatie And Auto-Onderhoud",
    "sg:phone":"+31 20 632 8132",
    "sg:postcode":"1021 JT",
    "sg:province":"Noord-Holland",
    "wof:name":"Autobedrijf Kuijl",
    "wof:placetype":"venue"
},
  "geometry": {"coordinates":[4.92246,52.384159],"type":"Point"}
}