{
  "type": "Feature",
  "properties": {
    "iso:country":"NL",
    "sg:address":"Cirkel 67",
    "sg:city":"Vlissingen",
    "sg:orig_category":"Kappers",
    "sg:phone":"+31 118 469 267",
    "sg:postcode":"4384 DS",
    "sg:province":"Zeeland",
    "wof:name":"Angelina'S",
    "wof:placetype":"venue"
},
  "geometry": {"coordinates":[3.556055069,51.4615058899],"type":"Point"}
}