{
  "type": "Feature",
  "properties": {
    "addr:full":"Straatweg 38 Rotterdam Zuid-Holland 3051 BG",
    "addr:housenumber":"38",
    "addr:postcode":"3051",
    "addr:street":"Straatweg",
    "iso:country":"NL",
    "sg:address":"Straatweg 38",
    "sg:city":"Rotterdam",
    "sg:orig_category":"Makelaars In Onroerend Goed",
    "sg:phone":"+31 10 233 0101",
    "sg:postcode":"3051 BG",
    "sg:province":"Zuid-Holland",
    "wof:name":"Matchmakers",
    "wof:placetype":"venue"
},
  "geometry": {"coordinates":[-73.97154999999999,42.786839],"type":"Point"}
}