{
  "type": "Feature",
  "properties": {
    "addr:full":"Hoofdstr 2 Leiderdorp Zuid-Holland 2351 AJ",
    "addr:housenumber":"2",
    "addr:postcode":"2351 aj",
    "addr:street":"Hoofdstr",
    "iso:country":"NL",
    "sg:address":"Hoofdstr 2",
    "sg:city":"Leiderdorp",
    "sg:orig_category":"Adviesbureaus Bedrijfsorganisatie",
    "sg:phone":"+31 71 542 3761",
    "sg:postcode":"2351 AJ",
    "sg:province":"Zuid-Holland",
    "wof:name":"Philosopher Stone",
    "wof:placetype":"venue"
},
  "geometry": {"coordinates":[4.522633,52.151936],"type":"Point"}
}