{
  "type": "Feature",
  "properties": {
    "addr:full":"Rijksstraatweg 138 Leersum Utrecht 3956 CT",
    "addr:housenumber":"138",
    "addr:postcode":"3956 ct",
    "addr:street":"Rijksstraatweg",
    "iso:country":"NL",
    "sg:address":"Rijksstraatweg 138",
    "sg:city":"Leersum",
    "sg:orig_category":"Kappers",
    "sg:phone":"+31 343 452 837",
    "sg:postcode":"3956 CT",
    "sg:province":"Utrecht",
    "wof:name":"John Pierre",
    "wof:placetype":"venue"
},
  "geometry": {"coordinates":[5.4267749786,52.0126991272],"type":"Point"}
}