{
  "type": "Feature",
  "properties": {
    "addr:full":"Boekweitstr 144-146 Nieuw Vennep North Holland 2153 GL",
    "addr:housenumber":"144-146",
    "addr:postcode":"2153 gl",
    "addr:street":"Nieuw Vennep North",
    "iso:country":"NL",
    "sg:address":"Boekweitstr 144-146",
    "sg:city":"Nieuw Vennep",
    "sg:orig_category":"Kunststof Ramen",
    "sg:phone":"+31 252 675 080",
    "sg:postcode":"2153 GL",
    "sg:province":"North Holland",
    "wof:name":"Multigevel Bv",
    "wof:placetype":"venue"
},
  "geometry": {"coordinates":[4.652061,52.266239],"type":"Point"}
}