{
  "type": "Feature",
  "properties": {
    "addr:full":"Brieversstraat 7 Eede Zld Zeeland 4529 GW",
    "addr:housenumber":"7",
    "addr:postcode":"4529 gw",
    "addr:street":"Brieversstraat",
    "iso:country":"NL",
    "sg:address":"Brieversstraat 7",
    "sg:city":"Eede Zld",
    "sg:orig_category":"Zuivelproducten And Spijsoli?n Gh",
    "sg:phone":"+31 117 491 247",
    "sg:postcode":"4529 GW",
    "sg:province":"Zeeland",
    "wof:name":"W.A.M. Thilleman",
    "wof:placetype":"venue"
},
  "geometry": {"coordinates":[3.443996,51.247814],"type":"Point"}
}