{
  "type": "Feature",
  "properties": {
    "addr:full":"Fregatweg 52 Maastricht Limburg 6222 NZ",
    "addr:housenumber":"52",
    "addr:postcode":"6222 nz",
    "addr:street":"Fregatweg",
    "iso:country":"NL",
    "sg:address":"Fregatweg 52",
    "sg:city":"Maastricht",
    "sg:orig_category":"Huishoudelijk Textiel Fab",
    "sg:phone":"+31 43 325 3312",
    "sg:postcode":"6222 NZ",
    "sg:province":"Limburg",
    "wof:name":"Firma Gorkon",
    "wof:placetype":"venue"
},
  "geometry": {"coordinates":[5.713917,50.873959],"type":"Point"}
}