{
  "type": "Feature",
  "properties": {
    "addr:full":"De Kreek 16A Oosterhout Nb Noord-Brabant 4906 BB",
    "addr:housenumber":"16a",
    "addr:postcode":"4906 bb",
    "addr:street":"De Kreek",
    "iso:country":"NL",
    "sg:address":"De Kreek 16A",
    "sg:city":"Oosterhout Nb",
    "sg:orig_category":"Prijs- En Codeerapparatuur",
    "sg:phone":"+31 162 498 888",
    "sg:postcode":"4906 BB",
    "sg:province":"Noord-Brabant",
    "wof:name":"Matthews Benelux Bv",
    "wof:placetype":"venue"
},
  "geometry": {"coordinates":[4.843415,51.651779],"type":"Point"}
}