{
  "type": "Feature",
  "properties": {
    "addr:full":"Dorpsstraat 15 Graauw Zeeland 4569 AG",
    "addr:housenumber":"15",
    "addr:postcode":"4569",
    "addr:street":"Dorpsstraat",
    "iso:country":"NL",
    "sg:address":"Dorpsstraat 15",
    "sg:city":"Graauw",
    "sg:orig_category":"Goederenvervoer Over De Weg",
    "sg:phone":"+31 114 635 583",
    "sg:postcode":"4569 AG",
    "sg:province":"Zeeland",
    "wof:name":"Luna Transport Vof",
    "wof:placetype":"venue"
},
  "geometry": {"coordinates":[4.10394,51.327679],"type":"Point"}
}