{
  "type": "Feature",
  "properties": {
    "iso:country":"NL",
    "sg:address":"Brederodeln 104",
    "sg:city":"Papendrecht",
    "sg:orig_category":"Kappers",
    "sg:phone":"+31 78 615 6320",
    "sg:postcode":"3353 GG",
    "sg:province":"Zuid-Holland",
    "wof:name":"Frederique",
    "wof:placetype":"venue"
},
  "geometry": {"coordinates":[4.684689045,51.8257102966],"type":"Point"}
}