{
  "type": "Feature",
  "properties": {
    "iso:country":"NL",
    "sg:address":"3 Decembersngl 38",
    "sg:city":"Venlo",
    "sg:orig_category":"Verloskundigen",
    "sg:phone":"+31 77 323 0864",
    "sg:postcode":"5922 BD",
    "sg:province":"Limburg",
    "wof:name":"Verloskundigenpraktijk Venlo-Blerick",
    "wof:placetype":"venue"
},
  "geometry": {"coordinates":[6.137717,51.372154],"type":"Point"}
}