{
  "type": "Feature",
  "properties": {
    "addr:full":"Gymnasiumstraat 2 Groningen Groningen 9711 VN",
    "addr:housenumber":"2",
    "addr:postcode":"9711 vn",
    "addr:street":"Gymnasiumstraat",
    "iso:country":"NL",
    "sg:address":"Gymnasiumstraat 2",
    "sg:city":"Groningen",
    "sg:orig_category":"Muziekinstrumenten",
    "sg:phone":"+31 50 316 5853",
    "sg:postcode":"9711 VN",
    "sg:province":"Groningen",
    "wof:name":"Fons Sluijter",
    "wof:placetype":"venue"
},
  "geometry": {"coordinates":[6.571168,53.221397],"type":"Point"}
}