{
  "type": "Feature",
  "properties": {
    "addr:full":"Hoepel 15 Sliedrecht Zuid-Holland 3362 JA",
    "addr:housenumber":"15",
    "addr:postcode":"3362 ja",
    "addr:street":"Hoepel",
    "iso:country":"NL",
    "sg:address":"Hoepel 15",
    "sg:city":"Sliedrecht",
    "sg:orig_category":"Adviesbureaus Bedrijfsorganisatie",
    "sg:phone":"+31 6 51330665",
    "sg:postcode":"3362 JA",
    "sg:province":"Zuid-Holland",
    "wof:name":"Libra Consultancy",
    "wof:placetype":"venue"
},
  "geometry": {"coordinates":[4.795046,51.823177],"type":"Point"}
}