{
  "type": "Feature",
  "properties": {
    "iso:country":"NL",
    "sg:address":"Brugstr 10",
    "sg:city":"Ommen",
    "sg:orig_category":"Warenhuizen",
    "sg:phone":"+31 529 453 415",
    "sg:postcode":"7731 CT",
    "sg:province":"NL.08",
    "wof:name":"Hema",
    "wof:placetype":"venue"
},
  "geometry": {"coordinates":[6.4226679802,52.5179100037],"type":"Point"}
}