{
  "type": "Feature",
  "properties": {
    "addr:full":"Markenweg 1 Varsseveld Gelderland 7051 HS",
    "addr:housenumber":"1",
    "addr:postcode":"7051 hs",
    "addr:street":"Markenweg;Gelderland",
    "iso:country":"NL",
    "sg:address":"Markenweg 1",
    "sg:city":"Varsseveld",
    "sg:orig_category":"Pompen And Compressoren Fab",
    "sg:phone":"+31 315 258 181",
    "sg:postcode":"7051 HS",
    "sg:province":"Gelderland",
    "wof:name":"Waterkracht Bv",
    "wof:placetype":"venue"
},
  "geometry": {"coordinates":[6.482183,51.93837],"type":"Point"}
}