{
  "type": "Feature",
  "properties": {
    "iso:country":"NL",
    "sg:address":"Hembrugstraat 11",
    "sg:city":"Amsterdam",
    "sg:orig_category":"Diverse Grafische Activiteiten",
    "sg:phone":"+31 20 681 1703",
    "sg:postcode":"1013 WV",
    "sg:province":"Noord-Holland",
    "wof:name":"R.P.L. Designs Cv",
    "wof:placetype":"venue"
},
  "geometry": {"coordinates":[4.877062,52.391846],"type":"Point"}
}