{
  "type": "Feature",
  "properties": {
    "iso:country":"NL",
    "sg:address":"Dorpsstraat 342",
    "sg:city":"Assendelft",
    "sg:orig_category":"Kappers",
    "sg:phone":"+31 75 687 5316",
    "sg:postcode":"1566 BR",
    "sg:province":"Noord-Holland",
    "wof:name":"Jura Hairstyling",
    "wof:placetype":"venue"
},
  "geometry": {"coordinates":[4.7391319275,52.4649353027],"type":"Point"}
}