{
  "type": "Feature",
  "properties": {
    "addr:full":"Rietveld 26 Vinkeveen Utrecht 3645 XH",
    "addr:housenumber":"26",
    "addr:postcode":"3645 xh",
    "addr:street":"Rietveld",
    "iso:country":"NL",
    "sg:address":"Rietveld 26",
    "sg:city":"Vinkeveen",
    "sg:orig_category":"Koeriersdiensten",
    "sg:phone":"+31 297 266 958",
    "sg:postcode":"3645 XH",
    "sg:province":"Utrecht",
    "wof:name":"B & B",
    "wof:placetype":"venue"
},
  "geometry": {"coordinates":[4.923574,52.210178],"type":"Point"}
}