{
  "type": "Feature",
  "properties": {
    "iso:country":"NL",
    "sg:address":"Frederiklaan 209",
    "sg:city":"Eindhoven",
    "sg:orig_category":"Elektronische Bedrijfsinstallaties",
    "sg:phone":"+31 40 251 8235",
    "sg:postcode":"5616 NG",
    "sg:province":"Noord-Brabant",
    "wof:name":"I B O Elektronica",
    "wof:placetype":"venue"
},
  "geometry": {"coordinates":[5.456267,51.441593],"type":"Point"}
}