{
  "type": "Feature",
  "properties": {
    "addr:full":"Hoofdstr 18A Best Noord-Brabant 5683 AD",
    "addr:housenumber":"18a",
    "addr:postcode":"5683 ad",
    "addr:street":"Hoofdstr",
    "iso:country":"NL",
    "sg:address":"Hoofdstr 18A",
    "sg:city":"Best",
    "sg:orig_category":"Podotherapeuten",
    "sg:phone":"+31 499 393 352",
    "sg:postcode":"5683 AD",
    "sg:province":"Noord-Brabant",
    "wof:name":"Brons & De Koning",
    "wof:placetype":"venue"
},
  "geometry": {"coordinates":[-101.618134,31.224251],"type":"Point"}
}