{
  "type": "Feature",
  "properties": {
    "addr:full":"Burg Roelenwg 15 Zwolle Overijssel 8031 ES",
    "addr:housenumber":"15",
    "addr:postcode":"8031 es",
    "addr:street":"Burg",
    "iso:country":"NL",
    "sg:address":"Burg Roelenwg 15",
    "sg:city":"Zwolle",
    "sg:orig_category":"Automaterialen En Gereedschappen",
    "sg:phone":"+31 38 421 2949",
    "sg:postcode":"8031 ES",
    "sg:province":"Overijssel",
    "wof:name":"Ferwerda Bv, Gebr",
    "wof:placetype":"venue"
},
  "geometry": {"coordinates":[6.083594,52.51852],"type":"Point"}
}