{
  "type": "Feature",
  "properties": {
    "addr:full":"Barneveldsestr 29 Renswoude Utrecht 3927 CA",
    "addr:housenumber":"29",
    "addr:postcode":"3927 ca",
    "addr:street":"Barneveldsestr",
    "iso:country":"NL",
    "sg:address":"Barneveldsestr 29",
    "sg:city":"Renswoude",
    "sg:orig_category":"Autopoetsbedrijven",
    "sg:phone":"+31 6 51329087",
    "sg:postcode":"3927 CA",
    "sg:province":"Utrecht",
    "wof:name":"A & W",
    "wof:placetype":"venue"
},
  "geometry": {"coordinates":[5.538958,52.080193],"type":"Point"}
}