{
  "type": "Feature",
  "properties": {
    "iso:country":"NL",
    "sg:address":"Biezenstr 7",
    "sg:city":"Roosendaal",
    "sg:orig_category":"Honden- En Kattentrimsalons",
    "sg:phone":"+31 165 539 955",
    "sg:postcode":"4703 SM",
    "sg:province":"Noord-Brabant",
    "wof:name":"Kuip, Van Der",
    "wof:placetype":"venue"
},
  "geometry": {"coordinates":[4.414994,51.543995],"type":"Point"}
}