{
  "type": "Feature",
  "properties": {
    "addr:full":"Binnen Bant Str 4 Amsterdam Noord-Holland 1011 CK",
    "addr:housenumber":"4",
    "addr:postcode":"1011 ck",
    "addr:street":"Binnen Bant Str",
    "iso:country":"NL",
    "sg:address":"Binnen Bant Str 4",
    "sg:city":"Amsterdam",
    "sg:orig_category":"Evenementenverzorging",
    "sg:phone":"+31 20 771 8558",
    "sg:postcode":"1011 CK",
    "sg:province":"Noord-Holland",
    "sg:website":"http://www.amsterdam-entertainment.nl",
    "wof:name":"Amsterdam Entertainment Prod",
    "wof:placetype":"venue"
},
  "geometry": {"coordinates":[4.901684,52.373859],"type":"Point"}
}