{
  "type": "Feature",
  "properties": {
    "addr:full":"Graaf Ottolaan 17 Harderwijk Gelderland 3843 AK",
    "addr:housenumber":"17",
    "addr:postcode":"3843 ak",
    "addr:street":"Graaf Ottolaan;Gelderland",
    "iso:country":"NL",
    "sg:address":"Graaf Ottolaan 17",
    "sg:city":"Harderwijk",
    "sg:orig_category":"Autokeuringen",
    "sg:phone":"+31 341 412 463",
    "sg:postcode":"3843 AK",
    "sg:province":"Gelderland",
    "wof:name":"Brouwer Tankservice/Carwash",
    "wof:placetype":"venue"
},
  "geometry": {"coordinates":[5.628244,52.336529],"type":"Point"}
}