{
  "type": "Feature",
  "properties": {
    "iso:country":"NL",
    "sg:address":"G Flinckstr 227",
    "sg:city":"Amsterdam",
    "sg:orig_category":"Meubelmakerijen",
    "sg:phone":"+31 20 676 7671",
    "sg:postcode":"1073 BW",
    "sg:province":"Noord-Holland",
    "wof:name":"Ladiges, Peter",
    "wof:placetype":"venue"
},
  "geometry": {"coordinates":[4.896567,52.355919],"type":"Point"}
}