{
  "type": "Feature",
  "properties": {
    "iso:country":"NL",
    "sg:address":"Olststraat 4",
    "sg:city":"'S Gravenhage",
    "sg:orig_category":"Loodgieterswerk, Verwarming And Sanitaire Installaties",
    "sg:phone":"+31 70 366 7547",
    "sg:postcode":"2541 AB",
    "sg:province":"Zuid-Holland",
    "wof:name":"H J Fortunati En Zn",
    "wof:placetype":"venue"
},
  "geometry": {"coordinates":[4.28115,52.04451],"type":"Point"}
}