{
  "type": "Feature",
  "properties": {
    "addr:full":"Achterdoelen 90 Ede Gld Gelderland 6711 AV",
    "addr:housenumber":"90;6711",
    "addr:postcode":"av",
    "addr:street":"Achterdoelen;Gld Gelderland",
    "iso:country":"NL",
    "sg:address":"Achterdoelen 90",
    "sg:city":"Ede Gld",
    "sg:orig_category":"Lijstenmakerijen",
    "sg:phone":"+31 318 653 863",
    "sg:postcode":"6711 AV",
    "sg:province":"Gelderland",
    "sg:website":"http://www.expo.nl",
    "wof:name":"Expo",
    "wof:placetype":"venue"
},
  "geometry": {"coordinates":[5.671583,52.044804],"type":"Point"}
}