{
  "type": "Feature",
  "properties": {
    "addr:full":"Christiaan Eberhardstr 14 Nieuweschans Lower Saxony 9693 BJ",
    "addr:housenumber":"14",
    "addr:postcode":"9693 bj",
    "addr:street":"Christiaan Eberhardstr;Nieuweschans Lower Saxony",
    "iso:country":"NL",
    "sg:address":"Christiaan Eberhardstr 14",
    "sg:city":"Nieuweschans",
    "sg:orig_category":"Goederenvervoer Over De Weg",
    "sg:phone":"+31 597 521 494",
    "sg:postcode":"9693 BJ",
    "sg:province":"Lower Saxony",
    "wof:name":"Internationaal Transport Abels",
    "wof:placetype":"venue"
},
  "geometry": {"coordinates":[7.212668,53.183994],"type":"Point"}
}