{
  "type": "Feature",
  "properties": {
    "addr:full":"Rijnstraat 4 Oss Virginia 5347 KL",
    "addr:housenumber":"4",
    "addr:postcode":"5347 kl",
    "addr:street":"Rijnstraat",
    "iso:country":"NL",
    "sg:address":"Rijnstraat 4",
    "sg:city":"Oss",
    "sg:orig_category":"Chemische Producten Gh",
    "sg:phone":"+31 412 643 834",
    "sg:postcode":"5347 KL",
    "sg:province":"Virginia",
    "wof:name":"Heesen Kunstoffen Bv",
    "wof:placetype":"venue"
},
  "geometry": {"coordinates":[-77.235214,38.312599],"type":"Point"}
}