{
  "type": "Feature",
  "properties": {
    "addr:full":"Houtkopersstr 14 Zwyndrecht Zuid-Holland 3334 KD",
    "addr:housenumber":"14",
    "addr:postcode":"3334 kd",
    "addr:street":"Houtkopersstr",
    "iso:country":"NL",
    "sg:address":"Houtkopersstr 14",
    "sg:city":"Zwyndrecht",
    "sg:orig_category":"Bedrijfsmechanisatie En -Automatisering",
    "sg:phone":"+31 78 610 0645",
    "sg:postcode":"3334 KD",
    "sg:province":"Zuid-Holland",
    "sg:website":"HTTP://www.rijlaarsdam.biz",
    "wof:name":"Rijlaarsdam",
    "wof:placetype":"venue"
},
  "geometry": {"coordinates":[4.60917,51.817219],"type":"Point"}
}