{
  "type": "Feature",
  "properties": {
    "addr:full":"Voske 12 Baarle Nassau Noord-Brabant 5111 PE",
    "addr:housenumber":"12",
    "addr:postcode":"5111 pe",
    "addr:street":"Voske",
    "iso:country":"NL",
    "sg:address":"Voske 12",
    "sg:city":"Baarle Nassau",
    "sg:orig_category":"Landbouwmachines Gh",
    "sg:phone":"+31 13 507 9967",
    "sg:postcode":"5111 PE",
    "sg:province":"Noord-Brabant",
    "wof:name":"A. V.D. Broek",
    "wof:placetype":"venue"
},
  "geometry": {"coordinates":[4.986795,51.449715],"type":"Point"}
}