{
  "type": "Feature",
  "properties": {
    "addr:full":"Strenkhaarswg 16 Lemelerveld NL.08 8152 DL",
    "addr:housenumber":"16;nl.08",
    "addr:postcode":"8152 dl",
    "addr:street":"Strenkhaarswg",
    "iso:country":"NL",
    "sg:address":"Strenkhaarswg 16",
    "sg:city":"Lemelerveld",
    "sg:orig_category":"Oldtimers",
    "sg:phone":"+31 572 372 998",
    "sg:postcode":"8152 DL",
    "sg:province":"NL.08",
    "wof:name":"Merlin",
    "wof:placetype":"venue"
},
  "geometry": {"coordinates":[6.309624,52.438587],"type":"Point"}
}