{
  "type": "Feature",
  "properties": {
    "addr:full":"Postbus 25281 Rotterdam Noord-Brabant 3001 HG",
    "addr:housenumber":"25281",
    "addr:postcode":"3001 hg",
    "addr:street":"Postbus",
    "iso:country":"NL",
    "sg:address":"Postbus 25281",
    "sg:city":"Rotterdam",
    "sg:orig_category":"Verenigingen En Stichtingen",
    "sg:phone":"+31 10 436 6667",
    "sg:postcode":"3001 HG",
    "sg:province":"Noord-Brabant",
    "wof:name":"Kunst & Zaken, Sticht",
    "wof:placetype":"venue"
},
  "geometry": {"coordinates":[4.47075,51.922619],"type":"Point"}
}