{
  "type": "Feature",
  "properties": {
    "addr:full":"Papenhoeflaan 28 Oudewater Utrecht 3421 XR",
    "addr:housenumber":"28",
    "addr:postcode":"3421 xr",
    "addr:street":"Papenhoeflaan",
    "iso:country":"NL",
    "sg:address":"Papenhoeflaan 28",
    "sg:city":"Oudewater",
    "sg:orig_category":"Boekhouders",
    "sg:phone":"+31 348 562 298",
    "sg:postcode":"3421 XR",
    "sg:province":"Utrecht",
    "wof:name":"Administratiekantoor Peter Kelder",
    "wof:placetype":"venue"
},
  "geometry": {"coordinates":[4.863195,52.02702],"type":"Point"}
}