{
  "type": "Feature",
  "properties": {
    "iso:country":"NL",
    "sg:address":"Grotestraat 28",
    "sg:city":"Markelo",
    "sg:orig_category":"Kappers",
    "sg:phone":"+31 547 361 819",
    "sg:postcode":"7475 AX",
    "sg:province":"NL.08",
    "wof:name":"Diabolo Haarmode",
    "wof:placetype":"venue"
},
  "geometry": {"coordinates":[6.4914121628,52.2364997864],"type":"Point"}
}