{
  "type": "Feature",
  "properties": {
    "iso:country":"NL",
    "sg:address":"R Schumanring 225",
    "sg:city":"Vlaardingen",
    "sg:orig_category":"Grafisch Ontwerpers",
    "sg:phone":"+31 10 460 0117",
    "sg:postcode":"3137 VB",
    "sg:province":"Zuid-Holland",
    "wof:name":"Kakiriboe",
    "wof:placetype":"venue"
},
  "geometry": {"coordinates":[4.341935,51.933144],"type":"Point"}
}