{
  "type": "Feature",
  "properties": {
    "addr:full":"Kavelweg 25 Broeksterwoude Provincie Friesland 9108 MC",
    "addr:housenumber":"25;9108",
    "addr:street":"Kavelweg;Provincie Friesland;Mc",
    "iso:country":"NL",
    "sg:address":"Kavelweg 25",
    "sg:city":"Broeksterwoude",
    "sg:orig_category":"Fietshandelaren",
    "sg:phone":"+31 511 421 997",
    "sg:postcode":"9108 MC",
    "sg:province":"Provincie Friesland",
    "wof:name":"M. Boorsma",
    "wof:placetype":"venue"
},
  "geometry": {"coordinates":[5.995576,53.274368],"type":"Point"}
}