{
  "type": "Feature",
  "properties": {
    "addr:full":"Oostwal 4 Oss Noord-Brabant 5341 KX",
    "addr:housenumber":"4",
    "addr:postcode":"5341 kx",
    "addr:street":"Oostwal",
    "iso:country":"NL",
    "sg:address":"Oostwal 4",
    "sg:city":"Oss",
    "sg:classifiers":[
        {
            "category":"Food & Beverages",
            "subcategory":"Bakery",
            "type":"Retail Goods"
        }
    ],
    "sg:phone":"+31 412 650 969",
    "sg:postcode":"5341 KX",
    "sg:province":"Noord-Brabant",
    "sg:tags":[
        "pizza"
    ],
    "wof:name":"Shalom",
    "wof:placetype":"venue"
},
  "geometry": {"coordinates":[-77.235214,38.312599],"type":"Point"}
}