{
  "type": "Feature",
  "properties": {
    "iso:country":"NL",
    "sg:address":"Nieuwez Voorburgw 328C",
    "sg:city":"Amsterdam",
    "sg:orig_category":"Architecten En Architectenbureaus",
    "sg:phone":"+31 20 625 0035",
    "sg:postcode":"1012 RW",
    "sg:province":"Noord-Holland",
    "wof:name":"Frontline Studio",
    "wof:placetype":"venue"
},
  "geometry": {"coordinates":[4.889399,52.369675],"type":"Point"}
}