{
  "type": "Feature",
  "properties": {
    "addr:full":"Oldemarktsew 141 Steenwijkerwold Overijssel 8341 SE",
    "addr:housenumber":"141",
    "addr:postcode":"8341 se",
    "iso:country":"NL",
    "sg:address":"Oldemarktsew 141",
    "sg:city":"Steenwijkerwold",
    "sg:orig_category":"Verenigingen En Stichtingen",
    "sg:phone":"+31 521 588 788",
    "sg:postcode":"8341 SE",
    "sg:province":"Overijssel",
    "wof:name":"Raad Voor Bejaarden Werk, Sticht",
    "wof:placetype":"venue"
},
  "geometry": {"coordinates":[6.064699,52.804592],"type":"Point"}
}