{
  "type": "Feature",
  "properties": {
    "addr:full":"Moerven 201 Veghel Noord-Brabant 5464 PE",
    "addr:housenumber":"201",
    "addr:postcode":"veghel;5464 pe",
    "addr:street":"Moerven",
    "iso:country":"NL",
    "sg:address":"Moerven 201",
    "sg:city":"Veghel",
    "sg:orig_category":"Schoonheidsinstituten",
    "sg:phone":"+31 413 351 594",
    "sg:postcode":"5464 PE",
    "sg:province":"Noord-Brabant",
    "wof:name":"Isis",
    "wof:placetype":"venue"
},
  "geometry": {"coordinates":[5.559953,51.631977],"type":"Point"}
}