{
  "type": "Feature",
  "properties": {
    "addr:full":"Volantestraat 19 Hellevoetsluis Zuid-Holland 3223 PH",
    "addr:housenumber":"19",
    "addr:postcode":"3223",
    "addr:street":"Volantestraat",
    "iso:country":"NL",
    "sg:address":"Volantestraat 19",
    "sg:city":"Hellevoetsluis",
    "sg:orig_category":"Beautyfarms And Sauna'S",
    "sg:phone":"+31 181 327 772",
    "sg:postcode":"3223 PH",
    "sg:province":"Zuid-Holland",
    "wof:name":"Esthemaro",
    "wof:placetype":"venue"
},
  "geometry": {"coordinates":[4.162631,51.843361],"type":"Point"}
}