{
  "type": "Feature",
  "properties": {
    "iso:country":"NL",
    "sg:address":"Akeleiwg 74",
    "sg:city":"Groningen",
    "sg:orig_category":"Artsen - Huisartsen",
    "sg:phone":"+31 50 542 4324",
    "sg:postcode":"9731 JB",
    "sg:province":"Groningen",
    "wof:name":"Veenen, M S Van",
    "wof:placetype":"venue"
},
  "geometry": {"coordinates":[6.598292,53.232475],"type":"Point"}
}