{
  "type": "Feature",
  "properties": {
    "addr:full":"Cuykseweg 9 Oeffelt Noord-Brabant 5441 XA",
    "addr:housenumber":"9",
    "addr:postcode":"5441 xa",
    "addr:street":"Cuykseweg",
    "iso:country":"NL",
    "sg:address":"Cuykseweg 9",
    "sg:city":"Oeffelt",
    "sg:orig_category":"Metaalwerken",
    "sg:phone":"+31 485 362 072",
    "sg:postcode":"5441 XA",
    "sg:province":"Noord-Brabant",
    "wof:name":"Gijsberts Rolluiken En Zonnewering",
    "wof:placetype":"venue"
},
  "geometry": {"coordinates":[5.927333,51.700066],"type":"Point"}
}