{
  "type": "Feature",
  "properties": {
    "addr:full":"Vd Palmkd 117 Amsterdam Noord-Holland 1051 RH",
    "addr:housenumber":"117",
    "addr:postcode":"1051 rh",
    "iso:country":"NL",
    "sg:address":"Vd Palmkd 117",
    "sg:city":"Amsterdam",
    "sg:orig_category":"Vertalers",
    "sg:phone":"+31 20 612 3777",
    "sg:postcode":"1051 RH",
    "sg:province":"Noord-Holland",
    "wof:name":"Mercks M F Kleijer, K",
    "wof:placetype":"venue"
},
  "geometry": {"coordinates":[4.87107,52.37925],"type":"Point"}
}