{
  "type": "Feature",
  "properties": {
    "addr:full":"Olykewg 26 Soest Utrecht 3764 CZ",
    "addr:housenumber":"26",
    "addr:postcode":"3764",
    "addr:street":"Olykewg",
    "iso:country":"NL",
    "sg:address":"Olykewg 26",
    "sg:city":"Soest",
    "sg:orig_category":"Manueel Therapeuten",
    "sg:phone":"+31 35 602 1411",
    "sg:postcode":"3764 CZ",
    "sg:province":"Utrecht",
    "wof:name":"Broek G J Van Den & Kroon H T",
    "wof:placetype":"venue"
},
  "geometry": {"coordinates":[5.312662,52.17057],"type":"Point"}
}