{
  "type": "Feature",
  "properties": {
    "addr:full":"2E Loswal 17 Hilversum Noord-Holland 1216 BC",
    "addr:housenumber":"17",
    "addr:postcode":"1216 bc",
    "addr:street":"2E Loswal",
    "iso:country":"NL",
    "sg:address":"2E Loswal 17",
    "sg:city":"Hilversum",
    "sg:orig_category":"Gespecialiseerde Bouw",
    "sg:phone":"+31 35 624 4176",
    "sg:postcode":"1216 BC",
    "sg:province":"Noord-Holland",
    "wof:name":"Machinefabriek En Constructie- Bedrijf Van Galen B",
    "wof:placetype":"venue"
},
  "geometry": {"coordinates":[5.14642,52.22266],"type":"Point"}
}