{
  "type": "Feature",
  "properties": {
    "addr:full":"Agricolastr 75 Sittard Limburg 6131 JW",
    "addr:housenumber":"75",
    "addr:postcode":"6131 jw",
    "addr:street":"Agricolastr",
    "iso:country":"NL",
    "sg:address":"Agricolastr 75",
    "sg:city":"Sittard",
    "sg:orig_category":"Vakorganisaties",
    "sg:phone":"+31 46 420 2870",
    "sg:postcode":"6131 JW",
    "sg:province":"Limburg",
    "sg:website":"http://www.cnv.net",
    "wof:name":"Cnv Bedrijvenbond",
    "wof:placetype":"venue"
},
  "geometry": {"coordinates":[5.863892,50.993752],"type":"Point"}
}