{
  "type": "Feature",
  "properties": {
    "addr:full":"Hoofdstraat 21 Exloo Drenthe 7875 AA",
    "addr:housenumber":"21",
    "addr:postcode":"7875 aa",
    "addr:street":"Hoofdstraat",
    "iso:country":"NL",
    "sg:address":"Hoofdstraat 21",
    "sg:city":"Exloo",
    "sg:classifiers":[
        {
            "category":"Travel",
            "subcategory":"Hotels & Motels",
            "type":"Entertainment"
        }
    ],
    "sg:phone":"+31 591 549 678",
    "sg:postcode":"7875 AA",
    "sg:province":"Drenthe",
    "wof:name":"Olde Volte",
    "wof:placetype":"venue"
},
  "geometry": {"coordinates":[6.871359,52.883186],"type":"Point"}
}