{
  "type": "Feature",
  "properties": {
    "addr:full":"Julialaan 6 Wateringen Zuid-Holland 2291 BM",
    "addr:housenumber":"6",
    "addr:postcode":"2291 bm",
    "addr:street":"Julialaan",
    "iso:country":"NL",
    "sg:address":"Julialaan 6",
    "sg:city":"Wateringen",
    "sg:orig_category":"Alternatieve Geneeskunde",
    "sg:phone":"+31 174 295 833",
    "sg:postcode":"2291 BM",
    "sg:province":"Zuid-Holland",
    "wof:name":"Fysiotherapie Wateringen",
    "wof:placetype":"venue"
},
  "geometry": {"coordinates":[4.280271,52.026131],"type":"Point"}
}