{
  "type": "Feature",
  "properties": {
    "iso:country":"NL",
    "sg:address":"Putterlaan 2",
    "sg:city":"Leidschendam",
    "sg:orig_category":"Juridische Dienstverlening",
    "sg:phone":"+31 70 320 1469",
    "sg:postcode":"2261 EM",
    "sg:province":"Zuid-Holland",
    "wof:name":"Merken & Modellenbur Holland Bv",
    "wof:placetype":"venue"
},
  "geometry": {"coordinates":[4.386315,52.095741],"type":"Point"}
}