{
  "type": "Feature",
  "properties": {
    "iso:country":"NL",
    "sg:address":"Verhoevenstr 21",
    "sg:city":"Wateringen",
    "sg:orig_category":"Schoonheidsinstituten",
    "sg:phone":"+31 174 290 534",
    "sg:postcode":"2291 RN",
    "sg:province":"South Holland",
    "wof:name":"Jacqueline Van Der Knaap",
    "wof:placetype":"venue"
},
  "geometry": {"coordinates":[4.275794,52.027264],"type":"Point"}
}