{
  "type": "Feature",
  "properties": {
    "addr:full":"F Rooseveltln 12 Breda Noord-Brabant 4835 AB",
    "addr:housenumber":"12",
    "addr:postcode":"4835 ab",
    "iso:country":"NL",
    "sg:address":"F Rooseveltln 12",
    "sg:city":"Breda",
    "sg:orig_category":"Adviesbureaus Gezondheidszorg",
    "sg:phone":"+31 76 565 8807",
    "sg:postcode":"4835 AB",
    "sg:province":"Noord-Brabant",
    "wof:name":"Bruininks",
    "wof:placetype":"venue"
},
  "geometry": {"coordinates":[4.784676,51.573605],"type":"Point"}
}