{
  "type": "Feature",
  "properties": {
    "addr:full":"Zuidstraat 27 Westkapelle Zeeland 4361 AA",
    "addr:housenumber":"27",
    "addr:postcode":"4361 aa",
    "addr:street":"Zuidstraat",
    "iso:country":"NL",
    "sg:address":"Zuidstraat 27",
    "sg:city":"Westkapelle",
    "sg:orig_category":"Autokeuringen",
    "sg:phone":"+31 118 571 292",
    "sg:postcode":"4361 AA",
    "sg:province":"Zeeland",
    "wof:name":"Faasse Kaland",
    "wof:placetype":"venue"
},
  "geometry": {"coordinates":[3.443156,51.528229],"type":"Point"}
}