{
  "type": "Feature",
  "properties": {
    "iso:country":"NL",
    "sg:address":"Bazillehof 13",
    "sg:city":"Hoorn Nh",
    "sg:orig_category":"Voetbalverenigingen",
    "sg:phone":"+31 229 262 747",
    "sg:postcode":"1628 XD",
    "sg:province":"North Holland",
    "wof:name":"Westfriezen",
    "wof:placetype":"venue"
},
  "geometry": {"coordinates":[5.107918,52.653164],"type":"Point"}
}