{
  "type": "Feature",
  "properties": {
    "iso:country":"NL",
    "sg:address":"Rangeerstraat 7",
    "sg:city":"'S Gravenpolder",
    "sg:orig_category":"Metaalbekleding And -Behandeling",
    "sg:phone":"+31 113 313 319",
    "sg:postcode":"4431 NL",
    "sg:province":"Zeeland",
    "wof:name":"Elfrink",
    "wof:placetype":"venue"
},
  "geometry": {"coordinates":[3.883515,51.450489],"type":"Point"}
}