{
  "type": "Feature",
  "properties": {
    "addr:full":"Konijnenberg 43 Breda Noord-Brabant 4825 BC",
    "addr:housenumber":"43",
    "addr:postcode":"4825 bc",
    "addr:street":"Konijnenberg",
    "iso:country":"NL",
    "sg:address":"Konijnenberg 43",
    "sg:city":"Breda",
    "sg:orig_category":"Kantoorartikelen",
    "sg:phone":"+31 76 587 3750",
    "sg:postcode":"4825 BC",
    "sg:province":"Noord-Brabant",
    "wof:name":"Staalimex Bv",
    "wof:placetype":"venue"
},
  "geometry": {"coordinates":[4.7700681686,51.6050453186],"type":"Point"}
}