{
  "type": "Feature",
  "properties": {
    "iso:country":"NL",
    "sg:address":"Burg Joostenln 15",
    "sg:city":"Wessem",
    "sg:orig_category":"Projectinrichting",
    "sg:phone":"+31 475 564 248",
    "sg:postcode":"6019 BX",
    "sg:province":"Limburg",
    "wof:name":"Tradart",
    "wof:placetype":"venue"
},
  "geometry": {"coordinates":[5.879622,51.160892],"type":"Point"}
}