{
  "type": "Feature",
  "properties": {
    "addr:full":"Burg Joostenln 15 Wessem Limburg 6019 BX",
    "addr:housenumber":"15",
    "addr:postcode":"6019 bx",
    "addr:street":"Burg;Wessem Limburg",
    "iso:country":"NL",
    "sg:address":"Burg Joostenln 15",
    "sg:city":"Wessem",
    "sg:orig_category":"Projectinrichting",
    "sg:phone":"+31 475 564 248",
    "sg:postcode":"6019 BX",
    "sg:province":"Limburg",
    "wof:name":"Tradart",
    "wof:placetype":"venue"
},
  "geometry": {"coordinates":[5.879622,51.160892],"type":"Point"}
}