{
  "type": "Feature",
  "properties": {
    "addr:full":"Kloosterln 158 Hilversum Noord-Holland 1216 NT",
    "addr:housenumber":"158",
    "addr:postcode":"hilversum;1216 nt",
    "iso:country":"NL",
    "sg:address":"Kloosterln 158",
    "sg:city":"Hilversum",
    "sg:orig_category":"Vertalers",
    "sg:phone":"+31 35 623 3152",
    "sg:postcode":"1216 NT",
    "sg:province":"Noord-Holland",
    "wof:name":"Kumek Milan",
    "wof:placetype":"venue"
},
  "geometry": {"coordinates":[5.1695,52.228565],"type":"Point"}
}