{
  "type": "Feature",
  "properties": {
    "addr:full":"De Schepel 52 Dronten NL. 8252 JL",
    "addr:housenumber":"52",
    "addr:postcode":"8252 jl",
    "addr:street":"De Schepel;Nl.",
    "iso:country":"NL",
    "sg:address":"De Schepel 52",
    "sg:city":"Dronten",
    "sg:orig_category":"Marktonderzoekbureaus",
    "sg:phone":"+31 321 380 886",
    "sg:postcode":"8252 JL",
    "sg:province":"NL.",
    "wof:name":"Reflex Management Support",
    "wof:placetype":"venue"
},
  "geometry": {"coordinates":[5.700623,52.514053],"type":"Point"}
}