{
  "type": "Feature",
  "properties": {
    "iso:country":"NL",
    "sg:address":"Postbus 1068",
    "sg:city":"S Hertogenbosch",
    "sg:orig_category":"Waterleidingbedrijven",
    "sg:phone":"+31 73 692 2345",
    "sg:postcode":"5200 BC",
    "sg:province":"North Brabant",
    "sg:website":"http://www.nvwob.nl",
    "wof:name":"Wob",
    "wof:placetype":"venue"
},
  "geometry": {"coordinates":[5.2982401848,51.6907501221],"type":"Point"}
}