{
  "type": "Feature",
  "properties": {
    "addr:full":"Molenakkerstr 108 Gemert Noord-Brabant 5421 BP",
    "addr:housenumber":"108",
    "addr:postcode":"5421 bp",
    "iso:country":"NL",
    "sg:address":"Molenakkerstr 108",
    "sg:city":"Gemert",
    "sg:orig_category":"Videotheken",
    "sg:phone":"+31 492 364 906",
    "sg:postcode":"5421 BP",
    "sg:province":"Noord-Brabant",
    "wof:name":"Berlo, Van",
    "wof:placetype":"venue"
},
  "geometry": {"coordinates":[5.691887,51.557407],"type":"Point"}
}