{
  "type": "Feature",
  "properties": {
    "addr:full":"Sterrenoord 95 'S Gravenhage South Holland 2544 JW",
    "addr:housenumber":"95",
    "addr:postcode":"2544 jw",
    "addr:street":"Sterrenoord;' S Gravenhage",
    "iso:country":"NL",
    "sg:address":"Sterrenoord 95",
    "sg:city":"'S Gravenhage",
    "sg:orig_category":"Werving And Selectie Van Tijdelijk Personeel And Uitzendkantoren",
    "sg:phone":"+31 70 367 4340",
    "sg:postcode":"2544 JW",
    "sg:province":"South Holland",
    "wof:name":"Dadas",
    "wof:placetype":"venue"
},
  "geometry": {"coordinates":[4.2586112022,52.0430297852],"type":"Point"}
}