{
  "type": "Feature",
  "properties": {
    "addr:full":"Herensngl 147 Weesp Noord-Holland 1382 VP",
    "addr:housenumber":"147",
    "addr:postcode":"1382 vp",
    "iso:country":"NL",
    "sg:address":"Herensngl 147",
    "sg:city":"Weesp",
    "sg:orig_category":"Webdesign Bureaus",
    "sg:phone":"+31 294 457 419",
    "sg:postcode":"1382 VP",
    "sg:province":"Noord-Holland",
    "wof:name":"Dtp Producties Weesp",
    "wof:placetype":"venue"
},
  "geometry": {"coordinates":[5.0382800102,52.3083152771],"type":"Point"}
}