{
  "type": "Feature",
  "properties": {
    "addr:full":"Helmersstr 8 Gouda Zuid-Holland 2802 ND",
    "addr:housenumber":"8",
    "addr:postcode":"2802 nd",
    "addr:street":"Helmersstr",
    "iso:country":"NL",
    "sg:address":"Helmersstr 8",
    "sg:city":"Gouda",
    "sg:orig_category":"Fotografie Reclame En Mode",
    "sg:phone":"+31 182 514 721",
    "sg:postcode":"2802 ND",
    "sg:province":"Zuid-Holland",
    "wof:name":"Marco",
    "wof:placetype":"venue"
},
  "geometry": {"coordinates":[4.703442,52.004341],"type":"Point"}
}