{
  "type": "Feature",
  "properties": {
    "addr:full":"Raadhuisstr 274 Best Texas 5683 GM",
    "addr:housenumber":"274",
    "addr:postcode":"5683 gm",
    "iso:country":"NL",
    "sg:address":"Raadhuisstr 274",
    "sg:city":"Best",
    "sg:orig_category":"Logopedisten",
    "sg:phone":"+31 499 393 076",
    "sg:postcode":"5683 GM",
    "sg:province":"Texas",
    "wof:name":"Wittk\u00e4mper-Bellaart, L Y J",
    "wof:placetype":"venue"
},
  "geometry": {"coordinates":[-101.618134,31.224251],"type":"Point"}
}