{
  "type": "Feature",
  "properties": {
    "iso:country":"NL",
    "sg:address":"Kruitmolenlaan 45",
    "sg:city":"Middelburg",
    "sg:orig_category":"Hypotheken And Hypotheekbanken",
    "sg:phone":"+31 118 634 325",
    "sg:postcode":"4337 KP",
    "sg:province":"Zeeland",
    "wof:name":"Hartzema Assurantien",
    "wof:placetype":"venue"
},
  "geometry": {"coordinates":[3.628645,51.49403],"type":"Point"}
}