{
  "type": "Feature",
  "properties": {
    "iso:country":"NL",
    "sg:address":"Molenberg 2",
    "sg:city":"Reusel",
    "sg:orig_category":"Huishoudapparatuur, Televisies And Radio'S",
    "sg:phone":"+31 497 641 918",
    "sg:postcode":"5541 VW",
    "sg:province":"Noord-Brabant",
    "wof:name":"F. Timmermans",
    "wof:placetype":"venue"
},
  "geometry": {"coordinates":[5.163133,51.365219],"type":"Point"}
}