{
  "type": "Feature",
  "properties": {
    "addr:full":"Wilhelminastraat 39 Roden Provincie Drenthe 9301 AJ",
    "addr:housenumber":"39",
    "addr:postcode":"9301 aj",
    "addr:street":"Wilhelminastraat;Provincie Drenthe",
    "iso:country":"NL",
    "sg:address":"Wilhelminastraat 39",
    "sg:city":"Roden",
    "sg:orig_category":"Kinderkleding",
    "sg:phone":"+31 50 501 0041",
    "sg:postcode":"9301 AJ",
    "sg:province":"Provincie Drenthe",
    "wof:name":"Pico Bello",
    "wof:placetype":"venue"
},
  "geometry": {"coordinates":[6.429937,53.13855],"type":"Point"}
}