{
  "type": "Feature",
  "properties": {
    "iso:country":"NL",
    "sg:address":"Nieuwewg 45A",
    "sg:city":"Hoofddorp",
    "sg:orig_category":"Orthopedische Artikelen",
    "sg:phone":"+31 23 563 9468",
    "sg:postcode":"2132 CL",
    "sg:province":"North Holland",
    "wof:name":"Hoofddorp Orthopedie",
    "wof:placetype":"venue"
},
  "geometry": {"coordinates":[4.6984300613,52.3042068481],"type":"Point"}
}