{
  "type": "Feature",
  "properties": {
    "addr:full":"Beckumerstraat 1 Hengelo Ov Overijssel 7553 VB",
    "addr:housenumber":"1",
    "addr:postcode":"7553 vb",
    "addr:street":"Beckumerstraat;Ov",
    "iso:country":"NL",
    "sg:address":"Beckumerstraat 1",
    "sg:city":"Hengelo Ov",
    "sg:orig_category":"Wegen And Sportterreinen",
    "sg:phone":"+31 74 242 6996",
    "sg:postcode":"7553 VB",
    "sg:province":"Overijssel",
    "wof:name":"E.G.M. Bont",
    "wof:placetype":"venue"
},
  "geometry": {"coordinates":[6.7851967812,52.260219574],"type":"Point"}
}