{
  "type": "Feature",
  "properties": {
    "addr:full":"Heide 5 Panningen Limburg 5981 NX",
    "addr:housenumber":"5",
    "addr:postcode":"5981 nx",
    "addr:street":"Heide",
    "iso:country":"NL",
    "sg:address":"Heide 5",
    "sg:city":"Panningen",
    "sg:orig_category":"Kampeerterreinen",
    "sg:phone":"+31 77 307 2095",
    "sg:postcode":"5981 NX",
    "sg:province":"Limburg",
    "wof:name":"Camping Beringerzand",
    "wof:placetype":"venue"
},
  "geometry": {"coordinates":[5.9602370262,51.3479652405],"type":"Point"}
}