{
  "type": "Feature",
  "properties": {
    "addr:full":"Hoofdstr 44E Kloosterburen Groningen 9977 RE",
    "addr:housenumber":"44e",
    "addr:postcode":"9977 re",
    "addr:street":"Hoofdstr",
    "iso:country":"NL",
    "sg:address":"Hoofdstr 44E",
    "sg:city":"Kloosterburen",
    "sg:orig_category":"Peuterspeelzalen",
    "sg:phone":"+31 595 481 831",
    "sg:postcode":"9977 RE",
    "sg:province":"Groningen",
    "wof:name":"Kruimelnestje, 'T",
    "wof:placetype":"venue"
},
  "geometry": {"coordinates":[6.396575,53.387688],"type":"Point"}
}