{
  "type": "Feature",
  "properties": {
    "addr:full":"Postbus 24 Zuidhorn Groningen 9800 AA",
    "addr:housenumber":"24",
    "addr:postcode":"9800 aa",
    "addr:street":"Postbus",
    "iso:country":"NL",
    "sg:address":"Postbus 24",
    "sg:city":"Zuidhorn",
    "sg:orig_category":"Werving En Selectie",
    "sg:phone":"+31 594 528 809",
    "sg:postcode":"9800 AA",
    "sg:province":"Groningen",
    "sg:website":"http://www.axient.nl",
    "wof:name":"Axient",
    "wof:placetype":"venue"
},
  "geometry": {"coordinates":[6.4079098701,53.2443733215],"type":"Point"}
}