{
  "type": "Feature",
  "properties": {
    "addr:full":"Wormerhoek 14 Capelle A/D Ijssel Zuid-Holland 2905 TX",
    "addr:housenumber":"14;a / d",
    "addr:postcode":"2905 tx",
    "addr:street":"Wormerhoek",
    "iso:country":"NL",
    "sg:address":"Wormerhoek 14",
    "sg:city":"Capelle A/D Ijssel",
    "sg:orig_category":"Boekhouders",
    "sg:phone":"+31 10 442 5522",
    "sg:postcode":"2905 TX",
    "sg:province":"Zuid-Holland",
    "wof:name":"Administratiekantoor De Ijssel Bv",
    "wof:placetype":"venue"
},
  "geometry": {"coordinates":[-100.07679,31.168989],"type":"Point"}
}