{
  "type": "Feature",
  "properties": {
    "addr:full":"Nieuwe Burg 12 Middelburg Zeeland 4331 AH",
    "addr:housenumber":"12",
    "addr:postcode":"4331 ah",
    "addr:street":"Nieuwe Burg",
    "iso:country":"NL",
    "sg:address":"Nieuwe Burg 12",
    "sg:city":"Middelburg",
    "sg:orig_category":"Herenmodezaken",
    "sg:phone":"+31 118 613 481",
    "sg:postcode":"4331 AH",
    "sg:province":"Zeeland",
    "wof:name":"Bijleveld Heren Bv",
    "wof:placetype":"venue"
},
  "geometry": {"coordinates":[3.612995,51.498772],"type":"Point"}
}