{
  "type": "Feature",
  "properties": {
    "addr:full":"Biggekerksestr 8 Koudekerke Zeeland 4371 EZ",
    "addr:housenumber":"8",
    "addr:postcode":"4371 ez",
    "addr:street":"Biggekerksestr",
    "iso:country":"NL",
    "sg:address":"Biggekerksestr 8",
    "sg:city":"Koudekerke",
    "sg:orig_category":"Sportverenigingen En Ontspannings- Verenigingen",
    "sg:phone":"+31 118 551 203",
    "sg:postcode":"4371 EZ",
    "sg:province":"Zeeland",
    "wof:name":"Ltc De Stoof Tennisver",
    "wof:placetype":"venue"
},
  "geometry": {"coordinates":[3.551083,51.485058],"type":"Point"}
}