{
  "type": "Feature",
  "properties": {
    "addr:full":"Heuvel 30 St Oedenrode Noord-Brabant 5492 AD",
    "addr:housenumber":"30",
    "addr:postcode":"5492 ad",
    "addr:street":"Heuvel",
    "iso:country":"NL",
    "sg:address":"Heuvel 30",
    "sg:city":"St Oedenrode",
    "sg:orig_category":"Opticiens",
    "sg:phone":"+31 413 472 720",
    "sg:postcode":"5492 AD",
    "sg:province":"Noord-Brabant",
    "wof:name":"Huiskens",
    "wof:placetype":"venue"
},
  "geometry": {"coordinates":[5.4594740868,51.5628700256],"type":"Point"}
}