{
  "type": "Feature",
  "properties": {
    "addr:full":"Hammarskjoldhof 53 Utrecht Utrecht 3527 HD",
    "addr:housenumber":"53",
    "addr:postcode":"3527 hd",
    "addr:street":"Hammarskjoldhof",
    "iso:country":"NL",
    "sg:address":"Hammarskjoldhof 53",
    "sg:city":"Utrecht",
    "sg:orig_category":"Bijouterie?n",
    "sg:phone":"+31 30 296 7039",
    "sg:postcode":"3527 HD",
    "sg:province":"Utrecht",
    "wof:name":"Trends",
    "wof:placetype":"venue"
},
  "geometry": {"coordinates":[5.093891,52.074291],"type":"Point"}
}