{
  "type": "Feature",
  "properties": {
    "addr:full":"Noordzee 2 A Maassluis South Holland 3144 DB",
    "addr:housenumber":"2 a",
    "addr:postcode":"3144 db",
    "addr:street":"Noordzee",
    "iso:country":"NL",
    "sg:address":"Noordzee 2 A",
    "sg:city":"Maassluis",
    "sg:orig_category":"Boekhouders",
    "sg:phone":"+31 10 592 0018",
    "sg:postcode":"3144 DB",
    "sg:province":"South Holland",
    "wof:name":"Hofman & Ligthart Assurantien Bv",
    "wof:placetype":"venue"
},
  "geometry": {"coordinates":[4.243531,51.917576],"type":"Point"}
}