{
  "type": "Feature",
  "properties": {
    "addr:full":"Ambachtswei 1 Joure Friesland 8501 XA",
    "addr:housenumber":"1",
    "addr:postcode":"8501 xa",
    "addr:street":"Ambachtswei",
    "iso:country":"NL",
    "sg:address":"Ambachtswei 1",
    "sg:city":"Joure",
    "sg:orig_category":"Drukkerijen And Copyshops",
    "sg:phone":"+31 513 413 130",
    "sg:postcode":"8501 XA",
    "sg:province":"Friesland",
    "wof:name":"Framarand Bv",
    "wof:placetype":"venue"
},
  "geometry": {"coordinates":[5.816528,52.964516],"type":"Point"}
}