{
  "type": "Feature",
  "properties": {
    "iso:country":"NL",
    "sg:address":"Dorpsstraat 134",
    "sg:city":"Houten",
    "sg:orig_category":"Kantoorapparatuur Gh",
    "sg:phone":"+31 30 601 9300",
    "sg:postcode":"3991 BZ",
    "sg:province":"Utrecht",
    "wof:name":"Jpi Innovators Bv",
    "wof:placetype":"venue"
},
  "geometry": {"coordinates":[5.1638159752,52.0236587524],"type":"Point"}
}