{
  "type": "Feature",
  "properties": {
    "iso:country":"NL",
    "sg:address":"Puikman 5",
    "sg:city":"Castricum",
    "sg:orig_category":"Boekhouders",
    "sg:phone":"+31 251 670 522",
    "sg:postcode":"1901 NN",
    "sg:province":"North Holland",
    "wof:name":"Compas Administraties",
    "wof:placetype":"venue"
},
  "geometry": {"coordinates":[4.656647,52.545315],"type":"Point"}
}