{
  "type": "Feature",
  "properties": {
    "addr:full":"Wegterswg 14 Hengelo Ov Overijssel 7556 BR",
    "addr:housenumber":"14",
    "addr:postcode":"7556 br",
    "addr:street":"Wegterswg;Ov",
    "iso:country":"NL",
    "sg:address":"Wegterswg 14",
    "sg:city":"Hengelo Ov",
    "sg:orig_category":"Automaterialen En Gereedschappen",
    "sg:phone":"+31 74 250 5043",
    "sg:postcode":"7556 BR",
    "sg:province":"Overijssel",
    "sg:website":"http://www.koskamp.nl",
    "wof:name":"Koskamp Bv",
    "wof:placetype":"venue"
},
  "geometry": {"coordinates":[6.777103,52.276897],"type":"Point"}
}