{
  "type": "Feature",
  "properties": {
    "addr:full":"Pascalstr 20 Heerhugowaard Noord-Holland 1704 RD",
    "addr:housenumber":"20",
    "addr:postcode":"1704 rd",
    "addr:street":"Pascalstr",
    "iso:country":"NL",
    "sg:address":"Pascalstr 20",
    "sg:city":"Heerhugowaard",
    "sg:orig_category":"Koffie-Automaten",
    "sg:phone":"+31 72 575 1751",
    "sg:postcode":"1704 RD",
    "sg:province":"Noord-Holland",
    "sg:website":"http://www.bravilor.com/",
    "wof:name":"Bravilor Bonamat Bv",
    "wof:placetype":"venue"
},
  "geometry": {"coordinates":[4.828183,52.683384],"type":"Point"}
}