{
  "type": "Feature",
  "properties": {
    "addr:full":"Broekakkerstr 2 Nispen Noord-Brabant 4709 PE",
    "addr:housenumber":"2",
    "addr:postcode":"4709 pe",
    "addr:street":"Broekakkerstr",
    "iso:country":"NL",
    "sg:address":"Broekakkerstr 2",
    "sg:city":"Nispen",
    "sg:orig_category":"Makelaars En Adviseurs Onroerende Goederen",
    "sg:phone":"+31 165 364 196",
    "sg:postcode":"4709 PE",
    "sg:province":"Noord-Brabant",
    "wof:name":"Nieuwe Stede Bv, De",
    "wof:placetype":"venue"
},
  "geometry": {"coordinates":[4.46429,51.472492],"type":"Point"}
}