{
  "type": "Feature",
  "properties": {
    "addr:full":"F E Meerburg Sr Kade 38 Katwijk Zh Zuid-Holland 2225 VB",
    "addr:housenumber":"38",
    "addr:postcode":"2225 vb",
    "addr:street":"Sr Kade",
    "iso:country":"NL",
    "sg:address":"F E Meerburg Sr Kade 38",
    "sg:city":"Katwijk Zh",
    "sg:classifiers":[
        {
            "category":"Education",
            "subcategory":"Preschool",
            "type":"Public Place"
        }
    ],
    "sg:phone":"+31 71 401 4467",
    "sg:postcode":"2225 VB",
    "sg:province":"Zuid-Holland",
    "sg:tags":[
        "kleuteronderwijs",
        "basis-"
    ],
    "wof:name":"Gaspard De Colignyschool",
    "wof:placetype":"venue"
},
  "geometry": {"coordinates":[4.396585,52.205109],"type":"Point"}
}