{
  "type": "Feature",
  "properties": {
    "addr:full":"J Heinsstr 26 S Hertogenbosch Noord-Brabant 5211 TD",
    "addr:housenumber":"26",
    "addr:postcode":"5211 td",
    "addr:street":"S",
    "iso:country":"NL",
    "sg:address":"J Heinsstr 26",
    "sg:city":"S Hertogenbosch",
    "sg:orig_category":"Verenigingen En Stichtingen",
    "sg:phone":"+31 73 612 7766",
    "sg:postcode":"5211 TD",
    "sg:province":"Noord-Brabant",
    "sg:website":"http://www.st-jan.nl",
    "wof:name":"Nationaal Monument Sint-Jan, Sticht",
    "wof:placetype":"venue"
},
  "geometry": {"coordinates":[5.302907,51.693069],"type":"Point"}
}