{
  "type": "Feature",
  "properties": {
    "addr:full":"Ulgersmawg 31-33 Groningen Groningen 9731 BK",
    "addr:housenumber":"31-33",
    "addr:postcode":"9731 bk",
    "iso:country":"NL",
    "sg:address":"Ulgersmawg 31-33",
    "sg:city":"Groningen",
    "sg:orig_category":"Verhuur",
    "sg:phone":"+31 50 541 0191",
    "sg:postcode":"9731 BK",
    "sg:province":"Groningen",
    "sg:website":"http://www.hettemaverhuur.nl",
    "wof:name":"Hettema Verhuur",
    "wof:placetype":"venue"
},
  "geometry": {"coordinates":[6.587706,53.233227],"type":"Point"}
}