{
  "type": "Feature",
  "properties": {
    "iso:country":"NL",
    "sg:address":"Kasteel N 124",
    "sg:city":"Helmond",
    "sg:orig_category":"Verenigingen En Stichtingen",
    "sg:phone":"+31 492 542 497",
    "sg:postcode":"5702 NX",
    "sg:province":"North Brabant",
    "wof:name":"Sena Samen En Alleen, Sticht",
    "wof:placetype":"venue"
},
  "geometry": {"coordinates":[5.656077,51.48637],"type":"Point"}
}