{
  "type": "Feature",
  "properties": {
    "addr:full":"Dirk Duivelsweg 5 Alkmaar Noord-Holland 1811 NP",
    "addr:housenumber":"5",
    "addr:postcode":"1811 np",
    "addr:street":"Dirk Duivelsweg",
    "iso:country":"NL",
    "sg:address":"Dirk Duivelsweg 5",
    "sg:city":"Alkmaar",
    "sg:orig_category":"Bloemen And Planten",
    "sg:phone":"+31 72 512 6117",
    "sg:postcode":"1811 NP",
    "sg:province":"Noord-Holland",
    "wof:name":"Vof Bloembinderij Jaap Schipper",
    "wof:placetype":"venue"
},
  "geometry": {"coordinates":[4.753208,52.632118],"type":"Point"}
}