{
  "type": "Feature",
  "properties": {
    "addr:full":"Leliestr 7 Berkel En Rodenrys Zuid-Holland 2651 PV",
    "addr:housenumber":"7",
    "addr:postcode":"2651 pv",
    "addr:street":"Leliestr;Berkel",
    "iso:country":"NL",
    "sg:address":"Leliestr 7",
    "sg:city":"Berkel En Rodenrys",
    "sg:orig_category":"Nagelstudio'S",
    "sg:phone":"+31 10 519 9091",
    "sg:postcode":"2651 PV",
    "sg:province":"Zuid-Holland",
    "wof:name":"Beauty Select",
    "wof:placetype":"venue"
},
  "geometry": {"coordinates":[4.465507,51.981781],"type":"Point"}
}