{
  "type": "Feature",
  "properties": {
    "addr:full":"Hommerterwg 241 Hoensbroek Limburg 6431 EV",
    "addr:housenumber":"241",
    "addr:postcode":"6431 ev",
    "addr:street":"Hoensbroek Limburg",
    "iso:country":"NL",
    "sg:address":"Hommerterwg 241",
    "sg:city":"Hoensbroek",
    "sg:orig_category":"Administratie- En Boekhoudkantoren",
    "sg:phone":"+31 46 442 3235",
    "sg:postcode":"6431 EV",
    "sg:province":"Limburg",
    "wof:name":"Borghmans Bv",
    "wof:placetype":"venue"
},
  "geometry": {"coordinates":[5.921689,50.933598],"type":"Point"}
}