{
  "type": "Feature",
  "properties": {
    "addr:full":"Strausslaan 52 Groningen Groningen 9722 KV",
    "addr:housenumber":"52",
    "addr:postcode":"9722 kv",
    "addr:street":"Strausslaan",
    "iso:country":"NL",
    "sg:address":"Strausslaan 52",
    "sg:city":"Groningen",
    "sg:orig_category":"Paramedische Behandelingen",
    "sg:phone":"+31 50 525 9435",
    "sg:postcode":"9722 KV",
    "sg:province":"Groningen",
    "wof:name":"Verloskundige J. Van Berkum",
    "wof:placetype":"venue"
},
  "geometry": {"coordinates":[6.589951,53.199268],"type":"Point"}
}