{
  "type": "Feature",
  "properties": {
    "addr:full":"Oudlandstr 20 Lage Zwaluwe North Brabant 4926 RD",
    "addr:housenumber":"20",
    "addr:postcode":"4926 rd",
    "addr:street":"Oudlandstr",
    "iso:country":"NL",
    "sg:address":"Oudlandstr 20",
    "sg:city":"Lage Zwaluwe",
    "sg:orig_category":"Administratie- En Boekhoudkantoren",
    "sg:phone":"+31 168 483 572",
    "sg:postcode":"4926 RD",
    "sg:province":"North Brabant",
    "wof:name":"Acr",
    "wof:placetype":"venue"
},
  "geometry": {"coordinates":[4.706553,51.703964],"type":"Point"}
}