{
  "type": "Feature",
  "properties": {
    "addr:full":"P De Hoochwg 115 Rotterdam South Holland 3024 BG",
    "addr:housenumber":"115",
    "addr:postcode":"3024",
    "addr:street":"P",
    "iso:country":"NL",
    "sg:address":"P De Hoochwg 115",
    "sg:city":"Rotterdam",
    "sg:classifiers":[
        {
            "category":"Travel",
            "subcategory":"Hotels & Motels",
            "type":"Entertainment"
        }
    ],
    "sg:phone":"+31 10 476 5277",
    "sg:postcode":"3024 BG",
    "sg:province":"South Holland",
    "wof:name":"Alexander",
    "wof:placetype":"venue"
},
  "geometry": {"coordinates":[4.458908,51.907337],"type":"Point"}
}