{
  "type": "Feature",
  "properties": {
    "addr:full":"Waterpoortsgracht 32 Sneek Friesland 8601 EM",
    "addr:housenumber":"32",
    "addr:postcode":"8601 em",
    "addr:street":"Waterpoortsgracht",
    "iso:country":"NL",
    "sg:address":"Waterpoortsgracht 32",
    "sg:city":"Sneek",
    "sg:orig_category":"Verzekeringen",
    "sg:phone":"+31 515 420 611",
    "sg:postcode":"8601 EM",
    "sg:province":"Friesland",
    "wof:name":"Cees Hiemstra Verzekeringen Sneek",
    "wof:placetype":"venue"
},
  "geometry": {"coordinates":[5.658671,53.029846],"type":"Point"}
}