{
  "type": "Feature",
  "properties": {
    "iso:country":"NL",
    "sg:address":"Pereboom 5",
    "sg:city":"Culemborg",
    "sg:orig_category":"Artsen - Huisartsen",
    "sg:phone":"+31 345 514 110",
    "sg:postcode":"4101 VH",
    "sg:province":"Gelderland",
    "wof:name":"Franken, D C",
    "wof:placetype":"venue"
},
  "geometry": {"coordinates":[5.242793,51.957554],"type":"Point"}
}