{
  "type": "Feature",
  "properties": {
    "addr:full":"Postbus 251 Hillegom Zuid-Holland 2180 AG",
    "addr:housenumber":"251",
    "addr:postcode":"2180",
    "addr:street":"Postbus",
    "iso:country":"NL",
    "sg:address":"Postbus 251",
    "sg:city":"Hillegom",
    "sg:orig_category":"Farmaceutische Industrie En Groothandel",
    "sg:phone":"+31 252 532 366",
    "sg:postcode":"2180 AG",
    "sg:province":"Zuid-Holland",
    "wof:name":"Hexal Pharma Ned Bv",
    "wof:placetype":"venue"
},
  "geometry": {"coordinates":[4.578603,52.290993],"type":"Point"}
}