{
  "type": "Feature",
  "properties": {
    "iso:country":"NL",
    "sg:address":"Kempenaar 2901",
    "sg:city":"Lelystad",
    "sg:orig_category":"Kunsthandel",
    "sg:phone":"+31 320 242 526",
    "sg:postcode":"8231 CW",
    "sg:province":"NL.",
    "wof:name":"Selby",
    "wof:placetype":"venue"
},
  "geometry": {"coordinates":[5.470468,52.516529],"type":"Point"}
}