{
  "type": "Feature",
  "properties": {
    "iso:country":"NL",
    "sg:address":"Grt Houtstr 118",
    "sg:city":"Haarlem",
    "sg:orig_category":"Herenkleding",
    "sg:phone":"+31 23 551 1075",
    "sg:postcode":"2011 ST",
    "sg:province":"Noord-Holland",
    "wof:name":"Robert Mode",
    "wof:placetype":"venue"
},
  "geometry": {"coordinates":[4.631908,52.378139],"type":"Point"}
}