{
  "type": "Feature",
  "properties": {
    "addr:full":"Hessenwg 9 De Bilt Utrecht 3731 JC",
    "addr:housenumber":"9",
    "addr:postcode":"3731 jc",
    "addr:street":"Hessenwg",
    "iso:country":"NL",
    "sg:address":"Hessenwg 9",
    "sg:city":"De Bilt",
    "sg:orig_category":"Kinderkleding - Fabrieken En Groothandel",
    "sg:phone":"+31 30 271 3375",
    "sg:postcode":"3731 JC",
    "sg:province":"Utrecht",
    "sg:website":"http://www.tomtomkids.nl",
    "wof:name":"Jansen En Kids",
    "wof:placetype":"venue"
},
  "geometry": {"coordinates":[5.178377,52.105942],"type":"Point"}
}