{
  "type": "Feature",
  "properties": {
    "addr:full":"Overschiestr 63 Amsterdam Noord-Holland 1062 XD",
    "addr:housenumber":"63",
    "addr:postcode":"1062 xd",
    "addr:street":"Overschiestr",
    "iso:country":"NL",
    "sg:address":"Overschiestr 63",
    "sg:city":"Amsterdam",
    "sg:orig_category":"Grafisch Ontwerpers",
    "sg:phone":"+31 20 669 7405",
    "sg:postcode":"1062 XD",
    "sg:province":"Noord-Holland",
    "sg:website":"http://www.vormedia.nl",
    "wof:name":"Vormedia Marketing & Design",
    "wof:placetype":"venue"
},
  "geometry": {"coordinates":[4.839737,52.344559],"type":"Point"}
}