{
  "type": "Feature",
  "properties": {
    "iso:country":"NL",
    "sg:address":"Kloosterln 41",
    "sg:city":"Sas Van Gent",
    "sg:orig_category":"Koeriersdiensten",
    "sg:phone":"+31 115 460 066",
    "sg:postcode":"4551 BB",
    "sg:province":"Zeeland",
    "wof:name":"Provo, Theo",
    "wof:placetype":"venue"
},
  "geometry": {"coordinates":[3.79839,51.229065],"type":"Point"}
}