{
  "type": "Feature",
  "properties": {
    "addr:full":"Van Oldenbarneveltstraat 138 Rotterdam Zuid-Holland 3012 GW",
    "addr:housenumber":"138",
    "addr:postcode":"3012 gw",
    "addr:street":"Van Oldenbarneveltstraat",
    "iso:country":"NL",
    "sg:address":"Van Oldenbarneveltstraat 138",
    "sg:city":"Rotterdam",
    "sg:orig_category":"Parfum And Cosmetica Gh",
    "sg:phone":"+31 10 213 2280",
    "sg:postcode":"3012 GW",
    "sg:province":"Zuid-Holland",
    "wof:name":"M.B. Estetica",
    "wof:placetype":"venue"
},
  "geometry": {"coordinates":[4.473623,51.918907],"type":"Point"}
}