{
  "type": "Feature",
  "properties": {
    "addr:full":"Kanaalstraat 38 Roden Drenthe 9301 LT",
    "addr:housenumber":"38",
    "addr:postcode":"9301 lt",
    "addr:street":"Kanaalstraat",
    "iso:country":"NL",
    "sg:address":"Kanaalstraat 38",
    "sg:city":"Roden",
    "sg:classifiers":[
        {
            "category":"Education",
            "subcategory":"Preschool",
            "type":"Public Place"
        }
    ],
    "sg:phone":"+31 50 501 9646",
    "sg:postcode":"9301 LT",
    "sg:province":"Drenthe",
    "sg:tags":[
        "kleuteronderwijs",
        "basis-"
    ],
    "wof:name":"Christelijke Basisschool De Haven",
    "wof:placetype":"venue"
},
  "geometry": {"coordinates":[6.43229,53.140663],"type":"Point"}
}