{
  "type": "Feature",
  "properties": {
    "addr:full":"Beukenln 13 Venray Limburg 5802 CJ",
    "addr:housenumber":"13",
    "addr:postcode":"5802 cj",
    "addr:street":"Beukenln",
    "iso:country":"NL",
    "sg:address":"Beukenln 13",
    "sg:city":"Venray",
    "sg:orig_category":"Accountants - Administratie- Consulenten En -Kantoren",
    "sg:phone":"+31 478 569 862",
    "sg:postcode":"5802 CJ",
    "sg:province":"Limburg",
    "wof:name":"Liebrand, F J",
    "wof:placetype":"venue"
},
  "geometry": {"coordinates":[5.981308,51.521976],"type":"Point"}
}