{
  "type": "Feature",
  "properties": {
    "addr:full":"Parkln 43 Bussum Noord-Holland 1405 GP",
    "addr:housenumber":"43",
    "addr:postcode":"1405 gp",
    "addr:street":"Parkln",
    "iso:country":"NL",
    "sg:address":"Parkln 43",
    "sg:city":"Bussum",
    "sg:orig_category":"Wijnkoperijen En -Groothandel",
    "sg:phone":"+31 35 695 2929",
    "sg:postcode":"1405 GP",
    "sg:province":"Noord-Holland",
    "wof:name":"Fourcroy Lenselink Bv",
    "wof:placetype":"venue"
},
  "geometry": {"coordinates":[5.1626048088,52.2768287659],"type":"Point"}
}