{
  "type": "Feature",
  "properties": {
    "addr:full":"Zwartwaterswg 196 Assen Drenthe 9406 NN",
    "addr:housenumber":"196",
    "addr:postcode":"9406 nn",
    "iso:country":"NL",
    "sg:address":"Zwartwaterswg 196",
    "sg:city":"Assen",
    "sg:orig_category":"Administratie- En Boekhoudkantoren",
    "sg:phone":"+31 592 346 487",
    "sg:postcode":"9406 NN",
    "sg:province":"Drenthe",
    "wof:name":"Gerlofsma, R G",
    "wof:placetype":"venue"
},
  "geometry": {"coordinates":[6.55269,53.008453],"type":"Point"}
}