{
  "type": "Feature",
  "properties": {
    "addr:full":"Hoofdwg 114 Slochteren Groningen 9621 AN",
    "addr:housenumber":"114",
    "addr:postcode":"9621 an",
    "iso:country":"NL",
    "sg:address":"Hoofdwg 114",
    "sg:city":"Slochteren",
    "sg:orig_category":"Verzekeringen - Verzekeringskantoren",
    "sg:phone":"+31 598 422 434",
    "sg:postcode":"9621 AN",
    "sg:province":"Groningen",
    "wof:name":"Hartog, H E J",
    "wof:placetype":"venue"
},
  "geometry": {"coordinates":[6.79717,53.207817],"type":"Point"}
}