{
  "type": "Feature",
  "properties": {
    "addr:full":"Parkwykln 88 Almere Flevoland 1326 BT",
    "addr:housenumber":"88",
    "addr:postcode":"1326 bt",
    "addr:street":"Parkwykln;Flevoland",
    "iso:country":"NL",
    "sg:address":"Parkwykln 88",
    "sg:city":"Almere",
    "sg:orig_category":"Psychologen",
    "sg:phone":"+31 36 545 0129",
    "sg:postcode":"1326 BT",
    "sg:province":"Flevoland",
    "wof:name":"Berg, Drs Wil Van Den",
    "wof:placetype":"venue"
},
  "geometry": {"coordinates":[5.24996,52.368961],"type":"Point"}
}