{
  "type": "Feature",
  "properties": {
    "addr:full":"Houttuinln 14 Woerden Utrecht 3447 GM",
    "addr:housenumber":"14",
    "addr:postcode":"3447 gm",
    "addr:street":"Houttuinln",
    "iso:country":"NL",
    "sg:address":"Houttuinln 14",
    "sg:city":"Woerden",
    "sg:orig_category":"Kalenders En Agenda'S",
    "sg:phone":"+31 348 496 020",
    "sg:postcode":"3447 GM",
    "sg:province":"Utrecht",
    "sg:website":"http://www.succes.com",
    "wof:name":"Succes Ryam Trax",
    "wof:placetype":"venue"
},
  "geometry": {"coordinates":[4.8884601593,52.0816612244],"type":"Point"}
}