{
  "type": "Feature",
  "properties": {
    "iso:country":"NL",
    "sg:address":"Postbus 1999",
    "sg:city":"Amsterdam",
    "sg:orig_category":"Beeldende Kunstenaars",
    "sg:phone":"+31 20 684 5176",
    "sg:postcode":"1000 BZ",
    "sg:province":"Noord-Holland",
    "sg:website":"http://www.philbloom.com",
    "wof:name":"Bloom, Phil",
    "wof:placetype":"venue"
},
  "geometry": {"coordinates":[4.89319,52.373119],"type":"Point"}
}