{
  "type": "Feature",
  "properties": {
    "addr:full":"Rembrandtweg 90 Amstelveen North Holland 1181 GW",
    "addr:housenumber":"90",
    "addr:postcode":"1181 gw",
    "addr:street":"Rembrandtweg",
    "iso:country":"NL",
    "sg:address":"Rembrandtweg 90",
    "sg:city":"Amstelveen",
    "sg:orig_category":"Verzekeringen",
    "sg:phone":"+31 20 641 2568",
    "sg:postcode":"1181 GW",
    "sg:province":"North Holland",
    "wof:name":"Tan Assurantien",
    "wof:placetype":"venue"
},
  "geometry": {"coordinates":[4.861631,52.304485],"type":"Point"}
}