{
  "type": "Feature",
  "properties": {
    "addr:full":"Dwarsweg 13 Zaltbommel Gelderland 5301 KB",
    "addr:housenumber":"13",
    "addr:postcode":"5301 kb",
    "addr:street":"Dwarsweg;Gelderland",
    "iso:country":"NL",
    "sg:address":"Dwarsweg 13",
    "sg:city":"Zaltbommel",
    "sg:orig_category":"Chemische Producten Gh",
    "sg:phone":"+31 418 512 139",
    "sg:postcode":"5301 KB",
    "sg:province":"Gelderland",
    "wof:name":"Navara Fibreglass",
    "wof:placetype":"venue"
},
  "geometry": {"coordinates":[5.267414,51.812263],"type":"Point"}
}