{
  "type": "Feature",
  "properties": {
    "iso:country":"NL",
    "sg:address":"Carnisselaan 32",
    "sg:city":"Rotterdam",
    "sg:orig_category":"Gespecialiseerde Voeding",
    "sg:phone":"+31 10 480 6229",
    "sg:postcode":"3083 HJ",
    "sg:province":"South Holland",
    "wof:name":"Oz Dilek Market",
    "wof:placetype":"venue"
},
  "geometry": {"coordinates":[4.478738,51.889584],"type":"Point"}
}