{
  "type": "Feature",
  "properties": {
    "addr:full":"W V Noortstr 138 Utrecht Utrecht 3514 GH",
    "addr:housenumber":"138",
    "addr:postcode":"3514 gh",
    "addr:street":"W V Noortstr",
    "iso:country":"NL",
    "sg:address":"W V Noortstr 138",
    "sg:city":"Utrecht",
    "sg:orig_category":"Adviesbureaus Bedrijfsorganisatie",
    "sg:phone":"+31 30 276 3453",
    "sg:postcode":"3514 GH",
    "sg:province":"Utrecht",
    "sg:website":"http://www.boshouwers.nl",
    "wof:name":"Boshouwers In Core Business",
    "wof:placetype":"venue"
},
  "geometry": {"coordinates":[5.115405,52.088932],"type":"Point"}
}