{
  "type": "Feature",
  "properties": {
    "iso:country":"NL",
    "sg:address":"Willemspln 44-3",
    "sg:city":"Arnhem",
    "sg:orig_category":"Verenigingen En Stichtingen",
    "sg:phone":"+31 26 351 8798",
    "sg:postcode":"6811 KD",
    "sg:province":"Gelderland",
    "wof:name":"Nbvp - Vrouwen Van Nu",
    "wof:placetype":"venue"
},
  "geometry": {"coordinates":[5.906386,51.98365],"type":"Point"}
}