{
  "type": "Feature",
  "properties": {
    "addr:full":"Pr Beatrixln 266 Voorburg Zuid-Holland 2273 XV",
    "addr:housenumber":"266",
    "addr:postcode":"2273 xv",
    "iso:country":"NL",
    "sg:address":"Pr Beatrixln 266",
    "sg:city":"Voorburg",
    "sg:orig_category":"Administratie- En Boekhoudkantoren",
    "sg:phone":"+31 70 387 0705",
    "sg:postcode":"2273 XV",
    "sg:province":"Zuid-Holland",
    "sg:website":"http://www.xs4all.nl/~olym/",
    "wof:name":"Olympia",
    "wof:placetype":"venue"
},
  "geometry": {"coordinates":[4.359539,52.079964],"type":"Point"}
}