{
  "type": "Feature",
  "properties": {
    "addr:full":"Vrankerkerkln 57 Heerlen Limburg 6412 HS",
    "addr:housenumber":"57",
    "addr:postcode":"6412 hs",
    "addr:street":"Vrankerkerkln",
    "iso:country":"NL",
    "sg:address":"Vrankerkerkln 57",
    "sg:city":"Heerlen",
    "sg:orig_category":"Geluidsinstallaties - Verhuur",
    "sg:phone":"+31 45 572 6033",
    "sg:postcode":"6412 HS",
    "sg:province":"Limburg",
    "wof:name":"La",
    "wof:placetype":"venue"
},
  "geometry": {"coordinates":[5.952679,50.903118],"type":"Point"}
}