{
  "type": "Feature",
  "properties": {
    "addr:full":"Steenbergerweg 2 Zuidwolde Dr Drenthe 7921 GE",
    "addr:housenumber":"2",
    "addr:postcode":"7921",
    "addr:street":"Steenbergerweg;Dr",
    "iso:country":"NL",
    "sg:address":"Steenbergerweg 2",
    "sg:city":"Zuidwolde Dr",
    "sg:orig_category":"Herenmodezaken",
    "sg:phone":"+31 528 371 300",
    "sg:postcode":"7921 GE",
    "sg:province":"Drenthe",
    "wof:name":"Vof J.T. Dekker",
    "wof:placetype":"venue"
},
  "geometry": {"coordinates":[6.42853,52.67675],"type":"Point"}
}