{
  "type": "Feature",
  "properties": {
    "addr:full":"Kievitln 64 Goes Zeeland 4461 RB",
    "addr:housenumber":"64",
    "addr:postcode":"4461 rb",
    "addr:street":"Kievitln",
    "iso:country":"NL",
    "sg:address":"Kievitln 64",
    "sg:city":"Goes",
    "sg:orig_category":"Bejaarden - Verzorgingstehuizen",
    "sg:phone":"+31 113 214 210",
    "sg:postcode":"4461 RB",
    "sg:province":"Zeeland",
    "wof:name":"Gasthuis, Zorgcentrum",
    "wof:placetype":"venue"
},
  "geometry": {"coordinates":[-83.914169,39.768833],"type":"Point"}
}