{
  "type": "Feature",
  "properties": {
    "addr:full":"Parkstr 83 S Gravenhage Zuid-Holland 2514 JG",
    "addr:housenumber":"83;gravenhage",
    "addr:postcode":"2514 jg",
    "addr:street":"Parkstr;S",
    "iso:country":"NL",
    "sg:address":"Parkstr 83",
    "sg:city":"S Gravenhage",
    "sg:orig_category":"Adviesbureaus Bedrijfsorganisatie",
    "sg:phone":"+31 70 353 8355",
    "sg:postcode":"2514 JG",
    "sg:province":"Zuid-Holland",
    "sg:website":"http://www.europa-marchand.com",
    "wof:name":"Europa Marchand Inc",
    "wof:placetype":"venue"
},
  "geometry": {"coordinates":[4.30935,52.084148],"type":"Point"}
}