{
  "type": "Feature",
  "properties": {
    "addr:full":"Welsummerwg 13 Dalfsen NL.08 7722 RP",
    "addr:housenumber":"13;nl.08",
    "addr:postcode":"7722",
    "addr:street":"Welsummerwg",
    "iso:country":"NL",
    "sg:address":"Welsummerwg 13",
    "sg:city":"Dalfsen",
    "sg:orig_category":"Woninginrichting",
    "sg:phone":"+31 529 432 866",
    "sg:postcode":"7722 RP",
    "sg:province":"NL.08",
    "wof:name":"Ardesch, J",
    "wof:placetype":"venue"
},
  "geometry": {"coordinates":[6.2665290833,52.5078163147],"type":"Point"}
}