{
  "type": "Feature",
  "properties": {
    "iso:country":"NL",
    "sg:address":"Welsummerwg 13",
    "sg:city":"Dalfsen",
    "sg:orig_category":"Woninginrichting",
    "sg:phone":"+31 529 432 866",
    "sg:postcode":"7722 RP",
    "sg:province":"NL.08",
    "wof:name":"Ardesch, J",
    "wof:placetype":"venue"
},
  "geometry": {"coordinates":[6.2665290833,52.5078163147],"type":"Point"}
}