{
  "type": "Feature",
  "properties": {
    "iso:country":"NL",
    "sg:address":"Hubertusln 20",
    "sg:city":"Breda",
    "sg:orig_category":"Belastingconsulenten/ Belastingadviseurs",
    "sg:phone":"+31 76 561 1252",
    "sg:postcode":"4834 SH",
    "sg:province":"North Brabant",
    "wof:name":"Kars, Drs P M",
    "wof:placetype":"venue"
},
  "geometry": {"coordinates":[4.80125,51.56654],"type":"Point"}
}