{
  "type": "Feature",
  "properties": {
    "iso:country":"NL",
    "sg:address":"V Woustr 193",
    "sg:city":"Amsterdam",
    "sg:orig_category":"Koffie- En Theehuizen",
    "sg:phone":"+31 20 673 2972",
    "sg:postcode":"1074 AN",
    "sg:province":"North Holland",
    "wof:name":"Keeper, De",
    "wof:placetype":"venue"
},
  "geometry": {"coordinates":[4.90494,52.35408],"type":"Point"}
}