{
  "type": "Feature",
  "properties": {
    "addr:full":"Kollenberg 19 Esch Noord-Brabant 5296 LC",
    "addr:housenumber":"19",
    "addr:postcode":"5296 lc",
    "addr:street":"Kollenberg",
    "iso:country":"NL",
    "sg:address":"Kollenberg 19",
    "sg:city":"Esch",
    "sg:orig_category":"Webdesign Bureaus",
    "sg:phone":"+31 411 601 224",
    "sg:postcode":"5296 LC",
    "sg:province":"Noord-Brabant",
    "wof:name":"Wessels, N",
    "wof:placetype":"venue"
},
  "geometry": {"coordinates":[5.2861509323,51.6099624634],"type":"Point"}
}