{
  "type": "Feature",
  "properties": {
    "iso:country":"NL",
    "sg:address":"Iepln 83",
    "sg:city":"S Gravenhage",
    "sg:orig_category":"Psychologen",
    "sg:phone":"+31 70 360 3525",
    "sg:postcode":"2565 LH",
    "sg:province":"South Holland",
    "wof:name":"Bartels, Drs A C",
    "wof:placetype":"venue"
},
  "geometry": {"coordinates":[4.26129,52.076382],"type":"Point"}
}