{
  "type": "Feature",
  "properties": {
    "addr:full":"Laan Van Haagvliet 30 Voorburg Zuid-Holland 2271 XP",
    "addr:housenumber":"30",
    "addr:postcode":"2271 xp",
    "addr:street":"Laan Van Haagvliet",
    "iso:country":"NL",
    "sg:address":"Laan Van Haagvliet 30",
    "sg:city":"Voorburg",
    "sg:orig_category":"Diverse Grafische Activiteiten",
    "sg:phone":"+31 70 386 4591",
    "sg:postcode":"2271 XP",
    "sg:province":"Zuid-Holland",
    "wof:name":"Boekbinderij Verschoor Vof",
    "wof:placetype":"venue"
},
  "geometry": {"coordinates":[4.362609,52.070873],"type":"Point"}
}