{
  "type": "Feature",
  "properties": {
    "addr:full":"Han Hoekstrahof 11 Hoorn Nh Noord-Holland 1628 WR",
    "addr:housenumber":"11",
    "addr:postcode":"1628 wr",
    "addr:street":"Han Hoekstrahof",
    "iso:country":"NL",
    "sg:address":"Han Hoekstrahof 11",
    "sg:city":"Hoorn Nh",
    "sg:orig_category":"Huishoudapparatuur, Televisies And Radio'S",
    "sg:phone":"+31 229 263 573",
    "sg:postcode":"1628 WR",
    "sg:province":"Noord-Holland",
    "wof:name":"Rovu",
    "wof:placetype":"venue"
},
  "geometry": {"coordinates":[5.103327,52.657391],"type":"Point"}
}