{
  "type": "Feature",
  "properties": {
    "iso:country":"NL",
    "sg:address":"Bloemendaalsewg 229",
    "sg:city":"Overveen",
    "sg:orig_category":"Beeldende Kunstenaars",
    "sg:phone":"+31 23 525 7266",
    "sg:postcode":"2051 GC",
    "sg:province":"North Holland",
    "wof:name":"Fokelien Faber",
    "wof:placetype":"venue"
},
  "geometry": {"coordinates":[4.610559,52.394104],"type":"Point"}
}