{
  "type": "Feature",
  "properties": {
    "iso:country":"NL",
    "sg:address":"Myntjeserf 3",
    "sg:city":"Hoogblokland",
    "sg:orig_category":"Administratie- En Boekhoudkantoren",
    "sg:phone":"+31 183 562 288",
    "sg:postcode":"4221 MH",
    "sg:province":"Zuid-Holland",
    "wof:name":"Kievits",
    "wof:placetype":"venue"
},
  "geometry": {"coordinates":[4.972077,51.875381],"type":"Point"}
}