{
  "type": "Feature",
  "properties": {
    "addr:full":"Wilhelminastr 30 Sittard Limburg 6131 KP",
    "addr:housenumber":"30",
    "addr:postcode":"6131 kp",
    "addr:street":"Wilhelminastr",
    "iso:country":"NL",
    "sg:address":"Wilhelminastr 30",
    "sg:city":"Sittard",
    "sg:classifiers":[
        {
            "category":"Professional",
            "subcategory":"Accounting & Tax Preparation",
            "type":"Services"
        }
    ],
    "sg:phone":"+31 46 420 3400",
    "sg:postcode":"6131 KP",
    "sg:province":"Limburg",
    "sg:tags":[
        "accountant",
        "en",
        "-kantoren",
        "register-"
    ],
    "sg:website":"http://www.ey.nl",
    "wof:name":"Ernst & Young",
    "wof:placetype":"venue"
},
  "geometry": {"coordinates":[5.860495,50.999371],"type":"Point"}
}