{
  "type": "Feature",
  "properties": {
    "iso:country":"NL",
    "sg:address":"Hogeweyselaan 151",
    "sg:city":"Weesp",
    "sg:orig_category":"Boekhouders",
    "sg:phone":"+31 294 480 105",
    "sg:postcode":"1382 JK",
    "sg:province":"Noord-Holland",
    "wof:name":"Administratiekantoor Van Arnhem Bv",
    "wof:placetype":"venue"
},
  "geometry": {"coordinates":[5.027086,52.313515],"type":"Point"}
}