{
  "type": "Feature",
  "properties": {
    "addr:full":"Beurtschippershoek 11 Bunnik Utrecht 3981 TB",
    "addr:housenumber":"11",
    "addr:postcode":"3981 tb",
    "addr:street":"Beurtschippershoek",
    "iso:country":"NL",
    "sg:address":"Beurtschippershoek 11",
    "sg:city":"Bunnik",
    "sg:orig_category":"Vertaal- And Tolkenbureaus",
    "sg:phone":"+31 30 656 2458",
    "sg:postcode":"3981 TB",
    "sg:province":"Utrecht",
    "wof:name":"Intertaal-Vertaalbureau",
    "wof:placetype":"venue"
},
  "geometry": {"coordinates":[5.186703,52.06945],"type":"Point"}
}