{
  "type": "Feature",
  "properties": {
    "iso:country":"NL",
    "sg:address":"V Tynstr 9",
    "sg:city":"Naaldwyk",
    "sg:orig_category":"Kappers",
    "sg:phone":"+31 174 625 685",
    "sg:postcode":"2671 GG",
    "sg:province":"South Holland",
    "wof:name":"Elegance",
    "wof:placetype":"venue"
},
  "geometry": {"coordinates":[4.2052488327,51.9913978577],"type":"Point"}
}