{
  "type": "Feature",
  "properties": {
    "addr:full":"V Tynstr 9 Naaldwyk South Holland 2671 GG",
    "addr:housenumber":"9",
    "addr:postcode":"2671 gg",
    "addr:street":"Tynstr",
    "iso:country":"NL",
    "sg:address":"V Tynstr 9",
    "sg:city":"Naaldwyk",
    "sg:orig_category":"Kappers",
    "sg:phone":"+31 174 625 685",
    "sg:postcode":"2671 GG",
    "sg:province":"South Holland",
    "wof:name":"Elegance",
    "wof:placetype":"venue"
},
  "geometry": {"coordinates":[4.2052488327,51.9913978577],"type":"Point"}
}