{
  "type": "Feature",
  "properties": {
    "iso:country":"NL",
    "sg:address":"Parelwegje 1",
    "sg:city":"Middelburg",
    "sg:orig_category":"Kampeerterreinen",
    "sg:phone":"+31 118 626 010",
    "sg:postcode":"4336 AD",
    "sg:province":"Zeeland",
    "wof:name":"Vof Caravanverhuur Van De Boomgaard",
    "wof:placetype":"venue"
},
  "geometry": {"coordinates":[3.6103270054,51.4909439087],"type":"Point"}
}