{
  "type": "Feature",
  "properties": {
    "addr:full":"Postbus 4060 Zutphen Gelderland 7200 BB",
    "addr:postcode":"4060;7200 bb",
    "addr:street":"Postbus",
    "iso:country":"NL",
    "sg:address":"Postbus 4060",
    "sg:city":"Zutphen",
    "sg:orig_category":"Adviesbureaus Bedrijfsorganisatie",
    "sg:phone":"+31 575 570 068",
    "sg:postcode":"7200 BB",
    "sg:province":"Gelderland",
    "sg:website":"http://www.logistiek-op-afroep.nl",
    "wof:name":"Hms",
    "wof:placetype":"venue"
},
  "geometry": {"coordinates":[6.191525,52.140202],"type":"Point"}
}