{
  "type": "Feature",
  "properties": {
    "addr:full":"Ekkersrijt 4040 Eindhoven North Brabant 5692 DA",
    "addr:housenumber":"4040",
    "addr:postcode":"5692 da",
    "addr:street":"Ekkersrijt",
    "iso:country":"NL",
    "sg:address":"Ekkersrijt 4040",
    "sg:city":"Eindhoven",
    "sg:orig_category":"Meubelzaken, Woning- And Keukeninrichting",
    "sg:phone":"+31 499 490 976",
    "sg:postcode":"5692 DA",
    "sg:province":"North Brabant",
    "wof:name":"Leolux",
    "wof:placetype":"venue"
},
  "geometry": {"coordinates":[5.398423,51.473431],"type":"Point"}
}