{
  "type": "Feature",
  "properties": {
    "addr:full":"Fluitenbergseweg 94 Fluitenberg Drenthe 7931 TC",
    "addr:housenumber":"94",
    "addr:postcode":"7931 tc",
    "addr:street":"Fluitenbergseweg",
    "iso:country":"NL",
    "sg:address":"Fluitenbergseweg 94",
    "sg:city":"Fluitenberg",
    "sg:orig_category":"Kampeerterreinen",
    "sg:phone":"+31 528 251 451",
    "sg:postcode":"7931 TC",
    "sg:province":"Drenthe",
    "wof:name":"Vakatieboerderij Sonneclaer",
    "wof:placetype":"venue"
},
  "geometry": {"coordinates":[6.4194931984,52.7237167358],"type":"Point"}
}