{
  "type": "Feature",
  "properties": {
    "addr:full":"Katwoudehof 90 Arnhem Gelderland 6843 BZ",
    "addr:housenumber":"90",
    "addr:postcode":"6843 bz",
    "addr:street":"Katwoudehof",
    "iso:country":"NL",
    "sg:address":"Katwoudehof 90",
    "sg:city":"Arnhem",
    "sg:orig_category":"Parkeergarages",
    "sg:phone":"+31 26 381 8577",
    "sg:postcode":"6843 BZ",
    "sg:province":"Gelderland",
    "wof:name":"Pr Parkeer Realisatie",
    "wof:placetype":"venue"
},
  "geometry": {"coordinates":[5.868765,51.962284],"type":"Point"}
}