{
  "type": "Feature",
  "properties": {
    "addr:full":"Baronieln 258 Breda North Brabant 4837 BH",
    "addr:housenumber":"258",
    "addr:postcode":"4837 bh",
    "iso:country":"NL",
    "sg:address":"Baronieln 258",
    "sg:city":"Breda",
    "sg:orig_category":"Verenigingen En Stichtingen",
    "sg:phone":"+31 76 561 1565",
    "sg:postcode":"4837 BH",
    "sg:province":"North Brabant",
    "wof:name":"Maranathahuis, Sticht",
    "wof:placetype":"venue"
},
  "geometry": {"coordinates":[4.76205,51.56707],"type":"Point"}
}