{
  "type": "Feature",
  "properties": {
    "addr:full":"Patryzenwg 2 Callantsoog North Holland 1759 GD",
    "addr:housenumber":"2",
    "addr:postcode":"1759 gd",
    "addr:street":"Patryzenwg",
    "iso:country":"NL",
    "sg:address":"Patryzenwg 2",
    "sg:city":"Callantsoog",
    "sg:orig_category":"Bejaarden - Verzorgingstehuizen",
    "sg:phone":"+31 224 581 944",
    "sg:postcode":"1759 GD",
    "sg:province":"North Holland",
    "wof:name":"Huys Ten Oghe",
    "wof:placetype":"venue"
},
  "geometry": {"coordinates":[4.697063,52.837574],"type":"Point"}
}