{
  "type": "Feature",
  "properties": {
    "addr:full":"Jan Vermeerstraat 11 Meppel Drenthe 7944 BV",
    "addr:housenumber":"11",
    "addr:postcode":"7944 bv",
    "addr:street":"Jan Vermeerstraat",
    "iso:country":"NL",
    "sg:address":"Jan Vermeerstraat 11",
    "sg:city":"Meppel",
    "sg:orig_category":"Boekenuitgeverijen",
    "sg:phone":"+31 522 254 286",
    "sg:postcode":"7944 BV",
    "sg:province":"Drenthe",
    "wof:name":"Feniks Pers Bv",
    "wof:placetype":"venue"
},
  "geometry": {"coordinates":[6.18463,52.684917],"type":"Point"}
}