{
  "type": "Feature",
  "properties": {
    "addr:full":"Koninginneweg 93 Lisse North Holland 2161 ZB",
    "addr:housenumber":"93",
    "addr:postcode":"2161 zb",
    "addr:street":"Koninginneweg",
    "iso:country":"NL",
    "sg:address":"Koninginneweg 93",
    "sg:city":"Lisse",
    "sg:orig_category":"Verlichting And Huishoudartikelen",
    "sg:phone":"+31 252 420 276",
    "sg:postcode":"2161 ZB",
    "sg:province":"North Holland",
    "wof:name":"Interieur Service Lisse",
    "wof:placetype":"venue"
},
  "geometry": {"coordinates":[4.559604,52.260021],"type":"Point"}
}