{
  "type": "Feature",
  "properties": {
    "iso:country":"NL",
    "sg:address":"Nieuwendammerdk 44",
    "sg:city":"Amsterdam",
    "sg:orig_category":"Psychotherapeuten",
    "sg:phone":"+31 20 636 7260",
    "sg:postcode":"1025 LN",
    "sg:province":"Noord-Holland",
    "wof:name":"Jong, Ds B De",
    "wof:placetype":"venue"
},
  "geometry": {"coordinates":[4.927572,52.391132],"type":"Point"}
}