{
  "type": "Feature",
  "properties": {
    "iso:country":"NL",
    "sg:address":"Noordelijke Dwarsweg 99",
    "sg:city":"Zevenhuizen Zh",
    "sg:orig_category":"Hoefdierhouderijen",
    "sg:phone":"+31 180 631 853",
    "sg:postcode":"2761 GD",
    "sg:province":"Zuid-Holland",
    "wof:name":"J.G. Van Asch",
    "wof:placetype":"venue"
},
  "geometry": {"coordinates":[4.599703,52.019905],"type":"Point"}
}