{
  "type": "Feature",
  "properties": {
    "addr:full":"Poolmansweg 130 Enschede NL.08 7545 LV",
    "addr:housenumber":"130",
    "addr:postcode":"7545",
    "addr:street":"Poolmansweg",
    "iso:country":"NL",
    "sg:address":"Poolmansweg 130",
    "sg:city":"Enschede",
    "sg:orig_category":"Loodgieterswerk, Verwarming And Sanitaire Installaties",
    "sg:phone":"+31 53 431 0784",
    "sg:postcode":"7545 LV",
    "sg:province":"NL.08",
    "wof:name":"Feenstra Oost Bv",
    "wof:placetype":"venue"
},
  "geometry": {"coordinates":[6.866307,52.2178],"type":"Point"}
}