{
  "type": "Feature",
  "properties": {
    "addr:full":"Groep Welterhof 17 Almere NL. 1318 CN",
    "addr:housenumber":"17",
    "addr:postcode":"1318 cn",
    "addr:street":"Groep Welterhof;Nl.",
    "iso:country":"NL",
    "sg:address":"Groep Welterhof 17",
    "sg:city":"Almere",
    "sg:orig_category":"Adviesbureaus Bouwkunde",
    "sg:phone":"+31 36 537 3236",
    "sg:postcode":"1318 CN",
    "sg:province":"NL.",
    "wof:name":"Wdg",
    "wof:placetype":"venue"
},
  "geometry": {"coordinates":[5.244963,52.379417],"type":"Point"}
}