{
  "type": "Feature",
  "properties": {
    "addr:full":"Past Geenenstr 5 Baarlo Lb Limburg 5991 BH",
    "addr:housenumber":"5",
    "addr:postcode":"lb;5991 bh",
    "iso:country":"NL",
    "sg:address":"Past Geenenstr 5",
    "sg:city":"Baarlo Lb",
    "sg:orig_category":"Gehandicapteninformatie",
    "sg:phone":"+31 77 477 2820",
    "sg:postcode":"5991 BH",
    "sg:province":"Limburg",
    "wof:name":"Gehandicaptenzorg Limburg, Sticht",
    "wof:placetype":"venue"
},
  "geometry": {"coordinates":[6.099167,51.33292],"type":"Point"}
}