{
  "type": "Feature",
  "properties": {
    "iso:country":"NL",
    "sg:address":"Albinonistr 1",
    "sg:city":"Boxtel",
    "sg:orig_category":"Schilders",
    "sg:phone":"+31 411 673 509",
    "sg:postcode":"5283 KL",
    "sg:province":"Noord-Brabant",
    "wof:name":"Melis",
    "wof:placetype":"venue"
},
  "geometry": {"coordinates":[5.34486,51.584648],"type":"Point"}
}