{
  "type": "Feature",
  "properties": {
    "addr:full":"Barteljorisstr 1 Haarlem Noord-Holland 2011 RA",
    "addr:housenumber":"1",
    "addr:postcode":"2011 ra",
    "addr:street":"Barteljorisstr",
    "iso:country":"NL",
    "sg:address":"Barteljorisstr 1",
    "sg:city":"Haarlem",
    "sg:orig_category":"Juweliers",
    "sg:phone":"+31 23 532 0300",
    "sg:postcode":"2011 RA",
    "sg:province":"Noord-Holland",
    "wof:name":"Driessen Juweliers",
    "wof:placetype":"venue"
},
  "geometry": {"coordinates":[4.635337,52.382786],"type":"Point"}
}