{
  "type": "Feature",
  "properties": {
    "addr:full":"Oranjeln 40 Amersfoort Utrecht 3818 GR",
    "addr:housenumber":"40",
    "addr:postcode":"3818",
    "addr:street":"Oranjeln",
    "iso:country":"NL",
    "sg:address":"Oranjeln 40",
    "sg:city":"Amersfoort",
    "sg:orig_category":"Adviesbureaus Personeel",
    "sg:phone":"+31 33 494 4810",
    "sg:postcode":"3818 GR",
    "sg:province":"Utrecht",
    "wof:name":"Gustap",
    "wof:placetype":"venue"
},
  "geometry": {"coordinates":[5.361447,52.145622],"type":"Point"}
}