{
  "type": "Feature",
  "properties": {
    "addr:full":"Kerkwg 1 Cothen Utrecht 3945 BM",
    "addr:housenumber":"1",
    "addr:postcode":"3945 bm",
    "addr:street":"Kerkwg",
    "iso:country":"NL",
    "sg:address":"Kerkwg 1",
    "sg:city":"Cothen",
    "sg:classifiers":[
        {
            "category":"Retail",
            "subcategory":"Auto Repair",
            "type":"Services"
        }
    ],
    "sg:phone":"+31 343 562 444",
    "sg:postcode":"3945 BM",
    "sg:province":"Utrecht",
    "sg:tags":[
        "garage"
    ],
    "wof:name":"Stooker Bv",
    "wof:placetype":"venue"
},
  "geometry": {"coordinates":[5.31158,51.99876],"type":"Point"}
}