{
  "type": "Feature",
  "properties": {
    "addr:full":"Edisonstr 33A Reeuwyk South Holland 2811 EM",
    "addr:housenumber":"33a",
    "addr:postcode":"2811 em",
    "addr:street":"Edisonstr",
    "iso:country":"NL",
    "sg:address":"Edisonstr 33A",
    "sg:city":"Reeuwyk",
    "sg:orig_category":"Jachthavens - Jachtwerven",
    "sg:phone":"+31 6 18515781",
    "sg:postcode":"2811 EM",
    "sg:province":"South Holland",
    "wof:name":"Zijp, Thom Van",
    "wof:placetype":"venue"
},
  "geometry": {"coordinates":[4.71765,52.039661],"type":"Point"}
}