{
  "type": "Feature",
  "properties": {
    "addr:full":"V Andelstr 7 Steenbergen Nb North Brabant 4651 TA",
    "addr:housenumber":"7;nb",
    "addr:postcode":"4651 ta",
    "addr:street":"Andelstr",
    "iso:country":"NL",
    "sg:address":"V Andelstr 7",
    "sg:city":"Steenbergen Nb",
    "sg:orig_category":"Non-Classified Establishments",
    "sg:phone":"+31 167 566 984",
    "sg:postcode":"4651 TA",
    "sg:province":"North Brabant",
    "sg:website":"http://www.econoclean.nl",
    "wof:name":"Engineering Chemicals Bv",
    "wof:placetype":"venue"
},
  "geometry": {"coordinates":[4.314555,51.585594],"type":"Point"}
}