{
  "type": "Feature",
  "properties": {
    "addr:full":"Borchwerf 40A Roosendaal Noord-Brabant 4704 RG",
    "addr:housenumber":"40a",
    "addr:postcode":"4704 rg",
    "addr:street":"Borchwerf",
    "iso:country":"NL",
    "sg:address":"Borchwerf 40A",
    "sg:city":"Roosendaal",
    "sg:orig_category":"Autoschade- Herstelbedrijven",
    "sg:phone":"+31 165 395 996",
    "sg:postcode":"4704 RG",
    "sg:province":"Noord-Brabant",
    "wof:name":"Care Schadeservice Roosendaal Bv",
    "wof:placetype":"venue"
},
  "geometry": {"coordinates":[4.472752,51.555599],"type":"Point"}
}