{
  "type": "Feature",
  "properties": {
    "addr:full":"Beuningstraat 3 Wageningen Gelderland 6701 AW",
    "addr:housenumber":"3",
    "addr:postcode":"6701 aw",
    "addr:street":"Beuningstraat;Gelderland",
    "iso:country":"NL",
    "sg:address":"Beuningstraat 3",
    "sg:city":"Wageningen",
    "sg:classifiers":[
        {
            "category":"Shopping",
            "subcategory":"Gifts & Souvenirs",
            "type":"Retail Goods"
        }
    ],
    "sg:phone":"+31 317 415 957",
    "sg:postcode":"6701 AW",
    "sg:province":"Gelderland",
    "sg:tags":[
        "geschenken"
    ],
    "wof:name":"Tjonge Jonge Kadoshop",
    "wof:placetype":"venue"
},
  "geometry": {"coordinates":[5.663106,51.966549],"type":"Point"}
}