{
  "type": "Feature",
  "properties": {
    "iso:country":"NL",
    "sg:address":"Eindhovensewg 54",
    "sg:city":"Waalre",
    "sg:orig_category":"Fietsen En Bromfietsen",
    "sg:phone":"+31 40 221 8054",
    "sg:postcode":"5582 HT",
    "sg:province":"North Brabant",
    "wof:name":"Azzuri Wielersport",
    "wof:placetype":"venue"
},
  "geometry": {"coordinates":[5.476679,51.395325],"type":"Point"}
}