{
  "type": "Feature",
  "properties": {
    "addr:full":"Amperestr 36 Badhoevedorp Noord-Holland 1171 BV",
    "addr:housenumber":"36",
    "addr:postcode":"1171 bv",
    "addr:street":"Amperestr",
    "iso:country":"NL",
    "sg:address":"Amperestr 36",
    "sg:city":"Badhoevedorp",
    "sg:orig_category":"Adviesbureaus",
    "sg:phone":"+31 20 659 3492",
    "sg:postcode":"1171 BV",
    "sg:province":"Noord-Holland",
    "wof:name":"Ts",
    "wof:placetype":"venue"
},
  "geometry": {"coordinates":[4.776319,52.336823],"type":"Point"}
}