{
  "type": "Feature",
  "properties": {
    "addr:full":"Weerdslag 60 Zutphen Gelderland 7206 BT",
    "addr:housenumber":"60",
    "addr:postcode":"7206 bt",
    "addr:street":"Weerdslag;Gelderland",
    "iso:country":"NL",
    "sg:address":"Weerdslag 60",
    "sg:city":"Zutphen",
    "sg:orig_category":"Verenigingen En Stichtingen",
    "sg:phone":"+31 575 573 900",
    "sg:postcode":"7206 BT",
    "sg:province":"Gelderland",
    "wof:name":"Worm",
    "wof:placetype":"venue"
},
  "geometry": {"coordinates":[6.194873,52.126732],"type":"Point"}
}