{
  "type": "Feature",
  "properties": {
    "iso:country":"NL",
    "sg:address":"Pauwhof 160",
    "sg:city":"Rijswijk Zh",
    "sg:orig_category":"Adviesbureaus Automatisering",
    "sg:phone":"+31 6 24748829",
    "sg:postcode":"2289 BL",
    "sg:province":"Zuid-Holland",
    "sg:website":"http://www.infinit-it.nl",
    "wof:name":"Infinit Vof",
    "wof:placetype":"venue"
},
  "geometry": {"coordinates":[4.348454,52.023697],"type":"Point"}
}