{
  "type": "Feature",
  "properties": {
    "addr:full":"Naarderstr 12-14 Laren Nh North Holland 1251 BB",
    "addr:housenumber":"12-14",
    "addr:postcode":"1251 bb",
    "addr:street":"Nh North",
    "iso:country":"NL",
    "sg:address":"Naarderstr 12-14",
    "sg:city":"Laren Nh",
    "sg:classifiers":[
        {
            "category":"Wholesale",
            "subcategory":"Meat",
            "type":"Manufacturing & Wholesale Goods"
        }
    ],
    "sg:phone":"+31 35 539 5303",
    "sg:postcode":"1251 BB",
    "sg:province":"North Holland",
    "sg:tags":[
        "hang-",
        "sluitwerk",
        "en"
    ],
    "sg:website":"http://www.kerkhoflaren.nl",
    "wof:name":"Kerkhof Laren Bv",
    "wof:placetype":"venue"
},
  "geometry": {"coordinates":[5.223717,52.257671],"type":"Point"}
}