{
  "type": "Feature",
  "properties": {
    "addr:full":"Koningin Julianalaan 353 Voorburg Zuid-Holland 2273 JJ",
    "addr:housenumber":"353",
    "addr:postcode":"2273 jj",
    "addr:street":"Koningin Julianalaan",
    "iso:country":"NL",
    "sg:address":"Koningin Julianalaan 353",
    "sg:city":"Voorburg",
    "sg:orig_category":"Banken And Kredietinstellingen",
    "sg:phone":"+31 70 386 7474",
    "sg:postcode":"2273 JJ",
    "sg:province":"Zuid-Holland",
    "wof:name":"Abn Amro",
    "wof:placetype":"venue"
},
  "geometry": {"coordinates":[4.360489,52.074745],"type":"Point"}
}