{
  "type": "Feature",
  "properties": {
    "iso:country":"NL",
    "sg:address":"K Doormanwg 31",
    "sg:city":"Schiedam",
    "sg:orig_category":"Onroerende Goederen",
    "sg:phone":"+31 10 426 4930",
    "sg:postcode":"3115 JD",
    "sg:province":"South Holland",
    "sg:website":"http://www.vdtempel.nl",
    "wof:name":"Tempel Bv, Van Den",
    "wof:placetype":"venue"
},
  "geometry": {"coordinates":[4.372861,51.907291],"type":"Point"}
}