{
  "type": "Feature",
  "properties": {
    "addr:full":"Hoefweg 142 Bleiswijk Zuid-Holland 2665 LC",
    "addr:housenumber":"142",
    "addr:postcode":"2665 lc",
    "addr:street":"Hoefweg",
    "iso:country":"NL",
    "sg:address":"Hoefweg 142",
    "sg:city":"Bleiswijk",
    "sg:orig_category":"Goederenvervoer Over De Weg",
    "sg:phone":"+31 10 521 5750",
    "sg:postcode":"2665 LC",
    "sg:province":"Zuid-Holland",
    "wof:name":"De Wilde Transport Bv",
    "wof:placetype":"venue"
},
  "geometry": {"coordinates":[4.534747,52.021301],"type":"Point"}
}