{
  "type": "Feature",
  "properties": {
    "addr:full":"Oosteinde 8 Marknesse Flevoland 8316 BL",
    "addr:housenumber":"8",
    "addr:postcode":"8316 bl",
    "addr:street":"Oosteinde;Flevoland",
    "iso:country":"NL",
    "sg:address":"Oosteinde 8",
    "sg:city":"Marknesse",
    "sg:orig_category":"Artsen - Huisartsen",
    "sg:phone":"+31 527 203 000",
    "sg:postcode":"8316 BL",
    "sg:province":"Flevoland",
    "wof:name":"Rijken, A M",
    "wof:placetype":"venue"
},
  "geometry": {"coordinates":[5.866384,52.710953],"type":"Point"}
}