{
  "type": "Feature",
  "properties": {
    "iso:country":"NL",
    "sg:address":"Merelln 14",
    "sg:city":"Bilthoven",
    "sg:classifiers":[
        {
            "category":"Personal",
            "subcategory":"Nail Salon",
            "type":"Services"
        }
    ],
    "sg:phone":"+31 30 228 6651",
    "sg:postcode":"3722 AL",
    "sg:province":"Utrecht",
    "sg:tags":[
        "pedicure"
    ],
    "wof:name":"Post-Ott, M",
    "wof:placetype":"venue"
},
  "geometry": {"coordinates":[5.21093,52.121498],"type":"Point"}
}