{
  "type": "Feature",
  "properties": {
    "iso:country":"NL",
    "sg:address":"Zuideinde 165B",
    "sg:city":"Oostzaan",
    "sg:orig_category":"Geluidsopnamen",
    "sg:phone":"+31 75 684 2385",
    "sg:postcode":"1511 GD",
    "sg:province":"Noord-Holland",
    "wof:name":"Harmony Sound",
    "wof:placetype":"venue"
},
  "geometry": {"coordinates":[4.881766,52.432312],"type":"Point"}
}