{
  "type": "Feature",
  "properties": {
    "addr:full":"Leidsegr 66 Amsterdam Noord-Holland 1016 CP",
    "addr:housenumber":"66",
    "addr:postcode":"1016 cp",
    "addr:street":"Leidsegr",
    "iso:country":"NL",
    "sg:address":"Leidsegr 66",
    "sg:city":"Amsterdam",
    "sg:orig_category":"Bloemen En Planten - Decoratie",
    "sg:phone":"+31 20 627 4416",
    "sg:postcode":"1016 CP",
    "sg:province":"Noord-Holland",
    "wof:name":"Bouquetterie",
    "wof:placetype":"venue"
},
  "geometry": {"coordinates":[4.883096,52.366558],"type":"Point"}
}