{
  "type": "Feature",
  "properties": {
    "addr:full":"Broeklaan 45 Tegelen Limburg 5931 KN",
    "addr:housenumber":"45",
    "addr:postcode":"5931 kn",
    "addr:street":"Broeklaan",
    "iso:country":"NL",
    "sg:address":"Broeklaan 45",
    "sg:city":"Tegelen",
    "sg:orig_category":"Kappers",
    "sg:phone":"+31 77 373 0818",
    "sg:postcode":"5931 KN",
    "sg:province":"Limburg",
    "wof:name":"A.E. Denessen",
    "wof:placetype":"venue"
},
  "geometry": {"coordinates":[6.1465277672,51.3469047546],"type":"Point"}
}