{
  "type": "Feature",
  "properties": {
    "addr:full":"Reigerskamp 390 Maarssen Utrecht 3607 HX",
    "addr:housenumber":"390",
    "addr:postcode":"3607 hx",
    "addr:street":"Reigerskamp",
    "iso:country":"NL",
    "sg:address":"Reigerskamp 390",
    "sg:city":"Maarssen",
    "sg:orig_category":"Adviesbureaus Automatisering",
    "sg:phone":"+31 346 579 232",
    "sg:postcode":"3607 HX",
    "sg:province":"Utrecht",
    "wof:name":"Wubs Holding Bv",
    "wof:placetype":"venue"
},
  "geometry": {"coordinates":[5.015251,52.133858],"type":"Point"}
}