{
  "type": "Feature",
  "properties": {
    "addr:full":"Van Wijngaardenlaan 1 Rotterdam Zuid-Holland 3078 JP",
    "addr:housenumber":"1",
    "addr:postcode":"3078 jp",
    "addr:street":"Van Wijngaardenlaan",
    "iso:country":"NL",
    "sg:address":"Van Wijngaardenlaan 1",
    "sg:city":"Rotterdam",
    "sg:classifiers":[
        {
            "category":"Education",
            "subcategory":"Preschool",
            "type":"Public Place"
        }
    ],
    "sg:phone":"+31 10 483 5036",
    "sg:postcode":"3078 JP",
    "sg:province":"Zuid-Holland",
    "sg:tags":[
        "kleuteronderwijs",
        "basis-"
    ],
    "wof:name":"Groene De Palm",
    "wof:placetype":"venue"
},
  "geometry": {"coordinates":[4.544807,51.893837],"type":"Point"}
}