{
  "type": "Feature",
  "properties": {
    "addr:full":"St Annaln 13 Maastricht Limburg 6214 AA",
    "addr:housenumber":"13",
    "addr:postcode":"6214 aa",
    "iso:country":"NL",
    "sg:address":"St Annaln 13",
    "sg:city":"Maastricht",
    "sg:classifiers":[
        {
            "category":"Food & Beverages",
            "subcategory":"Bakery",
            "type":"Retail Goods"
        }
    ],
    "sg:phone":"+31 43 358 1045",
    "sg:postcode":"6214 AA",
    "sg:province":"Limburg",
    "sg:tags":[
        "pizza"
    ],
    "sg:website":"http://www.dominos.nl",
    "wof:name":"Domino",
    "wof:placetype":"venue"
},
  "geometry": {"coordinates":[5.672786,50.848454],"type":"Point"}
}