{
  "type": "Feature",
  "properties": {
    "addr:full":"De Zwaaikom 12A Veendam Groningen 9641 KV",
    "addr:housenumber":"12a",
    "addr:postcode":"9641 kv",
    "addr:street":"De Zwaaikom",
    "iso:country":"NL",
    "sg:address":"De Zwaaikom 12A",
    "sg:city":"Veendam",
    "sg:orig_category":"Kunststoffen- Verwerkende Industrie",
    "sg:phone":"+31 598 628 278",
    "sg:postcode":"9641 KV",
    "sg:province":"Groningen",
    "wof:name":"Drenth Perserij Vof",
    "wof:placetype":"venue"
},
  "geometry": {"coordinates":[6.894445,53.102009],"type":"Point"}
}