{
  "type": "Feature",
  "properties": {
    "iso:country":"NL",
    "sg:address":"John Davisstraat 1",
    "sg:city":"Geldrop",
    "sg:classifiers":[
        {
            "category":"Education",
            "subcategory":"Preschool",
            "type":"Public Place"
        }
    ],
    "sg:phone":"+31 40 280 1790",
    "sg:postcode":"5665 GC",
    "sg:province":"North Brabant",
    "sg:tags":[
        "kleuteronderwijs",
        "basis-"
    ],
    "wof:name":"Nutsschool De Regenboog",
    "wof:placetype":"venue"
},
  "geometry": {"coordinates":[5.575971,51.418236],"type":"Point"}
}