{
  "type": "Feature",
  "properties": {
    "iso:country":"NL",
    "sg:address":"Spekkeln 10",
    "sg:city":"Lisse",
    "sg:orig_category":"Sportverenigingen En Ontspannings- Verenigingen",
    "sg:phone":"+31 252 418 226",
    "sg:postcode":"2161 GH",
    "sg:province":"Zuid-Holland",
    "wof:name":"Flags, Honk- En Softbalver The",
    "wof:placetype":"venue"
},
  "geometry": {"coordinates":[4.552546,52.257221],"type":"Point"}
}