{
  "type": "Feature",
  "properties": {
    "addr:full":"Pim Mulierwei 34 Stiens Friesland 9051 KA",
    "addr:housenumber":"34",
    "addr:postcode":"9051 ka",
    "addr:street":"Pim Mulierwei",
    "iso:country":"NL",
    "sg:address":"Pim Mulierwei 34",
    "sg:city":"Stiens",
    "sg:orig_category":"Verzekeringen",
    "sg:phone":"+31 58 257 1953",
    "sg:postcode":"9051 KA",
    "sg:province":"Friesland",
    "wof:name":"Context Verzekeringen",
    "wof:placetype":"venue"
},
  "geometry": {"coordinates":[5.773979,53.26001],"type":"Point"}
}