{
  "type": "Feature",
  "properties": {
    "addr:full":"Ambachtsmark 27 Almere Flevoland 1355 EB",
    "addr:housenumber":"27",
    "addr:postcode":"1355 eb",
    "addr:street":"Ambachtsmark;Flevoland",
    "iso:country":"NL",
    "sg:address":"Ambachtsmark 27",
    "sg:city":"Almere",
    "sg:orig_category":"Stukadoorsbedrijven",
    "sg:phone":"+31 36 531 9327",
    "sg:postcode":"1355 EB",
    "sg:province":"Flevoland",
    "wof:name":"Flevogips",
    "wof:placetype":"venue"
},
  "geometry": {"coordinates":[5.225409,52.342495],"type":"Point"}
}