{
  "type": "Feature",
  "properties": {
    "addr:full":"Zwaerdecroonstr 64A Rotterdam Zuid-Holland 3021 WX",
    "addr:housenumber":"64a",
    "addr:postcode":"3021 wx",
    "addr:street":"Zwaerdecroonstr",
    "iso:country":"NL",
    "sg:address":"Zwaerdecroonstr 64A",
    "sg:city":"Rotterdam",
    "sg:orig_category":"Beeldende Kunstenaars",
    "sg:phone":"+31 10 477 9780",
    "sg:postcode":"3021 WX",
    "sg:province":"Zuid-Holland",
    "wof:name":"Ewijk, M A Van",
    "wof:placetype":"venue"
},
  "geometry": {"coordinates":[4.460676,51.912395],"type":"Point"}
}