{
  "type": "Feature",
  "properties": {
    "addr:full":"Marktstr 9 Hengelo Ov Overijssel 7551 DR",
    "addr:housenumber":"9",
    "addr:postcode":"7551 dr",
    "addr:street":"Marktstr;Ov",
    "iso:country":"NL",
    "sg:address":"Marktstr 9",
    "sg:city":"Hengelo Ov",
    "sg:orig_category":"Wijnkoperijen En -Groothandel",
    "sg:phone":"+31 74 291 2483",
    "sg:postcode":"7551 DR",
    "sg:province":"Overijssel",
    "wof:name":"Walhof",
    "wof:placetype":"venue"
},
  "geometry": {"coordinates":[6.7918381691,52.2647743225],"type":"Point"}
}