{
  "type": "Feature",
  "properties": {
    "addr:full":"Vondelstraat 56 Amsterdam Noord-Holland 1054 GE",
    "addr:housenumber":"56",
    "addr:postcode":"1054",
    "addr:street":"Vondelstraat",
    "iso:country":"NL",
    "sg:address":"Vondelstraat 56",
    "sg:city":"Amsterdam",
    "sg:orig_category":"Kinderopvang Behalve Thuis",
    "sg:phone":"+31 20 612 6944",
    "sg:postcode":"1054 GE",
    "sg:province":"Noord-Holland",
    "wof:name":"Stichting Welzijn Oud-West",
    "wof:placetype":"venue"
},
  "geometry": {"coordinates":[4.87657,52.362217],"type":"Point"}
}