{
  "type": "Feature",
  "properties": {
    "iso:country":"NL",
    "sg:address":"Diepenveensewg 1A",
    "sg:city":"Olst",
    "sg:orig_category":"Adviesbureaus",
    "sg:phone":"+31 570 564 401",
    "sg:postcode":"8121 DV",
    "sg:province":"Overijssel",
    "wof:name":"Sts",
    "wof:placetype":"venue"
},
  "geometry": {"coordinates":[6.122897,52.323547],"type":"Point"}
}