{
  "type": "Feature",
  "properties": {
    "addr:full":"Keizerstr 14 Montfoort Utrecht 3417 EB",
    "addr:housenumber":"14",
    "addr:postcode":"3417 eb",
    "addr:street":"Keizerstr",
    "iso:country":"NL",
    "sg:address":"Keizerstr 14",
    "sg:city":"Montfoort",
    "sg:orig_category":"Makelaars En Adviseurs Onroerende Goederen",
    "sg:phone":"+31 348 471 220",
    "sg:postcode":"3417 EB",
    "sg:province":"Utrecht",
    "sg:website":"http://www.vbo.nl",
    "wof:name":"Wissel, De",
    "wof:placetype":"venue"
},
  "geometry": {"coordinates":[4.9499,52.045685],"type":"Point"}
}