{
  "type": "Feature",
  "properties": {
    "addr:full":"Kreekwg 10 Dordrecht South Holland 3316 BD",
    "addr:housenumber":"10",
    "addr:postcode":"3316 bd",
    "addr:street":"Kreekwg",
    "iso:country":"NL",
    "sg:address":"Kreekwg 10",
    "sg:city":"Dordrecht",
    "sg:orig_category":"Levensmiddelen - Fabrieken En Groothandel",
    "sg:phone":"+31 78 617 7586",
    "sg:postcode":"3316 BD",
    "sg:province":"South Holland",
    "wof:name":"Int Rice",
    "wof:placetype":"venue"
},
  "geometry": {"coordinates":[4.64133,51.788181],"type":"Point"}
}