{
  "type": "Feature",
  "properties": {
    "addr:full":"Edo Jongamastraat 133 Sneek Friesland 8602 VW",
    "addr:housenumber":"133",
    "addr:postcode":"8602 vw",
    "addr:street":"Edo Jongamastraat",
    "iso:country":"NL",
    "sg:address":"Edo Jongamastraat 133",
    "sg:city":"Sneek",
    "sg:classifiers":[
        {
            "category":"Recreation",
            "subcategory":"Amusement Park",
            "type":"Entertainment"
        }
    ],
    "sg:phone":"+31 6 25556454",
    "sg:postcode":"8602 VW",
    "sg:province":"Friesland",
    "wof:name":"Pirve Producties",
    "wof:placetype":"venue"
},
  "geometry": {"coordinates":[5.659224,53.042294],"type":"Point"}
}