{
  "type": "Feature",
  "properties": {
    "addr:full":"St Theresiastr 4 Eindhoven Noord-Brabant 5652 ET",
    "addr:housenumber":"4",
    "addr:postcode":"5652 et",
    "iso:country":"NL",
    "sg:address":"St Theresiastr 4",
    "sg:city":"Eindhoven",
    "sg:orig_category":"Cafetaria'S",
    "sg:phone":"+31 40 255 2092",
    "sg:postcode":"5652 ET",
    "sg:province":"Noord-Brabant",
    "wof:name":"Saigon",
    "wof:placetype":"venue"
},
  "geometry": {"coordinates":[5.442618,51.438084],"type":"Point"}
}