{
  "type": "Feature",
  "properties": {
    "addr:full":"Boskamp 48 Olst Overijssel 8121 CZ",
    "addr:housenumber":"48",
    "addr:postcode":"8121",
    "addr:street":"Boskamp",
    "iso:country":"NL",
    "sg:address":"Boskamp 48",
    "sg:city":"Olst",
    "sg:orig_category":"Gordijnenateliers",
    "sg:phone":"+31 570 562 114",
    "sg:postcode":"8121 CZ",
    "sg:province":"Overijssel",
    "wof:name":"Gormado",
    "wof:placetype":"venue"
},
  "geometry": {"coordinates":[6.132415,52.331303],"type":"Point"}
}