{
  "type": "Feature",
  "properties": {
    "addr:full":"Graauwsedijk 4 Graauw Zeeland 4569 PH",
    "addr:housenumber":"4",
    "addr:postcode":"4569",
    "addr:street":"Graauwsedijk",
    "iso:country":"NL",
    "sg:address":"Graauwsedijk 4",
    "sg:city":"Graauw",
    "sg:orig_category":"Fietshandelaren",
    "sg:phone":"+31 114 635 774",
    "sg:postcode":"4569 PH",
    "sg:province":"Zeeland",
    "wof:name":"Rijwielhandel Vernimmen",
    "wof:placetype":"venue"
},
  "geometry": {"coordinates":[4.102916,51.33046],"type":"Point"}
}