{
  "type": "Feature",
  "properties": {
    "iso:country":"NL",
    "sg:address":"Heveringseweg 62",
    "sg:city":"Oostvoorne",
    "sg:orig_category":"Goederenvervoer Over De Weg",
    "sg:phone":"+31 181 482 274",
    "sg:postcode":"3233 SE",
    "sg:province":"South Holland",
    "wof:name":"Transportbedrijf R. Van Der Hoek Bv",
    "wof:placetype":"venue"
},
  "geometry": {"coordinates":[4.093182,51.900036],"type":"Point"}
}