{
  "type": "Feature",
  "properties": {
    "addr:full":"Lingedijk 14 Wadenoijen Gelderland 4014 MG",
    "addr:housenumber":"14",
    "addr:postcode":"4014 mg",
    "addr:street":"Lingedijk;Gelderland",
    "iso:country":"NL",
    "sg:address":"Lingedijk 14",
    "sg:city":"Wadenoijen",
    "sg:orig_category":"Meubelreparatie And -Restauratie",
    "sg:phone":"+31 344 662 370",
    "sg:postcode":"4014 MG",
    "sg:province":"Gelderland",
    "wof:name":"Beekhuysen",
    "wof:placetype":"venue"
},
  "geometry": {"coordinates":[5.365674,51.876163],"type":"Point"}
}