{
  "type": "Feature",
  "properties": {
    "iso:country":"NL",
    "sg:address":"Halleywg 189",
    "sg:city":"Dordrecht",
    "sg:orig_category":"Onderzoekbureaus",
    "sg:phone":"+31 78 651 4427",
    "sg:postcode":"3318 CG",
    "sg:province":"Zuid-Holland",
    "wof:name":"Nieuwe Energie, Sticht",
    "wof:placetype":"venue"
},
  "geometry": {"coordinates":[4.678657,51.786358],"type":"Point"}
}