{
  "type": "Feature",
  "properties": {
    "addr:full":"Eendrachtskade Zuidzijde 4 Groningen Groningen 9726 CW",
    "addr:housenumber":"4",
    "addr:postcode":"9726 cw",
    "addr:street":"Eendrachtskade Zuidzijde",
    "iso:country":"NL",
    "sg:address":"Eendrachtskade Zuidzijde 4",
    "sg:city":"Groningen",
    "sg:orig_category":"Werving And Selectie Van Tijdelijk Personeel And Uitzendkantoren",
    "sg:phone":"+31 50 313 8375",
    "sg:postcode":"9726 CW",
    "sg:province":"Groningen",
    "wof:name":"Start",
    "wof:placetype":"venue"
},
  "geometry": {"coordinates":[6.5553917885,53.2137145996],"type":"Point"}
}