{
  "type": "Feature",
  "properties": {
    "addr:full":"1E Industriedwarsstraat 3 Ijmuiden Noord-Holland 1976 DD",
    "addr:housenumber":"3",
    "addr:postcode":"1976 dd",
    "addr:street":"1E Industriedwarsstraat",
    "iso:country":"NL",
    "sg:address":"1E Industriedwarsstraat 3",
    "sg:city":"Ijmuiden",
    "sg:orig_category":"Makelaars In Onroerend Goed",
    "sg:phone":"+31 255 523 850",
    "sg:postcode":"1976 DD",
    "sg:province":"Noord-Holland",
    "wof:name":"Benjamin Velzen Ontwikkeling",
    "wof:placetype":"venue"
},
  "geometry": {"coordinates":[4.586727,52.458088],"type":"Point"}
}