{
  "type": "Feature",
  "properties": {
    "addr:full":"G V Loonstr 9 Delft South Holland 2612 HV",
    "addr:housenumber":"9",
    "addr:postcode":"2612 hv",
    "addr:street":"V Loonstr",
    "iso:country":"NL",
    "sg:address":"G V Loonstr 9",
    "sg:city":"Delft",
    "sg:orig_category":"Onderhoudswerken",
    "sg:phone":"+31 15 214 3600",
    "sg:postcode":"2612 HV",
    "sg:province":"South Holland",
    "wof:name":"Olsthoorn, W A M",
    "wof:placetype":"venue"
},
  "geometry": {"coordinates":[4.35869,52.011505],"type":"Point"}
}