{
  "type": "Feature",
  "properties": {
    "addr:full":"Kerkstraat 35 Kerkdriel Gelderland 5331 CB",
    "addr:housenumber":"35",
    "addr:postcode":"5331 cb",
    "addr:street":"Kerkstraat;Gelderland",
    "iso:country":"NL",
    "sg:address":"Kerkstraat 35",
    "sg:city":"Kerkdriel",
    "sg:orig_category":"Kappers",
    "sg:phone":"+31 418 632 775",
    "sg:postcode":"5331 CB",
    "sg:province":"Gelderland",
    "wof:name":"H. Van Houten",
    "wof:placetype":"venue"
},
  "geometry": {"coordinates":[5.3400969505,51.7717971802],"type":"Point"}
}