{
  "type": "Feature",
  "properties": {
    "addr:full":"Treubweg 11 Diemen Noord-Holland 1112 BA",
    "addr:housenumber":"11",
    "addr:postcode":"1112 ba",
    "addr:street":"Treubweg",
    "iso:country":"NL",
    "sg:address":"Treubweg 11",
    "sg:city":"Diemen",
    "sg:orig_category":"Drogisterijen",
    "sg:phone":"+31 20 600 2180",
    "sg:postcode":"1112 BA",
    "sg:province":"Noord-Holland",
    "wof:name":"Faco",
    "wof:placetype":"venue"
},
  "geometry": {"coordinates":[4.97311,52.331627],"type":"Point"}
}