{
  "type": "Feature",
  "properties": {
    "addr:full":"De Gouwe 4 Landsmeer North Holland 1121 GD",
    "addr:housenumber":"4",
    "addr:postcode":"1121 gd",
    "addr:street":"De Gouwe",
    "iso:country":"NL",
    "sg:address":"De Gouwe 4",
    "sg:city":"Landsmeer",
    "sg:orig_category":"Omroep",
    "sg:phone":"+31 20 482 3366",
    "sg:postcode":"1121 GD",
    "sg:province":"North Holland",
    "sg:website":"http://www.lokaleomroeplandsmeer.nl",
    "wof:name":"Lokale Omroep Landsmeer Sticht",
    "wof:placetype":"venue"
},
  "geometry": {"coordinates":[4.924077,52.430851],"type":"Point"}
}