{
  "type": "Feature",
  "properties": {
    "addr:full":"Gouderaksedijk 34 Gouda South Holland 2808 NG",
    "addr:housenumber":"34",
    "addr:postcode":"2808 ng",
    "addr:street":"Gouderaksedijk",
    "iso:country":"NL",
    "sg:address":"Gouderaksedijk 34",
    "sg:city":"Gouda",
    "sg:orig_category":"Wegen And Sportterreinen",
    "sg:phone":"+31 182 524 344",
    "sg:postcode":"2808 NG",
    "sg:province":"South Holland",
    "wof:name":"Koudasfalt Bv",
    "wof:placetype":"venue"
},
  "geometry": {"coordinates":[4.7149558067,52.0055236816],"type":"Point"}
}