{
  "type": "Feature",
  "properties": {
    "iso:country":"NL",
    "sg:address":"Hoofdwg 735",
    "sg:city":"Hoofddorp",
    "sg:orig_category":"Honden- En Kattentrimsalons",
    "sg:phone":"+31 23 561 3014",
    "sg:postcode":"2131 BD",
    "sg:province":"Noord-Holland",
    "wof:name":"Harmers",
    "wof:placetype":"venue"
},
  "geometry": {"coordinates":[4.68622,52.30212],"type":"Point"}
}