{
  "type": "Feature",
  "properties": {
    "iso:country":"NL",
    "sg:address":"S Signoretstr 6",
    "sg:city":"Almere",
    "sg:orig_category":"Projectontwikkeling",
    "sg:phone":"+31 36 537 5702",
    "sg:postcode":"1325 LE",
    "sg:province":"NL.",
    "wof:name":"Havenja Bv",
    "wof:placetype":"venue"
},
  "geometry": {"coordinates":[5.23586,52.369087],"type":"Point"}
}