{
  "type": "Feature",
  "properties": {
    "addr:full":"Dorpstr 41 Oirsbeek Limburg 6438 JS",
    "addr:housenumber":"41",
    "addr:postcode":"6438 js",
    "addr:street":"Dorpstr",
    "iso:country":"NL",
    "sg:address":"Dorpstr 41",
    "sg:city":"Oirsbeek",
    "sg:orig_category":"Grafisch Ontwerpers",
    "sg:phone":"+31 46 442 8305",
    "sg:postcode":"6438 JS",
    "sg:province":"Limburg",
    "wof:name":"Setola Vof",
    "wof:placetype":"venue"
},
  "geometry": {"coordinates":[5.913307,50.949074],"type":"Point"}
}