{
  "type": "Feature",
  "properties": {
    "addr:full":"Stobbenkamp 21 Ootmarsum Overijssel 7631 CM",
    "addr:housenumber":"21",
    "addr:postcode":"7631 cm",
    "addr:street":"Stobbenkamp",
    "iso:country":"NL",
    "sg:address":"Stobbenkamp 21",
    "sg:city":"Ootmarsum",
    "sg:orig_category":"Adviesbureaus Bedrijfsorganisatie",
    "sg:phone":"+31 541 515 958",
    "sg:postcode":"7631 CM",
    "sg:province":"Overijssel",
    "wof:name":"Kramer",
    "wof:placetype":"venue"
},
  "geometry": {"coordinates":[6.893029,52.405373],"type":"Point"}
}