{
  "type": "Feature",
  "properties": {
    "addr:full":"Ericalaan 42 Oostwold Gem Leek Groningen 9828 PH",
    "addr:housenumber":"42",
    "addr:postcode":"9828",
    "addr:street":"Ericalaan",
    "iso:country":"NL",
    "sg:address":"Ericalaan 42",
    "sg:city":"Oostwold Gem Leek",
    "sg:orig_category":"Metaalbekleding And -Behandeling",
    "sg:phone":"+31 50 551 5797",
    "sg:postcode":"9828 PH",
    "sg:province":"Groningen",
    "wof:name":"Staalbewerking Noord Bv",
    "wof:placetype":"venue"
},
  "geometry": {"coordinates":[6.44483,53.201771],"type":"Point"}
}