{
  "type": "Feature",
  "properties": {
    "addr:full":"Markt 14 Epe Gelderland 8161 CL",
    "addr:housenumber":"14",
    "addr:postcode":"8161",
    "addr:street":"Markt;Gelderland",
    "iso:country":"NL",
    "sg:address":"Markt 14",
    "sg:city":"Epe",
    "sg:orig_category":"Overheidsdiensten",
    "sg:phone":"+31 578 678 787",
    "sg:postcode":"8161 CL",
    "sg:province":"Gelderland",
    "wof:name":"Gemeente Epe",
    "wof:placetype":"venue"
},
  "geometry": {"coordinates":[5.9846348763,52.3486099243],"type":"Point"}
}