{
  "type": "Feature",
  "properties": {
    "iso:country":"NL",
    "sg:address":"Kerkstr 256 3Hoog",
    "sg:city":"Amsterdam",
    "sg:orig_category":"Psychotherapeuten",
    "sg:phone":"+31 20 627 8010",
    "sg:postcode":"1017 HA",
    "sg:province":"Noord-Holland",
    "wof:name":"Annemieke Monsma, Drs",
    "wof:placetype":"venue"
},
  "geometry": {"coordinates":[4.892952,52.362671],"type":"Point"}
}