{
  "type": "Feature",
  "properties": {
    "addr:full":"Oude Vismarkt 23 Zwolle NL.08 8011 TA",
    "addr:housenumber":"23",
    "addr:postcode":"8011 ta",
    "addr:street":"Oude Vismarkt",
    "iso:country":"NL",
    "sg:address":"Oude Vismarkt 23",
    "sg:city":"Zwolle",
    "sg:orig_category":"Muziekinstrumenten",
    "sg:phone":"+31 38 421 1520",
    "sg:postcode":"8011 TA",
    "sg:province":"NL.08",
    "wof:name":"Van Lohuizen Muziek Bv",
    "wof:placetype":"venue"
},
  "geometry": {"coordinates":[6.094565,52.511814],"type":"Point"}
}