{
  "type": "Feature",
  "properties": {
    "iso:country":"NL",
    "sg:address":"Snippendalseweg 14",
    "sg:city":"Hierden",
    "sg:orig_category":"Pluimveehouderijen",
    "sg:phone":"+31 341 425 515",
    "sg:postcode":"3849 NE",
    "sg:province":"Gelderland",
    "wof:name":"K.J. En J.L. De Boer-Van Bijsteren",
    "wof:placetype":"venue"
},
  "geometry": {"coordinates":[5.662788,52.348209],"type":"Point"}
}