{
  "type": "Feature",
  "properties": {
    "addr:full":"Baarsjeswg 301 Amsterdam Noord-Holland 1058 AG",
    "addr:housenumber":"301",
    "addr:postcode":"1058",
    "iso:country":"NL",
    "sg:address":"Baarsjeswg 301",
    "sg:city":"Amsterdam",
    "sg:orig_category":"Loopbaanbegeleiding",
    "sg:phone":"+31 20 683 3982",
    "sg:postcode":"1058 AG",
    "sg:province":"Noord-Holland",
    "wof:name":"Instapcentrum",
    "wof:placetype":"venue"
},
  "geometry": {"coordinates":[4.855346,52.359241],"type":"Point"}
}