{
  "type": "Feature",
  "properties": {
    "iso:country":"NL",
    "sg:address":"Dassenakker 57",
    "sg:city":"Houten",
    "sg:orig_category":"Administratie- En Boekhoudkantoren",
    "sg:phone":"+31 30 635 2365",
    "sg:postcode":"3994 EE",
    "sg:province":"Utrecht",
    "wof:name":"Homoed, Van",
    "wof:placetype":"venue"
},
  "geometry": {"coordinates":[5.180351,52.034348],"type":"Point"}
}