{
  "type": "Feature",
  "properties": {
    "addr:full":"Emmaln 4 Dirksland Zuid-Holland 3247 AE",
    "addr:housenumber":"4",
    "addr:postcode":"3247 ae",
    "addr:street":"Emmaln",
    "iso:country":"NL",
    "sg:address":"Emmaln 4",
    "sg:city":"Dirksland",
    "sg:orig_category":"Kunstnijverheidsateliers",
    "sg:phone":"+31 187 603 445",
    "sg:postcode":"3247 AE",
    "sg:province":"Zuid-Holland",
    "wof:name":"Clarine, B",
    "wof:placetype":"venue"
},
  "geometry": {"coordinates":[4.105012,51.748753],"type":"Point"}
}