{
  "type": "Feature",
  "properties": {
    "addr:full":"V Veldekeln 23 Roosendaal Noord-Brabant 4707 AH",
    "addr:housenumber":"23",
    "addr:postcode":"4707 ah",
    "iso:country":"NL",
    "sg:address":"V Veldekeln 23",
    "sg:city":"Roosendaal",
    "sg:orig_category":"Voetbalverenigingen",
    "sg:phone":"+31 165 541 662",
    "sg:postcode":"4707 AH",
    "sg:province":"Noord-Brabant",
    "wof:name":"Dvo '60",
    "wof:placetype":"venue"
},
  "geometry": {"coordinates":[4.45767,51.531403],"type":"Point"}
}