{
  "type": "Feature",
  "properties": {
    "addr:full":"Hyacinthstr 2 Voorschoten Zuid-Holland 2252 VB",
    "addr:housenumber":"2",
    "addr:postcode":"2252 vb",
    "addr:street":"Hyacinthstr",
    "iso:country":"NL",
    "sg:address":"Hyacinthstr 2",
    "sg:city":"Voorschoten",
    "sg:orig_category":"Meubelmakerijen",
    "sg:phone":"+31 71 561 7674",
    "sg:postcode":"2252 VB",
    "sg:province":"Zuid-Holland",
    "wof:name":"Vreugd, J De",
    "wof:placetype":"venue"
},
  "geometry": {"coordinates":[4.440201,52.124969],"type":"Point"}
}