{
  "type": "Feature",
  "properties": {
    "addr:full":"Verloren Van Themaatweg 2 Born Limburg 6121 RG",
    "addr:housenumber":"2",
    "addr:postcode":"6121 rg",
    "addr:street":"Verloren Van Themaatweg",
    "iso:country":"NL",
    "sg:address":"Verloren Van Themaatweg 2",
    "sg:city":"Born",
    "sg:orig_category":"Autokeuringen",
    "sg:phone":"+31 46 489 1515",
    "sg:postcode":"6121 RG",
    "sg:province":"Limburg",
    "wof:name":"Qek Global Solutions Bv",
    "wof:placetype":"venue"
},
  "geometry": {"coordinates":[-156.93781999999999,67.060463],"type":"Point"}
}