{
  "type": "Feature",
  "properties": {
    "iso:country":"NL",
    "sg:address":"Skoallestrjitte 1",
    "sg:city":"Easterein",
    "sg:orig_category":"Vaste And Vloeibare Brandstoffen",
    "sg:phone":"+31 515 331 705",
    "sg:postcode":"8734 GL",
    "sg:province":"Friesland",
    "wof:name":"Joustra Branje",
    "wof:placetype":"venue"
},
  "geometry": {"coordinates":[5.619339,53.095985],"type":"Point"}
}