{
  "type": "Feature",
  "properties": {
    "iso:country":"NL",
    "sg:address":"Plakstr 6A",
    "sg:city":"Winssen",
    "sg:orig_category":"Verenigingsgebouwen",
    "sg:phone":"+31 487 521 646",
    "sg:postcode":"6645 KL",
    "sg:province":"Gelderland",
    "wof:name":"Boshof",
    "wof:placetype":"venue"
},
  "geometry": {"coordinates":[5.712181,51.876518],"type":"Point"}
}