{
  "type": "Feature",
  "properties": {
    "addr:full":"Winkelcentrum Woensel 76A Eindhoven Noord-Brabant 5625 AD",
    "addr:housenumber":"76a",
    "addr:postcode":"5625 ad",
    "addr:street":"Winkelcentrum Woensel",
    "iso:country":"NL",
    "sg:address":"Winkelcentrum Woensel 76A",
    "sg:city":"Eindhoven",
    "sg:orig_category":"Wasserettes And Stomerijen",
    "sg:phone":"+31 40 248 1138",
    "sg:postcode":"5625 AD",
    "sg:province":"Noord-Brabant",
    "wof:name":"Palthe Stomerijen Bv",
    "wof:placetype":"venue"
},
  "geometry": {"coordinates":[5.4774680138,51.4703788757],"type":"Point"}
}