{
  "type": "Feature",
  "properties": {
    "addr:full":"C.V.Maasdijkstraat 74 Utrecht Utrecht 3555 VP",
    "addr:housenumber":"74",
    "addr:postcode":"3555 vp",
    "addr:street":"C.V.Maasdijkstraat",
    "iso:country":"NL",
    "sg:address":"C.V.Maasdijkstraat 74",
    "sg:city":"Utrecht",
    "sg:orig_category":"Binnenhuisarchitecten",
    "sg:phone":"+31 30 246 8598",
    "sg:postcode":"3555 VP",
    "sg:province":"Utrecht",
    "wof:name":"Madico Entreematten",
    "wof:placetype":"venue"
},
  "geometry": {"coordinates":[5.07365,52.119228],"type":"Point"}
}