{
  "type": "Feature",
  "properties": {
    "addr:full":"Kroonkruid 157 Nieuwerkerk Ad Ijssel South Holland 2914 TL",
    "addr:housenumber":"157",
    "addr:postcode":"2914 tl",
    "addr:street":"Kroonkruid;Ijssel",
    "iso:country":"NL",
    "sg:address":"Kroonkruid 157",
    "sg:city":"Nieuwerkerk Ad Ijssel",
    "sg:orig_category":"Autokeuringen",
    "sg:phone":"+31 180 313 589",
    "sg:postcode":"2914 TL",
    "sg:province":"South Holland",
    "wof:name":"F. De Graaff",
    "wof:placetype":"venue"
},
  "geometry": {"coordinates":[4.619134,51.976238],"type":"Point"}
}