{
  "type": "Feature",
  "properties": {
    "iso:country":"NL",
    "sg:address":"Houwg 23",
    "sg:city":"Elst Ut",
    "sg:orig_category":"Belastingconsulenten/ Belastingadviseurs",
    "sg:phone":"+31 318 472 203",
    "sg:postcode":"3921 DB",
    "sg:province":"Utrecht",
    "wof:name":"Man, M De",
    "wof:placetype":"venue"
},
  "geometry": {"coordinates":[5.492269,51.988846],"type":"Point"}
}