{
  "type": "Feature",
  "properties": {
    "addr:full":"Admiraliteitskd 21M Rotterdam South Holland 3063 ED",
    "addr:housenumber":"21m",
    "addr:postcode":"3063 ed",
    "addr:street":"Admiraliteitskd",
    "iso:country":"NL",
    "sg:address":"Admiraliteitskd 21M",
    "sg:city":"Rotterdam",
    "sg:orig_category":"Bierbrouwerijen",
    "sg:phone":"+31 10 212 3263",
    "sg:postcode":"3063 ED",
    "sg:province":"South Holland",
    "wof:name":"Metmate",
    "wof:placetype":"venue"
},
  "geometry": {"coordinates":[4.505556,51.920906],"type":"Point"}
}