{
  "type": "Feature",
  "properties": {
    "iso:country":"NL",
    "sg:address":"Schoolstraat 40",
    "sg:city":"Herten",
    "sg:orig_category":"Verzekeringen",
    "sg:phone":"+31 475 334 758",
    "sg:postcode":"6049 BN",
    "sg:province":"Limburg",
    "wof:name":"Jbc-Assurantien B.G.A.R. Clevers",
    "wof:placetype":"venue"
},
  "geometry": {"coordinates":[5.961821,51.182987],"type":"Point"}
}