{
  "type": "Feature",
  "properties": {
    "addr:full":"Eperweg 1 Mechelen Limburg 6281 NA",
    "addr:housenumber":"1",
    "addr:postcode":"6281 na",
    "addr:street":"Eperweg",
    "iso:country":"NL",
    "sg:address":"Eperweg 1",
    "sg:city":"Mechelen",
    "sg:orig_category":"Vakantiehuizen",
    "sg:phone":"+31 43 455 1518",
    "sg:postcode":"6281 NA",
    "sg:province":"Limburg",
    "wof:name":"A Gen Graet",
    "wof:placetype":"venue"
},
  "geometry": {"coordinates":[5.917992,50.793938],"type":"Point"}
}