{
  "type": "Feature",
  "properties": {
    "addr:full":"Vlasblok 7 Hoeven Noord-Brabant 4741 GA",
    "addr:housenumber":"7",
    "addr:postcode":"4741 ga",
    "addr:street":"Vlasblok",
    "iso:country":"NL",
    "sg:address":"Vlasblok 7",
    "sg:city":"Hoeven",
    "sg:classifiers":[
        {
            "category":"Food & Beverages",
            "subcategory":"Bakery",
            "type":"Retail Goods"
        }
    ],
    "sg:phone":"+31 165 503 287",
    "sg:postcode":"4741 GA",
    "sg:province":"Noord-Brabant",
    "sg:tags":[
        "brood",
        "en",
        "banket"
    ],
    "wof:name":"Reuvers, R",
    "wof:placetype":"venue"
},
  "geometry": {"coordinates":[-83.222931,32.678131],"type":"Point"}
}