{
  "type": "Feature",
  "properties": {
    "addr:full":"Industriewg 6 Terneuzen Zeeland 4538 AH",
    "addr:housenumber":"6",
    "addr:postcode":"4538 ah",
    "addr:street":"Industriewg",
    "iso:country":"NL",
    "sg:address":"Industriewg 6",
    "sg:city":"Terneuzen",
    "sg:orig_category":"Woningbouw- Verenigingen En -Stichtingen",
    "sg:phone":"+31 115 610 010",
    "sg:postcode":"4538 AH",
    "sg:province":"Zeeland",
    "wof:name":"Stichting Clavis",
    "wof:placetype":"venue"
},
  "geometry": {"coordinates":[3.8273251057,51.3282318115],"type":"Point"}
}