{
  "type": "Feature",
  "properties": {
    "addr:full":"Singel 66 Dordrecht South Holland 3311 SJ",
    "addr:housenumber":"66",
    "addr:postcode":"3311",
    "addr:street":"Singel",
    "iso:country":"NL",
    "sg:address":"Singel 66",
    "sg:city":"Dordrecht",
    "sg:orig_category":"Musea And Historische Gebouwen",
    "sg:phone":"+31 78 614 2678",
    "sg:postcode":"3311 SJ",
    "sg:province":"South Holland",
    "wof:name":"Museum Naaimachines Dordrecht",
    "wof:placetype":"venue"
},
  "geometry": {"coordinates":[4.677643,51.813526],"type":"Point"}
}