{
  "type": "Feature",
  "properties": {
    "addr:full":"Aubertstr 1 Waalwyk Noord-Brabant 5144 WN",
    "addr:housenumber":"1",
    "addr:postcode":"5144 wn",
    "addr:street":"Aubertstr",
    "iso:country":"NL",
    "sg:address":"Aubertstr 1",
    "sg:city":"Waalwyk",
    "sg:orig_category":"Schoenen - Groothandel",
    "sg:phone":"+31 416 339 392",
    "sg:postcode":"5144 WN",
    "sg:province":"Noord-Brabant",
    "wof:name":"Jong-Van Ark, De",
    "wof:placetype":"venue"
},
  "geometry": {"coordinates":[5.064115,51.673996],"type":"Point"}
}