{
  "type": "Feature",
  "properties": {
    "addr:full":"De Heul 10 Maasdam South Holland 3299 WH",
    "addr:housenumber":"10",
    "addr:postcode":"3299 wh",
    "addr:street":"De Heul",
    "iso:country":"NL",
    "sg:address":"De Heul 10",
    "sg:city":"Maasdam",
    "sg:orig_category":"Boekhouders",
    "sg:phone":"+31 78 676 1483",
    "sg:postcode":"3299 WH",
    "sg:province":"South Holland",
    "wof:name":"Adm.- & Belastingadviseur Scheernoorn",
    "wof:placetype":"venue"
},
  "geometry": {"coordinates":[4.562718,51.786224],"type":"Point"}
}