{
  "type": "Feature",
  "properties": {
    "addr:full":"P Guillaumestr 17 Tegelen Limburg 5931 CH",
    "addr:housenumber":"17",
    "addr:postcode":"5931",
    "addr:street":"P",
    "iso:country":"NL",
    "sg:address":"P Guillaumestr 17",
    "sg:city":"Tegelen",
    "sg:orig_category":"Poeliers",
    "sg:phone":"+31 77 373 0940",
    "sg:postcode":"5931 CH",
    "sg:province":"Limburg",
    "wof:name":"Schatorj\u00e9 Bv, Gebr",
    "wof:placetype":"venue"
},
  "geometry": {"coordinates":[6.132911,51.340252],"type":"Point"}
}