{
  "type": "Feature",
  "properties": {
    "addr:full":"Hooghei 21 Berlicum Nb Noord-Brabant 5258 SX",
    "addr:housenumber":"21",
    "addr:postcode":"5258 sx",
    "addr:street":"Hooghei",
    "iso:country":"NL",
    "sg:address":"Hooghei 21",
    "sg:city":"Berlicum Nb",
    "sg:orig_category":"Kappers",
    "sg:phone":"+31 73 503 3682",
    "sg:postcode":"5258 SX",
    "sg:province":"Noord-Brabant",
    "wof:name":"J.P.A. Van Grinsven",
    "wof:placetype":"venue"
},
  "geometry": {"coordinates":[5.4129190445,51.6967010498],"type":"Point"}
}