{
  "type": "Feature",
  "properties": {
    "addr:full":"Weverstraat 16 Uden Noord-Brabant 5405 BN",
    "addr:housenumber":"16",
    "addr:postcode":"5405 bn",
    "addr:street":"Weverstraat",
    "iso:country":"NL",
    "sg:address":"Weverstraat 16",
    "sg:city":"Uden",
    "sg:orig_category":"Wasserettes And Stomerijen",
    "sg:phone":"+31 413 263 940",
    "sg:postcode":"5405 BN",
    "sg:province":"Noord-Brabant",
    "wof:name":"Berendsen Textielservice Bv",
    "wof:placetype":"venue"
},
  "geometry": {"coordinates":[114.5989685059,4.5251297951],"type":"Point"}
}