{
  "type": "Feature",
  "properties": {
    "iso:country":"NL",
    "sg:address":"Wyk 8 12A",
    "sg:city":"Urk",
    "sg:orig_category":"Kappers",
    "sg:phone":"+31 527 683 939",
    "sg:postcode":"8321 TG",
    "sg:province":"Flevoland",
    "wof:name":"Jowy",
    "wof:placetype":"venue"
},
  "geometry": {"coordinates":[5.5980319977,52.663318634],"type":"Point"}
}