{
  "type": "Feature",
  "properties": {
    "addr:full":"Oostplein 97 Rotterdam South Holland 3011 KW",
    "addr:housenumber":"97",
    "addr:postcode":"3011 kw",
    "addr:street":"Oostplein",
    "iso:country":"NL",
    "sg:address":"Oostplein 97",
    "sg:city":"Rotterdam",
    "sg:orig_category":"Verlichting And Huishoudartikelen",
    "sg:phone":"+31 10 433 0188",
    "sg:postcode":"3011 KW",
    "sg:province":"South Holland",
    "wof:name":"Lorje Verlichtingsadviseurs Rotterdam Vof",
    "wof:placetype":"venue"
},
  "geometry": {"coordinates":[4.49581,51.923512],"type":"Point"}
}