{
  "type": "Feature",
  "properties": {
    "addr:full":"Oosteinde 23 Harderwijk Gelderland 3842 DR",
    "addr:housenumber":"23",
    "addr:postcode":"3842 dr",
    "addr:street":"Oosteinde;Gelderland",
    "iso:country":"NL",
    "sg:address":"Oosteinde 23",
    "sg:city":"Harderwijk",
    "sg:orig_category":"Werving And Selectie Van Vast Personeel",
    "sg:phone":"+31 341 430 700",
    "sg:postcode":"3842 DR",
    "sg:province":"Gelderland",
    "wof:name":"Stoevelaar & Partners",
    "wof:placetype":"venue"
},
  "geometry": {"coordinates":[5.6372141838,52.3501777649],"type":"Point"}
}