{
  "type": "Feature",
  "properties": {
    "addr:full":"Beresteinln 110 S Gravenhage Zuid-Holland 2542 KD",
    "addr:housenumber":"110;gravenhage",
    "addr:postcode":"2542 kd",
    "addr:street":"S",
    "iso:country":"NL",
    "sg:address":"Beresteinln 110",
    "sg:city":"S Gravenhage",
    "sg:orig_category":"Orthopedagogen",
    "sg:phone":"+31 70 321 6500",
    "sg:postcode":"2542 KD",
    "sg:province":"Zuid-Holland",
    "wof:name":"Bruggen, De",
    "wof:placetype":"venue"
},
  "geometry": {"coordinates":[4.2703499794,52.0357704163],"type":"Point"}
}