{
  "type": "Feature",
  "properties": {
    "addr:full":"Ambyerstraat-Noord 35 Maastricht Limburg 6225 EA",
    "addr:housenumber":"35",
    "addr:postcode":"6225 ea",
    "addr:street":"Ambyerstraat-Noord",
    "iso:country":"NL",
    "sg:address":"Ambyerstraat-Noord 35",
    "sg:city":"Maastricht",
    "sg:orig_category":"Banken And Kredietinstellingen",
    "sg:phone":"+31 43 363 6630",
    "sg:postcode":"6225 EA",
    "sg:province":"Limburg",
    "wof:name":"Postkantoor",
    "wof:placetype":"venue"
},
  "geometry": {"coordinates":[5.732397,50.86372],"type":"Point"}
}