{
  "type": "Feature",
  "properties": {
    "addr:full":"A V Schendelstr 25 Gemert Noord-Brabant 5421 RE",
    "addr:housenumber":"25",
    "addr:postcode":"5421 re",
    "addr:street":"A;Schendelstr",
    "iso:country":"NL",
    "sg:address":"A V Schendelstr 25",
    "sg:city":"Gemert",
    "sg:orig_category":"Verzekeringen - Verzekeringskantoren",
    "sg:phone":"+31 492 321 182",
    "sg:postcode":"5421 RE",
    "sg:province":"Noord-Brabant",
    "wof:name":"Berg & Broek",
    "wof:placetype":"venue"
},
  "geometry": {"coordinates":[5.681675,51.556126],"type":"Point"}
}