{
  "type": "Feature",
  "properties": {
    "iso:country":"NL",
    "sg:address":"Van Den Broekeweg 12",
    "sg:city":"Almelo",
    "sg:orig_category":"Bedrijfsinventaris Gh",
    "sg:phone":"+31 546 865 447",
    "sg:postcode":"7602 PH",
    "sg:province":"NL.08",
    "wof:name":"Sligro Almelo",
    "wof:placetype":"venue"
},
  "geometry": {"coordinates":[6.641815,52.375042],"type":"Point"}
}