{
  "type": "Feature",
  "properties": {
    "iso:country":"NL",
    "sg:address":"Gaspeldoornlaan 42",
    "sg:city":"Valkenswaard",
    "sg:orig_category":"Kappers",
    "sg:phone":"+31 40 201 9173",
    "sg:postcode":"5552 GC",
    "sg:province":"Noord-Brabant",
    "wof:name":"Kinki Bv",
    "wof:placetype":"venue"
},
  "geometry": {"coordinates":[5.4510560036,51.3633995056],"type":"Point"}
}