{
  "type": "Feature",
  "properties": {
    "addr:full":"Dorpsstraat 12 Elim Drenthe 7916 PC",
    "addr:housenumber":"12",
    "addr:postcode":"7916 pc",
    "addr:street":"Dorpsstraat",
    "iso:country":"NL",
    "sg:address":"Dorpsstraat 12",
    "sg:city":"Elim",
    "sg:classifiers":[
        {
            "category":"Food & Beverages",
            "subcategory":"Fruits & Vegetables",
            "type":"Retail Goods"
        }
    ],
    "sg:phone":"+31 528 352 562",
    "sg:postcode":"7916 PC",
    "sg:province":"Drenthe",
    "sg:tags":[
        "groenten"
    ],
    "wof:name":"F. Benjamins, Groente- En Fruithandel",
    "wof:placetype":"venue"
},
  "geometry": {"coordinates":[6.580209,52.681129],"type":"Point"}
}