{
  "type": "Feature",
  "properties": {
    "addr:full":"Oude Rykswg 255-5 Rouveen Overijssel 7954 EJ",
    "addr:housenumber":"255-5",
    "addr:postcode":"7954 ej",
    "addr:street":"Oude Rykswg",
    "iso:country":"NL",
    "sg:address":"Oude Rykswg 255-5",
    "sg:city":"Rouveen",
    "sg:orig_category":"Medische Installaties En Instrumenten",
    "sg:phone":"+31 522 466 766",
    "sg:postcode":"7954 EJ",
    "sg:province":"Overijssel",
    "sg:website":"http://www.laservision.nl",
    "wof:name":"Laservision Instruments Bv",
    "wof:placetype":"venue"
},
  "geometry": {"coordinates":[6.182914,52.627239],"type":"Point"}
}