{
  "type": "Feature",
  "properties": {
    "addr:full":"Avelingen W 5 Gorinchem Zuid-Holland 4202 MS",
    "addr:housenumber":"5",
    "addr:postcode":"4202 ms",
    "addr:street":"Avelingen W",
    "iso:country":"NL",
    "sg:address":"Avelingen W 5",
    "sg:city":"Gorinchem",
    "sg:orig_category":"Administratie- En Boekhoudkantoren",
    "sg:phone":"+31 183 631 644",
    "sg:postcode":"4202 MS",
    "sg:province":"Zuid-Holland",
    "wof:name":"Abea Bv",
    "wof:placetype":"venue"
},
  "geometry": {"coordinates":[4.939961,51.835842],"type":"Point"}
}