{
  "type": "Feature",
  "properties": {
    "addr:full":"Konijnenberg 101 Breda North Brabant 4825 BC",
    "addr:housenumber":"101",
    "addr:postcode":"4825 bc",
    "addr:street":"Konijnenberg",
    "iso:country":"NL",
    "sg:address":"Konijnenberg 101",
    "sg:city":"Breda",
    "sg:orig_category":"Autokeuringen",
    "sg:phone":"+31 76 572 2180",
    "sg:postcode":"4825 BC",
    "sg:province":"North Brabant",
    "wof:name":"Perfekta Autoschade",
    "wof:placetype":"venue"
},
  "geometry": {"coordinates":[4.768559,51.615788],"type":"Point"}
}