{
  "type": "Feature",
  "properties": {
    "iso:country":"NL",
    "sg:address":"Floralaan 2",
    "sg:city":"Wervershoof",
    "sg:orig_category":"Schilderwerk",
    "sg:phone":"+31 228 584 921",
    "sg:postcode":"1693 GM",
    "sg:province":"Noord-Holland",
    "wof:name":"Van Houten Schilderwerken",
    "wof:placetype":"venue"
},
  "geometry": {"coordinates":[5.155814,52.730244],"type":"Point"}
}