{
  "type": "Feature",
  "properties": {
    "addr:full":"Lambertusstraat 64 Rotterdam Zuid-Holland 3062 WJ",
    "addr:housenumber":"64",
    "addr:postcode":"3062 wj",
    "addr:street":"Lambertusstraat",
    "iso:country":"NL",
    "sg:address":"Lambertusstraat 64",
    "sg:city":"Rotterdam",
    "sg:orig_category":"Film-, Tv- And Videoproductie",
    "sg:phone":"+31 10 413 0103",
    "sg:postcode":"3062 WJ",
    "sg:province":"Zuid-Holland",
    "wof:name":"Keyframe Images",
    "wof:placetype":"venue"
},
  "geometry": {"coordinates":[4.511789,51.924229],"type":"Point"}
}