{
  "type": "Feature",
  "properties": {
    "addr:full":"Kethelweg 203C Vlaardingen South Holland 3135 GJ",
    "addr:housenumber":"203c",
    "addr:postcode":"3135 gj",
    "addr:street":"Kethelweg",
    "iso:country":"NL",
    "sg:address":"Kethelweg 203C",
    "sg:city":"Vlaardingen",
    "sg:orig_category":"Modellenbureaus",
    "sg:phone":"+31 10 470 9510",
    "sg:postcode":"3135 GJ",
    "sg:province":"South Holland",
    "wof:name":"Modellenburo Hc.",
    "wof:placetype":"venue"
},
  "geometry": {"coordinates":[4.359306,51.92128],"type":"Point"}
}