{
  "type": "Feature",
  "properties": {
    "addr:full":"Raaimoeren 17 Breda Noord-Brabant 4824 KA",
    "addr:housenumber":"17",
    "addr:postcode":"4824 ka",
    "addr:street":"Raaimoeren",
    "iso:country":"NL",
    "sg:address":"Raaimoeren 17",
    "sg:city":"Breda",
    "sg:orig_category":"Scholen Voor Basisonderwijs",
    "sg:phone":"+31 76 549 3005",
    "sg:postcode":"4824 KA",
    "sg:province":"Noord-Brabant",
    "wof:name":"Berkenhof, De",
    "wof:placetype":"venue"
},
  "geometry": {"coordinates":[4.741266,51.609894],"type":"Point"}
}