{
  "type": "Feature",
  "properties": {
    "addr:full":"Albert Schweitzersingel 90 Amersfoort Utrecht 3822 BX",
    "addr:housenumber":"90",
    "addr:postcode":"3822 bx",
    "addr:street":"Albert Schweitzersingel",
    "iso:country":"NL",
    "sg:address":"Albert Schweitzersingel 90",
    "sg:city":"Amersfoort",
    "sg:classifiers":[
        {
            "category":"Fast Food",
            "type":"Food & Drink"
        }
    ],
    "sg:phone":"+31 33 455 8074",
    "sg:postcode":"3822 BX",
    "sg:province":"Utrecht",
    "sg:tags":[
        "afhaal",
        "restaurant"
    ],
    "wof:name":"Cafetaria Zielhorst",
    "wof:placetype":"venue"
},
  "geometry": {"coordinates":[5.40377,52.176666],"type":"Point"}
}