{
  "type": "Feature",
  "properties": {
    "iso:country":"NL",
    "sg:address":"C Trooststr 60",
    "sg:city":"Amsterdam",
    "sg:orig_category":"Exploitatie- Maatschappijen",
    "sg:phone":"+31 20 671 7731",
    "sg:postcode":"1072 JH",
    "sg:province":"Noord-Holland",
    "wof:name":"Eeuwen, H Van",
    "wof:placetype":"venue"
},
  "geometry": {"coordinates":[4.889535,52.350487],"type":"Point"}
}