{
  "type": "Feature",
  "properties": {
    "iso:country":"NL",
    "sg:address":"S Gravesandestr 11",
    "sg:city":"Badhoevedorp",
    "sg:orig_category":"Verenigingen En Stichtingen",
    "sg:phone":"+31 20 659 4394",
    "sg:postcode":"1171 XP",
    "sg:province":"Noord-Holland",
    "wof:name":"Justus Van Maurik Jr",
    "wof:placetype":"venue"
},
  "geometry": {"coordinates":[4.780702,52.342396],"type":"Point"}
}