{
  "type": "Feature",
  "properties": {
    "addr:full":"Nieuwendammerdk 133 Amsterdam Noord-Holland 1025 LG",
    "addr:housenumber":"133",
    "addr:postcode":"1025 lg",
    "iso:country":"NL",
    "sg:address":"Nieuwendammerdk 133",
    "sg:city":"Amsterdam",
    "sg:orig_category":"Psychotherapeuten",
    "sg:phone":"+31 20 636 9643",
    "sg:postcode":"1025 LG",
    "sg:province":"Noord-Holland",
    "wof:name":"Vliet, Anke Van",
    "wof:placetype":"venue"
},
  "geometry": {"coordinates":[4.93057,52.391651],"type":"Point"}
}