{
  "type": "Feature",
  "properties": {
    "iso:country":"NL",
    "sg:address":"Aardborstwg 24",
    "sg:city":"Mierlo",
    "sg:orig_category":"Kinderkleding - Fabrieken En Groothandel",
    "sg:phone":"+31 492 665 137",
    "sg:postcode":"5731 PS",
    "sg:province":"Noord-Brabant",
    "wof:name":"Dutch Domino",
    "wof:placetype":"venue"
},
  "geometry": {"coordinates":[5.620751,51.427879],"type":"Point"}
}