{
  "type": "Feature",
  "properties": {
    "addr:full":"Rossinilaan 32 Vlissingen Zeeland 4384 MA",
    "addr:housenumber":"32",
    "addr:postcode":"4384 ma",
    "addr:street":"Rossinilaan",
    "iso:country":"NL",
    "sg:address":"Rossinilaan 32",
    "sg:city":"Vlissingen",
    "sg:classifiers":[
        {
            "category":"Professional",
            "subcategory":"Accounting & Tax Preparation",
            "type":"Services"
        }
    ],
    "sg:phone":"+31 118 442 442",
    "sg:postcode":"4384 MA",
    "sg:province":"Zeeland",
    "sg:tags":[
        "accountant"
    ],
    "wof:name":"C.J. Lobbezoo Accountants En Administratieconsulen",
    "wof:placetype":"venue"
},
  "geometry": {"coordinates":[3.547261,51.463512],"type":"Point"}
}