{
  "type": "Feature",
  "properties": {
    "addr:full":"Veldkampwg 1C Ommen Overijssel 7731 HL",
    "addr:housenumber":"1c",
    "addr:postcode":"7731 hl",
    "addr:street":"Veldkampwg",
    "iso:country":"NL",
    "sg:address":"Veldkampwg 1C",
    "sg:city":"Ommen",
    "sg:orig_category":"Sanitaire Artikelen - Installatie En Onderhoud",
    "sg:phone":"+31 529 456 969",
    "sg:postcode":"7731 HL",
    "sg:province":"Overijssel",
    "sg:website":"http://www.backers.nl",
    "wof:name":"Backers Bv",
    "wof:placetype":"venue"
},
  "geometry": {"coordinates":[6.427987,52.527462],"type":"Point"}
}