{
  "type": "Feature",
  "properties": {
    "addr:full":"Kooiwalwg 1 Barendrecht Zuid-Holland 2992 XA",
    "addr:housenumber":"1",
    "addr:postcode":"2992 xa",
    "addr:street":"Kooiwalwg",
    "iso:country":"NL",
    "sg:address":"Kooiwalwg 1",
    "sg:city":"Barendrecht",
    "sg:classifiers":[
        {
            "category":"Sports & Exercise",
            "subcategory":"Stables",
            "type":"Entertainment"
        }
    ],
    "sg:phone":"+31 180 614 361",
    "sg:postcode":"2992 XA",
    "sg:province":"Zuid-Holland",
    "sg:tags":[
        "maneges"
    ],
    "wof:name":"Hippisch Centr Barendrecht",
    "wof:placetype":"venue"
},
  "geometry": {"coordinates":[4.534565,51.869221],"type":"Point"}
}