{
  "type": "Feature",
  "properties": {
    "addr:full":"Zestienhovensekd 376 Rotterdam South Holland 3043 KZ",
    "addr:housenumber":"376",
    "addr:postcode":"3043 kz",
    "iso:country":"NL",
    "sg:address":"Zestienhovensekd 376",
    "sg:city":"Rotterdam",
    "sg:orig_category":"Adviesbureaus Bedrijfsorganisatie",
    "sg:phone":"+31 10 467 0731",
    "sg:postcode":"3043 KZ",
    "sg:province":"South Holland",
    "wof:name":"Wel, Saul Van",
    "wof:placetype":"venue"
},
  "geometry": {"coordinates":[4.440416,51.9384],"type":"Point"}
}