{
  "type": "Feature",
  "properties": {
    "addr:full":"Koningstraat 23 Bodegraven Zuid-Holland 2411 CL",
    "addr:housenumber":"23",
    "addr:postcode":"2411",
    "addr:street":"Koningstraat",
    "iso:country":"NL",
    "sg:address":"Koningstraat 23",
    "sg:city":"Bodegraven",
    "sg:orig_category":"Metaalwerken",
    "sg:phone":"+31 172 617 508",
    "sg:postcode":"2411 CL",
    "sg:province":"Zuid-Holland",
    "wof:name":"C. Glismeyer",
    "wof:placetype":"venue"
},
  "geometry": {"coordinates":[4.747547,52.085552],"type":"Point"}
}