{
  "type": "Feature",
  "properties": {
    "addr:full":"Buorren 22 Tersoal Friesland 9014 CD",
    "addr:housenumber":"22",
    "addr:postcode":"9014 cd",
    "addr:street":"Buorren",
    "iso:country":"NL",
    "sg:address":"Buorren 22",
    "sg:city":"Tersoal",
    "sg:orig_category":"Keramische Producten Fab",
    "sg:phone":"+31 515 521 565",
    "sg:postcode":"9014 CD",
    "sg:province":"Friesland",
    "wof:name":"Pottenbakkerij Kitty",
    "wof:placetype":"venue"
},
  "geometry": {"coordinates":[5.737738,53.075378],"type":"Point"}
}