{
  "type": "Feature",
  "properties": {
    "addr:full":"Heinsiusstr 31A Schiedam South Holland 3119 TE",
    "addr:housenumber":"31a",
    "addr:postcode":"3119 te",
    "addr:street":"Heinsiusstr",
    "iso:country":"NL",
    "sg:address":"Heinsiusstr 31A",
    "sg:city":"Schiedam",
    "sg:classifiers":[
        {
            "category":"Wholesale",
            "subcategory":"Meat",
            "type":"Manufacturing & Wholesale Goods"
        }
    ],
    "sg:phone":"+31 10 471 4662",
    "sg:postcode":"3119 TE",
    "sg:province":"South Holland",
    "sg:tags":[
        "regeltechniek",
        "en",
        "meet-"
    ],
    "wof:name":"Ultramatics Benelux",
    "wof:placetype":"venue"
},
  "geometry": {"coordinates":[4.388554,51.923962],"type":"Point"}
}