{
  "type": "Feature",
  "properties": {
    "iso:country":"NL",
    "sg:address":"V Diemenstr 410",
    "sg:city":"Amsterdam",
    "sg:orig_category":"Beeldende Kunstenaars",
    "sg:phone":"+31 20 422 7890",
    "sg:postcode":"1013 CR",
    "sg:province":"Noord-Holland",
    "wof:name":"Witte, Anneke De",
    "wof:placetype":"venue"
},
  "geometry": {"coordinates":[4.893195,52.373119],"type":"Point"}
}