{
  "type": "Feature",
  "properties": {
    "addr:full":"V W V Dykveldstr 51 S Gravenhage Zuid-Holland 2582 KR",
    "addr:housenumber":"51;gravenhage",
    "addr:postcode":"2582 kr",
    "addr:street":"W V Dykveldstr;S",
    "iso:country":"NL",
    "sg:address":"V W V Dykveldstr 51",
    "sg:city":"S Gravenhage",
    "sg:orig_category":"Architecten En Architectenbureaus",
    "sg:phone":"+31 70 358 6834",
    "sg:postcode":"2582 KR",
    "sg:province":"Zuid-Holland",
    "sg:website":"http://www.aqgroep.com",
    "wof:name":"Queeste-Aq",
    "wof:placetype":"venue"
},
  "geometry": {"coordinates":[4.27852,52.092411],"type":"Point"}
}