{
  "type": "Feature",
  "properties": {
    "addr:full":"Palacepln 256-257 S Gravenhage Zuid-Holland 2587 WL",
    "addr:housenumber":"256-257;gravenhage",
    "addr:postcode":"2587 wl",
    "addr:street":"S",
    "iso:country":"NL",
    "sg:address":"Palacepln 256-257",
    "sg:city":"S Gravenhage",
    "sg:orig_category":"Herenkleding",
    "sg:phone":"+31 70 322 9601",
    "sg:postcode":"2587 WL",
    "sg:province":"Zuid-Holland",
    "sg:website":"http://www.gant.com",
    "wof:name":"Gant Store Scheveningen, The",
    "wof:placetype":"venue"
},
  "geometry": {"coordinates":[4.29118,52.112942],"type":"Point"}
}