{
  "type": "Feature",
  "properties": {
    "addr:full":"Parkzoom 173 Delft Zuid-Holland 2614 TD",
    "addr:housenumber":"173",
    "addr:postcode":"2614 td",
    "addr:street":"Parkzoom",
    "iso:country":"NL",
    "sg:address":"Parkzoom 173",
    "sg:city":"Delft",
    "sg:orig_category":"Boekhouders",
    "sg:phone":"+31 15 214 8385",
    "sg:postcode":"2614 TD",
    "sg:province":"Zuid-Holland",
    "wof:name":"P. Spaans",
    "wof:placetype":"venue"
},
  "geometry": {"coordinates":[4.33444,52.009731],"type":"Point"}
}