{
  "type": "Feature",
  "properties": {
    "addr:full":"Moerwijk 72 Breda Noord-Brabant 4826 HS",
    "addr:housenumber":"72",
    "addr:postcode":"4826 hs",
    "addr:street":"Moerwijk",
    "iso:country":"NL",
    "sg:address":"Moerwijk 72",
    "sg:city":"Breda",
    "sg:orig_category":"Postkantoren",
    "sg:phone":"+31 76 587 2611",
    "sg:postcode":"4826 HS",
    "sg:province":"Noord-Brabant",
    "sg:website":"http://www.postkantoor.nl",
    "wof:name":"Postkantoor",
    "wof:placetype":"venue"
},
  "geometry": {"coordinates":[4.790616,51.608433],"type":"Point"}
}