{
  "type": "Feature",
  "properties": {
    "iso:country":"NL",
    "sg:address":"Ambachtsstraat 8",
    "sg:city":"Wolvega",
    "sg:orig_category":"Kunststofverpakkingen Fab",
    "sg:phone":"+31 561 691 091",
    "sg:postcode":"8471 AJ",
    "sg:province":"Provincie Friesland",
    "wof:name":"Linpac Plastics Bv",
    "wof:placetype":"venue"
},
  "geometry": {"coordinates":[5.988083,52.881432],"type":"Point"}
}