{
  "type": "Feature",
  "properties": {
    "addr:full":"Bocht Oosterdiep 29 Veendam Groningen 9641 JH",
    "addr:housenumber":"29",
    "addr:postcode":"9641 jh",
    "addr:street":"Bocht Oosterdiep",
    "iso:country":"NL",
    "sg:address":"Bocht Oosterdiep 29",
    "sg:city":"Veendam",
    "sg:orig_category":"Overheidsdiensten",
    "sg:phone":"+31 598 628 151",
    "sg:postcode":"9641 JH",
    "sg:province":"Groningen",
    "wof:name":"Stichting Tov",
    "wof:placetype":"venue"
},
  "geometry": {"coordinates":[6.8775157928,53.1027603149],"type":"Point"}
}