{
  "type": "Feature",
  "properties": {
    "addr:full":"Maasln 45 Groningen Groningen 9725 HV",
    "addr:housenumber":"45",
    "addr:postcode":"9725 hv",
    "addr:street":"Maasln",
    "iso:country":"NL",
    "sg:address":"Maasln 45",
    "sg:city":"Groningen",
    "sg:orig_category":"Makelaars En Adviseurs Schepen En Jachten",
    "sg:phone":"+31 50 526 8233",
    "sg:postcode":"9725 HV",
    "sg:province":"Groningen",
    "wof:name":"Boersma",
    "wof:placetype":"venue"
},
  "geometry": {"coordinates":[6.57043,53.207001],"type":"Point"}
}