{
  "type": "Feature",
  "properties": {
    "iso:country":"NL",
    "sg:address":"Maasln 45",
    "sg:city":"Groningen",
    "sg:orig_category":"Makelaars En Adviseurs Schepen En Jachten",
    "sg:phone":"+31 50 526 8233",
    "sg:postcode":"9725 HV",
    "sg:province":"Groningen",
    "wof:name":"Boersma",
    "wof:placetype":"venue"
},
  "geometry": {"coordinates":[6.57043,53.207001],"type":"Point"}
}