{
  "type": "Feature",
  "properties": {
    "iso:country":"NL",
    "sg:address":"Energieweg 116",
    "sg:city":"Mijdrecht",
    "sg:orig_category":"Goederenvervoer Over De Weg",
    "sg:phone":"+31 297 281 546",
    "sg:postcode":"3641 RT",
    "sg:province":"Utrecht",
    "wof:name":"Aafjes Transport Bv",
    "wof:placetype":"venue"
},
  "geometry": {"coordinates":[4.884667,52.203739],"type":"Point"}
}