{
  "type": "Feature",
  "properties": {
    "iso:country":"NL",
    "sg:address":"Opvliet 22",
    "sg:city":"Hendrik Ido Ambacht",
    "sg:orig_category":"Boekhouders",
    "sg:phone":"+31 78 681 7922",
    "sg:postcode":"3341 CR",
    "sg:province":"South Holland",
    "wof:name":"Administratie-Kantoor De Vreugd",
    "wof:placetype":"venue"
},
  "geometry": {"coordinates":[4.649403,51.845684],"type":"Point"}
}