{
  "type": "Feature",
  "properties": {
    "iso:country":"NL",
    "sg:address":"Morsstr 31",
    "sg:city":"Leiden",
    "sg:orig_category":"Verf En Lak",
    "sg:phone":"+31 71 512 3958",
    "sg:postcode":"2312 BK",
    "sg:province":"Zuid-Holland",
    "wof:name":"Nicolaas Bv",
    "wof:placetype":"venue"
},
  "geometry": {"coordinates":[4.483317,52.162079],"type":"Point"}
}