{
  "type": "Feature",
  "properties": {
    "addr:full":"Dorpsstr 18 Schoonrewoerd South Holland 4145 KC",
    "addr:housenumber":"18",
    "addr:postcode":"4145 kc",
    "addr:street":"Dorpsstr",
    "iso:country":"NL",
    "sg:address":"Dorpsstr 18",
    "sg:city":"Schoonrewoerd",
    "sg:orig_category":"Kappers",
    "sg:phone":"+31 345 641 471",
    "sg:postcode":"4145 KC",
    "sg:province":"South Holland",
    "wof:name":"Giulietta",
    "wof:placetype":"venue"
},
  "geometry": {"coordinates":[5.1165299416,51.9202346802],"type":"Point"}
}