{
  "type": "Feature",
  "properties": {
    "addr:full":"Braakse Bosdk 2 Helmond North Brabant 5703 HZ",
    "addr:housenumber":"2",
    "addr:postcode":"5703 hz",
    "addr:street":"Bosdk",
    "iso:country":"NL",
    "sg:address":"Braakse Bosdk 2",
    "sg:city":"Helmond",
    "sg:orig_category":"Hulpverlening Sociaal",
    "sg:phone":"+31 492 532 554",
    "sg:postcode":"5703 HZ",
    "sg:province":"North Brabant",
    "wof:name":"Sbu",
    "wof:placetype":"venue"
},
  "geometry": {"coordinates":[5.67783,51.487148],"type":"Point"}
}