{
  "type": "Feature",
  "properties": {
    "addr:full":"Kinkerstraat 1 Amsterdam North Holland 1053 DB",
    "addr:housenumber":"1",
    "addr:postcode":"1053 db",
    "addr:street":"Kinkerstraat",
    "iso:country":"NL",
    "sg:address":"Kinkerstraat 1",
    "sg:city":"Amsterdam",
    "sg:orig_category":"Meubelzaken, Woning- And Keukeninrichting",
    "sg:phone":"+31 20 612 4344",
    "sg:postcode":"1053 DB",
    "sg:province":"North Holland",
    "wof:name":"A1 De Waterbed Specialist",
    "wof:placetype":"venue"
},
  "geometry": {"coordinates":[4.876112,52.368202],"type":"Point"}
}