{
  "type": "Feature",
  "properties": {
    "addr:full":"De Ruyterstr 1 Lisse Zuid-Holland 2161 TA",
    "addr:housenumber":"1",
    "addr:postcode":"2161 ta",
    "iso:country":"NL",
    "sg:address":"De Ruyterstr 1",
    "sg:city":"Lisse",
    "sg:orig_category":"Autorijscholen",
    "sg:phone":"+31 252 416 466",
    "sg:postcode":"2161 TA",
    "sg:province":"Zuid-Holland",
    "wof:name":"Huizer, Jack",
    "wof:placetype":"venue"
},
  "geometry": {"coordinates":[4.564637,52.259953],"type":"Point"}
}