{
  "type": "Feature",
  "properties": {
    "iso:country":"NL",
    "sg:address":"Nieuwkerksedijk 10",
    "sg:city":"Goirle",
    "sg:orig_category":"Bedrijfsinventaris Gh",
    "sg:phone":"+31 13 530 8700",
    "sg:postcode":"5051 HT",
    "sg:province":"Noord-Brabant",
    "wof:name":"Daub Bakery Machinery Bv",
    "wof:placetype":"venue"
},
  "geometry": {"coordinates":[5.051804,51.51226],"type":"Point"}
}