{
  "type": "Feature",
  "properties": {
    "addr:full":"Markt 2 Lichtenvoorde Gelderland 7131 DG",
    "addr:housenumber":"2",
    "addr:postcode":"7131 dg",
    "addr:street":"Markt;Gelderland",
    "iso:country":"NL",
    "sg:address":"Markt 2",
    "sg:city":"Lichtenvoorde",
    "sg:orig_category":"Verlichting And Huishoudartikelen",
    "sg:phone":"+31 544 375 853",
    "sg:postcode":"7131 DG",
    "sg:province":"Gelderland",
    "wof:name":"Blokker",
    "wof:placetype":"venue"
},
  "geometry": {"coordinates":[6.567455,51.986973],"type":"Point"}
}