{
  "type": "Feature",
  "properties": {
    "iso:country":"NL",
    "sg:address":"Octrooiwg 1",
    "sg:city":"Vlissingen",
    "sg:orig_category":"Schilders",
    "sg:phone":"+31 118 413 611",
    "sg:postcode":"4387 PJ",
    "sg:province":"Zeeland",
    "wof:name":"Buitelaar-Pouwer, Schildersbedrijf",
    "wof:placetype":"venue"
},
  "geometry": {"coordinates":[3.590821,51.473278],"type":"Point"}
}