{
  "type": "Feature",
  "properties": {
    "addr:full":"Broederenstraat 33-35 Deventer Overijssel 7411 LA",
    "addr:housenumber":"33-35",
    "addr:postcode":"7411 la",
    "addr:street":"Broederenstraat",
    "iso:country":"NL",
    "sg:address":"Broederenstraat 33-35",
    "sg:city":"Deventer",
    "sg:orig_category":"Drogisterijen",
    "sg:phone":"+31 570 615 107",
    "sg:postcode":"7411 LA",
    "sg:province":"Overijssel",
    "wof:name":"Drogisterij Dd",
    "wof:placetype":"venue"
},
  "geometry": {"coordinates":[6.156716,52.254021],"type":"Point"}
}