{
  "type": "Feature",
  "properties": {
    "iso:country":"NL",
    "sg:address":"Stadionkd To 72 To",
    "sg:city":"Amsterdam",
    "sg:orig_category":"Bloemen En Planten",
    "sg:phone":"+31 20 664 1376",
    "sg:postcode":"1077 VS",
    "sg:province":"Noord-Holland",
    "wof:name":"Four Seasons",
    "wof:placetype":"venue"
},
  "geometry": {"coordinates":[-94.58503,38.350479],"type":"Point"}
}