{
  "type": "Feature",
  "properties": {
    "addr:full":"Javastraat 33 Amsterdam Noord-Holland 1094 GZ",
    "addr:housenumber":"33",
    "addr:postcode":"1094 gz",
    "addr:street":"Javastraat",
    "iso:country":"NL",
    "sg:address":"Javastraat 33",
    "sg:city":"Amsterdam",
    "sg:orig_category":"Medische Apparatuur And Prothesen Fab",
    "sg:phone":"+31 20 694 2707",
    "sg:postcode":"1094 GZ",
    "sg:province":"Noord-Holland",
    "wof:name":"Dental Techniek Oost",
    "wof:placetype":"venue"
},
  "geometry": {"coordinates":[4.932984,52.363724],"type":"Point"}
}