{
  "type": "Feature",
  "properties": {
    "addr:full":"Hoogstr 19 Veghel Noord-Brabant 5462 CW",
    "addr:housenumber":"19",
    "addr:postcode":"5462 cw",
    "addr:street":"Hoogstr",
    "iso:country":"NL",
    "sg:address":"Hoogstr 19",
    "sg:city":"Veghel",
    "sg:orig_category":"Woninginrichting",
    "sg:phone":"+31 413 340 166",
    "sg:postcode":"5462 CW",
    "sg:province":"Noord-Brabant",
    "wof:name":"Lensen Bv, Frank",
    "wof:placetype":"venue"
},
  "geometry": {"coordinates":[5.6143121719,51.5938301086],"type":"Point"}
}