{
  "type": "Feature",
  "properties": {
    "addr:full":"Tenelenweg 110 Voerendaal Limburg 6367 VX",
    "addr:housenumber":"110",
    "addr:postcode":"6367 vx",
    "addr:street":"Tenelenweg",
    "iso:country":"NL",
    "sg:address":"Tenelenweg 110",
    "sg:city":"Voerendaal",
    "sg:classifiers":[
        {
            "category":"Bakery",
            "type":"Food & Drink"
        }
    ],
    "sg:phone":"+31 45 575 0044",
    "sg:postcode":"6367 VX",
    "sg:province":"Limburg",
    "sg:tags":[
        "brood",
        "banket"
    ],
    "wof:name":"L J Van Veen",
    "wof:placetype":"venue"
},
  "geometry": {"coordinates":[5.923033,50.880344],"type":"Point"}
}