{
  "type": "Feature",
  "properties": {
    "addr:full":"Willem Barentszstraat 78 UTRECHT 3572PN",
    "addr:housenumber":"78",
    "addr:postcode":"3572pn",
    "addr:street":"Willem Barentszstraat",
    "iso:country":"NL",
    "sg:address":"Willem Barentszstraat 78",
    "sg:city":"UTRECHT",
    "sg:classifiers":[
        {
            "category":"Professional",
            "subcategory":"Management & Consulting",
            "type":"Services"
        }
    ],
    "sg:postcode":"3572PN",
    "sg:website":"http://www.ec-con.nl",
    "wof:name":"EC-CON BV",
    "wof:placetype":"venue"
},
  "geometry": {"coordinates":[5.140821,52.098271],"type":"Point"}
}