{
  "type": "Feature",
  "properties": {
    "iso:country":"NL",
    "sg:address":"Wachtelenbergwg 9",
    "sg:city":"Epe",
    "sg:orig_category":"Fotoreportages",
    "sg:phone":"+31 578 615 207",
    "sg:postcode":"8162 XC",
    "sg:province":"Gelderland",
    "wof:name":"Paasman, J A F",
    "wof:placetype":"venue"
},
  "geometry": {"coordinates":[5.982345,52.355305],"type":"Point"}
}