{
  "type": "Feature",
  "properties": {
    "addr:full":"Biesboschstr 16 Amsterdam North Holland 1078 MS",
    "addr:housenumber":"16",
    "addr:postcode":"1078 ms",
    "addr:street":"Biesboschstr",
    "iso:country":"NL",
    "sg:address":"Biesboschstr 16",
    "sg:city":"Amsterdam",
    "sg:orig_category":"Binnenhuisarchitectuur",
    "sg:phone":"+31 20 679 6742",
    "sg:postcode":"1078 MS",
    "sg:province":"North Holland",
    "wof:name":"Metsing",
    "wof:placetype":"venue"
},
  "geometry": {"coordinates":[4.898898,52.345516],"type":"Point"}
}