{
  "type": "Feature",
  "properties": {
    "addr:full":"Aan De Wolf 11 Vylen Limburg 6294 BH",
    "addr:housenumber":"11",
    "addr:postcode":"6294 bh",
    "addr:street":"Aan De Wolf;Limburg",
    "iso:country":"NL",
    "sg:address":"Aan De Wolf 11",
    "sg:city":"Vylen",
    "sg:orig_category":"Adviesbureaus Bouwkosten",
    "sg:phone":"+31 43 306 2809",
    "sg:postcode":"6294 BH",
    "sg:province":"Limburg",
    "wof:name":"Voort Bv, J J P G Van Der",
    "wof:placetype":"venue"
},
  "geometry": {"coordinates":[5.967839,50.788845],"type":"Point"}
}