{
  "type": "Feature",
  "properties": {
    "iso:country":"NL",
    "sg:address":"Pleintjes 100",
    "sg:city":"Veldhoven",
    "sg:orig_category":"Schoenen",
    "sg:phone":"+31 40 230 0327",
    "sg:postcode":"5501 EC",
    "sg:province":"Noord-Brabant",
    "wof:name":"Bovendeert Bv",
    "wof:placetype":"venue"
},
  "geometry": {"coordinates":[5.407276,51.418831],"type":"Point"}
}