{
  "type": "Feature",
  "properties": {
    "addr:full":"Rogstr 11 S Gravenhage South Holland 2584 XA",
    "addr:housenumber":"11",
    "addr:postcode":"2584 xa",
    "addr:street":"Rogstr;S Gravenhage",
    "iso:country":"NL",
    "sg:address":"Rogstr 11",
    "sg:city":"S Gravenhage",
    "sg:orig_category":"Onderhoudswerken",
    "sg:phone":"+31 70 354 5334",
    "sg:postcode":"2584 XA",
    "sg:province":"South Holland",
    "wof:name":"Pronk, Jacques",
    "wof:placetype":"venue"
},
  "geometry": {"coordinates":[4.28131,52.103199],"type":"Point"}
}