{
  "type": "Feature",
  "properties": {
    "addr:full":"Rhonedreef 40 Utrecht Utrecht 3561 VA",
    "addr:housenumber":"40",
    "addr:postcode":"3561",
    "addr:street":"Rhonedreef",
    "iso:country":"NL",
    "sg:address":"Rhonedreef 40",
    "sg:city":"Utrecht",
    "sg:orig_category":"Overheidsdiensten",
    "sg:phone":"+31 30 261 8636",
    "sg:postcode":"3561 VA",
    "sg:province":"Utrecht",
    "wof:name":"Mzw Noord-Oost & Overvecht",
    "wof:placetype":"venue"
},
  "geometry": {"coordinates":[5.1158242226,52.1106719971],"type":"Point"}
}