{
  "type": "Feature",
  "properties": {
    "addr:full":"Dukdalfwg 41 Almere Flevoland 1332 BK",
    "addr:housenumber":"41",
    "addr:postcode":"1332 bk",
    "addr:street":"Dukdalfwg;Flevoland",
    "iso:country":"NL",
    "sg:address":"Dukdalfwg 41",
    "sg:city":"Almere",
    "sg:orig_category":"Verf En Lak - Fabrieken En Groothandel",
    "sg:phone":"+31 36 537 1303",
    "sg:postcode":"1332 BK",
    "sg:province":"Flevoland",
    "sg:website":"http://www.bichemie.nl",
    "wof:name":"Bichemie",
    "wof:placetype":"venue"
},
  "geometry": {"coordinates":[5.256626,52.409729],"type":"Point"}
}