{
  "type": "Feature",
  "properties": {
    "addr:full":"Hovystr 37 Veenendaal Utrecht 3904 DZ",
    "addr:housenumber":"37",
    "addr:postcode":"3904 dz",
    "addr:street":"Hovystr",
    "iso:country":"NL",
    "sg:address":"Hovystr 37",
    "sg:city":"Veenendaal",
    "sg:orig_category":"Fitnesscentra",
    "sg:phone":"+31 318 668 789",
    "sg:postcode":"3904 DZ",
    "sg:province":"Utrecht",
    "sg:website":"http://www.kangal.nl",
    "wof:name":"Kangal Fitness Sun & Health Studio",
    "wof:placetype":"venue"
},
  "geometry": {"coordinates":[5.543622,52.017685],"type":"Point"}
}