{
  "type": "Feature",
  "properties": {
    "addr:full":"V Renessewg 15 Eindhoven North Brabant 5645 JN",
    "addr:housenumber":"15",
    "addr:postcode":"5645 jn",
    "iso:country":"NL",
    "sg:address":"V Renessewg 15",
    "sg:city":"Eindhoven",
    "sg:orig_category":"Beeldende Kunstenaars",
    "sg:phone":"+31 40 212 1718",
    "sg:postcode":"5645 JN",
    "sg:province":"North Brabant",
    "wof:name":"Cats, E J",
    "wof:placetype":"venue"
},
  "geometry": {"coordinates":[5.515999794,51.4255714417],"type":"Point"}
}