{
  "type": "Feature",
  "properties": {
    "addr:full":"Kennedyln 102 Brunssum Limburg 6441 JG",
    "addr:housenumber":"102",
    "addr:postcode":"6441 jg",
    "addr:street":"Brunssum Limburg",
    "iso:country":"NL",
    "sg:address":"Kennedyln 102",
    "sg:city":"Brunssum",
    "sg:classifiers":[
        {
            "category":"Food & Beverages",
            "subcategory":"Bakery",
            "type":"Retail Goods"
        }
    ],
    "sg:phone":"+31 45 525 3356",
    "sg:postcode":"6441 JG",
    "sg:province":"Limburg",
    "sg:tags":[
        "brood",
        "en",
        "banket"
    ],
    "wof:name":"Steevens Bv",
    "wof:placetype":"venue"
},
  "geometry": {"coordinates":[5.970233,50.943302],"type":"Point"}
}