{
  "type": "Feature",
  "properties": {
    "iso:country":"NL",
    "sg:address":"Graham Bellstraat 3",
    "sg:city":"Zwolle",
    "sg:orig_category":"Autokeuringen",
    "sg:phone":"+31 38 460 0054",
    "sg:postcode":"8013 PL",
    "sg:province":"Overijssel",
    "wof:name":"Schafer Auto'S",
    "wof:placetype":"venue"
},
  "geometry": {"coordinates":[6.130061,52.485859],"type":"Point"}
}