{
  "type": "Feature",
  "properties": {
    "addr:full":"Oud Veldzichtln 25 Apeldoorn Gelderland 7322 HT",
    "addr:housenumber":"25",
    "addr:postcode":"7322 ht",
    "addr:street":"Oud Veldzichtln;Gelderland",
    "iso:country":"NL",
    "sg:address":"Oud Veldzichtln 25",
    "sg:city":"Apeldoorn",
    "sg:orig_category":"Onderwijsmateriaal",
    "sg:phone":"+31 55 366 8153",
    "sg:postcode":"7322 HT",
    "sg:province":"Gelderland",
    "wof:name":"Uit De Tijd",
    "wof:placetype":"venue"
},
  "geometry": {"coordinates":[5.976348877,52.217338562],"type":"Point"}
}