{
  "type": "Feature",
  "properties": {
    "addr:full":"Vogelenzangstr 22 Amsterdam Noord-Holland 1058 ST",
    "addr:housenumber":"22",
    "addr:postcode":"1058 st",
    "addr:street":"Vogelenzangstr",
    "iso:country":"NL",
    "sg:address":"Vogelenzangstr 22",
    "sg:city":"Amsterdam",
    "sg:orig_category":"Artiesten/Gezelschappen",
    "sg:phone":"+31 20 615 6619",
    "sg:postcode":"1058 ST",
    "sg:province":"Noord-Holland",
    "sg:website":"http://www.triomfo-infanti.nu",
    "wof:name":"Triomfo Infanti, Circus",
    "wof:placetype":"venue"
},
  "geometry": {"coordinates":[4.848259,52.354469],"type":"Point"}
}