{
  "type": "Feature",
  "properties": {
    "addr:full":"Mathildastraat 52 Oosterhout Nb Noord-Brabant 4901 HC",
    "addr:housenumber":"52",
    "addr:postcode":"4901 hc",
    "addr:street":"Mathildastraat",
    "iso:country":"NL",
    "sg:address":"Mathildastraat 52",
    "sg:city":"Oosterhout Nb",
    "sg:orig_category":"Woningbouwverenigingen",
    "sg:phone":"+31 162 491 100",
    "sg:postcode":"4901 HC",
    "sg:province":"Noord-Brabant",
    "wof:name":"Woningbouwstichting Oosterhout",
    "wof:placetype":"venue"
},
  "geometry": {"coordinates":[4.8648581505,51.6447601318],"type":"Point"}
}