{
  "type": "Feature",
  "properties": {
    "iso:country":"NL",
    "sg:address":"Pylstr 20",
    "sg:city":"Utrecht",
    "sg:orig_category":"Koeriersdiensten",
    "sg:phone":"+31 6 25047123",
    "sg:postcode":"3552 XP",
    "sg:province":"Utrecht",
    "sg:website":"http://www.aklogistics.nl",
    "wof:name":"Akl",
    "wof:placetype":"venue"
},
  "geometry": {"coordinates":[5.10422,52.107819],"type":"Point"}
}