{
  "type": "Feature",
  "properties": {
    "addr:full":"Wilhelminastraat 39 Amsterdam North Holland 1054 VV",
    "addr:housenumber":"39",
    "addr:postcode":"1054 vv",
    "addr:street":"Wilhelminastraat",
    "iso:country":"NL",
    "sg:address":"Wilhelminastraat 39",
    "sg:city":"Amsterdam",
    "sg:orig_category":"Binnenhuisarchitecten",
    "sg:phone":"+31 20 685 4660",
    "sg:postcode":"1054 VV",
    "sg:province":"North Holland",
    "wof:name":"Traza",
    "wof:placetype":"venue"
},
  "geometry": {"coordinates":[4.865906,52.362091],"type":"Point"}
}