{
  "type": "Feature",
  "properties": {
    "iso:country":"NL",
    "sg:address":"Dr. Willem Dreessingel 195",
    "sg:city":"Arnhem",
    "sg:orig_category":"Artsen And Specialisten",
    "sg:phone":"+31 26 323 6323",
    "sg:postcode":"6836 CS",
    "sg:province":"Gelderland",
    "wof:name":"Awater & Nahuijsen Huisartsenpraktijk",
    "wof:placetype":"venue"
},
  "geometry": {"coordinates":[5.886653,51.946442],"type":"Point"}
}