{
  "type": "Feature",
  "properties": {
    "iso:country":"NL",
    "sg:address":"L Brugstr 1/A",
    "sg:city":"Etten Leur",
    "sg:orig_category":"Kappers",
    "sg:phone":"+31 76 501 3575",
    "sg:postcode":"4871 CL",
    "sg:province":"North Brabant",
    "wof:name":"Cp",
    "wof:placetype":"venue"
},
  "geometry": {"coordinates":[4.6564030647,51.5863189697],"type":"Point"}
}