{
  "type": "Feature",
  "properties": {
    "addr:full":"Domineeslaan 87 Zwanenburg North Holland 1161 BW",
    "addr:housenumber":"87",
    "addr:postcode":"1161 bw",
    "addr:street":"Domineeslaan",
    "iso:country":"NL",
    "sg:address":"Domineeslaan 87",
    "sg:city":"Zwanenburg",
    "sg:orig_category":"Werving And Selectie Van Tijdelijk Personeel And Uitzendkantoren",
    "sg:phone":"+31 20 497 5150",
    "sg:postcode":"1161 BW",
    "sg:province":"North Holland",
    "wof:name":"Pja",
    "wof:placetype":"venue"
},
  "geometry": {"coordinates":[4.7396659851,52.3800506592],"type":"Point"}
}