{
  "type": "Feature",
  "properties": {
    "addr:full":"Lavendelstraat 69 Apeldoorn Gelderland 7322 PD",
    "addr:housenumber":"69",
    "addr:postcode":"7322 pd",
    "addr:street":"Lavendelstraat;Gelderland",
    "iso:country":"NL",
    "sg:address":"Lavendelstraat 69",
    "sg:city":"Apeldoorn",
    "sg:orig_category":"Muziekinstrumenten",
    "sg:phone":"+31 55 360 1650",
    "sg:postcode":"7322 PD",
    "sg:province":"Gelderland",
    "wof:name":"Piano All",
    "wof:placetype":"venue"
},
  "geometry": {"coordinates":[5.994901,52.219917],"type":"Point"}
}