{
  "type": "Feature",
  "properties": {
    "addr:full":"Gen Cronjestr 19 Haarlem Noord-Holland 2021 JB",
    "addr:housenumber":"19",
    "addr:postcode":"2021 jb",
    "iso:country":"NL",
    "sg:address":"Gen Cronjestr 19",
    "sg:city":"Haarlem",
    "sg:orig_category":"Videotheken",
    "sg:phone":"+31 23 527 7667",
    "sg:postcode":"2021 JB",
    "sg:province":"Noord-Holland",
    "wof:name":"Jumbo",
    "wof:placetype":"venue"
},
  "geometry": {"coordinates":[4.640964,52.393047],"type":"Point"}
}