{
  "type": "Feature",
  "properties": {
    "addr:full":"Boven Boukoul 6 Swalmen Limburg 6071 AC",
    "addr:housenumber":"6",
    "addr:postcode":"6071 ac",
    "addr:street":"Boven Boukoul",
    "iso:country":"NL",
    "sg:address":"Boven Boukoul 6",
    "sg:city":"Swalmen",
    "sg:orig_category":"Muziekinstrumenten Fab",
    "sg:phone":"+31 475 504 441",
    "sg:postcode":"6071 AC",
    "sg:province":"Limburg",
    "wof:name":"Stefan'S Orgelpijpen A.J. Steffani",
    "wof:placetype":"venue"
},
  "geometry": {"coordinates":[6.041664,51.214748],"type":"Point"}
}