{
  "type": "Feature",
  "properties": {
    "addr:full":"Het Kerkehout 28 Wassenaar South Holland 2245 XR",
    "addr:housenumber":"28",
    "addr:postcode":"2245 xr",
    "addr:street":"Het Kerkehout",
    "iso:country":"NL",
    "sg:address":"Het Kerkehout 28",
    "sg:city":"Wassenaar",
    "sg:orig_category":"Postzegels",
    "sg:phone":"+31 70 511 7379",
    "sg:postcode":"2245 XR",
    "sg:province":"South Holland",
    "sg:website":"http://www.gerooide.nl",
    "wof:name":"Gerooide Postzegels",
    "wof:placetype":"venue"
},
  "geometry": {"coordinates":[4.373285,52.110821],"type":"Point"}
}