{
  "type": "Feature",
  "properties": {
    "addr:full":"Binnenweg 10 Eefde Gelderland 7211 MA",
    "addr:housenumber":"10",
    "addr:postcode":"7211 ma",
    "addr:street":"Binnenweg;Gelderland",
    "iso:country":"NL",
    "sg:address":"Binnenweg 10",
    "sg:city":"Eefde",
    "sg:orig_category":"Juridische Dienstverlening",
    "sg:phone":"+31 575 513 520",
    "sg:postcode":"7211 MA",
    "sg:province":"Gelderland",
    "wof:name":"Merkenbureau Kaper",
    "wof:placetype":"venue"
},
  "geometry": {"coordinates":[6.241343,52.152611],"type":"Point"}
}