{
  "type": "Feature",
  "properties": {
    "addr:full":"Havenweg 71 Dinteloord Noord-Brabant 4671 RM",
    "addr:housenumber":"71",
    "addr:postcode":"4671 rm",
    "addr:street":"Havenweg",
    "iso:country":"NL",
    "sg:address":"Havenweg 71",
    "sg:city":"Dinteloord",
    "sg:orig_category":"Bloemen And Planten",
    "sg:phone":"+31 167 523 206",
    "sg:postcode":"4671 RM",
    "sg:province":"Noord-Brabant",
    "wof:name":"Welkoop",
    "wof:placetype":"venue"
},
  "geometry": {"coordinates":[4.382838,51.642029],"type":"Point"}
}