{
  "type": "Feature",
  "properties": {
    "addr:full":"Rigawg 5 Groningen Groningen 9723 TE",
    "addr:housenumber":"5",
    "addr:postcode":"9723 te",
    "addr:street":"Rigawg",
    "iso:country":"NL",
    "sg:address":"Rigawg 5",
    "sg:city":"Groningen",
    "sg:orig_category":"Wijnkoperijen En -Groothandel",
    "sg:phone":"+31 50 544 5750",
    "sg:postcode":"9723 TE",
    "sg:province":"Groningen",
    "wof:name":"Noor Bv",
    "wof:placetype":"venue"
},
  "geometry": {"coordinates":[6.6074528694,53.2102737427],"type":"Point"}
}