{
  "type": "Feature",
  "properties": {
    "addr:full":"Westvoorstr 60 Dinteloord Noord-Brabant 4671 CE",
    "addr:housenumber":"60",
    "addr:postcode":"4671 ce",
    "addr:street":"Westvoorstr",
    "iso:country":"NL",
    "sg:address":"Westvoorstr 60",
    "sg:city":"Dinteloord",
    "sg:orig_category":"Kappers",
    "sg:phone":"+31 167 524 208",
    "sg:postcode":"4671 CE",
    "sg:province":"Noord-Brabant",
    "wof:name":"Haren Van De Keijzer, De",
    "wof:placetype":"venue"
},
  "geometry": {"coordinates":[4.3697118759,51.6356086731],"type":"Point"}
}