{
  "type": "Feature",
  "properties": {
    "addr:full":"Dorpsstr 77 Zieuwent Gelderland 7136 LJ",
    "addr:housenumber":"77;lj",
    "addr:postcode":"7136",
    "addr:street":"Dorpsstr;Gelderland",
    "iso:country":"NL",
    "sg:address":"Dorpsstr 77",
    "sg:city":"Zieuwent",
    "sg:orig_category":"Kappers",
    "sg:phone":"+31 544 351 982",
    "sg:postcode":"7136 LJ",
    "sg:province":"Gelderland",
    "wof:name":"He-Ar",
    "wof:placetype":"venue"
},
  "geometry": {"coordinates":[6.5194001198,52.006401062],"type":"Point"}
}