{
  "type": "Feature",
  "properties": {
    "addr:full":"Korte Woldpromenade 1 Steenwijk NL.08 8331 JK",
    "addr:housenumber":"1;nl.08",
    "addr:postcode":"8331 jk",
    "addr:street":"Korte Woldpromenade",
    "iso:country":"NL",
    "sg:address":"Korte Woldpromenade 1",
    "sg:city":"Steenwijk",
    "sg:orig_category":"Juweliers",
    "sg:phone":"+31 521 512 602",
    "sg:postcode":"8331 JK",
    "sg:province":"NL.08",
    "wof:name":"Vof Juwelier Visser",
    "wof:placetype":"venue"
},
  "geometry": {"coordinates":[6.113943,52.786713],"type":"Point"}
}