{
  "type": "Feature",
  "properties": {
    "iso:country":"NL",
    "sg:address":"Acacialaan 12",
    "sg:city":"Soest",
    "sg:orig_category":"Marktonderzoekbureaus",
    "sg:phone":"+31 35 602 6137",
    "sg:postcode":"3768 AR",
    "sg:province":"Utrecht",
    "wof:name":"Trenet Bv",
    "wof:placetype":"venue"
},
  "geometry": {"coordinates":[5.30005,52.162441],"type":"Point"}
}