{
  "type": "Feature",
  "properties": {
    "addr:full":"Hoekse Aarkd 13A Ter Aar Zuid-Holland 2461 ET",
    "addr:housenumber":"13a",
    "addr:postcode":"aar;2461 et",
    "addr:street":"Ter",
    "iso:country":"NL",
    "sg:address":"Hoekse Aarkd 13A",
    "sg:city":"Ter Aar",
    "sg:orig_category":"Projectontwikkeling",
    "sg:phone":"+31 172 602 434",
    "sg:postcode":"2461 ET",
    "sg:province":"Zuid-Holland",
    "wof:name":"Nek Bv",
    "wof:placetype":"venue"
},
  "geometry": {"coordinates":[4.73157,52.18087],"type":"Point"}
}