{
  "type": "Feature",
  "properties": {
    "addr:full":"Hanzeln 276 Zwolle Overijssel 8017 JJ",
    "addr:housenumber":"276",
    "addr:postcode":"8017 jj",
    "iso:country":"NL",
    "sg:address":"Hanzeln 276",
    "sg:city":"Zwolle",
    "sg:orig_category":"Kantoor- En Bedrijfsmeubelen",
    "sg:phone":"+31 38 467 0844",
    "sg:postcode":"8017 JJ",
    "sg:province":"Overijssel",
    "wof:name":"Pfs",
    "wof:placetype":"venue"
},
  "geometry": {"coordinates":[6.0887379646,52.5125656128],"type":"Point"}
}