{
  "type": "Feature",
  "properties": {
    "addr:full":"Wellewg 75 Brielle Zuid-Holland 3232 AV",
    "addr:housenumber":"75",
    "addr:postcode":"3232 av",
    "addr:street":"Wellewg",
    "iso:country":"NL",
    "sg:address":"Wellewg 75",
    "sg:city":"Brielle",
    "sg:orig_category":"Logopedisten",
    "sg:phone":"+31 181 479 035",
    "sg:postcode":"3232 AV",
    "sg:province":"Zuid-Holland",
    "wof:name":"Bijvank, A",
    "wof:placetype":"venue"
},
  "geometry": {"coordinates":[4.152882,51.898186],"type":"Point"}
}