{
  "type": "Feature",
  "properties": {
    "iso:country":"NL",
    "sg:address":"Kapelstr 14E",
    "sg:city":"Bussum",
    "sg:orig_category":"Herenkleding",
    "sg:phone":"+31 35 693 4650",
    "sg:postcode":"1404 HX",
    "sg:province":"Noord-Holland",
    "wof:name":"Factory Outlet",
    "wof:placetype":"venue"
},
  "geometry": {"coordinates":[5.164384,52.274677],"type":"Point"}
}