{
  "type": "Feature",
  "properties": {
    "addr:full":"Kapelstraat 54 Ophemert Gelderland 4061 RD",
    "addr:housenumber":"54",
    "addr:postcode":"4061",
    "addr:street":"Kapelstraat;Gelderland;Rd",
    "iso:country":"NL",
    "sg:address":"Kapelstraat 54",
    "sg:city":"Ophemert",
    "sg:orig_category":"Makelaars In Onroerend Goed",
    "sg:phone":"+31 344 651 797",
    "sg:postcode":"4061 RD",
    "sg:province":"Gelderland",
    "wof:name":"Acre Bv",
    "wof:placetype":"venue"
},
  "geometry": {"coordinates":[5.375505,51.854389],"type":"Point"}
}