{
  "type": "Feature",
  "properties": {
    "iso:country":"NL",
    "sg:address":"Vd M De Walch Str 2",
    "sg:city":"Lichtenvoorde",
    "sg:orig_category":"Banken",
    "sg:phone":"+31 544 374 860",
    "sg:postcode":"7131 EN",
    "sg:province":"Vaud",
    "sg:website":"http://www.sns.nl",
    "wof:name":"Sns",
    "wof:placetype":"venue"
},
  "geometry": {"coordinates":[6.65772,46.56155],"type":"Point"}
}