{
  "type": "Feature",
  "properties": {
    "addr:full":"Voorw 25 Noorden California 2431 AL",
    "addr:housenumber":"25;2431",
    "addr:postcode":"al",
    "addr:street":"Voorw",
    "iso:country":"NL",
    "sg:address":"Voorw 25",
    "sg:city":"Noorden",
    "sg:orig_category":"Optiek - Fabrieken En Groothandel",
    "sg:phone":"+31 172 408 765",
    "sg:postcode":"2431 AL",
    "sg:province":"California",
    "wof:name":"Otten Bv",
    "wof:placetype":"venue"
},
  "geometry": {"coordinates":[-120.3638534546,39.3203735352],"type":"Point"}
}