{
  "type": "Feature",
  "properties": {
    "addr:full":"Bottelaarpassage 87 Almere Flevoland 1315 ER",
    "addr:housenumber":"87",
    "addr:postcode":"1315 er",
    "addr:street":"Bottelaarpassage;Flevoland",
    "iso:country":"NL",
    "sg:address":"Bottelaarpassage 87",
    "sg:city":"Almere",
    "sg:orig_category":"Fotolaboratoria",
    "sg:phone":"+31 36 533 0330",
    "sg:postcode":"1315 ER",
    "sg:province":"Flevoland",
    "sg:website":"http://www.fotoprintservice.com",
    "wof:name":"Almere Foto Print Service",
    "wof:placetype":"venue"
},
  "geometry": {"coordinates":[5.215764,52.370968],"type":"Point"}
}