{
  "type": "Feature",
  "properties": {
    "addr:full":"Grasgroen 5 Zoetermeer South Holland 2718 GZ",
    "addr:housenumber":"5",
    "addr:postcode":"2718 gz",
    "addr:street":"Grasgroen",
    "iso:country":"NL",
    "sg:address":"Grasgroen 5",
    "sg:city":"Zoetermeer",
    "sg:classifiers":[
        {
            "category":"Professional",
            "subcategory":"Accounting & Tax Preparation",
            "type":"Services"
        }
    ],
    "sg:phone":"+31 79 362 0219",
    "sg:postcode":"2718 GZ",
    "sg:province":"South Holland",
    "sg:tags":[
        "accountant"
    ],
    "wof:name":"J.H. De Wilde Accountant Administratieconsultant B",
    "wof:placetype":"venue"
},
  "geometry": {"coordinates":[4.490185,52.038677],"type":"Point"}
}