{
  "type": "Feature",
  "properties": {
    "addr:full":"Griffioen 10 Mijdrecht Utrecht 3641 LZ",
    "addr:housenumber":"10",
    "addr:postcode":"3641 lz",
    "addr:street":"Griffioen",
    "iso:country":"NL",
    "sg:address":"Griffioen 10",
    "sg:city":"Mijdrecht",
    "sg:orig_category":"Schilderwerk",
    "sg:phone":"+31 297 286 257",
    "sg:postcode":"3641 LZ",
    "sg:province":"Utrecht",
    "wof:name":"Schildersbedrijf L. Jongerling Vof",
    "wof:placetype":"venue"
},
  "geometry": {"coordinates":[4.865622,52.2127],"type":"Point"}
}