{
  "type": "Feature",
  "properties": {
    "addr:full":"Ysvogelstr 13 Venlo Limburg 5912 XW",
    "addr:housenumber":"13",
    "addr:postcode":"5912 xw",
    "addr:street":"Ysvogelstr",
    "iso:country":"NL",
    "sg:address":"Ysvogelstr 13",
    "sg:city":"Venlo",
    "sg:orig_category":"Scholen Voor Basisonderwijs",
    "sg:phone":"+31 77 351 8121",
    "sg:postcode":"5912 XW",
    "sg:province":"Limburg",
    "wof:name":"Springplank, De",
    "wof:placetype":"venue"
},
  "geometry": {"coordinates":[6.160578,51.359406],"type":"Point"}
}