{
  "type": "Feature",
  "properties": {
    "addr:full":"Mariaplaats 45 Utrecht Utrecht 3511 LL",
    "addr:housenumber":"45",
    "addr:postcode":"3511 ll",
    "addr:street":"Mariaplaats",
    "iso:country":"NL",
    "sg:address":"Mariaplaats 45",
    "sg:city":"Utrecht",
    "sg:orig_category":"Antiquiteiten",
    "sg:phone":"+31 30 232 8065",
    "sg:postcode":"3511 LL",
    "sg:province":"Utrecht",
    "wof:name":"Abbey Green",
    "wof:placetype":"venue"
},
  "geometry": {"coordinates":[5.118031,52.089085],"type":"Point"}
}