{
  "type": "Feature",
  "properties": {
    "addr:full":"Franseweg 93 Elst Ut Utrecht 3921 DG",
    "addr:housenumber":"93",
    "addr:postcode":"ut;3921 dg",
    "addr:street":"Franseweg",
    "iso:country":"NL",
    "sg:address":"Franseweg 93",
    "sg:city":"Elst Ut",
    "sg:orig_category":"Fitnesscentra",
    "sg:phone":"+31 318 472 716",
    "sg:postcode":"3921 DG",
    "sg:province":"Utrecht",
    "wof:name":"Fitness Studio Van Koningsbrugge",
    "wof:placetype":"venue"
},
  "geometry": {"coordinates":[5.498612,51.988838],"type":"Point"}
}