{
  "type": "Feature",
  "properties": {
    "addr:full":"Lauriergracht 17 Amsterdam Noord-Holland 1016 RE",
    "addr:housenumber":"17",
    "addr:postcode":"1016 re",
    "addr:street":"Lauriergracht",
    "iso:country":"NL",
    "sg:address":"Lauriergracht 17",
    "sg:city":"Amsterdam",
    "sg:orig_category":"Werving En Selectie",
    "sg:phone":"+31 20 772 4606",
    "sg:postcode":"1016 RE",
    "sg:province":"Noord-Holland",
    "wof:name":"Starterslinq Bv",
    "wof:placetype":"venue"
},
  "geometry": {"coordinates":[4.8820528984,52.3714866638],"type":"Point"}
}