{
  "type": "Feature",
  "properties": {
    "iso:country":"NL",
    "sg:address":"1E J Vd Heydenstr 161",
    "sg:city":"Amsterdam",
    "sg:orig_category":"Peuterspeelzalen",
    "sg:phone":"+31 20 679 1476",
    "sg:postcode":"1072 TS",
    "sg:province":"New York",
    "wof:name":"Koko",
    "wof:placetype":"venue"
},
  "geometry": {"coordinates":[-74.224487,42.905121],"type":"Point"}
}