{
  "type": "Feature",
  "properties": {
    "addr:full":"Beukemaplein 66 Hoogeveen Provincie Drenthe 7906 AK",
    "addr:housenumber":"66",
    "addr:postcode":"7906 ak",
    "addr:street":"Beukemaplein;Provincie",
    "iso:country":"NL",
    "sg:address":"Beukemaplein 66",
    "sg:city":"Hoogeveen",
    "sg:orig_category":"Fitnesscentra",
    "sg:phone":"+31 528 269 508",
    "sg:postcode":"7906 AK",
    "sg:province":"Provincie Drenthe",
    "wof:name":"Fantastic Sports",
    "wof:placetype":"venue"
},
  "geometry": {"coordinates":[6.478916,52.718719],"type":"Point"}
}