{
  "type": "Feature",
  "properties": {
    "addr:full":"Handelspln 99 Rotterdam South Holland 3071 PR",
    "addr:housenumber":"99",
    "addr:postcode":"3071 pr",
    "addr:street":"Handelspln",
    "iso:country":"NL",
    "sg:address":"Handelspln 99",
    "sg:city":"Rotterdam",
    "sg:orig_category":"Facilitaire Dienstverlening",
    "sg:phone":"+31 10 486 5882",
    "sg:postcode":"3071 PR",
    "sg:province":"South Holland",
    "wof:name":"Kgs",
    "wof:placetype":"venue"
},
  "geometry": {"coordinates":[4.499496,51.911209],"type":"Point"}
}