{
  "type": "Feature",
  "properties": {
    "addr:full":"Gaetano Martinolaan 85 Maastricht Limburg 6229 GS",
    "addr:housenumber":"85",
    "addr:postcode":"6229 gs",
    "addr:street":"Gaetano Martinolaan",
    "iso:country":"NL",
    "sg:address":"Gaetano Martinolaan 85",
    "sg:city":"Maastricht",
    "sg:orig_category":"Elektrische Apparatuur Gh",
    "sg:phone":"+31 43 350 9711",
    "sg:postcode":"6229 GS",
    "sg:province":"Limburg",
    "wof:name":"M & C Management And Communications Bv",
    "wof:placetype":"venue"
},
  "geometry": {"coordinates":[5.714364,50.838142],"type":"Point"}
}