{
  "type": "Feature",
  "properties": {
    "addr:full":"Steile Bank 40 Lemmer Friesland 8531 MC",
    "addr:housenumber":"40",
    "addr:postcode":"8531 mc",
    "addr:street":"Steile Bank",
    "iso:country":"NL",
    "sg:address":"Steile Bank 40",
    "sg:city":"Lemmer",
    "sg:orig_category":"Metaalafval, Schrootrecycling And Sloperijen",
    "sg:phone":"+31 514 565 332",
    "sg:postcode":"8531 MC",
    "sg:province":"Friesland",
    "wof:name":"D. Verwer",
    "wof:placetype":"venue"
},
  "geometry": {"coordinates":[5.70472,52.849453],"type":"Point"}
}