{
  "type": "Feature",
  "properties": {
    "addr:full":"Van Humboldtstraat 36 Utrecht Utrecht 3514 GR",
    "addr:housenumber":"36",
    "addr:postcode":"3514",
    "addr:street":"Van Humboldtstraat",
    "iso:country":"NL",
    "sg:address":"Van Humboldtstraat 36",
    "sg:city":"Utrecht",
    "sg:orig_category":"Advocaten And Juridische Adviseurs",
    "sg:phone":"+31 30 271 1347",
    "sg:postcode":"3514 GR",
    "sg:province":"Utrecht",
    "wof:name":"Advocatenkantoor Mr. E. Van Voolen",
    "wof:placetype":"venue"
},
  "geometry": {"coordinates":[5.122255,52.0998],"type":"Point"}
}