{
  "type": "Feature",
  "properties": {
    "addr:full":"Amsteldiep 23 Capelle Aan Den Ijssel Zuid-Holland 2904 EA",
    "addr:housenumber":"23",
    "addr:postcode":"aan den ijssel;2904 ea",
    "addr:street":"Amsteldiep",
    "iso:country":"NL",
    "sg:address":"Amsteldiep 23",
    "sg:city":"Capelle Aan Den Ijssel",
    "sg:orig_category":"Werving And Selectie Van Tijdelijk Personeel And Uitzendkantoren",
    "sg:phone":"+31 10 458 8700",
    "sg:postcode":"2904 EA",
    "sg:province":"Zuid-Holland",
    "wof:name":"Dactylo",
    "wof:placetype":"venue"
},
  "geometry": {"coordinates":[4.6020522118,51.9365272522],"type":"Point"}
}