{
  "type": "Feature",
  "properties": {
    "addr:full":"Boomryk 6 Breukelen Ut Utrecht 3621 VL",
    "addr:housenumber":"6",
    "addr:postcode":"3621 vl",
    "addr:street":"Boomryk",
    "iso:country":"NL",
    "sg:address":"Boomryk 6",
    "sg:city":"Breukelen Ut",
    "sg:orig_category":"Scholen Voor Algemeen Voortgezet Onderwijs",
    "sg:phone":"+31 346 262 238",
    "sg:postcode":"3621 VL",
    "sg:province":"Utrecht",
    "wof:name":"Roc Utrecht",
    "wof:placetype":"venue"
},
  "geometry": {"coordinates":[5.001585,52.172958],"type":"Point"}
}