{
  "type": "Feature",
  "properties": {
    "addr:full":"Platinastraat 125 Zoetermeer South Holland 2718 ST",
    "addr:housenumber":"125",
    "addr:postcode":"2718 st",
    "addr:street":"Platinastraat",
    "iso:country":"NL",
    "sg:address":"Platinastraat 125",
    "sg:city":"Zoetermeer",
    "sg:orig_category":"Kantoorartikelen",
    "sg:phone":"+31 79 361 5739",
    "sg:postcode":"2718 ST",
    "sg:province":"South Holland",
    "wof:name":"Bv Avim",
    "wof:placetype":"venue"
},
  "geometry": {"coordinates":[4.506444931,52.0374946594],"type":"Point"}
}