{
  "type": "Feature",
  "properties": {
    "addr:full":"Besterdplein 29 Tilburg North Brabant 5014 HP",
    "addr:housenumber":"29",
    "addr:postcode":"5014 hp",
    "addr:street":"Besterdplein",
    "iso:country":"NL",
    "sg:address":"Besterdplein 29",
    "sg:city":"Tilburg",
    "sg:orig_category":"Verlichting And Huishoudartikelen",
    "sg:phone":"+31 13 543 7008",
    "sg:postcode":"5014 HP",
    "sg:province":"North Brabant",
    "wof:name":"Strik & Strook",
    "wof:placetype":"venue"
},
  "geometry": {"coordinates":[5.09102,51.564415],"type":"Point"}
}