{
  "type": "Feature",
  "properties": {
    "addr:full":"Kanaalstr 103B Someren Noord-Brabant 5711 EG",
    "addr:housenumber":"103b",
    "addr:postcode":"5711 eg",
    "iso:country":"NL",
    "sg:address":"Kanaalstr 103B",
    "sg:city":"Someren",
    "sg:orig_category":"Bloemen En Planten - Groothandel",
    "sg:phone":"+31 493 495 444",
    "sg:postcode":"5711 EG",
    "sg:province":"Noord-Brabant",
    "sg:website":"http://www.carloslegers.nl",
    "wof:name":"Slegers Droogbloemen Groothandel, Carlo",
    "wof:placetype":"venue"
},
  "geometry": {"coordinates":[5.711272,51.384651],"type":"Point"}
}