{
  "type": "Feature",
  "properties": {
    "addr:full":"De Sluis 8 Vroomshoop Overijssel 7681 KB",
    "addr:housenumber":"8",
    "addr:postcode":"7681 kb",
    "addr:street":"De Sluis",
    "iso:country":"NL",
    "sg:address":"De Sluis 8",
    "sg:city":"Vroomshoop",
    "sg:orig_category":"Schilders",
    "sg:phone":"+31 546 643 683",
    "sg:postcode":"7681 KB",
    "sg:province":"Overijssel",
    "wof:name":"Blauw-Dopmeijer",
    "wof:placetype":"venue"
},
  "geometry": {"coordinates":[6.563864,52.449612],"type":"Point"}
}