{
  "type": "Feature",
  "properties": {
    "addr:full":"Van Konijnenburgweg 1 Bergen Op Zoom North Brabant 4611 HK",
    "addr:housenumber":"1",
    "addr:postcode":"4611 hk",
    "addr:street":"Van Konijnenburgweg",
    "iso:country":"NL",
    "sg:address":"Van Konijnenburgweg 1",
    "sg:city":"Bergen Op Zoom",
    "sg:orig_category":"Meubelzaken, Woning- And Keukeninrichting",
    "sg:phone":"+31 164 211 405",
    "sg:postcode":"4611 HK",
    "sg:province":"North Brabant",
    "wof:name":"Beter Bed",
    "wof:placetype":"venue"
},
  "geometry": {"coordinates":[4.28072,51.493401],"type":"Point"}
}