{
  "type": "Feature",
  "properties": {
    "addr:full":"Spechtendonk 23 Sint Willebrord Noord-Brabant 4711 LN",
    "addr:housenumber":"23",
    "addr:postcode":"4711 ln",
    "addr:street":"Spechtendonk",
    "iso:country":"NL",
    "sg:address":"Spechtendonk 23",
    "sg:city":"Sint Willebrord",
    "sg:orig_category":"Gespecialiseerde Bouw",
    "sg:phone":"+31 165 387 619",
    "sg:postcode":"4711 LN",
    "sg:province":"Noord-Brabant",
    "wof:name":"Anrico Voegbedrijf",
    "wof:placetype":"venue"
},
  "geometry": {"coordinates":[4.58513,51.540943],"type":"Point"}
}