{
  "type": "Feature",
  "properties": {
    "addr:full":"Ploegstr 2 Someren Noord-Brabant 5712 GH",
    "addr:housenumber":"2",
    "addr:postcode":"5712 gh",
    "addr:street":"Ploegstr",
    "iso:country":"NL",
    "sg:address":"Ploegstr 2",
    "sg:city":"Someren",
    "sg:orig_category":"Sanitaire Artikelen",
    "sg:phone":"+31 493 495 628",
    "sg:postcode":"5712 GH",
    "sg:province":"Noord-Brabant",
    "wof:name":"Saes, Peter",
    "wof:placetype":"venue"
},
  "geometry": {"coordinates":[5.69842,51.351479],"type":"Point"}
}