{
  "type": "Feature",
  "properties": {
    "addr:full":"Benedenkerkstr 86 Waspik Noord-Brabant 5165 CD",
    "addr:housenumber":"86",
    "addr:postcode":"5165 cd",
    "addr:street":"Benedenkerkstr",
    "iso:country":"NL",
    "sg:address":"Benedenkerkstr 86",
    "sg:city":"Waspik",
    "sg:orig_category":"Autorijscholen",
    "sg:phone":"+31 416 313 013",
    "sg:postcode":"5165 CD",
    "sg:province":"Noord-Brabant",
    "wof:name":"Roksnoer, H",
    "wof:placetype":"venue"
},
  "geometry": {"coordinates":[4.931216,51.686466],"type":"Point"}
}