{
  "type": "Feature",
  "properties": {
    "addr:full":"Tilburgseweg 184 Goirle Noord-Brabant 5051 AN",
    "addr:housenumber":"184",
    "addr:postcode":"5051 an",
    "addr:street":"Tilburgseweg",
    "iso:country":"NL",
    "sg:address":"Tilburgseweg 184",
    "sg:city":"Goirle",
    "sg:orig_category":"Paramedische Behandelingen",
    "sg:phone":"+31 13 532 2622",
    "sg:postcode":"5051 AN",
    "sg:province":"Noord-Brabant",
    "wof:name":"De Meiboom Kraamhotel",
    "wof:placetype":"venue"
},
  "geometry": {"coordinates":[5.062285,51.535831],"type":"Point"}
}