{
  "type": "Feature",
  "properties": {
    "iso:country":"NL",
    "sg:address":"Ringbaan Oost 246",
    "sg:city":"Tilburg",
    "sg:orig_category":"Schoonheidssalons",
    "sg:phone":"+31 13 544 7576",
    "sg:postcode":"5018 HC",
    "sg:province":"North Brabant",
    "wof:name":"Schoonheidssalon Boa Dia",
    "wof:placetype":"venue"
},
  "geometry": {"coordinates":[5.10571,51.555893],"type":"Point"}
}