{
  "type": "Feature",
  "properties": {
    "addr:full":"Vondelstraat 31 Vlaardingen South Holland 3131 WT",
    "addr:housenumber":"31",
    "addr:postcode":"3131 wt",
    "addr:street":"Vondelstraat",
    "iso:country":"NL",
    "sg:address":"Vondelstraat 31",
    "sg:city":"Vlaardingen",
    "sg:classifiers":[
        {
            "category":"Food & Beverages",
            "subcategory":"Fruits & Vegetables",
            "type":"Retail Goods"
        }
    ],
    "sg:phone":"+31 10 434 2977",
    "sg:postcode":"3131 WT",
    "sg:province":"South Holland",
    "sg:tags":[
        "groenten"
    ],
    "wof:name":"P.A. Janson",
    "wof:placetype":"venue"
},
  "geometry": {"coordinates":[4.336911,51.911018],"type":"Point"}
}