{
  "type": "Feature",
  "properties": {
    "iso:country":"NL",
    "sg:address":"Raadhuisstraat 1",
    "sg:city":"Grou",
    "sg:orig_category":"Drukkerijen And Copyshops",
    "sg:phone":"+31 566 621 441",
    "sg:postcode":"9001 AG",
    "sg:province":"Friesland",
    "wof:name":"Sporthuis It Beaken",
    "wof:placetype":"venue"
},
  "geometry": {"coordinates":[5.839555,53.096321],"type":"Point"}
}