{
  "type": "Feature",
  "properties": {
    "iso:country":"NL",
    "sg:address":"Bilgaardpassage 22",
    "sg:city":"Leeuwarden",
    "sg:orig_category":"Parketvloeren",
    "sg:phone":"+31 58 267 1500",
    "sg:postcode":"8918 HR",
    "sg:province":"Provincie Friesland",
    "wof:name":"Overeem Woontrends",
    "wof:placetype":"venue"
},
  "geometry": {"coordinates":[5.794146,53.215591],"type":"Point"}
}