{
  "type": "Feature",
  "properties": {
    "addr:full":"Gulden Huis 19 Oss Noord-Brabant 5346 VN",
    "addr:housenumber":"19",
    "addr:postcode":"5346 vn",
    "addr:street":"Gulden Huis",
    "iso:country":"NL",
    "sg:address":"Gulden Huis 19",
    "sg:city":"Oss",
    "sg:orig_category":"Artsen - Huisartsen",
    "sg:phone":"+31 412 623 422",
    "sg:postcode":"5346 VN",
    "sg:province":"Noord-Brabant",
    "wof:name":"Schouten, S J M",
    "wof:placetype":"venue"
},
  "geometry": {"coordinates":[5.516784,51.77726],"type":"Point"}
}