{
  "type": "Feature",
  "properties": {
    "addr:full":"Mauritswg 35 Rotterdam Zuid-Holland 3012 JT",
    "addr:housenumber":"35",
    "addr:postcode":"3012 jt",
    "addr:street":"Mauritswg",
    "iso:country":"NL",
    "sg:address":"Mauritswg 35",
    "sg:city":"Rotterdam",
    "sg:orig_category":"Verenigingen En Stichtingen",
    "sg:phone":"+31 10 433 5833",
    "sg:postcode":"3012 JT",
    "sg:province":"Zuid-Holland",
    "sg:website":"http://www.rks.nl",
    "wof:name":"Rotterdamse Kunststichting",
    "wof:placetype":"venue"
},
  "geometry": {"coordinates":[4.472655,51.918976],"type":"Point"}
}