{
  "type": "Feature",
  "properties": {
    "iso:country":"NL",
    "sg:address":"Distellaan 17",
    "sg:city":"De Kwakel",
    "sg:orig_category":"Makelaars In Onroerend Goed",
    "sg:phone":"+31 297 521 248",
    "sg:postcode":"1424 SC",
    "sg:province":"Noord-Holland",
    "wof:name":"Falkenstein Bedrijfshuisvesting",
    "wof:placetype":"venue"
},
  "geometry": {"coordinates":[4.796258,52.238651],"type":"Point"}
}