{
  "type": "Feature",
  "properties": {
    "iso:country":"NL",
    "sg:address":"Holtjesstr 28",
    "sg:city":"Almelo",
    "sg:orig_category":"Woninginrichting",
    "sg:phone":"+31 546 815 801",
    "sg:postcode":"7607 JG",
    "sg:province":"Overijssel",
    "wof:name":"Stokvis, Hennie",
    "wof:placetype":"venue"
},
  "geometry": {"coordinates":[6.6649661064,52.3530006409],"type":"Point"}
}