{
  "type": "Feature",
  "properties": {
    "addr:full":"Holtjesstr 28 Almelo Overijssel 7607 JG",
    "addr:housenumber":"28",
    "addr:postcode":"7607 jg",
    "addr:street":"Holtjesstr",
    "iso:country":"NL",
    "sg:address":"Holtjesstr 28",
    "sg:city":"Almelo",
    "sg:orig_category":"Woninginrichting",
    "sg:phone":"+31 546 815 801",
    "sg:postcode":"7607 JG",
    "sg:province":"Overijssel",
    "wof:name":"Stokvis, Hennie",
    "wof:placetype":"venue"
},
  "geometry": {"coordinates":[6.6649661064,52.3530006409],"type":"Point"}
}