{
  "type": "Feature",
  "properties": {
    "addr:full":"Edelhertstr 2-4 Capelle Ad Yssel South Holland 2901 BJ",
    "addr:housenumber":"2-4;2901",
    "addr:postcode":"bj",
    "addr:street":"Edelhertstr;Yssel",
    "iso:country":"NL",
    "sg:address":"Edelhertstr 2-4",
    "sg:city":"Capelle Ad Yssel",
    "sg:orig_category":"Centrale Verwarming - Installatie En Onderhoud",
    "sg:phone":"+31 10 286 9319",
    "sg:postcode":"2901 BJ",
    "sg:province":"South Holland",
    "wof:name":"Aceve Totaalinstallateurs",
    "wof:placetype":"venue"
},
  "geometry": {"coordinates":[4.557218,51.91114],"type":"Point"}
}