{
  "type": "Feature",
  "properties": {
    "addr:full":"Postbus 20111 Apeldoorn Noord-Holland 7302 HC",
    "addr:postcode":"20111;7302 hc",
    "addr:street":"Postbus",
    "iso:country":"NL",
    "sg:address":"Postbus 20111",
    "sg:city":"Apeldoorn",
    "sg:orig_category":"Bedrijfsopleidingen",
    "sg:phone":"+31 55 541 7156",
    "sg:postcode":"7302 HC",
    "sg:province":"Noord-Holland",
    "wof:name":"Geo, Hogeschool",
    "wof:placetype":"venue"
},
  "geometry": {"coordinates":[5.96246,52.214329],"type":"Point"}
}