{
  "type": "Feature",
  "properties": {
    "addr:full":"Postbus 102 Mydrecht 3640 AC",
    "addr:housenumber":"102",
    "addr:postcode":"3640 ac",
    "addr:street":"Postbus",
    "iso:country":"NL",
    "sg:address":"Postbus 102",
    "sg:city":"Mydrecht",
    "sg:orig_category":"Verlichtingsartikelen - Groothandel",
    "sg:phone":"+31 297 237 237",
    "sg:postcode":"3640 AC",
    "sg:website":"http://www.heno-elektro.nl",
    "wof:name":"H & O Bv",
    "wof:placetype":"venue"
},
  "geometry": {"coordinates":[4.86584,52.2075],"type":"Point"}
}