{
  "type": "Feature",
  "properties": {
    "addr:full":"Edisonstr 17 Harlingen Friesland 8861 NA",
    "addr:housenumber":"17",
    "addr:postcode":"8861 na",
    "addr:street":"Edisonstr",
    "iso:country":"NL",
    "sg:address":"Edisonstr 17",
    "sg:city":"Harlingen",
    "sg:orig_category":"Horecabenodigdheden",
    "sg:phone":"+31 517 432 732",
    "sg:postcode":"8861 NA",
    "sg:province":"Friesland",
    "wof:name":"Selekt Vleesservice",
    "wof:placetype":"venue"
},
  "geometry": {"coordinates":[5.452824,53.180634],"type":"Point"}
}