{
  "type": "Feature",
  "properties": {
    "addr:full":"L Brugstr 41 Breda North Brabant 4811 WP",
    "addr:housenumber":"41",
    "addr:postcode":"4811 wp",
    "iso:country":"NL",
    "sg:address":"L Brugstr 41",
    "sg:city":"Breda",
    "sg:orig_category":"Hoortoestellen",
    "sg:phone":"+31 76 521 3746",
    "sg:postcode":"4811 WP",
    "sg:province":"North Brabant",
    "wof:name":"Schoonenberg Hoorcomfort",
    "wof:placetype":"venue"
},
  "geometry": {"coordinates":[4.773286,51.58799],"type":"Point"}
}