{
  "type": "Feature",
  "properties": {
    "iso:country":"NL",
    "sg:address":"Arena Boulev 226",
    "sg:city":"Amsterdam Zuidoost",
    "sg:orig_category":"Meubelen",
    "sg:phone":"+31 20 672 1051",
    "sg:postcode":"1101 DJ",
    "sg:province":"North Holland",
    "sg:website":"http://www.interliving.nl",
    "wof:name":"Interliving",
    "wof:placetype":"venue"
},
  "geometry": {"coordinates":[4.94054,52.312859],"type":"Point"}
}