{
  "type": "Feature",
  "properties": {
    "addr:full":"Oudeschans 40 Amsterdam Noord-Holland 1011 LC",
    "addr:housenumber":"40",
    "addr:postcode":"1011 lc",
    "addr:street":"Oudeschans",
    "iso:country":"NL",
    "sg:address":"Oudeschans 40",
    "sg:city":"Amsterdam",
    "sg:orig_category":"Meubelreparatie And -Restauratie",
    "sg:phone":"+31 20 693 5452",
    "sg:postcode":"1011 LC",
    "sg:province":"Noord-Holland",
    "wof:name":"Meubelstoffeerderij Acanthus",
    "wof:placetype":"venue"
},
  "geometry": {"coordinates":[4.903639,52.371304],"type":"Point"}
}