{
  "type": "Feature",
  "properties": {
    "addr:full":"Dykhuizenwg 92 Appingedam Groningen 9903 AG",
    "addr:housenumber":"92",
    "addr:postcode":"9903",
    "addr:street":"Dykhuizenwg",
    "iso:country":"NL",
    "sg:address":"Dykhuizenwg 92",
    "sg:city":"Appingedam",
    "sg:orig_category":"Verzekeringen - Verzekeringskantoren",
    "sg:phone":"+31 596 620 457",
    "sg:postcode":"9903 AG",
    "sg:province":"Groningen",
    "wof:name":"Schonewille",
    "wof:placetype":"venue"
},
  "geometry": {"coordinates":[6.842595,53.319118],"type":"Point"}
}