{
  "type": "Feature",
  "properties": {
    "addr:full":"Dr Kantersln 214 Grave North Brabant 5361 NL",
    "addr:housenumber":"214",
    "addr:postcode":"5361 nl",
    "addr:street":"Grave North",
    "iso:country":"NL",
    "sg:address":"Dr Kantersln 214",
    "sg:city":"Grave",
    "sg:orig_category":"Adviesbureaus Bedrijfsorganisatie",
    "sg:phone":"+31 486 422 709",
    "sg:postcode":"5361 NL",
    "sg:province":"North Brabant",
    "sg:website":"http://www.com-tactics.com",
    "wof:name":"Com Tactics",
    "wof:placetype":"venue"
},
  "geometry": {"coordinates":[5.750393,51.753738],"type":"Point"}
}