{
  "type": "Feature",
  "properties": {
    "addr:full":"Nannie Van Wehlstraat 1 Leiden South Holland 2331 GB",
    "addr:housenumber":"1",
    "addr:postcode":"2331 gb",
    "addr:street":"Nannie Van Wehlstraat",
    "iso:country":"NL",
    "sg:address":"Nannie Van Wehlstraat 1",
    "sg:city":"Leiden",
    "sg:orig_category":"Loodgieterswerk, Verwarming And Sanitaire Installaties",
    "sg:phone":"+31 71 531 4926",
    "sg:postcode":"2331 GB",
    "sg:province":"South Holland",
    "wof:name":"H. Van Der Zeeuw En Zn",
    "wof:placetype":"venue"
},
  "geometry": {"coordinates":[4.454975,52.153728],"type":"Point"}
}