{
  "type": "Feature",
  "properties": {
    "addr:full":"Oude Roswinkel Wg 59 Emmen Drenthe 7822 AC",
    "addr:housenumber":"59",
    "addr:postcode":"7822 ac",
    "addr:street":"Oude;Wg",
    "iso:country":"NL",
    "sg:address":"Oude Roswinkel Wg 59",
    "sg:city":"Emmen",
    "sg:orig_category":"Sportverenigingen En Ontspannings- Verenigingen",
    "sg:phone":"+31 591 630 357",
    "sg:postcode":"7822 AC",
    "sg:province":"Drenthe",
    "wof:name":"Euterpe Harmonie",
    "wof:placetype":"venue"
},
  "geometry": {"coordinates":[6.906258,52.797909],"type":"Point"}
}