{
  "type": "Feature",
  "properties": {
    "iso:country":"NL",
    "sg:address":"F Hendrikstr 30",
    "sg:city":"Capelle Ad Yssel",
    "sg:orig_category":"Glasdecoratie",
    "sg:phone":"+31 10 451 4592",
    "sg:postcode":"2902 HE",
    "sg:province":"Zuid-Holland",
    "wof:name":"Aadjes Tiffany",
    "wof:placetype":"venue"
},
  "geometry": {"coordinates":[4.57697,51.926311],"type":"Point"}
}