{
  "type": "Feature",
  "properties": {
    "addr:full":"Kreijelmusweg 4 Ospel Limburg 6035 PA",
    "addr:housenumber":"4",
    "addr:postcode":"6035 pa",
    "addr:street":"Kreijelmusweg",
    "iso:country":"NL",
    "sg:address":"Kreijelmusweg 4",
    "sg:city":"Ospel",
    "sg:orig_category":"Pluimveehouderijen",
    "sg:phone":"+31 495 632 030",
    "sg:postcode":"6035 PA",
    "sg:province":"Limburg",
    "wof:name":"Pluimveebedrijf Frits Jacobs Bv",
    "wof:placetype":"venue"
},
  "geometry": {"coordinates":[-86.165451,34.620892],"type":"Point"}
}