{
  "type": "Feature",
  "properties": {
    "addr:full":"J De Snoostr 1 Rotterdam Zuid-Holland 3065 NE",
    "addr:housenumber":"1",
    "addr:postcode":"3065 ne",
    "addr:street":"J De Snoostr",
    "iso:country":"NL",
    "sg:address":"J De Snoostr 1",
    "sg:city":"Rotterdam",
    "sg:orig_category":"Beveiliging",
    "sg:phone":"+31 10 447 3022",
    "sg:postcode":"3065 NE",
    "sg:province":"Zuid-Holland",
    "wof:name":"Cdr Bv",
    "wof:placetype":"venue"
},
  "geometry": {"coordinates":[4.544109,51.924347],"type":"Point"}
}