{
  "type": "Feature",
  "properties": {
    "addr:full":"Linnaeusstr 124 S Gravenhage South Holland 2522 GV",
    "addr:housenumber":"124",
    "addr:postcode":"2522 gv",
    "addr:street":"S Gravenhage",
    "iso:country":"NL",
    "sg:address":"Linnaeusstr 124",
    "sg:city":"S Gravenhage",
    "sg:orig_category":"Kappers",
    "sg:phone":"+31 70 399 6363",
    "sg:postcode":"2522 GV",
    "sg:province":"South Holland",
    "wof:name":"Eclair",
    "wof:placetype":"venue"
},
  "geometry": {"coordinates":[4.3272900581,52.0608482361],"type":"Point"}
}