{
  "type": "Feature",
  "properties": {
    "addr:full":"Kramersweide 12 Terborg Gelderland 7061 BD",
    "addr:housenumber":"12",
    "addr:postcode":"7061 bd",
    "addr:street":"Kramersweide;Gelderland",
    "iso:country":"NL",
    "sg:address":"Kramersweide 12",
    "sg:city":"Terborg",
    "sg:orig_category":"Fotojournalisten Freelance",
    "sg:phone":"+31 315 329 679",
    "sg:postcode":"7061 BD",
    "sg:province":"Gelderland",
    "wof:name":"Vliet, Ton Van",
    "wof:placetype":"venue"
},
  "geometry": {"coordinates":[6.353326,51.920528],"type":"Point"}
}