{
  "type": "Feature",
  "properties": {
    "addr:full":"Kalkbranderstr 35 Zwolle Overijssel 8043 BG",
    "addr:housenumber":"35",
    "addr:postcode":"8043",
    "addr:street":"Kalkbranderstr",
    "iso:country":"NL",
    "sg:address":"Kalkbranderstr 35",
    "sg:city":"Zwolle",
    "sg:orig_category":"Adviesbureaus Bedrijfsorganisatie",
    "sg:phone":"+31 38 420 1318",
    "sg:postcode":"8043 BG",
    "sg:province":"Overijssel",
    "wof:name":"Collet",
    "wof:placetype":"venue"
},
  "geometry": {"coordinates":[6.064162,52.534752],"type":"Point"}
}