{
  "type": "Feature",
  "properties": {
    "addr:full":"Schoutenstraat 11 Utrecht Utrecht 3512 GA",
    "addr:housenumber":"11",
    "addr:postcode":"3512 ga",
    "addr:street":"Schoutenstraat",
    "iso:country":"NL",
    "sg:address":"Schoutenstraat 11",
    "sg:city":"Utrecht",
    "sg:orig_category":"Drogisterijen",
    "sg:phone":"+31 30 231 6934",
    "sg:postcode":"3512 GA",
    "sg:province":"Utrecht",
    "wof:name":"Abraham Mostert Bv",
    "wof:placetype":"venue"
},
  "geometry": {"coordinates":[5.119558,52.092682],"type":"Point"}
}