{
  "type": "Feature",
  "properties": {
    "iso:country":"NL",
    "sg:address":"Ruinerwg 26",
    "sg:city":"Koekange",
    "sg:orig_category":"Scholen Voor Basisonderwijs",
    "sg:phone":"+31 522 451 546",
    "sg:postcode":"7958 RC",
    "sg:province":"Provincie Drenthe",
    "wof:name":"Veldkei Openb, De",
    "wof:placetype":"venue"
},
  "geometry": {"coordinates":[6.334824,52.715794],"type":"Point"}
}