{
  "type": "Feature",
  "properties": {
    "addr:full":"Singel 3 Puttershoek South Holland 3297 BS",
    "addr:housenumber":"3",
    "addr:postcode":"3297 bs",
    "addr:street":"Singel",
    "iso:country":"NL",
    "sg:address":"Singel 3",
    "sg:city":"Puttershoek",
    "sg:classifiers":[
        {
            "category":"Education",
            "subcategory":"Preschool",
            "type":"Public Place"
        }
    ],
    "sg:phone":"+31 78 676 3807",
    "sg:postcode":"3297 BS",
    "sg:province":"South Holland",
    "sg:tags":[
        "kleuteronderwijs",
        "basis-"
    ],
    "wof:name":"Openbare Basisschool Het Driespan",
    "wof:placetype":"venue"
},
  "geometry": {"coordinates":[4.564252,51.803505],"type":"Point"}
}