{
  "type": "Feature",
  "properties": {
    "addr:full":"Postbus 141 Gilze Noord-Brabant 5126 ZJ",
    "addr:housenumber":"141",
    "addr:postcode":"5126 zj",
    "addr:street":"Postbus",
    "iso:country":"NL",
    "sg:address":"Postbus 141",
    "sg:city":"Gilze",
    "sg:orig_category":"Sportverenigingen En Ontspannings- Verenigingen",
    "sg:phone":"+31 161 226 030",
    "sg:postcode":"5126 ZJ",
    "sg:province":"Noord-Brabant",
    "sg:website":"http://www.dit.is./glcillustrious",
    "wof:name":"Illustrious, Zweefvliegclub",
    "wof:placetype":"venue"
},
  "geometry": {"coordinates":[4.942423,51.541756],"type":"Point"}
}