{
  "type": "Feature",
  "properties": {
    "addr:full":"Osdorppln 382 Amsterdam North Holland 1068 EV",
    "addr:housenumber":"382",
    "addr:postcode":"1068 ev",
    "iso:country":"NL",
    "sg:address":"Osdorppln 382",
    "sg:city":"Amsterdam",
    "sg:orig_category":"Schoenen",
    "sg:phone":"+31 20 619 6528",
    "sg:postcode":"1068 EV",
    "sg:province":"North Holland",
    "wof:name":"Andorra - Shoes",
    "wof:placetype":"venue"
},
  "geometry": {"coordinates":[4.804872,52.359444],"type":"Point"}
}