{
  "type": "Feature",
  "properties": {
    "addr:full":"Menkema S Uiterdijk 6 Uithuizen Groningen 9981 TM",
    "addr:housenumber":"6",
    "addr:postcode":"9981 tm",
    "addr:street":"S Uiterdijk",
    "iso:country":"NL",
    "sg:address":"Menkema S Uiterdijk 6",
    "sg:city":"Uithuizen",
    "sg:orig_category":"Bloemen And Planten",
    "sg:phone":"+31 595 433 830",
    "sg:postcode":"9981 TM",
    "sg:province":"Groningen",
    "wof:name":"W.A. Quak",
    "wof:placetype":"venue"
},
  "geometry": {"coordinates":[6.684523,53.424061],"type":"Point"}
}