{
  "type": "Feature",
  "properties": {
    "addr:full":"Roelof Hartstraat 24 Amsterdam North Holland 1071 VJ",
    "addr:housenumber":"24",
    "addr:postcode":"1071 vj",
    "addr:street":"Roelof Hartstraat",
    "iso:country":"NL",
    "sg:address":"Roelof Hartstraat 24",
    "sg:city":"Amsterdam",
    "sg:orig_category":"Autoverhuur",
    "sg:phone":"+31 20 671 1571",
    "sg:postcode":"1071 VJ",
    "sg:province":"North Holland",
    "wof:name":"Luxor Autoverhuur Bv",
    "wof:placetype":"venue"
},
  "geometry": {"coordinates":[4.883328,52.352379],"type":"Point"}
}