{
  "type": "Feature",
  "properties": {
    "iso:country":"NL",
    "sg:address":"Centauriestr 34",
    "sg:city":"Eindhoven",
    "sg:orig_category":"Horloges En Klokken - Reparatie En Onderhoud",
    "sg:phone":"+31 40 211 9961",
    "sg:postcode":"5643 JL",
    "sg:province":"Noord-Brabant",
    "wof:name":"Aarts, T A L",
    "wof:placetype":"venue"
},
  "geometry": {"coordinates":[5.499611,51.417709],"type":"Point"}
}