{
  "type": "Feature",
  "properties": {
    "addr:full":"Noorderhoofdstr 150 Krommenie Noord-Holland 1561 AX",
    "addr:housenumber":"150",
    "addr:postcode":"1561 ax",
    "iso:country":"NL",
    "sg:address":"Noorderhoofdstr 150",
    "sg:city":"Krommenie",
    "sg:orig_category":"Loodgieters",
    "sg:phone":"+31 6 18953159",
    "sg:postcode":"1561 AX",
    "sg:province":"Noord-Holland",
    "wof:name":"Legdeur",
    "wof:placetype":"venue"
},
  "geometry": {"coordinates":[4.7723,52.50246],"type":"Point"}
}