{
  "type": "Feature",
  "properties": {
    "iso:country":"NL",
    "sg:address":"Staten Bolwerk 24",
    "sg:city":"Haarlem",
    "sg:orig_category":"Vertalers",
    "sg:phone":"+31 23 531 1064",
    "sg:postcode":"2011 ML",
    "sg:province":"Noord-Holland",
    "wof:name":"Bakermans, Drs T J J M",
    "wof:placetype":"venue"
},
  "geometry": {"coordinates":[4.63545,52.388947],"type":"Point"}
}