{
  "type": "Feature",
  "properties": {
    "iso:country":"NL",
    "sg:address":"Oude Veiling 4",
    "sg:city":"Maasland",
    "sg:orig_category":"Wegen And Sportterreinen",
    "sg:phone":"+31 10 599 1810",
    "sg:postcode":"3155 EN",
    "sg:province":"Zuid-Holland",
    "wof:name":"Kv Bouw Bv",
    "wof:placetype":"venue"
},
  "geometry": {"coordinates":[4.2712001801,51.9251899719],"type":"Point"}
}