{
  "type": "Feature",
  "properties": {
    "addr:full":"Waterstr 42 Tiel Gelderland 4001 AP",
    "addr:housenumber":"42",
    "addr:postcode":"4001 ap",
    "addr:street":"Waterstr;Gelderland",
    "iso:country":"NL",
    "sg:address":"Waterstr 42",
    "sg:city":"Tiel",
    "sg:orig_category":"Sportschoenen - Winkels",
    "sg:phone":"+31 344 626 397",
    "sg:postcode":"4001 AP",
    "sg:province":"Gelderland",
    "sg:website":"http://www.aktiesport.nl",
    "wof:name":"Aktiesport",
    "wof:placetype":"venue"
},
  "geometry": {"coordinates":[5.430696,51.888096],"type":"Point"}
}