{
  "type": "Feature",
  "properties": {
    "addr:full":"Siriusstr 11 Tilburg Noord-Brabant 5015 BT",
    "addr:housenumber":"11",
    "addr:postcode":"5015 bt",
    "addr:street":"Siriusstr",
    "iso:country":"NL",
    "sg:address":"Siriusstr 11",
    "sg:city":"Tilburg",
    "sg:orig_category":"Metaalveredeling",
    "sg:phone":"+31 13 542 7627",
    "sg:postcode":"5015 BT",
    "sg:province":"Noord-Brabant",
    "wof:name":"Loa Bv",
    "wof:placetype":"venue"
},
  "geometry": {"coordinates":[5.113881,51.578587],"type":"Point"}
}