{
  "type": "Feature",
  "properties": {
    "addr:full":"3E Oomsberg 30 Vledderveen Gn Groningen 9585 PG",
    "addr:housenumber":"30",
    "addr:postcode":"gn;9585 pg",
    "addr:street":"3E Oomsberg",
    "iso:country":"NL",
    "sg:address":"3E Oomsberg 30",
    "sg:city":"Vledderveen Gn",
    "sg:orig_category":"Bloemen And Planten",
    "sg:phone":"+31 599 454 498",
    "sg:postcode":"9585 PG",
    "sg:province":"Groningen",
    "wof:name":"Tuincentrum Veldhuis",
    "wof:placetype":"venue"
},
  "geometry": {"coordinates":[7.01885,52.970905],"type":"Point"}
}