{
  "type": "Feature",
  "properties": {
    "addr:full":"Kievitln 95 Gebouw Kwakelhuis Schagen Noord-Holland 1742 AC",
    "addr:housenumber":"95",
    "addr:postcode":"1742 ac",
    "addr:street":"Kievitln;Schagen",
    "iso:country":"NL",
    "sg:address":"Kievitln 95 Gebouw Kwakelhuis",
    "sg:city":"Schagen",
    "sg:orig_category":"Marketingbureaus",
    "sg:phone":"+31 224 215 291",
    "sg:postcode":"1742 AC",
    "sg:province":"Noord-Holland",
    "wof:name":"3R",
    "wof:placetype":"venue"
},
  "geometry": {"coordinates":[4.79503,52.78484],"type":"Point"}
}