{
  "type": "Feature",
  "properties": {
    "addr:full":"Overburgkd 89 Voorburg South Holland 2275 XX",
    "addr:housenumber":"89",
    "addr:postcode":"2275 xx",
    "addr:street":"Overburgkd",
    "iso:country":"NL",
    "sg:address":"Overburgkd 89",
    "sg:city":"Voorburg",
    "sg:orig_category":"Adviesbureaus Bedrijfsorganisatie",
    "sg:phone":"+31 70 386 8429",
    "sg:postcode":"2275 XX",
    "sg:province":"South Holland",
    "wof:name":"Knoet",
    "wof:placetype":"venue"
},
  "geometry": {"coordinates":[4.353,52.062248],"type":"Point"}
}