{
  "type": "Feature",
  "properties": {
    "addr:full":"Krytenberg 11 Oosterhout Nb Noord-Brabant 4904 PW",
    "addr:housenumber":"11",
    "addr:postcode":"4904 pw",
    "addr:street":"Krytenberg",
    "iso:country":"NL",
    "sg:address":"Krytenberg 11",
    "sg:city":"Oosterhout Nb",
    "sg:orig_category":"Onroerende Goederen",
    "sg:phone":"+31 162 459 160",
    "sg:postcode":"4904 PW",
    "sg:province":"Noord-Brabant",
    "wof:name":"Recrea Domus Bv",
    "wof:placetype":"venue"
},
  "geometry": {"coordinates":[4.843391,51.625614],"type":"Point"}
}