{
  "type": "Feature",
  "properties": {
    "addr:full":"Haarlemmerstrwg 149 Halfweg Nh Noord-Holland 1165 MK",
    "addr:housenumber":"149",
    "addr:postcode":"1165",
    "iso:country":"NL",
    "sg:address":"Haarlemmerstrwg 149",
    "sg:city":"Halfweg Nh",
    "sg:orig_category":"Zand En Grind - Vervoer",
    "sg:phone":"+31 20 497 4871",
    "sg:postcode":"1165 MK",
    "sg:province":"Noord-Holland",
    "wof:name":"Markus Bv",
    "wof:placetype":"venue"
},
  "geometry": {"coordinates":[4.75446,52.383404],"type":"Point"}
}