{
  "type": "Feature",
  "properties": {
    "addr:full":"Bellstr 1C Nykerk Gld Gelderland 3861 NP",
    "addr:housenumber":"1c",
    "addr:postcode":"3861 np",
    "addr:street":"Bellstr;Nykerk Gld Gelderland",
    "iso:country":"NL",
    "sg:address":"Bellstr 1C",
    "sg:city":"Nykerk Gld",
    "sg:orig_category":"Verpakkingen En Verpakkingsmaterialen",
    "sg:phone":"+31 33 465 8237",
    "sg:postcode":"3861 NP",
    "sg:province":"Gelderland",
    "sg:website":"http://www.ho-wipe.nl",
    "wof:name":"Wipe",
    "wof:placetype":"venue"
},
  "geometry": {"coordinates":[5.4831,52.221569],"type":"Point"}
}