{
  "type": "Feature",
  "properties": {
    "addr:full":"Melkweg 10 Dreumel Gelderland 6621 BT",
    "addr:housenumber":"10",
    "addr:postcode":"6621 bt",
    "addr:street":"Melkweg;Gelderland",
    "iso:country":"NL",
    "sg:address":"Melkweg 10",
    "sg:city":"Dreumel",
    "sg:orig_category":"Autokeuringen",
    "sg:phone":"+31 487 572 856",
    "sg:postcode":"6621 BT",
    "sg:province":"Gelderland",
    "wof:name":"M.J.M. La Garde",
    "wof:placetype":"venue"
},
  "geometry": {"coordinates":[5.444,51.858299],"type":"Point"}
}