{
  "type": "Feature",
  "properties": {
    "addr:full":"Molendk 70 S Heerenhoek Zeeland 4453 VA",
    "addr:housenumber":"70",
    "addr:postcode":"4453",
    "addr:street":"Molendk;S Heerenhoek Zeeland",
    "iso:country":"NL",
    "sg:address":"Molendk 70",
    "sg:city":"S Heerenhoek",
    "sg:orig_category":"Pompen - Revisie",
    "sg:phone":"+31 113 561 383",
    "sg:postcode":"4453 VA",
    "sg:province":"Zeeland",
    "wof:name":"Pomptechn Zeeland",
    "wof:placetype":"venue"
},
  "geometry": {"coordinates":[3.767036,51.459797],"type":"Point"}
}