{
  "type": "Feature",
  "properties": {
    "iso:country":"NL",
    "sg:address":"Sportln 2",
    "sg:city":"Oud Beyerland",
    "sg:orig_category":"Artsen - Huisartsen",
    "sg:phone":"+31 186 617 999",
    "sg:postcode":"3261 AV",
    "sg:province":"South Holland",
    "wof:name":"Nieuwaal, J W P Van",
    "wof:placetype":"venue"
},
  "geometry": {"coordinates":[4.42806,51.807892],"type":"Point"}
}