{
  "type": "Feature",
  "properties": {
    "iso:country":"NL",
    "sg:address":"Parallelweg 101",
    "sg:city":"Veenendaal",
    "sg:orig_category":"Bedrijfsinventaris Gh",
    "sg:phone":"+31 318 541 244",
    "sg:postcode":"3903 BE",
    "sg:province":"Utrecht",
    "wof:name":"P. Valkenburg Automatenexp",
    "wof:placetype":"venue"
},
  "geometry": {"coordinates":[5.555912,52.011181],"type":"Point"}
}