{
  "type": "Feature",
  "properties": {
    "addr:full":"Noorderweg 4 Leeuwarden Friesland 8911 ES",
    "addr:housenumber":"4",
    "addr:postcode":"8911 es",
    "addr:street":"Noorderweg",
    "iso:country":"NL",
    "sg:address":"Noorderweg 4",
    "sg:city":"Leeuwarden",
    "sg:orig_category":"Juridische Dienstverlening",
    "sg:phone":"+31 58 299 1428",
    "sg:postcode":"8911 ES",
    "sg:province":"Friesland",
    "wof:name":"H. Van Der Tuin Consultancy",
    "wof:placetype":"venue"
},
  "geometry": {"coordinates":[5.798885,53.205322],"type":"Point"}
}