{
  "type": "Feature",
  "properties": {
    "addr:full":"Groenewg 21 Bunnik Utrecht 3981 CK",
    "addr:housenumber":"21",
    "addr:postcode":"3981 ck",
    "addr:street":"Groenewg",
    "iso:country":"NL",
    "sg:address":"Groenewg 21",
    "sg:city":"Bunnik",
    "sg:orig_category":"Kantoorbenodigdheden",
    "sg:phone":"+31 30 656 2751",
    "sg:postcode":"3981 CK",
    "sg:province":"Utrecht",
    "wof:name":"Righart Bv",
    "wof:placetype":"venue"
},
  "geometry": {"coordinates":[5.1958999634,52.0628166199],"type":"Point"}
}