{
  "type": "Feature",
  "properties": {
    "iso:country":"NL",
    "sg:address":"S Gravelandsewg 563",
    "sg:city":"Schiedam",
    "sg:classifiers":[
        {
            "category":"Food & Beverages",
            "subcategory":"Bakery",
            "type":"Retail Goods"
        }
    ],
    "sg:phone":"+31 10 473 2292",
    "sg:postcode":"3119 XT",
    "sg:province":"Zuid-Holland",
    "sg:tags":[
        "brood",
        "en",
        "banket"
    ],
    "wof:name":"Breggen, Van Der",
    "wof:placetype":"venue"
},
  "geometry": {"coordinates":[4.403183,51.921947],"type":"Point"}
}