{
  "type": "Feature",
  "properties": {
    "addr:full":"Edisonstr 4 Hoogeveen Provincie Drenthe 7903 AN",
    "addr:housenumber":"4",
    "addr:postcode":"7903 an",
    "addr:street":"Edisonstr;Provincie",
    "iso:country":"NL",
    "sg:address":"Edisonstr 4",
    "sg:city":"Hoogeveen",
    "sg:orig_category":"Keukens",
    "sg:phone":"+31 528 280 280",
    "sg:postcode":"7903 AN",
    "sg:province":"Provincie Drenthe",
    "wof:name":"Hagro",
    "wof:placetype":"venue"
},
  "geometry": {"coordinates":[6.50158,52.736626],"type":"Point"}
}