{
  "type": "Feature",
  "properties": {
    "iso:country":"NL",
    "sg:address":"Boezemln 11",
    "sg:city":"Rotterdam",
    "sg:orig_category":"Beeldende Kunstenaars",
    "sg:phone":"+31 10 412 5237",
    "sg:postcode":"3034 XA",
    "sg:province":"Zuid-Holland",
    "wof:name":"Notenboom, J",
    "wof:placetype":"venue"
},
  "geometry": {"coordinates":[4.498061,51.930435],"type":"Point"}
}