{
  "type": "Feature",
  "properties": {
    "addr:full":"Geysendorfferstraat 16 Bussum North Holland 1403 VZ",
    "addr:housenumber":"16",
    "addr:postcode":"1403 vz",
    "addr:street":"Geysendorfferstraat",
    "iso:country":"NL",
    "sg:address":"Geysendorfferstraat 16",
    "sg:city":"Bussum",
    "sg:orig_category":"Loodgieterswerk, Verwarming And Sanitaire Installaties",
    "sg:phone":"+31 35 691 8761",
    "sg:postcode":"1403 VZ",
    "sg:province":"North Holland",
    "wof:name":"Westereng",
    "wof:placetype":"venue"
},
  "geometry": {"coordinates":[5.176766,52.26466],"type":"Point"}
}