{
  "type": "Feature",
  "properties": {
    "addr:full":"L Nering 118 Emmeloord Flevoland 8302 EG",
    "addr:housenumber":"118",
    "addr:postcode":"8302 eg",
    "addr:street":"Flevoland",
    "iso:country":"NL",
    "sg:address":"L Nering 118",
    "sg:city":"Emmeloord",
    "sg:orig_category":"Verlichting",
    "sg:phone":"+31 527 610 010",
    "sg:postcode":"8302 EG",
    "sg:province":"Flevoland",
    "wof:name":"Lampenier Emmeloord",
    "wof:placetype":"venue"
},
  "geometry": {"coordinates":[5.760451,52.711124],"type":"Point"}
}