{
  "type": "Feature",
  "properties": {
    "addr:full":"Laan Van Meerdervoort 778 'S Gravenhage Zuid-Holland 2564 AP",
    "addr:housenumber":"778 '",
    "addr:postcode":"2564 ap",
    "addr:street":"Laan Van Meerdervoort",
    "iso:country":"NL",
    "sg:address":"Laan Van Meerdervoort 778",
    "sg:city":"'S Gravenhage",
    "sg:orig_category":"Verzekeringen",
    "sg:phone":"+31 70 323 3395",
    "sg:postcode":"2564 AP",
    "sg:province":"Zuid-Holland",
    "wof:name":"Adv Bur Wetters Bv",
    "wof:placetype":"venue"
},
  "geometry": {"coordinates":[4.255019,52.07045],"type":"Point"}
}