{
  "type": "Feature",
  "properties": {
    "iso:country":"NL",
    "sg:address":"Witte Paal 48",
    "sg:city":"Schagen",
    "sg:orig_category":"Loodgieters",
    "sg:phone":"+31 224 297 897",
    "sg:postcode":"1742 NV",
    "sg:province":"North Holland",
    "wof:name":"Berg, E Van Den",
    "wof:placetype":"venue"
},
  "geometry": {"coordinates":[4.807549,52.776428],"type":"Point"}
}