{
  "type": "Feature",
  "properties": {
    "addr:full":"De Boender 4 Noordwijk Zh Zuid-Holland 2204 AG",
    "addr:housenumber":"4",
    "addr:postcode":"2204",
    "addr:street":"De Boender",
    "iso:country":"NL",
    "sg:address":"De Boender 4",
    "sg:city":"Noordwijk Zh",
    "sg:orig_category":"Bloemen And Planten",
    "sg:phone":"+31 252 374 428",
    "sg:postcode":"2204 AG",
    "sg:province":"Zuid-Holland",
    "wof:name":"Firma Van Den Berg-De Groot",
    "wof:placetype":"venue"
},
  "geometry": {"coordinates":[4.498886,52.28804],"type":"Point"}
}