{
  "type": "Feature",
  "properties": {
    "addr:full":"Vermeerstraat 5 Ommen NL.08 7731 SM",
    "addr:housenumber":"5;nl.08",
    "addr:postcode":"7731 sm",
    "addr:street":"Vermeerstraat",
    "iso:country":"NL",
    "sg:address":"Vermeerstraat 5",
    "sg:city":"Ommen",
    "sg:orig_category":"Loodgieterswerk, Verwarming And Sanitaire Installaties",
    "sg:phone":"+31 529 454 900",
    "sg:postcode":"7731 SM",
    "sg:province":"NL.08",
    "wof:name":"Gawalobedrijf Woertink",
    "wof:placetype":"venue"
},
  "geometry": {"coordinates":[6.426372,52.533123],"type":"Point"}
}