{
  "type": "Feature",
  "properties": {
    "iso:country":"NL",
    "sg:address":"Van Ostadelaan 264",
    "sg:city":"Alkmaar",
    "sg:orig_category":"Damesmodezaken",
    "sg:phone":"+31 72 515 9089",
    "sg:postcode":"1816 JG",
    "sg:province":"Noord-Holland",
    "wof:name":"Modehuis Karsten",
    "wof:placetype":"venue"
},
  "geometry": {"coordinates":[4.72525,52.632843],"type":"Point"}
}