{
  "type": "Feature",
  "properties": {
    "addr:full":"Raadhuisstr 33 Maasdam Zuid-Holland 3299 AP",
    "addr:housenumber":"33",
    "addr:postcode":"3299 ap",
    "addr:street":"Raadhuisstr",
    "iso:country":"NL",
    "sg:address":"Raadhuisstr 33",
    "sg:city":"Maasdam",
    "sg:orig_category":"Banken",
    "sg:phone":"+31 78 676 8800",
    "sg:postcode":"3299 AP",
    "sg:province":"Zuid-Holland",
    "sg:website":"http://www.rabobank.nl",
    "wof:name":"Rabobank",
    "wof:placetype":"venue"
},
  "geometry": {"coordinates":[4.553883,51.787891],"type":"Point"}
}