{
  "type": "Feature",
  "properties": {
    "addr:full":"Christoffelwg 13 Mook Limburg 6585 KN",
    "addr:housenumber":"13",
    "addr:postcode":"6585 kn",
    "addr:street":"Christoffelwg",
    "iso:country":"NL",
    "sg:address":"Christoffelwg 13",
    "sg:city":"Mook",
    "sg:orig_category":"Autorijscholen",
    "sg:phone":"+31 24 696 2700",
    "sg:postcode":"6585 KN",
    "sg:province":"Limburg",
    "wof:name":"Excel",
    "wof:placetype":"venue"
},
  "geometry": {"coordinates":[5.905983,51.755791],"type":"Point"}
}