{
  "type": "Feature",
  "properties": {
    "addr:full":"Schenkwg 96 S Gravenhage Zuid-Holland 2595 XX",
    "addr:housenumber":"96;gravenhage",
    "addr:postcode":"2595 xx",
    "addr:street":"Schenkwg;S",
    "iso:country":"NL",
    "sg:address":"Schenkwg 96",
    "sg:city":"S Gravenhage",
    "sg:orig_category":"Onderhoudswerken",
    "sg:phone":"+31 6 53810050",
    "sg:postcode":"2595 XX",
    "sg:province":"Zuid-Holland",
    "sg:website":"http://www.deschenk.nl",
    "wof:name":"Schenk, De",
    "wof:placetype":"venue"
},
  "geometry": {"coordinates":[4.33507,52.081421],"type":"Point"}
}