{
  "type": "Feature",
  "properties": {
    "addr:full":"Denestr 8 Reusel North Brabant 5541 RL",
    "addr:housenumber":"8",
    "addr:postcode":"5541 rl",
    "addr:street":"Denestr",
    "iso:country":"NL",
    "sg:address":"Denestr 8",
    "sg:city":"Reusel",
    "sg:orig_category":"Fournituren - Fabrieken En Groothandel",
    "sg:phone":"+31 497 641 107",
    "sg:postcode":"5541 RL",
    "sg:province":"North Brabant",
    "wof:name":"Star-Belts Euro Bv",
    "wof:placetype":"venue"
},
  "geometry": {"coordinates":[5.172144,51.366138],"type":"Point"}
}