{
  "type": "Feature",
  "properties": {
    "addr:full":"Sportln 1 Culemborg Gelderland 4102 HM",
    "addr:housenumber":"1",
    "addr:postcode":"4102 hm",
    "addr:street":"Sportln;Gelderland",
    "iso:country":"NL",
    "sg:address":"Sportln 1",
    "sg:city":"Culemborg",
    "sg:orig_category":"Sportverenigingen En Ontspannings- Verenigingen",
    "sg:phone":"+31 345 512 572",
    "sg:postcode":"4102 HM",
    "sg:province":"Gelderland",
    "wof:name":"Culemborg Beheer Sportaccomodaties",
    "wof:placetype":"venue"
},
  "geometry": {"coordinates":[5.22148,51.952175],"type":"Point"}
}