{
  "type": "Feature",
  "properties": {
    "iso:country":"NL",
    "sg:address":"Oirschotsebaan 15",
    "sg:city":"Oisterwijk",
    "sg:orig_category":"Kampeerterreinen",
    "sg:phone":"+31 13 528 4857",
    "sg:postcode":"5062 TE",
    "sg:province":"Noord-Brabant",
    "wof:name":"Caravan Park De Rosep",
    "wof:placetype":"venue"
},
  "geometry": {"coordinates":[5.2247872353,51.5574645996],"type":"Point"}
}