{
  "type": "Feature",
  "properties": {
    "addr:full":"Boschstr 70 Maastricht Limburg 6211 AX",
    "addr:housenumber":"70",
    "addr:postcode":"6211 ax",
    "addr:street":"Boschstr",
    "iso:country":"NL",
    "sg:address":"Boschstr 70",
    "sg:city":"Maastricht",
    "sg:classifiers":[
        {
            "category":"Travel",
            "subcategory":"Hotels & Motels",
            "type":"Entertainment"
        }
    ],
    "sg:phone":"+31 43 350 3333",
    "sg:postcode":"6211 AX",
    "sg:province":"Limburg",
    "sg:website":"http://www.pauwenhof.nl",
    "wof:name":"Pauwenhof, De",
    "wof:placetype":"venue"
},
  "geometry": {"coordinates":[5.689868,50.853409],"type":"Point"}
}