{
  "type": "Feature",
  "properties": {
    "addr:full":"De Jagerweg 225 Dordrecht Zuid-Holland 3328 AA",
    "addr:housenumber":"225",
    "addr:postcode":"3328 aa",
    "addr:street":"De Jagerweg",
    "iso:country":"NL",
    "sg:address":"De Jagerweg 225",
    "sg:city":"Dordrecht",
    "sg:orig_category":"Fitnesscentra",
    "sg:phone":"+31 78 651 4524",
    "sg:postcode":"3328 AA",
    "sg:province":"Zuid-Holland",
    "wof:name":"Aerobic Studio B-Fit",
    "wof:placetype":"venue"
},
  "geometry": {"coordinates":[4.682636,51.77713],"type":"Point"}
}