{
  "type": "Feature",
  "properties": {
    "iso:country":"NL",
    "sg:address":"Ginnekenwg 27-29",
    "sg:city":"Breda",
    "sg:orig_category":"Perzische En Oosterse Tapijten",
    "sg:phone":"+31 76 521 2287",
    "sg:postcode":"4818 JA",
    "sg:province":"North Brabant",
    "sg:website":"http://www.farah.nl",
    "wof:name":"Farah Perzisch Tapijtenhuis",
    "wof:placetype":"venue"
},
  "geometry": {"coordinates":[4.779997,51.577854],"type":"Point"}
}