{
  "type": "Feature",
  "properties": {
    "iso:country":"NL",
    "sg:address":"Glaciswg 53",
    "sg:city":"Hellevoetsluis",
    "sg:orig_category":"Verloskundigen",
    "sg:phone":"+31 181 315 655",
    "sg:postcode":"3221 XA",
    "sg:province":"Zuid-Holland",
    "wof:name":"Brussel-De Reus, T Van",
    "wof:placetype":"venue"
},
  "geometry": {"coordinates":[4.134513,51.826904],"type":"Point"}
}