{
  "type": "Feature",
  "properties": {
    "addr:full":"Glaciswg 53 Hellevoetsluis Zuid-Holland 3221 XA",
    "addr:housenumber":"53",
    "addr:postcode":"3221 xa",
    "addr:street":"Glaciswg",
    "iso:country":"NL",
    "sg:address":"Glaciswg 53",
    "sg:city":"Hellevoetsluis",
    "sg:orig_category":"Verloskundigen",
    "sg:phone":"+31 181 315 655",
    "sg:postcode":"3221 XA",
    "sg:province":"Zuid-Holland",
    "wof:name":"Brussel-De Reus, T Van",
    "wof:placetype":"venue"
},
  "geometry": {"coordinates":[4.134513,51.826904],"type":"Point"}
}