{
  "type": "Feature",
  "properties": {
    "iso:country":"NL",
    "sg:address":"Mercuriusstr 1",
    "sg:city":"Venlo",
    "sg:orig_category":"Verlichting",
    "sg:phone":"+31 77 352 1960",
    "sg:postcode":"5914 CR",
    "sg:province":"Limburg",
    "wof:name":"Midas Eur",
    "wof:placetype":"venue"
},
  "geometry": {"coordinates":[6.171509,51.378452],"type":"Point"}
}