{
  "type": "Feature",
  "properties": {
    "addr:full":"Nieuweweg 97 Soest Utrecht 3765 GC",
    "addr:housenumber":"97",
    "addr:postcode":"3765 gc",
    "addr:street":"Nieuweweg",
    "iso:country":"NL",
    "sg:address":"Nieuweweg 97",
    "sg:city":"Soest",
    "sg:orig_category":"Fietshandelaren",
    "sg:phone":"+31 35 601 3462",
    "sg:postcode":"3765 GC",
    "sg:province":"Utrecht",
    "wof:name":"Profile Soest",
    "wof:placetype":"venue"
},
  "geometry": {"coordinates":[5.300385,52.184044],"type":"Point"}
}