{
  "type": "Feature",
  "properties": {
    "addr:full":"Julianastr 49 Waarde Zeeland 4414 AR",
    "addr:housenumber":"49",
    "addr:postcode":"4414",
    "addr:street":"Julianastr",
    "iso:country":"NL",
    "sg:address":"Julianastr 49",
    "sg:city":"Waarde",
    "sg:orig_category":"Verzekeringen - Verzekeringskantoren",
    "sg:phone":"+31 113 504 556",
    "sg:postcode":"4414 AR",
    "sg:province":"Zeeland",
    "wof:name":"Waterman Assuranti\u00ebn-Hypotheken",
    "wof:placetype":"venue"
},
  "geometry": {"coordinates":[4.069684,51.418301],"type":"Point"}
}