{
  "type": "Feature",
  "properties": {
    "addr:full":"Ankersmidpln 59 Zaandam Noord-Holland 1506 CK",
    "addr:housenumber":"59",
    "addr:postcode":"1506 ck",
    "addr:street":"Ankersmidpln",
    "iso:country":"NL",
    "sg:address":"Ankersmidpln 59",
    "sg:city":"Zaandam",
    "sg:orig_category":"Vertalers",
    "sg:phone":"+31 75 670 4106",
    "sg:postcode":"1506 CK",
    "sg:province":"Noord-Holland",
    "wof:name":"Kanik, M B",
    "wof:placetype":"venue"
},
  "geometry": {"coordinates":[4.816238,52.43837],"type":"Point"}
}