{
  "type": "Feature",
  "properties": {
    "addr:full":"Ghyseland 16 Rhoon Zuid-Holland 3161 VC",
    "addr:housenumber":"16",
    "addr:postcode":"3161 vc",
    "addr:street":"Ghyseland",
    "iso:country":"NL",
    "sg:address":"Ghyseland 16",
    "sg:city":"Rhoon",
    "sg:orig_category":"Grafmonumenten",
    "sg:phone":"+31 10 501 3141",
    "sg:postcode":"3161 VC",
    "sg:province":"Zuid-Holland",
    "wof:name":"Funerama",
    "wof:placetype":"venue"
},
  "geometry": {"coordinates":[4.427355,51.85656],"type":"Point"}
}