{
  "type": "Feature",
  "properties": {
    "addr:full":"Plantage Middenln 4P Amsterdam Noord-Holland 1018 DD",
    "addr:housenumber":"4p",
    "addr:postcode":"1018 dd",
    "addr:street":"Plantage Middenln",
    "iso:country":"NL",
    "sg:address":"Plantage Middenln 4P",
    "sg:city":"Amsterdam",
    "sg:orig_category":"Adviesbureaus Economie",
    "sg:phone":"+31 20 622 9722",
    "sg:postcode":"1018 DD",
    "sg:province":"Noord-Holland",
    "wof:name":"Oost Europa, Business Bur",
    "wof:placetype":"venue"
},
  "geometry": {"coordinates":[4.909346,52.367165],"type":"Point"}
}