{
  "type": "Feature",
  "properties": {
    "iso:country":"NL",
    "sg:address":"Touwslagersdreef 73",
    "sg:city":"Tholen",
    "sg:orig_category":"Paramedische Behandelingen",
    "sg:phone":"+31 166 602 084",
    "sg:postcode":"4691 LW",
    "sg:province":"Zeeland",
    "wof:name":"J W Groeneveld",
    "wof:placetype":"venue"
},
  "geometry": {"coordinates":[4.214436,51.526489],"type":"Point"}
}