{
  "type": "Feature",
  "properties": {
    "iso:country":"NL",
    "sg:address":"Korianderstr 5",
    "sg:city":"Utrecht",
    "sg:orig_category":"Verenigingen En Stichtingen",
    "sg:phone":"+31 30 670 2000",
    "sg:postcode":"3544 BN",
    "sg:province":"Utrecht",
    "wof:name":"Reijearde, Sticht",
    "wof:placetype":"venue"
},
  "geometry": {"coordinates":[5.063843,52.088428],"type":"Point"}
}