{
  "type": "Feature",
  "properties": {
    "addr:full":"Dorpsstraat 2 Eckelrade Limburg 6252 ND",
    "addr:housenumber":"2",
    "addr:postcode":"6252 nd",
    "addr:street":"Dorpsstraat",
    "iso:country":"NL",
    "sg:address":"Dorpsstraat 2",
    "sg:city":"Eckelrade",
    "sg:classifiers":[
        {
            "category":"Shopping",
            "subcategory":"Gifts & Souvenirs",
            "type":"Retail Goods"
        }
    ],
    "sg:phone":"+31 43 408 2168",
    "sg:postcode":"6252 ND",
    "sg:province":"Limburg",
    "sg:tags":[
        "geschenken"
    ],
    "wof:name":"Paulien Bisscheroux",
    "wof:placetype":"venue"
},
  "geometry": {"coordinates":[5.760484,50.804127],"type":"Point"}
}