{
  "type": "Feature",
  "properties": {
    "iso:country":"NL",
    "sg:address":"Vikingstraat 10",
    "sg:city":"Westkapelle",
    "sg:orig_category":"Architecten",
    "sg:phone":"+31 118 571 318",
    "sg:postcode":"4361 CR",
    "sg:province":"Zeeland",
    "wof:name":"P. Kodde",
    "wof:placetype":"venue"
},
  "geometry": {"coordinates":[3.441767,51.530334],"type":"Point"}
}