{
  "type": "Feature",
  "properties": {
    "addr:full":"T Harde 2 Haren Gn Groningen 9752 VD",
    "addr:housenumber":"2",
    "addr:postcode":"9752 vd",
    "addr:street":"T Harde",
    "iso:country":"NL",
    "sg:address":"T Harde 2",
    "sg:city":"Haren Gn",
    "sg:orig_category":"Adviesbureaus Bouwkunde",
    "sg:phone":"+31 50 535 0002",
    "sg:postcode":"9752 VD",
    "sg:province":"Groningen",
    "wof:name":"Hoft, J A J",
    "wof:placetype":"venue"
},
  "geometry": {"coordinates":[6.608826,53.164204],"type":"Point"}
}