{
  "type": "Feature",
  "properties": {
    "addr:full":"Melrose 3 Duiven Gelderland 6922 BB",
    "addr:housenumber":"3",
    "addr:postcode":"6922 bb",
    "addr:street":"Melrose;Gelderland",
    "iso:country":"NL",
    "sg:address":"Melrose 3",
    "sg:city":"Duiven",
    "sg:classifiers":[
        {
            "category":"Personal",
            "subcategory":"Nail Salon",
            "type":"Services"
        }
    ],
    "sg:phone":"+31 316 267 861",
    "sg:postcode":"6922 BB",
    "sg:province":"Gelderland",
    "sg:tags":[
        "pedicure"
    ],
    "wof:name":"Hendriksen, A",
    "wof:placetype":"venue"
},
  "geometry": {"coordinates":[-71.064072,42.45718],"type":"Point"}
}