{
  "type": "Feature",
  "properties": {
    "addr:full":"Minstreelpad 6 Soest Utrecht 3766 BT",
    "addr:housenumber":"6",
    "addr:postcode":"3766 bt",
    "addr:street":"Minstreelpad",
    "iso:country":"NL",
    "sg:address":"Minstreelpad 6",
    "sg:city":"Soest",
    "sg:orig_category":"Onderhoudswerken",
    "sg:phone":"+31 35 601 0443",
    "sg:postcode":"3766 BT",
    "sg:province":"Utrecht",
    "wof:name":"Schimmel, I G",
    "wof:placetype":"venue"
},
  "geometry": {"coordinates":[5.284098,52.168194],"type":"Point"}
}