{
  "type": "Feature",
  "properties": {
    "addr:full":"Stationsplein 41 Den Bosch North Brabant 5211 BJ",
    "addr:housenumber":"41",
    "addr:postcode":"5211 bj",
    "addr:street":"Stationsplein",
    "iso:country":"NL",
    "sg:address":"Stationsplein 41",
    "sg:city":"Den Bosch",
    "sg:orig_category":"Werving And Selectie Van Tijdelijk Personeel And Uitzendkantoren",
    "sg:phone":"+31 73 612 4477",
    "sg:postcode":"5211 BJ",
    "sg:province":"North Brabant",
    "wof:name":"Vedior",
    "wof:placetype":"venue"
},
  "geometry": {"coordinates":[5.2982401848,51.6907501221],"type":"Point"}
}