{
  "type": "Feature",
  "properties": {
    "addr:full":"Bisschopstr 31 Oldenzaal Overijssel 7571 CX",
    "addr:housenumber":"31",
    "addr:postcode":"7571 cx",
    "addr:street":"Bisschopstr",
    "iso:country":"NL",
    "sg:address":"Bisschopstr 31",
    "sg:city":"Oldenzaal",
    "sg:orig_category":"Naaimachines - Reparatie En Onderhoud",
    "sg:phone":"+31 541 516 315",
    "sg:postcode":"7571 CX",
    "sg:province":"Overijssel",
    "wof:name":"Buuren, Johan Ten",
    "wof:placetype":"venue"
},
  "geometry": {"coordinates":[6.930074,52.315056],"type":"Point"}
}