{
  "type": "Feature",
  "properties": {
    "iso:country":"NL",
    "sg:address":"Schans 5",
    "sg:city":"Uithoorn",
    "sg:classifiers":[
        {
            "category":"Professional",
            "subcategory":"Accounting & Tax Preparation",
            "type":"Services"
        }
    ],
    "sg:phone":"+31 297 561 814",
    "sg:postcode":"1421 BA",
    "sg:province":"Noord-Holland",
    "sg:tags":[
        "accountant",
        "en",
        "-kantoren",
        "register-"
    ],
    "wof:name":"Smit, A H",
    "wof:placetype":"venue"
},
  "geometry": {"coordinates":[4.829186,52.232197],"type":"Point"}
}