{
  "type": "Feature",
  "properties": {
    "addr:full":"Schoterweg 94 Haarlem North Holland 2021 HR",
    "addr:housenumber":"94",
    "addr:postcode":"2021 hr",
    "addr:street":"Schoterweg",
    "iso:country":"NL",
    "sg:address":"Schoterweg 94",
    "sg:city":"Haarlem",
    "sg:orig_category":"Banken And Kredietinstellingen",
    "sg:phone":"+31 23 525 5888",
    "sg:postcode":"2021 HR",
    "sg:province":"North Holland",
    "wof:name":"Postkantoor",
    "wof:placetype":"venue"
},
  "geometry": {"coordinates":[4.640466,52.393185],"type":"Point"}
}