{
  "type": "Feature",
  "properties": {
    "addr:full":"Havikweg 21 Alkmaar Noord-Holland 1826 JT",
    "addr:housenumber":"21",
    "addr:postcode":"1826 jt",
    "addr:street":"Havikweg",
    "iso:country":"NL",
    "sg:address":"Havikweg 21",
    "sg:city":"Alkmaar",
    "sg:orig_category":"Loodgieterswerk, Verwarming And Sanitaire Installaties",
    "sg:phone":"+31 72 562 6922",
    "sg:postcode":"1826 JT",
    "sg:province":"Noord-Holland",
    "wof:name":"F.J.M. Burgering",
    "wof:placetype":"venue"
},
  "geometry": {"coordinates":[4.769255,52.661518],"type":"Point"}
}