{
  "type": "Feature",
  "properties": {
    "addr:full":"Boterwyksestr 20 Oirschot Noord-Brabant 5688 HX",
    "addr:housenumber":"20",
    "addr:postcode":"5688 hx",
    "addr:street":"Boterwyksestr",
    "iso:country":"NL",
    "sg:address":"Boterwyksestr 20",
    "sg:city":"Oirschot",
    "sg:orig_category":"Mengmachines",
    "sg:phone":"+31 499 571 013",
    "sg:postcode":"5688 HX",
    "sg:province":"Noord-Brabant",
    "wof:name":"Alucon Gmbh",
    "wof:placetype":"venue"
},
  "geometry": {"coordinates":[5.291806,51.508945],"type":"Point"}
}