{
  "type": "Feature",
  "properties": {
    "addr:full":"Haarbrinksweg 26 Geesteren Ov NL.08 7678 RT",
    "addr:housenumber":"26",
    "addr:postcode":"7678 rt",
    "addr:street":"Haarbrinksweg;Ov",
    "iso:country":"NL",
    "sg:address":"Haarbrinksweg 26",
    "sg:city":"Geesteren Ov",
    "sg:orig_category":"Bloemen And Planten",
    "sg:phone":"+31 546 631 715",
    "sg:postcode":"7678 RT",
    "sg:province":"NL.08",
    "wof:name":"Vof Tuincentrum Heerdink",
    "wof:placetype":"venue"
},
  "geometry": {"coordinates":[6.732868,52.413517],"type":"Point"}
}