{
  "type": "Feature",
  "properties": {
    "iso:country":"NL",
    "sg:address":"Zuiddk 63",
    "sg:city":"Oude Tonge",
    "sg:orig_category":"Voetbalverenigingen",
    "sg:phone":"+31 187 641 685",
    "sg:postcode":"3255 LV",
    "sg:province":"South Holland",
    "wof:name":"Dbgc",
    "wof:placetype":"venue"
},
  "geometry": {"coordinates":[4.209938,51.68779],"type":"Point"}
}