{
  "type": "Feature",
  "properties": {
    "addr:full":"Loddersweer 1 Raamsdonksveer Noord-Brabant 4942 AE",
    "addr:housenumber":"1",
    "addr:postcode":"4942 ae",
    "addr:street":"Loddersweer",
    "iso:country":"NL",
    "sg:address":"Loddersweer 1",
    "sg:city":"Raamsdonksveer",
    "sg:orig_category":"Kappersbenodigdheden",
    "sg:phone":"+31 162 511 514",
    "sg:postcode":"4942 AE",
    "sg:province":"Noord-Brabant",
    "wof:name":"Eslabon",
    "wof:placetype":"venue"
},
  "geometry": {"coordinates":[4.881924,51.703789],"type":"Point"}
}