{
  "type": "Feature",
  "properties": {
    "addr:full":"Dorpsstr 34 Oegstgeest South Holland 2343 BA",
    "addr:housenumber":"34",
    "addr:postcode":"2343 ba",
    "addr:street":"Dorpsstr",
    "iso:country":"NL",
    "sg:address":"Dorpsstr 34",
    "sg:city":"Oegstgeest",
    "sg:orig_category":"Oldtimers",
    "sg:phone":"+31 71 523 7455",
    "sg:postcode":"2343 BA",
    "sg:province":"South Holland",
    "wof:name":"Retrocar Bv",
    "wof:placetype":"venue"
},
  "geometry": {"coordinates":[4.467485,52.189327],"type":"Point"}
}