{
  "type": "Feature",
  "properties": {
    "addr:full":"Beestenmarkt 20 Goes Zeeland 4461 CT",
    "addr:housenumber":"20",
    "addr:postcode":"4461 ct",
    "addr:street":"Beestenmarkt",
    "iso:country":"NL",
    "sg:address":"Beestenmarkt 20",
    "sg:city":"Goes",
    "sg:orig_category":"Architecten En Architectenbureaus",
    "sg:phone":"+31 113 215 260",
    "sg:postcode":"4461 CT",
    "sg:province":"Zeeland",
    "wof:name":"Weertman Architectenbureau Bna",
    "wof:placetype":"venue"
},
  "geometry": {"coordinates":[-83.914169,39.768833],"type":"Point"}
}