{
  "type": "Feature",
  "properties": {
    "addr:full":"Telingstr 4 Utrecht Utrecht 3512 GV",
    "addr:housenumber":"4",
    "addr:postcode":"3512 gv",
    "addr:street":"Telingstr",
    "iso:country":"NL",
    "sg:address":"Telingstr 4",
    "sg:city":"Utrecht",
    "sg:orig_category":"Kappers",
    "sg:phone":"+31 30 232 2699",
    "sg:postcode":"3512 GV",
    "sg:province":"Utrecht",
    "wof:name":"Byblos",
    "wof:placetype":"venue"
},
  "geometry": {"coordinates":[5.1196122169,52.0925941467],"type":"Point"}
}