{
  "type": "Feature",
  "properties": {
    "addr:full":"Kerkstraat 7 Meijel Limburg 5768 BH",
    "addr:housenumber":"7",
    "addr:postcode":"5768 bh",
    "addr:street":"Kerkstraat",
    "iso:country":"NL",
    "sg:address":"Kerkstraat 7",
    "sg:city":"Meijel",
    "sg:classifiers":[
        {
            "category":"Education",
            "subcategory":"Preschool",
            "type":"Public Place"
        }
    ],
    "sg:phone":"+31 77 466 9210",
    "sg:postcode":"5768 BH",
    "sg:province":"Limburg",
    "sg:tags":[
        "kleuteronderwijs",
        "basis-"
    ],
    "wof:name":"Basisschool Den Doelhof",
    "wof:placetype":"venue"
},
  "geometry": {"coordinates":[5.887763,51.344524],"type":"Point"}
}