{
  "type": "Feature",
  "properties": {
    "iso:country":"NL",
    "sg:address":"Sprengenweg 4",
    "sg:city":"Apeldoorn",
    "sg:orig_category":"Kappers",
    "sg:phone":"+31 55 521 5824",
    "sg:postcode":"7314 ES",
    "sg:province":"Gelderland",
    "wof:name":"Dames En Herenkapsalon Anja",
    "wof:placetype":"venue"
},
  "geometry": {"coordinates":[5.9545898438,52.2182312012],"type":"Point"}
}