{
  "type": "Feature",
  "properties": {
    "addr:full":"Prinses Margrietlaan 62B Rotterdam South Holland 3051 AX",
    "addr:housenumber":"62b",
    "addr:postcode":"3051 ax",
    "addr:street":"Prinses Margrietlaan",
    "iso:country":"NL",
    "sg:address":"Prinses Margrietlaan 62B",
    "sg:city":"Rotterdam",
    "sg:orig_category":"Vertaal- And Tolkenbureaus",
    "sg:phone":"+31 10 418 6875",
    "sg:postcode":"3051 AX",
    "sg:province":"South Holland",
    "wof:name":"Chang Y",
    "wof:placetype":"venue"
},
  "geometry": {"coordinates":[4.488035,51.945637],"type":"Point"}
}