{
  "type": "Feature",
  "properties": {
    "addr:full":"Utopialaan 50 'S Hertogenbosch Noord-Brabant 5232 CE",
    "addr:housenumber":"50",
    "addr:postcode":"5232 ce",
    "addr:street":"Utopialaan;' S",
    "iso:country":"NL",
    "sg:address":"Utopialaan 50",
    "sg:city":"'S Hertogenbosch",
    "sg:orig_category":"Werving And Selectie Van Tijdelijk Personeel And Uitzendkantoren",
    "sg:phone":"+31 73 640 6301",
    "sg:postcode":"5232 CE",
    "sg:province":"Noord-Brabant",
    "wof:name":"Datelnet Services Bv",
    "wof:placetype":"venue"
},
  "geometry": {"coordinates":[5.3374371529,51.7133522034],"type":"Point"}
}