{
  "type": "Feature",
  "properties": {
    "addr:full":"Grt Markt 195 Almere NL. 1315 JE",
    "addr:housenumber":"195",
    "addr:postcode":"1315 je",
    "addr:street":"Markt;Nl.",
    "iso:country":"NL",
    "sg:address":"Grt Markt 195",
    "sg:city":"Almere",
    "sg:orig_category":"Boeken En Tijdschriften",
    "sg:phone":"+31 36 534 3995",
    "sg:postcode":"1315 JE",
    "sg:province":"NL.",
    "sg:website":"http://www.rataplan.nl",
    "wof:name":"Rataplan",
    "wof:placetype":"venue"
},
  "geometry": {"coordinates":[5.21998,52.374531],"type":"Point"}
}