{
  "type": "Feature",
  "properties": {
    "iso:country":"NL",
    "sg:address":"Scharleijen 2",
    "sg:city":"Sint Nicolaasga",
    "sg:orig_category":"Watersport-, Sport- And Kampeerbenodigdheden Verhuur",
    "sg:phone":"+31 6 51384671",
    "sg:postcode":"8521 NM",
    "sg:province":"Friesland",
    "wof:name":"Wilro Vof",
    "wof:placetype":"venue"
},
  "geometry": {"coordinates":[5.7471709251,52.9210548401],"type":"Point"}
}