{
  "type": "Feature",
  "properties": {
    "iso:country":"NL",
    "sg:address":"Westphalingsgoed 4",
    "sg:city":"Nykerk Gld",
    "sg:orig_category":"Onderhoudswerken",
    "sg:phone":"+31 33 245 7846",
    "sg:postcode":"3863 XW",
    "sg:province":"Gelderland",
    "wof:name":"Graaf, A De",
    "wof:placetype":"venue"
},
  "geometry": {"coordinates":[5.466054,52.219727],"type":"Point"}
}