{
  "type": "Feature",
  "properties": {
    "iso:country":"NL",
    "sg:address":"Galgenweg 5",
    "sg:city":"Zevenbergen",
    "sg:orig_category":"Diverse Bedrijfsinstallaties Gh",
    "sg:phone":"+31 168 326 465",
    "sg:postcode":"4761 KP",
    "sg:province":"Noord-Brabant",
    "wof:name":"Vdv Agencies Bv",
    "wof:placetype":"venue"
},
  "geometry": {"coordinates":[4.597294,51.646397],"type":"Point"}
}