{
  "type": "Feature",
  "properties": {
    "addr:full":"Rakerstraat 10 Weert Limburg 6003 NN",
    "addr:housenumber":"10",
    "addr:postcode":"6003 nn",
    "addr:street":"Rakerstraat",
    "iso:country":"NL",
    "sg:address":"Rakerstraat 10",
    "sg:city":"Weert",
    "sg:orig_category":"Wegen And Sportterreinen",
    "sg:phone":"+31 495 545 608",
    "sg:postcode":"6003 NN",
    "sg:province":"Limburg",
    "wof:name":"Bv Bouwmaatschappij V/H J. Wijnen En Zn.",
    "wof:placetype":"venue"
},
  "geometry": {"coordinates":[5.7103719711,51.2748908997],"type":"Point"}
}