{
  "type": "Feature",
  "properties": {
    "iso:country":"NL",
    "sg:address":"Leuvensbroek 2164",
    "sg:city":"Nijmegen",
    "sg:orig_category":"Paramedische Behandelingen",
    "sg:phone":"+31 24 373 0142",
    "sg:postcode":"6546 TB",
    "sg:province":"Gelderland",
    "wof:name":"Logopediepraktijk Nooijens En Terpstra",
    "wof:placetype":"venue"
},
  "geometry": {"coordinates":[5.779525,51.832298],"type":"Point"}
}