{
  "type": "Feature",
  "properties": {
    "addr:full":"Witte Paal 331 Schagen Noord-Holland 1742 LE",
    "addr:housenumber":"331",
    "addr:postcode":"1742 le",
    "addr:street":"Witte Paal",
    "iso:country":"NL",
    "sg:address":"Witte Paal 331",
    "sg:city":"Schagen",
    "sg:orig_category":"Bestratingen",
    "sg:phone":"+31 224 296 222",
    "sg:postcode":"1742 LE",
    "sg:province":"Noord-Holland",
    "wof:name":"Bos",
    "wof:placetype":"venue"
},
  "geometry": {"coordinates":[4.816159,52.776516],"type":"Point"}
}