{
  "type": "Feature",
  "properties": {
    "addr:full":"J Roepespad 4 Hollum Provincie Friesland 9161 CT",
    "addr:housenumber":"4",
    "addr:postcode":"9161 ct",
    "addr:street":"Roepespad;Provincie Friesland",
    "iso:country":"NL",
    "sg:address":"J Roepespad 4",
    "sg:city":"Hollum",
    "sg:orig_category":"Fietsen En Bromfietsen Verhuur",
    "sg:phone":"+31 519 556 103",
    "sg:postcode":"9161 CT",
    "sg:province":"Provincie Friesland",
    "wof:name":"Faber Ameland",
    "wof:placetype":"venue"
},
  "geometry": {"coordinates":[5.637006,53.449593],"type":"Point"}
}