{
  "type": "Feature",
  "properties": {
    "addr:full":"Kosmonaut 8A Amersfoort Utrecht 3824 MK",
    "addr:housenumber":"8a",
    "addr:postcode":"3824",
    "addr:street":"Kosmonaut",
    "iso:country":"NL",
    "sg:address":"Kosmonaut 8A",
    "sg:city":"Amersfoort",
    "sg:orig_category":"Kantoor- En Bedrijfsmeubelen",
    "sg:phone":"+31 33 456 5586",
    "sg:postcode":"3824 MK",
    "sg:province":"Utrecht",
    "sg:website":"http://www.prokant.nl",
    "wof:name":"Prokant",
    "wof:placetype":"venue"
},
  "geometry": {"coordinates":[5.3900327682,52.1969261169],"type":"Point"}
}