{
  "type": "Feature",
  "properties": {
    "addr:full":"Vd Weteringstr 69 Utrecht Utrecht 3581 ED",
    "addr:housenumber":"69",
    "addr:postcode":"3581 ed",
    "iso:country":"NL",
    "sg:address":"Vd Weteringstr 69",
    "sg:city":"Utrecht",
    "sg:orig_category":"Verenigingen En Stichtingen",
    "sg:phone":"+31 30 231 3888",
    "sg:postcode":"3581 ED",
    "sg:province":"Utrecht",
    "wof:name":"Tawhid Al Islami Al, Ver",
    "wof:placetype":"venue"
},
  "geometry": {"coordinates":[5.13447,52.089989],"type":"Point"}
}