{
  "type": "Feature",
  "properties": {
    "addr:full":"Rading 124 Loosdrecht Noord-Holland 1231 KD",
    "addr:housenumber":"124",
    "addr:postcode":"1231 kd",
    "addr:street":"Rading",
    "iso:country":"NL",
    "sg:address":"Rading 124",
    "sg:city":"Loosdrecht",
    "sg:orig_category":"Lijstenmakerijen",
    "sg:phone":"+31 35 582 8510",
    "sg:postcode":"1231 KD",
    "sg:province":"Noord-Holland",
    "wof:name":"Stijl",
    "wof:placetype":"venue"
},
  "geometry": {"coordinates":[5.145082,52.197018],"type":"Point"}
}