{
  "type": "Feature",
  "properties": {
    "addr:full":"De Clercqstr 42-44 Amsterdam Noord-Holland 1052 NG",
    "addr:housenumber":"42-44",
    "addr:postcode":"1052 ng",
    "iso:country":"NL",
    "sg:address":"De Clercqstr 42-44",
    "sg:city":"Amsterdam",
    "sg:orig_category":"Bloemen En Planten",
    "sg:phone":"+31 20 616 8685",
    "sg:postcode":"1052 NG",
    "sg:province":"Noord-Holland",
    "wof:name":"Roos Bloemisten Sinds 1927, De",
    "wof:placetype":"venue"
},
  "geometry": {"coordinates":[4.870647,52.371208],"type":"Point"}
}