{
  "type": "Feature",
  "properties": {
    "addr:full":"Luxoolseweg 20A Nykerk Gld Gelderland 3862 WJ",
    "addr:housenumber":"20a;3862",
    "addr:postcode":"wj",
    "addr:street":"Luxoolseweg;Gld Gelderland",
    "iso:country":"NL",
    "sg:address":"Luxoolseweg 20A",
    "sg:city":"Nykerk Gld",
    "sg:orig_category":"Verhuur",
    "sg:phone":"+31 33 246 2824",
    "sg:postcode":"3862 WJ",
    "sg:province":"Gelderland",
    "sg:website":"http://www.selmco.com",
    "wof:name":"Selmco Partyverhuur",
    "wof:placetype":"venue"
},
  "geometry": {"coordinates":[5.5141501427,52.213760376],"type":"Point"}
}