{
  "type": "Feature",
  "properties": {
    "addr:full":"Pastoor Vonckenstraat 61 Geleen Limburg 6166 CW",
    "addr:housenumber":"61",
    "addr:postcode":"6166 cw",
    "addr:street":"Pastoor Vonckenstraat",
    "iso:country":"NL",
    "sg:address":"Pastoor Vonckenstraat 61",
    "sg:city":"Geleen",
    "sg:orig_category":"Fruit And Groenten Gh",
    "sg:phone":"+31 46 474 3332",
    "sg:postcode":"6166 CW",
    "sg:province":"Limburg",
    "wof:name":"Ch Willems En Zoon Groenten En Fruit Exp",
    "wof:placetype":"venue"
},
  "geometry": {"coordinates":[5.838674,50.972698],"type":"Point"}
}