{
  "type": "Feature",
  "properties": {
    "iso:country":"NL",
    "sg:address":"Debussystr 13",
    "sg:city":"Eindhoven",
    "sg:orig_category":"Autopoetsbedrijven",
    "sg:phone":"+31 40 251 0836",
    "sg:postcode":"5654 SB",
    "sg:province":"North Brabant",
    "wof:name":"N+Q Vof",
    "wof:placetype":"venue"
},
  "geometry": {"coordinates":[5.453526,51.421715],"type":"Point"}
}