{
  "type": "Feature",
  "properties": {
    "addr:full":"Jan Van Galenstraat 55 Amsterdam Noord-Holland 1056 BH",
    "addr:housenumber":"55",
    "addr:postcode":"1056 bh",
    "addr:street":"Jan Van Galenstraat",
    "iso:country":"NL",
    "sg:address":"Jan Van Galenstraat 55",
    "sg:city":"Amsterdam",
    "sg:classifiers":[
        {
            "category":"Communications",
            "subcategory":"Television Station",
            "type":"Services"
        }
    ],
    "sg:phone":"+31 20 683 2005",
    "sg:postcode":"1056 BH",
    "sg:province":"Noord-Holland",
    "sg:tags":[
        "video",
        "audio",
        "verhuur"
    ],
    "wof:name":"De Sloterplas West Movie",
    "wof:placetype":"venue"
},
  "geometry": {"coordinates":[4.862338,52.375103],"type":"Point"}
}