{
  "type": "Feature",
  "properties": {
    "addr:full":"Warmoezierswg 29 Bergschenhoek Zuid-Holland 2661 EH",
    "addr:housenumber":"29",
    "addr:postcode":"2661 eh",
    "addr:street":"Warmoezierswg",
    "iso:country":"NL",
    "sg:address":"Warmoezierswg 29",
    "sg:city":"Bergschenhoek",
    "sg:orig_category":"Kassenbouw",
    "sg:phone":"+31 10 522 0595",
    "sg:postcode":"2661 EH",
    "sg:province":"Zuid-Holland",
    "wof:name":"Hgs Bv",
    "wof:placetype":"venue"
},
  "geometry": {"coordinates":[4.514759,51.995811],"type":"Point"}
}