{
  "type": "Feature",
  "properties": {
    "addr:full":"Molkenbosweg 1 Terschelling Formerum Friesland 8894 KJ",
    "addr:housenumber":"1",
    "addr:postcode":"8894 kj",
    "addr:street":"Molkenbosweg",
    "iso:country":"NL",
    "sg:address":"Molkenbosweg 1",
    "sg:city":"Terschelling Formerum",
    "sg:orig_category":"Kampeerterreinen",
    "sg:phone":"+31 562 448 046",
    "sg:postcode":"8894 KJ",
    "sg:province":"Friesland",
    "wof:name":"Firma Damstra-Andela",
    "wof:placetype":"venue"
},
  "geometry": {"coordinates":[5.3029260635,53.3915405273],"type":"Point"}
}