{
  "type": "Feature",
  "properties": {
    "iso:country":"NL",
    "sg:address":"Wooldstraat 57",
    "sg:city":"Winterswijk",
    "sg:orig_category":"Huishoudapparatuur, Televisies And Radio'S",
    "sg:phone":"+31 543 512 735",
    "sg:postcode":"7101 NN",
    "sg:province":"Gelderland",
    "wof:name":"Radio Obbink Bv",
    "wof:placetype":"venue"
},
  "geometry": {"coordinates":[6.721466,51.969872],"type":"Point"}
}