{
  "type": "Feature",
  "properties": {
    "addr:full":"H G Zwerusstr 612 Staphorst NL.08 7951 CZ",
    "addr:housenumber":"612;nl.08 7951",
    "iso:country":"NL",
    "sg:address":"H G Zwerusstr 612",
    "sg:city":"Staphorst",
    "sg:orig_category":"Ventilatiesystemen",
    "sg:phone":"+31 522 466 444",
    "sg:postcode":"7951 CZ",
    "sg:province":"NL.08",
    "wof:name":"Bergschenhoek Bv",
    "wof:placetype":"venue"
},
  "geometry": {"coordinates":[6.22151,52.643871],"type":"Point"}
}