{
  "type": "Feature",
  "properties": {
    "iso:country":"NL",
    "sg:address":"Breestr 2",
    "sg:city":"Opmeer",
    "sg:orig_category":"Beveiliging",
    "sg:phone":"+31 226 360 260",
    "sg:postcode":"1716 DB",
    "sg:province":"Noord-Holland",
    "sg:website":"http://www.regiocontrol.nl",
    "wof:name":"Regio Control",
    "wof:placetype":"venue"
},
  "geometry": {"coordinates":[4.945366,52.706779],"type":"Point"}
}