{
  "type": "Feature",
  "properties": {
    "iso:country":"NL",
    "sg:address":"Zeeburgerdk 175-1Hg",
    "sg:city":"Amsterdam",
    "sg:orig_category":"Grafisch Ontwerpers",
    "sg:phone":"+31 20 465 0283",
    "sg:postcode":"1095 AB",
    "sg:province":"Noord-Holland",
    "sg:website":"http://www.van-der-mark.nl",
    "wof:name":"Mark Tekst & Grafiek, Van Der",
    "wof:placetype":"venue"
},
  "geometry": {"coordinates":[4.941253,52.366249],"type":"Point"}
}