{
  "type": "Feature",
  "properties": {
    "addr:full":"Nieuwe Ellestraat 2 Heikant Zeeland 4566 BG",
    "addr:housenumber":"2",
    "addr:postcode":"4566",
    "addr:street":"Nieuwe Ellestraat",
    "iso:country":"NL",
    "sg:address":"Nieuwe Ellestraat 2",
    "sg:city":"Heikant",
    "sg:orig_category":"Levende Dieren Gh",
    "sg:phone":"+31 114 313 772",
    "sg:postcode":"4566 BG",
    "sg:province":"Zeeland",
    "wof:name":"Veehandel J. Van Dorsselaer",
    "wof:placetype":"venue"
},
  "geometry": {"coordinates":[4.025267,51.255039],"type":"Point"}
}