{
  "type": "Feature",
  "properties": {
    "addr:full":"V D Bergln 30 Voorthuizen Gelderland 3781 GH",
    "addr:housenumber":"30",
    "addr:postcode":"3781 gh",
    "addr:street":"V;Bergln;Gelderland",
    "iso:country":"NL",
    "sg:address":"V D Bergln 30",
    "sg:city":"Voorthuizen",
    "sg:orig_category":"Bejaarden - Verzorgingstehuizen",
    "sg:phone":"+31 342 479 500",
    "sg:postcode":"3781 GH",
    "sg:province":"Gelderland",
    "wof:name":"Avondrust",
    "wof:placetype":"venue"
},
  "geometry": {"coordinates":[5.605344,52.186821],"type":"Point"}
}