{
  "type": "Feature",
  "properties": {
    "addr:full":"Warmoesstr 102 Amsterdam North Holland 1012 JJ",
    "addr:housenumber":"102",
    "addr:postcode":"1012 jj",
    "iso:country":"NL",
    "sg:address":"Warmoesstr 102",
    "sg:city":"Amsterdam",
    "sg:orig_category":"Koffie En Thee - Groothandel",
    "sg:phone":"+31 20 624 0436",
    "sg:postcode":"1012 JJ",
    "sg:province":"North Holland",
    "sg:website":"http://www.wijs-zonen.nl",
    "wof:name":"Wijs En Zonen Bv",
    "wof:placetype":"venue"
},
  "geometry": {"coordinates":[4.896677,52.374397],"type":"Point"}
}