{
  "type": "Feature",
  "properties": {
    "addr:full":"Mr Troelstraln 1 Assen Provincie Drenthe 9402 BA",
    "addr:housenumber":"1",
    "addr:postcode":"9402 ba",
    "addr:street":"Provincie Drenthe",
    "iso:country":"NL",
    "sg:address":"Mr Troelstraln 1",
    "sg:city":"Assen",
    "sg:orig_category":"Autorijscholen",
    "sg:phone":"+31 592 346 760",
    "sg:postcode":"9402 BA",
    "sg:province":"Provincie Drenthe",
    "wof:name":"Reilman'S Verkeersschool",
    "wof:placetype":"venue"
},
  "geometry": {"coordinates":[6.563471,53.00058],"type":"Point"}
}