{
  "type": "Feature",
  "properties": {
    "addr:full":"Sterrenboslaan 25 Driebergen-Rijsenburg Utrecht 3972 GC",
    "addr:housenumber":"25",
    "addr:postcode":"3972 gc",
    "addr:street":"Sterrenboslaan",
    "iso:country":"NL",
    "sg:address":"Sterrenboslaan 25",
    "sg:city":"Driebergen-Rijsenburg",
    "sg:orig_category":"Verzekeringen",
    "sg:phone":"+31 343 531 815",
    "sg:postcode":"3972 GC",
    "sg:province":"Utrecht",
    "wof:name":"Van Dongen Assurantien",
    "wof:placetype":"venue"
},
  "geometry": {"coordinates":[5.284019,52.046463],"type":"Point"}
}