{
  "type": "Feature",
  "properties": {
    "iso:country":"NL",
    "sg:address":"Victorialn 21",
    "sg:city":"S Hertogenbosch",
    "sg:orig_category":"Voetbalverenigingen",
    "sg:phone":"+31 73 646 4700",
    "sg:postcode":"5213 JG",
    "sg:province":"North Brabant",
    "sg:website":"http://www.fcdenbosch.nl",
    "wof:name":"Fc Den Bosch",
    "wof:placetype":"venue"
},
  "geometry": {"coordinates":[5.328965,51.702465],"type":"Point"}
}