{
  "type": "Feature",
  "properties": {
    "addr:full":"Heerenwg 144 Heiloo North Holland 1851 KW",
    "addr:housenumber":"144",
    "addr:postcode":"1851 kw",
    "iso:country":"NL",
    "sg:address":"Heerenwg 144",
    "sg:city":"Heiloo",
    "sg:orig_category":"Schilders",
    "sg:phone":"+31 72 322 0606",
    "sg:postcode":"1851 KW",
    "sg:province":"North Holland",
    "wof:name":"Ursem & Zoon, Nic",
    "wof:placetype":"venue"
},
  "geometry": {"coordinates":[4.702716,52.599701],"type":"Point"}
}