{
  "type": "Feature",
  "properties": {
    "addr:full":"Westerkd 24 Utrecht Utrecht 3511 HB",
    "addr:housenumber":"24",
    "addr:postcode":"3511 hb",
    "addr:street":"Westerkd",
    "iso:country":"NL",
    "sg:address":"Westerkd 24",
    "sg:city":"Utrecht",
    "sg:orig_category":"Verloskundigen",
    "sg:phone":"+31 30 233 4976",
    "sg:postcode":"3511 HB",
    "sg:province":"Utrecht",
    "wof:name":"Praktijk Westerkade",
    "wof:placetype":"venue"
},
  "geometry": {"coordinates":[5.115405,52.088932],"type":"Point"}
}