{
  "type": "Feature",
  "properties": {
    "addr:full":"Spoetnikstr 6 Dirkshorn Noord-Holland 1746 AM",
    "addr:housenumber":"6",
    "addr:postcode":"1746",
    "addr:street":"Spoetnikstr",
    "iso:country":"NL",
    "sg:address":"Spoetnikstr 6",
    "sg:city":"Dirkshorn",
    "sg:orig_category":"Onderhoudswerken",
    "sg:phone":"+31 224 551 233",
    "sg:postcode":"1746 AM",
    "sg:province":"Noord-Holland",
    "wof:name":"Wedekind, B",
    "wof:placetype":"venue"
},
  "geometry": {"coordinates":[4.779081,52.745995],"type":"Point"}
}