{
  "type": "Feature",
  "properties": {
    "iso:country":"NL",
    "sg:address":"Spoetnikstr 6",
    "sg:city":"Dirkshorn",
    "sg:orig_category":"Onderhoudswerken",
    "sg:phone":"+31 224 551 233",
    "sg:postcode":"1746 AM",
    "sg:province":"Noord-Holland",
    "wof:name":"Wedekind, B",
    "wof:placetype":"venue"
},
  "geometry": {"coordinates":[4.779081,52.745995],"type":"Point"}
}