{
  "type": "Feature",
  "properties": {
    "iso:country":"NL",
    "sg:address":"Balistr 25",
    "sg:city":"S Gravenhage",
    "sg:orig_category":"Vertalers",
    "sg:phone":"+31 70 363 7554",
    "sg:postcode":"2585 XK",
    "sg:province":"Zuid-Holland",
    "wof:name":"Tucker, J",
    "wof:placetype":"venue"
},
  "geometry": {"coordinates":[4.29777,52.094799],"type":"Point"}
}