{
  "type": "Feature",
  "properties": {
    "iso:country":"NL",
    "sg:address":"Vlierdenseweg 191",
    "sg:city":"Vlierden",
    "sg:classifiers":[
        {
            "category":"Travel",
            "subcategory":"Hotels & Motels",
            "type":"Entertainment"
        }
    ],
    "sg:phone":"+31 493 315 171",
    "sg:postcode":"5756 AB",
    "sg:province":"Noord-Brabant",
    "wof:name":"Cafe De Vlierbocht",
    "wof:placetype":"venue"
},
  "geometry": {"coordinates":[5.761265,51.443726],"type":"Point"}
}