{
  "type": "Feature",
  "properties": {
    "addr:full":"Hof Van Spaland 22 Schiedam Zuid-Holland 3121 CB",
    "addr:housenumber":"22",
    "addr:postcode":"3121 cb",
    "addr:street":"Hof Van Spaland",
    "iso:country":"NL",
    "sg:address":"Hof Van Spaland 22",
    "sg:city":"Schiedam",
    "sg:orig_category":"Boekenuitgeverijen",
    "sg:phone":"+31 10 247 7185",
    "sg:postcode":"3121 CB",
    "sg:province":"Zuid-Holland",
    "wof:name":"Bruna",
    "wof:placetype":"venue"
},
  "geometry": {"coordinates":[4.376934,51.934612],"type":"Point"}
}