{
  "type": "Feature",
  "properties": {
    "addr:full":"Kastanjeboom 3 Culemborg Gelderland 4101 VS",
    "addr:housenumber":"3",
    "addr:postcode":"4101",
    "addr:street":"Kastanjeboom;Gelderland",
    "iso:country":"NL",
    "sg:address":"Kastanjeboom 3",
    "sg:city":"Culemborg",
    "sg:orig_category":"Marktonderzoekbureaus",
    "sg:phone":"+31 345 531 090",
    "sg:postcode":"4101 VS",
    "sg:province":"Gelderland",
    "wof:name":"Eacy Consultancy",
    "wof:placetype":"venue"
},
  "geometry": {"coordinates":[5.241828,51.95908],"type":"Point"}
}