{
  "type": "Feature",
  "properties": {
    "addr:full":"Aalsumerpoort 6 Dokkum Friesland 9101 JL",
    "addr:housenumber":"6",
    "addr:postcode":"9101 jl",
    "addr:street":"Aalsumerpoort",
    "iso:country":"NL",
    "sg:address":"Aalsumerpoort 6",
    "sg:city":"Dokkum",
    "sg:orig_category":"Hypotheken",
    "sg:phone":"+31 519 220 040",
    "sg:postcode":"9101 JL",
    "sg:province":"Friesland",
    "sg:website":"http://www.dokkum.hypotheekshop.nl/120",
    "wof:name":"Hypotheekshop, De",
    "wof:placetype":"venue"
},
  "geometry": {"coordinates":[6.000646,53.327858],"type":"Point"}
}