{
  "type": "Feature",
  "properties": {
    "addr:full":"Edisonstraat 31 Zoetermeer Zuid-Holland 2723 RS",
    "addr:housenumber":"31",
    "addr:postcode":"2723 rs",
    "addr:street":"Edisonstraat",
    "iso:country":"NL",
    "sg:address":"Edisonstraat 31",
    "sg:city":"Zoetermeer",
    "sg:orig_category":"Meubelreparatie And -Restauratie",
    "sg:phone":"+31 79 342 6652",
    "sg:postcode":"2723 RS",
    "sg:province":"Zuid-Holland",
    "wof:name":"Novanet Interieur Vernieuwers",
    "wof:placetype":"venue"
},
  "geometry": {"coordinates":[4.521839,52.061314],"type":"Point"}
}