{
  "type": "Feature",
  "properties": {
    "addr:full":"Strypln 371 Ryswyk Zh South Holland 2285 GM",
    "addr:housenumber":"371",
    "addr:postcode":"2285 gm",
    "addr:street":"Ryswyk Zh",
    "iso:country":"NL",
    "sg:address":"Strypln 371",
    "sg:city":"Ryswyk Zh",
    "sg:orig_category":"Onderhoudswerken",
    "sg:phone":"+31 70 396 8394",
    "sg:postcode":"2285 GM",
    "sg:province":"South Holland",
    "wof:name":"Schoe, L",
    "wof:placetype":"venue"
},
  "geometry": {"coordinates":[4.32436,52.037251],"type":"Point"}
}