{
  "type": "Feature",
  "properties": {
    "iso:country":"NL",
    "sg:address":"Kerkewijk 31A",
    "sg:city":"Veenendaal",
    "sg:orig_category":"Werving And Selectie Van Tijdelijk Personeel And Uitzendkantoren",
    "sg:phone":"+31 318 550 022",
    "sg:postcode":"3901 EB",
    "sg:province":"Utrecht",
    "wof:name":"Flair Bv",
    "wof:placetype":"venue"
},
  "geometry": {"coordinates":[5.5539050102,52.0241889954],"type":"Point"}
}