{
  "type": "Feature",
  "properties": {
    "addr:full":"Haarlemmerstraat 270 Leiden South Holland 2312 GL",
    "addr:housenumber":"270",
    "addr:postcode":"2312 gl",
    "addr:street":"Haarlemmerstraat",
    "iso:country":"NL",
    "sg:address":"Haarlemmerstraat 270",
    "sg:city":"Leiden",
    "sg:classifiers":[
        {
            "category":"Fast Food",
            "type":"Food & Drink"
        }
    ],
    "sg:phone":"+31 71 514 3308",
    "sg:postcode":"2312 GL",
    "sg:province":"South Holland",
    "sg:tags":[
        "afhaal",
        "restaurant"
    ],
    "wof:name":"O Sole Mio",
    "wof:placetype":"venue"
},
  "geometry": {"coordinates":[4.499508,52.161118],"type":"Point"}
}