{
  "type": "Feature",
  "properties": {
    "iso:country":"NL",
    "sg:address":"Karveel 4851",
    "sg:city":"Lelystad",
    "sg:orig_category":"Binnenhuisarchitecten",
    "sg:phone":"+31 320 245 487",
    "sg:postcode":"8242 VL",
    "sg:province":"Flevoland",
    "wof:name":"Mekaron",
    "wof:placetype":"venue"
},
  "geometry": {"coordinates":[5.459517,52.522682],"type":"Point"}
}