{
  "type": "Feature",
  "properties": {
    "addr:full":"Groenestr 343 Nijmegen Gelderland 6531 HN",
    "addr:housenumber":"343",
    "addr:postcode":"6531 hn",
    "addr:street":"Gelderland",
    "iso:country":"NL",
    "sg:address":"Groenestr 343",
    "sg:city":"Nijmegen",
    "sg:orig_category":"Schoenen",
    "sg:phone":"+31 24 377 0443",
    "sg:postcode":"6531 HN",
    "sg:province":"Gelderland",
    "wof:name":"Hol",
    "wof:placetype":"venue"
},
  "geometry": {"coordinates":[5.8412,51.83379],"type":"Point"}
}