{
  "type": "Feature",
  "properties": {
    "iso:country":"NL",
    "sg:address":"Scheveningsebos 6",
    "sg:city":"Zoetermeer",
    "sg:orig_category":"Juridische Dienstverlening",
    "sg:phone":"+31 79 351 3578",
    "sg:postcode":"2716 HT",
    "sg:province":"Zuid-Holland",
    "wof:name":"H.A. Brouwer",
    "wof:placetype":"venue"
},
  "geometry": {"coordinates":[4.465879,52.057205],"type":"Point"}
}