{
  "type": "Feature",
  "properties": {
    "addr:full":"Schaepmanlaan 3A Bergen Op Zoom North Brabant 4623 XV",
    "addr:housenumber":"3a",
    "addr:postcode":"4623 xv",
    "addr:street":"Schaepmanlaan",
    "iso:country":"NL",
    "sg:address":"Schaepmanlaan 3A",
    "sg:city":"Bergen Op Zoom",
    "sg:orig_category":"Medische And Orthopedische Artikelen",
    "sg:phone":"+31 164 212 828",
    "sg:postcode":"4623 XV",
    "sg:province":"North Brabant",
    "wof:name":"Welzorg",
    "wof:placetype":"venue"
},
  "geometry": {"coordinates":[4.311404,51.497002],"type":"Point"}
}