{
  "type": "Feature",
  "properties": {
    "addr:full":"Thiemsbrug 33 Hengelo Ov NL.08 7551 EZ",
    "addr:housenumber":"33",
    "addr:postcode":"7551 ez",
    "addr:street":"Thiemsbrug;Ov",
    "iso:country":"NL",
    "sg:address":"Thiemsbrug 33",
    "sg:city":"Hengelo Ov",
    "sg:orig_category":"Parkeergarages",
    "sg:phone":"+31 74 291 3986",
    "sg:postcode":"7551 EZ",
    "sg:province":"NL.08",
    "wof:name":"Thiemsbrug",
    "wof:placetype":"venue"
},
  "geometry": {"coordinates":[6.794759,52.267296],"type":"Point"}
}