{
  "type": "Feature",
  "properties": {
    "iso:country":"NL",
    "sg:address":"Vd Duinstr 89",
    "sg:city":"Sprang Capelle",
    "sg:orig_category":"Hek- En Rasterwerken",
    "sg:phone":"+31 416 280 995",
    "sg:postcode":"5161 BN",
    "sg:province":"Noord-Brabant",
    "wof:name":"Wico",
    "wof:placetype":"venue"
},
  "geometry": {"coordinates":[5.036857,51.667553],"type":"Point"}
}