{
  "type": "Feature",
  "properties": {
    "iso:country":"NL",
    "sg:address":"Jachthuisln 19",
    "sg:city":"Soest",
    "sg:classifiers":[
        {
            "category":"Sports & Exercise",
            "subcategory":"Stables",
            "type":"Entertainment"
        }
    ],
    "sg:phone":"+31 35 685 9038",
    "sg:postcode":"3762 LB",
    "sg:province":"Utrecht",
    "sg:tags":[
        "maneges"
    ],
    "wof:name":"Willemshoeve",
    "wof:placetype":"venue"
},
  "geometry": {"coordinates":[5.300385,52.184044],"type":"Point"}
}