{
  "type": "Feature",
  "properties": {
    "addr:full":"Zuidelyke Dwwg 9 Zevenhuizen Zh Zuid-Holland 2761 JN",
    "addr:housenumber":"9",
    "addr:postcode":"2761 jn",
    "addr:street":"Dwwg",
    "iso:country":"NL",
    "sg:address":"Zuidelyke Dwwg 9",
    "sg:city":"Zevenhuizen Zh",
    "sg:orig_category":"Bloemen En Planten - Groothandel",
    "sg:phone":"+31 180 631 433",
    "sg:postcode":"2761 JN",
    "sg:province":"Zuid-Holland",
    "wof:name":"Chamca Bv",
    "wof:placetype":"venue"
},
  "geometry": {"coordinates":[4.583465,52.008991],"type":"Point"}
}