{
  "type": "Feature",
  "properties": {
    "iso:country":"NL",
    "sg:address":"Wagenaarstr 6",
    "sg:city":"Amsterdam",
    "sg:orig_category":"Meubelmakerijen",
    "sg:phone":"+31 20 693 6612",
    "sg:postcode":"1093 CP",
    "sg:province":"North Holland",
    "wof:name":"Honk, Lilian Van",
    "wof:placetype":"venue"
},
  "geometry": {"coordinates":[4.924206,52.362492],"type":"Point"}
}