{
  "type": "Feature",
  "properties": {
    "addr:full":"Stationspln 45 Rotterdam South Holland 3013 AK",
    "addr:housenumber":"45",
    "addr:postcode":"3013 ak",
    "addr:street":"Stationspln",
    "iso:country":"NL",
    "sg:address":"Stationspln 45",
    "sg:city":"Rotterdam",
    "sg:orig_category":"Plotservice",
    "sg:phone":"+31 10 281 0134",
    "sg:postcode":"3013 AK",
    "sg:province":"South Holland",
    "wof:name":"Kontrast",
    "wof:placetype":"venue"
},
  "geometry": {"coordinates":[4.469456,51.923141],"type":"Point"}
}