{
  "type": "Feature",
  "properties": {
    "addr:full":"Boulevard 129 Katwyk Zh Zuid-Holland 2225 HC",
    "addr:housenumber":"129",
    "addr:postcode":"2225 hc",
    "addr:street":"Boulevard",
    "iso:country":"NL",
    "sg:address":"Boulevard 129",
    "sg:city":"Katwyk Zh",
    "sg:classifiers":[
        {
            "category":"Banks & Credit Unions",
            "subcategory":"Investment Brokerage",
            "type":"Services"
        }
    ],
    "sg:phone":"+31 71 401 3890",
    "sg:postcode":"2225 HC",
    "sg:province":"Zuid-Holland",
    "sg:tags":[
        "pension"
    ],
    "wof:name":"Anker, Het",
    "wof:placetype":"venue"
},
  "geometry": {"coordinates":[4.39099,52.20092],"type":"Point"}
}