{
  "type": "Feature",
  "properties": {
    "addr:full":"Langheckweg 13 Kerkrade Limburg 6468 EL",
    "addr:housenumber":"13",
    "addr:postcode":"6468 el",
    "addr:street":"Langheckweg",
    "iso:country":"NL",
    "sg:address":"Langheckweg 13",
    "sg:city":"Kerkrade",
    "sg:orig_category":"Loodgieterswerk, Verwarming And Sanitaire Installaties",
    "sg:phone":"+31 45 545 1200",
    "sg:postcode":"6468 EL",
    "sg:province":"Limburg",
    "wof:name":"Verwarmingsbedrijf F.A. Hajnadi Bv",
    "wof:placetype":"venue"
},
  "geometry": {"coordinates":[6.041135,50.873104],"type":"Point"}
}