{
  "type": "Feature",
  "properties": {
    "iso:country":"NL",
    "sg:address":"De Strengen 19",
    "sg:city":"Malden",
    "sg:orig_category":"Beveiliging",
    "sg:phone":"+31 24 357 3960",
    "sg:postcode":"6581 JX",
    "sg:province":"Gelderland",
    "wof:name":"Vdh Advice",
    "wof:placetype":"venue"
},
  "geometry": {"coordinates":[5.855423,51.771954],"type":"Point"}
}