{
  "type": "Feature",
  "properties": {
    "addr:full":"Wilhelminastr 49B Emmen Provincie Drenthe 7811 JE",
    "addr:housenumber":"49b",
    "addr:postcode":"7811 je",
    "addr:street":"Wilhelminastr;Provincie Drenthe",
    "iso:country":"NL",
    "sg:address":"Wilhelminastr 49B",
    "sg:city":"Emmen",
    "sg:orig_category":"Fotopersbureaus",
    "sg:phone":"+31 591 649 668",
    "sg:postcode":"7811 JE",
    "sg:province":"Provincie Drenthe",
    "wof:name":"Benting, B",
    "wof:placetype":"venue"
},
  "geometry": {"coordinates":[6.897003,52.784073],"type":"Point"}
}