{
  "type": "Feature",
  "properties": {
    "addr:full":"Oosterkd 24 Stadskanaal Groningen 9503 HP",
    "addr:housenumber":"24",
    "addr:postcode":"9503 hp",
    "addr:street":"Oosterkd",
    "iso:country":"NL",
    "sg:address":"Oosterkd 24",
    "sg:city":"Stadskanaal",
    "sg:orig_category":"Autopoetsbedrijven",
    "sg:phone":"+31 599 612 804",
    "sg:postcode":"9503 HP",
    "sg:province":"Groningen",
    "wof:name":"Musch",
    "wof:placetype":"venue"
},
  "geometry": {"coordinates":[6.959475,52.984375],"type":"Point"}
}