{
  "type": "Feature",
  "properties": {
    "addr:full":"Molvense Erven 254 Nuenen Noord-Brabant 5672 HS",
    "addr:housenumber":"254",
    "addr:postcode":"5672 hs",
    "addr:street":"Molvense Erven",
    "iso:country":"NL",
    "sg:address":"Molvense Erven 254",
    "sg:city":"Nuenen",
    "sg:orig_category":"Adviesbureaus Bedrijfsorganisatie",
    "sg:phone":"+31 40 290 6190",
    "sg:postcode":"5672 HS",
    "sg:province":"Noord-Brabant",
    "wof:name":"Zimad Bv",
    "wof:placetype":"venue"
},
  "geometry": {"coordinates":[5.543774,51.460819],"type":"Point"}
}