{
  "type": "Feature",
  "properties": {
    "addr:full":"Pynssen 8 Alkmaar Noord-Holland 1823 HC",
    "addr:housenumber":"8",
    "addr:postcode":"1823 hc",
    "addr:street":"Pynssen",
    "iso:country":"NL",
    "sg:address":"Pynssen 8",
    "sg:city":"Alkmaar",
    "sg:orig_category":"Webdesign Bureaus",
    "sg:phone":"+31 72 515 4117",
    "sg:postcode":"1823 HC",
    "sg:province":"Noord-Holland",
    "sg:website":"http://www.dutchwebfactory.nl",
    "wof:name":"Dutch Web Factory, Dwf",
    "wof:placetype":"venue"
},
  "geometry": {"coordinates":[4.7661027908,52.6351470947],"type":"Point"}
}