{
  "type": "Feature",
  "properties": {
    "iso:country":"NL",
    "sg:address":"Cromwielstraat 27",
    "sg:city":"Bergen Op Zoom",
    "sg:classifiers":[
        {
            "category":"Professional",
            "subcategory":"Accounting & Tax Preparation",
            "type":"Services"
        }
    ],
    "sg:phone":"+31 164 253 455",
    "sg:postcode":"4611 RM",
    "sg:province":"Noord-Brabant",
    "sg:tags":[
        "accountant"
    ],
    "wof:name":"R.G. Halderberge Bv",
    "wof:placetype":"venue"
},
  "geometry": {"coordinates":[4.288787,51.495659],"type":"Point"}
}