{
  "type": "Feature",
  "properties": {
    "addr:full":"Park De Horion 13 Tilburg Noord-Brabant 5014 EX",
    "addr:housenumber":"13",
    "addr:postcode":"5014 ex",
    "addr:street":"Park De Horion",
    "iso:country":"NL",
    "sg:address":"Park De Horion 13",
    "sg:city":"Tilburg",
    "sg:orig_category":"Diverse Grafische Activiteiten",
    "sg:phone":"+31 13 544 1964",
    "sg:postcode":"5014 EX",
    "sg:province":"Noord-Brabant",
    "wof:name":"Carla Dolk",
    "wof:placetype":"venue"
},
  "geometry": {"coordinates":[5.094027,51.562237],"type":"Point"}
}