{
  "type": "Feature",
  "properties": {
    "addr:full":"Tooropstr 46 Arnhem Gelderland 6813 KT",
    "addr:housenumber":"46",
    "addr:postcode":"6813 kt",
    "addr:street":"Tooropstr",
    "iso:country":"NL",
    "sg:address":"Tooropstr 46",
    "sg:city":"Arnhem",
    "sg:orig_category":"Grafisch Ontwerpers",
    "sg:phone":"+31 26 351 9667",
    "sg:postcode":"6813 KT",
    "sg:province":"Gelderland",
    "sg:website":"http://www.bureaukarakter.nl",
    "wof:name":"Karakter, Bureau",
    "wof:placetype":"venue"
},
  "geometry": {"coordinates":[5.885404,51.991817],"type":"Point"}
}