{
  "type": "Feature",
  "properties": {
    "addr:full":"Provincialewg 11A Vinkeveen Utrecht 3645 CN",
    "addr:housenumber":"11a",
    "addr:postcode":"3645 cn",
    "addr:street":"Provincialewg",
    "iso:country":"NL",
    "sg:address":"Provincialewg 11A",
    "sg:city":"Vinkeveen",
    "sg:orig_category":"Adviesbureaus Bedrijfsorganisatie",
    "sg:phone":"+31 297 255 929",
    "sg:postcode":"3645 CN",
    "sg:province":"Utrecht",
    "wof:name":"Rozema, Drs H",
    "wof:placetype":"venue"
},
  "geometry": {"coordinates":[4.9138832092,52.2159957886],"type":"Point"}
}