{
  "type": "Feature",
  "properties": {
    "addr:full":"Julianaweg 3 Utrecht Utrecht 3525 VA",
    "addr:housenumber":"3",
    "addr:postcode":"3525",
    "addr:street":"Julianaweg",
    "iso:country":"NL",
    "sg:address":"Julianaweg 3",
    "sg:city":"Utrecht",
    "sg:orig_category":"Organisaties And Verenigingen",
    "sg:phone":"+31 30 289 3256",
    "sg:postcode":"3525 VA",
    "sg:province":"Utrecht",
    "wof:name":"Puch Club Nederland",
    "wof:placetype":"venue"
},
  "geometry": {"coordinates":[5.1159548759,52.061050415],"type":"Point"}
}