{
  "type": "Feature",
  "properties": {
    "addr:full":"De Streek 9 Oude Leye Friesland 9071 XG",
    "addr:housenumber":"9",
    "addr:postcode":"9071 xg",
    "addr:street":"De Streek",
    "iso:country":"NL",
    "sg:address":"De Streek 9",
    "sg:city":"Oude Leye",
    "sg:orig_category":"Verenigingsgebouwen",
    "sg:phone":"+31 518 421 700",
    "sg:postcode":"9071 XG",
    "sg:province":"Friesland",
    "wof:name":"Ons Gebouw",
    "wof:placetype":"venue"
},
  "geometry": {"coordinates":[5.729084,53.288696],"type":"Point"}
}