{
  "type": "Feature",
  "properties": {
    "iso:country":"NL",
    "sg:address":"Gravenstr 8",
    "sg:city":"Amsterdam",
    "sg:orig_category":"Verenigingen En Stichtingen",
    "sg:phone":"+31 20 623 7509",
    "sg:postcode":"1012 NM",
    "sg:province":"North Holland",
    "wof:name":"Afghanistan Comit\u00e9 Ned, Sticht",
    "wof:placetype":"venue"
},
  "geometry": {"coordinates":[4.892922,52.374416],"type":"Point"}
}