{
  "type": "Feature",
  "properties": {
    "addr:full":"Statenlaan 17 Arnhem Gelderland 6828 WB",
    "addr:housenumber":"17",
    "addr:postcode":"6828 wb",
    "addr:street":"Statenlaan",
    "iso:country":"NL",
    "sg:address":"Statenlaan 17",
    "sg:city":"Arnhem",
    "sg:orig_category":"Bedrijfs- And Managementsconsultants",
    "sg:phone":"+31 26 442 1610",
    "sg:postcode":"6828 WB",
    "sg:province":"Gelderland",
    "wof:name":"Trendbureau If",
    "wof:placetype":"venue"
},
  "geometry": {"coordinates":[5.92156,51.979099],"type":"Point"}
}