{
  "type": "Feature",
  "properties": {
    "addr:full":"T Tuintje 16 Laren Nh North Holland 1251 RZ",
    "addr:housenumber":"16",
    "addr:postcode":"1251 rz",
    "addr:street":"T Tuintje;Nh North",
    "iso:country":"NL",
    "sg:address":"T Tuintje 16",
    "sg:city":"Laren Nh",
    "sg:orig_category":"Film-, Tv- And Videoproductie",
    "sg:phone":"+31 35 531 1961",
    "sg:postcode":"1251 RZ",
    "sg:province":"North Holland",
    "wof:name":"Frits Spits Communications Bv",
    "wof:placetype":"venue"
},
  "geometry": {"coordinates":[5.225496,52.248161],"type":"Point"}
}