{
  "type": "Feature",
  "properties": {
    "iso:country":"NL",
    "sg:address":"Zwaluwstr 90",
    "sg:city":"Hardenberg",
    "sg:orig_category":"Geluidsinstallaties",
    "sg:phone":"+31 523 262 761",
    "sg:postcode":"7771 AV",
    "sg:province":"Overijssel",
    "wof:name":"Hesselink",
    "wof:placetype":"venue"
},
  "geometry": {"coordinates":[6.607672,52.576294],"type":"Point"}
}