{
  "type": "Feature",
  "properties": {
    "addr:full":"Maartenbroerswg 97 Hansweert Zeeland 4417 BK",
    "addr:housenumber":"97",
    "addr:postcode":"4417 bk",
    "addr:street":"Maartenbroerswg",
    "iso:country":"NL",
    "sg:address":"Maartenbroerswg 97",
    "sg:city":"Hansweert",
    "sg:orig_category":"Oud Metaal",
    "sg:phone":"+31 113 382 877",
    "sg:postcode":"4417 BK",
    "sg:province":"Zeeland",
    "wof:name":"Reijerse, J P M",
    "wof:placetype":"venue"
},
  "geometry": {"coordinates":[4.0003972054,51.4513778687],"type":"Point"}
}