{
  "type": "Feature",
  "properties": {
    "addr:full":"Papaverweg 58 Nunspeet Gelderland 8072 EC",
    "addr:housenumber":"58",
    "addr:postcode":"8072 ec",
    "addr:street":"Papaverweg;Gelderland",
    "iso:country":"NL",
    "sg:address":"Papaverweg 58",
    "sg:city":"Nunspeet",
    "sg:orig_category":"Bloemen And Planten",
    "sg:phone":"+31 341 251 849",
    "sg:postcode":"8072 EC",
    "sg:province":"Gelderland",
    "wof:name":"De Papaver",
    "wof:placetype":"venue"
},
  "geometry": {"coordinates":[5.798545,52.383915],"type":"Point"}
}