{
  "type": "Feature",
  "properties": {
    "addr:full":"Ambachtswg 18 Zelhem Gelderland 7021 BT",
    "addr:housenumber":"18",
    "addr:postcode":"7021 bt",
    "addr:street":"Ambachtswg;Gelderland",
    "iso:country":"NL",
    "sg:address":"Ambachtswg 18",
    "sg:city":"Zelhem",
    "sg:orig_category":"Kunststoffen - Fabrieken En Groothandel",
    "sg:phone":"+31 314 627 762",
    "sg:postcode":"7021 BT",
    "sg:province":"Gelderland",
    "wof:name":"Mea Bv",
    "wof:placetype":"venue"
},
  "geometry": {"coordinates":[6.353922,51.999271],"type":"Point"}
}