{
  "type": "Feature",
  "properties": {
    "addr:full":"Ged Turfhaven 26A Hoorn Nh Noord-Holland 1621 HE",
    "addr:housenumber":"26a",
    "addr:postcode":"1621 he",
    "addr:street":"Turfhaven",
    "iso:country":"NL",
    "sg:address":"Ged Turfhaven 26A",
    "sg:city":"Hoorn Nh",
    "sg:orig_category":"Verzekeringen - Verzekeringskantoren",
    "sg:phone":"+31 229 298 883",
    "sg:postcode":"1621 HE",
    "sg:province":"Noord-Holland",
    "wof:name":"West Fries",
    "wof:placetype":"venue"
},
  "geometry": {"coordinates":[5.05207,52.642399],"type":"Point"}
}