{
  "type": "Feature",
  "properties": {
    "addr:full":"Hoefslag 15 Nijkerk Gld Gelderland 3862 KA",
    "addr:housenumber":"15",
    "addr:postcode":"3862 ka",
    "addr:street":"Hoefslag;Gld Gelderland",
    "iso:country":"NL",
    "sg:address":"Hoefslag 15",
    "sg:city":"Nijkerk Gld",
    "sg:classifiers":[
        {
            "category":"Education",
            "subcategory":"Preschool",
            "type":"Public Place"
        }
    ],
    "sg:phone":"+31 33 245 4338",
    "sg:postcode":"3862 KA",
    "sg:province":"Gelderland",
    "sg:tags":[
        "kleuteronderwijs",
        "basis-"
    ],
    "wof:name":"Het Baken",
    "wof:placetype":"venue"
},
  "geometry": {"coordinates":[5.49289,52.216721],"type":"Point"}
}