{
  "type": "Feature",
  "properties": {
    "addr:full":"Kamerlingh Onnesweg 44 Dordrecht South Holland 3316 GL",
    "addr:housenumber":"44",
    "addr:postcode":"3316 gl",
    "addr:street":"Kamerlingh Onnesweg",
    "iso:country":"NL",
    "sg:address":"Kamerlingh Onnesweg 44",
    "sg:city":"Dordrecht",
    "sg:orig_category":"Kantoorartikelen",
    "sg:phone":"+31 78 617 3333",
    "sg:postcode":"3316 GL",
    "sg:province":"South Holland",
    "wof:name":"De Singel & Naber Bv",
    "wof:placetype":"venue"
},
  "geometry": {"coordinates":[4.63352108,51.7798423767],"type":"Point"}
}