{
  "type": "Feature",
  "properties": {
    "addr:full":"Oudezijl 2 Nieuweschans Groningen 9693 PA",
    "addr:housenumber":"2",
    "addr:postcode":"9693 pa",
    "addr:street":"Oudezijl",
    "iso:country":"NL",
    "sg:address":"Oudezijl 2",
    "sg:city":"Nieuweschans",
    "sg:classifiers":[
        {
            "category":"Travel",
            "subcategory":"Hotels & Motels",
            "type":"Entertainment"
        }
    ],
    "sg:phone":"+31 597 521 282",
    "sg:postcode":"9693 PA",
    "sg:province":"Groningen",
    "wof:name":"Leeuwerik",
    "wof:placetype":"venue"
},
  "geometry": {"coordinates":[7.209017,53.180283],"type":"Point"}
}