{
  "type": "Feature",
  "properties": {
    "addr:full":"Julianastr 5 Berghem North Brabant 5351 AL",
    "addr:housenumber":"5",
    "addr:postcode":"5351 al",
    "addr:street":"Julianastr",
    "iso:country":"NL",
    "sg:address":"Julianastr 5",
    "sg:city":"Berghem",
    "sg:orig_category":"Kinderkleding",
    "sg:phone":"+31 412 405 166",
    "sg:postcode":"5351 AL",
    "sg:province":"North Brabant",
    "wof:name":"Kijkdoos, De",
    "wof:placetype":"venue"
},
  "geometry": {"coordinates":[5.565307,51.773285],"type":"Point"}
}