{
  "type": "Feature",
  "properties": {
    "addr:full":"Wendakker 33 Siddeburen Groningen 9628 BX",
    "addr:housenumber":"33",
    "addr:postcode":"9628 bx",
    "addr:street":"Wendakker",
    "iso:country":"NL",
    "sg:address":"Wendakker 33",
    "sg:city":"Siddeburen",
    "sg:classifiers":[
        {
            "category":"Retail",
            "subcategory":"Storage",
            "type":"Services"
        }
    ],
    "sg:phone":"+31 598 431 525",
    "sg:postcode":"9628 BX",
    "sg:province":"Groningen",
    "sg:tags":[
        "opslag",
        "bewaring"
    ],
    "wof:name":"Wit",
    "wof:placetype":"venue"
},
  "geometry": {"coordinates":[6.8608078957,53.2542953491],"type":"Point"}
}