{
  "type": "Feature",
  "properties": {
    "addr:full":"Plataanstraat 72 Hengelo Ov NL.08 7556 CB",
    "addr:housenumber":"72;7556",
    "addr:postcode":"cb",
    "addr:street":"Plataanstraat;Ov",
    "iso:country":"NL",
    "sg:address":"Plataanstraat 72",
    "sg:city":"Hengelo Ov",
    "sg:classifiers":[
        {
            "category":"Professional",
            "subcategory":"Accounting & Tax Preparation",
            "type":"Services"
        }
    ],
    "sg:phone":"+31 74 250 9702",
    "sg:postcode":"7556 CB",
    "sg:province":"NL.08",
    "sg:tags":[
        "accountant"
    ],
    "wof:name":"Tbn A.J. Nieuwenhuis",
    "wof:placetype":"venue"
},
  "geometry": {"coordinates":[6.792721,52.26981],"type":"Point"}
}