{
  "type": "Feature",
  "properties": {
    "iso:country":"NL",
    "sg:address":"Baarsjeswg 258",
    "sg:city":"Amsterdam",
    "sg:orig_category":"Projectontwikkeling",
    "sg:phone":"+31 20 486 0149",
    "sg:postcode":"1058 AC",
    "sg:province":"North Holland",
    "sg:website":"http://www.deomslag.nl",
    "wof:name":"Omslag, De",
    "wof:placetype":"venue"
},
  "geometry": {"coordinates":[4.856603,52.360954],"type":"Point"}
}