{
  "type": "Feature",
  "properties": {
    "addr:full":"Assumburg 6 Zwyndrecht Zuid-Holland 3334 EA",
    "addr:housenumber":"6",
    "addr:postcode":"3334 ea",
    "addr:street":"Assumburg",
    "iso:country":"NL",
    "sg:address":"Assumburg 6",
    "sg:city":"Zwyndrecht",
    "sg:orig_category":"Afslankinstituten",
    "sg:phone":"+31 78 612 4573",
    "sg:postcode":"3334 EA",
    "sg:province":"Zuid-Holland",
    "wof:name":"Ega Ned",
    "wof:placetype":"venue"
},
  "geometry": {"coordinates":[4.60917,51.817219],"type":"Point"}
}