{
  "type": "Feature",
  "properties": {
    "addr:full":"Langesteeg 20 Sint Oedenrode North Brabant 5491 TM",
    "addr:housenumber":"20",
    "addr:postcode":"5491 tm",
    "addr:street":"Langesteeg;Oedenrode",
    "iso:country":"NL",
    "sg:address":"Langesteeg 20",
    "sg:city":"Sint Oedenrode",
    "sg:orig_category":"Verzekeringen",
    "sg:phone":"+31 413 476 674",
    "sg:postcode":"5491 TM",
    "sg:province":"North Brabant",
    "wof:name":"Karin Bekkers Assurantien",
    "wof:placetype":"venue"
},
  "geometry": {"coordinates":[5.467915,51.580463],"type":"Point"}
}