{
  "type": "Feature",
  "properties": {
    "addr:full":"Visserstraat 38 Steenbergen Nb Noord-Brabant 4651 BJ",
    "addr:housenumber":"38",
    "addr:postcode":"4651 bj",
    "addr:street":"Visserstraat",
    "iso:country":"NL",
    "sg:address":"Visserstraat 38",
    "sg:city":"Steenbergen Nb",
    "sg:classifiers":[
        {
            "category":"Professional",
            "subcategory":"Accounting & Tax Preparation",
            "type":"Services"
        }
    ],
    "sg:phone":"+31 167 561 400",
    "sg:postcode":"4651 BJ",
    "sg:province":"Noord-Brabant",
    "sg:tags":[
        "accountant"
    ],
    "wof:name":"Administratiekantoor Goossens En Van Der Weegen",
    "wof:placetype":"venue"
},
  "geometry": {"coordinates":[4.318086,51.58736],"type":"Point"}
}