{
  "type": "Feature",
  "properties": {
    "addr:full":"Atlantischestr 17 Emmeloord NL. 8303 VT",
    "addr:housenumber":"17",
    "addr:postcode":"8303",
    "addr:street":"Atlantischestr;Nl.",
    "iso:country":"NL",
    "sg:address":"Atlantischestr 17",
    "sg:city":"Emmeloord",
    "sg:orig_category":"Woningstoffeerders",
    "sg:phone":"+31 527 616 766",
    "sg:postcode":"8303 VT",
    "sg:province":"NL.",
    "wof:name":"Zeldenthuis",
    "wof:placetype":"venue"
},
  "geometry": {"coordinates":[5.7331461906,52.7132911682],"type":"Point"}
}