{
  "type": "Feature",
  "properties": {
    "addr:full":"M Cherubinastr 142 Breda Noord-Brabant 4817 KZ",
    "addr:housenumber":"142",
    "addr:postcode":"4817 kz",
    "iso:country":"NL",
    "sg:address":"M Cherubinastr 142",
    "sg:city":"Breda",
    "sg:orig_category":"Bedrijfsopleidingen",
    "sg:phone":"+31 76 520 4815",
    "sg:postcode":"4817 KZ",
    "sg:province":"Noord-Brabant",
    "wof:name":"Zandberg",
    "wof:placetype":"venue"
},
  "geometry": {"coordinates":[4.79164,51.590218],"type":"Point"}
}