{
  "type": "Feature",
  "properties": {
    "addr:full":"Bosheide 49 Landgraaf Limburg 6373 CK",
    "addr:housenumber":"49",
    "addr:postcode":"6373 ck",
    "addr:street":"Bosheide",
    "iso:country":"NL",
    "sg:address":"Bosheide 49",
    "sg:city":"Landgraaf",
    "sg:orig_category":"Boekhouders",
    "sg:phone":"+31 45 531 5529",
    "sg:postcode":"6373 CK",
    "sg:province":"Limburg",
    "wof:name":"Administratiekantoor Erkens",
    "wof:placetype":"venue"
},
  "geometry": {"coordinates":[6.02408,50.912312],"type":"Point"}
}