{
  "type": "Feature",
  "properties": {
    "addr:full":"Grt Markt 29 Schiedam Zuid-Holland 3111 NH",
    "addr:housenumber":"29",
    "addr:postcode":"3111 nh",
    "addr:street":"Markt",
    "iso:country":"NL",
    "sg:address":"Grt Markt 29",
    "sg:city":"Schiedam",
    "sg:orig_category":"Balletscholen",
    "sg:phone":"+31 10 426 9050",
    "sg:postcode":"3111 NH",
    "sg:province":"Zuid-Holland",
    "wof:name":"Balm Ballet Dance & Sport, Tosca",
    "wof:placetype":"venue"
},
  "geometry": {"coordinates":[4.39816,51.918472],"type":"Point"}
}