{
  "type": "Feature",
  "properties": {
    "addr:full":"Kwartslaan 10 Rhoon South Holland 3162 RD",
    "addr:housenumber":"10",
    "addr:postcode":"3162 rd",
    "addr:street":"Kwartslaan",
    "iso:country":"NL",
    "sg:address":"Kwartslaan 10",
    "sg:city":"Rhoon",
    "sg:orig_category":"Tuinaanleg En -Onderhoud",
    "sg:phone":"+31 180 634 200",
    "sg:postcode":"3162 RD",
    "sg:province":"South Holland",
    "wof:name":"Akkers, De",
    "wof:placetype":"venue"
},
  "geometry": {"coordinates":[4.48324,51.85297],"type":"Point"}
}