{
  "type": "Feature",
  "properties": {
    "addr:full":"Melkmarkt 47 Zwolle Overijssel 8011 MB",
    "addr:housenumber":"47",
    "addr:postcode":"8011 mb",
    "addr:street":"Melkmarkt",
    "iso:country":"NL",
    "sg:address":"Melkmarkt 47",
    "sg:city":"Zwolle",
    "sg:orig_category":"Adviesbureaus Bedrijfsorganisatie",
    "sg:phone":"+31 38 422 4299",
    "sg:postcode":"8011 MB",
    "sg:province":"Overijssel",
    "sg:website":"http://www.vandebuntzwolle.nl",
    "wof:name":"Bunt Zwolle Bv, Van De",
    "wof:placetype":"venue"
},
  "geometry": {"coordinates":[6.090224,52.512985],"type":"Point"}
}