{
  "type": "Feature",
  "properties": {
    "iso:country":"NL",
    "sg:address":"Mr. P.J. Troelstraweg 185",
    "sg:city":"Leeuwarden",
    "sg:orig_category":"Drukkerijen And Copyshops",
    "sg:phone":"+31 58 215 7015",
    "sg:postcode":"8919 AB",
    "sg:province":"Friesland",
    "wof:name":"Henk Louwen Drukwerk",
    "wof:placetype":"venue"
},
  "geometry": {"coordinates":[5.779481,53.223804],"type":"Point"}
}