{
  "type": "Feature",
  "properties": {
    "addr:full":"Meidoornln 18A Brummen Gelderland 6971 EX",
    "addr:housenumber":"18a",
    "addr:postcode":"6971 ex",
    "addr:street":"Meidoornln;Gelderland",
    "iso:country":"NL",
    "sg:address":"Meidoornln 18A",
    "sg:city":"Brummen",
    "sg:orig_category":"Peuterspeelzalen",
    "sg:phone":"+31 575 562 632",
    "sg:postcode":"6971 EX",
    "sg:province":"Gelderland",
    "wof:name":"Brummeltje, 'T",
    "wof:placetype":"venue"
},
  "geometry": {"coordinates":[6.154282,52.092381],"type":"Point"}
}