{
  "type": "Feature",
  "properties": {
    "iso:country":"NL",
    "sg:address":"Rotterd Airp Pln 56",
    "sg:city":"Rotterdam",
    "sg:orig_category":"Luchtreclame",
    "sg:phone":"+31 10 437 7877",
    "sg:postcode":"3045 AP",
    "sg:province":"Zuid-Holland",
    "wof:name":"Sand",
    "wof:placetype":"venue"
},
  "geometry": {"coordinates":[4.433566,51.949123],"type":"Point"}
}