{
  "type": "Feature",
  "properties": {
    "addr:full":"Stationsweg 6 'S Hertogenbosch Noord-Brabant 5211 TW",
    "addr:housenumber":"6 ' s",
    "addr:postcode":"5211 tw",
    "addr:street":"Stationsweg",
    "iso:country":"NL",
    "sg:address":"Stationsweg 6",
    "sg:city":"'S Hertogenbosch",
    "sg:orig_category":"Apothekers",
    "sg:phone":"+31 73 613 7575",
    "sg:postcode":"5211 TW",
    "sg:province":"Noord-Brabant",
    "wof:name":"Apotheek Van Den Dries",
    "wof:placetype":"venue"
},
  "geometry": {"coordinates":[5.297747,51.690201],"type":"Point"}
}