{
  "type": "Feature",
  "properties": {
    "addr:full":"Waarddijk Noord 4 Oudkarspel Noord-Holland 1724 PH",
    "addr:housenumber":"4",
    "addr:postcode":"1724",
    "addr:street":"Waarddijk Noord",
    "iso:country":"NL",
    "sg:address":"Waarddijk Noord 4",
    "sg:city":"Oudkarspel",
    "sg:orig_category":"Metaalafval, Schrootrecycling And Sloperijen",
    "sg:phone":"+31 226 313 087",
    "sg:postcode":"1724 PH",
    "sg:province":"Noord-Holland",
    "wof:name":"Cees Van Der Zel",
    "wof:placetype":"venue"
},
  "geometry": {"coordinates":[4.828356,52.717178],"type":"Point"}
}