{
  "type": "Feature",
  "properties": {
    "addr:full":"Meester Borgesiusstraat 30 Appingedam Groningen 9902 GD",
    "addr:housenumber":"30",
    "addr:postcode":"9902 gd",
    "addr:street":"Meester Borgesiusstraat",
    "iso:country":"NL",
    "sg:address":"Meester Borgesiusstraat 30",
    "sg:city":"Appingedam",
    "sg:orig_category":"Begrafenisondernemers",
    "sg:phone":"+31 596 623 015",
    "sg:postcode":"9902 GD",
    "sg:province":"Groningen",
    "wof:name":"Begrafenisvereniging Opwierde",
    "wof:placetype":"venue"
},
  "geometry": {"coordinates":[6.870144,53.318748],"type":"Point"}
}