{
  "type": "Feature",
  "properties": {
    "addr:full":"Horstacker 2329 Nijmegen Gelderland 6546 GK",
    "addr:housenumber":"2329",
    "addr:postcode":"6546 gk",
    "addr:street":"Horstacker;Gelderland",
    "iso:country":"NL",
    "sg:address":"Horstacker 2329",
    "sg:city":"Nijmegen",
    "sg:orig_category":"Diverse Bedrijfsinstallaties Gh",
    "sg:phone":"+31 24 378 7701",
    "sg:postcode":"6546 GK",
    "sg:province":"Gelderland",
    "wof:name":"Arntz Heftrucks",
    "wof:placetype":"venue"
},
  "geometry": {"coordinates":[5.794511,51.829575],"type":"Point"}
}