{
  "type": "Feature",
  "properties": {
    "addr:full":"De Poel 8 Gennep Limburg 6591 BV",
    "addr:housenumber":"8",
    "addr:postcode":"6591 bv",
    "addr:street":"De Poel",
    "iso:country":"NL",
    "sg:address":"De Poel 8",
    "sg:city":"Gennep",
    "sg:classifiers":[
        {
            "category":"Food & Beverages",
            "subcategory":"Fruits & Vegetables",
            "type":"Retail Goods"
        }
    ],
    "sg:phone":"+31 485 514 244",
    "sg:postcode":"6591 BV",
    "sg:province":"Limburg",
    "sg:tags":[
        "en",
        "groenten"
    ],
    "wof:name":"Elemans, F J",
    "wof:placetype":"venue"
},
  "geometry": {"coordinates":[5.968822,51.700638],"type":"Point"}
}