{
  "type": "Feature",
  "properties": {
    "addr:full":"Kelvinstr 21 Dedemsvaart Overijssel 7701 BZ",
    "addr:housenumber":"21",
    "addr:postcode":"7701 bz",
    "addr:street":"Kelvinstr",
    "iso:country":"NL",
    "sg:address":"Kelvinstr 21",
    "sg:city":"Dedemsvaart",
    "sg:orig_category":"Verhuur",
    "sg:phone":"+31 523 614 823",
    "sg:postcode":"7701 BZ",
    "sg:province":"Overijssel",
    "sg:website":"http://www.augie-attractieverhuur.nl",
    "wof:name":"Augie Attractieverhuur",
    "wof:placetype":"venue"
},
  "geometry": {"coordinates":[6.477657,52.605042],"type":"Point"}
}