{
  "type": "Feature",
  "properties": {
    "addr:full":"Oosterhamriklaan 195 Groningen Groningen 9715 PD",
    "addr:housenumber":"195",
    "addr:postcode":"9715 pd",
    "addr:street":"Oosterhamriklaan",
    "iso:country":"NL",
    "sg:address":"Oosterhamriklaan 195",
    "sg:city":"Groningen",
    "sg:orig_category":"Kinderopvang Behalve Thuis",
    "sg:phone":"+31 50 577 3103",
    "sg:postcode":"9715 PD",
    "sg:province":"Groningen",
    "wof:name":"Kinderdagverblijf De Grote Smurf",
    "wof:placetype":"venue"
},
  "geometry": {"coordinates":[6.570968,53.235977],"type":"Point"}
}