{
  "type": "Feature",
  "properties": {
    "addr:full":"Sportmark 134 Almere NL. 1355 KK",
    "addr:housenumber":"134",
    "addr:postcode":"1355 kk",
    "addr:street":"Sportmark;Nl.",
    "iso:country":"NL",
    "sg:address":"Sportmark 134",
    "sg:city":"Almere",
    "sg:orig_category":"Webdesign Bureaus",
    "sg:phone":"+31 36 538 6260",
    "sg:postcode":"1355 KK",
    "sg:province":"NL.",
    "sg:website":"http://www.roccomastino-internetproductions.nl",
    "wof:name":"Rocco Mastino",
    "wof:placetype":"venue"
},
  "geometry": {"coordinates":[5.2319288254,52.3447418213],"type":"Point"}
}