{
  "type": "Feature",
  "properties": {
    "addr:full":"Sydneystr 40 Rotterdam Zuid-Holland 3047 BP",
    "addr:housenumber":"40",
    "addr:postcode":"3047 bp",
    "addr:street":"Sydneystr",
    "iso:country":"NL",
    "sg:address":"Sydneystr 40",
    "sg:city":"Rotterdam",
    "sg:orig_category":"Koeltechniek",
    "sg:phone":"+31 10 415 2676",
    "sg:postcode":"3047 BP",
    "sg:province":"Zuid-Holland",
    "wof:name":"Ecr-Nederland Bv",
    "wof:placetype":"venue"
},
  "geometry": {"coordinates":[4.407637,51.941051],"type":"Point"}
}