{
  "type": "Feature",
  "properties": {
    "addr:full":"Dillenburgstr 16 Eindhoven North Brabant 5652 AP",
    "addr:housenumber":"16",
    "addr:postcode":"5652 ap",
    "addr:street":"Dillenburgstr",
    "iso:country":"NL",
    "sg:address":"Dillenburgstr 16",
    "sg:city":"Eindhoven",
    "sg:orig_category":"Metaalbewerking",
    "sg:phone":"+31 40 238 0800",
    "sg:postcode":"5652 AP",
    "sg:province":"North Brabant",
    "sg:website":"http://www.anoprint.com",
    "wof:name":"Anoprint Bv",
    "wof:placetype":"venue"
},
  "geometry": {"coordinates":[5.437164,51.426849],"type":"Point"}
}