{
  "type": "Feature",
  "properties": {
    "iso:country":"NL",
    "sg:address":"Tempeliersstr 20A",
    "sg:city":"Haarlem",
    "sg:orig_category":"Notarissen En Notariskantoren",
    "sg:phone":"+31 23 553 0900",
    "sg:postcode":"2012 ED",
    "sg:province":"North Holland",
    "sg:website":"http://www.batenburg.net",
    "wof:name":"Mr H Feijen, Notaris Maatschap Batenburg",
    "wof:placetype":"venue"
},
  "geometry": {"coordinates":[4.626775,52.375751],"type":"Point"}
}