{
  "type": "Feature",
  "properties": {
    "addr:full":"Akkerweg 1 Wintelre Mendoza 5513 AR",
    "addr:housenumber":"1",
    "addr:postcode":"5513",
    "addr:street":"Akkerweg;Mendoza",
    "iso:country":"NL",
    "sg:address":"Akkerweg 1",
    "sg:city":"Wintelre",
    "sg:orig_category":"Overheidsdiensten",
    "sg:phone":"+31 40 205 1444",
    "sg:postcode":"5513 AR",
    "sg:province":"Mendoza",
    "wof:name":"Gemeenschaphuis De Rosdoek",
    "wof:placetype":"venue"
},
  "geometry": {"coordinates":[-68.7401809692,-32.9599189758],"type":"Point"}
}