{
  "type": "Feature",
  "properties": {
    "addr:full":"Wordragensestr 1A Ammerzoden Gelderland 5324 JL",
    "addr:housenumber":"1a",
    "addr:postcode":"5324 jl",
    "addr:street":"Wordragensestr;Gelderland",
    "iso:country":"NL",
    "sg:address":"Wordragensestr 1A",
    "sg:city":"Ammerzoden",
    "sg:orig_category":"Koeltechniek",
    "sg:phone":"+31 73 599 1561",
    "sg:postcode":"5324 JL",
    "sg:province":"Gelderland",
    "sg:website":"http://www.delaat.nl",
    "wof:name":"Laat, De",
    "wof:placetype":"venue"
},
  "geometry": {"coordinates":[5.228174,51.756458],"type":"Point"}
}