{
  "type": "Feature",
  "properties": {
    "addr:full":"Huis Te Landeln 29 Ryswyk Zh Zuid-Holland 2283 SE",
    "addr:housenumber":"29",
    "addr:postcode":"2283 se",
    "addr:street":"Huis Te Landeln",
    "iso:country":"NL",
    "sg:address":"Huis Te Landeln 29",
    "sg:city":"Ryswyk Zh",
    "sg:orig_category":"Onroerende Goederen",
    "sg:phone":"+31 70 394 3395",
    "sg:postcode":"2283 SE",
    "sg:province":"Zuid-Holland",
    "wof:name":"Cort Bv",
    "wof:placetype":"venue"
},
  "geometry": {"coordinates":[4.32436,52.037251],"type":"Point"}
}