{
  "type": "Feature",
  "properties": {
    "addr:full":"Dalemstraat 54 Gorinchem South Holland 4201 BR",
    "addr:housenumber":"54",
    "addr:postcode":"4201 br",
    "addr:street":"Dalemstraat",
    "iso:country":"NL",
    "sg:address":"Dalemstraat 54",
    "sg:city":"Gorinchem",
    "sg:orig_category":"Autokeuringen",
    "sg:phone":"+31 183 638 248",
    "sg:postcode":"4201 BR",
    "sg:province":"South Holland",
    "wof:name":"Martin Roest",
    "wof:placetype":"venue"
},
  "geometry": {"coordinates":[4.979502,51.828655],"type":"Point"}
}