{
  "type": "Feature",
  "properties": {
    "iso:country":"NL",
    "sg:address":"Boerkist 14",
    "sg:city":"Meppel",
    "sg:orig_category":"Zonnebank- En Solariumcentra",
    "sg:phone":"+31 522 262 323",
    "sg:postcode":"7943 LA",
    "sg:province":"Drenthe",
    "wof:name":"Aqua-Sun",
    "wof:placetype":"venue"
},
  "geometry": {"coordinates":[6.223591,52.699883],"type":"Point"}
}