{
  "type": "Feature",
  "properties": {
    "iso:country":"NL",
    "sg:address":"Julianastr 46",
    "sg:city":"Alphen Aan Den Ryn",
    "sg:orig_category":"Herenkleding",
    "sg:phone":"+31 172 472 135",
    "sg:postcode":"2405 CH",
    "sg:province":"Zuid-Holland",
    "wof:name":"Odijk",
    "wof:placetype":"venue"
},
  "geometry": {"coordinates":[6.703417,47.01318],"type":"Point"}
}