{
  "type": "Feature",
  "properties": {
    "iso:country":"NL",
    "sg:address":"Parallelwg 59",
    "sg:city":"De Krim",
    "sg:orig_category":"Verzekeringen - Verzekeringskantoren",
    "sg:phone":"+31 524 571 225",
    "sg:postcode":"7782 PG",
    "sg:province":"Overijssel",
    "wof:name":"Coevorden",
    "wof:placetype":"venue"
},
  "geometry": {"coordinates":[6.632782,52.652687],"type":"Point"}
}