{
  "type": "Feature",
  "properties": {
    "addr:full":"Bette Van Suttnerlaan 152 Amstelveen Noord-Holland 1187 SZ",
    "addr:housenumber":"152",
    "addr:postcode":"1187 sz",
    "addr:street":"Bette Van Suttnerlaan",
    "iso:country":"NL",
    "sg:address":"Bette Van Suttnerlaan 152",
    "sg:city":"Amstelveen",
    "sg:orig_category":"Gebouwenafwerking, Renovaties And Reiniging",
    "sg:phone":"+31 20 641 7520",
    "sg:postcode":"1187 SZ",
    "sg:province":"Noord-Holland",
    "wof:name":"Fa. Dol",
    "wof:placetype":"venue"
},
  "geometry": {"coordinates":[4.830125,52.276489],"type":"Point"}
}