{
  "type": "Feature",
  "properties": {
    "addr:full":"Dorpsstr 61 Lexmond South Holland 4128 BW",
    "addr:housenumber":"61",
    "addr:postcode":"4128 bw",
    "addr:street":"Dorpsstr",
    "iso:country":"NL",
    "sg:address":"Dorpsstr 61",
    "sg:city":"Lexmond",
    "sg:orig_category":"Kappers",
    "sg:phone":"+31 347 341 580",
    "sg:postcode":"4128 BW",
    "sg:province":"South Holland",
    "wof:name":"Isabel",
    "wof:placetype":"venue"
},
  "geometry": {"coordinates":[5.0363712311,51.9632644653],"type":"Point"}
}