{
  "type": "Feature",
  "properties": {
    "addr:full":"Sportln 5 Vlaardingen Zuid-Holland 3135 GR",
    "addr:housenumber":"5",
    "addr:postcode":"3135",
    "addr:street":"Sportln",
    "iso:country":"NL",
    "sg:address":"Sportln 5",
    "sg:city":"Vlaardingen",
    "sg:orig_category":"Adviesbureaus Bouwkunde",
    "sg:phone":"+31 10 434 8820",
    "sg:postcode":"3135 GR",
    "sg:province":"Zuid-Holland",
    "wof:name":"Maat, C",
    "wof:placetype":"venue"
},
  "geometry": {"coordinates":[4.340359,51.910442],"type":"Point"}
}