{
  "type": "Feature",
  "properties": {
    "addr:full":"Vrystr 50 Eindhoven Noord-Brabant 5611 AW",
    "addr:housenumber":"50",
    "addr:postcode":"5611 aw",
    "addr:street":"Vrystr",
    "iso:country":"NL",
    "sg:address":"Vrystr 50",
    "sg:city":"Eindhoven",
    "sg:orig_category":"Schoenen",
    "sg:phone":"+31 40 244 3991",
    "sg:postcode":"5611 AW",
    "sg:province":"Noord-Brabant",
    "wof:name":"Bristol",
    "wof:placetype":"venue"
},
  "geometry": {"coordinates":[5.484105,51.434471],"type":"Point"}
}