{
  "type": "Feature",
  "properties": {
    "iso:country":"NL",
    "sg:address":"Het Kant 43",
    "sg:city":"Houten",
    "sg:orig_category":"Werving And Selectie Van Tijdelijk Personeel And Uitzendkantoren",
    "sg:phone":"+31 30 635 3433",
    "sg:postcode":"3995 DZ",
    "sg:province":"Utrecht",
    "wof:name":"Adecco",
    "wof:placetype":"venue"
},
  "geometry": {"coordinates":[5.1656827927,52.0347824097],"type":"Point"}
}