{
  "type": "Feature",
  "properties": {
    "addr:full":"Eversstraat 30 Loo Gld Gelderland 6924 BB",
    "addr:housenumber":"30",
    "addr:postcode":"6924 bb",
    "addr:street":"Eversstraat",
    "iso:country":"NL",
    "sg:address":"Eversstraat 30",
    "sg:city":"Loo Gld",
    "sg:orig_category":"Fotografische And Optische Artikelen Gh",
    "sg:phone":"+31 316 263 747",
    "sg:postcode":"6924 BB",
    "sg:province":"Gelderland",
    "wof:name":"W M Rosendahl",
    "wof:placetype":"venue"
},
  "geometry": {"coordinates":[5.990712,51.927906],"type":"Point"}
}