{
  "type": "Feature",
  "properties": {
    "addr:full":"Westzeedk 78 Rotterdam Zuid-Holland 3016 AG",
    "addr:housenumber":"78",
    "addr:postcode":"3016",
    "addr:street":"Westzeedk",
    "iso:country":"NL",
    "sg:address":"Westzeedk 78",
    "sg:city":"Rotterdam",
    "sg:classifiers":[
        {
            "category":"Education",
            "subcategory":"Special Training",
            "type":"Public Place"
        }
    ],
    "sg:phone":"+31 10 241 8282",
    "sg:postcode":"3016 AG",
    "sg:province":"Zuid-Holland",
    "sg:tags":[
        "expertise"
    ],
    "wof:name":"Surallmar",
    "wof:placetype":"venue"
},
  "geometry": {"coordinates":[4.476849,51.910954],"type":"Point"}
}