{
  "type": "Feature",
  "properties": {
    "addr:full":"Bedrijvenweg 2 Fijnaart North Brabant 4793 SK",
    "addr:housenumber":"2",
    "addr:postcode":"4793 sk",
    "addr:street":"Bedrijvenweg",
    "iso:country":"NL",
    "sg:address":"Bedrijvenweg 2",
    "sg:city":"Fijnaart",
    "sg:orig_category":"Werving And Selectie Van Tijdelijk Personeel And Uitzendkantoren",
    "sg:phone":"+31 168 468 183",
    "sg:postcode":"4793 SK",
    "sg:province":"North Brabant",
    "wof:name":"Albotec",
    "wof:placetype":"venue"
},
  "geometry": {"coordinates":[4.4779801369,51.6404037476],"type":"Point"}
}