{
  "type": "Feature",
  "properties": {
    "addr:full":"Klappolder 130 Bleiswijk Zuid-Holland 2665 LP",
    "addr:housenumber":"130",
    "addr:postcode":"2665 lp",
    "addr:street":"Klappolder",
    "iso:country":"NL",
    "sg:address":"Klappolder 130",
    "sg:city":"Bleiswijk",
    "sg:orig_category":"Veilingen",
    "sg:phone":"+31 10 529 7777",
    "sg:postcode":"2665 LP",
    "sg:province":"Zuid-Holland",
    "wof:name":"Bloemenveiling Holland Veilcentrum Bleis",
    "wof:placetype":"venue"
},
  "geometry": {"coordinates":[4.541841,52.028355],"type":"Point"}
}