{
  "type": "Feature",
  "properties": {
    "addr:full":"Industrieweg 17 Wolvega Friesland 8471 AD",
    "addr:housenumber":"17",
    "addr:postcode":"8471 ad",
    "addr:street":"Industrieweg",
    "iso:country":"NL",
    "sg:address":"Industrieweg 17",
    "sg:city":"Wolvega",
    "sg:orig_category":"Metaalwerken",
    "sg:phone":"+31 561 614 255",
    "sg:postcode":"8471 AD",
    "sg:province":"Friesland",
    "wof:name":"Wolvega Panelen Bv",
    "wof:placetype":"venue"
},
  "geometry": {"coordinates":[5.994632,52.883129],"type":"Point"}
}