{
  "type": "Feature",
  "properties": {
    "addr:full":"Kapitein Hatterasstraat 17 Tilburg Noord-Brabant 5015 BB",
    "addr:housenumber":"17",
    "addr:postcode":"5015 bb",
    "addr:street":"Kapitein Hatterasstraat",
    "iso:country":"NL",
    "sg:address":"Kapitein Hatterasstraat 17",
    "sg:city":"Tilburg",
    "sg:orig_category":"Autokeuringen",
    "sg:phone":"+31 13 583 5353",
    "sg:postcode":"5015 BB",
    "sg:province":"Noord-Brabant",
    "wof:name":"Autotaalglas",
    "wof:placetype":"venue"
},
  "geometry": {"coordinates":[5.1107192039,51.569519043],"type":"Point"}
}