{
  "type": "Feature",
  "properties": {
    "iso:country":"NL",
    "sg:address":"Kapitein Hatterasstraat 17",
    "sg:city":"Tilburg",
    "sg:orig_category":"Autokeuringen",
    "sg:phone":"+31 13 583 5353",
    "sg:postcode":"5015 BB",
    "sg:province":"Noord-Brabant",
    "wof:name":"Autotaalglas",
    "wof:placetype":"venue"
},
  "geometry": {"coordinates":[5.1107192039,51.569519043],"type":"Point"}
}