{
  "type": "Feature",
  "properties": {
    "addr:full":"Apollowg 18 Leeuwarden Friesland 8938 AT",
    "addr:housenumber":"18",
    "addr:postcode":"8938",
    "addr:street":"Apollowg",
    "iso:country":"NL",
    "sg:address":"Apollowg 18",
    "sg:city":"Leeuwarden",
    "sg:orig_category":"Verf En Lak - Fabrieken En Groothandel",
    "sg:phone":"+31 58 213 6487",
    "sg:postcode":"8938 AT",
    "sg:province":"Friesland",
    "wof:name":"Friesche Olie En Verfhdl Bv",
    "wof:placetype":"venue"
},
  "geometry": {"coordinates":[5.851904,53.200809],"type":"Point"}
}