{
  "type": "Feature",
  "properties": {
    "addr:full":"Callenburgstr 19A Vlaardingen South Holland 3134 GA",
    "addr:housenumber":"19a",
    "addr:postcode":"3134 ga",
    "addr:street":"Callenburgstr",
    "iso:country":"NL",
    "sg:address":"Callenburgstr 19A",
    "sg:city":"Vlaardingen",
    "sg:orig_category":"Grafisch Ontwerpers",
    "sg:phone":"+31 10 435 6758",
    "sg:postcode":"3134 GA",
    "sg:province":"South Holland",
    "wof:name":"Jonge, Ernst De",
    "wof:placetype":"venue"
},
  "geometry": {"coordinates":[4.348868,51.909584],"type":"Point"}
}