{
  "type": "Feature",
  "properties": {
    "addr:full":"Grote Beer 1 Hoorn Nh North Holland 1622 ES",
    "addr:housenumber":"1",
    "addr:postcode":"1622 es",
    "addr:street":"Grote Beer;Nh North",
    "iso:country":"NL",
    "sg:address":"Grote Beer 1",
    "sg:city":"Hoorn Nh",
    "sg:classifiers":[
        {
            "category":"Education",
            "subcategory":"Preschool",
            "type":"Public Place"
        }
    ],
    "sg:phone":"+31 229 216 084",
    "sg:postcode":"1622 ES",
    "sg:province":"North Holland",
    "sg:tags":[
        "kleuteronderwijs",
        "basis-"
    ],
    "wof:name":"Ichthusschool",
    "wof:placetype":"venue"
},
  "geometry": {"coordinates":[5.05207,52.642399],"type":"Point"}
}