{
  "type": "Feature",
  "properties": {
    "addr:full":"J Mauritspln 24 Overveen North Holland 2051 LR",
    "addr:housenumber":"24",
    "addr:postcode":"2051 lr",
    "iso:country":"NL",
    "sg:address":"J Mauritspln 24",
    "sg:city":"Overveen",
    "sg:orig_category":"Juridische Adviseurs",
    "sg:phone":"+31 23 526 4449",
    "sg:postcode":"2051 LR",
    "sg:province":"North Holland",
    "wof:name":"Baas, Letizia M",
    "wof:placetype":"venue"
},
  "geometry": {"coordinates":[4.613943,52.393085],"type":"Point"}
}