{
  "type": "Feature",
  "properties": {
    "addr:full":"Sluisstraat 29 Geldrop North Brabant 5666 AA",
    "addr:housenumber":"29",
    "addr:postcode":"5666 aa",
    "addr:street":"Sluisstraat",
    "iso:country":"NL",
    "sg:address":"Sluisstraat 29",
    "sg:city":"Geldrop",
    "sg:orig_category":"Kappers",
    "sg:phone":"+31 40 286 2723",
    "sg:postcode":"5666 AA",
    "sg:province":"North Brabant",
    "wof:name":"Kapsalon Carla",
    "wof:placetype":"venue"
},
  "geometry": {"coordinates":[5.5674519539,51.4222373962],"type":"Point"}
}