{
  "type": "Feature",
  "properties": {
    "iso:country":"NL",
    "sg:address":"Hanzewg 12",
    "sg:city":"Almere",
    "sg:orig_category":"Postorderbedrijven",
    "sg:phone":"+31 36 529 6369",
    "sg:postcode":"1335 SV",
    "sg:province":"Flevoland",
    "sg:website":"http://www.coolgoodies.com",
    "wof:name":"Coolgoodies",
    "wof:placetype":"venue"
},
  "geometry": {"coordinates":[5.289775,52.408508],"type":"Point"}
}