{
  "type": "Feature",
  "properties": {
    "addr:full":"Oude Provincia Wg 77A Hapert Noord-Brabant 5527 BN",
    "addr:housenumber":"77a",
    "addr:postcode":"5527 bn",
    "addr:street":"Oude;Wg",
    "iso:country":"NL",
    "sg:address":"Oude Provincia Wg 77A",
    "sg:city":"Hapert",
    "sg:orig_category":"Artsen - Huisartsen",
    "sg:phone":"+31 497 331 010",
    "sg:postcode":"5527 BN",
    "sg:province":"Noord-Brabant",
    "wof:name":"Barneveld En H Vissers, J Van",
    "wof:placetype":"venue"
},
  "geometry": {"coordinates":[5.246116,51.37162],"type":"Point"}
}