{
  "type": "Feature",
  "properties": {
    "addr:full":"Ir J P Van Muijlwijkstr 68C Arnhem Gelderland 6828 BT",
    "addr:housenumber":"68c",
    "addr:postcode":"6828 bt",
    "addr:street":"Ir J P Van Muijlwijkstr",
    "iso:country":"NL",
    "sg:address":"Ir J P Van Muijlwijkstr 68C",
    "sg:city":"Arnhem",
    "sg:orig_category":"Meubelzaken, Woning- And Keukeninrichting",
    "sg:phone":"+31 26 445 5042",
    "sg:postcode":"6828 BT",
    "sg:province":"Gelderland",
    "sg:website":"http://www.aqua-comfort.nl",
    "wof:name":"Aquacomfort",
    "wof:placetype":"venue"
},
  "geometry": {"coordinates":[5.915827,51.984402],"type":"Point"}
}