{
  "type": "Feature",
  "properties": {
    "addr:full":"Oude Ryksstrwg 9 Twello Gelderland 7391 MA",
    "addr:housenumber":"9",
    "addr:postcode":"7391 ma",
    "addr:street":"Oude Ryksstrwg;Gelderland",
    "iso:country":"NL",
    "sg:address":"Oude Ryksstrwg 9",
    "sg:city":"Twello",
    "sg:orig_category":"Webdesign Bureaus",
    "sg:phone":"+31 571 272 790",
    "sg:postcode":"7391 MA",
    "sg:province":"Gelderland",
    "sg:website":"http://www.andersites.nl",
    "wof:name":"Andersites",
    "wof:placetype":"venue"
},
  "geometry": {"coordinates":[6.0932760239,52.238822937],"type":"Point"}
}