{
  "type": "Feature",
  "properties": {
    "iso:country":"NL",
    "sg:address":"Lyndonk 128",
    "sg:city":"Oosterhout Nb",
    "sg:orig_category":"Adviesbureaus Automatisering",
    "sg:phone":"+31 162 470 067",
    "sg:postcode":"4907 XG",
    "sg:province":"North Brabant",
    "sg:website":"http://www.zoeteweijconsulting.nl",
    "wof:name":"Zoeteweij Consultants",
    "wof:placetype":"venue"
},
  "geometry": {"coordinates":[4.86778,51.656559],"type":"Point"}
}