{
  "type": "Feature",
  "properties": {
    "addr:full":"Kromme Nieuwegracht 12 Utrecht Utrecht 3512 HG",
    "addr:housenumber":"12",
    "addr:postcode":"3512 hg",
    "addr:street":"Kromme Nieuwegracht",
    "iso:country":"NL",
    "sg:address":"Kromme Nieuwegracht 12",
    "sg:city":"Utrecht",
    "sg:orig_category":"Antiquiteiten - Restauratie",
    "sg:phone":"+31 30 230 2711",
    "sg:postcode":"3512 HG",
    "sg:province":"Utrecht",
    "wof:name":"Adriaan Van Dam",
    "wof:placetype":"venue"
},
  "geometry": {"coordinates":[5.123877,52.092449],"type":"Point"}
}