{
  "type": "Feature",
  "properties": {
    "addr:full":"Rypmakan 6 Harkstede Groningen 9617 CA",
    "addr:housenumber":"6",
    "addr:postcode":"9617 ca",
    "addr:street":"Rypmakan",
    "iso:country":"NL",
    "sg:address":"Rypmakan 6",
    "sg:city":"Harkstede",
    "sg:orig_category":"Metaalbewerking",
    "sg:phone":"+31 50 404 2073",
    "sg:postcode":"9617 CA",
    "sg:province":"Groningen",
    "wof:name":"Folkersma Bv",
    "wof:placetype":"venue"
},
  "geometry": {"coordinates":[6.702841,53.213451],"type":"Point"}
}