{
  "type": "Feature",
  "properties": {
    "addr:full":"Drachtsterweg 58 Opende Groningen 9865 VJ",
    "addr:housenumber":"58",
    "addr:postcode":"9865 vj",
    "addr:street":"Drachtsterweg",
    "iso:country":"NL",
    "sg:address":"Drachtsterweg 58",
    "sg:city":"Opende",
    "sg:classifiers":[
        {
            "category":"Professional",
            "subcategory":"Accounting & Tax Preparation",
            "type":"Services"
        }
    ],
    "sg:phone":"+31 594 659 882",
    "sg:postcode":"9865 VJ",
    "sg:province":"Groningen",
    "sg:tags":[
        "accountant"
    ],
    "wof:name":"Administratiekantoor Foppema",
    "wof:placetype":"venue"
},
  "geometry": {"coordinates":[6.190442,53.157822],"type":"Point"}
}