{
  "type": "Feature",
  "properties": {
    "addr:full":"Panoramaweg 13 Puth Limburg 6155 LZ",
    "addr:housenumber":"13",
    "addr:postcode":"6155 lz",
    "addr:street":"Panoramaweg",
    "iso:country":"NL",
    "sg:address":"Panoramaweg 13",
    "sg:city":"Puth",
    "sg:orig_category":"Vertaal- And Tolkenbureaus",
    "sg:phone":"+31 46 443 1955",
    "sg:postcode":"6155 LZ",
    "sg:province":"Limburg",
    "wof:name":"Krans-Romanszky",
    "wof:placetype":"venue"
},
  "geometry": {"coordinates":[12.73821,42.02174],"type":"Point"}
}