{
  "type": "Feature",
  "properties": {
    "addr:full":"Mahlerstr 27 Vlaardingen Zuid-Holland 3131 SG",
    "addr:housenumber":"27",
    "addr:postcode":"3131 sg",
    "addr:street":"Mahlerstr",
    "iso:country":"NL",
    "sg:address":"Mahlerstr 27",
    "sg:city":"Vlaardingen",
    "sg:orig_category":"Kappers",
    "sg:phone":"+31 10 434 3977",
    "sg:postcode":"3131 SG",
    "sg:province":"Zuid-Holland",
    "wof:name":"Selma",
    "wof:placetype":"venue"
},
  "geometry": {"coordinates":[4.335433,51.904999],"type":"Point"}
}