{
  "type": "Feature",
  "properties": {
    "addr:full":"Ondersloot 1-1A Stegeren Overijssel 7737 PD",
    "addr:housenumber":"1-1a",
    "addr:postcode":"7737 pd",
    "addr:street":"Ondersloot",
    "iso:country":"NL",
    "sg:address":"Ondersloot 1-1A",
    "sg:city":"Stegeren",
    "sg:orig_category":"Hoefdierhouderijen",
    "sg:phone":"+31 523 638 594",
    "sg:postcode":"7737 PD",
    "sg:province":"Overijssel",
    "wof:name":"Magic Corner",
    "wof:placetype":"venue"
},
  "geometry": {"coordinates":[6.483644,52.557816],"type":"Point"}
}