{
  "type": "Feature",
  "properties": {
    "addr:full":"Industriewg 5 Meppel Drenthe 7944 HT",
    "addr:housenumber":"5",
    "addr:postcode":"7944 ht",
    "addr:street":"Industriewg",
    "iso:country":"NL",
    "sg:address":"Industriewg 5",
    "sg:city":"Meppel",
    "sg:orig_category":"Boekbinderijen",
    "sg:phone":"+31 522 255 868",
    "sg:postcode":"7944 HT",
    "sg:province":"Drenthe",
    "wof:name":"Emb? Bv",
    "wof:placetype":"venue"
},
  "geometry": {"coordinates":[6.181302,52.693268],"type":"Point"}
}