{
  "type": "Feature",
  "properties": {
    "addr:full":"Gebroeders Wienerstraat 7 Venlo Limburg 5913 XN",
    "addr:housenumber":"7",
    "addr:postcode":"5913 xn",
    "addr:street":"Gebroeders Wienerstraat",
    "iso:country":"NL",
    "sg:address":"Gebroeders Wienerstraat 7",
    "sg:city":"Venlo",
    "sg:classifiers":[
        {
            "category":"Fast Food",
            "type":"Food & Drink"
        }
    ],
    "sg:phone":"+31 77 354 4753",
    "sg:postcode":"5913 XN",
    "sg:province":"Limburg",
    "sg:tags":[
        "afhaal",
        "restaurant"
    ],
    "wof:name":"Friture Van Boekhold",
    "wof:placetype":"venue"
},
  "geometry": {"coordinates":[6.188325,51.377182],"type":"Point"}
}