{
  "type": "Feature",
  "properties": {
    "addr:full":"Rokkeveenseweg 2 Zoetermeer South Holland 2712 XZ",
    "addr:housenumber":"2",
    "addr:postcode":"2712 xz",
    "addr:street":"Rokkeveenseweg",
    "iso:country":"NL",
    "sg:address":"Rokkeveenseweg 2",
    "sg:city":"Zoetermeer",
    "sg:classifiers":[
        {
            "category":"Fast Food",
            "type":"Food & Drink"
        }
    ],
    "sg:phone":"+31 79 331 5231",
    "sg:postcode":"2712 XZ",
    "sg:province":"South Holland",
    "sg:tags":[
        "afhaal",
        "restaurant"
    ],
    "wof:name":"Firma Westhoek En Zonen",
    "wof:placetype":"venue"
},
  "geometry": {"coordinates":[4.506537,52.049606],"type":"Point"}
}