{
  "type": "Feature",
  "properties": {
    "addr:full":"Leeuwerkstr 22 Oud-Turnhout B-23 60",
    "addr:housenumber":"22;b-23 60",
    "addr:street":"Leeuwerkstr",
    "iso:country":"NL",
    "sg:address":"Leeuwerkstr 22",
    "sg:city":"Oud-Turnhout",
    "sg:classifiers":[
        {
            "category":"Animal Shelter",
            "type":"Public Place"
        }
    ],
    "sg:phone":"+31 475 540 952",
    "sg:postcode":"B-23 60",
    "sg:tags":[
        "kennel"
    ],
    "sg:website":"http://www.oosthof.net",
    "wof:name":"Corstiaensen Rashonden",
    "wof:placetype":"venue"
},
  "geometry": {"coordinates":[4.98263,51.317799],"type":"Point"}
}