{
  "type": "Feature",
  "properties": {
    "addr:full":"Westerparallelstraat 72 Stadskanaal Groningen 9501 GX",
    "addr:housenumber":"72",
    "addr:postcode":"9501 gx",
    "addr:street":"Westerparallelstraat",
    "iso:country":"NL",
    "sg:address":"Westerparallelstraat 72",
    "sg:city":"Stadskanaal",
    "sg:orig_category":"Begrafenisondernemers",
    "sg:phone":"+31 599 612 482",
    "sg:postcode":"9501 GX",
    "sg:province":"Groningen",
    "wof:name":"Begrafenis En Crematieverzorging J Stout",
    "wof:placetype":"venue"
},
  "geometry": {"coordinates":[6.925859,53.005829],"type":"Point"}
}