{
  "type": "Feature",
  "properties": {
    "iso:country":"NL",
    "sg:address":"Nordhornsestraat 234",
    "sg:city":"Denekamp",
    "sg:orig_category":"Werving And Selectie Van Tijdelijk Personeel And Uitzendkantoren",
    "sg:phone":"+31 541 517 071",
    "sg:postcode":"7591 NM",
    "sg:province":"Overijssel",
    "wof:name":"Emtes Werkgevers Bv",
    "wof:placetype":"venue"
},
  "geometry": {"coordinates":[7.0348200798,52.4025611877],"type":"Point"}
}