{
  "type": "Feature",
  "properties": {
    "addr:full":"Stadhouderspln 2535 Wassenaar Zuid-Holland 2241 EA",
    "addr:postcode":"2535 wassenaar;2241 ea",
    "iso:country":"NL",
    "sg:address":"Stadhouderspln 2535",
    "sg:city":"Wassenaar",
    "sg:orig_category":"Apotheken",
    "sg:phone":"+31 70 512 1010",
    "sg:postcode":"2241 EA",
    "sg:province":"Zuid-Holland",
    "sg:website":"http://www.wassenaarseapotheek.nl",
    "wof:name":"Wassenaarse Kring",
    "wof:placetype":"venue"
},
  "geometry": {"coordinates":[4.40353,52.144772],"type":"Point"}
}