{
  "type": "Feature",
  "properties": {
    "iso:country":"NL",
    "sg:address":"Broeksewg 40",
    "sg:city":"Meerkerk",
    "sg:orig_category":"Autorijscholen",
    "sg:phone":"+31 183 352 520",
    "sg:postcode":"4231 VG",
    "sg:province":"South Holland",
    "wof:name":"Brakband",
    "wof:placetype":"venue"
},
  "geometry": {"coordinates":[4.985132,51.93206],"type":"Point"}
}