{
  "type": "Feature",
  "properties": {
    "addr:full":"Postbus 456 Terneuzen Zeeland 4530 AL",
    "addr:housenumber":"456",
    "addr:postcode":"4530 al",
    "addr:street":"Postbus",
    "iso:country":"NL",
    "sg:address":"Postbus 456",
    "sg:city":"Terneuzen",
    "sg:orig_category":"Diverse Opleidingen And Onderwijs",
    "sg:phone":"+31 115 630 188",
    "sg:postcode":"4530 AL",
    "sg:province":"Zeeland",
    "wof:name":"Dins Opleidingen",
    "wof:placetype":"venue"
},
  "geometry": {"coordinates":[3.827559,51.338146],"type":"Point"}
}