{
  "type": "Feature",
  "properties": {
    "addr:full":"Printerweg 1 Amersfoort Utrecht 3821 AP",
    "addr:housenumber":"1",
    "addr:postcode":"3821 ap",
    "addr:street":"Printerweg",
    "iso:country":"NL",
    "sg:address":"Printerweg 1",
    "sg:city":"Amersfoort",
    "sg:orig_category":"Bouwmaterialen Gh",
    "sg:phone":"+31 33 455 6044",
    "sg:postcode":"3821 AP",
    "sg:province":"Utrecht",
    "wof:name":"Keramag Bv",
    "wof:placetype":"venue"
},
  "geometry": {"coordinates":[5.408367,52.175632],"type":"Point"}
}