{
  "type": "Feature",
  "properties": {
    "iso:country":"NL",
    "sg:address":"De Grent 16",
    "sg:city":"Noordwyk Zh",
    "sg:orig_category":"Discotheken",
    "sg:phone":"+31 71 361 5407",
    "sg:postcode":"2202 EL",
    "sg:province":"South Holland",
    "wof:name":"Zeepaardje, 'T",
    "wof:placetype":"venue"
},
  "geometry": {"coordinates":[4.429994,52.242554],"type":"Point"}
}