{
  "type": "Feature",
  "properties": {
    "addr:full":"Bolstoen 5A Amsterdam North Holland 1046 AS",
    "addr:housenumber":"5a",
    "addr:postcode":"1046 as",
    "addr:street":"Bolstoen",
    "iso:country":"NL",
    "sg:address":"Bolstoen 5A",
    "sg:city":"Amsterdam",
    "sg:classifiers":[
        {
            "category":"Retail",
            "subcategory":"Auto Repair",
            "type":"Services"
        }
    ],
    "sg:phone":"+31 20 411 8844",
    "sg:postcode":"1046 AS",
    "sg:province":"North Holland",
    "sg:tags":[
        "garage"
    ],
    "wof:name":"Geesink Bv",
    "wof:placetype":"venue"
},
  "geometry": {"coordinates":[4.788293,52.390343],"type":"Point"}
}