{
  "type": "Feature",
  "properties": {
    "addr:full":"Stratumsedijk 38 Eindhoven Noord-Brabant 5611 NE",
    "addr:housenumber":"38",
    "addr:postcode":"5611 ne",
    "addr:street":"Stratumsedijk",
    "iso:country":"NL",
    "sg:address":"Stratumsedijk 38",
    "sg:city":"Eindhoven",
    "sg:orig_category":"Werving And Selectie Van Tijdelijk Personeel And Uitzendkantoren",
    "sg:phone":"+31 40 212 8889",
    "sg:postcode":"5611 NE",
    "sg:province":"Noord-Brabant",
    "wof:name":"Techno Job",
    "wof:placetype":"venue"
},
  "geometry": {"coordinates":[5.4852108955,51.4310874939],"type":"Point"}
}