{
  "type": "Feature",
  "properties": {
    "addr:full":"Nw Tielsewg 69B Tiel Gelderland 4001 JT",
    "addr:housenumber":"69b",
    "addr:postcode":"4001 jt",
    "addr:street":"Gelderland",
    "iso:country":"NL",
    "sg:address":"Nw Tielsewg 69B",
    "sg:city":"Tiel",
    "sg:orig_category":"Verf En Lak",
    "sg:phone":"+31 344 617 585",
    "sg:postcode":"4001 JT",
    "sg:province":"Gelderland",
    "wof:name":"Wijk Bv, Henk Van",
    "wof:placetype":"venue"
},
  "geometry": {"coordinates":[5.429184,51.882309],"type":"Point"}
}