{
  "type": "Feature",
  "properties": {
    "addr:full":"Rottekd 256 Bergschenhoek Zuid-Holland 2661 JX",
    "addr:housenumber":"256",
    "addr:postcode":"2661 jx",
    "iso:country":"NL",
    "sg:address":"Rottekd 256",
    "sg:city":"Bergschenhoek",
    "sg:orig_category":"Behangers",
    "sg:phone":"+31 10 521 6358",
    "sg:postcode":"2661 JX",
    "sg:province":"Zuid-Holland",
    "wof:name":"Verduyn, W J",
    "wof:placetype":"venue"
},
  "geometry": {"coordinates":[4.500133,51.989536],"type":"Point"}
}