{
  "type": "Feature",
  "properties": {
    "addr:full":"Beemstraat 8 Gameren Gelderland 5311 AC",
    "addr:housenumber":"8",
    "addr:postcode":"5311 ac",
    "addr:street":"Beemstraat;Gelderland",
    "iso:country":"NL",
    "sg:address":"Beemstraat 8",
    "sg:city":"Gameren",
    "sg:orig_category":"Metaalwerken",
    "sg:phone":"+31 418 561 592",
    "sg:postcode":"5311 AC",
    "sg:province":"Gelderland",
    "wof:name":"Van Willigen Vof",
    "wof:placetype":"venue"
},
  "geometry": {"coordinates":[5.208488,51.803055],"type":"Point"}
}