{
  "type": "Feature",
  "properties": {
    "addr:full":"Heistraat 74 Kerkrade Limburg 6467 LR",
    "addr:housenumber":"74",
    "addr:postcode":"6467 lr",
    "addr:street":"Heistraat",
    "iso:country":"NL",
    "sg:address":"Heistraat 74",
    "sg:city":"Kerkrade",
    "sg:orig_category":"Kunst And Kunstenaarsbenodigdheden",
    "sg:phone":"+31 45 541 3541",
    "sg:postcode":"6467 LR",
    "sg:province":"Limburg",
    "wof:name":"Inlijsterij J. Last",
    "wof:placetype":"venue"
},
  "geometry": {"coordinates":[6.021088,50.870502],"type":"Point"}
}