{
  "type": "Feature",
  "properties": {
    "iso:country":"NL",
    "sg:address":"Dalwg 11",
    "sg:city":"Baarn",
    "sg:orig_category":"Peuterspeelzalen",
    "sg:phone":"+31 35 542 9699",
    "sg:postcode":"3741 AT",
    "sg:province":"Utrecht",
    "wof:name":"Dribbel",
    "wof:placetype":"venue"
},
  "geometry": {"coordinates":[5.289403,52.214169],"type":"Point"}
}