{
  "type": "Feature",
  "properties": {
    "addr:full":"Badmeester Schenkpad 8 Zeist Utrecht 3705 GK",
    "addr:housenumber":"8",
    "addr:postcode":"3705 gk",
    "addr:street":"Badmeester Schenkpad",
    "iso:country":"NL",
    "sg:address":"Badmeester Schenkpad 8",
    "sg:city":"Zeist",
    "sg:orig_category":"Fitnesscentra",
    "sg:phone":"+31 30 699 0192",
    "sg:postcode":"3705 GK",
    "sg:province":"Utrecht",
    "wof:name":"Zwembad Dijnselburg Zeist",
    "wof:placetype":"venue"
},
  "geometry": {"coordinates":[5.238694,52.105515],"type":"Point"}
}