{
  "type": "Feature",
  "properties": {
    "iso:country":"NL",
    "sg:address":"Schepenstr 31A",
    "sg:city":"Rotterdam",
    "sg:orig_category":"Groepsaccommodaties",
    "sg:phone":"+31 10 404 7723",
    "sg:postcode":"3039 NB",
    "sg:province":"Zuid-Holland",
    "wof:name":"Singel Kamphuis, De",
    "wof:placetype":"venue"
},
  "geometry": {"coordinates":[4.466225,51.930492],"type":"Point"}
}