{
  "type": "Feature",
  "properties": {
    "addr:full":"Dorpsstr 19 Gulpen Limburg 6271 BK",
    "addr:housenumber":"19",
    "addr:postcode":"6271 bk",
    "addr:street":"Dorpsstr",
    "iso:country":"NL",
    "sg:address":"Dorpsstr 19",
    "sg:city":"Gulpen",
    "sg:orig_category":"Discotheken",
    "sg:phone":"+31 43 450 1151",
    "sg:postcode":"6271 BK",
    "sg:province":"Limburg",
    "wof:name":"Life Palace",
    "wof:placetype":"venue"
},
  "geometry": {"coordinates":[5.891152,50.815971],"type":"Point"}
}