{
  "type": "Feature",
  "properties": {
    "addr:full":"Jordaan 31 Laren Nh North Holland 1251 PB",
    "addr:housenumber":"31",
    "addr:postcode":"1251 pb",
    "addr:street":"Jordaan;Nh North",
    "iso:country":"NL",
    "sg:address":"Jordaan 31",
    "sg:city":"Laren Nh",
    "sg:classifiers":[
        {
            "category":"Shopping",
            "subcategory":"Gifts & Souvenirs",
            "type":"Retail Goods"
        }
    ],
    "sg:phone":"+31 35 531 6266",
    "sg:postcode":"1251 PB",
    "sg:province":"North Holland",
    "sg:tags":[
        "geschenken"
    ],
    "wof:name":"Karen'S",
    "wof:placetype":"venue"
},
  "geometry": {"coordinates":[5.236819,52.254425],"type":"Point"}
}