{
  "type": "Feature",
  "properties": {
    "addr:full":"Zuiderdiep 403 Valthermond Provincie Drenthe 7876 AW",
    "addr:housenumber":"403",
    "addr:postcode":"7876 aw",
    "addr:street":"Zuiderdiep;Provincie Drenthe",
    "iso:country":"NL",
    "sg:address":"Zuiderdiep 403",
    "sg:city":"Valthermond",
    "sg:orig_category":"Kappers",
    "sg:phone":"+31 599 662 693",
    "sg:postcode":"7876 AW",
    "sg:province":"Provincie Drenthe",
    "wof:name":"Kapsalon Anet",
    "wof:placetype":"venue"
},
  "geometry": {"coordinates":[6.9781241417,52.8886375427],"type":"Point"}
}