{
  "type": "Feature",
  "properties": {
    "addr:full":"Boulev Heuvelink 37 Arnhem Gelderland 6828 KH",
    "addr:housenumber":"37",
    "addr:postcode":"6828 kh",
    "addr:street":"Boulev Heuvelink",
    "iso:country":"NL",
    "sg:address":"Boulev Heuvelink 37",
    "sg:city":"Arnhem",
    "sg:orig_category":"Parketvloeren",
    "sg:phone":"+31 6 21805632",
    "sg:postcode":"6828 KH",
    "sg:province":"Gelderland",
    "sg:website":"http://www.maasparket.nl",
    "wof:name":"Maas",
    "wof:placetype":"venue"
},
  "geometry": {"coordinates":[5.919084,51.978401],"type":"Point"}
}