{
  "type": "Feature",
  "properties": {
    "addr:full":"Vaartveld 19 Roosendaal Noord-Brabant 4704 SE",
    "addr:housenumber":"19",
    "addr:postcode":"4704 se",
    "addr:street":"Vaartveld",
    "iso:country":"NL",
    "sg:address":"Vaartveld 19",
    "sg:city":"Roosendaal",
    "sg:orig_category":"Fietsen - Fabrieken En Groothandel",
    "sg:phone":"+31 165 564 241",
    "sg:postcode":"4704 SE",
    "sg:province":"Noord-Brabant",
    "wof:name":"Card Sports",
    "wof:placetype":"venue"
},
  "geometry": {"coordinates":[4.467751,51.557362],"type":"Point"}
}