{
  "type": "Feature",
  "properties": {
    "iso:country":"NL",
    "sg:address":"Rijksweg 45",
    "sg:city":"Gronsveld",
    "sg:orig_category":"Handelsbemiddeling Textiel And Lederwaren",
    "sg:phone":"+31 43 408 2145",
    "sg:postcode":"6247 AA",
    "sg:province":"Limburg",
    "wof:name":"Slijpen Textiles Bv",
    "wof:placetype":"venue"
},
  "geometry": {"coordinates":[5.730324,50.812969],"type":"Point"}
}