{
  "type": "Feature",
  "properties": {
    "addr:full":"Kleine Bergerweg 15 Sint Odilienberg Limburg 6077 PC",
    "addr:housenumber":"15",
    "addr:postcode":"6077 pc",
    "addr:street":"Kleine Bergerweg;Limburg",
    "iso:country":"NL",
    "sg:address":"Kleine Bergerweg 15",
    "sg:city":"Sint Odilienberg",
    "sg:orig_category":"Granen, Zaden And Diervoeders Gh",
    "sg:phone":"+31 475 534 153",
    "sg:postcode":"6077 PC",
    "sg:province":"Limburg",
    "wof:name":"Selectiebedrijf Mortelshof",
    "wof:placetype":"venue"
},
  "geometry": {"coordinates":[5.976481,51.147457],"type":"Point"}
}