{
  "type": "Feature",
  "properties": {
    "addr:full":"Hoogstraat 46 Hasselt NL.08 8061 HD",
    "addr:housenumber":"46",
    "addr:postcode":"8061",
    "addr:street":"Hoogstraat;Hd",
    "iso:country":"NL",
    "sg:address":"Hoogstraat 46",
    "sg:city":"Hasselt",
    "sg:orig_category":"Autokeuringen",
    "sg:phone":"+31 38 477 4178",
    "sg:postcode":"8061 HD",
    "sg:province":"NL.08",
    "wof:name":"Revisiebedrijf Henk Melenhorst",
    "wof:placetype":"venue"
},
  "geometry": {"coordinates":[6.088488,52.592396],"type":"Point"}
}