{
  "type": "Feature",
  "properties": {
    "addr:full":"Geerdinkhof 464 Amsterdam Zuidoost North Holland 1103 RG",
    "addr:housenumber":"464",
    "addr:postcode":"1103 rg",
    "addr:street":"Geerdinkhof",
    "iso:country":"NL",
    "sg:address":"Geerdinkhof 464",
    "sg:city":"Amsterdam Zuidoost",
    "sg:orig_category":"Bedrijfsopleidingen",
    "sg:phone":"+31 20 416 0352",
    "sg:postcode":"1103 RG",
    "sg:province":"North Holland",
    "wof:name":"Savonije Bv",
    "wof:placetype":"venue"
},
  "geometry": {"coordinates":[4.980314,52.328758],"type":"Point"}
}