{
  "type": "Feature",
  "properties": {
    "addr:full":"Passage 5 Geleen Limburg 6161 ER",
    "addr:housenumber":"5",
    "addr:postcode":"6161 er",
    "addr:street":"Passage",
    "iso:country":"NL",
    "sg:address":"Passage 5",
    "sg:city":"Geleen",
    "sg:orig_category":"Opticiens",
    "sg:phone":"+31 46 474 9401",
    "sg:postcode":"6161 ER",
    "sg:province":"Limburg",
    "wof:name":"Brederode, Optiek Van",
    "wof:placetype":"venue"
},
  "geometry": {"coordinates":[5.8296971321,50.9693450928],"type":"Point"}
}