{
  "type": "Feature",
  "properties": {
    "iso:country":"NL",
    "sg:address":"Wagnerln 2",
    "sg:city":"Arnhem",
    "sg:orig_category":"Kinderopvang",
    "sg:phone":"+31 26 443 8627",
    "sg:postcode":"6815 AG",
    "sg:province":"Gelderland",
    "wof:name":"Brummel, De",
    "wof:placetype":"venue"
},
  "geometry": {"coordinates":[5.909601,51.998894],"type":"Point"}
}