{
  "type": "Feature",
  "properties": {
    "iso:country":"NL",
    "sg:address":"18 Septemberpln 3",
    "sg:city":"Eindhoven",
    "sg:orig_category":"Bijouterie?n",
    "sg:phone":"+31 40 243 1945",
    "sg:postcode":"5611 AL",
    "sg:province":"North Brabant",
    "wof:name":"Amie",
    "wof:placetype":"venue"
},
  "geometry": {"coordinates":[5.477793,51.441345],"type":"Point"}
}