{
  "type": "Feature",
  "properties": {
    "addr:full":"Op E Wal 12 Warns Friesland 8721 GJ",
    "addr:housenumber":"12",
    "addr:postcode":"8721 gj",
    "addr:street":"Op E Wal",
    "iso:country":"NL",
    "sg:address":"Op E Wal 12",
    "sg:city":"Warns",
    "sg:orig_category":"Jachthavens - Jachtwerven",
    "sg:phone":"+31 514 681 623",
    "sg:postcode":"8721 GJ",
    "sg:province":"Friesland",
    "sg:website":"http://www.de-vrijheid.nl",
    "wof:name":"Vrijheid Jachthaven / Jachtwerf, De",
    "wof:placetype":"venue"
},
  "geometry": {"coordinates":[-83.884407,34.997856],"type":"Point"}
}