{
  "type": "Feature",
  "properties": {
    "addr:full":"Handelsplein 5 Amstelveen Noord-Holland 1181 WC",
    "addr:housenumber":"5",
    "addr:postcode":"1181 wc",
    "addr:street":"Handelsplein",
    "iso:country":"NL",
    "sg:address":"Handelsplein 5",
    "sg:city":"Amstelveen",
    "sg:orig_category":"Parkeergarages",
    "sg:phone":"+31 20 453 9919",
    "sg:postcode":"1181 WC",
    "sg:province":"Noord-Holland",
    "wof:name":"Anwb Parking Amstelveen",
    "wof:placetype":"venue"
},
  "geometry": {"coordinates":[4.865721,52.301067],"type":"Point"}
}