{
  "type": "Feature",
  "properties": {
    "addr:full":"Zwaluwtong 7 Monnickendam Noord-Holland 1141 KN",
    "addr:housenumber":"7",
    "addr:postcode":"1141 kn",
    "addr:street":"Zwaluwtong",
    "iso:country":"NL",
    "sg:address":"Zwaluwtong 7",
    "sg:city":"Monnickendam",
    "sg:orig_category":"Adviesbureaus Marketing",
    "sg:phone":"+31 299 654 937",
    "sg:postcode":"1141 KN",
    "sg:province":"Noord-Holland",
    "wof:name":"Dijk, Van",
    "wof:placetype":"venue"
},
  "geometry": {"coordinates":[5.040088,52.446987],"type":"Point"}
}