{
  "type": "Feature",
  "properties": {
    "addr:full":"Minervum 73188 Breda North Brabant 4817 ZH",
    "addr:housenumber":"73188",
    "addr:postcode":"4817 zh",
    "addr:street":"Minervum",
    "iso:country":"NL",
    "sg:address":"Minervum 73188",
    "sg:city":"Breda",
    "sg:orig_category":"Meubelzaken, Woning- And Keukeninrichting",
    "sg:phone":"+31 76 572 8000",
    "sg:postcode":"4817 ZH",
    "sg:province":"North Brabant",
    "wof:name":"Double You Meubelcollectie Bv",
    "wof:placetype":"venue"
},
  "geometry": {"coordinates":[4.83472,51.589958],"type":"Point"}
}