{
  "type": "Feature",
  "properties": {
    "addr:full":"Beyert 33 Naarden North Holland 1411 RA",
    "addr:housenumber":"33",
    "addr:postcode":"1411 ra",
    "addr:street":"Beyert",
    "iso:country":"NL",
    "sg:address":"Beyert 33",
    "sg:city":"Naarden",
    "sg:orig_category":"Belastingconsulenten/ Belastingadviseurs",
    "sg:phone":"+31 35 694 4746",
    "sg:postcode":"1411 RA",
    "sg:province":"North Holland",
    "wof:name":"Vesting, De",
    "wof:placetype":"venue"
},
  "geometry": {"coordinates":[5.161848,52.296371],"type":"Point"}
}