{
  "type": "Feature",
  "properties": {
    "addr:full":"Genenberg 1A St Michielsgestel North Brabant 5271 SC",
    "addr:housenumber":"1a",
    "addr:postcode":"5271 sc",
    "addr:street":"Genenberg;St Michielsgestel",
    "iso:country":"NL",
    "sg:address":"Genenberg 1A",
    "sg:city":"St Michielsgestel",
    "sg:orig_category":"Kunstbloemen En -Planten - Fabrieken En Groothandel",
    "sg:phone":"+31 73 551 5072",
    "sg:postcode":"5271 SC",
    "sg:province":"North Brabant",
    "wof:name":"Stampertje, 'T",
    "wof:placetype":"venue"
},
  "geometry": {"coordinates":[5.358342,51.6376],"type":"Point"}
}