{
  "type": "Feature",
  "properties": {
    "addr:full":"Hunenborglaan 182 Oldenzaal NL.08 7576 XE",
    "addr:housenumber":"182;nl.08",
    "addr:postcode":"7576 xe",
    "addr:street":"Hunenborglaan",
    "iso:country":"NL",
    "sg:address":"Hunenborglaan 182",
    "sg:city":"Oldenzaal",
    "sg:orig_category":"Kantoorartikelen",
    "sg:phone":"+31 541 534 930",
    "sg:postcode":"7576 XE",
    "sg:province":"NL.08",
    "wof:name":"J J M Schoenmaker",
    "wof:placetype":"venue"
},
  "geometry": {"coordinates":[6.9062871933,52.3171882629],"type":"Point"}
}