{
  "type": "Feature",
  "properties": {
    "addr:full":"Mechelaarstr 7 Oosterhout Nb Noord-Brabant 4903 RE",
    "addr:housenumber":"7",
    "addr:postcode":"4903 re",
    "addr:street":"Mechelaarstr",
    "iso:country":"NL",
    "sg:address":"Mechelaarstr 7",
    "sg:city":"Oosterhout Nb",
    "sg:orig_category":"Bouwelementenindustrie",
    "sg:phone":"+31 162 423 600",
    "sg:postcode":"4903 RE",
    "sg:province":"Noord-Brabant",
    "wof:name":"Zwart Bv",
    "wof:placetype":"venue"
},
  "geometry": {"coordinates":[4.878712,51.626457],"type":"Point"}
}