{
  "type": "Feature",
  "properties": {
    "addr:full":"Mathenesserln 173 Rotterdam Zuid-Holland 3014 HA",
    "addr:housenumber":"173",
    "addr:postcode":"3014 ha",
    "iso:country":"NL",
    "sg:address":"Mathenesserln 173",
    "sg:city":"Rotterdam",
    "sg:orig_category":"Verenigingen En Stichtingen",
    "sg:phone":"+31 10 436 5730",
    "sg:postcode":"3014 HA",
    "sg:province":"Zuid-Holland",
    "wof:name":"Jip, Sticht",
    "wof:placetype":"venue"
},
  "geometry": {"coordinates":[4.465365,51.9151],"type":"Point"}
}