{
  "type": "Feature",
  "properties": {
    "addr:full":"Lloydsweg 17 Veendam Groningen 9641 KJ",
    "addr:housenumber":"17",
    "addr:postcode":"9641 kj",
    "addr:street":"Lloydsweg",
    "iso:country":"NL",
    "sg:address":"Lloydsweg 17",
    "sg:city":"Veendam",
    "sg:orig_category":"Goederenvervoer Over De Weg",
    "sg:phone":"+31 598 657 911",
    "sg:postcode":"9641 KJ",
    "sg:province":"Groningen",
    "wof:name":"Vos Logistics Veendam Bv",
    "wof:placetype":"venue"
},
  "geometry": {"coordinates":[6.89189,53.108738],"type":"Point"}
}