{
  "type": "Feature",
  "properties": {
    "iso:country":"NL",
    "sg:address":"Bachstraat 39",
    "sg:city":"Leiden",
    "sg:orig_category":"Fotografische And Optische Artikelen Gh",
    "sg:phone":"+31 71 576 5201",
    "sg:postcode":"2324 GK",
    "sg:province":"Zuid-Holland",
    "wof:name":"Dr. J.C. Roskam",
    "wof:placetype":"venue"
},
  "geometry": {"coordinates":[4.47555,52.142502],"type":"Point"}
}