{
  "type": "Feature",
  "properties": {
    "addr:full":"Concourslaan 2 Dronten NL. 8252 GJ",
    "addr:housenumber":"2",
    "addr:postcode":"8252 gj",
    "addr:street":"Concourslaan;Nl.",
    "iso:country":"NL",
    "sg:address":"Concourslaan 2",
    "sg:city":"Dronten",
    "sg:classifiers":[
        {
            "category":"Education",
            "subcategory":"Preschool",
            "type":"Public Place"
        }
    ],
    "sg:phone":"+31 321 313 235",
    "sg:postcode":"8252 GJ",
    "sg:province":"NL.",
    "sg:tags":[
        "kleuteronderwijs",
        "basis-"
    ],
    "wof:name":"Prot Chr Basisschool Het Kompas",
    "wof:placetype":"venue"
},
  "geometry": {"coordinates":[5.706557,52.515434],"type":"Point"}
}