{
  "type": "Feature",
  "properties": {
    "addr:full":"Keizersveld 14 Venray Limburg 5803 AN",
    "addr:housenumber":"14",
    "addr:postcode":"5803 an",
    "addr:street":"Keizersveld",
    "iso:country":"NL",
    "sg:address":"Keizersveld 14",
    "sg:city":"Venray",
    "sg:orig_category":"Ventilatoren",
    "sg:phone":"+31 478 559 955",
    "sg:postcode":"5803 AN",
    "sg:province":"Limburg",
    "sg:website":"http://www.rotodyne.nl",
    "wof:name":"Rotodyne Bv",
    "wof:placetype":"venue"
},
  "geometry": {"coordinates":[5.99333,51.539581],"type":"Point"}
}