{
  "type": "Feature",
  "properties": {
    "addr:full":"Kloosterlaan 39 'S Hertogenbosch Noord-Brabant 5235 BA",
    "addr:housenumber":"39",
    "addr:postcode":"5235 ba",
    "addr:street":"Kloosterlaan;' S",
    "iso:country":"NL",
    "sg:address":"Kloosterlaan 39",
    "sg:city":"'S Hertogenbosch",
    "sg:orig_category":"Paramedische Behandelingen",
    "sg:phone":"+31 73 641 5673",
    "sg:postcode":"5235 BA",
    "sg:province":"Noord-Brabant",
    "wof:name":"C.M.Th. Kraan",
    "wof:placetype":"venue"
},
  "geometry": {"coordinates":[5.315576,51.725826],"type":"Point"}
}