{
  "type": "Feature",
  "properties": {
    "addr:full":"Postbus 1875 Maastricht Limburg 6201 BW",
    "addr:housenumber":"1875",
    "addr:postcode":"6201 bw",
    "addr:street":"Postbus",
    "iso:country":"NL",
    "sg:address":"Postbus 1875",
    "sg:city":"Maastricht",
    "sg:orig_category":"Reclame",
    "sg:phone":"+31 43 363 8522",
    "sg:postcode":"6201 BW",
    "sg:province":"Limburg",
    "sg:website":"http://www.marvingroup.nl",
    "wof:name":"Marvin Group",
    "wof:placetype":"venue"
},
  "geometry": {"coordinates":[5.68726,50.84985],"type":"Point"}
}