{
  "type": "Feature",
  "properties": {
    "addr:full":"Graan Voor Visch 14006 Hoofddorp North Holland 2132 VW",
    "addr:housenumber":"14006",
    "addr:postcode":"2132 vw",
    "addr:street":"Graan Voor Visch",
    "iso:country":"NL",
    "sg:address":"Graan Voor Visch 14006",
    "sg:city":"Hoofddorp",
    "sg:classifiers":[
        {
            "category":"Fast Food",
            "type":"Food & Drink"
        }
    ],
    "sg:phone":"+31 23 562 8400",
    "sg:postcode":"2132 VW",
    "sg:province":"North Holland",
    "sg:tags":[
        "afhaal",
        "restaurant"
    ],
    "wof:name":"Happy Snack",
    "wof:placetype":"venue"
},
  "geometry": {"coordinates":[4.69203,52.29628],"type":"Point"}
}