{
  "type": "Feature",
  "properties": {
    "addr:full":"Werenfriedplein 7 Elst Gld Gelderland 6661 EJ",
    "addr:housenumber":"7",
    "addr:postcode":"6661 ej",
    "addr:street":"Werenfriedplein;Gld Gelderland",
    "iso:country":"NL",
    "sg:address":"Werenfriedplein 7",
    "sg:city":"Elst Gld",
    "sg:orig_category":"Kappers",
    "sg:phone":"+31 481 372 724",
    "sg:postcode":"6661 EJ",
    "sg:province":"Gelderland",
    "wof:name":"Kapsalon De Kinderkapper",
    "wof:placetype":"venue"
},
  "geometry": {"coordinates":[5.8426680565,51.9184989929],"type":"Point"}
}