{
  "type": "Feature",
  "properties": {
    "addr:full":"Burg. Pappersweg 30 Mechelen Limburg 6281 BK",
    "addr:housenumber":"30",
    "addr:postcode":"6281 bk",
    "addr:street":"Burg. Pappersweg",
    "iso:country":"NL",
    "sg:address":"Burg. Pappersweg 30",
    "sg:city":"Mechelen",
    "sg:orig_category":"Boekhouders",
    "sg:phone":"+31 43 455 1832",
    "sg:postcode":"6281 BK",
    "sg:province":"Limburg",
    "wof:name":"Poconad",
    "wof:placetype":"venue"
},
  "geometry": {"coordinates":[5.924421,50.793743],"type":"Point"}
}