{
  "type": "Feature",
  "properties": {
    "addr:full":"Troelstralaan 42 Heemstede Noord-Holland 2104 VP",
    "addr:housenumber":"42",
    "addr:postcode":"2104 vp",
    "addr:street":"Troelstralaan",
    "iso:country":"NL",
    "sg:address":"Troelstralaan 42",
    "sg:city":"Heemstede",
    "sg:orig_category":"Overheidsdiensten",
    "sg:phone":"+31 23 547 2731",
    "sg:postcode":"2104 VP",
    "sg:province":"Noord-Holland",
    "wof:name":"Van Oene",
    "wof:placetype":"venue"
},
  "geometry": {"coordinates":[4.6139531136,52.3308982849],"type":"Point"}
}