{
  "type": "Feature",
  "properties": {
    "addr:full":"Prikkewei 6 Ny Beets Friesland 9245 HS",
    "addr:housenumber":"6",
    "addr:postcode":"beets;9245 hs",
    "addr:street":"Prikkewei",
    "iso:country":"NL",
    "sg:address":"Prikkewei 6",
    "sg:city":"Ny Beets",
    "sg:orig_category":"Satellietontvangst- En Antenne-Installaties",
    "sg:phone":"+31 512 461 651",
    "sg:postcode":"9245 HS",
    "sg:province":"Friesland",
    "wof:name":"Groot, Sjouke De",
    "wof:placetype":"venue"
},
  "geometry": {"coordinates":[6.017703,53.066967],"type":"Point"}
}