{
  "type": "Feature",
  "properties": {
    "iso:country":"NL",
    "sg:address":"De Vonderkampen 28",
    "sg:city":"Beilen",
    "sg:orig_category":"Facilitaire Dienstverlening",
    "sg:phone":"+31 6 53379459",
    "sg:postcode":"9411 RD",
    "sg:province":"Provincie Drenthe",
    "wof:name":"Meijering",
    "wof:placetype":"venue"
},
  "geometry": {"coordinates":[6.514873,52.857067],"type":"Point"}
}