{
  "type": "Feature",
  "properties": {
    "addr:full":"De Vonderkampen 28 Beilen Provincie Drenthe 9411 RD",
    "addr:housenumber":"28",
    "addr:postcode":"9411",
    "addr:street":"De Vonderkampen;Provincie Drenthe;Rd",
    "iso:country":"NL",
    "sg:address":"De Vonderkampen 28",
    "sg:city":"Beilen",
    "sg:orig_category":"Facilitaire Dienstverlening",
    "sg:phone":"+31 6 53379459",
    "sg:postcode":"9411 RD",
    "sg:province":"Provincie Drenthe",
    "wof:name":"Meijering",
    "wof:placetype":"venue"
},
  "geometry": {"coordinates":[6.514873,52.857067],"type":"Point"}
}