{
  "type": "Feature",
  "properties": {
    "addr:full":"Venestraat 7 'S Gravenhage Zuid-Holland 2511 AR",
    "addr:housenumber":"7 '",
    "addr:postcode":"2511",
    "addr:street":"Venestraat",
    "iso:country":"NL",
    "sg:address":"Venestraat 7",
    "sg:city":"'S Gravenhage",
    "sg:orig_category":"Opticiens",
    "sg:phone":"+31 70 364 3892",
    "sg:postcode":"2511 AR",
    "sg:province":"Zuid-Holland",
    "wof:name":"Hans Anders Opticiens/007",
    "wof:placetype":"venue"
},
  "geometry": {"coordinates":[4.3092808723,52.0777397156],"type":"Point"}
}