{
  "type": "Feature",
  "properties": {
    "addr:full":"Gazellelaan 25 Helmond Noord-Brabant 5704 DK",
    "addr:housenumber":"25",
    "addr:postcode":"5704 dk",
    "addr:street":"Gazellelaan",
    "iso:country":"NL",
    "sg:address":"Gazellelaan 25",
    "sg:city":"Helmond",
    "sg:orig_category":"Diverse Grafische Activiteiten",
    "sg:phone":"+31 492 513 751",
    "sg:postcode":"5704 DK",
    "sg:province":"Noord-Brabant",
    "wof:name":"Bigsjake",
    "wof:placetype":"venue"
},
  "geometry": {"coordinates":[5.696674,51.457981],"type":"Point"}
}