{
  "type": "Feature",
  "properties": {
    "addr:full":"Nw Vliekerwg 1 Ulestraten Limburg 6235 NP",
    "addr:housenumber":"1",
    "addr:postcode":"6235 np",
    "addr:street":"Vliekerwg",
    "iso:country":"NL",
    "sg:address":"Nw Vliekerwg 1",
    "sg:city":"Ulestraten",
    "sg:orig_category":"Antiquiteiten",
    "sg:phone":"+31 43 364 4932",
    "sg:postcode":"6235 NP",
    "sg:province":"Limburg",
    "sg:website":"http://www.omega-antiques.com",
    "wof:name":"Omega Antiques & Art",
    "wof:placetype":"venue"
},
  "geometry": {"coordinates":[5.766904,50.90308],"type":"Point"}
}