{
  "type": "Feature",
  "properties": {
    "addr:full":"Kerkewyk 163 Veenendaal Utrecht 3904 JC",
    "addr:housenumber":"163",
    "addr:postcode":"3904 jc",
    "iso:country":"NL",
    "sg:address":"Kerkewyk 163",
    "sg:city":"Veenendaal",
    "sg:orig_category":"Adviesbureaus Bouwkunde",
    "sg:phone":"+31 318 555 464",
    "sg:postcode":"3904 JC",
    "sg:province":"Utrecht",
    "wof:name":"Merwe, Van De",
    "wof:placetype":"venue"
},
  "geometry": {"coordinates":[5.544768,52.012573],"type":"Point"}
}