{
  "type": "Feature",
  "properties": {
    "iso:country":"NL",
    "sg:address":"Rijksweg A7 1",
    "sg:city":"Wons",
    "sg:orig_category":"Benzinestations And Brandstoffen",
    "sg:phone":"+31 517 531 480",
    "sg:postcode":"8747 NK",
    "sg:province":"Friesland",
    "wof:name":"Esso",
    "wof:placetype":"venue"
},
  "geometry": {"coordinates":[-96.77237700000001,38.156345],"type":"Point"}
}