{
  "type": "Feature",
  "properties": {
    "iso:country":"NL",
    "sg:address":"Ommershofln 2",
    "sg:city":"Oosterbeek",
    "sg:classifiers":[
        {
            "category":"Personal",
            "subcategory":"Nail Salon",
            "type":"Services"
        }
    ],
    "sg:phone":"+31 26 333 2267",
    "sg:postcode":"6861 CK",
    "sg:province":"Gelderland",
    "sg:tags":[
        "pedicure"
    ],
    "wof:name":"Tippersma-Bekema, G M",
    "wof:placetype":"venue"
},
  "geometry": {"coordinates":[5.835463,51.992435],"type":"Point"}
}