{
  "type": "Feature",
  "properties": {
    "addr:full":"Grevelingenmeer 179 Purmerend North Holland 1447 AP",
    "addr:housenumber":"179",
    "addr:postcode":"1447 ap",
    "addr:street":"Grevelingenmeer",
    "iso:country":"NL",
    "sg:address":"Grevelingenmeer 179",
    "sg:city":"Purmerend",
    "sg:orig_category":"Krantenuitgeverijen",
    "sg:phone":"+31 299 649 972",
    "sg:postcode":"1447 AP",
    "sg:province":"North Holland",
    "wof:name":"F.S.W.",
    "wof:placetype":"venue"
},
  "geometry": {"coordinates":[4.971902,52.495411],"type":"Point"}
}