{
  "type": "Feature",
  "properties": {
    "iso:country":"NL",
    "sg:address":"Herenweg 285",
    "sg:city":"Egmond A/D Hoef",
    "sg:orig_category":"Bloemen And Planten Gh",
    "sg:phone":"+31 72 506 3598",
    "sg:postcode":"1934 BC",
    "sg:province":"Noord-Holland",
    "wof:name":"Firma P. Bras",
    "wof:placetype":"venue"
},
  "geometry": {"coordinates":[-126.555511,54.485668],"type":"Point"}
}