{
  "type": "Feature",
  "properties": {
    "addr:full":"Kanaalstraat 134 Amsterdam Noord-Holland 1054 XN",
    "addr:housenumber":"134",
    "addr:postcode":"1054 xn",
    "addr:street":"Kanaalstraat",
    "iso:country":"NL",
    "sg:address":"Kanaalstraat 134",
    "sg:city":"Amsterdam",
    "sg:orig_category":"Autokeuringen",
    "sg:phone":"+31 20 689 8728",
    "sg:postcode":"1054 XN",
    "sg:province":"Noord-Holland",
    "wof:name":"Kanaalgarage",
    "wof:placetype":"venue"
},
  "geometry": {"coordinates":[4.860871,52.36171],"type":"Point"}
}