{
  "type": "Feature",
  "properties": {
    "addr:full":"Generaal Maczekstraat 32 Breda Noord-Brabant 4818 BW",
    "addr:housenumber":"32",
    "addr:postcode":"4818 bw",
    "addr:street":"Generaal Maczekstraat",
    "iso:country":"NL",
    "sg:address":"Generaal Maczekstraat 32",
    "sg:city":"Breda",
    "sg:orig_category":"Kappers",
    "sg:phone":"+31 76 521 2313",
    "sg:postcode":"4818 BW",
    "sg:province":"Noord-Brabant",
    "wof:name":"Hairs Ahead Kappers",
    "wof:placetype":"venue"
},
  "geometry": {"coordinates":[4.7865610123,51.5802307129],"type":"Point"}
}