{
  "type": "Feature",
  "properties": {
    "addr:full":"J Evertsenstr 107 Amsterdam North Holland 1057 BT",
    "addr:housenumber":"107",
    "addr:postcode":"1057 bt",
    "iso:country":"NL",
    "sg:address":"J Evertsenstr 107",
    "sg:city":"Amsterdam",
    "sg:orig_category":"Psychologen",
    "sg:phone":"+31 20 616 1358",
    "sg:postcode":"1057 BT",
    "sg:province":"North Holland",
    "wof:name":"Zaitman, Drs A",
    "wof:placetype":"venue"
},
  "geometry": {"coordinates":[4.852875,52.370296],"type":"Point"}
}