{
  "type": "Feature",
  "properties": {
    "addr:full":"Hoorn 12 Ede Gld Gelderland 6713 KR",
    "addr:housenumber":"12",
    "addr:postcode":"6713 kr",
    "addr:street":"Hoorn;Gld Gelderland",
    "iso:country":"NL",
    "sg:address":"Hoorn 12",
    "sg:city":"Ede Gld",
    "sg:orig_category":"Metaalbekleding And -Behandeling",
    "sg:phone":"+31 318 625 090",
    "sg:postcode":"6713 KR",
    "sg:province":"Gelderland",
    "wof:name":"Speciaal Spuiterij Hanegraaf Bv",
    "wof:placetype":"venue"
},
  "geometry": {"coordinates":[5.652859,52.03326],"type":"Point"}
}