{
  "type": "Feature",
  "properties": {
    "addr:full":"Preludeweg 15 Almere Flevoland 1312 SM",
    "addr:housenumber":"15;1312",
    "addr:postcode":"sm",
    "addr:street":"Preludeweg;Flevoland",
    "iso:country":"NL",
    "sg:address":"Preludeweg 15",
    "sg:city":"Almere",
    "sg:orig_category":"Verzekeringen",
    "sg:phone":"+31 36 536 0336",
    "sg:postcode":"1312 SM",
    "sg:province":"Flevoland",
    "wof:name":"E R Hamden Assurantien",
    "wof:placetype":"venue"
},
  "geometry": {"coordinates":[5.186782,52.37772],"type":"Point"}
}