{
  "type": "Feature",
  "properties": {
    "addr:full":"Pleintjes 191 Veldhoven North Brabant 5501 EH",
    "addr:housenumber":"191",
    "addr:postcode":"5501 eh",
    "addr:street":"Pleintjes",
    "iso:country":"NL",
    "sg:address":"Pleintjes 191",
    "sg:city":"Veldhoven",
    "sg:orig_category":"Partyservice",
    "sg:phone":"+31 40 230 0155",
    "sg:postcode":"5501 EH",
    "sg:province":"North Brabant",
    "wof:name":"Selamat Makan",
    "wof:placetype":"venue"
},
  "geometry": {"coordinates":[5.40751,51.419144],"type":"Point"}
}