{
  "type": "Feature",
  "properties": {
    "addr:full":"Reviusrondeel 94 Capelle Ad Yssel Zuid-Holland 2902 EC",
    "addr:housenumber":"94",
    "addr:postcode":"2902 ec",
    "addr:street":"Reviusrondeel",
    "iso:country":"NL",
    "sg:address":"Reviusrondeel 94",
    "sg:city":"Capelle Ad Yssel",
    "sg:classifiers":[
        {
            "category":"Personal",
            "subcategory":"Nail Salon",
            "type":"Services"
        }
    ],
    "sg:phone":"+31 10 227 1801",
    "sg:postcode":"2902 EC",
    "sg:province":"Zuid-Holland",
    "sg:tags":[
        "pedicure"
    ],
    "wof:name":"Diepenbroek, G S D",
    "wof:placetype":"venue"
},
  "geometry": {"coordinates":[4.57273,51.923618],"type":"Point"}
}