{
  "type": "Feature",
  "properties": {
    "addr:full":"Innovatieln 25 Nyehaske Friesland 8466 SN",
    "addr:housenumber":"25",
    "addr:postcode":"8466 sn",
    "addr:street":"Innovatieln",
    "iso:country":"NL",
    "sg:address":"Innovatieln 25",
    "sg:city":"Nyehaske",
    "sg:orig_category":"Machinehandel",
    "sg:phone":"+31 513 617 071",
    "sg:postcode":"8466 SN",
    "sg:province":"Friesland",
    "wof:name":"Rvk Bv",
    "wof:placetype":"venue"
},
  "geometry": {"coordinates":[5.893304,52.961056],"type":"Point"}
}