{
  "type": "Feature",
  "properties": {
    "addr:full":"Fabriekswg 5 Huizen Noord-Holland 1271 AK",
    "addr:housenumber":"5",
    "addr:postcode":"1271 ak",
    "addr:street":"Fabriekswg",
    "iso:country":"NL",
    "sg:address":"Fabriekswg 5",
    "sg:city":"Huizen",
    "sg:orig_category":"Loodgieters",
    "sg:phone":"+31 35 525 3312",
    "sg:postcode":"1271 AK",
    "sg:province":"Noord-Holland",
    "wof:name":"Rebel",
    "wof:placetype":"venue"
},
  "geometry": {"coordinates":[5.241492,52.301022],"type":"Point"}
}