{
  "type": "Feature",
  "properties": {
    "addr:full":"Heilige Stoel 4833 Wijchen Gelderland 6601 VR",
    "addr:housenumber":"4833",
    "addr:postcode":"6601 vr",
    "addr:street":"Heilige Stoel;Gelderland",
    "iso:country":"NL",
    "sg:address":"Heilige Stoel 4833",
    "sg:city":"Wijchen",
    "sg:orig_category":"Boekhouders",
    "sg:phone":"+31 24 645 3844",
    "sg:postcode":"6601 VR",
    "sg:province":"Gelderland",
    "wof:name":"Administratiekantoor Dehue",
    "wof:placetype":"venue"
},
  "geometry": {"coordinates":[5.718256,51.81612],"type":"Point"}
}