{
  "type": "Feature",
  "properties": {
    "addr:full":"Baarskampstraat 3 Kessel Lb Limburg 5995 AS",
    "addr:housenumber":"3",
    "addr:postcode":"lb;5995 as",
    "addr:street":"Baarskampstraat",
    "iso:country":"NL",
    "sg:address":"Baarskampstraat 3",
    "sg:city":"Kessel Lb",
    "sg:orig_category":"Kappers",
    "sg:phone":"+31 77 462 1259",
    "sg:postcode":"5995 AS",
    "sg:province":"Limburg",
    "wof:name":"Les Artistes",
    "wof:placetype":"venue"
},
  "geometry": {"coordinates":[6.052873,51.290802],"type":"Point"}
}