{
  "type": "Feature",
  "properties": {
    "addr:full":"Esdoornpk 35 Beuningen Gld Gelderland 6642 CC",
    "addr:housenumber":"35",
    "addr:postcode":"6642 cc",
    "addr:street":"Esdoornpk",
    "iso:country":"NL",
    "sg:address":"Esdoornpk 35",
    "sg:city":"Beuningen Gld",
    "sg:orig_category":"Kantinebeheer",
    "sg:phone":"+31 24 677 9695",
    "sg:postcode":"6642 CC",
    "sg:province":"Gelderland",
    "wof:name":"Bruisten",
    "wof:placetype":"venue"
},
  "geometry": {"coordinates":[5.7648482323,51.8539848328],"type":"Point"}
}