{
  "type": "Feature",
  "properties": {
    "addr:full":"Farmsumerweg 43 Delfzijl Groningen 9932 BA",
    "addr:housenumber":"43",
    "addr:postcode":"9932 ba",
    "addr:street":"Farmsumerweg",
    "iso:country":"NL",
    "sg:address":"Farmsumerweg 43",
    "sg:city":"Delfzijl",
    "sg:classifiers":[
        {
            "category":"Education",
            "subcategory":"Preschool",
            "type":"Public Place"
        }
    ],
    "sg:phone":"+31 596 627 716",
    "sg:postcode":"9932 BA",
    "sg:province":"Groningen",
    "sg:tags":[
        "kleuteronderwijs",
        "basis-"
    ],
    "wof:name":"Christelijke Basisschool De Vore",
    "wof:placetype":"venue"
},
  "geometry": {"coordinates":[6.891831,53.319149],"type":"Point"}
}