{
  "type": "Feature",
  "properties": {
    "addr:full":"Dorpsstraat 127A Harmelen Utrecht 3481 EC",
    "addr:housenumber":"127a",
    "addr:postcode":"3481 ec",
    "addr:street":"Dorpsstraat",
    "iso:country":"NL",
    "sg:address":"Dorpsstraat 127A",
    "sg:city":"Harmelen",
    "sg:orig_category":"Kappers",
    "sg:phone":"+31 348 442 111",
    "sg:postcode":"3481 EC",
    "sg:province":"Utrecht",
    "wof:name":"Trudy & Jaco Hairstylist",
    "wof:placetype":"venue"
},
  "geometry": {"coordinates":[4.96131,52.090832],"type":"Point"}
}