{
  "type": "Feature",
  "properties": {
    "iso:country":"NL",
    "sg:address":"Kerkstraat 22",
    "sg:city":"Hoogmade",
    "sg:orig_category":"Pleziervaartuigen And Reparatie",
    "sg:phone":"+31 71 501 8530",
    "sg:postcode":"2355 AE",
    "sg:province":"South Holland",
    "wof:name":"Scheeps En Jachtwerf Hoogmade",
    "wof:placetype":"venue"
},
  "geometry": {"coordinates":[4.581201,52.167873],"type":"Point"}
}