{
  "type": "Feature",
  "properties": {
    "addr:full":"Ter Apelkan O 79 Ter Apelkanaal Groningen 9563 RD",
    "addr:housenumber":"79",
    "addr:postcode":"9563 rd",
    "addr:street":"O",
    "iso:country":"NL",
    "sg:address":"Ter Apelkan O 79",
    "sg:city":"Ter Apelkanaal",
    "sg:orig_category":"Verenigingsgebouwen",
    "sg:phone":"+31 599 417 572",
    "sg:postcode":"9563 RD",
    "sg:province":"Groningen",
    "wof:name":"Dorpshuis De Aole School",
    "wof:placetype":"venue"
},
  "geometry": {"coordinates":[7.048644,52.908691],"type":"Point"}
}