{
  "type": "Feature",
  "properties": {
    "addr:full":"Herenstraat 43 Rijswijk Zh Zuid-Holland 2282 BP",
    "addr:housenumber":"43",
    "addr:postcode":"zh;2282 bp",
    "addr:street":"Herenstraat",
    "iso:country":"NL",
    "sg:address":"Herenstraat 43",
    "sg:city":"Rijswijk Zh",
    "sg:orig_category":"Paramedische Behandelingen",
    "sg:phone":"+31 70 319 1878",
    "sg:postcode":"2282 BP",
    "sg:province":"Zuid-Holland",
    "wof:name":"Vof Bur Kraamzorg Extra",
    "wof:placetype":"venue"
},
  "geometry": {"coordinates":[4.335635,52.055878],"type":"Point"}
}