{
  "type": "Feature",
  "properties": {
    "addr:full":"Bouwerskamp 10 Emmeloord Flevoland 8301 AG",
    "addr:housenumber":"10",
    "addr:postcode":"8301",
    "addr:street":"Bouwerskamp;Flevoland",
    "iso:country":"NL",
    "sg:address":"Bouwerskamp 10",
    "sg:city":"Emmeloord",
    "sg:orig_category":"Houtgroothandel",
    "sg:phone":"+31 527 616 951",
    "sg:postcode":"8301 AG",
    "sg:province":"Flevoland",
    "wof:name":"Oberman Oppedijk Bv",
    "wof:placetype":"venue"
},
  "geometry": {"coordinates":[5.753461,52.707081],"type":"Point"}
}