{
  "type": "Feature",
  "properties": {
    "iso:country":"NL",
    "sg:address":"3E Loosterweg 12",
    "sg:city":"Hillegom",
    "sg:orig_category":"Bloemen- And Plantenteelt",
    "sg:phone":"+31 252 515 388",
    "sg:postcode":"2182 CV",
    "sg:province":"North Holland",
    "wof:name":"Fa. J.C. Meeldijk En Zonen",
    "wof:placetype":"venue"
},
  "geometry": {"coordinates":[4.562774,52.294823],"type":"Point"}
}