{
  "type": "Feature",
  "properties": {
    "addr:full":"Sint Jorisstraat 131 'S Hertogenbosch Noord-Brabant 5211 HA",
    "addr:housenumber":"131 ' s",
    "addr:postcode":"5211 ha",
    "addr:street":"Sint Jorisstraat",
    "iso:country":"NL",
    "sg:address":"Sint Jorisstraat 131",
    "sg:city":"'S Hertogenbosch",
    "sg:orig_category":"Juridische Dienstverlening",
    "sg:phone":"+31 73 614 2404",
    "sg:postcode":"5211 HA",
    "sg:province":"Noord-Brabant",
    "wof:name":"Buro Bosch Instituut Voor Bewustzijnsman",
    "wof:placetype":"venue"
},
  "geometry": {"coordinates":[5.30209589,51.6853179932],"type":"Point"}
}