{
  "type": "Feature",
  "properties": {
    "addr:full":"Heulwg 90 Kwintsheul South Holland 2295 KJ",
    "addr:housenumber":"90",
    "addr:postcode":"2295 kj",
    "addr:street":"Heulwg",
    "iso:country":"NL",
    "sg:address":"Heulwg 90",
    "sg:city":"Kwintsheul",
    "sg:orig_category":"Touringcars",
    "sg:phone":"+31 174 221 219",
    "sg:postcode":"2295 KJ",
    "sg:province":"South Holland",
    "wof:name":"Kwibus Fun-Bus",
    "wof:placetype":"venue"
},
  "geometry": {"coordinates":[4.261013,52.016872],"type":"Point"}
}