{
  "type": "Feature",
  "properties": {
    "iso:country":"NL",
    "sg:address":"Tussen De Bogen 85",
    "sg:city":"Amsterdam",
    "sg:orig_category":"Meubelmakerijen",
    "sg:phone":"+31 20 638 5111",
    "sg:postcode":"1013 JB",
    "sg:province":"Noord-Holland",
    "wof:name":"In Hout",
    "wof:placetype":"venue"
},
  "geometry": {"coordinates":[4.885078,52.384995],"type":"Point"}
}