{
  "type": "Feature",
  "properties": {
    "addr:full":"Dierenseln 24 Den Haag South Holland 2573 KH",
    "addr:housenumber":"24",
    "addr:postcode":"2573 kh",
    "addr:street":"Dierenseln",
    "iso:country":"NL",
    "sg:address":"Dierenseln 24",
    "sg:city":"Den Haag",
    "sg:orig_category":"Postkantoren",
    "sg:phone":"+31 70 360 6120",
    "sg:postcode":"2573 KH",
    "sg:province":"South Holland",
    "sg:website":"http://www.postkantoor.nl",
    "wof:name":"Postkantoor",
    "wof:placetype":"venue"
},
  "geometry": {"coordinates":[4.285998,52.066895],"type":"Point"}
}