{
  "type": "Feature",
  "properties": {
    "addr:full":"St Annadal 18 Maastricht Limburg 6214 PB",
    "addr:housenumber":"18",
    "addr:postcode":"6214 pb",
    "addr:street":"St Annadal",
    "iso:country":"NL",
    "sg:address":"St Annadal 18",
    "sg:city":"Maastricht",
    "sg:orig_category":"Mensendieck - Oefentherapeuten",
    "sg:phone":"+31 43 347 4073",
    "sg:postcode":"6214 PB",
    "sg:province":"Limburg",
    "wof:name":"Obers, Twan",
    "wof:placetype":"venue"
},
  "geometry": {"coordinates":[5.672879,50.848106],"type":"Point"}
}