{
  "type": "Feature",
  "properties": {
    "addr:full":"Sumatraln 24A Hilversum North Holland 1217 GS",
    "addr:housenumber":"24a",
    "addr:postcode":"1217 gs",
    "addr:street":"Sumatraln",
    "iso:country":"NL",
    "sg:address":"Sumatraln 24A",
    "sg:city":"Hilversum",
    "sg:orig_category":"Fotoreportages",
    "sg:phone":"+31 35 623 4325",
    "sg:postcode":"1217 GS",
    "sg:province":"North Holland",
    "sg:website":"http://www.tkf-foto.nl",
    "wof:name":"Ton Kastermans Fotografie",
    "wof:placetype":"venue"
},
  "geometry": {"coordinates":[5.174714,52.232498],"type":"Point"}
}