{
  "type": "Feature",
  "properties": {
    "iso:country":"NL",
    "sg:address":"Strevelswg 210",
    "sg:city":"Rotterdam",
    "sg:orig_category":"Administratie- En Boekhoudkantoren",
    "sg:phone":"+31 10 423 1829",
    "sg:postcode":"3075 AW",
    "sg:province":"Zuid-Holland",
    "wof:name":"Jong, De",
    "wof:placetype":"venue"
},
  "geometry": {"coordinates":[4.496865,51.889278],"type":"Point"}
}