{
  "type": "Feature",
  "properties": {
    "addr:full":"Gouvernementsplein 27 Bergen Op Zoom Noord-Brabant 4611 PM",
    "addr:housenumber":"27",
    "addr:postcode":"4611 pm",
    "addr:street":"Gouvernementsplein",
    "iso:country":"NL",
    "sg:address":"Gouvernementsplein 27",
    "sg:city":"Bergen Op Zoom",
    "sg:orig_category":"Discountwinkels",
    "sg:phone":"+31 164 211 122",
    "sg:postcode":"4611 PM",
    "sg:province":"Noord-Brabant",
    "wof:name":"Wibra Bv",
    "wof:placetype":"venue"
},
  "geometry": {"coordinates":[4.29061,51.495567],"type":"Point"}
}