{
  "type": "Feature",
  "properties": {
    "iso:country":"NL",
    "sg:address":"Meerzyde 31",
    "sg:city":"Volendam",
    "sg:orig_category":"Geschenkartikelen",
    "sg:phone":"+31 299 362 118",
    "sg:postcode":"1131 ZZ",
    "sg:province":"North Holland",
    "wof:name":"Juwelaartje, 'T",
    "wof:placetype":"venue"
},
  "geometry": {"coordinates":[5.071785,52.496269],"type":"Point"}
}