{
  "type": "Feature",
  "properties": {
    "addr:full":"Streefoordln 10 Eemnes Utrecht 3755 BB",
    "addr:housenumber":"10",
    "addr:postcode":"3755 bb",
    "addr:street":"Streefoordln",
    "iso:country":"NL",
    "sg:address":"Streefoordln 10",
    "sg:city":"Eemnes",
    "sg:orig_category":"Kinderopvang",
    "sg:phone":"+31 35 538 4224",
    "sg:postcode":"3755 BB",
    "sg:province":"Utrecht",
    "wof:name":"Astrix Eemnes",
    "wof:placetype":"venue"
},
  "geometry": {"coordinates":[5.254452,52.253124],"type":"Point"}
}