{
  "type": "Feature",
  "properties": {
    "addr:full":"Oostkd 2 Huizen North Holland 1274 NC",
    "addr:housenumber":"2",
    "addr:postcode":"1274 nc",
    "addr:street":"Oostkd",
    "iso:country":"NL",
    "sg:address":"Oostkd 2",
    "sg:city":"Huizen",
    "sg:orig_category":"Zonnebank- En Solariumcentra",
    "sg:phone":"+31 35 525 1399",
    "sg:postcode":"1274 NC",
    "sg:province":"North Holland",
    "sg:website":"http://www.altrasol.nl",
    "wof:name":"Altra Sol",
    "wof:placetype":"venue"
},
  "geometry": {"coordinates":[5.23421,52.29504],"type":"Point"}
}