{
  "type": "Feature",
  "properties": {
    "addr:full":"Fazantenlaan 4 Veere Zeeland 4351 RV",
    "addr:housenumber":"4",
    "addr:postcode":"4351 rv",
    "addr:street":"Fazantenlaan",
    "iso:country":"NL",
    "sg:address":"Fazantenlaan 4",
    "sg:city":"Veere",
    "sg:orig_category":"Hoger Onderwijs",
    "sg:phone":"+31 118 501 556",
    "sg:postcode":"4351 RV",
    "sg:province":"Zeeland",
    "wof:name":"Veere",
    "wof:placetype":"venue"
},
  "geometry": {"coordinates":[3.65587,51.552528],"type":"Point"}
}