{
  "type": "Feature",
  "properties": {
    "addr:full":"Ds L Kooymansln 9 Waalwyk Noord-Brabant 5142 GE",
    "addr:housenumber":"9",
    "addr:postcode":"5142",
    "addr:street":"Ds;Kooymansln",
    "iso:country":"NL",
    "sg:address":"Ds L Kooymansln 9",
    "sg:city":"Waalwyk",
    "sg:orig_category":"Kinderopvang",
    "sg:phone":"+31 416 338 039",
    "sg:postcode":"5142 GE",
    "sg:province":"Noord-Brabant",
    "wof:name":"Pinokkio",
    "wof:placetype":"venue"
},
  "geometry": {"coordinates":[5.0872,51.689838],"type":"Point"}
}