{
  "type": "Feature",
  "properties": {
    "iso:country":"NL",
    "sg:address":"Klaverpln 28",
    "sg:city":"Veldhoven",
    "sg:orig_category":"Metselwerken",
    "sg:phone":"+31 40 253 9110",
    "sg:postcode":"5503 PJ",
    "sg:province":"North Brabant",
    "wof:name":"Dijssel, Van Den",
    "wof:placetype":"venue"
},
  "geometry": {"coordinates":[5.402374,51.414944],"type":"Point"}
}