{
  "type": "Feature",
  "properties": {
    "addr:full":"Mariahoeveplein 6 'S Gravenhage Zuid-Holland 2591 TV",
    "addr:housenumber":"6 '",
    "addr:postcode":"2591 tv",
    "addr:street":"Mariahoeveplein",
    "iso:country":"NL",
    "sg:address":"Mariahoeveplein 6",
    "sg:city":"'S Gravenhage",
    "sg:orig_category":"Metalen And Ertsen Gh",
    "sg:phone":"+31 70 315 6666",
    "sg:postcode":"2591 TV",
    "sg:province":"Zuid-Holland",
    "wof:name":"Billiton Marketing & Trading Bv",
    "wof:placetype":"venue"
},
  "geometry": {"coordinates":[4.368252,52.090836],"type":"Point"}
}