{
  "type": "Feature",
  "properties": {
    "addr:full":"Kloosterln 203 Hilversum North Holland 1216 NN",
    "addr:housenumber":"203",
    "addr:postcode":"1216 nn",
    "iso:country":"NL",
    "sg:address":"Kloosterln 203",
    "sg:city":"Hilversum",
    "sg:orig_category":"Kappers",
    "sg:phone":"+31 35 624 8329",
    "sg:postcode":"1216 NN",
    "sg:province":"North Holland",
    "wof:name":"Joke Schmidt",
    "wof:placetype":"venue"
},
  "geometry": {"coordinates":[5.1694998741,52.2285652161],"type":"Point"}
}