{
  "type": "Feature",
  "properties": {
    "addr:full":"Grietmansln 43 Oosterwolde Fr Friesland 8431 CM",
    "addr:housenumber":"43",
    "addr:postcode":"8431 cm",
    "addr:street":"Grietmansln",
    "iso:country":"NL",
    "sg:address":"Grietmansln 43",
    "sg:city":"Oosterwolde Fr",
    "sg:orig_category":"Geluidsinstallaties",
    "sg:phone":"+31 516 513 116",
    "sg:postcode":"8431 CM",
    "sg:province":"Friesland",
    "wof:name":"Sound, E J",
    "wof:placetype":"venue"
},
  "geometry": {"coordinates":[6.289522,52.984825],"type":"Point"}
}