{
  "type": "Feature",
  "properties": {
    "iso:country":"NL",
    "sg:address":"Pieter Braaijweg 10",
    "sg:city":"Amsterdam",
    "sg:orig_category":"Architecten",
    "sg:phone":"+31 20 460 4220",
    "sg:postcode":"1099 DG",
    "sg:province":"Noord-Holland",
    "wof:name":"Omegam Wegenbouwlaboratorium",
    "wof:placetype":"venue"
},
  "geometry": {"coordinates":[4.92343,52.328621],"type":"Point"}
}