{
  "type": "Feature",
  "properties": {
    "addr:full":"Beukelsdijk 55 Rotterdam Zuid-Holland 3021 AD",
    "addr:housenumber":"55",
    "addr:postcode":"3021 ad",
    "addr:street":"Beukelsdijk",
    "iso:country":"NL",
    "sg:address":"Beukelsdijk 55",
    "sg:city":"Rotterdam",
    "sg:orig_category":"Werving And Selectie Van Tijdelijk Personeel And Uitzendkantoren",
    "sg:phone":"+31 10 476 6332",
    "sg:postcode":"3021 AD",
    "sg:province":"Zuid-Holland",
    "wof:name":"Hitech",
    "wof:placetype":"venue"
},
  "geometry": {"coordinates":[4.4604768753,51.9221153259],"type":"Point"}
}