{
  "type": "Feature",
  "properties": {
    "iso:country":"NL",
    "sg:address":"Boekelerschoolpad 1",
    "sg:city":"Enschede",
    "sg:classifiers":[
        {
            "category":"Education",
            "subcategory":"Preschool",
            "type":"Public Place"
        }
    ],
    "sg:phone":"+31 53 428 1543",
    "sg:postcode":"7548 AH",
    "sg:province":"Overijssel",
    "sg:tags":[
        "kleuteronderwijs",
        "basis-"
    ],
    "wof:name":"Boekelerschool",
    "wof:placetype":"venue"
},
  "geometry": {"coordinates":[6.80094,52.202965],"type":"Point"}
}