{
  "type": "Feature",
  "properties": {
    "addr:full":"Ommelsewg 46 Asten Noord-Brabant 5721 WV",
    "addr:housenumber":"46",
    "addr:postcode":"5721 wv",
    "addr:street":"Ommelsewg",
    "iso:country":"NL",
    "sg:address":"Ommelsewg 46",
    "sg:city":"Asten",
    "sg:orig_category":"Autoschade- Herstelbedrijven",
    "sg:phone":"+31 493 695 874",
    "sg:postcode":"5721 WV",
    "sg:province":"Noord-Brabant",
    "wof:name":"Heuvel, Van Den",
    "wof:placetype":"venue"
},
  "geometry": {"coordinates":[5.749469,51.415257],"type":"Point"}
}