{
  "type": "Feature",
  "properties": {
    "addr:full":"Markt 5 Lobith Gelderland 6915 AH",
    "addr:housenumber":"5",
    "addr:postcode":"6915 ah",
    "addr:street":"Markt;Gelderland",
    "iso:country":"NL",
    "sg:address":"Markt 5",
    "sg:city":"Lobith",
    "sg:orig_category":"Overheidsdiensten",
    "sg:phone":"+31 316 565 600",
    "sg:postcode":"6915 AH",
    "sg:province":"Gelderland",
    "wof:name":"Gemeente Rijnwaarden",
    "wof:placetype":"venue"
},
  "geometry": {"coordinates":[6.1202921867,51.8606414795],"type":"Point"}
}