{
  "type": "Feature",
  "properties": {
    "addr:full":"Oranjeln 5 Paterswolde Drenthe 9765 AG",
    "addr:housenumber":"5",
    "addr:postcode":"9765",
    "addr:street":"Oranjeln",
    "iso:country":"NL",
    "sg:address":"Oranjeln 5",
    "sg:city":"Paterswolde",
    "sg:orig_category":"Modevakscholen",
    "sg:phone":"+31 50 309 2798",
    "sg:postcode":"9765 AG",
    "sg:province":"Drenthe",
    "wof:name":"Veltink, H G",
    "wof:placetype":"venue"
},
  "geometry": {"coordinates":[6.571063,53.143681],"type":"Point"}
}