{
  "type": "Feature",
  "properties": {
    "addr:full":"Oudendk 46 Dordrecht Zuid-Holland 3318 AH",
    "addr:housenumber":"46",
    "addr:postcode":"3318 ah",
    "addr:street":"Oudendk",
    "iso:country":"NL",
    "sg:address":"Oudendk 46",
    "sg:city":"Dordrecht",
    "sg:orig_category":"Scheepvaartmijen",
    "sg:phone":"+31 78 617 4676",
    "sg:postcode":"3318 AH",
    "sg:province":"Zuid-Holland",
    "wof:name":"Societas Vof",
    "wof:placetype":"venue"
},
  "geometry": {"coordinates":[4.684437,51.790409],"type":"Point"}
}