{
  "type": "Feature",
  "properties": {
    "iso:country":"NL",
    "sg:address":"Akkeroord 3B",
    "sg:city":"Waddinxveen",
    "sg:orig_category":"Goederenvervoer Over De Weg",
    "sg:phone":"+31 182 612 037",
    "sg:postcode":"2741 PZ",
    "sg:province":"Zuid-Holland",
    "wof:name":"H. Hoogendoorn",
    "wof:placetype":"venue"
},
  "geometry": {"coordinates":[4.661969,52.025513],"type":"Point"}
}