{
  "type": "Feature",
  "properties": {
    "addr:full":"Hoofdstraat Oost 4 Uithuizen Groningen 9981 AH",
    "addr:housenumber":"4",
    "addr:postcode":"9981 ah",
    "addr:street":"Hoofdstraat Oost",
    "iso:country":"NL",
    "sg:address":"Hoofdstraat Oost 4",
    "sg:city":"Uithuizen",
    "sg:orig_category":"Schoenen",
    "sg:phone":"+31 595 431 204",
    "sg:postcode":"9981 AH",
    "sg:province":"Groningen",
    "wof:name":"E. Dijkhuis En Zoon",
    "wof:placetype":"venue"
},
  "geometry": {"coordinates":[6.674331,53.40744],"type":"Point"}
}