{
  "type": "Feature",
  "properties": {
    "addr:full":"Hoogstraat 10 Schiedam Zuid-Holland 3111 HH",
    "addr:housenumber":"10",
    "addr:postcode":"3111 hh",
    "addr:street":"Hoogstraat",
    "iso:country":"NL",
    "sg:address":"Hoogstraat 10",
    "sg:city":"Schiedam",
    "sg:orig_category":"Herenmodezaken",
    "sg:phone":"+31 10 427 0687",
    "sg:postcode":"3111 HH",
    "sg:province":"Zuid-Holland",
    "wof:name":"Jacomo Exclusieve Herenmode",
    "wof:placetype":"venue"
},
  "geometry": {"coordinates":[4.39816,51.918472],"type":"Point"}
}