{
  "type": "Feature",
  "properties": {
    "addr:full":"Tongerloseweg 13 Diessen Noord-Brabant 5087 KX",
    "addr:housenumber":"13",
    "addr:postcode":"5087 kx",
    "addr:street":"Tongerloseweg",
    "iso:country":"NL",
    "sg:address":"Tongerloseweg 13",
    "sg:city":"Diessen",
    "sg:orig_category":"Boekhouders",
    "sg:phone":"+31 13 504 1382",
    "sg:postcode":"5087 KX",
    "sg:province":"Noord-Brabant",
    "wof:name":"A. Doderlein De Win",
    "wof:placetype":"venue"
},
  "geometry": {"coordinates":[5.181488,51.460327],"type":"Point"}
}