{
  "type": "Feature",
  "properties": {
    "addr:full":"Aalsmeerderwg 170 Aalsmeer Noord-Holland 1432 CV",
    "addr:housenumber":"170",
    "addr:postcode":"aalsmeer;1432 cv",
    "iso:country":"NL",
    "sg:address":"Aalsmeerderwg 170",
    "sg:city":"Aalsmeer",
    "sg:orig_category":"Bouwbureaus",
    "sg:phone":"+31 297 343 812",
    "sg:postcode":"1432 CV",
    "sg:province":"Noord-Holland",
    "wof:name":"Koert, Ab Van",
    "wof:placetype":"venue"
},
  "geometry": {"coordinates":[4.785765,52.276257],"type":"Point"}
}