{
  "type": "Feature",
  "properties": {
    "addr:full":"Lessinglaan 98 Utrecht Utrecht 3533 AZ",
    "addr:housenumber":"98",
    "addr:postcode":"3533",
    "addr:street":"Lessinglaan",
    "iso:country":"NL",
    "sg:address":"Lessinglaan 98",
    "sg:city":"Utrecht",
    "sg:orig_category":"Alternatieve Geneeskunde",
    "sg:phone":"+31 30 293 1553",
    "sg:postcode":"3533 AZ",
    "sg:province":"Utrecht",
    "wof:name":"Fysiotherapiepraktijk Oog In Al",
    "wof:placetype":"venue"
},
  "geometry": {"coordinates":[5.083373,52.088051],"type":"Point"}
}