{
  "type": "Feature",
  "properties": {
    "addr:full":"Franseln 281A Rotterdam South Holland 3028 AD",
    "addr:housenumber":"281a",
    "addr:postcode":"3028 ad",
    "iso:country":"NL",
    "sg:address":"Franseln 281A",
    "sg:city":"Rotterdam",
    "sg:classifiers":[
        {
            "category":"Food & Beverages",
            "subcategory":"Fruits & Vegetables",
            "type":"Retail Goods"
        }
    ],
    "sg:phone":"+31 10 437 9363",
    "sg:postcode":"3028 AD",
    "sg:province":"South Holland",
    "sg:tags":[
        "en",
        "groenten"
    ],
    "sg:website":"http://www.vita-mina.nl",
    "wof:name":"Agf Vita-Mina",
    "wof:placetype":"venue"
},
  "geometry": {"coordinates":[4.418261,51.917622],"type":"Point"}
}