{
  "type": "Feature",
  "properties": {
    "iso:country":"NL",
    "sg:address":"Orteliusstraat 212-3",
    "sg:city":"Amsterdam",
    "sg:orig_category":"Binnenhuisarchitectuur",
    "sg:phone":"+31 20 612 4147",
    "sg:postcode":"1056 PG",
    "sg:province":"North Holland",
    "wof:name":"Fk 68",
    "wof:placetype":"venue"
},
  "geometry": {"coordinates":[4.849063,52.370674],"type":"Point"}
}