{
  "type": "Feature",
  "properties": {
    "addr:full":"Waalresewg 2 Valkenswaard Noord-Brabant 5554 HC",
    "addr:housenumber":"2",
    "addr:postcode":"5554 hc",
    "addr:street":"Waalresewg",
    "iso:country":"NL",
    "sg:address":"Waalresewg 2",
    "sg:city":"Valkenswaard",
    "sg:classifiers":[
        {
            "category":"Professional",
            "subcategory":"Accounting & Tax Preparation",
            "type":"Services"
        }
    ],
    "sg:phone":"+31 40 201 4517",
    "sg:postcode":"5554 HC",
    "sg:province":"Noord-Brabant",
    "sg:tags":[
        "accountant",
        "en",
        "-kantoren",
        "register-"
    ],
    "wof:name":"Kalb En Partners",
    "wof:placetype":"venue"
},
  "geometry": {"coordinates":[5.458858,51.351116],"type":"Point"}
}