{
  "type": "Feature",
  "properties": {
    "iso:country":"NL",
    "sg:address":"De Kievit 2",
    "sg:city":"Meerlo",
    "sg:orig_category":"Hypotheken And Hypotheekbanken",
    "sg:phone":"+31 478 692 848",
    "sg:postcode":"5864 BX",
    "sg:province":"Limburg",
    "wof:name":"Katja De Geus",
    "wof:placetype":"venue"
},
  "geometry": {"coordinates":[6.085497,51.510403],"type":"Point"}
}