{
  "type": "Feature",
  "properties": {
    "addr:full":"H De Swaeffstr 9 Helmond Noord-Brabant 5706 MX",
    "addr:housenumber":"9",
    "addr:postcode":"5706 mx",
    "iso:country":"NL",
    "sg:address":"H De Swaeffstr 9",
    "sg:city":"Helmond",
    "sg:orig_category":"Woningstoffeerders",
    "sg:phone":"+31 492 574 735",
    "sg:postcode":"5706 MX",
    "sg:province":"Noord-Brabant",
    "wof:name":"Billekens",
    "wof:placetype":"venue"
},
  "geometry": {"coordinates":[5.6313681602,51.4578742981],"type":"Point"}
}