{
  "type": "Feature",
  "properties": {
    "addr:full":"J Enschedewg 15 Uithoorn Noord-Holland 1422 DR",
    "addr:housenumber":"15",
    "addr:postcode":"1422 dr",
    "iso:country":"NL",
    "sg:address":"J Enschedewg 15",
    "sg:city":"Uithoorn",
    "sg:orig_category":"Hypotheken",
    "sg:phone":"+31 297 562 080",
    "sg:postcode":"1422 DR",
    "sg:province":"Noord-Holland",
    "wof:name":"Fraenkel, E E",
    "wof:placetype":"venue"
},
  "geometry": {"coordinates":[4.839918,52.243198],"type":"Point"}
}