{
  "type": "Feature",
  "properties": {
    "addr:full":"Merwede 34 Heerhugowaard North Holland 1703 KT",
    "addr:housenumber":"34",
    "addr:postcode":"1703 kt",
    "addr:street":"Merwede",
    "iso:country":"NL",
    "sg:address":"Merwede 34",
    "sg:city":"Heerhugowaard",
    "sg:orig_category":"Yoga-Instituten",
    "sg:phone":"+31 72 571 0757",
    "sg:postcode":"1703 KT",
    "sg:province":"North Holland",
    "wof:name":"Bock, Mieke De",
    "wof:placetype":"venue"
},
  "geometry": {"coordinates":[4.827424,52.657173],"type":"Point"}
}