{
  "type": "Feature",
  "properties": {
    "addr:full":"Rozenburgln 10 Duivendrecht Noord-Holland 1115 BS",
    "addr:housenumber":"10",
    "addr:postcode":"1115 bs",
    "addr:street":"Rozenburgln",
    "iso:country":"NL",
    "sg:address":"Rozenburgln 10",
    "sg:city":"Duivendrecht",
    "sg:orig_category":"Touringcars",
    "sg:phone":"+31 20 699 1605",
    "sg:postcode":"1115 BS",
    "sg:province":"Noord-Holland",
    "sg:website":"http://www.meering.nl",
    "wof:name":"Meering Touringcars Amsterdam Bv",
    "wof:placetype":"venue"
},
  "geometry": {"coordinates":[4.946026,52.33559],"type":"Point"}
}