{
  "type": "Feature",
  "properties": {
    "addr:full":"H Hoekstr 57 Wateringen Zuid-Holland 2291 SL",
    "addr:housenumber":"57",
    "addr:postcode":"2291 sl",
    "iso:country":"NL",
    "sg:address":"H Hoekstr 57",
    "sg:city":"Wateringen",
    "sg:orig_category":"Verloskundigen",
    "sg:phone":"+31 174 295 807",
    "sg:postcode":"2291 SL",
    "sg:province":"Zuid-Holland",
    "wof:name":"In Het Wateringse, Verloskundige Praktijk",
    "wof:placetype":"venue"
},
  "geometry": {"coordinates":[4.2662391663,52.0257644653],"type":"Point"}
}