{
  "type": "Feature",
  "properties": {
    "addr:full":"Wierdensestraat 23 Almelo Overijssel 7607 GE",
    "addr:housenumber":"23",
    "addr:postcode":"7607",
    "addr:street":"Wierdensestraat",
    "iso:country":"NL",
    "sg:address":"Wierdensestraat 23",
    "sg:city":"Almelo",
    "sg:orig_category":"Banken And Kredietinstellingen",
    "sg:phone":"+31 546 835 555",
    "sg:postcode":"7607 GE",
    "sg:province":"Overijssel",
    "wof:name":"Ing Bank",
    "wof:placetype":"venue"
},
  "geometry": {"coordinates":[6.661877,52.355225],"type":"Point"}
}