{
  "type": "Feature",
  "properties": {
    "addr:full":"Lizzy Ansinghstraat 15 Hoofddorp Noord-Holland 2135 TL",
    "addr:housenumber":"15",
    "addr:postcode":"2135 tl",
    "addr:street":"Lizzy Ansinghstraat",
    "iso:country":"NL",
    "sg:address":"Lizzy Ansinghstraat 15",
    "sg:city":"Hoofddorp",
    "sg:orig_category":"Boekhouders",
    "sg:phone":"+31 23 565 3930",
    "sg:postcode":"2135 TL",
    "sg:province":"Noord-Holland",
    "wof:name":"Administratiekantoor Ruigrok",
    "wof:placetype":"venue"
},
  "geometry": {"coordinates":[4.660451,52.295567],"type":"Point"}
}