{
  "type": "Feature",
  "properties": {
    "addr:full":"J Catsstr 66B Rotterdam Zuid-Holland 3035 PP",
    "addr:housenumber":"66b",
    "addr:postcode":"3035 pp",
    "iso:country":"NL",
    "sg:address":"J Catsstr 66B",
    "sg:city":"Rotterdam",
    "sg:orig_category":"Meubelmakerijen",
    "sg:phone":"+31 10 466 0210",
    "sg:postcode":"3035 PP",
    "sg:province":"Zuid-Holland",
    "wof:name":"3D Realisietse",
    "wof:placetype":"venue"
},
  "geometry": {"coordinates":[4.481705,51.933014],"type":"Point"}
}