{
  "type": "Feature",
  "properties": {
    "addr:full":"V Rynstr 6 De Lier Zuid-Holland 2678 BP",
    "addr:housenumber":"6",
    "addr:postcode":"2678 bp",
    "addr:street":"Rynstr",
    "iso:country":"NL",
    "sg:address":"V Rynstr 6",
    "sg:city":"De Lier",
    "sg:orig_category":"Administratie- En Boekhoudkantoren",
    "sg:phone":"+31 174 518 332",
    "sg:postcode":"2678 BP",
    "sg:province":"Zuid-Holland",
    "wof:name":"Dijkhuizen, P A",
    "wof:placetype":"venue"
},
  "geometry": {"coordinates":[4.25138,51.975086],"type":"Point"}
}