{
  "type": "Feature",
  "properties": {
    "addr:full":"Jaagpad 19 Haastrecht Zuid-Holland 2851 CE",
    "addr:housenumber":"19",
    "addr:postcode":"2851 ce",
    "addr:street":"Jaagpad",
    "iso:country":"NL",
    "sg:address":"Jaagpad 19",
    "sg:city":"Haastrecht",
    "sg:orig_category":"Bloemen En Planten",
    "sg:phone":"+31 182 501 850",
    "sg:postcode":"2851 CE",
    "sg:province":"Zuid-Holland",
    "wof:name":"Gils, Fa E & T Van",
    "wof:placetype":"venue"
},
  "geometry": {"coordinates":[4.775012,52.002678],"type":"Point"}
}