{
  "type": "Feature",
  "properties": {
    "addr:full":"Eeckelhagen 37 Nunspeet Gelderland 8071 ZR",
    "addr:housenumber":"37",
    "addr:postcode":"8071",
    "addr:street":"Eeckelhagen;Gelderland",
    "iso:country":"NL",
    "sg:address":"Eeckelhagen 37",
    "sg:city":"Nunspeet",
    "sg:orig_category":"Scholen Voor Basisonderwijs",
    "sg:phone":"+31 341 253 637",
    "sg:postcode":"8071 ZR",
    "sg:province":"Gelderland",
    "sg:website":"http://web.inter.NL.net/hcc/dacosta",
    "wof:name":"Da Costa Chr",
    "wof:placetype":"venue"
},
  "geometry": {"coordinates":[5.765402,52.370113],"type":"Point"}
}