{
  "type": "Feature",
  "properties": {
    "addr:full":"Eshofln 37 Woudenberg Utrecht 3931 SB",
    "addr:housenumber":"37",
    "addr:postcode":"3931 sb",
    "addr:street":"Eshofln",
    "iso:country":"NL",
    "sg:address":"Eshofln 37",
    "sg:city":"Woudenberg",
    "sg:orig_category":"Metaalbewerking",
    "sg:phone":"+31 6 20539203",
    "sg:postcode":"3931 SB",
    "sg:province":"Utrecht",
    "wof:name":"Barten",
    "wof:placetype":"venue"
},
  "geometry": {"coordinates":[5.415759,52.08215],"type":"Point"}
}