{
  "type": "Feature",
  "properties": {
    "addr:full":"Heuvel 22 Geldrop Noord-Brabant 5664 HL",
    "addr:housenumber":"22",
    "addr:postcode":"5664 hl",
    "addr:street":"Heuvel",
    "iso:country":"NL",
    "sg:address":"Heuvel 22",
    "sg:city":"Geldrop",
    "sg:orig_category":"Binnenhuisarchitecten",
    "sg:phone":"+31 40 286 2297",
    "sg:postcode":"5664 HL",
    "sg:province":"Noord-Brabant",
    "wof:name":"Domus Interieur Bv",
    "wof:placetype":"venue"
},
  "geometry": {"coordinates":[5.560628,51.422607],"type":"Point"}
}