{
  "type": "Feature",
  "properties": {
    "addr:full":"Uiterweg 131 Aalsmeer Noord-Holland 1431 AD",
    "addr:housenumber":"131",
    "addr:postcode":"1431 ad",
    "addr:street":"Uiterweg",
    "iso:country":"NL",
    "sg:address":"Uiterweg 131",
    "sg:city":"Aalsmeer",
    "sg:orig_category":"Aanvullende Diensten Watertransport",
    "sg:phone":"+31 297 320 484",
    "sg:postcode":"1431 AD",
    "sg:province":"Noord-Holland",
    "wof:name":"De Aalscholver",
    "wof:placetype":"venue"
},
  "geometry": {"coordinates":[4.736948,52.263153],"type":"Point"}
}