{
  "type": "Feature",
  "properties": {
    "addr:full":"Noordwal 28 S Hertogenbosch North Brabant 5211 RN",
    "addr:housenumber":"28",
    "addr:postcode":"5211 rn",
    "addr:street":"Noordwal;S Hertogenbosch",
    "iso:country":"NL",
    "sg:address":"Noordwal 28",
    "sg:city":"S Hertogenbosch",
    "sg:orig_category":"Verenigingen En Stichtingen",
    "sg:phone":"+31 73 691 1818",
    "sg:postcode":"5211 RN",
    "sg:province":"North Brabant",
    "sg:website":"http://www.uno-inkomen.org",
    "wof:name":"Uno Inkomen, Sticht",
    "wof:placetype":"venue"
},
  "geometry": {"coordinates":[5.310897,51.691452],"type":"Point"}
}