{
  "type": "Feature",
  "properties": {
    "addr:full":"Traay 135 Driebergen Rysenb Utrecht 3971 GE",
    "addr:housenumber":"135",
    "addr:postcode":"3971",
    "addr:street":"Driebergen Rysenb",
    "iso:country":"NL",
    "sg:address":"Traay 135",
    "sg:city":"Driebergen Rysenb",
    "sg:orig_category":"Kappers",
    "sg:phone":"+31 343 513 134",
    "sg:postcode":"3971 GE",
    "sg:province":"Utrecht",
    "wof:name":"Miranda'S Haarmode",
    "wof:placetype":"venue"
},
  "geometry": {"coordinates":[5.288734,52.054501],"type":"Point"}
}