{
  "type": "Feature",
  "properties": {
    "addr:full":"Walgtsestr 26A Varik Gelderland 4064 CL",
    "addr:housenumber":"26a",
    "addr:postcode":"4064",
    "addr:street":"Walgtsestr;Gelderland",
    "iso:country":"NL",
    "sg:address":"Walgtsestr 26A",
    "sg:city":"Varik",
    "sg:orig_category":"Peuterspeelzalen",
    "sg:phone":"+31 344 651 727",
    "sg:postcode":"4064 CL",
    "sg:province":"Gelderland",
    "wof:name":"Olifantje, 'T",
    "wof:placetype":"venue"
},
  "geometry": {"coordinates":[5.364522,51.821236],"type":"Point"}
}