{
  "type": "Feature",
  "properties": {
    "addr:full":"W A Scholtenstr 15 Assen Provincie Drenthe 9403 AJ",
    "addr:housenumber":"15",
    "addr:postcode":"9403 aj",
    "addr:street":"W A Scholtenstr;Provincie Drenthe",
    "iso:country":"NL",
    "sg:address":"W A Scholtenstr 15",
    "sg:city":"Assen",
    "sg:orig_category":"Verpakkingsbedrijven",
    "sg:phone":"+31 592 377 111",
    "sg:postcode":"9403 AJ",
    "sg:province":"Provincie Drenthe",
    "sg:website":"http://www.multa.nl",
    "wof:name":"Multa Bedrijven",
    "wof:placetype":"venue"
},
  "geometry": {"coordinates":[6.573584,53.006466],"type":"Point"}
}