{
  "type": "Feature",
  "properties": {
    "addr:full":"Sterkenburg 4 Leusden Utrecht 3834 BB",
    "addr:housenumber":"4",
    "addr:postcode":"3834 bb",
    "addr:street":"Sterkenburg",
    "iso:country":"NL",
    "sg:address":"Sterkenburg 4",
    "sg:city":"Leusden",
    "sg:orig_category":"Beeldende Kunstenaars",
    "sg:phone":"+31 33 495 0315",
    "sg:postcode":"3834 BB",
    "sg:province":"Utrecht",
    "wof:name":"Hoogenraad, M F",
    "wof:placetype":"venue"
},
  "geometry": {"coordinates":[5.431603,52.127583],"type":"Point"}
}