{
  "type": "Feature",
  "properties": {
    "addr:full":"Hoogstraat 13 Bergen Op Zoom Noord-Brabant 4611 MS",
    "addr:housenumber":"13",
    "addr:postcode":"4611 ms",
    "addr:street":"Hoogstraat",
    "iso:country":"NL",
    "sg:address":"Hoogstraat 13",
    "sg:city":"Bergen Op Zoom",
    "sg:orig_category":"Artsen And Specialisten",
    "sg:phone":"+31 164 233 167",
    "sg:postcode":"4611 MS",
    "sg:province":"Noord-Brabant",
    "wof:name":"Ij.J.J. Jungerling",
    "wof:placetype":"venue"
},
  "geometry": {"coordinates":[4.288218,51.493591],"type":"Point"}
}