{
  "type": "Feature",
  "properties": {
    "iso:country":"NL",
    "sg:address":"Singel 420",
    "sg:city":"Amsterdam",
    "sg:classifiers":[
        {
            "category":"Travel",
            "subcategory":"Hotels & Motels",
            "type":"Entertainment"
        }
    ],
    "sg:phone":"+31 20 625 8673",
    "sg:postcode":"1016 AK",
    "sg:province":"Noord-Holland",
    "wof:name":"Singel Suite",
    "wof:placetype":"venue"
},
  "geometry": {"coordinates":[4.88752,52.368752],"type":"Point"}
}