{
  "type": "Feature",
  "properties": {
    "addr:full":"Singel 420 Amsterdam Noord-Holland 1016 AK",
    "addr:housenumber":"420",
    "addr:postcode":"1016 ak",
    "addr:street":"Singel",
    "iso:country":"NL",
    "sg:address":"Singel 420",
    "sg:city":"Amsterdam",
    "sg:classifiers":[
        {
            "category":"Travel",
            "subcategory":"Hotels & Motels",
            "type":"Entertainment"
        }
    ],
    "sg:phone":"+31 20 625 8673",
    "sg:postcode":"1016 AK",
    "sg:province":"Noord-Holland",
    "wof:name":"Singel Suite",
    "wof:placetype":"venue"
},
  "geometry": {"coordinates":[4.88752,52.368752],"type":"Point"}
}