{
  "type": "Feature",
  "properties": {
    "addr:full":"Haagwg 165 Breda North Brabant 4812 XC",
    "addr:housenumber":"165",
    "addr:postcode":"4812 xc",
    "iso:country":"NL",
    "sg:address":"Haagwg 165",
    "sg:city":"Breda",
    "sg:orig_category":"Koeriersdiensten",
    "sg:phone":"+31 6 11017097",
    "sg:postcode":"4812 XC",
    "sg:province":"North Brabant",
    "wof:name":"Quick & Quality",
    "wof:placetype":"venue"
},
  "geometry": {"coordinates":[4.756318,51.581329],"type":"Point"}
}