{
  "type": "Feature",
  "properties": {
    "iso:country":"NL",
    "sg:address":"Assendorperstraat 166",
    "sg:city":"Zwolle",
    "sg:orig_category":"Verlichting And Huishoudartikelen",
    "sg:phone":"+31 38 421 7212",
    "sg:postcode":"8012 CD",
    "sg:province":"NL.08",
    "wof:name":"Marskramer",
    "wof:placetype":"venue"
},
  "geometry": {"coordinates":[6.103986,52.503956],"type":"Point"}
}