{
  "type": "Feature",
  "properties": {
    "addr:full":"Landjuweel 16-5 Veenendaal Utrecht 3905 PG",
    "addr:housenumber":"16-5",
    "addr:postcode":"3905 pg",
    "addr:street":"Landjuweel",
    "iso:country":"NL",
    "sg:address":"Landjuweel 16-5",
    "sg:city":"Veenendaal",
    "sg:orig_category":"Verenigingen En Stichtingen",
    "sg:phone":"+31 318 519 076",
    "sg:postcode":"3905 PG",
    "sg:province":"Utrecht",
    "wof:name":"Cpov, Sticht",
    "wof:placetype":"venue"
},
  "geometry": {"coordinates":[5.550676,52.039665],"type":"Point"}
}