{
  "type": "Feature",
  "properties": {
    "addr:full":"Lindenln 1+3 Baarn Utrecht 3741 WN",
    "addr:housenumber":"1 + 3",
    "addr:postcode":"3741 wn",
    "addr:street":"Lindenln",
    "iso:country":"NL",
    "sg:address":"Lindenln 1+3",
    "sg:city":"Baarn",
    "sg:orig_category":"Kappers",
    "sg:phone":"+31 35 541 4000",
    "sg:postcode":"3741 WN",
    "sg:province":"Utrecht",
    "wof:name":"Kooy",
    "wof:placetype":"venue"
},
  "geometry": {"coordinates":[5.292121,52.21101],"type":"Point"}
}