{
  "type": "Feature",
  "properties": {
    "addr:full":"Joubertstr 15 Amsterdam Noord-Holland 1091 XN",
    "addr:housenumber":"15",
    "addr:postcode":"1091 xn",
    "addr:street":"Joubertstr",
    "iso:country":"NL",
    "sg:address":"Joubertstr 15",
    "sg:city":"Amsterdam",
    "sg:orig_category":"Verenigingsgebouwen",
    "sg:phone":"+31 20 694 0652",
    "sg:postcode":"1091 XN",
    "sg:province":"Noord-Holland",
    "wof:name":"Marokkaans Sociaal Cultureel Centrum",
    "wof:placetype":"venue"
},
  "geometry": {"coordinates":[4.917219,52.353275],"type":"Point"}
}