{
  "type": "Feature",
  "properties": {
    "addr:full":"Hazenspoor 11 Maasbracht Limburg 6051 AB",
    "addr:housenumber":"11",
    "addr:postcode":"6051 ab",
    "addr:street":"Hazenspoor",
    "iso:country":"NL",
    "sg:address":"Hazenspoor 11",
    "sg:city":"Maasbracht",
    "sg:classifiers":[
        {
            "category":"Home & Garden",
            "subcategory":"Hardware",
            "type":"Retail Goods"
        }
    ],
    "sg:phone":"+31 475 464 340",
    "sg:postcode":"6051 AB",
    "sg:province":"Limburg",
    "sg:tags":[
        "machine",
        "-",
        "metaalbewerking"
    ],
    "wof:name":"Jareco",
    "wof:placetype":"venue"
},
  "geometry": {"coordinates":[5.896053,51.151127],"type":"Point"}
}