{
  "type": "Feature",
  "properties": {
    "addr:full":"Raadhuisplein 3 Maastricht Limburg 6226 GN",
    "addr:housenumber":"3",
    "addr:postcode":"6226 gn",
    "addr:street":"Raadhuisplein",
    "iso:country":"NL",
    "sg:address":"Raadhuisplein 3",
    "sg:city":"Maastricht",
    "sg:classifiers":[
        {
            "category":"Professional",
            "subcategory":"Accounting & Tax Preparation",
            "type":"Services"
        }
    ],
    "sg:phone":"+31 43 363 5111",
    "sg:postcode":"6226 GN",
    "sg:province":"Limburg",
    "sg:tags":[
        "accountant"
    ],
    "wof:name":"Accountancy P.A.A. Kostons",
    "wof:placetype":"venue"
},
  "geometry": {"coordinates":[5.726698,50.844646],"type":"Point"}
}