{
  "type": "Feature",
  "properties": {
    "addr:full":"Populierenhof 74 Sliedrecht Zuid-Holland 3363 HN",
    "addr:housenumber":"74",
    "addr:postcode":"3363 hn",
    "addr:street":"Populierenhof",
    "iso:country":"NL",
    "sg:address":"Populierenhof 74",
    "sg:city":"Sliedrecht",
    "sg:orig_category":"Kappers",
    "sg:phone":"+31 184 413 445",
    "sg:postcode":"3363 HN",
    "sg:province":"Zuid-Holland",
    "wof:name":"Priscilla Rombout, Haarstudio",
    "wof:placetype":"venue"
},
  "geometry": {"coordinates":[4.760591,51.826267],"type":"Point"}
}