{
  "type": "Feature",
  "properties": {
    "addr:full":"Pastoor Schoenmaekerstraat 44 Geleen Limburg 6163 BW",
    "addr:housenumber":"44",
    "addr:postcode":"6163 bw",
    "addr:street":"Pastoor Schoenmaekerstraat",
    "iso:country":"NL",
    "sg:address":"Pastoor Schoenmaekerstraat 44",
    "sg:city":"Geleen",
    "sg:orig_category":"Alternatieve Geneeskunde",
    "sg:phone":"+31 46 474 7106",
    "sg:postcode":"6163 BW",
    "sg:province":"Limburg",
    "wof:name":"Schoonheidsalon Olga Claassen",
    "wof:placetype":"venue"
},
  "geometry": {"coordinates":[5.818841,50.98357],"type":"Point"}
}