{
  "type": "Feature",
  "properties": {
    "iso:country":"NL",
    "sg:address":"Wooldrikswg 100",
    "sg:city":"Enschede",
    "sg:orig_category":"Loodgieters",
    "sg:phone":"+31 53 433 7031",
    "sg:postcode":"7512 AV",
    "sg:province":"NL.08",
    "sg:website":"http://www.velo-vd-bij.nl",
    "wof:name":"Velo Van Der Bij Bv",
    "wof:placetype":"venue"
},
  "geometry": {"coordinates":[6.891625,52.214691],"type":"Point"}
}