{
  "type": "Feature",
  "properties": {
    "iso:country":"NL",
    "sg:address":"Roerdomphof 4",
    "sg:city":"Delft",
    "sg:orig_category":"Glas, Porselein En Aardewerk",
    "sg:phone":"+31 15 262 3602",
    "sg:postcode":"2623 NP",
    "sg:province":"Zuid-Holland",
    "wof:name":"Multispect",
    "wof:placetype":"venue"
},
  "geometry": {"coordinates":[4.358341,51.98175],"type":"Point"}
}