{
  "type": "Feature",
  "properties": {
    "addr:full":"Boeweg 49 Beverwijk Noord-Holland 1943 JM",
    "addr:housenumber":"49",
    "addr:postcode":"1943 jm",
    "addr:street":"Boeweg",
    "iso:country":"NL",
    "sg:address":"Boeweg 49",
    "sg:city":"Beverwijk",
    "sg:orig_category":"Huishoudapparatuur, Televisies And Radio'S",
    "sg:phone":"+31 251 227 265",
    "sg:postcode":"1943 JM",
    "sg:province":"Noord-Holland",
    "wof:name":"C. Smit En Zoon",
    "wof:placetype":"venue"
},
  "geometry": {"coordinates":[4.652822,52.486595],"type":"Point"}
}