{
  "type": "Feature",
  "properties": {
    "addr:full":"Groentje 1 Breda Noord-Brabant 4814 TH",
    "addr:housenumber":"1",
    "addr:postcode":"4814 th",
    "addr:street":"Groentje",
    "iso:country":"NL",
    "sg:address":"Groentje 1",
    "sg:city":"Breda",
    "sg:orig_category":"Herenkleding",
    "sg:phone":"+31 76 515 4010",
    "sg:postcode":"4814 TH",
    "sg:province":"Noord-Brabant",
    "wof:name":"Jenje, Hans",
    "wof:placetype":"venue"
},
  "geometry": {"coordinates":[4.746713,51.591137],"type":"Point"}
}