{
  "type": "Feature",
  "properties": {
    "iso:country":"NL",
    "sg:address":"Warkensewg 3",
    "sg:city":"Warnsveld",
    "sg:orig_category":"Adviesbureaus Bedrijfsorganisatie",
    "sg:phone":"+31 575 432 122",
    "sg:postcode":"7231 PT",
    "sg:province":"Gelderland",
    "wof:name":"Pr Woodward Bv",
    "wof:placetype":"venue"
},
  "geometry": {"coordinates":[6.288448,52.133091],"type":"Point"}
}