{
  "type": "Feature",
  "properties": {
    "iso:country":"NL",
    "sg:address":"Westzijde 55",
    "sg:city":"Zaandam",
    "sg:orig_category":"Huishoudapparatuur, Televisies And Radio'S",
    "sg:phone":"+31 75 614 0790",
    "sg:postcode":"1506 EB",
    "sg:province":"North Holland",
    "wof:name":"Bcc Elektro Speciaalzaken",
    "wof:placetype":"venue"
},
  "geometry": {"coordinates":[4.820478,52.443462],"type":"Point"}
}