{
  "type": "Feature",
  "properties": {
    "addr:full":"Postbus 1082 Emmen Provincie Drenthe 7801 BB",
    "addr:housenumber":"1082",
    "addr:postcode":"7801 bb",
    "addr:street":"Postbus;Provincie Drenthe",
    "iso:country":"NL",
    "sg:address":"Postbus 1082",
    "sg:city":"Emmen",
    "sg:orig_category":"Verenigingen En Stichtingen",
    "sg:phone":"+31 591 622 226",
    "sg:postcode":"7801 BB",
    "sg:province":"Provincie Drenthe",
    "wof:name":"Huurdersfed",
    "wof:placetype":"venue"
},
  "geometry": {"coordinates":[6.89971,52.795959],"type":"Point"}
}