{
  "type": "Feature",
  "properties": {
    "addr:full":"De Vyvers 45 Dwingeloo Drenthe 7991 BV",
    "addr:housenumber":"45",
    "addr:postcode":"7991 bv",
    "iso:country":"NL",
    "sg:address":"De Vyvers 45",
    "sg:city":"Dwingeloo",
    "sg:orig_category":"Voetbalverenigingen",
    "sg:phone":"+31 521 592 933",
    "sg:postcode":"7991 BV",
    "sg:province":"Drenthe",
    "wof:name":"Dwingeloo Vv",
    "wof:placetype":"venue"
},
  "geometry": {"coordinates":[6.370522,52.836433],"type":"Point"}
}