{
  "type": "Feature",
  "properties": {
    "addr:full":"Hattemln 107 S Gravenhage Zuid-Holland 2573 WJ",
    "addr:housenumber":"107;gravenhage",
    "addr:postcode":"2573 wj",
    "addr:street":"S",
    "iso:country":"NL",
    "sg:address":"Hattemln 107",
    "sg:city":"S Gravenhage",
    "sg:orig_category":"Adviesbureaus Bedrijfsorganisatie",
    "sg:phone":"+31 6 55323369",
    "sg:postcode":"2573 WJ",
    "sg:province":"Zuid-Holland",
    "wof:name":"M-I Services",
    "wof:placetype":"venue"
},
  "geometry": {"coordinates":[4.2844,52.064911],"type":"Point"}
}