{
  "type": "Feature",
  "properties": {
    "addr:full":"Deekland 6 Sneek Friesland 8607 KK",
    "addr:housenumber":"6",
    "addr:postcode":"8607 kk",
    "addr:street":"Deekland",
    "iso:country":"NL",
    "sg:address":"Deekland 6",
    "sg:city":"Sneek",
    "sg:orig_category":"Bloemen And Planten",
    "sg:phone":"+31 515 422 800",
    "sg:postcode":"8607 KK",
    "sg:province":"Friesland",
    "wof:name":"Fa. Ruis-Houtman Bloemenhandel",
    "wof:placetype":"venue"
},
  "geometry": {"coordinates":[5.671344,53.016735],"type":"Point"}
}