{
  "type": "Feature",
  "properties": {
    "addr:full":"Scheppery 4 Ten Boer Groningen 9791 LV",
    "addr:housenumber":"4",
    "addr:postcode":"boer;9791",
    "addr:street":"Scheppery",
    "iso:country":"NL",
    "sg:address":"Scheppery 4",
    "sg:city":"Ten Boer",
    "sg:orig_category":"Scheepsstofferingen",
    "sg:phone":"+31 50 302 2322",
    "sg:postcode":"9791 LV",
    "sg:province":"Groningen",
    "wof:name":"Wimet",
    "wof:placetype":"venue"
},
  "geometry": {"coordinates":[6.701103,53.279301],"type":"Point"}
}