{
  "type": "Feature",
  "properties": {
    "addr:full":"Akerkhof 13 Groningen Groningen 9712 BA",
    "addr:housenumber":"13",
    "addr:postcode":"9712 ba",
    "addr:street":"Akerkhof",
    "iso:country":"NL",
    "sg:address":"Akerkhof 13",
    "sg:city":"Groningen",
    "sg:orig_category":"Makelaars En Adviseurs Onroerende Goederen",
    "sg:phone":"+31 50 318 4080",
    "sg:postcode":"9712 BA",
    "sg:province":"Groningen",
    "sg:website":"http://www.lagro.nl",
    "wof:name":"Lagro Ebens Makelaardij",
    "wof:placetype":"venue"
},
  "geometry": {"coordinates":[6.563174,53.217064],"type":"Point"}
}