{
  "type": "Feature",
  "properties": {
    "addr:full":"Produktiewg 4 Roden Drenthe 9301 ZS",
    "addr:housenumber":"4",
    "addr:postcode":"9301 zs",
    "addr:street":"Produktiewg",
    "iso:country":"NL",
    "sg:address":"Produktiewg 4",
    "sg:city":"Roden",
    "sg:orig_category":"Geluidsisolatie",
    "sg:phone":"+31 50 501 2525",
    "sg:postcode":"9301 ZS",
    "sg:province":"Drenthe",
    "sg:website":"http://www.demoed.nl",
    "wof:name":"Moed, De",
    "wof:placetype":"venue"
},
  "geometry": {"coordinates":[6.446452,53.148998],"type":"Point"}
}