{
  "type": "Feature",
  "properties": {
    "addr:full":"Dorpsstr 48 Terschelling Hoorn Friesland 8896 JE",
    "addr:housenumber":"48",
    "addr:postcode":"8896 je",
    "addr:street":"Dorpsstr",
    "iso:country":"NL",
    "sg:address":"Dorpsstr 48",
    "sg:city":"Terschelling Hoorn",
    "sg:orig_category":"Vakantieverblijven",
    "sg:phone":"+31 562 448 769",
    "sg:postcode":"8896 JE",
    "sg:province":"Friesland",
    "wof:name":"Mier",
    "wof:placetype":"venue"
},
  "geometry": {"coordinates":[5.342486,53.39666],"type":"Point"}
}