{
  "type": "Feature",
  "properties": {
    "addr:full":"Helftheuvelpassage 258 'S Hertogenbosch Noord-Brabant 5224 AR",
    "addr:housenumber":"258 ' s",
    "addr:postcode":"5224",
    "addr:street":"Helftheuvelpassage",
    "iso:country":"NL",
    "sg:address":"Helftheuvelpassage 258",
    "sg:city":"'S Hertogenbosch",
    "sg:orig_category":"Kantoorartikelen",
    "sg:phone":"+31 73 624 1835",
    "sg:postcode":"5224 AR",
    "sg:province":"Noord-Brabant",
    "wof:name":"Bruna",
    "wof:placetype":"venue"
},
  "geometry": {"coordinates":[5.2663168907,51.6948814392],"type":"Point"}
}