{
  "type": "Feature",
  "properties": {
    "addr:full":"Kuiperpln 35 Ede Gld Gelderland 6713 AX",
    "addr:housenumber":"35",
    "addr:postcode":"6713 ax",
    "addr:street":"Kuiperpln;Gld Gelderland",
    "iso:country":"NL",
    "sg:address":"Kuiperpln 35",
    "sg:city":"Ede Gld",
    "sg:orig_category":"Verlichting",
    "sg:phone":"+31 318 628 705",
    "sg:postcode":"6713 AX",
    "sg:province":"Gelderland",
    "wof:name":"Beter Licht Vof",
    "wof:placetype":"venue"
},
  "geometry": {"coordinates":[5.66902,52.044685],"type":"Point"}
}