{
  "type": "Feature",
  "properties": {
    "addr:full":"Amstelveensewg 1160 Amsterdam Noord-Holland 1081 JW",
    "addr:housenumber":"1160",
    "addr:postcode":"1081 jw",
    "iso:country":"NL",
    "sg:address":"Amstelveensewg 1160",
    "sg:city":"Amsterdam",
    "sg:orig_category":"Koffie- En Theehuizen",
    "sg:phone":"+31 20 642 0681",
    "sg:postcode":"1081 JW",
    "sg:province":"Noord-Holland",
    "sg:website":"http://www.the-border.nl",
    "wof:name":"Border, The",
    "wof:placetype":"venue"
},
  "geometry": {"coordinates":[4.857226,52.321926],"type":"Point"}
}