{
  "type": "Feature",
  "properties": {
    "addr:full":"De Steenbok 10 S Hertogenbosch Noord-Brabant 5215 ME",
    "addr:housenumber":"10",
    "addr:postcode":"5215 me",
    "addr:street":"De Steenbok;S",
    "iso:country":"NL",
    "sg:address":"De Steenbok 10",
    "sg:city":"S Hertogenbosch",
    "sg:orig_category":"Koperslagerijen",
    "sg:phone":"+31 73 691 0710",
    "sg:postcode":"5215 ME",
    "sg:province":"Noord-Brabant",
    "wof:name":"Goldsteen Metal",
    "wof:placetype":"venue"
},
  "geometry": {"coordinates":[5.359747,51.686569],"type":"Point"}
}