{
  "type": "Feature",
  "properties": {
    "addr:full":"Landsheerln 70 Zwolle Overijssel 8016 KH",
    "addr:housenumber":"70",
    "addr:postcode":"8016 kh",
    "addr:street":"Landsheerln",
    "iso:country":"NL",
    "sg:address":"Landsheerln 70",
    "sg:city":"Zwolle",
    "sg:orig_category":"Adviesbureaus Bedrijfsorganisatie",
    "sg:phone":"+31 38 333 3743",
    "sg:postcode":"8016 KH",
    "sg:province":"Overijssel",
    "wof:name":"Boom Management, Van",
    "wof:placetype":"venue"
},
  "geometry": {"coordinates":[6.088738,52.512566],"type":"Point"}
}