{
  "type": "Feature",
  "properties": {
    "addr:full":"Loodstraat 12 Zoetermeer Zuid-Holland 2718 RW",
    "addr:housenumber":"12",
    "addr:postcode":"2718 rw",
    "addr:street":"Loodstraat",
    "iso:country":"NL",
    "sg:address":"Loodstraat 12",
    "sg:city":"Zoetermeer",
    "sg:orig_category":"Diverse Bedrijfsinstallaties Gh",
    "sg:phone":"+31 79 361 8510",
    "sg:postcode":"2718 RW",
    "sg:province":"Zuid-Holland",
    "wof:name":"Djoeneri Hydrauliek Service (Dhs) Bv",
    "wof:placetype":"venue"
},
  "geometry": {"coordinates":[4.511464,52.040619],"type":"Point"}
}