{
  "type": "Feature",
  "properties": {
    "addr:full":"Obriglaan 44 Heiloo Noord-Holland 1852 KB",
    "addr:housenumber":"44",
    "addr:postcode":"1852 kb",
    "addr:street":"Obriglaan",
    "iso:country":"NL",
    "sg:address":"Obriglaan 44",
    "sg:city":"Heiloo",
    "sg:orig_category":"Vertaal- And Tolkenbureaus",
    "sg:phone":"+31 72 533 2073",
    "sg:postcode":"1852 KB",
    "sg:province":"Noord-Holland",
    "wof:name":"Vertaalbureau Vd Bijl Bv",
    "wof:placetype":"venue"
},
  "geometry": {"coordinates":[4.693023,52.603203],"type":"Point"}
}