{
  "type": "Feature",
  "properties": {
    "addr:full":"Almerewg 35 Medemblik North Holland 1671 ND",
    "addr:housenumber":"35",
    "addr:postcode":"1671 nd",
    "addr:street":"Almerewg",
    "iso:country":"NL",
    "sg:address":"Almerewg 35",
    "sg:city":"Medemblik",
    "sg:orig_category":"Koel- En Vrieshuizen",
    "sg:phone":"+31 227 544 563",
    "sg:postcode":"1671 ND",
    "sg:province":"North Holland",
    "wof:name":"Medemblik Bv",
    "wof:placetype":"venue"
},
  "geometry": {"coordinates":[5.093518,52.762501],"type":"Point"}
}