{
  "type": "Feature",
  "properties": {
    "iso:country":"NL",
    "sg:address":"Waterwg 2",
    "sg:city":"Westerland",
    "sg:orig_category":"Watersport-, Sport- And Kampeerbenodigdheden Verhuur",
    "sg:phone":"+31 227 593 426",
    "sg:postcode":"1778 KG",
    "sg:province":"Noord-Holland",
    "wof:name":"F Zoutman",
    "wof:placetype":"venue"
},
  "geometry": {"coordinates":[4.9309659004,52.8890075684],"type":"Point"}
}