{
  "type": "Feature",
  "properties": {
    "addr:full":"Groene Hilledk 199B Rotterdam Zuid-Holland 3073 AD",
    "addr:housenumber":"199b",
    "addr:postcode":"3073 ad",
    "addr:street":"Groene",
    "iso:country":"NL",
    "sg:address":"Groene Hilledk 199B",
    "sg:city":"Rotterdam",
    "sg:orig_category":"Juweliers",
    "sg:phone":"+31 10 215 1080",
    "sg:postcode":"3073 AD",
    "sg:province":"Zuid-Holland",
    "wof:name":"Simmer",
    "wof:placetype":"venue"
},
  "geometry": {"coordinates":[4.50884,51.89233],"type":"Point"}
}