{
  "type": "Feature",
  "properties": {
    "addr:full":"Vd Duynstr 71 Amsterdam Missouri 1051 AT",
    "addr:housenumber":"71",
    "addr:postcode":"1051",
    "iso:country":"NL",
    "sg:address":"Vd Duynstr 71",
    "sg:city":"Amsterdam",
    "sg:orig_category":"Journalisten Freelance",
    "sg:phone":"+31 20 684 9454",
    "sg:postcode":"1051 AT",
    "sg:province":"Missouri",
    "wof:name":"Rob De Blok",
    "wof:placetype":"venue"
},
  "geometry": {"coordinates":[-94.58503,38.350479],"type":"Point"}
}