{
  "type": "Feature",
  "properties": {
    "addr:full":"Esdoornlaan 2 Gorssel Gelderland 7213 WV",
    "addr:housenumber":"2",
    "addr:postcode":"7213 wv",
    "addr:street":"Esdoornlaan;Gelderland",
    "iso:country":"NL",
    "sg:address":"Esdoornlaan 2",
    "sg:city":"Gorssel",
    "sg:orig_category":"Vakantieverblijven",
    "sg:phone":"+31 575 494 746",
    "sg:postcode":"7213 WV",
    "sg:province":"Gelderland",
    "wof:name":"Dilaram",
    "wof:placetype":"venue"
},
  "geometry": {"coordinates":[6.197948,52.202255],"type":"Point"}
}