{
  "type": "Feature",
  "properties": {
    "addr:full":"Graftermeerstr 67 Hoofddorp North Holland 2131 AB",
    "addr:housenumber":"67",
    "addr:postcode":"2131 ab",
    "addr:street":"Graftermeerstr",
    "iso:country":"NL",
    "sg:address":"Graftermeerstr 67",
    "sg:city":"Hoofddorp",
    "sg:orig_category":"Horecabenodigdheden",
    "sg:phone":"+31 23 563 8050",
    "sg:postcode":"2131 AB",
    "sg:province":"North Holland",
    "sg:website":"http://www.delixl.nl",
    "wof:name":"Deli Xl",
    "wof:placetype":"venue"
},
  "geometry": {"coordinates":[4.690674,52.314518],"type":"Point"}
}