{
  "type": "Feature",
  "properties": {
    "addr:full":"Theodoor Schaepkensstr 15 Maastricht Limburg 6221 VX",
    "addr:housenumber":"15",
    "addr:postcode":"6221 vx",
    "iso:country":"NL",
    "sg:address":"Theodoor Schaepkensstr 15",
    "sg:city":"Maastricht",
    "sg:orig_category":"Loodgieterswerk, Verwarming And Sanitaire Installaties",
    "sg:phone":"+31 43 325 4019",
    "sg:postcode":"6221 VX",
    "sg:province":"Limburg",
    "wof:name":"J.A. Wilbers",
    "wof:placetype":"venue"
},
  "geometry": {"coordinates":[5.702942,50.852055],"type":"Point"}
}