{
  "type": "Feature",
  "properties": {
    "addr:full":"Molenstr 77 Oudenbosch North Brabant 4731 HC",
    "addr:housenumber":"77",
    "addr:postcode":"4731 hc",
    "addr:street":"Molenstr",
    "iso:country":"NL",
    "sg:address":"Molenstr 77",
    "sg:city":"Oudenbosch",
    "sg:orig_category":"Woninginrichting",
    "sg:phone":"+31 165 330 206",
    "sg:postcode":"4731 HC",
    "sg:province":"North Brabant",
    "wof:name":"Mol",
    "wof:placetype":"venue"
},
  "geometry": {"coordinates":[4.5250148773,51.58644104],"type":"Point"}
}