{
  "type": "Feature",
  "properties": {
    "iso:country":"NL",
    "sg:address":"Grote Tocht 2",
    "sg:city":"Zaandam",
    "sg:orig_category":"Algemene Werktuigbouw",
    "sg:phone":"+31 75 615 9506",
    "sg:postcode":"1507 CG",
    "sg:province":"Noord-Holland",
    "wof:name":"Metalas Zaandam Bv",
    "wof:placetype":"venue"
},
  "geometry": {"coordinates":[4.811932,52.428551],"type":"Point"}
}