{
  "type": "Feature",
  "properties": {
    "iso:country":"NL",
    "sg:address":"Den Hof 1",
    "sg:city":"Waalre",
    "sg:orig_category":"Juweliers",
    "sg:phone":"+31 40 221 7444",
    "sg:postcode":"5582 JZ",
    "sg:province":"North Brabant",
    "wof:name":"Hooff, Van",
    "wof:placetype":"venue"
},
  "geometry": {"coordinates":[5.475386,51.395565],"type":"Point"}
}