{
  "type": "Feature",
  "properties": {
    "addr:full":"Comriekd 20 Woubrugge Zuid-Holland 2481 AD",
    "addr:housenumber":"20",
    "addr:postcode":"2481 ad",
    "addr:street":"Comriekd",
    "iso:country":"NL",
    "sg:address":"Comriekd 20",
    "sg:city":"Woubrugge",
    "sg:orig_category":"Kappers",
    "sg:phone":"+31 172 518 263",
    "sg:postcode":"2481 AD",
    "sg:province":"Zuid-Holland",
    "wof:name":"Groot, Jan",
    "wof:placetype":"venue"
},
  "geometry": {"coordinates":[4.6395101547,52.1689567566],"type":"Point"}
}