{
  "type": "Feature",
  "properties": {
    "addr:full":"Geerdinkhof 544 Amsterdam Zuidoost Noord-Holland 1103 RJ",
    "addr:housenumber":"544",
    "addr:postcode":"zuidoost;1103 rj",
    "addr:street":"Geerdinkhof",
    "iso:country":"NL",
    "sg:address":"Geerdinkhof 544",
    "sg:city":"Amsterdam Zuidoost",
    "sg:orig_category":"Bedrijfsopleidingen",
    "sg:phone":"+31 20 690 9055",
    "sg:postcode":"1103 RJ",
    "sg:province":"Noord-Holland",
    "sg:website":"http://www.vanderhoogte .nl",
    "wof:name":"Hoogte, Drs F Van Der",
    "wof:placetype":"venue"
},
  "geometry": {"coordinates":[4.978235,52.327335],"type":"Point"}
}