{
  "type": "Feature",
  "properties": {
    "iso:country":"NL",
    "sg:address":"Haagwg 332",
    "sg:city":"Breda",
    "sg:orig_category":"Begrafenisverzorging",
    "sg:phone":"+31 76 565 4055",
    "sg:postcode":"4813 XE",
    "sg:province":"North Brabant",
    "wof:name":"Zuylen",
    "wof:placetype":"venue"
},
  "geometry": {"coordinates":[4.749506,51.579384],"type":"Point"}
}