{
  "type": "Feature",
  "properties": {
    "addr:full":"Bankastraat 54 Utrecht Utrecht 3531 HH",
    "addr:housenumber":"54",
    "addr:postcode":"3531 hh",
    "addr:street":"Bankastraat",
    "iso:country":"NL",
    "sg:address":"Bankastraat 54",
    "sg:city":"Utrecht",
    "sg:orig_category":"Geluidsopnamestudio'S",
    "sg:phone":"+31 30 658 0134",
    "sg:postcode":"3531 HH",
    "sg:province":"Utrecht",
    "wof:name":"Big Orange Music",
    "wof:placetype":"venue"
},
  "geometry": {"coordinates":[5.094218,52.088554],"type":"Point"}
}