{
  "type": "Feature",
  "properties": {
    "addr:full":"Buitenveld 8 Zeeland Noord-Brabant 5411 TR",
    "addr:housenumber":"8",
    "addr:postcode":"5411 tr",
    "addr:street":"Buitenveld",
    "iso:country":"NL",
    "sg:address":"Buitenveld 8",
    "sg:city":"Zeeland",
    "sg:orig_category":"Fotolitho- En Reprografie - Inrichtingen",
    "sg:phone":"+31 486 452 250",
    "sg:postcode":"5411 TR",
    "sg:province":"Noord-Brabant",
    "wof:name":"Kremers",
    "wof:placetype":"venue"
},
  "geometry": {"coordinates":[5.668702,51.69875],"type":"Point"}
}