{
  "type": "Feature",
  "properties": {
    "addr:full":"Langeweg 67 Breskens Zeeland 4511 GB",
    "addr:housenumber":"67",
    "addr:postcode":"4511 gb",
    "addr:street":"Langeweg",
    "iso:country":"NL",
    "sg:address":"Langeweg 67",
    "sg:city":"Breskens",
    "sg:orig_category":"Goederenvervoer Over De Weg",
    "sg:phone":"+31 117 382 000",
    "sg:postcode":"4511 GB",
    "sg:province":"Zeeland",
    "wof:name":"Transportbedrijf Keijmel",
    "wof:placetype":"venue"
},
  "geometry": {"coordinates":[3.550231,51.396774],"type":"Point"}
}