{
  "type": "Feature",
  "properties": {
    "iso:country":"NL",
    "sg:address":"Jansveld 21",
    "sg:city":"Utrecht",
    "sg:orig_category":"Luchtfotografie",
    "sg:phone":"+31 30 231 9658",
    "sg:postcode":"3512 BD",
    "sg:province":"Utrecht",
    "sg:website":"http://www.luchtfotografie.com",
    "wof:name":"Your Captain",
    "wof:placetype":"venue"
},
  "geometry": {"coordinates":[5.120071,52.094048],"type":"Point"}
}