{
  "type": "Feature",
  "properties": {
    "addr:full":"Kruidentuin 2 Barendrecht Zuid-Holland 2991 RK",
    "addr:housenumber":"2",
    "addr:postcode":"2991 rk",
    "addr:street":"Kruidentuin",
    "iso:country":"NL",
    "sg:address":"Kruidentuin 2",
    "sg:city":"Barendrecht",
    "sg:orig_category":"Verzekeringen",
    "sg:phone":"+31 180 612 500",
    "sg:postcode":"2991 RK",
    "sg:province":"Zuid-Holland",
    "wof:name":"Den Hollander Assurantien Bv",
    "wof:placetype":"venue"
},
  "geometry": {"coordinates":[4.545838,51.853367],"type":"Point"}
}