{
  "type": "Feature",
  "properties": {
    "addr:full":"Kerkstraat 4 Koudekerke Zeeland 4371 AP",
    "addr:housenumber":"4",
    "addr:postcode":"4371 ap",
    "addr:street":"Kerkstraat",
    "iso:country":"NL",
    "sg:address":"Kerkstraat 4",
    "sg:city":"Koudekerke",
    "sg:orig_category":"Bloemen And Planten Gh",
    "sg:phone":"+31 118 552 345",
    "sg:postcode":"4371 AP",
    "sg:province":"Zeeland",
    "wof:name":"Bloemen- En Plantenhandel Koudekerke",
    "wof:placetype":"venue"
},
  "geometry": {"coordinates":[3.552422,51.481945],"type":"Point"}
}