{
  "type": "Feature",
  "properties": {
    "addr:full":"V Loostr 28 Ootmarsum NL.08 7631 GM",
    "addr:housenumber":"28;nl.08",
    "addr:postcode":"7631 gm",
    "iso:country":"NL",
    "sg:address":"V Loostr 28",
    "sg:city":"Ootmarsum",
    "sg:orig_category":"Fotojournalisten Freelance",
    "sg:phone":"+31 541 292 867",
    "sg:postcode":"7631 GM",
    "sg:province":"NL.08",
    "wof:name":"Frons",
    "wof:placetype":"venue"
},
  "geometry": {"coordinates":[6.89415,52.406929],"type":"Point"}
}