{
  "type": "Feature",
  "properties": {
    "addr:full":"Leemveld 80 Assen Drenthe 9407 GC",
    "addr:housenumber":"80",
    "addr:postcode":"9407 gc",
    "addr:street":"Leemveld",
    "iso:country":"NL",
    "sg:address":"Leemveld 80",
    "sg:city":"Assen",
    "sg:orig_category":"Fotostudio'S And Fotografen",
    "sg:phone":"+31 592 347 710",
    "sg:postcode":"9407 GC",
    "sg:province":"Drenthe",
    "wof:name":"Anne Froma, Fotografie",
    "wof:placetype":"venue"
},
  "geometry": {"coordinates":[6.553801,53.019173],"type":"Point"}
}