{
  "type": "Feature",
  "properties": {
    "iso:country":"NL",
    "sg:address":"Smitshoek 62",
    "sg:city":"Bergschenhoek",
    "sg:orig_category":"Begrafenisondernemers",
    "sg:phone":"+31 10 529 0097",
    "sg:postcode":"2661 CK",
    "sg:province":"Zuid-Holland",
    "wof:name":"P.J. Van Uden",
    "wof:placetype":"venue"
},
  "geometry": {"coordinates":[4.497442,51.988453],"type":"Point"}
}