{
  "type": "Feature",
  "properties": {
    "addr:full":"Mynbouwpln 11 Delft Zuid-Holland 2628 RT",
    "addr:housenumber":"11",
    "addr:postcode":"2628 rt",
    "addr:street":"Mynbouwpln",
    "iso:country":"NL",
    "sg:address":"Mynbouwpln 11",
    "sg:city":"Delft",
    "sg:orig_category":"Adviesbureaus",
    "sg:phone":"+31 15 256 7511",
    "sg:postcode":"2628 RT",
    "sg:province":"Zuid-Holland",
    "sg:website":"http://www.oli.tudelft.nl/~upd",
    "wof:name":"Unipartners Delft",
    "wof:placetype":"venue"
},
  "geometry": {"coordinates":[4.367201,52.006405],"type":"Point"}
}