{
  "type": "Feature",
  "properties": {
    "addr:full":"Alver 29 Avenhorn North Holland 1633 DL",
    "addr:housenumber":"29",
    "addr:postcode":"1633 dl",
    "addr:street":"Alver",
    "iso:country":"NL",
    "sg:address":"Alver 29",
    "sg:city":"Avenhorn",
    "sg:orig_category":"Kappers",
    "sg:phone":"+31 229 544 077",
    "sg:postcode":"1633 DL",
    "sg:province":"North Holland",
    "wof:name":"Mariola",
    "wof:placetype":"venue"
},
  "geometry": {"coordinates":[4.948587,52.622395],"type":"Point"}
}