{
  "type": "Feature",
  "properties": {
    "addr:full":"Reigerln 1A Zeist Utrecht 3704 XE",
    "addr:housenumber":"1a",
    "addr:postcode":"3704 xe",
    "addr:street":"Reigerln",
    "iso:country":"NL",
    "sg:address":"Reigerln 1A",
    "sg:city":"Zeist",
    "sg:orig_category":"Peuterspeelzalen",
    "sg:phone":"+31 30 695 1821",
    "sg:postcode":"3704 XE",
    "sg:province":"Utrecht",
    "wof:name":"Kroost, De",
    "wof:placetype":"venue"
},
  "geometry": {"coordinates":[5.24387,52.08548],"type":"Point"}
}