{
  "type": "Feature",
  "properties": {
    "addr:full":"Clercstr 34 Brunssum Limburg 6441 CT",
    "addr:housenumber":"34",
    "addr:postcode":"6441 ct",
    "addr:street":"Clercstr",
    "iso:country":"NL",
    "sg:address":"Clercstr 34",
    "sg:city":"Brunssum",
    "sg:classifiers":[
        {
            "category":"Personal",
            "subcategory":"Nail Salon",
            "type":"Services"
        }
    ],
    "sg:phone":"+31 45 525 0917",
    "sg:postcode":"6441 CT",
    "sg:province":"Limburg",
    "sg:tags":[
        "pedicure"
    ],
    "wof:name":"Pedimass",
    "wof:placetype":"venue"
},
  "geometry": {"coordinates":[5.966538,50.951618],"type":"Point"}
}