{
  "type": "Feature",
  "properties": {
    "addr:full":"Utrechtsestraat 129 Amsterdam North Holland 1017 VM",
    "addr:housenumber":"129",
    "addr:postcode":"1017 vm",
    "addr:street":"Utrechtsestraat",
    "iso:country":"NL",
    "sg:address":"Utrechtsestraat 129",
    "sg:city":"Amsterdam",
    "sg:orig_category":"Verlichting And Huishoudartikelen",
    "sg:phone":"+31 20 420 1374",
    "sg:postcode":"1017 VM",
    "sg:province":"North Holland",
    "wof:name":"Fa Aardewerk De Kom",
    "wof:placetype":"venue"
},
  "geometry": {"coordinates":[4.899328,52.361748],"type":"Point"}
}