{
  "type": "Feature",
  "properties": {
    "addr:full":"L J Costerstr 5 Oud Beyerland South Holland 3261 LH",
    "addr:housenumber":"5",
    "addr:postcode":"3261 lh",
    "addr:street":"L;Costerstr;Oud Beyerland",
    "iso:country":"NL",
    "sg:address":"L J Costerstr 5",
    "sg:city":"Oud Beyerland",
    "sg:classifiers":[
        {
            "category":"Shopping",
            "subcategory":"Gifts & Souvenirs",
            "type":"Retail Goods"
        }
    ],
    "sg:phone":"+31 186 619 788",
    "sg:postcode":"3261 LH",
    "sg:province":"South Holland",
    "sg:tags":[
        "wens-",
        "en",
        "prentbriefkaarten"
    ],
    "wof:name":"Royal Licence Bv",
    "wof:placetype":"venue"
},
  "geometry": {"coordinates":[4.4280600548,51.8078918457],"type":"Point"}
}