{
  "type": "Feature",
  "properties": {
    "iso:country":"NL",
    "sg:address":"Bornsestr 86",
    "sg:city":"Hengelo Ov",
    "sg:orig_category":"Kunsthandel",
    "sg:phone":"+31 74 250 3699",
    "sg:postcode":"7556 BH",
    "sg:province":"Overijssel",
    "wof:name":"Haarhuis",
    "wof:placetype":"venue"
},
  "geometry": {"coordinates":[6.789516,52.270248],"type":"Point"}
}