{
  "type": "Feature",
  "properties": {
    "addr:full":"Gasthuisstraat 19 Steenwijk NL.08 8331 JM",
    "addr:housenumber":"19;nl.08",
    "addr:postcode":"8331 jm",
    "addr:street":"Gasthuisstraat",
    "iso:country":"NL",
    "sg:address":"Gasthuisstraat 19",
    "sg:city":"Steenwijk",
    "sg:orig_category":"Boekhandels",
    "sg:phone":"+31 521 515 439",
    "sg:postcode":"8331 JM",
    "sg:province":"NL.08",
    "wof:name":"Kerkvoorde & Hollander",
    "wof:placetype":"venue"
},
  "geometry": {"coordinates":[6.115635,52.786015],"type":"Point"}
}