{
  "type": "Feature",
  "properties": {
    "addr:full":"Tragelwg 1 Lobith Gelderland 6915 SE",
    "addr:housenumber":"1",
    "addr:postcode":"6915",
    "addr:street":"Tragelwg;Gelderland;Se",
    "iso:country":"NL",
    "sg:address":"Tragelwg 1",
    "sg:city":"Lobith",
    "sg:orig_category":"Verenigingsgebouwen",
    "sg:phone":"+31 316 542 794",
    "sg:postcode":"6915 SE",
    "sg:province":"Gelderland",
    "sg:website":"http://www.jipliemers.nl",
    "wof:name":"Sfinx, De",
    "wof:placetype":"venue"
},
  "geometry": {"coordinates":[6.110564,51.858284],"type":"Point"}
}