{
  "type": "Feature",
  "properties": {
    "addr:full":"Mr Gerbrandysngl 45 Arnhem Gelderland 6836 KS",
    "addr:housenumber":"45",
    "addr:postcode":"6836 ks",
    "iso:country":"NL",
    "sg:address":"Mr Gerbrandysngl 45",
    "sg:city":"Arnhem",
    "sg:orig_category":"Verenigingen En Stichtingen",
    "sg:phone":"+31 26 320 0600",
    "sg:postcode":"6836 KS",
    "sg:province":"Gelderland",
    "wof:name":"Koonings Jaght Dependance, 'S",
    "wof:placetype":"venue"
},
  "geometry": {"coordinates":[5.898468,51.943027],"type":"Point"}
}