{
  "type": "Feature",
  "properties": {
    "addr:full":"Dillenburgpln 50 Ridderkerk South Holland 2983 CC",
    "addr:housenumber":"50",
    "addr:postcode":"2983 cc",
    "addr:street":"Dillenburgpln",
    "iso:country":"NL",
    "sg:address":"Dillenburgpln 50",
    "sg:city":"Ridderkerk",
    "sg:orig_category":"Bloemen En Planten",
    "sg:phone":"+31 180 410 660",
    "sg:postcode":"2983 CC",
    "sg:province":"South Holland",
    "wof:name":"Dillenburg",
    "wof:placetype":"venue"
},
  "geometry": {"coordinates":[4.605373,51.88467],"type":"Point"}
}