{
  "type": "Feature",
  "properties": {
    "addr:full":"Aalsmeerderwg 320 Aalsmeer Noord-Holland 1432 CZ",
    "addr:housenumber":"320",
    "addr:postcode":"aalsmeer;1432",
    "iso:country":"NL",
    "sg:address":"Aalsmeerderwg 320",
    "sg:city":"Aalsmeer",
    "sg:orig_category":"Adviesbureaus Bedrijfsorganisatie",
    "sg:phone":"+31 297 342 113",
    "sg:postcode":"1432 CZ",
    "sg:province":"Noord-Holland",
    "wof:name":"Jip Bv",
    "wof:placetype":"venue"
},
  "geometry": {"coordinates":[4.802987,52.282326],"type":"Point"}
}