{
  "type": "Feature",
  "properties": {
    "iso:country":"NL",
    "sg:address":"Oysedwwg 4",
    "sg:city":"Wilp Gld",
    "sg:orig_category":"Vertaalbureaus",
    "sg:phone":"+31 571 261 581",
    "sg:postcode":"7384 CG",
    "sg:province":"Gelderland",
    "sg:website":"http://www.natives.nl",
    "wof:name":"Natives",
    "wof:placetype":"venue"
},
  "geometry": {"coordinates":[6.171654,52.207424],"type":"Point"}
}