{
  "type": "Feature",
  "properties": {
    "addr:full":"Dr Berlageln 24 Eindhoven Noord-Brabant 5622 HD",
    "addr:housenumber":"24",
    "addr:postcode":"5622 hd",
    "iso:country":"NL",
    "sg:address":"Dr Berlageln 24",
    "sg:city":"Eindhoven",
    "sg:orig_category":"Verenigingen En Stichtingen",
    "sg:phone":"+31 40 233 3250",
    "sg:postcode":"5622 HD",
    "sg:province":"Noord-Brabant",
    "wof:name":"Skpo",
    "wof:placetype":"venue"
},
  "geometry": {"coordinates":[5.46291,51.459381],"type":"Point"}
}