{
  "type": "Feature",
  "properties": {
    "iso:country":"NL",
    "sg:address":"Hunze 244",
    "sg:city":"Drachten",
    "sg:orig_category":"Ballonnen - Fabrieken En Groothandel",
    "sg:phone":"+31 512 511 063",
    "sg:postcode":"9204 BX",
    "sg:province":"Friesland",
    "wof:name":"Ballonnenspecialist, De",
    "wof:placetype":"venue"
},
  "geometry": {"coordinates":[6.075375,53.100761],"type":"Point"}
}