{
  "type": "Feature",
  "properties": {
    "addr:full":"Binnenhof 7 Almelo Overijssel 7608 KG",
    "addr:housenumber":"7",
    "addr:postcode":"7608 kg",
    "addr:street":"Binnenhof",
    "iso:country":"NL",
    "sg:address":"Binnenhof 7",
    "sg:city":"Almelo",
    "sg:orig_category":"Kappers",
    "sg:phone":"+31 546 863 260",
    "sg:postcode":"7608 KG",
    "sg:province":"Overijssel",
    "wof:name":"Kapsalon Walter'S Haarmode",
    "wof:placetype":"venue"
},
  "geometry": {"coordinates":[6.6783928871,52.3792953491],"type":"Point"}
}