{
  "type": "Feature",
  "properties": {
    "iso:country":"NL",
    "sg:address":"St Martinusln 121",
    "sg:city":"Voorburg",
    "sg:orig_category":"Onderhoudswerken",
    "sg:phone":"+31 70 386 8745",
    "sg:postcode":"2273 AS",
    "sg:province":"Zuid-Holland",
    "wof:name":"Waal, P De",
    "wof:placetype":"venue"
},
  "geometry": {"coordinates":[4.367262,52.080288],"type":"Point"}
}