{
  "type": "Feature",
  "properties": {
    "addr:full":"Jagtlustweg 6 Hantumeruitburen Provincie Friesland 9146 CJ",
    "addr:housenumber":"6",
    "addr:postcode":"9146 cj",
    "addr:street":"Jagtlustweg;Provincie Friesland",
    "iso:country":"NL",
    "sg:address":"Jagtlustweg 6",
    "sg:city":"Hantumeruitburen",
    "sg:orig_category":"Levende Dieren Gh",
    "sg:phone":"+31 519 241 883",
    "sg:postcode":"9146 CJ",
    "sg:province":"Provincie Friesland",
    "wof:name":"A. En G. Kingma",
    "wof:placetype":"venue"
},
  "geometry": {"coordinates":[6.020571,53.353645],"type":"Point"}
}