{
  "type": "Feature",
  "properties": {
    "addr:full":"Pilarenln 1 Noordwykerhout Zuid-Holland 2211 LH",
    "addr:housenumber":"1",
    "addr:postcode":"2211 lh",
    "addr:street":"Pilarenln",
    "iso:country":"NL",
    "sg:address":"Pilarenln 1",
    "sg:city":"Noordwykerhout",
    "sg:orig_category":"Mensendieck - Oefentherapeuten",
    "sg:phone":"+31 252 370 843",
    "sg:postcode":"2211 LH",
    "sg:province":"Zuid-Holland",
    "wof:name":"Scheepstra, K",
    "wof:placetype":"venue"
},
  "geometry": {"coordinates":[4.495251,52.254681],"type":"Point"}
}