{
  "type": "Feature",
  "properties": {
    "iso:country":"NL",
    "sg:address":"Bestevaerstraat 2",
    "sg:city":"Alkmaar",
    "sg:orig_category":"Kantoorartikelen",
    "sg:phone":"+31 72 540 1521",
    "sg:postcode":"1813 PA",
    "sg:province":"Noord-Holland",
    "wof:name":"De Graaf En Zn Bv",
    "wof:placetype":"venue"
},
  "geometry": {"coordinates":[4.7641692162,52.6235466003],"type":"Point"}
}