{
  "type": "Feature",
  "properties": {
    "addr:full":"Middelw 94 Uitgeest Noord-Holland 1911 EJ",
    "addr:housenumber":"94",
    "addr:postcode":"1911 ej",
    "addr:street":"Middelw",
    "iso:country":"NL",
    "sg:address":"Middelw 94",
    "sg:city":"Uitgeest",
    "sg:orig_category":"Schoenen - Reparaties",
    "sg:phone":"+31 251 312 604",
    "sg:postcode":"1911 EJ",
    "sg:province":"Noord-Holland",
    "wof:name":"Heine, H",
    "wof:placetype":"venue"
},
  "geometry": {"coordinates":[4.709754,52.524323],"type":"Point"}
}