{
  "type": "Feature",
  "properties": {
    "iso:country":"NL",
    "sg:address":"Amaliastraat 9",
    "sg:city":"'S Gravenhage",
    "sg:orig_category":"Diverse Consumentenartikelen Gh",
    "sg:phone":"+31 70 365 8834",
    "sg:postcode":"2514 JC",
    "sg:province":"South Holland",
    "wof:name":"Rtc Rabbani Trading & Consulting Bv",
    "wof:placetype":"venue"
},
  "geometry": {"coordinates":[4.306372,52.083511],"type":"Point"}
}