{
  "type": "Feature",
  "properties": {
    "addr:full":"Heuvelpoort 377 Tilburg North Brabant 5038 DX",
    "addr:housenumber":"377",
    "addr:postcode":"5038 dx",
    "addr:street":"Heuvelpoort",
    "iso:country":"NL",
    "sg:address":"Heuvelpoort 377",
    "sg:city":"Tilburg",
    "sg:orig_category":"Zuivelproducten",
    "sg:phone":"+31 13 535 6098",
    "sg:postcode":"5038 DX",
    "sg:province":"North Brabant",
    "wof:name":"Kaasland Van Outheusden",
    "wof:placetype":"venue"
},
  "geometry": {"coordinates":[5.09067,51.557114],"type":"Point"}
}