{
  "type": "Feature",
  "properties": {
    "addr:full":"Wilhelminalaan 7 Boskoop Zuid-Holland 2771 VL",
    "addr:housenumber":"7",
    "addr:postcode":"2771 vl",
    "addr:street":"Wilhelminalaan",
    "iso:country":"NL",
    "sg:address":"Wilhelminalaan 7",
    "sg:city":"Boskoop",
    "sg:classifiers":[
        {
            "category":"Education",
            "subcategory":"Preschool",
            "type":"Public Place"
        }
    ],
    "sg:phone":"+31 172 213 711",
    "sg:postcode":"2771 VL",
    "sg:province":"Zuid-Holland",
    "sg:tags":[
        "kleuteronderwijs",
        "basis-"
    ],
    "wof:name":"Immanuel Prot Chr",
    "wof:placetype":"venue"
},
  "geometry": {"coordinates":[4.646673,52.070091],"type":"Point"}
}