{
  "type": "Feature",
  "properties": {
    "addr:full":"Marinus De Jongstraat 5 Oosterhout Nb North Brabant 4904 PK",
    "addr:housenumber":"5;nb",
    "addr:postcode":"4904 pk",
    "addr:street":"Marinus De Jongstraat",
    "iso:country":"NL",
    "sg:address":"Marinus De Jongstraat 5",
    "sg:city":"Oosterhout Nb",
    "sg:orig_category":"Adviesbureaus Bedrijfsorganisatie",
    "sg:phone":"+31 162 424 496",
    "sg:postcode":"4904 PK",
    "sg:province":"North Brabant",
    "wof:name":"Vmc",
    "wof:placetype":"venue"
},
  "geometry": {"coordinates":[4.848331,51.627277],"type":"Point"}
}