{
  "type": "Feature",
  "properties": {
    "iso:country":"NL",
    "sg:address":"Speuldestr 18",
    "sg:city":"Amsterdam Zuidoost",
    "sg:orig_category":"Adviesbureaus Bedrijfsorganisatie",
    "sg:phone":"+31 20 691 0995",
    "sg:postcode":"1107 WX",
    "sg:province":"Noord-Holland",
    "wof:name":"Know-How",
    "wof:placetype":"venue"
},
  "geometry": {"coordinates":[4.978166,52.290539],"type":"Point"}
}