{
  "type": "Feature",
  "properties": {
    "addr:full":"Speuldestr 18 Amsterdam Zuidoost Noord-Holland 1107 WX",
    "addr:housenumber":"18",
    "addr:postcode":"zuidoost;1107 wx",
    "addr:street":"Speuldestr",
    "iso:country":"NL",
    "sg:address":"Speuldestr 18",
    "sg:city":"Amsterdam Zuidoost",
    "sg:orig_category":"Adviesbureaus Bedrijfsorganisatie",
    "sg:phone":"+31 20 691 0995",
    "sg:postcode":"1107 WX",
    "sg:province":"Noord-Holland",
    "wof:name":"Know-How",
    "wof:placetype":"venue"
},
  "geometry": {"coordinates":[4.978166,52.290539],"type":"Point"}
}