{
  "type": "Feature",
  "properties": {
    "addr:full":"P Debyeln 31 Maastricht Limburg 6229 HX",
    "addr:housenumber":"31",
    "addr:postcode":"6229 hx",
    "addr:street":"P",
    "iso:country":"NL",
    "sg:address":"P Debyeln 31",
    "sg:city":"Maastricht",
    "sg:orig_category":"Parkeergarages",
    "sg:phone":"+31 900 4466880",
    "sg:postcode":"6229 HX",
    "sg:province":"Limburg",
    "wof:name":"Q-Park",
    "wof:placetype":"venue"
},
  "geometry": {"coordinates":[5.70559,50.822762],"type":"Point"}
}