{
  "type": "Feature",
  "properties": {
    "addr:full":"Bosdreef 27 St Maartensdyk Zeeland 4695 JD",
    "addr:housenumber":"27",
    "addr:postcode":"4695 jd",
    "addr:street":"Bosdreef",
    "iso:country":"NL",
    "sg:address":"Bosdreef 27",
    "sg:city":"St Maartensdyk",
    "sg:orig_category":"Schilders",
    "sg:phone":"+31 166 662 527",
    "sg:postcode":"4695 JD",
    "sg:province":"Zeeland",
    "wof:name":"Vermaas",
    "wof:placetype":"venue"
},
  "geometry": {"coordinates":[4.07501,51.546577],"type":"Point"}
}