{
  "type": "Feature",
  "properties": {
    "addr:full":"Borgstee 6 Assen Provincie Drenthe 9403 TV",
    "addr:housenumber":"6",
    "addr:postcode":"9403 tv",
    "addr:street":"Borgstee;Provincie Drenthe",
    "iso:country":"NL",
    "sg:address":"Borgstee 6",
    "sg:city":"Assen",
    "sg:orig_category":"Woninginrichting",
    "sg:phone":"+31 592 347 888",
    "sg:postcode":"9403 TV",
    "sg:province":"Provincie Drenthe",
    "wof:name":"Kwantum",
    "wof:placetype":"venue"
},
  "geometry": {"coordinates":[6.5737600327,53.0113830566],"type":"Point"}
}