{
  "type": "Feature",
  "properties": {
    "addr:full":"Poolswijk 3 Nieuw Roden Drenthe 9311 TE",
    "addr:housenumber":"3",
    "addr:postcode":"9311 te",
    "addr:street":"Poolswijk;Nieuw",
    "iso:country":"NL",
    "sg:address":"Poolswijk 3",
    "sg:city":"Nieuw Roden",
    "sg:orig_category":"Verhuur Catering-, Feest- En Evenementbenodigdheden",
    "sg:phone":"+31 50 501 9159",
    "sg:postcode":"9311 TE",
    "sg:province":"Drenthe",
    "wof:name":"Handelsonderneming Sparo Bv",
    "wof:placetype":"venue"
},
  "geometry": {"coordinates":[6.391128,53.130512],"type":"Point"}
}