{
  "type": "Feature",
  "properties": {
    "iso:country":"NL",
    "sg:address":"Vijfhuizenberg 109",
    "sg:city":"Roosendaal",
    "sg:orig_category":"Daken And Skeletbouw",
    "sg:phone":"+31 165 560 449",
    "sg:postcode":"4708 AJ",
    "sg:province":"Noord-Brabant",
    "wof:name":"Dakbedekkingsbedrijf Rooftime Bv",
    "wof:placetype":"venue"
},
  "geometry": {"coordinates":[4.442333,51.519817],"type":"Point"}
}