{
  "type": "Feature",
  "properties": {
    "addr:full":"Arendshof 207 Oosterhout Nb Noord-Brabant 4901 ND",
    "addr:housenumber":"207",
    "addr:postcode":"4901 nd",
    "addr:street":"Arendshof",
    "iso:country":"NL",
    "sg:address":"Arendshof 207",
    "sg:city":"Oosterhout Nb",
    "sg:orig_category":"Kinderkleding",
    "sg:phone":"+31 162 427 912",
    "sg:postcode":"4901 ND",
    "sg:province":"Noord-Brabant",
    "wof:name":"Esprit",
    "wof:placetype":"venue"
},
  "geometry": {"coordinates":[4.85749,51.644409],"type":"Point"}
}