{
  "type": "Feature",
  "properties": {
    "addr:full":"Lombardpassage 8 S Hertogenbosch Noord-Brabant 5211 JM",
    "addr:housenumber":"8",
    "addr:postcode":"5211 jm",
    "addr:street":"Lombardpassage",
    "iso:country":"NL",
    "sg:address":"Lombardpassage 8",
    "sg:city":"S Hertogenbosch",
    "sg:classifiers":[
        {
            "category":"Shopping",
            "subcategory":"News",
            "type":"Retail Goods"
        }
    ],
    "sg:phone":"+31 73 613 5116",
    "sg:postcode":"5211 JM",
    "sg:province":"Noord-Brabant",
    "sg:tags":[
        "maandbladen",
        "en",
        "week-"
    ],
    "wof:name":"Bossche Omroep, De",
    "wof:placetype":"venue"
},
  "geometry": {"coordinates":[5.3029279709,51.6875686646],"type":"Point"}
}