{
  "type": "Feature",
  "properties": {
    "addr:full":"Pr Hendrikstr 30 Wateringen South Holland 2291 ER",
    "addr:housenumber":"30",
    "addr:postcode":"2291 er",
    "iso:country":"NL",
    "sg:address":"Pr Hendrikstr 30",
    "sg:city":"Wateringen",
    "sg:orig_category":"Autorijscholen",
    "sg:phone":"+31 174 221 693",
    "sg:postcode":"2291 ER",
    "sg:province":"South Holland",
    "wof:name":"Arianne",
    "wof:placetype":"venue"
},
  "geometry": {"coordinates":[4.270399,52.030327],"type":"Point"}
}