{
  "type": "Feature",
  "properties": {
    "addr:full":"Herman Gorterhof 158 Delft South Holland 2624 XL",
    "addr:housenumber":"158",
    "addr:postcode":"2624 xl",
    "addr:street":"Herman Gorterhof",
    "iso:country":"NL",
    "sg:address":"Herman Gorterhof 158",
    "sg:city":"Delft",
    "sg:orig_category":"Boekhouders",
    "sg:phone":"+31 15 257 8180",
    "sg:postcode":"2624 XL",
    "sg:province":"South Holland",
    "wof:name":"H K De Boer Bedr Admin",
    "wof:placetype":"venue"
},
  "geometry": {"coordinates":[4.357995,51.993401],"type":"Point"}
}