{
  "type": "Feature",
  "properties": {
    "addr:full":"Hoofdstr 34 Oostwold Scheemda Groningen 9682 PK",
    "addr:housenumber":"34",
    "addr:postcode":"9682 pk",
    "addr:street":"Hoofdstr",
    "iso:country":"NL",
    "sg:address":"Hoofdstr 34",
    "sg:city":"Oostwold Scheemda",
    "sg:orig_category":"Verzekeringen - Verzekeringskantoren",
    "sg:phone":"+31 597 552 002",
    "sg:postcode":"9682 PK",
    "sg:province":"Groningen",
    "wof:name":"Korte",
    "wof:placetype":"venue"
},
  "geometry": {"coordinates":[7.044962,53.202744],"type":"Point"}
}