{
  "type": "Feature",
  "properties": {
    "iso:country":"NL",
    "sg:address":"Mgr. Bekkersplein 2",
    "sg:city":"Sint Oedenrode",
    "sg:orig_category":"Biljart- And Snookerzalen",
    "sg:phone":"+31 413 473 668",
    "sg:postcode":"5491 EB",
    "sg:province":"Noord-Brabant",
    "wof:name":"T Wapen Van Eerschot",
    "wof:placetype":"venue"
},
  "geometry": {"coordinates":[5.468544,51.56971],"type":"Point"}
}