{
  "type": "Feature",
  "properties": {
    "addr:full":"Wettertoer 11 Heerenveen Friesland 8442 PC",
    "addr:housenumber":"11",
    "addr:postcode":"8442 pc",
    "addr:street":"Wettertoer",
    "iso:country":"NL",
    "sg:address":"Wettertoer 11",
    "sg:city":"Heerenveen",
    "sg:orig_category":"Binnenhuisarchitecten",
    "sg:phone":"+31 513 622 640",
    "sg:postcode":"8442 PC",
    "sg:province":"Friesland",
    "wof:name":"Borger Interieuradvies Tiffany",
    "wof:placetype":"venue"
},
  "geometry": {"coordinates":[5.929095,52.95845],"type":"Point"}
}