{
  "type": "Feature",
  "properties": {
    "iso:country":"NL",
    "sg:address":"Dr. Deelenlaan 5",
    "sg:city":"Tilburg",
    "sg:orig_category":"Ziekenhuizen And Zorginstellingen",
    "sg:phone":"+31 13 465 5655",
    "sg:postcode":"5042 AD",
    "sg:province":"Noord-Brabant",
    "wof:name":"Tweesteden Ziekenhuis Vestiging Tilburg",
    "wof:placetype":"venue"
},
  "geometry": {"coordinates":[5.063226,51.577179],"type":"Point"}
}