{
  "type": "Feature",
  "properties": {
    "addr:full":"Wilhelminaplantsoen 47 Bussum North Holland 1404 JP",
    "addr:housenumber":"47",
    "addr:postcode":"1404 jp",
    "addr:street":"Wilhelminaplantsoen",
    "iso:country":"NL",
    "sg:address":"Wilhelminaplantsoen 47",
    "sg:city":"Bussum",
    "sg:orig_category":"Partycatering And -Organisatie",
    "sg:phone":"+31 35 693 4087",
    "sg:postcode":"1404 JP",
    "sg:province":"North Holland",
    "wof:name":"Les Cuisiniers",
    "wof:placetype":"venue"
},
  "geometry": {"coordinates":[5.163963,52.275852],"type":"Point"}
}