{
  "type": "Feature",
  "properties": {
    "addr:full":"Noorddijkstraat 56 Brouwershaven Zeeland 4318 BK",
    "addr:housenumber":"56",
    "addr:postcode":"4318 bk",
    "addr:street":"Noorddijkstraat",
    "iso:country":"NL",
    "sg:address":"Noorddijkstraat 56",
    "sg:city":"Brouwershaven",
    "sg:orig_category":"Granen, Zaden And Diervoeders Gh",
    "sg:phone":"+31 111 695 030",
    "sg:postcode":"4318 BK",
    "sg:province":"Zeeland",
    "wof:name":"J. Beeke",
    "wof:placetype":"venue"
},
  "geometry": {"coordinates":[3.908313,51.727207],"type":"Point"}
}