{
  "type": "Feature",
  "properties": {
    "addr:full":"Berschotten 12 Bladel Noord-Brabant 5531 NW",
    "addr:housenumber":"12",
    "addr:postcode":"5531 nw",
    "addr:street":"Berschotten",
    "iso:country":"NL",
    "sg:address":"Berschotten 12",
    "sg:city":"Bladel",
    "sg:orig_category":"Beveiliging",
    "sg:phone":"+31 497 388 239",
    "sg:postcode":"5531 NW",
    "sg:province":"Noord-Brabant",
    "wof:name":"Dol Bv, R",
    "wof:placetype":"venue"
},
  "geometry": {"coordinates":[5.206089,51.358833],"type":"Point"}
}