{
  "type": "Feature",
  "properties": {
    "addr:full":"Leen Acker 26 Heemskerk North Holland 1965 RS",
    "addr:housenumber":"26",
    "addr:postcode":"1965 rs",
    "addr:street":"Leen Acker",
    "iso:country":"NL",
    "sg:address":"Leen Acker 26",
    "sg:city":"Heemskerk",
    "sg:orig_category":"Verzekeringen",
    "sg:phone":"+31 251 238 563",
    "sg:postcode":"1965 RS",
    "sg:province":"North Holland",
    "wof:name":"M En M Van Der Worp",
    "wof:placetype":"venue"
},
  "geometry": {"coordinates":[4.660859,52.505581],"type":"Point"}
}