{
  "type": "Feature",
  "properties": {
    "addr:full":"Jasmynstr 5 Hengelo Ov Overijssel 7552 AH",
    "addr:housenumber":"5",
    "addr:postcode":"7552 ah",
    "addr:street":"Jasmynstr;Ov",
    "iso:country":"NL",
    "sg:address":"Jasmynstr 5",
    "sg:city":"Hengelo Ov",
    "sg:orig_category":"Verenigingsgebouwen",
    "sg:phone":"+31 74 242 6649",
    "sg:postcode":"7552 AH",
    "sg:province":"Overijssel",
    "wof:name":"Heester De",
    "wof:placetype":"venue"
},
  "geometry": {"coordinates":[6.78971,52.266331],"type":"Point"}
}