{
  "type": "Feature",
  "properties": {
    "addr:full":"Kuifeend 6 Broek Op Langedijk Noord-Holland 1721 DM",
    "addr:housenumber":"6",
    "addr:postcode":"1721 dm",
    "addr:street":"Kuifeend",
    "iso:country":"NL",
    "sg:address":"Kuifeend 6",
    "sg:city":"Broek Op Langedijk",
    "sg:orig_category":"Beautyfarms And Sauna'S",
    "sg:phone":"+31 226 318 978",
    "sg:postcode":"1721 DM",
    "sg:province":"Noord-Holland",
    "wof:name":"C.J. Heeremans",
    "wof:placetype":"venue"
},
  "geometry": {"coordinates":[4.821964,52.685955],"type":"Point"}
}