{
  "type": "Feature",
  "properties": {
    "addr:full":"Vondelln 37 Bergen Op Zoom Noord-Brabant 4624 HL",
    "addr:housenumber":"37",
    "addr:postcode":"4624 hl",
    "addr:street":"Vondelln",
    "iso:country":"NL",
    "sg:address":"Vondelln 37",
    "sg:city":"Bergen Op Zoom",
    "sg:orig_category":"Etalageverzorging",
    "sg:phone":"+31 6 53533206",
    "sg:postcode":"4624 HL",
    "sg:province":"Noord-Brabant",
    "wof:name":"Art'S Art",
    "wof:placetype":"venue"
},
  "geometry": {"coordinates":[4.33397,51.473049],"type":"Point"}
}