{
  "type": "Feature",
  "properties": {
    "addr:full":"Prof Quackln 12 Ryswyk Zh Zuid-Holland 2285 VS",
    "addr:housenumber":"12",
    "addr:postcode":"2285 vs",
    "addr:street":"Ryswyk",
    "iso:country":"NL",
    "sg:address":"Prof Quackln 12",
    "sg:city":"Ryswyk Zh",
    "sg:orig_category":"Verhuizingen",
    "sg:phone":"+31 70 362 1109",
    "sg:postcode":"2285 VS",
    "sg:province":"Zuid-Holland",
    "sg:website":"http://www.verhuisexpress.nl",
    "wof:name":"Verhuisexpress, De",
    "wof:placetype":"venue"
},
  "geometry": {"coordinates":[4.32436,52.037251],"type":"Point"}
}