{
  "type": "Feature",
  "properties": {
    "addr:full":"Weresteyn 86 Sliedrecht Zuid-Holland 3363 BR",
    "addr:housenumber":"86",
    "addr:postcode":"3363 br",
    "addr:street":"Weresteyn",
    "iso:country":"NL",
    "sg:address":"Weresteyn 86",
    "sg:city":"Sliedrecht",
    "sg:orig_category":"Diverse Opleidingen And Onderwijs",
    "sg:phone":"+31 184 414 356",
    "sg:postcode":"3363 BR",
    "sg:province":"Zuid-Holland",
    "wof:name":"G. Diamandidis",
    "wof:placetype":"venue"
},
  "geometry": {"coordinates":[4.761831,51.827011],"type":"Point"}
}