{
  "type": "Feature",
  "properties": {
    "iso:country":"NL",
    "sg:address":"Zuiderzeestr 45",
    "sg:city":"Aartswoud",
    "sg:orig_category":"Geluidsinstallaties - Verhuur",
    "sg:phone":"+31 229 581 927",
    "sg:postcode":"1719 LC",
    "sg:province":"Noord-Holland",
    "wof:name":"Fz Sound Systems",
    "wof:placetype":"venue"
},
  "geometry": {"coordinates":[4.95513,52.749798],"type":"Point"}
}