{
  "type": "Feature",
  "properties": {
    "addr:full":"Sijdneijstr 62 64 Rotterdam Zuid-Holland 3047 BP",
    "addr:housenumber":"62 64",
    "addr:postcode":"3047 bp",
    "addr:street":"Sijdneijstr",
    "iso:country":"NL",
    "sg:address":"Sijdneijstr 62 64",
    "sg:city":"Rotterdam",
    "sg:orig_category":"Medische And Orthopedische Artikelen",
    "sg:phone":"+31 10 298 2626",
    "sg:postcode":"3047 BP",
    "sg:province":"Zuid-Holland",
    "wof:name":"Zorglease Nederland",
    "wof:placetype":"venue"
},
  "geometry": {"coordinates":[4.40616,51.94207],"type":"Point"}
}