{
  "type": "Feature",
  "properties": {
    "addr:full":"Ellermanstr 18 Amsterdam North Holland 1099 BX",
    "addr:housenumber":"18",
    "addr:postcode":"1099 bx",
    "addr:street":"Ellermanstr",
    "iso:country":"NL",
    "sg:address":"Ellermanstr 18",
    "sg:city":"Amsterdam",
    "sg:orig_category":"Makelaars En Adviseurs Onroerende Goederen",
    "sg:phone":"+31 20 665 4489",
    "sg:postcode":"1099 BX",
    "sg:province":"North Holland",
    "wof:name":"Vlaanderen Meybaum",
    "wof:placetype":"venue"
},
  "geometry": {"coordinates":[4.93058,52.326759],"type":"Point"}
}