{
  "type": "Feature",
  "properties": {
    "addr:full":"Ir Lelywg 44A Haarlem Noord-Holland 2031 CD",
    "addr:housenumber":"44a",
    "addr:postcode":"2031 cd",
    "iso:country":"NL",
    "sg:address":"Ir Lelywg 44A",
    "sg:city":"Haarlem",
    "sg:orig_category":"Grafisch Ontwerpers",
    "sg:phone":"+31 23 532 2067",
    "sg:postcode":"2031 CD",
    "sg:province":"Noord-Holland",
    "sg:website":"http://www.planb.nl",
    "wof:name":"Plan B Grafimediabureau",
    "wof:placetype":"venue"
},
  "geometry": {"coordinates":[4.655921,52.38773],"type":"Point"}
}