{
  "type": "Feature",
  "properties": {
    "iso:country":"NL",
    "sg:address":"Graafschap Hornelaan 136",
    "sg:city":"Weert",
    "sg:orig_category":"Fitnesscentra",
    "sg:phone":"+31 495 520 010",
    "sg:postcode":"6004 HT",
    "sg:province":"Limburg",
    "wof:name":"Sportcentrum Van Heel Bv",
    "wof:placetype":"venue"
},
  "geometry": {"coordinates":[5.723594,51.261662],"type":"Point"}
}