{
  "type": "Feature",
  "properties": {
    "addr:full":"De Klerkstr 7 Zeist Utrecht 3701 DL",
    "addr:housenumber":"7",
    "addr:postcode":"3701 dl",
    "iso:country":"NL",
    "sg:address":"De Klerkstr 7",
    "sg:city":"Zeist",
    "sg:orig_category":"Poeliers",
    "sg:phone":"+31 30 691 6520",
    "sg:postcode":"3701 DL",
    "sg:province":"Utrecht",
    "wof:name":"Broer, J",
    "wof:placetype":"venue"
},
  "geometry": {"coordinates":[5.241004,52.085674],"type":"Point"}
}