{
  "type": "Feature",
  "properties": {
    "addr:full":"De Looch 3-5 Vianen Zh Utrecht 4133 DK",
    "addr:housenumber":"3-5",
    "addr:postcode":"zh;4133 dk",
    "addr:street":"De Looch",
    "iso:country":"NL",
    "sg:address":"De Looch 3-5",
    "sg:city":"Vianen Zh",
    "sg:orig_category":"Scholen Voor Basisonderwijs",
    "sg:phone":"+31 347 373 527",
    "sg:postcode":"4133 DK",
    "sg:province":"Utrecht",
    "wof:name":"Voorhof Chr, De",
    "wof:placetype":"venue"
},
  "geometry": {"coordinates":[5.080396,51.982586],"type":"Point"}
}