{
  "type": "Feature",
  "properties": {
    "iso:country":"NL",
    "sg:address":"Molenpaal 6",
    "sg:city":"Sneek",
    "sg:orig_category":"Pleziervaartuigen And Reparatie",
    "sg:phone":"+31 515 417 810",
    "sg:postcode":"8608 ZJ",
    "sg:province":"Provincie Friesland",
    "wof:name":"Bijstra Scheepsinstallatie",
    "wof:placetype":"venue"
},
  "geometry": {"coordinates":[5.645468,53.021168],"type":"Point"}
}