{
  "type": "Feature",
  "properties": {
    "addr:full":"Karveel 4009 Lelystad NL. 8231 DK",
    "addr:postcode":"4009;8231 dk",
    "addr:street":"Karveel;Nl.",
    "iso:country":"NL",
    "sg:address":"Karveel 4009",
    "sg:city":"Lelystad",
    "sg:orig_category":"Public Relationbureaus",
    "sg:phone":"+31 320 219 220",
    "sg:postcode":"8231 DK",
    "sg:province":"NL.",
    "wof:name":"Abf & Partners Bv",
    "wof:placetype":"venue"
},
  "geometry": {"coordinates":[5.464323,52.524632],"type":"Point"}
}