{
  "type": "Feature",
  "properties": {
    "addr:full":"Schoolstraat 68 Voorschoten Zuid-Holland 2251 BK",
    "addr:housenumber":"68",
    "addr:postcode":"2251 bk",
    "addr:street":"Schoolstraat",
    "iso:country":"NL",
    "sg:address":"Schoolstraat 68",
    "sg:city":"Voorschoten",
    "sg:orig_category":"Boekenuitgeverijen",
    "sg:phone":"+31 71 561 5784",
    "sg:postcode":"2251 BK",
    "sg:province":"Zuid-Holland",
    "wof:name":"Boekhandel De Kler Bv",
    "wof:placetype":"venue"
},
  "geometry": {"coordinates":[4.445997,52.125145],"type":"Point"}
}