{
  "type": "Feature",
  "properties": {
    "addr:full":"Leopoldstr 19 A Rotterdam Zuid-Holland 3031 SV",
    "addr:housenumber":"19 a",
    "addr:postcode":"3031 sv",
    "addr:street":"Leopoldstr",
    "iso:country":"NL",
    "sg:address":"Leopoldstr 19 A",
    "sg:city":"Rotterdam",
    "sg:orig_category":"Meubelen",
    "sg:phone":"+31 10 213 1972",
    "sg:postcode":"3031 SV",
    "sg:province":"Zuid-Holland",
    "wof:name":"Dieges, R",
    "wof:placetype":"venue"
},
  "geometry": {"coordinates":[4.489179,51.925331],"type":"Point"}
}