{
  "type": "Feature",
  "properties": {
    "addr:full":"Vijfheerenlanden 553 Vianen Zh South Holland 4131 GT",
    "addr:housenumber":"553",
    "addr:postcode":"zh;4131 gt",
    "addr:street":"Vijfheerenlanden",
    "iso:country":"NL",
    "sg:address":"Vijfheerenlanden 553",
    "sg:city":"Vianen Zh",
    "sg:orig_category":"Kappers",
    "sg:phone":"+31 347 372 737",
    "sg:postcode":"4131 GT",
    "sg:province":"South Holland",
    "wof:name":"H.G. Den Hartogh",
    "wof:placetype":"venue"
},
  "geometry": {"coordinates":[5.1027898788,51.9942855835],"type":"Point"}
}