{
  "type": "Feature",
  "properties": {
    "addr:full":"T Boonrak 21 Valkenburg Zh South Holland 2235 ED",
    "addr:housenumber":"21",
    "addr:postcode":"zh;2235 ed",
    "addr:street":"T Boonrak",
    "iso:country":"NL",
    "sg:address":"T Boonrak 21",
    "sg:city":"Valkenburg Zh",
    "sg:orig_category":"Politie",
    "sg:phone":"+31 900 8844",
    "sg:postcode":"2235 ED",
    "sg:province":"South Holland",
    "wof:name":"Politie",
    "wof:placetype":"venue"
},
  "geometry": {"coordinates":[4.437293,52.179447],"type":"Point"}
}