{
  "type": "Feature",
  "properties": {
    "addr:full":"Aspert 4 Horssen Gelderland 6631 KS",
    "addr:housenumber":"4",
    "addr:postcode":"6631 ks",
    "addr:street":"Aspert;Gelderland",
    "iso:country":"NL",
    "sg:address":"Aspert 4",
    "sg:city":"Horssen",
    "sg:orig_category":"Adviesbureaus Beroeps- En Schoolkeuze",
    "sg:phone":"+31 487 542 540",
    "sg:postcode":"6631 KS",
    "sg:province":"Gelderland",
    "wof:name":"Nicam",
    "wof:placetype":"venue"
},
  "geometry": {"coordinates":[-98.320213,38.498058],"type":"Point"}
}