{
  "type": "Feature",
  "properties": {
    "addr:full":"Ookmeerwg 255 Amsterdam Noord-Holland 1069 MT",
    "addr:housenumber":"255;1069",
    "addr:street":"Mt",
    "iso:country":"NL",
    "sg:address":"Ookmeerwg 255",
    "sg:city":"Amsterdam",
    "sg:orig_category":"Glazenwasserijen",
    "sg:phone":"+31 20 619 7521",
    "sg:postcode":"1069 MT",
    "sg:province":"Noord-Holland",
    "wof:name":"Oude Lutkehuis, A",
    "wof:placetype":"venue"
},
  "geometry": {"coordinates":[-94.58503,38.350479],"type":"Point"}
}