{
  "type": "Feature",
  "properties": {
    "addr:full":"Hemmerbuurt 52 Hem Noord-Holland 1607 CK",
    "addr:housenumber":"52",
    "addr:postcode":"1607 ck",
    "addr:street":"Hemmerbuurt",
    "iso:country":"NL",
    "sg:address":"Hemmerbuurt 52",
    "sg:city":"Hem",
    "sg:orig_category":"Bloemen- And Plantenteelt",
    "sg:phone":"+31 228 543 229",
    "sg:postcode":"1607 CK",
    "sg:province":"Noord-Holland",
    "wof:name":"Obdam Bloembollen Bv",
    "wof:placetype":"venue"
},
  "geometry": {"coordinates":[-89.0961608887,39.9037284851],"type":"Point"}
}