{
  "type": "Feature",
  "properties": {
    "addr:full":"Postbus 465 Delft Zuid-Holland 2600 AL",
    "addr:housenumber":"465",
    "addr:postcode":"2600 al",
    "addr:street":"Postbus",
    "iso:country":"NL",
    "sg:address":"Postbus 465",
    "sg:city":"Delft",
    "sg:orig_category":"Voetbalverenigingen",
    "sg:phone":"+31 15 262 4533",
    "sg:postcode":"2600 AL",
    "sg:province":"Zuid-Holland",
    "wof:name":"Delfia Vv",
    "wof:placetype":"venue"
},
  "geometry": {"coordinates":[4.35869,52.011501],"type":"Point"}
}