{
  "type": "Feature",
  "properties": {
    "addr:full":"Stationstr 24 Baexem Limburg 6095 BS",
    "addr:housenumber":"24",
    "addr:postcode":"6095 bs",
    "addr:street":"Stationstr",
    "iso:country":"NL",
    "sg:address":"Stationstr 24",
    "sg:city":"Baexem",
    "sg:orig_category":"Ventilatiesystemen",
    "sg:phone":"+31 475 459 040",
    "sg:postcode":"6095 BS",
    "sg:province":"Limburg",
    "wof:name":"Ottenheijm Bv",
    "wof:placetype":"venue"
},
  "geometry": {"coordinates":[5.881974,51.231339],"type":"Point"}
}