{
  "type": "Feature",
  "properties": {
    "iso:country":"NL",
    "sg:address":"Lauwerecht 7Bis",
    "sg:city":"Utrecht",
    "sg:orig_category":"Voetbalverenigingen",
    "sg:phone":"+31 30 243 4830",
    "sg:postcode":"3514 BA",
    "sg:province":"Utrecht",
    "wof:name":"Dso Ultrajectum",
    "wof:placetype":"venue"
},
  "geometry": {"coordinates":[5.112737,52.100361],"type":"Point"}
}