{
  "type": "Feature",
  "properties": {
    "addr:full":"Mr E N Van Kleffensstr 4 Arnhem Gelderland 6842 CV",
    "addr:housenumber":"4",
    "addr:postcode":"6842 cv",
    "addr:street":"N;Kleffensstr",
    "iso:country":"NL",
    "sg:address":"Mr E N Van Kleffensstr 4",
    "sg:city":"Arnhem",
    "sg:classifiers":[
        {
            "category":"Professional",
            "subcategory":"Accounting & Tax Preparation",
            "type":"Services"
        }
    ],
    "sg:phone":"+31 26 351 0228",
    "sg:postcode":"6842 CV",
    "sg:province":"Gelderland",
    "sg:tags":[
        "accountant"
    ],
    "wof:name":"Amstelheerd",
    "wof:placetype":"venue"
},
  "geometry": {"coordinates":[5.872055,51.953415],"type":"Point"}
}