{
  "type": "Feature",
  "properties": {
    "iso:country":"NL",
    "sg:address":"Hobbemastr 7",
    "sg:city":"Zaandam",
    "sg:orig_category":"Vertaalbureaus",
    "sg:phone":"+31 75 616 8826",
    "sg:postcode":"1506 JV",
    "sg:province":"North Holland",
    "wof:name":"Bax, Drs H",
    "wof:placetype":"venue"
},
  "geometry": {"coordinates":[4.809365,52.450981],"type":"Point"}
}