{
  "type": "Feature",
  "properties": {
    "addr:full":"Ladderbaai 6 Almere NL. 1317 AX",
    "addr:housenumber":"6",
    "addr:postcode":"1317 ax",
    "addr:street":"Ladderbaai;Nl.",
    "iso:country":"NL",
    "sg:address":"Ladderbaai 6",
    "sg:city":"Almere",
    "sg:orig_category":"Fitnesscentra",
    "sg:phone":"+31 36 534 7000",
    "sg:postcode":"1317 AX",
    "sg:province":"NL.",
    "wof:name":"Taekwondo Taek Kyun Mudo Korean",
    "wof:placetype":"venue"
},
  "geometry": {"coordinates":[5.230716,52.387833],"type":"Point"}
}