{
  "type": "Feature",
  "properties": {
    "addr:full":"R Luxemburgstr 7 Almelo Overijssel 7607 SM",
    "addr:housenumber":"7",
    "addr:postcode":"7607 sm",
    "iso:country":"NL",
    "sg:address":"R Luxemburgstr 7",
    "sg:city":"Almelo",
    "sg:classifiers":[
        {
            "category":"Food & Beverages",
            "subcategory":"Bakery",
            "type":"Retail Goods"
        }
    ],
    "sg:phone":"+31 546 852 853",
    "sg:postcode":"7607 SM",
    "sg:province":"Overijssel",
    "sg:tags":[
        "pizza"
    ],
    "wof:name":"Carrello Pizza Express",
    "wof:placetype":"venue"
},
  "geometry": {"coordinates":[6.661983,52.35675],"type":"Point"}
}