{
  "type": "Feature",
  "properties": {
    "addr:full":"Oranjestr 59 Rysbergen Noord-Brabant 4891 XP",
    "addr:housenumber":"59",
    "addr:postcode":"4891 xp",
    "addr:street":"Oranjestr",
    "iso:country":"NL",
    "sg:address":"Oranjestr 59",
    "sg:city":"Rysbergen",
    "sg:orig_category":"Bevrachting",
    "sg:phone":"+31 76 596 2370",
    "sg:postcode":"4891 XP",
    "sg:province":"Noord-Brabant",
    "wof:name":"Panneman Shipping Bv",
    "wof:placetype":"venue"
},
  "geometry": {"coordinates":[4.697626,51.520454],"type":"Point"}
}