{
  "type": "Feature",
  "properties": {
    "addr:full":"Kerkstr 3 Scherpenisse Zeeland 4694 BW",
    "addr:housenumber":"3",
    "addr:postcode":"4694 bw",
    "addr:street":"Kerkstr",
    "iso:country":"NL",
    "sg:address":"Kerkstr 3",
    "sg:city":"Scherpenisse",
    "sg:classifiers":[
        {
            "category":"Personal",
            "subcategory":"Nail Salon",
            "type":"Services"
        }
    ],
    "sg:phone":"+31 166 667 100",
    "sg:postcode":"4694 BW",
    "sg:province":"Zeeland",
    "sg:tags":[
        "pedicure"
    ],
    "wof:name":"Jantien Moerland",
    "wof:placetype":"venue"
},
  "geometry": {"coordinates":[4.104976,51.548157],"type":"Point"}
}