{
  "type": "Feature",
  "properties": {
    "addr:full":"Dollard 4B Zwyndrecht Zuid-Holland 3332 EE",
    "addr:housenumber":"4b",
    "addr:postcode":"3332 ee",
    "addr:street":"Dollard",
    "iso:country":"NL",
    "sg:address":"Dollard 4B",
    "sg:city":"Zwyndrecht",
    "sg:orig_category":"Broodjeszaken",
    "sg:phone":"+31 78 619 6430",
    "sg:postcode":"3332 EE",
    "sg:province":"Zuid-Holland",
    "wof:name":"Pipo Pita'S",
    "wof:placetype":"venue"
},
  "geometry": {"coordinates":[4.653172,51.822979],"type":"Point"}
}