{
  "type": "Feature",
  "properties": {
    "addr:full":"Singel 87 Amsterdam Noord-Holland 1012 VG",
    "addr:housenumber":"87",
    "addr:postcode":"1012 vg",
    "addr:street":"Singel",
    "iso:country":"NL",
    "sg:address":"Singel 87",
    "sg:city":"Amsterdam",
    "sg:orig_category":"Boeken Antiquarische En Gebruikte",
    "sg:phone":"+31 20 625 2345",
    "sg:postcode":"1012 VG",
    "sg:province":"Noord-Holland",
    "wof:name":"Nauta Boekhandel",
    "wof:placetype":"venue"
},
  "geometry": {"coordinates":[4.891759,52.37627],"type":"Point"}
}