{
  "type": "Feature",
  "properties": {
    "iso:country":"NL",
    "sg:address":"Multatuliln 17",
    "sg:city":"Roosendaal",
    "sg:orig_category":"Wijnkoperijen En -Groothandel",
    "sg:phone":"+31 165 557 411",
    "sg:postcode":"4707 LZ",
    "sg:province":"North Brabant",
    "sg:website":"http://www.kaapzicht.nl",
    "wof:name":"Tafelberg Bv",
    "wof:placetype":"venue"
},
  "geometry": {"coordinates":[4.4576702118,51.5314025879],"type":"Point"}
}