{
  "type": "Feature",
  "properties": {
    "addr:full":"Industrieweg 19 Bergeyk Noord-Brabant 5571 LJ",
    "addr:housenumber":"19",
    "addr:postcode":"5571 lj",
    "addr:street":"Industrieweg",
    "iso:country":"NL",
    "sg:address":"Industrieweg 19",
    "sg:city":"Bergeyk",
    "sg:orig_category":"Huishoudelijk Textiel Fab",
    "sg:phone":"+31 497 572 626",
    "sg:postcode":"5571 LJ",
    "sg:province":"Noord-Brabant",
    "wof:name":"N.K. Hezemans Textiel Bv",
    "wof:placetype":"venue"
},
  "geometry": {"coordinates":[5.350404,51.315201],"type":"Point"}
}