{
  "type": "Feature",
  "properties": {
    "addr:full":"Eemweg 9A 'S Hertogenbosch North Brabant 5215 HM",
    "addr:housenumber":"9a ' s",
    "addr:postcode":"5215 hm",
    "addr:street":"Eemweg;Hertogenbosch",
    "iso:country":"NL",
    "sg:address":"Eemweg 9A",
    "sg:city":"'S Hertogenbosch",
    "sg:orig_category":"Boekhouders",
    "sg:phone":"+31 73 613 7197",
    "sg:postcode":"5215 HM",
    "sg:province":"North Brabant",
    "wof:name":"Cfa Groep",
    "wof:placetype":"venue"
},
  "geometry": {"coordinates":[5.336031,51.692036],"type":"Point"}
}