{
  "type": "Feature",
  "properties": {
    "iso:country":"NL",
    "sg:address":"Eemweg 9A",
    "sg:city":"'S Hertogenbosch",
    "sg:orig_category":"Boekhouders",
    "sg:phone":"+31 73 613 7197",
    "sg:postcode":"5215 HM",
    "sg:province":"North Brabant",
    "wof:name":"Cfa Groep",
    "wof:placetype":"venue"
},
  "geometry": {"coordinates":[5.336031,51.692036],"type":"Point"}
}