{
  "type": "Feature",
  "properties": {
    "addr:full":"Fahrenheitweg 35 Leeuwarden Friesland 8912 AK",
    "addr:housenumber":"35",
    "addr:postcode":"8912 ak",
    "addr:street":"Fahrenheitweg",
    "iso:country":"NL",
    "sg:address":"Fahrenheitweg 35",
    "sg:city":"Leeuwarden",
    "sg:orig_category":"Diverse Bedrijfsinstallaties Gh",
    "sg:phone":"+31 58 212 3774",
    "sg:postcode":"8912 AK",
    "sg:province":"Friesland",
    "wof:name":"Wavo Pompen Bv",
    "wof:placetype":"venue"
},
  "geometry": {"coordinates":[5.761413,53.192654],"type":"Point"}
}