{
  "type": "Feature",
  "properties": {
    "addr:full":"Leguaanstr 2 Almere Flevoland 1338 HD",
    "addr:housenumber":"2",
    "addr:postcode":"1338 hd",
    "addr:street":"Leguaanstr;Flevoland",
    "iso:country":"NL",
    "sg:address":"Leguaanstr 2",
    "sg:city":"Almere",
    "sg:orig_category":"Administratie- En Boekhoudkantoren",
    "sg:phone":"+31 36 549 0796",
    "sg:postcode":"1338 HD",
    "sg:province":"Flevoland",
    "wof:name":"Js",
    "wof:placetype":"venue"
},
  "geometry": {"coordinates":[5.266905,52.383663],"type":"Point"}
}