{
  "type": "Feature",
  "properties": {
    "addr:full":"Meenthof 6 Kortenhoef Noord-Holland 1241 CP",
    "addr:housenumber":"6",
    "addr:postcode":"1241 cp",
    "addr:street":"Meenthof",
    "iso:country":"NL",
    "sg:address":"Meenthof 6",
    "sg:city":"Kortenhoef",
    "sg:classifiers":[
        {
            "category":"Fast Food",
            "type":"Food & Drink"
        }
    ],
    "sg:phone":"+31 35 656 2026",
    "sg:postcode":"1241 CP",
    "sg:province":"Noord-Holland",
    "sg:tags":[
        "afhaal",
        "restaurant"
    ],
    "wof:name":"Cafetaria De Meenthof",
    "wof:placetype":"venue"
},
  "geometry": {"coordinates":[5.112541,52.239967],"type":"Point"}
}