{
  "type": "Feature",
  "properties": {
    "iso:country":"NL",
    "sg:address":"Writsaert 146",
    "sg:city":"Noordwijk Zh",
    "sg:orig_category":"Bloemen And Planten Gh",
    "sg:phone":"+31 71 361 6965",
    "sg:postcode":"2202 PV",
    "sg:province":"Zuid-Holland",
    "wof:name":"H.J. Visser Flower Export",
    "wof:placetype":"venue"
},
  "geometry": {"coordinates":[4.435614,52.248837],"type":"Point"}
}