{
  "type": "Feature",
  "properties": {
    "addr:full":"Oudez Achterburgw 155Bg Amsterdam Noord-Holland 1012 DH",
    "addr:postcode":"1012 dh",
    "addr:street":"155Bg",
    "iso:country":"NL",
    "sg:address":"Oudez Achterburgw 155Bg",
    "sg:city":"Amsterdam",
    "sg:orig_category":"Hotels: Reservation",
    "sg:phone":"+31 20 535 3193",
    "sg:postcode":"1012 DH",
    "sg:province":"Noord-Holland",
    "sg:website":"http://www.srs-worldhotels.com",
    "wof:name":"Srs-Worldhotels",
    "wof:placetype":"venue"
},
  "geometry": {"coordinates":[4.896863,52.371223],"type":"Point"}
}