{
  "type": "Feature",
  "properties": {
    "addr:full":"Zelledijk 4 Hengelo Gld Gelderland 7255 MR",
    "addr:housenumber":"4",
    "addr:postcode":"7255 mr",
    "addr:street":"Zelledijk",
    "iso:country":"NL",
    "sg:address":"Zelledijk 4",
    "sg:city":"Hengelo Gld",
    "sg:orig_category":"Verhuur Audiovisuele Apparatuur",
    "sg:phone":"+31 575 467 574",
    "sg:postcode":"7255 MR",
    "sg:province":"Gelderland",
    "wof:name":"B.E.J. Ten Have",
    "wof:placetype":"venue"
},
  "geometry": {"coordinates":[6.381273,52.059849],"type":"Point"}
}