{
  "type": "Feature",
  "properties": {
    "addr:full":"Staringstraat 16 Nijmegen Gelderland 6521 AJ",
    "addr:housenumber":"16",
    "addr:postcode":"6521 aj",
    "addr:street":"Staringstraat;Gelderland",
    "iso:country":"NL",
    "sg:address":"Staringstraat 16",
    "sg:city":"Nijmegen",
    "sg:orig_category":"Overheidsdiensten",
    "sg:phone":"+31 24 323 9076",
    "sg:postcode":"6521 AJ",
    "sg:province":"Gelderland",
    "wof:name":"Woonrijk Vereniging",
    "wof:placetype":"venue"
},
  "geometry": {"coordinates":[5.8681168556,51.84217453],"type":"Point"}
}