{
  "type": "Feature",
  "properties": {
    "addr:full":"Pampus 26 Medemblik Noord-Holland 1671 RK",
    "addr:housenumber":"26",
    "addr:postcode":"1671 rk",
    "addr:street":"Pampus",
    "iso:country":"NL",
    "sg:address":"Pampus 26",
    "sg:city":"Medemblik",
    "sg:orig_category":"Kappers",
    "sg:phone":"+31 227 541 038",
    "sg:postcode":"1671 RK",
    "sg:province":"Noord-Holland",
    "wof:name":"Trendy & Tof",
    "wof:placetype":"venue"
},
  "geometry": {"coordinates":[5.101974,52.759022],"type":"Point"}
}