{
  "type": "Feature",
  "properties": {
    "addr:full":"V V Goghstr 21 Ryen Noord-Brabant 5121 CK",
    "addr:housenumber":"21",
    "addr:postcode":"5121 ck",
    "addr:street":"Goghstr",
    "iso:country":"NL",
    "sg:address":"V V Goghstr 21",
    "sg:city":"Ryen",
    "sg:orig_category":"Lederwaren - Fabrieken En Groothandel",
    "sg:phone":"+31 161 222 518",
    "sg:postcode":"5121 CK",
    "sg:province":"Noord-Brabant",
    "wof:name":"Kuijsters, Gebr",
    "wof:placetype":"venue"
},
  "geometry": {"coordinates":[4.9197,51.588017],"type":"Point"}
}