{
  "type": "Feature",
  "properties": {
    "addr:full":"Torenplein 1 Leende Noord-Brabant 5595 CE",
    "addr:housenumber":"1",
    "addr:postcode":"5595 ce",
    "addr:street":"Torenplein",
    "iso:country":"NL",
    "sg:address":"Torenplein 1",
    "sg:city":"Leende",
    "sg:orig_category":"Apothekers",
    "sg:phone":"+31 40 206 2915",
    "sg:postcode":"5595 CE",
    "sg:province":"Noord-Brabant",
    "wof:name":"Leende",
    "wof:placetype":"venue"
},
  "geometry": {"coordinates":[-39.34277,-5.32226],"type":"Point"}
}