{
  "type": "Feature",
  "properties": {
    "iso:country":"NL",
    "sg:address":"Zinkwerf 24",
    "sg:city":"S Gravenhage",
    "sg:orig_category":"Landkaarten En Plattegronden",
    "sg:phone":"+31 70 329 1291",
    "sg:postcode":"2544 EE",
    "sg:province":"South Holland",
    "wof:name":"Haagse Speciaal Vouwerij",
    "wof:placetype":"venue"
},
  "geometry": {"coordinates":[4.2515702248,52.0395507812],"type":"Point"}
}