{
  "type": "Feature",
  "properties": {
    "addr:full":"Vyfhuizenberg 72A Roosendaal Noord-Brabant 4708 AL",
    "addr:housenumber":"72a",
    "addr:postcode":"4708 al",
    "addr:street":"Vyfhuizenberg",
    "iso:country":"NL",
    "sg:address":"Vyfhuizenberg 72A",
    "sg:city":"Roosendaal",
    "sg:orig_category":"Heftrucks",
    "sg:phone":"+31 165 559 320",
    "sg:postcode":"4708 AL",
    "sg:province":"Noord-Brabant",
    "wof:name":"Schrauwen Vorkheftrucks",
    "wof:placetype":"venue"
},
  "geometry": {"coordinates":[4.444655,51.52142],"type":"Point"}
}