{
  "type": "Feature",
  "properties": {
    "addr:full":"Tweede Leliedwarsstraat 14 Amsterdam Noord-Holland 1015 TC",
    "addr:housenumber":"14",
    "addr:postcode":"1015 tc",
    "addr:street":"Tweede Leliedwarsstraat",
    "iso:country":"NL",
    "sg:address":"Tweede Leliedwarsstraat 14",
    "sg:city":"Amsterdam",
    "sg:orig_category":"Juridische Dienstverlening",
    "sg:phone":"+31 20 626 1397",
    "sg:postcode":"1015 TC",
    "sg:province":"Noord-Holland",
    "wof:name":"Van Vleuten Onderzoek- En Advies Bureau",
    "wof:placetype":"venue"
},
  "geometry": {"coordinates":[4.88066,52.375374],"type":"Point"}
}