{
  "type": "Feature",
  "properties": {
    "addr:full":"De Grt Weer 152 Weesp Noord-Holland 1383 BT",
    "addr:housenumber":"152",
    "addr:postcode":"1383 bt",
    "addr:street":"Weer",
    "iso:country":"NL",
    "sg:address":"De Grt Weer 152",
    "sg:city":"Weesp",
    "sg:orig_category":"Tekstschrijversters",
    "sg:phone":"+31 294 410 088",
    "sg:postcode":"1383 BT",
    "sg:province":"Noord-Holland",
    "wof:name":"Linea Directa",
    "wof:placetype":"venue"
},
  "geometry": {"coordinates":[5.042857,52.300907],"type":"Point"}
}