{
  "type": "Feature",
  "properties": {
    "addr:full":"Pylstaart 85 Hellevoetsluis Zuid-Holland 3225 CD",
    "addr:housenumber":"85",
    "addr:postcode":"3225 cd",
    "addr:street":"Pylstaart",
    "iso:country":"NL",
    "sg:address":"Pylstaart 85",
    "sg:city":"Hellevoetsluis",
    "sg:orig_category":"Geluidsinstallaties - Verhuur",
    "sg:phone":"+31 181 323 926",
    "sg:postcode":"3225 CD",
    "sg:province":"Zuid-Holland",
    "wof:name":"Woer-Com",
    "wof:placetype":"venue"
},
  "geometry": {"coordinates":[4.153447,51.830856],"type":"Point"}
}