{
  "type": "Feature",
  "properties": {
    "addr:full":"Breemarswg 231 Hengelo Ov NL.08 7553 HJ",
    "addr:housenumber":"231",
    "addr:postcode":"7553 hj",
    "addr:street":"Ov",
    "iso:country":"NL",
    "sg:address":"Breemarswg 231",
    "sg:city":"Hengelo Ov",
    "sg:orig_category":"Materiaalonderzoek",
    "sg:phone":"+31 74 291 3517",
    "sg:postcode":"7553 HJ",
    "sg:province":"NL.08",
    "wof:name":"Hengelose Kwaliteits Controle Bv",
    "wof:placetype":"venue"
},
  "geometry": {"coordinates":[6.786363,52.25214],"type":"Point"}
}