{
  "type": "Feature",
  "properties": {
    "addr:full":"Bronsweg 9A Lelystad NL. 8211 AL",
    "addr:housenumber":"9a",
    "addr:postcode":"8211",
    "addr:street":"Bronsweg;Nl.",
    "iso:country":"NL",
    "sg:address":"Bronsweg 9A",
    "sg:city":"Lelystad",
    "sg:orig_category":"Begrafenisondernemers",
    "sg:phone":"+31 320 223 207",
    "sg:postcode":"8211 AL",
    "sg:province":"NL.",
    "wof:name":"Majesta Huisdierencrematorium Lelystad",
    "wof:placetype":"venue"
},
  "geometry": {"coordinates":[5.516092,52.539879],"type":"Point"}
}