{
  "type": "Feature",
  "properties": {
    "addr:full":"Zekkenwg 100 Hoek Van Holland Zuid-Holland 3151 ZC",
    "addr:housenumber":"100",
    "addr:postcode":"3151 zc",
    "iso:country":"NL",
    "sg:address":"Zekkenwg 100",
    "sg:city":"Hoek Van Holland",
    "sg:orig_category":"Bloembollen - Groothandel",
    "sg:phone":"+31 174 310 798",
    "sg:postcode":"3151 ZC",
    "sg:province":"Zuid-Holland",
    "wof:name":"Calla Int Bv",
    "wof:placetype":"venue"
},
  "geometry": {"coordinates":[4.141808,51.971806],"type":"Point"}
}