{
  "type": "Feature",
  "properties": {
    "addr:full":"Biezenstr 31 Oisterwyk Noord-Brabant 5062 HH",
    "addr:housenumber":"31",
    "addr:postcode":"5062 hh",
    "addr:street":"Biezenstr",
    "iso:country":"NL",
    "sg:address":"Biezenstr 31",
    "sg:city":"Oisterwyk",
    "sg:classifiers":[
        {
            "category":"Personal",
            "subcategory":"Nail Salon",
            "type":"Services"
        }
    ],
    "sg:phone":"+31 13 521 7227",
    "sg:postcode":"5062 HH",
    "sg:province":"Noord-Brabant",
    "sg:tags":[
        "pedicure"
    ],
    "wof:name":"Gils, Van",
    "wof:placetype":"venue"
},
  "geometry": {"coordinates":[5.192407,51.575039],"type":"Point"}
}