{
  "type": "Feature",
  "properties": {
    "addr:full":"Schouwburgplein 13 Venray Limburg 5801 BV",
    "addr:housenumber":"13",
    "addr:postcode":"5801 bv",
    "addr:street":"Schouwburgplein",
    "iso:country":"NL",
    "sg:address":"Schouwburgplein 13",
    "sg:city":"Venray",
    "sg:orig_category":"Banken And Kredietinstellingen",
    "sg:phone":"+31 478 530 200",
    "sg:postcode":"5801 BV",
    "sg:province":"Limburg",
    "wof:name":"Rabobank",
    "wof:placetype":"venue"
},
  "geometry": {"coordinates":[5.973576,51.52486],"type":"Point"}
}