{
  "type": "Feature",
  "properties": {
    "iso:country":"NL",
    "sg:address":"Postbus 145",
    "sg:city":"Zeewolde",
    "sg:orig_category":"Graveermachines",
    "sg:phone":"+31 36 522 7675",
    "sg:postcode":"3890 AC",
    "sg:province":"Flevoland",
    "sg:website":"http://www.houtstra.nl",
    "wof:name":"Houtstra Bv",
    "wof:placetype":"venue"
},
  "geometry": {"coordinates":[5.54213,52.332512],"type":"Point"}
}