{
  "type": "Feature",
  "properties": {
    "addr:full":"Limbrichterstraat 21 Sittard Limburg 6131 EA",
    "addr:housenumber":"21",
    "addr:postcode":"6131 ea",
    "addr:street":"Limbrichterstraat",
    "iso:country":"NL",
    "sg:address":"Limbrichterstraat 21",
    "sg:city":"Sittard",
    "sg:orig_category":"Opticiens",
    "sg:phone":"+31 46 451 3058",
    "sg:postcode":"6131 EA",
    "sg:province":"Limburg",
    "wof:name":"Gijsen Optiek Bv",
    "wof:placetype":"venue"
},
  "geometry": {"coordinates":[5.8691191673,50.9981269836],"type":"Point"}
}