{
  "type": "Feature",
  "properties": {
    "addr:full":"Stationspln 49 Beverwyk Noord-Holland 1948 LC",
    "addr:housenumber":"49",
    "addr:postcode":"1948 lc",
    "addr:street":"Stationspln",
    "iso:country":"NL",
    "sg:address":"Stationspln 49",
    "sg:city":"Beverwyk",
    "sg:orig_category":"Bioscopen",
    "sg:phone":"+31 900 1213456",
    "sg:postcode":"1948 LC",
    "sg:province":"Noord-Holland",
    "sg:website":"http://www.cineworld.nl",
    "wof:name":"Cineworld Beverwijk",
    "wof:placetype":"venue"
},
  "geometry": {"coordinates":[4.65316,52.477673],"type":"Point"}
}