{
  "type": "Feature",
  "properties": {
    "addr:full":"R Vosstr 17 Coevorden Drenthe 7741 RJ",
    "addr:housenumber":"17",
    "addr:postcode":"7741 rj",
    "iso:country":"NL",
    "sg:address":"R Vosstr 17",
    "sg:city":"Coevorden",
    "sg:orig_category":"Adviesbureaus Bedrijfsorganisatie",
    "sg:phone":"+31 524 523 548",
    "sg:postcode":"7741 RJ",
    "sg:province":"Drenthe",
    "wof:name":"Quinta",
    "wof:placetype":"venue"
},
  "geometry": {"coordinates":[6.731179,52.67255],"type":"Point"}
}