{
  "type": "Feature",
  "properties": {
    "addr:full":"Amphion 34 Apeldoorn Gelderland 7314 AT",
    "addr:housenumber":"34",
    "addr:postcode":"7314",
    "addr:street":"Amphion;Gelderland",
    "iso:country":"NL",
    "sg:address":"Amphion 34",
    "sg:city":"Apeldoorn",
    "sg:orig_category":"Psychotherapeuten",
    "sg:phone":"+31 55 521 1031",
    "sg:postcode":"7314 AT",
    "sg:province":"Gelderland",
    "wof:name":"Montfoort-Wassenaar, M Van",
    "wof:placetype":"venue"
},
  "geometry": {"coordinates":[5.955093,52.218414],"type":"Point"}
}