{
  "type": "Feature",
  "properties": {
    "addr:full":"Banckertplein 157 Hendrik Ido Ambacht Zuid-Holland 3342 TG",
    "addr:housenumber":"157",
    "addr:postcode":"3342 tg",
    "addr:street":"Banckertplein",
    "iso:country":"NL",
    "sg:address":"Banckertplein 157",
    "sg:city":"Hendrik Ido Ambacht",
    "sg:orig_category":"Goederenvervoer Over De Weg",
    "sg:phone":"+31 78 681 8938",
    "sg:postcode":"3342 TG",
    "sg:province":"Zuid-Holland",
    "wof:name":"Transport Service Conceicao Tsc",
    "wof:placetype":"venue"
},
  "geometry": {"coordinates":[4.626304,51.846252],"type":"Point"}
}