{
  "type": "Feature",
  "properties": {
    "iso:country":"NL",
    "sg:address":"Louis Armstrongweg 23",
    "sg:city":"Almere",
    "sg:orig_category":"Geluidsopnamen",
    "sg:phone":"+31 36 546 5830",
    "sg:postcode":"1311 RJ",
    "sg:province":"Flevoland",
    "wof:name":"Studio La 23",
    "wof:placetype":"venue"
},
  "geometry": {"coordinates":[5.18747,52.367645],"type":"Point"}
}