{
  "type": "Feature",
  "properties": {
    "iso:country":"NL",
    "sg:address":"Startbaan 8",
    "sg:city":"Amstelveen",
    "sg:orig_category":"Krantenuitgeverijen",
    "sg:phone":"+31 20 545 5555",
    "sg:postcode":"1185 XR",
    "sg:province":"Noord-Holland",
    "wof:name":"Admedia Bv",
    "wof:placetype":"venue"
},
  "geometry": {"coordinates":[4.85246,52.286682],"type":"Point"}
}