{
  "type": "Feature",
  "properties": {
    "addr:full":"Oortlaan 1 Utrecht Utrecht 3572 ZM",
    "addr:housenumber":"1",
    "addr:postcode":"3572 zm",
    "addr:street":"Oortlaan",
    "iso:country":"NL",
    "sg:address":"Oortlaan 1",
    "sg:city":"Utrecht",
    "sg:classifiers":[
        {
            "category":"Education",
            "subcategory":"Preschool",
            "type":"Public Place"
        }
    ],
    "sg:phone":"+31 30 271 7436",
    "sg:postcode":"3572 ZM",
    "sg:province":"Utrecht",
    "sg:tags":[
        "kleuteronderwijs",
        "basis-"
    ],
    "wof:name":"Gereformeerde Basisschool De Wissel",
    "wof:placetype":"venue"
},
  "geometry": {"coordinates":[5.139137,52.100975],"type":"Point"}
}