{
  "type": "Feature",
  "properties": {
    "addr:full":"Oudelandsdk 4 Spykerboor Nh North Holland 1458 PN",
    "addr:housenumber":"4",
    "addr:postcode":"1458 pn",
    "addr:street":"Oudelandsdk;Nh North",
    "iso:country":"NL",
    "sg:address":"Oudelandsdk 4",
    "sg:city":"Spykerboor Nh",
    "sg:orig_category":"Bouwmachines",
    "sg:phone":"+31 75 641 1451",
    "sg:postcode":"1458 PN",
    "sg:province":"North Holland",
    "wof:name":"Tiel Service, Van",
    "wof:placetype":"venue"
},
  "geometry": {"coordinates":[4.834611,52.538097],"type":"Point"}
}