{
  "type": "Feature",
  "properties": {
    "addr:full":"Brugstr 17 A Gennep Limburg 6591 BA",
    "addr:housenumber":"17 a",
    "addr:postcode":"6591 ba",
    "addr:street":"Brugstr",
    "iso:country":"NL",
    "sg:address":"Brugstr 17 A",
    "sg:city":"Gennep",
    "sg:orig_category":"Verenigingsgebouwen",
    "sg:phone":"+31 485 515 382",
    "sg:postcode":"6591 BA",
    "sg:province":"Limburg",
    "wof:name":"Zo Wie Zo",
    "wof:placetype":"venue"
},
  "geometry": {"coordinates":[5.969944,51.698761],"type":"Point"}
}