{
  "type": "Feature",
  "properties": {
    "addr:full":"Stationswg 65B Zuidlaren Drenthe 9471 GL",
    "addr:housenumber":"65b",
    "addr:postcode":"9471 gl",
    "addr:street":"Stationswg",
    "iso:country":"NL",
    "sg:address":"Stationswg 65B",
    "sg:city":"Zuidlaren",
    "sg:orig_category":"Kinderkleding",
    "sg:phone":"+31 50 409 6080",
    "sg:postcode":"9471 GL",
    "sg:province":"Drenthe",
    "wof:name":"Pico Bello",
    "wof:placetype":"venue"
},
  "geometry": {"coordinates":[6.678541,53.091759],"type":"Point"}
}