{
  "type": "Feature",
  "properties": {
    "addr:full":"Brantjesstr 55 Purmerend Noord-Holland 1447 PL",
    "addr:housenumber":"55",
    "addr:postcode":"1447 pl",
    "addr:street":"Brantjesstr",
    "iso:country":"NL",
    "sg:address":"Brantjesstr 55",
    "sg:city":"Purmerend",
    "sg:orig_category":"Adviesbureaus Bedrijfsorganisatie",
    "sg:phone":"+31 299 461 804",
    "sg:postcode":"1447 PL",
    "sg:province":"Noord-Holland",
    "wof:name":"Kammeijer",
    "wof:placetype":"venue"
},
  "geometry": {"coordinates":[4.973958,52.487919],"type":"Point"}
}