{
  "type": "Feature",
  "properties": {
    "addr:full":"Lieven De Keystraat 4 Almere NL. 1333 NP",
    "addr:housenumber":"4",
    "addr:postcode":"1333 np",
    "addr:street":"Lieven De Keystraat;Nl.",
    "iso:country":"NL",
    "sg:address":"Lieven De Keystraat 4",
    "sg:city":"Almere",
    "sg:orig_category":"Onderhoud And Reparatie Kantoorapparatuur",
    "sg:phone":"+31 36 537 2564",
    "sg:postcode":"1333 NP",
    "sg:province":"NL.",
    "wof:name":"Compufix",
    "wof:placetype":"venue"
},
  "geometry": {"coordinates":[5.256564,52.392391],"type":"Point"}
}