{
  "type": "Feature",
  "properties": {
    "addr:full":"Statenln 92 S Gravenhage South Holland 2582 GT",
    "addr:housenumber":"92",
    "addr:postcode":"2582 gt",
    "addr:street":"Statenln;S Gravenhage",
    "iso:country":"NL",
    "sg:address":"Statenln 92",
    "sg:city":"S Gravenhage",
    "sg:orig_category":"Acupunctuur",
    "sg:phone":"+31 70 355 5111",
    "sg:postcode":"2582 GT",
    "sg:province":"South Holland",
    "wof:name":"The, Ing Lok",
    "wof:placetype":"venue"
},
  "geometry": {"coordinates":[4.27852,52.092411],"type":"Point"}
}