{
  "type": "Feature",
  "properties": {
    "addr:full":"Duinwg 4 Nes Ameland Friesland 9163 GH",
    "addr:housenumber":"4",
    "addr:postcode":"9163 gh",
    "addr:street":"Duinwg",
    "iso:country":"NL",
    "sg:address":"Duinwg 4",
    "sg:city":"Nes Ameland",
    "sg:classifiers":[
        {
            "category":"Banks & Credit Unions",
            "subcategory":"Investment Brokerage",
            "type":"Services"
        }
    ],
    "sg:phone":"+31 519 542 427",
    "sg:postcode":"9163 GH",
    "sg:province":"Friesland",
    "sg:tags":[
        "pension"
    ],
    "wof:name":"Bakema",
    "wof:placetype":"venue"
},
  "geometry": {"coordinates":[5.768717,53.447487],"type":"Point"}
}