{
  "type": "Feature",
  "properties": {
    "addr:full":"Energiestr 9B Geesbrug Provincie Drenthe 7917 RB",
    "addr:housenumber":"9b",
    "addr:postcode":"7917 rb",
    "addr:street":"Energiestr;Provincie Drenthe",
    "iso:country":"NL",
    "sg:address":"Energiestr 9B",
    "sg:city":"Geesbrug",
    "sg:orig_category":"Autopoetsbedrijven",
    "sg:phone":"+31 528 351 010",
    "sg:postcode":"7917 RB",
    "sg:province":"Provincie Drenthe",
    "wof:name":"Patrick",
    "wof:placetype":"venue"
},
  "geometry": {"coordinates":[6.63214,52.727962],"type":"Point"}
}