{
  "type": "Feature",
  "properties": {
    "addr:full":"Zylwg 47 Haarlem Noord-Holland 2013 DC",
    "addr:housenumber":"47",
    "addr:postcode":"2013",
    "addr:street":"Zylwg",
    "iso:country":"NL",
    "sg:address":"Zylwg 47",
    "sg:city":"Haarlem",
    "sg:orig_category":"Horloges En Klokken - Reparatie En Onderhoud",
    "sg:phone":"+31 23 531 4492",
    "sg:postcode":"2013 DC",
    "sg:province":"Noord-Holland",
    "wof:name":"Mienis & Zn, H",
    "wof:placetype":"venue"
},
  "geometry": {"coordinates":[4.642253,52.380562],"type":"Point"}
}