{
  "type": "Feature",
  "properties": {
    "iso:country":"NL",
    "sg:address":"Industrieweg 9",
    "sg:city":"Amersfoort",
    "sg:orig_category":"Autokeuringen",
    "sg:phone":"+31 33 465 0827",
    "sg:postcode":"3812 RX",
    "sg:province":"Utrecht",
    "wof:name":"Texaco",
    "wof:placetype":"venue"
},
  "geometry": {"coordinates":[5.371762,52.163494],"type":"Point"}
}