{
  "type": "Feature",
  "properties": {
    "addr:full":"Grote Doelenlaan 8 Sint Oedenrode Noord-Brabant 5491 EG",
    "addr:housenumber":"8;oedenrode",
    "addr:postcode":"5491 eg",
    "addr:street":"Grote Doelenlaan",
    "iso:country":"NL",
    "sg:address":"Grote Doelenlaan 8",
    "sg:city":"Sint Oedenrode",
    "sg:orig_category":"Fotostudio'S And Fotografen",
    "sg:phone":"+31 413 477 895",
    "sg:postcode":"5491 EG",
    "sg:province":"Noord-Brabant",
    "wof:name":"Fotografie Gerard V.D. Wijdeven",
    "wof:placetype":"venue"
},
  "geometry": {"coordinates":[5.466873,51.570999],"type":"Point"}
}