{
  "type": "Feature",
  "properties": {
    "addr:full":"Pannekoekstraat 45 Rotterdam Zuid-Holland 3011 LC",
    "addr:housenumber":"45",
    "addr:postcode":"3011 lc",
    "addr:street":"Pannekoekstraat",
    "iso:country":"NL",
    "sg:address":"Pannekoekstraat 45",
    "sg:city":"Rotterdam",
    "sg:orig_category":"Schoenen",
    "sg:phone":"+31 10 412 6459",
    "sg:postcode":"3011 LC",
    "sg:province":"Zuid-Holland",
    "wof:name":"Chr Van Den Aarsen",
    "wof:placetype":"venue"
},
  "geometry": {"coordinates":[4.487456,51.923462],"type":"Point"}
}