{
  "type": "Feature",
  "properties": {
    "iso:country":"NL",
    "sg:address":"Kerkpln 50",
    "sg:city":"Voerendaal",
    "sg:orig_category":"Opticiens",
    "sg:phone":"+31 45 575 0986",
    "sg:postcode":"6367 ES",
    "sg:province":"Limburg",
    "wof:name":"Kreutzer",
    "wof:placetype":"venue"
},
  "geometry": {"coordinates":[5.9274120331,50.8829689026],"type":"Point"}
}