{
  "type": "Feature",
  "properties": {
    "addr:full":"Ter Stegestraat 23 Olst Overijssel 8121 XB",
    "addr:housenumber":"23",
    "addr:postcode":"8121 xb",
    "addr:street":"Ter Stegestraat",
    "iso:country":"NL",
    "sg:address":"Ter Stegestraat 23",
    "sg:city":"Olst",
    "sg:classifiers":[
        {
            "category":"Education",
            "subcategory":"Preschool",
            "type":"Public Place"
        }
    ],
    "sg:phone":"+31 570 561 805",
    "sg:postcode":"8121 XB",
    "sg:province":"Overijssel",
    "sg:tags":[
        "kleuteronderwijs",
        "basis-"
    ],
    "wof:name":"Openbare Basisschool Ter Stege",
    "wof:placetype":"venue"
},
  "geometry": {"coordinates":[6.1148428917,52.3397636414],"type":"Point"}
}