{
  "type": "Feature",
  "properties": {
    "iso:country":"NL",
    "sg:address":"Parkweg 38",
    "sg:city":"Maastricht",
    "sg:orig_category":"Architecten",
    "sg:phone":"+31 43 321 4555",
    "sg:postcode":"6212 XN",
    "sg:province":"Limburg",
    "wof:name":"Architectenbureau Ir. D. Noordman Bna",
    "wof:placetype":"venue"
},
  "geometry": {"coordinates":[5.696364,50.840359],"type":"Point"}
}