{
  "type": "Feature",
  "properties": {
    "addr:full":"Gildenveld 35 Zeewolde Flevoland 3892 DD",
    "addr:housenumber":"35",
    "addr:postcode":"3892 dd",
    "addr:street":"Gildenveld;Flevoland",
    "iso:country":"NL",
    "sg:address":"Gildenveld 35",
    "sg:city":"Zeewolde",
    "sg:orig_category":"Projectontwikkeling",
    "sg:phone":"+31 36 522 4780",
    "sg:postcode":"3892 DD",
    "sg:province":"Flevoland",
    "wof:name":"Invo Bv",
    "wof:placetype":"venue"
},
  "geometry": {"coordinates":[5.530209,52.325237],"type":"Point"}
}