{
  "type": "Feature",
  "properties": {
    "addr:full":"Florijn 66 Hoorn Nh Noord-Holland 1628 RL",
    "addr:housenumber":"66",
    "addr:postcode":"1628 rl",
    "addr:street":"Florijn",
    "iso:country":"NL",
    "sg:address":"Florijn 66",
    "sg:city":"Hoorn Nh",
    "sg:orig_category":"Wegen And Sportterreinen",
    "sg:phone":"+31 229 249 227",
    "sg:postcode":"1628 RL",
    "sg:province":"Noord-Holland",
    "wof:name":"J.J.P. Vlaar",
    "wof:placetype":"venue"
},
  "geometry": {"coordinates":[5.0922861099,52.6483802795],"type":"Point"}
}