{
  "type": "Feature",
  "properties": {
    "addr:full":"De S Lohmanplnts 77 Voorschoten Zuid-Holland 2253 VN",
    "addr:housenumber":"77",
    "addr:postcode":"2253 vn",
    "addr:street":"De",
    "iso:country":"NL",
    "sg:address":"De S Lohmanplnts 77",
    "sg:city":"Voorschoten",
    "sg:orig_category":"Adviesbureaus Bedrijfsorganisatie",
    "sg:phone":"+31 71 576 3990",
    "sg:postcode":"2253 VN",
    "sg:province":"Zuid-Holland",
    "sg:website":"http://www.cirkels.nl",
    "wof:name":"Cirkels",
    "wof:placetype":"venue"
},
  "geometry": {"coordinates":[4.44429,52.124825],"type":"Point"}
}