{
  "type": "Feature",
  "properties": {
    "addr:full":"Oranjestraat 1 Didam Gelderland 6942 BD",
    "addr:housenumber":"1",
    "addr:postcode":"6942 bd",
    "addr:street":"Oranjestraat;Gelderland",
    "iso:country":"NL",
    "sg:address":"Oranjestraat 1",
    "sg:city":"Didam",
    "sg:orig_category":"Schoenen",
    "sg:phone":"+31 316 221 388",
    "sg:postcode":"6942 BD",
    "sg:province":"Gelderland",
    "wof:name":"Fa. Ros Schoenhandel",
    "wof:placetype":"venue"
},
  "geometry": {"coordinates":[6.128507,51.937588],"type":"Point"}
}