{
  "type": "Feature",
  "properties": {
    "addr:full":"De Afslag 7 Nieuw Amsterdam Drenthe 7833 HW",
    "addr:housenumber":"7",
    "addr:postcode":"7833 hw",
    "addr:street":"De Afslag;Nieuw",
    "iso:country":"NL",
    "sg:address":"De Afslag 7",
    "sg:city":"Nieuw Amsterdam",
    "sg:classifiers":[
        {
            "category":"Food & Beverages",
            "subcategory":"Fruits & Vegetables",
            "type":"Retail Goods"
        }
    ],
    "sg:phone":"+31 591 577 577",
    "sg:postcode":"7833 HW",
    "sg:province":"Drenthe",
    "sg:tags":[
        "groenten"
    ],
    "wof:name":"Jager Holland Bv",
    "wof:placetype":"venue"
},
  "geometry": {"coordinates":[-74.146919,42.940887],"type":"Point"}
}