{
  "type": "Feature",
  "properties": {
    "addr:full":"In De Houtzaagmolen 4 Duivendrecht Noord-Holland 1115 GJ",
    "addr:housenumber":"4",
    "addr:postcode":"1115 gj",
    "addr:street":"In De Houtzaagmolen",
    "iso:country":"NL",
    "sg:address":"In De Houtzaagmolen 4",
    "sg:city":"Duivendrecht",
    "sg:orig_category":"Beautyfarms And Sauna'S",
    "sg:phone":"+31 20 416 0078",
    "sg:postcode":"1115 GJ",
    "sg:province":"Noord-Holland",
    "wof:name":"S.J. Jansen",
    "wof:placetype":"venue"
},
  "geometry": {"coordinates":[4.94432,52.332905],"type":"Point"}
}