{
  "type": "Feature",
  "properties": {
    "addr:full":"Ln V Meerdervoort 467 S Gravenhage Zuid-Holland 2563 AT",
    "addr:housenumber":"467;gravenhage",
    "addr:postcode":"2563",
    "addr:street":"Ln;Meerdervoort;S",
    "iso:country":"NL",
    "sg:address":"Ln V Meerdervoort 467",
    "sg:city":"S Gravenhage",
    "sg:orig_category":"Glas, Porselein En Aardewerk",
    "sg:phone":"+31 70 345 8864",
    "sg:postcode":"2563 AT",
    "sg:province":"Zuid-Holland",
    "wof:name":"Kandelaar, De",
    "wof:placetype":"venue"
},
  "geometry": {"coordinates":[4.270956,52.072578],"type":"Point"}
}