{
  "type": "Feature",
  "properties": {
    "addr:full":"Roosendaalsestraat 33 Wouw Noord-Brabant 4724 AA",
    "addr:housenumber":"33",
    "addr:postcode":"4724 aa",
    "addr:street":"Roosendaalsestraat",
    "iso:country":"NL",
    "sg:address":"Roosendaalsestraat 33",
    "sg:city":"Wouw",
    "sg:orig_category":"Verlichting And Huishoudartikelen",
    "sg:phone":"+31 165 302 757",
    "sg:postcode":"4724 AA",
    "sg:province":"Noord-Brabant",
    "wof:name":"Karien Woningstoffering",
    "wof:placetype":"venue"
},
  "geometry": {"coordinates":[4.390439,51.524002],"type":"Point"}
}