{
  "type": "Feature",
  "properties": {
    "addr:full":"Vincentiusstr 56 Roosendaal Noord-Brabant 4701 LR",
    "addr:housenumber":"56",
    "addr:postcode":"4701 lr",
    "addr:street":"Vincentiusstr",
    "iso:country":"NL",
    "sg:address":"Vincentiusstr 56",
    "sg:city":"Roosendaal",
    "sg:orig_category":"Verenigingen En Stichtingen",
    "sg:phone":"+31 165 564 186",
    "sg:postcode":"4701 LR",
    "sg:province":"Noord-Brabant",
    "wof:name":"Kader, Sticht",
    "wof:placetype":"venue"
},
  "geometry": {"coordinates":[4.456688,51.537724],"type":"Point"}
}