{
  "type": "Feature",
  "properties": {
    "addr:full":"Gronausestr 150 Losser Overijssel 7581 CK",
    "addr:housenumber":"150",
    "addr:postcode":"7581 ck",
    "iso:country":"NL",
    "sg:address":"Gronausestr 150",
    "sg:city":"Losser",
    "sg:classifiers":[
        {
            "category":"Retail",
            "subcategory":"Auto Repair",
            "type":"Services"
        }
    ],
    "sg:phone":"+31 53 538 1275",
    "sg:postcode":"7581 CK",
    "sg:province":"Overijssel",
    "sg:tags":[
        "garage"
    ],
    "wof:name":"Schorfhaar Bv",
    "wof:placetype":"venue"
},
  "geometry": {"coordinates":[7.009283,52.255714],"type":"Point"}
}