{
  "type": "Feature",
  "properties": {
    "addr:full":"Orpheusl 1 Eindhoven North Brabant 5631 BP",
    "addr:housenumber":"1",
    "addr:postcode":"5631 bp",
    "addr:street":"Orpheusl",
    "iso:country":"NL",
    "sg:address":"Orpheusl 1",
    "sg:city":"Eindhoven",
    "sg:orig_category":"Artsen - Huisartsen",
    "sg:phone":"+31 40 295 0955",
    "sg:postcode":"5631 BP",
    "sg:province":"North Brabant",
    "wof:name":"Dassen, P J G",
    "wof:placetype":"venue"
},
  "geometry": {"coordinates":[5.50844,51.45776],"type":"Point"}
}