{
  "type": "Feature",
  "properties": {
    "addr:full":"Hoofdstr 332 Bovenkarspel Noord-Holland 1611 AP",
    "addr:housenumber":"332",
    "addr:postcode":"1611 ap",
    "iso:country":"NL",
    "sg:address":"Hoofdstr 332",
    "sg:city":"Bovenkarspel",
    "sg:orig_category":"Kaas",
    "sg:phone":"+31 228 516 269",
    "sg:postcode":"1611 AP",
    "sg:province":"Noord-Holland",
    "wof:name":"Floor",
    "wof:placetype":"venue"
},
  "geometry": {"coordinates":[5.258038044,52.6995162964],"type":"Point"}
}