{
  "type": "Feature",
  "properties": {
    "addr:full":"Schavenweide 1 Doetinchem Gelderland 7003 EA",
    "addr:housenumber":"1",
    "addr:postcode":"7003 ea",
    "addr:street":"Schavenweide;Gelderland",
    "iso:country":"NL",
    "sg:address":"Schavenweide 1",
    "sg:city":"Doetinchem",
    "sg:orig_category":"Bejaarden - Verzorgingstehuizen",
    "sg:phone":"+31 314 333 651",
    "sg:postcode":"7003 EA",
    "sg:province":"Gelderland",
    "wof:name":"Schavenweide",
    "wof:placetype":"venue"
},
  "geometry": {"coordinates":[6.30189,51.961514],"type":"Point"}
}