{
  "type": "Feature",
  "properties": {
    "addr:full":"Beechavenue 101 Schiphol Ryk Noord-Holland 1119 RB",
    "addr:housenumber":"101",
    "addr:postcode":"1119 rb",
    "addr:street":"Beechavenue",
    "iso:country":"NL",
    "sg:address":"Beechavenue 101",
    "sg:city":"Schiphol Ryk",
    "sg:orig_category":"Reisbureaus",
    "sg:phone":"+31 20 201 1211",
    "sg:postcode":"1119 RB",
    "sg:province":"Noord-Holland",
    "sg:website":"http://www.odysseus.com",
    "wof:name":"Odysseus",
    "wof:placetype":"venue"
},
  "geometry": {"coordinates":[4.746734,52.279755],"type":"Point"}
}