{
  "type": "Feature",
  "properties": {
    "iso:country":"NL",
    "sg:address":"Leliestr 1",
    "sg:city":"Eindhoven",
    "sg:orig_category":"Adviesbureaus Bouwkunde",
    "sg:phone":"+31 40 211 4091",
    "sg:postcode":"5615 BK",
    "sg:province":"Noord-Brabant",
    "wof:name":"Zaal, Ype",
    "wof:placetype":"venue"
},
  "geometry": {"coordinates":[5.490039,51.424168],"type":"Point"}
}