{
  "type": "Feature",
  "properties": {
    "addr:full":"Geldersestraat 30 Geldermalsen Gelderland 4191 BC",
    "addr:housenumber":"30",
    "addr:postcode":"4191 bc",
    "addr:street":"Geldersestraat;Gelderland",
    "iso:country":"NL",
    "sg:address":"Geldersestraat 30",
    "sg:city":"Geldermalsen",
    "sg:orig_category":"Huishoudapparatuur, Televisies And Radio'S",
    "sg:phone":"+31 345 571 227",
    "sg:postcode":"4191 BC",
    "sg:province":"Gelderland",
    "wof:name":"J. Verhagen",
    "wof:placetype":"venue"
},
  "geometry": {"coordinates":[5.291314,51.883022],"type":"Point"}
}