{
  "type": "Feature",
  "properties": {
    "iso:country":"NL",
    "sg:address":"Nieuwestg 5",
    "sg:city":"Leeuwarden",
    "sg:orig_category":"Musea",
    "sg:phone":"+31 58 215 3427",
    "sg:postcode":"8911 DT",
    "sg:province":"Provincie Friesland",
    "wof:name":"Museumwinkel",
    "wof:placetype":"venue"
},
  "geometry": {"coordinates":[5.793114,53.201576],"type":"Point"}
}