{
  "type": "Feature",
  "properties": {
    "addr:full":"H Geeststr 28A Venlo Limburg 5911 JA",
    "addr:housenumber":"28a",
    "addr:postcode":"5911 ja",
    "iso:country":"NL",
    "sg:address":"H Geeststr 28A",
    "sg:city":"Venlo",
    "sg:orig_category":"Herenkleding",
    "sg:phone":"+31 77 351 1002",
    "sg:postcode":"5911 JA",
    "sg:province":"Limburg",
    "wof:name":"Uomo",
    "wof:placetype":"venue"
},
  "geometry": {"coordinates":[6.16784,51.369545],"type":"Point"}
}