{
  "type": "Feature",
  "properties": {
    "addr:full":"Akkerstraat 17 Eindhoven Noord-Brabant 5615 HP",
    "addr:housenumber":"17",
    "addr:postcode":"5615 hp",
    "addr:street":"Akkerstraat",
    "iso:country":"NL",
    "sg:address":"Akkerstraat 17",
    "sg:city":"Eindhoven",
    "sg:orig_category":"Binnenhuisarchitecten",
    "sg:phone":"+31 40 244 5403",
    "sg:postcode":"5615 HP",
    "sg:province":"Noord-Brabant",
    "wof:name":"Binnenhuisarchitectenbureau M. Glas",
    "wof:placetype":"venue"
},
  "geometry": {"coordinates":[5.474796,51.432621],"type":"Point"}
}