{
  "type": "Feature",
  "properties": {
    "addr:full":"Herenstr 67 Voorburg Zuid-Holland 2271 CB",
    "addr:housenumber":"67",
    "addr:postcode":"2271 cb",
    "addr:street":"Herenstr",
    "iso:country":"NL",
    "sg:address":"Herenstr 67",
    "sg:city":"Voorburg",
    "sg:orig_category":"Opticiens",
    "sg:phone":"+31 70 386 3302",
    "sg:postcode":"2271 CB",
    "sg:province":"Zuid-Holland",
    "sg:website":"http://www.irisoptiek.com",
    "wof:name":"Iris",
    "wof:placetype":"venue"
},
  "geometry": {"coordinates":[4.3647689819,52.0679512024],"type":"Point"}
}