{
  "type": "Feature",
  "properties": {
    "addr:full":"Gronausestr 1080 Enschede Overijssel 7534 AP",
    "addr:housenumber":"1080",
    "addr:postcode":"7534 ap",
    "iso:country":"NL",
    "sg:address":"Gronausestr 1080",
    "sg:city":"Enschede",
    "sg:orig_category":"Wijnkoperijen En -Groothandel",
    "sg:phone":"+31 53 461 5454",
    "sg:postcode":"7534 AP",
    "sg:province":"Overijssel",
    "wof:name":"Koershuis",
    "wof:placetype":"venue"
},
  "geometry": {"coordinates":[6.9548602104,52.2164001465],"type":"Point"}
}