{
  "type": "Feature",
  "properties": {
    "addr:full":"Kasteel 1 Diever Drenthe 7981 AN",
    "addr:housenumber":"1",
    "addr:postcode":"7981 an",
    "addr:street":"Kasteel",
    "iso:country":"NL",
    "sg:address":"Kasteel 1",
    "sg:city":"Diever",
    "sg:orig_category":"Levende Dieren Gh",
    "sg:phone":"+31 521 593 267",
    "sg:postcode":"7981 AN",
    "sg:province":"Drenthe",
    "wof:name":"Vee- En Varkenshandel M. Boers",
    "wof:placetype":"venue"
},
  "geometry": {"coordinates":[6.322034,52.856339],"type":"Point"}
}