{
  "type": "Feature",
  "properties": {
    "addr:full":"Bosschewg 39 Drunen Noord-Brabant 5151 BA",
    "addr:housenumber":"39",
    "addr:postcode":"5151 ba",
    "addr:street":"Bosschewg",
    "iso:country":"NL",
    "sg:address":"Bosschewg 39",
    "sg:city":"Drunen",
    "sg:orig_category":"Sportverenigingen En Ontspannings- Verenigingen",
    "sg:phone":"+31 416 379 103",
    "sg:postcode":"5151 BA",
    "sg:province":"Noord-Brabant",
    "wof:name":"Covs De Langstraat",
    "wof:placetype":"venue"
},
  "geometry": {"coordinates":[5.150487,51.686977],"type":"Point"}
}