{
  "type": "Feature",
  "properties": {
    "addr:full":"Zeeburgerpad 74 Amsterdam Noord-Holland 1019 AD",
    "addr:housenumber":"74",
    "addr:postcode":"1019 ad",
    "addr:street":"Zeeburgerpad",
    "iso:country":"NL",
    "sg:address":"Zeeburgerpad 74",
    "sg:city":"Amsterdam",
    "sg:orig_category":"Geluidsisolatie",
    "sg:phone":"+31 20 694 8415",
    "sg:postcode":"1019 AD",
    "sg:province":"Noord-Holland",
    "wof:name":"No-Decibel",
    "wof:placetype":"venue"
},
  "geometry": {"coordinates":[4.942411,52.367058],"type":"Point"}
}