{
  "type": "Feature",
  "properties": {
    "addr:full":"Ringbaan N 85 Tilburg North Brabant 5046 AA",
    "addr:housenumber":"85",
    "addr:postcode":"5046 aa",
    "addr:street":"Ringbaan N",
    "iso:country":"NL",
    "sg:address":"Ringbaan N 85",
    "sg:city":"Tilburg",
    "sg:orig_category":"Verzekeringen - Verzekeringskantoren",
    "sg:phone":"+31 13 581 2560",
    "sg:postcode":"5046 AA",
    "sg:province":"North Brabant",
    "wof:name":"Ondernemers Bv, Bur Voor",
    "wof:placetype":"venue"
},
  "geometry": {"coordinates":[5.07169,51.575981],"type":"Point"}
}