{
  "type": "Feature",
  "properties": {
    "addr:full":"Turfspoor 195 Lisserbroek North Holland 2165 AW",
    "addr:housenumber":"195",
    "addr:postcode":"2165 aw",
    "addr:street":"Turfspoor",
    "iso:country":"NL",
    "sg:address":"Turfspoor 195",
    "sg:city":"Lisserbroek",
    "sg:orig_category":"Kantoor- En Interieurbeplanting",
    "sg:phone":"+31 252 418 519",
    "sg:postcode":"2165 AW",
    "sg:province":"North Holland",
    "wof:name":"Maris, Van",
    "wof:placetype":"venue"
},
  "geometry": {"coordinates":[4.56975317,52.2436714172],"type":"Point"}
}