{
  "type": "Feature",
  "properties": {
    "addr:full":"L Amerikawg 163 Apeldoorn Gelderland 7332 BP",
    "addr:housenumber":"163",
    "addr:postcode":"7332 bp",
    "addr:street":"Gelderland",
    "iso:country":"NL",
    "sg:address":"L Amerikawg 163",
    "sg:city":"Apeldoorn",
    "sg:orig_category":"Kopieerservice",
    "sg:phone":"+31 55 533 6634",
    "sg:postcode":"7332 BP",
    "sg:province":"Gelderland",
    "sg:website":"http://www.multicopy.com",
    "wof:name":"Multicopy Apeldoorn",
    "wof:placetype":"venue"
},
  "geometry": {"coordinates":[5.98991,52.181339],"type":"Point"}
}