{
  "type": "Feature",
  "properties": {
    "addr:full":"Kykduinsestr 878 S Gravenhage Zuid-Holland 2554 AC",
    "addr:housenumber":"878;gravenhage",
    "addr:postcode":"2554 ac",
    "addr:street":"S",
    "iso:country":"NL",
    "sg:address":"Kykduinsestr 878",
    "sg:city":"S Gravenhage",
    "sg:orig_category":"Bloemen En Planten - Decoratie",
    "sg:phone":"+31 70 325 8012",
    "sg:postcode":"2554 AC",
    "sg:province":"Zuid-Holland",
    "wof:name":"Lew-Lew",
    "wof:placetype":"venue"
},
  "geometry": {"coordinates":[4.22476,52.067989],"type":"Point"}
}