{
  "type": "Feature",
  "properties": {
    "addr:full":"Haemstedelaan 2 Heemstede North Holland 2101 WG",
    "addr:housenumber":"2",
    "addr:postcode":"2101 wg",
    "addr:street":"Haemstedelaan",
    "iso:country":"NL",
    "sg:address":"Haemstedelaan 2",
    "sg:city":"Heemstede",
    "sg:classifiers":[
        {
            "category":"Food & Beverages",
            "subcategory":"Fruits & Vegetables",
            "type":"Retail Goods"
        }
    ],
    "sg:phone":"+31 23 529 2129",
    "sg:postcode":"2101 WG",
    "sg:province":"North Holland",
    "sg:tags":[
        "groenten"
    ],
    "wof:name":"John Schilder Groente & Fruit",
    "wof:placetype":"venue"
},
  "geometry": {"coordinates":[4.621665,52.350735],"type":"Point"}
}