{
  "type": "Feature",
  "properties": {
    "addr:full":"Ridderspoorstraat 2 Den Bosch North Brabant 5221 XP",
    "addr:housenumber":"2",
    "addr:postcode":"5221 xp",
    "addr:street":"Ridderspoorstraat",
    "iso:country":"NL",
    "sg:address":"Ridderspoorstraat 2",
    "sg:city":"Den Bosch",
    "sg:orig_category":"Meubelreparatie And -Restauratie",
    "sg:phone":"+31 73 613 1974",
    "sg:postcode":"5221 XP",
    "sg:province":"North Brabant",
    "wof:name":"De Cirkel Kringloopbedrijf Den Bosch",
    "wof:placetype":"venue"
},
  "geometry": {"coordinates":[5.271835,51.720615],"type":"Point"}
}