{
  "type": "Feature",
  "properties": {
    "iso:country":"NL",
    "sg:address":"Zeldenruststraat 5",
    "sg:city":"Heerhugowaard",
    "sg:orig_category":"Sportcentra",
    "sg:phone":"+31 72 574 3851",
    "sg:postcode":"1704 BR",
    "sg:province":"North Holland",
    "wof:name":"Sporthal Noorderend",
    "wof:placetype":"venue"
},
  "geometry": {"coordinates":[4.8538,52.706589],"type":"Point"}
}