{
  "type": "Feature",
  "properties": {
    "addr:full":"Peelhorst 18 Deurne Noord-Brabant 5754 GR",
    "addr:housenumber":"18",
    "addr:postcode":"5754",
    "addr:street":"Peelhorst",
    "iso:country":"NL",
    "sg:address":"Peelhorst 18",
    "sg:city":"Deurne",
    "sg:orig_category":"Diverse Dierenfokkers",
    "sg:phone":"+31 493 317 411",
    "sg:postcode":"5754 GR",
    "sg:province":"Noord-Brabant",
    "wof:name":"Mibron Bv",
    "wof:placetype":"venue"
},
  "geometry": {"coordinates":[5.814239,51.462921],"type":"Point"}
}