{
  "type": "Feature",
  "properties": {
    "iso:country":"NL",
    "sg:address":"Bankastr 70",
    "sg:city":"S Gravenhage",
    "sg:orig_category":"Bloemen En Planten",
    "sg:phone":"+31 70 355 8544",
    "sg:postcode":"2585 EP",
    "sg:province":"Zuid-Holland",
    "wof:name":"Heemskerk & Zoon, Jac",
    "wof:placetype":"venue"
},
  "geometry": {"coordinates":[4.29777,52.094799],"type":"Point"}
}