{
  "type": "Feature",
  "properties": {
    "addr:full":"Waterwolf 29 Bemmel Gelderland 6681 TH",
    "addr:housenumber":"29",
    "addr:postcode":"6681 th",
    "addr:street":"Waterwolf;Gelderland",
    "iso:country":"NL",
    "sg:address":"Waterwolf 29",
    "sg:city":"Bemmel",
    "sg:orig_category":"Keukens",
    "sg:phone":"+31 481 452 991",
    "sg:postcode":"6681 TH",
    "sg:province":"Gelderland",
    "sg:website":"http://cucineitalia.nl",
    "wof:name":"Keuken Interieur, Het",
    "wof:placetype":"venue"
},
  "geometry": {"coordinates":[5.918089,51.890293],"type":"Point"}
}