{
  "type": "Feature",
  "properties": {
    "addr:full":"Zomerdk 35 Meppel Drenthe 7942 JS",
    "addr:housenumber":"35",
    "addr:postcode":"7942 js",
    "addr:street":"Zomerdk",
    "iso:country":"NL",
    "sg:address":"Zomerdk 35",
    "sg:city":"Meppel",
    "sg:orig_category":"Jachthavens - Jachtwerven",
    "sg:phone":"+31 522 258 113",
    "sg:postcode":"7942 JS",
    "sg:province":"Drenthe",
    "wof:name":"Meppel Bv",
    "wof:placetype":"venue"
},
  "geometry": {"coordinates":[6.163696,52.692696],"type":"Point"}
}