{
  "type": "Feature",
  "properties": {
    "addr:full":"Luybenstr 25 S Hertogenbosch North Brabant 5211 BS",
    "addr:housenumber":"25",
    "addr:postcode":"5211 bs",
    "addr:street":"Luybenstr;S Hertogenbosch",
    "iso:country":"NL",
    "sg:address":"Luybenstr 25",
    "sg:city":"S Hertogenbosch",
    "sg:orig_category":"Loopbaanbegeleiding",
    "sg:phone":"+31 73 612 2521",
    "sg:postcode":"5211 BS",
    "sg:province":"North Brabant",
    "sg:website":"http://www.apa.nl",
    "wof:name":"Arbeids Psychologisch Advies",
    "wof:placetype":"venue"
},
  "geometry": {"coordinates":[5.296361,51.689819],"type":"Point"}
}