{
  "type": "Feature",
  "properties": {
    "addr:full":"Kuipery 13 Amstelveen Noord-Holland 1185 XS",
    "addr:housenumber":"13",
    "addr:postcode":"1185 xs",
    "addr:street":"Kuipery",
    "iso:country":"NL",
    "sg:address":"Kuipery 13",
    "sg:city":"Amstelveen",
    "sg:orig_category":"Drukkerijen",
    "sg:phone":"+31 20 545 6960",
    "sg:postcode":"1185 XS",
    "sg:province":"Noord-Holland",
    "wof:name":"Lenoir Schuring",
    "wof:placetype":"venue"
},
  "geometry": {"coordinates":[4.837592,52.282745],"type":"Point"}
}