{
  "type": "Feature",
  "properties": {
    "addr:full":"I Tademastr 53 Creil Flevoland 8312 AL",
    "addr:housenumber":"53",
    "addr:postcode":"8312",
    "addr:street":"Flevoland",
    "iso:country":"NL",
    "sg:address":"I Tademastr 53",
    "sg:city":"Creil",
    "sg:orig_category":"Kappers",
    "sg:phone":"+31 527 274 219",
    "sg:postcode":"8312 AL",
    "sg:province":"Flevoland",
    "wof:name":"Hoogeweg",
    "wof:placetype":"venue"
},
  "geometry": {"coordinates":[5.6599011421,52.7643432617],"type":"Point"}
}