{
  "type": "Feature",
  "properties": {
    "addr:full":"Hazenakkerstr 13 Oss Noord-Brabant 5343 EA",
    "addr:housenumber":"13",
    "addr:postcode":"5343 ea",
    "addr:street":"Hazenakkerstr",
    "iso:country":"NL",
    "sg:address":"Hazenakkerstr 13",
    "sg:city":"Oss",
    "sg:orig_category":"Verzekeringen - Verzekeringskantoren",
    "sg:phone":"+31 412 647 855",
    "sg:postcode":"5343 EA",
    "sg:province":"Noord-Brabant",
    "wof:name":"Aa Bv, Van Der",
    "wof:placetype":"venue"
},
  "geometry": {"coordinates":[-93.52149199999999,45.170681],"type":"Point"}
}