{
  "type": "Feature",
  "properties": {
    "iso:country":"NL",
    "sg:address":"Steenhuis 9",
    "sg:city":"Delfzyl",
    "sg:orig_category":"Fotostudio'S",
    "sg:phone":"+31 596 681 663",
    "sg:postcode":"9932 CH",
    "sg:province":"Groningen",
    "wof:name":"Molema, W",
    "wof:placetype":"venue"
},
  "geometry": {"coordinates":[6.891985,53.321938],"type":"Point"}
}