{
  "type": "Feature",
  "properties": {
    "addr:full":"Stadhouderskade 71 Amsterdam North Holland 1072 AE",
    "addr:housenumber":"71",
    "addr:postcode":"1072 ae",
    "addr:street":"Stadhouderskade",
    "iso:country":"NL",
    "sg:address":"Stadhouderskade 71",
    "sg:city":"Amsterdam",
    "sg:orig_category":"Kappers",
    "sg:phone":"+31 20 664 2285",
    "sg:postcode":"1072 AE",
    "sg:province":"North Holland",
    "wof:name":"Short Cut",
    "wof:placetype":"venue"
},
  "geometry": {"coordinates":[4.888632,52.358925],"type":"Point"}
}