{
  "type": "Feature",
  "properties": {
    "iso:country":"NL",
    "sg:address":"Haagwinde 83",
    "sg:city":"Abcoude",
    "sg:orig_category":"Journalisten Freelance",
    "sg:phone":"+31 294 283 623",
    "sg:postcode":"1391 XX",
    "sg:province":"Utrecht",
    "wof:name":"Dirks, Jeroen",
    "wof:placetype":"venue"
},
  "geometry": {"coordinates":[4.971947,52.277756],"type":"Point"}
}