{
  "type": "Feature",
  "properties": {
    "iso:country":"NL",
    "sg:address":"Edisonstraat 11",
    "sg:city":"Zoetermeer",
    "sg:orig_category":"Autokeuringen",
    "sg:phone":"+31 79 342 7800",
    "sg:postcode":"2723 RS",
    "sg:province":"Zuid-Holland",
    "wof:name":"Vof Kamphuis & De Bruyn",
    "wof:placetype":"venue"
},
  "geometry": {"coordinates":[4.521935,52.061714],"type":"Point"}
}