{
  "type": "Feature",
  "properties": {
    "addr:full":"Van Nijenrodeweg 349 Amsterdam Noord-Holland 1082 HD",
    "addr:housenumber":"349",
    "addr:postcode":"1082 hd",
    "addr:street":"Van Nijenrodeweg",
    "iso:country":"NL",
    "sg:address":"Van Nijenrodeweg 349",
    "sg:city":"Amsterdam",
    "sg:orig_category":"Vertaal- And Tolkenbureaus",
    "sg:phone":"+31 20 642 6319",
    "sg:postcode":"1082 HD",
    "sg:province":"Noord-Holland",
    "wof:name":"R.R. Blanken",
    "wof:placetype":"venue"
},
  "geometry": {"coordinates":[4.877954,52.327545],"type":"Point"}
}