{
  "type": "Feature",
  "properties": {
    "addr:full":"Grotestraat 62 Eibergen Gelderland 7151 BD",
    "addr:housenumber":"62",
    "addr:postcode":"7151 bd",
    "addr:street":"Grotestraat;Gelderland",
    "iso:country":"NL",
    "sg:address":"Grotestraat 62",
    "sg:city":"Eibergen",
    "sg:orig_category":"Werving And Selectie Van Tijdelijk Personeel And Uitzendkantoren",
    "sg:phone":"+31 545 461 080",
    "sg:postcode":"7151 BD",
    "sg:province":"Gelderland",
    "wof:name":"Randstad Uitzendbureau Bv",
    "wof:placetype":"venue"
},
  "geometry": {"coordinates":[6.6469779015,52.1028938293],"type":"Point"}
}