{
  "type": "Feature",
  "properties": {
    "iso:country":"NL",
    "sg:address":"Wilhelminastr 5",
    "sg:city":"Meteren",
    "sg:orig_category":"Adviesbureaus Economie",
    "sg:phone":"+31 345 569 898",
    "sg:postcode":"4194 TT",
    "sg:province":"Gelderland",
    "wof:name":"Oso Loco Bv",
    "wof:placetype":"venue"
},
  "geometry": {"coordinates":[5.28462,51.864677],"type":"Point"}
}