{
  "type": "Feature",
  "properties": {
    "addr:full":"C De Vriesweg 51 Dirkshorn Noord-Holland 1746 CM",
    "addr:housenumber":"51",
    "addr:postcode":"1746 cm",
    "addr:street":"C De Vriesweg",
    "iso:country":"NL",
    "sg:address":"C De Vriesweg 51",
    "sg:city":"Dirkshorn",
    "sg:orig_category":"Architecten",
    "sg:phone":"+31 224 551 941",
    "sg:postcode":"1746 CM",
    "sg:province":"Noord-Holland",
    "wof:name":"Sjaak Dekker Projecten Bv",
    "wof:placetype":"venue"
},
  "geometry": {"coordinates":[4.778507,52.731682],"type":"Point"}
}