{
  "type": "Feature",
  "properties": {
    "addr:full":"Wilhelminapark 35 Utrecht Utrecht 3581 NJ",
    "addr:housenumber":"35",
    "addr:postcode":"3581 nj",
    "addr:street":"Wilhelminapark",
    "iso:country":"NL",
    "sg:address":"Wilhelminapark 35",
    "sg:city":"Utrecht",
    "sg:orig_category":"Kinderopvang Behalve Thuis",
    "sg:phone":"+31 30 254 0027",
    "sg:postcode":"3581 NJ",
    "sg:province":"Utrecht",
    "wof:name":"Kinderdagverblijf Daffie Duck (Skon)",
    "wof:placetype":"venue"
},
  "geometry": {"coordinates":[5.138324,52.087154],"type":"Point"}
}