{
  "type": "Feature",
  "properties": {
    "addr:full":"Breugomsln 14 Honselersdyk Zuid-Holland 2675 LA",
    "addr:housenumber":"14",
    "addr:postcode":"2675 la",
    "addr:street":"Breugomsln",
    "iso:country":"NL",
    "sg:address":"Breugomsln 14",
    "sg:city":"Honselersdyk",
    "sg:orig_category":"Bloemen En Planten - Groothandel",
    "sg:phone":"+31 174 627 127",
    "sg:postcode":"2675 LA",
    "sg:province":"Zuid-Holland",
    "wof:name":"Voort, Van Der",
    "wof:placetype":"venue"
},
  "geometry": {"coordinates":[4.259599,51.998631],"type":"Point"}
}