{
  "type": "Feature",
  "properties": {
    "addr:full":"Landbouwkade 14 Emmeloord Flevoland 8304 AE",
    "addr:housenumber":"14",
    "addr:postcode":"8304 ae",
    "addr:street":"Landbouwkade;Flevoland",
    "iso:country":"NL",
    "sg:address":"Landbouwkade 14",
    "sg:city":"Emmeloord",
    "sg:orig_category":"Bedrijfsinventaris Gh",
    "sg:phone":"+31 527 638 600",
    "sg:postcode":"8304 AE",
    "sg:province":"Flevoland",
    "wof:name":"Gti Koudetechniek Bv",
    "wof:placetype":"venue"
},
  "geometry": {"coordinates":[5.752827,52.700966],"type":"Point"}
}