{
  "type": "Feature",
  "properties": {
    "addr:full":"Olmenln 6+8 Ridderkerk South Holland 2982 CP",
    "addr:housenumber":"6 + 8",
    "addr:postcode":"2982 cp",
    "addr:street":"Olmenln",
    "iso:country":"NL",
    "sg:address":"Olmenln 6+8",
    "sg:city":"Ridderkerk",
    "sg:orig_category":"Verzekeringen - Verzekeringskantoren",
    "sg:phone":"+31 180 413 855",
    "sg:postcode":"2982 CP",
    "sg:province":"South Holland",
    "wof:name":"Lagendijk Bv",
    "wof:placetype":"venue"
},
  "geometry": {"coordinates":[4.586255,51.873554],"type":"Point"}
}