{
  "type": "Feature",
  "properties": {
    "addr:full":"Harste 1 Sneek Friesland 8602 JX",
    "addr:housenumber":"1",
    "addr:postcode":"8602 jx",
    "addr:street":"Harste",
    "iso:country":"NL",
    "sg:address":"Harste 1",
    "sg:city":"Sneek",
    "sg:orig_category":"Bloemen And Planten",
    "sg:phone":"+31 515 413 049",
    "sg:postcode":"8602 JX",
    "sg:province":"Friesland",
    "wof:name":"Blommerye Joke Niemarkt",
    "wof:placetype":"venue"
},
  "geometry": {"coordinates":[5.642426,53.039322],"type":"Point"}
}