{
  "type": "Feature",
  "properties": {
    "addr:full":"Walenburg 13 Heemskerk Noord-Holland 1965 MD",
    "addr:housenumber":"13",
    "addr:postcode":"1965",
    "addr:street":"Walenburg",
    "iso:country":"NL",
    "sg:address":"Walenburg 13",
    "sg:city":"Heemskerk",
    "sg:orig_category":"Kappers",
    "sg:phone":"+31 251 250 987",
    "sg:postcode":"1965 MD",
    "sg:province":"Noord-Holland",
    "wof:name":"Kopzorg",
    "wof:placetype":"venue"
},
  "geometry": {"coordinates":[-75.923759,38.823399],"type":"Point"}
}