{
  "type": "Feature",
  "properties": {
    "iso:country":"NL",
    "sg:address":"Gietery 14",
    "sg:city":"Noordwykerhout",
    "sg:orig_category":"Bodemonderzoek",
    "sg:phone":"+31 252 374 545",
    "sg:postcode":"2211 XK",
    "sg:province":"South Holland",
    "sg:website":"http://www.ibozo.nl",
    "wof:name":"Ibozo",
    "wof:placetype":"venue"
},
  "geometry": {"coordinates":[4.491268,52.248016],"type":"Point"}
}