{
  "type": "Feature",
  "properties": {
    "addr:full":"Gietery 14 Noordwykerhout South Holland 2211 XK",
    "addr:housenumber":"14",
    "addr:postcode":"2211 xk",
    "addr:street":"Gietery",
    "iso:country":"NL",
    "sg:address":"Gietery 14",
    "sg:city":"Noordwykerhout",
    "sg:orig_category":"Bodemonderzoek",
    "sg:phone":"+31 252 374 545",
    "sg:postcode":"2211 XK",
    "sg:province":"South Holland",
    "sg:website":"http://www.ibozo.nl",
    "wof:name":"Ibozo",
    "wof:placetype":"venue"
},
  "geometry": {"coordinates":[4.491268,52.248016],"type":"Point"}
}