{
  "type": "Feature",
  "properties": {
    "addr:full":"Goereesestraat 5 Rotterdam Zuid-Holland 3083 DB",
    "addr:housenumber":"5",
    "addr:postcode":"3083 db",
    "addr:street":"Goereesestraat",
    "iso:country":"NL",
    "sg:address":"Goereesestraat 5",
    "sg:city":"Rotterdam",
    "sg:orig_category":"Kappers",
    "sg:phone":"+31 10 481 9090",
    "sg:postcode":"3083 DB",
    "sg:province":"Zuid-Holland",
    "wof:name":"E C Van Klaveren",
    "wof:placetype":"venue"
},
  "geometry": {"coordinates":[4.4871759415,51.8893623352],"type":"Point"}
}