{
  "type": "Feature",
  "properties": {
    "addr:full":"Diamantplein 2 Leiden Zuid-Holland 2332 HR",
    "addr:housenumber":"2",
    "addr:postcode":"2332 hr",
    "addr:street":"Diamantplein",
    "iso:country":"NL",
    "sg:address":"Diamantplein 2",
    "sg:city":"Leiden",
    "sg:orig_category":"Drogisterijen",
    "sg:phone":"+31 71 576 4735",
    "sg:postcode":"2332 HR",
    "sg:province":"Zuid-Holland",
    "wof:name":"Fa F.N. De Witt",
    "wof:placetype":"venue"
},
  "geometry": {"coordinates":[4.464456,52.156631],"type":"Point"}
}