{
  "type": "Feature",
  "properties": {
    "iso:country":"NL",
    "sg:address":"Lindensteinlaan 10",
    "sg:city":"Leek",
    "sg:orig_category":"Metaalbekleding And -Behandeling",
    "sg:phone":"+31 594 514 370",
    "sg:postcode":"9351 KE",
    "sg:province":"Groningen",
    "wof:name":"K Boer",
    "wof:placetype":"venue"
},
  "geometry": {"coordinates":[6.383077,53.163441],"type":"Point"}
}