{
  "type": "Feature",
  "properties": {
    "addr:full":"Postbus 430 Heerlen Limburg 6400 AK",
    "addr:housenumber":"430",
    "addr:postcode":"6400 ak",
    "addr:street":"Postbus",
    "iso:country":"NL",
    "sg:address":"Postbus 430",
    "sg:city":"Heerlen",
    "sg:orig_category":"Verzekeringen - Verzekeringskantoren",
    "sg:phone":"+31 45 574 0200",
    "sg:postcode":"6400 AK",
    "sg:province":"Limburg",
    "wof:name":"Lahaye Heerlen Bv",
    "wof:placetype":"venue"
},
  "geometry": {"coordinates":[5.98093,50.883041],"type":"Point"}
}