{
  "type": "Feature",
  "properties": {
    "addr:full":"Smaragdlaan. Bij 99 Leiden South Holland 2332 JP",
    "addr:housenumber":"99",
    "addr:postcode":"2332 jp",
    "iso:country":"NL",
    "sg:address":"Smaragdlaan. Bij 99",
    "sg:city":"Leiden",
    "sg:orig_category":"Overheidsdiensten",
    "sg:phone":"+31 70 372 0500",
    "sg:postcode":"2332 JP",
    "sg:province":"South Holland",
    "wof:name":"Cbr",
    "wof:placetype":"venue"
},
  "geometry": {"coordinates":[4.4551949501,52.1596260071],"type":"Point"}
}