{
  "type": "Feature",
  "properties": {
    "iso:country":"NL",
    "sg:address":"J Naberstr 43-45",
    "sg:city":"Alkmaar",
    "sg:orig_category":"Apotheken",
    "sg:phone":"+31 72 561 3434",
    "sg:postcode":"1827 LB",
    "sg:province":"Noord-Holland",
    "wof:name":"Daalmeer",
    "wof:placetype":"venue"
},
  "geometry": {"coordinates":[4.766802,52.665661],"type":"Point"}
}