{
  "type": "Feature",
  "properties": {
    "addr:full":"Voorstad 28 Sittard Limburg 6131 CR",
    "addr:housenumber":"28;6131",
    "addr:postcode":"cr",
    "addr:street":"Voorstad",
    "iso:country":"NL",
    "sg:address":"Voorstad 28",
    "sg:city":"Sittard",
    "sg:orig_category":"Homeopathie",
    "sg:phone":"+31 46 451 2426",
    "sg:postcode":"6131 CR",
    "sg:province":"Limburg",
    "wof:name":"Smulders",
    "wof:placetype":"venue"
},
  "geometry": {"coordinates":[5.86383,50.999035],"type":"Point"}
}