{
  "type": "Feature",
  "properties": {
    "iso:country":"NL",
    "sg:address":"Ophoven 21",
    "sg:city":"Sittard",
    "sg:orig_category":"Goederenvervoer Over De Weg",
    "sg:phone":"+31 46 451 5025",
    "sg:postcode":"6133 XP",
    "sg:province":"Limburg",
    "wof:name":"H M Jeurissen",
    "wof:placetype":"venue"
},
  "geometry": {"coordinates":[5.861366,50.994213],"type":"Point"}
}