{
  "type": "Feature",
  "properties": {
    "addr:full":"Diepenstr 87 Tilburg Noord-Brabant 5025 MR",
    "addr:housenumber":"87",
    "addr:postcode":"5025 mr",
    "addr:street":"Diepenstr",
    "iso:country":"NL",
    "sg:address":"Diepenstr 87",
    "sg:city":"Tilburg",
    "sg:orig_category":"Ketelbemetseling",
    "sg:phone":"+31 13 463 4307",
    "sg:postcode":"5025 MR",
    "sg:province":"Noord-Brabant",
    "wof:name":"Leijser",
    "wof:placetype":"venue"
},
  "geometry": {"coordinates":[5.069055,51.55022],"type":"Point"}
}