{
  "type": "Feature",
  "properties": {
    "addr:full":"Strobloem 18 Leiden Zuid-Holland 2317 LE",
    "addr:housenumber":"18",
    "addr:postcode":"2317 le",
    "addr:street":"Strobloem",
    "iso:country":"NL",
    "sg:address":"Strobloem 18",
    "sg:city":"Leiden",
    "sg:orig_category":"Verzekeringen - Verzekeringskantoren",
    "sg:phone":"+31 71 521 5730",
    "sg:postcode":"2317 LE",
    "sg:province":"Zuid-Holland",
    "wof:name":"Willigen, Van",
    "wof:placetype":"venue"
},
  "geometry": {"coordinates":[4.514028,52.176495],"type":"Point"}
}