{
  "type": "Feature",
  "properties": {
    "addr:full":"Koehoornstraat 38 Nieuw Dordrecht Provincie Drenthe 7885 AH",
    "addr:housenumber":"38",
    "addr:postcode":"7885 ah",
    "addr:street":"Koehoornstraat;Nieuw Dordrecht Provincie Drenthe",
    "iso:country":"NL",
    "sg:address":"Koehoornstraat 38",
    "sg:city":"Nieuw Dordrecht",
    "sg:orig_category":"Gespecialiseerde Bouw",
    "sg:phone":"+31 591 317 530",
    "sg:postcode":"7885 AH",
    "sg:province":"Provincie Drenthe",
    "wof:name":"Albert Vos",
    "wof:placetype":"venue"
},
  "geometry": {"coordinates":[6.96291,52.750195],"type":"Point"}
}