{
  "type": "Feature",
  "properties": {
    "addr:full":"Dorpsstr 574 Noord Scharwoude Noord-Holland 1723 HJ",
    "addr:housenumber":"574",
    "addr:postcode":"1723 hj",
    "iso:country":"NL",
    "sg:address":"Dorpsstr 574",
    "sg:city":"Noord Scharwoude",
    "sg:orig_category":"Boeken En Tijdschriften",
    "sg:phone":"+31 226 340 733",
    "sg:postcode":"1723 HJ",
    "sg:province":"Noord-Holland",
    "wof:name":"Bruna",
    "wof:placetype":"venue"
},
  "geometry": {"coordinates":[4.811055,52.700859],"type":"Point"}
}