{
  "type": "Feature",
  "properties": {
    "addr:full":"Stadspln 1 Capelle Ad Yssel Zuid-Holland 2903 HH",
    "addr:housenumber":"1",
    "addr:postcode":"2903 hh",
    "addr:street":"Stadspln",
    "iso:country":"NL",
    "sg:address":"Stadspln 1",
    "sg:city":"Capelle Ad Yssel",
    "sg:orig_category":"Banken",
    "sg:phone":"+31 10 450 9840",
    "sg:postcode":"2903 HH",
    "sg:province":"Zuid-Holland",
    "wof:name":"Fortis",
    "wof:placetype":"venue"
},
  "geometry": {"coordinates":[4.587788,51.931461],"type":"Point"}
}