{
  "type": "Feature",
  "properties": {
    "addr:full":"Bolderikkamp 49 Leiderdorp Zuid-Holland 2353 HL",
    "addr:housenumber":"49",
    "addr:postcode":"2353 hl",
    "addr:street":"Bolderikkamp",
    "iso:country":"NL",
    "sg:address":"Bolderikkamp 49",
    "sg:city":"Leiderdorp",
    "sg:orig_category":"Artiestenbureaus",
    "sg:phone":"+31 71 589 6119",
    "sg:postcode":"2353 HL",
    "sg:province":"Zuid-Holland",
    "wof:name":"L Hakker",
    "wof:placetype":"venue"
},
  "geometry": {"coordinates":[4.537628,52.158028],"type":"Point"}
}