{
  "type": "Feature",
  "properties": {
    "addr:full":"Schoolstr 14 Lisse Zuid-Holland 2161 HC",
    "addr:housenumber":"14",
    "addr:postcode":"2161 hc",
    "addr:street":"Schoolstr",
    "iso:country":"NL",
    "sg:address":"Schoolstr 14",
    "sg:city":"Lisse",
    "sg:orig_category":"Hek- En Rasterwerken",
    "sg:phone":"+31 6 22607990",
    "sg:postcode":"2161 HC",
    "sg:province":"Zuid-Holland",
    "wof:name":"Jp",
    "wof:placetype":"venue"
},
  "geometry": {"coordinates":[4.555603,52.258297],"type":"Point"}
}