{
  "type": "Feature",
  "properties": {
    "addr:full":"Schroefstraat 8 Lelystad Flevoland 8223 ED",
    "addr:housenumber":"8",
    "addr:postcode":"8223 ed",
    "addr:street":"Schroefstraat;Flevoland",
    "iso:country":"NL",
    "sg:address":"Schroefstraat 8",
    "sg:city":"Lelystad",
    "sg:orig_category":"Hout Gh",
    "sg:phone":"+31 320 231 345",
    "sg:postcode":"8223 ED",
    "sg:province":"Flevoland",
    "wof:name":"Praxis",
    "wof:placetype":"venue"
},
  "geometry": {"coordinates":[5.496262,52.522339],"type":"Point"}
}