{
  "type": "Feature",
  "properties": {
    "addr:full":"Postbus 441 Zevenaar Gelderland 6900 AA",
    "addr:housenumber":"441",
    "addr:postcode":"6900 aa",
    "addr:street":"Postbus",
    "iso:country":"NL",
    "sg:address":"Postbus 441",
    "sg:city":"Zevenaar",
    "sg:orig_category":"Wasserettes, Stomerijen And Reiniging",
    "sg:phone":"+31 316 341 302",
    "sg:postcode":"6900 AA",
    "sg:province":"Gelderland",
    "wof:name":"Chemdry",
    "wof:placetype":"venue"
},
  "geometry": {"coordinates":[6.0768780708,51.9316177368],"type":"Point"}
}