{
  "type": "Feature",
  "properties": {
    "iso:country":"NL",
    "sg:address":"Onruststr 23",
    "sg:city":"Kamperland",
    "sg:orig_category":"Glazenwasserijen",
    "sg:phone":"+31 113 372 222",
    "sg:postcode":"4493 EC",
    "sg:province":"Zeeland",
    "wof:name":"Wagt, P Van Der",
    "wof:placetype":"venue"
},
  "geometry": {"coordinates":[3.70029,51.568291],"type":"Point"}
}