{
  "type": "Feature",
  "properties": {
    "addr:full":"Ysselmeerdk 16 Warder Noord-Holland 1473 PP",
    "addr:housenumber":"16",
    "addr:postcode":"1473 pp",
    "addr:street":"Ysselmeerdk",
    "iso:country":"NL",
    "sg:address":"Ysselmeerdk 16",
    "sg:city":"Warder",
    "sg:orig_category":"Betonijzervlechten",
    "sg:phone":"+31 299 401 880",
    "sg:postcode":"1473 PP",
    "sg:province":"Noord-Holland",
    "wof:name":"Sucan",
    "wof:placetype":"venue"
},
  "geometry": {"coordinates":[5.049266,52.550598],"type":"Point"}
}