{
  "type": "Feature",
  "properties": {
    "addr:full":"Rynstr 170 Amsterdam Noord-Holland 1079 HS",
    "addr:housenumber":"170",
    "addr:postcode":"1079 hs",
    "iso:country":"NL",
    "sg:address":"Rynstr 170",
    "sg:city":"Amsterdam",
    "sg:orig_category":"Banken",
    "sg:phone":"+31 20 644 4811",
    "sg:postcode":"1079 HS",
    "sg:province":"Noord-Holland",
    "wof:name":"Fortis",
    "wof:placetype":"venue"
},
  "geometry": {"coordinates":[4.89319,52.373119],"type":"Point"}
}