{
  "type": "Feature",
  "properties": {
    "addr:full":"Ordel 4 Norg Provincie Drenthe 9331 EX",
    "addr:housenumber":"4",
    "addr:postcode":"9331 ex",
    "addr:street":"Ordel;Provincie Drenthe",
    "iso:country":"NL",
    "sg:address":"Ordel 4",
    "sg:city":"Norg",
    "sg:orig_category":"Hoefsmederijen",
    "sg:phone":"+31 592 612 118",
    "sg:postcode":"9331 EX",
    "sg:province":"Provincie Drenthe",
    "wof:name":"Stevens",
    "wof:placetype":"venue"
},
  "geometry": {"coordinates":[6.451527,53.071907],"type":"Point"}
}