{
  "type": "Feature",
  "properties": {
    "addr:full":"Badorfstraat 17 Wijk Bij Duurstede Utrecht 3962 CB",
    "addr:housenumber":"17",
    "addr:postcode":"3962 cb",
    "addr:street":"Badorfstraat",
    "iso:country":"NL",
    "sg:address":"Badorfstraat 17",
    "sg:city":"Wijk Bij Duurstede",
    "sg:orig_category":"Diverse Grafische Activiteiten",
    "sg:phone":"+31 343 591 748",
    "sg:postcode":"3962 CB",
    "sg:province":"Utrecht",
    "wof:name":"Hoogstraten Studio",
    "wof:placetype":"venue"
},
  "geometry": {"coordinates":[5.342008,51.977764],"type":"Point"}
}