{
  "type": "Feature",
  "properties": {
    "iso:country":"NL",
    "sg:address":"Middel 18",
    "sg:city":"Westzaan",
    "sg:orig_category":"Verhuur Landbouwmachines",
    "sg:phone":"+31 75 621 6689",
    "sg:postcode":"1551 SP",
    "sg:province":"Noord-Holland",
    "wof:name":"Germieco All Services Bv",
    "wof:placetype":"venue"
},
  "geometry": {"coordinates":[4.780126,52.468071],"type":"Point"}
}