{
  "type": "Feature",
  "properties": {
    "addr:full":"Bedryvenwg 7 St Michielsgestel Noord-Brabant 5272 PA",
    "addr:housenumber":"7",
    "addr:postcode":"5272 pa",
    "addr:street":"Bedryvenwg",
    "iso:country":"NL",
    "sg:address":"Bedryvenwg 7",
    "sg:city":"St Michielsgestel",
    "sg:orig_category":"Kabels",
    "sg:phone":"+31 73 553 1370",
    "sg:postcode":"5272 PA",
    "sg:province":"Noord-Brabant",
    "wof:name":"Compose Bv",
    "wof:placetype":"venue"
},
  "geometry": {"coordinates":[5.3617291451,51.6490821838],"type":"Point"}
}