{
  "type": "Feature",
  "properties": {
    "addr:full":"Kastanjelaan 1 Staphorst Overijssel 7951 KD",
    "addr:housenumber":"1",
    "addr:postcode":"7951 kd",
    "addr:street":"Kastanjelaan",
    "iso:country":"NL",
    "sg:address":"Kastanjelaan 1",
    "sg:city":"Staphorst",
    "sg:orig_category":"Mobiele Service Aan Motorvoertuigen",
    "sg:phone":"+31 522 253 198",
    "sg:postcode":"7951 KD",
    "sg:province":"Overijssel",
    "wof:name":"Handelsonderneming Kba",
    "wof:placetype":"venue"
},
  "geometry": {"coordinates":[6.184519,52.678055],"type":"Point"}
}