{
  "type": "Feature",
  "properties": {
    "addr:full":"Kernwg 21 Hoorn Nh Noord-Holland 1627 LH",
    "addr:housenumber":"21",
    "addr:postcode":"1627 lh",
    "addr:street":"Kernwg",
    "iso:country":"NL",
    "sg:address":"Kernwg 21",
    "sg:city":"Hoorn Nh",
    "sg:classifiers":[
        {
            "category":"Building & Trades",
            "subcategory":"Electrical",
            "type":"Services"
        }
    ],
    "sg:phone":"+31 229 285 858",
    "sg:postcode":"1627 LH",
    "sg:province":"Noord-Holland",
    "sg:tags":[
        "distributor"
    ],
    "wof:name":"His Bv",
    "wof:placetype":"venue"
},
  "geometry": {"coordinates":[5.099641,52.640392],"type":"Point"}
}