{
  "type": "Feature",
  "properties": {
    "addr:full":"S Burgerhartsngl 163 Amersfoort Utrecht 3813 NG",
    "addr:housenumber":"163",
    "addr:postcode":"3813 ng",
    "iso:country":"NL",
    "sg:address":"S Burgerhartsngl 163",
    "sg:city":"Amersfoort",
    "sg:orig_category":"Vertaalbureaus",
    "sg:phone":"+31 33 480 8822",
    "sg:postcode":"3813 NG",
    "sg:province":"Utrecht",
    "wof:name":"Franscript",
    "wof:placetype":"venue"
},
  "geometry": {"coordinates":[5.386085,52.152325],"type":"Point"}
}