{
  "type": "Feature",
  "properties": {
    "addr:full":"V Galenstr 56 Arnhem Gelderland 6826 RZ",
    "addr:housenumber":"56",
    "addr:postcode":"6826 rz",
    "iso:country":"NL",
    "sg:address":"V Galenstr 56",
    "sg:city":"Arnhem",
    "sg:orig_category":"Homeopathie",
    "sg:phone":"+31 26 364 9292",
    "sg:postcode":"6826 RZ",
    "sg:province":"Gelderland",
    "wof:name":"Hollander-Priester, C M",
    "wof:placetype":"venue"
},
  "geometry": {"coordinates":[5.94473,51.98209],"type":"Point"}
}