{
  "type": "Feature",
  "properties": {
    "addr:full":"Ringlaan 4 Breskens Zeeland 4511 HH",
    "addr:housenumber":"4",
    "addr:postcode":"4511 hh",
    "addr:street":"Ringlaan",
    "iso:country":"NL",
    "sg:address":"Ringlaan 4",
    "sg:city":"Breskens",
    "sg:orig_category":"Bejaardeninstellingen And Serviceflats",
    "sg:phone":"+31 117 381 210",
    "sg:postcode":"4511 HH",
    "sg:province":"Zeeland",
    "wof:name":"Verzorgingstehuis Ter Schelde",
    "wof:placetype":"venue"
},
  "geometry": {"coordinates":[3.54885,51.394417],"type":"Point"}
}