{
  "type": "Feature",
  "properties": {
    "iso:country":"NL",
    "sg:address":"Aardster 93",
    "sg:city":"Alphen Aan Den Ryn",
    "sg:orig_category":"Facilitaire Dienstverlening",
    "sg:phone":"+31 172 240 096",
    "sg:postcode":"2403 RL",
    "sg:province":"South Holland",
    "wof:name":"Wallaart",
    "wof:placetype":"venue"
},
  "geometry": {"coordinates":[4.678549,52.149517],"type":"Point"}
}