{
  "type": "Feature",
  "properties": {
    "addr:full":"Warmoesstr 16 Amsterdam North Holland 1012 JD",
    "addr:housenumber":"16",
    "addr:postcode":"1012 jd",
    "addr:street":"Warmoesstr",
    "iso:country":"NL",
    "sg:address":"Warmoesstr 16",
    "sg:city":"Amsterdam",
    "sg:orig_category":"Kaas",
    "sg:phone":"+31 20 623 0878",
    "sg:postcode":"1012 JD",
    "sg:province":"North Holland",
    "wof:name":"Eenhoorn, De",
    "wof:placetype":"venue"
},
  "geometry": {"coordinates":[4.8989868164,52.3760643005],"type":"Point"}
}