{
  "type": "Feature",
  "properties": {
    "addr:full":"Lg Klompwg 16 E Weesp Noord-Holland 1381 HD",
    "addr:housenumber":"16",
    "addr:postcode":"1381 hd",
    "addr:street":"Lg;E",
    "iso:country":"NL",
    "sg:address":"Lg Klompwg 16 E",
    "sg:city":"Weesp",
    "sg:orig_category":"Projectinrichting",
    "sg:phone":"+31 294 416 754",
    "sg:postcode":"1381 HD",
    "sg:province":"Noord-Holland",
    "wof:name":"Jw",
    "wof:placetype":"venue"
},
  "geometry": {"coordinates":[5.03828,52.308315],"type":"Point"}
}