{
  "type": "Feature",
  "properties": {
    "addr:full":"Om T Wedde 5A Montfoort Utrecht 3417 HH",
    "addr:housenumber":"5a",
    "addr:postcode":"3417 hh",
    "addr:street":"T Wedde",
    "iso:country":"NL",
    "sg:address":"Om T Wedde 5A",
    "sg:city":"Montfoort",
    "sg:orig_category":"Bloemen En Planten - Groothandel",
    "sg:phone":"+31 348 473 377",
    "sg:postcode":"3417 HH",
    "sg:province":"Utrecht",
    "wof:name":"Voorhout, H",
    "wof:placetype":"venue"
},
  "geometry": {"coordinates":[4.946623,52.044689],"type":"Point"}
}