{
  "type": "Feature",
  "properties": {
    "addr:full":"Bredaseweg 100 Tilburg North Brabant 5038 NJ",
    "addr:housenumber":"100",
    "addr:postcode":"5038 nj",
    "addr:street":"Bredaseweg",
    "iso:country":"NL",
    "sg:address":"Bredaseweg 100",
    "sg:city":"Tilburg",
    "sg:orig_category":"Opticiens",
    "sg:phone":"+31 13 542 2871",
    "sg:postcode":"5038 NJ",
    "sg:province":"North Brabant",
    "wof:name":"Eekelaar Brillen En Contactlenzen Bv",
    "wof:placetype":"venue"
},
  "geometry": {"coordinates":[5.0758252144,51.5552825928],"type":"Point"}
}