{
  "type": "Feature",
  "properties": {
    "addr:full":"Frank Van Borselenlaan 15 Voorhout Zuid-Holland 2215 RM",
    "addr:housenumber":"15",
    "addr:postcode":"2215 rm",
    "addr:street":"Frank Van Borselenlaan",
    "iso:country":"NL",
    "sg:address":"Frank Van Borselenlaan 15",
    "sg:city":"Voorhout",
    "sg:orig_category":"Bloemen And Planten Gh",
    "sg:phone":"+31 252 212 933",
    "sg:postcode":"2215 RM",
    "sg:province":"Zuid-Holland",
    "wof:name":"L. Koning Holland Bloembollenexport Bv",
    "wof:placetype":"venue"
},
  "geometry": {"coordinates":[4.515582,52.233067],"type":"Point"}
}