{
  "type": "Feature",
  "properties": {
    "addr:full":"Houtmarkt 17 Breda North Brabant 4811 JC",
    "addr:housenumber":"17",
    "addr:postcode":"4811 jc",
    "addr:street":"Houtmarkt",
    "iso:country":"NL",
    "sg:address":"Houtmarkt 17",
    "sg:city":"Breda",
    "sg:orig_category":"Werving And Selectie Van Tijdelijk Personeel And Uitzendkantoren",
    "sg:phone":"+31 76 523 0080",
    "sg:postcode":"4811 JC",
    "sg:province":"North Brabant",
    "wof:name":"Constructief",
    "wof:placetype":"venue"
},
  "geometry": {"coordinates":[4.7771220207,51.5863227844],"type":"Point"}
}