{
  "type": "Feature",
  "properties": {
    "addr:full":"Schuttersveldstr 22 Oldenzaal Overijssel 7575 BR",
    "addr:housenumber":"22",
    "addr:postcode":"7575 br",
    "addr:street":"Schuttersveldstr",
    "iso:country":"NL",
    "sg:address":"Schuttersveldstr 22",
    "sg:city":"Oldenzaal",
    "sg:orig_category":"Kabelwerken",
    "sg:phone":"+31 541 572 200",
    "sg:postcode":"7575 BR",
    "sg:province":"Overijssel",
    "wof:name":"Siers Bv",
    "wof:placetype":"venue"
},
  "geometry": {"coordinates":[6.9285821915,52.2987213135],"type":"Point"}
}