{
  "type": "Feature",
  "properties": {
    "iso:country":"NL",
    "sg:address":"Horapark 6",
    "sg:city":"Ede Gld",
    "sg:orig_category":"Bedrijfsopleidingen",
    "sg:phone":"+31 318 696 999",
    "sg:postcode":"6717 LZ",
    "sg:province":"Gelderland",
    "sg:website":"http://www.lsbl.nl",
    "wof:name":"Lsbl Services",
    "wof:placetype":"venue"
},
  "geometry": {"coordinates":[5.676048,52.021004],"type":"Point"}
}