{
  "type": "Feature",
  "properties": {
    "addr:full":"Javastr 145 Amsterdam North Holland 1094 HE",
    "addr:housenumber":"145",
    "addr:postcode":"1094 he",
    "iso:country":"NL",
    "sg:address":"Javastr 145",
    "sg:city":"Amsterdam",
    "sg:orig_category":"Zoetwaren - Winkels",
    "sg:phone":"+31 20 694 5046",
    "sg:postcode":"1094 HE",
    "sg:province":"North Holland",
    "wof:name":"Snoeppaleis",
    "wof:placetype":"venue"
},
  "geometry": {"coordinates":[4.937823,52.363865],"type":"Point"}
}