{
  "type": "Feature",
  "properties": {
    "addr:full":"Lieoever 62 Haarlem Noord-Holland 2033 AD",
    "addr:housenumber":"62",
    "addr:postcode":"2033 ad",
    "addr:street":"Lieoever",
    "iso:country":"NL",
    "sg:address":"Lieoever 62",
    "sg:city":"Haarlem",
    "sg:orig_category":"Sportclubs",
    "sg:phone":"+31 23 536 2803",
    "sg:postcode":"2033 AD",
    "sg:province":"Noord-Holland",
    "wof:name":"Stichting Iads",
    "wof:placetype":"venue"
},
  "geometry": {"coordinates":[4.678006,52.379627],"type":"Point"}
}