{
  "type": "Feature",
  "properties": {
    "addr:full":"Kaaiwg 19 Borssele Zeeland 4454 PN",
    "addr:housenumber":"19",
    "addr:postcode":"4454 pn",
    "addr:street":"Kaaiwg",
    "iso:country":"NL",
    "sg:address":"Kaaiwg 19",
    "sg:city":"Borssele",
    "sg:orig_category":"Land- En Tuinbouw - Loonbedrijven",
    "sg:phone":"+31 113 352 066",
    "sg:postcode":"4454 PN",
    "sg:province":"Zeeland",
    "wof:name":"Nieuwenhuyse, Fa W",
    "wof:placetype":"venue"
},
  "geometry": {"coordinates":[3.744706,51.429482],"type":"Point"}
}