{
  "type": "Feature",
  "properties": {
    "addr:full":"Oudelandseweg 19 Woerden Utrecht 3443 AB",
    "addr:housenumber":"19",
    "addr:postcode":"3443 ab",
    "addr:street":"Oudelandseweg",
    "iso:country":"NL",
    "sg:address":"Oudelandseweg 19",
    "sg:city":"Woerden",
    "sg:orig_category":"Advocaten And Juridische Adviseurs",
    "sg:phone":"+31 348 415 630",
    "sg:postcode":"3443 AB",
    "sg:province":"Utrecht",
    "wof:name":"Advocatenkantoor Derks",
    "wof:placetype":"venue"
},
  "geometry": {"coordinates":[4.893038,52.088615],"type":"Point"}
}