{
  "type": "Feature",
  "properties": {
    "addr:full":"Westerstraat 4 Winsum Gn Groningen 9951 EN",
    "addr:housenumber":"4",
    "addr:postcode":"gn;9951 en",
    "addr:street":"Westerstraat",
    "iso:country":"NL",
    "sg:address":"Westerstraat 4",
    "sg:city":"Winsum Gn",
    "sg:orig_category":"Architecten",
    "sg:phone":"+31 595 442 880",
    "sg:postcode":"9951 EN",
    "sg:province":"Groningen",
    "wof:name":"Architectenburo Harry Vos",
    "wof:placetype":"venue"
},
  "geometry": {"coordinates":[6.517395,53.334412],"type":"Point"}
}