{
  "type": "Feature",
  "properties": {
    "addr:full":"Bredaseweg 207 Tilburg North Brabant 5038 NE",
    "addr:housenumber":"207",
    "addr:postcode":"5038 ne",
    "addr:street":"Bredaseweg",
    "iso:country":"NL",
    "sg:address":"Bredaseweg 207",
    "sg:city":"Tilburg",
    "sg:orig_category":"Waterbeheer",
    "sg:phone":"+31 13 584 0400",
    "sg:postcode":"5038 NE",
    "sg:province":"North Brabant",
    "wof:name":"Nv Tilburgsche Waterleiding Maatschappij",
    "wof:placetype":"venue"
},
  "geometry": {"coordinates":[5.0688638687,51.556022644],"type":"Point"}
}