{
  "type": "Feature",
  "properties": {
    "addr:full":"Koepoortstr 15 Zaamslag Zeeland 4543 AR",
    "addr:housenumber":"15",
    "addr:postcode":"4543",
    "addr:street":"Koepoortstr",
    "iso:country":"NL",
    "sg:address":"Koepoortstr 15",
    "sg:city":"Zaamslag",
    "sg:orig_category":"Vertaalbureaus",
    "sg:phone":"+31 115 431 932",
    "sg:postcode":"4543 AR",
    "sg:province":"Zeeland",
    "wof:name":"Mano",
    "wof:placetype":"venue"
},
  "geometry": {"coordinates":[3.913831,51.313957],"type":"Point"}
}