{
  "type": "Feature",
  "properties": {
    "addr:full":"Coenecoop 14 Waddinxveen Zuid-Holland 2741 PG",
    "addr:housenumber":"14",
    "addr:postcode":"2741 pg",
    "addr:street":"Coenecoop",
    "iso:country":"NL",
    "sg:address":"Coenecoop 14",
    "sg:city":"Waddinxveen",
    "sg:orig_category":"Meubelen - Fabrieken En Groothandel",
    "sg:phone":"+31 182 635 855",
    "sg:postcode":"2741 PG",
    "sg:province":"Zuid-Holland",
    "wof:name":"Hageman Collection Bv",
    "wof:placetype":"venue"
},
  "geometry": {"coordinates":[4.655069828,52.0446014404],"type":"Point"}
}