{
  "type": "Feature",
  "properties": {
    "addr:full":"Willemstr 9 Bakel Noord-Brabant 5761 BD",
    "addr:housenumber":"9",
    "addr:postcode":"5761 bd",
    "addr:street":"Willemstr",
    "iso:country":"NL",
    "sg:address":"Willemstr 9",
    "sg:city":"Bakel",
    "sg:orig_category":"Architecten En Architectenbureaus",
    "sg:phone":"+31 492 341 846",
    "sg:postcode":"5761 BD",
    "sg:province":"Noord-Brabant",
    "wof:name":"Rasenberg, H",
    "wof:placetype":"venue"
},
  "geometry": {"coordinates":[5.741613,51.507034],"type":"Point"}
}