{
  "type": "Feature",
  "properties": {
    "addr:full":"Buorren 17 Hemelum Friesland 8584 VC",
    "addr:housenumber":"17",
    "addr:postcode":"8584 vc",
    "addr:street":"Buorren",
    "iso:country":"NL",
    "sg:address":"Buorren 17",
    "sg:city":"Hemelum",
    "sg:classifiers":[
        {
            "category":"Bakery",
            "type":"Food & Drink"
        }
    ],
    "sg:phone":"+31 514 581 213",
    "sg:postcode":"8584 VC",
    "sg:province":"Friesland",
    "sg:tags":[
        "brood",
        "banket"
    ],
    "wof:name":"Kosters Bakkerij",
    "wof:placetype":"venue"
},
  "geometry": {"coordinates":[5.454831,52.881805],"type":"Point"}
}