{
  "type": "Feature",
  "properties": {
    "addr:full":"Bachstr 151 Capelle Ad Yssel South Holland 2901 JZ",
    "addr:housenumber":"151;2901",
    "addr:postcode":"jz",
    "addr:street":"Bachstr;Yssel",
    "iso:country":"NL",
    "sg:address":"Bachstr 151",
    "sg:city":"Capelle Ad Yssel",
    "sg:orig_category":"Projectinrichting",
    "sg:phone":"+31 10 202 7993",
    "sg:postcode":"2901 JZ",
    "sg:province":"South Holland",
    "wof:name":"Rb",
    "wof:placetype":"venue"
},
  "geometry": {"coordinates":[4.565626,51.921516],"type":"Point"}
}