{
  "type": "Feature",
  "properties": {
    "addr:full":"Keizersdk 70 Raamsdonksveer Noord-Brabant 4941 GG",
    "addr:housenumber":"70",
    "addr:postcode":"4941 gg",
    "addr:street":"Keizersdk",
    "iso:country":"NL",
    "sg:address":"Keizersdk 70",
    "sg:city":"Raamsdonksveer",
    "sg:orig_category":"Koffie- En Theehuizen",
    "sg:phone":"+31 162 523 185",
    "sg:postcode":"4941 GG",
    "sg:province":"Noord-Brabant",
    "wof:name":"Relax",
    "wof:placetype":"venue"
},
  "geometry": {"coordinates":[4.872311,51.698887],"type":"Point"}
}