{
  "type": "Feature",
  "properties": {
    "iso:country":"NL",
    "sg:address":"Haringvliet 88",
    "sg:city":"Rotterdam",
    "sg:orig_category":"Grafisch Ontwerpers",
    "sg:phone":"+31 10 412 2192",
    "sg:postcode":"3011 TG",
    "sg:province":"Zuid-Holland",
    "wof:name":"Nu Design",
    "wof:placetype":"venue"
},
  "geometry": {"coordinates":[4.494638,51.91935],"type":"Point"}
}