{
  "type": "Feature",
  "properties": {
    "iso:country":"NL",
    "sg:address":"Nieuwstraat 30",
    "sg:city":"Alphen A/D Rijn",
    "sg:orig_category":"Koeriersdiensten",
    "sg:phone":"+31 172 425 575",
    "sg:postcode":"2406 TP",
    "sg:province":"Zuid-Holland",
    "wof:name":"E.K.D. Euro Koeriers Diensten",
    "wof:placetype":"venue"
},
  "geometry": {"coordinates":[4.665421,52.136589],"type":"Point"}
}