{
  "type": "Feature",
  "properties": {
    "addr:full":"Blomsgaarden 28 Eibergen Gelderland 7151 AM",
    "addr:housenumber":"28",
    "addr:postcode":"7151",
    "addr:street":"Blomsgaarden;Gelderland",
    "iso:country":"NL",
    "sg:address":"Blomsgaarden 28",
    "sg:city":"Eibergen",
    "sg:orig_category":"Journalisten Freelance",
    "sg:phone":"+31 545 472 543",
    "sg:postcode":"7151 AM",
    "sg:province":"Gelderland",
    "wof:name":"Gossink Publiciteit",
    "wof:placetype":"venue"
},
  "geometry": {"coordinates":[6.652473,52.100475],"type":"Point"}
}