{
  "type": "Feature",
  "properties": {
    "addr:full":"Spoorstraat 59 Kesteren Gelderland 4041 CL",
    "addr:housenumber":"59",
    "addr:postcode":"4041",
    "addr:street":"Spoorstraat;Gelderland",
    "iso:country":"NL",
    "sg:address":"Spoorstraat 59",
    "sg:city":"Kesteren",
    "sg:orig_category":"Autokeuringen",
    "sg:phone":"+31 488 483 833",
    "sg:postcode":"4041 CL",
    "sg:province":"Gelderland",
    "wof:name":"Glasgarage Kesteren",
    "wof:placetype":"venue"
},
  "geometry": {"coordinates":[5.585212,51.93232],"type":"Point"}
}