{
  "type": "Feature",
  "properties": {
    "iso:country":"NL",
    "sg:address":"Donjon 1",
    "sg:city":"Vianen Zh",
    "sg:orig_category":"Verenigingen En Stichtingen",
    "sg:phone":"+31 347 374 097",
    "sg:postcode":"4131 XA",
    "sg:province":"Utrecht",
    "wof:name":"Swov",
    "wof:placetype":"venue"
},
  "geometry": {"coordinates":[5.1008,51.994118],"type":"Point"}
}