{
  "type": "Feature",
  "properties": {
    "addr:full":"Beilerstraat 13A Westerbork Drenthe 9431 GA",
    "addr:housenumber":"13a",
    "addr:postcode":"9431 ga",
    "addr:street":"Beilerstraat",
    "iso:country":"NL",
    "sg:address":"Beilerstraat 13A",
    "sg:city":"Westerbork",
    "sg:orig_category":"Kampeerterreinen",
    "sg:phone":"+31 593 331 546",
    "sg:postcode":"9431 GA",
    "sg:province":"Drenthe",
    "wof:name":"Vof De Valkenhof",
    "wof:placetype":"venue"
},
  "geometry": {"coordinates":[6.5960907936,52.8531341553],"type":"Point"}
}