{
  "type": "Feature",
  "properties": {
    "iso:country":"NL",
    "sg:address":"Hunzingo 18",
    "sg:city":"Dronten",
    "sg:orig_category":"Yoga-Instituten",
    "sg:phone":"+31 321 382 979",
    "sg:postcode":"8251 VZ",
    "sg:province":"NL.",
    "wof:name":"Muizelaar, Annette",
    "wof:placetype":"venue"
},
  "geometry": {"coordinates":[5.726018,52.511288],"type":"Point"}
}