{
  "type": "Feature",
  "properties": {
    "addr:full":"Mariadal 35 Venlo Limburg 5916 SL",
    "addr:housenumber":"35",
    "addr:postcode":"5916 sl",
    "addr:street":"Mariadal",
    "iso:country":"NL",
    "sg:address":"Mariadal 35",
    "sg:city":"Venlo",
    "sg:orig_category":"Beeldende Kunstenaars",
    "sg:phone":"+31 77 354 8990",
    "sg:postcode":"5916 SL",
    "sg:province":"Limburg",
    "wof:name":"Smets Atelier",
    "wof:placetype":"venue"
},
  "geometry": {"coordinates":[6.189626,51.387901],"type":"Point"}
}