{
  "type": "Feature",
  "properties": {
    "addr:full":"Kerkln 58 St Nicolaasga Provincie Friesland 8521 KM",
    "addr:housenumber":"58;8521",
    "addr:street":"Kerkln;St;Provincie Friesland;Km",
    "iso:country":"NL",
    "sg:address":"Kerkln 58",
    "sg:city":"St Nicolaasga",
    "sg:orig_category":"Bestratingen",
    "sg:phone":"+31 513 432 971",
    "sg:postcode":"8521 KM",
    "sg:province":"Provincie Friesland",
    "wof:name":"Postma, M",
    "wof:placetype":"venue"
},
  "geometry": {"coordinates":[5.743665,52.923367],"type":"Point"}
}