{
  "type": "Feature",
  "properties": {
    "addr:full":"Prinsenweg 22 Wassenaar Zuid-Holland 2242 EG",
    "addr:housenumber":"22",
    "addr:postcode":"2242 eg",
    "addr:street":"Prinsenweg",
    "iso:country":"NL",
    "sg:address":"Prinsenweg 22",
    "sg:city":"Wassenaar",
    "sg:orig_category":"Verzekeringen",
    "sg:phone":"+31 70 511 5554",
    "sg:postcode":"2242 EG",
    "sg:province":"Zuid-Holland",
    "wof:name":"Assurantie Kantoor Berkel Bv",
    "wof:placetype":"venue"
},
  "geometry": {"coordinates":[4.397574,52.140217],"type":"Point"}
}