{
  "type": "Feature",
  "properties": {
    "iso:country":"NL",
    "sg:address":"Veldzigt 48A",
    "sg:city":"De Meern",
    "sg:orig_category":"Beveiliging",
    "sg:phone":"+31 30 669 0990",
    "sg:postcode":"3454 PW",
    "sg:province":"Utrecht",
    "wof:name":"Chubb Lips",
    "wof:placetype":"venue"
},
  "geometry": {"coordinates":[5.049966,52.075783],"type":"Point"}
}