{
  "type": "Feature",
  "properties": {
    "addr:full":"Vogelwg 143 Alkmaar North Holland 1826 HL",
    "addr:housenumber":"143",
    "addr:postcode":"1826 hl",
    "iso:country":"NL",
    "sg:address":"Vogelwg 143",
    "sg:city":"Alkmaar",
    "sg:orig_category":"Webdesign Bureaus",
    "sg:phone":"+31 72 561 2366",
    "sg:postcode":"1826 HL",
    "sg:province":"North Holland",
    "sg:website":"http://www.atraxion.nl",
    "wof:name":"Atraxion Nl",
    "wof:placetype":"venue"
},
  "geometry": {"coordinates":[4.7684669495,52.6610908508],"type":"Point"}
}