{
  "type": "Feature",
  "properties": {
    "addr:full":"Brinkgreverwg 112 Deventer NL.08 7413 AE",
    "addr:housenumber":"112;nl.08",
    "addr:postcode":"7413 ae",
    "iso:country":"NL",
    "sg:address":"Brinkgreverwg 112",
    "sg:city":"Deventer",
    "sg:orig_category":"Kappers",
    "sg:phone":"+31 570 630 281",
    "sg:postcode":"7413 AE",
    "sg:province":"NL.08",
    "wof:name":"Haar & Co",
    "wof:placetype":"venue"
},
  "geometry": {"coordinates":[6.1672058105,52.258480072],"type":"Point"}
}