{
  "type": "Feature",
  "properties": {
    "addr:full":"Blamanstraat 13 'S Gravenzande South Holland 2692 DL",
    "addr:housenumber":"13",
    "addr:postcode":"2692 dl",
    "addr:street":"Blamanstraat;' S Gravenzande",
    "iso:country":"NL",
    "sg:address":"Blamanstraat 13",
    "sg:city":"'S Gravenzande",
    "sg:orig_category":"Boekhouders",
    "sg:phone":"+31 174 417 522",
    "sg:postcode":"2692 DL",
    "sg:province":"South Holland",
    "wof:name":"Administratie- & Adviesburo Kaman",
    "wof:placetype":"venue"
},
  "geometry": {"coordinates":[4.158804,51.998753],"type":"Point"}
}