{
  "type": "Feature",
  "properties": {
    "iso:country":"NL",
    "sg:address":"Nudepark 144",
    "sg:city":"Wageningen",
    "sg:orig_category":"Diverse Grafische Activiteiten",
    "sg:phone":"+31 317 426 000",
    "sg:postcode":"6702 DX",
    "sg:province":"Gelderland",
    "wof:name":"Vada Graphic Bv",
    "wof:placetype":"venue"
},
  "geometry": {"coordinates":[5.646004,51.958019],"type":"Point"}
}