{
  "type": "Feature",
  "properties": {
    "addr:full":"Mennonietenk Str 10 Uithuizen Groningen 9981 BB",
    "addr:housenumber":"10",
    "addr:postcode":"9981 bb",
    "addr:street":"Str",
    "iso:country":"NL",
    "sg:address":"Mennonietenk Str 10",
    "sg:city":"Uithuizen",
    "sg:orig_category":"Hengelsportartikelen",
    "sg:phone":"+31 595 433 717",
    "sg:postcode":"9981 BB",
    "sg:province":"Groningen",
    "wof:name":"Bisschop Hengelsportartikelen",
    "wof:placetype":"venue"
},
  "geometry": {"coordinates":[6.670185,53.408695],"type":"Point"}
}