{
  "type": "Feature",
  "properties": {
    "addr:full":"Oudegracht 119 Utrecht Utrecht 3511 AH",
    "addr:housenumber":"119",
    "addr:postcode":"3511 ah",
    "addr:street":"Oudegracht",
    "iso:country":"NL",
    "sg:address":"Oudegracht 119",
    "sg:city":"Utrecht",
    "sg:orig_category":"Kantoorapparatuur Gh",
    "sg:phone":"+31 30 231 0088",
    "sg:postcode":"3511 AH",
    "sg:province":"Utrecht",
    "wof:name":"Kantoor Vakhandel Mado Bv",
    "wof:placetype":"venue"
},
  "geometry": {"coordinates":[5.1154050827,52.0889320374],"type":"Point"}
}