{
  "type": "Feature",
  "properties": {
    "iso:country":"NL",
    "sg:address":"P Borstr 1",
    "sg:city":"Amsterdam",
    "sg:orig_category":"Administratie- En Boekhoudkantoren",
    "sg:phone":"+31 20 610 4210",
    "sg:postcode":"1065 AE",
    "sg:province":"Noord-Holland",
    "wof:name":"Mans, Minke",
    "wof:placetype":"venue"
},
  "geometry": {"coordinates":[4.82478,52.362034],"type":"Point"}
}