{
  "type": "Feature",
  "properties": {
    "iso:country":"NL",
    "sg:address":"Stationswg 7C",
    "sg:city":"Venray",
    "sg:orig_category":"Huidtherapeuten",
    "sg:phone":"+31 6 53760218",
    "sg:postcode":"5802 AA",
    "sg:province":"Limburg",
    "wof:name":"Sharpe-Swart, J A",
    "wof:placetype":"venue"
},
  "geometry": {"coordinates":[5.977791,51.528507],"type":"Point"}
}