{
  "type": "Feature",
  "properties": {
    "iso:country":"NL",
    "sg:address":"Reeoordwg 2",
    "sg:city":"Vorden",
    "sg:orig_category":"Natuurvoeding En Reformartikelen",
    "sg:phone":"+31 575 554 202",
    "sg:postcode":"7251 JJ",
    "sg:province":"Gelderland",
    "wof:name":"Vijfsprong, De",
    "wof:placetype":"venue"
},
  "geometry": {"coordinates":[6.346209,52.117504],"type":"Point"}
}