{
  "type": "Feature",
  "properties": {
    "iso:country":"NL",
    "sg:address":"Nyverdalsestr 134",
    "sg:city":"Wierden",
    "sg:classifiers":[
        {
            "category":"Animal Shelter",
            "type":"Public Place"
        }
    ],
    "sg:phone":"+31 548 620 988",
    "sg:postcode":"7642 LG",
    "sg:province":"NL.08",
    "sg:tags":[
        "kennel"
    ],
    "sg:website":"HTTP://www.duitsedog.nl",
    "wof:name":"Huis Halfweg, Van",
    "wof:placetype":"venue"
},
  "geometry": {"coordinates":[6.590784,52.356815],"type":"Point"}
}