{
  "type": "Feature",
  "properties": {
    "addr:full":"Verl Poolsewg 34-36 Breda Noord-Brabant 4818 CL",
    "addr:housenumber":"34-36",
    "addr:postcode":"breda;4818",
    "iso:country":"NL",
    "sg:address":"Verl Poolsewg 34-36",
    "sg:city":"Breda",
    "sg:orig_category":"Werving En Selectie",
    "sg:phone":"+31 76 524 5064",
    "sg:postcode":"4818 CL",
    "sg:province":"Noord-Brabant",
    "sg:website":"http://www.finale.nl",
    "wof:name":"Finale",
    "wof:placetype":"venue"
},
  "geometry": {"coordinates":[4.802382946,51.5808105469],"type":"Point"}
}