{
  "type": "Feature",
  "properties": {
    "addr:full":"Zuidelijke Industrieweg 8 Franeker Provincie Friesland 8801 JB",
    "addr:housenumber":"8",
    "addr:postcode":"8801 jb",
    "addr:street":"Zuidelijke Industrieweg;Provincie Friesland",
    "iso:country":"NL",
    "sg:address":"Zuidelijke Industrieweg 8",
    "sg:city":"Franeker",
    "sg:orig_category":"Verhuur Catering-, Feest- En Evenementbenodigdheden",
    "sg:phone":"+31 517 392 501",
    "sg:postcode":"8801 JB",
    "sg:province":"Provincie Friesland",
    "wof:name":"Handelsonderneming J. Meijer En Zoon Bv",
    "wof:placetype":"venue"
},
  "geometry": {"coordinates":[5.542219162,53.1817016602],"type":"Point"}
}