{
  "type": "Feature",
  "properties": {
    "iso:country":"NL",
    "sg:address":"Postbus 30",
    "sg:city":"Middenmeer",
    "sg:orig_category":"Kantoormachines - Fabrieken En Groothandel",
    "sg:phone":"+31 227 503 650",
    "sg:postcode":"1775 ZG",
    "sg:province":"North Holland",
    "sg:website":"http://www.ruvo.org",
    "wof:name":"Ruvo Bv",
    "wof:placetype":"venue"
},
  "geometry": {"coordinates":[4.9986748695,52.8078231812],"type":"Point"}
}