{
  "type": "Feature",
  "properties": {
    "addr:full":"Dr W Beckmanln 48 Egmond Aan Zee North Holland 1931 BW",
    "addr:housenumber":"48",
    "addr:postcode":"1931 bw",
    "addr:street":"Dr W Beckmanln",
    "iso:country":"NL",
    "sg:address":"Dr W Beckmanln 48",
    "sg:city":"Egmond Aan Zee",
    "sg:orig_category":"Verzekeringen - Verzekeringskantoren",
    "sg:phone":"+31 72 506 4845",
    "sg:postcode":"1931 BW",
    "sg:province":"North Holland",
    "wof:name":"Greve, C J",
    "wof:placetype":"venue"
},
  "geometry": {"coordinates":[4.624575,52.623127],"type":"Point"}
}