{
  "type": "Feature",
  "properties": {
    "addr:full":"Abelenberg 19 Roosendaal Noord-Brabant 4707 ME",
    "addr:housenumber":"19",
    "addr:postcode":"4707 me",
    "addr:street":"Abelenberg",
    "iso:country":"NL",
    "sg:address":"Abelenberg 19",
    "sg:city":"Roosendaal",
    "sg:orig_category":"Autorijscholen",
    "sg:phone":"+31 165 554 260",
    "sg:postcode":"4707 ME",
    "sg:province":"Noord-Brabant",
    "sg:website":"http://www.herrijgers.nl",
    "wof:name":"Herrijgers",
    "wof:placetype":"venue"
},
  "geometry": {"coordinates":[4.452576,51.514786],"type":"Point"}
}