{
  "type": "Feature",
  "properties": {
    "addr:full":"Zevenbergenstraat 16 Eindhoven North Brabant 5652 JP",
    "addr:housenumber":"16",
    "addr:postcode":"5652 jp",
    "addr:street":"Zevenbergenstraat",
    "iso:country":"NL",
    "sg:address":"Zevenbergenstraat 16",
    "sg:city":"Eindhoven",
    "sg:orig_category":"Loodgieterswerk, Verwarming And Sanitaire Installaties",
    "sg:phone":"+31 40 292 0880",
    "sg:postcode":"5652 JP",
    "sg:province":"North Brabant",
    "wof:name":"Kbd",
    "wof:placetype":"venue"
},
  "geometry": {"coordinates":[5.436541,51.43898],"type":"Point"}
}