{
  "type": "Feature",
  "properties": {
    "addr:full":"Klimopstr 12 S Gravenhage Zuid-Holland 2565 VK",
    "addr:housenumber":"12;gravenhage",
    "addr:postcode":"2565 vk",
    "addr:street":"Klimopstr;S",
    "iso:country":"NL",
    "sg:address":"Klimopstr 12",
    "sg:city":"S Gravenhage",
    "sg:orig_category":"Beeldende Kunstenaars",
    "sg:phone":"+31 70 363 0663",
    "sg:postcode":"2565 VK",
    "sg:province":"Zuid-Holland",
    "wof:name":"Sans, K",
    "wof:placetype":"venue"
},
  "geometry": {"coordinates":[4.26129,52.076382],"type":"Point"}
}