{
  "type": "Feature",
  "properties": {
    "iso:country":"NL",
    "sg:address":"V W Poelmanwg 12",
    "sg:city":"Almelo",
    "sg:orig_category":"Lasapparaten En Benodigdheden",
    "sg:phone":"+31 546 491 464",
    "sg:postcode":"7602 PC",
    "sg:province":"Overijssel",
    "wof:name":"Vlh Bv",
    "wof:placetype":"venue"
},
  "geometry": {"coordinates":[6.664543,52.354954],"type":"Point"}
}