{
  "type": "Feature",
  "properties": {
    "iso:country":"NL",
    "sg:address":"Schenkelstraat 1",
    "sg:city":"Zoeterwoude",
    "sg:orig_category":"Boekhouders",
    "sg:phone":"+31 71 580 3700",
    "sg:postcode":"2381 BD",
    "sg:province":"South Holland",
    "wof:name":"Hulsbos Administraties Bv",
    "wof:placetype":"venue"
},
  "geometry": {"coordinates":[4.499346,52.117764],"type":"Point"}
}