{
  "type": "Feature",
  "properties": {
    "iso:country":"NL",
    "sg:address":"Wulp 5",
    "sg:city":"Genemuiden",
    "sg:orig_category":"Plafonds",
    "sg:phone":"+31 38 385 4871",
    "sg:postcode":"8281 GP",
    "sg:province":"NL.08",
    "wof:name":"Last, Plafonds & Wanden",
    "wof:placetype":"venue"
},
  "geometry": {"coordinates":[6.049025,52.617416],"type":"Point"}
}