{
  "type": "Feature",
  "properties": {
    "addr:full":"Wulp 5 Genemuiden NL.08 8281 GP",
    "addr:housenumber":"5;nl.08",
    "addr:postcode":"8281 gp",
    "addr:street":"Wulp",
    "iso:country":"NL",
    "sg:address":"Wulp 5",
    "sg:city":"Genemuiden",
    "sg:orig_category":"Plafonds",
    "sg:phone":"+31 38 385 4871",
    "sg:postcode":"8281 GP",
    "sg:province":"NL.08",
    "wof:name":"Last, Plafonds & Wanden",
    "wof:placetype":"venue"
},
  "geometry": {"coordinates":[6.049025,52.617416],"type":"Point"}
}