{
  "type": "Feature",
  "properties": {
    "addr:full":"Nieuwstr 17 Ravenstein Noord-Brabant 5371 AH",
    "addr:housenumber":"17",
    "addr:postcode":"5371 ah",
    "addr:street":"Nieuwstr",
    "iso:country":"NL",
    "sg:address":"Nieuwstr 17",
    "sg:city":"Ravenstein",
    "sg:orig_category":"Grafisch Ontwerpers",
    "sg:phone":"+31 486 411 944",
    "sg:postcode":"5371 AH",
    "sg:province":"Noord-Brabant",
    "wof:name":"Jb",
    "wof:placetype":"venue"
},
  "geometry": {"coordinates":[5.652966,51.797073],"type":"Point"}
}