{
  "type": "Feature",
  "properties": {
    "addr:full":"Iepenlaan 54 Schagen North Holland 1741 TG",
    "addr:housenumber":"54",
    "addr:postcode":"1741 tg",
    "addr:street":"Iepenlaan",
    "iso:country":"NL",
    "sg:address":"Iepenlaan 54",
    "sg:city":"Schagen",
    "sg:classifiers":[
        {
            "category":"Education",
            "subcategory":"Preschool",
            "type":"Public Place"
        }
    ],
    "sg:phone":"+31 224 213 286",
    "sg:postcode":"1741 TG",
    "sg:province":"North Holland",
    "sg:tags":[
        "kleuteronderwijs",
        "basis-"
    ],
    "wof:name":"Juliana Groeneweg School",
    "wof:placetype":"venue"
},
  "geometry": {"coordinates":[4.793873,52.797142],"type":"Point"}
}