{
  "type": "Feature",
  "properties": {
    "addr:full":"Amstelveensewg 718C Amsterdam Noord-Holland 1081 JK",
    "addr:housenumber":"718c",
    "addr:postcode":"1081 jk",
    "addr:street":"Amstelveensewg",
    "iso:country":"NL",
    "sg:address":"Amstelveensewg 718C",
    "sg:city":"Amsterdam",
    "sg:orig_category":"Adviesbureaus Bedrijfsorganisatie",
    "sg:phone":"+31 20 463 8327",
    "sg:postcode":"1081 JK",
    "sg:province":"Noord-Holland",
    "sg:website":"http://www.maaskantconsulting.com",
    "wof:name":"Maaskant Consulting",
    "wof:placetype":"venue"
},
  "geometry": {"coordinates":[4.856847,52.33329],"type":"Point"}
}