{
  "type": "Feature",
  "properties": {
    "iso:country":"NL",
    "sg:address":"Abtsln 15-A",
    "sg:city":"Terheyden",
    "sg:orig_category":"Peuterspeelzalen",
    "sg:phone":"+31 76 593 4151",
    "sg:postcode":"4844 SL",
    "sg:province":"Noord-Brabant",
    "wof:name":"Brakkensoos",
    "wof:placetype":"venue"
},
  "geometry": {"coordinates":[4.75427,51.641541],"type":"Point"}
}