{
  "type": "Feature",
  "properties": {
    "addr:full":"Kerkstr 61 Bunschoten Spakenb Utrecht 3751 AS",
    "addr:housenumber":"61",
    "addr:postcode":"3751 as",
    "addr:street":"Kerkstr",
    "iso:country":"NL",
    "sg:address":"Kerkstr 61",
    "sg:city":"Bunschoten Spakenb",
    "sg:orig_category":"Meubelen",
    "sg:phone":"+31 33 298 1453",
    "sg:postcode":"3751 AS",
    "sg:province":"Utrecht",
    "wof:name":"Loef",
    "wof:placetype":"venue"
},
  "geometry": {"coordinates":[5.378175,52.252949],"type":"Point"}
}