{
  "type": "Feature",
  "properties": {
    "iso:country":"NL",
    "sg:address":"Groenhof 111",
    "sg:city":"Amstelveen",
    "sg:orig_category":"Banken And Kredietinstellingen",
    "sg:phone":"+31 20 645 5951",
    "sg:postcode":"1186 EW",
    "sg:province":"Noord-Holland",
    "wof:name":"Abn Amro",
    "wof:placetype":"venue"
},
  "geometry": {"coordinates":[4.870042,52.289497],"type":"Point"}
}