{
  "type": "Feature",
  "properties": {
    "addr:full":"Reeln 12 Vierhouten Gelderland 8076 PK",
    "addr:housenumber":"12",
    "addr:postcode":"8076 pk",
    "addr:street":"Reeln;Gelderland",
    "iso:country":"NL",
    "sg:address":"Reeln 12",
    "sg:city":"Vierhouten",
    "sg:orig_category":"Pottenbakkerijen",
    "sg:phone":"+31 577 411 628",
    "sg:postcode":"8076 PK",
    "sg:province":"Gelderland",
    "wof:name":"Pandora",
    "wof:placetype":"venue"
},
  "geometry": {"coordinates":[5.827685,52.33218],"type":"Point"}
}