{
  "type": "Feature",
  "properties": {
    "addr:full":"Mercuriusplein 86 Berlicum Nb Noord-Brabant 5258 AW",
    "addr:housenumber":"86",
    "addr:postcode":"5258 aw",
    "addr:street":"Mercuriusplein",
    "iso:country":"NL",
    "sg:address":"Mercuriusplein 86",
    "sg:city":"Berlicum Nb",
    "sg:classifiers":[
        {
            "category":"Fast Food",
            "type":"Food & Drink"
        }
    ],
    "sg:phone":"+31 73 503 4114",
    "sg:postcode":"5258 AW",
    "sg:province":"Noord-Brabant",
    "sg:tags":[
        "afhaal",
        "restaurant"
    ],
    "wof:name":"Cafetaria 'T Vosje",
    "wof:placetype":"venue"
},
  "geometry": {"coordinates":[5.399582,51.678421],"type":"Point"}
}