{
  "type": "Feature",
  "properties": {
    "addr:full":"Utrechtsewg 213 Amersfoort Utrecht 3818 EE",
    "addr:housenumber":"213",
    "addr:postcode":"3818 ee",
    "iso:country":"NL",
    "sg:address":"Utrechtsewg 213",
    "sg:city":"Amersfoort",
    "sg:orig_category":"Pensioenen",
    "sg:phone":"+31 33 462 0142",
    "sg:postcode":"3818 EE",
    "sg:province":"Utrecht",
    "wof:name":"Meybaum, B J",
    "wof:placetype":"venue"
},
  "geometry": {"coordinates":[5.367164,52.144676],"type":"Point"}
}