{
  "type": "Feature",
  "properties": {
    "addr:full":"Losewg 39 Apeldoorn Gelderland 7315 BB",
    "addr:housenumber":"39",
    "addr:postcode":"7315 bb",
    "addr:street":"Losewg;Gelderland",
    "iso:country":"NL",
    "sg:address":"Losewg 39",
    "sg:city":"Apeldoorn",
    "sg:orig_category":"Modelbouw",
    "sg:phone":"+31 55 521 2270",
    "sg:postcode":"7315 BB",
    "sg:province":"Gelderland",
    "wof:name":"Wentink",
    "wof:placetype":"venue"
},
  "geometry": {"coordinates":[5.953059,52.224545],"type":"Point"}
}