{
  "type": "Feature",
  "properties": {
    "iso:country":"NL",
    "sg:address":"Postbus 60178",
    "sg:city":"Almere",
    "sg:orig_category":"Bedrijfsopleidingen",
    "sg:phone":"+31 36 545 2927",
    "sg:postcode":"1320 AE",
    "sg:province":"NL.",
    "sg:website":"http://www.bmztraining.nl",
    "wof:name":"Bmz",
    "wof:placetype":"venue"
},
  "geometry": {"coordinates":[5.21802,52.372211],"type":"Point"}
}