{
  "type": "Feature",
  "properties": {
    "addr:full":"Optimiststr 34 Rotterdam Zuid-Holland 3077 ZC",
    "addr:housenumber":"34",
    "addr:postcode":"3077 zc",
    "addr:street":"Optimiststr",
    "iso:country":"NL",
    "sg:address":"Optimiststr 34",
    "sg:city":"Rotterdam",
    "sg:orig_category":"Kantoor- En Secretariaatsservice",
    "sg:phone":"+31 10 482 8306",
    "sg:postcode":"3077 ZC",
    "sg:province":"Zuid-Holland",
    "wof:name":"Heer, De",
    "wof:placetype":"venue"
},
  "geometry": {"coordinates":[4.5547437668,51.9028244019],"type":"Point"}
}