{
  "type": "Feature",
  "properties": {
    "iso:country":"NL",
    "sg:address":"Troelstraplein 37",
    "sg:city":"Koog A/D Zaan",
    "sg:orig_category":"Zuivelproducten",
    "sg:phone":"+31 75 616 2548",
    "sg:postcode":"1541 EB",
    "sg:province":"Noord-Holland",
    "wof:name":"Zuivelhandel P.A. Glas",
    "wof:placetype":"venue"
},
  "geometry": {"coordinates":[4.809519,52.459023],"type":"Point"}
}