{
  "type": "Feature",
  "properties": {
    "addr:full":"Troelstraplein 37 Koog A/D Zaan Noord-Holland 1541 EB",
    "addr:housenumber":"37;a / d",
    "addr:postcode":"1541 eb",
    "addr:street":"Troelstraplein",
    "iso:country":"NL",
    "sg:address":"Troelstraplein 37",
    "sg:city":"Koog A/D Zaan",
    "sg:orig_category":"Zuivelproducten",
    "sg:phone":"+31 75 616 2548",
    "sg:postcode":"1541 EB",
    "sg:province":"Noord-Holland",
    "wof:name":"Zuivelhandel P.A. Glas",
    "wof:placetype":"venue"
},
  "geometry": {"coordinates":[4.809519,52.459023],"type":"Point"}
}