{
  "type": "Feature",
  "properties": {
    "addr:full":"O Nassaustr 13 Heerlen Limburg 6411 LE",
    "addr:housenumber":"13",
    "addr:postcode":"6411 le",
    "iso:country":"NL",
    "sg:address":"O Nassaustr 13",
    "sg:city":"Heerlen",
    "sg:orig_category":"Herenkleding",
    "sg:phone":"+31 45 571 6637",
    "sg:postcode":"6411 LE",
    "sg:province":"Limburg",
    "wof:name":"Inizio",
    "wof:placetype":"venue"
},
  "geometry": {"coordinates":[5.978695,50.88892],"type":"Point"}
}