{
  "type": "Feature",
  "properties": {
    "addr:full":"Tuinweg 40 Hoofddorp North Holland 2132 DP",
    "addr:housenumber":"40",
    "addr:postcode":"2132 dp",
    "addr:street":"Tuinweg",
    "iso:country":"NL",
    "sg:address":"Tuinweg 40",
    "sg:city":"Hoofddorp",
    "sg:orig_category":"Wasserettes And Stomerijen",
    "sg:phone":"+31 23 563 4062",
    "sg:postcode":"2132 DP",
    "sg:province":"North Holland",
    "sg:website":"http://www.citydrycleaning.nl",
    "wof:name":"City Dry Cleaning",
    "wof:placetype":"venue"
},
  "geometry": {"coordinates":[4.6921491623,52.3033714294],"type":"Point"}
}