{
  "type": "Feature",
  "properties": {
    "iso:country":"NL",
    "sg:address":"Kouvenderstraat 25",
    "sg:city":"Hoensbroek",
    "sg:orig_category":"Werving And Selectie Van Tijdelijk Personeel And Uitzendkantoren",
    "sg:phone":"+31 45 523 1680",
    "sg:postcode":"6431 HA",
    "sg:province":"Limburg",
    "wof:name":"Adecco",
    "wof:placetype":"venue"
},
  "geometry": {"coordinates":[5.9278659821,50.9250068665],"type":"Point"}
}