{
  "type": "Feature",
  "properties": {
    "addr:full":"Ringbaan West 365 Tilburg North Brabant 5037 PE",
    "addr:housenumber":"365",
    "addr:postcode":"5037 pe",
    "addr:street":"Ringbaan West",
    "iso:country":"NL",
    "sg:address":"Ringbaan West 365",
    "sg:city":"Tilburg",
    "sg:orig_category":"Autokeuringen",
    "sg:phone":"+31 13 467 3337",
    "sg:postcode":"5037 PE",
    "sg:province":"North Brabant",
    "wof:name":"Bp",
    "wof:placetype":"venue"
},
  "geometry": {"coordinates":[5.06388,51.556969],"type":"Point"}
}