{
  "type": "Feature",
  "properties": {
    "iso:country":"NL",
    "sg:address":"Brederodestr 108",
    "sg:city":"Amsterdam",
    "sg:orig_category":"Kinderopvang",
    "sg:phone":"+31 20 683 4327",
    "sg:postcode":"1054 VH",
    "sg:province":"Noord-Holland",
    "wof:name":"Rozenbottel",
    "wof:placetype":"venue"
},
  "geometry": {"coordinates":[4.862184,52.360878],"type":"Point"}
}