{
  "type": "Feature",
  "properties": {
    "iso:country":"NL",
    "sg:address":"Burg Sweensln 6",
    "sg:city":"Leidschendam",
    "sg:orig_category":"Verenigingsgebouwen",
    "sg:phone":"+31 70 320 2036",
    "sg:postcode":"2262 EB",
    "sg:province":"Zuid-Holland",
    "wof:name":"Heuvel, De",
    "wof:placetype":"venue"
},
  "geometry": {"coordinates":[4.389703,52.090912],"type":"Point"}
}