{
  "type": "Feature",
  "properties": {
    "iso:country":"NL",
    "sg:address":"Pythagorasstr 10",
    "sg:city":"Apeldoorn",
    "sg:orig_category":"Acupunctuur",
    "sg:phone":"+31 55 366 0392",
    "sg:postcode":"7323 HE",
    "sg:province":"Gelderland",
    "wof:name":"Stuijvenberg, W J",
    "wof:placetype":"venue"
},
  "geometry": {"coordinates":[5.987534,52.227863],"type":"Point"}
}