{
  "type": "Feature",
  "properties": {
    "addr:full":"Weibuorren 114 Ureterp Provincie Friesland 9247 BD",
    "addr:housenumber":"114",
    "addr:postcode":"9247 bd",
    "addr:street":"Weibuorren;Provincie Friesland",
    "iso:country":"NL",
    "sg:address":"Weibuorren 114",
    "sg:city":"Ureterp",
    "sg:orig_category":"Bouwmaterialen Gh",
    "sg:phone":"+31 512 301 417",
    "sg:postcode":"9247 BD",
    "sg:province":"Provincie Friesland",
    "wof:name":"Bouwmaterialen Eppinga Bv",
    "wof:placetype":"venue"
},
  "geometry": {"coordinates":[6.173947,53.095303],"type":"Point"}
}