{
  "type": "Feature",
  "properties": {
    "iso:country":"NL",
    "sg:address":"Hessenweg 201",
    "sg:city":"Achterveld",
    "sg:orig_category":"Glaszetten",
    "sg:phone":"+31 342 451 771",
    "sg:postcode":"3791 PG",
    "sg:province":"Utrecht",
    "wof:name":"Schildersbedrijf Bertus Blom",
    "wof:placetype":"venue"
},
  "geometry": {"coordinates":[5.485375,52.140518],"type":"Point"}
}