{
  "type": "Feature",
  "properties": {
    "addr:full":"Grieteny 43 Leek Groningen 9351 JC",
    "addr:housenumber":"43",
    "addr:postcode":"9351 jc",
    "addr:street":"Grieteny",
    "iso:country":"NL",
    "sg:address":"Grieteny 43",
    "sg:city":"Leek",
    "sg:orig_category":"Mensendieck - Oefentherapeuten",
    "sg:phone":"+31 594 511 114",
    "sg:postcode":"9351 JC",
    "sg:province":"Groningen",
    "wof:name":"Noordman, B",
    "wof:placetype":"venue"
},
  "geometry": {"coordinates":[6.373524,53.159782],"type":"Point"}
}