{
  "type": "Feature",
  "properties": {
    "iso:country":"NL",
    "sg:address":"Zwartewater 40",
    "sg:city":"Utrecht",
    "sg:orig_category":"Psychotherapeuten",
    "sg:phone":"+31 30 271 8691",
    "sg:postcode":"3514 BP",
    "sg:province":"Utrecht",
    "wof:name":"Surrendra, Prakt",
    "wof:placetype":"venue"
},
  "geometry": {"coordinates":[5.117228,52.100418],"type":"Point"}
}