{
  "type": "Feature",
  "properties": {
    "addr:full":"Vanillestr 16 Almere Flevoland 1314 KE",
    "addr:housenumber":"16",
    "addr:postcode":"1314 ke",
    "addr:street":"Vanillestr;Flevoland",
    "iso:country":"NL",
    "sg:address":"Vanillestr 16",
    "sg:city":"Almere",
    "sg:orig_category":"Administratie- En Boekhoudkantoren",
    "sg:phone":"+31 36 533 0834",
    "sg:postcode":"1314 KE",
    "sg:province":"Flevoland",
    "wof:name":"Ag",
    "wof:placetype":"venue"
},
  "geometry": {"coordinates":[5.210369,52.378567],"type":"Point"}
}