{
  "type": "Feature",
  "properties": {
    "addr:full":"Keetberglaan 17 Ijmuiden North Holland 1974 XA",
    "addr:housenumber":"17",
    "addr:postcode":"1974 xa",
    "addr:street":"Keetberglaan",
    "iso:country":"NL",
    "sg:address":"Keetberglaan 17",
    "sg:city":"Ijmuiden",
    "sg:classifiers":[
        {
            "category":"Education",
            "subcategory":"Preschool",
            "type":"Public Place"
        }
    ],
    "sg:phone":"+31 255 513 547",
    "sg:postcode":"1974 XA",
    "sg:province":"North Holland",
    "sg:tags":[
        "kleuteronderwijs",
        "basis-"
    ],
    "wof:name":"Basisschool De Zandloper",
    "wof:placetype":"venue"
},
  "geometry": {"coordinates":[4.583554,52.449654],"type":"Point"}
}