{
  "type": "Feature",
  "properties": {
    "addr:full":"Hoofdstr 60 Nieuwolda Groningen 9944 AG",
    "addr:housenumber":"60",
    "addr:postcode":"9944",
    "addr:street":"Hoofdstr",
    "iso:country":"NL",
    "sg:address":"Hoofdstr 60",
    "sg:city":"Nieuwolda",
    "sg:orig_category":"Zalenverhuur",
    "sg:phone":"+31 596 541 572",
    "sg:postcode":"9944 AG",
    "sg:province":"Groningen",
    "wof:name":"Trefpunt, 'T",
    "wof:placetype":"venue"
},
  "geometry": {"coordinates":[6.976595,53.244896],"type":"Point"}
}