{
  "type": "Feature",
  "properties": {
    "addr:full":"Herengracht 316 Amsterdam Noord-Holland 1016 CD",
    "addr:housenumber":"316",
    "addr:postcode":"1016 cd",
    "addr:street":"Herengracht",
    "iso:country":"NL",
    "sg:address":"Herengracht 316",
    "sg:city":"Amsterdam",
    "sg:orig_category":"Ambassades And Consulaten",
    "sg:phone":"+31 20 626 7762",
    "sg:postcode":"1016 CD",
    "sg:province":"Noord-Holland",
    "wof:name":"Consulaat Of Jamaica",
    "wof:placetype":"venue"
},
  "geometry": {"coordinates":[4.886363,52.369793],"type":"Point"}
}