{
  "type": "Feature",
  "properties": {
    "iso:country":"NL",
    "sg:address":"Kabelbaan 19",
    "sg:city":"Leiderdorp",
    "sg:orig_category":"Zonweringen",
    "sg:phone":"+31 71 582 3823",
    "sg:postcode":"2352 BL",
    "sg:province":"South Holland",
    "wof:name":"Klinkenberg",
    "wof:placetype":"venue"
},
  "geometry": {"coordinates":[4.51967,52.164986],"type":"Point"}
}