{
  "type": "Feature",
  "properties": {
    "addr:full":"Oosteinde 19 Harderwijk Gelderland 3842 DR",
    "addr:housenumber":"19",
    "addr:postcode":"3842 dr",
    "addr:street":"Oosteinde;Gelderland",
    "iso:country":"NL",
    "sg:address":"Oosteinde 19",
    "sg:city":"Harderwijk",
    "sg:classifiers":[
        {
            "category":"Professional",
            "subcategory":"Accounting & Tax Preparation",
            "type":"Services"
        }
    ],
    "sg:phone":"+31 341 432 044",
    "sg:postcode":"3842 DR",
    "sg:province":"Gelderland",
    "sg:tags":[
        "accountant"
    ],
    "wof:name":"Accountantskantoor Adw Accountants",
    "wof:placetype":"venue"
},
  "geometry": {"coordinates":[5.636294,52.350456],"type":"Point"}
}