{
  "type": "Feature",
  "properties": {
    "addr:full":"Kolkrijst 38 Hoogland Utrecht 3828 EK",
    "addr:housenumber":"38",
    "addr:postcode":"3828 ek",
    "addr:street":"Kolkrijst",
    "iso:country":"NL",
    "sg:address":"Kolkrijst 38",
    "sg:city":"Hoogland",
    "sg:orig_category":"Handelsbemiddeling Textiel And Lederwaren",
    "sg:phone":"+31 33 480 3060",
    "sg:postcode":"3828 EK",
    "sg:province":"Utrecht",
    "wof:name":"Leloux Agenturen",
    "wof:placetype":"venue"
},
  "geometry": {"coordinates":[5.377794,52.191395],"type":"Point"}
}