{
  "type": "Feature",
  "properties": {
    "addr:full":"Debussylaan 24 Assen Drenthe 9402 WE",
    "addr:housenumber":"24",
    "addr:postcode":"9402 we",
    "addr:street":"Debussylaan",
    "iso:country":"NL",
    "sg:address":"Debussylaan 24",
    "sg:city":"Assen",
    "sg:orig_category":"Kappers",
    "sg:phone":"+31 592 346 694",
    "sg:postcode":"9402 WE",
    "sg:province":"Drenthe",
    "wof:name":"Haaratelier Tineke",
    "wof:placetype":"venue"
},
  "geometry": {"coordinates":[6.5561060905,53.0116043091],"type":"Point"}
}