{
  "type": "Feature",
  "properties": {
    "addr:full":"Hooyerstg 10A Koekange Provincie Drenthe 7958 PC",
    "addr:housenumber":"10a",
    "addr:postcode":"7958 pc",
    "addr:street":"Hooyerstg;Provincie Drenthe",
    "iso:country":"NL",
    "sg:address":"Hooyerstg 10A",
    "sg:city":"Koekange",
    "sg:orig_category":"Acupunctuur",
    "sg:phone":"+31 522 452 176",
    "sg:postcode":"7958 PC",
    "sg:province":"Provincie Drenthe",
    "wof:name":"Steuns, S",
    "wof:placetype":"venue"
},
  "geometry": {"coordinates":[6.321846,52.69772],"type":"Point"}
}