{
  "type": "Feature",
  "properties": {
    "addr:full":"Kosterstr 1 Zandvoort North Holland 2042 JJ",
    "addr:housenumber":"1",
    "addr:postcode":"2042 jj",
    "addr:street":"Kosterstr",
    "iso:country":"NL",
    "sg:address":"Kosterstr 1",
    "sg:city":"Zandvoort",
    "sg:orig_category":"Discotheken",
    "sg:phone":"+31 23 571 4347",
    "sg:postcode":"2042 JJ",
    "sg:province":"North Holland",
    "sg:website":"http://www.seasonscafe.nl",
    "wof:name":"Seasons Zandvoort Bv",
    "wof:placetype":"venue"
},
  "geometry": {"coordinates":[4.52765,52.372444],"type":"Point"}
}