{
  "type": "Feature",
  "properties": {
    "addr:full":"Gildewg 22 Vlissingen Zeeland 4383 NK",
    "addr:housenumber":"22",
    "addr:postcode":"4383 nk",
    "addr:street":"Gildewg",
    "iso:country":"NL",
    "sg:address":"Gildewg 22",
    "sg:city":"Vlissingen",
    "sg:classifiers":[
        {
            "category":"Professional",
            "type":"Services"
        }
    ],
    "sg:phone":"+31 118 424 022",
    "sg:postcode":"4383 NK",
    "sg:province":"Zeeland",
    "sg:tags":[
        "leasing"
    ],
    "wof:name":"Walcheren Auto Lease Bv",
    "wof:placetype":"venue"
},
  "geometry": {"coordinates":[3.587893,51.456005],"type":"Point"}
}