{
  "type": "Feature",
  "properties": {
    "addr:full":"Schultestraat 45 Hoogersmilde Drenthe 9423 PK",
    "addr:housenumber":"45",
    "addr:postcode":"9423 pk",
    "addr:street":"Schultestraat",
    "iso:country":"NL",
    "sg:address":"Schultestraat 45",
    "sg:city":"Hoogersmilde",
    "sg:orig_category":"Levende Dieren Gh",
    "sg:phone":"+31 592 459 251",
    "sg:postcode":"9423 PK",
    "sg:province":"Drenthe",
    "wof:name":"C.A. Hatzmann",
    "wof:placetype":"venue"
},
  "geometry": {"coordinates":[6.392423,52.907703],"type":"Point"}
}