{
  "type": "Feature",
  "properties": {
    "addr:full":"Makado Centrum 47 Schagen Noord-Holland 1741 JA",
    "addr:housenumber":"47",
    "addr:postcode":"1741 ja",
    "addr:street":"Makado Centrum",
    "iso:country":"NL",
    "sg:address":"Makado Centrum 47",
    "sg:city":"Schagen",
    "sg:orig_category":"Wasserettes And Stomerijen",
    "sg:phone":"+31 224 213 415",
    "sg:postcode":"1741 JA",
    "sg:province":"Noord-Holland",
    "wof:name":"Clean Inn Fa Wijnstok-De Pijper",
    "wof:placetype":"venue"
},
  "geometry": {"coordinates":[4.7993459702,52.7878417969],"type":"Point"}
}