{
  "type": "Feature",
  "properties": {
    "iso:country":"NL",
    "sg:address":"Weegschaal 49",
    "sg:city":"Bilthoven",
    "sg:orig_category":"Vertaalbureaus",
    "sg:phone":"+31 30 228 5656",
    "sg:postcode":"3721 WN",
    "sg:province":"Utrecht",
    "wof:name":"Rusnet",
    "wof:placetype":"venue"
},
  "geometry": {"coordinates":[5.182185,52.122643],"type":"Point"}
}