{
  "type": "Feature",
  "properties": {
    "addr:full":"P Donderspln 25 St Michielsgestel Noord-Brabant 5271 AA",
    "addr:housenumber":"25",
    "addr:postcode":"5271 aa",
    "addr:street":"P;St Michielsgestel",
    "iso:country":"NL",
    "sg:address":"P Donderspln 25",
    "sg:city":"St Michielsgestel",
    "sg:orig_category":"Grafisch Ontwerpers",
    "sg:phone":"+31 73 551 2307",
    "sg:postcode":"5271 AA",
    "sg:province":"Noord-Brabant",
    "wof:name":"Veenman, J",
    "wof:placetype":"venue"
},
  "geometry": {"coordinates":[5.350359,51.638638],"type":"Point"}
}