{
  "type": "Feature",
  "properties": {
    "iso:country":"NL",
    "sg:address":"Meidoornstraat 6",
    "sg:city":"'S Gravenhage",
    "sg:orig_category":"Verhuisdiensten",
    "sg:phone":"+31 70 368 7522",
    "sg:postcode":"2563 GH",
    "sg:province":"Zuid-Holland",
    "wof:name":"De Verhuizer",
    "wof:placetype":"venue"
},
  "geometry": {"coordinates":[4.26966,52.072639],"type":"Point"}
}