{
  "type": "Feature",
  "properties": {
    "addr:full":"Aldringastr 7 Niekerk Grootegast Groningen 9822 AM",
    "addr:housenumber":"7",
    "addr:postcode":"9822",
    "addr:street":"Aldringastr",
    "iso:country":"NL",
    "sg:address":"Aldringastr 7",
    "sg:city":"Niekerk Grootegast",
    "sg:orig_category":"Kopieerapparaten",
    "sg:phone":"+31 594 505 985",
    "sg:postcode":"9822 AM",
    "sg:province":"Groningen",
    "wof:name":"Mepo Reproservice",
    "wof:placetype":"venue"
},
  "geometry": {"coordinates":[6.353183,53.22501],"type":"Point"}
}