{
  "type": "Feature",
  "properties": {
    "addr:full":"Waalreseweg 17 Valkenswaard Noord-Brabant 5554 HA",
    "addr:housenumber":"17",
    "addr:postcode":"5554 ha",
    "addr:street":"Waalreseweg",
    "iso:country":"NL",
    "sg:address":"Waalreseweg 17",
    "sg:city":"Valkenswaard",
    "sg:orig_category":"Metaalbekleding And -Behandeling",
    "sg:phone":"+31 40 208 9292",
    "sg:postcode":"5554 HA",
    "sg:province":"Noord-Brabant",
    "wof:name":"Co-Metronic",
    "wof:placetype":"venue"
},
  "geometry": {"coordinates":[5.457215,51.351959],"type":"Point"}
}