{
  "type": "Feature",
  "properties": {
    "addr:full":"Haringvliet 76 Rotterdam Zuid-Holland 3011 TG",
    "addr:housenumber":"76",
    "addr:postcode":"3011 tg",
    "addr:street":"Haringvliet",
    "iso:country":"NL",
    "sg:address":"Haringvliet 76",
    "sg:city":"Rotterdam",
    "sg:orig_category":"Partycatering And -Organisatie",
    "sg:phone":"+31 10 213 0912",
    "sg:postcode":"3011 TG",
    "sg:province":"Zuid-Holland",
    "wof:name":"Kantjil Catering & Dinner Service",
    "wof:placetype":"venue"
},
  "geometry": {"coordinates":[4.495221,51.919548],"type":"Point"}
}