{
  "type": "Feature",
  "properties": {
    "iso:country":"NL",
    "sg:address":"T Sant 2",
    "sg:city":"Wyk By Duurstede",
    "sg:orig_category":"Autorijscholen",
    "sg:phone":"+31 343 597 779",
    "sg:postcode":"3962 TB",
    "sg:province":"Utrecht",
    "sg:website":"http://www.rijschoolbeumer.nl",
    "wof:name":"Beumer Auto- & Aanhangwagenrijschool",
    "wof:placetype":"venue"
},
  "geometry": {"coordinates":[5.349215,51.977615],"type":"Point"}
}