{
  "type": "Feature",
  "properties": {
    "iso:country":"NL",
    "sg:address":"Westravenstr 19",
    "sg:city":"Utrecht",
    "sg:orig_category":"Vertalers",
    "sg:phone":"+31 30 287 0648",
    "sg:postcode":"3522 TA",
    "sg:province":"Utrecht",
    "wof:name":"Boissevain, R L",
    "wof:placetype":"venue"
},
  "geometry": {"coordinates":[5.11761,52.072758],"type":"Point"}
}