{
  "type": "Feature",
  "properties": {
    "addr:full":"Schoolstraat 12 Varsseveld Gelderland 7051 DC",
    "addr:housenumber":"12",
    "addr:postcode":"7051",
    "addr:street":"Schoolstraat;Gelderland",
    "iso:country":"NL",
    "sg:address":"Schoolstraat 12",
    "sg:city":"Varsseveld",
    "sg:orig_category":"Kappers",
    "sg:phone":"+31 315 242 121",
    "sg:postcode":"7051 DC",
    "sg:province":"Gelderland",
    "wof:name":"Salon New Image",
    "wof:placetype":"venue"
},
  "geometry": {"coordinates":[6.465558,51.94376],"type":"Point"}
}