{
  "type": "Feature",
  "properties": {
    "addr:full":"De Warande 89 Driebergen Rysenb Utrecht 3972 XX",
    "addr:housenumber":"89",
    "addr:postcode":"3972 xx",
    "addr:street":"De Warande;Rysenb",
    "iso:country":"NL",
    "sg:address":"De Warande 89",
    "sg:city":"Driebergen Rysenb",
    "sg:orig_category":"Adviesbureaus Bedrijfsorganisatie",
    "sg:phone":"+31 343 510 704",
    "sg:postcode":"3972 XX",
    "sg:province":"Utrecht",
    "wof:name":"Jenken",
    "wof:placetype":"venue"
},
  "geometry": {"coordinates":[5.269002,52.048126],"type":"Point"}
}