{
  "type": "Feature",
  "properties": {
    "iso:country":"NL",
    "sg:address":"Roerdompstraat 32",
    "sg:city":"Landsmeer",
    "sg:orig_category":"Loodgieterswerk, Verwarming And Sanitaire Installaties",
    "sg:phone":"+31 20 482 5268",
    "sg:postcode":"1121 NB",
    "sg:province":"North Holland",
    "wof:name":"Loodgietersbedrijf J. Kroon",
    "wof:placetype":"venue"
},
  "geometry": {"coordinates":[4.918267,52.430405],"type":"Point"}
}