{
  "type": "Feature",
  "properties": {
    "addr:full":"Lakenstr 54 Geldrop Noord-Brabant 5667 TR",
    "addr:housenumber":"54",
    "addr:postcode":"5667 tr",
    "addr:street":"Lakenstr",
    "iso:country":"NL",
    "sg:address":"Lakenstr 54",
    "sg:city":"Geldrop",
    "sg:orig_category":"Projectinrichting",
    "sg:phone":"+31 6 53149770",
    "sg:postcode":"5667 TR",
    "sg:province":"Noord-Brabant",
    "wof:name":"Buys, M J Op Den",
    "wof:placetype":"venue"
},
  "geometry": {"coordinates":[5.570397,51.431385],"type":"Point"}
}