{
  "type": "Feature",
  "properties": {
    "addr:full":"Rutbeek 21 Zwolle Overijssel 8033 BK",
    "addr:housenumber":"21",
    "addr:postcode":"8033 bk",
    "addr:street":"Rutbeek",
    "iso:country":"NL",
    "sg:address":"Rutbeek 21",
    "sg:city":"Zwolle",
    "sg:orig_category":"Mobiele- En Autotelefoons",
    "sg:phone":"+31 38 455 0520",
    "sg:postcode":"8033 BK",
    "sg:province":"Overijssel",
    "wof:name":"C-Tec",
    "wof:placetype":"venue"
},
  "geometry": {"coordinates":[6.112339,52.533398],"type":"Point"}
}