{
  "type": "Feature",
  "properties": {
    "addr:full":"Duerswald 8 Wynjewoude Provincie Friesland 9241 GX",
    "addr:housenumber":"8",
    "addr:postcode":"9241 gx",
    "addr:street":"Duerswald;Provincie Friesland",
    "iso:country":"NL",
    "sg:address":"Duerswald 8",
    "sg:city":"Wynjewoude",
    "sg:orig_category":"Fietsen En Bromfietsen",
    "sg:phone":"+31 516 541 268",
    "sg:postcode":"9241 GX",
    "sg:province":"Provincie Friesland",
    "wof:name":"Meinsma & Zn Vof, J",
    "wof:placetype":"venue"
},
  "geometry": {"coordinates":[6.214111,53.057331],"type":"Point"}
}