{
  "type": "Feature",
  "properties": {
    "addr:full":"Steniawg 10 Zeist Utrecht 3702 AG",
    "addr:housenumber":"10",
    "addr:postcode":"3702",
    "addr:street":"Steniawg",
    "iso:country":"NL",
    "sg:address":"Steniawg 10",
    "sg:city":"Zeist",
    "sg:orig_category":"Meubelmakerijen",
    "sg:phone":"+31 6 51560021",
    "sg:postcode":"3702 AG",
    "sg:province":"Utrecht",
    "wof:name":"Tenso",
    "wof:placetype":"venue"
},
  "geometry": {"coordinates":[5.234946,52.086029],"type":"Point"}
}