{
  "type": "Feature",
  "properties": {
    "iso:country":"NL",
    "sg:address":"Stationswg 7",
    "sg:city":"Aalsmeer",
    "sg:orig_category":"Accountants - Administratie- Consulenten En -Kantoren",
    "sg:phone":"+31 297 326 957",
    "sg:postcode":"1431 EG",
    "sg:province":"Noord-Holland",
    "wof:name":"Amstelland",
    "wof:placetype":"venue"
},
  "geometry": {"coordinates":[4.749774,52.266064],"type":"Point"}
}