{
  "type": "Feature",
  "properties": {
    "addr:full":"Westeinde 26 Roelofarendsveen Zuid-Holland 2371 BC",
    "addr:housenumber":"26",
    "addr:postcode":"2371 bc",
    "addr:street":"Westeinde",
    "iso:country":"NL",
    "sg:address":"Westeinde 26",
    "sg:city":"Roelofarendsveen",
    "sg:orig_category":"Fotostudio'S And Fotografen",
    "sg:phone":"+31 71 331 3664",
    "sg:postcode":"2371 BC",
    "sg:province":"Zuid-Holland",
    "wof:name":"Fotografie- Fotostudio Erico Van Der Hor",
    "wof:placetype":"venue"
},
  "geometry": {"coordinates":[4.623142,52.201908],"type":"Point"}
}