{
  "type": "Feature",
  "properties": {
    "addr:full":"Wite Burch 7 Bakhuizen Provincie Friesland 8574 VC",
    "addr:housenumber":"7",
    "addr:postcode":"8574 vc",
    "addr:street":"Wite Burch;Provincie Friesland",
    "iso:country":"NL",
    "sg:address":"Wite Burch 7",
    "sg:city":"Bakhuizen",
    "sg:orig_category":"Jeugdherbergen And Berghutten",
    "sg:phone":"+31 514 581 382",
    "sg:postcode":"8574 VC",
    "sg:province":"Provincie Friesland",
    "wof:name":"De Wite Burch",
    "wof:placetype":"venue"
},
  "geometry": {"coordinates":[5.468729,52.871609],"type":"Point"}
}