{
  "type": "Feature",
  "properties": {
    "addr:full":"A-Straat 15 Groningen Groningen 9718 CP",
    "addr:housenumber":"15",
    "addr:postcode":"9718 cp",
    "addr:street":"A-Straat",
    "iso:country":"NL",
    "sg:address":"A-Straat 15",
    "sg:city":"Groningen",
    "sg:orig_category":"Muziekinstrumenten",
    "sg:phone":"+31 900 7001432",
    "sg:postcode":"9718 CP",
    "sg:province":"Groningen",
    "wof:name":"Muziekhuis Westerhaven",
    "wof:placetype":"venue"
},
  "geometry": {"coordinates":[6.574715,53.217144],"type":"Point"}
}