{
  "type": "Feature",
  "properties": {
    "iso:country":"NL",
    "sg:address":"Scholiersberg 18",
    "sg:city":"Bergen Op Zoom",
    "sg:classifiers":[
        {
            "category":"Food & Beverages",
            "subcategory":"Fruits & Vegetables",
            "type":"Retail Goods"
        }
    ],
    "sg:phone":"+31 164 210 372",
    "sg:postcode":"4611 SX",
    "sg:province":"Noord-Brabant",
    "sg:tags":[
        "groenten"
    ],
    "wof:name":"Jan Bruijs",
    "wof:placetype":"venue"
},
  "geometry": {"coordinates":[4.285405,51.496601],"type":"Point"}
}