{
  "type": "Feature",
  "properties": {
    "iso:country":"NL",
    "sg:address":"Tussen Meer 65",
    "sg:city":"Amsterdam",
    "sg:orig_category":"Bloemen En Planten",
    "sg:phone":"+31 20 619 0086",
    "sg:postcode":"1068 EZ",
    "sg:province":"Noord-Holland",
    "wof:name":"Flori Cultura",
    "wof:placetype":"venue"
},
  "geometry": {"coordinates":[4.800936,52.35815],"type":"Point"}
}