{
  "type": "Feature",
  "properties": {
    "addr:full":"Albert Verweystraat 52 Noordwijk Zh South Holland 2202 NP",
    "addr:housenumber":"52",
    "addr:postcode":"zh;2202 np",
    "addr:street":"Albert Verweystraat",
    "iso:country":"NL",
    "sg:address":"Albert Verweystraat 52",
    "sg:city":"Noordwijk Zh",
    "sg:classifiers":[
        {
            "category":"Food & Beverages",
            "subcategory":"Fruits & Vegetables",
            "type":"Retail Goods"
        }
    ],
    "sg:phone":"+31 71 361 2163",
    "sg:postcode":"2202 NP",
    "sg:province":"South Holland",
    "sg:tags":[
        "groenten"
    ],
    "wof:name":"J A Th V D Meer",
    "wof:placetype":"venue"
},
  "geometry": {"coordinates":[4.439382,52.248901],"type":"Point"}
}