{
  "type": "Feature",
  "properties": {
    "addr:full":"Marathon 3 Hilversum Noord-Holland 1213 PB",
    "addr:housenumber":"3",
    "addr:postcode":"1213 pb",
    "addr:street":"Marathon",
    "iso:country":"NL",
    "sg:address":"Marathon 3",
    "sg:city":"Hilversum",
    "sg:classifiers":[
        {
            "category":"Professional",
            "subcategory":"Accounting & Tax Preparation",
            "type":"Services"
        }
    ],
    "sg:phone":"+31 35 688 5151",
    "sg:postcode":"1213 PB",
    "sg:province":"Noord-Holland",
    "sg:tags":[
        "accountant",
        "en",
        "-kantoren",
        "register-"
    ],
    "sg:website":"http://www.deloitte.nl/",
    "wof:name":"Deloitte & Touche",
    "wof:placetype":"venue"
},
  "geometry": {"coordinates":[5.194061,52.211098],"type":"Point"}
}