{
  "type": "Feature",
  "properties": {
    "addr:full":"Kantemarswg 6 Hoevelaken Gelderland 3871 AP",
    "addr:housenumber":"6",
    "addr:postcode":"3871 ap",
    "addr:street":"Kantemarswg;Gelderland",
    "iso:country":"NL",
    "sg:address":"Kantemarswg 6",
    "sg:city":"Hoevelaken",
    "sg:orig_category":"Verenigingen En Stichtingen",
    "sg:phone":"+31 33 253 7876",
    "sg:postcode":"3871 AP",
    "sg:province":"Gelderland",
    "wof:name":"Jeugd En Jongerenwerk, Sticht",
    "wof:placetype":"venue"
},
  "geometry": {"coordinates":[5.455554,52.176418],"type":"Point"}
}