{
  "type": "Feature",
  "properties": {
    "addr:full":"Markt 6 Geertruidenberg North Brabant 4931 BS",
    "addr:housenumber":"6",
    "addr:postcode":"4931 bs",
    "addr:street":"Markt",
    "iso:country":"NL",
    "sg:address":"Markt 6",
    "sg:city":"Geertruidenberg",
    "sg:orig_category":"Notarissen En Notariskantoren",
    "sg:phone":"+31 162 516 400",
    "sg:postcode":"4931 BS",
    "sg:province":"North Brabant",
    "sg:website":"http://www.knb.nl",
    "wof:name":"Meijer Notariskantoor, Mr J K A",
    "wof:placetype":"venue"
},
  "geometry": {"coordinates":[4.861088,51.700634],"type":"Point"}
}