{
  "type": "Feature",
  "properties": {
    "iso:country":"NL",
    "sg:address":"Eschdoornln 8",
    "sg:city":"Zaandyk",
    "sg:orig_category":"Montagebedrijven",
    "sg:phone":"+31 75 621 8897",
    "sg:postcode":"1544 AZ",
    "sg:province":"North Holland",
    "wof:name":"Schoolmeester",
    "wof:placetype":"venue"
},
  "geometry": {"coordinates":[4.808343,52.472748],"type":"Point"}
}