{
  "type": "Feature",
  "properties": {
    "addr:full":"Wilhelminapln 18 Best Texas 5684 VL",
    "addr:housenumber":"18",
    "addr:postcode":"5684 vl",
    "addr:street":"Wilhelminapln",
    "iso:country":"NL",
    "sg:address":"Wilhelminapln 18",
    "sg:city":"Best",
    "sg:orig_category":"Boeken En Tijdschriften",
    "sg:phone":"+31 499 378 444",
    "sg:postcode":"5684 VL",
    "sg:province":"Texas",
    "wof:name":"Paperas",
    "wof:placetype":"venue"
},
  "geometry": {"coordinates":[-101.618134,31.224251],"type":"Point"}
}