{
  "type": "Feature",
  "properties": {
    "iso:country":"NL",
    "sg:address":"Molenwieken 3",
    "sg:city":"Veghel",
    "sg:orig_category":"Boekhandels",
    "sg:phone":"+31 413 363 081",
    "sg:postcode":"5461 KE",
    "sg:province":"Noord-Brabant",
    "wof:name":"Schellen",
    "wof:placetype":"venue"
},
  "geometry": {"coordinates":[5.544677,51.616432],"type":"Point"}
}