{
  "type": "Feature",
  "properties": {
    "addr:full":"Knsm Ln 749 Amsterdam North Holland 1019 LJ",
    "addr:housenumber":"749",
    "addr:postcode":"1019 lj",
    "addr:street":"Knsm Ln",
    "iso:country":"NL",
    "sg:address":"Knsm Ln 749",
    "sg:city":"Amsterdam",
    "sg:orig_category":"Accountants - Administratie- Consulenten En -Kantoren",
    "sg:phone":"+31 20 418 0909",
    "sg:postcode":"1019 LJ",
    "sg:province":"North Holland",
    "sg:website":"http://www.integrityaccounts.nl",
    "wof:name":"Integrity (Ac)Counts",
    "wof:placetype":"venue"
},
  "geometry": {"coordinates":[4.945036,52.377289],"type":"Point"}
}