{
  "type": "Feature",
  "properties": {
    "addr:full":"Zeedijk 89 Amsterdam Noord-Holland 1012 AT",
    "addr:housenumber":"89",
    "addr:postcode":"1012",
    "addr:street":"Zeedijk",
    "iso:country":"NL",
    "sg:address":"Zeedijk 89",
    "sg:city":"Amsterdam",
    "sg:classifiers":[
        {
            "category":"Shopping",
            "subcategory":"Gifts & Souvenirs",
            "type":"Retail Goods"
        }
    ],
    "sg:phone":"+31 20 622 2868",
    "sg:postcode":"1012 AT",
    "sg:province":"Noord-Holland",
    "sg:tags":[
        "geschenken"
    ],
    "wof:name":"Trading Company Holwha",
    "wof:placetype":"venue"
},
  "geometry": {"coordinates":[4.900624,52.374241],"type":"Point"}
}