{
  "type": "Feature",
  "properties": {
    "iso:country":"NL",
    "sg:address":"Oude Watering 281",
    "sg:city":"Rotterdam",
    "sg:orig_category":"Kappers",
    "sg:phone":"+31 10 483 3639",
    "sg:postcode":"3077 RG",
    "sg:province":"Zuid-Holland",
    "wof:name":"Sylviana Haarstudio",
    "wof:placetype":"venue"
},
  "geometry": {"coordinates":[4.56849,51.892464],"type":"Point"}
}