{
  "type": "Feature",
  "properties": {
    "addr:full":"Parklaan 8/1 Nuth Limburg 6361 VV",
    "addr:housenumber":"8 / 1",
    "addr:postcode":"6361 vv",
    "addr:street":"Parklaan",
    "iso:country":"NL",
    "sg:address":"Parklaan 8/1",
    "sg:city":"Nuth",
    "sg:orig_category":"Schilderwerk",
    "sg:phone":"+31 45 524 5194",
    "sg:postcode":"6361 VV",
    "sg:province":"Limburg",
    "wof:name":"R. Smeets",
    "wof:placetype":"venue"
},
  "geometry": {"coordinates":[5.885011,50.915127],"type":"Point"}
}