{
  "type": "Feature",
  "properties": {
    "iso:country":"NL",
    "sg:address":"Wittenburgerweg 28",
    "sg:city":"Wassenaar",
    "sg:orig_category":"Binnenhuisarchitecten",
    "sg:phone":"+31 70 511 2294",
    "sg:postcode":"2244 CB",
    "sg:province":"South Holland",
    "wof:name":"Philomene Chapot Interieurs",
    "wof:placetype":"venue"
},
  "geometry": {"coordinates":[4.354249,52.11087],"type":"Point"}
}