{
  "type": "Feature",
  "properties": {
    "addr:full":"Wittenburgerweg 28 Wassenaar South Holland 2244 CB",
    "addr:housenumber":"28",
    "addr:postcode":"2244 cb",
    "addr:street":"Wittenburgerweg",
    "iso:country":"NL",
    "sg:address":"Wittenburgerweg 28",
    "sg:city":"Wassenaar",
    "sg:orig_category":"Binnenhuisarchitecten",
    "sg:phone":"+31 70 511 2294",
    "sg:postcode":"2244 CB",
    "sg:province":"South Holland",
    "wof:name":"Philomene Chapot Interieurs",
    "wof:placetype":"venue"
},
  "geometry": {"coordinates":[4.354249,52.11087],"type":"Point"}
}