{
  "type": "Feature",
  "properties": {
    "iso:country":"NL",
    "sg:address":"Tichelwerk 6",
    "sg:city":"Delfzyl",
    "sg:classifiers":[
        {
            "category":"Personal",
            "subcategory":"Nail Salon",
            "type":"Services"
        }
    ],
    "sg:phone":"+31 596 615 983",
    "sg:postcode":"9934 LB",
    "sg:province":"Groningen",
    "sg:tags":[
        "pedicure"
    ],
    "wof:name":"Supriatna, Helga",
    "wof:placetype":"venue"
},
  "geometry": {"coordinates":[6.906708,53.328651],"type":"Point"}
}