{
  "type": "Feature",
  "properties": {
    "addr:full":"Bedryvenpk Twente 301A Almelo Overijssel 7602 KL",
    "addr:housenumber":"301a",
    "addr:postcode":"7602 kl",
    "addr:street":"Twente",
    "iso:country":"NL",
    "sg:address":"Bedryvenpk Twente 301A",
    "sg:city":"Almelo",
    "sg:orig_category":"Verpakkingen En Verpakkingsmaterialen",
    "sg:phone":"+31 546 579 648",
    "sg:postcode":"7602 KL",
    "sg:province":"Overijssel",
    "wof:name":"A-1 Packaging Bv",
    "wof:placetype":"venue"
},
  "geometry": {"coordinates":[6.610497,52.368282],"type":"Point"}
}