{
  "type": "Feature",
  "properties": {
    "addr:full":"Huizersdk 4 Zevenbergen North Brabant 4761 PV",
    "addr:housenumber":"4",
    "addr:postcode":"4761 pv",
    "addr:street":"Huizersdk",
    "iso:country":"NL",
    "sg:address":"Huizersdk 4",
    "sg:city":"Zevenbergen",
    "sg:orig_category":"Autoruiten",
    "sg:phone":"+31 168 323 479",
    "sg:postcode":"4761 PV",
    "sg:province":"North Brabant",
    "wof:name":"Wsz",
    "wof:placetype":"venue"
},
  "geometry": {"coordinates":[4.597569,51.642185],"type":"Point"}
}