{
  "type": "Feature",
  "properties": {
    "addr:full":"Het Rond 132 Houten Utrecht 3995 DP",
    "addr:housenumber":"132",
    "addr:postcode":"3995 dp",
    "addr:street":"Het Rond",
    "iso:country":"NL",
    "sg:address":"Het Rond 132",
    "sg:city":"Houten",
    "sg:orig_category":"Werving And Selectie Van Tijdelijk Personeel And Uitzendkantoren",
    "sg:phone":"+31 30 637 4823",
    "sg:postcode":"3995 DP",
    "sg:province":"Utrecht",
    "wof:name":"Dactylo",
    "wof:placetype":"venue"
},
  "geometry": {"coordinates":[5.1692528725,52.0348548889],"type":"Point"}
}