{
  "type": "Feature",
  "properties": {
    "addr:full":"Bruggelaantje 2 Mildam Friesland 8454 KH",
    "addr:housenumber":"2",
    "addr:postcode":"8454 kh",
    "addr:street":"Bruggelaantje",
    "iso:country":"NL",
    "sg:address":"Bruggelaantje 2",
    "sg:city":"Mildam",
    "sg:orig_category":"Goederenvervoer Over De Weg",
    "sg:phone":"+31 513 636 133",
    "sg:postcode":"8454 KH",
    "sg:province":"Friesland",
    "wof:name":"Firma S Wiebenga En Zonen",
    "wof:placetype":"venue"
},
  "geometry": {"coordinates":[6.000613,52.93399],"type":"Point"}
}