{
  "type": "Feature",
  "properties": {
    "addr:full":"Vd Aastr 88 S Gravenhage South Holland 2597 SN",
    "addr:housenumber":"88",
    "addr:postcode":"2597 sn",
    "addr:street":"S Gravenhage",
    "iso:country":"NL",
    "sg:address":"Vd Aastr 88",
    "sg:city":"S Gravenhage",
    "sg:orig_category":"Organisatiebureaus",
    "sg:phone":"+31 70 324 0998",
    "sg:postcode":"2597 SN",
    "sg:province":"South Holland",
    "wof:name":"Connells Consulting",
    "wof:placetype":"venue"
},
  "geometry": {"coordinates":[4.3181700706,52.1103096008],"type":"Point"}
}