{
  "type": "Feature",
  "properties": {
    "addr:full":"Rykswg Z 8 Sittard Limburg 6131 AN",
    "addr:housenumber":"8",
    "addr:postcode":"6131 an",
    "addr:street":"Sittard Limburg",
    "iso:country":"NL",
    "sg:address":"Rykswg Z 8",
    "sg:city":"Sittard",
    "sg:orig_category":"Video - Faciliteiten En Producties",
    "sg:phone":"+31 46 458 4537",
    "sg:postcode":"6131 AN",
    "sg:province":"Limburg",
    "wof:name":"Editor, The",
    "wof:placetype":"venue"
},
  "geometry": {"coordinates":[5.862448,50.998039],"type":"Point"}
}