{
  "type": "Feature",
  "properties": {
    "addr:full":"Keetzijde 9 Edam North Holland 1135 VX",
    "addr:housenumber":"9",
    "addr:postcode":"1135 vx",
    "addr:street":"Keetzijde",
    "iso:country":"NL",
    "sg:address":"Keetzijde 9",
    "sg:city":"Edam",
    "sg:orig_category":"Meubelreparatie And -Restauratie",
    "sg:phone":"+31 299 350 807",
    "sg:postcode":"1135 VX",
    "sg:province":"North Holland",
    "wof:name":"Ewoud Hooijberg",
    "wof:placetype":"venue"
},
  "geometry": {"coordinates":[5.053218,52.511219],"type":"Point"}
}