{
  "type": "Feature",
  "properties": {
    "iso:country":"NL",
    "sg:address":"Singel 63",
    "sg:city":"Sneek",
    "sg:orig_category":"Bloemen And Planten",
    "sg:phone":"+31 515 422 524",
    "sg:postcode":"8601 AH",
    "sg:province":"Friesland",
    "wof:name":"Bloemen Ruis",
    "wof:placetype":"venue"
},
  "geometry": {"coordinates":[5.66252,53.031471],"type":"Point"}
}