{
  "type": "Feature",
  "properties": {
    "iso:country":"NL",
    "sg:address":"Durgerdamstr 23",
    "sg:city":"Zaandam",
    "sg:orig_category":"Onderhoudswerken",
    "sg:phone":"+31 75 670 2992",
    "sg:postcode":"1507 JL",
    "sg:province":"North Holland",
    "wof:name":"Jager Bv, De",
    "wof:placetype":"venue"
},
  "geometry": {"coordinates":[4.805435,52.445259],"type":"Point"}
}