{
  "type": "Feature",
  "properties": {
    "addr:full":"Platinastraat 21 Zoetermeer Zuid-Holland 2718 SZ",
    "addr:housenumber":"21",
    "addr:postcode":"2718 sz",
    "addr:street":"Platinastraat",
    "iso:country":"NL",
    "sg:address":"Platinastraat 21",
    "sg:city":"Zoetermeer",
    "sg:orig_category":"Drukkerijen And Copyshops",
    "sg:phone":"+31 79 362 0400",
    "sg:postcode":"2718 SZ",
    "sg:province":"Zuid-Holland",
    "wof:name":"Multicopy",
    "wof:placetype":"venue"
},
  "geometry": {"coordinates":[4.505201,52.038113],"type":"Point"}
}