{
  "type": "Feature",
  "properties": {
    "iso:country":"NL",
    "sg:address":"Amperestraat 4",
    "sg:city":"Nunspeet",
    "sg:orig_category":"Muziekinstrumenten Fab",
    "sg:phone":"+31 341 252 484",
    "sg:postcode":"8071 PH",
    "sg:province":"Gelderland",
    "wof:name":"Hendriksen En Reitsma",
    "wof:placetype":"venue"
},
  "geometry": {"coordinates":[5.766027,52.367607],"type":"Point"}
}