{
  "type": "Feature",
  "properties": {
    "addr:full":"Purmersteenweg 42 Purmerend Noord-Holland 1441 DM",
    "addr:housenumber":"42",
    "addr:postcode":"1441 dm",
    "addr:street":"Purmersteenweg",
    "iso:country":"NL",
    "sg:address":"Purmersteenweg 42",
    "sg:city":"Purmerend",
    "sg:orig_category":"Overheidsdiensten",
    "sg:phone":"+31 299 452 911",
    "sg:postcode":"1441 DM",
    "sg:province":"Noord-Holland",
    "wof:name":"Gemeente Purmerend",
    "wof:placetype":"venue"
},
  "geometry": {"coordinates":[4.9547419548,52.5068244934],"type":"Point"}
}