{
  "type": "Feature",
  "properties": {
    "addr:full":"Zoom 17-15 Lelystad Flevoland 8225 KL",
    "addr:postcode":"17-15;8225 kl",
    "addr:street":"Zoom;Flevoland",
    "iso:country":"NL",
    "sg:address":"Zoom 17-15",
    "sg:city":"Lelystad",
    "sg:orig_category":"Nagelstudio'S",
    "sg:phone":"+31 320 248 681",
    "sg:postcode":"8225 KL",
    "sg:province":"Flevoland",
    "wof:name":"Magic Nails",
    "wof:placetype":"venue"
},
  "geometry": {"coordinates":[5.50959,52.503201],"type":"Point"}
}