{
  "type": "Feature",
  "properties": {
    "addr:full":"Hofmeestery 40 Huissen Gelderland 6852 ND",
    "addr:housenumber":"40",
    "addr:postcode":"6852 nd",
    "addr:street":"Hofmeestery;Gelderland",
    "iso:country":"NL",
    "sg:address":"Hofmeestery 40",
    "sg:city":"Huissen",
    "sg:orig_category":"Schilders",
    "sg:phone":"+31 26 325 4316",
    "sg:postcode":"6852 ND",
    "sg:province":"Gelderland",
    "wof:name":"Dibbets, J",
    "wof:placetype":"venue"
},
  "geometry": {"coordinates":[5.928121,51.936535],"type":"Point"}
}