{
  "type": "Feature",
  "properties": {
    "iso:country":"NL",
    "sg:address":"Prins Bernhardlaan 8",
    "sg:city":"Vlagtwedde",
    "sg:orig_category":"Schoonheidssalons",
    "sg:phone":"+31 599 312 926",
    "sg:postcode":"9541 BT",
    "sg:province":"Groningen",
    "wof:name":"A.W.H. Drenth-Bodde",
    "wof:placetype":"venue"
},
  "geometry": {"coordinates":[7.114521,53.027412],"type":"Point"}
}