{
  "type": "Feature",
  "properties": {
    "addr:full":"Past Kampstr 8 De Moer Noord-Brabant 5176 NP",
    "addr:housenumber":"8",
    "addr:postcode":"5176 np",
    "addr:street":"Past Kampstr",
    "iso:country":"NL",
    "sg:address":"Past Kampstr 8",
    "sg:city":"De Moer",
    "sg:orig_category":"Machinehandel",
    "sg:phone":"+31 13 515 6000",
    "sg:postcode":"5176 NP",
    "sg:province":"Noord-Brabant",
    "wof:name":"Belvor Bv",
    "wof:placetype":"venue"
},
  "geometry": {"coordinates":[5.013672,51.622566],"type":"Point"}
}