{
  "type": "Feature",
  "properties": {
    "addr:full":"Hoogstr 104 Vlaardingen Zuid-Holland 3131 BP",
    "addr:housenumber":"104",
    "addr:postcode":"3131 bp",
    "iso:country":"NL",
    "sg:address":"Hoogstr 104",
    "sg:city":"Vlaardingen",
    "sg:orig_category":"Wereldwinkels",
    "sg:phone":"+31 10 234 0773",
    "sg:postcode":"3131 BP",
    "sg:province":"Zuid-Holland",
    "wof:name":"Wereldwinkel",
    "wof:placetype":"venue"
},
  "geometry": {"coordinates":[4.3435811996,51.9111442566],"type":"Point"}
}