{
  "type": "Feature",
  "properties": {
    "addr:full":"Kanaaldijk Noord 109 Eindhoven Noord-Brabant 5642 JA",
    "addr:housenumber":"109",
    "addr:postcode":"5642 ja",
    "addr:street":"Kanaaldijk Noord",
    "iso:country":"NL",
    "sg:address":"Kanaaldijk Noord 109",
    "sg:city":"Eindhoven",
    "sg:orig_category":"Beursorganisaties And Standbouw",
    "sg:phone":"+31 40 281 8084",
    "sg:postcode":"5642 JA",
    "sg:province":"Noord-Brabant",
    "wof:name":"Oxijz Bv",
    "wof:placetype":"venue"
},
  "geometry": {"coordinates":[5.509041,51.434662],"type":"Point"}
}