{
  "type": "Feature",
  "properties": {
    "addr:full":"Postbus 546 Groningen Groningen 9700 AM",
    "addr:housenumber":"546",
    "addr:postcode":"9700",
    "addr:street":"Postbus",
    "iso:country":"NL",
    "sg:address":"Postbus 546",
    "sg:city":"Groningen",
    "sg:orig_category":"Woningbouw- Verenigingen En -Stichtingen",
    "sg:phone":"+31 50 365 7100",
    "sg:postcode":"9700 AM",
    "sg:province":"Groningen",
    "wof:name":"Shbs-G",
    "wof:placetype":"venue"
},
  "geometry": {"coordinates":[6.5650200844,53.2164497375],"type":"Point"}
}