{
  "type": "Feature",
  "properties": {
    "addr:full":"Oosterwyzend 1 Hoogkarspel Noord-Holland 1616 LE",
    "addr:housenumber":"1",
    "addr:postcode":"1616 le",
    "addr:street":"Oosterwyzend",
    "iso:country":"NL",
    "sg:address":"Oosterwyzend 1",
    "sg:city":"Hoogkarspel",
    "sg:orig_category":"Houtgroothandel",
    "sg:phone":"+31 228 563 968",
    "sg:postcode":"1616 LE",
    "sg:province":"Noord-Holland",
    "sg:website":"http://www.jpbakker.nl",
    "wof:name":"Bakker De Houthandel Vof",
    "wof:placetype":"venue"
},
  "geometry": {"coordinates":[5.186018,52.69075],"type":"Point"}
}