{
  "type": "Feature",
  "properties": {
    "addr:full":"Bedryvenwg 22D Leiderdorp Zuid-Holland 2351 BC",
    "addr:housenumber":"22d",
    "addr:postcode":"2351 bc",
    "addr:street":"Bedryvenwg",
    "iso:country":"NL",
    "sg:address":"Bedryvenwg 22D",
    "sg:city":"Leiderdorp",
    "sg:orig_category":"Schoenen - Groothandel",
    "sg:phone":"+31 71 589 0011",
    "sg:postcode":"2351 BC",
    "sg:province":"Zuid-Holland",
    "wof:name":"Dennis",
    "wof:placetype":"venue"
},
  "geometry": {"coordinates":[4.546467,52.141518],"type":"Point"}
}