{
  "type": "Feature",
  "properties": {
    "addr:full":"Koppelstr 19 Roggel Limburg 6088 EM",
    "addr:housenumber":"19",
    "addr:postcode":"6088 em",
    "addr:street":"Koppelstr",
    "iso:country":"NL",
    "sg:address":"Koppelstr 19",
    "sg:city":"Roggel",
    "sg:orig_category":"Kinderkleding",
    "sg:phone":"+31 475 491 395",
    "sg:postcode":"6088 EM",
    "sg:province":"Limburg",
    "wof:name":"Sivero",
    "wof:placetype":"venue"
},
  "geometry": {"coordinates":[5.924201,51.264725],"type":"Point"}
}