{
  "type": "Feature",
  "properties": {
    "addr:full":"Rooseveltlaan 238Hs Amsterdam Noord-Holland 1078 NX",
    "addr:housenumber":"238hs",
    "addr:postcode":"1078 nx",
    "addr:street":"Rooseveltlaan",
    "iso:country":"NL",
    "sg:address":"Rooseveltlaan 238Hs",
    "sg:city":"Amsterdam",
    "sg:orig_category":"Werving And Selectie Van Vast Personeel",
    "sg:phone":"+31 20 670 6275",
    "sg:postcode":"1078 NX",
    "sg:province":"Noord-Holland",
    "wof:name":"Anjo Communicatie Support",
    "wof:placetype":"venue"
},
  "geometry": {"coordinates":[4.8946809769,52.3426933289],"type":"Point"}
}