{
  "type": "Feature",
  "properties": {
    "iso:country":"NL",
    "sg:address":"Arnesteinwg 61",
    "sg:city":"Middelburg",
    "sg:orig_category":"Gasapparaten En -Artikelen - Reparatie En Onderhoud",
    "sg:phone":"+31 118 635 256",
    "sg:postcode":"4338 PD",
    "sg:province":"Zeeland",
    "sg:website":"http://www.inhome.nl",
    "wof:name":"Delta Gasservice Inhome",
    "wof:placetype":"venue"
},
  "geometry": {"coordinates":[3.645464,51.498695],"type":"Point"}
}