{
  "type": "Feature",
  "properties": {
    "iso:country":"NL",
    "sg:address":"Amperestr 41",
    "sg:city":"Purmerend",
    "sg:orig_category":"Beveiliging",
    "sg:phone":"+31 299 419 005",
    "sg:postcode":"1446 TR",
    "sg:province":"North Holland",
    "wof:name":"Pro-Service Bv",
    "wof:placetype":"venue"
},
  "geometry": {"coordinates":[4.996685,52.516914],"type":"Point"}
}