{
  "type": "Feature",
  "properties": {
    "addr:full":"Baanstraat 11 Hoorn Nh Noord-Holland 1621 HS",
    "addr:housenumber":"11",
    "addr:postcode":"1621 hs",
    "addr:street":"Baanstraat",
    "iso:country":"NL",
    "sg:address":"Baanstraat 11",
    "sg:city":"Hoorn Nh",
    "sg:orig_category":"Boekhandels",
    "sg:phone":"+31 229 239 921",
    "sg:postcode":"1621 HS",
    "sg:province":"Noord-Holland",
    "wof:name":"Evangelische Bookshop De Oase",
    "wof:placetype":"venue"
},
  "geometry": {"coordinates":[5.055196,52.643681],"type":"Point"}
}