{
  "type": "Feature",
  "properties": {
    "addr:full":"Gebroken Meeldijk 88 Barendrecht Zuid-Holland 2991 CH",
    "addr:housenumber":"88",
    "addr:postcode":"2991",
    "addr:street":"Gebroken Meeldijk",
    "iso:country":"NL",
    "sg:address":"Gebroken Meeldijk 88",
    "sg:city":"Barendrecht",
    "sg:classifiers":[
        {
            "category":"Shopping",
            "subcategory":"Gifts & Souvenirs",
            "type":"Retail Goods"
        }
    ],
    "sg:phone":"+31 180 618 952",
    "sg:postcode":"2991 CH",
    "sg:province":"Zuid-Holland",
    "sg:tags":[
        "geschenken"
    ],
    "wof:name":"M. Peters",
    "wof:placetype":"venue"
},
  "geometry": {"coordinates":[4.552198,51.85273],"type":"Point"}
}