{
  "type": "Feature",
  "properties": {
    "iso:country":"NL",
    "sg:address":"Margrietlaan 80",
    "sg:city":"Weert",
    "sg:classifiers":[
        {
            "category":"Education",
            "subcategory":"Preschool",
            "type":"Public Place"
        }
    ],
    "sg:phone":"+31 495 536 622",
    "sg:postcode":"6006 ZZ",
    "sg:province":"Limburg",
    "sg:tags":[
        "kleuteronderwijs",
        "basis-"
    ],
    "wof:name":"Basisschool Nassauhof",
    "wof:placetype":"venue"
},
  "geometry": {"coordinates":[5.713163,51.240852],"type":"Point"}
}