{
  "type": "Feature",
  "properties": {
    "addr:full":"Planciusplein 35 Breda Noord-Brabant 4812 SE",
    "addr:housenumber":"35",
    "addr:postcode":"4812 se",
    "addr:street":"Planciusplein",
    "iso:country":"NL",
    "sg:address":"Planciusplein 35",
    "sg:city":"Breda",
    "sg:classifiers":[
        {
            "category":"Communications",
            "subcategory":"Television Station",
            "type":"Services"
        }
    ],
    "sg:phone":"+31 76 514 1953",
    "sg:postcode":"4812 SE",
    "sg:province":"Noord-Brabant",
    "sg:tags":[
        "video",
        "audio",
        "verhuur"
    ],
    "wof:name":"Videogigant Jumbo",
    "wof:placetype":"venue"
},
  "geometry": {"coordinates":[4.756024,51.5751],"type":"Point"}
}