{
  "type": "Feature",
  "properties": {
    "addr:full":"Nieuwe Gouw 42 Landsmeer Noord-Holland 1121 GX",
    "addr:housenumber":"42",
    "addr:postcode":"1121 gx",
    "addr:street":"Nieuwe Gouw",
    "iso:country":"NL",
    "sg:address":"Nieuwe Gouw 42",
    "sg:city":"Landsmeer",
    "sg:classifiers":[
        {
            "category":"Shopping",
            "subcategory":"Gifts & Souvenirs",
            "type":"Retail Goods"
        }
    ],
    "sg:phone":"+31 20 482 1216",
    "sg:postcode":"1121 GX",
    "sg:province":"Noord-Holland",
    "sg:tags":[
        "geschenken"
    ],
    "wof:name":"Kadoshop Kaleidoscoop",
    "wof:placetype":"venue"
},
  "geometry": {"coordinates":[4.91381,52.428463],"type":"Point"}
}