{
  "type": "Feature",
  "properties": {
    "addr:full":"Grootveldscheln 4 Malden Gelderland 6581 GT",
    "addr:housenumber":"4",
    "addr:postcode":"6581 gt",
    "addr:street":"Grootveldscheln;Gelderland",
    "iso:country":"NL",
    "sg:address":"Grootveldscheln 4",
    "sg:city":"Malden",
    "sg:orig_category":"Accountants - Administratie- Consulenten En -Kantoren",
    "sg:phone":"+31 24 358 0632",
    "sg:postcode":"6581 GT",
    "sg:province":"Gelderland",
    "wof:name":"Bisseling, G H",
    "wof:placetype":"venue"
},
  "geometry": {"coordinates":[5.845772,51.789333],"type":"Point"}
}