{
  "type": "Feature",
  "properties": {
    "addr:full":"Bjirkewei 99 Twyzelerheide Provincie Friesland 9287 LC",
    "addr:housenumber":"99",
    "addr:postcode":"9287 lc",
    "addr:street":"Bjirkewei;Provincie Friesland",
    "iso:country":"NL",
    "sg:address":"Bjirkewei 99",
    "sg:city":"Twyzelerheide",
    "sg:orig_category":"Fietsen En Bromfietsen",
    "sg:phone":"+31 511 441 238",
    "sg:postcode":"9287 LC",
    "sg:province":"Provincie Friesland",
    "wof:name":"Kempenaar, A P",
    "wof:placetype":"venue"
},
  "geometry": {"coordinates":[6.044787,53.242119],"type":"Point"}
}