{
  "type": "Feature",
  "properties": {
    "addr:full":"Oude Markt 3 Vlissingen Zeeland 4381 ER",
    "addr:housenumber":"3",
    "addr:postcode":"4381 er",
    "addr:street":"Oude Markt",
    "iso:country":"NL",
    "sg:address":"Oude Markt 3",
    "sg:city":"Vlissingen",
    "sg:orig_category":"Verenigingen En Stichtingen",
    "sg:phone":"+31 118 422 190",
    "sg:postcode":"4381 ER",
    "sg:province":"Zeeland",
    "wof:name":"Vlissingen Promotie, Sticht",
    "wof:placetype":"venue"
},
  "geometry": {"coordinates":[3.573634,51.442677],"type":"Point"}
}