{
  "type": "Feature",
  "properties": {
    "addr:full":"Vrijthof 3 Wittem Limburg 6286 DB",
    "addr:housenumber":"3",
    "addr:postcode":"6286 db",
    "addr:street":"Vrijthof",
    "iso:country":"NL",
    "sg:address":"Vrijthof 3",
    "sg:city":"Wittem",
    "sg:orig_category":"Verzekeringen",
    "sg:phone":"+31 43 451 1762",
    "sg:postcode":"6286 DB",
    "sg:province":"Limburg",
    "wof:name":"Algemeen Assurantiekantoor Limburg",
    "wof:placetype":"venue"
},
  "geometry": {"coordinates":[5.936336,50.810379],"type":"Point"}
}