{
  "type": "Feature",
  "properties": {
    "addr:full":"Hykerveld 88 Rotterdam Zuid-Holland 3085 PC",
    "addr:housenumber":"88",
    "addr:postcode":"3085 pc",
    "addr:street":"Hykerveld",
    "iso:country":"NL",
    "sg:address":"Hykerveld 88",
    "sg:city":"Rotterdam",
    "sg:classifiers":[
        {
            "category":"Personal",
            "subcategory":"Nail Salon",
            "type":"Services"
        }
    ],
    "sg:phone":"+31 10 480 5995",
    "sg:postcode":"3085 PC",
    "sg:province":"Zuid-Holland",
    "sg:tags":[
        "pedicure"
    ],
    "wof:name":"Zuidam",
    "wof:placetype":"venue"
},
  "geometry": {"coordinates":[4.481639,51.87096],"type":"Point"}
}