{
  "type": "Feature",
  "properties": {
    "iso:country":"NL",
    "sg:address":"Eikelhofwg 18A",
    "sg:city":"Olst",
    "sg:orig_category":"Oldtimers",
    "sg:phone":"+31 570 591 981",
    "sg:postcode":"8121 RC",
    "sg:province":"NL.08",
    "sg:website":"http://www.van-emst.nl",
    "wof:name":"Emst, Van",
    "wof:placetype":"venue"
},
  "geometry": {"coordinates":[6.157632,52.318508],"type":"Point"}
}