{
  "type": "Feature",
  "properties": {
    "addr:full":"Mallemoolen 23 Zevenaar Gelderland 6901 GS",
    "addr:housenumber":"23",
    "addr:postcode":"6901 gs",
    "addr:street":"Mallemoolen",
    "iso:country":"NL",
    "sg:address":"Mallemoolen 23",
    "sg:city":"Zevenaar",
    "sg:orig_category":"Architecten",
    "sg:phone":"+31 316 523 710",
    "sg:postcode":"6901 GS",
    "sg:province":"Gelderland",
    "wof:name":"De Bruin Architecten En Ingenieurs",
    "wof:placetype":"venue"
},
  "geometry": {"coordinates":[6.07573,51.929363],"type":"Point"}
}