{
  "type": "Feature",
  "properties": {
    "iso:country":"NL",
    "sg:address":"Reitschewg 7A",
    "sg:city":"S Hertogenbosch",
    "sg:orig_category":"Adviesbureaus Bedrijfsorganisatie",
    "sg:phone":"+31 73 648 4800",
    "sg:postcode":"5232 BX",
    "sg:province":"Noord-Brabant",
    "wof:name":"Koers Bv",
    "wof:placetype":"venue"
},
  "geometry": {"coordinates":[5.33996,51.709061],"type":"Point"}
}