{
  "type": "Feature",
  "properties": {
    "iso:country":"NL",
    "sg:address":"Nieuwstraat 13",
    "sg:city":"Gilze",
    "sg:classifiers":[
        {
            "category":"Professional",
            "subcategory":"Accounting & Tax Preparation",
            "type":"Services"
        }
    ],
    "sg:phone":"+31 161 455 272",
    "sg:postcode":"5126 CB",
    "sg:province":"North Brabant",
    "sg:tags":[
        "accountant"
    ],
    "wof:name":"Accountantskantoor Wouters Bv",
    "wof:placetype":"venue"
},
  "geometry": {"coordinates":[4.941007,51.543312],"type":"Point"}
}