{
  "type": "Feature",
  "properties": {
    "addr:full":"E Vereln 36 Oosterhout Nb Noord-Brabant 4906 JA",
    "addr:housenumber":"36",
    "addr:postcode":"4906 ja",
    "addr:street":"E",
    "iso:country":"NL",
    "sg:address":"E Vereln 36",
    "sg:city":"Oosterhout Nb",
    "sg:orig_category":"Administratie- En Boekhoudkantoren",
    "sg:phone":"+31 162 435 429",
    "sg:postcode":"4906 JA",
    "sg:province":"Noord-Brabant",
    "wof:name":"Mercurius",
    "wof:placetype":"venue"
},
  "geometry": {"coordinates":[4.8394098282,51.6514892578],"type":"Point"}
}