{
  "type": "Feature",
  "properties": {
    "iso:country":"NL",
    "sg:address":"Westerveerstraat 55",
    "sg:city":"Heerhugowaard",
    "sg:orig_category":"Kunststofverpakkingen Fab",
    "sg:phone":"+31 72 572 0551",
    "sg:postcode":"1705 AT",
    "sg:province":"North Holland",
    "wof:name":"Artipack Nederland",
    "wof:placetype":"venue"
},
  "geometry": {"coordinates":[4.83923,52.64983],"type":"Point"}
}