{
  "type": "Feature",
  "properties": {
    "addr:full":"Westwagenstraat 52 Gorinchem Zuid-Holland 4201 HJ",
    "addr:housenumber":"52",
    "addr:postcode":"4201 hj",
    "addr:street":"Westwagenstraat",
    "iso:country":"NL",
    "sg:address":"Westwagenstraat 52",
    "sg:city":"Gorinchem",
    "sg:orig_category":"Verlichting And Huishoudartikelen",
    "sg:phone":"+31 183 634 860",
    "sg:postcode":"4201 HJ",
    "sg:province":"Zuid-Holland",
    "wof:name":"Riloe Vof",
    "wof:placetype":"venue"
},
  "geometry": {"coordinates":[4.970754,51.830688],"type":"Point"}
}