{
  "type": "Feature",
  "properties": {
    "addr:full":"Postbus 333 Doetinchem Gelderland 7000 AH",
    "addr:housenumber":"333",
    "addr:postcode":"7000 ah",
    "addr:street":"Postbus;Gelderland",
    "iso:country":"NL",
    "sg:address":"Postbus 333",
    "sg:city":"Doetinchem",
    "sg:orig_category":"Omroep",
    "sg:phone":"+31 26 371 3411",
    "sg:postcode":"7000 AH",
    "sg:province":"Gelderland",
    "wof:name":"Gelderland",
    "wof:placetype":"venue"
},
  "geometry": {"coordinates":[6.291055,51.963596],"type":"Point"}
}