{
  "type": "Feature",
  "properties": {
    "iso:country":"NL",
    "sg:address":"A V Altenastr 11",
    "sg:city":"Dordrecht",
    "sg:orig_category":"Webdesign Bureaus",
    "sg:phone":"+31 78 631 6039",
    "sg:postcode":"3312 EB",
    "sg:province":"Zuid-Holland",
    "wof:name":"Balen, Van",
    "wof:placetype":"venue"
},
  "geometry": {"coordinates":[4.6565060616,51.8119163513],"type":"Point"}
}