{
  "type": "Feature",
  "properties": {
    "addr:full":"Sporkenhoutln 1 Gouda Zuid-Holland 2803 VJ",
    "addr:housenumber":"1",
    "addr:postcode":"2803 vj",
    "addr:street":"Sporkenhoutln",
    "iso:country":"NL",
    "sg:address":"Sporkenhoutln 1",
    "sg:city":"Gouda",
    "sg:orig_category":"Beeldende Kunstenaars",
    "sg:phone":"+31 182 535 382",
    "sg:postcode":"2803 VJ",
    "sg:province":"Zuid-Holland",
    "wof:name":"Santen, Ria Van",
    "wof:placetype":"venue"
},
  "geometry": {"coordinates":[4.695022,52.024643],"type":"Point"}
}