{
  "type": "Feature",
  "properties": {
    "addr:full":"Zuiderkerkhof 3 Amsterdam North Holland 1011 WB",
    "addr:housenumber":"3",
    "addr:postcode":"1011 wb",
    "addr:street":"Zuiderkerkhof",
    "iso:country":"NL",
    "sg:address":"Zuiderkerkhof 3",
    "sg:city":"Amsterdam",
    "sg:orig_category":"Werving And Selectie Van Vast Personeel",
    "sg:phone":"+31 20 427 5573",
    "sg:postcode":"1011 WB",
    "sg:province":"North Holland",
    "wof:name":"Russian Delegation Serv",
    "wof:placetype":"venue"
},
  "geometry": {"coordinates":[4.9003782272,52.3699913025],"type":"Point"}
}