{
  "type": "Feature",
  "properties": {
    "addr:full":"Adelaarswg 11 Amsterdam Noord-Holland 1021 BM",
    "addr:housenumber":"11",
    "addr:postcode":"1021 bm",
    "addr:street":"Adelaarswg",
    "iso:country":"NL",
    "sg:address":"Adelaarswg 11",
    "sg:city":"Amsterdam",
    "sg:orig_category":"Onderzoekbureaus",
    "sg:phone":"+31 20 637 3623",
    "sg:postcode":"1021 BM",
    "sg:province":"Noord-Holland",
    "wof:name":"Dijk12",
    "wof:placetype":"venue"
},
  "geometry": {"coordinates":[4.911769,52.384144],"type":"Point"}
}