{
  "type": "Feature",
  "properties": {
    "addr:full":"Lopikerwg O 159A Lopikerkapel Utrecht 3412 KD",
    "addr:housenumber":"159a",
    "addr:postcode":"3412 kd",
    "addr:street":"Lopikerkapel",
    "iso:country":"NL",
    "sg:address":"Lopikerwg O 159A",
    "sg:city":"Lopikerkapel",
    "sg:classifiers":[
        {
            "category":"Retail",
            "subcategory":"Auto Repair",
            "type":"Services"
        }
    ],
    "sg:phone":"+31 30 688 2056",
    "sg:postcode":"3412 KD",
    "sg:province":"Utrecht",
    "sg:tags":[
        "garage"
    ],
    "wof:name":"Wolters Vof",
    "wof:placetype":"venue"
},
  "geometry": {"coordinates":[5.042666,51.990261],"type":"Point"}
}