{
  "type": "Feature",
  "properties": {
    "addr:full":"Herensingel 196 Weesp Noord-Holland 1382 VV",
    "addr:housenumber":"196",
    "addr:postcode":"1382 vv",
    "addr:street":"Herensingel",
    "iso:country":"NL",
    "sg:address":"Herensingel 196",
    "sg:city":"Weesp",
    "sg:orig_category":"Onderhoud And Reparatie Kantoorapparatuur",
    "sg:phone":"+31 294 411 854",
    "sg:postcode":"1382 VV",
    "sg:province":"Noord-Holland",
    "wof:name":"F.W. Van Deursen",
    "wof:placetype":"venue"
},
  "geometry": {"coordinates":[5.03948,52.310539],"type":"Point"}
}