{
  "type": "Feature",
  "properties": {
    "addr:full":"A Cuypstr 225 Amsterdam North Holland 1073 BG",
    "addr:housenumber":"225",
    "addr:postcode":"1073",
    "iso:country":"NL",
    "sg:address":"A Cuypstr 225",
    "sg:city":"Amsterdam",
    "sg:orig_category":"Kappersbenodigdheden",
    "sg:phone":"+31 20 676 9864",
    "sg:postcode":"1073 BG",
    "sg:province":"North Holland",
    "wof:name":"Suhail Cosmetics Bv",
    "wof:placetype":"venue"
},
  "geometry": {"coordinates":[4.896333,52.356373],"type":"Point"}
}