{
  "type": "Feature",
  "properties": {
    "addr:full":"Strypsestr 196A Eindhoven Noord-Brabant 5616 GW",
    "addr:housenumber":"196a",
    "addr:postcode":"5616 gw",
    "iso:country":"NL",
    "sg:address":"Strypsestr 196A",
    "sg:city":"Eindhoven",
    "sg:orig_category":"Kaas",
    "sg:phone":"+31 40 255 1160",
    "sg:postcode":"5616 GW",
    "sg:province":"Noord-Brabant",
    "wof:name":"Kaasboerderijtje, 'T",
    "wof:placetype":"venue"
},
  "geometry": {"coordinates":[5.4536471367,51.4412384033],"type":"Point"}
}