{
  "type": "Feature",
  "properties": {
    "iso:country":"NL",
    "sg:address":"Peperstr 162",
    "sg:city":"Zaandam",
    "sg:orig_category":"Adviesbureaus Installatietechniek",
    "sg:phone":"+31 75 670 5794",
    "sg:postcode":"1502 AL",
    "sg:province":"Noord-Holland",
    "sg:website":"http://www.ab2w.nl",
    "wof:name":"A&B2W Bv",
    "wof:placetype":"venue"
},
  "geometry": {"coordinates":[4.828987,52.441643],"type":"Point"}
}