{
  "type": "Feature",
  "properties": {
    "iso:country":"NL",
    "sg:address":"Aylvaweg 29",
    "sg:city":"Witmarsum",
    "sg:orig_category":"Bejaarden - Verzorgingstehuizen",
    "sg:phone":"+31 517 531 456",
    "sg:postcode":"8748 CC",
    "sg:province":"Friesland",
    "wof:name":"Aylva-State",
    "wof:placetype":"venue"
},
  "geometry": {"coordinates":[5.464761,53.101315],"type":"Point"}
}