{
  "type": "Feature",
  "properties": {
    "addr:full":"De La Reyweg 229 'S Gravenhage Zuid-Holland 2571 EE",
    "addr:housenumber":"229 '",
    "addr:postcode":"2571 ee",
    "addr:street":"De La Reyweg",
    "iso:country":"NL",
    "sg:address":"De La Reyweg 229",
    "sg:city":"'S Gravenhage",
    "sg:orig_category":"Kappers",
    "sg:phone":"+31 70 392 4507",
    "sg:postcode":"2571 EE",
    "sg:province":"Zuid-Holland",
    "wof:name":"M.C. Haarmode",
    "wof:placetype":"venue"
},
  "geometry": {"coordinates":[4.286127,52.06741],"type":"Point"}
}