{
  "type": "Feature",
  "properties": {
    "addr:full":"Veldhovenring 68 Tilburg North Brabant 5041 BD",
    "addr:housenumber":"68",
    "addr:postcode":"5041 bd",
    "addr:street":"Veldhovenring",
    "iso:country":"NL",
    "sg:address":"Veldhovenring 68",
    "sg:city":"Tilburg",
    "sg:orig_category":"Fietshandelaren",
    "sg:phone":"+31 13 536 7696",
    "sg:postcode":"5041 BD",
    "sg:province":"North Brabant",
    "wof:name":"Eurobike",
    "wof:placetype":"venue"
},
  "geometry": {"coordinates":[5.085103,51.567642],"type":"Point"}
}