{
  "type": "Feature",
  "properties": {
    "addr:full":"Merenhoef 1 Maarssen Utrecht 3601 AC",
    "addr:housenumber":"1",
    "addr:postcode":"3601 ac",
    "addr:street":"Merenhoef",
    "iso:country":"NL",
    "sg:address":"Merenhoef 1",
    "sg:city":"Maarssen",
    "sg:orig_category":"Bejaarden - Verzorgingstehuizen",
    "sg:phone":"+31 346 587 400",
    "sg:postcode":"3601 AC",
    "sg:province":"Utrecht",
    "wof:name":"Merenhoef",
    "wof:placetype":"venue"
},
  "geometry": {"coordinates":[5.050126,52.141335],"type":"Point"}
}