{
  "type": "Feature",
  "properties": {
    "addr:full":"Laagwaalderweg 39 De Waal Noord-Holland 1793 ED",
    "addr:housenumber":"39",
    "addr:postcode":"waal;1793 ed",
    "addr:street":"Laagwaalderweg",
    "iso:country":"NL",
    "sg:address":"Laagwaalderweg 39",
    "sg:city":"De Waal",
    "sg:orig_category":"Huishoudapparatuur, Televisies And Radio'S",
    "sg:phone":"+31 222 322 344",
    "sg:postcode":"1793 ED",
    "sg:province":"Noord-Holland",
    "wof:name":"Service Center Texel",
    "wof:placetype":"venue"
},
  "geometry": {"coordinates":[4.82576,53.07338],"type":"Point"}
}