{
  "type": "Feature",
  "properties": {
    "addr:full":"Stoepemaheerd 20 Groningen Groningen 9737 TL",
    "addr:housenumber":"20",
    "addr:postcode":"9737 tl",
    "addr:street":"Stoepemaheerd",
    "iso:country":"NL",
    "sg:address":"Stoepemaheerd 20",
    "sg:city":"Groningen",
    "sg:orig_category":"Verlichting And Huishoudartikelen",
    "sg:phone":"+31 50 542 0232",
    "sg:postcode":"9737 TL",
    "sg:province":"Groningen",
    "wof:name":"Shoppingheerd",
    "wof:placetype":"venue"
},
  "geometry": {"coordinates":[6.588862,53.247196],"type":"Point"}
}