{
  "type": "Feature",
  "properties": {
    "addr:full":"Postbus 57 Lisse North Holland 2160 AB",
    "addr:housenumber":"57",
    "addr:postcode":"2160 ab",
    "addr:street":"Postbus",
    "iso:country":"NL",
    "sg:address":"Postbus 57",
    "sg:city":"Lisse",
    "sg:orig_category":"Plafonds",
    "sg:phone":"+31 252 225 208",
    "sg:postcode":"2160 AB",
    "sg:province":"North Holland",
    "wof:name":"Gebros Bv",
    "wof:placetype":"venue"
},
  "geometry": {"coordinates":[4.552546,52.257221],"type":"Point"}
}