{
  "type": "Feature",
  "properties": {
    "iso:country":"NL",
    "sg:address":"Celsiusweg 32",
    "sg:city":"Leeuwarden",
    "sg:classifiers":[
        {
            "category":"Parking",
            "subcategory":"Lot",
            "type":"Transportation"
        }
    ],
    "sg:phone":"+31 58 213 7961",
    "sg:postcode":"8912 AN",
    "sg:province":"Friesland",
    "sg:tags":[
        "fab",
        "metalen",
        "tank"
    ],
    "wof:name":"Mous Leidingwerken",
    "wof:placetype":"venue"
},
  "geometry": {"coordinates":[5.762351,53.196953],"type":"Point"}
}