{
  "type": "Feature",
  "properties": {
    "addr:full":"Drogteropslagen 30 Drogteropslagen NL.08 7705 PG",
    "addr:housenumber":"30;nl.08",
    "addr:postcode":"7705 pg",
    "addr:street":"Drogteropslagen",
    "iso:country":"NL",
    "sg:address":"Drogteropslagen 30",
    "sg:city":"Drogteropslagen",
    "sg:orig_category":"Diverse Grafische Activiteiten",
    "sg:phone":"+31 523 614 562",
    "sg:postcode":"7705 PG",
    "sg:province":"NL.08",
    "wof:name":"Dynamic",
    "wof:placetype":"venue"
},
  "geometry": {"coordinates":[6.497988,52.621925],"type":"Point"}
}