{
  "type": "Feature",
  "properties": {
    "addr:full":"Annastr 2 Delft South Holland 2611 VX",
    "addr:housenumber":"2",
    "addr:postcode":"2611 vx",
    "addr:street":"Annastr",
    "iso:country":"NL",
    "sg:address":"Annastr 2",
    "sg:city":"Delft",
    "sg:orig_category":"Onroerende Goederen",
    "sg:phone":"+31 15 214 5665",
    "sg:postcode":"2611 VX",
    "sg:province":"South Holland",
    "wof:name":"Nieuwkers Bv",
    "wof:placetype":"venue"
},
  "geometry": {"coordinates":[4.354134,52.015839],"type":"Point"}
}