{
  "type": "Feature",
  "properties": {
    "addr:full":"Abrikozengaarde 22 Houten Utrecht 3992 KT",
    "addr:housenumber":"22",
    "addr:postcode":"3992 kt",
    "addr:street":"Abrikozengaarde",
    "iso:country":"NL",
    "sg:address":"Abrikozengaarde 22",
    "sg:city":"Houten",
    "sg:orig_category":"Adviesbureaus Bedrijfsorganisatie",
    "sg:phone":"+31 30 634 1657",
    "sg:postcode":"3992 KT",
    "sg:province":"Utrecht",
    "wof:name":"Loon, Van",
    "wof:placetype":"venue"
},
  "geometry": {"coordinates":[5.151683,52.037731],"type":"Point"}
}