{
  "type": "Feature",
  "properties": {
    "addr:full":"Handelswg 14 Emmen Provincie Drenthe 7826 TC",
    "addr:housenumber":"14",
    "addr:postcode":"7826 tc",
    "addr:street":"Handelswg;Provincie Drenthe",
    "iso:country":"NL",
    "sg:address":"Handelswg 14",
    "sg:city":"Emmen",
    "sg:orig_category":"Bewakingsdiensten",
    "sg:phone":"+31 591 648 183",
    "sg:postcode":"7826 TC",
    "sg:province":"Provincie Drenthe",
    "wof:name":"Inter-Guard",
    "wof:placetype":"venue"
},
  "geometry": {"coordinates":[6.952616,52.776127],"type":"Point"}
}