{
  "type": "Feature",
  "properties": {
    "iso:country":"NL",
    "sg:address":"Langestr 99",
    "sg:city":"Klazienaveen",
    "sg:classifiers":[
        {
            "category":"Shopping",
            "subcategory":"Adult",
            "type":"Retail Goods"
        }
    ],
    "sg:phone":"+31 591 316 111",
    "sg:postcode":"7891 GG",
    "sg:province":"Drenthe",
    "sg:tags":[
        "lingerie",
        "en",
        "tricotage"
    ],
    "wof:name":"Merlin",
    "wof:placetype":"venue"
},
  "geometry": {"coordinates":[6.986942,52.724606],"type":"Point"}
}