{
  "type": "Feature",
  "properties": {
    "iso:country":"NL",
    "sg:address":"De Hofstede 27",
    "sg:city":"Lienden",
    "sg:orig_category":"Meubellakkerijen En -Spuiterijen",
    "sg:phone":"+31 344 600 722",
    "sg:postcode":"4033 BV",
    "sg:province":"Gelderland",
    "wof:name":"Prijs Vof, Ardy",
    "wof:placetype":"venue"
},
  "geometry": {"coordinates":[5.520454,51.940319],"type":"Point"}
}