{
  "type": "Feature",
  "properties": {
    "addr:full":"V Tuyll V Serooskerkenwg 37/3 Amsterdam Noord-Holland 1076 JB",
    "addr:housenumber":"37 / 3",
    "addr:postcode":"1076 jb",
    "addr:street":"V Tuyll V Serooskerkenwg",
    "iso:country":"NL",
    "sg:address":"V Tuyll V Serooskerkenwg 37/3",
    "sg:city":"Amsterdam",
    "sg:orig_category":"Paramedische Behandelingen",
    "sg:phone":"+31 20 679 0273",
    "sg:postcode":"1076 JB",
    "sg:province":"Noord-Holland",
    "wof:name":"N. Van Doesum",
    "wof:placetype":"venue"
},
  "geometry": {"coordinates":[4.85812,52.344231],"type":"Point"}
}