{
  "type": "Feature",
  "properties": {
    "addr:full":"Krabbenhoek 15 Heesch North Brabant 5384 MS",
    "addr:housenumber":"15",
    "addr:postcode":"5384 ms",
    "addr:street":"Krabbenhoek",
    "iso:country":"NL",
    "sg:address":"Krabbenhoek 15",
    "sg:city":"Heesch",
    "sg:orig_category":"Verenigingen En Stichtingen",
    "sg:phone":"+31 412 455 875",
    "sg:postcode":"5384 MS",
    "sg:province":"North Brabant",
    "wof:name":"Bossche Palet, Het",
    "wof:placetype":"venue"
},
  "geometry": {"coordinates":[5.512925,51.734341],"type":"Point"}
}