{
  "type": "Feature",
  "properties": {
    "addr:full":"Middenwaard 96 Heerhugowaard Noord-Holland 1703 SH",
    "addr:housenumber":"96;1703",
    "addr:postcode":"sh",
    "addr:street":"Middenwaard",
    "iso:country":"NL",
    "sg:address":"Middenwaard 96",
    "sg:city":"Heerhugowaard",
    "sg:orig_category":"Wasserettes And Stomerijen",
    "sg:phone":"+31 72 574 2674",
    "sg:postcode":"1703 SH",
    "sg:province":"Noord-Holland",
    "wof:name":"Stomerij Zeekant",
    "wof:placetype":"venue"
},
  "geometry": {"coordinates":[4.8265929222,52.6636695862],"type":"Point"}
}