{
  "type": "Feature",
  "properties": {
    "addr:full":"Rijssensestraat 160 Wierden Overijssel 7642 NN",
    "addr:housenumber":"160",
    "addr:postcode":"7642 nn",
    "addr:street":"Rijssensestraat",
    "iso:country":"NL",
    "sg:address":"Rijssensestraat 160",
    "sg:city":"Wierden",
    "sg:orig_category":"Diverse Consumentenartikelen Gh",
    "sg:phone":"+31 548 545 277",
    "sg:postcode":"7642 NN",
    "sg:province":"Overijssel",
    "wof:name":"Hofman Lieve'S Diergeneesmiddelen Bv",
    "wof:placetype":"venue"
},
  "geometry": {"coordinates":[6.534901,52.319141],"type":"Point"}
}