{
  "type": "Feature",
  "properties": {
    "addr:full":"Gordel V Smaragd 31 Purmerend North Holland 1448 AE",
    "addr:housenumber":"31",
    "addr:postcode":"1448 ae",
    "addr:street":"Smaragd",
    "iso:country":"NL",
    "sg:address":"Gordel V Smaragd 31",
    "sg:city":"Purmerend",
    "sg:classifiers":[
        {
            "category":"Shopping",
            "subcategory":"Gifts & Souvenirs",
            "type":"Retail Goods"
        }
    ],
    "sg:phone":"+31 299 425 701",
    "sg:postcode":"1448 AE",
    "sg:province":"North Holland",
    "sg:tags":[
        "wens-",
        "en",
        "prentbriefkaarten"
    ],
    "wof:name":"Lange, De",
    "wof:placetype":"venue"
},
  "geometry": {"coordinates":[4.9383997917,52.4982681274],"type":"Point"}
}