{
  "type": "Feature",
  "properties": {
    "addr:full":"Kloosterstraat 66 Simpelveld Limburg 6369 AE",
    "addr:housenumber":"66",
    "addr:postcode":"6369 ae",
    "addr:street":"Kloosterstraat",
    "iso:country":"NL",
    "sg:address":"Kloosterstraat 66",
    "sg:city":"Simpelveld",
    "sg:classifiers":[
        {
            "category":"Education",
            "subcategory":"Preschool",
            "type":"Public Place"
        }
    ],
    "sg:phone":"+31 45 544 1932",
    "sg:postcode":"6369 AE",
    "sg:province":"Limburg",
    "sg:tags":[
        "kleuteronderwijs",
        "basis-"
    ],
    "wof:name":"Basisschool De Klimboom",
    "wof:placetype":"venue"
},
  "geometry": {"coordinates":[5.987259,50.834545],"type":"Point"}
}