{
  "type": "Feature",
  "properties": {
    "addr:full":"Bar G A Tindalstr 13 Amsterdam North Holland 1019 TS",
    "addr:housenumber":"13",
    "addr:postcode":"1019 ts",
    "addr:street":"G;Tindalstr",
    "iso:country":"NL",
    "sg:address":"Bar G A Tindalstr 13",
    "sg:city":"Amsterdam",
    "sg:orig_category":"Verzekeringen - Verzekeringskantoren",
    "sg:phone":"+31 20 419 8009",
    "sg:postcode":"1019 TS",
    "sg:province":"North Holland",
    "sg:website":"http://www.sporenburgadviesgroep.nl",
    "wof:name":"Sporenburg Groep",
    "wof:placetype":"venue"
},
  "geometry": {"coordinates":[4.941276,52.372959],"type":"Point"}
}