{
  "type": "Feature",
  "properties": {
    "addr:full":"Heinsbergerwg 180 Roermond Limburg 6045 CK",
    "addr:housenumber":"180",
    "addr:postcode":"6045 ck",
    "iso:country":"NL",
    "sg:address":"Heinsbergerwg 180",
    "sg:city":"Roermond",
    "sg:orig_category":"Verenigingen En Stichtingen",
    "sg:phone":"+31 475 322 324",
    "sg:postcode":"6045 CK",
    "sg:province":"Limburg",
    "wof:name":"Onderwijs Midden Limburg, Sticht",
    "wof:placetype":"venue"
},
  "geometry": {"coordinates":[6.00144,51.171944],"type":"Point"}
}