{
  "type": "Feature",
  "properties": {
    "iso:country":"NL",
    "sg:address":"Karel Doormanstraat 1",
    "sg:city":"Stramproy",
    "sg:orig_category":"Paramedische Behandelingen",
    "sg:phone":"+31 495 561 297",
    "sg:postcode":"6039 AT",
    "sg:province":"Limburg",
    "wof:name":"Thuiszorg Stichting Midden-Limburg",
    "wof:placetype":"venue"
},
  "geometry": {"coordinates":[5.719541,51.195915],"type":"Point"}
}