{
  "type": "Feature",
  "properties": {
    "addr:full":"Ijselweg 18 Zutphen Gelderland 7207 DJ",
    "addr:housenumber":"18",
    "addr:postcode":"7207 dj",
    "addr:street":"Ijselweg;Gelderland",
    "iso:country":"NL",
    "sg:address":"Ijselweg 18",
    "sg:city":"Zutphen",
    "sg:orig_category":"Gebouwenafwerking, Renovaties And Reiniging",
    "sg:phone":"+31 575 570 873",
    "sg:postcode":"7207 DJ",
    "sg:province":"Gelderland",
    "wof:name":"B.M.S. Brummelman Mobiele Straalservice",
    "wof:placetype":"venue"
},
  "geometry": {"coordinates":[6.224274,52.109444],"type":"Point"}
}