{
  "type": "Feature",
  "properties": {
    "addr:full":"Emmastr 24A Velp Gld Gelderland 6881 SV",
    "addr:housenumber":"24a",
    "addr:postcode":"6881 sv",
    "addr:street":"Emmastr;Gld Gelderland",
    "iso:country":"NL",
    "sg:address":"Emmastr 24A",
    "sg:city":"Velp Gld",
    "sg:orig_category":"Kopieerservice",
    "sg:phone":"+31 26 361 6335",
    "sg:postcode":"6881 SV",
    "sg:province":"Gelderland",
    "wof:name":"Print Boetiek Velp",
    "wof:placetype":"venue"
},
  "geometry": {"coordinates":[5.973947,51.993813],"type":"Point"}
}