{
  "type": "Feature",
  "properties": {
    "addr:full":"Oude Kijk In 'T Jatstr 67 Groningen Groningen 9712 EE",
    "addr:housenumber":"67",
    "addr:postcode":"9712 ee",
    "addr:street":"Oude Kijk In ' T Jatstr",
    "iso:country":"NL",
    "sg:address":"Oude Kijk In 'T Jatstr 67",
    "sg:city":"Groningen",
    "sg:orig_category":"Antiekzaken",
    "sg:phone":"+31 50 312 9654",
    "sg:postcode":"9712 EE",
    "sg:province":"Groningen",
    "wof:name":"Elan Antiek En Curiosa",
    "wof:placetype":"venue"
},
  "geometry": {"coordinates":[6.56368,53.221481],"type":"Point"}
}