{
  "type": "Feature",
  "properties": {
    "addr:full":"Handelsweg 42-44 Dronten Flevoland 8251 JT",
    "addr:housenumber":"42-44",
    "addr:postcode":"8251 jt",
    "addr:street":"Handelsweg;Flevoland",
    "iso:country":"NL",
    "sg:address":"Handelsweg 42-44",
    "sg:city":"Dronten",
    "sg:orig_category":"Autoreparatie And Auto-Onderhoud",
    "sg:phone":"+31 321 313 436",
    "sg:postcode":"8251 JT",
    "sg:province":"Flevoland",
    "sg:website":"http://www.butter.nl",
    "wof:name":"Butter Bedrijfswagenonderhoud",
    "wof:placetype":"venue"
},
  "geometry": {"coordinates":[5.722433,52.537731],"type":"Point"}
}