{
  "type": "Feature",
  "properties": {
    "addr:full":"Wemenstraat 37 Hengelo Ov NL.08 7551 EV",
    "addr:housenumber":"37",
    "addr:street":"Wemenstraat;Ov",
    "iso:country":"NL",
    "sg:address":"Wemenstraat 37",
    "sg:city":"Hengelo Ov",
    "sg:classifiers":[
        {
            "category":"Retail",
            "subcategory":"Photofinishing",
            "type":"Services"
        }
    ],
    "sg:phone":"+31 74 291 3723",
    "sg:postcode":"7551 EV",
    "sg:province":"NL.08",
    "sg:tags":[
        "foto",
        "film"
    ],
    "wof:name":"Fa. W. Grabosch - B. Van Der Velde",
    "wof:placetype":"venue"
},
  "geometry": {"coordinates":[6.794302,52.266384],"type":"Point"}
}