{
  "type": "Feature",
  "properties": {
    "addr:full":"Nw Binnenwg 438B Rotterdam South Holland 3023 EX",
    "addr:housenumber":"438b",
    "addr:postcode":"3023 ex",
    "iso:country":"NL",
    "sg:address":"Nw Binnenwg 438B",
    "sg:city":"Rotterdam",
    "sg:orig_category":"Webdesign Bureaus",
    "sg:phone":"+31 10 425 9355",
    "sg:postcode":"3023 EX",
    "sg:province":"South Holland",
    "wof:name":"Soeltan Designs",
    "wof:placetype":"venue"
},
  "geometry": {"coordinates":[4.451543808,51.9105415344],"type":"Point"}
}