{
  "type": "Feature",
  "properties": {
    "addr:full":"Weesperstr 432 Amsterdam Noord-Holland 1018 DN",
    "addr:housenumber":"432",
    "addr:postcode":"1018 dn",
    "iso:country":"NL",
    "sg:address":"Weesperstr 432",
    "sg:city":"Amsterdam",
    "sg:orig_category":"Adviesbureaus Bedrijfsorganisatie",
    "sg:phone":"+31 20 621 4111",
    "sg:postcode":"1018 DN",
    "sg:province":"Noord-Holland",
    "wof:name":"Project Management Bureau",
    "wof:placetype":"venue"
},
  "geometry": {"coordinates":[4.907059,52.36256],"type":"Point"}
}