{
  "type": "Feature",
  "properties": {
    "addr:full":"Patryspoort 104 Groningen Groningen 9733 GN",
    "addr:housenumber":"104",
    "addr:postcode":"9733 gn",
    "iso:country":"NL",
    "sg:address":"Patryspoort 104",
    "sg:city":"Groningen",
    "sg:orig_category":"Webdesign Bureaus",
    "sg:phone":"+31 50 542 5626",
    "sg:postcode":"9733 GN",
    "sg:province":"Groningen",
    "sg:website":"http://www.pteg.nl",
    "wof:name":"Pteg",
    "wof:placetype":"venue"
},
  "geometry": {"coordinates":[6.6206641197,53.2397384644],"type":"Point"}
}