{
  "type": "Feature",
  "properties": {
    "iso:country":"NL",
    "sg:address":"Burg Banningln 2",
    "sg:city":"Leidschendam",
    "sg:orig_category":"Warenhuizen",
    "sg:phone":"+31 70 317 8854",
    "sg:postcode":"2262 CJ",
    "sg:province":"Zuid-Holland",
    "wof:name":"Xenos Bv",
    "wof:placetype":"venue"
},
  "geometry": {"coordinates":[4.3875198364,52.0913887024],"type":"Point"}
}