{
  "type": "Feature",
  "properties": {
    "addr:full":"Ksg Straat 40 Heerlen Limburg 6413 CZ",
    "addr:housenumber":"40",
    "addr:postcode":"6413",
    "addr:street":"Ksg Straat",
    "iso:country":"NL",
    "sg:address":"Ksg Straat 40",
    "sg:city":"Heerlen",
    "sg:orig_category":"Kantoorapparatuur Gh",
    "sg:phone":"+31 45 563 0212",
    "sg:postcode":"6413 CZ",
    "sg:province":"Limburg",
    "wof:name":"Vof Schnitzeler-Beckers",
    "wof:placetype":"venue"
},
  "geometry": {"coordinates":[5.9626750946,50.918346405],"type":"Point"}
}