{
  "type": "Feature",
  "properties": {
    "iso:country":"NL",
    "sg:address":"Nimrodlaan 4",
    "sg:city":"Bilthoven",
    "sg:orig_category":"Loodgieterswerk, Verwarming And Sanitaire Installaties",
    "sg:phone":"+31 30 225 1206",
    "sg:postcode":"3721 BX",
    "sg:province":"Utrecht",
    "wof:name":"J. Kool",
    "wof:placetype":"venue"
},
  "geometry": {"coordinates":[5.196679,52.122936],"type":"Point"}
}