{
  "type": "Feature",
  "properties": {
    "addr:full":"Axelsestr 62 Terneuzen Zeeland 4537 AL",
    "addr:housenumber":"62",
    "addr:postcode":"4537 al",
    "addr:street":"Axelsestr",
    "iso:country":"NL",
    "sg:address":"Axelsestr 62",
    "sg:city":"Terneuzen",
    "sg:orig_category":"Verzekeringen - Verzekeringskantoren",
    "sg:phone":"+31 115 614 982",
    "sg:postcode":"4537 AL",
    "sg:province":"Zeeland",
    "wof:name":"Boidin Terneuzen Vof",
    "wof:placetype":"venue"
},
  "geometry": {"coordinates":[3.833027,51.331657],"type":"Point"}
}