{
  "type": "Feature",
  "properties": {
    "addr:full":"Wolput 77 Vlijmen North Brabant 5251 CE",
    "addr:housenumber":"77",
    "addr:postcode":"5251 ce",
    "addr:street":"Wolput",
    "iso:country":"NL",
    "sg:address":"Wolput 77",
    "sg:city":"Vlijmen",
    "sg:orig_category":"Kinderopvang Behalve Thuis",
    "sg:phone":"+31 73 511 3620",
    "sg:postcode":"5251 CE",
    "sg:province":"North Brabant",
    "wof:name":"Kinderdagverblijf De Boerderij",
    "wof:placetype":"venue"
},
  "geometry": {"coordinates":[5.204499,51.695004],"type":"Point"}
}