{
  "type": "Feature",
  "properties": {
    "iso:country":"NL",
    "sg:address":"Veldpoortstraat 11",
    "sg:city":"Wijk Bij Duurstede",
    "sg:orig_category":"Werving And Selectie Van Tijdelijk Personeel And Uitzendkantoren",
    "sg:phone":"+31 343 577 606",
    "sg:postcode":"3961 BK",
    "sg:province":"Utrecht",
    "wof:name":"Planmaster Bv",
    "wof:placetype":"venue"
},
  "geometry": {"coordinates":[5.3445148468,51.9736061096],"type":"Point"}
}