{
  "type": "Feature",
  "properties": {
    "addr:full":"Bronsteewg 49A Heemstede Noord-Holland 2101 AB",
    "addr:housenumber":"49a",
    "addr:postcode":"2101 ab",
    "addr:street":"Bronsteewg",
    "iso:country":"NL",
    "sg:address":"Bronsteewg 49A",
    "sg:city":"Heemstede",
    "sg:orig_category":"Psychologen",
    "sg:phone":"+31 23 548 4000",
    "sg:postcode":"2101 AB",
    "sg:province":"Noord-Holland",
    "sg:website":"http://www.hfmpsy.nl",
    "wof:name":"Hofkes Fr\u00f6lke Meekel Bv",
    "wof:placetype":"venue"
},
  "geometry": {"coordinates":[4.623433,52.359772],"type":"Point"}
}