{
  "type": "Feature",
  "properties": {
    "addr:full":"Ln V Middenhoeve 4 Dordrecht Zuid-Holland 3329 KE",
    "addr:housenumber":"4",
    "addr:postcode":"3329 ke",
    "addr:street":"Ln;Middenhoeve",
    "iso:country":"NL",
    "sg:address":"Ln V Middenhoeve 4",
    "sg:city":"Dordrecht",
    "sg:orig_category":"Bestratingen",
    "sg:phone":"+31 78 616 4552",
    "sg:postcode":"3329 KE",
    "sg:province":"Zuid-Holland",
    "wof:name":"Jos Vd Graaf Bv",
    "wof:placetype":"venue"
},
  "geometry": {"coordinates":[4.70258,51.763569],"type":"Point"}
}