{
  "type": "Feature",
  "properties": {
    "iso:country":"NL",
    "sg:address":"Heuvelwg 10",
    "sg:city":"Heerlen",
    "sg:orig_category":"Parketvloeren",
    "sg:phone":"+31 45 572 4458",
    "sg:postcode":"6415 XX",
    "sg:province":"Limburg",
    "wof:name":"Living Floor",
    "wof:placetype":"venue"
},
  "geometry": {"coordinates":[5.985303,50.89061],"type":"Point"}
}