{
  "type": "Feature",
  "properties": {
    "addr:full":"Binnenhavenstr 68 Hengelo Ov Overijssel 7553 GK",
    "addr:housenumber":"68",
    "addr:postcode":"7553 gk",
    "addr:street":"Binnenhavenstr;Ov",
    "iso:country":"NL",
    "sg:address":"Binnenhavenstr 68",
    "sg:city":"Hengelo Ov",
    "sg:orig_category":"Autoschade- Herstelbedrijven",
    "sg:phone":"+31 74 243 9434",
    "sg:postcode":"7553 GK",
    "sg:province":"Overijssel",
    "wof:name":"Binnenhaven Autoschade",
    "wof:placetype":"venue"
},
  "geometry": {"coordinates":[6.774643,52.251991],"type":"Point"}
}