{
  "type": "Feature",
  "properties": {
    "iso:country":"NL",
    "sg:address":"Caspar Houbenstraat 109",
    "sg:city":"Tilburg",
    "sg:orig_category":"Overheidsdiensten",
    "sg:phone":"+31 13 542 4798",
    "sg:postcode":"5018 BP",
    "sg:province":"North Brabant",
    "wof:name":"Buurthuis Jeruzalem",
    "wof:placetype":"venue"
},
  "geometry": {"coordinates":[5.1081337929,51.5536270142],"type":"Point"}
}