{
  "type": "Feature",
  "properties": {
    "iso:country":"NL",
    "sg:address":"Grt Markt 51",
    "sg:city":"Almere",
    "sg:orig_category":"Kopieerservice",
    "sg:phone":"+31 36 534 0721",
    "sg:postcode":"1315 JC",
    "sg:province":"Flevoland",
    "sg:website":"http://www.multicopy.nl",
    "wof:name":"Multicopy Almere",
    "wof:placetype":"venue"
},
  "geometry": {"coordinates":[5.21998,52.374531],"type":"Point"}
}