{
  "type": "Feature",
  "properties": {
    "addr:full":"Haarsteegsestraat 3B Haarsteeg Noord-Brabant 5254  J",
    "addr:housenumber":"3b;5254 j",
    "addr:street":"Haarsteegsestraat",
    "iso:country":"NL",
    "sg:address":"Haarsteegsestraat 3B",
    "sg:city":"Haarsteeg",
    "sg:orig_category":"Bloemen And Planten",
    "sg:phone":"+31 73 511 4173",
    "sg:postcode":"5254  J",
    "sg:province":"Noord-Brabant",
    "wof:name":"Bloemen En Planten De Fontein",
    "wof:placetype":"venue"
},
  "geometry": {"coordinates":[5.200603,51.710133],"type":"Point"}
}