{
  "type": "Feature",
  "properties": {
    "addr:full":"Populierenln 147 Krimpen Ad Yssel Zuid-Holland 2925 CR",
    "addr:housenumber":"147;2925",
    "addr:postcode":"cr",
    "addr:street":"Krimpen",
    "iso:country":"NL",
    "sg:address":"Populierenln 147",
    "sg:city":"Krimpen Ad Yssel",
    "sg:orig_category":"Adviesbureaus Gezondheidszorg",
    "sg:phone":"+31 180 524 275",
    "sg:postcode":"2925 CR",
    "sg:province":"Zuid-Holland",
    "wof:name":"Med-At-Tec",
    "wof:placetype":"venue"
},
  "geometry": {"coordinates":[4.623036,51.915245],"type":"Point"}
}