{
  "type": "Feature",
  "properties": {
    "addr:full":"Dorpstraat 19 Maastricht Limburg 6227 BK",
    "addr:housenumber":"19",
    "addr:postcode":"6227 bk",
    "addr:street":"Dorpstraat",
    "iso:country":"NL",
    "sg:address":"Dorpstraat 19",
    "sg:city":"Maastricht",
    "sg:orig_category":"Verlichting And Huishoudartikelen",
    "sg:phone":"+31 43 361 3201",
    "sg:postcode":"6227 BK",
    "sg:province":"Limburg",
    "wof:name":"Kicken Kadoshop Huishoudelijke Artikelen",
    "wof:placetype":"venue"
},
  "geometry": {"coordinates":[5.727724,50.842663],"type":"Point"}
}