{
  "type": "Feature",
  "properties": {
    "addr:full":"Arlandabaan 17 Rotterdam Zuid-Holland 3045 AA",
    "addr:housenumber":"17",
    "addr:postcode":"3045 aa",
    "addr:street":"Arlandabaan",
    "iso:country":"NL",
    "sg:address":"Arlandabaan 17",
    "sg:city":"Rotterdam",
    "sg:orig_category":"Verhuur Kantoorapparatuur",
    "sg:phone":"+31 10 262 3303",
    "sg:postcode":"3045 AA",
    "sg:province":"Zuid-Holland",
    "sg:website":"http://www.beamrent.nl",
    "wof:name":"Beamrent Projector",
    "wof:placetype":"venue"
},
  "geometry": {"coordinates":[4.431234,51.950413],"type":"Point"}
}