{
  "type": "Feature",
  "properties": {
    "addr:full":"Oosteinde 96 Berkhout Noord-Holland 1647 AE",
    "addr:housenumber":"96",
    "addr:postcode":"1647 ae",
    "addr:street":"Oosteinde",
    "iso:country":"NL",
    "sg:address":"Oosteinde 96",
    "sg:city":"Berkhout",
    "sg:orig_category":"Voeding, Dranken And Tabak Gh",
    "sg:phone":"+31 229 553 518",
    "sg:postcode":"1647 AE",
    "sg:province":"Noord-Holland",
    "wof:name":"R. Van Der Beek",
    "wof:placetype":"venue"
},
  "geometry": {"coordinates":[5.009764,52.641521],"type":"Point"}
}