{
  "type": "Feature",
  "properties": {
    "addr:full":"Aardvletterwg 8 Montfoort Utrecht 3417 XL",
    "addr:housenumber":"8",
    "addr:postcode":"3417 xl",
    "addr:street":"Aardvletterwg",
    "iso:country":"NL",
    "sg:address":"Aardvletterwg 8",
    "sg:city":"Montfoort",
    "sg:orig_category":"Autoschade- Herstelbedrijven",
    "sg:phone":"+31 348 470 064",
    "sg:postcode":"3417 XL",
    "sg:province":"Utrecht",
    "wof:name":"G & R Spuitwerken",
    "wof:placetype":"venue"
},
  "geometry": {"coordinates":[4.939145,52.043087],"type":"Point"}
}