{
  "type": "Feature",
  "properties": {
    "addr:full":"C T Storkstr 1 Hengelo Ov NL.08 7553 AN",
    "addr:housenumber":"1",
    "addr:postcode":"7553 an",
    "addr:street":"Ov",
    "iso:country":"NL",
    "sg:address":"C T Storkstr 1",
    "sg:city":"Hengelo Ov",
    "sg:orig_category":"Logopedisten",
    "sg:phone":"+31 74 250 5011",
    "sg:postcode":"7553 AN",
    "sg:province":"NL.08",
    "wof:name":"Wolters K Van Galen-Albers En S Zandman, H P",
    "wof:placetype":"venue"
},
  "geometry": {"coordinates":[6.784056,52.260437],"type":"Point"}
}