{
  "type": "Feature",
  "properties": {
    "iso:country":"NL",
    "sg:address":"Vd Peylstr 1",
    "sg:city":"Terneuzen",
    "sg:orig_category":"Scholen Voor Basisonderwijs",
    "sg:phone":"+31 115 619 097",
    "sg:postcode":"4537 PL",
    "sg:province":"Zeeland",
    "wof:name":"Groene Zwaan, De",
    "wof:placetype":"venue"
},
  "geometry": {"coordinates":[3.827559,51.338146],"type":"Point"}
}