{
  "type": "Feature",
  "properties": {
    "addr:full":"J Steenln 5 Stolwyk Virginia 2821 VA",
    "addr:housenumber":"5;2821",
    "addr:street":"Stolwyk Virginia",
    "iso:country":"NL",
    "sg:address":"J Steenln 5",
    "sg:city":"Stolwyk",
    "sg:orig_category":"Bedrijfsorganisaties",
    "sg:phone":"+31 182 341 601",
    "sg:postcode":"2821 VA",
    "sg:province":"Virginia",
    "wof:name":"Stenvi",
    "wof:placetype":"venue"
},
  "geometry": {"coordinates":[-79.771446,38.003349],"type":"Point"}
}