{
  "type": "Feature",
  "properties": {
    "addr:full":"Boudier Bakkerln 43 Zutphen Gelderland 7207 KX",
    "addr:housenumber":"43",
    "addr:postcode":"7207 kx",
    "addr:street":"Gelderland",
    "iso:country":"NL",
    "sg:address":"Boudier Bakkerln 43",
    "sg:city":"Zutphen",
    "sg:orig_category":"Kappers",
    "sg:phone":"+31 575 575 565",
    "sg:postcode":"7207 KX",
    "sg:province":"Gelderland",
    "wof:name":"Via Via",
    "wof:placetype":"venue"
},
  "geometry": {"coordinates":[6.233016,52.123772],"type":"Point"}
}