{
  "type": "Feature",
  "properties": {
    "iso:country":"NL",
    "sg:address":"Boudier Bakkerln 43",
    "sg:city":"Zutphen",
    "sg:orig_category":"Kappers",
    "sg:phone":"+31 575 575 565",
    "sg:postcode":"7207 KX",
    "sg:province":"Gelderland",
    "wof:name":"Via Via",
    "wof:placetype":"venue"
},
  "geometry": {"coordinates":[6.233016,52.123772],"type":"Point"}
}