{
  "type": "Feature",
  "properties": {
    "addr:full":"Burgemeester Oudlaan 50 Rotterdam Zuid-Holland 3062 PA",
    "addr:housenumber":"50",
    "addr:postcode":"3062 pa",
    "addr:street":"Burgemeester Oudlaan",
    "iso:country":"NL",
    "sg:address":"Burgemeester Oudlaan 50",
    "sg:city":"Rotterdam",
    "sg:orig_category":"Boekenuitgeverijen",
    "sg:phone":"+31 10 408 1150",
    "sg:postcode":"3062 PA",
    "sg:province":"Zuid-Holland",
    "wof:name":"Donner Boeken",
    "wof:placetype":"venue"
},
  "geometry": {"coordinates":[4.5241,51.919659],"type":"Point"}
}