{
  "type": "Feature",
  "properties": {
    "iso:country":"NL",
    "sg:address":"E Strouvenln 33",
    "sg:city":"Maastricht",
    "sg:orig_category":"Vertalers",
    "sg:phone":"+31 43 325 1078",
    "sg:postcode":"6214 AW",
    "sg:province":"Limburg",
    "wof:name":"Jongh Bv, De",
    "wof:placetype":"venue"
},
  "geometry": {"coordinates":[5.679303,50.84568],"type":"Point"}
}