{
  "type": "Feature",
  "properties": {
    "addr:full":"Soetendaal 63 Amsterdam Noord-Holland 1081 BN",
    "addr:housenumber":"63",
    "addr:postcode":"1081 bn",
    "addr:street":"Soetendaal",
    "iso:country":"NL",
    "sg:address":"Soetendaal 63",
    "sg:city":"Amsterdam",
    "sg:orig_category":"Evenementenverzorging",
    "sg:phone":"+31 20 670 4296",
    "sg:postcode":"1081 BN",
    "sg:province":"Noord-Holland",
    "wof:name":"Assist In Communication",
    "wof:placetype":"venue"
},
  "geometry": {"coordinates":[4.863669,52.324154],"type":"Point"}
}