{
  "type": "Feature",
  "properties": {
    "addr:full":"Fresia 100 Krimpen A/D Ijssel South Holland 2925 EL",
    "addr:housenumber":"100;a / d;2925",
    "addr:postcode":"el",
    "addr:street":"Fresia;Ijssel South",
    "iso:country":"NL",
    "sg:address":"Fresia 100",
    "sg:city":"Krimpen A/D Ijssel",
    "sg:orig_category":"Binnenhuisarchitecten",
    "sg:phone":"+31 180 521 970",
    "sg:postcode":"2925 EL",
    "sg:province":"South Holland",
    "wof:name":"S.P. Suvaal",
    "wof:placetype":"venue"
},
  "geometry": {"coordinates":[4.623405,51.923264],"type":"Point"}
}