{
  "type": "Feature",
  "properties": {
    "addr:full":"J P Coenstr 41 Ymuiden Noord-Holland 1972 AP",
    "addr:housenumber":"41",
    "addr:postcode":"1972 ap",
    "addr:street":"J P Coenstr",
    "iso:country":"NL",
    "sg:address":"J P Coenstr 41",
    "sg:city":"Ymuiden",
    "sg:orig_category":"Loodgieters",
    "sg:phone":"+31 255 533 746",
    "sg:postcode":"1972 AP",
    "sg:province":"Noord-Holland",
    "wof:name":"Klepper Loodgietersbedrijf Bv",
    "wof:placetype":"venue"
},
  "geometry": {"coordinates":[4.61762,52.458302],"type":"Point"}
}