{
  "type": "Feature",
  "properties": {
    "addr:full":"Erasmusln 197 Zwolle NL.08 8024 DB",
    "addr:housenumber":"197",
    "addr:postcode":"8024 db",
    "iso:country":"NL",
    "sg:address":"Erasmusln 197",
    "sg:city":"Zwolle",
    "sg:orig_category":"Adviesbureaus Bedrijfsorganisatie",
    "sg:phone":"+31 38 453 7441",
    "sg:postcode":"8024 DB",
    "sg:province":"NL.08",
    "wof:name":"Weenk, E",
    "wof:placetype":"venue"
},
  "geometry": {"coordinates":[6.137313,52.526436],"type":"Point"}
}