{
  "type": "Feature",
  "properties": {
    "addr:full":"Postbus 140 Nieuw Vennep 2150 AC",
    "addr:housenumber":"140",
    "addr:postcode":"2150 ac",
    "addr:street":"Postbus;Nieuw Vennep",
    "iso:country":"NL",
    "sg:address":"Postbus 140",
    "sg:city":"Nieuw Vennep",
    "sg:orig_category":"Zuigers/Zuigerveren - Fabrieken En Groothandel",
    "sg:phone":"+31 252 687 713",
    "sg:postcode":"2150 AC",
    "sg:website":"http://www.pro-x.com",
    "wof:name":"Prox Inter Bv",
    "wof:placetype":"venue"
},
  "geometry": {"coordinates":[4.6335,52.26474],"type":"Point"}
}