{
  "type": "Feature",
  "properties": {
    "iso:country":"NL",
    "sg:address":"Nagelerweg 9",
    "sg:city":"Emmeloord",
    "sg:orig_category":"Goederenvervoer Over De Weg",
    "sg:phone":"+31 527 699 680",
    "sg:postcode":"8304 AB",
    "sg:province":"NL.",
    "wof:name":"Handelsonderneming Peter Borgijink",
    "wof:placetype":"venue"
},
  "geometry": {"coordinates":[5.754205,52.708984],"type":"Point"}
}