{
  "type": "Feature",
  "properties": {
    "addr:full":"Kruizemuntstr 145 Apeldoorn Gelderland 7322 LG",
    "addr:housenumber":"145",
    "addr:postcode":"7322 lg",
    "addr:street":"Gelderland",
    "iso:country":"NL",
    "sg:address":"Kruizemuntstr 145",
    "sg:city":"Apeldoorn",
    "sg:orig_category":"Psychotherapeuten",
    "sg:phone":"+31 55 366 2776",
    "sg:postcode":"7322 LG",
    "sg:province":"Gelderland",
    "wof:name":"Nievaard, Y M W",
    "wof:placetype":"venue"
},
  "geometry": {"coordinates":[5.988653,52.218407],"type":"Point"}
}