{
  "type": "Feature",
  "properties": {
    "addr:full":"Witte Sngl 56 Leiden South Holland 2311 BL",
    "addr:housenumber":"56",
    "addr:postcode":"2311 bl",
    "addr:street":"Sngl",
    "iso:country":"NL",
    "sg:address":"Witte Sngl 56",
    "sg:city":"Leiden",
    "sg:orig_category":"Verzekeringen - Verzekeringskantoren",
    "sg:phone":"+31 71 512 6408",
    "sg:postcode":"2311 BL",
    "sg:province":"South Holland",
    "wof:name":"Hoogt, Van Der",
    "wof:placetype":"venue"
},
  "geometry": {"coordinates":[4.483557,52.152016],"type":"Point"}
}