{
  "type": "Feature",
  "properties": {
    "addr:full":"Van Grobbendoncklaan 69 'S Hertogenbosch Noord-Brabant 5213 AV",
    "addr:housenumber":"69",
    "addr:postcode":"5213 av",
    "addr:street":"Van Grobbendoncklaan;' S",
    "iso:country":"NL",
    "sg:address":"Van Grobbendoncklaan 69",
    "sg:city":"'S Hertogenbosch",
    "sg:orig_category":"Verzekeringen",
    "sg:phone":"+31 73 690 1340",
    "sg:postcode":"5213 AV",
    "sg:province":"Noord-Brabant",
    "wof:name":"Gouden De Handdruk Pensioenen En Verz Bv",
    "wof:placetype":"venue"
},
  "geometry": {"coordinates":[5.320123,51.698128],"type":"Point"}
}