{
  "type": "Feature",
  "properties": {
    "addr:full":"Hemonyln 19A Amsterdam Noord-Holland 1074 BH",
    "addr:housenumber":"19a",
    "addr:postcode":"1074 bh",
    "addr:street":"Hemonyln",
    "iso:country":"NL",
    "sg:address":"Hemonyln 19A",
    "sg:city":"Amsterdam",
    "sg:orig_category":"Fotografie Reclame En Mode",
    "sg:phone":"+31 20 681 3407",
    "sg:postcode":"1074 BH",
    "sg:province":"Noord-Holland",
    "wof:name":"Brandsma, Dennis",
    "wof:placetype":"venue"
},
  "geometry": {"coordinates":[4.901251,52.357471],"type":"Point"}
}