{
  "type": "Feature",
  "properties": {
    "addr:full":"Hefbrug 2 Houten Utrecht 3991 LB",
    "addr:housenumber":"2",
    "addr:postcode":"3991 lb",
    "addr:street":"Hefbrug",
    "iso:country":"NL",
    "sg:address":"Hefbrug 2",
    "sg:city":"Houten",
    "sg:orig_category":"Balletscholen",
    "sg:phone":"+31 30 638 1501",
    "sg:postcode":"3991 LB",
    "sg:province":"Utrecht",
    "sg:website":"http://www.stardance.nl",
    "wof:name":"Stardance",
    "wof:placetype":"venue"
},
  "geometry": {"coordinates":[5.1598,52.022572],"type":"Point"}
}