{
  "type": "Feature",
  "properties": {
    "addr:full":"Schoolweg 3 Andijk Noord-Holland 1619 AL",
    "addr:housenumber":"3",
    "addr:postcode":"1619 al",
    "addr:street":"Schoolweg",
    "iso:country":"NL",
    "sg:address":"Schoolweg 3",
    "sg:city":"Andijk",
    "sg:orig_category":"Bloemen And Planten",
    "sg:phone":"+31 228 591 290",
    "sg:postcode":"1619 AL",
    "sg:province":"Noord-Holland",
    "wof:name":"Oriental Andijk Bv",
    "wof:placetype":"venue"
},
  "geometry": {"coordinates":[5.222525,52.744362],"type":"Point"}
}