{
  "type": "Feature",
  "properties": {
    "iso:country":"NL",
    "sg:address":"Beethovenstr 169",
    "sg:city":"Amsterdam",
    "sg:orig_category":"Makelaars En Adviseurs Onroerende Goederen",
    "sg:phone":"+31 20 662 8942",
    "sg:postcode":"1077 JD",
    "sg:province":"North Holland",
    "wof:name":"Marina Van Schaik",
    "wof:placetype":"venue"
},
  "geometry": {"coordinates":[4.877326,52.342358],"type":"Point"}
}