{
  "type": "Feature",
  "properties": {
    "addr:full":"Scharenweg 24 Panningen Limburg 5981 BW",
    "addr:housenumber":"24",
    "addr:postcode":"5981 bw",
    "addr:street":"Scharenweg",
    "iso:country":"NL",
    "sg:address":"Scharenweg 24",
    "sg:city":"Panningen",
    "sg:orig_category":"Drukkerijen And Copyshops",
    "sg:phone":"+31 77 307 4018",
    "sg:postcode":"5981 BW",
    "sg:province":"Limburg",
    "wof:name":"Offsetdrukkerij Jac Ottenheijm",
    "wof:placetype":"venue"
},
  "geometry": {"coordinates":[5.974543,51.32373],"type":"Point"}
}