{
  "type": "Feature",
  "properties": {
    "addr:full":"Nieuwstad 8 Groenlo Gelderland 7141 BD",
    "addr:housenumber":"8",
    "addr:postcode":"7141 bd",
    "addr:street":"Nieuwstad;Gelderland",
    "iso:country":"NL",
    "sg:address":"Nieuwstad 8",
    "sg:city":"Groenlo",
    "sg:orig_category":"Kappers",
    "sg:phone":"+31 544 464 949",
    "sg:postcode":"7141 BD",
    "sg:province":"Gelderland",
    "wof:name":"Salon Elan Haarmode",
    "wof:placetype":"venue"
},
  "geometry": {"coordinates":[6.616186,52.040691],"type":"Point"}
}