{
  "type": "Feature",
  "properties": {
    "addr:full":"Grooten Sloot 45 Bergschenhoek Zuid-Holland 2661 SN",
    "addr:housenumber":"45",
    "addr:postcode":"2661 sn",
    "addr:street":"Grooten Sloot",
    "iso:country":"NL",
    "sg:address":"Grooten Sloot 45",
    "sg:city":"Bergschenhoek",
    "sg:orig_category":"Boten",
    "sg:phone":"+31 10 521 0050",
    "sg:postcode":"2661 SN",
    "sg:province":"Zuid-Holland",
    "wof:name":"Sepra",
    "wof:placetype":"venue"
},
  "geometry": {"coordinates":[4.508956,51.995541],"type":"Point"}
}