{
  "type": "Feature",
  "properties": {
    "addr:full":"Beukerstraat 75 Zutphen Gelderland 7201 LC",
    "addr:housenumber":"75",
    "addr:postcode":"7201 lc",
    "addr:street":"Beukerstraat;Gelderland",
    "iso:country":"NL",
    "sg:address":"Beukerstraat 75",
    "sg:city":"Zutphen",
    "sg:orig_category":"Kappers",
    "sg:phone":"+31 575 512 271",
    "sg:postcode":"7201 LC",
    "sg:province":"Gelderland",
    "wof:name":"Kapsalon Desiree-Barber Shop",
    "wof:placetype":"venue"
},
  "geometry": {"coordinates":[6.1977720261,52.1412620544],"type":"Point"}
}