{
  "type": "Feature",
  "properties": {
    "addr:full":"Kalverstraat 124 Amsterdam North Holland 1012 PK",
    "addr:housenumber":"124",
    "addr:postcode":"1012 pk",
    "addr:street":"Kalverstraat",
    "iso:country":"NL",
    "sg:address":"Kalverstraat 124",
    "sg:city":"Amsterdam",
    "sg:classifiers":[
        {
            "category":"Shopping",
            "subcategory":"Gifts & Souvenirs",
            "type":"Retail Goods"
        }
    ],
    "sg:phone":"+31 20 624 8618",
    "sg:postcode":"1012 PK",
    "sg:province":"North Holland",
    "sg:tags":[
        "geschenken"
    ],
    "wof:name":"Het Kantenhuis Bv",
    "wof:placetype":"venue"
},
  "geometry": {"coordinates":[4.89103,52.369762],"type":"Point"}
}