{
  "type": "Feature",
  "properties": {
    "addr:full":"Gele Rijders Plein 6 Arnhem Gelderland 6811 AN",
    "addr:housenumber":"6",
    "addr:postcode":"6811 an",
    "addr:street":"Gele Rijders Plein",
    "iso:country":"NL",
    "sg:address":"Gele Rijders Plein 6",
    "sg:city":"Arnhem",
    "sg:orig_category":"Makelaars In Onroerend Goed",
    "sg:phone":"+31 26 442 9388",
    "sg:postcode":"6811 AN",
    "sg:province":"Gelderland",
    "wof:name":"Annemiek Schwieters Makelaardij O.G. Vof",
    "wof:placetype":"venue"
},
  "geometry": {"coordinates":[5.908162,51.983166],"type":"Point"}
}