{
  "type": "Feature",
  "properties": {
    "addr:full":"Veerstalblok 7 Gouderak South Holland 2831 BS",
    "addr:housenumber":"7",
    "addr:postcode":"2831 bs",
    "addr:street":"Veerstalblok",
    "iso:country":"NL",
    "sg:address":"Veerstalblok 7",
    "sg:city":"Gouderak",
    "sg:orig_category":"Loonbedrijven",
    "sg:phone":"+31 182 518 060",
    "sg:postcode":"2831 BS",
    "sg:province":"South Holland",
    "wof:name":"Hogendoorn, G M",
    "wof:placetype":"venue"
},
  "geometry": {"coordinates":[4.701876,51.997379],"type":"Point"}
}