{
  "type": "Feature",
  "properties": {
    "addr:full":"Reewg 116A Landgraaf Limburg 6374 BZ",
    "addr:housenumber":"116a",
    "addr:postcode":"6374 bz",
    "iso:country":"NL",
    "sg:address":"Reewg 116A",
    "sg:city":"Landgraaf",
    "sg:orig_category":"Ongediertebestrijding En Ontsmetting",
    "sg:phone":"+31 800 5690206",
    "sg:postcode":"6374 BZ",
    "sg:province":"Limburg",
    "wof:name":"Janssen, Sjaak",
    "wof:placetype":"venue"
},
  "geometry": {"coordinates":[6.025217,50.919277],"type":"Point"}
}