{
  "type": "Feature",
  "properties": {
    "addr:full":"Hobbemapln 4 S Gravenhage Zuid-Holland 2526 JA",
    "addr:housenumber":"4;gravenhage",
    "addr:postcode":"2526 ja",
    "addr:street":"Hobbemapln;S",
    "iso:country":"NL",
    "sg:address":"Hobbemapln 4",
    "sg:city":"S Gravenhage",
    "sg:orig_category":"Schoenen",
    "sg:phone":"+31 70 380 5774",
    "sg:postcode":"2526 JA",
    "sg:province":"Zuid-Holland",
    "wof:name":"Herman",
    "wof:placetype":"venue"
},
  "geometry": {"coordinates":[4.30555,52.0681],"type":"Point"}
}