{
  "type": "Feature",
  "properties": {
    "addr:full":"Middenwg 31 Wateringen Zuid-Holland 2291 HW",
    "addr:housenumber":"31",
    "addr:postcode":"2291 hw",
    "addr:street":"Middenwg",
    "iso:country":"NL",
    "sg:address":"Middenwg 31",
    "sg:city":"Wateringen",
    "sg:orig_category":"Bloemen En Planten",
    "sg:phone":"+31 174 298 267",
    "sg:postcode":"2291 HW",
    "sg:province":"Zuid-Holland",
    "wof:name":"Raaf Westland Bv, De",
    "wof:placetype":"venue"
},
  "geometry": {"coordinates":[4.283824,52.014595],"type":"Point"}
}