{
  "type": "Feature",
  "properties": {
    "iso:country":"NL",
    "sg:address":"Laan 1945 20B",
    "sg:city":"Weurt",
    "sg:orig_category":"Kappers",
    "sg:phone":"+31 24 677 7376",
    "sg:postcode":"6551 CZ",
    "sg:province":"Gelderland",
    "wof:name":"Haarstudio 95",
    "wof:placetype":"venue"
},
  "geometry": {"coordinates":[15.4752702713,49.8037910461],"type":"Point"}
}