{
  "type": "Feature",
  "properties": {
    "addr:full":"Hoofdstraat 110 Posterholt Limburg 6061 CG",
    "addr:housenumber":"110",
    "addr:postcode":"6061 cg",
    "addr:street":"Hoofdstraat",
    "iso:country":"NL",
    "sg:address":"Hoofdstraat 110",
    "sg:city":"Posterholt",
    "sg:orig_category":"Muziekinstrumenten",
    "sg:phone":"+31 475 401 731",
    "sg:postcode":"6061 CG",
    "sg:province":"Limburg",
    "wof:name":"Vof Jeurissen Muziekinstrumenten",
    "wof:placetype":"venue"
},
  "geometry": {"coordinates":[6.035792,51.121841],"type":"Point"}
}