{
  "type": "Feature",
  "properties": {
    "addr:full":"Hectorlaan 2 Heerhugowaard Noord-Holland 1702 CL",
    "addr:housenumber":"2",
    "addr:postcode":"1702",
    "addr:street":"Hectorlaan",
    "iso:country":"NL",
    "sg:address":"Hectorlaan 2",
    "sg:city":"Heerhugowaard",
    "sg:classifiers":[
        {
            "category":"Professional",
            "subcategory":"Accounting & Tax Preparation",
            "type":"Services"
        }
    ],
    "sg:phone":"+31 72 574 1144",
    "sg:postcode":"1702 CL",
    "sg:province":"Noord-Holland",
    "sg:tags":[
        "accountant"
    ],
    "wof:name":"Administratiekantoor Dekker",
    "wof:placetype":"venue"
},
  "geometry": {"coordinates":[4.835264,52.674301],"type":"Point"}
}