{
  "type": "Feature",
  "properties": {
    "iso:country":"NL",
    "sg:address":"Pastoorstr 11",
    "sg:city":"Naarden",
    "sg:orig_category":"Fotografie Reclame En Mode",
    "sg:phone":"+31 35 695 2061",
    "sg:postcode":"1411 SC",
    "sg:province":"Noord-Holland",
    "wof:name":"Kc",
    "wof:placetype":"venue"
},
  "geometry": {"coordinates":[5.160789,52.29583],"type":"Point"}
}