{
  "type": "Feature",
  "properties": {
    "addr:full":"Nieuwstraat 16 Leidschendam Zuid-Holland 2266 AD",
    "addr:housenumber":"16",
    "addr:postcode":"2266 ad",
    "addr:street":"Nieuwstraat",
    "iso:country":"NL",
    "sg:address":"Nieuwstraat 16",
    "sg:city":"Leidschendam",
    "sg:orig_category":"Meubelzaken, Woning- And Keukeninrichting",
    "sg:phone":"+31 70 327 0131",
    "sg:postcode":"2266 AD",
    "sg:province":"Zuid-Holland",
    "wof:name":"Georgina Bv",
    "wof:placetype":"venue"
},
  "geometry": {"coordinates":[4.395146,52.078526],"type":"Point"}
}