{
  "type": "Feature",
  "properties": {
    "iso:country":"NL",
    "sg:address":"Bremstr 3",
    "sg:city":"Bussum",
    "sg:orig_category":"Orthopedische Artikelen",
    "sg:phone":"+31 35 693 8070",
    "sg:postcode":"1402 BD",
    "sg:province":"Noord-Holland",
    "wof:name":"Frenzel, Mw M I E",
    "wof:placetype":"venue"
},
  "geometry": {"coordinates":[5.1823191643,52.2717514038],"type":"Point"}
}