{
  "type": "Feature",
  "properties": {
    "iso:country":"NL",
    "sg:address":"Fleminghof 45",
    "sg:city":"Schoonhoven",
    "sg:orig_category":"Metselwerken",
    "sg:phone":"+31 182 384 772",
    "sg:postcode":"2871 LT",
    "sg:province":"Zuid-Holland",
    "wof:name":"Peh",
    "wof:placetype":"venue"
},
  "geometry": {"coordinates":[4.837861,51.950829],"type":"Point"}
}