{
  "type": "Feature",
  "properties": {
    "iso:country":"NL",
    "sg:address":"Varsseveldsewg 22",
    "sg:city":"Lichtenvoorde",
    "sg:classifiers":[
        {
            "category":"Retail",
            "subcategory":"Auto Repair",
            "type":"Services"
        }
    ],
    "sg:phone":"+31 544 372 808",
    "sg:postcode":"7131 BJ",
    "sg:province":"Gelderland",
    "sg:tags":[
        "garage"
    ],
    "wof:name":"Vos Bv",
    "wof:placetype":"venue"
},
  "geometry": {"coordinates":[6.56185,51.98735],"type":"Point"}
}