{
  "type": "Feature",
  "properties": {
    "addr:full":"Ringvaartsingel 36 Waddinxveen Zuid-Holland 2741 JL",
    "addr:housenumber":"36",
    "addr:postcode":"2741 jl",
    "addr:street":"Ringvaartsingel",
    "iso:country":"NL",
    "sg:address":"Ringvaartsingel 36",
    "sg:city":"Waddinxveen",
    "sg:orig_category":"Wegen And Sportterreinen",
    "sg:phone":"+31 182 614 609",
    "sg:postcode":"2741 JL",
    "sg:province":"Zuid-Holland",
    "wof:name":"J. Vos",
    "wof:placetype":"venue"
},
  "geometry": {"coordinates":[4.6589679718,52.0294532776],"type":"Point"}
}