{
  "type": "Feature",
  "properties": {
    "addr:full":"Schoolstr 30 Hoek Van Holland Zuid-Holland 3151 AZ",
    "addr:housenumber":"30",
    "addr:postcode":"3151 az",
    "addr:street":"Schoolstr",
    "iso:country":"NL",
    "sg:address":"Schoolstr 30",
    "sg:city":"Hoek Van Holland",
    "sg:orig_category":"Woninginrichting",
    "sg:phone":"+31 174 382 636",
    "sg:postcode":"3151 AZ",
    "sg:province":"Zuid-Holland",
    "wof:name":"Ons Huis",
    "wof:placetype":"venue"
},
  "geometry": {"coordinates":[4.1326098442,51.9768600464],"type":"Point"}
}