{
  "type": "Feature",
  "properties": {
    "addr:full":"Aelbrechtskd 118A Rotterdam Zuid-Holland 3023 JE",
    "addr:housenumber":"118a",
    "addr:postcode":"3023 je",
    "iso:country":"NL",
    "sg:address":"Aelbrechtskd 118A",
    "sg:city":"Rotterdam",
    "sg:orig_category":"Automaterialen En Gereedschappen",
    "sg:phone":"+31 10 477 9372",
    "sg:postcode":"3023 JE",
    "sg:province":"Zuid-Holland",
    "wof:name":"Lachman",
    "wof:placetype":"venue"
},
  "geometry": {"coordinates":[4.446416,51.914425],"type":"Point"}
}