{
  "type": "Feature",
  "properties": {
    "addr:full":"Kerkstraat 71 Tegelen Limburg 5931 NM",
    "addr:housenumber":"71",
    "addr:postcode":"5931",
    "addr:street":"Kerkstraat",
    "iso:country":"NL",
    "sg:address":"Kerkstraat 71",
    "sg:city":"Tegelen",
    "sg:classifiers":[
        {
            "category":"Food & Beverages",
            "subcategory":"Fruits & Vegetables",
            "type":"Retail Goods"
        }
    ],
    "sg:phone":"+31 77 373 0197",
    "sg:postcode":"5931 NM",
    "sg:province":"Limburg",
    "sg:tags":[
        "groenten"
    ],
    "wof:name":"P. Ottenheijm Groenten Fruit Delic. Vof",
    "wof:placetype":"venue"
},
  "geometry": {"coordinates":[6.13959,51.341579],"type":"Point"}
}