{
  "type": "Feature",
  "properties": {
    "iso:country":"NL",
    "sg:address":"H Druckerstr 13",
    "sg:city":"Tilburg",
    "sg:orig_category":"Administratie- En Boekhoudkantoren",
    "sg:phone":"+31 13 590 0236",
    "sg:postcode":"5042 NA",
    "sg:province":"Noord-Brabant",
    "wof:name":"Ad Van De Besselaar",
    "wof:placetype":"venue"
},
  "geometry": {"coordinates":[5.057342,51.568581],"type":"Point"}
}