{
  "type": "Feature",
  "properties": {
    "addr:full":"Stalen Enk 41 Velp Gld Gelderland 6881 BN",
    "addr:housenumber":"41",
    "addr:postcode":"6881 bn",
    "addr:street":"Stalen Enk;Gld Gelderland",
    "iso:country":"NL",
    "sg:address":"Stalen Enk 41",
    "sg:city":"Velp Gld",
    "sg:orig_category":"Onroerende Goederen",
    "sg:phone":"+31 26 361 9870",
    "sg:postcode":"6881 BN",
    "sg:province":"Gelderland",
    "wof:name":"Holtjer Bv",
    "wof:placetype":"venue"
},
  "geometry": {"coordinates":[5.97722,52.004135],"type":"Point"}
}