{
  "type": "Feature",
  "properties": {
    "addr:full":"Rabroekenwg 5 Meppel Provincie Drenthe 7942 JE",
    "addr:housenumber":"5",
    "addr:postcode":"7942 je",
    "addr:street":"Rabroekenwg;Provincie Drenthe",
    "iso:country":"NL",
    "sg:address":"Rabroekenwg 5",
    "sg:city":"Meppel",
    "sg:orig_category":"Verf En Lak - Fabrieken En Groothandel",
    "sg:phone":"+31 522 251 099",
    "sg:postcode":"7942 JE",
    "sg:province":"Provincie Drenthe",
    "sg:website":"http://www.olijslager.nl",
    "wof:name":"Olijslager Bv",
    "wof:placetype":"venue"
},
  "geometry": {"coordinates":[6.197458,52.711353],"type":"Point"}
}