{
  "type": "Feature",
  "properties": {
    "addr:full":"Nw Karseln 45 Amstelveen Noord-Holland 1182 BP",
    "addr:housenumber":"45",
    "addr:postcode":"1182 bp",
    "iso:country":"NL",
    "sg:address":"Nw Karseln 45",
    "sg:city":"Amstelveen",
    "sg:orig_category":"Schilders",
    "sg:phone":"+31 20 441 4351",
    "sg:postcode":"1182 BP",
    "sg:province":"Noord-Holland",
    "wof:name":"Brinkman Schildersbedrijf",
    "wof:placetype":"venue"
},
  "geometry": {"coordinates":[4.856945,52.303444],"type":"Point"}
}