{
  "type": "Feature",
  "properties": {
    "iso:country":"NL",
    "sg:address":"Kloosterstraat 10",
    "sg:city":"Chaam",
    "sg:orig_category":"Makelaars In Onroerend Goed",
    "sg:phone":"+31 161 492 371",
    "sg:postcode":"4861 PB",
    "sg:province":"Noord-Brabant",
    "wof:name":"Makelaars- En Adviesbureau Broeders",
    "wof:placetype":"venue"
},
  "geometry": {"coordinates":[4.869421,51.525742],"type":"Point"}
}