{
  "type": "Feature",
  "properties": {
    "addr:full":"Boekel 33 Akersloot North Holland 1921 CE",
    "addr:housenumber":"33",
    "addr:postcode":"1921 ce",
    "addr:street":"Boekel",
    "iso:country":"NL",
    "sg:address":"Boekel 33",
    "sg:city":"Akersloot",
    "sg:orig_category":"Onderhoudswerken",
    "sg:phone":"+31 72 532 1111",
    "sg:postcode":"1921 CE",
    "sg:province":"North Holland",
    "wof:name":"Teerenstra",
    "wof:placetype":"venue"
},
  "geometry": {"coordinates":[4.752763,52.586163],"type":"Point"}
}