{
  "type": "Feature",
  "properties": {
    "iso:country":"NL",
    "sg:address":"Landstraat 49",
    "sg:city":"Aalten",
    "sg:orig_category":"Wasserettes And Stomerijen",
    "sg:phone":"+31 543 472 342",
    "sg:postcode":"7121 CP",
    "sg:province":"Gelderland",
    "wof:name":"Roeloffzen & Co Bv",
    "wof:placetype":"venue"
},
  "geometry": {"coordinates":[6.5812149048,51.9158821106],"type":"Point"}
}