{
  "type": "Feature",
  "properties": {
    "addr:full":"Julianawg 147 Volendam North Holland 1131 DH",
    "addr:housenumber":"147",
    "addr:postcode":"1131 dh",
    "iso:country":"NL",
    "sg:address":"Julianawg 147",
    "sg:city":"Volendam",
    "sg:orig_category":"Keukens",
    "sg:phone":"+31 299 350 300",
    "sg:postcode":"1131 DH",
    "sg:province":"North Holland",
    "wof:name":"Gbm",
    "wof:placetype":"venue"
},
  "geometry": {"coordinates":[5.071785,52.496269],"type":"Point"}
}