{
  "type": "Feature",
  "properties": {
    "addr:full":"Kruidenhof 7 Diemen North Holland 1112 NV",
    "addr:housenumber":"7",
    "addr:postcode":"1112 nv",
    "addr:street":"Kruidenhof",
    "iso:country":"NL",
    "sg:address":"Kruidenhof 7",
    "sg:city":"Diemen",
    "sg:classifiers":[
        {
            "category":"Food & Beverages",
            "subcategory":"Fruits & Vegetables",
            "type":"Retail Goods"
        }
    ],
    "sg:phone":"+31 20 698 0890",
    "sg:postcode":"1112 NV",
    "sg:province":"North Holland",
    "sg:tags":[
        "groenten"
    ],
    "wof:name":"J. Muus Groente En Fruit",
    "wof:placetype":"venue"
},
  "geometry": {"coordinates":[4.958002,52.334496],"type":"Point"}
}