{
  "type": "Feature",
  "properties": {
    "addr:full":"Zeearend 12 Almelo NL.08 7609 PT",
    "addr:housenumber":"12;nl.08",
    "addr:postcode":"7609 pt",
    "addr:street":"Zeearend",
    "iso:country":"NL",
    "sg:address":"Zeearend 12",
    "sg:city":"Almelo",
    "sg:orig_category":"Werving And Selectie Van Tijdelijk Personeel And Uitzendkantoren",
    "sg:phone":"+31 546 821 840",
    "sg:postcode":"7609 PT",
    "sg:province":"NL.08",
    "wof:name":"Creyf'S Select",
    "wof:placetype":"venue"
},
  "geometry": {"coordinates":[6.6400461197,52.3393554688],"type":"Point"}
}