{
  "type": "Feature",
  "properties": {
    "addr:full":"Grotendorst 8 Broek Op Langedyk North Holland 1721 CW",
    "addr:housenumber":"8",
    "addr:postcode":"1721 cw",
    "addr:street":"Grotendorst;Op Langedyk North",
    "iso:country":"NL",
    "sg:address":"Grotendorst 8",
    "sg:city":"Broek Op Langedyk",
    "sg:orig_category":"Loodgieters",
    "sg:phone":"+31 226 316 444",
    "sg:postcode":"1721 CW",
    "sg:province":"North Holland",
    "wof:name":"Poll Bv, Installatiebedrijf V/D",
    "wof:placetype":"venue"
},
  "geometry": {"coordinates":[4.798759,52.678623],"type":"Point"}
}