{
  "type": "Feature",
  "properties": {
    "iso:country":"NL",
    "sg:address":"Vresselseweg 73",
    "sg:city":"Sint Oedenrode",
    "sg:orig_category":"Diverse Grafische Activiteiten",
    "sg:phone":"+31 499 473 867",
    "sg:postcode":"5491 PB",
    "sg:province":"North Brabant",
    "wof:name":"Katelijne De Neeve",
    "wof:placetype":"venue"
},
  "geometry": {"coordinates":[5.509875,51.532413],"type":"Point"}
}