{
  "type": "Feature",
  "properties": {
    "addr:full":"Raadhuispln 13 Best Noord-Brabant 5683 EB",
    "addr:housenumber":"13",
    "addr:postcode":"5683 eb",
    "addr:street":"Raadhuispln",
    "iso:country":"NL",
    "sg:address":"Raadhuispln 13",
    "sg:city":"Best",
    "sg:orig_category":"Verlichting",
    "sg:phone":"+31 499 399 000",
    "sg:postcode":"5683 EB",
    "sg:province":"Noord-Brabant",
    "wof:name":"Bruin Verlichting Best",
    "wof:placetype":"venue"
},
  "geometry": {"coordinates":[-101.618134,31.224251],"type":"Point"}
}