{
  "type": "Feature",
  "properties": {
    "iso:country":"NL",
    "sg:address":"Schelde 30",
    "sg:city":"Deurne",
    "sg:classifiers":[
        {
            "category":"Fast Food",
            "type":"Food & Drink"
        }
    ],
    "sg:phone":"+31 493 316 195",
    "sg:postcode":"5751 VH",
    "sg:province":"North Brabant",
    "sg:tags":[
        "afhaal",
        "restaurant"
    ],
    "wof:name":"Cafetaria 'T Hofke",
    "wof:placetype":"venue"
},
  "geometry": {"coordinates":[5.803597,51.456383],"type":"Point"}
}