{
  "type": "Feature",
  "properties": {
    "addr:full":"Goudseplein 256 Rotterdam South Holland 3031 ZH",
    "addr:housenumber":"256",
    "addr:postcode":"3031 zh",
    "addr:street":"Goudseplein",
    "iso:country":"NL",
    "sg:address":"Goudseplein 256",
    "sg:city":"Rotterdam",
    "sg:orig_category":"Kappers",
    "sg:phone":"+31 10 414 2692",
    "sg:postcode":"3031 ZH",
    "sg:province":"South Holland",
    "wof:name":"Dameskapsalon Rubroek",
    "wof:placetype":"venue"
},
  "geometry": {"coordinates":[4.4902319908,51.9283676147],"type":"Point"}
}