{
  "type": "Feature",
  "properties": {
    "addr:full":"Industrieweg 9 Oirschot Noord-Brabant 5688 DP",
    "addr:housenumber":"9",
    "addr:postcode":"5688 dp",
    "addr:street":"Industrieweg",
    "iso:country":"NL",
    "sg:address":"Industrieweg 9",
    "sg:city":"Oirschot",
    "sg:orig_category":"Meubelzaken, Woning- And Keukeninrichting",
    "sg:phone":"+31 499 571 580",
    "sg:postcode":"5688 DP",
    "sg:province":"Noord-Brabant",
    "wof:name":"B En G Meubelen Bv",
    "wof:placetype":"venue"
},
  "geometry": {"coordinates":[5.32343,51.502598],"type":"Point"}
}