{
  "type": "Feature",
  "properties": {
    "iso:country":"NL",
    "sg:address":"Heiligharn 242",
    "sg:city":"Den Helder",
    "sg:orig_category":"Verenigingen En Stichtingen",
    "sg:phone":"+31 223 635 150",
    "sg:postcode":"1785 ST",
    "sg:province":"Noord-Holland",
    "wof:name":"Samen Sterker De Schooten",
    "wof:placetype":"venue"
},
  "geometry": {"coordinates":[4.773366,52.935902],"type":"Point"}
}