{
  "type": "Feature",
  "properties": {
    "addr:full":"Molenstr 2 Winssen Gelderland 6645 BT",
    "addr:housenumber":"2",
    "addr:postcode":"6645 bt",
    "addr:street":"Molenstr;Gelderland",
    "iso:country":"NL",
    "sg:address":"Molenstr 2",
    "sg:city":"Winssen",
    "sg:orig_category":"Kappers",
    "sg:phone":"+31 487 521 413",
    "sg:postcode":"6645 BT",
    "sg:province":"Gelderland",
    "wof:name":"Yvon, Knipboetiek",
    "wof:placetype":"venue"
},
  "geometry": {"coordinates":[5.70616,51.883274],"type":"Point"}
}