{
  "type": "Feature",
  "properties": {
    "addr:full":"Iepenrode 28 Leiden Zuid-Holland 2317 BL",
    "addr:housenumber":"28",
    "addr:postcode":"2317 bl",
    "addr:street":"Iepenrode",
    "iso:country":"NL",
    "sg:address":"Iepenrode 28",
    "sg:city":"Leiden",
    "sg:orig_category":"Fotojournalisten Freelance",
    "sg:phone":"+31 71 521 1626",
    "sg:postcode":"2317 BL",
    "sg:province":"Zuid-Holland",
    "wof:name":"P Schipper",
    "wof:placetype":"venue"
},
  "geometry": {"coordinates":[4.500315,52.173717],"type":"Point"}
}