{
  "type": "Feature",
  "properties": {
    "addr:full":"Samanthagang 6 Zoetermeer Zuid-Holland 2719 CJ",
    "addr:housenumber":"6",
    "addr:postcode":"2719 cj",
    "addr:street":"Samanthagang",
    "iso:country":"NL",
    "sg:address":"Samanthagang 6",
    "sg:city":"Zoetermeer",
    "sg:orig_category":"Fotozaken",
    "sg:phone":"+31 79 361 6461",
    "sg:postcode":"2719 CJ",
    "sg:province":"Zuid-Holland",
    "wof:name":"Bos, Huub",
    "wof:placetype":"venue"
},
  "geometry": {"coordinates":[4.475991,52.043636],"type":"Point"}
}