{
  "type": "Feature",
  "properties": {
    "addr:full":"Dr Bouwdykstr 2B Zoeterwoude Zuid-Holland 2381 CA",
    "addr:housenumber":"2b",
    "addr:postcode":"2381 ca",
    "iso:country":"NL",
    "sg:address":"Dr Bouwdykstr 2B",
    "sg:city":"Zoeterwoude",
    "sg:orig_category":"Pensioenen",
    "sg:phone":"+31 71 580 1246",
    "sg:postcode":"2381 CA",
    "sg:province":"Zuid-Holland",
    "sg:website":"http://www.paardekooper-advies.nl",
    "wof:name":"Paardekooper Advies",
    "wof:placetype":"venue"
},
  "geometry": {"coordinates":[4.495484,52.121399],"type":"Point"}
}