{
  "type": "Feature",
  "properties": {
    "iso:country":"NL",
    "sg:address":"Poortersdreef 23",
    "sg:city":"Amersfoort",
    "sg:orig_category":"Adviesbureaus",
    "sg:phone":"+31 33 456 9470",
    "sg:postcode":"3824 DL",
    "sg:province":"Utrecht",
    "sg:website":"http://www.torquit.nl",
    "wof:name":"Torquit",
    "wof:placetype":"venue"
},
  "geometry": {"coordinates":[5.378372,52.195648],"type":"Point"}
}