{
  "type": "Feature",
  "properties": {
    "addr:full":"Kanaalpark 159 Leiden Zuid-Holland 2321 JW",
    "addr:housenumber":"159",
    "addr:postcode":"2321 jw",
    "addr:street":"Kanaalpark",
    "iso:country":"NL",
    "sg:address":"Kanaalpark 159",
    "sg:city":"Leiden",
    "sg:orig_category":"Technische Studies And Onderzoek",
    "sg:phone":"+31 71 579 2444",
    "sg:postcode":"2321 JW",
    "sg:province":"Zuid-Holland",
    "wof:name":"Nem Bv",
    "wof:placetype":"venue"
},
  "geometry": {"coordinates":[4.495374,52.144325],"type":"Point"}
}