{
  "type": "Feature",
  "properties": {
    "addr:full":"Tuinbouwland 3 Hindeloopen Provincie Friesland 8713 JW",
    "addr:housenumber":"3",
    "addr:postcode":"8713 jw",
    "addr:street":"Tuinbouwland;Provincie Friesland",
    "iso:country":"NL",
    "sg:address":"Tuinbouwland 3",
    "sg:city":"Hindeloopen",
    "sg:orig_category":"Visspeciaalzaken",
    "sg:phone":"+31 514 522 212",
    "sg:postcode":"8713 JW",
    "sg:province":"Provincie Friesland",
    "wof:name":"Visrokerij Hoekstra",
    "wof:placetype":"venue"
},
  "geometry": {"coordinates":[5.408847,52.941101],"type":"Point"}
}