{
  "type": "Feature",
  "properties": {
    "iso:country":"NL",
    "sg:address":"Tuinbouwland 3",
    "sg:city":"Hindeloopen",
    "sg:orig_category":"Visspeciaalzaken",
    "sg:phone":"+31 514 522 212",
    "sg:postcode":"8713 JW",
    "sg:province":"Provincie Friesland",
    "wof:name":"Visrokerij Hoekstra",
    "wof:placetype":"venue"
},
  "geometry": {"coordinates":[5.408847,52.941101],"type":"Point"}
}