{
  "type": "Feature",
  "properties": {
    "addr:full":"Distelwg 79 Amsterdam Noord-Holland 1031 HD",
    "addr:housenumber":"79",
    "addr:postcode":"1031 hd",
    "addr:street":"Distelwg",
    "iso:country":"NL",
    "sg:address":"Distelwg 79",
    "sg:city":"Amsterdam",
    "sg:orig_category":"Watersportartikelen",
    "sg:phone":"+31 20 636 1996",
    "sg:postcode":"1031 HD",
    "sg:province":"Noord-Holland",
    "sg:website":"http://www.riendewolf.nl",
    "wof:name":"Rien De Wolf",
    "wof:placetype":"venue"
},
  "geometry": {"coordinates":[4.9072809219,52.3915061951],"type":"Point"}
}