{
  "type": "Feature",
  "properties": {
    "iso:country":"NL",
    "sg:address":"Surinamestr 17",
    "sg:city":"Denhaag",
    "sg:orig_category":"Onroerende Goederen",
    "sg:phone":"+31 70 346 8323",
    "sg:postcode":"2585 GG",
    "sg:province":"Zuid-Holland",
    "wof:name":"Nieuwe Uitleg Bv",
    "wof:placetype":"venue"
},
  "geometry": {"coordinates":[4.307852,52.089935],"type":"Point"}
}