{
  "type": "Feature",
  "properties": {
    "addr:full":"Bolwerk 17A Appingedam Groningen 9901 GA",
    "addr:housenumber":"17a",
    "addr:postcode":"9901 ga",
    "addr:street":"Bolwerk",
    "iso:country":"NL",
    "sg:address":"Bolwerk 17A",
    "sg:city":"Appingedam",
    "sg:classifiers":[
        {
            "category":"Food & Beverages",
            "subcategory":"Fruits & Vegetables",
            "type":"Retail Goods"
        }
    ],
    "sg:phone":"+31 596 680 218",
    "sg:postcode":"9901 GA",
    "sg:province":"Groningen",
    "sg:tags":[
        "groenten"
    ],
    "wof:name":"Oscar'S Groentetuin",
    "wof:placetype":"venue"
},
  "geometry": {"coordinates":[6.853963,53.322338],"type":"Point"}
}