{
  "type": "Feature",
  "properties": {
    "addr:full":"Hoffmansweg 12 Vriezenveen Overijssel 7671 SM",
    "addr:housenumber":"12",
    "addr:postcode":"7671 sm",
    "addr:street":"Hoffmansweg",
    "iso:country":"NL",
    "sg:address":"Hoffmansweg 12",
    "sg:city":"Vriezenveen",
    "sg:orig_category":"Diverse Dierenfokkers",
    "sg:phone":"+31 546 658 786",
    "sg:postcode":"7671 SM",
    "sg:province":"Overijssel",
    "wof:name":"Fa Goossen Meijer En Grob",
    "wof:placetype":"venue"
},
  "geometry": {"coordinates":[6.633534,52.437855],"type":"Point"}
}