{
  "type": "Feature",
  "properties": {
    "addr:full":"Emmawg 5 Kortenhoef North Holland 1241 LE",
    "addr:housenumber":"5",
    "addr:postcode":"1241 le",
    "addr:street":"Emmawg",
    "iso:country":"NL",
    "sg:address":"Emmawg 5",
    "sg:city":"Kortenhoef",
    "sg:orig_category":"Fietsen En Bromfietsen",
    "sg:phone":"+31 35 582 4749",
    "sg:postcode":"1241 LE",
    "sg:province":"North Holland",
    "wof:name":"Jongh, W De",
    "wof:placetype":"venue"
},
  "geometry": {"coordinates":[5.120952,52.237785],"type":"Point"}
}