{
  "type": "Feature",
  "properties": {
    "addr:full":"Lange Nieuwstraat 451 Ijmuiden North Holland 1971 GE",
    "addr:housenumber":"451",
    "addr:postcode":"1971",
    "addr:street":"Lange Nieuwstraat",
    "iso:country":"NL",
    "sg:address":"Lange Nieuwstraat 451",
    "sg:city":"Ijmuiden",
    "sg:classifiers":[
        {
            "category":"Food & Beverages",
            "subcategory":"Fruits & Vegetables",
            "type":"Retail Goods"
        }
    ],
    "sg:phone":"+31 255 536 661",
    "sg:postcode":"1971 GE",
    "sg:province":"North Holland",
    "sg:tags":[
        "groenten"
    ],
    "wof:name":"Firma A.J. Hermans",
    "wof:placetype":"venue"
},
  "geometry": {"coordinates":[4.618629,52.458557],"type":"Point"}
}