{
  "type": "Feature",
  "properties": {
    "iso:country":"NL",
    "sg:address":"Dommer V Poldersveldtwg 71",
    "sg:city":"Nijmegen",
    "sg:orig_category":"Kinderopvang Behalve Thuis",
    "sg:phone":"+31 24 324 3795",
    "sg:postcode":"6523 CW",
    "sg:province":"Gelderland",
    "wof:name":"Poespas",
    "wof:placetype":"venue"
},
  "geometry": {"coordinates":[5.881865,51.834942],"type":"Point"}
}