{
  "type": "Feature",
  "properties": {
    "addr:full":"Vincent Cleerdinlaan 8 Waalre North Brabant 5582 EK",
    "addr:housenumber":"8",
    "addr:postcode":"5582 ek",
    "addr:street":"Vincent Cleerdinlaan",
    "iso:country":"NL",
    "sg:address":"Vincent Cleerdinlaan 8",
    "sg:city":"Waalre",
    "sg:orig_category":"Verzekeringen",
    "sg:phone":"+31 40 221 8818",
    "sg:postcode":"5582 EK",
    "sg:province":"North Brabant",
    "wof:name":"Scheffers Verzekeringen",
    "wof:placetype":"venue"
},
  "geometry": {"coordinates":[5.464454,51.39439],"type":"Point"}
}