{
  "type": "Feature",
  "properties": {
    "addr:full":"Grondhuttenwg 2A Bentelo Overijssel 7497 NE",
    "addr:housenumber":"2a",
    "addr:postcode":"7497 ne",
    "addr:street":"Grondhuttenwg",
    "iso:country":"NL",
    "sg:address":"Grondhuttenwg 2A",
    "sg:city":"Bentelo",
    "sg:orig_category":"Administratie- En Boekhoudkantoren",
    "sg:phone":"+31 547 292 153",
    "sg:postcode":"7497 NE",
    "sg:province":"Overijssel",
    "wof:name":"Ermena Support",
    "wof:placetype":"venue"
},
  "geometry": {"coordinates":[6.686215,52.22488],"type":"Point"}
}