{
  "type": "Feature",
  "properties": {
    "iso:country":"NL",
    "sg:address":"Sint Jansgildestraat 46",
    "sg:city":"Beek Gem Bergh",
    "sg:orig_category":"Banken And Kredietinstellingen",
    "sg:phone":"+31 316 531 355",
    "sg:postcode":"7037 AX",
    "sg:province":"Gelderland",
    "wof:name":"Postkantoor",
    "wof:placetype":"venue"
},
  "geometry": {"coordinates":[6.190664,51.908569],"type":"Point"}
}