{
  "type": "Feature",
  "properties": {
    "addr:full":"Sint Jansgildestraat 46 Beek Gem Bergh Gelderland 7037 AX",
    "addr:housenumber":"46",
    "addr:postcode":"7037 ax",
    "addr:street":"Sint Jansgildestraat",
    "iso:country":"NL",
    "sg:address":"Sint Jansgildestraat 46",
    "sg:city":"Beek Gem Bergh",
    "sg:orig_category":"Banken And Kredietinstellingen",
    "sg:phone":"+31 316 531 355",
    "sg:postcode":"7037 AX",
    "sg:province":"Gelderland",
    "wof:name":"Postkantoor",
    "wof:placetype":"venue"
},
  "geometry": {"coordinates":[6.190664,51.908569],"type":"Point"}
}