{
  "type": "Feature",
  "properties": {
    "addr:full":"Grutto 12 Castricum North Holland 1902 KV",
    "addr:housenumber":"12",
    "addr:postcode":"1902 kv",
    "addr:street":"Grutto",
    "iso:country":"NL",
    "sg:address":"Grutto 12",
    "sg:city":"Castricum",
    "sg:orig_category":"Adviesbureaus Bouwkosten",
    "sg:phone":"+31 251 651 335",
    "sg:postcode":"1902 KV",
    "sg:province":"North Holland",
    "wof:name":"Heijne, H A B",
    "wof:placetype":"venue"
},
  "geometry": {"coordinates":[4.682167,52.559151],"type":"Point"}
}