{
  "type": "Feature",
  "properties": {
    "iso:country":"NL",
    "sg:address":"Beekstraat 19",
    "sg:city":"Epe",
    "sg:orig_category":"Bedrijfs- And Managementsconsultants",
    "sg:phone":"+31 578 627 404",
    "sg:postcode":"8162 HA",
    "sg:province":"Gelderland",
    "wof:name":"Atrias Omp",
    "wof:placetype":"venue"
},
  "geometry": {"coordinates":[5.979339,52.347561],"type":"Point"}
}