{
  "type": "Feature",
  "properties": {
    "addr:full":"Het Kompas 35 Amersfoort Utrecht 3823 SJ",
    "addr:housenumber":"35",
    "addr:postcode":"3823",
    "addr:street":"Het Kompas",
    "iso:country":"NL",
    "sg:address":"Het Kompas 35",
    "sg:city":"Amersfoort",
    "sg:orig_category":"Verzekeringen",
    "sg:phone":"+31 33 455 5494",
    "sg:postcode":"3823 SJ",
    "sg:province":"Utrecht",
    "wof:name":"Bemiddelingsbureau D.J. Van Den Hoorn",
    "wof:placetype":"venue"
},
  "geometry": {"coordinates":[5.390539,52.19416],"type":"Point"}
}