{
  "type": "Feature",
  "properties": {
    "addr:full":"H K Pootpln 1 Schipluiden South Holland 2636 GJ",
    "addr:housenumber":"1",
    "addr:postcode":"2636 gj",
    "addr:street":"Pootpln",
    "iso:country":"NL",
    "sg:address":"H K Pootpln 1",
    "sg:city":"Schipluiden",
    "sg:orig_category":"Facilitaire Dienstverlening",
    "sg:phone":"+31 15 380 9435",
    "sg:postcode":"2636 GJ",
    "sg:province":"South Holland",
    "sg:website":"http://www.issues.nl",
    "wof:name":"Issues",
    "wof:placetype":"venue"
},
  "geometry": {"coordinates":[4.316758,51.975834],"type":"Point"}
}