{
  "type": "Feature",
  "properties": {
    "addr:full":"Benedenrijweg 227 Ridderkerk Zuid-Holland 2983 GC",
    "addr:housenumber":"227",
    "addr:postcode":"2983 gc",
    "addr:street":"Benedenrijweg",
    "iso:country":"NL",
    "sg:address":"Benedenrijweg 227",
    "sg:city":"Ridderkerk",
    "sg:orig_category":"Wegen And Sportterreinen",
    "sg:phone":"+31 180 416 269",
    "sg:postcode":"2983 GC",
    "sg:province":"Zuid-Holland",
    "wof:name":"Ten Oever & Stierman Vof",
    "wof:placetype":"venue"
},
  "geometry": {"coordinates":[4.6117339134,51.8813667297],"type":"Point"}
}