{
  "type": "Feature",
  "properties": {
    "addr:full":"Herenstraat 31 Voorburg Zuid-Holland 2271 CA",
    "addr:housenumber":"31",
    "addr:postcode":"2271 ca",
    "addr:street":"Herenstraat",
    "iso:country":"NL",
    "sg:address":"Herenstraat 31",
    "sg:city":"Voorburg",
    "sg:orig_category":"Binnenhuisarchitecten",
    "sg:phone":"+31 70 386 3481",
    "sg:postcode":"2271 CA",
    "sg:province":"Zuid-Holland",
    "wof:name":"Declemy Decorateurs",
    "wof:placetype":"venue"
},
  "geometry": {"coordinates":[4.365867,52.068775],"type":"Point"}
}