{
  "type": "Feature",
  "properties": {
    "iso:country":"NL",
    "sg:address":"Milenagang 8",
    "sg:city":"Zoetermeer",
    "sg:orig_category":"Gespecialiseerde Bouw",
    "sg:phone":"+31 79 361 9669",
    "sg:postcode":"2719 CM",
    "sg:province":"Zuid-Holland",
    "wof:name":"Ro Azier",
    "wof:placetype":"venue"
},
  "geometry": {"coordinates":[4.480772,52.043373],"type":"Point"}
}