{
  "type": "Feature",
  "properties": {
    "addr:full":"Julianawg 3 St Geertruid Limburg 6265 AH",
    "addr:housenumber":"3",
    "addr:postcode":"6265 ah",
    "addr:street":"Julianawg",
    "iso:country":"NL",
    "sg:address":"Julianawg 3",
    "sg:city":"St Geertruid",
    "sg:orig_category":"Organisatiebureaus",
    "sg:phone":"+31 43 408 3140",
    "sg:postcode":"6265 AH",
    "sg:province":"Limburg",
    "wof:name":"Frambach, E",
    "wof:placetype":"venue"
},
  "geometry": {"coordinates":[5.7656412125,50.7952384949],"type":"Point"}
}