{
  "type": "Feature",
  "properties": {
    "addr:full":"Velletriweg 21 Oudenbosch North Brabant 4731 DP",
    "addr:housenumber":"21",
    "addr:postcode":"4731 dp",
    "addr:street":"Velletriweg",
    "iso:country":"NL",
    "sg:address":"Velletriweg 21",
    "sg:city":"Oudenbosch",
    "sg:orig_category":"Kantoor- And Schoolbenodigdheden Gh",
    "sg:phone":"+31 165 314 754",
    "sg:postcode":"4731 DP",
    "sg:province":"North Brabant",
    "wof:name":"Label Service",
    "wof:placetype":"venue"
},
  "geometry": {"coordinates":[4.5499458313,51.5924758911],"type":"Point"}
}