{
  "type": "Feature",
  "properties": {
    "addr:full":"Poeldk 12C Breukelen Ut Utrecht 3621 CZ",
    "addr:housenumber":"12c",
    "addr:postcode":"3621",
    "addr:street":"Poeldk",
    "iso:country":"NL",
    "sg:address":"Poeldk 12C",
    "sg:city":"Breukelen Ut",
    "sg:orig_category":"Open Haarden",
    "sg:phone":"+31 346 264 950",
    "sg:postcode":"3621 CZ",
    "sg:province":"Utrecht",
    "wof:name":"Flame Design",
    "wof:placetype":"venue"
},
  "geometry": {"coordinates":[4.997067,52.16851],"type":"Point"}
}