{
  "type": "Feature",
  "properties": {
    "addr:full":"Voshol 2 Boskoop South Holland 2771 NK",
    "addr:housenumber":"2",
    "addr:postcode":"2771 nk",
    "addr:street":"Voshol",
    "iso:country":"NL",
    "sg:address":"Voshol 2",
    "sg:city":"Boskoop",
    "sg:orig_category":"Architecten",
    "sg:phone":"+31 172 218 006",
    "sg:postcode":"2771 NK",
    "sg:province":"South Holland",
    "wof:name":"Adrem Tuinen",
    "wof:placetype":"venue"
},
  "geometry": {"coordinates":[4.703459,52.089481],"type":"Point"}
}