{
  "type": "Feature",
  "properties": {
    "addr:full":"De Kuiper 9 Heeze Noord-Brabant 5591 MZ",
    "addr:housenumber":"9",
    "addr:postcode":"5591 mz",
    "addr:street":"De Kuiper",
    "iso:country":"NL",
    "sg:address":"De Kuiper 9",
    "sg:city":"Heeze",
    "sg:orig_category":"Juridische Adviseurs",
    "sg:phone":"+31 40 226 0760",
    "sg:postcode":"5591 MZ",
    "sg:province":"Noord-Brabant",
    "wof:name":"Foxen",
    "wof:placetype":"venue"
},
  "geometry": {"coordinates":[5.564233,51.384907],"type":"Point"}
}