{
  "type": "Feature",
  "properties": {
    "addr:full":"Grt Hertoginneln 8 V S Gravenhage Zuid-Holland 2517 EG",
    "addr:housenumber":"8",
    "addr:postcode":"2517 eg",
    "addr:street":"Hertoginneln;S",
    "iso:country":"NL",
    "sg:address":"Grt Hertoginneln 8 V",
    "sg:city":"S Gravenhage",
    "sg:orig_category":"Schilders",
    "sg:phone":"+31 70 364 5896",
    "sg:postcode":"2517 EG",
    "sg:province":"Zuid-Holland",
    "wof:name":"Alphen Schilderwerken Bv, Van",
    "wof:placetype":"venue"
},
  "geometry": {"coordinates":[4.28708,52.08667],"type":"Point"}
}