{
  "type": "Feature",
  "properties": {
    "addr:full":"Hessenweg 98 Stoutenburg Utrecht 3835 PL",
    "addr:housenumber":"98",
    "addr:postcode":"3835 pl",
    "addr:street":"Hessenweg",
    "iso:country":"NL",
    "sg:address":"Hessenweg 98",
    "sg:city":"Stoutenburg",
    "sg:orig_category":"Huizensloop And Bouwrijp Maken",
    "sg:phone":"+31 342 451 249",
    "sg:postcode":"3835 PL",
    "sg:province":"Utrecht",
    "wof:name":"W W Vd Hengel",
    "wof:placetype":"venue"
},
  "geometry": {"coordinates":[5.450081,52.147491],"type":"Point"}
}