{
  "type": "Feature",
  "properties": {
    "addr:full":"Wethouder Lanenstraat 8 Roosendaal Noord-Brabant 4703 HS",
    "addr:housenumber":"8",
    "addr:postcode":"4703 hs",
    "addr:street":"Wethouder Lanenstraat",
    "iso:country":"NL",
    "sg:address":"Wethouder Lanenstraat 8",
    "sg:city":"Roosendaal",
    "sg:orig_category":"Verhuisdiensten",
    "sg:phone":"+31 165 564 488",
    "sg:postcode":"4703 HS",
    "sg:province":"Noord-Brabant",
    "wof:name":"W. Van Egeraat Bv",
    "wof:placetype":"venue"
},
  "geometry": {"coordinates":[4.44797,51.536644],"type":"Point"}
}