{
  "type": "Feature",
  "properties": {
    "iso:country":"NL",
    "sg:address":"Schuringsedk 94",
    "sg:city":"Numansdorp",
    "sg:orig_category":"Beeldende Kunstenaars",
    "sg:phone":"+31 186 653 056",
    "sg:postcode":"3281 KR",
    "sg:province":"Zuid-Holland",
    "wof:name":"Eugenie Degenaar",
    "wof:placetype":"venue"
},
  "geometry": {"coordinates":[4.47274,51.729477],"type":"Point"}
}