{
  "type": "Feature",
  "properties": {
    "addr:full":"Postbus 130 Hoofddorp Noord-Holland 2130 AC",
    "addr:housenumber":"130",
    "addr:postcode":"2130 ac",
    "addr:street":"Postbus",
    "iso:country":"NL",
    "sg:address":"Postbus 130",
    "sg:city":"Hoofddorp",
    "sg:orig_category":"Juridische Adviseurs",
    "sg:phone":"+31 23 565 7656",
    "sg:postcode":"2130 AC",
    "sg:province":"Noord-Holland",
    "wof:name":"Lawwatch Nederland",
    "wof:placetype":"venue"
},
  "geometry": {"coordinates":[4.68729,52.308708],"type":"Point"}
}