{
  "type": "Feature",
  "properties": {
    "addr:full":"Ceintuurbaan 288 Amsterdam Noord-Holland 1072 GK",
    "addr:housenumber":"288",
    "addr:postcode":"1072 gk",
    "addr:street":"Ceintuurbaan",
    "iso:country":"NL",
    "sg:address":"Ceintuurbaan 288",
    "sg:city":"Amsterdam",
    "sg:orig_category":"Banken And Kredietinstellingen",
    "sg:phone":"+31 20 664 2942",
    "sg:postcode":"1072 GK",
    "sg:province":"Noord-Holland",
    "wof:name":"Postkantoor",
    "wof:placetype":"venue"
},
  "geometry": {"coordinates":[4.891605,52.352703],"type":"Point"}
}