{
  "type": "Feature",
  "properties": {
    "addr:full":"Roekln 2 Lieshout North Brabant 5737 PD",
    "addr:housenumber":"2",
    "addr:postcode":"5737 pd",
    "addr:street":"Roekln",
    "iso:country":"NL",
    "sg:address":"Roekln 2",
    "sg:city":"Lieshout",
    "sg:orig_category":"Beeldende Kunstenaars",
    "sg:phone":"+31 499 425 050",
    "sg:postcode":"5737 PD",
    "sg:province":"North Brabant",
    "sg:website":"http://www.wimheesakkers.com",
    "wof:name":"Heesakkers, Wim",
    "wof:placetype":"venue"
},
  "geometry": {"coordinates":[5.595371,51.517857],"type":"Point"}
}