{
  "type": "Feature",
  "properties": {
    "addr:full":"De Vlotkampweg 42 Nijmegen Gelderland 6545 AG",
    "addr:housenumber":"42",
    "addr:postcode":"6545",
    "addr:street":"De Vlotkampweg;Gelderland",
    "iso:country":"NL",
    "sg:address":"De Vlotkampweg 42",
    "sg:city":"Nijmegen",
    "sg:orig_category":"Autokeuringen",
    "sg:phone":"+31 24 377 2400",
    "sg:postcode":"6545 AG",
    "sg:province":"Gelderland",
    "wof:name":"M.A.A.M. Bisselink",
    "wof:placetype":"venue"
},
  "geometry": {"coordinates":[5.809794,51.847515],"type":"Point"}
}