{
  "type": "Feature",
  "properties": {
    "addr:full":"Zaagmolenkade 11 Gouda South Holland 2807 EP",
    "addr:housenumber":"11",
    "addr:postcode":"2807 ep",
    "addr:street":"Zaagmolenkade",
    "iso:country":"NL",
    "sg:address":"Zaagmolenkade 11",
    "sg:city":"Gouda",
    "sg:orig_category":"Bedrijfs- And Managementsconsultants",
    "sg:phone":"+31 182 581 958",
    "sg:postcode":"2807 EP",
    "sg:province":"South Holland",
    "wof:name":"Van Setten Management Consulting Bv",
    "wof:placetype":"venue"
},
  "geometry": {"coordinates":[4.743658,52.008823],"type":"Point"}
}