{
  "type": "Feature",
  "properties": {
    "iso:country":"NL",
    "sg:address":"Roggeakker 6",
    "sg:city":"Doorn",
    "sg:orig_category":"Bedrijfs- And Managementsconsultants",
    "sg:phone":"+31 343 415 224",
    "sg:postcode":"3941 LC",
    "sg:province":"Utrecht",
    "wof:name":"Praxim",
    "wof:placetype":"venue"
},
  "geometry": {"coordinates":[5.345076,52.02903],"type":"Point"}
}