{
  "type": "Feature",
  "properties": {
    "addr:full":"Kattenburg 48 Druten Gelderland 6651 AP",
    "addr:housenumber":"48",
    "addr:postcode":"6651 ap",
    "addr:street":"Kattenburg",
    "iso:country":"NL",
    "sg:address":"Kattenburg 48",
    "sg:city":"Druten",
    "sg:orig_category":"Verzekerings- Maatschappijen",
    "sg:phone":"+31 345 588 030",
    "sg:postcode":"6651 AP",
    "sg:province":"Gelderland",
    "wof:name":"Univ\u00e9 Rivierenland",
    "wof:placetype":"venue"
},
  "geometry": {"coordinates":[5.608006,51.891994],"type":"Point"}
}