{
  "type": "Feature",
  "properties": {
    "addr:full":"Lutterveldweg 11 Tiel Gelderland 4005 LD",
    "addr:housenumber":"11",
    "addr:postcode":"4005 ld",
    "addr:street":"Lutterveldweg;Gelderland",
    "iso:country":"NL",
    "sg:address":"Lutterveldweg 11",
    "sg:city":"Tiel",
    "sg:orig_category":"Autokeuringen",
    "sg:phone":"+31 344 630 729",
    "sg:postcode":"4005 LD",
    "sg:province":"Gelderland",
    "wof:name":"Van Dooijeweert Auto'S",
    "wof:placetype":"venue"
},
  "geometry": {"coordinates":[5.4469,51.898655],"type":"Point"}
}