{
  "type": "Feature",
  "properties": {
    "addr:full":"Postbus 1735 Maastricht Limburg 6201 BS",
    "addr:housenumber":"1735",
    "addr:postcode":"6201 bs",
    "addr:street":"Postbus",
    "iso:country":"NL",
    "sg:address":"Postbus 1735",
    "sg:city":"Maastricht",
    "sg:orig_category":"Verenigingen En Stichtingen",
    "sg:phone":"+31 43 325 2724",
    "sg:postcode":"6201 BS",
    "sg:province":"Limburg",
    "wof:name":"Vrienden Van Het Bonnefantenmuseum, Ver Van",
    "wof:placetype":"venue"
},
  "geometry": {"coordinates":[5.68726,50.84985],"type":"Point"}
}