{
  "type": "Feature",
  "properties": {
    "iso:country":"NL",
    "sg:address":"Melkpad 5",
    "sg:city":"Hilversum",
    "sg:orig_category":"Diverse Zakelijke Dienstverlening",
    "sg:phone":"+31 35 623 3999",
    "sg:postcode":"1217 JZ",
    "sg:province":"North Holland",
    "wof:name":"Woonhuis Holland Og Bv",
    "wof:placetype":"venue"
},
  "geometry": {"coordinates":[5.175307,52.226974],"type":"Point"}
}