{
  "type": "Feature",
  "properties": {
    "iso:country":"NL",
    "sg:address":"Provincialewg 75",
    "sg:city":"Maren Kessel",
    "sg:orig_category":"Projectontwikkeling",
    "sg:phone":"+31 412 479 701",
    "sg:postcode":"5398 JJ",
    "sg:province":"Noord-Brabant",
    "wof:name":"Top Center Ned",
    "wof:placetype":"venue"
},
  "geometry": {"coordinates":[5.384677,51.794178],"type":"Point"}
}