{
  "type": "Feature",
  "properties": {
    "addr:full":"A Kuyperstr 10 Twello Gelderland 7391 KR",
    "addr:housenumber":"10",
    "addr:postcode":"7391 kr",
    "addr:street":"Gelderland",
    "iso:country":"NL",
    "sg:address":"A Kuyperstr 10",
    "sg:city":"Twello",
    "sg:orig_category":"Orgels",
    "sg:phone":"+31 571 272 030",
    "sg:postcode":"7391 KR",
    "sg:province":"Gelderland",
    "wof:name":"Neonvox",
    "wof:placetype":"venue"
},
  "geometry": {"coordinates":[6.1029171944,52.2319984436],"type":"Point"}
}