{
  "type": "Feature",
  "properties": {
    "addr:full":"Parklaan 269 Culemborg Gelderland 4102 EJ",
    "addr:housenumber":"269",
    "addr:postcode":"4102 ej",
    "addr:street":"Parklaan;Gelderland",
    "iso:country":"NL",
    "sg:address":"Parklaan 269",
    "sg:city":"Culemborg",
    "sg:orig_category":"Boekhouders",
    "sg:phone":"+31 345 513 629",
    "sg:postcode":"4102 EJ",
    "sg:province":"Gelderland",
    "wof:name":"Administratiekantoor De Ruiter",
    "wof:placetype":"venue"
},
  "geometry": {"coordinates":[5.244898,51.950611],"type":"Point"}
}