{
  "type": "Feature",
  "properties": {
    "addr:full":"Eekterwg 36 Oosterwolde Gld Gelderland 8097 PE",
    "addr:housenumber":"36",
    "addr:postcode":"8097 pe",
    "addr:street":"Eekterwg",
    "iso:country":"NL",
    "sg:address":"Eekterwg 36",
    "sg:city":"Oosterwolde Gld",
    "sg:orig_category":"Pluimveebedrijven En -Handelaren",
    "sg:phone":"+31 525 621 631",
    "sg:postcode":"8097 PE",
    "sg:province":"Gelderland",
    "wof:name":"Veen, K Van 'T",
    "wof:placetype":"venue"
},
  "geometry": {"coordinates":[5.8895688057,52.4575767517],"type":"Point"}
}