{
  "type": "Feature",
  "properties": {
    "iso:country":"NL",
    "sg:address":"Mijtenstraat 145",
    "sg:city":"Den Haag",
    "sg:orig_category":"Verhuur Audiovisuele Apparatuur",
    "sg:phone":"+31 6 51136073",
    "sg:postcode":"2525 VC",
    "sg:province":"Zuid-Holland",
    "wof:name":"Pro Acoustic",
    "wof:placetype":"venue"
},
  "geometry": {"coordinates":[4.305295,52.061932],"type":"Point"}
}