{
  "type": "Feature",
  "properties": {
    "addr:full":"Koningswg 1 Harlingen Provincie Friesland 8861 KN",
    "addr:housenumber":"1",
    "addr:postcode":"8861 kn",
    "addr:street":"Koningswg;Provincie Friesland",
    "iso:country":"NL",
    "sg:address":"Koningswg 1",
    "sg:city":"Harlingen",
    "sg:orig_category":"Metaalbewerking",
    "sg:phone":"+31 517 579 580",
    "sg:postcode":"8861 KN",
    "sg:province":"Provincie Friesland",
    "wof:name":"Dijkstra",
    "wof:placetype":"venue"
},
  "geometry": {"coordinates":[5.443745,53.174812],"type":"Point"}
}