{
  "type": "Feature",
  "properties": {
    "addr:full":"Zandwg 3 Wyk By Duurstede Utrecht 3962 EA",
    "addr:housenumber":"3",
    "addr:postcode":"duurstede;3962 ea",
    "addr:street":"Zandwg",
    "iso:country":"NL",
    "sg:address":"Zandwg 3",
    "sg:city":"Wyk By Duurstede",
    "sg:orig_category":"Bloemen En Planten",
    "sg:phone":"+31 343 592 244",
    "sg:postcode":"3962 EA",
    "sg:province":"Utrecht",
    "sg:website":"http://www.ganzeman.nl",
    "wof:name":"Henk Ganzeman Bloemsierkunst",
    "wof:placetype":"venue"
},
  "geometry": {"coordinates":[5.3754,51.985378],"type":"Point"}
}