{
  "type": "Feature",
  "properties": {
    "iso:country":"NL",
    "sg:address":"Westeinde 59",
    "sg:city":"Lekkerkerk",
    "sg:orig_category":"Koeriersdiensten",
    "sg:phone":"+31 180 661 387",
    "sg:postcode":"2941 EE",
    "sg:province":"Zuid-Holland",
    "wof:name":"Lkd Koeriersdiensten",
    "wof:placetype":"venue"
},
  "geometry": {"coordinates":[4.67714,51.893681],"type":"Point"}
}