{
  "type": "Feature",
  "properties": {
    "addr:full":"Weth Driessenstr 149 Amsterdam Zuidoost Noord-Holland 1107 XJ",
    "addr:housenumber":"149",
    "addr:postcode":"zuidoost;1107 xj",
    "addr:street":"Weth Driessenstr",
    "iso:country":"NL",
    "sg:address":"Weth Driessenstr 149",
    "sg:city":"Amsterdam Zuidoost",
    "sg:orig_category":"Koffie En Thee - Apparaten En Artikelen",
    "sg:phone":"+31 20 696 6121",
    "sg:postcode":"1107 XJ",
    "sg:province":"Noord-Holland",
    "wof:name":"Bosio",
    "wof:placetype":"venue"
},
  "geometry": {"coordinates":[4.98602,52.291813],"type":"Point"}
}