{
  "type": "Feature",
  "properties": {
    "addr:full":"Heuvel Galerie 223 Eindhoven North Brabant 5611 DK",
    "addr:housenumber":"223",
    "addr:postcode":"5611 dk",
    "addr:street":"Heuvel Galerie",
    "iso:country":"NL",
    "sg:address":"Heuvel Galerie 223",
    "sg:city":"Eindhoven",
    "sg:orig_category":"Kinderkleding",
    "sg:phone":"+31 40 246 4635",
    "sg:postcode":"5611 DK",
    "sg:province":"North Brabant",
    "wof:name":"Mexx",
    "wof:placetype":"venue"
},
  "geometry": {"coordinates":[5.480784,51.43821],"type":"Point"}
}