{
  "type": "Feature",
  "properties": {
    "addr:full":"Van Oosthuijzelaan 7A 'S Gravenzande Zuid-Holland 2691 NJ",
    "addr:housenumber":"7a ';2691",
    "addr:postcode":"nj",
    "addr:street":"Van Oosthuijzelaan",
    "iso:country":"NL",
    "sg:address":"Van Oosthuijzelaan 7A",
    "sg:city":"'S Gravenzande",
    "sg:orig_category":"Bloemen And Planten Gh",
    "sg:phone":"+31 174 413 728",
    "sg:postcode":"2691 NJ",
    "sg:province":"Zuid-Holland",
    "wof:name":"W. Prins",
    "wof:placetype":"venue"
},
  "geometry": {"coordinates":[4.182481,51.976692],"type":"Point"}
}