{
  "type": "Feature",
  "properties": {
    "addr:full":"B J Schurerwg 14 Surhuisterveen Friesland 9231 CE",
    "addr:housenumber":"14",
    "addr:postcode":"9231 ce",
    "addr:street":"B",
    "iso:country":"NL",
    "sg:address":"B J Schurerwg 14",
    "sg:city":"Surhuisterveen",
    "sg:orig_category":"Bibliotheken En Leeszalen Openbare",
    "sg:phone":"+31 512 368 550",
    "sg:postcode":"9231 CE",
    "sg:province":"Friesland",
    "wof:name":"Openb Bibliotheek",
    "wof:placetype":"venue"
},
  "geometry": {"coordinates":[6.168885,53.182072],"type":"Point"}
}