{
  "type": "Feature",
  "properties": {
    "addr:full":"Griend 5 Diemen Noord-Holland 1112 KW",
    "addr:housenumber":"5",
    "addr:postcode":"1112 kw",
    "addr:street":"Griend",
    "iso:country":"NL",
    "sg:address":"Griend 5",
    "sg:city":"Diemen",
    "sg:orig_category":"Geschenkartikelen",
    "sg:phone":"+31 20 683 1674",
    "sg:postcode":"1112 KW",
    "sg:province":"Noord-Holland",
    "sg:website":"http://www.irmiz.com",
    "wof:name":"Irmiz",
    "wof:placetype":"venue"
},
  "geometry": {"coordinates":[4.946816,52.329014],"type":"Point"}
}