{
  "type": "Feature",
  "properties": {
    "addr:full":"Ellermanstr 12 Amsterdam Noord-Holland 1099 BW",
    "addr:housenumber":"12",
    "addr:postcode":"1099 bw",
    "addr:street":"Ellermanstr",
    "iso:country":"NL",
    "sg:address":"Ellermanstr 12",
    "sg:city":"Amsterdam",
    "sg:orig_category":"Adviesbureaus Bedrijfsorganisatie",
    "sg:phone":"+31 20 462 7482",
    "sg:postcode":"1099 BW",
    "sg:province":"Noord-Holland",
    "wof:name":"Mozaiqnet Bv",
    "wof:placetype":"venue"
},
  "geometry": {"coordinates":[4.930862,52.326847],"type":"Point"}
}