{
  "type": "Feature",
  "properties": {
    "addr:full":"Stadsplein 1 Capelle A/D Ijssel Zuid-Holland 2903 HH",
    "addr:housenumber":"1;a / d",
    "addr:postcode":"2903 hh",
    "addr:street":"Stadsplein",
    "iso:country":"NL",
    "sg:address":"Stadsplein 1",
    "sg:city":"Capelle A/D Ijssel",
    "sg:orig_category":"Banken And Kredietinstellingen",
    "sg:phone":"+31 10 450 9840",
    "sg:postcode":"2903 HH",
    "sg:province":"Zuid-Holland",
    "wof:name":"Fortis Bank",
    "wof:placetype":"venue"
},
  "geometry": {"coordinates":[4.587788,51.931461],"type":"Point"}
}