{
  "type": "Feature",
  "properties": {
    "addr:full":"Postbus 138 Putten Gelderland 3880 AC",
    "addr:housenumber":"138",
    "addr:postcode":"3880 ac",
    "addr:street":"Postbus;Gelderland",
    "iso:country":"NL",
    "sg:address":"Postbus 138",
    "sg:city":"Putten",
    "sg:orig_category":"Administratie- En Boekhoudkantoren",
    "sg:phone":"+31 6 51611292",
    "sg:postcode":"3880 AC",
    "sg:province":"Gelderland",
    "wof:name":"Hemel Bv, Van",
    "wof:placetype":"venue"
},
  "geometry": {"coordinates":[5.605482,52.257221],"type":"Point"}
}