{
  "type": "Feature",
  "properties": {
    "addr:full":"Eendrachtstr 25 Wormer Noord-Holland 1531 DT",
    "addr:housenumber":"25",
    "addr:postcode":"1531 dt",
    "addr:street":"Eendrachtstr",
    "iso:country":"NL",
    "sg:address":"Eendrachtstr 25",
    "sg:city":"Wormer",
    "sg:orig_category":"Sanitaire Artikelen",
    "sg:phone":"+31 75 642 6909",
    "sg:postcode":"1531 DT",
    "sg:province":"Noord-Holland",
    "wof:name":"Meijns Bv",
    "wof:placetype":"venue"
},
  "geometry": {"coordinates":[4.812407,52.487774],"type":"Point"}
}