{
  "type": "Feature",
  "properties": {
    "iso:country":"NL",
    "sg:address":"Veerdam 1",
    "sg:city":"Rotterdam",
    "sg:orig_category":"Sportverenigingen En Ontspannings- Verenigingen",
    "sg:phone":"+31 10 413 8514",
    "sg:postcode":"3016 DD",
    "sg:province":"South Holland",
    "sg:website":"http://www.de-maas.nl/default.htm",
    "wof:name":"Maas Roei- En Zeilver, De",
    "wof:placetype":"venue"
},
  "geometry": {"coordinates":[4.479303,51.907616],"type":"Point"}
}