{
  "type": "Feature",
  "properties": {
    "addr:full":"Dukaatruwe 26 Maastricht Limburg 6218 CS",
    "addr:housenumber":"26",
    "addr:postcode":"6218 cs",
    "addr:street":"Dukaatruwe",
    "iso:country":"NL",
    "sg:address":"Dukaatruwe 26",
    "sg:city":"Maastricht",
    "sg:orig_category":"Modevakscholen",
    "sg:phone":"+31 43 347 3028",
    "sg:postcode":"6218 CS",
    "sg:province":"Limburg",
    "wof:name":"Theunissen, M",
    "wof:placetype":"venue"
},
  "geometry": {"coordinates":[5.658777,50.863426],"type":"Point"}
}