{
  "type": "Feature",
  "properties": {
    "addr:full":"Tolbergcentrum 55 Roosendaal Noord-Brabant 4708 GB",
    "addr:housenumber":"55",
    "addr:postcode":"4708 gb",
    "addr:street":"Tolbergcentrum",
    "iso:country":"NL",
    "sg:address":"Tolbergcentrum 55",
    "sg:city":"Roosendaal",
    "sg:orig_category":"Peuterspeelzalen",
    "sg:phone":"+31 165 561 682",
    "sg:postcode":"4708 GB",
    "sg:province":"Noord-Brabant",
    "wof:name":"Oebele",
    "wof:placetype":"venue"
},
  "geometry": {"coordinates":[4.438694,51.513397],"type":"Point"}
}