{
  "type": "Feature",
  "properties": {
    "addr:full":"Havinghastraat 58 Alkmaar North Holland 1817 DA",
    "addr:housenumber":"58",
    "addr:postcode":"1817 da",
    "addr:street":"Havinghastraat",
    "iso:country":"NL",
    "sg:address":"Havinghastraat 58",
    "sg:city":"Alkmaar",
    "sg:orig_category":"Boekenuitgeverijen",
    "sg:phone":"+31 72 515 2222",
    "sg:postcode":"1817 DA",
    "sg:province":"North Holland",
    "wof:name":"Drukkerij Ter Burg Bv",
    "wof:placetype":"venue"
},
  "geometry": {"coordinates":[4.739827,52.647297],"type":"Point"}
}