{
  "type": "Feature",
  "properties": {
    "iso:country":"NL",
    "sg:address":"Steegstr 22",
    "sg:city":"Meyel",
    "sg:orig_category":"Logopedisten",
    "sg:phone":"+31 77 466 4035",
    "sg:postcode":"5768 AV",
    "sg:province":"Limburg",
    "wof:name":"Stappers-Naus",
    "wof:placetype":"venue"
},
  "geometry": {"coordinates":[5.88575,51.34428],"type":"Point"}
}