{
  "type": "Feature",
  "properties": {
    "addr:full":"Meeuwenln 66 Lisse Zuid-Holland 2162 HH",
    "addr:housenumber":"66",
    "addr:postcode":"2162 hh",
    "addr:street":"Meeuwenln",
    "iso:country":"NL",
    "sg:address":"Meeuwenln 66",
    "sg:city":"Lisse",
    "sg:orig_category":"Adviesbureaus Bedrijfsorganisatie",
    "sg:phone":"+31 252 411 242",
    "sg:postcode":"2162 HH",
    "sg:province":"Zuid-Holland",
    "wof:name":"Kleijhorst Bv",
    "wof:placetype":"venue"
},
  "geometry": {"coordinates":[4.557672,52.252674],"type":"Point"}
}