{
  "type": "Feature",
  "properties": {
    "addr:full":"Postbus 3422 S Hertogenbosch 5203 DK",
    "addr:housenumber":"3422",
    "addr:postcode":"5203 dk",
    "addr:street":"Postbus;S Hertogenbosch",
    "iso:country":"NL",
    "sg:address":"Postbus 3422",
    "sg:city":"S Hertogenbosch",
    "sg:orig_category":"Scholen: Hoger Beroepsonderwijs",
    "sg:phone":"+31 73 623 0223",
    "sg:postcode":"5203 DK",
    "wof:name":"Middelbare Vakopleiding Metaal",
    "wof:placetype":"venue"
},
  "geometry": {"coordinates":[5.30421,51.68922],"type":"Point"}
}