{
  "type": "Feature",
  "properties": {
    "addr:full":"A J Ernststr 115 Amsterdam Noord-Holland 1083 GR",
    "addr:housenumber":"115",
    "addr:postcode":"1083",
    "addr:street":"A",
    "iso:country":"NL",
    "sg:address":"A J Ernststr 115",
    "sg:city":"Amsterdam",
    "sg:orig_category":"Modeontwerpen",
    "sg:phone":"+31 20 644 0261",
    "sg:postcode":"1083 GR",
    "sg:province":"Noord-Holland",
    "wof:name":"Sips, I L M",
    "wof:placetype":"venue"
},
  "geometry": {"coordinates":[4.88921,52.33028],"type":"Point"}
}