{
  "type": "Feature",
  "properties": {
    "addr:full":"Het Spant 6 Amersfoort Utrecht 3823 VC",
    "addr:housenumber":"6",
    "addr:postcode":"3823 vc",
    "addr:street":"Het Spant",
    "iso:country":"NL",
    "sg:address":"Het Spant 6",
    "sg:city":"Amersfoort",
    "sg:orig_category":"Verenigingen En Stichtingen",
    "sg:phone":"+31 33 455 1874",
    "sg:postcode":"3823 VC",
    "sg:province":"Utrecht",
    "wof:name":"Fokus",
    "wof:placetype":"venue"
},
  "geometry": {"coordinates":[5.401919,52.190884],"type":"Point"}
}