{
  "type": "Feature",
  "properties": {
    "iso:country":"NL",
    "sg:address":"Kanaalwg 34C",
    "sg:city":"S Gravenhage",
    "sg:orig_category":"Adviesbureaus Bouwkunde",
    "sg:phone":"+31 70 338 3205",
    "sg:postcode":"2584 CK",
    "sg:province":"Zuid-Holland",
    "wof:name":"Newsolutions",
    "wof:placetype":"venue"
},
  "geometry": {"coordinates":[4.28131,52.103199],"type":"Point"}
}