{
  "type": "Feature",
  "properties": {
    "addr:full":"Admiraal De Ruijterweg 162 Amsterdam Noord-Holland 1056 GW",
    "addr:housenumber":"162",
    "addr:postcode":"1056 gw",
    "addr:street":"Admiraal De Ruijterweg",
    "iso:country":"NL",
    "sg:address":"Admiraal De Ruijterweg 162",
    "sg:city":"Amsterdam",
    "sg:classifiers":[
        {
            "category":"Retail",
            "subcategory":"Photofinishing",
            "type":"Services"
        }
    ],
    "sg:phone":"+31 20 612 2105",
    "sg:postcode":"1056 GW",
    "sg:province":"Noord-Holland",
    "sg:tags":[
        "foto",
        "film"
    ],
    "wof:name":"Firma Gebr. Zaalberg",
    "wof:placetype":"venue"
},
  "geometry": {"coordinates":[4.858817,52.37458],"type":"Point"}
}