{
  "type": "Feature",
  "properties": {
    "addr:full":"Balistraat 15 Dordrecht South Holland 3312 VA",
    "addr:housenumber":"15",
    "addr:postcode":"3312",
    "addr:street":"Balistraat",
    "iso:country":"NL",
    "sg:address":"Balistraat 15",
    "sg:city":"Dordrecht",
    "sg:orig_category":"Autokeuringen",
    "sg:phone":"+31 78 631 2020",
    "sg:postcode":"3312 VA",
    "sg:province":"South Holland",
    "wof:name":"Angrolease",
    "wof:placetype":"venue"
},
  "geometry": {"coordinates":[4.681168,51.80751],"type":"Point"}
}