{
  "type": "Feature",
  "properties": {
    "addr:full":"De La Sallestraat 4 Heesch North Brabant 5384 NK",
    "addr:housenumber":"4",
    "addr:postcode":"5384 nk",
    "addr:street":"De La Sallestraat",
    "iso:country":"NL",
    "sg:address":"De La Sallestraat 4",
    "sg:city":"Heesch",
    "sg:orig_category":"Boekhouders",
    "sg:phone":"+31 412 456 294",
    "sg:postcode":"5384 NK",
    "sg:province":"North Brabant",
    "wof:name":"J. De Rijk",
    "wof:placetype":"venue"
},
  "geometry": {"coordinates":[5.521233,51.734417],"type":"Point"}
}