{
  "type": "Feature",
  "properties": {
    "iso:country":"NL",
    "sg:address":"Monnikenweg 11",
    "sg:city":"Nijbroek",
    "sg:orig_category":"Granen, Zaden And Diervoeders Gh",
    "sg:phone":"+31 571 291 465",
    "sg:postcode":"7397 NB",
    "sg:province":"Gelderland",
    "wof:name":"R Van Eek",
    "wof:placetype":"venue"
},
  "geometry": {"coordinates":[6.05145,52.287704],"type":"Point"}
}