{
  "type": "Feature",
  "properties": {
    "addr:full":"Telegraafstr 50A Tilburg Noord-Brabant 5038 BM",
    "addr:housenumber":"50a",
    "addr:postcode":"5038 bm",
    "addr:street":"Telegraafstr",
    "iso:country":"NL",
    "sg:address":"Telegraafstr 50A",
    "sg:city":"Tilburg",
    "sg:orig_category":"Verenigingen En Stichtingen",
    "sg:phone":"+31 13 536 3418",
    "sg:postcode":"5038 BM",
    "sg:province":"Noord-Brabant",
    "wof:name":"A-One Dispuut Van Het Tsc St Olof",
    "wof:placetype":"venue"
},
  "geometry": {"coordinates":[5.087907,51.558517],"type":"Point"}
}