{
  "type": "Feature",
  "properties": {
    "addr:full":"Edisonstr 16F Gouda Zuid-Holland 2809 PB",
    "addr:housenumber":"16f",
    "addr:postcode":"2809 pb",
    "iso:country":"NL",
    "sg:address":"Edisonstr 16F",
    "sg:city":"Gouda",
    "sg:classifiers":[
        {
            "category":"Shopping",
            "subcategory":"Adult",
            "type":"Retail Goods"
        }
    ],
    "sg:phone":"+31 182 684 045",
    "sg:postcode":"2809 PB",
    "sg:province":"Zuid-Holland",
    "sg:tags":[
        "lingerie",
        "en",
        "tricotage"
    ],
    "wof:name":"Livera",
    "wof:placetype":"venue"
},
  "geometry": {"coordinates":[4.690901,52.00499],"type":"Point"}
}