{
  "type": "Feature",
  "properties": {
    "addr:full":"L De Colignystr 8 Eindhoven Noord-Brabant 5616 ER",
    "addr:housenumber":"8",
    "addr:postcode":"5616 er",
    "addr:street":"L;Colignystr",
    "iso:country":"NL",
    "sg:address":"L De Colignystr 8",
    "sg:city":"Eindhoven",
    "sg:orig_category":"Adviesbureaus Elektrotechniek",
    "sg:phone":"+31 40 251 8659",
    "sg:postcode":"5616 ER",
    "sg:province":"Noord-Brabant",
    "wof:name":"Latour, T",
    "wof:placetype":"venue"
},
  "geometry": {"coordinates":[5.461249,51.431324],"type":"Point"}
}