{
  "type": "Feature",
  "properties": {
    "addr:full":"Ommerkanaal Oost 31 Ommen NL.08 7731 TS",
    "addr:housenumber":"31;nl.08",
    "addr:postcode":"7731 ts",
    "addr:street":"Ommerkanaal Oost",
    "iso:country":"NL",
    "sg:address":"Ommerkanaal Oost 31",
    "sg:city":"Ommen",
    "sg:classifiers":[
        {
            "category":"Education",
            "subcategory":"Preschool",
            "type":"Public Place"
        }
    ],
    "sg:phone":"+31 523 613 164",
    "sg:postcode":"7731 TS",
    "sg:province":"NL.08",
    "sg:tags":[
        "kleuteronderwijs",
        "basis-"
    ],
    "wof:name":"Christelijk Nationale School Ommerkanaal",
    "wof:placetype":"venue"
},
  "geometry": {"coordinates":[6.435463,52.565292],"type":"Point"}
}