{
  "type": "Feature",
  "properties": {
    "addr:full":"Franciscushof 1 Zeeland North Brabant 5411 BK",
    "addr:housenumber":"1",
    "addr:postcode":"5411 bk",
    "addr:street":"Franciscushof",
    "iso:country":"NL",
    "sg:address":"Franciscushof 1",
    "sg:city":"Zeeland",
    "sg:orig_category":"Bejaarden - Verzorgingstehuizen",
    "sg:phone":"+31 486 458 585",
    "sg:postcode":"5411 BK",
    "sg:province":"North Brabant",
    "wof:name":"Compostella",
    "wof:placetype":"venue"
},
  "geometry": {"coordinates":[5.674939,51.695713],"type":"Point"}
}