{
  "type": "Feature",
  "properties": {
    "addr:full":"V Heukelomstr 4 Weert Limburg 6006 JS",
    "addr:housenumber":"4",
    "addr:postcode":"6006 js",
    "addr:street":"Heukelomstr",
    "iso:country":"NL",
    "sg:address":"V Heukelomstr 4",
    "sg:city":"Weert",
    "sg:orig_category":"Administratie- En Boekhoudkantoren",
    "sg:phone":"+31 495 521 192",
    "sg:postcode":"6006 JS",
    "sg:province":"Limburg",
    "wof:name":"Adacta",
    "wof:placetype":"venue"
},
  "geometry": {"coordinates":[5.6822,51.22126],"type":"Point"}
}