{
  "type": "Feature",
  "properties": {
    "addr:full":"Emopad 29 Geldrop Noord-Brabant 5663 PA",
    "addr:housenumber":"29",
    "addr:postcode":"5663 pa",
    "addr:street":"Emopad",
    "iso:country":"NL",
    "sg:address":"Emopad 29",
    "sg:city":"Geldrop",
    "sg:orig_category":"Heftrucks",
    "sg:phone":"+31 40 289 4080",
    "sg:postcode":"5663 PA",
    "sg:province":"Noord-Brabant",
    "sg:website":"http://www.heftruckmarkt.nl",
    "wof:name":"Bedrijfswagencollectief Nederland",
    "wof:placetype":"venue"
},
  "geometry": {"coordinates":[5.55426,51.412251],"type":"Point"}
}