{
  "type": "Feature",
  "properties": {
    "addr:full":"Oosteinderlaan 32 Hillegom Zuid-Holland 2181 HJ",
    "addr:housenumber":"32",
    "addr:postcode":"2181 hj",
    "addr:street":"Oosteinderlaan",
    "iso:country":"NL",
    "sg:address":"Oosteinderlaan 32",
    "sg:city":"Hillegom",
    "sg:orig_category":"Bloemen And Planten",
    "sg:phone":"+31 252 515 255",
    "sg:postcode":"2181 HJ",
    "sg:province":"Zuid-Holland",
    "wof:name":"S.J. Spijker Bv",
    "wof:placetype":"venue"
},
  "geometry": {"coordinates":[4.592514,52.30954],"type":"Point"}
}