{
  "type": "Feature",
  "properties": {
    "addr:full":"Winkelveldstr 21 Venlo Limburg 5916 NX",
    "addr:housenumber":"21",
    "addr:postcode":"5916 nx",
    "addr:street":"Winkelveldstr",
    "iso:country":"NL",
    "sg:address":"Winkelveldstr 21",
    "sg:city":"Venlo",
    "sg:orig_category":"Houtgroothandel",
    "sg:phone":"+31 77 354 2866",
    "sg:postcode":"5916 NX",
    "sg:province":"Limburg",
    "wof:name":"Venlo Bv",
    "wof:placetype":"venue"
},
  "geometry": {"coordinates":[6.184459,51.384869],"type":"Point"}
}