{
  "type": "Feature",
  "properties": {
    "iso:country":"NL",
    "sg:address":"Dorpsstr 31-33",
    "sg:city":"Putten",
    "sg:orig_category":"Meubelen",
    "sg:phone":"+31 341 360 136",
    "sg:postcode":"3881 BA",
    "sg:province":"Gelderland",
    "sg:website":"http://www.stoelenhuys.nl",
    "wof:name":"Stoelenhuys Putten, Het",
    "wof:placetype":"venue"
},
  "geometry": {"coordinates":[5.605191,52.260319],"type":"Point"}
}