{
  "type": "Feature",
  "properties": {
    "addr:full":"Zuidergrachtswal 13 Leeuwarden Friesland 8933 AD",
    "addr:housenumber":"13",
    "addr:postcode":"8933 ad",
    "addr:street":"Zuidergrachtswal",
    "iso:country":"NL",
    "sg:address":"Zuidergrachtswal 13",
    "sg:city":"Leeuwarden",
    "sg:orig_category":"Antiquiteiten",
    "sg:phone":"+31 58 213 7751",
    "sg:postcode":"8933 AD",
    "sg:province":"Friesland",
    "wof:name":"Anna",
    "wof:placetype":"venue"
},
  "geometry": {"coordinates":[5.800747,53.199005],"type":"Point"}
}