{
  "type": "Feature",
  "properties": {
    "iso:country":"NL",
    "sg:address":"Kloosterstr 68",
    "sg:city":"Helmond",
    "sg:orig_category":"Loopbaanbegeleiding",
    "sg:phone":"+31 492 537 930",
    "sg:postcode":"5708 GM",
    "sg:province":"Noord-Brabant",
    "sg:website":"http://www.simonisenpartners.nl",
    "wof:name":"Simonis & Partners Bv",
    "wof:placetype":"venue"
},
  "geometry": {"coordinates":[5.62169,51.487671],"type":"Point"}
}