{
  "type": "Feature",
  "properties": {
    "addr:full":"Dukdalfwg 50-52 Amsterdam Noord-Holland 1041 BE",
    "addr:housenumber":"50-52",
    "addr:postcode":"1041",
    "iso:country":"NL",
    "sg:address":"Dukdalfwg 50-52",
    "sg:city":"Amsterdam",
    "sg:orig_category":"Verhuizingen",
    "sg:phone":"+31 20 614 9393",
    "sg:postcode":"1041 BE",
    "sg:province":"Noord-Holland",
    "wof:name":"Duim Verhuizingen Bv",
    "wof:placetype":"venue"
},
  "geometry": {"coordinates":[-94.58503,38.350479],"type":"Point"}
}