{
  "type": "Feature",
  "properties": {
    "addr:full":"Vechtstraat 38 Zwolle Overijssel 8021 AX",
    "addr:housenumber":"38",
    "addr:postcode":"8021 ax",
    "addr:street":"Vechtstraat",
    "iso:country":"NL",
    "sg:address":"Vechtstraat 38",
    "sg:city":"Zwolle",
    "sg:orig_category":"Meubelzaken, Woning- And Keukeninrichting",
    "sg:phone":"+31 38 454 4778",
    "sg:postcode":"8021 AX",
    "sg:province":"Overijssel",
    "wof:name":"Firma L. Van Dijk En Zn",
    "wof:placetype":"venue"
},
  "geometry": {"coordinates":[6.105812,52.515511],"type":"Point"}
}