{
  "type": "Feature",
  "properties": {
    "addr:full":"Rumpenerstr 65 Brunssum Limburg 6443 CC",
    "addr:housenumber":"65",
    "addr:postcode":"6443 cc",
    "addr:street":"Rumpenerstr",
    "iso:country":"NL",
    "sg:address":"Rumpenerstr 65",
    "sg:city":"Brunssum",
    "sg:orig_category":"Fotoreportages",
    "sg:phone":"+31 45 525 2098",
    "sg:postcode":"6443 CC",
    "sg:province":"Limburg",
    "wof:name":"Holtus",
    "wof:placetype":"venue"
},
  "geometry": {"coordinates":[5.969262,50.940468],"type":"Point"}
}