{
  "type": "Feature",
  "properties": {
    "addr:full":"Lepelaar 24 Mydrecht Utrecht 3641 TN",
    "addr:housenumber":"24",
    "addr:postcode":"3641",
    "addr:street":"Lepelaar",
    "iso:country":"NL",
    "sg:address":"Lepelaar 24",
    "sg:city":"Mydrecht",
    "sg:orig_category":"Woningstoffeerders",
    "sg:phone":"+31 297 286 468",
    "sg:postcode":"3641 TN",
    "sg:province":"Utrecht",
    "wof:name":"Stoesser, B",
    "wof:placetype":"venue"
},
  "geometry": {"coordinates":[4.8518061638,52.2022781372],"type":"Point"}
}