{
  "type": "Feature",
  "properties": {
    "iso:country":"NL",
    "sg:address":"Javastr 18",
    "sg:city":"Amsterdam",
    "sg:orig_category":"Fietsen En Bromfietsen",
    "sg:phone":"+31 20 665 1877",
    "sg:postcode":"1094 HG",
    "sg:province":"North Holland",
    "wof:name":"Martens, Harry",
    "wof:placetype":"venue"
},
  "geometry": {"coordinates":[4.932483,52.363396],"type":"Point"}
}