{
  "type": "Feature",
  "properties": {
    "addr:full":"Steentilstr 26 Groningen Groningen 9711 GM",
    "addr:housenumber":"26",
    "addr:postcode":"9711 gm",
    "addr:street":"Steentilstr",
    "iso:country":"NL",
    "sg:address":"Steentilstr 26",
    "sg:city":"Groningen",
    "sg:orig_category":"Geluidsinstallaties",
    "sg:phone":"+31 50 313 0760",
    "sg:postcode":"9711 GM",
    "sg:province":"Groningen",
    "wof:name":"Groef, De",
    "wof:placetype":"venue"
},
  "geometry": {"coordinates":[6.572228,53.216442],"type":"Point"}
}