{
  "type": "Feature",
  "properties": {
    "addr:full":"Van Brerostraat 87 Apeldoorn Gelderland 7312 VL",
    "addr:housenumber":"87",
    "addr:postcode":"7312 vl",
    "addr:street":"Van Brerostraat;Gelderland",
    "iso:country":"NL",
    "sg:address":"Van Brerostraat 87",
    "sg:city":"Apeldoorn",
    "sg:orig_category":"Paramedische Behandelingen",
    "sg:phone":"+31 55 356 0712",
    "sg:postcode":"7312 VL",
    "sg:province":"Gelderland",
    "wof:name":"Privazorg Apeldoorn E O",
    "wof:placetype":"venue"
},
  "geometry": {"coordinates":[5.944759,52.205177],"type":"Point"}
}