{
  "type": "Feature",
  "properties": {
    "iso:country":"NL",
    "sg:address":"Dikkeboomweg 30",
    "sg:city":"Nijmegen",
    "sg:orig_category":"Metaalbekleding And -Behandeling",
    "sg:phone":"+31 24 377 1119",
    "sg:postcode":"6542 RK",
    "sg:province":"Gelderland",
    "wof:name":"Firma H.J. Schamp En Zoon",
    "wof:placetype":"venue"
},
  "geometry": {"coordinates":[5.837794,51.84042],"type":"Point"}
}