{
  "type": "Feature",
  "properties": {
    "addr:full":"Gen V Haersolteln 40 Eindhoven Noord-Brabant 5623 JK",
    "addr:housenumber":"40",
    "addr:postcode":"5623 jk",
    "addr:street":"Gen;Haersolteln",
    "iso:country":"NL",
    "sg:address":"Gen V Haersolteln 40",
    "sg:city":"Eindhoven",
    "sg:orig_category":"Administratie- En Boekhoudkantoren",
    "sg:phone":"+31 40 243 2603",
    "sg:postcode":"5623 JK",
    "sg:province":"Noord-Brabant",
    "wof:name":"Fekken, J H",
    "wof:placetype":"venue"
},
  "geometry": {"coordinates":[5.47708,51.460041],"type":"Point"}
}