{
  "type": "Feature",
  "properties": {
    "addr:full":"Westsngl 1 Goes Zeeland 4461 DK",
    "addr:housenumber":"1",
    "addr:postcode":"4461 dk",
    "addr:street":"Westsngl",
    "iso:country":"NL",
    "sg:address":"Westsngl 1",
    "sg:city":"Goes",
    "sg:orig_category":"Partyservice",
    "sg:phone":"+31 113 232 030",
    "sg:postcode":"4461 DK",
    "sg:province":"Zeeland",
    "sg:website":"http://www.wapenvangoes.nl",
    "wof:name":"Schrijver Party- En Cateringservice",
    "wof:placetype":"venue"
},
  "geometry": {"coordinates":[-83.914169,39.768833],"type":"Point"}
}