{
  "type": "Feature",
  "properties": {
    "addr:full":"Walchersestr 59A Rotterdam Zuid-Holland 3083 NG",
    "addr:housenumber":"59a",
    "addr:postcode":"3083 ng",
    "addr:street":"Walchersestr",
    "iso:country":"NL",
    "sg:address":"Walchersestr 59A",
    "sg:city":"Rotterdam",
    "sg:orig_category":"Adviesbureaus Automatisering",
    "sg:phone":"+31 10 210 0172",
    "sg:postcode":"3083 NG",
    "sg:province":"Zuid-Holland",
    "wof:name":"Cognitio Fortes",
    "wof:placetype":"venue"
},
  "geometry": {"coordinates":[4.48469,51.887699],"type":"Point"}
}