{
  "type": "Feature",
  "properties": {
    "addr:full":"Brouwerywg 24 Domburg Zeeland 4357 CE",
    "addr:housenumber":"24",
    "addr:postcode":"4357 ce",
    "addr:street":"Brouwerywg",
    "iso:country":"NL",
    "sg:address":"Brouwerywg 24",
    "sg:city":"Domburg",
    "sg:classifiers":[
        {
            "category":"Travel",
            "subcategory":"Hotels & Motels",
            "type":"Entertainment"
        }
    ],
    "sg:phone":"+31 118 581 938",
    "sg:postcode":"4357 CE",
    "sg:province":"Zeeland",
    "wof:name":"Kijkduin",
    "wof:placetype":"venue"
},
  "geometry": {"coordinates":[3.496995,51.560493],"type":"Point"}
}