{
  "type": "Feature",
  "properties": {
    "addr:full":"Winkelerzand 37/A Winkel Noord-Holland 1731 LR",
    "addr:housenumber":"37 / a",
    "addr:postcode":"1731 lr",
    "addr:street":"Winkelerzand",
    "iso:country":"NL",
    "sg:address":"Winkelerzand 37/A",
    "sg:city":"Winkel",
    "sg:orig_category":"Adviesbureaus Werktuigbouwkunde",
    "sg:phone":"+31 224 542 789",
    "sg:postcode":"1731 LR",
    "sg:province":"Noord-Holland",
    "wof:name":"Gke",
    "wof:placetype":"venue"
},
  "geometry": {"coordinates":[-89.62237500000001,40.348873],"type":"Point"}
}