{
  "type": "Feature",
  "properties": {
    "addr:full":"Beneden Oosterd 42 Veendam Groningen 9641 JE",
    "addr:housenumber":"42",
    "addr:postcode":"9641 je",
    "addr:street":"Beneden Oosterd",
    "iso:country":"NL",
    "sg:address":"Beneden Oosterd 42",
    "sg:city":"Veendam",
    "sg:orig_category":"Zetterijen",
    "sg:phone":"+31 598 615 421",
    "sg:postcode":"9641 JE",
    "sg:province":"Groningen",
    "sg:website":"http://www.staalprepress.nl",
    "wof:name":"Staal Prepress Bv",
    "wof:placetype":"venue"
},
  "geometry": {"coordinates":[6.882477,53.106041],"type":"Point"}
}