{
  "type": "Feature",
  "properties": {
    "addr:full":"Goudsesingel 178 Rotterdam South Holland 3011 KD",
    "addr:housenumber":"178",
    "addr:postcode":"3011 kd",
    "addr:street":"Goudsesingel",
    "iso:country":"NL",
    "sg:address":"Goudsesingel 178",
    "sg:city":"Rotterdam",
    "sg:orig_category":"Werving And Selectie Van Tijdelijk Personeel And Uitzendkantoren",
    "sg:phone":"+31 10 433 3522",
    "sg:postcode":"3011 KD",
    "sg:province":"South Holland",
    "wof:name":"Teleprofs Bv",
    "wof:placetype":"venue"
},
  "geometry": {"coordinates":[4.4922418594,51.923915863],"type":"Point"}
}