{
  "type": "Feature",
  "properties": {
    "iso:country":"NL",
    "sg:address":"Ywg 96",
    "sg:city":"Zwanenburg",
    "sg:orig_category":"Autoreclame",
    "sg:phone":"+31 20 497 7164",
    "sg:postcode":"1161 GC",
    "sg:province":"Noord-Holland",
    "wof:name":"Groot Letters",
    "wof:placetype":"venue"
},
  "geometry": {"coordinates":[4.74723,52.376625],"type":"Point"}
}