{
  "type": "Feature",
  "properties": {
    "addr:full":"Werkendelsln 118 Heiloo Noord-Holland 1851 VE",
    "addr:housenumber":"118",
    "addr:postcode":"1851",
    "addr:street":"Ve",
    "iso:country":"NL",
    "sg:address":"Werkendelsln 118",
    "sg:city":"Heiloo",
    "sg:orig_category":"Koeriersdiensten",
    "sg:phone":"+31 72 533 7731",
    "sg:postcode":"1851 VE",
    "sg:province":"Noord-Holland",
    "wof:name":"Kroon, De",
    "wof:placetype":"venue"
},
  "geometry": {"coordinates":[4.713702,52.604191],"type":"Point"}
}