{
  "type": "Feature",
  "properties": {
    "addr:full":"Lindeln 30 Alblasserdam Zuid-Holland 2951 BN",
    "addr:housenumber":"30",
    "addr:postcode":"2951 bn",
    "addr:street":"Lindeln",
    "iso:country":"NL",
    "sg:address":"Lindeln 30",
    "sg:city":"Alblasserdam",
    "sg:orig_category":"Woningstoffeerders",
    "sg:phone":"+31 78 691 6536",
    "sg:postcode":"2951 BN",
    "sg:province":"Zuid-Holland",
    "wof:name":"Visser, J",
    "wof:placetype":"venue"
},
  "geometry": {"coordinates":[4.6612520218,51.8690109253],"type":"Point"}
}