{
  "type": "Feature",
  "properties": {
    "addr:full":"V Vollenhovenstr 15 Rotterdam South Holland 3016 BE",
    "addr:housenumber":"15",
    "addr:postcode":"3016",
    "iso:country":"NL",
    "sg:address":"V Vollenhovenstr 15",
    "sg:city":"Rotterdam",
    "sg:orig_category":"Kunsthandel",
    "sg:phone":"+31 10 241 0450",
    "sg:postcode":"3016 BE",
    "sg:province":"South Holland",
    "wof:name":"Smelik & Stokking",
    "wof:placetype":"venue"
},
  "geometry": {"coordinates":[4.478455,51.922836],"type":"Point"}
}