{
  "type": "Feature",
  "properties": {
    "iso:country":"NL",
    "sg:address":"Deilsegraaf 2",
    "sg:city":"Enspijk",
    "sg:orig_category":"Gespecialiseerde Voeding",
    "sg:phone":"+31 345 651 457",
    "sg:postcode":"4157 PC",
    "sg:province":"Gelderland",
    "wof:name":"De Fruitladder",
    "wof:placetype":"venue"
},
  "geometry": {"coordinates":[5.220715,51.876564],"type":"Point"}
}