{
  "type": "Feature",
  "properties": {
    "addr:full":"Eglantierhof 5 Leidschendam South Holland 2262 AS",
    "addr:housenumber":"5",
    "addr:postcode":"2262 as",
    "addr:street":"Eglantierhof",
    "iso:country":"NL",
    "sg:address":"Eglantierhof 5",
    "sg:city":"Leidschendam",
    "sg:orig_category":"Kousen En Sokken",
    "sg:phone":"+31 70 327 2573",
    "sg:postcode":"2262 AS",
    "sg:province":"South Holland",
    "wof:name":"Kousenhuis Leidsenhage",
    "wof:placetype":"venue"
},
  "geometry": {"coordinates":[4.384586,52.089962],"type":"Point"}
}