{
  "type": "Feature",
  "properties": {
    "iso:country":"NL",
    "sg:address":"Matlingeweg 43",
    "sg:city":"Rotterdam",
    "sg:orig_category":"Boekhouders",
    "sg:phone":"+31 10 415 1571",
    "sg:postcode":"3044 EV",
    "sg:province":"Zuid-Holland",
    "wof:name":"De Mark Vof",
    "wof:placetype":"venue"
},
  "geometry": {"coordinates":[4.4113,51.934517],"type":"Point"}
}