{
  "type": "Feature",
  "properties": {
    "addr:full":"Schenkeldk 10A S Gravendeel Zuid-Holland 3295 EG",
    "addr:housenumber":"10a",
    "addr:postcode":"3295 eg",
    "addr:street":"Schenkeldk;S Gravendeel",
    "iso:country":"NL",
    "sg:address":"Schenkeldk 10A",
    "sg:city":"S Gravendeel",
    "sg:classifiers":[
        {
            "category":"Animal Shelter",
            "type":"Public Place"
        }
    ],
    "sg:phone":"+31 78 673 1790",
    "sg:postcode":"3295 EG",
    "sg:province":"Zuid-Holland",
    "sg:tags":[
        "kennel"
    ],
    "wof:name":"Jos-Co-Sal",
    "wof:placetype":"venue"
},
  "geometry": {"coordinates":[4.594634,51.747192],"type":"Point"}
}