{
  "type": "Feature",
  "properties": {
    "addr:full":"Rivieradreef 9 Haarlem North Holland 2037 AC",
    "addr:housenumber":"9",
    "addr:postcode":"2037 ac",
    "addr:street":"Rivieradreef",
    "iso:country":"NL",
    "sg:address":"Rivieradreef 9",
    "sg:city":"Haarlem",
    "sg:orig_category":"Opticiens",
    "sg:phone":"+31 23 533 0076",
    "sg:postcode":"2037 AC",
    "sg:province":"North Holland",
    "wof:name":"Federmann Opticiens",
    "wof:placetype":"venue"
},
  "geometry": {"coordinates":[4.6535491943,52.3599014282],"type":"Point"}
}