{
  "type": "Feature",
  "properties": {
    "iso:country":"NL",
    "sg:address":"Parallelwg 52",
    "sg:city":"Woudenberg",
    "sg:orig_category":"Schilders",
    "sg:phone":"+31 33 286 7021",
    "sg:postcode":"3931 MT",
    "sg:province":"Utrecht",
    "sg:website":"http://www.vakwerkhuis.nl",
    "wof:name":"Boersma",
    "wof:placetype":"venue"
},
  "geometry": {"coordinates":[5.446108,52.085983],"type":"Point"}
}