{
  "type": "Feature",
  "properties": {
    "addr:full":"Kerkstraat 1 Raamsdonk Noord-Brabant 4944 XB",
    "addr:housenumber":"1",
    "addr:postcode":"4944 xb",
    "addr:street":"Kerkstraat",
    "iso:country":"NL",
    "sg:address":"Kerkstraat 1",
    "sg:city":"Raamsdonk",
    "sg:orig_category":"Discountwinkels",
    "sg:phone":"+31 162 512 829",
    "sg:postcode":"4944 XB",
    "sg:province":"Noord-Brabant",
    "wof:name":"Leemans-Niessen",
    "wof:placetype":"venue"
},
  "geometry": {"coordinates":[4.907164,51.687248],"type":"Point"}
}