{
  "type": "Feature",
  "properties": {
    "addr:full":"Ketelaarsstraat 7 Rotterdam Zuid-Holland 3011 CM",
    "addr:housenumber":"7",
    "addr:postcode":"3011 cm",
    "addr:street":"Ketelaarsstraat",
    "iso:country":"NL",
    "sg:address":"Ketelaarsstraat 7",
    "sg:city":"Rotterdam",
    "sg:orig_category":"Fitnesscentra",
    "sg:phone":"+31 10 433 0793",
    "sg:postcode":"3011 CM",
    "sg:province":"Zuid-Holland",
    "wof:name":"Sportschool Sandow C.V.",
    "wof:placetype":"venue"
},
  "geometry": {"coordinates":[4.48155,51.913914],"type":"Point"}
}