{
  "type": "Feature",
  "properties": {
    "iso:country":"NL",
    "sg:address":"Ginderover 23A",
    "sg:city":"Heeze",
    "sg:orig_category":"Administratie- En Boekhoudkantoren",
    "sg:phone":"+31 40 224 0405",
    "sg:postcode":"5591 JM",
    "sg:province":"Noord-Brabant",
    "wof:name":"Ginderover",
    "wof:placetype":"venue"
},
  "geometry": {"coordinates":[5.582436,51.373802],"type":"Point"}
}