{
  "type": "Feature",
  "properties": {
    "addr:full":"Schouwweg 32 Wassenaar Zuid-Holland 2243 BC",
    "addr:housenumber":"32",
    "addr:postcode":"2243 bc",
    "addr:street":"Schouwweg",
    "iso:country":"NL",
    "sg:address":"Schouwweg 32",
    "sg:city":"Wassenaar",
    "sg:orig_category":"Makelaars In Onroerend Goed",
    "sg:phone":"+31 70 511 9229",
    "sg:postcode":"2243 BC",
    "sg:province":"Zuid-Holland",
    "wof:name":"Bv Makelaarskantoren Paul F. De Haas & Co",
    "wof:placetype":"venue"
},
  "geometry": {"coordinates":[4.387305,52.135811],"type":"Point"}
}