{
  "type": "Feature",
  "properties": {
    "addr:full":"Ulvenhoutselaan 38 Breda Noord-Brabant 4834 MG",
    "addr:housenumber":"38",
    "addr:postcode":"4834 mg",
    "addr:street":"Ulvenhoutselaan",
    "iso:country":"NL",
    "sg:address":"Ulvenhoutselaan 38",
    "sg:city":"Breda",
    "sg:orig_category":"Paramedische Behandelingen",
    "sg:phone":"+31 76 565 6889",
    "sg:postcode":"4834 MG",
    "sg:province":"Noord-Brabant",
    "wof:name":"J.A.A.C. Stoop",
    "wof:placetype":"venue"
},
  "geometry": {"coordinates":[4.792161,51.560581],"type":"Point"}
}