{
  "type": "Feature",
  "properties": {
    "addr:full":"Kapelstraat 5 Molenschot Noord-Brabant 5124 RL",
    "addr:housenumber":"5",
    "addr:postcode":"5124 rl",
    "addr:street":"Kapelstraat",
    "iso:country":"NL",
    "sg:address":"Kapelstraat 5",
    "sg:city":"Molenschot",
    "sg:orig_category":"Overheidsdiensten",
    "sg:phone":"+31 161 411 787",
    "sg:postcode":"5124 RL",
    "sg:province":"Noord-Brabant",
    "wof:name":"Gemeenschapshuis",
    "wof:placetype":"venue"
},
  "geometry": {"coordinates":[4.8812060356,51.573135376],"type":"Point"}
}