{
  "type": "Feature",
  "properties": {
    "addr:full":"Ds T O Hylkemawg 37 Giethoorn Overijssel 8355 CE",
    "addr:housenumber":"37",
    "addr:postcode":"8355 ce",
    "addr:street":"Ds T O Hylkemawg",
    "iso:country":"NL",
    "sg:address":"Ds T O Hylkemawg 37",
    "sg:city":"Giethoorn",
    "sg:orig_category":"Vakantieverblijven",
    "sg:phone":"+31 521 361 254",
    "sg:postcode":"8355 CE",
    "sg:province":"Overijssel",
    "sg:website":"http://members.tripod.lycos.nl/Babbeltien",
    "wof:name":"Babbeltien",
    "wof:placetype":"venue"
},
  "geometry": {"coordinates":[6.085835,52.722439],"type":"Point"}
}