{
  "type": "Feature",
  "properties": {
    "iso:country":"NL",
    "sg:address":"Dorpsstr 239",
    "sg:city":"Assendelft",
    "sg:classifiers":[
        {
            "category":"Retail",
            "subcategory":"Auto Repair",
            "type":"Services"
        }
    ],
    "sg:phone":"+31 75 687 1214",
    "sg:postcode":"1566 BA",
    "sg:province":"Noord-Holland",
    "sg:tags":[
        "garage"
    ],
    "wof:name":"Metz",
    "wof:placetype":"venue"
},
  "geometry": {"coordinates":[4.734638,52.457001],"type":"Point"}
}