{
  "type": "Feature",
  "properties": {
    "addr:full":"Gerrit Van Der Veenstr 2 Leiden Zuid-Holland 2321 CD",
    "addr:housenumber":"2",
    "addr:postcode":"2321 cd",
    "addr:street":"Gerrit Van Der Veenstr",
    "iso:country":"NL",
    "sg:address":"Gerrit Van Der Veenstr 2",
    "sg:city":"Leiden",
    "sg:orig_category":"Woningbouwverenigingen",
    "sg:phone":"+31 71 579 8700",
    "sg:postcode":"2321 CD",
    "sg:province":"Zuid-Holland",
    "wof:name":"Woningbouwvereniging De Sleutels",
    "wof:placetype":"venue"
},
  "geometry": {"coordinates":[4.4798231125,52.1468200684],"type":"Point"}
}