{
  "type": "Feature",
  "properties": {
    "addr:full":"Fokkerstr 475 Schiedam Zuid-Holland 3125 BD",
    "addr:housenumber":"475",
    "addr:postcode":"3125 bd",
    "iso:country":"NL",
    "sg:address":"Fokkerstr 475",
    "sg:city":"Schiedam",
    "sg:orig_category":"Pneumatische Gereedschappen",
    "sg:phone":"+31 10 262 0844",
    "sg:postcode":"3125 BD",
    "sg:province":"Zuid-Holland",
    "sg:website":"http://www.technotrading.nl",
    "wof:name":"Technotrading Schiedam Bv",
    "wof:placetype":"venue"
},
  "geometry": {"coordinates":[4.396371,51.935673],"type":"Point"}
}