{
  "type": "Feature",
  "properties": {
    "addr:full":"Dr Holtropstr 152 Ermelo Gelderland 3851 JM",
    "addr:housenumber":"152",
    "addr:postcode":"3851 jm",
    "addr:street":"Gelderland",
    "iso:country":"NL",
    "sg:address":"Dr Holtropstr 152",
    "sg:city":"Ermelo",
    "sg:orig_category":"Kappers",
    "sg:phone":"+31 341 551 733",
    "sg:postcode":"3851 JM",
    "sg:province":"Gelderland",
    "wof:name":"Willigen, J Van",
    "wof:placetype":"venue"
},
  "geometry": {"coordinates":[5.612,52.297489],"type":"Point"}
}