{
  "type": "Feature",
  "properties": {
    "addr:full":"Pashof 11 Winterswyk British Columbia 7103 BC",
    "addr:housenumber":"11",
    "addr:postcode":"7103 bc",
    "addr:street":"Pashof",
    "iso:country":"NL",
    "sg:address":"Pashof 11",
    "sg:city":"Winterswyk",
    "sg:orig_category":"Kappers",
    "sg:phone":"+31 543 516 300",
    "sg:postcode":"7103 BC",
    "sg:province":"British Columbia",
    "wof:name":"Linda",
    "wof:placetype":"venue"
},
  "geometry": {"coordinates":[-126.555511,54.485668],"type":"Point"}
}