{
  "type": "Feature",
  "properties": {
    "addr:full":"2E Boerhaavestr 17-19 Amsterdam Noord-Holland 1091 AK",
    "addr:housenumber":"17-19",
    "addr:postcode":"1091 ak",
    "addr:street":"2E Boerhaavestr",
    "iso:country":"NL",
    "sg:address":"2E Boerhaavestr 17-19",
    "sg:city":"Amsterdam",
    "sg:classifiers":[
        {
            "category":"Retail",
            "subcategory":"Auto Repair",
            "type":"Services"
        }
    ],
    "sg:phone":"+31 20 665 3126",
    "sg:postcode":"1091 AK",
    "sg:province":"Noord-Holland",
    "sg:tags":[
        "garage"
    ],
    "wof:name":"Schnabel, Automobielbedrijf",
    "wof:placetype":"venue"
},
  "geometry": {"coordinates":[4.911902,52.359272],"type":"Point"}
}