{
  "type": "Feature",
  "properties": {
    "addr:full":"Groeneweg 71 'S Gravenzande Zuid-Holland 2691 MK",
    "addr:housenumber":"71",
    "addr:postcode":"2691",
    "addr:street":"Groeneweg;' S",
    "iso:country":"NL",
    "sg:address":"Groeneweg 71",
    "sg:city":"'S Gravenzande",
    "sg:orig_category":"Fruitteelt",
    "sg:phone":"+31 174 627 436",
    "sg:postcode":"2691 MK",
    "sg:province":"Zuid-Holland",
    "wof:name":"Firma P. Van Der Wel En Zoon",
    "wof:placetype":"venue"
},
  "geometry": {"coordinates":[4.197063,51.981583],"type":"Point"}
}