{
  "type": "Feature",
  "properties": {
    "addr:full":"Rabenhauptstr 8 Groningen Groningen 9725 CD",
    "addr:housenumber":"8",
    "addr:postcode":"9725 cd",
    "addr:street":"Rabenhauptstr",
    "iso:country":"NL",
    "sg:address":"Rabenhauptstr 8",
    "sg:city":"Groningen",
    "sg:classifiers":[
        {
            "category":"Food & Beverages",
            "subcategory":"Bakery",
            "type":"Retail Goods"
        }
    ],
    "sg:phone":"+31 50 527 8962",
    "sg:postcode":"9725 CD",
    "sg:province":"Groningen",
    "sg:tags":[
        "pizza"
    ],
    "wof:name":"Pronto",
    "wof:placetype":"venue"
},
  "geometry": {"coordinates":[6.571316,53.20948],"type":"Point"}
}