{
  "type": "Feature",
  "properties": {
    "iso:country":"NL",
    "sg:address":"Postbus 64",
    "sg:city":"Haarlem",
    "sg:orig_category":"Actuarissen",
    "sg:phone":"+31 23 540 0683",
    "sg:postcode":"2000 AB",
    "sg:province":"Noord-Holland",
    "wof:name":"Acturix",
    "wof:placetype":"venue"
},
  "geometry": {"coordinates":[4.63698,52.379608],"type":"Point"}
}