{
  "type": "Feature",
  "properties": {
    "iso:country":"NL",
    "sg:address":"Dorpsstraat 145",
    "sg:city":"Zevenhuizen Zh",
    "sg:orig_category":"Meubelzaken, Woning- And Keukeninrichting",
    "sg:phone":"+31 180 631 238",
    "sg:postcode":"2761 AL",
    "sg:province":"Zuid-Holland",
    "wof:name":"Bac Wonen En Slapen",
    "wof:placetype":"venue"
},
  "geometry": {"coordinates":[4.579966,52.013393],"type":"Point"}
}