{
  "type": "Feature",
  "properties": {
    "addr:full":"Den Adelszwet 22 Rijsenhout Noord-Holland 1435 NN",
    "addr:housenumber":"22",
    "addr:postcode":"1435 nn",
    "addr:street":"Den Adelszwet",
    "iso:country":"NL",
    "sg:address":"Den Adelszwet 22",
    "sg:city":"Rijsenhout",
    "sg:orig_category":"Bloemen And Planten",
    "sg:phone":"+31 297 327 432",
    "sg:postcode":"1435 NN",
    "sg:province":"Noord-Holland",
    "wof:name":"Van Rijswijk'S Planten Bv",
    "wof:placetype":"venue"
},
  "geometry": {"coordinates":[4.716964,52.265656],"type":"Point"}
}