{
  "type": "Feature",
  "properties": {
    "addr:full":"Postbus 116 Ryen 5120 AC",
    "addr:housenumber":"116",
    "addr:postcode":"5120 ac",
    "addr:street":"Postbus",
    "iso:country":"NL",
    "sg:address":"Postbus 116",
    "sg:city":"Ryen",
    "sg:orig_category":"Scholen Voor Basisonderwijs",
    "sg:phone":"+31 161 222 962",
    "sg:postcode":"5120 AC",
    "wof:name":"Spie Kbs, De",
    "wof:placetype":"venue"
},
  "geometry": {"coordinates":[4.91944,51.588322],"type":"Point"}
}