{
  "type": "Feature",
  "properties": {
    "addr:full":"De Hammen 2 Ravenstein Noord-Brabant 5371 MK",
    "addr:housenumber":"2",
    "addr:postcode":"5371",
    "addr:street":"De Hammen",
    "iso:country":"NL",
    "sg:address":"De Hammen 2",
    "sg:city":"Ravenstein",
    "sg:orig_category":"Geluidsinstallaties - Verhuur",
    "sg:phone":"+31 486 412 777",
    "sg:postcode":"5371 MK",
    "sg:province":"Noord-Brabant",
    "wof:name":"Hvr",
    "wof:placetype":"venue"
},
  "geometry": {"coordinates":[5.65162,51.796925],"type":"Point"}
}