{
  "type": "Feature",
  "properties": {
    "addr:full":"Wilhelminastr 10 Roosendaal Noord-Brabant 4701 GW",
    "addr:housenumber":"10",
    "addr:postcode":"4701 gw",
    "addr:street":"Wilhelminastr",
    "iso:country":"NL",
    "sg:address":"Wilhelminastr 10",
    "sg:city":"Roosendaal",
    "sg:orig_category":"Kansspelen",
    "sg:phone":"+31 165 555 275",
    "sg:postcode":"4701 GW",
    "sg:province":"Noord-Brabant",
    "wof:name":"Brabant Bingo",
    "wof:placetype":"venue"
},
  "geometry": {"coordinates":[4.4634342194,51.5324287415],"type":"Point"}
}