{
  "type": "Feature",
  "properties": {
    "addr:full":"Energieweg 14 Oosterhout Nb Noord-Brabant 4906 CG",
    "addr:housenumber":"14",
    "addr:postcode":"4906 cg",
    "addr:street":"Energieweg",
    "iso:country":"NL",
    "sg:address":"Energieweg 14",
    "sg:city":"Oosterhout Nb",
    "sg:orig_category":"Houten Verpakkingen Fab",
    "sg:phone":"+31 162 422 908",
    "sg:postcode":"4906 CG",
    "sg:province":"Noord-Brabant",
    "wof:name":"Pema Pallets Bv",
    "wof:placetype":"venue"
},
  "geometry": {"coordinates":[4.84382,51.657982],"type":"Point"}
}