{
  "type": "Feature",
  "properties": {
    "addr:full":"Van Der Molenallee 145 Doorwerth Gelderland 6865 CE",
    "addr:housenumber":"145",
    "addr:postcode":"6865 ce",
    "addr:street":"Van Der Molenallee;Gelderland",
    "iso:country":"NL",
    "sg:address":"Van Der Molenallee 145",
    "sg:city":"Doorwerth",
    "sg:orig_category":"Bedrijfs- And Managementsconsultants",
    "sg:phone":"+31 317 350 040",
    "sg:postcode":"6865 CE",
    "sg:province":"Gelderland",
    "wof:name":"Bosmann Management Consulting Bv",
    "wof:placetype":"venue"
},
  "geometry": {"coordinates":[5.783694,51.981079],"type":"Point"}
}