{
  "type": "Feature",
  "properties": {
    "iso:country":"NL",
    "sg:address":"Zuideinde 87",
    "sg:city":"Westzaan",
    "sg:orig_category":"Autokeuringen",
    "sg:phone":"+31 75 631 8672",
    "sg:postcode":"1551 EC",
    "sg:province":"North Holland",
    "wof:name":"Dck Classic Cars",
    "wof:placetype":"venue"
},
  "geometry": {"coordinates":[4.780022,52.434425],"type":"Point"}
}