{
  "type": "Feature",
  "properties": {
    "addr:full":"Takkebijsters 37 A Breda Noord-Brabant 4817 BL",
    "addr:housenumber":"37 a",
    "addr:postcode":"4817 bl",
    "addr:street":"Takkebijsters",
    "iso:country":"NL",
    "sg:address":"Takkebijsters 37 A",
    "sg:city":"Breda",
    "sg:orig_category":"Huishoudapparatuur, Televisies And Radio'S",
    "sg:phone":"+31 76 572 0505",
    "sg:postcode":"4817 BL",
    "sg:province":"Noord-Brabant",
    "wof:name":"* A & M Whiteparts.",
    "wof:placetype":"venue"
},
  "geometry": {"coordinates":[4.829161,51.597038],"type":"Point"}
}