{
  "type": "Feature",
  "properties": {
    "addr:full":"Torenstraat 4 Nes Ameland Friesland 9163 HE",
    "addr:housenumber":"4",
    "addr:postcode":"9163 he",
    "addr:street":"Torenstraat",
    "iso:country":"NL",
    "sg:address":"Torenstraat 4",
    "sg:city":"Nes Ameland",
    "sg:orig_category":"Verlichting And Huishoudartikelen",
    "sg:phone":"+31 519 542 621",
    "sg:postcode":"9163 HE",
    "sg:province":"Friesland",
    "wof:name":"De Zilvermeeuw",
    "wof:placetype":"venue"
},
  "geometry": {"coordinates":[5.771447,53.446114],"type":"Point"}
}