{
  "type": "Feature",
  "properties": {
    "iso:country":"NL",
    "sg:address":"Torenstraat 4",
    "sg:city":"Nes Ameland",
    "sg:orig_category":"Verlichting And Huishoudartikelen",
    "sg:phone":"+31 519 542 621",
    "sg:postcode":"9163 HE",
    "sg:province":"Friesland",
    "wof:name":"De Zilvermeeuw",
    "wof:placetype":"venue"
},
  "geometry": {"coordinates":[5.771447,53.446114],"type":"Point"}
}