{
  "type": "Feature",
  "properties": {
    "addr:full":"Karveel 775 Lelystad Flevoland 8231 AK",
    "addr:housenumber":"775",
    "addr:postcode":"8231 ak",
    "addr:street":"Karveel;Flevoland",
    "iso:country":"NL",
    "sg:address":"Karveel 775",
    "sg:city":"Lelystad",
    "sg:orig_category":"Vertaalbureaus",
    "sg:phone":"+31 320 221 155",
    "sg:postcode":"8231 AK",
    "sg:province":"Flevoland",
    "wof:name":"Jonkheid & Horijon",
    "wof:placetype":"venue"
},
  "geometry": {"coordinates":[5.470049,52.521088],"type":"Point"}
}