{
  "type": "Feature",
  "properties": {
    "addr:full":"J Gossaertln 23 Bilthoven Utrecht 3723 CM",
    "addr:housenumber":"23",
    "addr:postcode":"3723 cm",
    "iso:country":"NL",
    "sg:address":"J Gossaertln 23",
    "sg:city":"Bilthoven",
    "sg:orig_category":"Adviesbureaus",
    "sg:phone":"+31 30 225 4538",
    "sg:postcode":"3723 CM",
    "sg:province":"Utrecht",
    "wof:name":"Beijma Bv, U H Van",
    "wof:placetype":"venue"
},
  "geometry": {"coordinates":[5.205415,52.13023],"type":"Point"}
}