{
  "type": "Feature",
  "properties": {
    "iso:country":"NL",
    "sg:address":"Kloosterstr 13-15",
    "sg:city":"Helmond",
    "sg:orig_category":"Banken",
    "sg:phone":"+31 492 549 071",
    "sg:postcode":"5708 GM",
    "sg:province":"North Brabant",
    "wof:name":"Regio Bank",
    "wof:placetype":"venue"
},
  "geometry": {"coordinates":[5.619178,51.485939],"type":"Point"}
}