{
  "type": "Feature",
  "properties": {
    "addr:full":"Kloosterstr 13-15 Helmond North Brabant 5708 GM",
    "addr:housenumber":"13-15",
    "addr:postcode":"5708 gm",
    "iso:country":"NL",
    "sg:address":"Kloosterstr 13-15",
    "sg:city":"Helmond",
    "sg:orig_category":"Banken",
    "sg:phone":"+31 492 549 071",
    "sg:postcode":"5708 GM",
    "sg:province":"North Brabant",
    "wof:name":"Regio Bank",
    "wof:placetype":"venue"
},
  "geometry": {"coordinates":[5.619178,51.485939],"type":"Point"}
}