{
  "type": "Feature",
  "properties": {
    "iso:country":"NL",
    "sg:address":"St Jozefstr 30",
    "sg:city":"Deurne",
    "sg:orig_category":"Woningbouw- Verenigingen En -Stichtingen",
    "sg:phone":"+31 493 327 300",
    "sg:postcode":"5753 AV",
    "sg:province":"North Brabant",
    "sg:website":"http://www.bergopwaarts.nl",
    "wof:name":"Bergopwaarts Woningbouwver",
    "wof:placetype":"venue"
},
  "geometry": {"coordinates":[5.7842240334,51.4520835876],"type":"Point"}
}