{
  "type": "Feature",
  "properties": {
    "addr:full":"Wijkamplaan 71 Baarn Utrecht 3742 WP",
    "addr:housenumber":"71",
    "addr:postcode":"3742 wp",
    "addr:street":"Wijkamplaan",
    "iso:country":"NL",
    "sg:address":"Wijkamplaan 71",
    "sg:city":"Baarn",
    "sg:orig_category":"Begrafenisondernemers",
    "sg:phone":"+31 35 541 2814",
    "sg:postcode":"3742 WP",
    "sg:province":"Utrecht",
    "wof:name":"Begraafplaats Gemeentelijke",
    "wof:placetype":"venue"
},
  "geometry": {"coordinates":[5.291915,52.202667],"type":"Point"}
}