{
  "type": "Feature",
  "properties": {
    "addr:full":"Meppelweg 32 'S Gravenhage South Holland 2544 BA",
    "addr:housenumber":"32",
    "addr:postcode":"2544 ba",
    "addr:street":"Meppelweg;' S Gravenhage",
    "iso:country":"NL",
    "sg:address":"Meppelweg 32",
    "sg:city":"'S Gravenhage",
    "sg:orig_category":"Huishoudapparatuur, Televisies And Radio'S",
    "sg:phone":"+31 70 367 4301",
    "sg:postcode":"2544 BA",
    "sg:province":"South Holland",
    "wof:name":"Ariane Satellite Systems",
    "wof:placetype":"venue"
},
  "geometry": {"coordinates":[4.274053,52.055038],"type":"Point"}
}