{
  "type": "Feature",
  "properties": {
    "addr:full":"Linnaeuslaan 56 Aalsmeer Noord-Holland 1431  J",
    "addr:housenumber":"56;1431 j",
    "addr:street":"Linnaeuslaan",
    "iso:country":"NL",
    "sg:address":"Linnaeuslaan 56",
    "sg:city":"Aalsmeer",
    "sg:orig_category":"Vertaal- And Tolkenbureaus",
    "sg:phone":"+31 297 325 911",
    "sg:postcode":"1431  J",
    "sg:province":"Noord-Holland",
    "wof:name":"Vertaalbureau Van Eijk",
    "wof:placetype":"venue"
},
  "geometry": {"coordinates":[4.772638,52.26543],"type":"Point"}
}