{
  "type": "Feature",
  "properties": {
    "iso:country":"NL",
    "sg:address":"Oranjeweg 70",
    "sg:city":"Zuid-Beijerland",
    "sg:classifiers":[
        {
            "category":"Retail",
            "subcategory":"Storage",
            "type":"Services"
        }
    ],
    "sg:phone":"+31 186 669 005",
    "sg:postcode":"3284 KT",
    "sg:province":"South Holland",
    "sg:tags":[
        "opslag",
        "bewaring"
    ],
    "wof:name":"Aannemersbedrijf Joh. Van Brakel En Zone",
    "wof:placetype":"venue"
},
  "geometry": {"coordinates":[4.3649578094,51.7564048767],"type":"Point"}
}