{
  "type": "Feature",
  "properties": {
    "iso:country":"NL",
    "sg:address":"Nieuwe Leliestraat 80",
    "sg:city":"Amsterdam",
    "sg:orig_category":"Kappers",
    "sg:phone":"+31 20 624 7969",
    "sg:postcode":"1015 SV",
    "sg:province":"Noord-Holland",
    "wof:name":"A J Van Musscher",
    "wof:placetype":"venue"
},
  "geometry": {"coordinates":[4.8811159134,52.3754997253],"type":"Point"}
}