{
  "type": "Feature",
  "properties": {
    "addr:full":"Aegidiusstr 110 Rotterdam South Holland 3061 XP",
    "addr:housenumber":"110",
    "addr:postcode":"3061 xp",
    "iso:country":"NL",
    "sg:address":"Aegidiusstr 110",
    "sg:city":"Rotterdam",
    "sg:orig_category":"Adviesbureaus Bouwkunde",
    "sg:phone":"+31 10 453 2500",
    "sg:postcode":"3061 XP",
    "sg:province":"South Holland",
    "wof:name":"Technical Services Holland Bv",
    "wof:placetype":"venue"
},
  "geometry": {"coordinates":[4.510452,51.923267],"type":"Point"}
}