{
  "type": "Feature",
  "properties": {
    "iso:country":"NL",
    "sg:address":"Boslaan 4",
    "sg:city":"Borger",
    "sg:orig_category":"Loodgieterswerk, Verwarming And Sanitaire Installaties",
    "sg:phone":"+31 599 235 605",
    "sg:postcode":"9531 BB",
    "sg:province":"Drenthe",
    "wof:name":"Klussenbureau Boekholt",
    "wof:placetype":"venue"
},
  "geometry": {"coordinates":[6.790319,52.920013],"type":"Point"}
}