{
  "type": "Feature",
  "properties": {
    "addr:full":"Kleine Poot 22 Deventer NL.08 7411 PE",
    "addr:housenumber":"22;nl.08",
    "addr:postcode":"7411 pe",
    "addr:street":"Kleine Poot",
    "iso:country":"NL",
    "sg:address":"Kleine Poot 22",
    "sg:city":"Deventer",
    "sg:orig_category":"Opticiens",
    "sg:phone":"+31 570 614 583",
    "sg:postcode":"7411 PE",
    "sg:province":"NL.08",
    "wof:name":"Firma F. Oosterlaar",
    "wof:placetype":"venue"
},
  "geometry": {"coordinates":[6.1556949615,52.2524185181],"type":"Point"}
}