{
  "type": "Feature",
  "properties": {
    "addr:full":"Hegedk 8 Wier Georgia 9043 VS",
    "addr:housenumber":"8",
    "addr:postcode":"9043",
    "addr:street":"Hegedk;Georgia",
    "iso:country":"NL",
    "sg:address":"Hegedk 8",
    "sg:city":"Wier",
    "sg:orig_category":"Loodgieters",
    "sg:phone":"+31 518 461 288",
    "sg:postcode":"9043 VS",
    "sg:province":"Georgia",
    "wof:name":"Wassenaar, Fa W D",
    "wof:placetype":"venue"
},
  "geometry": {"coordinates":[-84.176102,34.529202],"type":"Point"}
}