{
  "type": "Feature",
  "properties": {
    "iso:country":"NL",
    "sg:address":"Streilerwg 24",
    "sg:city":"Wilp Gld",
    "sg:orig_category":"Onroerende Goederen",
    "sg:phone":"+31 571 262 242",
    "sg:postcode":"7384 CW",
    "sg:province":"Gelderland",
    "wof:name":"Jca Bv",
    "wof:placetype":"venue"
},
  "geometry": {"coordinates":[6.100208,52.206631],"type":"Point"}
}