{
  "type": "Feature",
  "properties": {
    "addr:full":"Gilzewg 1 Chaam North Brabant 4861 AS",
    "addr:housenumber":"1",
    "addr:postcode":"4861 as",
    "addr:street":"Gilzewg",
    "iso:country":"NL",
    "sg:address":"Gilzewg 1",
    "sg:city":"Chaam",
    "sg:orig_category":"Kappers",
    "sg:phone":"+31 161 492 433",
    "sg:postcode":"4861 AS",
    "sg:province":"North Brabant",
    "wof:name":"Marij",
    "wof:placetype":"venue"
},
  "geometry": {"coordinates":[4.861236,51.505699],"type":"Point"}
}