{
  "type": "Feature",
  "properties": {
    "addr:full":"Passage 26 Valkenswaard Noord-Brabant 5554 AH",
    "addr:housenumber":"26",
    "addr:postcode":"5554 ah",
    "addr:street":"Passage",
    "iso:country":"NL",
    "sg:address":"Passage 26",
    "sg:city":"Valkenswaard",
    "sg:orig_category":"Bloemen And Planten",
    "sg:phone":"+31 40 204 8286",
    "sg:postcode":"5554 AH",
    "sg:province":"Noord-Brabant",
    "wof:name":"Bloemsierkunst Detifleur Vof",
    "wof:placetype":"venue"
},
  "geometry": {"coordinates":[5.458207,51.352058],"type":"Point"}
}