{
  "type": "Feature",
  "properties": {
    "addr:full":"Drie Weikes 2 Oud Gastel Noord-Brabant 4751 SJ",
    "addr:housenumber":"2",
    "addr:postcode":"4751",
    "addr:street":"Drie Weikes",
    "iso:country":"NL",
    "sg:address":"Drie Weikes 2",
    "sg:city":"Oud Gastel",
    "sg:classifiers":[
        {
            "category":"Personal",
            "subcategory":"Nail Salon",
            "type":"Services"
        }
    ],
    "sg:phone":"+31 165 317 116",
    "sg:postcode":"4751 SJ",
    "sg:province":"Noord-Brabant",
    "sg:tags":[
        "pedicure"
    ],
    "wof:name":"Pedicura",
    "wof:placetype":"venue"
},
  "geometry": {"coordinates":[4.511684,51.589382],"type":"Point"}
}