{
  "type": "Feature",
  "properties": {
    "addr:full":"Ginnekenwg 241 Breda Noord-Brabant 4835 NB",
    "addr:housenumber":"241",
    "addr:postcode":"4835 nb",
    "iso:country":"NL",
    "sg:address":"Ginnekenwg 241",
    "sg:city":"Breda",
    "sg:orig_category":"Kantoorbenodigdheden",
    "sg:phone":"+31 76 565 2987",
    "sg:postcode":"4835 NB",
    "sg:province":"Noord-Brabant",
    "wof:name":"Holster Van Aken",
    "wof:placetype":"venue"
},
  "geometry": {"coordinates":[4.7839121819,51.5713233948],"type":"Point"}
}