{
  "type": "Feature",
  "properties": {
    "addr:full":"Van Dissellaan 8 Bladel Noord-Brabant 5531 BR",
    "addr:housenumber":"8",
    "addr:postcode":"5531 br",
    "addr:street":"Van Dissellaan",
    "iso:country":"NL",
    "sg:address":"Van Dissellaan 8",
    "sg:city":"Bladel",
    "sg:orig_category":"Werving And Selectie Van Tijdelijk Personeel And Uitzendkantoren",
    "sg:phone":"+31 497 383 925",
    "sg:postcode":"5531 BR",
    "sg:province":"Noord-Brabant",
    "wof:name":"Randstad",
    "wof:placetype":"venue"
},
  "geometry": {"coordinates":[5.2143850327,51.3676719666],"type":"Point"}
}