{
  "type": "Feature",
  "properties": {
    "addr:full":"Vyfhuizerdk 60B Vyfhuizen North Holland 2141 BC",
    "addr:housenumber":"60b vyfhuizen",
    "addr:postcode":"2141 bc",
    "addr:street":"Vyfhuizerdk",
    "iso:country":"NL",
    "sg:address":"Vyfhuizerdk 60B",
    "sg:city":"Vyfhuizen",
    "sg:orig_category":"Postkantoren",
    "sg:phone":"+31 23 558 1411",
    "sg:postcode":"2141 BC",
    "sg:province":"North Holland",
    "sg:website":"http://www.postkantoor.nl",
    "wof:name":"Postkantoor",
    "wof:placetype":"venue"
},
  "geometry": {"coordinates":[4.679655,52.352299],"type":"Point"}
}