{
  "type": "Feature",
  "properties": {
    "addr:full":"Rosmolenstraat 100 Leusden Utrecht 3833 KH",
    "addr:housenumber":"100",
    "addr:postcode":"3833 kh",
    "addr:street":"Rosmolenstraat",
    "iso:country":"NL",
    "sg:address":"Rosmolenstraat 100",
    "sg:city":"Leusden",
    "sg:orig_category":"Schoonheidssalons",
    "sg:phone":"+31 33 494 1481",
    "sg:postcode":"3833 KH",
    "sg:province":"Utrecht",
    "wof:name":"Ada",
    "wof:placetype":"venue"
},
  "geometry": {"coordinates":[5.422079,52.123001],"type":"Point"}
}