{
  "type": "Feature",
  "properties": {
    "iso:country":"NL",
    "sg:address":"Erasmusweg 2",
    "sg:city":"Hoogezand",
    "sg:orig_category":"Overheidsdiensten",
    "sg:phone":"+31 598 327 474",
    "sg:postcode":"9602 AE",
    "sg:province":"Groningen",
    "wof:name":"Spokie",
    "wof:placetype":"venue"
},
  "geometry": {"coordinates":[6.7418489456,53.1590843201],"type":"Point"}
}