{
  "type": "Feature",
  "properties": {
    "addr:full":"Hoofdstr 108 Apeldoorn Gelderland 7311 KJ",
    "addr:housenumber":"108",
    "addr:postcode":"7311 kj",
    "addr:street":"Gelderland",
    "iso:country":"NL",
    "sg:address":"Hoofdstr 108",
    "sg:city":"Apeldoorn",
    "sg:orig_category":"Opticiens",
    "sg:phone":"+31 55 521 7467",
    "sg:postcode":"7311 KJ",
    "sg:province":"Gelderland",
    "sg:website":"http://www.sandmannoptiek.nl",
    "wof:name":"Sandmann Optiek",
    "wof:placetype":"venue"
},
  "geometry": {"coordinates":[5.9622478485,52.2147674561],"type":"Point"}
}