{
  "type": "Feature",
  "properties": {
    "addr:full":"Arkendonk 46 Oosterhout Nb North Brabant 4907 XP",
    "addr:housenumber":"46;nb",
    "addr:postcode":"4907 xp",
    "addr:street":"Arkendonk",
    "iso:country":"NL",
    "sg:address":"Arkendonk 46",
    "sg:city":"Oosterhout Nb",
    "sg:orig_category":"Visspeciaalzaken",
    "sg:phone":"+31 162 423 711",
    "sg:postcode":"4907 XP",
    "sg:province":"North Brabant",
    "wof:name":"Visspeciaalzaak V. Reenen",
    "wof:placetype":"venue"
},
  "geometry": {"coordinates":[4.864412,51.657833],"type":"Point"}
}