{
  "type": "Feature",
  "properties": {
    "addr:full":"Nachtegaal 19 Nieuwegein Utrecht 3435 AJ",
    "addr:housenumber":"19",
    "addr:postcode":"3435 aj",
    "addr:street":"Nachtegaal",
    "iso:country":"NL",
    "sg:address":"Nachtegaal 19",
    "sg:city":"Nieuwegein",
    "sg:orig_category":"Diverse Opleidingen And Onderwijs",
    "sg:phone":"+31 30 603 9443",
    "sg:postcode":"3435 AJ",
    "sg:province":"Utrecht",
    "wof:name":"Edumar Opleidingen",
    "wof:placetype":"venue"
},
  "geometry": {"coordinates":[5.073098,52.025402],"type":"Point"}
}