{
  "type": "Feature",
  "properties": {
    "iso:country":"NL",
    "sg:address":"Hoofdstraat 90",
    "sg:city":"Veenendaal",
    "sg:orig_category":"Herenmodezaken",
    "sg:phone":"+31 318 589 040",
    "sg:postcode":"3901 AW",
    "sg:province":"Utrecht",
    "wof:name":"Jan Van Schuppen Vof",
    "wof:placetype":"venue"
},
  "geometry": {"coordinates":[5.556818,52.028111],"type":"Point"}
}