{
  "type": "Feature",
  "properties": {
    "addr:full":"Grote Markt 3 Zwolle NL.08 8011 LV",
    "addr:housenumber":"3",
    "addr:postcode":"8011",
    "addr:street":"Grote Markt",
    "iso:country":"NL",
    "sg:address":"Grote Markt 3",
    "sg:city":"Zwolle",
    "sg:orig_category":"Kappers",
    "sg:phone":"+31 38 421 6313",
    "sg:postcode":"8011 LV",
    "sg:province":"NL.08",
    "wof:name":"Fa H S Wolff En Zn",
    "wof:placetype":"venue"
},
  "geometry": {"coordinates":[6.0887379646,52.5125656128],"type":"Point"}
}