{
  "type": "Feature",
  "properties": {
    "addr:full":"Burglaan 2 Apeldoorn Gelderland 7314 BL",
    "addr:housenumber":"2",
    "addr:postcode":"7314 bl",
    "addr:street":"Burglaan;Gelderland",
    "iso:country":"NL",
    "sg:address":"Burglaan 2",
    "sg:city":"Apeldoorn",
    "sg:orig_category":"Benzinestations And Brandstoffen",
    "sg:phone":"+31 55 521 7733",
    "sg:postcode":"7314 BL",
    "sg:province":"Gelderland",
    "wof:name":"Bp",
    "wof:placetype":"venue"
},
  "geometry": {"coordinates":[5.951208,52.22047],"type":"Point"}
}