{
  "type": "Feature",
  "properties": {
    "addr:full":"Boterbloemstraat 13 Krimpen A/D Lek Zuid-Holland 2931 TA",
    "addr:housenumber":"13;a / d",
    "addr:postcode":"2931 ta",
    "addr:street":"Boterbloemstraat",
    "iso:country":"NL",
    "sg:address":"Boterbloemstraat 13",
    "sg:city":"Krimpen A/D Lek",
    "sg:classifiers":[
        {
            "category":"Professional",
            "subcategory":"Accounting & Tax Preparation",
            "type":"Services"
        }
    ],
    "sg:phone":"+31 180 590 954",
    "sg:postcode":"2931 TA",
    "sg:province":"Zuid-Holland",
    "sg:tags":[
        "accountant"
    ],
    "wof:name":"Accountantskantoor Straver",
    "wof:placetype":"venue"
},
  "geometry": {"coordinates":[4.622508,51.896282],"type":"Point"}
}