{
  "type": "Feature",
  "properties": {
    "iso:country":"NL",
    "sg:address":"Zandvaart 53",
    "sg:city":"Breezand",
    "sg:classifiers":[
        {
            "category":"Fast Food",
            "type":"Food & Drink"
        }
    ],
    "sg:phone":"+31 223 521 226",
    "sg:postcode":"1764 NK",
    "sg:province":"Noord-Holland",
    "sg:tags":[
        "afhaal",
        "restaurant"
    ],
    "wof:name":"Snackbar Picasso",
    "wof:placetype":"venue"
},
  "geometry": {"coordinates":[4.802584,52.888077],"type":"Point"}
}