{
  "type": "Feature",
  "properties": {
    "iso:country":"NL",
    "sg:address":"Oudenhil 5",
    "sg:city":"Ouddorp Zh",
    "sg:orig_category":"Keukens",
    "sg:phone":"+31 187 683 706",
    "sg:postcode":"3253 EE",
    "sg:province":"Zuid-Holland",
    "wof:name":"Timmer Service Ouddorp",
    "wof:placetype":"venue"
},
  "geometry": {"coordinates":[3.94105,51.806198],"type":"Point"}
}