{
  "type": "Feature",
  "properties": {
    "addr:full":"Wijkerstraatweg 211 Velsen-Noord North Holland 1951 EE",
    "addr:housenumber":"211",
    "addr:postcode":"1951 ee",
    "addr:street":"Wijkerstraatweg",
    "iso:country":"NL",
    "sg:address":"Wijkerstraatweg 211",
    "sg:city":"Velsen-Noord",
    "sg:orig_category":"Hoger Onderwijs",
    "sg:phone":"+31 251 224 268",
    "sg:postcode":"1951 EE",
    "sg:province":"North Holland",
    "wof:name":"A.M.J. Gaarthuis",
    "wof:placetype":"venue"
},
  "geometry": {"coordinates":[4.646156,52.473907],"type":"Point"}
}