{
  "type": "Feature",
  "properties": {
    "addr:full":"Van Slichtenhorststraat 106 Nijmegen Gelderland 6524 JW",
    "addr:housenumber":"106",
    "addr:postcode":"6524 jw",
    "addr:street":"Van Slichtenhorststraat;Gelderland",
    "iso:country":"NL",
    "sg:address":"Van Slichtenhorststraat 106",
    "sg:city":"Nijmegen",
    "sg:orig_category":"Fitnesscentra",
    "sg:phone":"+31 24 322 9209",
    "sg:postcode":"6524 JW",
    "sg:province":"Gelderland",
    "wof:name":"W.J. Scheerder",
    "wof:placetype":"venue"
},
  "geometry": {"coordinates":[5.864996,51.83688],"type":"Point"}
}