{
  "type": "Feature",
  "properties": {
    "addr:full":"Hoofdstraat West 38 Uithuizen Groningen 9981 AD",
    "addr:housenumber":"38",
    "addr:postcode":"9981 ad",
    "addr:street":"Hoofdstraat West",
    "iso:country":"NL",
    "sg:address":"Hoofdstraat West 38",
    "sg:city":"Uithuizen",
    "sg:orig_category":"Opticiens",
    "sg:phone":"+31 595 431 344",
    "sg:postcode":"9981 AD",
    "sg:province":"Groningen",
    "wof:name":"In 'T Veen",
    "wof:placetype":"venue"
},
  "geometry": {"coordinates":[6.6693229675,53.4081878662],"type":"Point"}
}