{
  "type": "Feature",
  "properties": {
    "addr:full":"Aidastraat 20-22 Amstelveen Noord-Holland 1183 PB",
    "addr:housenumber":"20-22",
    "addr:postcode":"1183 pb",
    "addr:street":"Aidastraat",
    "iso:country":"NL",
    "sg:address":"Aidastraat 20-22",
    "sg:city":"Amstelveen",
    "sg:orig_category":"Artsen And Specialisten",
    "sg:phone":"+31 20 641 2550",
    "sg:postcode":"1183 PB",
    "sg:province":"Noord-Holland",
    "wof:name":"C.M. Ham",
    "wof:placetype":"venue"
},
  "geometry": {"coordinates":[4.8781571388,52.3006134033],"type":"Point"}
}