{
  "type": "Feature",
  "properties": {
    "addr:full":"Bornsestr 80 Almelo Overijssel 7607 KS",
    "addr:housenumber":"80",
    "addr:postcode":"7607 ks",
    "addr:street":"Bornsestr",
    "iso:country":"NL",
    "sg:address":"Bornsestr 80",
    "sg:city":"Almelo",
    "sg:orig_category":"Verzekeringen - Verzekeringskantoren",
    "sg:phone":"+31 546 822 640",
    "sg:postcode":"7607 KS",
    "sg:province":"Overijssel",
    "wof:name":"Ronag",
    "wof:placetype":"venue"
},
  "geometry": {"coordinates":[6.668686,52.350613],"type":"Point"}
}