{
  "type": "Feature",
  "properties": {
    "addr:full":"Herenweg 46 Wilnis Utrecht 3648 CJ",
    "addr:housenumber":"46",
    "addr:postcode":"3648 cj",
    "addr:street":"Herenweg",
    "iso:country":"NL",
    "sg:address":"Herenweg 46",
    "sg:city":"Wilnis",
    "sg:orig_category":"Verlichting And Huishoudartikelen",
    "sg:phone":"+31 297 281 746",
    "sg:postcode":"3648 CJ",
    "sg:province":"Utrecht",
    "wof:name":"Fabiola",
    "wof:placetype":"venue"
},
  "geometry": {"coordinates":[4.898242,52.194798],"type":"Point"}
}