{
  "type": "Feature",
  "properties": {
    "iso:country":"NL",
    "sg:address":"Admiraliteitskade 81",
    "sg:city":"Rotterdam",
    "sg:classifiers":[
        {
            "category":"Shopping",
            "subcategory":"Clothing, Apparel, & Fashions",
            "type":"Retail Goods"
        }
    ],
    "sg:phone":"+31 10 214 3500",
    "sg:postcode":"3063 EG",
    "sg:province":"Zuid-Holland",
    "sg:tags":[
        "ondergoed",
        "lingerie"
    ],
    "wof:name":"Louisana",
    "wof:placetype":"venue"
},
  "geometry": {"coordinates":[4.500111,51.922279],"type":"Point"}
}