{
  "type": "Feature",
  "properties": {
    "addr:full":"De Taling 36 Vriezenveen NL.08 7671 TW",
    "addr:housenumber":"36;nl.08",
    "addr:postcode":"7671 tw",
    "addr:street":"De Taling",
    "iso:country":"NL",
    "sg:address":"De Taling 36",
    "sg:city":"Vriezenveen",
    "sg:orig_category":"Projectontwikkeling",
    "sg:phone":"+31 546 567 684",
    "sg:postcode":"7671 TW",
    "sg:province":"NL.08",
    "wof:name":"Nijko Bv",
    "wof:placetype":"venue"
},
  "geometry": {"coordinates":[6.619822,52.401016],"type":"Point"}
}