{
  "type": "Feature",
  "properties": {
    "iso:country":"NL",
    "sg:address":"De Taling 36",
    "sg:city":"Vriezenveen",
    "sg:orig_category":"Projectontwikkeling",
    "sg:phone":"+31 546 567 684",
    "sg:postcode":"7671 TW",
    "sg:province":"NL.08",
    "wof:name":"Nijko Bv",
    "wof:placetype":"venue"
},
  "geometry": {"coordinates":[6.619822,52.401016],"type":"Point"}
}