{
  "type": "Feature",
  "properties": {
    "iso:country":"NL",
    "sg:address":"T Dorp 11",
    "sg:city":"Heesch",
    "sg:orig_category":"Huishoudapparatuur, Televisies And Radio'S",
    "sg:phone":"+31 412 457 120",
    "sg:postcode":"5384 MA",
    "sg:province":"Noord-Brabant",
    "wof:name":"Henk Van Den Akker",
    "wof:placetype":"venue"
},
  "geometry": {"coordinates":[5.533636,51.735943],"type":"Point"}
}