{
  "type": "Feature",
  "properties": {
    "addr:full":"Prinsenstr 12 Dalfsen Overijssel 7721 AJ",
    "addr:housenumber":"12",
    "addr:postcode":"7721 aj",
    "addr:street":"Prinsenstr",
    "iso:country":"NL",
    "sg:address":"Prinsenstr 12",
    "sg:city":"Dalfsen",
    "sg:orig_category":"Drogisterijen",
    "sg:phone":"+31 529 431 522",
    "sg:postcode":"7721 AJ",
    "sg:province":"Overijssel",
    "wof:name":"Da",
    "wof:placetype":"venue"
},
  "geometry": {"coordinates":[6.259953,52.503712],"type":"Point"}
}