{
  "type": "Feature",
  "properties": {
    "addr:full":"Dorpspln 8 Westervoort Gelderland 6931 CZ",
    "addr:housenumber":"8",
    "addr:postcode":"6931",
    "addr:street":"Dorpspln;Gelderland",
    "iso:country":"NL",
    "sg:address":"Dorpspln 8",
    "sg:city":"Westervoort",
    "sg:orig_category":"Opticiens",
    "sg:phone":"+31 26 311 3013",
    "sg:postcode":"6931 CZ",
    "sg:province":"Gelderland",
    "wof:name":"Bril 2000",
    "wof:placetype":"venue"
},
  "geometry": {"coordinates":[5.9668111801,51.961856842],"type":"Point"}
}