{
  "type": "Feature",
  "properties": {
    "iso:country":"NL",
    "sg:address":"Industriewg 6H",
    "sg:city":"Culemborg",
    "sg:orig_category":"Webdesign Bureaus",
    "sg:phone":"+31 345 510 438",
    "sg:postcode":"4104 AR",
    "sg:province":"Gelderland",
    "wof:name":"Viruz",
    "wof:placetype":"venue"
},
  "geometry": {"coordinates":[5.2204627991,51.9429130554],"type":"Point"}
}