{
  "type": "Feature",
  "properties": {
    "addr:full":"Nieuwe Spiegelstraat 37Hs Amsterdam Noord-Holland 1017 DC",
    "addr:housenumber":"37hs",
    "addr:postcode":"1017",
    "addr:street":"Nieuwe Spiegelstraat",
    "iso:country":"NL",
    "sg:address":"Nieuwe Spiegelstraat 37Hs",
    "sg:city":"Amsterdam",
    "sg:orig_category":"Antiekzaken",
    "sg:phone":"+31 20 624 0322",
    "sg:postcode":"1017 DC",
    "sg:province":"Noord-Holland",
    "wof:name":"R. De Slegte",
    "wof:placetype":"venue"
},
  "geometry": {"coordinates":[4.88911,52.363613],"type":"Point"}
}