{
  "type": "Feature",
  "properties": {
    "addr:full":"Luiendijk 18 Purmerend Noord-Holland 1446 BG",
    "addr:housenumber":"18",
    "addr:postcode":"1446",
    "addr:street":"Luiendijk",
    "iso:country":"NL",
    "sg:address":"Luiendijk 18",
    "sg:city":"Purmerend",
    "sg:orig_category":"Marktonderzoekbureaus",
    "sg:phone":"+31 299 648 505",
    "sg:postcode":"1446 BG",
    "sg:province":"Noord-Holland",
    "wof:name":"Permocon Marktonderzoek",
    "wof:placetype":"venue"
},
  "geometry": {"coordinates":[4.985081,52.510262],"type":"Point"}
}