{
  "type": "Feature",
  "properties": {
    "iso:country":"NL",
    "sg:address":"Amstel 90",
    "sg:city":"Wijk Bij Duurstede",
    "sg:orig_category":"Geluidsopnamen",
    "sg:phone":"+31 343 591 361",
    "sg:postcode":"3961 HL",
    "sg:province":"Utrecht",
    "wof:name":"Andre Remkes Muziekprodukties",
    "wof:placetype":"venue"
},
  "geometry": {"coordinates":[5.322889,51.972523],"type":"Point"}
}