{
  "type": "Feature",
  "properties": {
    "iso:country":"NL",
    "sg:address":"Sleutelbloemstr 3",
    "sg:city":"Voorhout",
    "sg:orig_category":"Koeriersdiensten",
    "sg:phone":"+31 6 51808018",
    "sg:postcode":"2215 DB",
    "sg:province":"Zuid-Holland",
    "wof:name":"Struik Int, M C",
    "wof:placetype":"venue"
},
  "geometry": {"coordinates":[4.489281,52.22263],"type":"Point"}
}