{
  "type": "Feature",
  "properties": {
    "addr:full":"Rykswg 86 Mook Limburg 6585 AH",
    "addr:housenumber":"86",
    "addr:postcode":"6585 ah",
    "addr:street":"Rykswg",
    "iso:country":"NL",
    "sg:address":"Rykswg 86",
    "sg:city":"Mook",
    "sg:orig_category":"Bedrijfsopleidingen",
    "sg:phone":"+31 24 696 2950",
    "sg:postcode":"6585 AH",
    "sg:province":"Limburg",
    "wof:name":"Oellers Inst",
    "wof:placetype":"venue"
},
  "geometry": {"coordinates":[5.882488,51.750374],"type":"Point"}
}