{
  "type": "Feature",
  "properties": {
    "addr:full":"Van Swietenlaan 25 Groningen Groningen 9728 NX",
    "addr:housenumber":"25",
    "addr:postcode":"9728 nx",
    "addr:street":"Van Swietenlaan",
    "iso:country":"NL",
    "sg:address":"Van Swietenlaan 25",
    "sg:city":"Groningen",
    "sg:orig_category":"Bedrijfs- And Managementsconsultants",
    "sg:phone":"+31 50 527 4061",
    "sg:postcode":"9728 NX",
    "sg:province":"Groningen",
    "wof:name":"De Boer Management Support",
    "wof:placetype":"venue"
},
  "geometry": {"coordinates":[6.548545,53.189156],"type":"Point"}
}