{
  "type": "Feature",
  "properties": {
    "addr:full":"Curiewg 1 Spykenisse South Holland 3208 KJ",
    "addr:housenumber":"1",
    "addr:postcode":"3208 kj",
    "addr:street":"Curiewg",
    "iso:country":"NL",
    "sg:address":"Curiewg 1",
    "sg:city":"Spykenisse",
    "sg:orig_category":"Kappers",
    "sg:phone":"+31 181 625 005",
    "sg:postcode":"3208 KJ",
    "sg:province":"South Holland",
    "wof:name":"Glenn",
    "wof:placetype":"venue"
},
  "geometry": {"coordinates":[4.3028998375,51.8426399231],"type":"Point"}
}