{
  "type": "Feature",
  "properties": {
    "iso:country":"NL",
    "sg:address":"Pascalstraat 15",
    "sg:city":"Purmerend",
    "sg:orig_category":"Verlichting And Huishoudartikelen",
    "sg:phone":"+31 299 641 522",
    "sg:postcode":"1446 TH",
    "sg:province":"North Holland",
    "wof:name":"Atelier Zuidinga",
    "wof:placetype":"venue"
},
  "geometry": {"coordinates":[4.992954,52.515194],"type":"Point"}
}