{
  "type": "Feature",
  "properties": {
    "addr:full":"Bachstr 37 Akersloot Noord-Holland 1921 EW",
    "addr:housenumber":"37",
    "addr:postcode":"1921 ew",
    "addr:street":"Bachstr",
    "iso:country":"NL",
    "sg:address":"Bachstr 37",
    "sg:city":"Akersloot",
    "sg:orig_category":"Evenementenverzorging",
    "sg:phone":"+31 6 54264399",
    "sg:postcode":"1921 EW",
    "sg:province":"Noord-Holland",
    "sg:website":"http://www.danspoppen.nl",
    "wof:name":"Air Fantasy",
    "wof:placetype":"venue"
},
  "geometry": {"coordinates":[4.73289,52.562473],"type":"Point"}
}