{
  "type": "Feature",
  "properties": {
    "addr:full":"Kleingouw 28 Andijk Noord-Holland 1619 CB",
    "addr:housenumber":"28",
    "addr:postcode":"1619 cb",
    "addr:street":"Kleingouw",
    "iso:country":"NL",
    "sg:address":"Kleingouw 28",
    "sg:city":"Andijk",
    "sg:orig_category":"Verzekeringen",
    "sg:phone":"+31 228 592 420",
    "sg:postcode":"1619 CB",
    "sg:province":"Noord-Holland",
    "wof:name":"Bert Vrolijk Verzekeringen Bv",
    "wof:placetype":"venue"
},
  "geometry": {"coordinates":[5.200143,52.741104],"type":"Point"}
}