{
  "type": "Feature",
  "properties": {
    "addr:full":"Edisonweg 14 Alkmaar Noord-Holland 1821 BN",
    "addr:housenumber":"14",
    "addr:postcode":"1821 bn",
    "addr:street":"Edisonweg",
    "iso:country":"NL",
    "sg:address":"Edisonweg 14",
    "sg:city":"Alkmaar",
    "sg:orig_category":"Schilderwerk",
    "sg:phone":"+31 72 511 3401",
    "sg:postcode":"1821 BN",
    "sg:province":"Noord-Holland",
    "wof:name":"Vreeker Schilderwerken Bv",
    "wof:placetype":"venue"
},
  "geometry": {"coordinates":[4.764115,52.627621],"type":"Point"}
}