{
  "type": "Feature",
  "properties": {
    "addr:full":"Sportparkstraat 68 Etten-Leur Noord-Brabant 4871 ZW",
    "addr:housenumber":"68",
    "addr:postcode":"4871 zw",
    "addr:street":"Sportparkstraat",
    "iso:country":"NL",
    "sg:address":"Sportparkstraat 68",
    "sg:city":"Etten-Leur",
    "sg:orig_category":"Bedrijfsinventaris Gh",
    "sg:phone":"+31 76 501 7189",
    "sg:postcode":"4871 ZW",
    "sg:province":"Noord-Brabant",
    "wof:name":"Wave Company",
    "wof:placetype":"venue"
},
  "geometry": {"coordinates":[4.644246,51.578312],"type":"Point"}
}