{
  "type": "Feature",
  "properties": {
    "addr:full":"Bedumerwg 44-45 Groningen Groningen 9716 AD",
    "addr:housenumber":"44-45",
    "addr:postcode":"9716 ad",
    "iso:country":"NL",
    "sg:address":"Bedumerwg 44-45",
    "sg:city":"Groningen",
    "sg:orig_category":"Kunststof Ramen",
    "sg:phone":"+31 800 5990880",
    "sg:postcode":"9716 AD",
    "sg:province":"Groningen",
    "sg:website":"http://www.knipping.org",
    "wof:name":"Knipping Klok",
    "wof:placetype":"venue"
},
  "geometry": {"coordinates":[6.561528,53.230686],"type":"Point"}
}