{
  "type": "Feature",
  "properties": {
    "addr:full":"Nicolaas Maesstraat 49 Enschede NL.08 7545 CD",
    "addr:housenumber":"49",
    "addr:postcode":"7545 cd",
    "addr:street":"Nicolaas Maesstraat",
    "iso:country":"NL",
    "sg:address":"Nicolaas Maesstraat 49",
    "sg:city":"Enschede",
    "sg:classifiers":[
        {
            "category":"Food & Beverages",
            "subcategory":"Fruits & Vegetables",
            "type":"Retail Goods"
        }
    ],
    "sg:phone":"+31 53 431 5183",
    "sg:postcode":"7545 CD",
    "sg:province":"NL.08",
    "sg:tags":[
        "groenten"
    ],
    "wof:name":"Van Der Linden",
    "wof:placetype":"venue"
},
  "geometry": {"coordinates":[6.862345,52.210381],"type":"Point"}
}