{
  "type": "Feature",
  "properties": {
    "addr:full":"Laanenderweg 65 Alkmaar Noord-Holland 1812 PW",
    "addr:housenumber":"65",
    "addr:postcode":"1812 pw",
    "addr:street":"Laanenderweg",
    "iso:country":"NL",
    "sg:address":"Laanenderweg 65",
    "sg:city":"Alkmaar",
    "sg:orig_category":"Pleziervaartuigen And Reparatie",
    "sg:phone":"+31 72 540 1122",
    "sg:postcode":"1812 PW",
    "sg:province":"Noord-Holland",
    "wof:name":"Pel Kajak Centrum",
    "wof:placetype":"venue"
},
  "geometry": {"coordinates":[4.763191,52.611851],"type":"Point"}
}