{
  "type": "Feature",
  "properties": {
    "addr:full":"Gloriantdreef 321 Utrecht Utrecht 3562 KW",
    "addr:housenumber":"321",
    "addr:postcode":"3562 kw",
    "addr:street":"Gloriantdreef",
    "iso:country":"NL",
    "sg:address":"Gloriantdreef 321",
    "sg:city":"Utrecht",
    "sg:orig_category":"Verenigingen En Stichtingen",
    "sg:phone":"+31 30 262 3850",
    "sg:postcode":"3562 KW",
    "sg:province":"Utrecht",
    "wof:name":"Woongroep",
    "wof:placetype":"venue"
},
  "geometry": {"coordinates":[5.109347,52.114594],"type":"Point"}
}