{
  "type": "Feature",
  "properties": {
    "addr:full":"Molenwerf 21N Uitgeest Noord-Holland 1911 DB",
    "addr:housenumber":"21n",
    "addr:postcode":"1911 db",
    "addr:street":"Molenwerf",
    "iso:country":"NL",
    "sg:address":"Molenwerf 21N",
    "sg:city":"Uitgeest",
    "sg:orig_category":"Adviesbureaus Bouwkunde",
    "sg:phone":"+31 251 315 935",
    "sg:postcode":"1911 DB",
    "sg:province":"Noord-Holland",
    "wof:name":"Bba",
    "wof:placetype":"venue"
},
  "geometry": {"coordinates":[4.719805,52.535969],"type":"Point"}
}