{
  "type": "Feature",
  "properties": {
    "addr:full":"Amersfoortseweg 24 Maarn Utrecht 3951 LB",
    "addr:housenumber":"24",
    "addr:postcode":"3951 lb",
    "addr:street":"Amersfoortseweg",
    "iso:country":"NL",
    "sg:address":"Amersfoortseweg 24",
    "sg:city":"Maarn",
    "sg:orig_category":"Meubelzaken, Woning- And Keukeninrichting",
    "sg:phone":"+31 343 442 144",
    "sg:postcode":"3951 LB",
    "sg:province":"Utrecht",
    "wof:name":"Van Es Bed- En Badmode Bv",
    "wof:placetype":"venue"
},
  "geometry": {"coordinates":[5.356424,52.062737],"type":"Point"}
}