{
  "type": "Feature",
  "properties": {
    "addr:full":"Ruimersdk 50 Diepenheim Overijssel 7478 AL",
    "addr:housenumber":"50",
    "addr:postcode":"7478 al",
    "addr:street":"Ruimersdk",
    "iso:country":"NL",
    "sg:address":"Ruimersdk 50",
    "sg:city":"Diepenheim",
    "sg:orig_category":"Meubelen - Fabrieken En Groothandel",
    "sg:phone":"+31 547 352 209",
    "sg:postcode":"7478 AL",
    "sg:province":"Overijssel",
    "wof:name":"Wissink",
    "wof:placetype":"venue"
},
  "geometry": {"coordinates":[6.556908,52.203197],"type":"Point"}
}