{
  "type": "Feature",
  "properties": {
    "addr:full":"Kerkweg 25 Schoonrewoerd Zuid-Holland 4145 MP",
    "addr:housenumber":"25",
    "addr:postcode":"4145 mp",
    "addr:street":"Kerkweg",
    "iso:country":"NL",
    "sg:address":"Kerkweg 25",
    "sg:city":"Schoonrewoerd",
    "sg:orig_category":"Autokeuringen",
    "sg:phone":"+31 345 641 989",
    "sg:postcode":"4145 MP",
    "sg:province":"Zuid-Holland",
    "wof:name":"H. De Leeuw",
    "wof:placetype":"venue"
},
  "geometry": {"coordinates":[5.131888,51.918026],"type":"Point"}
}