{
  "type": "Feature",
  "properties": {
    "addr:full":"Markt 82 Etten Leur Noord-Brabant 4875 CG",
    "addr:housenumber":"82",
    "addr:postcode":"4875 cg",
    "addr:street":"Markt",
    "iso:country":"NL",
    "sg:address":"Markt 82",
    "sg:city":"Etten Leur",
    "sg:orig_category":"Biljartzalen",
    "sg:phone":"+31 76 501 2459",
    "sg:postcode":"4875 CG",
    "sg:province":"Noord-Brabant",
    "wof:name":"Happy Days",
    "wof:placetype":"venue"
},
  "geometry": {"coordinates":[4.634452,51.571976],"type":"Point"}
}