{
  "type": "Feature",
  "properties": {
    "addr:full":"Ravenswade 110 Nieuwegein Utrecht 3439 LD",
    "addr:housenumber":"110",
    "addr:postcode":"3439 ld",
    "addr:street":"Ravenswade",
    "iso:country":"NL",
    "sg:address":"Ravenswade 110",
    "sg:city":"Nieuwegein",
    "sg:orig_category":"Fotolaboratoria",
    "sg:phone":"+31 30 288 8464",
    "sg:postcode":"3439 LD",
    "sg:province":"Utrecht",
    "wof:name":"S-Color Nieuwegein Bv",
    "wof:placetype":"venue"
},
  "geometry": {"coordinates":[5.11672,52.052738],"type":"Point"}
}