{
  "type": "Feature",
  "properties": {
    "addr:full":"Ijsseldijk 202 Krimpen A/D Ijssel Zuid-Holland 2924 AW",
    "addr:housenumber":"202;a / d",
    "addr:postcode":"2924 aw",
    "addr:street":"Ijsseldijk",
    "iso:country":"NL",
    "sg:address":"Ijsseldijk 202",
    "sg:city":"Krimpen A/D Ijssel",
    "sg:orig_category":"Huizensloop And Bouwrijp Maken",
    "sg:phone":"+31 180 518 307",
    "sg:postcode":"2924 AW",
    "sg:province":"Zuid-Holland",
    "wof:name":"W. Van Rij Grondverzet",
    "wof:placetype":"venue"
},
  "geometry": {"coordinates":[4.600433,51.925083],"type":"Point"}
}