{
  "type": "Feature",
  "properties": {
    "addr:full":"J Wattwg 7 Vlaardingen Zuid-Holland 3133 KK",
    "addr:housenumber":"7",
    "addr:postcode":"3133 kk",
    "iso:country":"NL",
    "sg:address":"J Wattwg 7",
    "sg:city":"Vlaardingen",
    "sg:orig_category":"Hondenscholen",
    "sg:phone":"+31 10 460 2928",
    "sg:postcode":"3133 KK",
    "sg:province":"Zuid-Holland",
    "wof:name":"Woef",
    "wof:placetype":"venue"
},
  "geometry": {"coordinates":[4.317741,51.901566],"type":"Point"}
}