{
  "type": "Feature",
  "properties": {
    "addr:full":"Sniederslaan 25 Bladel North Brabant 5531 EG",
    "addr:housenumber":"25",
    "addr:postcode":"5531 eg",
    "addr:street":"Sniederslaan",
    "iso:country":"NL",
    "sg:address":"Sniederslaan 25",
    "sg:city":"Bladel",
    "sg:orig_category":"Opticiens",
    "sg:phone":"+31 497 383 353",
    "sg:postcode":"5531 EG",
    "sg:province":"North Brabant",
    "wof:name":"Wijnen Van Den Borne Optiek",
    "wof:placetype":"venue"
},
  "geometry": {"coordinates":[5.2182469368,51.3671417236],"type":"Point"}
}