{
  "type": "Feature",
  "properties": {
    "iso:country":"NL",
    "sg:address":"Bachpln 589",
    "sg:city":"Schiedam",
    "sg:orig_category":"Fietsen En Bromfietsen",
    "sg:phone":"+31 10 470 6558",
    "sg:postcode":"3122 JM",
    "sg:province":"Zuid-Holland",
    "wof:name":"Blauwe Brug",
    "wof:placetype":"venue"
},
  "geometry": {"coordinates":[4.373538,51.934563],"type":"Point"}
}