{
  "type": "Feature",
  "properties": {
    "addr:full":"Ystr 30 Enschede NL.08 7523 HK",
    "addr:housenumber":"30",
    "addr:postcode":"7523 hk",
    "addr:street":"Ystr",
    "iso:country":"NL",
    "sg:address":"Ystr 30",
    "sg:city":"Enschede",
    "sg:orig_category":"Verenigingen En Stichtingen",
    "sg:phone":"+31 53 430 5007",
    "sg:postcode":"7523 HK",
    "sg:province":"NL.08",
    "wof:name":"Marokkanen Enschede Noord, Sticht",
    "wof:placetype":"venue"
},
  "geometry": {"coordinates":[6.89691,52.235901],"type":"Point"}
}