{
  "type": "Feature",
  "properties": {
    "iso:country":"NL",
    "sg:address":"Frankenstraat 166",
    "sg:city":"Maastricht",
    "sg:orig_category":"Metaalbekleding And -Behandeling",
    "sg:phone":"+31 43 362 2782",
    "sg:postcode":"6224 GV",
    "sg:province":"Limburg",
    "wof:name":"Sjojo",
    "wof:placetype":"venue"
},
  "geometry": {"coordinates":[5.712874,50.850285],"type":"Point"}
}