{
  "type": "Feature",
  "properties": {
    "addr:full":"Tolstr 26G Haaksbergen Overijssel 7482 DB",
    "addr:housenumber":"26g",
    "addr:postcode":"7482 db",
    "addr:street":"Tolstr",
    "iso:country":"NL",
    "sg:address":"Tolstr 26G",
    "sg:city":"Haaksbergen",
    "sg:orig_category":"Drukkerijen",
    "sg:phone":"+31 53 572 3790",
    "sg:postcode":"7482 DB",
    "sg:province":"Overijssel",
    "sg:website":"HTTP://www.pipimaging.nl",
    "wof:name":"Pip Imaging",
    "wof:placetype":"venue"
},
  "geometry": {"coordinates":[6.712139,52.151428],"type":"Point"}
}