{
  "type": "Feature",
  "properties": {
    "addr:full":"Sophiastraat 15 Leiden South Holland 2316 PJ",
    "addr:housenumber":"15",
    "addr:postcode":"2316 pj",
    "addr:street":"Sophiastraat",
    "iso:country":"NL",
    "sg:address":"Sophiastraat 15",
    "sg:city":"Leiden",
    "sg:orig_category":"Overheidsdiensten",
    "sg:phone":"+31 6 22775296",
    "sg:postcode":"2316 PJ",
    "sg:province":"South Holland",
    "wof:name":"Leidse Watervrienden",
    "wof:placetype":"venue"
},
  "geometry": {"coordinates":[4.5002799034,52.1646614075],"type":"Point"}
}