{
  "type": "Feature",
  "properties": {
    "addr:full":"Dorpsstr 24 Schipluiden Zuid-Holland 2636 CE",
    "addr:housenumber":"24",
    "addr:postcode":"2636 ce",
    "addr:street":"Dorpsstr",
    "iso:country":"NL",
    "sg:address":"Dorpsstr 24",
    "sg:city":"Schipluiden",
    "sg:orig_category":"Glas In Lood",
    "sg:phone":"+31 15 380 9067",
    "sg:postcode":"2636 CE",
    "sg:province":"Zuid-Holland",
    "wof:name":"Vermeer, C",
    "wof:placetype":"venue"
},
  "geometry": {"coordinates":[4.314388,51.976585],"type":"Point"}
}