{
  "type": "Feature",
  "properties": {
    "iso:country":"NL",
    "sg:address":"Nieuweweg 151",
    "sg:city":"Wijchen",
    "sg:orig_category":"Hout Gh",
    "sg:phone":"+31 24 641 5244",
    "sg:postcode":"6603 BL",
    "sg:province":"Gelderland",
    "wof:name":"Praxis",
    "wof:placetype":"venue"
},
  "geometry": {"coordinates":[5.757906,51.80262],"type":"Point"}
}