{
  "type": "Feature",
  "properties": {
    "addr:full":"V Echtenstr 15 Hoogeveen Drenthe 7902 EK",
    "addr:housenumber":"15",
    "addr:postcode":"7902 ek",
    "iso:country":"NL",
    "sg:address":"V Echtenstr 15",
    "sg:city":"Hoogeveen",
    "sg:orig_category":"Fietsen En Bromfietsen",
    "sg:phone":"+31 528 264 020",
    "sg:postcode":"7902 EK",
    "sg:province":"Drenthe",
    "wof:name":"Sijbesma",
    "wof:placetype":"venue"
},
  "geometry": {"coordinates":[6.47552,52.725975],"type":"Point"}
}