{
  "type": "Feature",
  "properties": {
    "addr:full":"Nieuwe Rijn 15 Leiden Zuid-Holland 2312 JC",
    "addr:housenumber":"15",
    "addr:postcode":"2312 jc",
    "addr:street":"Nieuwe Rijn",
    "iso:country":"NL",
    "sg:address":"Nieuwe Rijn 15",
    "sg:city":"Leiden",
    "sg:orig_category":"Werving And Selectie Van Tijdelijk Personeel And Uitzendkantoren",
    "sg:phone":"+31 71 516 0055",
    "sg:postcode":"2312 JC",
    "sg:province":"Zuid-Holland",
    "wof:name":"Imach Uitzendburo",
    "wof:placetype":"venue"
},
  "geometry": {"coordinates":[4.4919347763,52.1585502625],"type":"Point"}
}