{
  "type": "Feature",
  "properties": {
    "addr:full":"Voltwg 11 Hoogerheide North Brabant 4631 SR",
    "addr:housenumber":"11",
    "addr:postcode":"4631 sr",
    "addr:street":"Voltwg",
    "iso:country":"NL",
    "sg:address":"Voltwg 11",
    "sg:city":"Hoogerheide",
    "sg:orig_category":"Fietsen - Fabrieken En Groothandel",
    "sg:phone":"+31 164 612 264",
    "sg:postcode":"4631 SR",
    "sg:province":"North Brabant",
    "wof:name":"Jan Janssen",
    "wof:placetype":"venue"
},
  "geometry": {"coordinates":[4.352019,51.429123],"type":"Point"}
}