{
  "type": "Feature",
  "properties": {
    "addr:full":"Arent Janszoon Ernststr 667 Amsterdam Noord-Holland 1082 LH",
    "addr:housenumber":"667",
    "addr:postcode":"1082 lh",
    "addr:street":"Arent Janszoon Ernststr",
    "iso:country":"NL",
    "sg:address":"Arent Janszoon Ernststr 667",
    "sg:city":"Amsterdam",
    "sg:orig_category":"Diverse Grafische Activiteiten",
    "sg:phone":"+31 20 644 7434",
    "sg:postcode":"1082 LH",
    "sg:province":"Noord-Holland",
    "wof:name":"Qua Forma Design",
    "wof:placetype":"venue"
},
  "geometry": {"coordinates":[4.87334,52.331989],"type":"Point"}
}