{
  "type": "Feature",
  "properties": {
    "addr:full":"Lederambachtstr 166 Amsterdam Noord-Holland 1069 HK",
    "addr:housenumber":"166",
    "addr:postcode":"1069 hk",
    "iso:country":"NL",
    "sg:address":"Lederambachtstr 166",
    "sg:city":"Amsterdam",
    "sg:orig_category":"Vertaalbureaus",
    "sg:phone":"+31 20 470 7910",
    "sg:postcode":"1069 HK",
    "sg:province":"Noord-Holland",
    "sg:website":"http://www.transcopy.nl",
    "wof:name":"Trans Copy",
    "wof:placetype":"venue"
},
  "geometry": {"coordinates":[4.79581,52.354794],"type":"Point"}
}