{
  "type": "Feature",
  "properties": {
    "iso:country":"NL",
    "sg:address":"Joh. Enschedeweg 15",
    "sg:city":"Uithoorn",
    "sg:orig_category":"Koeriersdiensten",
    "sg:phone":"+31 297 560 039",
    "sg:postcode":"1422 DR",
    "sg:province":"Noord-Holland",
    "wof:name":"Express Car",
    "wof:placetype":"venue"
},
  "geometry": {"coordinates":[4.839918,52.243198],"type":"Point"}
}