{
  "type": "Feature",
  "properties": {
    "addr:full":"Nw Loosdrechtsedk 96A Loosdrecht Noord-Holland 1231 LA",
    "addr:housenumber":"96a",
    "addr:postcode":"1231 la",
    "iso:country":"NL",
    "sg:address":"Nw Loosdrechtsedk 96A",
    "sg:city":"Loosdrecht",
    "sg:orig_category":"Peuterspeelzalen",
    "sg:phone":"+31 35 582 4719",
    "sg:postcode":"1231 LA",
    "sg:province":"Noord-Holland",
    "wof:name":"Appeltje, 'T",
    "wof:placetype":"venue"
},
  "geometry": {"coordinates":[5.099436,52.20718],"type":"Point"}
}