{
  "type": "Feature",
  "properties": {
    "addr:full":"Eenbes 10 Rotterdam Zuid-Holland 3069 LM",
    "addr:housenumber":"10",
    "addr:postcode":"3069 lm",
    "addr:street":"Eenbes",
    "iso:country":"NL",
    "sg:address":"Eenbes 10",
    "sg:city":"Rotterdam",
    "sg:orig_category":"Webdesign Bureaus",
    "sg:phone":"+31 10 286 7986",
    "sg:postcode":"3069 LM",
    "sg:province":"Zuid-Holland",
    "wof:name":"Mmcd",
    "wof:placetype":"venue"
},
  "geometry": {"coordinates":[4.5513567924,51.9693908691],"type":"Point"}
}