{
  "type": "Feature",
  "properties": {
    "iso:country":"NL",
    "sg:address":"Brederostraat 90",
    "sg:city":"Zwolle",
    "sg:orig_category":"Juridische Dienstverlening",
    "sg:phone":"+31 38 454 9555",
    "sg:postcode":"8023 AW",
    "sg:province":"Overijssel",
    "wof:name":"Iq Media-Internet Quality & Design",
    "wof:placetype":"venue"
},
  "geometry": {"coordinates":[6.115693,52.516415],"type":"Point"}
}