{
  "type": "Feature",
  "properties": {
    "iso:country":"NL",
    "sg:address":"Asterstr 51",
    "sg:city":"Oss",
    "sg:orig_category":"Levensmiddelen - Fabrieken En Groothandel",
    "sg:phone":"+31 412 648 312",
    "sg:postcode":"5342 BL",
    "sg:province":"Virginia",
    "wof:name":"Looman Bv",
    "wof:placetype":"venue"
},
  "geometry": {"coordinates":[-77.235214,38.312599],"type":"Point"}
}