{
  "type": "Feature",
  "properties": {
    "addr:full":"Rapsodieplnts 6 Almere Flevoland 1312 EJ",
    "addr:housenumber":"6",
    "addr:postcode":"1312 ej",
    "addr:street":"Rapsodieplnts;Flevoland",
    "iso:country":"NL",
    "sg:address":"Rapsodieplnts 6",
    "sg:city":"Almere",
    "sg:orig_category":"Adviesbureaus Financieel",
    "sg:phone":"+31 36 529 7681",
    "sg:postcode":"1312 EJ",
    "sg:province":"Flevoland",
    "sg:website":"http://www.trecon.nl",
    "wof:name":"Trecon Bv",
    "wof:placetype":"venue"
},
  "geometry": {"coordinates":[5.18826,52.375332],"type":"Point"}
}