{
  "type": "Feature",
  "properties": {
    "addr:full":"Ysselstr 23 Krimpen Ad Yssel Zuid-Holland 2922 AR",
    "addr:housenumber":"23;2922",
    "addr:street":"Ysselstr",
    "iso:country":"NL",
    "sg:address":"Ysselstr 23",
    "sg:city":"Krimpen Ad Yssel",
    "sg:orig_category":"Bloemen En Planten - Decoratie",
    "sg:phone":"+31 6 14114904",
    "sg:postcode":"2922 AR",
    "sg:province":"Zuid-Holland",
    "wof:name":"Hanneke",
    "wof:placetype":"venue"
},
  "geometry": {"coordinates":[4.59243,51.918571],"type":"Point"}
}