{
  "type": "Feature",
  "properties": {
    "iso:country":"NL",
    "sg:address":"Stationsstr 37",
    "sg:city":"Waalwyk",
    "sg:orig_category":"Schoenen",
    "sg:phone":"+31 416 651 598",
    "sg:postcode":"5141 GB",
    "sg:province":"Noord-Brabant",
    "wof:name":"Mata Hari",
    "wof:placetype":"venue"
},
  "geometry": {"coordinates":[5.067154,51.688629],"type":"Point"}
}