{
  "type": "Feature",
  "properties": {
    "iso:country":"NL",
    "sg:address":"H Andriessenweg 40",
    "sg:city":"Almere",
    "sg:orig_category":"Loodgieterswerk, Verwarming And Sanitaire Installaties",
    "sg:phone":"+31 36 536 7226",
    "sg:postcode":"1323 EP",
    "sg:province":"NL.",
    "wof:name":"Installatie- En Onderhoudsburo Van Der Veer",
    "wof:placetype":"venue"
},
  "geometry": {"coordinates":[5.195985,52.363743],"type":"Point"}
}