{
  "type": "Feature",
  "properties": {
    "addr:full":"Voorstad St Jacob 158 Roermond Limburg 6041 LN",
    "addr:housenumber":"158",
    "addr:postcode":"6041 ln",
    "addr:street":"Voorstad St Jacob",
    "iso:country":"NL",
    "sg:address":"Voorstad St Jacob 158",
    "sg:city":"Roermond",
    "sg:orig_category":"Jachthavens - Jachtwerven",
    "sg:phone":"+31 475 318 304",
    "sg:postcode":"6041 LN",
    "sg:province":"Limburg",
    "wof:name":"Steelhaven Bv",
    "wof:placetype":"venue"
},
  "geometry": {"coordinates":[5.977723,51.189732],"type":"Point"}
}