{
  "type": "Feature",
  "properties": {
    "addr:full":"W Hentostr 26 Marienberg Overijssel 7692 AM",
    "addr:housenumber":"26",
    "addr:postcode":"7692",
    "addr:street":"W",
    "iso:country":"NL",
    "sg:address":"W Hentostr 26",
    "sg:city":"Marienberg",
    "sg:orig_category":"Honden- En Kattentrimsalons",
    "sg:phone":"+31 523 251 680",
    "sg:postcode":"7692 AM",
    "sg:province":"Overijssel",
    "wof:name":"Mirjam",
    "wof:placetype":"venue"
},
  "geometry": {"coordinates":[6.57466,52.511597],"type":"Point"}
}