{
  "type": "Feature",
  "properties": {
    "addr:full":"Krommebeemd 55 Oosterhout Nb Noord-Brabant 4907 DS",
    "addr:housenumber":"55",
    "addr:postcode":"4907 ds",
    "addr:street":"Krommebeemd",
    "iso:country":"NL",
    "sg:address":"Krommebeemd 55",
    "sg:city":"Oosterhout Nb",
    "sg:orig_category":"Kantoorartikelen",
    "sg:phone":"+31 162 470 479",
    "sg:postcode":"4907 DS",
    "sg:province":"Noord-Brabant",
    "wof:name":"Servitek Oosterhout",
    "wof:placetype":"venue"
},
  "geometry": {"coordinates":[4.8604240417,51.6592826843],"type":"Point"}
}