{
  "type": "Feature",
  "properties": {
    "addr:full":"Koninginnelaan 106 Rijswijk Zh Zuid-Holland 2281 HH",
    "addr:housenumber":"106",
    "addr:postcode":"zh;2281 hh",
    "addr:street":"Koninginnelaan",
    "iso:country":"NL",
    "sg:address":"Koninginnelaan 106",
    "sg:city":"Rijswijk Zh",
    "sg:orig_category":"Diverse Grafische Activiteiten",
    "sg:phone":"+31 70 399 6086",
    "sg:postcode":"2281 HH",
    "sg:province":"Zuid-Holland",
    "wof:name":"Fred Schellart",
    "wof:placetype":"venue"
},
  "geometry": {"coordinates":[4.3453,52.055176],"type":"Point"}
}