{
  "type": "Feature",
  "properties": {
    "addr:full":"Venkelstraat 18 Brielle South Holland 3231 XT",
    "addr:housenumber":"18",
    "addr:postcode":"3231 xt",
    "addr:street":"Venkelstraat",
    "iso:country":"NL",
    "sg:address":"Venkelstraat 18",
    "sg:city":"Brielle",
    "sg:classifiers":[
        {
            "category":"Education",
            "subcategory":"Preschool",
            "type":"Public Place"
        }
    ],
    "sg:phone":"+31 181 414 557",
    "sg:postcode":"3231 XT",
    "sg:province":"South Holland",
    "sg:tags":[
        "kleuteronderwijs",
        "basis-"
    ],
    "wof:name":"Christelijke Basisschool Ichthus",
    "wof:placetype":"venue"
},
  "geometry": {"coordinates":[4.163318,51.901806],"type":"Point"}
}