{
  "type": "Feature",
  "properties": {
    "iso:country":"NL",
    "sg:address":"Biltstr 166",
    "sg:city":"Utrecht",
    "sg:orig_category":"Grafisch Ontwerpers",
    "sg:phone":"+31 30 276 3550",
    "sg:postcode":"3572 BP",
    "sg:province":"Utrecht",
    "sg:website":"http://www.xs4all.nl/~havb",
    "wof:name":"Bostelen, Herman Van",
    "wof:placetype":"venue"
},
  "geometry": {"coordinates":[5.136392,52.095715],"type":"Point"}
}