{
  "type": "Feature",
  "properties": {
    "addr:full":"Reigerstraat 18 Ilpendam Noord-Holland 1452 XR",
    "addr:housenumber":"18",
    "addr:postcode":"1452 xr",
    "addr:street":"Reigerstraat",
    "iso:country":"NL",
    "sg:address":"Reigerstraat 18",
    "sg:city":"Ilpendam",
    "sg:orig_category":"Huishoudapparatuur, Televisies And Radio'S",
    "sg:phone":"+31 20 436 1530",
    "sg:postcode":"1452 XR",
    "sg:province":"Noord-Holland",
    "wof:name":"Bv Handelmaatschappij Asbeek Brusse",
    "wof:placetype":"venue"
},
  "geometry": {"coordinates":[4.954206,52.465576],"type":"Point"}
}