{
  "type": "Feature",
  "properties": {
    "addr:full":"Pieter Christiaanstraat 9 Sint Oedenrode North Brabant 5491 JN",
    "addr:housenumber":"9",
    "addr:postcode":"5491 jn",
    "addr:street":"Pieter Christiaanstraat;Oedenrode",
    "iso:country":"NL",
    "sg:address":"Pieter Christiaanstraat 9",
    "sg:city":"Sint Oedenrode",
    "sg:orig_category":"Bloemen And Planten",
    "sg:phone":"+31 413 478 161",
    "sg:postcode":"5491 JN",
    "sg:province":"North Brabant",
    "wof:name":"Bloembinderij Le Papillon",
    "wof:placetype":"venue"
},
  "geometry": {"coordinates":[5.456807,51.571709],"type":"Point"}
}