{
  "type": "Feature",
  "properties": {
    "iso:country":"NL",
    "sg:address":"Boeingavenue 204",
    "sg:city":"Schiphol Ryk",
    "sg:orig_category":"Accountants - Administratie- Consulenten En -Kantoren",
    "sg:phone":"+31 20 653 1812",
    "sg:postcode":"1119 PN",
    "sg:province":"Noord-Holland",
    "wof:name":"Wallast",
    "wof:placetype":"venue"
},
  "geometry": {"coordinates":[4.752996,52.277473],"type":"Point"}
}