{
  "type": "Feature",
  "properties": {
    "addr:full":"Boeingavenue 204 Schiphol Ryk Noord-Holland 1119 PN",
    "addr:housenumber":"204",
    "addr:postcode":"1119 pn",
    "addr:street":"Boeingavenue",
    "iso:country":"NL",
    "sg:address":"Boeingavenue 204",
    "sg:city":"Schiphol Ryk",
    "sg:orig_category":"Accountants - Administratie- Consulenten En -Kantoren",
    "sg:phone":"+31 20 653 1812",
    "sg:postcode":"1119 PN",
    "sg:province":"Noord-Holland",
    "wof:name":"Wallast",
    "wof:placetype":"venue"
},
  "geometry": {"coordinates":[4.752996,52.277473],"type":"Point"}
}