{
  "type": "Feature",
  "properties": {
    "addr:full":"Geulstr 34 Bunde Limburg 6241 NA",
    "addr:housenumber":"34",
    "addr:postcode":"6241 na",
    "addr:street":"Geulstr",
    "iso:country":"NL",
    "sg:address":"Geulstr 34",
    "sg:city":"Bunde",
    "sg:orig_category":"Administratie- En Boekhoudkantoren",
    "sg:phone":"+31 43 365 2441",
    "sg:postcode":"6241 NA",
    "sg:province":"Limburg",
    "wof:name":"Caris, P J M",
    "wof:placetype":"venue"
},
  "geometry": {"coordinates":[5.725678,50.897873],"type":"Point"}
}