{
  "type": "Feature",
  "properties": {
    "iso:country":"NL",
    "sg:address":"Lindberghstraat 33",
    "sg:city":"Hoogeveen",
    "sg:orig_category":"Technische Studies And Onderzoek",
    "sg:phone":"+31 528 225 678",
    "sg:postcode":"7903 BM",
    "sg:province":"Provincie Drenthe",
    "wof:name":"Troll Engineering",
    "wof:placetype":"venue"
},
  "geometry": {"coordinates":[6.529036,52.732582],"type":"Point"}
}