{
  "type": "Feature",
  "properties": {
    "iso:country":"NL",
    "sg:address":"Badhuiswg 21",
    "sg:city":"Zutphen",
    "sg:orig_category":"Loodgieters",
    "sg:phone":"+31 575 517 725",
    "sg:postcode":"7201 GM",
    "sg:province":"Gelderland",
    "wof:name":"Boer Vof, H",
    "wof:placetype":"venue"
},
  "geometry": {"coordinates":[6.19285,52.135914],"type":"Point"}
}