{
  "type": "Feature",
  "properties": {
    "iso:country":"NL",
    "sg:address":"Willemstr 2A",
    "sg:city":"Waalre",
    "sg:orig_category":"Wasmachines En Wasdrogers",
    "sg:phone":"+31 40 221 3942",
    "sg:postcode":"5583 CK",
    "sg:province":"Noord-Brabant",
    "wof:name":"Oers, Van",
    "wof:placetype":"venue"
},
  "geometry": {"coordinates":[5.4843840599,51.3995742798],"type":"Point"}
}