{
  "type": "Feature",
  "properties": {
    "addr:full":"Van Coevenhovenstraat 35 Heemskerk North Holland 1961 NW",
    "addr:housenumber":"35",
    "addr:postcode":"1961 nw",
    "addr:street":"Van Coevenhovenstraat",
    "iso:country":"NL",
    "sg:address":"Van Coevenhovenstraat 35",
    "sg:city":"Heemskerk",
    "sg:orig_category":"Kantoorartikelen",
    "sg:phone":"+31 251 245 010",
    "sg:postcode":"1961 NW",
    "sg:province":"North Holland",
    "wof:name":"Stumpel Bv",
    "wof:placetype":"venue"
},
  "geometry": {"coordinates":[4.6691231728,52.5111618042],"type":"Point"}
}