{
  "type": "Feature",
  "properties": {
    "iso:country":"NL",
    "sg:address":"Vryburgln 1",
    "sg:city":"Heemskerk",
    "sg:orig_category":"Recreatie",
    "sg:phone":"+31 251 238 191",
    "sg:postcode":"1962 VA",
    "sg:province":"Noord-Holland",
    "wof:name":"Kinderboerderij Heemskerk, Sticht",
    "wof:placetype":"venue"
},
  "geometry": {"coordinates":[-79.771446,38.003349],"type":"Point"}
}