{
  "type": "Feature",
  "properties": {
    "addr:full":"Vryburgln 1 Heemskerk Noord-Holland 1962 VA",
    "addr:housenumber":"1",
    "addr:postcode":"1962",
    "addr:street":"Vryburgln",
    "iso:country":"NL",
    "sg:address":"Vryburgln 1",
    "sg:city":"Heemskerk",
    "sg:orig_category":"Recreatie",
    "sg:phone":"+31 251 238 191",
    "sg:postcode":"1962 VA",
    "sg:province":"Noord-Holland",
    "wof:name":"Kinderboerderij Heemskerk, Sticht",
    "wof:placetype":"venue"
},
  "geometry": {"coordinates":[-79.771446,38.003349],"type":"Point"}
}