{
  "type": "Feature",
  "properties": {
    "iso:country":"NL",
    "sg:address":"Kamp 43",
    "sg:city":"Amersfoort",
    "sg:orig_category":"Werving And Selectie Van Tijdelijk Personeel And Uitzendkantoren",
    "sg:phone":"+31 33 472 9413",
    "sg:postcode":"3811 AN",
    "sg:province":"Utrecht",
    "wof:name":"Viawerk Uitzendbureau",
    "wof:placetype":"venue"
},
  "geometry": {"coordinates":[5.3956108093,52.1578292847],"type":"Point"}
}