{
  "type": "Feature",
  "properties": {
    "addr:full":"Hasseltweg 10 Haaksbergen Overijssel 7481 VB",
    "addr:housenumber":"10",
    "addr:postcode":"7481 vb",
    "addr:street":"Hasseltweg",
    "iso:country":"NL",
    "sg:address":"Hasseltweg 10",
    "sg:city":"Haaksbergen",
    "sg:classifiers":[
        {
            "category":"Education",
            "subcategory":"Preschool",
            "type":"Public Place"
        }
    ],
    "sg:phone":"+31 53 572 1548",
    "sg:postcode":"7481 VB",
    "sg:province":"Overijssel",
    "sg:tags":[
        "kleuteronderwijs",
        "basis-"
    ],
    "wof:name":"Hone School",
    "wof:placetype":"venue"
},
  "geometry": {"coordinates":[6.733987,52.140656],"type":"Point"}
}