{
  "type": "Feature",
  "properties": {
    "addr:full":"Pr Bernhardln 19 Amersfoort Utrecht 3818 ZE",
    "addr:housenumber":"19",
    "addr:postcode":"3818 ze",
    "iso:country":"NL",
    "sg:address":"Pr Bernhardln 19",
    "sg:city":"Amersfoort",
    "sg:orig_category":"Adviesbureaus Marketing",
    "sg:phone":"+31 33 461 0591",
    "sg:postcode":"3818 ZE",
    "sg:province":"Utrecht",
    "wof:name":"Wezenberg",
    "wof:placetype":"venue"
},
  "geometry": {"coordinates":[5.386085,52.152325],"type":"Point"}
}