{
  "type": "Feature",
  "properties": {
    "iso:country":"NL",
    "sg:address":"Duinwg 14",
    "sg:city":"Hellevoetsluis",
    "sg:orig_category":"Woninginrichting",
    "sg:phone":"+31 181 339 690",
    "sg:postcode":"3221 LC",
    "sg:province":"Zuid-Holland",
    "wof:name":"Rijma",
    "wof:placetype":"venue"
},
  "geometry": {"coordinates":[4.0849041939,51.838394165],"type":"Point"}
}