{
  "type": "Feature",
  "properties": {
    "addr:full":"Emelissedijk 247-249 Rotterdam Zuid-Holland 3079 HA",
    "addr:housenumber":"247-249",
    "addr:postcode":"3079 ha",
    "addr:street":"Emelissedijk",
    "iso:country":"NL",
    "sg:address":"Emelissedijk 247-249",
    "sg:city":"Rotterdam",
    "sg:classifiers":[
        {
            "category":"Fast Food",
            "type":"Food & Drink"
        }
    ],
    "sg:phone":"+31 10 483 1450",
    "sg:postcode":"3079 HA",
    "sg:province":"Zuid-Holland",
    "sg:tags":[
        "afhaal",
        "restaurant"
    ],
    "wof:name":"Chinees-Indisch Restaurant Golden Palace",
    "wof:placetype":"venue"
},
  "geometry": {"coordinates":[4.548045,51.878899],"type":"Point"}
}