{
  "type": "Feature",
  "properties": {
    "iso:country":"NL",
    "sg:address":"K Hei 4",
    "sg:city":"Sprundel",
    "sg:orig_category":"Verpakkingsbedrijven",
    "sg:phone":"+31 165 383 039",
    "sg:postcode":"4714 RD",
    "sg:province":"Noord-Brabant",
    "wof:name":"Eskopack Bv",
    "wof:placetype":"venue"
},
  "geometry": {"coordinates":[4.586168,51.53693],"type":"Point"}
}