{
  "type": "Feature",
  "properties": {
    "addr:full":"Berkakkers 1A Eersel Noord-Brabant 5521 GD",
    "addr:housenumber":"1a",
    "addr:postcode":"5521 gd",
    "addr:street":"Berkakkers",
    "iso:country":"NL",
    "sg:address":"Berkakkers 1A",
    "sg:city":"Eersel",
    "sg:orig_category":"Scholen Voor Basisonderwijs",
    "sg:phone":"+31 497 514 657",
    "sg:postcode":"5521 GD",
    "sg:province":"Noord-Brabant",
    "wof:name":"Busseltje Openb, 'T",
    "wof:placetype":"venue"
},
  "geometry": {"coordinates":[5.30905,51.358311],"type":"Point"}
}