{
  "type": "Feature",
  "properties": {
    "addr:full":"Bellewg 4 Someren Noord-Brabant 5711 DH",
    "addr:housenumber":"4",
    "addr:postcode":"5711 dh",
    "addr:street":"Bellewg",
    "iso:country":"NL",
    "sg:address":"Bellewg 4",
    "sg:city":"Someren",
    "sg:orig_category":"Metaalbewerking",
    "sg:phone":"+31 493 440 088",
    "sg:postcode":"5711 DH",
    "sg:province":"Noord-Brabant",
    "wof:name":"Laar-Verboogen Vof, Van De",
    "wof:placetype":"venue"
},
  "geometry": {"coordinates":[5.725837,51.388588],"type":"Point"}
}