{
  "type": "Feature",
  "properties": {
    "addr:full":"Herensngl 151 Haarlem Noord-Holland 2032 RW",
    "addr:housenumber":"151",
    "addr:postcode":"2032 rw",
    "iso:country":"NL",
    "sg:address":"Herensngl 151",
    "sg:city":"Haarlem",
    "sg:orig_category":"Onderhoudswerken",
    "sg:phone":"+31 23 535 3067",
    "sg:postcode":"2032 RW",
    "sg:province":"Noord-Holland",
    "wof:name":"Molling",
    "wof:placetype":"venue"
},
  "geometry": {"coordinates":[4.65117,52.378342],"type":"Point"}
}