{
  "type": "Feature",
  "properties": {
    "addr:full":"Jan Campertlaan 16 Oegstgeest Zuid-Holland 2343 DH",
    "addr:housenumber":"16",
    "addr:postcode":"2343 dh",
    "addr:street":"Jan Campertlaan",
    "iso:country":"NL",
    "sg:address":"Jan Campertlaan 16",
    "sg:city":"Oegstgeest",
    "sg:orig_category":"Schoonheidssalons",
    "sg:phone":"+31 71 519 0100",
    "sg:postcode":"2343 DH",
    "sg:province":"Zuid-Holland",
    "wof:name":"Beautique Oegstgeest",
    "wof:placetype":"venue"
},
  "geometry": {"coordinates":[4.479829,52.192089],"type":"Point"}
}