{
  "type": "Feature",
  "properties": {
    "addr:full":"Noordeinde 159 Almere NL. 1334 AN",
    "addr:housenumber":"159",
    "addr:postcode":"1334 an",
    "addr:street":"Noordeinde;Nl.",
    "iso:country":"NL",
    "sg:address":"Noordeinde 159",
    "sg:city":"Almere",
    "sg:orig_category":"Banken And Kredietinstellingen",
    "sg:phone":"+31 36 532 1520",
    "sg:postcode":"1334 AN",
    "sg:province":"NL.",
    "wof:name":"Sns Bank Randstad",
    "wof:placetype":"venue"
},
  "geometry": {"coordinates":[5.277256,52.395008],"type":"Point"}
}