{
  "type": "Feature",
  "properties": {
    "iso:country":"NL",
    "sg:address":"Louwesweg 1",
    "sg:city":"Amsterdam",
    "sg:orig_category":"Hoger Onderwijs",
    "sg:phone":"+31 20 518 8888",
    "sg:postcode":"1066 EA",
    "sg:province":"Noord-Holland",
    "wof:name":"Academisch Centrum Tandheelkunde Amsterdam",
    "wof:placetype":"venue"
},
  "geometry": {"coordinates":[4.826301,52.346596],"type":"Point"}
}