{
  "type": "Feature",
  "properties": {
    "addr:full":"Eemdijk 102 Eemdijk Utrecht 3754 NK",
    "addr:housenumber":"102",
    "addr:postcode":"3754 nk",
    "addr:street":"Eemdijk",
    "iso:country":"NL",
    "sg:address":"Eemdijk 102",
    "sg:city":"Eemdijk",
    "sg:orig_category":"Verzekeringen",
    "sg:phone":"+31 33 298 2646",
    "sg:postcode":"3754 NK",
    "sg:province":"Utrecht",
    "wof:name":"Vof De Jong En Van Diermen",
    "wof:placetype":"venue"
},
  "geometry": {"coordinates":[5.327646,52.253628],"type":"Point"}
}