{
  "type": "Feature",
  "properties": {
    "addr:full":"Greffelingsestraat 29 Alphen Gld Gelderland 6626 AP",
    "addr:housenumber":"29",
    "addr:postcode":"6626 ap",
    "addr:street":"Greffelingsestraat;Gld Gelderland",
    "iso:country":"NL",
    "sg:address":"Greffelingsestraat 29",
    "sg:city":"Alphen Gld",
    "sg:orig_category":"Pleziervaartuigen And Reparatie",
    "sg:phone":"+31 487 561 304",
    "sg:postcode":"6626 AP",
    "sg:province":"Gelderland",
    "wof:name":"W P Van Ooijen",
    "wof:placetype":"venue"
},
  "geometry": {"coordinates":[5.47509,51.824944],"type":"Point"}
}