{
  "type": "Feature",
  "properties": {
    "addr:full":"Schildstraat 46 Brunssum Limburg 6444 XM",
    "addr:housenumber":"46",
    "addr:postcode":"6444 xm",
    "addr:street":"Schildstraat",
    "iso:country":"NL",
    "sg:address":"Schildstraat 46",
    "sg:city":"Brunssum",
    "sg:orig_category":"Bloemen And Planten",
    "sg:phone":"+31 45 543 0830",
    "sg:postcode":"6444 XM",
    "sg:province":"Limburg",
    "wof:name":"Bloemsierkunst Veders",
    "wof:placetype":"venue"
},
  "geometry": {"coordinates":[5.952124,50.936127],"type":"Point"}
}