{
  "type": "Feature",
  "properties": {
    "addr:full":"V L Stirumstr 20A Amsterdam Noord-Holland 1051 BB",
    "addr:housenumber":"20a",
    "addr:postcode":"1051 bb",
    "addr:street":"V",
    "iso:country":"NL",
    "sg:address":"V L Stirumstr 20A",
    "sg:city":"Amsterdam",
    "sg:orig_category":"Verenigingen En Stichtingen",
    "sg:phone":"+31 20 688 5700",
    "sg:postcode":"1051 BB",
    "sg:province":"Noord-Holland",
    "wof:name":"Nationaal Jeugd Orkest, Sticht",
    "wof:placetype":"venue"
},
  "geometry": {"coordinates":[4.87107,52.37925],"type":"Point"}
}