{
  "type": "Feature",
  "properties": {
    "addr:full":"Kastanjelaan 9 Apeldoorn Gelderland 7316 BM",
    "addr:housenumber":"9",
    "addr:postcode":"7316 bm",
    "addr:street":"Kastanjelaan;Gelderland",
    "iso:country":"NL",
    "sg:address":"Kastanjelaan 9",
    "sg:city":"Apeldoorn",
    "sg:classifiers":[
        {
            "category":"Education",
            "subcategory":"Preschool",
            "type":"Public Place"
        }
    ],
    "sg:phone":"+31 55 579 0390",
    "sg:postcode":"7316 BM",
    "sg:province":"Gelderland",
    "sg:tags":[
        "kleuteronderwijs",
        "basis-"
    ],
    "wof:name":"De Parkenschool",
    "wof:placetype":"venue"
},
  "geometry": {"coordinates":[5.966477,52.22015],"type":"Point"}
}