{
  "type": "Feature",
  "properties": {
    "addr:full":"Sassenstraat 53 Zwolle Overijssel 8011 PB",
    "addr:housenumber":"53",
    "addr:postcode":"8011 pb",
    "addr:street":"Sassenstraat",
    "iso:country":"NL",
    "sg:address":"Sassenstraat 53",
    "sg:city":"Zwolle",
    "sg:orig_category":"Juridische Dienstverlening",
    "sg:phone":"+31 38 422 8847",
    "sg:postcode":"8011 PB",
    "sg:province":"Overijssel",
    "wof:name":"Provisa",
    "wof:placetype":"venue"
},
  "geometry": {"coordinates":[6.095746,52.509964],"type":"Point"}
}