{
  "type": "Feature",
  "properties": {
    "addr:full":"Industriestr 19 Numansdorp South Holland 3281 LB",
    "addr:housenumber":"19",
    "addr:postcode":"3281 lb",
    "addr:street":"Industriestr",
    "iso:country":"NL",
    "sg:address":"Industriestr 19",
    "sg:city":"Numansdorp",
    "sg:orig_category":"Onderhoudswerken",
    "sg:phone":"+31 186 653 022",
    "sg:postcode":"3281 LB",
    "sg:province":"South Holland",
    "wof:name":"Hart Pernis Bv, G 'T",
    "wof:placetype":"venue"
},
  "geometry": {"coordinates":[4.447305,51.743942],"type":"Point"}
}