{
  "type": "Feature",
  "properties": {
    "addr:full":"P Keyln 17 Bloemendaal Noord-Holland 2061 XT",
    "addr:housenumber":"17",
    "addr:postcode":"2061 xt",
    "iso:country":"NL",
    "sg:address":"P Keyln 17",
    "sg:city":"Bloemendaal",
    "sg:orig_category":"Adviesbureaus Bedrijfsorganisatie",
    "sg:phone":"+31 23 526 8321",
    "sg:postcode":"2061 XT",
    "sg:province":"Noord-Holland",
    "wof:name":"At Tune Bv",
    "wof:placetype":"venue"
},
  "geometry": {"coordinates":[4.622791,52.405197],"type":"Point"}
}