{
  "type": "Feature",
  "properties": {
    "addr:full":"Veldwg 1 Laren Nh North Holland 1251 HC",
    "addr:housenumber":"1",
    "addr:postcode":"1251 hc",
    "addr:street":"Veldwg;Nh North",
    "iso:country":"NL",
    "sg:address":"Veldwg 1",
    "sg:city":"Laren Nh",
    "sg:orig_category":"Kappers",
    "sg:phone":"+31 35 538 7372",
    "sg:postcode":"1251 HC",
    "sg:province":"North Holland",
    "wof:name":"Elegance",
    "wof:placetype":"venue"
},
  "geometry": {"coordinates":[5.227684021,52.2607650757],"type":"Point"}
}