{
  "type": "Feature",
  "properties": {
    "addr:full":"Nieuwe Ebbingestraat 16 Groningen Groningen 9712 NK",
    "addr:housenumber":"16",
    "addr:postcode":"9712 nk",
    "addr:street":"Nieuwe Ebbingestraat",
    "iso:country":"NL",
    "sg:address":"Nieuwe Ebbingestraat 16",
    "sg:city":"Groningen",
    "sg:orig_category":"Meubelzaken, Woning- And Keukeninrichting",
    "sg:phone":"+31 50 312 6339",
    "sg:postcode":"9712 NK",
    "sg:province":"Groningen",
    "wof:name":"Het Rietmeubelhuis",
    "wof:placetype":"venue"
},
  "geometry": {"coordinates":[6.5643820763,53.2225723267],"type":"Point"}
}