{
  "type": "Feature",
  "properties": {
    "iso:country":"NL",
    "sg:address":"Gestelsestraat 51",
    "sg:city":"Eindhoven",
    "sg:orig_category":"Verzekeringen",
    "sg:phone":"+31 40 252 4023",
    "sg:postcode":"5615 LA",
    "sg:province":"Noord-Brabant",
    "wof:name":"Pieter Dekker Assurantien En Hypotheken",
    "wof:placetype":"venue"
},
  "geometry": {"coordinates":[5.472095,51.431217],"type":"Point"}
}