{
  "type": "Feature",
  "properties": {
    "addr:full":"De Pol 35 De Pol Overijssel 8337 KT",
    "addr:postcode":"8337 kt",
    "addr:street":"De;De;Overijssel",
    "iso:country":"NL",
    "sg:address":"De Pol 35",
    "sg:city":"De Pol",
    "sg:orig_category":"Kampeerterreinen",
    "sg:phone":"+31 521 588 241",
    "sg:postcode":"8337 KT",
    "sg:province":"Overijssel",
    "wof:name":"Camping T Veentje",
    "wof:placetype":"venue"
},
  "geometry": {"coordinates":[6.0764579773,52.8237762451],"type":"Point"}
}