{
  "type": "Feature",
  "properties": {
    "addr:full":"Toldwstr 2 Amsterdam Noord-Holland 1073 RR",
    "addr:housenumber":"2",
    "addr:postcode":"1073 rr",
    "addr:street":"Toldwstr",
    "iso:country":"NL",
    "sg:address":"Toldwstr 2",
    "sg:city":"Amsterdam",
    "sg:orig_category":"Kappers",
    "sg:phone":"+31 20 671 3006",
    "sg:postcode":"1073 RR",
    "sg:province":"Noord-Holland",
    "wof:name":"Ted",
    "wof:placetype":"venue"
},
  "geometry": {"coordinates":[4.900982,52.352299],"type":"Point"}
}