{
  "type": "Feature",
  "properties": {
    "addr:full":"De Schutsboom 3 Helvoirt Noord-Brabant 5268 EP",
    "addr:housenumber":"3",
    "addr:postcode":"5268 ep",
    "addr:street":"De Schutsboom",
    "iso:country":"NL",
    "sg:address":"De Schutsboom 3",
    "sg:city":"Helvoirt",
    "sg:orig_category":"Jachten - Schilderwerken En Onderhoud",
    "sg:phone":"+31 418 639 430",
    "sg:postcode":"5268 EP",
    "sg:province":"Noord-Brabant",
    "wof:name":"Groenendaal, J M",
    "wof:placetype":"venue"
},
  "geometry": {"coordinates":[5.227571,51.626022],"type":"Point"}
}