{
  "type": "Feature",
  "properties": {
    "iso:country":"NL",
    "sg:address":"Hartensewg 58",
    "sg:city":"Wageningen",
    "sg:classifiers":[
        {
            "category":"Sports & Exercise",
            "subcategory":"Stables",
            "type":"Entertainment"
        }
    ],
    "sg:phone":"+31 317 312 910",
    "sg:postcode":"6704 PA",
    "sg:province":"Gelderland",
    "sg:tags":[
        "maneges"
    ],
    "wof:name":"Renkumse Manege",
    "wof:placetype":"venue"
},
  "geometry": {"coordinates":[5.716086,51.984631],"type":"Point"}
}