{
  "type": "Feature",
  "properties": {
    "addr:full":"Bankastraat 1 Doetinchem Gelderland 7009 GA",
    "addr:housenumber":"1",
    "addr:postcode":"7009 ga",
    "addr:street":"Bankastraat;Gelderland",
    "iso:country":"NL",
    "sg:address":"Bankastraat 1",
    "sg:city":"Doetinchem",
    "sg:orig_category":"Loodgieterswerk, Verwarming And Sanitaire Installaties",
    "sg:phone":"+31 314 335 847",
    "sg:postcode":"7009 GA",
    "sg:province":"Gelderland",
    "wof:name":"J.J. Brand",
    "wof:placetype":"venue"
},
  "geometry": {"coordinates":[6.294847,51.97422],"type":"Point"}
}