{
  "type": "Feature",
  "properties": {
    "iso:country":"NL",
    "sg:address":"Tweede Achterstraat 11",
    "sg:city":"Tiel",
    "sg:orig_category":"Fitnesscentra",
    "sg:phone":"+31 344 612 118",
    "sg:postcode":"4001 MS",
    "sg:province":"Gelderland",
    "wof:name":"G.D. Velders",
    "wof:placetype":"venue"
},
  "geometry": {"coordinates":[5.432772,51.886444],"type":"Point"}
}