{
  "type": "Feature",
  "properties": {
    "addr:full":"K Onneswg 32 Dordrecht Zuid-Holland 3316 GL",
    "addr:housenumber":"32",
    "addr:postcode":"3316 gl",
    "addr:street":"Onneswg",
    "iso:country":"NL",
    "sg:address":"K Onneswg 32",
    "sg:city":"Dordrecht",
    "sg:orig_category":"Wegenbouw",
    "sg:phone":"+31 78 617 0422",
    "sg:postcode":"3316 GL",
    "sg:province":"Zuid-Holland",
    "sg:website":"http://www.verzijl-timmer.nl",
    "wof:name":"Verzijl Bv",
    "wof:placetype":"venue"
},
  "geometry": {"coordinates":[4.6565060616,51.8119163513],"type":"Point"}
}