{
  "type": "Feature",
  "properties": {
    "addr:full":"Postbus 1533 Maastricht Limburg 6201 BM",
    "addr:housenumber":"1533",
    "addr:postcode":"6201 bm",
    "addr:street":"Postbus",
    "iso:country":"NL",
    "sg:address":"Postbus 1533",
    "sg:city":"Maastricht",
    "sg:orig_category":"Openbaar Vervoer",
    "sg:phone":"+31 43 350 5754",
    "sg:postcode":"6201 BM",
    "sg:province":"Limburg",
    "wof:name":"Sbm-Groep Nv",
    "wof:placetype":"venue"
},
  "geometry": {"coordinates":[5.6872601509,50.8498497009],"type":"Point"}
}