{
  "type": "Feature",
  "properties": {
    "addr:full":"Postbus 361 Coevorden Provincie Drenthe 7740 AJ",
    "addr:housenumber":"361",
    "addr:postcode":"7740 aj",
    "addr:street":"Postbus;Provincie Drenthe",
    "iso:country":"NL",
    "sg:address":"Postbus 361",
    "sg:city":"Coevorden",
    "sg:orig_category":"Verzekeringen - Verzekeringskantoren",
    "sg:phone":"+31 524 517 659",
    "sg:postcode":"7740 AJ",
    "sg:province":"Provincie Drenthe",
    "sg:website":"http://www.wboer.nl",
    "wof:name":"Boer W Assuranti\u00ebn",
    "wof:placetype":"venue"
},
  "geometry": {"coordinates":[6.73891,52.6642],"type":"Point"}
}