{
  "type": "Feature",
  "properties": {
    "addr:full":"G Vd Lindestr 87 Rotterdam Zuid-Holland 3022 TG",
    "addr:housenumber":"87",
    "addr:postcode":"3022 tg",
    "iso:country":"NL",
    "sg:address":"G Vd Lindestr 87",
    "sg:city":"Rotterdam",
    "sg:classifiers":[
        {
            "category":"Food & Beverages",
            "subcategory":"Fruits & Vegetables",
            "type":"Retail Goods"
        }
    ],
    "sg:phone":"+31 10 425 7795",
    "sg:postcode":"3022 TG",
    "sg:province":"Zuid-Holland",
    "sg:tags":[
        "en",
        "groenten"
    ],
    "wof:name":"Cosmopolitan Props",
    "wof:placetype":"venue"
},
  "geometry": {"coordinates":[4.449868,51.917885],"type":"Point"}
}