{
  "type": "Feature",
  "properties": {
    "addr:full":"Burgemeester Kuperuspln 49A Heerenveen Provincie Friesland 8442 CL",
    "addr:housenumber":"49a",
    "addr:postcode":"8442",
    "addr:street":"Burgemeester Kuperuspln;Provincie Friesland",
    "iso:country":"NL",
    "sg:address":"Burgemeester Kuperuspln 49A",
    "sg:city":"Heerenveen",
    "sg:orig_category":"Werving And Selectie Van Tijdelijk Personeel And Uitzendkantoren",
    "sg:phone":"+31 513 653 399",
    "sg:postcode":"8442 CL",
    "sg:province":"Provincie Friesland",
    "wof:name":"Adecco",
    "wof:placetype":"venue"
},
  "geometry": {"coordinates":[5.9275331497,52.9572486877],"type":"Point"}
}