{
  "type": "Feature",
  "properties": {
    "addr:full":"Scherpencamp 6 Nykerk Gld Gelderland 3861 LT",
    "addr:housenumber":"6",
    "addr:postcode":"3861 lt",
    "addr:street":"Scherpencamp;Gld Gelderland",
    "iso:country":"NL",
    "sg:address":"Scherpencamp 6",
    "sg:city":"Nykerk Gld",
    "sg:orig_category":"Adviesbureaus Bedrijfsorganisatie",
    "sg:phone":"+31 33 245 4223",
    "sg:postcode":"3861 LT",
    "sg:province":"Gelderland",
    "wof:name":"Gw Support",
    "wof:placetype":"venue"
},
  "geometry": {"coordinates":[5.488865,52.231453],"type":"Point"}
}