{
  "type": "Feature",
  "properties": {
    "iso:country":"NL",
    "sg:address":"Weemstraat 16",
    "sg:city":"Noordwolde Fr",
    "sg:orig_category":"Boekenuitgeverijen",
    "sg:phone":"+31 561 431 600",
    "sg:postcode":"8391 AE",
    "sg:province":"Provincie Friesland",
    "wof:name":"Uitgeverij Van Nieuwenhoven Bv",
    "wof:placetype":"venue"
},
  "geometry": {"coordinates":[6.139013,52.892727],"type":"Point"}
}