{
  "type": "Feature",
  "properties": {
    "addr:full":"Doelen 9 Breda Noord-Brabant 4813 GP",
    "addr:housenumber":"9",
    "addr:postcode":"4813 gp",
    "addr:street":"Doelen",
    "iso:country":"NL",
    "sg:address":"Doelen 9",
    "sg:city":"Breda",
    "sg:orig_category":"Scholen Voor Basisonderwijs",
    "sg:phone":"+31 76 521 3129",
    "sg:postcode":"4813 GP",
    "sg:province":"Noord-Brabant",
    "wof:name":"Vlier, Openb De",
    "wof:placetype":"venue"
},
  "geometry": {"coordinates":[4.738122,51.576923],"type":"Point"}
}