{
  "type": "Feature",
  "properties": {
    "iso:country":"NL",
    "sg:address":"Zonneplein 2",
    "sg:city":"Amsterdam",
    "sg:orig_category":"Herenmodezaken",
    "sg:phone":"+31 20 631 9293",
    "sg:postcode":"1033 EK",
    "sg:province":"Noord-Holland",
    "wof:name":"Polyetherhuis Zwebe",
    "wof:placetype":"venue"
},
  "geometry": {"coordinates":[4.89089,52.413094],"type":"Point"}
}