{
  "type": "Feature",
  "properties": {
    "addr:full":"Voltstraat 4 Hillegom Zuid-Holland 2181 HA",
    "addr:housenumber":"4",
    "addr:postcode":"2181 ha",
    "addr:street":"Voltstraat",
    "iso:country":"NL",
    "sg:address":"Voltstraat 4",
    "sg:city":"Hillegom",
    "sg:orig_category":"Bloemen And Planten",
    "sg:phone":"+31 252 421 958",
    "sg:postcode":"2181 HA",
    "sg:province":"Zuid-Holland",
    "wof:name":"Id Unlimited Natural Art",
    "wof:placetype":"venue"
},
  "geometry": {"coordinates":[4.590859,52.30127],"type":"Point"}
}