{
  "type": "Feature",
  "properties": {
    "addr:full":"Looi 12D Oeffelt Noord-Brabant 5441 XB",
    "addr:housenumber":"12d",
    "addr:postcode":"5441 xb",
    "addr:street":"Looi",
    "iso:country":"NL",
    "sg:address":"Looi 12D",
    "sg:city":"Oeffelt",
    "sg:orig_category":"Verzekeringen - Verzekeringskantoren",
    "sg:phone":"+31 485 361 177",
    "sg:postcode":"5441 XB",
    "sg:province":"Noord-Brabant",
    "wof:name":"Cloosterman",
    "wof:placetype":"venue"
},
  "geometry": {"coordinates":[5.929806,51.700237],"type":"Point"}
}