{
  "type": "Feature",
  "properties": {
    "iso:country":"NL",
    "sg:address":"Naardermeer 353",
    "sg:city":"Rotterdam",
    "sg:orig_category":"Goederenvervoer Over De Weg",
    "sg:phone":"+31 10 456 3226",
    "sg:postcode":"3068 KH",
    "sg:province":"Zuid-Holland",
    "wof:name":"Handelsonderneming C. Steenstraten",
    "wof:placetype":"venue"
},
  "geometry": {"coordinates":[4.575366,51.963497],"type":"Point"}
}