{
  "type": "Feature",
  "properties": {
    "iso:country":"NL",
    "sg:address":"Leharstr 104A",
    "sg:city":"Tilburg",
    "sg:orig_category":"Kappers",
    "sg:phone":"+31 13 455 3859",
    "sg:postcode":"5011 KD",
    "sg:province":"North Brabant",
    "wof:name":"Buren, Louis Van",
    "wof:placetype":"venue"
},
  "geometry": {"coordinates":[5.0893740654,51.5869865417],"type":"Point"}
}