{
  "type": "Feature",
  "properties": {
    "addr:full":"W V Pruisenln 75 Gouda South Holland 2807 KG",
    "addr:housenumber":"75",
    "addr:postcode":"2807 kg",
    "addr:street":"W V Pruisenln",
    "iso:country":"NL",
    "sg:address":"W V Pruisenln 75",
    "sg:city":"Gouda",
    "sg:orig_category":"Ongediertebestrijding En Ontsmetting",
    "sg:phone":"+31 182 523 902",
    "sg:postcode":"2807 KG",
    "sg:province":"South Holland",
    "wof:name":"Fit Plan Hoefnagel",
    "wof:placetype":"venue"
},
  "geometry": {"coordinates":[4.710715,52.010006],"type":"Point"}
}