{
  "type": "Feature",
  "properties": {
    "iso:country":"NL",
    "sg:address":"Molenstr 4",
    "sg:city":"Middelharnis",
    "sg:orig_category":"Videoreportages",
    "sg:phone":"+31 187 487 580",
    "sg:postcode":"3241 GP",
    "sg:province":"South Holland",
    "wof:name":"Viar",
    "wof:placetype":"venue"
},
  "geometry": {"coordinates":[4.157221,51.759277],"type":"Point"}
}