{
  "type": "Feature",
  "properties": {
    "iso:country":"NL",
    "sg:address":"Langemoor 5",
    "sg:city":"Nieuw Vennep",
    "sg:orig_category":"Werving And Selectie Van Vast Personeel",
    "sg:phone":"+31 252 624 595",
    "sg:postcode":"2151 VE",
    "sg:province":"Noord-Holland",
    "wof:name":"Delta Automatisering Support D.A.S.",
    "wof:placetype":"venue"
},
  "geometry": {"coordinates":[4.6148519516,52.2640914917],"type":"Point"}
}