{
  "type": "Feature",
  "properties": {
    "addr:full":"Lelywg 2931 Bergen Op Zoom Noord-Brabant 4612 PS",
    "addr:postcode":"2931;4612 ps",
    "iso:country":"NL",
    "sg:address":"Lelywg 2931",
    "sg:city":"Bergen Op Zoom",
    "sg:orig_category":"Levensmiddelen- Grondstoffen - Fabrieken En Groothandel",
    "sg:phone":"+31 164 282 200",
    "sg:postcode":"4612 PS",
    "sg:province":"Noord-Brabant",
    "wof:name":"Cargill Bv",
    "wof:placetype":"venue"
},
  "geometry": {"coordinates":[4.26185,51.509048],"type":"Point"}
}