{
  "type": "Feature",
  "properties": {
    "addr:full":"Merwedestr 58 Maasdam Zuid-Holland 3299 XD",
    "addr:housenumber":"58",
    "addr:postcode":"3299 xd",
    "addr:street":"Merwedestr",
    "iso:country":"NL",
    "sg:address":"Merwedestr 58",
    "sg:city":"Maasdam",
    "sg:orig_category":"Peuterspeelzalen",
    "sg:phone":"+31 78 676 5047",
    "sg:postcode":"3299 XD",
    "sg:province":"Zuid-Holland",
    "wof:name":"Olleke Bolleke",
    "wof:placetype":"venue"
},
  "geometry": {"coordinates":[4.554426,51.790298],"type":"Point"}
}