{
  "type": "Feature",
  "properties": {
    "addr:full":"Daalseweg 331 Nijmegen Gelderland 6523 CB",
    "addr:housenumber":"331",
    "addr:postcode":"6523 cb",
    "addr:street":"Daalseweg;Gelderland",
    "iso:country":"NL",
    "sg:address":"Daalseweg 331",
    "sg:city":"Nijmegen",
    "sg:orig_category":"Binnenhuisarchitecten",
    "sg:phone":"+31 24 365 6766",
    "sg:postcode":"6523 CB",
    "sg:province":"Gelderland",
    "wof:name":"Living Design",
    "wof:placetype":"venue"
},
  "geometry": {"coordinates":[5.878841,51.83551],"type":"Point"}
}