{
  "type": "Feature",
  "properties": {
    "addr:full":"Schuttershofwg 1 Terneuzen Zeeland 4538 AA",
    "addr:housenumber":"1",
    "addr:postcode":"4538 aa",
    "addr:street":"Schuttershofwg",
    "iso:country":"NL",
    "sg:address":"Schuttershofwg 1",
    "sg:city":"Terneuzen",
    "sg:orig_category":"Arbo- En Bedrijfsgezondheids- Diensten",
    "sg:phone":"+31 113 272 300",
    "sg:postcode":"4538 AA",
    "sg:province":"Zeeland",
    "sg:website":"http://www.arboduo.nl",
    "wof:name":"Arboduo Terneuzen",
    "wof:placetype":"venue"
},
  "geometry": {"coordinates":[3.828656,51.334576],"type":"Point"}
}