{
  "type": "Feature",
  "properties": {
    "addr:full":"Parkstr 18 Utrecht Utrecht 3581 PJ",
    "addr:housenumber":"18",
    "addr:postcode":"3581 pj",
    "addr:street":"Parkstr",
    "iso:country":"NL",
    "sg:address":"Parkstr 18",
    "sg:city":"Utrecht",
    "sg:orig_category":"Adviesbureaus Personeel",
    "sg:phone":"+31 30 238 2800",
    "sg:postcode":"3581 PJ",
    "sg:province":"Utrecht",
    "wof:name":"Benoist",
    "wof:placetype":"venue"
},
  "geometry": {"coordinates":[5.129235,52.090961],"type":"Point"}
}