{
  "type": "Feature",
  "properties": {
    "addr:full":"Esmoreitstraat 19 Amsterdam North Holland 1055 BZ",
    "addr:housenumber":"19",
    "addr:postcode":"1055 bz",
    "addr:street":"Esmoreitstraat",
    "iso:country":"NL",
    "sg:address":"Esmoreitstraat 19",
    "sg:city":"Amsterdam",
    "sg:orig_category":"Autokeuringen",
    "sg:phone":"+31 20 681 2023",
    "sg:postcode":"1055 BZ",
    "sg:province":"North Holland",
    "wof:name":"Kemper'S Automobielbedrijf",
    "wof:placetype":"venue"
},
  "geometry": {"coordinates":[4.851597,52.377178],"type":"Point"}
}