{
  "type": "Feature",
  "properties": {
    "addr:full":"De Boskrane 9 Stiens Provincie Friesland 9051 SN",
    "addr:housenumber":"9",
    "addr:postcode":"9051 sn",
    "addr:street":"Provincie Friesland",
    "iso:country":"NL",
    "sg:address":"De Boskrane 9",
    "sg:city":"Stiens",
    "sg:orig_category":"Bedrijfsopleidingen",
    "sg:phone":"+31 58 257 0173",
    "sg:postcode":"9051 SN",
    "sg:province":"Provincie Friesland",
    "wof:name":"Moc Friesland",
    "wof:placetype":"venue"
},
  "geometry": {"coordinates":[5.768014,53.264221],"type":"Point"}
}