{
  "type": "Feature",
  "properties": {
    "addr:full":"Amsterdamsestrwg 45A Naarden Noord-Holland 1411 AX",
    "addr:housenumber":"45a",
    "addr:postcode":"1411 ax",
    "addr:street":"Amsterdamsestrwg",
    "iso:country":"NL",
    "sg:address":"Amsterdamsestrwg 45A",
    "sg:city":"Naarden",
    "sg:orig_category":"Evenementenverzorging",
    "sg:phone":"+31 35 526 9114",
    "sg:postcode":"1411 AX",
    "sg:province":"Noord-Holland",
    "sg:website":"http://www.degroep-waerts.nl",
    "wof:name":"Degroep & Waerts The Art Of Event Management",
    "wof:placetype":"venue"
},
  "geometry": {"coordinates":[5.143671,52.303814],"type":"Point"}
}