{
  "type": "Feature",
  "properties": {
    "iso:country":"NL",
    "sg:address":"Mooyeveld 5",
    "sg:city":"Egmond Binnen",
    "sg:orig_category":"Bloembollen - Groothandel",
    "sg:phone":"+31 72 506 1290",
    "sg:postcode":"1935 AK",
    "sg:province":"North Holland",
    "wof:name":"Roozen Nic Zn, Fa Harry",
    "wof:placetype":"venue"
},
  "geometry": {"coordinates":[4.655705,52.596455],"type":"Point"}
}