{
  "type": "Feature",
  "properties": {
    "addr:full":"Walk 23 Heythuysen Limburg 6093 GS",
    "addr:housenumber":"23",
    "addr:postcode":"6093 gs",
    "addr:street":"Walk",
    "iso:country":"NL",
    "sg:address":"Walk 23",
    "sg:city":"Heythuysen",
    "sg:orig_category":"Fotoreportages",
    "sg:phone":"+31 475 494 363",
    "sg:postcode":"6093 GS",
    "sg:province":"Limburg",
    "wof:name":"Pero",
    "wof:placetype":"venue"
},
  "geometry": {"coordinates":[5.906993,51.250587],"type":"Point"}
}