{
  "type": "Feature",
  "properties": {
    "addr:full":"Dorpsstraat 54 Nunspeet Gelderland 8071 BZ",
    "addr:housenumber":"54",
    "addr:postcode":"8071 bz",
    "addr:street":"Dorpsstraat;Gelderland",
    "iso:country":"NL",
    "sg:address":"Dorpsstraat 54",
    "sg:city":"Nunspeet",
    "sg:classifiers":[
        {
            "category":"Retail",
            "subcategory":"Photofinishing",
            "type":"Services"
        }
    ],
    "sg:phone":"+31 341 254 065",
    "sg:postcode":"8071 BZ",
    "sg:province":"Gelderland",
    "sg:tags":[
        "foto",
        "film"
    ],
    "wof:name":"Foto-Film Bert Van De Bunte",
    "wof:placetype":"venue"
},
  "geometry": {"coordinates":[5.782467,52.376163],"type":"Point"}
}