{
  "type": "Feature",
  "properties": {
    "addr:full":"Papeweg 36 Wolphaartsdijk Zeeland 4471 BG",
    "addr:housenumber":"36",
    "addr:postcode":"4471",
    "addr:street":"Papeweg",
    "iso:country":"NL",
    "sg:address":"Papeweg 36",
    "sg:city":"Wolphaartsdijk",
    "sg:orig_category":"Kappers",
    "sg:phone":"+31 113 581 455",
    "sg:postcode":"4471 BG",
    "sg:province":"Zeeland",
    "wof:name":"Kapsalon Anlida",
    "wof:placetype":"venue"
},
  "geometry": {"coordinates":[3.8194999695,51.5323219299],"type":"Point"}
}