{
  "type": "Feature",
  "properties": {
    "iso:country":"NL",
    "sg:address":"Enschedesestraat 24",
    "sg:city":"Hengelo Ov",
    "sg:classifiers":[
        {
            "category":"Fast Food",
            "type":"Food & Drink"
        }
    ],
    "sg:phone":"+31 74 290 9113",
    "sg:postcode":"7551 EN",
    "sg:province":"NL.08",
    "sg:tags":[
        "afhaal",
        "restaurant"
    ],
    "wof:name":"Automatiek De Muur",
    "wof:placetype":"venue"
},
  "geometry": {"coordinates":[6.794554,52.264694],"type":"Point"}
}