{
  "type": "Feature",
  "properties": {
    "addr:full":"Eusebiusbuit Sngl 1 Arnhem Gelderland 6828 HS",
    "addr:housenumber":"1",
    "addr:postcode":"6828 hs",
    "addr:street":"Sngl",
    "iso:country":"NL",
    "sg:address":"Eusebiusbuit Sngl 1",
    "sg:city":"Arnhem",
    "sg:orig_category":"Beeldende Kunstenaars",
    "sg:phone":"+31 26 351 5157",
    "sg:postcode":"6828 HS",
    "sg:province":"Gelderland",
    "wof:name":"Lanters, C",
    "wof:placetype":"venue"
},
  "geometry": {"coordinates":[5.915327,51.981861],"type":"Point"}
}