{
  "type": "Feature",
  "properties": {
    "addr:full":"Halstraat 31 Breda Noord-Brabant 4811 HV",
    "addr:housenumber":"31",
    "addr:postcode":"4811 hv",
    "addr:street":"Halstraat",
    "iso:country":"NL",
    "sg:address":"Halstraat 31",
    "sg:city":"Breda",
    "sg:orig_category":"Kappers",
    "sg:phone":"+31 76 522 4414",
    "sg:postcode":"4811 HV",
    "sg:province":"Noord-Brabant",
    "wof:name":"Cosmo Hairstyling",
    "wof:placetype":"venue"
},
  "geometry": {"coordinates":[4.777749,51.586575],"type":"Point"}
}