{
  "type": "Feature",
  "properties": {
    "iso:country":"NL",
    "sg:address":"Wagenwg 10D",
    "sg:city":"Purmerend",
    "sg:orig_category":"Autopoetsbedrijven",
    "sg:phone":"+31 299 439 797",
    "sg:postcode":"1442 BX",
    "sg:province":"Noord-Holland",
    "wof:name":"Born Again",
    "wof:placetype":"venue"
},
  "geometry": {"coordinates":[4.955088,52.510448],"type":"Point"}
}