{
  "type": "Feature",
  "properties": {
    "addr:full":"Wagenwg 10D Purmerend Noord-Holland 1442 BX",
    "addr:housenumber":"10d",
    "addr:postcode":"1442 bx",
    "addr:street":"Wagenwg",
    "iso:country":"NL",
    "sg:address":"Wagenwg 10D",
    "sg:city":"Purmerend",
    "sg:orig_category":"Autopoetsbedrijven",
    "sg:phone":"+31 299 439 797",
    "sg:postcode":"1442 BX",
    "sg:province":"Noord-Holland",
    "wof:name":"Born Again",
    "wof:placetype":"venue"
},
  "geometry": {"coordinates":[4.955088,52.510448],"type":"Point"}
}