{
  "type": "Feature",
  "properties": {
    "addr:full":"Nieuwe Molstraat 24 'S Gravenhage Zuid-Holland 2512 BK",
    "addr:housenumber":"24",
    "addr:postcode":"2512 bk",
    "addr:street":"Nieuwe Molstraat;' S",
    "iso:country":"NL",
    "sg:address":"Nieuwe Molstraat 24",
    "sg:city":"'S Gravenhage",
    "sg:orig_category":"Bedrijfsinventaris Gh",
    "sg:phone":"+31 70 364 4834",
    "sg:postcode":"2512 BK",
    "sg:province":"Zuid-Holland",
    "wof:name":"Se Sa Decor",
    "wof:placetype":"venue"
},
  "geometry": {"coordinates":[4.312991,52.074043],"type":"Point"}
}