{
  "type": "Feature",
  "properties": {
    "iso:country":"NL",
    "sg:address":"Spoorstr 56A",
    "sg:city":"Den Helder",
    "sg:orig_category":"Warenhuizen",
    "sg:phone":"+31 900 9800",
    "sg:postcode":"1781 JH",
    "sg:province":"Noord-Holland",
    "wof:name":"Kijkshop",
    "wof:placetype":"venue"
},
  "geometry": {"coordinates":[4.7636671066,52.9597969055],"type":"Point"}
}