{
  "type": "Feature",
  "properties": {
    "iso:country":"NL",
    "sg:address":"Magdalenenstraat 19",
    "sg:city":"Alkmaar",
    "sg:classifiers":[
        {
            "category":"Bakery",
            "type":"Food & Drink"
        }
    ],
    "sg:phone":"+31 72 515 1009",
    "sg:postcode":"1811 JR",
    "sg:province":"Noord-Holland",
    "sg:tags":[
        "brood",
        "banket"
    ],
    "wof:name":"L'Art Du Pain",
    "wof:placetype":"venue"
},
  "geometry": {"coordinates":[4.748308,52.631748],"type":"Point"}
}