{
  "type": "Feature",
  "properties": {
    "addr:full":"Nieuwe Dam 10 Ochten Gelderland 4051 BB",
    "addr:housenumber":"10",
    "addr:postcode":"4051 bb",
    "addr:street":"Nieuwe Dam;Gelderland",
    "iso:country":"NL",
    "sg:address":"Nieuwe Dam 10",
    "sg:city":"Ochten",
    "sg:orig_category":"Zuivelproducten",
    "sg:phone":"+31 344 642 063",
    "sg:postcode":"4051 BB",
    "sg:province":"Gelderland",
    "wof:name":"T. Hommersom",
    "wof:placetype":"venue"
},
  "geometry": {"coordinates":[5.567517,51.906296],"type":"Point"}
}