{
  "type": "Feature",
  "properties": {
    "addr:full":"Brucknerstraat 28 Zwijndrecht South Holland 3335 CN",
    "addr:housenumber":"28",
    "addr:postcode":"3335 cn",
    "addr:street":"Brucknerstraat",
    "iso:country":"NL",
    "sg:address":"Brucknerstraat 28",
    "sg:city":"Zwijndrecht",
    "sg:orig_category":"Boekhouders",
    "sg:phone":"+31 78 610 2793",
    "sg:postcode":"3335 CN",
    "sg:province":"South Holland",
    "wof:name":"Administratieve Dienstverlening J.M. Van",
    "wof:placetype":"venue"
},
  "geometry": {"coordinates":[4.619859,51.82011],"type":"Point"}
}