{
  "type": "Feature",
  "properties": {
    "addr:full":"Noordplein 15 Roelofarendsveen Zuid-Holland 2371 DA",
    "addr:housenumber":"15",
    "addr:postcode":"2371 da",
    "addr:street":"Noordplein",
    "iso:country":"NL",
    "sg:address":"Noordplein 15",
    "sg:city":"Roelofarendsveen",
    "sg:orig_category":"Huishoudapparatuur, Televisies And Radio'S",
    "sg:phone":"+31 71 331 2891",
    "sg:postcode":"2371 DA",
    "sg:province":"Zuid-Holland",
    "wof:name":"Radio-Hoogeveen",
    "wof:placetype":"venue"
},
  "geometry": {"coordinates":[4.631895,52.201923],"type":"Point"}
}