{
  "type": "Feature",
  "properties": {
    "addr:full":"Industriewg 17 Hoogeveen Drenthe 7903 AH",
    "addr:housenumber":"17",
    "addr:postcode":"7903 ah",
    "addr:street":"Industriewg",
    "iso:country":"NL",
    "sg:address":"Industriewg 17",
    "sg:city":"Hoogeveen",
    "sg:orig_category":"Kartonnage - Fabrieken En Groothandel",
    "sg:phone":"+31 528 293 911",
    "sg:postcode":"7903 AH",
    "sg:province":"Drenthe",
    "wof:name":"Kappa, Twincorr",
    "wof:placetype":"venue"
},
  "geometry": {"coordinates":[6.481884,52.732101],"type":"Point"}
}