{
  "type": "Feature",
  "properties": {
    "addr:full":"Maaseikerwg 158 Weert Limburg 6006 AC",
    "addr:housenumber":"158",
    "addr:postcode":"6006 ac",
    "addr:street":"Weert Limburg",
    "iso:country":"NL",
    "sg:address":"Maaseikerwg 158",
    "sg:city":"Weert",
    "sg:orig_category":"Parketvloeren",
    "sg:phone":"+31 495 548 075",
    "sg:postcode":"6006 AC",
    "sg:province":"Limburg",
    "wof:name":"Kuepers",
    "wof:placetype":"venue"
},
  "geometry": {"coordinates":[5.717195,51.23999],"type":"Point"}
}