{
  "type": "Feature",
  "properties": {
    "addr:full":"Stationsstr 6 Beek Lb Missouri 6191 BD",
    "addr:housenumber":"6",
    "addr:postcode":"6191 bd",
    "addr:street":"Stationsstr",
    "iso:country":"NL",
    "sg:address":"Stationsstr 6",
    "sg:city":"Beek Lb",
    "sg:orig_category":"Kappers",
    "sg:phone":"+31 6 13480684",
    "sg:postcode":"6191 BD",
    "sg:province":"Missouri",
    "wof:name":"Geknipt",
    "wof:placetype":"venue"
},
  "geometry": {"coordinates":[-93.1299362183,36.7056617737],"type":"Point"}
}