{
  "type": "Feature",
  "properties": {
    "iso:country":"NL",
    "sg:address":"Olmenlaan 32 B",
    "sg:city":"Bussum",
    "sg:orig_category":"Juridische Dienstverlening",
    "sg:phone":"+31 35 691 9011",
    "sg:postcode":"1404 DG",
    "sg:province":"North Holland",
    "wof:name":"Merkenbureau Hendriks & Co. C.V.",
    "wof:placetype":"venue"
},
  "geometry": {"coordinates":[5.161564,52.276672],"type":"Point"}
}