{
  "type": "Feature",
  "properties": {
    "addr:full":"Populierenln 11 Huizen Noord-Holland 1272 CW",
    "addr:housenumber":"11",
    "addr:postcode":"1272 cw",
    "addr:street":"Populierenln",
    "iso:country":"NL",
    "sg:address":"Populierenln 11",
    "sg:city":"Huizen",
    "sg:orig_category":"Adviesbureaus Bedrijfsorganisatie",
    "sg:phone":"+31 35 526 0407",
    "sg:postcode":"1272 CW",
    "sg:province":"Noord-Holland",
    "wof:name":"Joosse Kcc",
    "wof:placetype":"venue"
},
  "geometry": {"coordinates":[5.217312,52.292114],"type":"Point"}
}