{
  "type": "Feature",
  "properties": {
    "addr:full":"Bikolaan 197 Delft Zuid-Holland 2622 GS",
    "addr:housenumber":"197",
    "addr:postcode":"2622 gs",
    "addr:street":"Bikolaan",
    "iso:country":"NL",
    "sg:address":"Bikolaan 197",
    "sg:city":"Delft",
    "sg:orig_category":"Gespecialiseerde Voeding",
    "sg:phone":"+31 15 262 1706",
    "sg:postcode":"2622 GS",
    "sg:province":"Zuid-Holland",
    "wof:name":"Klein Westland Fruitige Relatiegeschenken",
    "wof:placetype":"venue"
},
  "geometry": {"coordinates":[4.345811,51.982067],"type":"Point"}
}