{
  "type": "Feature",
  "properties": {
    "addr:full":"Keizerstraat 51 Den Helder North Holland 1781 GE",
    "addr:housenumber":"51",
    "addr:postcode":"1781",
    "addr:street":"Keizerstraat",
    "iso:country":"NL",
    "sg:address":"Keizerstraat 51",
    "sg:city":"Den Helder",
    "sg:orig_category":"Damesmodezaken",
    "sg:phone":"+31 223 625 844",
    "sg:postcode":"1781 GE",
    "sg:province":"North Holland",
    "wof:name":"Nameless",
    "wof:placetype":"venue"
},
  "geometry": {"coordinates":[4.7636370659,52.9581489563],"type":"Point"}
}