{
  "type": "Feature",
  "properties": {
    "addr:full":"Cornelis Kraanstraat 1 Rotterdam Zuid-Holland 3065 HD",
    "addr:housenumber":"1",
    "addr:postcode":"3065 hd",
    "addr:street":"Cornelis Kraanstraat",
    "iso:country":"NL",
    "sg:address":"Cornelis Kraanstraat 1",
    "sg:city":"Rotterdam",
    "sg:orig_category":"Goederenvervoer Over De Weg",
    "sg:phone":"+31 10 447 1208",
    "sg:postcode":"3065 HD",
    "sg:province":"Zuid-Holland",
    "wof:name":"Rama",
    "wof:placetype":"venue"
},
  "geometry": {"coordinates":[4.553092,51.928871],"type":"Point"}
}