{
  "type": "Feature",
  "properties": {
    "iso:country":"NL",
    "sg:address":"Parkln 6",
    "sg:city":"Maasbracht",
    "sg:orig_category":"Artsen - Huisartsen",
    "sg:phone":"+31 475 462 974",
    "sg:postcode":"6051 BN",
    "sg:province":"Limburg",
    "wof:name":"Ficken, E W J",
    "wof:placetype":"venue"
},
  "geometry": {"coordinates":[5.891523,51.147671],"type":"Point"}
}