{
  "type": "Feature",
  "properties": {
    "addr:full":"Amperestraat 36 Hilversum North Holland 1221 GJ",
    "addr:housenumber":"36",
    "addr:postcode":"1221 gj",
    "addr:street":"Amperestraat",
    "iso:country":"NL",
    "sg:address":"Amperestraat 36",
    "sg:city":"Hilversum",
    "sg:orig_category":"Autokeuringen",
    "sg:phone":"+31 35 685 6756",
    "sg:postcode":"1221 GJ",
    "sg:province":"North Holland",
    "wof:name":"Tek Autobedrijf",
    "wof:placetype":"venue"
},
  "geometry": {"coordinates":[5.189403,52.229153],"type":"Point"}
}