{
  "type": "Feature",
  "properties": {
    "addr:full":"Oude Ysbaan 25 Delft Zuid-Holland 2612 NA",
    "addr:housenumber":"25",
    "addr:postcode":"2612 na",
    "addr:street":"Oude Ysbaan",
    "iso:country":"NL",
    "sg:address":"Oude Ysbaan 25",
    "sg:city":"Delft",
    "sg:orig_category":"Tegelwerken",
    "sg:phone":"+31 15 214 0685",
    "sg:postcode":"2612 NA",
    "sg:province":"Zuid-Holland",
    "wof:name":"Vrijland, E",
    "wof:placetype":"venue"
},
  "geometry": {"coordinates":[4.369459,52.016808],"type":"Point"}
}