{
  "type": "Feature",
  "properties": {
    "addr:full":"Protonwg 1 Hoorn Nh Noord-Holland 1627 LD",
    "addr:housenumber":"1",
    "addr:postcode":"1627 ld",
    "addr:street":"Protonwg",
    "iso:country":"NL",
    "sg:address":"Protonwg 1",
    "sg:city":"Hoorn Nh",
    "sg:orig_category":"Heftrucks",
    "sg:phone":"+31 229 218 045",
    "sg:postcode":"1627 LD",
    "sg:province":"Noord-Holland",
    "wof:name":"Cascade Nv",
    "wof:placetype":"venue"
},
  "geometry": {"coordinates":[5.09643,52.644306],"type":"Point"}
}