{
  "type": "Feature",
  "properties": {
    "iso:country":"NL",
    "sg:address":"Lijnbaanstraat 25",
    "sg:city":"Franeker",
    "sg:orig_category":"Verhuur Audiovisuele Apparatuur",
    "sg:phone":"+31 517 391 426",
    "sg:postcode":"8801 LX",
    "sg:province":"Friesland",
    "wof:name":"Unlimited Lighting",
    "wof:placetype":"venue"
},
  "geometry": {"coordinates":[5.544368,53.185211],"type":"Point"}
}