{
  "type": "Feature",
  "properties": {
    "iso:country":"NL",
    "sg:address":"Postbus 1032",
    "sg:city":"Giessenburg",
    "sg:orig_category":"Veiligheidsuitrusting En -Kleding",
    "sg:phone":"+31 184 652 866",
    "sg:postcode":"3380 AA",
    "sg:province":"South Holland",
    "wof:name":"Hantex",
    "wof:placetype":"venue"
},
  "geometry": {"coordinates":[4.88866,51.851799],"type":"Point"}
}