{
  "type": "Feature",
  "properties": {
    "addr:full":"Mauritswg 57E Rotterdam Zuid-Holland 3012 JX",
    "addr:housenumber":"57e",
    "addr:postcode":"3012 jx",
    "addr:street":"Mauritswg",
    "iso:country":"NL",
    "sg:address":"Mauritswg 57E",
    "sg:city":"Rotterdam",
    "sg:orig_category":"Organisatiebureaus",
    "sg:phone":"+31 10 413 7713",
    "sg:postcode":"3012 JX",
    "sg:province":"Zuid-Holland",
    "wof:name":"Wolf",
    "wof:placetype":"venue"
},
  "geometry": {"coordinates":[4.473069191,51.917640686],"type":"Point"}
}