{
  "type": "Feature",
  "properties": {
    "iso:country":"NL",
    "sg:address":"Flevoln 6",
    "sg:city":"Enkhuizen",
    "sg:orig_category":"Jachthavens - Jachtwerven",
    "sg:phone":"+31 228 315 660",
    "sg:postcode":"1601 MA",
    "sg:province":"Noord-Holland",
    "wof:name":"Buyshaven",
    "wof:placetype":"venue"
},
  "geometry": {"coordinates":[5.290085,52.703674],"type":"Point"}
}