{
  "type": "Feature",
  "properties": {
    "iso:country":"NL",
    "sg:address":"Richterswg 368A",
    "sg:city":"Doorwerth",
    "sg:orig_category":"Koffie-Automaten",
    "sg:phone":"+31 26 333 5013",
    "sg:postcode":"6865 GV",
    "sg:province":"Gelderland",
    "sg:website":"http://www. fountainservice.nl",
    "wof:name":"Fountain Service Bv",
    "wof:placetype":"venue"
},
  "geometry": {"coordinates":[5.797059,51.979439],"type":"Point"}
}