{
  "type": "Feature",
  "properties": {
    "addr:full":"Asterwg 36 Amsterdam Noord-Holland 1031 HP",
    "addr:housenumber":"36",
    "addr:postcode":"1031 hp",
    "addr:street":"Asterwg",
    "iso:country":"NL",
    "sg:address":"Asterwg 36",
    "sg:city":"Amsterdam",
    "sg:orig_category":"Logerijen",
    "sg:phone":"+31 20 632 4367",
    "sg:postcode":"1031 HP",
    "sg:province":"Noord-Holland",
    "wof:name":"Blankhout",
    "wof:placetype":"venue"
},
  "geometry": {"coordinates":[4.903172,52.392635],"type":"Point"}
}