{
  "type": "Feature",
  "properties": {
    "addr:full":"Broekhem 71 Valkenburg Lb Limburg 6301 HE",
    "addr:housenumber":"71",
    "addr:postcode":"lb;6301 he",
    "addr:street":"Broekhem",
    "iso:country":"NL",
    "sg:address":"Broekhem 71",
    "sg:city":"Valkenburg Lb",
    "sg:classifiers":[
        {
            "category":"Fast Food",
            "type":"Food & Drink"
        }
    ],
    "sg:phone":"+31 43 601 6811",
    "sg:postcode":"6301 HE",
    "sg:province":"Limburg",
    "sg:tags":[
        "afhaal",
        "restaurant"
    ],
    "wof:name":"Chinees Restaurant International",
    "wof:placetype":"venue"
},
  "geometry": {"coordinates":[5.822751,50.871059],"type":"Point"}
}