{
  "type": "Feature",
  "properties": {
    "iso:country":"NL",
    "sg:address":"Weerdingerstr 10A",
    "sg:city":"Emmen",
    "sg:orig_category":"Keukens",
    "sg:phone":"+31 591 645 454",
    "sg:postcode":"7815 SB",
    "sg:province":"Drenthe",
    "sg:website":"http://www.keukenkanjer.nl",
    "wof:name":"Keukenkanjer",
    "wof:placetype":"venue"
},
  "geometry": {"coordinates":[6.892832,52.789017],"type":"Point"}
}