{
  "type": "Feature",
  "properties": {
    "addr:full":"H V Althenastr 2 Heinenoord Zuid-Holland 3274 CD",
    "addr:housenumber":"2",
    "addr:postcode":"3274 cd",
    "addr:street":"H;Althenastr",
    "iso:country":"NL",
    "sg:address":"H V Althenastr 2",
    "sg:city":"Heinenoord",
    "sg:orig_category":"Scholen Voor Basisonderwijs",
    "sg:phone":"+31 186 602 255",
    "sg:postcode":"3274 CD",
    "sg:province":"Zuid-Holland",
    "wof:name":"Anker Openb, Het",
    "wof:placetype":"venue"
},
  "geometry": {"coordinates":[4.51067,51.814201],"type":"Point"}
}