{
  "type": "Feature",
  "properties": {
    "addr:full":"P Wariusln 24 Midwoud North Holland 1679 XK",
    "addr:housenumber":"24",
    "addr:postcode":"1679 xk",
    "addr:street":"P",
    "iso:country":"NL",
    "sg:address":"P Wariusln 24",
    "sg:city":"Midwoud",
    "sg:orig_category":"Homeopathie",
    "sg:phone":"+31 229 202 704",
    "sg:postcode":"1679 XK",
    "sg:province":"North Holland",
    "wof:name":"Vermaat Suzan",
    "wof:placetype":"venue"
},
  "geometry": {"coordinates":[5.076329,52.715698],"type":"Point"}
}