{
  "type": "Feature",
  "properties": {
    "addr:full":"Stadhoudersln 57 Utrecht Utrecht 3583 JD",
    "addr:housenumber":"57",
    "addr:postcode":"3583 jd",
    "addr:street":"Stadhoudersln",
    "iso:country":"NL",
    "sg:address":"Stadhoudersln 57",
    "sg:city":"Utrecht",
    "sg:orig_category":"Hulpverlening Sociaal",
    "sg:phone":"+31 30 251 6016",
    "sg:postcode":"3583 JD",
    "sg:province":"Utrecht",
    "wof:name":"Nidos, Sticht",
    "wof:placetype":"venue"
},
  "geometry": {"coordinates":[5.14371,52.086601],"type":"Point"}
}