{
  "type": "Feature",
  "properties": {
    "addr:full":"Florapark 9 Haarlem Noord-Holland 2012 HK",
    "addr:housenumber":"9",
    "addr:postcode":"2012 hk",
    "addr:street":"Florapark",
    "iso:country":"NL",
    "sg:address":"Florapark 9",
    "sg:city":"Haarlem",
    "sg:orig_category":"Voeding, Dranken And Tabak Gh",
    "sg:phone":"+31 23 531 5195",
    "sg:postcode":"2012 HK",
    "sg:province":"Noord-Holland",
    "wof:name":"Conservi Bv",
    "wof:placetype":"venue"
},
  "geometry": {"coordinates":[4.628171,52.372055],"type":"Point"}
}