{
  "type": "Feature",
  "properties": {
    "addr:full":"Oranjepln 2 Riel North Brabant 5133 TW",
    "addr:housenumber":"2",
    "addr:postcode":"5133 tw",
    "addr:street":"Oranjepln",
    "iso:country":"NL",
    "sg:address":"Oranjepln 2",
    "sg:city":"Riel",
    "sg:orig_category":"Kousen En Sokken",
    "sg:phone":"+31 13 518 1464",
    "sg:postcode":"5133 TW",
    "sg:province":"North Brabant",
    "wof:name":"Baans Zoontjes, N N C",
    "wof:placetype":"venue"
},
  "geometry": {"coordinates":[5.026982,51.526188],"type":"Point"}
}