{
  "type": "Feature",
  "properties": {
    "iso:country":"NL",
    "sg:address":"Schoutenstraat 6",
    "sg:city":"Alkmaar",
    "sg:orig_category":"Verlichting And Huishoudartikelen",
    "sg:phone":"+31 72 512 0321",
    "sg:postcode":"1811 HD",
    "sg:province":"Noord-Holland",
    "wof:name":"Amphora",
    "wof:placetype":"venue"
},
  "geometry": {"coordinates":[4.745069,52.631939],"type":"Point"}
}