{
  "type": "Feature",
  "properties": {
    "addr:full":"Hoofdpoort 18 Kaatsheuvel North Brabant 5171 DN",
    "addr:housenumber":"18",
    "addr:postcode":"5171 dn",
    "addr:street":"Hoofdpoort",
    "iso:country":"NL",
    "sg:address":"Hoofdpoort 18",
    "sg:city":"Kaatsheuvel",
    "sg:orig_category":"Fotolaboratoria",
    "sg:phone":"+31 416 280 932",
    "sg:postcode":"5171 DN",
    "sg:province":"North Brabant",
    "wof:name":"Hema",
    "wof:placetype":"venue"
},
  "geometry": {"coordinates":[5.035874,51.661411],"type":"Point"}
}