{
  "type": "Feature",
  "properties": {
    "addr:full":"Madoerastraat 27 Haarlem Noord-Holland 2022 ZL",
    "addr:housenumber":"27",
    "addr:postcode":"2022 zl",
    "addr:street":"Madoerastraat",
    "iso:country":"NL",
    "sg:address":"Madoerastraat 27",
    "sg:city":"Haarlem",
    "sg:orig_category":"Alternatieve Geneeskunde",
    "sg:phone":"+31 23 525 6257",
    "sg:postcode":"2022 ZL",
    "sg:province":"Noord-Holland",
    "wof:name":"Salon Ineke",
    "wof:placetype":"venue"
},
  "geometry": {"coordinates":[4.649075,52.397766],"type":"Point"}
}