{
  "type": "Feature",
  "properties": {
    "addr:full":"Rigel 34 Waddinxveen Zuid-Holland 2743 MJ",
    "addr:housenumber":"34",
    "addr:postcode":"2743 mj",
    "addr:street":"Rigel",
    "iso:country":"NL",
    "sg:address":"Rigel 34",
    "sg:city":"Waddinxveen",
    "sg:orig_category":"Adviesbureaus Bedrijfsorganisatie",
    "sg:phone":"+31 182 612 104",
    "sg:postcode":"2743 MJ",
    "sg:province":"Zuid-Holland",
    "wof:name":"Choice Bv",
    "wof:placetype":"venue"
},
  "geometry": {"coordinates":[4.628446,52.034813],"type":"Point"}
}