{
  "type": "Feature",
  "properties": {
    "addr:full":"Portsmuiden 2 Amsterdam Noord-Holland 1046 AJ",
    "addr:housenumber":"2",
    "addr:postcode":"1046 aj",
    "addr:street":"Portsmuiden",
    "iso:country":"NL",
    "sg:address":"Portsmuiden 2",
    "sg:city":"Amsterdam",
    "sg:orig_category":"Farmaceutische Producten Gh",
    "sg:phone":"+31 20 506 1800",
    "sg:postcode":"1046 AJ",
    "sg:province":"Noord-Holland",
    "wof:name":"Opg Groothandel Bv",
    "wof:placetype":"venue"
},
  "geometry": {"coordinates":[4.785114,52.391052],"type":"Point"}
}