{
  "type": "Feature",
  "properties": {
    "addr:full":"Pastoor Doensstraat 5 Bavel North Brabant 4854 CP",
    "addr:housenumber":"5",
    "addr:postcode":"4854 cp",
    "addr:street":"Pastoor Doensstraat",
    "iso:country":"NL",
    "sg:address":"Pastoor Doensstraat 5",
    "sg:city":"Bavel",
    "sg:orig_category":"Kinderopvang Behalve Thuis",
    "sg:phone":"+31 161 432 305",
    "sg:postcode":"4854 CP",
    "sg:province":"North Brabant",
    "wof:name":"Dribbel Kinderdagverblijf",
    "wof:placetype":"venue"
},
  "geometry": {"coordinates":[4.832036,51.56723],"type":"Point"}
}