{
  "type": "Feature",
  "properties": {
    "addr:full":"Kleiweg Gouda Zuid-Holland 2801 GH",
    "addr:postcode":"2801 gh",
    "addr:street":"Kleiweg",
    "iso:country":"NL",
    "sg:address":"Kleiweg",
    "sg:city":"Gouda",
    "sg:orig_category":"Koopzondagen Zondag 1 December 2002",
    "sg:phone":"+31 0",
    "sg:postcode":"2801 GH",
    "sg:province":"Zuid-Holland",
    "wof:name":"Gouda Winkelcentrum Nieuwe Markt Passage",
    "wof:placetype":"venue"
},
  "geometry": {"coordinates":[4.70976,52.012924],"type":"Point"}
}