{
  "type": "Feature",
  "properties": {
    "addr:full":"Zwartewg 18 Oosterwolde Gld Gelderland 8097 PV",
    "addr:housenumber":"18",
    "addr:postcode":"8097 pv",
    "addr:street":"Zwartewg",
    "iso:country":"NL",
    "sg:address":"Zwartewg 18",
    "sg:city":"Oosterwolde Gld",
    "sg:orig_category":"Verenigingen En Stichtingen",
    "sg:phone":"+31 6 20036698",
    "sg:postcode":"8097 PV",
    "sg:province":"Gelderland",
    "wof:name":"Memento Mori",
    "wof:placetype":"venue"
},
  "geometry": {"coordinates":[5.896221,52.463661],"type":"Point"}
}