{
  "type": "Feature",
  "properties": {
    "iso:country":"NL",
    "sg:address":"Stargardln 1",
    "sg:city":"Bussum",
    "sg:orig_category":"Loopbaanbegeleiding",
    "sg:phone":"+31 35 632 1276",
    "sg:postcode":"1404 BC",
    "sg:province":"North Holland",
    "wof:name":"Waard Consult, De",
    "wof:placetype":"venue"
},
  "geometry": {"coordinates":[5.159418,52.281307],"type":"Point"}
}