{
  "type": "Feature",
  "properties": {
    "addr:full":"Oude Trambaan 141 Leidschendam South Holland 2265 DA",
    "addr:housenumber":"141",
    "addr:postcode":"2265 da",
    "addr:street":"Oude Trambaan",
    "iso:country":"NL",
    "sg:address":"Oude Trambaan 141",
    "sg:city":"Leidschendam",
    "sg:orig_category":"Autokeuringen",
    "sg:phone":"+31 70 327 8907",
    "sg:postcode":"2265 DA",
    "sg:province":"South Holland",
    "wof:name":"Fina",
    "wof:placetype":"venue"
},
  "geometry": {"coordinates":[4.389253,52.080284],"type":"Point"}
}