{
  "type": "Feature",
  "properties": {
    "addr:full":"Spuistraat 93 Bunschoten Spakenburg Utrecht 3752 AK",
    "addr:housenumber":"93",
    "addr:postcode":"3752 ak",
    "addr:street":"Spuistraat",
    "iso:country":"NL",
    "sg:address":"Spuistraat 93",
    "sg:city":"Bunschoten Spakenburg",
    "sg:orig_category":"Damesmodezaken",
    "sg:phone":"+31 33 298 1439",
    "sg:postcode":"3752 AK",
    "sg:province":"Utrecht",
    "wof:name":"Modehuis Wedo",
    "wof:placetype":"venue"
},
  "geometry": {"coordinates":[5.377225,52.252457],"type":"Point"}
}