{
  "type": "Feature",
  "properties": {
    "addr:full":"Vrystr 10 Eindhoven Noord-Brabant 5611 AV",
    "addr:housenumber":"10",
    "addr:postcode":"5611 av",
    "addr:street":"Vrystr",
    "iso:country":"NL",
    "sg:address":"Vrystr 10",
    "sg:city":"Eindhoven",
    "sg:orig_category":"Wijnkoperijen En -Groothandel",
    "sg:phone":"+31 40 244 8954",
    "sg:postcode":"5611 AV",
    "sg:province":"Noord-Brabant",
    "wof:name":"Bloems, Henri",
    "wof:placetype":"venue"
},
  "geometry": {"coordinates":[5.4841051102,51.4344711304],"type":"Point"}
}