{
  "type": "Feature",
  "properties": {
    "addr:full":"Irisln 43 Berkel En Rodenrys Zuid-Holland 2651 PP",
    "addr:housenumber":"43",
    "addr:postcode":"2651 pp",
    "addr:street":"Irisln;Berkel",
    "iso:country":"NL",
    "sg:address":"Irisln 43",
    "sg:city":"Berkel En Rodenrys",
    "sg:orig_category":"Kantoor- En Secretariaatsservice",
    "sg:phone":"+31 10 512 1714",
    "sg:postcode":"2651 PP",
    "sg:province":"Zuid-Holland",
    "wof:name":"Schipperus, Roelie",
    "wof:placetype":"venue"
},
  "geometry": {"coordinates":[4.4785552025,51.9925346375],"type":"Point"}
}