{
  "type": "Feature",
  "properties": {
    "addr:full":"Tussenlanen 44 Bergambacht Zuid-Holland 2861 CE",
    "addr:housenumber":"44",
    "addr:postcode":"2861 ce",
    "addr:street":"Tussenlanen",
    "iso:country":"NL",
    "sg:address":"Tussenlanen 44",
    "sg:city":"Bergambacht",
    "sg:orig_category":"Schilderwerk",
    "sg:phone":"+31 182 351 924",
    "sg:postcode":"2861 CE",
    "sg:province":"Zuid-Holland",
    "wof:name":"Schildersbedrijf C. Nieuwveld Bv",
    "wof:placetype":"venue"
},
  "geometry": {"coordinates":[4.806617,51.942677],"type":"Point"}
}