{
  "type": "Feature",
  "properties": {
    "addr:full":"Konynenberg 51 Breda Noord-Brabant 4825 BC",
    "addr:housenumber":"51",
    "addr:postcode":"4825 bc",
    "addr:street":"Konynenberg",
    "iso:country":"NL",
    "sg:address":"Konynenberg 51",
    "sg:city":"Breda",
    "sg:orig_category":"Automaterialen En Gereedschappen",
    "sg:phone":"+31 76 572 5000",
    "sg:postcode":"4825 BC",
    "sg:province":"Noord-Brabant",
    "sg:website":"http://www.aps-bv.nl",
    "wof:name":"Aps",
    "wof:placetype":"venue"
},
  "geometry": {"coordinates":[4.76852,51.611752],"type":"Point"}
}