{
  "type": "Feature",
  "properties": {
    "iso:country":"NL",
    "sg:address":"Onderduikersstraat 1",
    "sg:city":"Groningen",
    "sg:orig_category":"Bedrijfsinventaris Gh",
    "sg:phone":"+31 50 526 4849",
    "sg:postcode":"9727 CD",
    "sg:province":"Groningen",
    "wof:name":"Tamse Projectcatering",
    "wof:placetype":"venue"
},
  "geometry": {"coordinates":[6.555342,53.209133],"type":"Point"}
}