{
  "type": "Feature",
  "properties": {
    "addr:full":"Luikerwg 42 Maastricht Limburg 6212 EW",
    "addr:housenumber":"42",
    "addr:postcode":"6212 ew",
    "addr:street":"Luikerwg",
    "iso:country":"NL",
    "sg:address":"Luikerwg 42",
    "sg:city":"Maastricht",
    "sg:orig_category":"Administratie- En Boekhoudkantoren",
    "sg:phone":"+31 43 356 0393",
    "sg:postcode":"6212 EW",
    "sg:province":"Limburg",
    "wof:name":"Bakker",
    "wof:placetype":"venue"
},
  "geometry": {"coordinates":[5.686912,50.839172],"type":"Point"}
}