{
  "type": "Feature",
  "properties": {
    "addr:full":"De Run 4308 Veldhoven Noord-Brabant 5503 LN",
    "addr:housenumber":"4308",
    "addr:postcode":"5503 ln",
    "addr:street":"De Run",
    "iso:country":"NL",
    "sg:address":"De Run 4308",
    "sg:city":"Veldhoven",
    "sg:orig_category":"Elektronische Bedrijfsinstallaties",
    "sg:phone":"+31 40 254 2395",
    "sg:postcode":"5503 LN",
    "sg:province":"Noord-Brabant",
    "wof:name":"Communication Technology Centre Bv",
    "wof:placetype":"venue"
},
  "geometry": {"coordinates":[5.424792,51.406361],"type":"Point"}
}