{
  "type": "Feature",
  "properties": {
    "addr:full":"Badhuisln 10 Hilversum North Holland 1217 SK",
    "addr:housenumber":"10",
    "addr:postcode":"1217 sk",
    "addr:street":"Badhuisln",
    "iso:country":"NL",
    "sg:address":"Badhuisln 10",
    "sg:city":"Hilversum",
    "sg:orig_category":"Loopbaanbegeleiding",
    "sg:phone":"+31 35 624 1529",
    "sg:postcode":"1217 SK",
    "sg:province":"North Holland",
    "sg:website":"http://www.sherpavoorwerk.nl",
    "wof:name":"Sherpa Bureau Voorwerk, Sticht",
    "wof:placetype":"venue"
},
  "geometry": {"coordinates":[5.1695,52.228565],"type":"Point"}
}