{
  "type": "Feature",
  "properties": {
    "iso:country":"NL",
    "sg:address":"Plesmanstr 5",
    "sg:city":"Leerdam",
    "sg:orig_category":"Motoren - Onderdelen",
    "sg:phone":"+31 345 612 123",
    "sg:postcode":"4143 HL",
    "sg:province":"Zuid-Holland",
    "wof:name":"Flinterman, M",
    "wof:placetype":"venue"
},
  "geometry": {"coordinates":[5.100396,51.896988],"type":"Point"}
}