{
  "type": "Feature",
  "properties": {
    "addr:full":"Kringloop 15 Zeewolde Flevoland 3893 DL",
    "addr:housenumber":"15",
    "addr:postcode":"3893 dl",
    "addr:street":"Kringloop;Flevoland",
    "iso:country":"NL",
    "sg:address":"Kringloop 15",
    "sg:city":"Zeewolde",
    "sg:orig_category":"Verzekeringen",
    "sg:phone":"+31 36 521 8080",
    "sg:postcode":"3893 DL",
    "sg:province":"Flevoland",
    "wof:name":"Assurantie Service Nederland",
    "wof:placetype":"venue"
},
  "geometry": {"coordinates":[5.523492,52.331497],"type":"Point"}
}