{
  "type": "Feature",
  "properties": {
    "iso:country":"NL",
    "sg:address":"Beekln 180",
    "sg:city":"Tilburg",
    "sg:orig_category":"Administratie- En Boekhoudkantoren",
    "sg:phone":"+31 13 468 0883",
    "sg:postcode":"5032 AJ",
    "sg:province":"North Brabant",
    "wof:name":"Minos, Buro Van",
    "wof:placetype":"venue"
},
  "geometry": {"coordinates":[5.0039,51.553379],"type":"Point"}
}