{
  "type": "Feature",
  "properties": {
    "iso:country":"NL",
    "sg:address":"Rynln 49",
    "sg:city":"Heemstede",
    "sg:orig_category":"Kappers",
    "sg:phone":"+31 23 528 2738",
    "sg:postcode":"2105 XJ",
    "sg:province":"Noord-Holland",
    "wof:name":"Albertina",
    "wof:placetype":"venue"
},
  "geometry": {"coordinates":[4.6212477684,52.345287323],"type":"Point"}
}