{
  "type": "Feature",
  "properties": {
    "addr:full":"Sittardstr 39 Arnhem Gelderland 6845 DJ",
    "addr:housenumber":"39",
    "addr:postcode":"6845 dj",
    "addr:street":"Sittardstr",
    "iso:country":"NL",
    "sg:address":"Sittardstr 39",
    "sg:city":"Arnhem",
    "sg:orig_category":"Administratie- En Boekhoudkantoren",
    "sg:phone":"+31 26 389 1890",
    "sg:postcode":"6845 DJ",
    "sg:province":"Gelderland",
    "wof:name":"Haveber",
    "wof:placetype":"venue"
},
  "geometry": {"coordinates":[5.870183,51.942753],"type":"Point"}
}