{
  "type": "Feature",
  "properties": {
    "addr:full":"Klaverstr 10 Den Helder North Holland 1786 AN",
    "addr:housenumber":"10",
    "addr:postcode":"1786 an",
    "addr:street":"Klaverstr",
    "iso:country":"NL",
    "sg:address":"Klaverstr 10",
    "sg:city":"Den Helder",
    "sg:orig_category":"Grafisch Ontwerpers",
    "sg:phone":"+31 223 690 251",
    "sg:postcode":"1786 AN",
    "sg:province":"North Holland",
    "wof:name":"Kisteman, Studio",
    "wof:placetype":"venue"
},
  "geometry": {"coordinates":[4.753196,52.894913],"type":"Point"}
}