{
  "type": "Feature",
  "properties": {
    "addr:full":"Dorpstr 24 Maastricht Limburg 6227 BN",
    "addr:housenumber":"24",
    "addr:postcode":"6227 bn",
    "addr:street":"Dorpstr",
    "iso:country":"NL",
    "sg:address":"Dorpstr 24",
    "sg:city":"Maastricht",
    "sg:orig_category":"Schoenen - Reparaties",
    "sg:phone":"+31 43 361 3129",
    "sg:postcode":"6227 BN",
    "sg:province":"Limburg",
    "wof:name":"Glenmit",
    "wof:placetype":"venue"
},
  "geometry": {"coordinates":[5.727391,50.842751],"type":"Point"}
}