{
  "type": "Feature",
  "properties": {
    "addr:full":"Oslowg 61 Groningen Groningen 9723 BH",
    "addr:housenumber":"61",
    "addr:postcode":"9723 bh",
    "addr:street":"Oslowg",
    "iso:country":"NL",
    "sg:address":"Oslowg 61",
    "sg:city":"Groningen",
    "sg:orig_category":"Drukkerijen",
    "sg:phone":"+31 50 314 2626",
    "sg:postcode":"9723 BH",
    "sg:province":"Groningen",
    "wof:name":"Plantijncasparie Groningen",
    "wof:placetype":"venue"
},
  "geometry": {"coordinates":[6.59539,53.211807],"type":"Point"}
}