{
  "type": "Feature",
  "properties": {
    "addr:full":"Mariniersweg 106 Rotterdam South Holland 3011 ZZ",
    "addr:housenumber":"106",
    "addr:postcode":"3011 zz",
    "addr:street":"Mariniersweg",
    "iso:country":"NL",
    "sg:address":"Mariniersweg 106",
    "sg:city":"Rotterdam",
    "sg:orig_category":"Meubelzaken, Woning- And Keukeninrichting",
    "sg:phone":"+31 10 413 8620",
    "sg:postcode":"3011 ZZ",
    "sg:province":"South Holland",
    "wof:name":"Hulshoff Wonen",
    "wof:placetype":"venue"
},
  "geometry": {"coordinates":[4.490333,51.921822],"type":"Point"}
}