{
  "type": "Feature",
  "properties": {
    "addr:full":"Walingswg 17 Wieringerwaard Noord-Holland 1766 GH",
    "addr:housenumber":"17",
    "addr:postcode":"1766 gh",
    "addr:street":"Walingswg",
    "iso:country":"NL",
    "sg:address":"Walingswg 17",
    "sg:city":"Wieringerwaard",
    "sg:orig_category":"Begrafenisverzorging",
    "sg:phone":"+31 224 221 865",
    "sg:postcode":"1766 GH",
    "sg:province":"Noord-Holland",
    "wof:name":"Remember",
    "wof:placetype":"venue"
},
  "geometry": {"coordinates":[4.844929,52.814129],"type":"Point"}
}