{
  "type": "Feature",
  "properties": {
    "addr:full":"Kleis 50 Uitgeest Noord-Holland 1911 MH",
    "addr:housenumber":"50",
    "addr:postcode":"1911 mh",
    "addr:street":"Kleis",
    "iso:country":"NL",
    "sg:address":"Kleis 50",
    "sg:city":"Uitgeest",
    "sg:orig_category":"Verzekeringen - Verzekeringskantoren",
    "sg:phone":"+31 251 315 294",
    "sg:postcode":"1911 MH",
    "sg:province":"Noord-Holland",
    "wof:name":"Martens, P",
    "wof:placetype":"venue"
},
  "geometry": {"coordinates":[4.702611,52.517658],"type":"Point"}
}