{
  "type": "Feature",
  "properties": {
    "addr:full":"Zuringhof 39 Tilburg North Brabant 5044 DD",
    "addr:housenumber":"39",
    "addr:postcode":"5044 dd",
    "addr:street":"Zuringhof",
    "iso:country":"NL",
    "sg:address":"Zuringhof 39",
    "sg:city":"Tilburg",
    "sg:orig_category":"Verlichting And Huishoudartikelen",
    "sg:phone":"+31 13 467 8084",
    "sg:postcode":"5044 DD",
    "sg:province":"North Brabant",
    "wof:name":"C.A.M. Versantvoort En C. Van Huygevoort",
    "wof:placetype":"venue"
},
  "geometry": {"coordinates":[5.033646,51.578892],"type":"Point"}
}