{
  "type": "Feature",
  "properties": {
    "addr:full":"Koningshoek 93051-93053 Maassluis South Holland 3144 BA",
    "addr:housenumber":"93051-93053",
    "addr:postcode":"3144 ba",
    "iso:country":"NL",
    "sg:address":"Koningshoek 93051-93053",
    "sg:city":"Maassluis",
    "sg:orig_category":"Schoenen",
    "sg:phone":"+31 10 592 4477",
    "sg:postcode":"3144 BA",
    "sg:province":"South Holland",
    "wof:name":"Schoenenreus",
    "wof:placetype":"venue"
},
  "geometry": {"coordinates":[4.2397742271,51.9280052185],"type":"Point"}
}