{
  "type": "Feature",
  "properties": {
    "addr:full":"Hessenweg 78 Dalfsen Overijssel 7722 SH",
    "addr:housenumber":"78",
    "addr:postcode":"7722 sh",
    "addr:street":"Hessenweg",
    "iso:country":"NL",
    "sg:address":"Hessenweg 78",
    "sg:city":"Dalfsen",
    "sg:orig_category":"Erotische Etablissementen",
    "sg:phone":"+31 529 471 689",
    "sg:postcode":"7722 SH",
    "sg:province":"Overijssel",
    "wof:name":"Surprise",
    "wof:placetype":"venue"
},
  "geometry": {"coordinates":[6.347087,52.527988],"type":"Point"}
}