{
  "type": "Feature",
  "properties": {
    "addr:full":"Zuidbuitenpoldersekade 7 Dordrecht Zuid-Holland 3329 LA",
    "addr:housenumber":"7",
    "addr:postcode":"3329 la",
    "addr:street":"Zuidbuitenpoldersekade",
    "iso:country":"NL",
    "sg:address":"Zuidbuitenpoldersekade 7",
    "sg:city":"Dordrecht",
    "sg:classifiers":[
        {
            "category":"Retail",
            "subcategory":"Storage",
            "type":"Services"
        }
    ],
    "sg:phone":"+31 78 616 5522",
    "sg:postcode":"3329 LA",
    "sg:province":"Zuid-Holland",
    "sg:tags":[
        "op-",
        "en",
        "overslagbedrijven"
    ],
    "wof:name":"Schoonderwoerd, H M",
    "wof:placetype":"venue"
},
  "geometry": {"coordinates":[4.69205,51.769432],"type":"Point"}
}