{
  "type": "Feature",
  "properties": {
    "iso:country":"NL",
    "sg:address":"Gerstdk 7",
    "sg:city":"Helmond",
    "sg:orig_category":"Grafische Materialen",
    "sg:phone":"+31 492 579 600",
    "sg:postcode":"5704 RG",
    "sg:province":"Noord-Brabant",
    "sg:website":"http://www.druckchemie.com",
    "wof:name":"Druckchemie Benelux Bv",
    "wof:placetype":"venue"
},
  "geometry": {"coordinates":[5.69585,51.444962],"type":"Point"}
}