{
  "type": "Feature",
  "properties": {
    "addr:full":"Antwerpsestraat 17 Bergen Op Zoom Noord-Brabant 4611 AB",
    "addr:housenumber":"17",
    "addr:postcode":"4611 ab",
    "addr:street":"Antwerpsestraat",
    "iso:country":"NL",
    "sg:address":"Antwerpsestraat 17",
    "sg:city":"Bergen Op Zoom",
    "sg:orig_category":"Bruidskleding",
    "sg:phone":"+31 164 265 020",
    "sg:postcode":"4611 AB",
    "sg:province":"Noord-Brabant",
    "wof:name":"Babouche",
    "wof:placetype":"venue"
},
  "geometry": {"coordinates":[4.288727,51.491467],"type":"Point"}
}