{
  "type": "Feature",
  "properties": {
    "iso:country":"NL",
    "sg:address":"Oude Rykswg 80",
    "sg:city":"Staphorst",
    "sg:orig_category":"Logopedisten",
    "sg:phone":"+31 522 463 655",
    "sg:postcode":"7951 DL",
    "sg:province":"Overijssel",
    "wof:name":"Nouwels, C",
    "wof:placetype":"venue"
},
  "geometry": {"coordinates":[6.20808,52.646076],"type":"Point"}
}