{
  "type": "Feature",
  "properties": {
    "addr:full":"Ambachtsweg 9 Malden Gelderland 6581 AX",
    "addr:housenumber":"9",
    "addr:postcode":"6581 ax",
    "addr:street":"Ambachtsweg;Gelderland",
    "iso:country":"NL",
    "sg:address":"Ambachtsweg 9",
    "sg:city":"Malden",
    "sg:orig_category":"Architecten",
    "sg:phone":"+31 24 358 5828",
    "sg:postcode":"6581 AX",
    "sg:province":"Gelderland",
    "wof:name":"Decs-Waterbehandeling Bv",
    "wof:placetype":"venue"
},
  "geometry": {"coordinates":[5.847758,51.780132],"type":"Point"}
}