{
  "type": "Feature",
  "properties": {
    "iso:country":"NL",
    "sg:address":"Metiusstr 19",
    "sg:city":"Alkmaar",
    "sg:orig_category":"Orthopedische Artikelen",
    "sg:phone":"+31 72 520 2250",
    "sg:postcode":"1815 HN",
    "sg:province":"Noord-Holland",
    "wof:name":"Welzorg",
    "wof:placetype":"venue"
},
  "geometry": {"coordinates":[4.7383170128,52.6289863586],"type":"Point"}
}