{
  "type": "Feature",
  "properties": {
    "addr:full":"Baambrugse Zuwe 127 Vinkeveen Utrecht 3645 AD",
    "addr:housenumber":"127",
    "addr:postcode":"3645 ad",
    "addr:street":"Baambrugse Zuwe",
    "iso:country":"NL",
    "sg:address":"Baambrugse Zuwe 127",
    "sg:city":"Vinkeveen",
    "sg:orig_category":"Jachthavens - Jachtwerven",
    "sg:phone":"+31 297 261 242",
    "sg:postcode":"3645 AD",
    "sg:province":"Utrecht",
    "wof:name":"Oldenburger, H K",
    "wof:placetype":"venue"
},
  "geometry": {"coordinates":[4.9552,52.23114],"type":"Point"}
}