{
  "type": "Feature",
  "properties": {
    "addr:full":"Pastoor Schreursstraat 9 Meijel Limburg 5768 CM",
    "addr:housenumber":"9",
    "addr:postcode":"5768 cm",
    "addr:street":"Pastoor Schreursstraat",
    "iso:country":"NL",
    "sg:address":"Pastoor Schreursstraat 9",
    "sg:city":"Meijel",
    "sg:orig_category":"Verzekeringen",
    "sg:phone":"+31 77 466 1771",
    "sg:postcode":"5768 CM",
    "sg:province":"Limburg",
    "wof:name":"Assurantiekantoor Vullings P.L. Vullings",
    "wof:placetype":"venue"
},
  "geometry": {"coordinates":[5.880937,51.344776],"type":"Point"}
}