{
  "type": "Feature",
  "properties": {
    "addr:full":"Penninghove 38 Zoetermeer Zuid-Holland 2726 BV",
    "addr:housenumber":"38",
    "addr:postcode":"2726 bv",
    "addr:street":"Penninghove",
    "iso:country":"NL",
    "sg:address":"Penninghove 38",
    "sg:city":"Zoetermeer",
    "sg:orig_category":"Werving And Selectie Van Vast Personeel",
    "sg:phone":"+31 79 323 8150",
    "sg:postcode":"2726 BV",
    "sg:province":"Zuid-Holland",
    "wof:name":"Break Consultancy",
    "wof:placetype":"venue"
},
  "geometry": {"coordinates":[4.4845161438,52.0663719177],"type":"Point"}
}