{
  "type": "Feature",
  "properties": {
    "addr:full":"Stationswg O 186 Woudenberg Utrecht 3931 EW",
    "addr:housenumber":"186",
    "addr:postcode":"3931 ew",
    "iso:country":"NL",
    "sg:address":"Stationswg O 186",
    "sg:city":"Woudenberg",
    "sg:orig_category":"Architecten En Architectenbureaus",
    "sg:phone":"+31 33 286 3464",
    "sg:postcode":"3931 EW",
    "sg:province":"Utrecht",
    "wof:name":"Elsenaar, M",
    "wof:placetype":"venue"
},
  "geometry": {"coordinates":[5.452171,52.080601],"type":"Point"}
}