{
  "type": "Feature",
  "properties": {
    "iso:country":"NL",
    "sg:address":"Oldenaller 7",
    "sg:city":"Amsterdam",
    "sg:orig_category":"Logopedisten",
    "sg:phone":"+31 20 644 0329",
    "sg:postcode":"1081 HJ",
    "sg:province":"North Holland",
    "wof:name":"Buitenveldert",
    "wof:placetype":"venue"
},
  "geometry": {"coordinates":[4.86351,52.331207],"type":"Point"}
}