{
  "type": "Feature",
  "properties": {
    "iso:country":"NL",
    "sg:address":"Haarsteegsestr 14-14A",
    "sg:city":"Haarsteeg",
    "sg:orig_category":"Kinderopvang",
    "sg:phone":"+31 73 511 2179",
    "sg:postcode":"5254 JR",
    "sg:province":"North Brabant",
    "sg:website":"http://www.dikkertjedapuwnet.nl",
    "wof:name":"Dikkertje Dap",
    "wof:placetype":"venue"
},
  "geometry": {"coordinates":[5.198282,51.710281],"type":"Point"}
}