{
  "type": "Feature",
  "properties": {
    "addr:full":"Postbus 350 Veghel North Brabant 5460 AJ",
    "addr:housenumber":"350",
    "addr:postcode":"5460 aj",
    "addr:street":"Postbus",
    "iso:country":"NL",
    "sg:address":"Postbus 350",
    "sg:city":"Veghel",
    "sg:orig_category":"Bejaarden - Verzorgingstehuizen",
    "sg:phone":"+31 413 362 951",
    "sg:postcode":"5460 AJ",
    "sg:province":"North Brabant",
    "wof:name":"Welstaete",
    "wof:placetype":"venue"
},
  "geometry": {"coordinates":[5.54175,51.617222],"type":"Point"}
}