{
  "type": "Feature",
  "properties": {
    "addr:full":"Fahrenheitstr 337 Den Haag South Holland 2561 DW",
    "addr:housenumber":"337",
    "addr:postcode":"2561 dw",
    "iso:country":"NL",
    "sg:address":"Fahrenheitstr 337",
    "sg:city":"Den Haag",
    "sg:orig_category":"Postkantoren",
    "sg:phone":"+31 70 364 9887",
    "sg:postcode":"2561 DW",
    "sg:province":"South Holland",
    "sg:website":"http://www.postkantoor.nl",
    "wof:name":"Postkantoor",
    "wof:placetype":"venue"
},
  "geometry": {"coordinates":[4.27421,52.073978],"type":"Point"}
}