{
  "type": "Feature",
  "properties": {
    "addr:full":"Prins Willemstraat 88 Hoensbroek Limburg 6433 HD",
    "addr:housenumber":"88",
    "addr:postcode":"6433 hd",
    "addr:street":"Prins Willemstraat",
    "iso:country":"NL",
    "sg:address":"Prins Willemstraat 88",
    "sg:city":"Hoensbroek",
    "sg:orig_category":"Beautyfarms And Sauna'S",
    "sg:phone":"+31 45 563 1900",
    "sg:postcode":"6433 HD",
    "sg:province":"Limburg",
    "wof:name":"La Primavera",
    "wof:placetype":"venue"
},
  "geometry": {"coordinates":[5.933333,50.909187],"type":"Point"}
}