{
  "type": "Feature",
  "properties": {
    "addr:full":"Koestraat 2 Oudenbosch Noord-Brabant 4731 SK",
    "addr:housenumber":"2",
    "addr:street":"Koestraat;4731",
    "iso:country":"NL",
    "sg:address":"Koestraat 2",
    "sg:city":"Oudenbosch",
    "sg:orig_category":"Landbouwmachines Gh",
    "sg:phone":"+31 165 316 998",
    "sg:postcode":"4731 SK",
    "sg:province":"Noord-Brabant",
    "wof:name":"Meesters Machinehandel",
    "wof:placetype":"venue"
},
  "geometry": {"coordinates":[4.532588,51.575485],"type":"Point"}
}