{
  "type": "Feature",
  "properties": {
    "iso:country":"NL",
    "sg:address":"De Eglantier 530",
    "sg:city":"Apeldoorn",
    "sg:orig_category":"Antiquiteiten",
    "sg:phone":"+31 55 542 5413",
    "sg:postcode":"7329 DM",
    "sg:province":"Gelderland",
    "wof:name":"Grootmoeder'S Boetiek",
    "wof:placetype":"venue"
},
  "geometry": {"coordinates":[6.00546,52.194538],"type":"Point"}
}