{
  "type": "Feature",
  "properties": {
    "iso:country":"NL",
    "sg:address":"Postbus 4058",
    "sg:city":"Zutphen",
    "sg:orig_category":"Organisatiebureaus",
    "sg:phone":"+31 570 517 366",
    "sg:postcode":"7200 BB",
    "sg:province":"Gelderland",
    "wof:name":"Mocamu",
    "wof:placetype":"venue"
},
  "geometry": {"coordinates":[6.1915249825,52.1402015686],"type":"Point"}
}