{
  "type": "Feature",
  "properties": {
    "addr:full":"Kuijperstraat 45 Bunschoten Spakenburg Utrecht 3752 BC",
    "addr:housenumber":"45",
    "addr:postcode":"3752 bc",
    "addr:street":"Kuijperstraat",
    "iso:country":"NL",
    "sg:address":"Kuijperstraat 45",
    "sg:city":"Bunschoten Spakenburg",
    "sg:orig_category":"Visspeciaalzaken",
    "sg:phone":"+31 33 298 3788",
    "sg:postcode":"3752 BC",
    "sg:province":"Utrecht",
    "wof:name":"Vof De Graaf Roos & Zn",
    "wof:placetype":"venue"
},
  "geometry": {"coordinates":[5.373617,52.252174],"type":"Point"}
}