{
  "type": "Feature",
  "properties": {
    "addr:full":"Vincent Van Goghstraat 25 Helvoirt Noord-Brabant 5268 BL",
    "addr:housenumber":"25",
    "addr:postcode":"5268 bl",
    "addr:street":"Vincent Van Goghstraat",
    "iso:country":"NL",
    "sg:address":"Vincent Van Goghstraat 25",
    "sg:city":"Helvoirt",
    "sg:orig_category":"Autokeuringen",
    "sg:phone":"+31 411 641 936",
    "sg:postcode":"5268 BL",
    "sg:province":"Noord-Brabant",
    "wof:name":"Automobiel- En Garagebedrijf Pijnenburg Bv",
    "wof:placetype":"venue"
},
  "geometry": {"coordinates":[5.229053,51.63044],"type":"Point"}
}