{
  "type": "Feature",
  "properties": {
    "addr:full":"T Vlak 8 Barendrecht Zuid-Holland 2991 EP",
    "addr:housenumber":"8",
    "addr:postcode":"2991 ep",
    "addr:street":"T Vlak",
    "iso:country":"NL",
    "sg:address":"T Vlak 8",
    "sg:city":"Barendrecht",
    "sg:orig_category":"Woninginrichting",
    "sg:phone":"+31 180 621 801",
    "sg:postcode":"2991 EP",
    "sg:province":"Zuid-Holland",
    "wof:name":"Merwede",
    "wof:placetype":"venue"
},
  "geometry": {"coordinates":[4.5396738052,51.8554611206],"type":"Point"}
}