{
  "type": "Feature",
  "properties": {
    "addr:full":"Avenhornstr 16 Amsterdam North Holland 1023 TS",
    "addr:housenumber":"16",
    "addr:postcode":"1023 ts",
    "addr:street":"Avenhornstr",
    "iso:country":"NL",
    "sg:address":"Avenhornstr 16",
    "sg:city":"Amsterdam",
    "sg:orig_category":"Vertalers",
    "sg:phone":"+31 20 632 7641",
    "sg:postcode":"1023 TS",
    "sg:province":"North Holland",
    "wof:name":"Bonte, Drs F J",
    "wof:placetype":"venue"
},
  "geometry": {"coordinates":[4.945405,52.390354],"type":"Point"}
}