{
  "type": "Feature",
  "properties": {
    "addr:full":"Boulev P Loot 83A Zandvoort Noord-Holland 2042 AG",
    "addr:housenumber":"83a",
    "addr:postcode":"2042",
    "addr:street":"P Loot",
    "iso:country":"NL",
    "sg:address":"Boulev P Loot 83A",
    "sg:city":"Zandvoort",
    "sg:orig_category":"Adviesbureaus Bedrijfsorganisatie",
    "sg:phone":"+31 23 573 0931",
    "sg:postcode":"2042 AG",
    "sg:province":"Noord-Holland",
    "wof:name":"Chaps Zandvoort Bv",
    "wof:placetype":"venue"
},
  "geometry": {"coordinates":[4.519605,52.364189],"type":"Point"}
}