{
  "type": "Feature",
  "properties": {
    "addr:full":"G Kasteinstr 22 Hoogvliet Rt Zuid-Holland 3191 BB",
    "addr:housenumber":"22",
    "addr:postcode":"rt;3191 bb",
    "iso:country":"NL",
    "sg:address":"G Kasteinstr 22",
    "sg:city":"Hoogvliet Rt",
    "sg:orig_category":"Afslankinstituten",
    "sg:phone":"+31 10 416 8344",
    "sg:postcode":"3191 BB",
    "sg:province":"Zuid-Holland",
    "wof:name":"Ega Ned",
    "wof:placetype":"venue"
},
  "geometry": {"coordinates":[4.3655,51.861012],"type":"Point"}
}