{
  "type": "Feature",
  "properties": {
    "addr:full":"Sloterweg 1301 Amsterdam Noord-Holland 1066 CL",
    "addr:housenumber":"1301",
    "addr:postcode":"1066",
    "addr:street":"Sloterweg",
    "iso:country":"NL",
    "sg:address":"Sloterweg 1301",
    "sg:city":"Amsterdam",
    "sg:orig_category":"Artsen And Specialisten",
    "sg:phone":"+31 20 615 1515",
    "sg:postcode":"1066 CL",
    "sg:province":"Noord-Holland",
    "wof:name":"J.G.M. Maarschalk",
    "wof:placetype":"venue"
},
  "geometry": {"coordinates":[4.795018,52.341297],"type":"Point"}
}