{
  "type": "Feature",
  "properties": {
    "iso:country":"NL",
    "sg:address":"Eenendertigste Wijk-Z 17",
    "sg:city":"Hollandscheveld",
    "sg:orig_category":"Kansspelen",
    "sg:phone":"+31 528 341 021",
    "sg:postcode":"7913 AC",
    "sg:province":"Drenthe",
    "wof:name":"Soepenberg Amusement Bv",
    "wof:placetype":"venue"
},
  "geometry": {"coordinates":[6.5378599167,52.715171814],"type":"Point"}
}