{
  "type": "Feature",
  "properties": {
    "addr:full":"Neptunusstr 1 Hoofddorp Noord-Holland 2132 JA",
    "addr:housenumber":"1",
    "addr:postcode":"2132 ja",
    "addr:street":"Neptunusstr",
    "iso:country":"NL",
    "sg:address":"Neptunusstr 1",
    "sg:city":"Hoofddorp",
    "sg:orig_category":"Kantoormachines",
    "sg:phone":"+31 23 568 1600",
    "sg:postcode":"2132 JA",
    "sg:province":"Noord-Holland",
    "sg:website":"http://www.canon.nl/",
    "wof:name":"Canon Center Utrecht",
    "wof:placetype":"venue"
},
  "geometry": {"coordinates":[4.7027058601,52.2954483032],"type":"Point"}
}