{
  "type": "Feature",
  "properties": {
    "addr:full":"Paradyswg 35 Ter Aar Zuid-Holland 2461 TL",
    "addr:housenumber":"35",
    "addr:postcode":"aar;2461 tl",
    "addr:street":"Paradyswg;Ter",
    "iso:country":"NL",
    "sg:address":"Paradyswg 35",
    "sg:city":"Ter Aar",
    "sg:orig_category":"Bloemen En Planten",
    "sg:phone":"+31 172 603 247",
    "sg:postcode":"2461 TL",
    "sg:province":"Zuid-Holland",
    "wof:name":"Hoorn, J M M Van Der",
    "wof:placetype":"venue"
},
  "geometry": {"coordinates":[4.720758,52.185284],"type":"Point"}
}