{
  "type": "Feature",
  "properties": {
    "addr:full":"Hyacintstr 48 Katwyk Zh South Holland 2223 GV",
    "addr:housenumber":"48;zh",
    "addr:postcode":"2223 gv",
    "addr:street":"Hyacintstr",
    "iso:country":"NL",
    "sg:address":"Hyacintstr 48",
    "sg:city":"Katwyk Zh",
    "sg:orig_category":"Bijouterie?n - Fabrieken En Groothandel",
    "sg:phone":"+31 71 407 6407",
    "sg:postcode":"2223 GV",
    "sg:province":"South Holland",
    "wof:name":"Biesheuvel, P",
    "wof:placetype":"venue"
},
  "geometry": {"coordinates":[4.419952,52.188351],"type":"Point"}
}