{
  "type": "Feature",
  "properties": {
    "addr:full":"De Sluis 4 Vroomshoop Overijssel 7681 KB",
    "addr:housenumber":"4",
    "addr:postcode":"7681 kb",
    "addr:street":"De Sluis",
    "iso:country":"NL",
    "sg:address":"De Sluis 4",
    "sg:city":"Vroomshoop",
    "sg:orig_category":"Metaalbewerking",
    "sg:phone":"+31 546 643 871",
    "sg:postcode":"7681 KB",
    "sg:province":"Overijssel",
    "wof:name":"Denissen Bv",
    "wof:placetype":"venue"
},
  "geometry": {"coordinates":[6.563637,52.450069],"type":"Point"}
}