{
  "type": "Feature",
  "properties": {
    "iso:country":"NL",
    "sg:address":"Oosteinde 37",
    "sg:city":"De Ryp",
    "sg:orig_category":"Loodgieters",
    "sg:phone":"+31 299 675 912",
    "sg:postcode":"1483 AC",
    "sg:province":"Noord-Holland",
    "wof:name":"Bruntink & Zn, D",
    "wof:placetype":"venue"
},
  "geometry": {"coordinates":[4.857405,52.559818],"type":"Point"}
}