{
  "type": "Feature",
  "properties": {
    "addr:full":"Heerenpolderweg 13 Wolphaartsdijk Zeeland 4471 RV",
    "addr:housenumber":"13",
    "addr:postcode":"4471 rv",
    "addr:street":"Heerenpolderweg",
    "iso:country":"NL",
    "sg:address":"Heerenpolderweg 13",
    "sg:city":"Wolphaartsdijk",
    "sg:orig_category":"Diverse Bedrijfsinstallaties Gh",
    "sg:phone":"+31 113 586 006",
    "sg:postcode":"4471 RV",
    "sg:province":"Zeeland",
    "wof:name":"Technomarine",
    "wof:placetype":"venue"
},
  "geometry": {"coordinates":[3.818462,51.519203],"type":"Point"}
}