{
  "type": "Feature",
  "properties": {
    "addr:full":"Paradijsvogelstraat 2 Groningen Groningen 9713 BV",
    "addr:housenumber":"2",
    "addr:postcode":"9713 bv",
    "addr:street":"Paradijsvogelstraat",
    "iso:country":"NL",
    "sg:address":"Paradijsvogelstraat 2",
    "sg:city":"Groningen",
    "sg:orig_category":"Autokeuringen",
    "sg:phone":"+31 50 311 9316",
    "sg:postcode":"9713 BV",
    "sg:province":"Groningen",
    "wof:name":"Klein",
    "wof:placetype":"venue"
},
  "geometry": {"coordinates":[6.585826,53.230236],"type":"Point"}
}