{
  "type": "Feature",
  "properties": {
    "addr:full":"Westergeest 54 Uitgeest North Holland 1911 AK",
    "addr:housenumber":"54",
    "addr:postcode":"1911 ak",
    "addr:street":"Westergeest",
    "iso:country":"NL",
    "sg:address":"Westergeest 54",
    "sg:city":"Uitgeest",
    "sg:orig_category":"Bloemen And Planten",
    "sg:phone":"+31 251 312 796",
    "sg:postcode":"1911 AK",
    "sg:province":"North Holland",
    "wof:name":"W G Willemse",
    "wof:placetype":"venue"
},
  "geometry": {"coordinates":[4.709666,52.522259],"type":"Point"}
}