{
  "type": "Feature",
  "properties": {
    "addr:full":"Hooilandsewg 75 Roodeschool Groningen 9983 PB",
    "addr:housenumber":"75",
    "addr:postcode":"9983 pb",
    "addr:street":"Hooilandsewg",
    "iso:country":"NL",
    "sg:address":"Hooilandsewg 75",
    "sg:city":"Roodeschool",
    "sg:orig_category":"Verenigingsgebouwen",
    "sg:phone":"+31 595 412 428",
    "sg:postcode":"9983 PB",
    "sg:province":"Groningen",
    "wof:name":"Ontmoetingscentrum",
    "wof:placetype":"venue"
},
  "geometry": {"coordinates":[6.768556,53.419411],"type":"Point"}
}