{
  "type": "Feature",
  "properties": {
    "addr:full":"Spanbroekerweg 219 Spanbroek North Holland 1715 GN",
    "addr:housenumber":"219",
    "addr:postcode":"1715 gn",
    "addr:street":"Spanbroekerweg",
    "iso:country":"NL",
    "sg:address":"Spanbroekerweg 219",
    "sg:city":"Spanbroek",
    "sg:orig_category":"Gespecialiseerde Bouw",
    "sg:phone":"+31 226 354 856",
    "sg:postcode":"1715 GN",
    "sg:province":"North Holland",
    "wof:name":"Nico Blank",
    "wof:placetype":"venue"
},
  "geometry": {"coordinates":[4.97858,52.691479],"type":"Point"}
}