{
  "type": "Feature",
  "properties": {
    "addr:full":"Nieuwlandsewg 46 Hilversum Noord-Holland 1215 DA",
    "addr:housenumber":"46",
    "addr:postcode":"1215 da",
    "addr:street":"Nieuwlandsewg",
    "iso:country":"NL",
    "sg:address":"Nieuwlandsewg 46",
    "sg:city":"Hilversum",
    "sg:orig_category":"Schilders",
    "sg:phone":"+31 35 621 6165",
    "sg:postcode":"1215 DA",
    "sg:province":"Noord-Holland",
    "wof:name":"Dekker",
    "wof:placetype":"venue"
},
  "geometry": {"coordinates":[5.161136,52.209084],"type":"Point"}
}