{
  "type": "Feature",
  "properties": {
    "iso:country":"NL",
    "sg:address":"Spoorlaan 35",
    "sg:city":"Tilburg",
    "sg:orig_category":"Fietshandelaren",
    "sg:phone":"+31 13 543 6194",
    "sg:postcode":"5038 CB",
    "sg:province":"Noord-Brabant",
    "wof:name":"Fietspoint Derks",
    "wof:placetype":"venue"
},
  "geometry": {"coordinates":[5.08323,51.560242],"type":"Point"}
}