{
  "type": "Feature",
  "properties": {
    "addr:full":"Amersfoortseweg 30 Huis Ter Heide Ut Utrecht 3712 BD",
    "addr:housenumber":"30",
    "addr:postcode":"3712 bd",
    "addr:street":"Amersfoortseweg",
    "iso:country":"NL",
    "sg:address":"Amersfoortseweg 30",
    "sg:city":"Huis Ter Heide Ut",
    "sg:orig_category":"Autokeuringen",
    "sg:phone":"+31 346 351 033",
    "sg:postcode":"3712 BD",
    "sg:province":"Utrecht",
    "wof:name":"Servicestation Amersfoortseweg Bv",
    "wof:placetype":"venue"
},
  "geometry": {"coordinates":[5.265921,52.115612],"type":"Point"}
}