{
  "type": "Feature",
  "properties": {
    "addr:full":"Kouvenderstr 38 Hoensbroek Limburg 6431 HG",
    "addr:housenumber":"38",
    "addr:postcode":"6431 hg",
    "addr:street":"Kouvenderstr",
    "iso:country":"NL",
    "sg:address":"Kouvenderstr 38",
    "sg:city":"Hoensbroek",
    "sg:classifiers":[
        {
            "category":"Food & Beverages",
            "subcategory":"Bakery",
            "type":"Retail Goods"
        }
    ],
    "sg:phone":"+31 45 521 1104",
    "sg:postcode":"6431 HG",
    "sg:province":"Limburg",
    "sg:tags":[
        "brood",
        "en",
        "banket"
    ],
    "wof:name":"Eeghem Bv, Van",
    "wof:placetype":"venue"
},
  "geometry": {"coordinates":[5.928324,50.925091],"type":"Point"}
}