{
  "type": "Feature",
  "properties": {
    "iso:country":"NL",
    "sg:address":"Prins Hendrikstraat 30",
    "sg:city":"Hoogerheide",
    "sg:orig_category":"Diverse Consumentenartikelen Gh",
    "sg:phone":"+31 164 616 763",
    "sg:postcode":"4631 KC",
    "sg:province":"North Brabant",
    "wof:name":"Richard Mulders Veeverzorgingsmiddelen",
    "wof:placetype":"venue"
},
  "geometry": {"coordinates":[4.328414,51.425678],"type":"Point"}
}