{
  "type": "Feature",
  "properties": {
    "addr:full":"Tormentilstr 23 Groningen Groningen 9731 DR",
    "addr:housenumber":"23",
    "addr:postcode":"9731 dr",
    "addr:street":"Tormentilstr",
    "iso:country":"NL",
    "sg:address":"Tormentilstr 23",
    "sg:city":"Groningen",
    "sg:classifiers":[
        {
            "category":"Personal",
            "subcategory":"Nail Salon",
            "type":"Services"
        }
    ],
    "sg:phone":"+31 50 541 6008",
    "sg:postcode":"9731 DR",
    "sg:province":"Groningen",
    "sg:tags":[
        "pedicure"
    ],
    "wof:name":"Visser, R",
    "wof:placetype":"venue"
},
  "geometry": {"coordinates":[6.595607,53.230747],"type":"Point"}
}