{
  "type": "Feature",
  "properties": {
    "addr:full":"Bongerd 19 Heerlen Limburg 6411 JL",
    "addr:housenumber":"19",
    "addr:postcode":"6411 jl",
    "addr:street":"Bongerd",
    "iso:country":"NL",
    "sg:address":"Bongerd 19",
    "sg:city":"Heerlen",
    "sg:orig_category":"Behangselpapier En Wandbekleding",
    "sg:phone":"+31 45 571 3581",
    "sg:postcode":"6411 JL",
    "sg:province":"Limburg",
    "wof:name":"Decorette Aug V Wersch",
    "wof:placetype":"venue"
},
  "geometry": {"coordinates":[5.97991,50.888508],"type":"Point"}
}