{
  "type": "Feature",
  "properties": {
    "addr:full":"Clemensweg 1 Merkelbeek Limburg 6447 AZ",
    "addr:housenumber":"1",
    "addr:postcode":"6447 az",
    "addr:street":"Clemensweg",
    "iso:country":"NL",
    "sg:address":"Clemensweg 1",
    "sg:city":"Merkelbeek",
    "sg:orig_category":"Overheidsdiensten",
    "sg:phone":"+31 46 442 2415",
    "sg:postcode":"6447 AZ",
    "sg:province":"Limburg",
    "wof:name":"De Henkhof",
    "wof:placetype":"venue"
},
  "geometry": {"coordinates":[-111.9303436279,34.1680908203],"type":"Point"}
}