{
  "type": "Feature",
  "properties": {
    "addr:full":"Postbus 82 Veghel North Brabant 5460 AB",
    "addr:housenumber":"82",
    "addr:postcode":"5460 ab",
    "addr:street":"Postbus",
    "iso:country":"NL",
    "sg:address":"Postbus 82",
    "sg:city":"Veghel",
    "sg:orig_category":"Bedrijfsopleidingen",
    "sg:phone":"+31 413 344 113",
    "sg:postcode":"5460 AB",
    "sg:province":"North Brabant",
    "wof:name":"Sovo",
    "wof:placetype":"venue"
},
  "geometry": {"coordinates":[5.54175,51.617222],"type":"Point"}
}