{
  "type": "Feature",
  "properties": {
    "addr:full":"Dampln 7 Dordrecht Zuid-Holland 3319 HC",
    "addr:housenumber":"7",
    "addr:postcode":"3319 hc",
    "addr:street":"Dampln",
    "iso:country":"NL",
    "sg:address":"Dampln 7",
    "sg:city":"Dordrecht",
    "sg:orig_category":"Kappers",
    "sg:phone":"+31 78 616 0397",
    "sg:postcode":"3319 HC",
    "sg:province":"Zuid-Holland",
    "wof:name":"Pelt, Van",
    "wof:placetype":"venue"
},
  "geometry": {"coordinates":[4.704518,51.794182],"type":"Point"}
}