{
  "type": "Feature",
  "properties": {
    "addr:full":"J J Allanstraat 377 Westzaan North Holland 1551 RJ",
    "addr:housenumber":"377",
    "addr:postcode":"1551 rj",
    "addr:street":"Allanstraat",
    "iso:country":"NL",
    "sg:address":"J J Allanstraat 377",
    "sg:city":"Westzaan",
    "sg:orig_category":"Bloemen And Planten",
    "sg:phone":"+31 75 670 4228",
    "sg:postcode":"1551 RJ",
    "sg:province":"North Holland",
    "wof:name":"Provence",
    "wof:placetype":"venue"
},
  "geometry": {"coordinates":[4.773409,52.458584],"type":"Point"}
}