{
  "type": "Feature",
  "properties": {
    "addr:full":"Pater Beatusstraat 7 Heerlen Limburg 6411 TR",
    "addr:housenumber":"7",
    "addr:postcode":"6411 tr",
    "addr:street":"Pater Beatusstraat",
    "iso:country":"NL",
    "sg:address":"Pater Beatusstraat 7",
    "sg:city":"Heerlen",
    "sg:orig_category":"Overheidsdiensten",
    "sg:phone":"+31 45 571 5241",
    "sg:postcode":"6411 TR",
    "sg:province":"Limburg",
    "wof:name":"T Loon",
    "wof:placetype":"venue"
},
  "geometry": {"coordinates":[5.9693632126,50.8887329102],"type":"Point"}
}