{
  "type": "Feature",
  "properties": {
    "addr:full":"Azielaan 12 'S Hertogenbosch Noord-Brabant 5232 BA",
    "addr:housenumber":"12",
    "addr:postcode":"5232 ba",
    "addr:street":"Azielaan;' S",
    "iso:country":"NL",
    "sg:address":"Azielaan 12",
    "sg:city":"'S Hertogenbosch",
    "sg:orig_category":"Elektrische Apparatuur Gh",
    "sg:phone":"+31 73 641 1655",
    "sg:postcode":"5232 BA",
    "sg:province":"Noord-Brabant",
    "wof:name":"Hesdo Bv",
    "wof:placetype":"venue"
},
  "geometry": {"coordinates":[5.34093,51.707596],"type":"Point"}
}