{
  "type": "Feature",
  "properties": {
    "addr:full":"Lariksweg 14 Epe Gelderland 8162 EG",
    "addr:housenumber":"14",
    "addr:postcode":"8162 eg",
    "addr:street":"Lariksweg;Gelderland",
    "iso:country":"NL",
    "sg:address":"Lariksweg 14",
    "sg:city":"Epe",
    "sg:orig_category":"Bedrijfs- And Managementsconsultants",
    "sg:phone":"+31 578 612 635",
    "sg:postcode":"8162 EG",
    "sg:province":"Gelderland",
    "wof:name":"Buro Innen",
    "wof:placetype":"venue"
},
  "geometry": {"coordinates":[5.968735,52.361],"type":"Point"}
}