{
  "type": "Feature",
  "properties": {
    "iso:country":"NL",
    "sg:address":"S Heer Lauwendorp 3",
    "sg:city":"Zierikzee",
    "sg:orig_category":"Psychosociale Therapeuten",
    "sg:phone":"+31 111 417 573",
    "sg:postcode":"4301 RA",
    "sg:province":"Zeeland",
    "wof:name":"Abvc",
    "wof:placetype":"venue"
},
  "geometry": {"coordinates":[3.926702,51.646843],"type":"Point"}
}