{
  "type": "Feature",
  "properties": {
    "iso:country":"NL",
    "sg:address":"Postbus 220",
    "sg:city":"Spykenisse",
    "sg:orig_category":"Scholen Voor Algemeen Voortgezet Onderwijs",
    "sg:phone":"+31 181 600 200",
    "sg:postcode":"3200 AE",
    "sg:website":"http://www.penta.nl",
    "wof:name":"Penta College Csg",
    "wof:placetype":"venue"
},
  "geometry": {"coordinates":[4.35844,51.837879],"type":"Point"}
}