{
  "type": "Feature",
  "properties": {
    "iso:country":"NL",
    "sg:address":"Albertsbaan 17",
    "sg:city":"Roden",
    "sg:orig_category":"Kappers",
    "sg:phone":"+31 50 501 5000",
    "sg:postcode":"9301 KS",
    "sg:province":"Provincie Drenthe",
    "wof:name":"Sylvia",
    "wof:placetype":"venue"
},
  "geometry": {"coordinates":[6.431259,53.136589],"type":"Point"}
}