{
  "type": "Feature",
  "properties": {
    "addr:full":"Noordwijnkade 30 Honselersdijk South Holland 2675 TL",
    "addr:housenumber":"30",
    "addr:postcode":"2675 tl",
    "addr:street":"Noordwijnkade",
    "iso:country":"NL",
    "sg:address":"Noordwijnkade 30",
    "sg:city":"Honselersdijk",
    "sg:orig_category":"Gebouwenafwerking, Renovaties And Reiniging",
    "sg:phone":"+31 174 627 373",
    "sg:postcode":"2675 TL",
    "sg:province":"South Holland",
    "wof:name":"Reijntjes Reinigings Technieken",
    "wof:placetype":"venue"
},
  "geometry": {"coordinates":[4.22951,52.008755],"type":"Point"}
}