{
  "type": "Feature",
  "properties": {
    "iso:country":"NL",
    "sg:address":"Lieven De Keylaan 56",
    "sg:city":"Hilversum",
    "sg:classifiers":[
        {
            "category":"Education",
            "subcategory":"Preschool",
            "type":"Public Place"
        }
    ],
    "sg:phone":"+31 35 685 6200",
    "sg:postcode":"1222 LH",
    "sg:province":"North Holland",
    "sg:tags":[
        "kleuteronderwijs",
        "basis-"
    ],
    "wof:name":"Prot Chr Basisschool Kruispunt Vestiging Da Costas",
    "wof:placetype":"venue"
},
  "geometry": {"coordinates":[5.184825,52.236519],"type":"Point"}
}