{
  "type": "Feature",
  "properties": {
    "addr:full":"Havenzicht 41 Almere Flevoland 1357  N",
    "addr:housenumber":"41;1357",
    "addr:street":"Havenzicht;Flevoland;N",
    "iso:country":"NL",
    "sg:address":"Havenzicht 41",
    "sg:city":"Almere",
    "sg:orig_category":"Diverse Opleidingen And Onderwijs",
    "sg:phone":"+31 36 536 2620",
    "sg:postcode":"1357  N",
    "sg:province":"Flevoland",
    "wof:name":"Forecast Brainstorm B.V.",
    "wof:placetype":"venue"
},
  "geometry": {"coordinates":[5.21916,52.33448],"type":"Point"}
}