{
  "type": "Feature",
  "properties": {
    "addr:full":"Anjerstr 2 Dongen ZA. 5102 ZA",
    "addr:housenumber":"2",
    "addr:postcode":"5102",
    "addr:street":"Anjerstr;Za.",
    "iso:country":"NL",
    "sg:address":"Anjerstr 2",
    "sg:city":"Dongen",
    "sg:orig_category":"Accountants - Administratie- Consulenten En -Kantoren",
    "sg:phone":"+31 162 319 000",
    "sg:postcode":"5102 ZA",
    "sg:province":"ZA.",
    "wof:name":"Smulders & Jacobs",
    "wof:placetype":"venue"
},
  "geometry": {"coordinates":[28.693939,-31.75271],"type":"Point"}
}