{
  "type": "Feature",
  "properties": {
    "addr:full":"Beemsterstr 491 Amsterdam North Holland 1024 BE",
    "addr:housenumber":"491",
    "addr:postcode":"1024",
    "iso:country":"NL",
    "sg:address":"Beemsterstr 491",
    "sg:city":"Amsterdam",
    "sg:orig_category":"Peuterspeelzalen",
    "sg:phone":"+31 20 636 7334",
    "sg:postcode":"1024 BE",
    "sg:province":"North Holland",
    "wof:name":"Zwanemeer, 'T",
    "wof:placetype":"venue"
},
  "geometry": {"coordinates":[4.949679,52.395287],"type":"Point"}
}