{
  "type": "Feature",
  "properties": {
    "iso:country":"NL",
    "sg:address":"Hoornzwaluw 12",
    "sg:city":"Veenendaal",
    "sg:orig_category":"Artsen And Specialisten",
    "sg:phone":"+31 318 517 037",
    "sg:postcode":"3905 RM",
    "sg:province":"Utrecht",
    "wof:name":"Huisartsenpraktijk West",
    "wof:placetype":"venue"
},
  "geometry": {"coordinates":[5.533068,52.029377],"type":"Point"}
}