{
  "type": "Feature",
  "properties": {
    "addr:full":"Charl Kerksngl 8 Rotterdam Zuid-Holland 3082 DA",
    "addr:housenumber":"8",
    "addr:postcode":"3082 da",
    "addr:street":"Kerksngl",
    "iso:country":"NL",
    "sg:address":"Charl Kerksngl 8",
    "sg:city":"Rotterdam",
    "sg:classifiers":[
        {
            "category":"Retail",
            "subcategory":"Auto Repair",
            "type":"Services"
        }
    ],
    "sg:phone":"+31 10 429 5640",
    "sg:postcode":"3082 DA",
    "sg:province":"Zuid-Holland",
    "sg:tags":[
        "garage"
    ],
    "wof:name":"Schobben",
    "wof:placetype":"venue"
},
  "geometry": {"coordinates":[4.46731,51.889462],"type":"Point"}
}