{
  "type": "Feature",
  "properties": {
    "addr:full":"Leenderwg 178A Eindhoven Noord-Brabant 5644 AA",
    "addr:housenumber":"178a",
    "addr:postcode":"5644 aa",
    "iso:country":"NL",
    "sg:address":"Leenderwg 178A",
    "sg:city":"Eindhoven",
    "sg:orig_category":"Woninginrichting",
    "sg:phone":"+31 40 211 0767",
    "sg:postcode":"5644 AA",
    "sg:province":"Noord-Brabant",
    "wof:name":"Hespa Bv",
    "wof:placetype":"venue"
},
  "geometry": {"coordinates":[5.4938287735,51.4225273132],"type":"Point"}
}