{
  "type": "Feature",
  "properties": {
    "addr:full":"Royaardsplein 13 Schiedam Zuid-Holland 3123 AK",
    "addr:housenumber":"13",
    "addr:postcode":"3123 ak",
    "addr:street":"Royaardsplein",
    "iso:country":"NL",
    "sg:address":"Royaardsplein 13",
    "sg:city":"Schiedam",
    "sg:orig_category":"Bedrijfs- And Managementsconsultants",
    "sg:phone":"+31 10 471 1435",
    "sg:postcode":"3123 AK",
    "sg:province":"Zuid-Holland",
    "wof:name":"Ajt Advies En Projecten Bv",
    "wof:placetype":"venue"
},
  "geometry": {"coordinates":[4.367212,51.938389],"type":"Point"}
}