{
  "type": "Feature",
  "properties": {
    "addr:full":"Klipper 31 Wyk By Duurstede Utrecht 3961 KH",
    "addr:housenumber":"31",
    "addr:postcode":"duurstede;3961 kh",
    "addr:street":"Klipper",
    "iso:country":"NL",
    "sg:address":"Klipper 31",
    "sg:city":"Wyk By Duurstede",
    "sg:orig_category":"Adviesbureaus Bedrijfsorganisatie",
    "sg:phone":"+31 343 597 577",
    "sg:postcode":"3961 KH",
    "sg:province":"Utrecht",
    "wof:name":"Zeven",
    "wof:placetype":"venue"
},
  "geometry": {"coordinates":[5.32892,51.969933],"type":"Point"}
}