{
  "type": "Feature",
  "properties": {
    "iso:country":"NL",
    "sg:address":"Hinthamerstr 18",
    "sg:city":"S Hertogenbosch",
    "sg:classifiers":[
        {
            "category":"Food & Beverages",
            "subcategory":"Bakery",
            "type":"Retail Goods"
        }
    ],
    "sg:phone":"+31 73 612 0954",
    "sg:postcode":"5211 MP",
    "sg:province":"Noord-Brabant",
    "sg:tags":[
        "brood",
        "en",
        "banket"
    ],
    "wof:name":"Bart",
    "wof:placetype":"venue"
},
  "geometry": {"coordinates":[5.305537,51.689045],"type":"Point"}
}