{
  "type": "Feature",
  "properties": {
    "addr:full":"Stationsweg 18 Baarn Utrecht 3743 EN",
    "addr:housenumber":"18",
    "addr:postcode":"3743 en",
    "addr:street":"Stationsweg",
    "iso:country":"NL",
    "sg:address":"Stationsweg 18",
    "sg:city":"Baarn",
    "sg:orig_category":"Overheidsdiensten",
    "sg:phone":"+31 35 548 1611",
    "sg:postcode":"3743 EN",
    "sg:province":"Utrecht",
    "wof:name":"Gemeente Baarn",
    "wof:placetype":"venue"
},
  "geometry": {"coordinates":[5.2921209335,52.2110099792],"type":"Point"}
}