{
  "type": "Feature",
  "properties": {
    "addr:full":"Hogestr 60 Druten Gelderland 6651 BM",
    "addr:housenumber":"60",
    "addr:postcode":"6651 bm",
    "addr:street":"Hogestr",
    "iso:country":"NL",
    "sg:address":"Hogestr 60",
    "sg:city":"Druten",
    "sg:orig_category":"Fotoreportages",
    "sg:phone":"+31 487 512 438",
    "sg:postcode":"6651 BM",
    "sg:province":"Gelderland",
    "sg:website":"http://www.vanaltena.nl",
    "wof:name":"Altena Vakfotografie, Van",
    "wof:placetype":"venue"
},
  "geometry": {"coordinates":[5.60526,51.88567],"type":"Point"}
}