{
  "type": "Feature",
  "properties": {
    "addr:full":"Kapt Rondairestr 14 Tilburg North Brabant 5015 BC",
    "addr:housenumber":"14",
    "addr:postcode":"5015 bc",
    "iso:country":"NL",
    "sg:address":"Kapt Rondairestr 14",
    "sg:city":"Tilburg",
    "sg:orig_category":"Hydraulische Apparaten En Installaties",
    "sg:phone":"+31 13 536 5806",
    "sg:postcode":"5015 BC",
    "sg:province":"North Brabant",
    "wof:name":"Hydro Vasli",
    "wof:placetype":"venue"
},
  "geometry": {"coordinates":[5.111916,51.568413],"type":"Point"}
}