{
  "type": "Feature",
  "properties": {
    "addr:full":"Zeelenweg 24 Helmond Noord-Brabant 5704 BA",
    "addr:housenumber":"24",
    "addr:postcode":"5704 ba",
    "addr:street":"Zeelenweg",
    "iso:country":"NL",
    "sg:address":"Zeelenweg 24",
    "sg:city":"Helmond",
    "sg:orig_category":"Metaalwerken",
    "sg:phone":"+31 492 510 234",
    "sg:postcode":"5704 BA",
    "sg:province":"Noord-Brabant",
    "wof:name":"Naustuco Bv",
    "wof:placetype":"venue"
},
  "geometry": {"coordinates":[5.700286,51.458355],"type":"Point"}
}