{
  "type": "Feature",
  "properties": {
    "iso:country":"NL",
    "sg:address":"Kloosterstraat 4",
    "sg:city":"Haarlem",
    "sg:orig_category":"Wasserettes And Stomerijen",
    "sg:phone":"+31 23 525 9147",
    "sg:postcode":"2021 VN",
    "sg:province":"North Holland",
    "wof:name":"Wasserette/Wassalon Cronje",
    "wof:placetype":"venue"
},
  "geometry": {"coordinates":[4.641313076,52.3940010071],"type":"Point"}
}