{
  "type": "Feature",
  "properties": {
    "addr:full":"Bergstraat 17 Leerdam South Holland 4141 BS",
    "addr:housenumber":"17",
    "addr:postcode":"4141 bs",
    "addr:street":"Bergstraat",
    "iso:country":"NL",
    "sg:address":"Bergstraat 17",
    "sg:city":"Leerdam",
    "sg:orig_category":"Loodgieterswerk, Verwarming And Sanitaire Installaties",
    "sg:phone":"+31 345 619 630",
    "sg:postcode":"4141 BS",
    "sg:province":"South Holland",
    "wof:name":"J.A. Rouwenhorst",
    "wof:placetype":"venue"
},
  "geometry": {"coordinates":[5.094854,51.892254],"type":"Point"}
}