{
  "type": "Feature",
  "properties": {
    "iso:country":"NL",
    "sg:address":"Wilhelminawg 19",
    "sg:city":"Doorn",
    "sg:orig_category":"Adviesbureaus Bedrijfsorganisatie",
    "sg:phone":"+31 343 421 844",
    "sg:postcode":"3941 DE",
    "sg:province":"Utrecht",
    "wof:name":"Quen\u00e9, J M",
    "wof:placetype":"venue"
},
  "geometry": {"coordinates":[5.342243,52.042618],"type":"Point"}
}