{
  "type": "Feature",
  "properties": {
    "addr:full":"Wilhelminawg 19 Doorn Utrecht 3941 DE",
    "addr:housenumber":"19",
    "addr:postcode":"3941 de",
    "addr:street":"Wilhelminawg",
    "iso:country":"NL",
    "sg:address":"Wilhelminawg 19",
    "sg:city":"Doorn",
    "sg:orig_category":"Adviesbureaus Bedrijfsorganisatie",
    "sg:phone":"+31 343 421 844",
    "sg:postcode":"3941 DE",
    "sg:province":"Utrecht",
    "wof:name":"Quen\u00e9, J M",
    "wof:placetype":"venue"
},
  "geometry": {"coordinates":[5.342243,52.042618],"type":"Point"}
}