{
  "type": "Feature",
  "properties": {
    "addr:full":"Paduaweg 3 Den Dolder Utrecht 3734 GG",
    "addr:housenumber":"3",
    "addr:postcode":"3734 gg",
    "addr:street":"Paduaweg",
    "iso:country":"NL",
    "sg:address":"Paduaweg 3",
    "sg:city":"Den Dolder",
    "sg:orig_category":"Banken And Kredietinstellingen",
    "sg:phone":"+31 30 698 3666",
    "sg:postcode":"3734 GG",
    "sg:province":"Utrecht",
    "wof:name":"Rabobank",
    "wof:placetype":"venue"
},
  "geometry": {"coordinates":[5.240073,52.139374],"type":"Point"}
}