{
  "type": "Feature",
  "properties": {
    "addr:full":"Schapenweide 10 Breda Noord-Brabant 4824 AN",
    "addr:housenumber":"10",
    "addr:postcode":"4824 an",
    "addr:street":"Schapenweide",
    "iso:country":"NL",
    "sg:address":"Schapenweide 10",
    "sg:city":"Breda",
    "sg:orig_category":"Diverse Grafische Activiteiten",
    "sg:phone":"+31 76 541 0050",
    "sg:postcode":"4824 AN",
    "sg:province":"Noord-Brabant",
    "wof:name":"Tiboscreen Bv",
    "wof:placetype":"venue"
},
  "geometry": {"coordinates":[4.757306,51.611698],"type":"Point"}
}