{
  "type": "Feature",
  "properties": {
    "addr:full":"Ritmeesterlaan 14 Veenendaal Utrecht 3903 XG",
    "addr:housenumber":"14",
    "addr:postcode":"3903 xg",
    "addr:street":"Ritmeesterlaan",
    "iso:country":"NL",
    "sg:address":"Ritmeesterlaan 14",
    "sg:city":"Veenendaal",
    "sg:orig_category":"Goederenvervoer Over De Weg",
    "sg:phone":"+31 318 523 839",
    "sg:postcode":"3903 XG",
    "sg:province":"Utrecht",
    "wof:name":"Europeeer International Bv",
    "wof:placetype":"venue"
},
  "geometry": {"coordinates":[5.54992,52.01627],"type":"Point"}
}