{
  "type": "Feature",
  "properties": {
    "addr:full":"Hoefsmidstr 41 Hoogvliet Rt South Holland 3194 AA",
    "addr:housenumber":"41",
    "addr:postcode":"3194 aa",
    "addr:street":"Hoefsmidstr;Rt South",
    "iso:country":"NL",
    "sg:address":"Hoefsmidstr 41",
    "sg:city":"Hoogvliet Rt",
    "sg:orig_category":"Webdesign Bureaus",
    "sg:phone":"+31 10 231 0615",
    "sg:postcode":"3194 AA",
    "sg:province":"South Holland",
    "sg:website":"http://www.atlantis-interactive.nl",
    "wof:name":"Atlantis Interactive",
    "wof:placetype":"venue"
},
  "geometry": {"coordinates":[4.3724789619,51.8716773987],"type":"Point"}
}