{
  "type": "Feature",
  "properties": {
    "iso:country":"NL",
    "sg:address":"Eikenlaan 133",
    "sg:city":"Oosterhout Nb",
    "sg:orig_category":"Onderhoud And Reparatie Kantoorapparatuur",
    "sg:phone":"+31 162 470 322",
    "sg:postcode":"4902 RC",
    "sg:province":"North Brabant",
    "wof:name":"Stichting Brabant Computer Services",
    "wof:placetype":"venue"
},
  "geometry": {"coordinates":[4.872141,51.634079],"type":"Point"}
}