{
  "type": "Feature",
  "properties": {
    "addr:full":"Donk 3 Kessel Lb Limburg 5995 PL",
    "addr:housenumber":"3",
    "addr:postcode":"lb;5995 pl",
    "addr:street":"Donk",
    "iso:country":"NL",
    "sg:address":"Donk 3",
    "sg:city":"Kessel Lb",
    "sg:orig_category":"Fruit And Groenten Gh",
    "sg:phone":"+31 77 462 1972",
    "sg:postcode":"5995 PL",
    "sg:province":"Limburg",
    "wof:name":"P.A.F. Lenders-Janssen",
    "wof:placetype":"venue"
},
  "geometry": {"coordinates":[6.058261,51.310329],"type":"Point"}
}