{
  "type": "Feature",
  "properties": {
    "addr:full":"Kuiperswg 37 Woerden Utrecht 3449 JA",
    "addr:housenumber":"37",
    "addr:postcode":"3449 ja",
    "addr:street":"Kuiperswg",
    "iso:country":"NL",
    "sg:address":"Kuiperswg 37",
    "sg:city":"Woerden",
    "sg:orig_category":"Medische Installaties En Instrumenten",
    "sg:phone":"+31 348 423 661",
    "sg:postcode":"3449 JA",
    "sg:province":"Utrecht",
    "wof:name":"Pmv Bv",
    "wof:placetype":"venue"
},
  "geometry": {"coordinates":[4.863616,52.083679],"type":"Point"}
}