{
  "type": "Feature",
  "properties": {
    "iso:country":"NL",
    "sg:address":"Barrierweg 250",
    "sg:city":"Eindhoven",
    "sg:orig_category":"Metaalwerken",
    "sg:phone":"+31 40 245 5870",
    "sg:postcode":"5622 CS",
    "sg:province":"North Brabant",
    "wof:name":"Systems Van De Wetering",
    "wof:placetype":"venue"
},
  "geometry": {"coordinates":[5.45946,51.457169],"type":"Point"}
}