{
  "type": "Feature",
  "properties": {
    "addr:full":"3E Loosterweg 44 Hillegom Zuid-Holland 2182 CV",
    "addr:housenumber":"44",
    "addr:postcode":"2182 cv",
    "addr:street":"3E Loosterweg",
    "iso:country":"NL",
    "sg:address":"3E Loosterweg 44",
    "sg:city":"Hillegom",
    "sg:orig_category":"Airconditioning And Ventilatie",
    "sg:phone":"+31 252 524 528",
    "sg:postcode":"2182 CV",
    "sg:province":"Zuid-Holland",
    "wof:name":"Novair Bv",
    "wof:placetype":"venue"
},
  "geometry": {"coordinates":[4.561913,52.293262],"type":"Point"}
}