{
  "type": "Feature",
  "properties": {
    "addr:full":"Molenweg 53 Bunnik Utrecht 3981 KB",
    "addr:housenumber":"53",
    "addr:postcode":"3981 kb",
    "addr:street":"Molenweg",
    "iso:country":"NL",
    "sg:address":"Molenweg 53",
    "sg:city":"Bunnik",
    "sg:classifiers":[
        {
            "category":"Fast Food",
            "type":"Food & Drink"
        }
    ],
    "sg:phone":"+31 30 656 1740",
    "sg:postcode":"3981 KB",
    "sg:province":"Utrecht",
    "sg:tags":[
        "afhaal",
        "restaurant"
    ],
    "wof:name":"Chinees Rest. Hong Kong Garden",
    "wof:placetype":"venue"
},
  "geometry": {"coordinates":[5.202742,52.065662],"type":"Point"}
}