{
  "type": "Feature",
  "properties": {
    "addr:full":"Beemsterstr 22 Assendelft North Holland 1566 WR",
    "addr:housenumber":"22",
    "addr:postcode":"1566 wr",
    "addr:street":"Beemsterstr",
    "iso:country":"NL",
    "sg:address":"Beemsterstr 22",
    "sg:city":"Assendelft",
    "sg:classifiers":[
        {
            "category":"Personal",
            "subcategory":"Nail Salon",
            "type":"Services"
        }
    ],
    "sg:phone":"+31 75 687 3944",
    "sg:postcode":"1566 WR",
    "sg:province":"North Holland",
    "sg:tags":[
        "pedicure"
    ],
    "wof:name":"Kooten, H M Van",
    "wof:placetype":"venue"
},
  "geometry": {"coordinates":[4.744239,52.466705],"type":"Point"}
}