{
  "type": "Feature",
  "properties": {
    "addr:full":"Kerkstraat 11 Leende North Brabant 5595 CX",
    "addr:housenumber":"11",
    "addr:postcode":"5595 cx",
    "addr:street":"Kerkstraat",
    "iso:country":"NL",
    "sg:address":"Kerkstraat 11",
    "sg:city":"Leende",
    "sg:orig_category":"Boekhouders",
    "sg:phone":"+31 40 206 2657",
    "sg:postcode":"5595 CX",
    "sg:province":"North Brabant",
    "wof:name":"Slenders Administraties",
    "wof:placetype":"venue"
},
  "geometry": {"coordinates":[5.556626,51.348919],"type":"Point"}
}