{
  "type": "Feature",
  "properties": {
    "iso:country":"NL",
    "sg:address":"Havenkade 16",
    "sg:city":"Bruinisse",
    "sg:orig_category":"Pleziervaartuigen And Reparatie",
    "sg:phone":"+31 111 484 088",
    "sg:postcode":"4311 BA",
    "sg:province":"Zeeland",
    "wof:name":"Oosterschelde Jachtwerf",
    "wof:placetype":"venue"
},
  "geometry": {"coordinates":[4.093211,51.66573],"type":"Point"}
}