{
  "type": "Feature",
  "properties": {
    "addr:full":"Postbus 131 Voorschoten Zuid-Holland 2250 AC",
    "addr:housenumber":"131",
    "addr:postcode":"2250 ac",
    "addr:street":"Postbus",
    "iso:country":"NL",
    "sg:address":"Postbus 131",
    "sg:city":"Voorschoten",
    "sg:orig_category":"Webdesign Bureaus",
    "sg:phone":"+31 71 576 9543",
    "sg:postcode":"2250 AC",
    "sg:province":"Zuid-Holland",
    "sg:website":"http://www.imagoo.nl",
    "wof:name":"Imagoo",
    "wof:placetype":"venue"
},
  "geometry": {"coordinates":[4.4442901611,52.1248245239],"type":"Point"}
}