{
  "type": "Feature",
  "properties": {
    "addr:full":"Onyx 89 Heerhugowaard Noord-Holland 1703 CG",
    "addr:housenumber":"89",
    "addr:postcode":"1703 cg",
    "addr:street":"Onyx",
    "iso:country":"NL",
    "sg:address":"Onyx 89",
    "sg:city":"Heerhugowaard",
    "sg:classifiers":[
        {
            "category":"Education",
            "subcategory":"Preschool",
            "type":"Public Place"
        }
    ],
    "sg:phone":"+31 72 571 4766",
    "sg:postcode":"1703 CG",
    "sg:province":"Noord-Holland",
    "sg:tags":[
        "kleuteronderwijs",
        "basis-"
    ],
    "wof:name":"Chr Basisschool De Tweemaster",
    "wof:placetype":"venue"
},
  "geometry": {"coordinates":[4.819871,52.660919],"type":"Point"}
}