{
  "type": "Feature",
  "properties": {
    "addr:full":"Voorstraat 48 Dirksland Zuid-Holland 3247 CE",
    "addr:housenumber":"48",
    "addr:postcode":"3247 ce",
    "addr:street":"Voorstraat",
    "iso:country":"NL",
    "sg:address":"Voorstraat 48",
    "sg:city":"Dirksland",
    "sg:classifiers":[
        {
            "category":"Fast Food",
            "type":"Food & Drink"
        }
    ],
    "sg:phone":"+31 187 603 783",
    "sg:postcode":"3247 CE",
    "sg:province":"Zuid-Holland",
    "sg:tags":[
        "afhaal",
        "restaurant"
    ],
    "wof:name":"Vof Chow- De Jong",
    "wof:placetype":"venue"
},
  "geometry": {"coordinates":[4.105012,51.748753],"type":"Point"}
}