{
  "type": "Feature",
  "properties": {
    "addr:full":"Bloemstede 1 Maarssen Utrecht 3608 TK",
    "addr:housenumber":"1",
    "addr:postcode":"3608 tk",
    "addr:street":"Bloemstede",
    "iso:country":"NL",
    "sg:address":"Bloemstede 1",
    "sg:city":"Maarssen",
    "sg:classifiers":[
        {
            "category":"Education",
            "subcategory":"Preschool",
            "type":"Public Place"
        }
    ],
    "sg:phone":"+31 346 564 576",
    "sg:postcode":"3608 TK",
    "sg:province":"Utrecht",
    "sg:tags":[
        "kleuteronderwijs",
        "basis-"
    ],
    "wof:name":"De Wilde Wingerd",
    "wof:placetype":"venue"
},
  "geometry": {"coordinates":[5.031642,52.126358],"type":"Point"}
}