{
  "type": "Feature",
  "properties": {
    "addr:full":"Ommoordsehof 9A Rotterdam Zuid-Holland 3056 JR",
    "addr:housenumber":"9a",
    "addr:postcode":"3056 jr",
    "addr:street":"Ommoordsehof",
    "iso:country":"NL",
    "sg:address":"Ommoordsehof 9A",
    "sg:city":"Rotterdam",
    "sg:orig_category":"Adviesbureaus Bedrijfsorganisatie",
    "sg:phone":"+31 10 286 2411",
    "sg:postcode":"3056 JR",
    "sg:province":"Zuid-Holland",
    "wof:name":"Gyba Bv",
    "wof:placetype":"venue"
},
  "geometry": {"coordinates":[4.5210390091,51.9547386169],"type":"Point"}
}