{
  "type": "Feature",
  "properties": {
    "addr:full":"Meeuwensngl 61 Rozenburg Zh South Holland 3181 SW",
    "addr:housenumber":"61",
    "addr:postcode":"zh;3181 sw",
    "addr:street":"Meeuwensngl",
    "iso:country":"NL",
    "sg:address":"Meeuwensngl 61",
    "sg:city":"Rozenburg Zh",
    "sg:orig_category":"Autorijscholen",
    "sg:phone":"+31 181 213 114",
    "sg:postcode":"3181 SW",
    "sg:province":"South Holland",
    "wof:name":"West",
    "wof:placetype":"venue"
},
  "geometry": {"coordinates":[4.249615,51.904446],"type":"Point"}
}