{
  "type": "Feature",
  "properties": {
    "addr:full":"Elegaststraat 28 Amersfoort Utrecht 3813 HK",
    "addr:housenumber":"28",
    "addr:postcode":"3813 hk",
    "addr:street":"Elegaststraat",
    "iso:country":"NL",
    "sg:address":"Elegaststraat 28",
    "sg:city":"Amersfoort",
    "sg:orig_category":"Fotografische And Optische Artikelen Gh",
    "sg:phone":"+31 33 475 2421",
    "sg:postcode":"3813 HK",
    "sg:province":"Utrecht",
    "wof:name":"Filtrade",
    "wof:placetype":"venue"
},
  "geometry": {"coordinates":[5.388451,52.171574],"type":"Point"}
}