{
  "type": "Feature",
  "properties": {
    "iso:country":"NL",
    "sg:address":"Choorstraat 45",
    "sg:city":"Delft",
    "sg:orig_category":"Meubelzaken, Woning- And Keukeninrichting",
    "sg:phone":"+31 15 212 6694",
    "sg:postcode":"2611 JE",
    "sg:province":"Zuid-Holland",
    "wof:name":"La Dependance",
    "wof:placetype":"venue"
},
  "geometry": {"coordinates":[4.358515,52.013191],"type":"Point"}
}