{
  "type": "Feature",
  "properties": {
    "addr:full":"Dr Bakstr 89 Maastricht Limburg 6216 CD",
    "addr:housenumber":"89",
    "addr:postcode":"6216 cd",
    "iso:country":"NL",
    "sg:address":"Dr Bakstr 89",
    "sg:city":"Maastricht",
    "sg:orig_category":"Adviesbureaus Bouwkosten",
    "sg:phone":"+31 43 354 7766",
    "sg:postcode":"6216 CD",
    "sg:province":"Limburg",
    "wof:name":"Bertram Maastricht Bv, Adviesburo",
    "wof:placetype":"venue"
},
  "geometry": {"coordinates":[5.665041,50.84877],"type":"Point"}
}