{
  "type": "Feature",
  "properties": {
    "addr:full":"V Benthuizenln 3 Heerhugowaard Noord-Holland 1701 BZ",
    "addr:housenumber":"3",
    "addr:postcode":"1701 bz",
    "addr:street":"Benthuizenln",
    "iso:country":"NL",
    "sg:address":"V Benthuizenln 3",
    "sg:city":"Heerhugowaard",
    "sg:classifiers":[
        {
            "category":"Retail",
            "subcategory":"Auto Repair",
            "type":"Services"
        }
    ],
    "sg:phone":"+31 72 571 0011",
    "sg:postcode":"1701 BZ",
    "sg:province":"Noord-Holland",
    "sg:tags":[
        "garage"
    ],
    "wof:name":"Andriessen Bv",
    "wof:placetype":"venue"
},
  "geometry": {"coordinates":[4.827522,52.665195],"type":"Point"}
}