{
  "type": "Feature",
  "properties": {
    "addr:full":"Leidsegr 92 Amsterdam North Holland 1016 CS",
    "addr:housenumber":"92",
    "addr:postcode":"1016 cs",
    "addr:street":"Leidsegr",
    "iso:country":"NL",
    "sg:address":"Leidsegr 92",
    "sg:city":"Amsterdam",
    "sg:orig_category":"Webdesign Bureaus",
    "sg:phone":"+31 20 422 9922",
    "sg:postcode":"1016 CS",
    "sg:province":"North Holland",
    "sg:website":"http://www.distanttrain.com",
    "wof:name":"Distant Train",
    "wof:placetype":"venue"
},
  "geometry": {"coordinates":[4.8813848495,52.3659515381],"type":"Point"}
}