{
  "type": "Feature",
  "properties": {
    "addr:full":"Dijkweg 87 Naaldwijk South Holland 2671 CX",
    "addr:housenumber":"87",
    "addr:postcode":"2671 cx",
    "addr:street":"Dijkweg",
    "iso:country":"NL",
    "sg:address":"Dijkweg 87",
    "sg:city":"Naaldwijk",
    "sg:orig_category":"Aannemers Woningbouw",
    "sg:phone":"+31 174 642 674",
    "sg:postcode":"2671 CX",
    "sg:province":"South Holland",
    "wof:name":"Aannemingsbedrijf A. Van Der Meer",
    "wof:placetype":"venue"
},
  "geometry": {"coordinates":[4.217262,52.000389],"type":"Point"}
}