{
  "type": "Feature",
  "properties": {
    "addr:full":"De Warren 1 Drachten Friesland 9203 HT",
    "addr:housenumber":"1",
    "addr:postcode":"9203 ht",
    "addr:street":"De Warren",
    "iso:country":"NL",
    "sg:address":"De Warren 1",
    "sg:city":"Drachten",
    "sg:orig_category":"Makelaars In Onroerend Goed",
    "sg:phone":"+31 512 541 400",
    "sg:postcode":"9203 HT",
    "sg:province":"Friesland",
    "wof:name":"Dijkstra",
    "wof:placetype":"venue"
},
  "geometry": {"coordinates":[6.102618,53.098602],"type":"Point"}
}