{
  "type": "Feature",
  "properties": {
    "iso:country":"NL",
    "sg:address":"Denenburg 145",
    "sg:city":"S Gravenhage",
    "sg:orig_category":"Agenturen En Commissiehandel",
    "sg:phone":"+31 70 385 5634",
    "sg:postcode":"2591 AC",
    "sg:province":"Zuid-Holland",
    "wof:name":"Tempel Impex Bv, Van Den",
    "wof:placetype":"venue"
},
  "geometry": {"coordinates":[4.3639,52.09351],"type":"Point"}
}