{
  "type": "Feature",
  "properties": {
    "addr:full":"Rosheuvel 1 Valkenswaard Noord-Brabant 5554 HW",
    "addr:housenumber":"1",
    "addr:postcode":"5554 hw",
    "addr:street":"Rosheuvel",
    "iso:country":"NL",
    "sg:address":"Rosheuvel 1",
    "sg:city":"Valkenswaard",
    "sg:orig_category":"Adviesbureaus Personeel",
    "sg:phone":"+31 40 207 1800",
    "sg:postcode":"5554 HW",
    "sg:province":"Noord-Brabant",
    "sg:website":"http://www.evodevelopment.nl",
    "wof:name":"Evo Development",
    "wof:placetype":"venue"
},
  "geometry": {"coordinates":[5.454916,51.354725],"type":"Point"}
}