{
  "type": "Feature",
  "properties": {
    "addr:full":"Planetenlaan 95 Groningen Groningen 9742 HC",
    "addr:housenumber":"95",
    "addr:postcode":"9742 hc",
    "addr:street":"Planetenlaan",
    "iso:country":"NL",
    "sg:address":"Planetenlaan 95",
    "sg:city":"Groningen",
    "sg:orig_category":"Verzekeringen",
    "sg:phone":"+31 50 573 2411",
    "sg:postcode":"9742 HC",
    "sg:province":"Groningen",
    "wof:name":"Financieel Bemiddelings- En Adviesbureau",
    "wof:placetype":"venue"
},
  "geometry": {"coordinates":[6.537337,53.234962],"type":"Point"}
}