{
  "type": "Feature",
  "properties": {
    "addr:full":"Burg H Blokstr 22 Almkerk Noord-Brabant 4286 CC",
    "addr:housenumber":"22",
    "addr:postcode":"4286 cc",
    "addr:street":"Burg",
    "iso:country":"NL",
    "sg:address":"Burg H Blokstr 22",
    "sg:city":"Almkerk",
    "sg:orig_category":"Bejaarden - Verzorgingstehuizen",
    "sg:phone":"+31 183 401 177",
    "sg:postcode":"4286 CC",
    "sg:province":"Noord-Brabant",
    "wof:name":"Antonia",
    "wof:placetype":"venue"
},
  "geometry": {"coordinates":[4.95516,51.771572],"type":"Point"}
}