{
  "type": "Feature",
  "properties": {
    "addr:full":"Piazza Center 9 Gorinchem South Holland 4204 BN",
    "addr:housenumber":"9",
    "addr:postcode":"4204 bn",
    "addr:street":"Piazza Center",
    "iso:country":"NL",
    "sg:address":"Piazza Center 9",
    "sg:city":"Gorinchem",
    "sg:orig_category":"Kinderkleding",
    "sg:phone":"+31 183 635 125",
    "sg:postcode":"4204 BN",
    "sg:province":"South Holland",
    "wof:name":"Mickymo",
    "wof:placetype":"venue"
},
  "geometry": {"coordinates":[4.962821,51.836754],"type":"Point"}
}