{
  "type": "Feature",
  "properties": {
    "addr:full":"Gouderakstraat 45 Tilburg Noord-Brabant 5043 LM",
    "addr:housenumber":"45",
    "addr:postcode":"5043 lm",
    "addr:street":"Gouderakstraat",
    "iso:country":"NL",
    "sg:address":"Gouderakstraat 45",
    "sg:city":"Tilburg",
    "sg:orig_category":"Loodgieterswerk, Verwarming And Sanitaire Installaties",
    "sg:phone":"+31 13 570 3509",
    "sg:postcode":"5043 LM",
    "sg:province":"Noord-Brabant",
    "wof:name":"Peter De Groot",
    "wof:placetype":"venue"
},
  "geometry": {"coordinates":[5.011205,51.580803],"type":"Point"}
}