{
  "type": "Feature",
  "properties": {
    "addr:full":"V Beekstr 9 Landsmeer North Holland 1121 ND",
    "addr:housenumber":"9",
    "addr:postcode":"1121 nd",
    "addr:street":"Beekstr",
    "iso:country":"NL",
    "sg:address":"V Beekstr 9",
    "sg:city":"Landsmeer",
    "sg:orig_category":"Muziekdrukkerijen En -Uitgeverijen",
    "sg:phone":"+31 20 482 4027",
    "sg:postcode":"1121 ND",
    "sg:province":"North Holland",
    "wof:name":"All Music Publishing Bv",
    "wof:placetype":"venue"
},
  "geometry": {"coordinates":[4.91374,52.429974],"type":"Point"}
}