{
  "type": "Feature",
  "properties": {
    "addr:full":"Welgelegenlaan 21 Apeldoorn Gelderland 7321 AR",
    "addr:housenumber":"21",
    "addr:postcode":"7321",
    "addr:street":"Welgelegenlaan;Gelderland",
    "iso:country":"NL",
    "sg:address":"Welgelegenlaan 21",
    "sg:city":"Apeldoorn",
    "sg:orig_category":"Marktonderzoekbureaus",
    "sg:phone":"+31 55 366 7179",
    "sg:postcode":"7321 AR",
    "sg:province":"Gelderland",
    "wof:name":"Stap",
    "wof:placetype":"venue"
},
  "geometry": {"coordinates":[5.976466,52.214359],"type":"Point"}
}