{
  "type": "Feature",
  "properties": {
    "addr:full":"Sabotageln 58 Groningen Groningen 9727 CP",
    "addr:housenumber":"58",
    "addr:postcode":"9727 cp",
    "addr:street":"Sabotageln",
    "iso:country":"NL",
    "sg:address":"Sabotageln 58",
    "sg:city":"Groningen",
    "sg:orig_category":"Journalisten Freelance",
    "sg:phone":"+31 50 526 8251",
    "sg:postcode":"9727 CP",
    "sg:province":"Groningen",
    "wof:name":"Ebens, Ren?",
    "wof:placetype":"venue"
},
  "geometry": {"coordinates":[6.552921,53.209045],"type":"Point"}
}