{
  "type": "Feature",
  "properties": {
    "addr:full":"Oosterwoldsewg 14 Haulerwyk Friesland 8433 PV",
    "addr:housenumber":"14",
    "addr:postcode":"8433 pv",
    "addr:street":"Oosterwoldsewg",
    "iso:country":"NL",
    "sg:address":"Oosterwoldsewg 14",
    "sg:city":"Haulerwyk",
    "sg:orig_category":"Banken",
    "sg:phone":"+31 516 422 244",
    "sg:postcode":"8433 PV",
    "sg:province":"Friesland",
    "wof:name":"Regio Bank",
    "wof:placetype":"venue"
},
  "geometry": {"coordinates":[6.330632,53.065403],"type":"Point"}
}