{
  "type": "Feature",
  "properties": {
    "addr:full":"Wulpln 9 Ede Gld Gelderland 6713 BT",
    "addr:housenumber":"9",
    "addr:postcode":"6713 bt",
    "addr:street":"Wulpln;Gld Gelderland",
    "iso:country":"NL",
    "sg:address":"Wulpln 9",
    "sg:city":"Ede Gld",
    "sg:orig_category":"Scholen Voor Basisonderwijs",
    "sg:phone":"+31 318 618 592",
    "sg:postcode":"6713 BT",
    "sg:province":"Gelderland",
    "wof:name":"Groen Van Prinsterer, Cns",
    "wof:placetype":"venue"
},
  "geometry": {"coordinates":[5.667675,52.044979],"type":"Point"}
}