{
  "type": "Feature",
  "properties": {
    "addr:full":"Kampstr 23 Groessen Gelderland 6923 AJ",
    "addr:housenumber":"23",
    "addr:postcode":"6923 aj",
    "addr:street":"Kampstr;Gelderland",
    "iso:country":"NL",
    "sg:address":"Kampstr 23",
    "sg:city":"Groessen",
    "sg:orig_category":"Administratie- En Boekhoudkantoren",
    "sg:phone":"+31 316 331 704",
    "sg:postcode":"6923 AJ",
    "sg:province":"Gelderland",
    "wof:name":"Meijer",
    "wof:placetype":"venue"
},
  "geometry": {"coordinates":[6.027953,51.933018],"type":"Point"}
}