{
  "type": "Feature",
  "properties": {
    "addr:full":"Treubstraat 35 Rijswijk Zh Zuid-Holland 2288 EH",
    "addr:housenumber":"35",
    "addr:postcode":"zh;2288 eh",
    "addr:street":"Treubstraat",
    "iso:country":"NL",
    "sg:address":"Treubstraat 35",
    "sg:city":"Rijswijk Zh",
    "sg:orig_category":"Gebouwenafwerking, Renovaties And Reiniging",
    "sg:phone":"+31 70 399 8437",
    "sg:postcode":"2288 EH",
    "sg:province":"Zuid-Holland",
    "wof:name":"Heibra Bv",
    "wof:placetype":"venue"
},
  "geometry": {"coordinates":[4.327178,52.039429],"type":"Point"}
}