{
  "type": "Feature",
  "properties": {
    "iso:country":"NL",
    "sg:address":"Ramgatsewg 11D",
    "sg:city":"Raamsdonksveer",
    "sg:orig_category":"Kappersbenodigdheden",
    "sg:phone":"+31 162 522 885",
    "sg:postcode":"4941 VN",
    "sg:province":"Noord-Brabant",
    "wof:name":"Barbicos Bv",
    "wof:placetype":"venue"
},
  "geometry": {"coordinates":[4.873224,51.710957],"type":"Point"}
}