{
  "type": "Feature",
  "properties": {
    "addr:full":"Admiraalsborch 8 Houten Utrecht 3992 CP",
    "addr:housenumber":"8",
    "addr:postcode":"3992 cp",
    "addr:street":"Admiraalsborch",
    "iso:country":"NL",
    "sg:address":"Admiraalsborch 8",
    "sg:city":"Houten",
    "sg:orig_category":"Adviesbureaus Bedrijfsorganisatie",
    "sg:phone":"+31 30 634 3290",
    "sg:postcode":"3992 CP",
    "sg:province":"Utrecht",
    "wof:name":"I & Ho Bv",
    "wof:placetype":"venue"
},
  "geometry": {"coordinates":[5.148105,52.036442],"type":"Point"}
}