{
  "type": "Feature",
  "properties": {
    "addr:full":"Middachtenln 45 Almere NL. 1333 XT",
    "addr:housenumber":"45",
    "addr:postcode":"1333 xt",
    "addr:street":"Middachtenln;Nl.",
    "iso:country":"NL",
    "sg:address":"Middachtenln 45",
    "sg:city":"Almere",
    "sg:orig_category":"Adviesbureaus Bouwkunde",
    "sg:phone":"+31 36 530 4117",
    "sg:postcode":"1333 XT",
    "sg:province":"NL.",
    "sg:website":"http://www.bouwconsulting.nl",
    "wof:name":"Bargmann & Van Ek Bv",
    "wof:placetype":"venue"
},
  "geometry": {"coordinates":[5.269273,52.388138],"type":"Point"}
}