{
  "type": "Feature",
  "properties": {
    "addr:full":"Kwakerspln 10 Amsterdam Noord-Holland 1053 TZ",
    "addr:housenumber":"10",
    "addr:postcode":"1053 tz",
    "addr:street":"Kwakerspln",
    "iso:country":"NL",
    "sg:address":"Kwakerspln 10",
    "sg:city":"Amsterdam",
    "sg:orig_category":"Artsen - Huisartsen",
    "sg:phone":"+31 20 618 7071",
    "sg:postcode":"1053 TZ",
    "sg:province":"Noord-Holland",
    "wof:name":"Schoots-De Zeeuw, E C",
    "wof:placetype":"venue"
},
  "geometry": {"coordinates":[4.869979,52.368839],"type":"Point"}
}