{
  "type": "Feature",
  "properties": {
    "addr:full":"Kelbergen 16 Amsterdam Zuidoost North Holland 1104 LA",
    "addr:housenumber":"16",
    "addr:postcode":"1104 la",
    "addr:street":"Kelbergen",
    "iso:country":"NL",
    "sg:address":"Kelbergen 16",
    "sg:city":"Amsterdam Zuidoost",
    "sg:orig_category":"Kinderopvang Behalve Thuis",
    "sg:phone":"+31 20 698 1292",
    "sg:postcode":"1104 LA",
    "sg:province":"North Holland",
    "wof:name":"Kinderdagverblijf De Klapmuts",
    "wof:placetype":"venue"
},
  "geometry": {"coordinates":[4.973034,52.313099],"type":"Point"}
}