{
  "type": "Feature",
  "properties": {
    "addr:full":"Eindhovenseweg 27 Waalre Noord-Brabant 5582 HN",
    "addr:housenumber":"27",
    "addr:postcode":"5582 hn",
    "addr:street":"Eindhovenseweg",
    "iso:country":"NL",
    "sg:address":"Eindhovenseweg 27",
    "sg:city":"Waalre",
    "sg:orig_category":"Antiekzaken",
    "sg:phone":"+31 40 221 4802",
    "sg:postcode":"5582 HN",
    "sg:province":"Noord-Brabant",
    "wof:name":"Schafer Antiek Bv",
    "wof:placetype":"venue"
},
  "geometry": {"coordinates":[5.475911,51.394569],"type":"Point"}
}