{
  "type": "Feature",
  "properties": {
    "addr:full":"Poelgeest 13 Haarlem Noord-Holland 2036 HL",
    "addr:housenumber":"13",
    "addr:postcode":"2036 hl",
    "addr:street":"Poelgeest",
    "iso:country":"NL",
    "sg:address":"Poelgeest 13",
    "sg:city":"Haarlem",
    "sg:orig_category":"Agenturen En Commissiehandel",
    "sg:phone":"+31 23 535 5566",
    "sg:postcode":"2036 HL",
    "sg:province":"Noord-Holland",
    "sg:website":"HTTP://www.devriesengeene.nl",
    "wof:name":"Vries & Geene, De",
    "wof:placetype":"venue"
},
  "geometry": {"coordinates":[4.647049,52.350391],"type":"Point"}
}