{
  "type": "Feature",
  "properties": {
    "addr:full":"T V Poortvlietstr 107 S Gravenhage Zuid-Holland 2521 ZB",
    "addr:housenumber":"107;gravenhage",
    "addr:postcode":"2521 zb",
    "addr:street":"T;Poortvlietstr;S",
    "iso:country":"NL",
    "sg:address":"T V Poortvlietstr 107",
    "sg:city":"S Gravenhage",
    "sg:orig_category":"Onderhoudswerken",
    "sg:phone":"+31 70 395 2238",
    "sg:postcode":"2521 ZB",
    "sg:province":"Zuid-Holland",
    "wof:name":"Strik-Strida",
    "wof:placetype":"venue"
},
  "geometry": {"coordinates":[4.32071,52.062988],"type":"Point"}
}