{
  "type": "Feature",
  "properties": {
    "addr:full":"Westerkade 18 Utrecht 3511 HB",
    "addr:housenumber":"18",
    "addr:postcode":"3511 hb",
    "addr:street":"Westerkade",
    "iso:country":"NL",
    "sg:address":"Westerkade 18",
    "sg:city":"Utrecht",
    "sg:classifiers":[
        {
            "category":"Professional",
            "subcategory":"Computer Services",
            "type":"Services"
        }
    ],
    "sg:postcode":"3511 HB",
    "sg:tags":[
        "file-sharing",
        "search",
        "bittorrent",
        "tracker",
        "torrents"
    ],
    "sg:website":"http://www.mininova.org/",
    "wof:name":"Mininova",
    "wof:placetype":"venue"
},
  "geometry": {"coordinates":[5.1230002,52.0799794],"type":"Point"}
}