{
  "type": "Feature",
  "properties": {
    "addr:full":"Obrechtlaan 15 Rotterdam Zuid-Holland 3055 TJ",
    "addr:housenumber":"15",
    "addr:postcode":"3055 tj",
    "addr:street":"Obrechtlaan",
    "iso:country":"NL",
    "sg:address":"Obrechtlaan 15",
    "sg:city":"Rotterdam",
    "sg:orig_category":"Public Relationbureaus",
    "sg:phone":"+31 10 461 4003",
    "sg:postcode":"3055 TJ",
    "sg:province":"Zuid-Holland",
    "wof:name":"Dvlg",
    "wof:placetype":"venue"
},
  "geometry": {"coordinates":[4.506484,51.959766],"type":"Point"}
}