{
  "type": "Feature",
  "properties": {
    "addr:full":"Boschdykstr 15 S Hertogenbosch North Brabant 5211 VD",
    "addr:housenumber":"15",
    "addr:postcode":"5211 vd",
    "addr:street":"Boschdykstr;S Hertogenbosch",
    "iso:country":"NL",
    "sg:address":"Boschdykstr 15",
    "sg:city":"S Hertogenbosch",
    "sg:orig_category":"Banden",
    "sg:phone":"+31 73 614 5611",
    "sg:postcode":"5211 VD",
    "sg:province":"North Brabant",
    "sg:website":"http://www.kwik-fit.nl",
    "wof:name":"Kwik-Fit",
    "wof:placetype":"venue"
},
  "geometry": {"coordinates":[5.298702,51.69479],"type":"Point"}
}