{
  "type": "Feature",
  "properties": {
    "addr:full":"Muntplein 18 Nieuwegein Utrecht 3437 AN",
    "addr:housenumber":"18",
    "addr:postcode":"3437 an",
    "addr:street":"Muntplein",
    "iso:country":"NL",
    "sg:address":"Muntplein 18",
    "sg:city":"Nieuwegein",
    "sg:orig_category":"Opticiens",
    "sg:phone":"+31 30 604 4820",
    "sg:postcode":"3437 AN",
    "sg:province":"Utrecht",
    "wof:name":"Style Optiek Nieuwegein",
    "wof:placetype":"venue"
},
  "geometry": {"coordinates":[5.078042984,52.0410690308],"type":"Point"}
}