{
  "type": "Feature",
  "properties": {
    "iso:country":"NL",
    "sg:address":"Amazone 269",
    "sg:city":"Dordrecht",
    "sg:orig_category":"Schilders",
    "sg:phone":"+31 78 622 8540",
    "sg:postcode":"3315 WV",
    "sg:province":"Zuid-Holland",
    "wof:name":"Bani, Schildersbedrijf",
    "wof:placetype":"venue"
},
  "geometry": {"coordinates":[4.705262,51.809364],"type":"Point"}
}