{
  "type": "Feature",
  "properties": {
    "addr:full":"Postbus 35 Hoogvliet Rt South Holland 3190 AA",
    "addr:housenumber":"35",
    "addr:postcode":"3190 aa",
    "addr:street":"Postbus;Rt South",
    "iso:country":"NL",
    "sg:address":"Postbus 35",
    "sg:city":"Hoogvliet Rt",
    "sg:orig_category":"Folies",
    "sg:phone":"+31 800 0240585",
    "sg:postcode":"3190 AA",
    "sg:province":"South Holland",
    "wof:name":"Quality Window Films",
    "wof:placetype":"venue"
},
  "geometry": {"coordinates":[4.35827,51.863811],"type":"Point"}
}