{
  "type": "Feature",
  "properties": {
    "addr:full":"Hoogeindsestr 4 Tiel Gelderland 4001 AB",
    "addr:housenumber":"4",
    "addr:postcode":"4001 ab",
    "addr:street":"Hoogeindsestr;Gelderland",
    "iso:country":"NL",
    "sg:address":"Hoogeindsestr 4",
    "sg:city":"Tiel",
    "sg:orig_category":"Kappers",
    "sg:phone":"+31 344 633 661",
    "sg:postcode":"4001 AB",
    "sg:province":"Gelderland",
    "wof:name":"Sevinc",
    "wof:placetype":"venue"
},
  "geometry": {"coordinates":[5.432586,51.888248],"type":"Point"}
}