{
  "type": "Feature",
  "properties": {
    "addr:full":"Dr H T S Jacobln 36 Utrecht Utrecht 3571 BM",
    "addr:housenumber":"36",
    "addr:postcode":"3571 bm",
    "addr:street":"Dr;T",
    "iso:country":"NL",
    "sg:address":"Dr H T S Jacobln 36",
    "sg:city":"Utrecht",
    "sg:orig_category":"Journalisten Freelance",
    "sg:phone":"+31 30 273 0229",
    "sg:postcode":"3571 BM",
    "sg:province":"Utrecht",
    "wof:name":"Schilling, Govert",
    "wof:placetype":"venue"
},
  "geometry": {"coordinates":[5.123716,52.106941],"type":"Point"}
}