{
  "type": "Feature",
  "properties": {
    "addr:full":"Nieuwe Passage 29 Schiedam Zuid-Holland 3111 EG",
    "addr:housenumber":"29",
    "addr:postcode":"3111 eg",
    "addr:street":"Nieuwe Passage",
    "iso:country":"NL",
    "sg:address":"Nieuwe Passage 29",
    "sg:city":"Schiedam",
    "sg:orig_category":"Opticiens",
    "sg:phone":"+31 10 473 5868",
    "sg:postcode":"3111 EG",
    "sg:province":"Zuid-Holland",
    "wof:name":"Hans Anders Opticiens",
    "wof:placetype":"venue"
},
  "geometry": {"coordinates":[4.3981599808,51.91847229],"type":"Point"}
}