{
  "type": "Feature",
  "properties": {
    "iso:country":"NL",
    "sg:address":"Sophiastraat 162",
    "sg:city":"Rotterdam",
    "sg:orig_category":"Glaszetten",
    "sg:phone":"+31 10 452 1364",
    "sg:postcode":"3061 LX",
    "sg:province":"Zuid-Holland",
    "wof:name":"Glashandel Centraal J F Hommes",
    "wof:placetype":"venue"
},
  "geometry": {"coordinates":[4.499533,51.929115],"type":"Point"}
}