{
  "type": "Feature",
  "properties": {
    "addr:full":"Beethovenstr 29 Amsterdam North Holland 1077 HM",
    "addr:housenumber":"29",
    "addr:postcode":"1077 hm",
    "addr:street":"Beethovenstr",
    "iso:country":"NL",
    "sg:address":"Beethovenstr 29",
    "sg:city":"Amsterdam",
    "sg:classifiers":[
        {
            "category":"Farming",
            "subcategory":"Fish & Marine Products",
            "type":"Manufacturing & Wholesale Goods"
        }
    ],
    "sg:phone":"+31 20 662 8071",
    "sg:postcode":"1077 HM",
    "sg:province":"North Holland",
    "sg:tags":[
        "vi"
    ],
    "wof:name":"Centrale Vishandel",
    "wof:placetype":"venue"
},
  "geometry": {"coordinates":[4.877562,52.348869],"type":"Point"}
}