{
  "type": "Feature",
  "properties": {
    "addr:full":"Grosthuizen 23 Huizen Noord-Holland 1633 EL",
    "addr:housenumber":"23",
    "addr:postcode":"1633 el",
    "addr:street":"Grosthuizen",
    "iso:country":"NL",
    "sg:address":"Grosthuizen 23",
    "sg:city":"Huizen",
    "sg:orig_category":"Bedrijfsinventaris Gh",
    "sg:phone":"+31 229 543 626",
    "sg:postcode":"1633 EL",
    "sg:province":"Noord-Holland",
    "wof:name":"V. Rooyen Etalages",
    "wof:placetype":"venue"
},
  "geometry": {"coordinates":[4.950444,52.616669],"type":"Point"}
}