{
  "type": "Feature",
  "properties": {
    "iso:country":"NL",
    "sg:address":"Lopikersingel 11",
    "sg:city":"Schoonhoven",
    "sg:orig_category":"Krantenuitgeverijen",
    "sg:phone":"+31 182 389 000",
    "sg:postcode":"2871 AP",
    "sg:province":"South Holland",
    "wof:name":"Uitgeversgroep Van Zwienen",
    "wof:placetype":"venue"
},
  "geometry": {"coordinates":[4.85691,51.94672],"type":"Point"}
}