{
  "type": "Feature",
  "properties": {
    "addr:full":"Schoolstr 32 Kloosterhaar Overijssel 7694 AX",
    "addr:housenumber":"32",
    "addr:postcode":"7694 ax",
    "addr:street":"Schoolstr",
    "iso:country":"NL",
    "sg:address":"Schoolstr 32",
    "sg:city":"Kloosterhaar",
    "sg:orig_category":"Scholen Voor Basisonderwijs",
    "sg:phone":"+31 523 241 473",
    "sg:postcode":"7694 AX",
    "sg:province":"Overijssel",
    "wof:name":"Cantecleer Openb",
    "wof:placetype":"venue"
},
  "geometry": {"coordinates":[6.66809,52.495918],"type":"Point"}
}