{
  "type": "Feature",
  "properties": {
    "addr:full":"Schalk Burgerstraat 26 Leeuwarden Provincie Friesland 8917 BR",
    "addr:housenumber":"26",
    "addr:postcode":"8917 br",
    "addr:street":"Schalk Burgerstraat;Provincie Friesland",
    "iso:country":"NL",
    "sg:address":"Schalk Burgerstraat 26",
    "sg:city":"Leeuwarden",
    "sg:orig_category":"Bloemen And Planten",
    "sg:phone":"+31 58 212 0649",
    "sg:postcode":"8917 BR",
    "sg:province":"Provincie Friesland",
    "wof:name":"R Dijkstra",
    "wof:placetype":"venue"
},
  "geometry": {"coordinates":[5.791354,53.206585],"type":"Point"}
}