{
  "type": "Feature",
  "properties": {
    "addr:full":"Fluitekruidlaan 17 Scherpenzeel Gld Gelderland 3925 SB",
    "addr:housenumber":"17",
    "addr:postcode":"3925 sb",
    "addr:street":"Fluitekruidlaan;Gld Gelderland",
    "iso:country":"NL",
    "sg:address":"Fluitekruidlaan 17",
    "sg:city":"Scherpenzeel Gld",
    "sg:orig_category":"Artsen And Specialisten",
    "sg:phone":"+31 33 277 3488",
    "sg:postcode":"3925 SB",
    "sg:province":"Gelderland",
    "wof:name":"Drs. I.M. Van Schothorst",
    "wof:placetype":"venue"
},
  "geometry": {"coordinates":[5.494502,52.075546],"type":"Point"}
}