{
  "type": "Feature",
  "properties": {
    "addr:full":"Wilhelminastraat 2 Groot Ammers Zuid-Holland 2964 CP",
    "addr:housenumber":"2",
    "addr:postcode":"2964 cp",
    "addr:street":"Wilhelminastraat;Groot Ammers",
    "iso:country":"NL",
    "sg:address":"Wilhelminastraat 2",
    "sg:city":"Groot Ammers",
    "sg:orig_category":"Huishoudapparatuur, Televisies And Radio'S",
    "sg:phone":"+31 184 661 377",
    "sg:postcode":"2964 CP",
    "sg:province":"Zuid-Holland",
    "wof:name":"Aanen Elektro",
    "wof:placetype":"venue"
},
  "geometry": {"coordinates":[4.818472,51.923248],"type":"Point"}
}