{
  "type": "Feature",
  "properties": {
    "iso:country":"NL",
    "sg:address":"Havenstr 106",
    "sg:city":"Rotterdam",
    "sg:orig_category":"Biljartzalen",
    "sg:phone":"+31 10 477 2251",
    "sg:postcode":"3024 TJ",
    "sg:province":"Zuid-Holland",
    "wof:name":"Windhoek, De",
    "wof:placetype":"venue"
},
  "geometry": {"coordinates":[4.45117,51.90733],"type":"Point"}
}