{
  "type": "Feature",
  "properties": {
    "addr:full":"Hoevestr 25A Rotterdam South Holland 3033 GB",
    "addr:housenumber":"25a",
    "addr:postcode":"3033 gb",
    "addr:street":"Hoevestr",
    "iso:country":"NL",
    "sg:address":"Hoevestr 25A",
    "sg:city":"Rotterdam",
    "sg:orig_category":"Organisatiebureaus",
    "sg:phone":"+31 10 467 1105",
    "sg:postcode":"3033 GB",
    "sg:province":"South Holland",
    "sg:website":"http://www.d-tails.nl",
    "wof:name":"D.Tails",
    "wof:placetype":"venue"
},
  "geometry": {"coordinates":[4.4660959244,51.9275093079],"type":"Point"}
}