{
  "type": "Feature",
  "properties": {
    "addr:full":"Rietdekkerstr 5 Ridderkerk Zuid-Holland 2984 BM",
    "addr:housenumber":"5",
    "addr:postcode":"2984 bm",
    "addr:street":"Rietdekkerstr",
    "iso:country":"NL",
    "sg:address":"Rietdekkerstr 5",
    "sg:city":"Ridderkerk",
    "sg:orig_category":"Keukens",
    "sg:phone":"+31 180 411 300",
    "sg:postcode":"2984 BM",
    "sg:province":"Zuid-Holland",
    "wof:name":"Kom Design Bv",
    "wof:placetype":"venue"
},
  "geometry": {"coordinates":[4.617645,51.876686],"type":"Point"}
}