{
  "type": "Feature",
  "properties": {
    "addr:full":"Einsteinstraat 6 Zevenaar Gelderland 6902 PB",
    "addr:housenumber":"6",
    "addr:postcode":"6902 pb",
    "addr:street":"Einsteinstraat",
    "iso:country":"NL",
    "sg:address":"Einsteinstraat 6",
    "sg:city":"Zevenaar",
    "sg:orig_category":"Fitnesscentra",
    "sg:phone":"+31 316 341 560",
    "sg:postcode":"6902 PB",
    "sg:province":"Gelderland",
    "wof:name":"Sportsworld Edcor",
    "wof:placetype":"venue"
},
  "geometry": {"coordinates":[6.09571,51.924629],"type":"Point"}
}