{
  "type": "Feature",
  "properties": {
    "addr:full":"Mimosastraat 31 Hoogeveen Drenthe 7906 PJ",
    "addr:housenumber":"31",
    "addr:postcode":"7906 pj",
    "addr:street":"Mimosastraat",
    "iso:country":"NL",
    "sg:address":"Mimosastraat 31",
    "sg:city":"Hoogeveen",
    "sg:classifiers":[
        {
            "category":"Food & Beverages",
            "subcategory":"Fruits & Vegetables",
            "type":"Retail Goods"
        }
    ],
    "sg:phone":"+31 528 267 583",
    "sg:postcode":"7906 PJ",
    "sg:province":"Drenthe",
    "sg:tags":[
        "groenten"
    ],
    "wof:name":"R Prijs Rzn",
    "wof:placetype":"venue"
},
  "geometry": {"coordinates":[6.488338,52.716629],"type":"Point"}
}