{
  "type": "Feature",
  "properties": {
    "addr:full":"Prinsessegr 33 S Gravenhage South Holland 2514 AP",
    "addr:housenumber":"33",
    "addr:postcode":"2514 ap",
    "addr:street":"Prinsessegr;S Gravenhage",
    "iso:country":"NL",
    "sg:address":"Prinsessegr 33",
    "sg:city":"S Gravenhage",
    "sg:classifiers":[
        {
            "category":"Professional",
            "subcategory":"Accounting & Tax Preparation",
            "type":"Services"
        }
    ],
    "sg:phone":"+31 70 346 9442",
    "sg:postcode":"2514 AP",
    "sg:province":"South Holland",
    "sg:tags":[
        "accountant",
        "en",
        "-kantoren",
        "register-"
    ],
    "sg:website":"http://www.svde.nl",
    "wof:name":"Sprangers Van Den Ende",
    "wof:placetype":"venue"
},
  "geometry": {"coordinates":[4.30935,52.084148],"type":"Point"}
}