{
  "type": "Feature",
  "properties": {
    "addr:full":"Keiwg 44 Koudekerke Zeeland 4371 MX",
    "addr:housenumber":"44",
    "addr:postcode":"4371 mx",
    "addr:street":"Keiwg",
    "iso:country":"NL",
    "sg:address":"Keiwg 44",
    "sg:city":"Koudekerke",
    "sg:orig_category":"Autorijscholen",
    "sg:phone":"+31 118 552 752",
    "sg:postcode":"4371 MX",
    "sg:province":"Zeeland",
    "wof:name":"Oranje",
    "wof:placetype":"venue"
},
  "geometry": {"coordinates":[3.549612,51.478809],"type":"Point"}
}