{
  "type": "Feature",
  "properties": {
    "addr:full":"Binnenhof 47 Almelo NL.08 7608 KH",
    "addr:housenumber":"47;nl.08",
    "addr:postcode":"7608 kh",
    "addr:street":"Binnenhof",
    "iso:country":"NL",
    "sg:address":"Binnenhof 47",
    "sg:city":"Almelo",
    "sg:classifiers":[
        {
            "category":"Fast Food",
            "type":"Food & Drink"
        }
    ],
    "sg:phone":"+31 546 871 719",
    "sg:postcode":"7608 KH",
    "sg:province":"NL.08",
    "sg:tags":[
        "afhaal",
        "restaurant"
    ],
    "wof:name":"Restaurant Nice Gathering",
    "wof:placetype":"venue"
},
  "geometry": {"coordinates":[6.677821,52.379215],"type":"Point"}
}