{
  "type": "Feature",
  "properties": {
    "iso:country":"NL",
    "sg:address":"Kenaupk 28",
    "sg:city":"Haarlem",
    "sg:orig_category":"Psychotherapeuten",
    "sg:phone":"+31 23 542 2479",
    "sg:postcode":"2011 MT",
    "sg:province":"North Holland",
    "wof:name":"Henny Verhagen Centrum",
    "wof:placetype":"venue"
},
  "geometry": {"coordinates":[4.63373,52.385921],"type":"Point"}
}