{
  "type": "Feature",
  "properties": {
    "addr:full":"Pretoriusstraat 42 Ermelo Gelderland 3851 ZM",
    "addr:housenumber":"42",
    "addr:postcode":"3851 zm",
    "addr:street":"Pretoriusstraat;Gelderland",
    "iso:country":"NL",
    "sg:address":"Pretoriusstraat 42",
    "sg:city":"Ermelo",
    "sg:orig_category":"Alternatieve Geneeskunde",
    "sg:phone":"+31 341 556 457",
    "sg:postcode":"3851 ZM",
    "sg:province":"Gelderland",
    "wof:name":"A.J. Boers",
    "wof:placetype":"venue"
},
  "geometry": {"coordinates":[5.614367,52.291283],"type":"Point"}
}