{
  "type": "Feature",
  "properties": {
    "addr:full":"Burg De Zeeuwstraat 294 Ridderkerk Zuid-Holland 2981 AJ",
    "addr:housenumber":"294",
    "addr:postcode":"2981 aj",
    "addr:street":"De Zeeuwstraat",
    "iso:country":"NL",
    "sg:address":"Burg De Zeeuwstraat 294",
    "sg:city":"Ridderkerk",
    "sg:classifiers":[
        {
            "category":"Education",
            "subcategory":"Preschool",
            "type":"Public Place"
        }
    ],
    "sg:phone":"+31 180 499 010",
    "sg:postcode":"2981 AJ",
    "sg:province":"Zuid-Holland",
    "sg:tags":[
        "kleuteronderwijs",
        "basis-"
    ],
    "wof:name":"De Piramide Openbare Basisschool",
    "wof:placetype":"venue"
},
  "geometry": {"coordinates":[4.598051,51.871727],"type":"Point"}
}