{
  "type": "Feature",
  "properties": {
    "addr:full":"Damsterdiep 60 Groningen Groningen 9713 EJ",
    "addr:housenumber":"60",
    "addr:postcode":"9713 ej",
    "addr:street":"Damsterdiep",
    "iso:country":"NL",
    "sg:address":"Damsterdiep 60",
    "sg:city":"Groningen",
    "sg:orig_category":"Wasserettes And Stomerijen",
    "sg:phone":"+31 50 313 3825",
    "sg:postcode":"9713 EJ",
    "sg:province":"Groningen",
    "wof:name":"Gerner Stomen",
    "wof:placetype":"venue"
},
  "geometry": {"coordinates":[6.5785851479,53.2186737061],"type":"Point"}
}