{
  "type": "Feature",
  "properties": {
    "addr:full":"Stationsstr 94 Putten Gelderland 3881 AG",
    "addr:housenumber":"94",
    "addr:postcode":"3881",
    "addr:street":"Stationsstr;Gelderland",
    "iso:country":"NL",
    "sg:address":"Stationsstr 94",
    "sg:city":"Putten",
    "sg:orig_category":"Adviesbureaus Bedrijfsorganisatie",
    "sg:phone":"+31 341 353 211",
    "sg:postcode":"3881 AG",
    "sg:province":"Gelderland",
    "wof:name":"Poorter En Partners",
    "wof:placetype":"venue"
},
  "geometry": {"coordinates":[5.582313,52.264496],"type":"Point"}
}