{
  "type": "Feature",
  "properties": {
    "addr:full":"Margrietstr 17 Dreumel Gelderland 6621 BV",
    "addr:housenumber":"17",
    "addr:postcode":"6621 bv",
    "addr:street":"Margrietstr;Gelderland",
    "iso:country":"NL",
    "sg:address":"Margrietstr 17",
    "sg:city":"Dreumel",
    "sg:orig_category":"Scheidingswanden - Fabrieken",
    "sg:phone":"+31 487 572 698",
    "sg:postcode":"6621 BV",
    "sg:province":"Gelderland",
    "wof:name":"Da Montage",
    "wof:placetype":"venue"
},
  "geometry": {"coordinates":[5.439146,51.851482],"type":"Point"}
}