{
  "type": "Feature",
  "properties": {
    "addr:full":"Molenvliet 95 Zwyndrecht Zuid-Holland 3335 LH",
    "addr:housenumber":"95",
    "addr:postcode":"3335 lh",
    "addr:street":"Molenvliet",
    "iso:country":"NL",
    "sg:address":"Molenvliet 95",
    "sg:city":"Zwyndrecht",
    "sg:orig_category":"Discotheken",
    "sg:phone":"+31 78 610 1949",
    "sg:postcode":"3335 LH",
    "sg:province":"Zuid-Holland",
    "wof:name":"The Blue Lagoon",
    "wof:placetype":"venue"
},
  "geometry": {"coordinates":[4.60712,51.827839],"type":"Point"}
}