{
  "type": "Feature",
  "properties": {
    "addr:full":"Steentilstraat 2 Groningen Groningen 9711 GM",
    "addr:housenumber":"2",
    "addr:postcode":"9711 gm",
    "addr:street":"Steentilstraat",
    "iso:country":"NL",
    "sg:address":"Steentilstraat 2",
    "sg:city":"Groningen",
    "sg:orig_category":"Schoenen",
    "sg:phone":"+31 50 313 7264",
    "sg:postcode":"9711 GM",
    "sg:province":"Groningen",
    "wof:name":"Happy Walker Schoenen",
    "wof:placetype":"venue"
},
  "geometry": {"coordinates":[6.571408,53.216118],"type":"Point"}
}