{
  "type": "Feature",
  "properties": {
    "addr:full":"Hessenwg 196B Achterveld Utrecht 3791 PN",
    "addr:housenumber":"196b",
    "addr:postcode":"3791 pn",
    "addr:street":"Achterveld",
    "iso:country":"NL",
    "sg:address":"Hessenwg 196B",
    "sg:city":"Achterveld",
    "sg:orig_category":"Kappers",
    "sg:phone":"+31 342 451 850",
    "sg:postcode":"3791 PN",
    "sg:province":"Utrecht",
    "wof:name":"Marieke",
    "wof:placetype":"venue"
},
  "geometry": {"coordinates":[5.494551,52.135155],"type":"Point"}
}