{
  "type": "Feature",
  "properties": {
    "iso:country":"NL",
    "sg:address":"Anjerstr 21",
    "sg:city":"Ter Aar",
    "sg:orig_category":"Projectontwikkeling",
    "sg:phone":"+31 172 603 416",
    "sg:postcode":"2461 TE",
    "sg:province":"Zuid-Holland",
    "sg:website":"http://www.trionisis.nl",
    "wof:name":"Trionisis Bv",
    "wof:placetype":"venue"
},
  "geometry": {"coordinates":[4.724917,52.184029],"type":"Point"}
}