{
  "type": "Feature",
  "properties": {
    "iso:country":"NL",
    "sg:address":"Postbus 5419",
    "sg:city":"Maasdam",
    "sg:orig_category":"Fotoreportages",
    "sg:phone":"+31 78 676 3533",
    "sg:postcode":"3299 ZG",
    "sg:province":"South Holland",
    "wof:name":"Multivision",
    "wof:placetype":"venue"
},
  "geometry": {"coordinates":[4.55633,51.787514],"type":"Point"}
}