{
  "type": "Feature",
  "properties": {
    "addr:full":"S Stevinstr 15 Oud Beyerland Zuid-Holland 3261 MG",
    "addr:housenumber":"15",
    "addr:postcode":"3261 mg",
    "addr:street":"Oud Beyerland",
    "iso:country":"NL",
    "sg:address":"S Stevinstr 15",
    "sg:city":"Oud Beyerland",
    "sg:orig_category":"Postorderbedrijven",
    "sg:phone":"+31 186 615 267",
    "sg:postcode":"3261 MG",
    "sg:province":"Zuid-Holland",
    "wof:name":"Precare",
    "wof:placetype":"venue"
},
  "geometry": {"coordinates":[4.43262,51.816826],"type":"Point"}
}