{
  "type": "Feature",
  "properties": {
    "iso:country":"NL",
    "sg:address":"Stuijvesantstraat 65",
    "sg:city":"Haarlem",
    "sg:orig_category":"Bloemen And Planten",
    "sg:phone":"+31 23 525 0260",
    "sg:postcode":"2023 KL",
    "sg:province":"North Holland",
    "wof:name":"Bloemsierkunst Fleurella",
    "wof:placetype":"venue"
},
  "geometry": {"coordinates":[4.629204,52.401299],"type":"Point"}
}