{
  "type": "Feature",
  "properties": {
    "iso:country":"NL",
    "sg:address":"Ambachtstraat 14",
    "sg:city":"Almelo",
    "sg:orig_category":"Werving And Selectie Van Tijdelijk Personeel And Uitzendkantoren",
    "sg:phone":"+31 546 826 980",
    "sg:postcode":"7609 RA",
    "sg:province":"NL.08",
    "wof:name":"Keytech Bv",
    "wof:placetype":"venue"
},
  "geometry": {"coordinates":[6.6543340683,52.3334312439],"type":"Point"}
}