{
  "type": "Feature",
  "properties": {
    "addr:full":"Dieselstraat 68 Schiedam Zuid-Holland 3112 KC",
    "addr:housenumber":"68",
    "addr:postcode":"3112 kc",
    "addr:street":"Dieselstraat",
    "iso:country":"NL",
    "sg:address":"Dieselstraat 68",
    "sg:city":"Schiedam",
    "sg:orig_category":"Loodgieterswerk, Verwarming And Sanitaire Installaties",
    "sg:phone":"+31 10 437 5260",
    "sg:postcode":"3112 KC",
    "sg:province":"Zuid-Holland",
    "wof:name":"R. Broekhuizen",
    "wof:placetype":"venue"
},
  "geometry": {"coordinates":[4.415262,51.919083],"type":"Point"}
}