{
  "type": "Feature",
  "properties": {
    "addr:full":"Luteynmarke 16 Zwolle NL.08 8016 NA",
    "addr:housenumber":"16",
    "addr:postcode":"8016 na",
    "addr:street":"Luteynmarke",
    "iso:country":"NL",
    "sg:address":"Luteynmarke 16",
    "sg:city":"Zwolle",
    "sg:orig_category":"Marktonderzoekbureaus",
    "sg:phone":"+31 38 460 4700",
    "sg:postcode":"8016 NA",
    "sg:province":"NL.08",
    "wof:name":"Hanny Graatsma",
    "wof:placetype":"venue"
},
  "geometry": {"coordinates":[6.102943,52.476048],"type":"Point"}
}