{
  "type": "Feature",
  "properties": {
    "addr:full":"Korvelseweg 26A Tilburg Noord-Brabant 5025 JH",
    "addr:housenumber":"26a",
    "addr:postcode":"5025 jh",
    "addr:street":"Korvelseweg",
    "iso:country":"NL",
    "sg:address":"Korvelseweg 26A",
    "sg:city":"Tilburg",
    "sg:orig_category":"Wasserettes And Stomerijen",
    "sg:phone":"+31 13 542 6424",
    "sg:postcode":"5025 JH",
    "sg:province":"Noord-Brabant",
    "wof:name":"Stomerij Buddemeyer",
    "wof:placetype":"venue"
},
  "geometry": {"coordinates":[5.0782608986,51.5526313782],"type":"Point"}
}