{
  "type": "Feature",
  "properties": {
    "addr:full":"Portlandse Baan 2 Barendrecht Zuid-Holland 2993 SB",
    "addr:housenumber":"2",
    "addr:postcode":"2993 sb",
    "addr:street":"Portlandse Baan",
    "iso:country":"NL",
    "sg:address":"Portlandse Baan 2",
    "sg:city":"Barendrecht",
    "sg:orig_category":"Banken And Kredietinstellingen",
    "sg:phone":"+31 180 613 202",
    "sg:postcode":"2993 SB",
    "sg:province":"Zuid-Holland",
    "wof:name":"Abn Amro",
    "wof:placetype":"venue"
},
  "geometry": {"coordinates":[4.49796,51.848343],"type":"Point"}
}