{
  "type": "Feature",
  "properties": {
    "iso:country":"NL",
    "sg:address":"Rembrandtgalerij 97",
    "sg:city":"Roosendaal",
    "sg:classifiers":[
        {
            "category":"Fast Food",
            "type":"Food & Drink"
        }
    ],
    "sg:phone":"+31 165 542 755",
    "sg:postcode":"4703 GX",
    "sg:province":"North Brabant",
    "sg:tags":[
        "afhaal",
        "restaurant"
    ],
    "wof:name":"Chinees Indisch Restaurant Peking",
    "wof:placetype":"venue"
},
  "geometry": {"coordinates":[4.443201,51.534981],"type":"Point"}
}