{
  "type": "Feature",
  "properties": {
    "addr:full":"Ommershofseln 4 Velp Gld Gelderland 6881 RT",
    "addr:housenumber":"4;6881",
    "addr:postcode":"rt",
    "addr:street":"Ommershofseln;Gld Gelderland",
    "iso:country":"NL",
    "sg:address":"Ommershofseln 4",
    "sg:city":"Velp Gld",
    "sg:orig_category":"Adviesbureaus Bouwkunde",
    "sg:phone":"+31 26 362 8422",
    "sg:postcode":"6881 RT",
    "sg:province":"Gelderland",
    "wof:name":"Vgom",
    "wof:placetype":"venue"
},
  "geometry": {"coordinates":[5.966519,51.994625],"type":"Point"}
}