{
  "type": "Feature",
  "properties": {
    "iso:country":"NL",
    "sg:address":"Soesterweg 41",
    "sg:city":"Amersfoort",
    "sg:orig_category":"Loodgieterswerk, Verwarming And Sanitaire Installaties",
    "sg:phone":"+31 33 461 6014",
    "sg:postcode":"3812 AB",
    "sg:province":"Utrecht",
    "wof:name":"H. Veer Loodgieters- Electrotechnisch Be",
    "wof:placetype":"venue"
},
  "geometry": {"coordinates":[5.376346,52.155369],"type":"Point"}
}