{
  "type": "Feature",
  "properties": {
    "addr:full":"Wolweg 45 Stroe Gelderland 3776 LN",
    "addr:housenumber":"45",
    "addr:postcode":"3776 ln",
    "addr:street":"Wolweg;Gelderland",
    "iso:country":"NL",
    "sg:address":"Wolweg 45",
    "sg:city":"Stroe",
    "sg:orig_category":"Autokeuringen",
    "sg:phone":"+31 342 442 360",
    "sg:postcode":"3776 LN",
    "sg:province":"Gelderland",
    "wof:name":"Vof Autobedrijf Johan Schouten",
    "wof:placetype":"venue"
},
  "geometry": {"coordinates":[5.692122,52.186752],"type":"Point"}
}