{
  "type": "Feature",
  "properties": {
    "iso:country":"NL",
    "sg:address":"Industriestr 31D",
    "sg:city":"Sittard",
    "sg:orig_category":"Keuringsdiensten",
    "sg:phone":"+31 46 436 1694",
    "sg:postcode":"6135 KG",
    "sg:province":"Limburg",
    "wof:name":"Herton Keuringen En Reparaties",
    "wof:placetype":"venue"
},
  "geometry": {"coordinates":[5.844953,51.002235],"type":"Point"}
}