{
  "type": "Feature",
  "properties": {
    "iso:country":"NL",
    "sg:address":"J P Grootstr 15",
    "sg:city":"Purmerend",
    "sg:orig_category":"Kinderopvang",
    "sg:phone":"+31 299 421 203",
    "sg:postcode":"1443 LV",
    "sg:province":"Noord-Holland",
    "wof:name":"Blauwe Ballon, De",
    "wof:placetype":"venue"
},
  "geometry": {"coordinates":[4.969557,52.506096],"type":"Point"}
}