{
  "type": "Feature",
  "properties": {
    "addr:full":"Kerkstr 6 Burgh Haamstede Zeeland 4328 LJ",
    "addr:housenumber":"6",
    "addr:postcode":"4328 lj",
    "addr:street":"Kerkstr;Haamstede",
    "iso:country":"NL",
    "sg:address":"Kerkstr 6",
    "sg:city":"Burgh Haamstede",
    "sg:orig_category":"Schilders",
    "sg:phone":"+31 111 651 506",
    "sg:postcode":"4328 LJ",
    "sg:province":"Zeeland",
    "wof:name":"Meij En Zn, Fa J De",
    "wof:placetype":"venue"
},
  "geometry": {"coordinates":[3.734715,51.691723],"type":"Point"}
}