{
  "type": "Feature",
  "properties": {
    "iso:country":"NL",
    "sg:address":"Langstr 34",
    "sg:city":"Zoutelande",
    "sg:orig_category":"Zoetwaren - Winkels",
    "sg:phone":"+31 6 23178814",
    "sg:postcode":"4374 AP",
    "sg:province":"Zeeland",
    "wof:name":"Spek'S Place",
    "wof:placetype":"venue"
},
  "geometry": {"coordinates":[3.484862,51.499828],"type":"Point"}
}