{
  "type": "Feature",
  "properties": {
    "addr:full":"Hoofdwg 90 Harkstede Groningen 9617 AJ",
    "addr:housenumber":"90",
    "addr:postcode":"9617 aj",
    "addr:street":"Hoofdwg",
    "iso:country":"NL",
    "sg:address":"Hoofdwg 90",
    "sg:city":"Harkstede",
    "sg:orig_category":"Verzekeringen - Verzekeringskantoren",
    "sg:phone":"+31 50 404 1671",
    "sg:postcode":"9617 AJ",
    "sg:province":"Groningen",
    "wof:name":"Avdl",
    "wof:placetype":"venue"
},
  "geometry": {"coordinates":[6.693426,53.212337],"type":"Point"}
}