{
  "type": "Feature",
  "properties": {
    "iso:country":"NL",
    "sg:address":"Hoofdwg 90",
    "sg:city":"Harkstede",
    "sg:orig_category":"Verzekeringen - Verzekeringskantoren",
    "sg:phone":"+31 50 404 1671",
    "sg:postcode":"9617 AJ",
    "sg:province":"Groningen",
    "wof:name":"Avdl",
    "wof:placetype":"venue"
},
  "geometry": {"coordinates":[6.693426,53.212337],"type":"Point"}
}