{
  "type": "Feature",
  "properties": {
    "iso:country":"NL",
    "sg:address":"Vd Wildenbergstr 12",
    "sg:city":"Gilze",
    "sg:orig_category":"Autorijscholen",
    "sg:phone":"+31 161 451 613",
    "sg:postcode":"5126 TM",
    "sg:province":"Noord-Brabant",
    "wof:name":"Vogel",
    "wof:placetype":"venue"
},
  "geometry": {"coordinates":[4.94263,51.549286],"type":"Point"}
}