{
  "type": "Feature",
  "properties": {
    "addr:full":"Rogstr 20 Grave Oklahoma 5361 GR",
    "addr:housenumber":"20",
    "addr:postcode":"5361",
    "addr:street":"Rogstr;Oklahoma",
    "iso:country":"NL",
    "sg:address":"Rogstr 20",
    "sg:city":"Grave",
    "sg:orig_category":"Opticiens",
    "sg:phone":"+31 486 420 665",
    "sg:postcode":"5361 GR",
    "sg:province":"Oklahoma",
    "wof:name":"Giesbers Kompleet Optiek",
    "wof:placetype":"venue"
},
  "geometry": {"coordinates":[-94.6178359985,36.4973373413],"type":"Point"}
}