{
  "type": "Feature",
  "properties": {
    "iso:country":"NL",
    "sg:address":"Brede Haven 35",
    "sg:city":"S Hertogenbosch",
    "sg:orig_category":"Juridische Adviseurs",
    "sg:phone":"+31 73 614 9331",
    "sg:postcode":"5211 TM",
    "sg:province":"North Brabant",
    "wof:name":"Meijlink",
    "wof:placetype":"venue"
},
  "geometry": {"coordinates":[5.299672,51.692608],"type":"Point"}
}