{
  "type": "Feature",
  "properties": {
    "addr:full":"Uddelstraat 81 Den Haag South Holland 2573 VC",
    "addr:housenumber":"81",
    "addr:postcode":"2573 vc",
    "addr:street":"Uddelstraat",
    "iso:country":"NL",
    "sg:address":"Uddelstraat 81",
    "sg:city":"Den Haag",
    "sg:orig_category":"Huisdierenfokkers",
    "sg:phone":"+31 70 388 9262",
    "sg:postcode":"2573 VC",
    "sg:province":"South Holland",
    "wof:name":"A.M. Den Buurman Van Wees",
    "wof:placetype":"venue"
},
  "geometry": {"coordinates":[4.285893,52.062328],"type":"Point"}
}