{
  "type": "Feature",
  "properties": {
    "addr:full":"De Middend 72 Bovenkarspel Noord-Holland 1611 KT",
    "addr:housenumber":"72",
    "addr:postcode":"1611 kt",
    "addr:street":"De Middend",
    "iso:country":"NL",
    "sg:address":"De Middend 72",
    "sg:city":"Bovenkarspel",
    "sg:orig_category":"Postkantoren",
    "sg:phone":"+31 228 511 210",
    "sg:postcode":"1611 KT",
    "sg:province":"Noord-Holland",
    "sg:website":"http://www.postkantoor.nl",
    "wof:name":"Postkantoor",
    "wof:placetype":"venue"
},
  "geometry": {"coordinates":[5.234457,52.695938],"type":"Point"}
}