{
  "type": "Feature",
  "properties": {
    "addr:full":"Past Deckersstr 14 Venlo Limburg 5913 TT",
    "addr:housenumber":"14",
    "addr:postcode":"5913 tt",
    "iso:country":"NL",
    "sg:address":"Past Deckersstr 14",
    "sg:city":"Venlo",
    "sg:orig_category":"Administratie- En Boekhoudkantoren",
    "sg:phone":"+31 77 354 6934",
    "sg:postcode":"5913 TT",
    "sg:province":"Limburg",
    "sg:website":"http://www.geldwebsite.nl",
    "wof:name":"Groenveld Bv",
    "wof:placetype":"venue"
},
  "geometry": {"coordinates":[6.178462,51.365143],"type":"Point"}
}