{
  "type": "Feature",
  "properties": {
    "addr:full":"T Woud 37 Brielle Zuid-Holland 3232 LN",
    "addr:housenumber":"37",
    "addr:postcode":"3232 ln",
    "addr:street":"T Woud",
    "iso:country":"NL",
    "sg:address":"T Woud 37",
    "sg:city":"Brielle",
    "sg:orig_category":"Autopoetsbedrijven",
    "sg:phone":"+31 181 472 687",
    "sg:postcode":"3232 LN",
    "sg:province":"Zuid-Holland",
    "wof:name":"Nieuwenburg, Gebroeders",
    "wof:placetype":"venue"
},
  "geometry": {"coordinates":[4.160328,51.887718],"type":"Point"}
}