{
  "type": "Feature",
  "properties": {
    "addr:full":"H Polakln 17 Zutphen Gelderland 7207 HS",
    "addr:housenumber":"17",
    "addr:postcode":"7207 hs",
    "addr:street":"Gelderland",
    "iso:country":"NL",
    "sg:address":"H Polakln 17",
    "sg:city":"Zutphen",
    "sg:orig_category":"Bedrijfsopleidingen",
    "sg:phone":"+31 575 572 212",
    "sg:postcode":"7207 HS",
    "sg:province":"Gelderland",
    "sg:website":"http://www.kinterview.com",
    "wof:name":"Kinterview",
    "wof:placetype":"venue"
},
  "geometry": {"coordinates":[6.191525,52.140202],"type":"Point"}
}