{
  "type": "Feature",
  "properties": {
    "addr:full":"Stofkuipstr 3 Wormer Noord-Holland 1531 NC",
    "addr:housenumber":"3",
    "addr:postcode":"1531 nc",
    "addr:street":"Stofkuipstr",
    "iso:country":"NL",
    "sg:address":"Stofkuipstr 3",
    "sg:city":"Wormer",
    "sg:orig_category":"Papier - Fabrieken En Groothandel",
    "sg:phone":"+31 75 642 7566",
    "sg:postcode":"1531 NC",
    "sg:province":"Noord-Holland",
    "wof:name":"Haza Bv",
    "wof:placetype":"venue"
},
  "geometry": {"coordinates":[4.811797,52.489056],"type":"Point"}
}