{
  "type": "Feature",
  "properties": {
    "addr:full":"Hoofdstraat 69 Kortgene Zeeland 4484 CC",
    "addr:housenumber":"69",
    "addr:postcode":"4484 cc",
    "addr:street":"Hoofdstraat",
    "iso:country":"NL",
    "sg:address":"Hoofdstraat 69",
    "sg:city":"Kortgene",
    "sg:orig_category":"Zuivelproducten",
    "sg:phone":"+31 113 301 972",
    "sg:postcode":"4484 CC",
    "sg:province":"Zeeland",
    "wof:name":"Reijnhout Kaashandel",
    "wof:placetype":"venue"
},
  "geometry": {"coordinates":[3.801516,51.558464],"type":"Point"}
}