{
  "type": "Feature",
  "properties": {
    "iso:country":"NL",
    "sg:address":"Ambachtsweg 29",
    "sg:city":"Wateringen",
    "sg:orig_category":"Metaalwerken",
    "sg:phone":"+31 174 290 005",
    "sg:postcode":"2291 EV",
    "sg:province":"South Holland",
    "wof:name":"P.G. Bouwer",
    "wof:placetype":"venue"
},
  "geometry": {"coordinates":[4.269785,52.030567],"type":"Point"}
}