{
  "type": "Feature",
  "properties": {
    "addr:full":"Sara Burgerhartstraat 3 Amsterdam Noord-Holland 1055 KV",
    "addr:housenumber":"3",
    "addr:postcode":"1055 kv",
    "addr:street":"Sara Burgerhartstraat",
    "iso:country":"NL",
    "sg:address":"Sara Burgerhartstraat 3",
    "sg:city":"Amsterdam",
    "sg:orig_category":"Volwassenenonderwijs",
    "sg:phone":"+31 20 681 0571",
    "sg:postcode":"1055 KV",
    "sg:province":"Noord-Holland",
    "wof:name":"Joke Smit College",
    "wof:placetype":"venue"
},
  "geometry": {"coordinates":[4.848807,52.382706],"type":"Point"}
}