{
  "type": "Feature",
  "properties": {
    "addr:full":"Gestelsestr 14 Waalre North Brabant 5582 HH",
    "addr:housenumber":"14",
    "addr:postcode":"5582 hh",
    "addr:street":"Gestelsestr",
    "iso:country":"NL",
    "sg:address":"Gestelsestr 14",
    "sg:city":"Waalre",
    "sg:orig_category":"Projectinrichting",
    "sg:phone":"+31 40 221 6133",
    "sg:postcode":"5582 HH",
    "sg:province":"North Brabant",
    "wof:name":"Valk, Van Der",
    "wof:placetype":"venue"
},
  "geometry": {"coordinates":[5.47678,51.398174],"type":"Point"}
}