{
  "type": "Feature",
  "properties": {
    "addr:full":"Eschauzierstr 17 Terschelling West Provincie Friesland 8881 AR",
    "addr:housenumber":"17",
    "addr:postcode":"8881",
    "addr:street":"Eschauzierstr;Friesland",
    "iso:country":"NL",
    "sg:address":"Eschauzierstr 17",
    "sg:city":"Terschelling West",
    "sg:classifiers":[
        {
            "category":"Farming",
            "subcategory":"Fish & Marine Products",
            "type":"Manufacturing & Wholesale Goods"
        }
    ],
    "sg:phone":"+31 562 443 600",
    "sg:postcode":"8881 AR",
    "sg:province":"Provincie Friesland",
    "sg:tags":[
        "vi"
    ],
    "wof:name":"Meulen, A Van Der",
    "wof:placetype":"venue"
},
  "geometry": {"coordinates":[5.214094,53.360294],"type":"Point"}
}