{
  "type": "Feature",
  "properties": {
    "addr:full":"Goudoever 3 Bunschoten Spakenburg Utrecht 3752 GS",
    "addr:housenumber":"3",
    "addr:postcode":"3752 gs",
    "addr:street":"Goudoever",
    "iso:country":"NL",
    "sg:address":"Goudoever 3",
    "sg:city":"Bunschoten Spakenburg",
    "sg:orig_category":"Artsen - Huisartsen",
    "sg:phone":"+31 33 299 6806",
    "sg:postcode":"3752 GS",
    "sg:province":"Utrecht",
    "wof:name":"Graaf & E J Meyer-Kleinjan, T L De",
    "wof:placetype":"venue"
},
  "geometry": {"coordinates":[5.370925,52.251328],"type":"Point"}
}