{
  "type": "Feature",
  "properties": {
    "addr:full":"Ijsselkade 13 Ijsselstein Ut Utrecht 3401 RC",
    "addr:housenumber":"13",
    "addr:postcode":"3401 rc",
    "addr:street":"Ijsselkade",
    "iso:country":"NL",
    "sg:address":"Ijsselkade 13",
    "sg:city":"Ijsselstein Ut",
    "sg:orig_category":"Kunst And Kunstenaarsbenodigdheden",
    "sg:phone":"+31 30 688 8214",
    "sg:postcode":"3401 RC",
    "sg:province":"Utrecht",
    "wof:name":"Lijstmakerij Wim Baars Vof",
    "wof:placetype":"venue"
},
  "geometry": {"coordinates":[5.051214,52.018997],"type":"Point"}
}