{
  "type": "Feature",
  "properties": {
    "iso:country":"NL",
    "sg:address":"Bottelaarpassage 102-104",
    "sg:city":"Almere",
    "sg:orig_category":"Opticiens",
    "sg:phone":"+31 36 534 4996",
    "sg:postcode":"1315 ET",
    "sg:province":"NL.",
    "sg:website":"http://www.hansanders.nl",
    "wof:name":"Hans Anders",
    "wof:placetype":"venue"
},
  "geometry": {"coordinates":[5.2157678604,52.3707351685],"type":"Point"}
}