{
  "type": "Feature",
  "properties": {
    "iso:country":"NL",
    "sg:address":"Jan Luykenstraat 16",
    "sg:city":"Utrecht",
    "sg:orig_category":"Wegen And Sportterreinen",
    "sg:phone":"+31 30 296 1066",
    "sg:postcode":"3521 VC",
    "sg:province":"Utrecht",
    "wof:name":"A. Koot En Zoon Vof",
    "wof:placetype":"venue"
},
  "geometry": {"coordinates":[5.1121988297,52.0824661255],"type":"Point"}
}