{
  "type": "Feature",
  "properties": {
    "iso:country":"NL",
    "sg:address":"Roggestr 1",
    "sg:city":"Markelo",
    "sg:orig_category":"Voetbalverenigingen",
    "sg:phone":"+31 547 362 977",
    "sg:postcode":"7475 EL",
    "sg:province":"Overijssel",
    "wof:name":"Markvogels",
    "wof:placetype":"venue"
},
  "geometry": {"coordinates":[6.505232,52.239944],"type":"Point"}
}