{
  "type": "Feature",
  "properties": {
    "addr:full":"Industrieweg 1C Boxtel Noord-Brabant 5281 RW",
    "addr:housenumber":"1c",
    "addr:postcode":"5281 rw",
    "addr:street":"Industrieweg",
    "iso:country":"NL",
    "sg:address":"Industrieweg 1C",
    "sg:city":"Boxtel",
    "sg:orig_category":"Autokeuringen",
    "sg:phone":"+31 411 682 510",
    "sg:postcode":"5281 RW",
    "sg:province":"Noord-Brabant",
    "wof:name":"J.A. Raja",
    "wof:placetype":"venue"
},
  "geometry": {"coordinates":[5.311774,51.5807],"type":"Point"}
}