{
  "type": "Feature",
  "properties": {
    "addr:full":"Langestraat 33B Delden Overijssel 7491 AA",
    "addr:housenumber":"33b",
    "addr:postcode":"7491 aa",
    "addr:street":"Langestraat",
    "iso:country":"NL",
    "sg:address":"Langestraat 33B",
    "sg:city":"Delden",
    "sg:classifiers":[
        {
            "category":"Fast Food",
            "type":"Food & Drink"
        }
    ],
    "sg:phone":"+31 74 376 3196",
    "sg:postcode":"7491 AA",
    "sg:province":"Overijssel",
    "sg:tags":[
        "afhaal",
        "restaurant"
    ],
    "wof:name":"Shoarma Restaurant Luxor",
    "wof:placetype":"venue"
},
  "geometry": {"coordinates":[6.712075,52.262424],"type":"Point"}
}