{
  "type": "Feature",
  "properties": {
    "addr:full":"Hoofdstr 261 Beerta Groningen 9686 PC",
    "addr:housenumber":"261",
    "addr:postcode":"9686 pc",
    "addr:street":"Beerta",
    "iso:country":"NL",
    "sg:address":"Hoofdstr 261",
    "sg:city":"Beerta",
    "sg:orig_category":"Bejaarden - Verzorgingstehuizen",
    "sg:phone":"+31 597 596 200",
    "sg:postcode":"9686 PC",
    "sg:province":"Groningen",
    "sg:website":"http://www.oosterlengte.nl",
    "wof:name":"Tjamme, De",
    "wof:placetype":"venue"
},
  "geometry": {"coordinates":[7.09801,53.17527],"type":"Point"}
}