{
  "type": "Feature",
  "properties": {
    "addr:full":"Steenstraat 8 Wijk Bij Duurstede Utrecht 3961 VP",
    "addr:housenumber":"8",
    "addr:postcode":"3961 vp",
    "addr:street":"Steenstraat",
    "iso:country":"NL",
    "sg:address":"Steenstraat 8",
    "sg:city":"Wijk Bij Duurstede",
    "sg:orig_category":"Banken And Kredietinstellingen",
    "sg:phone":"+31 343 590 911",
    "sg:postcode":"3961 VP",
    "sg:province":"Utrecht",
    "wof:name":"Rabobank",
    "wof:placetype":"venue"
},
  "geometry": {"coordinates":[5.342915,51.974892],"type":"Point"}
}