{
  "type": "Feature",
  "properties": {
    "addr:full":"Brouwersstr 5 Druten Gelderland 6651 AH",
    "addr:housenumber":"5",
    "addr:postcode":"6651 ah",
    "addr:street":"Brouwersstr",
    "iso:country":"NL",
    "sg:address":"Brouwersstr 5",
    "sg:city":"Druten",
    "sg:orig_category":"Zonnebank- En Solariumcentra",
    "sg:phone":"+31 487 517 484",
    "sg:postcode":"6651 AH",
    "sg:province":"Gelderland",
    "wof:name":"Decozon",
    "wof:placetype":"venue"
},
  "geometry": {"coordinates":[5.611819,51.892525],"type":"Point"}
}