{
  "type": "Feature",
  "properties": {
    "iso:country":"NL",
    "sg:address":"Prins Hendrikkade 165E",
    "sg:city":"Amsterdam",
    "sg:orig_category":"Kinderopvang Behalve Thuis",
    "sg:phone":"+31 20 638 3825",
    "sg:postcode":"1011 TB",
    "sg:province":"Noord-Holland",
    "wof:name":"Creche Joop Gilliamse",
    "wof:placetype":"venue"
},
  "geometry": {"coordinates":[4.909237,52.371895],"type":"Point"}
}