{
  "type": "Feature",
  "properties": {
    "addr:full":"Strandweg 16 Den Haag Scheveningen South Holland 2586 JK",
    "addr:housenumber":"16",
    "addr:postcode":"2586 jk",
    "addr:street":"Strandweg",
    "iso:country":"NL",
    "sg:address":"Strandweg 16",
    "sg:city":"Den Haag Scheveningen",
    "sg:classifiers":[
        {
            "category":"Fast Food",
            "type":"Food & Drink"
        }
    ],
    "sg:phone":"+31 70 354 7042",
    "sg:postcode":"2586 JK",
    "sg:province":"South Holland",
    "sg:tags":[
        "afhaal",
        "restaurant"
    ],
    "wof:name":"Strandpaviljoen Veronica",
    "wof:placetype":"venue"
},
  "geometry": {"coordinates":[4.27721,52.10672],"type":"Point"}
}