{
  "type": "Feature",
  "properties": {
    "addr:full":"Europawg 218 Apeldoorn Gelderland 7336 AR",
    "addr:housenumber":"218",
    "addr:postcode":"7336",
    "addr:street":"Gelderland",
    "iso:country":"NL",
    "sg:address":"Europawg 218",
    "sg:city":"Apeldoorn",
    "sg:orig_category":"Autoruiten",
    "sg:phone":"+31 55 534 1919",
    "sg:postcode":"7336 AR",
    "sg:province":"Gelderland",
    "sg:website":"http://www.carglass.nl",
    "wof:name":"Carglass",
    "wof:placetype":"venue"
},
  "geometry": {"coordinates":[5.933727,52.192966],"type":"Point"}
}