{
  "type": "Feature",
  "properties": {
    "addr:full":"Nassauln 70-76 Haarlem North Holland 2011 PE",
    "addr:housenumber":"70-76",
    "addr:postcode":"2011 pe",
    "iso:country":"NL",
    "sg:address":"Nassauln 70-76",
    "sg:city":"Haarlem",
    "sg:orig_category":"Horren",
    "sg:phone":"+31 23 531 0040",
    "sg:postcode":"2011 PE",
    "sg:province":"North Holland",
    "wof:name":"Senft & Zn",
    "wof:placetype":"venue"
},
  "geometry": {"coordinates":[4.6422529221,52.3805618286],"type":"Point"}
}