{
  "type": "Feature",
  "properties": {
    "addr:full":"Grotewg 20 Wapenveld Gelderland 8191 JW",
    "addr:housenumber":"20",
    "addr:postcode":"8191 jw",
    "addr:street":"Grotewg;Gelderland",
    "iso:country":"NL",
    "sg:address":"Grotewg 20",
    "sg:city":"Wapenveld",
    "sg:classifiers":[
        {
            "category":"Retail",
            "subcategory":"Auto Repair",
            "type":"Services"
        }
    ],
    "sg:phone":"+31 38 447 8514",
    "sg:postcode":"8191 JW",
    "sg:province":"Gelderland",
    "sg:tags":[
        "garage"
    ],
    "wof:name":"Rorije Vof, S",
    "wof:placetype":"venue"
},
  "geometry": {"coordinates":[6.061602,52.422249],"type":"Point"}
}