{
  "type": "Feature",
  "properties": {
    "addr:full":"Spanjaardstr 133B Rotterdam South Holland 3025 TN",
    "addr:housenumber":"133b",
    "addr:postcode":"3025",
    "iso:country":"NL",
    "sg:address":"Spanjaardstr 133B",
    "sg:city":"Rotterdam",
    "sg:orig_category":"Kappers",
    "sg:phone":"+31 10 476 7198",
    "sg:postcode":"3025 TN",
    "sg:province":"South Holland",
    "wof:name":"Kauffman, Hairstylist",
    "wof:placetype":"venue"
},
  "geometry": {"coordinates":[4.4453201294,51.9063796997],"type":"Point"}
}