{
  "type": "Feature",
  "properties": {
    "addr:full":"Hogezoom 114 Renesse Zeeland 4325 CL",
    "addr:housenumber":"114",
    "addr:postcode":"4325",
    "addr:street":"Hogezoom",
    "iso:country":"NL",
    "sg:address":"Hogezoom 114",
    "sg:city":"Renesse",
    "sg:orig_category":"Kampeerterreinen",
    "sg:phone":"+31 111 461 408",
    "sg:postcode":"4325 CL",
    "sg:province":"Zeeland",
    "wof:name":"Camping De Pionier",
    "wof:placetype":"venue"
},
  "geometry": {"coordinates":[3.765089035,51.7234649658],"type":"Point"}
}