{
  "type": "Feature",
  "properties": {
    "addr:full":"Weststr 1 Domburg Zeeland 4357 BL",
    "addr:housenumber":"1",
    "addr:postcode":"4357 bl",
    "addr:street":"Weststr",
    "iso:country":"NL",
    "sg:address":"Weststr 1",
    "sg:city":"Domburg",
    "sg:orig_category":"Elektrotechnische Installatiebureaus",
    "sg:phone":"+31 118 581 442",
    "sg:postcode":"4357 BL",
    "sg:province":"Zeeland",
    "wof:name":"Akkerdaas",
    "wof:placetype":"venue"
},
  "geometry": {"coordinates":[3.496206,51.563023],"type":"Point"}
}