{
  "type": "Feature",
  "properties": {
    "iso:country":"NL",
    "sg:address":"Harste 5",
    "sg:city":"Sneek",
    "sg:orig_category":"Huizensloop And Bouwrijp Maken",
    "sg:phone":"+31 515 417 325",
    "sg:postcode":"8602 JX",
    "sg:province":"Friesland",
    "wof:name":"Donker Cultuurtechn Bv",
    "wof:placetype":"venue"
},
  "geometry": {"coordinates":[5.643057,53.039066],"type":"Point"}
}