{
  "type": "Feature",
  "properties": {
    "iso:country":"NL",
    "sg:address":"Vlasveld 47",
    "sg:city":"Hulsberg",
    "sg:orig_category":"Film-, Tv- And Videoproductie",
    "sg:phone":"+31 45 405 5803",
    "sg:postcode":"6336 WN",
    "sg:province":"Limburg",
    "wof:name":"Marell Digitale Muzieksystemen",
    "wof:placetype":"venue"
},
  "geometry": {"coordinates":[5.848278,50.888268],"type":"Point"}
}