{
  "type": "Feature",
  "properties": {
    "addr:full":"Godsweerdersngl 77 Roermond Limburg 6041 GK",
    "addr:housenumber":"77",
    "addr:postcode":"6041 gk",
    "addr:street":"Godsweerdersngl",
    "iso:country":"NL",
    "sg:address":"Godsweerdersngl 77",
    "sg:city":"Roermond",
    "sg:orig_category":"Verenigingen En Stichtingen",
    "sg:phone":"+31 475 356 000",
    "sg:postcode":"6041 GK",
    "sg:province":"Limburg",
    "wof:name":"Awvn-Vno Ncw",
    "wof:placetype":"venue"
},
  "geometry": {"coordinates":[5.993553,51.195213],"type":"Point"}
}