{
  "type": "Feature",
  "properties": {
    "addr:full":"Spijk 2 Wijk En Aalburg Gelderland 4261 KE",
    "addr:housenumber":"2",
    "addr:postcode":"4261 ke",
    "addr:street":"Spijk",
    "iso:country":"NL",
    "sg:address":"Spijk 2",
    "sg:city":"Wijk En Aalburg",
    "sg:orig_category":"Technische Studies And Onderzoek",
    "sg:phone":"+31 416 693 464",
    "sg:postcode":"4261 KE",
    "sg:province":"Gelderland",
    "wof:name":"Van Dijk Engineering",
    "wof:placetype":"venue"
},
  "geometry": {"coordinates":[5.12226,51.768116],"type":"Point"}
}