{
  "type": "Feature",
  "properties": {
    "iso:country":"NL",
    "sg:address":"Spijk 2",
    "sg:city":"Wijk En Aalburg",
    "sg:orig_category":"Technische Studies And Onderzoek",
    "sg:phone":"+31 416 693 464",
    "sg:postcode":"4261 KE",
    "sg:province":"Gelderland",
    "wof:name":"Van Dijk Engineering",
    "wof:placetype":"venue"
},
  "geometry": {"coordinates":[5.12226,51.768116],"type":"Point"}
}