{
  "type": "Feature",
  "properties": {
    "addr:full":"Onderdendamsterwg 33/B Winsum Gn Groningen 9951 TD",
    "addr:housenumber":"33 / b",
    "addr:postcode":"gn;9951 td",
    "addr:street":"Onderdendamsterwg",
    "iso:country":"NL",
    "sg:address":"Onderdendamsterwg 33/B",
    "sg:city":"Winsum Gn",
    "sg:classifiers":[
        {
            "category":"Retail",
            "subcategory":"Auto Repair",
            "type":"Services"
        }
    ],
    "sg:phone":"+31 595 442 296",
    "sg:postcode":"9951 TD",
    "sg:province":"Groningen",
    "sg:tags":[
        "garage"
    ],
    "sg:website":"http://www.mazda.nl/terpstra",
    "wof:name":"Terpstra",
    "wof:placetype":"venue"
},
  "geometry": {"coordinates":[6.5206,53.334473],"type":"Point"}
}