{
  "type": "Feature",
  "properties": {
    "addr:full":"Officiersvliet 40 Zwyndrecht Zuid-Holland 3331 KM",
    "addr:housenumber":"40",
    "addr:postcode":"3331 km",
    "addr:street":"Officiersvliet",
    "iso:country":"NL",
    "sg:address":"Officiersvliet 40",
    "sg:city":"Zwyndrecht",
    "sg:orig_category":"Onderhoudswerken",
    "sg:phone":"+31 78 619 1145",
    "sg:postcode":"3331 KM",
    "sg:province":"Zuid-Holland",
    "wof:name":"Hans Robbemond Klus En Montage",
    "wof:placetype":"venue"
},
  "geometry": {"coordinates":[4.64073,51.820702],"type":"Point"}
}