{
  "type": "Feature",
  "properties": {
    "addr:full":"J V Heemskerckstr 026 Den Helder Noord-Holland 1782 XD",
    "addr:housenumber":"026",
    "addr:postcode":"1782 xd",
    "addr:street":"J;Heemskerckstr",
    "iso:country":"NL",
    "sg:address":"J V Heemskerckstr 026",
    "sg:city":"Den Helder",
    "sg:orig_category":"Onderhoudswerken",
    "sg:phone":"+31 223 683 631",
    "sg:postcode":"1782 XD",
    "sg:province":"Noord-Holland",
    "wof:name":"Td",
    "wof:placetype":"venue"
},
  "geometry": {"coordinates":[4.758825,52.958191],"type":"Point"}
}