{
  "type": "Feature",
  "properties": {
    "addr:full":"Kloetingsewg 45 Goes Zeeland 4462 AV",
    "addr:housenumber":"45",
    "addr:postcode":"4462 av",
    "addr:street":"Kloetingsewg",
    "iso:country":"NL",
    "sg:address":"Kloetingsewg 45",
    "sg:city":"Goes",
    "sg:orig_category":"Notarissen En Notariskantoren",
    "sg:phone":"+31 113 232 800",
    "sg:postcode":"4462 AV",
    "sg:province":"Zeeland",
    "sg:website":"http://www.doh-notarissen.nl",
    "wof:name":"Dissel Oostinga Hage, V",
    "wof:placetype":"venue"
},
  "geometry": {"coordinates":[-83.914169,39.768833],"type":"Point"}
}