{
  "type": "Feature",
  "properties": {
    "addr:full":"Hofpad 28 Barneveld Gelderland 3773 AZ",
    "addr:housenumber":"28",
    "addr:postcode":"3773",
    "addr:street":"Hofpad;Gelderland",
    "iso:country":"NL",
    "sg:address":"Hofpad 28",
    "sg:city":"Barneveld",
    "sg:orig_category":"Keukens",
    "sg:phone":"+31 342 493 046",
    "sg:postcode":"3773 AZ",
    "sg:province":"Gelderland",
    "wof:name":"Uleman",
    "wof:placetype":"venue"
},
  "geometry": {"coordinates":[5.601882,52.139519],"type":"Point"}
}