{
  "type": "Feature",
  "properties": {
    "addr:full":"Kerkstraat 271 Gaanderen Gelderland 7011 CN",
    "addr:housenumber":"271",
    "addr:postcode":"7011 cn",
    "addr:street":"Kerkstraat;Gelderland",
    "iso:country":"NL",
    "sg:address":"Kerkstraat 271",
    "sg:city":"Gaanderen",
    "sg:orig_category":"Autokeuringen",
    "sg:phone":"+31 315 341 666",
    "sg:postcode":"7011 CN",
    "sg:province":"Gelderland",
    "wof:name":"Vof Garagebedrijf R. Massop",
    "wof:placetype":"venue"
},
  "geometry": {"coordinates":[6.357493,51.927174],"type":"Point"}
}