{
  "type": "Feature",
  "properties": {
    "iso:country":"NL",
    "sg:address":"Lindeln 31",
    "sg:city":"Delft",
    "sg:orig_category":"Bloemen En Planten",
    "sg:phone":"+31 15 213 5889",
    "sg:postcode":"2612 VH",
    "sg:province":"Zuid-Holland",
    "wof:name":"Colijn, A",
    "wof:placetype":"venue"
},
  "geometry": {"coordinates":[4.365159,52.018391],"type":"Point"}
}