{
  "type": "Feature",
  "properties": {
    "addr:full":"Pottenbakkerssingel 12 Middelburg Zeeland 4331 NA",
    "addr:housenumber":"12",
    "addr:postcode":"4331 na",
    "addr:street":"Pottenbakkerssingel",
    "iso:country":"NL",
    "sg:address":"Pottenbakkerssingel 12",
    "sg:city":"Middelburg",
    "sg:orig_category":"Wasserettes And Stomerijen",
    "sg:phone":"+31 118 638 029",
    "sg:postcode":"4331 NA",
    "sg:province":"Zeeland",
    "wof:name":"Konmar",
    "wof:placetype":"venue"
},
  "geometry": {"coordinates":[3.6064920425,51.4972763062],"type":"Point"}
}