{
  "type": "Feature",
  "properties": {
    "addr:full":"Pinksterbloemstraat 1 Zevenbergen Noord-Brabant 4761 ZT",
    "addr:housenumber":"1",
    "addr:postcode":"4761 zt",
    "addr:street":"Pinksterbloemstraat",
    "iso:country":"NL",
    "sg:address":"Pinksterbloemstraat 1",
    "sg:city":"Zevenbergen",
    "sg:orig_category":"Artsen And Specialisten",
    "sg:phone":"+31 168 326 560",
    "sg:postcode":"4761 ZT",
    "sg:province":"Noord-Brabant",
    "wof:name":"Huisartsenpraktijk G.H.M. Kips",
    "wof:placetype":"venue"
},
  "geometry": {"coordinates":[4.593726,51.6404],"type":"Point"}
}