{
  "type": "Feature",
  "properties": {
    "addr:full":"Avondsterweg 11 Leeuwarden Friesland 8938 AK",
    "addr:housenumber":"11",
    "addr:postcode":"8938 ak",
    "addr:street":"Avondsterweg",
    "iso:country":"NL",
    "sg:address":"Avondsterweg 11",
    "sg:city":"Leeuwarden",
    "sg:orig_category":"Watersport-, Sport- And Kampeerbenodigdheden Verhuur",
    "sg:phone":"+31 58 288 3982",
    "sg:postcode":"8938 AK",
    "sg:province":"Friesland",
    "wof:name":"Froskepolle Kanocentrum",
    "wof:placetype":"venue"
},
  "geometry": {"coordinates":[5.8430957794,53.1907844543],"type":"Point"}
}