{
  "type": "Feature",
  "properties": {
    "addr:full":"Vermeerstr 46 Anna Paulowna Noord-Holland 1761 WR",
    "addr:housenumber":"46",
    "addr:postcode":"1761 wr",
    "addr:street":"Vermeerstr",
    "iso:country":"NL",
    "sg:address":"Vermeerstr 46",
    "sg:city":"Anna Paulowna",
    "sg:orig_category":"Wereldwinkels",
    "sg:phone":"+31 223 532 729",
    "sg:postcode":"1761 WR",
    "sg:province":"Noord-Holland",
    "wof:name":"Wereldwinkel",
    "wof:placetype":"venue"
},
  "geometry": {"coordinates":[4.8196158409,52.8576545715],"type":"Point"}
}