{
  "type": "Feature",
  "properties": {
    "iso:country":"NL",
    "sg:address":"Energiewg 7A",
    "sg:city":"Groningen",
    "sg:orig_category":"Kantoorbenodigdheden",
    "sg:phone":"+31 50 313 7047",
    "sg:postcode":"9743 AN",
    "sg:province":"Groningen",
    "sg:website":"http://www.cpet.nl",
    "wof:name":"Carlier",
    "wof:placetype":"venue"
},
  "geometry": {"coordinates":[6.5366158485,53.2122955322],"type":"Point"}
}