{
  "type": "Feature",
  "properties": {
    "addr:full":"Stuurmanstr 32 Zutphen Gelderland 7203 DC",
    "addr:housenumber":"32",
    "addr:postcode":"7203",
    "addr:street":"Stuurmanstr;Gelderland",
    "iso:country":"NL",
    "sg:address":"Stuurmanstr 32",
    "sg:city":"Zutphen",
    "sg:orig_category":"Elektronica - Ontwikkeling En Groothandel",
    "sg:phone":"+31 575 548 668",
    "sg:postcode":"7203 DC",
    "sg:province":"Gelderland",
    "sg:website":"http://www.mereltron.nl",
    "wof:name":"Mereltron Bv",
    "wof:placetype":"venue"
},
  "geometry": {"coordinates":[6.220057,52.152931],"type":"Point"}
}