{
  "type": "Feature",
  "properties": {
    "addr:full":"Maaibeemd 91 Breda Noord-Brabant 4824 ND",
    "addr:housenumber":"91",
    "addr:postcode":"4824 nd",
    "addr:street":"Maaibeemd",
    "iso:country":"NL",
    "sg:address":"Maaibeemd 91",
    "sg:city":"Breda",
    "sg:orig_category":"Fietsen En Bromfietsen",
    "sg:phone":"+31 76 541 8519",
    "sg:postcode":"4824 ND",
    "sg:province":"Noord-Brabant",
    "wof:name":"Grafa",
    "wof:placetype":"venue"
},
  "geometry": {"coordinates":[4.74043,51.608315],"type":"Point"}
}