{
  "type": "Feature",
  "properties": {
    "iso:country":"NL",
    "sg:address":"2E Middellandstraat 17A",
    "sg:city":"Rotterdam",
    "sg:classifiers":[
        {
            "category":"Fast Food",
            "type":"Food & Drink"
        }
    ],
    "sg:phone":"+31 10 476 9228",
    "sg:postcode":"3021 BL",
    "sg:province":"South Holland",
    "sg:tags":[
        "afhaal",
        "restaurant"
    ],
    "wof:name":"Snackbar In 'T Smulhuijs",
    "wof:placetype":"venue"
},
  "geometry": {"coordinates":[4.456639,51.917782],"type":"Point"}
}