{
  "type": "Feature",
  "properties": {
    "addr:full":"Naarderstr 12 Huizen North Holland 1271 CE",
    "addr:housenumber":"12",
    "addr:postcode":"1271 ce",
    "addr:street":"Naarderstr",
    "iso:country":"NL",
    "sg:address":"Naarderstr 12",
    "sg:city":"Huizen",
    "sg:orig_category":"Accountants - Administratie- Consulenten En -Kantoren",
    "sg:phone":"+31 35 526 2008",
    "sg:postcode":"1271 CE",
    "sg:province":"North Holland",
    "wof:name":"Scheepers",
    "wof:placetype":"venue"
},
  "geometry": {"coordinates":[5.229924,52.296993],"type":"Point"}
}