{
  "type": "Feature",
  "properties": {
    "iso:country":"NL",
    "sg:address":"Raadhuisstraat 17",
    "sg:city":"Moergestel",
    "sg:orig_category":"Damesmodezaken",
    "sg:phone":"+31 13 513 1287",
    "sg:postcode":"5066 AP",
    "sg:province":"Noord-Brabant",
    "wof:name":"Modehuis Poirters",
    "wof:placetype":"venue"
},
  "geometry": {"coordinates":[5.183539,51.545616],"type":"Point"}
}