{
  "type": "Feature",
  "properties": {
    "addr:full":"Boteringesngl 13 Groningen Groningen 9712 XR",
    "addr:housenumber":"13",
    "addr:postcode":"9712 xr",
    "addr:street":"Boteringesngl",
    "iso:country":"NL",
    "sg:address":"Boteringesngl 13",
    "sg:city":"Groningen",
    "sg:orig_category":"Scheepvaart- Agentschappen",
    "sg:phone":"+31 50 312 6078",
    "sg:postcode":"9712 XR",
    "sg:province":"Groningen",
    "wof:name":"Sea Lily",
    "wof:placetype":"venue"
},
  "geometry": {"coordinates":[6.562431,53.220615],"type":"Point"}
}