{
  "type": "Feature",
  "properties": {
    "addr:full":"L Voorhout 43 S Gravenhage Zuid-Holland 2514 EC",
    "addr:housenumber":"43;gravenhage",
    "addr:postcode":"2514 ec",
    "addr:street":"L Voorhout;S",
    "iso:country":"NL",
    "sg:address":"L Voorhout 43",
    "sg:city":"S Gravenhage",
    "sg:orig_category":"Organisatiebureaus",
    "sg:phone":"+31 70 324 1169",
    "sg:postcode":"2514 EC",
    "sg:province":"Zuid-Holland",
    "sg:website":"http://www.vankooy-partners.nl",
    "wof:name":"Kooy & Partners, Van",
    "wof:placetype":"venue"
},
  "geometry": {"coordinates":[4.3093500137,52.084148407],"type":"Point"}
}