{
  "type": "Feature",
  "properties": {
    "addr:full":"Grotestraat 101 Goor NL.08 7471  B",
    "addr:housenumber":"101;nl.08 7471 b",
    "addr:street":"Grotestraat",
    "iso:country":"NL",
    "sg:address":"Grotestraat 101",
    "sg:city":"Goor",
    "sg:orig_category":"Boekenuitgeverijen",
    "sg:phone":"+31 547 273 176",
    "sg:postcode":"7471  B",
    "sg:province":"NL.08",
    "wof:name":"Bruna",
    "wof:placetype":"venue"
},
  "geometry": {"coordinates":[6.586206,52.232655],"type":"Point"}
}