{
  "type": "Feature",
  "properties": {
    "addr:full":"Hoogstr 73 Eindhoven Noord-Brabant 5615 PB",
    "addr:housenumber":"73",
    "addr:postcode":"5615 pb",
    "addr:street":"Hoogstr",
    "iso:country":"NL",
    "sg:address":"Hoogstr 73",
    "sg:city":"Eindhoven",
    "sg:orig_category":"Kappers",
    "sg:phone":"+31 40 237 4650",
    "sg:postcode":"5615 PB",
    "sg:province":"Noord-Brabant",
    "sg:website":"http://www.hedz.nl",
    "wof:name":"Hedz",
    "wof:placetype":"venue"
},
  "geometry": {"coordinates":[5.4841051102,51.4344711304],"type":"Point"}
}