{
  "type": "Feature",
  "properties": {
    "addr:full":"Sluisweg 2 Zoutkamp Groningen 9974 RJ",
    "addr:housenumber":"2",
    "addr:postcode":"9974 rj",
    "addr:street":"Sluisweg",
    "iso:country":"NL",
    "sg:address":"Sluisweg 2",
    "sg:city":"Zoutkamp",
    "sg:orig_category":"Kappers",
    "sg:phone":"+31 595 402 659",
    "sg:postcode":"9974 RJ",
    "sg:province":"Groningen",
    "wof:name":"Haarmode Zoutkamp",
    "wof:placetype":"venue"
},
  "geometry": {"coordinates":[6.3004889488,53.3376121521],"type":"Point"}
}