{
  "type": "Feature",
  "properties": {
    "addr:full":"Pootstr 43 Rotterdam Zuid-Holland 3034 BB",
    "addr:housenumber":"43",
    "addr:postcode":"3034 bb",
    "addr:street":"Pootstr",
    "iso:country":"NL",
    "sg:address":"Pootstr 43",
    "sg:city":"Rotterdam",
    "sg:orig_category":"Beeldende Kunstenaars",
    "sg:phone":"+31 10 433 0761",
    "sg:postcode":"3034 BB",
    "sg:province":"Zuid-Holland",
    "sg:website":"http://www.webman-tm.com",
    "wof:name":"Montebasso",
    "wof:placetype":"venue"
},
  "geometry": {"coordinates":[4.49475,51.932396],"type":"Point"}
}