{
  "type": "Feature",
  "properties": {
    "addr:full":"Kerkpln 1 Dalfsen Overijssel 7721 AC",
    "addr:housenumber":"1",
    "addr:postcode":"7721 ac",
    "addr:street":"Kerkpln",
    "iso:country":"NL",
    "sg:address":"Kerkpln 1",
    "sg:city":"Dalfsen",
    "sg:orig_category":"Bloemen En Planten",
    "sg:phone":"+31 529 435 013",
    "sg:postcode":"7721 AC",
    "sg:province":"Overijssel",
    "wof:name":"Hertsenberg Vof",
    "wof:placetype":"venue"
},
  "geometry": {"coordinates":[6.26187,52.50462],"type":"Point"}
}