{
  "type": "Feature",
  "properties": {
    "addr:full":"Wijk Aan Zeeerweg 54 Ijmuiden Noord-Holland 1972 NS",
    "addr:housenumber":"54",
    "addr:postcode":"1972 ns",
    "addr:street":"Wijk Aan Zeeerweg",
    "iso:country":"NL",
    "sg:address":"Wijk Aan Zeeerweg 54",
    "sg:city":"Ijmuiden",
    "sg:orig_category":"Goederenvervoer Over De Weg",
    "sg:phone":"+31 255 514 465",
    "sg:postcode":"1972 NS",
    "sg:province":"Noord-Holland",
    "wof:name":"Hessels Transport",
    "wof:placetype":"venue"
},
  "geometry": {"coordinates":[4.617584,52.460865],"type":"Point"}
}