{
  "type": "Feature",
  "properties": {
    "iso:country":"NL",
    "sg:address":"Wedelsvoort 1",
    "sg:city":"Helmond",
    "sg:orig_category":"Horren",
    "sg:phone":"+31 492 514 783",
    "sg:postcode":"5706 KR",
    "sg:province":"Noord-Brabant",
    "wof:name":"Java",
    "wof:placetype":"venue"
},
  "geometry": {"coordinates":[5.623619,51.459435],"type":"Point"}
}