{
  "type": "Feature",
  "properties": {
    "iso:country":"NL",
    "sg:address":"Leyweg 649",
    "sg:city":"'S Gravenhage",
    "sg:orig_category":"Verlichting And Huishoudartikelen",
    "sg:phone":"+31 70 309 9405",
    "sg:postcode":"2545 GK",
    "sg:province":"Zuid-Holland",
    "wof:name":"Van Gent Handelsonderneming",
    "wof:placetype":"venue"
},
  "geometry": {"coordinates":[4.2759,52.048092],"type":"Point"}
}