{
  "type": "Feature",
  "properties": {
    "addr:full":"Pluutwerf 31 Gouda South Holland 2804 MC",
    "addr:housenumber":"31",
    "addr:postcode":"2804 mc",
    "addr:street":"Pluutwerf",
    "iso:country":"NL",
    "sg:address":"Pluutwerf 31",
    "sg:city":"Gouda",
    "sg:orig_category":"Leesportefeuilles",
    "sg:phone":"+31 182 530 503",
    "sg:postcode":"2804 MC",
    "sg:province":"South Holland",
    "wof:name":"Slb",
    "wof:placetype":"venue"
},
  "geometry": {"coordinates":[4.716607,52.036201],"type":"Point"}
}