{
  "type": "Feature",
  "properties": {
    "addr:full":"Parklaan 11 Sittard Limburg 6131 KE",
    "addr:housenumber":"11",
    "addr:postcode":"6131 ke",
    "addr:street":"Parklaan",
    "iso:country":"NL",
    "sg:address":"Parklaan 11",
    "sg:city":"Sittard",
    "sg:orig_category":"Verzekeringen",
    "sg:phone":"+31 46 451 3417",
    "sg:postcode":"6131 KE",
    "sg:province":"Limburg",
    "wof:name":"Assurantiekantoor P J M Moling",
    "wof:placetype":"venue"
},
  "geometry": {"coordinates":[5.864537,50.997623],"type":"Point"}
}