{
  "type": "Feature",
  "properties": {
    "addr:full":"Bredestr 35 Maastricht Limburg 6211 HB",
    "addr:housenumber":"35",
    "addr:postcode":"6211 hb",
    "addr:street":"Bredestr",
    "iso:country":"NL",
    "sg:address":"Bredestr 35",
    "sg:city":"Maastricht",
    "sg:orig_category":"Babyartikelen",
    "sg:phone":"+31 43 327 0532",
    "sg:postcode":"6211 HB",
    "sg:province":"Limburg",
    "sg:website":"http://www.sterre-en-tijl.nl",
    "wof:name":"Sterre & Tijl",
    "wof:placetype":"venue"
},
  "geometry": {"coordinates":[5.689761,50.848122],"type":"Point"}
}