{
  "type": "Feature",
  "properties": {
    "addr:full":"Beemdstraat 23 Eindhoven Noord-Brabant 5653 MA",
    "addr:housenumber":"23",
    "addr:postcode":"5653 ma",
    "addr:street":"Beemdstraat",
    "iso:country":"NL",
    "sg:address":"Beemdstraat 23",
    "sg:city":"Eindhoven",
    "sg:orig_category":"Farmaceutische Producten Gh",
    "sg:phone":"+31 40 250 2050",
    "sg:postcode":"5653 MA",
    "sg:province":"Noord-Brabant",
    "wof:name":"Occam International Bv",
    "wof:placetype":"venue"
},
  "geometry": {"coordinates":[5.448376,51.428932],"type":"Point"}
}