{
  "type": "Feature",
  "properties": {
    "addr:full":"Offenweg 101 Noordwijk Zh South Holland 2201 HC",
    "addr:housenumber":"101",
    "addr:postcode":"zh;2201 hc",
    "iso:country":"NL",
    "sg:address":"Offenweg 101",
    "sg:city":"Noordwijk Zh",
    "sg:orig_category":"Kantoorartikelen",
    "sg:phone":"+31 71 362 9167",
    "sg:postcode":"2201 HC",
    "sg:province":"South Holland",
    "wof:name":"Beamerrent Nederland",
    "wof:placetype":"venue"
},
  "geometry": {"coordinates":[4.4476938248,52.2311897278],"type":"Point"}
}