{
  "type": "Feature",
  "properties": {
    "addr:full":"Heuvel Galerie 116 Eindhoven Noord-Brabant 5611 DK",
    "addr:housenumber":"116",
    "addr:postcode":"5611 dk",
    "addr:street":"Heuvel Galerie",
    "iso:country":"NL",
    "sg:address":"Heuvel Galerie 116",
    "sg:city":"Eindhoven",
    "sg:orig_category":"Herenkleding",
    "sg:phone":"+31 40 246 4474",
    "sg:postcode":"5611 DK",
    "sg:province":"Noord-Brabant",
    "wof:name":"Hom By Topman",
    "wof:placetype":"venue"
},
  "geometry": {"coordinates":[5.47965,51.439102],"type":"Point"}
}