{
  "type": "Feature",
  "properties": {
    "addr:full":"Ijsseldijk 220 Krimpen A/D Ijssel Zuid-Holland 2924 AZ",
    "addr:housenumber":"220;a / d",
    "addr:postcode":"2924 az",
    "addr:street":"Ijsseldijk",
    "iso:country":"NL",
    "sg:address":"Ijsseldijk 220",
    "sg:city":"Krimpen A/D Ijssel",
    "sg:orig_category":"Architecten",
    "sg:phone":"+31 180 518 800",
    "sg:postcode":"2924 AZ",
    "sg:province":"Zuid-Holland",
    "wof:name":"Architectenbureau Kasbergen",
    "wof:placetype":"venue"
},
  "geometry": {"coordinates":[4.598734,51.92411],"type":"Point"}
}