{
  "type": "Feature",
  "properties": {
    "addr:full":"Buitenvest 32 Geertruidenberg Noord-Brabant 4931 CH",
    "addr:housenumber":"32",
    "addr:postcode":"4931",
    "addr:street":"Buitenvest",
    "iso:country":"NL",
    "sg:address":"Buitenvest 32",
    "sg:city":"Geertruidenberg",
    "sg:orig_category":"Platenmaatschappijen",
    "sg:phone":"+31 162 570 064",
    "sg:postcode":"4931 CH",
    "sg:province":"Noord-Brabant",
    "wof:name":"Vianet Bv",
    "wof:placetype":"venue"
},
  "geometry": {"coordinates":[4.847567,51.698486],"type":"Point"}
}