{
  "type": "Feature",
  "properties": {
    "iso:country":"NL",
    "sg:address":"Golfwg 18",
    "sg:city":"Noordwyk Zh",
    "sg:orig_category":"Bloemen En Planten - Groothandel",
    "sg:phone":"+31 71 364 6062",
    "sg:postcode":"2202 JK",
    "sg:province":"South Holland",
    "wof:name":"Ridder Varkevisser, De",
    "wof:placetype":"venue"
},
  "geometry": {"coordinates":[4.435115,52.246437],"type":"Point"}
}