{
  "type": "Feature",
  "properties": {
    "addr:full":"Koperstr 10 Vaals North Rhine-Westphalia 6291 AJ",
    "addr:housenumber":"10",
    "addr:postcode":"6291 aj",
    "addr:street":"Koperstr",
    "iso:country":"NL",
    "sg:address":"Koperstr 10",
    "sg:city":"Vaals",
    "sg:orig_category":"Glazenwasserijen",
    "sg:phone":"+31 43 306 1665",
    "sg:postcode":"6291 AJ",
    "sg:province":"North Rhine-Westphalia",
    "wof:name":"Kohlen-Frederiks Vof",
    "wof:placetype":"venue"
},
  "geometry": {"coordinates":[6.021042,50.771503],"type":"Point"}
}