{
  "type": "Feature",
  "properties": {
    "addr:full":"Acaciahage 21-23 Stadskanaal Groningen 9501 WD",
    "addr:housenumber":"21-23",
    "addr:postcode":"stadskanaal;9501 wd",
    "addr:street":"Acaciahage",
    "iso:country":"NL",
    "sg:address":"Acaciahage 21-23",
    "sg:city":"Stadskanaal",
    "sg:orig_category":"Scholen Voor Basisonderwijs",
    "sg:phone":"+31 599 613 310",
    "sg:postcode":"9501 WD",
    "sg:province":"Groningen",
    "wof:name":"Hagenhof Obs",
    "wof:placetype":"venue"
},
  "geometry": {"coordinates":[6.965382,52.983612],"type":"Point"}
}