{
  "type": "Feature",
  "properties": {
    "addr:full":"Voetboogstr 26 Amsterdam North Holland 1012 XL",
    "addr:housenumber":"26",
    "addr:postcode":"1012 xl",
    "addr:street":"Voetboogstr",
    "iso:country":"NL",
    "sg:address":"Voetboogstr 26",
    "sg:city":"Amsterdam",
    "sg:orig_category":"Organisatiebureaus",
    "sg:phone":"+31 20 626 2890",
    "sg:postcode":"1012 XL",
    "sg:province":"North Holland",
    "wof:name":"Voster Events",
    "wof:placetype":"venue"
},
  "geometry": {"coordinates":[4.8907499313,52.3678321838],"type":"Point"}
}