{
  "type": "Feature",
  "properties": {
    "iso:country":"NL",
    "sg:address":"Wilhelminastraat 65",
    "sg:city":"Bodegraven",
    "sg:orig_category":"Wasmachines En Wasdrogers - Onderhoud En Reparatie",
    "sg:phone":"+31 172 617 952",
    "sg:postcode":"2411 CX",
    "sg:province":"Zuid-Holland",
    "wof:name":"Neut, H Van Der",
    "wof:placetype":"venue"
},
  "geometry": {"coordinates":[4.7475471497,52.0855522156],"type":"Point"}
}