{
  "type": "Feature",
  "properties": {
    "iso:country":"NL",
    "sg:address":"Dr Ringersstr 6",
    "sg:city":"Waalwyk",
    "sg:orig_category":"Plafonds",
    "sg:phone":"+31 416 348 779",
    "sg:postcode":"5144 RZ",
    "sg:province":"Noord-Brabant",
    "sg:website":"http://www.vossenbergafbouw.nl",
    "wof:name":"Vossenberg Afbouw",
    "wof:placetype":"venue"
},
  "geometry": {"coordinates":[5.073277,51.680977],"type":"Point"}
}