{
  "type": "Feature",
  "properties": {
    "addr:full":"Bosboom Toussaintstraat 50 Amsterdam Noord-Holland 1054  A",
    "addr:housenumber":"50;1054 a",
    "addr:street":"Bosboom Toussaintstraat",
    "iso:country":"NL",
    "sg:address":"Bosboom Toussaintstraat 50",
    "sg:city":"Amsterdam",
    "sg:orig_category":"Wasserettes And Stomerijen",
    "sg:phone":"+31 20 616 0199",
    "sg:postcode":"1054  A",
    "sg:province":"Noord-Holland",
    "wof:name":"Wassalon Bosboom",
    "wof:placetype":"venue"
},
  "geometry": {"coordinates":[4.8753099442,52.3654251099],"type":"Point"}
}