{
  "type": "Feature",
  "properties": {
    "addr:full":"Dorpsstraat 31 Hellendoorn Overijssel 7447 CM",
    "addr:housenumber":"31",
    "addr:postcode":"7447 cm",
    "addr:street":"Dorpsstraat",
    "iso:country":"NL",
    "sg:address":"Dorpsstraat 31",
    "sg:city":"Hellendoorn",
    "sg:orig_category":"Huishoudapparatuur, Televisies And Radio'S",
    "sg:phone":"+31 548 654 220",
    "sg:postcode":"7447 CM",
    "sg:province":"Overijssel",
    "wof:name":"Novy Stobbelaar-Broeze",
    "wof:placetype":"venue"
},
  "geometry": {"coordinates":[6.449285,52.38826],"type":"Point"}
}