{
  "type": "Feature",
  "properties": {
    "addr:full":"Westerstr 71 Enkhuizen North Holland 1601 AC",
    "addr:housenumber":"71",
    "addr:postcode":"1601 ac",
    "addr:street":"Westerstr",
    "iso:country":"NL",
    "sg:address":"Westerstr 71",
    "sg:city":"Enkhuizen",
    "sg:orig_category":"Kaas",
    "sg:phone":"+31 228 319 707",
    "sg:postcode":"1601 AC",
    "sg:province":"North Holland",
    "sg:website":"http://www.edwindegraaff.com",
    "wof:name":"Graaff, Edwin De",
    "wof:placetype":"venue"
},
  "geometry": {"coordinates":[5.2905449867,52.7038497925],"type":"Point"}
}