{
  "type": "Feature",
  "properties": {
    "addr:full":"Industrieweg 102 Berkel En Rodenrijs South Holland 2651 BD",
    "addr:housenumber":"102",
    "addr:postcode":"2651 bd",
    "addr:street":"Industrieweg",
    "iso:country":"NL",
    "sg:address":"Industrieweg 102",
    "sg:city":"Berkel En Rodenrijs",
    "sg:orig_category":"Kantoorartikelen",
    "sg:phone":"+31 10 511 4727",
    "sg:postcode":"2651 BD",
    "sg:province":"South Holland",
    "wof:name":"Ton Wooning Kantoormeubelen",
    "wof:placetype":"venue"
},
  "geometry": {"coordinates":[4.4565172195,51.9806976318],"type":"Point"}
}