{
  "type": "Feature",
  "properties": {
    "iso:country":"NL",
    "sg:address":"Oostzeedijk Beneden 241",
    "sg:city":"Rotterdam",
    "sg:orig_category":"Werving And Selectie Van Tijdelijk Personeel And Uitzendkantoren",
    "sg:phone":"+31 10 404 7337",
    "sg:postcode":"3061 VW",
    "sg:province":"South Holland",
    "wof:name":"Jmw",
    "wof:placetype":"venue"
},
  "geometry": {"coordinates":[4.5010399818,51.9228210449],"type":"Point"}
}