{
  "type": "Feature",
  "properties": {
    "iso:country":"NL",
    "sg:address":"De Praets 35",
    "sg:city":"Arnhem",
    "sg:orig_category":"Binnenvaart",
    "sg:phone":"+31 26 322 9439",
    "sg:postcode":"6841 HD",
    "sg:province":"Gelderland",
    "wof:name":"Rederij Scheers Bv",
    "wof:placetype":"venue"
},
  "geometry": {"coordinates":[5.898017,51.979122],"type":"Point"}
}