{
  "type": "Feature",
  "properties": {
    "addr:full":"Raadhuisstraat 14 Hengelo Gld Gelderland 7255 BM",
    "addr:housenumber":"14",
    "addr:postcode":"7255 bm",
    "addr:street":"Raadhuisstraat",
    "iso:country":"NL",
    "sg:address":"Raadhuisstraat 14",
    "sg:city":"Hengelo Gld",
    "sg:orig_category":"Huishoudapparatuur, Televisies And Radio'S",
    "sg:phone":"+31 575 464 261",
    "sg:postcode":"7255 BM",
    "sg:province":"Gelderland",
    "wof:name":"Expert Arendsen",
    "wof:placetype":"venue"
},
  "geometry": {"coordinates":[6.309102,52.052013],"type":"Point"}
}