{
  "type": "Feature",
  "properties": {
    "addr:full":"Burg V Royensngl 18 Zwolle Overijssel 8011 CT",
    "addr:housenumber":"18",
    "addr:postcode":"8011 ct",
    "addr:street":"Burg V Royensngl",
    "iso:country":"NL",
    "sg:address":"Burg V Royensngl 18",
    "sg:city":"Zwolle",
    "sg:orig_category":"Adviesbureaus Bedrijfsorganisatie",
    "sg:phone":"+31 38 421 8456",
    "sg:postcode":"8011 CT",
    "sg:province":"Overijssel",
    "wof:name":"Claassen Moolenbeek & Partners",
    "wof:placetype":"venue"
},
  "geometry": {"coordinates":[6.088738,52.512566],"type":"Point"}
}