{
  "type": "Feature",
  "properties": {
    "addr:full":"Julianastraat 33 Heikant Zeeland 4566 AC",
    "addr:housenumber":"33",
    "addr:postcode":"4566 ac",
    "addr:street":"Julianastraat",
    "iso:country":"NL",
    "sg:address":"Julianastraat 33",
    "sg:city":"Heikant",
    "sg:orig_category":"Kappers",
    "sg:phone":"+31 114 319 242",
    "sg:postcode":"4566 AC",
    "sg:province":"Zeeland",
    "wof:name":"La Creature",
    "wof:placetype":"venue"
},
  "geometry": {"coordinates":[4.021037,51.249104],"type":"Point"}
}