{
  "type": "Feature",
  "properties": {
    "addr:full":"Mecklenburgstr 28 Breukelen Ut Utrecht 3621 GP",
    "addr:housenumber":"28",
    "addr:postcode":"3621 gp",
    "addr:street":"Mecklenburgstr",
    "iso:country":"NL",
    "sg:address":"Mecklenburgstr 28",
    "sg:city":"Breukelen Ut",
    "sg:orig_category":"Autorijscholen",
    "sg:phone":"+31 346 261 271",
    "sg:postcode":"3621 GP",
    "sg:province":"Utrecht",
    "wof:name":"Meerkerk",
    "wof:placetype":"venue"
},
  "geometry": {"coordinates":[5.000494,52.173389],"type":"Point"}
}