{
  "type": "Feature",
  "properties": {
    "addr:full":"Emmastraat 31 Groningen Groningen 9722 EW",
    "addr:housenumber":"31",
    "addr:postcode":"9722 ew",
    "addr:street":"Emmastraat",
    "iso:country":"NL",
    "sg:address":"Emmastraat 31",
    "sg:city":"Groningen",
    "sg:orig_category":"Boekenuitgeverijen",
    "sg:phone":"+31 50 526 5559",
    "sg:postcode":"9722 EW",
    "sg:province":"Groningen",
    "wof:name":"Benjamin & Partners Art Books Bv",
    "wof:placetype":"venue"
},
  "geometry": {"coordinates":[6.5826,53.198215],"type":"Point"}
}