{
  "type": "Feature",
  "properties": {
    "iso:country":"NL",
    "sg:address":"Meridiaan 40",
    "sg:city":"Amersfoort",
    "sg:orig_category":"Levensmiddelen - Fabrieken En Groothandel",
    "sg:phone":"+31 33 479 0286",
    "sg:postcode":"3813 AW",
    "sg:province":"Utrecht",
    "wof:name":"Matrico Eur Bv",
    "wof:placetype":"venue"
},
  "geometry": {"coordinates":[5.385445,52.165089],"type":"Point"}
}