{
  "type": "Feature",
  "properties": {
    "addr:full":"Weth Schimmelln 2 Barneveld Gelderland 3771 KW",
    "addr:housenumber":"2",
    "addr:postcode":"3771 kw",
    "addr:street":"Weth Schimmelln;Gelderland",
    "iso:country":"NL",
    "sg:address":"Weth Schimmelln 2",
    "sg:city":"Barneveld",
    "sg:orig_category":"Mensendieck - Oefentherapeuten",
    "sg:phone":"+31 342 416 545",
    "sg:postcode":"3771 KW",
    "sg:province":"Gelderland",
    "wof:name":"Kempen-Nijhof, J L J",
    "wof:placetype":"venue"
},
  "geometry": {"coordinates":[5.583418,52.151054],"type":"Point"}
}