{
  "type": "Feature",
  "properties": {
    "iso:country":"NL",
    "sg:address":"Galvanistr 17",
    "sg:city":"Nykerk Gld",
    "sg:orig_category":"Wijnkoperijen En -Groothandel",
    "sg:phone":"+31 33 254 2130",
    "sg:postcode":"3861 NJ",
    "sg:province":"Gelderland",
    "wof:name":"Intercaves Bv",
    "wof:placetype":"venue"
},
  "geometry": {"coordinates":[5.4695448875,52.2368392944],"type":"Point"}
}