{
  "type": "Feature",
  "properties": {
    "addr:full":"Montagewg 28 Nieuwegein Utrecht 3433 NT",
    "addr:housenumber":"28",
    "addr:postcode":"3433 nt",
    "addr:street":"Montagewg",
    "iso:country":"NL",
    "sg:address":"Montagewg 28",
    "sg:city":"Nieuwegein",
    "sg:orig_category":"Wolartikelen En Breiwol - Fabrieken En Groothandel",
    "sg:phone":"+31 30 606 1991",
    "sg:postcode":"3433 NT",
    "sg:province":"Utrecht",
    "wof:name":"Markoma Bv",
    "wof:placetype":"venue"
},
  "geometry": {"coordinates":[5.1048598289,52.0139007568],"type":"Point"}
}