{
  "type": "Feature",
  "properties": {
    "addr:full":"Herengracht 420 Amsterdam Noord-Holland 1017 BZ",
    "addr:housenumber":"420",
    "addr:postcode":"1017 bz",
    "addr:street":"Herengracht",
    "iso:country":"NL",
    "sg:address":"Herengracht 420",
    "sg:city":"Amsterdam",
    "sg:orig_category":"Boekhouders",
    "sg:phone":"+31 20 623 6991",
    "sg:postcode":"1017 BZ",
    "sg:province":"Noord-Holland",
    "wof:name":"Bv Trustkantoor Intermediair",
    "wof:placetype":"venue"
},
  "geometry": {"coordinates":[4.887582,52.366776],"type":"Point"}
}