{
  "type": "Feature",
  "properties": {
    "iso:country":"NL",
    "sg:address":"Binnenban 81",
    "sg:city":"Hoogvliet Rt",
    "sg:orig_category":"Kappers",
    "sg:phone":"+31 10 416 9872",
    "sg:postcode":"3191 CB",
    "sg:province":"Zuid-Holland",
    "wof:name":"H.R. Elkerbout",
    "wof:placetype":"venue"
},
  "geometry": {"coordinates":[4.3547291756,51.8652305603],"type":"Point"}
}