{
  "type": "Feature",
  "properties": {
    "addr:full":"Thamerln 7 Uithoorn Noord-Holland 1421 XX",
    "addr:housenumber":"7",
    "addr:postcode":"1421 xx",
    "addr:street":"Thamerln",
    "iso:country":"NL",
    "sg:address":"Thamerln 7",
    "sg:city":"Uithoorn",
    "sg:orig_category":"Schilders",
    "sg:phone":"+31 297 567 784",
    "sg:postcode":"1421 XX",
    "sg:province":"Noord-Holland",
    "wof:name":"Bunning, Schildersbedrijf",
    "wof:placetype":"venue"
},
  "geometry": {"coordinates":[4.829042,52.23394],"type":"Point"}
}