{
  "type": "Feature",
  "properties": {
    "addr:full":"A V Leeuwenhoekwg 24 Drunen North Brabant 5151 DV",
    "addr:housenumber":"24",
    "addr:postcode":"5151 dv",
    "addr:street":"A;Leeuwenhoekwg",
    "iso:country":"NL",
    "sg:address":"A V Leeuwenhoekwg 24",
    "sg:city":"Drunen",
    "sg:orig_category":"Orthopedagogen",
    "sg:phone":"+31 416 650 882",
    "sg:postcode":"5151 DV",
    "sg:province":"North Brabant",
    "wof:name":"Pedagogisch Hulp- & Adviesbur",
    "wof:placetype":"venue"
},
  "geometry": {"coordinates":[5.1401047707,51.6867485046],"type":"Point"}
}