{
  "type": "Feature",
  "properties": {
    "addr:full":"Schadeken 191 Leidschendam Zuid-Holland 2264 KL",
    "addr:housenumber":"191",
    "addr:postcode":"2264 kl",
    "addr:street":"Schadeken",
    "iso:country":"NL",
    "sg:address":"Schadeken 191",
    "sg:city":"Leidschendam",
    "sg:orig_category":"Evenementenverzorging",
    "sg:phone":"+31 70 320 8220",
    "sg:postcode":"2264 KL",
    "sg:province":"Zuid-Holland",
    "wof:name":"Artimusic",
    "wof:placetype":"venue"
},
  "geometry": {"coordinates":[4.400912,52.090225],"type":"Point"}
}