{
  "type": "Feature",
  "properties": {
    "addr:full":"Rode Klaver 34 Krimpen Ad Yssel Zuid-Holland 2923 GH",
    "addr:housenumber":"34",
    "addr:postcode":"2923 gh",
    "addr:street":"Rode Klaver",
    "iso:country":"NL",
    "sg:address":"Rode Klaver 34",
    "sg:city":"Krimpen Ad Yssel",
    "sg:classifiers":[
        {
            "category":"Personal",
            "subcategory":"Nail Salon",
            "type":"Services"
        }
    ],
    "sg:phone":"+31 180 513 584",
    "sg:postcode":"2923 GH",
    "sg:province":"Zuid-Holland",
    "sg:tags":[
        "pedicure"
    ],
    "wof:name":"Herk-Van Den Heerik, J",
    "wof:placetype":"venue"
},
  "geometry": {"coordinates":[4.606721,51.913307],"type":"Point"}
}