{
  "type": "Feature",
  "properties": {
    "iso:country":"NL",
    "sg:address":"Hoofdstr 105",
    "sg:city":"Noordbroek",
    "sg:orig_category":"Fietsen En Bromfietsen",
    "sg:phone":"+31 598 451 797",
    "sg:postcode":"9635 AV",
    "sg:province":"Groningen",
    "wof:name":"Buurke, G",
    "wof:placetype":"venue"
},
  "geometry": {"coordinates":[6.873072,53.200417],"type":"Point"}
}