{
  "type": "Feature",
  "properties": {
    "addr:full":"St Rochuspln 10 Berg En Terblyt Limburg 6325 AZ",
    "addr:housenumber":"10",
    "addr:postcode":"6325",
    "addr:street":"Berg",
    "iso:country":"NL",
    "sg:address":"St Rochuspln 10",
    "sg:city":"Berg En Terblyt",
    "sg:orig_category":"Verf En Lak - Fabrieken En Groothandel",
    "sg:phone":"+31 43 604 0204",
    "sg:postcode":"6325 AZ",
    "sg:province":"Limburg",
    "wof:name":"Gerdon Coatings Verfcentrum",
    "wof:placetype":"venue"
},
  "geometry": {"coordinates":[5.810365,50.857407],"type":"Point"}
}