{
  "type": "Feature",
  "properties": {
    "iso:country":"NL",
    "sg:address":"Marktstr 84",
    "sg:city":"Musselkanaal",
    "sg:orig_category":"Fietsen En Bromfietsen",
    "sg:phone":"+31 599 412 145",
    "sg:postcode":"9581 AD",
    "sg:province":"Groningen",
    "sg:website":"http://www.rolfesrijwielen.nl",
    "wof:name":"Rolfes Rijwielen",
    "wof:placetype":"venue"
},
  "geometry": {"coordinates":[7.015449,52.928844],"type":"Point"}
}