{
  "type": "Feature",
  "properties": {
    "iso:country":"NL",
    "sg:address":"Oosteinderwg 415",
    "sg:city":"Aalsmeer",
    "sg:orig_category":"Boekbinderijen",
    "sg:phone":"+31 297 324 580",
    "sg:postcode":"1432 BH",
    "sg:province":"Noord-Holland",
    "wof:name":"Josuma",
    "wof:placetype":"venue"
},
  "geometry": {"coordinates":[4.802878,52.286224],"type":"Point"}
}