{
  "type": "Feature",
  "properties": {
    "addr:full":"Postbus 18663 S Gravenhage South Holland 2502 ER",
    "addr:housenumber":"18663",
    "addr:postcode":"2502 er",
    "addr:street":"Postbus;S Gravenhage",
    "iso:country":"NL",
    "sg:address":"Postbus 18663",
    "sg:city":"S Gravenhage",
    "sg:orig_category":"Adviesbureaus Bedrijfsorganisatie",
    "sg:phone":"+31 6 23413890",
    "sg:postcode":"2502 ER",
    "sg:province":"South Holland",
    "wof:name":"Mccoaster",
    "wof:placetype":"venue"
},
  "geometry": {"coordinates":[4.31361,52.07832],"type":"Point"}
}