{
  "type": "Feature",
  "properties": {
    "addr:full":"Oranjeln 22 Groenekan Utrecht 3737 AT",
    "addr:housenumber":"22",
    "addr:postcode":"3737",
    "addr:street":"Oranjeln",
    "iso:country":"NL",
    "sg:address":"Oranjeln 22",
    "sg:city":"Groenekan",
    "sg:orig_category":"Peuterspeelzalen",
    "sg:phone":"+31 346 211 498",
    "sg:postcode":"3737 AT",
    "sg:province":"Utrecht",
    "wof:name":"Groentjes, De",
    "wof:placetype":"venue"
},
  "geometry": {"coordinates":[5.147357,52.122284],"type":"Point"}
}