{
  "type": "Feature",
  "properties": {
    "addr:full":"Eeneind 50 Nuenen Noord-Brabant 5674 VP",
    "addr:housenumber":"50",
    "addr:postcode":"5674 vp",
    "addr:street":"Eeneind",
    "iso:country":"NL",
    "sg:address":"Eeneind 50",
    "sg:city":"Nuenen",
    "sg:orig_category":"Schilderwerk",
    "sg:phone":"+31 40 295 2009",
    "sg:postcode":"5674 VP",
    "sg:province":"Noord-Brabant",
    "wof:name":"Hemme Vof",
    "wof:placetype":"venue"
},
  "geometry": {"coordinates":[5.547924,51.448959],"type":"Point"}
}