{
  "type": "Feature",
  "properties": {
    "addr:full":"Langakker 5 Ravenstein North Brabant 5371 EV",
    "addr:housenumber":"5",
    "addr:postcode":"5371 ev",
    "addr:street":"Langakker",
    "iso:country":"NL",
    "sg:address":"Langakker 5",
    "sg:city":"Ravenstein",
    "sg:orig_category":"Bedrijfs- And Managementsconsultants",
    "sg:phone":"+31 485 397 561",
    "sg:postcode":"5371 EV",
    "sg:province":"North Brabant",
    "wof:name":"Targa Training Bv",
    "wof:placetype":"venue"
},
  "geometry": {"coordinates":[5.603069,51.811909],"type":"Point"}
}