{
  "type": "Feature",
  "properties": {
    "iso:country":"NL",
    "sg:address":"Westerln 10",
    "sg:city":"Rotterdam",
    "sg:orig_category":"Adviesbureaus",
    "sg:phone":"+31 10 464 2700",
    "sg:postcode":"3016 CK",
    "sg:province":"Zuid-Holland",
    "wof:name":"Trag",
    "wof:placetype":"venue"
},
  "geometry": {"coordinates":[4.478455,51.922836],"type":"Point"}
}