{
  "type": "Feature",
  "properties": {
    "iso:country":"NL",
    "sg:address":"Zadelmaker 113",
    "sg:city":"Nieuw Vennep",
    "sg:orig_category":"Administratie- En Boekhoudkantoren",
    "sg:phone":"+31 252 621 361",
    "sg:postcode":"2152 LP",
    "sg:province":"Noord-Holland",
    "wof:name":"Deno",
    "wof:placetype":"venue"
},
  "geometry": {"coordinates":[4.639525,52.26952],"type":"Point"}
}