{
  "type": "Feature",
  "properties": {
    "iso:country":"NL",
    "sg:address":"Knipstraat 37",
    "sg:city":"Wijlre",
    "sg:orig_category":"Kappers",
    "sg:phone":"+31 43 450 1973",
    "sg:postcode":"6321 AM",
    "sg:province":"Limburg",
    "wof:name":"Kapsalon Ligne",
    "wof:placetype":"venue"
},
  "geometry": {"coordinates":[5.9006481171,50.821182251],"type":"Point"}
}