{
  "type": "Feature",
  "properties": {
    "addr:full":"Schoolstr 11 Belfeld Limburg 5951 CJ",
    "addr:housenumber":"11",
    "addr:postcode":"5951 cj",
    "addr:street":"Schoolstr",
    "iso:country":"NL",
    "sg:address":"Schoolstr 11",
    "sg:city":"Belfeld",
    "sg:orig_category":"Zalenverhuur",
    "sg:phone":"+31 77 475 2733",
    "sg:postcode":"5951 CJ",
    "sg:province":"Limburg",
    "wof:name":"Trefpunt, Caf?-Zaal 'T",
    "wof:placetype":"venue"
},
  "geometry": {"coordinates":[6.113237,51.312733],"type":"Point"}
}