{
  "type": "Feature",
  "properties": {
    "addr:full":"Lange Nering 41 Emmeloord Flevoland 8302 EA",
    "addr:housenumber":"41",
    "addr:postcode":"8302 ea",
    "addr:street":"Lange Nering;Flevoland",
    "iso:country":"NL",
    "sg:address":"Lange Nering 41",
    "sg:city":"Emmeloord",
    "sg:orig_category":"Hypotheken And Hypotheekbanken",
    "sg:phone":"+31 527 611 109",
    "sg:postcode":"8302 EA",
    "sg:province":"Flevoland",
    "wof:name":"Fdc",
    "wof:placetype":"venue"
},
  "geometry": {"coordinates":[5.756375,52.711468],"type":"Point"}
}