{
  "type": "Feature",
  "properties": {
    "iso:country":"NL",
    "sg:address":"Boonswg 57",
    "sg:city":"Heinenoord",
    "sg:orig_category":"Onroerende Goederen",
    "sg:phone":"+31 186 601 000",
    "sg:postcode":"3274 LH",
    "sg:province":"Zuid-Holland",
    "sg:website":"http://www.amzevenbergen.nl",
    "wof:name":"Zevenbergen, A M",
    "wof:placetype":"venue"
},
  "geometry": {"coordinates":[4.521932,51.815945],"type":"Point"}
}