{
  "type": "Feature",
  "properties": {
    "addr:full":"Kampbrugweg 1 Beuningen Ov Overijssel 7588 RK",
    "addr:housenumber":"1",
    "addr:postcode":"7588 rk",
    "addr:street":"Kampbrugweg;Ov",
    "iso:country":"NL",
    "sg:address":"Kampbrugweg 1",
    "sg:city":"Beuningen Ov",
    "sg:orig_category":"Verhuur Gereedschapsmachines And Gereedschappen",
    "sg:phone":"+31 541 351 534",
    "sg:postcode":"7588 RK",
    "sg:province":"Overijssel",
    "wof:name":"Twents Huifkar Verhuurbedrijf",
    "wof:placetype":"venue"
},
  "geometry": {"coordinates":[7.009733,52.353142],"type":"Point"}
}