{
  "type": "Feature",
  "properties": {
    "addr:full":"Mackayln 19 Eindhoven North Brabant 5631 NM",
    "addr:housenumber":"19",
    "addr:postcode":"5631",
    "addr:street":"Mackayln",
    "iso:country":"NL",
    "sg:address":"Mackayln 19",
    "sg:city":"Eindhoven",
    "sg:orig_category":"Muziekinstrumenten En Bladmuziek",
    "sg:phone":"+31 40 281 5394",
    "sg:postcode":"5631 NM",
    "sg:province":"North Brabant",
    "wof:name":"Antique Musical Instrument",
    "wof:placetype":"venue"
},
  "geometry": {"coordinates":[5.50844,51.45776],"type":"Point"}
}