{
  "type": "Feature",
  "properties": {
    "addr:full":"Noorderwg 4 Leeuwarden Provincie Friesland 8911 ES",
    "addr:housenumber":"4",
    "addr:postcode":"8911 es",
    "addr:street":"Noorderwg;Provincie Friesland",
    "iso:country":"NL",
    "sg:address":"Noorderwg 4",
    "sg:city":"Leeuwarden",
    "sg:orig_category":"Juridische Adviseurs",
    "sg:phone":"+31 58 299 1428",
    "sg:postcode":"8911 ES",
    "sg:province":"Provincie Friesland",
    "sg:website":"http://www.huisjurist.nl",
    "wof:name":"Tuin Consultancy, H Van Der",
    "wof:placetype":"venue"
},
  "geometry": {"coordinates":[5.798885,53.205322],"type":"Point"}
}