{
  "type": "Feature",
  "properties": {
    "addr:full":"Zwanenveld 9050 Nijmegen Gelderland 6538 SB",
    "addr:housenumber":"9050",
    "addr:postcode":"6538 sb",
    "addr:street":"Zwanenveld;Gelderland",
    "iso:country":"NL",
    "sg:address":"Zwanenveld 9050",
    "sg:city":"Nijmegen",
    "sg:classifiers":[
        {
            "category":"Retail",
            "subcategory":"Photofinishing",
            "type":"Services"
        }
    ],
    "sg:phone":"+31 24 344 0180",
    "sg:postcode":"6538 SB",
    "sg:province":"Gelderland",
    "sg:tags":[
        "foto",
        "film"
    ],
    "wof:name":"Foto Roos",
    "wof:placetype":"venue"
},
  "geometry": {"coordinates":[5.795219,51.822693],"type":"Point"}
}