{
  "type": "Feature",
  "properties": {
    "iso:country":"NL",
    "sg:address":"De Paldert 58",
    "sg:city":"Klazienaveen",
    "sg:orig_category":"Voegwerken",
    "sg:phone":"+31 591 316 540",
    "sg:postcode":"7891 SL",
    "sg:province":"Provincie Drenthe",
    "wof:name":"Wanders Bv",
    "wof:placetype":"venue"
},
  "geometry": {"coordinates":[6.981803,52.72007],"type":"Point"}
}