{
  "type": "Feature",
  "properties": {
    "iso:country":"NL",
    "sg:address":"Satellietstr 6",
    "sg:city":"Dordrecht",
    "sg:orig_category":"Grafisch Ontwerpers",
    "sg:phone":"+31 78 617 4196",
    "sg:postcode":"3328 GL",
    "sg:province":"Zuid-Holland",
    "wof:name":"Kaptein",
    "wof:placetype":"venue"
},
  "geometry": {"coordinates":[4.677368,51.780338],"type":"Point"}
}