{
  "type": "Feature",
  "properties": {
    "addr:full":"Espakker 126 Teteringen North Brabant 4847 HB",
    "addr:housenumber":"126",
    "addr:postcode":"4847 hb",
    "addr:street":"Espakker",
    "iso:country":"NL",
    "sg:address":"Espakker 126",
    "sg:city":"Teteringen",
    "sg:orig_category":"Boekhandels",
    "sg:phone":"+31 76 571 9550",
    "sg:postcode":"4847 HB",
    "sg:province":"North Brabant",
    "wof:name":"Media Expresse",
    "wof:placetype":"venue"
},
  "geometry": {"coordinates":[4.814213,51.60918],"type":"Point"}
}