{
  "type": "Feature",
  "properties": {
    "addr:full":"Fokkerhof 76 Tilburg Noord-Brabant 5025 DR",
    "addr:housenumber":"76",
    "addr:postcode":"5025 dr",
    "addr:street":"Fokkerhof",
    "iso:country":"NL",
    "sg:address":"Fokkerhof 76",
    "sg:city":"Tilburg",
    "sg:orig_category":"Vertalers",
    "sg:phone":"+31 13 544 0397",
    "sg:postcode":"5025 DR",
    "sg:province":"Noord-Brabant",
    "wof:name":"Wordsupport",
    "wof:placetype":"venue"
},
  "geometry": {"coordinates":[5.073592,51.550041],"type":"Point"}
}