{
  "type": "Feature",
  "properties": {
    "addr:full":"Ariens 65 Avenhorn North Holland 1633 HH",
    "addr:housenumber":"65",
    "addr:postcode":"1633 hh",
    "addr:street":"Ariens",
    "iso:country":"NL",
    "sg:address":"Ariens 65",
    "sg:city":"Avenhorn",
    "sg:orig_category":"Goederenvervoer Over De Weg",
    "sg:phone":"+31 229 544 117",
    "sg:postcode":"1633 HH",
    "sg:province":"North Holland",
    "wof:name":"Transportbedrijf P Visser",
    "wof:placetype":"venue"
},
  "geometry": {"coordinates":[4.95684,52.619888],"type":"Point"}
}