{
  "type": "Feature",
  "properties": {
    "addr:full":"Prinsenbaan 106 Koningsbosch Limburg 6104 BH",
    "addr:housenumber":"106",
    "addr:postcode":"6104 bh",
    "addr:street":"Prinsenbaan",
    "iso:country":"NL",
    "sg:address":"Prinsenbaan 106",
    "sg:city":"Koningsbosch",
    "sg:orig_category":"Bloemen And Planten",
    "sg:phone":"+31 475 301 554",
    "sg:postcode":"6104 BH",
    "sg:province":"Limburg",
    "wof:name":"P.J.H. Von Lumich",
    "wof:placetype":"venue"
},
  "geometry": {"coordinates":[5.962818,51.057335],"type":"Point"}
}