{
  "type": "Feature",
  "properties": {
    "addr:full":"Hupselsewg 80 Eibergen Gelderland 7151 NP",
    "addr:housenumber":"80",
    "addr:postcode":"7151 np",
    "addr:street":"Hupselsewg;Gelderland",
    "iso:country":"NL",
    "sg:address":"Hupselsewg 80",
    "sg:city":"Eibergen",
    "sg:orig_category":"Verenigingen En Stichtingen",
    "sg:phone":"+31 545 475 574",
    "sg:postcode":"7151 NP",
    "sg:province":"Gelderland",
    "wof:name":"Polvo, Sticht",
    "wof:placetype":"venue"
},
  "geometry": {"coordinates":[6.633331,52.094395],"type":"Point"}
}