{
  "type": "Feature",
  "properties": {
    "iso:country":"NL",
    "sg:address":"Brinkenhofsestr 12",
    "sg:city":"Arnhem",
    "sg:orig_category":"Organisatiebureaus",
    "sg:phone":"+31 26 327 4414",
    "sg:postcode":"6831 AB",
    "sg:province":"Gelderland",
    "sg:website":"http://www.kynobur.nl",
    "wof:name":"Kynobur",
    "wof:placetype":"venue"
},
  "geometry": {"coordinates":[5.8888230324,51.9554481506],"type":"Point"}
}