{
  "type": "Feature",
  "properties": {
    "addr:full":"B V Zuylenstr 10 Gorinchem South Holland 4207 KG",
    "addr:housenumber":"10",
    "addr:postcode":"4207 kg",
    "addr:street":"V Zuylenstr",
    "iso:country":"NL",
    "sg:address":"B V Zuylenstr 10",
    "sg:city":"Gorinchem",
    "sg:orig_category":"Bakkerijmachines En -Gereedschappen",
    "sg:phone":"+31 183 699 509",
    "sg:postcode":"4207 KG",
    "sg:province":"South Holland",
    "wof:name":"Machines & Bakery Techn Bv",
    "wof:placetype":"venue"
},
  "geometry": {"coordinates":[4.969185,51.830631],"type":"Point"}
}