{
  "type": "Feature",
  "properties": {
    "iso:country":"NL",
    "sg:address":"Op De Vyf Bunder 3",
    "sg:city":"Nuth",
    "sg:orig_category":"Scholen Voor Basisonderwijs",
    "sg:phone":"+31 45 524 1894",
    "sg:postcode":"6361 JE",
    "sg:province":"Limburg",
    "wof:name":"Servatius Rk, St",
    "wof:placetype":"venue"
},
  "geometry": {"coordinates":[5.885999,50.918785],"type":"Point"}
}