{
  "type": "Feature",
  "properties": {
    "addr:full":"Groenlosewg 17 Eibergen Gelderland 7151 HX",
    "addr:housenumber":"17",
    "addr:postcode":"7151 hx",
    "addr:street":"Groenlosewg;Gelderland",
    "iso:country":"NL",
    "sg:address":"Groenlosewg 17",
    "sg:city":"Eibergen",
    "sg:orig_category":"Wasmachines En Wasdrogers - Onderhoud En Reparatie",
    "sg:phone":"+31 545 472 366",
    "sg:postcode":"7151 HX",
    "sg:province":"Gelderland",
    "wof:name":"Tempert",
    "wof:placetype":"venue"
},
  "geometry": {"coordinates":[6.6489701271,52.0920257568],"type":"Point"}
}