{
  "type": "Feature",
  "properties": {
    "addr:full":"Den Uitvanck 12 Oirschot Noord-Brabant 5688 XG",
    "addr:housenumber":"12",
    "addr:postcode":"5688 xg",
    "addr:street":"Den Uitvanck",
    "iso:country":"NL",
    "sg:address":"Den Uitvanck 12",
    "sg:city":"Oirschot",
    "sg:orig_category":"Autokeuringen",
    "sg:phone":"+31 499 577 627",
    "sg:postcode":"5688 XG",
    "sg:province":"Noord-Brabant",
    "wof:name":"Walla Import",
    "wof:placetype":"venue"
},
  "geometry": {"coordinates":[5.335094,51.501431],"type":"Point"}
}