{
  "type": "Feature",
  "properties": {
    "addr:full":"Gastelseweg 9 Rucphen Noord-Brabant 4715 AA",
    "addr:housenumber":"9",
    "addr:postcode":"4715 aa",
    "addr:street":"Gastelseweg",
    "iso:country":"NL",
    "sg:address":"Gastelseweg 9",
    "sg:city":"Rucphen",
    "sg:orig_category":"Bloemen And Planten",
    "sg:phone":"+31 165 341 811",
    "sg:postcode":"4715 AA",
    "sg:province":"Noord-Brabant",
    "wof:name":"T Karhuis",
    "wof:placetype":"venue"
},
  "geometry": {"coordinates":[4.548769,51.534569],"type":"Point"}
}