{
  "type": "Feature",
  "properties": {
    "addr:full":"Professor Drionlaan 9 Baarn Utrecht 3741 XD",
    "addr:housenumber":"9",
    "addr:postcode":"3741 xd",
    "addr:street":"Professor Drionlaan",
    "iso:country":"NL",
    "sg:address":"Professor Drionlaan 9",
    "sg:city":"Baarn",
    "sg:orig_category":"Diverse Grafische Activiteiten",
    "sg:phone":"+31 35 543 1360",
    "sg:postcode":"3741 XD",
    "sg:province":"Utrecht",
    "wof:name":"Esser Grafisch Ontwerper",
    "wof:placetype":"venue"
},
  "geometry": {"coordinates":[5.275324,52.220421],"type":"Point"}
}