{
  "type": "Feature",
  "properties": {
    "iso:country":"NL",
    "sg:address":"Eifel 68",
    "sg:city":"Utrecht",
    "sg:orig_category":"Voetverzorging",
    "sg:phone":"+31 30 288 0249",
    "sg:postcode":"3524 HJ",
    "sg:province":"Utrecht",
    "wof:name":"Vreeswijk, W Van",
    "wof:placetype":"venue"
},
  "geometry": {"coordinates":[5.133608,52.060215],"type":"Point"}
}