{
  "type": "Feature",
  "properties": {
    "addr:full":"De Jonghlaan 5 Nieuwegein Utrecht 3431 GW",
    "addr:housenumber":"5",
    "addr:postcode":"3431 gw",
    "addr:street":"De Jonghlaan",
    "iso:country":"NL",
    "sg:address":"De Jonghlaan 5",
    "sg:city":"Nieuwegein",
    "sg:orig_category":"Verzekeringen",
    "sg:phone":"+31 30 603 1467",
    "sg:postcode":"3431 GW",
    "sg:province":"Utrecht",
    "wof:name":"Wouda Verzekeringen",
    "wof:placetype":"venue"
},
  "geometry": {"coordinates":[5.079276,52.035622],"type":"Point"}
}