{
  "type": "Feature",
  "properties": {
    "addr:full":"Varsenerweg 12A Ommen Overijssel 7731 PZ",
    "addr:housenumber":"12a",
    "addr:postcode":"7731 pz",
    "addr:street":"Varsenerweg",
    "iso:country":"NL",
    "sg:address":"Varsenerweg 12A",
    "sg:city":"Ommen",
    "sg:orig_category":"Pluimveehouderijen",
    "sg:phone":"+31 529 454 517",
    "sg:postcode":"7731 PZ",
    "sg:province":"Overijssel",
    "wof:name":"G.J. Schepers",
    "wof:placetype":"venue"
},
  "geometry": {"coordinates":[6.422973,52.519325],"type":"Point"}
}