{
  "type": "Feature",
  "properties": {
    "iso:country":"NL",
    "sg:address":"Dorpstraat 5",
    "sg:city":"Ulestraten",
    "sg:orig_category":"Makelaars In Onroerend Goed",
    "sg:phone":"+31 43 364 7393",
    "sg:postcode":"6235 AC",
    "sg:province":"Limburg",
    "wof:name":"Aarts & Partn Bv",
    "wof:placetype":"venue"
},
  "geometry": {"coordinates":[5.785524,50.905853],"type":"Point"}
}