{
  "type": "Feature",
  "properties": {
    "addr:full":"Brinkstraat 46 Beilen Drenthe 9411 KN",
    "addr:housenumber":"46",
    "addr:postcode":"9411 kn",
    "addr:street":"Brinkstraat",
    "iso:country":"NL",
    "sg:address":"Brinkstraat 46",
    "sg:city":"Beilen",
    "sg:orig_category":"Discountwinkels",
    "sg:phone":"+31 593 540 342",
    "sg:postcode":"9411 KN",
    "sg:province":"Drenthe",
    "wof:name":"Zeeman Textielsupers",
    "wof:placetype":"venue"
},
  "geometry": {"coordinates":[6.516266,52.85918],"type":"Point"}
}