{
  "type": "Feature",
  "properties": {
    "iso:country":"NL",
    "sg:address":"Kerkstr 2",
    "sg:city":"Makkum Fr",
    "sg:classifiers":[
        {
            "category":"Food & Beverages",
            "subcategory":"Bakery",
            "type":"Retail Goods"
        }
    ],
    "sg:phone":"+31 515 232 892",
    "sg:postcode":"8754 CS",
    "sg:province":"Provincie Friesland",
    "sg:tags":[
        "pizza"
    ],
    "wof:name":"Milano",
    "wof:placetype":"venue"
},
  "geometry": {"coordinates":[5.402552,53.054756],"type":"Point"}
}