{
  "type": "Feature",
  "properties": {
    "addr:full":"F Hendrikln 142 S Gravenhage Zuid-Holland 2582 BH",
    "addr:housenumber":"142;gravenhage",
    "addr:postcode":"2582 bh",
    "addr:street":"S",
    "iso:country":"NL",
    "sg:address":"F Hendrikln 142",
    "sg:city":"S Gravenhage",
    "sg:orig_category":"Linnenshops",
    "sg:phone":"+31 70 350 0801",
    "sg:postcode":"2582 BH",
    "sg:province":"Zuid-Holland",
    "sg:website":"http://www.engeringslaapcomfort.nl",
    "wof:name":"Engering",
    "wof:placetype":"venue"
},
  "geometry": {"coordinates":[4.27852,52.092411],"type":"Point"}
}