{
  "type": "Feature",
  "properties": {
    "addr:full":"Wernhoutseweg 54 Wernhout Noord-Brabant 4884 AW",
    "addr:housenumber":"54",
    "addr:postcode":"4884 aw",
    "addr:street":"Wernhoutseweg",
    "iso:country":"NL",
    "sg:address":"Wernhoutseweg 54",
    "sg:city":"Wernhout",
    "sg:orig_category":"Meubelreparatie And -Restauratie",
    "sg:phone":"+31 76 597 4013",
    "sg:postcode":"4884 AW",
    "sg:province":"Noord-Brabant",
    "wof:name":"Meubelstoffeerderij Leon Pluym",
    "wof:placetype":"venue"
},
  "geometry": {"coordinates":[4.650928,51.462322],"type":"Point"}
}