{
  "type": "Feature",
  "properties": {
    "addr:full":"St. Willibrordstraat 43 Berkel-Enschot North Brabant 5056 HT",
    "addr:housenumber":"43",
    "addr:postcode":"5056 ht",
    "addr:street":"Willibrordstraat",
    "iso:country":"NL",
    "sg:address":"St. Willibrordstraat 43",
    "sg:city":"Berkel-Enschot",
    "sg:orig_category":"Marketingbureaus",
    "sg:phone":"+31 13 533 3084",
    "sg:postcode":"5056 HT",
    "sg:province":"North Brabant",
    "wof:name":"Multi Service",
    "wof:placetype":"venue"
},
  "geometry": {"coordinates":[5.138969,51.588615],"type":"Point"}
}