{
  "type": "Feature",
  "properties": {
    "addr:full":"Herenwg 6 Wassenaar Zuid-Holland 2242 ES",
    "addr:housenumber":"6",
    "addr:postcode":"2242 es",
    "addr:street":"Herenwg",
    "iso:country":"NL",
    "sg:address":"Herenwg 6",
    "sg:city":"Wassenaar",
    "sg:orig_category":"Adviesbureaus Bouwkunde",
    "sg:phone":"+31 70 511 7190",
    "sg:postcode":"2242 ES",
    "sg:province":"Zuid-Holland",
    "wof:name":"Bcs Herenweg Bv",
    "wof:placetype":"venue"
},
  "geometry": {"coordinates":[4.39573,52.141399],"type":"Point"}
}