{
  "type": "Feature",
  "properties": {
    "addr:full":"W De Withstr 34 S Gravenhage Zuid-Holland 2518 CV",
    "addr:housenumber":"34;gravenhage",
    "addr:postcode":"2518 cv",
    "addr:street":"W De Withstr;S",
    "iso:country":"NL",
    "sg:address":"W De Withstr 34",
    "sg:city":"S Gravenhage",
    "sg:orig_category":"Psychotherapeuten",
    "sg:phone":"+31 70 363 7813",
    "sg:postcode":"2518 CV",
    "sg:province":"Zuid-Holland",
    "sg:website":"http://home.wanadoo.nl/ellen.verheij",
    "wof:name":"Ellen Verheij, Trainer-Coach",
    "wof:placetype":"venue"
},
  "geometry": {"coordinates":[4.29348,52.080318],"type":"Point"}
}