{
  "type": "Feature",
  "properties": {
    "iso:country":"NL",
    "sg:address":"Gen Wichersln 2",
    "sg:city":"Eindhoven",
    "sg:orig_category":"Schilders",
    "sg:phone":"+31 40 243 5569",
    "sg:postcode":"5623 GS",
    "sg:province":"Noord-Brabant",
    "wof:name":"Edwin Van Gool Schilderwerken",
    "wof:placetype":"venue"
},
  "geometry": {"coordinates":[5.47708,51.460041],"type":"Point"}
}