{
  "type": "Feature",
  "properties": {
    "addr:full":"Jacob Catsstraat 16 Spijkenisse Zuid-Holland 3202 AK",
    "addr:housenumber":"16",
    "addr:postcode":"3202 ak",
    "addr:street":"Jacob Catsstraat",
    "iso:country":"NL",
    "sg:address":"Jacob Catsstraat 16",
    "sg:city":"Spijkenisse",
    "sg:orig_category":"Film-, Tv- And Videoproductie",
    "sg:phone":"+31 181 620 106",
    "sg:postcode":"3202 AK",
    "sg:province":"Zuid-Holland",
    "wof:name":"E.T. Citroen Produkties",
    "wof:placetype":"venue"
},
  "geometry": {"coordinates":[4.31224,51.852261],"type":"Point"}
}