{
  "type": "Feature",
  "properties": {
    "iso:country":"NL",
    "sg:address":"Rutherfordstraat 3",
    "sg:city":"Haarlem",
    "sg:orig_category":"Diverse Grafische Activiteiten",
    "sg:phone":"+31 23 524 2262",
    "sg:postcode":"2014 KA",
    "sg:province":"Noord-Holland",
    "wof:name":"Direkt Litho Bv",
    "wof:placetype":"venue"
},
  "geometry": {"coordinates":[4.613448,52.370697],"type":"Point"}
}