{
  "type": "Feature",
  "properties": {
    "addr:full":"Stationsstr 46 Lanaken BE.05 B-36 20",
    "addr:housenumber":"46;b-36 20",
    "addr:street":"Stationsstr",
    "iso:country":"NL",
    "sg:address":"Stationsstr 46",
    "sg:city":"Lanaken",
    "sg:classifiers":[
        {
            "category":"Shopping",
            "subcategory":"Adult",
            "type":"Retail Goods"
        }
    ],
    "sg:phone":"+31 89731155",
    "sg:postcode":"B-36 20",
    "sg:province":"BE.05",
    "sg:tags":[
        "lingerie",
        "en",
        "tricotage"
    ],
    "sg:website":"http://www.lingerierina.be",
    "wof:name":"Rina, Lingerie",
    "wof:placetype":"venue"
},
  "geometry": {"coordinates":[5.655135,50.891228],"type":"Point"}
}