{
  "type": "Feature",
  "properties": {
    "addr:full":"Bourgondischeln 6 Ridderkerk Zuid-Holland 2983 SH",
    "addr:housenumber":"6",
    "addr:postcode":"2983 sh",
    "addr:street":"Bourgondischeln",
    "iso:country":"NL",
    "sg:address":"Bourgondischeln 6",
    "sg:city":"Ridderkerk",
    "sg:orig_category":"Plafonds",
    "sg:phone":"+31 180 487 037",
    "sg:postcode":"2983 SH",
    "sg:province":"Zuid-Holland",
    "wof:name":"Blouw Bv, J",
    "wof:placetype":"venue"
},
  "geometry": {"coordinates":[4.612263,51.887657],"type":"Point"}
}