{
  "type": "Feature",
  "properties": {
    "addr:full":"Bosplaat 46 Zwolle NL.08 8032 DM",
    "addr:housenumber":"46",
    "addr:postcode":"8032 dm",
    "addr:street":"Bosplaat",
    "iso:country":"NL",
    "sg:address":"Bosplaat 46",
    "sg:city":"Zwolle",
    "sg:orig_category":"Beursorganisaties And Standbouw",
    "sg:phone":"+31 38 452 8406",
    "sg:postcode":"8032 DM",
    "sg:province":"NL.08",
    "wof:name":"Reclameburo Decor Line",
    "wof:placetype":"venue"
},
  "geometry": {"coordinates":[6.096646,52.527775],"type":"Point"}
}