{
  "type": "Feature",
  "properties": {
    "addr:full":"Zeestraat 214 Beverwijk North Holland 1943 AE",
    "addr:housenumber":"214",
    "addr:postcode":"1943 ae",
    "addr:street":"Zeestraat",
    "iso:country":"NL",
    "sg:address":"Zeestraat 214",
    "sg:city":"Beverwijk",
    "sg:orig_category":"Begrafenisondernemers",
    "sg:phone":"+31 251 216 363",
    "sg:postcode":"1943 AE",
    "sg:province":"North Holland",
    "wof:name":"Westerhout Dierencrematorium",
    "wof:placetype":"venue"
},
  "geometry": {"coordinates":[4.640468,52.485226],"type":"Point"}
}