{
  "type": "Feature",
  "properties": {
    "addr:full":"Ds Van Paddenburghweg 53 Elspeet Gelderland 8075 AJ",
    "addr:housenumber":"53",
    "addr:postcode":"8075 aj",
    "addr:street":"Ds Van Paddenburghweg;Gelderland",
    "iso:country":"NL",
    "sg:address":"Ds Van Paddenburghweg 53",
    "sg:city":"Elspeet",
    "sg:orig_category":"Visspeciaalzaken",
    "sg:phone":"+31 577 491 665",
    "sg:postcode":"8075 AJ",
    "sg:province":"Gelderland",
    "wof:name":"W H Averesch Vishandel",
    "wof:placetype":"venue"
},
  "geometry": {"coordinates":[5.788165,52.291374],"type":"Point"}
}