{
  "type": "Feature",
  "properties": {
    "addr:full":"Jupiterstraat 2 Hardinxveld Giessend Zuid-Holland 3371 TE",
    "addr:housenumber":"2;giessend;3371",
    "addr:postcode":"te",
    "addr:street":"Jupiterstraat",
    "iso:country":"NL",
    "sg:address":"Jupiterstraat 2",
    "sg:city":"Hardinxveld Giessend",
    "sg:classifiers":[
        {
            "category":"Education",
            "subcategory":"Preschool",
            "type":"Public Place"
        }
    ],
    "sg:phone":"+31 184 614 053",
    "sg:postcode":"3371 TE",
    "sg:province":"Zuid-Holland",
    "sg:tags":[
        "kleuteronderwijs",
        "basis-"
    ],
    "wof:name":"Koningin Wilhelminaschool",
    "wof:placetype":"venue"
},
  "geometry": {"coordinates":[4.821939,51.82378],"type":"Point"}
}