{
  "type": "Feature",
  "properties": {
    "addr:full":"Torenstr 5 Kesteren Gelderland 4041 GA",
    "addr:housenumber":"5",
    "addr:postcode":"4041 ga",
    "addr:street":"Torenstr;Gelderland",
    "iso:country":"NL",
    "sg:address":"Torenstr 5",
    "sg:city":"Kesteren",
    "sg:orig_category":"Accountants - Administratie- Consulenten En -Kantoren",
    "sg:phone":"+31 488 487 487",
    "sg:postcode":"4041 GA",
    "sg:province":"Gelderland",
    "wof:name":"Alfa Bv",
    "wof:placetype":"venue"
},
  "geometry": {"coordinates":[5.573433,51.934399],"type":"Point"}
}