{
  "type": "Feature",
  "properties": {
    "addr:full":"Klompenmaker 15 Leiderdorp Zuid-Holland 2353 WE",
    "addr:housenumber":"15",
    "addr:postcode":"2353 we",
    "addr:street":"Klompenmaker",
    "iso:country":"NL",
    "sg:address":"Klompenmaker 15",
    "sg:city":"Leiderdorp",
    "sg:orig_category":"Timmerwerken",
    "sg:phone":"+31 71 521 7129",
    "sg:postcode":"2353 WE",
    "sg:province":"Zuid-Holland",
    "wof:name":"So Timmerwerken Vof",
    "wof:placetype":"venue"
},
  "geometry": {"coordinates":[4.523755,52.168526],"type":"Point"}
}