{
  "type": "Feature",
  "properties": {
    "addr:full":"Wilhelminastraat 53 Haarlem Noord-Holland 2011 VL",
    "addr:housenumber":"53",
    "addr:postcode":"2011 vl",
    "addr:street":"Wilhelminastraat",
    "iso:country":"NL",
    "sg:address":"Wilhelminastraat 53",
    "sg:city":"Haarlem",
    "sg:orig_category":"Diverse Opleidingen And Onderwijs",
    "sg:phone":"+31 23 532 1088",
    "sg:postcode":"2011 VL",
    "sg:province":"Noord-Holland",
    "wof:name":"Beta",
    "wof:placetype":"venue"
},
  "geometry": {"coordinates":[4.627322,52.378876],"type":"Point"}
}