{
  "type": "Feature",
  "properties": {
    "addr:full":"Stationsstr 20 Scheemda Groningen 9679 ED",
    "addr:housenumber":"20",
    "addr:postcode":"9679 ed",
    "addr:street":"Stationsstr",
    "iso:country":"NL",
    "sg:address":"Stationsstr 20",
    "sg:city":"Scheemda",
    "sg:orig_category":"Fietsen En Bromfietsen",
    "sg:phone":"+31 597 592 746",
    "sg:postcode":"9679 ED",
    "sg:province":"Groningen",
    "wof:name":"Doedens",
    "wof:placetype":"venue"
},
  "geometry": {"coordinates":[6.971254,53.174816],"type":"Point"}
}