{
  "type": "Feature",
  "properties": {
    "addr:full":"St. Maartensloop 31 Tilburg Noord-Brabant 5032 CV",
    "addr:housenumber":"31",
    "addr:postcode":"5032 cv",
    "iso:country":"NL",
    "sg:address":"St. Maartensloop 31",
    "sg:city":"Tilburg",
    "sg:orig_category":"Loodgieterswerk, Verwarming And Sanitaire Installaties",
    "sg:phone":"+31 13 463 5412",
    "sg:postcode":"5032 CV",
    "sg:province":"Noord-Brabant",
    "wof:name":"P Wc Huijbrechts",
    "wof:placetype":"venue"
},
  "geometry": {"coordinates":[5.034944,51.542484],"type":"Point"}
}