{
  "type": "Feature",
  "properties": {
    "addr:full":"Thorbeckestraat 2A Alphen A/D Rijn Zuid-Holland 2406 CM",
    "addr:housenumber":"2a",
    "addr:postcode":"2406 cm",
    "addr:street":"Thorbeckestraat",
    "iso:country":"NL",
    "sg:address":"Thorbeckestraat 2A",
    "sg:city":"Alphen A/D Rijn",
    "sg:orig_category":"Kinderopvang Behalve Thuis",
    "sg:phone":"+31 172 492 067",
    "sg:postcode":"2406 CM",
    "sg:province":"Zuid-Holland",
    "wof:name":"Peuterspeelzaal Haasje Over",
    "wof:placetype":"venue"
},
  "geometry": {"coordinates":[4.665684,52.131214],"type":"Point"}
}