{
  "type": "Feature",
  "properties": {
    "iso:country":"NL",
    "sg:address":"Markt 64",
    "sg:city":"Geertruidenberg",
    "sg:orig_category":"Postkantoren",
    "sg:phone":"+31 162 512 520",
    "sg:postcode":"4931 BT",
    "sg:province":"North Brabant",
    "sg:website":"http://www.postkantoor.nl",
    "wof:name":"Postkantoor",
    "wof:placetype":"venue"
},
  "geometry": {"coordinates":[4.8596420288,51.7007789612],"type":"Point"}
}