{
  "type": "Feature",
  "properties": {
    "addr:full":"Markt 64 Geertruidenberg North Brabant 4931 BT",
    "addr:housenumber":"64",
    "addr:postcode":"4931 bt",
    "addr:street":"Markt",
    "iso:country":"NL",
    "sg:address":"Markt 64",
    "sg:city":"Geertruidenberg",
    "sg:orig_category":"Postkantoren",
    "sg:phone":"+31 162 512 520",
    "sg:postcode":"4931 BT",
    "sg:province":"North Brabant",
    "sg:website":"http://www.postkantoor.nl",
    "wof:name":"Postkantoor",
    "wof:placetype":"venue"
},
  "geometry": {"coordinates":[4.8596420288,51.7007789612],"type":"Point"}
}