{
  "type": "Feature",
  "properties": {
    "iso:country":"NL",
    "sg:address":"Rijksstraatweg 447",
    "sg:city":"Wassenaar",
    "sg:orig_category":"Autokeuringen",
    "sg:phone":"+31 70 511 4463",
    "sg:postcode":"2245 AC",
    "sg:province":"Zuid-Holland",
    "wof:name":"Swart Autobrandstoffen",
    "wof:placetype":"venue"
},
  "geometry": {"coordinates":[4.409748,52.13903],"type":"Point"}
}