{
  "type": "Feature",
  "properties": {
    "addr:full":"Lisztgaarde 128 Oss Virginia 5344 EJ",
    "addr:housenumber":"128",
    "addr:postcode":"5344 ej",
    "addr:street":"Lisztgaarde",
    "iso:country":"NL",
    "sg:address":"Lisztgaarde 128",
    "sg:city":"Oss",
    "sg:orig_category":"Beveiliging",
    "sg:phone":"+31 6 28438754",
    "sg:postcode":"5344 EJ",
    "sg:province":"Virginia",
    "sg:website":"http://www.happysales.nl",
    "wof:name":"Happysales.Nl",
    "wof:placetype":"venue"
},
  "geometry": {"coordinates":[-77.235214,38.312599],"type":"Point"}
}