{
  "type": "Feature",
  "properties": {
    "addr:full":"18 Septemberplein 15 Eindhoven North Brabant 5611 AL",
    "addr:housenumber":"15",
    "addr:postcode":"5611 al",
    "addr:street":"18 Septemberplein",
    "iso:country":"NL",
    "sg:address":"18 Septemberplein 15",
    "sg:city":"Eindhoven",
    "sg:orig_category":"Bloemen And Planten",
    "sg:phone":"+31 40 244 4664",
    "sg:postcode":"5611 AL",
    "sg:province":"North Brabant",
    "wof:name":"De Bloem",
    "wof:placetype":"venue"
},
  "geometry": {"coordinates":[5.476258,51.441151],"type":"Point"}
}