{
  "type": "Feature",
  "properties": {
    "addr:full":"Postbus 2011 Amersfoort Noord-Holland 3800 CA",
    "addr:housenumber":"2011",
    "addr:postcode":"3800 ca",
    "addr:street":"Postbus",
    "iso:country":"NL",
    "sg:address":"Postbus 2011",
    "sg:city":"Amersfoort",
    "sg:orig_category":"Kantoor- En Secretariaatsservice",
    "sg:phone":"+31 33 460 3860",
    "sg:postcode":"3800 CA",
    "sg:province":"Noord-Holland",
    "wof:name":"Lievense",
    "wof:placetype":"venue"
},
  "geometry": {"coordinates":[5.3895897865,52.1561012268],"type":"Point"}
}