{
  "type": "Feature",
  "properties": {
    "addr:full":"Rozengaardsewg 38-06 Doetinchem Gelderland 7001 DP",
    "addr:housenumber":"38-06",
    "addr:postcode":"7001 dp",
    "addr:street":"Gelderland",
    "iso:country":"NL",
    "sg:address":"Rozengaardsewg 38-06",
    "sg:city":"Doetinchem",
    "sg:orig_category":"Adviesbureaus Bouwkunde",
    "sg:phone":"+31 314 360 580",
    "sg:postcode":"7001 DP",
    "sg:province":"Gelderland",
    "wof:name":"Bruggeman",
    "wof:placetype":"venue"
},
  "geometry": {"coordinates":[6.295921,51.967995],"type":"Point"}
}