{
  "type": "Feature",
  "properties": {
    "iso:country":"NL",
    "sg:address":"Herenstraat 13A",
    "sg:city":"Culemborg",
    "sg:orig_category":"Kinderopvang Behalve Thuis",
    "sg:phone":"+31 345 521 411",
    "sg:postcode":"4101 BR",
    "sg:province":"Gelderland",
    "wof:name":"Kinderdagverblijf Kiekeboe",
    "wof:placetype":"venue"
},
  "geometry": {"coordinates":[5.223318,51.957775],"type":"Point"}
}