{
  "type": "Feature",
  "properties": {
    "iso:country":"NL",
    "sg:address":"P Kiesstr 78A",
    "sg:city":"Haarlem",
    "sg:orig_category":"Kappers",
    "sg:phone":"+31 23 532 6600",
    "sg:postcode":"2013 BK",
    "sg:province":"Noord-Holland",
    "wof:name":"Wino, The Hairshop",
    "wof:placetype":"venue"
},
  "geometry": {"coordinates":[4.629649,52.387085],"type":"Point"}
}