{
  "type": "Feature",
  "properties": {
    "addr:full":"Hoofdwg 322A Bellingwolde Groningen 9695 AX",
    "addr:housenumber":"322a",
    "addr:postcode":"9695 ax",
    "iso:country":"NL",
    "sg:address":"Hoofdwg 322A",
    "sg:city":"Bellingwolde",
    "sg:orig_category":"Verf En Lak - Grondstoffen",
    "sg:phone":"+31 597 532 420",
    "sg:postcode":"9695 AX",
    "sg:province":"Groningen",
    "wof:name":"Scholtens, Verfstoffen",
    "wof:placetype":"venue"
},
  "geometry": {"coordinates":[7.171586,53.126736],"type":"Point"}
}