{
  "type": "Feature",
  "properties": {
    "iso:country":"NL",
    "sg:address":"Wandelwg 98A",
    "sg:city":"Wormerveer",
    "sg:orig_category":"Gelegenheidskleding",
    "sg:phone":"+31 75 628 3868",
    "sg:postcode":"1521 AJ",
    "sg:province":"Noord-Holland",
    "wof:name":"Burch Fashion, V/D",
    "wof:placetype":"venue"
},
  "geometry": {"coordinates":[4.802268,52.486435],"type":"Point"}
}