{
  "type": "Feature",
  "properties": {
    "iso:country":"NL",
    "sg:address":"Vijzelgracht 47",
    "sg:city":"Amsterdam",
    "sg:orig_category":"Kappers",
    "sg:phone":"+31 20 626 2619",
    "sg:postcode":"1017 HP",
    "sg:province":"Noord-Holland",
    "wof:name":"G. Van Dulst Cv",
    "wof:placetype":"venue"
},
  "geometry": {"coordinates":[4.8913068771,52.3606033325],"type":"Point"}
}