{
  "type": "Feature",
  "properties": {
    "addr:full":"G Doupln 80 Amsterdam Noord-Holland 1073 XG",
    "addr:housenumber":"80",
    "addr:postcode":"1073 xg",
    "iso:country":"NL",
    "sg:address":"G Doupln 80",
    "sg:city":"Amsterdam",
    "sg:orig_category":"Modeontwerpen",
    "sg:phone":"+31 20 776 4332",
    "sg:postcode":"1073 XG",
    "sg:province":"Noord-Holland",
    "sg:website":"http://www.hipholland.nl",
    "wof:name":"Hipholland",
    "wof:placetype":"venue"
},
  "geometry": {"coordinates":[4.893336,52.355961],"type":"Point"}
}