{
  "type": "Feature",
  "properties": {
    "addr:full":"Kerkhofln 43 Bennekom Gelderland 6721 EX",
    "addr:housenumber":"43",
    "addr:postcode":"6721 ex",
    "addr:street":"Kerkhofln;Gelderland",
    "iso:country":"NL",
    "sg:address":"Kerkhofln 43",
    "sg:city":"Bennekom",
    "sg:orig_category":"Mensendieck - Oefentherapeuten",
    "sg:phone":"+31 318 420 123",
    "sg:postcode":"6721 EX",
    "sg:province":"Gelderland",
    "wof:name":"Blooijs, Lenette Van",
    "wof:placetype":"venue"
},
  "geometry": {"coordinates":[5.675792,52.000942],"type":"Point"}
}