{
  "type": "Feature",
  "properties": {
    "addr:full":"Uiterdykenwg 44 Marknesse NL.08 8316 RS",
    "addr:housenumber":"44;nl.08",
    "addr:postcode":"8316 rs",
    "addr:street":"Uiterdykenwg",
    "iso:country":"NL",
    "sg:address":"Uiterdykenwg 44",
    "sg:city":"Marknesse",
    "sg:orig_category":"Bloembollen - Groothandel",
    "sg:phone":"+31 527 202 474",
    "sg:postcode":"8316 RS",
    "sg:province":"NL.08",
    "wof:name":"Bentem Bluefields, Van",
    "wof:placetype":"venue"
},
  "geometry": {"coordinates":[5.931737,52.735569],"type":"Point"}
}