{
  "type": "Feature",
  "properties": {
    "addr:full":"De Brouwery 5 Leusden Utrecht 3831 ND",
    "addr:housenumber":"5",
    "addr:postcode":"3831 nd",
    "iso:country":"NL",
    "sg:address":"De Brouwery 5",
    "sg:city":"Leusden",
    "sg:orig_category":"Kappers",
    "sg:phone":"+31 33 456 7430",
    "sg:postcode":"3831 ND",
    "sg:province":"Utrecht",
    "wof:name":"Carroussel",
    "wof:placetype":"venue"
},
  "geometry": {"coordinates":[5.4295902252,52.1312484741],"type":"Point"}
}