{
  "type": "Feature",
  "properties": {
    "addr:full":"Domelaarswg 3 Markelo Overijssel 7475 RR",
    "addr:housenumber":"3",
    "addr:postcode":"7475 rr",
    "addr:street":"Domelaarswg",
    "iso:country":"NL",
    "sg:address":"Domelaarswg 3",
    "sg:city":"Markelo",
    "sg:classifiers":[
        {
            "category":"Home & Garden",
            "subcategory":"Garden Supply",
            "type":"Retail Goods"
        }
    ],
    "sg:phone":"+31 547 362 430",
    "sg:postcode":"7475 RR",
    "sg:province":"Overijssel",
    "sg:tags":[
        "zand",
        "en",
        "grind"
    ],
    "wof:name":"Domelaar Centrale Zandwinning Bv, De",
    "wof:placetype":"venue"
},
  "geometry": {"coordinates":[6.467532,52.250366],"type":"Point"}
}