{
  "type": "Feature",
  "properties": {
    "addr:full":"Nieuwewg 77 Veenendaal Utrecht 3905 LH",
    "addr:housenumber":"77",
    "addr:postcode":"3905 lh",
    "addr:street":"Nieuwewg",
    "iso:country":"NL",
    "sg:address":"Nieuwewg 77",
    "sg:city":"Veenendaal",
    "sg:orig_category":"Cafetaria'S",
    "sg:phone":"+31 318 514 651",
    "sg:postcode":"3905 LH",
    "sg:province":"Utrecht",
    "wof:name":"Molen, De",
    "wof:placetype":"venue"
},
  "geometry": {"coordinates":[5.553216,52.033295],"type":"Point"}
}