{
  "type": "Feature",
  "properties": {
    "addr:full":"Binnenlandse Baan 7 Barendrecht South Holland 2991 EA",
    "addr:housenumber":"7",
    "addr:postcode":"2991 ea",
    "addr:street":"Binnenlandse Baan",
    "iso:country":"NL",
    "sg:address":"Binnenlandse Baan 7",
    "sg:city":"Barendrecht",
    "sg:orig_category":"Postkantoren",
    "sg:phone":"+31 180 612 222",
    "sg:postcode":"2991 EA",
    "sg:province":"South Holland",
    "sg:website":"http://www.postkantoor.nl",
    "wof:name":"Postkantoor",
    "wof:placetype":"venue"
},
  "geometry": {"coordinates":[4.539639,51.856152],"type":"Point"}
}