{
  "type": "Feature",
  "properties": {
    "addr:full":"De Zulthe 4 Roden Drenthe 9301 AV",
    "addr:housenumber":"4",
    "addr:postcode":"9301 av",
    "addr:street":"De Zulthe",
    "iso:country":"NL",
    "sg:address":"De Zulthe 4",
    "sg:city":"Roden",
    "sg:orig_category":"Loonbedrijven",
    "sg:phone":"+31 50 501 5150",
    "sg:postcode":"9301 AV",
    "sg:province":"Drenthe",
    "wof:name":"Graaf, De",
    "wof:placetype":"venue"
},
  "geometry": {"coordinates":[6.420039,53.142921],"type":"Point"}
}