{
  "type": "Feature",
  "properties": {
    "addr:full":"Castricumpln 33 S Gravenhage Zuid-Holland 2547 JA",
    "addr:housenumber":"33;gravenhage",
    "addr:postcode":"2547 ja",
    "addr:street":"Castricumpln;S",
    "iso:country":"NL",
    "sg:address":"Castricumpln 33",
    "sg:city":"S Gravenhage",
    "sg:orig_category":"Cafetaria'S",
    "sg:phone":"+31 70 368 7541",
    "sg:postcode":"2547 JA",
    "sg:province":"Zuid-Holland",
    "wof:name":"Jong, De",
    "wof:placetype":"venue"
},
  "geometry": {"coordinates":[4.26694,52.061771],"type":"Point"}
}