{
  "type": "Feature",
  "properties": {
    "addr:full":"Vuurwerkerweg 9 Amsterdam Noord-Holland 1032 KN",
    "addr:housenumber":"9",
    "addr:postcode":"1032 kn",
    "addr:street":"Vuurwerkerweg",
    "iso:country":"NL",
    "sg:address":"Vuurwerkerweg 9",
    "sg:city":"Amsterdam",
    "sg:orig_category":"Autokeuringen",
    "sg:phone":"+31 20 494 5602",
    "sg:postcode":"1032 KN",
    "sg:province":"Noord-Holland",
    "wof:name":"Appie & Sen Garage",
    "wof:placetype":"venue"
},
  "geometry": {"coordinates":[4.907,52.399632],"type":"Point"}
}