{
  "type": "Feature",
  "properties": {
    "addr:full":"Elegaststraat 14 Geleen Limburg 6166 KE",
    "addr:housenumber":"14",
    "addr:postcode":"6166 ke",
    "addr:street":"Elegaststraat",
    "iso:country":"NL",
    "sg:address":"Elegaststraat 14",
    "sg:city":"Geleen",
    "sg:orig_category":"Alternatieve Geneeskunde",
    "sg:phone":"+31 46 475 4073",
    "sg:postcode":"6166 KE",
    "sg:province":"Limburg",
    "wof:name":"Dhr. R.W.J. Kusters",
    "wof:placetype":"venue"
},
  "geometry": {"coordinates":[5.845816,50.977802],"type":"Point"}
}