{
  "type": "Feature",
  "properties": {
    "iso:country":"NL",
    "sg:address":"Noordster 14",
    "sg:city":"Puttershoek",
    "sg:orig_category":"Verzekeringen",
    "sg:phone":"+31 78 676 3220",
    "sg:postcode":"3297 VC",
    "sg:province":"South Holland",
    "wof:name":"Assurantiekantoor F.H. Suverein",
    "wof:placetype":"venue"
},
  "geometry": {"coordinates":[4.570736,51.80262],"type":"Point"}
}