{
  "type": "Feature",
  "properties": {
    "addr:full":"Oranjewg 43 Emst Gelderland 8166 JA",
    "addr:housenumber":"43",
    "addr:postcode":"8166 ja",
    "addr:street":"Oranjewg;Gelderland",
    "iso:country":"NL",
    "sg:address":"Oranjewg 43",
    "sg:city":"Emst",
    "sg:orig_category":"Grondwerken",
    "sg:phone":"+31 578 661 410",
    "sg:postcode":"8166 JA",
    "sg:province":"Gelderland",
    "wof:name":"Eiland Bv",
    "wof:placetype":"venue"
},
  "geometry": {"coordinates":[5.966136,52.32151],"type":"Point"}
}