{
  "type": "Feature",
  "properties": {
    "addr:full":"Noorddijk 17 Krabbendijke Zeeland 4413 NE",
    "addr:housenumber":"17",
    "addr:postcode":"4413 ne",
    "addr:street":"Noorddijk",
    "iso:country":"NL",
    "sg:address":"Noorddijk 17",
    "sg:city":"Krabbendijke",
    "sg:orig_category":"Bloemen And Planten",
    "sg:phone":"+31 113 502 336",
    "sg:postcode":"4413 NE",
    "sg:province":"Zeeland",
    "wof:name":"Uienschilbedrijf Van 'T Leven",
    "wof:placetype":"venue"
},
  "geometry": {"coordinates":[4.115363,51.435898],"type":"Point"}
}