{
  "type": "Feature",
  "properties": {
    "addr:full":"Molenstr 4 Zwartsluis Overijssel 8064 DH",
    "addr:housenumber":"4",
    "addr:postcode":"8064 dh",
    "addr:street":"Molenstr",
    "iso:country":"NL",
    "sg:address":"Molenstr 4",
    "sg:city":"Zwartsluis",
    "sg:orig_category":"Verenigingsgebouwen",
    "sg:phone":"+31 38 386 6731",
    "sg:postcode":"8064 DH",
    "sg:province":"Overijssel",
    "wof:name":"Vrede",
    "wof:placetype":"venue"
},
  "geometry": {"coordinates":[6.070416,52.640533],"type":"Point"}
}