{
  "type": "Feature",
  "properties": {
    "addr:full":"Purmerwg 9 Almere Flevoland 1311 XE",
    "addr:housenumber":"9",
    "addr:postcode":"1311 xe",
    "addr:street":"Purmerwg;Flevoland",
    "iso:country":"NL",
    "sg:address":"Purmerwg 9",
    "sg:city":"Almere",
    "sg:classifiers":[
        {
            "category":"Farming",
            "subcategory":"Fish & Marine Products",
            "type":"Manufacturing & Wholesale Goods"
        }
    ],
    "sg:phone":"+31 36 539 7373",
    "sg:postcode":"1311 XE",
    "sg:province":"Flevoland",
    "sg:tags":[
        "vi"
    ],
    "sg:website":"http://www.bestfish.nl",
    "wof:name":"Best Fish Almere Holland",
    "wof:placetype":"venue"
},
  "geometry": {"coordinates":[5.176585,52.362125],"type":"Point"}
}