{
  "type": "Feature",
  "properties": {
    "iso:country":"NL",
    "sg:address":"Berflowg 106",
    "sg:city":"Hengelo Ov",
    "sg:orig_category":"Automaterialen En Gereedschappen",
    "sg:phone":"+31 74 291 6383",
    "sg:postcode":"7553 JT",
    "sg:province":"Overijssel",
    "wof:name":"Boensma, Jan",
    "wof:placetype":"venue"
},
  "geometry": {"coordinates":[6.795786,52.257122],"type":"Point"}
}