{
  "type": "Feature",
  "properties": {
    "addr:full":"Steenenstr 30 Oud Beyerland Zuid-Holland 3262 JM",
    "addr:housenumber":"30",
    "addr:postcode":"3262 jm",
    "addr:street":"Steenenstr;Oud Beyerland",
    "iso:country":"NL",
    "sg:address":"Steenenstr 30",
    "sg:city":"Oud Beyerland",
    "sg:orig_category":"Verzekeringen - Verzekeringskantoren",
    "sg:phone":"+31 186 634 210",
    "sg:postcode":"3262 JM",
    "sg:province":"Zuid-Holland",
    "sg:website":"http://www.schep-meijerink.nl",
    "wof:name":"Schep En Meijerink",
    "wof:placetype":"venue"
},
  "geometry": {"coordinates":[4.416132,51.821293],"type":"Point"}
}