{
  "type": "Feature",
  "properties": {
    "addr:full":"Kerkstr 20A Keyenborg Gelderland 7256 AS",
    "addr:housenumber":"20a",
    "addr:postcode":"7256 as",
    "addr:street":"Kerkstr;Gelderland",
    "iso:country":"NL",
    "sg:address":"Kerkstr 20A",
    "sg:city":"Keyenborg",
    "sg:orig_category":"Bloemen En Planten",
    "sg:phone":"+31 575 462 977",
    "sg:postcode":"7256 AS",
    "sg:province":"Gelderland",
    "wof:name":"Jolanda",
    "wof:placetype":"venue"
},
  "geometry": {"coordinates":[6.2971200943,52.0304718018],"type":"Point"}
}