{
  "type": "Feature",
  "properties": {
    "addr:full":"Toccatastr 29 Enschede Overijssel 7534 XP",
    "addr:housenumber":"29",
    "addr:postcode":"7534 xp",
    "addr:street":"Toccatastr",
    "iso:country":"NL",
    "sg:address":"Toccatastr 29",
    "sg:city":"Enschede",
    "sg:orig_category":"Administratie- En Boekhoudkantoren",
    "sg:phone":"+31 53 461 4488",
    "sg:postcode":"7534 XP",
    "sg:province":"Overijssel",
    "wof:name":"Bolk, F A",
    "wof:placetype":"venue"
},
  "geometry": {"coordinates":[6.976551,52.21423],"type":"Point"}
}