{
  "type": "Feature",
  "properties": {
    "addr:full":"H J Koenenstr 5 Haarlem Noord-Holland 2012 BA",
    "addr:housenumber":"5",
    "addr:postcode":"2012 ba",
    "iso:country":"NL",
    "sg:address":"H J Koenenstr 5",
    "sg:city":"Haarlem",
    "sg:orig_category":"Werving En Selectie",
    "sg:phone":"+31 23 531 9657",
    "sg:postcode":"2012 BA",
    "sg:province":"Noord-Holland",
    "wof:name":"Tromer",
    "wof:placetype":"venue"
},
  "geometry": {"coordinates":[4.6377029419,52.3721199036],"type":"Point"}
}