{
  "type": "Feature",
  "properties": {
    "iso:country":"NL",
    "sg:address":"Aegidiusstraat 199",
    "sg:city":"Rotterdam",
    "sg:orig_category":"Zalenexploitatie",
    "sg:phone":"+31 10 413 5055",
    "sg:postcode":"3061 XJ",
    "sg:province":"Zuid-Holland",
    "wof:name":"Galerie Fotomania",
    "wof:placetype":"venue"
},
  "geometry": {"coordinates":[4.509209,51.922108],"type":"Point"}
}