{
  "type": "Feature",
  "properties": {
    "iso:country":"NL",
    "sg:address":"Maastrichtsestr 34",
    "sg:city":"S Gravenhage",
    "sg:orig_category":"Open Haard Houtblokken",
    "sg:phone":"+31 70 352 2007",
    "sg:postcode":"2587 XE",
    "sg:province":"Zuid-Holland",
    "wof:name":"Mooy, G A De",
    "wof:placetype":"venue"
},
  "geometry": {"coordinates":[4.29118,52.112942],"type":"Point"}
}