{
  "type": "Feature",
  "properties": {
    "addr:full":"Stephensonstr 8N Zoetermeer Zuid-Holland 2723 RN",
    "addr:housenumber":"8n",
    "addr:postcode":"2723 rn",
    "addr:street":"Stephensonstr",
    "iso:country":"NL",
    "sg:address":"Stephensonstr 8N",
    "sg:city":"Zoetermeer",
    "sg:orig_category":"Fotografie Reclame En Mode",
    "sg:phone":"+31 79 331 9684",
    "sg:postcode":"2723 RN",
    "sg:province":"Zuid-Holland",
    "wof:name":"Pictures & Peanuts",
    "wof:placetype":"venue"
},
  "geometry": {"coordinates":[4.526331,52.06295],"type":"Point"}
}