{
  "type": "Feature",
  "properties": {
    "addr:full":"Oosterkerkstraat 1 Leiden South Holland 2312 SN",
    "addr:housenumber":"1",
    "addr:postcode":"2312 sn",
    "addr:street":"Oosterkerkstraat",
    "iso:country":"NL",
    "sg:address":"Oosterkerkstraat 1",
    "sg:city":"Leiden",
    "sg:orig_category":"Werving And Selectie Van Vast Personeel",
    "sg:phone":"+31 71 535 4242",
    "sg:postcode":"2312 SN",
    "sg:province":"South Holland",
    "wof:name":"Arbeidsbureau Leiden",
    "wof:placetype":"venue"
},
  "geometry": {"coordinates":[4.5015850067,52.1587867737],"type":"Point"}
}