{
  "type": "Feature",
  "properties": {
    "iso:country":"NL",
    "sg:address":"Wierdensestraat 78",
    "sg:city":"Almelo",
    "sg:orig_category":"Paramedische Behandelingen",
    "sg:phone":"+31 546 815 554",
    "sg:postcode":"7604 BK",
    "sg:province":"NL.08",
    "wof:name":"I.A. Schaake",
    "wof:placetype":"venue"
},
  "geometry": {"coordinates":[6.65532,52.35503],"type":"Point"}
}