{
  "type": "Feature",
  "properties": {
    "iso:country":"NL",
    "sg:address":"Blijhamsterstraat 37",
    "sg:city":"Winschoten",
    "sg:orig_category":"Verzekeringen",
    "sg:phone":"+31 597 417 929",
    "sg:postcode":"9671 AT",
    "sg:province":"Groningen",
    "wof:name":"Assurantiekantoor Houwing",
    "wof:placetype":"venue"
},
  "geometry": {"coordinates":[7.039954,53.139805],"type":"Point"}
}