{
  "type": "Feature",
  "properties": {
    "addr:full":"Ketelstr 2 Hengelo Ov NL.08 7553 BR",
    "addr:housenumber":"2",
    "addr:postcode":"7553 br",
    "addr:street":"Ketelstr;Ov",
    "iso:country":"NL",
    "sg:address":"Ketelstr 2",
    "sg:city":"Hengelo Ov",
    "sg:orig_category":"Loodgieters",
    "sg:phone":"+31 74 243 3719",
    "sg:postcode":"7553 BR",
    "sg:province":"NL.08",
    "wof:name":"Potter Huiskes Bv",
    "wof:placetype":"venue"
},
  "geometry": {"coordinates":[6.78971,52.266331],"type":"Point"}
}