{
  "type": "Feature",
  "properties": {
    "iso:country":"NL",
    "sg:address":"Amaranthout 31",
    "sg:city":"Zoetermeer",
    "sg:orig_category":"Werving And Selectie Van Vast Personeel",
    "sg:phone":"+31 79 363 0433",
    "sg:postcode":"2719 MR",
    "sg:province":"Zuid-Holland",
    "wof:name":"Code Red Consult Bv",
    "wof:placetype":"venue"
},
  "geometry": {"coordinates":[4.4632210732,52.0467681885],"type":"Point"}
}