{
  "type": "Feature",
  "properties": {
    "addr:full":"Schuttekamp 111 Enschede Overijssel 7524 BK",
    "addr:housenumber":"111",
    "addr:postcode":"7524 bk",
    "addr:street":"Schuttekamp",
    "iso:country":"NL",
    "sg:address":"Schuttekamp 111",
    "sg:city":"Enschede",
    "sg:orig_category":"Adviesbureaus Bedrijfsorganisatie",
    "sg:phone":"+31 53 434 6485",
    "sg:postcode":"7524 BK",
    "sg:province":"Overijssel",
    "wof:name":"P&P",
    "wof:placetype":"venue"
},
  "geometry": {"coordinates":[6.908878,52.248222],"type":"Point"}
}