{
  "type": "Feature",
  "properties": {
    "addr:full":"Bloemendaalse Zeedijk 10 Zevenbergschen Hoek North Brabant 4765 BP",
    "addr:housenumber":"10",
    "addr:postcode":"4765 bp",
    "addr:street":"Bloemendaalse Zeedijk",
    "iso:country":"NL",
    "sg:address":"Bloemendaalse Zeedijk 10",
    "sg:city":"Zevenbergschen Hoek",
    "sg:classifiers":[
        {
            "category":"Retail",
            "subcategory":"Storage",
            "type":"Services"
        }
    ],
    "sg:phone":"+31 168 452 438",
    "sg:postcode":"4765 BP",
    "sg:province":"North Brabant",
    "sg:tags":[
        "opslag",
        "bewaring"
    ],
    "wof:name":"Hartog Logistics Bv",
    "wof:placetype":"venue"
},
  "geometry": {"coordinates":[4.682682991,51.6747627258],"type":"Point"}
}