{
  "type": "Feature",
  "properties": {
    "addr:full":"A Vd Bergln 39 Enschede Overijssel 7545 RV",
    "addr:housenumber":"39",
    "addr:postcode":"7545 rv",
    "addr:street":"A",
    "iso:country":"NL",
    "sg:address":"A Vd Bergln 39",
    "sg:city":"Enschede",
    "sg:orig_category":"Boekhandels",
    "sg:phone":"+31 53 430 6624",
    "sg:postcode":"7545 RV",
    "sg:province":"Overijssel",
    "wof:name":"Media Expresse",
    "wof:placetype":"venue"
},
  "geometry": {"coordinates":[6.8566,52.211689],"type":"Point"}
}