{
  "type": "Feature",
  "properties": {
    "addr:full":"Roemer Visscherstraat 62 Almere NL. 1321 CB",
    "addr:housenumber":"62",
    "addr:postcode":"1321 cb",
    "addr:street":"Roemer Visscherstraat;Nl.",
    "iso:country":"NL",
    "sg:address":"Roemer Visscherstraat 62",
    "sg:city":"Almere",
    "sg:orig_category":"Wegen And Sportterreinen",
    "sg:phone":"+31 36 535 0509",
    "sg:postcode":"1321 CB",
    "sg:province":"NL.",
    "wof:name":"D.A. Van Tongeren",
    "wof:placetype":"venue"
},
  "geometry": {"coordinates":[5.185713768,52.3615455627],"type":"Point"}
}