{
  "type": "Feature",
  "properties": {
    "iso:country":"NL",
    "sg:address":"Kanaalstr 29",
    "sg:city":"Amsterdam",
    "sg:orig_category":"Glas, Porselein En Aardewerk",
    "sg:phone":"+31 6 52006929",
    "sg:postcode":"1054 WZ",
    "sg:province":"Noord-Holland",
    "wof:name":"Persika Nova",
    "wof:placetype":"venue"
},
  "geometry": {"coordinates":[4.865977,52.362671],"type":"Point"}
}