{
  "type": "Feature",
  "properties": {
    "iso:country":"NL",
    "sg:address":"Achterstraat 35",
    "sg:city":"Woerden",
    "sg:orig_category":"Huishoudapparatuur, Televisies And Radio'S",
    "sg:phone":"+31 348 422 522",
    "sg:postcode":"3441 EG",
    "sg:province":"Utrecht",
    "wof:name":"Repond Service",
    "wof:placetype":"venue"
},
  "geometry": {"coordinates":[4.886699,52.086758],"type":"Point"}
}