{
  "type": "Feature",
  "properties": {
    "addr:full":"Dillenburgstr 84-86 Breda North Brabant 4835 ED",
    "addr:housenumber":"84-86",
    "addr:postcode":"4835 ed",
    "iso:country":"NL",
    "sg:address":"Dillenburgstr 84-86",
    "sg:city":"Breda",
    "sg:orig_category":"Postkantoren",
    "sg:phone":"+31 76 565 0222",
    "sg:postcode":"4835 ED",
    "sg:province":"North Brabant",
    "sg:website":"http://www.postkantoor.nl",
    "wof:name":"Postkantoor",
    "wof:placetype":"venue"
},
  "geometry": {"coordinates":[4.790034,51.569786],"type":"Point"}
}