{
  "type": "Feature",
  "properties": {
    "addr:full":"Hoogstr 9 Abcoude Utrecht 1391 BP",
    "addr:housenumber":"9",
    "addr:postcode":"1391 bp",
    "addr:street":"Hoogstr",
    "iso:country":"NL",
    "sg:address":"Hoogstr 9",
    "sg:city":"Abcoude",
    "sg:orig_category":"Verzekeringen - Verzekeringskantoren",
    "sg:phone":"+31 294 285 515",
    "sg:postcode":"1391 BP",
    "sg:province":"Utrecht",
    "wof:name":"Eerste Abcouder",
    "wof:placetype":"venue"
},
  "geometry": {"coordinates":[4.974658,52.271275],"type":"Point"}
}