{
  "type": "Feature",
  "properties": {
    "iso:country":"NL",
    "sg:address":"Romulushof 17",
    "sg:city":"Maastricht",
    "sg:orig_category":"Administratie- En Boekhoudkantoren",
    "sg:phone":"+31 43 343 5379",
    "sg:postcode":"6215 EJ",
    "sg:province":"Limburg",
    "wof:name":"Adcom",
    "wof:placetype":"venue"
},
  "geometry": {"coordinates":[5.645604,50.841927],"type":"Point"}
}