{
  "type": "Feature",
  "properties": {
    "addr:full":"De Biezen 2 Ijsselstein Ut Utrecht 3401 GD",
    "addr:housenumber":"2",
    "addr:postcode":"3401 gd",
    "addr:street":"De Biezen",
    "iso:country":"NL",
    "sg:address":"De Biezen 2",
    "sg:city":"Ijsselstein Ut",
    "sg:orig_category":"Zuivelproducten",
    "sg:phone":"+31 30 687 0220",
    "sg:postcode":"3401 GD",
    "sg:province":"Utrecht",
    "wof:name":"Lekkerkerker Kaas En Wijn Special",
    "wof:placetype":"venue"
},
  "geometry": {"coordinates":[5.027299,52.021954],"type":"Point"}
}