{
  "type": "Feature",
  "properties": {
    "addr:full":"Postbus 1390 Utrecht North Holland 3500 BJ",
    "addr:housenumber":"1390",
    "addr:postcode":"3500 bj",
    "addr:street":"Postbus",
    "iso:country":"NL",
    "sg:address":"Postbus 1390",
    "sg:city":"Utrecht",
    "sg:orig_category":"Verenigingen En Stichtingen",
    "sg:phone":"+31 30 230 6000",
    "sg:postcode":"3500 BJ",
    "sg:province":"North Holland",
    "wof:name":"Steunbeer, Sticht",
    "wof:placetype":"venue"
},
  "geometry": {"coordinates":[4.97469,52.272449],"type":"Point"}
}