{
  "type": "Feature",
  "properties": {
    "addr:full":"Dorpsstr 9 Bruchem Gelderland 5314 AD",
    "addr:housenumber":"9",
    "addr:postcode":"5314 ad",
    "addr:street":"Dorpsstr;Gelderland",
    "iso:country":"NL",
    "sg:address":"Dorpsstr 9",
    "sg:city":"Bruchem",
    "sg:orig_category":"Land- En Tuinbouw - Mechanisatie",
    "sg:phone":"+31 418 642 293",
    "sg:postcode":"5314 AD",
    "sg:province":"Gelderland",
    "wof:name":"Hobo",
    "wof:placetype":"venue"
},
  "geometry": {"coordinates":[5.236386,51.788387],"type":"Point"}
}