{
  "type": "Feature",
  "properties": {
    "iso:country":"NL",
    "sg:address":"Draakstr 13",
    "sg:city":"Groningen",
    "sg:orig_category":"Vertaalbureaus",
    "sg:phone":"+31 50 573 2864",
    "sg:postcode":"9742 TD",
    "sg:province":"Groningen",
    "wof:name":"Bulgarian Language Centre",
    "wof:placetype":"venue"
},
  "geometry": {"coordinates":[6.543297,53.225685],"type":"Point"}
}