{
  "type": "Feature",
  "properties": {
    "addr:full":"Beemdstraat 34 Eindhoven Noord-Brabant 5652 AB",
    "addr:housenumber":"34",
    "addr:postcode":"5652 ab",
    "addr:street":"Beemdstraat",
    "iso:country":"NL",
    "sg:address":"Beemdstraat 34",
    "sg:city":"Eindhoven",
    "sg:orig_category":"Architecten",
    "sg:phone":"+31 40 292 3700",
    "sg:postcode":"5652 AB",
    "sg:province":"Noord-Brabant",
    "wof:name":"Toon Van Aken Architektuur Bv",
    "wof:placetype":"venue"
},
  "geometry": {"coordinates":[5.450052,51.430199],"type":"Point"}
}