{
  "type": "Feature",
  "properties": {
    "addr:full":"Fazantenhof 122 Eemnes Utrecht 3755 EK",
    "addr:housenumber":"122",
    "addr:postcode":"3755 ek",
    "addr:street":"Fazantenhof",
    "iso:country":"NL",
    "sg:address":"Fazantenhof 122",
    "sg:city":"Eemnes",
    "sg:orig_category":"Homeopathie",
    "sg:phone":"+31 35 533 4257",
    "sg:postcode":"3755 EK",
    "sg:province":"Utrecht",
    "wof:name":"Bakker, A",
    "wof:placetype":"venue"
},
  "geometry": {"coordinates":[5.260758,52.254353],"type":"Point"}
}