{
  "type": "Feature",
  "properties": {
    "iso:country":"NL",
    "sg:address":"Ommeresstr 11",
    "sg:city":"Ommen",
    "sg:orig_category":"Autoschade- Herstelbedrijven",
    "sg:phone":"+31 529 451 294",
    "sg:postcode":"7731 XD",
    "sg:province":"Overijssel",
    "wof:name":"Koggel, H",
    "wof:placetype":"venue"
},
  "geometry": {"coordinates":[6.429764,52.524925],"type":"Point"}
}