{
  "type": "Feature",
  "properties": {
    "addr:full":"Oosteinde 76D S Gravenhage Zuid-Holland 2548 AM",
    "addr:housenumber":"76d;gravenhage",
    "addr:postcode":"2548",
    "addr:street":"Oosteinde;S",
    "iso:country":"NL",
    "sg:address":"Oosteinde 76D",
    "sg:city":"S Gravenhage",
    "sg:orig_category":"Logopedisten",
    "sg:phone":"+31 174 225 430",
    "sg:postcode":"2548 AM",
    "sg:province":"Zuid-Holland",
    "wof:name":"Logopediepraktijk Wateringse Veld",
    "wof:placetype":"venue"
},
  "geometry": {"coordinates":[4.2901,52.029888],"type":"Point"}
}