{
  "type": "Feature",
  "properties": {
    "iso:country":"NL",
    "sg:address":"Hertzogstraat 66Bb",
    "sg:city":"Den Helder",
    "sg:orig_category":"Verhuur Audiovisuele Apparatuur",
    "sg:phone":"+31 223 624 007",
    "sg:postcode":"1782 RP",
    "sg:province":"North Holland",
    "wof:name":"Fa Bakker Geluidsinstallatie",
    "wof:placetype":"venue"
},
  "geometry": {"coordinates":[4.757389,52.958454],"type":"Point"}
}