{
  "type": "Feature",
  "properties": {
    "addr:full":"Hoofdstr W 54 Noordwolde Fr Friesland 8391 AP",
    "addr:housenumber":"54",
    "addr:postcode":"8391 ap",
    "addr:street":"W",
    "iso:country":"NL",
    "sg:address":"Hoofdstr W 54",
    "sg:city":"Noordwolde Fr",
    "sg:orig_category":"Kappers",
    "sg:phone":"+31 561 431 658",
    "sg:postcode":"8391 AP",
    "sg:province":"Friesland",
    "wof:name":"Oord, W",
    "wof:placetype":"venue"
},
  "geometry": {"coordinates":[6.14197,52.891758],"type":"Point"}
}