{
  "type": "Feature",
  "properties": {
    "iso:country":"NL",
    "sg:address":"Grote Hout- Of Koningswg 49",
    "sg:city":"Velsen-Noord",
    "sg:orig_category":"Olie- And Gaswinning",
    "sg:phone":"+31 251 290 222",
    "sg:postcode":"1951 GN",
    "sg:province":"Noord-Holland",
    "wof:name":"Nederlandse Aardolie Maatschappij Bv",
    "wof:placetype":"venue"
},
  "geometry": {"coordinates":[4.645905,52.472397],"type":"Point"}
}