{
  "type": "Feature",
  "properties": {
    "addr:full":"Kupperswg 1 Haarlem Noord-Holland 2031 EA",
    "addr:housenumber":"1",
    "addr:postcode":"2031 ea",
    "addr:street":"Kupperswg",
    "iso:country":"NL",
    "sg:address":"Kupperswg 1",
    "sg:city":"Haarlem",
    "sg:orig_category":"Loodgieters",
    "sg:phone":"+31 23 532 0895",
    "sg:postcode":"2031 EA",
    "sg:province":"Noord-Holland",
    "wof:name":"Slierings Dakbedekkers",
    "wof:placetype":"venue"
},
  "geometry": {"coordinates":[4.653264,52.390934],"type":"Point"}
}