{
  "type": "Feature",
  "properties": {
    "iso:country":"NL",
    "sg:address":"Hoofdstraat 51",
    "sg:city":"Diever",
    "sg:orig_category":"Kappers",
    "sg:phone":"+31 521 591 542",
    "sg:postcode":"7981 AD",
    "sg:province":"Drenthe",
    "wof:name":"A.W. Kapper En Shop Vof",
    "wof:placetype":"venue"
},
  "geometry": {"coordinates":[6.3185520172,52.8555641174],"type":"Point"}
}