{
  "type": "Feature",
  "properties": {
    "addr:full":"Kanariestraat 37 Zundert Noord-Brabant 4881 WK",
    "addr:housenumber":"37",
    "addr:postcode":"4881 wk",
    "addr:street":"Kanariestraat",
    "iso:country":"NL",
    "sg:address":"Kanariestraat 37",
    "sg:city":"Zundert",
    "sg:orig_category":"Drukkerijen And Copyshops",
    "sg:phone":"+31 76 599 0280",
    "sg:postcode":"4881 WK",
    "sg:province":"Noord-Brabant",
    "wof:name":"Offsetdruk G. Vissers",
    "wof:placetype":"venue"
},
  "geometry": {"coordinates":[4.653289,51.466537],"type":"Point"}
}