{
  "type": "Feature",
  "properties": {
    "iso:country":"NL",
    "sg:address":"Bloemstraat 12",
    "sg:city":"Breda",
    "sg:orig_category":"Loodgieterswerk, Verwarming And Sanitaire Installaties",
    "sg:phone":"+31 76 561 4939",
    "sg:postcode":"4835 CE",
    "sg:province":"Noord-Brabant",
    "wof:name":"W.A. Van Den Berk",
    "wof:placetype":"venue"
},
  "geometry": {"coordinates":[4.785932,51.569687],"type":"Point"}
}