{
  "type": "Feature",
  "properties": {
    "addr:full":"Kleindorp 5 Merselo Limburg 5815 CL",
    "addr:housenumber":"5",
    "addr:postcode":"5815",
    "addr:street":"Kleindorp",
    "iso:country":"NL",
    "sg:address":"Kleindorp 5",
    "sg:city":"Merselo",
    "sg:orig_category":"Onderhoudswerken",
    "sg:phone":"+31 478 546 611",
    "sg:postcode":"5815 CL",
    "sg:province":"Limburg",
    "wof:name":"Verhoeven, Geert",
    "wof:placetype":"venue"
},
  "geometry": {"coordinates":[5.929764,51.530125],"type":"Point"}
}