{
  "type": "Feature",
  "properties": {
    "addr:full":"Hazendanspln 2 Maastricht Limburg 6215 JB",
    "addr:housenumber":"2",
    "addr:postcode":"6215 jb",
    "addr:street":"Hazendanspln",
    "iso:country":"NL",
    "sg:address":"Hazendanspln 2",
    "sg:city":"Maastricht",
    "sg:orig_category":"Kappers",
    "sg:phone":"+31 43 321 8160",
    "sg:postcode":"6215 JB",
    "sg:province":"Limburg",
    "wof:name":"Jan",
    "wof:placetype":"venue"
},
  "geometry": {"coordinates":[5.646668911,50.8461303711],"type":"Point"}
}