{
  "type": "Feature",
  "properties": {
    "iso:country":"NL",
    "sg:address":"Hoofdstr 17",
    "sg:city":"Amstenrade",
    "sg:orig_category":"Postkantoren",
    "sg:phone":"+31 46 442 1481",
    "sg:postcode":"6436 CA",
    "sg:province":"Limburg",
    "sg:website":"http://www.postkantoor.nl",
    "wof:name":"Postkantoor",
    "wof:placetype":"venue"
},
  "geometry": {"coordinates":[5.924,50.940819],"type":"Point"}
}