{
  "type": "Feature",
  "properties": {
    "addr:full":"Zandstr 49 Veenendaal Utrecht 3901 CJ",
    "addr:housenumber":"49",
    "addr:postcode":"3901 cj",
    "addr:street":"Zandstr",
    "iso:country":"NL",
    "sg:address":"Zandstr 49",
    "sg:city":"Veenendaal",
    "sg:orig_category":"Kappers",
    "sg:phone":"+31 318 551 283",
    "sg:postcode":"3901 CJ",
    "sg:province":"Utrecht",
    "wof:name":"Cb Headline",
    "wof:placetype":"venue"
},
  "geometry": {"coordinates":[5.5546741486,52.0289955139],"type":"Point"}
}