{
  "type": "Feature",
  "properties": {
    "iso:country":"NL",
    "sg:address":"Lariksln 5",
    "sg:city":"Marum",
    "sg:orig_category":"Kamerverhuur En -Bemiddeling",
    "sg:phone":"+31 594 644 873",
    "sg:postcode":"9363 JT",
    "sg:province":"Groningen",
    "sg:website":"http://www.ottema.com",
    "wof:name":"Ottema Kamer & Verhuur",
    "wof:placetype":"venue"
},
  "geometry": {"coordinates":[6.2687568665,53.1444396973],"type":"Point"}
}