{
  "type": "Feature",
  "properties": {
    "addr:full":"Raadhuisstr 121 Hoogerheide Noord-Brabant 4631 ND",
    "addr:housenumber":"121",
    "addr:postcode":"4631 nd",
    "iso:country":"NL",
    "sg:address":"Raadhuisstr 121",
    "sg:city":"Hoogerheide",
    "sg:orig_category":"Schoenen",
    "sg:phone":"+31 164 612 829",
    "sg:postcode":"4631 ND",
    "sg:province":"Noord-Brabant",
    "wof:name":"Borremans",
    "wof:placetype":"venue"
},
  "geometry": {"coordinates":[4.323648,51.423492],"type":"Point"}
}