{
  "type": "Feature",
  "properties": {
    "addr:full":"A Hoogvlietstr 33 Vlaardingen Zuid-Holland 3134 CA",
    "addr:housenumber":"33",
    "addr:postcode":"3134 ca",
    "iso:country":"NL",
    "sg:address":"A Hoogvlietstr 33",
    "sg:city":"Vlaardingen",
    "sg:orig_category":"Video - Faciliteiten En Producties",
    "sg:phone":"+31 10 248 0368",
    "sg:postcode":"3134 CA",
    "sg:province":"Zuid-Holland",
    "sg:website":"http://www.afs-video.nl",
    "wof:name":"A'Fs Bv",
    "wof:placetype":"venue"
},
  "geometry": {"coordinates":[4.34989,51.90868],"type":"Point"}
}