{
  "type": "Feature",
  "properties": {
    "iso:country":"NL",
    "sg:address":"Vrijthof 20",
    "sg:city":"Maastricht",
    "sg:orig_category":"Notarissen",
    "sg:phone":"+31 43 321 7174",
    "sg:postcode":"6211 LD",
    "sg:province":"Limburg",
    "wof:name":"Versteeg & Giesbers Notarissen",
    "wof:placetype":"venue"
},
  "geometry": {"coordinates":[5.688615,50.848331],"type":"Point"}
}