{
  "type": "Feature",
  "properties": {
    "addr:full":"Soldaatwg 6 Wormerveer North Holland 1521 RL",
    "addr:housenumber":"6",
    "addr:postcode":"1521 rl",
    "addr:street":"Soldaatwg",
    "iso:country":"NL",
    "sg:address":"Soldaatwg 6",
    "sg:city":"Wormerveer",
    "sg:orig_category":"Kappersbenodigdheden",
    "sg:phone":"+31 75 670 0699",
    "sg:postcode":"1521 RL",
    "sg:province":"North Holland",
    "sg:website":"http://www.alfaparf.nl",
    "wof:name":"Alfaparf Nederland Bv",
    "wof:placetype":"venue"
},
  "geometry": {"coordinates":[4.784001,52.507843],"type":"Point"}
}