{
  "type": "Feature",
  "properties": {
    "iso:country":"NL",
    "sg:address":"Julianastr 13",
    "sg:city":"Rosmalen",
    "sg:orig_category":"Koeltechniek",
    "sg:phone":"+31 73 644 4096",
    "sg:postcode":"5246 XG",
    "sg:province":"North Brabant",
    "wof:name":"Dielbandhoesing",
    "wof:placetype":"venue"
},
  "geometry": {"coordinates":[5.340926,51.701683],"type":"Point"}
}