{
  "type": "Feature",
  "properties": {
    "addr:full":"Harfsensestg 28 Harfsen Gelderland 7217 ME",
    "addr:housenumber":"28",
    "addr:postcode":"7217 me",
    "addr:street":"Harfsensestg;Gelderland",
    "iso:country":"NL",
    "sg:address":"Harfsensestg 28",
    "sg:city":"Harfsen",
    "sg:orig_category":"Metaalbewerking",
    "sg:phone":"+31 575 431 682",
    "sg:postcode":"7217 ME",
    "sg:province":"Gelderland",
    "wof:name":"Eska-Tech",
    "wof:placetype":"venue"
},
  "geometry": {"coordinates":[6.293514,52.180973],"type":"Point"}
}