{
  "type": "Feature",
  "properties": {
    "addr:full":"Apeldoornseweg 160 Vaassen Gelderland 8172 EP",
    "addr:housenumber":"160",
    "addr:postcode":"8172 ep",
    "addr:street":"Apeldoornseweg;Gelderland",
    "iso:country":"NL",
    "sg:address":"Apeldoornseweg 160",
    "sg:city":"Vaassen",
    "sg:orig_category":"Voeding, Dranken And Tabak Gh",
    "sg:phone":"+31 578 571 406",
    "sg:postcode":"8172 EP",
    "sg:province":"Gelderland",
    "wof:name":"Snack Service Hans De Jong",
    "wof:placetype":"venue"
},
  "geometry": {"coordinates":[5.959554,52.27272],"type":"Point"}
}