{
  "type": "Feature",
  "properties": {
    "iso:country":"NL",
    "sg:address":"Herenwg 269",
    "sg:city":"Wilnis",
    "sg:orig_category":"Medische Installaties En Instrumenten",
    "sg:phone":"+31 297 282 101",
    "sg:postcode":"3648 CH",
    "sg:province":"Utrecht",
    "wof:name":"Oostveen Bv, Van",
    "wof:placetype":"venue"
},
  "geometry": {"coordinates":[4.875989,52.199116],"type":"Point"}
}