{
  "type": "Feature",
  "properties": {
    "addr:full":"Energiewg 17 Harmelen Utrecht 3481 MC",
    "addr:housenumber":"17",
    "addr:postcode":"3481 mc",
    "addr:street":"Energiewg",
    "iso:country":"NL",
    "sg:address":"Energiewg 17",
    "sg:city":"Harmelen",
    "sg:orig_category":"Parketvloeren",
    "sg:phone":"+31 348 444 070",
    "sg:postcode":"3481 MC",
    "sg:province":"Utrecht",
    "sg:website":"http://www.beversvloeren.nl",
    "wof:name":"Bevers Houten Vloeren",
    "wof:placetype":"venue"
},
  "geometry": {"coordinates":[4.947065,52.098957],"type":"Point"}
}