{
  "type": "Feature",
  "properties": {
    "addr:full":"Julianalaan 64 Vleuten Utrecht 3451 CZ",
    "addr:housenumber":"64",
    "addr:postcode":"3451",
    "addr:street":"Julianalaan",
    "iso:country":"NL",
    "sg:address":"Julianalaan 64",
    "sg:city":"Vleuten",
    "sg:orig_category":"Binnenhuisarchitecten",
    "sg:phone":"+31 30 677 4174",
    "sg:postcode":"3451 CZ",
    "sg:province":"Utrecht",
    "wof:name":"M.C. Ruijs",
    "wof:placetype":"venue"
},
  "geometry": {"coordinates":[5.011314,52.099705],"type":"Point"}
}