{
  "type": "Feature",
  "properties": {
    "addr:full":"Karpervijver 1B Zeist Utrecht 3703 CJ",
    "addr:housenumber":"1b",
    "addr:postcode":"3703 cj",
    "addr:street":"Karpervijver",
    "iso:country":"NL",
    "sg:address":"Karpervijver 1B",
    "sg:city":"Zeist",
    "sg:orig_category":"Bloemen And Planten",
    "sg:phone":"+31 30 691 8145",
    "sg:postcode":"3703 CJ",
    "sg:province":"Utrecht",
    "wof:name":"H. Van Burken",
    "wof:placetype":"venue"
},
  "geometry": {"coordinates":[5.239536,52.080074],"type":"Point"}
}