{
  "type": "Feature",
  "properties": {
    "addr:full":"Margriet 56 Hardenberg Overijssel 7772 ND",
    "addr:housenumber":"56",
    "addr:postcode":"7772 nd",
    "addr:street":"Margriet",
    "iso:country":"NL",
    "sg:address":"Margriet 56",
    "sg:city":"Hardenberg",
    "sg:orig_category":"Boekhouders",
    "sg:phone":"+31 523 270 957",
    "sg:postcode":"7772 ND",
    "sg:province":"Overijssel",
    "wof:name":"Liebrechts Administraties",
    "wof:placetype":"venue"
},
  "geometry": {"coordinates":[6.651723,52.579575],"type":"Point"}
}