{
  "type": "Feature",
  "properties": {
    "addr:full":"Breedschotsestraat 18 Rijsbergen North Brabant 4891 PL",
    "addr:housenumber":"18",
    "addr:postcode":"4891 pl",
    "addr:street":"Breedschotsestraat",
    "iso:country":"NL",
    "sg:address":"Breedschotsestraat 18",
    "sg:city":"Rijsbergen",
    "sg:orig_category":"Hoefdierhouderijen",
    "sg:phone":"+31 76 596 3766",
    "sg:postcode":"4891 PL",
    "sg:province":"North Brabant",
    "wof:name":"M.E.C. Billet",
    "wof:placetype":"venue"
},
  "geometry": {"coordinates":[4.700989,51.493694],"type":"Point"}
}