{
  "type": "Feature",
  "properties": {
    "addr:full":"Ons Limburgstraat 66A Kerkrade Limburg 6466 CD",
    "addr:housenumber":"66a",
    "addr:postcode":"6466 cd",
    "addr:street":"Ons Limburgstraat",
    "iso:country":"NL",
    "sg:address":"Ons Limburgstraat 66A",
    "sg:city":"Kerkrade",
    "sg:orig_category":"Bibliotheken And Openbare Archieven",
    "sg:phone":"+31 45 541 3708",
    "sg:postcode":"6466 CD",
    "sg:province":"Limburg",
    "wof:name":"Openbare Bibliotheek",
    "wof:placetype":"venue"
},
  "geometry": {"coordinates":[6.030876,50.859882],"type":"Point"}
}