{
  "type": "Feature",
  "properties": {
    "iso:country":"NL",
    "sg:address":"Hooiwg 196",
    "sg:city":"Paterswolde",
    "sg:orig_category":"Sportverenigingen En Ontspannings- Verenigingen",
    "sg:phone":"+31 50 309 1407",
    "sg:postcode":"9765 EM",
    "sg:province":"Provincie Drenthe",
    "wof:name":"Hockeyclub Eelde",
    "wof:placetype":"venue"
},
  "geometry": {"coordinates":[6.55451,53.148743],"type":"Point"}
}