{
  "type": "Feature",
  "properties": {
    "addr:full":"Provinciepassage 11 Alphen Aan Den Ryn Zuid-Holland 2408 GT",
    "addr:housenumber":"11",
    "addr:postcode":"2408 gt",
    "addr:street":"Provinciepassage;Aan Den Ryn",
    "iso:country":"NL",
    "sg:address":"Provinciepassage 11",
    "sg:city":"Alphen Aan Den Ryn",
    "sg:orig_category":"Autorijscholen",
    "sg:phone":"+31 6 25056103",
    "sg:postcode":"2408 GT",
    "sg:province":"Zuid-Holland",
    "wof:name":"Challenge",
    "wof:placetype":"venue"
},
  "geometry": {"coordinates":[4.651569,52.124123],"type":"Point"}
}