{
  "type": "Feature",
  "properties": {
    "addr:full":"Doormanstr 6 Huissen Gelderland 6852 AK",
    "addr:housenumber":"6",
    "addr:postcode":"6852 ak",
    "addr:street":"Doormanstr;Gelderland",
    "iso:country":"NL",
    "sg:address":"Doormanstr 6",
    "sg:city":"Huissen",
    "sg:orig_category":"Bloemen En Planten - Groothandel",
    "sg:phone":"+31 26 325 0194",
    "sg:postcode":"6852 AK",
    "sg:province":"Gelderland",
    "wof:name":"Hofstede-Scholten",
    "wof:placetype":"venue"
},
  "geometry": {"coordinates":[5.930303,51.939602],"type":"Point"}
}