{
  "type": "Feature",
  "properties": {
    "addr:full":"Kerkstraat 81 Wormerveer Noord-Holland 1521 JD",
    "addr:housenumber":"81",
    "addr:postcode":"1521 jd",
    "addr:street":"Kerkstraat",
    "iso:country":"NL",
    "sg:address":"Kerkstraat 81",
    "sg:city":"Wormerveer",
    "sg:orig_category":"Recreatie",
    "sg:phone":"+31 75 628 7643",
    "sg:postcode":"1521 JD",
    "sg:province":"Noord-Holland",
    "wof:name":"Kerkstraat",
    "wof:placetype":"venue"
},
  "geometry": {"coordinates":[4.789275,52.494846],"type":"Point"}
}