{
  "type": "Feature",
  "properties": {
    "addr:full":"Nw Tiendwg 11A Krimpen Ad Yssel South Holland 2922 EN",
    "addr:housenumber":"11a",
    "addr:postcode":"2922 en",
    "addr:street":"Yssel",
    "iso:country":"NL",
    "sg:address":"Nw Tiendwg 11A",
    "sg:city":"Krimpen Ad Yssel",
    "sg:orig_category":"Bedrijfsopleidingen",
    "sg:phone":"+31 180 552 260",
    "sg:postcode":"2922 EN",
    "sg:province":"South Holland",
    "sg:website":"http://www.visie-in-bedrijf.nl",
    "wof:name":"Burg, Van Den",
    "wof:placetype":"venue"
},
  "geometry": {"coordinates":[4.59243,51.918571],"type":"Point"}
}