{
  "type": "Feature",
  "properties": {
    "addr:full":"B Ballotstr 6 Heerhugowaard Noord-Holland 1704 SK",
    "addr:housenumber":"6",
    "addr:street":"1704",
    "iso:country":"NL",
    "sg:address":"B Ballotstr 6",
    "sg:city":"Heerhugowaard",
    "sg:orig_category":"Houtwormverdelging",
    "sg:phone":"+31 800 0242000",
    "sg:postcode":"1704 SK",
    "sg:province":"Noord-Holland",
    "wof:name":"Attack",
    "wof:placetype":"venue"
},
  "geometry": {"coordinates":[4.830237,52.688507],"type":"Point"}
}