{
  "type": "Feature",
  "properties": {
    "addr:full":"Marialn 101 Zwanenburg Noord-Holland 1161 XB",
    "addr:housenumber":"101",
    "addr:postcode":"1161 xb",
    "addr:street":"Zwanenburg",
    "iso:country":"NL",
    "sg:address":"Marialn 101",
    "sg:city":"Zwanenburg",
    "sg:orig_category":"Webdesign Bureaus",
    "sg:phone":"+31 20 497 6811",
    "sg:postcode":"1161 XB",
    "sg:province":"Noord-Holland",
    "sg:website":"http://www.bratpack.nl",
    "wof:name":"Bratpack",
    "wof:placetype":"venue"
},
  "geometry": {"coordinates":[4.7472300529,52.376625061],"type":"Point"}
}