{
  "type": "Feature",
  "properties": {
    "addr:full":"V Rietln 25A Linschoten Utrecht 3461 HW",
    "addr:housenumber":"25a",
    "addr:postcode":"3461 hw",
    "iso:country":"NL",
    "sg:address":"V Rietln 25A",
    "sg:city":"Linschoten",
    "sg:classifiers":[
        {
            "category":"Retail",
            "subcategory":"Auto Repair",
            "type":"Services"
        }
    ],
    "sg:phone":"+31 348 423 618",
    "sg:postcode":"3461 HW",
    "sg:province":"Utrecht",
    "sg:tags":[
        "garage"
    ],
    "wof:name":"Colj?, H A",
    "wof:placetype":"venue"
},
  "geometry": {"coordinates":[4.915227,52.061867],"type":"Point"}
}