{
  "type": "Feature",
  "properties": {
    "addr:full":"Heslingahuis 9 Almelo Overijssel 7608 HR",
    "addr:housenumber":"9",
    "addr:postcode":"7608 hr",
    "addr:street":"Heslingahuis",
    "iso:country":"NL",
    "sg:address":"Heslingahuis 9",
    "sg:city":"Almelo",
    "sg:orig_category":"Keuringsdiensten",
    "sg:phone":"+31 546 493 887",
    "sg:postcode":"7608 HR",
    "sg:province":"Overijssel",
    "wof:name":"Hoope, J Ten",
    "wof:placetype":"venue"
},
  "geometry": {"coordinates":[6.672425,52.380692],"type":"Point"}
}