{
  "type": "Feature",
  "properties": {
    "addr:full":"Berglustln 3 Rotterdam Zuid-Holland 3054 BA",
    "addr:housenumber":"3",
    "addr:postcode":"3054 ba",
    "addr:street":"Berglustln",
    "iso:country":"NL",
    "sg:address":"Berglustln 3",
    "sg:city":"Rotterdam",
    "sg:orig_category":"Adviesbureaus Bouwkunde",
    "sg:phone":"+31 10 418 0648",
    "sg:postcode":"3054 BA",
    "sg:province":"Zuid-Holland",
    "wof:name":"Huising, Bouwk Adv & Management",
    "wof:placetype":"venue"
},
  "geometry": {"coordinates":[4.492569,51.954422],"type":"Point"}
}