{
  "type": "Feature",
  "properties": {
    "addr:full":"Westplantsoen 64 Delft Zuid-Holland 2613 GM",
    "addr:housenumber":"64",
    "addr:postcode":"2613 gm",
    "addr:street":"Westplantsoen",
    "iso:country":"NL",
    "sg:address":"Westplantsoen 64",
    "sg:city":"Delft",
    "sg:orig_category":"Loodgieterswerk, Verwarming And Sanitaire Installaties",
    "sg:phone":"+31 15 214 3645",
    "sg:postcode":"2613 GM",
    "sg:province":"Zuid-Holland",
    "wof:name":"Van Bemmelen",
    "wof:placetype":"venue"
},
  "geometry": {"coordinates":[4.347062,52.007755],"type":"Point"}
}