{
  "type": "Feature",
  "properties": {
    "addr:full":"Postbus 4603 Breda Noord-Brabant 4803 EP",
    "addr:housenumber":"4603",
    "addr:postcode":"breda;4803 ep",
    "addr:street":"Postbus",
    "iso:country":"NL",
    "sg:address":"Postbus 4603",
    "sg:city":"Breda",
    "sg:orig_category":"Verzekeringen - Verzekeringskantoren",
    "sg:phone":"+31 76 565 6227",
    "sg:postcode":"4803 EP",
    "sg:province":"Noord-Brabant",
    "sg:website":"http://www.iiccompany.com",
    "wof:name":"Iic Company Bv",
    "wof:placetype":"venue"
},
  "geometry": {"coordinates":[4.77492,51.588699],"type":"Point"}
}