{
  "type": "Feature",
  "properties": {
    "addr:full":"G Metsuln 23 Eindhoven Noord-Brabant 5613 LC",
    "addr:housenumber":"23",
    "addr:postcode":"5613 lc",
    "iso:country":"NL",
    "sg:address":"G Metsuln 23",
    "sg:city":"Eindhoven",
    "sg:orig_category":"Psychologen",
    "sg:phone":"+31 40 212 5722",
    "sg:postcode":"5613 LC",
    "sg:province":"Noord-Brabant",
    "wof:name":"Verhulst, Drs F J C M",
    "wof:placetype":"venue"
},
  "geometry": {"coordinates":[5.484105,51.434471],"type":"Point"}
}