{
  "type": "Feature",
  "properties": {
    "iso:country":"NL",
    "sg:address":"Penningwg 44A",
    "sg:city":"Etten Leur",
    "sg:classifiers":[
        {
            "category":"Manufacturing",
            "subcategory":"Motor Vehicles & Parts",
            "type":"Manufacturing & Wholesale Goods"
        }
    ],
    "sg:phone":"+31 76 504 1222",
    "sg:postcode":"4879 AG",
    "sg:province":"Noord-Brabant",
    "sg:tags":[
        "kleding",
        "scooter",
        "en",
        "-"
    ],
    "sg:website":"http://www.damen-leathers.com",
    "wof:name":"Damen Schuh",
    "wof:placetype":"venue"
},
  "geometry": {"coordinates":[4.618691,51.563576],"type":"Point"}
}