{
  "type": "Feature",
  "properties": {
    "addr:full":"Lange Putstraat 10 'S Hertogenbosch Noord-Brabant 5211 KN",
    "addr:housenumber":"10",
    "addr:postcode":"5211 kn",
    "addr:street":"Lange Putstraat;' S",
    "iso:country":"NL",
    "sg:address":"Lange Putstraat 10",
    "sg:city":"'S Hertogenbosch",
    "sg:classifiers":[
        {
            "category":"Shopping",
            "subcategory":"Gifts & Souvenirs",
            "type":"Retail Goods"
        }
    ],
    "sg:phone":"+31 73 614 0481",
    "sg:postcode":"5211 KN",
    "sg:province":"Noord-Brabant",
    "sg:tags":[
        "geschenken"
    ],
    "wof:name":"Farfallino",
    "wof:placetype":"venue"
},
  "geometry": {"coordinates":[5.305469,51.687176],"type":"Point"}
}