{
  "type": "Feature",
  "properties": {
    "addr:full":"Postbus 28062 Rotterdam Zuid-Holland 3003 KB",
    "addr:housenumber":"28062",
    "addr:postcode":"3003 kb",
    "addr:street":"Postbus",
    "iso:country":"NL",
    "sg:address":"Postbus 28062",
    "sg:city":"Rotterdam",
    "sg:orig_category":"Webdesign Bureaus",
    "sg:phone":"+31 10 265 5101",
    "sg:postcode":"3003 KB",
    "sg:province":"Zuid-Holland",
    "sg:website":"http://www.1024solutions.nl",
    "wof:name":"Webdesign & Grafische Vormgeving",
    "wof:placetype":"venue"
},
  "geometry": {"coordinates":[4.4784197807,51.9228897095],"type":"Point"}
}