{
  "type": "Feature",
  "properties": {
    "addr:full":"Kloosterstr 19 Venlo Limburg 5921 HA",
    "addr:housenumber":"19",
    "addr:postcode":"5921 ha",
    "addr:street":"Kloosterstr",
    "iso:country":"NL",
    "sg:address":"Kloosterstr 19",
    "sg:city":"Venlo",
    "sg:orig_category":"Verlichting",
    "sg:phone":"+31 77 382 2960",
    "sg:postcode":"5921 HA",
    "sg:province":"Limburg",
    "wof:name":"Lempke, 'T",
    "wof:placetype":"venue"
},
  "geometry": {"coordinates":[6.152867,51.366272],"type":"Point"}
}