{
  "type": "Feature",
  "properties": {
    "addr:full":"Oberonwg 288 Spykenisse Zuid-Holland 3208 PG",
    "addr:housenumber":"288",
    "addr:postcode":"3208 pg",
    "addr:street":"Oberonwg",
    "iso:country":"NL",
    "sg:address":"Oberonwg 288",
    "sg:city":"Spykenisse",
    "sg:orig_category":"Fitnesscentra",
    "sg:phone":"+31 181 674 004",
    "sg:postcode":"3208 PG",
    "sg:province":"Zuid-Holland",
    "sg:website":"http://www.studiopowerenergie.nl",
    "wof:name":"Studio Power Energie",
    "wof:placetype":"venue"
},
  "geometry": {"coordinates":[4.318886,51.83424],"type":"Point"}
}