{
  "type": "Feature",
  "properties": {
    "iso:country":"NL",
    "sg:address":"Doelenstr 6A",
    "sg:city":"Eindhoven",
    "sg:orig_category":"Beeldende Kunstenaars",
    "sg:phone":"+31 40 252 0753",
    "sg:postcode":"5616 RL",
    "sg:province":"North Brabant",
    "sg:website":"http://m-lommers.nl",
    "wof:name":"Margo Lommers",
    "wof:placetype":"venue"
},
  "geometry": {"coordinates":[5.453901,51.442665],"type":"Point"}
}