{
  "type": "Feature",
  "properties": {
    "addr:full":"Eurokd 46 Amsterdam Noord-Holland 1060 RZ",
    "addr:housenumber":"46",
    "addr:postcode":"1060 rz",
    "addr:street":"Eurokd",
    "iso:country":"NL",
    "sg:address":"Eurokd 46",
    "sg:city":"Amsterdam",
    "sg:orig_category":"Kantoor- En Secretariaatsservice",
    "sg:phone":"+31 20 610 4488",
    "sg:postcode":"1060 RZ",
    "sg:province":"Noord-Holland",
    "wof:name":"Personal Touch",
    "wof:placetype":"venue"
},
  "geometry": {"coordinates":[4.7775402069,52.3498802185],"type":"Point"}
}