{
  "type": "Feature",
  "properties": {
    "addr:full":"Keizerstr 48 Landgraaf Limburg 6371 AJ",
    "addr:housenumber":"48",
    "addr:postcode":"6371 aj",
    "addr:street":"Keizerstr",
    "iso:country":"NL",
    "sg:address":"Keizerstr 48",
    "sg:city":"Landgraaf",
    "sg:orig_category":"Begrafenisverzorging",
    "sg:phone":"+31 45 531 1841",
    "sg:postcode":"6371 AJ",
    "sg:province":"Limburg",
    "wof:name":"Schaesberg",
    "wof:placetype":"venue"
},
  "geometry": {"coordinates":[6.0235,50.903328],"type":"Point"}
}