{
  "type": "Feature",
  "properties": {
    "addr:full":"Molenstraat 9 Harskamp Gelderland 6732 BP",
    "addr:housenumber":"9",
    "addr:postcode":"6732 bp",
    "addr:street":"Molenstraat;Gelderland",
    "iso:country":"NL",
    "sg:address":"Molenstraat 9",
    "sg:city":"Harskamp",
    "sg:orig_category":"Autokeuringen",
    "sg:phone":"+31 318 453 005",
    "sg:postcode":"6732 BP",
    "sg:province":"Gelderland",
    "wof:name":"Paul'S Car Cleaning",
    "wof:placetype":"venue"
},
  "geometry": {"coordinates":[5.755587,52.12426],"type":"Point"}
}