{
  "type": "Feature",
  "properties": {
    "addr:full":"Zaaiwaard 10 Aalst Gld Gelderland 5308 JK",
    "addr:housenumber":"10",
    "addr:postcode":"5308 jk",
    "addr:street":"Zaaiwaard;Gld Gelderland",
    "iso:country":"NL",
    "sg:address":"Zaaiwaard 10",
    "sg:city":"Aalst Gld",
    "sg:orig_category":"Pleziervaartuigen And Reparatie",
    "sg:phone":"+31 418 677 033",
    "sg:postcode":"5308 JK",
    "sg:province":"Gelderland",
    "wof:name":"Paay Jachtbouw Betimmeringen Vof",
    "wof:placetype":"venue"
},
  "geometry": {"coordinates":[5.11629,51.78339],"type":"Point"}
}