{
  "type": "Feature",
  "properties": {
    "addr:full":"Kerkstraat 12 Boekel North Brabant 5427 BC",
    "addr:housenumber":"12",
    "addr:postcode":"5427 bc",
    "addr:street":"Kerkstraat",
    "iso:country":"NL",
    "sg:address":"Kerkstraat 12",
    "sg:city":"Boekel",
    "sg:orig_category":"Opticiens",
    "sg:phone":"+31 492 321 029",
    "sg:postcode":"5427 BC",
    "sg:province":"North Brabant",
    "wof:name":"Franssen Optiek",
    "wof:placetype":"venue"
},
  "geometry": {"coordinates":[5.6724090576,51.6048774719],"type":"Point"}
}