{
  "type": "Feature",
  "properties": {
    "addr:full":"Kerkstraat 20 Didam Gelderland 6941 AG",
    "addr:housenumber":"20",
    "addr:postcode":"6941",
    "addr:street":"Kerkstraat;Gelderland",
    "iso:country":"NL",
    "sg:address":"Kerkstraat 20",
    "sg:city":"Didam",
    "sg:orig_category":"Banken And Kredietinstellingen",
    "sg:phone":"+31 316 297 777",
    "sg:postcode":"6941 AG",
    "sg:province":"Gelderland",
    "wof:name":"Rabobank",
    "wof:placetype":"venue"
},
  "geometry": {"coordinates":[6.129089,51.941586],"type":"Point"}
}