{
  "type": "Feature",
  "properties": {
    "addr:full":"Ijselstraat 25 Rotterdam Zuid-Holland 3029 BM",
    "addr:housenumber":"25",
    "addr:postcode":"3029 bm",
    "addr:street":"Ijselstraat",
    "iso:country":"NL",
    "sg:address":"Ijselstraat 25",
    "sg:city":"Rotterdam",
    "sg:classifiers":[
        {
            "category":"Retail",
            "subcategory":"Storage",
            "type":"Services"
        }
    ],
    "sg:phone":"+31 10 477 7366",
    "sg:postcode":"3029 BM",
    "sg:province":"Zuid-Holland",
    "sg:tags":[
        "opslag",
        "bewaring"
    ],
    "wof:name":"European Juice Terminal Bv",
    "wof:placetype":"venue"
},
  "geometry": {"coordinates":[4.4350762367,51.9040107727],"type":"Point"}
}