{
  "type": "Feature",
  "properties": {
    "iso:country":"NL",
    "sg:address":"Noord Parallelweg 1C",
    "sg:city":"Wierden",
    "sg:orig_category":"Kantoorartikelen",
    "sg:phone":"+31 546 577 001",
    "sg:postcode":"7641 AW",
    "sg:province":"Overijssel",
    "wof:name":"Holiday Presentatie Licht & Geluid",
    "wof:placetype":"venue"
},
  "geometry": {"coordinates":[6.5908908844,52.3618392944],"type":"Point"}
}