{
  "type": "Feature",
  "properties": {
    "addr:full":"Vd Berkhofwg 5 Kockengen Utrecht 3628 BD",
    "addr:housenumber":"5",
    "addr:postcode":"3628 bd",
    "addr:street":"Kockengen",
    "iso:country":"NL",
    "sg:address":"Vd Berkhofwg 5",
    "sg:city":"Kockengen",
    "sg:orig_category":"Onderhoudswerken",
    "sg:phone":"+31 346 241 517",
    "sg:postcode":"3628 BD",
    "sg:province":"Utrecht",
    "wof:name":"Dijk, Frans Van",
    "wof:placetype":"venue"
},
  "geometry": {"coordinates":[4.952677,52.148949],"type":"Point"}
}