{
  "type": "Feature",
  "properties": {
    "addr:full":"Hooidrift 127 Rotterdam Zuid-Holland 3023 KL",
    "addr:housenumber":"127",
    "addr:postcode":"3023 kl",
    "addr:street":"Hooidrift",
    "iso:country":"NL",
    "sg:address":"Hooidrift 127",
    "sg:city":"Rotterdam",
    "sg:classifiers":[
        {
            "category":"Bars & Pubs",
            "type":"Food & Drink"
        }
    ],
    "sg:phone":"+31 10 425 5625",
    "sg:postcode":"3023 KL",
    "sg:province":"Zuid-Holland",
    "wof:name":"Koffieshop Manolya",
    "wof:placetype":"venue"
},
  "geometry": {"coordinates":[4.449084,51.913464],"type":"Point"}
}