{
  "type": "Feature",
  "properties": {
    "addr:full":"Oude Graaf 2 Weert Limburg 6002 NL",
    "addr:housenumber":"2",
    "addr:postcode":"6002 nl",
    "addr:street":"Oude Graaf",
    "iso:country":"NL",
    "sg:address":"Oude Graaf 2",
    "sg:city":"Weert",
    "sg:orig_category":"Gespecialiseerde Bouw",
    "sg:phone":"+31 495 580 000",
    "sg:postcode":"6002 NL",
    "sg:province":"Limburg",
    "wof:name":"Derckx Weert Bv",
    "wof:placetype":"venue"
},
  "geometry": {"coordinates":[5.658589,51.244442],"type":"Point"}
}