{
  "type": "Feature",
  "properties": {
    "addr:full":"V Beeckstr 65 Zoetermeer Zuid-Holland 2722 BC",
    "addr:housenumber":"65",
    "addr:postcode":"2722 bc",
    "iso:country":"NL",
    "sg:address":"V Beeckstr 65",
    "sg:city":"Zoetermeer",
    "sg:orig_category":"Scholen Voor Basisonderwijs",
    "sg:phone":"+31 79 331 3129",
    "sg:postcode":"2722 BC",
    "sg:province":"Zuid-Holland",
    "wof:name":"Achtsprong Rk, De",
    "wof:placetype":"venue"
},
  "geometry": {"coordinates":[4.51464,52.053829],"type":"Point"}
}