{
  "type": "Feature",
  "properties": {
    "addr:full":"Noordewierwg 138 Amersfoort Utrecht 3812 DN",
    "addr:housenumber":"138",
    "addr:postcode":"3812 dn",
    "iso:country":"NL",
    "sg:address":"Noordewierwg 138",
    "sg:city":"Amersfoort",
    "sg:orig_category":"Adviesbureaus Bedrijfsorganisatie",
    "sg:phone":"+31 33 461 3612",
    "sg:postcode":"3812 DN",
    "sg:province":"Utrecht",
    "wof:name":"Promess Consultancy",
    "wof:placetype":"venue"
},
  "geometry": {"coordinates":[5.360052,52.160751],"type":"Point"}
}