{
  "type": "Feature",
  "properties": {
    "addr:full":"Slangenburgweg 61 Rotterdam Zuid-Holland 3077 JL",
    "addr:housenumber":"61",
    "addr:postcode":"3077 jl",
    "addr:street":"Slangenburgweg",
    "iso:country":"NL",
    "sg:address":"Slangenburgweg 61",
    "sg:city":"Rotterdam",
    "sg:orig_category":"Onderhoud And Reparatie Kantoorapparatuur",
    "sg:phone":"+31 10 292 7466",
    "sg:postcode":"3077 JL",
    "sg:province":"Zuid-Holland",
    "wof:name":"Hd Computers",
    "wof:placetype":"venue"
},
  "geometry": {"coordinates":[4.569878,51.896439],"type":"Point"}
}