{
  "type": "Feature",
  "properties": {
    "iso:country":"NL",
    "sg:address":"Beverweertseweg 14",
    "sg:city":"Werkhoven",
    "sg:orig_category":"Fitnesscentra",
    "sg:phone":"+31 343 551 490",
    "sg:postcode":"3985 RD",
    "sg:province":"Utrecht",
    "wof:name":"C.E.J. Dorresteijn De Sain",
    "wof:placetype":"venue"
},
  "geometry": {"coordinates":[5.248101,52.02507],"type":"Point"}
}