{
  "type": "Feature",
  "properties": {
    "addr:full":"Lippe-Biesterfeldstraat 67 Apeldoorn Gelderland 7315 JL",
    "addr:housenumber":"67",
    "addr:postcode":"7315 jl",
    "addr:street":"Lippe-Biesterfeldstraat;Gelderland",
    "iso:country":"NL",
    "sg:address":"Lippe-Biesterfeldstraat 67",
    "sg:city":"Apeldoorn",
    "sg:classifiers":[
        {
            "category":"Food & Beverages",
            "subcategory":"Fruits & Vegetables",
            "type":"Retail Goods"
        }
    ],
    "sg:phone":"+31 55 579 1773",
    "sg:postcode":"7315 JL",
    "sg:province":"Gelderland",
    "sg:tags":[
        "groenten"
    ],
    "wof:name":"J.W. Bonenberg",
    "wof:placetype":"venue"
},
  "geometry": {"coordinates":[5.95499,52.235809],"type":"Point"}
}