{
  "type": "Feature",
  "properties": {
    "addr:full":"Winterswyksewg 20 Vragender Gelderland 7134 NE",
    "addr:housenumber":"20;7134",
    "addr:street":"Winterswyksewg;Gelderland;Ne",
    "iso:country":"NL",
    "sg:address":"Winterswyksewg 20",
    "sg:city":"Vragender",
    "sg:orig_category":"Scholen Voor Basisonderwijs",
    "sg:phone":"+31 544 372 429",
    "sg:postcode":"7134 NE",
    "sg:province":"Gelderland",
    "wof:name":"Antonius Kath",
    "wof:placetype":"venue"
},
  "geometry": {"coordinates":[6.611804,51.986214],"type":"Point"}
}