{
  "type": "Feature",
  "properties": {
    "addr:full":"Schalmeistr 8 Almere Flevoland 1312 NS",
    "addr:housenumber":"8",
    "addr:postcode":"1312 ns",
    "addr:street":"Schalmeistr;Flevoland",
    "iso:country":"NL",
    "sg:address":"Schalmeistr 8",
    "sg:city":"Almere",
    "sg:classifiers":[
        {
            "category":"Personal",
            "subcategory":"Nail Salon",
            "type":"Services"
        }
    ],
    "sg:phone":"+31 36 536 2738",
    "sg:postcode":"1312 NS",
    "sg:province":"Flevoland",
    "sg:tags":[
        "pedicure"
    ],
    "wof:name":"Puttelaar, Van Den",
    "wof:placetype":"venue"
},
  "geometry": {"coordinates":[5.185573,52.373318],"type":"Point"}
}