{
  "type": "Feature",
  "properties": {
    "iso:country":"NL",
    "sg:address":"D Curtiusstr 7",
    "sg:city":"Amsterdam",
    "sg:orig_category":"Vertaalbureaus",
    "sg:phone":"+31 20 475 0295",
    "sg:postcode":"1051 JL",
    "sg:province":"Noord-Holland",
    "wof:name":"Quellijn",
    "wof:placetype":"venue"
},
  "geometry": {"coordinates":[4.871745,52.379089],"type":"Point"}
}