{
  "type": "Feature",
  "properties": {
    "addr:full":"Stationswg O 281 Woudenberg Utrecht 3931 ER",
    "addr:housenumber":"281",
    "addr:postcode":"3931 er",
    "iso:country":"NL",
    "sg:address":"Stationswg O 281",
    "sg:city":"Woudenberg",
    "sg:orig_category":"Kabels",
    "sg:phone":"+31 33 461 4844",
    "sg:postcode":"3931 ER",
    "sg:province":"Utrecht",
    "wof:name":"Westmark Bv",
    "wof:placetype":"venue"
},
  "geometry": {"coordinates":[5.4543027878,52.08152771],"type":"Point"}
}