{
  "type": "Feature",
  "properties": {
    "addr:full":"Burg Janssenstr 43 Beesel Limburg 5954 BP",
    "addr:housenumber":"43",
    "addr:postcode":"5954 bp",
    "addr:street":"Burg",
    "iso:country":"NL",
    "sg:address":"Burg Janssenstr 43",
    "sg:city":"Beesel",
    "sg:orig_category":"Adviesbureaus",
    "sg:phone":"+31 77 474 8095",
    "sg:postcode":"5954 BP",
    "sg:province":"Limburg",
    "wof:name":"He Bv",
    "wof:placetype":"venue"
},
  "geometry": {"coordinates":[6.033719,51.25531],"type":"Point"}
}