{
  "type": "Feature",
  "properties": {
    "addr:full":"Kagerstr 7 Leiden Zuid-Holland 2334 CP",
    "addr:housenumber":"7",
    "addr:postcode":"2334 cp",
    "addr:street":"Kagerstr",
    "iso:country":"NL",
    "sg:address":"Kagerstr 7",
    "sg:city":"Leiden",
    "sg:orig_category":"Scholen Voor Algemeen Voortgezet Onderwijs",
    "sg:phone":"+31 71 515 4121",
    "sg:postcode":"2334 CP",
    "sg:province":"Zuid-Holland",
    "wof:name":"Da Vinci College",
    "wof:placetype":"venue"
},
  "geometry": {"coordinates":[4.479804,52.171165],"type":"Point"}
}