{
  "type": "Feature",
  "properties": {
    "iso:country":"NL",
    "sg:address":"Slachthuiskd 20",
    "sg:city":"Poeldijk",
    "sg:orig_category":"Bedrijfsmechanisatie En -Automatisering",
    "sg:phone":"+31 174 243 696",
    "sg:postcode":"2685 LN",
    "sg:province":"South Holland",
    "wof:name":"Pego",
    "wof:placetype":"venue"
},
  "geometry": {"coordinates":[4.210303,52.020912],"type":"Point"}
}