{
  "type": "Feature",
  "properties": {
    "addr:full":"De Schelp 29 Zandvoort North Holland 2042 DV",
    "addr:housenumber":"29",
    "addr:postcode":"2042 dv",
    "addr:street":"De Schelp",
    "iso:country":"NL",
    "sg:address":"De Schelp 29",
    "sg:city":"Zandvoort",
    "sg:orig_category":"Verenigingen En Stichtingen",
    "sg:phone":"+31 23 571 5569",
    "sg:postcode":"2042 DV",
    "sg:province":"North Holland",
    "wof:name":"Eigenaren, Ver Van",
    "wof:placetype":"venue"
},
  "geometry": {"coordinates":[4.536359,52.368851],"type":"Point"}
}