{
  "type": "Feature",
  "properties": {
    "addr:full":"Borretstr 14 S Hertogenbosch North Brabant 5224 CE",
    "addr:housenumber":"14",
    "addr:postcode":"5224 ce",
    "addr:street":"Borretstr;S Hertogenbosch",
    "iso:country":"NL",
    "sg:address":"Borretstr 14",
    "sg:city":"S Hertogenbosch",
    "sg:orig_category":"Verzekeringen - Verzekeringskantoren",
    "sg:phone":"+31 73 621 3756",
    "sg:postcode":"5224 CE",
    "sg:province":"North Brabant",
    "wof:name":"Roeters En Zn, J",
    "wof:placetype":"venue"
},
  "geometry": {"coordinates":[5.262348,51.692905],"type":"Point"}
}