{
  "type": "Feature",
  "properties": {
    "addr:full":"Kerkstraat 56 Zeeland Noord-Brabant 5411 BA",
    "addr:housenumber":"56",
    "addr:postcode":"5411 ba",
    "addr:street":"Kerkstraat",
    "iso:country":"NL",
    "sg:address":"Kerkstraat 56",
    "sg:city":"Zeeland",
    "sg:orig_category":"Begrafenisondernemers",
    "sg:phone":"+31 486 451 313",
    "sg:postcode":"5411 BA",
    "sg:province":"Noord-Brabant",
    "wof:name":"Antoon Van Dongen",
    "wof:placetype":"venue"
},
  "geometry": {"coordinates":[5.674503,51.697155],"type":"Point"}
}