{
  "type": "Feature",
  "properties": {
    "iso:country":"NL",
    "sg:address":"Holtwiklanden 55",
    "sg:city":"Enschede",
    "sg:orig_category":"Koeriersdiensten",
    "sg:phone":"+31 6 22750646",
    "sg:postcode":"7542 JX",
    "sg:province":"NL.08",
    "wof:name":"Koeriersbedrijf Enschede",
    "wof:placetype":"venue"
},
  "geometry": {"coordinates":[6.89491,52.187092],"type":"Point"}
}