{
  "type": "Feature",
  "properties": {
    "addr:full":"Kerkbuurt 43 Sliedrecht Zuid-Holland 3361 BC",
    "addr:housenumber":"43",
    "addr:postcode":"3361 bc",
    "addr:street":"Kerkbuurt",
    "iso:country":"NL",
    "sg:address":"Kerkbuurt 43",
    "sg:city":"Sliedrecht",
    "sg:orig_category":"Warenhuizen",
    "sg:phone":"+31 184 415 772",
    "sg:postcode":"3361 BC",
    "sg:province":"Zuid-Holland",
    "wof:name":"Hema",
    "wof:placetype":"venue"
},
  "geometry": {"coordinates":[4.7745780945,51.8196983337],"type":"Point"}
}