{
  "type": "Feature",
  "properties": {
    "iso:country":"NL",
    "sg:address":"Hoofdstr 74",
    "sg:city":"Stadskanaal",
    "sg:classifiers":[
        {
            "category":"Food & Beverages",
            "subcategory":"Bakery",
            "type":"Retail Goods"
        }
    ],
    "sg:phone":"+31 599 652 787",
    "sg:postcode":"9501 CN",
    "sg:province":"Groningen",
    "sg:tags":[
        "pizza"
    ],
    "wof:name":"Manara, Eethuis",
    "wof:placetype":"venue"
},
  "geometry": {"coordinates":[6.955972,52.98518],"type":"Point"}
}