{
  "type": "Feature",
  "properties": {
    "addr:full":"Postbus 97 Joure Provincie Friesland 8500 AB",
    "addr:housenumber":"97",
    "addr:postcode":"8500 ab",
    "addr:street":"Postbus;Provincie Friesland",
    "iso:country":"NL",
    "sg:address":"Postbus 97",
    "sg:city":"Joure",
    "sg:orig_category":"Voetbalverenigingen",
    "sg:phone":"+31 513 414 362",
    "sg:postcode":"8500 AB",
    "sg:province":"Provincie Friesland",
    "wof:name":"Joure Vv",
    "wof:placetype":"venue"
},
  "geometry": {"coordinates":[5.80003,52.964851],"type":"Point"}
}