{
  "type": "Feature",
  "properties": {
    "addr:full":"Steijnstraat 29 Utrecht Utrecht 3531 AV",
    "addr:housenumber":"29",
    "addr:postcode":"3531 av",
    "addr:street":"Steijnstraat",
    "iso:country":"NL",
    "sg:address":"Steijnstraat 29",
    "sg:city":"Utrecht",
    "sg:orig_category":"Public Relationbureaus",
    "sg:phone":"+31 30 284 0440",
    "sg:postcode":"3531 AV",
    "sg:province":"Utrecht",
    "wof:name":"De Zonzijde",
    "wof:placetype":"venue"
},
  "geometry": {"coordinates":[5.096901,52.086674],"type":"Point"}
}