{
  "type": "Feature",
  "properties": {
    "addr:full":"Korssendk 3 Reeuwyk Zuid-Holland 2811 HJ",
    "addr:housenumber":"3",
    "addr:postcode":"2811 hj",
    "addr:street":"Korssendk",
    "iso:country":"NL",
    "sg:address":"Korssendk 3",
    "sg:city":"Reeuwyk",
    "sg:orig_category":"Verzekeringen - Verzekeringskantoren",
    "sg:phone":"+31 182 300 822",
    "sg:postcode":"2811 HJ",
    "sg:province":"Zuid-Holland",
    "wof:name":"Have En Goed",
    "wof:placetype":"venue"
},
  "geometry": {"coordinates":[4.738775,52.033264],"type":"Point"}
}