{
  "type": "Feature",
  "properties": {
    "addr:full":"Zijlweg 2 Waalwijk Noord-Brabant 5145 NR",
    "addr:housenumber":"2",
    "addr:postcode":"5145 nr",
    "addr:street":"Zijlweg",
    "iso:country":"NL",
    "sg:address":"Zijlweg 2",
    "sg:city":"Waalwijk",
    "sg:orig_category":"Verhuisdiensten",
    "sg:phone":"+31 416 336 551",
    "sg:postcode":"5145 NR",
    "sg:province":"Noord-Brabant",
    "wof:name":"Transportbedrijf B. De Rooij & Zn Bv",
    "wof:placetype":"venue"
},
  "geometry": {"coordinates":[5.050996,51.701958],"type":"Point"}
}