{
  "type": "Feature",
  "properties": {
    "addr:full":"Schelphorst 59 Wieringerwerf North Holland 1771 SM",
    "addr:housenumber":"59",
    "addr:postcode":"1771 sm",
    "addr:street":"Schelphorst",
    "iso:country":"NL",
    "sg:address":"Schelphorst 59",
    "sg:city":"Wieringerwerf",
    "sg:orig_category":"Wegen And Sportterreinen",
    "sg:phone":"+31 227 602 977",
    "sg:postcode":"1771 SM",
    "sg:province":"North Holland",
    "wof:name":"Jet Set Hydrotechniek Bv",
    "wof:placetype":"venue"
},
  "geometry": {"coordinates":[5.0159769058,52.8408813477],"type":"Point"}
}