{
  "type": "Feature",
  "properties": {
    "addr:full":"Klompenmakersd 3 Geleen Limburg 6162 JN",
    "addr:housenumber":"3",
    "addr:postcode":"6162 jn",
    "addr:street":"Klompenmakersd",
    "iso:country":"NL",
    "sg:address":"Klompenmakersd 3",
    "sg:city":"Geleen",
    "sg:orig_category":"Tegelwerken",
    "sg:phone":"+31 46 474 2261",
    "sg:postcode":"6162 JN",
    "sg:province":"Limburg",
    "wof:name":"Wall, Peter Van De",
    "wof:placetype":"venue"
},
  "geometry": {"coordinates":[5.832942,50.978325],"type":"Point"}
}