{
  "type": "Feature",
  "properties": {
    "addr:full":"Nieuwstr 4 Tilburg Noord-Brabant 5021 WT",
    "addr:housenumber":"4",
    "addr:postcode":"5021 wt",
    "addr:street":"Nieuwstr",
    "iso:country":"NL",
    "sg:address":"Nieuwstr 4",
    "sg:city":"Tilburg",
    "sg:orig_category":"Natuurvoeding En Reformartikelen - Fabrieken En Groothandel",
    "sg:phone":"+31 6 53131393",
    "sg:postcode":"5021 WT",
    "sg:province":"Noord-Brabant",
    "wof:name":"Fitfood",
    "wof:placetype":"venue"
},
  "geometry": {"coordinates":[5.09061,51.548569],"type":"Point"}
}