{
  "type": "Feature",
  "properties": {
    "addr:full":"Bergstraat 20 Amersfoort Utrecht 3811 NJ",
    "addr:housenumber":"20",
    "addr:postcode":"3811 nj",
    "addr:street":"Bergstraat",
    "iso:country":"NL",
    "sg:address":"Bergstraat 20",
    "sg:city":"Amersfoort",
    "sg:orig_category":"Advocaten And Juridische Adviseurs",
    "sg:phone":"+31 33 463 2437",
    "sg:postcode":"3811 NJ",
    "sg:province":"Utrecht",
    "wof:name":"Advocatenkantoor Mevr Mr. C. Theunissen",
    "wof:placetype":"venue"
},
  "geometry": {"coordinates":[5.386085,52.152325],"type":"Point"}
}