{
  "type": "Feature",
  "properties": {
    "addr:full":"Zuiderpk 4 Domburg Zeeland 4357 HD",
    "addr:housenumber":"4",
    "addr:postcode":"4357 hd",
    "addr:street":"Zuiderpk",
    "iso:country":"NL",
    "sg:address":"Zuiderpk 4",
    "sg:city":"Domburg",
    "sg:orig_category":"Adviesbureaus Bouwkosten",
    "sg:phone":"+31 118 582 148",
    "sg:postcode":"4357 HD",
    "sg:province":"Zeeland",
    "wof:name":"Kba Vof",
    "wof:placetype":"venue"
},
  "geometry": {"coordinates":[3.498021,51.555466],"type":"Point"}
}