{
  "type": "Feature",
  "properties": {
    "addr:full":"C V Rennesstr 101 S Gravenhage South Holland 2551 GK",
    "addr:housenumber":"101",
    "addr:postcode":"2551 gk",
    "addr:street":"V Rennesstr;S Gravenhage",
    "iso:country":"NL",
    "sg:address":"C V Rennesstr 101",
    "sg:city":"S Gravenhage",
    "sg:orig_category":"Organisatiebureaus",
    "sg:phone":"+31 70 448 0061",
    "sg:postcode":"2551 GK",
    "sg:province":"South Holland",
    "wof:name":"Troost Bv",
    "wof:placetype":"venue"
},
  "geometry": {"coordinates":[4.2377500534,52.0586013794],"type":"Point"}
}