{
  "type": "Feature",
  "properties": {
    "iso:country":"NL",
    "sg:address":"Leliestr 10",
    "sg:city":"Winsum Gn",
    "sg:orig_category":"Schilders",
    "sg:phone":"+31 595 443 486",
    "sg:postcode":"9951 GH",
    "sg:province":"Groningen",
    "wof:name":"Calker, Van",
    "wof:placetype":"venue"
},
  "geometry": {"coordinates":[6.516338,53.337292],"type":"Point"}
}