{
  "type": "Feature",
  "properties": {
    "addr:full":"Oude Varsselsewg 12 Hengelo Gld Gelderland 7255 MC",
    "addr:housenumber":"12",
    "addr:postcode":"7255 mc",
    "addr:street":"Oude Varsselsewg",
    "iso:country":"NL",
    "sg:address":"Oude Varsselsewg 12",
    "sg:city":"Hengelo Gld",
    "sg:orig_category":"Maquettes",
    "sg:phone":"+31 575 462 144",
    "sg:postcode":"7255 MC",
    "sg:province":"Gelderland",
    "wof:name":"Eric Jansen, Maquettebouw",
    "wof:placetype":"venue"
},
  "geometry": {"coordinates":[6.326715,52.051662],"type":"Point"}
}