{
  "type": "Feature",
  "properties": {
    "iso:country":"NL",
    "sg:address":"Markt 12",
    "sg:city":"Maassluis",
    "sg:orig_category":"Herenmodezaken",
    "sg:phone":"+31 10 591 3613",
    "sg:postcode":"3142 GG",
    "sg:province":"South Holland",
    "wof:name":"Nuovo",
    "wof:placetype":"venue"
},
  "geometry": {"coordinates":[4.254505,51.922165],"type":"Point"}
}