{
  "type": "Feature",
  "properties": {
    "addr:full":"Xenonwg 29 Amersfoort Utrecht 3812 SZ",
    "addr:housenumber":"29",
    "addr:postcode":"3812 sz",
    "addr:street":"Xenonwg",
    "iso:country":"NL",
    "sg:address":"Xenonwg 29",
    "sg:city":"Amersfoort",
    "sg:orig_category":"Fotolitho- En Reprografie - Inrichtingen",
    "sg:phone":"+31 33 480 8559",
    "sg:postcode":"3812 SZ",
    "sg:province":"Utrecht",
    "wof:name":"Scan Partners Bv",
    "wof:placetype":"venue"
},
  "geometry": {"coordinates":[5.352705,52.16647],"type":"Point"}
}