{
  "type": "Feature",
  "properties": {
    "iso:country":"NL",
    "sg:address":"Lipperkerkstraat 13",
    "sg:city":"Enschede",
    "sg:classifiers":[
        {
            "category":"Fast Food",
            "type":"Food & Drink"
        }
    ],
    "sg:phone":"+31 53 432 2656",
    "sg:postcode":"7511 CT",
    "sg:province":"NL.08",
    "sg:tags":[
        "afhaal",
        "restaurant"
    ],
    "wof:name":"La Lasagna",
    "wof:placetype":"venue"
},
  "geometry": {"coordinates":[6.90378,52.220261],"type":"Point"}
}