{
  "type": "Feature",
  "properties": {
    "addr:full":"Regenboogstr 43 Dordrecht Zuid-Holland 3328 HS",
    "addr:housenumber":"43",
    "addr:postcode":"3328 hs",
    "addr:street":"Regenboogstr",
    "iso:country":"NL",
    "sg:address":"Regenboogstr 43",
    "sg:city":"Dordrecht",
    "sg:orig_category":"Artsen - Overigen",
    "sg:phone":"+31 78 618 8522",
    "sg:postcode":"3328 HS",
    "sg:province":"Zuid-Holland",
    "wof:name":"Naarden, H A",
    "wof:placetype":"venue"
},
  "geometry": {"coordinates":[4.681811,51.78112],"type":"Point"}
}