{
  "type": "Feature",
  "properties": {
    "addr:full":"Edisonweg 5 A Tholen Zeeland 4691 RB",
    "addr:housenumber":"5 a",
    "addr:postcode":"4691 rb",
    "addr:street":"Edisonweg",
    "iso:country":"NL",
    "sg:address":"Edisonweg 5 A",
    "sg:city":"Tholen",
    "sg:orig_category":"Visspeciaalzaken",
    "sg:phone":"+31 166 605 160",
    "sg:postcode":"4691 RB",
    "sg:province":"Zeeland",
    "wof:name":"Schot-Bout Vof",
    "wof:placetype":"venue"
},
  "geometry": {"coordinates":[4.22511,51.535431],"type":"Point"}
}