{
  "type": "Feature",
  "properties": {
    "addr:full":"Ulftseweg 30 Silvolde Gelderland 7064 BD",
    "addr:housenumber":"30",
    "addr:postcode":"7064 bd",
    "addr:street":"Ulftseweg;Gelderland",
    "iso:country":"NL",
    "sg:address":"Ulftseweg 30",
    "sg:city":"Silvolde",
    "sg:orig_category":"Loodgieterswerk, Verwarming And Sanitaire Installaties",
    "sg:phone":"+31 315 325 550",
    "sg:postcode":"7064 BD",
    "sg:province":"Gelderland",
    "wof:name":"Putman Karwei Service",
    "wof:placetype":"venue"
},
  "geometry": {"coordinates":[6.381553,51.909229],"type":"Point"}
}