{
  "type": "Feature",
  "properties": {
    "iso:country":"NL",
    "sg:address":"Pottebakkerstr 91",
    "sg:city":"Oosterhout Nb",
    "sg:orig_category":"Golfbanen",
    "sg:phone":"+31 162 458 730",
    "sg:postcode":"4905 AJ",
    "sg:province":"North Brabant",
    "wof:name":"Tee2Green Golf Unlimited",
    "wof:placetype":"venue"
},
  "geometry": {"coordinates":[4.85048,51.645561],"type":"Point"}
}