{
  "type": "Feature",
  "properties": {
    "addr:full":"Ringlaan 58 Eerbeek Gelderland 6961 KL",
    "addr:housenumber":"58",
    "addr:postcode":"6961 kl",
    "addr:street":"Ringlaan;Gelderland",
    "iso:country":"NL",
    "sg:address":"Ringlaan 58",
    "sg:city":"Eerbeek",
    "sg:orig_category":"Schoonheidssalons",
    "sg:phone":"+31 313 652 860",
    "sg:postcode":"6961 KL",
    "sg:province":"Gelderland",
    "wof:name":"Schoonheidssalon Dineke Omta-Wesselink",
    "wof:placetype":"venue"
},
  "geometry": {"coordinates":[6.064313,52.110935],"type":"Point"}
}