{
  "type": "Feature",
  "properties": {
    "addr:full":"Wylerbaan 3 Groesbeek Gelderland 6561 KN",
    "addr:housenumber":"3",
    "addr:postcode":"6561 kn",
    "addr:street":"Wylerbaan;Gelderland",
    "iso:country":"NL",
    "sg:address":"Wylerbaan 3",
    "sg:city":"Groesbeek",
    "sg:orig_category":"Partycatering And -Organisatie",
    "sg:phone":"+31 24 397 4430",
    "sg:postcode":"6561 KN",
    "sg:province":"Gelderland",
    "wof:name":"Frisco",
    "wof:placetype":"venue"
},
  "geometry": {"coordinates":[5.935552,51.785809],"type":"Point"}
}