{
  "type": "Feature",
  "properties": {
    "addr:full":"Iabc 5177 Breda North Brabant 4814 RA",
    "addr:housenumber":"5177",
    "addr:postcode":"4814 ra",
    "addr:street":"Iabc",
    "iso:country":"NL",
    "sg:address":"Iabc 5177",
    "sg:city":"Breda",
    "sg:orig_category":"Fruit And Groenten Gh",
    "sg:phone":"+31 76 522 2030",
    "sg:postcode":"4814 RA",
    "sg:province":"North Brabant",
    "wof:name":"Groente- En Fruithandel Gebrs. De Mooij Breda Bv",
    "wof:placetype":"venue"
},
  "geometry": {"coordinates":[4.731353,51.586956],"type":"Point"}
}