{
  "type": "Feature",
  "properties": {
    "addr:full":"Transportweg 6 Emmeloord NL. 8304 AX",
    "addr:housenumber":"6",
    "addr:postcode":"8304 ax",
    "addr:street":"Transportweg;Nl.",
    "iso:country":"NL",
    "sg:address":"Transportweg 6",
    "sg:city":"Emmeloord",
    "sg:orig_category":"Metalen And Ertsen Gh",
    "sg:phone":"+31 527 615 551",
    "sg:postcode":"8304 AX",
    "sg:province":"NL.",
    "wof:name":"Kolf & Molijn Bv",
    "wof:placetype":"venue"
},
  "geometry": {"coordinates":[5.752049,52.695187],"type":"Point"}
}