{
  "type": "Feature",
  "properties": {
    "addr:full":"Imkersplaats 38 Apeldoorn Gelderland 7328 CJ",
    "addr:housenumber":"38",
    "addr:postcode":"7328 cj",
    "addr:street":"Imkersplaats;Gelderland",
    "iso:country":"NL",
    "sg:address":"Imkersplaats 38",
    "sg:city":"Apeldoorn",
    "sg:classifiers":[
        {
            "category":"Education",
            "subcategory":"Preschool",
            "type":"Public Place"
        }
    ],
    "sg:phone":"+31 55 533 6094",
    "sg:postcode":"7328 CJ",
    "sg:province":"Gelderland",
    "sg:tags":[
        "kleuteronderwijs",
        "basis-"
    ],
    "wof:name":"Jenaplanschool De Korf",
    "wof:placetype":"venue"
},
  "geometry": {"coordinates":[5.985129,52.19952],"type":"Point"}
}