{
  "type": "Feature",
  "properties": {
    "addr:full":"Schalkwykerstr 17 Haarlem Noord-Holland 2033 JB",
    "addr:housenumber":"17",
    "addr:postcode":"2033 jb",
    "addr:street":"Schalkwykerstr",
    "iso:country":"NL",
    "sg:address":"Schalkwykerstr 17",
    "sg:city":"Haarlem",
    "sg:orig_category":"Behangselpapier En Wandbekleding",
    "sg:phone":"+31 23 536 1666",
    "sg:postcode":"2033 JB",
    "sg:province":"Noord-Holland",
    "wof:name":"Tjade Petri",
    "wof:placetype":"venue"
},
  "geometry": {"coordinates":[4.64338,52.373631],"type":"Point"}
}