{
  "type": "Feature",
  "properties": {
    "addr:full":"Hoofdstr 24 Kaatsheuvel Noord-Brabant 5171 DD",
    "addr:housenumber":"24",
    "addr:postcode":"5171 dd",
    "addr:street":"Hoofdstr",
    "iso:country":"NL",
    "sg:address":"Hoofdstr 24",
    "sg:city":"Kaatsheuvel",
    "sg:orig_category":"Bloemen En Planten",
    "sg:phone":"+31 416 280 266",
    "sg:postcode":"5171 DD",
    "sg:province":"Noord-Brabant",
    "wof:name":"A En S",
    "wof:placetype":"venue"
},
  "geometry": {"coordinates":[5.036135,51.661133],"type":"Point"}
}