{
  "type": "Feature",
  "properties": {
    "addr:full":"Molensteyn 37 De Meern Utrecht 3454 PT",
    "addr:housenumber":"37",
    "addr:postcode":"3454 pt",
    "addr:street":"Molensteyn",
    "iso:country":"NL",
    "sg:address":"Molensteyn 37",
    "sg:city":"De Meern",
    "sg:orig_category":"Machinetransporten",
    "sg:phone":"+31 30 294 7454",
    "sg:postcode":"3454 PT",
    "sg:province":"Utrecht",
    "sg:website":"http://www.edvandijk.nl",
    "wof:name":"Ed Van Dijk Bv",
    "wof:placetype":"venue"
},
  "geometry": {"coordinates":[5.053806,52.077911],"type":"Point"}
}