{
  "type": "Feature",
  "properties": {
    "addr:full":"De Boskamp 1 Tolbert Groningen 9356 CE",
    "addr:housenumber":"1",
    "addr:postcode":"9356 ce",
    "addr:street":"De Boskamp",
    "iso:country":"NL",
    "sg:address":"De Boskamp 1",
    "sg:city":"Tolbert",
    "sg:orig_category":"Adviesbureaus Bedrijfsorganisatie",
    "sg:phone":"+31 594 516 987",
    "sg:postcode":"9356 CE",
    "sg:province":"Groningen",
    "wof:name":"Oblomov Tao",
    "wof:placetype":"venue"
},
  "geometry": {"coordinates":[-99.414536,34.226662],"type":"Point"}
}