{
  "type": "Feature",
  "properties": {
    "addr:full":"Steenovenwg 1 Helmond Noord-Brabant 5708 HN",
    "addr:housenumber":"1",
    "addr:postcode":"5708 hn",
    "addr:street":"Steenovenwg",
    "iso:country":"NL",
    "sg:address":"Steenovenwg 1",
    "sg:city":"Helmond",
    "sg:orig_category":"Vervoercentra",
    "sg:phone":"+31 492 562 013",
    "sg:postcode":"5708 HN",
    "sg:province":"Noord-Brabant",
    "wof:name":"Apts Bv",
    "wof:placetype":"venue"
},
  "geometry": {"coordinates":[5.626881,51.474503],"type":"Point"}
}