{
  "type": "Feature",
  "properties": {
    "iso:country":"NL",
    "sg:address":"Steenovenwg 1",
    "sg:city":"Helmond",
    "sg:orig_category":"Vervoercentra",
    "sg:phone":"+31 492 562 013",
    "sg:postcode":"5708 HN",
    "sg:province":"Noord-Brabant",
    "wof:name":"Apts Bv",
    "wof:placetype":"venue"
},
  "geometry": {"coordinates":[5.626881,51.474503],"type":"Point"}
}