{
  "type": "Feature",
  "properties": {
    "addr:full":"Kastanjestr 17 Bentelo Overijssel 7497 NZ",
    "addr:housenumber":"17",
    "addr:postcode":"7497 nz",
    "addr:street":"Kastanjestr",
    "iso:country":"NL",
    "sg:address":"Kastanjestr 17",
    "sg:city":"Bentelo",
    "sg:orig_category":"Kappers",
    "sg:phone":"+31 6 29974522",
    "sg:postcode":"7497 NZ",
    "sg:province":"Overijssel",
    "wof:name":"Manon",
    "wof:placetype":"venue"
},
  "geometry": {"coordinates":[6.685454,52.225185],"type":"Point"}
}