{
  "type": "Feature",
  "properties": {
    "addr:full":"Bergambachterstraat 7 Schoonhoven South Holland 2871 JB",
    "addr:housenumber":"7",
    "addr:postcode":"2871 jb",
    "addr:street":"Bergambachterstraat",
    "iso:country":"NL",
    "sg:address":"Bergambachterstraat 7",
    "sg:city":"Schoonhoven",
    "sg:orig_category":"Metaalbekleding And -Behandeling",
    "sg:phone":"+31 182 382 733",
    "sg:postcode":"2871 JB",
    "sg:province":"South Holland",
    "wof:name":"Galvanische Metaalindustrie J. Ende En Zoon Bv",
    "wof:placetype":"venue"
},
  "geometry": {"coordinates":[4.845207,51.955158],"type":"Point"}
}