{
  "type": "Feature",
  "properties": {
    "addr:full":"Heimerstein 61 Dordrecht Zuid-Holland 3328 MG",
    "addr:housenumber":"61",
    "addr:postcode":"3328 mg",
    "addr:street":"Heimerstein",
    "iso:country":"NL",
    "sg:address":"Heimerstein 61",
    "sg:city":"Dordrecht",
    "sg:orig_category":"Afslankinstituten",
    "sg:phone":"+31 78 651 3251",
    "sg:postcode":"3328 MG",
    "sg:province":"Zuid-Holland",
    "wof:name":"Huijsdens",
    "wof:placetype":"venue"
},
  "geometry": {"coordinates":[4.669655,51.774273],"type":"Point"}
}