{
  "type": "Feature",
  "properties": {
    "addr:full":"Molenstr 46 Sassenheim Zuid-Holland 2171 GN",
    "addr:housenumber":"46",
    "addr:postcode":"2171 gn",
    "addr:street":"Molenstr",
    "iso:country":"NL",
    "sg:address":"Molenstr 46",
    "sg:city":"Sassenheim",
    "sg:orig_category":"Advocaten En Advocatenkantoren",
    "sg:phone":"+31 252 230 607",
    "sg:postcode":"2171 GN",
    "sg:province":"Zuid-Holland",
    "wof:name":"Jongh-Moolenaar, Mr C J De",
    "wof:placetype":"venue"
},
  "geometry": {"coordinates":[4.528691,52.228088],"type":"Point"}
}