{
  "type": "Feature",
  "properties": {
    "addr:full":"Paltrokmolen 43 Purmerend North Holland 1444 GM",
    "addr:housenumber":"43",
    "addr:postcode":"1444 gm",
    "addr:street":"Paltrokmolen",
    "iso:country":"NL",
    "sg:address":"Paltrokmolen 43",
    "sg:city":"Purmerend",
    "sg:orig_category":"Podotherapeuten",
    "sg:phone":"+31 299 421 661",
    "sg:postcode":"1444 GM",
    "sg:province":"North Holland",
    "wof:name":"Voorloop, P L",
    "wof:placetype":"venue"
},
  "geometry": {"coordinates":[4.97069,52.521122],"type":"Point"}
}