{
  "type": "Feature",
  "properties": {
    "addr:full":"A J Ernststr 179A-181 Amsterdam Noord-Holland 1083 GV",
    "addr:housenumber":"179a-181",
    "addr:postcode":"1083 gv",
    "addr:street":"A;Ernststr",
    "iso:country":"NL",
    "sg:address":"A J Ernststr 179A-181",
    "sg:city":"Amsterdam",
    "sg:orig_category":"Fotoarchieven",
    "sg:phone":"+31 800 0234532",
    "sg:postcode":"1083 GV",
    "sg:province":"Noord-Holland",
    "sg:website":"http://www.getty-images.com",
    "wof:name":"Getty Images",
    "wof:placetype":"venue"
},
  "geometry": {"coordinates":[4.88921,52.33028],"type":"Point"}
}