{
  "type": "Feature",
  "properties": {
    "addr:full":"Bachln 11 Doetinchem Gelderland 7002 MZ",
    "addr:housenumber":"11",
    "addr:postcode":"7002 mz",
    "addr:street":"Bachln;Gelderland",
    "iso:country":"NL",
    "sg:address":"Bachln 11",
    "sg:city":"Doetinchem",
    "sg:classifiers":[
        {
            "category":"Education",
            "subcategory":"School",
            "type":"Public Place"
        }
    ],
    "sg:phone":"+31 314 374 141",
    "sg:postcode":"7002 MZ",
    "sg:province":"Gelderland",
    "sg:tags":[
        "studiebegeleiding",
        "en",
        "school-"
    ],
    "sg:website":"http://www.iselinge.nl",
    "wof:name":"Iselinge Onderwijsbegeleidingsdienst",
    "wof:placetype":"venue"
},
  "geometry": {"coordinates":[6.291055,51.963596],"type":"Point"}
}