{
  "type": "Feature",
  "properties": {
    "addr:full":"Molenstr 19 Boekel Noord-Brabant 5427 PV",
    "addr:housenumber":"19",
    "addr:postcode":"5427 pv",
    "addr:street":"Molenstr",
    "iso:country":"NL",
    "sg:address":"Molenstr 19",
    "sg:city":"Boekel",
    "sg:orig_category":"Matrijzen",
    "sg:phone":"+31 492 323 487",
    "sg:postcode":"5427 PV",
    "sg:province":"Noord-Brabant",
    "wof:name":"Tiebosch Trading",
    "wof:placetype":"venue"
},
  "geometry": {"coordinates":[5.669432,51.614277],"type":"Point"}
}