{
  "type": "Feature",
  "properties": {
    "addr:full":"Gerberastr 23 Roelofarendsveen South Holland 2371 GP",
    "addr:housenumber":"23",
    "addr:postcode":"2371 gp",
    "addr:street":"Gerberastr",
    "iso:country":"NL",
    "sg:address":"Gerberastr 23",
    "sg:city":"Roelofarendsveen",
    "sg:orig_category":"Autorijscholen",
    "sg:phone":"+31 71 331 3070",
    "sg:postcode":"2371 GP",
    "sg:province":"South Holland",
    "wof:name":"Meer, G Van Der",
    "wof:placetype":"venue"
},
  "geometry": {"coordinates":[4.633827,52.208057],"type":"Point"}
}