{
  "type": "Feature",
  "properties": {
    "iso:country":"NL",
    "sg:address":"Troelstraln 11",
    "sg:city":"Huizen",
    "sg:orig_category":"Metselwerken",
    "sg:phone":"+31 35 525 6388",
    "sg:postcode":"1272 JX",
    "sg:province":"Noord-Holland",
    "wof:name":"Born, Van Den",
    "wof:placetype":"venue"
},
  "geometry": {"coordinates":[5.227197,52.290363],"type":"Point"}
}