{
  "type": "Feature",
  "properties": {
    "addr:full":"Mozartlaan 17 Rosmalen North Brabant 5242 HR",
    "addr:housenumber":"17",
    "addr:postcode":"5242 hr",
    "addr:street":"Mozartlaan",
    "iso:country":"NL",
    "sg:address":"Mozartlaan 17",
    "sg:city":"Rosmalen",
    "sg:classifiers":[
        {
            "category":"Education",
            "subcategory":"Preschool",
            "type":"Public Place"
        }
    ],
    "sg:phone":"+31 73 521 3183",
    "sg:postcode":"5242 HR",
    "sg:province":"North Brabant",
    "sg:tags":[
        "kleuteronderwijs",
        "basis-"
    ],
    "wof:name":"Basisschool De Troubadour",
    "wof:placetype":"venue"
},
  "geometry": {"coordinates":[5.362425,51.707733],"type":"Point"}
}