{
  "type": "Feature",
  "properties": {
    "addr:full":"Langevliet 17 Den Helder North Holland 1788 BD",
    "addr:housenumber":"17",
    "addr:postcode":"1788 bd",
    "addr:street":"Langevliet",
    "iso:country":"NL",
    "sg:address":"Langevliet 17",
    "sg:city":"Den Helder",
    "sg:orig_category":"Keramische Producten Fab",
    "sg:phone":"+31 223 643 263",
    "sg:postcode":"1788 BD",
    "sg:province":"North Holland",
    "wof:name":"Potterie/Galerie 'T Tiende Kind",
    "wof:placetype":"venue"
},
  "geometry": {"coordinates":[4.752402,52.900253],"type":"Point"}
}