{
  "type": "Feature",
  "properties": {
    "addr:full":"Tempspln 12 Heerlen Limburg 6411 ES",
    "addr:housenumber":"12",
    "addr:postcode":"6411 es",
    "addr:street":"Tempspln",
    "iso:country":"NL",
    "sg:address":"Tempspln 12",
    "sg:city":"Heerlen",
    "sg:orig_category":"Projectontwikkeling",
    "sg:phone":"+31 45 571 6333",
    "sg:postcode":"6411 ES",
    "sg:province":"Limburg",
    "wof:name":"Meijs Bv",
    "wof:placetype":"venue"
},
  "geometry": {"coordinates":[5.97888,50.884995],"type":"Point"}
}