{
  "type": "Feature",
  "properties": {
    "addr:full":"Proosdijweg 51 Maastricht Limburg 6214 RK",
    "addr:housenumber":"51",
    "addr:postcode":"6214 rk",
    "addr:street":"Proosdijweg",
    "iso:country":"NL",
    "sg:address":"Proosdijweg 51",
    "sg:city":"Maastricht",
    "sg:orig_category":"Schoenen",
    "sg:phone":"+31 43 321 3728",
    "sg:postcode":"6214 RK",
    "sg:province":"Limburg",
    "wof:name":"J.P. Schuimer En Zoon",
    "wof:placetype":"venue"
},
  "geometry": {"coordinates":[5.676322,50.846195],"type":"Point"}
}