{
  "type": "Feature",
  "properties": {
    "addr:full":"Dintel 36 Deurne Noord-Brabant 5751 SZ",
    "addr:housenumber":"36",
    "addr:postcode":"5751 sz",
    "addr:street":"Dintel",
    "iso:country":"NL",
    "sg:address":"Dintel 36",
    "sg:city":"Deurne",
    "sg:orig_category":"Huishoudapparatuur, Televisies And Radio'S",
    "sg:phone":"+31 493 313 479",
    "sg:postcode":"5751 SZ",
    "sg:province":"Noord-Brabant",
    "wof:name":"Uw Antenne Service",
    "wof:placetype":"venue"
},
  "geometry": {"coordinates":[5.8083,51.459846],"type":"Point"}
}