{
  "type": "Feature",
  "properties": {
    "iso:country":"NL",
    "sg:address":"Brinksestr 3",
    "sg:city":"Arnhem",
    "sg:orig_category":"Handwerkartikelen - Fabrieken En Groothandel",
    "sg:phone":"+31 26 381 8366",
    "sg:postcode":"6842 AN",
    "sg:province":"Gelderland",
    "sg:website":"http://www.telekabel.nl/sprinter/lelijvel",
    "wof:name":"Lelijveld",
    "wof:placetype":"venue"
},
  "geometry": {"coordinates":[5.883819,51.957615],"type":"Point"}
}