{
  "type": "Feature",
  "properties": {
    "iso:country":"NL",
    "sg:address":"Misterstraat 98",
    "sg:city":"Winterswijk",
    "sg:orig_category":"Krantenuitgeverijen",
    "sg:phone":"+31 543 517 500",
    "sg:postcode":"7101 EZ",
    "sg:province":"Gelderland",
    "wof:name":"Achterhoek Nieuws",
    "wof:placetype":"venue"
},
  "geometry": {"coordinates":[6.71519,51.970268],"type":"Point"}
}