{
  "type": "Feature",
  "properties": {
    "addr:full":"Insulindewg 29 Middenbeemster North Holland 1462 MJ",
    "addr:housenumber":"29",
    "addr:postcode":"1462 mj",
    "addr:street":"Insulindewg",
    "iso:country":"NL",
    "sg:address":"Insulindewg 29",
    "sg:city":"Middenbeemster",
    "sg:orig_category":"Zoetwaren - Fabrieken En Groothandel",
    "sg:phone":"+31 299 683 851",
    "sg:postcode":"1462 MJ",
    "sg:province":"North Holland",
    "wof:name":"Beemster Bv",
    "wof:placetype":"venue"
},
  "geometry": {"coordinates":[4.902205,52.552723],"type":"Point"}
}