{
  "type": "Feature",
  "properties": {
    "addr:full":"Strawinskiplein 8 Rhoon Zuid-Holland 3161 WG",
    "addr:housenumber":"8",
    "addr:postcode":"3161 wg",
    "addr:street":"Strawinskiplein",
    "iso:country":"NL",
    "sg:address":"Strawinskiplein 8",
    "sg:city":"Rhoon",
    "sg:classifiers":[
        {
            "category":"Communications",
            "subcategory":"Television Station",
            "type":"Services"
        }
    ],
    "sg:phone":"+31 10 501 0004",
    "sg:postcode":"3161 WG",
    "sg:province":"Zuid-Holland",
    "sg:tags":[
        "video",
        "audio",
        "verhuur"
    ],
    "wof:name":"Cinerent Rhoon",
    "wof:placetype":"venue"
},
  "geometry": {"coordinates":[4.419789,51.856716],"type":"Point"}
}