{
  "type": "Feature",
  "properties": {
    "addr:full":"Hermoesestr 11A Zennewynen Gelderland 4062 PP",
    "addr:housenumber":"11a",
    "addr:postcode":"4062 pp",
    "addr:street":"Hermoesestr;Gelderland",
    "iso:country":"NL",
    "sg:address":"Hermoesestr 11A",
    "sg:city":"Zennewynen",
    "sg:orig_category":"Bloemen En Planten",
    "sg:phone":"+31 344 651 724",
    "sg:postcode":"4062 PP",
    "sg:province":"Gelderland",
    "wof:name":"Zennewijnen Bv",
    "wof:placetype":"venue"
},
  "geometry": {"coordinates":[5.404367,51.854584],"type":"Point"}
}