{
  "type": "Feature",
  "properties": {
    "addr:full":"Industrieweg 92 Waalwijk North Brabant 5145 PW",
    "addr:housenumber":"92",
    "addr:postcode":"5145 pw",
    "addr:street":"Industrieweg",
    "iso:country":"NL",
    "sg:address":"Industrieweg 92",
    "sg:city":"Waalwijk",
    "sg:orig_category":"Hout Gh",
    "sg:phone":"+31 416 672 400",
    "sg:postcode":"5145 PW",
    "sg:province":"North Brabant",
    "wof:name":"Plastica Plaat Bv",
    "wof:placetype":"venue"
},
  "geometry": {"coordinates":[5.061319,51.706009],"type":"Point"}
}