{
  "type": "Feature",
  "properties": {
    "addr:full":"Winkelhof 19 Leiderdorp Zuid-Holland 2353 TS",
    "addr:housenumber":"19",
    "addr:postcode":"2353 ts",
    "addr:street":"Winkelhof",
    "iso:country":"NL",
    "sg:address":"Winkelhof 19",
    "sg:city":"Leiderdorp",
    "sg:orig_category":"Dameskleding",
    "sg:phone":"+31 71 541 2772",
    "sg:postcode":"2353 TS",
    "sg:province":"Zuid-Holland",
    "wof:name":"Eva",
    "wof:placetype":"venue"
},
  "geometry": {"coordinates":[4.532246,52.163265],"type":"Point"}
}