{
  "type": "Feature",
  "properties": {
    "addr:full":"Hillendonk 7 Helmond Noord-Brabant 5708 AR",
    "addr:housenumber":"7",
    "addr:postcode":"5708",
    "addr:street":"Hillendonk",
    "iso:country":"NL",
    "sg:address":"Hillendonk 7",
    "sg:city":"Helmond",
    "sg:orig_category":"Fitnesscentra",
    "sg:phone":"+31 492 526 058",
    "sg:postcode":"5708 AR",
    "sg:province":"Noord-Brabant",
    "wof:name":"Sportstudio De Zelle",
    "wof:placetype":"venue"
},
  "geometry": {"coordinates":[5.627566,51.484489],"type":"Point"}
}