{
  "type": "Feature",
  "properties": {
    "addr:full":"Verspycklaan 50 Naaldwijk Zuid-Holland 2671 CS",
    "addr:housenumber":"50",
    "addr:postcode":"2671 cs",
    "addr:street":"Verspycklaan",
    "iso:country":"NL",
    "sg:address":"Verspycklaan 50",
    "sg:city":"Naaldwijk",
    "sg:orig_category":"Metaalwerken",
    "sg:phone":"+31 174 622 721",
    "sg:postcode":"2671 CS",
    "sg:province":"Zuid-Holland",
    "wof:name":"Alna",
    "wof:placetype":"venue"
},
  "geometry": {"coordinates":[4.209689,51.997269],"type":"Point"}
}