{
  "type": "Feature",
  "properties": {
    "addr:full":"Feike De Boerlaan 23 Amsterdam Noord-Holland 1019 KS",
    "addr:housenumber":"23",
    "addr:postcode":"1019 ks",
    "addr:street":"Feike De Boerlaan",
    "iso:country":"NL",
    "sg:address":"Feike De Boerlaan 23",
    "sg:city":"Amsterdam",
    "sg:orig_category":"Keramische Producten Fab",
    "sg:phone":"+31 20 419 3713",
    "sg:postcode":"1019 KS",
    "sg:province":"Noord-Holland",
    "wof:name":"De Pijl Van Borneo",
    "wof:placetype":"venue"
},
  "geometry": {"coordinates":[4.940442,52.371201],"type":"Point"}
}