{
  "type": "Feature",
  "properties": {
    "iso:country":"NL",
    "sg:address":"Juliana Van Stolberglaan 214",
    "sg:city":"'S Gravenhage",
    "sg:orig_category":"Autokeuringen",
    "sg:phone":"+31 70 322 2233",
    "sg:postcode":"2595 CN",
    "sg:province":"Zuid-Holland",
    "wof:name":"Glass On Wheels",
    "wof:placetype":"venue"
},
  "geometry": {"coordinates":[4.334364,52.082497],"type":"Point"}
}