{
  "type": "Feature",
  "properties": {
    "addr:full":"Munninghofflaan 2 Oosterbeek Gelderland 6861 GN",
    "addr:housenumber":"2",
    "addr:postcode":"6861 gn",
    "addr:street":"Munninghofflaan;Gelderland",
    "iso:country":"NL",
    "sg:address":"Munninghofflaan 2",
    "sg:city":"Oosterbeek",
    "sg:classifiers":[
        {
            "category":"Education",
            "subcategory":"Preschool",
            "type":"Public Place"
        }
    ],
    "sg:phone":"+31 26 333 2458",
    "sg:postcode":"6861 GN",
    "sg:province":"Gelderland",
    "sg:tags":[
        "kleuteronderwijs",
        "basis-"
    ],
    "wof:name":"Basisschool Bernulphus",
    "wof:placetype":"venue"
},
  "geometry": {"coordinates":[5.843716,51.989365],"type":"Point"}
}