{
  "type": "Feature",
  "properties": {
    "iso:country":"NL",
    "sg:address":"Terppad 1",
    "sg:city":"Wieringerwerf",
    "sg:orig_category":"Scholen Voor Basisonderwijs",
    "sg:phone":"+31 227 602 204",
    "sg:postcode":"1771 RZ",
    "sg:province":"North Holland",
    "wof:name":"Don Bosco Rk",
    "wof:placetype":"venue"
},
  "geometry": {"coordinates":[5.026148,52.849968],"type":"Point"}
}