{
  "type": "Feature",
  "properties": {
    "iso:country":"NL",
    "sg:address":"Kaasmarkt 5",
    "sg:city":"Medemblik",
    "sg:orig_category":"Hypotheken",
    "sg:phone":"+31 227 549 034",
    "sg:postcode":"1671 BH",
    "sg:province":"Noord-Holland",
    "sg:website":"http://www.woonengeldzaken.nl",
    "wof:name":"Woon & Geldzaken",
    "wof:placetype":"venue"
},
  "geometry": {"coordinates":[5.107204,52.770622],"type":"Point"}
}