{
  "type": "Feature",
  "properties": {
    "addr:full":"Takkebysters 27A Breda North Brabant 4817 BL",
    "addr:housenumber":"27a",
    "addr:postcode":"4817 bl",
    "addr:street":"Takkebysters",
    "iso:country":"NL",
    "sg:address":"Takkebysters 27A",
    "sg:city":"Breda",
    "sg:orig_category":"Beurzen",
    "sg:phone":"+31 76 581 1005",
    "sg:postcode":"4817 BL",
    "sg:province":"North Brabant",
    "wof:name":"Evenementen Organisatie Bv, Bureau",
    "wof:placetype":"venue"
},
  "geometry": {"coordinates":[4.827015,51.596966],"type":"Point"}
}