{
  "type": "Feature",
  "properties": {
    "addr:full":"Vughterstr 37 S Hertogenbosch North Brabant 5211 EX",
    "addr:housenumber":"37",
    "addr:postcode":"5211 ex",
    "addr:street":"Vughterstr;S Hertogenbosch",
    "iso:country":"NL",
    "sg:address":"Vughterstr 37",
    "sg:city":"S Hertogenbosch",
    "sg:orig_category":"Zonnebank- En Solariumcentra",
    "sg:phone":"+31 73 612 3404",
    "sg:postcode":"5211 EX",
    "sg:province":"North Brabant",
    "wof:name":"Ayk",
    "wof:placetype":"venue"
},
  "geometry": {"coordinates":[5.301045,51.687443],"type":"Point"}
}