{
  "type": "Feature",
  "properties": {
    "addr:full":"Nieuwe Parklaan 105 'S Gravenhage Zuid-Holland 2587 BP",
    "addr:housenumber":"105 '",
    "addr:postcode":"2587 bp",
    "addr:street":"Nieuwe Parklaan",
    "iso:country":"NL",
    "sg:address":"Nieuwe Parklaan 105",
    "sg:city":"'S Gravenhage",
    "sg:orig_category":"Diverse Opleidingen And Onderwijs",
    "sg:phone":"+31 70 351 5351",
    "sg:postcode":"2587 BP",
    "sg:province":"Zuid-Holland",
    "wof:name":"Ardis Management Development",
    "wof:placetype":"venue"
},
  "geometry": {"coordinates":[4.289082,52.107838],"type":"Point"}
}