{
  "type": "Feature",
  "properties": {
    "addr:full":"Flevostr 10 Almere Flevoland 1315 CC",
    "addr:housenumber":"10",
    "addr:postcode":"1315 cc",
    "addr:street":"Flevostr;Flevoland",
    "iso:country":"NL",
    "sg:address":"Flevostr 10",
    "sg:city":"Almere",
    "sg:orig_category":"Kinderopvang",
    "sg:phone":"+31 36 548 2858",
    "sg:postcode":"1315 CC",
    "sg:province":"Flevoland",
    "wof:name":"Humanitas Almere/Amsterdam",
    "wof:placetype":"venue"
},
  "geometry": {"coordinates":[5.217579,52.369045],"type":"Point"}
}