{
  "type": "Feature",
  "properties": {
    "addr:full":"Zonwg 65 S Gravenhage Zuid-Holland 2516 AK",
    "addr:housenumber":"65;gravenhage",
    "addr:postcode":"2516 ak",
    "addr:street":"Zonwg;S",
    "iso:country":"NL",
    "sg:address":"Zonwg 65",
    "sg:city":"S Gravenhage",
    "sg:classifiers":[
        {
            "category":"Retail",
            "subcategory":"Auto Repair",
            "type":"Services"
        }
    ],
    "sg:phone":"+31 70 381 4816",
    "sg:postcode":"2516 AK",
    "sg:province":"Zuid-Holland",
    "sg:tags":[
        "garage"
    ],
    "wof:name":"Humaro, Autobedrijf",
    "wof:placetype":"venue"
},
  "geometry": {"coordinates":[4.33931,52.06786],"type":"Point"}
}