{
  "type": "Feature",
  "properties": {
    "addr:full":"Noorderhavenkade 157B Rotterdam Zuid-Holland 3039 RR",
    "addr:housenumber":"157b",
    "addr:postcode":"3039 rr",
    "addr:street":"Noorderhavenkade",
    "iso:country":"NL",
    "sg:address":"Noorderhavenkade 157B",
    "sg:city":"Rotterdam",
    "sg:orig_category":"Kansspelen",
    "sg:phone":"+31 10 466 5011",
    "sg:postcode":"3039 RR",
    "sg:province":"Zuid-Holland",
    "wof:name":"Reup Vof",
    "wof:placetype":"venue"
},
  "geometry": {"coordinates":[4.4609417915,51.932144165],"type":"Point"}
}