{
  "type": "Feature",
  "properties": {
    "addr:full":"Driebergenstr 256 S Gravenhage Zuid-Holland 2546 BR",
    "addr:housenumber":"256;gravenhage",
    "addr:postcode":"2546 br",
    "addr:street":"S",
    "iso:country":"NL",
    "sg:address":"Driebergenstr 256",
    "sg:city":"S Gravenhage",
    "sg:orig_category":"Wassalons",
    "sg:phone":"+31 70 366 5586",
    "sg:postcode":"2546 BR",
    "sg:province":"Zuid-Holland",
    "wof:name":"Pearl Wassalon",
    "wof:placetype":"venue"
},
  "geometry": {"coordinates":[4.2742710114,52.0587158203],"type":"Point"}
}