{
  "type": "Feature",
  "properties": {
    "iso:country":"NL",
    "sg:address":"Bredestraat 20",
    "sg:city":"Maastricht",
    "sg:orig_category":"Kappers",
    "sg:phone":"+31 43 321 2508",
    "sg:postcode":"6211 HC",
    "sg:province":"Limburg",
    "wof:name":"Salon Martie",
    "wof:placetype":"venue"
},
  "geometry": {"coordinates":[5.689985,50.848351],"type":"Point"}
}