{
  "type": "Feature",
  "properties": {
    "addr:full":"Nieuwstraat 98 Made Noord-Brabant 4921 CZ",
    "addr:housenumber":"98",
    "addr:postcode":"4921",
    "addr:street":"Nieuwstraat",
    "iso:country":"NL",
    "sg:address":"Nieuwstraat 98",
    "sg:city":"Made",
    "sg:orig_category":"Diverse Grafische Activiteiten",
    "sg:phone":"+31 162 683 221",
    "sg:postcode":"4921 CZ",
    "sg:province":"Noord-Brabant",
    "wof:name":"Prega Prepress",
    "wof:placetype":"venue"
},
  "geometry": {"coordinates":[15.47527,49.803791],"type":"Point"}
}