{
  "type": "Feature",
  "properties": {
    "addr:full":"Keursweg 4 Bornerbroek Overijssel 7627 LE",
    "addr:housenumber":"4",
    "addr:postcode":"7627 le",
    "addr:street":"Keursweg",
    "iso:country":"NL",
    "sg:address":"Keursweg 4",
    "sg:city":"Bornerbroek",
    "sg:orig_category":"Levende Dieren Gh",
    "sg:phone":"+31 74 384 1857",
    "sg:postcode":"7627 LE",
    "sg:province":"Overijssel",
    "wof:name":"Stamsnijder Vee- En Varkenshandel Bv",
    "wof:placetype":"venue"
},
  "geometry": {"coordinates":[6.611927,52.314362],"type":"Point"}
}