{
  "type": "Feature",
  "properties": {
    "iso:country":"NL",
    "sg:address":"Pastoor Smitsstraat 64",
    "sg:city":"Sint Oedenrode",
    "sg:orig_category":"Verhuur Kantoorapparatuur",
    "sg:phone":"+31 413 475 659",
    "sg:postcode":"5491 XP",
    "sg:province":"Noord-Brabant",
    "wof:name":"A.C.G. Brinkman - Termeer & A. Brinkman",
    "wof:placetype":"venue"
},
  "geometry": {"coordinates":[5.4009,51.582878],"type":"Point"}
}