{
  "type": "Feature",
  "properties": {
    "addr:full":"Bleulandwg 28 Gouda South Holland 2803 HH",
    "addr:housenumber":"28",
    "addr:postcode":"2803 hh",
    "addr:street":"Bleulandwg",
    "iso:country":"NL",
    "sg:address":"Bleulandwg 28",
    "sg:city":"Gouda",
    "sg:orig_category":"Adviesbureaus Bedrijfsorganisatie",
    "sg:phone":"+31 182 571 051",
    "sg:postcode":"2803 HH",
    "sg:province":"South Holland",
    "sg:website":"http://www.franzolet.nl",
    "wof:name":"Franzolet",
    "wof:placetype":"venue"
},
  "geometry": {"coordinates":[4.703138,52.020409],"type":"Point"}
}