{
  "type": "Feature",
  "properties": {
    "addr:full":"Beukelswijk 199 Rotterdam South Holland 3020 DH",
    "addr:housenumber":"199",
    "addr:postcode":"3020 dh",
    "iso:country":"NL",
    "sg:address":"Beukelswijk 199",
    "sg:city":"Rotterdam",
    "sg:orig_category":"Huishoudapparatuur, Televisies And Radio'S",
    "sg:phone":"+31 10 276 3940",
    "sg:postcode":"3020 DH",
    "sg:province":"South Holland",
    "wof:name":"Alfa Electronics",
    "wof:placetype":"venue"
},
  "geometry": {"coordinates":[4.449078,51.919979],"type":"Point"}
}