{
  "type": "Feature",
  "properties": {
    "iso:country":"NL",
    "sg:address":"Montgomeryln 20",
    "sg:city":"Delft",
    "sg:orig_category":"Vertalers",
    "sg:phone":"+31 15 257 0811",
    "sg:postcode":"2625 PN",
    "sg:province":"Zuid-Holland",
    "wof:name":"Trustword",
    "wof:placetype":"venue"
},
  "geometry": {"coordinates":[4.346057,51.988445],"type":"Point"}
}