{
  "type": "Feature",
  "properties": {
    "addr:full":"Nw Tyningen 84 Zaltbommel Gelderland 5301 DA",
    "addr:housenumber":"84",
    "addr:postcode":"5301 da",
    "addr:street":"Gelderland",
    "iso:country":"NL",
    "sg:address":"Nw Tyningen 84",
    "sg:city":"Zaltbommel",
    "sg:orig_category":"Bloemen En Planten",
    "sg:phone":"+31 418 561 404",
    "sg:postcode":"5301 DA",
    "sg:province":"Gelderland",
    "wof:name":"Spiering, G",
    "wof:placetype":"venue"
},
  "geometry": {"coordinates":[5.228948,51.801167],"type":"Point"}
}