{
  "type": "Feature",
  "properties": {
    "iso:country":"NL",
    "sg:address":"Smedenstraat 280",
    "sg:city":"Deventer",
    "sg:orig_category":"Werving And Selectie Van Vast Personeel",
    "sg:phone":"+31 570 690 700",
    "sg:postcode":"7411 RD",
    "sg:province":"NL.08",
    "wof:name":"Arbeidsbureau Deventer",
    "wof:placetype":"venue"
},
  "geometry": {"coordinates":[6.153151989,52.255821228],"type":"Point"}
}