{
  "type": "Feature",
  "properties": {
    "addr:full":"Molsln 33 Delft Zuid-Holland 2611 RJ",
    "addr:housenumber":"33",
    "addr:postcode":"2611 rj",
    "addr:street":"Molsln",
    "iso:country":"NL",
    "sg:address":"Molsln 33",
    "sg:city":"Delft",
    "sg:orig_category":"Warenhuizen",
    "sg:phone":"+31 15 212 0948",
    "sg:postcode":"2611 RJ",
    "sg:province":"Zuid-Holland",
    "wof:name":"Hema",
    "wof:placetype":"venue"
},
  "geometry": {"coordinates":[4.358689785,52.011505127],"type":"Point"}
}