{
  "type": "Feature",
  "properties": {
    "iso:country":"NL",
    "sg:address":"De Giem 3",
    "sg:city":"Enschede",
    "sg:orig_category":"Elektrotechnische Apparatuur - Fabrieken En Groothandel",
    "sg:phone":"+31 53 480 0088",
    "sg:postcode":"7547 SW",
    "sg:province":"Overijssel",
    "wof:name":"Smelt, B",
    "wof:placetype":"venue"
},
  "geometry": {"coordinates":[6.838759,52.219501],"type":"Point"}
}