{
  "type": "Feature",
  "properties": {
    "iso:country":"NL",
    "sg:address":"Wilgenhof 7",
    "sg:city":"Nieuw Beijerland",
    "sg:orig_category":"Metaalwerken",
    "sg:phone":"+31 186 692 610",
    "sg:postcode":"3264 TE",
    "sg:province":"Zuid-Holland",
    "wof:name":"Oorbeek",
    "wof:placetype":"venue"
},
  "geometry": {"coordinates":[4.346098,51.81139],"type":"Point"}
}