{
  "type": "Feature",
  "properties": {
    "addr:full":"Peulenstraat 235 Hardinxveld Giessend South Holland 3371 AM",
    "addr:housenumber":"235",
    "addr:postcode":"3371",
    "addr:street":"Peulenstraat",
    "iso:country":"NL",
    "sg:address":"Peulenstraat 235",
    "sg:city":"Hardinxveld Giessend",
    "sg:orig_category":"Kappers",
    "sg:phone":"+31 184 614 213",
    "sg:postcode":"3371 AM",
    "sg:province":"South Holland",
    "wof:name":"Ria Ouwerkerk",
    "wof:placetype":"venue"
},
  "geometry": {"coordinates":[4.833441,51.827705],"type":"Point"}
}