{
  "type": "Feature",
  "properties": {
    "addr:full":"Dagelijkse Groenmarkt 24 'S Gravenhage Zuid-Holland 2513 AL",
    "addr:housenumber":"24",
    "addr:postcode":"2513 al",
    "addr:street":"Dagelijkse Groenmarkt;' S",
    "iso:country":"NL",
    "sg:address":"Dagelijkse Groenmarkt 24",
    "sg:city":"'S Gravenhage",
    "sg:orig_category":"Schoenen",
    "sg:phone":"+31 70 365 3626",
    "sg:postcode":"2513 AL",
    "sg:province":"Zuid-Holland",
    "wof:name":"De Graaff Schoenen Bv",
    "wof:placetype":"venue"
},
  "geometry": {"coordinates":[4.309104,52.077827],"type":"Point"}
}