{
  "type": "Feature",
  "properties": {
    "addr:full":"Voorzorgstraat 82Rd Haarlem Noord-Holland 2013 VS",
    "addr:housenumber":"82rd",
    "addr:postcode":"2013 vs",
    "addr:street":"Voorzorgstraat",
    "iso:country":"NL",
    "sg:address":"Voorzorgstraat 82Rd",
    "sg:city":"Haarlem",
    "sg:orig_category":"Film-, Tv- And Videoproductie",
    "sg:phone":"+31 23 542 0415",
    "sg:postcode":"2013 VS",
    "sg:province":"Noord-Holland",
    "wof:name":"Free Film Productions",
    "wof:placetype":"venue"
},
  "geometry": {"coordinates":[4.620201,52.378662],"type":"Point"}
}