{
  "type": "Feature",
  "properties": {
    "addr:full":"Zuidereinde 193 S Graveland Noord-Holland 1243 KW",
    "addr:housenumber":"193",
    "addr:postcode":"1243 kw",
    "addr:street":"Zuidereinde;S Graveland",
    "iso:country":"NL",
    "sg:address":"Zuidereinde 193",
    "sg:city":"S Graveland",
    "sg:orig_category":"Plafonds",
    "sg:phone":"+31 35 656 9596",
    "sg:postcode":"1243 KW",
    "sg:province":"Noord-Holland",
    "wof:name":"Bree, De",
    "wof:placetype":"venue"
},
  "geometry": {"coordinates":[5.122638,52.221882],"type":"Point"}
}