{
  "type": "Feature",
  "properties": {
    "addr:full":"Gerbrandyborch 18 Rosmalen Noord-Brabant 5241 HK",
    "addr:housenumber":"18",
    "addr:postcode":"5241 hk",
    "addr:street":"Gerbrandyborch",
    "iso:country":"NL",
    "sg:address":"Gerbrandyborch 18",
    "sg:city":"Rosmalen",
    "sg:orig_category":"Adviesbureaus",
    "sg:phone":"+31 73 528 0030",
    "sg:postcode":"5241 HK",
    "sg:province":"Noord-Brabant",
    "sg:website":"http://www.tascmgt.com",
    "wof:name":"Tasc Consultants",
    "wof:placetype":"venue"
},
  "geometry": {"coordinates":[5.355831,51.722778],"type":"Point"}
}