{
  "type": "Feature",
  "properties": {
    "addr:full":"V L Stirumstr 125 S Gravenhage Zuid-Holland 2515 PC",
    "addr:housenumber":"125;gravenhage",
    "addr:postcode":"2515 pc",
    "addr:street":"V;S",
    "iso:country":"NL",
    "sg:address":"V L Stirumstr 125",
    "sg:city":"S Gravenhage",
    "sg:orig_category":"Architecten En Architectenbureaus",
    "sg:phone":"+31 70 389 2216",
    "sg:postcode":"2515 PC",
    "sg:province":"Zuid-Holland",
    "wof:name":"Mourik, Ir Hans Van",
    "wof:placetype":"venue"
},
  "geometry": {"coordinates":[4.31741,52.083988],"type":"Point"}
}