{
  "type": "Feature",
  "properties": {
    "addr:full":"Postbus 52 Heteren Z\u00fcrich 6666 ZH",
    "addr:housenumber":"52",
    "addr:postcode":"6666",
    "addr:street":"Postbus",
    "iso:country":"NL",
    "sg:address":"Postbus 52",
    "sg:city":"Heteren",
    "sg:orig_category":"Sportverenigingen En Ontspannings- Verenigingen",
    "sg:phone":"+31 26 472 2674",
    "sg:postcode":"6666 ZH",
    "sg:province":"Z\u00fcrich",
    "sg:website":"http://www.trefpunt.net/pages/ntv",
    "wof:name":"Htv Tennisver",
    "wof:placetype":"venue"
},
  "geometry": {"coordinates":[8.6711,47.426941],"type":"Point"}
}