{
  "type": "Feature",
  "properties": {
    "addr:full":"Stationsstraat 3 Sint Philipsland Zeeland 4675 CG",
    "addr:housenumber":"3",
    "addr:postcode":"4675 cg",
    "addr:street":"Stationsstraat",
    "iso:country":"NL",
    "sg:address":"Stationsstraat 3",
    "sg:city":"Sint Philipsland",
    "sg:orig_category":"Architecten",
    "sg:phone":"+31 167 573 444",
    "sg:postcode":"4675 CG",
    "sg:province":"Zeeland",
    "wof:name":"Ir M J Voves Architect",
    "wof:placetype":"venue"
},
  "geometry": {"coordinates":[4.168625,51.6171],"type":"Point"}
}