{
  "type": "Feature",
  "properties": {
    "iso:country":"NL",
    "sg:address":"De Hondert Margen 7",
    "sg:city":"De Lier",
    "sg:orig_category":"Technische Studies And Onderzoek",
    "sg:phone":"+31 174 511 056",
    "sg:postcode":"2678 AC",
    "sg:province":"Zuid-Holland",
    "wof:name":"R H Transportkoeling Westland",
    "wof:placetype":"venue"
},
  "geometry": {"coordinates":[4.236465,51.97337],"type":"Point"}
}