{
  "type": "Feature",
  "properties": {
    "addr:full":"Indus 25 Dordrecht Zuid-Holland 3328 NB",
    "addr:housenumber":"25",
    "addr:postcode":"3328 nb",
    "addr:street":"Indus",
    "iso:country":"NL",
    "sg:address":"Indus 25",
    "sg:city":"Dordrecht",
    "sg:orig_category":"Huishoudapparatuur, Televisies And Radio'S",
    "sg:phone":"+31 78 651 3029",
    "sg:postcode":"3328 NB",
    "sg:province":"Zuid-Holland",
    "wof:name":"Elmes Engineering Vof",
    "wof:placetype":"venue"
},
  "geometry": {"coordinates":[4.669853,51.779076],"type":"Point"}
}