{
  "type": "Feature",
  "properties": {
    "addr:full":"Gasthuisstraat 11 Tiel Gelderland 4001 BD",
    "addr:housenumber":"11",
    "addr:postcode":"4001 bd",
    "addr:street":"Gasthuisstraat;Gelderland",
    "iso:country":"NL",
    "sg:address":"Gasthuisstraat 11",
    "sg:city":"Tiel",
    "sg:orig_category":"Geluidsopnamen",
    "sg:phone":"+31 344 621 106",
    "sg:postcode":"4001 BD",
    "sg:province":"Gelderland",
    "wof:name":"Rodisc",
    "wof:placetype":"venue"
},
  "geometry": {"coordinates":[5.434955,51.88731],"type":"Point"}
}