{
  "type": "Feature",
  "properties": {
    "addr:full":"Hoenkoops Buurtwg 31A Oudewater Utrecht 3421 GA",
    "addr:housenumber":"31a",
    "addr:postcode":"3421 ga",
    "iso:country":"NL",
    "sg:address":"Hoenkoops Buurtwg 31A",
    "sg:city":"Oudewater",
    "sg:orig_category":"Adviesbureaus Elektrotechniek",
    "sg:phone":"+31 348 561 433",
    "sg:postcode":"3421 GA",
    "sg:province":"Utrecht",
    "wof:name":"Gerssen",
    "wof:placetype":"venue"
},
  "geometry": {"coordinates":[4.852034,52.004341],"type":"Point"}
}