{
  "type": "Feature",
  "properties": {
    "addr:full":"Roelvinkstr 45 Bredevoort Gelderland 7126 BR",
    "addr:housenumber":"45",
    "addr:postcode":"7126 br",
    "addr:street":"Roelvinkstr;Gelderland",
    "iso:country":"NL",
    "sg:address":"Roelvinkstr 45",
    "sg:city":"Bredevoort",
    "sg:orig_category":"Verzekeringen - Verzekeringskantoren",
    "sg:phone":"+31 543 451 242",
    "sg:postcode":"7126 BR",
    "sg:province":"Gelderland",
    "wof:name":"Boom, B W",
    "wof:placetype":"venue"
},
  "geometry": {"coordinates":[6.625639,51.940804],"type":"Point"}
}