{
  "type": "Feature",
  "properties": {
    "iso:country":"NL",
    "sg:address":"Pr Marieln 5",
    "sg:city":"Bussum",
    "sg:orig_category":"Verlichting",
    "sg:phone":"+31 35 691 0380",
    "sg:postcode":"1405 EN",
    "sg:province":"Noord-Holland",
    "wof:name":"Lumi Klaas",
    "wof:placetype":"venue"
},
  "geometry": {"coordinates":[5.162605,52.276829],"type":"Point"}
}