{
  "type": "Feature",
  "properties": {
    "addr:full":"Marktstr 13 Apeldoorn Gelderland 7311 LH",
    "addr:housenumber":"13",
    "addr:postcode":"7311 lh",
    "addr:street":"Marktstr;Gelderland",
    "iso:country":"NL",
    "sg:address":"Marktstr 13",
    "sg:city":"Apeldoorn",
    "sg:orig_category":"Biljartzalen",
    "sg:phone":"+31 55 521 5325",
    "sg:postcode":"7311 LH",
    "sg:province":"Gelderland",
    "wof:name":"Apeldoorns Biljart Centr",
    "wof:placetype":"venue"
},
  "geometry": {"coordinates":[5.964616,52.214123],"type":"Point"}
}