{
  "type": "Feature",
  "properties": {
    "addr:full":"Minervum 7046 ,(Ind.Terr.Hoogeind) Breda North Brabant 4817 ZL",
    "addr:housenumber":"7046",
    "addr:postcode":"4817 zl",
    "addr:street":"Minervum;Ind.Terr.Hoogeind Breda",
    "iso:country":"NL",
    "sg:address":"Minervum 7046 ,(Ind.Terr.Hoogeind)",
    "sg:city":"Breda",
    "sg:orig_category":"Hang- En Sluitwerk - Fabrieken En Groothandel",
    "sg:phone":"+31 76 571 2223",
    "sg:postcode":"4817 ZL",
    "sg:province":"North Brabant",
    "wof:name":"Wallebroek Bv",
    "wof:placetype":"venue"
},
  "geometry": {"coordinates":[4.83144,51.587227],"type":"Point"}
}