{
  "type": "Feature",
  "properties": {
    "iso:country":"NL",
    "sg:address":"Kloetingsewg 20",
    "sg:city":"S Heer Abtskerke",
    "sg:orig_category":"Betonijzervlechten",
    "sg:phone":"+31 113 316 212",
    "sg:postcode":"4444 AD",
    "sg:province":"Zeeland",
    "wof:name":"Jan Pannekoek",
    "wof:placetype":"venue"
},
  "geometry": {"coordinates":[3.884867,51.473309],"type":"Point"}
}