{
  "type": "Feature",
  "properties": {
    "addr:full":"Haringvliet 359 Rotterdam South Holland 3011 ZP",
    "addr:housenumber":"359",
    "addr:postcode":"3011 zp",
    "addr:street":"Haringvliet",
    "iso:country":"NL",
    "sg:address":"Haringvliet 359",
    "sg:city":"Rotterdam",
    "sg:orig_category":"Fotoreportages",
    "sg:phone":"+31 10 214 1060",
    "sg:postcode":"3011 ZP",
    "sg:province":"South Holland",
    "sg:website":"http://www.willeboordse.nl",
    "wof:name":"Willeboordse",
    "wof:placetype":"venue"
},
  "geometry": {"coordinates":[4.496042,51.920986],"type":"Point"}
}