{
  "type": "Feature",
  "properties": {
    "addr:full":"Nieuwe Vlissingseweg 93 Vlissingen Zeeland 4387 AB",
    "addr:housenumber":"93",
    "addr:postcode":"4387 ab",
    "addr:street":"Nieuwe Vlissingseweg",
    "iso:country":"NL",
    "sg:address":"Nieuwe Vlissingseweg 93",
    "sg:city":"Vlissingen",
    "sg:orig_category":"Pleziervaartuigen And Reparatie",
    "sg:phone":"+31 118 464 372",
    "sg:postcode":"4387 AB",
    "sg:province":"Zeeland",
    "wof:name":"Reparatiebedrijf V D Watersport De Kam",
    "wof:placetype":"venue"
},
  "geometry": {"coordinates":[3.595264,51.469868],"type":"Point"}
}