{
  "type": "Feature",
  "properties": {
    "addr:full":"Amperestraat 28 Zwolle NL.08 8013 PV",
    "addr:housenumber":"28",
    "addr:postcode":"8013 pv",
    "addr:street":"Amperestraat",
    "iso:country":"NL",
    "sg:address":"Amperestraat 28",
    "sg:city":"Zwolle",
    "sg:orig_category":"Elektrische Apparatuur Gh",
    "sg:phone":"+31 38 469 8200",
    "sg:postcode":"8013 PV",
    "sg:province":"NL.08",
    "wof:name":"Hemmink Elektro Bv",
    "wof:placetype":"venue"
},
  "geometry": {"coordinates":[6.127081,52.492695],"type":"Point"}
}