{
  "type": "Feature",
  "properties": {
    "iso:country":"NL",
    "sg:address":"Gouwzeestr 4",
    "sg:city":"Weesp",
    "sg:classifiers":[
        {
            "category":"Retail",
            "subcategory":"Auto Repair",
            "type":"Services"
        }
    ],
    "sg:phone":"+31 294 253 047",
    "sg:postcode":"1382 KD",
    "sg:province":"Noord-Holland",
    "sg:tags":[
        "garage"
    ],
    "sg:website":"http://www.app-porsche.nl",
    "wof:name":"App Porsche Service",
    "wof:placetype":"venue"
},
  "geometry": {"coordinates":[5.0242,52.316959],"type":"Point"}
}