{
  "type": "Feature",
  "properties": {
    "addr:full":"Weg Naar Voorst 150 Zutphen Gelderland 7205 CV",
    "addr:housenumber":"150",
    "addr:postcode":"7205 cv",
    "addr:street":"Weg Naar Voorst;Gelderland",
    "iso:country":"NL",
    "sg:address":"Weg Naar Voorst 150",
    "sg:city":"Zutphen",
    "sg:orig_category":"Vertaal- And Tolkenbureaus",
    "sg:phone":"+31 575 546 457",
    "sg:postcode":"7205 CV",
    "sg:province":"Gelderland",
    "wof:name":"Vertalink Translations",
    "wof:placetype":"venue"
},
  "geometry": {"coordinates":[6.182822,52.143517],"type":"Point"}
}