{
  "type": "Feature",
  "properties": {
    "addr:full":"T V Goghhof 91 Nuenen Noord-Brabant 5671 DW",
    "addr:housenumber":"91",
    "addr:postcode":"5671 dw",
    "addr:street":"T;Goghhof",
    "iso:country":"NL",
    "sg:address":"T V Goghhof 91",
    "sg:city":"Nuenen",
    "sg:orig_category":"Verenigingen En Stichtingen",
    "sg:phone":"+31 40 283 1907",
    "sg:postcode":"5671 DW",
    "sg:province":"Noord-Brabant",
    "wof:name":"Seniorweb Nuenen",
    "wof:placetype":"venue"
},
  "geometry": {"coordinates":[5.54933,51.474911],"type":"Point"}
}