{
  "type": "Feature",
  "properties": {
    "addr:full":"Galmanspad 9 Meppel Drenthe 7941 XZ",
    "addr:housenumber":"9",
    "addr:postcode":"7941 xz",
    "addr:street":"Galmanspad",
    "iso:country":"NL",
    "sg:address":"Galmanspad 9",
    "sg:city":"Meppel",
    "sg:orig_category":"Adviesbureaus Werktuigbouwkunde",
    "sg:phone":"+31 522 262 126",
    "sg:postcode":"7941 XZ",
    "sg:province":"Drenthe",
    "wof:name":"Derix",
    "wof:placetype":"venue"
},
  "geometry": {"coordinates":[6.188507,52.695217],"type":"Point"}
}