{
  "type": "Feature",
  "properties": {
    "addr:full":"Burg Ketelaarstraat 19 Warmond Zuid-Holland 2361 AA",
    "addr:housenumber":"19",
    "addr:postcode":"2361 aa",
    "addr:street":"Burg Ketelaarstraat",
    "iso:country":"NL",
    "sg:address":"Burg Ketelaarstraat 19",
    "sg:city":"Warmond",
    "sg:orig_category":"Pleziervaartuigen And Reparatie",
    "sg:phone":"+31 71 301 0300",
    "sg:postcode":"2361 AA",
    "sg:province":"Zuid-Holland",
    "wof:name":"Jachtwerf Gebrs Visch Cv",
    "wof:placetype":"venue"
},
  "geometry": {"coordinates":[4.509589,52.200321],"type":"Point"}
}