{
  "type": "Feature",
  "properties": {
    "addr:full":"Weteringschans 191 Amsterdam Noord-Holland 1017 XE",
    "addr:housenumber":"191",
    "addr:postcode":"1017 xe",
    "addr:street":"Weteringschans",
    "iso:country":"NL",
    "sg:address":"Weteringschans 191",
    "sg:city":"Amsterdam",
    "sg:orig_category":"Accountants - Administratie- Consulenten En -Kantoren",
    "sg:phone":"+31 20 627 1636",
    "sg:postcode":"1017 XE",
    "sg:province":"Noord-Holland",
    "wof:name":"Scheer Groep",
    "wof:placetype":"venue"
},
  "geometry": {"coordinates":[4.892939,52.359638],"type":"Point"}
}