{
  "type": "Feature",
  "properties": {
    "addr:full":"Kamelenspoor 79A Maarssen Utrecht 3605 ED",
    "addr:housenumber":"79a",
    "addr:postcode":"3605 ed",
    "addr:street":"Kamelenspoor",
    "iso:country":"NL",
    "sg:address":"Kamelenspoor 79A",
    "sg:city":"Maarssen",
    "sg:orig_category":"Kinderopvang Behalve Thuis",
    "sg:phone":"+31 346 564 100",
    "sg:postcode":"3605 ED",
    "sg:province":"Utrecht",
    "wof:name":"Kinderdagverblijf D' Ukkies",
    "wof:placetype":"venue"
},
  "geometry": {"coordinates":[5.022885,52.138577],"type":"Point"}
}