{
  "type": "Feature",
  "properties": {
    "addr:full":"Houtduif 2 Schagen North Holland 1742 KR",
    "addr:housenumber":"2",
    "addr:postcode":"1742 kr",
    "addr:street":"Houtduif",
    "iso:country":"NL",
    "sg:address":"Houtduif 2",
    "sg:city":"Schagen",
    "sg:orig_category":"Fotoreportages",
    "sg:phone":"+31 224 216 939",
    "sg:postcode":"1742 KR",
    "sg:province":"North Holland",
    "wof:name":"Welman, Rien",
    "wof:placetype":"venue"
},
  "geometry": {"coordinates":[4.786794,52.781483],"type":"Point"}
}