{
  "type": "Feature",
  "properties": {
    "addr:full":"Rigolettostr 1 Apeldoorn Gelderland 7323 CV",
    "addr:housenumber":"1",
    "addr:postcode":"7323 cv",
    "addr:street":"Rigolettostr;Gelderland",
    "iso:country":"NL",
    "sg:address":"Rigolettostr 1",
    "sg:city":"Apeldoorn",
    "sg:orig_category":"Verenigingen En Stichtingen",
    "sg:phone":"+31 55 366 6739",
    "sg:postcode":"7323 CV",
    "sg:province":"Gelderland",
    "wof:name":"Grifolet",
    "wof:placetype":"venue"
},
  "geometry": {"coordinates":[5.982892,52.233395],"type":"Point"}
}