{
  "type": "Feature",
  "properties": {
    "addr:full":"Postbus 9229 Alkmaar North Holland 1800 GE",
    "addr:housenumber":"9229",
    "addr:postcode":"1800",
    "addr:street":"Postbus",
    "iso:country":"NL",
    "sg:address":"Postbus 9229",
    "sg:city":"Alkmaar",
    "sg:orig_category":"Meubelen",
    "sg:phone":"+31 72 562 7170",
    "sg:postcode":"1800 GE",
    "sg:province":"North Holland",
    "wof:name":"Stam Artistic, Addie",
    "wof:placetype":"venue"
},
  "geometry": {"coordinates":[4.74625,52.634361],"type":"Point"}
}