{
  "type": "Feature",
  "properties": {
    "addr:full":"Robijnlaan 1 Hoofddorp North Holland 2132 WX",
    "addr:housenumber":"1",
    "addr:postcode":"2132 wx",
    "addr:street":"Robijnlaan",
    "iso:country":"NL",
    "sg:address":"Robijnlaan 1",
    "sg:city":"Hoofddorp",
    "sg:orig_category":"Papieren Kantoorbenodigdheden Fab",
    "sg:phone":"+31 23 562 5224",
    "sg:postcode":"2132 WX",
    "sg:province":"North Holland",
    "wof:name":"Keurtiss Bv",
    "wof:placetype":"venue"
},
  "geometry": {"coordinates":[4.685702,52.289143],"type":"Point"}
}