{
  "type": "Feature",
  "properties": {
    "iso:country":"NL",
    "sg:address":"Kleiweg 44",
    "sg:city":"Rotterdam",
    "sg:orig_category":"Public Relationbureaus",
    "sg:phone":"+31 10 285 0654",
    "sg:postcode":"3051 GS",
    "sg:province":"South Holland",
    "wof:name":"Communicatie-Advies Judith Van Gilst",
    "wof:placetype":"venue"
},
  "geometry": {"coordinates":[4.48052,51.945034],"type":"Point"}
}