{
  "type": "Feature",
  "properties": {
    "iso:country":"NL",
    "sg:address":"Hupselsewg 13A",
    "sg:city":"Eibergen",
    "sg:orig_category":"Geluidsinstallaties - Verhuur",
    "sg:phone":"+31 545 471 389",
    "sg:postcode":"7151 EL",
    "sg:province":"Gelderland",
    "wof:name":"W-Sound",
    "wof:placetype":"venue"
},
  "geometry": {"coordinates":[6.641946,52.097946],"type":"Point"}
}