{
  "type": "Feature",
  "properties": {
    "addr:full":"Hupselsewg 13A Eibergen Gelderland 7151 EL",
    "addr:housenumber":"13a;7151",
    "addr:postcode":"el",
    "addr:street":"Hupselsewg;Gelderland",
    "iso:country":"NL",
    "sg:address":"Hupselsewg 13A",
    "sg:city":"Eibergen",
    "sg:orig_category":"Geluidsinstallaties - Verhuur",
    "sg:phone":"+31 545 471 389",
    "sg:postcode":"7151 EL",
    "sg:province":"Gelderland",
    "wof:name":"W-Sound",
    "wof:placetype":"venue"
},
  "geometry": {"coordinates":[6.641946,52.097946],"type":"Point"}
}