{
  "type": "Feature",
  "properties": {
    "addr:full":"K Du Jardinstr 54 Amsterdam Noord-Holland 1073 TC",
    "addr:housenumber":"54",
    "addr:postcode":"1073 tc",
    "addr:street":"K Du Jardinstr",
    "iso:country":"NL",
    "sg:address":"K Du Jardinstr 54",
    "sg:city":"Amsterdam",
    "sg:orig_category":"Scholen Voor Algemeen Voortgezet Onderwijs",
    "sg:phone":"+31 20 662 6499",
    "sg:postcode":"1073 TC",
    "sg:province":"Noord-Holland",
    "wof:name":"Esprit Scholengem",
    "wof:placetype":"venue"
},
  "geometry": {"coordinates":[4.895717,52.351353],"type":"Point"}
}