{
  "type": "Feature",
  "properties": {
    "iso:country":"NL",
    "sg:address":"Baroniehof 212",
    "sg:city":"Helmond",
    "sg:classifiers":[
        {
            "category":"Education",
            "subcategory":"Preschool",
            "type":"Public Place"
        }
    ],
    "sg:phone":"+31 492 511 157",
    "sg:postcode":"5709 HD",
    "sg:province":"North Brabant",
    "sg:tags":[
        "kleuteronderwijs",
        "basis-"
    ],
    "wof:name":"Openbare Basisschool De Rakt",
    "wof:placetype":"venue"
},
  "geometry": {"coordinates":[5.700872,51.473019],"type":"Point"}
}