{
  "type": "Feature",
  "properties": {
    "addr:full":"Molenstraat 44 Winssen Gelderland 6645 BV",
    "addr:housenumber":"44",
    "addr:postcode":"6645 bv",
    "addr:street":"Molenstraat;Gelderland",
    "iso:country":"NL",
    "sg:address":"Molenstraat 44",
    "sg:city":"Winssen",
    "sg:orig_category":"Fruitteelt",
    "sg:phone":"+31 487 521 330",
    "sg:postcode":"6645 BV",
    "sg:province":"Gelderland",
    "wof:name":"J.A.E.G. Janssen",
    "wof:placetype":"venue"
},
  "geometry": {"coordinates":[5.691687,51.883293],"type":"Point"}
}