{
  "type": "Feature",
  "properties": {
    "iso:country":"NL",
    "sg:address":"Springwg 174",
    "sg:city":"Utrecht",
    "sg:orig_category":"Beeldende Kunstenaars",
    "sg:phone":"+31 30 232 1336",
    "sg:postcode":"3511 VZ",
    "sg:province":"Utrecht",
    "sg:website":"http://www.dutch-ceramics.com",
    "wof:name":"Holtrop, Tsjerk",
    "wof:placetype":"venue"
},
  "geometry": {"coordinates":[5.121108,52.085209],"type":"Point"}
}