{
  "type": "Feature",
  "properties": {
    "addr:full":"Harmonielaan 9 Someren Noord-Brabant 5712 BX",
    "addr:housenumber":"9",
    "addr:postcode":"5712 bx",
    "addr:street":"Harmonielaan",
    "iso:country":"NL",
    "sg:address":"Harmonielaan 9",
    "sg:city":"Someren",
    "sg:orig_category":"Wegen And Sportterreinen",
    "sg:phone":"+31 493 492 301",
    "sg:postcode":"5712 BX",
    "sg:province":"Noord-Brabant",
    "wof:name":"F.H. Lomans",
    "wof:placetype":"venue"
},
  "geometry": {"coordinates":[5.7366518974,51.353729248],"type":"Point"}
}