{
  "type": "Feature",
  "properties": {
    "addr:full":"Staten Bolwerk 36 Haarlem Noord-Holland 2011 MN",
    "addr:housenumber":"36",
    "addr:postcode":"2011 mn",
    "addr:street":"Staten Bolwerk",
    "iso:country":"NL",
    "sg:address":"Staten Bolwerk 36",
    "sg:city":"Haarlem",
    "sg:orig_category":"Organisatiebureaus",
    "sg:phone":"+31 23 526 0375",
    "sg:postcode":"2011 MN",
    "sg:province":"Noord-Holland",
    "wof:name":"Fmd Cons Bv",
    "wof:placetype":"venue"
},
  "geometry": {"coordinates":[4.6357741356,52.3889427185],"type":"Point"}
}