{
  "type": "Feature",
  "properties": {
    "iso:country":"NL",
    "sg:address":"Rooseveltstr 49",
    "sg:city":"Leiden",
    "sg:orig_category":"Boekbinderijen",
    "sg:phone":"+31 71 576 9321",
    "sg:postcode":"2321 BL",
    "sg:province":"Zuid-Holland",
    "wof:name":"Jansen Bv",
    "wof:placetype":"venue"
},
  "geometry": {"coordinates":[4.481175,52.144627],"type":"Point"}
}