{
  "type": "Feature",
  "properties": {
    "iso:country":"NL",
    "sg:address":"Brinkstraat 40",
    "sg:city":"Losser",
    "sg:orig_category":"Overheidsdiensten",
    "sg:phone":"+31 53 538 1900",
    "sg:postcode":"7581 GD",
    "sg:province":"Overijssel",
    "wof:name":"Ons Gebouw",
    "wof:placetype":"venue"
},
  "geometry": {"coordinates":[7.0081419945,52.2632102966],"type":"Point"}
}