{
  "type": "Feature",
  "properties": {
    "addr:full":"Insteek 67 Boskoop Zuid-Holland 2771 AA",
    "addr:housenumber":"67",
    "addr:postcode":"2771 aa",
    "addr:street":"Insteek",
    "iso:country":"NL",
    "sg:address":"Insteek 67",
    "sg:city":"Boskoop",
    "sg:orig_category":"Bloemen En Planten - Groothandel",
    "sg:phone":"+31 172 217 029",
    "sg:postcode":"2771 AA",
    "sg:province":"Zuid-Holland",
    "wof:name":"Bloemendaal, De",
    "wof:placetype":"venue"
},
  "geometry": {"coordinates":[4.693309,52.091324],"type":"Point"}
}