{
  "type": "Feature",
  "properties": {
    "addr:full":"Falckstr 51 Amsterdam Noord-Holland 1017 VV",
    "addr:housenumber":"51",
    "addr:postcode":"1017 vv",
    "addr:street":"Falckstr",
    "iso:country":"NL",
    "sg:address":"Falckstr 51",
    "sg:city":"Amsterdam",
    "sg:orig_category":"Zonnebank- En Solariumcentra",
    "sg:phone":"+31 20 627 9798",
    "sg:postcode":"1017 VV",
    "sg:province":"Noord-Holland",
    "wof:name":"Sun Fit",
    "wof:placetype":"venue"
},
  "geometry": {"coordinates":[4.897614,52.360813],"type":"Point"}
}