{
  "type": "Feature",
  "properties": {
    "addr:full":"Bouwsteeg 4 Middelaar Limburg 6587 AW",
    "addr:housenumber":"4",
    "addr:postcode":"6587 aw",
    "addr:street":"Bouwsteeg",
    "iso:country":"NL",
    "sg:address":"Bouwsteeg 4",
    "sg:city":"Middelaar",
    "sg:orig_category":"Chemische Producten Gh",
    "sg:phone":"+31 24 696 2327",
    "sg:postcode":"6587 AW",
    "sg:province":"Limburg",
    "wof:name":"Piton Bekledingsprofielen",
    "wof:placetype":"venue"
},
  "geometry": {"coordinates":[5.916842,51.724403],"type":"Point"}
}