{
  "type": "Feature",
  "properties": {
    "iso:country":"NL",
    "sg:address":"Leptonenwg 8",
    "sg:city":"Utrecht",
    "sg:orig_category":"Autosloperijen En Autodemontagebedrijven",
    "sg:phone":"+31 30 241 4430",
    "sg:postcode":"3542 CJ",
    "sg:province":"Utrecht",
    "wof:name":"Vaart, J Van Der",
    "wof:placetype":"venue"
},
  "geometry": {"coordinates":[5.061576,52.117519],"type":"Point"}
}