{
  "type": "Feature",
  "properties": {
    "addr:full":"Liessentstr 2B Uden Noord-Brabant 5405 AG",
    "addr:housenumber":"2b",
    "addr:postcode":"5405",
    "addr:street":"Liessentstr",
    "iso:country":"NL",
    "sg:address":"Liessentstr 2B",
    "sg:city":"Uden",
    "sg:orig_category":"Beveiliging",
    "sg:phone":"+31 413 256 261",
    "sg:postcode":"5405 AG",
    "sg:province":"Noord-Brabant",
    "sg:website":"http://www.videologyinc.com",
    "wof:name":"Videology Europe Bv",
    "wof:placetype":"venue"
},
  "geometry": {"coordinates":[5.640941,51.651955],"type":"Point"}
}