{
  "type": "Feature",
  "properties": {
    "addr:full":"Postbus 85012 Rotterdam Friesland 3009 MA",
    "addr:housenumber":"85012",
    "addr:postcode":"3009 ma",
    "addr:street":"Postbus",
    "iso:country":"NL",
    "sg:address":"Postbus 85012",
    "sg:city":"Rotterdam",
    "sg:orig_category":"Bewakingsdiensten",
    "sg:phone":"+31 10 286 7316",
    "sg:postcode":"3009 MA",
    "sg:province":"Friesland",
    "sg:website":"http://www.reeberg.nl",
    "wof:name":"Rb Security Holland Bv",
    "wof:placetype":"venue"
},
  "geometry": {"coordinates":[4.47075,51.922619],"type":"Point"}
}