{
  "type": "Feature",
  "properties": {
    "iso:country":"NL",
    "sg:address":"Nazarethstr 6",
    "sg:city":"Tilburg",
    "sg:orig_category":"Fotografie Reclame En Mode",
    "sg:phone":"+31 13 581 0560",
    "sg:postcode":"5021 VX",
    "sg:province":"North Brabant",
    "wof:name":"Fashiontalk",
    "wof:placetype":"venue"
},
  "geometry": {"coordinates":[5.079537,51.55304],"type":"Point"}
}