{
  "type": "Feature",
  "properties": {
    "addr:full":"Kerkstr 104 Amsterdam North Holland 1017 GP",
    "addr:housenumber":"104",
    "addr:postcode":"1017 gp",
    "iso:country":"NL",
    "sg:address":"Kerkstr 104",
    "sg:city":"Amsterdam",
    "sg:orig_category":"Pottenbakkerijen",
    "sg:phone":"+31 20 627 7868",
    "sg:postcode":"1017 GP",
    "sg:province":"North Holland",
    "wof:name":"Kleinveld, Atelier",
    "wof:placetype":"venue"
},
  "geometry": {"coordinates":[4.887088,52.364182],"type":"Point"}
}