{
  "type": "Feature",
  "properties": {
    "addr:full":"Frederikstraat 31 'S Gravenhage South Holland 2514 LA",
    "addr:housenumber":"31",
    "addr:postcode":"2514 la",
    "addr:street":"Frederikstraat;' S Gravenhage",
    "iso:country":"NL",
    "sg:address":"Frederikstraat 31",
    "sg:city":"'S Gravenhage",
    "sg:orig_category":"Verlichting And Huishoudartikelen",
    "sg:phone":"+31 70 363 4040",
    "sg:postcode":"2514 LA",
    "sg:province":"South Holland",
    "wof:name":"At Your Place Bv",
    "wof:placetype":"venue"
},
  "geometry": {"coordinates":[4.311257,52.086941],"type":"Point"}
}