{
  "type": "Feature",
  "properties": {
    "iso:country":"NL",
    "sg:address":"Poststraat 22",
    "sg:city":"Nieuwerkerk",
    "sg:orig_category":"Kappers",
    "sg:phone":"+31 111 641 602",
    "sg:postcode":"4306 CA",
    "sg:province":"Zeeland",
    "wof:name":"Kapsalon Adriaan",
    "wof:placetype":"venue"
},
  "geometry": {"coordinates":[4.0006642342,51.6490478516],"type":"Point"}
}