{
  "type": "Feature",
  "properties": {
    "addr:full":"Oosterdijk 59 Sneek Friesland 8601 BR",
    "addr:housenumber":"59",
    "addr:postcode":"8601 br",
    "addr:street":"Oosterdijk",
    "iso:country":"NL",
    "sg:address":"Oosterdijk 59",
    "sg:city":"Sneek",
    "sg:orig_category":"Discountwinkels",
    "sg:phone":"+31 515 433 838",
    "sg:postcode":"8601 BR",
    "sg:province":"Friesland",
    "wof:name":"Bentex Nederland Bv",
    "wof:placetype":"venue"
},
  "geometry": {"coordinates":[5.66197,53.033459],"type":"Point"}
}