{
  "type": "Feature",
  "properties": {
    "addr:full":"Richerstraat 35 Kerkrade Limburg 6461 VP",
    "addr:housenumber":"35",
    "addr:postcode":"6461 vp",
    "addr:street":"Richerstraat",
    "iso:country":"NL",
    "sg:address":"Richerstraat 35",
    "sg:city":"Kerkrade",
    "sg:orig_category":"Volwassenenonderwijs",
    "sg:phone":"+31 45 567 7900",
    "sg:postcode":"6461 VP",
    "sg:province":"Limburg",
    "wof:name":"College Rolduc",
    "wof:placetype":"venue"
},
  "geometry": {"coordinates":[6.07599,50.865555],"type":"Point"}
}