{
  "type": "Feature",
  "properties": {
    "addr:full":"Fuutlaan 47 Eindhoven Noord-Brabant 5613 AA",
    "addr:housenumber":"47",
    "addr:postcode":"5613 aa",
    "addr:street":"Fuutlaan",
    "iso:country":"NL",
    "sg:address":"Fuutlaan 47",
    "sg:city":"Eindhoven",
    "sg:orig_category":"Overheidsdiensten",
    "sg:phone":"+31 40 244 3424",
    "sg:postcode":"5613 AA",
    "sg:province":"Noord-Brabant",
    "wof:name":"Tachos Studentendispuuthuis",
    "wof:placetype":"venue"
},
  "geometry": {"coordinates":[5.4920678139,51.4430618286],"type":"Point"}
}