{
  "type": "Feature",
  "properties": {
    "addr:full":"Ruinerwoldstraat 18 Tilburg Noord-Brabant 5035 DB",
    "addr:housenumber":"18",
    "addr:postcode":"5035 db",
    "addr:street":"Ruinerwoldstraat",
    "iso:country":"NL",
    "sg:address":"Ruinerwoldstraat 18",
    "sg:city":"Tilburg",
    "sg:orig_category":"Kantoorartikelen",
    "sg:phone":"+31 13 571 6632",
    "sg:postcode":"5035 DB",
    "sg:province":"Noord-Brabant",
    "wof:name":"Korthals Meubel Service",
    "wof:placetype":"venue"
},
  "geometry": {"coordinates":[4.9823980331,51.5883255005],"type":"Point"}
}