{
  "type": "Feature",
  "properties": {
    "addr:full":"Planetenln 60 Groningen Groningen 9742 JC",
    "addr:housenumber":"60",
    "addr:postcode":"9742 jc",
    "addr:street":"Planetenln",
    "iso:country":"NL",
    "sg:address":"Planetenln 60",
    "sg:city":"Groningen",
    "sg:orig_category":"Beeldende Kunstenaars",
    "sg:phone":"+31 6 22030238",
    "sg:postcode":"9742 JC",
    "sg:province":"Groningen",
    "sg:website":"http://www.members.xoom.com/johnridder",
    "wof:name":"Ridder, J W",
    "wof:placetype":"venue"
},
  "geometry": {"coordinates":[6.537674,53.234848],"type":"Point"}
}