{
  "type": "Feature",
  "properties": {
    "addr:full":"Monseigneur Swinkelsstr 1 Eindhoven North Brabant 5623 AP",
    "addr:housenumber":"1",
    "addr:postcode":"5623 ap",
    "addr:street":"Monseigneur Swinkelsstr",
    "iso:country":"NL",
    "sg:address":"Monseigneur Swinkelsstr 1",
    "sg:city":"Eindhoven",
    "sg:orig_category":"Kinderopvang Behalve Thuis",
    "sg:phone":"+31 40 244 5480",
    "sg:postcode":"5623 AP",
    "sg:province":"North Brabant",
    "wof:name":"Orthopedagogisch Dagcentrum Monique",
    "wof:placetype":"venue"
},
  "geometry": {"coordinates":[5.471983,51.455513],"type":"Point"}
}