{
  "type": "Feature",
  "properties": {
    "addr:full":"De Akker 43 Vlijmen Noord-Brabant 5251 CA",
    "addr:housenumber":"43",
    "addr:postcode":"5251 ca",
    "addr:street":"De Akker",
    "iso:country":"NL",
    "sg:address":"De Akker 43",
    "sg:city":"Vlijmen",
    "sg:orig_category":"Meubelzaken, Woning- And Keukeninrichting",
    "sg:phone":"+31 73 511 2338",
    "sg:postcode":"5251 CA",
    "sg:province":"Noord-Brabant",
    "wof:name":"Handelsonderneming Ron Fitters",
    "wof:placetype":"venue"
},
  "geometry": {"coordinates":[5.218067,51.694992],"type":"Point"}
}