{
  "type": "Feature",
  "properties": {
    "addr:full":"Sophiastraat 12 Nuenen Noord-Brabant 5671 XK",
    "addr:housenumber":"12",
    "addr:postcode":"5671 xk",
    "addr:street":"Sophiastraat",
    "iso:country":"NL",
    "sg:address":"Sophiastraat 12",
    "sg:city":"Nuenen",
    "sg:orig_category":"Vertaal- And Tolkenbureaus",
    "sg:phone":"+31 40 290 6400",
    "sg:postcode":"5671 XK",
    "sg:province":"Noord-Brabant",
    "wof:name":"E.J. Luit",
    "wof:placetype":"venue"
},
  "geometry": {"coordinates":[5.538516,51.470669],"type":"Point"}
}