{
  "type": "Feature",
  "properties": {
    "addr:full":"Kerkstraat 22 Hapert Noord-Brabant 5527 EG",
    "addr:housenumber":"22",
    "addr:postcode":"5527 eg",
    "addr:street":"Kerkstraat",
    "iso:country":"NL",
    "sg:address":"Kerkstraat 22",
    "sg:city":"Hapert",
    "sg:orig_category":"Verlichting And Huishoudartikelen",
    "sg:phone":"+31 497 381 471",
    "sg:postcode":"5527 EG",
    "sg:province":"Noord-Brabant",
    "wof:name":"Familux 'T Bazarke",
    "wof:placetype":"venue"
},
  "geometry": {"coordinates":[5.252762,51.369576],"type":"Point"}
}