{
  "type": "Feature",
  "properties": {
    "addr:full":"Groeneweg 1A Wijk En Aalburg Gelderland 4261 RG",
    "addr:housenumber":"1a",
    "addr:postcode":"4261 rg",
    "addr:street":"Groeneweg",
    "iso:country":"NL",
    "sg:address":"Groeneweg 1A",
    "sg:city":"Wijk En Aalburg",
    "sg:orig_category":"Bloemen And Planten",
    "sg:phone":"+31 416 696 469",
    "sg:postcode":"4261 RG",
    "sg:province":"Gelderland",
    "wof:name":"Bloembinderij 'T Pompoentje",
    "wof:placetype":"venue"
},
  "geometry": {"coordinates":[5.10312,51.773659],"type":"Point"}
}