{
  "type": "Feature",
  "properties": {
    "addr:full":"Voorthuizerstr 31 Putten Gelderland 3881 SB",
    "addr:housenumber":"31",
    "addr:postcode":"3881 sb",
    "addr:street":"Voorthuizerstr;Gelderland",
    "iso:country":"NL",
    "sg:address":"Voorthuizerstr 31",
    "sg:city":"Putten",
    "sg:orig_category":"Artsen - Huisartsen",
    "sg:phone":"+31 341 351 640",
    "sg:postcode":"3881 SB",
    "sg:province":"Gelderland",
    "wof:name":"Coveen, R",
    "wof:placetype":"venue"
},
  "geometry": {"coordinates":[5.607633,52.253426],"type":"Point"}
}