{
  "type": "Feature",
  "properties": {
    "addr:full":"Coolsingel 87 Rotterdam Zuid-Holland 3012 AE",
    "addr:housenumber":"87",
    "addr:postcode":"3012 ae",
    "addr:street":"Coolsingel",
    "iso:country":"NL",
    "sg:address":"Coolsingel 87",
    "sg:city":"Rotterdam",
    "sg:orig_category":"Opticiens",
    "sg:phone":"+31 10 413 2984",
    "sg:postcode":"3012 AE",
    "sg:province":"Zuid-Holland",
    "wof:name":"De Lensclub",
    "wof:placetype":"venue"
},
  "geometry": {"coordinates":[4.4789061546,51.9215545654],"type":"Point"}
}