{
  "type": "Feature",
  "properties": {
    "iso:country":"NL",
    "sg:address":"Oude Essenerwg 13",
    "sg:city":"Kootwykerbroek",
    "sg:orig_category":"Meubelmakerijen",
    "sg:phone":"+31 342 443 533",
    "sg:postcode":"3774 JK",
    "sg:province":"Gelderland",
    "wof:name":"Lagen, J Van",
    "wof:placetype":"venue"
},
  "geometry": {"coordinates":[5.71966,52.153873],"type":"Point"}
}