{
  "type": "Feature",
  "properties": {
    "iso:country":"NL",
    "sg:address":"Ln V Nw Oosteinde 35",
    "sg:city":"Voorburg",
    "sg:orig_category":"Octrooionderzoek- En Exploitatiebureaus",
    "sg:phone":"+31 70 387 9714",
    "sg:postcode":"2274 EA",
    "sg:province":"Zuid-Holland",
    "wof:name":"Fondse Valves Bv",
    "wof:placetype":"venue"
},
  "geometry": {"coordinates":[4.34952,52.073792],"type":"Point"}
}