{
  "type": "Feature",
  "properties": {
    "iso:country":"NL",
    "sg:address":"Torendreef 3",
    "sg:city":"Bladel",
    "sg:orig_category":"Kappers",
    "sg:phone":"+31 497 382 379",
    "sg:postcode":"5531 ES",
    "sg:province":"Noord-Brabant",
    "wof:name":"Kapsalon Helma'S Hairstyling Dames Heren",
    "wof:placetype":"venue"
},
  "geometry": {"coordinates":[5.2216119766,51.3694534302],"type":"Point"}
}