{
  "type": "Feature",
  "properties": {
    "addr:full":"Noordeinde 6 Roelofarendsveen Zuid-Holland 2371 CT",
    "addr:housenumber":"6",
    "addr:postcode":"2371 ct",
    "addr:street":"Noordeinde",
    "iso:country":"NL",
    "sg:address":"Noordeinde 6",
    "sg:city":"Roelofarendsveen",
    "sg:orig_category":"Boekhouders",
    "sg:phone":"+31 71 331 3213",
    "sg:postcode":"2371 CT",
    "sg:province":"Zuid-Holland",
    "wof:name":"J.A. Kortekaas",
    "wof:placetype":"venue"
},
  "geometry": {"coordinates":[4.631685,52.202271],"type":"Point"}
}