{
  "type": "Feature",
  "properties": {
    "addr:full":"Noord 57 Schagen North Holland 1741 BB",
    "addr:housenumber":"57",
    "addr:postcode":"1741 bb",
    "addr:street":"Noord",
    "iso:country":"NL",
    "sg:address":"Noord 57",
    "sg:city":"Schagen",
    "sg:orig_category":"Boekhouders",
    "sg:phone":"+31 224 213 307",
    "sg:postcode":"1741 BB",
    "sg:province":"North Holland",
    "wof:name":"Administratieknt & Belastingadviesburo D",
    "wof:placetype":"venue"
},
  "geometry": {"coordinates":[4.792316,52.790642],"type":"Point"}
}