{
  "type": "Feature",
  "properties": {
    "addr:full":"Wieder 7 De Goorn North Holland 1648 GA",
    "addr:housenumber":"7",
    "addr:postcode":"1648 ga",
    "addr:street":"Wieder",
    "iso:country":"NL",
    "sg:address":"Wieder 7",
    "sg:city":"De Goorn",
    "sg:orig_category":"Hek- En Rasterwerken",
    "sg:phone":"+31 229 544 100",
    "sg:postcode":"1648 GA",
    "sg:province":"North Holland",
    "wof:name":"Veno Bv",
    "wof:placetype":"venue"
},
  "geometry": {"coordinates":[4.958999,52.625591],"type":"Point"}
}