{
  "type": "Feature",
  "properties": {
    "addr:full":"Nyverheidswg N 62 Amersfoort Utrecht 3812 PM",
    "addr:housenumber":"62",
    "addr:postcode":"3812 pm",
    "addr:street":"N",
    "iso:country":"NL",
    "sg:address":"Nyverheidswg N 62",
    "sg:city":"Amersfoort",
    "sg:orig_category":"Horecabenodigdheden",
    "sg:phone":"+31 33 462 0064",
    "sg:postcode":"3812 PM",
    "sg:province":"Utrecht",
    "sg:website":"http://www.wilcor.nl",
    "wof:name":"Wilcor",
    "wof:placetype":"venue"
},
  "geometry": {"coordinates":[5.370769,52.165344],"type":"Point"}
}