{
  "type": "Feature",
  "properties": {
    "addr:full":"Groenendaal 78 Landgraaf Limburg 6374 GM",
    "addr:housenumber":"78",
    "addr:postcode":"6374 gm",
    "addr:street":"Groenendaal",
    "iso:country":"NL",
    "sg:address":"Groenendaal 78",
    "sg:city":"Landgraaf",
    "sg:orig_category":"Hulpverlening Sociaal",
    "sg:phone":"+31 45 569 0840",
    "sg:postcode":"6374 GM",
    "sg:province":"Limburg",
    "wof:name":"Kamertraining",
    "wof:placetype":"venue"
},
  "geometry": {"coordinates":[6.043384,50.915649],"type":"Point"}
}