{
  "type": "Feature",
  "properties": {
    "addr:full":"Boterbloem 43 Bennekom Gelderland 6721 RC",
    "addr:housenumber":"43",
    "addr:postcode":"6721 rc",
    "addr:street":"Boterbloem;Gelderland",
    "iso:country":"NL",
    "sg:address":"Boterbloem 43",
    "sg:city":"Bennekom",
    "sg:orig_category":"Onderhoudswerken",
    "sg:phone":"+31 318 418 033",
    "sg:postcode":"6721 RC",
    "sg:province":"Gelderland",
    "wof:name":"Holland, J Van",
    "wof:placetype":"venue"
},
  "geometry": {"coordinates":[5.665957,52.001789],"type":"Point"}
}