{
  "type": "Feature",
  "properties": {
    "addr:full":"Landingsplaats 14 Ysselstein Ut Utrecht 3402 DA",
    "addr:housenumber":"14",
    "addr:postcode":"3402 da",
    "addr:street":"Landingsplaats",
    "iso:country":"NL",
    "sg:address":"Landingsplaats 14",
    "sg:city":"Ysselstein Ut",
    "sg:orig_category":"Autorijscholen",
    "sg:phone":"+31 6 24683107",
    "sg:postcode":"3402 DA",
    "sg:province":"Utrecht",
    "wof:name":"Ashna",
    "wof:placetype":"venue"
},
  "geometry": {"coordinates":[5.057742,52.025517],"type":"Point"}
}