{
  "type": "Feature",
  "properties": {
    "addr:full":"De Wiek 41 Ede Gld Gelderland 6712 JB",
    "addr:housenumber":"41",
    "addr:postcode":"6712 jb",
    "addr:street":"De Wiek;Gld Gelderland",
    "iso:country":"NL",
    "sg:address":"De Wiek 41",
    "sg:city":"Ede Gld",
    "sg:orig_category":"Paramedische Behandelingen",
    "sg:phone":"+31 318 616 038",
    "sg:postcode":"6712 JB",
    "sg:province":"Gelderland",
    "wof:name":"Logopediste Jo J. Pel Van Der Spek",
    "wof:placetype":"venue"
},
  "geometry": {"coordinates":[5.668653,52.046074],"type":"Point"}
}