{
  "type": "Feature",
  "properties": {
    "iso:country":"NL",
    "sg:address":"Het Zicht 39",
    "sg:city":"S Gravenhage",
    "sg:orig_category":"Verpakkingsmachines",
    "sg:phone":"+31 70 321 0031",
    "sg:postcode":"2543 AJ",
    "sg:province":"Zuid-Holland",
    "wof:name":"Opti Pack Bv",
    "wof:placetype":"venue"
},
  "geometry": {"coordinates":[4.26264,52.040501],"type":"Point"}
}