{
  "type": "Feature",
  "properties": {
    "iso:country":"NL",
    "sg:address":"J Wagenaarstr 26",
    "sg:city":"Groningen",
    "sg:orig_category":"Grafisch Ontwerpers",
    "sg:phone":"+31 6 13513501",
    "sg:postcode":"9728 VP",
    "sg:province":"Groningen",
    "wof:name":"Pijl",
    "wof:placetype":"venue"
},
  "geometry": {"coordinates":[6.554379,53.190163],"type":"Point"}
}