{
  "type": "Feature",
  "properties": {
    "addr:full":"De Morinel 73 Dronten Flevoland 8251 HT",
    "addr:housenumber":"73",
    "addr:postcode":"8251 ht",
    "addr:street":"De Morinel;Flevoland",
    "iso:country":"NL",
    "sg:address":"De Morinel 73",
    "sg:city":"Dronten",
    "sg:orig_category":"Verzekeringen - Verzekeringskantoren",
    "sg:phone":"+31 321 319 201",
    "sg:postcode":"8251 HT",
    "sg:province":"Flevoland",
    "wof:name":"Pas, Te",
    "wof:placetype":"venue"
},
  "geometry": {"coordinates":[5.7308897972,52.5315284729],"type":"Point"}
}