{
  "type": "Feature",
  "properties": {
    "iso:country":"NL",
    "sg:address":"Lissebeemd 14",
    "sg:city":"Oosterhout Nb",
    "sg:orig_category":"Airconditioning And Ventilatie",
    "sg:phone":"+31 162 432 287",
    "sg:postcode":"4907 DR",
    "sg:province":"Noord-Brabant",
    "wof:name":"Dawood",
    "wof:placetype":"venue"
},
  "geometry": {"coordinates":[4.860991,51.659679],"type":"Point"}
}