{
  "type": "Feature",
  "properties": {
    "addr:full":"Rubensstr 65 Deventer NL.08 7412 GX",
    "addr:housenumber":"65;nl.08",
    "addr:postcode":"7412 gx",
    "addr:street":"Rubensstr",
    "iso:country":"NL",
    "sg:address":"Rubensstr 65",
    "sg:city":"Deventer",
    "sg:orig_category":"Meubelmakerijen",
    "sg:phone":"+31 570 644 679",
    "sg:postcode":"7412 GX",
    "sg:province":"NL.08",
    "sg:website":"http://www.meubelbeelden.nl",
    "wof:name":"Voorde, Paul Ten",
    "wof:placetype":"venue"
},
  "geometry": {"coordinates":[6.130456,52.266087],"type":"Point"}
}