{
  "type": "Feature",
  "properties": {
    "addr:full":"Produktiewg 5 Ijsselstein Utrecht 3401 MG",
    "addr:housenumber":"5",
    "addr:postcode":"3401 mg",
    "addr:street":"Produktiewg",
    "iso:country":"NL",
    "sg:address":"Produktiewg 5",
    "sg:city":"Ijsselstein",
    "sg:orig_category":"Bedrijfskleding - Verhuur",
    "sg:phone":"+31 30 212 3000",
    "sg:postcode":"3401 MG",
    "sg:province":"Utrecht",
    "wof:name":"Vendrig-Ijsselstein Bv",
    "wof:placetype":"venue"
},
  "geometry": {"coordinates":[5.057838,52.011227],"type":"Point"}
}