{
  "type": "Feature",
  "properties": {
    "iso:country":"NL",
    "sg:address":"Parallelstr 1",
    "sg:city":"Oyen",
    "sg:orig_category":"Waterschappen",
    "sg:phone":"+31 412 492 571",
    "sg:postcode":"5394 LW",
    "sg:province":"Noord-Brabant",
    "wof:name":"Maaskant, De",
    "wof:placetype":"venue"
},
  "geometry": {"coordinates":[-96.0559387207,42.8205337524],"type":"Point"}
}