{
  "type": "Feature",
  "properties": {
    "addr:full":"A Coolenln 2A Eindhoven North Brabant 5644 RX",
    "addr:housenumber":"2a",
    "addr:postcode":"5644 rx",
    "iso:country":"NL",
    "sg:address":"A Coolenln 2A",
    "sg:city":"Eindhoven",
    "sg:orig_category":"Midgetgolf",
    "sg:phone":"+31 40 252 4632",
    "sg:postcode":"5644 RX",
    "sg:province":"North Brabant",
    "wof:name":"Gennep",
    "wof:placetype":"venue"
},
  "geometry": {"coordinates":[5.48331,51.41238],"type":"Point"}
}