{
  "type": "Feature",
  "properties": {
    "addr:full":"Duiveland 13D Beverwyk Noord-Holland 1948 RB",
    "addr:housenumber":"13d",
    "addr:postcode":"1948 rb",
    "addr:street":"Duiveland",
    "iso:country":"NL",
    "sg:address":"Duiveland 13D",
    "sg:city":"Beverwyk",
    "sg:orig_category":"Bloemen En Planten - Groothandel",
    "sg:phone":"+31 251 224 129",
    "sg:postcode":"1948 RB",
    "sg:province":"Noord-Holland",
    "wof:name":"Rixel Velsen Bv, Van",
    "wof:placetype":"venue"
},
  "geometry": {"coordinates":[4.67361,52.467064],"type":"Point"}
}