{
  "type": "Feature",
  "properties": {
    "iso:country":"NL",
    "sg:address":"Freesiastr 60",
    "sg:city":"Oosterhout Nb",
    "sg:orig_category":"Meubelen",
    "sg:phone":"+31 162 451 052",
    "sg:postcode":"4904 CS",
    "sg:province":"Noord-Brabant",
    "wof:name":"Bakx",
    "wof:placetype":"venue"
},
  "geometry": {"coordinates":[4.861803,51.626091],"type":"Point"}
}