{
  "type": "Feature",
  "properties": {
    "iso:country":"NL",
    "sg:address":"Kroonstr 43",
    "sg:city":"Etten Leur",
    "sg:orig_category":"Grondwerken",
    "sg:phone":"+31 76 501 9967",
    "sg:postcode":"4879 AV",
    "sg:province":"North Brabant",
    "wof:name":"Veeke",
    "wof:placetype":"venue"
},
  "geometry": {"coordinates":[4.626861,51.55759],"type":"Point"}
}