{
  "type": "Feature",
  "properties": {
    "addr:full":"Hoofdstr 202 Santpoort Noord California 2071 EN",
    "addr:housenumber":"202",
    "addr:postcode":"2071 en",
    "addr:street":"Santpoort Noord",
    "iso:country":"NL",
    "sg:address":"Hoofdstr 202",
    "sg:city":"Santpoort Noord",
    "sg:orig_category":"Mensendieck - Oefentherapeuten",
    "sg:phone":"+31 23 537 3026",
    "sg:postcode":"2071 EN",
    "sg:province":"California",
    "wof:name":"Tjiam, A L J M",
    "wof:placetype":"venue"
},
  "geometry": {"coordinates":[-121.95871,39.780125],"type":"Point"}
}