{
  "type": "Feature",
  "properties": {
    "addr:full":"Rykswg W 18C Westerbroek Groningen 9608 PC",
    "addr:housenumber":"18c",
    "addr:postcode":"9608 pc",
    "addr:street":"W",
    "iso:country":"NL",
    "sg:address":"Rykswg W 18C",
    "sg:city":"Westerbroek",
    "sg:orig_category":"Onroerende Goederen",
    "sg:phone":"+31 50 404 2993",
    "sg:postcode":"9608 PC",
    "sg:province":"Groningen",
    "wof:name":"Anker, 'T",
    "wof:placetype":"venue"
},
  "geometry": {"coordinates":[6.685745,53.177608],"type":"Point"}
}