{
  "type": "Feature",
  "properties": {
    "addr:full":"Kerkeind 51 Milheeze North Brabant 5763 BB",
    "addr:housenumber":"51",
    "addr:postcode":"5763 bb",
    "addr:street":"Kerkeind",
    "iso:country":"NL",
    "sg:address":"Kerkeind 51",
    "sg:city":"Milheeze",
    "sg:orig_category":"Kappers",
    "sg:phone":"+31 492 342 374",
    "sg:postcode":"5763 BB",
    "sg:province":"North Brabant",
    "wof:name":"Anmarie",
    "wof:placetype":"venue"
},
  "geometry": {"coordinates":[5.777132988,51.5027732849],"type":"Point"}
}