{
  "type": "Feature",
  "properties": {
    "addr:full":"Westerstraat 150 Emmen Provincie Drenthe 7811 MV",
    "addr:housenumber":"150",
    "addr:postcode":"7811 mv",
    "addr:street":"Westerstraat;Provincie Drenthe",
    "iso:country":"NL",
    "sg:address":"Westerstraat 150",
    "sg:city":"Emmen",
    "sg:orig_category":"Bedrijvencentra",
    "sg:phone":"+31 591 641 000",
    "sg:postcode":"7811 MV",
    "sg:province":"Provincie Drenthe",
    "wof:name":"Dominent International Bv",
    "wof:placetype":"venue"
},
  "geometry": {"coordinates":[6.892099,52.786316],"type":"Point"}
}