{
  "type": "Feature",
  "properties": {
    "addr:full":"Zadelmakerstraat 8 Almere Flevoland 1315 AP",
    "addr:housenumber":"8",
    "addr:postcode":"1315 ap",
    "addr:street":"Zadelmakerstraat;Flevoland",
    "iso:country":"NL",
    "sg:address":"Zadelmakerstraat 8",
    "sg:city":"Almere",
    "sg:orig_category":"Fietshandelaren",
    "sg:phone":"+31 36 534 4530",
    "sg:postcode":"1315 AP",
    "sg:province":"Flevoland",
    "wof:name":"Profile De Fietsspecialist",
    "wof:placetype":"venue"
},
  "geometry": {"coordinates":[5.21589,52.368771],"type":"Point"}
}