{
  "type": "Feature",
  "properties": {
    "iso:country":"NL",
    "sg:address":"Willem De Zwijgerstraat 16",
    "sg:city":"Eindhoven",
    "sg:orig_category":"Makelaars In Onroerend Goed",
    "sg:phone":"+31 40 244 8025",
    "sg:postcode":"5611 JL",
    "sg:province":"North Brabant",
    "wof:name":"Makelaarskantoor Ottenheim",
    "wof:placetype":"venue"
},
  "geometry": {"coordinates":[5.471703,51.435558],"type":"Point"}
}