{
  "type": "Feature",
  "properties": {
    "addr:full":"Molenstr 16 Renswoude Utrecht 3927 AC",
    "addr:housenumber":"16",
    "addr:postcode":"3927 ac",
    "addr:street":"Molenstr",
    "iso:country":"NL",
    "sg:address":"Molenstr 16",
    "sg:city":"Renswoude",
    "sg:orig_category":"Winkelinrichting",
    "sg:phone":"+31 318 574 015",
    "sg:postcode":"3927 AC",
    "sg:province":"Utrecht",
    "sg:website":"http://www.perfotube.nl",
    "wof:name":"Perfo Tube",
    "wof:placetype":"venue"
},
  "geometry": {"coordinates":[5.5361890793,52.0763893127],"type":"Point"}
}