{
  "type": "Feature",
  "properties": {
    "addr:full":"Liesveld 18 Terheijden North Brabant 4844 RA",
    "addr:housenumber":"18",
    "addr:postcode":"4844 ra",
    "addr:street":"Liesveld",
    "iso:country":"NL",
    "sg:address":"Liesveld 18",
    "sg:city":"Terheijden",
    "sg:orig_category":"Projectontwikkeling",
    "sg:phone":"+31 76 593 2774",
    "sg:postcode":"4844 RA",
    "sg:province":"North Brabant",
    "wof:name":"Domo",
    "wof:placetype":"venue"
},
  "geometry": {"coordinates":[4.753733,51.646023],"type":"Point"}
}