{
  "type": "Feature",
  "properties": {
    "addr:full":"Hoefblad 29 Culemborg Gelderland 4102 JR",
    "addr:housenumber":"29",
    "addr:postcode":"4102 jr",
    "addr:street":"Hoefblad;Gelderland",
    "iso:country":"NL",
    "sg:address":"Hoefblad 29",
    "sg:city":"Culemborg",
    "sg:orig_category":"Metaalwerken",
    "sg:phone":"+31 6 26222368",
    "sg:postcode":"4102 JR",
    "sg:province":"Gelderland",
    "wof:name":"D Beltman",
    "wof:placetype":"venue"
},
  "geometry": {"coordinates":[5.24619,51.952606],"type":"Point"}
}