{
  "type": "Feature",
  "properties": {
    "iso:country":"NL",
    "sg:address":"Rynlanderwg 1265",
    "sg:city":"Nieuw Vennep",
    "sg:orig_category":"Loonbedrijven",
    "sg:phone":"+31 6 24262092",
    "sg:postcode":"2153 KC",
    "sg:province":"Noord-Holland",
    "wof:name":"Gort, J R",
    "wof:placetype":"venue"
},
  "geometry": {"coordinates":[4.672,52.26347],"type":"Point"}
}