{
  "type": "Feature",
  "properties": {
    "addr:full":"Ten Katestr 34 Amsterdam Noord-Holland 1053 CG",
    "addr:housenumber":"34",
    "addr:postcode":"1053 cg",
    "addr:street":"Ten",
    "iso:country":"NL",
    "sg:address":"Ten Katestr 34",
    "sg:city":"Amsterdam",
    "sg:orig_category":"Babyartikelen",
    "sg:phone":"+31 20 612 9361",
    "sg:postcode":"1053 CG",
    "sg:province":"Noord-Holland",
    "sg:website":"http://www.baby-boem.nl",
    "wof:name":"Baby Boem",
    "wof:placetype":"venue"
},
  "geometry": {"coordinates":[4.867091,52.366352],"type":"Point"}
}