{
  "type": "Feature",
  "properties": {
    "iso:country":"NL",
    "sg:address":"Thorbeckeln 38",
    "sg:city":"Barneveld",
    "sg:orig_category":"Adviesbureaus Automatisering",
    "sg:phone":"+31 342 462 618",
    "sg:postcode":"3771 EH",
    "sg:province":"Gelderland",
    "wof:name":"Clements & Baan",
    "wof:placetype":"venue"
},
  "geometry": {"coordinates":[5.588843,52.141216],"type":"Point"}
}