{
  "type": "Feature",
  "properties": {
    "addr:full":"Keersluiswg 7 Almere Flevoland 1332 EE",
    "addr:housenumber":"7",
    "addr:postcode":"1332 ee",
    "addr:street":"Keersluiswg;Flevoland",
    "iso:country":"NL",
    "sg:address":"Keersluiswg 7",
    "sg:city":"Almere",
    "sg:orig_category":"Airconditioning",
    "sg:phone":"+31 36 532 4580",
    "sg:postcode":"1332 EE",
    "sg:province":"Flevoland",
    "sg:website":"http://www.bmr.nl",
    "wof:name":"Bm-Air Service Bv",
    "wof:placetype":"venue"
},
  "geometry": {"coordinates":[5.248432,52.409443],"type":"Point"}
}