{
  "type": "Feature",
  "properties": {
    "addr:full":"Geestbrugwg 109 Ryswyk Zh South Holland 2281 CJ",
    "addr:housenumber":"109",
    "addr:postcode":"2281 cj",
    "addr:street":"Ryswyk Zh",
    "iso:country":"NL",
    "sg:address":"Geestbrugwg 109",
    "sg:city":"Ryswyk Zh",
    "sg:orig_category":"Boeken En Tijdschriften",
    "sg:phone":"+31 70 399 0655",
    "sg:postcode":"2281 CJ",
    "sg:province":"South Holland",
    "sg:website":"http://www.kettenis.nl",
    "wof:name":"Kettenis Studieboeken",
    "wof:placetype":"venue"
},
  "geometry": {"coordinates":[4.341704,52.056934],"type":"Point"}
}