{
  "type": "Feature",
  "properties": {
    "addr:full":"Postbus 1030 Groningen Groningen 9701 BA",
    "addr:housenumber":"1030",
    "addr:postcode":"9701 ba",
    "addr:street":"Postbus",
    "iso:country":"NL",
    "sg:address":"Postbus 1030",
    "sg:city":"Groningen",
    "sg:orig_category":"Organisaties And Verenigingen",
    "sg:phone":"+31 50 541 2709",
    "sg:postcode":"9701 BA",
    "sg:province":"Groningen",
    "wof:name":"Gereformeerde Studentenvereniging",
    "wof:placetype":"venue"
},
  "geometry": {"coordinates":[6.5650200844,53.2164497375],"type":"Point"}
}