{
  "type": "Feature",
  "properties": {
    "iso:country":"NL",
    "sg:address":"Kapelstr 60",
    "sg:city":"Heeze",
    "sg:orig_category":"Banken",
    "sg:phone":"+31 40 226 1370",
    "sg:postcode":"5591 HG",
    "sg:province":"North Brabant",
    "wof:name":"Regio Bank",
    "wof:placetype":"venue"
},
  "geometry": {"coordinates":[5.580116,51.382423],"type":"Point"}
}