{
  "type": "Feature",
  "properties": {
    "addr:full":"Plutostr 3 Krommenie Noord-Holland 1562 XG",
    "addr:housenumber":"3",
    "addr:postcode":"1562 xg",
    "addr:street":"Plutostr",
    "iso:country":"NL",
    "sg:address":"Plutostr 3",
    "sg:city":"Krommenie",
    "sg:orig_category":"Administratie- En Boekhoudkantoren",
    "sg:phone":"+31 75 621 6339",
    "sg:postcode":"1562 XG",
    "sg:province":"Noord-Holland",
    "wof:name":"Neeft",
    "wof:placetype":"venue"
},
  "geometry": {"coordinates":[4.753072,52.502525],"type":"Point"}
}