{
  "type": "Feature",
  "properties": {
    "iso:country":"NL",
    "sg:address":"Lijsterbeslaan 28",
    "sg:city":"Scherpenzeel Gld",
    "sg:orig_category":"Fotostudio'S And Fotografen",
    "sg:phone":"+31 33 277 8271",
    "sg:postcode":"3925 JJ",
    "sg:province":"Gelderland",
    "wof:name":"Dick Van De Lagemaat Fotografie",
    "wof:placetype":"venue"
},
  "geometry": {"coordinates":[5.489952,52.08157],"type":"Point"}
}