{
  "type": "Feature",
  "properties": {
    "addr:full":"Schipperswal 36 Roermond Limburg 6041 TC",
    "addr:housenumber":"36",
    "addr:postcode":"6041 tc",
    "addr:street":"Schipperswal",
    "iso:country":"NL",
    "sg:address":"Schipperswal 36",
    "sg:city":"Roermond",
    "sg:orig_category":"Schilders",
    "sg:phone":"+31 475 333 035",
    "sg:postcode":"6041 TC",
    "sg:province":"Limburg",
    "wof:name":"Loven Bv",
    "wof:placetype":"venue"
},
  "geometry": {"coordinates":[5.994513,51.200474],"type":"Point"}
}