{
  "type": "Feature",
  "properties": {
    "iso:country":"NL",
    "sg:address":"Breedstraat 1",
    "sg:city":"Weesp",
    "sg:orig_category":"Werving And Selectie Van Tijdelijk Personeel And Uitzendkantoren",
    "sg:phone":"+31 294 432 626",
    "sg:postcode":"1381 BX",
    "sg:province":"North Holland",
    "wof:name":"Always Action Uitzendbureau",
    "wof:placetype":"venue"
},
  "geometry": {"coordinates":[5.0417580605,52.3062095642],"type":"Point"}
}