{
  "type": "Feature",
  "properties": {
    "addr:full":"Spankerenseweg 16 Leuvenheim Gelderland 6974 BC",
    "addr:housenumber":"16",
    "addr:postcode":"6974 bc",
    "addr:street":"Spankerenseweg;Gelderland",
    "iso:country":"NL",
    "sg:address":"Spankerenseweg 16",
    "sg:city":"Leuvenheim",
    "sg:orig_category":"Granen, Zaden And Diervoeders Gh",
    "sg:phone":"+31 575 569 965",
    "sg:postcode":"6974 BC",
    "sg:province":"Gelderland",
    "wof:name":"Peak International Products Bv",
    "wof:placetype":"venue"
},
  "geometry": {"coordinates":[-126.555511,54.485668],"type":"Point"}
}