{
  "type": "Feature",
  "properties": {
    "addr:full":"Postbus 6810 Breda Noord-Brabant 4802 HV",
    "addr:housenumber":"6810",
    "addr:postcode":"breda;4802 hv",
    "addr:street":"Postbus",
    "iso:country":"NL",
    "sg:address":"Postbus 6810",
    "sg:city":"Breda",
    "sg:orig_category":"Fotoreportages",
    "sg:phone":"+31 76 572 0350",
    "sg:postcode":"4802 HV",
    "sg:province":"Noord-Brabant",
    "sg:website":"http://www.dimitrivisser.nl/marriage",
    "wof:name":"Dimitri Visser",
    "wof:placetype":"venue"
},
  "geometry": {"coordinates":[4.7723,51.590759],"type":"Point"}
}