{
  "type": "Feature",
  "properties": {
    "addr:full":"Telexstr 31 Tilburg Noord-Brabant 5038 DJ",
    "addr:housenumber":"31",
    "addr:postcode":"5038 dj",
    "addr:street":"Telexstr",
    "iso:country":"NL",
    "sg:address":"Telexstr 31",
    "sg:city":"Tilburg",
    "sg:orig_category":"Architecten En Architectenbureaus",
    "sg:phone":"+31 13 536 6466",
    "sg:postcode":"5038 DJ",
    "sg:province":"Noord-Brabant",
    "wof:name":"Tol, Ir B",
    "wof:placetype":"venue"
},
  "geometry": {"coordinates":[5.085651,51.557549],"type":"Point"}
}