{
  "type": "Feature",
  "properties": {
    "addr:full":"Kloosterwg 68 Laren Nh North Holland 1251 WG",
    "addr:housenumber":"68",
    "addr:postcode":"1251 wg",
    "addr:street":"Kloosterwg;Nh North",
    "iso:country":"NL",
    "sg:address":"Kloosterwg 68",
    "sg:city":"Laren Nh",
    "sg:orig_category":"Bloemen En Planten",
    "sg:phone":"+31 35 538 2568",
    "sg:postcode":"1251 WG",
    "sg:province":"North Holland",
    "wof:name":"Larense Bloemenhdl",
    "wof:placetype":"venue"
},
  "geometry": {"coordinates":[5.236094,52.248306],"type":"Point"}
}