{
  "type": "Feature",
  "properties": {
    "iso:country":"NL",
    "sg:address":"Vlas Oord 20",
    "sg:city":"Houten",
    "sg:orig_category":"Artiesten/Gezelschappen",
    "sg:phone":"+31 6 18062865",
    "sg:postcode":"3991 XC",
    "sg:province":"Utrecht",
    "wof:name":"Wit Wout, De",
    "wof:placetype":"venue"
},
  "geometry": {"coordinates":[5.160716,52.032085],"type":"Point"}
}