{
  "type": "Feature",
  "properties": {
    "iso:country":"NL",
    "sg:address":"Spijkerstraat 193",
    "sg:city":"Arnhem",
    "sg:orig_category":"Wasserettes And Stomerijen",
    "sg:phone":"+31 26 442 6482",
    "sg:postcode":"6828 DC",
    "sg:province":"Gelderland",
    "wof:name":"Wassalon Stomerij Dijkkamp",
    "wof:placetype":"venue"
},
  "geometry": {"coordinates":[5.9185647964,51.9826393127],"type":"Point"}
}