{
  "type": "Feature",
  "properties": {
    "addr:full":"Postbus 1151 Roosendaal North Brabant 4700 BD",
    "addr:housenumber":"1151",
    "addr:postcode":"4700 bd",
    "addr:street":"Postbus",
    "iso:country":"NL",
    "sg:address":"Postbus 1151",
    "sg:city":"Roosendaal",
    "sg:orig_category":"Medische Installaties En Instrumenten",
    "sg:phone":"+31 165 301 045",
    "sg:postcode":"4700 BD",
    "sg:province":"North Brabant",
    "wof:name":"Yoris",
    "wof:placetype":"venue"
},
  "geometry": {"coordinates":[4.45767,51.531403],"type":"Point"}
}