{
  "type": "Feature",
  "properties": {
    "addr:full":"Graanmarkt 3 Zwaagdijk North Holland 1681 PA",
    "addr:housenumber":"3",
    "addr:postcode":"1681 pa",
    "addr:street":"Graanmarkt",
    "iso:country":"NL",
    "sg:address":"Graanmarkt 3",
    "sg:city":"Zwaagdijk",
    "sg:classifiers":[
        {
            "category":"Professional",
            "subcategory":"Accounting & Tax Preparation",
            "type":"Services"
        }
    ],
    "sg:phone":"+31 228 562 004",
    "sg:postcode":"1681 PA",
    "sg:province":"North Holland",
    "sg:tags":[
        "accountant"
    ],
    "wof:name":"Ltb Accountants En Adviseurs Bv",
    "wof:placetype":"venue"
},
  "geometry": {"coordinates":[5.151344,52.701035],"type":"Point"}
}