{
  "type": "Feature",
  "properties": {
    "addr:full":"Valkenierstraat 1 Ridderkerk South Holland 2984 AZ",
    "addr:housenumber":"1",
    "addr:postcode":"2984 az",
    "addr:street":"Valkenierstraat",
    "iso:country":"NL",
    "sg:address":"Valkenierstraat 1",
    "sg:city":"Ridderkerk",
    "sg:orig_category":"Metalen And Ertsen Gh",
    "sg:phone":"+31 180 412 133",
    "sg:postcode":"2984 AZ",
    "sg:province":"South Holland",
    "wof:name":"Technisch Handelsburo Verhoef Bv",
    "wof:placetype":"venue"
},
  "geometry": {"coordinates":[4.61451,51.877064],"type":"Point"}
}