{
  "type": "Feature",
  "properties": {
    "iso:country":"NL",
    "sg:address":"Kleibultwg 27",
    "sg:city":"Oldenzaal",
    "sg:orig_category":"Schilders",
    "sg:phone":"+31 541 515 986",
    "sg:postcode":"7575 BM",
    "sg:province":"Overijssel",
    "wof:name":"Belderink, H G M",
    "wof:placetype":"venue"
},
  "geometry": {"coordinates":[6.927134,52.29388],"type":"Point"}
}