{
  "type": "Feature",
  "properties": {
    "addr:full":"Grt Noord 120 Hoorn Nh Noord-Holland 1621 KM",
    "addr:housenumber":"120",
    "addr:postcode":"1621 km",
    "iso:country":"NL",
    "sg:address":"Grt Noord 120",
    "sg:city":"Hoorn Nh",
    "sg:orig_category":"Wolartikelen En Breiwol",
    "sg:phone":"+31 229 215 682",
    "sg:postcode":"1621 KM",
    "sg:province":"Noord-Holland",
    "wof:name":"Schouten Vof, Paul",
    "wof:placetype":"venue"
},
  "geometry": {"coordinates":[5.0520701408,52.6423988342],"type":"Point"}
}