{
  "type": "Feature",
  "properties": {
    "iso:country":"NL",
    "sg:address":"Stationsstraat 25",
    "sg:city":"Wierden",
    "sg:orig_category":"Bloemen And Planten",
    "sg:phone":"+31 546 574 691",
    "sg:postcode":"7641 BV",
    "sg:province":"NL.08",
    "wof:name":"Vof W. Nijzink Wierden",
    "wof:placetype":"venue"
},
  "geometry": {"coordinates":[6.590784,52.356815],"type":"Point"}
}