{
  "type": "Feature",
  "properties": {
    "addr:full":"Ransdalerstraat 64 Ransdaal Limburg 6312 AJ",
    "addr:housenumber":"64",
    "addr:postcode":"6312 aj",
    "addr:street":"Ransdalerstraat",
    "iso:country":"NL",
    "sg:address":"Ransdalerstraat 64",
    "sg:city":"Ransdaal",
    "sg:orig_category":"Bibliotheken And Openbare Archieven",
    "sg:phone":"+31 43 459 2769",
    "sg:postcode":"6312 AJ",
    "sg:province":"Limburg",
    "wof:name":"Openb Bibliotheken",
    "wof:placetype":"venue"
},
  "geometry": {"coordinates":[5.893331,50.86372],"type":"Point"}
}