{
  "type": "Feature",
  "properties": {
    "iso:country":"NL",
    "sg:address":"Schoolstraat 22",
    "sg:city":"Halfweg Nh",
    "sg:orig_category":"Bedrijfs- And Managementsconsultants",
    "sg:phone":"+31 20 497 8565",
    "sg:postcode":"1165 HC",
    "sg:province":"Noord-Holland",
    "wof:name":"Arboconsult",
    "wof:placetype":"venue"
},
  "geometry": {"coordinates":[4.752783,52.382919],"type":"Point"}
}