{
  "type": "Feature",
  "properties": {
    "addr:full":"West 92 Avenhorn Noord-Holland 1633 JG",
    "addr:housenumber":"92",
    "addr:postcode":"1633 jg",
    "addr:street":"West",
    "iso:country":"NL",
    "sg:address":"West 92",
    "sg:city":"Avenhorn",
    "sg:orig_category":"Metaalwerken",
    "sg:phone":"+31 229 541 274",
    "sg:postcode":"1633 JG",
    "sg:province":"Noord-Holland",
    "wof:name":"J.T. Kuypers",
    "wof:placetype":"venue"
},
  "geometry": {"coordinates":[4.944391,52.623367],"type":"Point"}
}