{
  "type": "Feature",
  "properties": {
    "addr:full":"Aagje Dekenlaan 30 Soest Utrecht 3768 XR",
    "addr:housenumber":"30",
    "addr:postcode":"3768 xr",
    "addr:street":"Aagje Dekenlaan",
    "iso:country":"NL",
    "sg:address":"Aagje Dekenlaan 30",
    "sg:city":"Soest",
    "sg:orig_category":"Film-, Tv- And Videoproductie",
    "sg:phone":"+31 35 603 2889",
    "sg:postcode":"3768 XR",
    "sg:province":"Utrecht",
    "wof:name":"Ron Zoeteman Av Bv",
    "wof:placetype":"venue"
},
  "geometry": {"coordinates":[5.313841,52.164661],"type":"Point"}
}