{
  "type": "Feature",
  "properties": {
    "addr:full":"Past Blommaertstr 12 Ravenstein North Brabant 5371 RG",
    "addr:housenumber":"12",
    "addr:postcode":"5371 rg",
    "iso:country":"NL",
    "sg:address":"Past Blommaertstr 12",
    "sg:city":"Ravenstein",
    "sg:orig_category":"Kabels",
    "sg:phone":"+31 486 414 136",
    "sg:postcode":"5371 RG",
    "sg:province":"North Brabant",
    "wof:name":"Akker, Van Den",
    "wof:placetype":"venue"
},
  "geometry": {"coordinates":[5.6723608971,51.7763786316],"type":"Point"}
}