{
  "type": "Feature",
  "properties": {
    "iso:country":"NL",
    "sg:address":"Bloemfonteinstr 65",
    "sg:city":"S Gravenhage",
    "sg:classifiers":[
        {
            "category":"Retail",
            "subcategory":"Auto Repair",
            "type":"Services"
        }
    ],
    "sg:phone":"+31 70 380 1933",
    "sg:postcode":"2572 JB",
    "sg:province":"Zuid-Holland",
    "sg:tags":[
        "garage"
    ],
    "wof:name":"Turkmen",
    "wof:placetype":"venue"
},
  "geometry": {"coordinates":[4.29421,52.06422],"type":"Point"}
}