{
  "type": "Feature",
  "properties": {
    "addr:full":"Hg Hondstr 192 Deventer NL.08 7415 GH",
    "addr:housenumber":"192;nl.08",
    "addr:postcode":"7415 gh",
    "iso:country":"NL",
    "sg:address":"Hg Hondstr 192",
    "sg:city":"Deventer",
    "sg:orig_category":"Bloemen En Planten",
    "sg:phone":"+31 570 606 775",
    "sg:postcode":"7415 GH",
    "sg:province":"NL.08",
    "wof:name":"Maaike",
    "wof:placetype":"venue"
},
  "geometry": {"coordinates":[6.169074,52.265236],"type":"Point"}
}