{
  "type": "Feature",
  "properties": {
    "addr:full":"Wolfeynde 6 Beek Lb Limburg 6191 EB",
    "addr:housenumber":"6",
    "addr:postcode":"lb;6191 eb",
    "addr:street":"Wolfeynde",
    "iso:country":"NL",
    "sg:address":"Wolfeynde 6",
    "sg:city":"Beek Lb",
    "sg:orig_category":"Zonweringen",
    "sg:phone":"+31 46 437 7331",
    "sg:postcode":"6191 EB",
    "sg:province":"Limburg",
    "wof:name":"Gecolux Bv",
    "wof:placetype":"venue"
},
  "geometry": {"coordinates":[-93.129936,36.705662],"type":"Point"}
}