{
  "type": "Feature",
  "properties": {
    "addr:full":"Langestr 3-5 Huissen Gelderland 6851 AK",
    "addr:housenumber":"3-5",
    "addr:postcode":"6851 ak",
    "addr:street":"Langestr;Gelderland",
    "iso:country":"NL",
    "sg:address":"Langestr 3-5",
    "sg:city":"Huissen",
    "sg:orig_category":"Herenkleding",
    "sg:phone":"+31 26 325 3333",
    "sg:postcode":"6851 AK",
    "sg:province":"Gelderland",
    "wof:name":"Broekman",
    "wof:placetype":"venue"
},
  "geometry": {"coordinates":[5.94326,51.937325],"type":"Point"}
}