{
  "type": "Feature",
  "properties": {
    "iso:country":"NL",
    "sg:address":"Sarphatistr 179",
    "sg:city":"Amsterdam",
    "sg:orig_category":"Video - Faciliteiten En Producties",
    "sg:phone":"+31 20 422 6611",
    "sg:postcode":"1018 GE",
    "sg:province":"Noord-Holland",
    "wof:name":"Moving Image",
    "wof:placetype":"venue"
},
  "geometry": {"coordinates":[4.914033,52.362633],"type":"Point"}
}