{
  "type": "Feature",
  "properties": {
    "addr:full":"Maatweg 67 Elspeet Gelderland 8075 BD",
    "addr:housenumber":"67",
    "addr:postcode":"8075 bd",
    "addr:street":"Maatweg;Gelderland",
    "iso:country":"NL",
    "sg:address":"Maatweg 67",
    "sg:city":"Elspeet",
    "sg:orig_category":"Goederenvervoer Over De Weg",
    "sg:phone":"+31 577 491 258",
    "sg:postcode":"8075 BD",
    "sg:province":"Gelderland",
    "wof:name":"Vof Van De Brug Transporten",
    "wof:placetype":"venue"
},
  "geometry": {"coordinates":[5.794497,52.29752],"type":"Point"}
}