{
  "type": "Feature",
  "properties": {
    "addr:full":"Kerkhofln 58 Zwanenburg Noord-Holland 1161 JD",
    "addr:housenumber":"58",
    "addr:postcode":"1161 jd",
    "addr:street":"Kerkhofln",
    "iso:country":"NL",
    "sg:address":"Kerkhofln 58",
    "sg:city":"Zwanenburg",
    "sg:orig_category":"Begrafenisverzorging",
    "sg:phone":"+31 20 497 0901",
    "sg:postcode":"1161 JD",
    "sg:province":"Noord-Holland",
    "sg:website":"http://www.monuta.nl",
    "wof:name":"Monuta Hoogland",
    "wof:placetype":"venue"
},
  "geometry": {"coordinates":[4.74723,52.376625],"type":"Point"}
}