{
  "type": "Feature",
  "properties": {
    "iso:country":"NL",
    "sg:address":"Westzijde 390",
    "sg:city":"Zaandam",
    "sg:orig_category":"Vaste And Vloeibare Brandstoffen",
    "sg:phone":"+31 75 635 1695",
    "sg:postcode":"1506 GL",
    "sg:province":"Noord-Holland",
    "wof:name":"Havenhout Bv",
    "wof:placetype":"venue"
},
  "geometry": {"coordinates":[4.813923,52.453182],"type":"Point"}
}