{
  "type": "Feature",
  "properties": {
    "addr:full":"Bredewg 94 Nederweert Limburg 6031 CM",
    "addr:housenumber":"94",
    "addr:postcode":"6031 cm",
    "addr:street":"Bredewg",
    "iso:country":"NL",
    "sg:address":"Bredewg 94",
    "sg:city":"Nederweert",
    "sg:orig_category":"Adviesbureaus Bedrijfsorganisatie",
    "sg:phone":"+31 495 460 560",
    "sg:postcode":"6031 CM",
    "sg:province":"Limburg",
    "wof:name":"Dzyan",
    "wof:placetype":"venue"
},
  "geometry": {"coordinates":[5.738363,51.287151],"type":"Point"}
}