{
  "type": "Feature",
  "properties": {
    "addr:full":"Redewg 10B Ens NL. 8307 RE",
    "addr:housenumber":"10b",
    "addr:postcode":"8307",
    "addr:street":"Redewg;Nl.",
    "iso:country":"NL",
    "sg:address":"Redewg 10B",
    "sg:city":"Ens",
    "sg:orig_category":"Keukens",
    "sg:phone":"+31 527 253 454",
    "sg:postcode":"8307 RE",
    "sg:province":"NL.",
    "wof:name":"Dijk, Keukenmontagebedrijf Van",
    "wof:placetype":"venue"
},
  "geometry": {"coordinates":[5.79352,52.61742],"type":"Point"}
}