{
  "type": "Feature",
  "properties": {
    "iso:country":"NL",
    "sg:address":"Pompstr 24",
    "sg:city":"Norg",
    "sg:orig_category":"Hengelsportartikelen",
    "sg:phone":"+31 592 614 230",
    "sg:postcode":"9331 AN",
    "sg:province":"Drenthe",
    "wof:name":"Willem Emmens",
    "wof:placetype":"venue"
},
  "geometry": {"coordinates":[6.465554,53.066227],"type":"Point"}
}