{
  "type": "Feature",
  "properties": {
    "addr:full":"Hogewg 49 Voerendaal Limburg 6367 BB",
    "addr:housenumber":"49",
    "addr:postcode":"6367 bb",
    "addr:street":"Hogewg",
    "iso:country":"NL",
    "sg:address":"Hogewg 49",
    "sg:city":"Voerendaal",
    "sg:orig_category":"Postkantoren",
    "sg:phone":"+31 45 575 1290",
    "sg:postcode":"6367 BB",
    "sg:province":"Limburg",
    "sg:website":"http://www.postkantoor.nl",
    "wof:name":"Postkantoor",
    "wof:placetype":"venue"
},
  "geometry": {"coordinates":[5.931746,50.879631],"type":"Point"}
}