{
  "type": "Feature",
  "properties": {
    "iso:country":"NL",
    "sg:address":"Schansstr 9",
    "sg:city":"Nederweert",
    "sg:orig_category":"Metselwerken",
    "sg:phone":"+31 495 631 576",
    "sg:postcode":"6031 AB",
    "sg:province":"Limburg",
    "wof:name":"Eijk, A L W Van",
    "wof:placetype":"venue"
},
  "geometry": {"coordinates":[5.7682957649,51.2855758667],"type":"Point"}
}