{
  "type": "Feature",
  "properties": {
    "addr:full":"Hoogstraat 24 Harderwijk Gelderland 3841 BS",
    "addr:housenumber":"24",
    "addr:postcode":"3841 bs",
    "addr:street":"Hoogstraat;Gelderland",
    "iso:country":"NL",
    "sg:address":"Hoogstraat 24",
    "sg:city":"Harderwijk",
    "sg:orig_category":"Kappers",
    "sg:phone":"+31 341 432 319",
    "sg:postcode":"3841 BS",
    "sg:province":"Gelderland",
    "wof:name":"La Cosa",
    "wof:placetype":"venue"
},
  "geometry": {"coordinates":[5.618918,52.35075],"type":"Point"}
}