{
  "type": "Feature",
  "properties": {
    "addr:full":"Nieuwe Oosterstraat 8 Leeuwarden Provincie Friesland 8911 KN",
    "addr:housenumber":"8",
    "addr:postcode":"8911 kn",
    "addr:street":"Nieuwe Oosterstraat;Provincie Friesland",
    "iso:country":"NL",
    "sg:address":"Nieuwe Oosterstraat 8",
    "sg:city":"Leeuwarden",
    "sg:orig_category":"Kunst And Kunstenaarsbenodigdheden",
    "sg:phone":"+31 58 213 8306",
    "sg:postcode":"8911 KN",
    "sg:province":"Provincie Friesland",
    "wof:name":"Koopman Lijsten",
    "wof:placetype":"venue"
},
  "geometry": {"coordinates":[5.800461,53.200706],"type":"Point"}
}