{
  "type": "Feature",
  "properties": {
    "addr:full":"Hoogvensestr 87 Tilburg Noord-Brabant 5017 CB",
    "addr:housenumber":"87",
    "addr:postcode":"5017 cb",
    "addr:street":"Hoogvensestr",
    "iso:country":"NL",
    "sg:address":"Hoogvensestr 87",
    "sg:city":"Tilburg",
    "sg:orig_category":"Webdesign Bureaus",
    "sg:phone":"+31 13 467 4171",
    "sg:postcode":"5017 CB",
    "sg:province":"Noord-Brabant",
    "sg:website":"http://www.niqui.nl",
    "wof:name":"Apestaart",
    "wof:placetype":"venue"
},
  "geometry": {"coordinates":[5.0957012177,51.5552177429],"type":"Point"}
}