{
  "type": "Feature",
  "properties": {
    "addr:full":"Hanzewg 5 Zutphen Gelderland 7202 CG",
    "addr:housenumber":"5",
    "addr:postcode":"7202 cg",
    "addr:street":"Hanzewg;Gelderland",
    "iso:country":"NL",
    "sg:address":"Hanzewg 5",
    "sg:city":"Zutphen",
    "sg:orig_category":"Kantinebeheer",
    "sg:phone":"+31 575 595 022",
    "sg:postcode":"7202 CG",
    "sg:province":"Gelderland",
    "wof:name":"Linda'S",
    "wof:placetype":"venue"
},
  "geometry": {"coordinates":[6.2024598122,52.1561203003],"type":"Point"}
}