{
  "type": "Feature",
  "properties": {
    "iso:country":"NL",
    "sg:address":"Torenstraat 132",
    "sg:city":"'S Gravenhage",
    "sg:orig_category":"Muziekinstrumenten",
    "sg:phone":"+31 70 364 3938",
    "sg:postcode":"2513 BW",
    "sg:province":"Zuid-Holland",
    "wof:name":"Rock Palace Bv",
    "wof:placetype":"venue"
},
  "geometry": {"coordinates":[4.304928,52.078022],"type":"Point"}
}