{
  "type": "Feature",
  "properties": {
    "addr:full":"Valkenboslaan 21 'S Gravenhage Zuid-Holland 2563 CD",
    "addr:housenumber":"21",
    "addr:postcode":"2563 cd",
    "addr:street":"Valkenboslaan;' S",
    "iso:country":"NL",
    "sg:address":"Valkenboslaan 21",
    "sg:city":"'S Gravenhage",
    "sg:orig_category":"Boekhouders",
    "sg:phone":"+31 70 363 0895",
    "sg:postcode":"2563 CD",
    "sg:province":"Zuid-Holland",
    "wof:name":"V Agten & V Doeland",
    "wof:placetype":"venue"
},
  "geometry": {"coordinates":[4.274769,52.069942],"type":"Point"}
}