{
  "type": "Feature",
  "properties": {
    "addr:full":"Schoener 10 Velserbroek North Holland 1991 XC",
    "addr:housenumber":"10",
    "addr:postcode":"1991 xc",
    "addr:street":"Schoener",
    "iso:country":"NL",
    "sg:address":"Schoener 10",
    "sg:city":"Velserbroek",
    "sg:orig_category":"Marketingbureaus",
    "sg:phone":"+31 23 538 5187",
    "sg:postcode":"1991 XC",
    "sg:province":"North Holland",
    "wof:name":"Roode, De",
    "wof:placetype":"venue"
},
  "geometry": {"coordinates":[4.661605,52.42659],"type":"Point"}
}