{
  "type": "Feature",
  "properties": {
    "addr:full":"Tegelsewg 136 Venlo Limburg 5912 BL",
    "addr:housenumber":"136",
    "addr:postcode":"5912 bl",
    "iso:country":"NL",
    "sg:address":"Tegelsewg 136",
    "sg:city":"Venlo",
    "sg:classifiers":[
        {
            "category":"Retail",
            "subcategory":"Auto Repair",
            "type":"Services"
        }
    ],
    "sg:phone":"+31 77 352 0975",
    "sg:postcode":"5912 BL",
    "sg:province":"Limburg",
    "sg:tags":[
        "garage"
    ],
    "sg:website":"http://www.lutgens.nl",
    "wof:name":"Lutgens Bv",
    "wof:placetype":"venue"
},
  "geometry": {"coordinates":[6.160876,51.362133],"type":"Point"}
}