{
  "type": "Feature",
  "properties": {
    "addr:full":"Raadhuisstr 7 Lichtenvoorde Gelderland 7131 CL",
    "addr:housenumber":"7",
    "addr:postcode":"7131",
    "addr:street":"Raadhuisstr;Gelderland",
    "iso:country":"NL",
    "sg:address":"Raadhuisstr 7",
    "sg:city":"Lichtenvoorde",
    "sg:orig_category":"Postkantoren",
    "sg:phone":"+31 544 378 211",
    "sg:postcode":"7131 CL",
    "sg:province":"Gelderland",
    "sg:website":"http://www.postkantoor.nl",
    "wof:name":"Postkantoor",
    "wof:placetype":"venue"
},
  "geometry": {"coordinates":[6.5629,51.988407],"type":"Point"}
}