{
  "type": "Feature",
  "properties": {
    "addr:full":"Hertog Albrechtstraat 40B Zevenhoven Zuid-Holland 2435 XD",
    "addr:housenumber":"40b",
    "addr:postcode":"2435 xd",
    "addr:street":"Hertog Albrechtstraat",
    "iso:country":"NL",
    "sg:address":"Hertog Albrechtstraat 40B",
    "sg:city":"Zevenhoven",
    "sg:orig_category":"Goederenvervoer Over De Weg",
    "sg:phone":"+31 172 538 311",
    "sg:postcode":"2435 XD",
    "sg:province":"Zuid-Holland",
    "wof:name":"Firma J. En L.P. Van Der Meer",
    "wof:placetype":"venue"
},
  "geometry": {"coordinates":[4.780345,52.181202],"type":"Point"}
}