{
  "type": "Feature",
  "properties": {
    "addr:full":"Oudeveen 37 Veenendaal Utrecht 3905 WB",
    "addr:housenumber":"37",
    "addr:postcode":"3905 wb",
    "addr:street":"Oudeveen",
    "iso:country":"NL",
    "sg:address":"Oudeveen 37",
    "sg:city":"Veenendaal",
    "sg:orig_category":"Metaalwerken",
    "sg:phone":"+31 318 540 945",
    "sg:postcode":"3905 WB",
    "sg:province":"Utrecht",
    "wof:name":"Sjonwering",
    "wof:placetype":"venue"
},
  "geometry": {"coordinates":[5.5393,52.03302],"type":"Point"}
}