{
  "type": "Feature",
  "properties": {
    "addr:full":"Beatrixstr 10 Den Helder Noord-Holland 1781 EN",
    "addr:housenumber":"10",
    "addr:postcode":"1781 en",
    "addr:street":"Beatrixstr",
    "iso:country":"NL",
    "sg:address":"Beatrixstr 10",
    "sg:city":"Den Helder",
    "sg:orig_category":"Schoenen",
    "sg:phone":"+31 223 619 244",
    "sg:postcode":"1781 EN",
    "sg:province":"Noord-Holland",
    "wof:name":"Naturel Schoenen",
    "wof:placetype":"venue"
},
  "geometry": {"coordinates":[4.761576,52.957378],"type":"Point"}
}