{
  "type": "Feature",
  "properties": {
    "addr:full":"Oostereinde 4 Winschoten Groningen 9672 TC",
    "addr:housenumber":"4",
    "addr:postcode":"9672 tc",
    "addr:street":"Oostereinde",
    "iso:country":"NL",
    "sg:address":"Oostereinde 4",
    "sg:city":"Winschoten",
    "sg:orig_category":"Musea And Historische Gebouwen",
    "sg:phone":"+31 597 425 070",
    "sg:postcode":"9672 TC",
    "sg:province":"Groningen",
    "wof:name":"Museum Stoomgemaal Winschoten",
    "wof:placetype":"venue"
},
  "geometry": {"coordinates":[7.0699,53.15374],"type":"Point"}
}