{
  "type": "Feature",
  "properties": {
    "addr:full":"Dijkweg 134 Andijk Noord-Holland 1619 HH",
    "addr:housenumber":"134",
    "addr:postcode":"1619 hh",
    "addr:street":"Dijkweg",
    "iso:country":"NL",
    "sg:address":"Dijkweg 134",
    "sg:city":"Andijk",
    "sg:orig_category":"Bloemen And Planten Gh",
    "sg:phone":"+31 228 591 333",
    "sg:postcode":"1619 HH",
    "sg:province":"Noord-Holland",
    "wof:name":"Fa Mantel Garden",
    "wof:placetype":"venue"
},
  "geometry": {"coordinates":[5.186135,52.745903],"type":"Point"}
}