{
  "type": "Feature",
  "properties": {
    "iso:country":"NL",
    "sg:address":"Venneveld 44",
    "sg:city":"Roosendaal",
    "sg:orig_category":"Koffie, Thee And Specerijen Gh",
    "sg:phone":"+31 165 557 264",
    "sg:postcode":"4705 RR",
    "sg:province":"Noord-Brabant",
    "wof:name":"Gewurzmuller Nederland Bv",
    "wof:placetype":"venue"
},
  "geometry": {"coordinates":[4.497306,51.543953],"type":"Point"}
}