{
  "type": "Feature",
  "properties": {
    "iso:country":"NL",
    "sg:address":"Lijnbaan 11",
    "sg:city":"Heemskerk",
    "sg:orig_category":"Waterbeheer",
    "sg:phone":"+31 251 257 120",
    "sg:postcode":"1969 NB",
    "sg:province":"Noord-Holland",
    "wof:name":"Nv Pwn Waterleidingbedrijf Noord-Holland",
    "wof:placetype":"venue"
},
  "geometry": {"coordinates":[4.6542229652,52.5026130676],"type":"Point"}
}