{
  "type": "Feature",
  "properties": {
    "addr:full":"Huisterheide 17 St Nicolaasga Friesland 8521 NC",
    "addr:housenumber":"17",
    "addr:postcode":"8521 nc",
    "addr:street":"Huisterheide",
    "iso:country":"NL",
    "sg:address":"Huisterheide 17",
    "sg:city":"St Nicolaasga",
    "sg:orig_category":"Milieu",
    "sg:phone":"+31 513 434 333",
    "sg:postcode":"8521 NC",
    "sg:province":"Friesland",
    "wof:name":"Dvl",
    "wof:placetype":"venue"
},
  "geometry": {"coordinates":[5.759016037,52.935749054],"type":"Point"}
}