{
  "type": "Feature",
  "properties": {
    "addr:full":"Charloisse Hoofd 85D Rotterdam Zuid-Holland 3087 CA",
    "addr:housenumber":"85d",
    "addr:postcode":"3087 ca",
    "addr:street":"Charloisse Hoofd",
    "iso:country":"NL",
    "sg:address":"Charloisse Hoofd 85D",
    "sg:city":"Rotterdam",
    "sg:orig_category":"Onderhoudswerken",
    "sg:phone":"+31 10 476 2816",
    "sg:postcode":"3087 CA",
    "sg:province":"Zuid-Holland",
    "wof:name":"Filius, P G",
    "wof:placetype":"venue"
},
  "geometry": {"coordinates":[4.466208,51.897511],"type":"Point"}
}