{
  "type": "Feature",
  "properties": {
    "addr:full":"Oldenzaalsestraat 340 Enschede Overijssel 7523 AJ",
    "addr:housenumber":"340",
    "addr:postcode":"7523 aj",
    "addr:street":"Oldenzaalsestraat",
    "iso:country":"NL",
    "sg:address":"Oldenzaalsestraat 340",
    "sg:city":"Enschede",
    "sg:orig_category":"Fietshandelaren",
    "sg:phone":"+31 53 435 8219",
    "sg:postcode":"7523 AJ",
    "sg:province":"Overijssel",
    "wof:name":"Fietsenwinkel Ten Tusscher Bv",
    "wof:placetype":"venue"
},
  "geometry": {"coordinates":[6.904117,52.231789],"type":"Point"}
}