{
  "type": "Feature",
  "properties": {
    "addr:full":"Past Lippertspln 1 Beek Lb Limburg 6191 NZ",
    "addr:housenumber":"1",
    "addr:postcode":"lb;6191 nz",
    "iso:country":"NL",
    "sg:address":"Past Lippertspln 1",
    "sg:city":"Beek Lb",
    "sg:orig_category":"Verenigingsgebouwen",
    "sg:phone":"+31 46 437 3952",
    "sg:postcode":"6191 NZ",
    "sg:province":"Limburg",
    "wof:name":"Trefpunt, 'T",
    "wof:placetype":"venue"
},
  "geometry": {"coordinates":[170.36663799999999,-43.587711],"type":"Point"}
}