{
  "type": "Feature",
  "properties": {
    "addr:full":"Aaltje Bakstraat 8 Gouda South Holland 2801 NH",
    "addr:housenumber":"8",
    "addr:postcode":"2801 nh",
    "addr:street":"Aaltje Bakstraat",
    "iso:country":"NL",
    "sg:address":"Aaltje Bakstraat 8",
    "sg:city":"Gouda",
    "sg:classifiers":[
        {
            "category":"Fast Food",
            "type":"Food & Drink"
        }
    ],
    "sg:phone":"+31 182 524 272",
    "sg:postcode":"2801 NH",
    "sg:province":"South Holland",
    "sg:tags":[
        "afhaal",
        "restaurant"
    ],
    "wof:name":"Cafetaria-Broodjeszaak 'T Bikkertje",
    "wof:placetype":"venue"
},
  "geometry": {"coordinates":[4.706764,52.009636],"type":"Point"}
}