{
  "type": "Feature",
  "properties": {
    "iso:country":"NL",
    "sg:address":"Navoln 46",
    "sg:city":"Stadskanaal",
    "sg:orig_category":"Woninginrichting",
    "sg:phone":"+31 599 650 056",
    "sg:postcode":"9501 VJ",
    "sg:province":"Groningen",
    "wof:name":"Kwantum",
    "wof:placetype":"venue"
},
  "geometry": {"coordinates":[6.9594750404,52.984375],"type":"Point"}
}