{
  "type": "Feature",
  "properties": {
    "addr:full":"Poelkd 32A S Gravenzande South Holland 2691 ME",
    "addr:housenumber":"32a",
    "addr:postcode":"2691 me",
    "addr:street":"Poelkd;S Gravenzande",
    "iso:country":"NL",
    "sg:address":"Poelkd 32A",
    "sg:city":"S Gravenzande",
    "sg:orig_category":"Bloemen En Planten",
    "sg:phone":"+31 174 612 666",
    "sg:postcode":"2691 ME",
    "sg:province":"South Holland",
    "sg:website":"http://www.koppen.nl",
    "wof:name":"Koppen",
    "wof:placetype":"venue"
},
  "geometry": {"coordinates":[4.16946,51.994629],"type":"Point"}
}