{
  "type": "Feature",
  "properties": {
    "iso:country":"NL",
    "sg:address":"Bisschopstr 55",
    "sg:city":"Enschede",
    "sg:orig_category":"Bodemonderzoek",
    "sg:phone":"+31 53 480 7080",
    "sg:postcode":"7513 AJ",
    "sg:province":"NL.08",
    "sg:website":"http://www.benb.nl",
    "wof:name":"Borger & Burghouts Milieu-Advies Bv",
    "wof:placetype":"venue"
},
  "geometry": {"coordinates":[6.884704,52.218933],"type":"Point"}
}