{
  "type": "Feature",
  "properties": {
    "iso:country":"NL",
    "sg:address":"Zinniadal 1",
    "sg:city":"Leiden",
    "sg:orig_category":"Verzekeringen",
    "sg:phone":"+31 71 521 6187",
    "sg:postcode":"2317 JB",
    "sg:province":"Zuid-Holland",
    "wof:name":"Assurantiekantoor De Zijl",
    "wof:placetype":"venue"
},
  "geometry": {"coordinates":[4.511243,52.181992],"type":"Point"}
}