{
  "type": "Feature",
  "properties": {
    "addr:full":"Vrieseplein 12 Dordrecht Zuid-Holland 3311 NK",
    "addr:housenumber":"12",
    "addr:postcode":"3311 nk",
    "addr:street":"Vrieseplein",
    "iso:country":"NL",
    "sg:address":"Vrieseplein 12",
    "sg:city":"Dordrecht",
    "sg:orig_category":"Kansspelen",
    "sg:phone":"+31 13 613 7314",
    "sg:postcode":"3311 NK",
    "sg:province":"Zuid-Holland",
    "wof:name":"Amusementshal Toy Toy",
    "wof:placetype":"venue"
},
  "geometry": {"coordinates":[4.6711959839,51.8118591309],"type":"Point"}
}