{
  "type": "Feature",
  "properties": {
    "addr:full":"Hoornweg 17 Rotterdam Zuid-Holland 3042 BC",
    "addr:housenumber":"17",
    "addr:postcode":"3042 bc",
    "addr:street":"Hoornweg",
    "iso:country":"NL",
    "sg:address":"Hoornweg 17",
    "sg:city":"Rotterdam",
    "sg:orig_category":"Kantoorartikelen",
    "sg:phone":"+31 10 415 3434",
    "sg:postcode":"3042 BC",
    "sg:province":"Zuid-Holland",
    "wof:name":"Kantoor- En Speelgoedhandel 'De Posthoek'",
    "wof:placetype":"venue"
},
  "geometry": {"coordinates":[4.4277610779,51.9334068298],"type":"Point"}
}