{
  "type": "Feature",
  "properties": {
    "addr:full":"De Kolk 38 Surhuisterveen Friesland 9231 CX",
    "addr:housenumber":"38",
    "addr:postcode":"9231 cx",
    "addr:street":"De Kolk",
    "iso:country":"NL",
    "sg:address":"De Kolk 38",
    "sg:city":"Surhuisterveen",
    "sg:orig_category":"Warenhuizen",
    "sg:phone":"+31 512 362 611",
    "sg:postcode":"9231 CX",
    "sg:province":"Friesland",
    "wof:name":"Hema",
    "wof:placetype":"venue"
},
  "geometry": {"coordinates":[6.1668629646,53.1825370789],"type":"Point"}
}