{
  "type": "Feature",
  "properties": {
    "addr:full":"Druivenstr 30 Naaldwyk South Holland 2671 SK",
    "addr:housenumber":"30",
    "addr:street":"Druivenstr;2671",
    "iso:country":"NL",
    "sg:address":"Druivenstr 30",
    "sg:city":"Naaldwyk",
    "sg:orig_category":"Kinderopvang",
    "sg:phone":"+31 174 623 064",
    "sg:postcode":"2671 SK",
    "sg:province":"South Holland",
    "wof:name":"Do Re Mi Kindercentrum",
    "wof:placetype":"venue"
},
  "geometry": {"coordinates":[4.205249,51.991398],"type":"Point"}
}