{
  "type": "Feature",
  "properties": {
    "addr:full":"F A Molynln 172 Nunspeet Gelderland 8071 AK",
    "addr:housenumber":"172",
    "addr:postcode":"8071 ak",
    "addr:street":"F;Gelderland",
    "iso:country":"NL",
    "sg:address":"F A Molynln 172",
    "sg:city":"Nunspeet",
    "sg:orig_category":"Verzekeringen - Verzekeringskantoren",
    "sg:phone":"+31 341 263 016",
    "sg:postcode":"8071 AK",
    "sg:province":"Gelderland",
    "wof:name":"Ann",
    "wof:placetype":"venue"
},
  "geometry": {"coordinates":[5.772205,52.374981],"type":"Point"}
}