{
  "type": "Feature",
  "properties": {
    "addr:full":"Zalmwater 91 Barendrecht Zuid-Holland 2993 DX",
    "addr:housenumber":"91",
    "addr:postcode":"2993 dx",
    "addr:street":"Zalmwater",
    "iso:country":"NL",
    "sg:address":"Zalmwater 91",
    "sg:city":"Barendrecht",
    "sg:orig_category":"Plafonds",
    "sg:phone":"+31 180 610 314",
    "sg:postcode":"2993 DX",
    "sg:province":"Zuid-Holland",
    "wof:name":"Kelsys",
    "wof:placetype":"venue"
},
  "geometry": {"coordinates":[4.505521,51.845806],"type":"Point"}
}