{
  "type": "Feature",
  "properties": {
    "addr:full":"Kleine Pelsterstraat 5 Groningen Groningen 9711 KN",
    "addr:housenumber":"5",
    "addr:postcode":"9711 kn",
    "addr:street":"Kleine Pelsterstraat",
    "iso:country":"NL",
    "sg:address":"Kleine Pelsterstraat 5",
    "sg:city":"Groningen",
    "sg:orig_category":"Organisaties And Verenigingen",
    "sg:phone":"+31 50 311 4800",
    "sg:postcode":"9711 KN",
    "sg:province":"Groningen",
    "wof:name":"Studentenvereniging Cleopatra",
    "wof:placetype":"venue"
},
  "geometry": {"coordinates":[6.5675439835,53.2158737183],"type":"Point"}
}