{
  "type": "Feature",
  "properties": {
    "addr:full":"Mr. P.J. Troelstralaan 251 Assen Drenthe 9406 BA",
    "addr:housenumber":"251",
    "addr:postcode":"9406 ba",
    "addr:street":"Mr. P.J. Troelstralaan",
    "iso:country":"NL",
    "sg:address":"Mr. P.J. Troelstralaan 251",
    "sg:city":"Assen",
    "sg:classifiers":[
        {
            "category":"Communications",
            "subcategory":"Television Station",
            "type":"Services"
        }
    ],
    "sg:phone":"+31 592 398 150",
    "sg:postcode":"9406 BA",
    "sg:province":"Drenthe",
    "sg:tags":[
        "video",
        "audio",
        "verhuur"
    ],
    "wof:name":"Videotheek Videosound",
    "wof:placetype":"venue"
},
  "geometry": {"coordinates":[6.553337,52.997948],"type":"Point"}
}