{
  "type": "Feature",
  "properties": {
    "iso:country":"NL",
    "sg:address":"Haarlemmerstr 142",
    "sg:city":"Amsterdam",
    "sg:orig_category":"Kappers",
    "sg:phone":"+31 20 620 6063",
    "sg:postcode":"1013 EZ",
    "sg:province":"Noord-Holland",
    "wof:name":"Manous",
    "wof:placetype":"venue"
},
  "geometry": {"coordinates":[4.889993,52.38129],"type":"Point"}
}