{
  "type": "Feature",
  "properties": {
    "addr:full":"Delflandplein 1 Amsterdam North Holland 1062 HP",
    "addr:housenumber":"1",
    "addr:postcode":"1062 hp",
    "addr:street":"Delflandplein",
    "iso:country":"NL",
    "sg:address":"Delflandplein 1",
    "sg:city":"Amsterdam",
    "sg:orig_category":"Architecten",
    "sg:phone":"+31 20 615 3711",
    "sg:postcode":"1062 HP",
    "sg:province":"North Holland",
    "wof:name":"Ingenieursgroep Van Rossum",
    "wof:placetype":"venue"
},
  "geometry": {"coordinates":[4.840935,52.349537],"type":"Point"}
}