{
  "type": "Feature",
  "properties": {
    "iso:country":"NL",
    "sg:address":"Driegaardsestr 2A",
    "sg:city":"Huissen",
    "sg:orig_category":"Verzekeringen - Verzekeringskantoren",
    "sg:phone":"+31 26 325 1178",
    "sg:postcode":"6851 GP",
    "sg:province":"Gelderland",
    "wof:name":"Diepenbroek",
    "wof:placetype":"venue"
},
  "geometry": {"coordinates":[5.929943,51.929585],"type":"Point"}
}