{
  "type": "Feature",
  "properties": {
    "iso:country":"NL",
    "sg:address":"Burchtstraat 4",
    "sg:city":"Oostburg",
    "sg:classifiers":[
        {
            "category":"Retail",
            "subcategory":"Photofinishing",
            "type":"Services"
        }
    ],
    "sg:phone":"+31 117 452 867",
    "sg:postcode":"4501 BJ",
    "sg:province":"Zeeland",
    "sg:tags":[
        "foto",
        "film"
    ],
    "wof:name":"Combi De Milliano",
    "wof:placetype":"venue"
},
  "geometry": {"coordinates":[3.487707,51.32674],"type":"Point"}
}