{
  "type": "Feature",
  "properties": {
    "addr:full":"Dopplerdomein 62D Maastricht Limburg 6229 GP",
    "addr:housenumber":"62d",
    "addr:postcode":"6229 gp",
    "addr:street":"Dopplerdomein",
    "iso:country":"NL",
    "sg:address":"Dopplerdomein 62D",
    "sg:city":"Maastricht",
    "sg:orig_category":"Fotoreportages",
    "sg:phone":"+31 43 367 0045",
    "sg:postcode":"6229 GP",
    "sg:province":"Limburg",
    "wof:name":"Alf Mertens",
    "wof:placetype":"venue"
},
  "geometry": {"coordinates":[5.708058,50.836433],"type":"Point"}
}