{
  "type": "Feature",
  "properties": {
    "addr:full":"Rederijklaan 36 Mierlo Noord-Brabant 5731 PV",
    "addr:housenumber":"36",
    "addr:postcode":"5731 pv",
    "addr:street":"Rederijklaan",
    "iso:country":"NL",
    "sg:address":"Rederijklaan 36",
    "sg:city":"Mierlo",
    "sg:orig_category":"Adviesbureaus Bedrijfsorganisatie",
    "sg:phone":"+31 40 246 3020",
    "sg:postcode":"5731 PV",
    "sg:province":"Noord-Brabant",
    "wof:name":"Kerkhof Bv, W F W Van De",
    "wof:placetype":"venue"
},
  "geometry": {"coordinates":[5.584327,51.430115],"type":"Point"}
}