{
  "type": "Feature",
  "properties": {
    "addr:full":"Nautilusstraat 163 Tilburg Noord-Brabant 5015 AN",
    "addr:housenumber":"163",
    "addr:postcode":"5015 an",
    "addr:street":"Nautilusstraat",
    "iso:country":"NL",
    "sg:address":"Nautilusstraat 163",
    "sg:city":"Tilburg",
    "sg:orig_category":"Voeding, Dranken And Tabak Gh",
    "sg:phone":"+31 13 549 0290",
    "sg:postcode":"5015 AN",
    "sg:province":"Noord-Brabant",
    "wof:name":"Easy Bakprodukten Bv",
    "wof:placetype":"venue"
},
  "geometry": {"coordinates":[5.109846,51.565437],"type":"Point"}
}