{
  "type": "Feature",
  "properties": {
    "addr:full":"Vinkenstraat 99 Amsterdam Noord-Holland 1013 JN",
    "addr:housenumber":"99",
    "addr:postcode":"1013 jn",
    "addr:street":"Vinkenstraat",
    "iso:country":"NL",
    "sg:address":"Vinkenstraat 99",
    "sg:city":"Amsterdam",
    "sg:orig_category":"Loodgieterswerk, Verwarming And Sanitaire Installaties",
    "sg:phone":"+31 20 639 2007",
    "sg:postcode":"1013 JN",
    "sg:province":"Noord-Holland",
    "wof:name":"B. Beekman",
    "wof:placetype":"venue"
},
  "geometry": {"coordinates":[4.88572,52.382755],"type":"Point"}
}