{
  "type": "Feature",
  "properties": {
    "iso:country":"NL",
    "sg:address":"Zwaanhoefstr 4-6A",
    "sg:city":"Roosendaal",
    "sg:orig_category":"Koeriersdiensten",
    "sg:phone":"+31 165 378 288",
    "sg:postcode":"4702 LC",
    "sg:province":"North Brabant",
    "sg:website":"http://www.2xt.nl",
    "wof:name":"2 X T",
    "wof:placetype":"venue"
},
  "geometry": {"coordinates":[4.482208,51.545071],"type":"Point"}
}