{
  "type": "Feature",
  "properties": {
    "addr:full":"Akerstraat 82 Heerlen Limburg 6411 HC",
    "addr:housenumber":"82",
    "addr:postcode":"6411 hc",
    "addr:street":"Akerstraat",
    "iso:country":"NL",
    "sg:address":"Akerstraat 82",
    "sg:city":"Heerlen",
    "sg:orig_category":"Muziekinstrumenten",
    "sg:phone":"+31 45 571 3751",
    "sg:postcode":"6411 HC",
    "sg:province":"Limburg",
    "wof:name":"J. Somers En Zoon",
    "wof:placetype":"venue"
},
  "geometry": {"coordinates":[5.981899,50.884377],"type":"Point"}
}