{
  "type": "Feature",
  "properties": {
    "addr:full":"Vonderweg 9 Beek En Donk Noord-Brabant 5741 TE",
    "addr:housenumber":"9",
    "addr:postcode":"5741 te",
    "addr:street":"Vonderweg",
    "iso:country":"NL",
    "sg:address":"Vonderweg 9",
    "sg:city":"Beek En Donk",
    "sg:orig_category":"Huizensloop And Bouwrijp Maken",
    "sg:phone":"+31 492 461 272",
    "sg:postcode":"5741 TE",
    "sg:province":"Noord-Brabant",
    "wof:name":"Hans Maas Cultuurtechnische Werken Grondwerken",
    "wof:placetype":"venue"
},
  "geometry": {"coordinates":[5.629407,51.546646],"type":"Point"}
}