{
  "type": "Feature",
  "properties": {
    "addr:full":"Irenelaan 3 Kaag South Holland 2159 LL",
    "addr:housenumber":"3",
    "addr:postcode":"2159 ll",
    "addr:street":"Irenelaan",
    "iso:country":"NL",
    "sg:address":"Irenelaan 3",
    "sg:city":"Kaag",
    "sg:orig_category":"Kampeerterreinen",
    "sg:phone":"+31 252 544 266",
    "sg:postcode":"2159 LL",
    "sg:province":"South Holland",
    "wof:name":"Camping Het Kagereiland",
    "wof:placetype":"venue"
},
  "geometry": {"coordinates":[4.5588188171,52.2125892639],"type":"Point"}
}