{
  "type": "Feature",
  "properties": {
    "addr:full":"Jan Amentstraat 67 Roermond Limburg 6041 BD",
    "addr:housenumber":"67",
    "addr:postcode":"6041 bd",
    "addr:street":"Jan Amentstraat",
    "iso:country":"NL",
    "sg:address":"Jan Amentstraat 67",
    "sg:city":"Roermond",
    "sg:orig_category":"Goederenvervoer Over De Weg",
    "sg:phone":"+31 475 335 913",
    "sg:postcode":"6041 BD",
    "sg:province":"Limburg",
    "wof:name":"Transportbedrijf Mertens-Simons Bv",
    "wof:placetype":"venue"
},
  "geometry": {"coordinates":[6.002769,51.2094],"type":"Point"}
}