{
  "type": "Feature",
  "properties": {
    "iso:country":"NL",
    "sg:address":"Oranjesingel 8",
    "sg:city":"Nijmegen",
    "sg:orig_category":"Diverse Grafische Activiteiten",
    "sg:phone":"+31 24 360 3558",
    "sg:postcode":"6511 NT",
    "sg:province":"Gelderland",
    "wof:name":"Fontline Vertalingen En Grafische Producties",
    "wof:placetype":"venue"
},
  "geometry": {"coordinates":[5.862974,51.842285],"type":"Point"}
}