{
  "type": "Feature",
  "properties": {
    "addr:full":"Bovenstraat 35 Maastricht Limburg 6223 AC",
    "addr:housenumber":"35",
    "addr:postcode":"6223 ac",
    "addr:street":"Bovenstraat",
    "iso:country":"NL",
    "sg:address":"Bovenstraat 35",
    "sg:city":"Maastricht",
    "sg:orig_category":"Architecten",
    "sg:phone":"+31 43 363 5032",
    "sg:postcode":"6223 AC",
    "sg:province":"Limburg",
    "wof:name":"A.H.M. Konig Architect Avb Bna",
    "wof:placetype":"venue"
},
  "geometry": {"coordinates":[5.690734,50.873543],"type":"Point"}
}