{
  "type": "Feature",
  "properties": {
    "addr:full":"Torenstr 37 Winschoten Groningen 9671 ED",
    "addr:housenumber":"37",
    "addr:postcode":"9671 ed",
    "addr:street":"Torenstr",
    "iso:country":"NL",
    "sg:address":"Torenstr 37",
    "sg:city":"Winschoten",
    "sg:orig_category":"Bloemen En Planten",
    "sg:phone":"+31 597 413 162",
    "sg:postcode":"9671 ED",
    "sg:province":"Groningen",
    "wof:name":"Jager, Willem",
    "wof:placetype":"venue"
},
  "geometry": {"coordinates":[7.038691,53.141182],"type":"Point"}
}