{
  "type": "Feature",
  "properties": {
    "addr:full":"Stationsstraat 26 Sittard Limburg 6131 AZ",
    "addr:housenumber":"26",
    "addr:postcode":"6131 az",
    "addr:street":"Stationsstraat",
    "iso:country":"NL",
    "sg:address":"Stationsstraat 26",
    "sg:city":"Sittard",
    "sg:orig_category":"Werving And Selectie Van Tijdelijk Personeel And Uitzendkantoren",
    "sg:phone":"+31 46 420 6380",
    "sg:postcode":"6131 AZ",
    "sg:province":"Limburg",
    "wof:name":"Bouwflex",
    "wof:placetype":"venue"
},
  "geometry": {"coordinates":[5.8599348068,51.0016708374],"type":"Point"}
}