{
  "type": "Feature",
  "properties": {
    "addr:full":"Leeuwenhoekstr 61 Amsterdam Noord-Holland 1091 RX",
    "addr:housenumber":"61",
    "addr:postcode":"1091 rx",
    "addr:street":"Leeuwenhoekstr",
    "iso:country":"NL",
    "sg:address":"Leeuwenhoekstr 61",
    "sg:city":"Amsterdam",
    "sg:orig_category":"Vertaalbureaus",
    "sg:phone":"+31 20 663 8032",
    "sg:postcode":"1091 RX",
    "sg:province":"Noord-Holland",
    "wof:name":"Mook & Jansen",
    "wof:placetype":"venue"
},
  "geometry": {"coordinates":[4.908343,52.357773],"type":"Point"}
}