{
  "type": "Feature",
  "properties": {
    "addr:full":"Maricowg 39 Den Burg Noord-Holland 1791 MD",
    "addr:housenumber":"39",
    "addr:postcode":"1791",
    "addr:street":"Maricowg",
    "iso:country":"NL",
    "sg:address":"Maricowg 39",
    "sg:city":"Den Burg",
    "sg:orig_category":"Schilders",
    "sg:phone":"+31 222 312 138",
    "sg:postcode":"1791 MD",
    "sg:province":"Noord-Holland",
    "wof:name":"Schilders Texel Bv, Verenigde",
    "wof:placetype":"venue"
},
  "geometry": {"coordinates":[-94.071686,34.232082],"type":"Point"}
}