{
  "type": "Feature",
  "properties": {
    "addr:full":"Forsythiastr 9 Berkel En Rodenrys Zuid-Holland 2651 TC",
    "addr:housenumber":"9",
    "addr:postcode":"2651 tc",
    "addr:street":"Forsythiastr;Berkel",
    "iso:country":"NL",
    "sg:address":"Forsythiastr 9",
    "sg:city":"Berkel En Rodenrys",
    "sg:orig_category":"Onderhoudswerken",
    "sg:phone":"+31 10 511 0395",
    "sg:postcode":"2651 TC",
    "sg:province":"Zuid-Holland",
    "wof:name":"Modern Times",
    "wof:placetype":"venue"
},
  "geometry": {"coordinates":[4.486355,52.001411],"type":"Point"}
}