{
  "type": "Feature",
  "properties": {
    "addr:full":"Nieuwe Crooswijkseweg 42 Rotterdam South Holland 3034 PR",
    "addr:housenumber":"42",
    "addr:postcode":"3034 pr",
    "addr:street":"Nieuwe Crooswijkseweg",
    "iso:country":"NL",
    "sg:address":"Nieuwe Crooswijkseweg 42",
    "sg:city":"Rotterdam",
    "sg:orig_category":"Wasserettes And Stomerijen",
    "sg:phone":"+31 10 412 5395",
    "sg:postcode":"3034 PR",
    "sg:province":"South Holland",
    "wof:name":"Van Der Wal Vof",
    "wof:placetype":"venue"
},
  "geometry": {"coordinates":[4.4975500107,51.9350738525],"type":"Point"}
}