{
  "type": "Feature",
  "properties": {
    "addr:full":"Gentiaanstr 752 Apeldoorn Gelderland 7322 CW",
    "addr:housenumber":"752",
    "addr:postcode":"7322 cw",
    "addr:street":"Gelderland",
    "iso:country":"NL",
    "sg:address":"Gentiaanstr 752",
    "sg:city":"Apeldoorn",
    "sg:orig_category":"Tehuizen",
    "sg:phone":"+31 55 368 0440",
    "sg:postcode":"7322 CW",
    "sg:province":"Gelderland",
    "wof:name":"Philadelphia, Zorg Apeldoorn Noord",
    "wof:placetype":"venue"
},
  "geometry": {"coordinates":[5.98024,52.228531],"type":"Point"}
}