{
  "type": "Feature",
  "properties": {
    "addr:full":"Leunestr 18 St Oedenrode North Brabant 5492 TS",
    "addr:housenumber":"18",
    "addr:postcode":"5492 ts",
    "addr:street":"Leunestr",
    "iso:country":"NL",
    "sg:address":"Leunestr 18",
    "sg:city":"St Oedenrode",
    "sg:classifiers":[
        {
            "category":"Food & Beverages",
            "subcategory":"Fruits & Vegetables",
            "type":"Retail Goods"
        }
    ],
    "sg:phone":"+31 413 473 088",
    "sg:postcode":"5492 TS",
    "sg:province":"North Brabant",
    "sg:tags":[
        "en",
        "groenten"
    ],
    "wof:name":"Elsen Vof, Van Den",
    "wof:placetype":"venue"
},
  "geometry": {"coordinates":[5.448725,51.553848],"type":"Point"}
}