{
  "type": "Feature",
  "properties": {
    "addr:full":"Wendtsteinweg 28 Marum Groningen 9363 AN",
    "addr:housenumber":"28",
    "addr:postcode":"9363 an",
    "addr:street":"Wendtsteinweg",
    "iso:country":"NL",
    "sg:address":"Wendtsteinweg 28",
    "sg:city":"Marum",
    "sg:orig_category":"Fotostudio'S And Fotografen",
    "sg:phone":"+31 594 644 843",
    "sg:postcode":"9363 AN",
    "sg:province":"Groningen",
    "wof:name":"Foto Boezerooy",
    "wof:placetype":"venue"
},
  "geometry": {"coordinates":[6.272705,53.146114],"type":"Point"}
}