{
  "type": "Feature",
  "properties": {
    "iso:country":"NL",
    "sg:address":"Vd Kunstr 112",
    "sg:city":"S Gravenhage",
    "sg:orig_category":"Metaalgroothandel",
    "sg:phone":"+31 70 389 3555",
    "sg:postcode":"2521 AW",
    "sg:province":"South Holland",
    "wof:name":"Kokkelink Bv",
    "wof:placetype":"venue"
},
  "geometry": {"coordinates":[4.32071,52.062988],"type":"Point"}
}