{
  "type": "Feature",
  "properties": {
    "addr:full":"Binnenwg 138 Heemstede Noord-Holland 2101 JP",
    "addr:housenumber":"138",
    "addr:postcode":"2101 jp",
    "iso:country":"NL",
    "sg:address":"Binnenwg 138",
    "sg:city":"Heemstede",
    "sg:orig_category":"Boeken En Tijdschriften",
    "sg:phone":"+31 23 528 2472",
    "sg:postcode":"2101 JP",
    "sg:province":"Noord-Holland",
    "wof:name":"Blokker, Boekhandel",
    "wof:placetype":"venue"
},
  "geometry": {"coordinates":[4.621426,52.353588],"type":"Point"}
}