{
  "type": "Feature",
  "properties": {
    "addr:full":"Aquamaryn 12 Mydrecht Utrecht 3641 XG",
    "addr:housenumber":"12",
    "addr:postcode":"3641 xg",
    "addr:street":"Aquamaryn",
    "iso:country":"NL",
    "sg:address":"Aquamaryn 12",
    "sg:city":"Mydrecht",
    "sg:orig_category":"Elektrotechnische Installatiebureaus",
    "sg:phone":"+31 297 273 106",
    "sg:postcode":"3641 XG",
    "sg:province":"Utrecht",
    "wof:name":"Bruyn, H L De",
    "wof:placetype":"venue"
},
  "geometry": {"coordinates":[4.86178,52.20578],"type":"Point"}
}