{
  "type": "Feature",
  "properties": {
    "iso:country":"NL",
    "sg:address":"Doelwg 35",
    "sg:city":"Goedereede",
    "sg:orig_category":"Vakantieverblijven",
    "sg:phone":"+31 187 491 516",
    "sg:postcode":"3252 AJ",
    "sg:province":"South Holland",
    "wof:name":"Stroo",
    "wof:placetype":"venue"
},
  "geometry": {"coordinates":[3.977522,51.81926],"type":"Point"}
}