{
  "type": "Feature",
  "properties": {
    "addr:full":"Sporthal Oosterbliek Gorinchem Zuid-Holland 4207 NC",
    "addr:housenumber":"4207",
    "addr:postcode":"nc",
    "iso:country":"NL",
    "sg:address":"Sporthal Oosterbliek",
    "sg:city":"Gorinchem",
    "sg:orig_category":"Balletscholen",
    "sg:phone":"+31 183 625 008",
    "sg:postcode":"4207 NC",
    "sg:province":"Zuid-Holland",
    "wof:name":"Papillon, Balletschool",
    "wof:placetype":"venue"
},
  "geometry": {"coordinates":[4.969185,51.830631],"type":"Point"}
}