{
  "type": "Feature",
  "properties": {
    "addr:full":"Sint Odgerusstraat 3 Roermond Limburg 6045 ET",
    "addr:housenumber":"3",
    "addr:postcode":"6045 et",
    "addr:street":"Odgerusstraat",
    "iso:country":"NL",
    "sg:address":"Sint Odgerusstraat 3",
    "sg:city":"Roermond",
    "sg:orig_category":"Fitnesscentra",
    "sg:phone":"+31 475 375 185",
    "sg:postcode":"6045 ET",
    "sg:province":"Limburg",
    "wof:name":"Fysio Fitnesscentrum Fincken",
    "wof:placetype":"venue"
},
  "geometry": {"coordinates":[6.003065,51.173088],"type":"Point"}
}