{
  "type": "Feature",
  "properties": {
    "addr:full":"Eindhovenseweg 12 Boxtel Noord-Brabant 5281 RA",
    "addr:housenumber":"12",
    "addr:postcode":"5281 ra",
    "addr:street":"Eindhovenseweg",
    "iso:country":"NL",
    "sg:address":"Eindhovenseweg 12",
    "sg:city":"Boxtel",
    "sg:orig_category":"Diverse Consumentenartikelen Gh",
    "sg:phone":"+31 411 688 287",
    "sg:postcode":"5281 RA",
    "sg:province":"Noord-Brabant",
    "wof:name":"Joris Trading Bv",
    "wof:placetype":"venue"
},
  "geometry": {"coordinates":[5.333371,51.582596],"type":"Point"}
}