{
  "type": "Feature",
  "properties": {
    "addr:full":"H W Iordensweg 57 Twello Gelderland 7391 KD",
    "addr:housenumber":"57",
    "addr:postcode":"7391 kd",
    "addr:street":"H W Iordensweg;Gelderland",
    "iso:country":"NL",
    "sg:address":"H W Iordensweg 57",
    "sg:city":"Twello",
    "sg:orig_category":"Huishoudapparatuur, Televisies And Radio'S",
    "sg:phone":"+31 571 271 507",
    "sg:postcode":"7391 KD",
    "sg:province":"Gelderland",
    "wof:name":"Debora",
    "wof:placetype":"venue"
},
  "geometry": {"coordinates":[6.110571,52.23016],"type":"Point"}
}