{
  "type": "Feature",
  "properties": {
    "addr:full":"Energiestraat 8 Naarden Noord-Holland 1411 AT",
    "addr:housenumber":"8",
    "addr:postcode":"1411",
    "addr:street":"Energiestraat",
    "iso:country":"NL",
    "sg:address":"Energiestraat 8",
    "sg:city":"Naarden",
    "sg:orig_category":"Diverse Bedrijfsinstallaties Gh",
    "sg:phone":"+31 35 694 7306",
    "sg:postcode":"1411 AT",
    "sg:province":"Noord-Holland",
    "wof:name":"Condor Technology Limited",
    "wof:placetype":"venue"
},
  "geometry": {"coordinates":[5.15417,52.300632],"type":"Point"}
}