{
  "type": "Feature",
  "properties": {
    "addr:full":"Meerten Verhoffstraat 16 Breda Noord-Brabant 4811 AS",
    "addr:housenumber":"16",
    "addr:postcode":"4811 as",
    "addr:street":"Meerten Verhoffstraat",
    "iso:country":"NL",
    "sg:address":"Meerten Verhoffstraat 16",
    "sg:city":"Breda",
    "sg:orig_category":"Overheidsdiensten",
    "sg:phone":"+31 76 528 2611",
    "sg:postcode":"4811 AS",
    "sg:province":"Noord-Brabant",
    "wof:name":"Cadans",
    "wof:placetype":"venue"
},
  "geometry": {"coordinates":[4.7813711166,51.5938491821],"type":"Point"}
}