{
  "type": "Feature",
  "properties": {
    "addr:full":"Museumplein 1 Drachten Friesland 9203 DD",
    "addr:housenumber":"1",
    "addr:postcode":"9203 dd",
    "addr:street":"Museumplein",
    "iso:country":"NL",
    "sg:address":"Museumplein 1",
    "sg:city":"Drachten",
    "sg:orig_category":"Bibliotheken And Openbare Archieven",
    "sg:phone":"+31 512 512 680",
    "sg:postcode":"9203 DD",
    "sg:province":"Friesland",
    "wof:name":"Openbare Bibliotheek Smallingerland",
    "wof:placetype":"venue"
},
  "geometry": {"coordinates":[6.098297,53.104599],"type":"Point"}
}