{
  "type": "Feature",
  "properties": {
    "addr:full":"Hoofdstr 16 Kerkrade Limburg 6461 CP",
    "addr:housenumber":"16",
    "addr:postcode":"6461 cp",
    "addr:street":"Hoofdstr",
    "iso:country":"NL",
    "sg:address":"Hoofdstr 16",
    "sg:city":"Kerkrade",
    "sg:orig_category":"Postkantoren",
    "sg:phone":"+31 45 535 7777",
    "sg:postcode":"6461 CP",
    "sg:province":"Limburg",
    "sg:website":"http://www.postkantoor.nl",
    "wof:name":"Postkantoor",
    "wof:placetype":"venue"
},
  "geometry": {"coordinates":[6.065293,50.864986],"type":"Point"}
}