{
  "type": "Feature",
  "properties": {
    "addr:full":"Tiendweg 8 Naaldwijk Zuid-Holland 2671 SB",
    "addr:housenumber":"8",
    "addr:postcode":"2671 sb",
    "addr:street":"Tiendweg",
    "iso:country":"NL",
    "sg:address":"Tiendweg 8",
    "sg:city":"Naaldwijk",
    "sg:classifiers":[
        {
            "category":"Professional",
            "subcategory":"Accounting & Tax Preparation",
            "type":"Services"
        }
    ],
    "sg:phone":"+31 174 640 139",
    "sg:postcode":"2671 SB",
    "sg:province":"Zuid-Holland",
    "sg:tags":[
        "accountant"
    ],
    "wof:name":"Lodder & Co Registeraccountant Belastingadviseurs",
    "wof:placetype":"venue"
},
  "geometry": {"coordinates":[4.220108,51.990734],"type":"Point"}
}