{
  "type": "Feature",
  "properties": {
    "iso:country":"NL",
    "sg:address":"Hooghiemstraplein 116",
    "sg:city":"Utrecht",
    "sg:orig_category":"Farmaceutische Producten Gh",
    "sg:phone":"+31 30 276 9190",
    "sg:postcode":"3514 AZ",
    "sg:province":"Utrecht",
    "wof:name":"Machnet Bv",
    "wof:placetype":"venue"
},
  "geometry": {"coordinates":[5.125106,52.098331],"type":"Point"}
}