{
  "type": "Feature",
  "properties": {
    "addr:full":"Gasthuissingel 4 Haarlem Noord-Holland 2012 DN",
    "addr:housenumber":"4",
    "addr:postcode":"2012 dn",
    "addr:street":"Gasthuissingel",
    "iso:country":"NL",
    "sg:address":"Gasthuissingel 4",
    "sg:city":"Haarlem",
    "sg:orig_category":"Kappers",
    "sg:phone":"+31 23 531 7393",
    "sg:postcode":"2012 DN",
    "sg:province":"Noord-Holland",
    "wof:name":"Dameskapsalon Frits",
    "wof:placetype":"venue"
},
  "geometry": {"coordinates":[4.6311631203,52.3757667542],"type":"Point"}
}