{
  "type": "Feature",
  "properties": {
    "addr:full":"K Doormanln 42 Bussum Noord-Holland 1403 TN",
    "addr:housenumber":"42",
    "addr:postcode":"1403",
    "addr:street":"Doormanln",
    "iso:country":"NL",
    "sg:address":"K Doormanln 42",
    "sg:city":"Bussum",
    "sg:orig_category":"Kappers",
    "sg:phone":"+31 35 693 4000",
    "sg:postcode":"1403 TN",
    "sg:province":"Noord-Holland",
    "wof:name":"Free Style Hairstudio",
    "wof:placetype":"venue"
},
  "geometry": {"coordinates":[5.1776690483,52.2664031982],"type":"Point"}
}