{
  "type": "Feature",
  "properties": {
    "iso:country":"NL",
    "sg:address":"C V Eyckln 18",
    "sg:city":"Pynacker",
    "sg:orig_category":"Kinderopvang",
    "sg:phone":"+31 15 369 2081",
    "sg:postcode":"2642 BM",
    "sg:province":"Zuid-Holland",
    "wof:name":"Zevensprong, De",
    "wof:placetype":"venue"
},
  "geometry": {"coordinates":[4.45025,52.008888],"type":"Point"}
}