{
  "type": "Feature",
  "properties": {
    "iso:country":"NL",
    "sg:address":"Koepoortswg 94",
    "sg:city":"Hoorn Nh",
    "sg:orig_category":"Voegwerken",
    "sg:phone":"+31 229 214 586",
    "sg:postcode":"1624 AH",
    "sg:province":"Noord-Holland",
    "wof:name":"Greeuw, Voegbedrijf Ton De",
    "wof:placetype":"venue"
},
  "geometry": {"coordinates":[5.057069,52.648083],"type":"Point"}
}