{
  "type": "Feature",
  "properties": {
    "addr:full":"Dorpsstr 2 Wagenberg Noord-Brabant 4845 CE",
    "addr:housenumber":"2",
    "addr:postcode":"4845 ce",
    "addr:street":"Dorpsstr",
    "iso:country":"NL",
    "sg:address":"Dorpsstr 2",
    "sg:city":"Wagenberg",
    "sg:orig_category":"Modelbouw",
    "sg:phone":"+31 76 593 3895",
    "sg:postcode":"4845 CE",
    "sg:province":"Noord-Brabant",
    "wof:name":"Spoorbrug, De",
    "wof:placetype":"venue"
},
  "geometry": {"coordinates":[4.739616,51.660782],"type":"Point"}
}