{
  "type": "Feature",
  "properties": {
    "addr:full":"Stationsplein 8 Apeldoorn Gelderland 7311 NZ",
    "addr:housenumber":"8",
    "addr:postcode":"7311 nz",
    "addr:street":"Stationsplein;Gelderland",
    "iso:country":"NL",
    "sg:address":"Stationsplein 8",
    "sg:city":"Apeldoorn",
    "sg:orig_category":"Bloemen And Planten",
    "sg:phone":"+31 55 521 2927",
    "sg:postcode":"7311 NZ",
    "sg:province":"Gelderland",
    "wof:name":"Bloemenboetiek 'T Station",
    "wof:placetype":"venue"
},
  "geometry": {"coordinates":[5.96677,52.210461],"type":"Point"}
}