{
  "type": "Feature",
  "properties": {
    "addr:full":"L Zelke 16 Vlissingen Zeeland 4381 GA",
    "addr:housenumber":"16",
    "addr:postcode":"4381 ga",
    "addr:street":"L Zelke",
    "iso:country":"NL",
    "sg:address":"L Zelke 16",
    "sg:city":"Vlissingen",
    "sg:orig_category":"Warenhuizen",
    "sg:phone":"+31 118 416 130",
    "sg:postcode":"4381 GA",
    "sg:province":"Zeeland",
    "wof:name":"Hema",
    "wof:placetype":"venue"
},
  "geometry": {"coordinates":[3.5738561153,51.443321228],"type":"Point"}
}