{
  "type": "Feature",
  "properties": {
    "addr:full":"Julianapark 42 Tilburg Noord-Brabant 5046 GB",
    "addr:housenumber":"42",
    "addr:postcode":"5046 gb",
    "addr:street":"Julianapark",
    "iso:country":"NL",
    "sg:address":"Julianapark 42",
    "sg:city":"Tilburg",
    "sg:orig_category":"Fietshandelaren",
    "sg:phone":"+31 13 542 3675",
    "sg:postcode":"5046 GB",
    "sg:province":"Noord-Brabant",
    "wof:name":"W.J. De Jong",
    "wof:placetype":"venue"
},
  "geometry": {"coordinates":[5.07823,51.57272],"type":"Point"}
}