{
  "type": "Feature",
  "properties": {
    "addr:full":"Meidoornstraat 6 Bergambacht Zuid-Holland 2861 VH",
    "addr:housenumber":"6",
    "addr:postcode":"2861 vh",
    "addr:street":"Meidoornstraat",
    "iso:country":"NL",
    "sg:address":"Meidoornstraat 6",
    "sg:city":"Bergambacht",
    "sg:orig_category":"Goederenvervoer Over De Weg",
    "sg:phone":"+31 182 354 292",
    "sg:postcode":"2861 VH",
    "sg:province":"Zuid-Holland",
    "wof:name":"J.P. Heikoop",
    "wof:placetype":"venue"
},
  "geometry": {"coordinates":[4.78757,51.933411],"type":"Point"}
}