{
  "type": "Feature",
  "properties": {
    "addr:full":"Bernadotteln 5 Doorwerth Gelderland 6865 BK",
    "addr:housenumber":"5",
    "addr:postcode":"6865 bk",
    "addr:street":"Bernadotteln;Gelderland",
    "iso:country":"NL",
    "sg:address":"Bernadotteln 5",
    "sg:city":"Doorwerth",
    "sg:orig_category":"Verenigingen En Stichtingen",
    "sg:phone":"+31 317 318 129",
    "sg:postcode":"6865 BK",
    "sg:province":"Gelderland",
    "wof:name":"Humanistisch Verbond Arnhem Eo",
    "wof:placetype":"venue"
},
  "geometry": {"coordinates":[5.811587,51.974442],"type":"Point"}
}