{
  "type": "Feature",
  "properties": {
    "iso:country":"NL",
    "sg:address":"J V Maerlantstr 86-90",
    "sg:city":"S Hertogenbosch",
    "sg:orig_category":"Koeriersdiensten",
    "sg:phone":"+31 73 614 3449",
    "sg:postcode":"5216 JM",
    "sg:province":"Noord-Brabant",
    "wof:name":"Desk, Koerier",
    "wof:placetype":"venue"
},
  "geometry": {"coordinates":[5.29824,51.69075],"type":"Point"}
}