{
  "type": "Feature",
  "properties": {
    "addr:full":"Zuiderhaven 65/A Harlingen Friesland 8861 CM",
    "addr:housenumber":"65 / a",
    "addr:postcode":"8861 cm",
    "addr:street":"Zuiderhaven",
    "iso:country":"NL",
    "sg:address":"Zuiderhaven 65/A",
    "sg:city":"Harlingen",
    "sg:orig_category":"Verzekeringen - Verzekeringskantoren",
    "sg:phone":"+31 517 430 344",
    "sg:postcode":"8861 CM",
    "sg:province":"Friesland",
    "wof:name":"Kramer, J S",
    "wof:placetype":"venue"
},
  "geometry": {"coordinates":[5.416987,53.172832],"type":"Point"}
}