{
  "type": "Feature",
  "properties": {
    "addr:full":"Gerrit Van Den Boschpad 60 Amsterdam Zuidoost Noord-Holland 1106 WJ",
    "addr:housenumber":"60",
    "addr:postcode":"zuidoost;1106 wj",
    "addr:street":"Gerrit Van Den Boschpad",
    "iso:country":"NL",
    "sg:address":"Gerrit Van Den Boschpad 60",
    "sg:city":"Amsterdam Zuidoost",
    "sg:orig_category":"Boekhouders",
    "sg:phone":"+31 20 451 5420",
    "sg:postcode":"1106 WJ",
    "sg:province":"Noord-Holland",
    "wof:name":"J. De Haan Administraties",
    "wof:placetype":"venue"
},
  "geometry": {"coordinates":[4.994923,52.297981],"type":"Point"}
}