{
  "type": "Feature",
  "properties": {
    "iso:country":"NL",
    "sg:address":"Edelmanstr 66",
    "sg:city":"Kerkdriel",
    "sg:orig_category":"Verzekeringen - Verzekeringskantoren",
    "sg:phone":"+31 418 637 245",
    "sg:postcode":"5331 TL",
    "sg:province":"Gelderland",
    "wof:name":"Abi",
    "wof:placetype":"venue"
},
  "geometry": {"coordinates":[5.339096,51.769047],"type":"Point"}
}