{
  "type": "Feature",
  "properties": {
    "addr:full":"Edisonwg 9 Spykenisse Zuid-Holland 3208 KB",
    "addr:housenumber":"9",
    "addr:postcode":"3208 kb",
    "addr:street":"Edisonwg",
    "iso:country":"NL",
    "sg:address":"Edisonwg 9",
    "sg:city":"Spykenisse",
    "sg:orig_category":"Verzekeringen - Verzekeringskantoren",
    "sg:phone":"+31 181 690 232",
    "sg:postcode":"3208 KB",
    "sg:province":"Zuid-Holland",
    "wof:name":"Gmd Bv",
    "wof:placetype":"venue"
},
  "geometry": {"coordinates":[4.301783,51.85181],"type":"Point"}
}