{
  "type": "Feature",
  "properties": {
    "iso:country":"NL",
    "sg:address":"Lange Hofstedestraat 2",
    "sg:city":"Buren Gld",
    "sg:orig_category":"Autokeuringen",
    "sg:phone":"+31 344 572 506",
    "sg:postcode":"4116 EX",
    "sg:province":"Gelderland",
    "wof:name":"Autoservice W.J.J. Van Der Leeden Vof",
    "wof:placetype":"venue"
},
  "geometry": {"coordinates":[5.33347,51.908058],"type":"Point"}
}