{
  "type": "Feature",
  "properties": {
    "addr:full":"Hoofdstr 20 Schoonloo Drenthe 9443 PA",
    "addr:housenumber":"20",
    "addr:postcode":"9443 pa",
    "addr:street":"Hoofdstr",
    "iso:country":"NL",
    "sg:address":"Hoofdstr 20",
    "sg:city":"Schoonloo",
    "sg:classifiers":[
        {
            "category":"Travel",
            "subcategory":"Hotels & Motels",
            "type":"Entertainment"
        }
    ],
    "sg:phone":"+31 592 501 490",
    "sg:postcode":"9443 PA",
    "sg:province":"Drenthe",
    "sg:website":"http://www.deloohoeve.nl",
    "wof:name":"Loohoeve, De",
    "wof:placetype":"venue"
},
  "geometry": {"coordinates":[-77.604507,40.99464],"type":"Point"}
}