{
  "type": "Feature",
  "properties": {
    "addr:full":"Oldenzaalsestr 617 Enschede Overijssel 7524 AB",
    "addr:housenumber":"617",
    "addr:postcode":"7524 ab",
    "iso:country":"NL",
    "sg:address":"Oldenzaalsestr 617",
    "sg:city":"Enschede",
    "sg:orig_category":"Facilitaire Dienstverlening",
    "sg:phone":"+31 53 433 1115",
    "sg:postcode":"7524 AB",
    "sg:province":"Overijssel",
    "wof:name":"Logisch Werk Bv",
    "wof:placetype":"venue"
},
  "geometry": {"coordinates":[6.916429,52.246048],"type":"Point"}
}