{
  "type": "Feature",
  "properties": {
    "addr:full":"Klein Zwitserland 8 Gilze Noord-Brabant 5126 TA",
    "addr:housenumber":"8",
    "addr:postcode":"5126 ta",
    "addr:street":"Klein Zwitserland",
    "iso:country":"NL",
    "sg:address":"Klein Zwitserland 8",
    "sg:city":"Gilze",
    "sg:orig_category":"Fitnesscentra",
    "sg:phone":"+31 161 453 197",
    "sg:postcode":"5126 TA",
    "sg:province":"Noord-Brabant",
    "wof:name":"Toucan Health Club Bv",
    "wof:placetype":"venue"
},
  "geometry": {"coordinates":[4.945092,51.552582],"type":"Point"}
}