{
  "type": "Feature",
  "properties": {
    "iso:country":"NL",
    "sg:address":"Mark 20",
    "sg:city":"Apeldoorn",
    "sg:orig_category":"Kantoor- En Secretariaatsservice",
    "sg:phone":"+31 55 542 7944",
    "sg:postcode":"7333 KC",
    "sg:province":"Gelderland",
    "wof:name":"Hm Office Support",
    "wof:placetype":"venue"
},
  "geometry": {"coordinates":[5.9748158455,52.1886978149],"type":"Point"}
}