{
  "type": "Feature",
  "properties": {
    "iso:country":"NL",
    "sg:address":"Prins Hendrikweg 38",
    "sg:city":"Doorn",
    "sg:orig_category":"Diverse Dierenfokkers",
    "sg:phone":"+31 343 416 457",
    "sg:postcode":"3941 GH",
    "sg:province":"Utrecht",
    "wof:name":"Meyers Bijenteeltbedrijf De Heuvelrug",
    "wof:placetype":"venue"
},
  "geometry": {"coordinates":[5.343046,52.039852],"type":"Point"}
}