{
  "type": "Feature",
  "properties": {
    "addr:full":"Grotestraat 19 Tubbergen NL.08 7651 CG",
    "addr:housenumber":"19;nl.08",
    "addr:postcode":"7651 cg",
    "addr:street":"Grotestraat",
    "iso:country":"NL",
    "sg:address":"Grotestraat 19",
    "sg:city":"Tubbergen",
    "sg:orig_category":"Makelaars In Onroerend Goed",
    "sg:phone":"+31 546 621 800",
    "sg:postcode":"7651 CG",
    "sg:province":"NL.08",
    "wof:name":"G.J. Boers Makelaardij O.Z. & Taxatiebureau",
    "wof:placetype":"venue"
},
  "geometry": {"coordinates":[6.781925,52.405525],"type":"Point"}
}