{
  "type": "Feature",
  "properties": {
    "addr:full":"Ryksstrwg 52 Wassenaar Zuid-Holland 2241 BW",
    "addr:housenumber":"52",
    "addr:postcode":"2241 bw",
    "addr:street":"Ryksstrwg",
    "iso:country":"NL",
    "sg:address":"Ryksstrwg 52",
    "sg:city":"Wassenaar",
    "sg:orig_category":"Fietsen - Fabrieken En Groothandel",
    "sg:phone":"+31 70 511 9259",
    "sg:postcode":"2241 BW",
    "sg:province":"Zuid-Holland",
    "wof:name":"Tacx Bv",
    "wof:placetype":"venue"
},
  "geometry": {"coordinates":[4.393863,52.14307],"type":"Point"}
}