{
  "type": "Feature",
  "properties": {
    "addr:full":"De Morgenster 4 Gorredyk Friesland 8401 TB",
    "addr:housenumber":"4",
    "addr:postcode":"8401 tb",
    "addr:street":"De Morgenster",
    "iso:country":"NL",
    "sg:address":"De Morgenster 4",
    "sg:city":"Gorredyk",
    "sg:orig_category":"Makelaars En Adviseurs Onroerende Goederen",
    "sg:phone":"+31 513 464 521",
    "sg:postcode":"8401 TB",
    "sg:province":"Friesland",
    "wof:name":"Bijker",
    "wof:placetype":"venue"
},
  "geometry": {"coordinates":[6.071868,53.00322],"type":"Point"}
}