{
  "type": "Feature",
  "properties": {
    "iso:country":"NL",
    "sg:address":"Goorsestraat 39",
    "sg:city":"Haaksbergen",
    "sg:orig_category":"Fotostudio'S And Fotografen",
    "sg:phone":"+31 53 572 8872",
    "sg:postcode":"7482 CB",
    "sg:province":"NL.08",
    "wof:name":"Fotografie Herman Put",
    "wof:placetype":"venue"
},
  "geometry": {"coordinates":[6.734402,52.158653],"type":"Point"}
}