{
  "type": "Feature",
  "properties": {
    "addr:full":"Beemsterstraat 491 Amsterdam Noord-Holland 1024 BE",
    "addr:housenumber":"491",
    "addr:postcode":"1024",
    "addr:street":"Beemsterstraat",
    "iso:country":"NL",
    "sg:address":"Beemsterstraat 491",
    "sg:city":"Amsterdam",
    "sg:classifiers":[
        {
            "category":"Education",
            "subcategory":"Preschool",
            "type":"Public Place"
        }
    ],
    "sg:phone":"+31 20 636 7334",
    "sg:postcode":"1024 BE",
    "sg:province":"Noord-Holland",
    "sg:tags":[
        "kleuteronderwijs",
        "basis-"
    ],
    "wof:name":"T Zwanemeer",
    "wof:placetype":"venue"
},
  "geometry": {"coordinates":[4.949679,52.395287],"type":"Point"}
}