{
  "type": "Feature",
  "properties": {
    "addr:full":"Boulevard 7 Velp Gld Gelderland 6881 HN",
    "addr:housenumber":"7",
    "addr:postcode":"6881 hn",
    "addr:street":"Boulevard;Gld Gelderland",
    "iso:country":"NL",
    "sg:address":"Boulevard 7",
    "sg:city":"Velp Gld",
    "sg:orig_category":"Farmaceutische Producten Gh",
    "sg:phone":"+31 26 364 1010",
    "sg:postcode":"6881 HN",
    "sg:province":"Gelderland",
    "wof:name":"Larousse Nederland Bv",
    "wof:placetype":"venue"
},
  "geometry": {"coordinates":[5.973217,51.99752],"type":"Point"}
}