{
  "type": "Feature",
  "properties": {
    "addr:full":"Elzenlaan 12 Bergen Aan Zee North Holland 1865 BM",
    "addr:housenumber":"12",
    "addr:postcode":"1865 bm",
    "addr:street":"Elzenlaan",
    "iso:country":"NL",
    "sg:address":"Elzenlaan 12",
    "sg:city":"Bergen Aan Zee",
    "sg:orig_category":"Fietshandelaren",
    "sg:phone":"+31 72 581 2254",
    "sg:postcode":"1865 BM",
    "sg:province":"North Holland",
    "wof:name":"Twigt Ligfietsen",
    "wof:placetype":"venue"
},
  "geometry": {"coordinates":[4.636477,52.665062],"type":"Point"}
}