{
  "type": "Feature",
  "properties": {
    "iso:country":"NL",
    "sg:address":"Reeweg Oost 67",
    "sg:city":"Dordrecht",
    "sg:classifiers":[
        {
            "category":"Food & Beverages",
            "subcategory":"Fruits & Vegetables",
            "type":"Retail Goods"
        }
    ],
    "sg:phone":"+31 78 613 5554",
    "sg:postcode":"3312 CL",
    "sg:province":"South Holland",
    "sg:tags":[
        "groenten"
    ],
    "wof:name":"Jos Brand Groenten En Fruit",
    "wof:placetype":"venue"
},
  "geometry": {"coordinates":[4.680485,51.808262],"type":"Point"}
}