{
  "type": "Feature",
  "properties": {
    "addr:full":"Cornelis Kooijmanlaan 3 Bergen Nh Noord-Holland 1862 GG",
    "addr:housenumber":"3",
    "addr:postcode":"1862 gg",
    "addr:street":"Cornelis Kooijmanlaan",
    "iso:country":"NL",
    "sg:address":"Cornelis Kooijmanlaan 3",
    "sg:city":"Bergen Nh",
    "sg:orig_category":"Bloemen And Planten Gh",
    "sg:phone":"+31 72 589 9758",
    "sg:postcode":"1862 GG",
    "sg:province":"Noord-Holland",
    "wof:name":"S Giannakoudis",
    "wof:placetype":"venue"
},
  "geometry": {"coordinates":[4.713,52.670868],"type":"Point"}
}