{
  "type": "Feature",
  "properties": {
    "iso:country":"NL",
    "sg:address":"Tasmanstr 2B",
    "sg:city":"Amsterdam",
    "sg:orig_category":"Architecten En Architectenbureaus",
    "sg:phone":"+31 20 488 0538",
    "sg:postcode":"1013 AH",
    "sg:province":"Noord-Holland",
    "wof:name":"Abl",
    "wof:placetype":"venue"
},
  "geometry": {"coordinates":[4.8856,52.391685],"type":"Point"}
}