{
  "type": "Feature",
  "properties": {
    "addr:full":"Boshoverwg 61 Weert Limburg 6002 AM",
    "addr:housenumber":"61",
    "addr:postcode":"6002",
    "addr:street":"Boshoverwg",
    "iso:country":"NL",
    "sg:address":"Boshoverwg 61",
    "sg:city":"Weert",
    "sg:orig_category":"Banken",
    "sg:phone":"+31 495 459 591",
    "sg:postcode":"6002 AM",
    "sg:province":"Limburg",
    "sg:website":"http://www.rabobank.nl",
    "wof:name":"Rabobank",
    "wof:placetype":"venue"
},
  "geometry": {"coordinates":[5.686261,51.261948],"type":"Point"}
}