{
  "type": "Feature",
  "properties": {
    "iso:country":"NL",
    "sg:address":"Touwslagerstraat 11",
    "sg:city":"Purmerend",
    "sg:orig_category":"Verzekeringen",
    "sg:phone":"+31 299 645 009",
    "sg:postcode":"1445 BR",
    "sg:province":"Noord-Holland",
    "wof:name":"Rokass",
    "wof:placetype":"venue"
},
  "geometry": {"coordinates":[4.984944,52.503151],"type":"Point"}
}