{
  "type": "Feature",
  "properties": {
    "addr:full":"Malbergplein 18 Maastricht Limburg 6218 BC",
    "addr:housenumber":"18",
    "addr:postcode":"6218 bc",
    "addr:street":"Malbergplein",
    "iso:country":"NL",
    "sg:address":"Malbergplein 18",
    "sg:city":"Maastricht",
    "sg:orig_category":"Kappers",
    "sg:phone":"+31 43 343 3356",
    "sg:postcode":"6218 BC",
    "sg:province":"Limburg",
    "wof:name":"Coiffures Edgar",
    "wof:placetype":"venue"
},
  "geometry": {"coordinates":[5.6560549736,50.8646087646],"type":"Point"}
}