{
  "type": "Feature",
  "properties": {
    "addr:full":"Niersstraat 75 Enschede NL.08 7523 SG",
    "addr:housenumber":"75",
    "addr:postcode":"7523 sg",
    "addr:street":"Niersstraat",
    "iso:country":"NL",
    "sg:address":"Niersstraat 75",
    "sg:city":"Enschede",
    "sg:orig_category":"Fotostudio'S And Fotografen",
    "sg:phone":"+31 53 433 8123",
    "sg:postcode":"7523 SG",
    "sg:province":"NL.08",
    "wof:name":"A. Zilverberg",
    "wof:placetype":"venue"
},
  "geometry": {"coordinates":[6.892888,52.242218],"type":"Point"}
}