{
  "type": "Feature",
  "properties": {
    "addr:full":"Delistr 25-Iv Amsterdam Noord-Holland 1094 CT",
    "addr:housenumber":"25-iv",
    "addr:postcode":"1094 ct",
    "addr:street":"Delistr",
    "iso:country":"NL",
    "sg:address":"Delistr 25-Iv",
    "sg:city":"Amsterdam",
    "sg:orig_category":"Adviesbureaus",
    "sg:phone":"+31 6 51337151",
    "sg:postcode":"1094 CT",
    "sg:province":"Noord-Holland",
    "wof:name":"Edc",
    "wof:placetype":"venue"
},
  "geometry": {"coordinates":[4.93594,52.36198],"type":"Point"}
}