{
  "type": "Feature",
  "properties": {
    "addr:full":"Wilhelminastr 35A Vlagtwedde Groningen 9541 AM",
    "addr:housenumber":"35a",
    "addr:postcode":"9541",
    "addr:street":"Wilhelminastr",
    "iso:country":"NL",
    "sg:address":"Wilhelminastr 35A",
    "sg:city":"Vlagtwedde",
    "sg:orig_category":"Banken",
    "sg:phone":"+31 599 312 307",
    "sg:postcode":"9541 AM",
    "sg:province":"Groningen",
    "wof:name":"Sns",
    "wof:placetype":"venue"
},
  "geometry": {"coordinates":[7.113088,53.025909],"type":"Point"}
}