{
  "type": "Feature",
  "properties": {
    "iso:country":"NL",
    "sg:address":"Hobbemastraat 32",
    "sg:city":"'S-Gravenhage",
    "sg:orig_category":"Verenigingsgebouwen",
    "sg:phone":"+31 70 380 3012",
    "sg:postcode":"2526 JP",
    "sg:province":"Zuid-Holland",
    "wof:name":"Hobbema, Buurtcentrum",
    "wof:placetype":"venue"
},
  "geometry": {"coordinates":[4.307702,52.070362],"type":"Point"}
}