{
  "type": "Feature",
  "properties": {
    "addr:full":"De S Lohmanpln 11 Groningen Groningen 9722 HS",
    "addr:housenumber":"11",
    "addr:postcode":"9722 hs",
    "addr:street":"De",
    "iso:country":"NL",
    "sg:address":"De S Lohmanpln 11",
    "sg:city":"Groningen",
    "sg:orig_category":"Adviesbureaus Bedrijfsorganisatie",
    "sg:phone":"+31 50 525 8073",
    "sg:postcode":"9722 HS",
    "sg:province":"Groningen",
    "wof:name":"Groenhof Organisatie Adviseurs",
    "wof:placetype":"venue"
},
  "geometry": {"coordinates":[6.58354,53.195923],"type":"Point"}
}