{
  "type": "Feature",
  "properties": {
    "addr:full":"Coenecoop 15 Waddinxveen Zuid-Holland 2741 PG",
    "addr:housenumber":"15",
    "addr:postcode":"2741 pg",
    "addr:street":"Coenecoop",
    "iso:country":"NL",
    "sg:address":"Coenecoop 15",
    "sg:city":"Waddinxveen",
    "sg:orig_category":"Elektronica - Ontwikkeling En Groothandel",
    "sg:phone":"+31 182 630 001",
    "sg:postcode":"2741 PG",
    "sg:province":"Zuid-Holland",
    "sg:website":"http://www.delden.nl",
    "wof:name":"Delden Bv, G W J J Van",
    "wof:placetype":"venue"
},
  "geometry": {"coordinates":[4.650848,52.0312],"type":"Point"}
}