{
  "type": "Feature",
  "properties": {
    "addr:full":"Haagse Schouwwg 10A Leiden South Holland 2332 KG",
    "addr:housenumber":"10a",
    "addr:postcode":"2332 kg",
    "iso:country":"NL",
    "sg:address":"Haagse Schouwwg 10A",
    "sg:city":"Leiden",
    "sg:orig_category":"Grafmonumenten",
    "sg:phone":"+31 71 576 4047",
    "sg:postcode":"2332 KG",
    "sg:province":"South Holland",
    "wof:name":"Keuzenkamp Bv",
    "wof:placetype":"venue"
},
  "geometry": {"coordinates":[4.457308,52.16383],"type":"Point"}
}