{
  "type": "Feature",
  "properties": {
    "addr:full":"Bloemerd 6 Leiderdorp Zuid-Holland 2353 BZ",
    "addr:housenumber":"6",
    "addr:postcode":"2353 bz",
    "addr:street":"Bloemerd",
    "iso:country":"NL",
    "sg:address":"Bloemerd 6",
    "sg:city":"Leiderdorp",
    "sg:orig_category":"Sportverenigingen En Ontspannings- Verenigingen",
    "sg:phone":"+31 71 589 1814",
    "sg:postcode":"2353 BZ",
    "sg:province":"Zuid-Holland",
    "wof:name":"Lsc Alecto",
    "wof:placetype":"venue"
},
  "geometry": {"coordinates":[4.540806,52.16811],"type":"Point"}
}