{
  "type": "Feature",
  "properties": {
    "iso:country":"NL",
    "sg:address":"Bredyk 1",
    "sg:city":"Langweer",
    "sg:classifiers":[
        {
            "category":"Education",
            "subcategory":"Preschool",
            "type":"Public Place"
        }
    ],
    "sg:phone":"+31 513 499 375",
    "sg:postcode":"8525 EP",
    "sg:province":"Friesland",
    "sg:tags":[
        "kleuteronderwijs",
        "basis-"
    ],
    "wof:name":"Openbare Basisschool 'T Swannestee",
    "wof:placetype":"venue"
},
  "geometry": {"coordinates":[5.723404,52.957081],"type":"Point"}
}