{
  "type": "Feature",
  "properties": {
    "addr:full":"Middenwetering 160 Krimpen Ad Yssel Zuid-Holland 2922 EH",
    "addr:housenumber":"160",
    "addr:postcode":"2922 eh",
    "addr:street":"Middenwetering",
    "iso:country":"NL",
    "sg:address":"Middenwetering 160",
    "sg:city":"Krimpen Ad Yssel",
    "sg:orig_category":"Administratie- En Boekhoudkantoren",
    "sg:phone":"+31 180 517 991",
    "sg:postcode":"2922 EH",
    "sg:province":"Zuid-Holland",
    "wof:name":"Feddes, C M",
    "wof:placetype":"venue"
},
  "geometry": {"coordinates":[4.59843,51.918507],"type":"Point"}
}