{
  "type": "Feature",
  "properties": {
    "addr:full":"Planetenbaan 46 Ijsselstein Ut Utrecht 3402 HP",
    "addr:housenumber":"46",
    "addr:postcode":"3402 hp",
    "addr:street":"Planetenbaan",
    "iso:country":"NL",
    "sg:address":"Planetenbaan 46",
    "sg:city":"Ijsselstein Ut",
    "sg:classifiers":[
        {
            "category":"Education",
            "subcategory":"Preschool",
            "type":"Public Place"
        }
    ],
    "sg:phone":"+31 30 688 9260",
    "sg:postcode":"3402 HP",
    "sg:province":"Utrecht",
    "sg:tags":[
        "kleuteronderwijs",
        "basis-"
    ],
    "wof:name":"Stichting Welzijnswerk Ysselsteinse",
    "wof:placetype":"venue"
},
  "geometry": {"coordinates":[5.044845,52.030365],"type":"Point"}
}