{
  "type": "Feature",
  "properties": {
    "addr:full":"1E Hogewg 15 Zeist Utrecht 3701 HG",
    "addr:housenumber":"15",
    "addr:postcode":"3701 hg",
    "addr:street":"1E Hogewg",
    "iso:country":"NL",
    "sg:address":"1E Hogewg 15",
    "sg:city":"Zeist",
    "sg:orig_category":"Parkeergarages",
    "sg:phone":"+31 30 693 0479",
    "sg:postcode":"3701 HG",
    "sg:province":"Utrecht",
    "wof:name":"Slof, De",
    "wof:placetype":"venue"
},
  "geometry": {"coordinates":[5.240619,52.085854],"type":"Point"}
}