{
  "type": "Feature",
  "properties": {
    "addr:full":"Wolphaertsbocht 500 Rotterdam South Holland 3081 KZ",
    "addr:housenumber":"500",
    "addr:postcode":"3081 kz",
    "addr:street":"Wolphaertsbocht",
    "iso:country":"NL",
    "sg:address":"Wolphaertsbocht 500",
    "sg:city":"Rotterdam",
    "sg:orig_category":"Overheidsdiensten",
    "sg:phone":"+31 10 423 0944",
    "sg:postcode":"3081 KZ",
    "sg:province":"South Holland",
    "wof:name":"Wijkgebouw Tarwewijk",
    "wof:placetype":"venue"
},
  "geometry": {"coordinates":[4.4839420319,51.8945846558],"type":"Point"}
}