{
  "type": "Feature",
  "properties": {
    "addr:full":"Menno Simonszhof 51 Hilversum North Holland 1216 LK",
    "addr:housenumber":"51",
    "addr:postcode":"1216 lk",
    "addr:street":"Menno Simonszhof",
    "iso:country":"NL",
    "sg:address":"Menno Simonszhof 51",
    "sg:city":"Hilversum",
    "sg:classifiers":[
        {
            "category":"Professional",
            "subcategory":"Accounting & Tax Preparation",
            "type":"Services"
        }
    ],
    "sg:phone":"+31 35 621 5781",
    "sg:postcode":"1216 LK",
    "sg:province":"North Holland",
    "sg:tags":[
        "accountant"
    ],
    "wof:name":"Accountantskantoor F.V.D.Brink",
    "wof:placetype":"venue"
},
  "geometry": {"coordinates":[5.133887,52.217487],"type":"Point"}
}