{
  "type": "Feature",
  "properties": {
    "addr:full":"Wittenstein 92 Dordrecht South Holland 3328 MS",
    "addr:housenumber":"92",
    "addr:postcode":"3328 ms",
    "addr:street":"Wittenstein",
    "iso:country":"NL",
    "sg:address":"Wittenstein 92",
    "sg:city":"Dordrecht",
    "sg:orig_category":"Kantoorartikelen",
    "sg:phone":"+31 78 617 9319",
    "sg:postcode":"3328 MS",
    "sg:province":"South Holland",
    "wof:name":"Bre-Pro Kantoorefficiency",
    "wof:placetype":"venue"
},
  "geometry": {"coordinates":[4.6650972366,51.7728881836],"type":"Point"}
}