{
  "type": "Feature",
  "properties": {
    "iso:country":"NL",
    "sg:address":"Soesterwg 92",
    "sg:city":"Amersfoort",
    "sg:orig_category":"Autopoetsbedrijven",
    "sg:phone":"+31 33 463 1795",
    "sg:postcode":"3812 BC",
    "sg:province":"Utrecht",
    "wof:name":"Glanscar",
    "wof:placetype":"venue"
},
  "geometry": {"coordinates":[5.371586,52.156254],"type":"Point"}
}