{
  "type": "Feature",
  "properties": {
    "iso:country":"NL",
    "sg:address":"Kloeveln 43",
    "sg:city":"Giessenburg",
    "sg:orig_category":"Adviesbureaus Bedrijfsorganisatie",
    "sg:phone":"+31 184 651 916",
    "sg:postcode":"3381 LG",
    "sg:province":"South Holland",
    "wof:name":"Ivens Bv",
    "wof:placetype":"venue"
},
  "geometry": {"coordinates":[4.890527,51.852509],"type":"Point"}
}