{
  "type": "Feature",
  "properties": {
    "addr:full":"Veldwg 28 Bussum North Holland 1404 CV",
    "addr:housenumber":"28",
    "addr:postcode":"1404 cv",
    "addr:street":"Veldwg",
    "iso:country":"NL",
    "sg:address":"Veldwg 28",
    "sg:city":"Bussum",
    "sg:orig_category":"Video - Faciliteiten En Producties",
    "sg:phone":"+31 35 691 2050",
    "sg:postcode":"1404 CV",
    "sg:province":"North Holland",
    "wof:name":"Y-Frame",
    "wof:placetype":"venue"
},
  "geometry": {"coordinates":[5.16069,52.274548],"type":"Point"}
}