{
  "type": "Feature",
  "properties": {
    "iso:country":"NL",
    "sg:address":"Einderstraat 22",
    "sg:city":"Kerkrade",
    "sg:orig_category":"Verplichte Sociale Verzekeringen",
    "sg:phone":"+31 45 545 6464",
    "sg:postcode":"6461 EP",
    "sg:province":"Limburg",
    "wof:name":"Cz Groep Zorgverzekeringen",
    "wof:placetype":"venue"
},
  "geometry": {"coordinates":[6.062075,50.864193],"type":"Point"}
}