{
  "type": "Feature",
  "properties": {
    "addr:full":"Rechterstraat 37 Boxtel Noord-Brabant 5281 BS",
    "addr:housenumber":"37",
    "addr:postcode":"5281 bs",
    "addr:street":"Rechterstraat",
    "iso:country":"NL",
    "sg:address":"Rechterstraat 37",
    "sg:city":"Boxtel",
    "sg:orig_category":"Fotolaboratoria",
    "sg:phone":"+31 411 683 331",
    "sg:postcode":"5281 BS",
    "sg:province":"Noord-Brabant",
    "wof:name":"Kim Color Vaklaboratorium",
    "wof:placetype":"venue"
},
  "geometry": {"coordinates":[5.327091,51.587887],"type":"Point"}
}