{
  "type": "Feature",
  "properties": {
    "addr:full":"Schout 38 Naaldwyk Zuid-Holland 2671 ZR",
    "addr:housenumber":"38",
    "addr:postcode":"2671 zr",
    "addr:street":"Schout",
    "iso:country":"NL",
    "sg:address":"Schout 38",
    "sg:city":"Naaldwyk",
    "sg:classifiers":[
        {
            "category":"Shopping",
            "subcategory":"Gifts & Souvenirs",
            "type":"Retail Goods"
        }
    ],
    "sg:phone":"+31 174 631 457",
    "sg:postcode":"2671 ZR",
    "sg:province":"Zuid-Holland",
    "sg:tags":[
        "wens-",
        "en",
        "prentbriefkaarten"
    ],
    "wof:name":"Crealine",
    "wof:placetype":"venue"
},
  "geometry": {"coordinates":[4.2052488327,51.9913978577],"type":"Point"}
}