{
  "type": "Feature",
  "properties": {
    "addr:full":"Heuvelwg 9 Soest Utrecht 3761 XL",
    "addr:housenumber":"9",
    "addr:postcode":"3761 xl",
    "addr:street":"Heuvelwg",
    "iso:country":"NL",
    "sg:address":"Heuvelwg 9",
    "sg:city":"Soest",
    "sg:orig_category":"Administratie- En Boekhoudkantoren",
    "sg:phone":"+31 35 602 0346",
    "sg:postcode":"3761 XL",
    "sg:province":"Utrecht",
    "wof:name":"Activa",
    "wof:placetype":"venue"
},
  "geometry": {"coordinates":[5.289123,52.187771],"type":"Point"}
}