{
  "type": "Feature",
  "properties": {
    "addr:full":"C V Bruggenstr 14 Apeldoorn Gelderland 7321 JL",
    "addr:housenumber":"14",
    "addr:postcode":"7321 jl",
    "addr:street":"V Bruggenstr;Gelderland",
    "iso:country":"NL",
    "sg:address":"C V Bruggenstr 14",
    "sg:city":"Apeldoorn",
    "sg:orig_category":"Honden- En Kattentrimsalons",
    "sg:phone":"+31 55 366 7609",
    "sg:postcode":"7321 JL",
    "sg:province":"Gelderland",
    "wof:name":"Brouwers, Elsje",
    "wof:placetype":"venue"
},
  "geometry": {"coordinates":[5.98598,52.21265],"type":"Point"}
}