{
  "type": "Feature",
  "properties": {
    "addr:full":"De Kempenaerstraat 13 Oegstgeest Zuid-Holland 2341 GE",
    "addr:housenumber":"13",
    "addr:postcode":"2341",
    "addr:street":"De Kempenaerstraat",
    "iso:country":"NL",
    "sg:address":"De Kempenaerstraat 13",
    "sg:city":"Oegstgeest",
    "sg:orig_category":"Kappers",
    "sg:phone":"+31 71 517 3608",
    "sg:postcode":"2341 GE",
    "sg:province":"Zuid-Holland",
    "wof:name":"Firma G. De Groot & Zoon",
    "wof:placetype":"venue"
},
  "geometry": {"coordinates":[4.4681720734,52.1775588989],"type":"Point"}
}