{
  "type": "Feature",
  "properties": {
    "iso:country":"NL",
    "sg:address":"Winkelcentrum Woensel 122",
    "sg:city":"Eindhoven",
    "sg:classifiers":[
        {
            "category":"Fast Food",
            "type":"Food & Drink"
        }
    ],
    "sg:phone":"+31 40 242 8080",
    "sg:postcode":"5625 AG",
    "sg:province":"North Brabant",
    "sg:tags":[
        "afhaal",
        "restaurant"
    ],
    "wof:name":"Pizza Pronto Bv",
    "wof:placetype":"venue"
},
  "geometry": {"coordinates":[5.475394,51.467854],"type":"Point"}
}