{
  "type": "Feature",
  "properties": {
    "addr:full":"Postbus 117 Waalwijk Noord-Brabant 5140 AC",
    "addr:housenumber":"117",
    "addr:postcode":"5140 ac",
    "addr:street":"Postbus",
    "iso:country":"NL",
    "sg:address":"Postbus 117",
    "sg:city":"Waalwijk",
    "sg:orig_category":"Verpakkingen En Verpakkingsmaterialen",
    "sg:phone":"+31 416 333 744",
    "sg:postcode":"5140 AC",
    "sg:province":"Noord-Brabant",
    "wof:name":"Brabo-Pack",
    "wof:placetype":"venue"
},
  "geometry": {"coordinates":[5.062876,51.689789],"type":"Point"}
}