{
  "type": "Feature",
  "properties": {
    "iso:country":"NL",
    "sg:address":"Bolwerk 35",
    "sg:city":"Naarden",
    "sg:orig_category":"Bloemen En Planten - Groothandel",
    "sg:phone":"+31 35 695 3974",
    "sg:postcode":"1411 LK",
    "sg:province":"North Holland",
    "wof:name":"Aalsmeerse Bloemenshow Bv",
    "wof:placetype":"venue"
},
  "geometry": {"coordinates":[5.157054,52.307232],"type":"Point"}
}