{
  "type": "Feature",
  "properties": {
    "addr:full":"Spyksedk 36-B Gorinchem Zuid-Holland 4207 GN",
    "addr:housenumber":"36-b",
    "addr:postcode":"4207 gn",
    "addr:street":"Spyksedk",
    "iso:country":"NL",
    "sg:address":"Spyksedk 36-B",
    "sg:city":"Gorinchem",
    "sg:orig_category":"Wegenbouw",
    "sg:phone":"+31 183 635 268",
    "sg:postcode":"4207 GN",
    "sg:province":"Zuid-Holland",
    "sg:website":"http://www.anoordzij.nl",
    "wof:name":"Noordzij Bv",
    "wof:placetype":"venue"
},
  "geometry": {"coordinates":[4.9880709648,51.8395996094],"type":"Point"}
}