{
  "type": "Feature",
  "properties": {
    "addr:full":"Singel 159 Amsterdam Noord-Holland 1012 VK",
    "addr:housenumber":"159",
    "addr:postcode":"1012 vk",
    "addr:street":"Singel",
    "iso:country":"NL",
    "sg:address":"Singel 159",
    "sg:city":"Amsterdam",
    "sg:orig_category":"Architecten",
    "sg:phone":"+31 20 638 6240",
    "sg:postcode":"1012 VK",
    "sg:province":"Noord-Holland",
    "wof:name":"Janson Adriaanssen Architecten",
    "wof:placetype":"venue"
},
  "geometry": {"coordinates":[4.889876,52.374577],"type":"Point"}
}