{
  "type": "Feature",
  "properties": {
    "addr:full":"Javastr 1C S Gravenhage Zuid-Holland 2585 AA",
    "addr:housenumber":"1c s",
    "addr:postcode":"2585 aa",
    "addr:street":"Javastr",
    "iso:country":"NL",
    "sg:address":"Javastr 1C",
    "sg:city":"S Gravenhage",
    "sg:orig_category":"Hypotheken",
    "sg:phone":"+31 70 310 5110",
    "sg:postcode":"2585 AA",
    "sg:province":"Zuid-Holland",
    "wof:name":"Ib, Consult",
    "wof:placetype":"venue"
},
  "geometry": {"coordinates":[4.29777,52.094799],"type":"Point"}
}