{
  "type": "Feature",
  "properties": {
    "iso:country":"NL",
    "sg:address":"Kesperstr 11",
    "sg:city":"Gouda",
    "sg:orig_category":"Wasmachines En Wasdrogers - Onderhoud En Reparatie",
    "sg:phone":"+31 182 537 640",
    "sg:postcode":"2804 JT",
    "sg:province":"Zuid-Holland",
    "wof:name":"Kreft",
    "wof:placetype":"venue"
},
  "geometry": {"coordinates":[4.7093977928,52.0249404907],"type":"Point"}
}