{
  "type": "Feature",
  "properties": {
    "addr:full":"Langstraat 86 Wijhe Overijssel 8131 BG",
    "addr:housenumber":"86",
    "addr:postcode":"8131",
    "addr:street":"Langstraat",
    "iso:country":"NL",
    "sg:address":"Langstraat 86",
    "sg:city":"Wijhe",
    "sg:classifiers":[
        {
            "category":"Food & Beverages",
            "subcategory":"Fruits & Vegetables",
            "type":"Retail Goods"
        }
    ],
    "sg:phone":"+31 570 523 330",
    "sg:postcode":"8131 BG",
    "sg:province":"Overijssel",
    "sg:tags":[
        "groenten"
    ],
    "wof:name":"Van Der Linde",
    "wof:placetype":"venue"
},
  "geometry": {"coordinates":[6.135673,52.386196],"type":"Point"}
}