{
  "type": "Feature",
  "properties": {
    "addr:full":"Admiraal De Ruijterweg 81 Amsterdam Noord-Holland 1057 JZ",
    "addr:housenumber":"81",
    "addr:postcode":"1057 jz",
    "addr:street":"Admiraal De Ruijterweg",
    "iso:country":"NL",
    "sg:address":"Admiraal De Ruijterweg 81",
    "sg:city":"Amsterdam",
    "sg:classifiers":[
        {
            "category":"Communications",
            "subcategory":"Television Station",
            "type":"Services"
        }
    ],
    "sg:phone":"+31 20 612 1864",
    "sg:postcode":"1057 JZ",
    "sg:province":"Noord-Holland",
    "sg:tags":[
        "video",
        "audio",
        "verhuur"
    ],
    "wof:name":"Videotheek Video Palace",
    "wof:placetype":"venue"
},
  "geometry": {"coordinates":[4.859517,52.37146],"type":"Point"}
}