{
  "type": "Feature",
  "properties": {
    "addr:full":"Esschewg 105 Vught Noord-Brabant 5262 TV",
    "addr:housenumber":"105",
    "addr:postcode":"vught;5262 tv",
    "iso:country":"NL",
    "sg:address":"Esschewg 105",
    "sg:city":"Vught",
    "sg:orig_category":"Wegenbouw",
    "sg:phone":"+31 73 656 1801",
    "sg:postcode":"5262 TV",
    "sg:province":"Noord-Brabant",
    "wof:name":"Koac-Wmd Bv",
    "wof:placetype":"venue"
},
  "geometry": {"coordinates":[5.2810249329,51.6420860291],"type":"Point"}
}