{
  "type": "Feature",
  "properties": {
    "addr:full":"Ehrlichstr 7 Hilversum Noord-Holland 1221 JB",
    "addr:housenumber":"7",
    "addr:postcode":"1221 jb",
    "addr:street":"Ehrlichstr",
    "iso:country":"NL",
    "sg:address":"Ehrlichstr 7",
    "sg:city":"Hilversum",
    "sg:orig_category":"Arbo- En Bedrijfsgezondheids- Diensten",
    "sg:phone":"+31 35 772 9376",
    "sg:postcode":"1221 JB",
    "sg:province":"Noord-Holland",
    "wof:name":"Roijen, L Van",
    "wof:placetype":"venue"
},
  "geometry": {"coordinates":[5.187053,52.225109],"type":"Point"}
}