{
  "type": "Feature",
  "properties": {
    "iso:country":"NL",
    "sg:address":"Mr Haafkensstr 2",
    "sg:city":"Lexmond",
    "sg:orig_category":"Loonbedrijven",
    "sg:phone":"+31 347 342 518",
    "sg:postcode":"4128 CJ",
    "sg:province":"Zuid-Holland",
    "wof:name":"Jong, H A De",
    "wof:placetype":"venue"
},
  "geometry": {"coordinates":[5.033452,51.961033],"type":"Point"}
}