{
  "type": "Feature",
  "properties": {
    "addr:full":"Folkingestraat 25 Groningen Groningen 9711 JT",
    "addr:housenumber":"25",
    "addr:postcode":"9711 jt",
    "addr:street":"Folkingestraat",
    "iso:country":"NL",
    "sg:address":"Folkingestraat 25",
    "sg:city":"Groningen",
    "sg:orig_category":"Muziekinstrumenten",
    "sg:phone":"+31 50 313 7303",
    "sg:postcode":"9711 JT",
    "sg:province":"Groningen",
    "wof:name":"Stiggelbout Slagwerk",
    "wof:placetype":"venue"
},
  "geometry": {"coordinates":[6.564359,53.215847],"type":"Point"}
}