{
  "type": "Feature",
  "properties": {
    "addr:full":"Gropiuslijn 13 Zoetermeer South Holland 2728 AV",
    "addr:housenumber":"13",
    "addr:postcode":"2728 av",
    "addr:street":"Gropiuslijn",
    "iso:country":"NL",
    "sg:address":"Gropiuslijn 13",
    "sg:city":"Zoetermeer",
    "sg:classifiers":[
        {
            "category":"Fast Food",
            "type":"Food & Drink"
        }
    ],
    "sg:phone":"+31 70 389 9767",
    "sg:postcode":"2728 AV",
    "sg:province":"South Holland",
    "sg:tags":[
        "afhaal",
        "restaurant"
    ],
    "wof:name":"Vof A Buijs",
    "wof:placetype":"venue"
},
  "geometry": {"coordinates":[4.512048,52.076317],"type":"Point"}
}