{
  "type": "Feature",
  "properties": {
    "addr:full":"Molenkolk 8 Oostzaan Noord-Holland 1511 JX",
    "addr:housenumber":"8",
    "addr:postcode":"1511 jx",
    "addr:street":"Molenkolk",
    "iso:country":"NL",
    "sg:address":"Molenkolk 8",
    "sg:city":"Oostzaan",
    "sg:orig_category":"Accountants - Administratie- Consulenten En -Kantoren",
    "sg:phone":"+31 75 684 5846",
    "sg:postcode":"1511 JX",
    "sg:province":"Noord-Holland",
    "wof:name":"Hemert, R Van",
    "wof:placetype":"venue"
},
  "geometry": {"coordinates":[4.875193,52.434055],"type":"Point"}
}