{
  "type": "Feature",
  "properties": {
    "addr:full":"Willem Smuldersplein 4A Waalre Noord-Brabant 5582 JJ",
    "addr:housenumber":"4a",
    "addr:postcode":"5582 jj",
    "addr:street":"Willem Smuldersplein",
    "iso:country":"NL",
    "sg:address":"Willem Smuldersplein 4A",
    "sg:city":"Waalre",
    "sg:orig_category":"Kinderopvang Behalve Thuis",
    "sg:phone":"+31 40 221 4504",
    "sg:postcode":"5582 JJ",
    "sg:province":"Noord-Brabant",
    "wof:name":"Kinderopvangcentrum De Dondersteentjes",
    "wof:placetype":"venue"
},
  "geometry": {"coordinates":[5.471563,51.396778],"type":"Point"}
}