{
  "type": "Feature",
  "properties": {
    "addr:full":"Brinkman Passage 33-35 Haarlem Noord-Holland 2011 NZ",
    "addr:housenumber":"33-35",
    "addr:postcode":"2011 nz",
    "addr:street":"Passage",
    "iso:country":"NL",
    "sg:address":"Brinkman Passage 33-35",
    "sg:city":"Haarlem",
    "sg:orig_category":"Verlichting And Huishoudartikelen",
    "sg:phone":"+31 23 532 3370",
    "sg:postcode":"2011 NZ",
    "sg:province":"Noord-Holland",
    "wof:name":"De Gezellige Winkel Van Heemskerk",
    "wof:placetype":"venue"
},
  "geometry": {"coordinates":[4.63594,52.381596],"type":"Point"}
}