{
  "type": "Feature",
  "properties": {
    "addr:full":"De Kuil 45 Hapert Noord-Brabant 5527 AA",
    "addr:housenumber":"45",
    "addr:postcode":"5527 aa",
    "addr:street":"De Kuil",
    "iso:country":"NL",
    "sg:address":"De Kuil 45",
    "sg:city":"Hapert",
    "sg:orig_category":"Handelscentra",
    "sg:phone":"+31 497 386 027",
    "sg:postcode":"5527 AA",
    "sg:province":"Noord-Brabant",
    "wof:name":"Lavrijssen Bv, A",
    "wof:placetype":"venue"
},
  "geometry": {"coordinates":[5.258059,51.371223],"type":"Point"}
}