{
  "type": "Feature",
  "properties": {
    "iso:country":"NL",
    "sg:address":"Sydneystraat 10",
    "sg:city":"Rotterdam",
    "sg:orig_category":"Kantoorapparatuur Gh",
    "sg:phone":"+31 10 462 7783",
    "sg:postcode":"3074 BP",
    "sg:province":"South Holland",
    "wof:name":"Office Centre Rotterdam",
    "wof:placetype":"venue"
},
  "geometry": {"coordinates":[4.4085788727,51.9412574768],"type":"Point"}
}