{
  "type": "Feature",
  "properties": {
    "addr:full":"Dorpsstr 19 Uithoorn Noord-Holland 1421 AR",
    "addr:housenumber":"19",
    "addr:postcode":"1421",
    "addr:street":"Dorpsstr",
    "iso:country":"NL",
    "sg:address":"Dorpsstr 19",
    "sg:city":"Uithoorn",
    "sg:orig_category":"Kinderkleding",
    "sg:phone":"+31 297 533 945",
    "sg:postcode":"1421 AR",
    "sg:province":"Noord-Holland",
    "wof:name":"Joepie Joepie",
    "wof:placetype":"venue"
},
  "geometry": {"coordinates":[4.83039,52.232742],"type":"Point"}
}