{
  "type": "Feature",
  "properties": {
    "addr:full":"Kl Meerln 16 Valkenswaard Noord-Brabant 5553 CB",
    "addr:housenumber":"16",
    "addr:postcode":"5553 cb",
    "iso:country":"NL",
    "sg:address":"Kl Meerln 16",
    "sg:city":"Valkenswaard",
    "sg:orig_category":"Makelaars En Adviseurs Onroerende Goederen",
    "sg:phone":"+31 40 201 7427",
    "sg:postcode":"5553 CB",
    "sg:province":"Noord-Brabant",
    "wof:name":"Wijkre Bv",
    "wof:placetype":"venue"
},
  "geometry": {"coordinates":[5.463468,51.361134],"type":"Point"}
}