{
  "type": "Feature",
  "properties": {
    "addr:full":"Koekoeksedk 36 Zevenbergen Noord-Brabant 4761 PJ",
    "addr:housenumber":"36",
    "addr:postcode":"4761 pj",
    "addr:street":"Koekoeksedk",
    "iso:country":"NL",
    "sg:address":"Koekoeksedk 36",
    "sg:city":"Zevenbergen",
    "sg:orig_category":"Bestratingen",
    "sg:phone":"+31 168 326 412",
    "sg:postcode":"4761 PJ",
    "sg:province":"Noord-Brabant",
    "sg:website":"http://www.stekaysierbestrating.nl",
    "wof:name":"Stekay",
    "wof:placetype":"venue"
},
  "geometry": {"coordinates":[4.609768,51.65723],"type":"Point"}
}