{
  "type": "Feature",
  "properties": {
    "addr:full":"Kerkstraat 26 Zeeland Noord-Brabant 5411 BA",
    "addr:housenumber":"26",
    "addr:postcode":"5411 ba",
    "addr:street":"Kerkstraat",
    "iso:country":"NL",
    "sg:address":"Kerkstraat 26",
    "sg:city":"Zeeland",
    "sg:orig_category":"Fietshandelaren",
    "sg:phone":"+31 486 451 700",
    "sg:postcode":"5411 BA",
    "sg:province":"Noord-Brabant",
    "wof:name":"Toon Vd Burgt",
    "wof:placetype":"venue"
},
  "geometry": {"coordinates":[5.673245,51.695114],"type":"Point"}
}