{
  "type": "Feature",
  "properties": {
    "addr:full":"Crynssenstr 10 Amsterdam North Holland 1058 XW",
    "addr:housenumber":"10",
    "addr:postcode":"1058 xw",
    "addr:street":"Crynssenstr",
    "iso:country":"NL",
    "sg:address":"Crynssenstr 10",
    "sg:city":"Amsterdam",
    "sg:classifiers":[
        {
            "category":"Retail",
            "subcategory":"Auto Repair",
            "type":"Services"
        }
    ],
    "sg:phone":"+31 20 618 4402",
    "sg:postcode":"1058 XW",
    "sg:province":"North Holland",
    "sg:tags":[
        "garage"
    ],
    "wof:name":"Crijnssen",
    "wof:placetype":"venue"
},
  "geometry": {"coordinates":[4.856428,52.361534],"type":"Point"}
}