{
  "type": "Feature",
  "properties": {
    "addr:full":"Nijverheidsstraat 38 Nijkerk Gld Gelderland 3861 RJ",
    "addr:housenumber":"38",
    "addr:postcode":"3861 rj",
    "addr:street":"Nijverheidsstraat;Gld Gelderland",
    "iso:country":"NL",
    "sg:address":"Nijverheidsstraat 38",
    "sg:city":"Nijkerk Gld",
    "sg:orig_category":"Wegen And Sportterreinen",
    "sg:phone":"+31 33 245 5560",
    "sg:postcode":"3861 RJ",
    "sg:province":"Gelderland",
    "wof:name":"Heijmans Beton En Waterbouw Bv Rayon Midden West",
    "wof:placetype":"venue"
},
  "geometry": {"coordinates":[5.4747271538,52.2384910583],"type":"Point"}
}