{
  "type": "Feature",
  "properties": {
    "iso:country":"NL",
    "sg:address":"Markt 18",
    "sg:city":"Boxtel",
    "sg:orig_category":"Banken And Kredietinstellingen",
    "sg:phone":"+31 411 676 905",
    "sg:postcode":"5281 AV",
    "sg:province":"Noord-Brabant",
    "wof:name":"Abn Amro",
    "wof:placetype":"venue"
},
  "geometry": {"coordinates":[5.326473,51.588394],"type":"Point"}
}