{
  "type": "Feature",
  "properties": {
    "iso:country":"NL",
    "sg:address":"Julianapln 152",
    "sg:city":"Beuningen Gld",
    "sg:orig_category":"Kappers",
    "sg:phone":"+31 24 677 3001",
    "sg:postcode":"6641 CT",
    "sg:province":"Gelderland",
    "wof:name":"Kapper, De",
    "wof:placetype":"venue"
},
  "geometry": {"coordinates":[5.7713499069,51.8609733582],"type":"Point"}
}