{
  "type": "Feature",
  "properties": {
    "addr:full":"Industriestr 6 Noordwolde Fr Friesland 8391 AG",
    "addr:housenumber":"6",
    "addr:postcode":"8391",
    "addr:street":"Industriestr",
    "iso:country":"NL",
    "sg:address":"Industriestr 6",
    "sg:city":"Noordwolde Fr",
    "sg:orig_category":"Antiquiteiten",
    "sg:phone":"+31 561 433 593",
    "sg:postcode":"8391 AG",
    "sg:province":"Friesland",
    "wof:name":"Bertus Van Veen",
    "wof:placetype":"venue"
},
  "geometry": {"coordinates":[6.138839,52.893002],"type":"Point"}
}