{
  "type": "Feature",
  "properties": {
    "addr:full":"Hudsonstr 7 Amsterdam Noord-Holland 1057 RW",
    "addr:housenumber":"7",
    "addr:postcode":"1057 rw",
    "addr:street":"Hudsonstr",
    "iso:country":"NL",
    "sg:address":"Hudsonstr 7",
    "sg:city":"Amsterdam",
    "sg:orig_category":"Autorijscholen",
    "sg:phone":"+31 20 618 9542",
    "sg:postcode":"1057 RW",
    "sg:province":"Noord-Holland",
    "wof:name":"West Verkeersschool",
    "wof:placetype":"venue"
},
  "geometry": {"coordinates":[4.853889,52.364506],"type":"Point"}
}