{
  "type": "Feature",
  "properties": {
    "addr:full":"Marktstr 57 Wormerveer Noord-Holland 1521 DX",
    "addr:housenumber":"57",
    "addr:postcode":"1521 dx",
    "addr:street":"Marktstr",
    "iso:country":"NL",
    "sg:address":"Marktstr 57",
    "sg:city":"Wormerveer",
    "sg:orig_category":"Warenhuizen",
    "sg:phone":"+31 75 622 9868",
    "sg:postcode":"1521 DX",
    "sg:province":"Noord-Holland",
    "wof:name":"Action Wormerveer",
    "wof:placetype":"venue"
},
  "geometry": {"coordinates":[4.7886209488,52.4931640625],"type":"Point"}
}