{
  "type": "Feature",
  "properties": {
    "addr:full":"Kostverlorenstraat 935 Weesp Noord-Holland 1382 BH",
    "addr:housenumber":"935",
    "addr:postcode":"1382 bh",
    "addr:street":"Kostverlorenstraat",
    "iso:country":"NL",
    "sg:address":"Kostverlorenstraat 935",
    "sg:city":"Weesp",
    "sg:orig_category":"Huishoudelijk And Sanitair Papier Fab",
    "sg:phone":"+31 294 415 687",
    "sg:postcode":"1382 BH",
    "sg:province":"Noord-Holland",
    "wof:name":"A J J Mandersloot Agenturen",
    "wof:placetype":"venue"
},
  "geometry": {"coordinates":[5.033045,52.31282],"type":"Point"}
}