{
  "type": "Feature",
  "properties": {
    "addr:full":"Lobelius Serre 2 Amersfoort Utrecht 3823 DK",
    "addr:housenumber":"2",
    "addr:postcode":"3823 dk",
    "addr:street":"Serre",
    "iso:country":"NL",
    "sg:address":"Lobelius Serre 2",
    "sg:city":"Amersfoort",
    "sg:orig_category":"Kappers",
    "sg:phone":"+31 33 456 6322",
    "sg:postcode":"3823 DK",
    "sg:province":"Utrecht",
    "wof:name":"Crystal Palace",
    "wof:placetype":"venue"
},
  "geometry": {"coordinates":[5.3907051086,52.1891899109],"type":"Point"}
}