{
  "type": "Feature",
  "properties": {
    "addr:full":"Noordeind 4 Emmen Provincie Drenthe 7815 PA",
    "addr:housenumber":"4;7815",
    "addr:street":"Noordeind;Provincie Drenthe",
    "iso:country":"NL",
    "sg:address":"Noordeind 4",
    "sg:city":"Emmen",
    "sg:orig_category":"Wegen And Sportterreinen",
    "sg:phone":"+31 591 612 680",
    "sg:postcode":"7815 PA",
    "sg:province":"Provincie Drenthe",
    "wof:name":"G. Hemmen Bv",
    "wof:placetype":"venue"
},
  "geometry": {"coordinates":[6.8908438683,52.7895202637],"type":"Point"}
}