{
  "type": "Feature",
  "properties": {
    "addr:full":"Oude Dinxperl Wg 69 Silvolde Gelderland 7064 KX",
    "addr:housenumber":"69",
    "addr:postcode":"7064 kx",
    "addr:street":"Oude;Wg;Gelderland",
    "iso:country":"NL",
    "sg:address":"Oude Dinxperl Wg 69",
    "sg:city":"Silvolde",
    "sg:classifiers":[
        {
            "category":"Wholesale",
            "subcategory":"Motor Vehicles",
            "type":"Manufacturing & Wholesale Goods"
        }
    ],
    "sg:phone":"+31 315 640 568",
    "sg:postcode":"7064 KX",
    "sg:province":"Gelderland",
    "sg:tags":[
        "scooter",
        "en"
    ],
    "sg:website":"http://www.crosshop.nl",
    "wof:name":"Crosshop",
    "wof:placetype":"venue"
},
  "geometry": {"coordinates":[6.408959,51.899281],"type":"Point"}
}