{
  "type": "Feature",
  "properties": {
    "iso:country":"NL",
    "sg:address":"Paulus Potterlaan 47",
    "sg:city":"Woudenberg",
    "sg:orig_category":"Goederenvervoer Over De Weg",
    "sg:phone":"+31 33 286 1452",
    "sg:postcode":"3931 TD",
    "sg:province":"Utrecht",
    "wof:name":"A.J. Gersen Jr.",
    "wof:placetype":"venue"
},
  "geometry": {"coordinates":[5.42443,52.07674],"type":"Point"}
}