{
  "type": "Feature",
  "properties": {
    "addr:full":"Eksterln 32 Leidschendam Zuid-Holland 2261 EL",
    "addr:housenumber":"32",
    "addr:postcode":"2261 el",
    "addr:street":"Eksterln",
    "iso:country":"NL",
    "sg:address":"Eksterln 32",
    "sg:city":"Leidschendam",
    "sg:orig_category":"Vertalers",
    "sg:phone":"+31 70 320 3468",
    "sg:postcode":"2261 EL",
    "sg:province":"Zuid-Holland",
    "wof:name":"Faddegon, M",
    "wof:placetype":"venue"
},
  "geometry": {"coordinates":[4.38851,52.096661],"type":"Point"}
}