{
  "type": "Feature",
  "properties": {
    "addr:full":"Langewg 7A Gennep Limburg 6591 XX",
    "addr:housenumber":"7a",
    "addr:postcode":"6591 xx",
    "addr:street":"Langewg",
    "iso:country":"NL",
    "sg:address":"Langewg 7A",
    "sg:city":"Gennep",
    "sg:orig_category":"Metselwerken",
    "sg:phone":"+31 485 511 436",
    "sg:postcode":"6591 XX",
    "sg:province":"Limburg",
    "wof:name":"G\u00fclen Bouwservice",
    "wof:placetype":"venue"
},
  "geometry": {"coordinates":[5.97119,51.699299],"type":"Point"}
}