{
  "type": "Feature",
  "properties": {
    "addr:full":"Kerstroosstraat 3 Rotterdam Zuid-Holland 3053 EB",
    "addr:housenumber":"3",
    "addr:postcode":"3053 eb",
    "addr:street":"Kerstroosstraat",
    "iso:country":"NL",
    "sg:address":"Kerstroosstraat 3",
    "sg:city":"Rotterdam",
    "sg:orig_category":"Juweliers",
    "sg:phone":"+31 10 418 8727",
    "sg:postcode":"3053 EB",
    "sg:province":"Zuid-Holland",
    "wof:name":"Y Commeren Bv",
    "wof:placetype":"venue"
},
  "geometry": {"coordinates":[4.472186,51.959671],"type":"Point"}
}