{
  "type": "Feature",
  "properties": {
    "iso:country":"NL",
    "sg:address":"Barwoutswaarder 83",
    "sg:city":"Woerden",
    "sg:orig_category":"Kaas",
    "sg:phone":"+31 348 688 194",
    "sg:postcode":"3449 HK",
    "sg:province":"Utrecht",
    "wof:name":"Nap, P J",
    "wof:placetype":"venue"
},
  "geometry": {"coordinates":[4.8346338272,52.0785369873],"type":"Point"}
}