{
  "type": "Feature",
  "properties": {
    "iso:country":"NL",
    "sg:address":"Briljantstraat 185",
    "sg:city":"Groningen",
    "sg:orig_category":"Schoonheidssalons",
    "sg:phone":"+31 50 573 2915",
    "sg:postcode":"9743 NG",
    "sg:province":"Groningen",
    "wof:name":"Schoonheidssalon Alessandra",
    "wof:placetype":"venue"
},
  "geometry": {"coordinates":[6.52554,53.231274],"type":"Point"}
}