{
  "type": "Feature",
  "properties": {
    "addr:full":"Briljantstraat 185 Groningen Groningen 9743 NG",
    "addr:housenumber":"185",
    "addr:postcode":"9743 ng",
    "addr:street":"Briljantstraat",
    "iso:country":"NL",
    "sg:address":"Briljantstraat 185",
    "sg:city":"Groningen",
    "sg:orig_category":"Schoonheidssalons",
    "sg:phone":"+31 50 573 2915",
    "sg:postcode":"9743 NG",
    "sg:province":"Groningen",
    "wof:name":"Schoonheidssalon Alessandra",
    "wof:placetype":"venue"
},
  "geometry": {"coordinates":[6.52554,53.231274],"type":"Point"}
}