{
  "type": "Feature",
  "properties": {
    "iso:country":"NL",
    "sg:address":"Henri Dunantlaan 24",
    "sg:city":"Vleuten",
    "sg:orig_category":"Fotostudio'S And Fotografen",
    "sg:phone":"+31 30 677 3643",
    "sg:postcode":"3451 EP",
    "sg:province":"Utrecht",
    "wof:name":"Frons",
    "wof:placetype":"venue"
},
  "geometry": {"coordinates":[5.015973,52.109646],"type":"Point"}
}