{
  "type": "Feature",
  "properties": {
    "addr:full":"Bunuelstrook 42 Zoetermeer Zuid-Holland 2726 SE",
    "addr:housenumber":"42",
    "addr:postcode":"2726 se",
    "addr:street":"Bunuelstrook",
    "iso:country":"NL",
    "sg:address":"Bunuelstrook 42",
    "sg:city":"Zoetermeer",
    "sg:orig_category":"Kantoor- En Secretariaatsservice",
    "sg:phone":"+31 79 331 6558",
    "sg:postcode":"2726 SE",
    "sg:province":"Zuid-Holland",
    "wof:name":"Secretaresse Service Zoetermeer",
    "wof:placetype":"venue"
},
  "geometry": {"coordinates":[4.4860568047,52.0717964172],"type":"Point"}
}