{
  "type": "Feature",
  "properties": {
    "addr:full":"Vlietsend 28 Krommenie Noord-Holland 1561 AD",
    "addr:housenumber":"28",
    "addr:postcode":"1561 ad",
    "addr:street":"Vlietsend",
    "iso:country":"NL",
    "sg:address":"Vlietsend 28",
    "sg:city":"Krommenie",
    "sg:orig_category":"Keukens",
    "sg:phone":"+31 75 621 7260",
    "sg:postcode":"1561 AD",
    "sg:province":"Noord-Holland",
    "sg:website":"http://www.wstkeukens.nl",
    "wof:name":"Wst",
    "wof:placetype":"venue"
},
  "geometry": {"coordinates":[4.766583,52.495663],"type":"Point"}
}