{
  "type": "Feature",
  "properties": {
    "addr:full":"Haagseboswg 33 Enschede Overijssel 7525 PP",
    "addr:housenumber":"33",
    "addr:postcode":"7525 pp",
    "addr:street":"Haagseboswg",
    "iso:country":"NL",
    "sg:address":"Haagseboswg 33",
    "sg:city":"Enschede",
    "sg:orig_category":"Acupunctuur",
    "sg:phone":"+31 53 538 5826",
    "sg:postcode":"7525 PP",
    "sg:province":"Overijssel",
    "wof:name":"Ridder, J C De",
    "wof:placetype":"venue"
},
  "geometry": {"coordinates":[6.956334,52.259178],"type":"Point"}
}