{
  "type": "Feature",
  "properties": {
    "iso:country":"NL",
    "sg:address":"Traay 19A",
    "sg:city":"Driebergen Rysenb",
    "sg:orig_category":"Poeliers",
    "sg:phone":"+31 343 515 391",
    "sg:postcode":"3971 GB",
    "sg:province":"Utrecht",
    "wof:name":"Wildhuis, 'T",
    "wof:placetype":"venue"
},
  "geometry": {"coordinates":[5.283711,52.052437],"type":"Point"}
}