{
  "type": "Feature",
  "properties": {
    "iso:country":"NL",
    "sg:address":"De Tocht 7",
    "sg:city":"Bovenkarspel",
    "sg:orig_category":"Fruit And Groenten Gh",
    "sg:phone":"+31 228 515 739",
    "sg:postcode":"1611 HT",
    "sg:province":"North Holland",
    "wof:name":"Bakker Agf Groothandel En Koelvervoer Bv",
    "wof:placetype":"venue"
},
  "geometry": {"coordinates":[5.239765,52.693668],"type":"Point"}
}