{
  "type": "Feature",
  "properties": {
    "addr:full":"Klaverveld 19 Oud Vossemeer Zeeland 4698 PS",
    "addr:housenumber":"19",
    "addr:postcode":"4698 ps",
    "addr:street":"Klaverveld",
    "iso:country":"NL",
    "sg:address":"Klaverveld 19",
    "sg:city":"Oud Vossemeer",
    "sg:orig_category":"Artiesten/Gezelschappen",
    "sg:phone":"+31 166 602 298",
    "sg:postcode":"4698 PS",
    "sg:province":"Zeeland",
    "wof:name":"Pico & Bello",
    "wof:placetype":"venue"
},
  "geometry": {"coordinates":[4.19825,51.564968],"type":"Point"}
}