{
  "type": "Feature",
  "properties": {
    "addr:full":"Deventerwg 20 Zutphen Gelderland 7203 AK",
    "addr:housenumber":"20",
    "addr:postcode":"7203 ak",
    "addr:street":"Deventerwg;Gelderland",
    "iso:country":"NL",
    "sg:address":"Deventerwg 20",
    "sg:city":"Zutphen",
    "sg:classifiers":[
        {
            "category":"Professional",
            "subcategory":"Accounting & Tax Preparation",
            "type":"Services"
        }
    ],
    "sg:phone":"+31 575 517 523",
    "sg:postcode":"7203 AK",
    "sg:province":"Gelderland",
    "sg:tags":[
        "accountant",
        "en",
        "-kantoren",
        "register-"
    ],
    "wof:name":"Meerman, Drs J",
    "wof:placetype":"venue"
},
  "geometry": {"coordinates":[6.204928,52.148392],"type":"Point"}
}