{
  "type": "Feature",
  "properties": {
    "addr:full":"Heezerwg 157 Eindhoven Noord-Brabant 5614 HD",
    "addr:housenumber":"157",
    "addr:postcode":"5614 hd",
    "iso:country":"NL",
    "sg:address":"Heezerwg 157",
    "sg:city":"Eindhoven",
    "sg:orig_category":"Kappers",
    "sg:phone":"+31 40 211 0497",
    "sg:postcode":"5614 HD",
    "sg:province":"Noord-Brabant",
    "wof:name":"Bevers Herenkapsalon, Pieter",
    "wof:placetype":"venue"
},
  "geometry": {"coordinates":[5.4940919876,51.4262046814],"type":"Point"}
}