{
  "type": "Feature",
  "properties": {
    "iso:country":"NL",
    "sg:address":"Parkwg 296",
    "sg:city":"Voorburg",
    "sg:orig_category":"Postkantoren",
    "sg:phone":"+31 70 387 0161",
    "sg:postcode":"2271 BJ",
    "sg:province":"South Holland",
    "sg:website":"http://www.postkantoor.nl",
    "wof:name":"Postkantoor",
    "wof:placetype":"venue"
},
  "geometry": {"coordinates":[4.37397,52.075836],"type":"Point"}
}