{
  "type": "Feature",
  "properties": {
    "addr:full":"Hoofdwg 282 Paterswolde Provincie Drenthe 9765 CN",
    "addr:housenumber":"282",
    "addr:postcode":"9765 cn",
    "addr:street":"Provincie Drenthe",
    "iso:country":"NL",
    "sg:address":"Hoofdwg 282",
    "sg:city":"Paterswolde",
    "sg:orig_category":"Acupunctuur",
    "sg:phone":"+31 50 309 2800",
    "sg:postcode":"9765 CN",
    "sg:province":"Provincie Drenthe",
    "wof:name":"Sie-Oh Arts/Acupuncturiste, J G L",
    "wof:placetype":"venue"
},
  "geometry": {"coordinates":[6.564392,53.154964],"type":"Point"}
}