{
  "type": "Feature",
  "properties": {
    "addr:full":"Whistlerstraat 3 Venray Limburg 5801 VJ",
    "addr:housenumber":"3",
    "addr:postcode":"5801 vj",
    "addr:street":"Whistlerstraat",
    "iso:country":"NL",
    "sg:address":"Whistlerstraat 3",
    "sg:city":"Venray",
    "sg:orig_category":"Kinderopvang Behalve Thuis",
    "sg:phone":"+31 478 514 322",
    "sg:postcode":"5801 VJ",
    "sg:province":"Limburg",
    "wof:name":"Mkd De Kleuterhof",
    "wof:placetype":"venue"
},
  "geometry": {"coordinates":[5.967448,51.521915],"type":"Point"}
}