{
  "type": "Feature",
  "properties": {
    "addr:full":"Grenswg 21 Rilland Zeeland 4411 ST",
    "addr:housenumber":"21",
    "addr:postcode":"4411 st",
    "addr:street":"Grenswg",
    "iso:country":"NL",
    "sg:address":"Grenswg 21",
    "sg:city":"Rilland",
    "sg:orig_category":"Golfbanen",
    "sg:phone":"+31 113 551 265",
    "sg:postcode":"4411 ST",
    "sg:province":"Zeeland",
    "wof:name":"Birdy'S",
    "wof:placetype":"venue"
},
  "geometry": {"coordinates":[4.239023,51.389572],"type":"Point"}
}