{
  "type": "Feature",
  "properties": {
    "addr:full":"Meerkoetlaan 7 Bilthoven Utrecht 3722 WK",
    "addr:housenumber":"7",
    "addr:postcode":"3722 wk",
    "addr:street":"Meerkoetlaan",
    "iso:country":"NL",
    "sg:address":"Meerkoetlaan 7",
    "sg:city":"Bilthoven",
    "sg:orig_category":"Hypotheken And Hypotheekbanken",
    "sg:phone":"+31 30 228 8792",
    "sg:postcode":"3722 WK",
    "sg:province":"Utrecht",
    "wof:name":"Knegjens Financieel Advies",
    "wof:placetype":"venue"
},
  "geometry": {"coordinates":[5.211059,52.126286],"type":"Point"}
}