{
  "type": "Feature",
  "properties": {
    "addr:full":"Hoofdwg 244A Rotterdam Zuid-Holland 3067 GJ",
    "addr:housenumber":"244a",
    "addr:postcode":"3067 gj",
    "iso:country":"NL",
    "sg:address":"Hoofdwg 244A",
    "sg:city":"Rotterdam",
    "sg:orig_category":"Belastingconsulenten/ Belastingadviseurs",
    "sg:phone":"+31 10 421 8327",
    "sg:postcode":"3067 GJ",
    "sg:province":"Zuid-Holland",
    "wof:name":"Afortuna",
    "wof:placetype":"venue"
},
  "geometry": {"coordinates":[4.549165,51.948311],"type":"Point"}
}