{
  "type": "Feature",
  "properties": {
    "iso:country":"NL",
    "sg:address":"De Munniksplaat 6A",
    "sg:city":"Makkum Fr",
    "sg:orig_category":"Jachten - Schilderwerken En Onderhoud",
    "sg:phone":"+31 515 233 314",
    "sg:postcode":"8754 HG",
    "sg:province":"Provincie Friesland",
    "sg:website":"http://www.blue-mariene.nl",
    "wof:name":"Blue Mariene",
    "wof:placetype":"venue"
},
  "geometry": {"coordinates":[5.399421,53.049587],"type":"Point"}
}