{
  "type": "Feature",
  "properties": {
    "addr:full":"Klaroenring 153 Etten Leur North Brabant 4876 ZD",
    "addr:housenumber":"153",
    "addr:postcode":"4876 zd",
    "addr:street":"Klaroenring",
    "iso:country":"NL",
    "sg:address":"Klaroenring 153",
    "sg:city":"Etten Leur",
    "sg:orig_category":"Autorijscholen",
    "sg:phone":"+31 76 501 8533",
    "sg:postcode":"4876 ZD",
    "sg:province":"North Brabant",
    "wof:name":"Autorijschool Etten-Leur",
    "wof:placetype":"venue"
},
  "geometry": {"coordinates":[4.634388,51.556499],"type":"Point"}
}