{
  "type": "Feature",
  "properties": {
    "addr:full":"Van Bruhezedal 14 Valkenswaard Noord-Brabant 5551 EW",
    "addr:housenumber":"14",
    "addr:postcode":"5551 ew",
    "addr:street":"Van Bruhezedal",
    "iso:country":"NL",
    "sg:address":"Van Bruhezedal 14",
    "sg:city":"Valkenswaard",
    "sg:orig_category":"Kappers",
    "sg:phone":"+31 40 204 4893",
    "sg:postcode":"5551 EW",
    "sg:province":"Noord-Brabant",
    "wof:name":"Kapsalon Zo Zo",
    "wof:placetype":"venue"
},
  "geometry": {"coordinates":[5.430850029,51.3564071655],"type":"Point"}
}