{
  "type": "Feature",
  "properties": {
    "iso:country":"NL",
    "sg:address":"Jister 15A",
    "sg:city":"Grou",
    "sg:orig_category":"Watersportartikelen",
    "sg:phone":"+31 566 621 888",
    "sg:postcode":"9001 XX",
    "sg:province":"Idaho",
    "wof:name":"Kijlstra",
    "wof:placetype":"venue"
},
  "geometry": {"coordinates":[-113.6119232178,43.688873291],"type":"Point"}
}