{
  "type": "Feature",
  "properties": {
    "iso:country":"NL",
    "sg:address":"Hagelkruisstr 13",
    "sg:city":"Oss",
    "sg:orig_category":"Verenigingsgebouwen",
    "sg:phone":"+31 412 643 005",
    "sg:postcode":"5348 TB",
    "sg:province":"Noord-Brabant",
    "wof:name":"Schadewijk Wijkcentr",
    "wof:placetype":"venue"
},
  "geometry": {"coordinates":[-93.52149199999999,45.170681],"type":"Point"}
}