{
  "type": "Feature",
  "properties": {
    "addr:full":"Past V Laakstr 56 Lent Gelderland 6663 CB",
    "addr:housenumber":"56",
    "addr:postcode":"6663 cb",
    "addr:street":"Past;Laakstr;Gelderland",
    "iso:country":"NL",
    "sg:address":"Past V Laakstr 56",
    "sg:city":"Lent",
    "sg:orig_category":"Aggregaten",
    "sg:phone":"+31 24 322 0085",
    "sg:postcode":"6663 CB",
    "sg:province":"Gelderland",
    "wof:name":"Meijco Holland",
    "wof:placetype":"venue"
},
  "geometry": {"coordinates":[-77.241432,38.151344],"type":"Point"}
}