{
  "type": "Feature",
  "properties": {
    "addr:full":"J Israelsln 27 Arnhem Gelderland 6813 JA",
    "addr:housenumber":"27",
    "addr:postcode":"6813 ja",
    "iso:country":"NL",
    "sg:address":"J Israelsln 27",
    "sg:city":"Arnhem",
    "sg:orig_category":"Bloemen En Planten",
    "sg:phone":"+31 26 446 2701",
    "sg:postcode":"6813 JA",
    "sg:province":"Gelderland",
    "sg:website":"http://www.grafbloemen.nl",
    "wof:name":"Groothedde & Scharringa Vof",
    "wof:placetype":"venue"
},
  "geometry": {"coordinates":[5.881739,51.996353],"type":"Point"}
}