{
  "type": "Feature",
  "properties": {
    "addr:full":"Spaarneweg 12 Cruquius Noord-Holland 2142 EN",
    "addr:housenumber":"12",
    "addr:postcode":"2142 en",
    "addr:street":"Spaarneweg",
    "iso:country":"NL",
    "sg:address":"Spaarneweg 12",
    "sg:city":"Cruquius",
    "sg:orig_category":"Verhuisdiensten",
    "sg:phone":"+31 23 528 2245",
    "sg:postcode":"2142 EN",
    "sg:province":"Noord-Holland",
    "wof:name":"Wesseling Interland Meubeltransport Bv",
    "wof:placetype":"venue"
},
  "geometry": {"coordinates":[4.633244,52.334549],"type":"Point"}
}