{
  "type": "Feature",
  "properties": {
    "iso:country":"NL",
    "sg:address":"Uiterwg 15/A",
    "sg:city":"Aalsmeer",
    "sg:orig_category":"Jachthavens - Jachtwerven",
    "sg:phone":"+31 297 343 464",
    "sg:postcode":"1431 AA",
    "sg:province":"Noord-Holland",
    "wof:name":"B\u00f7Schen",
    "wof:placetype":"venue"
},
  "geometry": {"coordinates":[4.747422,52.26569],"type":"Point"}
}