{
  "type": "Feature",
  "properties": {
    "iso:country":"NL",
    "sg:address":"Heuvelstr 30",
    "sg:city":"Diessen",
    "sg:orig_category":"Accountants - Administratie- Consulenten En -Kantoren",
    "sg:phone":"+31 13 504 1991",
    "sg:postcode":"5087 AB",
    "sg:province":"North Brabant",
    "wof:name":"Gibo Groep",
    "wof:placetype":"venue"
},
  "geometry": {"coordinates":[5.173064,51.475399],"type":"Point"}
}