{
  "type": "Feature",
  "properties": {
    "addr:full":"Molenwg 58 Loppersum Groningen 9919 AJ",
    "addr:housenumber":"58",
    "addr:postcode":"9919 aj",
    "addr:street":"Molenwg",
    "iso:country":"NL",
    "sg:address":"Molenwg 58",
    "sg:city":"Loppersum",
    "sg:orig_category":"Accountants - Administratie- Consulenten En -Kantoren",
    "sg:phone":"+31 596 572 655",
    "sg:postcode":"9919 AJ",
    "sg:province":"Groningen",
    "wof:name":"Mendelts",
    "wof:placetype":"venue"
},
  "geometry": {"coordinates":[6.743985,53.33276],"type":"Point"}
}