{
  "type": "Feature",
  "properties": {
    "addr:full":"Plevier 43 Hoorn Nh Noord-Holland 1628 ET",
    "addr:housenumber":"43",
    "addr:postcode":"1628 et",
    "addr:street":"Plevier",
    "iso:country":"NL",
    "sg:address":"Plevier 43",
    "sg:city":"Hoorn Nh",
    "sg:orig_category":"Adviesbureaus Bedrijfsorganisatie",
    "sg:phone":"+31 229 230 968",
    "sg:postcode":"1628 ET",
    "sg:province":"Noord-Holland",
    "wof:name":"Beuze, De",
    "wof:placetype":"venue"
},
  "geometry": {"coordinates":[5.091997,52.658401],"type":"Point"}
}