{
  "type": "Feature",
  "properties": {
    "addr:full":"Not. L. P. V D Blinklaan 20 Brielle Zuid-Holland 3232 EK",
    "addr:housenumber":"20",
    "addr:postcode":"3232 ek",
    "addr:street":"Not. L. P. V D Blinklaan",
    "iso:country":"NL",
    "sg:address":"Not. L. P. V D Blinklaan 20",
    "sg:city":"Brielle",
    "sg:orig_category":"Advocaten And Juridische Adviseurs",
    "sg:phone":"+31 181 416 177",
    "sg:postcode":"3232 EK",
    "sg:province":"Zuid-Holland",
    "wof:name":"Sepers Advocaten",
    "wof:placetype":"venue"
},
  "geometry": {"coordinates":[4.167875,51.90406],"type":"Point"}
}