{
  "type": "Feature",
  "properties": {
    "iso:country":"NL",
    "sg:address":"Magdalenalaan 20",
    "sg:city":"Hengelo Ov",
    "sg:orig_category":"Architecten",
    "sg:phone":"+31 74 291 2486",
    "sg:postcode":"7555 TB",
    "sg:province":"Overijssel",
    "wof:name":"Tuinontwerp & Adviesburo Jansen",
    "wof:placetype":"venue"
},
  "geometry": {"coordinates":[6.771901,52.261383],"type":"Point"}
}