{
  "type": "Feature",
  "properties": {
    "addr:full":"Dorpsstr 45 Aalsmeer Noord-Holland 1431 CA",
    "addr:housenumber":"45",
    "addr:postcode":"1431 ca",
    "addr:street":"Dorpsstr",
    "iso:country":"NL",
    "sg:address":"Dorpsstr 45",
    "sg:city":"Aalsmeer",
    "sg:orig_category":"Grafisch Ontwerpers",
    "sg:phone":"+31 297 323 853",
    "sg:postcode":"1431 CA",
    "sg:province":"Noord-Holland",
    "wof:name":"Jc, Studio",
    "wof:placetype":"venue"
},
  "geometry": {"coordinates":[4.748208,52.270763],"type":"Point"}
}