{
  "type": "Feature",
  "properties": {
    "iso:country":"NL",
    "sg:address":"Amstel 326",
    "sg:city":"Amsterdam",
    "sg:orig_category":"Makelaars In Onroerend Goed",
    "sg:phone":"+31 20 626 2827",
    "sg:postcode":"1017 AR",
    "sg:province":"Noord-Holland",
    "wof:name":"Ter Linden & Heijer Bv",
    "wof:placetype":"venue"
},
  "geometry": {"coordinates":[-94.58503,38.350479],"type":"Point"}
}