{
  "type": "Feature",
  "properties": {
    "iso:country":"NL",
    "sg:address":"Liberiastr 3",
    "sg:city":"Delft",
    "sg:orig_category":"Verenigingen En Stichtingen",
    "sg:phone":"+31 15 261 3403",
    "sg:postcode":"2622 DE",
    "sg:province":"Zuid-Holland",
    "wof:name":"Ned Ver Van Slechthorenden",
    "wof:placetype":"venue"
},
  "geometry": {"coordinates":[4.340766,51.982292],"type":"Point"}
}