{
  "type": "Feature",
  "properties": {
    "iso:country":"NL",
    "sg:address":"Wollefoppenweg 81",
    "sg:city":"Zevenhuizen Zh",
    "sg:orig_category":"Marktonderzoekbureaus",
    "sg:phone":"+31 10 220 2108",
    "sg:postcode":"2761 DK",
    "sg:province":"South Holland",
    "wof:name":"Heuvel Marketing Consultancy Vof",
    "wof:placetype":"venue"
},
  "geometry": {"coordinates":[4.572311,51.972488],"type":"Point"}
}