{
  "type": "Feature",
  "properties": {
    "addr:full":"Weesperstraat 270 Amsterdam Noord-Holland 1018 DN",
    "addr:housenumber":"270",
    "addr:postcode":"1018 dn",
    "addr:street":"Weesperstraat",
    "iso:country":"NL",
    "sg:address":"Weesperstraat 270",
    "sg:city":"Amsterdam",
    "sg:orig_category":"Diverse Grafische Activiteiten",
    "sg:phone":"+31 20 623 6837",
    "sg:postcode":"1018 DN",
    "sg:province":"Noord-Holland",
    "wof:name":"Friso Henstra",
    "wof:placetype":"venue"
},
  "geometry": {"coordinates":[4.905399,52.365265],"type":"Point"}
}