{
  "type": "Feature",
  "properties": {
    "addr:full":"Philips De Goedestraat 84 Vlaardingen Zuid-Holland 3132 XS",
    "addr:housenumber":"84",
    "addr:postcode":"3132 xs",
    "addr:street":"Philips De Goedestraat",
    "iso:country":"NL",
    "sg:address":"Philips De Goedestraat 84",
    "sg:city":"Vlaardingen",
    "sg:orig_category":"Metalen And Ertsen Gh",
    "sg:phone":"+31 10 435 6127",
    "sg:postcode":"3132 XS",
    "sg:province":"Zuid-Holland",
    "wof:name":"Handelsonderneming D.K.J. Zandijk",
    "wof:placetype":"venue"
},
  "geometry": {"coordinates":[4.320293,51.914024],"type":"Point"}
}