{
  "type": "Feature",
  "properties": {
    "iso:country":"NL",
    "sg:address":"Buitenwatersloot 132A",
    "sg:city":"Delft",
    "sg:orig_category":"Woninginrichting",
    "sg:phone":"+31 15 212 5333",
    "sg:postcode":"2613 SV",
    "sg:province":"South Holland",
    "sg:website":"http://www.vanbaarle.com",
    "wof:name":"Baarle & Zn, H H P Van",
    "wof:placetype":"venue"
},
  "geometry": {"coordinates":[4.3516278267,52.0077629089],"type":"Point"}
}