{
  "type": "Feature",
  "properties": {
    "addr:full":"Viltmakersdonk 107 Apeldoorn Gelderland 7326 LJ",
    "addr:housenumber":"107;lj",
    "addr:postcode":"7326",
    "addr:street":"Viltmakersdonk;Gelderland",
    "iso:country":"NL",
    "sg:address":"Viltmakersdonk 107",
    "sg:city":"Apeldoorn",
    "sg:orig_category":"Adviesbureaus Automatisering",
    "sg:phone":"+31 55 844 0388",
    "sg:postcode":"7326 LJ",
    "sg:province":"Gelderland",
    "sg:website":"http://www.youngdesign.nl",
    "wof:name":"Young Design",
    "wof:placetype":"venue"
},
  "geometry": {"coordinates":[6.008642,52.196777],"type":"Point"}
}