{
  "type": "Feature",
  "properties": {
    "addr:full":"1E Hogewg 19 Zeist Utrecht 3701 HG",
    "addr:housenumber":"19",
    "addr:postcode":"3701 hg",
    "addr:street":"1E Hogewg",
    "iso:country":"NL",
    "sg:address":"1E Hogewg 19",
    "sg:city":"Zeist",
    "sg:orig_category":"Verzekeringen - Verzekeringskantoren",
    "sg:phone":"+31 30 691 2084",
    "sg:postcode":"3701 HG",
    "sg:province":"Utrecht",
    "wof:name":"Vendopolis Bv",
    "wof:placetype":"venue"
},
  "geometry": {"coordinates":[5.240885,52.08572],"type":"Point"}
}