{
  "type": "Feature",
  "properties": {
    "addr:full":"Handelsstr 51 Hardenberg Overijssel 7772 TS",
    "addr:housenumber":"51",
    "addr:postcode":"7772 ts",
    "addr:street":"Handelsstr",
    "iso:country":"NL",
    "sg:address":"Handelsstr 51",
    "sg:city":"Hardenberg",
    "sg:orig_category":"Oldtimers",
    "sg:phone":"+31 523 262 626",
    "sg:postcode":"7772 TS",
    "sg:province":"Overijssel",
    "sg:website":"http://www.autoeshuis.nl",
    "wof:name":"Eshuis Bv",
    "wof:placetype":"venue"
},
  "geometry": {"coordinates":[6.635295,52.56134],"type":"Point"}
}