{
  "type": "Feature",
  "properties": {
    "iso:country":"NL",
    "sg:address":"Grt Houtwg 61",
    "sg:city":"Beverwyk",
    "sg:orig_category":"Bloemen En Planten - Groothandel",
    "sg:phone":"+31 251 222 608",
    "sg:postcode":"1944 HB",
    "sg:province":"North Holland",
    "wof:name":"Aquafleur Bv",
    "wof:placetype":"venue"
},
  "geometry": {"coordinates":[4.657705,52.487766],"type":"Point"}
}