{
  "type": "Feature",
  "properties": {
    "addr:full":"Biest 124 Weert Limburg 6001 AT",
    "addr:housenumber":"124",
    "addr:postcode":"6001",
    "addr:street":"Biest",
    "iso:country":"NL",
    "sg:address":"Biest 124",
    "sg:city":"Weert",
    "sg:orig_category":"Meubelreparatie And -Restauratie",
    "sg:phone":"+31 495 537 727",
    "sg:postcode":"6001 AT",
    "sg:province":"Limburg",
    "wof:name":"Stoffeerderij Rudolf",
    "wof:placetype":"venue"
},
  "geometry": {"coordinates":[5.714223,51.260792],"type":"Point"}
}