{
  "type": "Feature",
  "properties": {
    "iso:country":"NL",
    "sg:address":"P De Hoochstr 103",
    "sg:city":"Rotterdam",
    "sg:orig_category":"Verenigingen En Stichtingen",
    "sg:phone":"+31 10 478 3515",
    "sg:postcode":"3024 CP",
    "sg:province":"Zuid-Holland",
    "wof:name":"Delphi, Sticht",
    "wof:placetype":"venue"
},
  "geometry": {"coordinates":[4.456263,51.90535],"type":"Point"}
}