{
  "type": "Feature",
  "properties": {
    "addr:full":"Bloemend Strwg 167 Santpoort Zuid North Holland 2082 GE",
    "addr:housenumber":"167",
    "addr:postcode":"2082",
    "addr:street":"Santpoort Zuid North Holland",
    "iso:country":"NL",
    "sg:address":"Bloemend Strwg 167",
    "sg:city":"Santpoort Zuid",
    "sg:orig_category":"Postkantoren",
    "sg:phone":"+31 23 537 8411",
    "sg:postcode":"2082 GE",
    "sg:province":"North Holland",
    "sg:website":"http://www.postkantoor.nl",
    "wof:name":"Postkantoor",
    "wof:placetype":"venue"
},
  "geometry": {"coordinates":[4.629593,52.417297],"type":"Point"}
}