{
  "type": "Feature",
  "properties": {
    "addr:full":"J Vroegopsngl 7 Amsterdam Noord-Holland 1096 CN",
    "addr:housenumber":"7",
    "addr:postcode":"1096 cn",
    "iso:country":"NL",
    "sg:address":"J Vroegopsngl 7",
    "sg:city":"Amsterdam",
    "sg:orig_category":"Verenigingen En Stichtingen",
    "sg:phone":"+31 20 693 6228",
    "sg:postcode":"1096 CN",
    "sg:province":"Noord-Holland",
    "wof:name":"Amstelglorie",
    "wof:placetype":"venue"
},
  "geometry": {"coordinates":[4.909308,52.334854],"type":"Point"}
}