{
  "type": "Feature",
  "properties": {
    "addr:full":"Duinweg Of Duivelslaan 32 Santpoort-Zuid North Holland 2082 CC",
    "addr:housenumber":"32",
    "addr:postcode":"2082 cc",
    "addr:street":"Duinweg Of Duivelslaan",
    "iso:country":"NL",
    "sg:address":"Duinweg Of Duivelslaan 32",
    "sg:city":"Santpoort-Zuid",
    "sg:orig_category":"Verzekeringen",
    "sg:phone":"+31 23 537 6425",
    "sg:postcode":"2082 CC",
    "sg:province":"North Holland",
    "wof:name":"N. Van Egmond Assurantien",
    "wof:placetype":"venue"
},
  "geometry": {"coordinates":[4.63207,52.424076],"type":"Point"}
}