{
  "type": "Feature",
  "properties": {
    "addr:full":"Langeweg 5 Hoek Zeeland 4542 RT",
    "addr:housenumber":"5",
    "addr:postcode":"4542 rt",
    "addr:street":"Langeweg",
    "iso:country":"NL",
    "sg:address":"Langeweg 5",
    "sg:city":"Hoek",
    "sg:orig_category":"Goederenvervoer Over De Weg",
    "sg:phone":"+31 115 441 368",
    "sg:postcode":"4542 RT",
    "sg:province":"Zeeland",
    "wof:name":"H.J.J. Van Doesselaar",
    "wof:placetype":"venue"
},
  "geometry": {"coordinates":[3.780146,51.293079],"type":"Point"}
}