{
  "type": "Feature",
  "properties": {
    "iso:country":"NL",
    "sg:address":"Bovendijk 13",
    "sg:city":"Kwintsheul",
    "sg:orig_category":"Autokeuringen",
    "sg:phone":"+31 174 290 990",
    "sg:postcode":"2295 RV",
    "sg:province":"South Holland",
    "wof:name":"Valstar Schade Bv",
    "wof:placetype":"venue"
},
  "geometry": {"coordinates":[4.258853,52.015656],"type":"Point"}
}