{
  "type": "Feature",
  "properties": {
    "addr:full":"Herenwg 231 Egmond Ad Hoef Noord-Holland 1934 BB",
    "addr:housenumber":"231",
    "addr:postcode":"1934 bb",
    "addr:street":"Egmond Ad",
    "iso:country":"NL",
    "sg:address":"Herenwg 231",
    "sg:city":"Egmond Ad Hoef",
    "sg:orig_category":"Fotopersbureaus",
    "sg:phone":"+31 72 506 9996",
    "sg:postcode":"1934 BB",
    "sg:province":"Noord-Holland",
    "wof:name":"Mooij, Cor",
    "wof:placetype":"venue"
},
  "geometry": {"coordinates":[4.650267,52.621872],"type":"Point"}
}