{
  "type": "Feature",
  "properties": {
    "addr:full":"Walingsdijk 15 Ursem North Holland 1645 RK",
    "addr:housenumber":"15",
    "addr:postcode":"1645 rk",
    "addr:street":"Walingsdijk",
    "iso:country":"NL",
    "sg:address":"Walingsdijk 15",
    "sg:city":"Ursem",
    "sg:orig_category":"Metaalwerken",
    "sg:phone":"+31 72 502 2174",
    "sg:postcode":"1645 RK",
    "sg:province":"North Holland",
    "wof:name":"D. Baas",
    "wof:placetype":"venue"
},
  "geometry": {"coordinates":[4.892652,52.624134],"type":"Point"}
}