{
  "type": "Feature",
  "properties": {
    "addr:full":"Stationslaan 97 Harderwijk Gelderland 3844 GB",
    "addr:housenumber":"97",
    "addr:postcode":"3844 gb",
    "addr:street":"Stationslaan;Gelderland",
    "iso:country":"NL",
    "sg:address":"Stationslaan 97",
    "sg:city":"Harderwijk",
    "sg:orig_category":"Meubelreparatie And -Restauratie",
    "sg:phone":"+31 341 427 662",
    "sg:postcode":"3844 GB",
    "sg:province":"Gelderland",
    "wof:name":"Peter Haver",
    "wof:placetype":"venue"
},
  "geometry": {"coordinates":[5.619015,52.342449],"type":"Point"}
}