{
  "type": "Feature",
  "properties": {
    "iso:country":"NL",
    "sg:address":"Van Diepeningenlaan 21",
    "sg:city":"Leiderdorp",
    "sg:orig_category":"Kappers",
    "sg:phone":"+31 71 589 0143",
    "sg:postcode":"2352 KA",
    "sg:province":"Zuid-Holland",
    "wof:name":"Hairmaxx",
    "wof:placetype":"venue"
},
  "geometry": {"coordinates":[4.5274958611,52.1586418152],"type":"Point"}
}