{
  "type": "Feature",
  "properties": {
    "addr:full":"Ruiterswg 3537 Hilversum Noord-Holland 1211 KT",
    "addr:housenumber":"3537",
    "addr:postcode":"hilversum;1211 kt",
    "iso:country":"NL",
    "sg:address":"Ruiterswg 3537",
    "sg:city":"Hilversum",
    "sg:orig_category":"Omroep",
    "sg:phone":"+31 35 625 4444",
    "sg:postcode":"1211 KT",
    "sg:province":"Noord-Holland",
    "sg:website":"http://www.broadcastpartners.nl",
    "wof:name":"Broadcast Co",
    "wof:placetype":"venue"
},
  "geometry": {"coordinates":[5.16919,52.22224],"type":"Point"}
}