{
  "type": "Feature",
  "properties": {
    "addr:full":"Hof Ter Veste 13A Middelburg Zeeland 4333 HG",
    "addr:housenumber":"13a",
    "addr:postcode":"4333 hg",
    "addr:street":"Hof Ter Veste",
    "iso:country":"NL",
    "sg:address":"Hof Ter Veste 13A",
    "sg:city":"Middelburg",
    "sg:orig_category":"Kappers",
    "sg:phone":"+31 118 679 208",
    "sg:postcode":"4333 HG",
    "sg:province":"Zeeland",
    "wof:name":"Ankie",
    "wof:placetype":"venue"
},
  "geometry": {"coordinates":[3.6068809032,51.5052871704],"type":"Point"}
}