{
  "type": "Feature",
  "properties": {
    "iso:country":"NL",
    "sg:address":"Kleine Overstraat 41",
    "sg:city":"Deventer",
    "sg:orig_category":"Medische Apparatuur And Prothesen Fab",
    "sg:phone":"+31 570 612 613",
    "sg:postcode":"7411 JJ",
    "sg:province":"NL.08",
    "wof:name":"Reiken Hoorapparaten",
    "wof:placetype":"venue"
},
  "geometry": {"coordinates":[6.158039,52.252426],"type":"Point"}
}