{
  "type": "Feature",
  "properties": {
    "addr:full":"Paradysvogelstr 11T Groningen Groningen 9713 BV",
    "addr:housenumber":"11t",
    "addr:postcode":"9713 bv",
    "addr:street":"Paradysvogelstr",
    "iso:country":"NL",
    "sg:address":"Paradysvogelstr 11T",
    "sg:city":"Groningen",
    "sg:orig_category":"Meubelstoffering",
    "sg:phone":"+31 50 579 9833",
    "sg:postcode":"9713 BV",
    "sg:province":"Groningen",
    "wof:name":"Bakker, A",
    "wof:placetype":"venue"
},
  "geometry": {"coordinates":[6.583062,53.231667],"type":"Point"}
}