{
  "type": "Feature",
  "properties": {
    "iso:country":"NL",
    "sg:address":"Oosterstraat 48",
    "sg:city":"Stadskanaal",
    "sg:orig_category":"Hout Gh",
    "sg:phone":"+31 599 613 386",
    "sg:postcode":"9502 EE",
    "sg:province":"Groningen",
    "wof:name":"A.J. Noorlag",
    "wof:placetype":"venue"
},
  "geometry": {"coordinates":[6.969998,52.976166],"type":"Point"}
}