{
  "type": "Feature",
  "properties": {
    "addr:full":"Dillenburgln 34 Ryswyk Zh Zuid-Holland 2281 CW",
    "addr:housenumber":"34",
    "addr:postcode":"2281 cw",
    "addr:street":"Dillenburgln",
    "iso:country":"NL",
    "sg:address":"Dillenburgln 34",
    "sg:city":"Ryswyk Zh",
    "sg:classifiers":[
        {
            "category":"Personal",
            "subcategory":"Nail Salon",
            "type":"Services"
        }
    ],
    "sg:phone":"+31 70 390 4935",
    "sg:postcode":"2281 CW",
    "sg:province":"Zuid-Holland",
    "sg:tags":[
        "pedicure"
    ],
    "wof:name":"Wijk-De Wit, A M Van",
    "wof:placetype":"venue"
},
  "geometry": {"coordinates":[4.341704,52.056934],"type":"Point"}
}