{
  "type": "Feature",
  "properties": {
    "addr:full":"Rykswg Centrum 39 Geleen Limburg 6161 EC",
    "addr:housenumber":"39",
    "addr:postcode":"6161 ec",
    "addr:street":"Centrum",
    "iso:country":"NL",
    "sg:address":"Rykswg Centrum 39",
    "sg:city":"Geleen",
    "sg:orig_category":"Glas, Porselein En Aardewerk",
    "sg:phone":"+31 46 474 3607",
    "sg:postcode":"6161 EC",
    "sg:province":"Limburg",
    "wof:name":"Tummers, P",
    "wof:placetype":"venue"
},
  "geometry": {"coordinates":[5.830162,50.969151],"type":"Point"}
}