{
  "type": "Feature",
  "properties": {
    "iso:country":"NL",
    "sg:address":"2E Emmastraat 41",
    "sg:city":"Enschede",
    "sg:orig_category":"Huishoudapparatuur, Televisies And Radio'S",
    "sg:phone":"+31 53 434 0288",
    "sg:postcode":"7513 CX",
    "sg:province":"NL.08",
    "wof:name":"Achterhuis Satelliet Communicatie",
    "wof:placetype":"venue"
},
  "geometry": {"coordinates":[6.874745,52.217232],"type":"Point"}
}