{
  "type": "Feature",
  "properties": {
    "addr:full":"W Barentszstr 19 Emmen Drenthe 7825 VZ",
    "addr:housenumber":"19",
    "addr:postcode":"7825 vz",
    "addr:street":"W",
    "iso:country":"NL",
    "sg:address":"W Barentszstr 19",
    "sg:city":"Emmen",
    "sg:classifiers":[
        {
            "category":"Retail",
            "subcategory":"Auto Repair",
            "type":"Services"
        }
    ],
    "sg:phone":"+31 591 316 618",
    "sg:postcode":"7825 VZ",
    "sg:province":"Drenthe",
    "sg:tags":[
        "garage"
    ],
    "wof:name":"Hats",
    "wof:placetype":"venue"
},
  "geometry": {"coordinates":[6.93785,52.748756],"type":"Point"}
}