{
  "type": "Feature",
  "properties": {
    "addr:full":"De Hoeven 40C Haarsteeg Noord-Brabant 5254 JX",
    "addr:housenumber":"40c",
    "addr:postcode":"5254 jx",
    "addr:street":"De Hoeven",
    "iso:country":"NL",
    "sg:address":"De Hoeven 40C",
    "sg:city":"Haarsteeg",
    "sg:orig_category":"Oud Metaal",
    "sg:phone":"+31 73 511 6530",
    "sg:postcode":"5254 JX",
    "sg:province":"Noord-Brabant",
    "wof:name":"Huiskes, J G",
    "wof:placetype":"venue"
},
  "geometry": {"coordinates":[5.1780261993,51.7070274353],"type":"Point"}
}