{
  "type": "Feature",
  "properties": {
    "addr:full":"Monseigneur Feronlaan 1 Hoensbroek Limburg 6433 CD",
    "addr:housenumber":"1",
    "addr:postcode":"6433 cd",
    "addr:street":"Monseigneur Feronlaan",
    "iso:country":"NL",
    "sg:address":"Monseigneur Feronlaan 1",
    "sg:city":"Hoensbroek",
    "sg:classifiers":[
        {
            "category":"Education",
            "subcategory":"Preschool",
            "type":"Public Place"
        }
    ],
    "sg:phone":"+31 45 522 0300",
    "sg:postcode":"6433 CD",
    "sg:province":"Limburg",
    "sg:tags":[
        "kleuteronderwijs",
        "basis-"
    ],
    "wof:name":"Basisschool Dr. Albert Schweitzer",
    "wof:placetype":"venue"
},
  "geometry": {"coordinates":[5.929002,50.917664],"type":"Point"}
}