{
  "type": "Feature",
  "properties": {
    "addr:full":"Ln V Moerkerken 27A Mynsheerenland Zuid-Holland 3271 AH",
    "addr:housenumber":"27a mynsheerenland",
    "addr:postcode":"3271 ah",
    "addr:street":"Ln;Moerkerken",
    "iso:country":"NL",
    "sg:address":"Ln V Moerkerken 27A",
    "sg:city":"Mynsheerenland",
    "sg:orig_category":"Sportverenigingen En Ontspannings- Verenigingen",
    "sg:phone":"+31 186 601 015",
    "sg:postcode":"3271 AH",
    "sg:province":"Zuid-Holland",
    "wof:name":"Eeuwes, Watersportver",
    "wof:placetype":"venue"
},
  "geometry": {"coordinates":[4.492185,51.797523],"type":"Point"}
}