{
  "type": "Feature",
  "properties": {
    "addr:full":"T Hoenstraat 5 'S Gravenhage Zuid-Holland 2596 HX",
    "addr:housenumber":"5 '",
    "addr:postcode":"2596 hx",
    "addr:street":"T Hoenstraat",
    "iso:country":"NL",
    "sg:address":"T Hoenstraat 5",
    "sg:city":"'S Gravenhage",
    "sg:orig_category":"Advocaten And Juridische Adviseurs",
    "sg:phone":"+31 70 346 7472",
    "sg:postcode":"2596 HX",
    "sg:province":"Zuid-Holland",
    "wof:name":"Sjocrona Van Stigt De Roos & Pen Advocaten",
    "wof:placetype":"venue"
},
  "geometry": {"coordinates":[4.309214,52.095364],"type":"Point"}
}