{
  "type": "Feature",
  "properties": {
    "iso:country":"NL",
    "sg:address":"Himmelumerdyk 3",
    "sg:city":"Warns",
    "sg:classifiers":[
        {
            "category":"Education",
            "subcategory":"Preschool",
            "type":"Public Place"
        }
    ],
    "sg:phone":"+31 514 682 050",
    "sg:postcode":"8721 GT",
    "sg:province":"Friesland",
    "sg:tags":[
        "kleuteronderwijs",
        "basis-"
    ],
    "wof:name":"Openbare Basisschool De Totem",
    "wof:placetype":"venue"
},
  "geometry": {"coordinates":[-83.884407,34.997856],"type":"Point"}
}