{
  "type": "Feature",
  "properties": {
    "addr:full":"Arkelstr 108 Gorinchem Zuid-Holland 4201 KH",
    "addr:housenumber":"108",
    "addr:postcode":"gorinchem;4201 kh",
    "iso:country":"NL",
    "sg:address":"Arkelstr 108",
    "sg:city":"Gorinchem",
    "sg:orig_category":"Werving En Selectie",
    "sg:phone":"+31 183 650 420",
    "sg:postcode":"4201 KH",
    "sg:province":"Zuid-Holland",
    "sg:website":"http://www.employmentvision.nl",
    "wof:name":"Employment Vision, Werving & Selectiebureau",
    "wof:placetype":"venue"
},
  "geometry": {"coordinates":[4.9754037857,51.8321075439],"type":"Point"}
}