{
  "type": "Feature",
  "properties": {
    "addr:full":"Wissinkbrinkweg 73 Haaksbergen NL.08 7482 RJ",
    "addr:housenumber":"73;nl.08",
    "addr:postcode":"7482 rj",
    "addr:street":"Wissinkbrinkweg",
    "iso:country":"NL",
    "sg:address":"Wissinkbrinkweg 73",
    "sg:city":"Haaksbergen",
    "sg:orig_category":"Loodgieterswerk, Verwarming And Sanitaire Installaties",
    "sg:phone":"+31 53 572 6434",
    "sg:postcode":"7482 RJ",
    "sg:province":"NL.08",
    "wof:name":"Erik Nijhof Klussenbedrijf",
    "wof:placetype":"venue"
},
  "geometry": {"coordinates":[6.738554,52.177582],"type":"Point"}
}