{
  "type": "Feature",
  "properties": {
    "iso:country":"NL",
    "sg:address":"Gezichtsln 38",
    "sg:city":"Doorn",
    "sg:orig_category":"Administratie- En Boekhoudkantoren",
    "sg:phone":"+31 343 420 050",
    "sg:postcode":"3941 JE",
    "sg:province":"Utrecht",
    "wof:name":"Bewe",
    "wof:placetype":"venue"
},
  "geometry": {"coordinates":[5.346976,52.033321],"type":"Point"}
}