{
  "type": "Feature",
  "properties": {
    "iso:country":"NL",
    "sg:address":"Legmeerdk 226A",
    "sg:city":"Amstelveen",
    "sg:classifiers":[
        {
            "category":"Autos & Motor Vehicles",
            "subcategory":"Automobile Sales",
            "type":"Retail Goods"
        }
    ],
    "sg:phone":"+31 20 647 6264",
    "sg:postcode":"1187 NK",
    "sg:province":"Noord-Holland",
    "sg:tags":[
        "caravan",
        "stalling",
        "-"
    ],
    "sg:website":"http://www.sheltercaravanstalling.nl",
    "wof:name":"Shelter Bv, De",
    "wof:placetype":"venue"
},
  "geometry": {"coordinates":[4.805497,52.271103],"type":"Point"}
}