{
  "type": "Feature",
  "properties": {
    "addr:full":"Beverstr 35 Utrecht Utrecht 3513 AP",
    "addr:housenumber":"35",
    "addr:postcode":"3513 ap",
    "addr:street":"Beverstr",
    "iso:country":"NL",
    "sg:address":"Beverstr 35",
    "sg:city":"Utrecht",
    "sg:orig_category":"Autorijscholen",
    "sg:phone":"+31 6 14480683",
    "sg:postcode":"3513 AP",
    "sg:province":"Utrecht",
    "sg:website":"http://www.rijschool-arikan.nl",
    "wof:name":"Arikan",
    "wof:placetype":"venue"
},
  "geometry": {"coordinates":[5.107485,52.097496],"type":"Point"}
}