{
  "type": "Feature",
  "properties": {
    "addr:full":"Prins Bernhardstraat 7 Silvolde Gelderland 7064 GC",
    "addr:housenumber":"7",
    "addr:postcode":"7064 gc",
    "addr:street":"Prins Bernhardstraat;Gelderland",
    "iso:country":"NL",
    "sg:address":"Prins Bernhardstraat 7",
    "sg:city":"Silvolde",
    "sg:orig_category":"Goederenvervoer Over De Weg",
    "sg:phone":"+31 315 324 383",
    "sg:postcode":"7064 GC",
    "sg:province":"Gelderland",
    "wof:name":"A J M Bieleveldt",
    "wof:placetype":"venue"
},
  "geometry": {"coordinates":[6.381904,51.911125],"type":"Point"}
}