{
  "type": "Feature",
  "properties": {
    "addr:full":"Biesbosch 297 Zwolle Overijssel 8032 VH",
    "addr:housenumber":"297",
    "addr:postcode":"8032 vh",
    "addr:street":"Biesbosch",
    "iso:country":"NL",
    "sg:address":"Biesbosch 297",
    "sg:city":"Zwolle",
    "sg:orig_category":"Binnenhuisarchitecten",
    "sg:phone":"+31 38 453 2753",
    "sg:postcode":"8032 VH",
    "sg:province":"Overijssel",
    "wof:name":"P.G.M. Uil",
    "wof:placetype":"venue"
},
  "geometry": {"coordinates":[6.105815,52.528309],"type":"Point"}
}