{
  "type": "Feature",
  "properties": {
    "addr:full":"Meander 7 Surhuisterveen Groningen 9231 DB",
    "addr:housenumber":"7",
    "addr:postcode":"9231 db",
    "addr:street":"Meander",
    "iso:country":"NL",
    "sg:address":"Meander 7",
    "sg:city":"Surhuisterveen",
    "sg:orig_category":"Verhuur Bouwmachines",
    "sg:phone":"+31 512 364 922",
    "sg:postcode":"9231 DB",
    "sg:province":"Groningen",
    "wof:name":"Demolition Tools Verhuur Bv",
    "wof:placetype":"venue"
},
  "geometry": {"coordinates":[6.18578,53.182053],"type":"Point"}
}