{
  "type": "Feature",
  "properties": {
    "iso:country":"NL",
    "sg:address":"Vlet 35",
    "sg:city":"Werkendam",
    "sg:orig_category":"Non-Classified Establishments",
    "sg:phone":"+31 183 505 693",
    "sg:postcode":"4251 DD",
    "sg:province":"Noord-Brabant",
    "wof:name":"Smits Service, A",
    "wof:placetype":"venue"
},
  "geometry": {"coordinates":[4.899525,51.813828],"type":"Point"}
}