{
  "type": "Feature",
  "properties": {
    "iso:country":"NL",
    "sg:address":"Bruisterbosch 5",
    "sg:city":"St Geertruid",
    "sg:orig_category":"Vakantieverblijven",
    "sg:phone":"+31 43 458 1816",
    "sg:postcode":"6265 NK",
    "sg:province":"Limburg",
    "wof:name":"Schols",
    "wof:placetype":"venue"
},
  "geometry": {"coordinates":[5.803768,50.80558],"type":"Point"}
}