{
  "type": "Feature",
  "properties": {
    "addr:full":"Kalenberg Z 44 Kalenberg Overijssel 8377 HH",
    "addr:housenumber":"44",
    "addr:postcode":"8377 hh",
    "iso:country":"NL",
    "sg:address":"Kalenberg Z 44",
    "sg:city":"Kalenberg",
    "sg:orig_category":"Loonbedrijven",
    "sg:phone":"+31 561 477 579",
    "sg:postcode":"8377 HH",
    "sg:province":"Overijssel",
    "wof:name":"Wagt, S De",
    "wof:placetype":"venue"
},
  "geometry": {"coordinates":[5.9480037689,52.7798156738],"type":"Point"}
}