{
  "type": "Feature",
  "properties": {
    "addr:full":"Bernhardln 1 Puttershoek Zuid-Holland 3297 CB",
    "addr:housenumber":"1",
    "addr:postcode":"3297 cb",
    "addr:street":"Bernhardln",
    "iso:country":"NL",
    "sg:address":"Bernhardln 1",
    "sg:city":"Puttershoek",
    "sg:orig_category":"Woningbouw- Verenigingen En -Stichtingen",
    "sg:phone":"+31 78 676 3088",
    "sg:postcode":"3297 CB",
    "sg:province":"Zuid-Holland",
    "wof:name":"Maashoek, De",
    "wof:placetype":"venue"
},
  "geometry": {"coordinates":[4.5687799454,51.805015564],"type":"Point"}
}