{
  "type": "Feature",
  "properties": {
    "addr:full":"Hofstr 66 Rynsburg South Holland 2231 WX",
    "addr:housenumber":"66",
    "addr:postcode":"2231 wx",
    "addr:street":"Hofstr",
    "iso:country":"NL",
    "sg:address":"Hofstr 66",
    "sg:city":"Rynsburg",
    "sg:orig_category":"Bloemen En Planten",
    "sg:phone":"+31 71 402 5011",
    "sg:postcode":"2231 WX",
    "sg:province":"South Holland",
    "wof:name":"Kromhout Bv, J",
    "wof:placetype":"venue"
},
  "geometry": {"coordinates":[4.440792,52.18959],"type":"Point"}
}