{
  "type": "Feature",
  "properties": {
    "addr:full":"Abberdaan 192 Amsterdam North Holland 1046 AB",
    "addr:housenumber":"192",
    "addr:postcode":"1046 ab",
    "addr:street":"Abberdaan",
    "iso:country":"NL",
    "sg:address":"Abberdaan 192",
    "sg:city":"Amsterdam",
    "sg:orig_category":"Verhuisdiensten",
    "sg:phone":"+31 20 618 5328",
    "sg:postcode":"1046 AB",
    "sg:province":"North Holland",
    "sg:website":"http://www.brusno.nl",
    "wof:name":"Brusno Verhuisservice",
    "wof:placetype":"venue"
},
  "geometry": {"coordinates":[4.785892,52.392029],"type":"Point"}
}