{
  "type": "Feature",
  "properties": {
    "iso:country":"NL",
    "sg:address":"Jhr Mockkd 23",
    "sg:city":"Hillegom",
    "sg:orig_category":"Keukens",
    "sg:phone":"+31 252 519 681",
    "sg:postcode":"2181 AL",
    "sg:province":"Zuid-Holland",
    "sg:website":"http://www.keukengildevanleeuwen.nl",
    "wof:name":"Leeuwen, Keukengilde Van",
    "wof:placetype":"venue"
},
  "geometry": {"coordinates":[4.578603,52.290993],"type":"Point"}
}