{
  "type": "Feature",
  "properties": {
    "addr:full":"Celsiusweg 5 Leeuwarden Provincie Friesland 8912 AM",
    "addr:housenumber":"5",
    "addr:postcode":"8912",
    "addr:street":"Celsiusweg;Provincie Friesland",
    "iso:country":"NL",
    "sg:address":"Celsiusweg 5",
    "sg:city":"Leeuwarden",
    "sg:orig_category":"Partycatering And -Organisatie",
    "sg:phone":"+31 58 213 0058",
    "sg:postcode":"8912 AM",
    "sg:province":"Provincie Friesland",
    "wof:name":"Big Apple",
    "wof:placetype":"venue"
},
  "geometry": {"coordinates":[5.763832,53.193386],"type":"Point"}
}