{
  "type": "Feature",
  "properties": {
    "addr:full":"N Leidsevaart 48 Hillegom Zuid-Holland 2182 NB",
    "addr:housenumber":"48",
    "addr:postcode":"2182 nb",
    "addr:street":"N Leidsevaart",
    "iso:country":"NL",
    "sg:address":"N Leidsevaart 48",
    "sg:city":"Hillegom",
    "sg:orig_category":"Bloemen En Planten - Groothandel",
    "sg:phone":"+31 252 532 149",
    "sg:postcode":"2182 NB",
    "sg:province":"Zuid-Holland",
    "wof:name":"Berkel, Fa L En A Van",
    "wof:placetype":"venue"
},
  "geometry": {"coordinates":[4.576205,52.288052],"type":"Point"}
}