{
  "type": "Feature",
  "properties": {
    "addr:full":"Corbulokd 13 Voorburg Zuid-Holland 2275 VN",
    "addr:housenumber":"13",
    "addr:postcode":"2275 vn",
    "addr:street":"Corbulokd",
    "iso:country":"NL",
    "sg:address":"Corbulokd 13",
    "sg:city":"Voorburg",
    "sg:classifiers":[
        {
            "category":"Professional",
            "subcategory":"Management & Consulting",
            "type":"Services"
        }
    ],
    "sg:phone":"+31 70 399 7353",
    "sg:postcode":"2275 VN",
    "sg:province":"Zuid-Holland",
    "sg:tags":[
        "relation",
        "adviesbureaus",
        "public"
    ],
    "wof:name":"Zakee",
    "wof:placetype":"venue"
},
  "geometry": {"coordinates":[4.353,52.062248],"type":"Point"}
}