{
  "type": "Feature",
  "properties": {
    "addr:full":"N Witsenstr 15 Hs Amsterdam Noord-Holland 1017 ZG",
    "addr:housenumber":"15 hs",
    "addr:postcode":"1017 zg",
    "addr:street":"N",
    "iso:country":"NL",
    "sg:address":"N Witsenstr 15 Hs",
    "sg:city":"Amsterdam",
    "sg:orig_category":"Adviesbureaus",
    "sg:phone":"+31 20 639 0158",
    "sg:postcode":"1017 ZG",
    "sg:province":"Noord-Holland",
    "wof:name":"Dorp, Van",
    "wof:placetype":"venue"
},
  "geometry": {"coordinates":[4.893195,52.373119],"type":"Point"}
}