{
  "type": "Feature",
  "properties": {
    "iso:country":"NL",
    "sg:address":"Sterrekroos 9",
    "sg:city":"Raamsdonksveer",
    "sg:orig_category":"Automaterialen En Gereedschappen",
    "sg:phone":"+31 162 522 967",
    "sg:postcode":"4941 VZ",
    "sg:province":"North Brabant",
    "wof:name":"Jece",
    "wof:placetype":"venue"
},
  "geometry": {"coordinates":[4.883641,51.710724],"type":"Point"}
}