{
  "type": "Feature",
  "properties": {
    "addr:full":"Oosterwg 2B C Heemskerk Noord-Holland 1968 KN",
    "addr:housenumber":"2b c",
    "addr:postcode":"1968 kn",
    "addr:street":"Oosterwg",
    "iso:country":"NL",
    "sg:address":"Oosterwg 2B C",
    "sg:city":"Heemskerk",
    "sg:orig_category":"Verenigingen En Stichtingen",
    "sg:phone":"+31 251 245 265",
    "sg:postcode":"1968 KN",
    "sg:province":"Noord-Holland",
    "wof:name":"Heemshof",
    "wof:placetype":"venue"
},
  "geometry": {"coordinates":[4.66983,52.513546],"type":"Point"}
}