{
  "type": "Feature",
  "properties": {
    "addr:full":"Smeepoortstraat 14 Harderwijk Gelderland 3841 EJ",
    "addr:housenumber":"14",
    "addr:postcode":"3841 ej",
    "addr:street":"Smeepoortstraat;Gelderland",
    "iso:country":"NL",
    "sg:address":"Smeepoortstraat 14",
    "sg:city":"Harderwijk",
    "sg:orig_category":"Werving And Selectie Van Tijdelijk Personeel And Uitzendkantoren",
    "sg:phone":"+31 341 433 009",
    "sg:postcode":"3841 EJ",
    "sg:province":"Gelderland",
    "wof:name":"Manpower Uitzendorganisatie Bv",
    "wof:placetype":"venue"
},
  "geometry": {"coordinates":[5.6161122322,52.3475151062],"type":"Point"}
}