{
  "type": "Feature",
  "properties": {
    "addr:full":"Industriepark 6 Zelhem Gelderland 7021 BL",
    "addr:housenumber":"6",
    "addr:postcode":"7021 bl",
    "addr:street":"Industriepark;Gelderland",
    "iso:country":"NL",
    "sg:address":"Industriepark 6",
    "sg:city":"Zelhem",
    "sg:orig_category":"Geluidsopnamen",
    "sg:phone":"+31 314 623 002",
    "sg:postcode":"7021 BL",
    "sg:province":"Gelderland",
    "wof:name":"Commodore",
    "wof:placetype":"venue"
},
  "geometry": {"coordinates":[6.348391,52.000828],"type":"Point"}
}