{
  "type": "Feature",
  "properties": {
    "iso:country":"NL",
    "sg:address":"Om 'T Wedde 7",
    "sg:city":"Montfoort",
    "sg:orig_category":"Schoenen - Reparaties",
    "sg:phone":"+31 348 471 310",
    "sg:postcode":"3417 HH",
    "sg:province":"Utrecht",
    "wof:name":"Gecroonde Leersse",
    "wof:placetype":"venue"
},
  "geometry": {"coordinates":[4.946692,52.044582],"type":"Point"}
}