{
  "type": "Feature",
  "properties": {
    "addr:full":"Oude Utrechtsewg 8 Baarn Utrecht 3743 KN",
    "addr:housenumber":"8",
    "addr:postcode":"3743 kn",
    "addr:street":"Oude Utrechtsewg",
    "iso:country":"NL",
    "sg:address":"Oude Utrechtsewg 8",
    "sg:city":"Baarn",
    "sg:orig_category":"Artsen - Huisartsen",
    "sg:phone":"+31 35 542 0219",
    "sg:postcode":"3743 KN",
    "sg:province":"Utrecht",
    "wof:name":"Doyer, A D",
    "wof:placetype":"venue"
},
  "geometry": {"coordinates":[5.281819,52.211006],"type":"Point"}
}