{
  "type": "Feature",
  "properties": {
    "addr:full":"Dorpsstr 55 Holten NL.08 7451 BS",
    "addr:housenumber":"55;nl.08",
    "addr:postcode":"7451 bs",
    "addr:street":"Dorpsstr",
    "iso:country":"NL",
    "sg:address":"Dorpsstr 55",
    "sg:city":"Holten",
    "sg:orig_category":"Loodgieters",
    "sg:phone":"+31 548 361 901",
    "sg:postcode":"7451 BS",
    "sg:province":"NL.08",
    "wof:name":"Zon Bv, Van",
    "wof:placetype":"venue"
},
  "geometry": {"coordinates":[6.418254,52.282982],"type":"Point"}
}