{
  "type": "Feature",
  "properties": {
    "addr:full":"Passage 5 Nieuwegein Utrecht 3431 LM",
    "addr:housenumber":"5",
    "addr:postcode":"3431 lm",
    "addr:street":"Passage",
    "iso:country":"NL",
    "sg:address":"Passage 5",
    "sg:city":"Nieuwegein",
    "sg:classifiers":[
        {
            "category":"Shopping",
            "subcategory":"Adult",
            "type":"Retail Goods"
        }
    ],
    "sg:phone":"+31 30 630 1002",
    "sg:postcode":"3431 LM",
    "sg:province":"Utrecht",
    "sg:tags":[
        "lingerie",
        "en",
        "tricotage"
    ],
    "wof:name":"Hunkem\u00f6ller",
    "wof:placetype":"venue"
},
  "geometry": {"coordinates":[5.083833,52.028786],"type":"Point"}
}