{
  "type": "Feature",
  "properties": {
    "iso:country":"NL",
    "sg:address":"Weidelaan 18",
    "sg:city":"Raalte",
    "sg:orig_category":"Kinderopvang Behalve Thuis",
    "sg:phone":"+31 572 355 494",
    "sg:postcode":"8103 NA",
    "sg:province":"NL.08",
    "wof:name":"Kindercreche",
    "wof:placetype":"venue"
},
  "geometry": {"coordinates":[6.286999,52.391602],"type":"Point"}
}