{
  "type": "Feature",
  "properties": {
    "iso:country":"NL",
    "sg:address":"Zuidplein Hoog 422",
    "sg:city":"Rotterdam",
    "sg:orig_category":"Boekhandels",
    "sg:phone":"+31 10 481 3928",
    "sg:postcode":"3083 BL",
    "sg:province":"Zuid-Holland",
    "wof:name":"Lektuurshop Populair",
    "wof:placetype":"venue"
},
  "geometry": {"coordinates":[4.489889,51.887039],"type":"Point"}
}