{
  "type": "Feature",
  "properties": {
    "iso:country":"NL",
    "sg:address":"Annastraat 15",
    "sg:city":"Geleen",
    "sg:orig_category":"Bloemen And Planten",
    "sg:phone":"+31 46 474 2684",
    "sg:postcode":"6161  G",
    "sg:province":"Limburg",
    "wof:name":"Arnold'S Bloemen",
    "wof:placetype":"venue"
},
  "geometry": {"coordinates":[5.82661,50.971127],"type":"Point"}
}