{
  "type": "Feature",
  "properties": {
    "addr:full":"Annastraat 15 Geleen Limburg 6161  G",
    "addr:housenumber":"15;6161 g",
    "addr:street":"Annastraat",
    "iso:country":"NL",
    "sg:address":"Annastraat 15",
    "sg:city":"Geleen",
    "sg:orig_category":"Bloemen And Planten",
    "sg:phone":"+31 46 474 2684",
    "sg:postcode":"6161  G",
    "sg:province":"Limburg",
    "wof:name":"Arnold'S Bloemen",
    "wof:placetype":"venue"
},
  "geometry": {"coordinates":[5.82661,50.971127],"type":"Point"}
}