{
  "type": "Feature",
  "properties": {
    "iso:country":"NL",
    "sg:address":"L Vore 28",
    "sg:city":"Bavel",
    "sg:orig_category":"Verzekeringen - Verzekeringskantoren",
    "sg:phone":"+31 161 432 530",
    "sg:postcode":"4854 CJ",
    "sg:province":"Noord-Brabant",
    "wof:name":"Made, Herman Van Der",
    "wof:placetype":"venue"
},
  "geometry": {"coordinates":[4.833336,51.565414],"type":"Point"}
}