{
  "type": "Feature",
  "properties": {
    "addr:full":"De Mors 37 Ootmarsum Overijssel 7631 AH",
    "addr:housenumber":"37",
    "addr:postcode":"7631 ah",
    "addr:street":"De Mors",
    "iso:country":"NL",
    "sg:address":"De Mors 37",
    "sg:city":"Ootmarsum",
    "sg:orig_category":"Bloemisterijartikelen - Fabrieken En Groothandel",
    "sg:phone":"+31 541 292 438",
    "sg:postcode":"7631 AH",
    "sg:province":"Overijssel",
    "sg:website":"HTTP://www.othmar.nl",
    "wof:name":"Othmar Trading Bv",
    "wof:placetype":"venue"
},
  "geometry": {"coordinates":[6.903965,52.411903],"type":"Point"}
}