{
  "type": "Feature",
  "properties": {
    "addr:full":"Ravenswade 116 Nieuwegein Utrecht 3439 LD",
    "addr:housenumber":"116",
    "addr:postcode":"3439 ld",
    "addr:street":"Ravenswade",
    "iso:country":"NL",
    "sg:address":"Ravenswade 116",
    "sg:city":"Nieuwegein",
    "sg:orig_category":"Diverse Bedrijfsinstallaties Gh",
    "sg:phone":"+31 30 288 5626",
    "sg:postcode":"3439 LD",
    "sg:province":"Utrecht",
    "wof:name":"Tramat Bv",
    "wof:placetype":"venue"
},
  "geometry": {"coordinates":[5.116699,52.053345],"type":"Point"}
}