{
  "type": "Feature",
  "properties": {
    "addr:full":"Steenweg 12 Roermond Limburg 6041 EW",
    "addr:housenumber":"12",
    "addr:postcode":"6041 ew",
    "addr:street":"Steenweg",
    "iso:country":"NL",
    "sg:address":"Steenweg 12",
    "sg:city":"Roermond",
    "sg:orig_category":"Juweliers",
    "sg:phone":"+31 475 420 055",
    "sg:postcode":"6041 EW",
    "sg:province":"Limburg",
    "wof:name":"Juwelier Ton Rijken",
    "wof:placetype":"venue"
},
  "geometry": {"coordinates":[5.986722,51.19408],"type":"Point"}
}