{
  "type": "Feature",
  "properties": {
    "addr:full":"Nieuwstraat 34 Kamperland Zeeland 4493 BE",
    "addr:housenumber":"34",
    "addr:postcode":"4493",
    "addr:street":"Nieuwstraat",
    "iso:country":"NL",
    "sg:address":"Nieuwstraat 34",
    "sg:city":"Kamperland",
    "sg:classifiers":[
        {
            "category":"Education",
            "subcategory":"Preschool",
            "type":"Public Place"
        }
    ],
    "sg:phone":"+31 113 371 224",
    "sg:postcode":"4493 BE",
    "sg:province":"Zeeland",
    "sg:tags":[
        "kleuteronderwijs",
        "basis-"
    ],
    "wof:name":"Peuterspeelzaal De Peut",
    "wof:placetype":"venue"
},
  "geometry": {"coordinates":[3.7053070068,51.5714530945],"type":"Point"}
}