{
  "type": "Feature",
  "properties": {
    "iso:country":"NL",
    "sg:address":"Kleiwg 80",
    "sg:city":"Gouda",
    "sg:orig_category":"Juweliers",
    "sg:phone":"+31 182 524 115",
    "sg:postcode":"2801 GJ",
    "sg:province":"Zuid-Holland",
    "wof:name":"Peltenburg",
    "wof:placetype":"venue"
},
  "geometry": {"coordinates":[4.709757,52.014233],"type":"Point"}
}