{
  "type": "Feature",
  "properties": {
    "addr:full":"A Vd Leeuwstr 51 Weesp North Holland 1382 TM",
    "addr:housenumber":"51",
    "addr:postcode":"1382 tm",
    "addr:street":"A",
    "iso:country":"NL",
    "sg:address":"A Vd Leeuwstr 51",
    "sg:city":"Weesp",
    "sg:orig_category":"Horecabenodigdheden",
    "sg:phone":"+31 294 414 429",
    "sg:postcode":"1382 TM",
    "sg:province":"North Holland",
    "wof:name":"Meesters",
    "wof:placetype":"venue"
},
  "geometry": {"coordinates":[5.0405731201,52.3130760193],"type":"Point"}
}