{
  "type": "Feature",
  "properties": {
    "addr:full":"Leimuiderdijk 290 Burgerveen Noord-Holland 2154 MR",
    "addr:housenumber":"290",
    "addr:postcode":"2154 mr",
    "addr:street":"Leimuiderdijk",
    "iso:country":"NL",
    "sg:address":"Leimuiderdijk 290",
    "sg:city":"Burgerveen",
    "sg:orig_category":"Alternatieve Geneeskunde",
    "sg:phone":"+31 172 507 163",
    "sg:postcode":"2154 MR",
    "sg:province":"Noord-Holland",
    "wof:name":"B&N Food Products",
    "wof:placetype":"venue"
},
  "geometry": {"coordinates":[4.679624,52.238636],"type":"Point"}
}