{
  "type": "Feature",
  "properties": {
    "iso:country":"NL",
    "sg:address":"Driemanssteeweg 60",
    "sg:city":"Rotterdam",
    "sg:orig_category":"Bedrijfsinventaris Gh",
    "sg:phone":"+31 10 210 0999",
    "sg:postcode":"3084 CB",
    "sg:province":"South Holland",
    "wof:name":"Grenco Transportkoeling Bv",
    "wof:placetype":"venue"
},
  "geometry": {"coordinates":[4.454222,51.865242],"type":"Point"}
}