{
  "type": "Feature",
  "properties": {
    "iso:country":"NL",
    "sg:address":"Van Limburg Stirumplein 6",
    "sg:city":"Brummen",
    "sg:classifiers":[
        {
            "category":"Education",
            "subcategory":"Preschool",
            "type":"Public Place"
        }
    ],
    "sg:phone":"+31 575 561 608",
    "sg:postcode":"6971 CE",
    "sg:province":"Gelderland",
    "sg:tags":[
        "kleuteronderwijs",
        "basis-"
    ],
    "wof:name":"Koningin Juliana School",
    "wof:placetype":"venue"
},
  "geometry": {"coordinates":[6.153922,52.089012],"type":"Point"}
}