{
  "type": "Feature",
  "properties": {
    "addr:full":"Stationsln 29 Nunspeet Gelderland 8071 CJ",
    "addr:housenumber":"29",
    "addr:postcode":"8071 cj",
    "addr:street":"Stationsln;Gelderland",
    "iso:country":"NL",
    "sg:address":"Stationsln 29",
    "sg:city":"Nunspeet",
    "sg:orig_category":"Meubelen",
    "sg:phone":"+31 341 253 432",
    "sg:postcode":"8071 CJ",
    "sg:province":"Gelderland",
    "wof:name":"Naturel Wonen",
    "wof:placetype":"venue"
},
  "geometry": {"coordinates":[5.772205,52.374981],"type":"Point"}
}