{
  "type": "Feature",
  "properties": {
    "addr:full":"Haaksbergerwg 17 Haaksbergen Overijssel 7481 RR",
    "addr:housenumber":"17",
    "addr:postcode":"7481 rr",
    "addr:street":"Haaksbergerwg",
    "iso:country":"NL",
    "sg:address":"Haaksbergerwg 17",
    "sg:city":"Haaksbergen",
    "sg:orig_category":"Land- En Tuinbouw - Mechanisatie",
    "sg:phone":"+31 53 569 6331",
    "sg:postcode":"7481 RR",
    "sg:province":"Overijssel",
    "wof:name":"Scholten",
    "wof:placetype":"venue"
},
  "geometry": {"coordinates":[6.813071,52.143505],"type":"Point"}
}