{
  "type": "Feature",
  "properties": {
    "addr:full":"Steijnln 74A Zeist Utrecht 3701 EJ",
    "addr:housenumber":"74a",
    "addr:postcode":"3701 ej",
    "addr:street":"Steijnln",
    "iso:country":"NL",
    "sg:address":"Steijnln 74A",
    "sg:city":"Zeist",
    "sg:orig_category":"Fietsen En Bromfietsen",
    "sg:phone":"+31 30 692 0578",
    "sg:postcode":"3701 EJ",
    "sg:province":"Utrecht",
    "wof:name":"Cyclorama Vof",
    "wof:placetype":"venue"
},
  "geometry": {"coordinates":[5.24387,52.08548],"type":"Point"}
}