{
  "type": "Feature",
  "properties": {
    "iso:country":"NL",
    "sg:address":"Zoutkaag 6",
    "sg:city":"Lutjewinkel",
    "sg:orig_category":"Voegwerken",
    "sg:phone":"+31 6 53763522",
    "sg:postcode":"1732 LW",
    "sg:province":"North Holland",
    "wof:name":"Dijk, Remco Van",
    "wof:placetype":"venue"
},
  "geometry": {"coordinates":[4.877732,52.77726],"type":"Point"}
}