{
  "type": "Feature",
  "properties": {
    "iso:country":"NL",
    "sg:address":"Jan Evertsenstraat 64",
    "sg:city":"Amsterdam",
    "sg:classifiers":[
        {
            "category":"Fast Food",
            "type":"Food & Drink"
        }
    ],
    "sg:phone":"+31 20 689 2574",
    "sg:postcode":"1056 ED",
    "sg:province":"Noord-Holland",
    "sg:tags":[
        "afhaal",
        "restaurant"
    ],
    "wof:name":"Snackbar Ufuk",
    "wof:placetype":"venue"
},
  "geometry": {"coordinates":[4.855458,52.37112],"type":"Point"}
}