{
  "type": "Feature",
  "properties": {
    "iso:country":"NL",
    "sg:address":"Zeeburgerdk 35",
    "sg:city":"Amsterdam",
    "sg:orig_category":"Adviesbureaus Economie",
    "sg:phone":"+31 20 692 0039",
    "sg:postcode":"1093 SL",
    "sg:province":"North Holland",
    "wof:name":"Deus Ex Machina Bv",
    "wof:placetype":"venue"
},
  "geometry": {"coordinates":[4.930355,52.366173],"type":"Point"}
}