{
  "type": "Feature",
  "properties": {
    "iso:country":"NL",
    "sg:address":"Jaagmeent 35-36",
    "sg:city":"Almere",
    "sg:orig_category":"Kinderopvang Behalve Thuis",
    "sg:phone":"+31 36 531 9742",
    "sg:postcode":"1356 AD",
    "sg:province":"Flevoland",
    "wof:name":"Kans 2 Ska Buitenschoolse Opvang",
    "wof:placetype":"venue"
},
  "geometry": {"coordinates":[5.234687,52.336807],"type":"Point"}
}