{
  "type": "Feature",
  "properties": {
    "addr:full":"Jaagmeent 35-36 Almere Flevoland 1356 AD",
    "addr:housenumber":"35-36",
    "addr:postcode":"1356 ad",
    "addr:street":"Jaagmeent;Flevoland",
    "iso:country":"NL",
    "sg:address":"Jaagmeent 35-36",
    "sg:city":"Almere",
    "sg:orig_category":"Kinderopvang Behalve Thuis",
    "sg:phone":"+31 36 531 9742",
    "sg:postcode":"1356 AD",
    "sg:province":"Flevoland",
    "wof:name":"Kans 2 Ska Buitenschoolse Opvang",
    "wof:placetype":"venue"
},
  "geometry": {"coordinates":[5.234687,52.336807],"type":"Point"}
}