{
  "type": "Feature",
  "properties": {
    "addr:full":"Steentilstr 25A Groningen Groningen 9711 GK",
    "addr:housenumber":"25a",
    "addr:postcode":"9711 gk",
    "addr:street":"Steentilstr",
    "iso:country":"NL",
    "sg:address":"Steentilstr 25A",
    "sg:city":"Groningen",
    "sg:orig_category":"Modellenbureaus En Modellen Freelance",
    "sg:phone":"+31 50 313 2212",
    "sg:postcode":"9711 GK",
    "sg:province":"Groningen",
    "wof:name":"Capelli Models",
    "wof:placetype":"venue"
},
  "geometry": {"coordinates":[6.572635,53.216412],"type":"Point"}
}