{
  "type": "Feature",
  "properties": {
    "addr:full":"Haagbeukweg 93 Almere NL. 1326 AV",
    "addr:housenumber":"93",
    "addr:postcode":"1326 av",
    "addr:street":"Haagbeukweg;Nl.",
    "iso:country":"NL",
    "sg:address":"Haagbeukweg 93",
    "sg:city":"Almere",
    "sg:orig_category":"Boekhouders",
    "sg:phone":"+31 36 537 9289",
    "sg:postcode":"1326 AV",
    "sg:province":"NL.",
    "wof:name":"M.C.J. Neering",
    "wof:placetype":"venue"
},
  "geometry": {"coordinates":[5.243078,52.374214],"type":"Point"}
}