{
  "type": "Feature",
  "properties": {
    "addr:full":"Ouvertureweg 127 Alphen A/D Rijn Zuid-Holland 2402 DX",
    "addr:housenumber":"127;2402",
    "addr:postcode":"dx",
    "addr:street":"Ouvertureweg",
    "iso:country":"NL",
    "sg:address":"Ouvertureweg 127",
    "sg:city":"Alphen A/D Rijn",
    "sg:orig_category":"Kappers",
    "sg:phone":"+31 172 420 039",
    "sg:postcode":"2402 DX",
    "sg:province":"Zuid-Holland",
    "wof:name":"Fast Hair Fashion",
    "wof:placetype":"venue"
},
  "geometry": {"coordinates":[4.6606421471,52.1495857239],"type":"Point"}
}