{
  "type": "Feature",
  "properties": {
    "iso:country":"NL",
    "sg:address":"Beekstraat 11",
    "sg:city":"Arnhem",
    "sg:classifiers":[
        {
            "category":"Bars & Pubs",
            "type":"Food & Drink"
        }
    ],
    "sg:phone":"+31 26 351 5397",
    "sg:postcode":"6811 DV",
    "sg:province":"Gelderland",
    "wof:name":"Upstairs Happy Smoking",
    "wof:placetype":"venue"
},
  "geometry": {"coordinates":[5.91224,51.980286],"type":"Point"}
}