{
  "type": "Feature",
  "properties": {
    "iso:country":"NL",
    "sg:address":"Dorpsstraat 196",
    "sg:city":"Zevenhuizen Zh",
    "sg:orig_category":"Artsen And Specialisten",
    "sg:phone":"+31 180 631 204",
    "sg:postcode":"2761 AJ",
    "sg:province":"Zuid-Holland",
    "wof:name":"C.W. Onderwater",
    "wof:placetype":"venue"
},
  "geometry": {"coordinates":[4.580586,52.01321],"type":"Point"}
}