{
  "type": "Feature",
  "properties": {
    "addr:full":"Hoogoorddreef 5 Amsterdam Zuidoost Noord-Holland 1101 BA",
    "addr:housenumber":"5",
    "addr:postcode":"zuidoost;1101 ba",
    "addr:street":"Hoogoorddreef",
    "iso:country":"NL",
    "sg:address":"Hoogoorddreef 5",
    "sg:city":"Amsterdam Zuidoost",
    "sg:orig_category":"Onderwijsmateriaal",
    "sg:phone":"+31 20 430 9190",
    "sg:postcode":"1101 BA",
    "sg:province":"Noord-Holland",
    "sg:website":"http://www.krantindeklas.nl",
    "wof:name":"Kik Krant In De Klas, Sticht",
    "wof:placetype":"venue"
},
  "geometry": {"coordinates":[4.947029,52.308937],"type":"Point"}
}