{
  "type": "Feature",
  "properties": {
    "iso:country":"NL",
    "sg:address":"Hoofdweg 75",
    "sg:city":"Huizen",
    "sg:orig_category":"Paramedische Behandelingen",
    "sg:phone":"+31 35 526 7795",
    "sg:postcode":"1275 AA",
    "sg:province":"North Holland",
    "wof:name":"J.A. Schipper",
    "wof:placetype":"venue"
},
  "geometry": {"coordinates":[5.265786,52.290718],"type":"Point"}
}