{
  "type": "Feature",
  "properties": {
    "addr:full":"V Dusseldorpstr 78 Goes Zeeland 4461 LV",
    "addr:housenumber":"78",
    "addr:postcode":"4461",
    "addr:street":"V Dusseldorpstr",
    "iso:country":"NL",
    "sg:address":"V Dusseldorpstr 78",
    "sg:city":"Goes",
    "sg:orig_category":"Scholen Voor Algemeen Voortgezet Onderwijs",
    "sg:phone":"+31 113 216 971",
    "sg:postcode":"4461 LV",
    "sg:province":"Zeeland",
    "wof:name":"Pontes",
    "wof:placetype":"venue"
},
  "geometry": {"coordinates":[-83.914169,39.768833],"type":"Point"}
}