{
  "type": "Feature",
  "properties": {
    "iso:country":"NL",
    "sg:address":"Bruinjoost 5",
    "sg:city":"Kortenhoef",
    "sg:orig_category":"Boekhouders",
    "sg:phone":"+31 35 656 4849",
    "sg:postcode":"1241 HN",
    "sg:province":"North Holland",
    "wof:name":"Hfs",
    "wof:placetype":"venue"
},
  "geometry": {"coordinates":[5.113462,52.23735],"type":"Point"}
}