{
  "type": "Feature",
  "properties": {
    "addr:full":"Rustenburgerln 115 Haarlem Noord-Holland 2012 AM",
    "addr:housenumber":"115",
    "addr:postcode":"2012",
    "iso:country":"NL",
    "sg:address":"Rustenburgerln 115",
    "sg:city":"Haarlem",
    "sg:orig_category":"Onderhoudswerken",
    "sg:phone":"+31 23 531 2920",
    "sg:postcode":"2012 AM",
    "sg:province":"Noord-Holland",
    "wof:name":"Helpende Hand, De",
    "wof:placetype":"venue"
},
  "geometry": {"coordinates":[4.63888,52.372066],"type":"Point"}
}