{
  "type": "Feature",
  "properties": {
    "addr:full":"Postbus 79 Beneden Leeuwen Gelderland 6658 ZH",
    "addr:housenumber":"79",
    "addr:postcode":"6658 zh",
    "addr:street":"Postbus",
    "iso:country":"NL",
    "sg:address":"Postbus 79",
    "sg:city":"Beneden Leeuwen",
    "sg:orig_category":"Belastingconsulenten/ Belastingadviseurs",
    "sg:phone":"+31 487 502 171",
    "sg:postcode":"6658 ZH",
    "sg:province":"Gelderland",
    "wof:name":"Croonen",
    "wof:placetype":"venue"
},
  "geometry": {"coordinates":[5.51556,51.882225],"type":"Point"}
}