{
  "type": "Feature",
  "properties": {
    "iso:country":"NL",
    "sg:address":"Geldersestraat 29",
    "sg:city":"Geldermalsen",
    "sg:orig_category":"Schoenen",
    "sg:phone":"+31 345 575 411",
    "sg:postcode":"4191 BA",
    "sg:province":"Gelderland",
    "wof:name":"Arbell Schoenen",
    "wof:placetype":"venue"
},
  "geometry": {"coordinates":[5.292224,51.882725],"type":"Point"}
}