{
  "type": "Feature",
  "properties": {
    "addr:full":"Zonneoordlaan 7 Ede Gld Gelderland 6718 TK",
    "addr:housenumber":"7",
    "addr:postcode":"6718 tk",
    "addr:street":"Zonneoordlaan;Gld Gelderland",
    "iso:country":"NL",
    "sg:address":"Zonneoordlaan 7",
    "sg:city":"Ede Gld",
    "sg:orig_category":"Bloemen And Planten",
    "sg:phone":"+31 318 613 081",
    "sg:postcode":"6718 TK",
    "sg:province":"Gelderland",
    "wof:name":"Tuincentrum J. Brouwer",
    "wof:placetype":"venue"
},
  "geometry": {"coordinates":[5.643243,52.059071],"type":"Point"}
}