{
  "type": "Feature",
  "properties": {
    "iso:country":"NL",
    "sg:address":"Singellaan 8",
    "sg:city":"Siddeburen",
    "sg:orig_category":"Huishoudapparatuur, Televisies And Radio'S",
    "sg:phone":"+31 598 432 692",
    "sg:postcode":"9628 AL",
    "sg:province":"Groningen",
    "wof:name":"Sky Light",
    "wof:placetype":"venue"
},
  "geometry": {"coordinates":[6.871247,53.248169],"type":"Point"}
}