{
  "type": "Feature",
  "properties": {
    "iso:country":"NL",
    "sg:address":"Marktstr 19",
    "sg:city":"Naarden",
    "sg:orig_category":"Boeken En Tijdschriften",
    "sg:phone":"+31 35 694 8484",
    "sg:postcode":"1411 CX",
    "sg:province":"North Holland",
    "wof:name":"Comenius",
    "wof:placetype":"venue"
},
  "geometry": {"coordinates":[5.162875,52.295956],"type":"Point"}
}