{
  "type": "Feature",
  "properties": {
    "iso:country":"NL",
    "sg:address":"Oostveenwg 26",
    "sg:city":"Enschede",
    "sg:orig_category":"Homeopathie",
    "sg:phone":"+31 53 431 7772",
    "sg:postcode":"7533 VV",
    "sg:province":"Overijssel",
    "wof:name":"Ast B L, Van",
    "wof:placetype":"venue"
},
  "geometry": {"coordinates":[6.915196,52.223438],"type":"Point"}
}