{
  "type": "Feature",
  "properties": {
    "addr:full":"Floryn 45 Hoorn Nh Noord-Holland 1628 RK",
    "addr:housenumber":"45",
    "addr:postcode":"1628 rk",
    "addr:street":"Floryn",
    "iso:country":"NL",
    "sg:address":"Floryn 45",
    "sg:city":"Hoorn Nh",
    "sg:orig_category":"Adviesbureaus Bedrijfsorganisatie",
    "sg:phone":"+31 229 218 301",
    "sg:postcode":"1628 RK",
    "sg:province":"Noord-Holland",
    "sg:website":"http://www.florijnen.nl",
    "wof:name":"Florijnen, De",
    "wof:placetype":"venue"
},
  "geometry": {"coordinates":[5.09426,52.654202],"type":"Point"}
}