{
  "type": "Feature",
  "properties": {
    "addr:full":"Vorstmanstraat 4 Enschede Overijssel 7545 SB",
    "addr:housenumber":"4",
    "addr:postcode":"7545 sb",
    "addr:street":"Vorstmanstraat",
    "iso:country":"NL",
    "sg:address":"Vorstmanstraat 4",
    "sg:city":"Enschede",
    "sg:orig_category":"Metaalwerken",
    "sg:phone":"+31 53 436 0468",
    "sg:postcode":"7545 SB",
    "sg:province":"Overijssel",
    "wof:name":"Samen Bouwen",
    "wof:placetype":"venue"
},
  "geometry": {"coordinates":[6.873764,52.216488],"type":"Point"}
}