{
  "type": "Feature",
  "properties": {
    "addr:full":"Leemkuilen 61 Best Texas 5683 BS",
    "addr:housenumber":"61",
    "addr:postcode":"5683 bs",
    "addr:street":"Leemkuilen",
    "iso:country":"NL",
    "sg:address":"Leemkuilen 61",
    "sg:city":"Best",
    "sg:orig_category":"Peuterspeelzalen",
    "sg:phone":"+31 499 373 730",
    "sg:postcode":"5683 BS",
    "sg:province":"Texas",
    "wof:name":"Bam Bam",
    "wof:placetype":"venue"
},
  "geometry": {"coordinates":[-101.618134,31.224251],"type":"Point"}
}