{
  "type": "Feature",
  "properties": {
    "iso:country":"NL",
    "sg:address":"Jan Teunisstraat 1",
    "sg:city":"Oudenbosch",
    "sg:orig_category":"Technische Studies And Onderzoek",
    "sg:phone":"+31 165 312 714",
    "sg:postcode":"4731 SN",
    "sg:province":"Noord-Brabant",
    "wof:name":"Tks Adviesburo Bv",
    "wof:placetype":"venue"
},
  "geometry": {"coordinates":[4.548719,51.581352],"type":"Point"}
}