{
  "type": "Feature",
  "properties": {
    "addr:full":"V Heeksbleekln 68 Enschede Overijssel 7522 LB",
    "addr:housenumber":"68",
    "addr:postcode":"7522 lb",
    "iso:country":"NL",
    "sg:address":"V Heeksbleekln 68",
    "sg:city":"Enschede",
    "sg:orig_category":"Natuur- En Milieuorganisaties",
    "sg:phone":"+31 53 435 1825",
    "sg:postcode":"7522 LB",
    "sg:province":"Overijssel",
    "wof:name":"Lammerinksw\u00f7Nner, 'T",
    "wof:placetype":"venue"
},
  "geometry": {"coordinates":[6.85852,52.25145],"type":"Point"}
}