{
  "type": "Feature",
  "properties": {
    "iso:country":"NL",
    "sg:address":"Sloterkade 58",
    "sg:city":"Amsterdam",
    "sg:orig_category":"Metaalafval, Schrootrecycling And Sloperijen",
    "sg:phone":"+31 20 615 7942",
    "sg:postcode":"1058 HG",
    "sg:province":"Noord-Holland",
    "wof:name":"Pieter Koorn & Zn",
    "wof:placetype":"venue"
},
  "geometry": {"coordinates":[4.853136,52.355179],"type":"Point"}
}