{
  "type": "Feature",
  "properties": {
    "iso:country":"NL",
    "sg:address":"Sluitdk 4",
    "sg:city":"Lochem",
    "sg:orig_category":"Golfbanen",
    "sg:phone":"+31 573 254 323",
    "sg:postcode":"7241 RR",
    "sg:province":"Gelderland",
    "sg:website":"HTTP://www.lochemsegolfclub.nl",
    "wof:name":"Graafschap Lochemse Golf & Countryclub, De",
    "wof:placetype":"venue"
},
  "geometry": {"coordinates":[6.361774,52.136566],"type":"Point"}
}