{
  "type": "Feature",
  "properties": {
    "addr:full":"Weteringdk 18 Epe Gelderland 8161 SE",
    "addr:housenumber":"18",
    "addr:postcode":"8161",
    "addr:street":"Weteringdk;Gelderland;Se",
    "iso:country":"NL",
    "sg:address":"Weteringdk 18",
    "sg:city":"Epe",
    "sg:orig_category":"Werving En Selectie",
    "sg:phone":"+31 578 560 705",
    "sg:postcode":"8161 SE",
    "sg:province":"Gelderland",
    "sg:website":"http://www.interimnow.nl",
    "wof:name":"Interimnow",
    "wof:placetype":"venue"
},
  "geometry": {"coordinates":[6.0298681259,52.3230247498],"type":"Point"}
}