{
  "type": "Feature",
  "properties": {
    "addr:full":"Heerewg 126 Schoorl Noord-Holland 1871 EL",
    "addr:housenumber":"126",
    "addr:postcode":"1871 el",
    "iso:country":"NL",
    "sg:address":"Heerewg 126",
    "sg:city":"Schoorl",
    "sg:orig_category":"Bedrijfsopleidingen",
    "sg:phone":"+31 72 509 4104",
    "sg:postcode":"1871 EL",
    "sg:province":"Noord-Holland",
    "wof:name":"Lugthart Vof",
    "wof:placetype":"venue"
},
  "geometry": {"coordinates":[4.687889,52.711754],"type":"Point"}
}