{
  "type": "Feature",
  "properties": {
    "iso:country":"NL",
    "sg:address":"Zilverenberg 46",
    "sg:city":"S Hertogenbosch",
    "sg:orig_category":"Machineonderhoud En -Reparatie",
    "sg:phone":"+31 73 640 6800",
    "sg:postcode":"5234 GM",
    "sg:province":"North Brabant",
    "wof:name":"Numac Bv",
    "wof:placetype":"venue"
},
  "geometry": {"coordinates":[5.285457,51.725319],"type":"Point"}
}