{
  "type": "Feature",
  "properties": {
    "addr:full":"Rielsedijk 3 Geldrop Noord-Brabant 5663 PJ",
    "addr:housenumber":"3",
    "addr:postcode":"5663 pj",
    "addr:street":"Rielsedijk",
    "iso:country":"NL",
    "sg:address":"Rielsedijk 3",
    "sg:city":"Geldrop",
    "sg:orig_category":"Verzekeringen",
    "sg:phone":"+31 40 286 0950",
    "sg:postcode":"5663 PJ",
    "sg:province":"Noord-Brabant",
    "wof:name":"Van Os/Sauter/Verheijden",
    "wof:placetype":"venue"
},
  "geometry": {"coordinates":[5.5395669937,51.4197654724],"type":"Point"}
}