{
  "type": "Feature",
  "properties": {
    "iso:country":"NL",
    "sg:address":"Groenmarkt 11",
    "sg:city":"Zutphen",
    "sg:orig_category":"Glaszetten",
    "sg:phone":"+31 575 546 295",
    "sg:postcode":"7201 HW",
    "sg:province":"Gelderland",
    "wof:name":"Tosja",
    "wof:placetype":"venue"
},
  "geometry": {"coordinates":[6.19376,52.141552],"type":"Point"}
}