{
  "type": "Feature",
  "properties": {
    "addr:full":"Vareseweg 55 Rotterdam Zuid-Holland 3047 AT",
    "addr:housenumber":"55",
    "addr:postcode":"3047",
    "addr:street":"Vareseweg",
    "iso:country":"NL",
    "sg:address":"Vareseweg 55",
    "sg:city":"Rotterdam",
    "sg:orig_category":"Loodgieterswerk, Verwarming And Sanitaire Installaties",
    "sg:phone":"+31 10 238 0638",
    "sg:postcode":"3047 AT",
    "sg:province":"Zuid-Holland",
    "wof:name":"Burgers Verwarming En Airconditioning Bv",
    "wof:placetype":"venue"
},
  "geometry": {"coordinates":[4.409408,51.946159],"type":"Point"}
}