{
  "type": "Feature",
  "properties": {
    "addr:full":"Smalthaarwg 10 Oosterhesselen Drenthe 7861 BN",
    "addr:housenumber":"10",
    "addr:postcode":"7861 bn",
    "addr:street":"Smalthaarwg",
    "iso:country":"NL",
    "sg:address":"Smalthaarwg 10",
    "sg:city":"Oosterhesselen",
    "sg:orig_category":"Vertalers",
    "sg:phone":"+31 524 581 331",
    "sg:postcode":"7861 BN",
    "sg:province":"Drenthe",
    "wof:name":"Cleveringa-Graffelman, H J",
    "wof:placetype":"venue"
},
  "geometry": {"coordinates":[6.716339,52.75182],"type":"Point"}
}