{
  "type": "Feature",
  "properties": {
    "addr:full":"Professor Van 'T Hoffln 12 Voorschoten Zuid-Holland 2251 GK",
    "addr:housenumber":"12",
    "addr:postcode":"2251 gk",
    "addr:street":"Professor Van",
    "iso:country":"NL",
    "sg:address":"Professor Van 'T Hoffln 12",
    "sg:city":"Voorschoten",
    "sg:orig_category":"Verzekeringen",
    "sg:phone":"+31 71 561 6446",
    "sg:postcode":"2251 GK",
    "sg:province":"Zuid-Holland",
    "wof:name":"Heeren Assurantien",
    "wof:placetype":"venue"
},
  "geometry": {"coordinates":[4.44501,52.117981],"type":"Point"}
}