{
  "type": "Feature",
  "properties": {
    "addr:full":"Valkenaarstr 67 Huizen Noord-Holland 1271 TK",
    "addr:housenumber":"67",
    "addr:postcode":"1271 tk",
    "addr:street":"Valkenaarstr",
    "iso:country":"NL",
    "sg:address":"Valkenaarstr 67",
    "sg:city":"Huizen",
    "sg:orig_category":"Non-Classified Establishments",
    "sg:phone":"+31 35 523 5096",
    "sg:postcode":"1271 TK",
    "sg:province":"Noord-Holland",
    "wof:name":"Dijk, R Van",
    "wof:placetype":"venue"
},
  "geometry": {"coordinates":[5.239374,52.298733],"type":"Point"}
}