{
  "type": "Feature",
  "properties": {
    "iso:country":"NL",
    "sg:address":"Hogezoom 98",
    "sg:city":"Burgh Haamstede",
    "sg:orig_category":"Fruitteelt",
    "sg:phone":"+31 111 652 073",
    "sg:postcode":"4328 EL",
    "sg:province":"Zeeland",
    "wof:name":"Fruitteeltbedrijf Tentebosch",
    "wof:placetype":"venue"
},
  "geometry": {"coordinates":[3.753521,51.714592],"type":"Point"}
}