{
  "type": "Feature",
  "properties": {
    "addr:full":"Pr Willem Alexanderpln 10 Benthuizen South Holland 2731 EJ",
    "addr:housenumber":"10",
    "addr:postcode":"2731 ej",
    "iso:country":"NL",
    "sg:address":"Pr Willem Alexanderpln 10",
    "sg:city":"Benthuizen",
    "sg:orig_category":"Bloemen And Planten",
    "sg:phone":"+31 79 331 3437",
    "sg:postcode":"2731 EJ",
    "sg:province":"South Holland",
    "wof:name":"Vof C.A. De Nobel",
    "wof:placetype":"venue"
},
  "geometry": {"coordinates":[4.543319,52.076721],"type":"Point"}
}