{
  "type": "Feature",
  "properties": {
    "iso:country":"NL",
    "sg:address":"Paltrokmolen 102",
    "sg:city":"Weert",
    "sg:orig_category":"Adviesbureaus",
    "sg:phone":"+31 495 536 552",
    "sg:postcode":"6003 CX",
    "sg:province":"Limburg",
    "wof:name":"European Conformity Services",
    "wof:placetype":"venue"
},
  "geometry": {"coordinates":[5.717745,51.264771],"type":"Point"}
}