{
  "type": "Feature",
  "properties": {
    "addr:full":"Eerste Nassaustraat 7 Amsterdam Noord-Holland 1052 BD",
    "addr:housenumber":"7",
    "addr:postcode":"1052 bd",
    "addr:street":"Eerste Nassaustraat",
    "iso:country":"NL",
    "sg:address":"Eerste Nassaustraat 7",
    "sg:city":"Amsterdam",
    "sg:orig_category":"Fitnesscentra",
    "sg:phone":"+31 20 673 5652",
    "sg:postcode":"1052 BD",
    "sg:province":"Noord-Holland",
    "wof:name":"Shorinji-Kempo Nederland",
    "wof:placetype":"venue"
},
  "geometry": {"coordinates":[4.879372,52.383038],"type":"Point"}
}