{
  "type": "Feature",
  "properties": {
    "addr:full":"Statenpln 2 S Gravenhage Zuid-Holland 2582 EW",
    "addr:housenumber":"2;gravenhage",
    "addr:postcode":"2582 ew",
    "addr:street":"Statenpln;S",
    "iso:country":"NL",
    "sg:address":"Statenpln 2",
    "sg:city":"S Gravenhage",
    "sg:orig_category":"Beurtvaartdiensten",
    "sg:phone":"+31 70 306 6700",
    "sg:postcode":"2582 EW",
    "sg:province":"Zuid-Holland",
    "wof:name":"Beurtvaartadres Bv",
    "wof:placetype":"venue"
},
  "geometry": {"coordinates":[4.27852,52.092411],"type":"Point"}
}