{
  "type": "Feature",
  "properties": {
    "addr:full":"Hectorln 31 Heerhugowaard Noord-Holland 1702 CL",
    "addr:housenumber":"31",
    "addr:postcode":"1702",
    "addr:street":"Hectorln",
    "iso:country":"NL",
    "sg:address":"Hectorln 31",
    "sg:city":"Heerhugowaard",
    "sg:orig_category":"Kinderopvang",
    "sg:phone":"+31 72 572 8172",
    "sg:postcode":"1702 CL",
    "sg:province":"Noord-Holland",
    "sg:website":"http://www.beregoed.nl",
    "wof:name":"Beregoed",
    "wof:placetype":"venue"
},
  "geometry": {"coordinates":[4.827522,52.665195],"type":"Point"}
}