{
  "type": "Feature",
  "properties": {
    "addr:full":"H Gortzakstr 10 Amsterdam Noord-Holland 1067 TP",
    "addr:housenumber":"10",
    "addr:postcode":"1067 tp",
    "iso:country":"NL",
    "sg:address":"H Gortzakstr 10",
    "sg:city":"Amsterdam",
    "sg:orig_category":"Fotojournalisten Freelance",
    "sg:phone":"+31 20 614 7387",
    "sg:postcode":"1067 TP",
    "sg:province":"Noord-Holland",
    "wof:name":"Bogaards, R W",
    "wof:placetype":"venue"
},
  "geometry": {"coordinates":[4.793144,52.378883],"type":"Point"}
}