{
  "type": "Feature",
  "properties": {
    "addr:full":"Hunenveldlaan 4 Oldenzaal Overijssel 7576 ZV",
    "addr:housenumber":"4",
    "addr:postcode":"7576 zv",
    "addr:street":"Hunenveldlaan",
    "iso:country":"NL",
    "sg:address":"Hunenveldlaan 4",
    "sg:city":"Oldenzaal",
    "sg:classifiers":[
        {
            "category":"Education",
            "subcategory":"Preschool",
            "type":"Public Place"
        }
    ],
    "sg:phone":"+31 541 571 404",
    "sg:postcode":"7576 ZV",
    "sg:province":"Overijssel",
    "sg:tags":[
        "kleuteronderwijs",
        "basis-"
    ],
    "wof:name":"Peuterspeelzaal Pino/Okkio",
    "wof:placetype":"venue"
},
  "geometry": {"coordinates":[6.90446,52.317768],"type":"Point"}
}