{
  "type": "Feature",
  "properties": {
    "addr:full":"Amsteldk 48 Amsterdam Noord-Holland 1074 HW",
    "addr:housenumber":"48",
    "addr:postcode":"1074 hw",
    "addr:street":"Amsteldk",
    "iso:country":"NL",
    "sg:address":"Amsteldk 48",
    "sg:city":"Amsterdam",
    "sg:orig_category":"Administratie- En Boekhoudkantoren",
    "sg:phone":"+31 20 676 0721",
    "sg:postcode":"1074 HW",
    "sg:province":"Noord-Holland",
    "wof:name":"Mahran",
    "wof:placetype":"venue"
},
  "geometry": {"coordinates":[4.906091,52.354515],"type":"Point"}
}