{
  "type": "Feature",
  "properties": {
    "iso:country":"NL",
    "sg:address":"Groenmarkt 9",
    "sg:city":"Zutphen",
    "sg:orig_category":"Antiekzaken",
    "sg:phone":"+31 575 516 980",
    "sg:postcode":"7201 HW",
    "sg:province":"Gelderland",
    "wof:name":"Langeberg",
    "wof:placetype":"venue"
},
  "geometry": {"coordinates":[6.193665,52.141579],"type":"Point"}
}