{
  "type": "Feature",
  "properties": {
    "iso:country":"NL",
    "sg:address":"Lierweg 34",
    "sg:city":"De Lier",
    "sg:orig_category":"Metaalwerken",
    "sg:phone":"+31 174 516 140",
    "sg:postcode":"2678 CW",
    "sg:province":"Zuid-Holland",
    "wof:name":"Boeters Glastuinbouwsystemen Bv",
    "wof:placetype":"venue"
},
  "geometry": {"coordinates":[4.260423,51.976795],"type":"Point"}
}