{
  "type": "Feature",
  "properties": {
    "addr:full":"Gelderlandpln 125 Amsterdam Missouri 1082 LV",
    "addr:housenumber":"125",
    "addr:postcode":"1082",
    "iso:country":"NL",
    "sg:address":"Gelderlandpln 125",
    "sg:city":"Amsterdam",
    "sg:orig_category":"Herenkleding",
    "sg:phone":"+31 20 644 7420",
    "sg:postcode":"1082 LV",
    "sg:province":"Missouri",
    "wof:name":"Adam",
    "wof:placetype":"venue"
},
  "geometry": {"coordinates":[-94.58503,38.350479],"type":"Point"}
}