{
  "type": "Feature",
  "properties": {
    "addr:full":"Wagenaarhof 21 S Gravenzande Zuid-Holland 2692 BJ",
    "addr:housenumber":"21;gravenzande",
    "addr:postcode":"2692 bj",
    "addr:street":"Wagenaarhof;S",
    "iso:country":"NL",
    "sg:address":"Wagenaarhof 21",
    "sg:city":"S Gravenzande",
    "sg:orig_category":"Land- En Tuinbouw - Loonbedrijven",
    "sg:phone":"+31 174 414 995",
    "sg:postcode":"2692 BJ",
    "sg:province":"Zuid-Holland",
    "wof:name":"Meer, Fa Van Der",
    "wof:placetype":"venue"
},
  "geometry": {"coordinates":[4.156681,52.002453],"type":"Point"}
}