{
  "type": "Feature",
  "properties": {
    "addr:full":"Het Rode Hert 38 Amersfoort Utrecht 3824 CG",
    "addr:housenumber":"38",
    "addr:postcode":"3824 cg",
    "addr:street":"Het Rode Hert",
    "iso:country":"NL",
    "sg:address":"Het Rode Hert 38",
    "sg:city":"Amersfoort",
    "sg:orig_category":"Homeopathie",
    "sg:phone":"+31 33 455 4338",
    "sg:postcode":"3824 CG",
    "sg:province":"Utrecht",
    "wof:name":"Sanoproducts Vof",
    "wof:placetype":"venue"
},
  "geometry": {"coordinates":[5.377345,52.197811],"type":"Point"}
}