{
  "type": "Feature",
  "properties": {
    "iso:country":"NL",
    "sg:address":"Stationsstraat 115",
    "sg:city":"Vlaardingen",
    "sg:classifiers":[
        {
            "category":"Education",
            "subcategory":"Preschool",
            "type":"Public Place"
        }
    ],
    "sg:phone":"+31 10 435 0808",
    "sg:postcode":"3131 PS",
    "sg:province":"Zuid-Holland",
    "sg:tags":[
        "kleuteronderwijs",
        "basis-"
    ],
    "wof:name":"Openbare Basisschool De Maatjes",
    "wof:placetype":"venue"
},
  "geometry": {"coordinates":[4.34263,51.904308],"type":"Point"}
}