{
  "type": "Feature",
  "properties": {
    "addr:full":"Brouwerstraat 11 Ede Gld Gelderland 6711 AS",
    "addr:housenumber":"11",
    "addr:postcode":"6711 as",
    "addr:street":"Brouwerstraat;Gld Gelderland",
    "iso:country":"NL",
    "sg:address":"Brouwerstraat 11",
    "sg:city":"Ede Gld",
    "sg:orig_category":"Juweliers",
    "sg:phone":"+31 318 617 636",
    "sg:postcode":"6711 AS",
    "sg:province":"Gelderland",
    "wof:name":"Juwelier Goudsmid J.H. Jorritsma",
    "wof:placetype":"venue"
},
  "geometry": {"coordinates":[5.670488,52.0467],"type":"Point"}
}