{
  "type": "Feature",
  "properties": {
    "addr:full":"H V Leyenstr 4 Born Limburg 6121 KH",
    "addr:housenumber":"4",
    "addr:postcode":"6121 kh",
    "addr:street":"H;Leyenstr",
    "iso:country":"NL",
    "sg:address":"H V Leyenstr 4",
    "sg:city":"Born",
    "sg:orig_category":"Verhuur",
    "sg:phone":"+31 46 486 0188",
    "sg:postcode":"6121 KH",
    "sg:province":"Limburg",
    "wof:name":"Swentibold",
    "wof:placetype":"venue"
},
  "geometry": {"coordinates":[-156.93781999999999,67.060463],"type":"Point"}
}