{
  "type": "Feature",
  "properties": {
    "iso:country":"NL",
    "sg:address":"Hendrik Hamerstraat 97",
    "sg:city":"'S Gravendeel",
    "sg:classifiers":[
        {
            "category":"Fast Food",
            "type":"Food & Drink"
        }
    ],
    "sg:phone":"+31 78 673 2944",
    "sg:postcode":"3295 CG",
    "sg:province":"Zuid-Holland",
    "sg:tags":[
        "afhaal",
        "restaurant"
    ],
    "wof:name":"Gouden Land",
    "wof:placetype":"venue"
},
  "geometry": {"coordinates":[4.613417,51.777088],"type":"Point"}
}