{
  "type": "Feature",
  "properties": {
    "addr:full":"Uraniumwg 23 Amersfoort Utrecht 3812 RJ",
    "addr:housenumber":"23",
    "addr:postcode":"3812 rj",
    "addr:street":"Uraniumwg",
    "iso:country":"NL",
    "sg:address":"Uraniumwg 23",
    "sg:city":"Amersfoort",
    "sg:orig_category":"Exploitatie- Maatschappijen",
    "sg:phone":"+31 33 461 9000",
    "sg:postcode":"3812 RJ",
    "sg:province":"Utrecht",
    "wof:name":"Sdw Bv",
    "wof:placetype":"venue"
},
  "geometry": {"coordinates":[5.353913,52.167454],"type":"Point"}
}