{
  "type": "Feature",
  "properties": {
    "addr:full":"De Gaarden 6 Raalte Overijssel 8101 ZD",
    "addr:housenumber":"6",
    "addr:postcode":"8101 zd",
    "addr:street":"De Gaarden",
    "iso:country":"NL",
    "sg:address":"De Gaarden 6",
    "sg:city":"Raalte",
    "sg:orig_category":"Binnenhuisarchitecten",
    "sg:phone":"+31 572 362 969",
    "sg:postcode":"8101 ZD",
    "sg:province":"Overijssel",
    "wof:name":"A A Ben",
    "wof:placetype":"venue"
},
  "geometry": {"coordinates":[6.261444,52.386753],"type":"Point"}
}