{
  "type": "Feature",
  "properties": {
    "addr:full":"Hoogbrugstraat 58 Maastricht Limburg 6221 CS",
    "addr:housenumber":"58",
    "addr:postcode":"6221 cs",
    "addr:street":"Hoogbrugstraat",
    "iso:country":"NL",
    "sg:address":"Hoogbrugstraat 58",
    "sg:city":"Maastricht",
    "sg:orig_category":"Kunst And Kunstenaarsbenodigdheden",
    "sg:phone":"+31 43 325 4698",
    "sg:postcode":"6221 CS",
    "sg:province":"Limburg",
    "wof:name":"Prima Vista",
    "wof:placetype":"venue"
},
  "geometry": {"coordinates":[5.699859,50.847469],"type":"Point"}
}