{
  "type": "Feature",
  "properties": {
    "addr:full":"Geertebolwerk 23 Utrecht Utrecht 3511 XA",
    "addr:housenumber":"23",
    "addr:postcode":"3511 xa",
    "addr:street":"Geertebolwerk",
    "iso:country":"NL",
    "sg:address":"Geertebolwerk 23",
    "sg:city":"Utrecht",
    "sg:orig_category":"Public Relationbureaus",
    "sg:phone":"+31 30 233 2330",
    "sg:postcode":"3511 XA",
    "sg:province":"Utrecht",
    "wof:name":"J. Van Beek Communicatie",
    "wof:placetype":"venue"
},
  "geometry": {"coordinates":[5.118899,52.086151],"type":"Point"}
}