{
  "type": "Feature",
  "properties": {
    "addr:full":"Postwg 15 De Glind Gelderland 3794 MJ",
    "addr:housenumber":"15",
    "addr:postcode":"3794 mj",
    "addr:street":"Postwg",
    "iso:country":"NL",
    "sg:address":"Postwg 15",
    "sg:city":"De Glind",
    "sg:orig_category":"Scholen Voor Basisonderwijs",
    "sg:phone":"+31 342 451 458",
    "sg:postcode":"3794 MJ",
    "sg:province":"Gelderland",
    "wof:name":"Beatrix Ned Herv, Pr",
    "wof:placetype":"venue"
},
  "geometry": {"coordinates":[5.534445,52.119755],"type":"Point"}
}