{
  "type": "Feature",
  "properties": {
    "addr:full":"Molenwal 2 Culemborg Gelderland 4101 EV",
    "addr:housenumber":"2",
    "addr:postcode":"4101 ev",
    "addr:street":"Molenwal;Gelderland",
    "iso:country":"NL",
    "sg:address":"Molenwal 2",
    "sg:city":"Culemborg",
    "sg:classifiers":[
        {
            "category":"Cinema",
            "subcategory":"Drive-in Theater",
            "type":"Entertainment"
        }
    ],
    "sg:phone":"+31 345 510 560",
    "sg:postcode":"4101 EV",
    "sg:province":"Gelderland",
    "sg:tags":[
        "drive-in-shows"
    ],
    "wof:name":"Feestje Bouwen.Com",
    "wof:placetype":"venue"
},
  "geometry": {"coordinates":[5.224751,51.95496],"type":"Point"}
}