{
  "type": "Feature",
  "properties": {
    "addr:full":"Pelgrimstraat 30 Vrouwenpolder Zeeland 4354 AS",
    "addr:housenumber":"30",
    "addr:postcode":"4354 as",
    "addr:street":"Pelgrimstraat",
    "iso:country":"NL",
    "sg:address":"Pelgrimstraat 30",
    "sg:city":"Vrouwenpolder",
    "sg:orig_category":"Verzekeringen",
    "sg:phone":"+31 118 591 641",
    "sg:postcode":"4354 AS",
    "sg:province":"Zeeland",
    "wof:name":"Assurantiekantoor J Moermond",
    "wof:placetype":"venue"
},
  "geometry": {"coordinates":[3.614869,51.575207],"type":"Point"}
}