{
  "type": "Feature",
  "properties": {
    "addr:full":"Trompstr 19 Vlaardingen South Holland 3134 XZ",
    "addr:housenumber":"19",
    "addr:postcode":"3134 xz",
    "addr:street":"Trompstr",
    "iso:country":"NL",
    "sg:address":"Trompstr 19",
    "sg:city":"Vlaardingen",
    "sg:orig_category":"Betonwerken",
    "sg:phone":"+31 6 22926356",
    "sg:postcode":"3134 XZ",
    "sg:province":"South Holland",
    "wof:name":"Kero",
    "wof:placetype":"venue"
},
  "geometry": {"coordinates":[4.35397,51.907036],"type":"Point"}
}