{
  "type": "Feature",
  "properties": {
    "addr:full":"Dorpsstr 42 Nigtevecht Utrecht 1393 NJ",
    "addr:housenumber":"42",
    "addr:postcode":"1393 nj",
    "addr:street":"Dorpsstr",
    "iso:country":"NL",
    "sg:address":"Dorpsstr 42",
    "sg:city":"Nigtevecht",
    "sg:orig_category":"Babyartikelen",
    "sg:phone":"+31 294 254 731",
    "sg:postcode":"1393 NJ",
    "sg:province":"Utrecht",
    "wof:name":"Koehler De Leeuw, M T E",
    "wof:placetype":"venue"
},
  "geometry": {"coordinates":[5.025165,52.273533],"type":"Point"}
}