{
  "type": "Feature",
  "properties": {
    "addr:full":"Kon Wilhelminahvn Zz 18 Vlaardingen Zuid-Holland 3134 KG",
    "addr:housenumber":"18",
    "addr:postcode":"3134 kg",
    "addr:street":"Kon;Zz",
    "iso:country":"NL",
    "sg:address":"Kon Wilhelminahvn Zz 18",
    "sg:city":"Vlaardingen",
    "sg:classifiers":[
        {
            "category":"Parking",
            "subcategory":"Lot",
            "type":"Transportation"
        }
    ],
    "sg:phone":"+31 10 248 5800",
    "sg:postcode":"3134 KG",
    "sg:province":"Zuid-Holland",
    "sg:tags":[
        "fab",
        "metalen",
        "tank"
    ],
    "wof:name":"J. De Jonge Constructie- En Pijpleidingenfabriek B",
    "wof:placetype":"venue"
},
  "geometry": {"coordinates":[4.340359,51.910442],"type":"Point"}
}