{
  "type": "Feature",
  "properties": {
    "addr:full":"Rode Kruisstraat 10 Amsterdam Noord-Holland 1025 KN",
    "addr:housenumber":"10",
    "addr:postcode":"1025 kn",
    "addr:street":"Rode Kruisstraat",
    "iso:country":"NL",
    "sg:address":"Rode Kruisstraat 10",
    "sg:city":"Amsterdam",
    "sg:classifiers":[
        {
            "category":"Education",
            "subcategory":"Preschool",
            "type":"Public Place"
        }
    ],
    "sg:phone":"+31 20 636 7723",
    "sg:postcode":"1025 KN",
    "sg:province":"Noord-Holland",
    "sg:tags":[
        "kleuteronderwijs",
        "basis-"
    ],
    "wof:name":"C.F. Capelleschool",
    "wof:placetype":"venue"
},
  "geometry": {"coordinates":[4.93181,52.394508],"type":"Point"}
}