{
  "type": "Feature",
  "properties": {
    "iso:country":"NL",
    "sg:address":"Noordsngl 204-206",
    "sg:city":"Rotterdam",
    "sg:orig_category":"Vertalers",
    "sg:phone":"+31 10 467 2400",
    "sg:postcode":"3032 BM",
    "sg:province":"Zuid-Holland",
    "wof:name":"Zwerner, Christiane",
    "wof:placetype":"venue"
},
  "geometry": {"coordinates":[4.47767,51.92852],"type":"Point"}
}