{
  "type": "Feature",
  "properties": {
    "addr:full":"H Polakln 42 Amsterdam Noord-Holland 1018 CT",
    "addr:housenumber":"42",
    "addr:postcode":"1018 ct",
    "iso:country":"NL",
    "sg:address":"H Polakln 42",
    "sg:city":"Amsterdam",
    "sg:orig_category":"Filmstudio'S En -Productie",
    "sg:phone":"+31 20 625 0714",
    "sg:postcode":"1018 CT",
    "sg:province":"Noord-Holland",
    "wof:name":"Motion",
    "wof:placetype":"venue"
},
  "geometry": {"coordinates":[4.893195,52.373119],"type":"Point"}
}