{
  "type": "Feature",
  "properties": {
    "addr:full":"Oliemolenstr 5 Drachten Friesland 9203 ZN",
    "addr:housenumber":"5",
    "addr:postcode":"9203 zn",
    "addr:street":"Oliemolenstr",
    "iso:country":"NL",
    "sg:address":"Oliemolenstr 5",
    "sg:city":"Drachten",
    "sg:orig_category":"Arbo- En Bedrijfsgezondheids- Diensten",
    "sg:phone":"+31 512 592 500",
    "sg:postcode":"9203 ZN",
    "sg:province":"Friesland",
    "wof:name":"Achmea Arbo",
    "wof:placetype":"venue"
},
  "geometry": {"coordinates":[6.089777,53.107231],"type":"Point"}
}