{
  "type": "Feature",
  "properties": {
    "addr:full":"Van Ostadestraat 51 Leeuwarden Friesland 8932 JZ",
    "addr:housenumber":"51",
    "addr:postcode":"8932 jz",
    "addr:street":"Van Ostadestraat",
    "iso:country":"NL",
    "sg:address":"Van Ostadestraat 51",
    "sg:city":"Leeuwarden",
    "sg:orig_category":"Loodgieterswerk, Verwarming And Sanitaire Installaties",
    "sg:phone":"+31 58 212 1287",
    "sg:postcode":"8932 JZ",
    "sg:province":"Friesland",
    "wof:name":"K. Dijkstra",
    "wof:placetype":"venue"
},
  "geometry": {"coordinates":[5.796033,53.189571],"type":"Point"}
}