{
  "type": "Feature",
  "properties": {
    "addr:full":"Klokbaai 25 Zaandam Noord-Holland 1506 VE",
    "addr:housenumber":"25",
    "addr:postcode":"1506",
    "addr:street":"Klokbaai;Ve",
    "iso:country":"NL",
    "sg:address":"Klokbaai 25",
    "sg:city":"Zaandam",
    "sg:orig_category":"Adviesbureaus Bouwkunde",
    "sg:phone":"+31 75 616 7857",
    "sg:postcode":"1506 VE",
    "sg:province":"Noord-Holland",
    "wof:name":"Bna",
    "wof:placetype":"venue"
},
  "geometry": {"coordinates":[4.818714,52.443542],"type":"Point"}
}