{
  "type": "Feature",
  "properties": {
    "addr:full":"Zuiderhoofdstraat 58 Krommenie Noord-Holland 1561 AN",
    "addr:housenumber":"58",
    "addr:postcode":"1561 an",
    "addr:street":"Zuiderhoofdstraat",
    "iso:country":"NL",
    "sg:address":"Zuiderhoofdstraat 58",
    "sg:city":"Krommenie",
    "sg:classifiers":[
        {
            "category":"Bakery",
            "type":"Food & Drink"
        }
    ],
    "sg:phone":"+31 75 628 2209",
    "sg:postcode":"1561 AN",
    "sg:province":"Noord-Holland",
    "sg:tags":[
        "brood",
        "banket"
    ],
    "wof:name":"Echte Bakker Kerssens",
    "wof:placetype":"venue"
},
  "geometry": {"coordinates":[4.768266,52.498547],"type":"Point"}
}