{
  "type": "Feature",
  "properties": {
    "iso:country":"NL",
    "sg:address":"Entrepothof 26",
    "sg:city":"Amsterdam",
    "sg:orig_category":"Adviesbureaus Bedrijfsorganisatie",
    "sg:phone":"+31 20 777 3280",
    "sg:postcode":"1019 DJ",
    "sg:province":"Noord-Holland",
    "wof:name":"Bsm Bv",
    "wof:placetype":"venue"
},
  "geometry": {"coordinates":[4.93606,52.368805],"type":"Point"}
}