{
  "type": "Feature",
  "properties": {
    "addr:full":"Ypesteinerln 63 Heiloo North Holland 1851 WG",
    "addr:housenumber":"63",
    "addr:postcode":"1851 wg",
    "addr:street":"Ypesteinerln",
    "iso:country":"NL",
    "sg:address":"Ypesteinerln 63",
    "sg:city":"Heiloo",
    "sg:orig_category":"Adviesbureaus Bouwkunde",
    "sg:phone":"+31 72 532 0515",
    "sg:postcode":"1851 WG",
    "sg:province":"North Holland",
    "wof:name":"Boom, R P H",
    "wof:placetype":"venue"
},
  "geometry": {"coordinates":[4.710473,52.589973],"type":"Point"}
}