{
  "type": "Feature",
  "properties": {
    "addr:full":"A Gogelwg 59 Vlissingen Zeeland 4384 EV",
    "addr:housenumber":"59",
    "addr:postcode":"4384 ev",
    "iso:country":"NL",
    "sg:address":"A Gogelwg 59",
    "sg:city":"Vlissingen",
    "sg:orig_category":"Verenigingen En Stichtingen",
    "sg:phone":"+31 118 462 098",
    "sg:postcode":"4384 EV",
    "sg:province":"Zeeland",
    "wof:name":"Paauwenburg, Wijkwinkel",
    "wof:placetype":"venue"
},
  "geometry": {"coordinates":[3.551988,51.461563],"type":"Point"}
}