{
  "type": "Feature",
  "properties": {
    "addr:full":"Nassauplein 33 Groningen Groningen 9717 CP",
    "addr:housenumber":"33",
    "addr:postcode":"9717 cp",
    "addr:street":"Nassauplein",
    "iso:country":"NL",
    "sg:address":"Nassauplein 33",
    "sg:city":"Groningen",
    "sg:orig_category":"Verzekeringen",
    "sg:phone":"+31 50 318 1950",
    "sg:postcode":"9717 CP",
    "sg:province":"Groningen",
    "wof:name":"Regionaal Assurantie Bedrijf Alzaad",
    "wof:placetype":"venue"
},
  "geometry": {"coordinates":[6.545292,53.22094],"type":"Point"}
}