{
  "type": "Feature",
  "properties": {
    "iso:country":"NL",
    "sg:address":"Nassauplein 33",
    "sg:city":"Groningen",
    "sg:orig_category":"Verzekeringen",
    "sg:phone":"+31 50 318 1950",
    "sg:postcode":"9717 CP",
    "sg:province":"Groningen",
    "wof:name":"Regionaal Assurantie Bedrijf Alzaad",
    "wof:placetype":"venue"
},
  "geometry": {"coordinates":[6.545292,53.22094],"type":"Point"}
}