{
  "type": "Feature",
  "properties": {
    "addr:full":"Marktstede 90 Roosendaal Noord-Brabant 4701 PZ",
    "addr:housenumber":"90",
    "addr:postcode":"4701 pz",
    "addr:street":"Marktstede",
    "iso:country":"NL",
    "sg:address":"Marktstede 90",
    "sg:city":"Roosendaal",
    "sg:orig_category":"Administratie- En Boekhoudkantoren",
    "sg:phone":"+31 165 559 619",
    "sg:postcode":"4701 PZ",
    "sg:province":"Noord-Brabant",
    "wof:name":"Hectors Admin Dienstverlening",
    "wof:placetype":"venue"
},
  "geometry": {"coordinates":[4.454421,51.533211],"type":"Point"}
}