{
  "type": "Feature",
  "properties": {
    "addr:full":"Scheepjeshof 141 Veenendaal Utrecht 3901 CS",
    "addr:housenumber":"141",
    "addr:postcode":"3901 cs",
    "addr:street":"Scheepjeshof",
    "iso:country":"NL",
    "sg:address":"Scheepjeshof 141",
    "sg:city":"Veenendaal",
    "sg:classifiers":[
        {
            "category":"Professional",
            "subcategory":"Accounting & Tax Preparation",
            "type":"Services"
        }
    ],
    "sg:phone":"+31 318 514 840",
    "sg:postcode":"3901 CS",
    "sg:province":"Utrecht",
    "sg:tags":[
        "accountant"
    ],
    "wof:name":"Administratiekant J C Heusinkveld",
    "wof:placetype":"venue"
},
  "geometry": {"coordinates":[5.55476,52.029636],"type":"Point"}
}