{
  "type": "Feature",
  "properties": {
    "addr:full":"Hogeweg 167 Limmen Noord-Holland 1906 CX",
    "addr:housenumber":"167",
    "addr:postcode":"1906 cx",
    "addr:street":"Hogeweg",
    "iso:country":"NL",
    "sg:address":"Hogeweg 167",
    "sg:city":"Limmen",
    "sg:orig_category":"Goederenvervoer Over De Weg",
    "sg:phone":"+31 72 505 1518",
    "sg:postcode":"1906 CX",
    "sg:province":"Noord-Holland",
    "wof:name":"Wempe Transport",
    "wof:placetype":"venue"
},
  "geometry": {"coordinates":[4.689594,52.576351],"type":"Point"}
}