{
  "type": "Feature",
  "properties": {
    "addr:full":"Konijnenlaan 1 Lunteren Gelderland 6741 RE",
    "addr:housenumber":"1",
    "addr:postcode":"6741",
    "addr:street":"Konijnenlaan;Gelderland",
    "iso:country":"NL",
    "sg:address":"Konijnenlaan 1",
    "sg:city":"Lunteren",
    "sg:orig_category":"Architecten En Architectenbureaus",
    "sg:phone":"+31 318 484 622",
    "sg:postcode":"6741 RE",
    "sg:province":"Gelderland",
    "wof:name":"Tempra",
    "wof:placetype":"venue"
},
  "geometry": {"coordinates":[5.614876,52.08466],"type":"Point"}
}