{
  "type": "Feature",
  "properties": {
    "iso:country":"NL",
    "sg:address":"De Kronkels 29",
    "sg:city":"Bunschoten Spakenb",
    "sg:orig_category":"Materiaalonderzoek",
    "sg:phone":"+31 33 298 6123",
    "sg:postcode":"3752 LM",
    "sg:province":"Utrecht",
    "sg:website":"http://www.rtd.nl",
    "wof:name":"R\u00f6ntgen Techn Dnst Bv",
    "wof:placetype":"venue"
},
  "geometry": {"coordinates":[5.364167,52.228939],"type":"Point"}
}