{
  "type": "Feature",
  "properties": {
    "iso:country":"NL",
    "sg:address":"Nanningh Keyserstraat 2",
    "sg:city":"Sleeuwijk",
    "sg:orig_category":"Verhuur Huishoudartikelen",
    "sg:phone":"+31 183 301 769",
    "sg:postcode":"4254 EP",
    "sg:province":"Noord-Brabant",
    "wof:name":"De Bolderik Sociaal Cultureel Centrum",
    "wof:placetype":"venue"
},
  "geometry": {"coordinates":[4.953247,51.817772],"type":"Point"}
}