{
  "type": "Feature",
  "properties": {
    "addr:full":"Voormeer 3 Alkmaar Noord-Holland 1813 SB",
    "addr:housenumber":"3",
    "addr:postcode":"1813 sb",
    "addr:street":"Voormeer",
    "iso:country":"NL",
    "sg:address":"Voormeer 3",
    "sg:city":"Alkmaar",
    "sg:orig_category":"Schilders",
    "sg:phone":"+31 72 511 2272",
    "sg:postcode":"1813 SB",
    "sg:province":"Noord-Holland",
    "wof:name":"Breed Van Arum Bv",
    "wof:placetype":"venue"
},
  "geometry": {"coordinates":[4.746258,52.634361],"type":"Point"}
}