{
  "type": "Feature",
  "properties": {
    "iso:country":"NL",
    "sg:address":"Kinkelenburgln 13",
    "sg:city":"Arnhem",
    "sg:orig_category":"Administratie- En Boekhoudkantoren",
    "sg:phone":"+31 26 381 6830",
    "sg:postcode":"6825 DJ",
    "sg:province":"Gelderland",
    "wof:name":"Bos\u00e9",
    "wof:placetype":"venue"
},
  "geometry": {"coordinates":[5.965182,51.983688],"type":"Point"}
}