{
  "type": "Feature",
  "properties": {
    "iso:country":"NL",
    "sg:address":"Horsterweg 64",
    "sg:city":"Sevenum",
    "sg:orig_category":"Warenhuizen",
    "sg:phone":"+31 77 467 2424",
    "sg:postcode":"5975 NB",
    "sg:province":"Limburg",
    "wof:name":"Phicoop Bv",
    "wof:placetype":"venue"
},
  "geometry": {"coordinates":[6.0351791382,51.4231796265],"type":"Point"}
}