{
  "type": "Feature",
  "properties": {
    "addr:full":"Saturnusweg 8 Brummen Gelderland 6971 GX",
    "addr:housenumber":"8",
    "addr:postcode":"6971 gx",
    "addr:street":"Saturnusweg;Gelderland",
    "iso:country":"NL",
    "sg:address":"Saturnusweg 8",
    "sg:city":"Brummen",
    "sg:orig_category":"Schilderwerk",
    "sg:phone":"+31 575 565 803",
    "sg:postcode":"6971 GX",
    "sg:province":"Gelderland",
    "wof:name":"Schildersbedrijf Waanders",
    "wof:placetype":"venue"
},
  "geometry": {"coordinates":[6.156266,52.103828],"type":"Point"}
}