{
  "type": "Feature",
  "properties": {
    "iso:country":"NL",
    "sg:address":"Luxemburglaan 152",
    "sg:city":"Zoetermeer",
    "sg:orig_category":"Schoenen",
    "sg:phone":"+31 79 331 0371",
    "sg:postcode":"2711 EH",
    "sg:province":"Zuid-Holland",
    "wof:name":"Tiron Schoenen Bv",
    "wof:placetype":"venue"
},
  "geometry": {"coordinates":[4.492053,52.062294],"type":"Point"}
}