{
  "type": "Feature",
  "properties": {
    "addr:full":"Breitnerstr 10 Leeuwarden Provincie Friesland 8932 CA",
    "addr:housenumber":"10",
    "addr:postcode":"8932 ca",
    "addr:street":"Breitnerstr;Provincie Friesland",
    "iso:country":"NL",
    "sg:address":"Breitnerstr 10",
    "sg:city":"Leeuwarden",
    "sg:orig_category":"Verenigingen En Stichtingen",
    "sg:phone":"+31 58 213 5187",
    "sg:postcode":"8932 CA",
    "sg:province":"Provincie Friesland",
    "wof:name":"Fleurich Frysk Stifting",
    "wof:placetype":"venue"
},
  "geometry": {"coordinates":[5.781551,53.191952],"type":"Point"}
}