{
  "type": "Feature",
  "properties": {
    "addr:full":"Bovenbuurtwg 33 Ede Gld Gelderland 6717 XA",
    "addr:housenumber":"33",
    "addr:postcode":"6717 xa",
    "addr:street":"Bovenbuurtwg;Gld Gelderland",
    "iso:country":"NL",
    "sg:address":"Bovenbuurtwg 33",
    "sg:city":"Ede Gld",
    "sg:orig_category":"Gehandicapteninformatie",
    "sg:phone":"+31 318 648 333",
    "sg:postcode":"6717 XA",
    "sg:province":"Gelderland",
    "wof:name":"Veldheim Dac",
    "wof:placetype":"venue"
},
  "geometry": {"coordinates":[5.662588,52.016933],"type":"Point"}
}