{
  "type": "Feature",
  "properties": {
    "iso:country":"NL",
    "sg:address":"Strawinskiplein 13",
    "sg:city":"Rhoon",
    "sg:classifiers":[
        {
            "category":"Fast Food",
            "type":"Food & Drink"
        }
    ],
    "sg:phone":"+31 10 501 2034",
    "sg:postcode":"3161 WG",
    "sg:province":"South Holland",
    "sg:tags":[
        "afhaal",
        "restaurant"
    ],
    "wof:name":"Cafetaria Familie Lang",
    "wof:placetype":"venue"
},
  "geometry": {"coordinates":[4.419944,51.85664],"type":"Point"}
}