{
  "type": "Feature",
  "properties": {
    "addr:full":"Deventerwg 121 Deventer Overijssel 7418 DA",
    "addr:housenumber":"121",
    "addr:postcode":"7418 da",
    "iso:country":"NL",
    "sg:address":"Deventerwg 121",
    "sg:city":"Deventer",
    "sg:classifiers":[
        {
            "category":"Travel",
            "subcategory":"Hotels & Motels",
            "type":"Entertainment"
        }
    ],
    "sg:phone":"+31 570 624 022",
    "sg:postcode":"7418 DA",
    "sg:province":"Overijssel",
    "sg:website":"http://www.postiljon.nl/",
    "wof:name":"Postiljon",
    "wof:placetype":"venue"
},
  "geometry": {"coordinates":[6.177551,52.23592],"type":"Point"}
}