{
  "type": "Feature",
  "properties": {
    "addr:full":"Leemkuil 11 Eindhoven Noord-Brabant 5626 EA",
    "addr:housenumber":"11",
    "addr:postcode":"5626 ea",
    "addr:street":"Leemkuil",
    "iso:country":"NL",
    "sg:address":"Leemkuil 11",
    "sg:city":"Eindhoven",
    "sg:orig_category":"Airconditioning",
    "sg:phone":"+31 40 266 2535",
    "sg:postcode":"5626 EA",
    "sg:province":"Noord-Brabant",
    "sg:website":"http://www.alaska-airco.nl",
    "wof:name":"Alaska Bv",
    "wof:placetype":"venue"
},
  "geometry": {"coordinates":[5.417139,51.481091],"type":"Point"}
}