{
  "type": "Feature",
  "properties": {
    "addr:full":"Zuiderparkwg 274 S Hertogenbosch Noord-Brabant 5216 HD",
    "addr:housenumber":"274",
    "addr:postcode":"5216 hd",
    "addr:street":"S",
    "iso:country":"NL",
    "sg:address":"Zuiderparkwg 274",
    "sg:city":"S Hertogenbosch",
    "sg:orig_category":"Adviesbureaus Bedrijfsorganisatie",
    "sg:phone":"+31 73 610 0945",
    "sg:postcode":"5216 HD",
    "sg:province":"Noord-Brabant",
    "wof:name":"Kt Dynamics",
    "wof:placetype":"venue"
},
  "geometry": {"coordinates":[5.317414,51.681717],"type":"Point"}
}