{
  "type": "Feature",
  "properties": {
    "addr:full":"Hoogtedwarsstraat 18 Tilburg North Brabant 5021 PB",
    "addr:housenumber":"18",
    "addr:postcode":"5021 pb",
    "addr:street":"Hoogtedwarsstraat",
    "iso:country":"NL",
    "sg:address":"Hoogtedwarsstraat 18",
    "sg:city":"Tilburg",
    "sg:orig_category":"Fitnesscentra",
    "sg:phone":"+31 13 536 6238",
    "sg:postcode":"5021 PB",
    "sg:province":"North Brabant",
    "wof:name":"Sportschool B-Fit",
    "wof:placetype":"venue"
},
  "geometry": {"coordinates":[5.0871,51.549648],"type":"Point"}
}