{
  "type": "Feature",
  "properties": {
    "addr:full":"Nieuwstraat 57 Medemblik Noord-Holland 1671 BB",
    "addr:housenumber":"57",
    "addr:postcode":"1671 bb",
    "addr:street":"Nieuwstraat",
    "iso:country":"NL",
    "sg:address":"Nieuwstraat 57",
    "sg:city":"Medemblik",
    "sg:orig_category":"Herenmodezaken",
    "sg:phone":"+31 227 544 792",
    "sg:postcode":"1671 BB",
    "sg:province":"Noord-Holland",
    "wof:name":"Brotex",
    "wof:placetype":"venue"
},
  "geometry": {"coordinates":[5.10694,52.772064],"type":"Point"}
}