{
  "type": "Feature",
  "properties": {
    "addr:full":"Grotestraat 174 Nijverdal Overijssel 7443 BR",
    "addr:housenumber":"174",
    "addr:postcode":"7443 br",
    "addr:street":"Grotestraat",
    "iso:country":"NL",
    "sg:address":"Grotestraat 174",
    "sg:city":"Nijverdal",
    "sg:orig_category":"Herenmodezaken",
    "sg:phone":"+31 528 620 341",
    "sg:postcode":"7443 BR",
    "sg:province":"Overijssel",
    "wof:name":"Dimmendaal Mode Voor De Man",
    "wof:placetype":"venue"
},
  "geometry": {"coordinates":[6.460103,52.365532],"type":"Point"}
}