{
  "type": "Feature",
  "properties": {
    "iso:country":"NL",
    "sg:address":"Willem Ii Straat 62",
    "sg:city":"Tilburg",
    "sg:orig_category":"Kappers",
    "sg:phone":"+31 13 542 5535",
    "sg:postcode":"5038 BH",
    "sg:province":"Noord-Brabant",
    "wof:name":"F.M. Van Erve",
    "wof:placetype":"venue"
},
  "geometry": {"coordinates":[5.0867090225,51.5576934814],"type":"Point"}
}