{
  "type": "Feature",
  "properties": {
    "addr:full":"Willem Ii Straat 62 Tilburg Noord-Brabant 5038 BH",
    "addr:housenumber":"62",
    "addr:postcode":"5038 bh",
    "addr:street":"Willem Ii Straat",
    "iso:country":"NL",
    "sg:address":"Willem Ii Straat 62",
    "sg:city":"Tilburg",
    "sg:orig_category":"Kappers",
    "sg:phone":"+31 13 542 5535",
    "sg:postcode":"5038 BH",
    "sg:province":"Noord-Brabant",
    "wof:name":"F.M. Van Erve",
    "wof:placetype":"venue"
},
  "geometry": {"coordinates":[5.0867090225,51.5576934814],"type":"Point"}
}