{
  "type": "Feature",
  "properties": {
    "addr:full":"Stadhouderslaan 126 Soest Utrecht 3761 EP",
    "addr:housenumber":"126",
    "addr:postcode":"3761 ep",
    "addr:street":"Stadhouderslaan",
    "iso:country":"NL",
    "sg:address":"Stadhouderslaan 126",
    "sg:city":"Soest",
    "sg:orig_category":"Glaszetten",
    "sg:phone":"+31 35 603 2905",
    "sg:postcode":"3761 EP",
    "sg:province":"Utrecht",
    "wof:name":"C.R.H. Miles",
    "wof:placetype":"venue"
},
  "geometry": {"coordinates":[5.296488,52.18644],"type":"Point"}
}