{
  "type": "Feature",
  "properties": {
    "addr:full":"Enkstr 88 Raalte Overijssel 8102 GN",
    "addr:housenumber":"88",
    "addr:postcode":"8102 gn",
    "addr:street":"Enkstr",
    "iso:country":"NL",
    "sg:address":"Enkstr 88",
    "sg:city":"Raalte",
    "sg:orig_category":"Voegwerken",
    "sg:phone":"+31 572 357 607",
    "sg:postcode":"8102 GN",
    "sg:province":"Overijssel",
    "wof:name":"Jos Koerhuis",
    "wof:placetype":"venue"
},
  "geometry": {"coordinates":[6.286367,52.38467],"type":"Point"}
}