{
  "type": "Feature",
  "properties": {
    "iso:country":"NL",
    "sg:address":"Enkstr 88",
    "sg:city":"Raalte",
    "sg:orig_category":"Voegwerken",
    "sg:phone":"+31 572 357 607",
    "sg:postcode":"8102 GN",
    "sg:province":"Overijssel",
    "wof:name":"Jos Koerhuis",
    "wof:placetype":"venue"
},
  "geometry": {"coordinates":[6.286367,52.38467],"type":"Point"}
}