{
  "type": "Feature",
  "properties": {
    "addr:full":"Esdoornln 6 St Odilienberg Limburg 6077 CP",
    "addr:housenumber":"6",
    "addr:postcode":"6077 cp",
    "addr:street":"Esdoornln",
    "iso:country":"NL",
    "sg:address":"Esdoornln 6",
    "sg:city":"St Odilienberg",
    "sg:orig_category":"Kampeerauto'S",
    "sg:phone":"+31 475 533 311",
    "sg:postcode":"6077 CP",
    "sg:province":"Limburg",
    "wof:name":"Lumens Kampeerautoverhuur",
    "wof:placetype":"venue"
},
  "geometry": {"coordinates":[6.0058050156,51.1399230957],"type":"Point"}
}