{
  "type": "Feature",
  "properties": {
    "addr:full":"Kon Julianaln 32 Ooy Gelderland 6576 AS",
    "addr:housenumber":"32",
    "addr:postcode":"6576 as",
    "addr:street":"Kon;Ooy Gelderland",
    "iso:country":"NL",
    "sg:address":"Kon Julianaln 32",
    "sg:city":"Ooy",
    "sg:classifiers":[
        {
            "category":"Travel",
            "subcategory":"Hotels & Motels",
            "type":"Entertainment"
        }
    ],
    "sg:phone":"+31 24 663 8213",
    "sg:postcode":"6576 AS",
    "sg:province":"Gelderland",
    "wof:name":"Haan, De",
    "wof:placetype":"venue"
},
  "geometry": {"coordinates":[83.34802999999999,24.4242],"type":"Point"}
}