{
  "type": "Feature",
  "properties": {
    "addr:full":"Bachstr 1 Gouda Zuid-Holland 2807 HZ",
    "addr:housenumber":"1",
    "addr:postcode":"2807 hz",
    "addr:street":"Bachstr",
    "iso:country":"NL",
    "sg:address":"Bachstr 1",
    "sg:city":"Gouda",
    "sg:orig_category":"Woningbouw- Verenigingen En -Stichtingen",
    "sg:phone":"+31 182 692 969",
    "sg:postcode":"2807 HZ",
    "sg:province":"Zuid-Holland",
    "sg:website":"http://www.tergouw.nl",
    "wof:name":"Ter Gouw",
    "wof:placetype":"venue"
},
  "geometry": {"coordinates":[4.7447199821,52.0132217407],"type":"Point"}
}