{
  "type": "Feature",
  "properties": {
    "iso:country":"NL",
    "sg:address":"St Willibrordusstraat 45",
    "sg:city":"Berghem",
    "sg:orig_category":"Banken And Kredietinstellingen",
    "sg:phone":"+31 412 401 225",
    "sg:postcode":"5351 EE",
    "sg:province":"North Brabant",
    "wof:name":"Postkantoor",
    "wof:placetype":"venue"
},
  "geometry": {"coordinates":[5.567617,51.770298],"type":"Point"}
}