{
  "type": "Feature",
  "properties": {
    "addr:full":"Makado Center 39 Alblasserdam South Holland 2951 EH",
    "addr:housenumber":"39",
    "addr:postcode":"2951 eh",
    "iso:country":"NL",
    "sg:address":"Makado Center 39",
    "sg:city":"Alblasserdam",
    "sg:orig_category":"Kinderkleding",
    "sg:phone":"+31 78 691 2067",
    "sg:postcode":"2951 EH",
    "sg:province":"South Holland",
    "wof:name":"Ballon Vof, De",
    "wof:placetype":"venue"
},
  "geometry": {"coordinates":[4.657964,51.863689],"type":"Point"}
}