{
  "type": "Feature",
  "properties": {
    "iso:country":"NL",
    "sg:address":"Raamgracht 72",
    "sg:city":"Amsterdam",
    "sg:orig_category":"Beursorganisaties And Standbouw",
    "sg:phone":"+31 20 620 1500",
    "sg:postcode":"1011 KK",
    "sg:province":"Noord-Holland",
    "wof:name":"M. V.D. Heiden",
    "wof:placetype":"venue"
},
  "geometry": {"coordinates":[4.899318,52.369453],"type":"Point"}
}