{
  "type": "Feature",
  "properties": {
    "addr:full":"Vleutensewg 151 Utrecht Utrecht 3532 HB",
    "addr:housenumber":"151",
    "addr:postcode":"3532 hb",
    "iso:country":"NL",
    "sg:address":"Vleutensewg 151",
    "sg:city":"Utrecht",
    "sg:orig_category":"Beeldende Kunstenaars",
    "sg:phone":"+31 30 294 0735",
    "sg:postcode":"3532 HB",
    "sg:province":"Utrecht",
    "wof:name":"Veld, Paul Ter",
    "wof:placetype":"venue"
},
  "geometry": {"coordinates":[5.101772,52.093136],"type":"Point"}
}