{
  "type": "Feature",
  "properties": {
    "addr:full":"Parsifalpad 12 Amersfoort Utrecht 3816 HA",
    "addr:housenumber":"12",
    "addr:postcode":"3816 ha",
    "addr:street":"Parsifalpad",
    "iso:country":"NL",
    "sg:address":"Parsifalpad 12",
    "sg:city":"Amersfoort",
    "sg:orig_category":"Boekhouders",
    "sg:phone":"+31 33 475 4040",
    "sg:postcode":"3816 HA",
    "sg:province":"Utrecht",
    "wof:name":"Oltipha",
    "wof:placetype":"venue"
},
  "geometry": {"coordinates":[5.410504,52.157566],"type":"Point"}
}