{
  "type": "Feature",
  "properties": {
    "iso:country":"NL",
    "sg:address":"Woudsingel 47",
    "sg:city":"Heerenveen",
    "sg:orig_category":"Verzekeringen",
    "sg:phone":"+31 513 681 441",
    "sg:postcode":"8443 DL",
    "sg:province":"Provincie Friesland",
    "wof:name":"U. Hijlkema Assurantien",
    "wof:placetype":"venue"
},
  "geometry": {"coordinates":[5.941928,52.946724],"type":"Point"}
}