{
  "type": "Feature",
  "properties": {
    "addr:full":"Marisstr 10 Geleen Limburg 6165 AS",
    "addr:housenumber":"10",
    "addr:postcode":"6165 as",
    "addr:street":"Marisstr",
    "iso:country":"NL",
    "sg:address":"Marisstr 10",
    "sg:city":"Geleen",
    "sg:orig_category":"Onderhoudswerken",
    "sg:phone":"+31 46 437 6340",
    "sg:postcode":"6165 AS",
    "sg:province":"Limburg",
    "wof:name":"Gatto Serv",
    "wof:placetype":"venue"
},
  "geometry": {"coordinates":[5.825423,50.959797],"type":"Point"}
}