{
  "type": "Feature",
  "properties": {
    "addr:full":"Prinsenhof 30 Ede Gld Gelderland 6715 LP",
    "addr:housenumber":"30",
    "addr:postcode":"6715 lp",
    "addr:street":"Prinsenhof;Gld Gelderland",
    "iso:country":"NL",
    "sg:address":"Prinsenhof 30",
    "sg:city":"Ede Gld",
    "sg:orig_category":"Marketingbureaus",
    "sg:phone":"+31 318 625 195",
    "sg:postcode":"6715 LP",
    "sg:province":"Gelderland",
    "wof:name":"Pmc",
    "wof:placetype":"venue"
},
  "geometry": {"coordinates":[5.632366,52.040443],"type":"Point"}
}