{
  "type": "Feature",
  "properties": {
    "addr:full":"Stationsstr 110 Waalwyk North Brabant 5141 GH",
    "addr:housenumber":"110",
    "addr:postcode":"5141 gh",
    "addr:street":"Waalwyk North",
    "iso:country":"NL",
    "sg:address":"Stationsstr 110",
    "sg:city":"Waalwyk",
    "sg:orig_category":"Makelaars En Adviseurs Onroerende Goederen",
    "sg:phone":"+31 416 343 711",
    "sg:postcode":"5141 GH",
    "sg:province":"North Brabant",
    "sg:website":"http://www.knepflevandermee.nl",
    "wof:name":"Knepfl\u00e9 & Van Der Mee",
    "wof:placetype":"venue"
},
  "geometry": {"coordinates":[5.067104,51.686352],"type":"Point"}
}