{
  "type": "Feature",
  "properties": {
    "addr:full":"Hoofddorppln 19 Amsterdam Noord-Holland 1059 CV",
    "addr:housenumber":"19",
    "addr:postcode":"1059 cv",
    "addr:street":"Hoofddorppln",
    "iso:country":"NL",
    "sg:address":"Hoofddorppln 19",
    "sg:city":"Amsterdam",
    "sg:orig_category":"Zoetwaren - Winkels",
    "sg:phone":"+31 20 615 6984",
    "sg:postcode":"1059 CV",
    "sg:province":"Noord-Holland",
    "wof:name":"Hans Chocolaterie",
    "wof:placetype":"venue"
},
  "geometry": {"coordinates":[4.851117,52.35088],"type":"Point"}
}