{
  "type": "Feature",
  "properties": {
    "addr:full":"Rietwykeroordwg 22 Aalsmeer Noord-Holland 1432 JE",
    "addr:housenumber":"22",
    "addr:postcode":"1432 je",
    "addr:street":"Rietwykeroordwg",
    "iso:country":"NL",
    "sg:address":"Rietwykeroordwg 22",
    "sg:city":"Aalsmeer",
    "sg:orig_category":"Bloemen En Planten - Groothandel",
    "sg:phone":"+31 297 325 630",
    "sg:postcode":"1432 JE",
    "sg:province":"Noord-Holland",
    "wof:name":"Marginata Bv",
    "wof:placetype":"venue"
},
  "geometry": {"coordinates":[4.803011,52.292156],"type":"Point"}
}