{
  "type": "Feature",
  "properties": {
    "addr:full":"Kalkovenweg 2 Alphen A/D Rijn South Holland 2401 LK",
    "addr:housenumber":"2",
    "addr:postcode":"2401 lk",
    "addr:street":"Kalkovenweg",
    "iso:country":"NL",
    "sg:address":"Kalkovenweg 2",
    "sg:city":"Alphen A/D Rijn",
    "sg:classifiers":[
        {
            "category":"Professional",
            "subcategory":"Accounting & Tax Preparation",
            "type":"Services"
        }
    ],
    "sg:phone":"+31 172 443 674",
    "sg:postcode":"2401 LK",
    "sg:province":"South Holland",
    "sg:tags":[
        "accountant"
    ],
    "wof:name":"Yark Koestering & Van De Vechte Accounta",
    "wof:placetype":"venue"
},
  "geometry": {"coordinates":[4.648985,52.147793],"type":"Point"}
}