{
  "type": "Feature",
  "properties": {
    "addr:full":"Korte Kamperstraat 6 Zwolle Overijssel 8011 MP",
    "addr:housenumber":"6",
    "addr:postcode":"8011 mp",
    "addr:street":"Korte Kamperstraat",
    "iso:country":"NL",
    "sg:address":"Korte Kamperstraat 6",
    "sg:city":"Zwolle",
    "sg:orig_category":"Fotostudio'S And Fotografen",
    "sg:phone":"+31 38 421 0797",
    "sg:postcode":"8011 MP",
    "sg:province":"Overijssel",
    "wof:name":"E.F. Boeijinga Fotografie",
    "wof:placetype":"venue"
},
  "geometry": {"coordinates":[6.089556,52.513172],"type":"Point"}
}