{
  "type": "Feature",
  "properties": {
    "addr:full":"De Veenbies 8 Dedemsvaart NL.08 7702 AV",
    "addr:housenumber":"8;nl.08",
    "addr:postcode":"7702 av",
    "addr:street":"De Veenbies",
    "iso:country":"NL",
    "sg:address":"De Veenbies 8",
    "sg:city":"Dedemsvaart",
    "sg:orig_category":"Administratie- En Boekhoudkantoren",
    "sg:phone":"+31 523 614 225",
    "sg:postcode":"7702 AV",
    "sg:province":"NL.08",
    "wof:name":"Avs",
    "wof:placetype":"venue"
},
  "geometry": {"coordinates":[6.452325,52.593529],"type":"Point"}
}