{
  "type": "Feature",
  "properties": {
    "addr:full":"Meerweidenlaan 49 Velsen Noord North Holland 1951 BW",
    "addr:housenumber":"49",
    "addr:postcode":"1951 bw",
    "addr:street":"Meerweidenlaan;Velsen Noord North",
    "iso:country":"NL",
    "sg:address":"Meerweidenlaan 49",
    "sg:city":"Velsen Noord",
    "sg:orig_category":"Goederenvervoer Over De Weg",
    "sg:phone":"+31 251 226 127",
    "sg:postcode":"1951 BW",
    "sg:province":"North Holland",
    "wof:name":"A.J. Splinter Tinholt Transportbedrijf Bv",
    "wof:placetype":"venue"
},
  "geometry": {"coordinates":[4.649208,52.471401],"type":"Point"}
}