{
  "type": "Feature",
  "properties": {
    "iso:country":"NL",
    "sg:address":"Wetering West 39",
    "sg:city":"Wetering",
    "sg:orig_category":"Kampeerterreinen",
    "sg:phone":"+31 521 371 232",
    "sg:postcode":"8363 TL",
    "sg:province":"Overijssel",
    "wof:name":"Camping De Wilgenhof",
    "wof:placetype":"venue"
},
  "geometry": {"coordinates":[5.9942817688,52.7536621094],"type":"Point"}
}