{
  "type": "Feature",
  "properties": {
    "iso:country":"NL",
    "sg:address":"Gildenwg 16",
    "sg:city":"Zwijndrecht",
    "sg:classifiers":[
        {
            "category":"Wholesale",
            "subcategory":"Meat",
            "type":"Manufacturing & Wholesale Goods"
        }
    ],
    "sg:phone":"+31 78 610 2177",
    "sg:postcode":"3334 KC",
    "sg:province":"South Holland",
    "sg:tags":[
        "regeltechniek",
        "en",
        "meet-"
    ],
    "wof:name":"M C I",
    "wof:placetype":"venue"
},
  "geometry": {"coordinates":[4.596834,51.810341],"type":"Point"}
}