{
  "type": "Feature",
  "properties": {
    "iso:country":"NL",
    "sg:address":"De Tippe 12",
    "sg:city":"Drogteropslagen",
    "sg:orig_category":"Artiesten",
    "sg:phone":"+31 523 615 983",
    "sg:postcode":"7705 PL",
    "sg:province":"NL.08",
    "wof:name":"J F Rodrigo",
    "wof:placetype":"venue"
},
  "geometry": {"coordinates":[6.509354,52.615513],"type":"Point"}
}