{
  "type": "Feature",
  "properties": {
    "addr:full":"De Tippe 12 Drogteropslagen NL.08 7705 PL",
    "addr:housenumber":"12;nl.08",
    "addr:postcode":"7705 pl",
    "addr:street":"De Tippe",
    "iso:country":"NL",
    "sg:address":"De Tippe 12",
    "sg:city":"Drogteropslagen",
    "sg:orig_category":"Artiesten",
    "sg:phone":"+31 523 615 983",
    "sg:postcode":"7705 PL",
    "sg:province":"NL.08",
    "wof:name":"J F Rodrigo",
    "wof:placetype":"venue"
},
  "geometry": {"coordinates":[6.509354,52.615513],"type":"Point"}
}