{
  "type": "Feature",
  "properties": {
    "addr:full":"Hoofdwg 1704 Abbenes Noord-Holland 2157 NB",
    "addr:housenumber":"1704",
    "addr:postcode":"abbenes;2157 nb",
    "iso:country":"NL",
    "sg:address":"Hoofdwg 1704",
    "sg:city":"Abbenes",
    "sg:orig_category":"Pluimveebedrijven En -Handelaren",
    "sg:phone":"+31 252 545 247",
    "sg:postcode":"2157 NB",
    "sg:province":"Noord-Holland",
    "wof:name":"Spek, F Van De",
    "wof:placetype":"venue"
},
  "geometry": {"coordinates":[4.595192,52.236916],"type":"Point"}
}