{
  "type": "Feature",
  "properties": {
    "addr:full":"Driebanen 22 Enkhuizen Noord-Holland 1601 NP",
    "addr:housenumber":"22",
    "addr:postcode":"1601 np",
    "addr:street":"Driebanen",
    "iso:country":"NL",
    "sg:address":"Driebanen 22",
    "sg:city":"Enkhuizen",
    "sg:orig_category":"Woningstoffeerders",
    "sg:phone":"+31 228 313 614",
    "sg:postcode":"1601 NP",
    "sg:province":"Noord-Holland",
    "wof:name":"Kuipers, H",
    "wof:placetype":"venue"
},
  "geometry": {"coordinates":[5.2870488167,52.7044448853],"type":"Point"}
}