{
  "type": "Feature",
  "properties": {
    "addr:full":"Ringweg 32 Limbricht Limburg 6141 LZ",
    "addr:housenumber":"32",
    "addr:postcode":"6141 lz",
    "addr:street":"Ringweg",
    "iso:country":"NL",
    "sg:address":"Ringweg 32",
    "sg:city":"Limbricht",
    "sg:orig_category":"Boekhouders",
    "sg:phone":"+31 46 452 4118",
    "sg:postcode":"6141 LZ",
    "sg:province":"Limburg",
    "wof:name":"Administratiekantoor Zatorski",
    "wof:placetype":"venue"
},
  "geometry": {"coordinates":[5.837538,51.007584],"type":"Point"}
}