{
  "type": "Feature",
  "properties": {
    "addr:full":"Magnoliastraat 31 Dordrecht South Holland 3319 SH",
    "addr:housenumber":"31",
    "addr:postcode":"3319 sh",
    "addr:street":"Magnoliastraat",
    "iso:country":"NL",
    "sg:address":"Magnoliastraat 31",
    "sg:city":"Dordrecht",
    "sg:orig_category":"Boekhouders",
    "sg:phone":"+31 78 616 2127",
    "sg:postcode":"3319 SH",
    "sg:province":"South Holland",
    "wof:name":"Administratiekantoor W. Lagendijk Bv",
    "wof:placetype":"venue"
},
  "geometry": {"coordinates":[4.697688,51.79063],"type":"Point"}
}