{
  "type": "Feature",
  "properties": {
    "addr:full":"Dorpsstraat 40 Heerde Gelderland 8181 HS",
    "addr:housenumber":"40",
    "addr:postcode":"8181 hs",
    "addr:street":"Dorpsstraat;Gelderland",
    "iso:country":"NL",
    "sg:address":"Dorpsstraat 40",
    "sg:city":"Heerde",
    "sg:orig_category":"Bloemen And Planten",
    "sg:phone":"+31 578 694 817",
    "sg:postcode":"8181 HS",
    "sg:province":"Gelderland",
    "wof:name":"Van Dragt'S Bloemencentrum",
    "wof:placetype":"venue"
},
  "geometry": {"coordinates":[6.039704,52.386833],"type":"Point"}
}