{
  "type": "Feature",
  "properties": {
    "addr:full":"Nieuwelaan 42 Made California 4921 ZH",
    "addr:housenumber":"42",
    "addr:postcode":"4921 zh",
    "addr:street":"Nieuwelaan",
    "iso:country":"NL",
    "sg:address":"Nieuwelaan 42",
    "sg:city":"Made",
    "sg:orig_category":"Werving And Selectie Van Tijdelijk Personeel And Uitzendkantoren",
    "sg:phone":"+31 162 685 346",
    "sg:postcode":"4921 ZH",
    "sg:province":"California",
    "wof:name":"Adrianus Bv",
    "wof:placetype":"venue"
},
  "geometry": {"coordinates":[-120.0639953613,36.9620552063],"type":"Point"}
}