{
  "type": "Feature",
  "properties": {
    "addr:full":"Boterdk 186 De Kwakel North Holland 1424 NM",
    "addr:housenumber":"186",
    "addr:postcode":"1424",
    "addr:street":"De",
    "iso:country":"NL",
    "sg:address":"Boterdk 186",
    "sg:city":"De Kwakel",
    "sg:orig_category":"Parketvloeren",
    "sg:phone":"+31 297 523 489",
    "sg:postcode":"1424 NM",
    "sg:province":"North Holland",
    "wof:name":"Parkotech",
    "wof:placetype":"venue"
},
  "geometry": {"coordinates":[4.797998,52.240253],"type":"Point"}
}