{
  "type": "Feature",
  "properties": {
    "addr:full":"Bavelseln 111 Breda North Brabant 4834 TA",
    "addr:housenumber":"111",
    "addr:postcode":"4834 ta",
    "iso:country":"NL",
    "sg:address":"Bavelseln 111",
    "sg:city":"Breda",
    "sg:orig_category":"Organisatiebureaus",
    "sg:phone":"+31 76 565 9564",
    "sg:postcode":"4834 TA",
    "sg:province":"North Brabant",
    "wof:name":"Fpt Int Bv",
    "wof:placetype":"venue"
},
  "geometry": {"coordinates":[4.8012499809,51.5665397644],"type":"Point"}
}