{
  "type": "Feature",
  "properties": {
    "addr:full":"W De Zwygerln 35 Schiedam Zuid-Holland 3116 HW",
    "addr:housenumber":"35",
    "addr:postcode":"3116 hw",
    "addr:street":"W De Zwygerln",
    "iso:country":"NL",
    "sg:address":"W De Zwygerln 35",
    "sg:city":"Schiedam",
    "sg:orig_category":"Ziekenhuizen, Sanatoria, Verpleeghuizen",
    "sg:phone":"+31 10 409 1333",
    "sg:postcode":"3116 HW",
    "sg:province":"Zuid-Holland",
    "wof:name":"Fran?ois Haverschmidt, Sticht Zorgcentr",
    "wof:placetype":"venue"
},
  "geometry": {"coordinates":[4.39816,51.918472],"type":"Point"}
}