{
  "type": "Feature",
  "properties": {
    "addr:full":"Generaal Snijdersstraat 12 Nieuwe Tonge Zuid-Holland 3244 BC",
    "addr:housenumber":"12",
    "addr:postcode":"3244 bc",
    "addr:street":"Generaal Snijdersstraat;Nieuwe Tonge",
    "iso:country":"NL",
    "sg:address":"Generaal Snijdersstraat 12",
    "sg:city":"Nieuwe Tonge",
    "sg:orig_category":"Pleziervaartuigen And Reparatie",
    "sg:phone":"+31 187 651 696",
    "sg:postcode":"3244 BC",
    "sg:province":"Zuid-Holland",
    "wof:name":"Jachtservice Luchtenborg",
    "wof:placetype":"venue"
},
  "geometry": {"coordinates":[4.158838,51.714813],"type":"Point"}
}