{
  "type": "Feature",
  "properties": {
    "iso:country":"NL",
    "sg:address":"Rietveldstr 6",
    "sg:city":"Deventer",
    "sg:orig_category":"Loopbaanbegeleiding",
    "sg:phone":"+31 570 658 650",
    "sg:postcode":"7425 EL",
    "sg:province":"NL.08",
    "wof:name":"Delta Visie",
    "wof:placetype":"venue"
},
  "geometry": {"coordinates":[6.228326,52.257397],"type":"Point"}
}