{
  "type": "Feature",
  "properties": {
    "addr:full":"Bruntingerwg 12 Wyster Provincie Drenthe 9418 PP",
    "addr:housenumber":"12",
    "addr:postcode":"9418 pp",
    "addr:street":"Bruntingerwg;Provincie Drenthe",
    "iso:country":"NL",
    "sg:address":"Bruntingerwg 12",
    "sg:city":"Wyster",
    "sg:orig_category":"Fietsen En Bromfietsen",
    "sg:phone":"+31 593 562 229",
    "sg:postcode":"9418 PP",
    "sg:province":"Provincie Drenthe",
    "wof:name":"Geerts, H",
    "wof:placetype":"venue"
},
  "geometry": {"coordinates":[6.554363,52.813663],"type":"Point"}
}