{
  "type": "Feature",
  "properties": {
    "addr:full":"Tweede Kostverlorenkade 128 Amsterdam North Holland 1053 SE",
    "addr:housenumber":"128",
    "addr:postcode":"1053 se",
    "addr:street":"Tweede Kostverlorenkade",
    "iso:country":"NL",
    "sg:address":"Tweede Kostverlorenkade 128",
    "sg:city":"Amsterdam",
    "sg:orig_category":"Autokeuringen",
    "sg:phone":"+31 20 689 9154",
    "sg:postcode":"1053 SE",
    "sg:province":"North Holland",
    "wof:name":"Garage Oud-West",
    "wof:placetype":"venue"
},
  "geometry": {"coordinates":[4.86029,52.364231],"type":"Point"}
}