{
  "type": "Feature",
  "properties": {
    "addr:full":"Beethovenlaan 16 Hengelo Ov Overijssel 7557 BD",
    "addr:housenumber":"16",
    "addr:postcode":"7557 bd",
    "addr:street":"Beethovenlaan;Ov",
    "iso:country":"NL",
    "sg:address":"Beethovenlaan 16",
    "sg:city":"Hengelo Ov",
    "sg:orig_category":"Boekhouders",
    "sg:phone":"+31 74 291 4854",
    "sg:postcode":"7557 BD",
    "sg:province":"Overijssel",
    "wof:name":"Administratiekantoor Htm Hengelo",
    "wof:placetype":"venue"
},
  "geometry": {"coordinates":[6.808223,52.269718],"type":"Point"}
}