{
  "type": "Feature",
  "properties": {
    "iso:country":"NL",
    "sg:address":"Rheastr 25",
    "sg:city":"Tilburg",
    "sg:orig_category":"Meubelen - Fabrieken En Groothandel",
    "sg:phone":"+31 13 515 9460",
    "sg:postcode":"5047 TL",
    "sg:province":"North Brabant",
    "wof:name":"Ruveau Collection",
    "wof:placetype":"venue"
},
  "geometry": {"coordinates":[5.008624,51.592846],"type":"Point"}
}