{
  "type": "Feature",
  "properties": {
    "addr:full":"Parallelwg 10 Meerssen Limburg 6231 CJ",
    "addr:housenumber":"10",
    "addr:postcode":"6231 cj",
    "addr:street":"Parallelwg",
    "iso:country":"NL",
    "sg:address":"Parallelwg 10",
    "sg:city":"Meerssen",
    "sg:classifiers":[
        {
            "category":"Personal",
            "subcategory":"Nail Salon",
            "type":"Services"
        }
    ],
    "sg:phone":"+31 43 364 9015",
    "sg:postcode":"6231 CJ",
    "sg:province":"Limburg",
    "sg:tags":[
        "pedicure"
    ],
    "wof:name":"Kramer-Baltis, Marcelle",
    "wof:placetype":"venue"
},
  "geometry": {"coordinates":[5.752762,50.88224],"type":"Point"}
}