{
  "type": "Feature",
  "properties": {
    "addr:full":"Witte Paal 306 Schagen Noord-Holland 1742 LD",
    "addr:housenumber":"306",
    "addr:postcode":"1742 ld",
    "addr:street":"Witte Paal",
    "iso:country":"NL",
    "sg:address":"Witte Paal 306",
    "sg:city":"Schagen",
    "sg:classifiers":[
        {
            "category":"Retail",
            "subcategory":"Auto Repair",
            "type":"Services"
        }
    ],
    "sg:phone":"+31 224 213 000",
    "sg:postcode":"1742 LD",
    "sg:province":"Noord-Holland",
    "sg:tags":[
        "garage"
    ],
    "sg:website":"http://www.groenewoud-citroen.nl",
    "wof:name":"Groenewoud Bv",
    "wof:placetype":"venue"
},
  "geometry": {"coordinates":[4.814133,52.77858],"type":"Point"}
}