{
  "type": "Feature",
  "properties": {
    "addr:full":"V Heekstr 11 Schiedam Zuid-Holland 3125 BN",
    "addr:housenumber":"11",
    "addr:postcode":"3125 bn",
    "iso:country":"NL",
    "sg:address":"V Heekstr 11",
    "sg:city":"Schiedam",
    "sg:orig_category":"Verlichting",
    "sg:phone":"+31 10 415 1811",
    "sg:postcode":"3125 BN",
    "sg:province":"Zuid-Holland",
    "sg:website":"http://www.qcat.nl",
    "wof:name":"Q-Cat Ned Bv",
    "wof:placetype":"venue"
},
  "geometry": {"coordinates":[4.40341,51.934971],"type":"Point"}
}