{
  "type": "Feature",
  "properties": {
    "addr:full":"Kiotoweg 5 Rotterdam New York 3047 BG",
    "addr:housenumber":"5",
    "addr:postcode":"3047",
    "addr:street":"Kiotoweg",
    "iso:country":"NL",
    "sg:address":"Kiotoweg 5",
    "sg:city":"Rotterdam",
    "sg:orig_category":"Goederenvervoer Over De Weg",
    "sg:phone":"+31 10 244 4444",
    "sg:postcode":"3047 BG",
    "sg:province":"New York",
    "wof:name":"Van Gend & Loos",
    "wof:placetype":"venue"
},
  "geometry": {"coordinates":[-73.955635,42.81974],"type":"Point"}
}