{
  "type": "Feature",
  "properties": {
    "addr:full":"Dorpsstr 46 Renswoude Utrecht 3927 BD",
    "addr:housenumber":"46",
    "addr:postcode":"3927 bd",
    "addr:street":"Dorpsstr",
    "iso:country":"NL",
    "sg:address":"Dorpsstr 46",
    "sg:city":"Renswoude",
    "sg:orig_category":"Woninginrichting",
    "sg:phone":"+31 318 571 306",
    "sg:postcode":"3927 BD",
    "sg:province":"Utrecht",
    "wof:name":"Raaij, Van",
    "wof:placetype":"venue"
},
  "geometry": {"coordinates":[5.5433349609,52.0727920532],"type":"Point"}
}