{
  "type": "Feature",
  "properties": {
    "addr:full":"Rolderstr 56 Assen Drenthe 9401 AT",
    "addr:housenumber":"56",
    "addr:postcode":"9401",
    "addr:street":"Rolderstr",
    "iso:country":"NL",
    "sg:address":"Rolderstr 56",
    "sg:city":"Assen",
    "sg:orig_category":"Kappers",
    "sg:phone":"+31 592 311 102",
    "sg:postcode":"9401 AT",
    "sg:province":"Drenthe",
    "wof:name":"Style Kapsalon",
    "wof:placetype":"venue"
},
  "geometry": {"coordinates":[6.566778,52.995785],"type":"Point"}
}