{
  "type": "Feature",
  "properties": {
    "iso:country":"NL",
    "sg:address":"Hilvertswg 216",
    "sg:city":"Hilversum",
    "sg:classifiers":[
        {
            "category":"Shopping",
            "subcategory":"Gifts & Souvenirs",
            "type":"Retail Goods"
        }
    ],
    "sg:phone":"+31 35 621 7406",
    "sg:postcode":"1214 JN",
    "sg:province":"Noord-Holland",
    "sg:tags":[
        "wens-",
        "en",
        "prentbriefkaarten"
    ],
    "wof:name":"Geitz, B",
    "wof:placetype":"venue"
},
  "geometry": {"coordinates":[5.1666808128,52.2092628479],"type":"Point"}
}