{
  "type": "Feature",
  "properties": {
    "addr:full":"Hilvertswg 216 Hilversum Noord-Holland 1214 JN",
    "addr:housenumber":"216",
    "addr:postcode":"hilversum;1214 jn",
    "iso:country":"NL",
    "sg:address":"Hilvertswg 216",
    "sg:city":"Hilversum",
    "sg:classifiers":[
        {
            "category":"Shopping",
            "subcategory":"Gifts & Souvenirs",
            "type":"Retail Goods"
        }
    ],
    "sg:phone":"+31 35 621 7406",
    "sg:postcode":"1214 JN",
    "sg:province":"Noord-Holland",
    "sg:tags":[
        "wens-",
        "en",
        "prentbriefkaarten"
    ],
    "wof:name":"Geitz, B",
    "wof:placetype":"venue"
},
  "geometry": {"coordinates":[5.1666808128,52.2092628479],"type":"Point"}
}