{
  "type": "Feature",
  "properties": {
    "addr:full":"Emmawyk 11 Zwolle Overijssel 8011 CM",
    "addr:housenumber":"11",
    "addr:postcode":"8011 cm",
    "addr:street":"Emmawyk",
    "iso:country":"NL",
    "sg:address":"Emmawyk 11",
    "sg:city":"Zwolle",
    "sg:orig_category":"Hulpverlening Sociaal",
    "sg:phone":"+31 38 456 4732",
    "sg:postcode":"8011 CM",
    "sg:province":"Overijssel",
    "wof:name":"Jongeren Informatie Punt Zwolle",
    "wof:placetype":"venue"
},
  "geometry": {"coordinates":[6.088738,52.512566],"type":"Point"}
}