{
  "type": "Feature",
  "properties": {
    "addr:full":"Fazantenln 4 Veere Zeeland 4351 RV",
    "addr:housenumber":"4",
    "addr:postcode":"4351 rv",
    "addr:street":"Fazantenln",
    "iso:country":"NL",
    "sg:address":"Fazantenln 4",
    "sg:city":"Veere",
    "sg:orig_category":"Modevakscholen",
    "sg:phone":"+31 118 501 556",
    "sg:postcode":"4351 RV",
    "sg:province":"Zeeland",
    "wof:name":"Veere",
    "wof:placetype":"venue"
},
  "geometry": {"coordinates":[3.657013,51.552746],"type":"Point"}
}