{
  "type": "Feature",
  "properties": {
    "addr:full":"Molenstr 3 Tubbergen Overijssel 7651 AS",
    "addr:housenumber":"3",
    "addr:postcode":"7651 as",
    "addr:street":"Molenstr",
    "iso:country":"NL",
    "sg:address":"Molenstr 3",
    "sg:city":"Tubbergen",
    "sg:classifiers":[
        {
            "category":"Food & Beverages",
            "subcategory":"Bakery",
            "type":"Retail Goods"
        }
    ],
    "sg:phone":"+31 546 623 368",
    "sg:postcode":"7651 AS",
    "sg:province":"Overijssel",
    "sg:tags":[
        "pizza"
    ],
    "wof:name":"Shalom",
    "wof:placetype":"venue"
},
  "geometry": {"coordinates":[6.782483,52.405621],"type":"Point"}
}