{
  "type": "Feature",
  "properties": {
    "addr:full":"Spoorwg 7 Veendam Groningen 9641 KH",
    "addr:housenumber":"7",
    "addr:postcode":"9641 kh",
    "addr:street":"Spoorwg",
    "iso:country":"NL",
    "sg:address":"Spoorwg 7",
    "sg:city":"Veendam",
    "sg:orig_category":"Verpakkingen En Verpakkingsmaterialen",
    "sg:phone":"+31 598 612 233",
    "sg:postcode":"9641 KH",
    "sg:province":"Groningen",
    "wof:name":"Boiten Dozenfabriek Bv",
    "wof:placetype":"venue"
},
  "geometry": {"coordinates":[6.88648,53.104252],"type":"Point"}
}