{
  "type": "Feature",
  "properties": {
    "addr:full":"J Q C Lenshoekln 10 Kloetinge Zeeland 4481 BS",
    "addr:housenumber":"10",
    "addr:postcode":"4481 bs",
    "addr:street":"Q;Lenshoekln",
    "iso:country":"NL",
    "sg:address":"J Q C Lenshoekln 10",
    "sg:city":"Kloetinge",
    "sg:orig_category":"Artsen - Huisartsen",
    "sg:phone":"+31 113 231 805",
    "sg:postcode":"4481 BS",
    "sg:province":"Zeeland",
    "wof:name":"Oortman, M J",
    "wof:placetype":"venue"
},
  "geometry": {"coordinates":[3.918405,51.496899],"type":"Point"}
}