{
  "type": "Feature",
  "properties": {
    "addr:full":"Van Wassenaerlaan 26 Hilversum Noord-Holland 1215 PB",
    "addr:housenumber":"26",
    "addr:postcode":"1215 pb",
    "addr:street":"Van Wassenaerlaan",
    "iso:country":"NL",
    "sg:address":"Van Wassenaerlaan 26",
    "sg:city":"Hilversum",
    "sg:orig_category":"Architecten",
    "sg:phone":"+31 35 624 0318",
    "sg:postcode":"1215 PB",
    "sg:province":"Noord-Holland",
    "wof:name":"W & P Management Advies Planontwikkeling",
    "wof:placetype":"venue"
},
  "geometry": {"coordinates":[5.1535,52.211422],"type":"Point"}
}