{
  "type": "Feature",
  "properties": {
    "addr:full":"Min C Ruysstr 11 Venray Limburg 5802 BC",
    "addr:housenumber":"11",
    "addr:postcode":"5802 bc",
    "iso:country":"NL",
    "sg:address":"Min C Ruysstr 11",
    "sg:city":"Venray",
    "sg:orig_category":"Woningtextiel",
    "sg:phone":"+31 478 631 642",
    "sg:postcode":"5802 BC",
    "sg:province":"Limburg",
    "wof:name":"Gwendolino",
    "wof:placetype":"venue"
},
  "geometry": {"coordinates":[5.9833788872,51.52709198],"type":"Point"}
}