{
  "type": "Feature",
  "properties": {
    "addr:full":"1E Tochtwg 8 Nieuwerkerk Yssel South Holland 2913 LP",
    "addr:housenumber":"8",
    "addr:postcode":"2913 lp",
    "addr:street":"1E Tochtwg",
    "iso:country":"NL",
    "sg:address":"1E Tochtwg 8",
    "sg:city":"Nieuwerkerk Yssel",
    "sg:orig_category":"Banket",
    "sg:phone":"+31 180 312 453",
    "sg:postcode":"2913 LP",
    "sg:province":"South Holland",
    "sg:website":"http://www.stroopwafel.tk",
    "wof:name":"Bart Berkhout",
    "wof:placetype":"venue"
},
  "geometry": {"coordinates":[4.613597,51.980667],"type":"Point"}
}