{
  "type": "Feature",
  "properties": {
    "iso:country":"NL",
    "sg:address":"Vroenstr 97",
    "sg:city":"Kerkrade",
    "sg:orig_category":"Kappers",
    "sg:phone":"+31 45 545 6854",
    "sg:postcode":"6462 VA",
    "sg:province":"Limburg",
    "wof:name":"Huppertz, M",
    "wof:placetype":"venue"
},
  "geometry": {"coordinates":[6.063533783,50.8546867371],"type":"Point"}
}