{
  "type": "Feature",
  "properties": {
    "addr:full":"A Schweitzerln 64 Haarlem Noord-Holland 2037 RS",
    "addr:housenumber":"64",
    "addr:postcode":"2037 rs",
    "iso:country":"NL",
    "sg:address":"A Schweitzerln 64",
    "sg:city":"Haarlem",
    "sg:orig_category":"Metselwerken",
    "sg:phone":"+31 23 529 0356",
    "sg:postcode":"2037 RS",
    "sg:province":"Noord-Holland",
    "wof:name":"Matyni",
    "wof:placetype":"venue"
},
  "geometry": {"coordinates":[4.658747,52.353931],"type":"Point"}
}