{
  "type": "Feature",
  "properties": {
    "addr:full":"Hullerwg 50 Nunspeet Gelderland 8071 RP",
    "addr:housenumber":"50",
    "addr:postcode":"8071",
    "addr:street":"Hullerwg;Gelderland",
    "iso:country":"NL",
    "sg:address":"Hullerwg 50",
    "sg:city":"Nunspeet",
    "sg:orig_category":"Houtgroothandel",
    "sg:phone":"+31 341 262 701",
    "sg:postcode":"8071 RP",
    "sg:province":"Gelderland",
    "wof:name":"Deuveren, Van",
    "wof:placetype":"venue"
},
  "geometry": {"coordinates":[5.7751,52.384197],"type":"Point"}
}