{
  "type": "Feature",
  "properties": {
    "addr:full":"Grote Brugse Grintweg 46 Tiel Gelderland 4005 AJ",
    "addr:housenumber":"46",
    "addr:postcode":"4005 aj",
    "addr:street":"Grote Brugse Grintweg;Gelderland",
    "iso:country":"NL",
    "sg:address":"Grote Brugse Grintweg 46",
    "sg:city":"Tiel",
    "sg:orig_category":"Fitnesscentra",
    "sg:phone":"+31 344 617 978",
    "sg:postcode":"4005 AJ",
    "sg:province":"Gelderland",
    "wof:name":"Sportschool Bushido",
    "wof:placetype":"venue"
},
  "geometry": {"coordinates":[5.440239,51.890854],"type":"Point"}
}