{
  "type": "Feature",
  "properties": {
    "addr:full":"Borstelweg 22 Enschede Overijssel 7545 MR",
    "addr:housenumber":"22",
    "addr:postcode":"7545 mr",
    "addr:street":"Borstelweg",
    "iso:country":"NL",
    "sg:address":"Borstelweg 22",
    "sg:city":"Enschede",
    "sg:orig_category":"Schilderwerk",
    "sg:phone":"+31 53 431 5006",
    "sg:postcode":"7545 MR",
    "sg:province":"Overijssel",
    "wof:name":"J.M. Van Der Gulik",
    "wof:placetype":"venue"
},
  "geometry": {"coordinates":[6.872501,52.219566],"type":"Point"}
}