{
  "type": "Feature",
  "properties": {
    "iso:country":"NL",
    "sg:address":"Jasmynln 3",
    "sg:city":"Loosdrecht",
    "sg:orig_category":"Schilders",
    "sg:phone":"+31 35 582 7629",
    "sg:postcode":"1231 EJ",
    "sg:province":"Noord-Holland",
    "wof:name":"Langenberg, Frens",
    "wof:placetype":"venue"
},
  "geometry": {"coordinates":[5.138936,52.201031],"type":"Point"}
}