{
  "type": "Feature",
  "properties": {
    "addr:full":"Helmholtzstr 61 Amsterdam Noord-Holland 1098 LE",
    "addr:housenumber":"61",
    "addr:postcode":"1098 le",
    "addr:street":"Helmholtzstr",
    "iso:country":"NL",
    "sg:address":"Helmholtzstr 61",
    "sg:city":"Amsterdam",
    "sg:orig_category":"Gemeentelijke Informatie",
    "sg:phone":"+31 20 774 4444",
    "sg:postcode":"1098 LE",
    "sg:province":"Noord-Holland",
    "sg:website":"http://www.oost-watergraafsmeer.nl",
    "wof:name":"Stadsdeel Oost-Watergraafsmeer",
    "wof:placetype":"venue"
},
  "geometry": {"coordinates":[4.939492,52.349873],"type":"Point"}
}