{
  "type": "Feature",
  "properties": {
    "addr:full":"Gelderse Roos 1 Deventer Overijssel 7421 CM",
    "addr:housenumber":"1",
    "addr:postcode":"7421 cm",
    "addr:street":"Gelderse Roos",
    "iso:country":"NL",
    "sg:address":"Gelderse Roos 1",
    "sg:city":"Deventer",
    "sg:orig_category":"Technische Studies And Onderzoek",
    "sg:phone":"+31 570 654 410",
    "sg:postcode":"7421 CM",
    "sg:province":"Overijssel",
    "wof:name":"Pyrus",
    "wof:placetype":"venue"
},
  "geometry": {"coordinates":[6.209643,52.243694],"type":"Point"}
}