{
  "type": "Feature",
  "properties": {
    "iso:country":"NL",
    "sg:address":"Herenstr 29",
    "sg:city":"Rhenen",
    "sg:orig_category":"Dameskleding",
    "sg:phone":"+31 317 612 213",
    "sg:postcode":"3911 JB",
    "sg:province":"Utrecht",
    "wof:name":"Eveline",
    "wof:placetype":"venue"
},
  "geometry": {"coordinates":[5.567912,51.957527],"type":"Point"}
}