{
  "type": "Feature",
  "properties": {
    "iso:country":"NL",
    "sg:address":"Plesmanwg 507",
    "sg:city":"Beverwyk",
    "sg:orig_category":"Geluidsinstallaties - Verhuur",
    "sg:phone":"+31 251 231 162",
    "sg:postcode":"1945 WS",
    "sg:province":"Noord-Holland",
    "wof:name":"Trendy",
    "wof:placetype":"venue"
},
  "geometry": {"coordinates":[4.665834,52.498093],"type":"Point"}
}