{
  "type": "Feature",
  "properties": {
    "iso:country":"NL",
    "sg:address":"Oudestreek 49",
    "sg:city":"Zevenhuizen Gn",
    "sg:orig_category":"Onderhoudswerken",
    "sg:phone":"+31 594 632 493",
    "sg:postcode":"9354 AD",
    "sg:province":"Groningen",
    "wof:name":"Dik, W",
    "wof:placetype":"venue"
},
  "geometry": {"coordinates":[6.345687,53.110077],"type":"Point"}
}