{
  "type": "Feature",
  "properties": {
    "addr:full":"Oudestreek 49 Zevenhuizen Gn Groningen 9354 AD",
    "addr:housenumber":"49;gn",
    "addr:postcode":"9354 ad",
    "addr:street":"Oudestreek",
    "iso:country":"NL",
    "sg:address":"Oudestreek 49",
    "sg:city":"Zevenhuizen Gn",
    "sg:orig_category":"Onderhoudswerken",
    "sg:phone":"+31 594 632 493",
    "sg:postcode":"9354 AD",
    "sg:province":"Groningen",
    "wof:name":"Dik, W",
    "wof:placetype":"venue"
},
  "geometry": {"coordinates":[6.345687,53.110077],"type":"Point"}
}