{
  "type": "Feature",
  "properties": {
    "addr:full":"Ugchelseweg 209 Ugchelen Obwalden 7339 CH",
    "addr:housenumber":"209",
    "addr:postcode":"7339",
    "addr:street":"Ugchelseweg",
    "iso:country":"NL",
    "sg:address":"Ugchelseweg 209",
    "sg:city":"Ugchelen",
    "sg:classifiers":[
        {
            "category":"Professional",
            "subcategory":"Accounting & Tax Preparation",
            "type":"Services"
        }
    ],
    "sg:phone":"+31 55 541 8042",
    "sg:postcode":"7339 CH",
    "sg:province":"Obwalden",
    "sg:tags":[
        "accountant"
    ],
    "wof:name":"Accountantskantoor Drs. M.F.T.M. Harterink Ra",
    "wof:placetype":"venue"
},
  "geometry": {"coordinates":[8.22414,46.813091],"type":"Point"}
}