{
  "type": "Feature",
  "properties": {
    "addr:full":"Prinses Ireneweg 20 Gulpen Limburg 6271 JB",
    "addr:housenumber":"20",
    "addr:postcode":"6271 jb",
    "addr:street":"Prinses Ireneweg",
    "iso:country":"NL",
    "sg:address":"Prinses Ireneweg 20",
    "sg:city":"Gulpen",
    "sg:classifiers":[
        {
            "category":"Travel",
            "subcategory":"Hotels & Motels",
            "type":"Entertainment"
        }
    ],
    "sg:phone":"+31 43 450 1948",
    "sg:postcode":"6271 JB",
    "sg:province":"Limburg",
    "wof:name":"Pension Bel-Air",
    "wof:placetype":"venue"
},
  "geometry": {"coordinates":[5.892935,50.814014],"type":"Point"}
}