{
  "type": "Feature",
  "properties": {
    "addr:full":"Slotlaan 255-257 Zeist Utrecht 3701 GG",
    "addr:housenumber":"255-257",
    "addr:postcode":"3701 gg",
    "addr:street":"Slotlaan",
    "iso:country":"NL",
    "sg:address":"Slotlaan 255-257",
    "sg:city":"Zeist",
    "sg:orig_category":"Damesmodezaken",
    "sg:phone":"+31 30 691 4275",
    "sg:postcode":"3701 GG",
    "sg:province":"Utrecht",
    "wof:name":"Modehuis Houwelingen",
    "wof:placetype":"venue"
},
  "geometry": {"coordinates":[5.246766,52.087574],"type":"Point"}
}