{
  "type": "Feature",
  "properties": {
    "addr:full":"G Grootestr 3 Zwolle Overijssel 8022 CG",
    "addr:housenumber":"3",
    "addr:postcode":"8022 cg",
    "iso:country":"NL",
    "sg:address":"G Grootestr 3",
    "sg:city":"Zwolle",
    "sg:orig_category":"Fitnesscentra",
    "sg:phone":"+31 38 453 5503",
    "sg:postcode":"8022 CG",
    "sg:province":"Overijssel",
    "sg:website":"http://www.medisport.nl",
    "wof:name":"Medisport Zwolle",
    "wof:placetype":"venue"
},
  "geometry": {"coordinates":[6.105661,52.523369],"type":"Point"}
}