{
  "type": "Feature",
  "properties": {
    "addr:full":"Groenlandsekd 3 Vinkeveen Utrecht 3645 BA",
    "addr:housenumber":"3",
    "addr:postcode":"3645 ba",
    "addr:street":"Groenlandsekd",
    "iso:country":"NL",
    "sg:address":"Groenlandsekd 3",
    "sg:city":"Vinkeveen",
    "sg:orig_category":"Watersportartikelen",
    "sg:phone":"+31 294 291 460",
    "sg:postcode":"3645 BA",
    "sg:province":"Utrecht",
    "wof:name":"Ba Vinkeveen",
    "wof:placetype":"venue"
},
  "geometry": {"coordinates":[4.9814968109,52.2241401672],"type":"Point"}
}