{
  "type": "Feature",
  "properties": {
    "addr:full":"Wagenmaker 133 Wilnis Utrecht 3648 KX",
    "addr:housenumber":"133",
    "addr:postcode":"3648 kx",
    "addr:street":"Wagenmaker",
    "iso:country":"NL",
    "sg:address":"Wagenmaker 133",
    "sg:city":"Wilnis",
    "sg:orig_category":"Artsen - Huisartsen",
    "sg:phone":"+31 297 288 585",
    "sg:postcode":"3648 KX",
    "sg:province":"Utrecht",
    "wof:name":"Vries, C De",
    "wof:placetype":"venue"
},
  "geometry": {"coordinates":[4.890362,52.203346],"type":"Point"}
}