{
  "type": "Feature",
  "properties": {
    "addr:full":"Stephensonstraat 10 Tiel Gelderland 4004 JA",
    "addr:housenumber":"10",
    "addr:postcode":"4004 ja",
    "addr:street":"Stephensonstraat;Gelderland",
    "iso:country":"NL",
    "sg:address":"Stephensonstraat 10",
    "sg:city":"Tiel",
    "sg:orig_category":"Beursorganisaties And Standbouw",
    "sg:phone":"+31 344 610 999",
    "sg:postcode":"4004 JA",
    "sg:province":"Gelderland",
    "wof:name":"Ide Interbouw Bv",
    "wof:placetype":"venue"
},
  "geometry": {"coordinates":[5.427723,51.911335],"type":"Point"}
}