{
  "type": "Feature",
  "properties": {
    "addr:full":"Sarphatistr 117 Amsterdam North Holland 1018 GB",
    "addr:housenumber":"117",
    "addr:postcode":"1018 gb",
    "iso:country":"NL",
    "sg:address":"Sarphatistr 117",
    "sg:city":"Amsterdam",
    "sg:orig_category":"Werving En Selectie",
    "sg:phone":"+31 20 626 3739",
    "sg:postcode":"1018 GB",
    "sg:province":"North Holland",
    "sg:website":"http://www.pinas-partners.nl",
    "wof:name":"Pinas & Partners Bv",
    "wof:placetype":"venue"
},
  "geometry": {"coordinates":[4.910487175,52.3618812561],"type":"Point"}
}