{
  "type": "Feature",
  "properties": {
    "iso:country":"NL",
    "sg:address":"Vaandersweid 12",
    "sg:city":"Enkhuizen",
    "sg:orig_category":"Pleziervaartuigen And Reparatie",
    "sg:phone":"+31 228 315 328",
    "sg:postcode":"1602 MJ",
    "sg:province":"North Holland",
    "wof:name":"C.J. Fluiter",
    "wof:placetype":"venue"
},
  "geometry": {"coordinates":[5.271879,52.714569],"type":"Point"}
}