{
  "type": "Feature",
  "properties": {
    "addr:full":"Clausstr 18 Zegveld Utrecht 3474 JZ",
    "addr:housenumber":"18",
    "addr:postcode":"3474 jz",
    "addr:street":"Clausstr",
    "iso:country":"NL",
    "sg:address":"Clausstr 18",
    "sg:city":"Zegveld",
    "sg:orig_category":"Schilders",
    "sg:phone":"+31 348 692 433",
    "sg:postcode":"3474 JZ",
    "sg:province":"Utrecht",
    "wof:name":"Berg, Van Den",
    "wof:placetype":"venue"
},
  "geometry": {"coordinates":[4.833756,52.115955],"type":"Point"}
}