{
  "type": "Feature",
  "properties": {
    "addr:full":"De Cockstraat 58 Groningen Groningen 9746 BT",
    "addr:housenumber":"58",
    "addr:postcode":"9746 bt",
    "addr:street":"De Cockstraat",
    "iso:country":"NL",
    "sg:address":"De Cockstraat 58",
    "sg:city":"Groningen",
    "sg:orig_category":"Projectinrichting",
    "sg:phone":"+31 50 553 0951",
    "sg:postcode":"9746 BT",
    "sg:province":"Groningen",
    "wof:name":"Weening Stoffeerbedrijf, W",
    "wof:placetype":"venue"
},
  "geometry": {"coordinates":[6.504031,53.234867],"type":"Point"}
}