{
  "type": "Feature",
  "properties": {
    "addr:full":"Bremenwg 8 Deventer Overijssel 7418 EJ",
    "addr:housenumber":"8",
    "addr:postcode":"7418 ej",
    "addr:street":"Bremenwg",
    "iso:country":"NL",
    "sg:address":"Bremenwg 8",
    "sg:city":"Deventer",
    "sg:orig_category":"Kunststoffen - Fabrieken En Groothandel",
    "sg:phone":"+31 570 609 005",
    "sg:postcode":"7418 EJ",
    "sg:province":"Overijssel",
    "sg:website":"http://www.hoetra.nl",
    "wof:name":"Hoetra Plastics",
    "wof:placetype":"venue"
},
  "geometry": {"coordinates":[6.201143,52.243225],"type":"Point"}
}