{
  "type": "Feature",
  "properties": {
    "addr:full":"Afweg 8 Rhenen Utrecht 3911 VG",
    "addr:housenumber":"8",
    "addr:postcode":"3911 vg",
    "addr:street":"Afweg",
    "iso:country":"NL",
    "sg:address":"Afweg 8",
    "sg:city":"Rhenen",
    "sg:orig_category":"Verhuur Gereedschapsmachines And Gereedschappen",
    "sg:phone":"+31 317 424 953",
    "sg:postcode":"3911 VG",
    "sg:province":"Utrecht",
    "wof:name":"Ben Becker",
    "wof:placetype":"venue"
},
  "geometry": {"coordinates":[5.616335,51.951092],"type":"Point"}
}