{
  "type": "Feature",
  "properties": {
    "iso:country":"NL",
    "sg:address":"Heufkenswg 5",
    "sg:city":"Maasmechelen",
    "sg:classifiers":[
        {
            "category":"Arena",
            "subcategory":"Auto Racetrack",
            "type":"Entertainment"
        }
    ],
    "sg:phone":"+31 89772850",
    "sg:postcode":"B-36 30",
    "sg:province":"BE.05",
    "sg:tags":[
        "en",
        "racebanen",
        "kart-"
    ],
    "sg:website":"http://www.cargo-karting.be",
    "wof:name":"Cargo Indoor Karting",
    "wof:placetype":"venue"
},
  "geometry": {"coordinates":[5.696135,50.963848],"type":"Point"}
}