{
  "type": "Feature",
  "properties": {
    "addr:full":"Schimmelstr 14A/B Amsterdam Noord-Holland 1053 TE",
    "addr:housenumber":"14a / b",
    "addr:postcode":"1053 te",
    "addr:street":"Schimmelstr",
    "iso:country":"NL",
    "sg:address":"Schimmelstr 14A/B",
    "sg:city":"Amsterdam",
    "sg:orig_category":"Peuterspeelzalen",
    "sg:phone":"+31 20 683 9110",
    "sg:postcode":"1053 TE",
    "sg:province":"Noord-Holland",
    "wof:name":"Monelli",
    "wof:placetype":"venue"
},
  "geometry": {"coordinates":[4.86733,52.366638],"type":"Point"}
}