{
  "type": "Feature",
  "properties": {
    "addr:full":"Vrouwenregt 12-15 Delft Zuid-Holland 2611 KK",
    "addr:housenumber":"12-15",
    "addr:postcode":"delft;2611 kk",
    "addr:street":"Vrouwenregt",
    "iso:country":"NL",
    "sg:address":"Vrouwenregt 12-15",
    "sg:city":"Delft",
    "sg:orig_category":"Meubelzaken, Woning- And Keukeninrichting",
    "sg:phone":"+31 15 212 0162",
    "sg:postcode":"2611 KK",
    "sg:province":"Zuid-Holland",
    "wof:name":"Klaas Vaak Bedden",
    "wof:placetype":"venue"
},
  "geometry": {"coordinates":[4.361173,52.012886],"type":"Point"}
}