{
  "type": "Feature",
  "properties": {
    "addr:full":"Meerndk 15 De Meern Utrecht 3454 HM",
    "addr:housenumber":"15",
    "addr:postcode":"3454 hm",
    "addr:street":"Meerndk",
    "iso:country":"NL",
    "sg:address":"Meerndk 15",
    "sg:city":"De Meern",
    "sg:orig_category":"Woninginrichting",
    "sg:phone":"+31 30 666 1397",
    "sg:postcode":"3454 HM",
    "sg:province":"Utrecht",
    "wof:name":"Sterk Wonen",
    "wof:placetype":"venue"
},
  "geometry": {"coordinates":[5.0361361504,52.0813941956],"type":"Point"}
}