{
  "type": "Feature",
  "properties": {
    "addr:full":"Kerkstraat 61 Bunschoten Spakenburg Utrecht 3751 AS",
    "addr:housenumber":"61",
    "addr:postcode":"3751 as",
    "addr:street":"Kerkstraat",
    "iso:country":"NL",
    "sg:address":"Kerkstraat 61",
    "sg:city":"Bunschoten Spakenburg",
    "sg:orig_category":"Meubelzaken, Woning- And Keukeninrichting",
    "sg:phone":"+31 33 298 1453",
    "sg:postcode":"3751 AS",
    "sg:province":"Utrecht",
    "wof:name":"Meubelcentrum Loef",
    "wof:placetype":"venue"
},
  "geometry": {"coordinates":[5.378175,52.252949],"type":"Point"}
}