{
  "type": "Feature",
  "properties": {
    "addr:full":"Koemarkt 53 Purmerend Noord-Holland 1441 DB",
    "addr:housenumber":"53",
    "addr:postcode":"1441 db",
    "addr:street":"Koemarkt",
    "iso:country":"NL",
    "sg:address":"Koemarkt 53",
    "sg:city":"Purmerend",
    "sg:orig_category":"Partyservice",
    "sg:phone":"+31 299 477 024",
    "sg:postcode":"1441 DB",
    "sg:province":"Noord-Holland",
    "sg:website":"http://www.serfaus.nl",
    "wof:name":"Serfaus, Centrum",
    "wof:placetype":"venue"
},
  "geometry": {"coordinates":[4.950827,52.508369],"type":"Point"}
}