{
  "type": "Feature",
  "properties": {
    "addr:full":"Kochstr 1 Heerlen Limburg 6412 TH",
    "addr:housenumber":"1",
    "addr:postcode":"6412 th",
    "addr:street":"Kochstr",
    "iso:country":"NL",
    "sg:address":"Kochstr 1",
    "sg:city":"Heerlen",
    "sg:orig_category":"Kappers",
    "sg:phone":"+31 45 572 3309",
    "sg:postcode":"6412 TH",
    "sg:province":"Limburg",
    "wof:name":"Breeschoten",
    "wof:placetype":"venue"
},
  "geometry": {"coordinates":[5.9769392014,50.8983917236],"type":"Point"}
}