{
  "type": "Feature",
  "properties": {
    "iso:country":"NL",
    "sg:address":"Morellengaarde 1",
    "sg:city":"Houten",
    "sg:orig_category":"Organisatiebureaus",
    "sg:phone":"+31 30 637 2549",
    "sg:postcode":"3992 JX",
    "sg:province":"Utrecht",
    "wof:name":"Vonk",
    "wof:placetype":"venue"
},
  "geometry": {"coordinates":[5.158654213,52.0359916687],"type":"Point"}
}