{
  "type": "Feature",
  "properties": {
    "addr:full":"Neringstraat 18 Enschede Overijssel 7532 SC",
    "addr:housenumber":"18",
    "addr:postcode":"7532 sc",
    "addr:street":"Neringstraat",
    "iso:country":"NL",
    "sg:address":"Neringstraat 18",
    "sg:city":"Enschede",
    "sg:orig_category":"Metalen And Ertsen Gh",
    "sg:phone":"+31 53 432 1517",
    "sg:postcode":"7532 SC",
    "sg:province":"Overijssel",
    "wof:name":"Firma Zwarts",
    "wof:placetype":"venue"
},
  "geometry": {"coordinates":[6.93798,52.221458],"type":"Point"}
}