{
  "type": "Feature",
  "properties": {
    "addr:full":"P Van Dijkstraat 12 Winschoten Groningen 9672 AJ",
    "addr:housenumber":"12",
    "addr:postcode":"9672 aj",
    "addr:street":"P Van Dijkstraat",
    "iso:country":"NL",
    "sg:address":"P Van Dijkstraat 12",
    "sg:city":"Winschoten",
    "sg:orig_category":"Woningbouwverenigingen",
    "sg:phone":"+31 597 454 545",
    "sg:postcode":"9672 AJ",
    "sg:province":"Groningen",
    "wof:name":"Stichting Acantus Woonservice",
    "wof:placetype":"venue"
},
  "geometry": {"coordinates":[7.0455999374,53.1386604309],"type":"Point"}
}