{
  "type": "Feature",
  "properties": {
    "iso:country":"NL",
    "sg:address":"P Van Dijkstraat 12",
    "sg:city":"Winschoten",
    "sg:orig_category":"Woningbouwverenigingen",
    "sg:phone":"+31 597 454 545",
    "sg:postcode":"9672 AJ",
    "sg:province":"Groningen",
    "wof:name":"Stichting Acantus Woonservice",
    "wof:placetype":"venue"
},
  "geometry": {"coordinates":[7.0455999374,53.1386604309],"type":"Point"}
}