{
  "type": "Feature",
  "properties": {
    "addr:full":"Burgemeester Galleestr 10 Vorden Gelderland 7251 EB",
    "addr:housenumber":"10",
    "addr:postcode":"7251 eb",
    "addr:street":"Burgemeester Galleestr;Gelderland",
    "iso:country":"NL",
    "sg:address":"Burgemeester Galleestr 10",
    "sg:city":"Vorden",
    "sg:orig_category":"Verzekeringen",
    "sg:phone":"+31 575 551 967",
    "sg:postcode":"7251 EB",
    "sg:province":"Gelderland",
    "wof:name":"Assurantie Advies- En Bemiddelingsburo N",
    "wof:placetype":"venue"
},
  "geometry": {"coordinates":[6.312915,52.105022],"type":"Point"}
}