{
  "type": "Feature",
  "properties": {
    "iso:country":"NL",
    "sg:address":"Oranjekanaal Noordzijde 4",
    "sg:city":"Emmen",
    "sg:orig_category":"Bloemen And Planten",
    "sg:phone":"+31 591 630 559",
    "sg:postcode":"7825 TK",
    "sg:province":"Drenthe",
    "wof:name":"Vof Tuincentrum En Dierenspeciaalzaak Omvlee",
    "wof:placetype":"venue"
},
  "geometry": {"coordinates":[6.909314,52.749065],"type":"Point"}
}