{
  "type": "Feature",
  "properties": {
    "addr:full":"W Pyrmontln 10 Wassenaar South Holland 2243 HM",
    "addr:housenumber":"10",
    "addr:postcode":"2243 hm",
    "addr:street":"W",
    "iso:country":"NL",
    "sg:address":"W Pyrmontln 10",
    "sg:city":"Wassenaar",
    "sg:orig_category":"Machinehandel",
    "sg:phone":"+31 70 511 2713",
    "sg:postcode":"2243 HM",
    "sg:province":"South Holland",
    "wof:name":"Inci Bv",
    "wof:placetype":"venue"
},
  "geometry": {"coordinates":[4.359457,52.122036],"type":"Point"}
}