{
  "type": "Feature",
  "properties": {
    "addr:full":"Steenhoffstraat 62 Soest Utrecht 3764 BM",
    "addr:housenumber":"62",
    "addr:postcode":"3764 bm",
    "addr:street":"Steenhoffstraat",
    "iso:country":"NL",
    "sg:address":"Steenhoffstraat 62",
    "sg:city":"Soest",
    "sg:orig_category":"Binnenhuisarchitecten",
    "sg:phone":"+31 35 603 0979",
    "sg:postcode":"3764 BM",
    "sg:province":"Utrecht",
    "wof:name":"Bart Baars Interieur Ontwerp En Uitvoering",
    "wof:placetype":"venue"
},
  "geometry": {"coordinates":[5.305286,52.179485],"type":"Point"}
}