{
  "type": "Feature",
  "properties": {
    "addr:full":"Beneden Beekloop 34 Geldrop North Brabant 5662 HL",
    "addr:housenumber":"34",
    "addr:postcode":"5662 hl",
    "addr:street":"Beneden Beekloop",
    "iso:country":"NL",
    "sg:address":"Beneden Beekloop 34",
    "sg:city":"Geldrop",
    "sg:orig_category":"Hypotheken",
    "sg:phone":"+31 40 284 6076",
    "sg:postcode":"5662 HL",
    "sg:province":"North Brabant",
    "sg:website":"http://www.vz-advies.nl",
    "wof:name":"Vz Financieel Advies",
    "wof:placetype":"venue"
},
  "geometry": {"coordinates":[5.550901,51.426178],"type":"Point"}
}