{
  "type": "Feature",
  "properties": {
    "iso:country":"NL",
    "sg:address":"Koetsveld 16",
    "sg:city":"Boskoop",
    "sg:orig_category":"Bloemen En Planten",
    "sg:phone":"+31 172 210 130",
    "sg:postcode":"2771 AM",
    "sg:province":"Zuid-Holland",
    "wof:name":"Sonja",
    "wof:placetype":"venue"
},
  "geometry": {"coordinates":[4.681119,52.095493],"type":"Point"}
}