{
  "type": "Feature",
  "properties": {
    "addr:full":"Parallelweg 113 Veenendaal Utrecht 3903 BG",
    "addr:housenumber":"113",
    "addr:postcode":"3903",
    "addr:street":"Parallelweg",
    "iso:country":"NL",
    "sg:address":"Parallelweg 113",
    "sg:city":"Veenendaal",
    "sg:orig_category":"Verzekeringen - Verzekeringskantoren",
    "sg:phone":"+31 318 561 157",
    "sg:postcode":"3903 BG",
    "sg:province":"Utrecht",
    "wof:name":"Blankenspoor",
    "wof:placetype":"venue"
},
  "geometry": {"coordinates":[5.556481,52.010178],"type":"Point"}
}