{
  "type": "Feature",
  "properties": {
    "addr:full":"Vlinderslag 1 Almkerk Noord-Brabant 4286 GA",
    "addr:housenumber":"1",
    "addr:postcode":"4286 ga",
    "addr:street":"Vlinderslag",
    "iso:country":"NL",
    "sg:address":"Vlinderslag 1",
    "sg:city":"Almkerk",
    "sg:orig_category":"Alternatieve Geneeskunde",
    "sg:phone":"+31 183 403 227",
    "sg:postcode":"4286 GA",
    "sg:province":"Noord-Brabant",
    "wof:name":"Huidverzorgingsinstituut Belviso",
    "wof:placetype":"venue"
},
  "geometry": {"coordinates":[4.951036,51.769878],"type":"Point"}
}