{
  "type": "Feature",
  "properties": {
    "addr:full":"Purmerweg 33 A Purmerend Noord-Holland 1441 RA",
    "addr:housenumber":"33 a",
    "addr:postcode":"1441 ra",
    "addr:street":"Purmerweg",
    "iso:country":"NL",
    "sg:address":"Purmerweg 33 A",
    "sg:city":"Purmerend",
    "sg:orig_category":"Loodgieterswerk, Verwarming And Sanitaire Installaties",
    "sg:phone":"+31 299 654 321",
    "sg:postcode":"1441 RA",
    "sg:province":"Noord-Holland",
    "wof:name":"Lasbo Installatiegroep",
    "wof:placetype":"venue"
},
  "geometry": {"coordinates":[4.966874,52.504025],"type":"Point"}
}