{
  "type": "Feature",
  "properties": {
    "addr:full":"Sumatrastraat 63 'S Hertogenbosch North Brabant 5215 AX",
    "addr:housenumber":"63",
    "addr:postcode":"5215 ax",
    "addr:street":"Sumatrastraat;' S Hertogenbosch",
    "iso:country":"NL",
    "sg:address":"Sumatrastraat 63",
    "sg:city":"'S Hertogenbosch",
    "sg:orig_category":"Wasserettes And Stomerijen",
    "sg:phone":"+31 73 612 2924",
    "sg:postcode":"5215 AX",
    "sg:province":"North Brabant",
    "wof:name":"Stomerij Amsto Stomerij/Wasserij",
    "wof:placetype":"venue"
},
  "geometry": {"coordinates":[5.3290958405,51.6898345947],"type":"Point"}
}