{
  "type": "Feature",
  "properties": {
    "addr:full":"Haverkampswg 22 Epe Gelderland 8161 VN",
    "addr:housenumber":"22",
    "addr:postcode":"8161 vn",
    "addr:street":"Haverkampswg;Gelderland",
    "iso:country":"NL",
    "sg:address":"Haverkampswg 22",
    "sg:city":"Epe",
    "sg:orig_category":"Ongediertebestrijding En Ontsmetting",
    "sg:phone":"+31 578 628 300",
    "sg:postcode":"8161 VN",
    "sg:province":"Gelderland",
    "sg:website":"http://www.freekvanessen.nl",
    "wof:name":"Essen Ongediertebestrijding, Van",
    "wof:placetype":"venue"
},
  "geometry": {"coordinates":[5.985232,52.342834],"type":"Point"}
}