{
  "type": "Feature",
  "properties": {
    "addr:full":"Minervum 7070 Breda Noord-Brabant 4817 ZK",
    "addr:housenumber":"7070",
    "addr:postcode":"breda;4817",
    "addr:street":"Minervum;Zk",
    "iso:country":"NL",
    "sg:address":"Minervum 7070",
    "sg:city":"Breda",
    "sg:orig_category":"Verzekerings- Maatschappijen",
    "sg:phone":"+31 76 578 1578",
    "sg:postcode":"4817 ZK",
    "sg:province":"Noord-Brabant",
    "wof:name":"Gothaer Nederland Bv",
    "wof:placetype":"venue"
},
  "geometry": {"coordinates":[4.832774,51.588722],"type":"Point"}
}