{
  "type": "Feature",
  "properties": {
    "addr:full":"Torenlaan 10 Hengelo Ov Overijssel 7559 PJ",
    "addr:housenumber":"10",
    "addr:postcode":"7559 pj",
    "addr:street":"Torenlaan;Ov",
    "iso:country":"NL",
    "sg:address":"Torenlaan 10",
    "sg:city":"Hengelo Ov",
    "sg:orig_category":"Autokeuringen",
    "sg:phone":"+31 74 276 1000",
    "sg:postcode":"7559 PJ",
    "sg:province":"Overijssel",
    "wof:name":"Treva Bandenservice Bv",
    "wof:placetype":"venue"
},
  "geometry": {"coordinates":[6.813404,52.283791],"type":"Point"}
}