{
  "type": "Feature",
  "properties": {
    "addr:full":"Pappersjans 50 Heerlen Limburg 6413 CL",
    "addr:housenumber":"50",
    "addr:postcode":"6413",
    "addr:street":"Pappersjans",
    "iso:country":"NL",
    "sg:address":"Pappersjans 50",
    "sg:city":"Heerlen",
    "sg:orig_category":"Nagelstudio'S",
    "sg:phone":"+31 45 574 3864",
    "sg:postcode":"6413 CL",
    "sg:province":"Limburg",
    "wof:name":"Roma Nagelstudio/Opleidingen",
    "wof:placetype":"venue"
},
  "geometry": {"coordinates":[5.96314,50.914448],"type":"Point"}
}