{
  "type": "Feature",
  "properties": {
    "iso:country":"NL",
    "sg:address":"Klaverweide 113",
    "sg:city":"Voorburg",
    "sg:orig_category":"Boekhouders",
    "sg:phone":"+31 70 320 9306",
    "sg:postcode":"2272 VX",
    "sg:province":"Zuid-Holland",
    "wof:name":"Vonk Administratie- En Belastingconsultancykantoor",
    "wof:placetype":"venue"
},
  "geometry": {"coordinates":[4.376546,52.084679],"type":"Point"}
}