{
  "type": "Feature",
  "properties": {
    "addr:full":"Paauwenburgweg 75 Vlissingen Zeeland 4384 JC",
    "addr:housenumber":"75",
    "addr:postcode":"4384 jc",
    "addr:street":"Paauwenburgweg",
    "iso:country":"NL",
    "sg:address":"Paauwenburgweg 75",
    "sg:city":"Vlissingen",
    "sg:classifiers":[
        {
            "category":"Communications",
            "subcategory":"Television Station",
            "type":"Services"
        }
    ],
    "sg:phone":"+31 118 471 449",
    "sg:postcode":"4384 JC",
    "sg:province":"Zeeland",
    "sg:tags":[
        "video",
        "audio",
        "verhuur"
    ],
    "wof:name":"Filmclub Paauwenburg",
    "wof:placetype":"venue"
},
  "geometry": {"coordinates":[3.550573,51.462215],"type":"Point"}
}