{
  "type": "Feature",
  "properties": {
    "addr:full":"K Brinkwg 37B Soest Utrecht 3761 EC",
    "addr:housenumber":"37b",
    "addr:postcode":"3761 ec",
    "addr:street":"Brinkwg",
    "iso:country":"NL",
    "sg:address":"K Brinkwg 37B",
    "sg:city":"Soest",
    "sg:orig_category":"Loodgieters",
    "sg:phone":"+31 35 601 4332",
    "sg:postcode":"3761 EC",
    "sg:province":"Utrecht",
    "wof:name":"Kerkhof Bv",
    "wof:placetype":"venue"
},
  "geometry": {"coordinates":[5.296164,52.186829],"type":"Point"}
}