{
  "type": "Feature",
  "properties": {
    "addr:full":"Schuberthof 45 Alphen A/D Rijn Zuid-Holland 2402 GJ",
    "addr:housenumber":"45",
    "addr:postcode":"2402 gj",
    "addr:street":"Schuberthof",
    "iso:country":"NL",
    "sg:address":"Schuberthof 45",
    "sg:city":"Alphen A/D Rijn",
    "sg:orig_category":"Manueel Therapeuten",
    "sg:phone":"+31 172 421 056",
    "sg:postcode":"2402 GJ",
    "sg:province":"Zuid-Holland",
    "wof:name":"Reen, R A Van",
    "wof:placetype":"venue"
},
  "geometry": {"coordinates":[4.667655,52.147415],"type":"Point"}
}