{
  "type": "Feature",
  "properties": {
    "iso:country":"NL",
    "sg:address":"Lindelaan 275",
    "sg:city":"Rijswijk Zh",
    "sg:orig_category":"Medische Apparatuur And Prothesen Fab",
    "sg:phone":"+31 70 414 0683",
    "sg:postcode":"2282 EV",
    "sg:province":"Zuid-Holland",
    "wof:name":"Beter Horen Audire",
    "wof:placetype":"venue"
},
  "geometry": {"coordinates":[4.3336429596,52.0494041443],"type":"Point"}
}