{
  "type": "Feature",
  "properties": {
    "addr:full":"Voorstraat 128 Egmond Aan Zee Noord-Holland 1931 AP",
    "addr:housenumber":"128",
    "addr:postcode":"1931 ap",
    "addr:street":"Voorstraat",
    "iso:country":"NL",
    "sg:address":"Voorstraat 128",
    "sg:city":"Egmond Aan Zee",
    "sg:classifiers":[
        {
            "category":"Bakery",
            "type":"Food & Drink"
        }
    ],
    "sg:phone":"+31 72 506 1307",
    "sg:postcode":"1931 AP",
    "sg:province":"Noord-Holland",
    "sg:tags":[
        "brood",
        "banket"
    ],
    "wof:name":"Echte Bakker Piet Kerssens",
    "wof:placetype":"venue"
},
  "geometry": {"coordinates":[4.623573,52.618111],"type":"Point"}
}