{
  "type": "Feature",
  "properties": {
    "addr:full":"Rosmolenstraat 38 Sittard Limburg 6131 HZ",
    "addr:housenumber":"38",
    "addr:postcode":"6131 hz",
    "addr:street":"Rosmolenstraat",
    "iso:country":"NL",
    "sg:address":"Rosmolenstraat 38",
    "sg:city":"Sittard",
    "sg:classifiers":[
        {
            "category":"Retail",
            "subcategory":"Photofinishing",
            "type":"Services"
        }
    ],
    "sg:phone":"+31 46 451 2416",
    "sg:postcode":"6131 HZ",
    "sg:province":"Limburg",
    "sg:tags":[
        "foto",
        "film"
    ],
    "wof:name":"Direct Foto Limburg Bv",
    "wof:placetype":"venue"
},
  "geometry": {"coordinates":[5.8691,50.996147],"type":"Point"}
}