{
  "type": "Feature",
  "properties": {
    "addr:full":"Wingerdstr 21 Schagen Noord-Holland 1741 TP",
    "addr:housenumber":"21",
    "addr:postcode":"1741 tp",
    "addr:street":"Wingerdstr",
    "iso:country":"NL",
    "sg:address":"Wingerdstr 21",
    "sg:city":"Schagen",
    "sg:orig_category":"Jachthavens - Jachtwerven",
    "sg:phone":"+31 224 296 595",
    "sg:postcode":"1741 TP",
    "sg:province":"Noord-Holland",
    "wof:name":"Jan Van Ketel Watersportver",
    "wof:placetype":"venue"
},
  "geometry": {"coordinates":[4.792064,52.798302],"type":"Point"}
}