{
  "type": "Feature",
  "properties": {
    "addr:full":"Arendshof 4 Oosterhout Nb North Brabant 4901 LH",
    "addr:housenumber":"4;nb",
    "addr:postcode":"4901 lh",
    "addr:street":"Arendshof",
    "iso:country":"NL",
    "sg:address":"Arendshof 4",
    "sg:city":"Oosterhout Nb",
    "sg:orig_category":"Discountwinkels",
    "sg:phone":"+31 162 470 491",
    "sg:postcode":"4901 LH",
    "sg:province":"North Brabant",
    "wof:name":"Zeeman Textielsupers",
    "wof:placetype":"venue"
},
  "geometry": {"coordinates":[4.856909,51.643856],"type":"Point"}
}