{
  "type": "Feature",
  "properties": {
    "addr:full":"V W Poelmanstr 1 Hardegaryp Provincie Friesland 9254 CS",
    "addr:housenumber":"1",
    "addr:postcode":"9254 cs",
    "addr:street":"Provincie Friesland",
    "iso:country":"NL",
    "sg:address":"V W Poelmanstr 1",
    "sg:city":"Hardegaryp",
    "sg:orig_category":"Peuterspeelzalen",
    "sg:phone":"+31 511 475 078",
    "sg:postcode":"9254 CS",
    "sg:province":"Provincie Friesland",
    "wof:name":"Wisseltje, 'T",
    "wof:placetype":"venue"
},
  "geometry": {"coordinates":[5.94131,53.215366],"type":"Point"}
}