{
  "type": "Feature",
  "properties": {
    "addr:full":"Druckerstr 16 Arnhem Gelderland 6823 HS",
    "addr:housenumber":"16",
    "addr:postcode":"6823 hs",
    "addr:street":"Druckerstr",
    "iso:country":"NL",
    "sg:address":"Druckerstr 16",
    "sg:city":"Arnhem",
    "sg:orig_category":"Acupunctuur",
    "sg:phone":"+31 26 443 7736",
    "sg:postcode":"6823 HS",
    "sg:province":"Gelderland",
    "wof:name":"Bouwmeister, F H M",
    "wof:placetype":"venue"
},
  "geometry": {"coordinates":[5.940946,52.002754],"type":"Point"}
}