{
  "type": "Feature",
  "properties": {
    "iso:country":"NL",
    "sg:address":"Kerkln 5",
    "sg:city":"Schiedam",
    "sg:orig_category":"Hengelsportartikelen - Fabrieken En Groothandel",
    "sg:phone":"+31 10 449 0211",
    "sg:postcode":"3121 KC",
    "sg:province":"Zuid-Holland",
    "wof:name":"Mac Bv",
    "wof:placetype":"venue"
},
  "geometry": {"coordinates":[4.378448,51.932404],"type":"Point"}
}