{
  "type": "Feature",
  "properties": {
    "addr:full":"Waagstraat 2 Lelystad Flevoland 8232 DZ",
    "addr:housenumber":"2",
    "addr:postcode":"8232 dz",
    "addr:street":"Waagstraat;Flevoland",
    "iso:country":"NL",
    "sg:address":"Waagstraat 2",
    "sg:city":"Lelystad",
    "sg:orig_category":"Autokeuringen",
    "sg:phone":"+31 320 221 941",
    "sg:postcode":"8232 DZ",
    "sg:province":"Flevoland",
    "wof:name":"Quickservice Station Van Olst Bv",
    "wof:placetype":"venue"
},
  "geometry": {"coordinates":[5.473467,52.510643],"type":"Point"}
}