{
  "type": "Feature",
  "properties": {
    "addr:full":"Passage 18 Rotterdam South Holland 3011 AP",
    "addr:housenumber":"18",
    "addr:postcode":"3011 ap",
    "addr:street":"Passage",
    "iso:country":"NL",
    "sg:address":"Passage 18",
    "sg:city":"Rotterdam",
    "sg:orig_category":"Herenkleding",
    "sg:phone":"+31 10 404 9840",
    "sg:postcode":"3011 AP",
    "sg:province":"South Holland",
    "wof:name":"Gant Usa",
    "wof:placetype":"venue"
},
  "geometry": {"coordinates":[4.480825,51.919975],"type":"Point"}
}