{
  "type": "Feature",
  "properties": {
    "addr:full":"Trompethoarn 2 Stiens Friesland 9051 MP",
    "addr:housenumber":"2",
    "addr:postcode":"9051 mp",
    "addr:street":"Trompethoarn",
    "iso:country":"NL",
    "sg:address":"Trompethoarn 2",
    "sg:city":"Stiens",
    "sg:orig_category":"Drukkerijen And Copyshops",
    "sg:phone":"+31 58 257 5360",
    "sg:postcode":"9051 MP",
    "sg:province":"Friesland",
    "wof:name":"Stiensprint",
    "wof:placetype":"venue"
},
  "geometry": {"coordinates":[5.754377,53.265793],"type":"Point"}
}