{
  "type": "Feature",
  "properties": {
    "addr:full":"Zwaagdijk 328 Zwaagdijk Noord-Holland 1686 PG",
    "addr:housenumber":"328",
    "addr:postcode":"1686 pg",
    "addr:street":"Zwaagdijk",
    "iso:country":"NL",
    "sg:address":"Zwaagdijk 328",
    "sg:city":"Zwaagdijk",
    "sg:orig_category":"Fruitteelt",
    "sg:phone":"+31 229 571 582",
    "sg:postcode":"1686 PG",
    "sg:province":"Noord-Holland",
    "wof:name":"Fruitbedrijf Pronk",
    "wof:placetype":"venue"
},
  "geometry": {"coordinates":[5.11317,52.696972],"type":"Point"}
}