{
  "type": "Feature",
  "properties": {
    "addr:full":"Vogellaan 77 Boskoop Zuid-Holland 2771 KJ",
    "addr:housenumber":"77",
    "addr:postcode":"2771 kj",
    "addr:street":"Vogellaan",
    "iso:country":"NL",
    "sg:address":"Vogellaan 77",
    "sg:city":"Boskoop",
    "sg:orig_category":"Boekhouders",
    "sg:phone":"+31 172 230 301",
    "sg:postcode":"2771 KJ",
    "sg:province":"Zuid-Holland",
    "wof:name":"Adfin",
    "wof:placetype":"venue"
},
  "geometry": {"coordinates":[4.640042,52.066761],"type":"Point"}
}