{
  "type": "Feature",
  "properties": {
    "addr:full":"Postbus 19 Berg En Dal Gelderland 6570 AA",
    "addr:housenumber":"19",
    "addr:postcode":"6570 aa",
    "addr:street":"Postbus",
    "iso:country":"NL",
    "sg:address":"Postbus 19",
    "sg:city":"Berg En Dal",
    "sg:orig_category":"Verenigingen En Stichtingen",
    "sg:phone":"+31 487 522 252",
    "sg:postcode":"6570 AA",
    "sg:province":"Gelderland",
    "wof:name":"Hulpfonds O-Europa Azi\u00eb",
    "wof:placetype":"venue"
},
  "geometry": {"coordinates":[5.91786,51.818199],"type":"Point"}
}