{
  "type": "Feature",
  "properties": {
    "addr:full":"Veenbesstraat 664 Soest Utrecht 3765 BT",
    "addr:housenumber":"664",
    "addr:postcode":"3765 bt",
    "addr:street":"Veenbesstraat",
    "iso:country":"NL",
    "sg:address":"Veenbesstraat 664",
    "sg:city":"Soest",
    "sg:orig_category":"Farmaceutische Producten Gh",
    "sg:phone":"+31 35 601 7842",
    "sg:postcode":"3765 BT",
    "sg:province":"Utrecht",
    "wof:name":"Medilapro +",
    "wof:placetype":"venue"
},
  "geometry": {"coordinates":[5.28751,52.168213],"type":"Point"}
}