{
  "type": "Feature",
  "properties": {
    "addr:full":"Gasthuisstraat 8 Winterswijk Gelderland 7101 DV",
    "addr:housenumber":"8",
    "addr:postcode":"7101",
    "addr:street":"Gasthuisstraat;Gelderland",
    "iso:country":"NL",
    "sg:address":"Gasthuisstraat 8",
    "sg:city":"Winterswijk",
    "sg:orig_category":"Werving And Selectie Van Tijdelijk Personeel And Uitzendkantoren",
    "sg:phone":"+31 543 522 048",
    "sg:postcode":"7101 DV",
    "sg:province":"Gelderland",
    "wof:name":"Start",
    "wof:placetype":"venue"
},
  "geometry": {"coordinates":[6.7144351006,51.9705696106],"type":"Point"}
}