{
  "type": "Feature",
  "properties": {
    "iso:country":"NL",
    "sg:address":"Scholtiss Holenwg 2",
    "sg:city":"Schinnen",
    "sg:orig_category":"Plafonds",
    "sg:phone":"+31 46 443 4659",
    "sg:postcode":"6365 BN",
    "sg:province":"Limburg",
    "sg:website":"http://www.gobouw .nl",
    "wof:name":"Gobouw Plafond & Wand",
    "wof:placetype":"venue"
},
  "geometry": {"coordinates":[5.889095,50.950401],"type":"Point"}
}