{
  "type": "Feature",
  "properties": {
    "addr:full":"Zeelt 139 Alblasserdam Zuid-Holland 2954 BL",
    "addr:housenumber":"139",
    "addr:postcode":"2954 bl",
    "addr:street":"Zeelt",
    "iso:country":"NL",
    "sg:address":"Zeelt 139",
    "sg:city":"Alblasserdam",
    "sg:orig_category":"Adviesbureaus",
    "sg:phone":"+31 6 41541543",
    "sg:postcode":"2954 BL",
    "sg:province":"Zuid-Holland",
    "wof:name":"Velde, Van De",
    "wof:placetype":"venue"
},
  "geometry": {"coordinates":[4.654613,51.872173],"type":"Point"}
}