{
  "type": "Feature",
  "properties": {
    "iso:country":"NL",
    "sg:address":"Hortsedk 41",
    "sg:city":"Helmond",
    "sg:orig_category":"Autopoetsbedrijven",
    "sg:phone":"+31 492 543 459",
    "sg:postcode":"5708 HB",
    "sg:province":"North Brabant",
    "wof:name":"Ven, Dennis Van De",
    "wof:placetype":"venue"
},
  "geometry": {"coordinates":[5.630342,51.476772],"type":"Point"}
}