{
  "type": "Feature",
  "properties": {
    "iso:country":"NL",
    "sg:address":"Estersveldln 55",
    "sg:city":"Grave",
    "sg:orig_category":"Verzekeringen - Verzekeringskantoren",
    "sg:phone":"+31 486 475 141",
    "sg:postcode":"5361 HS",
    "sg:province":"Noord-Brabant",
    "wof:name":"Weisz, J L",
    "wof:placetype":"venue"
},
  "geometry": {"coordinates":[-92.151741,32.929253],"type":"Point"}
}