{
  "type": "Feature",
  "properties": {
    "iso:country":"NL",
    "sg:address":"Van Den Berghstraat 43",
    "sg:city":"Maastricht",
    "sg:orig_category":"Diverse Grafische Activiteiten",
    "sg:phone":"+31 43 326 1608",
    "sg:postcode":"6221 XB",
    "sg:province":"Limburg",
    "wof:name":"Bos",
    "wof:placetype":"venue"
},
  "geometry": {"coordinates":[5.702565,50.852608],"type":"Point"}
}