{
  "type": "Feature",
  "properties": {
    "addr:full":"Eenhoornplnts 6 Oostburg Zeeland 4501 CL",
    "addr:housenumber":"6",
    "addr:postcode":"4501",
    "addr:street":"Eenhoornplnts",
    "iso:country":"NL",
    "sg:address":"Eenhoornplnts 6",
    "sg:city":"Oostburg",
    "sg:orig_category":"Kappers",
    "sg:phone":"+31 117 455 814",
    "sg:postcode":"4501 CL",
    "sg:province":"Zeeland",
    "wof:name":"Andr? Verstraten",
    "wof:placetype":"venue"
},
  "geometry": {"coordinates":[3.489276886,51.3257713318],"type":"Point"}
}