{
  "type": "Feature",
  "properties": {
    "addr:full":"Zandstr 5A Alphen Nb Noord-Brabant 5131 AB",
    "addr:housenumber":"5a",
    "addr:postcode":"5131 ab",
    "addr:street":"Zandstr",
    "iso:country":"NL",
    "sg:address":"Zandstr 5A",
    "sg:city":"Alphen Nb",
    "sg:orig_category":"Sportverenigingen En Ontspannings- Verenigingen",
    "sg:phone":"+31 13 508 1873",
    "sg:postcode":"5131 AB",
    "sg:province":"Noord-Brabant",
    "wof:name":"Alphen Tennisclub",
    "wof:placetype":"venue"
},
  "geometry": {"coordinates":[4.952751,51.485783],"type":"Point"}
}