{
  "type": "Feature",
  "properties": {
    "addr:full":"Rykswg Z 83 Sittard Limburg 6131 AM",
    "addr:housenumber":"83;6131",
    "addr:street":"Sittard Limburg",
    "iso:country":"NL",
    "sg:address":"Rykswg Z 83",
    "sg:city":"Sittard",
    "sg:orig_category":"Kappers",
    "sg:phone":"+31 46 451 5729",
    "sg:postcode":"6131 AM",
    "sg:province":"Limburg",
    "wof:name":"Kusters, T",
    "wof:placetype":"venue"
},
  "geometry": {"coordinates":[5.859662,50.996098],"type":"Point"}
}