{
  "type": "Feature",
  "properties": {
    "addr:full":"Oksholm 20 Hoofddorp North Holland 2133 KX",
    "addr:housenumber":"20",
    "addr:postcode":"2133 kx",
    "addr:street":"Oksholm",
    "iso:country":"NL",
    "sg:address":"Oksholm 20",
    "sg:city":"Hoofddorp",
    "sg:orig_category":"Goederenvervoer Over De Weg",
    "sg:phone":"+31 23 563 0559",
    "sg:postcode":"2133 KX",
    "sg:province":"North Holland",
    "wof:name":"Transportbedrijf Hans Sol",
    "wof:placetype":"venue"
},
  "geometry": {"coordinates":[4.665227,52.313454],"type":"Point"}
}