{
  "type": "Feature",
  "properties": {
    "addr:full":"Annastraat 41 Geleen Limburg 6161 GW",
    "addr:housenumber":"41",
    "addr:postcode":"6161 gw",
    "addr:street":"Annastraat",
    "iso:country":"NL",
    "sg:address":"Annastraat 41",
    "sg:city":"Geleen",
    "sg:orig_category":"Schoenen",
    "sg:phone":"+31 46 474 3704",
    "sg:postcode":"6161 GW",
    "sg:province":"Limburg",
    "wof:name":"J.H. Baggen",
    "wof:placetype":"venue"
},
  "geometry": {"coordinates":[5.825931,50.971722],"type":"Point"}
}