{
  "type": "Feature",
  "properties": {
    "iso:country":"NL",
    "sg:address":"Zwartepad 5",
    "sg:city":"Voorburg",
    "sg:orig_category":"Drukkerijen And Copyshops",
    "sg:phone":"+31 70 386 7371",
    "sg:postcode":"2271 BT",
    "sg:province":"Zuid-Holland",
    "wof:name":"Drukkerij Timmermans",
    "wof:placetype":"venue"
},
  "geometry": {"coordinates":[4.362466,52.067528],"type":"Point"}
}