{
  "type": "Feature",
  "properties": {
    "iso:country":"NL",
    "sg:address":"Raadhuisplein 7",
    "sg:city":"Dinteloord",
    "sg:orig_category":"Boekenuitgeverijen",
    "sg:phone":"+31 167 528 082",
    "sg:postcode":"4671  D",
    "sg:province":"Noord-Brabant",
    "wof:name":"Bruna",
    "wof:placetype":"venue"
},
  "geometry": {"coordinates":[4.372114,51.636345],"type":"Point"}
}