{
  "type": "Feature",
  "properties": {
    "iso:country":"NL",
    "sg:address":"H.J.E. Wenckebachweg 99",
    "sg:city":"Amsterdam",
    "sg:orig_category":"Metaalafval, Schrootrecycling And Sloperijen",
    "sg:phone":"+31 20 692 2032",
    "sg:postcode":"1096 AL",
    "sg:province":"Noord-Holland",
    "wof:name":"Autobedrijf Nico",
    "wof:placetype":"venue"
},
  "geometry": {"coordinates":[4.92923,52.338291],"type":"Point"}
}