{
  "type": "Feature",
  "properties": {
    "addr:full":"Koperslagerij 25 Zevenbergen Noord-Brabant 4762 AR",
    "addr:housenumber":"25",
    "addr:postcode":"4762",
    "addr:street":"Koperslagerij",
    "iso:country":"NL",
    "sg:address":"Koperslagerij 25",
    "sg:city":"Zevenbergen",
    "sg:orig_category":"Gebouwenafwerking, Renovaties And Reiniging",
    "sg:phone":"+31 168 329 937",
    "sg:postcode":"4762 AR",
    "sg:province":"Noord-Brabant",
    "wof:name":"Hogedruktechniek Zuid Nederland Bv",
    "wof:placetype":"venue"
},
  "geometry": {"coordinates":[4.616886,51.644405],"type":"Point"}
}