{
  "type": "Feature",
  "properties": {
    "iso:country":"NL",
    "sg:address":"Industriestr 52",
    "sg:city":"Hengelo Ov",
    "sg:orig_category":"Opticiens",
    "sg:phone":"+31 74 291 4687",
    "sg:postcode":"7553 CR",
    "sg:province":"Overijssel",
    "wof:name":"Braak, Ter",
    "wof:placetype":"venue"
},
  "geometry": {"coordinates":[6.7881221771,52.257724762],"type":"Point"}
}