{
  "type": "Feature",
  "properties": {
    "addr:full":"Sandhil 2 Zuidland Zuid-Holland 3214 EC",
    "addr:housenumber":"2",
    "addr:postcode":"3214 ec",
    "addr:street":"Sandhil",
    "iso:country":"NL",
    "sg:address":"Sandhil 2",
    "sg:city":"Zuidland",
    "sg:orig_category":"Kappers",
    "sg:phone":"+31 181 451 523",
    "sg:postcode":"3214 EC",
    "sg:province":"Zuid-Holland",
    "wof:name":"Frida Bijl",
    "wof:placetype":"venue"
},
  "geometry": {"coordinates":[4.2604160309,51.8174438477],"type":"Point"}
}