{
  "type": "Feature",
  "properties": {
    "addr:full":"Demertstraat 23 Maastricht Limburg 6227 AM",
    "addr:housenumber":"23",
    "addr:postcode":"6227",
    "addr:street":"Demertstraat",
    "iso:country":"NL",
    "sg:address":"Demertstraat 23",
    "sg:city":"Maastricht",
    "sg:orig_category":"Autokeuringen",
    "sg:phone":"+31 43 367 1486",
    "sg:postcode":"6227 AM",
    "sg:province":"Limburg",
    "wof:name":"A.M. Gulikers",
    "wof:placetype":"venue"
},
  "geometry": {"coordinates":[5.723487,50.842682],"type":"Point"}
}