{
  "type": "Feature",
  "properties": {
    "addr:full":"Groenewoudsedk 5G-5H Utrecht Utrecht 3528 BG",
    "addr:housenumber":"5g-5h",
    "addr:postcode":"3528",
    "addr:street":"Groenewoudsedk",
    "iso:country":"NL",
    "sg:address":"Groenewoudsedk 5G-5H",
    "sg:city":"Utrecht",
    "sg:orig_category":"Oud Metaal",
    "sg:phone":"+31 30 294 9044",
    "sg:postcode":"3528 BG",
    "sg:province":"Utrecht",
    "wof:name":"Doorn Recycling, G Van",
    "wof:placetype":"venue"
},
  "geometry": {"coordinates":[-73.9962921143,40.6130905151],"type":"Point"}
}