{
  "type": "Feature",
  "properties": {
    "addr:full":"Parallelweg West 13 Culemborg Gelderland 4104 AX",
    "addr:housenumber":"13",
    "addr:postcode":"4104 ax",
    "addr:street":"Parallelweg West;Gelderland",
    "iso:country":"NL",
    "sg:address":"Parallelweg West 13",
    "sg:city":"Culemborg",
    "sg:orig_category":"Meubelreparatie And -Restauratie",
    "sg:phone":"+31 345 514 335",
    "sg:postcode":"4104 AX",
    "sg:province":"Gelderland",
    "wof:name":"Meubelstoffeerderij- En Stikkerij Correct",
    "wof:placetype":"venue"
},
  "geometry": {"coordinates":[5.225022,51.94714],"type":"Point"}
}