{
  "type": "Feature",
  "properties": {
    "addr:full":"Singel 38 Woerden Utrecht 3442 AL",
    "addr:housenumber":"38",
    "addr:postcode":"3442 al",
    "addr:street":"Singel",
    "iso:country":"NL",
    "sg:address":"Singel 38",
    "sg:city":"Woerden",
    "sg:orig_category":"Bestratingen",
    "sg:phone":"+31 348 410 924",
    "sg:postcode":"3442 AL",
    "sg:province":"Utrecht",
    "wof:name":"Overbeek, J G",
    "wof:placetype":"venue"
},
  "geometry": {"coordinates":[4.888959,52.083519],"type":"Point"}
}