{
  "type": "Feature",
  "properties": {
    "addr:full":"Van Ostadestraat 220 Amsterdam Noord-Holland 1073 TT",
    "addr:housenumber":"220",
    "addr:postcode":"1073 tt",
    "addr:street":"Van Ostadestraat",
    "iso:country":"NL",
    "sg:address":"Van Ostadestraat 220",
    "sg:city":"Amsterdam",
    "sg:orig_category":"Vertaal- And Tolkenbureaus",
    "sg:phone":"+31 20 675 1172",
    "sg:postcode":"1073 TT",
    "sg:province":"Noord-Holland",
    "wof:name":"Paradox Language",
    "wof:placetype":"venue"
},
  "geometry": {"coordinates":[4.896203,52.352657],"type":"Point"}
}