{
  "type": "Feature",
  "properties": {
    "addr:full":"Voordijk 36 Schelluinen Zuid-Holland 4209 SC",
    "addr:housenumber":"36",
    "addr:postcode":"4209 sc",
    "addr:street":"Voordijk",
    "iso:country":"NL",
    "sg:address":"Voordijk 36",
    "sg:city":"Schelluinen",
    "sg:orig_category":"Beautyfarms And Sauna'S",
    "sg:phone":"+31 183 625 109",
    "sg:postcode":"4209 SC",
    "sg:province":"Zuid-Holland",
    "wof:name":"Schoonheidssalon En Zonnestudio Kosmetie",
    "wof:placetype":"venue"
},
  "geometry": {"coordinates":[4.923553,51.850777],"type":"Point"}
}