{
  "type": "Feature",
  "properties": {
    "addr:full":"Postbus 721 S Gravenhage South Holland 2501 CS",
    "addr:housenumber":"721",
    "addr:postcode":"2501 cs",
    "addr:street":"Postbus;S Gravenhage",
    "iso:country":"NL",
    "sg:address":"Postbus 721",
    "sg:city":"S Gravenhage",
    "sg:orig_category":"Fotoreportages",
    "sg:phone":"+31 6 26358146",
    "sg:postcode":"2501 CS",
    "sg:province":"South Holland",
    "wof:name":"Marle, Ilja Van",
    "wof:placetype":"venue"
},
  "geometry": {"coordinates":[4.31361,52.07832],"type":"Point"}
}