{
  "type": "Feature",
  "properties": {
    "addr:full":"Wagnerkade 49 Heemstede Noord-Holland 2102 CT",
    "addr:housenumber":"49",
    "addr:postcode":"2102 ct",
    "addr:street":"Wagnerkade",
    "iso:country":"NL",
    "sg:address":"Wagnerkade 49",
    "sg:city":"Heemstede",
    "sg:orig_category":"Vertaal- And Tolkenbureaus",
    "sg:phone":"+31 23 528 7051",
    "sg:postcode":"2102 CT",
    "sg:province":"Noord-Holland",
    "wof:name":"Mr Drs P T J Uiterwaal",
    "wof:placetype":"venue"
},
  "geometry": {"coordinates":[4.62828,52.35445],"type":"Point"}
}