{
  "type": "Feature",
  "properties": {
    "addr:full":"Ruysdaelstr 21-23 Amsterdam Noord-Holland 1071 WZ",
    "addr:housenumber":"21-23",
    "addr:postcode":"1071 wz",
    "iso:country":"NL",
    "sg:address":"Ruysdaelstr 21-23",
    "sg:city":"Amsterdam",
    "sg:orig_category":"Boeken En Tijdschriften",
    "sg:phone":"+31 20 679 3817",
    "sg:postcode":"1071 WZ",
    "sg:province":"Noord-Holland",
    "wof:name":"Zaailing",
    "wof:placetype":"venue"
},
  "geometry": {"coordinates":[4.885076,52.354198],"type":"Point"}
}