{
  "type": "Feature",
  "properties": {
    "addr:full":"Lochemseweg 47 Borculo Gelderland 7271 WC",
    "addr:housenumber":"47",
    "addr:postcode":"7271 wc",
    "addr:street":"Lochemseweg;Gelderland",
    "iso:country":"NL",
    "sg:address":"Lochemseweg 47",
    "sg:city":"Borculo",
    "sg:orig_category":"Vertaal- And Tolkenbureaus",
    "sg:phone":"+31 545 271 701",
    "sg:postcode":"7271 WC",
    "sg:province":"Gelderland",
    "wof:name":"N. Joling/ Tolk-Vertaler",
    "wof:placetype":"venue"
},
  "geometry": {"coordinates":[6.520631,52.122288],"type":"Point"}
}