{
  "type": "Feature",
  "properties": {
    "iso:country":"NL",
    "sg:address":"Pater Eijmardweg 6",
    "sg:city":"Nijmegen",
    "sg:orig_category":"Loodgieterswerk, Verwarming And Sanitaire Installaties",
    "sg:phone":"+31 24 355 5058",
    "sg:postcode":"6525 RM",
    "sg:province":"Gelderland",
    "wof:name":"Installatie En Onderhoudsbedrijf Thijssen",
    "wof:placetype":"venue"
},
  "geometry": {"coordinates":[5.870076,51.813042],"type":"Point"}
}