{
  "type": "Feature",
  "properties": {
    "addr:full":"Groenkampen 56 Assen Drenthe 9407 RC",
    "addr:housenumber":"56",
    "addr:postcode":"9407 rc",
    "addr:street":"Groenkampen",
    "iso:country":"NL",
    "sg:address":"Groenkampen 56",
    "sg:city":"Assen",
    "sg:orig_category":"Kappers",
    "sg:phone":"+31 592 346 685",
    "sg:postcode":"9407 RC",
    "sg:province":"Drenthe",
    "wof:name":"Sandra",
    "wof:placetype":"venue"
},
  "geometry": {"coordinates":[6.569734,53.019077],"type":"Point"}
}