{
  "type": "Feature",
  "properties": {
    "addr:full":"Kade 30 Rucphen North Brabant 4715 AE",
    "addr:housenumber":"30",
    "addr:postcode":"4715 ae",
    "addr:street":"Kade",
    "iso:country":"NL",
    "sg:address":"Kade 30",
    "sg:city":"Rucphen",
    "sg:orig_category":"Diverse Consumentenartikelen Gh",
    "sg:phone":"+31 165 342 959",
    "sg:postcode":"4715 AE",
    "sg:province":"North Brabant",
    "wof:name":"Interkado",
    "wof:placetype":"venue"
},
  "geometry": {"coordinates":[4.551391,51.531754],"type":"Point"}
}