{
  "type": "Feature",
  "properties": {
    "addr:full":"Waterlelie 2 Abcoude Utrecht 1391 TN",
    "addr:housenumber":"2",
    "addr:postcode":"1391",
    "addr:street":"Waterlelie",
    "iso:country":"NL",
    "sg:address":"Waterlelie 2",
    "sg:city":"Abcoude",
    "sg:orig_category":"Verhuur Audiovisuele Apparatuur",
    "sg:phone":"+31 294 283 441",
    "sg:postcode":"1391 TN",
    "sg:province":"Utrecht",
    "wof:name":"Oscar Pieterse Geluidstechniek",
    "wof:placetype":"venue"
},
  "geometry": {"coordinates":[4.975154,52.276588],"type":"Point"}
}