{
  "type": "Feature",
  "properties": {
    "addr:full":"Stationsstraat 34 Deurne Noord-Brabant 5751 HE",
    "addr:housenumber":"34",
    "addr:postcode":"5751 he",
    "addr:street":"Stationsstraat",
    "iso:country":"NL",
    "sg:address":"Stationsstraat 34",
    "sg:city":"Deurne",
    "sg:orig_category":"Verlichting And Huishoudartikelen",
    "sg:phone":"+31 493 312 404",
    "sg:postcode":"5751 HE",
    "sg:province":"Noord-Brabant",
    "wof:name":"Magazijn De Molen",
    "wof:placetype":"venue"
},
  "geometry": {"coordinates":[5.792491,51.46212],"type":"Point"}
}