{
  "type": "Feature",
  "properties": {
    "addr:full":"Nieuweweg 64 Soest Utrecht 3765 GE",
    "addr:housenumber":"64",
    "addr:postcode":"3765",
    "addr:street":"Nieuweweg",
    "iso:country":"NL",
    "sg:address":"Nieuweweg 64",
    "sg:city":"Soest",
    "sg:classifiers":[
        {
            "category":"Fast Food",
            "type":"Food & Drink"
        }
    ],
    "sg:phone":"+31 35 602 6857",
    "sg:postcode":"3765 GE",
    "sg:province":"Utrecht",
    "sg:tags":[
        "afhaal",
        "restaurant"
    ],
    "wof:name":"Riksja",
    "wof:placetype":"venue"
},
  "geometry": {"coordinates":[5.300385,52.184044],"type":"Point"}
}