{
  "type": "Feature",
  "properties": {
    "addr:full":"Achterhaven 51 Edam Noord-Holland 1135 XS",
    "addr:housenumber":"51",
    "addr:postcode":"1135 xs",
    "addr:street":"Achterhaven",
    "iso:country":"NL",
    "sg:address":"Achterhaven 51",
    "sg:city":"Edam",
    "sg:orig_category":"Maquettes",
    "sg:phone":"+31 6 21564603",
    "sg:postcode":"1135 XS",
    "sg:province":"Noord-Holland",
    "wof:name":"Karsten, C J",
    "wof:placetype":"venue"
},
  "geometry": {"coordinates":[5.054026,52.513779],"type":"Point"}
}