{
  "type": "Feature",
  "properties": {
    "addr:full":"Amstel 1 Amsterdam Noord-Holland 1011 PN",
    "addr:housenumber":"1",
    "addr:postcode":"1011 pn",
    "addr:street":"Amstel",
    "iso:country":"NL",
    "sg:address":"Amstel 1",
    "sg:city":"Amsterdam",
    "sg:orig_category":"Voorlichtingsbureaus",
    "sg:phone":"+31 20 624 1111",
    "sg:postcode":"1011 PN",
    "sg:province":"Noord-Holland",
    "sg:website":"http://www.amsterdam.nl",
    "wof:name":"Voorlichtingscentrum, Gemeente Amsterdam",
    "wof:placetype":"venue"
},
  "geometry": {"coordinates":[4.899899,52.367371],"type":"Point"}
}