{
  "type": "Feature",
  "properties": {
    "iso:country":"NL",
    "sg:address":"Poelruit 31",
    "sg:city":"Boskoop",
    "sg:orig_category":"Voetbalverenigingen",
    "sg:phone":"+31 172 215 849",
    "sg:postcode":"2771 RD",
    "sg:province":"South Holland",
    "wof:name":"Bvp",
    "wof:placetype":"venue"
},
  "geometry": {"coordinates":[4.639581,52.072811],"type":"Point"}
}