{
  "type": "Feature",
  "properties": {
    "addr:full":"Domselaerstr 114 Amsterdam Noord-Holland 1093 MA",
    "addr:housenumber":"114",
    "addr:postcode":"1093 ma",
    "iso:country":"NL",
    "sg:address":"Domselaerstr 114",
    "sg:city":"Amsterdam",
    "sg:orig_category":"Vertaalbureaus",
    "sg:phone":"+31 20 663 5837",
    "sg:postcode":"1093 MA",
    "sg:province":"Noord-Holland",
    "wof:name":"Quadt & Rieger",
    "wof:placetype":"venue"
},
  "geometry": {"coordinates":[4.928453,52.359985],"type":"Point"}
}