{
  "type": "Feature",
  "properties": {
    "iso:country":"NL",
    "sg:address":"Postbus 2129",
    "sg:city":"Hoogeveen",
    "sg:orig_category":"Verzekeringen - Verzekeringskantoren",
    "sg:phone":"+31 524 291 040",
    "sg:postcode":"7900 BC",
    "sg:province":"British Columbia",
    "sg:website":"http://www.elswijk-esmeijer.nl",
    "wof:name":"Elswijk & Esmeijer, Van",
    "wof:placetype":"venue"
},
  "geometry": {"coordinates":[-126.555511,54.485668],"type":"Point"}
}