{
  "type": "Feature",
  "properties": {
    "addr:full":"F Olterdissenstr 56 Maastricht Limburg 6217 HW",
    "addr:housenumber":"56",
    "addr:postcode":"6217 hw",
    "iso:country":"NL",
    "sg:address":"F Olterdissenstr 56",
    "sg:city":"Maastricht",
    "sg:orig_category":"Schilders",
    "sg:phone":"+31 43 343 7598",
    "sg:postcode":"6217 HW",
    "sg:province":"Limburg",
    "wof:name":"Vanderstappen, G",
    "wof:placetype":"venue"
},
  "geometry": {"coordinates":[5.6680788994,50.8545913696],"type":"Point"}
}