{
  "type": "Feature",
  "properties": {
    "addr:full":"Hamwg 15 Harkstede Groningen 9617 AP",
    "addr:housenumber":"15",
    "addr:postcode":"9617 ap",
    "addr:street":"Hamwg",
    "iso:country":"NL",
    "sg:address":"Hamwg 15",
    "sg:city":"Harkstede",
    "sg:orig_category":"Plafonds",
    "sg:phone":"+31 50 549 2040",
    "sg:postcode":"9617 AP",
    "sg:province":"Groningen",
    "wof:name":"Kajuit Wanden En Plafonds",
    "wof:placetype":"venue"
},
  "geometry": {"coordinates":[6.70184,53.214737],"type":"Point"}
}