{
  "type": "Feature",
  "properties": {
    "iso:country":"NL",
    "sg:address":"Hoofdstraat 31",
    "sg:city":"Nieuwolda",
    "sg:classifiers":[
        {
            "category":"Bakery",
            "type":"Food & Drink"
        }
    ],
    "sg:phone":"+31 596 541 293",
    "sg:postcode":"9944 AB",
    "sg:province":"Groningen",
    "sg:tags":[
        "brood",
        "banket"
    ],
    "wof:name":"J J Niehof",
    "wof:placetype":"venue"
},
  "geometry": {"coordinates":[6.974985,53.244869],"type":"Point"}
}