{
  "type": "Feature",
  "properties": {
    "iso:country":"NL",
    "sg:address":"Ambachtsherenln 18",
    "sg:city":"Raamsdonksveer",
    "sg:orig_category":"Schoenen - Reparaties",
    "sg:phone":"+31 162 514 301",
    "sg:postcode":"4941 AS",
    "sg:province":"Noord-Brabant",
    "wof:name":"Iersel, J Van",
    "wof:placetype":"venue"
},
  "geometry": {"coordinates":[4.879671,51.694592],"type":"Point"}
}