{
  "type": "Feature",
  "properties": {
    "addr:full":"Parkwykln 131 Almere NL. 1326 DS",
    "addr:housenumber":"131",
    "addr:postcode":"1326 ds",
    "addr:street":"Nl.",
    "iso:country":"NL",
    "sg:address":"Parkwykln 131",
    "sg:city":"Almere",
    "sg:orig_category":"Glasdecoratie",
    "sg:phone":"+31 36 537 8633",
    "sg:postcode":"1326 DS",
    "sg:province":"NL.",
    "wof:name":"Emily'S Art'S",
    "wof:placetype":"venue"
},
  "geometry": {"coordinates":[5.24996,52.368961],"type":"Point"}
}