{
  "type": "Feature",
  "properties": {
    "iso:country":"NL",
    "sg:address":"Zeestr 55",
    "sg:city":"S Gravenhage",
    "sg:orig_category":"Ambassades/Consulaten",
    "sg:phone":"+31 70 346 4900",
    "sg:postcode":"2518 AA",
    "sg:province":"Zuid-Holland",
    "sg:website":"http://www.embassy.nl",
    "wof:name":"Ambassade Diensten",
    "wof:placetype":"venue"
},
  "geometry": {"coordinates":[4.29348,52.080318],"type":"Point"}
}