{
  "type": "Feature",
  "properties": {
    "addr:full":"Rozenlaan 10 Valkenburg Zh South Holland 2235 ER",
    "addr:housenumber":"10",
    "addr:postcode":"zh;2235 er",
    "addr:street":"Rozenlaan",
    "iso:country":"NL",
    "sg:address":"Rozenlaan 10",
    "sg:city":"Valkenburg Zh",
    "sg:orig_category":"Bloemen And Planten",
    "sg:phone":"+31 71 407 4590",
    "sg:postcode":"2235 ER",
    "sg:province":"South Holland",
    "wof:name":"De Bloemenkoning",
    "wof:placetype":"venue"
},
  "geometry": {"coordinates":[4.438394,52.179161],"type":"Point"}
}