{
  "type": "Feature",
  "properties": {
    "addr:full":"M Meeswg 115 Rotterdam Zuid-Holland 3068 AV",
    "addr:housenumber":"115",
    "addr:postcode":"3068 av",
    "iso:country":"NL",
    "sg:address":"M Meeswg 115",
    "sg:city":"Rotterdam",
    "sg:orig_category":"Psychologen",
    "sg:phone":"+31 10 407 2660",
    "sg:postcode":"3068 AV",
    "sg:province":"Zuid-Holland",
    "sg:website":"http://www.ey.nl",
    "wof:name":"Ernst & Young",
    "wof:placetype":"venue"
},
  "geometry": {"coordinates":[4.552689,51.952682],"type":"Point"}
}