{
  "type": "Feature",
  "properties": {
    "addr:full":"Kon Wilhelminapln 5 Krimpen Ad Yssel Zuid-Holland 2921 AB",
    "addr:housenumber":"5",
    "addr:postcode":"2921 ab",
    "addr:street":"Kon Wilhelminapln",
    "iso:country":"NL",
    "sg:address":"Kon Wilhelminapln 5",
    "sg:city":"Krimpen Ad Yssel",
    "sg:orig_category":"Verzekeringen - Verzekeringskantoren",
    "sg:phone":"+31 180 530 000",
    "sg:postcode":"2921 AB",
    "sg:province":"Zuid-Holland",
    "wof:name":"Herk Bv, Makelaardij Drs Van",
    "wof:placetype":"venue"
},
  "geometry": {"coordinates":[4.585131,51.91383],"type":"Point"}
}