{
  "type": "Feature",
  "properties": {
    "addr:full":"Hendoweg 3 Dokkum Friesland 9101 PC",
    "addr:housenumber":"3",
    "addr:postcode":"9101 pc",
    "addr:street":"Hendoweg",
    "iso:country":"NL",
    "sg:address":"Hendoweg 3",
    "sg:city":"Dokkum",
    "sg:orig_category":"Werving And Selectie Van Tijdelijk Personeel And Uitzendkantoren",
    "sg:phone":"+31 519 220 780",
    "sg:postcode":"9101 PC",
    "sg:province":"Friesland",
    "wof:name":"Zaankracht",
    "wof:placetype":"venue"
},
  "geometry": {"coordinates":[5.983645916,53.3263168335],"type":"Point"}
}