{
  "type": "Feature",
  "properties": {
    "addr:full":"Nieuwe Gr 45 Haarlem North Holland 2011 ND",
    "addr:housenumber":"45",
    "addr:postcode":"2011 nd",
    "addr:street":"Nieuwe Gr",
    "iso:country":"NL",
    "sg:address":"Nieuwe Gr 45",
    "sg:city":"Haarlem",
    "sg:orig_category":"Onroerende Goederen",
    "sg:phone":"+31 23 531 0996",
    "sg:postcode":"2011 ND",
    "sg:province":"North Holland",
    "wof:name":"Oeps Bv",
    "wof:placetype":"venue"
},
  "geometry": {"coordinates":[4.633143,52.384949],"type":"Point"}
}