{
  "type": "Feature",
  "properties": {
    "addr:full":"Bloemendalerweg 52 Weesp Noord-Holland 1382 KC",
    "addr:housenumber":"52",
    "addr:postcode":"1382 kc",
    "addr:street":"Bloemendalerweg",
    "iso:country":"NL",
    "sg:address":"Bloemendalerweg 52",
    "sg:city":"Weesp",
    "sg:orig_category":"Pompen And Compressoren Fab",
    "sg:phone":"+31 294 418 686",
    "sg:postcode":"1382 KC",
    "sg:province":"Noord-Holland",
    "wof:name":"Rietschle Bv",
    "wof:placetype":"venue"
},
  "geometry": {"coordinates":[5.023023,52.321217],"type":"Point"}
}