{
  "type": "Feature",
  "properties": {
    "addr:full":"Muntslag 40 Houten Utrecht 3991 WT",
    "addr:housenumber":"40",
    "addr:postcode":"3991 wt",
    "addr:street":"Muntslag",
    "iso:country":"NL",
    "sg:address":"Muntslag 40",
    "sg:city":"Houten",
    "sg:orig_category":"Verenigingen En Stichtingen",
    "sg:phone":"+31 30 637 8511",
    "sg:postcode":"3991 WT",
    "sg:province":"Utrecht",
    "wof:name":"Evangelisch Werkverband, Sticht",
    "wof:placetype":"venue"
},
  "geometry": {"coordinates":[5.149668,52.029926],"type":"Point"}
}