{
  "type": "Feature",
  "properties": {
    "addr:full":"Suiestr 7A Rotterdam South Holland 3028 JA",
    "addr:housenumber":"7a",
    "addr:postcode":"3028 ja",
    "addr:street":"Suiestr",
    "iso:country":"NL",
    "sg:address":"Suiestr 7A",
    "sg:city":"Rotterdam",
    "sg:orig_category":"Bedrijfsmechanisatie En -Automatisering",
    "sg:phone":"+31 6 48081501",
    "sg:postcode":"3028 JA",
    "sg:province":"South Holland",
    "sg:website":"http://www.munitor.nl",
    "wof:name":"Munitor",
    "wof:placetype":"venue"
},
  "geometry": {"coordinates":[4.420933,51.918537],"type":"Point"}
}