{
  "type": "Feature",
  "properties": {
    "addr:full":"Benedenlangs 115 Amsterdam Noord-Holland 1025 KD",
    "addr:housenumber":"115",
    "addr:postcode":"1025 kd",
    "addr:street":"Benedenlangs",
    "iso:country":"NL",
    "sg:address":"Benedenlangs 115",
    "sg:city":"Amsterdam",
    "sg:orig_category":"Diverse Dierenfokkers",
    "sg:phone":"+31 20 636 7804",
    "sg:postcode":"1025 KD",
    "sg:province":"Noord-Holland",
    "wof:name":"F.H. Mosterd",
    "wof:placetype":"venue"
},
  "geometry": {"coordinates":[4.932411,52.3965],"type":"Point"}
}