{
  "type": "Feature",
  "properties": {
    "addr:full":"Bakelsedk 55 Helmond North Brabant 5701 HB",
    "addr:housenumber":"55",
    "addr:postcode":"5701 hb",
    "addr:street":"Bakelsedk",
    "iso:country":"NL",
    "sg:address":"Bakelsedk 55",
    "sg:city":"Helmond",
    "sg:orig_category":"Autorijscholen",
    "sg:phone":"+31 492 542 812",
    "sg:postcode":"5701 HB",
    "sg:province":"North Brabant",
    "wof:name":"Wit, Jan De",
    "wof:placetype":"venue"
},
  "geometry": {"coordinates":[5.674899,51.483543],"type":"Point"}
}