{
  "type": "Feature",
  "properties": {
    "addr:full":"Vughterhage 60 Vught Noord-Brabant 5263 BR",
    "addr:housenumber":"60",
    "addr:postcode":"5263 br",
    "addr:street":"Vughterhage",
    "iso:country":"NL",
    "sg:address":"Vughterhage 60",
    "sg:city":"Vught",
    "sg:orig_category":"Adviesbureaus Bedrijfsorganisatie",
    "sg:phone":"+31 73 684 0188",
    "sg:postcode":"5263 BR",
    "sg:province":"Noord-Brabant",
    "wof:name":"Vanderploeg Bv",
    "wof:placetype":"venue"
},
  "geometry": {"coordinates":[5.286009,51.66164],"type":"Point"}
}