{
  "type": "Feature",
  "properties": {
    "addr:full":"Varnebroek 31 Alkmaar Noord-Holland 1815 HA",
    "addr:housenumber":"31",
    "addr:postcode":"1815 ha",
    "addr:street":"Varnebroek",
    "iso:country":"NL",
    "sg:address":"Varnebroek 31",
    "sg:city":"Alkmaar",
    "sg:orig_category":"Verenigingsgebouwen",
    "sg:phone":"+31 72 512 5357",
    "sg:postcode":"1815 HA",
    "sg:province":"Noord-Holland",
    "wof:name":"Kath Bond Voor Ouderen",
    "wof:placetype":"venue"
},
  "geometry": {"coordinates":[4.739617,52.629307],"type":"Point"}
}