{
  "type": "Feature",
  "properties": {
    "addr:full":"Schoolstraat 3 Venray Limburg 5801 BN",
    "addr:housenumber":"3",
    "addr:postcode":"5801 bn",
    "addr:street":"Schoolstraat",
    "iso:country":"NL",
    "sg:address":"Schoolstraat 3",
    "sg:city":"Venray",
    "sg:orig_category":"Huishoudapparatuur, Televisies And Radio'S",
    "sg:phone":"+31 478 513 535",
    "sg:postcode":"5801 BN",
    "sg:province":"Limburg",
    "wof:name":"Modern Electronics",
    "wof:placetype":"venue"
},
  "geometry": {"coordinates":[5.974418,51.526981],"type":"Point"}
}