{
  "type": "Feature",
  "properties": {
    "addr:full":"Maasboulev 154 Rotterdam Zuid-Holland 3011 TX",
    "addr:housenumber":"154",
    "addr:postcode":"3011 tx",
    "iso:country":"NL",
    "sg:address":"Maasboulev 154",
    "sg:city":"Rotterdam",
    "sg:orig_category":"Vertaalbureaus",
    "sg:phone":"+31 10 404 6803",
    "sg:postcode":"3011 TX",
    "sg:province":"Zuid-Holland",
    "wof:name":"Berkhof Haig, E J",
    "wof:placetype":"venue"
},
  "geometry": {"coordinates":[4.498589,51.91993],"type":"Point"}
}