{
  "type": "Feature",
  "properties": {
    "addr:full":"Tjalk 5 Franeker Friesland 8802 NP",
    "addr:housenumber":"5",
    "addr:postcode":"8802 np",
    "addr:street":"Tjalk",
    "iso:country":"NL",
    "sg:address":"Tjalk 5",
    "sg:city":"Franeker",
    "sg:orig_category":"Autokeuringen",
    "sg:phone":"+31 517 396 738",
    "sg:postcode":"8802 NP",
    "sg:province":"Friesland",
    "wof:name":"Dynamo & Startmotoren Revisiebedrijf Vro",
    "wof:placetype":"venue"
},
  "geometry": {"coordinates":[5.546387,53.196682],"type":"Point"}
}