{
  "type": "Feature",
  "properties": {
    "addr:full":"Oude Apeldoornseweg 28 Apeldoorn Gelderland 7333 NS",
    "addr:housenumber":"28",
    "addr:postcode":"7333 ns",
    "addr:street":"Oude Apeldoornseweg;Gelderland",
    "iso:country":"NL",
    "sg:address":"Oude Apeldoornseweg 28",
    "sg:city":"Apeldoorn",
    "sg:orig_category":"Kantoorartikelen",
    "sg:phone":"+31 55 549 2333",
    "sg:postcode":"7333 NS",
    "sg:province":"Gelderland",
    "wof:name":"Corporate Express Apeldoorn",
    "wof:placetype":"venue"
},
  "geometry": {"coordinates":[5.9698739052,52.1755638123],"type":"Point"}
}