{
  "type": "Feature",
  "properties": {
    "addr:full":"Raalterwg 32 Wesepe Overijssel 8124 AE",
    "addr:housenumber":"32",
    "addr:postcode":"8124 ae",
    "addr:street":"Raalterwg",
    "iso:country":"NL",
    "sg:address":"Raalterwg 32",
    "sg:city":"Wesepe",
    "sg:orig_category":"Horecabenodigdheden",
    "sg:phone":"+31 570 531 266",
    "sg:postcode":"8124 AE",
    "sg:province":"Overijssel",
    "wof:name":"Rijssen Vof, J G Van",
    "wof:placetype":"venue"
},
  "geometry": {"coordinates":[6.206686,52.32626],"type":"Point"}
}