{
  "type": "Feature",
  "properties": {
    "addr:full":"Bangert 21 Medemblik North Holland 1671 AK",
    "addr:housenumber":"21",
    "addr:postcode":"1671 ak",
    "addr:street":"Bangert",
    "iso:country":"NL",
    "sg:address":"Bangert 21",
    "sg:city":"Medemblik",
    "sg:orig_category":"Boekhouders",
    "sg:phone":"+31 227 543 746",
    "sg:postcode":"1671 AK",
    "sg:province":"North Holland",
    "wof:name":"Administratiekantoor F. Kok",
    "wof:placetype":"venue"
},
  "geometry": {"coordinates":[5.107823,52.772507],"type":"Point"}
}