{
  "type": "Feature",
  "properties": {
    "addr:full":"Rotterdamsewg 186 Vlaardingen South Holland 3135 PX",
    "addr:housenumber":"186",
    "addr:postcode":"3135 px",
    "iso:country":"NL",
    "sg:address":"Rotterdamsewg 186",
    "sg:city":"Vlaardingen",
    "sg:orig_category":"Autorijscholen",
    "sg:phone":"+31 10 434 3399",
    "sg:postcode":"3135 PX",
    "sg:province":"South Holland",
    "sg:website":"http://www.de-hoog.nl",
    "wof:name":"Hoog, Auto- En Motorrijschool De",
    "wof:placetype":"venue"
},
  "geometry": {"coordinates":[4.358598,51.916084],"type":"Point"}
}