{
  "type": "Feature",
  "properties": {
    "addr:full":"Buurserstr 152 Haaksbergen NL.08 7481 EL",
    "addr:housenumber":"152;nl.08",
    "addr:postcode":"7481 el",
    "iso:country":"NL",
    "sg:address":"Buurserstr 152",
    "sg:city":"Haaksbergen",
    "sg:orig_category":"Belastingconsulenten/ Belastingadviseurs",
    "sg:phone":"+31 53 572 2293",
    "sg:postcode":"7481 EL",
    "sg:province":"NL.08",
    "wof:name":"Horck, A A",
    "wof:placetype":"venue"
},
  "geometry": {"coordinates":[6.759732,52.153736],"type":"Point"}
}