{
  "type": "Feature",
  "properties": {
    "addr:full":"Langedaal 6 Dordrecht Zuid-Holland 3317 MC",
    "addr:housenumber":"6;3317",
    "addr:postcode":"mc",
    "addr:street":"Langedaal",
    "iso:country":"NL",
    "sg:address":"Langedaal 6",
    "sg:city":"Dordrecht",
    "sg:orig_category":"Verloskundigen",
    "sg:phone":"+31 78 651 3231",
    "sg:postcode":"3317 MC",
    "sg:province":"Zuid-Holland",
    "wof:name":"Oudsten Vernaeve, H E H Den",
    "wof:placetype":"venue"
},
  "geometry": {"coordinates":[4.656437,51.782722],"type":"Point"}
}