{
  "type": "Feature",
  "properties": {
    "addr:full":"Argonautenweg 13 Rotterdam Zuid-Holland 3054 RP",
    "addr:housenumber":"13",
    "addr:postcode":"3054 rp",
    "addr:street":"Argonautenweg",
    "iso:country":"NL",
    "sg:address":"Argonautenweg 13",
    "sg:city":"Rotterdam",
    "sg:classifiers":[
        {
            "category":"Fast Food",
            "type":"Food & Drink"
        }
    ],
    "sg:phone":"+31 10 418 2737",
    "sg:postcode":"3054 RP",
    "sg:province":"Zuid-Holland",
    "sg:tags":[
        "afhaal",
        "restaurant"
    ],
    "wof:name":"The Snackplace Corner",
    "wof:placetype":"venue"
},
  "geometry": {"coordinates":[4.490473,51.960476],"type":"Point"}
}