{
  "type": "Feature",
  "properties": {
    "addr:full":"Bos En Lommerweg 307 Amsterdam Noord-Holland 1055 DX",
    "addr:housenumber":"307",
    "addr:postcode":"1055 dx",
    "addr:street":"Bos En Lommerweg",
    "iso:country":"NL",
    "sg:address":"Bos En Lommerweg 307",
    "sg:city":"Amsterdam",
    "sg:orig_category":"Opticiens",
    "sg:phone":"+31 20 684 3764",
    "sg:postcode":"1055 DX",
    "sg:province":"Noord-Holland",
    "wof:name":"Prins Brillen Bv",
    "wof:placetype":"venue"
},
  "geometry": {"coordinates":[4.8488869667,52.3786087036],"type":"Point"}
}