{
  "type": "Feature",
  "properties": {
    "iso:country":"NL",
    "sg:address":"Bredewg 26 A",
    "sg:city":"Moerkapelle",
    "sg:orig_category":"Antiquiteiten - Restauratie",
    "sg:phone":"+31 79 593 3599",
    "sg:postcode":"2752 AA",
    "sg:province":"Zuid-Holland",
    "wof:name":"Hielema, Meubelstoffeerderij",
    "wof:placetype":"venue"
},
  "geometry": {"coordinates":[4.581607,52.040558],"type":"Point"}
}