{
  "type": "Feature",
  "properties": {
    "iso:country":"NL",
    "sg:address":"Esplanade 28",
    "sg:city":"Hellevoetsluis",
    "sg:orig_category":"Voegwerken",
    "sg:phone":"+31 181 312 191",
    "sg:postcode":"3221 LW",
    "sg:province":"Zuid-Holland",
    "wof:name":"Horik Vof, Van",
    "wof:placetype":"venue"
},
  "geometry": {"coordinates":[4.123661,51.831635],"type":"Point"}
}