{
  "type": "Feature",
  "properties": {
    "addr:full":"Hoofdstraat 61 Exloo Drenthe 7875 AB",
    "addr:housenumber":"61",
    "addr:postcode":"7875 ab",
    "addr:street":"Hoofdstraat",
    "iso:country":"NL",
    "sg:address":"Hoofdstraat 61",
    "sg:city":"Exloo",
    "sg:orig_category":"Biljart- And Snookerzalen",
    "sg:phone":"+31 591 549 188",
    "sg:postcode":"7875 AB",
    "sg:province":"Drenthe",
    "wof:name":"Hollandhotel De Meulenhoek",
    "wof:placetype":"venue"
},
  "geometry": {"coordinates":[6.861945,52.882416],"type":"Point"}
}