{
  "type": "Feature",
  "properties": {
    "addr:full":"Castricummer Werf 20 Castricum Noord-Holland 1901 RW",
    "addr:housenumber":"20;1901",
    "addr:postcode":"rw",
    "addr:street":"Castricummer Werf",
    "iso:country":"NL",
    "sg:address":"Castricummer Werf 20",
    "sg:city":"Castricum",
    "sg:orig_category":"Gespecialiseerde Bouw",
    "sg:phone":"+31 251 658 658",
    "sg:postcode":"1901 RW",
    "sg:province":"Noord-Holland",
    "wof:name":"Marse Montage",
    "wof:placetype":"venue"
},
  "geometry": {"coordinates":[4.665057,52.540195],"type":"Point"}
}