{
  "type": "Feature",
  "properties": {
    "addr:full":"Promenade 100 Rozenburg Zh Zuid-Holland 3181 NB",
    "addr:housenumber":"100",
    "addr:postcode":"zh;3181 nb",
    "addr:street":"Promenade",
    "iso:country":"NL",
    "sg:address":"Promenade 100",
    "sg:city":"Rozenburg Zh",
    "sg:orig_category":"Kappers",
    "sg:phone":"+31 181 212 514",
    "sg:postcode":"3181 NB",
    "sg:province":"Zuid-Holland",
    "wof:name":"Mirjam",
    "wof:placetype":"venue"
},
  "geometry": {"coordinates":[4.240404,51.910465],"type":"Point"}
}