{
  "type": "Feature",
  "properties": {
    "addr:full":"Zwanenzyde 9 Leiden Zuid-Holland 2317 XB",
    "addr:housenumber":"9",
    "addr:postcode":"2317 xb",
    "addr:street":"Zwanenzyde",
    "iso:country":"NL",
    "sg:address":"Zwanenzyde 9",
    "sg:city":"Leiden",
    "sg:orig_category":"Acupunctuur",
    "sg:phone":"+31 71 522 7311",
    "sg:postcode":"2317 XB",
    "sg:province":"Zuid-Holland",
    "wof:name":"Tjong Tjin Tai Chirurg, Dr H",
    "wof:placetype":"venue"
},
  "geometry": {"coordinates":[4.49463,52.154572],"type":"Point"}
}