{
  "type": "Feature",
  "properties": {
    "iso:country":"NL",
    "sg:address":"Demkawg 11C",
    "sg:city":"Utrecht",
    "sg:orig_category":"Loopbaanbegeleiding",
    "sg:phone":"+31 30 242 8185",
    "sg:postcode":"3555 HW",
    "sg:province":"Utrecht",
    "sg:website":"http://www.baantraject.nl",
    "wof:name":"Baantraject",
    "wof:placetype":"venue"
},
  "geometry": {"coordinates":[5.080136,52.111073],"type":"Point"}
}