{
  "type": "Feature",
  "properties": {
    "iso:country":"NL",
    "sg:address":"Oost Voorgors 75",
    "sg:city":"Middelharnis",
    "sg:orig_category":"Pluimveehouderijen",
    "sg:phone":"+31 187 483 902",
    "sg:postcode":"3241 KD",
    "sg:province":"Zuid-Holland",
    "wof:name":"M.A.C. Knape",
    "wof:placetype":"venue"
},
  "geometry": {"coordinates":[4.174964,51.757942],"type":"Point"}
}