{
  "type": "Feature",
  "properties": {
    "iso:country":"NL",
    "sg:address":"Bogaardenstr 50",
    "sg:city":"Maastricht",
    "sg:orig_category":"Verenigingen En Stichtingen",
    "sg:phone":"+31 43 350 0625",
    "sg:postcode":"6211 SP",
    "sg:province":"Limburg",
    "wof:name":"Rooden Leeuw, In Den",
    "wof:placetype":"venue"
},
  "geometry": {"coordinates":[5.688043,50.851246],"type":"Point"}
}