{
  "type": "Feature",
  "properties": {
    "addr:full":"Oude Beekbergerwg 10 Apeldoorn Gelderland 7331 HL",
    "addr:housenumber":"10",
    "addr:postcode":"7331 hl",
    "addr:street":"Oude Beekbergerwg;Gelderland",
    "iso:country":"NL",
    "sg:address":"Oude Beekbergerwg 10",
    "sg:city":"Apeldoorn",
    "sg:orig_category":"Autorijscholen",
    "sg:phone":"+31 55 533 4373",
    "sg:postcode":"7331 HL",
    "sg:province":"Gelderland",
    "sg:website":"http://www.deweerd.net",
    "wof:name":"Weerd Bv Verkeersschool, De",
    "wof:placetype":"venue"
},
  "geometry": {"coordinates":[5.969856,52.201729],"type":"Point"}
}