{
  "type": "Feature",
  "properties": {
    "addr:full":"Gildewg 22 Barneveld Gelderland 3771 NB",
    "addr:housenumber":"22",
    "addr:postcode":"3771 nb",
    "addr:street":"Gildewg;Gelderland",
    "iso:country":"NL",
    "sg:address":"Gildewg 22",
    "sg:city":"Barneveld",
    "sg:orig_category":"Houtgroothandel",
    "sg:phone":"+31 342 424 166",
    "sg:postcode":"3771 NB",
    "sg:province":"Gelderland",
    "wof:name":"Nifterik Holl Bv, Van",
    "wof:placetype":"venue"
},
  "geometry": {"coordinates":[5.603119,52.16539],"type":"Point"}
}