{
  "type": "Feature",
  "properties": {
    "addr:full":"Menso Altingstraat 13 Sleen Provincie Drenthe 7841 CA",
    "addr:housenumber":"13",
    "addr:postcode":"7841 ca",
    "addr:street":"Menso Altingstraat;Provincie Drenthe",
    "iso:country":"NL",
    "sg:address":"Menso Altingstraat 13",
    "sg:city":"Sleen",
    "sg:orig_category":"Verzekeringen",
    "sg:phone":"+31 591 361 388",
    "sg:postcode":"7841 CA",
    "sg:province":"Provincie Drenthe",
    "wof:name":"Ludwig Assurantien En Onroerend Goed",
    "wof:placetype":"venue"
},
  "geometry": {"coordinates":[6.800994,52.777363],"type":"Point"}
}