{
  "type": "Feature",
  "properties": {
    "iso:country":"NL",
    "sg:address":"Dag Hammarskjoldlaan 80",
    "sg:city":"Hellevoetsluis",
    "sg:orig_category":"Verf En Lak",
    "sg:phone":"+31 181 311 491",
    "sg:postcode":"3223 HE",
    "sg:province":"South Holland",
    "wof:name":"Tjallinks",
    "wof:placetype":"venue"
},
  "geometry": {"coordinates":[4.150549,51.845032],"type":"Point"}
}