{
  "type": "Feature",
  "properties": {
    "addr:full":"Proveniersplein 2 Rotterdam Zuid-Holland 3033 EA",
    "addr:housenumber":"2",
    "addr:postcode":"3033 ea",
    "addr:street":"Proveniersplein",
    "iso:country":"NL",
    "sg:address":"Proveniersplein 2",
    "sg:city":"Rotterdam",
    "sg:orig_category":"Bedrijfs- And Managementsconsultants",
    "sg:phone":"+31 10 412 4755",
    "sg:postcode":"3033 EA",
    "sg:province":"Zuid-Holland",
    "wof:name":"Senata Bv Voor Werk En Training",
    "wof:placetype":"venue"
},
  "geometry": {"coordinates":[4.468533,51.926182],"type":"Point"}
}