{
  "type": "Feature",
  "properties": {
    "addr:full":"Brinkstraat 1 Denekamp Overijssel 7591 DM",
    "addr:housenumber":"1",
    "addr:postcode":"7591 dm",
    "addr:street":"Brinkstraat",
    "iso:country":"NL",
    "sg:address":"Brinkstraat 1",
    "sg:city":"Denekamp",
    "sg:orig_category":"Apothekers",
    "sg:phone":"+31 541 354 386",
    "sg:postcode":"7591 DM",
    "sg:province":"Overijssel",
    "wof:name":"Apotheek Denekamp",
    "wof:placetype":"venue"
},
  "geometry": {"coordinates":[7.003954,52.375896],"type":"Point"}
}