{
  "type": "Feature",
  "properties": {
    "addr:full":"Nieuwe Dk 5 Kesteren Gelderland 4041 CZ",
    "addr:housenumber":"5",
    "addr:postcode":"4041",
    "addr:street":"Nieuwe Dk;Gelderland",
    "iso:country":"NL",
    "sg:address":"Nieuwe Dk 5",
    "sg:city":"Kesteren",
    "sg:orig_category":"Pluimveebedrijven En -Handelaren",
    "sg:phone":"+31 488 482 573",
    "sg:postcode":"4041 CZ",
    "sg:province":"Gelderland",
    "wof:name":"Anker Bv, Het",
    "wof:placetype":"venue"
},
  "geometry": {"coordinates":[5.590361,51.922993],"type":"Point"}
}