{
  "type": "Feature",
  "properties": {
    "addr:full":"Liguster 79 Leidschendam South Holland 2262 AC",
    "addr:housenumber":"79",
    "addr:postcode":"2262 ac",
    "addr:street":"Liguster",
    "iso:country":"NL",
    "sg:address":"Liguster 79",
    "sg:city":"Leidschendam",
    "sg:orig_category":"Huishoudelijke Apparaten En Artikelen",
    "sg:phone":"+31 70 320 6920",
    "sg:postcode":"2262 AC",
    "sg:province":"South Holland",
    "sg:website":"http://www.vogeer-tafelenkoken.nl",
    "wof:name":"Geer, Van De",
    "wof:placetype":"venue"
},
  "geometry": {"coordinates":[4.38399,52.087357],"type":"Point"}
}