{
  "type": "Feature",
  "properties": {
    "addr:full":"Van Duivenvoordestraat 9 Lage Zwaluwe Noord-Brabant 4926 BT",
    "addr:housenumber":"9",
    "addr:postcode":"zwaluwe;4926 bt",
    "addr:street":"Van Duivenvoordestraat",
    "iso:country":"NL",
    "sg:address":"Van Duivenvoordestraat 9",
    "sg:city":"Lage Zwaluwe",
    "sg:orig_category":"Boekhouders",
    "sg:phone":"+31 168 483 136",
    "sg:postcode":"4926 BT",
    "sg:province":"Noord-Brabant",
    "wof:name":"Van Der Stelt Administratiekantoor",
    "wof:placetype":"venue"
},
  "geometry": {"coordinates":[4.698999,51.708576],"type":"Point"}
}