{
  "type": "Feature",
  "properties": {
    "addr:full":"Bosland 2 Den Bommel Zuid-Holland 3258 AC",
    "addr:housenumber":"2",
    "addr:postcode":"3258 ac",
    "addr:street":"Bosland",
    "iso:country":"NL",
    "sg:address":"Bosland 2",
    "sg:city":"Den Bommel",
    "sg:orig_category":"Wasserijen",
    "sg:phone":"+31 187 611 655",
    "sg:postcode":"3258 AC",
    "sg:province":"Zuid-Holland",
    "wof:name":"Wasbedrijf Zuid West Ned Bv",
    "wof:placetype":"venue"
},
  "geometry": {"coordinates":[4.2802810669,51.7132492065],"type":"Point"}
}