{
  "type": "Feature",
  "properties": {
    "iso:country":"NL",
    "sg:address":"Visserssteeg 19",
    "sg:city":"Bunschoten Spakenburg",
    "sg:classifiers":[
        {
            "category":"Communications",
            "subcategory":"Television Station",
            "type":"Services"
        }
    ],
    "sg:phone":"+31 33 298 8511",
    "sg:postcode":"3752 BZ",
    "sg:province":"Utrecht",
    "sg:tags":[
        "video",
        "audio",
        "verhuur"
    ],
    "wof:name":"Filmblik Videotheek",
    "wof:placetype":"venue"
},
  "geometry": {"coordinates":[5.37706,52.254162],"type":"Point"}
}