{
  "type": "Feature",
  "properties": {
    "addr:full":"Elingsln 25 Burgum Minnesota 9251 MN",
    "addr:housenumber":"25;9251",
    "addr:postcode":"mn",
    "addr:street":"Elingsln;Minnesota",
    "iso:country":"NL",
    "sg:address":"Elingsln 25",
    "sg:city":"Burgum",
    "sg:orig_category":"Verpakkingen En Verpakkingsmaterialen",
    "sg:phone":"+31 511 482 626",
    "sg:postcode":"9251 MN",
    "sg:province":"Minnesota",
    "wof:name":"Elka Bv",
    "wof:placetype":"venue"
},
  "geometry": {"coordinates":[-93.365471,46.441929],"type":"Point"}
}