{
  "type": "Feature",
  "properties": {
    "iso:country":"NL",
    "sg:address":"Zuidplaspolderwg 3-5",
    "sg:city":"Moordrecht",
    "sg:orig_category":"Projectontwikkeling",
    "sg:phone":"+31 182 375 561",
    "sg:postcode":"2841 DC",
    "sg:province":"Zuid-Holland",
    "wof:name":"Vink Bv",
    "wof:placetype":"venue"
},
  "geometry": {"coordinates":[4.6721100807,51.9930038452],"type":"Point"}
}