{
  "type": "Feature",
  "properties": {
    "addr:full":"Wethouder Gerbertstraat 63 Enschede NL.08 7543 AW",
    "addr:housenumber":"63",
    "addr:postcode":"7543 aw",
    "addr:street":"Wethouder Gerbertstraat",
    "iso:country":"NL",
    "sg:address":"Wethouder Gerbertstraat 63",
    "sg:city":"Enschede",
    "sg:orig_category":"Banken And Kredietinstellingen",
    "sg:phone":"+31 53 476 2217",
    "sg:postcode":"7543 AW",
    "sg:province":"NL.08",
    "wof:name":"Postagentschap Blankestijn",
    "wof:placetype":"venue"
},
  "geometry": {"coordinates":[6.878918,52.205486],"type":"Point"}
}