{
  "type": "Feature",
  "properties": {
    "addr:full":"Dorpsstr 17 Riethoven Noord-Brabant 5561 AS",
    "addr:housenumber":"17",
    "addr:postcode":"5561 as",
    "addr:street":"Dorpsstr",
    "iso:country":"NL",
    "sg:address":"Dorpsstr 17",
    "sg:city":"Riethoven",
    "sg:orig_category":"Oldtimers",
    "sg:phone":"+31 40 201 2650",
    "sg:postcode":"5561 AS",
    "sg:province":"Noord-Brabant",
    "wof:name":"Poppel, Frans Van",
    "wof:placetype":"venue"
},
  "geometry": {"coordinates":[5.387076,51.348301],"type":"Point"}
}