{
  "type": "Feature",
  "properties": {
    "addr:full":"Hoogstraat 47 Werkendam Noord-Brabant 4251 CJ",
    "addr:housenumber":"47",
    "addr:postcode":"4251 cj",
    "addr:street":"Hoogstraat",
    "iso:country":"NL",
    "sg:address":"Hoogstraat 47",
    "sg:city":"Werkendam",
    "sg:orig_category":"Zuivelproducten",
    "sg:phone":"+31 183 503 856",
    "sg:postcode":"4251 CJ",
    "sg:province":"Noord-Brabant",
    "wof:name":"Vers Shop",
    "wof:placetype":"venue"
},
  "geometry": {"coordinates":[4.895317,51.808372],"type":"Point"}
}