{
  "type": "Feature",
  "properties": {
    "addr:full":"G V Ijselsteinstr 181 Amsterdam North Holland 1082 KH",
    "addr:housenumber":"181",
    "addr:postcode":"1082 kh",
    "addr:street":"V Ijselsteinstr",
    "iso:country":"NL",
    "sg:address":"G V Ijselsteinstr 181",
    "sg:city":"Amsterdam",
    "sg:orig_category":"Marktonderzoekbureaus",
    "sg:phone":"+31 20 642 2402",
    "sg:postcode":"1082 KH",
    "sg:province":"North Holland",
    "wof:name":"Tci Communicaties",
    "wof:placetype":"venue"
},
  "geometry": {"coordinates":[4.87756,52.330521],"type":"Point"}
}