{
  "type": "Feature",
  "properties": {
    "iso:country":"NL",
    "sg:address":"Boshoverweg 53",
    "sg:city":"Weert",
    "sg:orig_category":"Kappers",
    "sg:phone":"+31 495 543 892",
    "sg:postcode":"6002 AM",
    "sg:province":"Limburg",
    "wof:name":"Valentino Coiff. M.J.C.H. Steuten-Van Hunsel",
    "wof:placetype":"venue"
},
  "geometry": {"coordinates":[5.685294,51.261177],"type":"Point"}
}