{
  "type": "Feature",
  "properties": {
    "addr:full":"Brusselln 7B Eindhoven North Brabant 5628 TA",
    "addr:housenumber":"7b",
    "addr:postcode":"5628 ta",
    "addr:street":"Brusselln",
    "iso:country":"NL",
    "sg:address":"Brusselln 7B",
    "sg:city":"Eindhoven",
    "sg:orig_category":"Makelaars En Adviseurs Onroerende Goederen",
    "sg:phone":"+31 40 241 5959",
    "sg:postcode":"5628 TA",
    "sg:province":"North Brabant",
    "wof:name":"Uffelen Bv, Van",
    "wof:placetype":"venue"
},
  "geometry": {"coordinates":[5.47191,51.48011],"type":"Point"}
}