{
  "type": "Feature",
  "properties": {
    "iso:country":"NL",
    "sg:address":"Hauwert 74",
    "sg:city":"Hauwert",
    "sg:orig_category":"Bloemen And Planten",
    "sg:phone":"+31 229 201 302",
    "sg:postcode":"1691 EJ",
    "sg:province":"Noord-Holland",
    "wof:name":"Levensmiddelenbedrijf J. Monen",
    "wof:placetype":"venue"
},
  "geometry": {"coordinates":[5.098989,52.706787],"type":"Point"}
}