{
  "type": "Feature",
  "properties": {
    "iso:country":"NL",
    "sg:address":"Fazant 26",
    "sg:city":"Rotterdam",
    "sg:orig_category":"Onderhoud And Reparatie Kantoorapparatuur",
    "sg:phone":"+31 10 438 6280",
    "sg:postcode":"3191 DB",
    "sg:province":"Zuid-Holland",
    "wof:name":"Optimaal",
    "wof:placetype":"venue"
},
  "geometry": {"coordinates":[4.377205,51.855358],"type":"Point"}
}