{
  "type": "Feature",
  "properties": {
    "addr:full":"Lange Hezelstraat 77 Nijmegen Gelderland 6511 CD",
    "addr:housenumber":"77",
    "addr:postcode":"6511 cd",
    "addr:street":"Lange Hezelstraat;Gelderland",
    "iso:country":"NL",
    "sg:address":"Lange Hezelstraat 77",
    "sg:city":"Nijmegen",
    "sg:orig_category":"Herenmodezaken",
    "sg:phone":"+31 24 322 6698",
    "sg:postcode":"6511 CD",
    "sg:province":"Gelderland",
    "wof:name":"Leder Exact",
    "wof:placetype":"venue"
},
  "geometry": {"coordinates":[5.858606,51.848125],"type":"Point"}
}