{
  "type": "Feature",
  "properties": {
    "addr:full":"De Molenpol 7 Lunteren Gelderland 6741 ZN",
    "addr:housenumber":"7",
    "addr:postcode":"6741 zn",
    "addr:street":"De Molenpol;Gelderland",
    "iso:country":"NL",
    "sg:address":"De Molenpol 7",
    "sg:city":"Lunteren",
    "sg:orig_category":"Werving En Selectie",
    "sg:phone":"+31 318 487 188",
    "sg:postcode":"6741 ZN",
    "sg:province":"Gelderland",
    "wof:name":"B & P",
    "wof:placetype":"venue"
},
  "geometry": {"coordinates":[5.6195192337,52.0887565613],"type":"Point"}
}