{
  "type": "Feature",
  "properties": {
    "addr:full":"Westermarkt 36A Tilburg Noord-Brabant 5042 MD",
    "addr:housenumber":"36a",
    "addr:postcode":"5042",
    "addr:street":"Westermarkt",
    "iso:country":"NL",
    "sg:address":"Westermarkt 36A",
    "sg:city":"Tilburg",
    "sg:orig_category":"Natuurvoeding En Reformartikelen",
    "sg:phone":"+31 13 468 0811",
    "sg:postcode":"5042 MD",
    "sg:province":"Noord-Brabant",
    "wof:name":"Westermarkt",
    "wof:placetype":"venue"
},
  "geometry": {"coordinates":[5.053399,51.569523],"type":"Point"}
}