{
  "type": "Feature",
  "properties": {
    "addr:full":"Burg J G Legrowg 21 Paterswolde Drenthe 9765 AD",
    "addr:housenumber":"21",
    "addr:postcode":"9765 ad",
    "addr:street":"Burg J G Legrowg",
    "iso:country":"NL",
    "sg:address":"Burg J G Legrowg 21",
    "sg:city":"Paterswolde",
    "sg:orig_category":"Evenementenverzorging",
    "sg:phone":"+31 50 525 9150",
    "sg:postcode":"9765 AD",
    "sg:province":"Drenthe",
    "wof:name":"D' Ancona Bv, Jacques J",
    "wof:placetype":"venue"
},
  "geometry": {"coordinates":[6.569054,53.143013],"type":"Point"}
}