{
  "type": "Feature",
  "properties": {
    "addr:full":"Narcisstr 33 Brummen Gelderland 6971 AW",
    "addr:housenumber":"33",
    "addr:postcode":"6971 aw",
    "addr:street":"Narcisstr;Gelderland",
    "iso:country":"NL",
    "sg:address":"Narcisstr 33",
    "sg:city":"Brummen",
    "sg:orig_category":"Adviesbureaus Bedrijfsorganisatie",
    "sg:phone":"+31 575 564 521",
    "sg:postcode":"6971 AW",
    "sg:province":"Gelderland",
    "wof:name":"Martens",
    "wof:placetype":"venue"
},
  "geometry": {"coordinates":[6.150545,52.083752],"type":"Point"}
}