{
  "type": "Feature",
  "properties": {
    "iso:country":"NL",
    "sg:address":"Franciscuswg 20A",
    "sg:city":"Hilversum",
    "sg:orig_category":"Autoruiten",
    "sg:phone":"+31 35 623 0511",
    "sg:postcode":"1216 SK",
    "sg:province":"North Holland",
    "wof:name":"Autotaalglas",
    "wof:placetype":"venue"
},
  "geometry": {"coordinates":[5.145611,52.213997],"type":"Point"}
}