{
  "type": "Feature",
  "properties": {
    "iso:country":"NL",
    "sg:address":"Vaartdijk 18",
    "sg:city":"Assendelft",
    "sg:orig_category":"Metaalbekleding And -Behandeling",
    "sg:phone":"+31 75 687 1747",
    "sg:postcode":"1566 PM",
    "sg:province":"Noord-Holland",
    "wof:name":"Las- En Spuitbedrijf Kramer",
    "wof:placetype":"venue"
},
  "geometry": {"coordinates":[4.764067,52.464176],"type":"Point"}
}