{
  "type": "Feature",
  "properties": {
    "iso:country":"NL",
    "sg:address":"Valkenburgerwg 12",
    "sg:city":"Voerendaal",
    "sg:orig_category":"Fietsen En Bromfietsen",
    "sg:phone":"+31 45 575 4244",
    "sg:postcode":"6367 GV",
    "sg:province":"Limburg",
    "wof:name":"Renkens, Jos",
    "wof:placetype":"venue"
},
  "geometry": {"coordinates":[5.919593,50.876423],"type":"Point"}
}