{
  "type": "Feature",
  "properties": {
    "addr:full":"Bloemberg 20 Veeningen Drenthe 7924 PW",
    "addr:housenumber":"20",
    "addr:postcode":"7924 pw",
    "addr:street":"Bloemberg",
    "iso:country":"NL",
    "sg:address":"Bloemberg 20",
    "sg:city":"Veeningen",
    "sg:orig_category":"Advocaten En Advocatenkantoren",
    "sg:phone":"+31 528 391 819",
    "sg:postcode":"7924 PW",
    "sg:province":"Drenthe",
    "wof:name":"Munk",
    "wof:placetype":"venue"
},
  "geometry": {"coordinates":[6.346304,52.652122],"type":"Point"}
}