{
  "type": "Feature",
  "properties": {
    "addr:full":"Nootwg 45 Loosdrecht North Holland 1231 CR",
    "addr:housenumber":"45",
    "addr:postcode":"1231 cr",
    "addr:street":"Nootwg",
    "iso:country":"NL",
    "sg:address":"Nootwg 45",
    "sg:city":"Loosdrecht",
    "sg:orig_category":"Bodemsanering",
    "sg:phone":"+31 35 582 6391",
    "sg:postcode":"1231 CR",
    "sg:province":"North Holland",
    "wof:name":"Ieg",
    "wof:placetype":"venue"
},
  "geometry": {"coordinates":[5.138801,52.199879],"type":"Point"}
}