{
  "type": "Feature",
  "properties": {
    "addr:full":"Marishof 24 Nunspeet Gelderland 8072 JZ",
    "addr:housenumber":"24",
    "addr:postcode":"8072 jz",
    "addr:street":"Marishof;Gelderland",
    "iso:country":"NL",
    "sg:address":"Marishof 24",
    "sg:city":"Nunspeet",
    "sg:orig_category":"Bedrijfsopleidingen",
    "sg:phone":"+31 341 251 884",
    "sg:postcode":"8072 JZ",
    "sg:province":"Gelderland",
    "sg:website":"http://www.meqchange.nl",
    "wof:name":"Meq Change",
    "wof:placetype":"venue"
},
  "geometry": {"coordinates":[5.802802,52.389778],"type":"Point"}
}