{
  "type": "Feature",
  "properties": {
    "addr:full":"De Sleutel 15 Eindhoven Noord-Brabant 5652 AS",
    "addr:housenumber":"15",
    "addr:postcode":"5652 as",
    "addr:street":"De Sleutel",
    "iso:country":"NL",
    "sg:address":"De Sleutel 15",
    "sg:city":"Eindhoven",
    "sg:orig_category":"Fietsen - Fabrieken En Groothandel",
    "sg:phone":"+31 40 295 0130",
    "sg:postcode":"5652 AS",
    "sg:province":"Noord-Brabant",
    "wof:name":"Lintech",
    "wof:placetype":"venue"
},
  "geometry": {"coordinates":[5.433682,51.42448],"type":"Point"}
}