{
  "type": "Feature",
  "properties": {
    "iso:country":"NL",
    "sg:address":"St Janskerkstr 4",
    "sg:city":"Culemborg",
    "sg:orig_category":"Meubelen - Fabrieken En Groothandel",
    "sg:phone":"+31 345 512 628",
    "sg:postcode":"4101 CZ",
    "sg:province":"Gelderland",
    "wof:name":"Hc 2000",
    "wof:placetype":"venue"
},
  "geometry": {"coordinates":[5.227393,51.955284],"type":"Point"}
}