{
  "type": "Feature",
  "properties": {
    "iso:country":"NL",
    "sg:address":"J C De Haanstraat 21",
    "sg:city":"Lisse",
    "sg:orig_category":"Recreatie",
    "sg:phone":"+31 252 214 998",
    "sg:postcode":"2161 CM",
    "sg:province":"Zuid-Holland",
    "wof:name":"Kindervreugd",
    "wof:placetype":"venue"
},
  "geometry": {"coordinates":[4.537576,52.243423],"type":"Point"}
}