{
  "type": "Feature",
  "properties": {
    "addr:full":"Techniekweg 18 Gorinchem South Holland 4207 HD",
    "addr:housenumber":"18",
    "addr:postcode":"4207 hd",
    "addr:street":"Techniekweg",
    "iso:country":"NL",
    "sg:address":"Techniekweg 18",
    "sg:city":"Gorinchem",
    "sg:orig_category":"Kantoorartikelen",
    "sg:phone":"+31 183 695 555",
    "sg:postcode":"4207 HD",
    "sg:province":"South Holland",
    "wof:name":"Buren Systems International",
    "wof:placetype":"venue"
},
  "geometry": {"coordinates":[4.9999260902,51.8416938782],"type":"Point"}
}