{
  "type": "Feature",
  "properties": {
    "iso:country":"NL",
    "sg:address":"Einsteinstr 44",
    "sg:city":"Dordrecht",
    "sg:orig_category":"Werving En Selectie",
    "sg:phone":"+31 78 618 7679",
    "sg:postcode":"3316 GG",
    "sg:province":"Zuid-Holland",
    "wof:name":"Facillicom Bv",
    "wof:placetype":"venue"
},
  "geometry": {"coordinates":[4.6367230415,51.7766456604],"type":"Point"}
}