{
  "type": "Feature",
  "properties": {
    "addr:full":"Plataanstr 49 Gouda Zuid-Holland 2803 SV",
    "addr:housenumber":"49",
    "addr:postcode":"2803 sv",
    "addr:street":"Plataanstr",
    "iso:country":"NL",
    "sg:address":"Plataanstr 49",
    "sg:city":"Gouda",
    "sg:orig_category":"Autorijscholen",
    "sg:phone":"+31 182 531 203",
    "sg:postcode":"2803 SV",
    "sg:province":"Zuid-Holland",
    "wof:name":"Beer, A C De",
    "wof:placetype":"venue"
},
  "geometry": {"coordinates":[4.688608,52.026905],"type":"Point"}
}