{
  "type": "Feature",
  "properties": {
    "addr:full":"Industriewg 50 Staphorst Overijssel 7951 TA",
    "addr:housenumber":"50",
    "addr:postcode":"7951 ta",
    "addr:street":"Industriewg",
    "iso:country":"NL",
    "sg:address":"Industriewg 50",
    "sg:city":"Staphorst",
    "sg:classifiers":[
        {
            "category":"Retail",
            "subcategory":"Auto Repair",
            "type":"Services"
        }
    ],
    "sg:phone":"+31 522 463 335",
    "sg:postcode":"7951 TA",
    "sg:province":"Overijssel",
    "sg:tags":[
        "garage"
    ],
    "wof:name":"Jaap Bisschop",
    "wof:placetype":"venue"
},
  "geometry": {"coordinates":[6.224861,52.636486],"type":"Point"}
}