{
  "type": "Feature",
  "properties": {
    "iso:country":"NL",
    "sg:address":"Dyksterburen 4",
    "sg:city":"Kimswerd",
    "sg:orig_category":"Vertaalbureaus",
    "sg:phone":"+31 517 579 780",
    "sg:postcode":"8821 LA",
    "sg:province":"Provincie Friesland",
    "sg:website":"http://www.detweehanen.nl",
    "wof:name":"Twee Hanen, De",
    "wof:placetype":"venue"
},
  "geometry": {"coordinates":[5.425691,53.132999],"type":"Point"}
}