{
  "type": "Feature",
  "properties": {
    "addr:full":"Rykswg N 20 Geleen Limburg 6162 AJ",
    "addr:postcode":"6162 aj",
    "addr:street":"N 20",
    "iso:country":"NL",
    "sg:address":"Rykswg N 20",
    "sg:city":"Geleen",
    "sg:orig_category":"Autoradio'S",
    "sg:phone":"+31 46 423 0333",
    "sg:postcode":"6162 AJ",
    "sg:province":"Limburg",
    "sg:website":"http://www.caraudioplus.nl",
    "wof:name":"Car Audio Plus",
    "wof:placetype":"venue"
},
  "geometry": {"coordinates":[5.832196,50.971249],"type":"Point"}
}