{
  "type": "Feature",
  "properties": {
    "addr:full":"Frambozengaarde 1 Houten Utrecht 3992 KC",
    "addr:housenumber":"1",
    "addr:postcode":"3992 kc",
    "addr:street":"Frambozengaarde",
    "iso:country":"NL",
    "sg:address":"Frambozengaarde 1",
    "sg:city":"Houten",
    "sg:orig_category":"Onderhoudswerken",
    "sg:phone":"+31 30 638 0399",
    "sg:postcode":"3992 KC",
    "sg:province":"Utrecht",
    "wof:name":"Leemrijse Vof",
    "wof:placetype":"venue"
},
  "geometry": {"coordinates":[5.157163,52.036903],"type":"Point"}
}