{
  "type": "Feature",
  "properties": {
    "iso:country":"NL",
    "sg:address":"Grote Maote 23",
    "sg:city":"Aalten",
    "sg:orig_category":"Vertaal- And Tolkenbureaus",
    "sg:phone":"+31 543 477 789",
    "sg:postcode":"7123 CA",
    "sg:province":"Gelderland",
    "wof:name":"R.E.O. Tolkamp",
    "wof:placetype":"venue"
},
  "geometry": {"coordinates":[6.588056,51.9151],"type":"Point"}
}