{
  "type": "Feature",
  "properties": {
    "addr:full":"Joan Maetsuyckerstraat 38 'S Gravenhage Zuid-Holland 2593 ZL",
    "addr:housenumber":"38",
    "addr:postcode":"2593 zl",
    "addr:street":"Joan Maetsuyckerstraat;' S",
    "iso:country":"NL",
    "sg:address":"Joan Maetsuyckerstraat 38",
    "sg:city":"'S Gravenhage",
    "sg:orig_category":"Binnenhuisarchitecten",
    "sg:phone":"+31 70 385 6223",
    "sg:postcode":"2593 ZL",
    "sg:province":"Zuid-Holland",
    "wof:name":"Hensema Bur V Binnenhuis Arch",
    "wof:placetype":"venue"
},
  "geometry": {"coordinates":[4.338053,52.088425],"type":"Point"}
}