{
  "type": "Feature",
  "properties": {
    "iso:country":"NL",
    "sg:address":"Ballumerbocht 21",
    "sg:city":"Emmeloord",
    "sg:orig_category":"Schilderwerk",
    "sg:phone":"+31 527 614 453",
    "sg:postcode":"8303 KB",
    "sg:province":"Flevoland",
    "wof:name":"Schildersbedrijf C.A. Olgers",
    "wof:placetype":"venue"
},
  "geometry": {"coordinates":[5.727359,52.715481],"type":"Point"}
}