{
  "type": "Feature",
  "properties": {
    "iso:country":"NL",
    "sg:address":"Rijksstraatweg 86",
    "sg:city":"De Meern",
    "sg:orig_category":"Boekhouders",
    "sg:phone":"+31 30 666 1967",
    "sg:postcode":"3454 JG",
    "sg:province":"Utrecht",
    "wof:name":"Antoon Glissenaar Administratiekantoor",
    "wof:placetype":"venue"
},
  "geometry": {"coordinates":[5.040928,52.081886],"type":"Point"}
}