{
  "type": "Feature",
  "properties": {
    "addr:full":"Doomhoeve 59 Maastricht Limburg 6225 DG",
    "addr:housenumber":"59",
    "addr:postcode":"6225 dg",
    "addr:street":"Doomhoeve",
    "iso:country":"NL",
    "sg:address":"Doomhoeve 59",
    "sg:city":"Maastricht",
    "sg:orig_category":"Adviesbureaus Elektronica",
    "sg:phone":"+31 43 363 8058",
    "sg:postcode":"6225 DG",
    "sg:province":"Limburg",
    "wof:name":"Rsa",
    "wof:placetype":"venue"
},
  "geometry": {"coordinates":[5.727059,50.858932],"type":"Point"}
}