{
  "type": "Feature",
  "properties": {
    "addr:full":"Drievogelstr 128 Kerkrade Limburg 6466 GR",
    "addr:housenumber":"128",
    "addr:postcode":"6466",
    "iso:country":"NL",
    "sg:address":"Drievogelstr 128",
    "sg:city":"Kerkrade",
    "sg:orig_category":"Grondwerken",
    "sg:phone":"+31 45 541 1453",
    "sg:postcode":"6466 GR",
    "sg:province":"Limburg",
    "wof:name":"Maessen, H",
    "wof:placetype":"venue"
},
  "geometry": {"coordinates":[6.016024,50.852909],"type":"Point"}
}