{
  "type": "Feature",
  "properties": {
    "addr:full":"Fransebaan 16 Eindhoven Noord-Brabant 5627 JD",
    "addr:housenumber":"16",
    "addr:postcode":"5627 jd",
    "addr:street":"Fransebaan",
    "iso:country":"NL",
    "sg:address":"Fransebaan 16",
    "sg:city":"Eindhoven",
    "sg:orig_category":"Boekhouders",
    "sg:phone":"+31 40 242 2399",
    "sg:postcode":"5627 JD",
    "sg:province":"Noord-Brabant",
    "wof:name":"Administratiekantoor Wiesen",
    "wof:placetype":"venue"
},
  "geometry": {"coordinates":[5.45043,51.480297],"type":"Point"}
}