{
  "type": "Feature",
  "properties": {
    "addr:full":"Rykswg 111 Gaanderen Gelderland 7011 DT",
    "addr:housenumber":"111",
    "addr:postcode":"7011 dt",
    "addr:street":"Gelderland",
    "iso:country":"NL",
    "sg:address":"Rykswg 111",
    "sg:city":"Gaanderen",
    "sg:orig_category":"Bloemen En Planten",
    "sg:phone":"+31 315 340 931",
    "sg:postcode":"7011 DT",
    "sg:province":"Gelderland",
    "wof:name":"Fleur, La",
    "wof:placetype":"venue"
},
  "geometry": {"coordinates":[6.346154,51.928734],"type":"Point"}
}