{
  "type": "Feature",
  "properties": {
    "addr:full":"Vaartuigenln 51 Woerden Utrecht 3448 WL",
    "addr:housenumber":"51",
    "addr:postcode":"3448 wl",
    "addr:street":"Vaartuigenln",
    "iso:country":"NL",
    "sg:address":"Vaartuigenln 51",
    "sg:city":"Woerden",
    "sg:orig_category":"Facilitaire Dienstverlening",
    "sg:phone":"+31 348 565 703",
    "sg:postcode":"3448 WL",
    "sg:province":"Utrecht",
    "wof:name":"Gpa Consultancy",
    "wof:placetype":"venue"
},
  "geometry": {"coordinates":[4.853315,52.07996],"type":"Point"}
}