{
  "type": "Feature",
  "properties": {
    "addr:full":"Epicurusstraat 23 Rotterdam Zuid-Holland 3076 NG",
    "addr:housenumber":"23",
    "addr:postcode":"3076 ng",
    "addr:street":"Epicurusstraat",
    "iso:country":"NL",
    "sg:address":"Epicurusstraat 23",
    "sg:city":"Rotterdam",
    "sg:orig_category":"Film-, Tv- And Videoproductie",
    "sg:phone":"+31 6 21290783",
    "sg:postcode":"3076 NG",
    "sg:province":"Zuid-Holland",
    "wof:name":"Sacred",
    "wof:placetype":"venue"
},
  "geometry": {"coordinates":[4.524571,51.879196],"type":"Point"}
}