{
  "type": "Feature",
  "properties": {
    "iso:country":"NL",
    "sg:address":"Boeninln 112",
    "sg:city":"Amsterdam Zuidoost",
    "sg:orig_category":"Administratie- En Boekhoudkantoren",
    "sg:phone":"+31 20 698 0818",
    "sg:postcode":"1102 TN",
    "sg:province":"Noord-Holland",
    "wof:name":"Oben",
    "wof:placetype":"venue"
},
  "geometry": {"coordinates":[4.94249,52.320126],"type":"Point"}
}