{
  "type": "Feature",
  "properties": {
    "addr:full":"Tolstraat 7 Haaksbergen NL.08 7482 DC",
    "addr:housenumber":"7;nl.08",
    "addr:postcode":"7482",
    "addr:street":"Tolstraat",
    "iso:country":"NL",
    "sg:address":"Tolstraat 7",
    "sg:city":"Haaksbergen",
    "sg:orig_category":"Kantoorartikelen",
    "sg:phone":"+31 53 572 5010",
    "sg:postcode":"7482 DC",
    "sg:province":"NL.08",
    "wof:name":"Gecos Pharma Bv",
    "wof:placetype":"venue"
},
  "geometry": {"coordinates":[6.7118477821,52.1536865234],"type":"Point"}
}