{
  "type": "Feature",
  "properties": {
    "addr:full":"Valkenboslaan 251 'S Gravenhage South Holland 2563 CW",
    "addr:housenumber":"251 '",
    "addr:postcode":"2563 cw",
    "addr:street":"Valkenboslaan",
    "iso:country":"NL",
    "sg:address":"Valkenboslaan 251",
    "sg:city":"'S Gravenhage",
    "sg:orig_category":"Boekhouders",
    "sg:phone":"+31 70 346 4546",
    "sg:postcode":"2563 CW",
    "sg:province":"South Holland",
    "wof:name":"Aam Advies & Administratiekantoor",
    "wof:placetype":"venue"
},
  "geometry": {"coordinates":[4.275148,52.070583],"type":"Point"}
}