{
  "type": "Feature",
  "properties": {
    "addr:full":"Raadhuisstraat 158 Alphen A/D Rijn South Holland 2406 AJ",
    "addr:housenumber":"158",
    "addr:postcode":"2406 aj",
    "addr:street":"Raadhuisstraat",
    "iso:country":"NL",
    "sg:address":"Raadhuisstraat 158",
    "sg:city":"Alphen A/D Rijn",
    "sg:orig_category":"Bedrijfsinventaris Gh",
    "sg:phone":"+31 172 477 796",
    "sg:postcode":"2406 AJ",
    "sg:province":"South Holland",
    "wof:name":"Piekhaar & Co",
    "wof:placetype":"venue"
},
  "geometry": {"coordinates":[4.66341,52.127357],"type":"Point"}
}