{
  "type": "Feature",
  "properties": {
    "iso:country":"NL",
    "sg:address":"Lavendelstr 4",
    "sg:city":"Bergeyk",
    "sg:orig_category":"Accountants - Administratie- Consulenten En -Kantoren",
    "sg:phone":"+31 497 571 786",
    "sg:postcode":"5571 HM",
    "sg:province":"Noord-Brabant",
    "wof:name":"Broek, Van Den",
    "wof:placetype":"venue"
},
  "geometry": {"coordinates":[5.355685,51.319462],"type":"Point"}
}