{
  "type": "Feature",
  "properties": {
    "addr:full":"K De Grotestr 65 Wyk By Duurstede Utrecht 3962 CK",
    "addr:housenumber":"65",
    "addr:postcode":"3962 ck",
    "addr:street":"K De Grotestr;Duurstede",
    "iso:country":"NL",
    "sg:address":"K De Grotestr 65",
    "sg:city":"Wyk By Duurstede",
    "sg:orig_category":"Postkantoren",
    "sg:phone":"+31 343 575 054",
    "sg:postcode":"3962 CK",
    "sg:province":"Utrecht",
    "sg:website":"http://www.postkantoor.nl",
    "wof:name":"Postkantoor",
    "wof:placetype":"venue"
},
  "geometry": {"coordinates":[5.3754,51.985378],"type":"Point"}
}