{
  "type": "Feature",
  "properties": {
    "iso:country":"NL",
    "sg:address":"Bronbeekln 14",
    "sg:city":"Arnhem",
    "sg:orig_category":"Organisatiebureaus",
    "sg:phone":"+31 26 364 4402",
    "sg:postcode":"6824 PG",
    "sg:province":"Gelderland",
    "sg:website":"http://www.hostessing.nl",
    "wof:name":"Ovco",
    "wof:placetype":"venue"
},
  "geometry": {"coordinates":[5.9484429359,51.9964332581],"type":"Point"}
}