{
  "type": "Feature",
  "properties": {
    "addr:full":"Westblaak 24 Rotterdam South Holland 3012 KM",
    "addr:housenumber":"24",
    "addr:postcode":"3012 km",
    "addr:street":"Westblaak",
    "iso:country":"NL",
    "sg:address":"Westblaak 24",
    "sg:city":"Rotterdam",
    "sg:orig_category":"Werving And Selectie Van Tijdelijk Personeel And Uitzendkantoren",
    "sg:phone":"+31 10 411 5355",
    "sg:postcode":"3012 KM",
    "sg:province":"South Holland",
    "wof:name":"Content",
    "wof:placetype":"venue"
},
  "geometry": {"coordinates":[4.4787402153,51.917098999],"type":"Point"}
}