{
  "type": "Feature",
  "properties": {
    "addr:full":"Vaart Noordzijde 111 Appelscha Provincie Friesland 8426 AX",
    "addr:housenumber":"111",
    "addr:postcode":"8426 ax",
    "addr:street":"Vaart Noordzijde;Provincie Friesland",
    "iso:country":"NL",
    "sg:address":"Vaart Noordzijde 111",
    "sg:city":"Appelscha",
    "sg:orig_category":"Goederenvervoer Over De Weg",
    "sg:phone":"+31 516 432 923",
    "sg:postcode":"8426 AX",
    "sg:province":"Provincie Friesland",
    "wof:name":"Transportbedrijf Libbe Karsten",
    "wof:placetype":"venue"
},
  "geometry": {"coordinates":[6.364223,52.951805],"type":"Point"}
}