{
  "type": "Feature",
  "properties": {
    "iso:country":"NL",
    "sg:address":"Gageldonk 28",
    "sg:city":"Bavel",
    "sg:classifiers":[
        {
            "category":"Personal",
            "subcategory":"Nail Salon",
            "type":"Services"
        }
    ],
    "sg:phone":"+31 161 434 810",
    "sg:postcode":"4854 LH",
    "sg:province":"North Brabant",
    "sg:tags":[
        "pedicure"
    ],
    "wof:name":"Elbers-Broers, A",
    "wof:placetype":"venue"
},
  "geometry": {"coordinates":[4.828848,51.569061],"type":"Point"}
}