{
  "type": "Feature",
  "properties": {
    "addr:full":"De Bleek 5 Hengevelde Overijssel 7496 DB",
    "addr:housenumber":"5",
    "addr:postcode":"7496 db",
    "addr:street":"De Bleek",
    "iso:country":"NL",
    "sg:address":"De Bleek 5",
    "sg:city":"Hengevelde",
    "sg:orig_category":"Verenigingen En Stichtingen",
    "sg:phone":"+31 547 333 800",
    "sg:postcode":"7496 DB",
    "sg:province":"Overijssel",
    "wof:name":"Zomerfeesten, Sticht",
    "wof:placetype":"venue"
},
  "geometry": {"coordinates":[6.630151,52.198547],"type":"Point"}
}