{
  "type": "Feature",
  "properties": {
    "addr:full":"Nw Havenwg 39 Hilversum Noord-Holland 1216 BK",
    "addr:housenumber":"39",
    "addr:postcode":"1216 bk",
    "iso:country":"NL",
    "sg:address":"Nw Havenwg 39",
    "sg:city":"Hilversum",
    "sg:orig_category":"Keukens",
    "sg:phone":"+31 35 625 5222",
    "sg:postcode":"1216 BK",
    "sg:province":"Noord-Holland",
    "sg:website":"http://www.schipperhilv.nl",
    "wof:name":"Schipper Keukens",
    "wof:placetype":"venue"
},
  "geometry": {"coordinates":[5.145928,52.223736],"type":"Point"}
}