{
  "type": "Feature",
  "properties": {
    "addr:full":"Grotewaard 3 Zoetermeer Zuid-Holland 2716 XP",
    "addr:housenumber":"3",
    "addr:postcode":"2716 xp",
    "addr:street":"Grotewaard",
    "iso:country":"NL",
    "sg:address":"Grotewaard 3",
    "sg:city":"Zoetermeer",
    "sg:orig_category":"Pensioenen",
    "sg:phone":"+31 79 320 8889",
    "sg:postcode":"2716 XP",
    "sg:province":"Zuid-Holland",
    "wof:name":"Samenwerkende Financieel Specialisten, De",
    "wof:placetype":"venue"
},
  "geometry": {"coordinates":[4.469352,52.055725],"type":"Point"}
}