{
  "type": "Feature",
  "properties": {
    "addr:full":"J Deckersstr 27 Heeze North Brabant 5591 HN",
    "addr:housenumber":"27",
    "addr:postcode":"5591 hn",
    "iso:country":"NL",
    "sg:address":"J Deckersstr 27",
    "sg:city":"Heeze",
    "sg:orig_category":"Juweliers",
    "sg:phone":"+31 40 241 5149",
    "sg:postcode":"5591 HN",
    "sg:province":"North Brabant",
    "wof:name":"Eric Rooijmans Edelsmid",
    "wof:placetype":"venue"
},
  "geometry": {"coordinates":[5.578265,51.378506],"type":"Point"}
}