{
  "type": "Feature",
  "properties": {
    "addr:full":"Pelikaanwg 19 Werkhoven Utrecht 3985 RZ",
    "addr:housenumber":"19",
    "addr:postcode":"3985 rz",
    "addr:street":"Pelikaanwg",
    "iso:country":"NL",
    "sg:address":"Pelikaanwg 19",
    "sg:city":"Werkhoven",
    "sg:orig_category":"Autorijscholen",
    "sg:phone":"+31 343 551 655",
    "sg:postcode":"3985 RZ",
    "sg:province":"Utrecht",
    "wof:name":"Aperloo Auto/Motorrijschool, Nico",
    "wof:placetype":"venue"
},
  "geometry": {"coordinates":[5.242171,52.024384],"type":"Point"}
}