{
  "type": "Feature",
  "properties": {
    "addr:full":"Dr. Kuijperstraat 6 Oldenzaal Overijssel 7572 VT",
    "addr:housenumber":"6",
    "addr:postcode":"7572",
    "addr:street":"Dr. Kuijperstraat",
    "iso:country":"NL",
    "sg:address":"Dr. Kuijperstraat 6",
    "sg:city":"Oldenzaal",
    "sg:orig_category":"Verzekeringen",
    "sg:phone":"+31 541 516 619",
    "sg:postcode":"7572 VT",
    "sg:province":"Overijssel",
    "wof:name":"H.M.G. Hazewinkel",
    "wof:placetype":"venue"
},
  "geometry": {"coordinates":[6.923675,52.317482],"type":"Point"}
}