{
  "type": "Feature",
  "properties": {
    "addr:full":"Diemerschans 25 Nieuwegein Utrecht 3432 CW",
    "addr:housenumber":"25",
    "addr:postcode":"3432 cw",
    "addr:street":"Diemerschans",
    "iso:country":"NL",
    "sg:address":"Diemerschans 25",
    "sg:city":"Nieuwegein",
    "sg:orig_category":"Administratie- En Boekhoudkantoren",
    "sg:phone":"+31 30 636 5449",
    "sg:postcode":"3432 CW",
    "sg:province":"Utrecht",
    "wof:name":"Eck, Van",
    "wof:placetype":"venue"
},
  "geometry": {"coordinates":[5.096845,52.018791],"type":"Point"}
}