{
  "type": "Feature",
  "properties": {
    "addr:full":"Stationspk 100 Sliedrecht Zuid-Holland 3364 DA",
    "addr:housenumber":"100",
    "addr:postcode":"3364 da",
    "iso:country":"NL",
    "sg:address":"Stationspk 100",
    "sg:city":"Sliedrecht",
    "sg:orig_category":"Beveiliging",
    "sg:phone":"+31 184 480 808",
    "sg:postcode":"3364 DA",
    "sg:province":"Zuid-Holland",
    "wof:name":"Unit 4 Bv",
    "wof:placetype":"venue"
},
  "geometry": {"coordinates":[4.778374,51.828838],"type":"Point"}
}