{
  "type": "Feature",
  "properties": {
    "addr:full":"Pakhuisstr 2 Luchth Schiphol Noord-Holland 1118 DJ",
    "addr:housenumber":"2",
    "addr:postcode":"1118 dj",
    "addr:street":"Pakhuisstr",
    "iso:country":"NL",
    "sg:address":"Pakhuisstr 2",
    "sg:city":"Luchth Schiphol",
    "sg:classifiers":[
        {
            "category":"Retail",
            "subcategory":"Auto Repair",
            "type":"Services"
        }
    ],
    "sg:phone":"+31 20 657 0700",
    "sg:postcode":"1118 DJ",
    "sg:province":"Noord-Holland",
    "sg:tags":[
        "garage"
    ],
    "wof:name":"Ets Schiphol Bv",
    "wof:placetype":"venue"
},
  "geometry": {"coordinates":[4.75221,52.305019],"type":"Point"}
}