{
  "type": "Feature",
  "properties": {
    "addr:full":"Ruiterskwartier 183 Leeuwarden Friesland 8911 BT",
    "addr:housenumber":"183",
    "addr:postcode":"8911 bt",
    "addr:street":"Ruiterskwartier",
    "iso:country":"NL",
    "sg:address":"Ruiterskwartier 183",
    "sg:city":"Leeuwarden",
    "sg:orig_category":"Sportschoenen - Winkels",
    "sg:phone":"+31 58 213 1782",
    "sg:postcode":"8911 BT",
    "sg:province":"Friesland",
    "wof:name":"Coach Leeuwarden",
    "wof:placetype":"venue"
},
  "geometry": {"coordinates":[5.796228,53.199532],"type":"Point"}
}