{
  "type": "Feature",
  "properties": {
    "addr:full":"Berlage Erf 26 Dordrecht Zuid-Holland 3315 JJ",
    "addr:housenumber":"26",
    "addr:postcode":"3315 jj",
    "addr:street":"Berlage Erf",
    "iso:country":"NL",
    "sg:address":"Berlage Erf 26",
    "sg:city":"Dordrecht",
    "sg:orig_category":"Elektronica - Ontwikkeling En Groothandel",
    "sg:phone":"+31 78 621 4120",
    "sg:postcode":"3315 JJ",
    "sg:province":"Zuid-Holland",
    "wof:name":"Bunk",
    "wof:placetype":"venue"
},
  "geometry": {"coordinates":[4.722016,51.804283],"type":"Point"}
}