{
  "type": "Feature",
  "properties": {
    "iso:country":"NL",
    "sg:address":"Javastr 15",
    "sg:city":"Nijmegen",
    "sg:orig_category":"Beeldende Kunstenaars",
    "sg:phone":"+31 24 322 4313",
    "sg:postcode":"6524 LS",
    "sg:province":"Gelderland",
    "wof:name":"Roest, C",
    "wof:placetype":"venue"
},
  "geometry": {"coordinates":[5.862555,51.83744],"type":"Point"}
}