{
  "type": "Feature",
  "properties": {
    "addr:full":"Hoogmadeseweg 48 Leiderdorp Zuid-Holland 2351 CT",
    "addr:housenumber":"48",
    "addr:postcode":"2351 ct",
    "addr:street":"Hoogmadeseweg",
    "iso:country":"NL",
    "sg:address":"Hoogmadeseweg 48",
    "sg:city":"Leiderdorp",
    "sg:orig_category":"Bloemen And Planten",
    "sg:phone":"+31 71 589 5368",
    "sg:postcode":"2351 CT",
    "sg:province":"Zuid-Holland",
    "wof:name":"Rasser Bloemisterij Bv",
    "wof:placetype":"venue"
},
  "geometry": {"coordinates":[4.527181,52.150566],"type":"Point"}
}