{
  "type": "Feature",
  "properties": {
    "addr:full":"Siebangaweg 1 Heerenveen Friesland 8444 DD",
    "addr:housenumber":"1",
    "addr:postcode":"8444 dd",
    "addr:street":"Siebangaweg",
    "iso:country":"NL",
    "sg:address":"Siebangaweg 1",
    "sg:city":"Heerenveen",
    "sg:orig_category":"Materiaalonderzoek",
    "sg:phone":"+31 513 633 683",
    "sg:postcode":"8444 DD",
    "sg:province":"Friesland",
    "sg:website":"http://www.mme-group.com",
    "wof:name":"Mme",
    "wof:placetype":"venue"
},
  "geometry": {"coordinates":[5.929095,52.95845],"type":"Point"}
}