{
  "type": "Feature",
  "properties": {
    "iso:country":"NL",
    "sg:address":"Drielse Wetering 64",
    "sg:city":"Zaandam",
    "sg:orig_category":"Verlichting And Huishoudartikelen",
    "sg:phone":"+31 75 617 3381",
    "sg:postcode":"1509 KR",
    "sg:province":"Noord-Holland",
    "wof:name":"T Winkeltje",
    "wof:placetype":"venue"
},
  "geometry": {"coordinates":[4.834628,52.468025],"type":"Point"}
}