{
  "type": "Feature",
  "properties": {
    "iso:country":"NL",
    "sg:address":"Middelwg W 164",
    "sg:city":"St Annaparochie",
    "sg:orig_category":"Politie",
    "sg:phone":"+31 900 8844",
    "sg:postcode":"9076 GE",
    "sg:province":"Friesland",
    "wof:name":"Politie",
    "wof:placetype":"venue"
},
  "geometry": {"coordinates":[5.641913,53.275532],"type":"Point"}
}