{
  "type": "Feature",
  "properties": {
    "addr:full":"Middelwg W 164 St Annaparochie Friesland 9076 GE",
    "addr:housenumber":"164",
    "addr:postcode":"9076",
    "addr:street":"W;St",
    "iso:country":"NL",
    "sg:address":"Middelwg W 164",
    "sg:city":"St Annaparochie",
    "sg:orig_category":"Politie",
    "sg:phone":"+31 900 8844",
    "sg:postcode":"9076 GE",
    "sg:province":"Friesland",
    "wof:name":"Politie",
    "wof:placetype":"venue"
},
  "geometry": {"coordinates":[5.641913,53.275532],"type":"Point"}
}