{
  "type": "Feature",
  "properties": {
    "iso:country":"NL",
    "sg:address":"Boswg 4",
    "sg:city":"Velp Gld",
    "sg:orig_category":"Bakkerijbenodigdheden En -Grondstoffen",
    "sg:phone":"+31 26 364 6205",
    "sg:postcode":"6881 KK",
    "sg:province":"Gelderland",
    "wof:name":"Vamo Bv",
    "wof:placetype":"venue"
},
  "geometry": {"coordinates":[5.973834,52.000568],"type":"Point"}
}