{
  "type": "Feature",
  "properties": {
    "addr:full":"De Kiepe 256 Enschede Overijssel 7544 HK",
    "addr:housenumber":"256",
    "addr:postcode":"7544 hk",
    "addr:street":"De Kiepe",
    "iso:country":"NL",
    "sg:address":"De Kiepe 256",
    "sg:city":"Enschede",
    "sg:orig_category":"Beeldende Kunstenaars",
    "sg:phone":"+31 53 476 0083",
    "sg:postcode":"7544 HK",
    "sg:province":"Overijssel",
    "wof:name":"Pararealisme, Sticht",
    "wof:placetype":"venue"
},
  "geometry": {"coordinates":[6.884356,52.192333],"type":"Point"}
}