{
  "type": "Feature",
  "properties": {
    "addr:full":"Goudenregenstraat 174 Den Haag Zuid-Holland 2565 GC",
    "addr:housenumber":"174",
    "addr:postcode":"2565 gc",
    "addr:street":"Goudenregenstraat",
    "iso:country":"NL",
    "sg:address":"Goudenregenstraat 174",
    "sg:city":"Den Haag",
    "sg:orig_category":"Partycatering And -Organisatie",
    "sg:phone":"+31 900 7000584",
    "sg:postcode":"2565 GC",
    "sg:province":"Zuid-Holland",
    "wof:name":"Sarinah Catering En Partyservice",
    "wof:placetype":"venue"
},
  "geometry": {"coordinates":[4.263353,52.076935],"type":"Point"}
}