{
  "type": "Feature",
  "properties": {
    "iso:country":"NL",
    "sg:address":"Europawg 222",
    "sg:city":"Zoetermeer",
    "sg:orig_category":"Schilders",
    "sg:phone":"+31 79 342 3888",
    "sg:postcode":"2711 PW",
    "sg:province":"Zuid-Holland",
    "wof:name":"Alex W?hl",
    "wof:placetype":"venue"
},
  "geometry": {"coordinates":[4.489664,52.063419],"type":"Point"}
}