{
  "type": "Feature",
  "properties": {
    "addr:full":"Kometenlaan 43 Bergen Op Zoom North Brabant 4624 CP",
    "addr:housenumber":"43",
    "addr:postcode":"4624 cp",
    "addr:street":"Kometenlaan",
    "iso:country":"NL",
    "sg:address":"Kometenlaan 43",
    "sg:city":"Bergen Op Zoom",
    "sg:orig_category":"Boekhouders",
    "sg:phone":"+31 164 241 476",
    "sg:postcode":"4624 CP",
    "sg:province":"North Brabant",
    "wof:name":"Administratie- & Belastingadv.Bureau G.D",
    "wof:placetype":"venue"
},
  "geometry": {"coordinates":[4.306228,51.48838],"type":"Point"}
}