{
  "type": "Feature",
  "properties": {
    "iso:country":"NL",
    "sg:address":"Alberts Cuypstraat 17-2",
    "sg:city":"Amsterdam",
    "sg:orig_category":"Vertaal- And Tolkenbureaus",
    "sg:phone":"+31 20 470 2131",
    "sg:postcode":"1072 CK",
    "sg:province":"Noord-Holland",
    "wof:name":"Grisel M",
    "wof:placetype":"venue"
},
  "geometry": {"coordinates":[4.88738,52.354744],"type":"Point"}
}