{
  "type": "Feature",
  "properties": {
    "addr:full":"Borgerspk 43 Veendam Groningen 9642 LL",
    "addr:housenumber":"43",
    "addr:postcode":"9642 ll",
    "addr:street":"Borgerspk",
    "iso:country":"NL",
    "sg:address":"Borgerspk 43",
    "sg:city":"Veendam",
    "sg:orig_category":"Adviesbureaus Bedrijfsorganisatie",
    "sg:phone":"+31 598 633 221",
    "sg:postcode":"9642 LL",
    "sg:province":"Groningen",
    "wof:name":"Borgerswold",
    "wof:placetype":"venue"
},
  "geometry": {"coordinates":[6.853888,53.099903],"type":"Point"}
}