{
  "type": "Feature",
  "properties": {
    "addr:full":"Kruisstr 12 Batenburg Gelderland 6634 AG",
    "addr:housenumber":"12",
    "addr:postcode":"6634",
    "addr:street":"Kruisstr;Gelderland",
    "iso:country":"NL",
    "sg:address":"Kruisstr 12",
    "sg:city":"Batenburg",
    "sg:orig_category":"Bloemen En Planten - Decoratie",
    "sg:phone":"+31 487 541 883",
    "sg:postcode":"6634 AG",
    "sg:province":"Gelderland",
    "wof:name":"Ru?Ne Van Batenburg",
    "wof:placetype":"venue"
},
  "geometry": {"coordinates":[5.630588,51.823036],"type":"Point"}
}