{
  "type": "Feature",
  "properties": {
    "addr:full":"Wielewaallaan 69 Tiel Gelderland 4005 EZ",
    "addr:housenumber":"69",
    "addr:postcode":"4005 ez",
    "addr:street":"Wielewaallaan;Gelderland",
    "iso:country":"NL",
    "sg:address":"Wielewaallaan 69",
    "sg:city":"Tiel",
    "sg:orig_category":"Warmtetechniek",
    "sg:phone":"+31 6 54281094",
    "sg:postcode":"4005 EZ",
    "sg:province":"Gelderland",
    "wof:name":"Wijnja",
    "wof:placetype":"venue"
},
  "geometry": {"coordinates":[5.447013855,51.8925209045],"type":"Point"}
}