{
  "type": "Feature",
  "properties": {
    "iso:country":"NL",
    "sg:address":"Oudekerksplein 8",
    "sg:city":"Amsterdam",
    "sg:orig_category":"Kinderopvang Behalve Thuis",
    "sg:phone":"+31 20 638 6575",
    "sg:postcode":"1012 GZ",
    "sg:province":"Noord-Holland",
    "wof:name":"Prinses Juliana",
    "wof:placetype":"venue"
},
  "geometry": {"coordinates":[4.898762,52.374714],"type":"Point"}
}