{
  "type": "Feature",
  "properties": {
    "addr:full":"Komkommerstr 1 Wateringen South Holland 2292 AB",
    "addr:housenumber":"1",
    "addr:postcode":"2292 ab",
    "addr:street":"Komkommerstr",
    "iso:country":"NL",
    "sg:address":"Komkommerstr 1",
    "sg:city":"Wateringen",
    "sg:orig_category":"Artsen - Huisartsen",
    "sg:phone":"+31 174 270 665",
    "sg:postcode":"2292 AB",
    "sg:province":"South Holland",
    "wof:name":"Bruin, C G De",
    "wof:placetype":"venue"
},
  "geometry": {"coordinates":[4.281986,52.01968],"type":"Point"}
}