{
  "type": "Feature",
  "properties": {
    "addr:full":"Westersngl 5 Hoorn Nh Noord-Holland 1622 AB",
    "addr:housenumber":"5",
    "addr:postcode":"1622 ab",
    "addr:street":"Westersngl",
    "iso:country":"NL",
    "sg:address":"Westersngl 5",
    "sg:city":"Hoorn Nh",
    "sg:orig_category":"Schilders",
    "sg:phone":"+31 229 212 837",
    "sg:postcode":"1622 AB",
    "sg:province":"Noord-Holland",
    "wof:name":"Ehs",
    "wof:placetype":"venue"
},
  "geometry": {"coordinates":[5.05207,52.642399],"type":"Point"}
}