{
  "type": "Feature",
  "properties": {
    "addr:full":"Hamerstr 20 Edam Noord-Holland 1135 GA",
    "addr:housenumber":"20",
    "addr:postcode":"1135 ga",
    "addr:street":"Hamerstr",
    "iso:country":"NL",
    "sg:address":"Hamerstr 20",
    "sg:city":"Edam",
    "sg:orig_category":"Autoschade- Herstelbedrijven",
    "sg:phone":"+31 299 371 829",
    "sg:postcode":"1135 GA",
    "sg:province":"Noord-Holland",
    "wof:name":"Hoop & Veerman, De",
    "wof:placetype":"venue"
},
  "geometry": {"coordinates":[5.038798,52.515938],"type":"Point"}
}