{
  "type": "Feature",
  "properties": {
    "addr:full":"Past Heggeln 6 Bunnik Utrecht 3981 GJ",
    "addr:housenumber":"6",
    "addr:postcode":"3981 gj",
    "iso:country":"NL",
    "sg:address":"Past Heggeln 6",
    "sg:city":"Bunnik",
    "sg:orig_category":"Scholen Voor Basisonderwijs",
    "sg:phone":"+31 30 656 3659",
    "sg:postcode":"3981 GJ",
    "sg:province":"Utrecht",
    "wof:name":"Cammingha Rk",
    "wof:placetype":"venue"
},
  "geometry": {"coordinates":[5.194544,52.068981],"type":"Point"}
}