{
  "type": "Feature",
  "properties": {
    "iso:country":"NL",
    "sg:address":"De Zanden 11F",
    "sg:city":"Teuge",
    "sg:orig_category":"Goederenvervoer Over De Weg",
    "sg:phone":"+31 55 323 2389",
    "sg:postcode":"7395 PA",
    "sg:province":"Gelderland",
    "wof:name":"Ballistic",
    "wof:placetype":"venue"
},
  "geometry": {"coordinates":[6.046148,52.240131],"type":"Point"}
}