{
  "type": "Feature",
  "properties": {
    "addr:full":"De Zanden 11F Teuge Gelderland 7395 PA",
    "addr:housenumber":"11f",
    "addr:postcode":"7395",
    "addr:street":"De Zanden;Gelderland",
    "iso:country":"NL",
    "sg:address":"De Zanden 11F",
    "sg:city":"Teuge",
    "sg:orig_category":"Goederenvervoer Over De Weg",
    "sg:phone":"+31 55 323 2389",
    "sg:postcode":"7395 PA",
    "sg:province":"Gelderland",
    "wof:name":"Ballistic",
    "wof:placetype":"venue"
},
  "geometry": {"coordinates":[6.046148,52.240131],"type":"Point"}
}