{
  "type": "Feature",
  "properties": {
    "iso:country":"NL",
    "sg:address":"Palmgr 56",
    "sg:city":"Amsterdam",
    "sg:orig_category":"Fotografie Reclame En Mode",
    "sg:phone":"+31 20 627 5005",
    "sg:postcode":"1015 HN",
    "sg:province":"Noord-Holland",
    "wof:name":"Zwetsloot, Geek",
    "wof:placetype":"venue"
},
  "geometry": {"coordinates":[4.883059,52.382164],"type":"Point"}
}