{
  "type": "Feature",
  "properties": {
    "addr:full":"Oude Rijksweg 6 Nieuw En St Joosland Zeeland 4339 BC",
    "addr:housenumber":"6",
    "addr:postcode":"4339 bc",
    "addr:street":"Oude Rijksweg;Nieuw En St Joosland",
    "iso:country":"NL",
    "sg:address":"Oude Rijksweg 6",
    "sg:city":"Nieuw En St Joosland",
    "sg:orig_category":"Artsen And Specialisten",
    "sg:phone":"+31 118 601 340",
    "sg:postcode":"4339 BC",
    "sg:province":"Zeeland",
    "wof:name":"Apotheekhoudend Huisarts J.C. Ponten",
    "wof:placetype":"venue"
},
  "geometry": {"coordinates":[3.661409,51.485081],"type":"Point"}
}