{
  "type": "Feature",
  "properties": {
    "iso:country":"NL",
    "sg:address":"Tjalkstraat 10",
    "sg:city":"Alkmaar",
    "sg:orig_category":"Boekenuitgeverijen",
    "sg:phone":"+31 72 562 0825",
    "sg:postcode":"1826 DT",
    "sg:province":"Noord-Holland",
    "wof:name":"Idema",
    "wof:placetype":"venue"
},
  "geometry": {"coordinates":[4.763024,52.655388],"type":"Point"}
}