{
  "type": "Feature",
  "properties": {
    "addr:full":"Zandstr 109 Culemborg Gelderland 4101 EE",
    "addr:housenumber":"109",
    "addr:postcode":"4101 ee",
    "addr:street":"Gelderland",
    "iso:country":"NL",
    "sg:address":"Zandstr 109",
    "sg:city":"Culemborg",
    "sg:orig_category":"Kappers",
    "sg:phone":"+31 345 512 123",
    "sg:postcode":"4101 EE",
    "sg:province":"Gelderland",
    "wof:name":"Marian",
    "wof:placetype":"venue"
},
  "geometry": {"coordinates":[5.228968,51.952747],"type":"Point"}
}