{
  "type": "Feature",
  "properties": {
    "addr:full":"V Deventerln 30 Voorburg Zuid-Holland 2271 TX",
    "addr:housenumber":"30",
    "addr:postcode":"2271 tx",
    "addr:street":"V Deventerln",
    "iso:country":"NL",
    "sg:address":"V Deventerln 30",
    "sg:city":"Voorburg",
    "sg:orig_category":"Adviesbureaus Bedrijfsorganisatie",
    "sg:phone":"+31 70 383 9373",
    "sg:postcode":"2271 TX",
    "sg:province":"Zuid-Holland",
    "wof:name":"Versloot Bv",
    "wof:placetype":"venue"
},
  "geometry": {"coordinates":[4.363825,52.068233],"type":"Point"}
}