{
  "type": "Feature",
  "properties": {
    "addr:full":"Mauritslaan 20 Best Noord-Brabant 5684 LE",
    "addr:housenumber":"20",
    "addr:postcode":"5684 le",
    "addr:street":"Mauritslaan",
    "iso:country":"NL",
    "sg:address":"Mauritslaan 20",
    "sg:city":"Best",
    "sg:orig_category":"Diverse Consumentenartikelen Gh",
    "sg:phone":"+31 499 377 080",
    "sg:postcode":"5684 LE",
    "sg:province":"Noord-Brabant",
    "wof:name":"Boosey & Hawkes Benelux",
    "wof:placetype":"venue"
},
  "geometry": {"coordinates":[-101.618134,31.224251],"type":"Point"}
}