{
  "type": "Feature",
  "properties": {
    "addr:full":"Rolafwg N 5 Lopik Utrecht 3411 BH",
    "addr:housenumber":"5",
    "addr:postcode":"3411 bh",
    "addr:street":"N",
    "iso:country":"NL",
    "sg:address":"Rolafwg N 5",
    "sg:city":"Lopik",
    "sg:orig_category":"Banken",
    "sg:phone":"+31 348 551 643",
    "sg:postcode":"3411 BH",
    "sg:province":"Utrecht",
    "wof:name":"Regio Bank",
    "wof:placetype":"venue"
},
  "geometry": {"coordinates":[4.950272,51.972446],"type":"Point"}
}