{
  "type": "Feature",
  "properties": {
    "iso:country":"NL",
    "sg:address":"Oranjebaan 13",
    "sg:city":"Amstelveen",
    "sg:orig_category":"Notarissen En Notariskantoren",
    "sg:phone":"+31 20 496 7676",
    "sg:postcode":"1183 NN",
    "sg:province":"North Holland",
    "wof:name":"B\u00f7Ggemann",
    "wof:placetype":"venue"
},
  "geometry": {"coordinates":[4.881936,52.3013],"type":"Point"}
}