{
  "type": "Feature",
  "properties": {
    "addr:full":"Eindhovensewg 53 Valkenswaard Noord-Brabant 5554 AB",
    "addr:housenumber":"53",
    "addr:postcode":"5554 ab",
    "addr:street":"Eindhovensewg",
    "iso:country":"NL",
    "sg:address":"Eindhovensewg 53",
    "sg:city":"Valkenswaard",
    "sg:orig_category":"Fietsen En Bromfietsen",
    "sg:phone":"+31 40 201 3803",
    "sg:postcode":"5554 AB",
    "sg:province":"Noord-Brabant",
    "wof:name":"Kemps, Wim",
    "wof:placetype":"venue"
},
  "geometry": {"coordinates":[5.459888,51.353504],"type":"Point"}
}