{
  "type": "Feature",
  "properties": {
    "addr:full":"Emmastr 19 Velp Gld Gelderland 6881 SM",
    "addr:housenumber":"19;6881",
    "addr:postcode":"sm",
    "addr:street":"Emmastr;Gld Gelderland",
    "iso:country":"NL",
    "sg:address":"Emmastr 19",
    "sg:city":"Velp Gld",
    "sg:orig_category":"Verlichting",
    "sg:phone":"+31 26 364 6645",
    "sg:postcode":"6881 SM",
    "sg:province":"Gelderland",
    "wof:name":"Kamp, Van Der",
    "wof:placetype":"venue"
},
  "geometry": {"coordinates":[5.973607,51.995007],"type":"Point"}
}