{
  "type": "Feature",
  "properties": {
    "addr:full":"De Eik 68/K354 Hellevoetsluis Zuid-Holland 3224 TD",
    "addr:housenumber":"68 / k354",
    "addr:postcode":"3224 td",
    "addr:street":"De Eik",
    "iso:country":"NL",
    "sg:address":"De Eik 68/K354",
    "sg:city":"Hellevoetsluis",
    "sg:orig_category":"Paramedische Behandelingen",
    "sg:phone":"+31 181 313 325",
    "sg:postcode":"3224 TD",
    "sg:province":"Zuid-Holland",
    "wof:name":"R. Albregts",
    "wof:placetype":"venue"
},
  "geometry": {"coordinates":[4.14703,51.830406],"type":"Point"}
}