{
  "type": "Feature",
  "properties": {
    "iso:country":"NL",
    "sg:address":"Weimarstr 136",
    "sg:city":"S Gravenhage",
    "sg:orig_category":"Schoenen - Reparaties",
    "sg:phone":"+31 70 360 7029",
    "sg:postcode":"2562 HC",
    "sg:province":"Zuid-Holland",
    "sg:website":"http://www.weimarstraat.nl",
    "wof:name":"Geest, Schoenrepar Sleutelserv V/D",
    "wof:placetype":"venue"
},
  "geometry": {"coordinates":[4.28326,52.075001],"type":"Point"}
}