{
  "type": "Feature",
  "properties": {
    "addr:full":"Noorderwg 40 Hilversum North Holland 1221 AA",
    "addr:housenumber":"40",
    "addr:postcode":"1221 aa",
    "addr:street":"Noorderwg",
    "iso:country":"NL",
    "sg:address":"Noorderwg 40",
    "sg:city":"Hilversum",
    "sg:orig_category":"Honden- En Kattentrimsalons",
    "sg:phone":"+31 35 683 5725",
    "sg:postcode":"1221 AA",
    "sg:province":"North Holland",
    "wof:name":"D'Anja",
    "wof:placetype":"venue"
},
  "geometry": {"coordinates":[5.18608,52.226601],"type":"Point"}
}