{
  "type": "Feature",
  "properties": {
    "iso:country":"NL",
    "sg:address":"Postbus 1549",
    "sg:city":"Haarlem",
    "sg:orig_category":"Pensioenen",
    "sg:phone":"+31 23 517 5300",
    "sg:postcode":"2003 BN",
    "sg:province":"North Holland",
    "sg:website":"http://www.wtc-advies.nl",
    "wof:name":"Westland & Van Der Toolen",
    "wof:placetype":"venue"
},
  "geometry": {"coordinates":[4.64225,52.380562],"type":"Point"}
}