{
  "type": "Feature",
  "properties": {
    "iso:country":"NL",
    "sg:address":"Veertwg 20",
    "sg:city":"Noord Scharwoude",
    "sg:orig_category":"Webdesign Bureaus",
    "sg:phone":"+31 226 315 125",
    "sg:postcode":"1723 PV",
    "sg:province":"North Holland",
    "wof:name":"Swebs",
    "wof:placetype":"venue"
},
  "geometry": {"coordinates":[4.7817621231,52.6940307617],"type":"Point"}
}