{
  "type": "Feature",
  "properties": {
    "addr:full":"Buitenhuizerwg 9 Velsen Zuid Noord-Holland 1981 LK",
    "addr:housenumber":"9",
    "addr:postcode":"1981 lk",
    "addr:street":"Buitenhuizerwg;Velsen",
    "iso:country":"NL",
    "sg:address":"Buitenhuizerwg 9",
    "sg:city":"Velsen Zuid",
    "sg:orig_category":"Jachthavens - Jachtwerven",
    "sg:phone":"+31 23 538 4457",
    "sg:postcode":"1981 LK",
    "sg:province":"Noord-Holland",
    "wof:name":"Kantine I Jmond",
    "wof:placetype":"venue"
},
  "geometry": {"coordinates":[4.702342,52.43771],"type":"Point"}
}