{
  "type": "Feature",
  "properties": {
    "iso:country":"NL",
    "sg:address":"Kortedreef 27",
    "sg:city":"Rotterdam",
    "sg:orig_category":"Boekhouders",
    "sg:phone":"+31 10 432 4557",
    "sg:postcode":"3075 GN",
    "sg:province":"Zuid-Holland",
    "wof:name":"Adm.Kant + Inc. Bureau M.P. V.D. Sluijs",
    "wof:placetype":"venue"
},
  "geometry": {"coordinates":[4.513117,51.88438],"type":"Point"}
}