{
  "type": "Feature",
  "properties": {
    "addr:full":"Buitenhavenweg 56 Schiedam South Holland 3113 BD",
    "addr:housenumber":"56",
    "addr:postcode":"3113 bd",
    "addr:street":"Buitenhavenweg",
    "iso:country":"NL",
    "sg:address":"Buitenhavenweg 56",
    "sg:city":"Schiedam",
    "sg:orig_category":"Pleziervaartuigen And Reparatie",
    "sg:phone":"+31 10 473 9897",
    "sg:postcode":"3113 BD",
    "sg:province":"South Holland",
    "wof:name":"Jet Sports Europe",
    "wof:placetype":"venue"
},
  "geometry": {"coordinates":[4.408859,51.908161],"type":"Point"}
}