{
  "type": "Feature",
  "properties": {
    "addr:full":"Vissersln 51 Arnhem Gelderland 6833 EL",
    "addr:housenumber":"51",
    "addr:postcode":"6833 el",
    "addr:street":"Vissersln",
    "iso:country":"NL",
    "sg:address":"Vissersln 51",
    "sg:city":"Arnhem",
    "sg:orig_category":"Koeriersdiensten",
    "sg:phone":"+31 6 53683516",
    "sg:postcode":"6833 EL",
    "sg:province":"Gelderland",
    "wof:name":"Fantomas",
    "wof:placetype":"venue"
},
  "geometry": {"coordinates":[5.92045,51.965302],"type":"Point"}
}