{
  "type": "Feature",
  "properties": {
    "addr:full":"Turfstreek 217 Soest Utrecht 3766 HW",
    "addr:housenumber":"217",
    "addr:postcode":"3766 hw",
    "addr:street":"Turfstreek",
    "iso:country":"NL",
    "sg:address":"Turfstreek 217",
    "sg:city":"Soest",
    "sg:orig_category":"Adviesbureaus Bedrijfsorganisatie",
    "sg:phone":"+31 35 602 4512",
    "sg:postcode":"3766 HW",
    "sg:province":"Utrecht",
    "wof:name":"Zanen Bv, Organisatie-Adviesbureau Van",
    "wof:placetype":"venue"
},
  "geometry": {"coordinates":[5.272659,52.169743],"type":"Point"}
}