{
  "type": "Feature",
  "properties": {
    "addr:full":"Heerewg 190 Schoorl Noord-Holland 1871 EN",
    "addr:housenumber":"190",
    "addr:postcode":"1871 en",
    "iso:country":"NL",
    "sg:address":"Heerewg 190",
    "sg:city":"Schoorl",
    "sg:orig_category":"Foerage",
    "sg:phone":"+31 72 509 1447",
    "sg:postcode":"1871 EN",
    "sg:province":"Noord-Holland",
    "wof:name":"Meereboer",
    "wof:placetype":"venue"
},
  "geometry": {"coordinates":[4.678468,52.715366],"type":"Point"}
}