{
  "type": "Feature",
  "properties": {
    "addr:full":"Langewijk 47 Dedemsvaart NL.08 7701 AB",
    "addr:housenumber":"47;nl.08",
    "addr:postcode":"7701 ab",
    "addr:street":"Langewijk",
    "iso:country":"NL",
    "sg:address":"Langewijk 47",
    "sg:city":"Dedemsvaart",
    "sg:orig_category":"Verzekeringen",
    "sg:phone":"+31 523 615 700",
    "sg:postcode":"7701 AB",
    "sg:province":"NL.08",
    "wof:name":"Aveco Assurantien",
    "wof:placetype":"venue"
},
  "geometry": {"coordinates":[6.455894,52.605034],"type":"Point"}
}