{
  "type": "Feature",
  "properties": {
    "addr:full":"Hoekenrode 1 Amsterdam Noord-Holland 1102 BR",
    "addr:housenumber":"1",
    "addr:postcode":"1102 br",
    "addr:street":"Hoekenrode",
    "iso:country":"NL",
    "sg:address":"Hoekenrode 1",
    "sg:city":"Amsterdam",
    "sg:orig_category":"Boekenuitgeverijen",
    "sg:phone":"+31 20 567 6767",
    "sg:postcode":"1102 BR",
    "sg:province":"Noord-Holland",
    "wof:name":"Gouden Gids Bv",
    "wof:placetype":"venue"
},
  "geometry": {"coordinates":[4.949633,52.311787],"type":"Point"}
}