{
  "type": "Feature",
  "properties": {
    "addr:full":"Turfmarkt 7 Leeuwarden Provincie Friesland 8911 KS",
    "addr:housenumber":"7",
    "addr:postcode":"8911 ks",
    "addr:street":"Turfmarkt;Provincie Friesland",
    "iso:country":"NL",
    "sg:address":"Turfmarkt 7",
    "sg:city":"Leeuwarden",
    "sg:orig_category":"Adviesbureaus",
    "sg:phone":"+31 58 266 4668",
    "sg:postcode":"8911 KS",
    "sg:province":"Provincie Friesland",
    "sg:website":"http://www.crossover.nl",
    "wof:name":"Crossover",
    "wof:placetype":"venue"
},
  "geometry": {"coordinates":[5.801468,53.202782],"type":"Point"}
}