{
  "type": "Feature",
  "properties": {
    "addr:full":"Hanzestr 15 Arnhem Gelderland 6826 ME",
    "addr:housenumber":"15",
    "addr:postcode":"6826 me",
    "addr:street":"Hanzestr",
    "iso:country":"NL",
    "sg:address":"Hanzestr 15",
    "sg:city":"Arnhem",
    "sg:orig_category":"Bloemen En Planten",
    "sg:phone":"+31 26 361 3067",
    "sg:postcode":"6826 ME",
    "sg:province":"Gelderland",
    "sg:website":"http://www.melenhorst.info",
    "wof:name":"Melenhorst Bloemsierkunst",
    "wof:placetype":"venue"
},
  "geometry": {"coordinates":[5.949256,51.982475],"type":"Point"}
}