{
  "type": "Feature",
  "properties": {
    "addr:full":"Scheveningseweg 58 'S Gravenhage South Holland 2517 KW",
    "addr:housenumber":"58",
    "addr:postcode":"2517 kw",
    "addr:street":"Scheveningseweg;' S Gravenhage",
    "iso:country":"NL",
    "sg:address":"Scheveningseweg 58",
    "sg:city":"'S Gravenhage",
    "sg:orig_category":"Technische Studies And Onderzoek",
    "sg:phone":"+31 70 306 6500",
    "sg:postcode":"2517 KW",
    "sg:province":"South Holland",
    "wof:name":"Jgc Corporation Europe Bv",
    "wof:placetype":"venue"
},
  "geometry": {"coordinates":[4.284391,52.097282],"type":"Point"}
}