{
  "type": "Feature",
  "properties": {
    "addr:full":"Langestraat 32 Delden NL.08 7491 AG",
    "addr:housenumber":"32;nl.08",
    "addr:postcode":"7491",
    "addr:street":"Langestraat",
    "iso:country":"NL",
    "sg:address":"Langestraat 32",
    "sg:city":"Delden",
    "sg:classifiers":[
        {
            "category":"Shopping",
            "subcategory":"Gifts & Souvenirs",
            "type":"Retail Goods"
        }
    ],
    "sg:phone":"+31 74 376 4940",
    "sg:postcode":"7491 AG",
    "sg:province":"NL.08",
    "sg:tags":[
        "geschenken"
    ],
    "wof:name":"Emilie Kunstnijverheid",
    "wof:placetype":"venue"
},
  "geometry": {"coordinates":[6.712082,52.262688],"type":"Point"}
}