{
  "type": "Feature",
  "properties": {
    "addr:full":"Emmastraat 38 Hilversum Noord-Holland 1211 NH",
    "addr:housenumber":"38",
    "addr:postcode":"1211 nh",
    "addr:street":"Emmastraat",
    "iso:country":"NL",
    "sg:address":"Emmastraat 38",
    "sg:city":"Hilversum",
    "sg:orig_category":"Opticiens",
    "sg:phone":"+31 35 621 2072",
    "sg:postcode":"1211 NH",
    "sg:province":"Noord-Holland",
    "wof:name":"Van Gestel Optiek Bv",
    "wof:placetype":"venue"
},
  "geometry": {"coordinates":[5.1794672012,52.2208023071],"type":"Point"}
}