{
  "type": "Feature",
  "properties": {
    "addr:full":"Industrieweg 19 Rogat/Meppel Provincie Drenthe 7949 AJ",
    "addr:housenumber":"19",
    "addr:postcode":"7949 aj",
    "addr:street":"Industrieweg;Drenthe",
    "iso:country":"NL",
    "sg:address":"Industrieweg 19",
    "sg:city":"Rogat/Meppel",
    "sg:orig_category":"Verhuur Bouwmachines",
    "sg:phone":"+31 522 440 445",
    "sg:postcode":"7949 AJ",
    "sg:province":"Provincie Drenthe",
    "sg:website":"http://www.schreur-meppel.nl",
    "wof:name":"Schreur Hoogwerken",
    "wof:placetype":"venue"
},
  "geometry": {"coordinates":[6.273542,52.686707],"type":"Point"}
}