{
  "type": "Feature",
  "properties": {
    "iso:country":"NL",
    "sg:address":"Perobahout 2",
    "sg:city":"Zoetermeer",
    "sg:orig_category":"Adviesbureaus Bedrijfsorganisatie",
    "sg:phone":"+31 79 362 0784",
    "sg:postcode":"2719 KR",
    "sg:province":"Zuid-Holland",
    "wof:name":"Batikon",
    "wof:placetype":"venue"
},
  "geometry": {"coordinates":[4.466631,52.044121],"type":"Point"}
}