{
  "type": "Feature",
  "properties": {
    "addr:full":"Marisplnts 14 Nieuwegein Utrecht 3431 GZ",
    "addr:housenumber":"14",
    "addr:postcode":"3431 gz",
    "addr:street":"Marisplnts",
    "iso:country":"NL",
    "sg:address":"Marisplnts 14",
    "sg:city":"Nieuwegein",
    "sg:orig_category":"Logopedisten",
    "sg:phone":"+31 30 603 8026",
    "sg:postcode":"3431 GZ",
    "sg:province":"Utrecht",
    "wof:name":"Boon, P J Den",
    "wof:placetype":"venue"
},
  "geometry": {"coordinates":[5.082197,52.027325],"type":"Point"}
}