{
  "type": "Feature",
  "properties": {
    "iso:country":"NL",
    "sg:address":"Oud Blaricummerwg 21A",
    "sg:city":"Laren Nh",
    "sg:orig_category":"Scholen Voor Basisonderwijs",
    "sg:phone":"+31 35 538 2234",
    "sg:postcode":"1251 GV",
    "sg:province":"North Holland",
    "wof:name":"Gooische School, De",
    "wof:placetype":"venue"
},
  "geometry": {"coordinates":[5.226999,52.26244],"type":"Point"}
}