{
  "type": "Feature",
  "properties": {
    "addr:full":"Trompstraat 150 Ijmuiden Noord-Holland 1972 AK",
    "addr:housenumber":"150",
    "addr:postcode":"1972 ak",
    "addr:street":"Trompstraat",
    "iso:country":"NL",
    "sg:address":"Trompstraat 150",
    "sg:city":"Ijmuiden",
    "sg:orig_category":"Goederenvervoer Over De Weg",
    "sg:phone":"+31 255 513 626",
    "sg:postcode":"1972 AK",
    "sg:province":"Noord-Holland",
    "wof:name":"Visser Transport",
    "wof:placetype":"venue"
},
  "geometry": {"coordinates":[4.619088,52.462215],"type":"Point"}
}