{
  "type": "Feature",
  "properties": {
    "iso:country":"NL",
    "sg:address":"Hastelwg 272",
    "sg:city":"Eindhoven",
    "sg:orig_category":"Accumulatoren",
    "sg:phone":"+31 40 252 4262",
    "sg:postcode":"5652 CN",
    "sg:province":"Noord-Brabant",
    "sg:website":"http://www.aep-ehv.nl",
    "wof:name":"Bosch Accu'S",
    "wof:placetype":"venue"
},
  "geometry": {"coordinates":[5.432574,51.437508],"type":"Point"}
}