{
  "type": "Feature",
  "properties": {
    "addr:full":"Jan Bestevaerstraat 15 Koog A/D Zaan North Holland 1541 KM",
    "addr:housenumber":"15;a / d",
    "addr:street":"Jan Bestevaerstraat;Koog;Zaan North;1541 Km",
    "iso:country":"NL",
    "sg:address":"Jan Bestevaerstraat 15",
    "sg:city":"Koog A/D Zaan",
    "sg:orig_category":"Bloemen And Planten",
    "sg:phone":"+31 75 617 1324",
    "sg:postcode":"1541 KM",
    "sg:province":"North Holland",
    "wof:name":"Geertje'S Bloemenhandel",
    "wof:placetype":"venue"
},
  "geometry": {"coordinates":[4.812176,52.467339],"type":"Point"}
}