{
  "type": "Feature",
  "properties": {
    "addr:full":"Kennedylaan 30 Maarssen Utrecht 3601 VG",
    "addr:housenumber":"30",
    "addr:postcode":"3601 vg",
    "addr:street":"Kennedylaan",
    "iso:country":"NL",
    "sg:address":"Kennedylaan 30",
    "sg:city":"Maarssen",
    "sg:orig_category":"Verzekeringen",
    "sg:phone":"+31 346 562 912",
    "sg:postcode":"3601 VG",
    "sg:province":"Utrecht",
    "wof:name":"J.B. Van Scherpenzeel Assurantien Bv",
    "wof:placetype":"venue"
},
  "geometry": {"coordinates":[5.047003,52.143463],"type":"Point"}
}