{
  "type": "Feature",
  "properties": {
    "iso:country":"NL",
    "sg:address":"S Undsetwg 300",
    "sg:city":"Rotterdam",
    "sg:orig_category":"Verenigingsgebouwen",
    "sg:phone":"+31 10 421 2722",
    "sg:postcode":"3069 BV",
    "sg:province":"Zuid-Holland",
    "wof:name":"Molshoop, De",
    "wof:placetype":"venue"
},
  "geometry": {"coordinates":[4.550957,51.963486],"type":"Point"}
}