{
  "type": "Feature",
  "properties": {
    "addr:full":"Haulsterwg 22 Haskerhorne Friesland 8506 BJ",
    "addr:housenumber":"22",
    "addr:postcode":"8506 bj",
    "addr:street":"Haulsterwg",
    "iso:country":"NL",
    "sg:address":"Haulsterwg 22",
    "sg:city":"Haskerhorne",
    "sg:orig_category":"Mengmachines",
    "sg:phone":"+31 513 528 810",
    "sg:postcode":"8506 BJ",
    "sg:province":"Friesland",
    "sg:website":"http://www.aquartel.nl",
    "wof:name":"Aquartel Bv",
    "wof:placetype":"venue"
},
  "geometry": {"coordinates":[5.827618,52.950966],"type":"Point"}
}