{
  "type": "Feature",
  "properties": {
    "addr:full":"Wezenstr 25 Den Helder Noord-Holland 1781 GJ",
    "addr:housenumber":"25",
    "addr:postcode":"1781 gj",
    "addr:street":"Wezenstr",
    "iso:country":"NL",
    "sg:address":"Wezenstr 25",
    "sg:city":"Den Helder",
    "sg:orig_category":"Beeldende Kunstenaars",
    "sg:phone":"+31 223 613 119",
    "sg:postcode":"1781 GJ",
    "sg:province":"Noord-Holland",
    "wof:name":"Araxes",
    "wof:placetype":"venue"
},
  "geometry": {"coordinates":[4.76387,52.958706],"type":"Point"}
}