{
  "type": "Feature",
  "properties": {
    "addr:full":"Hemonystr 66 Amsterdam Noord-Holland 1074 BT",
    "addr:housenumber":"66",
    "addr:postcode":"1074 bt",
    "addr:street":"Hemonystr",
    "iso:country":"NL",
    "sg:address":"Hemonystr 66",
    "sg:city":"Amsterdam",
    "sg:orig_category":"Fotografie Reclame En Mode",
    "sg:phone":"+31 20 470 2934",
    "sg:postcode":"1074 BT",
    "sg:province":"Noord-Holland",
    "wof:name":"Fitzpatrick",
    "wof:placetype":"venue"
},
  "geometry": {"coordinates":[4.903085,52.355705],"type":"Point"}
}