{
  "type": "Feature",
  "properties": {
    "addr:full":"Ln V Nw Oosteinde 130A Voorburg South Holland 2274 EL",
    "addr:housenumber":"130a",
    "addr:postcode":"2274 el",
    "addr:street":"Ln V Nw Oosteinde",
    "iso:country":"NL",
    "sg:address":"Ln V Nw Oosteinde 130A",
    "sg:city":"Voorburg",
    "sg:orig_category":"Kantoormachines - Reparatie En Onderhoud",
    "sg:phone":"+31 70 386 1385",
    "sg:postcode":"2274 EL",
    "sg:province":"South Holland",
    "wof:name":"Zanoni, C H",
    "wof:placetype":"venue"
},
  "geometry": {"coordinates":[4.3495202065,52.0737915039],"type":"Point"}
}