{
  "type": "Feature",
  "properties": {
    "addr:full":"Willem Barendszstraat 37 Arnhem Gelderland 6828 ZJ",
    "addr:housenumber":"37",
    "addr:postcode":"6828 zj",
    "addr:street":"Willem Barendszstraat",
    "iso:country":"NL",
    "sg:address":"Willem Barendszstraat 37",
    "sg:city":"Arnhem",
    "sg:orig_category":"Geluidsopnamen",
    "sg:phone":"+31 26 445 3556",
    "sg:postcode":"6828 ZJ",
    "sg:province":"Gelderland",
    "wof:name":"Mastertracks",
    "wof:placetype":"venue"
},
  "geometry": {"coordinates":[5.922559,51.976952],"type":"Point"}
}