{
  "type": "Feature",
  "properties": {
    "addr:full":"Evertsenstraat 23 Capelle A/D Ijssel South Holland 2901 AK",
    "addr:housenumber":"23;a / d",
    "addr:postcode":"2901 ak",
    "addr:street":"Evertsenstraat;Ijssel South",
    "iso:country":"NL",
    "sg:address":"Evertsenstraat 23",
    "sg:city":"Capelle A/D Ijssel",
    "sg:orig_category":"Autokeuringen",
    "sg:phone":"+31 10 458 1293",
    "sg:postcode":"2901 AK",
    "sg:province":"South Holland",
    "wof:name":"Smits' Autobedrijf Bv",
    "wof:placetype":"venue"
},
  "geometry": {"coordinates":[4.566963,51.91198],"type":"Point"}
}