{
  "type": "Feature",
  "properties": {
    "addr:full":"Star Numanstr 83B Groningen Groningen 9714 JL",
    "addr:housenumber":"83b",
    "addr:postcode":"9714 jl",
    "iso:country":"NL",
    "sg:address":"Star Numanstr 83B",
    "sg:city":"Groningen",
    "sg:orig_category":"Verenigingen En Stichtingen",
    "sg:phone":"+31 50 577 7425",
    "sg:postcode":"9714 JL",
    "sg:province":"Groningen",
    "wof:name":"Eendracht Rederijkerskamer",
    "wof:placetype":"venue"
},
  "geometry": {"coordinates":[6.578474,53.231789],"type":"Point"}
}