{
  "type": "Feature",
  "properties": {
    "iso:country":"NL",
    "sg:address":"Rietvoorndaal 144",
    "sg:city":"S Gravenhage",
    "sg:orig_category":"Fotojournalisten Freelance",
    "sg:phone":"+31 70 397 9299",
    "sg:postcode":"2553 NN",
    "sg:province":"Zuid-Holland",
    "wof:name":"Krul, L N",
    "wof:placetype":"venue"
},
  "geometry": {"coordinates":[4.21987,52.046589],"type":"Point"}
}