{
  "type": "Feature",
  "properties": {
    "iso:country":"NL",
    "sg:address":"Steenovenwg 13",
    "sg:city":"Helmond",
    "sg:orig_category":"Video - Faciliteiten En Producties",
    "sg:phone":"+31 492 564 014",
    "sg:postcode":"5708 HN",
    "sg:province":"Noord-Brabant",
    "wof:name":"Uni-Visie Holl Bv",
    "wof:placetype":"venue"
},
  "geometry": {"coordinates":[5.628626,51.476128],"type":"Point"}
}