{
  "type": "Feature",
  "properties": {
    "iso:country":"NL",
    "sg:address":"Postbus 19",
    "sg:city":"Gulpen",
    "sg:orig_category":"Voetbalverenigingen",
    "sg:phone":"+31 43 450 1805",
    "sg:postcode":"6270 AA",
    "sg:province":"Limburg",
    "wof:name":"Gulpen Vv",
    "wof:placetype":"venue"
},
  "geometry": {"coordinates":[5.88998,50.817322],"type":"Point"}
}