{
  "type": "Feature",
  "properties": {
    "addr:full":"Postbus 19 Gulpen Limburg 6270 AA",
    "addr:housenumber":"19",
    "addr:postcode":"6270 aa",
    "addr:street":"Postbus",
    "iso:country":"NL",
    "sg:address":"Postbus 19",
    "sg:city":"Gulpen",
    "sg:orig_category":"Voetbalverenigingen",
    "sg:phone":"+31 43 450 1805",
    "sg:postcode":"6270 AA",
    "sg:province":"Limburg",
    "wof:name":"Gulpen Vv",
    "wof:placetype":"venue"
},
  "geometry": {"coordinates":[5.88998,50.817322],"type":"Point"}
}