{
  "type": "Feature",
  "properties": {
    "iso:country":"NL",
    "sg:address":"Albert Verweijlaan 45",
    "sg:city":"Hillegom",
    "sg:orig_category":"Autokeuringen",
    "sg:phone":"+31 6 53744443",
    "sg:postcode":"2182 PS",
    "sg:province":"Zuid-Holland",
    "wof:name":"Dva",
    "wof:placetype":"venue"
},
  "geometry": {"coordinates":[4.589228,52.284893],"type":"Point"}
}