{
  "type": "Feature",
  "properties": {
    "addr:full":"J Evertsenstr 51 Amsterdam Noord-Holland 1057 BN",
    "addr:housenumber":"51",
    "addr:postcode":"1057 bn",
    "iso:country":"NL",
    "sg:address":"J Evertsenstr 51",
    "sg:city":"Amsterdam",
    "sg:orig_category":"Opticiens",
    "sg:phone":"+31 20 618 0187",
    "sg:postcode":"1057 BN",
    "sg:province":"Noord-Holland",
    "wof:name":"Spannet & Co Oogadviseur",
    "wof:placetype":"venue"
},
  "geometry": {"coordinates":[4.855782032,52.3707962036],"type":"Point"}
}