{
  "type": "Feature",
  "properties": {
    "addr:full":"Lijsterlaan 132 Maassluis South Holland 3145 VM",
    "addr:housenumber":"132",
    "addr:postcode":"3145 vm",
    "addr:street":"Lijsterlaan",
    "iso:country":"NL",
    "sg:address":"Lijsterlaan 132",
    "sg:city":"Maassluis",
    "sg:orig_category":"Marktonderzoekbureaus",
    "sg:phone":"+31 10 592 2535",
    "sg:postcode":"3145 VM",
    "sg:province":"South Holland",
    "wof:name":"J. Versloot En H.G. Engbers",
    "wof:placetype":"venue"
},
  "geometry": {"coordinates":[4.232808,51.932529],"type":"Point"}
}