{
  "type": "Feature",
  "properties": {
    "addr:full":"Plantage Muidergr 69-71 Amsterdam Noord-Holland 1018 TM",
    "addr:housenumber":"69-71",
    "addr:postcode":"1018 tm",
    "addr:street":"Plantage",
    "iso:country":"NL",
    "sg:address":"Plantage Muidergr 69-71",
    "sg:city":"Amsterdam",
    "sg:orig_category":"Maaltijdbezorging",
    "sg:phone":"+31 20 421 4939",
    "sg:postcode":"1018 TM",
    "sg:province":"Noord-Holland",
    "wof:name":"Kerklaan Express",
    "wof:placetype":"venue"
},
  "geometry": {"coordinates":[4.910801,52.365715],"type":"Point"}
}