{
  "type": "Feature",
  "properties": {
    "addr:full":"Bylmerpln 728 Amsterdam Zuidoost Noord-Holland 1102 MA",
    "addr:housenumber":"728",
    "addr:postcode":"zuidoost;1102 ma",
    "iso:country":"NL",
    "sg:address":"Bylmerpln 728",
    "sg:city":"Amsterdam Zuidoost",
    "sg:orig_category":"Hoortoestellen",
    "sg:phone":"+31 20 451 2000",
    "sg:postcode":"1102 MA",
    "sg:province":"Noord-Holland",
    "wof:name":"Te-Pa",
    "wof:placetype":"venue"
},
  "geometry": {"coordinates":[4.951315,52.316166],"type":"Point"}
}