{
  "type": "Feature",
  "properties": {
    "addr:full":"Postbus 24036 Rotterdam South Holland 3007 DA",
    "addr:housenumber":"24036",
    "addr:postcode":"3007 da",
    "addr:street":"Postbus",
    "iso:country":"NL",
    "sg:address":"Postbus 24036",
    "sg:city":"Rotterdam",
    "sg:orig_category":"Verenigingen En Stichtingen",
    "sg:phone":"+31 10 432 5126",
    "sg:postcode":"3007 DA",
    "sg:province":"South Holland",
    "wof:name":"Feyenoord Supportersver",
    "wof:placetype":"venue"
},
  "geometry": {"coordinates":[4.47075,51.922619],"type":"Point"}
}