{
  "type": "Feature",
  "properties": {
    "iso:country":"NL",
    "sg:address":"Pr Hendrikstr 27",
    "sg:city":"Groot Ammers",
    "sg:orig_category":"Fotojournalisten Freelance",
    "sg:phone":"+31 6 51841871",
    "sg:postcode":"2964 CL",
    "sg:province":"South Holland",
    "wof:name":"Independent Freelancer",
    "wof:placetype":"venue"
},
  "geometry": {"coordinates":[4.823415,51.924168],"type":"Point"}
}