{
  "type": "Feature",
  "properties": {
    "addr:full":"Bolle Akker 13 Bakel Noord-Brabant 5761 RW",
    "addr:housenumber":"13",
    "addr:postcode":"5761 rw",
    "addr:street":"Bolle Akker",
    "iso:country":"NL",
    "sg:address":"Bolle Akker 13",
    "sg:city":"Bakel",
    "sg:classifiers":[
        {
            "category":"Retail",
            "subcategory":"Auto Repair",
            "type":"Services"
        }
    ],
    "sg:phone":"+31 492 340 765",
    "sg:postcode":"5761 RW",
    "sg:province":"Noord-Brabant",
    "sg:tags":[
        "garage"
    ],
    "wof:name":"Mertens Bv",
    "wof:placetype":"venue"
},
  "geometry": {"coordinates":[5.743736,51.49786],"type":"Point"}
}