{
  "type": "Feature",
  "properties": {
    "iso:country":"NL",
    "sg:address":"Vriezenveensewg 61",
    "sg:city":"Almelo",
    "sg:orig_category":"Kunstgebitten",
    "sg:phone":"+31 546 568 090",
    "sg:postcode":"7602 AA",
    "sg:province":"Overijssel",
    "wof:name":"Schultz Tandprothetische Praktijk",
    "wof:placetype":"venue"
},
  "geometry": {"coordinates":[6.668242,52.368134],"type":"Point"}
}