{
  "type": "Feature",
  "properties": {
    "iso:country":"NL",
    "sg:address":"De Gealanden 89",
    "sg:city":"Leeuwarden",
    "sg:orig_category":"Metaalbekleding And -Behandeling",
    "sg:phone":"+31 58 267 3549",
    "sg:postcode":"8918 KC",
    "sg:province":"Friesland",
    "wof:name":"D. Olteanu",
    "wof:placetype":"venue"
},
  "geometry": {"coordinates":[5.785105,53.21571],"type":"Point"}
}