{
  "type": "Feature",
  "properties": {
    "addr:full":"Oude Wanroyseweg 24 Sint Hubert Noord-Brabant 5454 NA",
    "addr:housenumber":"24",
    "addr:postcode":"5454 na",
    "addr:street":"Oude Wanroyseweg",
    "iso:country":"NL",
    "sg:address":"Oude Wanroyseweg 24",
    "sg:city":"Sint Hubert",
    "sg:orig_category":"Kampeerterreinen",
    "sg:phone":"+31 485 470 193",
    "sg:postcode":"5454 NA",
    "sg:province":"Noord-Brabant",
    "wof:name":"Camping Van Rossums Troost",
    "wof:placetype":"venue"
},
  "geometry": {"coordinates":[5.7965350151,51.6693077087],"type":"Point"}
}