{
  "type": "Feature",
  "properties": {
    "addr:full":"Zuiderzeepad 12 Harderwijk Gelderland 3844 JV",
    "addr:housenumber":"12",
    "addr:postcode":"3844 jv",
    "addr:street":"Zuiderzeepad;Gelderland",
    "iso:country":"NL",
    "sg:address":"Zuiderzeepad 12",
    "sg:city":"Harderwijk",
    "sg:orig_category":"Loodgieterswerk, Verwarming And Sanitaire Installaties",
    "sg:phone":"+31 341 433 480",
    "sg:postcode":"3844 JV",
    "sg:province":"Gelderland",
    "wof:name":"Firma Klusrijk",
    "wof:placetype":"venue"
},
  "geometry": {"coordinates":[5.609357,52.336712],"type":"Point"}
}