{
  "type": "Feature",
  "properties": {
    "addr:full":"L Springerln 1 Groningen Groningen 9727 KB",
    "addr:housenumber":"1",
    "addr:postcode":"9727 kb",
    "iso:country":"NL",
    "sg:address":"L Springerln 1",
    "sg:city":"Groningen",
    "sg:orig_category":"Wegenbouw",
    "sg:phone":"+31 50 525 5020",
    "sg:postcode":"9727 KB",
    "sg:province":"Groningen",
    "wof:name":"Ntwc",
    "wof:placetype":"venue"
},
  "geometry": {"coordinates":[6.55753088,53.204044342],"type":"Point"}
}