{
  "type": "Feature",
  "properties": {
    "addr:full":"Leliegr 21 Amsterdam Noord-Holland 1016 GR",
    "addr:housenumber":"21",
    "addr:postcode":"1016",
    "addr:street":"Leliegr",
    "iso:country":"NL",
    "sg:address":"Leliegr 21",
    "sg:city":"Amsterdam",
    "sg:orig_category":"Adviesbureaus Bedrijfsorganisatie",
    "sg:phone":"+31 20 422 8271",
    "sg:postcode":"1016 GR",
    "sg:province":"Noord-Holland",
    "wof:name":"Denker",
    "wof:placetype":"venue"
},
  "geometry": {"coordinates":[4.886463,52.374969],"type":"Point"}
}