{
  "type": "Feature",
  "properties": {
    "addr:full":"Prinsenbaan 134 Koningsbosch North Rhine-Westphalia 6104 BJ",
    "addr:housenumber":"134",
    "addr:postcode":"6104 bj",
    "addr:street":"Prinsenbaan",
    "iso:country":"NL",
    "sg:address":"Prinsenbaan 134",
    "sg:city":"Koningsbosch",
    "sg:orig_category":"Beautyfarms And Sauna'S",
    "sg:phone":"+31 475 300 438",
    "sg:postcode":"6104 BJ",
    "sg:province":"North Rhine-Westphalia",
    "wof:name":"M En M",
    "wof:placetype":"venue"
},
  "geometry": {"coordinates":[5.9576587677,51.0510406494],"type":"Point"}
}