{
  "type": "Feature",
  "properties": {
    "addr:full":"Nieuwe Leliestraat 196A Amsterdam Noord-Holland 1015 HG",
    "addr:housenumber":"196a",
    "addr:postcode":"1015 hg",
    "addr:street":"Nieuwe Leliestraat",
    "iso:country":"NL",
    "sg:address":"Nieuwe Leliestraat 196A",
    "sg:city":"Amsterdam",
    "sg:orig_category":"Marktonderzoekbureaus",
    "sg:phone":"+31 20 420 0078",
    "sg:postcode":"1015 HG",
    "sg:province":"Noord-Holland",
    "wof:name":"Van Hellemond Market Research Support",
    "wof:placetype":"venue"
},
  "geometry": {"coordinates":[4.877379,52.374641],"type":"Point"}
}