{
  "type": "Feature",
  "properties": {
    "addr:full":"Grindweg 16 Rotterdam Zuid-Holland 3055 VA",
    "addr:housenumber":"16",
    "addr:postcode":"3055",
    "addr:street":"Grindweg",
    "iso:country":"NL",
    "sg:address":"Grindweg 16",
    "sg:city":"Rotterdam",
    "sg:orig_category":"Autokeuringen",
    "sg:phone":"+31 10 418 1997",
    "sg:postcode":"3055 VA",
    "sg:province":"Zuid-Holland",
    "wof:name":"M Van Leeuwen",
    "wof:placetype":"venue"
},
  "geometry": {"coordinates":[4.49537,51.963791],"type":"Point"}
}