{
  "type": "Feature",
  "properties": {
    "iso:country":"NL",
    "sg:address":"Herckenrathweg 3",
    "sg:city":"Bemmel",
    "sg:orig_category":"Autokeuringen",
    "sg:phone":"+31 481 461 465",
    "sg:postcode":"6681 DC",
    "sg:province":"Gelderland",
    "wof:name":"Automobielbedrijf Gerard Tap",
    "wof:placetype":"venue"
},
  "geometry": {"coordinates":[5.893882,51.892273],"type":"Point"}
}