{
  "type": "Feature",
  "properties": {
    "addr:full":"Valkenkamp 634 Maarssen Utrecht 3607 MP",
    "addr:housenumber":"634",
    "addr:postcode":"3607 mp",
    "addr:street":"Valkenkamp",
    "iso:country":"NL",
    "sg:address":"Valkenkamp 634",
    "sg:city":"Maarssen",
    "sg:orig_category":"Schoonheidssalons",
    "sg:phone":"+31 346 572 908",
    "sg:postcode":"3607 MP",
    "sg:province":"Utrecht",
    "wof:name":"Ans Vogels",
    "wof:placetype":"venue"
},
  "geometry": {"coordinates":[5.01182,52.136139],"type":"Point"}
}