{
  "type": "Feature",
  "properties": {
    "addr:full":"Pastoor Leijtenstraat 51 Bavel Noord-Brabant 4854 KP",
    "addr:housenumber":"51",
    "addr:postcode":"4854 kp",
    "addr:street":"Pastoor Leijtenstraat",
    "iso:country":"NL",
    "sg:address":"Pastoor Leijtenstraat 51",
    "sg:city":"Bavel",
    "sg:orig_category":"Koeriersdiensten",
    "sg:phone":"+31 161 432 342",
    "sg:postcode":"4854 KP",
    "sg:province":"Noord-Brabant",
    "wof:name":"Berli Services",
    "wof:placetype":"venue"
},
  "geometry": {"coordinates":[4.833621,51.566307],"type":"Point"}
}