{
  "type": "Feature",
  "properties": {
    "addr:full":"Postbus 13 Woudenberg Utrecht 3930 EA",
    "addr:housenumber":"13",
    "addr:postcode":"3930 ea",
    "addr:street":"Postbus",
    "iso:country":"NL",
    "sg:address":"Postbus 13",
    "sg:city":"Woudenberg",
    "sg:orig_category":"Verenigingen En Stichtingen",
    "sg:phone":"+31 33 286 1166",
    "sg:postcode":"3930 EA",
    "sg:province":"Utrecht",
    "wof:name":"Boom, De",
    "wof:placetype":"venue"
},
  "geometry": {"coordinates":[5.415759,52.08215],"type":"Point"}
}