{
  "type": "Feature",
  "properties": {
    "iso:country":"NL",
    "sg:address":"Pasmanshaard 5",
    "sg:city":"Ruurlo",
    "sg:orig_category":"Verloskundigen",
    "sg:phone":"+31 573 454 445",
    "sg:postcode":"7261 VL",
    "sg:province":"Gelderland",
    "wof:name":"Voortman-Schuite, C S",
    "wof:placetype":"venue"
},
  "geometry": {"coordinates":[6.448858,52.091831],"type":"Point"}
}