{
  "type": "Feature",
  "properties": {
    "addr:full":"Markt 15 Steenbergen Nb Noord-Brabant 4651 BC",
    "addr:housenumber":"15",
    "addr:postcode":"4651 bc",
    "addr:street":"Markt",
    "iso:country":"NL",
    "sg:address":"Markt 15",
    "sg:city":"Steenbergen Nb",
    "sg:orig_category":"Gedistilleerd En Likeuren - Groothandel",
    "sg:phone":"+31 167 562 676",
    "sg:postcode":"4651 BC",
    "sg:province":"Noord-Brabant",
    "wof:name":"Harvis Bv",
    "wof:placetype":"venue"
},
  "geometry": {"coordinates":[4.318032,51.587589],"type":"Point"}
}