{
  "type": "Feature",
  "properties": {
    "addr:full":"Haaksbergweg 23 Amsterdam Zuidoost North Holland 1101 BP",
    "addr:housenumber":"23",
    "addr:postcode":"1101 bp",
    "addr:street":"Haaksbergweg",
    "iso:country":"NL",
    "sg:address":"Haaksbergweg 23",
    "sg:city":"Amsterdam Zuidoost",
    "sg:orig_category":"Verenigingen En Stichtingen",
    "sg:phone":"+31 20 696 7536",
    "sg:postcode":"1101 BP",
    "sg:province":"North Holland",
    "wof:name":"Amsterdam Z O",
    "wof:placetype":"venue"
},
  "geometry": {"coordinates":[4.943037,52.309856],"type":"Point"}
}