{
  "type": "Feature",
  "properties": {
    "iso:country":"NL",
    "sg:address":"Edesewg 25",
    "sg:city":"Wekerom",
    "sg:classifiers":[
        {
            "category":"Retail",
            "subcategory":"Auto Repair",
            "type":"Services"
        }
    ],
    "sg:phone":"+31 318 461 946",
    "sg:postcode":"6733 AB",
    "sg:province":"Gelderland",
    "sg:tags":[
        "garage"
    ],
    "wof:name":"Tichelaar, J",
    "wof:placetype":"venue"
},
  "geometry": {"coordinates":[5.711533,52.109962],"type":"Point"}
}