{
  "type": "Feature",
  "properties": {
    "addr:full":"Frederik Hendrikstraat 26 Amsterdam Noord-Holland 1052 HV",
    "addr:housenumber":"26",
    "addr:postcode":"1052 hv",
    "addr:street":"Frederik Hendrikstraat",
    "iso:country":"NL",
    "sg:address":"Frederik Hendrikstraat 26",
    "sg:city":"Amsterdam",
    "sg:orig_category":"Medische Apparatuur And Prothesen Fab",
    "sg:phone":"+31 20 684 4102",
    "sg:postcode":"1052 HV",
    "sg:province":"Noord-Holland",
    "wof:name":"A De Jong",
    "wof:placetype":"venue"
},
  "geometry": {"coordinates":[4.874517,52.377659],"type":"Point"}
}