{
  "type": "Feature",
  "properties": {
    "iso:country":"NL",
    "sg:address":"Westerdorpsstraat 39",
    "sg:city":"Hoevelaken",
    "sg:orig_category":"Juweliers",
    "sg:phone":"+31 33 253 6306",
    "sg:postcode":"3871 AT",
    "sg:province":"Gelderland",
    "wof:name":"Firma Diepeveen",
    "wof:placetype":"venue"
},
  "geometry": {"coordinates":[5.454286,52.175121],"type":"Point"}
}