{
  "type": "Feature",
  "properties": {
    "addr:full":"Delta 19 Lelystad NL. 8224 EL",
    "addr:housenumber":"19",
    "addr:postcode":"8224 el",
    "addr:street":"Delta;Nl.",
    "iso:country":"NL",
    "sg:address":"Delta 19",
    "sg:city":"Lelystad",
    "sg:orig_category":"Kappers",
    "sg:phone":"+31 320 244 931",
    "sg:postcode":"8224 EL",
    "sg:province":"NL.",
    "wof:name":"A.D.A. Gal",
    "wof:placetype":"venue"
},
  "geometry": {"coordinates":[5.4940681458,52.5161361694],"type":"Point"}
}