{
  "type": "Feature",
  "properties": {
    "iso:country":"NL",
    "sg:address":"Meiboomstraat 10",
    "sg:city":"Nijverdal",
    "sg:orig_category":"Verlichting And Huishoudartikelen",
    "sg:phone":"+31 548 620 680",
    "sg:postcode":"7443 CB",
    "sg:province":"Overijssel",
    "wof:name":"Gordijngigant",
    "wof:placetype":"venue"
},
  "geometry": {"coordinates":[6.460703,52.366035],"type":"Point"}
}