{
  "type": "Feature",
  "properties": {
    "addr:full":"Monnickskamp 8 Huizen Noord-Holland 1273 JS",
    "addr:housenumber":"8",
    "addr:postcode":"1273 js",
    "addr:street":"Monnickskamp",
    "iso:country":"NL",
    "sg:address":"Monnickskamp 8",
    "sg:city":"Huizen",
    "sg:orig_category":"Boekhouders",
    "sg:phone":"+31 35 525 9692",
    "sg:postcode":"1273 JS",
    "sg:province":"Noord-Holland",
    "wof:name":"Administratiekantoor H. De Munnik",
    "wof:placetype":"venue"
},
  "geometry": {"coordinates":[5.26262,52.294613],"type":"Point"}
}