{
  "type": "Feature",
  "properties": {
    "addr:full":"Herbergierserf 17 Houten Utrecht 3991 KH",
    "addr:housenumber":"17",
    "addr:postcode":"3991 kh",
    "addr:street":"Herbergierserf",
    "iso:country":"NL",
    "sg:address":"Herbergierserf 17",
    "sg:city":"Houten",
    "sg:orig_category":"Artsen And Specialisten",
    "sg:phone":"+31 30 635 0246",
    "sg:postcode":"3991 KH",
    "sg:province":"Utrecht",
    "wof:name":"J. Abarbanel",
    "wof:placetype":"venue"
},
  "geometry": {"coordinates":[5.168767,52.027817],"type":"Point"}
}