{
  "type": "Feature",
  "properties": {
    "iso:country":"NL",
    "sg:address":"Dr Vd Koppelstr 2",
    "sg:city":"Ophemert",
    "sg:orig_category":"Adviesbureaus Bedrijfsorganisatie",
    "sg:phone":"+31 344 651 567",
    "sg:postcode":"4061 AT",
    "sg:province":"Gelderland",
    "wof:name":"Flexwork Facilities Vof",
    "wof:placetype":"venue"
},
  "geometry": {"coordinates":[5.387516,51.844536],"type":"Point"}
}