{
  "type": "Feature",
  "properties": {
    "addr:full":"Molenhoek 21 Vlijmen Noord-Brabant 5251 EK",
    "addr:housenumber":"21",
    "addr:postcode":"5251 ek",
    "addr:street":"Molenhoek",
    "iso:country":"NL",
    "sg:address":"Molenhoek 21",
    "sg:city":"Vlijmen",
    "sg:orig_category":"Beeldende Kunstenaars",
    "sg:phone":"+31 73 511 2983",
    "sg:postcode":"5251 EK",
    "sg:province":"Noord-Brabant",
    "wof:name":"Griendt, Guido Van De",
    "wof:placetype":"venue"
},
  "geometry": {"coordinates":[5.234435,51.702442],"type":"Point"}
}