{
  "type": "Feature",
  "properties": {
    "addr:full":"Marke Mander 4 Almelo Overijssel 7603 GL",
    "addr:housenumber":"4",
    "addr:postcode":"7603 gl",
    "addr:street":"Marke Mander",
    "iso:country":"NL",
    "sg:address":"Marke Mander 4",
    "sg:city":"Almelo",
    "sg:orig_category":"Arbo- En Bedrijfsgezondheids- Diensten",
    "sg:phone":"+31 546 490 256",
    "sg:postcode":"7603 GL",
    "sg:province":"Overijssel",
    "wof:name":"Arbo Office",
    "wof:placetype":"venue"
},
  "geometry": {"coordinates":[6.693844,52.368999],"type":"Point"}
}