{
  "type": "Feature",
  "properties": {
    "addr:full":"Oostkerkestr 24 Wolphaartsdyk Zeeland 4471 BB",
    "addr:housenumber":"24",
    "addr:postcode":"4471 bb",
    "addr:street":"Oostkerkestr;Zeeland",
    "iso:country":"NL",
    "sg:address":"Oostkerkestr 24",
    "sg:city":"Wolphaartsdyk",
    "sg:orig_category":"Verenigingsgebouwen",
    "sg:phone":"+31 113 581 313",
    "sg:postcode":"4471 BB",
    "sg:province":"Zeeland",
    "wof:name":"Griffioen",
    "wof:placetype":"venue"
},
  "geometry": {"coordinates":[3.821006,51.530136],"type":"Point"}
}