{
  "type": "Feature",
  "properties": {
    "iso:country":"NL",
    "sg:address":"Eikbosserwg 15",
    "sg:city":"Hilversum",
    "sg:orig_category":"Kinderopvang",
    "sg:phone":"+31 35 629 4150",
    "sg:postcode":"1214 AE",
    "sg:province":"Noord-Holland",
    "wof:name":"Kwibus",
    "wof:placetype":"venue"
},
  "geometry": {"coordinates":[5.174732,52.218136],"type":"Point"}
}