{
  "type": "Feature",
  "properties": {
    "addr:full":"Veldhorststr 26A Lisse Zuid-Holland 2161 ER",
    "addr:housenumber":"26a",
    "addr:postcode":"2161 er",
    "addr:street":"Veldhorststr",
    "iso:country":"NL",
    "sg:address":"Veldhorststr 26A",
    "sg:city":"Lisse",
    "sg:orig_category":"Vertalers",
    "sg:phone":"+31 252 420 445",
    "sg:postcode":"2161 ER",
    "sg:province":"Zuid-Holland",
    "wof:name":"Deloo-Frogneux",
    "wof:placetype":"venue"
},
  "geometry": {"coordinates":[4.553202,52.262703],"type":"Point"}
}