{
  "type": "Feature",
  "properties": {
    "addr:full":"Heemraadssngl 97 Rotterdam Zuid-Holland 3022 CB",
    "addr:housenumber":"97",
    "addr:postcode":"3022 cb",
    "addr:street":"Heemraadssngl",
    "iso:country":"NL",
    "sg:address":"Heemraadssngl 97",
    "sg:city":"Rotterdam",
    "sg:orig_category":"Levensmiddelen - Fabrieken En Groothandel",
    "sg:phone":"+31 10 425 6300",
    "sg:postcode":"3022 CB",
    "sg:province":"Zuid-Holland",
    "wof:name":"Veder Bv",
    "wof:placetype":"venue"
},
  "geometry": {"coordinates":[4.454588,51.92017],"type":"Point"}
}