{
  "type": "Feature",
  "properties": {
    "addr:full":"L Couperusstr 42 Voorburg Zuid-Holland 2274 XR",
    "addr:housenumber":"42",
    "addr:postcode":"2274 xr",
    "iso:country":"NL",
    "sg:address":"L Couperusstr 42",
    "sg:city":"Voorburg",
    "sg:orig_category":"Kantoor- En Secretariaatsservice",
    "sg:phone":"+31 70 369 2244",
    "sg:postcode":"2274 XR",
    "sg:province":"Zuid-Holland",
    "wof:name":"Amstock Interim",
    "wof:placetype":"venue"
},
  "geometry": {"coordinates":[4.3586769104,52.0733757019],"type":"Point"}
}