{
  "type": "Feature",
  "properties": {
    "addr:full":"Bergwg 80 Zeist Utrecht 3707 AD",
    "addr:housenumber":"80",
    "addr:postcode":"3707 ad",
    "addr:street":"Bergwg",
    "iso:country":"NL",
    "sg:address":"Bergwg 80",
    "sg:city":"Zeist",
    "sg:orig_category":"Adviesbureaus Bedrijfsorganisatie",
    "sg:phone":"+31 30 691 2550",
    "sg:postcode":"3707 AD",
    "sg:province":"Utrecht",
    "wof:name":"P & O",
    "wof:placetype":"venue"
},
  "geometry": {"coordinates":[5.24387,52.08548],"type":"Point"}
}