{
  "type": "Feature",
  "properties": {
    "addr:full":"Noorderwg 34 Hoogeveen Drenthe 7902 AR",
    "addr:housenumber":"34",
    "addr:postcode":"7902",
    "addr:street":"Noorderwg",
    "iso:country":"NL",
    "sg:address":"Noorderwg 34",
    "sg:city":"Hoogeveen",
    "sg:orig_category":"Centrale Verwarming - Installatie En Onderhoud",
    "sg:phone":"+31 528 240 710",
    "sg:postcode":"7902 AR",
    "sg:province":"Drenthe",
    "wof:name":"Achteren, Warmteservice Van",
    "wof:placetype":"venue"
},
  "geometry": {"coordinates":[6.483002,52.731171],"type":"Point"}
}