{
  "type": "Feature",
  "properties": {
    "addr:full":"Zandvoortstr 13 S Gravenhage Zuid-Holland 2586 VT",
    "addr:housenumber":"13;gravenhage",
    "addr:postcode":"2586",
    "addr:street":"Zandvoortstr;S",
    "iso:country":"NL",
    "sg:address":"Zandvoortstr 13",
    "sg:city":"S Gravenhage",
    "sg:orig_category":"Verzekeringen - Verzekeringskantoren",
    "sg:phone":"+31 70 352 2262",
    "sg:postcode":"2586 VT",
    "sg:province":"Zuid-Holland",
    "wof:name":"Gode",
    "wof:placetype":"venue"
},
  "geometry": {"coordinates":[4.277215,52.10672],"type":"Point"}
}