{
  "type": "Feature",
  "properties": {
    "iso:country":"NL",
    "sg:address":"C Ouwerkerkstr 1",
    "sg:city":"Emmen",
    "sg:orig_category":"Fietsen En Bromfietsen Verhuur",
    "sg:phone":"+31 591 618 267",
    "sg:postcode":"7815 CT",
    "sg:province":"Provincie Drenthe",
    "wof:name":"Drentse Rijwielverhuur",
    "wof:placetype":"venue"
},
  "geometry": {"coordinates":[6.889705,52.801556],"type":"Point"}
}