{
  "type": "Feature",
  "properties": {
    "iso:country":"NL",
    "sg:address":"Linnaeusstraat 104",
    "sg:city":"Amsterdam",
    "sg:orig_category":"Opticiens",
    "sg:phone":"+31 20 463 6062",
    "sg:postcode":"1092 CR",
    "sg:province":"Noord-Holland",
    "wof:name":"Pearle Opticiens",
    "wof:placetype":"venue"
},
  "geometry": {"coordinates":[4.9278688431,52.3554992676],"type":"Point"}
}