{
  "type": "Feature",
  "properties": {
    "addr:full":"Julianaln 63 Delft South Holland 2628 BC",
    "addr:housenumber":"63",
    "addr:postcode":"2628 bc",
    "addr:street":"Julianaln",
    "iso:country":"NL",
    "sg:address":"Julianaln 63",
    "sg:city":"Delft",
    "sg:orig_category":"Kinderopvang",
    "sg:phone":"+31 15 214 6636",
    "sg:postcode":"2628 BC",
    "sg:province":"South Holland",
    "wof:name":"Berenhonk, Het",
    "wof:placetype":"venue"
},
  "geometry": {"coordinates":[4.37106,52.009411],"type":"Point"}
}