{
  "type": "Feature",
  "properties": {
    "addr:full":"Laarderwg 298 Bussum Noord-Holland 1403 RR",
    "addr:housenumber":"298",
    "addr:postcode":"1403 rr",
    "iso:country":"NL",
    "sg:address":"Laarderwg 298",
    "sg:city":"Bussum",
    "sg:orig_category":"Administratie- En Boekhoudkantoren",
    "sg:phone":"+31 35 693 5207",
    "sg:postcode":"1403 RR",
    "sg:province":"Noord-Holland",
    "wof:name":"Berg, H Van De",
    "wof:placetype":"venue"
},
  "geometry": {"coordinates":[5.172227,52.262608],"type":"Point"}
}