{
  "type": "Feature",
  "properties": {
    "iso:country":"NL",
    "sg:address":"Sportparkln 40",
    "sg:city":"Tiel",
    "sg:orig_category":"New Age-Artikelen En -Diensten",
    "sg:phone":"+31 344 634 365",
    "sg:postcode":"4002 AW",
    "sg:province":"Gelderland",
    "wof:name":"Blauwe Zon, De",
    "wof:placetype":"venue"
},
  "geometry": {"coordinates":[5.421918,51.897453],"type":"Point"}
}