{
  "type": "Feature",
  "properties": {
    "iso:country":"NL",
    "sg:address":"Dorpsstraat 19",
    "sg:city":"Loosbroek",
    "sg:orig_category":"Goederenvervoer Over De Weg",
    "sg:phone":"+31 413 229 811",
    "sg:postcode":"5472 PH",
    "sg:province":"Noord-Brabant",
    "wof:name":"W.J.M. Lunenburg",
    "wof:placetype":"venue"
},
  "geometry": {"coordinates":[5.512764,51.678818],"type":"Point"}
}