{
  "type": "Feature",
  "properties": {
    "iso:country":"NL",
    "sg:address":"Wilgenstr 7",
    "sg:city":"Bergambacht",
    "sg:classifiers":[
        {
            "category":"Personal",
            "subcategory":"Nail Salon",
            "type":"Services"
        }
    ],
    "sg:phone":"+31 182 354 402",
    "sg:postcode":"2861 TN",
    "sg:province":"South Holland",
    "sg:tags":[
        "pedicure"
    ],
    "wof:name":"Ooms, H",
    "wof:placetype":"venue"
},
  "geometry": {"coordinates":[4.787674,51.93634],"type":"Point"}
}