{
  "type": "Feature",
  "properties": {
    "addr:full":"Riouwstr 17 Utrecht Utrecht 3531 CT",
    "addr:housenumber":"17",
    "addr:postcode":"3531 ct",
    "addr:street":"Riouwstr",
    "iso:country":"NL",
    "sg:address":"Riouwstr 17",
    "sg:city":"Utrecht",
    "sg:orig_category":"Vertalers",
    "sg:phone":"+31 30 294 8202",
    "sg:postcode":"3531 CT",
    "sg:province":"Utrecht",
    "wof:name":"Willems, E",
    "wof:placetype":"venue"
},
  "geometry": {"coordinates":[5.100104,52.092415],"type":"Point"}
}