{
  "type": "Feature",
  "properties": {
    "addr:full":"Flevoweg 77 Harderwijk Gelderland 3846 AH",
    "addr:housenumber":"77",
    "addr:postcode":"3846 ah",
    "addr:street":"Flevoweg;Gelderland",
    "iso:country":"NL",
    "sg:address":"Flevoweg 77",
    "sg:city":"Harderwijk",
    "sg:orig_category":"Bouwnijverheidsmachines Gh",
    "sg:phone":"+31 341 426 656",
    "sg:postcode":"3846 AH",
    "sg:province":"Gelderland",
    "wof:name":"Handelsonderneming Piet Krijnen Bv",
    "wof:placetype":"venue"
},
  "geometry": {"coordinates":[5.628592,52.354588],"type":"Point"}
}