{
  "type": "Feature",
  "properties": {
    "addr:full":"Nieuwstraat 124 Tilburg Noord-Brabant 5021 WX",
    "addr:housenumber":"124",
    "addr:postcode":"5021 wx",
    "addr:street":"Nieuwstraat",
    "iso:country":"NL",
    "sg:address":"Nieuwstraat 124",
    "sg:city":"Tilburg",
    "sg:classifiers":[
        {
            "category":"Fast Food",
            "type":"Food & Drink"
        }
    ],
    "sg:phone":"+31 13 542 2283",
    "sg:postcode":"5021 WX",
    "sg:province":"Noord-Brabant",
    "sg:tags":[
        "afhaal",
        "restaurant"
    ],
    "wof:name":"Frietaria Spooky",
    "wof:placetype":"venue"
},
  "geometry": {"coordinates":[5.09061,51.548569],"type":"Point"}
}