{
  "type": "Feature",
  "properties": {
    "addr:full":"Burgemeester Stramanweg 105/2 Amsterdam Zuidoost North Holland 1101 AA",
    "addr:housenumber":"105 / 2",
    "addr:postcode":"1101 aa",
    "addr:street":"Burgemeester Stramanweg",
    "iso:country":"NL",
    "sg:address":"Burgemeester Stramanweg 105/2",
    "sg:city":"Amsterdam Zuidoost",
    "sg:classifiers":[
        {
            "category":"Professional",
            "subcategory":"Accounting & Tax Preparation",
            "type":"Services"
        }
    ],
    "sg:phone":"+31 20 691 7335",
    "sg:postcode":"1101 AA",
    "sg:province":"North Holland",
    "sg:tags":[
        "accountant"
    ],
    "wof:name":"Stighter & Partners",
    "wof:placetype":"venue"
},
  "geometry": {"coordinates":[4.936558,52.312305],"type":"Point"}
}