{
  "type": "Feature",
  "properties": {
    "iso:country":"NL",
    "sg:address":"Markt 10",
    "sg:city":"Wageningen",
    "sg:orig_category":"Kappers",
    "sg:phone":"+31 317 412 153",
    "sg:postcode":"6701 CZ",
    "sg:province":"Gelderland",
    "wof:name":"Kapsalon Dammingh",
    "wof:placetype":"venue"
},
  "geometry": {"coordinates":[5.6620960236,51.9645347595],"type":"Point"}
}