{
  "type": "Feature",
  "properties": {
    "iso:country":"NL",
    "sg:address":"Vyfhuizenbaan 30",
    "sg:city":"Riel",
    "sg:orig_category":"Grondwerken",
    "sg:phone":"+31 13 518 1335",
    "sg:postcode":"5133 NH",
    "sg:province":"Noord-Brabant",
    "wof:name":"Graafmans",
    "wof:placetype":"venue"
},
  "geometry": {"coordinates":[4.986282,51.522217],"type":"Point"}
}