{
  "type": "Feature",
  "properties": {
    "addr:full":"Korenstr 57 Dalfsen Overijssel 7722 RS",
    "addr:housenumber":"57",
    "addr:postcode":"7722 rs",
    "addr:street":"Korenstr",
    "iso:country":"NL",
    "sg:address":"Korenstr 57",
    "sg:city":"Dalfsen",
    "sg:orig_category":"Mengmachines",
    "sg:phone":"+31 529 430 767",
    "sg:postcode":"7722 RS",
    "sg:province":"Overijssel",
    "sg:website":"http://www.sps-group.com",
    "wof:name":"Sps Group Bv",
    "wof:placetype":"venue"
},
  "geometry": {"coordinates":[6.266825,52.509708],"type":"Point"}
}