{
  "type": "Feature",
  "properties": {
    "addr:full":"Postbus 231 Eindhoven Noord-Brabant 5600 AE",
    "addr:housenumber":"231",
    "addr:postcode":"5600 ae",
    "addr:street":"Postbus",
    "iso:country":"NL",
    "sg:address":"Postbus 231",
    "sg:city":"Eindhoven",
    "sg:orig_category":"Verenigingen En Stichtingen",
    "sg:phone":"+31 40 293 9134",
    "sg:postcode":"5600 AE",
    "sg:province":"Noord-Brabant",
    "wof:name":"Aandacht, Sticht",
    "wof:placetype":"venue"
},
  "geometry": {"coordinates":[5.48411,51.434471],"type":"Point"}
}