{
  "type": "Feature",
  "properties": {
    "addr:full":"Diergaarde 20 Ulft Gelderland 7071 WX",
    "addr:housenumber":"20",
    "addr:postcode":"7071 wx",
    "addr:street":"Diergaarde;Gelderland",
    "iso:country":"NL",
    "sg:address":"Diergaarde 20",
    "sg:city":"Ulft",
    "sg:classifiers":[
        {
            "category":"Personal",
            "subcategory":"Nail Salon",
            "type":"Services"
        }
    ],
    "sg:phone":"+31 315 683 362",
    "sg:postcode":"7071 WX",
    "sg:province":"Gelderland",
    "sg:tags":[
        "pedicure"
    ],
    "wof:name":"Oostendorp, B",
    "wof:placetype":"venue"
},
  "geometry": {"coordinates":[6.382803,51.889774],"type":"Point"}
}