{
  "type": "Feature",
  "properties": {
    "addr:full":"Bredasewg 41 Baarle Nassau Noord-Brabant 5111 GD",
    "addr:housenumber":"41",
    "addr:postcode":"5111 gd",
    "addr:street":"Bredasewg",
    "iso:country":"NL",
    "sg:address":"Bredasewg 41",
    "sg:city":"Baarle Nassau",
    "sg:orig_category":"Verenigingen En Stichtingen",
    "sg:phone":"+31 13 507 9843",
    "sg:postcode":"5111 GD",
    "sg:province":"Noord-Brabant",
    "wof:name":"Sint Franciscus",
    "wof:placetype":"venue"
},
  "geometry": {"coordinates":[4.895393,51.474659],"type":"Point"}
}