{
  "type": "Feature",
  "properties": {
    "iso:country":"NL",
    "sg:address":"Pr Beatrixstr 46A",
    "sg:city":"Eck En Wiel",
    "sg:orig_category":"Kinderopvang",
    "sg:phone":"+31 344 694 098",
    "sg:postcode":"4024 HM",
    "sg:province":"Gelderland",
    "wof:name":"Hummelhof, De",
    "wof:placetype":"venue"
},
  "geometry": {"coordinates":[5.455375,51.968937],"type":"Point"}
}