{
  "type": "Feature",
  "properties": {
    "addr:full":"Dillestr 32 Haarlem North Holland 2034 MP",
    "addr:housenumber":"32",
    "addr:postcode":"2034 mp",
    "addr:street":"Dillestr",
    "iso:country":"NL",
    "sg:address":"Dillestr 32",
    "sg:city":"Haarlem",
    "sg:orig_category":"Honden- En Kattentrimsalons",
    "sg:phone":"+31 23 535 4045",
    "sg:postcode":"2034 MP",
    "sg:province":"North Holland",
    "wof:name":"Dijkstra, A",
    "wof:placetype":"venue"
},
  "geometry": {"coordinates":[4.642407,52.366837],"type":"Point"}
}