{
  "type": "Feature",
  "properties": {
    "addr:full":"Dukaatstr 13 Oosterhout Nb Noord-Brabant 4903 RN",
    "addr:housenumber":"13",
    "addr:postcode":"4903 rn",
    "addr:street":"Dukaatstr",
    "iso:country":"NL",
    "sg:address":"Dukaatstr 13",
    "sg:city":"Oosterhout Nb",
    "sg:orig_category":"Hek- En Rasterwerken",
    "sg:phone":"+31 162 457 744",
    "sg:postcode":"4903 RN",
    "sg:province":"Noord-Brabant",
    "wof:name":"Brabant Bv",
    "wof:placetype":"venue"
},
  "geometry": {"coordinates":[4.870225,51.621567],"type":"Point"}
}