{
  "type": "Feature",
  "properties": {
    "addr:full":"Harnaslaan 21 Utrecht Utrecht 3525 GE",
    "addr:housenumber":"21",
    "addr:postcode":"3525",
    "addr:street":"Harnaslaan",
    "iso:country":"NL",
    "sg:address":"Harnaslaan 21",
    "sg:city":"Utrecht",
    "sg:orig_category":"Schilderwerk",
    "sg:phone":"+31 30 289 7996",
    "sg:postcode":"3525 GE",
    "sg:province":"Utrecht",
    "wof:name":"Scipio Schilderwerken",
    "wof:placetype":"venue"
},
  "geometry": {"coordinates":[5.121112,52.058739],"type":"Point"}
}