{
  "type": "Feature",
  "properties": {
    "iso:country":"NL",
    "sg:address":"Jeruzalem 15",
    "sg:city":"Velp Gld",
    "sg:orig_category":"Psychotherapeuten",
    "sg:phone":"+31 26 363 8298",
    "sg:postcode":"6881 JK",
    "sg:province":"Gelderland",
    "wof:name":"Agogische-Praktijk",
    "wof:placetype":"venue"
},
  "geometry": {"coordinates":[5.973432,51.999405],"type":"Point"}
}