{
  "type": "Feature",
  "properties": {
    "addr:full":"Breeuwerswg 14 Den Helder Noord-Holland 1786 PG",
    "addr:housenumber":"14",
    "addr:postcode":"1786 pg",
    "addr:street":"Breeuwerswg",
    "iso:country":"NL",
    "sg:address":"Breeuwerswg 14",
    "sg:city":"Den Helder",
    "sg:classifiers":[
        {
            "category":"Retail",
            "subcategory":"Auto Repair",
            "type":"Services"
        }
    ],
    "sg:phone":"+31 223 631 826",
    "sg:postcode":"1786 PG",
    "sg:province":"Noord-Holland",
    "sg:tags":[
        "garage"
    ],
    "wof:name":"Kooij Klassiekers & Garage",
    "wof:placetype":"venue"
},
  "geometry": {"coordinates":[4.781769,52.913879],"type":"Point"}
}