{
  "type": "Feature",
  "properties": {
    "addr:full":"Beststr 38 Arnhem Gelderland 6844 BJ",
    "addr:housenumber":"38",
    "addr:postcode":"6844 bj",
    "addr:street":"Beststr",
    "iso:country":"NL",
    "sg:address":"Beststr 38",
    "sg:city":"Arnhem",
    "sg:orig_category":"Webdesign Bureaus",
    "sg:phone":"+31 26 381 0881",
    "sg:postcode":"6844 BJ",
    "sg:province":"Gelderland",
    "sg:website":"http://www.look33.nl",
    "wof:name":"Look 33",
    "wof:placetype":"venue"
},
  "geometry": {"coordinates":[5.8603482246,51.9469909668],"type":"Point"}
}