{
  "type": "Feature",
  "properties": {
    "iso:country":"NL",
    "sg:address":"Havenstraatse Wal 64",
    "sg:city":"Schoonhoven",
    "sg:orig_category":"Beeldende Kunstenaars",
    "sg:phone":"+31 182 385 208",
    "sg:postcode":"2871 ES",
    "sg:province":"Zuid-Holland",
    "wof:name":"Suringh, Hanneke",
    "wof:placetype":"venue"
},
  "geometry": {"coordinates":[4.849298,51.94455],"type":"Point"}
}