{
  "type": "Feature",
  "properties": {
    "iso:country":"NL",
    "sg:address":"Modem 2L",
    "sg:city":"Coevorden",
    "sg:orig_category":"Keukens",
    "sg:phone":"+31 524 515 641",
    "sg:postcode":"7741 MJ",
    "sg:province":"Drenthe",
    "sg:website":"http://www.kombuis-coevorden.nl",
    "wof:name":"Kombuis, 'T",
    "wof:placetype":"venue"
},
  "geometry": {"coordinates":[6.724501,52.66095],"type":"Point"}
}