{
  "type": "Feature",
  "properties": {
    "iso:country":"NL",
    "sg:address":"Kouwenoord 1872",
    "sg:city":"Amsterdam Zuidoost",
    "sg:orig_category":"Fotostudio'S And Fotografen",
    "sg:phone":"+31 20 699 4995",
    "sg:postcode":"1104 KB",
    "sg:province":"North Holland",
    "wof:name":"C.J. Levesque",
    "wof:placetype":"venue"
},
  "geometry": {"coordinates":[4.984383,52.317757],"type":"Point"}
}