{
  "type": "Feature",
  "properties": {
    "addr:full":"Kouwenoord 1872 Amsterdam Zuidoost North Holland 1104 KB",
    "addr:housenumber":"1872",
    "addr:postcode":"1104 kb",
    "addr:street":"Kouwenoord",
    "iso:country":"NL",
    "sg:address":"Kouwenoord 1872",
    "sg:city":"Amsterdam Zuidoost",
    "sg:orig_category":"Fotostudio'S And Fotografen",
    "sg:phone":"+31 20 699 4995",
    "sg:postcode":"1104 KB",
    "sg:province":"North Holland",
    "wof:name":"C.J. Levesque",
    "wof:placetype":"venue"
},
  "geometry": {"coordinates":[4.984383,52.317757],"type":"Point"}
}