{
  "type": "Feature",
  "properties": {
    "addr:full":"Getydelant 7 Volendam Noord-Holland 1132 ES",
    "addr:housenumber":"7",
    "addr:postcode":"1132 es",
    "addr:street":"Getydelant",
    "iso:country":"NL",
    "sg:address":"Getydelant 7",
    "sg:city":"Volendam",
    "sg:orig_category":"Keukens",
    "sg:phone":"+31 6 22279740",
    "sg:postcode":"1132 ES",
    "sg:province":"Noord-Holland",
    "wof:name":"Schilder",
    "wof:placetype":"venue"
},
  "geometry": {"coordinates":[5.045227,52.49575],"type":"Point"}
}