{
  "type": "Feature",
  "properties": {
    "addr:full":"G B De Vroomenstr 19 Sassenheim South Holland 2172 SM",
    "addr:housenumber":"19",
    "addr:postcode":"2172 sm",
    "iso:country":"NL",
    "sg:address":"G B De Vroomenstr 19",
    "sg:city":"Sassenheim",
    "sg:orig_category":"Webdesign Bureaus",
    "sg:phone":"+31 252 221 620",
    "sg:postcode":"2172 SM",
    "sg:province":"South Holland",
    "sg:website":"http://www.icommus.nl",
    "wof:name":"Icommus",
    "wof:placetype":"venue"
},
  "geometry": {"coordinates":[4.5164561272,52.2212142944],"type":"Point"}
}