{
  "type": "Feature",
  "properties": {
    "addr:full":"St. Antoniusstraat 10 Eindhoven Centrum Noord-Brabant 5616 RT",
    "addr:housenumber":"10",
    "addr:postcode":"5616 rt",
    "addr:street":"St. Antoniusstraat",
    "iso:country":"NL",
    "sg:address":"St. Antoniusstraat 10",
    "sg:city":"Eindhoven Centrum",
    "sg:orig_category":"Fotostudio'S And Fotografen",
    "sg:phone":"+31 40 251 8180",
    "sg:postcode":"5616 RT",
    "sg:province":"Noord-Brabant",
    "wof:name":"Foto Visie",
    "wof:placetype":"venue"
},
  "geometry": {"coordinates":[5.46007,51.439308],"type":"Point"}
}