{
  "type": "Feature",
  "properties": {
    "iso:country":"NL",
    "sg:address":"Westeinde 2",
    "sg:city":"Berkenwoude",
    "sg:orig_category":"Kappers",
    "sg:phone":"+31 182 362 946",
    "sg:postcode":"2825 AK",
    "sg:province":"Zuid-Holland",
    "wof:name":"Hairfashion Rita",
    "wof:placetype":"venue"
},
  "geometry": {"coordinates":[4.7097787857,51.9445724487],"type":"Point"}
}