{
  "type": "Feature",
  "properties": {
    "addr:full":"Jansweg 37 Haarlem Noord-Holland 2011 KL",
    "addr:housenumber":"37",
    "addr:postcode":"2011 kl",
    "addr:street":"Jansweg",
    "iso:country":"NL",
    "sg:address":"Jansweg 37",
    "sg:city":"Haarlem",
    "sg:orig_category":"Huishoudapparatuur, Televisies And Radio'S",
    "sg:phone":"+31 23 532 0230",
    "sg:postcode":"2011 KL",
    "sg:province":"Noord-Holland",
    "wof:name":"Speaker & Co",
    "wof:placetype":"venue"
},
  "geometry": {"coordinates":[4.639659,52.38641],"type":"Point"}
}