{
  "type": "Feature",
  "properties": {
    "addr:full":"Croeselaan 183 Utrecht Utrecht 3521 BM",
    "addr:housenumber":"183",
    "addr:postcode":"3521 bm",
    "addr:street":"Croeselaan",
    "iso:country":"NL",
    "sg:address":"Croeselaan 183",
    "sg:city":"Utrecht",
    "sg:orig_category":"Fitnesscentra",
    "sg:phone":"+31 30 294 0300",
    "sg:postcode":"3521 BM",
    "sg:province":"Utrecht",
    "wof:name":"Paul Pessel Sport",
    "wof:placetype":"venue"
},
  "geometry": {"coordinates":[5.108869,52.084274],"type":"Point"}
}