{
  "type": "Feature",
  "properties": {
    "addr:full":"Kerkln 1 Zwammerdam Zuid-Holland 2471 AK",
    "addr:housenumber":"1",
    "addr:postcode":"2471 ak",
    "addr:street":"Kerkln",
    "iso:country":"NL",
    "sg:address":"Kerkln 1",
    "sg:city":"Zwammerdam",
    "sg:orig_category":"Peuterspeelzalen",
    "sg:phone":"+31 172 618 362",
    "sg:postcode":"2471 AK",
    "sg:province":"Zuid-Holland",
    "wof:name":"Speelhuis, 'T",
    "wof:placetype":"venue"
},
  "geometry": {"coordinates":[4.730431,52.104767],"type":"Point"}
}