{
  "type": "Feature",
  "properties": {
    "addr:full":"Evert Reddersland 20 Staphorst Overijssel 7951 GH",
    "addr:housenumber":"20",
    "addr:postcode":"7951 gh",
    "addr:street":"Evert Reddersland",
    "iso:country":"NL",
    "sg:address":"Evert Reddersland 20",
    "sg:city":"Staphorst",
    "sg:orig_category":"Landbouwmachines Gh",
    "sg:phone":"+31 522 462 348",
    "sg:postcode":"7951 GH",
    "sg:province":"Overijssel",
    "wof:name":"A. Van Nierop",
    "wof:placetype":"venue"
},
  "geometry": {"coordinates":[6.213142,52.643929],"type":"Point"}
}