{
  "type": "Feature",
  "properties": {
    "addr:full":"Molendijk 1 'S Gravenmoer Noord-Brabant 5109 RL",
    "addr:housenumber":"1",
    "addr:postcode":"gravenmoer;5109 rl",
    "addr:street":"Molendijk;S",
    "iso:country":"NL",
    "sg:address":"Molendijk 1",
    "sg:city":"'S Gravenmoer",
    "sg:orig_category":"Autokeuringen",
    "sg:phone":"+31 162 312 896",
    "sg:postcode":"5109 RL",
    "sg:province":"Noord-Brabant",
    "wof:name":"Autobedrijf J. Dekkers",
    "wof:placetype":"venue"
},
  "geometry": {"coordinates":[4.940901,51.658112],"type":"Point"}
}