{
  "type": "Feature",
  "properties": {
    "addr:full":"Signaal 3 Purmerend North Holland 1446 WT",
    "addr:housenumber":"3",
    "addr:postcode":"1446 wt",
    "addr:street":"Signaal",
    "iso:country":"NL",
    "sg:address":"Signaal 3",
    "sg:city":"Purmerend",
    "sg:orig_category":"Verhuur Diversen",
    "sg:phone":"+31 299 463 603",
    "sg:postcode":"1446 WT",
    "sg:province":"North Holland",
    "sg:website":"http://www.reemark.nl",
    "wof:name":"Reemark",
    "wof:placetype":"venue"
},
  "geometry": {"coordinates":[5.006764,52.511349],"type":"Point"}
}