{
  "type": "Feature",
  "properties": {
    "addr:full":"Borchmolendk 19A St Oedenrode North Brabant 5492 AJ",
    "addr:housenumber":"19a",
    "addr:postcode":"5492 aj",
    "addr:street":"Borchmolendk;St Oedenrode",
    "iso:country":"NL",
    "sg:address":"Borchmolendk 19A",
    "sg:city":"St Oedenrode",
    "sg:orig_category":"Accountants - Administratie- Consulenten En -Kantoren",
    "sg:phone":"+31 413 479 595",
    "sg:postcode":"5492 AJ",
    "sg:province":"North Brabant",
    "wof:name":"Zwanenberggroep Sint-Oedenrode",
    "wof:placetype":"venue"
},
  "geometry": {"coordinates":[5.463148,51.565746],"type":"Point"}
}