{
  "type": "Feature",
  "properties": {
    "iso:country":"NL",
    "sg:address":"Groenestraat 63",
    "sg:city":"Rheden",
    "sg:orig_category":"Postkantoren",
    "sg:phone":"+31 26 495 2540",
    "sg:postcode":"6991 GD",
    "sg:province":"Gelderland",
    "wof:name":"Postkantoor",
    "wof:placetype":"venue"
},
  "geometry": {"coordinates":[6.035493,52.005413],"type":"Point"}
}