{
  "type": "Feature",
  "properties": {
    "addr:full":"V Zylstr 9 S Heerenhoek Zeeland 4453 BB",
    "addr:housenumber":"9 s",
    "addr:postcode":"4453 bb",
    "addr:street":"Zylstr;Zeeland",
    "iso:country":"NL",
    "sg:address":"V Zylstr 9",
    "sg:city":"S Heerenhoek",
    "sg:orig_category":"Modevakscholen",
    "sg:phone":"+31 113 351 938",
    "sg:postcode":"4453 BB",
    "sg:province":"Zeeland",
    "wof:name":"Ensaid",
    "wof:placetype":"venue"
},
  "geometry": {"coordinates":[3.768905,51.451115],"type":"Point"}
}