{
  "type": "Feature",
  "properties": {
    "addr:full":"Molenstr 142A Kinderdyk Zuid-Holland 2961 AP",
    "addr:housenumber":"142a",
    "addr:postcode":"2961 ap",
    "addr:street":"Molenstr",
    "iso:country":"NL",
    "sg:address":"Molenstr 142A",
    "sg:city":"Kinderdyk",
    "sg:orig_category":"Galeries",
    "sg:phone":"+31 78 691 9423",
    "sg:postcode":"2961 AP",
    "sg:province":"Zuid-Holland",
    "wof:name":"Kooten, C Van",
    "wof:placetype":"venue"
},
  "geometry": {"coordinates":[4.632803,51.886402],"type":"Point"}
}