{
  "type": "Feature",
  "properties": {
    "addr:full":"Kweekgrasstr 29 Almere Flevoland 1313 BZ",
    "addr:housenumber":"29",
    "addr:postcode":"1313 bz",
    "addr:street":"Kweekgrasstr;Flevoland",
    "iso:country":"NL",
    "sg:address":"Kweekgrasstr 29",
    "sg:city":"Almere",
    "sg:orig_category":"Schoonheidsinstituten",
    "sg:phone":"+31 36 530 3953",
    "sg:postcode":"1313 BZ",
    "sg:province":"Flevoland",
    "wof:name":"Margriet",
    "wof:placetype":"venue"
},
  "geometry": {"coordinates":[5.200493,52.385746],"type":"Point"}
}