{
  "type": "Feature",
  "properties": {
    "addr:full":"Savannahwg 25 Utrecht Utrecht 3542 AW",
    "addr:housenumber":"25",
    "addr:postcode":"3542 aw",
    "addr:street":"Savannahwg",
    "iso:country":"NL",
    "sg:address":"Savannahwg 25",
    "sg:city":"Utrecht",
    "sg:orig_category":"Sanitaire Artikelen",
    "sg:phone":"+31 30 247 3400",
    "sg:postcode":"3542 AW",
    "sg:province":"Utrecht",
    "sg:website":"http://www.villeroy-boch.com",
    "wof:name":"Villeroy & Boch Wellness / Ucosan",
    "wof:placetype":"venue"
},
  "geometry": {"coordinates":[5.042043,52.116203],"type":"Point"}
}