{
  "type": "Feature",
  "properties": {
    "iso:country":"NL",
    "sg:address":"Noordplein 131",
    "sg:city":"Rotterdam",
    "sg:orig_category":"Kappers",
    "sg:phone":"+31 10 466 1417",
    "sg:postcode":"3035 EC",
    "sg:province":"South Holland",
    "wof:name":"Kapsalon Diana",
    "wof:placetype":"venue"
},
  "geometry": {"coordinates":[4.483894825,51.9307785034],"type":"Point"}
}