{
  "type": "Feature",
  "properties": {
    "addr:full":"Haarstraat 63 Gorinchem Zuid-Holland 4201 JB",
    "addr:housenumber":"63",
    "addr:postcode":"4201 jb",
    "addr:street":"Haarstraat",
    "iso:country":"NL",
    "sg:address":"Haarstraat 63",
    "sg:city":"Gorinchem",
    "sg:orig_category":"Werving And Selectie Van Tijdelijk Personeel And Uitzendkantoren",
    "sg:phone":"+31 183 633 488",
    "sg:postcode":"4201 JB",
    "sg:province":"Zuid-Holland",
    "wof:name":"Manpower",
    "wof:placetype":"venue"
},
  "geometry": {"coordinates":[4.9746689796,51.8321609497],"type":"Point"}
}