{
  "type": "Feature",
  "properties": {
    "iso:country":"NL",
    "sg:address":"Herengracht 12",
    "sg:city":"Maarssen",
    "sg:orig_category":"Binnenhuisarchitecten",
    "sg:phone":"+31 346 551 550",
    "sg:postcode":"3601 AM",
    "sg:province":"Utrecht",
    "wof:name":"Vandie",
    "wof:placetype":"venue"
},
  "geometry": {"coordinates":[5.038289,52.1408],"type":"Point"}
}