{
  "type": "Feature",
  "properties": {
    "addr:full":"Enschotsestr 238 Tilburg Noord-Brabant 5014 DK",
    "addr:housenumber":"238",
    "addr:postcode":"5014 dk",
    "addr:street":"Tilburg",
    "iso:country":"NL",
    "sg:address":"Enschotsestr 238",
    "sg:city":"Tilburg",
    "sg:orig_category":"Horeca-Inrichtingen En -Uitrustingen",
    "sg:phone":"+31 13 536 9281",
    "sg:postcode":"5014 DK",
    "sg:province":"Noord-Brabant",
    "sg:website":"http://www.gbmeubelen.nl",
    "wof:name":"Gb Horeca- En Projectmeubelen",
    "wof:placetype":"venue"
},
  "geometry": {"coordinates":[5.094397,51.561916],"type":"Point"}
}