{
  "type": "Feature",
  "properties": {
    "iso:country":"NL",
    "sg:address":"Hondsdrafwg 1",
    "sg:city":"Zoeterwoude",
    "sg:orig_category":"Verenigingen En Stichtingen",
    "sg:phone":"+31 71 580 9281",
    "sg:postcode":"2381 BZ",
    "sg:province":"Zuid-Holland",
    "wof:name":"Vluchtelingenwerk Zoeterwoude",
    "wof:placetype":"venue"
},
  "geometry": {"coordinates":[4.495526,52.11713],"type":"Point"}
}