{
  "type": "Feature",
  "properties": {
    "addr:full":"Molenpas 14 Tegelen Limburg 5931 NH",
    "addr:housenumber":"14",
    "addr:postcode":"5931 nh",
    "addr:street":"Molenpas",
    "iso:country":"NL",
    "sg:address":"Molenpas 14",
    "sg:city":"Tegelen",
    "sg:orig_category":"Geluidsinstallaties",
    "sg:phone":"+31 77 324 0683",
    "sg:postcode":"5931 NH",
    "sg:province":"Limburg",
    "wof:name":"Move It Entertainment",
    "wof:placetype":"venue"
},
  "geometry": {"coordinates":[6.140734,51.343071],"type":"Point"}
}