{
  "type": "Feature",
  "properties": {
    "addr:full":"Geldersedam 74 'S Hertogenbosch North Brabant 5212 RD",
    "addr:housenumber":"74",
    "addr:postcode":"5212 rd",
    "addr:street":"Geldersedam;' S Hertogenbosch",
    "iso:country":"NL",
    "sg:address":"Geldersedam 74",
    "sg:city":"'S Hertogenbosch",
    "sg:orig_category":"Fotostudio'S And Fotografen",
    "sg:phone":"+31 73 690 1654",
    "sg:postcode":"5212 RD",
    "sg:province":"North Brabant",
    "wof:name":"Jee Mol",
    "wof:placetype":"venue"
},
  "geometry": {"coordinates":[5.309251,51.696167],"type":"Point"}
}