{
  "type": "Feature",
  "properties": {
    "iso:country":"NL",
    "sg:address":"Grubbenweg 19",
    "sg:city":"Klimmen",
    "sg:orig_category":"Architecten",
    "sg:phone":"+31 45 405 1293",
    "sg:postcode":"6343 CA",
    "sg:province":"Limburg",
    "wof:name":"L.C. De Vor",
    "wof:placetype":"venue"
},
  "geometry": {"coordinates":[5.882715,50.874187],"type":"Point"}
}