{
  "type": "Feature",
  "properties": {
    "addr:full":"Rapenlandstr 9 Eindhoven Noord-Brabant 5623 EW",
    "addr:housenumber":"9",
    "addr:postcode":"5623 ew",
    "addr:street":"Rapenlandstr",
    "iso:country":"NL",
    "sg:address":"Rapenlandstr 9",
    "sg:city":"Eindhoven",
    "sg:classifiers":[
        {
            "category":"Retail",
            "subcategory":"Auto Repair",
            "type":"Services"
        }
    ],
    "sg:phone":"+31 40 246 2244",
    "sg:postcode":"5623 EW",
    "sg:province":"Noord-Brabant",
    "sg:tags":[
        "garage"
    ],
    "wof:name":"Bruijsten",
    "wof:placetype":"venue"
},
  "geometry": {"coordinates":[5.472454,51.461784],"type":"Point"}
}