{
  "type": "Feature",
  "properties": {
    "addr:full":"Zomerdijk 39 Meppel NL.08 7942 JS",
    "addr:housenumber":"39;nl.08",
    "addr:postcode":"7942 js",
    "addr:street":"Zomerdijk",
    "iso:country":"NL",
    "sg:address":"Zomerdijk 39",
    "sg:city":"Meppel",
    "sg:orig_category":"Pleziervaartuigen And Reparatie",
    "sg:phone":"+31 522 254 243",
    "sg:postcode":"7942 JS",
    "sg:province":"NL.08",
    "wof:name":"Jachtwerf Holterman",
    "wof:placetype":"venue"
},
  "geometry": {"coordinates":[6.160794,52.69249],"type":"Point"}
}