{
  "type": "Feature",
  "properties": {
    "addr:full":"T Hoogtln 15 Noordwykerhout Zuid-Holland 2211 AN",
    "addr:housenumber":"15",
    "addr:postcode":"2211 an",
    "iso:country":"NL",
    "sg:address":"T Hoogtln 15",
    "sg:city":"Noordwykerhout",
    "sg:orig_category":"Bloemen En Planten",
    "sg:phone":"+31 252 372 273",
    "sg:postcode":"2211 AN",
    "sg:province":"Zuid-Holland",
    "wof:name":"Lommerse Int Bv",
    "wof:placetype":"venue"
},
  "geometry": {"coordinates":[4.491189,52.26347],"type":"Point"}
}