{
  "type": "Feature",
  "properties": {
    "addr:full":"Piersonlaan 5 Huizen North Holland 1272 JR",
    "addr:housenumber":"5",
    "addr:postcode":"1272 jr",
    "addr:street":"Piersonlaan",
    "iso:country":"NL",
    "sg:address":"Piersonlaan 5",
    "sg:city":"Huizen",
    "sg:orig_category":"Technische Studies And Onderzoek",
    "sg:phone":"+31 35 525 1343",
    "sg:postcode":"1272 JR",
    "sg:province":"North Holland",
    "wof:name":"M Dijkxhoorn",
    "wof:placetype":"venue"
},
  "geometry": {"coordinates":[5.225164,52.291435],"type":"Point"}
}