{
  "type": "Feature",
  "properties": {
    "addr:full":"Herestr 33 Groningen Groningen 9711 LB",
    "addr:housenumber":"33",
    "addr:postcode":"9711 lb",
    "addr:street":"Herestr",
    "iso:country":"NL",
    "sg:address":"Herestr 33",
    "sg:city":"Groningen",
    "sg:orig_category":"Boeken Antiquarische En Gebruikte",
    "sg:phone":"+31 50 312 1422",
    "sg:postcode":"9711 LB",
    "sg:province":"Groningen",
    "sg:website":"http://www.deslegte.nl",
    "wof:name":"Slegte Bv, J De",
    "wof:placetype":"venue"
},
  "geometry": {"coordinates":[6.567027,53.217171],"type":"Point"}
}