{
  "type": "Feature",
  "properties": {
    "addr:full":"Koolemans Beynenstraat 82 Nijmegen Gelderland 6521 EX",
    "addr:housenumber":"82",
    "addr:postcode":"6521 ex",
    "addr:street":"Koolemans Beynenstraat;Gelderland",
    "iso:country":"NL",
    "sg:address":"Koolemans Beynenstraat 82",
    "sg:city":"Nijmegen",
    "sg:orig_category":"Kappers",
    "sg:phone":"+31 24 360 2559",
    "sg:postcode":"6521 EX",
    "sg:province":"Gelderland",
    "wof:name":"Kuif",
    "wof:placetype":"venue"
},
  "geometry": {"coordinates":[5.874353,51.83551],"type":"Point"}
}