{
  "type": "Feature",
  "properties": {
    "addr:full":"Kuilenstraat 15 Meerssen Limburg 6231 AT",
    "addr:housenumber":"15",
    "addr:postcode":"6231",
    "addr:street":"Kuilenstraat",
    "iso:country":"NL",
    "sg:address":"Kuilenstraat 15",
    "sg:city":"Meerssen",
    "sg:classifiers":[
        {
            "category":"Fast Food",
            "type":"Food & Drink"
        }
    ],
    "sg:phone":"+31 43 364 2246",
    "sg:postcode":"6231 AT",
    "sg:province":"Limburg",
    "sg:tags":[
        "afhaal",
        "restaurant"
    ],
    "wof:name":"Friture De Lange",
    "wof:placetype":"venue"
},
  "geometry": {"coordinates":[5.736431,50.876156],"type":"Point"}
}