{
  "type": "Feature",
  "properties": {
    "iso:country":"NL",
    "sg:address":"Nieuwstraat 27",
    "sg:city":"Bruinisse",
    "sg:orig_category":"Autokeuringen",
    "sg:phone":"+31 111 481 456",
    "sg:postcode":"4311 AM",
    "sg:province":"Zeeland",
    "wof:name":"Garagebedrijf Gebroeders Bal",
    "wof:placetype":"venue"
},
  "geometry": {"coordinates":[4.093957,51.660896],"type":"Point"}
}