{
  "type": "Feature",
  "properties": {
    "addr:full":"Middenhavenstraat 46 Ijmuiden North Holland 1976 CM",
    "addr:housenumber":"46",
    "addr:postcode":"1976 cm",
    "addr:street":"Middenhavenstraat",
    "iso:country":"NL",
    "sg:address":"Middenhavenstraat 46",
    "sg:city":"Ijmuiden",
    "sg:orig_category":"Pompen And Compressoren Fab",
    "sg:phone":"+31 255 514 564",
    "sg:postcode":"1976 CM",
    "sg:province":"North Holland",
    "wof:name":"Hydroservice Bv",
    "wof:placetype":"venue"
},
  "geometry": {"coordinates":[4.588027,52.458691],"type":"Point"}
}