{
  "type": "Feature",
  "properties": {
    "addr:full":"Peperstr 20 Buren Gld Gelderland 4116 BG",
    "addr:housenumber":"20",
    "addr:postcode":"4116",
    "addr:street":"Peperstr;Gld Gelderland",
    "iso:country":"NL",
    "sg:address":"Peperstr 20",
    "sg:city":"Buren Gld",
    "sg:orig_category":"Verzekeringen - Verzekeringskantoren",
    "sg:phone":"+31 344 576 123",
    "sg:postcode":"4116 BG",
    "sg:province":"Gelderland",
    "wof:name":"Rossum & Zn, Van",
    "wof:placetype":"venue"
},
  "geometry": {"coordinates":[5.334942,51.910599],"type":"Point"}
}