{
  "type": "Feature",
  "properties": {
    "addr:full":"Raaigras 11 Gouda South Holland 2804 NA",
    "addr:housenumber":"11",
    "addr:postcode":"2804 na",
    "addr:street":"Raaigras",
    "iso:country":"NL",
    "sg:address":"Raaigras 11",
    "sg:city":"Gouda",
    "sg:orig_category":"Woningtextiel - Fabrieken En Groothandel",
    "sg:phone":"+31 182 572 983",
    "sg:postcode":"2804 NA",
    "sg:province":"South Holland",
    "wof:name":"Euro Impex Trading",
    "wof:placetype":"venue"
},
  "geometry": {"coordinates":[4.7148981094,52.0325088501],"type":"Point"}
}