{
  "type": "Feature",
  "properties": {
    "addr:full":"O Nassauln 19 Amsterdam Noord-Holland 1075 AH",
    "addr:housenumber":"19",
    "addr:postcode":"1075 ah",
    "iso:country":"NL",
    "sg:address":"O Nassauln 19",
    "sg:city":"Amsterdam",
    "sg:orig_category":"Administratie- En Boekhoudkantoren",
    "sg:phone":"+31 20 492 4100",
    "sg:postcode":"1075 AH",
    "sg:province":"Noord-Holland",
    "sg:website":"http://www.financeview.nl",
    "wof:name":"Finance View",
    "wof:placetype":"venue"
},
  "geometry": {"coordinates":[4.85933,52.35051],"type":"Point"}
}