{
  "type": "Feature",
  "properties": {
    "addr:full":"Amsterdamsestrwg 9 Naarden North Holland 1411 AW",
    "addr:housenumber":"9",
    "addr:postcode":"1411 aw",
    "addr:street":"Amsterdamsestrwg",
    "iso:country":"NL",
    "sg:address":"Amsterdamsestrwg 9",
    "sg:city":"Naarden",
    "sg:orig_category":"Optiek - Fabrieken En Groothandel",
    "sg:phone":"+31 35 697 0866",
    "sg:postcode":"1411 AW",
    "sg:province":"North Holland",
    "wof:name":"Go Frames Bv",
    "wof:placetype":"venue"
},
  "geometry": {"coordinates":[5.15310812,52.3003807068],"type":"Point"}
}