{
  "type": "Feature",
  "properties": {
    "iso:country":"NL",
    "sg:address":"Radboud 5",
    "sg:city":"Grootebroek",
    "sg:orig_category":"Schilders",
    "sg:phone":"+31 228 516 431",
    "sg:postcode":"1613 LJ",
    "sg:province":"Noord-Holland",
    "wof:name":"Botman, Theo",
    "wof:placetype":"venue"
},
  "geometry": {"coordinates":[5.224976,52.698692],"type":"Point"}
}