{
  "type": "Feature",
  "properties": {
    "iso:country":"NL",
    "sg:address":"Hoofdweg 669",
    "sg:city":"Hoofddorp",
    "sg:orig_category":"Paramedische Behandelingen",
    "sg:phone":"+31 23 565 1931",
    "sg:postcode":"2131 BB",
    "sg:province":"Noord-Holland",
    "wof:name":"Podo Centrum Haarlemmermeer",
    "wof:placetype":"venue"
},
  "geometry": {"coordinates":[4.69216,52.305511],"type":"Point"}
}