{
  "type": "Feature",
  "properties": {
    "iso:country":"NL",
    "sg:address":"Nonnenstr 28",
    "sg:city":"Zaltbommel",
    "sg:orig_category":"Plafonds",
    "sg:phone":"+31 418 513 266",
    "sg:postcode":"5301 BJ",
    "sg:province":"Gelderland",
    "wof:name":"Atc",
    "wof:placetype":"venue"
},
  "geometry": {"coordinates":[5.248639,51.811443],"type":"Point"}
}