{
  "type": "Feature",
  "properties": {
    "iso:country":"NL",
    "sg:address":"Zuidwind 27",
    "sg:city":"'S Gravenzande",
    "sg:orig_category":"Meubelzaken, Woning- And Keukeninrichting",
    "sg:phone":"+31 174 623 958",
    "sg:postcode":"2691 RV",
    "sg:province":"Zuid-Holland",
    "wof:name":"Natuurlijk Wonen",
    "wof:placetype":"venue"
},
  "geometry": {"coordinates":[4.161627,51.999817],"type":"Point"}
}