{
  "type": "Feature",
  "properties": {
    "iso:country":"NL",
    "sg:address":"H Hoekstr 98",
    "sg:city":"Wateringen",
    "sg:orig_category":"Duiven En Duivensport - Artikelen",
    "sg:phone":"+31 174 294 019",
    "sg:postcode":"2291 SR",
    "sg:province":"Zuid-Holland",
    "wof:name":"Postduivenhoudersver Wateringen",
    "wof:placetype":"venue"
},
  "geometry": {"coordinates":[4.2735,52.023331],"type":"Point"}
}