{
  "type": "Feature",
  "properties": {
    "iso:country":"NL",
    "sg:address":"Schutsluis 6",
    "sg:city":"Vroomshoop",
    "sg:orig_category":"Verhuizingen",
    "sg:phone":"+31 546 642 734",
    "sg:postcode":"7681 KG",
    "sg:province":"NL.08",
    "wof:name":"Jan Hofman",
    "wof:placetype":"venue"
},
  "geometry": {"coordinates":[6.566861,52.449051],"type":"Point"}
}