{
  "type": "Feature",
  "properties": {
    "addr:full":"Leenderwg 194 Eindhoven Noord-Brabant 5644 AB",
    "addr:housenumber":"194",
    "addr:postcode":"5644 ab",
    "iso:country":"NL",
    "sg:address":"Leenderwg 194",
    "sg:city":"Eindhoven",
    "sg:orig_category":"Fotopersbureaus",
    "sg:phone":"+31 40 212 1584",
    "sg:postcode":"5644 AB",
    "sg:province":"Noord-Brabant",
    "wof:name":"Claessens, John",
    "wof:placetype":"venue"
},
  "geometry": {"coordinates":[5.494141,51.422146],"type":"Point"}
}