{
  "type": "Feature",
  "properties": {
    "addr:full":"Overmazepad 1 Weert Limburg 6004 VH",
    "addr:housenumber":"1",
    "addr:postcode":"6004 vh",
    "addr:street":"Overmazepad",
    "iso:country":"NL",
    "sg:address":"Overmazepad 1",
    "sg:city":"Weert",
    "sg:classifiers":[
        {
            "category":"Education",
            "subcategory":"Preschool",
            "type":"Public Place"
        }
    ],
    "sg:phone":"+31 495 452 088",
    "sg:postcode":"6004 VH",
    "sg:province":"Limburg",
    "sg:tags":[
        "kleuteronderwijs",
        "basis-"
    ],
    "wof:name":"Basisschool John F. Kennedy",
    "wof:placetype":"venue"
},
  "geometry": {"coordinates":[5.724811,51.25351],"type":"Point"}
}