{
  "type": "Feature",
  "properties": {
    "addr:full":"Langestr 26 Amersfoort Utrecht 3811 AH",
    "addr:housenumber":"26",
    "addr:postcode":"3811 ah",
    "addr:street":"Langestr",
    "iso:country":"NL",
    "sg:address":"Langestr 26",
    "sg:city":"Amersfoort",
    "sg:orig_category":"Schoenen",
    "sg:phone":"+31 33 461 1178",
    "sg:postcode":"3811 AH",
    "sg:province":"Utrecht",
    "wof:name":"Invito",
    "wof:placetype":"venue"
},
  "geometry": {"coordinates":[5.386085,52.152325],"type":"Point"}
}