{
  "type": "Feature",
  "properties": {
    "addr:full":"Juffersland 108 Leersum Utrecht 3956 TW",
    "addr:housenumber":"108",
    "addr:postcode":"3956 tw",
    "addr:street":"Juffersland",
    "iso:country":"NL",
    "sg:address":"Juffersland 108",
    "sg:city":"Leersum",
    "sg:orig_category":"Woninginrichting",
    "sg:phone":"+31 343 452 217",
    "sg:postcode":"3956 TW",
    "sg:province":"Utrecht",
    "wof:name":"Broek Vof, B Van Den",
    "wof:placetype":"venue"
},
  "geometry": {"coordinates":[5.4188570976,52.0123825073],"type":"Point"}
}