{
  "type": "Feature",
  "properties": {
    "addr:full":"Industriewg 9A Oudenbosch Noord-Brabant 4731 SB",
    "addr:housenumber":"9a",
    "addr:postcode":"4731 sb",
    "addr:street":"Industriewg",
    "iso:country":"NL",
    "sg:address":"Industriewg 9A",
    "sg:city":"Oudenbosch",
    "sg:classifiers":[
        {
            "category":"Wholesale",
            "subcategory":"Meat",
            "type":"Manufacturing & Wholesale Goods"
        }
    ],
    "sg:phone":"+31 165 320 104",
    "sg:postcode":"4731 SB",
    "sg:province":"Noord-Brabant",
    "sg:tags":[
        "regeltechniek",
        "en",
        "meet-"
    ],
    "sg:website":"http://www.randridge.nl",
    "wof:name":"Randridge Services Bv",
    "wof:placetype":"venue"
},
  "geometry": {"coordinates":[4.52324,51.582855],"type":"Point"}
}