{
  "type": "Feature",
  "properties": {
    "addr:full":"Oranjeplein 12 Loon Op Zand Noord-Brabant 5175 BE",
    "addr:housenumber":"12",
    "addr:postcode":"5175",
    "addr:street":"Oranjeplein",
    "iso:country":"NL",
    "sg:address":"Oranjeplein 12",
    "sg:city":"Loon Op Zand",
    "sg:orig_category":"Banken And Kredietinstellingen",
    "sg:phone":"+31 416 363 800",
    "sg:postcode":"5175 BE",
    "sg:province":"Noord-Brabant",
    "wof:name":"Postkantoor",
    "wof:placetype":"venue"
},
  "geometry": {"coordinates":[5.073982,51.627075],"type":"Point"}
}