{
  "type": "Feature",
  "properties": {
    "addr:full":"Uiterdijk 1 Geldermalsen Gelderland 4191 VJ",
    "addr:housenumber":"1",
    "addr:postcode":"4191 vj",
    "addr:street":"Uiterdijk;Gelderland",
    "iso:country":"NL",
    "sg:address":"Uiterdijk 1",
    "sg:city":"Geldermalsen",
    "sg:orig_category":"Hypotheken And Hypotheekbanken",
    "sg:phone":"+31 345 575 747",
    "sg:postcode":"4191 VJ",
    "sg:province":"Gelderland",
    "wof:name":"Haafs En Partners Adviseurs",
    "wof:placetype":"venue"
},
  "geometry": {"coordinates":[5.305524,51.890316],"type":"Point"}
}