{
  "type": "Feature",
  "properties": {
    "addr:full":"Eurowerft 20A Denekamp Overijssel 7591 DG",
    "addr:housenumber":"20a",
    "addr:postcode":"7591 dg",
    "addr:street":"Eurowerft",
    "iso:country":"NL",
    "sg:address":"Eurowerft 20A",
    "sg:city":"Denekamp",
    "sg:orig_category":"Zuivelproducten",
    "sg:phone":"+31 541 353 510",
    "sg:postcode":"7591 DG",
    "sg:province":"Overijssel",
    "wof:name":"Het Kaashal Boertje",
    "wof:placetype":"venue"
},
  "geometry": {"coordinates":[7.006218,52.375263],"type":"Point"}
}