{
  "type": "Feature",
  "properties": {
    "addr:full":"Rivieradreef 18 Haarlem Noord-Holland 2037 AG",
    "addr:housenumber":"18",
    "addr:postcode":"2037",
    "addr:street":"Rivieradreef",
    "iso:country":"NL",
    "sg:address":"Rivieradreef 18",
    "sg:city":"Haarlem",
    "sg:orig_category":"Drogisterijen",
    "sg:phone":"+31 23 535 4095",
    "sg:postcode":"2037 AG",
    "sg:province":"Noord-Holland",
    "wof:name":"De Tuin Van Haarlem",
    "wof:placetype":"venue"
},
  "geometry": {"coordinates":[4.654317,52.359615],"type":"Point"}
}