{
  "type": "Feature",
  "properties": {
    "addr:full":"P Calandwg 32 Arnhem Gelderland 6827 BK",
    "addr:housenumber":"32",
    "addr:postcode":"6827 bk",
    "addr:street":"P",
    "iso:country":"NL",
    "sg:address":"P Calandwg 32",
    "sg:city":"Arnhem",
    "sg:orig_category":"Milieu",
    "sg:phone":"+31 26 361 8691",
    "sg:postcode":"6827 BK",
    "sg:province":"Gelderland",
    "sg:website":"http://www.cso.nl",
    "wof:name":"Cso Adviesbureau",
    "wof:placetype":"venue"
},
  "geometry": {"coordinates":[5.946933,51.975224],"type":"Point"}
}