{
  "type": "Feature",
  "properties": {
    "addr:full":"Noorderveld 10 Ens Flevoland 8307 DS",
    "addr:housenumber":"10",
    "addr:postcode":"8307 ds",
    "addr:street":"Noorderveld;Flevoland",
    "iso:country":"NL",
    "sg:address":"Noorderveld 10",
    "sg:city":"Ens",
    "sg:orig_category":"Schilders",
    "sg:phone":"+31 527 253 737",
    "sg:postcode":"8307 DS",
    "sg:province":"Flevoland",
    "wof:name":"Altena, A Van",
    "wof:placetype":"venue"
},
  "geometry": {"coordinates":[5.819888,52.642265],"type":"Point"}
}