{
  "type": "Feature",
  "properties": {
    "addr:full":"De Bloemen 45 Meppel Provincie Drenthe 7943 LW",
    "addr:housenumber":"45",
    "addr:postcode":"7943 lw",
    "addr:street":"De Bloemen;Provincie Drenthe",
    "iso:country":"NL",
    "sg:address":"De Bloemen 45",
    "sg:city":"Meppel",
    "sg:orig_category":"Diverse Grafische Activiteiten",
    "sg:phone":"+31 522 258 787",
    "sg:postcode":"7943 LW",
    "sg:province":"Provincie Drenthe",
    "wof:name":"Kruithof Grafisch Ontwerper",
    "wof:placetype":"venue"
},
  "geometry": {"coordinates":[6.217665,52.700981],"type":"Point"}
}