{
  "type": "Feature",
  "properties": {
    "iso:country":"NL",
    "sg:address":"Nieuwstr 3",
    "sg:city":"Weesp",
    "sg:orig_category":"Verenigingen En Stichtingen",
    "sg:phone":"+31 294 452 211",
    "sg:postcode":"1381 BB",
    "sg:province":"Noord-Holland",
    "wof:name":"Ojec",
    "wof:placetype":"venue"
},
  "geometry": {"coordinates":[5.041506,52.308147],"type":"Point"}
}