{
  "type": "Feature",
  "properties": {
    "addr:full":"Bellamypark 44 Vlissingen Zeeland 4381 CK",
    "addr:housenumber":"44",
    "addr:postcode":"4381 ck",
    "addr:street":"Bellamypark",
    "iso:country":"NL",
    "sg:address":"Bellamypark 44",
    "sg:city":"Vlissingen",
    "sg:orig_category":"Visspeciaalzaken",
    "sg:phone":"+31 118 412 224",
    "sg:postcode":"4381 CK",
    "sg:province":"Zeeland",
    "wof:name":"Vishandel Janssen En Zoon",
    "wof:placetype":"venue"
},
  "geometry": {"coordinates":[3.573653,51.442238],"type":"Point"}
}