{
  "type": "Feature",
  "properties": {
    "addr:full":"De Kwakel 2 Klazienaveen Drenthe 7891 XD",
    "addr:housenumber":"2",
    "addr:postcode":"7891 xd",
    "addr:street":"De Kwakel",
    "iso:country":"NL",
    "sg:address":"De Kwakel 2",
    "sg:city":"Klazienaveen",
    "sg:orig_category":"Bloemen En Planten - Groothandel",
    "sg:phone":"+31 591 349 730",
    "sg:postcode":"7891 XD",
    "sg:province":"Drenthe",
    "wof:name":"Kwakel Bv, De",
    "wof:placetype":"venue"
},
  "geometry": {"coordinates":[7.019067,52.745548],"type":"Point"}
}