{
  "type": "Feature",
  "properties": {
    "addr:full":"Havenwg 9 Waalwyk North Brabant 5145 NJ",
    "addr:housenumber":"9",
    "addr:postcode":"5145 nj",
    "addr:street":"Havenwg",
    "iso:country":"NL",
    "sg:address":"Havenwg 9",
    "sg:city":"Waalwyk",
    "sg:orig_category":"Jachthavens - Jachtwerven",
    "sg:phone":"+31 416 335 635",
    "sg:postcode":"5145 NJ",
    "sg:province":"North Brabant",
    "wof:name":"Verhoeven Vof",
    "wof:placetype":"venue"
},
  "geometry": {"coordinates":[5.0695,51.706451],"type":"Point"}
}