{
  "type": "Feature",
  "properties": {
    "addr:full":"Castricumhoeve 36 Vlaardingen Zuid-Holland 3137 RN",
    "addr:housenumber":"36",
    "addr:postcode":"3137 rn",
    "addr:street":"Castricumhoeve",
    "iso:country":"NL",
    "sg:address":"Castricumhoeve 36",
    "sg:city":"Vlaardingen",
    "sg:orig_category":"Baggerwerken",
    "sg:phone":"+31 10 474 2796",
    "sg:postcode":"3137 RN",
    "sg:province":"Zuid-Holland",
    "wof:name":"Cta",
    "wof:placetype":"venue"
},
  "geometry": {"coordinates":[4.352154,51.939686],"type":"Point"}
}