{
  "type": "Feature",
  "properties": {
    "addr:full":"Zandsteen 42 Hoofddorp North Holland 2132 MR",
    "addr:housenumber":"42",
    "addr:postcode":"2132 mr",
    "addr:street":"Zandsteen",
    "iso:country":"NL",
    "sg:address":"Zandsteen 42",
    "sg:city":"Hoofddorp",
    "sg:orig_category":"Luchtvrachtexpediteurs",
    "sg:phone":"+31 20 316 0316",
    "sg:postcode":"2132 MR",
    "sg:province":"North Holland",
    "wof:name":"Traffic",
    "wof:placetype":"venue"
},
  "geometry": {"coordinates":[4.717902,52.293812],"type":"Point"}
}