{
  "type": "Feature",
  "properties": {
    "addr:full":"Queridoln 16 Groningen Groningen 9721 SX",
    "addr:housenumber":"16",
    "addr:postcode":"9721 sx",
    "addr:street":"Queridoln",
    "iso:country":"NL",
    "sg:address":"Queridoln 16",
    "sg:city":"Groningen",
    "sg:orig_category":"Horloges En Klokken - Reparatie En Onderhoud",
    "sg:phone":"+31 50 525 5357",
    "sg:postcode":"9721 SX",
    "sg:province":"Groningen",
    "wof:name":"Boer, A J De",
    "wof:placetype":"venue"
},
  "geometry": {"coordinates":[6.57473,53.194111],"type":"Point"}
}