{
  "type": "Feature",
  "properties": {
    "addr:full":"Ronerbrink 79 Emmen Drenthe 7812 LV",
    "addr:housenumber":"79",
    "addr:postcode":"7812",
    "addr:street":"Ronerbrink",
    "iso:country":"NL",
    "sg:address":"Ronerbrink 79",
    "sg:city":"Emmen",
    "sg:orig_category":"Hoger Onderwijs",
    "sg:phone":"+31 591 640 067",
    "sg:postcode":"7812 LV",
    "sg:province":"Drenthe",
    "wof:name":"Ensaid",
    "wof:placetype":"venue"
},
  "geometry": {"coordinates":[6.888688,52.770275],"type":"Point"}
}