{
  "type": "Feature",
  "properties": {
    "addr:full":"Lg Naarderwg 40 Hilversum Noord-Holland 1211 AC",
    "addr:housenumber":"40",
    "addr:postcode":"1211 ac",
    "addr:street":"Lg",
    "iso:country":"NL",
    "sg:address":"Lg Naarderwg 40",
    "sg:city":"Hilversum",
    "sg:orig_category":"Oldtimers",
    "sg:phone":"+31 35 642 0366",
    "sg:postcode":"1211 AC",
    "sg:province":"Noord-Holland",
    "sg:website":"http://www.superleggera.nl",
    "wof:name":"Superleggera",
    "wof:placetype":"venue"
},
  "geometry": {"coordinates":[5.176396,52.231823],"type":"Point"}
}