{
  "type": "Feature",
  "properties": {
    "addr:full":"Prinsessekd 14 Haarlem Noord-Holland 2012 MA",
    "addr:housenumber":"14",
    "addr:postcode":"2012 ma",
    "addr:street":"Prinsessekd",
    "iso:country":"NL",
    "sg:address":"Prinsessekd 14",
    "sg:city":"Haarlem",
    "sg:orig_category":"Organisatiebureaus",
    "sg:phone":"+31 23 531 8669",
    "sg:postcode":"2012 MA",
    "sg:province":"Noord-Holland",
    "sg:website":"http://www.rijswijk-en-partners.nl",
    "wof:name":"Rijswijk & Partners",
    "wof:placetype":"venue"
},
  "geometry": {"coordinates":[4.6180858612,52.3701095581],"type":"Point"}
}