{
  "type": "Feature",
  "properties": {
    "iso:country":"NL",
    "sg:address":"Nieuwe Stg 14",
    "sg:city":"Leersum",
    "sg:orig_category":"Beveiliging",
    "sg:phone":"+31 343 456 605",
    "sg:postcode":"3956 RD",
    "sg:province":"Utrecht",
    "sg:website":"http://www.dodehoekscamera.com",
    "wof:name":"T & A Bv",
    "wof:placetype":"venue"
},
  "geometry": {"coordinates":[5.42762,52.006401],"type":"Point"}
}