{
  "type": "Feature",
  "properties": {
    "addr:full":"Postbus 2431 Eindhoven Zuid-Holland 5600 CK",
    "addr:housenumber":"2431",
    "addr:postcode":"5600 ck",
    "addr:street":"Postbus",
    "iso:country":"NL",
    "sg:address":"Postbus 2431",
    "sg:city":"Eindhoven",
    "sg:orig_category":"Geluidsopnamestudio'S",
    "sg:phone":"+31 40 251 2532",
    "sg:postcode":"5600 CK",
    "sg:province":"Zuid-Holland",
    "sg:website":"http://www.bambamstudio.in.nl",
    "wof:name":"Bambam Studio",
    "wof:placetype":"venue"
},
  "geometry": {"coordinates":[5.48411,51.434471],"type":"Point"}
}