{
  "type": "Feature",
  "properties": {
    "addr:full":"Meerssenerweg 95 Maastricht Limburg 6222 AJ",
    "addr:housenumber":"95",
    "addr:postcode":"6222 aj",
    "addr:street":"Meerssenerweg",
    "iso:country":"NL",
    "sg:address":"Meerssenerweg 95",
    "sg:city":"Maastricht",
    "sg:classifiers":[
        {
            "category":"Communications",
            "subcategory":"Television Station",
            "type":"Services"
        }
    ],
    "sg:phone":"+31 43 362 3002",
    "sg:postcode":"6222 AJ",
    "sg:province":"Limburg",
    "sg:tags":[
        "video",
        "audio",
        "verhuur"
    ],
    "wof:name":"Video 2000",
    "wof:placetype":"venue"
},
  "geometry": {"coordinates":[5.710348,50.860226],"type":"Point"}
}