{
  "type": "Feature",
  "properties": {
    "addr:full":"Achterdijk 14 Helmond North Brabant 5705 CB",
    "addr:housenumber":"14",
    "addr:postcode":"5705 cb",
    "addr:street":"Achterdijk",
    "iso:country":"NL",
    "sg:address":"Achterdijk 14",
    "sg:city":"Helmond",
    "sg:orig_category":"Papier- And Kartonverpakkingen Fab",
    "sg:phone":"+31 492 523 376",
    "sg:postcode":"5705 CB",
    "sg:province":"North Brabant",
    "wof:name":"Snijders Industriele Verpakkingen Bv",
    "wof:placetype":"venue"
},
  "geometry": {"coordinates":[5.658284,51.482239],"type":"Point"}
}