{
  "type": "Feature",
  "properties": {
    "addr:full":"Hadrianussingel 32 Beuningen Gld Gelderland 6642 AJ",
    "addr:housenumber":"32",
    "addr:postcode":"6642 aj",
    "addr:street":"Hadrianussingel",
    "iso:country":"NL",
    "sg:address":"Hadrianussingel 32",
    "sg:city":"Beuningen Gld",
    "sg:orig_category":"Meubelzaken, Woning- And Keukeninrichting",
    "sg:phone":"+31 24 677 8688",
    "sg:postcode":"6642 AJ",
    "sg:province":"Gelderland",
    "wof:name":"Dynasty-Art Bv",
    "wof:placetype":"venue"
},
  "geometry": {"coordinates":[5.75083,51.855141],"type":"Point"}
}