{
  "type": "Feature",
  "properties": {
    "addr:full":"De Kolk 27 Surhuisterveen Friesland 9231 CV",
    "addr:housenumber":"27",
    "addr:postcode":"9231 cv",
    "addr:street":"De Kolk",
    "iso:country":"NL",
    "sg:address":"De Kolk 27",
    "sg:city":"Surhuisterveen",
    "sg:orig_category":"Discountwinkels",
    "sg:phone":"+31 512 363 989",
    "sg:postcode":"9231 CV",
    "sg:province":"Friesland",
    "wof:name":"Bentex Textiel",
    "wof:placetype":"venue"
},
  "geometry": {"coordinates":[6.165997,53.182529],"type":"Point"}
}