{
  "type": "Feature",
  "properties": {
    "iso:country":"NL",
    "sg:address":"Stationswg 29A",
    "sg:city":"Ede Gld",
    "sg:orig_category":"Fotoreportages",
    "sg:phone":"+31 318 616 858",
    "sg:postcode":"6711 PJ",
    "sg:province":"Gelderland",
    "wof:name":"Heco",
    "wof:placetype":"venue"
},
  "geometry": {"coordinates":[5.668861,52.038292],"type":"Point"}
}