{
  "type": "Feature",
  "properties": {
    "iso:country":"NL",
    "sg:address":"Mariastraat 14",
    "sg:city":"Stramproy",
    "sg:orig_category":"Schilderwerk",
    "sg:phone":"+31 495 563 549",
    "sg:postcode":"6039 AX",
    "sg:province":"Limburg",
    "wof:name":"Schildersbedrijf Henk Verhees",
    "wof:placetype":"venue"
},
  "geometry": {"coordinates":[5.718453,51.195747],"type":"Point"}
}