{
  "type": "Feature",
  "properties": {
    "iso:country":"NL",
    "sg:address":"Gyroscoopweg 10",
    "sg:city":"Amsterdam",
    "sg:orig_category":"Goederenvervoer Over De Weg",
    "sg:phone":"+31 20 587 1111",
    "sg:postcode":"1042 AB",
    "sg:province":"North Holland",
    "wof:name":"Nederlandse Pakketdienst Bv",
    "wof:placetype":"venue"
},
  "geometry": {"coordinates":[4.840738,52.399124],"type":"Point"}
}