{
  "type": "Feature",
  "properties": {
    "addr:full":"Oostkd 27 Waarland Noord-Holland 1738 JZ",
    "addr:housenumber":"27",
    "addr:postcode":"1738 jz",
    "addr:street":"Oostkd",
    "iso:country":"NL",
    "sg:address":"Oostkd 27",
    "sg:city":"Waarland",
    "sg:orig_category":"Administratie- En Boekhoudkantoren",
    "sg:phone":"+31 226 420 221",
    "sg:postcode":"1738 JZ",
    "sg:province":"Noord-Holland",
    "wof:name":"Afa",
    "wof:placetype":"venue"
},
  "geometry": {"coordinates":[4.827865,52.727863],"type":"Point"}
}