{
  "type": "Feature",
  "properties": {
    "addr:full":"Klenkerweg 7 Oosterhesselen Drenthe 7861 TG",
    "addr:housenumber":"7",
    "addr:postcode":"7861 tg",
    "addr:street":"Klenkerweg",
    "iso:country":"NL",
    "sg:address":"Klenkerweg 7",
    "sg:city":"Oosterhesselen",
    "sg:orig_category":"Wasserettes And Stomerijen",
    "sg:phone":"+31 524 581 424",
    "sg:postcode":"7861 TG",
    "sg:province":"Drenthe",
    "wof:name":"Eer Stomerij",
    "wof:placetype":"venue"
},
  "geometry": {"coordinates":[6.7162809372,52.7609062195],"type":"Point"}
}