{
  "type": "Feature",
  "properties": {
    "iso:country":"NL",
    "sg:address":"Eemslandweg 77",
    "sg:city":"Zwartemeer",
    "sg:orig_category":"Zuivelproducten",
    "sg:phone":"+31 591 316 397",
    "sg:postcode":"7894 AD",
    "sg:province":"Drenthe",
    "wof:name":"A Rink",
    "wof:placetype":"venue"
},
  "geometry": {"coordinates":[7.04422,52.72224],"type":"Point"}
}