{
  "type": "Feature",
  "properties": {
    "iso:country":"NL",
    "sg:address":"Westfriesedijk 3",
    "sg:city":"Aartswoud",
    "sg:orig_category":"Landbouwmachines Gh",
    "sg:phone":"+31 229 582 448",
    "sg:postcode":"1719 NK",
    "sg:province":"Noord-Holland",
    "wof:name":"Agra Service Harte",
    "wof:placetype":"venue"
},
  "geometry": {"coordinates":[4.947251,52.753651],"type":"Point"}
}