{
  "type": "Feature",
  "properties": {
    "addr:full":"Westfriesedijk 3 Aartswoud Noord-Holland 1719 NK",
    "addr:housenumber":"3",
    "addr:postcode":"1719 nk",
    "addr:street":"Westfriesedijk",
    "iso:country":"NL",
    "sg:address":"Westfriesedijk 3",
    "sg:city":"Aartswoud",
    "sg:orig_category":"Landbouwmachines Gh",
    "sg:phone":"+31 229 582 448",
    "sg:postcode":"1719 NK",
    "sg:province":"Noord-Holland",
    "wof:name":"Agra Service Harte",
    "wof:placetype":"venue"
},
  "geometry": {"coordinates":[4.947251,52.753651],"type":"Point"}
}