{
  "type": "Feature",
  "properties": {
    "addr:full":"Kwartelstraat 8 Silvolde Gelderland 7064 EN",
    "addr:housenumber":"8",
    "addr:postcode":"7064 en",
    "addr:street":"Kwartelstraat;Gelderland",
    "iso:country":"NL",
    "sg:address":"Kwartelstraat 8",
    "sg:city":"Silvolde",
    "sg:orig_category":"Antiekzaken",
    "sg:phone":"+31 315 323 818",
    "sg:postcode":"7064 EN",
    "sg:province":"Gelderland",
    "wof:name":"Antiekhandel Jos Wolters",
    "wof:placetype":"venue"
},
  "geometry": {"coordinates":[6.388739,51.90871],"type":"Point"}
}