{
  "type": "Feature",
  "properties": {
    "addr:full":"K Nieuwstr 15 Tilburg North Brabant 5014 HA",
    "addr:housenumber":"15",
    "addr:postcode":"5014 ha",
    "addr:street":"Nieuwstr",
    "iso:country":"NL",
    "sg:address":"K Nieuwstr 15",
    "sg:city":"Tilburg",
    "sg:orig_category":"Bloemen En Planten",
    "sg:phone":"+31 13 545 1215",
    "sg:postcode":"5014 HA",
    "sg:province":"North Brabant",
    "wof:name":"Merian",
    "wof:placetype":"venue"
},
  "geometry": {"coordinates":[5.092274,51.562412],"type":"Point"}
}