{
  "type": "Feature",
  "properties": {
    "iso:country":"NL",
    "sg:address":"Winkelc Woensel 38A",
    "sg:city":"Eindhoven",
    "sg:orig_category":"Huishoudelijke Apparaten En Artikelen",
    "sg:phone":"+31 40 292 6231",
    "sg:postcode":"5625 AC",
    "sg:province":"Noord-Brabant",
    "wof:name":"Blokker Bv",
    "wof:placetype":"venue"
},
  "geometry": {"coordinates":[5.475589,51.468773],"type":"Point"}
}