{
  "type": "Feature",
  "properties": {
    "addr:full":"Raadhuisstr 21 Roermond Limburg 6042 JK",
    "addr:housenumber":"21",
    "addr:postcode":"6042 jk",
    "addr:street":"Raadhuisstr",
    "iso:country":"NL",
    "sg:address":"Raadhuisstr 21",
    "sg:city":"Roermond",
    "sg:orig_category":"Artsen - Huisartsen",
    "sg:phone":"+31 475 329 455",
    "sg:postcode":"6042 JK",
    "sg:province":"Limburg",
    "wof:name":"Huisartsen Praktijk Maasniel",
    "wof:placetype":"venue"
},
  "geometry": {"coordinates":[6.012962,51.198738],"type":"Point"}
}