{
  "type": "Feature",
  "properties": {
    "addr:full":"E 72 Zuidlaren Drenthe 9471 KE",
    "addr:housenumber":"72",
    "addr:postcode":"9471 ke",
    "addr:street":"E",
    "iso:country":"NL",
    "sg:address":"E 72",
    "sg:city":"Zuidlaren",
    "sg:orig_category":"Ziekenhuizen, Sanatoria, Verpleeghuizen",
    "sg:phone":"+31 50 409 7777",
    "sg:postcode":"9471 KE",
    "sg:province":"Drenthe",
    "wof:name":"Enk, De",
    "wof:placetype":"venue"
},
  "geometry": {"coordinates":[6.66969,53.087807],"type":"Point"}
}