{
  "type": "Feature",
  "properties": {
    "addr:full":"Fort Kijk In De Potstr 27 Nijmegen Gelderland 6521 BT",
    "addr:housenumber":"27",
    "addr:postcode":"6521 bt",
    "addr:street":"Fort Kijk In De Potstr;Gelderland",
    "iso:country":"NL",
    "sg:address":"Fort Kijk In De Potstr 27",
    "sg:city":"Nijmegen",
    "sg:orig_category":"Artiesten",
    "sg:phone":"+31 24 360 5458",
    "sg:postcode":"6521 BT",
    "sg:province":"Gelderland",
    "wof:name":"Inge Hoetjes",
    "wof:placetype":"venue"
},
  "geometry": {"coordinates":[5.8701429367,51.8384017944],"type":"Point"}
}