{
  "type": "Feature",
  "properties": {
    "iso:country":"NL",
    "sg:address":"Lupine 44",
    "sg:city":"Rijnsburg",
    "sg:orig_category":"Fruit And Groenten Gh",
    "sg:phone":"+31 71 402 0323",
    "sg:postcode":"2231 PG",
    "sg:province":"Zuid-Holland",
    "wof:name":"J. Van Den Eijkel",
    "wof:placetype":"venue"
},
  "geometry": {"coordinates":[4.433345,52.196156],"type":"Point"}
}