{
  "type": "Feature",
  "properties": {
    "addr:full":"Palmstr 34 Amsterdam North Holland 1015 HS",
    "addr:housenumber":"34",
    "addr:postcode":"1015 hs",
    "addr:street":"Palmstr",
    "iso:country":"NL",
    "sg:address":"Palmstr 34",
    "sg:city":"Amsterdam",
    "sg:orig_category":"Sportverenigingen En Ontspannings- Verenigingen",
    "sg:phone":"+31 6 53315807",
    "sg:postcode":"1015 HS",
    "sg:province":"North Holland",
    "wof:name":"Heest Judover, Van",
    "wof:placetype":"venue"
},
  "geometry": {"coordinates":[4.884384,52.381886],"type":"Point"}
}