{
  "type": "Feature",
  "properties": {
    "addr:full":"Curacaostraat 50 Amsterdam Noord-Holland 1058 BX",
    "addr:housenumber":"50",
    "addr:postcode":"1058 bx",
    "addr:street":"Curacaostraat",
    "iso:country":"NL",
    "sg:address":"Curacaostraat 50",
    "sg:city":"Amsterdam",
    "sg:orig_category":"Artsen And Specialisten",
    "sg:phone":"+31 20 683 8838",
    "sg:postcode":"1058 BX",
    "sg:province":"Noord-Holland",
    "wof:name":"Friends Unlimited",
    "wof:placetype":"venue"
},
  "geometry": {"coordinates":[4.852153,52.360283],"type":"Point"}
}