{
  "type": "Feature",
  "properties": {
    "addr:full":"W Pijperln 28 Rotterdam South Holland 3055 WN",
    "addr:housenumber":"28",
    "addr:postcode":"3055 wn",
    "addr:street":"W",
    "iso:country":"NL",
    "sg:address":"W Pijperln 28",
    "sg:city":"Rotterdam",
    "sg:orig_category":"Verzekeringen - Verzekeringskantoren",
    "sg:phone":"+31 10 422 9355",
    "sg:postcode":"3055 WN",
    "sg:province":"South Holland",
    "wof:name":"Brummelen Jr, D J Van",
    "wof:placetype":"venue"
},
  "geometry": {"coordinates":[4.50689,51.961319],"type":"Point"}
}