{
  "type": "Feature",
  "properties": {
    "addr:full":"Nelissenstraat 59 Beltrum Gelderland 7156 MB",
    "addr:housenumber":"59",
    "addr:postcode":"7156 mb",
    "addr:street":"Nelissenstraat;Gelderland",
    "iso:country":"NL",
    "sg:address":"Nelissenstraat 59",
    "sg:city":"Beltrum",
    "sg:orig_category":"Discountwinkels",
    "sg:phone":"+31 544 481 300",
    "sg:postcode":"7156 MB",
    "sg:province":"Gelderland",
    "wof:name":"Amerongen-Grave",
    "wof:placetype":"venue"
},
  "geometry": {"coordinates":[6.565482,52.064972],"type":"Point"}
}