{
  "type": "Feature",
  "properties": {
    "addr:full":"Geert Teisplein 3 Stadskanaal Groningen 9501 VL",
    "addr:housenumber":"3",
    "addr:postcode":"9501 vl",
    "addr:street":"Geert Teisplein",
    "iso:country":"NL",
    "sg:address":"Geert Teisplein 3",
    "sg:city":"Stadskanaal",
    "sg:orig_category":"Bibliotheken And Openbare Archieven",
    "sg:phone":"+31 599 614 874",
    "sg:postcode":"9501 VL",
    "sg:province":"Groningen",
    "wof:name":"Openbare Bibliotheek",
    "wof:placetype":"venue"
},
  "geometry": {"coordinates":[6.931756,53.002075],"type":"Point"}
}