{
  "type": "Feature",
  "properties": {
    "addr:full":"Schinvelderstraat 19 Brunssum Limburg 6441 TE",
    "addr:housenumber":"19",
    "addr:postcode":"6441 te",
    "addr:street":"Schinvelderstraat",
    "iso:country":"NL",
    "sg:address":"Schinvelderstraat 19",
    "sg:city":"Brunssum",
    "sg:orig_category":"Fitnesscentra",
    "sg:phone":"+31 45 525 1676",
    "sg:postcode":"6441 TE",
    "sg:province":"Limburg",
    "wof:name":"Sport- En Fittnesscentrum Leo'S Arena",
    "wof:placetype":"venue"
},
  "geometry": {"coordinates":[5.974166,50.955231],"type":"Point"}
}