{
  "type": "Feature",
  "properties": {
    "iso:country":"NL",
    "sg:address":"Utrechtsestr 38",
    "sg:city":"Amsterdam",
    "sg:classifiers":[
        {
            "category":"Shopping",
            "subcategory":"Adult",
            "type":"Retail Goods"
        }
    ],
    "sg:phone":"+31 20 623 9857",
    "sg:postcode":"1017 VP",
    "sg:province":"Noord-Holland",
    "sg:tags":[
        "lingerie",
        "en",
        "tricotage"
    ],
    "sg:website":"http://www.salondelingerie.nl",
    "wof:name":"Salon De Lingerie",
    "wof:placetype":"venue"
},
  "geometry": {"coordinates":[4.897873,52.364292],"type":"Point"}
}