{
  "type": "Feature",
  "properties": {
    "iso:country":"NL",
    "sg:address":"Lindenln 34",
    "sg:city":"Heemstede",
    "sg:orig_category":"Lasbedrijven",
    "sg:phone":"+31 6 51825081",
    "sg:postcode":"2101 XJ",
    "sg:province":"Noord-Holland",
    "wof:name":"Sligte, Te",
    "wof:placetype":"venue"
},
  "geometry": {"coordinates":[4.621248,52.345287],"type":"Point"}
}