{
  "type": "Feature",
  "properties": {
    "iso:country":"NL",
    "sg:address":"Hoofdstr 51",
    "sg:city":"Noordbroek",
    "sg:orig_category":"Montagebedrijven",
    "sg:phone":"+31 598 453 228",
    "sg:postcode":"9635 AT",
    "sg:province":"Groningen",
    "wof:name":"H&L",
    "wof:placetype":"venue"
},
  "geometry": {"coordinates":[6.873005,53.196003],"type":"Point"}
}