{
  "type": "Feature",
  "properties": {
    "addr:full":"Oude Verlaat 1 Blokzijl NL.08 8356 DJ",
    "addr:housenumber":"1;nl.08",
    "addr:postcode":"8356 dj",
    "addr:street":"Oude Verlaat",
    "iso:country":"NL",
    "sg:address":"Oude Verlaat 1",
    "sg:city":"Blokzijl",
    "sg:orig_category":"Cafetaria'S",
    "sg:phone":"+31 527 291 694",
    "sg:postcode":"8356 DJ",
    "sg:province":"NL.08",
    "wof:name":"Halte, De",
    "wof:placetype":"venue"
},
  "geometry": {"coordinates":[5.95992,52.727314],"type":"Point"}
}