{
  "type": "Feature",
  "properties": {
    "addr:full":"Bosland 40 Den Bommel South Holland 3258 AC",
    "addr:housenumber":"40",
    "addr:postcode":"3258 ac",
    "addr:street":"Bosland",
    "iso:country":"NL",
    "sg:address":"Bosland 40",
    "sg:city":"Den Bommel",
    "sg:orig_category":"Fruit And Groenten Gh",
    "sg:phone":"+31 187 611 395",
    "sg:postcode":"3258 AC",
    "sg:province":"South Holland",
    "wof:name":"Mast Landbouwprodukten Bv",
    "wof:placetype":"venue"
},
  "geometry": {"coordinates":[4.2813,51.71442],"type":"Point"}
}