{
  "type": "Feature",
  "properties": {
    "addr:full":"Oosterstraat 107 Breda North Brabant 4812 VB",
    "addr:housenumber":"107",
    "addr:postcode":"4812 vb",
    "addr:street":"Oosterstraat",
    "iso:country":"NL",
    "sg:address":"Oosterstraat 107",
    "sg:city":"Breda",
    "sg:orig_category":"Verlichting And Huishoudartikelen",
    "sg:phone":"+31 76 522 2421",
    "sg:postcode":"4812 VB",
    "sg:province":"North Brabant",
    "wof:name":"Oomens Woninginrichting Breda Bv",
    "wof:placetype":"venue"
},
  "geometry": {"coordinates":[4.754151,51.579426],"type":"Point"}
}