{
  "type": "Feature",
  "properties": {
    "addr:full":"Kennemerland 48 Purmerend Noord-Holland 1447 BJ",
    "addr:housenumber":"48",
    "addr:postcode":"1447 bj",
    "addr:street":"Kennemerland",
    "iso:country":"NL",
    "sg:address":"Kennemerland 48",
    "sg:city":"Purmerend",
    "sg:orig_category":"Fotostudio'S And Fotografen",
    "sg:phone":"+31 299 645 194",
    "sg:postcode":"1447 BJ",
    "sg:province":"Noord-Holland",
    "wof:name":"Tom Blom Fotografie",
    "wof:placetype":"venue"
},
  "geometry": {"coordinates":[4.967898,52.498802],"type":"Point"}
}