{
  "type": "Feature",
  "properties": {
    "addr:full":"Amstelplein 31 Uithoorn Noord-Holland 1421 SB",
    "addr:housenumber":"31",
    "addr:postcode":"1421 sb",
    "addr:street":"Amstelplein",
    "iso:country":"NL",
    "sg:address":"Amstelplein 31",
    "sg:city":"Uithoorn",
    "sg:orig_category":"Schoenen",
    "sg:phone":"+31 297 561 202",
    "sg:postcode":"1421 SB",
    "sg:province":"Noord-Holland",
    "wof:name":"Hopman Bv",
    "wof:placetype":"venue"
},
  "geometry": {"coordinates":[4.828053,52.232697],"type":"Point"}
}