{
  "type": "Feature",
  "properties": {
    "addr:full":"Vd Burchstr 28 Hoofddorp North Holland 2132 RN",
    "addr:housenumber":"28",
    "addr:postcode":"2132 rn",
    "iso:country":"NL",
    "sg:address":"Vd Burchstr 28",
    "sg:city":"Hoofddorp",
    "sg:orig_category":"Organisatiebureaus",
    "sg:phone":"+31 23 562 8370",
    "sg:postcode":"2132 RN",
    "sg:province":"North Holland",
    "sg:website":"http://www.zwerfsport.nl",
    "wof:name":"Zwerfsport Outdoor",
    "wof:placetype":"venue"
},
  "geometry": {"coordinates":[4.6929597855,52.305393219],"type":"Point"}
}