{
  "type": "Feature",
  "properties": {
    "iso:country":"NL",
    "sg:address":"Klomperweg 101",
    "sg:city":"Lunteren",
    "sg:orig_category":"Levende Dieren Gh",
    "sg:phone":"+31 318 484 206",
    "sg:postcode":"6741 PE",
    "sg:province":"Gelderland",
    "wof:name":"Varkenshandel J. Zandsteeg",
    "wof:placetype":"venue"
},
  "geometry": {"coordinates":[5.609914,52.079037],"type":"Point"}
}