{
  "type": "Feature",
  "properties": {
    "addr:full":"Hoofdstraat 59 Velp Gld Gelderland 6881 TC",
    "addr:housenumber":"59",
    "addr:postcode":"6881 tc",
    "addr:street":"Hoofdstraat;Gld Gelderland",
    "iso:country":"NL",
    "sg:address":"Hoofdstraat 59",
    "sg:city":"Velp Gld",
    "sg:orig_category":"Herenmodezaken",
    "sg:phone":"+31 26 361 2529",
    "sg:postcode":"6881 TC",
    "sg:province":"Gelderland",
    "wof:name":"Firma Ge Jansen Herenmode",
    "wof:placetype":"venue"
},
  "geometry": {"coordinates":[5.972145,51.995773],"type":"Point"}
}