{
  "type": "Feature",
  "properties": {
    "addr:full":"Anna Paulownastraat 41 'S Gravenhage Zuid-Holland 2518 BB",
    "addr:housenumber":"41",
    "addr:postcode":"2518 bb",
    "addr:street":"Anna Paulownastraat;' S",
    "iso:country":"NL",
    "sg:address":"Anna Paulownastraat 41",
    "sg:city":"'S Gravenhage",
    "sg:orig_category":"Binnenhuisarchitecten",
    "sg:phone":"+31 70 365 8289",
    "sg:postcode":"2518 BB",
    "sg:province":"Zuid-Holland",
    "wof:name":"Eigen Stijl",
    "wof:placetype":"venue"
},
  "geometry": {"coordinates":[4.300414,52.084057],"type":"Point"}
}