{
  "type": "Feature",
  "properties": {
    "addr:full":"Wiebachstr 8 Kerkrade Limburg 6466 NG",
    "addr:housenumber":"8",
    "addr:postcode":"6466 ng",
    "addr:street":"Wiebachstr",
    "iso:country":"NL",
    "sg:address":"Wiebachstr 8",
    "sg:city":"Kerkrade",
    "sg:orig_category":"Kunststof Ramen",
    "sg:phone":"+31 45 546 5228",
    "sg:postcode":"6466 NG",
    "sg:province":"Limburg",
    "wof:name":"Vkt",
    "wof:placetype":"venue"
},
  "geometry": {"coordinates":[6.03203,50.86475],"type":"Point"}
}