{
  "type": "Feature",
  "properties": {
    "addr:full":"Vliet Zuid Zijde 46 Rijnsburg Zuid-Holland 2231 GJ",
    "addr:housenumber":"46",
    "addr:postcode":"2231 gj",
    "addr:street":"Vliet;Zijde",
    "iso:country":"NL",
    "sg:address":"Vliet Zuid Zijde 46",
    "sg:city":"Rijnsburg",
    "sg:orig_category":"Bloemen And Planten Gh",
    "sg:phone":"+31 71 402 1364",
    "sg:postcode":"2231 GJ",
    "sg:province":"Zuid-Holland",
    "wof:name":"G. Van Zuylen Jr Bv",
    "wof:placetype":"venue"
},
  "geometry": {"coordinates":[4.446681,52.190899],"type":"Point"}
}