{
  "type": "Feature",
  "properties": {
    "iso:country":"NL",
    "sg:address":"Molenakker 13",
    "sg:city":"Wyk By Duurstede",
    "sg:orig_category":"Kantoorbenodigdheden",
    "sg:phone":"+31 343 573 353",
    "sg:postcode":"3962 HH",
    "sg:province":"Utrecht",
    "wof:name":"Bkt",
    "wof:placetype":"venue"
},
  "geometry": {"coordinates":[5.3754000664,51.9853782654],"type":"Point"}
}