{
  "type": "Feature",
  "properties": {
    "addr:full":"Zuidlaarderweg 19 Tynaarlo Drenthe 9482 TV",
    "addr:housenumber":"19",
    "addr:postcode":"9482 tv",
    "addr:street":"Zuidlaarderweg",
    "iso:country":"NL",
    "sg:address":"Zuidlaarderweg 19",
    "sg:city":"Tynaarlo",
    "sg:orig_category":"Autokeuringen",
    "sg:phone":"+31 592 543 336",
    "sg:postcode":"9482 TV",
    "sg:province":"Drenthe",
    "wof:name":"Klein Auto'S",
    "wof:placetype":"venue"
},
  "geometry": {"coordinates":[6.627154,53.079712],"type":"Point"}
}