{
  "type": "Feature",
  "properties": {
    "addr:full":"Schutbocht 2 De Heen North Brabant 4655 AM",
    "addr:housenumber":"2",
    "addr:postcode":"4655",
    "addr:street":"Schutbocht",
    "iso:country":"NL",
    "sg:address":"Schutbocht 2",
    "sg:city":"De Heen",
    "sg:orig_category":"Kinderkleding",
    "sg:phone":"+31 167 562 533",
    "sg:postcode":"4655 AM",
    "sg:province":"North Brabant",
    "wof:name":"Funtex",
    "wof:placetype":"venue"
},
  "geometry": {"coordinates":[4.271071,51.608166],"type":"Point"}
}