{
  "type": "Feature",
  "properties": {
    "addr:full":"Brouwersstr 120 Haarlem Noord-Holland 2013 WR",
    "addr:housenumber":"120",
    "addr:postcode":"2013 wr",
    "iso:country":"NL",
    "sg:address":"Brouwersstr 120",
    "sg:city":"Haarlem",
    "sg:orig_category":"Organisatiebureaus",
    "sg:phone":"+31 23 534 3489",
    "sg:postcode":"2013 WR",
    "sg:province":"Noord-Holland",
    "wof:name":"Coach Pro",
    "wof:placetype":"venue"
},
  "geometry": {"coordinates":[4.6192989349,52.3800010681],"type":"Point"}
}