{
  "type": "Feature",
  "properties": {
    "addr:full":"Havendk 10F Oudenbosch Noord-Brabant 4731 KX",
    "addr:housenumber":"10f",
    "addr:postcode":"4731 kx",
    "iso:country":"NL",
    "sg:address":"Havendk 10F",
    "sg:city":"Oudenbosch",
    "sg:orig_category":"Meubelmakerijen",
    "sg:phone":"+31 165 310 596",
    "sg:postcode":"4731 KX",
    "sg:province":"Noord-Brabant",
    "wof:name":"Oosterom Meubel & Interieur",
    "wof:placetype":"venue"
},
  "geometry": {"coordinates":[4.522892,51.595547],"type":"Point"}
}