{
  "type": "Feature",
  "properties": {
    "addr:full":"Vordensewg 36 Warnsveld Gelderland 7231 PC",
    "addr:housenumber":"36",
    "addr:postcode":"7231 pc",
    "addr:street":"Vordensewg;Gelderland",
    "iso:country":"NL",
    "sg:address":"Vordensewg 36",
    "sg:city":"Warnsveld",
    "sg:orig_category":"Adviesbureaus",
    "sg:phone":"+31 575 552 533",
    "sg:postcode":"7231 PC",
    "sg:province":"Gelderland",
    "wof:name":"Sli Bv",
    "wof:placetype":"venue"
},
  "geometry": {"coordinates":[6.280327,52.124172],"type":"Point"}
}