{
  "type": "Feature",
  "properties": {
    "iso:country":"NL",
    "sg:address":"Boegspriet 20",
    "sg:city":"Amstelveen",
    "sg:orig_category":"Bedrijfsopleidingen",
    "sg:phone":"+31 20 453 8461",
    "sg:postcode":"1186 WX",
    "sg:province":"Noord-Holland",
    "wof:name":"Bureau Sociale Competentie",
    "wof:placetype":"venue"
},
  "geometry": {"coordinates":[4.862941,52.276573],"type":"Point"}
}