{
  "type": "Feature",
  "properties": {
    "addr:full":"Vijzelstraat 24 Arnhem Gelderland 6811 ET",
    "addr:housenumber":"24",
    "addr:postcode":"6811 et",
    "addr:street":"Vijzelstraat",
    "iso:country":"NL",
    "sg:address":"Vijzelstraat 24",
    "sg:city":"Arnhem",
    "sg:orig_category":"Juweliers",
    "sg:phone":"+31 26 443 9952",
    "sg:postcode":"6811 ET",
    "sg:province":"Gelderland",
    "wof:name":"Paul Van Zeeland Juweliers",
    "wof:placetype":"venue"
},
  "geometry": {"coordinates":[5.907071,51.981464],"type":"Point"}
}