{
  "type": "Feature",
  "properties": {
    "iso:country":"NL",
    "sg:address":"Stinswg 13",
    "sg:city":"Veenwouden",
    "sg:orig_category":"Banken",
    "sg:phone":"+31 511 472 682",
    "sg:postcode":"9269 TD",
    "sg:province":"Friesland",
    "sg:website":"http://www.rabobank.nl",
    "wof:name":"Rabobank",
    "wof:placetype":"venue"
},
  "geometry": {"coordinates":[5.987375,53.237],"type":"Point"}
}