{
  "type": "Feature",
  "properties": {
    "addr:full":"Vlinderveen 217 Wijkcentr Spykenisse Zuid-Holland 3205 EB",
    "addr:housenumber":"217;spykenisse",
    "addr:postcode":"3205 eb",
    "addr:street":"Vlinderveen",
    "iso:country":"NL",
    "sg:address":"Vlinderveen 217 Wijkcentr",
    "sg:city":"Spykenisse",
    "sg:orig_category":"Verenigingsgebouwen",
    "sg:phone":"+31 181 640 433",
    "sg:postcode":"3205 EB",
    "sg:province":"Zuid-Holland",
    "wof:name":"Rietlander",
    "wof:placetype":"venue"
},
  "geometry": {"coordinates":[4.34255,51.833431],"type":"Point"}
}