{
  "type": "Feature",
  "properties": {
    "addr:full":"Hasebroekstraat 33 Utrecht Utrecht 3532 GK",
    "addr:housenumber":"33",
    "addr:postcode":"3532 gk",
    "addr:street":"Hasebroekstraat",
    "iso:country":"NL",
    "sg:address":"Hasebroekstraat 33",
    "sg:city":"Utrecht",
    "sg:orig_category":"Autoverhuur",
    "sg:phone":"+31 30 296 1140",
    "sg:postcode":"3532 GK",
    "sg:province":"Utrecht",
    "wof:name":"Autoverhuurbedrijf Adrem",
    "wof:placetype":"venue"
},
  "geometry": {"coordinates":[5.096018,52.094822],"type":"Point"}
}