{
  "type": "Feature",
  "properties": {
    "addr:full":"Markt 2 Veere Zeeland 4351 AH",
    "addr:housenumber":"2",
    "addr:postcode":"4351 ah",
    "addr:street":"Markt",
    "iso:country":"NL",
    "sg:address":"Markt 2",
    "sg:city":"Veere",
    "sg:classifiers":[
        {
            "category":"Retail",
            "subcategory":"Photofinishing",
            "type":"Services"
        }
    ],
    "sg:phone":"+31 118 501 498",
    "sg:postcode":"4351 AH",
    "sg:province":"Zeeland",
    "sg:tags":[
        "foto",
        "film"
    ],
    "wof:name":"De Lichtflits",
    "wof:placetype":"venue"
},
  "geometry": {"coordinates":[3.667737,51.549294],"type":"Point"}
}