{
  "type": "Feature",
  "properties": {
    "iso:country":"NL",
    "sg:address":"Herikbeek 11",
    "sg:city":"Veldhoven",
    "sg:classifiers":[
        {
            "category":"Professional",
            "subcategory":"Accounting & Tax Preparation",
            "type":"Services"
        }
    ],
    "sg:phone":"+31 40 253 5245",
    "sg:postcode":"5501 CE",
    "sg:province":"North Brabant",
    "sg:tags":[
        "accountant"
    ],
    "wof:name":"J.J. Mos Registeraccountant",
    "wof:placetype":"venue"
},
  "geometry": {"coordinates":[5.402451,51.417439],"type":"Point"}
}