{
  "type": "Feature",
  "properties": {
    "addr:full":"Hoogenboomlaan 42 Renesse Zeeland 4325 DM",
    "addr:housenumber":"42",
    "addr:postcode":"4325 dm",
    "addr:street":"Hoogenboomlaan",
    "iso:country":"NL",
    "sg:address":"Hoogenboomlaan 42",
    "sg:city":"Renesse",
    "sg:orig_category":"Kampeerterreinen",
    "sg:phone":"+31 111 461 414",
    "sg:postcode":"4325 DM",
    "sg:province":"Zeeland",
    "wof:name":"Camping Julianahoeve",
    "wof:placetype":"venue"
},
  "geometry": {"coordinates":[3.7532629967,51.7303924561],"type":"Point"}
}