{
  "type": "Feature",
  "properties": {
    "addr:full":"Nieuwe Rijksweg 100 Lexmond Zuid-Holland 4128 BP",
    "addr:housenumber":"100",
    "addr:postcode":"4128 bp",
    "addr:street":"Nieuwe Rijksweg",
    "iso:country":"NL",
    "sg:address":"Nieuwe Rijksweg 100",
    "sg:city":"Lexmond",
    "sg:orig_category":"Fruitteelt",
    "sg:phone":"+31 347 341 515",
    "sg:postcode":"4128 BP",
    "sg:province":"Zuid-Holland",
    "wof:name":"B.W. Rietveld",
    "wof:placetype":"venue"
},
  "geometry": {"coordinates":[5.045532,51.965988],"type":"Point"}
}