{
  "type": "Feature",
  "properties": {
    "addr:full":"Ploegschaar 9 Wierden Overijssel 7641 HH",
    "addr:housenumber":"9",
    "addr:postcode":"7641 hh",
    "addr:street":"Ploegschaar",
    "iso:country":"NL",
    "sg:address":"Ploegschaar 9",
    "sg:city":"Wierden",
    "sg:orig_category":"Goederenvervoer Over De Weg",
    "sg:phone":"+31 546 571 432",
    "sg:postcode":"7641 HH",
    "sg:province":"Overijssel",
    "wof:name":"H. Borkent",
    "wof:placetype":"venue"
},
  "geometry": {"coordinates":[6.601256,52.366982],"type":"Point"}
}