{
  "type": "Feature",
  "properties": {
    "addr:full":"Hoogstraat 159 Vlaardingen Zuid-Holland 3131 BB",
    "addr:housenumber":"159",
    "addr:postcode":"3131 bb",
    "addr:street":"Hoogstraat",
    "iso:country":"NL",
    "sg:address":"Hoogstraat 159",
    "sg:city":"Vlaardingen",
    "sg:orig_category":"Bedrijfsinventaris Gh",
    "sg:phone":"+31 10 434 3181",
    "sg:postcode":"3131 BB",
    "sg:province":"Zuid-Holland",
    "wof:name":"Haar Import Vlaardingen",
    "wof:placetype":"venue"
},
  "geometry": {"coordinates":[4.343593,51.909885],"type":"Point"}
}