{
  "type": "Feature",
  "properties": {
    "iso:country":"NL",
    "sg:address":"Weststr 1A",
    "sg:city":"St Annaland",
    "sg:orig_category":"Onderhoudswerken",
    "sg:phone":"+31 166 653 971",
    "sg:postcode":"4697 GA",
    "sg:province":"Zeeland",
    "wof:name":"Easy Paint",
    "wof:placetype":"venue"
},
  "geometry": {"coordinates":[4.102611,51.601482],"type":"Point"}
}