{
  "type": "Feature",
  "properties": {
    "addr:full":"Z Meentstg 8B Rhenen Utrecht 3911 TD",
    "addr:housenumber":"8b",
    "addr:postcode":"3911 td",
    "iso:country":"NL",
    "sg:address":"Z Meentstg 8B",
    "sg:city":"Rhenen",
    "sg:orig_category":"Verhuur",
    "sg:phone":"+31 317 617 012",
    "sg:postcode":"3911 TD",
    "sg:province":"Utrecht",
    "wof:name":"Beek, W Van",
    "wof:placetype":"venue"
},
  "geometry": {"coordinates":[5.567005,51.957603],"type":"Point"}
}