{
  "type": "Feature",
  "properties": {
    "addr:full":"Luxemburgwg 1 Nieuwdorp Zld Zeeland 4455 TM",
    "addr:housenumber":"1",
    "addr:postcode":"4455 tm",
    "addr:street":"Luxemburgwg",
    "iso:country":"NL",
    "sg:address":"Luxemburgwg 1",
    "sg:city":"Nieuwdorp Zld",
    "sg:orig_category":"Petrochemische Industrie",
    "sg:phone":"+31 113 619 000",
    "sg:postcode":"4455 TM",
    "sg:province":"Zeeland",
    "wof:name":"Total Ned Nv",
    "wof:placetype":"venue"
},
  "geometry": {"coordinates":[3.726467,51.449722],"type":"Point"}
}