{
  "type": "Feature",
  "properties": {
    "addr:full":"Klaverhof 23 Kesteren Gelderland 4041 BC",
    "addr:housenumber":"23",
    "addr:postcode":"4041 bc",
    "addr:street":"Klaverhof;Gelderland",
    "iso:country":"NL",
    "sg:address":"Klaverhof 23",
    "sg:city":"Kesteren",
    "sg:orig_category":"Verenigingen En Stichtingen",
    "sg:phone":"+31 488 482 765",
    "sg:postcode":"4041 BC",
    "sg:province":"Gelderland",
    "sg:website":"http://www.harmonia-nl.org",
    "wof:name":"Harmonia Nederland",
    "wof:placetype":"venue"
},
  "geometry": {"coordinates":[5.569498,51.934486],"type":"Point"}
}