{
  "type": "Feature",
  "properties": {
    "addr:full":"Langstraat 6 Wijhe Overijssel 8131 BC",
    "addr:housenumber":"6",
    "addr:postcode":"8131 bc",
    "addr:street":"Langstraat",
    "iso:country":"NL",
    "sg:address":"Langstraat 6",
    "sg:city":"Wijhe",
    "sg:orig_category":"Bloemen And Planten",
    "sg:phone":"+31 570 521 225",
    "sg:postcode":"8131 BC",
    "sg:province":"Overijssel",
    "wof:name":"M.A. Veldhuis",
    "wof:placetype":"venue"
},
  "geometry": {"coordinates":[6.135076,52.389336],"type":"Point"}
}