{
  "type": "Feature",
  "properties": {
    "iso:country":"NL",
    "sg:address":"Operaplein 34",
    "sg:city":"Apeldoorn",
    "sg:orig_category":"Medische Apparatuur And Prothesen Fab",
    "sg:phone":"+31 55 366 2858",
    "sg:postcode":"7323 EL",
    "sg:province":"Gelderland",
    "wof:name":"Garant Optiek",
    "wof:placetype":"venue"
},
  "geometry": {"coordinates":[5.985523,52.229023],"type":"Point"}
}