{
  "type": "Feature",
  "properties": {
    "iso:country":"NL",
    "sg:address":"Hanzestraat 16",
    "sg:city":"Aardenburg",
    "sg:orig_category":"Makelaars In Onroerend Goed",
    "sg:phone":"+31 117 492 072",
    "sg:postcode":"4527 GG",
    "sg:province":"Zeeland",
    "wof:name":"C.G. De Jonge",
    "wof:placetype":"venue"
},
  "geometry": {"coordinates":[3.455433,51.270931],"type":"Point"}
}