{
  "type": "Feature",
  "properties": {
    "iso:country":"NL",
    "sg:address":"Pastoor Bloemenstraat 1",
    "sg:city":"Tubbergen",
    "sg:orig_category":"Sportcentra",
    "sg:phone":"+31 546 621 724",
    "sg:postcode":"7651 CD",
    "sg:province":"Overijssel",
    "wof:name":"Sporthal",
    "wof:placetype":"venue"
},
  "geometry": {"coordinates":[6.78431,52.405949],"type":"Point"}
}