{
  "type": "Feature",
  "properties": {
    "addr:full":"Gerestraat 1 Heesselt Gelderland 4063 CN",
    "addr:housenumber":"1",
    "addr:postcode":"4063 cn",
    "addr:street":"Gerestraat;Gelderland",
    "iso:country":"NL",
    "sg:address":"Gerestraat 1",
    "sg:city":"Heesselt",
    "sg:orig_category":"Bloemen And Planten",
    "sg:phone":"+31 344 651 233",
    "sg:postcode":"4063 CN",
    "sg:province":"Gelderland",
    "wof:name":"Fa.C.Visscher & Zoon",
    "wof:placetype":"venue"
},
  "geometry": {"coordinates":[5.357822,51.819553],"type":"Point"}
}