{
  "type": "Feature",
  "properties": {
    "addr:full":"Nw Ebbingestr 1-P Groningen Groningen 9712 NB",
    "addr:housenumber":"1-p",
    "addr:postcode":"9712 nb",
    "addr:street":"Ebbingestr",
    "iso:country":"NL",
    "sg:address":"Nw Ebbingestr 1-P",
    "sg:city":"Groningen",
    "sg:orig_category":"Bloemen En Planten",
    "sg:phone":"+31 50 313 3771",
    "sg:postcode":"9712 NB",
    "sg:province":"Groningen",
    "wof:name":"Bloemenpalet, 'T",
    "wof:placetype":"venue"
},
  "geometry": {"coordinates":[6.574715,53.217144],"type":"Point"}
}