{
  "type": "Feature",
  "properties": {
    "addr:full":"Quistplan 11 Zoetermeer Zuid-Holland 2728 DJ",
    "addr:housenumber":"11",
    "addr:postcode":"2728 dj",
    "addr:street":"Quistplan",
    "iso:country":"NL",
    "sg:address":"Quistplan 11",
    "sg:city":"Zoetermeer",
    "sg:orig_category":"Arbo- En Bedrijfsgezondheids- Diensten",
    "sg:phone":"+31 6 14361193",
    "sg:postcode":"2728 DJ",
    "sg:province":"Zuid-Holland",
    "sg:website":"http://www.arboadviesprimair.nl",
    "wof:name":"Primair",
    "wof:placetype":"venue"
},
  "geometry": {"coordinates":[4.519669,52.078045],"type":"Point"}
}