{
  "type": "Feature",
  "properties": {
    "addr:full":"Boslandwerf 19 Rotterdam Zuid-Holland 3063 PB",
    "addr:housenumber":"19",
    "addr:postcode":"3063 pb",
    "addr:street":"Boslandwerf",
    "iso:country":"NL",
    "sg:address":"Boslandwerf 19",
    "sg:city":"Rotterdam",
    "sg:orig_category":"Loodgieters",
    "sg:phone":"+31 10 414 9665",
    "sg:postcode":"3063 PB",
    "sg:province":"Zuid-Holland",
    "wof:name":"Garson, M J",
    "wof:placetype":"venue"
},
  "geometry": {"coordinates":[4.507105,51.919441],"type":"Point"}
}