{
  "type": "Feature",
  "properties": {
    "addr:full":"Julianalaan 4 Heeze Noord-Brabant 5591 GB",
    "addr:housenumber":"4",
    "addr:postcode":"5591 gb",
    "addr:street":"Julianalaan",
    "iso:country":"NL",
    "sg:address":"Julianalaan 4",
    "sg:city":"Heeze",
    "sg:orig_category":"Metaalbekleding And -Behandeling",
    "sg:phone":"+31 40 212 2238",
    "sg:postcode":"5591 GB",
    "sg:province":"Noord-Brabant",
    "wof:name":"Essit",
    "wof:placetype":"venue"
},
  "geometry": {"coordinates":[5.575075,51.382553],"type":"Point"}
}