{
  "type": "Feature",
  "properties": {
    "iso:country":"NL",
    "sg:address":"Waterhamweg 1",
    "sg:city":"Oldenzaal",
    "sg:orig_category":"Diverse Opleidingen And Onderwijs",
    "sg:phone":"+31 541 514 451",
    "sg:postcode":"7577 PZ",
    "sg:province":"Overijssel",
    "wof:name":"Antoinette Ruiter",
    "wof:placetype":"venue"
},
  "geometry": {"coordinates":[6.916798,52.320988],"type":"Point"}
}