{
  "type": "Feature",
  "properties": {
    "addr:full":"Produktiewg 12 Roden Drenthe 9301 ZS",
    "addr:housenumber":"12",
    "addr:postcode":"9301 zs",
    "addr:street":"Produktiewg",
    "iso:country":"NL",
    "sg:address":"Produktiewg 12",
    "sg:city":"Roden",
    "sg:classifiers":[
        {
            "category":"Retail",
            "subcategory":"Auto Repair",
            "type":"Services"
        }
    ],
    "sg:phone":"+31 50 501 8684",
    "sg:postcode":"9301 ZS",
    "sg:province":"Drenthe",
    "sg:tags":[
        "garage"
    ],
    "wof:name":"Hilberts Garage",
    "wof:placetype":"venue"
},
  "geometry": {"coordinates":[6.447988,53.147991],"type":"Point"}
}