{
  "type": "Feature",
  "properties": {
    "addr:full":"Molenakker 6 Vught North Brabant 5262 EV",
    "addr:housenumber":"6",
    "addr:postcode":"5262 ev",
    "addr:street":"Molenakker",
    "iso:country":"NL",
    "sg:address":"Molenakker 6",
    "sg:city":"Vught",
    "sg:orig_category":"Verenigingen En Stichtingen",
    "sg:phone":"+31 73 656 6706",
    "sg:postcode":"5262 EV",
    "sg:province":"North Brabant",
    "wof:name":"Ehbo",
    "wof:placetype":"venue"
},
  "geometry": {"coordinates":[5.297663,51.660519],"type":"Point"}
}