{
  "type": "Feature",
  "properties": {
    "addr:full":"Velserduinpln 2 Ymuiden North Holland 1971 BR",
    "addr:housenumber":"2",
    "addr:postcode":"1971 br",
    "addr:street":"Velserduinpln;North",
    "iso:country":"NL",
    "sg:address":"Velserduinpln 2",
    "sg:city":"Ymuiden",
    "sg:orig_category":"Poeliers",
    "sg:phone":"+31 255 511 684",
    "sg:postcode":"1971 BR",
    "sg:province":"North Holland",
    "wof:name":"Bart'S",
    "wof:placetype":"venue"
},
  "geometry": {"coordinates":[4.620201,52.460297],"type":"Point"}
}