{
  "type": "Feature",
  "properties": {
    "addr:full":"Achtersloot 11 Ijsselstein Ut Utrecht 3401 NR",
    "addr:housenumber":"11",
    "addr:postcode":"3401 nr",
    "addr:street":"Achtersloot",
    "iso:country":"NL",
    "sg:address":"Achtersloot 11",
    "sg:city":"Ijsselstein Ut",
    "sg:orig_category":"Public Relationbureaus",
    "sg:phone":"+31 30 688 6241",
    "sg:postcode":"3401 NR",
    "sg:province":"Utrecht",
    "wof:name":"Drs. Bernadet C.M. De Prins, Comm. Onder",
    "wof:placetype":"venue"
},
  "geometry": {"coordinates":[5.037724,52.02005],"type":"Point"}
}