{
  "type": "Feature",
  "properties": {
    "addr:full":"Professor V Ginnekenstr 6 Oudenbosch Noord-Brabant 4731 JZ",
    "addr:housenumber":"6",
    "addr:postcode":"4731 jz",
    "addr:street":"Professor;Ginnekenstr",
    "iso:country":"NL",
    "sg:address":"Professor V Ginnekenstr 6",
    "sg:city":"Oudenbosch",
    "sg:classifiers":[
        {
            "category":"Fast Food",
            "type":"Food & Drink"
        }
    ],
    "sg:phone":"+31 165 317 840",
    "sg:postcode":"4731 JZ",
    "sg:province":"Noord-Brabant",
    "sg:tags":[
        "afhaal",
        "restaurant"
    ],
    "wof:name":"Pizzeria Restaurant Mona Lisa",
    "wof:placetype":"venue"
},
  "geometry": {"coordinates":[4.526245,51.590565],"type":"Point"}
}