{
  "type": "Feature",
  "properties": {
    "addr:full":"Postbus 73 Hazerswoude Dorp 2390 AB",
    "addr:housenumber":"73",
    "addr:postcode":"2390 ab",
    "addr:street":"Postbus;Dorp",
    "iso:country":"NL",
    "sg:address":"Postbus 73",
    "sg:city":"Hazerswoude Dorp",
    "sg:orig_category":"Vakantieverblijven",
    "sg:phone":"+31 172 586 340",
    "sg:postcode":"2390 AB",
    "wof:name":"Hoeve Logies Ned",
    "wof:placetype":"venue"
},
  "geometry": {"coordinates":[4.58268,52.096748],"type":"Point"}
}