{
  "type": "Feature",
  "properties": {
    "addr:full":"Socratesstraat 9 Rotterdam Zuid-Holland 3076 BT",
    "addr:housenumber":"9",
    "addr:postcode":"3076 bt",
    "addr:street":"Socratesstraat",
    "iso:country":"NL",
    "sg:address":"Socratesstraat 9",
    "sg:city":"Rotterdam",
    "sg:orig_category":"Schilderwerk",
    "sg:phone":"+31 10 432 3899",
    "sg:postcode":"3076 BT",
    "sg:province":"Zuid-Holland",
    "wof:name":"Fa P.J. Van Zijp En Zoon Schildersbedrij",
    "wof:placetype":"venue"
},
  "geometry": {"coordinates":[4.522254,51.882534],"type":"Point"}
}