{
  "type": "Feature",
  "properties": {
    "addr:full":"Thorbeckelaan 6 Gouda South Holland 2805 CA",
    "addr:housenumber":"6",
    "addr:postcode":"2805 ca",
    "addr:street":"Thorbeckelaan",
    "iso:country":"NL",
    "sg:address":"Thorbeckelaan 6",
    "sg:city":"Gouda",
    "sg:orig_category":"Kinderopvang Behalve Thuis",
    "sg:phone":"+31 182 586 500",
    "sg:postcode":"2805 CA",
    "sg:province":"South Holland",
    "wof:name":"Kinderdagverblijf Skon Dagverblijf Flap",
    "wof:placetype":"venue"
},
  "geometry": {"coordinates":[4.710152,52.021488],"type":"Point"}
}