{
  "type": "Feature",
  "properties": {
    "addr:full":"Binnenwg 6 Tiel Gelderland 4001 ER",
    "addr:housenumber":"6",
    "addr:postcode":"4001 er",
    "addr:street":"Binnenwg;Gelderland",
    "iso:country":"NL",
    "sg:address":"Binnenwg 6",
    "sg:city":"Tiel",
    "sg:orig_category":"Schilders",
    "sg:phone":"+31 344 619 137",
    "sg:postcode":"4001 ER",
    "sg:province":"Gelderland",
    "wof:name":"Hv",
    "wof:placetype":"venue"
},
  "geometry": {"coordinates":[5.436571,51.890236],"type":"Point"}
}