{
  "type": "Feature",
  "properties": {
    "addr:full":"Tuinpad 9 Hekelingen Zuid-Holland 3209 BE",
    "addr:housenumber":"9",
    "addr:postcode":"3209",
    "addr:street":"Tuinpad",
    "iso:country":"NL",
    "sg:address":"Tuinpad 9",
    "sg:city":"Hekelingen",
    "sg:orig_category":"Honden- En Kattentrimsalons",
    "sg:phone":"+31 181 646 512",
    "sg:postcode":"3209 BE",
    "sg:province":"Zuid-Holland",
    "wof:name":"Sandra",
    "wof:placetype":"venue"
},
  "geometry": {"coordinates":[4.344068,51.825439],"type":"Point"}
}