{
  "type": "Feature",
  "properties": {
    "addr:full":"A Adamskistr 11 Voorschoten South Holland 2251 RT",
    "addr:housenumber":"11",
    "addr:postcode":"2251 rt",
    "iso:country":"NL",
    "sg:address":"A Adamskistr 11",
    "sg:city":"Voorschoten",
    "sg:orig_category":"Loodgieters",
    "sg:phone":"+31 71 561 6476",
    "sg:postcode":"2251 RT",
    "sg:province":"South Holland",
    "wof:name":"Dak En Gootspecialist",
    "wof:placetype":"venue"
},
  "geometry": {"coordinates":[4.447673,52.117996],"type":"Point"}
}