{
  "type": "Feature",
  "properties": {
    "addr:full":"Cornelis De Wittstraat 29 Wassenaar South Holland 2242 LV",
    "addr:housenumber":"29",
    "addr:postcode":"2242",
    "addr:street":"Cornelis De Wittstraat",
    "iso:country":"NL",
    "sg:address":"Cornelis De Wittstraat 29",
    "sg:city":"Wassenaar",
    "sg:orig_category":"Verzekeringen",
    "sg:phone":"+31 70 511 0818",
    "sg:postcode":"2242 LV",
    "sg:province":"South Holland",
    "wof:name":"Ass Kant M Schrama",
    "wof:placetype":"venue"
},
  "geometry": {"coordinates":[4.400411,52.144325],"type":"Point"}
}