{
  "type": "Feature",
  "properties": {
    "addr:full":"Anjelierstr 2 Almelo NL.08 7601 BL",
    "addr:housenumber":"2;nl.08",
    "addr:postcode":"7601 bl",
    "addr:street":"Anjelierstr",
    "iso:country":"NL",
    "sg:address":"Anjelierstr 2",
    "sg:city":"Almelo",
    "sg:orig_category":"Postkantoren",
    "sg:phone":"+31 546 812 980",
    "sg:postcode":"7601 BL",
    "sg:province":"NL.08",
    "sg:website":"http://www.postkantoor.nl",
    "wof:name":"Postkantoor",
    "wof:placetype":"venue"
},
  "geometry": {"coordinates":[6.661122,52.345966],"type":"Point"}
}