{
  "type": "Feature",
  "properties": {
    "iso:country":"NL",
    "sg:address":"Oudkerkhof 16",
    "sg:city":"Utrecht",
    "sg:orig_category":"Juweliers",
    "sg:phone":"+31 30 223 8422",
    "sg:postcode":"3512 GK",
    "sg:province":"Utrecht",
    "wof:name":"Outlet",
    "wof:placetype":"venue"
},
  "geometry": {"coordinates":[5.120957,52.091877],"type":"Point"}
}