{
  "type": "Feature",
  "properties": {
    "iso:country":"NL",
    "sg:address":"Stationsweg 63B",
    "sg:city":"Terneuzen",
    "sg:orig_category":"Verhuur Kantoorapparatuur",
    "sg:phone":"+31 115 648 501",
    "sg:postcode":"4538 AC",
    "sg:province":"Zeeland",
    "wof:name":"Hacktic Computer Products",
    "wof:placetype":"venue"
},
  "geometry": {"coordinates":[3.826078,51.329624],"type":"Point"}
}