{
  "type": "Feature",
  "properties": {
    "addr:full":"P Moreelsestr 30 Leeuwarden Friesland 8932 HS",
    "addr:housenumber":"30",
    "addr:postcode":"8932 hs",
    "addr:street":"P",
    "iso:country":"NL",
    "sg:address":"P Moreelsestr 30",
    "sg:city":"Leeuwarden",
    "sg:orig_category":"Begrafenisverzorging",
    "sg:phone":"+31 58 213 9707",
    "sg:postcode":"8932 HS",
    "sg:province":"Friesland",
    "sg:website":"http://www.uitvaartinformatie.nl",
    "wof:name":"Uitvaart Internet Diensten",
    "wof:placetype":"venue"
},
  "geometry": {"coordinates":[5.79609,53.191929],"type":"Point"}
}