{
  "type": "Feature",
  "properties": {
    "addr:full":"Heidenskipsterdyk 28 It Heidenskip Friesland 8724 HW",
    "addr:housenumber":"28",
    "addr:postcode":"8724 hw",
    "addr:street":"Heidenskipsterdyk",
    "iso:country":"NL",
    "sg:address":"Heidenskipsterdyk 28",
    "sg:city":"It Heidenskip",
    "sg:classifiers":[
        {
            "category":"Education",
            "subcategory":"Preschool",
            "type":"Public Place"
        }
    ],
    "sg:phone":"+31 514 521 466",
    "sg:postcode":"8724 HW",
    "sg:province":"Friesland",
    "sg:tags":[
        "kleuteronderwijs",
        "basis-"
    ],
    "wof:name":"Christelijke Basisschool De Brege",
    "wof:placetype":"venue"
},
  "geometry": {"coordinates":[5.499547,52.9506],"type":"Point"}
}