{
  "type": "Feature",
  "properties": {
    "iso:country":"NL",
    "sg:address":"Van Bergenplein 6",
    "sg:city":"Etten-Leur",
    "sg:orig_category":"Opticiens",
    "sg:phone":"+31 76 503 6038",
    "sg:postcode":"4871 CE",
    "sg:province":"North Brabant",
    "wof:name":"Frans Meijers Optiek",
    "wof:placetype":"venue"
},
  "geometry": {"coordinates":[4.6552920341,51.5852851868],"type":"Point"}
}