{
  "type": "Feature",
  "properties": {
    "iso:country":"NL",
    "sg:address":"Compagniestr 18",
    "sg:city":"Amsterdam",
    "sg:orig_category":"Makelaars En Adviseurs Schepen En Jachten",
    "sg:phone":"+31 20 420 9145",
    "sg:postcode":"1018 HL",
    "sg:province":"North Holland",
    "wof:name":"Thomas, R A",
    "wof:placetype":"venue"
},
  "geometry": {"coordinates":[4.923703,52.368874],"type":"Point"}
}