{
  "type": "Feature",
  "properties": {
    "addr:full":"Paddewg 37 Barendrecht Zuid-Holland 2992 CK",
    "addr:housenumber":"37",
    "addr:postcode":"2992 ck",
    "addr:street":"Paddewg",
    "iso:country":"NL",
    "sg:address":"Paddewg 37",
    "sg:city":"Barendrecht",
    "sg:orig_category":"Kappers",
    "sg:phone":"+31 180 621 626",
    "sg:postcode":"2992 CK",
    "sg:province":"Zuid-Holland",
    "wof:name":"Capelli",
    "wof:placetype":"venue"
},
  "geometry": {"coordinates":[4.5318880081,51.8552398682],"type":"Point"}
}