{
  "type": "Feature",
  "properties": {
    "addr:full":"Parallelweg 15 Giessenburg Zuid-Holland 3381 KS",
    "addr:housenumber":"15",
    "addr:postcode":"3381 ks",
    "addr:street":"Parallelweg",
    "iso:country":"NL",
    "sg:address":"Parallelweg 15",
    "sg:city":"Giessenburg",
    "sg:orig_category":"Autokeuringen",
    "sg:phone":"+31 184 652 011",
    "sg:postcode":"3381 KS",
    "sg:province":"Zuid-Holland",
    "wof:name":"Gebr. De Kreij",
    "wof:placetype":"venue"
},
  "geometry": {"coordinates":[4.9087,51.838898],"type":"Point"}
}