{
  "type": "Feature",
  "properties": {
    "addr:full":"Loverstr 35 Nederweert Limburg 6031 VJ",
    "addr:housenumber":"35",
    "addr:postcode":"6031 vj",
    "addr:street":"Loverstr",
    "iso:country":"NL",
    "sg:address":"Loverstr 35",
    "sg:city":"Nederweert",
    "sg:orig_category":"Dansscholen",
    "sg:phone":"+31 495 624 951",
    "sg:postcode":"6031 VJ",
    "sg:province":"Limburg",
    "sg:website":"http://www.le-niecountrydance.nl",
    "wof:name":"Western Services",
    "wof:placetype":"venue"
},
  "geometry": {"coordinates":[5.744221,51.285362],"type":"Point"}
}