{
  "type": "Feature",
  "properties": {
    "addr:full":"Waarderweg 3 Montfort Limburg 6065 EV",
    "addr:housenumber":"3",
    "addr:postcode":"6065 ev",
    "addr:street":"Waarderweg",
    "iso:country":"NL",
    "sg:address":"Waarderweg 3",
    "sg:city":"Montfort",
    "sg:classifiers":[
        {
            "category":"Food & Beverages",
            "subcategory":"Fruits & Vegetables",
            "type":"Retail Goods"
        }
    ],
    "sg:phone":"+31 475 541 627",
    "sg:postcode":"6065 EV",
    "sg:province":"Limburg",
    "sg:tags":[
        "groenten"
    ],
    "wof:name":"Groente- En Fruithal Janssen",
    "wof:placetype":"venue"
},
  "geometry": {"coordinates":[5.949429,51.130672],"type":"Point"}
}