{
  "type": "Feature",
  "properties": {
    "addr:full":"J Van Goyenstraat 2 Waalwijk Noord-Brabant 5143 JM",
    "addr:housenumber":"2",
    "addr:postcode":"5143 jm",
    "addr:street":"J Van Goyenstraat",
    "iso:country":"NL",
    "sg:address":"J Van Goyenstraat 2",
    "sg:city":"Waalwijk",
    "sg:orig_category":"Marktonderzoekbureaus",
    "sg:phone":"+31 416 560 774",
    "sg:postcode":"5143 JM",
    "sg:province":"Noord-Brabant",
    "wof:name":"Duquesnoy Marketing Consultancy",
    "wof:placetype":"venue"
},
  "geometry": {"coordinates":[5.084353,51.675724],"type":"Point"}
}