{
  "type": "Feature",
  "properties": {
    "addr:full":"Bouwerskamp 13 Emmeloord NL. 8301 AE",
    "addr:housenumber":"13",
    "addr:postcode":"8301 ae",
    "addr:street":"Bouwerskamp;Nl.",
    "iso:country":"NL",
    "sg:address":"Bouwerskamp 13",
    "sg:city":"Emmeloord",
    "sg:orig_category":"Houtindustrie",
    "sg:phone":"+31 527 249 950",
    "sg:postcode":"8301 AE",
    "sg:province":"NL.",
    "wof:name":"Houtkonstruktie Nederland Bv",
    "wof:placetype":"venue"
},
  "geometry": {"coordinates":[5.75277,52.706741],"type":"Point"}
}