{
  "type": "Feature",
  "properties": {
    "addr:full":"Leliestraat 52 Deventer Overijssel 7419 CW",
    "addr:housenumber":"52",
    "addr:postcode":"7419 cw",
    "addr:street":"Leliestraat",
    "iso:country":"NL",
    "sg:address":"Leliestraat 52",
    "sg:city":"Deventer",
    "sg:orig_category":"Verhuur Audiovisuele Apparatuur",
    "sg:phone":"+31 570 616 909",
    "sg:postcode":"7419 CW",
    "sg:province":"Overijssel",
    "wof:name":"Beeld & Geluid Deventer",
    "wof:placetype":"venue"
},
  "geometry": {"coordinates":[6.140055,52.249249],"type":"Point"}
}