{
  "type": "Feature",
  "properties": {
    "addr:full":"Nieuwe Markt 53 Roosendaal Noord-Brabant 4701 AD",
    "addr:housenumber":"53",
    "addr:postcode":"4701 ad",
    "addr:street":"Nieuwe Markt",
    "iso:country":"NL",
    "sg:address":"Nieuwe Markt 53",
    "sg:city":"Roosendaal",
    "sg:orig_category":"Werving And Selectie Van Tijdelijk Personeel And Uitzendkantoren",
    "sg:phone":"+31 165 557 047",
    "sg:postcode":"4701 AD",
    "sg:province":"Noord-Brabant",
    "wof:name":"Uitzendbureau Start",
    "wof:placetype":"venue"
},
  "geometry": {"coordinates":[4.4578828812,51.5317230225],"type":"Point"}
}