{
  "type": "Feature",
  "properties": {
    "addr:full":"De Veken 7 Opmeer Noord-Holland 1716 KE",
    "addr:housenumber":"7",
    "addr:postcode":"1716 ke",
    "addr:street":"De Veken",
    "iso:country":"NL",
    "sg:address":"De Veken 7",
    "sg:city":"Opmeer",
    "sg:orig_category":"Projectontwikkeling",
    "sg:phone":"+31 226 354 140",
    "sg:postcode":"1716 KE",
    "sg:province":"Noord-Holland",
    "wof:name":"Duyncroft Bv",
    "wof:placetype":"venue"
},
  "geometry": {"coordinates":[4.956657,52.707466],"type":"Point"}
}