{
  "type": "Feature",
  "properties": {
    "addr:full":"Sportln 10 Best Noord-Brabant 5683 CS",
    "addr:housenumber":"10",
    "addr:postcode":"5683 cs",
    "addr:street":"Sportln",
    "iso:country":"NL",
    "sg:address":"Sportln 10",
    "sg:city":"Best",
    "sg:orig_category":"Verenigingen En Stichtingen",
    "sg:phone":"+31 499 395 041",
    "sg:postcode":"5683 CS",
    "sg:province":"Noord-Brabant",
    "wof:name":"Dorpswerkplaats",
    "wof:placetype":"venue"
},
  "geometry": {"coordinates":[-101.379272,31.108017],"type":"Point"}
}