{
  "type": "Feature",
  "properties": {
    "addr:full":"Muggepln 9 Deventer Overijssel 7411 NW",
    "addr:housenumber":"9",
    "addr:postcode":"7411 nw",
    "addr:street":"Muggepln",
    "iso:country":"NL",
    "sg:address":"Muggepln 9",
    "sg:city":"Deventer",
    "sg:orig_category":"Zalenverhuur",
    "sg:phone":"+31 570 614 965",
    "sg:postcode":"7411 NW",
    "sg:province":"Overijssel",
    "wof:name":"Fermerie, De",
    "wof:placetype":"venue"
},
  "geometry": {"coordinates":[6.15183,52.253437],"type":"Point"}
}