{
  "type": "Feature",
  "properties": {
    "addr:full":"Winkelcentrum 17 Etten Leur Noord-Brabant 4873 AB",
    "addr:housenumber":"17",
    "addr:postcode":"4873 ab",
    "addr:street":"Winkelcentrum",
    "iso:country":"NL",
    "sg:address":"Winkelcentrum 17",
    "sg:city":"Etten Leur",
    "sg:classifiers":[
        {
            "category":"Food & Beverages",
            "subcategory":"Fruits & Vegetables",
            "type":"Retail Goods"
        }
    ],
    "sg:phone":"+31 76 502 0790",
    "sg:postcode":"4873 AB",
    "sg:province":"Noord-Brabant",
    "sg:tags":[
        "en",
        "groenten"
    ],
    "wof:name":"Carl'S Zonnetuin",
    "wof:placetype":"venue"
},
  "geometry": {"coordinates":[4.635686,51.568317],"type":"Point"}
}