{
  "type": "Feature",
  "properties": {
    "addr:full":"Hoge Rijndijk 197 Zoeterwoude Zuid-Holland 2382 AJ",
    "addr:housenumber":"197",
    "addr:postcode":"2382 aj",
    "addr:street":"Hoge Rijndijk",
    "iso:country":"NL",
    "sg:address":"Hoge Rijndijk 197",
    "sg:city":"Zoeterwoude",
    "sg:orig_category":"Boekhouders",
    "sg:phone":"+31 71 541 2508",
    "sg:postcode":"2382 AJ",
    "sg:province":"Zuid-Holland",
    "wof:name":"Administratiekantoor L.A.N. Stokman",
    "wof:placetype":"venue"
},
  "geometry": {"coordinates":[4.537441,52.139896],"type":"Point"}
}