{
  "type": "Feature",
  "properties": {
    "addr:full":"Kloosterweg 87 Burgh Haamstede Zeeland 4328 GP",
    "addr:housenumber":"87",
    "addr:postcode":"4328 gp",
    "addr:street":"Kloosterweg;Haamstede",
    "iso:country":"NL",
    "sg:address":"Kloosterweg 87",
    "sg:city":"Burgh Haamstede",
    "sg:orig_category":"Kampeerterreinen",
    "sg:phone":"+31 111 652 104",
    "sg:postcode":"4328 GP",
    "sg:province":"Zeeland",
    "wof:name":"Kampwinkel Supermarkt De Schuur",
    "wof:placetype":"venue"
},
  "geometry": {"coordinates":[3.7246489525,51.7107124329],"type":"Point"}
}