{
  "type": "Feature",
  "properties": {
    "iso:country":"NL",
    "sg:address":"Gordonstraat 4",
    "sg:city":"Schiedam",
    "sg:classifiers":[
        {
            "category":"Fast Food",
            "type":"Food & Drink"
        }
    ],
    "sg:phone":"+31 10 426 1229",
    "sg:postcode":"3117 MS",
    "sg:province":"South Holland",
    "sg:tags":[
        "afhaal",
        "restaurant"
    ],
    "wof:name":"Snackbar Ton",
    "wof:placetype":"venue"
},
  "geometry": {"coordinates":[4.392276,51.916805],"type":"Point"}
}