{
  "type": "Feature",
  "properties": {
    "addr:full":"Kerkstr 2 Tricht Gelderland 4196 AB",
    "addr:housenumber":"2",
    "addr:postcode":"4196 ab",
    "addr:street":"Kerkstr;Gelderland",
    "iso:country":"NL",
    "sg:address":"Kerkstr 2",
    "sg:city":"Tricht",
    "sg:orig_category":"Artsen - Huisartsen",
    "sg:phone":"+31 345 571 300",
    "sg:postcode":"4196 AB",
    "sg:province":"Gelderland",
    "wof:name":"Buyserd, E N",
    "wof:placetype":"venue"
},
  "geometry": {"coordinates":[5.270245,51.888824],"type":"Point"}
}