{
  "type": "Feature",
  "properties": {
    "addr:full":"Travertyndk 31 Roosendaal North Brabant 4706 TR",
    "addr:housenumber":"31",
    "addr:postcode":"4706 tr",
    "addr:street":"Travertyndk",
    "iso:country":"NL",
    "sg:address":"Travertyndk 31",
    "sg:city":"Roosendaal",
    "sg:orig_category":"Verenigingen En Stichtingen",
    "sg:phone":"+31 165 391 400",
    "sg:postcode":"4706 TR",
    "sg:province":"North Brabant",
    "sg:website":"http://www.jeugdronde.nl",
    "wof:name":"Jeugdronde, Sticht Nat",
    "wof:placetype":"venue"
},
  "geometry": {"coordinates":[4.497293,51.520248],"type":"Point"}
}