{
  "type": "Feature",
  "properties": {
    "addr:full":"Hemonystr 45 Amsterdam North Holland 1074 BN",
    "addr:housenumber":"45",
    "addr:postcode":"1074 bn",
    "addr:street":"Hemonystr",
    "iso:country":"NL",
    "sg:address":"Hemonystr 45",
    "sg:city":"Amsterdam",
    "sg:orig_category":"Fotolitho- En Reprografie - Inrichtingen",
    "sg:phone":"+31 20 625 8329",
    "sg:postcode":"1074 BN",
    "sg:province":"North Holland",
    "wof:name":"Reprov",
    "wof:placetype":"venue"
},
  "geometry": {"coordinates":[4.903241,52.356102],"type":"Point"}
}