{
  "type": "Feature",
  "properties": {
    "addr:full":"Kortestraat 3 Andelst Gelderland 6673 BJ",
    "addr:housenumber":"3",
    "addr:postcode":"6673 bj",
    "addr:street":"Kortestraat;Gelderland",
    "iso:country":"NL",
    "sg:address":"Kortestraat 3",
    "sg:city":"Andelst",
    "sg:orig_category":"Bedrijfsinventaris Gh",
    "sg:phone":"+31 488 452 051",
    "sg:postcode":"6673 BJ",
    "sg:province":"Gelderland",
    "wof:name":"Handelsmaatschappij G. Spronk & Zn Bv",
    "wof:placetype":"venue"
},
  "geometry": {"coordinates":[5.725518,51.907677],"type":"Point"}
}