{
  "type": "Feature",
  "properties": {
    "iso:country":"NL",
    "sg:address":"De Rail 50",
    "sg:city":"Stadskanaal",
    "sg:orig_category":"Glas, Porselein En Aardewerk",
    "sg:phone":"+31 599 616 847",
    "sg:postcode":"9503 AX",
    "sg:province":"Groningen",
    "wof:name":"Bodlinka",
    "wof:placetype":"venue"
},
  "geometry": {"coordinates":[6.942097,52.9921],"type":"Point"}
}