{
  "type": "Feature",
  "properties": {
    "iso:country":"NL",
    "sg:address":"Stationsplein 1",
    "sg:city":"Maastricht",
    "sg:orig_category":"Bloemen And Planten",
    "sg:phone":"+31 43 325 3710",
    "sg:postcode":"6221 BT",
    "sg:province":"Limburg",
    "wof:name":"Bloemenhuis Van Der Weyden Station Maastricht",
    "wof:placetype":"venue"
},
  "geometry": {"coordinates":[5.704967,50.849171],"type":"Point"}
}