{
  "type": "Feature",
  "properties": {
    "addr:full":"Windvaan 5 Geldermalsen Gelderland 4191 TK",
    "addr:housenumber":"5",
    "addr:postcode":"4191 tk",
    "addr:street":"Windvaan;Gelderland",
    "iso:country":"NL",
    "sg:address":"Windvaan 5",
    "sg:city":"Geldermalsen",
    "sg:orig_category":"Verzekeringen - Verzekeringskantoren",
    "sg:phone":"+31 345 572 932",
    "sg:postcode":"4191 TK",
    "sg:province":"Gelderland",
    "wof:name":"Windvaan, De",
    "wof:placetype":"venue"
},
  "geometry": {"coordinates":[5.281459,51.88063],"type":"Point"}
}