{
  "type": "Feature",
  "properties": {
    "addr:full":"Het Anker 8 Raamsdonksveer Noord-Brabant 4941 RG",
    "addr:housenumber":"8",
    "addr:postcode":"4941 rg",
    "addr:street":"Het Anker",
    "iso:country":"NL",
    "sg:address":"Het Anker 8",
    "sg:city":"Raamsdonksveer",
    "sg:orig_category":"Fotolaboratoria",
    "sg:phone":"+31 162 515 820",
    "sg:postcode":"4941 RG",
    "sg:province":"Noord-Brabant",
    "wof:name":"Foto Antoine Verschuuren",
    "wof:placetype":"venue"
},
  "geometry": {"coordinates":[4.873163,51.69569],"type":"Point"}
}