{
  "type": "Feature",
  "properties": {
    "addr:full":"Halstraat 3 Zaandam Noord-Holland 1502 VG",
    "addr:housenumber":"3",
    "addr:postcode":"1502 vg",
    "addr:street":"Halstraat",
    "iso:country":"NL",
    "sg:address":"Halstraat 3",
    "sg:city":"Zaandam",
    "sg:orig_category":"Schilderwerk",
    "sg:phone":"+31 75 616 4650",
    "sg:postcode":"1502 VG",
    "sg:province":"Noord-Holland",
    "wof:name":"Schildersbedrijf G Reurslag",
    "wof:placetype":"venue"
},
  "geometry": {"coordinates":[4.82572,52.442265],"type":"Point"}
}