{
  "type": "Feature",
  "properties": {
    "addr:full":"Postbus 21 Zierikzee Zeeland 4300 AA",
    "addr:housenumber":"21",
    "addr:postcode":"4300 aa",
    "addr:street":"Postbus",
    "iso:country":"NL",
    "sg:address":"Postbus 21",
    "sg:city":"Zierikzee",
    "sg:orig_category":"Voegwerken",
    "sg:phone":"+31 6 22919186",
    "sg:postcode":"4300 AA",
    "sg:province":"Zeeland",
    "wof:name":"Wall Resta",
    "wof:placetype":"venue"
},
  "geometry": {"coordinates":[3.91706,51.65007],"type":"Point"}
}