{
  "type": "Feature",
  "properties": {
    "iso:country":"NL",
    "sg:address":"Nieuwe Ebbingestraat 167",
    "sg:city":"Groningen",
    "sg:classifiers":[
        {
            "category":"Fast Food",
            "type":"Food & Drink"
        }
    ],
    "sg:phone":"+31 50 573 0401",
    "sg:postcode":"9715 BC",
    "sg:province":"Groningen",
    "sg:tags":[
        "afhaal",
        "restaurant"
    ],
    "wof:name":"Automatiek Krohne",
    "wof:placetype":"venue"
},
  "geometry": {"coordinates":[6.560354,53.228184],"type":"Point"}
}