{
  "type": "Feature",
  "properties": {
    "iso:country":"NL",
    "sg:address":"Doesburgwg 7",
    "sg:city":"Gouda",
    "sg:orig_category":"Adviesbureaus Financieel",
    "sg:phone":"+31 182 558 922",
    "sg:postcode":"2803 PL",
    "sg:province":"Zuid-Holland",
    "wof:name":"Mul Bv, A",
    "wof:placetype":"venue"
},
  "geometry": {"coordinates":[4.678374,52.025501],"type":"Point"}
}