{
  "type": "Feature",
  "properties": {
    "addr:full":"Doesburgwg 7 Gouda Zuid-Holland 2803 PL",
    "addr:housenumber":"7",
    "addr:postcode":"2803 pl",
    "addr:street":"Doesburgwg",
    "iso:country":"NL",
    "sg:address":"Doesburgwg 7",
    "sg:city":"Gouda",
    "sg:orig_category":"Adviesbureaus Financieel",
    "sg:phone":"+31 182 558 922",
    "sg:postcode":"2803 PL",
    "sg:province":"Zuid-Holland",
    "wof:name":"Mul Bv, A",
    "wof:placetype":"venue"
},
  "geometry": {"coordinates":[4.678374,52.025501],"type":"Point"}
}