{
  "type": "Feature",
  "properties": {
    "iso:country":"NL",
    "sg:address":"Kerkstraat 52",
    "sg:city":"Groningen",
    "sg:orig_category":"Mobiele Service Aan Motorvoertuigen",
    "sg:phone":"+31 50 556 5274",
    "sg:postcode":"9745 CK",
    "sg:province":"Groningen",
    "wof:name":"Takel- En Bergingsbedrijf Poort Bv",
    "wof:placetype":"venue"
},
  "geometry": {"coordinates":[6.500342,53.217724],"type":"Point"}
}