{
  "type": "Feature",
  "properties": {
    "addr:full":"Hollywoodln 70 Almere NL. 1325 HS",
    "addr:housenumber":"70",
    "addr:postcode":"1325 hs",
    "addr:street":"Hollywoodln;Nl.",
    "iso:country":"NL",
    "sg:address":"Hollywoodln 70",
    "sg:city":"Almere",
    "sg:orig_category":"Beeldende Kunstenaars",
    "sg:phone":"+31 36 537 6590",
    "sg:postcode":"1325 HS",
    "sg:province":"NL.",
    "wof:name":"Manson, M D",
    "wof:placetype":"venue"
},
  "geometry": {"coordinates":[5.23721,52.364529],"type":"Point"}
}