{
  "type": "Feature",
  "properties": {
    "addr:full":"Porporastraat 129 Zwolle NL.08 8031 HM",
    "addr:housenumber":"129",
    "addr:postcode":"8031 hm",
    "addr:street":"Porporastraat",
    "iso:country":"NL",
    "sg:address":"Porporastraat 129",
    "sg:city":"Zwolle",
    "sg:orig_category":"Kinderopvang Behalve Thuis",
    "sg:phone":"+31 38 422 8991",
    "sg:postcode":"8031 HM",
    "sg:province":"NL.08",
    "wof:name":"De Bengels",
    "wof:placetype":"venue"
},
  "geometry": {"coordinates":[6.079592,52.526859],"type":"Point"}
}