{
  "type": "Feature",
  "properties": {
    "addr:full":"Hallinxweg 20 Numansdorp Zuid-Holland 3281 KD",
    "addr:housenumber":"20",
    "addr:postcode":"3281 kd",
    "addr:street":"Hallinxweg",
    "iso:country":"NL",
    "sg:address":"Hallinxweg 20",
    "sg:city":"Numansdorp",
    "sg:orig_category":"Loodgieterswerk, Verwarming And Sanitaire Installaties",
    "sg:phone":"+31 186 652 297",
    "sg:postcode":"3281 KD",
    "sg:province":"Zuid-Holland",
    "wof:name":"B C Van Der Burgh",
    "wof:placetype":"venue"
},
  "geometry": {"coordinates":[4.428256,51.733932],"type":"Point"}
}