{
  "type": "Feature",
  "properties": {
    "addr:full":"Hazenakkerstr 20 Oss Noord-Brabant 5343 EA",
    "addr:housenumber":"20",
    "addr:postcode":"5343 ea",
    "addr:street":"Hazenakkerstr",
    "iso:country":"NL",
    "sg:address":"Hazenakkerstr 20",
    "sg:city":"Oss",
    "sg:orig_category":"Houtdraaierijen",
    "sg:phone":"+31 412 633 414",
    "sg:postcode":"5343 EA",
    "sg:province":"Noord-Brabant",
    "wof:name":"Artihout",
    "wof:placetype":"venue"
},
  "geometry": {"coordinates":[-77.235214,38.312599],"type":"Point"}
}