{
  "type": "Feature",
  "properties": {
    "iso:country":"NL",
    "sg:address":"Hazenakkerstr 20",
    "sg:city":"Oss",
    "sg:orig_category":"Houtdraaierijen",
    "sg:phone":"+31 412 633 414",
    "sg:postcode":"5343 EA",
    "sg:province":"Noord-Brabant",
    "wof:name":"Artihout",
    "wof:placetype":"venue"
},
  "geometry": {"coordinates":[-77.235214,38.312599],"type":"Point"}
}