{
  "type": "Feature",
  "properties": {
    "iso:country":"NL",
    "sg:address":"Zeelandweg Oost 35",
    "sg:city":"De Heen",
    "sg:orig_category":"Landbouwdiensten",
    "sg:phone":"+31 167 563 401",
    "sg:postcode":"4655 TT",
    "sg:province":"Noord-Brabant",
    "wof:name":"Firma C.P.M. Oomen En Zoon",
    "wof:placetype":"venue"
},
  "geometry": {"coordinates":[4.278425,51.59911],"type":"Point"}
}