{
  "type": "Feature",
  "properties": {
    "addr:full":"Marshalllaan 78 Hellevoetsluis Zuid-Holland 3223 HC",
    "addr:housenumber":"78",
    "addr:postcode":"3223 hc",
    "addr:street":"Marshalllaan",
    "iso:country":"NL",
    "sg:address":"Marshalllaan 78",
    "sg:city":"Hellevoetsluis",
    "sg:orig_category":"Diverse Grafische Activiteiten",
    "sg:phone":"+31 181 327 185",
    "sg:postcode":"3223 HC",
    "sg:province":"Zuid-Holland",
    "wof:name":"J.G. Janzen",
    "wof:placetype":"venue"
},
  "geometry": {"coordinates":[4.15442,51.844711],"type":"Point"}
}