{
  "type": "Feature",
  "properties": {
    "addr:full":"Pr Irenestr 3 Zelhem Gelderland 7021 CG",
    "addr:housenumber":"3",
    "addr:postcode":"7021 cg",
    "addr:street":"Gelderland",
    "iso:country":"NL",
    "sg:address":"Pr Irenestr 3",
    "sg:city":"Zelhem",
    "sg:orig_category":"Fotoreportages",
    "sg:phone":"+31 314 621 960",
    "sg:postcode":"7021 CG",
    "sg:province":"Gelderland",
    "wof:name":"Hulst, Henry Van",
    "wof:placetype":"venue"
},
  "geometry": {"coordinates":[6.349282,52.004967],"type":"Point"}
}