{
  "type": "Feature",
  "properties": {
    "addr:full":"Binnenweg 144/To Heemstede Noord-Holland 2101 JP",
    "addr:housenumber":"144 / to heemstede",
    "addr:postcode":"2101 jp",
    "addr:street":"Binnenweg",
    "iso:country":"NL",
    "sg:address":"Binnenweg 144/To",
    "sg:city":"Heemstede",
    "sg:orig_category":"Bloemen And Planten",
    "sg:phone":"+31 23 528 7102",
    "sg:postcode":"2101 JP",
    "sg:province":"Noord-Holland",
    "wof:name":"Rob'S Bloemenshop",
    "wof:placetype":"venue"
},
  "geometry": {"coordinates":[4.621248,52.345287],"type":"Point"}
}