{
  "type": "Feature",
  "properties": {
    "addr:full":"Operettewg 82 Almere NL. 1323 VC",
    "addr:housenumber":"82",
    "addr:postcode":"1323 vc",
    "addr:street":"Operettewg;Nl.",
    "iso:country":"NL",
    "sg:address":"Operettewg 82",
    "sg:city":"Almere",
    "sg:orig_category":"Keuken- Groot-Installaties",
    "sg:phone":"+31 36 536 3711",
    "sg:postcode":"1323 VC",
    "sg:province":"NL.",
    "wof:name":"Giezen",
    "wof:placetype":"venue"
},
  "geometry": {"coordinates":[5.187484,52.365238],"type":"Point"}
}