{
  "type": "Feature",
  "properties": {
    "addr:full":"Hollandshof 70 Bodegraven Zuid-Holland 2411 KG",
    "addr:housenumber":"70",
    "addr:postcode":"2411 kg",
    "addr:street":"Hollandshof",
    "iso:country":"NL",
    "sg:address":"Hollandshof 70",
    "sg:city":"Bodegraven",
    "sg:orig_category":"Webdesign Bureaus",
    "sg:phone":"+31 172 610 035",
    "sg:postcode":"2411 KG",
    "sg:province":"Zuid-Holland",
    "wof:name":"Compile",
    "wof:placetype":"venue"
},
  "geometry": {"coordinates":[4.7534770966,52.0794792175],"type":"Point"}
}