{
  "type": "Feature",
  "properties": {
    "iso:country":"NL",
    "sg:address":"Sperwerhoek 18",
    "sg:city":"Waddinxveen",
    "sg:orig_category":"Adviesbureaus Bedrijfsorganisatie",
    "sg:phone":"+31 182 640 560",
    "sg:postcode":"2743 GC",
    "sg:province":"Zuid-Holland",
    "sg:website":"http://www.on-flow.nl",
    "wof:name":"On Flow Bv",
    "wof:placetype":"venue"
},
  "geometry": {"coordinates":[4.641013,52.039986],"type":"Point"}
}