{
  "type": "Feature",
  "properties": {
    "addr:full":"H De Grootstr 7 Meppel Provincie Drenthe 7942 HA",
    "addr:housenumber":"7",
    "addr:postcode":"7942 ha",
    "addr:street":"Provincie Drenthe",
    "iso:country":"NL",
    "sg:address":"H De Grootstr 7",
    "sg:city":"Meppel",
    "sg:orig_category":"Verf En Lak",
    "sg:phone":"+31 522 241 005",
    "sg:postcode":"7942 HA",
    "sg:province":"Provincie Drenthe",
    "sg:website":"http://www.paintdiscount.nl",
    "wof:name":"Paint-Discount",
    "wof:placetype":"venue"
},
  "geometry": {"coordinates":[6.188218,52.703453],"type":"Point"}
}