{
  "type": "Feature",
  "properties": {
    "addr:full":"Mozartstraat 91 Heemskerk Noord-Holland 1962 AB",
    "addr:housenumber":"91",
    "addr:postcode":"1962 ab",
    "addr:street":"Mozartstraat",
    "iso:country":"NL",
    "sg:address":"Mozartstraat 91",
    "sg:city":"Heemskerk",
    "sg:orig_category":"Bejaardeninstellingen And Serviceflats",
    "sg:phone":"+31 251 236 493",
    "sg:postcode":"1962 AB",
    "sg:province":"Noord-Holland",
    "wof:name":"Meerstate Centrum Voor Verpleeghuiszorg",
    "wof:placetype":"venue"
},
  "geometry": {"coordinates":[4.675979,52.51852],"type":"Point"}
}