{
  "type": "Feature",
  "properties": {
    "iso:country":"NL",
    "sg:address":"Zevenhuisterweg 37",
    "sg:city":"Nieuw Roden",
    "sg:orig_category":"Benzinestations And Brandstoffen",
    "sg:phone":"+31 594 631 456",
    "sg:postcode":"9311 VA",
    "sg:province":"Provincie Drenthe",
    "wof:name":"Garage V.D. Veen",
    "wof:placetype":"venue"
},
  "geometry": {"coordinates":[6.3772411346,53.122253418],"type":"Point"}
}