{
  "type": "Feature",
  "properties": {
    "iso:country":"NL",
    "sg:address":"Lokerenpassage 148",
    "sg:city":"S Hertogenbosch",
    "sg:classifiers":[
        {
            "category":"Food & Beverages",
            "subcategory":"Bakery",
            "type":"Retail Goods"
        }
    ],
    "sg:phone":"+31 73 645 0708",
    "sg:postcode":"5235 KS",
    "sg:province":"Noord-Brabant",
    "sg:tags":[
        "brood",
        "en",
        "banket"
    ],
    "wof:name":"Keulen, Van",
    "wof:placetype":"venue"
},
  "geometry": {"coordinates":[5.307785,51.726482],"type":"Point"}
}