{
  "type": "Feature",
  "properties": {
    "iso:country":"NL",
    "sg:address":"Stadhoudersplein 1",
    "sg:city":"Wassenaar",
    "sg:orig_category":"Meubelzaken, Woning- And Keukeninrichting",
    "sg:phone":"+31 70 511 5138",
    "sg:postcode":"2241 EA",
    "sg:province":"Zuid-Holland",
    "wof:name":"C.W. Nieuwland Bv",
    "wof:placetype":"venue"
},
  "geometry": {"coordinates":[4.402855,52.144375],"type":"Point"}
}