{
  "type": "Feature",
  "properties": {
    "addr:full":"Forellendaal 302 S Gravenhage Zuid-Holland 2553 LM",
    "addr:housenumber":"302;gravenhage",
    "addr:postcode":"2553 lm",
    "addr:street":"Forellendaal;S",
    "iso:country":"NL",
    "sg:address":"Forellendaal 302",
    "sg:city":"S Gravenhage",
    "sg:orig_category":"Kappers",
    "sg:phone":"+31 70 397 8105",
    "sg:postcode":"2553 LM",
    "sg:province":"Zuid-Holland",
    "wof:name":"Aarle, John Van",
    "wof:placetype":"venue"
},
  "geometry": {"coordinates":[4.2198700905,52.0465888977],"type":"Point"}
}