{
  "type": "Feature",
  "properties": {
    "addr:full":"Groningenlaan 25 Lage Zwaluwe North Brabant 4926 GA",
    "addr:housenumber":"25",
    "addr:postcode":"4926 ga",
    "addr:street":"Groningenlaan",
    "iso:country":"NL",
    "sg:address":"Groningenlaan 25",
    "sg:city":"Lage Zwaluwe",
    "sg:orig_category":"Loodgieterswerk, Verwarming And Sanitaire Installaties",
    "sg:phone":"+31 168 484 815",
    "sg:postcode":"4926 GA",
    "sg:province":"North Brabant",
    "wof:name":"W T O De Wit",
    "wof:placetype":"venue"
},
  "geometry": {"coordinates":[4.70722,51.706635],"type":"Point"}
}