{
  "type": "Feature",
  "properties": {
    "addr:full":"Kennedyln 16A Bergeyk Noord-Brabant 5571 KC",
    "addr:housenumber":"16a",
    "addr:postcode":"5571 kc",
    "addr:street":"Kennedyln",
    "iso:country":"NL",
    "sg:address":"Kennedyln 16A",
    "sg:city":"Bergeyk",
    "sg:orig_category":"Elektrotechnische Artikelen",
    "sg:phone":"+31 497 571 769",
    "sg:postcode":"5571 KC",
    "sg:province":"Noord-Brabant",
    "wof:name":"Brandsma Bv",
    "wof:placetype":"venue"
},
  "geometry": {"coordinates":[5.360135,51.323326],"type":"Point"}
}