{
  "type": "Feature",
  "properties": {
    "addr:full":"Meesterswg 1 Staphorst NL.08 7951 BR",
    "addr:housenumber":"1;nl.08",
    "addr:postcode":"7951 br",
    "addr:street":"Meesterswg",
    "iso:country":"NL",
    "sg:address":"Meesterswg 1",
    "sg:city":"Staphorst",
    "sg:orig_category":"Meubelen - Fabrieken En Groothandel",
    "sg:phone":"+31 522 466 000",
    "sg:postcode":"7951 BR",
    "sg:province":"NL.08",
    "sg:website":"http://www.talens.com",
    "wof:name":"Talens",
    "wof:placetype":"venue"
},
  "geometry": {"coordinates":[6.209682,52.647717],"type":"Point"}
}