{
  "type": "Feature",
  "properties": {
    "addr:full":"Hellenburg 13 Vlissingen Zeeland 4385 EN",
    "addr:housenumber":"13",
    "addr:postcode":"4385 en",
    "addr:street":"Hellenburg",
    "iso:country":"NL",
    "sg:address":"Hellenburg 13",
    "sg:city":"Vlissingen",
    "sg:orig_category":"Gordijnstoffen - Fabrieken En Groothandel",
    "sg:phone":"+31 118 463 310",
    "sg:postcode":"4385 EN",
    "sg:province":"Zeeland",
    "wof:name":"Andr?'S Gordijnengroothandel",
    "wof:placetype":"venue"
},
  "geometry": {"coordinates":[3.570307,51.461212],"type":"Point"}
}