{
  "type": "Feature",
  "properties": {
    "addr:full":"Vischpoortstr 14 Elburg Gelderland 8081 ER",
    "addr:housenumber":"14",
    "addr:postcode":"8081 er",
    "addr:street":"Vischpoortstr;Gelderland",
    "iso:country":"NL",
    "sg:address":"Vischpoortstr 14",
    "sg:city":"Elburg",
    "sg:classifiers":[
        {
            "category":"Food & Beverages",
            "subcategory":"Bakery",
            "type":"Retail Goods"
        }
    ],
    "sg:phone":"+31 525 685 072",
    "sg:postcode":"8081 ER",
    "sg:province":"Gelderland",
    "sg:tags":[
        "brood",
        "en",
        "banket"
    ],
    "wof:name":"Olst, W Van",
    "wof:placetype":"venue"
},
  "geometry": {"coordinates":[5.83308,52.448997],"type":"Point"}
}