{
  "type": "Feature",
  "properties": {
    "iso:country":"NL",
    "sg:address":"Dobbelsteyn 16",
    "sg:city":"Doenrade",
    "sg:orig_category":"Horeca-Inrichtingen En -Uitrustingen",
    "sg:phone":"+31 46 442 0451",
    "sg:postcode":"6439 BM",
    "sg:province":"Limburg",
    "sg:website":"http://www.tumbroeck.com",
    "wof:name":"Tumbroeck Bv",
    "wof:placetype":"venue"
},
  "geometry": {"coordinates":[5.909501,50.965488],"type":"Point"}
}