{
  "type": "Feature",
  "properties": {
    "addr:full":"Ravenstr 78 Schellinkhout North Holland 1697 KR",
    "addr:housenumber":"78",
    "addr:postcode":"1697 kr",
    "addr:street":"Ravenstr",
    "iso:country":"NL",
    "sg:address":"Ravenstr 78",
    "sg:city":"Schellinkhout",
    "sg:orig_category":"Keukens",
    "sg:phone":"+31 229 503 200",
    "sg:postcode":"1697 KR",
    "sg:province":"North Holland",
    "wof:name":"Tkt Bv",
    "wof:placetype":"venue"
},
  "geometry": {"coordinates":[5.121367,52.636353],"type":"Point"}
}