{
  "type": "Feature",
  "properties": {
    "addr:full":"Hoge Rijndijk 307 Zoeterwoude Zuid-Holland 2382 AP",
    "addr:housenumber":"307",
    "addr:postcode":"2382 ap",
    "addr:street":"Hoge Rijndijk",
    "iso:country":"NL",
    "sg:address":"Hoge Rijndijk 307",
    "sg:city":"Zoeterwoude",
    "sg:orig_category":"Huishoudapparatuur, Televisies And Radio'S",
    "sg:phone":"+31 71 581 6666",
    "sg:postcode":"2382 AP",
    "sg:province":"Zuid-Holland",
    "wof:name":"Karwei Bouwmarkt",
    "wof:placetype":"venue"
},
  "geometry": {"coordinates":[4.547785,52.138199],"type":"Point"}
}