{
  "type": "Feature",
  "properties": {
    "iso:country":"NL",
    "sg:address":"Valeriaanstr 35",
    "sg:city":"Soest",
    "sg:orig_category":"Agenturen En Commissiehandel",
    "sg:phone":"+31 6 53226959",
    "sg:postcode":"3765 EJ",
    "sg:province":"Utrecht",
    "wof:name":"Tupker Bv, C J",
    "wof:placetype":"venue"
},
  "geometry": {"coordinates":[5.292903,52.167671],"type":"Point"}
}