{
  "type": "Feature",
  "properties": {
    "iso:country":"NL",
    "sg:address":"Zandsteeg 14",
    "sg:city":"Nieuwendijk Nb",
    "sg:orig_category":"Boekhouders",
    "sg:phone":"+31 183 403 734",
    "sg:postcode":"4255 SH",
    "sg:province":"North Brabant",
    "wof:name":"Administratie- En Adviesburo Rhino",
    "wof:placetype":"venue"
},
  "geometry": {"coordinates":[4.911137,51.779564],"type":"Point"}
}