{
  "type": "Feature",
  "properties": {
    "addr:full":"Fauna 17 Huizen Noord-Holland 1273 GV",
    "addr:housenumber":"17",
    "addr:postcode":"1273 gv",
    "addr:street":"Fauna",
    "iso:country":"NL",
    "sg:address":"Fauna 17",
    "sg:city":"Huizen",
    "sg:orig_category":"Product-Promotie",
    "sg:phone":"+31 6 53420684",
    "sg:postcode":"1273 GV",
    "sg:province":"Noord-Holland",
    "wof:name":"Mkp",
    "wof:placetype":"venue"
},
  "geometry": {"coordinates":[5.257438,52.297836],"type":"Point"}
}