{
  "type": "Feature",
  "properties": {
    "addr:full":"Straatsburgflat 1/B Uithoorn Noord-Holland 1422 VV",
    "addr:housenumber":"1 / b",
    "addr:postcode":"1422 vv",
    "addr:street":"Straatsburgflat",
    "iso:country":"NL",
    "sg:address":"Straatsburgflat 1/B",
    "sg:city":"Uithoorn",
    "sg:orig_category":"Mensendieck - Oefentherapeuten",
    "sg:phone":"+31 297 569 002",
    "sg:postcode":"1422 VV",
    "sg:province":"Noord-Holland",
    "wof:name":"Bruin En S D P Montero, J M C De",
    "wof:placetype":"venue"
},
  "geometry": {"coordinates":[4.833226,52.248581],"type":"Point"}
}