{
  "type": "Feature",
  "properties": {
    "addr:full":"Houtdraaier 5 Heerenveen Friesland 8447 GG",
    "addr:housenumber":"5",
    "addr:postcode":"8447 gg",
    "addr:street":"Houtdraaier",
    "iso:country":"NL",
    "sg:address":"Houtdraaier 5",
    "sg:city":"Heerenveen",
    "sg:orig_category":"Verlichting And Huishoudartikelen",
    "sg:phone":"+31 513 650 760",
    "sg:postcode":"8447 GG",
    "sg:province":"Friesland",
    "wof:name":"Lucente Exclusive Lighting",
    "wof:placetype":"venue"
},
  "geometry": {"coordinates":[5.902841,52.965225],"type":"Point"}
}