{
  "type": "Feature",
  "properties": {
    "addr:full":"T Holland 53 Duiven Gelderland 6921 GX",
    "addr:housenumber":"53",
    "addr:postcode":"6921 gx",
    "addr:street":"T Holland;Gelderland",
    "iso:country":"NL",
    "sg:address":"T Holland 53",
    "sg:city":"Duiven",
    "sg:classifiers":[
        {
            "category":"Professional",
            "type":"Services"
        }
    ],
    "sg:phone":"+31 316 540 252",
    "sg:postcode":"6921 GX",
    "sg:province":"Gelderland",
    "sg:tags":[
        "leasing"
    ],
    "wof:name":"B & W Bv",
    "wof:placetype":"venue"
},
  "geometry": {"coordinates":[6.023653,51.941257],"type":"Point"}
}