{
  "type": "Feature",
  "properties": {
    "addr:full":"Leuvensestraat 32 Groessen Gelderland 6923 BL",
    "addr:housenumber":"32",
    "addr:postcode":"6923 bl",
    "addr:street":"Leuvensestraat;Gelderland",
    "iso:country":"NL",
    "sg:address":"Leuvensestraat 32",
    "sg:city":"Groessen",
    "sg:orig_category":"Bloemen And Planten",
    "sg:phone":"+31 316 528 500",
    "sg:postcode":"6923 BL",
    "sg:province":"Gelderland",
    "wof:name":"Bloemkwekerij Koos Aaldering Bv",
    "wof:placetype":"venue"
},
  "geometry": {"coordinates":[6.03476,51.915878],"type":"Point"}
}