{
  "type": "Feature",
  "properties": {
    "iso:country":"NL",
    "sg:address":"Gerestein 53",
    "sg:city":"Tiel",
    "sg:orig_category":"Kunststof Ramen",
    "sg:phone":"+31 344 626 163",
    "sg:postcode":"4003 GE",
    "sg:province":"Gelderland",
    "sg:website":"http://www.schueco.de",
    "wof:name":"Fenestrae Kozijntechniek",
    "wof:placetype":"venue"
},
  "geometry": {"coordinates":[5.406398,51.898163],"type":"Point"}
}