{
  "type": "Feature",
  "properties": {
    "iso:country":"NL",
    "sg:address":"T Voorhuis 52",
    "sg:city":"Veenendaal",
    "sg:orig_category":"Vertalers",
    "sg:phone":"+31 318 543 697",
    "sg:postcode":"3902 CC",
    "sg:province":"Utrecht",
    "wof:name":"Sretenovic",
    "wof:placetype":"venue"
},
  "geometry": {"coordinates":[5.570339,52.033932],"type":"Point"}
}