{
  "type": "Feature",
  "properties": {
    "iso:country":"NL",
    "sg:address":"A V Burenstr 17",
    "sg:city":"Leiderdorp",
    "sg:orig_category":"Journalisten Freelance",
    "sg:phone":"+31 71 541 5675",
    "sg:postcode":"2351 RM",
    "sg:province":"Zuid-Holland",
    "wof:name":"Senli",
    "wof:placetype":"venue"
},
  "geometry": {"coordinates":[4.534218,52.156174],"type":"Point"}
}