{
  "type": "Feature",
  "properties": {
    "addr:full":"Ugchelseweg 107 Apeldoorn Gelderland 7335 JT",
    "addr:housenumber":"107",
    "addr:postcode":"7335 jt",
    "addr:street":"Ugchelseweg;Gelderland",
    "iso:country":"NL",
    "sg:address":"Ugchelseweg 107",
    "sg:city":"Apeldoorn",
    "sg:orig_category":"Boekhouders",
    "sg:phone":"+31 55 533 0808",
    "sg:postcode":"7335 JT",
    "sg:province":"Gelderland",
    "wof:name":"Administratiekantoor Arendse",
    "wof:placetype":"venue"
},
  "geometry": {"coordinates":[5.94532,52.191452],"type":"Point"}
}