{
  "type": "Feature",
  "properties": {
    "addr:full":"Nieuwstraat 2 Vrouwenpolder Zeeland 4354 AW",
    "addr:housenumber":"2",
    "addr:postcode":"4354 aw",
    "addr:street":"Nieuwstraat",
    "iso:country":"NL",
    "sg:address":"Nieuwstraat 2",
    "sg:city":"Vrouwenpolder",
    "sg:orig_category":"Modellenbureaus",
    "sg:phone":"+31 118 596 161",
    "sg:postcode":"4354 AW",
    "sg:province":"Zeeland",
    "wof:name":"My Way Models",
    "wof:placetype":"venue"
},
  "geometry": {"coordinates":[3.617037,51.575626],"type":"Point"}
}