{
  "type": "Feature",
  "properties": {
    "addr:full":"Nyverheidswg 3 Goor Overijssel 7471 EW",
    "addr:housenumber":"3",
    "addr:postcode":"7471 ew",
    "addr:street":"Nyverheidswg",
    "iso:country":"NL",
    "sg:address":"Nyverheidswg 3",
    "sg:city":"Goor",
    "sg:orig_category":"Verenigingen En Stichtingen",
    "sg:phone":"+31 547 274 159",
    "sg:postcode":"7471 EW",
    "sg:province":"Overijssel",
    "wof:name":"Goorse School En Volksfeesten",
    "wof:placetype":"venue"
},
  "geometry": {"coordinates":[6.587045,52.234573],"type":"Point"}
}