{
  "type": "Feature",
  "properties": {
    "addr:full":"Haarweg 2 Diever Drenthe 7981 LW",
    "addr:housenumber":"2",
    "addr:postcode":"7981 lw",
    "addr:street":"Haarweg",
    "iso:country":"NL",
    "sg:address":"Haarweg 2",
    "sg:city":"Diever",
    "sg:orig_category":"Kampeerterreinen",
    "sg:phone":"+31 521 591 644",
    "sg:postcode":"7981 LW",
    "sg:province":"Drenthe",
    "wof:name":"Camping Diever",
    "wof:placetype":"venue"
},
  "geometry": {"coordinates":[6.3201098442,52.8670158386],"type":"Point"}
}