{
  "type": "Feature",
  "properties": {
    "iso:country":"NL",
    "sg:address":"Haarweg 2",
    "sg:city":"Diever",
    "sg:orig_category":"Kampeerterreinen",
    "sg:phone":"+31 521 591 644",
    "sg:postcode":"7981 LW",
    "sg:province":"Drenthe",
    "wof:name":"Camping Diever",
    "wof:placetype":"venue"
},
  "geometry": {"coordinates":[6.3201098442,52.8670158386],"type":"Point"}
}