{
  "type": "Feature",
  "properties": {
    "addr:full":"Vosseleane 4 Woudsend Provincie Friesland 8551 RA",
    "addr:housenumber":"4",
    "addr:postcode":"8551 ra",
    "addr:street":"Vosseleane;Provincie Friesland",
    "iso:country":"NL",
    "sg:address":"Vosseleane 4",
    "sg:city":"Woudsend",
    "sg:orig_category":"Autokeuringen",
    "sg:phone":"+31 514 591 236",
    "sg:postcode":"8551 RA",
    "sg:province":"Provincie Friesland",
    "wof:name":"Garage Bote Pietersma",
    "wof:placetype":"venue"
},
  "geometry": {"coordinates":[5.631536,52.943153],"type":"Point"}
}