{
  "type": "Feature",
  "properties": {
    "iso:country":"NL",
    "sg:address":"Axelsestraat 12",
    "sg:city":"Zaamslag",
    "sg:orig_category":"Verlichting And Huishoudartikelen",
    "sg:phone":"+31 115 431 261",
    "sg:postcode":"4543 CJ",
    "sg:province":"Zeeland",
    "wof:name":"Dees Textiel En Interieur",
    "wof:placetype":"venue"
},
  "geometry": {"coordinates":[3.912431,51.311371],"type":"Point"}
}