{
  "type": "Feature",
  "properties": {
    "addr:full":"Axelsestraat 12 Zaamslag Zeeland 4543 CJ",
    "addr:housenumber":"12",
    "addr:postcode":"4543 cj",
    "addr:street":"Axelsestraat",
    "iso:country":"NL",
    "sg:address":"Axelsestraat 12",
    "sg:city":"Zaamslag",
    "sg:orig_category":"Verlichting And Huishoudartikelen",
    "sg:phone":"+31 115 431 261",
    "sg:postcode":"4543 CJ",
    "sg:province":"Zeeland",
    "wof:name":"Dees Textiel En Interieur",
    "wof:placetype":"venue"
},
  "geometry": {"coordinates":[3.912431,51.311371],"type":"Point"}
}