{
  "type": "Feature",
  "properties": {
    "addr:full":"Spoorven 16 Veghel North Brabant 5464 PA",
    "addr:housenumber":"16",
    "addr:postcode":"5464 pa",
    "addr:street":"Spoorven",
    "iso:country":"NL",
    "sg:address":"Spoorven 16",
    "sg:city":"Veghel",
    "sg:orig_category":"Verzekeringen - Verzekeringskantoren",
    "sg:phone":"+31 413 377 253",
    "sg:postcode":"5464 PA",
    "sg:province":"North Brabant",
    "wof:name":"Berendsen",
    "wof:placetype":"venue"
},
  "geometry": {"coordinates":[5.548245,51.628334],"type":"Point"}
}