{
  "type": "Feature",
  "properties": {
    "addr:full":"Genderdreef 19 Steensel Noord-Brabant 5524 AD",
    "addr:housenumber":"19",
    "addr:postcode":"5524 ad",
    "addr:street":"Genderdreef",
    "iso:country":"NL",
    "sg:address":"Genderdreef 19",
    "sg:city":"Steensel",
    "sg:classifiers":[
        {
            "category":"Food & Beverages",
            "subcategory":"Fruits & Vegetables",
            "type":"Retail Goods"
        }
    ],
    "sg:phone":"+31 497 514 249",
    "sg:postcode":"5524 AD",
    "sg:province":"Noord-Brabant",
    "sg:tags":[
        "groenten"
    ],
    "wof:name":"H. Wintermans",
    "wof:placetype":"venue"
},
  "geometry": {"coordinates":[5.352137,51.379349],"type":"Point"}
}