{
  "type": "Feature",
  "properties": {
    "iso:country":"NL",
    "sg:address":"Marktplein 12",
    "sg:city":"Winschoten",
    "sg:orig_category":"Bedrijfscatering",
    "sg:phone":"+31 597 417 423",
    "sg:postcode":"9671  A",
    "sg:province":"Groningen",
    "wof:name":"Le Gateau",
    "wof:placetype":"venue"
},
  "geometry": {"coordinates":[7.041662,53.14241],"type":"Point"}
}