{
  "type": "Feature",
  "properties": {
    "iso:country":"NL",
    "sg:address":"Javastr 34",
    "sg:city":"Oegstgeest",
    "sg:orig_category":"Administratie- En Boekhoudkantoren",
    "sg:phone":"+31 71 515 0112",
    "sg:postcode":"2341 XL",
    "sg:province":"Zuid-Holland",
    "wof:name":"Maduro",
    "wof:placetype":"venue"
},
  "geometry": {"coordinates":[4.455006,52.179646],"type":"Point"}
}