{
  "type": "Feature",
  "properties": {
    "addr:full":"Hazelaarstr 17 Woerden South Holland 3442 EM",
    "addr:housenumber":"17",
    "addr:postcode":"3442 em",
    "addr:street":"Hazelaarstr",
    "iso:country":"NL",
    "sg:address":"Hazelaarstr 17",
    "sg:city":"Woerden",
    "sg:orig_category":"Landmeetkundige Bureaus",
    "sg:phone":"+31 348 432 252",
    "sg:postcode":"3442 EM",
    "sg:province":"South Holland",
    "sg:website":"http://www.oostrum.nl",
    "wof:name":"Oostrum Woerden, Van",
    "wof:placetype":"venue"
},
  "geometry": {"coordinates":[4.874488,52.082741],"type":"Point"}
}