{
  "type": "Feature",
  "properties": {
    "addr:full":"Markt 4 Bredevoort Gelderland 7126 AZ",
    "addr:housenumber":"4",
    "addr:postcode":"7126",
    "addr:street":"Markt;Gelderland",
    "iso:country":"NL",
    "sg:address":"Markt 4",
    "sg:city":"Bredevoort",
    "sg:orig_category":"Boekhandels",
    "sg:phone":"+31 543 451 898",
    "sg:postcode":"7126 AZ",
    "sg:province":"Gelderland",
    "wof:name":"Boekenkring",
    "wof:placetype":"venue"
},
  "geometry": {"coordinates":[6.617284,51.943359],"type":"Point"}
}