{
  "type": "Feature",
  "properties": {
    "addr:full":"Avenhil 34 Heinenoord South Holland 3274 CT",
    "addr:housenumber":"34",
    "addr:postcode":"3274 ct",
    "addr:street":"Avenhil",
    "iso:country":"NL",
    "sg:address":"Avenhil 34",
    "sg:city":"Heinenoord",
    "sg:orig_category":"Afslankinstituten",
    "sg:phone":"+31 186 602 694",
    "sg:postcode":"3274 CT",
    "sg:province":"South Holland",
    "wof:name":"Vermaat-Bouman, A M",
    "wof:placetype":"venue"
},
  "geometry": {"coordinates":[4.483407,51.827209],"type":"Point"}
}