{
  "type": "Feature",
  "properties": {
    "addr:full":"Rompert Centrum 32 S Hertogenbosch Noord-Brabant 5233 RE",
    "addr:housenumber":"32",
    "addr:postcode":"5233 re",
    "addr:street":"Rompert Centrum;S Hertogenbosch",
    "iso:country":"NL",
    "sg:address":"Rompert Centrum 32",
    "sg:city":"S Hertogenbosch",
    "sg:orig_category":"Artiesten/Gezelschappen",
    "sg:phone":"+31 73 648 0598",
    "sg:postcode":"5233 RE",
    "sg:province":"Noord-Brabant",
    "sg:website":"http://www.totaaltheater.com",
    "wof:name":"Totaal Theater",
    "wof:placetype":"venue"
},
  "geometry": {"coordinates":[5.311927,51.711514],"type":"Point"}
}