{
  "type": "Feature",
  "properties": {
    "addr:full":"Vyftien Morgen 21 Veenendaal Utrecht 3901 HA",
    "addr:housenumber":"21",
    "addr:postcode":"3901 ha",
    "addr:street":"Morgen",
    "iso:country":"NL",
    "sg:address":"Vyftien Morgen 21",
    "sg:city":"Veenendaal",
    "sg:orig_category":"Bibliotheken En Leeszalen Openbare",
    "sg:phone":"+31 318 523 090",
    "sg:postcode":"3901 HA",
    "sg:province":"Utrecht",
    "sg:website":"http://www.obveenendaal.nl",
    "wof:name":"Openb Bibliotheek",
    "wof:placetype":"venue"
},
  "geometry": {"coordinates":[5.55418,52.024902],"type":"Point"}
}