{
  "type": "Feature",
  "properties": {
    "addr:full":"Ambachtsweg 19 Eindhoven Noord-Brabant 5627 BZ",
    "addr:housenumber":"19",
    "addr:postcode":"5627 bz",
    "addr:street":"Ambachtsweg",
    "iso:country":"NL",
    "sg:address":"Ambachtsweg 19",
    "sg:city":"Eindhoven",
    "sg:orig_category":"Elektronische Bedrijfsinstallaties",
    "sg:phone":"+31 40 248 3020",
    "sg:postcode":"5627 BZ",
    "sg:province":"Noord-Brabant",
    "wof:name":"C & K Systems Europe Bv",
    "wof:placetype":"venue"
},
  "geometry": {"coordinates":[5.439301,51.478413],"type":"Point"}
}