{
  "type": "Feature",
  "properties": {
    "addr:full":"Badhuisstraat 230 Scheveningen Zuid-Holland 2584 HN",
    "addr:housenumber":"230",
    "addr:postcode":"2584 hn",
    "addr:street":"Badhuisstraat",
    "iso:country":"NL",
    "sg:address":"Badhuisstraat 230",
    "sg:city":"Scheveningen",
    "sg:orig_category":"Glaszetten",
    "sg:phone":"+31 70 355 0488",
    "sg:postcode":"2584 HN",
    "sg:province":"Zuid-Holland",
    "wof:name":"Scheveningse Glashandel",
    "wof:placetype":"venue"
},
  "geometry": {"coordinates":[4.279263,52.103287],"type":"Point"}
}