{
  "type": "Feature",
  "properties": {
    "iso:country":"NL",
    "sg:address":"Nieuwe Hemweg 4",
    "sg:city":"Amsterdam",
    "sg:orig_category":"Kantoorartikelen",
    "sg:phone":"+31 20 684 3838",
    "sg:postcode":"1013 BG",
    "sg:province":"Noord-Holland",
    "wof:name":"Ate Telmac Kantoorinstallaties Bv",
    "wof:placetype":"venue"
},
  "geometry": {"coordinates":[4.8665719032,52.3948440552],"type":"Point"}
}