{
  "type": "Feature",
  "properties": {
    "iso:country":"NL",
    "sg:address":"Kerkplein 6",
    "sg:city":"Ovezande",
    "sg:orig_category":"Banken And Kredietinstellingen",
    "sg:phone":"+31 113 655 216",
    "sg:postcode":"4441 AG",
    "sg:province":"Zeeland",
    "wof:name":"Rabobank",
    "wof:placetype":"venue"
},
  "geometry": {"coordinates":[3.821803,51.428307],"type":"Point"}
}