{
  "type": "Feature",
  "properties": {
    "addr:full":"Dommer V Poldersveldtwg 295 Nijmegen Gelderland 6523 CW",
    "addr:housenumber":"295",
    "addr:postcode":"6523 cw",
    "addr:street":"Gelderland",
    "iso:country":"NL",
    "sg:address":"Dommer V Poldersveldtwg 295",
    "sg:city":"Nijmegen",
    "sg:orig_category":"Verzekeringen",
    "sg:phone":"+31 24 324 1144",
    "sg:postcode":"6523 CW",
    "sg:province":"Gelderland",
    "wof:name":"Buro Brakkenstein Bv",
    "wof:placetype":"venue"
},
  "geometry": {"coordinates":[5.881711,51.833046],"type":"Point"}
}