{
  "type": "Feature",
  "properties": {
    "addr:full":"Postbus 11040 'S-Hertogenbosch North Brabant 5200 EA",
    "addr:housenumber":"11040",
    "addr:postcode":"5200 ea",
    "addr:street":"Postbus",
    "iso:country":"NL",
    "sg:address":"Postbus 11040",
    "sg:city":"'S-Hertogenbosch",
    "sg:orig_category":"Omroep",
    "sg:phone":"+31 73 644 1155",
    "sg:postcode":"5200 EA",
    "sg:province":"North Brabant",
    "wof:name":"Boschtion",
    "wof:placetype":"venue"
},
  "geometry": {"coordinates":[5.29824,51.69075],"type":"Point"}
}