{
  "type": "Feature",
  "properties": {
    "addr:full":"Morsinkhofwg 36 Haaksbergen Overijssel 7481 TT",
    "addr:housenumber":"36",
    "addr:postcode":"7481 tt",
    "addr:street":"Morsinkhofwg",
    "iso:country":"NL",
    "sg:address":"Morsinkhofwg 36",
    "sg:city":"Haaksbergen",
    "sg:orig_category":"Bloemen En Planten - Groothandel",
    "sg:phone":"+31 53 572 7046",
    "sg:postcode":"7481 TT",
    "sg:province":"Overijssel",
    "wof:name":"Westerweel, J L",
    "wof:placetype":"venue"
},
  "geometry": {"coordinates":[6.743613,52.143105],"type":"Point"}
}