{
  "type": "Feature",
  "properties": {
    "iso:country":"NL",
    "sg:address":"Oude Veer 17",
    "sg:city":"Papendrecht",
    "sg:orig_category":"Meubelzaken, Woning- And Keukeninrichting",
    "sg:phone":"+31 78 615 1464",
    "sg:postcode":"3351 AH",
    "sg:province":"Zuid-Holland",
    "wof:name":"Bakker Wonen En Slapen Bv",
    "wof:placetype":"venue"
},
  "geometry": {"coordinates":[4.68304,51.825054],"type":"Point"}
}