{
  "type": "Feature",
  "properties": {
    "addr:full":"Wagenwg 1 Haarlem Noord-Holland 2012 NA",
    "addr:housenumber":"1",
    "addr:postcode":"2012 na",
    "addr:street":"Wagenwg",
    "iso:country":"NL",
    "sg:address":"Wagenwg 1",
    "sg:city":"Haarlem",
    "sg:orig_category":"Meubelen",
    "sg:phone":"+31 23 531 9195",
    "sg:postcode":"2012 NA",
    "sg:province":"Noord-Holland",
    "wof:name":"Terstal Interieurs Bv",
    "wof:placetype":"venue"
},
  "geometry": {"coordinates":[4.630082,52.374226],"type":"Point"}
}