{
  "type": "Feature",
  "properties": {
    "addr:full":"A Jacobsplnts 101 Voorschoten Zuid-Holland 2253 RP",
    "addr:housenumber":"101",
    "addr:postcode":"2253 rp",
    "iso:country":"NL",
    "sg:address":"A Jacobsplnts 101",
    "sg:city":"Voorschoten",
    "sg:orig_category":"Kinderopvang",
    "sg:phone":"+31 71 576 4491",
    "sg:postcode":"2253 RP",
    "sg:province":"Zuid-Holland",
    "wof:name":"Bibelebon",
    "wof:placetype":"venue"
},
  "geometry": {"coordinates":[4.44429,52.124825],"type":"Point"}
}