{
  "type": "Feature",
  "properties": {
    "addr:full":"Energiewg 9 Rotterdam Zuid-Holland 3041 JC",
    "addr:housenumber":"9",
    "addr:postcode":"3041 jc",
    "addr:street":"Energiewg",
    "iso:country":"NL",
    "sg:address":"Energiewg 9",
    "sg:city":"Rotterdam",
    "sg:orig_category":"Fitnesscentra",
    "sg:phone":"+31 10 245 1670",
    "sg:postcode":"3041 JC",
    "sg:province":"Zuid-Holland",
    "wof:name":"Cannons Akragon",
    "wof:placetype":"venue"
},
  "geometry": {"coordinates":[4.440494,51.926811],"type":"Point"}
}