{
  "type": "Feature",
  "properties": {
    "addr:full":"Voorstr 14 Stavoren Friesland 8715 JA",
    "addr:housenumber":"14",
    "addr:postcode":"8715 ja",
    "addr:street":"Voorstr",
    "iso:country":"NL",
    "sg:address":"Voorstr 14",
    "sg:city":"Stavoren",
    "sg:orig_category":"Watersportartikelen",
    "sg:phone":"+31 514 682 227",
    "sg:postcode":"8715 JA",
    "sg:province":"Friesland",
    "wof:name":"Boer, Max De",
    "wof:placetype":"venue"
},
  "geometry": {"coordinates":[5.357612133,52.8844642639],"type":"Point"}
}