{
  "type": "Feature",
  "properties": {
    "addr:full":"Romynstr 22 Lisse Zuid-Holland 2161 CP",
    "addr:housenumber":"22",
    "addr:postcode":"2161 cp",
    "addr:street":"Romynstr",
    "iso:country":"NL",
    "sg:address":"Romynstr 22",
    "sg:city":"Lisse",
    "sg:orig_category":"Open Haarden",
    "sg:phone":"+31 6 40032304",
    "sg:postcode":"2161 CP",
    "sg:province":"Zuid-Holland",
    "wof:name":"Keizer",
    "wof:placetype":"venue"
},
  "geometry": {"coordinates":[4.552546,52.257221],"type":"Point"}
}