{
  "type": "Feature",
  "properties": {
    "addr:full":"Korvetstraat 76 Den Helder North Holland 1784 MS",
    "addr:housenumber":"76",
    "addr:postcode":"1784 ms",
    "addr:street":"Korvetstraat",
    "iso:country":"NL",
    "sg:address":"Korvetstraat 76",
    "sg:city":"Den Helder",
    "sg:orig_category":"Vloer- And Wandbedekkingen",
    "sg:phone":"+31 223 632 196",
    "sg:postcode":"1784 MS",
    "sg:province":"North Holland",
    "wof:name":"C.J. Vermeer",
    "wof:placetype":"venue"
},
  "geometry": {"coordinates":[4.744609,52.936424],"type":"Point"}
}