{
  "type": "Feature",
  "properties": {
    "addr:full":"Bosrand 42 Putten Gelderland 3881 GV",
    "addr:housenumber":"42",
    "addr:postcode":"3881 gv",
    "addr:street":"Bosrand;Gelderland",
    "iso:country":"NL",
    "sg:address":"Bosrand 42",
    "sg:city":"Putten",
    "sg:orig_category":"Adviesbureaus Financieel",
    "sg:phone":"+31 341 353 500",
    "sg:postcode":"3881 GV",
    "sg:province":"Gelderland",
    "wof:name":"Fleischeuer",
    "wof:placetype":"venue"
},
  "geometry": {"coordinates":[5.618118,52.260212],"type":"Point"}
}