{
  "type": "Feature",
  "properties": {
    "iso:country":"NL",
    "sg:address":"Kerkln 37",
    "sg:city":"Heinkenszand",
    "sg:orig_category":"Onderwijsmateriaal",
    "sg:phone":"+31 113 568 047",
    "sg:postcode":"4451 BE",
    "sg:province":"BE.04",
    "wof:name":"Eoz",
    "wof:placetype":"venue"
},
  "geometry": {"coordinates":[5.554621,50.687103],"type":"Point"}
}