{
  "type": "Feature",
  "properties": {
    "iso:country":"NL",
    "sg:address":"Witte De Withstraat 87",
    "sg:city":"Rotterdam",
    "sg:orig_category":"Kappers",
    "sg:phone":"+31 10 404 5502",
    "sg:postcode":"3012 BN",
    "sg:province":"South Holland",
    "wof:name":"Dameskapsalon Juffrouw Corry",
    "wof:placetype":"venue"
},
  "geometry": {"coordinates":[4.4753680229,51.915309906],"type":"Point"}
}