{
  "type": "Feature",
  "properties": {
    "addr:full":"Oudedk 245 Rotterdam South Holland 3061 AH",
    "addr:housenumber":"245",
    "addr:postcode":"3061 ah",
    "iso:country":"NL",
    "sg:address":"Oudedk 245",
    "sg:city":"Rotterdam",
    "sg:orig_category":"Loodgieters",
    "sg:phone":"+31 10 452 2393",
    "sg:postcode":"3061 AH",
    "sg:province":"South Holland",
    "wof:name":"Vermeulen, L C",
    "wof:placetype":"venue"
},
  "geometry": {"coordinates":[4.506391,51.929024],"type":"Point"}
}