{
  "type": "Feature",
  "properties": {
    "addr:full":"Hoofdwg 329 Hoofddorp Noord-Holland 2131 LL",
    "addr:housenumber":"329",
    "addr:postcode":"2131 ll",
    "iso:country":"NL",
    "sg:address":"Hoofdwg 329",
    "sg:city":"Hoofddorp",
    "sg:orig_category":"Touringcars",
    "sg:phone":"+31 23 555 2175",
    "sg:postcode":"2131 LL",
    "sg:province":"Noord-Holland",
    "sg:website":"http://www.oad.nl",
    "wof:name":"Oad-Van Dam",
    "wof:placetype":"venue"
},
  "geometry": {"coordinates":[4.730222,52.332195],"type":"Point"}
}