{
  "type": "Feature",
  "properties": {
    "addr:full":"Hogestukke 4 Eibergen Gelderland 7152 KM",
    "addr:housenumber":"4",
    "addr:postcode":"7152",
    "addr:street":"Hogestukke;Gelderland;Km",
    "iso:country":"NL",
    "sg:address":"Hogestukke 4",
    "sg:city":"Eibergen",
    "sg:orig_category":"Webdesign Bureaus",
    "sg:phone":"+31 545 474 134",
    "sg:postcode":"7152 KM",
    "sg:province":"Gelderland",
    "sg:website":"http://www.maroz.nl",
    "wof:name":"Maroz",
    "wof:placetype":"venue"
},
  "geometry": {"coordinates":[6.6646099091,52.1008758545],"type":"Point"}
}