{
  "type": "Feature",
  "properties": {
    "addr:full":"Olmenlaan 6A Leusden Utrecht 3833 AV",
    "addr:housenumber":"6a",
    "addr:postcode":"3833 av",
    "addr:street":"Olmenlaan",
    "iso:country":"NL",
    "sg:address":"Olmenlaan 6A",
    "sg:city":"Leusden",
    "sg:orig_category":"Bedrijfsopleidingen",
    "sg:phone":"+31 33 434 5080",
    "sg:postcode":"3833 AV",
    "sg:province":"Utrecht",
    "sg:website":"http://www.segment-groep.nl",
    "wof:name":"Segment Groep",
    "wof:placetype":"venue"
},
  "geometry": {"coordinates":[5.424259,52.14098],"type":"Point"}
}