{
  "type": "Feature",
  "properties": {
    "iso:country":"NL",
    "sg:address":"Goorsestr 89",
    "sg:city":"Haaksbergen",
    "sg:orig_category":"Ballonvaarten En -Reclame",
    "sg:phone":"+31 53 572 4112",
    "sg:postcode":"7482 CC",
    "sg:province":"NL.08",
    "sg:website":"http://www.geocities.com/ballonvaren",
    "wof:name":"Achterberg Ballonvaarten",
    "wof:placetype":"venue"
},
  "geometry": {"coordinates":[6.733145,52.160412],"type":"Point"}
}