{
  "type": "Feature",
  "properties": {
    "addr:full":"Schoolstraat 8 Hollum Friesland 9161 BE",
    "addr:housenumber":"8",
    "addr:postcode":"9161",
    "addr:street":"Schoolstraat",
    "iso:country":"NL",
    "sg:address":"Schoolstraat 8",
    "sg:city":"Hollum",
    "sg:classifiers":[
        {
            "category":"Fast Food",
            "type":"Food & Drink"
        }
    ],
    "sg:phone":"+31 519 554 164",
    "sg:postcode":"9161 BE",
    "sg:province":"Friesland",
    "sg:tags":[
        "afhaal",
        "restaurant"
    ],
    "wof:name":"Pizzeria Hidde Kat",
    "wof:placetype":"venue"
},
  "geometry": {"coordinates":[5.639765,53.439175],"type":"Point"}
}