{
  "type": "Feature",
  "properties": {
    "addr:full":"Kievithof 3 Lekkerkerk Zuid-Holland 2941 PA",
    "addr:housenumber":"3",
    "addr:postcode":"2941 pa",
    "addr:street":"Kievithof",
    "iso:country":"NL",
    "sg:address":"Kievithof 3",
    "sg:city":"Lekkerkerk",
    "sg:orig_category":"Adviesbureaus Bedrijfsorganisatie",
    "sg:phone":"+31 180 661 975",
    "sg:postcode":"2941 PA",
    "sg:province":"Zuid-Holland",
    "wof:name":"Demast Bv",
    "wof:placetype":"venue"
},
  "geometry": {"coordinates":[4.686051,51.903107],"type":"Point"}
}