{
  "type": "Feature",
  "properties": {
    "addr:full":"Leeuwerikstraat 28 Varsseveld Gelderland 7051 XG",
    "addr:housenumber":"28",
    "addr:postcode":"7051 xg",
    "addr:street":"Leeuwerikstraat;Gelderland",
    "iso:country":"NL",
    "sg:address":"Leeuwerikstraat 28",
    "sg:city":"Varsseveld",
    "sg:classifiers":[
        {
            "category":"Professional",
            "subcategory":"Accounting & Tax Preparation",
            "type":"Services"
        }
    ],
    "sg:phone":"+31 315 230 234",
    "sg:postcode":"7051 XG",
    "sg:province":"Gelderland",
    "sg:tags":[
        "accountant"
    ],
    "wof:name":"Accountantskantoor Endeman Bv",
    "wof:placetype":"venue"
},
  "geometry": {"coordinates":[6.456551,51.949165],"type":"Point"}
}