{
  "type": "Feature",
  "properties": {
    "addr:full":"Jacoba Van Beierenlaan 189 Delft South Holland 2613 JG",
    "addr:housenumber":"189",
    "addr:postcode":"2613 jg",
    "addr:street":"Jacoba Van Beierenlaan",
    "iso:country":"NL",
    "sg:address":"Jacoba Van Beierenlaan 189",
    "sg:city":"Delft",
    "sg:orig_category":"Diverse Grafische Activiteiten",
    "sg:phone":"+31 15 213 1130",
    "sg:postcode":"2613 JG",
    "sg:province":"South Holland",
    "wof:name":"Icad",
    "wof:placetype":"venue"
},
  "geometry": {"coordinates":[4.349918,52.001831],"type":"Point"}
}