{
  "type": "Feature",
  "properties": {
    "addr:full":"Innsbruckwg 250 Rotterdam South Holland 3047 AH",
    "addr:housenumber":"250",
    "addr:postcode":"3047 ah",
    "iso:country":"NL",
    "sg:address":"Innsbruckwg 250",
    "sg:city":"Rotterdam",
    "sg:orig_category":"Verzekeringen - Verzekeringskantoren",
    "sg:phone":"+31 10 206 8520",
    "sg:postcode":"3047 AH",
    "sg:province":"South Holland",
    "sg:website":"http://www.heintz-rotterdam.nl",
    "wof:name":"Heintz Rotterdam, A J M G",
    "wof:placetype":"venue"
},
  "geometry": {"coordinates":[4.414068,51.940975],"type":"Point"}
}