{
  "type": "Feature",
  "properties": {
    "addr:full":"Cobbejennegats 1A Gulpen Limburg 6271 BC",
    "addr:housenumber":"1a",
    "addr:postcode":"6271 bc",
    "addr:street":"Cobbejennegats",
    "iso:country":"NL",
    "sg:address":"Cobbejennegats 1A",
    "sg:city":"Gulpen",
    "sg:orig_category":"Fietshandelaren",
    "sg:phone":"+31 43 450 4000",
    "sg:postcode":"6271 BC",
    "sg:province":"Limburg",
    "wof:name":"Jef Abels Bikes",
    "wof:placetype":"venue"
},
  "geometry": {"coordinates":[5.890835,50.816368],"type":"Point"}
}