{
  "type": "Feature",
  "properties": {
    "addr:full":"Zandstraat 7 Koewacht Zeeland 4576 BV",
    "addr:housenumber":"7",
    "addr:postcode":"4576 bv",
    "addr:street":"Zandstraat",
    "iso:country":"NL",
    "sg:address":"Zandstraat 7",
    "sg:city":"Koewacht",
    "sg:orig_category":"Goederenvervoer Over De Weg",
    "sg:phone":"+31 114 361 460",
    "sg:postcode":"4576 BV",
    "sg:province":"Zeeland",
    "wof:name":"Transportbedrijf J.E. Thijs",
    "wof:placetype":"venue"
},
  "geometry": {"coordinates":[3.947424,51.231396],"type":"Point"}
}