{
  "type": "Feature",
  "properties": {
    "addr:full":"Schokkerringweg 18 Ens Flevoland 8307 RD",
    "addr:housenumber":"18",
    "addr:postcode":"8307",
    "addr:street":"Schokkerringweg;Flevoland;Rd",
    "iso:country":"NL",
    "sg:address":"Schokkerringweg 18",
    "sg:city":"Ens",
    "sg:orig_category":"Bloemen And Planten",
    "sg:phone":"+31 527 253 059",
    "sg:postcode":"8307 RD",
    "sg:province":"Flevoland",
    "wof:name":"Vof Hoveniersbedrijf Dohmen",
    "wof:placetype":"venue"
},
  "geometry": {"coordinates":[5.820279,52.637733],"type":"Point"}
}