{
  "type": "Feature",
  "properties": {
    "addr:full":"Wesseler Nering 31 Enschede Overijssel 7544 JC",
    "addr:housenumber":"31",
    "addr:postcode":"7544 jc",
    "addr:street":"Nering",
    "iso:country":"NL",
    "sg:address":"Wesseler Nering 31",
    "sg:city":"Enschede",
    "sg:orig_category":"Bloemen En Planten",
    "sg:phone":"+31 53 476 3817",
    "sg:postcode":"7544 JC",
    "sg:province":"Overijssel",
    "sg:website":"http://www.huve-bloemisten.nl",
    "wof:name":"Le Tournesol",
    "wof:placetype":"venue"
},
  "geometry": {"coordinates":[6.878719,52.191959],"type":"Point"}
}