{
  "type": "Feature",
  "properties": {
    "addr:full":"Haarlemmerweg 26 Leiden Zuid-Holland 2316 AB",
    "addr:housenumber":"26",
    "addr:postcode":"2316 ab",
    "addr:street":"Haarlemmerweg",
    "iso:country":"NL",
    "sg:address":"Haarlemmerweg 26",
    "sg:city":"Leiden",
    "sg:classifiers":[
        {
            "category":"Bakery",
            "type":"Food & Drink"
        }
    ],
    "sg:phone":"+31 71 522 4200",
    "sg:postcode":"2316 AB",
    "sg:province":"Zuid-Holland",
    "sg:tags":[
        "brood",
        "banket"
    ],
    "wof:name":"J. Bakker",
    "wof:placetype":"venue"
},
  "geometry": {"coordinates":[4.490236,52.166641],"type":"Point"}
}