{
  "type": "Feature",
  "properties": {
    "iso:country":"NL",
    "sg:address":"Postbus 43",
    "sg:city":"Huizen",
    "sg:orig_category":"Huidverzorgingsartikelen",
    "sg:phone":"+31 35 526 1520",
    "sg:postcode":"1270 AA",
    "sg:province":"Noord-Holland",
    "wof:name":"Veraforte",
    "wof:placetype":"venue"
},
  "geometry": {"coordinates":[5.23421,52.29504],"type":"Point"}
}