{
  "type": "Feature",
  "properties": {
    "addr:full":"Gouwestr 6 Utrecht Utrecht 3522 CJ",
    "addr:housenumber":"6",
    "addr:postcode":"3522 cj",
    "addr:street":"Gouwestr",
    "iso:country":"NL",
    "sg:address":"Gouwestr 6",
    "sg:city":"Utrecht",
    "sg:orig_category":"Vertalers",
    "sg:phone":"+31 30 288 7967",
    "sg:postcode":"3522 CJ",
    "sg:province":"Utrecht",
    "sg:website":"http://www.braches.nl",
    "wof:name":"Braches",
    "wof:placetype":"venue"
},
  "geometry": {"coordinates":[5.112963,52.075329],"type":"Point"}
}