{
  "type": "Feature",
  "properties": {
    "addr:full":"Gravinnestraat 10 Wageningen Gelderland 6707 EX",
    "addr:housenumber":"10",
    "addr:postcode":"6707 ex",
    "addr:street":"Gravinnestraat;Gelderland",
    "iso:country":"NL",
    "sg:address":"Gravinnestraat 10",
    "sg:city":"Wageningen",
    "sg:orig_category":"Boekhouders",
    "sg:phone":"+31 317 424 025",
    "sg:postcode":"6707 EX",
    "sg:province":"Gelderland",
    "wof:name":"Boekhoudbureau Ziezo",
    "wof:placetype":"venue"
},
  "geometry": {"coordinates":[5.667277,51.972584],"type":"Point"}
}