{
  "type": "Feature",
  "properties": {
    "addr:full":"V Leeuwenhoekln 408 Zoetermeer Zuid-Holland 2713 RK",
    "addr:housenumber":"408",
    "addr:postcode":"2713 rk",
    "iso:country":"NL",
    "sg:address":"V Leeuwenhoekln 408",
    "sg:city":"Zoetermeer",
    "sg:orig_category":"Juridische Adviseurs",
    "sg:phone":"+31 79 316 0378",
    "sg:postcode":"2713 RK",
    "sg:province":"Zuid-Holland",
    "wof:name":"Eind",
    "wof:placetype":"venue"
},
  "geometry": {"coordinates":[4.488925,52.06308],"type":"Point"}
}