{
  "type": "Feature",
  "properties": {
    "addr:full":"Valkenhorst 23 Valkenburg Zh Zuid-Holland 2235 BX",
    "addr:housenumber":"23",
    "addr:postcode":"2235 bx",
    "addr:street":"Valkenhorst",
    "iso:country":"NL",
    "sg:address":"Valkenhorst 23",
    "sg:city":"Valkenburg Zh",
    "sg:orig_category":"Bloemen En Planten - Groothandel",
    "sg:phone":"+31 71 402 8747",
    "sg:postcode":"2235 BX",
    "sg:province":"Zuid-Holland",
    "wof:name":"Ravensbergen, W",
    "wof:placetype":"venue"
},
  "geometry": {"coordinates":[4.42726,52.179909],"type":"Point"}
}