{
  "type": "Feature",
  "properties": {
    "iso:country":"NL",
    "sg:address":"Rykswg 189",
    "sg:city":"Malden",
    "sg:orig_category":"Adviesbureaus Bedrijfsorganisatie",
    "sg:phone":"+31 24 358 2780",
    "sg:postcode":"6581 EK",
    "sg:province":"Gelderland",
    "wof:name":"Berne Cons, P A M Van",
    "wof:placetype":"venue"
},
  "geometry": {"coordinates":[5.855913,51.777973],"type":"Point"}
}