{
  "type": "Feature",
  "properties": {
    "addr:full":"Esrein 38 Hengelo Ov Overijssel 7553 CZ",
    "addr:housenumber":"38",
    "addr:postcode":"7553",
    "addr:street":"Esrein;Ov",
    "iso:country":"NL",
    "sg:address":"Esrein 38",
    "sg:city":"Hengelo Ov",
    "sg:orig_category":"Musea",
    "sg:phone":"+31 74 250 5535",
    "sg:postcode":"7553 CZ",
    "sg:province":"Overijssel",
    "wof:name":"Museum Electro Radio Nostalgie",
    "wof:placetype":"venue"
},
  "geometry": {"coordinates":[6.791131,52.256847],"type":"Point"}
}