{
  "type": "Feature",
  "properties": {
    "addr:full":"Kruisstr 18 Hattem Gelderland 8051 GE",
    "addr:housenumber":"18",
    "addr:postcode":"8051",
    "addr:street":"Kruisstr;Gelderland",
    "iso:country":"NL",
    "sg:address":"Kruisstr 18",
    "sg:city":"Hattem",
    "sg:orig_category":"Kappers",
    "sg:phone":"+31 38 444 7600",
    "sg:postcode":"8051 GE",
    "sg:province":"Gelderland",
    "wof:name":"Whair",
    "wof:placetype":"venue"
},
  "geometry": {"coordinates":[6.070066,52.475368],"type":"Point"}
}