{
  "type": "Feature",
  "properties": {
    "addr:full":"Noordweg 7 Zeist Utrecht 3704 GK",
    "addr:housenumber":"7",
    "addr:postcode":"3704 gk",
    "addr:street":"Noordweg",
    "iso:country":"NL",
    "sg:address":"Noordweg 7",
    "sg:city":"Zeist",
    "sg:orig_category":"Fietshandelaren",
    "sg:phone":"+31 30 695 9131",
    "sg:postcode":"3704 GK",
    "sg:province":"Utrecht",
    "wof:name":"Peter De Bree Fietsen",
    "wof:placetype":"venue"
},
  "geometry": {"coordinates":[5.220233,52.089413],"type":"Point"}
}