{
  "type": "Feature",
  "properties": {
    "iso:country":"NL",
    "sg:address":"Wapserveenstr 575",
    "sg:city":"S Gravenhage",
    "sg:orig_category":"Kappers",
    "sg:phone":"+31 70 366 3711",
    "sg:postcode":"2545 KZ",
    "sg:province":"Zuid-Holland",
    "wof:name":"Fred'S Hairshop",
    "wof:placetype":"venue"
},
  "geometry": {"coordinates":[4.2704901695,52.0509300232],"type":"Point"}
}