{
  "type": "Feature",
  "properties": {
    "addr:full":"Nyverheidswg 15 Vriezenveen NL.08 7671 DA",
    "addr:housenumber":"15;nl.08",
    "addr:postcode":"7671 da",
    "addr:street":"Nyverheidswg",
    "iso:country":"NL",
    "sg:address":"Nyverheidswg 15",
    "sg:city":"Vriezenveen",
    "sg:orig_category":"Autosloperijen En Autodemontagebedrijven",
    "sg:phone":"+31 546 566 498",
    "sg:postcode":"7671 DA",
    "sg:province":"NL.08",
    "sg:website":"http://www.jari.nl",
    "wof:name":"Jari Bv",
    "wof:placetype":"venue"
},
  "geometry": {"coordinates":[6.598046,52.411133],"type":"Point"}
}