{
  "type": "Feature",
  "properties": {
    "iso:country":"NL",
    "sg:address":"Bredasestr 19",
    "sg:city":"Bergen Op Zoom",
    "sg:orig_category":"Notarissen En Notariskantoren",
    "sg:phone":"+31 164 242 650",
    "sg:postcode":"4611 CE",
    "sg:province":"Noord-Brabant",
    "wof:name":"Fikkers En Zoon, Notariskantoor",
    "wof:placetype":"venue"
},
  "geometry": {"coordinates":[4.294284,51.495983],"type":"Point"}
}