{
  "type": "Feature",
  "properties": {
    "addr:full":"Fazantenkamp 546 Maarssen Utrecht 3607 DD",
    "addr:housenumber":"546",
    "addr:postcode":"3607 dd",
    "addr:street":"Fazantenkamp",
    "iso:country":"NL",
    "sg:address":"Fazantenkamp 546",
    "sg:city":"Maarssen",
    "sg:orig_category":"Adviesbureaus Bedrijfsorganisatie",
    "sg:phone":"+31 346 553 325",
    "sg:postcode":"3607 DD",
    "sg:province":"Utrecht",
    "wof:name":"Mediaweb",
    "wof:placetype":"venue"
},
  "geometry": {"coordinates":[5.022616,52.128529],"type":"Point"}
}