{
  "type": "Feature",
  "properties": {
    "addr:full":"Havenrak 1 Broek In Waterland Noord-Holland 1151 AE",
    "addr:housenumber":"1",
    "addr:postcode":"1151 ae",
    "addr:street":"Havenrak",
    "iso:country":"NL",
    "sg:address":"Havenrak 1",
    "sg:city":"Broek In Waterland",
    "sg:orig_category":"Antiekzaken",
    "sg:phone":"+31 20 403 1372",
    "sg:postcode":"1151 AE",
    "sg:province":"Noord-Holland",
    "wof:name":"Antiekhandel W. Bruigom-Six",
    "wof:placetype":"venue"
},
  "geometry": {"coordinates":[4.99397,52.435871],"type":"Point"}
}