{
  "type": "Feature",
  "properties": {
    "iso:country":"NL",
    "sg:address":"Allard Piersonlaan 132",
    "sg:city":"'S Gravenhage",
    "sg:orig_category":"Kappers",
    "sg:phone":"+31 70 399 5552",
    "sg:postcode":"2522 MS",
    "sg:province":"Zuid-Holland",
    "wof:name":"Kapsalon Adelheid",
    "wof:placetype":"venue"
},
  "geometry": {"coordinates":[4.3244280815,52.0603675842],"type":"Point"}
}