{
  "type": "Feature",
  "properties": {
    "addr:full":"Damseweg 80 Brandwijk Zuid-Holland 2974 VB",
    "addr:housenumber":"80",
    "addr:postcode":"2974 vb",
    "addr:street":"Damseweg",
    "iso:country":"NL",
    "sg:address":"Damseweg 80",
    "sg:city":"Brandwijk",
    "sg:classifiers":[
        {
            "category":"Fast Food",
            "type":"Food & Drink"
        }
    ],
    "sg:phone":"+31 184 642 549",
    "sg:postcode":"2974 VB",
    "sg:province":"Zuid-Holland",
    "sg:tags":[
        "afhaal",
        "restaurant"
    ],
    "wof:name":"P.A. Van Der Graaf",
    "wof:placetype":"venue"
},
  "geometry": {"coordinates":[4.847739,51.88406],"type":"Point"}
}