{
  "type": "Feature",
  "properties": {
    "addr:full":"Maasstraat 12 Dordrecht Zuid-Holland 3313 CR",
    "addr:housenumber":"12",
    "addr:postcode":"3313 cr",
    "addr:street":"Maasstraat",
    "iso:country":"NL",
    "sg:address":"Maasstraat 12",
    "sg:city":"Dordrecht",
    "sg:orig_category":"Elektronische Bedrijfsinstallaties",
    "sg:phone":"+31 78 614 9444",
    "sg:postcode":"3313 CR",
    "sg:province":"Zuid-Holland",
    "wof:name":"Plaat-En Constructiewerken Harold Bv",
    "wof:placetype":"venue"
},
  "geometry": {"coordinates":[4.682864,51.81847],"type":"Point"}
}