{
  "type": "Feature",
  "properties": {
    "addr:full":"De Genestetstraat 25 Ridderkerk Zuid-Holland 2985 CE",
    "addr:housenumber":"25",
    "addr:postcode":"2985 ce",
    "addr:street":"De Genestetstraat",
    "iso:country":"NL",
    "sg:address":"De Genestetstraat 25",
    "sg:city":"Ridderkerk",
    "sg:orig_category":"Boekhouders",
    "sg:phone":"+31 180 423 503",
    "sg:postcode":"2985 CE",
    "sg:province":"Zuid-Holland",
    "wof:name":"Administratiekantoor A. Van Gent",
    "wof:placetype":"venue"
},
  "geometry": {"coordinates":[4.602516,51.862392],"type":"Point"}
}