{
  "type": "Feature",
  "properties": {
    "addr:full":"Noordendijk 5 Dordrecht Zuid-Holland 3311 RM",
    "addr:housenumber":"5",
    "addr:postcode":"3311 rm",
    "addr:street":"Noordendijk",
    "iso:country":"NL",
    "sg:address":"Noordendijk 5",
    "sg:city":"Dordrecht",
    "sg:orig_category":"Verhuur Catering-, Feest- En Evenementbenodigdheden",
    "sg:phone":"+31 6 54256396",
    "sg:postcode":"3311 RM",
    "sg:province":"Zuid-Holland",
    "wof:name":"P.E. Noorlander",
    "wof:placetype":"venue"
},
  "geometry": {"coordinates":[4.674604,51.816448],"type":"Point"}
}