{
  "type": "Feature",
  "properties": {
    "addr:full":"Haarlemmerstr 161 Leiden South Holland 2312 DP",
    "addr:housenumber":"161",
    "addr:postcode":"2312 dp",
    "iso:country":"NL",
    "sg:address":"Haarlemmerstr 161",
    "sg:city":"Leiden",
    "sg:orig_category":"Drogisterijen",
    "sg:phone":"+31 71 514 9080",
    "sg:postcode":"2312 DP",
    "sg:province":"South Holland",
    "wof:name":"Kruidvat",
    "wof:placetype":"venue"
},
  "geometry": {"coordinates":[4.493265,52.160172],"type":"Point"}
}