{
  "type": "Feature",
  "properties": {
    "addr:full":"Langestraat 24 Enschede NL.08 7511 HC",
    "addr:housenumber":"24",
    "addr:postcode":"7511 hc",
    "addr:street":"Langestraat",
    "iso:country":"NL",
    "sg:address":"Langestraat 24",
    "sg:city":"Enschede",
    "sg:orig_category":"Overheidsdiensten",
    "sg:phone":"+31 53 481 8181",
    "sg:postcode":"7511 HC",
    "sg:province":"NL.08",
    "wof:name":"Gemeente Enschede",
    "wof:placetype":"venue"
},
  "geometry": {"coordinates":[6.8969898224,52.219379425],"type":"Point"}
}