{
  "type": "Feature",
  "properties": {
    "addr:full":"Lorentzpln 42 Badhoevedorp Noord-Holland 1171 BB",
    "addr:housenumber":"42",
    "addr:postcode":"1171 bb",
    "addr:street":"Lorentzpln",
    "iso:country":"NL",
    "sg:address":"Lorentzpln 42",
    "sg:city":"Badhoevedorp",
    "sg:orig_category":"Gelegenheidskleding",
    "sg:phone":"+31 20 659 5747",
    "sg:postcode":"1171 BB",
    "sg:province":"Noord-Holland",
    "sg:website":"http://www.jagtmanmode.nl",
    "wof:name":"Jagtman, Mode",
    "wof:placetype":"venue"
},
  "geometry": {"coordinates":[4.77836,52.339214],"type":"Point"}
}