{
  "type": "Feature",
  "properties": {
    "addr:full":"Heerderwg 138 Maastricht Limburg 6224 LJ",
    "addr:housenumber":"138",
    "addr:postcode":"6224 lj",
    "iso:country":"NL",
    "sg:address":"Heerderwg 138",
    "sg:city":"Maastricht",
    "sg:orig_category":"Banden",
    "sg:phone":"+31 43 362 1646",
    "sg:postcode":"6224 LJ",
    "sg:province":"Limburg",
    "wof:name":"Carl Koker Autobanden",
    "wof:placetype":"venue"
},
  "geometry": {"coordinates":[5.713981,50.844654],"type":"Point"}
}