{
  "type": "Feature",
  "properties": {
    "addr:full":"Bachstr 58 Hellevoetsluis Zuid-Holland 3223 TA",
    "addr:housenumber":"58",
    "addr:postcode":"3223 ta",
    "addr:street":"Bachstr",
    "iso:country":"NL",
    "sg:address":"Bachstr 58",
    "sg:city":"Hellevoetsluis",
    "sg:orig_category":"Adviesbureaus",
    "sg:phone":"+31 181 328 083",
    "sg:postcode":"3223 TA",
    "sg:province":"Zuid-Holland",
    "wof:name":"Ixel Advies",
    "wof:placetype":"venue"
},
  "geometry": {"coordinates":[4.158687,51.843136],"type":"Point"}
}