{
  "type": "Feature",
  "properties": {
    "addr:full":"Willem De Zwijgerlaan 20 Waddinxveen Zuid-Holland 2741 DC",
    "addr:housenumber":"20",
    "addr:postcode":"2741",
    "addr:street":"Willem De Zwijgerlaan",
    "iso:country":"NL",
    "sg:address":"Willem De Zwijgerlaan 20",
    "sg:city":"Waddinxveen",
    "sg:orig_category":"Autokeuringen",
    "sg:phone":"+31 182 615 426",
    "sg:postcode":"2741 DC",
    "sg:province":"Zuid-Holland",
    "wof:name":"H Van Ingen Onderh V Rijdendemelkontvang",
    "wof:placetype":"venue"
},
  "geometry": {"coordinates":[4.654962,52.049065],"type":"Point"}
}