{
  "type": "Feature",
  "properties": {
    "addr:full":"Lange Nering 86 Emmeloord Flevoland 8302 EE",
    "addr:housenumber":"86",
    "addr:postcode":"8302 ee",
    "addr:street":"Lange Nering;Flevoland",
    "iso:country":"NL",
    "sg:address":"Lange Nering 86",
    "sg:city":"Emmeloord",
    "sg:orig_category":"Bloemen And Planten",
    "sg:phone":"+31 527 613 638",
    "sg:postcode":"8302 EE",
    "sg:province":"Flevoland",
    "wof:name":"De Natuurvriend",
    "wof:placetype":"venue"
},
  "geometry": {"coordinates":[5.758738,52.71122],"type":"Point"}
}