{
  "type": "Feature",
  "properties": {
    "addr:full":"J Hilgerswg 8 Ede Gld Gelderland 6718 TP",
    "addr:housenumber":"8",
    "addr:postcode":"6718",
    "addr:street":"Gld Gelderland",
    "iso:country":"NL",
    "sg:address":"J Hilgerswg 8",
    "sg:city":"Ede Gld",
    "sg:classifiers":[
        {
            "category":"Organizations",
            "subcategory":"Community Association",
            "type":"Services"
        }
    ],
    "sg:phone":"+31 318 615 002",
    "sg:postcode":"6718 TP",
    "sg:province":"Gelderland",
    "sg:tags":[
        "badge"
    ],
    "wof:name":"Him Bv",
    "wof:placetype":"venue"
},
  "geometry": {"coordinates":[5.687871,52.066483],"type":"Point"}
}