{
  "type": "Feature",
  "properties": {
    "addr:full":"Binnenhof 37 Grootebroek North Holland 1613 EX",
    "addr:housenumber":"37",
    "addr:postcode":"1613 ex",
    "addr:street":"Binnenhof",
    "iso:country":"NL",
    "sg:address":"Binnenhof 37",
    "sg:city":"Grootebroek",
    "sg:orig_category":"Kappers",
    "sg:phone":"+31 6 15396230",
    "sg:postcode":"1613 EX",
    "sg:province":"North Holland",
    "wof:name":"Marlies",
    "wof:placetype":"venue"
},
  "geometry": {"coordinates":[5.221516,52.687771],"type":"Point"}
}