{
  "type": "Feature",
  "properties": {
    "addr:full":"Schipborgerwg 31 Zuidlaren Drenthe 9471 PP",
    "addr:housenumber":"31",
    "addr:postcode":"9471 pp",
    "addr:street":"Schipborgerwg",
    "iso:country":"NL",
    "sg:address":"Schipborgerwg 31",
    "sg:city":"Zuidlaren",
    "sg:orig_category":"Fitnesscentra",
    "sg:phone":"+31 50 409 0772",
    "sg:postcode":"9471 PP",
    "sg:province":"Drenthe",
    "wof:name":"Dynamia Zonnestudio",
    "wof:placetype":"venue"
},
  "geometry": {"coordinates":[6.667379,53.086838],"type":"Point"}
}