{
  "type": "Feature",
  "properties": {
    "addr:full":"Weverstr 41 Den Burg Arkansas 1791 AB",
    "addr:housenumber":"41",
    "addr:postcode":"1791 ab",
    "addr:street":"Weverstr",
    "iso:country":"NL",
    "sg:address":"Weverstr 41",
    "sg:city":"Den Burg",
    "sg:orig_category":"Wasmachines En Wasdrogers",
    "sg:phone":"+31 222 322 392",
    "sg:postcode":"1791 AB",
    "sg:province":"Arkansas",
    "wof:name":"Vem",
    "wof:placetype":"venue"
},
  "geometry": {"coordinates":[-94.07168579099999,34.2320823669],"type":"Point"}
}