{
  "type": "Feature",
  "properties": {
    "iso:country":"NL",
    "sg:address":"De Spinde 59",
    "sg:city":"Raalte",
    "sg:orig_category":"Diverse Grafische Activiteiten",
    "sg:phone":"+31 572 356 373",
    "sg:postcode":"8102 LB",
    "sg:province":"NL.08",
    "wof:name":"De Graaf Karton",
    "wof:placetype":"venue"
},
  "geometry": {"coordinates":[6.274681,52.37368],"type":"Point"}
}