{
  "type": "Feature",
  "properties": {
    "addr:full":"Holterweg 19 Markelo Overijssel 7475 AT",
    "addr:housenumber":"19",
    "addr:postcode":"7475",
    "addr:street":"Holterweg",
    "iso:country":"NL",
    "sg:address":"Holterweg 19",
    "sg:city":"Markelo",
    "sg:orig_category":"Chemische Producten Gh",
    "sg:phone":"+31 547 362 486",
    "sg:postcode":"7475 AT",
    "sg:province":"Overijssel",
    "wof:name":"Mestdistributie Twente Bv",
    "wof:placetype":"venue"
},
  "geometry": {"coordinates":[6.472245,52.248672],"type":"Point"}
}