{
  "type": "Feature",
  "properties": {
    "addr:full":"Bakenessergracht 51 Haarlem Noord-Holland 2011 JT",
    "addr:housenumber":"51",
    "addr:postcode":"2011 jt",
    "addr:street":"Bakenessergracht",
    "iso:country":"NL",
    "sg:address":"Bakenessergracht 51",
    "sg:city":"Haarlem",
    "sg:orig_category":"Elektronische Bedrijfsinstallaties",
    "sg:phone":"+31 23 534 1219",
    "sg:postcode":"2011 JT",
    "sg:province":"Noord-Holland",
    "wof:name":"Leipoldt & Roos Vof",
    "wof:placetype":"venue"
},
  "geometry": {"coordinates":[4.640564,52.382439],"type":"Point"}
}