{
  "type": "Feature",
  "properties": {
    "iso:country":"NL",
    "sg:address":"Radstakeweg 55",
    "sg:city":"Deventer",
    "sg:orig_category":"Vertaal- And Tolkenbureaus",
    "sg:phone":"+31 570 617 877",
    "sg:postcode":"7412 XS",
    "sg:province":"Overijssel",
    "wof:name":"J. Tolkamp",
    "wof:placetype":"venue"
},
  "geometry": {"coordinates":[6.143698,52.260555],"type":"Point"}
}