{
  "type": "Feature",
  "properties": {
    "addr:full":"Beverwijkstraat 22 Amsterdam North Holland 1024 VR",
    "addr:housenumber":"22",
    "addr:postcode":"1024 vr",
    "addr:street":"Beverwijkstraat",
    "iso:country":"NL",
    "sg:address":"Beverwijkstraat 22",
    "sg:city":"Amsterdam",
    "sg:orig_category":"Fotolaboratoria",
    "sg:phone":"+31 20 636 1533",
    "sg:postcode":"1024 VR",
    "sg:province":"North Holland",
    "wof:name":"Lcs Fotolab",
    "wof:placetype":"venue"
},
  "geometry": {"coordinates":[4.955053,52.393311],"type":"Point"}
}