{
  "type": "Feature",
  "properties": {
    "addr:full":"Achterste Kamp 13 Roden Provincie Drenthe 9301 RB",
    "addr:housenumber":"13",
    "addr:postcode":"9301 rb",
    "addr:street":"Achterste Kamp;Provincie Drenthe",
    "iso:country":"NL",
    "sg:address":"Achterste Kamp 13",
    "sg:city":"Roden",
    "sg:orig_category":"Paramedische Behandelingen",
    "sg:phone":"+31 50 501 8560",
    "sg:postcode":"9301 RB",
    "sg:province":"Provincie Drenthe",
    "wof:name":"J. Antons",
    "wof:placetype":"venue"
},
  "geometry": {"coordinates":[6.414369,53.142448],"type":"Point"}
}