{
  "type": "Feature",
  "properties": {
    "addr:full":"Blankenborghoek 26 Enschede Overijssel 7546 HA",
    "addr:housenumber":"26",
    "addr:postcode":"7546 ha",
    "addr:street":"Blankenborghoek",
    "iso:country":"NL",
    "sg:address":"Blankenborghoek 26",
    "sg:city":"Enschede",
    "sg:orig_category":"Goederenvervoer Over De Weg",
    "sg:phone":"+31 6 55836364",
    "sg:postcode":"7546 HA",
    "sg:province":"Overijssel",
    "wof:name":"Logistiek Express Nl",
    "wof:placetype":"venue"
},
  "geometry": {"coordinates":[6.857247,52.195328],"type":"Point"}
}