{
  "type": "Feature",
  "properties": {
    "iso:country":"NL",
    "sg:address":"Kortewg 63",
    "sg:city":"Apeldoorn",
    "sg:orig_category":"Kinderkleding",
    "sg:phone":"+31 6 23743199",
    "sg:postcode":"7315 CK",
    "sg:province":"Gelderland",
    "wof:name":"Inimini",
    "wof:placetype":"venue"
},
  "geometry": {"coordinates":[5.952276,52.228069],"type":"Point"}
}