{
  "type": "Feature",
  "properties": {
    "addr:full":"Terrastr 1 Oudorp Nh Noord-Holland 1829 XL",
    "addr:housenumber":"1",
    "addr:postcode":"1829 xl",
    "addr:street":"Terrastr",
    "iso:country":"NL",
    "sg:address":"Terrastr 1",
    "sg:city":"Oudorp Nh",
    "sg:orig_category":"Organisatiebureaus",
    "sg:phone":"+31 72 515 4847",
    "sg:postcode":"1829 XL",
    "sg:province":"Noord-Holland",
    "wof:name":"Tema",
    "wof:placetype":"venue"
},
  "geometry": {"coordinates":[4.7788281441,52.6283149719],"type":"Point"}
}