{
  "type": "Feature",
  "properties": {
    "iso:country":"NL",
    "sg:address":"Hooglandsekerkgr 47",
    "sg:city":"Leiden",
    "sg:orig_category":"Vertaalbureaus",
    "sg:phone":"+31 71 512 3890",
    "sg:postcode":"2312 HS",
    "sg:province":"Zuid-Holland",
    "wof:name":"Japan",
    "wof:placetype":"venue"
},
  "geometry": {"coordinates":[4.493437,52.158165],"type":"Point"}
}