{
  "type": "Feature",
  "properties": {
    "addr:full":"Hoendiep 97D Groningen Groningen 9718 TE",
    "addr:housenumber":"97d",
    "addr:postcode":"9718 te",
    "addr:street":"Hoendiep",
    "iso:country":"NL",
    "sg:address":"Hoendiep 97D",
    "sg:city":"Groningen",
    "sg:orig_category":"Meubelen",
    "sg:phone":"+31 50 318 4022",
    "sg:postcode":"9718 TE",
    "sg:province":"Groningen",
    "sg:website":"http://www.sandersmeubelstad.nl",
    "wof:name":"Sanders Bv",
    "wof:placetype":"venue"
},
  "geometry": {"coordinates":[6.543285,53.213638],"type":"Point"}
}