{
  "type": "Feature",
  "properties": {
    "addr:full":"Zuiderstraat 4 Noordlaren Groningen 9479 PP",
    "addr:housenumber":"4",
    "addr:postcode":"9479 pp",
    "addr:street":"Zuiderstraat",
    "iso:country":"NL",
    "sg:address":"Zuiderstraat 4",
    "sg:city":"Noordlaren",
    "sg:orig_category":"Alternatieve Geneeskunde",
    "sg:phone":"+31 50 409 4094",
    "sg:postcode":"9479 PP",
    "sg:province":"Groningen",
    "wof:name":"Praktijk De Eiseendenhof",
    "wof:placetype":"venue"
},
  "geometry": {"coordinates":[6.668703,53.11869],"type":"Point"}
}