{
  "type": "Feature",
  "properties": {
    "addr:full":"Leemskuilen 25 Westerhoven Noord-Brabant 5563 CL",
    "addr:housenumber":"25",
    "addr:postcode":"5563",
    "addr:street":"Leemskuilen",
    "iso:country":"NL",
    "sg:address":"Leemskuilen 25",
    "sg:city":"Westerhoven",
    "sg:orig_category":"Meubellakkerijen En -Spuiterijen",
    "sg:phone":"+31 40 255 5038",
    "sg:postcode":"5563 CL",
    "sg:province":"Noord-Brabant",
    "wof:name":"Maro Meubelspuiterij",
    "wof:placetype":"venue"
},
  "geometry": {"coordinates":[5.40612,51.336201],"type":"Point"}
}