{
  "type": "Feature",
  "properties": {
    "addr:full":"Borculosewg 57 Groenlo Gelderland 7141 VL",
    "addr:housenumber":"57",
    "addr:postcode":"7141 vl",
    "addr:street":"Borculosewg;Gelderland",
    "iso:country":"NL",
    "sg:address":"Borculosewg 57",
    "sg:city":"Groenlo",
    "sg:orig_category":"Benzine En Olie - Groothandel",
    "sg:phone":"+31 544 461 522",
    "sg:postcode":"7141 VL",
    "sg:province":"Gelderland",
    "sg:website":"http://www.kolkmanbv.nl",
    "wof:name":"Kolkman, Tankstation Oliehandel",
    "wof:placetype":"venue"
},
  "geometry": {"coordinates":[6.606745,52.047478],"type":"Point"}
}