{
  "type": "Feature",
  "properties": {
    "addr:full":"Niftrikplein 18 Tilburg Noord-Brabant 5045 MP",
    "addr:housenumber":"18",
    "addr:postcode":"5045 mp",
    "addr:street":"Niftrikplein",
    "iso:country":"NL",
    "sg:address":"Niftrikplein 18",
    "sg:city":"Tilburg",
    "sg:orig_category":"Vertaal- And Tolkenbureaus",
    "sg:phone":"+31 13 572 0030",
    "sg:postcode":"5045 MP",
    "sg:province":"Noord-Brabant",
    "wof:name":"Arina Byrdina Ba",
    "wof:placetype":"venue"
},
  "geometry": {"coordinates":[4.9906730652,51.5837173462],"type":"Point"}
}