{
  "type": "Feature",
  "properties": {
    "iso:country":"NL",
    "sg:address":"Dorpsstraat 6",
    "sg:city":"Oostkapelle",
    "sg:orig_category":"Gespecialiseerde Voeding",
    "sg:phone":"+31 118 583 133",
    "sg:postcode":"4356 AJ",
    "sg:province":"Zeeland",
    "wof:name":"K.P. Caspers",
    "wof:placetype":"venue"
},
  "geometry": {"coordinates":[3.551804,51.565475],"type":"Point"}
}