{
  "type": "Feature",
  "properties": {
    "addr:full":"Groenhovenwg 153 Gouda Zuid-Holland 2803 DC",
    "addr:housenumber":"153",
    "addr:postcode":"2803",
    "iso:country":"NL",
    "sg:address":"Groenhovenwg 153",
    "sg:city":"Gouda",
    "sg:orig_category":"Keukens",
    "sg:phone":"+31 182 553 604",
    "sg:postcode":"2803 DC",
    "sg:province":"Zuid-Holland",
    "wof:name":"Binnenhuis Totaal Hp",
    "wof:placetype":"venue"
},
  "geometry": {"coordinates":[4.690231,52.025082],"type":"Point"}
}