{
  "type": "Feature",
  "properties": {
    "addr:full":"W Schoutenstr 1Hs Amsterdam Noord-Holland 1057 DL",
    "addr:postcode":"1057 dl",
    "addr:street":"W;1Hs",
    "iso:country":"NL",
    "sg:address":"W Schoutenstr 1Hs",
    "sg:city":"Amsterdam",
    "sg:orig_category":"Verenigingen En Stichtingen",
    "sg:phone":"+31 20 683 1465",
    "sg:postcode":"1057 DL",
    "sg:province":"Noord-Holland",
    "wof:name":"Portugese Vereniging Amsterdam",
    "wof:placetype":"venue"
},
  "geometry": {"coordinates":[4.85502,52.367489],"type":"Point"}
}