{
  "type": "Feature",
  "properties": {
    "iso:country":"NL",
    "sg:address":"Krekelveen 638",
    "sg:city":"Spykenisse",
    "sg:orig_category":"Schilders",
    "sg:phone":"+31 181 632 310",
    "sg:postcode":"3205 RM",
    "sg:province":"South Holland",
    "wof:name":"Steensma Schilderwerken Vof",
    "wof:placetype":"venue"
},
  "geometry": {"coordinates":[4.337214,51.830677],"type":"Point"}
}