{
  "type": "Feature",
  "properties": {
    "iso:country":"NL",
    "sg:address":"Mr Arntzeniuswg 17",
    "sg:city":"Amsterdam",
    "sg:orig_category":"Fotojournalisten Freelance",
    "sg:phone":"+31 20 665 5777",
    "sg:postcode":"1098 GK",
    "sg:province":"Noord-Holland",
    "wof:name":"Kohn, Mark",
    "wof:placetype":"venue"
},
  "geometry": {"coordinates":[4.934762,52.355721],"type":"Point"}
}