{
  "type": "Feature",
  "properties": {
    "addr:full":"Beereveld 20 Breukelen Ut Utrecht 3621 GX",
    "addr:housenumber":"20",
    "addr:postcode":"3621 gx",
    "addr:street":"Beereveld",
    "iso:country":"NL",
    "sg:address":"Beereveld 20",
    "sg:city":"Breukelen Ut",
    "sg:orig_category":"Poppen En Poppenhuismaterialen",
    "sg:phone":"+31 346 266 666",
    "sg:postcode":"3621 GX",
    "sg:province":"Utrecht",
    "wof:name":"Verkuil, G",
    "wof:placetype":"venue"
},
  "geometry": {"coordinates":[5.001079,52.182369],"type":"Point"}
}