{
  "type": "Feature",
  "properties": {
    "iso:country":"NL",
    "sg:address":"Winnipegdreef 1",
    "sg:city":"Utrecht",
    "sg:orig_category":"Medische Apparatuur And Prothesen Fab",
    "sg:phone":"+31 30 262 4052",
    "sg:postcode":"3564 KV",
    "sg:province":"Utrecht",
    "wof:name":"J.G.P. De Bree",
    "wof:placetype":"venue"
},
  "geometry": {"coordinates":[5.097024,52.126705],"type":"Point"}
}