{
  "type": "Feature",
  "properties": {
    "addr:full":"Scheendk 16 Breukelen Ut Utrecht 3621 VC",
    "addr:housenumber":"16",
    "addr:postcode":"3621 vc",
    "addr:street":"Scheendk",
    "iso:country":"NL",
    "sg:address":"Scheendk 16",
    "sg:city":"Breukelen Ut",
    "sg:orig_category":"Jachthavens - Jachtwerven",
    "sg:phone":"+31 346 263 745",
    "sg:postcode":"3621 VC",
    "sg:province":"Utrecht",
    "wof:name":"Alexander",
    "wof:placetype":"venue"
},
  "geometry": {"coordinates":[5.001585,52.172958],"type":"Point"}
}