{
  "type": "Feature",
  "properties": {
    "addr:full":"Rondostraat 22 Almere Flevoland 1312 SK",
    "addr:housenumber":"22",
    "addr:street":"Rondostraat;Flevoland 1312",
    "iso:country":"NL",
    "sg:address":"Rondostraat 22",
    "sg:city":"Almere",
    "sg:orig_category":"Boekhouders",
    "sg:phone":"+31 36 536 6444",
    "sg:postcode":"1312 SK",
    "sg:province":"Flevoland",
    "wof:name":"A.H.S. Lotten",
    "wof:placetype":"venue"
},
  "geometry": {"coordinates":[5.183377,52.37579],"type":"Point"}
}