{
  "type": "Feature",
  "properties": {
    "addr:full":"Rozengracht 192 Amsterdam Noord-Holland 1016  N",
    "addr:housenumber":"192;1016",
    "addr:street":"Rozengracht;N",
    "iso:country":"NL",
    "sg:address":"Rozengracht 192",
    "sg:city":"Amsterdam",
    "sg:classifiers":[
        {
            "category":"Fast Food",
            "type":"Food & Drink"
        }
    ],
    "sg:phone":"+31 20 625 5376",
    "sg:postcode":"1016  N",
    "sg:province":"Noord-Holland",
    "sg:tags":[
        "afhaal",
        "restaurant"
    ],
    "wof:name":"Murugan",
    "wof:placetype":"venue"
},
  "geometry": {"coordinates":[4.877426,52.372704],"type":"Point"}
}