{
  "type": "Feature",
  "properties": {
    "addr:full":"Baarskolk 18 Zwolle Overijssel 8017 NA",
    "addr:housenumber":"18",
    "addr:postcode":"8017 na",
    "addr:street":"Baarskolk",
    "iso:country":"NL",
    "sg:address":"Baarskolk 18",
    "sg:city":"Zwolle",
    "sg:orig_category":"Honden- En Kattentrimsalons",
    "sg:phone":"+31 38 466 1385",
    "sg:postcode":"8017 NA",
    "sg:province":"Overijssel",
    "wof:name":"Yvonne",
    "wof:placetype":"venue"
},
  "geometry": {"coordinates":[6.097199,52.493969],"type":"Point"}
}