{
  "type": "Feature",
  "properties": {
    "addr:full":"Postbus 84 Harmelen Utrecht 3480 DB",
    "addr:housenumber":"84",
    "addr:postcode":"3480 db",
    "addr:street":"Postbus",
    "iso:country":"NL",
    "sg:address":"Postbus 84",
    "sg:city":"Harmelen",
    "sg:orig_category":"Adviesbureaus Bedrijfsorganisatie",
    "sg:phone":"+31 348 446 464",
    "sg:postcode":"3480 DB",
    "sg:province":"Utrecht",
    "wof:name":"Resource Integration Bv",
    "wof:placetype":"venue"
},
  "geometry": {"coordinates":[4.9643,52.091549],"type":"Point"}
}