{
  "type": "Feature",
  "properties": {
    "addr:full":"J C V Hattumwg 15 Amstelveen Noord-Holland 1187 ZN",
    "addr:housenumber":"15",
    "addr:postcode":"1187 zn",
    "addr:street":"J;V Hattumwg",
    "iso:country":"NL",
    "sg:address":"J C V Hattumwg 15",
    "sg:city":"Amstelveen",
    "sg:orig_category":"Bloemen En Planten - Groothandel",
    "sg:phone":"+31 20 341 1646",
    "sg:postcode":"1187 ZN",
    "sg:province":"Noord-Holland",
    "wof:name":"Heinico, Fa",
    "wof:placetype":"venue"
},
  "geometry": {"coordinates":[4.856945,52.303444],"type":"Point"}
}