{
  "type": "Feature",
  "properties": {
    "addr:full":"Landbouwwg 48 Zeewolde NL. 3899 BG",
    "addr:housenumber":"48",
    "addr:postcode":"3899",
    "addr:street":"Landbouwwg;Nl.",
    "iso:country":"NL",
    "sg:address":"Landbouwwg 48",
    "sg:city":"Zeewolde",
    "sg:orig_category":"Land- En Tuinbouw - Mechanisatie",
    "sg:phone":"+31 36 522 1571",
    "sg:postcode":"3899 BG",
    "sg:province":"NL.",
    "wof:name":"Weevers",
    "wof:placetype":"venue"
},
  "geometry": {"coordinates":[5.49601,52.355118],"type":"Point"}
}