{
  "type": "Feature",
  "properties": {
    "addr:full":"Argusvlinder 39 Breda Noord-Brabant 4814 SG",
    "addr:housenumber":"39",
    "addr:postcode":"4814 sg",
    "addr:street":"Argusvlinder",
    "iso:country":"NL",
    "sg:address":"Argusvlinder 39",
    "sg:city":"Breda",
    "sg:orig_category":"Administratie- En Boekhoudkantoren",
    "sg:phone":"+31 76 549 4620",
    "sg:postcode":"4814 SG",
    "sg:province":"Noord-Brabant",
    "wof:name":"Admindo",
    "wof:placetype":"venue"
},
  "geometry": {"coordinates":[4.745481,51.585831],"type":"Point"}
}