{
  "type": "Feature",
  "properties": {
    "addr:full":"Benedenheulsewg 2 Stolwyk Zuid-Holland 2821 LR",
    "addr:housenumber":"2",
    "addr:postcode":"2821 lr",
    "addr:street":"Benedenheulsewg",
    "iso:country":"NL",
    "sg:address":"Benedenheulsewg 2",
    "sg:city":"Stolwyk",
    "sg:orig_category":"Adviesbureaus",
    "sg:phone":"+31 182 343 892",
    "sg:postcode":"2821 LR",
    "sg:province":"Zuid-Holland",
    "wof:name":"Habben Jansen",
    "wof:placetype":"venue"
},
  "geometry": {"coordinates":[4.741089,51.961941],"type":"Point"}
}