{
  "type": "Feature",
  "properties": {
    "addr:full":"Roetgensgoed 32 Nykerk Gld Gelderland 3863 BM",
    "addr:housenumber":"32",
    "addr:postcode":"3863 bm",
    "addr:street":"Roetgensgoed;Gld Gelderland",
    "iso:country":"NL",
    "sg:address":"Roetgensgoed 32",
    "sg:city":"Nykerk Gld",
    "sg:orig_category":"Woningstoffeerders",
    "sg:phone":"+31 33 245 6184",
    "sg:postcode":"3863 BM",
    "sg:province":"Gelderland",
    "wof:name":"Smits, A",
    "wof:placetype":"venue"
},
  "geometry": {"coordinates":[5.4674119949,52.2171401978],"type":"Point"}
}