{
  "type": "Feature",
  "properties": {
    "addr:full":"Moltbos 6 Landgraaf Limburg 6371 EA",
    "addr:housenumber":"6",
    "addr:postcode":"6371 ea",
    "addr:street":"Moltbos",
    "iso:country":"NL",
    "sg:address":"Moltbos 6",
    "sg:city":"Landgraaf",
    "sg:orig_category":"Elektrotechnische Apparatuur - Fabrieken En Groothandel",
    "sg:phone":"+31 45 532 4491",
    "sg:postcode":"6371 EA",
    "sg:province":"Limburg",
    "wof:name":"Ehrbecker Schiefelbusch Bv",
    "wof:placetype":"venue"
},
  "geometry": {"coordinates":[6.012744,50.90377],"type":"Point"}
}