{
  "type": "Feature",
  "properties": {
    "iso:country":"NL",
    "sg:address":"Hoofdstr 54",
    "sg:city":"Hillegom",
    "sg:orig_category":"Geschenkartikelen",
    "sg:phone":"+31 252 523 982",
    "sg:postcode":"2181 EE",
    "sg:province":"Zuid-Holland",
    "wof:name":"Molenaar",
    "wof:placetype":"venue"
},
  "geometry": {"coordinates":[4.580144,52.293892],"type":"Point"}
}