{
  "type": "Feature",
  "properties": {
    "addr:full":"Hoekeindsewg 108 Bleiswyk South Holland 2665 KG",
    "addr:housenumber":"108",
    "addr:postcode":"2665 kg",
    "addr:street":"Bleiswyk South",
    "iso:country":"NL",
    "sg:address":"Hoekeindsewg 108",
    "sg:city":"Bleiswyk",
    "sg:orig_category":"Pluimveeslachterijen",
    "sg:phone":"+31 10 521 9942",
    "sg:postcode":"2665 KG",
    "sg:province":"South Holland",
    "wof:name":"Stam, H A C Van Der",
    "wof:placetype":"venue"
},
  "geometry": {"coordinates":[4.528515,52.001667],"type":"Point"}
}