{
  "type": "Feature",
  "properties": {
    "iso:country":"NL",
    "sg:address":"Glipperweg 37",
    "sg:city":"Heemstede",
    "sg:orig_category":"Verhuur Kantoorapparatuur",
    "sg:phone":"+31 23 528 4911",
    "sg:postcode":"2104 AH",
    "sg:province":"Noord-Holland",
    "wof:name":"Compules",
    "wof:placetype":"venue"
},
  "geometry": {"coordinates":[4.607892,52.329411],"type":"Point"}
}