{
  "type": "Feature",
  "properties": {
    "addr:full":"Houtrykstr 340 Amsterdam North Holland 1013 DX",
    "addr:housenumber":"340",
    "addr:postcode":"1013 dx",
    "iso:country":"NL",
    "sg:address":"Houtrykstr 340",
    "sg:city":"Amsterdam",
    "sg:orig_category":"Kappers",
    "sg:phone":"+31 20 682 9286",
    "sg:postcode":"1013 DX",
    "sg:province":"North Holland",
    "wof:name":"Diny",
    "wof:placetype":"venue"
},
  "geometry": {"coordinates":[4.8768072128,52.3916893005],"type":"Point"}
}