{
  "type": "Feature",
  "properties": {
    "addr:full":"Hoflaan 1 Oostvoorne Zuid-Holland 3233 AN",
    "addr:housenumber":"1",
    "addr:postcode":"3233 an",
    "addr:street":"Hoflaan",
    "iso:country":"NL",
    "sg:address":"Hoflaan 1",
    "sg:city":"Oostvoorne",
    "sg:orig_category":"Fitnesscentra",
    "sg:phone":"+31 181 484 591",
    "sg:postcode":"3233 AN",
    "sg:province":"Zuid-Holland",
    "wof:name":"Fitnesscentrum Oostvoorne",
    "wof:placetype":"venue"
},
  "geometry": {"coordinates":[4.102579,51.915569],"type":"Point"}
}