{
  "type": "Feature",
  "properties": {
    "iso:country":"NL",
    "sg:address":"Horndk 34",
    "sg:city":"Loosdrecht",
    "sg:orig_category":"Accountants - Administratie- Consulenten En -Kantoren",
    "sg:phone":"+31 35 582 3140",
    "sg:postcode":"1231 NX",
    "sg:province":"Noord-Holland",
    "wof:name":"Kerkhove Accountants",
    "wof:placetype":"venue"
},
  "geometry": {"coordinates":[5.067815,52.215221],"type":"Point"}
}