{
  "type": "Feature",
  "properties": {
    "addr:full":"Hoofdstr 183 Sassenheim Zuid-Holland 2171 BB",
    "addr:housenumber":"183",
    "addr:postcode":"sassenheim;2171 bb",
    "iso:country":"NL",
    "sg:address":"Hoofdstr 183",
    "sg:city":"Sassenheim",
    "sg:orig_category":"Dameskleding",
    "sg:phone":"+31 252 219 128",
    "sg:postcode":"2171 BB",
    "sg:province":"Zuid-Holland",
    "wof:name":"Esperanza",
    "wof:placetype":"venue"
},
  "geometry": {"coordinates":[4.521014,52.225773],"type":"Point"}
}