{
  "type": "Feature",
  "properties": {
    "addr:full":"Wingerdwg 52 Amsterdam North Holland 1032 AN",
    "addr:housenumber":"52",
    "addr:postcode":"1032 an",
    "addr:street":"Wingerdwg",
    "iso:country":"NL",
    "sg:address":"Wingerdwg 52",
    "sg:city":"Amsterdam",
    "sg:orig_category":"Logopedisten",
    "sg:phone":"+31 20 637 4030",
    "sg:postcode":"1032 AN",
    "sg:province":"North Holland",
    "wof:name":"Wingerd, De",
    "wof:placetype":"venue"
},
  "geometry": {"coordinates":[4.916658,52.391037],"type":"Point"}
}