{
  "type": "Feature",
  "properties": {
    "iso:country":"NL",
    "sg:address":"Albert Schweitzerlaan 58",
    "sg:city":"Rijswijk Zh",
    "sg:orig_category":"Boekhouders",
    "sg:phone":"+31 70 393 0999",
    "sg:postcode":"2286 JJ",
    "sg:province":"South Holland",
    "wof:name":"Administratie- & Financ Kant H.P. Bloems",
    "wof:placetype":"venue"
},
  "geometry": {"coordinates":[4.313394,52.026699],"type":"Point"}
}