{
  "type": "Feature",
  "properties": {
    "iso:country":"NL",
    "sg:address":"Heemskerkstr 7",
    "sg:city":"Sneek",
    "sg:orig_category":"Webdesign Bureaus",
    "sg:phone":"+31 515 432 930",
    "sg:postcode":"8603 BN",
    "sg:province":"Friesland",
    "wof:name":"Bons",
    "wof:placetype":"venue"
},
  "geometry": {"coordinates":[5.6658082008,53.0409812927],"type":"Point"}
}