{
  "type": "Feature",
  "properties": {
    "addr:full":"Grt Overstr 16-18 Deventer Overijssel 7411 JC",
    "addr:housenumber":"16-18",
    "addr:postcode":"7411 jc",
    "iso:country":"NL",
    "sg:address":"Grt Overstr 16-18",
    "sg:city":"Deventer",
    "sg:orig_category":"Kunsthandel",
    "sg:phone":"+31 6 55923799",
    "sg:postcode":"7411 JC",
    "sg:province":"Overijssel",
    "wof:name":"Koningshof, 'T",
    "wof:placetype":"venue"
},
  "geometry": {"coordinates":[6.15799,52.252739],"type":"Point"}
}