{
  "type": "Feature",
  "properties": {
    "iso:country":"NL",
    "sg:address":"De Weiert 1",
    "sg:city":"Emmen",
    "sg:classifiers":[
        {
            "category":"Food & Beverages",
            "subcategory":"Bakery",
            "type":"Retail Goods"
        }
    ],
    "sg:phone":"+31 591 649 596",
    "sg:postcode":"7811 BD",
    "sg:province":"Drenthe",
    "sg:tags":[
        "brood",
        "en",
        "banket"
    ],
    "wof:name":"Bart",
    "wof:placetype":"venue"
},
  "geometry": {"coordinates":[6.8964,52.782017],"type":"Point"}
}