{
  "type": "Feature",
  "properties": {
    "iso:country":"NL",
    "sg:address":"Prinsen Bolwerk 1",
    "sg:city":"Haarlem",
    "sg:orig_category":"Banken",
    "sg:phone":"+31 23 553 5900",
    "sg:postcode":"2011 MA",
    "sg:province":"North Holland",
    "sg:website":"HTTP://www.staalbankiers.nl",
    "wof:name":"Staalbankiers",
    "wof:placetype":"venue"
},
  "geometry": {"coordinates":[4.641063,52.388611],"type":"Point"}
}