{
  "type": "Feature",
  "properties": {
    "addr:full":"Knapheidewg 76 Groesbeek Gelderland 6562 DV",
    "addr:housenumber":"76",
    "addr:postcode":"6562",
    "addr:street":"Knapheidewg;Gelderland",
    "iso:country":"NL",
    "sg:address":"Knapheidewg 76",
    "sg:city":"Groesbeek",
    "sg:classifiers":[
        {
            "category":"Food & Beverages",
            "subcategory":"Fruits & Vegetables",
            "type":"Retail Goods"
        }
    ],
    "sg:phone":"+31 24 397 4403",
    "sg:postcode":"6562 DV",
    "sg:province":"Gelderland",
    "sg:tags":[
        "en",
        "groenten"
    ],
    "wof:name":"Ditshuizen",
    "wof:placetype":"venue"
},
  "geometry": {"coordinates":[5.930462,51.765865],"type":"Point"}
}