{
  "type": "Feature",
  "properties": {
    "addr:full":"Ambiorixweg 99 Maastricht Limburg 6225 CJ",
    "addr:housenumber":"99",
    "addr:postcode":"6225 cj",
    "addr:street":"Ambiorixweg",
    "iso:country":"NL",
    "sg:address":"Ambiorixweg 99",
    "sg:city":"Maastricht",
    "sg:orig_category":"Schilderwerk",
    "sg:phone":"+31 43 363 3478",
    "sg:postcode":"6225 CJ",
    "sg:province":"Limburg",
    "wof:name":"Schildersbedrijf Gebroeders Schellings Bv",
    "wof:placetype":"venue"
},
  "geometry": {"coordinates":[5.731853,50.865093],"type":"Point"}
}