{
  "type": "Feature",
  "properties": {
    "addr:full":"Sint Jansdijk 14 Nieuwvliet Pennsylvania 4504 PA",
    "addr:housenumber":"14",
    "addr:postcode":"4504 pa",
    "addr:street":"Sint Jansdijk",
    "iso:country":"NL",
    "sg:address":"Sint Jansdijk 14",
    "sg:city":"Nieuwvliet",
    "sg:orig_category":"Kampeerterreinen",
    "sg:phone":"+31 117 371 419",
    "sg:postcode":"4504 PA",
    "sg:province":"Pennsylvania",
    "wof:name":"Caravanpark Nooitgedacht Bv",
    "wof:placetype":"venue"
},
  "geometry": {"coordinates":[-77.6045074463,40.9946403503],"type":"Point"}
}