{
  "type": "Feature",
  "properties": {
    "iso:country":"NL",
    "sg:address":"Juliana Van Stolbergstr 3",
    "sg:city":"Tilburg",
    "sg:classifiers":[
        {
            "category":"Shopping",
            "subcategory":"Clothing, Apparel, & Fashions",
            "type":"Retail Goods"
        }
    ],
    "sg:phone":"+31 13 542 1124",
    "sg:postcode":"5038 AM",
    "sg:province":"Noord-Brabant",
    "sg:tags":[
        "ondergoed",
        "lingerie"
    ],
    "wof:name":"Kousenhuis Jambelle",
    "wof:placetype":"venue"
},
  "geometry": {"coordinates":[5.089497,51.556946],"type":"Point"}
}