{
  "type": "Feature",
  "properties": {
    "iso:country":"NL",
    "sg:address":"Carnisseln 52",
    "sg:city":"Rotterdam",
    "sg:orig_category":"Fietsen En Bromfietsen",
    "sg:phone":"+31 10 481 2547",
    "sg:postcode":"3083 HL",
    "sg:province":"South Holland",
    "wof:name":"Vermeulen Tweewieler",
    "wof:placetype":"venue"
},
  "geometry": {"coordinates":[4.48606,51.887791],"type":"Point"}
}