{
  "type": "Feature",
  "properties": {
    "addr:full":"Carnisseln 52 Rotterdam South Holland 3083 HL",
    "addr:housenumber":"52",
    "addr:postcode":"3083 hl",
    "addr:street":"Carnisseln",
    "iso:country":"NL",
    "sg:address":"Carnisseln 52",
    "sg:city":"Rotterdam",
    "sg:orig_category":"Fietsen En Bromfietsen",
    "sg:phone":"+31 10 481 2547",
    "sg:postcode":"3083 HL",
    "sg:province":"South Holland",
    "wof:name":"Vermeulen Tweewieler",
    "wof:placetype":"venue"
},
  "geometry": {"coordinates":[4.48606,51.887791],"type":"Point"}
}