{
  "type": "Feature",
  "properties": {
    "addr:full":"Midwouder Dorpsstraat 9 Midwoud Noord-Holland 1679 GA",
    "addr:housenumber":"9",
    "addr:postcode":"1679 ga",
    "addr:street":"Midwouder Dorpsstraat",
    "iso:country":"NL",
    "sg:address":"Midwouder Dorpsstraat 9",
    "sg:city":"Midwoud",
    "sg:orig_category":"Bloemen And Planten",
    "sg:phone":"+31 229 201 281",
    "sg:postcode":"1679 GA",
    "sg:province":"Noord-Holland",
    "wof:name":"C.C. Nooy",
    "wof:placetype":"venue"
},
  "geometry": {"coordinates":[5.0724611282,52.7133750916],"type":"Point"}
}