{
  "type": "Feature",
  "properties": {
    "addr:full":"Weteringschans 126 Amsterdam Noord-Holland 1017 XV",
    "addr:housenumber":"126",
    "addr:postcode":"1017 xv",
    "addr:street":"Weteringschans",
    "iso:country":"NL",
    "sg:address":"Weteringschans 126",
    "sg:city":"Amsterdam",
    "sg:orig_category":"Beeldende Kunstenaars",
    "sg:phone":"+31 20 627 6037",
    "sg:postcode":"1017 XV",
    "sg:province":"Noord-Holland",
    "sg:website":"http://www.come.to/dutchportraitgroup",
    "wof:name":"Portretschap, Het Nederlands",
    "wof:placetype":"venue"
},
  "geometry": {"coordinates":[4.896652,52.359188],"type":"Point"}
}