{
  "type": "Feature",
  "properties": {
    "addr:full":"Eendrachtstraat 4C Apeldoorn Gelderland 7335 CH",
    "addr:housenumber":"4c",
    "addr:postcode":"7335",
    "addr:street":"Eendrachtstraat;Gelderland",
    "iso:country":"NL",
    "sg:address":"Eendrachtstraat 4C",
    "sg:city":"Apeldoorn",
    "sg:orig_category":"Beautyfarms And Sauna'S",
    "sg:phone":"+31 55 541 0132",
    "sg:postcode":"7335 CH",
    "sg:province":"Gelderland",
    "wof:name":"Rodisun Center",
    "wof:placetype":"venue"
},
  "geometry": {"coordinates":[5.958859,52.200485],"type":"Point"}
}