{
  "type": "Feature",
  "properties": {
    "addr:full":"Oksewei 61 Joure Friesland 8501 TV",
    "addr:housenumber":"61",
    "addr:postcode":"8501 tv",
    "addr:street":"Oksewei",
    "iso:country":"NL",
    "sg:address":"Oksewei 61",
    "sg:city":"Joure",
    "sg:orig_category":"Kantoorbenodigdheden",
    "sg:phone":"+31 513 416 090",
    "sg:postcode":"8501 TV",
    "sg:province":"Friesland",
    "wof:name":"Kantoor-Noord",
    "wof:placetype":"venue"
},
  "geometry": {"coordinates":[5.8104119301,52.962726593],"type":"Point"}
}