{
  "type": "Feature",
  "properties": {
    "iso:country":"NL",
    "sg:address":"Thystr 28",
    "sg:city":"Rossum Ov",
    "sg:orig_category":"Bloemen En Planten",
    "sg:phone":"+31 541 626 380",
    "sg:postcode":"7596 KL",
    "sg:province":"NL.08",
    "wof:name":"Korero",
    "wof:placetype":"venue"
},
  "geometry": {"coordinates":[6.92388,52.351894],"type":"Point"}
}