{
  "type": "Feature",
  "properties": {
    "addr:full":"Brediusweg 57 Bussum Noord-Holland 1401 AD",
    "addr:housenumber":"57",
    "addr:postcode":"1401 ad",
    "addr:street":"Brediusweg",
    "iso:country":"NL",
    "sg:address":"Brediusweg 57",
    "sg:city":"Bussum",
    "sg:classifiers":[
        {
            "category":"Professional",
            "subcategory":"Accounting & Tax Preparation",
            "type":"Services"
        }
    ],
    "sg:phone":"+31 35 694 5570",
    "sg:postcode":"1401 AD",
    "sg:province":"Noord-Holland",
    "sg:tags":[
        "accountant"
    ],
    "wof:name":"Kantoor H. Welter Accountants En Administratiecons",
    "wof:placetype":"venue"
},
  "geometry": {"coordinates":[5.175627,52.282261],"type":"Point"}
}