{
  "type": "Feature",
  "properties": {
    "addr:full":"Heulstr 7 S Gravenhage Zuid-Holland 2514 ER",
    "addr:housenumber":"7 s",
    "addr:postcode":"2514 er",
    "addr:street":"Heulstr",
    "iso:country":"NL",
    "sg:address":"Heulstr 7",
    "sg:city":"S Gravenhage",
    "sg:orig_category":"Glas, Porselein En Aardewerk",
    "sg:phone":"+31 70 364 0083",
    "sg:postcode":"2514 ER",
    "sg:province":"Zuid-Holland",
    "sg:website":"http://www.saga-rd.com",
    "wof:name":"Saga Royal Design",
    "wof:placetype":"venue"
},
  "geometry": {"coordinates":[4.30935,52.084148],"type":"Point"}
}