{
  "type": "Feature",
  "properties": {
    "addr:full":"Spuistraat 8 Edam Noord-Holland 1135 AW",
    "addr:housenumber":"8",
    "addr:postcode":"1135 aw",
    "addr:street":"Spuistraat",
    "iso:country":"NL",
    "sg:address":"Spuistraat 8",
    "sg:city":"Edam",
    "sg:orig_category":"Public Relationbureaus",
    "sg:phone":"+31 299 372 044",
    "sg:postcode":"1135 AW",
    "sg:province":"Noord-Holland",
    "wof:name":"Syntaxis Communicatie",
    "wof:placetype":"venue"
},
  "geometry": {"coordinates":[5.048636,52.511742],"type":"Point"}
}