{
  "type": "Feature",
  "properties": {
    "addr:full":"Oudezijds Voorburgwal 249 Amsterdam Noord-Holland 1012 EZ",
    "addr:housenumber":"249",
    "addr:postcode":"1012 ez",
    "addr:street":"Oudezijds Voorburgwal",
    "iso:country":"NL",
    "sg:address":"Oudezijds Voorburgwal 249",
    "sg:city":"Amsterdam",
    "sg:orig_category":"Boekenuitgeverijen",
    "sg:phone":"+31 20 624 5781",
    "sg:postcode":"1012 EZ",
    "sg:province":"Noord-Holland",
    "wof:name":"Uitgeverij Huis Aan Drie Grachten Bv",
    "wof:placetype":"venue"
},
  "geometry": {"coordinates":[4.894667,52.369423],"type":"Point"}
}