{
  "type": "Feature",
  "properties": {
    "iso:country":"NL",
    "sg:address":"Nachtegaalln 29",
    "sg:city":"De Mortel",
    "sg:orig_category":"Bodemonderzoek",
    "sg:phone":"+31 492 319 434",
    "sg:postcode":"5425 RT",
    "sg:province":"North Brabant",
    "sg:website":"http://www.vlamings.nl",
    "wof:name":"Agro Lab Ned Bv",
    "wof:placetype":"venue"
},
  "geometry": {"coordinates":[5.722844,51.535484],"type":"Point"}
}