{
  "type": "Feature",
  "properties": {
    "iso:country":"NL",
    "sg:address":"Woldstr 3",
    "sg:city":"Meppel",
    "sg:orig_category":"Grafisch Ontwerpers",
    "sg:phone":"+31 522 242 448",
    "sg:postcode":"7941 LE",
    "sg:province":"Provincie Drenthe",
    "sg:website":"http://www.kampman.nl",
    "wof:name":"Kampman",
    "wof:placetype":"venue"
},
  "geometry": {"coordinates":[6.190639,52.697914],"type":"Point"}
}