{
  "type": "Feature",
  "properties": {
    "addr:full":"Smeekwg 49 Laren Nh Noord-Holland 1251 VK",
    "addr:housenumber":"49",
    "addr:postcode":"1251 vk",
    "addr:street":"Smeekwg",
    "iso:country":"NL",
    "sg:address":"Smeekwg 49",
    "sg:city":"Laren Nh",
    "sg:orig_category":"Schilders",
    "sg:phone":"+31 35 531 3247",
    "sg:postcode":"1251 VK",
    "sg:province":"Noord-Holland",
    "wof:name":"Meijer, J C H",
    "wof:placetype":"venue"
},
  "geometry": {"coordinates":[5.236574,52.246834],"type":"Point"}
}