{
  "type": "Feature",
  "properties": {
    "addr:full":"Stationsstraat 108 Deurne Noord-Brabant 5751 HJ",
    "addr:housenumber":"108",
    "addr:postcode":"5751 hj",
    "addr:street":"Stationsstraat",
    "iso:country":"NL",
    "sg:address":"Stationsstraat 108",
    "sg:city":"Deurne",
    "sg:orig_category":"Fietshandelaren",
    "sg:phone":"+31 493 312 354",
    "sg:postcode":"5751 HJ",
    "sg:province":"Noord-Brabant",
    "wof:name":"Manders Rijwielhandel",
    "wof:placetype":"venue"
},
  "geometry": {"coordinates":[5.786883,51.459068],"type":"Point"}
}