{
  "type": "Feature",
  "properties": {
    "addr:full":"Haagdk 254 Breda North Brabant 4811 TX",
    "addr:housenumber":"254",
    "addr:postcode":"4811 tx",
    "iso:country":"NL",
    "sg:address":"Haagdk 254",
    "sg:city":"Breda",
    "sg:orig_category":"Woninginrichting",
    "sg:phone":"+31 76 521 8680",
    "sg:postcode":"4811 TX",
    "sg:province":"North Brabant",
    "wof:name":"House & Home",
    "wof:placetype":"venue"
},
  "geometry": {"coordinates":[4.7662191391,51.5871696472],"type":"Point"}
}