{
  "type": "Feature",
  "properties": {
    "addr:full":"Wiltsangh 41-106 Nunspeet Gelderland 8070 AC",
    "addr:housenumber":"41-106",
    "addr:postcode":"8070 ac",
    "addr:street":"Wiltsangh;Gelderland",
    "iso:country":"NL",
    "sg:address":"Wiltsangh 41-106",
    "sg:city":"Nunspeet",
    "sg:classifiers":[
        {
            "category":"Recreation",
            "subcategory":"Amusement Park",
            "type":"Entertainment"
        }
    ],
    "sg:phone":"+31 341 262 650",
    "sg:postcode":"8070 AC",
    "sg:province":"Gelderland",
    "wof:name":"Hans Busch Productions",
    "wof:placetype":"venue"
},
  "geometry": {"coordinates":[5.814224,52.378056],"type":"Point"}
}