{
  "type": "Feature",
  "properties": {
    "addr:full":"Molenwyk 1 Blokzyl Overijssel 8356 ED",
    "addr:housenumber":"1",
    "addr:postcode":"8356 ed",
    "addr:street":"Molenwyk;Overijssel",
    "iso:country":"NL",
    "sg:address":"Molenwyk 1",
    "sg:city":"Blokzyl",
    "sg:orig_category":"Oud Metaal",
    "sg:phone":"+31 527 291 279",
    "sg:postcode":"8356 ED",
    "sg:province":"Overijssel",
    "wof:name":"Wijnand, M",
    "wof:placetype":"venue"
},
  "geometry": {"coordinates":[5.9605741501,52.7267684937],"type":"Point"}
}