{
  "type": "Feature",
  "properties": {
    "addr:full":"Elburgerweg 15 Dronten Flevoland 8251 RJ",
    "addr:housenumber":"15",
    "addr:postcode":"8251 rj",
    "addr:street":"Elburgerweg;Flevoland",
    "iso:country":"NL",
    "sg:address":"Elburgerweg 15",
    "sg:city":"Dronten",
    "sg:orig_category":"Granen, Zaden And Diervoeders Gh",
    "sg:phone":"+31 321 312 260",
    "sg:postcode":"8251 RJ",
    "sg:province":"Flevoland",
    "wof:name":"Overheul Agro Bv",
    "wof:placetype":"venue"
},
  "geometry": {"coordinates":[5.789329,52.501083],"type":"Point"}
}