{
  "type": "Feature",
  "properties": {
    "addr:full":"Grotestraat 231 Drunen North Brabant 5151 BL",
    "addr:housenumber":"231",
    "addr:postcode":"5151 bl",
    "addr:street":"Grotestraat",
    "iso:country":"NL",
    "sg:address":"Grotestraat 231",
    "sg:city":"Drunen",
    "sg:orig_category":"Fietshandelaren",
    "sg:phone":"+31 416 375 115",
    "sg:postcode":"5151 BL",
    "sg:province":"North Brabant",
    "wof:name":"Rijwielhandel Van Asten",
    "wof:placetype":"venue"
},
  "geometry": {"coordinates":[5.142308,51.68631],"type":"Point"}
}