{
  "type": "Feature",
  "properties": {
    "addr:full":"Mereveldplein 32 De Meern Utrecht 3454 CK",
    "addr:housenumber":"32",
    "addr:postcode":"3454 ck",
    "addr:street":"Mereveldplein",
    "iso:country":"NL",
    "sg:address":"Mereveldplein 32",
    "sg:city":"De Meern",
    "sg:orig_category":"Schoenen",
    "sg:phone":"+31 30 662 1907",
    "sg:postcode":"3454 CK",
    "sg:province":"Utrecht",
    "wof:name":"Schoenenmag J G Klabbers",
    "wof:placetype":"venue"
},
  "geometry": {"coordinates":[5.03872,52.079166],"type":"Point"}
}