{
  "type": "Feature",
  "properties": {
    "iso:country":"NL",
    "sg:address":"Noordkd 3A",
    "sg:city":"Veghel",
    "sg:orig_category":"Hengelsportartikelen",
    "sg:phone":"+31 413 352 995",
    "sg:postcode":"5462 EC",
    "sg:province":"Noord-Brabant",
    "wof:name":"Joep Van Pinxteren Lokvoeders",
    "wof:placetype":"venue"
},
  "geometry": {"coordinates":[5.54175,51.617222],"type":"Point"}
}