{
  "type": "Feature",
  "properties": {
    "addr:full":"Schiermonnikoog 92 Zaandam Noord-Holland 1506 ZR",
    "addr:housenumber":"92",
    "addr:postcode":"1506 zr",
    "addr:street":"Schiermonnikoog",
    "iso:country":"NL",
    "sg:address":"Schiermonnikoog 92",
    "sg:city":"Zaandam",
    "sg:orig_category":"Tekstschrijversters",
    "sg:phone":"+31 75 631 3623",
    "sg:postcode":"1506 ZR",
    "sg:province":"Noord-Holland",
    "wof:name":"Lorenzo",
    "wof:placetype":"venue"
},
  "geometry": {"coordinates":[4.807433,52.454571],"type":"Point"}
}