{
  "type": "Feature",
  "properties": {
    "iso:country":"NL",
    "sg:address":"Schiermonnikoog 92",
    "sg:city":"Zaandam",
    "sg:orig_category":"Tekstschrijversters",
    "sg:phone":"+31 75 631 3623",
    "sg:postcode":"1506 ZR",
    "sg:province":"Noord-Holland",
    "wof:name":"Lorenzo",
    "wof:placetype":"venue"
},
  "geometry": {"coordinates":[4.807433,52.454571],"type":"Point"}
}