{
  "type": "Feature",
  "properties": {
    "addr:full":"Hoofdstr 68 Terborg Gelderland 7061 CL",
    "addr:housenumber":"68",
    "addr:postcode":"7061",
    "addr:street":"Hoofdstr;Gelderland",
    "iso:country":"NL",
    "sg:address":"Hoofdstr 68",
    "sg:city":"Terborg",
    "sg:orig_category":"Bedrijfskleding",
    "sg:phone":"+31 315 324 966",
    "sg:postcode":"7061 CL",
    "sg:province":"Gelderland",
    "wof:name":"Beyenkorf, De",
    "wof:placetype":"venue"
},
  "geometry": {"coordinates":[6.357876,51.919373],"type":"Point"}
}