{
  "type": "Feature",
  "properties": {
    "addr:full":"Wouwsewg 174 Roosendaal Noord-Brabant 4703 BZ",
    "addr:housenumber":"174",
    "addr:postcode":"4703 bz",
    "iso:country":"NL",
    "sg:address":"Wouwsewg 174",
    "sg:city":"Roosendaal",
    "sg:orig_category":"Montagebedrijven",
    "sg:phone":"+31 165 549 895",
    "sg:postcode":"4703 BZ",
    "sg:province":"Noord-Brabant",
    "wof:name":"Wijk, Van",
    "wof:placetype":"venue"
},
  "geometry": {"coordinates":[4.434728,51.531551],"type":"Point"}
}