{
  "type": "Feature",
  "properties": {
    "addr:full":"Grote Berg 60 Eindhoven Noord-Brabant 5611 KL",
    "addr:housenumber":"60",
    "addr:postcode":"5611 kl",
    "addr:street":"Grote Berg",
    "iso:country":"NL",
    "sg:address":"Grote Berg 60",
    "sg:city":"Eindhoven",
    "sg:orig_category":"Kappers",
    "sg:phone":"+31 40 243 0085",
    "sg:postcode":"5611 KL",
    "sg:province":"Noord-Brabant",
    "wof:name":"Hairgalerie 60",
    "wof:placetype":"venue"
},
  "geometry": {"coordinates":[5.4841051102,51.4344711304],"type":"Point"}
}