{
  "type": "Feature",
  "properties": {
    "addr:full":"Brugstr 5A Swalmen Limburg 6071 JB",
    "addr:housenumber":"5a",
    "addr:postcode":"6071 jb",
    "addr:street":"Brugstr",
    "iso:country":"NL",
    "sg:address":"Brugstr 5A",
    "sg:city":"Swalmen",
    "sg:orig_category":"Woninginrichting",
    "sg:phone":"+31 475 502 782",
    "sg:postcode":"6071 JB",
    "sg:province":"Limburg",
    "wof:name":"Wijnands Bv",
    "wof:placetype":"venue"
},
  "geometry": {"coordinates":[6.0364031792,51.2307929993],"type":"Point"}
}