{
  "type": "Feature",
  "properties": {
    "iso:country":"NL",
    "sg:address":"Langstr 77",
    "sg:city":"Barneveld",
    "sg:orig_category":"Modelbouw",
    "sg:phone":"+31 342 421 937",
    "sg:postcode":"3771 BC",
    "sg:province":"Gelderland",
    "wof:name":"Teddy Speelgoedspeciaalzaak",
    "wof:placetype":"venue"
},
  "geometry": {"coordinates":[5.586776,52.138756],"type":"Point"}
}