{
  "type": "Feature",
  "properties": {
    "iso:country":"NL",
    "sg:address":"Morsstr 33",
    "sg:city":"Leiden",
    "sg:orig_category":"Kappers",
    "sg:phone":"+31 71 513 2415",
    "sg:postcode":"2312 BK",
    "sg:province":"South Holland",
    "wof:name":"Aderna",
    "wof:placetype":"venue"
},
  "geometry": {"coordinates":[4.4832611084,52.1620826721],"type":"Point"}
}