{
  "type": "Feature",
  "properties": {
    "addr:full":"Rijksstraatweg 21 Haarlem Noord-Holland 2023 HA",
    "addr:housenumber":"21",
    "addr:postcode":"2023 ha",
    "addr:street":"Rijksstraatweg",
    "iso:country":"NL",
    "sg:address":"Rijksstraatweg 21",
    "sg:city":"Haarlem",
    "sg:orig_category":"Advocaten And Juridische Adviseurs",
    "sg:phone":"+31 23 527 1373",
    "sg:postcode":"2023 HA",
    "sg:province":"Noord-Holland",
    "wof:name":"Advocatenkantoor Krol-Wisse",
    "wof:placetype":"venue"
},
  "geometry": {"coordinates":[4.644532,52.400307],"type":"Point"}
}