{
  "type": "Feature",
  "properties": {
    "iso:country":"NL",
    "sg:address":"Haltestr 63",
    "sg:city":"Zandvoort",
    "sg:orig_category":"Kappers",
    "sg:phone":"+31 23 571 2214",
    "sg:postcode":"2042 LL",
    "sg:province":"Noord-Holland",
    "wof:name":"Yvonne",
    "wof:placetype":"venue"
},
  "geometry": {"coordinates":[4.531851,52.374523],"type":"Point"}
}