{
  "type": "Feature",
  "properties": {
    "iso:country":"NL",
    "sg:address":"Vinkenln 38",
    "sg:city":"Malden",
    "sg:orig_category":"Schoonheidsinstituten",
    "sg:phone":"+31 24 358 0136",
    "sg:postcode":"6581 CL",
    "sg:province":"Gelderland",
    "wof:name":"Sevaux-Wessendorf, W De",
    "wof:placetype":"venue"
},
  "geometry": {"coordinates":[5.860468,51.786602],"type":"Point"}
}