{
  "type": "Feature",
  "properties": {
    "addr:full":"Bonksel 3 Asten North Brabant 5721 TP",
    "addr:housenumber":"3",
    "addr:postcode":"5721 tp",
    "addr:street":"Bonksel",
    "iso:country":"NL",
    "sg:address":"Bonksel 3",
    "sg:city":"Asten",
    "sg:orig_category":"Metaalbewerking",
    "sg:phone":"+31 493 492 034",
    "sg:postcode":"5721 TP",
    "sg:province":"North Brabant",
    "wof:name":"Aarts Metaal",
    "wof:placetype":"venue"
},
  "geometry": {"coordinates":[5.749823,51.414078],"type":"Point"}
}