{
  "type": "Feature",
  "properties": {
    "addr:full":"Assendorperstr 86 Ii Zwolle NL.08 8012 CB",
    "addr:housenumber":"86",
    "addr:postcode":"nl.08 8012 cb",
    "addr:street":"Assendorperstr",
    "iso:country":"NL",
    "sg:address":"Assendorperstr 86 Ii",
    "sg:city":"Zwolle",
    "sg:orig_category":"Kappers",
    "sg:phone":"+31 38 421 5771",
    "sg:postcode":"8012 CB",
    "sg:province":"NL.08",
    "wof:name":"Lentelink, J G",
    "wof:placetype":"venue"
},
  "geometry": {"coordinates":[6.088738,52.512566],"type":"Point"}
}