{
  "type": "Feature",
  "properties": {
    "iso:country":"NL",
    "sg:address":"Ellemare 263",
    "sg:city":"Rotterdam",
    "sg:orig_category":"Administratie- En Boekhoudkantoren",
    "sg:phone":"+31 10 410 2032",
    "sg:postcode":"3085 JS",
    "sg:province":"Zuid-Holland",
    "sg:website":"http://www.ericgroen.com",
    "wof:name":"Groen, Eric",
    "wof:placetype":"venue"
},
  "geometry": {"coordinates":[4.486042,51.870049],"type":"Point"}
}