{
  "type": "Feature",
  "properties": {
    "addr:full":"Zandloper 10A Winkel Illinois 1731 LM",
    "addr:housenumber":"10a",
    "addr:postcode":"1731 lm",
    "addr:street":"Zandloper",
    "iso:country":"NL",
    "sg:address":"Zandloper 10A",
    "sg:city":"Winkel",
    "sg:orig_category":"Motoren Verbrandingsmotoren",
    "sg:phone":"+31 224 543 300",
    "sg:postcode":"1731 LM",
    "sg:province":"Illinois",
    "wof:name":"Demco Bv",
    "wof:placetype":"venue"
},
  "geometry": {"coordinates":[-89.62237500000001,40.348873],"type":"Point"}
}