{
  "type": "Feature",
  "properties": {
    "iso:country":"NL",
    "sg:address":"Bloemstede 114",
    "sg:city":"Maarssen",
    "sg:orig_category":"Voetbalverenigingen",
    "sg:phone":"+31 346 562 318",
    "sg:postcode":"3608 TE",
    "sg:province":"Utrecht",
    "wof:name":"Bison Boys",
    "wof:placetype":"venue"
},
  "geometry": {"coordinates":[5.032721,52.125076],"type":"Point"}
}