{
  "type": "Feature",
  "properties": {
    "addr:full":"Oranjeln 38 Rozenburg Zh South Holland 3181 HA",
    "addr:housenumber":"38",
    "addr:postcode":"zh;3181 ha",
    "addr:street":"Oranjeln",
    "iso:country":"NL",
    "sg:address":"Oranjeln 38",
    "sg:city":"Rozenburg Zh",
    "sg:orig_category":"Autoschade- Herstelbedrijven",
    "sg:phone":"+31 181 215 581",
    "sg:postcode":"3181 HA",
    "sg:province":"South Holland",
    "wof:name":"Sven Autoherstelbedrijf",
    "wof:placetype":"venue"
},
  "geometry": {"coordinates":[4.241515,51.903381],"type":"Point"}
}