{
  "type": "Feature",
  "properties": {
    "addr:full":"Beukenhorstweg 27 Winterswijk Gelderland 7101 DJ",
    "addr:housenumber":"27",
    "addr:postcode":"7101 dj",
    "addr:street":"Beukenhorstweg;Gelderland",
    "iso:country":"NL",
    "sg:address":"Beukenhorstweg 27",
    "sg:city":"Winterswijk",
    "sg:orig_category":"Verzekeringen",
    "sg:phone":"+31 543 512 382",
    "sg:postcode":"7101 DJ",
    "sg:province":"Gelderland",
    "wof:name":"Brusse Assurantien Bv",
    "wof:placetype":"venue"
},
  "geometry": {"coordinates":[6.717651,51.973099],"type":"Point"}
}