{
  "type": "Feature",
  "properties": {
    "iso:country":"NL",
    "sg:address":"Postbus 2",
    "sg:city":"Schagerbrug",
    "sg:orig_category":"Notarissen En Notariskantoren",
    "sg:phone":"+31 224 571 641",
    "sg:postcode":"1750 AA",
    "sg:province":"Noord-Holland",
    "wof:name":"Zijper, Het",
    "wof:placetype":"venue"
},
  "geometry": {"coordinates":[4.76035,52.802601],"type":"Point"}
}