{
  "type": "Feature",
  "properties": {
    "addr:full":"Postbus 3125 Gouda Zuid-Holland 2800 CE",
    "addr:housenumber":"3125",
    "addr:postcode":"2800 ce",
    "addr:street":"Postbus",
    "iso:country":"NL",
    "sg:address":"Postbus 3125",
    "sg:city":"Gouda",
    "sg:orig_category":"Piano'S",
    "sg:phone":"+31 182 518 043",
    "sg:postcode":"2800 CE",
    "sg:province":"Zuid-Holland",
    "sg:website":"http://www.hetpianoatelier.nl",
    "wof:name":"Henk De Vries",
    "wof:placetype":"venue"
},
  "geometry": {"coordinates":[4.710715,52.010006],"type":"Point"}
}