{
  "type": "Feature",
  "properties": {
    "addr:full":"Tollenspark 17 'S Gravenzande Zuid-Holland 2692 DN",
    "addr:housenumber":"17",
    "addr:postcode":"2692 dn",
    "addr:street":"Tollenspark;' S",
    "iso:country":"NL",
    "sg:address":"Tollenspark 17",
    "sg:city":"'S Gravenzande",
    "sg:orig_category":"Hoger Onderwijs",
    "sg:phone":"+31 174 415 135",
    "sg:postcode":"2692 DN",
    "sg:province":"Zuid-Holland",
    "wof:name":"H. Dekkers",
    "wof:placetype":"venue"
},
  "geometry": {"coordinates":[4.159815,51.997704],"type":"Point"}
}