{
  "type": "Feature",
  "properties": {
    "addr:full":"Soestdykerstrwg 172 Hilversum North Holland 1213 XJ",
    "addr:housenumber":"172",
    "addr:postcode":"1213 xj",
    "iso:country":"NL",
    "sg:address":"Soestdykerstrwg 172",
    "sg:city":"Hilversum",
    "sg:orig_category":"Sportverenigingen En Ontspannings- Verenigingen",
    "sg:phone":"+31 35 685 7060",
    "sg:postcode":"1213 XJ",
    "sg:province":"North Holland",
    "wof:name":"Hilversumsche Golf Cl",
    "wof:placetype":"venue"
},
  "geometry": {"coordinates":[5.1695,52.228565],"type":"Point"}
}