{
  "type": "Feature",
  "properties": {
    "addr:full":"Blekerstr 113 Almere NL. 1315 AD",
    "addr:housenumber":"113",
    "addr:postcode":"1315 ad",
    "addr:street":"Nl.",
    "iso:country":"NL",
    "sg:address":"Blekerstr 113",
    "sg:city":"Almere",
    "sg:orig_category":"Verenigingen En Stichtingen",
    "sg:phone":"+31 36 534 7311",
    "sg:postcode":"1315 AD",
    "sg:province":"NL.",
    "wof:name":"Nbp Ned Bond Voor Pensioenbelangen",
    "wof:placetype":"venue"
},
  "geometry": {"coordinates":[5.215758,52.368793],"type":"Point"}
}