{
  "type": "Feature",
  "properties": {
    "addr:full":"Oostervelden 36 Bemmel Gelderland 6681 WX",
    "addr:housenumber":"36",
    "addr:postcode":"6681 wx",
    "addr:street":"Oostervelden;Gelderland",
    "iso:country":"NL",
    "sg:address":"Oostervelden 36",
    "sg:city":"Bemmel",
    "sg:orig_category":"Koeriersdiensten",
    "sg:phone":"+31 481 462 650",
    "sg:postcode":"6681 WX",
    "sg:province":"Gelderland",
    "wof:name":"D.V.G. Sneltransport",
    "wof:placetype":"venue"
},
  "geometry": {"coordinates":[5.907485,51.893272],"type":"Point"}
}