{
  "type": "Feature",
  "properties": {
    "addr:full":"Rijksstraatweg 107 Olst Overijssel 8121 ED",
    "addr:housenumber":"107",
    "addr:postcode":"8121 ed",
    "addr:street":"Rijksstraatweg",
    "iso:country":"NL",
    "sg:address":"Rijksstraatweg 107",
    "sg:city":"Olst",
    "sg:orig_category":"Verhuur Voertuigen Behalve Auto'S",
    "sg:phone":"+31 570 562 574",
    "sg:postcode":"8121 ED",
    "sg:province":"Overijssel",
    "wof:name":"De Wierholt",
    "wof:placetype":"venue"
},
  "geometry": {"coordinates":[6.110833,52.360733],"type":"Point"}
}