{
  "type": "Feature",
  "properties": {
    "addr:full":"De Burcht 14 Breda Noord-Brabant 4834 HE",
    "addr:housenumber":"14",
    "addr:postcode":"4834 he",
    "addr:street":"De Burcht",
    "iso:country":"NL",
    "sg:address":"De Burcht 14",
    "sg:city":"Breda",
    "sg:orig_category":"Kantoorartikelen",
    "sg:phone":"+31 76 565 4118",
    "sg:postcode":"4834 HE",
    "sg:province":"Noord-Brabant",
    "wof:name":"De Jong Boek- En Kantoorboekhandel",
    "wof:placetype":"venue"
},
  "geometry": {"coordinates":[4.8054938316,51.5725402832],"type":"Point"}
}