{
  "type": "Feature",
  "properties": {
    "addr:full":"Schoolstr 28 Huizen Noord-Holland 1271 SC",
    "addr:housenumber":"28",
    "addr:postcode":"1271 sc",
    "addr:street":"Schoolstr",
    "iso:country":"NL",
    "sg:address":"Schoolstr 28",
    "sg:city":"Huizen",
    "sg:orig_category":"Adviesbureaus Bouwkunde",
    "sg:phone":"+31 35 523 0770",
    "sg:postcode":"1271 SC",
    "sg:province":"Noord-Holland",
    "wof:name":"Next Dimension",
    "wof:placetype":"venue"
},
  "geometry": {"coordinates":[5.231321,52.299744],"type":"Point"}
}