{
  "type": "Feature",
  "properties": {
    "addr:full":"Hospesln 28 Haarlem Noord-Holland 2015 GK",
    "addr:housenumber":"28",
    "addr:postcode":"2015 gk",
    "addr:street":"Hospesln",
    "iso:country":"NL",
    "sg:address":"Hospesln 28",
    "sg:city":"Haarlem",
    "sg:orig_category":"Sportverenigingen En Ontspannings- Verenigingen",
    "sg:phone":"+31 23 544 1590",
    "sg:postcode":"2015 GK",
    "sg:province":"Noord-Holland",
    "wof:name":"Dss Honk En Softbalver",
    "wof:placetype":"venue"
},
  "geometry": {"coordinates":[4.642253,52.380562],"type":"Point"}
}