{
  "type": "Feature",
  "properties": {
    "iso:country":"NL",
    "sg:address":"Bergwg 268",
    "sg:city":"Rotterdam",
    "sg:orig_category":"Autorijscholen",
    "sg:phone":"+31 10 467 3322",
    "sg:postcode":"3035 BS",
    "sg:province":"South Holland",
    "wof:name":"Tempo",
    "wof:placetype":"venue"
},
  "geometry": {"coordinates":[4.47529,51.934818],"type":"Point"}
}