{
  "type": "Feature",
  "properties": {
    "iso:country":"NL",
    "sg:address":"Roterwg 7",
    "sg:city":"Echt",
    "sg:orig_category":"Administratie- En Boekhoudkantoren",
    "sg:phone":"+31 475 485 811",
    "sg:postcode":"6102 TM",
    "sg:province":"Limburg",
    "sg:website":"http://www.horstinklimburg.nl",
    "wof:name":"Horstink, T A",
    "wof:placetype":"venue"
},
  "geometry": {"coordinates":[5.8742,51.095325],"type":"Point"}
}