{
  "type": "Feature",
  "properties": {
    "addr:full":"Professor Krausstraat 14 Haarlem North Holland 2035 AE",
    "addr:housenumber":"14",
    "addr:postcode":"2035 ae",
    "addr:street":"Professor Krausstraat",
    "iso:country":"NL",
    "sg:address":"Professor Krausstraat 14",
    "sg:city":"Haarlem",
    "sg:orig_category":"Hout Gh",
    "sg:phone":"+31 23 536 7688",
    "sg:postcode":"2035 AE",
    "sg:province":"North Holland",
    "wof:name":"Rosiechels",
    "wof:placetype":"venue"
},
  "geometry": {"coordinates":[4.665395,52.362972],"type":"Point"}
}