{
  "type": "Feature",
  "properties": {
    "addr:full":"Oude Haagweg 10 'S Gravenhage Zuid-Holland 2552 EP",
    "addr:housenumber":"10",
    "addr:postcode":"2552 ep",
    "addr:street":"Oude Haagweg;' S",
    "iso:country":"NL",
    "sg:address":"Oude Haagweg 10",
    "sg:city":"'S Gravenhage",
    "sg:orig_category":"Autokeuringen",
    "sg:phone":"+31 70 391 1114",
    "sg:postcode":"2552 EP",
    "sg:province":"Zuid-Holland",
    "wof:name":"Garagebedrijf N.P. Van Leersum",
    "wof:placetype":"venue"
},
  "geometry": {"coordinates":[4.242808,52.05537],"type":"Point"}
}