{
  "type": "Feature",
  "properties": {
    "iso:country":"NL",
    "sg:address":"Dierensedijk 8",
    "sg:city":"Ellecom",
    "sg:orig_category":"Drukkerijen And Copyshops",
    "sg:phone":"+31 313 472 868",
    "sg:postcode":"6955 JG",
    "sg:province":"Gelderland",
    "wof:name":"Hecla",
    "wof:placetype":"venue"
},
  "geometry": {"coordinates":[6.125504,52.020042],"type":"Point"}
}