{
  "type": "Feature",
  "properties": {
    "iso:country":"NL",
    "sg:address":"Wilhelminaplein 15",
    "sg:city":"Geertruidenberg",
    "sg:classifiers":[
        {
            "category":"Shopping",
            "subcategory":"Gifts & Souvenirs",
            "type":"Retail Goods"
        }
    ],
    "sg:phone":"+31 162 520 684",
    "sg:postcode":"4931 DA",
    "sg:province":"Noord-Brabant",
    "sg:tags":[
        "geschenken"
    ],
    "wof:name":"Coramiek",
    "wof:placetype":"venue"
},
  "geometry": {"coordinates":[4.858335,51.701351],"type":"Point"}
}