{
  "type": "Feature",
  "properties": {
    "iso:country":"NL",
    "sg:address":"Telefoonstraat 2",
    "sg:city":"Venhorst",
    "sg:orig_category":"Autokeuringen",
    "sg:phone":"+31 492 351 570",
    "sg:postcode":"5428 GJ",
    "sg:province":"Noord-Brabant",
    "wof:name":"Vakgarage Kanters Vof",
    "wof:placetype":"venue"
},
  "geometry": {"coordinates":[5.733624,51.608662],"type":"Point"}
}