{
  "type": "Feature",
  "properties": {
    "iso:country":"NL",
    "sg:address":"Veerstraat 9",
    "sg:city":"Dreumel",
    "sg:orig_category":"Herenmodezaken",
    "sg:phone":"+31 487 572 542",
    "sg:postcode":"6621 AE",
    "sg:province":"Gelderland",
    "wof:name":"Daan Versteegh",
    "wof:placetype":"venue"
},
  "geometry": {"coordinates":[5.419197,51.837128],"type":"Point"}
}