{
  "type": "Feature",
  "properties": {
    "addr:full":"T Mannplaats 150 Rotterdam Zuid-Holland 3069 NE",
    "addr:housenumber":"150",
    "addr:postcode":"3069 ne",
    "addr:street":"T Mannplaats",
    "iso:country":"NL",
    "sg:address":"T Mannplaats 150",
    "sg:city":"Rotterdam",
    "sg:orig_category":"Bejaarden - Verzorgingstehuizen",
    "sg:phone":"+31 10 251 1400",
    "sg:postcode":"3069 NE",
    "sg:province":"Zuid-Holland",
    "wof:name":"Gerard Goosen Flat",
    "wof:placetype":"venue"
},
  "geometry": {"coordinates":[4.553788,51.964214],"type":"Point"}
}