{
  "type": "Feature",
  "properties": {
    "iso:country":"NL",
    "sg:address":"Hof Der Gedachten 13",
    "sg:city":"Amersfoort",
    "sg:orig_category":"Kappers",
    "sg:phone":"+31 33 455 8080",
    "sg:postcode":"3823 WB",
    "sg:province":"Utrecht",
    "wof:name":"Hairdesign",
    "wof:placetype":"venue"
},
  "geometry": {"coordinates":[5.3951539993,52.1875724792],"type":"Point"}
}