{
  "type": "Feature",
  "properties": {
    "addr:full":"Singraven 4 Zwijndrecht Zuid-Holland 3334 CV",
    "addr:housenumber":"4",
    "addr:postcode":"3334 cv",
    "addr:street":"Singraven",
    "iso:country":"NL",
    "sg:address":"Singraven 4",
    "sg:city":"Zwijndrecht",
    "sg:orig_category":"Partycatering And -Organisatie",
    "sg:phone":"+31 78 612 9665",
    "sg:postcode":"3334 CV",
    "sg:province":"Zuid-Holland",
    "wof:name":"De Woelige Roef",
    "wof:placetype":"venue"
},
  "geometry": {"coordinates":[4.59985,51.813992],"type":"Point"}
}