{
  "type": "Feature",
  "properties": {
    "iso:country":"NL",
    "sg:address":"G Bokelln 31",
    "sg:city":"Voorburg",
    "sg:orig_category":"Beeldende Kunstenaars",
    "sg:phone":"+31 70 386 8766",
    "sg:postcode":"2273 GT",
    "sg:province":"Zuid-Holland",
    "wof:name":"Haak, Tosca Van Den",
    "wof:placetype":"venue"
},
  "geometry": {"coordinates":[4.35977,52.07848],"type":"Point"}
}