{
  "type": "Feature",
  "properties": {
    "addr:full":"Reigersln 5 Voorhout South Holland 2215 NL",
    "addr:housenumber":"5",
    "addr:postcode":"2215 nl",
    "addr:street":"Reigersln",
    "iso:country":"NL",
    "sg:address":"Reigersln 5",
    "sg:city":"Voorhout",
    "sg:orig_category":"Verenigingen En Stichtingen",
    "sg:phone":"+31 252 215 340",
    "sg:postcode":"2215 NL",
    "sg:province":"South Holland",
    "wof:name":"Thuisfront Ned Priesters In Frankrijk",
    "wof:placetype":"venue"
},
  "geometry": {"coordinates":[4.48252,52.221874],"type":"Point"}
}