{
  "type": "Feature",
  "properties": {
    "addr:full":"J V Stolbergln 148 S Gravenhage South Holland 2595 CL",
    "addr:housenumber":"148",
    "addr:postcode":"2595",
    "addr:street":"J;Stolbergln;S Gravenhage",
    "iso:country":"NL",
    "sg:address":"J V Stolbergln 148",
    "sg:city":"S Gravenhage",
    "sg:classifiers":[
        {
            "category":"Shopping",
            "subcategory":"News",
            "type":"Retail Goods"
        }
    ],
    "sg:phone":"+31 70 304 6215",
    "sg:postcode":"2595 CL",
    "sg:province":"South Holland",
    "sg:tags":[
        "maandbladen",
        "en",
        "week-"
    ],
    "wof:name":"Bouwexpresse Bv",
    "wof:placetype":"venue"
},
  "geometry": {"coordinates":[4.3350701332,52.0814208984],"type":"Point"}
}