{
  "type": "Feature",
  "properties": {
    "addr:full":"Bredasewg 252 Tilburg North Brabant 5038 NM",
    "addr:housenumber":"252",
    "addr:postcode":"5038",
    "iso:country":"NL",
    "sg:address":"Bredasewg 252",
    "sg:city":"Tilburg",
    "sg:orig_category":"Kappers",
    "sg:phone":"+31 13 468 3560",
    "sg:postcode":"5038 NM",
    "sg:province":"North Brabant",
    "wof:name":"Figaro, De",
    "wof:placetype":"venue"
},
  "geometry": {"coordinates":[5.0665540695,51.5559158325],"type":"Point"}
}