{
  "type": "Feature",
  "properties": {
    "addr:full":"Kortenhoefsedk 197A Kortenhoef Noord-Holland 1241 NB",
    "addr:housenumber":"197a",
    "addr:postcode":"1241 nb",
    "iso:country":"NL",
    "sg:address":"Kortenhoefsedk 197A",
    "sg:city":"Kortenhoef",
    "sg:orig_category":"Administratie- En Boekhoudkantoren",
    "sg:phone":"+31 35 656 3427",
    "sg:postcode":"1241 NB",
    "sg:province":"Noord-Holland",
    "wof:name":"Assist",
    "wof:placetype":"venue"
},
  "geometry": {"coordinates":[5.086199,52.227097],"type":"Point"}
}