{
  "type": "Feature",
  "properties": {
    "addr:full":"Klooienbergln 583 Zwolle Overijssel 8031 GD",
    "addr:housenumber":"583",
    "addr:postcode":"8031 gd",
    "iso:country":"NL",
    "sg:address":"Klooienbergln 583",
    "sg:city":"Zwolle",
    "sg:orig_category":"Webdesign Bureaus",
    "sg:phone":"+31 38 421 9262",
    "sg:postcode":"8031 GD",
    "sg:province":"Overijssel",
    "sg:website":"http://www.thelookwebsites.nl",
    "wof:name":"Look, The",
    "wof:placetype":"venue"
},
  "geometry": {"coordinates":[6.075097084,52.5279045105],"type":"Point"}
}