{
  "type": "Feature",
  "properties": {
    "addr:full":"Dannestraat 2 Breukelen Ut Utrecht 3621 AE",
    "addr:housenumber":"2",
    "addr:postcode":"3621 ae",
    "addr:street":"Dannestraat",
    "iso:country":"NL",
    "sg:address":"Dannestraat 2",
    "sg:city":"Breukelen Ut",
    "sg:orig_category":"Boekenuitgeverijen",
    "sg:phone":"+31 346 265 886",
    "sg:postcode":"3621 AE",
    "sg:province":"Utrecht",
    "wof:name":"Van Lindonk Special Projects Bv",
    "wof:placetype":"venue"
},
  "geometry": {"coordinates":[5.003669,52.172005],"type":"Point"}
}