{
  "type": "Feature",
  "properties": {
    "iso:country":"NL",
    "sg:address":"Juristenlaan 11",
    "sg:city":"Tilburg",
    "sg:orig_category":"Verhuur Bouwmachines",
    "sg:phone":"+31 13 467 9128",
    "sg:postcode":"5037 GJ",
    "sg:province":"North Brabant",
    "wof:name":"Orit Bv",
    "wof:placetype":"venue"
},
  "geometry": {"coordinates":[5.041596,51.559605],"type":"Point"}
}