{
  "type": "Feature",
  "properties": {
    "addr:full":"Molenwg 44B Bunnik Utrecht 3981 CC",
    "addr:housenumber":"44b",
    "addr:postcode":"3981 cc",
    "addr:street":"Molenwg",
    "iso:country":"NL",
    "sg:address":"Molenwg 44B",
    "sg:city":"Bunnik",
    "sg:orig_category":"Kappers",
    "sg:phone":"+31 30 656 5022",
    "sg:postcode":"3981 CC",
    "sg:province":"Utrecht",
    "wof:name":"Marjan'S Kapsalon",
    "wof:placetype":"venue"
},
  "geometry": {"coordinates":[5.202264,52.065239],"type":"Point"}
}