{
  "type": "Feature",
  "properties": {
    "addr:full":"Oude Barnev Wg 38 Nykerk Gld Gelderland 3862 WX",
    "addr:housenumber":"38;3862",
    "addr:postcode":"wx",
    "addr:street":"Oude;Wg;Gld Gelderland",
    "iso:country":"NL",
    "sg:address":"Oude Barnev Wg 38",
    "sg:city":"Nykerk Gld",
    "sg:orig_category":"Begrafenisverzorging",
    "sg:phone":"+31 33 245 8941",
    "sg:postcode":"3862 WX",
    "sg:province":"Gelderland",
    "wof:name":"Meewis, G",
    "wof:placetype":"venue"
},
  "geometry": {"coordinates":[5.62297,52.20557],"type":"Point"}
}