{
  "type": "Feature",
  "properties": {
    "addr:full":"Hoornespln 137-151 Katwyk Zh Zuid-Holland 2221 BE",
    "addr:housenumber":"137-151",
    "addr:postcode":"2221",
    "addr:street":"Katwyk",
    "iso:country":"NL",
    "sg:address":"Hoornespln 137-151",
    "sg:city":"Katwyk Zh",
    "sg:orig_category":"Postkantoren",
    "sg:phone":"+31 71 402 6355",
    "sg:postcode":"2221 BE",
    "sg:province":"Zuid-Holland",
    "sg:website":"http://www.postkantoor.nl",
    "wof:name":"Postkantoor",
    "wof:placetype":"venue"
},
  "geometry": {"coordinates":[4.417624,52.206306],"type":"Point"}
}