{
  "type": "Feature",
  "properties": {
    "addr:full":"Commandeurswg 4A Bennekom Gelderland 6721 TZ",
    "addr:housenumber":"4a",
    "addr:postcode":"6721 tz",
    "addr:street":"Commandeurswg;Gelderland",
    "iso:country":"NL",
    "sg:address":"Commandeurswg 4A",
    "sg:city":"Bennekom",
    "sg:orig_category":"Verzekeringen - Verzekeringskantoren",
    "sg:phone":"+31 318 637 048",
    "sg:postcode":"6721 TZ",
    "sg:province":"Gelderland",
    "wof:name":"Berge, W F J Van Den",
    "wof:placetype":"venue"
},
  "geometry": {"coordinates":[5.675792,52.000942],"type":"Point"}
}