{
  "type": "Feature",
  "properties": {
    "addr:full":"Eschoter Engwg 12 Otterlo Gelderland 6731 EH",
    "addr:housenumber":"12",
    "addr:postcode":"6731 eh",
    "addr:street":"Gelderland",
    "iso:country":"NL",
    "sg:address":"Eschoter Engwg 12",
    "sg:city":"Otterlo",
    "sg:orig_category":"Schoonheidsinstituten",
    "sg:phone":"+31 318 591 406",
    "sg:postcode":"6731 EH",
    "sg:province":"Gelderland",
    "wof:name":"Berg Vof, Van Den",
    "wof:placetype":"venue"
},
  "geometry": {"coordinates":[5.75982,52.106789],"type":"Point"}
}