{
  "type": "Feature",
  "properties": {
    "iso:country":"NL",
    "sg:address":"Reeweg 16",
    "sg:city":"Nes Ameland",
    "sg:orig_category":"Kampeerterreinen",
    "sg:phone":"+31 519 542 736",
    "sg:postcode":"9163 GV",
    "sg:province":"Friesland",
    "wof:name":"T. Beijaard",
    "wof:placetype":"venue"
},
  "geometry": {"coordinates":[5.771999836,53.4450187683],"type":"Point"}
}