{
  "type": "Feature",
  "properties": {
    "addr:full":"Martinus Nijhofflaan 111 Kloetinge Zeeland 4481 DH",
    "addr:housenumber":"111",
    "addr:postcode":"4481 dh",
    "addr:street":"Martinus Nijhofflaan",
    "iso:country":"NL",
    "sg:address":"Martinus Nijhofflaan 111",
    "sg:city":"Kloetinge",
    "sg:orig_category":"Metaalwerken",
    "sg:phone":"+31 113 231 771",
    "sg:postcode":"4481 DH",
    "sg:province":"Zeeland",
    "wof:name":"De Stijl Zonwering",
    "wof:placetype":"venue"
},
  "geometry": {"coordinates":[3.912696,51.491848],"type":"Point"}
}