{
  "type": "Feature",
  "properties": {
    "iso:country":"NL",
    "sg:address":"Bulkseweg 9",
    "sg:city":"Kerkdriel",
    "sg:orig_category":"Autokeuringen",
    "sg:phone":"+31 418 634 186",
    "sg:postcode":"5331 PK",
    "sg:province":"Gelderland",
    "wof:name":"Ab Auto'S",
    "wof:placetype":"venue"
},
  "geometry": {"coordinates":[5.323864,51.77029],"type":"Point"}
}