{
  "type": "Feature",
  "properties": {
    "addr:full":"Eendrachtstr 4D Apeldoorn Gelderland 7335 CH",
    "addr:housenumber":"4d",
    "addr:postcode":"7335",
    "addr:street":"Gelderland",
    "iso:country":"NL",
    "sg:address":"Eendrachtstr 4D",
    "sg:city":"Apeldoorn",
    "sg:orig_category":"Kinderkleding",
    "sg:phone":"+31 6 24157611",
    "sg:postcode":"7335 CH",
    "sg:province":"Gelderland",
    "wof:name":"Wizzkids",
    "wof:placetype":"venue"
},
  "geometry": {"coordinates":[5.958859,52.200485],"type":"Point"}
}