{
  "type": "Feature",
  "properties": {
    "iso:country":"NL",
    "sg:address":"De Giezen 12",
    "sg:city":"Rijssen",
    "sg:orig_category":"Overheidsdiensten",
    "sg:phone":"+31 548 513 145",
    "sg:postcode":"7461 BB",
    "sg:province":"Overijssel",
    "wof:name":"Jongerencentrum Pand 11",
    "wof:placetype":"venue"
},
  "geometry": {"coordinates":[6.5216031075,52.3088874817],"type":"Point"}
}