{
  "type": "Feature",
  "properties": {
    "iso:country":"NL",
    "sg:address":"Afrikaanderpln 2",
    "sg:city":"Rotterdam",
    "sg:orig_category":"Bejaarden - Verzorgingstehuizen",
    "sg:phone":"+31 10 484 5555",
    "sg:postcode":"3072 EA",
    "sg:province":"Zuid-Holland",
    "wof:name":"Maasveld",
    "wof:placetype":"venue"
},
  "geometry": {"coordinates":[4.501808,51.901531],"type":"Point"}
}