{
  "type": "Feature",
  "properties": {
    "addr:full":"Schepenbergwg 3 Amsterdam Zuidoost North Holland 1105 AS",
    "addr:housenumber":"3",
    "addr:postcode":"1105 as",
    "addr:street":"Schepenbergwg",
    "iso:country":"NL",
    "sg:address":"Schepenbergwg 3",
    "sg:city":"Amsterdam Zuidoost",
    "sg:orig_category":"Hoogwerkers",
    "sg:phone":"+31 20 697 1518",
    "sg:postcode":"1105 AS",
    "sg:province":"North Holland",
    "sg:website":"http://www.skyworks.nl",
    "wof:name":"Skyworks Bv",
    "wof:placetype":"venue"
},
  "geometry": {"coordinates":[4.943584,52.296833],"type":"Point"}
}