{
  "type": "Feature",
  "properties": {
    "iso:country":"NL",
    "sg:address":"Concoursln 41-A",
    "sg:city":"Hoofddorp",
    "sg:orig_category":"Modelbouw",
    "sg:phone":"+31 23 565 4442",
    "sg:postcode":"2132 DJ",
    "sg:province":"North Holland",
    "sg:website":"http://www.modelsport.nl",
    "wof:name":"Modelsport",
    "wof:placetype":"venue"
},
  "geometry": {"coordinates":[4.69296,52.305393],"type":"Point"}
}