{
  "type": "Feature",
  "properties": {
    "iso:country":"NL",
    "sg:address":"Bergseln 245B",
    "sg:city":"Rotterdam",
    "sg:orig_category":"Fietsen En Bromfietsen",
    "sg:phone":"+31 10 466 9659",
    "sg:postcode":"3038 CB",
    "sg:province":"Zuid-Holland",
    "wof:name":"Quick Rijwielservice",
    "wof:placetype":"venue"
},
  "geometry": {"coordinates":[4.46465,51.935558],"type":"Point"}
}