{
  "type": "Feature",
  "properties": {
    "addr:full":"Varroln 51 Utrecht Utrecht 3584 BT",
    "addr:housenumber":"51",
    "addr:postcode":"3584 bt",
    "addr:street":"Varroln",
    "iso:country":"NL",
    "sg:address":"Varroln 51",
    "sg:city":"Utrecht",
    "sg:orig_category":"Banken",
    "sg:phone":"+31 30 252 4252",
    "sg:postcode":"3584 BT",
    "sg:province":"Utrecht",
    "wof:name":"Fortis",
    "wof:placetype":"venue"
},
  "geometry": {"coordinates":[5.16837,52.08736],"type":"Point"}
}