{
  "type": "Feature",
  "properties": {
    "addr:full":"Pepynstr 26 Eindhoven North Brabant 5616 EN",
    "addr:housenumber":"26",
    "addr:postcode":"5616 en",
    "addr:street":"Pepynstr",
    "iso:country":"NL",
    "sg:address":"Pepynstr 26",
    "sg:city":"Eindhoven",
    "sg:orig_category":"Autorijscholen",
    "sg:phone":"+31 6 27474829",
    "sg:postcode":"5616 EN",
    "sg:province":"North Brabant",
    "wof:name":"Coskun, I",
    "wof:placetype":"venue"
},
  "geometry": {"coordinates":[5.484105,51.434471],"type":"Point"}
}