{
  "type": "Feature",
  "properties": {
    "addr:full":"Mangaanstr 34 S Gravenhage Zuid-Holland 2544 DW",
    "addr:housenumber":"34;gravenhage",
    "addr:postcode":"2544 dw",
    "addr:street":"Mangaanstr;S",
    "iso:country":"NL",
    "sg:address":"Mangaanstr 34",
    "sg:city":"S Gravenhage",
    "sg:orig_category":"Drukkerijen",
    "sg:phone":"+31 70 367 1635",
    "sg:postcode":"2544 DW",
    "sg:province":"Zuid-Holland",
    "wof:name":"Matveld Bv",
    "wof:placetype":"venue"
},
  "geometry": {"coordinates":[4.25157,52.039551],"type":"Point"}
}