{
  "type": "Feature",
  "properties": {
    "addr:full":"Fahrenheitstraat 35 Harderwijk Gelderland 3846 CC",
    "addr:housenumber":"35",
    "addr:postcode":"3846 cc",
    "addr:street":"Fahrenheitstraat;Gelderland",
    "iso:country":"NL",
    "sg:address":"Fahrenheitstraat 35",
    "sg:city":"Harderwijk",
    "sg:orig_category":"Huishoudapparatuur, Televisies And Radio'S",
    "sg:phone":"+31 341 467 070",
    "sg:postcode":"3846 CC",
    "sg:province":"Gelderland",
    "wof:name":"Diesel Buchli Bv",
    "wof:placetype":"venue"
},
  "geometry": {"coordinates":[5.645654,52.361748],"type":"Point"}
}