{
  "type": "Feature",
  "properties": {
    "addr:full":"Kampenringwg 19 Gouda Zuid-Holland 2803 PE",
    "addr:housenumber":"19",
    "addr:postcode":"2803 pe",
    "addr:street":"Kampenringwg",
    "iso:country":"NL",
    "sg:address":"Kampenringwg 19",
    "sg:city":"Gouda",
    "sg:orig_category":"Verf En Lak",
    "sg:phone":"+31 182 570 888",
    "sg:postcode":"2803 PE",
    "sg:province":"Zuid-Holland",
    "wof:name":"Sikkens",
    "wof:placetype":"venue"
},
  "geometry": {"coordinates":[4.673464,52.025471],"type":"Point"}
}