{
  "type": "Feature",
  "properties": {
    "addr:full":"Hoogstr 180 Schiedam Zuid-Holland 3111 HP",
    "addr:housenumber":"180",
    "addr:postcode":"3111 hp",
    "iso:country":"NL",
    "sg:address":"Hoogstr 180",
    "sg:city":"Schiedam",
    "sg:orig_category":"Noten",
    "sg:phone":"+31 10 426 0868",
    "sg:postcode":"3111 HP",
    "sg:province":"Zuid-Holland",
    "sg:website":"http://www.cestbon.nl",
    "wof:name":"C'Est Bon",
    "wof:placetype":"venue"
},
  "geometry": {"coordinates":[4.39816,51.918472],"type":"Point"}
}