{
  "type": "Feature",
  "properties": {
    "iso:country":"NL",
    "sg:address":"Lenghengang 30",
    "sg:city":"Dordrecht",
    "sg:orig_category":"Technische Studies And Onderzoek",
    "sg:phone":"+31 78 614 3435",
    "sg:postcode":"3311 NP",
    "sg:province":"South Holland",
    "wof:name":"Topoplan",
    "wof:placetype":"venue"
},
  "geometry": {"coordinates":[4.668397,51.813068],"type":"Point"}
}