{
  "type": "Feature",
  "properties": {
    "addr:full":"Torenstraat 12 Vught Noord-Brabant 5261 BR",
    "addr:housenumber":"12",
    "addr:postcode":"5261 br",
    "addr:street":"Torenstraat",
    "iso:country":"NL",
    "sg:address":"Torenstraat 12",
    "sg:city":"Vught",
    "sg:orig_category":"Airconditioning And Ventilatie",
    "sg:phone":"+31 73 657 9000",
    "sg:postcode":"5261 BR",
    "sg:province":"Noord-Brabant",
    "wof:name":"Broeders Technische Installaties Bv",
    "wof:placetype":"venue"
},
  "geometry": {"coordinates":[5.299197,51.659557],"type":"Point"}
}