{
  "type": "Feature",
  "properties": {
    "addr:full":"Julianastraat 31 Berghem Noord-Brabant 5351 AL",
    "addr:housenumber":"31",
    "addr:postcode":"5351 al",
    "addr:street":"Julianastraat",
    "iso:country":"NL",
    "sg:address":"Julianastraat 31",
    "sg:city":"Berghem",
    "sg:orig_category":"Loodgieterswerk, Verwarming And Sanitaire Installaties",
    "sg:phone":"+31 412 403 616",
    "sg:postcode":"5351 AL",
    "sg:province":"Noord-Brabant",
    "wof:name":"Montagebedrijf Van Den Akker",
    "wof:placetype":"venue"
},
  "geometry": {"coordinates":[5.565099,51.771236],"type":"Point"}
}