{
  "type": "Feature",
  "properties": {
    "iso:country":"NL",
    "sg:address":"Gen Cronjestr 122",
    "sg:city":"Haarlem",
    "sg:orig_category":"Schoenen",
    "sg:phone":"+31 23 525 8337",
    "sg:postcode":"2021 JM",
    "sg:province":"North Holland",
    "wof:name":"Brossois, De",
    "wof:placetype":"venue"
},
  "geometry": {"coordinates":[4.642356,52.395161],"type":"Point"}
}