{
  "type": "Feature",
  "properties": {
    "addr:full":"Boersteeg 2 Groesbeek Gelderland 6562 LX",
    "addr:housenumber":"2",
    "addr:postcode":"6562 lx",
    "addr:street":"Boersteeg;Gelderland",
    "iso:country":"NL",
    "sg:address":"Boersteeg 2",
    "sg:city":"Groesbeek",
    "sg:orig_category":"Marktonderzoekbureaus",
    "sg:phone":"+31 24 397 5093",
    "sg:postcode":"6562 LX",
    "sg:province":"Gelderland",
    "wof:name":"G.J. Hofmans Dienstencentrum Bv",
    "wof:placetype":"venue"
},
  "geometry": {"coordinates":[5.97111,51.782021],"type":"Point"}
}