{
  "type": "Feature",
  "properties": {
    "addr:full":"Leusderwg 155 Amersfoort Utrecht 3818 AC",
    "addr:housenumber":"155",
    "addr:postcode":"3818 ac",
    "iso:country":"NL",
    "sg:address":"Leusderwg 155",
    "sg:city":"Amersfoort",
    "sg:orig_category":"Kappers",
    "sg:phone":"+31 33 463 7913",
    "sg:postcode":"3818 AC",
    "sg:province":"Utrecht",
    "sg:website":"http://www.cosmo.nl/",
    "wof:name":"Cosmo",
    "wof:placetype":"venue"
},
  "geometry": {"coordinates":[5.3787250519,52.1416702271],"type":"Point"}
}