{
  "type": "Feature",
  "properties": {
    "addr:full":"K Nieuwstr 29 Utrecht Utrecht 3512 NM",
    "addr:housenumber":"29",
    "addr:postcode":"3512",
    "addr:street":"Nieuwstr",
    "iso:country":"NL",
    "sg:address":"K Nieuwstr 29",
    "sg:city":"Utrecht",
    "sg:orig_category":"Journalisten Freelance",
    "sg:phone":"+31 30 234 0113",
    "sg:postcode":"3512 NM",
    "sg:province":"Utrecht",
    "wof:name":"Mcb Script",
    "wof:placetype":"venue"
},
  "geometry": {"coordinates":[5.121959,52.089497],"type":"Point"}
}