{
  "type": "Feature",
  "properties": {
    "iso:country":"NL",
    "sg:address":"Lepelaar 29",
    "sg:city":"Nieuwegein",
    "sg:orig_category":"Diverse Opleidingen And Onderwijs",
    "sg:phone":"+31 30 603 7422",
    "sg:postcode":"3435 DT",
    "sg:province":"Utrecht",
    "wof:name":"Arendshorst Informatica-Opleidingen",
    "wof:placetype":"venue"
},
  "geometry": {"coordinates":[5.079715,52.020409],"type":"Point"}
}