{
  "type": "Feature",
  "properties": {
    "addr:full":"Achterom 14 Utrecht Utrecht 3512 KT",
    "addr:housenumber":"14",
    "addr:postcode":"3512 kt",
    "addr:street":"Achterom",
    "iso:country":"NL",
    "sg:address":"Achterom 14",
    "sg:city":"Utrecht",
    "sg:orig_category":"Loopbaanbegeleiding",
    "sg:phone":"+31 30 234 2271",
    "sg:postcode":"3512 KT",
    "sg:province":"Utrecht",
    "sg:website":"http://www.els.maas.nl",
    "wof:name":"Maas, Els",
    "wof:placetype":"venue"
},
  "geometry": {"coordinates":[5.127442,52.088345],"type":"Point"}
}