{
  "type": "Feature",
  "properties": {
    "addr:full":"Mandefjild 15A Bakkeveen South Carolina 9243 SC",
    "addr:housenumber":"15a",
    "addr:postcode":"9243 sc",
    "addr:street":"Mandefjild",
    "iso:country":"NL",
    "sg:address":"Mandefjild 15A",
    "sg:city":"Bakkeveen",
    "sg:orig_category":"Grondwerken",
    "sg:phone":"+31 516 425 010",
    "sg:postcode":"9243 SC",
    "sg:province":"South Carolina",
    "sg:website":"http://www.kok-bakkeveen.nl",
    "wof:name":"Kok Bakkeveen, Gebr",
    "wof:placetype":"venue"
},
  "geometry": {"coordinates":[-80.947441,33.624981],"type":"Point"}
}