{
  "type": "Feature",
  "properties": {
    "addr:full":"Coenensparkstr 6 Zutphen Gelderland 7202 AN",
    "addr:housenumber":"6",
    "addr:postcode":"7202 an",
    "addr:street":"Coenensparkstr;Gelderland",
    "iso:country":"NL",
    "sg:address":"Coenensparkstr 6",
    "sg:city":"Zutphen",
    "sg:orig_category":"Meubelen",
    "sg:phone":"+31 575 514 990",
    "sg:postcode":"7202 AN",
    "sg:province":"Gelderland",
    "wof:name":"Lederland Zutphen Bv",
    "wof:placetype":"venue"
},
  "geometry": {"coordinates":[6.190667,52.146545],"type":"Point"}
}