{
  "type": "Feature",
  "properties": {
    "addr:full":"Vijverlaan 30 Scherpenzeel Gld Gelderland 3925 EM",
    "addr:housenumber":"30",
    "addr:postcode":"3925 em",
    "addr:street":"Vijverlaan;Gld Gelderland",
    "iso:country":"NL",
    "sg:address":"Vijverlaan 30",
    "sg:city":"Scherpenzeel Gld",
    "sg:orig_category":"Postorderbedrijven",
    "sg:phone":"+31 33 277 3172",
    "sg:postcode":"3925 EM",
    "sg:province":"Gelderland",
    "wof:name":"Herbalife Nanny",
    "wof:placetype":"venue"
},
  "geometry": {"coordinates":[5.484544,52.07597],"type":"Point"}
}