{
  "type": "Feature",
  "properties": {
    "addr:full":"Keesomln 13 Den Burg Noord-Holland 1791 DA",
    "addr:housenumber":"13",
    "addr:postcode":"1791 da",
    "addr:street":"Keesomln",
    "iso:country":"NL",
    "sg:address":"Keesomln 13",
    "sg:city":"Den Burg",
    "sg:orig_category":"Beveiliging",
    "sg:phone":"+31 222 314 779",
    "sg:postcode":"1791 DA",
    "sg:province":"Noord-Holland",
    "wof:name":"Beveiligingsservice Texel",
    "wof:placetype":"venue"
},
  "geometry": {"coordinates":[-94.071686,34.232082],"type":"Point"}
}