{
  "type": "Feature",
  "properties": {
    "iso:country":"NL",
    "sg:address":"Staalstr 13",
    "sg:city":"Ridderkerk",
    "sg:orig_category":"Keuken- Inbouwapparatuur",
    "sg:phone":"+31 180 420 488",
    "sg:postcode":"2984 AJ",
    "sg:province":"Zuid-Holland",
    "sg:website":"http://www.quooker.nl",
    "wof:name":"Quooker",
    "wof:placetype":"venue"
},
  "geometry": {"coordinates":[4.607657,51.873962],"type":"Point"}
}