{
  "type": "Feature",
  "properties": {
    "addr:full":"Benesserln 35 Uitgeest Noord-Holland 1911 VC",
    "addr:housenumber":"35",
    "addr:postcode":"1911 vc",
    "addr:street":"Benesserln",
    "iso:country":"NL",
    "sg:address":"Benesserln 35",
    "sg:city":"Uitgeest",
    "sg:orig_category":"Kinderopvang",
    "sg:phone":"+31 251 316 023",
    "sg:postcode":"1911 VC",
    "sg:province":"Noord-Holland",
    "wof:name":"Regenboog, De",
    "wof:placetype":"venue"
},
  "geometry": {"coordinates":[4.713915,52.528736],"type":"Point"}
}