{
  "type": "Feature",
  "properties": {
    "addr:full":"Zeddamsewg 41 Etten Gld Gelderland 7075 ED",
    "addr:housenumber":"41",
    "addr:postcode":"7075 ed",
    "addr:street":"Zeddamsewg;Gld Gelderland",
    "iso:country":"NL",
    "sg:address":"Zeddamsewg 41",
    "sg:city":"Etten Gld",
    "sg:orig_category":"Verzekeringen - Verzekeringskantoren",
    "sg:phone":"+31 315 683 007",
    "sg:postcode":"7075 ED",
    "sg:province":"Gelderland",
    "sg:website":"http://www.theohof.com",
    "wof:name":"Hof Vof",
    "wof:placetype":"venue"
},
  "geometry": {"coordinates":[6.3428301811,51.9155464172],"type":"Point"}
}