{
  "type": "Feature",
  "properties": {
    "addr:full":"Koudhoornsewg 54 Garderen Gelderland 3886 PK",
    "addr:housenumber":"54",
    "addr:postcode":"3886 pk",
    "addr:street":"Koudhoornsewg;Gelderland",
    "iso:country":"NL",
    "sg:address":"Koudhoornsewg 54",
    "sg:city":"Garderen",
    "sg:orig_category":"Oldtimers",
    "sg:phone":"+31 577 462 381",
    "sg:postcode":"3886 PK",
    "sg:province":"Gelderland",
    "wof:name":"Koudhoorn Bv, De",
    "wof:placetype":"venue"
},
  "geometry": {"coordinates":[5.70105,52.233665],"type":"Point"}
}