{
  "type": "Feature",
  "properties": {
    "addr:full":"Doejenburg 7 Eck En Wiel Gelderland 4024 HE",
    "addr:housenumber":"7",
    "addr:postcode":"4024 he",
    "addr:street":"Doejenburg",
    "iso:country":"NL",
    "sg:address":"Doejenburg 7",
    "sg:city":"Eck En Wiel",
    "sg:orig_category":"Houtverwerking",
    "sg:phone":"+31 344 692 637",
    "sg:postcode":"4024 HE",
    "sg:province":"Gelderland",
    "wof:name":"J.G. Van Der Heiden",
    "wof:placetype":"venue"
},
  "geometry": {"coordinates":[5.442108,51.96386],"type":"Point"}
}