{
  "type": "Feature",
  "properties": {
    "addr:full":"Edisonlaan 16 Weert Limburg 6003 DB",
    "addr:housenumber":"16",
    "addr:postcode":"6003 db",
    "addr:street":"Edisonlaan",
    "iso:country":"NL",
    "sg:address":"Edisonlaan 16",
    "sg:city":"Weert",
    "sg:orig_category":"Waterbeheer",
    "sg:phone":"+31 495 434 700",
    "sg:postcode":"6003 DB",
    "sg:province":"Limburg",
    "wof:name":"Nv Waterleiding Maatschappij Limburg",
    "wof:placetype":"venue"
},
  "geometry": {"coordinates":[5.7308697701,51.2719917297],"type":"Point"}
}