{
  "type": "Feature",
  "properties": {
    "addr:full":"Langekerkstr 27 Huissen Gelderland 6851 BM",
    "addr:housenumber":"27",
    "addr:postcode":"6851 bm",
    "addr:street":"Langekerkstr;Gelderland",
    "iso:country":"NL",
    "sg:address":"Langekerkstr 27",
    "sg:city":"Huissen",
    "sg:orig_category":"Architecten En Architectenbureaus",
    "sg:phone":"+31 26 325 5656",
    "sg:postcode":"6851 BM",
    "sg:province":"Gelderland",
    "sg:website":"http://www.vandelooienjacobs.nl",
    "wof:name":"Looi En Jacobs Bv, Van De",
    "wof:placetype":"venue"
},
  "geometry": {"coordinates":[5.940903,51.937565],"type":"Point"}
}