{
  "type": "Feature",
  "properties": {
    "addr:full":"Nieuwland 13 Boxtel Noord-Brabant 5283 AJ",
    "addr:housenumber":"13",
    "addr:postcode":"5283 aj",
    "addr:street":"Nieuwland",
    "iso:country":"NL",
    "sg:address":"Nieuwland 13",
    "sg:city":"Boxtel",
    "sg:orig_category":"Boekhouders",
    "sg:phone":"+31 411 610 110",
    "sg:postcode":"5283 AJ",
    "sg:province":"Noord-Brabant",
    "wof:name":"Kastelijn",
    "wof:placetype":"venue"
},
  "geometry": {"coordinates":[5.342577,51.593266],"type":"Point"}
}