{
  "type": "Feature",
  "properties": {
    "addr:full":"Da Costakd 158 Amsterdam North Holland 1053 XC",
    "addr:housenumber":"158",
    "addr:postcode":"1053 xc",
    "iso:country":"NL",
    "sg:address":"Da Costakd 158",
    "sg:city":"Amsterdam",
    "sg:orig_category":"Meubelmakerijen",
    "sg:phone":"+31 20 685 4152",
    "sg:postcode":"1053 XC",
    "sg:province":"North Holland",
    "wof:name":"Ttt",
    "wof:placetype":"venue"
},
  "geometry": {"coordinates":[4.86733,52.366638],"type":"Point"}
}