{
  "type": "Feature",
  "properties": {
    "iso:country":"NL",
    "sg:address":"Signaal 7",
    "sg:city":"Purmerend",
    "sg:classifiers":[
        {
            "category":"Wholesale",
            "subcategory":"Meat",
            "type":"Manufacturing & Wholesale Goods"
        }
    ],
    "sg:phone":"+31 299 474 050",
    "sg:postcode":"1446 WT",
    "sg:province":"Noord-Holland",
    "sg:tags":[
        "regeltechniek",
        "en",
        "meet-"
    ],
    "wof:name":"Maelok Bv",
    "wof:placetype":"venue"
},
  "geometry": {"coordinates":[5.006983,52.511265],"type":"Point"}
}