{
  "type": "Feature",
  "properties": {
    "iso:country":"NL",
    "sg:address":"Jister 53",
    "sg:city":"Heerenveen",
    "sg:classifiers":[
        {
            "category":"Fast Food",
            "type":"Food & Drink"
        }
    ],
    "sg:phone":"+31 513 627 405",
    "sg:postcode":"8446 CG",
    "sg:province":"Provincie Friesland",
    "sg:tags":[
        "afhaal",
        "restaurant"
    ],
    "wof:name":"Cafetaria De Greiden",
    "wof:placetype":"venue"
},
  "geometry": {"coordinates":[5.91523,52.953278],"type":"Point"}
}