{
  "type": "Feature",
  "properties": {
    "addr:full":"Alkmaardermeer 30 Rotterdam Zuid-Holland 3068 KB",
    "addr:housenumber":"30",
    "addr:postcode":"3068 kb",
    "addr:street":"Alkmaardermeer",
    "iso:country":"NL",
    "sg:address":"Alkmaardermeer 30",
    "sg:city":"Rotterdam",
    "sg:classifiers":[
        {
            "category":"Professional",
            "subcategory":"Accounting & Tax Preparation",
            "type":"Services"
        }
    ],
    "sg:phone":"+31 10 421 9228",
    "sg:postcode":"3068 KB",
    "sg:province":"Zuid-Holland",
    "sg:tags":[
        "accountant"
    ],
    "wof:name":"F.J. Breevoort Assurantien",
    "wof:placetype":"venue"
},
  "geometry": {"coordinates":[4.57948,51.9646],"type":"Point"}
}