{
  "type": "Feature",
  "properties": {
    "addr:full":"J V Arkelstr 15 Raalte Overijssel 8101 EN",
    "addr:housenumber":"15",
    "addr:postcode":"8101 en",
    "addr:street":"J;Arkelstr",
    "iso:country":"NL",
    "sg:address":"J V Arkelstr 15",
    "sg:city":"Raalte",
    "sg:orig_category":"Ziekenhuizen, Sanatoria, Verpleeghuizen",
    "sg:phone":"+31 572 358 283",
    "sg:postcode":"8101 EN",
    "sg:province":"Overijssel",
    "wof:name":"Hartkamp, De",
    "wof:placetype":"venue"
},
  "geometry": {"coordinates":[6.274628,52.387249],"type":"Point"}
}