{
  "type": "Feature",
  "properties": {
    "addr:full":"Sluisweg 2 'S Hertogenbosch North Brabant 5235 AH",
    "addr:housenumber":"2 ' s",
    "addr:postcode":"5235 ah",
    "addr:street":"Sluisweg;Hertogenbosch",
    "iso:country":"NL",
    "sg:address":"Sluisweg 2",
    "sg:city":"'S Hertogenbosch",
    "sg:classifiers":[
        {
            "category":"Food & Beverages",
            "subcategory":"Fruits & Vegetables",
            "type":"Retail Goods"
        }
    ],
    "sg:phone":"+31 73 642 1061",
    "sg:postcode":"5235 AH",
    "sg:province":"North Brabant",
    "sg:tags":[
        "groenten"
    ],
    "wof:name":"J W De Kleijn",
    "wof:placetype":"venue"
},
  "geometry": {"coordinates":[5.309281,51.731548],"type":"Point"}
}