{
  "type": "Feature",
  "properties": {
    "addr:full":"Hisveltplein 7 Arnhem Gelderland 6826 LE",
    "addr:housenumber":"7",
    "addr:postcode":"6826 le",
    "addr:street":"Hisveltplein",
    "iso:country":"NL",
    "sg:address":"Hisveltplein 7",
    "sg:city":"Arnhem",
    "sg:orig_category":"Beveiligingsdiensten And Bewakingsbedrijven",
    "sg:phone":"+31 26 362 9291",
    "sg:postcode":"6826 LE",
    "sg:province":"Gelderland",
    "wof:name":"Prened Beveiliging Bv",
    "wof:placetype":"venue"
},
  "geometry": {"coordinates":[5.953009,51.984276],"type":"Point"}
}