{
  "type": "Feature",
  "properties": {
    "addr:full":"Marienhageln 2 Weert Limburg 6001 TP",
    "addr:housenumber":"2",
    "addr:postcode":"6001 tp",
    "addr:street":"Marienhageln",
    "iso:country":"NL",
    "sg:address":"Marienhageln 2",
    "sg:city":"Weert",
    "sg:orig_category":"Scholen Voor Basisonderwijs",
    "sg:phone":"+31 495 533 086",
    "sg:postcode":"6001 TP",
    "sg:province":"Limburg",
    "wof:name":"Fatima Kath",
    "wof:placetype":"venue"
},
  "geometry": {"coordinates":[5.701299,51.251766],"type":"Point"}
}