{
  "type": "Feature",
  "properties": {
    "addr:full":"Mr W M O V Veenwg 8A Burgum Georgia 9251 GA",
    "addr:housenumber":"8a",
    "addr:postcode":"9251 ga",
    "addr:street":"W;Veenwg;Georgia",
    "iso:country":"NL",
    "sg:address":"Mr W M O V Veenwg 8A",
    "sg:city":"Burgum",
    "sg:orig_category":"Administratie- En Boekhoudkantoren",
    "sg:phone":"+31 511 462 075",
    "sg:postcode":"9251 GA",
    "sg:province":"Georgia",
    "wof:name":"Breeden Vof, Van",
    "wof:placetype":"venue"
},
  "geometry": {"coordinates":[-83.222931,32.678131],"type":"Point"}
}