{
  "type": "Feature",
  "properties": {
    "addr:full":"Europaln 5 Liempde Noord-Brabant 5298 TM",
    "addr:housenumber":"5",
    "addr:postcode":"5298 tm",
    "addr:street":"Europaln",
    "iso:country":"NL",
    "sg:address":"Europaln 5",
    "sg:city":"Liempde",
    "sg:orig_category":"Drukkerijen",
    "sg:phone":"+31 411 631 587",
    "sg:postcode":"5298 TM",
    "sg:province":"Noord-Brabant",
    "wof:name":"Thomassen",
    "wof:placetype":"venue"
},
  "geometry": {"coordinates":[5.371345,51.570347],"type":"Point"}
}