{
  "type": "Feature",
  "properties": {
    "addr:full":"Rijksstraatweg 775 Wassenaar Zuid-Holland 2245 CE",
    "addr:housenumber":"775",
    "addr:postcode":"2245 ce",
    "addr:street":"Rijksstraatweg",
    "iso:country":"NL",
    "sg:address":"Rijksstraatweg 775",
    "sg:city":"Wassenaar",
    "sg:orig_category":"Public Relationbureaus",
    "sg:phone":"+31 70 517 8937",
    "sg:postcode":"2245 CE",
    "sg:province":"Zuid-Holland",
    "wof:name":"Molenbroek Communicatie Management Bv",
    "wof:placetype":"venue"
},
  "geometry": {"coordinates":[4.3651,52.10947],"type":"Point"}
}