{
  "type": "Feature",
  "properties": {
    "addr:full":"Industriekade 10 Breda Noord-Brabant 4815 HD",
    "addr:housenumber":"10",
    "addr:postcode":"4815 hd",
    "addr:street":"Industriekade",
    "iso:country":"NL",
    "sg:address":"Industriekade 10",
    "sg:city":"Breda",
    "sg:orig_category":"Wegen And Sportterreinen",
    "sg:phone":"+31 76 578 9789",
    "sg:postcode":"4815 HD",
    "sg:province":"Noord-Brabant",
    "wof:name":"Rasenberg Kabels En Leidingen Bv",
    "wof:placetype":"venue"
},
  "geometry": {"coordinates":[4.7698960304,51.5986366272],"type":"Point"}
}