{
  "type": "Feature",
  "properties": {
    "addr:full":"Emmastraat 36 Panningen Limburg 5981 BP",
    "addr:housenumber":"36",
    "addr:postcode":"5981 bp",
    "addr:street":"Emmastraat",
    "iso:country":"NL",
    "sg:address":"Emmastraat 36",
    "sg:city":"Panningen",
    "sg:orig_category":"Onderhoud And Reparatie Kantoorapparatuur",
    "sg:phone":"+31 77 307 2371",
    "sg:postcode":"5981 BP",
    "sg:province":"Limburg",
    "wof:name":"Asc Computer Systemen",
    "wof:placetype":"venue"
},
  "geometry": {"coordinates":[5.974392,51.321941],"type":"Point"}
}