{
  "type": "Feature",
  "properties": {
    "addr:full":"Couperusstr 104 Groningen Groningen 9721 JJ",
    "addr:housenumber":"104",
    "addr:postcode":"9721 jj",
    "iso:country":"NL",
    "sg:address":"Couperusstr 104",
    "sg:city":"Groningen",
    "sg:classifiers":[
        {
            "category":"Personal",
            "subcategory":"Nail Salon",
            "type":"Services"
        }
    ],
    "sg:phone":"+31 50 318 6933",
    "sg:postcode":"9721 JJ",
    "sg:province":"Groningen",
    "sg:tags":[
        "pedicure"
    ],
    "wof:name":"Ploeg, Alie Van Der",
    "wof:placetype":"venue"
},
  "geometry": {"coordinates":[6.570354,53.198952],"type":"Point"}
}