{
  "type": "Feature",
  "properties": {
    "addr:full":"Neerhofstr 5 Zevenbergen Noord-Brabant 4761 BM",
    "addr:housenumber":"5",
    "addr:postcode":"4761 bm",
    "addr:street":"Neerhofstr",
    "iso:country":"NL",
    "sg:address":"Neerhofstr 5",
    "sg:city":"Zevenbergen",
    "sg:orig_category":"Artsen - Huisartsen",
    "sg:phone":"+31 168 324 162",
    "sg:postcode":"4761 BM",
    "sg:province":"Noord-Brabant",
    "wof:name":"Slort En Dr Tan, Dr",
    "wof:placetype":"venue"
},
  "geometry": {"coordinates":[4.608777,51.642834],"type":"Point"}
}