{
  "type": "Feature",
  "properties": {
    "addr:full":"Blijversweg 27 Rijpwetering Zuid-Holland 2375 XV",
    "addr:housenumber":"27",
    "addr:postcode":"2375 xv",
    "addr:street":"Blijversweg",
    "iso:country":"NL",
    "sg:address":"Blijversweg 27",
    "sg:city":"Rijpwetering",
    "sg:orig_category":"Geluidsopnamen",
    "sg:phone":"+31 71 501 3013",
    "sg:postcode":"2375 XV",
    "sg:province":"Zuid-Holland",
    "wof:name":"Wesselius Audio Bv",
    "wof:placetype":"venue"
},
  "geometry": {"coordinates":[4.578274,52.193954],"type":"Point"}
}