{
  "type": "Feature",
  "properties": {
    "iso:country":"NL",
    "sg:address":"Tijm 4",
    "sg:city":"Oisterwijk",
    "sg:orig_category":"Loodgieterswerk, Verwarming And Sanitaire Installaties",
    "sg:phone":"+31 13 521 6041",
    "sg:postcode":"5063 EK",
    "sg:province":"Noord-Brabant",
    "wof:name":"A. V.D. Gaag",
    "wof:placetype":"venue"
},
  "geometry": {"coordinates":[5.173167,51.584911],"type":"Point"}
}