{
  "type": "Feature",
  "properties": {
    "addr:full":"Doetinchemsewg 6 Varsseveld Gelderland 7051 AC",
    "addr:housenumber":"6",
    "addr:postcode":"7051 ac",
    "addr:street":"Doetinchemsewg;Gelderland",
    "iso:country":"NL",
    "sg:address":"Doetinchemsewg 6",
    "sg:city":"Varsseveld",
    "sg:orig_category":"Postkantoren",
    "sg:phone":"+31 315 244 666",
    "sg:postcode":"7051 AC",
    "sg:province":"Gelderland",
    "sg:website":"http://www.postkantoor.nl",
    "wof:name":"Postkantoor",
    "wof:placetype":"venue"
},
  "geometry": {"coordinates":[6.461596,51.943928],"type":"Point"}
}