{
  "type": "Feature",
  "properties": {
    "addr:full":"Delflandln 1 Amsterdam North Holland 1062 EA",
    "addr:housenumber":"1",
    "addr:postcode":"1062 ea",
    "addr:street":"Delflandln",
    "iso:country":"NL",
    "sg:address":"Delflandln 1",
    "sg:city":"Amsterdam",
    "sg:orig_category":"Werving En Selectie",
    "sg:phone":"+31 20 355 3420",
    "sg:postcode":"1062 EA",
    "sg:province":"North Holland",
    "sg:website":"http://www.client-first.nl",
    "wof:name":"Client First",
    "wof:placetype":"venue"
},
  "geometry": {"coordinates":[4.8410367966,52.3513031006],"type":"Point"}
}