{
  "type": "Feature",
  "properties": {
    "addr:full":"Herengr 27 Leiden Zuid-Holland 2312 LA",
    "addr:housenumber":"27",
    "addr:postcode":"2312 la",
    "addr:street":"Herengr",
    "iso:country":"NL",
    "sg:address":"Herengr 27",
    "sg:city":"Leiden",
    "sg:orig_category":"Artsen - Manuele Geneeskunde",
    "sg:phone":"+31 71 512 2995",
    "sg:postcode":"2312 LA",
    "sg:province":"Zuid-Holland",
    "sg:website":"http://www.waningarts.nl",
    "wof:name":"Waning Arts, J F Van",
    "wof:placetype":"venue"
},
  "geometry": {"coordinates":[4.499744,52.157001],"type":"Point"}
}