{
  "type": "Feature",
  "properties": {
    "addr:full":"Westerdreef 5 Lisse Zuid-Holland 2161 EN",
    "addr:housenumber":"5",
    "addr:postcode":"2161 en",
    "addr:street":"Westerdreef",
    "iso:country":"NL",
    "sg:address":"Westerdreef 5",
    "sg:city":"Lisse",
    "sg:orig_category":"Elektronische Bedrijfsinstallaties",
    "sg:phone":"+31 252 420 399",
    "sg:postcode":"2161 EN",
    "sg:province":"Zuid-Holland",
    "wof:name":"Barten Telesecurity",
    "wof:placetype":"venue"
},
  "geometry": {"coordinates":[4.55533,52.262051],"type":"Point"}
}