{
  "type": "Feature",
  "properties": {
    "iso:country":"NL",
    "sg:address":"Kromme Spieringweg 433",
    "sg:city":"Vijfhuizen",
    "sg:orig_category":"Fotostudio'S And Fotografen",
    "sg:phone":"+31 23 558 1864",
    "sg:postcode":"2141 AH",
    "sg:province":"North Holland",
    "wof:name":"Fotografie Christian Lohman",
    "wof:placetype":"venue"
},
  "geometry": {"coordinates":[4.68151,52.353703],"type":"Point"}
}