{
  "type": "Feature",
  "properties": {
    "addr:full":"Muziekpln 12 Barendrecht South Holland 2992 GH",
    "addr:housenumber":"12",
    "addr:postcode":"2992 gh",
    "addr:street":"Muziekpln",
    "iso:country":"NL",
    "sg:address":"Muziekpln 12",
    "sg:city":"Barendrecht",
    "sg:orig_category":"Verzekeringen - Verzekeringskantoren",
    "sg:phone":"+31 180 610 894",
    "sg:postcode":"2992 GH",
    "sg:province":"South Holland",
    "sg:website":"http://www.to-the-point.nl",
    "wof:name":"To The Point Fin Adviesburo",
    "wof:placetype":"venue"
},
  "geometry": {"coordinates":[4.522149,51.854572],"type":"Point"}
}