{
  "type": "Feature",
  "properties": {
    "addr:full":"Sint Jorisstraat 35 Beesel Limburg 5954 AN",
    "addr:housenumber":"35",
    "addr:postcode":"5954 an",
    "addr:street":"Sint Jorisstraat",
    "iso:country":"NL",
    "sg:address":"Sint Jorisstraat 35",
    "sg:city":"Beesel",
    "sg:orig_category":"Boekhouders",
    "sg:phone":"+31 77 474 8080",
    "sg:postcode":"5954 AN",
    "sg:province":"Limburg",
    "wof:name":"Geerlings & Partners",
    "wof:placetype":"venue"
},
  "geometry": {"coordinates":[6.042909,51.271637],"type":"Point"}
}