{
  "type": "Feature",
  "properties": {
    "iso:country":"NL",
    "sg:address":"Churchilllaan 223",
    "sg:city":"Amsterdam",
    "sg:orig_category":"Advocaten And Juridische Adviseurs",
    "sg:phone":"+31 20 673 3351",
    "sg:postcode":"1078 ED",
    "sg:province":"Noord-Holland",
    "wof:name":"Sorko Advocaten Cs",
    "wof:placetype":"venue"
},
  "geometry": {"coordinates":[4.886541,52.347172],"type":"Point"}
}