{
  "type": "Feature",
  "properties": {
    "addr:full":"Utrechtsewg 34 Ysselstein Ut Utrecht 3402 PL",
    "addr:housenumber":"34",
    "addr:postcode":"3402 pl",
    "addr:street":"Utrechtsewg",
    "iso:country":"NL",
    "sg:address":"Utrechtsewg 34",
    "sg:city":"Ysselstein Ut",
    "sg:orig_category":"Honden- En Kattentrimsalons",
    "sg:phone":"+31 30 688 2369",
    "sg:postcode":"3402 PL",
    "sg:province":"Utrecht",
    "wof:name":"Pretty Pets",
    "wof:placetype":"venue"
},
  "geometry": {"coordinates":[5.051877,52.020985],"type":"Point"}
}