{
  "type": "Feature",
  "properties": {
    "addr:full":"Hovendsedk 21 Brakel Gelderland 5306 AH",
    "addr:housenumber":"21",
    "addr:postcode":"5306 ah",
    "addr:street":"Hovendsedk;Gelderland",
    "iso:country":"NL",
    "sg:address":"Hovendsedk 21",
    "sg:city":"Brakel",
    "sg:orig_category":"Plafonds",
    "sg:phone":"+31 418 674 041",
    "sg:postcode":"5306 AH",
    "sg:province":"Gelderland",
    "wof:name":"Plameco",
    "wof:placetype":"venue"
},
  "geometry": {"coordinates":[5.089248,51.817677],"type":"Point"}
}