{
  "type": "Feature",
  "properties": {
    "addr:full":"Gloxiniawg 7 Zwolle NL.08 8042 AS",
    "addr:housenumber":"7",
    "addr:postcode":"8042 as",
    "addr:street":"Gloxiniawg",
    "iso:country":"NL",
    "sg:address":"Gloxiniawg 7",
    "sg:city":"Zwolle",
    "sg:orig_category":"Video - Faciliteiten En Producties",
    "sg:phone":"+31 38 421 9603",
    "sg:postcode":"8042 AS",
    "sg:province":"NL.08",
    "wof:name":"Douma, Yvonne",
    "wof:placetype":"venue"
},
  "geometry": {"coordinates":[6.048189,52.522434],"type":"Point"}
}