{
  "type": "Feature",
  "properties": {
    "addr:full":"H Dunantln 2A Apeldoorn Gelderland 7312 BE",
    "addr:housenumber":"2a",
    "addr:postcode":"7312",
    "addr:street":"Gelderland",
    "iso:country":"NL",
    "sg:address":"H Dunantln 2A",
    "sg:city":"Apeldoorn",
    "sg:orig_category":"Voorlichtingsbureaus",
    "sg:phone":"+31 55 534 0034",
    "sg:postcode":"7312 BE",
    "sg:province":"Gelderland",
    "wof:name":"Foto Film Video",
    "wof:placetype":"venue"
},
  "geometry": {"coordinates":[5.942212,52.210396],"type":"Point"}
}