{
  "type": "Feature",
  "properties": {
    "addr:full":"Plaswg 44 Soest Utrecht 3768 AN",
    "addr:housenumber":"44",
    "addr:postcode":"3768 an",
    "addr:street":"Plaswg",
    "iso:country":"NL",
    "sg:address":"Plaswg 44",
    "sg:city":"Soest",
    "sg:orig_category":"Grafisch Ontwerpers",
    "sg:phone":"+31 35 601 3369",
    "sg:postcode":"3768 AN",
    "sg:province":"Utrecht",
    "wof:name":"Vis, Cees",
    "wof:placetype":"venue"
},
  "geometry": {"coordinates":[5.300373,52.160645],"type":"Point"}
}