{
  "type": "Feature",
  "properties": {
    "addr:full":"Rijksstraatweg 164 Elst Ut Utrecht 3921 AM",
    "addr:housenumber":"164",
    "addr:postcode":"ut;3921",
    "addr:street":"Rijksstraatweg",
    "iso:country":"NL",
    "sg:address":"Rijksstraatweg 164",
    "sg:city":"Elst Ut",
    "sg:orig_category":"Overheidsdiensten",
    "sg:phone":"+31 318 471 764",
    "sg:postcode":"3921 AM",
    "sg:province":"Utrecht",
    "wof:name":"Dorpshuis",
    "wof:placetype":"venue"
},
  "geometry": {"coordinates":[5.5076899529,51.9821624756],"type":"Point"}
}