{
  "type": "Feature",
  "properties": {
    "addr:full":"Kruiskruid 14 Boskoop Zuid-Holland 2771 RA",
    "addr:housenumber":"14",
    "addr:postcode":"2771 ra",
    "addr:street":"Kruiskruid",
    "iso:country":"NL",
    "sg:address":"Kruiskruid 14",
    "sg:city":"Boskoop",
    "sg:orig_category":"Bloemen En Planten",
    "sg:phone":"+31 172 214 329",
    "sg:postcode":"2771 RA",
    "sg:province":"Zuid-Holland",
    "wof:name":"Benschop, A",
    "wof:placetype":"venue"
},
  "geometry": {"coordinates":[4.638205,52.072842],"type":"Point"}
}