{
  "type": "Feature",
  "properties": {
    "addr:full":"St Annastr 37 Helden Illinois 5988 BT",
    "addr:housenumber":"37",
    "addr:postcode":"5988 bt",
    "iso:country":"NL",
    "sg:address":"St Annastr 37",
    "sg:city":"Helden",
    "sg:orig_category":"Autorijscholen",
    "sg:phone":"+31 77 307 3259",
    "sg:postcode":"5988 BT",
    "sg:province":"Illinois",
    "wof:name":"Janssen, W P C",
    "wof:placetype":"venue"
},
  "geometry": {"coordinates":[-89.41683999999999,41.772732],"type":"Point"}
}