{
  "type": "Feature",
  "properties": {
    "addr:full":"Kerkstraat 25 Makkum Fr Provincie Friesland 8754 CR",
    "addr:housenumber":"25;8754",
    "addr:postcode":"cr",
    "addr:street":"Kerkstraat;Friesland",
    "iso:country":"NL",
    "sg:address":"Kerkstraat 25",
    "sg:city":"Makkum Fr",
    "sg:orig_category":"Kappers",
    "sg:phone":"+31 515 231 651",
    "sg:postcode":"8754 CR",
    "sg:province":"Provincie Friesland",
    "wof:name":"Knipsalon Durkje",
    "wof:placetype":"venue"
},
  "geometry": {"coordinates":[5.402502,53.056217],"type":"Point"}
}