{
  "type": "Feature",
  "properties": {
    "iso:country":"NL",
    "sg:address":"Vlut 2",
    "sg:city":"Ospel",
    "sg:orig_category":"Metaalbekleding And -Behandeling",
    "sg:phone":"+31 495 626 116",
    "sg:postcode":"6035 PJ",
    "sg:province":"Limburg",
    "wof:name":"Slijperij Van Hoek Vof",
    "wof:placetype":"venue"
},
  "geometry": {"coordinates":[-86.1654510498,34.620891571],"type":"Point"}
}