{
  "type": "Feature",
  "properties": {
    "iso:country":"NL",
    "sg:address":"Tjonger 7",
    "sg:city":"Zeewolde",
    "sg:orig_category":"Homeopathie",
    "sg:phone":"+31 36 531 8731",
    "sg:postcode":"3891 CE",
    "sg:province":"NL.",
    "wof:name":"Kuysten, M Y",
    "wof:placetype":"venue"
},
  "geometry": {"coordinates":[5.529137,52.330715],"type":"Point"}
}