{
  "type": "Feature",
  "properties": {
    "addr:full":"Voorstraat 27 Utrecht Utrecht 3512 AJ",
    "addr:housenumber":"27",
    "addr:postcode":"3512 aj",
    "addr:street":"Voorstraat",
    "iso:country":"NL",
    "sg:address":"Voorstraat 27",
    "sg:city":"Utrecht",
    "sg:orig_category":"Banken And Kredietinstellingen",
    "sg:phone":"+31 30 231 6015",
    "sg:postcode":"3512 AJ",
    "sg:province":"Utrecht",
    "wof:name":"Adviesbureau Banque Commerciale Du Maroc",
    "wof:placetype":"venue"
},
  "geometry": {"coordinates":[5.119813,52.094479],"type":"Point"}
}