{
  "type": "Feature",
  "properties": {
    "addr:full":"Ameroever 31 Lage Zwaluwe North Brabant 4926 EC",
    "addr:housenumber":"31",
    "addr:postcode":"4926 ec",
    "addr:street":"Ameroever",
    "iso:country":"NL",
    "sg:address":"Ameroever 31",
    "sg:city":"Lage Zwaluwe",
    "sg:orig_category":"Verzekeringen",
    "sg:phone":"+31 168 482 091",
    "sg:postcode":"4926 EC",
    "sg:province":"North Brabant",
    "wof:name":"Pensioenadviesburo G. Fillekes",
    "wof:placetype":"venue"
},
  "geometry": {"coordinates":[4.701016,51.717571],"type":"Point"}
}