{
  "type": "Feature",
  "properties": {
    "addr:full":"Lieftinckstr 5 Naaldwyk Zuid-Holland 2672 DT",
    "addr:housenumber":"5",
    "addr:postcode":"2672 dt",
    "addr:street":"Lieftinckstr",
    "iso:country":"NL",
    "sg:address":"Lieftinckstr 5",
    "sg:city":"Naaldwyk",
    "sg:orig_category":"Modevakscholen",
    "sg:phone":"+31 174 628 566",
    "sg:postcode":"2672 DT",
    "sg:province":"Zuid-Holland",
    "wof:name":"Verheij, W D",
    "wof:placetype":"venue"
},
  "geometry": {"coordinates":[4.221239,51.992851],"type":"Point"}
}