{
  "type": "Feature",
  "properties": {
    "addr:full":"Ryndk 2B Hazerswoude Ryndyk Zuid-Holland 2394 AH",
    "addr:housenumber":"2b;ryndyk",
    "addr:postcode":"2394 ah",
    "addr:street":"Ryndk",
    "iso:country":"NL",
    "sg:address":"Ryndk 2B",
    "sg:city":"Hazerswoude Ryndyk",
    "sg:orig_category":"Meubelen",
    "sg:phone":"+31 71 341 3861",
    "sg:postcode":"2394 AH",
    "sg:province":"Zuid-Holland",
    "sg:website":"http://www.kroesinterieur.nl",
    "wof:name":"Kroes Interieur",
    "wof:placetype":"venue"
},
  "geometry": {"coordinates":[4.595154,52.131054],"type":"Point"}
}