{
  "type": "Feature",
  "properties": {
    "addr:full":"Jacob Van Lennepkade 9 Amsterdam North Holland 1054 ZD",
    "addr:housenumber":"9",
    "addr:postcode":"1054 zd",
    "addr:street":"Jacob Van Lennepkade",
    "iso:country":"NL",
    "sg:address":"Jacob Van Lennepkade 9",
    "sg:city":"Amsterdam",
    "sg:orig_category":"Medische Apparatuur And Prothesen Fab",
    "sg:phone":"+31 20 612 8925",
    "sg:postcode":"1054 ZD",
    "sg:province":"North Holland",
    "wof:name":"M Matiasen",
    "wof:placetype":"venue"
},
  "geometry": {"coordinates":[4.876712,52.366199],"type":"Point"}
}