{
  "type": "Feature",
  "properties": {
    "addr:full":"Plesmanlaan 21 Utrecht Utrecht 3555 AM",
    "addr:housenumber":"21",
    "addr:postcode":"3555",
    "addr:street":"Plesmanlaan",
    "iso:country":"NL",
    "sg:address":"Plesmanlaan 21",
    "sg:city":"Utrecht",
    "sg:classifiers":[
        {
            "category":"Education",
            "subcategory":"Preschool",
            "type":"Public Place"
        }
    ],
    "sg:phone":"+31 30 244 1005",
    "sg:postcode":"3555 AM",
    "sg:province":"Utrecht",
    "sg:tags":[
        "kleuteronderwijs",
        "basis-"
    ],
    "wof:name":"Basisschool De Piramide",
    "wof:placetype":"venue"
},
  "geometry": {"coordinates":[5.08052,52.114544],"type":"Point"}
}