{
  "type": "Feature",
  "properties": {
    "addr:full":"Breukelsestr 112 Boxtel Noord-Brabant 5281 HG",
    "addr:housenumber":"112",
    "addr:postcode":"5281 hg",
    "iso:country":"NL",
    "sg:address":"Breukelsestr 112",
    "sg:city":"Boxtel",
    "sg:orig_category":"Opticiens",
    "sg:phone":"+31 411 683 843",
    "sg:postcode":"5281 HG",
    "sg:province":"Noord-Brabant",
    "wof:name":"Buisman, Sybilla",
    "wof:placetype":"venue"
},
  "geometry": {"coordinates":[5.315955162,51.5883255005],"type":"Point"}
}