{
  "type": "Feature",
  "properties": {
    "iso:country":"NL",
    "sg:address":"Geldropsewg 80A",
    "sg:city":"Heeze",
    "sg:orig_category":"Adviesbureaus Bedrijfsorganisatie",
    "sg:phone":"+31 40 226 2490",
    "sg:postcode":"5591 ED",
    "sg:province":"Noord-Brabant",
    "wof:name":"Bancare Vof",
    "wof:placetype":"venue"
},
  "geometry": {"coordinates":[5.574241,51.387314],"type":"Point"}
}