{
  "type": "Feature",
  "properties": {
    "iso:country":"NL",
    "sg:address":"Baetenburg 93",
    "sg:city":"Heiloo",
    "sg:orig_category":"Boekhouders",
    "sg:phone":"+31 72 533 4089",
    "sg:postcode":"1852 TT",
    "sg:province":"Noord-Holland",
    "wof:name":"Administratiekantoor B.M. Breedveld",
    "wof:placetype":"venue"
},
  "geometry": {"coordinates":[4.68693,52.600933],"type":"Point"}
}