{
  "type": "Feature",
  "properties": {
    "addr:full":"Griftdk N 26 Lent Gelderland 6663 AC",
    "addr:postcode":"6663 ac",
    "addr:street":"N 26;Gelderland",
    "iso:country":"NL",
    "sg:address":"Griftdk N 26",
    "sg:city":"Lent",
    "sg:orig_category":"Bloemisterijartikelen - Fabrieken En Groothandel",
    "sg:phone":"+31 24 323 9500",
    "sg:postcode":"6663 AC",
    "sg:province":"Gelderland",
    "sg:website":"http://www.hortimea.nl",
    "wof:name":"Lentse Potgrond Bv",
    "wof:placetype":"venue"
},
  "geometry": {"coordinates":[-77.241432,38.151344],"type":"Point"}
}