{
  "type": "Feature",
  "properties": {
    "addr:full":"Noorderstr 60 Sappemeer Groningen 9611 AM",
    "addr:housenumber":"60",
    "addr:postcode":"9611",
    "addr:street":"Noorderstr",
    "iso:country":"NL",
    "sg:address":"Noorderstr 60",
    "sg:city":"Sappemeer",
    "sg:orig_category":"Voetbalverenigingen",
    "sg:phone":"+31 598 397 292",
    "sg:postcode":"9611 AM",
    "sg:province":"Groningen",
    "wof:name":"Hoogezand Vv",
    "wof:placetype":"venue"
},
  "geometry": {"coordinates":[6.780776,53.16375],"type":"Point"}
}