{
  "type": "Feature",
  "properties": {
    "addr:full":"Rederijweg 37 Oosterhout Nb North Brabant 4906 CX",
    "addr:housenumber":"37;nb",
    "addr:postcode":"4906 cx",
    "addr:street":"Rederijweg",
    "iso:country":"NL",
    "sg:address":"Rederijweg 37",
    "sg:city":"Oosterhout Nb",
    "sg:orig_category":"Goederenvervoer Over De Weg",
    "sg:phone":"+31 162 453 725",
    "sg:postcode":"4906 CX",
    "sg:province":"North Brabant",
    "wof:name":"Taks Van Gils Transportbedrijf Bv",
    "wof:placetype":"venue"
},
  "geometry": {"coordinates":[4.837508,51.664425],"type":"Point"}
}