{
  "type": "Feature",
  "properties": {
    "iso:country":"NL",
    "sg:address":"Drieharingstraat 4",
    "sg:city":"Utrecht",
    "sg:orig_category":"Babyartikelen Detailhandel",
    "sg:phone":"+31 30 231 7064",
    "sg:postcode":"3511 BJ",
    "sg:province":"Utrecht",
    "wof:name":"Sterre En Tijl",
    "wof:placetype":"venue"
},
  "geometry": {"coordinates":[5.116281,52.091923],"type":"Point"}
}