{
  "type": "Feature",
  "properties": {
    "iso:country":"NL",
    "sg:address":"F Ukenaln 30",
    "sg:city":"Appingedam",
    "sg:orig_category":"Videotheken",
    "sg:phone":"+31 596 623 936",
    "sg:postcode":"9902 GC",
    "sg:province":"Groningen",
    "wof:name":"Videowereld",
    "wof:placetype":"venue"
},
  "geometry": {"coordinates":[6.873551,53.313633],"type":"Point"}
}