{
  "type": "Feature",
  "properties": {
    "addr:full":"Abberdaan 42 Amsterdam Noord-Holland 1046 AA",
    "addr:housenumber":"42",
    "addr:postcode":"1046 aa",
    "addr:street":"Abberdaan",
    "iso:country":"NL",
    "sg:address":"Abberdaan 42",
    "sg:city":"Amsterdam",
    "sg:orig_category":"Pijpleidingen",
    "sg:phone":"+31 20 682 5513",
    "sg:postcode":"1046 AA",
    "sg:province":"Noord-Holland",
    "wof:name":"Skm Bv",
    "wof:placetype":"venue"
},
  "geometry": {"coordinates":[4.787823,52.392262],"type":"Point"}
}