{
  "type": "Feature",
  "properties": {
    "addr:full":"Zilvermeer 1 Groningen Groningen 9735 BA",
    "addr:housenumber":"1",
    "addr:postcode":"9735 ba",
    "addr:street":"Zilvermeer",
    "iso:country":"NL",
    "sg:address":"Zilvermeer 1",
    "sg:city":"Groningen",
    "sg:orig_category":"Verzekeringen - Verzekeringskantoren",
    "sg:phone":"+31 50 549 0365",
    "sg:postcode":"9735 BA",
    "sg:province":"Groningen",
    "wof:name":"Bronsema",
    "wof:placetype":"venue"
},
  "geometry": {"coordinates":[6.60449,53.236351],"type":"Point"}
}