{
  "type": "Feature",
  "properties": {
    "addr:full":"Waalbroek 5 Simpelveld Limburg 6369 TE",
    "addr:housenumber":"5",
    "addr:postcode":"6369 te",
    "addr:street":"Waalbroek",
    "iso:country":"NL",
    "sg:address":"Waalbroek 5",
    "sg:city":"Simpelveld",
    "sg:orig_category":"Touringcars",
    "sg:phone":"+31 45 544 4275",
    "sg:postcode":"6369 TE",
    "sg:province":"Limburg",
    "wof:name":"Meurs Bv, Van",
    "wof:placetype":"venue"
},
  "geometry": {"coordinates":[5.99306,50.828701],"type":"Point"}
}