{
  "type": "Feature",
  "properties": {
    "addr:full":"Meerheide 56 Eersel North Brabant 5521 DZ",
    "addr:housenumber":"56",
    "addr:postcode":"5521 dz",
    "addr:street":"Meerheide",
    "iso:country":"NL",
    "sg:address":"Meerheide 56",
    "sg:city":"Eersel",
    "sg:orig_category":"Offsetdrukkerijen",
    "sg:phone":"+31 497 512 175",
    "sg:postcode":"5521 DZ",
    "sg:province":"North Brabant",
    "wof:name":"Exclusief",
    "wof:placetype":"venue"
},
  "geometry": {"coordinates":[5.316216,51.37442],"type":"Point"}
}