{
  "type": "Feature",
  "properties": {
    "addr:full":"Prins Clauslaan 19 Waalre Noord-Brabant 5582 JP",
    "addr:housenumber":"19",
    "addr:postcode":"5582 jp",
    "addr:street":"Prins Clauslaan",
    "iso:country":"NL",
    "sg:address":"Prins Clauslaan 19",
    "sg:city":"Waalre",
    "sg:orig_category":"Vertaal- And Tolkenbureaus",
    "sg:phone":"+31 40 221 3607",
    "sg:postcode":"5582 JP",
    "sg:province":"Noord-Brabant",
    "wof:name":"W. Prast-Jonkers",
    "wof:placetype":"venue"
},
  "geometry": {"coordinates":[5.470866,51.393806],"type":"Point"}
}