{
  "type": "Feature",
  "properties": {
    "addr:full":"Beethovenlaan 24 Hengelo Ov NL.08 7557 BD",
    "addr:housenumber":"24",
    "addr:postcode":"7557",
    "addr:street":"Beethovenlaan;Ov;Bd",
    "iso:country":"NL",
    "sg:address":"Beethovenlaan 24",
    "sg:city":"Hengelo Ov",
    "sg:orig_category":"Verzekeringen - Verzekeringskantoren",
    "sg:phone":"+31 74 259 3710",
    "sg:postcode":"7557 BD",
    "sg:province":"NL.08",
    "wof:name":"Jp",
    "wof:placetype":"venue"
},
  "geometry": {"coordinates":[6.808431,52.269161],"type":"Point"}
}