{
  "type": "Feature",
  "properties": {
    "addr:full":"Kerkstraat 75 Wassenaar South Holland 2242 HE",
    "addr:housenumber":"75",
    "addr:postcode":"2242 he",
    "addr:street":"Kerkstraat",
    "iso:country":"NL",
    "sg:address":"Kerkstraat 75",
    "sg:city":"Wassenaar",
    "sg:orig_category":"Verenigingen En Stichtingen",
    "sg:phone":"+31 70 511 1881",
    "sg:postcode":"2242 HE",
    "sg:province":"South Holland",
    "wof:name":"Uvv",
    "wof:placetype":"venue"
},
  "geometry": {"coordinates":[4.391084,52.140423],"type":"Point"}
}