{
  "type": "Feature",
  "properties": {
    "addr:full":"Stationspln 42 S Gravenhage South Holland 2515 BW",
    "addr:housenumber":"42",
    "addr:postcode":"2515 bw",
    "addr:street":"Stationspln;S Gravenhage",
    "iso:country":"NL",
    "sg:address":"Stationspln 42",
    "sg:city":"S Gravenhage",
    "sg:orig_category":"Bloemen En Planten",
    "sg:phone":"+31 70 389 5858",
    "sg:postcode":"2515 BW",
    "sg:province":"South Holland",
    "wof:name":"Bloemenexpress",
    "wof:placetype":"venue"
},
  "geometry": {"coordinates":[4.31741,52.083988],"type":"Point"}
}