{
  "type": "Feature",
  "properties": {
    "iso:country":"NL",
    "sg:address":"Hommerterweg 235",
    "sg:city":"Hoensbroek",
    "sg:orig_category":"Diverse Bedrijfsinstallaties Gh",
    "sg:phone":"+31 45 523 2560",
    "sg:postcode":"6431 EV",
    "sg:province":"Limburg",
    "wof:name":"Ntse Machines Vof",
    "wof:placetype":"venue"
},
  "geometry": {"coordinates":[5.922062,50.933453],"type":"Point"}
}