{
  "type": "Feature",
  "properties": {
    "iso:country":"NL",
    "sg:address":"Kolkakkers 57",
    "sg:city":"Dalen",
    "sg:orig_category":"Tuinontwerp En -Advies",
    "sg:phone":"+31 524 552 763",
    "sg:postcode":"7751 DL",
    "sg:province":"Drenthe",
    "wof:name":"Planterij, De",
    "wof:placetype":"venue"
},
  "geometry": {"coordinates":[6.7467,52.698494],"type":"Point"}
}