{
  "type": "Feature",
  "properties": {
    "iso:country":"NL",
    "sg:address":"Stationspln 7",
    "sg:city":"Lelystad",
    "sg:orig_category":"Bloemen En Planten",
    "sg:phone":"+31 320 231 669",
    "sg:postcode":"8232 DL",
    "sg:province":"NL.",
    "wof:name":"Cinqualbre",
    "wof:placetype":"venue"
},
  "geometry": {"coordinates":[5.472985,52.507801],"type":"Point"}
}