{
  "type": "Feature",
  "properties": {
    "addr:full":"Vlakeweg 1 Hansweert Zeeland 4417 PD",
    "addr:housenumber":"1",
    "addr:postcode":"4417 pd",
    "addr:street":"Vlakeweg",
    "iso:country":"NL",
    "sg:address":"Vlakeweg 1",
    "sg:city":"Hansweert",
    "sg:orig_category":"Groententeelt",
    "sg:phone":"+31 113 381 525",
    "sg:postcode":"4417 PD",
    "sg:province":"Zeeland",
    "wof:name":"Landb Bedr Wed Rijk-Vermue & Kinderen",
    "wof:placetype":"venue"
},
  "geometry": {"coordinates":[4.015434,51.478146],"type":"Point"}
}