{
  "type": "Feature",
  "properties": {
    "addr:full":"Postbus 268 Valkenswaard North Brabant 5550 AG",
    "addr:housenumber":"268",
    "addr:postcode":"5550",
    "addr:street":"Postbus",
    "iso:country":"NL",
    "sg:address":"Postbus 268",
    "sg:city":"Valkenswaard",
    "sg:orig_category":"Sportverenigingen En Ontspannings- Verenigingen",
    "sg:phone":"+31 40 204 7619",
    "sg:postcode":"5550 AG",
    "sg:province":"North Brabant",
    "wof:name":"Ginneve Tennisver",
    "wof:placetype":"venue"
},
  "geometry": {"coordinates":[5.45897,51.35051],"type":"Point"}
}