{
  "type": "Feature",
  "properties": {
    "addr:full":"Locht 66 Veldhoven North Brabant 5504 KE",
    "addr:housenumber":"66",
    "addr:postcode":"5504 ke",
    "addr:street":"Locht",
    "iso:country":"NL",
    "sg:address":"Locht 66",
    "sg:city":"Veldhoven",
    "sg:orig_category":"Fruit And Groenten Gh",
    "sg:phone":"+31 40 254 4777",
    "sg:postcode":"5504 KE",
    "sg:province":"North Brabant",
    "wof:name":"W. Van Kemenade Veldhoven Bv",
    "wof:placetype":"venue"
},
  "geometry": {"coordinates":[5.39136,51.397968],"type":"Point"}
}