{
  "type": "Feature",
  "properties": {
    "addr:full":"Kooltjesbuurt 1 Naarden North Holland 1411 RZ",
    "addr:housenumber":"1",
    "addr:postcode":"1411 rz",
    "addr:street":"Kooltjesbuurt",
    "iso:country":"NL",
    "sg:address":"Kooltjesbuurt 1",
    "sg:city":"Naarden",
    "sg:orig_category":"Verzekeringen - Verzekeringskantoren",
    "sg:phone":"+31 35 694 0325",
    "sg:postcode":"1411 RZ",
    "sg:province":"North Holland",
    "sg:website":"http://www.tryg.dk/tbi",
    "wof:name":"Tryg-Baltica Int. Bv",
    "wof:placetype":"venue"
},
  "geometry": {"coordinates":[5.16154,52.29723],"type":"Point"}
}