{
  "type": "Feature",
  "properties": {
    "addr:full":"Grebbe 42 Tilburg North Brabant 5032 RT",
    "addr:housenumber":"42",
    "addr:postcode":"5032 rt",
    "addr:street":"Grebbe",
    "iso:country":"NL",
    "sg:address":"Grebbe 42",
    "sg:city":"Tilburg",
    "sg:classifiers":[
        {
            "category":"Education",
            "subcategory":"Preschool",
            "type":"Public Place"
        }
    ],
    "sg:phone":"+31 13 463 2334",
    "sg:postcode":"5032 RT",
    "sg:province":"North Brabant",
    "sg:tags":[
        "kleuteronderwijs",
        "basis-"
    ],
    "wof:name":"Openbare Basisschool De Blaak",
    "wof:placetype":"venue"
},
  "geometry": {"coordinates":[5.045049,51.54612],"type":"Point"}
}