{
  "type": "Feature",
  "properties": {
    "iso:country":"NL",
    "sg:address":"Heiman Akkerstraat 15",
    "sg:city":"Appingedam",
    "sg:orig_category":"Kinderopvang Behalve Thuis",
    "sg:phone":"+31 596 626 182",
    "sg:postcode":"9902 GE",
    "sg:province":"Groningen",
    "wof:name":"Stichting Kinderopvang",
    "wof:placetype":"venue"
},
  "geometry": {"coordinates":[6.86927,53.317326],"type":"Point"}
}