{
  "type": "Feature",
  "properties": {
    "addr:full":"Voorstr 8 Willemstad Nb Noord-Brabant 4797 BG",
    "addr:housenumber":"8",
    "addr:postcode":"4797",
    "addr:street":"Voorstr",
    "iso:country":"NL",
    "sg:address":"Voorstr 8",
    "sg:city":"Willemstad Nb",
    "sg:orig_category":"Logopedisten",
    "sg:phone":"+31 168 473 798",
    "sg:postcode":"4797 BG",
    "sg:province":"Noord-Brabant",
    "wof:name":"Zegers-Maasdam, L P",
    "wof:placetype":"venue"
},
  "geometry": {"coordinates":[4.439531,51.693787],"type":"Point"}
}