{
  "type": "Feature",
  "properties": {
    "iso:country":"NL",
    "sg:address":"Weipoortseweg 34",
    "sg:city":"Zoeterwoude",
    "sg:orig_category":"Marktonderzoekbureaus",
    "sg:phone":"+31 71 580 1290",
    "sg:postcode":"2381 NC",
    "sg:province":"Zuid-Holland",
    "wof:name":"Van Leeuwen Marketing Bv",
    "wof:placetype":"venue"
},
  "geometry": {"coordinates":[4.526314,52.120781],"type":"Point"}
}