{
  "type": "Feature",
  "properties": {
    "iso:country":"NL",
    "sg:address":"Rosenburglaan 4",
    "sg:city":"Vlissingen",
    "sg:orig_category":"Public Relationbureaus",
    "sg:phone":"+31 118 474 519",
    "sg:postcode":"4385 JD",
    "sg:province":"Zeeland",
    "wof:name":"Mission Public Relations",
    "wof:placetype":"venue"
},
  "geometry": {"coordinates":[3.567728,51.462601],"type":"Point"}
}