{
  "type": "Feature",
  "properties": {
    "iso:country":"NL",
    "sg:address":"Venne 7",
    "sg:city":"Winschoten",
    "sg:classifiers":[
        {
            "category":"Food & Beverages",
            "subcategory":"Fruits & Vegetables",
            "type":"Retail Goods"
        }
    ],
    "sg:phone":"+31 597 422 201",
    "sg:postcode":"9671 DA",
    "sg:province":"Groningen",
    "sg:tags":[
        "groenten"
    ],
    "wof:name":"Boneschansker Versspecialist",
    "wof:placetype":"venue"
},
  "geometry": {"coordinates":[7.03356,53.145538],"type":"Point"}
}