{
  "type": "Feature",
  "properties": {
    "addr:full":"Hemmerbuurt 243 Hem Fribourg 1607 CH",
    "addr:housenumber":"243",
    "addr:postcode":"1607",
    "addr:street":"Hemmerbuurt",
    "iso:country":"NL",
    "sg:address":"Hemmerbuurt 243",
    "sg:city":"Hem",
    "sg:orig_category":"Psychologen",
    "sg:phone":"+31 228 542 181",
    "sg:postcode":"1607 CH",
    "sg:province":"Fribourg",
    "wof:name":"Helmerhorst, Drs A M",
    "wof:placetype":"venue"
},
  "geometry": {"coordinates":[6.829845,46.554893],"type":"Point"}
}