{
  "type": "Feature",
  "properties": {
    "addr:full":"Sterre Der Zeestr 17 Margraten Limburg 6269 AK",
    "addr:housenumber":"17",
    "addr:postcode":"6269 ak",
    "addr:street":"Sterre",
    "iso:country":"NL",
    "sg:address":"Sterre Der Zeestr 17",
    "sg:city":"Margraten",
    "sg:orig_category":"Loopbaanbegeleiding",
    "sg:phone":"+31 43 458 3418",
    "sg:postcode":"6269 AK",
    "sg:province":"Limburg",
    "wof:name":"Thea Geurts",
    "wof:placetype":"venue"
},
  "geometry": {"coordinates":[5.831001,50.816597],"type":"Point"}
}