{
  "type": "Feature",
  "properties": {
    "addr:full":"De Dommel 1 Hattem Gelderland 8051 TA",
    "addr:housenumber":"1",
    "addr:postcode":"8051 ta",
    "addr:street":"De Dommel;Gelderland",
    "iso:country":"NL",
    "sg:address":"De Dommel 1",
    "sg:city":"Hattem",
    "sg:orig_category":"Afslankinstituten",
    "sg:phone":"+31 38 444 2226",
    "sg:postcode":"8051 TA",
    "sg:province":"Gelderland",
    "wof:name":"Couleur",
    "wof:placetype":"venue"
},
  "geometry": {"coordinates":[6.0489,52.476585],"type":"Point"}
}