{
  "type": "Feature",
  "properties": {
    "addr:full":"Soesterwg 228 Amersfoort Utrecht 3812 BG",
    "addr:housenumber":"228",
    "addr:postcode":"3812",
    "iso:country":"NL",
    "sg:address":"Soesterwg 228",
    "sg:city":"Amersfoort",
    "sg:classifiers":[
        {
            "category":"Food & Beverages",
            "subcategory":"Bakery",
            "type":"Retail Goods"
        }
    ],
    "sg:phone":"+31 33 465 1189",
    "sg:postcode":"3812 BG",
    "sg:province":"Utrecht",
    "sg:tags":[
        "pizza"
    ],
    "wof:name":"Verdi",
    "wof:placetype":"venue"
},
  "geometry": {"coordinates":[5.365672,52.157478],"type":"Point"}
}