{
  "type": "Feature",
  "properties": {
    "addr:full":"Parallelwg 31 Beverwyk Noord-Holland 1948 NK",
    "addr:housenumber":"31",
    "addr:postcode":"1948 nk",
    "addr:street":"Parallelwg",
    "iso:country":"NL",
    "sg:address":"Parallelwg 31",
    "sg:city":"Beverwyk",
    "sg:orig_category":"Automaterialen En Gereedschappen",
    "sg:phone":"+31 251 226 448",
    "sg:postcode":"1948 NK",
    "sg:province":"Noord-Holland",
    "wof:name":"Gamo",
    "wof:placetype":"venue"
},
  "geometry": {"coordinates":[4.658605,52.477421],"type":"Point"}
}