{
  "type": "Feature",
  "properties": {
    "addr:full":"Dorpsstraat 32 Hagestein Utrecht 4124 AM",
    "addr:housenumber":"32",
    "addr:postcode":"4124",
    "addr:street":"Dorpsstraat",
    "iso:country":"NL",
    "sg:address":"Dorpsstraat 32",
    "sg:city":"Hagestein",
    "sg:orig_category":"Banken And Kredietinstellingen",
    "sg:phone":"+31 347 357 765",
    "sg:postcode":"4124 AM",
    "sg:province":"Utrecht",
    "wof:name":"Rabobank",
    "wof:placetype":"venue"
},
  "geometry": {"coordinates":[5.121225,51.980717],"type":"Point"}
}