{
  "type": "Feature",
  "properties": {
    "addr:full":"Voorstr 18 Gramsbergen NL.08 7783 AM",
    "addr:housenumber":"18;nl.08",
    "addr:postcode":"7783",
    "addr:street":"Voorstr",
    "iso:country":"NL",
    "sg:address":"Voorstr 18",
    "sg:city":"Gramsbergen",
    "sg:classifiers":[
        {
            "category":"Food & Beverages",
            "subcategory":"Fruits & Vegetables",
            "type":"Retail Goods"
        }
    ],
    "sg:phone":"+31 524 561 298",
    "sg:postcode":"7783 AM",
    "sg:province":"NL.08",
    "sg:tags":[
        "en",
        "groenten"
    ],
    "wof:name":"Vasse, A",
    "wof:placetype":"venue"
},
  "geometry": {"coordinates":[6.672185,52.611107],"type":"Point"}
}