{
  "type": "Feature",
  "properties": {
    "iso:country":"NL",
    "sg:address":"Karel Doormanlaan 17",
    "sg:city":"Hardenberg",
    "sg:classifiers":[
        {
            "category":"Education",
            "subcategory":"Preschool",
            "type":"Public Place"
        }
    ],
    "sg:phone":"+31 523 262 299",
    "sg:postcode":"7772 XW",
    "sg:province":"NL.08",
    "sg:tags":[
        "kleuteronderwijs",
        "basis-"
    ],
    "wof:name":"Openb Sch De Kern",
    "wof:placetype":"venue"
},
  "geometry": {"coordinates":[6.620763,52.573143],"type":"Point"}
}