{
  "type": "Feature",
  "properties": {
    "addr:full":"Lekkenburg 39 Gouda Zuid-Holland 2804 XB",
    "addr:housenumber":"39",
    "addr:postcode":"2804 xb",
    "addr:street":"Lekkenburg",
    "iso:country":"NL",
    "sg:address":"Lekkenburg 39",
    "sg:city":"Gouda",
    "sg:classifiers":[
        {
            "category":"Retail",
            "subcategory":"Photofinishing",
            "type":"Services"
        }
    ],
    "sg:phone":"+31 182 532 332",
    "sg:postcode":"2804 XB",
    "sg:province":"Zuid-Holland",
    "sg:tags":[
        "foto",
        "film"
    ],
    "wof:name":"Foto Klein Bv",
    "wof:placetype":"venue"
},
  "geometry": {"coordinates":[4.705231,52.032005],"type":"Point"}
}