{
  "type": "Feature",
  "properties": {
    "addr:full":"Ambachten 3 Someren North Brabant 5711 LC",
    "addr:housenumber":"3",
    "addr:postcode":"5711 lc",
    "addr:street":"Ambachten",
    "iso:country":"NL",
    "sg:address":"Ambachten 3",
    "sg:city":"Someren",
    "sg:orig_category":"Kunststoffen- Verwerkende Industrie",
    "sg:phone":"+31 493 495 076",
    "sg:postcode":"5711 LC",
    "sg:province":"North Brabant",
    "sg:website":"http://www.custers-kunststoffen.nl",
    "wof:name":"Custers Bv",
    "wof:placetype":"venue"
},
  "geometry": {"coordinates":[5.727366,51.386944],"type":"Point"}
}