{
  "type": "Feature",
  "properties": {
    "addr:full":"Leyweg 559 A Den Haag South Holland 2545 GH",
    "addr:housenumber":"559 a",
    "addr:postcode":"2545 gh",
    "addr:street":"Leyweg",
    "iso:country":"NL",
    "sg:address":"Leyweg 559 A",
    "sg:city":"Den Haag",
    "sg:orig_category":"Kappers",
    "sg:phone":"+31 70 329 5467",
    "sg:postcode":"2545 GH",
    "sg:province":"South Holland",
    "wof:name":"Robin En Jill Kappers",
    "wof:placetype":"venue"
},
  "geometry": {"coordinates":[4.274454,52.049637],"type":"Point"}
}