{
  "type": "Feature",
  "properties": {
    "addr:full":"Coolhaven 5052 Rotterdam Noord-Brabant 3024 AD",
    "addr:housenumber":"5052",
    "addr:postcode":"3024 ad",
    "addr:street":"Coolhaven",
    "iso:country":"NL",
    "sg:address":"Coolhaven 5052",
    "sg:city":"Rotterdam",
    "sg:orig_category":"Galeries",
    "sg:phone":"+31 10 244 0079",
    "sg:postcode":"3024 AD",
    "sg:province":"Noord-Brabant",
    "sg:website":"http://www.dutch-art.nl",
    "wof:name":"Dutch-Art.Nl",
    "wof:placetype":"venue"
},
  "geometry": {"coordinates":[4.45573,51.907589],"type":"Point"}
}