{
  "type": "Feature",
  "properties": {
    "iso:country":"NL",
    "sg:address":"Herderplein 22",
    "sg:city":"Utrecht",
    "sg:classifiers":[
        {
            "category":"Communications",
            "subcategory":"Television Station",
            "type":"Services"
        }
    ],
    "sg:phone":"+31 30 293 0116",
    "sg:postcode":"3533 BP",
    "sg:province":"Utrecht",
    "sg:tags":[
        "video",
        "audio",
        "verhuur"
    ],
    "wof:name":"Videotheek Oog In Al",
    "wof:placetype":"venue"
},
  "geometry": {"coordinates":[5.081227,52.090572],"type":"Point"}
}