{
  "type": "Feature",
  "properties": {
    "addr:full":"Pr Willem Alexanderstr 2 Lopik Utrecht 3411 BG",
    "addr:housenumber":"2",
    "addr:postcode":"3411",
    "addr:street":"Alexanderstr",
    "iso:country":"NL",
    "sg:address":"Pr Willem Alexanderstr 2",
    "sg:city":"Lopik",
    "sg:orig_category":"Boekhandels",
    "sg:phone":"+31 348 551 185",
    "sg:postcode":"3411 BG",
    "sg:province":"Utrecht",
    "wof:name":"The Read Shop",
    "wof:placetype":"venue"
},
  "geometry": {"coordinates":[4.949712,51.974659],"type":"Point"}
}