{
  "type": "Feature",
  "properties": {
    "addr:full":"Blokweg 9 Zevenbergen Noord-Brabant 4761 RA",
    "addr:housenumber":"9",
    "addr:postcode":"4761 ra",
    "addr:street":"Blokweg",
    "iso:country":"NL",
    "sg:address":"Blokweg 9",
    "sg:city":"Zevenbergen",
    "sg:orig_category":"Pleziervaartuigen And Reparatie",
    "sg:phone":"+31 168 326 122",
    "sg:postcode":"4761 RA",
    "sg:province":"Noord-Brabant",
    "wof:name":"Van Der Torre & Teunissen Jachtbouw",
    "wof:placetype":"venue"
},
  "geometry": {"coordinates":[4.610683,51.647499],"type":"Point"}
}