{
  "type": "Feature",
  "properties": {
    "addr:full":"Herenstraat 82 Voorburg Zuid-Holland 2271 CK",
    "addr:housenumber":"82",
    "addr:postcode":"2271 ck",
    "addr:street":"Herenstraat",
    "iso:country":"NL",
    "sg:address":"Herenstraat 82",
    "sg:city":"Voorburg",
    "sg:classifiers":[
        {
            "category":"Food & Beverages",
            "subcategory":"Fruits & Vegetables",
            "type":"Retail Goods"
        }
    ],
    "sg:phone":"+31 70 386 4154",
    "sg:postcode":"2271 CK",
    "sg:province":"Zuid-Holland",
    "sg:tags":[
        "groenten"
    ],
    "wof:name":"A.P. Gijben",
    "wof:placetype":"venue"
},
  "geometry": {"coordinates":[4.364193,52.067307],"type":"Point"}
}