{
  "type": "Feature",
  "properties": {
    "addr:full":"Aalsmeerweg 96 Amsterdam North Holland 1059 AN",
    "addr:housenumber":"96",
    "addr:postcode":"1059 an",
    "addr:street":"Aalsmeerweg",
    "iso:country":"NL",
    "sg:address":"Aalsmeerweg 96",
    "sg:city":"Amsterdam",
    "sg:classifiers":[
        {
            "category":"Fast Food",
            "type":"Food & Drink"
        }
    ],
    "sg:phone":"+31 20 617 6838",
    "sg:postcode":"1059 AN",
    "sg:province":"North Holland",
    "sg:tags":[
        "afhaal",
        "restaurant"
    ],
    "wof:name":"Snackbar Hanny",
    "wof:placetype":"venue"
},
  "geometry": {"coordinates":[4.847459,52.347992],"type":"Point"}
}