{
  "type": "Feature",
  "properties": {
    "addr:full":"Planetenln 82 Nieuw Lekkerland Zuid-Holland 2957 SN",
    "addr:housenumber":"82",
    "addr:postcode":"lekkerland;2957 sn",
    "addr:street":"Planetenln",
    "iso:country":"NL",
    "sg:address":"Planetenln 82",
    "sg:city":"Nieuw Lekkerland",
    "sg:orig_category":"Accountants - Administratie- Consulenten En -Kantoren",
    "sg:phone":"+31 184 681 551",
    "sg:postcode":"2957 SN",
    "sg:province":"Zuid-Holland",
    "wof:name":"Pellikaan Bv, M",
    "wof:placetype":"venue"
},
  "geometry": {"coordinates":[4.678453,51.886353],"type":"Point"}
}