{
  "type": "Feature",
  "properties": {
    "addr:full":"N Japiksestr 69 Amsterdam Noord-Holland 1065 KE",
    "addr:housenumber":"69",
    "addr:postcode":"1065 ke",
    "addr:street":"N",
    "iso:country":"NL",
    "sg:address":"N Japiksestr 69",
    "sg:city":"Amsterdam",
    "sg:orig_category":"Beeldende Kunstenaars",
    "sg:phone":"+31 20 615 2722",
    "sg:postcode":"1065 KE",
    "sg:province":"Noord-Holland",
    "wof:name":"L\u00f7B, Kurt",
    "wof:placetype":"venue"
},
  "geometry": {"coordinates":[4.826239,52.362015],"type":"Point"}
}