{
  "type": "Feature",
  "properties": {
    "addr:full":"Valkenburgerln 111 Boskoop South Holland 2771 CZ",
    "addr:housenumber":"111;2771",
    "addr:street":"Boskoop South",
    "iso:country":"NL",
    "sg:address":"Valkenburgerln 111",
    "sg:city":"Boskoop",
    "sg:orig_category":"Vertaalbureaus",
    "sg:phone":"+31 172 216 949",
    "sg:postcode":"2771 CZ",
    "sg:province":"South Holland",
    "wof:name":"Hispania",
    "wof:placetype":"venue"
},
  "geometry": {"coordinates":[4.669371,52.077972],"type":"Point"}
}