{
  "type": "Feature",
  "properties": {
    "addr:full":"Burg V Cannstr 2 Helden Limburg 5988 CR",
    "addr:housenumber":"2",
    "addr:postcode":"5988 cr",
    "addr:street":"Burg V Cannstr",
    "iso:country":"NL",
    "sg:address":"Burg V Cannstr 2",
    "sg:city":"Helden",
    "sg:orig_category":"Verenigingen En Stichtingen",
    "sg:phone":"+31 77 307 3379",
    "sg:postcode":"5988 CR",
    "sg:province":"Limburg",
    "wof:name":"Lambertus Kon Schuttersgilde, St",
    "wof:placetype":"venue"
},
  "geometry": {"coordinates":[-89.41683999999999,41.772732],"type":"Point"}
}