{
  "type": "Feature",
  "properties": {
    "iso:country":"NL",
    "sg:address":"Steenbergsestr 9",
    "sg:city":"Bergen Op Zoom",
    "sg:orig_category":"Vakantieverblijven",
    "sg:phone":"+31 164 238 730",
    "sg:postcode":"4611 TC",
    "sg:province":"Noord-Brabant",
    "sg:website":"http://www.celticshop.nl",
    "wof:name":"Celtic Shop, The",
    "wof:placetype":"venue"
},
  "geometry": {"coordinates":[4.284555,51.495842],"type":"Point"}
}