{
  "type": "Feature",
  "properties": {
    "addr:full":"Het Ronsel 22 Bergeyk North Brabant 5571 SW",
    "addr:housenumber":"22",
    "addr:postcode":"5571 sw",
    "addr:street":"Het Ronsel",
    "iso:country":"NL",
    "sg:address":"Het Ronsel 22",
    "sg:city":"Bergeyk",
    "sg:orig_category":"Metselwerken",
    "sg:phone":"+31 6 54364705",
    "sg:postcode":"5571 SW",
    "sg:province":"North Brabant",
    "wof:name":"Box",
    "wof:placetype":"venue"
},
  "geometry": {"coordinates":[5.342599,51.318722],"type":"Point"}
}