{
  "type": "Feature",
  "properties": {
    "addr:full":"M Ruthplaats 68 Leiden Zuid-Holland 2331 RJ",
    "addr:housenumber":"68",
    "addr:postcode":"2331 rj",
    "addr:street":"M Ruthplaats",
    "iso:country":"NL",
    "sg:address":"M Ruthplaats 68",
    "sg:city":"Leiden",
    "sg:orig_category":"Betonijzervlechten",
    "sg:phone":"+31 71 532 1117",
    "sg:postcode":"2331 RJ",
    "sg:province":"Zuid-Holland",
    "wof:name":"Groenendijk, J",
    "wof:placetype":"venue"
},
  "geometry": {"coordinates":[4.450312,52.158367],"type":"Point"}
}