{
  "type": "Feature",
  "properties": {
    "iso:country":"NL",
    "sg:address":"Voorsterstr 13",
    "sg:city":"Nuth",
    "sg:orig_category":"Onroerende Goederen",
    "sg:phone":"+31 45 524 4877",
    "sg:postcode":"6361 ES",
    "sg:province":"Limburg",
    "wof:name":"Voorsterkleef Bv",
    "wof:placetype":"venue"
},
  "geometry": {"coordinates":[5.87683,50.916248],"type":"Point"}
}