{
  "type": "Feature",
  "properties": {
    "addr:full":"Oudewg 99 Siddeburen Groningen 9628 CD",
    "addr:housenumber":"99",
    "addr:postcode":"9628 cd",
    "addr:street":"Oudewg",
    "iso:country":"NL",
    "sg:address":"Oudewg 99",
    "sg:city":"Siddeburen",
    "sg:orig_category":"Verzekeringen - Verzekeringskantoren",
    "sg:phone":"+31 598 432 278",
    "sg:postcode":"9628 CD",
    "sg:province":"Groningen",
    "wof:name":"Huisman",
    "wof:placetype":"venue"
},
  "geometry": {"coordinates":[6.872812,53.249344],"type":"Point"}
}