{
  "type": "Feature",
  "properties": {
    "iso:country":"NL",
    "sg:address":"Nieuwenoord 275",
    "sg:city":"Rotterdam",
    "sg:orig_category":"Beveiliging",
    "sg:phone":"+31 10 292 0775",
    "sg:postcode":"3079 LK",
    "sg:province":"Zuid-Holland",
    "wof:name":"Waal, R V/D",
    "wof:placetype":"venue"
},
  "geometry": {"coordinates":[4.558908,51.880596],"type":"Point"}
}