{
  "type": "Feature",
  "properties": {
    "addr:full":"Albrechtln 14A Bussum Noord-Holland 1404 AK",
    "addr:housenumber":"14a",
    "addr:postcode":"1404 ak",
    "addr:street":"Albrechtln",
    "iso:country":"NL",
    "sg:address":"Albrechtln 14A",
    "sg:city":"Bussum",
    "sg:orig_category":"Juridische Adviseurs",
    "sg:phone":"+31 35 695 4010",
    "sg:postcode":"1404 AK",
    "sg:province":"Noord-Holland",
    "sg:website":"http://www.apollamme.nl",
    "wof:name":"Apol & Lamme",
    "wof:placetype":"venue"
},
  "geometry": {"coordinates":[5.158568,52.280811],"type":"Point"}
}