{
  "type": "Feature",
  "properties": {
    "addr:full":"Wilhelminaln 4 Scheemda Groningen 9679 CR",
    "addr:housenumber":"4",
    "addr:postcode":"9679 cr",
    "addr:street":"Wilhelminaln",
    "iso:country":"NL",
    "sg:address":"Wilhelminaln 4",
    "sg:city":"Scheemda",
    "sg:orig_category":"Fotoreportages",
    "sg:phone":"+31 597 592 457",
    "sg:postcode":"9679 CR",
    "sg:province":"Groningen",
    "wof:name":"Ruiter",
    "wof:placetype":"venue"
},
  "geometry": {"coordinates":[6.985023,53.172039],"type":"Point"}
}