{
  "type": "Feature",
  "properties": {
    "addr:full":"2E Keucheniusstr 12 Amsterdam Noord-Holland 1051 VR",
    "addr:housenumber":"12",
    "addr:postcode":"1051 vr",
    "addr:street":"2E Keucheniusstr",
    "iso:country":"NL",
    "sg:address":"2E Keucheniusstr 12",
    "sg:city":"Amsterdam",
    "sg:classifiers":[
        {
            "category":"Food & Beverages",
            "subcategory":"Bakery",
            "type":"Retail Goods"
        }
    ],
    "sg:phone":"+31 20 688 9039",
    "sg:postcode":"1051 VR",
    "sg:province":"Noord-Holland",
    "sg:tags":[
        "pizza"
    ],
    "wof:name":"Pasto",
    "wof:placetype":"venue"
},
  "geometry": {"coordinates":[4.869017,52.380615],"type":"Point"}
}