{
  "type": "Feature",
  "properties": {
    "addr:full":"Overtoom 168 Amsterdam Noord-Holland 1054 HP",
    "addr:housenumber":"168",
    "addr:postcode":"1054 hp",
    "addr:street":"Overtoom",
    "iso:country":"NL",
    "sg:address":"Overtoom 168",
    "sg:city":"Amsterdam",
    "sg:orig_category":"Adviesbureaus Bedrijfsorganisatie",
    "sg:phone":"+31 20 618 6427",
    "sg:postcode":"1054 HP",
    "sg:province":"Noord-Holland",
    "wof:name":"Georgiades, P",
    "wof:placetype":"venue"
},
  "geometry": {"coordinates":[4.872712,52.362301],"type":"Point"}
}