{
  "type": "Feature",
  "properties": {
    "addr:full":"Graswg 2 Hellevoetsluis Zuid-Holland 3225 LB",
    "addr:housenumber":"2",
    "addr:postcode":"3225 lb",
    "addr:street":"Graswg",
    "iso:country":"NL",
    "sg:address":"Graswg 2",
    "sg:city":"Hellevoetsluis",
    "sg:orig_category":"Product-Promotie",
    "sg:phone":"+31 181 328 388",
    "sg:postcode":"3225 LB",
    "sg:province":"Zuid-Holland",
    "sg:website":"http://www.art-business-group.nl",
    "wof:name":"Art",
    "wof:placetype":"venue"
},
  "geometry": {"coordinates":[4.176336,51.83717],"type":"Point"}
}