{
  "type": "Feature",
  "properties": {
    "addr:full":"Noorderelsweg 6 Dordrecht Zuid-Holland 3329 KH",
    "addr:housenumber":"6",
    "addr:postcode":"3329 kh",
    "addr:street":"Noorderelsweg",
    "iso:country":"NL",
    "sg:address":"Noorderelsweg 6",
    "sg:city":"Dordrecht",
    "sg:orig_category":"Goederenvervoer Over De Weg",
    "sg:phone":"+31 78 616 5281",
    "sg:postcode":"3329 KH",
    "sg:province":"Zuid-Holland",
    "wof:name":"Transportbedrijf P. Neels En Zoon",
    "wof:placetype":"venue"
},
  "geometry": {"coordinates":[4.693884,51.760693],"type":"Point"}
}