{
  "type": "Feature",
  "properties": {
    "addr:full":"Tottenhamstr 50 Dedemsvaart NL.08 7701 BN",
    "addr:housenumber":"50;nl.08",
    "addr:postcode":"7701 bn",
    "addr:street":"Tottenhamstr",
    "iso:country":"NL",
    "sg:address":"Tottenhamstr 50",
    "sg:city":"Dedemsvaart",
    "sg:orig_category":"Autoschade- Herstelbedrijven",
    "sg:phone":"+31 523 612 879",
    "sg:postcode":"7701 BN",
    "sg:province":"NL.08",
    "wof:name":"Ekkel Vof",
    "wof:placetype":"venue"
},
  "geometry": {"coordinates":[6.523408,52.608067],"type":"Point"}
}