{
  "type": "Feature",
  "properties": {
    "addr:full":"T V Poortvlietstr 6 S Gravenhage South Holland 2521 ZC",
    "addr:housenumber":"6",
    "addr:postcode":"2521 zc",
    "addr:street":"T;Poortvlietstr;S Gravenhage",
    "iso:country":"NL",
    "sg:address":"T V Poortvlietstr 6",
    "sg:city":"S Gravenhage",
    "sg:orig_category":"Postkantoren",
    "sg:phone":"+31 70 399 4784",
    "sg:postcode":"2521 ZC",
    "sg:province":"South Holland",
    "sg:website":"http://www.postkantoor.nl",
    "wof:name":"Postkantoor",
    "wof:placetype":"venue"
},
  "geometry": {"coordinates":[4.32071,52.062988],"type":"Point"}
}