{
  "type": "Feature",
  "properties": {
    "iso:country":"NL",
    "sg:address":"F Erensln 16",
    "sg:city":"Landgraaf",
    "sg:orig_category":"Geluidsinstallaties",
    "sg:phone":"+31 45 569 1560",
    "sg:postcode":"6371 GV",
    "sg:province":"Limburg",
    "wof:name":"Jarco",
    "wof:placetype":"venue"
},
  "geometry": {"coordinates":[6.013921,50.897247],"type":"Point"}
}