{
  "type": "Feature",
  "properties": {
    "iso:country":"NL",
    "sg:address":"Schrassertstraat 5",
    "sg:city":"Arnhem",
    "sg:orig_category":"Boekenuitgeverijen",
    "sg:phone":"+31 26 351 6226",
    "sg:postcode":"6821 AD",
    "sg:province":"Gelderland",
    "wof:name":"Jan Brand Boeken",
    "wof:placetype":"venue"
},
  "geometry": {"coordinates":[5.911705,51.986149],"type":"Point"}
}