{
  "type": "Feature",
  "properties": {
    "addr:full":"Kromme Zandweg 12 Dordrecht Zuid-Holland 3319 GH",
    "addr:housenumber":"12",
    "addr:postcode":"3319 gh",
    "addr:street":"Kromme Zandweg",
    "iso:country":"NL",
    "sg:address":"Kromme Zandweg 12",
    "sg:city":"Dordrecht",
    "sg:orig_category":"Loodgieterswerk, Verwarming And Sanitaire Installaties",
    "sg:phone":"+31 78 616 5332",
    "sg:postcode":"3319 GH",
    "sg:province":"Zuid-Holland",
    "wof:name":"Am",
    "wof:placetype":"venue"
},
  "geometry": {"coordinates":[4.705931,51.79512],"type":"Point"}
}