{
  "type": "Feature",
  "properties": {
    "addr:full":"Auroraln 19 Apeldoorn Gelderland 7321 BN",
    "addr:housenumber":"19",
    "addr:postcode":"7321 bn",
    "addr:street":"Auroraln;Gelderland",
    "iso:country":"NL",
    "sg:address":"Auroraln 19",
    "sg:city":"Apeldoorn",
    "sg:orig_category":"Autopoetsbedrijven",
    "sg:phone":"+31 55 378 0010",
    "sg:postcode":"7321 BN",
    "sg:province":"Gelderland",
    "wof:name":"Verschoor",
    "wof:placetype":"venue"
},
  "geometry": {"coordinates":[5.98598,52.21265],"type":"Point"}
}