{
  "type": "Feature",
  "properties": {
    "addr:full":"Flemingweg 18 Alphen A/D Rijn South Holland 2408 AV",
    "addr:housenumber":"18",
    "addr:postcode":"2408 av",
    "addr:street":"Flemingweg",
    "iso:country":"NL",
    "sg:address":"Flemingweg 18",
    "sg:city":"Alphen A/D Rijn",
    "sg:orig_category":"Farmaceutische Producten Gh",
    "sg:phone":"+31 172 449 494",
    "sg:postcode":"2408 AV",
    "sg:province":"South Holland",
    "wof:name":"Novo Nordisk Farma Bv",
    "wof:placetype":"venue"
},
  "geometry": {"coordinates":[4.629631,52.123558],"type":"Point"}
}