{
  "type": "Feature",
  "properties": {
    "addr:full":"Lutterzandwg 19 Beuningen Ov Overijssel 7588 PB",
    "addr:housenumber":"19",
    "addr:postcode":"7588 pb",
    "addr:street":"Lutterzandwg;Ov",
    "iso:country":"NL",
    "sg:address":"Lutterzandwg 19",
    "sg:city":"Beuningen Ov",
    "sg:orig_category":"Exploitatie- Maatschappijen",
    "sg:phone":"+31 541 551 392",
    "sg:postcode":"7588 PB",
    "sg:province":"Overijssel",
    "wof:name":"Meuleman Bv",
    "wof:placetype":"venue"
},
  "geometry": {"coordinates":[7.028604,52.344318],"type":"Point"}
}