{
  "type": "Feature",
  "properties": {
    "iso:country":"NL",
    "sg:address":"De Steiger 34",
    "sg:city":"Almere",
    "sg:orig_category":"Scheidingswanden - Fabrieken",
    "sg:phone":"+31 36 523 9493",
    "sg:postcode":"1351 AB",
    "sg:province":"Flevoland",
    "wof:name":"Top Montage",
    "wof:placetype":"venue"
},
  "geometry": {"coordinates":[5.220182,52.349026],"type":"Point"}
}