{
  "type": "Feature",
  "properties": {
    "addr:full":"Voorstr 86 Brielle Zuid-Holland 3231 BK",
    "addr:housenumber":"86",
    "addr:postcode":"3231 bk",
    "addr:street":"Voorstr",
    "iso:country":"NL",
    "sg:address":"Voorstr 86",
    "sg:city":"Brielle",
    "sg:orig_category":"Artsen - Huisartsen",
    "sg:phone":"+31 181 417 449",
    "sg:postcode":"3231 BK",
    "sg:province":"Zuid-Holland",
    "wof:name":"Schoenmaker C J In 'T Veld, G M",
    "wof:placetype":"venue"
},
  "geometry": {"coordinates":[4.165842,51.904228],"type":"Point"}
}