{
  "type": "Feature",
  "properties": {
    "addr:full":"Hennekijnstraat 35 Rotterdam Zuid-Holland 3012 EB",
    "addr:housenumber":"35",
    "addr:postcode":"3012 eb",
    "addr:street":"Hennekijnstraat",
    "iso:country":"NL",
    "sg:address":"Hennekijnstraat 35",
    "sg:city":"Rotterdam",
    "sg:orig_category":"Verzekeringen",
    "sg:phone":"+31 10 414 8854",
    "sg:postcode":"3012 EB",
    "sg:province":"Zuid-Holland",
    "wof:name":"J. Mollen Assurantien",
    "wof:placetype":"venue"
},
  "geometry": {"coordinates":[4.477462,51.920216],"type":"Point"}
}