{
  "type": "Feature",
  "properties": {
    "addr:full":"Stationspln 19 Roermond Limburg 6041 GN",
    "addr:housenumber":"19",
    "addr:postcode":"6041 gn",
    "addr:street":"Stationspln",
    "iso:country":"NL",
    "sg:address":"Stationspln 19",
    "sg:city":"Roermond",
    "sg:orig_category":"Broodjeszaken",
    "sg:phone":"+31 475 311 681",
    "sg:postcode":"6041 GN",
    "sg:province":"Limburg",
    "wof:name":"Doedels",
    "wof:placetype":"venue"
},
  "geometry": {"coordinates":[5.991672,51.19268],"type":"Point"}
}