{
  "type": "Feature",
  "properties": {
    "addr:full":"Tuindorpstraat 126 Hengelo Ov Overijssel 7555 CS",
    "addr:housenumber":"126",
    "addr:postcode":"7555 cs",
    "addr:street":"Tuindorpstraat;Ov",
    "iso:country":"NL",
    "sg:address":"Tuindorpstraat 126",
    "sg:city":"Hengelo Ov",
    "sg:orig_category":"Drukkerijen And Copyshops",
    "sg:phone":"+31 74 250 5464",
    "sg:postcode":"7555 CS",
    "sg:province":"Overijssel",
    "wof:name":"Duo Tone",
    "wof:placetype":"venue"
},
  "geometry": {"coordinates":[6.781446,52.262718],"type":"Point"}
}