{
  "type": "Feature",
  "properties": {
    "iso:country":"NL",
    "sg:address":"Akerstr 69",
    "sg:city":"Heerlen",
    "sg:classifiers":[
        {
            "category":"Professional",
            "subcategory":"Accounting & Tax Preparation",
            "type":"Services"
        }
    ],
    "sg:phone":"+31 45 571 6965",
    "sg:postcode":"6417 BJ",
    "sg:province":"Limburg",
    "sg:tags":[
        "accountant",
        "en",
        "-kantoren",
        "register-"
    ],
    "wof:name":"Parkstad",
    "wof:placetype":"venue"
},
  "geometry": {"coordinates":[5.983442,50.883114],"type":"Point"}
}