{
  "type": "Feature",
  "properties": {
    "addr:full":"Eilewyksreed 10 Oudehorne Friesland 8413 NL",
    "addr:housenumber":"10",
    "addr:postcode":"8413 nl",
    "addr:street":"Eilewyksreed",
    "iso:country":"NL",
    "sg:address":"Eilewyksreed 10",
    "sg:city":"Oudehorne",
    "sg:orig_category":"Beeldende Kunstenaars",
    "sg:phone":"+31 513 542 110",
    "sg:postcode":"8413 NL",
    "sg:province":"Friesland",
    "wof:name":"Pereboom, Hanneke",
    "wof:placetype":"venue"
},
  "geometry": {"coordinates":[6.071414,52.965096],"type":"Point"}
}