{
  "type": "Feature",
  "properties": {
    "iso:country":"NL",
    "sg:address":"Beatrixpln 4A",
    "sg:city":"Urmond",
    "sg:orig_category":"Kappers",
    "sg:phone":"+31 46 433 9926",
    "sg:postcode":"6129 BE",
    "sg:province":"Limburg",
    "wof:name":"Movi'S",
    "wof:placetype":"venue"
},
  "geometry": {"coordinates":[5.770804,51.004841],"type":"Point"}
}