{
  "type": "Feature",
  "properties": {
    "addr:full":"Schiphol Boulev 159 Luchth Schiphol Noord-Holland 1118 BG",
    "addr:housenumber":"159",
    "addr:postcode":"1118",
    "addr:street":"Boulev",
    "iso:country":"NL",
    "sg:address":"Schiphol Boulev 159",
    "sg:city":"Luchth Schiphol",
    "sg:orig_category":"Luchtvaart- Maatschappijen",
    "sg:phone":"+31 20 316 3256",
    "sg:postcode":"1118 BG",
    "sg:province":"Noord-Holland",
    "wof:name":"Ghana Airways",
    "wof:placetype":"venue"
},
  "geometry": {"coordinates":[4.757639,52.30822],"type":"Point"}
}