{
  "type": "Feature",
  "properties": {
    "addr:full":"V Baerleplnts 26 Dordrecht Zuid-Holland 3314 BH",
    "addr:housenumber":"26",
    "addr:postcode":"3314 bh",
    "iso:country":"NL",
    "sg:address":"V Baerleplnts 26",
    "sg:city":"Dordrecht",
    "sg:orig_category":"Woningbouw- Verenigingen En -Stichtingen",
    "sg:phone":"+31 78 633 6888",
    "sg:postcode":"3314 BH",
    "sg:province":"Zuid-Holland",
    "sg:website":"http://www.woondrecht.nl",
    "wof:name":"Woondrecht",
    "wof:placetype":"venue"
},
  "geometry": {"coordinates":[4.6565060616,51.8119163513],"type":"Point"}
}