{
  "type": "Feature",
  "properties": {
    "addr:full":"Postelstraat 59/2Hg 'S Hertogenbosch North Brabant 5211 DX",
    "addr:housenumber":"59 / 2hg",
    "addr:postcode":"5211 dx",
    "addr:street":"Postelstraat;' S Hertogenbosch",
    "iso:country":"NL",
    "sg:address":"Postelstraat 59/2Hg",
    "sg:city":"'S Hertogenbosch",
    "sg:orig_category":"Boekhouders",
    "sg:phone":"+31 73 613 7414",
    "sg:postcode":"5211 DX",
    "sg:province":"North Brabant",
    "wof:name":"Fernandez Bedrijfsondersteuning",
    "wof:placetype":"venue"
},
  "geometry": {"coordinates":[5.300992,51.688576],"type":"Point"}
}