{
  "type": "Feature",
  "properties": {
    "addr:full":"Eperweg 1 Oene Gelderland 8167 LE",
    "addr:housenumber":"1",
    "addr:postcode":"8167 le",
    "addr:street":"Eperweg;Gelderland",
    "iso:country":"NL",
    "sg:address":"Eperweg 1",
    "sg:city":"Oene",
    "sg:orig_category":"Schilderwerk",
    "sg:phone":"+31 578 641 488",
    "sg:postcode":"8167 LE",
    "sg:province":"Gelderland",
    "wof:name":"Schildersbedrijf Buitenkamp Bv",
    "wof:placetype":"venue"
},
  "geometry": {"coordinates":[6.04686,52.344711],"type":"Point"}
}