{
  "type": "Feature",
  "properties": {
    "addr:full":"Begijnekade 6 Utrecht Utrecht 3512 VT",
    "addr:housenumber":"6",
    "addr:postcode":"3512",
    "addr:street":"Begijnekade",
    "iso:country":"NL",
    "sg:address":"Begijnekade 6",
    "sg:city":"Utrecht",
    "sg:orig_category":"Advocaten And Juridische Adviseurs",
    "sg:phone":"+31 30 230 0988",
    "sg:postcode":"3512 VT",
    "sg:province":"Utrecht",
    "wof:name":"Advocatenkantoor Mevr. Mr. M.D. Groot",
    "wof:placetype":"venue"
},
  "geometry": {"coordinates":[5.120755,52.096924],"type":"Point"}
}