{
  "type": "Feature",
  "properties": {
    "iso:country":"NL",
    "sg:address":"Moezelweg 220",
    "sg:city":"Europoort Rt",
    "sg:classifiers":[
        {
            "category":"Retail",
            "subcategory":"Storage",
            "type":"Services"
        }
    ],
    "sg:phone":"+31 181 263 466",
    "sg:postcode":"3198 LS",
    "sg:province":"South Holland",
    "sg:tags":[
        "opslag",
        "bewaring"
    ],
    "wof:name":"Hacon Containers Vof",
    "wof:placetype":"venue"
},
  "geometry": {"coordinates":[4.1774539948,51.922832489],"type":"Point"}
}