{
  "type": "Feature",
  "properties": {
    "addr:full":"Energieweg 3 Hapert Noord-Brabant 5527 AH",
    "addr:housenumber":"3",
    "addr:postcode":"5527 ah",
    "addr:street":"Energieweg",
    "iso:country":"NL",
    "sg:address":"Energieweg 3",
    "sg:city":"Hapert",
    "sg:orig_category":"Metaalbekleding And -Behandeling",
    "sg:phone":"+31 497 360 031",
    "sg:postcode":"5527 AH",
    "sg:province":"Noord-Brabant",
    "wof:name":"Comair Holland Bv",
    "wof:placetype":"venue"
},
  "geometry": {"coordinates":[5.270579,51.372364],"type":"Point"}
}