{
  "type": "Feature",
  "properties": {
    "addr:full":"Zilverpk 86 S Hertogenbosch Noord-Brabant 5237 HT",
    "addr:housenumber":"86",
    "addr:postcode":"5237 ht",
    "addr:street":"Zilverpk;S Hertogenbosch",
    "iso:country":"NL",
    "sg:address":"Zilverpk 86",
    "sg:city":"S Hertogenbosch",
    "sg:orig_category":"Adviesbureaus Bouwkunde",
    "sg:phone":"+31 73 645 0645",
    "sg:postcode":"5237 HT",
    "sg:province":"Noord-Brabant",
    "wof:name":"Space",
    "wof:placetype":"venue"
},
  "geometry": {"coordinates":[5.294175148,51.7292976379],"type":"Point"}
}