{
  "type": "Feature",
  "properties": {
    "addr:full":"Hofstraat 11 Aalten Gelderland 7121 DM",
    "addr:housenumber":"11",
    "addr:postcode":"7121 dm",
    "addr:street":"Hofstraat;Gelderland",
    "iso:country":"NL",
    "sg:address":"Hofstraat 11",
    "sg:city":"Aalten",
    "sg:orig_category":"Verzekeringen",
    "sg:phone":"+31 543 471 287",
    "sg:postcode":"7121 DM",
    "sg:province":"Gelderland",
    "wof:name":"B.C. Vreemann",
    "wof:placetype":"venue"
},
  "geometry": {"coordinates":[6.583479,51.926254],"type":"Point"}
}