{
  "type": "Feature",
  "properties": {
    "addr:full":"Ursulinenstr 29 Eysden Limburg 6245 CH",
    "addr:housenumber":"29",
    "addr:postcode":"6245",
    "addr:street":"Ursulinenstr",
    "iso:country":"NL",
    "sg:address":"Ursulinenstr 29",
    "sg:city":"Eysden",
    "sg:orig_category":"Adviesbureaus Bedrijfsorganisatie",
    "sg:phone":"+31 6 11353937",
    "sg:postcode":"6245 CH",
    "sg:province":"Limburg",
    "sg:website":"http://www.quvo.nl",
    "wof:name":"Quvo",
    "wof:placetype":"venue"
},
  "geometry": {"coordinates":[7.932855,47.1824],"type":"Point"}
}