{
  "type": "Feature",
  "properties": {
    "addr:full":"Zamenhofstraat 112 Amsterdam North Holland 1022 AG",
    "addr:housenumber":"112",
    "addr:postcode":"1022",
    "addr:street":"Zamenhofstraat",
    "iso:country":"NL",
    "sg:address":"Zamenhofstraat 112",
    "sg:city":"Amsterdam",
    "sg:orig_category":"Meubelreparatie And -Restauratie",
    "sg:phone":"+31 20 632 1164",
    "sg:postcode":"1022 AG",
    "sg:province":"North Holland",
    "wof:name":"Meubelstoffeerderij W. Schroder",
    "wof:placetype":"venue"
},
  "geometry": {"coordinates":[4.930848,52.38678],"type":"Point"}
}