{
  "type": "Feature",
  "properties": {
    "iso:country":"NL",
    "sg:address":"Veerkade 6",
    "sg:city":"Rotterdam",
    "sg:orig_category":"Makelaars In Onroerend Goed",
    "sg:phone":"+31 10 413 2460",
    "sg:postcode":"3016 DE",
    "sg:province":"Zuid-Holland",
    "wof:name":"Makelaarskantoor Rijndelta Bv",
    "wof:placetype":"venue"
},
  "geometry": {"coordinates":[4.479524,51.90831],"type":"Point"}
}