{
  "type": "Feature",
  "properties": {
    "addr:full":"Emmapassage 23 Tilburg Noord-Brabant 5038 XA",
    "addr:housenumber":"23",
    "addr:postcode":"5038 xa",
    "addr:street":"Emmapassage",
    "iso:country":"NL",
    "sg:address":"Emmapassage 23",
    "sg:city":"Tilburg",
    "sg:orig_category":"Huishoudapparatuur, Televisies And Radio'S",
    "sg:phone":"+31 13 544 3733",
    "sg:postcode":"5038 XA",
    "sg:province":"Noord-Brabant",
    "wof:name":"Mikro Electro Bv",
    "wof:placetype":"venue"
},
  "geometry": {"coordinates":[5.088871,51.555695],"type":"Point"}
}