{
  "type": "Feature",
  "properties": {
    "addr:full":"Corridor 6 Veenendaal Utrecht 3901 AA",
    "addr:housenumber":"6",
    "addr:postcode":"3901 aa",
    "addr:street":"Corridor",
    "iso:country":"NL",
    "sg:address":"Corridor 6",
    "sg:city":"Veenendaal",
    "sg:orig_category":"Schoenen",
    "sg:phone":"+31 318 500 006",
    "sg:postcode":"3901 AA",
    "sg:province":"Utrecht",
    "sg:website":"http://www.engelen-schoenmode.nl/veenendaal",
    "wof:name":"Engelen",
    "wof:placetype":"venue"
},
  "geometry": {"coordinates":[5.555002,52.025398],"type":"Point"}
}