{
  "type": "Feature",
  "properties": {
    "addr:full":"Meester Geertswei 15 Wijnjewoude Friesland 9241 GJ",
    "addr:housenumber":"15",
    "addr:postcode":"9241 gj",
    "addr:street":"Meester Geertswei",
    "iso:country":"NL",
    "sg:address":"Meester Geertswei 15",
    "sg:city":"Wijnjewoude",
    "sg:classifiers":[
        {
            "category":"Education",
            "subcategory":"Preschool",
            "type":"Public Place"
        }
    ],
    "sg:phone":"+31 516 481 721",
    "sg:postcode":"9241 GJ",
    "sg:province":"Friesland",
    "sg:tags":[
        "kleuteronderwijs",
        "basis-"
    ],
    "wof:name":"Peuterspeelplaats De Telle",
    "wof:placetype":"venue"
},
  "geometry": {"coordinates":[6.202857,53.05629],"type":"Point"}
}