{
  "type": "Feature",
  "properties": {
    "addr:full":"Kade 81 Roosendaal Noord-Brabant 4703 GD",
    "addr:housenumber":"81",
    "addr:postcode":"4703 gd",
    "addr:street":"Kade",
    "iso:country":"NL",
    "sg:address":"Kade 81",
    "sg:city":"Roosendaal",
    "sg:orig_category":"Gebouwenafwerking, Renovaties And Reiniging",
    "sg:phone":"+31 165 546 519",
    "sg:postcode":"4703 GD",
    "sg:province":"Noord-Brabant",
    "wof:name":"Kade Geveltechniek",
    "wof:placetype":"venue"
},
  "geometry": {"coordinates":[4.448185,51.533257],"type":"Point"}
}