{
  "type": "Feature",
  "properties": {
    "addr:full":"Dukaat 15 Emmeloord NL. 8305 BC",
    "addr:housenumber":"15",
    "addr:postcode":"8305 bc",
    "addr:street":"Dukaat;Nl.",
    "iso:country":"NL",
    "sg:address":"Dukaat 15",
    "sg:city":"Emmeloord",
    "sg:orig_category":"Elektrotechnische Installatiebureaus",
    "sg:phone":"+31 527 613 683",
    "sg:postcode":"8305 BC",
    "sg:province":"NL.",
    "wof:name":"Acm-Tcn Techniek Bv",
    "wof:placetype":"venue"
},
  "geometry": {"coordinates":[5.77832,52.716591],"type":"Point"}
}