{
  "type": "Feature",
  "properties": {
    "iso:country":"NL",
    "sg:address":"Cornelis Schuurmanhof 11",
    "sg:city":"Amsterdam",
    "sg:orig_category":"Boekhouders",
    "sg:phone":"+31 20 697 8528",
    "sg:postcode":"1106 WR",
    "sg:province":"Noord-Holland",
    "wof:name":"Herman Kluit Administratieburo",
    "wof:placetype":"venue"
},
  "geometry": {"coordinates":[4.992815,52.297543],"type":"Point"}
}