{
  "type": "Feature",
  "properties": {
    "addr:full":"De Hilde 34 Raalte NL.08 8102 KH",
    "addr:housenumber":"34;nl.08",
    "addr:postcode":"8102 kh",
    "addr:street":"De Hilde",
    "iso:country":"NL",
    "sg:address":"De Hilde 34",
    "sg:city":"Raalte",
    "sg:orig_category":"Verzekeringen",
    "sg:phone":"+31 572 354 179",
    "sg:postcode":"8102 KH",
    "sg:province":"NL.08",
    "wof:name":"Gerritsen Assurantien",
    "wof:placetype":"venue"
},
  "geometry": {"coordinates":[6.2661728859,52.372505188],"type":"Point"}
}