{
  "type": "Feature",
  "properties": {
    "addr:full":"Markerkant 1206/03 Almere NL. 1314 AK",
    "addr:housenumber":"1206 / 03",
    "addr:postcode":"1314 ak",
    "addr:street":"Markerkant;Nl.",
    "iso:country":"NL",
    "sg:address":"Markerkant 1206/03",
    "sg:city":"Almere",
    "sg:orig_category":"Glaszetten",
    "sg:phone":"+31 36 530 2839",
    "sg:postcode":"1314 AK",
    "sg:province":"NL.",
    "wof:name":"Garant Glas",
    "wof:placetype":"venue"
},
  "geometry": {"coordinates":[5.215593,52.386349],"type":"Point"}
}