{
  "type": "Feature",
  "properties": {
    "addr:full":"Achterdyken 84 Nes Ameland Friesland 9163 JV",
    "addr:housenumber":"84",
    "addr:postcode":"9163 jv",
    "addr:street":"Achterdyken",
    "iso:country":"NL",
    "sg:address":"Achterdyken 84",
    "sg:city":"Nes Ameland",
    "sg:classifiers":[
        {
            "category":"Taxi",
            "type":"Transportation"
        }
    ],
    "sg:phone":"+31 519 543 200",
    "sg:postcode":"9163 JV",
    "sg:province":"Friesland",
    "sg:tags":[
        "taxi's"
    ],
    "sg:website":"http://www.cosi-tax.com",
    "wof:name":"Cosi Taxi",
    "wof:placetype":"venue"
},
  "geometry": {"coordinates":[5.771521,53.440887],"type":"Point"}
}