{
  "type": "Feature",
  "properties": {
    "addr:full":"Handelskd 49 Ryswyk Zh Zuid-Holland 2288 BA",
    "addr:housenumber":"49",
    "addr:postcode":"2288 ba",
    "addr:street":"Handelskd",
    "iso:country":"NL",
    "sg:address":"Handelskd 49",
    "sg:city":"Ryswyk Zh",
    "sg:orig_category":"Omroep",
    "sg:phone":"+31 70 414 1375",
    "sg:postcode":"2288 BA",
    "sg:province":"Zuid-Holland",
    "sg:website":"http://www.anp.nl",
    "wof:name":"Anp Bv",
    "wof:placetype":"venue"
},
  "geometry": {"coordinates":[4.32436,52.037251],"type":"Point"}
}