{
  "type": "Feature",
  "properties": {
    "iso:country":"NL",
    "sg:address":"Heistraat 48",
    "sg:city":"Sittard",
    "sg:classifiers":[
        {
            "category":"Fast Food",
            "type":"Food & Drink"
        }
    ],
    "sg:phone":"+31 46 452 3235",
    "sg:postcode":"6136 BE",
    "sg:province":"Limburg",
    "sg:tags":[
        "afhaal",
        "restaurant"
    ],
    "wof:name":"Vof Friture Overhoven",
    "wof:placetype":"venue"
},
  "geometry": {"coordinates":[5.86636,51.009129],"type":"Point"}
}