{
  "type": "Feature",
  "properties": {
    "addr:full":"Schaapskooiwg 99 Heerlen Limburg 6414 EL",
    "addr:housenumber":"99",
    "addr:postcode":"6414 el",
    "addr:street":"Schaapskooiwg",
    "iso:country":"NL",
    "sg:address":"Schaapskooiwg 99",
    "sg:city":"Heerlen",
    "sg:orig_category":"Natuur- En Milieuorganisaties",
    "sg:phone":"+31 45 563 0355",
    "sg:postcode":"6414 EL",
    "sg:province":"Limburg",
    "wof:name":"Bezoekerscentr Brunssummerheide",
    "wof:placetype":"venue"
},
  "geometry": {"coordinates":[5.979675,50.923199],"type":"Point"}
}