{
  "type": "Feature",
  "properties": {
    "addr:full":"Meerstr 26 Emmen Provincie Drenthe 7815 XG",
    "addr:housenumber":"26",
    "addr:postcode":"7815 xg",
    "addr:street":"Meerstr;Provincie Drenthe",
    "iso:country":"NL",
    "sg:address":"Meerstr 26",
    "sg:city":"Emmen",
    "sg:classifiers":[
        {
            "category":"Farming",
            "subcategory":"Fish & Marine Products",
            "type":"Manufacturing & Wholesale Goods"
        }
    ],
    "sg:phone":"+31 591 641 441",
    "sg:postcode":"7815 XG",
    "sg:province":"Provincie Drenthe",
    "sg:tags":[
        "vi"
    ],
    "wof:name":"Lindeman Bv, Gebr",
    "wof:placetype":"venue"
},
  "geometry": {"coordinates":[6.893551,52.79324],"type":"Point"}
}