{
  "type": "Feature",
  "properties": {
    "addr:full":"Wolfsberg 20 Echt Carinthia 6102 RB",
    "addr:housenumber":"20",
    "addr:postcode":"6102 rb",
    "addr:street":"Wolfsberg",
    "iso:country":"NL",
    "sg:address":"Wolfsberg 20",
    "sg:city":"Echt",
    "sg:classifiers":[
        {
            "category":"Sports & Exercise",
            "subcategory":"Stables",
            "type":"Entertainment"
        }
    ],
    "sg:phone":"+31 475 484 117",
    "sg:postcode":"6102 RB",
    "sg:province":"Carinthia",
    "sg:tags":[
        "maneges"
    ],
    "wof:name":"Op De Berg, Manege",
    "wof:placetype":"venue"
},
  "geometry": {"coordinates":[14.84185,46.84021],"type":"Point"}
}