{
  "type": "Feature",
  "properties": {
    "addr:full":"Heyhoefpromenade 18 Tilburg Noord-Brabant 5043 RM",
    "addr:housenumber":"18",
    "addr:postcode":"5043 rm",
    "addr:street":"Heyhoefpromenade",
    "iso:country":"NL",
    "sg:address":"Heyhoefpromenade 18",
    "sg:city":"Tilburg",
    "sg:orig_category":"Opticiens",
    "sg:phone":"+31 13 571 3702",
    "sg:postcode":"5043 RM",
    "sg:province":"Noord-Brabant",
    "wof:name":"Oogmerk Opticien Ton Lips",
    "wof:placetype":"venue"
},
  "geometry": {"coordinates":[5.0063180923,51.5777549744],"type":"Point"}
}