{
  "type": "Feature",
  "properties": {
    "addr:full":"Noordwg 92 Pynacker South Holland 2641 ZB",
    "addr:housenumber":"92",
    "addr:postcode":"2641 zb",
    "addr:street":"Noordwg;Pynacker South",
    "iso:country":"NL",
    "sg:address":"Noordwg 92",
    "sg:city":"Pynacker",
    "sg:orig_category":"Bedrijfsmechanisatie En -Automatisering",
    "sg:phone":"+31 15 369 4346",
    "sg:postcode":"2641 ZB",
    "sg:province":"South Holland",
    "wof:name":"Sun Data Serv Bv",
    "wof:placetype":"venue"
},
  "geometry": {"coordinates":[4.425023,52.023746],"type":"Point"}
}