{
  "type": "Feature",
  "properties": {
    "addr:full":"Raadhuisstr 86 Waalre Noord-Brabant 5582 JG",
    "addr:housenumber":"86",
    "addr:postcode":"5582 jg",
    "addr:street":"Raadhuisstr",
    "iso:country":"NL",
    "sg:address":"Raadhuisstr 86",
    "sg:city":"Waalre",
    "sg:orig_category":"Beeldende Kunstenaars",
    "sg:phone":"+31 40 223 3881",
    "sg:postcode":"5582 JG",
    "sg:province":"Noord-Brabant",
    "wof:name":"Mibe",
    "wof:placetype":"venue"
},
  "geometry": {"coordinates":[5.468005,51.393532],"type":"Point"}
}