{
  "type": "Feature",
  "properties": {
    "addr:full":"Rottebandreef 40 Bergschenhoek Zuid-Holland 2661 JK",
    "addr:housenumber":"40",
    "addr:postcode":"2661 jk",
    "addr:street":"Rottebandreef",
    "iso:country":"NL",
    "sg:address":"Rottebandreef 40",
    "sg:city":"Bergschenhoek",
    "sg:orig_category":"Golfbanen",
    "sg:phone":"+31 10 522 0052",
    "sg:postcode":"2661 JK",
    "sg:province":"Zuid-Holland",
    "sg:website":"http://www.rottebergen.nl",
    "wof:name":"Rottebergen, De",
    "wof:placetype":"venue"
},
  "geometry": {"coordinates":[4.5307,51.969818],"type":"Point"}
}