{
  "type": "Feature",
  "properties": {
    "addr:full":"Plutoln 82 Bilthoven Utrecht 3721 MS",
    "addr:housenumber":"82",
    "addr:postcode":"3721 ms",
    "addr:street":"Plutoln",
    "iso:country":"NL",
    "sg:address":"Plutoln 82",
    "sg:city":"Bilthoven",
    "sg:orig_category":"Fotoreportages",
    "sg:phone":"+31 30 225 4002",
    "sg:postcode":"3721 MS",
    "sg:province":"Utrecht",
    "wof:name":"Elswijk, Yolanda Van",
    "wof:placetype":"venue"
},
  "geometry": {"coordinates":[5.18986,52.12133],"type":"Point"}
}