{
  "type": "Feature",
  "properties": {
    "addr:full":"Boterdiep Wz 21 Zuidwolde Gn Groningen 9785 AK",
    "addr:housenumber":"21",
    "addr:postcode":"gn;9785 ak",
    "addr:street":"Boterdiep Wz",
    "iso:country":"NL",
    "sg:address":"Boterdiep Wz 21",
    "sg:city":"Zuidwolde Gn",
    "sg:orig_category":"Makelaars En Adviseurs Onroerende Goederen",
    "sg:phone":"+31 50 301 0416",
    "sg:postcode":"9785 AK",
    "sg:province":"Groningen",
    "wof:name":"Wijnstra Vastgoed",
    "wof:placetype":"venue"
},
  "geometry": {"coordinates":[6.594972,53.263512],"type":"Point"}
}