{
  "type": "Feature",
  "properties": {
    "addr:full":"Rading 16 Loosdrecht North Holland 1231 KA",
    "addr:housenumber":"16",
    "addr:postcode":"1231 ka",
    "addr:street":"Rading",
    "iso:country":"NL",
    "sg:address":"Rading 16",
    "sg:city":"Loosdrecht",
    "sg:orig_category":"Film-, Tv- And Videoproductie",
    "sg:phone":"+31 35 582 7464",
    "sg:postcode":"1231 KA",
    "sg:province":"North Holland",
    "wof:name":"Leo Steetskamp Av-Produkties",
    "wof:placetype":"venue"
},
  "geometry": {"coordinates":[5.139695,52.207802],"type":"Point"}
}