{
  "type": "Feature",
  "properties": {
    "addr:full":"Stougjesdijk 123 Mijnsheerenland Zuid-Holland 3271 KB",
    "addr:housenumber":"123",
    "addr:postcode":"3271 kb",
    "addr:street":"Stougjesdijk",
    "iso:country":"NL",
    "sg:address":"Stougjesdijk 123",
    "sg:city":"Mijnsheerenland",
    "sg:orig_category":"Verhuur Audiovisuele Apparatuur",
    "sg:phone":"+31 186 612 385",
    "sg:postcode":"3271 KB",
    "sg:province":"Zuid-Holland",
    "wof:name":"Pass Professional Audio Service Stougjes",
    "wof:placetype":"venue"
},
  "geometry": {"coordinates":[4.435845,51.801125],"type":"Point"}
}