{
  "type": "Feature",
  "properties": {
    "addr:full":"Veurhuis 26 Blaricum North Holland 1261 KN",
    "addr:housenumber":"26",
    "addr:postcode":"1261 kn",
    "addr:street":"Veurhuis",
    "iso:country":"NL",
    "sg:address":"Veurhuis 26",
    "sg:city":"Blaricum",
    "sg:orig_category":"Boekhouders",
    "sg:phone":"+31 35 525 8584",
    "sg:postcode":"1261 KN",
    "sg:province":"North Holland",
    "wof:name":"Administratiekantoor C. Schouten",
    "wof:placetype":"venue"
},
  "geometry": {"coordinates":[5.262823,52.285984],"type":"Point"}
}