{
  "type": "Feature",
  "properties": {
    "iso:country":"NL",
    "sg:address":"Boschstr 57",
    "sg:city":"Breda",
    "sg:orig_category":"Bejaarden - Verzorgingstehuizen",
    "sg:phone":"+31 76 522 5150",
    "sg:postcode":"4811 GC",
    "sg:province":"North Brabant",
    "wof:name":"Raffy",
    "wof:placetype":"venue"
},
  "geometry": {"coordinates":[4.782637,51.590611],"type":"Point"}
}