{
  "type": "Feature",
  "properties": {
    "iso:country":"NL",
    "sg:address":"T De Smethstr 18",
    "sg:city":"Deurne",
    "sg:orig_category":"Kappers",
    "sg:phone":"+31 493 320 502",
    "sg:postcode":"5751 MT",
    "sg:province":"Noord-Brabant",
    "wof:name":"Seccelen, C G G Van",
    "wof:placetype":"venue"
},
  "geometry": {"coordinates":[5.793792,51.470264],"type":"Point"}
}