{
  "type": "Feature",
  "properties": {
    "addr:full":"Kerkwg 4 Gellicum Gelderland 4155 BD",
    "addr:housenumber":"4",
    "addr:postcode":"4155 bd",
    "addr:street":"Kerkwg;Gelderland",
    "iso:country":"NL",
    "sg:address":"Kerkwg 4",
    "sg:city":"Gellicum",
    "sg:orig_category":"Bedrijfsopleidingen",
    "sg:phone":"+31 345 682 682",
    "sg:postcode":"4155 BD",
    "sg:province":"Gelderland",
    "sg:website":"http://www.horden.nl",
    "wof:name":"Horden, Bur Kees",
    "wof:placetype":"venue"
},
  "geometry": {"coordinates":[5.155419,51.877132],"type":"Point"}
}