{
  "type": "Feature",
  "properties": {
    "addr:full":"Wolfswinkelwg 15 Amsterdam Noord-Holland 1035 TH",
    "addr:housenumber":"15",
    "addr:postcode":"1035 th",
    "addr:street":"Wolfswinkelwg",
    "iso:country":"NL",
    "sg:address":"Wolfswinkelwg 15",
    "sg:city":"Amsterdam",
    "sg:orig_category":"Koeriersdiensten",
    "sg:phone":"+31 6 54251469",
    "sg:postcode":"1035 TH",
    "sg:province":"Noord-Holland",
    "wof:name":"Miedema, B",
    "wof:placetype":"venue"
},
  "geometry": {"coordinates":[4.901324,52.422527],"type":"Point"}
}