{
  "type": "Feature",
  "properties": {
    "iso:country":"NL",
    "sg:address":"Abcovensewg 23A",
    "sg:city":"Goirle",
    "sg:orig_category":"Antiquiteiten",
    "sg:phone":"+31 13 534 3688",
    "sg:postcode":"5051 PT",
    "sg:province":"Noord-Brabant",
    "wof:name":"Amorini Antiek & Curiosa",
    "wof:placetype":"venue"
},
  "geometry": {"coordinates":[5.076984,51.522083],"type":"Point"}
}