{
  "type": "Feature",
  "properties": {
    "addr:full":"Abcovensewg 23A Goirle Noord-Brabant 5051 PT",
    "addr:housenumber":"23a",
    "addr:postcode":"5051 pt",
    "addr:street":"Abcovensewg",
    "iso:country":"NL",
    "sg:address":"Abcovensewg 23A",
    "sg:city":"Goirle",
    "sg:orig_category":"Antiquiteiten",
    "sg:phone":"+31 13 534 3688",
    "sg:postcode":"5051 PT",
    "sg:province":"Noord-Brabant",
    "wof:name":"Amorini Antiek & Curiosa",
    "wof:placetype":"venue"
},
  "geometry": {"coordinates":[5.076984,51.522083],"type":"Point"}
}