{
  "type": "Feature",
  "properties": {
    "addr:full":"Sumatrakd 1349 Amsterdam North Holland 1019 RN",
    "addr:housenumber":"1349",
    "addr:postcode":"1019 rn",
    "iso:country":"NL",
    "sg:address":"Sumatrakd 1349",
    "sg:city":"Amsterdam",
    "sg:orig_category":"Organisatiebureaus",
    "sg:phone":"+31 20 419 3462",
    "sg:postcode":"1019 RN",
    "sg:province":"North Holland",
    "wof:name":"Magma Co\u00f7P Ua",
    "wof:placetype":"venue"
},
  "geometry": {"coordinates":[4.9247341156,52.3796234131],"type":"Point"}
}