{
  "type": "Feature",
  "properties": {
    "addr:full":"Wollegrasstraat 2 Westerhaar Vriezenv W Overijssel 7676 BP",
    "addr:housenumber":"2",
    "addr:postcode":"7676 bp",
    "addr:street":"Wollegrasstraat;W",
    "iso:country":"NL",
    "sg:address":"Wollegrasstraat 2",
    "sg:city":"Westerhaar Vriezenv W",
    "sg:orig_category":"Banken And Kredietinstellingen",
    "sg:phone":"+31 548 631 111",
    "sg:postcode":"7676 BP",
    "sg:province":"Overijssel",
    "wof:name":"Rabobank",
    "wof:placetype":"venue"
},
  "geometry": {"coordinates":[6.619259,52.461456],"type":"Point"}
}