{
  "type": "Feature",
  "properties": {
    "iso:country":"NL",
    "sg:address":"Akkerwinde 3",
    "sg:city":"Waddinxveen",
    "sg:orig_category":"Diverse Grafische Activiteiten",
    "sg:phone":"+31 182 610 782",
    "sg:postcode":"2742 DS",
    "sg:province":"South Holland",
    "wof:name":"Buro Graphicstation (3D. Applicaties)",
    "wof:placetype":"venue"
},
  "geometry": {"coordinates":[4.644154,52.051205],"type":"Point"}
}