{
  "type": "Feature",
  "properties": {
    "addr:full":"Breemhorstsedijk 4 De Mortel Noord-Brabant 5425 XR",
    "addr:housenumber":"4",
    "addr:postcode":"5425 xr",
    "addr:street":"Breemhorstsedijk",
    "iso:country":"NL",
    "sg:address":"Breemhorstsedijk 4",
    "sg:city":"De Mortel",
    "sg:orig_category":"Loodgieterswerk, Verwarming And Sanitaire Installaties",
    "sg:phone":"+31 492 364 097",
    "sg:postcode":"5425 XR",
    "sg:province":"Noord-Brabant",
    "wof:name":"Van De Boomen Machinaal Timmerbedrijf",
    "wof:placetype":"venue"
},
  "geometry": {"coordinates":[5.718461,51.549824],"type":"Point"}
}