{
  "type": "Feature",
  "properties": {
    "iso:country":"NL",
    "sg:address":"Oedsmawei 24",
    "sg:city":"Grouw",
    "sg:orig_category":"Bierbrouwerijen",
    "sg:phone":"+31 566 625 555",
    "sg:postcode":"9001 ZJ",
    "sg:province":"Friesland",
    "wof:name":"Heineken Friesland",
    "wof:placetype":"venue"
},
  "geometry": {"coordinates":[5.824729,53.093716],"type":"Point"}
}