{
  "type": "Feature",
  "properties": {
    "addr:full":"Kleasterdk 16 Winsum Fr Provincie Friesland 8831 XB",
    "addr:housenumber":"16",
    "addr:postcode":"8831 xb",
    "addr:street":"Kleasterdk;Friesland",
    "iso:country":"NL",
    "sg:address":"Kleasterdk 16",
    "sg:city":"Winsum Fr",
    "sg:orig_category":"Kappers",
    "sg:phone":"+31 517 341 633",
    "sg:postcode":"8831 XB",
    "sg:province":"Provincie Friesland",
    "wof:name":"Sjoeke",
    "wof:placetype":"venue"
},
  "geometry": {"coordinates":[5.629913,53.154137],"type":"Point"}
}