{
  "type": "Feature",
  "properties": {
    "iso:country":"NL",
    "sg:address":"Oslowg 39",
    "sg:city":"Groningen",
    "sg:orig_category":"Keukens",
    "sg:phone":"+31 50 312 4492",
    "sg:postcode":"9723 BG",
    "sg:province":"Groningen",
    "wof:name":"Oudman",
    "wof:placetype":"venue"
},
  "geometry": {"coordinates":[6.595356,53.211796],"type":"Point"}
}