{
  "type": "Feature",
  "properties": {
    "addr:full":"H Boschstr 2 Hazerswoude Dorp Zuid-Holland 2391 VA",
    "addr:housenumber":"2",
    "addr:postcode":"2391",
    "addr:street":"Hazerswoude",
    "iso:country":"NL",
    "sg:address":"H Boschstr 2",
    "sg:city":"Hazerswoude Dorp",
    "sg:orig_category":"Podotherapeuten",
    "sg:phone":"+31 172 587 103",
    "sg:postcode":"2391 VA",
    "sg:province":"Zuid-Holland",
    "wof:name":"Wieringen, M Van",
    "wof:placetype":"venue"
},
  "geometry": {"coordinates":[4.59104,52.097099],"type":"Point"}
}