{
  "type": "Feature",
  "properties": {
    "addr:full":"Hoofdstraat 96 Exloo Provincie Drenthe 7875 AE",
    "addr:housenumber":"96",
    "addr:postcode":"7875 ae",
    "addr:street":"Hoofdstraat;Provincie Drenthe",
    "iso:country":"NL",
    "sg:address":"Hoofdstraat 96",
    "sg:city":"Exloo",
    "sg:classifiers":[
        {
            "category":"Travel",
            "subcategory":"Hotels & Motels",
            "type":"Entertainment"
        }
    ],
    "sg:phone":"+31 591 549 030",
    "sg:postcode":"7875 AE",
    "sg:province":"Provincie Drenthe",
    "wof:name":"Hotel Restaurant De Schoap'N Drift",
    "wof:placetype":"venue"
},
  "geometry": {"coordinates":[6.854836,52.883362],"type":"Point"}
}