{
  "type": "Feature",
  "properties": {
    "addr:full":"Vierhuisterweg 20 Leeuwarden Provincie Friesland 8919 AJ",
    "addr:housenumber":"20",
    "addr:postcode":"8919 aj",
    "addr:street":"Vierhuisterweg;Provincie Friesland",
    "iso:country":"NL",
    "sg:address":"Vierhuisterweg 20",
    "sg:city":"Leeuwarden",
    "sg:orig_category":"Zuivelproducten",
    "sg:phone":"+31 58 266 3998",
    "sg:postcode":"8919 AJ",
    "sg:province":"Provincie Friesland",
    "wof:name":"Zuivelhandel H. En J. Van Der Veen",
    "wof:placetype":"venue"
},
  "geometry": {"coordinates":[5.783141,53.220341],"type":"Point"}
}