{
  "type": "Feature",
  "properties": {
    "addr:full":"Paltz 17 Beilen Drenthe 9411 PM",
    "addr:housenumber":"17",
    "addr:postcode":"9411 pm",
    "addr:street":"Paltz",
    "iso:country":"NL",
    "sg:address":"Paltz 17",
    "sg:city":"Beilen",
    "sg:orig_category":"Glaszetten",
    "sg:phone":"+31 593 525 112",
    "sg:postcode":"9411 PM",
    "sg:province":"Drenthe",
    "wof:name":"F.B.S. Schilderwerken",
    "wof:placetype":"venue"
},
  "geometry": {"coordinates":[6.521901,52.857204],"type":"Point"}
}