{
  "type": "Feature",
  "properties": {
    "addr:full":"Maastrichterlaan 90 Vaals Limburg 6291 ET",
    "addr:housenumber":"90",
    "addr:postcode":"6291 et",
    "addr:street":"Maastrichterlaan",
    "iso:country":"NL",
    "sg:address":"Maastrichterlaan 90",
    "sg:city":"Vaals",
    "sg:classifiers":[
        {
            "category":"Retail",
            "subcategory":"Photofinishing",
            "type":"Services"
        }
    ],
    "sg:phone":"+31 43 306 3331",
    "sg:postcode":"6291 ET",
    "sg:province":"Limburg",
    "sg:tags":[
        "foto",
        "film"
    ],
    "wof:name":"Foto Kaldenbach",
    "wof:placetype":"venue"
},
  "geometry": {"coordinates":[6.017575,50.772915],"type":"Point"}
}