{
  "type": "Feature",
  "properties": {
    "addr:full":"Westeindsewg 15A Zoeterwoude Zuid-Holland 2381 EB",
    "addr:housenumber":"15a",
    "addr:postcode":"2381 eb",
    "addr:street":"Westeindsewg",
    "iso:country":"NL",
    "sg:address":"Westeindsewg 15A",
    "sg:city":"Zoeterwoude",
    "sg:classifiers":[
        {
            "category":"Cinema",
            "subcategory":"Drive-in Theater",
            "type":"Entertainment"
        }
    ],
    "sg:phone":"+31 71 580 3183",
    "sg:postcode":"2381 EB",
    "sg:province":"Zuid-Holland",
    "sg:tags":[
        "drive-in-shows"
    ],
    "sg:website":"http://www.exodus-disco.nl",
    "wof:name":"Exodus",
    "wof:placetype":"venue"
},
  "geometry": {"coordinates":[4.483817,52.113617],"type":"Point"}
}