{
  "type": "Feature",
  "properties": {
    "addr:full":"T Holland 11 Duiven Gelderland 6921 GX",
    "addr:housenumber":"11",
    "addr:postcode":"6921 gx",
    "addr:street":"T Holland;Gelderland",
    "iso:country":"NL",
    "sg:address":"T Holland 11",
    "sg:city":"Duiven",
    "sg:orig_category":"Wegen And Sportterreinen",
    "sg:phone":"+31 316 261 944",
    "sg:postcode":"6921 GX",
    "sg:province":"Gelderland",
    "wof:name":"De Liemers Wegenbouw Bv",
    "wof:placetype":"venue"
},
  "geometry": {"coordinates":[6.026143074,51.9422950745],"type":"Point"}
}