{
  "type": "Feature",
  "properties": {
    "addr:full":"Herengracht 446 1017 Noord-Holland AMST ER",
    "addr:housenumber":"446",
    "addr:postcode":"1017",
    "addr:street":"Herengracht",
    "iso:country":"NL",
    "sg:address":"Herengracht 446",
    "sg:city":"1017",
    "sg:classifiers":[
        {
            "category":"Banks & Credit Unions",
            "subcategory":"Bank",
            "type":"Services"
        }
    ],
    "sg:phone":"+31 20 521 6100",
    "sg:postcode":"AMST ER",
    "sg:province":"Noord-Holland",
    "wof:name":"Istituto Bancario, San Paolo Di Torino Spa",
    "wof:placetype":"venue"
},
  "geometry": {"coordinates":[4.889011,52.365967],"type":"Point"}
}