{
  "type": "Feature",
  "properties": {
    "addr:full":"Postjesweg 95 Amsterdam Noord-Holland 1057 DZ",
    "addr:housenumber":"95",
    "addr:postcode":"1057 dz",
    "addr:street":"Postjesweg",
    "iso:country":"NL",
    "sg:address":"Postjesweg 95",
    "sg:city":"Amsterdam",
    "sg:orig_category":"Zuivelproducten",
    "sg:phone":"+31 20 612 4457",
    "sg:postcode":"1057 DZ",
    "sg:province":"Noord-Holland",
    "wof:name":"De Kaashut",
    "wof:placetype":"venue"
},
  "geometry": {"coordinates":[4.853884,52.364117],"type":"Point"}
}