{
  "type": "Feature",
  "properties": {
    "addr:full":"Stadhouderstraat 5 Dordrecht Zuid-Holland 3319 RM",
    "addr:housenumber":"5",
    "addr:postcode":"3319 rm",
    "addr:street":"Stadhouderstraat",
    "iso:country":"NL",
    "sg:address":"Stadhouderstraat 5",
    "sg:city":"Dordrecht",
    "sg:orig_category":"Technische Studies And Onderzoek",
    "sg:phone":"+31 78 621 5056",
    "sg:postcode":"3319 RM",
    "sg:province":"Zuid-Holland",
    "wof:name":"Kruidhof Engineering Project Service",
    "wof:placetype":"venue"
},
  "geometry": {"coordinates":[4.695784,51.79697],"type":"Point"}
}