{
  "type": "Feature",
  "properties": {
    "addr:full":"Kerkwg 221B Heemskerk Noord-Holland 1964 KJ",
    "addr:housenumber":"221b",
    "addr:postcode":"1964 kj",
    "iso:country":"NL",
    "sg:address":"Kerkwg 221B",
    "sg:city":"Heemskerk",
    "sg:classifiers":[
        {
            "category":"Sports & Exercise",
            "subcategory":"Stables",
            "type":"Entertainment"
        }
    ],
    "sg:phone":"+31 251 231 164",
    "sg:postcode":"1964 KJ",
    "sg:province":"Noord-Holland",
    "sg:tags":[
        "maneges"
    ],
    "sg:website":"http://www.schimmelkroft.nl",
    "wof:name":"Schimmelkroft",
    "wof:placetype":"venue"
},
  "geometry": {"coordinates":[4.658726,52.515247],"type":"Point"}
}