{
  "type": "Feature",
  "properties": {
    "addr:full":"Johannes Vijghstraat 41 Nijmegen Gelderland 6524 BP",
    "addr:housenumber":"41",
    "addr:postcode":"6524 bp",
    "addr:street":"Johannes Vijghstraat;Gelderland",
    "iso:country":"NL",
    "sg:address":"Johannes Vijghstraat 41",
    "sg:city":"Nijmegen",
    "sg:orig_category":"Gespecialiseerde Voeding",
    "sg:phone":"+31 24 360 5116",
    "sg:postcode":"6524 BP",
    "sg:province":"Gelderland",
    "wof:name":"Demir Market Vof",
    "wof:placetype":"venue"
},
  "geometry": {"coordinates":[5.865821,51.839207],"type":"Point"}
}