{
  "type": "Feature",
  "properties": {
    "addr:full":"Kerkstraat 5 Tiel Gelderland 4001 MA",
    "addr:housenumber":"5",
    "addr:postcode":"4001 ma",
    "addr:street":"Kerkstraat;Gelderland",
    "iso:country":"NL",
    "sg:address":"Kerkstraat 5",
    "sg:city":"Tiel",
    "sg:orig_category":"Schoenen",
    "sg:phone":"+31 344 632 201",
    "sg:postcode":"4001 MA",
    "sg:province":"Gelderland",
    "wof:name":"By Zoe",
    "wof:placetype":"venue"
},
  "geometry": {"coordinates":[5.430696,51.888096],"type":"Point"}
}