{
  "type": "Feature",
  "properties": {
    "addr:full":"Badwg 9 De Koog Noord-Holland 1796 AA",
    "addr:housenumber":"9",
    "addr:postcode":"1796 aa",
    "addr:street":"Badwg",
    "iso:country":"NL",
    "sg:address":"Badwg 9",
    "sg:city":"De Koog",
    "sg:orig_category":"Badmode",
    "sg:phone":"+31 222 317 630",
    "sg:postcode":"1796 AA",
    "sg:province":"Noord-Holland",
    "wof:name":"Badweg",
    "wof:placetype":"venue"
},
  "geometry": {"coordinates":[4.762141,53.100098],"type":"Point"}
}