{
  "type": "Feature",
  "properties": {
    "addr:full":"Haaksbergerstraat 6-8 Diepenheim Overijssel 7478 AW",
    "addr:housenumber":"6-8",
    "addr:postcode":"7478 aw",
    "addr:street":"Haaksbergerstraat",
    "iso:country":"NL",
    "sg:address":"Haaksbergerstraat 6-8",
    "sg:city":"Diepenheim",
    "sg:orig_category":"Banken And Kredietinstellingen",
    "sg:phone":"+31 547 352 414",
    "sg:postcode":"7478 AW",
    "sg:province":"Overijssel",
    "wof:name":"Postkantoor",
    "wof:placetype":"venue"
},
  "geometry": {"coordinates":[6.554562,52.198997],"type":"Point"}
}