{
  "type": "Feature",
  "properties": {
    "iso:country":"NL",
    "sg:address":"Dorpsstraat 168",
    "sg:city":"Mierlo",
    "sg:orig_category":"Voeding, Dranken And Tabak Gh",
    "sg:phone":"+31 492 662 115",
    "sg:postcode":"5731 JL",
    "sg:province":"North Brabant",
    "wof:name":"Kerstpakketcentrale Harry Prick Bv",
    "wof:placetype":"venue"
},
  "geometry": {"coordinates":[5.619001,51.443279],"type":"Point"}
}