{
  "type": "Feature",
  "properties": {
    "addr:full":"Oostervalge 42 Warffum Groningen 9989 EK",
    "addr:housenumber":"42",
    "addr:postcode":"9989 ek",
    "addr:street":"Oostervalge",
    "iso:country":"NL",
    "sg:address":"Oostervalge 42",
    "sg:city":"Warffum",
    "sg:orig_category":"Kappers",
    "sg:phone":"+31 595 424 421",
    "sg:postcode":"9989 EK",
    "sg:province":"Groningen",
    "wof:name":"Op & Top",
    "wof:placetype":"venue"
},
  "geometry": {"coordinates":[6.56442,53.396992],"type":"Point"}
}