{
  "type": "Feature",
  "properties": {
    "iso:country":"NL",
    "sg:address":"Geerwg 5",
    "sg:city":"Zoeterwoude",
    "sg:orig_category":"Kaas",
    "sg:phone":"+31 71 580 1415",
    "sg:postcode":"2381 LT",
    "sg:province":"South Holland",
    "wof:name":"Vierhuizen, De",
    "wof:placetype":"venue"
},
  "geometry": {"coordinates":[4.4918708801,52.097743988],"type":"Point"}
}