{
  "type": "Feature",
  "properties": {
    "addr:full":"Braamgaarde 9 Nieuwegein Utrecht 3436 GL",
    "addr:housenumber":"9",
    "addr:postcode":"3436 gl",
    "addr:street":"Braamgaarde",
    "iso:country":"NL",
    "sg:address":"Braamgaarde 9",
    "sg:city":"Nieuwegein",
    "sg:orig_category":"Adviesbureaus Automatisering",
    "sg:phone":"+31 30 604 7217",
    "sg:postcode":"3436 GL",
    "sg:province":"Utrecht",
    "wof:name":"Zaccai",
    "wof:placetype":"venue"
},
  "geometry": {"coordinates":[5.071145,52.03418],"type":"Point"}
}