{
  "type": "Feature",
  "properties": {
    "iso:country":"NL",
    "sg:address":"Haarlemmerstraat 165",
    "sg:city":"Leiden",
    "sg:orig_category":"Verlichting And Huishoudartikelen",
    "sg:phone":"+31 71 514 0892",
    "sg:postcode":"2312 DP",
    "sg:province":"South Holland",
    "wof:name":"Oudshoorn Leiden Bv",
    "wof:placetype":"venue"
},
  "geometry": {"coordinates":[4.493459,52.160114],"type":"Point"}
}