{
  "type": "Feature",
  "properties": {
    "addr:full":"Kampervest 3 Haarlem North Holland 2011 EW",
    "addr:housenumber":"3",
    "addr:postcode":"2011 ew",
    "addr:street":"Kampervest",
    "iso:country":"NL",
    "sg:address":"Kampervest 3",
    "sg:city":"Haarlem",
    "sg:orig_category":"Makelaars In Onroerend Goed",
    "sg:phone":"+31 23 534 3433",
    "sg:postcode":"2011 EW",
    "sg:province":"North Holland",
    "wof:name":"Direkt Wonen Zuid Bv",
    "wof:placetype":"venue"
},
  "geometry": {"coordinates":[4.635579,52.376198],"type":"Point"}
}