{
  "type": "Feature",
  "properties": {
    "addr:full":"Gasthuisstraat 58 Oirschot Noord-Brabant 5688 AX",
    "addr:housenumber":"58",
    "addr:postcode":"5688 ax",
    "addr:street":"Gasthuisstraat",
    "iso:country":"NL",
    "sg:address":"Gasthuisstraat 58",
    "sg:city":"Oirschot",
    "sg:orig_category":"Discountwinkels",
    "sg:phone":"+31 499 571 208",
    "sg:postcode":"5688 AX",
    "sg:province":"Noord-Brabant",
    "wof:name":"Hems Kinderstoffen",
    "wof:placetype":"venue"
},
  "geometry": {"coordinates":[5.306273,51.505753],"type":"Point"}
}