{
  "type": "Feature",
  "properties": {
    "addr:full":"Reigerstr 19 Zierikzee Zeeland 4302 XA",
    "addr:housenumber":"19",
    "addr:postcode":"4302 xa",
    "addr:street":"Reigerstr",
    "iso:country":"NL",
    "sg:address":"Reigerstr 19",
    "sg:city":"Zierikzee",
    "sg:orig_category":"Adviesbureaus Bedrijfsorganisatie",
    "sg:phone":"+31 111 411 473",
    "sg:postcode":"4302 XA",
    "sg:province":"Zeeland",
    "wof:name":"Linse, Management Consultancy",
    "wof:placetype":"venue"
},
  "geometry": {"coordinates":[3.90212,51.643269],"type":"Point"}
}