{
  "type": "Feature",
  "properties": {
    "addr:full":"Spoorsngl 31B Rotterdam South Holland 3033 GE",
    "addr:housenumber":"31b",
    "addr:postcode":"3033",
    "addr:street":"Spoorsngl",
    "iso:country":"NL",
    "sg:address":"Spoorsngl 31B",
    "sg:city":"Rotterdam",
    "sg:orig_category":"Verenigingen En Stichtingen",
    "sg:phone":"+31 10 466 4991",
    "sg:postcode":"3033 GE",
    "sg:province":"South Holland",
    "wof:name":"Islamitisch Onderzoek Onderwijs & Cult, Sticht",
    "wof:placetype":"venue"
},
  "geometry": {"coordinates":[4.46912,51.927521],"type":"Point"}
}