{
  "type": "Feature",
  "properties": {
    "iso:country":"NL",
    "sg:address":"Kruiszwin 5107",
    "sg:city":"Den Helder",
    "sg:orig_category":"Glazenwasserijen",
    "sg:phone":"+31 223 643 753",
    "sg:postcode":"1788 RR",
    "sg:province":"Noord-Brabant",
    "wof:name":"Perplex",
    "wof:placetype":"venue"
},
  "geometry": {"coordinates":[4.740922,52.888451],"type":"Point"}
}