{
  "type": "Feature",
  "properties": {
    "addr:full":"Ristereind 8 Oosterhout Nb Noord-Brabant 4904 VM",
    "addr:housenumber":"8",
    "addr:postcode":"4904 vm",
    "addr:street":"Ristereind",
    "iso:country":"NL",
    "sg:address":"Ristereind 8",
    "sg:city":"Oosterhout Nb",
    "sg:orig_category":"Adviesbureaus Bedrijfsorganisatie",
    "sg:phone":"+31 6 21541820",
    "sg:postcode":"4904 VM",
    "sg:province":"Noord-Brabant",
    "wof:name":"Boer, R J C Den",
    "wof:placetype":"venue"
},
  "geometry": {"coordinates":[4.835819,51.641335],"type":"Point"}
}