{
  "type": "Feature",
  "properties": {
    "addr:full":"Akerstr 9A Brunssum Limburg 6445 CL",
    "addr:housenumber":"9a",
    "addr:postcode":"6445",
    "addr:street":"Akerstr",
    "iso:country":"NL",
    "sg:address":"Akerstr 9A",
    "sg:city":"Brunssum",
    "sg:orig_category":"Kappers",
    "sg:phone":"+31 45 564 1645",
    "sg:postcode":"6445 CL",
    "sg:province":"Limburg",
    "sg:website":"http://www.imagehairstyle.nl",
    "wof:name":"Image",
    "wof:placetype":"venue"
},
  "geometry": {"coordinates":[5.9736461639,50.9352111816],"type":"Point"}
}