{
  "type": "Feature",
  "properties": {
    "iso:country":"NL",
    "sg:address":"Strandweg 65",
    "sg:city":"Buren Fr",
    "sg:orig_category":"Kampeerterreinen",
    "sg:phone":"+31 519 542 389",
    "sg:postcode":"9164 KA",
    "sg:province":"Provincie Friesland",
    "wof:name":"Camping De Kiekduun",
    "wof:placetype":"venue"
},
  "geometry": {"coordinates":[5.8023481369,53.453338623],"type":"Point"}
}