{
  "type": "Feature",
  "properties": {
    "addr:full":"Zeewg 45-47 Castricum Noord-Holland 1901 NZ",
    "addr:housenumber":"45-47",
    "addr:postcode":"1901 nz",
    "iso:country":"NL",
    "sg:address":"Zeewg 45-47",
    "sg:city":"Castricum",
    "sg:orig_category":"Zalenverhuur",
    "sg:phone":"+31 251 651 333",
    "sg:postcode":"1901 NZ",
    "sg:province":"Noord-Holland",
    "wof:name":"Stranderey, De",
    "wof:placetype":"venue"
},
  "geometry": {"coordinates":[4.627728,52.560318],"type":"Point"}
}