{
  "type": "Feature",
  "properties": {
    "iso:country":"NL",
    "sg:address":"P Gabrielstr 3",
    "sg:city":"Deurne",
    "sg:orig_category":"Oldtimers",
    "sg:phone":"+31 493 321 222",
    "sg:postcode":"5753 DG",
    "sg:province":"Noord-Brabant",
    "wof:name":"Martens Autoparts",
    "wof:placetype":"venue"
},
  "geometry": {"coordinates":[5.7938718796,51.4533348083],"type":"Point"}
}