{
  "type": "Feature",
  "properties": {
    "iso:country":"NL",
    "sg:address":"Rooijsestraat 50",
    "sg:city":"Dreumel",
    "sg:orig_category":"Kantoorartikelen",
    "sg:phone":"+31 487 571 260",
    "sg:postcode":"6621 AN",
    "sg:province":"Gelderland",
    "wof:name":"Rook- En Kantoorshop Jos Van Lith",
    "wof:placetype":"venue"
},
  "geometry": {"coordinates":[5.4309120178,51.8481521606],"type":"Point"}
}