{
  "type": "Feature",
  "properties": {
    "addr:full":"Tupolevlaan 42 Schiphol-Rijk Noord-Holland 1119 NZ",
    "addr:housenumber":"42",
    "addr:postcode":"1119 nz",
    "addr:street":"Tupolevlaan",
    "iso:country":"NL",
    "sg:address":"Tupolevlaan 42",
    "sg:city":"Schiphol-Rijk",
    "sg:orig_category":"Goederenvervoer Over De Weg",
    "sg:phone":"+31 20 653 0599",
    "sg:postcode":"1119 NZ",
    "sg:province":"Noord-Holland",
    "wof:name":"Interport Bv",
    "wof:placetype":"venue"
},
  "geometry": {"coordinates":[4.757205,52.281868],"type":"Point"}
}