{
  "type": "Feature",
  "properties": {
    "addr:full":"Oude Hollewg 14 Berg En Dal Gelderland 6572 AB",
    "addr:housenumber":"14",
    "addr:postcode":"6572 ab",
    "addr:street":"Oude Hollewg",
    "iso:country":"NL",
    "sg:address":"Oude Hollewg 14",
    "sg:city":"Berg En Dal",
    "sg:orig_category":"Adviesbureaus Bedrijfsorganisatie",
    "sg:phone":"+31 24 684 2979",
    "sg:postcode":"6572 AB",
    "sg:province":"Gelderland",
    "sg:website":"http://www.esmeijer-log.nl",
    "wof:name":"Esmeijer Logistiek Adviesbureau Bv",
    "wof:placetype":"venue"
},
  "geometry": {"coordinates":[5.914579,51.824768],"type":"Point"}
}