{
  "type": "Feature",
  "properties": {
    "iso:country":"NL",
    "sg:address":"Heerewg 114",
    "sg:city":"Castricum",
    "sg:orig_category":"Kinderhuizen",
    "sg:phone":"+31 251 659 016",
    "sg:postcode":"1901 ME",
    "sg:province":"Noord-Holland",
    "wof:name":"Antonius Medisch Kinderhuis",
    "wof:placetype":"venue"
},
  "geometry": {"coordinates":[4.654927,52.573994],"type":"Point"}
}