{
  "type": "Feature",
  "properties": {
    "addr:full":"Jadeln 37-41 Hoofddorp Noord-Holland 2132 XX",
    "addr:housenumber":"37-41",
    "addr:postcode":"hoofddorp;2132 xx",
    "iso:country":"NL",
    "sg:address":"Jadeln 37-41",
    "sg:city":"Hoofddorp",
    "sg:orig_category":"Product-Promotie",
    "sg:phone":"+31 23 554 3966",
    "sg:postcode":"2132 XX",
    "sg:province":"Noord-Holland",
    "sg:website":"http://www.provocations.nl",
    "wof:name":"Pro Vocations",
    "wof:placetype":"venue"
},
  "geometry": {"coordinates":[4.69296,52.305393],"type":"Point"}
}