{
  "type": "Feature",
  "properties": {
    "addr:full":"Goudsbloemstr 29 Enschede Overijssel 7531 DD",
    "addr:housenumber":"29",
    "addr:postcode":"7531 dd",
    "addr:street":"Goudsbloemstr",
    "iso:country":"NL",
    "sg:address":"Goudsbloemstr 29",
    "sg:city":"Enschede",
    "sg:orig_category":"Boekbinderijen",
    "sg:phone":"+31 53 434 8342",
    "sg:postcode":"7531 DD",
    "sg:province":"Overijssel",
    "wof:name":"Euro Boekbinderij",
    "wof:placetype":"venue"
},
  "geometry": {"coordinates":[6.916318,52.230068],"type":"Point"}
}