{
  "type": "Feature",
  "properties": {
    "addr:full":"Bombardonstraat 37 Amersfoort Utrecht 3822 CG",
    "addr:housenumber":"37",
    "addr:postcode":"3822 cg",
    "addr:street":"Bombardonstraat",
    "iso:country":"NL",
    "sg:address":"Bombardonstraat 37",
    "sg:city":"Amersfoort",
    "sg:orig_category":"Diverse Opleidingen And Onderwijs",
    "sg:phone":"+31 33 455 3700",
    "sg:postcode":"3822 CG",
    "sg:province":"Utrecht",
    "wof:name":"J. Witlox Taleninstituut",
    "wof:placetype":"venue"
},
  "geometry": {"coordinates":[5.403439,52.180904],"type":"Point"}
}