{
  "type": "Feature",
  "properties": {
    "iso:country":"NL",
    "sg:address":"Telefoonstraat 43",
    "sg:city":"Zuidlaren",
    "sg:orig_category":"Werving And Selectie Van Vast Personeel",
    "sg:phone":"+31 6 11343415",
    "sg:postcode":"9471 EL",
    "sg:province":"Provincie Drenthe",
    "wof:name":"Kamille",
    "wof:placetype":"venue"
},
  "geometry": {"coordinates":[6.6809821129,53.0949897766],"type":"Point"}
}