{
  "type": "Feature",
  "properties": {
    "addr:full":"O L Vrouwepln 16A Maastricht Limburg 6211 HE",
    "addr:housenumber":"16a",
    "addr:postcode":"6211 he",
    "addr:street":"O",
    "iso:country":"NL",
    "sg:address":"O L Vrouwepln 16A",
    "sg:city":"Maastricht",
    "sg:orig_category":"Verzekeringen - Verzekeringskantoren",
    "sg:phone":"+31 43 321 2020",
    "sg:postcode":"6211 HE",
    "sg:province":"Limburg",
    "wof:name":"Hendriks",
    "wof:placetype":"venue"
},
  "geometry": {"coordinates":[5.693809,50.846951],"type":"Point"}
}