{
  "type": "Feature",
  "properties": {
    "addr:full":"Snoeckgensheuvel 13 Amersfoort Utrecht 3817 HK",
    "addr:housenumber":"13",
    "addr:postcode":"3817 hk",
    "addr:street":"Snoeckgensheuvel",
    "iso:country":"NL",
    "sg:address":"Snoeckgensheuvel 13",
    "sg:city":"Amersfoort",
    "sg:orig_category":"Adviesbureaus Bedrijfsorganisatie",
    "sg:phone":"+31 33 448 0965",
    "sg:postcode":"3817 HK",
    "sg:province":"Utrecht",
    "wof:name":"Lange, De",
    "wof:placetype":"venue"
},
  "geometry": {"coordinates":[5.394108,52.143253],"type":"Point"}
}