{
  "type": "Feature",
  "properties": {
    "addr:full":"Voorstraat 2 Utrecht Utrecht 3512 AM",
    "addr:housenumber":"2",
    "addr:postcode":"3512",
    "addr:street":"Voorstraat",
    "iso:country":"NL",
    "sg:address":"Voorstraat 2",
    "sg:city":"Utrecht",
    "sg:orig_category":"Werving And Selectie Van Tijdelijk Personeel And Uitzendkantoren",
    "sg:phone":"+31 30 231 0548",
    "sg:postcode":"3512 AM",
    "sg:province":"Utrecht",
    "wof:name":"Adecco",
    "wof:placetype":"venue"
},
  "geometry": {"coordinates":[5.1184129715,52.093662262],"type":"Point"}
}