{
  "type": "Feature",
  "properties": {
    "addr:full":"Herewg 66 Groningen Groningen 9725 AG",
    "addr:housenumber":"66",
    "addr:postcode":"9725",
    "addr:street":"Herewg",
    "iso:country":"NL",
    "sg:address":"Herewg 66",
    "sg:city":"Groningen",
    "sg:orig_category":"Kappers",
    "sg:phone":"+31 50 525 2839",
    "sg:postcode":"9725 AG",
    "sg:province":"Groningen",
    "wof:name":"Boucl?",
    "wof:placetype":"venue"
},
  "geometry": {"coordinates":[6.5724368095,53.208896637],"type":"Point"}
}