{
  "type": "Feature",
  "properties": {
    "addr:full":"Leidsestr 4 Amsterdam Noord-Holland 1017 PA",
    "addr:housenumber":"4",
    "addr:postcode":"1017 pa",
    "addr:street":"Leidsestr",
    "iso:country":"NL",
    "sg:address":"Leidsestr 4",
    "sg:city":"Amsterdam",
    "sg:orig_category":"Schoenen",
    "sg:phone":"+31 20 423 2867",
    "sg:postcode":"1017 PA",
    "sg:province":"Noord-Holland",
    "sg:website":"http://www.ecco.com",
    "wof:name":"Ecco",
    "wof:placetype":"venue"
},
  "geometry": {"coordinates":[-74.11945299999999,42.944771],"type":"Point"}
}