{
  "type": "Feature",
  "properties": {
    "iso:country":"NL",
    "sg:address":"Bemuurde Weerd Oz 18",
    "sg:city":"Utrecht",
    "sg:orig_category":"Meubelzaken, Woning- And Keukeninrichting",
    "sg:phone":"+31 30 271 7689",
    "sg:postcode":"3514 AN",
    "sg:province":"Utrecht",
    "wof:name":"Slaapkomfort",
    "wof:placetype":"venue"
},
  "geometry": {"coordinates":[5.115243,52.097569],"type":"Point"}
}