{
  "type": "Feature",
  "properties": {
    "addr:full":"Oranjestraat 8 Hoofddorp North Holland 2131 XP",
    "addr:housenumber":"8",
    "addr:postcode":"2131 xp",
    "addr:street":"Oranjestraat",
    "iso:country":"NL",
    "sg:address":"Oranjestraat 8",
    "sg:city":"Hoofddorp",
    "sg:orig_category":"Autokeuringen",
    "sg:phone":"+31 23 561 1607",
    "sg:postcode":"2131 XP",
    "sg:province":"North Holland",
    "wof:name":"L. Karman",
    "wof:placetype":"venue"
},
  "geometry": {"coordinates":[4.686661,52.310791],"type":"Point"}
}