{
  "type": "Feature",
  "properties": {
    "addr:full":"Oostkerkestr 21 Wolphaartsdyk Zeeland 4471 BA",
    "addr:housenumber":"21",
    "addr:postcode":"4471 ba",
    "addr:street":"Oostkerkestr;Zeeland",
    "iso:country":"NL",
    "sg:address":"Oostkerkestr 21",
    "sg:city":"Wolphaartsdyk",
    "sg:orig_category":"Postkantoren",
    "sg:phone":"+31 113 581 225",
    "sg:postcode":"4471 BA",
    "sg:province":"Zeeland",
    "wof:name":"Postkantoren",
    "wof:placetype":"venue"
},
  "geometry": {"coordinates":[3.821545,51.529114],"type":"Point"}
}