{
  "type": "Feature",
  "properties": {
    "addr:full":"Cimburgaln 88 Breda Noord-Brabant 4819 BD",
    "addr:housenumber":"88",
    "addr:postcode":"4819 bd",
    "addr:street":"Cimburgaln",
    "iso:country":"NL",
    "sg:address":"Cimburgaln 88",
    "sg:city":"Breda",
    "sg:orig_category":"Yoga-Instituten",
    "sg:phone":"+31 76 521 1653",
    "sg:postcode":"4819 BD",
    "sg:province":"Noord-Brabant",
    "wof:name":"Panta Rhei",
    "wof:placetype":"venue"
},
  "geometry": {"coordinates":[4.774023,51.573906],"type":"Point"}
}