{
  "type": "Feature",
  "properties": {
    "addr:full":"Drievriendenstr 26 Rotterdam South Holland 3014 JS",
    "addr:housenumber":"26",
    "addr:postcode":"3014 js",
    "addr:street":"Drievriendenstr",
    "iso:country":"NL",
    "sg:address":"Drievriendenstr 26",
    "sg:city":"Rotterdam",
    "sg:orig_category":"Beeldende Kunstenaars",
    "sg:phone":"+31 10 404 7572",
    "sg:postcode":"3014 JS",
    "sg:province":"South Holland",
    "wof:name":"Oosterwijk & Zoon, C",
    "wof:placetype":"venue"
},
  "geometry": {"coordinates":[4.466869,51.920887],"type":"Point"}
}