{
  "type": "Feature",
  "properties": {
    "addr:full":"Haven Kloosternol 2 Scharendijke Zeeland 4322 AK",
    "addr:housenumber":"2",
    "addr:postcode":"4322 ak",
    "addr:street":"Haven Kloosternol",
    "iso:country":"NL",
    "sg:address":"Haven Kloosternol 2",
    "sg:city":"Scharendijke",
    "sg:orig_category":"Jachthavens - Jachtwerven",
    "sg:phone":"+31 111 671 264",
    "sg:postcode":"4322 AK",
    "sg:province":"Zeeland",
    "wof:name":"Havenkantoor Scharendijke",
    "wof:placetype":"venue"
},
  "geometry": {"coordinates":[3.841135,51.733082],"type":"Point"}
}