{
  "type": "Feature",
  "properties": {
    "iso:country":"NL",
    "sg:address":"Dorpsstraat 12",
    "sg:city":"Tuitjenhorn",
    "sg:orig_category":"Binnenhuisarchitecten",
    "sg:phone":"+31 226 392 056",
    "sg:postcode":"1747 HD",
    "sg:province":"Noord-Holland",
    "wof:name":"Jac. Nota Interieurverzorging",
    "wof:placetype":"venue"
},
  "geometry": {"coordinates":[4.749064,52.73674],"type":"Point"}
}