{
  "type": "Feature",
  "properties": {
    "addr:full":"Bedryvenstr 21 Wierden NL.08 7641 AM",
    "addr:housenumber":"21;nl.08",
    "addr:postcode":"7641",
    "addr:street":"Bedryvenstr",
    "iso:country":"NL",
    "sg:address":"Bedryvenstr 21",
    "sg:city":"Wierden",
    "sg:orig_category":"Horeca-Inrichtingen En -Uitrustingen",
    "sg:phone":"+31 546 579 005",
    "sg:postcode":"7641 AM",
    "sg:province":"NL.08",
    "sg:website":"http://www.allureverlichting.nl",
    "wof:name":"Allure Verlichting Vof",
    "wof:placetype":"venue"
},
  "geometry": {"coordinates":[6.581372,52.361977],"type":"Point"}
}