{
  "type": "Feature",
  "properties": {
    "addr:full":"Stationsstraat 102 Elsloo Lb Limburg 6181 AK",
    "addr:housenumber":"102",
    "addr:postcode":"lb;6181 ak",
    "addr:street":"Stationsstraat",
    "iso:country":"NL",
    "sg:address":"Stationsstraat 102",
    "sg:city":"Elsloo Lb",
    "sg:orig_category":"Hout Gh",
    "sg:phone":"+31 46 437 7960",
    "sg:postcode":"6181 AK",
    "sg:province":"Limburg",
    "wof:name":"Hubo J Heijnen",
    "wof:placetype":"venue"
},
  "geometry": {"coordinates":[5.773171,50.946411],"type":"Point"}
}