{
  "type": "Feature",
  "properties": {
    "addr:full":"Fluwelen Burgwal 7 Monnickendam Noord-Holland 1141 TX",
    "addr:housenumber":"7",
    "addr:postcode":"1141 tx",
    "addr:street":"Fluwelen Burgwal",
    "iso:country":"NL",
    "sg:address":"Fluwelen Burgwal 7",
    "sg:city":"Monnickendam",
    "sg:orig_category":"Adviesbureaus Financieel",
    "sg:phone":"+31 299 651 350",
    "sg:postcode":"1141 TX",
    "sg:province":"Noord-Holland",
    "wof:name":"Financial Management Cons",
    "wof:placetype":"venue"
},
  "geometry": {"coordinates":[5.035144,52.45789],"type":"Point"}
}