{
  "type": "Feature",
  "properties": {
    "addr:full":"Voorstr 2 Franeker Provincie Friesland 8801 LC",
    "addr:housenumber":"2",
    "addr:postcode":"8801 lc",
    "addr:street":"Voorstr;Provincie Friesland",
    "iso:country":"NL",
    "sg:address":"Voorstr 2",
    "sg:city":"Franeker",
    "sg:orig_category":"Banken",
    "sg:phone":"+31 517 393 247",
    "sg:postcode":"8801 LC",
    "sg:province":"Provincie Friesland",
    "sg:website":"http://www.friba.nl",
    "wof:name":"Friesland Bank",
    "wof:placetype":"venue"
},
  "geometry": {"coordinates":[5.543833,53.186615],"type":"Point"}
}