{
  "type": "Feature",
  "properties": {
    "addr:full":"Prins Bernhardlaan 42 Uithoorn Noord-Holland 1421 AM",
    "addr:housenumber":"42",
    "addr:postcode":"1421",
    "addr:street":"Prins Bernhardlaan",
    "iso:country":"NL",
    "sg:address":"Prins Bernhardlaan 42",
    "sg:city":"Uithoorn",
    "sg:orig_category":"Metalen And Ertsen Gh",
    "sg:phone":"+31 297 530 000",
    "sg:postcode":"1421 AM",
    "sg:province":"Noord-Holland",
    "wof:name":"Vekagesta Bv",
    "wof:placetype":"venue"
},
  "geometry": {"coordinates":[4.832824,52.235172],"type":"Point"}
}