{
  "type": "Feature",
  "properties": {
    "addr:full":"Gedempte Zuiderdiep 154 Groningen Groningen 9711 HN",
    "addr:housenumber":"154",
    "addr:postcode":"9711 hn",
    "addr:street":"Gedempte Zuiderdiep",
    "iso:country":"NL",
    "sg:address":"Gedempte Zuiderdiep 154",
    "sg:city":"Groningen",
    "sg:classifiers":[
        {
            "category":"Bakery",
            "type":"Food & Drink"
        }
    ],
    "sg:phone":"+31 50 312 6266",
    "sg:postcode":"9711 HN",
    "sg:province":"Groningen",
    "sg:tags":[
        "brood",
        "banket"
    ],
    "wof:name":"Knol'S Koek, Iets Aparts",
    "wof:placetype":"venue"
},
  "geometry": {"coordinates":[6.562045,53.214813],"type":"Point"}
}