{
  "type": "Feature",
  "properties": {
    "iso:country":"NL",
    "sg:address":"Zylsterwg 7",
    "sg:city":"Feerwerd",
    "sg:classifiers":[
        {
            "category":"Travel",
            "subcategory":"Hotels & Motels",
            "type":"Entertainment"
        }
    ],
    "sg:phone":"+31 594 621 423",
    "sg:postcode":"9892 TE",
    "sg:province":"Groningen",
    "sg:website":"http://www.bart.nl/~zijlster/index.html",
    "wof:name":"Zijlsterhoeve, De",
    "wof:placetype":"venue"
},
  "geometry": {"coordinates":[6.465155,53.316669],"type":"Point"}
}