{
  "type": "Feature",
  "properties": {
    "addr:full":"Eelderstr 7 Groningen Groningen 9726 CT",
    "addr:housenumber":"7",
    "addr:postcode":"9726 ct",
    "addr:street":"Eelderstr",
    "iso:country":"NL",
    "sg:address":"Eelderstr 7",
    "sg:city":"Groningen",
    "sg:orig_category":"Adviesbureaus Bouwkunde",
    "sg:phone":"+31 50 535 2798",
    "sg:postcode":"9726 CT",
    "sg:province":"Groningen",
    "sg:website":"http://www.melessen.com",
    "wof:name":"Bbm",
    "wof:placetype":"venue"
},
  "geometry": {"coordinates":[6.556488,53.21312],"type":"Point"}
}