{
  "type": "Feature",
  "properties": {
    "addr:full":"Coevering 31 Geldrop Noord-Brabant 5665 GA",
    "addr:housenumber":"31",
    "addr:postcode":"5665 ga",
    "addr:street":"Coevering",
    "iso:country":"NL",
    "sg:address":"Coevering 31",
    "sg:city":"Geldrop",
    "sg:orig_category":"Artsen - Huisartsen",
    "sg:phone":"+31 40 285 0167",
    "sg:postcode":"5665 GA",
    "sg:province":"Noord-Brabant",
    "wof:name":"Bakx, N J M",
    "wof:placetype":"venue"
},
  "geometry": {"coordinates":[5.58213,51.416939],"type":"Point"}
}