{
  "type": "Feature",
  "properties": {
    "addr:full":"Sleutelwg 11 Bemelen Limburg 6268 NM",
    "addr:housenumber":"11",
    "addr:postcode":"6268",
    "addr:street":"Sleutelwg",
    "iso:country":"NL",
    "sg:address":"Sleutelwg 11",
    "sg:city":"Bemelen",
    "sg:orig_category":"Verenigingen En Stichtingen",
    "sg:phone":"+31 43 407 2233",
    "sg:postcode":"6268 NM",
    "sg:province":"Limburg",
    "wof:name":"Hart In Beweging Mergelland, Sticht",
    "wof:placetype":"venue"
},
  "geometry": {"coordinates":[5.761048,50.84602],"type":"Point"}
}