{
  "type": "Feature",
  "properties": {
    "iso:country":"NL",
    "sg:address":"Markt 53",
    "sg:city":"Gouda",
    "sg:orig_category":"Schoenen",
    "sg:phone":"+31 182 688 646",
    "sg:postcode":"2801 JL",
    "sg:province":"Zuid-Holland",
    "wof:name":"Amigo",
    "wof:placetype":"venue"
},
  "geometry": {"coordinates":[4.71026,52.01194],"type":"Point"}
}