{
  "type": "Feature",
  "properties": {
    "addr:full":"St Vitusholt 25 Winschoten Groningen 9674 AE",
    "addr:housenumber":"25",
    "addr:postcode":"9674 ae",
    "addr:street":"St Vitusholt",
    "iso:country":"NL",
    "sg:address":"St Vitusholt 25",
    "sg:city":"Winschoten",
    "sg:classifiers":[
        {
            "category":"Personal",
            "subcategory":"Nail Salon",
            "type":"Services"
        }
    ],
    "sg:phone":"+31 597 416 463",
    "sg:postcode":"9674 AE",
    "sg:province":"Groningen",
    "sg:tags":[
        "pedicure"
    ],
    "wof:name":"Deiman-Zwerver, S",
    "wof:placetype":"venue"
},
  "geometry": {"coordinates":[7.023434,53.146297],"type":"Point"}
}