{
  "type": "Feature",
  "properties": {
    "addr:full":"Musselwg 67 Mussel Groningen 9584 AB",
    "addr:housenumber":"67",
    "addr:postcode":"9584 ab",
    "addr:street":"Musselwg",
    "iso:country":"NL",
    "sg:address":"Musselwg 67",
    "sg:city":"Mussel",
    "sg:orig_category":"Oldtimers",
    "sg:phone":"+31 599 454 943",
    "sg:postcode":"9584 AB",
    "sg:province":"Groningen",
    "wof:name":"Mulder Specials",
    "wof:placetype":"venue"
},
  "geometry": {"coordinates":[-83.144104,39.370178],"type":"Point"}
}