{
  "type": "Feature",
  "properties": {
    "addr:full":"Singel 56 Bussum Noord-Holland 1402 NV",
    "addr:housenumber":"56",
    "addr:postcode":"1402 nv",
    "addr:street":"Singel",
    "iso:country":"NL",
    "sg:address":"Singel 56",
    "sg:city":"Bussum",
    "sg:orig_category":"Adviesbureaus Bedrijfsorganisatie",
    "sg:phone":"+31 6 53445938",
    "sg:postcode":"1402 NV",
    "sg:province":"Noord-Holland",
    "wof:name":"Drenth",
    "wof:placetype":"venue"
},
  "geometry": {"coordinates":[5.168523,52.270653],"type":"Point"}
}