{
  "type": "Feature",
  "properties": {
    "addr:full":"Kleverparkweg 7 Haarlem North Holland 2023 CA",
    "addr:housenumber":"7",
    "addr:postcode":"2023 ca",
    "addr:street":"Kleverparkweg",
    "iso:country":"NL",
    "sg:address":"Kleverparkweg 7",
    "sg:city":"Haarlem",
    "sg:classifiers":[
        {
            "category":"Retail",
            "subcategory":"Photofinishing",
            "type":"Services"
        }
    ],
    "sg:phone":"+31 23 526 1669",
    "sg:postcode":"2023 CA",
    "sg:province":"North Holland",
    "sg:tags":[
        "foto",
        "film"
    ],
    "wof:name":"Fotovak Engel Bv",
    "wof:placetype":"venue"
},
  "geometry": {"coordinates":[4.631565,52.390926],"type":"Point"}
}