{
  "type": "Feature",
  "properties": {
    "addr:full":"Lokkenstr 30 S Gravendeel Zuid-Holland 3295 VH",
    "addr:housenumber":"30",
    "addr:postcode":"3295 vh",
    "addr:street":"Lokkenstr;S",
    "iso:country":"NL",
    "sg:address":"Lokkenstr 30",
    "sg:city":"S Gravendeel",
    "sg:orig_category":"Juweliers",
    "sg:phone":"+31 78 673 4590",
    "sg:postcode":"3295 VH",
    "sg:province":"Zuid-Holland",
    "wof:name":"Chaton Kooijman",
    "wof:placetype":"venue"
},
  "geometry": {"coordinates":[4.612094,51.775974],"type":"Point"}
}