{
  "type": "Feature",
  "properties": {
    "iso:country":"NL",
    "sg:address":"Lamaweide 10",
    "sg:city":"Nieuwegein",
    "sg:orig_category":"Adviesbureaus Bedrijfsorganisatie",
    "sg:phone":"+31 30 601 3582",
    "sg:postcode":"3437 ES",
    "sg:province":"Utrecht",
    "wof:name":"Renaud & Renaud",
    "wof:placetype":"venue"
},
  "geometry": {"coordinates":[5.071986,52.045406],"type":"Point"}
}