{
  "type": "Feature",
  "properties": {
    "addr:full":"De Grutterij 11 Leusden Utrecht 3831 NE",
    "addr:housenumber":"11",
    "addr:postcode":"3831 ne",
    "addr:street":"De Grutterij",
    "iso:country":"NL",
    "sg:address":"De Grutterij 11",
    "sg:city":"Leusden",
    "sg:orig_category":"Kappers",
    "sg:phone":"+31 33 494 4113",
    "sg:postcode":"3831 NE",
    "sg:province":"Utrecht",
    "wof:name":"Pierre Bv",
    "wof:placetype":"venue"
},
  "geometry": {"coordinates":[5.427516,52.129234],"type":"Point"}
}