{
  "type": "Feature",
  "properties": {
    "iso:country":"NL",
    "sg:address":"Fultonstraat 6",
    "sg:city":"'S Gravenhage",
    "sg:orig_category":"Boekhouders",
    "sg:phone":"+31 70 364 8452",
    "sg:postcode":"2562 XH",
    "sg:province":"Zuid-Holland",
    "wof:name":"Frank Van Den Bos",
    "wof:placetype":"venue"
},
  "geometry": {"coordinates":[4.279175,52.075459],"type":"Point"}
}