{
  "type": "Feature",
  "properties": {
    "iso:country":"NL",
    "sg:address":"L V Vechelstr 21",
    "sg:city":"Tilburg",
    "sg:orig_category":"Afslankinstituten",
    "sg:phone":"+31 13 544 6004",
    "sg:postcode":"5014 HD",
    "sg:province":"Noord-Brabant",
    "wof:name":"Koral International",
    "wof:placetype":"venue"
},
  "geometry": {"coordinates":[5.106271,51.554928],"type":"Point"}
}