{
  "type": "Feature",
  "properties": {
    "addr:full":"Hoge Engweg 4-7 Putten Gelderland 3882 TA",
    "addr:housenumber":"4-7",
    "addr:postcode":"3882 ta",
    "addr:street":"Hoge Engweg;Gelderland",
    "iso:country":"NL",
    "sg:address":"Hoge Engweg 4-7",
    "sg:city":"Putten",
    "sg:orig_category":"Meubelreparatie And -Restauratie",
    "sg:phone":"+31 341 351 137",
    "sg:postcode":"3882 TA",
    "sg:province":"Gelderland",
    "wof:name":"P.A. Goudsmid",
    "wof:placetype":"venue"
},
  "geometry": {"coordinates":[5.604622,52.253563],"type":"Point"}
}