{
  "type": "Feature",
  "properties": {
    "addr:full":"Patronaatstraat 2 Made Noord-Brabant 4921 BL",
    "addr:housenumber":"2",
    "addr:postcode":"4921 bl",
    "addr:street":"Patronaatstraat",
    "iso:country":"NL",
    "sg:address":"Patronaatstraat 2",
    "sg:city":"Made",
    "sg:orig_category":"Werving And Selectie Van Tijdelijk Personeel And Uitzendkantoren",
    "sg:phone":"+31 162 683 000",
    "sg:postcode":"4921 BL",
    "sg:province":"Noord-Brabant",
    "wof:name":"Rooijen Bv",
    "wof:placetype":"venue"
},
  "geometry": {"coordinates":[-120.0639953613,36.9620552063],"type":"Point"}
}