{
  "type": "Feature",
  "properties": {
    "iso:country":"NL",
    "sg:address":"Streekwg 113A",
    "sg:city":"Hoogkarspel",
    "sg:orig_category":"Oldtimers",
    "sg:phone":"+31 228 561 340",
    "sg:postcode":"1616 AB",
    "sg:province":"Noord-Holland",
    "wof:name":"Soest, D Van",
    "wof:placetype":"venue"
},
  "geometry": {"coordinates":[5.166308,52.692829],"type":"Point"}
}