{
  "type": "Feature",
  "properties": {
    "iso:country":"NL",
    "sg:address":"Kuijpersdijk 12",
    "sg:city":"'S Heerenhoek",
    "sg:orig_category":"Verlichting And Huishoudartikelen",
    "sg:phone":"+31 113 351 393",
    "sg:postcode":"4453 AC",
    "sg:province":"Zeeland",
    "wof:name":"M.P. De Jonge-Van Eykeren Vof",
    "wof:placetype":"venue"
},
  "geometry": {"coordinates":[3.768209,51.449535],"type":"Point"}
}