{
  "type": "Feature",
  "properties": {
    "addr:full":"Gosewijnstraat 12 Valkenburg Lb Limburg 6301 DT",
    "addr:housenumber":"12",
    "addr:postcode":"lb;6301 dt",
    "addr:street":"Gosewijnstraat",
    "iso:country":"NL",
    "sg:address":"Gosewijnstraat 12",
    "sg:city":"Valkenburg Lb",
    "sg:orig_category":"Discountwinkels",
    "sg:phone":"+31 43 601 4043",
    "sg:postcode":"6301 DT",
    "sg:province":"Limburg",
    "wof:name":"Mode-Atelier Fleur",
    "wof:placetype":"venue"
},
  "geometry": {"coordinates":[5.833038,50.864254],"type":"Point"}
}