{
  "type": "Feature",
  "properties": {
    "addr:full":"Bentinckstraat 19 Oldenzaal Overijssel 7571 XN",
    "addr:housenumber":"19",
    "addr:postcode":"7571 xn",
    "addr:street":"Bentinckstraat",
    "iso:country":"NL",
    "sg:address":"Bentinckstraat 19",
    "sg:city":"Oldenzaal",
    "sg:orig_category":"Loodgieterswerk, Verwarming And Sanitaire Installaties",
    "sg:phone":"+31 541 512 318",
    "sg:postcode":"7571 XN",
    "sg:province":"Overijssel",
    "wof:name":"Firma G.J.R. Falkmann En Zoon",
    "wof:placetype":"venue"
},
  "geometry": {"coordinates":[6.925601,52.315334],"type":"Point"}
}