{
  "type": "Feature",
  "properties": {
    "addr:full":"Bruggertweg 7 Beltrum Gelderland 7156 NB",
    "addr:housenumber":"7",
    "addr:postcode":"7156 nb",
    "addr:street":"Bruggertweg;Gelderland",
    "iso:country":"NL",
    "sg:address":"Bruggertweg 7",
    "sg:city":"Beltrum",
    "sg:orig_category":"Gespecialiseerde Bouw",
    "sg:phone":"+31 545 261 257",
    "sg:postcode":"7156 NB",
    "sg:province":"Gelderland",
    "wof:name":"Constructiebedrijf R. Belterman",
    "wof:placetype":"venue"
},
  "geometry": {"coordinates":[6.561635,52.09446],"type":"Point"}
}