{
  "type": "Feature",
  "properties": {
    "addr:full":"Edisonweg 51 Vlissingen Zeeland 4382 NV",
    "addr:housenumber":"51",
    "addr:postcode":"4382 nv",
    "addr:street":"Edisonweg",
    "iso:country":"NL",
    "sg:address":"Edisonweg 51",
    "sg:city":"Vlissingen",
    "sg:orig_category":"Werving And Selectie Van Vast Personeel",
    "sg:phone":"+31 118 476 600",
    "sg:postcode":"4382 NV",
    "sg:province":"Zeeland",
    "wof:name":"Arbeidsbureau Vlissingen Hoger Opgeleiden",
    "wof:placetype":"venue"
},
  "geometry": {"coordinates":[3.5924110413,51.4542884827],"type":"Point"}
}