{
  "type": "Feature",
  "properties": {
    "iso:country":"NL",
    "sg:address":"Burgerwg 27",
    "sg:city":"Maasland",
    "sg:orig_category":"Bloemen En Planten - Groothandel",
    "sg:phone":"+31 174 518 977",
    "sg:postcode":"3155 RB",
    "sg:province":"Zuid-Holland",
    "wof:name":"Heboplant Bv",
    "wof:placetype":"venue"
},
  "geometry": {"coordinates":[4.25272,51.958729],"type":"Point"}
}