{
  "type": "Feature",
  "properties": {
    "addr:full":"J P Heyestr 56 Amsterdam Noord-Holland 1053 GP",
    "addr:housenumber":"56",
    "addr:postcode":"1053 gp",
    "addr:street":"J P Heyestr",
    "iso:country":"NL",
    "sg:address":"J P Heyestr 56",
    "sg:city":"Amsterdam",
    "sg:orig_category":"Bloemen En Planten",
    "sg:phone":"+31 20 612 7043",
    "sg:postcode":"1053 GP",
    "sg:province":"Noord-Holland",
    "wof:name":"John En Wil",
    "wof:placetype":"venue"
},
  "geometry": {"coordinates":[4.86733,52.366638],"type":"Point"}
}