{
  "type": "Feature",
  "properties": {
    "addr:full":"Oudenhovenstr (Beverwijcksplein) 30-36 Dordrecht Zuid-Holland 3311 GK",
    "addr:housenumber":"30-36",
    "addr:postcode":"3311 gk",
    "iso:country":"NL",
    "sg:address":"Oudenhovenstr (Beverwijcksplein) 30-36",
    "sg:city":"Dordrecht",
    "sg:orig_category":"Verf En Lak",
    "sg:phone":"+31 78 613 4500",
    "sg:postcode":"3311 GK",
    "sg:province":"Zuid-Holland",
    "sg:website":"http://www.vanreesverf.nl",
    "wof:name":"Rees, Verfhandel Van",
    "wof:placetype":"venue"
},
  "geometry": {"coordinates":[4.666423,51.80954],"type":"Point"}
}