{
  "type": "Feature",
  "properties": {
    "addr:full":"Huissen 3 Baarlo Lb Limburg 5991 PX",
    "addr:housenumber":"3",
    "addr:postcode":"lb;5991 px",
    "addr:street":"Huissen",
    "iso:country":"NL",
    "sg:address":"Huissen 3",
    "sg:city":"Baarlo Lb",
    "sg:orig_category":"Sportcentra",
    "sg:phone":"+31 77 477 2747",
    "sg:postcode":"5991 PX",
    "sg:province":"Limburg",
    "wof:name":"Sporthal Van Gemeente Maasbree",
    "wof:placetype":"venue"
},
  "geometry": {"coordinates":[6.092759,51.326157],"type":"Point"}
}