{
  "type": "Feature",
  "properties": {
    "addr:full":"Stationsstraat 5 Spijkenisse Zuid-Holland 3201 AS",
    "addr:housenumber":"5",
    "addr:postcode":"3201 as",
    "addr:street":"Stationsstraat",
    "iso:country":"NL",
    "sg:address":"Stationsstraat 5",
    "sg:city":"Spijkenisse",
    "sg:orig_category":"Metaalwerken",
    "sg:phone":"+31 181 622 277",
    "sg:postcode":"3201 AS",
    "sg:province":"Zuid-Holland",
    "wof:name":"Ansol Zonwering Bv",
    "wof:placetype":"venue"
},
  "geometry": {"coordinates":[4.325045,51.849525],"type":"Point"}
}