{
  "type": "Feature",
  "properties": {
    "addr:full":"C Huygenswg 1 Hellevoetsluis Zuid-Holland 3225 LD",
    "addr:housenumber":"1",
    "addr:postcode":"3225 ld",
    "iso:country":"NL",
    "sg:address":"C Huygenswg 1",
    "sg:city":"Hellevoetsluis",
    "sg:orig_category":"Horecabenodigdheden",
    "sg:phone":"+31 181 399 680",
    "sg:postcode":"3225 LD",
    "sg:province":"Zuid-Holland",
    "wof:name":"Deli Xl",
    "wof:placetype":"venue"
},
  "geometry": {"coordinates":[4.172114,51.838051],"type":"Point"}
}