{
  "type": "Feature",
  "properties": {
    "addr:full":"Wepel 25 Annen South Carolina 9468 HH",
    "addr:housenumber":"25;9468",
    "addr:postcode":"hh",
    "addr:street":"Wepel",
    "iso:country":"NL",
    "sg:address":"Wepel 25",
    "sg:city":"Annen",
    "sg:orig_category":"Beautyfarms And Sauna'S",
    "sg:phone":"+31 592 277 000",
    "sg:postcode":"9468 HH",
    "sg:province":"South Carolina",
    "wof:name":"Ido",
    "wof:placetype":"venue"
},
  "geometry": {"coordinates":[-79.253815,33.471233],"type":"Point"}
}