{
  "type": "Feature",
  "properties": {
    "addr:full":"Beekln 27 Tilburg Noord-Brabant 5032 AA",
    "addr:housenumber":"27",
    "addr:postcode":"5032 aa",
    "addr:street":"Beekln",
    "iso:country":"NL",
    "sg:address":"Beekln 27",
    "sg:city":"Tilburg",
    "sg:orig_category":"Adviesbureaus Bedrijfsorganisatie",
    "sg:phone":"+31 13 463 5456",
    "sg:postcode":"5032 AA",
    "sg:province":"Noord-Brabant",
    "wof:name":"Eijk, Van",
    "wof:placetype":"venue"
},
  "geometry": {"coordinates":[5.0039,51.553379],"type":"Point"}
}