{
  "type": "Feature",
  "properties": {
    "addr:full":"Langendijk 66 Gorinchem Zuid-Holland 4201 CJ",
    "addr:housenumber":"66",
    "addr:postcode":"4201 cj",
    "addr:street":"Langendijk",
    "iso:country":"NL",
    "sg:address":"Langendijk 66",
    "sg:city":"Gorinchem",
    "sg:classifiers":[
        {
            "category":"Shopping",
            "subcategory":"Gifts & Souvenirs",
            "type":"Retail Goods"
        }
    ],
    "sg:phone":"+31 183 630 049",
    "sg:postcode":"4201 CJ",
    "sg:province":"Zuid-Holland",
    "sg:tags":[
        "geschenken"
    ],
    "wof:name":"Jacky'S Kadootjes Vof",
    "wof:placetype":"venue"
},
  "geometry": {"coordinates":[4.975663,51.828671],"type":"Point"}
}