{
  "type": "Feature",
  "properties": {
    "addr:full":"Bazuinln 88 Etten Leur North Brabant 4876 AG",
    "addr:housenumber":"88",
    "addr:postcode":"4876",
    "addr:street":"Bazuinln",
    "iso:country":"NL",
    "sg:address":"Bazuinln 88",
    "sg:city":"Etten Leur",
    "sg:orig_category":"Wijnkoperijen En -Groothandel",
    "sg:phone":"+31 76 501 9601",
    "sg:postcode":"4876 AG",
    "sg:province":"North Brabant",
    "wof:name":"Vanovin Bv",
    "wof:placetype":"venue"
},
  "geometry": {"coordinates":[4.6268172264,51.5667457581],"type":"Point"}
}