{
  "type": "Feature",
  "properties": {
    "addr:full":"Granietstr 30 T Harde Gelderland 8084 CJ",
    "addr:housenumber":"30 t",
    "addr:postcode":"8084 cj",
    "addr:street":"Granietstr;Harde Gelderland",
    "iso:country":"NL",
    "sg:address":"Granietstr 30",
    "sg:city":"T Harde",
    "sg:orig_category":"Administratie- En Boekhoudkantoren",
    "sg:phone":"+31 525 651 512",
    "sg:postcode":"8084 CJ",
    "sg:province":"Gelderland",
    "wof:name":"Bossenbroek",
    "wof:placetype":"venue"
},
  "geometry": {"coordinates":[5.875574,52.414108],"type":"Point"}
}