{
  "type": "Feature",
  "properties": {
    "iso:country":"NL",
    "sg:address":"Granietstr 30",
    "sg:city":"T Harde",
    "sg:orig_category":"Administratie- En Boekhoudkantoren",
    "sg:phone":"+31 525 651 512",
    "sg:postcode":"8084 CJ",
    "sg:province":"Gelderland",
    "wof:name":"Bossenbroek",
    "wof:placetype":"venue"
},
  "geometry": {"coordinates":[5.875574,52.414108],"type":"Point"}
}