{
  "type": "Feature",
  "properties": {
    "addr:full":"Donkere Begijnhof 2 Haarlem North Holland 2011 HG",
    "addr:housenumber":"2",
    "addr:postcode":"2011 hg",
    "addr:street":"Donkere Begijnhof",
    "iso:country":"NL",
    "sg:address":"Donkere Begijnhof 2",
    "sg:city":"Haarlem",
    "sg:orig_category":"Verhuisdiensten",
    "sg:phone":"+31 23 532 0945",
    "sg:postcode":"2011 HG",
    "sg:province":"North Holland",
    "wof:name":"Transport- En Verhuisbedrijf Fabel",
    "wof:placetype":"venue"
},
  "geometry": {"coordinates":[4.638671,52.383049],"type":"Point"}
}