{
  "type": "Feature",
  "properties": {
    "addr:full":"Voorstraat 20 Piershil Zuid-Holland 3265 BV",
    "addr:housenumber":"20",
    "addr:postcode":"3265 bv",
    "addr:street":"Voorstraat",
    "iso:country":"NL",
    "sg:address":"Voorstraat 20",
    "sg:city":"Piershil",
    "sg:orig_category":"Fruit And Groenten Gh",
    "sg:phone":"+31 186 691 344",
    "sg:postcode":"3265 BV",
    "sg:province":"Zuid-Holland",
    "wof:name":"Aardappelhandel A.J.Verhorst Bv",
    "wof:placetype":"venue"
},
  "geometry": {"coordinates":[4.313837,51.793491],"type":"Point"}
}