{
  "type": "Feature",
  "properties": {
    "iso:country":"NL",
    "sg:address":"Marsmanlaan 1",
    "sg:city":"Uithoorn",
    "sg:orig_category":"Kappers",
    "sg:phone":"+31 297 566 447",
    "sg:postcode":"1422 CG",
    "sg:province":"Noord-Holland",
    "wof:name":"A.S. Hamstra",
    "wof:placetype":"venue"
},
  "geometry": {"coordinates":[4.8310379982,52.2445755005],"type":"Point"}
}