{
  "type": "Feature",
  "properties": {
    "iso:country":"NL",
    "sg:address":"S Stevinwg 2308",
    "sg:city":"Arnhem",
    "sg:orig_category":"Elektronica - Ontwikkeling En Groothandel",
    "sg:phone":"+31 26 362 2022",
    "sg:postcode":"6827 BS",
    "sg:province":"Gelderland",
    "sg:website":"http://www.carvision.nl",
    "wof:name":"Carvision",
    "wof:placetype":"venue"
},
  "geometry": {"coordinates":[5.94331,51.971031],"type":"Point"}
}