{
  "type": "Feature",
  "properties": {
    "addr:full":"Nw Koekoekstr 37 Utrecht Utrecht 3514 EB",
    "addr:housenumber":"37",
    "addr:postcode":"3514 eb",
    "iso:country":"NL",
    "sg:address":"Nw Koekoekstr 37",
    "sg:city":"Utrecht",
    "sg:orig_category":"Schilders",
    "sg:phone":"+31 6 53885505",
    "sg:postcode":"3514 EB",
    "sg:province":"Utrecht",
    "wof:name":"Quast",
    "wof:placetype":"venue"
},
  "geometry": {"coordinates":[5.119354,52.098099],"type":"Point"}
}