{
  "type": "Feature",
  "properties": {
    "iso:country":"NL",
    "sg:address":"Bergstraat 19",
    "sg:city":"Deventer",
    "sg:orig_category":"Juridische Dienstverlening",
    "sg:phone":"+31 570 644 454",
    "sg:postcode":"7411 ER",
    "sg:province":"NL.08",
    "wof:name":"Mr.Drs. A. Reinders-Subsidium",
    "wof:placetype":"venue"
},
  "geometry": {"coordinates":[6.161798,52.252193],"type":"Point"}
}