{
  "type": "Feature",
  "properties": {
    "addr:full":"Lobbendk 16 Houten Utrecht 3991 EC",
    "addr:housenumber":"16",
    "addr:postcode":"3991 ec",
    "addr:street":"Lobbendk",
    "iso:country":"NL",
    "sg:address":"Lobbendk 16",
    "sg:city":"Houten",
    "sg:orig_category":"Scholen Voor Basisonderwijs",
    "sg:phone":"+31 30 637 2100",
    "sg:postcode":"3991 EC",
    "sg:province":"Utrecht",
    "wof:name":"Bogerman Reform, Johannes",
    "wof:placetype":"venue"
},
  "geometry": {"coordinates":[5.161892,52.030304],"type":"Point"}
}