{
  "type": "Feature",
  "properties": {
    "addr:full":"Westeinde 16 Amsterdam North Holland 1017 ZP",
    "addr:housenumber":"16",
    "addr:postcode":"1017 zp",
    "addr:street":"Westeinde",
    "iso:country":"NL",
    "sg:address":"Westeinde 16",
    "sg:city":"Amsterdam",
    "sg:orig_category":"Boekenuitgeverijen",
    "sg:phone":"+31 20 625 6087",
    "sg:postcode":"1017 ZP",
    "sg:province":"North Holland",
    "wof:name":"Uitgeverij Jan Mets",
    "wof:placetype":"venue"
},
  "geometry": {"coordinates":[4.898709,52.35873],"type":"Point"}
}