{
  "type": "Feature",
  "properties": {
    "addr:full":"Grt Kr Elleboog 18-20 Groningen Groningen 9712 BK",
    "addr:housenumber":"18-20",
    "addr:postcode":"9712 bk",
    "addr:street":"Kr Elleboog",
    "iso:country":"NL",
    "sg:address":"Grt Kr Elleboog 18-20",
    "sg:city":"Groningen",
    "sg:orig_category":"Verlichting",
    "sg:phone":"+31 50 313 0796",
    "sg:postcode":"9712 BK",
    "sg:province":"Groningen",
    "wof:name":"Lighthouse",
    "wof:placetype":"venue"
},
  "geometry": {"coordinates":[6.562162,53.218014],"type":"Point"}
}