{
  "type": "Feature",
  "properties": {
    "addr:full":"Haringweg 31 Bunschoten Spakenburg Utrecht 3751 BG",
    "addr:housenumber":"31",
    "addr:postcode":"3751",
    "addr:street":"Haringweg",
    "iso:country":"NL",
    "sg:address":"Haringweg 31",
    "sg:city":"Bunschoten Spakenburg",
    "sg:orig_category":"Visspeciaalzaken",
    "sg:phone":"+31 33 298 3626",
    "sg:postcode":"3751 BG",
    "sg:province":"Utrecht",
    "wof:name":"Van De Groep Bv",
    "wof:placetype":"venue"
},
  "geometry": {"coordinates":[5.387058,52.251614],"type":"Point"}
}