{
  "type": "Feature",
  "properties": {
    "addr:full":"Oosterpk 54 Amsterdam Noord-Holland 1092 AP",
    "addr:housenumber":"54",
    "addr:postcode":"1092 ap",
    "addr:street":"Oosterpk",
    "iso:country":"NL",
    "sg:address":"Oosterpk 54",
    "sg:city":"Amsterdam",
    "sg:orig_category":"Grafisch Ontwerpers",
    "sg:phone":"+31 20 623 2499",
    "sg:postcode":"1092 AP",
    "sg:province":"Noord-Holland",
    "sg:website":"http://www.olykan.nl",
    "wof:name":"Olykan Studio Bv",
    "wof:placetype":"venue"
},
  "geometry": {"coordinates":[4.92155,52.358921],"type":"Point"}
}