{
  "type": "Feature",
  "properties": {
    "iso:country":"NL",
    "sg:address":"Bilderdam 36",
    "sg:city":"Leimuiden",
    "sg:orig_category":"Kalligrafische Ateliers",
    "sg:phone":"+31 172 508 566",
    "sg:postcode":"2451 CX",
    "sg:province":"Zuid-Holland",
    "wof:name":"Stilos Bilderdam",
    "wof:placetype":"venue"
},
  "geometry": {"coordinates":[4.7230210304,52.2149887085],"type":"Point"}
}