{
  "type": "Feature",
  "properties": {
    "addr:full":"Primulastraat 2 Rosmalen North Brabant 5241 AP",
    "addr:housenumber":"2",
    "addr:postcode":"5241 ap",
    "addr:street":"Primulastraat",
    "iso:country":"NL",
    "sg:address":"Primulastraat 2",
    "sg:city":"Rosmalen",
    "sg:orig_category":"Vertaal- And Tolkenbureaus",
    "sg:phone":"+31 73 521 3329",
    "sg:postcode":"5241 AP",
    "sg:province":"North Brabant",
    "wof:name":"Vertaalburo Cagdas",
    "wof:placetype":"venue"
},
  "geometry": {"coordinates":[5.354617,51.713764],"type":"Point"}
}