{
  "type": "Feature",
  "properties": {
    "addr:full":"Gorecht O 167 Hoogezand Groningen 9603 AE",
    "addr:housenumber":"167",
    "addr:postcode":"9603 ae",
    "iso:country":"NL",
    "sg:address":"Gorecht O 167",
    "sg:city":"Hoogezand",
    "sg:orig_category":"Artsen - Huisartsen",
    "sg:phone":"+31 598 320 254",
    "sg:postcode":"9603 AE",
    "sg:province":"Groningen",
    "wof:name":"Smilde, B J",
    "wof:placetype":"venue"
},
  "geometry": {"coordinates":[6.756076,53.153156],"type":"Point"}
}