{
  "type": "Feature",
  "properties": {
    "addr:full":"Roelantstraat 10 Amsterdam Noord-Holland 1055 LP",
    "addr:housenumber":"10",
    "addr:postcode":"1055 lp",
    "addr:street":"Roelantstraat",
    "iso:country":"NL",
    "sg:address":"Roelantstraat 10",
    "sg:city":"Amsterdam",
    "sg:orig_category":"Wasserettes And Stomerijen",
    "sg:phone":"+31 20 684 9294",
    "sg:postcode":"1055 LP",
    "sg:province":"Noord-Holland",
    "wof:name":"Erasmus Wasserette",
    "wof:placetype":"venue"
},
  "geometry": {"coordinates":[4.8570542336,52.3771591187],"type":"Point"}
}