{
  "type": "Feature",
  "properties": {
    "addr:full":"Scheepswerfstraat 12 Stadskanaal Groningen 9501 NP",
    "addr:housenumber":"12",
    "addr:postcode":"9501 np",
    "addr:street":"Scheepswerfstraat",
    "iso:country":"NL",
    "sg:address":"Scheepswerfstraat 12",
    "sg:city":"Stadskanaal",
    "sg:orig_category":"Goederenvervoer Over De Weg",
    "sg:phone":"+31 599 648 912",
    "sg:postcode":"9501 NP",
    "sg:province":"Groningen",
    "wof:name":"Rima Vof",
    "wof:placetype":"venue"
},
  "geometry": {"coordinates":[6.896588,53.023159],"type":"Point"}
}