{
  "type": "Feature",
  "properties": {
    "addr:full":"Middenweg 27 Limmen Noord-Holland 1906 AP",
    "addr:housenumber":"27",
    "addr:postcode":"1906 ap",
    "addr:street":"Middenweg",
    "iso:country":"NL",
    "sg:address":"Middenweg 27",
    "sg:city":"Limmen",
    "sg:orig_category":"Vaste And Vloeibare Brandstoffen",
    "sg:phone":"+31 72 505 3808",
    "sg:postcode":"1906 AP",
    "sg:province":"Noord-Holland",
    "wof:name":"Zonneveld Oliehandel",
    "wof:placetype":"venue"
},
  "geometry": {"coordinates":[4.694664,52.569809],"type":"Point"}
}