{
  "type": "Feature",
  "properties": {
    "addr:full":"Nijverheidsweg-Noord 95 Amersfoort Utrecht 3812 PL",
    "addr:housenumber":"95",
    "addr:postcode":"3812 pl",
    "addr:street":"Nijverheidsweg-Noord",
    "iso:country":"NL",
    "sg:address":"Nijverheidsweg-Noord 95",
    "sg:city":"Amersfoort",
    "sg:orig_category":"Medische And Orthopedische Artikelen",
    "sg:phone":"+31 33 461 9699",
    "sg:postcode":"3812 PL",
    "sg:province":"Utrecht",
    "wof:name":"Welzorg Amersfoort Revalidatietechniek",
    "wof:placetype":"venue"
},
  "geometry": {"coordinates":[5.351997,52.170918],"type":"Point"}
}