{
  "type": "Feature",
  "properties": {
    "addr:full":"Achterstraat 30 Lekkerkerk Zuid-Holland 2941 AB",
    "addr:housenumber":"30",
    "addr:postcode":"2941 ab",
    "addr:street":"Achterstraat",
    "iso:country":"NL",
    "sg:address":"Achterstraat 30",
    "sg:city":"Lekkerkerk",
    "sg:orig_category":"Geluidsopnamen",
    "sg:phone":"+31 180 664 459",
    "sg:postcode":"2941 AB",
    "sg:province":"Zuid-Holland",
    "wof:name":"Compact Studio",
    "wof:placetype":"venue"
},
  "geometry": {"coordinates":[4.684383,51.895218],"type":"Point"}
}