{
  "type": "Feature",
  "properties": {
    "addr:full":"Ons Doelstraat 81 Boxtel North Brabant 5281 GX",
    "addr:housenumber":"81",
    "addr:postcode":"5281 gx",
    "addr:street":"Ons Doelstraat",
    "iso:country":"NL",
    "sg:address":"Ons Doelstraat 81",
    "sg:city":"Boxtel",
    "sg:classifiers":[
        {
            "category":"Professional",
            "subcategory":"Accounting & Tax Preparation",
            "type":"Services"
        }
    ],
    "sg:phone":"+31 411 672 420",
    "sg:postcode":"5281 GX",
    "sg:province":"North Brabant",
    "sg:tags":[
        "accountant"
    ],
    "wof:name":"Accountantskantoor Zwanenberg Bv",
    "wof:placetype":"venue"
},
  "geometry": {"coordinates":[5.319145,51.588184],"type":"Point"}
}