{
  "type": "Feature",
  "properties": {
    "addr:full":"Dukaatpassage 33 Lelystad NL. 8232 GC",
    "addr:housenumber":"33",
    "addr:postcode":"8232 gc",
    "addr:street":"Dukaatpassage;Nl.",
    "iso:country":"NL",
    "sg:address":"Dukaatpassage 33",
    "sg:city":"Lelystad",
    "sg:orig_category":"Bioscopen",
    "sg:phone":"+31 320 226 562",
    "sg:postcode":"8232 GC",
    "sg:province":"NL.",
    "wof:name":"Alpha",
    "wof:placetype":"venue"
},
  "geometry": {"coordinates":[5.475639,52.508297],"type":"Point"}
}