{
  "type": "Feature",
  "properties": {
    "addr:full":"Straussln 311 S Gravenhage Zuid-Holland 2551 NE",
    "addr:housenumber":"311;gravenhage;2551",
    "addr:postcode":"ne",
    "addr:street":"S",
    "iso:country":"NL",
    "sg:address":"Straussln 311",
    "sg:city":"S Gravenhage",
    "sg:orig_category":"Adviesbureaus Bedrijfsorganisatie",
    "sg:phone":"+31 70 368 0088",
    "sg:postcode":"2551 NE",
    "sg:province":"Zuid-Holland",
    "wof:name":"Naeeda",
    "wof:placetype":"venue"
},
  "geometry": {"coordinates":[4.23775,52.058601],"type":"Point"}
}