{
  "type": "Feature",
  "properties": {
    "iso:country":"NL",
    "sg:address":"N Beetsstr 85",
    "sg:city":"Groningen",
    "sg:orig_category":"Administratie- En Boekhoudkantoren",
    "sg:phone":"+31 50 526 9653",
    "sg:postcode":"9721 RL",
    "sg:province":"Groningen",
    "wof:name":"Ad Damen Administratiekantoor",
    "wof:placetype":"venue"
},
  "geometry": {"coordinates":[6.565365,53.193653],"type":"Point"}
}