{
  "type": "Feature",
  "properties": {
    "addr:full":"Fokkerstraat 19 Veenendaal Utrecht 3905  K",
    "addr:housenumber":"19",
    "addr:postcode":"3905 k",
    "addr:street":"Fokkerstraat",
    "iso:country":"NL",
    "sg:address":"Fokkerstraat 19",
    "sg:city":"Veenendaal",
    "sg:orig_category":"Elektronische Bedrijfsinstallaties",
    "sg:phone":"+31 318 540 611",
    "sg:postcode":"3905  K",
    "sg:province":"Utrecht",
    "wof:name":"Deltatechniek",
    "wof:placetype":"venue"
},
  "geometry": {"coordinates":[5.56012,52.03891],"type":"Point"}
}