{
  "type": "Feature",
  "properties": {
    "addr:full":"De Bouwing 81 Dreumel Gelderland 6621 AZ",
    "addr:housenumber":"81",
    "addr:postcode":"6621",
    "addr:street":"De Bouwing;Gelderland",
    "iso:country":"NL",
    "sg:address":"De Bouwing 81",
    "sg:city":"Dreumel",
    "sg:orig_category":"Autokeuringen",
    "sg:phone":"+31 487 572 109",
    "sg:postcode":"6621 AZ",
    "sg:province":"Gelderland",
    "wof:name":"Vof C.R.J. Lemmers",
    "wof:placetype":"venue"
},
  "geometry": {"coordinates":[5.427764,51.848839],"type":"Point"}
}