{
  "type": "Feature",
  "properties": {
    "iso:country":"NL",
    "sg:address":"Vd Valk Boumanln 35",
    "sg:city":"Woerden",
    "sg:orig_category":"Hypotheken",
    "sg:phone":"+31 348 423 670",
    "sg:postcode":"3446 GG",
    "sg:province":"Utrecht",
    "wof:name":"Schans, De",
    "wof:placetype":"venue"
},
  "geometry": {"coordinates":[4.895296,52.08223],"type":"Point"}
}