{
  "type": "Feature",
  "properties": {
    "addr:full":"Magdalenastr 3 Goes Ohio 4461 AL",
    "addr:housenumber":"3",
    "addr:postcode":"4461 al",
    "addr:street":"Magdalenastr",
    "iso:country":"NL",
    "sg:address":"Magdalenastr 3",
    "sg:city":"Goes",
    "sg:orig_category":"Postzegels",
    "sg:phone":"+31 113 227 162",
    "sg:postcode":"4461 AL",
    "sg:province":"Ohio",
    "wof:name":"Daub, M",
    "wof:placetype":"venue"
},
  "geometry": {"coordinates":[-83.914169,39.768833],"type":"Point"}
}