{
  "type": "Feature",
  "properties": {
    "addr:full":"Houtse Parallelwg 10 Helmond Noord-Brabant 5706 AA",
    "addr:housenumber":"10",
    "addr:postcode":"5706 aa",
    "addr:street":"Houtse Parallelwg",
    "iso:country":"NL",
    "sg:address":"Houtse Parallelwg 10",
    "sg:city":"Helmond",
    "sg:orig_category":"Bijouterie?n - Fabrieken En Groothandel",
    "sg:phone":"+31 492 535 209",
    "sg:postcode":"5706 AA",
    "sg:province":"Noord-Brabant",
    "wof:name":"Natural Leathergoods Store",
    "wof:placetype":"venue"
},
  "geometry": {"coordinates":[5.652427,51.472919],"type":"Point"}
}