{
  "type": "Feature",
  "properties": {
    "addr:full":"Kastanjeln 18N Ridderkerk Zuid-Holland 2982 CM",
    "addr:housenumber":"18n",
    "addr:postcode":"2982 cm",
    "addr:street":"Kastanjeln",
    "iso:country":"NL",
    "sg:address":"Kastanjeln 18N",
    "sg:city":"Ridderkerk",
    "sg:classifiers":[
        {
            "category":"Professional",
            "subcategory":"Management & Consulting",
            "type":"Services"
        }
    ],
    "sg:phone":"+31 180 462 222",
    "sg:postcode":"2982 CM",
    "sg:province":"Zuid-Holland",
    "sg:tags":[
        "relation",
        "adviesbureaus",
        "public"
    ],
    "wof:name":"Npr",
    "wof:placetype":"venue"
},
  "geometry": {"coordinates":[4.588473,51.876415],"type":"Point"}
}