{
  "type": "Feature",
  "properties": {
    "iso:country":"NL",
    "sg:address":"St Amandusstr 23",
    "sg:city":"Maastricht",
    "sg:orig_category":"Vertaalbureaus",
    "sg:phone":"+31 43 321 6159",
    "sg:postcode":"6212 CL",
    "sg:province":"Limburg",
    "wof:name":"Medical Translations",
    "wof:placetype":"venue"
},
  "geometry": {"coordinates":[5.692718,50.837879],"type":"Point"}
}