{
  "type": "Feature",
  "properties": {
    "addr:full":"Gedempte Gracht 13 Zaandam Noord-Holland 1506 CA",
    "addr:housenumber":"13",
    "addr:postcode":"1506 ca",
    "addr:street":"Gedempte Gracht",
    "iso:country":"NL",
    "sg:address":"Gedempte Gracht 13",
    "sg:city":"Zaandam",
    "sg:classifiers":[
        {
            "category":"Fast Food",
            "type":"Food & Drink"
        }
    ],
    "sg:phone":"+31 75 615 6555",
    "sg:postcode":"1506 CA",
    "sg:province":"Noord-Holland",
    "sg:tags":[
        "afhaal",
        "restaurant"
    ],
    "wof:name":"Eric'S Automatiek",
    "wof:placetype":"venue"
},
  "geometry": {"coordinates":[4.823058,52.439732],"type":"Point"}
}