{
  "type": "Feature",
  "properties": {
    "addr:full":"Ludinge 4 Zuidlaren Drenthe 9471 JD",
    "addr:housenumber":"4",
    "addr:postcode":"9471 jd",
    "addr:street":"Ludinge",
    "iso:country":"NL",
    "sg:address":"Ludinge 4",
    "sg:city":"Zuidlaren",
    "sg:orig_category":"Verenigingen En Stichtingen",
    "sg:phone":"+31 50 409 1187",
    "sg:postcode":"9471 JD",
    "sg:province":"Drenthe",
    "wof:name":"Trias Zuidlaren, Sticht",
    "wof:placetype":"venue"
},
  "geometry": {"coordinates":[6.670158,53.091812],"type":"Point"}
}