{
  "type": "Feature",
  "properties": {
    "addr:full":"Rijssensestraat 51 Nijverdal Overijssel 7442 MR",
    "addr:housenumber":"51",
    "addr:postcode":"7442 mr",
    "addr:street":"Rijssensestraat",
    "iso:country":"NL",
    "sg:address":"Rijssensestraat 51",
    "sg:city":"Nijverdal",
    "sg:orig_category":"Fotostudio'S And Fotografen",
    "sg:phone":"+31 548 612 706",
    "sg:postcode":"7442 MR",
    "sg:province":"Overijssel",
    "wof:name":"Foto Eerdmans",
    "wof:placetype":"venue"
},
  "geometry": {"coordinates":[6.460422,52.363003],"type":"Point"}
}