{
  "type": "Feature",
  "properties": {
    "addr:full":"Zilkerbinnenweg 66 De Zilk Zuid-Holland 2191 AE",
    "addr:housenumber":"66",
    "addr:postcode":"2191 ae",
    "addr:street":"Zilkerbinnenweg",
    "iso:country":"NL",
    "sg:address":"Zilkerbinnenweg 66",
    "sg:city":"De Zilk",
    "sg:orig_category":"Bruidskleding",
    "sg:phone":"+31 252 515 995",
    "sg:postcode":"2191 AE",
    "sg:province":"Zuid-Holland",
    "wof:name":"Miando",
    "wof:placetype":"venue"
},
  "geometry": {"coordinates":[4.540901,52.296623],"type":"Point"}
}