{
  "type": "Feature",
  "properties": {
    "addr:full":"W V Haemstedestr 40B Rotterdam South Holland 3021 SZ",
    "addr:housenumber":"40b",
    "addr:postcode":"3021 sz",
    "addr:street":"W V Haemstedestr",
    "iso:country":"NL",
    "sg:address":"W V Haemstedestr 40B",
    "sg:city":"Rotterdam",
    "sg:orig_category":"Postkantoren",
    "sg:phone":"+31 10 477 1431",
    "sg:postcode":"3021 SZ",
    "sg:province":"South Holland",
    "sg:website":"http://www.postkantoor.nl",
    "wof:name":"Postkantoor",
    "wof:placetype":"venue"
},
  "geometry": {"coordinates":[4.45925,51.916531],"type":"Point"}
}