{
  "type": "Feature",
  "properties": {
    "addr:full":"Arendstraat 2 Oss Virginia 5341 RR",
    "addr:housenumber":"2",
    "addr:postcode":"5341 rr",
    "addr:street":"Arendstraat",
    "iso:country":"NL",
    "sg:address":"Arendstraat 2",
    "sg:city":"Oss",
    "sg:orig_category":"Diverse Grafische Activiteiten",
    "sg:phone":"+31 412 690 953",
    "sg:postcode":"5341 RR",
    "sg:province":"Virginia",
    "wof:name":"Design Gallery",
    "wof:placetype":"venue"
},
  "geometry": {"coordinates":[-77.235214,38.312599],"type":"Point"}
}