{
  "type": "Feature",
  "properties": {
    "addr:full":"Abraham Van De Hulstlaan 59 Bennebroek North Holland 2121 XR",
    "addr:housenumber":"59",
    "addr:postcode":"2121 xr",
    "addr:street":"Abraham Van De Hulstlaan",
    "iso:country":"NL",
    "sg:address":"Abraham Van De Hulstlaan 59",
    "sg:city":"Bennebroek",
    "sg:orig_category":"Boekhouders",
    "sg:phone":"+31 23 584 6835",
    "sg:postcode":"2121 XR",
    "sg:province":"North Holland",
    "wof:name":"Ksa Administraties",
    "wof:placetype":"venue"
},
  "geometry": {"coordinates":[4.602462,52.317032],"type":"Point"}
}