{
  "type": "Feature",
  "properties": {
    "addr:full":"Bloemakkers 37 Gieten Provincie Drenthe 9461 GX",
    "addr:housenumber":"37",
    "addr:postcode":"9461 gx",
    "addr:street":"Bloemakkers;Provincie Drenthe",
    "iso:country":"NL",
    "sg:address":"Bloemakkers 37",
    "sg:city":"Gieten",
    "sg:orig_category":"Autokeuringen",
    "sg:phone":"+31 592 264 146",
    "sg:postcode":"9461 GX",
    "sg:province":"Provincie Drenthe",
    "wof:name":"Meijer Autowasstraat Vof",
    "wof:placetype":"venue"
},
  "geometry": {"coordinates":[6.763011,52.996597],"type":"Point"}
}