{
  "type": "Feature",
  "properties": {
    "addr:full":"Lefebureplein 1 Oudewater Utrecht 3421 BG",
    "addr:housenumber":"1",
    "addr:postcode":"3421",
    "addr:street":"Lefebureplein",
    "iso:country":"NL",
    "sg:address":"Lefebureplein 1",
    "sg:city":"Oudewater",
    "sg:orig_category":"Kinderopvang Behalve Thuis",
    "sg:phone":"+31 348 561 010",
    "sg:postcode":"3421 BG",
    "sg:province":"Utrecht",
    "wof:name":"Kindercentrum Jip En Janneke",
    "wof:placetype":"venue"
},
  "geometry": {"coordinates":[4.868412,52.025063],"type":"Point"}
}