{
  "type": "Feature",
  "properties": {
    "addr:full":"C J Van Houtenlaan 1 Weesp Noord-Holland 1381 CN",
    "addr:housenumber":"1",
    "addr:postcode":"1381 cn",
    "addr:street":"C;Van Houtenlaan",
    "iso:country":"NL",
    "sg:address":"C J Van Houtenlaan 1",
    "sg:city":"Weesp",
    "sg:orig_category":"Makelaars In Onroerend Goed",
    "sg:phone":"+31 294 413 209",
    "sg:postcode":"1381 CN",
    "sg:province":"Noord-Holland",
    "wof:name":"D. De Haan Makelaardij In Onroerende Goe",
    "wof:placetype":"venue"
},
  "geometry": {"coordinates":[5.038881,52.304783],"type":"Point"}
}