{
  "type": "Feature",
  "properties": {
    "addr:full":"Klaproosln 46 Groningen Groningen 9713 SL",
    "addr:housenumber":"46",
    "addr:postcode":"9713 sl",
    "addr:street":"Klaproosln",
    "iso:country":"NL",
    "sg:address":"Klaproosln 46",
    "sg:city":"Groningen",
    "sg:orig_category":"Administratie- En Boekhoudkantoren",
    "sg:phone":"+31 50 571 9515",
    "sg:postcode":"9713 SL",
    "sg:province":"Groningen",
    "wof:name":"Blaauw, L",
    "wof:placetype":"venue"
},
  "geometry": {"coordinates":[6.580896,53.2258],"type":"Point"}
}