{
  "type": "Feature",
  "properties": {
    "addr:full":"Raadhuisstraat 38 Oud Vossemeer Zeeland 4698 AK",
    "addr:housenumber":"38",
    "addr:postcode":"4698 ak",
    "addr:street":"Raadhuisstraat",
    "iso:country":"NL",
    "sg:address":"Raadhuisstraat 38",
    "sg:city":"Oud Vossemeer",
    "sg:orig_category":"Verhuur Bouwmachines",
    "sg:phone":"+31 166 672 105",
    "sg:postcode":"4698 AK",
    "sg:province":"Zeeland",
    "wof:name":"E.M. Hommel-Veraart",
    "wof:placetype":"venue"
},
  "geometry": {"coordinates":[4.198477,51.570095],"type":"Point"}
}