{
  "type": "Feature",
  "properties": {
    "iso:country":"NL",
    "sg:address":"Noorderstr 76-76A",
    "sg:city":"Amsterdam",
    "sg:classifiers":[
        {
            "category":"Retail",
            "subcategory":"Auto Repair",
            "type":"Services"
        }
    ],
    "sg:phone":"+31 20 623 7028",
    "sg:postcode":"1017 TW",
    "sg:province":"Noord-Holland",
    "sg:tags":[
        "garage"
    ],
    "wof:name":"Recht, Garage 'T",
    "wof:placetype":"venue"
},
  "geometry": {"coordinates":[4.894965,52.360931],"type":"Point"}
}