{
  "type": "Feature",
  "properties": {
    "addr:full":"Boterweg 43 'S Hertogenbosch Noord-Brabant 5213 HS",
    "addr:housenumber":"43",
    "addr:postcode":"5213 hs",
    "addr:street":"Boterweg;' S",
    "iso:country":"NL",
    "sg:address":"Boterweg 43",
    "sg:city":"'S Hertogenbosch",
    "sg:orig_category":"Fotostudio'S And Fotografen",
    "sg:phone":"+31 73 614 2081",
    "sg:postcode":"5213 HS",
    "sg:province":"Noord-Brabant",
    "wof:name":"G. De Graaf",
    "wof:placetype":"venue"
},
  "geometry": {"coordinates":[5.3334,51.698158],"type":"Point"}
}