{
  "type": "Feature",
  "properties": {
    "addr:full":"Marktstr 164 Hoensbroek Limburg 6431 LT",
    "addr:housenumber":"164",
    "addr:postcode":"6431 lt",
    "addr:street":"Hoensbroek Limburg",
    "iso:country":"NL",
    "sg:address":"Marktstr 164",
    "sg:city":"Hoensbroek",
    "sg:orig_category":"Elektrotechnische Artikelen",
    "sg:phone":"+31 45 523 2038",
    "sg:postcode":"6431 LT",
    "sg:province":"Limburg",
    "wof:name":"Willory",
    "wof:placetype":"venue"
},
  "geometry": {"coordinates":[5.92754,50.923481],"type":"Point"}
}