{
  "type": "Feature",
  "properties": {
    "iso:country":"NL",
    "sg:address":"Kasteelhof 2",
    "sg:city":"Kessel Lb",
    "sg:orig_category":"Woningbouwverenigingen",
    "sg:phone":"+31 77 462 2376",
    "sg:postcode":"5995 BX",
    "sg:province":"Limburg",
    "wof:name":"Kessel",
    "wof:placetype":"venue"
},
  "geometry": {"coordinates":[6.0565972328,51.2913665771],"type":"Point"}
}