{
  "type": "Feature",
  "properties": {
    "addr:full":"Westeind 2 Norg Drenthe 9331 CB",
    "addr:housenumber":"2",
    "addr:postcode":"9331 cb",
    "addr:street":"Westeind",
    "iso:country":"NL",
    "sg:address":"Westeind 2",
    "sg:city":"Norg",
    "sg:orig_category":"Goudsmeden En Zilversmeden",
    "sg:phone":"+31 592 613 876",
    "sg:postcode":"9331 CB",
    "sg:province":"Drenthe",
    "sg:website":"http://www.edelsmederij-oberon.nl",
    "wof:name":"Oberon Edelsmederij",
    "wof:placetype":"venue"
},
  "geometry": {"coordinates":[6.459459,53.066349],"type":"Point"}
}