{
  "type": "Feature",
  "properties": {
    "addr:full":"Haven 54 Volendam Noord-Holland 1131 ES",
    "addr:housenumber":"54",
    "addr:postcode":"1131 es",
    "addr:street":"Haven",
    "iso:country":"NL",
    "sg:address":"Haven 54",
    "sg:city":"Volendam",
    "sg:classifiers":[
        {
            "category":"Shopping",
            "subcategory":"Gifts & Souvenirs",
            "type":"Retail Goods"
        }
    ],
    "sg:phone":"+31 299 363 718",
    "sg:postcode":"1131 ES",
    "sg:province":"Noord-Holland",
    "sg:tags":[
        "geschenken"
    ],
    "wof:name":"J. Smit",
    "wof:placetype":"venue"
},
  "geometry": {"coordinates":[5.076311,52.494282],"type":"Point"}
}