{
  "type": "Feature",
  "properties": {
    "addr:full":"Wintererf 1 Alphen A/D Rijn South Holland 2408 NH",
    "addr:housenumber":"1",
    "addr:postcode":"2408 nh",
    "addr:street":"Wintererf",
    "iso:country":"NL",
    "sg:address":"Wintererf 1",
    "sg:city":"Alphen A/D Rijn",
    "sg:orig_category":"Bedrijfs- And Managementsconsultants",
    "sg:phone":"+31 172 424 492",
    "sg:postcode":"2408 NH",
    "sg:province":"South Holland",
    "wof:name":"Cambrium",
    "wof:placetype":"venue"
},
  "geometry": {"coordinates":[4.652222,52.120876],"type":"Point"}
}