{
  "type": "Feature",
  "properties": {
    "iso:country":"NL",
    "sg:address":"Nieuwkuyksestr 128",
    "sg:city":"Nieuwkuyk",
    "sg:orig_category":"Schilders",
    "sg:phone":"+31 73 511 5011",
    "sg:postcode":"5253 AK",
    "sg:province":"Noord-Brabant",
    "wof:name":"Bert Van Heesbeen",
    "wof:placetype":"venue"
},
  "geometry": {"coordinates":[5.176167,51.690586],"type":"Point"}
}