{
  "type": "Feature",
  "properties": {
    "addr:full":"Leeuwenstraat 42 Hilversum North Holland 1211 EW",
    "addr:housenumber":"42",
    "addr:postcode":"1211 ew",
    "addr:street":"Leeuwenstraat",
    "iso:country":"NL",
    "sg:address":"Leeuwenstraat 42",
    "sg:city":"Hilversum",
    "sg:orig_category":"Boekenuitgeverijen",
    "sg:phone":"+31 35 624 7236",
    "sg:postcode":"1211 EW",
    "sg:province":"North Holland",
    "wof:name":"Boekhandel V/H Wout Vuyk",
    "wof:placetype":"venue"
},
  "geometry": {"coordinates":[5.178973,52.226025],"type":"Point"}
}