{
  "type": "Feature",
  "properties": {
    "addr:full":"G Lokkenstr 20 Marknesse Flevoland 8316 AE",
    "addr:housenumber":"20",
    "addr:postcode":"8316 ae",
    "addr:street":"Flevoland",
    "iso:country":"NL",
    "sg:address":"G Lokkenstr 20",
    "sg:city":"Marknesse",
    "sg:orig_category":"Oldtimers",
    "sg:phone":"+31 527 203 722",
    "sg:postcode":"8316 AE",
    "sg:province":"Flevoland",
    "wof:name":"Wageman",
    "wof:placetype":"venue"
},
  "geometry": {"coordinates":[5.8664288521,52.7093429565],"type":"Point"}
}