{
  "type": "Feature",
  "properties": {
    "iso:country":"NL",
    "sg:address":"G Lokkenstr 20",
    "sg:city":"Marknesse",
    "sg:orig_category":"Oldtimers",
    "sg:phone":"+31 527 203 722",
    "sg:postcode":"8316 AE",
    "sg:province":"Flevoland",
    "wof:name":"Wageman",
    "wof:placetype":"venue"
},
  "geometry": {"coordinates":[5.8664288521,52.7093429565],"type":"Point"}
}