{
  "type": "Feature",
  "properties": {
    "addr:full":"Vijzelweg 25 Waalwijk Noord-Brabant 5145 NK",
    "addr:housenumber":"25",
    "addr:postcode":"5145 nk",
    "addr:street":"Vijzelweg",
    "iso:country":"NL",
    "sg:address":"Vijzelweg 25",
    "sg:city":"Waalwijk",
    "sg:orig_category":"Kantoor- And Schoolbenodigdheden Gh",
    "sg:phone":"+31 416 330 503",
    "sg:postcode":"5145 NK",
    "sg:province":"Noord-Brabant",
    "wof:name":"Amas Export Bv",
    "wof:placetype":"venue"
},
  "geometry": {"coordinates":[5.0420651436,51.6971817017],"type":"Point"}
}