{
  "type": "Feature",
  "properties": {
    "addr:full":"V Nesstr 31 Alphen Aan Den Ryn Zuid-Holland 2404 AV",
    "addr:housenumber":"31",
    "addr:postcode":"2404 av",
    "addr:street":"Aan Den Ryn",
    "iso:country":"NL",
    "sg:address":"V Nesstr 31",
    "sg:city":"Alphen Aan Den Ryn",
    "sg:orig_category":"Wasmachines En Wasdrogers",
    "sg:phone":"+31 172 424 499",
    "sg:postcode":"2404 AV",
    "sg:province":"Zuid-Holland",
    "wof:name":"Hoogendoorn Witgoedservice",
    "wof:placetype":"venue"
},
  "geometry": {"coordinates":[4.6589207649,52.1271896362],"type":"Point"}
}