{
  "type": "Feature",
  "properties": {
    "addr:full":"Puntenburgerln 93 Amersfoort Utrecht 3812 CC",
    "addr:housenumber":"93",
    "addr:postcode":"3812 cc",
    "addr:street":"Puntenburgerln",
    "iso:country":"NL",
    "sg:address":"Puntenburgerln 93",
    "sg:city":"Amersfoort",
    "sg:orig_category":"Kinderopvang",
    "sg:phone":"+31 33 462 1780",
    "sg:postcode":"3812 CC",
    "sg:province":"Utrecht",
    "sg:website":"http://www.kruimelland.nl",
    "wof:name":"Kruimelland Kinderdagverblijf Bv",
    "wof:placetype":"venue"
},
  "geometry": {"coordinates":[5.374153,52.160591],"type":"Point"}
}