{
  "type": "Feature",
  "properties": {
    "addr:full":"Stationsstraat 28 Boxtel Noord-Brabant 5281 GD",
    "addr:housenumber":"28",
    "addr:postcode":"5281 gd",
    "addr:street":"Stationsstraat",
    "iso:country":"NL",
    "sg:address":"Stationsstraat 28",
    "sg:city":"Boxtel",
    "sg:orig_category":"Drukkerijen And Copyshops",
    "sg:phone":"+31 411 672 317",
    "sg:postcode":"5281 GD",
    "sg:province":"Noord-Brabant",
    "wof:name":"Drukkerij Tielen Bv",
    "wof:placetype":"venue"
},
  "geometry": {"coordinates":[5.322133,51.588154],"type":"Point"}
}