{
  "type": "Feature",
  "properties": {
    "iso:country":"NL",
    "sg:address":"Gemetstraat 72",
    "sg:city":"Purmerend",
    "sg:orig_category":"Timmerwerk Van Hout And Kunststof",
    "sg:phone":"+31 299 643 365",
    "sg:postcode":"1445 GH",
    "sg:province":"Noord-Holland",
    "wof:name":"Bouw En Renovatiebedrijf Tolsma",
    "wof:placetype":"venue"
},
  "geometry": {"coordinates":[4.986763,52.506542],"type":"Point"}
}