{
  "type": "Feature",
  "properties": {
    "addr:full":"Bergstr 105 Goirle North Brabant 5051 HB",
    "addr:housenumber":"105",
    "addr:postcode":"5051 hb",
    "addr:street":"Bergstr",
    "iso:country":"NL",
    "sg:address":"Bergstr 105",
    "sg:city":"Goirle",
    "sg:orig_category":"Hondenscholen",
    "sg:phone":"+31 6 47450249",
    "sg:postcode":"5051 HB",
    "sg:province":"North Brabant",
    "wof:name":"Vagebond, Hondenuitlaatservice",
    "wof:placetype":"venue"
},
  "geometry": {"coordinates":[5.062552,51.516159],"type":"Point"}
}