{
  "type": "Feature",
  "properties": {
    "iso:country":"NL",
    "sg:address":"It String 13",
    "sg:city":"Jirnsum",
    "sg:orig_category":"Pleziervaartuigen And Reparatie",
    "sg:phone":"+31 566 601 124",
    "sg:postcode":"9011 TA",
    "sg:province":"Provincie Friesland",
    "wof:name":"Aqualux Yacht Sharing En Charter",
    "wof:placetype":"venue"
},
  "geometry": {"coordinates":[5.802094,53.070286],"type":"Point"}
}