{
  "type": "Feature",
  "properties": {
    "addr:full":"It String 13 Jirnsum Provincie Friesland 9011 TA",
    "addr:housenumber":"13",
    "addr:postcode":"9011 ta",
    "addr:street":"It String;Provincie Friesland",
    "iso:country":"NL",
    "sg:address":"It String 13",
    "sg:city":"Jirnsum",
    "sg:orig_category":"Pleziervaartuigen And Reparatie",
    "sg:phone":"+31 566 601 124",
    "sg:postcode":"9011 TA",
    "sg:province":"Provincie Friesland",
    "wof:name":"Aqualux Yacht Sharing En Charter",
    "wof:placetype":"venue"
},
  "geometry": {"coordinates":[5.802094,53.070286],"type":"Point"}
}