{
  "type": "Feature",
  "properties": {
    "addr:full":"Bedrijfsweg 13 Nijmegen Gelderland 6541 DC",
    "addr:housenumber":"13",
    "addr:postcode":"6541",
    "addr:street":"Bedrijfsweg;Gelderland",
    "iso:country":"NL",
    "sg:address":"Bedrijfsweg 13",
    "sg:city":"Nijmegen",
    "sg:orig_category":"Diverse Consumentenartikelen Gh",
    "sg:phone":"+31 24 379 1541",
    "sg:postcode":"6541 DC",
    "sg:province":"Gelderland",
    "wof:name":"J.A.G. Van Zwaaij",
    "wof:placetype":"venue"
},
  "geometry": {"coordinates":[5.816952,51.840435],"type":"Point"}
}