{
  "type": "Feature",
  "properties": {
    "iso:country":"NL",
    "sg:address":"Amstellandlaan 80",
    "sg:city":"Weesp",
    "sg:orig_category":"Parfum And Cosmetica Gh",
    "sg:phone":"+31 294 480 134",
    "sg:postcode":"1382 CH",
    "sg:province":"Noord-Holland",
    "wof:name":"Parfums & Beaute Nederland Bv Divisie Biotherm",
    "wof:placetype":"venue"
},
  "geometry": {"coordinates":[5.025622,52.31041],"type":"Point"}
}