{
  "type": "Feature",
  "properties": {
    "iso:country":"NL",
    "sg:address":"Grt Markt 1",
    "sg:city":"Vlissingen",
    "sg:orig_category":"Scholen Voor Basisonderwijs",
    "sg:phone":"+31 118 441 122",
    "sg:postcode":"4381 JB",
    "sg:province":"Zeeland",
    "wof:name":"Branding, Openb De",
    "wof:placetype":"venue"
},
  "geometry": {"coordinates":[3.5737330914,51.4426460266],"type":"Point"}
}