{
  "type": "Feature",
  "properties": {
    "addr:full":"Kruisstraat 6 Waalwijk Noord-Brabant 5141 KL",
    "addr:housenumber":"6",
    "addr:postcode":"5141 kl",
    "addr:street":"Kruisstraat",
    "iso:country":"NL",
    "sg:address":"Kruisstraat 6",
    "sg:city":"Waalwijk",
    "sg:orig_category":"Boekhouders",
    "sg:phone":"+31 416 330 124",
    "sg:postcode":"5141 KL",
    "sg:province":"Noord-Brabant",
    "wof:name":"Administratiekantoor 3B",
    "wof:placetype":"venue"
},
  "geometry": {"coordinates":[5.049635,51.688759],"type":"Point"}
}