{
  "type": "Feature",
  "properties": {
    "iso:country":"NL",
    "sg:address":"Ankerstraat 37",
    "sg:city":"Oosterend Nh",
    "sg:orig_category":"Boekhouders",
    "sg:phone":"+31 222 318 602",
    "sg:postcode":"1794 BH",
    "sg:province":"Noord-Holland",
    "wof:name":"Administratiekantoor Ria Manse",
    "wof:placetype":"venue"
},
  "geometry": {"coordinates":[4.878886,53.083473],"type":"Point"}
}