{
  "type": "Feature",
  "properties": {
    "iso:country":"NL",
    "sg:address":"Schoterwg 27",
    "sg:city":"Haarlem",
    "sg:orig_category":"Zonweringen",
    "sg:phone":"+31 23 526 2425",
    "sg:postcode":"2021 HZ",
    "sg:province":"Noord-Holland",
    "sg:website":"http://www.handehaan.nl",
    "wof:name":"Haan, Han De",
    "wof:placetype":"venue"
},
  "geometry": {"coordinates":[4.640361,52.391521],"type":"Point"}
}