{
  "type": "Feature",
  "properties": {
    "addr:full":"Zwinstraat 66 Den Oever Noord-Holland 1779 BH",
    "addr:housenumber":"66",
    "addr:postcode":"1779 bh",
    "addr:street":"Zwinstraat",
    "iso:country":"NL",
    "sg:address":"Zwinstraat 66",
    "sg:city":"Den Oever",
    "sg:classifiers":[
        {
            "category":"Education",
            "subcategory":"Preschool",
            "type":"Public Place"
        }
    ],
    "sg:phone":"+31 227 512 276",
    "sg:postcode":"1779 BH",
    "sg:province":"Noord-Holland",
    "sg:tags":[
        "kleuteronderwijs",
        "basis-"
    ],
    "wof:name":"Christelijk Nationale School De Haven",
    "wof:placetype":"venue"
},
  "geometry": {"coordinates":[5.034242,52.934177],"type":"Point"}
}