{
  "type": "Feature",
  "properties": {
    "addr:full":"Hauwert 126 Hauwert North Holland 1691 EL",
    "addr:housenumber":"126;1691",
    "addr:postcode":"el",
    "addr:street":"Hauwert",
    "iso:country":"NL",
    "sg:address":"Hauwert 126",
    "sg:city":"Hauwert",
    "sg:orig_category":"Horeca-Inrichtingen En -Uitrustingen",
    "sg:phone":"+31 229 203 626",
    "sg:postcode":"1691 EL",
    "sg:province":"North Holland",
    "wof:name":"Stapel",
    "wof:placetype":"venue"
},
  "geometry": {"coordinates":[5.10906,52.71352],"type":"Point"}
}