{
  "type": "Feature",
  "properties": {
    "addr:full":"Zwart Janstr 144B Rotterdam South Holland 3035 AZ",
    "addr:housenumber":"144b",
    "addr:postcode":"3035 az",
    "iso:country":"NL",
    "sg:address":"Zwart Janstr 144B",
    "sg:city":"Rotterdam",
    "sg:orig_category":"Kappers",
    "sg:phone":"+31 10 465 0665",
    "sg:postcode":"3035 AZ",
    "sg:province":"South Holland",
    "wof:name":"Tussen De Oren",
    "wof:placetype":"venue"
},
  "geometry": {"coordinates":[4.474978,51.93412],"type":"Point"}
}