{
  "type": "Feature",
  "properties": {
    "iso:country":"NL",
    "sg:address":"Kettingstr 7",
    "sg:city":"Emmeloord",
    "sg:orig_category":"Koeriersdiensten",
    "sg:phone":"+31 527 613 101",
    "sg:postcode":"8302 EV",
    "sg:province":"Flevoland",
    "wof:name":"Select",
    "wof:placetype":"venue"
},
  "geometry": {"coordinates":[5.758474,52.710918],"type":"Point"}
}