{
  "type": "Feature",
  "properties": {
    "addr:full":"Kettingstr 7 Emmeloord Flevoland 8302 EV",
    "addr:housenumber":"7",
    "addr:postcode":"8302 ev",
    "addr:street":"Kettingstr;Flevoland",
    "iso:country":"NL",
    "sg:address":"Kettingstr 7",
    "sg:city":"Emmeloord",
    "sg:orig_category":"Koeriersdiensten",
    "sg:phone":"+31 527 613 101",
    "sg:postcode":"8302 EV",
    "sg:province":"Flevoland",
    "wof:name":"Select",
    "wof:placetype":"venue"
},
  "geometry": {"coordinates":[5.758474,52.710918],"type":"Point"}
}