{
  "type": "Feature",
  "properties": {
    "addr:full":"Lage Frontweg 22 Maastricht Limburg 6219 PD",
    "addr:housenumber":"22",
    "addr:postcode":"6219 pd",
    "addr:street":"Lage Frontweg",
    "iso:country":"NL",
    "sg:address":"Lage Frontweg 22",
    "sg:city":"Maastricht",
    "sg:orig_category":"Verhuur Audiovisuele Apparatuur",
    "sg:phone":"+31 43 325 5086",
    "sg:postcode":"6219 PD",
    "sg:province":"Limburg",
    "wof:name":"Power Acoustic Sound Systeem",
    "wof:placetype":"venue"
},
  "geometry": {"coordinates":[5.684215,50.859253],"type":"Point"}
}