{
  "type": "Feature",
  "properties": {
    "addr:full":"Marsweg 3 Zwolle Overijssel 8013 PD",
    "addr:housenumber":"3",
    "addr:postcode":"8013 pd",
    "addr:street":"Marsweg",
    "iso:country":"NL",
    "sg:address":"Marsweg 3",
    "sg:city":"Zwolle",
    "sg:orig_category":"Autokeuringen",
    "sg:phone":"+31 38 422 3108",
    "sg:postcode":"8013 PD",
    "sg:province":"Overijssel",
    "wof:name":"Protoplas",
    "wof:placetype":"venue"
},
  "geometry": {"coordinates":[6.12153,52.501232],"type":"Point"}
}