{
  "type": "Feature",
  "properties": {
    "addr:full":"1E Industriewg 13 Lopik Utrecht 3411 MG",
    "addr:housenumber":"13",
    "addr:postcode":"3411 mg",
    "addr:street":"1E Industriewg",
    "iso:country":"NL",
    "sg:address":"1E Industriewg 13",
    "sg:city":"Lopik",
    "sg:orig_category":"Kaasgroothandel",
    "sg:phone":"+31 348 558 020",
    "sg:postcode":"3411 MG",
    "sg:province":"Utrecht",
    "wof:name":"Lebo Bv",
    "wof:placetype":"venue"
},
  "geometry": {"coordinates":[4.9708919525,51.9827003479],"type":"Point"}
}