{
  "type": "Feature",
  "properties": {
    "addr:full":"Knsm Ln 284 Amsterdam Noord-Holland 1019 LM",
    "addr:housenumber":"284",
    "addr:postcode":"1019 lm",
    "addr:street":"Knsm Ln",
    "iso:country":"NL",
    "sg:address":"Knsm Ln 284",
    "sg:city":"Amsterdam",
    "sg:orig_category":"Architecten En Architectenbureaus",
    "sg:phone":"+31 20 418 4650",
    "sg:postcode":"1019 LM",
    "sg:province":"Noord-Holland",
    "wof:name":"Rapp + Rapp Bv",
    "wof:placetype":"venue"
},
  "geometry": {"coordinates":[4.940074,52.376781],"type":"Point"}
}