{
  "type": "Feature",
  "properties": {
    "iso:country":"NL",
    "sg:address":"Hemelricplaats 8",
    "sg:city":"Hoevelaken",
    "sg:orig_category":"Goederenvervoer Over De Weg",
    "sg:phone":"+31 33 253 6277",
    "sg:postcode":"3871 MG",
    "sg:province":"Gelderland",
    "wof:name":"Hajotrans Internationaal Transport Vof",
    "wof:placetype":"venue"
},
  "geometry": {"coordinates":[5.451798,52.170349],"type":"Point"}
}