{
  "type": "Feature",
  "properties": {
    "iso:country":"NL",
    "sg:address":"Broekerhavenweg 172",
    "sg:city":"Bovenkarspel",
    "sg:orig_category":"Pleziervaartuigen And Reparatie",
    "sg:phone":"+31 228 511 384",
    "sg:postcode":"1611 CJ",
    "sg:province":"Noord-Holland",
    "wof:name":"De Firma W. Botman En Zn.",
    "wof:placetype":"venue"
},
  "geometry": {"coordinates":[5.252698,52.692612],"type":"Point"}
}