{
  "type": "Feature",
  "properties": {
    "addr:full":"Keinsmerweg 46 'T Zand Nh Noord-Holland 1756 AH",
    "addr:housenumber":"46",
    "addr:postcode":"1756 ah",
    "addr:street":"Keinsmerweg",
    "iso:country":"NL",
    "sg:address":"Keinsmerweg 46",
    "sg:city":"'T Zand Nh",
    "sg:classifiers":[
        {
            "category":"Fast Food",
            "type":"Food & Drink"
        }
    ],
    "sg:phone":"+31 224 593 391",
    "sg:postcode":"1756 AH",
    "sg:province":"Noord-Holland",
    "sg:tags":[
        "afhaal",
        "restaurant"
    ],
    "wof:name":"Vof Smikkelhof",
    "wof:placetype":"venue"
},
  "geometry": {"coordinates":[4.756555,52.835407],"type":"Point"}
}