{
  "type": "Feature",
  "properties": {
    "addr:full":"Weerdingerstr 214 Emmen Provincie Drenthe 7811 CA",
    "addr:housenumber":"214",
    "addr:postcode":"7811 ca",
    "addr:street":"Provincie Drenthe",
    "iso:country":"NL",
    "sg:address":"Weerdingerstr 214",
    "sg:city":"Emmen",
    "sg:orig_category":"Fietsen En Bromfietsen",
    "sg:phone":"+31 591 649 860",
    "sg:postcode":"7811 CA",
    "sg:province":"Provincie Drenthe",
    "wof:name":"Vries Tweewielers, De",
    "wof:placetype":"venue"
},
  "geometry": {"coordinates":[6.898798,52.793564],"type":"Point"}
}