{
  "type": "Feature",
  "properties": {
    "iso:country":"NL",
    "sg:address":"Postbus 102",
    "sg:city":"Bergeyk",
    "sg:orig_category":"Kunststoffen- Verwerkende Industrie",
    "sg:phone":"+31 497 572 002",
    "sg:postcode":"5570 AC",
    "sg:province":"North Brabant",
    "wof:name":"Moss Benelux Bv",
    "wof:placetype":"venue"
},
  "geometry": {"coordinates":[5.35888,51.322739],"type":"Point"}
}