{
  "type": "Feature",
  "properties": {
    "addr:full":"De Valckestr 2 Ten Boer Groningen 9791 CK",
    "addr:housenumber":"2",
    "addr:postcode":"boer;9791 ck",
    "addr:street":"Ten",
    "iso:country":"NL",
    "sg:address":"De Valckestr 2",
    "sg:city":"Ten Boer",
    "sg:orig_category":"Politie",
    "sg:phone":"+31 900 8844",
    "sg:postcode":"9791 CK",
    "sg:province":"Groningen",
    "wof:name":"Politie",
    "wof:placetype":"venue"
},
  "geometry": {"coordinates":[6.696065,53.275185],"type":"Point"}
}