{
  "type": "Feature",
  "properties": {
    "iso:country":"NL",
    "sg:address":"Aak 37",
    "sg:city":"Wieringerwerf",
    "sg:orig_category":"Voetbalverenigingen",
    "sg:phone":"+31 227 601 548",
    "sg:postcode":"1771 GA",
    "sg:province":"North Holland",
    "wof:name":"Wieringermeer",
    "wof:placetype":"venue"
},
  "geometry": {"coordinates":[5.037183,52.851978],"type":"Point"}
}