{
  "type": "Feature",
  "properties": {
    "addr:full":"Paradijsstraat 6 Sittard Limburg 6131 JB",
    "addr:housenumber":"6",
    "addr:postcode":"6131 jb",
    "addr:street":"Paradijsstraat",
    "iso:country":"NL",
    "sg:address":"Paradijsstraat 6",
    "sg:city":"Sittard",
    "sg:orig_category":"Schoenen",
    "sg:phone":"+31 46 451 5507",
    "sg:postcode":"6131 JB",
    "sg:province":"Limburg",
    "wof:name":"Massa Schoen & Mode Bv",
    "wof:placetype":"venue"
},
  "geometry": {"coordinates":[5.869178,50.996624],"type":"Point"}
}