{
  "type": "Feature",
  "properties": {
    "addr:full":"West-Kruiskade 3 Rotterdam Zuid-Holland 3014 AJ",
    "addr:housenumber":"3",
    "addr:postcode":"3014 aj",
    "addr:street":"West-Kruiskade",
    "iso:country":"NL",
    "sg:address":"West-Kruiskade 3",
    "sg:city":"Rotterdam",
    "sg:orig_category":"Kappers",
    "sg:phone":"+31 10 404 9855",
    "sg:postcode":"3014 AJ",
    "sg:province":"Zuid-Holland",
    "wof:name":"The Favorite Hair Salon",
    "wof:placetype":"venue"
},
  "geometry": {"coordinates":[4.470428,51.920856],"type":"Point"}
}