{
  "type": "Feature",
  "properties": {
    "addr:full":"Turnhoutseweg 41 Reusel North Brabant 5541 NW",
    "addr:housenumber":"41",
    "addr:postcode":"5541 nw",
    "addr:street":"Turnhoutseweg",
    "iso:country":"NL",
    "sg:address":"Turnhoutseweg 41",
    "sg:city":"Reusel",
    "sg:orig_category":"Bloemen And Planten",
    "sg:phone":"+31 497 643 007",
    "sg:postcode":"5541 NW",
    "sg:province":"North Brabant",
    "wof:name":"P Van Gompel En Zonen",
    "wof:placetype":"venue"
},
  "geometry": {"coordinates":[5.140856,51.354343],"type":"Point"}
}