{
  "type": "Feature",
  "properties": {
    "iso:country":"NL",
    "sg:address":"Zevenbergseweg 22",
    "sg:city":"Berghem",
    "sg:orig_category":"Levende Dieren Gh",
    "sg:phone":"+31 412 401 836",
    "sg:postcode":"5351 PH",
    "sg:province":"Noord-Brabant",
    "wof:name":"A.A. Romijnders En Zoon",
    "wof:placetype":"venue"
},
  "geometry": {"coordinates":[5.564545,51.765938],"type":"Point"}
}