{
  "type": "Feature",
  "properties": {
    "iso:country":"NL",
    "sg:address":"Geestland 9",
    "sg:city":"Bavel",
    "sg:classifiers":[
        {
            "category":"Personal",
            "subcategory":"Nail Salon",
            "type":"Services"
        }
    ],
    "sg:phone":"+31 161 432 110",
    "sg:postcode":"4854 BE",
    "sg:province":"Noord-Brabant",
    "sg:tags":[
        "pedicure"
    ],
    "wof:name":"Liesbeth Vd Velden",
    "wof:placetype":"venue"
},
  "geometry": {"coordinates":[4.826694,51.56575],"type":"Point"}
}