{
  "type": "Feature",
  "properties": {
    "iso:country":"NL",
    "sg:address":"Dr O Botjesln 63",
    "sg:city":"Midwolda",
    "sg:orig_category":"Vertaalbureaus",
    "sg:phone":"+31 597 552 451",
    "sg:postcode":"9681 GD",
    "sg:province":"Groningen",
    "wof:name":"Nial",
    "wof:placetype":"venue"
},
  "geometry": {"coordinates":[7.016005,53.195511],"type":"Point"}
}