{
  "type": "Feature",
  "properties": {
    "addr:full":"Vliegdenweg 6 A Bussum North Holland 1406 MZ",
    "addr:housenumber":"6 a",
    "addr:postcode":"1406 mz",
    "addr:street":"Vliegdenweg",
    "iso:country":"NL",
    "sg:address":"Vliegdenweg 6 A",
    "sg:city":"Bussum",
    "sg:orig_category":"Loodgieterswerk, Verwarming And Sanitaire Installaties",
    "sg:phone":"+31 35 692 0718",
    "sg:postcode":"1406 MZ",
    "sg:province":"North Holland",
    "wof:name":"Posno Installatie En Daktechniek",
    "wof:placetype":"venue"
},
  "geometry": {"coordinates":[5.15438,52.269894],"type":"Point"}
}