{
  "type": "Feature",
  "properties": {
    "addr:full":"Kanaalstraat 96 Utrecht Utrecht 3531 CM",
    "addr:housenumber":"96",
    "addr:postcode":"3531 cm",
    "addr:street":"Kanaalstraat",
    "iso:country":"NL",
    "sg:address":"Kanaalstraat 96",
    "sg:city":"Utrecht",
    "sg:orig_category":"Juweliers",
    "sg:phone":"+31 30 293 4661",
    "sg:postcode":"3531 CM",
    "sg:province":"Utrecht",
    "wof:name":"Yucel Yildirim",
    "wof:placetype":"venue"
},
  "geometry": {"coordinates":[5.100699,52.091217],"type":"Point"}
}