{
  "type": "Feature",
  "properties": {
    "addr:full":"Dr Jan Mulderstraat 11 Zaandijk Noord-Holland 1544 VA",
    "addr:housenumber":"11",
    "addr:postcode":"1544",
    "addr:street":"Dr Jan Mulderstraat",
    "iso:country":"NL",
    "sg:address":"Dr Jan Mulderstraat 11",
    "sg:city":"Zaandijk",
    "sg:orig_category":"Bedrijfsinventaris Gh",
    "sg:phone":"+31 75 622 1985",
    "sg:postcode":"1544 VA",
    "sg:province":"Noord-Holland",
    "wof:name":"Corinne Kerssens",
    "wof:placetype":"venue"
},
  "geometry": {"coordinates":[4.801774,52.470371],"type":"Point"}
}