{
  "type": "Feature",
  "properties": {
    "addr:full":"Panovenwg 15 Tiel Gelderland 4004 JE",
    "addr:housenumber":"15",
    "addr:postcode":"4004 je",
    "addr:street":"Panovenwg;Gelderland",
    "iso:country":"NL",
    "sg:address":"Panovenwg 15",
    "sg:city":"Tiel",
    "sg:orig_category":"Betonwerken",
    "sg:phone":"+31 344 624 488",
    "sg:postcode":"4004 JE",
    "sg:province":"Gelderland",
    "sg:website":"http://www.kellen.nl",
    "wof:name":"Kellen Beton Bv",
    "wof:placetype":"venue"
},
  "geometry": {"coordinates":[5.44708,51.906979],"type":"Point"}
}