{
  "type": "Feature",
  "properties": {
    "iso:country":"NL",
    "sg:address":"Koopvaarder 4",
    "sg:city":"Hoorn Nh",
    "sg:orig_category":"Accountants - Administratie- Consulenten En -Kantoren",
    "sg:phone":"+31 229 239 034",
    "sg:postcode":"1625 BZ",
    "sg:province":"North Holland",
    "wof:name":"Ltb Bv",
    "wof:placetype":"venue"
},
  "geometry": {"coordinates":[5.05942,52.6572],"type":"Point"}
}