{
  "type": "Feature",
  "properties": {
    "addr:full":"Weth Seelenstr 30 Venlo Limburg 5913 SN",
    "addr:housenumber":"30",
    "addr:postcode":"5913 sn",
    "addr:street":"Weth Seelenstr",
    "iso:country":"NL",
    "sg:address":"Weth Seelenstr 30",
    "sg:city":"Venlo",
    "sg:orig_category":"Kappers",
    "sg:phone":"+31 77 352 0071",
    "sg:postcode":"5913 SN",
    "sg:province":"Limburg",
    "wof:name":"Bekerom Studio 30, A Van Den",
    "wof:placetype":"venue"
},
  "geometry": {"coordinates":[6.1846871376,51.3605117798],"type":"Point"}
}