{
  "type": "Feature",
  "properties": {
    "addr:full":"Queenboroughstr 4 Brielle South Holland 3231 XR",
    "addr:housenumber":"4",
    "addr:postcode":"3231 xr",
    "addr:street":"Queenboroughstr",
    "iso:country":"NL",
    "sg:address":"Queenboroughstr 4",
    "sg:city":"Brielle",
    "sg:orig_category":"Houtbewerking",
    "sg:phone":"+31 181 414 950",
    "sg:postcode":"3231 XR",
    "sg:province":"South Holland",
    "wof:name":"Zandloper, De",
    "wof:placetype":"venue"
},
  "geometry": {"coordinates":[4.163658,51.901035],"type":"Point"}
}