{
  "type": "Feature",
  "properties": {
    "addr:full":"Pepijnstraat 75 Venlo Limburg 5921 HL",
    "addr:housenumber":"75",
    "addr:postcode":"5921 hl",
    "addr:street":"Pepijnstraat",
    "iso:country":"NL",
    "sg:address":"Pepijnstraat 75",
    "sg:city":"Venlo",
    "sg:orig_category":"Kantoorapparatuur Gh",
    "sg:phone":"+31 77 387 0878",
    "sg:postcode":"5921 HL",
    "sg:province":"Limburg",
    "wof:name":"Venlose Kantoormachine Installatie V.K.I",
    "wof:placetype":"venue"
},
  "geometry": {"coordinates":[6.1508760452,51.3705558777],"type":"Point"}
}