{
  "type": "Feature",
  "properties": {
    "addr:full":"Vyfhuizenberg 113 Roosendaal Noord-Brabant 4708 AJ",
    "addr:housenumber":"113",
    "addr:postcode":"4708 aj",
    "addr:street":"Vyfhuizenberg",
    "iso:country":"NL",
    "sg:address":"Vyfhuizenberg 113",
    "sg:city":"Roosendaal",
    "sg:orig_category":"Nagelstudio'S",
    "sg:phone":"+31 165 393 279",
    "sg:postcode":"4708 AJ",
    "sg:province":"Noord-Brabant",
    "wof:name":"Chique, Le",
    "wof:placetype":"venue"
},
  "geometry": {"coordinates":[4.441693,51.519047],"type":"Point"}
}