{
  "type": "Feature",
  "properties": {
    "addr:full":"Westeinde 346A Berkhout Noord-Holland 1647 MT",
    "addr:housenumber":"346a;1647",
    "addr:street":"Westeinde;Mt",
    "iso:country":"NL",
    "sg:address":"Westeinde 346A",
    "sg:city":"Berkhout",
    "sg:orig_category":"Adviesbureaus Bedrijfsorganisatie",
    "sg:phone":"+31 6 53882217",
    "sg:postcode":"1647 MT",
    "sg:province":"Noord-Holland",
    "wof:name":"Nck Consultancy",
    "wof:placetype":"venue"
},
  "geometry": {"coordinates":[4.961137,52.636803],"type":"Point"}
}