{
  "type": "Feature",
  "properties": {
    "iso:country":"NL",
    "sg:address":"Kattestr 3",
    "sg:city":"Mill",
    "sg:orig_category":"Metaalbewerking",
    "sg:phone":"+31 485 451 030",
    "sg:postcode":"5451 GH",
    "sg:province":"Noord-Brabant",
    "wof:name":"Staalwerk Mill Bv",
    "wof:placetype":"venue"
},
  "geometry": {"coordinates":[-88.40593699999999,31.767021],"type":"Point"}
}