{
  "type": "Feature",
  "properties": {
    "addr:full":"Fazantwg 46 Paterswolde Drenthe 9765 JM",
    "addr:housenumber":"46",
    "addr:postcode":"9765 jm",
    "addr:street":"Fazantwg",
    "iso:country":"NL",
    "sg:address":"Fazantwg 46",
    "sg:city":"Paterswolde",
    "sg:orig_category":"Adviesbureaus Bedrijfsorganisatie",
    "sg:phone":"+31 50 308 0626",
    "sg:postcode":"9765 JM",
    "sg:province":"Drenthe",
    "sg:website":"http://www.cowlogic.nl",
    "wof:name":"Cowlogic",
    "wof:placetype":"venue"
},
  "geometry": {"coordinates":[6.559383,53.145363],"type":"Point"}
}