{
  "type": "Feature",
  "properties": {
    "addr:full":"Spoorstraat 53 Alkmaar Noord-Holland 1815 BH",
    "addr:housenumber":"53",
    "addr:postcode":"1815 bh",
    "addr:street":"Spoorstraat",
    "iso:country":"NL",
    "sg:address":"Spoorstraat 53",
    "sg:city":"Alkmaar",
    "sg:orig_category":"Verhuur Audiovisuele Apparatuur",
    "sg:phone":"+31 72 515 6957",
    "sg:postcode":"1815 BH",
    "sg:province":"Noord-Holland",
    "wof:name":"Bema Sound",
    "wof:placetype":"venue"
},
  "geometry": {"coordinates":[4.74253,52.636471],"type":"Point"}
}