{
  "type": "Feature",
  "properties": {
    "addr:full":"Kleiwg 147 Rotterdam Zuid-Holland 3051 GN",
    "addr:housenumber":"147",
    "addr:postcode":"3051 gn",
    "iso:country":"NL",
    "sg:address":"Kleiwg 147",
    "sg:city":"Rotterdam",
    "sg:orig_category":"Postkantoren",
    "sg:phone":"+31 10 418 9723",
    "sg:postcode":"3051 GN",
    "sg:province":"Zuid-Holland",
    "sg:website":"http://www.postkantoor.nl",
    "wof:name":"Postkantoor",
    "wof:placetype":"venue"
},
  "geometry": {"coordinates":[4.476235,51.945473],"type":"Point"}
}