{
  "type": "Feature",
  "properties": {
    "addr:full":"Geraniumstr 14 Zwolle Overijssel 8013 TK",
    "addr:housenumber":"14",
    "addr:postcode":"8013 tk",
    "addr:street":"Geraniumstr",
    "iso:country":"NL",
    "sg:address":"Geraniumstr 14",
    "sg:city":"Zwolle",
    "sg:orig_category":"Boeken En Tijdschriften",
    "sg:phone":"+31 38 423 2808",
    "sg:postcode":"8013 TK",
    "sg:province":"Overijssel",
    "wof:name":"Lighthouse",
    "wof:placetype":"venue"
},
  "geometry": {"coordinates":[6.110366,52.500141],"type":"Point"}
}