{
  "type": "Feature",
  "properties": {
    "addr:full":"A V Schendelstr 24 Utrecht Utrecht 3511 MD",
    "addr:housenumber":"24",
    "addr:postcode":"3511",
    "addr:street":"A;Schendelstr",
    "iso:country":"NL",
    "sg:address":"A V Schendelstr 24",
    "sg:city":"Utrecht",
    "sg:orig_category":"Fotoreportages",
    "sg:phone":"+31 30 231 3949",
    "sg:postcode":"3511 MD",
    "sg:province":"Utrecht",
    "wof:name":"Hendriks, Ron",
    "wof:placetype":"venue"
},
  "geometry": {"coordinates":[5.115405,52.088932],"type":"Point"}
}