{
  "type": "Feature",
  "properties": {
    "iso:country":"NL",
    "sg:address":"Strickledeweg 54",
    "sg:city":"Rotterdam",
    "sg:orig_category":"Marketingbureaus",
    "sg:phone":"+31 10 245 2000",
    "sg:postcode":"3044 EK",
    "sg:province":"South Holland",
    "wof:name":"Perfect Direct Mail Bv",
    "wof:placetype":"venue"
},
  "geometry": {"coordinates":[4.410511,51.929546],"type":"Point"}
}