{
  "type": "Feature",
  "properties": {
    "addr:full":"Edeseweg 117 Harskamp Gelderland 6732 DA",
    "addr:housenumber":"117",
    "addr:postcode":"6732 da",
    "addr:street":"Edeseweg;Gelderland",
    "iso:country":"NL",
    "sg:address":"Edeseweg 117",
    "sg:city":"Harskamp",
    "sg:orig_category":"Metaalwerken",
    "sg:phone":"+31 318 456 595",
    "sg:postcode":"6732 DA",
    "sg:province":"Gelderland",
    "wof:name":"W. Van Den Brink",
    "wof:placetype":"venue"
},
  "geometry": {"coordinates":[5.725928,52.124123],"type":"Point"}
}