{
  "type": "Feature",
  "properties": {
    "addr:full":"Willem 3 Ln 12 Breda Noord-Brabant 4835 LB",
    "addr:housenumber":"12",
    "addr:postcode":"4835 lb",
    "addr:street":"Willem 3 Ln",
    "iso:country":"NL",
    "sg:address":"Willem 3 Ln 12",
    "sg:city":"Breda",
    "sg:orig_category":"Psychotherapeuten",
    "sg:phone":"+31 76 561 4408",
    "sg:postcode":"4835 LB",
    "sg:province":"Noord-Brabant",
    "wof:name":"Schans-Sacchetti De Tuddo, Drs G Vd",
    "wof:placetype":"venue"
},
  "geometry": {"coordinates":[4.780807,51.57103],"type":"Point"}
}