{
  "type": "Feature",
  "properties": {
    "addr:full":"Brandevoort 7 Helmond North Brabant 5706 KA",
    "addr:housenumber":"7",
    "addr:postcode":"5706 ka",
    "addr:street":"Brandevoort",
    "iso:country":"NL",
    "sg:address":"Brandevoort 7",
    "sg:city":"Helmond",
    "sg:orig_category":"Babykleding - Fabrieken En Groothandel",
    "sg:phone":"+31 492 521 926",
    "sg:postcode":"5706 KA",
    "sg:province":"North Brabant",
    "wof:name":"Funnies",
    "wof:placetype":"venue"
},
  "geometry": {"coordinates":[5.622096,51.453053],"type":"Point"}
}