{
  "type": "Feature",
  "properties": {
    "addr:full":"Achterstr 36 Lekkerkerk South Holland 2941 AB",
    "addr:housenumber":"36",
    "addr:postcode":"2941 ab",
    "addr:street":"Achterstr",
    "iso:country":"NL",
    "sg:address":"Achterstr 36",
    "sg:city":"Lekkerkerk",
    "sg:orig_category":"Kappers",
    "sg:phone":"+31 180 663 679",
    "sg:postcode":"2941 AB",
    "sg:province":"South Holland",
    "wof:name":"Hair Style, Studio",
    "wof:placetype":"venue"
},
  "geometry": {"coordinates":[4.6841311455,51.8952140808],"type":"Point"}
}