{
  "type": "Feature",
  "properties": {
    "addr:full":"Molenweg 2D Eemnes Utrecht 3755 BD",
    "addr:housenumber":"2d",
    "addr:postcode":"3755 bd",
    "addr:street":"Molenweg",
    "iso:country":"NL",
    "sg:address":"Molenweg 2D",
    "sg:city":"Eemnes",
    "sg:orig_category":"Psychologen",
    "sg:phone":"+31 35 538 6192",
    "sg:postcode":"3755 BD",
    "sg:province":"Utrecht",
    "wof:name":"Hylkema-Goossens, Drs J A",
    "wof:placetype":"venue"
},
  "geometry": {"coordinates":[5.256756,52.253193],"type":"Point"}
}