{
  "type": "Feature",
  "properties": {
    "iso:country":"NL",
    "sg:address":"Biltstraat 156",
    "sg:city":"Utrecht",
    "sg:orig_category":"Diverse Grafische Activiteiten",
    "sg:phone":"+31 30 271 7646",
    "sg:postcode":"3572 BN",
    "sg:province":"Utrecht",
    "wof:name":"Koningsberger & Van Duijnhoven",
    "wof:placetype":"venue"
},
  "geometry": {"coordinates":[5.134926,52.095642],"type":"Point"}
}