{
  "type": "Feature",
  "properties": {
    "addr:full":"Arnhemsestraatweg 358 Velp Gld Gelderland 6881 NK",
    "addr:housenumber":"358",
    "addr:postcode":"6881 nk",
    "addr:street":"Arnhemsestraatweg;Gld Gelderland",
    "iso:country":"NL",
    "sg:address":"Arnhemsestraatweg 358",
    "sg:city":"Velp Gld",
    "sg:classifiers":[
        {
            "category":"Professional",
            "subcategory":"Accounting & Tax Preparation",
            "type":"Services"
        }
    ],
    "sg:phone":"+31 26 368 3240",
    "sg:postcode":"6881 NK",
    "sg:province":"Gelderland",
    "sg:tags":[
        "accountant"
    ],
    "wof:name":"Accountantskantoor Boerhof Bv",
    "wof:placetype":"venue"
},
  "geometry": {"coordinates":[5.955851,51.995846],"type":"Point"}
}