{
  "type": "Feature",
  "properties": {
    "addr:full":"Houtduifwg 6 Ysselstein Ut Utrecht 3403 BD",
    "addr:housenumber":"6",
    "addr:postcode":"3403 bd",
    "addr:street":"Houtduifwg",
    "iso:country":"NL",
    "sg:address":"Houtduifwg 6",
    "sg:city":"Ysselstein Ut",
    "sg:classifiers":[
        {
            "category":"Wholesale",
            "subcategory":"Meat",
            "type":"Manufacturing & Wholesale Goods"
        }
    ],
    "sg:phone":"+31 30 687 4852",
    "sg:postcode":"3403 BD",
    "sg:province":"Utrecht",
    "sg:tags":[
        "regeltechniek",
        "en",
        "meet-"
    ],
    "wof:name":"Unitronics Bv",
    "wof:placetype":"venue"
},
  "geometry": {"coordinates":[5.026175,52.027313],"type":"Point"}
}