{
  "type": "Feature",
  "properties": {
    "iso:country":"NL",
    "sg:address":"Veldseweg 2",
    "sg:city":"Gemonde",
    "sg:orig_category":"Loodgieterswerk, Verwarming And Sanitaire Installaties",
    "sg:phone":"+31 73 551 7682",
    "sg:postcode":"5291 PE",
    "sg:province":"North Brabant",
    "wof:name":"Verhagen",
    "wof:placetype":"venue"
},
  "geometry": {"coordinates":[5.3556,51.611568],"type":"Point"}
}