{
  "type": "Feature",
  "properties": {
    "addr:full":"Randersdk 22 Alkmaar Noord-Holland 1823 AA",
    "addr:housenumber":"22",
    "addr:postcode":"1823 aa",
    "addr:street":"Randersdk",
    "iso:country":"NL",
    "sg:address":"Randersdk 22",
    "sg:city":"Alkmaar",
    "sg:orig_category":"Antiquiteiten - Restauratie",
    "sg:phone":"+31 72 511 9531",
    "sg:postcode":"1823 AA",
    "sg:province":"Noord-Holland",
    "wof:name":"Artha",
    "wof:placetype":"venue"
},
  "geometry": {"coordinates":[4.756923,52.631474],"type":"Point"}
}