{
  "type": "Feature",
  "properties": {
    "iso:country":"NL",
    "sg:address":"Grotestr 1",
    "sg:city":"Rossum Ov",
    "sg:classifiers":[
        {
            "category":"Retail",
            "subcategory":"Auto Repair",
            "type":"Services"
        }
    ],
    "sg:phone":"+31 541 625 746",
    "sg:postcode":"7596 KC",
    "sg:province":"NL.08",
    "sg:tags":[
        "garage"
    ],
    "wof:name":"Roesthuis",
    "wof:placetype":"venue"
},
  "geometry": {"coordinates":[6.92626,52.35128],"type":"Point"}
}