{
  "type": "Feature",
  "properties": {
    "addr:full":"Van Hallstraat 288 Amsterdam North Holland 1051 HM",
    "addr:housenumber":"288",
    "addr:postcode":"1051 hm",
    "addr:street":"Van Hallstraat",
    "iso:country":"NL",
    "sg:address":"Van Hallstraat 288",
    "sg:city":"Amsterdam",
    "sg:classifiers":[
        {
            "category":"Communications",
            "subcategory":"Television Station",
            "type":"Services"
        }
    ],
    "sg:phone":"+31 20 684 8905",
    "sg:postcode":"1051 HM",
    "sg:province":"North Holland",
    "sg:tags":[
        "video",
        "audio",
        "verhuur"
    ],
    "wof:name":"Videotheek Beverly Hills",
    "wof:placetype":"venue"
},
  "geometry": {"coordinates":[4.872034,52.379147],"type":"Point"}
}