{
  "type": "Feature",
  "properties": {
    "addr:full":"Derpsestraat 1D Deurne Noord-Brabant 5751 KA",
    "addr:housenumber":"1d",
    "addr:postcode":"5751 ka",
    "addr:street":"Derpsestraat",
    "iso:country":"NL",
    "sg:address":"Derpsestraat 1D",
    "sg:city":"Deurne",
    "sg:orig_category":"Hypotheken And Hypotheekbanken",
    "sg:phone":"+31 493 317 055",
    "sg:postcode":"5751 KA",
    "sg:province":"Noord-Brabant",
    "wof:name":"Hendriks Assurantien",
    "wof:placetype":"venue"
},
  "geometry": {"coordinates":[5.792499,51.460033],"type":"Point"}
}