{
  "type": "Feature",
  "properties": {
    "iso:country":"NL",
    "sg:address":"Brouwersstraat 8",
    "sg:city":"Veenendaal",
    "sg:orig_category":"Banken And Kredietinstellingen",
    "sg:phone":"+31 318 566 711",
    "sg:postcode":"3901 RC",
    "sg:province":"Utrecht",
    "wof:name":"Ing Bank",
    "wof:placetype":"venue"
},
  "geometry": {"coordinates":[5.55941,52.028465],"type":"Point"}
}