{
  "type": "Feature",
  "properties": {
    "addr:full":"Voorstr 293 Dordrecht Zuid-Holland 3311 EP",
    "addr:housenumber":"293",
    "addr:postcode":"3311 ep",
    "iso:country":"NL",
    "sg:address":"Voorstr 293",
    "sg:city":"Dordrecht",
    "sg:orig_category":"Broodjeszaken",
    "sg:phone":"+31 78 635 2001",
    "sg:postcode":"3311 EP",
    "sg:province":"Zuid-Holland",
    "wof:name":"Hut, De",
    "wof:placetype":"venue"
},
  "geometry": {"coordinates":[4.667713,51.815182],"type":"Point"}
}