{
  "type": "Feature",
  "properties": {
    "addr:full":"Breezandpad 15 Arnhem Gelderland 6843 JM",
    "addr:housenumber":"15",
    "addr:postcode":"6843 jm",
    "addr:street":"Breezandpad",
    "iso:country":"NL",
    "sg:address":"Breezandpad 15",
    "sg:city":"Arnhem",
    "sg:orig_category":"Peuterspeelzalen",
    "sg:phone":"+31 26 382 0784",
    "sg:postcode":"6843 JM",
    "sg:province":"Gelderland",
    "wof:name":"Rakkertjes, De",
    "wof:placetype":"venue"
},
  "geometry": {"coordinates":[5.862649,51.960751],"type":"Point"}
}