{
  "type": "Feature",
  "properties": {
    "addr:full":"Liempdseweg 9 Sint Oedenrode Noord-Brabant 5492 SM",
    "addr:housenumber":"9;oedenrode",
    "addr:postcode":"5492 sm",
    "addr:street":"Liempdseweg",
    "iso:country":"NL",
    "sg:address":"Liempdseweg 9",
    "sg:city":"Sint Oedenrode",
    "sg:orig_category":"Binnenhuisarchitecten",
    "sg:phone":"+31 413 476 049",
    "sg:postcode":"5492 SM",
    "sg:province":"Noord-Brabant",
    "wof:name":"C.J.W. Janssen",
    "wof:placetype":"venue"
},
  "geometry": {"coordinates":[5.434916,51.559391],"type":"Point"}
}