{
  "type": "Feature",
  "properties": {
    "iso:country":"NL",
    "sg:address":"De Koumen 29",
    "sg:city":"Hoensbroek",
    "sg:orig_category":"Farmaceutische Industrie En Groothandel",
    "sg:phone":"+31 45 521 4800",
    "sg:postcode":"6433 KG",
    "sg:province":"Limburg",
    "wof:name":"Cosmas Bv",
    "wof:placetype":"venue"
},
  "geometry": {"coordinates":[5.940795,50.911999],"type":"Point"}
}