{
  "type": "Feature",
  "properties": {
    "iso:country":"NL",
    "sg:address":"Nieuwstraat 27",
    "sg:city":"Medemblik",
    "sg:orig_category":"Discountwinkels",
    "sg:phone":"+31 227 541 438",
    "sg:postcode":"1671 BA",
    "sg:province":"Noord-Holland",
    "wof:name":"Firma K. Bot & Zonen",
    "wof:placetype":"venue"
},
  "geometry": {"coordinates":[5.106758,52.772789],"type":"Point"}
}