{
  "type": "Feature",
  "properties": {
    "addr:full":"Kanaalwg 28 S Gravenhage Zuid-Holland 2584 CK",
    "addr:housenumber":"28;gravenhage",
    "addr:postcode":"2584 ck",
    "addr:street":"Kanaalwg;S",
    "iso:country":"NL",
    "sg:address":"Kanaalwg 28",
    "sg:city":"S Gravenhage",
    "sg:classifiers":[
        {
            "category":"Banks & Credit Unions",
            "subcategory":"Investment Brokerage",
            "type":"Services"
        }
    ],
    "sg:phone":"+31 70 355 0333",
    "sg:postcode":"2584 CK",
    "sg:province":"Zuid-Holland",
    "sg:tags":[
        "pension"
    ],
    "wof:name":"Schalke",
    "wof:placetype":"venue"
},
  "geometry": {"coordinates":[4.28131,52.103199],"type":"Point"}
}