{
  "type": "Feature",
  "properties": {
    "addr:full":"Mozartln 1 Vlissingen Zeeland 4384 KT",
    "addr:housenumber":"1",
    "addr:postcode":"4384 kt",
    "addr:street":"Mozartln",
    "iso:country":"NL",
    "sg:address":"Mozartln 1",
    "sg:city":"Vlissingen",
    "sg:orig_category":"Verhuur",
    "sg:phone":"+31 118 472 258",
    "sg:postcode":"4384 KT",
    "sg:province":"Zeeland",
    "wof:name":"Multi Box",
    "wof:placetype":"venue"
},
  "geometry": {"coordinates":[3.57262,51.442684],"type":"Point"}
}