{
  "type": "Feature",
  "properties": {
    "addr:full":"Ambachtsweg 6 Sint Oedenrode Noord-Brabant 5492 NJ",
    "addr:housenumber":"6;oedenrode",
    "addr:postcode":"5492 nj",
    "addr:street":"Ambachtsweg",
    "iso:country":"NL",
    "sg:address":"Ambachtsweg 6",
    "sg:city":"Sint Oedenrode",
    "sg:orig_category":"Technische Studies And Onderzoek",
    "sg:phone":"+31 413 475 125",
    "sg:postcode":"5492 NJ",
    "sg:province":"Noord-Brabant",
    "wof:name":"V.A. Engineering",
    "wof:placetype":"venue"
},
  "geometry": {"coordinates":[5.48037,51.555115],"type":"Point"}
}