{
  "type": "Feature",
  "properties": {
    "iso:country":"NL",
    "sg:address":"Hoge Naarderweg 7I",
    "sg:city":"Hilversum",
    "sg:orig_category":"Apothekers",
    "sg:phone":"+31 35 624 5787",
    "sg:postcode":"1217 AB",
    "sg:province":"Noord-Holland",
    "wof:name":"Apotheek Dudok",
    "wof:placetype":"venue"
},
  "geometry": {"coordinates":[5.168262,52.228634],"type":"Point"}
}