{
  "type": "Feature",
  "properties": {
    "addr:full":"Crocusveld 6 Nieuwerkerk Yssel South Holland 2914 PC",
    "addr:housenumber":"6",
    "addr:postcode":"2914 pc",
    "addr:street":"Crocusveld",
    "iso:country":"NL",
    "sg:address":"Crocusveld 6",
    "sg:city":"Nieuwerkerk Yssel",
    "sg:orig_category":"Verenigingen En Stichtingen",
    "sg:phone":"+31 180 318 320",
    "sg:postcode":"2914 PC",
    "sg:province":"South Holland",
    "wof:name":"Humanistisch Verbond Midden-Holl",
    "wof:placetype":"venue"
},
  "geometry": {"coordinates":[4.620178,51.972843],"type":"Point"}
}