{
  "type": "Feature",
  "properties": {
    "addr:full":"Haarlemmerdijk 93 Amsterdam Noord-Holland 1013 KD",
    "addr:housenumber":"93",
    "addr:postcode":"1013 kd",
    "addr:street":"Haarlemmerdijk",
    "iso:country":"NL",
    "sg:address":"Haarlemmerdijk 93",
    "sg:city":"Amsterdam",
    "sg:orig_category":"Bloemen And Planten",
    "sg:phone":"+31 20 625 3239",
    "sg:postcode":"1013 KD",
    "sg:province":"Noord-Holland",
    "wof:name":"Bloembinderij Madelief",
    "wof:placetype":"venue"
},
  "geometry": {"coordinates":[4.886503,52.382996],"type":"Point"}
}