{
  "type": "Feature",
  "properties": {
    "addr:full":"Bruuk 48 Groesbeek Gelderland 6562 KM",
    "addr:housenumber":"48",
    "addr:postcode":"6562",
    "addr:street":"Bruuk;Gelderland;Km",
    "iso:country":"NL",
    "sg:address":"Bruuk 48",
    "sg:city":"Groesbeek",
    "sg:orig_category":"Kappers",
    "sg:phone":"+31 6 12062744",
    "sg:postcode":"6562 KM",
    "sg:province":"Gelderland",
    "wof:name":"Alice",
    "wof:placetype":"venue"
},
  "geometry": {"coordinates":[5.944644928,51.7613983154],"type":"Point"}
}