{
  "type": "Feature",
  "properties": {
    "addr:full":"Akkerwinde 20 Venlo Limburg 5913 DE",
    "addr:housenumber":"20",
    "addr:postcode":"5913 de",
    "addr:street":"Akkerwinde",
    "iso:country":"NL",
    "sg:address":"Akkerwinde 20",
    "sg:city":"Venlo",
    "sg:orig_category":"Kantoorbenodigdheden - Fabrieken En Groothandel",
    "sg:phone":"+31 77 352 4418",
    "sg:postcode":"5913 DE",
    "sg:province":"Limburg",
    "wof:name":"Henia",
    "wof:placetype":"venue"
},
  "geometry": {"coordinates":[6.1940779686,51.3704719543],"type":"Point"}
}