{
  "type": "Feature",
  "properties": {
    "iso:country":"NL",
    "sg:address":"Akkerwinde 20",
    "sg:city":"Venlo",
    "sg:orig_category":"Kantoorbenodigdheden - Fabrieken En Groothandel",
    "sg:phone":"+31 77 352 4418",
    "sg:postcode":"5913 DE",
    "sg:province":"Limburg",
    "wof:name":"Henia",
    "wof:placetype":"venue"
},
  "geometry": {"coordinates":[6.1940779686,51.3704719543],"type":"Point"}
}