{
  "type": "Feature",
  "properties": {
    "addr:full":"Walingsdk 133C Avenhorn Noord-Holland 1633 RR",
    "addr:housenumber":"133c",
    "addr:postcode":"1633 rr",
    "addr:street":"Walingsdk",
    "iso:country":"NL",
    "sg:address":"Walingsdk 133C",
    "sg:city":"Avenhorn",
    "sg:orig_category":"Sanitaire Artikelen",
    "sg:phone":"+31 229 540 517",
    "sg:postcode":"1633 RR",
    "sg:province":"Noord-Holland",
    "wof:name":"Roko",
    "wof:placetype":"venue"
},
  "geometry": {"coordinates":[4.949257,52.614422],"type":"Point"}
}