{
  "type": "Feature",
  "properties": {
    "addr:full":"Nijverheidstraat 30 Leerdam Zuid-Holland 4143 HM",
    "addr:housenumber":"30",
    "addr:postcode":"4143 hm",
    "addr:street":"Nijverheidstraat",
    "iso:country":"NL",
    "sg:address":"Nijverheidstraat 30",
    "sg:city":"Leerdam",
    "sg:orig_category":"Autokeuringen",
    "sg:phone":"+31 345 617 636",
    "sg:postcode":"4143 HM",
    "sg:province":"Zuid-Holland",
    "wof:name":"Modern Auto Service",
    "wof:placetype":"venue"
},
  "geometry": {"coordinates":[5.099479,51.898769],"type":"Point"}
}