{
  "type": "Feature",
  "properties": {
    "addr:full":"Klenkerweg 13 Oosterhesselen Drenthe 7861 TG",
    "addr:housenumber":"13",
    "addr:postcode":"7861 tg",
    "addr:street":"Klenkerweg",
    "iso:country":"NL",
    "sg:address":"Klenkerweg 13",
    "sg:city":"Oosterhesselen",
    "sg:orig_category":"Hoefdierhouderijen",
    "sg:phone":"+31 524 581 665",
    "sg:postcode":"7861 TG",
    "sg:province":"Drenthe",
    "wof:name":"Handelsstal De Klencke",
    "wof:placetype":"venue"
},
  "geometry": {"coordinates":[6.745497,52.763],"type":"Point"}
}