{
  "type": "Feature",
  "properties": {
    "addr:full":"J De Wittln 12 Barneveld Gelderland 3771 HP",
    "addr:housenumber":"12",
    "addr:postcode":"3771 hp",
    "addr:street":"J De Wittln;Gelderland",
    "iso:country":"NL",
    "sg:address":"J De Wittln 12",
    "sg:city":"Barneveld",
    "sg:orig_category":"Bejaarden - Verzorgingstehuizen",
    "sg:phone":"+31 342 411 811",
    "sg:postcode":"3771 HP",
    "sg:province":"Gelderland",
    "wof:name":"Nebo",
    "wof:placetype":"venue"
},
  "geometry": {"coordinates":[5.588843,52.141216],"type":"Point"}
}