{
  "type": "Feature",
  "properties": {
    "iso:country":"NL",
    "sg:address":"Groenstraat 2B",
    "sg:city":"Waalwijk",
    "sg:classifiers":[
        {
            "category":"Travel",
            "subcategory":"Hotels & Motels",
            "type":"Entertainment"
        }
    ],
    "sg:phone":"+31 416 334 094",
    "sg:postcode":"5142 EB",
    "sg:province":"North Brabant",
    "wof:name":"F.L.A. Leenheers",
    "wof:placetype":"venue"
},
  "geometry": {"coordinates":[5.075106,51.691391],"type":"Point"}
}