{
  "type": "Feature",
  "properties": {
    "addr:full":"Stationswg 392 Scherpenzeel Gld Gelderland 3925 CG",
    "addr:housenumber":"392",
    "addr:postcode":"3925 cg",
    "addr:street":"Gld Gelderland",
    "iso:country":"NL",
    "sg:address":"Stationswg 392",
    "sg:city":"Scherpenzeel Gld",
    "sg:orig_category":"Houtplaatmaterialen",
    "sg:phone":"+31 33 277 1090",
    "sg:postcode":"3925 CG",
    "sg:province":"Gelderland",
    "wof:name":"Bouwhof, De",
    "wof:placetype":"venue"
},
  "geometry": {"coordinates":[5.469601,52.080856],"type":"Point"}
}