{
  "type": "Feature",
  "properties": {
    "addr:full":"Postbus 26 Leiden Zuid-Holland 2300 AA",
    "addr:housenumber":"26",
    "addr:postcode":"2300 aa",
    "addr:street":"Postbus",
    "iso:country":"NL",
    "sg:address":"Postbus 26",
    "sg:city":"Leiden",
    "sg:orig_category":"Schoonheidsinstituten",
    "sg:phone":"+31 6 30025358",
    "sg:postcode":"2300 AA",
    "sg:province":"Zuid-Holland",
    "wof:name":"Wit, J",
    "wof:placetype":"venue"
},
  "geometry": {"coordinates":[4.49015,52.161091],"type":"Point"}
}