{
  "type": "Feature",
  "properties": {
    "addr:full":"Schoener 2713 Lelystad NL. 8243 VN",
    "addr:postcode":"2713;8243 vn",
    "addr:street":"Schoener;Nl.",
    "iso:country":"NL",
    "sg:address":"Schoener 2713",
    "sg:city":"Lelystad",
    "sg:orig_category":"Loodgieterswerk, Verwarming And Sanitaire Installaties",
    "sg:phone":"+31 320 250 043",
    "sg:postcode":"8243 VN",
    "sg:province":"NL.",
    "wof:name":"R. Lina",
    "wof:placetype":"venue"
},
  "geometry": {"coordinates":[5.456917,52.50098],"type":"Point"}
}