{
  "type": "Feature",
  "properties": {
    "addr:full":"Diemerzeedijk 3 Amsterdam North Holland 1095 KK",
    "addr:housenumber":"3",
    "addr:postcode":"1095 kk",
    "addr:street":"Diemerzeedijk",
    "iso:country":"NL",
    "sg:address":"Diemerzeedijk 3",
    "sg:city":"Amsterdam",
    "sg:orig_category":"Pleziervaartuigen And Reparatie",
    "sg:phone":"+31 20 665 2452",
    "sg:postcode":"1095 KK",
    "sg:province":"North Holland",
    "wof:name":"Jan Dekker Epoxysystemen",
    "wof:placetype":"venue"
},
  "geometry": {"coordinates":[4.959652,52.363625],"type":"Point"}
}