{
  "type": "Feature",
  "properties": {
    "addr:full":"Godsweerdersngl 17 Roermond Limburg 6041 GJ",
    "addr:housenumber":"17",
    "addr:postcode":"6041 gj",
    "addr:street":"Godsweerdersngl",
    "iso:country":"NL",
    "sg:address":"Godsweerdersngl 17",
    "sg:city":"Roermond",
    "sg:orig_category":"Adviesbureaus Bedrijfsorganisatie",
    "sg:phone":"+31 475 331 105",
    "sg:postcode":"6041 GJ",
    "sg:province":"Limburg",
    "wof:name":"Ovimar",
    "wof:placetype":"venue"
},
  "geometry": {"coordinates":[5.993048,51.193741],"type":"Point"}
}