{
  "type": "Feature",
  "properties": {
    "iso:country":"NL",
    "sg:address":"Godsweerdersngl 17",
    "sg:city":"Roermond",
    "sg:orig_category":"Adviesbureaus Bedrijfsorganisatie",
    "sg:phone":"+31 475 331 105",
    "sg:postcode":"6041 GJ",
    "sg:province":"Limburg",
    "wof:name":"Ovimar",
    "wof:placetype":"venue"
},
  "geometry": {"coordinates":[5.993048,51.193741],"type":"Point"}
}