{
  "type": "Feature",
  "properties": {
    "addr:full":"Pr Hendrikstr 17 Hoogerheide Noord-Brabant 4631 KA",
    "addr:housenumber":"17",
    "addr:postcode":"4631 ka",
    "iso:country":"NL",
    "sg:address":"Pr Hendrikstr 17",
    "sg:city":"Hoogerheide",
    "sg:orig_category":"Fietsen En Bromfietsen",
    "sg:phone":"+31 164 610 808",
    "sg:postcode":"4631 KA",
    "sg:province":"Noord-Brabant",
    "sg:website":"http://www.multi-bikes.nl",
    "wof:name":"Multi-Bikes",
    "wof:placetype":"venue"
},
  "geometry": {"coordinates":[4.329191,51.424767],"type":"Point"}
}