{
  "type": "Feature",
  "properties": {
    "addr:full":"Van Bleiswijkstraat 10 'S Gravenhage Zuid-Holland 2582 LE",
    "addr:housenumber":"10",
    "addr:postcode":"2582 le",
    "addr:street":"Van Bleiswijkstraat;' S",
    "iso:country":"NL",
    "sg:address":"Van Bleiswijkstraat 10",
    "sg:city":"'S Gravenhage",
    "sg:orig_category":"Artiestenbureaus",
    "sg:phone":"+31 70 355 6414",
    "sg:postcode":"2582 LE",
    "sg:province":"Zuid-Holland",
    "wof:name":"Haagse Kringen",
    "wof:placetype":"venue"
},
  "geometry": {"coordinates":[4.283499,52.095474],"type":"Point"}
}