{
  "type": "Feature",
  "properties": {
    "addr:full":"De Vallei 64 Assen Drenthe 9405 KL",
    "addr:housenumber":"64",
    "addr:postcode":"9405 kl",
    "addr:street":"De Vallei",
    "iso:country":"NL",
    "sg:address":"De Vallei 64",
    "sg:city":"Assen",
    "sg:orig_category":"Landkaarten En Plattegronden",
    "sg:phone":"+31 592 407 848",
    "sg:postcode":"9405 KL",
    "sg:province":"Drenthe",
    "sg:website":"http://www.routekaartjes.nl",
    "wof:name":"Blixxum",
    "wof:placetype":"venue"
},
  "geometry": {"coordinates":[6.536354,52.980721],"type":"Point"}
}