{
  "type": "Feature",
  "properties": {
    "addr:full":"Pascalweg 24 Elst Gld Gelderland 6662 NX",
    "addr:housenumber":"24",
    "addr:postcode":"6662 nx",
    "addr:street":"Pascalweg;Gld Gelderland",
    "iso:country":"NL",
    "sg:address":"Pascalweg 24",
    "sg:city":"Elst Gld",
    "sg:orig_category":"Zuivelproducten And Spijsoli?n Gh",
    "sg:phone":"+31 481 361 382",
    "sg:postcode":"6662 NX",
    "sg:province":"Gelderland",
    "wof:name":"Lacto Trade",
    "wof:placetype":"venue"
},
  "geometry": {"coordinates":[5.865552,51.912521],"type":"Point"}
}