{
  "type": "Feature",
  "properties": {
    "iso:country":"NL",
    "sg:address":"V Brucken Fockln 20",
    "sg:city":"Heemstede",
    "sg:orig_category":"Bejaarden - Verzorgingstehuizen",
    "sg:phone":"+31 23 528 7250",
    "sg:postcode":"2102 XC",
    "sg:province":"Noord-Holland",
    "wof:name":"Heemhaven De",
    "wof:placetype":"venue"
},
  "geometry": {"coordinates":[4.629341,52.351768],"type":"Point"}
}