{
  "type": "Feature",
  "properties": {
    "addr:full":"Kaartenmakerstr 1 Ridderkerk Zuid-Holland 2984 CB",
    "addr:housenumber":"1",
    "addr:postcode":"2984 cb",
    "addr:street":"Kaartenmakerstr",
    "iso:country":"NL",
    "sg:address":"Kaartenmakerstr 1",
    "sg:city":"Ridderkerk",
    "sg:classifiers":[
        {
            "category":"Wholesale",
            "subcategory":"Motor Vehicles",
            "type":"Manufacturing & Wholesale Goods"
        }
    ],
    "sg:phone":"+31 180 418 952",
    "sg:postcode":"2984 CB",
    "sg:province":"Zuid-Holland",
    "sg:tags":[
        "scooter",
        "en"
    ],
    "sg:website":"http://www.benjanmotoren.nl",
    "wof:name":"Benjan Motoren",
    "wof:placetype":"venue"
},
  "geometry": {"coordinates":[4.605245,51.876137],"type":"Point"}
}