{
  "type": "Feature",
  "properties": {
    "iso:country":"NL",
    "sg:address":"Lorentzln 17",
    "sg:city":"Ysselstein Ut",
    "sg:classifiers":[
        {
            "category":"Wholesale",
            "subcategory":"Meat",
            "type":"Manufacturing & Wholesale Goods"
        }
    ],
    "sg:phone":"+31 30 289 6842",
    "sg:postcode":"3401 MX",
    "sg:province":"Utrecht",
    "sg:tags":[
        "regeltechniek",
        "en",
        "meet-"
    ],
    "wof:name":"Hanna Instruments Bv",
    "wof:placetype":"venue"
},
  "geometry": {"coordinates":[5.061158,52.013096],"type":"Point"}
}