{
  "type": "Feature",
  "properties": {
    "addr:full":"Grundelstr 2 Raalte Overijssel 8102 HT",
    "addr:housenumber":"2",
    "addr:postcode":"8102 ht",
    "addr:street":"Grundelstr",
    "iso:country":"NL",
    "sg:address":"Grundelstr 2",
    "sg:city":"Raalte",
    "sg:orig_category":"Autoschade- Herstelbedrijven",
    "sg:phone":"+31 572 352 929",
    "sg:postcode":"8102 HT",
    "sg:province":"Overijssel",
    "wof:name":"Keizershof Autoschade",
    "wof:placetype":"venue"
},
  "geometry": {"coordinates":[6.292629,52.38163],"type":"Point"}
}