{
  "type": "Feature",
  "properties": {
    "addr:full":"G Deynootwg 990 S Gravenhage South Holland 2586 BZ",
    "addr:housenumber":"990",
    "addr:postcode":"2586 bz",
    "addr:street":"S Gravenhage",
    "iso:country":"NL",
    "sg:address":"G Deynootwg 990",
    "sg:city":"S Gravenhage",
    "sg:classifiers":[
        {
            "category":"Farming",
            "subcategory":"Fish & Marine Products",
            "type":"Manufacturing & Wholesale Goods"
        }
    ],
    "sg:phone":"+31 70 352 2620",
    "sg:postcode":"2586 BZ",
    "sg:province":"South Holland",
    "sg:tags":[
        "vi"
    ],
    "wof:name":"Volendam En Jonk",
    "wof:placetype":"venue"
},
  "geometry": {"coordinates":[4.277215,52.10672],"type":"Point"}
}