{
  "type": "Feature",
  "properties": {
    "addr:full":"Robynln 10 Hoofddorp North Holland 2132 WX",
    "addr:housenumber":"10",
    "addr:postcode":"2132 wx",
    "addr:street":"Robynln",
    "iso:country":"NL",
    "sg:address":"Robynln 10",
    "sg:city":"Hoofddorp",
    "sg:orig_category":"Machinefabrieken",
    "sg:phone":"+31 23 567 8300",
    "sg:postcode":"2132 WX",
    "sg:province":"North Holland",
    "wof:name":"Spaans Bulk Handling Syst Bv",
    "wof:placetype":"venue"
},
  "geometry": {"coordinates":[4.69296,52.305393],"type":"Point"}
}