{
  "type": "Feature",
  "properties": {
    "iso:country":"NL",
    "sg:address":"Kon. Julianaplein 58",
    "sg:city":"Zaandam",
    "sg:orig_category":"Bloemen And Planten",
    "sg:phone":"+31 75 650 2606",
    "sg:postcode":"1502 DV",
    "sg:province":"Noord-Holland",
    "wof:name":"Loor'S Kiosk",
    "wof:placetype":"venue"
},
  "geometry": {"coordinates":[4.826045,52.454201],"type":"Point"}
}