{
  "type": "Feature",
  "properties": {
    "iso:country":"NL",
    "sg:address":"Waalkade 83-84",
    "sg:city":"Nijmegen",
    "sg:orig_category":"Musea And Historische Gebouwen",
    "sg:phone":"+31 24 323 8690",
    "sg:postcode":"6511 XR",
    "sg:province":"Gelderland",
    "wof:name":"Museum De Stratemakerstoren",
    "wof:placetype":"venue"
},
  "geometry": {"coordinates":[5.869547,51.848572],"type":"Point"}
}