{
  "type": "Feature",
  "properties": {
    "addr:full":"Ln V Duurzaamheid 139 Amersfoort Utrecht 3824 DZ",
    "addr:housenumber":"139",
    "addr:postcode":"3824 dz",
    "addr:street":"Ln V Duurzaamheid",
    "iso:country":"NL",
    "sg:address":"Ln V Duurzaamheid 139",
    "sg:city":"Amersfoort",
    "sg:orig_category":"Adviesbureaus Bedrijfsorganisatie",
    "sg:phone":"+31 6 21500878",
    "sg:postcode":"3824 DZ",
    "sg:province":"Utrecht",
    "sg:website":"http://www.dcg.myweb.nl",
    "wof:name":"Derksen",
    "wof:placetype":"venue"
},
  "geometry": {"coordinates":[5.384807,52.202198],"type":"Point"}
}