{
  "type": "Feature",
  "properties": {
    "addr:full":"Oranjeln 9 Leusden Utrecht 3832 ED",
    "addr:housenumber":"9",
    "addr:postcode":"3832 ed",
    "addr:street":"Oranjeln",
    "iso:country":"NL",
    "sg:address":"Oranjeln 9",
    "sg:city":"Leusden",
    "sg:orig_category":"Verzekeringen - Verzekeringskantoren",
    "sg:phone":"+31 33 494 6527",
    "sg:postcode":"3832 ED",
    "sg:province":"Utrecht",
    "wof:name":"Berghuis",
    "wof:placetype":"venue"
},
  "geometry": {"coordinates":[5.406114,52.121723],"type":"Point"}
}