{
  "type": "Feature",
  "properties": {
    "iso:country":"NL",
    "sg:address":"Voltwg 3",
    "sg:city":"Hoogerheide",
    "sg:orig_category":"Horecabenodigdheden",
    "sg:phone":"+31 164 612 176",
    "sg:postcode":"4631 SR",
    "sg:province":"Noord-Brabant",
    "wof:name":"Kommers En Zn Bv, Ad",
    "wof:placetype":"venue"
},
  "geometry": {"coordinates":[4.351597,51.429882],"type":"Point"}
}