{
  "type": "Feature",
  "properties": {
    "addr:full":"Drienerlolaan 5 Enschede Overijssel 7522 NB",
    "addr:housenumber":"5",
    "addr:postcode":"7522 nb",
    "addr:street":"Drienerlolaan",
    "iso:country":"NL",
    "sg:address":"Drienerlolaan 5",
    "sg:city":"Enschede",
    "sg:orig_category":"Boekenuitgeverijen",
    "sg:phone":"+31 53 489 2414",
    "sg:postcode":"7522 NB",
    "sg:province":"Overijssel",
    "wof:name":"Campus Boekhandel Geb Drienerburght",
    "wof:placetype":"venue"
},
  "geometry": {"coordinates":[6.851867,52.24065],"type":"Point"}
}