{
  "type": "Feature",
  "properties": {
    "addr:full":"Zeeruststr 126 S Gravenhage Zuid-Holland 2584 BZ",
    "addr:housenumber":"126;gravenhage",
    "addr:postcode":"2584 bz",
    "addr:street":"S",
    "iso:country":"NL",
    "sg:address":"Zeeruststr 126",
    "sg:city":"S Gravenhage",
    "sg:orig_category":"Verzekeringen - Verzekeringskantoren",
    "sg:phone":"+31 70 350 0634",
    "sg:postcode":"2584 BZ",
    "sg:province":"Zuid-Holland",
    "wof:name":"Tinga, J G",
    "wof:placetype":"venue"
},
  "geometry": {"coordinates":[4.2813100815,52.1031990051],"type":"Point"}
}