{
  "type": "Feature",
  "properties": {
    "addr:full":"Batterijenweg 19 Kesteren Gelderland 4041 DA",
    "addr:housenumber":"19",
    "addr:postcode":"4041 da",
    "addr:street":"Batterijenweg;Gelderland",
    "iso:country":"NL",
    "sg:address":"Batterijenweg 19",
    "sg:city":"Kesteren",
    "sg:orig_category":"Meubelzaken, Woning- And Keukeninrichting",
    "sg:phone":"+31 488 483 300",
    "sg:postcode":"4041 DA",
    "sg:province":"Gelderland",
    "wof:name":"Meubelpark De Bongerd Bv",
    "wof:placetype":"venue"
},
  "geometry": {"coordinates":[5.593373,51.936592],"type":"Point"}
}