{
  "type": "Feature",
  "properties": {
    "addr:full":"Sportln 2 Heerjansdam Zuid-Holland 2995 VN",
    "addr:housenumber":"2",
    "addr:postcode":"2995 vn",
    "addr:street":"Sportln",
    "iso:country":"NL",
    "sg:address":"Sportln 2",
    "sg:city":"Heerjansdam",
    "sg:orig_category":"Artsen - Huisartsen",
    "sg:phone":"+31 78 677 1208",
    "sg:postcode":"2995 VN",
    "sg:province":"Zuid-Holland",
    "wof:name":"Roest & R A P De Jong, W F M De",
    "wof:placetype":"venue"
},
  "geometry": {"coordinates":[4.562985,51.836254],"type":"Point"}
}