{
  "type": "Feature",
  "properties": {
    "addr:full":"Westmeerln 9 Roelofarendsveen Zuid-Holland 2371 CD",
    "addr:housenumber":"9",
    "addr:postcode":"2371 cd",
    "addr:street":"Westmeerln",
    "iso:country":"NL",
    "sg:address":"Westmeerln 9",
    "sg:city":"Roelofarendsveen",
    "sg:orig_category":"Journalisten Freelance",
    "sg:phone":"+31 71 331 3984",
    "sg:postcode":"2371 CD",
    "sg:province":"Zuid-Holland",
    "wof:name":"Zwp",
    "wof:placetype":"venue"
},
  "geometry": {"coordinates":[4.62821,52.190289],"type":"Point"}
}