{
  "type": "Feature",
  "properties": {
    "addr:full":"Passage 5 Schiedam South Holland 3111 EH",
    "addr:housenumber":"5",
    "addr:postcode":"3111 eh",
    "addr:street":"Passage",
    "iso:country":"NL",
    "sg:address":"Passage 5",
    "sg:city":"Schiedam",
    "sg:classifiers":[
        {
            "category":"Retail",
            "subcategory":"Photofinishing",
            "type":"Services"
        }
    ],
    "sg:phone":"+31 10 426 9606",
    "sg:postcode":"3111 EH",
    "sg:province":"South Holland",
    "sg:tags":[
        "foto",
        "film"
    ],
    "wof:name":"Foto Niestadt",
    "wof:placetype":"venue"
},
  "geometry": {"coordinates":[4.401559,51.915131],"type":"Point"}
}