{
  "type": "Feature",
  "properties": {
    "addr:full":"J V Maerlantstr 86-90 S Hertogenbosch North Brabant 5216 JM",
    "addr:housenumber":"86-90",
    "addr:postcode":"5216 jm",
    "addr:street":"J;Maerlantstr;S Hertogenbosch",
    "iso:country":"NL",
    "sg:address":"J V Maerlantstr 86-90",
    "sg:city":"S Hertogenbosch",
    "sg:orig_category":"Verf En Lak - Fabrieken En Groothandel",
    "sg:phone":"+31 73 613 5355",
    "sg:postcode":"5216 JM",
    "sg:province":"North Brabant",
    "wof:name":"Vink Verf",
    "wof:placetype":"venue"
},
  "geometry": {"coordinates":[5.29824,51.69075],"type":"Point"}
}