{
  "type": "Feature",
  "properties": {
    "iso:country":"NL",
    "sg:address":"Westzeedijk 463-465",
    "sg:city":"Rotterdam",
    "sg:orig_category":"Juweliers",
    "sg:phone":"+31 10 476 0607",
    "sg:postcode":"3024 EK",
    "sg:province":"Zuid-Holland",
    "wof:name":"Juwelier Peter De Knecht",
    "wof:placetype":"venue"
},
  "geometry": {"coordinates":[4.458152,51.905052],"type":"Point"}
}