{
  "type": "Feature",
  "properties": {
    "iso:country":"NL",
    "sg:address":"Markt 6",
    "sg:city":"Roosendaal",
    "sg:orig_category":"Antiquiteiten",
    "sg:phone":"+31 165 546 380",
    "sg:postcode":"4701 PE",
    "sg:province":"Noord-Brabant",
    "wof:name":"Biedermeier",
    "wof:placetype":"venue"
},
  "geometry": {"coordinates":[4.456081,51.533165],"type":"Point"}
}