{
  "type": "Feature",
  "properties": {
    "addr:full":"Puttelaar 20 Zeeland Noord-Brabant 5411 AB",
    "addr:housenumber":"20",
    "addr:postcode":"5411 ab",
    "addr:street":"Puttelaar",
    "iso:country":"NL",
    "sg:address":"Puttelaar 20",
    "sg:city":"Zeeland",
    "sg:orig_category":"Bloemen And Planten",
    "sg:phone":"+31 486 453 606",
    "sg:postcode":"5411 AB",
    "sg:province":"Noord-Brabant",
    "wof:name":"Bloemenatelier Mireille",
    "wof:placetype":"venue"
},
  "geometry": {"coordinates":[5.678298,51.693718],"type":"Point"}
}