{
  "type": "Feature",
  "properties": {
    "addr:full":"Mient 14 A Capelle Aan Den Ijssel Zuid-Holland 2903 LC",
    "addr:housenumber":"14 a",
    "addr:postcode":"aan den ijssel;2903 lc",
    "addr:street":"Mient",
    "iso:country":"NL",
    "sg:address":"Mient 14 A",
    "sg:city":"Capelle Aan Den Ijssel",
    "sg:orig_category":"Airconditioning And Ventilatie",
    "sg:phone":"+31 10 442 2564",
    "sg:postcode":"2903 LC",
    "sg:province":"Zuid-Holland",
    "wof:name":"Compair Airconditioning",
    "wof:placetype":"venue"
},
  "geometry": {"coordinates":[4.586955,51.924328],"type":"Point"}
}