{
  "type": "Feature",
  "properties": {
    "addr:full":"Wiardi Beckmanstraat 501 Soest Utrecht 3762 GR",
    "addr:housenumber":"501",
    "addr:postcode":"3762",
    "addr:street":"Wiardi Beckmanstraat",
    "iso:country":"NL",
    "sg:address":"Wiardi Beckmanstraat 501",
    "sg:city":"Soest",
    "sg:orig_category":"Film-, Tv- And Videoproductie",
    "sg:phone":"+31 35 601 1921",
    "sg:postcode":"3762 GR",
    "sg:province":"Utrecht",
    "wof:name":"Simar Productions Bv",
    "wof:placetype":"venue"
},
  "geometry": {"coordinates":[5.281894,52.175076],"type":"Point"}
}