{
  "type": "Feature",
  "properties": {
    "iso:country":"NL",
    "sg:address":"Bentinckstr 9",
    "sg:city":"S Gravenhage",
    "sg:orig_category":"Kinderopvang",
    "sg:phone":"+31 70 358 5363",
    "sg:postcode":"2582 SR",
    "sg:province":"Zuid-Holland",
    "wof:name":"2 Piraten",
    "wof:placetype":"venue"
},
  "geometry": {"coordinates":[4.27852,52.092411],"type":"Point"}
}