{
  "type": "Feature",
  "properties": {
    "addr:full":"Bakemastr 13 Groningen Groningen 9731 LZ",
    "addr:housenumber":"13",
    "addr:postcode":"9731 lz",
    "addr:street":"Bakemastr",
    "iso:country":"NL",
    "sg:address":"Bakemastr 13",
    "sg:city":"Groningen",
    "sg:orig_category":"Belastingconsulenten/ Belastingadviseurs",
    "sg:phone":"+31 50 542 5037",
    "sg:postcode":"9731 LZ",
    "sg:province":"Groningen",
    "wof:name":"Helm, Jan Van Den",
    "wof:placetype":"venue"
},
  "geometry": {"coordinates":[6.582755,53.241035],"type":"Point"}
}