{
  "type": "Feature",
  "properties": {
    "addr:full":"Fazantstr 14 Beneden Leeuwen Gelderland 6658 GD",
    "addr:housenumber":"14",
    "addr:postcode":"6658 gd",
    "addr:street":"Fazantstr",
    "iso:country":"NL",
    "sg:address":"Fazantstr 14",
    "sg:city":"Beneden Leeuwen",
    "sg:orig_category":"Grondwerken",
    "sg:phone":"+31 6 22238515",
    "sg:postcode":"6658 GD",
    "sg:province":"Gelderland",
    "wof:name":"Franks Kraanmach. En Grondverz.",
    "wof:placetype":"venue"
},
  "geometry": {"coordinates":[5.506108,51.88332],"type":"Point"}
}