{
  "type": "Feature",
  "properties": {
    "iso:country":"NL",
    "sg:address":"Antoinette Kleynstraat 4",
    "sg:city":"Leiden",
    "sg:classifiers":[
        {
            "category":"Education",
            "subcategory":"Preschool",
            "type":"Public Place"
        }
    ],
    "sg:phone":"+31 71 531 5109",
    "sg:postcode":"2331 DV",
    "sg:province":"South Holland",
    "sg:tags":[
        "kleuteronderwijs",
        "basis-"
    ],
    "wof:name":"Openbare Basisschool De Stevenshof",
    "wof:placetype":"venue"
},
  "geometry": {"coordinates":[4.448898,52.153683],"type":"Point"}
}