{
  "type": "Feature",
  "properties": {
    "addr:full":"Bijlmerplein 862 Amsterdam Zuidoost North Holland 1102 ME",
    "addr:housenumber":"862",
    "addr:postcode":"1102 me",
    "addr:street":"Bijlmerplein",
    "iso:country":"NL",
    "sg:address":"Bijlmerplein 862",
    "sg:city":"Amsterdam Zuidoost",
    "sg:orig_category":"Visspeciaalzaken",
    "sg:phone":"+31 20 697 3330",
    "sg:postcode":"1102 ME",
    "sg:province":"North Holland",
    "wof:name":"Vishandel Volendam Bv",
    "wof:placetype":"venue"
},
  "geometry": {"coordinates":[4.95452,52.313587],"type":"Point"}
}