{
  "type": "Feature",
  "properties": {
    "iso:country":"NL",
    "sg:address":"Houtstraat 34",
    "sg:city":"Echt",
    "sg:orig_category":"Paramedische Behandelingen",
    "sg:phone":"+31 475 483 092",
    "sg:postcode":"6102 BJ",
    "sg:province":"Limburg",
    "wof:name":"M. Van Houtem Vrehen",
    "wof:placetype":"venue"
},
  "geometry": {"coordinates":[5.89055,51.096939],"type":"Point"}
}