{
  "type": "Feature",
  "properties": {
    "addr:full":"Langestr 43 Amsterdam Noord-Holland 1015 AK",
    "addr:housenumber":"43",
    "addr:postcode":"1015 ak",
    "addr:street":"Langestr",
    "iso:country":"NL",
    "sg:address":"Langestr 43",
    "sg:city":"Amsterdam",
    "sg:orig_category":"Tuinontwerp En -Advies",
    "sg:phone":"+31 20 620 8302",
    "sg:postcode":"1015 AK",
    "sg:province":"Noord-Holland",
    "sg:website":"http://www.historischetuinen.nl",
    "wof:name":"Oldenburger",
    "wof:placetype":"venue"
},
  "geometry": {"coordinates":[4.891621,52.377468],"type":"Point"}
}