{
  "type": "Feature",
  "properties": {
    "iso:country":"NL",
    "sg:address":"Bizetstraat 1",
    "sg:city":"Zevenaar",
    "sg:classifiers":[
        {
            "category":"Education",
            "subcategory":"Preschool",
            "type":"Public Place"
        }
    ],
    "sg:phone":"+31 316 524 757",
    "sg:postcode":"6904 KL",
    "sg:province":"Gelderland",
    "sg:tags":[
        "kleuteronderwijs",
        "basis-"
    ],
    "wof:name":"Openbare Basisschool De Caroussel",
    "wof:placetype":"venue"
},
  "geometry": {"coordinates":[6.06287,51.934078],"type":"Point"}
}