{
  "type": "Feature",
  "properties": {
    "addr:full":"Van Echtenstraat 7 Hoogeveen Drenthe 7902 EK",
    "addr:housenumber":"7",
    "addr:postcode":"7902 ek",
    "addr:street":"Van Echtenstraat",
    "iso:country":"NL",
    "sg:address":"Van Echtenstraat 7",
    "sg:city":"Hoogeveen",
    "sg:orig_category":"Werving And Selectie Van Tijdelijk Personeel And Uitzendkantoren",
    "sg:phone":"+31 528 235 936",
    "sg:postcode":"7902 EK",
    "sg:province":"Drenthe",
    "wof:name":"Content",
    "wof:placetype":"venue"
},
  "geometry": {"coordinates":[6.479891777,52.7253570557],"type":"Point"}
}