{
  "type": "Feature",
  "properties": {
    "iso:country":"NL",
    "sg:address":"Industrieweg 29",
    "sg:city":"Hengelo",
    "sg:orig_category":"Partycatering And -Organisatie",
    "sg:phone":"+31 74 242 4384",
    "sg:postcode":"7553  C",
    "sg:province":"Overijssel",
    "wof:name":"Partyservice De Industrie",
    "wof:placetype":"venue"
},
  "geometry": {"coordinates":[6.788311,52.257347],"type":"Point"}
}