{
  "type": "Feature",
  "properties": {
    "addr:full":"Boscheind 49 Luyksgestel Noord-Brabant 5575 AA",
    "addr:housenumber":"49",
    "addr:postcode":"5575 aa",
    "addr:street":"Boscheind",
    "iso:country":"NL",
    "sg:address":"Boscheind 49",
    "sg:city":"Luyksgestel",
    "sg:orig_category":"Diverse Bedrijfsinstallaties Gh",
    "sg:phone":"+31 497 542 242",
    "sg:postcode":"5575 AA",
    "sg:province":"Noord-Brabant",
    "wof:name":"J Jansen",
    "wof:placetype":"venue"
},
  "geometry": {"coordinates":[5.307151,51.282143],"type":"Point"}
}