{
  "type": "Feature",
  "properties": {
    "addr:full":"Dr Schaepmanstr 15 Zevenaar Gelderland 6904 BK",
    "addr:housenumber":"15",
    "addr:postcode":"6904 bk",
    "iso:country":"NL",
    "sg:address":"Dr Schaepmanstr 15",
    "sg:city":"Zevenaar",
    "sg:orig_category":"Adviesbureaus Personeel",
    "sg:phone":"+31 316 344 950",
    "sg:postcode":"6904 BK",
    "sg:province":"Gelderland",
    "sg:website":"http://www.franckly.com",
    "wof:name":"Franckly",
    "wof:placetype":"venue"
},
  "geometry": {"coordinates":[6.076878,51.931618],"type":"Point"}
}