{
  "type": "Feature",
  "properties": {
    "addr:full":"F V Mierisstr 43 Amsterdam Noord-Holland 1071 RK",
    "addr:housenumber":"43",
    "addr:postcode":"1071 rk",
    "addr:street":"Mierisstr",
    "iso:country":"NL",
    "sg:address":"F V Mierisstr 43",
    "sg:city":"Amsterdam",
    "sg:orig_category":"Makelaars En Adviseurs Onroerende Goederen",
    "sg:phone":"+31 20 662 9010",
    "sg:postcode":"1071 RK",
    "sg:province":"Noord-Holland",
    "wof:name":"Roijen Bv, Van",
    "wof:placetype":"venue"
},
  "geometry": {"coordinates":[4.87701,52.355549],"type":"Point"}
}