{
  "type": "Feature",
  "properties": {
    "addr:full":"R P Geerligspad 11 Leiden Zuid-Holland 2331 GV",
    "addr:housenumber":"11",
    "addr:postcode":"2331 gv",
    "addr:street":"Geerligspad",
    "iso:country":"NL",
    "sg:address":"R P Geerligspad 11",
    "sg:city":"Leiden",
    "sg:orig_category":"Artsen - Huisartsen",
    "sg:phone":"+31 71 532 2402",
    "sg:postcode":"2331 GV",
    "sg:province":"Zuid-Holland",
    "wof:name":"Zaaijer & Zaaijer",
    "wof:placetype":"venue"
},
  "geometry": {"coordinates":[4.453983,52.151848],"type":"Point"}
}