{
  "type": "Feature",
  "properties": {
    "addr:full":"Handelsterrein 27 Oude Tonge Zuid-Holland 3255 LD",
    "addr:housenumber":"27",
    "addr:postcode":"3255 ld",
    "addr:street":"Handelsterrein",
    "iso:country":"NL",
    "sg:address":"Handelsterrein 27",
    "sg:city":"Oude Tonge",
    "sg:orig_category":"Architecten En Architectenbureaus",
    "sg:phone":"+31 187 641 553",
    "sg:postcode":"3255 LD",
    "sg:province":"Zuid-Holland",
    "wof:name":"Nimwegen Bv, Van",
    "wof:placetype":"venue"
},
  "geometry": {"coordinates":[4.211746,51.687477],"type":"Point"}
}