{
  "type": "Feature",
  "properties": {
    "iso:country":"NL",
    "sg:address":"Mimosalaan 28",
    "sg:city":"Eindhoven",
    "sg:orig_category":"Kinderopvang Behalve Thuis",
    "sg:phone":"+31 40 211 0478",
    "sg:postcode":"5643 BN",
    "sg:province":"Noord-Brabant",
    "wof:name":"Kinderdagverblijf Skon Okkie",
    "wof:placetype":"venue"
},
  "geometry": {"coordinates":[5.496476,51.421906],"type":"Point"}
}