{
  "type": "Feature",
  "properties": {
    "addr:full":"Fuutln 25 S Hertogenbosch Noord-Brabant 5221 GP",
    "addr:housenumber":"25",
    "addr:postcode":"5221 gp",
    "addr:street":"Fuutln;S",
    "iso:country":"NL",
    "sg:address":"Fuutln 25",
    "sg:city":"S Hertogenbosch",
    "sg:orig_category":"Luchtbehandelings- Apparaten",
    "sg:phone":"+31 73 631 1436",
    "sg:postcode":"5221 GP",
    "sg:province":"Noord-Brabant",
    "wof:name":"Bomitech Bv",
    "wof:placetype":"venue"
},
  "geometry": {"coordinates":[5.271835,51.720615],"type":"Point"}
}