{
  "type": "Feature",
  "properties": {
    "iso:country":"NL",
    "sg:address":"Bikbergerweg 23",
    "sg:city":"Huizen",
    "sg:orig_category":"Architecten",
    "sg:phone":"+31 35 695 2147",
    "sg:postcode":"1272 PL",
    "sg:province":"Noord-Holland",
    "wof:name":"C.A.P.",
    "wof:placetype":"venue"
},
  "geometry": {"coordinates":[5.198241,52.28735],"type":"Point"}
}