{
  "type": "Feature",
  "properties": {
    "iso:country":"NL",
    "sg:address":"Veluwewg 22A",
    "sg:city":"Waarland",
    "sg:orig_category":"Artsen - Huisartsen",
    "sg:phone":"+31 226 422 424",
    "sg:postcode":"1738 BE",
    "sg:province":"Montana",
    "wof:name":"Hageman En E P H M Steenvoorde, A M",
    "wof:placetype":"venue"
},
  "geometry": {"coordinates":[-115.30186500000001,48.500385],"type":"Point"}
}