{
  "type": "Feature",
  "properties": {
    "iso:country":"NL",
    "sg:address":"Merelwg 18",
    "sg:city":"Heusden Gem Asten",
    "sg:orig_category":"Non-Classified Establishments",
    "sg:phone":"+31 493 560 354",
    "sg:postcode":"5725 TH",
    "sg:province":"Noord-Brabant",
    "wof:name":"Deursen Bv, Van",
    "wof:placetype":"venue"
},
  "geometry": {"coordinates":[5.765085,51.374832],"type":"Point"}
}