{
  "type": "Feature",
  "properties": {
    "addr:full":"Ringbaan Zuid 360 Tilburg Noord-Brabant 5022 GA",
    "addr:housenumber":"360",
    "addr:postcode":"5022 ga",
    "addr:street":"Ringbaan Zuid",
    "iso:country":"NL",
    "sg:address":"Ringbaan Zuid 360",
    "sg:city":"Tilburg",
    "sg:orig_category":"Autokeuringen",
    "sg:phone":"+31 13 535 1735",
    "sg:postcode":"5022 GA",
    "sg:province":"Noord-Brabant",
    "wof:name":"Macwash Autowasserette",
    "wof:placetype":"venue"
},
  "geometry": {"coordinates":[5.08831,51.543003],"type":"Point"}
}