{
  "type": "Feature",
  "properties": {
    "addr:full":"Groningerstr 207 Assen Drenthe 9402 LE",
    "addr:housenumber":"207",
    "addr:postcode":"9402 le",
    "iso:country":"NL",
    "sg:address":"Groningerstr 207",
    "sg:city":"Assen",
    "sg:classifiers":[
        {
            "category":"Wholesale",
            "subcategory":"Motor Vehicles",
            "type":"Manufacturing & Wholesale Goods"
        }
    ],
    "sg:phone":"+31 592 347 529",
    "sg:postcode":"9402 LE",
    "sg:province":"Drenthe",
    "sg:tags":[
        "scooter",
        "en"
    ],
    "wof:name":"Buining",
    "wof:placetype":"venue"
},
  "geometry": {"coordinates":[6.566524,53.005508],"type":"Point"}
}