{
  "type": "Feature",
  "properties": {
    "addr:full":"Raadhuisstraat 68 Heemstede Noord-Holland 2101 HJ",
    "addr:housenumber":"68",
    "addr:postcode":"2101 hj",
    "addr:street":"Raadhuisstraat",
    "iso:country":"NL",
    "sg:address":"Raadhuisstraat 68",
    "sg:city":"Heemstede",
    "sg:orig_category":"Kappers",
    "sg:phone":"+31 23 528 8507",
    "sg:postcode":"2101 HJ",
    "sg:province":"Noord-Holland",
    "wof:name":"Vof Kapsalon Jan Ammerlaan",
    "wof:placetype":"venue"
},
  "geometry": {"coordinates":[4.621233,52.349106],"type":"Point"}
}