{
  "type": "Feature",
  "properties": {
    "addr:full":"Ald Haven 33 Lollum Friesland 8823 SR",
    "addr:housenumber":"33",
    "addr:postcode":"8823 sr",
    "addr:street":"Ald Haven",
    "iso:country":"NL",
    "sg:address":"Ald Haven 33",
    "sg:city":"Lollum",
    "sg:orig_category":"Arbo- En Bedrijfsgezondheids- Diensten",
    "sg:phone":"+31 517 469 340",
    "sg:postcode":"8823 SR",
    "sg:province":"Friesland",
    "wof:name":"Schouwen/J Versteeg",
    "wof:placetype":"venue"
},
  "geometry": {"coordinates":[5.53261,53.125725],"type":"Point"}
}