{
  "type": "Feature",
  "properties": {
    "addr:full":"Onderlangs 2B Barendrecht Zuid-Holland 2991 EM",
    "addr:housenumber":"2b",
    "addr:postcode":"2991 em",
    "addr:street":"Onderlangs",
    "iso:country":"NL",
    "sg:address":"Onderlangs 2B",
    "sg:city":"Barendrecht",
    "sg:orig_category":"Accountants - Administratie- Consulenten En -Kantoren",
    "sg:phone":"+31 180 695 444",
    "sg:postcode":"2991 EM",
    "sg:province":"Zuid-Holland",
    "sg:website":"http://www.schot-vandenbouwhuijsen.nl",
    "wof:name":"Schot & Van Den Bouwhuijsen",
    "wof:placetype":"venue"
},
  "geometry": {"coordinates":[4.538064,51.855762],"type":"Point"}
}