{
  "type": "Feature",
  "properties": {
    "addr:full":"Hoofdstraat 164 Velp Gld Gelderland 6881 TL",
    "addr:housenumber":"164",
    "addr:postcode":"6881 tl",
    "addr:street":"Hoofdstraat;Gld Gelderland",
    "iso:country":"NL",
    "sg:address":"Hoofdstraat 164",
    "sg:city":"Velp Gld",
    "sg:orig_category":"Verlichting And Huishoudartikelen",
    "sg:phone":"+31 26 362 0051",
    "sg:postcode":"6881 TL",
    "sg:province":"Gelderland",
    "wof:name":"Knoef Verlichting",
    "wof:placetype":"venue"
},
  "geometry": {"coordinates":[5.97364,51.996037],"type":"Point"}
}