{
  "type": "Feature",
  "properties": {
    "addr:full":"Sonderholm 124 Hoofddorp Noord-Holland 2133 JH",
    "addr:housenumber":"124",
    "addr:postcode":"2133 jh",
    "addr:street":"Sonderholm",
    "iso:country":"NL",
    "sg:address":"Sonderholm 124",
    "sg:city":"Hoofddorp",
    "sg:orig_category":"Schoonheidsinstituten",
    "sg:phone":"+31 23 562 8488",
    "sg:postcode":"2133 JH",
    "sg:province":"Noord-Holland",
    "wof:name":"Face & Body Lounge",
    "wof:placetype":"venue"
},
  "geometry": {"coordinates":[4.664831,52.307049],"type":"Point"}
}