{
  "type": "Feature",
  "properties": {
    "addr:full":"Kapelwg 26 Maarn Utrecht 3951 AD",
    "addr:housenumber":"26",
    "addr:postcode":"3951 ad",
    "addr:street":"Kapelwg",
    "iso:country":"NL",
    "sg:address":"Kapelwg 26",
    "sg:city":"Maarn",
    "sg:orig_category":"Directmail",
    "sg:phone":"+31 343 442 772",
    "sg:postcode":"3951 AD",
    "sg:province":"Utrecht",
    "wof:name":"Abc Maarn",
    "wof:placetype":"venue"
},
  "geometry": {"coordinates":[5.370306,52.063313],"type":"Point"}
}