{
  "type": "Feature",
  "properties": {
    "addr:full":"Kuipershoek 42 Drimmelen Noord-Brabant 4924 BW",
    "addr:housenumber":"42",
    "addr:postcode":"4924 bw",
    "addr:street":"Kuipershoek",
    "iso:country":"NL",
    "sg:address":"Kuipershoek 42",
    "sg:city":"Drimmelen",
    "sg:orig_category":"Glaszetten",
    "sg:phone":"+31 162 687 723",
    "sg:postcode":"4924 BW",
    "sg:province":"Noord-Brabant",
    "wof:name":"Vof G & W Glas En Montage",
    "wof:placetype":"venue"
},
  "geometry": {"coordinates":[4.801451,51.707668],"type":"Point"}
}