{
  "type": "Feature",
  "properties": {
    "addr:full":"Beemsterwg 12 Almere Flevoland 1311 XC",
    "addr:housenumber":"12",
    "addr:postcode":"1311 xc",
    "addr:street":"Beemsterwg;Flevoland",
    "iso:country":"NL",
    "sg:address":"Beemsterwg 12",
    "sg:city":"Almere",
    "sg:classifiers":[
        {
            "category":"Professional",
            "type":"Services"
        }
    ],
    "sg:phone":"+31 36 521 1611",
    "sg:postcode":"1311 XC",
    "sg:province":"Flevoland",
    "sg:tags":[
        "leasing"
    ],
    "sg:website":"http://www.koopslease.nl",
    "wof:name":"Koops",
    "wof:placetype":"venue"
},
  "geometry": {"coordinates":[5.177428,52.364571],"type":"Point"}
}