{
  "type": "Feature",
  "properties": {
    "iso:country":"NL",
    "sg:address":"Hilledijk 192",
    "sg:city":"Rotterdam",
    "sg:orig_category":"Verlichting And Huishoudartikelen",
    "sg:phone":"+31 10 484 9855",
    "sg:postcode":"3074 GA",
    "sg:province":"South Holland",
    "wof:name":"De Condor Bv",
    "wof:placetype":"venue"
},
  "geometry": {"coordinates":[4.509506,51.898636],"type":"Point"}
}