{
  "type": "Feature",
  "properties": {
    "addr:full":"R Feithln 30 S Gravenhage Zuid-Holland 2533 GE",
    "addr:housenumber":"30;gravenhage",
    "addr:postcode":"2533",
    "addr:street":"S",
    "iso:country":"NL",
    "sg:address":"R Feithln 30",
    "sg:city":"S Gravenhage",
    "sg:classifiers":[
        {
            "category":"Shopping",
            "subcategory":"News",
            "type":"Retail Goods"
        }
    ],
    "sg:phone":"+31 70 367 1764",
    "sg:postcode":"2533 GE",
    "sg:province":"Zuid-Holland",
    "sg:tags":[
        "maandbladen",
        "en",
        "week-"
    ],
    "wof:name":"Zuidwest Nieuws",
    "wof:placetype":"venue"
},
  "geometry": {"coordinates":[4.2858099937,52.05286026],"type":"Point"}
}