{
  "type": "Feature",
  "properties": {
    "addr:full":"Visser 27 Deurne Noord-Brabant 5751 BL",
    "addr:housenumber":"27",
    "addr:postcode":"5751 bl",
    "addr:street":"Visser",
    "iso:country":"NL",
    "sg:address":"Visser 27",
    "sg:city":"Deurne",
    "sg:orig_category":"Verenigingsgebouwen",
    "sg:phone":"+31 493 314 757",
    "sg:postcode":"5751 BL",
    "sg:province":"Noord-Brabant",
    "wof:name":"Asteffekan",
    "wof:placetype":"venue"
},
  "geometry": {"coordinates":[5.79238,51.465607],"type":"Point"}
}