{
  "type": "Feature",
  "properties": {
    "addr:full":"Hilversumseweg 21 Laren Nh North Holland 1251 EV",
    "addr:housenumber":"21",
    "addr:street":"Hilversumseweg;Nh North",
    "iso:country":"NL",
    "sg:address":"Hilversumseweg 21",
    "sg:city":"Laren Nh",
    "sg:orig_category":"Juridische Dienstverlening",
    "sg:phone":"+31 35 531 3738",
    "sg:postcode":"1251 EV",
    "sg:province":"North Holland",
    "wof:name":"Pit Partner In Transforming",
    "wof:placetype":"venue"
},
  "geometry": {"coordinates":[5.215918,52.252575],"type":"Point"}
}