{
  "type": "Feature",
  "properties": {
    "addr:full":"Espelerwg 50 Espel Minnesota 8311 PP",
    "addr:housenumber":"50",
    "addr:postcode":"8311 pp",
    "addr:street":"Espelerwg;Minnesota",
    "iso:country":"NL",
    "sg:address":"Espelerwg 50",
    "sg:city":"Espel",
    "sg:orig_category":"Bloembollen - Groothandel",
    "sg:phone":"+31 527 276 150",
    "sg:postcode":"8311 PP",
    "sg:province":"Minnesota",
    "sg:website":"http://www.qualitybulbs.com",
    "wof:name":"Meijel Bv, Van",
    "wof:placetype":"venue"
},
  "geometry": {"coordinates":[-95.71624799999999,48.223763],"type":"Point"}
}