{
  "type": "Feature",
  "properties": {
    "addr:full":"Stationsstraat 42 Raalte Overijssel 8102 ED",
    "addr:housenumber":"42",
    "addr:postcode":"8102 ed",
    "addr:street":"Stationsstraat",
    "iso:country":"NL",
    "sg:address":"Stationsstraat 42",
    "sg:city":"Raalte",
    "sg:orig_category":"Drukkerijen And Copyshops",
    "sg:phone":"+31 572 357 500",
    "sg:postcode":"8102 ED",
    "sg:province":"Overijssel",
    "wof:name":"Drukservice Sono Bv",
    "wof:placetype":"venue"
},
  "geometry": {"coordinates":[6.275907,52.38765],"type":"Point"}
}