{
  "type": "Feature",
  "properties": {
    "iso:country":"NL",
    "sg:address":"Distelvlinder 1",
    "sg:city":"Standdaarbuiten",
    "sg:orig_category":"Verhuur",
    "sg:phone":"+31 165 317 265",
    "sg:postcode":"4758 CK",
    "sg:province":"Noord-Brabant",
    "wof:name":"Christianen, G A M",
    "wof:placetype":"venue"
},
  "geometry": {"coordinates":[4.514678,51.616867],"type":"Point"}
}