{
  "type": "Feature",
  "properties": {
    "iso:country":"NL",
    "sg:address":"Keersluiswg 17",
    "sg:city":"Almere",
    "sg:orig_category":"Drukkerijen",
    "sg:phone":"+31 36 533 0182",
    "sg:postcode":"1332 EE",
    "sg:province":"Flevoland",
    "sg:website":"http://www.drukkerijalmere.nl",
    "wof:name":"Almere Bv Drukkerij",
    "wof:placetype":"venue"
},
  "geometry": {"coordinates":[5.247614,52.410053],"type":"Point"}
}