{
  "type": "Feature",
  "properties": {
    "addr:full":"Zevenblad 8 Oss Virginia 5345 KX",
    "addr:housenumber":"8",
    "addr:postcode":"5345 kx",
    "addr:street":"Zevenblad",
    "iso:country":"NL",
    "sg:address":"Zevenblad 8",
    "sg:city":"Oss",
    "sg:orig_category":"Orthopedagogen",
    "sg:phone":"+31 412 638 268",
    "sg:postcode":"5345 KX",
    "sg:province":"Virginia",
    "wof:name":"Hoek, Drs H C",
    "wof:placetype":"venue"
},
  "geometry": {"coordinates":[-77.2352142334,38.3125991821],"type":"Point"}
}