{
  "type": "Feature",
  "properties": {
    "addr:full":"Domselaerstr 27 Amsterdam North Holland 1093 JM",
    "addr:housenumber":"27",
    "addr:postcode":"1093 jm",
    "addr:street":"Domselaerstr",
    "iso:country":"NL",
    "sg:address":"Domselaerstr 27",
    "sg:city":"Amsterdam",
    "sg:orig_category":"Kappers",
    "sg:phone":"+31 20 693 4381",
    "sg:postcode":"1093 JM",
    "sg:province":"North Holland",
    "wof:name":"Charme",
    "wof:placetype":"venue"
},
  "geometry": {"coordinates":[4.9270467758,52.3599281311],"type":"Point"}
}