{
  "type": "Feature",
  "properties": {
    "addr:full":"Keizersveld 71 Venray Limburg 5803 AP",
    "addr:housenumber":"71",
    "addr:postcode":"5803 ap",
    "addr:street":"Keizersveld",
    "iso:country":"NL",
    "sg:address":"Keizersveld 71",
    "sg:city":"Venray",
    "sg:orig_category":"Metaalbekleding And -Behandeling",
    "sg:phone":"+31 478 550 300",
    "sg:postcode":"5803 AP",
    "sg:province":"Limburg",
    "wof:name":"Phoenix Coatings Bv",
    "wof:placetype":"venue"
},
  "geometry": {"coordinates":[5.994766,51.542622],"type":"Point"}
}