{
  "type": "Feature",
  "properties": {
    "addr:full":"Broederenstraat 20 Deventer Overijssel 7411 LB",
    "addr:housenumber":"20",
    "addr:postcode":"7411 lb",
    "addr:street":"Broederenstraat",
    "iso:country":"NL",
    "sg:address":"Broederenstraat 20",
    "sg:city":"Deventer",
    "sg:orig_category":"Herenmodezaken",
    "sg:phone":"+31 570 644 151",
    "sg:postcode":"7411 LB",
    "sg:province":"Overijssel",
    "wof:name":"Eugene Mode",
    "wof:placetype":"venue"
},
  "geometry": {"coordinates":[6.157034,52.254208],"type":"Point"}
}