{
  "type": "Feature",
  "properties": {
    "addr:full":"J Vd Heydenstr 16 Oud Beyerland South Holland 3261 LE",
    "addr:housenumber":"16",
    "addr:postcode":"3261 le",
    "addr:street":"Oud Beyerland",
    "iso:country":"NL",
    "sg:address":"J Vd Heydenstr 16",
    "sg:city":"Oud Beyerland",
    "sg:orig_category":"Accountants - Administratie- Consulenten En -Kantoren",
    "sg:phone":"+31 186 642 255",
    "sg:postcode":"3261 LE",
    "sg:province":"South Holland",
    "wof:name":"Kok",
    "wof:placetype":"venue"
},
  "geometry": {"coordinates":[4.42806,51.807892],"type":"Point"}
}