{
  "type": "Feature",
  "properties": {
    "addr:full":"Wethouder Broersstraat 20 Eijsden Limburg 6245 JB",
    "addr:housenumber":"20",
    "addr:postcode":"6245 jb",
    "addr:street":"Wethouder Broersstraat",
    "iso:country":"NL",
    "sg:address":"Wethouder Broersstraat 20",
    "sg:city":"Eijsden",
    "sg:orig_category":"Kappers",
    "sg:phone":"+31 43 409 3763",
    "sg:postcode":"6245 JB",
    "sg:province":"Limburg",
    "wof:name":"Scissors, Vivian Offermans",
    "wof:placetype":"venue"
},
  "geometry": {"coordinates":[5.713985,50.776577],"type":"Point"}
}