{
  "type": "Feature",
  "properties": {
    "addr:full":"Onnemaheerd 46 Groningen Groningen 9736 AP",
    "addr:housenumber":"46",
    "addr:postcode":"9736 ap",
    "addr:street":"Onnemaheerd",
    "iso:country":"NL",
    "sg:address":"Onnemaheerd 46",
    "sg:city":"Groningen",
    "sg:classifiers":[
        {
            "category":"Professional",
            "subcategory":"Accounting & Tax Preparation",
            "type":"Services"
        }
    ],
    "sg:phone":"+31 50 541 8151",
    "sg:postcode":"9736 AP",
    "sg:province":"Groningen",
    "sg:tags":[
        "accountant"
    ],
    "wof:name":"Accent Iq Vof",
    "wof:placetype":"venue"
},
  "geometry": {"coordinates":[6.596588,53.251434],"type":"Point"}
}