{
  "type": "Feature",
  "properties": {
    "addr:full":"Trumanlaan 60 Utrecht Utrecht 3527 BR",
    "addr:housenumber":"60",
    "addr:postcode":"3527 br",
    "addr:street":"Trumanlaan",
    "iso:country":"NL",
    "sg:address":"Trumanlaan 60",
    "sg:city":"Utrecht",
    "sg:classifiers":[
        {
            "category":"Education",
            "subcategory":"Preschool",
            "type":"Public Place"
        }
    ],
    "sg:phone":"+31 30 293 6476",
    "sg:postcode":"3527 BR",
    "sg:province":"Utrecht",
    "sg:tags":[
        "kleuteronderwijs",
        "basis-"
    ],
    "wof:name":"De Zeven Gavenschool",
    "wof:placetype":"venue"
},
  "geometry": {"coordinates":[5.091294,52.076233],"type":"Point"}
}