{
  "type": "Feature",
  "properties": {
    "addr:full":"Dorpstr 9 Ulvenhout Noord-Brabant 4851 CJ",
    "addr:housenumber":"9",
    "addr:postcode":"4851 cj",
    "addr:street":"Dorpstr",
    "iso:country":"NL",
    "sg:address":"Dorpstr 9",
    "sg:city":"Ulvenhout",
    "sg:orig_category":"Nagelstudio'S",
    "sg:phone":"+31 76 560 2189",
    "sg:postcode":"4851 CJ",
    "sg:province":"Noord-Brabant",
    "wof:name":"C'Est Ca",
    "wof:placetype":"venue"
},
  "geometry": {"coordinates":[4.795535,51.553806],"type":"Point"}
}