{
  "type": "Feature",
  "properties": {
    "iso:country":"NL",
    "sg:address":"Heggenstraat 1",
    "sg:city":"Maastricht",
    "sg:orig_category":"Schoenen",
    "sg:phone":"+31 43 326 5500",
    "sg:postcode":"6211 GW",
    "sg:province":"Limburg",
    "wof:name":"Tikke Takke Tone",
    "wof:placetype":"venue"
},
  "geometry": {"coordinates":[5.691098,50.848827],"type":"Point"}
}