{
  "type": "Feature",
  "properties": {
    "iso:country":"NL",
    "sg:address":"Midstr 151",
    "sg:city":"Joure",
    "sg:orig_category":"Opticiens",
    "sg:phone":"+31 513 418 651",
    "sg:postcode":"8501 AK",
    "sg:province":"Friesland",
    "sg:website":"http://www.hansanders.nl",
    "wof:name":"Hans Anders",
    "wof:placetype":"venue"
},
  "geometry": {"coordinates":[5.7979989052,52.9663925171],"type":"Point"}
}