{
  "type": "Feature",
  "properties": {
    "iso:country":"NL",
    "sg:address":"1E Hambaken 13",
    "sg:city":"S Hertogenbosch",
    "sg:orig_category":"Verhuur",
    "sg:phone":"+31 73 642 6317",
    "sg:postcode":"5231 RA",
    "sg:province":"Noord-Brabant",
    "wof:name":"Gulik Kinderamusement, Van",
    "wof:placetype":"venue"
},
  "geometry": {"coordinates":[5.308501,51.71294],"type":"Point"}
}