{
  "type": "Feature",
  "properties": {
    "addr:full":"Nauernase Vaartdk 29 Westzaan Noord-Holland 1551 BA",
    "addr:housenumber":"29",
    "addr:postcode":"1551 ba",
    "iso:country":"NL",
    "sg:address":"Nauernase Vaartdk 29",
    "sg:city":"Westzaan",
    "sg:orig_category":"Machineonderhoud En -Reparatie",
    "sg:phone":"+31 6 25044758",
    "sg:postcode":"1551 BA",
    "sg:province":"Noord-Holland",
    "wof:name":"Smit Westzaan, J",
    "wof:placetype":"venue"
},
  "geometry": {"coordinates":[4.762548,52.458233],"type":"Point"}
}