{
  "type": "Feature",
  "properties": {
    "addr:full":"Kiefte 19 Eibergen Gelderland 7151 HZ",
    "addr:housenumber":"19",
    "addr:postcode":"7151 hz",
    "addr:street":"Kiefte;Gelderland",
    "iso:country":"NL",
    "sg:address":"Kiefte 19",
    "sg:city":"Eibergen",
    "sg:orig_category":"Meubelzaken, Woning- And Keukeninrichting",
    "sg:phone":"+31 545 476 171",
    "sg:postcode":"7151 HZ",
    "sg:province":"Gelderland",
    "wof:name":"De Romph & Schutten Meubelen Bv",
    "wof:placetype":"venue"
},
  "geometry": {"coordinates":[6.640806,52.086788],"type":"Point"}
}