{
  "type": "Feature",
  "properties": {
    "addr:full":"Europaweg 8 Groningen Groningen 9723 AS",
    "addr:housenumber":"8",
    "addr:postcode":"9723 as",
    "addr:street":"Europaweg",
    "iso:country":"NL",
    "sg:address":"Europaweg 8",
    "sg:city":"Groningen",
    "sg:orig_category":"Meubels And Huishoudapparatuur Gh",
    "sg:phone":"+31 50 319 9111",
    "sg:postcode":"9723 AS",
    "sg:province":"Groningen",
    "wof:name":"Philips Domestic Appliances And Personal Care Bv",
    "wof:placetype":"venue"
},
  "geometry": {"coordinates":[6.587069,53.212681],"type":"Point"}
}