{
  "type": "Feature",
  "properties": {
    "addr:full":"Amsterdamsestrwg 2 Maarssen Utrecht 3604 AA",
    "addr:housenumber":"2",
    "addr:postcode":"3604 aa",
    "addr:street":"Amsterdamsestrwg",
    "iso:country":"NL",
    "sg:address":"Amsterdamsestrwg 2",
    "sg:city":"Maarssen",
    "sg:orig_category":"Sportverenigingen En Ontspannings- Verenigingen",
    "sg:phone":"+31 30 244 6263",
    "sg:postcode":"3604 AA",
    "sg:province":"Utrecht",
    "wof:name":"Dwsm Sportver",
    "wof:placetype":"venue"
},
  "geometry": {"coordinates":[5.060185,52.123848],"type":"Point"}
}