{
  "type": "Feature",
  "properties": {
    "iso:country":"NL",
    "sg:address":"Stadhouderskade 69",
    "sg:city":"Amsterdam",
    "sg:orig_category":"Kunst And Kunstenaarsbenodigdheden",
    "sg:phone":"+31 20 623 2958",
    "sg:postcode":"1072 AD",
    "sg:province":"Noord-Holland",
    "wof:name":"K. & V. Waterman Kunsthandel Bv",
    "wof:placetype":"venue"
},
  "geometry": {"coordinates":[4.888819,52.358818],"type":"Point"}
}