{
  "type": "Feature",
  "properties": {
    "addr:full":"Klippenweg 4 Heerde Gelderland 8181 PC",
    "addr:housenumber":"4",
    "addr:postcode":"8181 pc",
    "addr:street":"Klippenweg;Gelderland",
    "iso:country":"NL",
    "sg:address":"Klippenweg 4",
    "sg:city":"Heerde",
    "sg:orig_category":"Kampeerterreinen",
    "sg:phone":"+31 578 696 690",
    "sg:postcode":"8181 PC",
    "sg:province":"Gelderland",
    "wof:name":"Camping De Klippen",
    "wof:placetype":"venue"
},
  "geometry": {"coordinates":[6.0065808296,52.377784729],"type":"Point"}
}