{
  "type": "Feature",
  "properties": {
    "addr:full":"Kerkwg O 226 Waddinxveen Zuid-Holland 2741 HA",
    "addr:housenumber":"226",
    "addr:postcode":"waddinxveen;2741 ha",
    "iso:country":"NL",
    "sg:address":"Kerkwg O 226",
    "sg:city":"Waddinxveen",
    "sg:classifiers":[
        {
            "category":"Travel",
            "subcategory":"Hotels & Motels",
            "type":"Entertainment"
        }
    ],
    "sg:phone":"+31 182 612 103",
    "sg:postcode":"2741 HA",
    "sg:province":"Zuid-Holland",
    "sg:website":"http://www.tref.nl/waddinxveen/h-c-r-de-unie.nl",
    "wof:name":"Unie, De",
    "wof:placetype":"venue"
},
  "geometry": {"coordinates":[4.65692,52.044468],"type":"Point"}
}