{
  "type": "Feature",
  "properties": {
    "addr:full":"Westermarkt 2 Amsterdam Noord-Holland 1016 DK",
    "addr:housenumber":"2",
    "addr:postcode":"1016 dk",
    "addr:street":"Westermarkt",
    "iso:country":"NL",
    "sg:address":"Westermarkt 2",
    "sg:city":"Amsterdam",
    "sg:orig_category":"Advocaten And Juridische Adviseurs",
    "sg:phone":"+31 20 626 1441",
    "sg:postcode":"1016 DK",
    "sg:province":"Noord-Holland",
    "wof:name":"Bakker & Brouns",
    "wof:placetype":"venue"
},
  "geometry": {"coordinates":[-74.110527,42.937237],"type":"Point"}
}