{
  "type": "Feature",
  "properties": {
    "addr:full":"Oude Enghwg 14 Hilversum Noord-Holland 1217 JC",
    "addr:housenumber":"14",
    "addr:postcode":"1217 jc",
    "addr:street":"Oude Enghwg",
    "iso:country":"NL",
    "sg:address":"Oude Enghwg 14",
    "sg:city":"Hilversum",
    "sg:orig_category":"Hypotheken",
    "sg:phone":"+31 35 640 0800",
    "sg:postcode":"1217 JC",
    "sg:province":"Noord-Holland",
    "sg:website":"http://www.hilversum.hypotheekshop.nl/420",
    "wof:name":"Hypotheekshop, De",
    "wof:placetype":"venue"
},
  "geometry": {"coordinates":[5.171023,52.227791],"type":"Point"}
}