{
  "type": "Feature",
  "properties": {
    "addr:full":"Zomerstr 12 Ellewoutsdyk Zeeland 4437 AE",
    "addr:housenumber":"12",
    "addr:postcode":"4437 ae",
    "addr:street":"Zomerstr;Zeeland",
    "iso:country":"NL",
    "sg:address":"Zomerstr 12",
    "sg:city":"Ellewoutsdyk",
    "sg:orig_category":"Postkantoren",
    "sg:phone":"+31 113 548 278",
    "sg:postcode":"4437 AE",
    "sg:province":"Zeeland",
    "wof:name":"Postkantoren",
    "wof:placetype":"venue"
},
  "geometry": {"coordinates":[3.816465,51.389351],"type":"Point"}
}