{
  "type": "Feature",
  "properties": {
    "addr:full":"Bonairepln 9 Amsterdam North Holland 1058 XA",
    "addr:housenumber":"9",
    "addr:postcode":"1058 xa",
    "addr:street":"Bonairepln",
    "iso:country":"NL",
    "sg:address":"Bonairepln 9",
    "sg:city":"Amsterdam",
    "sg:orig_category":"Meubelmakerijen",
    "sg:phone":"+31 20 689 5107",
    "sg:postcode":"1058 XA",
    "sg:province":"North Holland",
    "wof:name":"Verhouter, De",
    "wof:placetype":"venue"
},
  "geometry": {"coordinates":[4.855597,52.361256],"type":"Point"}
}