{
  "type": "Feature",
  "properties": {
    "addr:full":"Postbus 299 Spykenisse South Holland 3200 AG",
    "addr:housenumber":"299",
    "addr:postcode":"3200",
    "addr:street":"Postbus",
    "iso:country":"NL",
    "sg:address":"Postbus 299",
    "sg:city":"Spykenisse",
    "sg:orig_category":"Begrafenisverzorging",
    "sg:phone":"+31 181 630 301",
    "sg:postcode":"3200 AG",
    "sg:province":"South Holland",
    "sg:website":"http://www.xs4all/~cenm.nl",
    "wof:name":"C & M Spijkenisse",
    "wof:placetype":"venue"
},
  "geometry": {"coordinates":[4.35844,51.837879],"type":"Point"}
}