{
  "type": "Feature",
  "properties": {
    "addr:full":"Grotestraat 18 Ede Gld Gelderland 6711 AM",
    "addr:housenumber":"18;6711",
    "addr:street":"Grotestraat;Gld Gelderland",
    "iso:country":"NL",
    "sg:address":"Grotestraat 18",
    "sg:city":"Ede Gld",
    "sg:orig_category":"Schoenen",
    "sg:phone":"+31 318 693 639",
    "sg:postcode":"6711 AM",
    "sg:province":"Gelderland",
    "wof:name":"Haren Bv, Van",
    "wof:placetype":"venue"
},
  "geometry": {"coordinates":[5.670267,52.044308],"type":"Point"}
}