{
  "type": "Feature",
  "properties": {
    "addr:full":"Lange Stammerdijk 18 Amsterdam Zuidoost Noord-Holland 1109 BN",
    "addr:housenumber":"18",
    "addr:postcode":"zuidoost;1109 bn",
    "addr:street":"Lange Stammerdijk",
    "iso:country":"NL",
    "sg:address":"Lange Stammerdijk 18",
    "sg:city":"Amsterdam Zuidoost",
    "sg:orig_category":"Kappers",
    "sg:phone":"+31 294 417 791",
    "sg:postcode":"1109 BN",
    "sg:province":"Noord-Holland",
    "wof:name":"Hairstyliste Rianne Griffioen",
    "wof:placetype":"venue"
},
  "geometry": {"coordinates":[5.0110831261,52.3069458008],"type":"Point"}
}