{
  "type": "Feature",
  "properties": {
    "addr:full":"Alferbos 83 Zoetermeer Zuid-Holland 2715 TD",
    "addr:housenumber":"83",
    "addr:postcode":"2715 td",
    "addr:street":"Alferbos",
    "iso:country":"NL",
    "sg:address":"Alferbos 83",
    "sg:city":"Zoetermeer",
    "sg:orig_category":"Adviesbureaus Bedrijfsorganisatie",
    "sg:phone":"+31 79 323 7224",
    "sg:postcode":"2715 TD",
    "sg:province":"Zuid-Holland",
    "wof:name":"Balhuizen",
    "wof:placetype":"venue"
},
  "geometry": {"coordinates":[4.476202,52.056152],"type":"Point"}
}