{
  "type": "Feature",
  "properties": {
    "addr:full":"Panovenwg 4 Helmond Noord-Brabant 5708 HR",
    "addr:housenumber":"4",
    "addr:postcode":"5708 hr",
    "addr:street":"Panovenwg",
    "iso:country":"NL",
    "sg:address":"Panovenwg 4",
    "sg:city":"Helmond",
    "sg:orig_category":"Medische Keuringen",
    "sg:phone":"+31 492 594 444",
    "sg:postcode":"5708 HR",
    "sg:province":"Noord-Brabant",
    "sg:website":"http://www.zvnadvies.nl",
    "wof:name":"Argonaut",
    "wof:placetype":"venue"
},
  "geometry": {"coordinates":[5.629802,51.474964],"type":"Point"}
}