{
  "type": "Feature",
  "properties": {
    "addr:full":"Jacob Catsstraat 70 Putten Gelderland 3881 XR",
    "addr:housenumber":"70",
    "addr:postcode":"3881 xr",
    "addr:street":"Jacob Catsstraat;Gelderland",
    "iso:country":"NL",
    "sg:address":"Jacob Catsstraat 70",
    "sg:city":"Putten",
    "sg:classifiers":[
        {
            "category":"Education",
            "subcategory":"Preschool",
            "type":"Public Place"
        }
    ],
    "sg:phone":"+31 341 353 541",
    "sg:postcode":"3881 XR",
    "sg:province":"Gelderland",
    "sg:tags":[
        "kleuteronderwijs",
        "basis-"
    ],
    "wof:name":"Basisschool Met De Bijbel De Akker",
    "wof:placetype":"venue"
},
  "geometry": {"coordinates":[5.611925,52.25378],"type":"Point"}
}