{
  "type": "Feature",
  "properties": {
    "addr:full":"Schoterlandsewg 221 Jubbega Friesland 8411 ZE",
    "addr:housenumber":"221",
    "addr:postcode":"8411 ze",
    "iso:country":"NL",
    "sg:address":"Schoterlandsewg 221",
    "sg:city":"Jubbega",
    "sg:orig_category":"Verenigingsgebouwen",
    "sg:phone":"+31 516 463 034",
    "sg:postcode":"8411 ZE",
    "sg:province":"Friesland",
    "wof:name":"Piepegaeltsje, Dorpshuis It",
    "wof:placetype":"venue"
},
  "geometry": {"coordinates":[6.14549,52.987091],"type":"Point"}
}