{
  "type": "Feature",
  "properties": {
    "addr:full":"Nw Koekoekstr 61 Utrecht Utrecht 3514 EB",
    "addr:housenumber":"61",
    "addr:postcode":"3514 eb",
    "iso:country":"NL",
    "sg:address":"Nw Koekoekstr 61",
    "sg:city":"Utrecht",
    "sg:orig_category":"Psychologen",
    "sg:phone":"+31 6 41237064",
    "sg:postcode":"3514 EB",
    "sg:province":"Utrecht",
    "wof:name":"Klamer",
    "wof:placetype":"venue"
},
  "geometry": {"coordinates":[5.11971,52.098213],"type":"Point"}
}