{
  "type": "Feature",
  "properties": {
    "addr:full":"Nettelhorststr 121 S Gravenhage Zuid-Holland 2532 BP",
    "addr:housenumber":"121;gravenhage",
    "addr:postcode":"2532 bp",
    "addr:street":"S",
    "iso:country":"NL",
    "sg:address":"Nettelhorststr 121",
    "sg:city":"S Gravenhage",
    "sg:orig_category":"Exploitatie- Maatschappijen",
    "sg:phone":"+31 70 366 3843",
    "sg:postcode":"2532 BP",
    "sg:province":"Zuid-Holland",
    "wof:name":"Gaby",
    "wof:placetype":"venue"
},
  "geometry": {"coordinates":[4.29807,52.048569],"type":"Point"}
}