{
  "type": "Feature",
  "properties": {
    "addr:full":"Mounebuorren 41 Engwierum Provincie Friesland 9132 EJ",
    "addr:housenumber":"41",
    "addr:postcode":"9132 ej",
    "addr:street":"Mounebuorren;Provincie Friesland",
    "iso:country":"NL",
    "sg:address":"Mounebuorren 41",
    "sg:city":"Engwierum",
    "sg:orig_category":"Bloemen- And Plantenteelt",
    "sg:phone":"+31 511 408 250",
    "sg:postcode":"9132 EJ",
    "sg:province":"Provincie Friesland",
    "wof:name":"J.W.P. 'S Bloemzaden",
    "wof:placetype":"venue"
},
  "geometry": {"coordinates":[6.142532,53.325024],"type":"Point"}
}