{
  "type": "Feature",
  "properties": {
    "addr:full":"Vlaardingerdk 61B Schiedam South Holland 3117 ED",
    "addr:housenumber":"61b",
    "addr:postcode":"3117 ed",
    "addr:street":"Vlaardingerdk",
    "iso:country":"NL",
    "sg:address":"Vlaardingerdk 61B",
    "sg:city":"Schiedam",
    "sg:orig_category":"Kappers",
    "sg:phone":"+31 10 473 7669",
    "sg:postcode":"3117 ED",
    "sg:province":"South Holland",
    "wof:name":"San",
    "wof:placetype":"venue"
},
  "geometry": {"coordinates":[4.390138,51.91629],"type":"Point"}
}