{
  "type": "Feature",
  "properties": {
    "addr:full":"Baroniebaan 1 Tilburg Noord-Brabant 5032 TA",
    "addr:housenumber":"1",
    "addr:postcode":"5032 ta",
    "addr:street":"Baroniebaan",
    "iso:country":"NL",
    "sg:address":"Baroniebaan 1",
    "sg:city":"Tilburg",
    "sg:orig_category":"Verenigingen En Stichtingen",
    "sg:phone":"+31 13 463 1978",
    "sg:postcode":"5032 TA",
    "sg:province":"Noord-Brabant",
    "wof:name":"Dahliaver Flora",
    "wof:placetype":"venue"
},
  "geometry": {"coordinates":[5.043733,51.556305],"type":"Point"}
}