{
  "type": "Feature",
  "properties": {
    "addr:full":"Fultonstraat 115 'S Gravenhage Zuid-Holland 2562 XD",
    "addr:housenumber":"115 '",
    "addr:postcode":"2562 xd",
    "addr:street":"Fultonstraat",
    "iso:country":"NL",
    "sg:address":"Fultonstraat 115",
    "sg:city":"'S Gravenhage",
    "sg:orig_category":"Schilderwerk",
    "sg:phone":"+31 70 362 3903",
    "sg:postcode":"2562 XD",
    "sg:province":"Zuid-Holland",
    "wof:name":"Willem Van Der Kaag",
    "wof:placetype":"venue"
},
  "geometry": {"coordinates":[4.277918,52.075134],"type":"Point"}
}