{
  "type": "Feature",
  "properties": {
    "addr:full":"Groningerwg 33 Groningen Groningen 9738 AB",
    "addr:housenumber":"33",
    "addr:postcode":"9738 ab",
    "addr:street":"Groningerwg",
    "iso:country":"NL",
    "sg:address":"Groningerwg 33",
    "sg:city":"Groningen",
    "sg:orig_category":"Beeldende Kunstenaars",
    "sg:phone":"+31 50 579 0798",
    "sg:postcode":"9738 AB",
    "sg:province":"Groningen",
    "wof:name":"Keuken, M",
    "wof:placetype":"venue"
},
  "geometry": {"coordinates":[6.572886,53.244095],"type":"Point"}
}