{
  "type": "Feature",
  "properties": {
    "iso:country":"NL",
    "sg:address":"Van Noortstraat 42",
    "sg:city":"Nijkerkerveen",
    "sg:classifiers":[
        {
            "category":"Education",
            "subcategory":"Preschool",
            "type":"Public Place"
        }
    ],
    "sg:phone":"+31 33 257 1968",
    "sg:postcode":"3864 EV",
    "sg:province":"Gelderland",
    "sg:tags":[
        "kleuteronderwijs",
        "basis-"
    ],
    "wof:name":"C.J. Van Rootselaarschool",
    "wof:placetype":"venue"
},
  "geometry": {"coordinates":[5.468461,52.195499],"type":"Point"}
}