{
  "type": "Feature",
  "properties": {
    "addr:full":"Biltstraat 60 Utrecht Utrecht 3572 BD",
    "addr:housenumber":"60",
    "addr:postcode":"3572 bd",
    "addr:street":"Biltstraat",
    "iso:country":"NL",
    "sg:address":"Biltstraat 60",
    "sg:city":"Utrecht",
    "sg:orig_category":"Makelaars In Onroerend Goed",
    "sg:phone":"+31 30 271 7188",
    "sg:postcode":"3572 BD",
    "sg:province":"Utrecht",
    "wof:name":"Domicilie Makelaars",
    "wof:placetype":"venue"
},
  "geometry": {"coordinates":[5.129142,52.095249],"type":"Point"}
}