{
  "type": "Feature",
  "properties": {
    "addr:full":"Bospolder 21 Honselersdijk South Holland 2675 BL",
    "addr:housenumber":"21",
    "addr:postcode":"2675 bl",
    "addr:street":"Bospolder",
    "iso:country":"NL",
    "sg:address":"Bospolder 21",
    "sg:city":"Honselersdijk",
    "sg:orig_category":"Bloemen- And Plantenteelt",
    "sg:phone":"+31 174 621 221",
    "sg:postcode":"2675 BL",
    "sg:province":"South Holland",
    "wof:name":"Penning Freesia Bv",
    "wof:placetype":"venue"
},
  "geometry": {"coordinates":[4.209649,52.012775],"type":"Point"}
}