{
  "type": "Feature",
  "properties": {
    "addr:full":"Bruglaan 4 Aadorp NL.08 7611 BL",
    "addr:housenumber":"4;nl.08",
    "addr:postcode":"7611 bl",
    "addr:street":"Bruglaan",
    "iso:country":"NL",
    "sg:address":"Bruglaan 4",
    "sg:city":"Aadorp",
    "sg:orig_category":"Autokeuringen",
    "sg:phone":"+31 546 575 577",
    "sg:postcode":"7611 BL",
    "sg:province":"NL.08",
    "wof:name":"Vof Autobedrijf 'De Tunnel",
    "wof:placetype":"venue"
},
  "geometry": {"coordinates":[6.628976,52.374622],"type":"Point"}
}