{
  "type": "Feature",
  "properties": {
    "addr:full":"Wilbertstraat 48 Hengelo Ov Overijssel 7556 WL",
    "addr:housenumber":"48",
    "addr:postcode":"7556 wl",
    "addr:street":"Wilbertstraat;Ov",
    "iso:country":"NL",
    "sg:address":"Wilbertstraat 48",
    "sg:city":"Hengelo Ov",
    "sg:orig_category":"Loodgieterswerk, Verwarming And Sanitaire Installaties",
    "sg:phone":"+31 74 242 6841",
    "sg:postcode":"7556 WL",
    "sg:province":"Overijssel",
    "wof:name":"A F P Veldhuis",
    "wof:placetype":"venue"
},
  "geometry": {"coordinates":[6.784993,52.275833],"type":"Point"}
}