{
  "type": "Feature",
  "properties": {
    "iso:country":"NL",
    "sg:address":"Markwg 9A",
    "sg:city":"Renkum",
    "sg:orig_category":"Adviesbureaus Bedrijfsorganisatie",
    "sg:phone":"+31 317 350 325",
    "sg:postcode":"6871 KW",
    "sg:province":"Gelderland",
    "wof:name":"Edelkoort",
    "wof:placetype":"venue"
},
  "geometry": {"coordinates":[5.746435,51.986832],"type":"Point"}
}