{
  "type": "Feature",
  "properties": {
    "addr:full":"Herenstr 27 Voorburg Zuid-Holland 2271 CA",
    "addr:housenumber":"27",
    "addr:postcode":"2271 ca",
    "addr:street":"Herenstr",
    "iso:country":"NL",
    "sg:address":"Herenstr 27",
    "sg:city":"Voorburg",
    "sg:orig_category":"Fotografie Reclame En Mode",
    "sg:phone":"+31 70 387 3295",
    "sg:postcode":"2271 CA",
    "sg:province":"Zuid-Holland",
    "wof:name":"Schimmel En Van Son",
    "wof:placetype":"venue"
},
  "geometry": {"coordinates":[4.365949,52.068829],"type":"Point"}
}