{
  "type": "Feature",
  "properties": {
    "iso:country":"NL",
    "sg:address":"Kromsteeg 18",
    "sg:city":"Kerkdriel",
    "sg:orig_category":"Meubelzaken, Woning- And Keukeninrichting",
    "sg:phone":"+31 418 631 255",
    "sg:postcode":"5331 AK",
    "sg:province":"Gelderland",
    "wof:name":"Arn. Van Eeuwijk",
    "wof:placetype":"venue"
},
  "geometry": {"coordinates":[5.334039,51.773506],"type":"Point"}
}