{
  "type": "Feature",
  "properties": {
    "addr:full":"Hoefkade 1502 'S Gravenhage South Holland 2525 HS",
    "addr:housenumber":"1502 '",
    "addr:postcode":"2525 hs",
    "addr:street":"Hoefkade",
    "iso:country":"NL",
    "sg:address":"Hoefkade 1502",
    "sg:city":"'S Gravenhage",
    "sg:orig_category":"Kappers",
    "sg:phone":"+31 70 389 5576",
    "sg:postcode":"2525 HS",
    "sg:province":"South Holland",
    "wof:name":"Kapsalon Kabadokya",
    "wof:placetype":"venue"
},
  "geometry": {"coordinates":[4.2960119247,52.0604400635],"type":"Point"}
}