{
  "type": "Feature",
  "properties": {
    "addr:full":"Vondellaan 47 Leiden South Holland 2332 AA",
    "addr:housenumber":"47",
    "addr:postcode":"2332 aa",
    "addr:street":"Vondellaan",
    "iso:country":"NL",
    "sg:address":"Vondellaan 47",
    "sg:city":"Leiden",
    "sg:classifiers":[
        {
            "category":"Parking",
            "subcategory":"Lot",
            "type":"Transportation"
        }
    ],
    "sg:phone":"+31 71 532 3110",
    "sg:postcode":"2332 AA",
    "sg:province":"South Holland",
    "sg:tags":[
        "fab",
        "metalen",
        "tank"
    ],
    "wof:name":"Heerema Oil And Gas Development Bv",
    "wof:placetype":"venue"
},
  "geometry": {"coordinates":[4.474165,52.162544],"type":"Point"}
}