{
  "type": "Feature",
  "properties": {
    "addr:full":"Bokkerijder 9 Bergeyk North Brabant 5571 MX",
    "addr:housenumber":"9",
    "addr:postcode":"5571 mx",
    "addr:street":"Bokkerijder",
    "iso:country":"NL",
    "sg:address":"Bokkerijder 9",
    "sg:city":"Bergeyk",
    "sg:orig_category":"Metaalbekleding And -Behandeling",
    "sg:phone":"+31 497 572 731",
    "sg:postcode":"5571 MX",
    "sg:province":"North Brabant",
    "wof:name":"P.A. Theuws",
    "wof:placetype":"venue"
},
  "geometry": {"coordinates":[5.33637,51.31905],"type":"Point"}
}