{
  "type": "Feature",
  "properties": {
    "addr:full":"F V Eedenln 6 Leiden South Holland 2321 BD",
    "addr:housenumber":"6",
    "addr:postcode":"2321 bd",
    "addr:street":"Eedenln",
    "iso:country":"NL",
    "sg:address":"F V Eedenln 6",
    "sg:city":"Leiden",
    "sg:orig_category":"Keukens",
    "sg:phone":"+31 71 531 1764",
    "sg:postcode":"2321 BD",
    "sg:province":"South Holland",
    "wof:name":"Holverda",
    "wof:placetype":"venue"
},
  "geometry": {"coordinates":[4.48449,52.149212],"type":"Point"}
}