{
  "type": "Feature",
  "properties": {
    "iso:country":"NL",
    "sg:address":"Parmentierstr 12",
    "sg:city":"Hoogeveen",
    "sg:orig_category":"Pluimveeslachterijen",
    "sg:phone":"+31 528 280 840",
    "sg:postcode":"7903 TP",
    "sg:province":"Provincie Drenthe",
    "sg:website":"http://www.heijsgroep.nl",
    "wof:name":"Heijs Food Products",
    "wof:placetype":"venue"
},
  "geometry": {"coordinates":[6.515868,52.73423],"type":"Point"}
}