{
  "type": "Feature",
  "properties": {
    "addr:full":"Itersondomein 4 Maastricht Limburg 6229 ED",
    "addr:housenumber":"4",
    "addr:postcode":"6229 ed",
    "addr:street":"Itersondomein",
    "iso:country":"NL",
    "sg:address":"Itersondomein 4",
    "sg:city":"Maastricht",
    "sg:orig_category":"Adviesbureaus Bouwkunde",
    "sg:phone":"+31 43 361 4873",
    "sg:postcode":"6229 ED",
    "sg:province":"Limburg",
    "wof:name":"Casa Nova",
    "wof:placetype":"venue"
},
  "geometry": {"coordinates":[5.709274,50.837357],"type":"Point"}
}