{
  "type": "Feature",
  "properties": {
    "addr:full":"Ptr V Donstr 3 Heibloem Limburg 6089 NM",
    "addr:housenumber":"3",
    "addr:postcode":"6089",
    "addr:street":"Donstr",
    "iso:country":"NL",
    "sg:address":"Ptr V Donstr 3",
    "sg:city":"Heibloem",
    "sg:classifiers":[
        {
            "category":"Food & Beverages",
            "subcategory":"Bakery",
            "type":"Retail Goods"
        }
    ],
    "sg:phone":"+31 475 495 137",
    "sg:postcode":"6089 NM",
    "sg:province":"Limburg",
    "sg:tags":[
        "brood",
        "en",
        "banket"
    ],
    "wof:name":"Nijssen, Christine",
    "wof:placetype":"venue"
},
  "geometry": {"coordinates":[5.895682,51.301228],"type":"Point"}
}