{
  "type": "Feature",
  "properties": {
    "addr:full":"Witsenborgstraat 7 Hoogeveen Drenthe 7906 NN",
    "addr:housenumber":"7",
    "addr:postcode":"7906 nn",
    "addr:street":"Witsenborgstraat",
    "iso:country":"NL",
    "sg:address":"Witsenborgstraat 7",
    "sg:city":"Hoogeveen",
    "sg:orig_category":"Zuivelproducten",
    "sg:phone":"+31 528 230 591",
    "sg:postcode":"7906 NN",
    "sg:province":"Drenthe",
    "wof:name":"Koekoek Kaas, Noten En Wijnen",
    "wof:placetype":"venue"
},
  "geometry": {"coordinates":[6.491794,52.717484],"type":"Point"}
}