{
  "type": "Feature",
  "properties": {
    "addr:full":"Schoolstr 28 Ryswyk Zh Zuid-Holland 2282 RD",
    "addr:housenumber":"28",
    "addr:postcode":"2282 rd",
    "addr:street":"Schoolstr",
    "iso:country":"NL",
    "sg:address":"Schoolstr 28",
    "sg:city":"Ryswyk Zh",
    "sg:orig_category":"Onroerende Goederen",
    "sg:phone":"+31 70 395 1400",
    "sg:postcode":"2282 RD",
    "sg:province":"Zuid-Holland",
    "wof:name":"Vetron",
    "wof:placetype":"venue"
},
  "geometry": {"coordinates":[4.33694,52.056503],"type":"Point"}
}