{
  "type": "Feature",
  "properties": {
    "addr:full":"Koolenstr 14 Oss CN. 5344 HK",
    "addr:housenumber":"14",
    "addr:postcode":"5344 hk",
    "addr:street":"Koolenstr;Cn.",
    "iso:country":"NL",
    "sg:address":"Koolenstr 14",
    "sg:city":"Oss",
    "sg:orig_category":"Adviesbureaus Bedrijfsorganisatie",
    "sg:phone":"+31 412 646 887",
    "sg:postcode":"5344 HK",
    "sg:province":"CN.",
    "wof:name":"Kraak Bv",
    "wof:placetype":"venue"
},
  "geometry": {"coordinates":[114.153542,22.411249],"type":"Point"}
}