{
  "type": "Feature",
  "properties": {
    "addr:full":"Prof K Onnesln 101 Schiedam Zuid-Holland 3112 VC",
    "addr:housenumber":"101",
    "addr:postcode":"3112 vc",
    "addr:street":"Prof K Onnesln",
    "iso:country":"NL",
    "sg:address":"Prof K Onnesln 101",
    "sg:city":"Schiedam",
    "sg:orig_category":"Wasmachines En Wasdrogers",
    "sg:phone":"+31 10 426 8832",
    "sg:postcode":"3112 VC",
    "sg:province":"Zuid-Holland",
    "sg:website":"http://www.martinelectronica.nl",
    "wof:name":"Martin Electr Serv",
    "wof:placetype":"venue"
},
  "geometry": {"coordinates":[4.4107718468,51.9191970825],"type":"Point"}
}