{
  "type": "Feature",
  "properties": {
    "iso:country":"NL",
    "sg:address":"Essensewg 47",
    "sg:city":"Nispen",
    "sg:orig_category":"Bloemen En Planten - Groothandel",
    "sg:phone":"+31 165 365 355",
    "sg:postcode":"4709 RB",
    "sg:province":"Noord-Brabant",
    "sg:website":"http://www.gova.nl",
    "wof:name":"Gova",
    "wof:placetype":"venue"
},
  "geometry": {"coordinates":[4.460461,51.47504],"type":"Point"}
}