{
  "type": "Feature",
  "properties": {
    "addr:full":"Zuiddk 20 St Philipsland Zeeland 4675 BC",
    "addr:housenumber":"20",
    "addr:postcode":"4675 bc",
    "addr:street":"Zuiddk",
    "iso:country":"NL",
    "sg:address":"Zuiddk 20",
    "sg:city":"St Philipsland",
    "sg:classifiers":[
        {
            "category":"Retail",
            "subcategory":"Auto Repair",
            "type":"Services"
        }
    ],
    "sg:phone":"+31 167 573 810",
    "sg:postcode":"4675 BC",
    "sg:province":"Zeeland",
    "sg:tags":[
        "garage"
    ],
    "wof:name":"Perfect Gear",
    "wof:placetype":"venue"
},
  "geometry": {"coordinates":[4.1653690338,51.6145935059],"type":"Point"}
}