{
  "type": "Feature",
  "properties": {
    "addr:full":"Zeestraat 11 Beverwijk Noord-Holland 1941 AJ",
    "addr:housenumber":"11",
    "addr:postcode":"1941 aj",
    "addr:street":"Zeestraat",
    "iso:country":"NL",
    "sg:address":"Zeestraat 11",
    "sg:city":"Beverwijk",
    "sg:classifiers":[
        {
            "category":"Fast Food",
            "type":"Food & Drink"
        }
    ],
    "sg:phone":"+31 251 214 619",
    "sg:postcode":"1941 AJ",
    "sg:province":"Noord-Holland",
    "sg:tags":[
        "afhaal",
        "restaurant"
    ],
    "wof:name":"Alexandria Eetsalon",
    "wof:placetype":"venue"
},
  "geometry": {"coordinates":[4.654969,52.480995],"type":"Point"}
}