{
  "type": "Feature",
  "properties": {
    "iso:country":"NL",
    "sg:address":"L Groenendaal 93",
    "sg:city":"Gouda",
    "sg:orig_category":"Woninginrichting",
    "sg:phone":"+31 182 519 013",
    "sg:postcode":"2801 LS",
    "sg:province":"Zuid-Holland",
    "wof:name":"Kempen, Van",
    "wof:placetype":"venue"
},
  "geometry": {"coordinates":[4.7079620361,52.0105056763],"type":"Point"}
}