{
  "type": "Feature",
  "properties": {
    "addr:full":"Zandstraat 33 Veenendaal Utrecht 3901 CJ",
    "addr:housenumber":"33",
    "addr:postcode":"3901 cj",
    "addr:street":"Zandstraat",
    "iso:country":"NL",
    "sg:address":"Zandstraat 33",
    "sg:city":"Veenendaal",
    "sg:orig_category":"Kunst And Kunstenaarsbenodigdheden",
    "sg:phone":"+31 318 555 652",
    "sg:postcode":"3901 CJ",
    "sg:province":"Utrecht",
    "wof:name":"Erwin Arts.",
    "wof:placetype":"venue"
},
  "geometry": {"coordinates":[5.554987,52.028912],"type":"Point"}
}