{
  "type": "Feature",
  "properties": {
    "addr:full":"Lage Witsiebaan 28 Tilburg North Brabant 5042 DA",
    "addr:housenumber":"28",
    "addr:postcode":"5042 da",
    "addr:street":"Lage Witsiebaan",
    "iso:country":"NL",
    "sg:address":"Lage Witsiebaan 28",
    "sg:city":"Tilburg",
    "sg:orig_category":"Juridische Dienstverlening",
    "sg:phone":"+31 13 542 7254",
    "sg:postcode":"5042 DA",
    "sg:province":"North Brabant",
    "wof:name":"Faam",
    "wof:placetype":"venue"
},
  "geometry": {"coordinates":[5.060961,51.572762],"type":"Point"}
}