{
  "type": "Feature",
  "properties": {
    "iso:country":"NL",
    "sg:address":"Bg Ruitenbeekerf 101",
    "sg:city":"Nykerkerveen",
    "sg:orig_category":"Administratie- En Boekhoudkantoren",
    "sg:phone":"+31 33 257 2881",
    "sg:postcode":"3864 PL",
    "sg:province":"Gelderland",
    "wof:name":"Blankestijn, B",
    "wof:placetype":"venue"
},
  "geometry": {"coordinates":[5.453913,52.199108],"type":"Point"}
}