{
  "type": "Feature",
  "properties": {
    "addr:full":"Grotestraat 125 Almelo Overijssel 7607 CH",
    "addr:housenumber":"125",
    "addr:postcode":"7607",
    "addr:street":"Grotestraat",
    "iso:country":"NL",
    "sg:address":"Grotestraat 125",
    "sg:city":"Almelo",
    "sg:orig_category":"Werving And Selectie Van Tijdelijk Personeel And Uitzendkantoren",
    "sg:phone":"+31 546 825 100",
    "sg:postcode":"7607 CH",
    "sg:province":"Overijssel",
    "wof:name":"Vedior",
    "wof:placetype":"venue"
},
  "geometry": {"coordinates":[6.6659779549,52.3546028137],"type":"Point"}
}