{
  "type": "Feature",
  "properties": {
    "addr:full":"Hancateweg 3 Hellendoorn Overijssel 7447 PW",
    "addr:housenumber":"3",
    "addr:postcode":"7447 pw",
    "addr:street":"Hancateweg",
    "iso:country":"NL",
    "sg:address":"Hancateweg 3",
    "sg:city":"Hellendoorn",
    "sg:orig_category":"Huizensloop And Bouwrijp Maken",
    "sg:phone":"+31 546 671 229",
    "sg:postcode":"7447 PW",
    "sg:province":"Overijssel",
    "wof:name":"Wemekamp'S Loonbedrijf",
    "wof:placetype":"venue"
},
  "geometry": {"coordinates":[6.439053,52.433556],"type":"Point"}
}