{
  "type": "Feature",
  "properties": {
    "addr:full":"Orthenstr 23 S Hertogenbosch Noord-Brabant 5211 SV",
    "addr:housenumber":"23",
    "addr:postcode":"5211 sv",
    "addr:street":"Orthenstr;S",
    "iso:country":"NL",
    "sg:address":"Orthenstr 23",
    "sg:city":"S Hertogenbosch",
    "sg:orig_category":"Hoortoestellen",
    "sg:phone":"+31 73 613 8922",
    "sg:postcode":"5211 SV",
    "sg:province":"Noord-Brabant",
    "sg:website":"http://www.schoonenberg.nl",
    "wof:name":"Schoonenberg Hoorcomfort",
    "wof:placetype":"venue"
},
  "geometry": {"coordinates":[5.301261,51.691086],"type":"Point"}
}