{
  "type": "Feature",
  "properties": {
    "iso:country":"NL",
    "sg:address":"Margrietstraat 9",
    "sg:city":"Culemborg",
    "sg:orig_category":"Kappers",
    "sg:phone":"+31 345 515 711",
    "sg:postcode":"4101 JH",
    "sg:province":"Gelderland",
    "wof:name":"M G J Sielhorst-Fremerie",
    "wof:placetype":"venue"
},
  "geometry": {"coordinates":[5.236048,51.957745],"type":"Point"}
}