{
  "type": "Feature",
  "properties": {
    "iso:country":"NL",
    "sg:address":"Rijnstraat 79",
    "sg:city":"Woerden",
    "sg:classifiers":[
        {
            "category":"Bakery",
            "type":"Food & Drink"
        }
    ],
    "sg:phone":"+31 348 431 319",
    "sg:postcode":"3441 BR",
    "sg:province":"Utrecht",
    "sg:tags":[
        "brood",
        "banket"
    ],
    "wof:name":"Vof De Limburgse Vlaaierie",
    "wof:placetype":"venue"
},
  "geometry": {"coordinates":[4.886266,52.085613],"type":"Point"}
}