{
  "type": "Feature",
  "properties": {
    "addr:full":"Schapenweg 3 Ulrum Groningen 9971 AH",
    "addr:housenumber":"3",
    "addr:postcode":"9971 ah",
    "addr:street":"Schapenweg",
    "iso:country":"NL",
    "sg:address":"Schapenweg 3",
    "sg:city":"Ulrum",
    "sg:orig_category":"Goederenvervoer Over De Weg",
    "sg:phone":"+31 595 402 087",
    "sg:postcode":"9971 AH",
    "sg:province":"Groningen",
    "wof:name":"Transportbedrijf T Buwalda",
    "wof:placetype":"venue"
},
  "geometry": {"coordinates":[6.334099,53.359806],"type":"Point"}
}