{
  "type": "Feature",
  "properties": {
    "addr:full":"Dracht 114 Heerenveen Friesland 8442 BX",
    "addr:housenumber":"114",
    "addr:postcode":"8442 bx",
    "addr:street":"Dracht",
    "iso:country":"NL",
    "sg:address":"Dracht 114",
    "sg:city":"Heerenveen",
    "sg:orig_category":"Verlichting And Huishoudartikelen",
    "sg:phone":"+31 513 622 860",
    "sg:postcode":"8442 BX",
    "sg:province":"Friesland",
    "wof:name":"A G Kras",
    "wof:placetype":"venue"
},
  "geometry": {"coordinates":[5.925411,52.957745],"type":"Point"}
}