{
  "type": "Feature",
  "properties": {
    "addr:full":"De Wyzend 38 Oosthuizen Noord-Holland 1474 PB",
    "addr:housenumber":"38",
    "addr:postcode":"1474 pb",
    "iso:country":"NL",
    "sg:address":"De Wyzend 38",
    "sg:city":"Oosthuizen",
    "sg:orig_category":"Autorijscholen",
    "sg:phone":"+31 299 401 014",
    "sg:postcode":"1474 PB",
    "sg:province":"Noord-Holland",
    "wof:name":"Robin Wolfs",
    "wof:placetype":"venue"
},
  "geometry": {"coordinates":[4.99894,52.574059],"type":"Point"}
}