{
  "type": "Feature",
  "properties": {
    "addr:full":"Baandert 62 Sittard Limburg 6136 ES",
    "addr:housenumber":"62",
    "addr:postcode":"6136 es",
    "addr:street":"Baandert",
    "iso:country":"NL",
    "sg:address":"Baandert 62",
    "sg:city":"Sittard",
    "sg:orig_category":"Autorijscholen",
    "sg:phone":"+31 46 458 8440",
    "sg:postcode":"6136 ES",
    "sg:province":"Limburg",
    "wof:name":"Magielka",
    "wof:placetype":"venue"
},
  "geometry": {"coordinates":[5.872346,51.004265],"type":"Point"}
}