{
  "type": "Feature",
  "properties": {
    "addr:full":"Mophosostr 19 Culemborg Gelderland 4105 GC",
    "addr:housenumber":"19",
    "addr:postcode":"4105 gc",
    "addr:street":"Mophosostr;Gelderland",
    "iso:country":"NL",
    "sg:address":"Mophosostr 19",
    "sg:city":"Culemborg",
    "sg:orig_category":"Onderhoudswerken",
    "sg:phone":"+31 345 516 969",
    "sg:postcode":"4105 GC",
    "sg:province":"Gelderland",
    "wof:name":"Ceri Serv",
    "wof:placetype":"venue"
},
  "geometry": {"coordinates":[5.218326,51.951916],"type":"Point"}
}