{
  "type": "Feature",
  "properties": {
    "iso:country":"NL",
    "sg:address":"Cederlaan 4",
    "sg:city":"Assen",
    "sg:orig_category":"Artsen And Specialisten",
    "sg:phone":"+31 592 300 090",
    "sg:postcode":"9401 RC",
    "sg:province":"Drenthe",
    "wof:name":"J. Pols",
    "wof:placetype":"venue"
},
  "geometry": {"coordinates":[6.563363,52.980961],"type":"Point"}
}