{
  "type": "Feature",
  "properties": {
    "addr:full":"Akerstraat Noord 110 Hoensbroek Limburg 6431 HP",
    "addr:housenumber":"110",
    "addr:postcode":"6431 hp",
    "addr:street":"Akerstraat Noord",
    "iso:country":"NL",
    "sg:address":"Akerstraat Noord 110",
    "sg:city":"Hoensbroek",
    "sg:classifiers":[
        {
            "category":"Fast Food",
            "type":"Food & Drink"
        }
    ],
    "sg:phone":"+31 45 523 3222",
    "sg:postcode":"6431 HP",
    "sg:province":"Limburg",
    "sg:tags":[
        "afhaal",
        "restaurant"
    ],
    "wof:name":"Da Roberto",
    "wof:placetype":"venue"
},
  "geometry": {"coordinates":[5.934198,50.931175],"type":"Point"}
}