{
  "type": "Feature",
  "properties": {
    "addr:full":"St Pieterstr 32 Kerkrade Limburg 6463 CT",
    "addr:housenumber":"32",
    "addr:postcode":"6463 ct",
    "iso:country":"NL",
    "sg:address":"St Pieterstr 32",
    "sg:city":"Kerkrade",
    "sg:orig_category":"Handwerkartikelen",
    "sg:phone":"+31 45 545 3406",
    "sg:postcode":"6463 CT",
    "sg:province":"Limburg",
    "wof:name":"Derwall-Wetenkamp, M",
    "wof:placetype":"venue"
},
  "geometry": {"coordinates":[6.066767,50.874699],"type":"Point"}
}