{
  "type": "Feature",
  "properties": {
    "iso:country":"NL",
    "sg:address":"Brinkstraat 19",
    "sg:city":"Baarn",
    "sg:orig_category":"Meubelzaken, Woning- And Keukeninrichting",
    "sg:phone":"+31 35 541 2801",
    "sg:postcode":"3741 AM",
    "sg:province":"Utrecht",
    "wof:name":"Jansen Woninginrichting",
    "wof:placetype":"venue"
},
  "geometry": {"coordinates":[5.292369,52.212734],"type":"Point"}
}