{
  "type": "Feature",
  "properties": {
    "iso:country":"NL",
    "sg:address":"Rustenburgerstr 40",
    "sg:city":"Amsterdam",
    "sg:orig_category":"Fotografie Reclame En Mode",
    "sg:phone":"+31 20 675 7707",
    "sg:postcode":"1074 EV",
    "sg:province":"Noord-Holland",
    "wof:name":"Bakker, A",
    "wof:placetype":"venue"
},
  "geometry": {"coordinates":[4.904657,52.353745],"type":"Point"}
}