{
  "type": "Feature",
  "properties": {
    "addr:full":"Sassenplein 19 Helmond North Brabant 5701 AX",
    "addr:housenumber":"19",
    "addr:postcode":"5701 ax",
    "addr:street":"Sassenplein",
    "iso:country":"NL",
    "sg:address":"Sassenplein 19",
    "sg:city":"Helmond",
    "sg:orig_category":"Zuivelproducten",
    "sg:phone":"+31 492 533 796",
    "sg:postcode":"5701 AX",
    "sg:province":"North Brabant",
    "wof:name":"Handelsonderneming Vd Reek",
    "wof:placetype":"venue"
},
  "geometry": {"coordinates":[5.662255,51.484489],"type":"Point"}
}