{
  "type": "Feature",
  "properties": {
    "addr:full":"De Ziel 5 Bunschoten Spakenburg Utrecht 3751 BT",
    "addr:housenumber":"5",
    "addr:postcode":"3751 bt",
    "addr:street":"De Ziel",
    "iso:country":"NL",
    "sg:address":"De Ziel 5",
    "sg:city":"Bunschoten Spakenburg",
    "sg:orig_category":"Boekhouders",
    "sg:phone":"+31 33 298 4213",
    "sg:postcode":"3751 BT",
    "sg:province":"Utrecht",
    "wof:name":"K. Huygen Adm En Belastingzaken",
    "wof:placetype":"venue"
},
  "geometry": {"coordinates":[5.378824,52.252537],"type":"Point"}
}