{
  "type": "Feature",
  "properties": {
    "addr:full":"Van Brederodestraat 6 Noordeloos Zuid-Holland 4225 RD",
    "addr:housenumber":"6",
    "addr:postcode":"4225 rd",
    "addr:street":"Van Brederodestraat",
    "iso:country":"NL",
    "sg:address":"Van Brederodestraat 6",
    "sg:city":"Noordeloos",
    "sg:orig_category":"Verzekeringen",
    "sg:phone":"+31 183 582 011",
    "sg:postcode":"4225 RD",
    "sg:province":"Zuid-Holland",
    "wof:name":"De Leeuw Assurantien",
    "wof:placetype":"venue"
},
  "geometry": {"coordinates":[4.939825,51.906017],"type":"Point"}
}