{
  "type": "Feature",
  "properties": {
    "addr:full":"Laan Van Nieuw Oosteinde 9 Voorburg Zuid-Holland 2271 AB",
    "addr:housenumber":"9",
    "addr:postcode":"2271 ab",
    "addr:street":"Laan Van Nieuw Oosteinde",
    "iso:country":"NL",
    "sg:address":"Laan Van Nieuw Oosteinde 9",
    "sg:city":"Voorburg",
    "sg:orig_category":"Schoonheidssalons",
    "sg:phone":"+31 70 386 8848",
    "sg:postcode":"2271 AB",
    "sg:province":"Zuid-Holland",
    "wof:name":"Annemieke'S Instituut Natural Beauty",
    "wof:placetype":"venue"
},
  "geometry": {"coordinates":[4.357159,52.06863],"type":"Point"}
}