{
  "type": "Feature",
  "properties": {
    "addr:full":"Ingenieur Albardastraat 9 Ridderkerk Zuid-Holland 2982 VK",
    "addr:housenumber":"9",
    "addr:postcode":"2982 vk",
    "addr:street":"Ingenieur Albardastraat",
    "iso:country":"NL",
    "sg:address":"Ingenieur Albardastraat 9",
    "sg:city":"Ridderkerk",
    "sg:orig_category":"Binnenhuisarchitecten",
    "sg:phone":"+31 180 417 714",
    "sg:postcode":"2982 VK",
    "sg:province":"Zuid-Holland",
    "wof:name":"D Plaisier",
    "wof:placetype":"venue"
},
  "geometry": {"coordinates":[4.590961,51.87196],"type":"Point"}
}