{
  "type": "Feature",
  "properties": {
    "iso:country":"NL",
    "sg:address":"Weteringkade 31",
    "sg:city":"'S Gravenhage",
    "sg:orig_category":"Fotostudio'S And Fotografen",
    "sg:phone":"+31 70 335 1909",
    "sg:postcode":"2515 AL",
    "sg:province":"Zuid-Holland",
    "wof:name":"H. Potharst",
    "wof:placetype":"venue"
},
  "geometry": {"coordinates":[4.325825,52.073353],"type":"Point"}
}