{
  "type": "Feature",
  "properties": {
    "addr:full":"Lissabonweg 2 Vlaardingen South Holland 3137 LR",
    "addr:housenumber":"2",
    "addr:postcode":"3137 lr",
    "addr:street":"Lissabonweg",
    "iso:country":"NL",
    "sg:address":"Lissabonweg 2",
    "sg:city":"Vlaardingen",
    "sg:classifiers":[
        {
            "category":"Education",
            "subcategory":"Preschool",
            "type":"Public Place"
        }
    ],
    "sg:phone":"+31 10 474 1474",
    "sg:postcode":"3137 LR",
    "sg:province":"South Holland",
    "sg:tags":[
        "kleuteronderwijs",
        "basis-"
    ],
    "wof:name":"Openbare Basisschool De Dolfijn",
    "wof:placetype":"venue"
},
  "geometry": {"coordinates":[4.350608,51.934086],"type":"Point"}
}