{
  "type": "Feature",
  "properties": {
    "addr:full":"Gelderlandstraat 74 Enschede Overijssel 7543 WP",
    "addr:housenumber":"74",
    "addr:postcode":"7543 wp",
    "addr:street":"Gelderlandstraat",
    "iso:country":"NL",
    "sg:address":"Gelderlandstraat 74",
    "sg:city":"Enschede",
    "sg:orig_category":"Koeriersdiensten",
    "sg:phone":"+31 53 477 0566",
    "sg:postcode":"7543 WP",
    "sg:province":"Overijssel",
    "wof:name":"Es Koerier Europa Sprint",
    "wof:placetype":"venue"
},
  "geometry": {"coordinates":[6.881567,52.205555],"type":"Point"}
}