{
  "type": "Feature",
  "properties": {
    "iso:country":"NL",
    "sg:address":"Maastrichterwg 249",
    "sg:city":"Valkenswaard",
    "sg:orig_category":"Paardenhandelaren",
    "sg:phone":"+31 40 206 8405",
    "sg:postcode":"5556 VB",
    "sg:province":"Noord-Brabant",
    "wof:name":"Tops, J A P",
    "wof:placetype":"venue"
},
  "geometry": {"coordinates":[5.468211,51.306683],"type":"Point"}
}