{
  "type": "Feature",
  "properties": {
    "addr:full":"De Hoven 27 Aalten Gelderland 7122 BJ",
    "addr:housenumber":"27",
    "addr:postcode":"7122 bj",
    "addr:street":"De Hoven;Gelderland",
    "iso:country":"NL",
    "sg:address":"De Hoven 27",
    "sg:city":"Aalten",
    "sg:orig_category":"Babyartikelen",
    "sg:phone":"+31 543 476 632",
    "sg:postcode":"7122 BJ",
    "sg:province":"Gelderland",
    "wof:name":"Kraamparadijs, 'T",
    "wof:placetype":"venue"
},
  "geometry": {"coordinates":[6.577911,51.927032],"type":"Point"}
}