{
  "type": "Feature",
  "properties": {
    "addr:full":"Mierlosewg 86 Helmond North Brabant 5707 AP",
    "addr:housenumber":"86",
    "addr:postcode":"5707 ap",
    "addr:street":"Mierlosewg",
    "iso:country":"NL",
    "sg:address":"Mierlosewg 86",
    "sg:city":"Helmond",
    "sg:orig_category":"Verf En Lak - Fabrieken En Groothandel",
    "sg:phone":"+31 492 535 066",
    "sg:postcode":"5707 AP",
    "sg:province":"North Brabant",
    "sg:website":"http://www.jandriessen.nl",
    "wof:name":"Driessen",
    "wof:placetype":"venue"
},
  "geometry": {"coordinates":[5.639909,51.4758],"type":"Point"}
}