{
  "type": "Feature",
  "properties": {
    "addr:full":"Akkerstraat 42 Gilze Noord-Brabant 5126 PJ",
    "addr:housenumber":"42",
    "addr:postcode":"5126 pj",
    "addr:street":"Akkerstraat",
    "iso:country":"NL",
    "sg:address":"Akkerstraat 42",
    "sg:city":"Gilze",
    "sg:orig_category":"Meubelreparatie And -Restauratie",
    "sg:phone":"+31 161 453 820",
    "sg:postcode":"5126 PJ",
    "sg:province":"Noord-Brabant",
    "wof:name":"Meubelmakerij Harold Van Den Bosch Vof",
    "wof:placetype":"venue"
},
  "geometry": {"coordinates":[4.9533882141,51.5436820984],"type":"Point"}
}