{
  "type": "Feature",
  "properties": {
    "iso:country":"NL",
    "sg:address":"S Gravenwg 631",
    "sg:city":"Rotterdam",
    "sg:orig_category":"Artsen - Overigen",
    "sg:phone":"+31 10 202 0815",
    "sg:postcode":"3065 SC",
    "sg:province":"Zuid-Holland",
    "wof:name":"B\u00e4nffer Bv, Dr J R J",
    "wof:placetype":"venue"
},
  "geometry": {"coordinates":[4.55201,51.921535],"type":"Point"}
}