{
  "type": "Feature",
  "properties": {
    "addr:full":"Remisewg 1 Nieuwegein Utrecht 3438 LA",
    "addr:housenumber":"1",
    "addr:postcode":"3438 la",
    "addr:street":"Remisewg",
    "iso:country":"NL",
    "sg:address":"Remisewg 1",
    "sg:city":"Nieuwegein",
    "sg:orig_category":"Openbaar Vervoer",
    "sg:phone":"+31 30 281 4600",
    "sg:postcode":"3438 LA",
    "sg:province":"Utrecht",
    "wof:name":"Connexxion",
    "wof:placetype":"venue"
},
  "geometry": {"coordinates":[5.1002402306,52.0525016785],"type":"Point"}
}