{
  "type": "Feature",
  "properties": {
    "addr:full":"Spectrumsngl 59 Zoetermeer Zuid-Holland 2718 CZ",
    "addr:housenumber":"59;2718",
    "addr:street":"Spectrumsngl",
    "iso:country":"NL",
    "sg:address":"Spectrumsngl 59",
    "sg:city":"Zoetermeer",
    "sg:orig_category":"Onderzoekbureaus",
    "sg:phone":"+31 79 362 3859",
    "sg:postcode":"2718 CZ",
    "sg:province":"Zuid-Holland",
    "wof:name":"Hmc Onderwijs",
    "wof:placetype":"venue"
},
  "geometry": {"coordinates":[4.486435,52.038136],"type":"Point"}
}