{
  "type": "Feature",
  "properties": {
    "addr:full":"Binnenban 87 Hoogvliet Rt Zuid-Holland 3191 CB",
    "addr:housenumber":"87",
    "addr:postcode":"rt;3191 cb",
    "addr:street":"Binnenban",
    "iso:country":"NL",
    "sg:address":"Binnenban 87",
    "sg:city":"Hoogvliet Rt",
    "sg:classifiers":[
        {
            "category":"Retail",
            "subcategory":"Photofinishing",
            "type":"Services"
        }
    ],
    "sg:phone":"+31 10 416 5910",
    "sg:postcode":"3191 CB",
    "sg:province":"Zuid-Holland",
    "sg:tags":[
        "foto",
        "film"
    ],
    "wof:name":"Super Photo Snelservice",
    "wof:placetype":"venue"
},
  "geometry": {"coordinates":[4.35518,51.865231],"type":"Point"}
}