{
  "type": "Feature",
  "properties": {
    "addr:full":"Zinkstr 33 Breda Noord-Brabant 4823 AD",
    "addr:housenumber":"33",
    "addr:postcode":"4823 ad",
    "addr:street":"Zinkstr",
    "iso:country":"NL",
    "sg:address":"Zinkstr 33",
    "sg:city":"Breda",
    "sg:orig_category":"Pijpleidingen",
    "sg:phone":"+31 76 541 8400",
    "sg:postcode":"4823 AD",
    "sg:province":"Noord-Brabant",
    "sg:website":"http://www.bsmbreda.nl",
    "wof:name":"Bsm Braacx Special Machining",
    "wof:placetype":"venue"
},
  "geometry": {"coordinates":[4.71821,51.612572],"type":"Point"}
}