{
  "type": "Feature",
  "properties": {
    "addr:full":"Westerhuizingerweg 53 Balkbrug Overijssel 7707 RG",
    "addr:housenumber":"53",
    "addr:postcode":"7707 rg",
    "addr:street":"Westerhuizingerweg",
    "iso:country":"NL",
    "sg:address":"Westerhuizingerweg 53",
    "sg:city":"Balkbrug",
    "sg:orig_category":"Huizensloop And Bouwrijp Maken",
    "sg:phone":"+31 523 649 378",
    "sg:postcode":"7707 RG",
    "sg:province":"Overijssel",
    "wof:name":"K. Tuin",
    "wof:placetype":"venue"
},
  "geometry": {"coordinates":[6.344264,52.613907],"type":"Point"}
}