{
  "type": "Feature",
  "properties": {
    "addr:full":"Burchtstr 4 Uithuizermeeden Groningen 9982 AP",
    "addr:housenumber":"4",
    "addr:postcode":"9982 ap",
    "addr:street":"Burchtstr",
    "iso:country":"NL",
    "sg:address":"Burchtstr 4",
    "sg:city":"Uithuizermeeden",
    "sg:orig_category":"Verenigingsgebouwen",
    "sg:phone":"+31 595 412 277",
    "sg:postcode":"9982 AP",
    "sg:province":"Groningen",
    "wof:name":"Rehoboth, Sticht",
    "wof:placetype":"venue"
},
  "geometry": {"coordinates":[6.721903,53.413055],"type":"Point"}
}