{
  "type": "Feature",
  "properties": {
    "addr:full":"Flevostraat 263 Purmerend Noord-Holland 1442 PX",
    "addr:housenumber":"263",
    "addr:postcode":"1442 px",
    "addr:street":"Flevostraat",
    "iso:country":"NL",
    "sg:address":"Flevostraat 263",
    "sg:city":"Purmerend",
    "sg:orig_category":"Bouwnijverheidsmachines Gh",
    "sg:phone":"+31 299 429 066",
    "sg:postcode":"1442 PX",
    "sg:province":"Noord-Holland",
    "wof:name":"Bakker Heftrucks Bv",
    "wof:placetype":"venue"
},
  "geometry": {"coordinates":[4.985202,52.518948],"type":"Point"}
}