{
  "type": "Feature",
  "properties": {
    "iso:country":"NL",
    "sg:address":"Flevostraat 263",
    "sg:city":"Purmerend",
    "sg:orig_category":"Bouwnijverheidsmachines Gh",
    "sg:phone":"+31 299 429 066",
    "sg:postcode":"1442 PX",
    "sg:province":"Noord-Holland",
    "wof:name":"Bakker Heftrucks Bv",
    "wof:placetype":"venue"
},
  "geometry": {"coordinates":[4.985202,52.518948],"type":"Point"}
}