{
  "type": "Feature",
  "properties": {
    "addr:full":"Gasln 69 Baarn Utrecht 3741 WK",
    "addr:housenumber":"69",
    "addr:postcode":"3741 wk",
    "addr:street":"Gasln",
    "iso:country":"NL",
    "sg:address":"Gasln 69",
    "sg:city":"Baarn",
    "sg:orig_category":"Plafonds",
    "sg:phone":"+31 35 542 1977",
    "sg:postcode":"3741 WK",
    "sg:province":"Utrecht",
    "wof:name":"Veer Bv, Gebr Van Der",
    "wof:placetype":"venue"
},
  "geometry": {"coordinates":[5.312465,52.224945],"type":"Point"}
}