{
  "type": "Feature",
  "properties": {
    "addr:full":"Molenvaart 353B Anna Paulowna North Holland 1761 AH",
    "addr:housenumber":"353b",
    "addr:postcode":"1761 ah",
    "addr:street":"Molenvaart",
    "iso:country":"NL",
    "sg:address":"Molenvaart 353B",
    "sg:city":"Anna Paulowna",
    "sg:orig_category":"Koeriersdiensten",
    "sg:phone":"+31 223 522 825",
    "sg:postcode":"1761 AH",
    "sg:province":"North Holland",
    "sg:website":"http://www.hilverinkkoeriers.nl",
    "wof:name":"Hilverink Koeriers",
    "wof:placetype":"venue"
},
  "geometry": {"coordinates":[4.803599,52.872311],"type":"Point"}
}