{
  "type": "Feature",
  "properties": {
    "iso:country":"NL",
    "sg:address":"V Rietln 19",
    "sg:city":"Linschoten",
    "sg:orig_category":"Verpakkingsmachines",
    "sg:phone":"+31 348 445 040",
    "sg:postcode":"3461 HW",
    "sg:province":"Utrecht",
    "wof:name":"Ett",
    "wof:placetype":"venue"
},
  "geometry": {"coordinates":[4.915227,52.061867],"type":"Point"}
}