{
  "type": "Feature",
  "properties": {
    "addr:full":"Pastoor Gautiusstraat 26 Gemert North Brabant 5421 SV",
    "addr:housenumber":"26",
    "addr:postcode":"5421 sv",
    "addr:street":"Pastoor Gautiusstraat",
    "iso:country":"NL",
    "sg:address":"Pastoor Gautiusstraat 26",
    "sg:city":"Gemert",
    "sg:orig_category":"Huisdierenfokkers",
    "sg:phone":"+31 492 368 351",
    "sg:postcode":"5421 SV",
    "sg:province":"North Brabant",
    "wof:name":"De Franse Bulldog Kennel",
    "wof:placetype":"venue"
},
  "geometry": {"coordinates":[5.691971,51.562851],"type":"Point"}
}