{
  "type": "Feature",
  "properties": {
    "iso:country":"NL",
    "sg:address":"Postbus 2205",
    "sg:city":"Zaltbommel",
    "sg:orig_category":"Medische Installaties En Instrumenten",
    "sg:phone":"+31 418 576 600",
    "sg:postcode":"5300 CE",
    "sg:province":"Gelderland",
    "sg:website":"http://www.tycohealthcare.nl",
    "wof:name":"Tyco Healthcare Nederland Bv",
    "wof:placetype":"venue"
},
  "geometry": {"coordinates":[5.24478,51.812744],"type":"Point"}
}