{
  "type": "Feature",
  "properties": {
    "addr:full":"Hengelosestraat 240 Deurningen Overijssel 7562 PK",
    "addr:housenumber":"240",
    "addr:postcode":"7562 pk",
    "addr:street":"Hengelosestraat",
    "iso:country":"NL",
    "sg:address":"Hengelosestraat 240",
    "sg:city":"Deurningen",
    "sg:orig_category":"Biljart- And Snookerzalen",
    "sg:phone":"+31 541 513 023",
    "sg:postcode":"7562 PK",
    "sg:province":"Overijssel",
    "wof:name":"Firma Golbach",
    "wof:placetype":"venue"
},
  "geometry": {"coordinates":[6.865191,52.289478],"type":"Point"}
}