{
  "type": "Feature",
  "properties": {
    "addr:full":"Burg Velthuysenln 142 Leidschendam Zuid-Holland 2262 VT",
    "addr:housenumber":"142",
    "addr:postcode":"2262",
    "addr:street":"Burg",
    "iso:country":"NL",
    "sg:address":"Burg Velthuysenln 142",
    "sg:city":"Leidschendam",
    "sg:orig_category":"Gordijnen",
    "sg:phone":"+31 70 317 6075",
    "sg:postcode":"2262 VT",
    "sg:province":"Zuid-Holland",
    "wof:name":"Vleugels, R",
    "wof:placetype":"venue"
},
  "geometry": {"coordinates":[4.390763,52.09277],"type":"Point"}
}