{
  "type": "Feature",
  "properties": {
    "addr:full":"K Dreef 13 Driebergen Rysenb Utrecht 3972 EB",
    "addr:housenumber":"13",
    "addr:postcode":"3972 eb",
    "addr:street":"K Dreef;Rysenb",
    "iso:country":"NL",
    "sg:address":"K Dreef 13",
    "sg:city":"Driebergen Rysenb",
    "sg:orig_category":"Accountants - Administratie- Consulenten En -Kantoren",
    "sg:phone":"+31 343 520 234",
    "sg:postcode":"3972 EB",
    "sg:province":"Utrecht",
    "wof:name":"Elferink & Co",
    "wof:placetype":"venue"
},
  "geometry": {"coordinates":[5.283655,52.051552],"type":"Point"}
}