{
  "type": "Feature",
  "properties": {
    "addr:full":"Theresiastr 147 S Gravenhage Zuid-Holland 2593 AG",
    "addr:housenumber":"147;gravenhage",
    "addr:postcode":"2593",
    "addr:street":"S",
    "iso:country":"NL",
    "sg:address":"Theresiastr 147",
    "sg:city":"S Gravenhage",
    "sg:orig_category":"Schoenen",
    "sg:phone":"+31 70 382 1935",
    "sg:postcode":"2593 AG",
    "sg:province":"Zuid-Holland",
    "sg:website":"http://www.joopdehaanschoenen.nl",
    "wof:name":"Joop De Haan",
    "wof:placetype":"venue"
},
  "geometry": {"coordinates":[4.34266,52.086121],"type":"Point"}
}