{
  "type": "Feature",
  "properties": {
    "addr:full":"Turfmarkt 12 Leeuwarden Provincie Friesland 8911 KT",
    "addr:housenumber":"12",
    "addr:postcode":"8911 kt",
    "addr:street":"Turfmarkt;Provincie Friesland",
    "iso:country":"NL",
    "sg:address":"Turfmarkt 12",
    "sg:city":"Leeuwarden",
    "sg:orig_category":"Verenigingen En Stichtingen",
    "sg:phone":"+31 58 212 3733",
    "sg:postcode":"8911 KT",
    "sg:province":"Provincie Friesland",
    "wof:name":"Friesland 1940-1945",
    "wof:placetype":"venue"
},
  "geometry": {"coordinates":[5.801183,53.203072],"type":"Point"}
}