{
  "type": "Feature",
  "properties": {
    "addr:full":"Middendorpweg 8A Rijswijk Zh Zuid-Holland 2286 KH",
    "addr:housenumber":"8a",
    "addr:postcode":"zh;2286 kh",
    "addr:street":"Middendorpweg",
    "iso:country":"NL",
    "sg:address":"Middendorpweg 8A",
    "sg:city":"Rijswijk Zh",
    "sg:orig_category":"Bloemen And Planten",
    "sg:phone":"+31 15 214 2452",
    "sg:postcode":"2286 KH",
    "sg:province":"Zuid-Holland",
    "wof:name":"M Dijkxhoorn Vof",
    "wof:placetype":"venue"
},
  "geometry": {"coordinates":[4.32535,52.016685],"type":"Point"}
}