{
  "type": "Feature",
  "properties": {
    "addr:full":"Nybracht 64 Emmen Provincie Drenthe 7821 CA",
    "addr:housenumber":"64",
    "addr:postcode":"7821 ca",
    "addr:street":"Nybracht;Provincie Drenthe",
    "iso:country":"NL",
    "sg:address":"Nybracht 64",
    "sg:city":"Emmen",
    "sg:orig_category":"Woninginrichting",
    "sg:phone":"+31 591 647 309",
    "sg:postcode":"7821 CA",
    "sg:province":"Provincie Drenthe",
    "wof:name":"Leen Bakker",
    "wof:placetype":"venue"
},
  "geometry": {"coordinates":[6.9049191475,52.7624816895],"type":"Point"}
}