{
  "type": "Feature",
  "properties": {
    "addr:full":"Zylwg 18 Haarlem North Holland 2013 DH",
    "addr:housenumber":"18",
    "addr:postcode":"2013 dh",
    "addr:street":"Zylwg",
    "iso:country":"NL",
    "sg:address":"Zylwg 18",
    "sg:city":"Haarlem",
    "sg:orig_category":"Kappers",
    "sg:phone":"+31 23 526 7400",
    "sg:postcode":"2013 DH",
    "sg:province":"North Holland",
    "sg:website":"http://htttp://www.haarcreaties.nl",
    "wof:name":"Haar Creaties",
    "wof:placetype":"venue"
},
  "geometry": {"coordinates":[4.6422529221,52.3805618286],"type":"Point"}
}