{
  "type": "Feature",
  "properties": {
    "addr:full":"Walderstraat 27 Lochem Gelderland 7241 BH",
    "addr:housenumber":"27",
    "addr:postcode":"7241 bh",
    "addr:street":"Walderstraat;Gelderland",
    "iso:country":"NL",
    "sg:address":"Walderstraat 27",
    "sg:city":"Lochem",
    "sg:orig_category":"Visspeciaalzaken",
    "sg:phone":"+31 573 251 717",
    "sg:postcode":"7241 BH",
    "sg:province":"Gelderland",
    "wof:name":"Vishandel Waninge",
    "wof:placetype":"venue"
},
  "geometry": {"coordinates":[6.412969,52.162102],"type":"Point"}
}