{
  "type": "Feature",
  "properties": {
    "addr:full":"Curiewg 15 Zwolle NL.08 8013 RA",
    "addr:housenumber":"15",
    "addr:postcode":"8013 ra",
    "addr:street":"Curiewg",
    "iso:country":"NL",
    "sg:address":"Curiewg 15",
    "sg:city":"Zwolle",
    "sg:orig_category":"Verhuizingen",
    "sg:phone":"+31 38 465 6560",
    "sg:postcode":"8013 RA",
    "sg:province":"NL.08",
    "sg:website":"http://www.hersevoort.nl",
    "wof:name":"Hersevoort Bv",
    "wof:placetype":"venue"
},
  "geometry": {"coordinates":[6.129627,52.499146],"type":"Point"}
}