{
  "type": "Feature",
  "properties": {
    "addr:full":"Kloetenseweg 3 Winterswijk Gelderland 7101 TV",
    "addr:housenumber":"3",
    "addr:postcode":"7101 tv",
    "addr:street":"Kloetenseweg;Gelderland",
    "iso:country":"NL",
    "sg:address":"Kloetenseweg 3",
    "sg:city":"Winterswijk",
    "sg:orig_category":"Huishoudapparatuur, Televisies And Radio'S",
    "sg:phone":"+31 543 532 688",
    "sg:postcode":"7101 TV",
    "sg:province":"Gelderland",
    "wof:name":"Veldkamp Installatie Bv",
    "wof:placetype":"venue"
},
  "geometry": {"coordinates":[6.729612,51.972649],"type":"Point"}
}