{
  "type": "Feature",
  "properties": {
    "addr:full":"Peppelwg 138A Rotterdam Zuid-Holland 3053 GV",
    "addr:housenumber":"138a",
    "addr:postcode":"3053 gv",
    "iso:country":"NL",
    "sg:address":"Peppelwg 138A",
    "sg:city":"Rotterdam",
    "sg:orig_category":"Kaas",
    "sg:phone":"+31 10 422 1049",
    "sg:postcode":"3053 GV",
    "sg:province":"Zuid-Holland",
    "wof:name":"Berkhout Bv",
    "wof:placetype":"venue"
},
  "geometry": {"coordinates":[4.4703722,51.9600486755],"type":"Point"}
}