{
  "type": "Feature",
  "properties": {
    "addr:full":"J Messchaertstr 3B Hoorn Nh North Holland 1623 LJ",
    "addr:housenumber":"3b",
    "addr:postcode":"1623 lj",
    "addr:street":"Nh North",
    "iso:country":"NL",
    "sg:address":"J Messchaertstr 3B",
    "sg:city":"Hoorn Nh",
    "sg:orig_category":"Kinderopvang",
    "sg:phone":"+31 229 210 800",
    "sg:postcode":"1623 LJ",
    "sg:province":"North Holland",
    "wof:name":"Tamboerijn, De",
    "wof:placetype":"venue"
},
  "geometry": {"coordinates":[5.07177,52.645481],"type":"Point"}
}