{
  "type": "Feature",
  "properties": {
    "iso:country":"NL",
    "sg:address":"Koning Lodewijklaan 40 B",
    "sg:city":"Apeldoorn",
    "sg:orig_category":"Fotostudio'S And Fotografen",
    "sg:phone":"+31 55 355 9633",
    "sg:postcode":"7314 GG",
    "sg:province":"Gelderland",
    "wof:name":"Reclamefotografie Gerhard Witteveen",
    "wof:placetype":"venue"
},
  "geometry": {"coordinates":[5.945804,52.221886],"type":"Point"}
}