{
  "type": "Feature",
  "properties": {
    "addr:full":"Van Arembergelaan 62 Voorburg South Holland 2274 BV",
    "addr:housenumber":"62",
    "addr:postcode":"2274 bv",
    "addr:street":"Van Arembergelaan",
    "iso:country":"NL",
    "sg:address":"Van Arembergelaan 62",
    "sg:city":"Voorburg",
    "sg:orig_category":"Boekhandels",
    "sg:phone":"+31 70 383 6294",
    "sg:postcode":"2274 BV",
    "sg:province":"South Holland",
    "wof:name":"Kant Boekhand Lectura Bv",
    "wof:placetype":"venue"
},
  "geometry": {"coordinates":[4.347821,52.074287],"type":"Point"}
}