{
  "type": "Feature",
  "properties": {
    "iso:country":"NL",
    "sg:address":"Smirnoffweg 3",
    "sg:city":"Rotterdam",
    "sg:classifiers":[
        {
            "category":"Retail",
            "subcategory":"Storage",
            "type":"Services"
        }
    ],
    "sg:phone":"+31 10 495 2800",
    "sg:postcode":"3088 HE",
    "sg:province":"South Holland",
    "sg:tags":[
        "opslag",
        "bewaring"
    ],
    "wof:name":"Bulkchart Services Bv",
    "wof:placetype":"venue"
},
  "geometry": {"coordinates":[4.436355114,51.8780860901],"type":"Point"}
}