{
  "type": "Feature",
  "properties": {
    "iso:country":"NL",
    "sg:address":"Stompwijkseweg 23",
    "sg:city":"Leidschendam",
    "sg:orig_category":"Goederenvervoer Over De Weg",
    "sg:phone":"+31 70 320 1692",
    "sg:postcode":"2266 GC",
    "sg:province":"Zuid-Holland",
    "wof:name":"Koos Overdevest Transport",
    "wof:placetype":"venue"
},
  "geometry": {"coordinates":[4.419615,52.081367],"type":"Point"}
}