{
  "type": "Feature",
  "properties": {
    "addr:full":"Vijf Meiplein 34 Leiden Zuid-Holland 2321 BP",
    "addr:housenumber":"34",
    "addr:postcode":"2321 bp",
    "addr:street":"Vijf Meiplein",
    "iso:country":"NL",
    "sg:address":"Vijf Meiplein 34",
    "sg:city":"Leiden",
    "sg:orig_category":"Herenmodezaken",
    "sg:phone":"+31 71 576 5604",
    "sg:postcode":"2321 BP",
    "sg:province":"Zuid-Holland",
    "wof:name":"Mentink Mode Leiden Bv",
    "wof:placetype":"venue"
},
  "geometry": {"coordinates":[4.480373,52.147629],"type":"Point"}
}