{
  "type": "Feature",
  "properties": {
    "addr:full":"Rozenstr 21 Zeist Utrecht 3702 VM",
    "addr:housenumber":"21",
    "addr:postcode":"3702 vm",
    "addr:street":"Rozenstr",
    "iso:country":"NL",
    "sg:address":"Rozenstr 21",
    "sg:city":"Zeist",
    "sg:orig_category":"Scholen Voor Basisonderwijs",
    "sg:phone":"+31 30 691 8394",
    "sg:postcode":"3702 VM",
    "sg:province":"Utrecht",
    "wof:name":"Damiaanschool Rk",
    "wof:placetype":"venue"
},
  "geometry": {"coordinates":[5.238065,52.089069],"type":"Point"}
}