{
  "type": "Feature",
  "properties": {
    "iso:country":"NL",
    "sg:address":"Zwaagdijk 214",
    "sg:city":"Zwaagdijk",
    "sg:orig_category":"Hoefdierhouderijen",
    "sg:phone":"+31 228 582 836",
    "sg:postcode":"1682 NP",
    "sg:province":"Noord-Holland",
    "wof:name":"Stal Fan 'T Nije Lok",
    "wof:placetype":"venue"
},
  "geometry": {"coordinates":[5.120366,52.69989],"type":"Point"}
}