{
  "type": "Feature",
  "properties": {
    "addr:full":"Vinkenwg 16 Berg En Terblyt Limburg 6325 BB",
    "addr:housenumber":"16",
    "addr:postcode":"6325 bb",
    "addr:street":"Vinkenwg;Limburg",
    "iso:country":"NL",
    "sg:address":"Vinkenwg 16",
    "sg:city":"Berg En Terblyt",
    "sg:orig_category":"Schoonheidsinstituten",
    "sg:phone":"+31 43 604 0317",
    "sg:postcode":"6325 BB",
    "sg:province":"Limburg",
    "wof:name":"Rosanne",
    "wof:placetype":"venue"
},
  "geometry": {"coordinates":[5.807257,50.858658],"type":"Point"}
}