{
  "type": "Feature",
  "properties": {
    "addr:full":"Clementinalaan 25 Veldhoven Noord-Brabant 5507 NE",
    "addr:housenumber":"25",
    "addr:postcode":"5507 ne",
    "addr:street":"Clementinalaan",
    "iso:country":"NL",
    "sg:address":"Clementinalaan 25",
    "sg:city":"Veldhoven",
    "sg:orig_category":"Drukkerijen And Copyshops",
    "sg:phone":"+31 40 205 1731",
    "sg:postcode":"5507 NE",
    "sg:province":"Noord-Brabant",
    "wof:name":"Forto Print",
    "wof:placetype":"venue"
},
  "geometry": {"coordinates":[5.374488,51.419754],"type":"Point"}
}