{
  "type": "Feature",
  "properties": {
    "addr:full":"Drostenstr 3 Coevorden Drenthe 7742 BB",
    "addr:housenumber":"3",
    "addr:postcode":"7742 bb",
    "addr:street":"Drostenstr",
    "iso:country":"NL",
    "sg:address":"Drostenstr 3",
    "sg:city":"Coevorden",
    "sg:orig_category":"Scholen Voor Basisonderwijs",
    "sg:phone":"+31 524 513 902",
    "sg:postcode":"7742 BB",
    "sg:province":"Drenthe",
    "wof:name":"Azc School",
    "wof:placetype":"venue"
},
  "geometry": {"coordinates":[6.750229,52.662209],"type":"Point"}
}