{
  "type": "Feature",
  "properties": {
    "addr:full":"De Roodstaart 21 Vriezenveen NL.08 7671 VN",
    "addr:housenumber":"21;nl.08",
    "addr:postcode":"7671 vn",
    "addr:street":"De Roodstaart",
    "iso:country":"NL",
    "sg:address":"De Roodstaart 21",
    "sg:city":"Vriezenveen",
    "sg:orig_category":"Metaalwerken",
    "sg:phone":"+31 546 566 042",
    "sg:postcode":"7671 VN",
    "sg:province":"NL.08",
    "wof:name":"Gerrit Smit Systeem Plafonds",
    "wof:placetype":"venue"
},
  "geometry": {"coordinates":[6.612483,52.40123],"type":"Point"}
}