{
  "type": "Feature",
  "properties": {
    "addr:full":"Hornwg 196 Aalsmeer North Holland 1432 GS",
    "addr:housenumber":"196",
    "addr:postcode":"1432 gs",
    "iso:country":"NL",
    "sg:address":"Hornwg 196",
    "sg:city":"Aalsmeer",
    "sg:orig_category":"Plastificeren",
    "sg:phone":"+31 297 342 855",
    "sg:postcode":"1432 GS",
    "sg:province":"North Holland",
    "wof:name":"Kooy Laminations Bv",
    "wof:placetype":"venue"
},
  "geometry": {"coordinates":[4.797236,52.271523],"type":"Point"}
}