{
  "type": "Feature",
  "properties": {
    "iso:country":"NL",
    "sg:address":"Nachtegaal 1",
    "sg:city":"Ijsselmuiden",
    "sg:orig_category":"Juridische Dienstverlening",
    "sg:phone":"+31 38 331 2500",
    "sg:postcode":"8271 HS",
    "sg:province":"NL.08",
    "wof:name":"Juridisch Advies- En Incassobureau Holtl",
    "wof:placetype":"venue"
},
  "geometry": {"coordinates":[5.941795,52.563381],"type":"Point"}
}