{
  "type": "Feature",
  "properties": {
    "addr:full":"Postbus 162 Deurne Noord-Brabant 5750 AD",
    "addr:housenumber":"162",
    "addr:postcode":"5750 ad",
    "addr:street":"Postbus",
    "iso:country":"NL",
    "sg:address":"Postbus 162",
    "sg:city":"Deurne",
    "sg:orig_category":"Metaaldraaierijen",
    "sg:phone":"+31 493 354 227",
    "sg:postcode":"5750 AD",
    "sg:province":"Noord-Brabant",
    "wof:name":"Aarts",
    "wof:placetype":"venue"
},
  "geometry": {"coordinates":[5.790711,51.461773],"type":"Point"}
}