{
  "type": "Feature",
  "properties": {
    "iso:country":"NL",
    "sg:address":"Laan Van Eik En Duinen 181",
    "sg:city":"'S Gravenhage",
    "sg:orig_category":"Kinderopvang Behalve Thuis",
    "sg:phone":"+31 70 360 0664",
    "sg:postcode":"2564 GP",
    "sg:province":"Zuid-Holland",
    "wof:name":"Stichting Welzijnsorganisatie Segbroek Loosduinen",
    "wof:placetype":"venue"
},
  "geometry": {"coordinates":[4.263341,52.071697],"type":"Point"}
}