{
  "type": "Feature",
  "properties": {
    "addr:full":"Laan Van Eik En Duinen 181 'S Gravenhage Zuid-Holland 2564 GP",
    "addr:housenumber":"181 '",
    "addr:postcode":"2564 gp",
    "addr:street":"Laan Van Eik En Duinen",
    "iso:country":"NL",
    "sg:address":"Laan Van Eik En Duinen 181",
    "sg:city":"'S Gravenhage",
    "sg:orig_category":"Kinderopvang Behalve Thuis",
    "sg:phone":"+31 70 360 0664",
    "sg:postcode":"2564 GP",
    "sg:province":"Zuid-Holland",
    "wof:name":"Stichting Welzijnsorganisatie Segbroek Loosduinen",
    "wof:placetype":"venue"
},
  "geometry": {"coordinates":[4.263341,52.071697],"type":"Point"}
}