{
  "type": "Feature",
  "properties": {
    "iso:country":"NL",
    "sg:address":"Zuiderbuuren 13",
    "sg:city":"Marum",
    "sg:orig_category":"Nagelstudio'S",
    "sg:phone":"+31 594 646 267",
    "sg:postcode":"9363 HK",
    "sg:province":"Groningen",
    "wof:name":"Allure Beauty",
    "wof:placetype":"venue"
},
  "geometry": {"coordinates":[6.246542,53.141994],"type":"Point"}
}