{
  "type": "Feature",
  "properties": {
    "addr:full":"B K Van De Bergstrjitte 2 Wergea Friesland 9005 PW",
    "addr:housenumber":"2",
    "addr:postcode":"9005 pw",
    "addr:street":"Van De Bergstrjitte",
    "iso:country":"NL",
    "sg:address":"B K Van De Bergstrjitte 2",
    "sg:city":"Wergea",
    "sg:classifiers":[
        {
            "category":"Education",
            "subcategory":"Preschool",
            "type":"Public Place"
        }
    ],
    "sg:phone":"+31 58 255 2557",
    "sg:postcode":"9005 PW",
    "sg:province":"Friesland",
    "sg:tags":[
        "kleuteronderwijs",
        "basis-"
    ],
    "wof:name":"Openbare Basisschool De Twamester",
    "wof:placetype":"venue"
},
  "geometry": {"coordinates":[5.84717,53.149899],"type":"Point"}
}