{
  "type": "Feature",
  "properties": {
    "addr:full":"Joubertstr 182 Gouda South Holland 2806 GK",
    "addr:housenumber":"182",
    "addr:postcode":"2806 gk",
    "iso:country":"NL",
    "sg:address":"Joubertstr 182",
    "sg:city":"Gouda",
    "sg:orig_category":"Projectinrichting",
    "sg:phone":"+31 182 519 516",
    "sg:postcode":"2806 GK",
    "sg:province":"South Holland",
    "wof:name":"Blom",
    "wof:placetype":"venue"
},
  "geometry": {"coordinates":[4.724596,52.009914],"type":"Point"}
}