{
  "type": "Feature",
  "properties": {
    "addr:full":"P J Troelstraln 59 Schiedam Zuid-Holland 3118 VB",
    "addr:housenumber":"59",
    "addr:postcode":"3118 vb",
    "iso:country":"NL",
    "sg:address":"P J Troelstraln 59",
    "sg:city":"Schiedam",
    "sg:orig_category":"Kappers",
    "sg:phone":"+31 10 470 3061",
    "sg:postcode":"3118 VB",
    "sg:province":"Zuid-Holland",
    "wof:name":"Nieuwland",
    "wof:placetype":"venue"
},
  "geometry": {"coordinates":[4.39816,51.918472],"type":"Point"}
}