{
  "type": "Feature",
  "properties": {
    "iso:country":"NL",
    "sg:address":"Windmolen 47",
    "sg:city":"Ridderkerk",
    "sg:orig_category":"Boekenuitgeverijen",
    "sg:phone":"+31 180 462 089",
    "sg:postcode":"2986 TK",
    "sg:province":"Zuid-Holland",
    "wof:name":"P & P Uitgeverij",
    "wof:placetype":"venue"
},
  "geometry": {"coordinates":[4.612847,51.861652],"type":"Point"}
}