{
  "type": "Feature",
  "properties": {
    "addr:full":"L Herenvest 134 Haarlem Noord-Holland 2011 BX",
    "addr:housenumber":"134",
    "addr:postcode":"2011 bx",
    "iso:country":"NL",
    "sg:address":"L Herenvest 134",
    "sg:city":"Haarlem",
    "sg:orig_category":"Fotoreportages",
    "sg:phone":"+31 23 542 4252",
    "sg:postcode":"2011 BX",
    "sg:province":"Noord-Holland",
    "sg:website":"http://www.sanderstoepker.nl",
    "wof:name":"Stoepker, Sander",
    "wof:placetype":"venue"
},
  "geometry": {"coordinates":[4.641881,52.377094],"type":"Point"}
}