{
  "type": "Feature",
  "properties": {
    "iso:country":"NL",
    "sg:address":"Hoofdstraat 21",
    "sg:city":"Albergen",
    "sg:orig_category":"Fotostudio'S And Fotografen",
    "sg:phone":"+31 546 441 110",
    "sg:postcode":"7665 AN",
    "sg:province":"Overijssel",
    "wof:name":"Fotografie Frank Visschedijk",
    "wof:placetype":"venue"
},
  "geometry": {"coordinates":[6.760923,52.372204],"type":"Point"}
}