{
  "type": "Feature",
  "properties": {
    "addr:full":"Ir Sassenstraat 49-51 Ulft Gelderland 7071 BB",
    "addr:housenumber":"49-51",
    "addr:postcode":"7071 bb",
    "addr:street":"Ir Sassenstraat;Gelderland",
    "iso:country":"NL",
    "sg:address":"Ir Sassenstraat 49-51",
    "sg:city":"Ulft",
    "sg:orig_category":"Schoonheidssalons",
    "sg:phone":"+31 315 640 959",
    "sg:postcode":"7071 BB",
    "sg:province":"Gelderland",
    "wof:name":"Beauty En Body",
    "wof:placetype":"venue"
},
  "geometry": {"coordinates":[6.377856,51.894272],"type":"Point"}
}