{
  "type": "Feature",
  "properties": {
    "addr:full":"Meidoornhof 42 De Lier Zuid-Holland 2678 RG",
    "addr:housenumber":"42",
    "addr:postcode":"2678 rg",
    "addr:street":"Meidoornhof",
    "iso:country":"NL",
    "sg:address":"Meidoornhof 42",
    "sg:city":"De Lier",
    "sg:orig_category":"Sportverenigingen En Ontspannings- Verenigingen",
    "sg:phone":"+31 174 514 756",
    "sg:postcode":"2678 RG",
    "sg:province":"Zuid-Holland",
    "wof:name":"Maasland Sv",
    "wof:placetype":"venue"
},
  "geometry": {"coordinates":[4.247303,51.977627],"type":"Point"}
}