{
  "type": "Feature",
  "properties": {
    "addr:full":"Lekerwaard 215 Alkmaar Noord-Holland 1824 HJ",
    "addr:housenumber":"215",
    "addr:postcode":"1824 hj",
    "addr:street":"Lekerwaard",
    "iso:country":"NL",
    "sg:address":"Lekerwaard 215",
    "sg:city":"Alkmaar",
    "sg:orig_category":"Verloskundigen",
    "sg:phone":"+31 72 564 6737",
    "sg:postcode":"1824 HJ",
    "sg:province":"Noord-Holland",
    "wof:name":"Burg & A A Schraag, J M Van Der",
    "wof:placetype":"venue"
},
  "geometry": {"coordinates":[4.756875,52.643349],"type":"Point"}
}