{
  "type": "Feature",
  "properties": {
    "addr:full":"Einderstr 1 Heerlen Limburg 6414 NG",
    "addr:housenumber":"1",
    "addr:postcode":"6414 ng",
    "addr:street":"Einderstr",
    "iso:country":"NL",
    "sg:address":"Einderstr 1",
    "sg:city":"Heerlen",
    "sg:orig_category":"Sauna'S",
    "sg:phone":"+31 45 521 4550",
    "sg:postcode":"6414 NG",
    "sg:province":"Limburg",
    "wof:name":"Poglajen, M",
    "wof:placetype":"venue"
},
  "geometry": {"coordinates":[5.960767,50.928219],"type":"Point"}
}