{
  "type": "Feature",
  "properties": {
    "addr:full":"Cranenburgsestraat 87 Groesbeek Gelderland 6562 LT",
    "addr:housenumber":"87",
    "addr:postcode":"6562 lt",
    "addr:street":"Cranenburgsestraat;Gelderland",
    "iso:country":"NL",
    "sg:address":"Cranenburgsestraat 87",
    "sg:city":"Groesbeek",
    "sg:orig_category":"Diverse Dierenfokkers",
    "sg:phone":"+31 24 397 3694",
    "sg:postcode":"6562 LT",
    "sg:province":"Gelderland",
    "wof:name":"Rutten",
    "wof:placetype":"venue"
},
  "geometry": {"coordinates":[5.980153,51.778126],"type":"Point"}
}