{
  "type": "Feature",
  "properties": {
    "addr:full":"Markt 2 Schagen Noord-Holland 1741 BS",
    "addr:housenumber":"2",
    "addr:postcode":"1741 bs",
    "addr:street":"Markt",
    "iso:country":"NL",
    "sg:address":"Markt 2",
    "sg:city":"Schagen",
    "sg:classifiers":[
        {
            "category":"Fast Food",
            "type":"Food & Drink"
        }
    ],
    "sg:phone":"+31 224 297 202",
    "sg:postcode":"1741 BS",
    "sg:province":"Noord-Holland",
    "sg:tags":[
        "afhaal",
        "restaurant"
    ],
    "wof:name":"Chinees-Indisch Restaurant Golden Valley",
    "wof:placetype":"venue"
},
  "geometry": {"coordinates":[4.796072,52.786945],"type":"Point"}
}