{
  "type": "Feature",
  "properties": {
    "addr:full":"Wilhelminaln 10 Hulst Zeeland 4561 HS",
    "addr:housenumber":"10",
    "addr:postcode":"4561 hs",
    "addr:street":"Wilhelminaln",
    "iso:country":"NL",
    "sg:address":"Wilhelminaln 10",
    "sg:city":"Hulst",
    "sg:orig_category":"Mensendieck - Oefentherapeuten",
    "sg:phone":"+31 114 311 136",
    "sg:postcode":"4561 HS",
    "sg:province":"Zeeland",
    "wof:name":"Feijter, De",
    "wof:placetype":"venue"
},
  "geometry": {"coordinates":[4.05389,51.280113],"type":"Point"}
}