{
  "type": "Feature",
  "properties": {
    "addr:full":"Boezemwg 174 Rotterdam Zuid-Holland 3031 BP",
    "addr:housenumber":"174",
    "addr:postcode":"3031 bp",
    "iso:country":"NL",
    "sg:address":"Boezemwg 174",
    "sg:city":"Rotterdam",
    "sg:orig_category":"Scholen Voor Basisonderwijs",
    "sg:phone":"+31 10 412 1819",
    "sg:postcode":"3031 BP",
    "sg:province":"Zuid-Holland",
    "wof:name":"Johannes Martinus Cso",
    "wof:placetype":"venue"
},
  "geometry": {"coordinates":[4.496191,51.924431],"type":"Point"}
}