{
  "type": "Feature",
  "properties": {
    "iso:country":"NL",
    "sg:address":"Leywg 595P",
    "sg:city":"S Gravenhage",
    "sg:orig_category":"Sportschoenen - Winkels",
    "sg:phone":"+31 70 359 8638",
    "sg:postcode":"2545 GH",
    "sg:province":"Zuid-Holland",
    "wof:name":"Aktiesport",
    "wof:placetype":"venue"
},
  "geometry": {"coordinates":[4.2704901695,52.0509300232],"type":"Point"}
}