{
  "type": "Feature",
  "properties": {
    "addr:full":"N Vd Laanstr 1 Haarlem Noord-Holland 2013 BL",
    "addr:housenumber":"1",
    "addr:postcode":"2013 bl",
    "addr:street":"N",
    "iso:country":"NL",
    "sg:address":"N Vd Laanstr 1",
    "sg:city":"Haarlem",
    "sg:orig_category":"Schilders",
    "sg:phone":"+31 6 23366519",
    "sg:postcode":"2013 BL",
    "sg:province":"Noord-Holland",
    "wof:name":"Beemsterboer",
    "wof:placetype":"venue"
},
  "geometry": {"coordinates":[4.642253,52.380562],"type":"Point"}
}