{
  "type": "Feature",
  "properties": {
    "addr:full":"Westermarkt 38 Tilburg Noord-Brabant 5042 MD",
    "addr:housenumber":"38",
    "addr:postcode":"5042",
    "addr:street":"Westermarkt",
    "iso:country":"NL",
    "sg:address":"Westermarkt 38",
    "sg:city":"Tilburg",
    "sg:orig_category":"Bloemen And Planten",
    "sg:phone":"+31 13 463 6126",
    "sg:postcode":"5042 MD",
    "sg:province":"Noord-Brabant",
    "wof:name":"Wero Bloemen",
    "wof:placetype":"venue"
},
  "geometry": {"coordinates":[5.053386,51.569489],"type":"Point"}
}