{
  "type": "Feature",
  "properties": {
    "iso:country":"NL",
    "sg:address":"Annastr 41",
    "sg:city":"Geleen",
    "sg:orig_category":"Schoenen",
    "sg:phone":"+31 46 474 3704",
    "sg:postcode":"6161 GW",
    "sg:province":"Limburg",
    "wof:name":"Baggen, J H",
    "wof:placetype":"venue"
},
  "geometry": {"coordinates":[5.825931,50.971722],"type":"Point"}
}