{
  "type": "Feature",
  "properties": {
    "addr:full":"Bolsterstraat 20 Slagharen NL.08 7776 BC",
    "addr:housenumber":"20;nl.08",
    "addr:postcode":"7776 bc",
    "addr:street":"Bolsterstraat",
    "iso:country":"NL",
    "sg:address":"Bolsterstraat 20",
    "sg:city":"Slagharen",
    "sg:orig_category":"Verzekeringen",
    "sg:phone":"+31 523 683 577",
    "sg:postcode":"7776 BC",
    "sg:province":"NL.08",
    "wof:name":"Assurantiekantoor Slagharen",
    "wof:placetype":"venue"
},
  "geometry": {"coordinates":[6.55442,52.628502],"type":"Point"}
}