{
  "type": "Feature",
  "properties": {
    "addr:full":"Grt Houtstr 8 Haarlem Noord-Holland 2011 SN",
    "addr:housenumber":"8",
    "addr:postcode":"2011 sn",
    "addr:street":"Houtstr",
    "iso:country":"NL",
    "sg:address":"Grt Houtstr 8",
    "sg:city":"Haarlem",
    "sg:orig_category":"Huishoudelijke Apparaten En Artikelen",
    "sg:phone":"+31 23 532 7243",
    "sg:postcode":"2011 SN",
    "sg:province":"Noord-Holland",
    "wof:name":"Marskramer Bv",
    "wof:placetype":"venue"
},
  "geometry": {"coordinates":[4.635509,52.380951],"type":"Point"}
}