{
  "type": "Feature",
  "properties": {
    "addr:full":"Bernhardstr 2 Bakel Noord-Brabant 5761 BJ",
    "addr:housenumber":"2",
    "addr:postcode":"5761 bj",
    "addr:street":"Bernhardstr",
    "iso:country":"NL",
    "sg:address":"Bernhardstr 2",
    "sg:city":"Bakel",
    "sg:orig_category":"Artsen - Huisartsen",
    "sg:phone":"+31 492 342 185",
    "sg:postcode":"5761 BJ",
    "sg:province":"Noord-Brabant",
    "wof:name":"Bakel, Huisartsenpraktijk",
    "wof:placetype":"venue"
},
  "geometry": {"coordinates":[5.741286,51.504337],"type":"Point"}
}