{
  "type": "Feature",
  "properties": {
    "iso:country":"NL",
    "sg:address":"Dokter Van Peltlaan 1",
    "sg:city":"Bergen Nh",
    "sg:classifiers":[
        {
            "category":"Professional",
            "subcategory":"Accounting & Tax Preparation",
            "type":"Services"
        }
    ],
    "sg:phone":"+31 72 581 2577",
    "sg:postcode":"1861 KA",
    "sg:province":"North Holland",
    "sg:tags":[
        "accountant"
    ],
    "wof:name":"Adm- En Belastingadviesbureau De Lange & Peijs Bv",
    "wof:placetype":"venue"
},
  "geometry": {"coordinates":[4.703866,52.670475],"type":"Point"}
}