{
  "type": "Feature",
  "properties": {
    "iso:country":"NL",
    "sg:address":"Mosln 44",
    "sg:city":"Arnhem",
    "sg:orig_category":"Kappers",
    "sg:phone":"+31 26 443 5984",
    "sg:postcode":"6823 JP",
    "sg:province":"Gelderland",
    "wof:name":"Helma",
    "wof:placetype":"venue"
},
  "geometry": {"coordinates":[5.9380397797,52.0026092529],"type":"Point"}
}