{
  "type": "Feature",
  "properties": {
    "addr:full":"Graafseweg 544 Wijchen Gelderland 6603 CK",
    "addr:housenumber":"544",
    "addr:postcode":"6603 ck",
    "addr:street":"Graafseweg;Gelderland",
    "iso:country":"NL",
    "sg:address":"Graafseweg 544",
    "sg:city":"Wijchen",
    "sg:orig_category":"Kappers",
    "sg:phone":"+31 24 641 2445",
    "sg:postcode":"6603 CK",
    "sg:province":"Gelderland",
    "wof:name":"Kapsalon H.F. Fleuren",
    "wof:placetype":"venue"
},
  "geometry": {"coordinates":[5.7523498535,51.7949409485],"type":"Point"}
}