{
  "type": "Feature",
  "properties": {
    "addr:full":"Teugeln 11 Schoorl North Holland 1871 AJ",
    "addr:housenumber":"11",
    "addr:postcode":"1871 aj",
    "addr:street":"Teugeln",
    "iso:country":"NL",
    "sg:address":"Teugeln 11",
    "sg:city":"Schoorl",
    "sg:orig_category":"Boekbinderijen",
    "sg:phone":"+31 72 509 2111",
    "sg:postcode":"1871 AJ",
    "sg:province":"North Holland",
    "wof:name":"Cmb",
    "wof:placetype":"venue"
},
  "geometry": {"coordinates":[4.68178,52.713909],"type":"Point"}
}