{
  "type": "Feature",
  "properties": {
    "addr:full":"Schierbeekstr 24 Enschede Overijssel 7548 DA",
    "addr:housenumber":"24",
    "addr:postcode":"7548 da",
    "addr:street":"Schierbeekstr",
    "iso:country":"NL",
    "sg:address":"Schierbeekstr 24",
    "sg:city":"Enschede",
    "sg:orig_category":"Geluidsinstallaties - Verhuur",
    "sg:phone":"+31 53 428 2486",
    "sg:postcode":"7548 DA",
    "sg:province":"Overijssel",
    "sg:website":"http://www.radstaake.com",
    "wof:name":"Bert Radstaake, Licht- En Geluidverhuur",
    "wof:placetype":"venue"
},
  "geometry": {"coordinates":[6.797805,52.203011],"type":"Point"}
}