{
  "type": "Feature",
  "properties": {
    "iso:country":"NL",
    "sg:address":"Gezellenbaan 12",
    "sg:city":"Ysselsteyn Lb",
    "sg:orig_category":"Metaalwaren - Fabrieken",
    "sg:phone":"+31 478 542 018",
    "sg:postcode":"5813 EA",
    "sg:province":"Limburg",
    "sg:website":"http://www.interal.nl",
    "wof:name":"Interal Bv",
    "wof:placetype":"venue"
},
  "geometry": {"coordinates":[5.898114,51.48922],"type":"Point"}
}