{
  "type": "Feature",
  "properties": {
    "addr:full":"Gezellenbaan 12 Ysselsteyn Lb Limburg 5813 EA",
    "addr:housenumber":"12",
    "addr:postcode":"lb;5813 ea",
    "addr:street":"Gezellenbaan",
    "iso:country":"NL",
    "sg:address":"Gezellenbaan 12",
    "sg:city":"Ysselsteyn Lb",
    "sg:orig_category":"Metaalwaren - Fabrieken",
    "sg:phone":"+31 478 542 018",
    "sg:postcode":"5813 EA",
    "sg:province":"Limburg",
    "sg:website":"http://www.interal.nl",
    "wof:name":"Interal Bv",
    "wof:placetype":"venue"
},
  "geometry": {"coordinates":[5.898114,51.48922],"type":"Point"}
}