{
  "type": "Feature",
  "properties": {
    "iso:country":"NL",
    "sg:address":"Zonnebloemveld 1",
    "sg:city":"Beuningen Gld",
    "sg:orig_category":"Woningbouwverenigingen",
    "sg:phone":"+31 24 677 2058",
    "sg:postcode":"6641 TA",
    "sg:province":"Gelderland",
    "wof:name":"Woningstichting Beuningen",
    "wof:placetype":"venue"
},
  "geometry": {"coordinates":[5.753824234,51.86378479],"type":"Point"}
}