{
  "type": "Feature",
  "properties": {
    "addr:full":"Zonnebloemveld 1 Beuningen Gld Gelderland 6641 TA",
    "addr:housenumber":"1",
    "addr:postcode":"6641 ta",
    "addr:street":"Zonnebloemveld",
    "iso:country":"NL",
    "sg:address":"Zonnebloemveld 1",
    "sg:city":"Beuningen Gld",
    "sg:orig_category":"Woningbouwverenigingen",
    "sg:phone":"+31 24 677 2058",
    "sg:postcode":"6641 TA",
    "sg:province":"Gelderland",
    "wof:name":"Woningstichting Beuningen",
    "wof:placetype":"venue"
},
  "geometry": {"coordinates":[5.753824234,51.86378479],"type":"Point"}
}