{
  "type": "Feature",
  "properties": {
    "addr:full":"Berkenhove 10A Leidschendam South Holland 2262 AK",
    "addr:housenumber":"10a",
    "addr:postcode":"2262 ak",
    "addr:street":"Berkenhove",
    "iso:country":"NL",
    "sg:address":"Berkenhove 10A",
    "sg:city":"Leidschendam",
    "sg:orig_category":"Woninginrichting",
    "sg:phone":"+31 70 320 1739",
    "sg:postcode":"2262 AK",
    "sg:province":"South Holland",
    "wof:name":"Struycken",
    "wof:placetype":"venue"
},
  "geometry": {"coordinates":[4.3835468292,52.0889701843],"type":"Point"}
}