{
  "type": "Feature",
  "properties": {
    "addr:full":"Hugo De Grootlaan 14 Amersfoort Utrecht 3818 TB",
    "addr:housenumber":"14",
    "addr:postcode":"3818 tb",
    "addr:street":"Hugo De Grootlaan",
    "iso:country":"NL",
    "sg:address":"Hugo De Grootlaan 14",
    "sg:city":"Amersfoort",
    "sg:orig_category":"Granen, Zaden And Diervoeders Gh",
    "sg:phone":"+31 33 465 6127",
    "sg:postcode":"3818 TB",
    "sg:province":"Utrecht",
    "wof:name":"Van Der Vaart, Veevoeder Bv",
    "wof:placetype":"venue"
},
  "geometry": {"coordinates":[5.371761,52.141895],"type":"Point"}
}