{
  "type": "Feature",
  "properties": {
    "addr:full":"Wildemansteeg 3 Wijk Bij Duurstede Utrecht 3961 AP",
    "addr:housenumber":"3",
    "addr:postcode":"3961 ap",
    "addr:street":"Wildemansteeg",
    "iso:country":"NL",
    "sg:address":"Wildemansteeg 3",
    "sg:city":"Wijk Bij Duurstede",
    "sg:orig_category":"Fitnesscentra",
    "sg:phone":"+31 343 579 470",
    "sg:postcode":"3961 AP",
    "sg:province":"Utrecht",
    "wof:name":"Energy Fitness En Aerobic Studio",
    "wof:placetype":"venue"
},
  "geometry": {"coordinates":[5.348632,51.972164],"type":"Point"}
}