{
  "type": "Feature",
  "properties": {
    "iso:country":"NL",
    "sg:address":"Achterstraat 63",
    "sg:city":"Vianen Zh",
    "sg:orig_category":"Goederenvervoer Over De Weg",
    "sg:phone":"+31 347 376 702",
    "sg:postcode":"4132 VB",
    "sg:province":"Utrecht",
    "wof:name":"Firma Jac. Baars En Zoon",
    "wof:placetype":"venue"
},
  "geometry": {"coordinates":[5.091648,51.993713],"type":"Point"}
}