{
  "type": "Feature",
  "properties": {
    "iso:country":"NL",
    "sg:address":"Kruisweg 1",
    "sg:city":"Meliskerke",
    "sg:orig_category":"Kampeerterreinen",
    "sg:phone":"+31 118 561 343",
    "sg:postcode":"4365 NM",
    "sg:province":"Zeeland",
    "wof:name":"P. Wisse",
    "wof:placetype":"venue"
},
  "geometry": {"coordinates":[3.5288069248,51.5280570984],"type":"Point"}
}