{
  "type": "Feature",
  "properties": {
    "addr:full":"Valeriaanstr 57 Soest Utrecht 3765 EJ",
    "addr:housenumber":"57",
    "addr:postcode":"3765 ej",
    "addr:street":"Valeriaanstr",
    "iso:country":"NL",
    "sg:address":"Valeriaanstr 57",
    "sg:city":"Soest",
    "sg:orig_category":"Drukkerijen",
    "sg:phone":"+31 35 601 9078",
    "sg:postcode":"3765 EJ",
    "sg:province":"Utrecht",
    "wof:name":"Horens",
    "wof:placetype":"venue"
},
  "geometry": {"coordinates":[5.293568,52.1675],"type":"Point"}
}