{
  "type": "Feature",
  "properties": {
    "addr:full":"Tolweg 10 Zeerijp Groningen 9914 TA",
    "addr:housenumber":"10",
    "addr:postcode":"9914 ta",
    "addr:street":"Tolweg",
    "iso:country":"NL",
    "sg:address":"Tolweg 10",
    "sg:city":"Zeerijp",
    "sg:orig_category":"Goederenvervoer Over De Weg",
    "sg:phone":"+31 596 582 099",
    "sg:postcode":"9914 TA",
    "sg:province":"Groningen",
    "wof:name":"Jan Jansen Transport",
    "wof:placetype":"venue"
},
  "geometry": {"coordinates":[6.784039,53.35313],"type":"Point"}
}