{
  "type": "Feature",
  "properties": {
    "addr:full":"Vd Hoopstr 12 Krimpen Ad Yssel Zuid-Holland 2921 LR",
    "addr:housenumber":"12",
    "addr:postcode":"2921 lr",
    "addr:street":"Krimpen",
    "iso:country":"NL",
    "sg:address":"Vd Hoopstr 12",
    "sg:city":"Krimpen Ad Yssel",
    "sg:classifiers":[
        {
            "category":"Wholesale",
            "subcategory":"Meat",
            "type":"Manufacturing & Wholesale Goods"
        }
    ],
    "sg:phone":"+31 180 512 166",
    "sg:postcode":"2921 LR",
    "sg:province":"Zuid-Holland",
    "sg:tags":[
        "bode-",
        "en",
        "lijndiensten"
    ],
    "wof:name":"Leeuwen & Znn Bv, G J Van",
    "wof:placetype":"venue"
},
  "geometry": {"coordinates":[4.5731,51.909908],"type":"Point"}
}