{
  "type": "Feature",
  "properties": {
    "iso:country":"NL",
    "sg:address":"Merendonk 91",
    "sg:city":"Leiden",
    "sg:orig_category":"Geluidsinstallaties - Verhuur",
    "sg:phone":"+31 71 523 0115",
    "sg:postcode":"2317 XS",
    "sg:province":"Zuid-Holland",
    "sg:website":"http://www.md-verhuur.nl",
    "wof:name":"Md Evenementenservice",
    "wof:placetype":"venue"
},
  "geometry": {"coordinates":[4.510556,52.172356],"type":"Point"}
}