{
  "type": "Feature",
  "properties": {
    "addr:full":"Wassenaarstr 100 Ter Aar South Holland 2461 RE",
    "addr:housenumber":"100",
    "addr:postcode":"2461 re",
    "addr:street":"Ter",
    "iso:country":"NL",
    "sg:address":"Wassenaarstr 100",
    "sg:city":"Ter Aar",
    "sg:orig_category":"Verenigingsgebouwen",
    "sg:phone":"+31 172 604 635",
    "sg:postcode":"2461 RE",
    "sg:province":"South Holland",
    "wof:name":"Welverro",
    "wof:placetype":"venue"
},
  "geometry": {"coordinates":[4.709815,52.19268],"type":"Point"}
}