{
  "type": "Feature",
  "properties": {
    "addr:full":"Muiderstrwg 39C Diemen Noord-Holland 1111 PS",
    "addr:housenumber":"39c",
    "addr:postcode":"1111 ps",
    "addr:street":"Muiderstrwg",
    "iso:country":"NL",
    "sg:address":"Muiderstrwg 39C",
    "sg:city":"Diemen",
    "sg:orig_category":"Video - Faciliteiten En Producties",
    "sg:phone":"+31 20 416 0390",
    "sg:postcode":"1111 PS",
    "sg:province":"Noord-Holland",
    "sg:website":"http://www.marvelmedia.nl",
    "wof:name":"Marvelmedia",
    "wof:placetype":"venue"
},
  "geometry": {"coordinates":[4.964805,52.34132],"type":"Point"}
}