{
  "type": "Feature",
  "properties": {
    "iso:country":"NL",
    "sg:address":"Zuidsngl 9",
    "sg:city":"Amersfoort",
    "sg:orig_category":"Bedrijfsopleidingen",
    "sg:phone":"+31 33 462 2837",
    "sg:postcode":"3811 HA",
    "sg:province":"Utrecht",
    "sg:website":"http://www.impulsus.com",
    "wof:name":"Impulsus",
    "wof:placetype":"venue"
},
  "geometry": {"coordinates":[5.386085,52.152325],"type":"Point"}
}