{
  "type": "Feature",
  "properties": {
    "addr:full":"Grt Maatwg 39 Wierden NL.08 7642 VL",
    "addr:housenumber":"39;nl.08",
    "addr:postcode":"7642 vl",
    "iso:country":"NL",
    "sg:address":"Grt Maatwg 39",
    "sg:city":"Wierden",
    "sg:orig_category":"Autorijscholen",
    "sg:phone":"+31 546 574 242",
    "sg:postcode":"7642 VL",
    "sg:province":"NL.08",
    "wof:name":"Slaghuis, Frits",
    "wof:placetype":"venue"
},
  "geometry": {"coordinates":[6.597979,52.353825],"type":"Point"}
}