{
  "type": "Feature",
  "properties": {
    "iso:country":"NL",
    "sg:address":"Korte Enkweg 2",
    "sg:city":"Epe",
    "sg:orig_category":"Krantenuitgeverijen",
    "sg:phone":"+31 578 629 061",
    "sg:postcode":"8162 VJ",
    "sg:province":"Gelderland",
    "wof:name":"Gelderland Vakbladen Uitgeverij (G.V.U.)",
    "wof:placetype":"venue"
},
  "geometry": {"coordinates":[5.9808478355,52.3449325562],"type":"Point"}
}