{
  "type": "Feature",
  "properties": {
    "iso:country":"NL",
    "sg:address":"Distellaan 17",
    "sg:city":"Arnhem",
    "sg:classifiers":[
        {
            "category":"Fast Food",
            "type":"Food & Drink"
        }
    ],
    "sg:phone":"+31 26 321 4404",
    "sg:postcode":"6833 AX",
    "sg:province":"Gelderland",
    "sg:tags":[
        "afhaal",
        "restaurant"
    ],
    "wof:name":"Snackbar De Snip",
    "wof:placetype":"venue"
},
  "geometry": {"coordinates":[5.909637,51.968246],"type":"Point"}
}