{
  "type": "Feature",
  "properties": {
    "addr:full":"Vlierdensewg 167 Vlierden Noord-Brabant 5756 AA",
    "addr:housenumber":"167",
    "addr:postcode":"5756 aa",
    "iso:country":"NL",
    "sg:address":"Vlierdensewg 167",
    "sg:city":"Vlierden",
    "sg:orig_category":"Kinderkleding",
    "sg:phone":"+31 493 354 567",
    "sg:postcode":"5756 AA",
    "sg:province":"Noord-Brabant",
    "wof:name":"Kinderschuur, De",
    "wof:placetype":"venue"
},
  "geometry": {"coordinates":[5.764862,51.444416],"type":"Point"}
}