{
  "type": "Feature",
  "properties": {
    "addr:full":"Duinmeiery 83 Leidschendam Zuid-Holland 2264 LJ",
    "addr:housenumber":"83",
    "addr:postcode":"2264 lj",
    "addr:street":"Duinmeiery",
    "iso:country":"NL",
    "sg:address":"Duinmeiery 83",
    "sg:city":"Leidschendam",
    "sg:orig_category":"Onderhoudswerken",
    "sg:phone":"+31 70 320 2388",
    "sg:postcode":"2264 LJ",
    "sg:province":"Zuid-Holland",
    "wof:name":"Weegen, J Van Der",
    "wof:placetype":"venue"
},
  "geometry": {"coordinates":[4.399772,52.089645],"type":"Point"}
}