{
  "type": "Feature",
  "properties": {
    "iso:country":"NL",
    "sg:address":"Frieswykstr 68",
    "sg:city":"Nykerk Gld",
    "sg:orig_category":"Advocaten En Advocatenkantoren",
    "sg:phone":"+31 33 245 8544",
    "sg:postcode":"3862 BM",
    "sg:province":"Gelderland",
    "sg:website":"http://www.vandermeijden.com",
    "wof:name":"Meijden & Reitsma, Van Der",
    "wof:placetype":"venue"
},
  "geometry": {"coordinates":[5.51415,52.21376],"type":"Point"}
}