{
  "type": "Feature",
  "properties": {
    "addr:full":"Kleine Looiersstraat 6 Maastricht Limburg 6211 JL",
    "addr:housenumber":"6",
    "addr:postcode":"6211 jl",
    "addr:street":"Kleine Looiersstraat",
    "iso:country":"NL",
    "sg:address":"Kleine Looiersstraat 6",
    "sg:city":"Maastricht",
    "sg:orig_category":"Architecten",
    "sg:phone":"+31 43 321 5505",
    "sg:postcode":"6211 JL",
    "sg:province":"Limburg",
    "wof:name":"Gulikers Architecten",
    "wof:placetype":"venue"
},
  "geometry": {"coordinates":[5.690747,50.84528],"type":"Point"}
}