{
  "type": "Feature",
  "properties": {
    "addr:full":"Laurastr 7A Eygelshoven Limburg 6471 JG",
    "addr:housenumber":"7a",
    "addr:postcode":"6471 jg",
    "addr:street":"Laurastr",
    "iso:country":"NL",
    "sg:address":"Laurastr 7A",
    "sg:city":"Eygelshoven",
    "sg:orig_category":"Verzekeringen - Verzekeringskantoren",
    "sg:phone":"+31 45 545 2026",
    "sg:postcode":"6471 JG",
    "sg:province":"Limburg",
    "wof:name":"Lauvenberg Assuranti\u00ebn",
    "wof:placetype":"venue"
},
  "geometry": {"coordinates":[6.05966,50.893543],"type":"Point"}
}