{
  "type": "Feature",
  "properties": {
    "addr:full":"Koetshusleane 24 Woudsend Friesland 8551 PW",
    "addr:housenumber":"24",
    "addr:postcode":"8551 pw",
    "addr:street":"Koetshusleane",
    "iso:country":"NL",
    "sg:address":"Koetshusleane 24",
    "sg:city":"Woudsend",
    "sg:orig_category":"Watersport-, Sport- And Kampeerbenodigdheden Verhuur",
    "sg:phone":"+31 514 591 435",
    "sg:postcode":"8551 PW",
    "sg:province":"Friesland",
    "wof:name":"Jachtenverhuurbedrijf Tusken De Marren",
    "wof:placetype":"venue"
},
  "geometry": {"coordinates":[5.6307578087,52.9419631958],"type":"Point"}
}