{
  "type": "Feature",
  "properties": {
    "addr:full":"F A Molynln 188-192 Nunspeet Gelderland 8071 AK",
    "addr:housenumber":"188-192",
    "addr:postcode":"8071 ak",
    "addr:street":"F;Gelderland",
    "iso:country":"NL",
    "sg:address":"F A Molynln 188-192",
    "sg:city":"Nunspeet",
    "sg:classifiers":[
        {
            "category":"Retail",
            "subcategory":"Auto Repair",
            "type":"Services"
        }
    ],
    "sg:phone":"+31 341 256 044",
    "sg:postcode":"8071 AK",
    "sg:province":"Gelderland",
    "sg:tags":[
        "garage"
    ],
    "wof:name":"Hurk, Vd",
    "wof:placetype":"venue"
},
  "geometry": {"coordinates":[5.772205,52.374981],"type":"Point"}
}