{
  "type": "Feature",
  "properties": {
    "iso:country":"NL",
    "sg:address":"Brinkstr 9-11-13",
    "sg:city":"Vries",
    "sg:orig_category":"Orthopedische Artikelen",
    "sg:phone":"+31 592 542 555",
    "sg:postcode":"9481 BJ",
    "sg:province":"Provincie Drenthe",
    "sg:website":"http://www.stelorthopedie.nl",
    "wof:name":"Stel Orthopedie Bv",
    "wof:placetype":"venue"
},
  "geometry": {"coordinates":[6.5764350891,53.0765228271],"type":"Point"}
}