{
  "type": "Feature",
  "properties": {
    "addr:full":"Rechterenstraat 32 Breda Noord-Brabant 4834 LV",
    "addr:housenumber":"32",
    "addr:postcode":"4834",
    "addr:street":"Rechterenstraat",
    "iso:country":"NL",
    "sg:address":"Rechterenstraat 32",
    "sg:city":"Breda",
    "sg:orig_category":"Verzekeringen",
    "sg:phone":"+31 76 564 0610",
    "sg:postcode":"4834 LV",
    "sg:province":"Noord-Brabant",
    "wof:name":"Servitas",
    "wof:placetype":"venue"
},
  "geometry": {"coordinates":[-94.976479,42.181561],"type":"Point"}
}