{
  "type": "Feature",
  "properties": {
    "addr:full":"Langstraat 68 Barneveld Gelderland 3771 BH",
    "addr:housenumber":"68",
    "addr:postcode":"3771 bh",
    "addr:street":"Langstraat;Gelderland",
    "iso:country":"NL",
    "sg:address":"Langstraat 68",
    "sg:city":"Barneveld",
    "sg:orig_category":"Opticiens",
    "sg:phone":"+31 342 413 421",
    "sg:postcode":"3771 BH",
    "sg:province":"Gelderland",
    "wof:name":"Vof Het Huis Blitz Brillen Barneveld",
    "wof:placetype":"venue"
},
  "geometry": {"coordinates":[5.5868678093,52.1385345459],"type":"Point"}
}