{
  "type": "Feature",
  "properties": {
    "addr:full":"Marconistr 7 Leeuwarden Friesland 8912 AX",
    "addr:housenumber":"7",
    "addr:postcode":"8912 ax",
    "addr:street":"Marconistr",
    "iso:country":"NL",
    "sg:address":"Marconistr 7",
    "sg:city":"Leeuwarden",
    "sg:orig_category":"Machinefabrieken",
    "sg:phone":"+31 58 213 0808",
    "sg:postcode":"8912 AX",
    "sg:province":"Friesland",
    "wof:name":"Jovi, Fa",
    "wof:placetype":"venue"
},
  "geometry": {"coordinates":[5.770469,53.18692],"type":"Point"}
}