{
  "type": "Feature",
  "properties": {
    "addr:full":"Ijsselmeer 36 Zwijndrecht South Holland 3332 EX",
    "addr:housenumber":"36",
    "addr:postcode":"3332 ex",
    "addr:street":"Ijsselmeer",
    "iso:country":"NL",
    "sg:address":"Ijsselmeer 36",
    "sg:city":"Zwijndrecht",
    "sg:orig_category":"Werving And Selectie Van Vast Personeel",
    "sg:phone":"+31 78 620 6888",
    "sg:postcode":"3332 EX",
    "sg:province":"South Holland",
    "wof:name":"Banencentrum Zwijndrecht",
    "wof:placetype":"venue"
},
  "geometry": {"coordinates":[4.6488099098,51.8219490051],"type":"Point"}
}