{
  "type": "Feature",
  "properties": {
    "iso:country":"NL",
    "sg:address":"Brugstraat 13",
    "sg:city":"Raalte",
    "sg:orig_category":"Artiesten/Gezelschappen",
    "sg:phone":"+31 572 352 720",
    "sg:postcode":"8102 EP",
    "sg:province":"Overijssel",
    "sg:website":"http://www.houthakkersroadshow.nl",
    "wof:name":"Houthakkers Roadshow",
    "wof:placetype":"venue"
},
  "geometry": {"coordinates":[6.276328,52.384178],"type":"Point"}
}