{
  "type": "Feature",
  "properties": {
    "addr:full":"Middenwg 17 Moerdyk Noord-Brabant 4782 PM",
    "addr:housenumber":"17",
    "addr:postcode":"4782 pm",
    "addr:street":"Middenwg",
    "iso:country":"NL",
    "sg:address":"Middenwg 17",
    "sg:city":"Moerdyk",
    "sg:orig_category":"Gassen Industrieel En Medisch",
    "sg:phone":"+31 168 384 300",
    "sg:postcode":"4782 PM",
    "sg:province":"Noord-Brabant",
    "sg:website":"http://www.messer.nl",
    "wof:name":"Messer Bv",
    "wof:placetype":"venue"
},
  "geometry": {"coordinates":[4.585968,51.676746],"type":"Point"}
}