{
  "type": "Feature",
  "properties": {
    "addr:full":"Vlaardingenstraat 1 Almere Flevoland 1324  L",
    "addr:housenumber":"1;1324 l",
    "addr:street":"Vlaardingenstraat;Flevoland",
    "iso:country":"NL",
    "sg:address":"Vlaardingenstraat 1",
    "sg:city":"Almere",
    "sg:orig_category":"Meubelzaken, Woning- And Keukeninrichting",
    "sg:phone":"+31 36 530 0049",
    "sg:postcode":"1324  L",
    "sg:province":"Flevoland",
    "wof:name":"Tegels & Zo",
    "wof:placetype":"venue"
},
  "geometry": {"coordinates":[5.202101,52.36261],"type":"Point"}
}