{
  "type": "Feature",
  "properties": {
    "addr:full":"Brinkstr 22 Losser Overijssel 7581 GD",
    "addr:housenumber":"22",
    "addr:postcode":"7581 gd",
    "addr:street":"Brinkstr",
    "iso:country":"NL",
    "sg:address":"Brinkstr 22",
    "sg:city":"Losser",
    "sg:orig_category":"Schoenen - Reparaties",
    "sg:phone":"+31 53 536 0506",
    "sg:postcode":"7581 GD",
    "sg:province":"Overijssel",
    "wof:name":"Hans Dijkstra Losser",
    "wof:placetype":"venue"
},
  "geometry": {"coordinates":[7.007979,52.262337],"type":"Point"}
}