{
  "type": "Feature",
  "properties": {
    "iso:country":"NL",
    "sg:address":"Lytse Side 10",
    "sg:city":"Balk",
    "sg:orig_category":"Watersportartikelen",
    "sg:phone":"+31 514 602 212",
    "sg:postcode":"8561 AX",
    "sg:province":"\u00c5land",
    "sg:website":"http://www.bens-watersport.nl",
    "wof:name":"B & S",
    "wof:placetype":"venue"
},
  "geometry": {"coordinates":[20.2172908783,60.1982498169],"type":"Point"}
}