{
  "type": "Feature",
  "properties": {
    "addr:full":"Soestdyksewg Z 274 Bilthoven Utrecht 3721 AK",
    "addr:housenumber":"274",
    "addr:postcode":"3721 ak",
    "addr:street":"Bilthoven",
    "iso:country":"NL",
    "sg:address":"Soestdyksewg Z 274",
    "sg:city":"Bilthoven",
    "sg:orig_category":"Adviesbureaus Bedrijfsorganisatie",
    "sg:phone":"+31 30 231 8022",
    "sg:postcode":"3721 AK",
    "sg:province":"Utrecht",
    "sg:website":"http://www.museumsetcetera.nl",
    "wof:name":"Museums Etcetera",
    "wof:placetype":"venue"
},
  "geometry": {"coordinates":[5.204181,52.128376],"type":"Point"}
}