{
  "type": "Feature",
  "properties": {
    "addr:full":"Dwarsgr 37 Giethoorn NL.08 8355 CV",
    "addr:housenumber":"37;nl.08",
    "addr:postcode":"8355 cv",
    "addr:street":"Dwarsgr",
    "iso:country":"NL",
    "sg:address":"Dwarsgr 37",
    "sg:city":"Giethoorn",
    "sg:orig_category":"Loonbedrijven",
    "sg:phone":"+31 521 361 942",
    "sg:postcode":"8355 CV",
    "sg:province":"NL.08",
    "wof:name":"Piek, W",
    "wof:placetype":"venue"
},
  "geometry": {"coordinates":[6.037093,52.725052],"type":"Point"}
}