{
  "type": "Feature",
  "properties": {
    "iso:country":"NL",
    "sg:address":"Westervoortsedijk 95",
    "sg:city":"Arnhem",
    "sg:orig_category":"Gespecialiseerde Bouw",
    "sg:phone":"+31 26 442 6739",
    "sg:postcode":"6827 AW",
    "sg:province":"Gelderland",
    "wof:name":"De Smidse Vof",
    "wof:placetype":"venue"
},
  "geometry": {"coordinates":[5.920819,51.972225],"type":"Point"}
}