{
  "type": "Feature",
  "properties": {
    "addr:full":"Helena Erf 38 Capelle A/D Ijssel Zuid-Holland 2907 VB",
    "addr:housenumber":"38;a / d",
    "addr:postcode":"2907 vb",
    "addr:street":"Helena Erf",
    "iso:country":"NL",
    "sg:address":"Helena Erf 38",
    "sg:city":"Capelle A/D Ijssel",
    "sg:orig_category":"Diverse Opleidingen And Onderwijs",
    "sg:phone":"+31 10 458 9310",
    "sg:postcode":"2907 VB",
    "sg:province":"Zuid-Holland",
    "wof:name":"Aunikom",
    "wof:placetype":"venue"
},
  "geometry": {"coordinates":[4.572975,51.95137],"type":"Point"}
}