{
  "type": "Feature",
  "properties": {
    "addr:full":"Voorderstg 8 Twello Gelderland 7391 TL",
    "addr:housenumber":"8",
    "addr:postcode":"7391 tl",
    "addr:street":"Voorderstg;Gelderland",
    "iso:country":"NL",
    "sg:address":"Voorderstg 8",
    "sg:city":"Twello",
    "sg:orig_category":"Bloemen En Planten",
    "sg:phone":"+31 571 271 864",
    "sg:postcode":"7391 TL",
    "sg:province":"Gelderland",
    "sg:website":"http://www.vanbrummelenbloemen.nl",
    "wof:name":"Brummelen Bloemen, Van",
    "wof:placetype":"venue"
},
  "geometry": {"coordinates":[6.113103,52.227848],"type":"Point"}
}