{
  "type": "Feature",
  "properties": {
    "addr:full":"J Luykenstr 22 Hs Amsterdam North Holland 1071 CN",
    "addr:housenumber":"22 hs",
    "addr:postcode":"1071 cn",
    "iso:country":"NL",
    "sg:address":"J Luykenstr 22 Hs",
    "sg:city":"Amsterdam",
    "sg:orig_category":"Fotografie Reclame En Mode",
    "sg:phone":"+31 20 679 9080",
    "sg:postcode":"1071 CN",
    "sg:province":"North Holland",
    "wof:name":"Sluijter, H",
    "wof:placetype":"venue"
},
  "geometry": {"coordinates":[4.87701,52.355549],"type":"Point"}
}