{
  "type": "Feature",
  "properties": {
    "addr:full":"Lange Wijngaardstraat 19 Haarlem Noord-Holland 2011 RK",
    "addr:housenumber":"19",
    "addr:postcode":"2011 rk",
    "addr:street":"Lange Wijngaardstraat",
    "iso:country":"NL",
    "sg:address":"Lange Wijngaardstraat 19",
    "sg:city":"Haarlem",
    "sg:orig_category":"Geluidsopnamen",
    "sg:phone":"+31 23 542 4029",
    "sg:postcode":"2011 RK",
    "sg:province":"Noord-Holland",
    "wof:name":"The Flowerhouse",
    "wof:placetype":"venue"
},
  "geometry": {"coordinates":[4.636493,52.382721],"type":"Point"}
}