{
  "type": "Feature",
  "properties": {
    "addr:full":"Wolphaertsbocht 316 Rotterdam South Holland 3081 KS",
    "addr:housenumber":"316",
    "addr:postcode":"3081 ks",
    "addr:street":"Wolphaertsbocht",
    "iso:country":"NL",
    "sg:address":"Wolphaertsbocht 316",
    "sg:city":"Rotterdam",
    "sg:orig_category":"Koeriersdiensten",
    "sg:phone":"+31 10 251 8543",
    "sg:postcode":"3081 KS",
    "sg:province":"South Holland",
    "wof:name":"Antillen Koeriers & Shipping",
    "wof:placetype":"venue"
},
  "geometry": {"coordinates":[4.480394,51.892624],"type":"Point"}
}