{
  "type": "Feature",
  "properties": {
    "addr:full":"Tussenmeer 98 Amsterdam Sloten-Osdorp North Holland 1069 DS",
    "addr:housenumber":"98",
    "addr:postcode":"1069 ds",
    "addr:street":"Tussenmeer",
    "iso:country":"NL",
    "sg:address":"Tussenmeer 98",
    "sg:city":"Amsterdam Sloten-Osdorp",
    "sg:orig_category":"Feestartikelen",
    "sg:phone":"+31 20 667 2093",
    "sg:postcode":"1069 DS",
    "sg:province":"North Holland",
    "wof:name":"The Mask Feestartikelen",
    "wof:placetype":"venue"
},
  "geometry": {"coordinates":[4.79369,52.357132],"type":"Point"}
}