{
  "type": "Feature",
  "properties": {
    "addr:full":"Mosselsepad 15 Otterlo Gelderland 6731 SL",
    "addr:housenumber":"15",
    "addr:postcode":"6731 sl",
    "addr:street":"Mosselsepad;Gelderland",
    "iso:country":"NL",
    "sg:address":"Mosselsepad 15",
    "sg:city":"Otterlo",
    "sg:orig_category":"Huishoudapparatuur, Televisies And Radio'S",
    "sg:phone":"+31 318 592 266",
    "sg:postcode":"6731 SL",
    "sg:province":"Gelderland",
    "wof:name":"Jacobsen Satellite Systemen",
    "wof:placetype":"venue"
},
  "geometry": {"coordinates":[5.77068,52.100075],"type":"Point"}
}