{
  "type": "Feature",
  "properties": {
    "addr:full":"Nyverheidsstr 16 Haaksbergen NL.08 7482 GZ",
    "addr:housenumber":"16;nl.08",
    "addr:postcode":"7482 gz",
    "addr:street":"Nyverheidsstr",
    "iso:country":"NL",
    "sg:address":"Nyverheidsstr 16",
    "sg:city":"Haaksbergen",
    "sg:orig_category":"Elektronica - Ontwikkeling En Groothandel",
    "sg:phone":"+31 53 573 3333",
    "sg:postcode":"7482 GZ",
    "sg:province":"NL.08",
    "sg:website":"http://www.eurodis.com",
    "wof:name":"Eurodis Texim Bv",
    "wof:placetype":"venue"
},
  "geometry": {"coordinates":[6.7335391045,52.1615447998],"type":"Point"}
}