{
  "type": "Feature",
  "properties": {
    "addr:full":"Meander 13 Swalmen Limburg 6071 SB",
    "addr:housenumber":"13",
    "addr:postcode":"6071 sb",
    "addr:street":"Meander",
    "iso:country":"NL",
    "sg:address":"Meander 13",
    "sg:city":"Swalmen",
    "sg:orig_category":"Adviesbureaus",
    "sg:phone":"+31 475 600 066",
    "sg:postcode":"6071 SB",
    "sg:province":"Limburg",
    "wof:name":"Oosterbaan",
    "wof:placetype":"venue"
},
  "geometry": {"coordinates":[6.046521,51.23378],"type":"Point"}
}