{
  "type": "Feature",
  "properties": {
    "addr:full":"Zijdelwaardplein 85 Uithoorn Noord-Holland 1422 DL",
    "addr:housenumber":"85",
    "addr:postcode":"1422 dl",
    "addr:street":"Zijdelwaardplein",
    "iso:country":"NL",
    "sg:address":"Zijdelwaardplein 85",
    "sg:city":"Uithoorn",
    "sg:orig_category":"Damesmodezaken",
    "sg:phone":"+31 297 569 205",
    "sg:postcode":"1422 DL",
    "sg:province":"Noord-Holland",
    "wof:name":"Boetiek De Boet Bv",
    "wof:placetype":"venue"
},
  "geometry": {"coordinates":[4.828081,52.246281],"type":"Point"}
}