{
  "type": "Feature",
  "properties": {
    "addr:full":"Westersngl 4 Leeuwarden Friesland 8913 CK",
    "addr:housenumber":"4",
    "addr:postcode":"8913 ck",
    "addr:street":"Westersngl",
    "iso:country":"NL",
    "sg:address":"Westersngl 4",
    "sg:city":"Leeuwarden",
    "sg:orig_category":"Hulpverlening Sociaal",
    "sg:phone":"+31 58 212 7772",
    "sg:postcode":"8913 CK",
    "sg:province":"Friesland",
    "wof:name":"Kindermishandeling, Advies En Meldpunt",
    "wof:placetype":"venue"
},
  "geometry": {"coordinates":[5.79257,53.197319],"type":"Point"}
}