{
  "type": "Feature",
  "properties": {
    "addr:full":"Jan Hobergstraat 27 Castricum North Holland 1901 PK",
    "addr:housenumber":"27",
    "addr:postcode":"1901 pk",
    "addr:street":"Jan Hobergstraat",
    "iso:country":"NL",
    "sg:address":"Jan Hobergstraat 27",
    "sg:city":"Castricum",
    "sg:orig_category":"Fotostudio'S And Fotografen",
    "sg:phone":"+31 251 656 139",
    "sg:postcode":"1901 PK",
    "sg:province":"North Holland",
    "wof:name":"Reportagefotografie Wim Peperkamp",
    "wof:placetype":"venue"
},
  "geometry": {"coordinates":[4.662749,52.544735],"type":"Point"}
}