{
  "type": "Feature",
  "properties": {
    "iso:country":"NL",
    "sg:address":"Vluttersven 5",
    "sg:city":"Eindhoven",
    "sg:orig_category":"Koelkasten - Reparatie En Onderhoud",
    "sg:phone":"+31 40 257 1704",
    "sg:postcode":"5646 HX",
    "sg:province":"Noord-Brabant",
    "wof:name":"Larue",
    "wof:placetype":"venue"
},
  "geometry": {"coordinates":[5.512602,51.419811],"type":"Point"}
}