{
  "type": "Feature",
  "properties": {
    "addr:full":"Vlietskd 7016 Arkel Zuid-Holland 4241 WR",
    "addr:postcode":"7016 arkel;4241 wr",
    "iso:country":"NL",
    "sg:address":"Vlietskd 7016",
    "sg:city":"Arkel",
    "sg:orig_category":"Lpg-Installaties",
    "sg:phone":"+31 183 562 344",
    "sg:postcode":"4241 WR",
    "sg:province":"Zuid-Holland",
    "wof:name":"Arkel",
    "wof:placetype":"venue"
},
  "geometry": {"coordinates":[4.99865,51.864128],"type":"Point"}
}