{
  "type": "Feature",
  "properties": {
    "iso:country":"NL",
    "sg:address":"Sluisdijkstraat 61",
    "sg:city":"Den Helder",
    "sg:classifiers":[
        {
            "category":"Communications",
            "subcategory":"Television Station",
            "type":"Services"
        }
    ],
    "sg:phone":"+31 223 617 525",
    "sg:postcode":"1781 EE",
    "sg:province":"North Holland",
    "sg:tags":[
        "video",
        "audio",
        "verhuur"
    ],
    "wof:name":"Videotheek Vogelwijk",
    "wof:placetype":"venue"
},
  "geometry": {"coordinates":[4.764731,52.955948],"type":"Point"}
}