{
  "type": "Feature",
  "properties": {
    "iso:country":"NL",
    "sg:address":"Innovatielaan 25",
    "sg:city":"Nijehaske",
    "sg:orig_category":"Facilitaire Dienstverlening",
    "sg:phone":"+31 800 3855737",
    "sg:postcode":"8466 SN",
    "sg:province":"Provincie Friesland",
    "wof:name":"Full Service Frysl\u00e2n",
    "wof:placetype":"venue"
},
  "geometry": {"coordinates":[5.890138,52.968662],"type":"Point"}
}