{
  "type": "Feature",
  "properties": {
    "iso:country":"NL",
    "sg:address":"Gemullehoekenweg 19",
    "sg:city":"Oisterwijk",
    "sg:classifiers":[
        {
            "category":"Bakery",
            "type":"Food & Drink"
        }
    ],
    "sg:phone":"+31 13 523 4986",
    "sg:postcode":"5061 MA",
    "sg:province":"Noord-Brabant",
    "sg:tags":[
        "brood",
        "banket"
    ],
    "wof:name":"Fa A Santegoets En Zn",
    "wof:placetype":"venue"
},
  "geometry": {"coordinates":[5.200476,51.580479],"type":"Point"}
}