{
  "type": "Feature",
  "properties": {
    "addr:full":"Estlandsestr 2A Zutphen Gelderland 7202 CP",
    "addr:housenumber":"2a",
    "addr:postcode":"7202 cp",
    "addr:street":"Estlandsestr;Gelderland",
    "iso:country":"NL",
    "sg:address":"Estlandsestr 2A",
    "sg:city":"Zutphen",
    "sg:orig_category":"Meubelen - Fabrieken En Groothandel",
    "sg:phone":"+31 575 543 654",
    "sg:postcode":"7202 CP",
    "sg:province":"Gelderland",
    "wof:name":"Kaya Zitmeubelen Bv",
    "wof:placetype":"venue"
},
  "geometry": {"coordinates":[6.1951861382,52.1576118469],"type":"Point"}
}