{
  "type": "Feature",
  "properties": {
    "addr:full":"Reijerskoop 341 Boskoop South Holland 2771 BN",
    "addr:housenumber":"341",
    "addr:postcode":"2771 bn",
    "addr:street":"Reijerskoop",
    "iso:country":"NL",
    "sg:address":"Reijerskoop 341",
    "sg:city":"Boskoop",
    "sg:orig_category":"Bloemen And Planten",
    "sg:phone":"+31 172 236 023",
    "sg:postcode":"2771 BN",
    "sg:province":"South Holland",
    "wof:name":"W.J. Ravestein & Zoon Bv",
    "wof:placetype":"venue"
},
  "geometry": {"coordinates":[4.685266,52.072655],"type":"Point"}
}