{
  "type": "Feature",
  "properties": {
    "addr:full":"Winhoffln 2 Ootmarsum Overijssel 7631 HX",
    "addr:housenumber":"2",
    "addr:postcode":"7631 hx",
    "addr:street":"Winhoffln",
    "iso:country":"NL",
    "sg:address":"Winhoffln 2",
    "sg:city":"Ootmarsum",
    "sg:classifiers":[
        {
            "category":"Travel",
            "subcategory":"Hotels & Motels",
            "type":"Entertainment"
        }
    ],
    "sg:phone":"+31 541 292 155",
    "sg:postcode":"7631 HX",
    "sg:province":"Overijssel",
    "sg:website":"http://www.wiemsel.nl",
    "wof:name":"Wiemsel Hotel, De",
    "wof:placetype":"venue"
},
  "geometry": {"coordinates":[6.89415,52.406929],"type":"Point"}
}