{
  "type": "Feature",
  "properties": {
    "addr:full":"Levantkade 184 Amsterdam Noord-Holland 1019 BG",
    "addr:housenumber":"184",
    "addr:postcode":"1019",
    "addr:street":"Levantkade",
    "iso:country":"NL",
    "sg:address":"Levantkade 184",
    "sg:city":"Amsterdam",
    "sg:orig_category":"Watersport-, Sport- And Kampeerbenodigdheden Verhuur",
    "sg:phone":"+31 20 419 8119",
    "sg:postcode":"1019 BG",
    "sg:province":"Noord-Holland",
    "wof:name":"Mees Charter",
    "wof:placetype":"venue"
},
  "geometry": {"coordinates":[4.94084692,52.376209259],"type":"Point"}
}