{
  "type": "Feature",
  "properties": {
    "addr:full":"Hogerwerf 16 Roosendaal Noord-Brabant 4704 RV",
    "addr:housenumber":"16",
    "addr:postcode":"4704 rv",
    "addr:street":"Hogerwerf",
    "iso:country":"NL",
    "sg:address":"Hogerwerf 16",
    "sg:city":"Roosendaal",
    "sg:orig_category":"Adviesbureaus Elektrotechniek",
    "sg:phone":"+31 165 558 316",
    "sg:postcode":"4704 RV",
    "sg:province":"Noord-Brabant",
    "wof:name":"Reinard",
    "wof:placetype":"venue"
},
  "geometry": {"coordinates":[4.468143,51.560394],"type":"Point"}
}