{
  "type": "Feature",
  "properties": {
    "addr:full":"St Nicolaasstr 33 Maastricht Limburg 6211 NM",
    "addr:housenumber":"33",
    "addr:postcode":"6211",
    "iso:country":"NL",
    "sg:address":"St Nicolaasstr 33",
    "sg:city":"Maastricht",
    "sg:orig_category":"Loodgieters",
    "sg:phone":"+31 6 27296278",
    "sg:postcode":"6211 NM",
    "sg:province":"Limburg",
    "wof:name":"Bijlevelt, J A M Van",
    "wof:placetype":"venue"
},
  "geometry": {"coordinates":[5.68015,50.848194],"type":"Point"}
}