{
  "type": "Feature",
  "properties": {
    "addr:full":"Korvelsewg 32 Tilburg North Brabant 5025 JH",
    "addr:housenumber":"32",
    "addr:postcode":"5025 jh",
    "addr:street":"Korvelsewg",
    "iso:country":"NL",
    "sg:address":"Korvelsewg 32",
    "sg:city":"Tilburg",
    "sg:orig_category":"Autorijscholen",
    "sg:phone":"+31 13 535 6935",
    "sg:postcode":"5025 JH",
    "sg:province":"North Brabant",
    "sg:website":"http://www.verkeersschooltilburg.nl",
    "wof:name":"Verkeersschool Tilburg Bv",
    "wof:placetype":"venue"
},
  "geometry": {"coordinates":[5.078137,51.552551],"type":"Point"}
}