{
  "type": "Feature",
  "properties": {
    "addr:full":"Kruisstr 12 Haarlem Noord-Holland 2011 PX",
    "addr:housenumber":"12",
    "addr:postcode":"2011 px",
    "addr:street":"Kruisstr",
    "iso:country":"NL",
    "sg:address":"Kruisstr 12",
    "sg:city":"Haarlem",
    "sg:orig_category":"Antiquiteiten",
    "sg:phone":"+31 23 531 5599",
    "sg:postcode":"2011 PX",
    "sg:province":"Noord-Holland",
    "wof:name":"Rovers",
    "wof:placetype":"venue"
},
  "geometry": {"coordinates":[4.635634,52.384354],"type":"Point"}
}