{
  "type": "Feature",
  "properties": {
    "iso:country":"NL",
    "sg:address":"Nw Ebbingestr 14",
    "sg:city":"Groningen",
    "sg:orig_category":"Opticiens",
    "sg:phone":"+31 50 313 4663",
    "sg:postcode":"9712 NK",
    "sg:province":"Groningen",
    "sg:website":"http://www.beterzicht.nl",
    "wof:name":"Sportel Optiek",
    "wof:placetype":"venue"
},
  "geometry": {"coordinates":[6.5644378662,53.2225227356],"type":"Point"}
}