{
  "type": "Feature",
  "properties": {
    "addr:full":"Boekhorsterweg 16 Noordwijkerhout Zuid-Holland 2211 AL",
    "addr:housenumber":"16",
    "addr:postcode":"2211 al",
    "addr:street":"Boekhorsterweg",
    "iso:country":"NL",
    "sg:address":"Boekhorsterweg 16",
    "sg:city":"Noordwijkerhout",
    "sg:orig_category":"Bloemen- And Plantenteelt",
    "sg:phone":"+31 252 373 311",
    "sg:postcode":"2211 AL",
    "sg:province":"Zuid-Holland",
    "wof:name":"Bloembollenkwekerij P.J.W. Wijnands",
    "wof:placetype":"venue"
},
  "geometry": {"coordinates":[4.501739,52.277378],"type":"Point"}
}