{
  "type": "Feature",
  "properties": {
    "addr:full":"Dopplerstr 6 Heerhugowaard Noord-Holland 1704 SR",
    "addr:housenumber":"6",
    "addr:postcode":"1704 sr",
    "addr:street":"Dopplerstr",
    "iso:country":"NL",
    "sg:address":"Dopplerstr 6",
    "sg:city":"Heerhugowaard",
    "sg:classifiers":[
        {
            "category":"Retail",
            "subcategory":"Auto Repair",
            "type":"Services"
        }
    ],
    "sg:phone":"+31 72 574 0859",
    "sg:postcode":"1704 SR",
    "sg:province":"Noord-Holland",
    "sg:tags":[
        "garage"
    ],
    "sg:website":"http://www.automolenaar.com",
    "wof:name":"Molenaar Auto",
    "wof:placetype":"venue"
},
  "geometry": {"coordinates":[4.836146,52.689049],"type":"Point"}
}