{
  "type": "Feature",
  "properties": {
    "addr:full":"Aresstr 13-05 Tilburg North Brabant 5048 CD",
    "addr:housenumber":"13-05",
    "addr:postcode":"5048 cd",
    "iso:country":"NL",
    "sg:address":"Aresstr 13-05",
    "sg:city":"Tilburg",
    "sg:orig_category":"Lichtreclame",
    "sg:phone":"+31 13 571 5355",
    "sg:postcode":"5048 CD",
    "sg:province":"North Brabant",
    "sg:website":"http://www.boomlichtreklame.am-s.nl",
    "wof:name":"Boom Lichtreclame, Van Der",
    "wof:placetype":"venue"
},
  "geometry": {"coordinates":[5.027452,51.594883],"type":"Point"}
}