{
  "type": "Feature",
  "properties": {
    "addr:full":"Henri Hermansstraat 7 Nuth Limburg 6361 BS",
    "addr:housenumber":"7",
    "addr:postcode":"6361 bs",
    "addr:street":"Henri Hermansstraat",
    "iso:country":"NL",
    "sg:address":"Henri Hermansstraat 7",
    "sg:city":"Nuth",
    "sg:orig_category":"Boekhouders",
    "sg:phone":"+31 45 524 4722",
    "sg:postcode":"6361 BS",
    "sg:province":"Limburg",
    "wof:name":"Administratiekantoor Van Birgelen & Kleuters",
    "wof:placetype":"venue"
},
  "geometry": {"coordinates":[5.887713,50.919266],"type":"Point"}
}