{
  "type": "Feature",
  "properties": {
    "addr:full":"Diemerhof 36 Diemen North Holland 1112 XN",
    "addr:housenumber":"36",
    "addr:postcode":"1112 xn",
    "addr:street":"Diemerhof",
    "iso:country":"NL",
    "sg:address":"Diemerhof 36",
    "sg:city":"Diemen",
    "sg:orig_category":"Verzekeringen",
    "sg:phone":"+31 20 660 7272",
    "sg:postcode":"1112 XN",
    "sg:province":"North Holland",
    "wof:name":"Vvs Verzekeringen Bv",
    "wof:placetype":"venue"
},
  "geometry": {"coordinates":[4.953216,52.326187],"type":"Point"}
}