{
  "type": "Feature",
  "properties": {
    "iso:country":"NL",
    "sg:address":"Hoedekenskerkestraat 37",
    "sg:city":"Arnhem",
    "sg:orig_category":"Onderhoud And Reparatie Kantoorapparatuur",
    "sg:phone":"+31 26 383 0878",
    "sg:postcode":"6845 AN",
    "sg:province":"Gelderland",
    "wof:name":"Redsoft",
    "wof:placetype":"venue"
},
  "geometry": {"coordinates":[5.864951,51.947655],"type":"Point"}
}