{
  "type": "Feature",
  "properties": {
    "addr:full":"Middenweg 161 Heerhugowaard Noord-Holland 1702 HB",
    "addr:housenumber":"161",
    "addr:postcode":"1702 hb",
    "addr:street":"Middenweg",
    "iso:country":"NL",
    "sg:address":"Middenweg 161",
    "sg:city":"Heerhugowaard",
    "sg:orig_category":"Schilderwerk",
    "sg:phone":"+31 72 571 1218",
    "sg:postcode":"1702 HB",
    "sg:province":"Noord-Holland",
    "wof:name":"Schildersbedrijf G.B. Dirkmaat",
    "wof:placetype":"venue"
},
  "geometry": {"coordinates":[4.840607,52.667229],"type":"Point"}
}