{
  "type": "Feature",
  "properties": {
    "addr:full":"Grootzand 77 Sneek Friesland 8601 AV",
    "addr:housenumber":"77",
    "addr:postcode":"8601 av",
    "addr:street":"Grootzand",
    "iso:country":"NL",
    "sg:address":"Grootzand 77",
    "sg:city":"Sneek",
    "sg:orig_category":"Kinderkleding",
    "sg:phone":"+31 515 439 800",
    "sg:postcode":"8601 AV",
    "sg:province":"Friesland",
    "wof:name":"Grachtje, 'T",
    "wof:placetype":"venue"
},
  "geometry": {"coordinates":[5.659918,53.03009],"type":"Point"}
}