{
  "type": "Feature",
  "properties": {
    "addr:full":"Dykwg 66 Honselersdyk Zuid-Holland 2675 AE",
    "addr:housenumber":"66",
    "addr:postcode":"2675 ae",
    "addr:street":"Dykwg",
    "iso:country":"NL",
    "sg:address":"Dykwg 66",
    "sg:city":"Honselersdyk",
    "sg:orig_category":"Bloemen En Planten - Groothandel",
    "sg:phone":"+31 174 626 083",
    "sg:postcode":"2675 AE",
    "sg:province":"Zuid-Holland",
    "wof:name":"Tromp & Zn Bv",
    "wof:placetype":"venue"
},
  "geometry": {"coordinates":[4.22951,52.008755],"type":"Point"}
}