{
  "type": "Feature",
  "properties": {
    "addr:full":"Ambachtwg 2 Moordrecht South Holland 2841 LZ",
    "addr:housenumber":"2",
    "addr:postcode":"2841 lz",
    "addr:street":"Ambachtwg",
    "iso:country":"NL",
    "sg:address":"Ambachtwg 2",
    "sg:city":"Moordrecht",
    "sg:orig_category":"Fotopersbureaus",
    "sg:phone":"+31 182 356 050",
    "sg:postcode":"2841 LZ",
    "sg:province":"South Holland",
    "wof:name":"Target Press",
    "wof:placetype":"venue"
},
  "geometry": {"coordinates":[4.67203,51.986553],"type":"Point"}
}