{
  "type": "Feature",
  "properties": {
    "iso:country":"NL",
    "sg:address":"Molenvlietwg 18B",
    "sg:city":"Aalsmeer",
    "sg:orig_category":"Motoren Verbrandingsmotoren",
    "sg:phone":"+31 297 380 000",
    "sg:postcode":"1432 GW",
    "sg:province":"Noord-Holland",
    "wof:name":"Geveke Bv",
    "wof:placetype":"venue"
},
  "geometry": {"coordinates":[4.778167,52.266171],"type":"Point"}
}