{
  "type": "Feature",
  "properties": {
    "addr:full":"Duizendroed 25 Enkhuizen North Holland 1602 KT",
    "addr:housenumber":"25",
    "addr:postcode":"1602 kt",
    "addr:street":"Duizendroed",
    "iso:country":"NL",
    "sg:address":"Duizendroed 25",
    "sg:city":"Enkhuizen",
    "sg:orig_category":"Glazenwasserijen",
    "sg:phone":"+31 228 314 841",
    "sg:postcode":"1602 KT",
    "sg:province":"North Holland",
    "wof:name":"Verhoeven, R",
    "wof:placetype":"venue"
},
  "geometry": {"coordinates":[5.271097,52.715584],"type":"Point"}
}