{
  "type": "Feature",
  "properties": {
    "addr:full":"Hoofdstr 100 Liessel Noord-Brabant 5757 AR",
    "addr:housenumber":"100",
    "addr:postcode":"5757",
    "addr:street":"Liessel",
    "iso:country":"NL",
    "sg:address":"Hoofdstr 100",
    "sg:city":"Liessel",
    "sg:orig_category":"Schilders",
    "sg:phone":"+31 493 342 526",
    "sg:postcode":"5757 AR",
    "sg:province":"Noord-Brabant",
    "wof:name":"Verheijen Vof, F",
    "wof:placetype":"venue"
},
  "geometry": {"coordinates":[5.819504,51.416805],"type":"Point"}
}