{
  "type": "Feature",
  "properties": {
    "iso:country":"NL",
    "sg:address":"Oosterweg 144",
    "sg:city":"Wijchen",
    "sg:orig_category":"Pluimveehouderijen",
    "sg:phone":"+31 24 641 3530",
    "sg:postcode":"6603 AB",
    "sg:province":"Gelderland",
    "wof:name":"B. Bruins",
    "wof:placetype":"venue"
},
  "geometry": {"coordinates":[5.7401,51.800346],"type":"Point"}
}