{
  "type": "Feature",
  "properties": {
    "addr:full":"Rusthofln 48B Rotterdam South Holland 3034 XM",
    "addr:housenumber":"48b",
    "addr:postcode":"3034 xm",
    "addr:street":"Rusthofln",
    "iso:country":"NL",
    "sg:address":"Rusthofln 48B",
    "sg:city":"Rotterdam",
    "sg:orig_category":"Podotherapeuten",
    "sg:phone":"+31 10 404 9707",
    "sg:postcode":"3034 XM",
    "sg:province":"South Holland",
    "wof:name":"Podo Mass",
    "wof:placetype":"venue"
},
  "geometry": {"coordinates":[4.495869,51.935642],"type":"Point"}
}