{
  "type": "Feature",
  "properties": {
    "addr:full":"Bloemendaalseweg 23 Bloemendaal Noord-Holland 2061 CA",
    "addr:housenumber":"23",
    "addr:postcode":"2061 ca",
    "addr:street":"Bloemendaalseweg",
    "iso:country":"NL",
    "sg:address":"Bloemendaalseweg 23",
    "sg:city":"Bloemendaal",
    "sg:orig_category":"Wasserettes And Stomerijen",
    "sg:phone":"+31 23 526 0938",
    "sg:postcode":"2061 CA",
    "sg:province":"Noord-Holland",
    "wof:name":"Beemsterboer",
    "wof:placetype":"venue"
},
  "geometry": {"coordinates":[4.6217451096,52.4055404663],"type":"Point"}
}