{
  "type": "Feature",
  "properties": {
    "addr:full":"Erfgenamenwg 22 Zwolle Overijssel 8026 PS",
    "addr:housenumber":"22",
    "addr:postcode":"8026 ps",
    "addr:street":"Erfgenamenwg",
    "iso:country":"NL",
    "sg:address":"Erfgenamenwg 22",
    "sg:city":"Zwolle",
    "sg:orig_category":"Sanitaire Artikelen - Fabrieken En Groothandel",
    "sg:phone":"+31 529 401 600",
    "sg:postcode":"8026 PS",
    "sg:province":"Overijssel",
    "wof:name":"Borst Handelsonderneming",
    "wof:placetype":"venue"
},
  "geometry": {"coordinates":[6.171311,52.491089],"type":"Point"}
}