{
  "type": "Feature",
  "properties": {
    "addr:full":"Balilaan 13 Apeldoorn Gelderland 7314 BE",
    "addr:housenumber":"13",
    "addr:postcode":"7314",
    "addr:street":"Balilaan;Gelderland",
    "iso:country":"NL",
    "sg:address":"Balilaan 13",
    "sg:city":"Apeldoorn",
    "sg:orig_category":"Binnenhuisarchitecten",
    "sg:phone":"+31 55 360 4010",
    "sg:postcode":"7314 BE",
    "sg:province":"Gelderland",
    "wof:name":"Interieurarchitectuur Raymond Gerritsen",
    "wof:placetype":"venue"
},
  "geometry": {"coordinates":[5.947219,52.222652],"type":"Point"}
}