{
  "type": "Feature",
  "properties": {
    "iso:country":"NL",
    "sg:address":"Nieuweweg 13E",
    "sg:city":"Groningen",
    "sg:orig_category":"Binnenhuisarchitecten",
    "sg:phone":"+31 50 312 4813",
    "sg:postcode":"9711 TA",
    "sg:province":"Groningen",
    "wof:name":"C.S. Liem",
    "wof:placetype":"venue"
},
  "geometry": {"coordinates":[6.57424,53.218224],"type":"Point"}
}