{
  "type": "Feature",
  "properties": {
    "addr:full":"Mahlersngl 18 Nieuwegein Utrecht 3438 XA",
    "addr:housenumber":"18",
    "addr:postcode":"3438 xa",
    "addr:street":"Mahlersngl",
    "iso:country":"NL",
    "sg:address":"Mahlersngl 18",
    "sg:city":"Nieuwegein",
    "sg:orig_category":"Koeltechniek",
    "sg:phone":"+31 30 603 4342",
    "sg:postcode":"3438 XA",
    "sg:province":"Utrecht",
    "wof:name":"Beerends",
    "wof:placetype":"venue"
},
  "geometry": {"coordinates":[5.082197,52.027325],"type":"Point"}
}