{
  "type": "Feature",
  "properties": {
    "addr:full":"Zonnebloemln 213 Drunen Noord-Brabant 5151 TA",
    "addr:housenumber":"213",
    "addr:postcode":"5151 ta",
    "iso:country":"NL",
    "sg:address":"Zonnebloemln 213",
    "sg:city":"Drunen",
    "sg:orig_category":"Schoenen - Groothandel",
    "sg:phone":"+31 416 372 953",
    "sg:postcode":"5151 TA",
    "sg:province":"Noord-Brabant",
    "wof:name":"Janssen Bv, Jac",
    "wof:placetype":"venue"
},
  "geometry": {"coordinates":[5.139423,51.693874],"type":"Point"}
}