{
  "type": "Feature",
  "properties": {
    "addr:full":"Raadhuisstraat 51 Amsterdam Noord-Holland 1016 DD",
    "addr:housenumber":"51",
    "addr:postcode":"1016 dd",
    "addr:street":"Raadhuisstraat",
    "iso:country":"NL",
    "sg:address":"Raadhuisstraat 51",
    "sg:city":"Amsterdam",
    "sg:classifiers":[
        {
            "category":"Travel",
            "subcategory":"Hotels & Motels",
            "type":"Entertainment"
        }
    ],
    "sg:phone":"+31 20 620 1550",
    "sg:postcode":"1016 DD",
    "sg:province":"Noord-Holland",
    "wof:name":"Nadia Hotel",
    "wof:placetype":"venue"
},
  "geometry": {"coordinates":[4.885551,52.373753],"type":"Point"}
}