{
  "type": "Feature",
  "properties": {
    "addr:full":"Zegwaardstraat 5 Rotterdam Zuid-Holland 3035 TM",
    "addr:housenumber":"5",
    "addr:postcode":"3035 tm",
    "addr:street":"Zegwaardstraat",
    "iso:country":"NL",
    "sg:address":"Zegwaardstraat 5",
    "sg:city":"Rotterdam",
    "sg:orig_category":"Boekhouders",
    "sg:phone":"+31 10 466 4881",
    "sg:postcode":"3035 TM",
    "sg:province":"Zuid-Holland",
    "wof:name":"Jrc Adviespraktijk",
    "wof:placetype":"venue"
},
  "geometry": {"coordinates":[4.476349,51.93362],"type":"Point"}
}