{
  "type": "Feature",
  "properties": {
    "addr:full":"Steenwijkerweg 20 Marknesse NL. 8316 RK",
    "addr:housenumber":"20",
    "addr:postcode":"8316 rk",
    "addr:street":"Steenwijkerweg;Nl.",
    "iso:country":"NL",
    "sg:address":"Steenwijkerweg 20",
    "sg:city":"Marknesse",
    "sg:orig_category":"Autokeuringen",
    "sg:phone":"+31 527 291 939",
    "sg:postcode":"8316 RK",
    "sg:province":"NL.",
    "wof:name":"M. Bonthuis",
    "wof:placetype":"venue"
},
  "geometry": {"coordinates":[5.898658,52.716709],"type":"Point"}
}