{
  "type": "Feature",
  "properties": {
    "addr:full":"Einsteinstraat 11 Heerhugowaard Noord-Holland 1704 RT",
    "addr:housenumber":"11",
    "addr:postcode":"1704 rt",
    "addr:street":"Einsteinstraat",
    "iso:country":"NL",
    "sg:address":"Einsteinstraat 11",
    "sg:city":"Heerhugowaard",
    "sg:orig_category":"Metaalbekleding And -Behandeling",
    "sg:phone":"+31 72 571 8693",
    "sg:postcode":"1704 RT",
    "sg:province":"Noord-Holland",
    "wof:name":"Polywaard Gritstraal Bv",
    "wof:placetype":"venue"
},
  "geometry": {"coordinates":[4.835052,52.68372],"type":"Point"}
}