{
  "type": "Feature",
  "properties": {
    "iso:country":"NL",
    "sg:address":"Burg De Bruinelaan 93",
    "sg:city":"Zwijndrecht",
    "sg:orig_category":"Advocaten And Juridische Adviseurs",
    "sg:phone":"+31 78 612 6520",
    "sg:postcode":"3331 AC",
    "sg:province":"Zuid-Holland",
    "wof:name":"Advocatenkantoor Ester",
    "wof:placetype":"venue"
},
  "geometry": {"coordinates":[4.647582,51.816341],"type":"Point"}
}