{
  "type": "Feature",
  "properties": {
    "addr:full":"Roggemolenstraat 1 Joure Friesland 8501 CC",
    "addr:housenumber":"1",
    "addr:postcode":"8501 cc",
    "addr:street":"Roggemolenstraat",
    "iso:country":"NL",
    "sg:address":"Roggemolenstraat 1",
    "sg:city":"Joure",
    "sg:classifiers":[
        {
            "category":"Fast Food",
            "type":"Food & Drink"
        }
    ],
    "sg:phone":"+31 513 412 414",
    "sg:postcode":"8501 CC",
    "sg:province":"Friesland",
    "sg:tags":[
        "afhaal",
        "restaurant"
    ],
    "wof:name":"Cafe Minnesma Meine'S Pub",
    "wof:placetype":"venue"
},
  "geometry": {"coordinates":[5.799048,52.965847],"type":"Point"}
}