{
  "type": "Feature",
  "properties": {
    "iso:country":"NL",
    "sg:address":"Rijksstraatweg 232",
    "sg:city":"Loenersloot",
    "sg:orig_category":"Verhuur Gereedschapsmachines And Gereedschappen",
    "sg:phone":"+31 294 293 148",
    "sg:postcode":"3634 AN",
    "sg:province":"Utrecht",
    "wof:name":"Event Rent",
    "wof:placetype":"venue"
},
  "geometry": {"coordinates":[4.998338,52.230087],"type":"Point"}
}