{
  "type": "Feature",
  "properties": {
    "addr:full":"De Krommert 72 Oosthuizen Noord-Holland 1474 PR",
    "addr:housenumber":"72",
    "addr:postcode":"1474 pr",
    "addr:street":"De Krommert",
    "iso:country":"NL",
    "sg:address":"De Krommert 72",
    "sg:city":"Oosthuizen",
    "sg:orig_category":"Verzekeringen",
    "sg:phone":"+31 299 402 142",
    "sg:postcode":"1474 PR",
    "sg:province":"Noord-Holland",
    "wof:name":"Harry Koning",
    "wof:placetype":"venue"
},
  "geometry": {"coordinates":[4.998072,52.569843],"type":"Point"}
}