{
  "type": "Feature",
  "properties": {
    "addr:full":"De Rotsduif 24 Almelo Overijssel 7609 VK",
    "addr:housenumber":"24",
    "addr:postcode":"7609 vk",
    "addr:street":"De Rotsduif",
    "iso:country":"NL",
    "sg:address":"De Rotsduif 24",
    "sg:city":"Almelo",
    "sg:classifiers":[
        {
            "category":"Education",
            "subcategory":"Preschool",
            "type":"Public Place"
        }
    ],
    "sg:phone":"+31 546 538 123",
    "sg:postcode":"7609 VK",
    "sg:province":"Overijssel",
    "sg:tags":[
        "kleuteronderwijs",
        "basis-"
    ],
    "wof:name":"Openbare Basisschool De Bonkelaar",
    "wof:placetype":"venue"
},
  "geometry": {"coordinates":[6.645499,52.331604],"type":"Point"}
}