{
  "type": "Feature",
  "properties": {
    "addr:full":"Oude Haagwg 495 S Gravenhage Zuid-Holland 2552 GG",
    "addr:housenumber":"495;gravenhage",
    "addr:postcode":"2552 gg",
    "addr:street":"Oude Haagwg;S",
    "iso:country":"NL",
    "sg:address":"Oude Haagwg 495",
    "sg:city":"S Gravenhage",
    "sg:orig_category":"Wasserijen",
    "sg:phone":"+31 70 368 6464",
    "sg:postcode":"2552 GG",
    "sg:province":"Zuid-Holland",
    "wof:name":"Giezeman",
    "wof:placetype":"venue"
},
  "geometry": {"coordinates":[4.2495799065,52.0536308289],"type":"Point"}
}