{
  "type": "Feature",
  "properties": {
    "iso:country":"NL",
    "sg:address":"Spoorln 72",
    "sg:city":"Hollandsche Rading",
    "sg:orig_category":"Adviesbureaus",
    "sg:phone":"+31 35 577 1977",
    "sg:postcode":"3739 KG",
    "sg:province":"Utrecht",
    "wof:name":"Mdr Prod Bv",
    "wof:placetype":"venue"
},
  "geometry": {"coordinates":[5.175085,52.174858],"type":"Point"}
}