{
  "type": "Feature",
  "properties": {
    "addr:full":"Burg Roosstr 28 Lekkerkerk Zuid-Holland 2941 AC",
    "addr:housenumber":"28",
    "addr:postcode":"2941 ac",
    "addr:street":"Burg",
    "iso:country":"NL",
    "sg:address":"Burg Roosstr 28",
    "sg:city":"Lekkerkerk",
    "sg:classifiers":[
        {
            "category":"Food & Beverages",
            "subcategory":"Fruits & Vegetables",
            "type":"Retail Goods"
        }
    ],
    "sg:phone":"+31 180 661 532",
    "sg:postcode":"2941 AC",
    "sg:province":"Zuid-Holland",
    "sg:tags":[
        "en",
        "groenten"
    ],
    "wof:name":"Verburg, A J A",
    "wof:placetype":"venue"
},
  "geometry": {"coordinates":[4.68424,51.896034],"type":"Point"}
}