{
  "type": "Feature",
  "properties": {
    "addr:full":"Nw Ebbingestr 80 Groningen Groningen 9712 NN",
    "addr:housenumber":"80",
    "addr:postcode":"9712 nn",
    "iso:country":"NL",
    "sg:address":"Nw Ebbingestr 80",
    "sg:city":"Groningen",
    "sg:orig_category":"Bedden En Matrassen",
    "sg:phone":"+31 50 318 3083",
    "sg:postcode":"9712 NN",
    "sg:province":"Groningen",
    "wof:name":"Matrassensuper",
    "wof:placetype":"venue"
},
  "geometry": {"coordinates":[6.562058,53.224758],"type":"Point"}
}