{
  "type": "Feature",
  "properties": {
    "addr:full":"Nassaustr 132 Kerkrade Limburg 6463 AW",
    "addr:housenumber":"132",
    "addr:postcode":"6463 aw",
    "iso:country":"NL",
    "sg:address":"Nassaustr 132",
    "sg:city":"Kerkrade",
    "sg:orig_category":"Adviesbureaus",
    "sg:phone":"+31 45 542 7172",
    "sg:postcode":"6463 AW",
    "sg:province":"Limburg",
    "wof:name":"Eca",
    "wof:placetype":"venue"
},
  "geometry": {"coordinates":[6.064367,50.875713],"type":"Point"}
}