{
  "type": "Feature",
  "properties": {
    "addr:full":"Vlamingstraat 89 Delft Zuid-Holland 2611 KV",
    "addr:housenumber":"89",
    "addr:postcode":"2611 kv",
    "addr:street":"Vlamingstraat",
    "iso:country":"NL",
    "sg:address":"Vlamingstraat 89",
    "sg:city":"Delft",
    "sg:orig_category":"Schilderwerk",
    "sg:phone":"+31 15 214 3228",
    "sg:postcode":"2611 KV",
    "sg:province":"Zuid-Holland",
    "wof:name":"Foet",
    "wof:placetype":"venue"
},
  "geometry": {"coordinates":[4.363158,52.013744],"type":"Point"}
}