{
  "type": "Feature",
  "properties": {
    "addr:full":"Montfort 24 Almelo Overijssel 7608 NW",
    "addr:housenumber":"24",
    "addr:postcode":"7608 nw",
    "addr:street":"Montfort",
    "iso:country":"NL",
    "sg:address":"Montfort 24",
    "sg:city":"Almelo",
    "sg:classifiers":[
        {
            "category":"Professional",
            "subcategory":"Accounting & Tax Preparation",
            "type":"Services"
        }
    ],
    "sg:phone":"+31 546 865 707",
    "sg:postcode":"7608 NW",
    "sg:province":"Overijssel",
    "sg:tags":[
        "accountant"
    ],
    "wof:name":"Administratiekantoor F.C. Stom",
    "wof:placetype":"venue"
},
  "geometry": {"coordinates":[6.681296,52.374016],"type":"Point"}
}