{
  "type": "Feature",
  "properties": {
    "addr:full":"Cannenburgerwg 14 S Graveland Noord-Holland 1243 JE",
    "addr:housenumber":"14",
    "addr:postcode":"1243 je",
    "addr:street":"Cannenburgerwg;S Graveland",
    "iso:country":"NL",
    "sg:address":"Cannenburgerwg 14",
    "sg:city":"S Graveland",
    "sg:orig_category":"Meubelen",
    "sg:phone":"+31 35 656 4002",
    "sg:postcode":"1243 JE",
    "sg:province":"Noord-Holland",
    "sg:website":"http://www.dehoeveantiek.nl",
    "wof:name":"Hoeve Bv, De",
    "wof:placetype":"venue"
},
  "geometry": {"coordinates":[5.120227,52.256638],"type":"Point"}
}