{
  "type": "Feature",
  "properties": {
    "iso:country":"NL",
    "sg:address":"Bergse L Rottekd 140",
    "sg:city":"Rotterdam",
    "sg:orig_category":"Keukens",
    "sg:phone":"+31 10 456 0708",
    "sg:postcode":"3056 LD",
    "sg:province":"Zuid-Holland",
    "wof:name":"Ls",
    "wof:placetype":"venue"
},
  "geometry": {"coordinates":[4.499597,51.947777],"type":"Point"}
}