{
  "type": "Feature",
  "properties": {
    "iso:country":"NL",
    "sg:address":"Noordmolenstraat 26-28",
    "sg:city":"Schiedam",
    "sg:orig_category":"Loodgieterswerk, Verwarming And Sanitaire Installaties",
    "sg:phone":"+31 10 473 8036",
    "sg:postcode":"3111 PD",
    "sg:province":"Zuid-Holland",
    "wof:name":"Van Arkel Installatiebedrijf",
    "wof:placetype":"venue"
},
  "geometry": {"coordinates":[4.396056,51.919655],"type":"Point"}
}