{
  "type": "Feature",
  "properties": {
    "addr:full":"Waterschans 16 Veenendaal Utrecht 3905 XR",
    "addr:housenumber":"16",
    "addr:postcode":"3905 xr",
    "addr:street":"Waterschans",
    "iso:country":"NL",
    "sg:address":"Waterschans 16",
    "sg:city":"Veenendaal",
    "sg:classifiers":[
        {
            "category":"Fast Food",
            "type":"Food & Drink"
        }
    ],
    "sg:phone":"+31 318 515 819",
    "sg:postcode":"3905 XR",
    "sg:province":"Utrecht",
    "sg:tags":[
        "afhaal",
        "restaurant"
    ],
    "wof:name":"E J Suve",
    "wof:placetype":"venue"
},
  "geometry": {"coordinates":[5.541835,52.037178],"type":"Point"}
}