{
  "type": "Feature",
  "properties": {
    "addr:full":"Van De Spiegelstraat 23 'S Gravenhage Zuid-Holland 2518 ES",
    "addr:housenumber":"23",
    "addr:postcode":"2518 es",
    "addr:street":"Van De Spiegelstraat;' S",
    "iso:country":"NL",
    "sg:address":"Van De Spiegelstraat 23",
    "sg:city":"'S Gravenhage",
    "sg:classifiers":[
        {
            "category":"Education",
            "subcategory":"Preschool",
            "type":"Public Place"
        }
    ],
    "sg:phone":"+31 70 345 7787",
    "sg:postcode":"2518 ES",
    "sg:province":"Zuid-Holland",
    "sg:tags":[
        "kleuteronderwijs",
        "basis-"
    ],
    "wof:name":"Da Costaschool Locatie Groen Van Prinstererschool",
    "wof:placetype":"venue"
},
  "geometry": {"coordinates":[4.296456,52.084808],"type":"Point"}
}