{
  "type": "Feature",
  "properties": {
    "addr:full":"Purperreigerln 33 Zwartsluis Overijssel 8064 DA",
    "addr:housenumber":"33",
    "addr:postcode":"8064 da",
    "addr:street":"Purperreigerln",
    "iso:country":"NL",
    "sg:address":"Purperreigerln 33",
    "sg:city":"Zwartsluis",
    "sg:orig_category":"Schippers",
    "sg:phone":"+31 6 53920250",
    "sg:postcode":"8064 DA",
    "sg:province":"Overijssel",
    "wof:name":"Delta",
    "wof:placetype":"venue"
},
  "geometry": {"coordinates":[6.073185,52.6436],"type":"Point"}
}