{
  "type": "Feature",
  "properties": {
    "addr:full":"Pres Rooseveltln 768 Vlissingen Zeeland 4382 NB",
    "addr:housenumber":"768",
    "addr:postcode":"4382 nb",
    "iso:country":"NL",
    "sg:address":"Pres Rooseveltln 768",
    "sg:city":"Vlissingen",
    "sg:classifiers":[
        {
            "category":"Retail",
            "subcategory":"Auto Repair",
            "type":"Services"
        }
    ],
    "sg:phone":"+31 118 417 610",
    "sg:postcode":"4382 NB",
    "sg:province":"Zeeland",
    "sg:tags":[
        "garage"
    ],
    "wof:name":"Fraassen Bv, Van",
    "wof:placetype":"venue"
},
  "geometry": {"coordinates":[3.583824,51.454372],"type":"Point"}
}