{
  "type": "Feature",
  "properties": {
    "addr:full":"Tilburgseweg 49 Breda Noord-Brabant 4817 BA",
    "addr:housenumber":"49",
    "addr:postcode":"4817 ba",
    "addr:street":"Tilburgseweg",
    "iso:country":"NL",
    "sg:address":"Tilburgseweg 49",
    "sg:city":"Breda",
    "sg:orig_category":"Meubelreparatie And -Restauratie",
    "sg:phone":"+31 76 587 7239",
    "sg:postcode":"4817 BA",
    "sg:province":"Noord-Brabant",
    "wof:name":"A.C. Gelens",
    "wof:placetype":"venue"
},
  "geometry": {"coordinates":[4.810679,51.595009],"type":"Point"}
}