{
  "type": "Feature",
  "properties": {
    "iso:country":"NL",
    "sg:address":"Birdieln 140",
    "sg:city":"Lelystad",
    "sg:orig_category":"Waterbehandeling En Waterzuiverings- Systemen",
    "sg:phone":"+31 320 264 277",
    "sg:postcode":"8241 AT",
    "sg:province":"North Holland",
    "wof:name":"Aqua Vital",
    "wof:placetype":"venue"
},
  "geometry": {"coordinates":[5.4677200317,52.5694618225],"type":"Point"}
}