{
  "type": "Feature",
  "properties": {
    "addr:full":"Klaaskamp 3 Lemmer Friesland 8531 XE",
    "addr:housenumber":"3",
    "addr:postcode":"8531 xe",
    "addr:street":"Klaaskamp",
    "iso:country":"NL",
    "sg:address":"Klaaskamp 3",
    "sg:city":"Lemmer",
    "sg:orig_category":"Pleziervaartuigen And Reparatie",
    "sg:phone":"+31 514 569 050",
    "sg:postcode":"8531 XE",
    "sg:province":"Friesland",
    "wof:name":"Jachtwerf Steinkamp",
    "wof:placetype":"venue"
},
  "geometry": {"coordinates":[5.671416,52.853081],"type":"Point"}
}