{
  "type": "Feature",
  "properties": {
    "addr:full":"Wildeman 14 Eindhoven North Brabant 5629 KH",
    "addr:housenumber":"14",
    "addr:postcode":"5629 kh",
    "addr:street":"Wildeman",
    "iso:country":"NL",
    "sg:address":"Wildeman 14",
    "sg:city":"Eindhoven",
    "sg:orig_category":"Fotoreportages",
    "sg:phone":"+31 40 207 6580",
    "sg:postcode":"5629 KH",
    "sg:province":"North Brabant",
    "sg:website":"http://www.precept.nl",
    "wof:name":"Precept",
    "wof:placetype":"venue"
},
  "geometry": {"coordinates":[5.484827,51.487606],"type":"Point"}
}