{
  "type": "Feature",
  "properties": {
    "iso:country":"NL",
    "sg:address":"Holterswg 81",
    "sg:city":"Hengelo Ov",
    "sg:orig_category":"Sanitaire Artikelen - Fabrieken En Groothandel",
    "sg:phone":"+31 74 250 5432",
    "sg:postcode":"7556 BS",
    "sg:province":"Overijssel",
    "sg:website":"http://www.lammering.nl",
    "wof:name":"Arnold Lammering Bv",
    "wof:placetype":"venue"
},
  "geometry": {"coordinates":[6.774231,52.283199],"type":"Point"}
}