{
  "type": "Feature",
  "properties": {
    "addr:full":"Klompwg 60 Nigtevecht North Holland 1393 PM",
    "addr:housenumber":"60",
    "addr:postcode":"1393 pm",
    "addr:street":"Klompwg",
    "iso:country":"NL",
    "sg:address":"Klompwg 60",
    "sg:city":"Nigtevecht",
    "sg:orig_category":"Adviesbureaus Bouwkunde",
    "sg:phone":"+31 294 255 703",
    "sg:postcode":"1393 PM",
    "sg:province":"North Holland",
    "wof:name":"Neervoort Bv",
    "wof:placetype":"venue"
},
  "geometry": {"coordinates":[5.04954,52.281288],"type":"Point"}
}