{
  "type": "Feature",
  "properties": {
    "addr:full":"Rapenburg 51Hs Amsterdam Noord-Holland 1011 TV",
    "addr:housenumber":"51hs",
    "addr:postcode":"1011 tv",
    "addr:street":"Rapenburg",
    "iso:country":"NL",
    "sg:address":"Rapenburg 51Hs",
    "sg:city":"Amsterdam",
    "sg:orig_category":"Kinderopvang Behalve Thuis",
    "sg:phone":"+31 20 626 1266",
    "sg:postcode":"1011 TV",
    "sg:province":"Noord-Holland",
    "wof:name":"Creche Oma Pap",
    "wof:placetype":"venue"
},
  "geometry": {"coordinates":[4.908727,52.371399],"type":"Point"}
}