{
  "type": "Feature",
  "properties": {
    "iso:country":"NL",
    "sg:address":"Spanbroekerweg 208",
    "sg:city":"Spanbroek",
    "sg:orig_category":"Diverse Bedrijfsinstallaties Gh",
    "sg:phone":"+31 226 352 544",
    "sg:postcode":"1715 GW",
    "sg:province":"Noord-Holland",
    "wof:name":"Handelsonderneming Beerepoot Bv",
    "wof:placetype":"venue"
},
  "geometry": {"coordinates":[4.969765,52.694984],"type":"Point"}
}