{
  "type": "Feature",
  "properties": {
    "addr:full":"Brucknerstraat 2 Amersfoort Utrecht 3816 LX",
    "addr:housenumber":"2",
    "addr:postcode":"3816 lx",
    "addr:street":"Brucknerstraat",
    "iso:country":"NL",
    "sg:address":"Brucknerstraat 2",
    "sg:city":"Amersfoort",
    "sg:orig_category":"Medische Apparatuur And Prothesen Fab",
    "sg:phone":"+31 33 470 1476",
    "sg:postcode":"3816 LX",
    "sg:province":"Utrecht",
    "wof:name":"Delfos Dental Ceramics",
    "wof:placetype":"venue"
},
  "geometry": {"coordinates":[5.40344,52.147217],"type":"Point"}
}