{
  "type": "Feature",
  "properties": {
    "addr:full":"Transportweg 31B Maasland South Holland 3155 RJ",
    "addr:housenumber":"31b",
    "addr:postcode":"3155 rj",
    "addr:street":"Transportweg",
    "iso:country":"NL",
    "sg:address":"Transportweg 31B",
    "sg:city":"Maasland",
    "sg:orig_category":"Verhuizingen",
    "sg:phone":"+31 174 513 120",
    "sg:postcode":"3155 RJ",
    "sg:province":"South Holland",
    "sg:website":"http://www.vit-verhuizingen.nl",
    "wof:name":"Vit",
    "wof:placetype":"venue"
},
  "geometry": {"coordinates":[4.275135,51.936325],"type":"Point"}
}