{
  "type": "Feature",
  "properties": {
    "addr:full":"Kruisstr 39A Oss Noord-Brabant 5341 HA",
    "addr:housenumber":"39a",
    "addr:postcode":"5341 ha",
    "addr:street":"Kruisstr",
    "iso:country":"NL",
    "sg:address":"Kruisstr 39A",
    "sg:city":"Oss",
    "sg:orig_category":"Kappers",
    "sg:phone":"+31 412 623 188",
    "sg:postcode":"5341 HA",
    "sg:province":"Noord-Brabant",
    "wof:name":"Sjaak Lodewijkx",
    "wof:placetype":"venue"
},
  "geometry": {"coordinates":[-77.235214,38.312599],"type":"Point"}
}