{
  "type": "Feature",
  "properties": {
    "addr:full":"Dykstr 15 Franeker Friesland 8801 LR",
    "addr:housenumber":"15",
    "addr:postcode":"8801 lr",
    "addr:street":"Dykstr",
    "iso:country":"NL",
    "sg:address":"Dykstr 15",
    "sg:city":"Franeker",
    "sg:orig_category":"Opticiens",
    "sg:phone":"+31 517 397 795",
    "sg:postcode":"8801 LR",
    "sg:province":"Friesland",
    "sg:website":"http://www.hansanders.nl",
    "wof:name":"Hans Anders",
    "wof:placetype":"venue"
},
  "geometry": {"coordinates":[5.5382151604,53.1853599548],"type":"Point"}
}