{
  "type": "Feature",
  "properties": {
    "iso:country":"NL",
    "sg:address":"L Ansinghstr 12",
    "sg:city":"Amsterdam",
    "sg:orig_category":"Voetbalverenigingen",
    "sg:phone":"+31 20 364 1046",
    "sg:postcode":"1072 RD",
    "sg:province":"Noord-Holland",
    "wof:name":"Knooppunt, 'T",
    "wof:placetype":"venue"
},
  "geometry": {"coordinates":[4.891744,52.349548],"type":"Point"}
}