{
  "type": "Feature",
  "properties": {
    "addr:full":"Raadhuispln 12 Oostburg Zeeland 4501 BG",
    "addr:housenumber":"12",
    "addr:postcode":"4501",
    "addr:street":"Raadhuispln",
    "iso:country":"NL",
    "sg:address":"Raadhuispln 12",
    "sg:city":"Oostburg",
    "sg:orig_category":"Glas, Porselein En Aardewerk",
    "sg:phone":"+31 117 452 113",
    "sg:postcode":"4501 BG",
    "sg:province":"Zeeland",
    "wof:name":"Fierens",
    "wof:placetype":"venue"
},
  "geometry": {"coordinates":[3.487009,51.326824],"type":"Point"}
}