{
  "type": "Feature",
  "properties": {
    "iso:country":"NL",
    "sg:address":"Johannes Van Zantenstr 67",
    "sg:city":"Tilburg",
    "sg:orig_category":"Diverse Grafische Activiteiten",
    "sg:phone":"+31 13 590 0069",
    "sg:postcode":"5025 VX",
    "sg:province":"Noord-Brabant",
    "wof:name":"Koudijs Buro Voor Ontwerpen",
    "wof:placetype":"venue"
},
  "geometry": {"coordinates":[5.060094,51.54829],"type":"Point"}
}