{
  "type": "Feature",
  "properties": {
    "addr:full":"Saffraanveld 20 Schiedam Zuid-Holland 3124 VJ",
    "addr:housenumber":"20",
    "addr:postcode":"3124 vj",
    "addr:street":"Saffraanveld",
    "iso:country":"NL",
    "sg:address":"Saffraanveld 20",
    "sg:city":"Schiedam",
    "sg:orig_category":"Montagebedrijven",
    "sg:phone":"+31 10 470 3868",
    "sg:postcode":"3124 VJ",
    "sg:province":"Zuid-Holland",
    "wof:name":"Global Service",
    "wof:placetype":"venue"
},
  "geometry": {"coordinates":[4.375325,51.947094],"type":"Point"}
}