{
  "type": "Feature",
  "properties": {
    "addr:full":"Stetlaantje 1 Limmen Noord-Holland 1906 AN",
    "addr:housenumber":"1",
    "addr:postcode":"1906 an",
    "addr:street":"Stetlaantje",
    "iso:country":"NL",
    "sg:address":"Stetlaantje 1",
    "sg:city":"Limmen",
    "sg:orig_category":"Begrafenisondernemers",
    "sg:phone":"+31 72 505 3009",
    "sg:postcode":"1906 AN",
    "sg:province":"Noord-Holland",
    "wof:name":"Uitvaartverzorging Lia Groot",
    "wof:placetype":"venue"
},
  "geometry": {"coordinates":[4.699832,52.570309],"type":"Point"}
}