{
  "type": "Feature",
  "properties": {
    "addr:full":"Industriewg 76 Berkel En Rodenrys South Holland 2651 BD",
    "addr:housenumber":"76",
    "addr:postcode":"2651 bd",
    "addr:street":"Industriewg;Berkel",
    "iso:country":"NL",
    "sg:address":"Industriewg 76",
    "sg:city":"Berkel En Rodenrys",
    "sg:orig_category":"Kantoor- En Bedrijfsmeubelen",
    "sg:phone":"+31 10 511 4727",
    "sg:postcode":"2651 BD",
    "sg:province":"South Holland",
    "sg:website":"http://www.wooning.nl",
    "wof:name":"Ton Wooning",
    "wof:placetype":"venue"
},
  "geometry": {"coordinates":[4.4551620483,51.9831504822],"type":"Point"}
}