{
  "type": "Feature",
  "properties": {
    "addr:full":"Ds V Couwenhoveln 163 Bergschenhoek Zuid-Holland 2661 BH",
    "addr:housenumber":"163",
    "addr:postcode":"2661 bh",
    "addr:street":"Ds;Couwenhoveln",
    "iso:country":"NL",
    "sg:address":"Ds V Couwenhoveln 163",
    "sg:city":"Bergschenhoek",
    "sg:orig_category":"Adviesbureaus Financieel",
    "sg:phone":"+31 10 426 9279",
    "sg:postcode":"2661 BH",
    "sg:province":"Zuid-Holland",
    "sg:website":"http://www.schumm.nu",
    "wof:name":"Schumm Bv",
    "wof:placetype":"venue"
},
  "geometry": {"coordinates":[4.500133,51.989536],"type":"Point"}
}