{
  "type": "Feature",
  "properties": {
    "iso:country":"NL",
    "sg:address":"Nieuwpoortkade 28",
    "sg:city":"Amsterdam",
    "sg:orig_category":"Boekhouders",
    "sg:phone":"+31 20 617 9747",
    "sg:postcode":"1055 RX",
    "sg:province":"North Holland",
    "wof:name":"Arlette Fashion Bv",
    "wof:placetype":"venue"
},
  "geometry": {"coordinates":[4.860509,52.383732],"type":"Point"}
}