{
  "type": "Feature",
  "properties": {
    "addr:full":"Haven 57 Schoonhoven Zuid-Holland 2871 CL",
    "addr:housenumber":"57",
    "addr:postcode":"2871",
    "addr:street":"Haven",
    "iso:country":"NL",
    "sg:address":"Haven 57",
    "sg:city":"Schoonhoven",
    "sg:classifiers":[
        {
            "category":"Bakery",
            "type":"Food & Drink"
        }
    ],
    "sg:phone":"+31 182 382 496",
    "sg:postcode":"2871 CL",
    "sg:province":"Zuid-Holland",
    "sg:tags":[
        "brood",
        "banket"
    ],
    "wof:name":"Kok'S Bakkerij Vof",
    "wof:placetype":"venue"
},
  "geometry": {"coordinates":[4.852024,51.945835],"type":"Point"}
}