{
  "type": "Feature",
  "properties": {
    "addr:full":"Leembaan 55 Deurne Noord-Brabant 5753 CW",
    "addr:housenumber":"55",
    "addr:postcode":"5753 cw",
    "addr:street":"Leembaan",
    "iso:country":"NL",
    "sg:address":"Leembaan 55",
    "sg:city":"Deurne",
    "sg:orig_category":"Autoradio'S",
    "sg:phone":"+31 493 319 009",
    "sg:postcode":"5753 CW",
    "sg:province":"Noord-Brabant",
    "sg:website":"http://www.qualitycentre.nl",
    "wof:name":"Goossens Quality Centre",
    "wof:placetype":"venue"
},
  "geometry": {"coordinates":[5.798488,51.450085],"type":"Point"}
}