{
  "type": "Feature",
  "properties": {
    "addr:full":"Hooiwg 198 Paterswolde Provincie Drenthe 9765 EM",
    "addr:housenumber":"198",
    "addr:postcode":"9765 em",
    "addr:street":"Provincie Drenthe",
    "iso:country":"NL",
    "sg:address":"Hooiwg 198",
    "sg:city":"Paterswolde",
    "sg:orig_category":"Artsen - Manuele Geneeskunde",
    "sg:phone":"+31 50 309 4361",
    "sg:postcode":"9765 EM",
    "sg:province":"Provincie Drenthe",
    "wof:name":"Jorritsma, W",
    "wof:placetype":"venue"
},
  "geometry": {"coordinates":[6.557149,53.148949],"type":"Point"}
}