{
  "type": "Feature",
  "properties": {
    "addr:full":"Vrijheidslaan 8 Amsterdam Noord-Holland 1078 PJ",
    "addr:housenumber":"8",
    "addr:postcode":"1078 pj",
    "addr:street":"Vrijheidslaan",
    "iso:country":"NL",
    "sg:address":"Vrijheidslaan 8",
    "sg:city":"Amsterdam",
    "sg:orig_category":"Verzekeringen",
    "sg:phone":"+31 20 664 0383",
    "sg:postcode":"1078 PJ",
    "sg:province":"Noord-Holland",
    "wof:name":"Surinaamse Crediet-Maatschappij Bv",
    "wof:placetype":"venue"
},
  "geometry": {"coordinates":[4.910637,52.347385],"type":"Point"}
}