{
  "type": "Feature",
  "properties": {
    "iso:country":"NL",
    "sg:address":"Leemwg 13",
    "sg:city":"Terschuur",
    "sg:orig_category":"Pluimveebedrijven En -Handelaren",
    "sg:phone":"+31 342 461 469",
    "sg:postcode":"3784 KC",
    "sg:province":"Gelderland",
    "wof:name":"Mheen, W Van De",
    "wof:placetype":"venue"
},
  "geometry": {"coordinates":[5.527943,52.167961],"type":"Point"}
}