{
  "type": "Feature",
  "properties": {
    "addr:full":"Leemwg 13 Terschuur Gelderland 3784 KC",
    "addr:housenumber":"13",
    "addr:postcode":"3784 kc",
    "addr:street":"Leemwg;Gelderland",
    "iso:country":"NL",
    "sg:address":"Leemwg 13",
    "sg:city":"Terschuur",
    "sg:orig_category":"Pluimveebedrijven En -Handelaren",
    "sg:phone":"+31 342 461 469",
    "sg:postcode":"3784 KC",
    "sg:province":"Gelderland",
    "wof:name":"Mheen, W Van De",
    "wof:placetype":"venue"
},
  "geometry": {"coordinates":[5.527943,52.167961],"type":"Point"}
}