{
  "type": "Feature",
  "properties": {
    "addr:full":"Past Oomenstr 5 Ryen North Brabant 5121 EN",
    "addr:housenumber":"5",
    "addr:postcode":"5121 en",
    "iso:country":"NL",
    "sg:address":"Past Oomenstr 5",
    "sg:city":"Ryen",
    "sg:orig_category":"Verzekeringen - Verzekeringskantoren",
    "sg:phone":"+31 161 222 591",
    "sg:postcode":"5121 EN",
    "sg:province":"North Brabant",
    "wof:name":"Brouwers",
    "wof:placetype":"venue"
},
  "geometry": {"coordinates":[4.9197,51.588017],"type":"Point"}
}