{
  "type": "Feature",
  "properties": {
    "addr:full":"W De Merodestr 28 Hengelo Ov Overijssel 7552 WZ",
    "addr:housenumber":"28",
    "addr:postcode":"7552 wz",
    "addr:street":"W De Merodestr;Ov",
    "iso:country":"NL",
    "sg:address":"W De Merodestr 28",
    "sg:city":"Hengelo Ov",
    "sg:orig_category":"Drogisterijen",
    "sg:phone":"+31 74 242 6097",
    "sg:postcode":"7552 WZ",
    "sg:province":"Overijssel",
    "wof:name":"Kruidvat",
    "wof:placetype":"venue"
},
  "geometry": {"coordinates":[6.822321,52.262615],"type":"Point"}
}