{
  "type": "Feature",
  "properties": {
    "iso:country":"NL",
    "sg:address":"Klaproosstr 11",
    "sg:city":"Alphen Aan Den Ryn",
    "sg:orig_category":"Psychologen",
    "sg:phone":"+31 172 420 293",
    "sg:postcode":"2403 EV",
    "sg:province":"South Holland",
    "wof:name":"Corbeau, Drs A C",
    "wof:placetype":"venue"
},
  "geometry": {"coordinates":[4.685023,52.144157],"type":"Point"}
}