{
  "type": "Feature",
  "properties": {
    "addr:full":"Rembrandtln 103B Schiedam South Holland 3117 VH",
    "addr:housenumber":"103b",
    "addr:postcode":"3117 vh",
    "iso:country":"NL",
    "sg:address":"Rembrandtln 103B",
    "sg:city":"Schiedam",
    "sg:orig_category":"Kappers",
    "sg:phone":"+31 10 246 0295",
    "sg:postcode":"3117 VH",
    "sg:province":"South Holland",
    "wof:name":"Peters, Patricia",
    "wof:placetype":"venue"
},
  "geometry": {"coordinates":[4.38459,51.914448],"type":"Point"}
}