{
  "type": "Feature",
  "properties": {
    "addr:full":"Groest 86-61 Hilversum Noord-Holland 1211 ED",
    "addr:housenumber":"86-61",
    "addr:postcode":"hilversum;1211 ed",
    "addr:street":"Groest",
    "iso:country":"NL",
    "sg:address":"Groest 86-61",
    "sg:city":"Hilversum",
    "sg:orig_category":"Zoetwaren - Winkels",
    "sg:phone":"+31 35 621 5254",
    "sg:postcode":"1211 ED",
    "sg:province":"Noord-Holland",
    "wof:name":"Mecca",
    "wof:placetype":"venue"
},
  "geometry": {"coordinates":[5.177286,52.224655],"type":"Point"}
}