{
  "type": "Feature",
  "properties": {
    "addr:full":"Kraaienln 74 S Gravenhage Zuid-Holland 2566 RK",
    "addr:housenumber":"74;gravenhage",
    "addr:postcode":"2566 rk",
    "addr:street":"Kraaienln;S",
    "iso:country":"NL",
    "sg:address":"Kraaienln 74",
    "sg:city":"S Gravenhage",
    "sg:orig_category":"Kantoor- En Secretariaatsservice",
    "sg:phone":"+31 70 368 6975",
    "sg:postcode":"2566 RK",
    "sg:province":"Zuid-Holland",
    "wof:name":"Zandvliet Bv",
    "wof:placetype":"venue"
},
  "geometry": {"coordinates":[4.2555298805,52.0791282654],"type":"Point"}
}