{
  "type": "Feature",
  "properties": {
    "addr:full":"Watermunt 2 Mierlo Noord-Brabant 5731 TE",
    "addr:housenumber":"2",
    "addr:postcode":"5731 te",
    "addr:street":"Watermunt",
    "iso:country":"NL",
    "sg:address":"Watermunt 2",
    "sg:city":"Mierlo",
    "sg:orig_category":"Geluidsopnamen",
    "sg:phone":"+31 492 665 392",
    "sg:postcode":"5731 TE",
    "sg:province":"Noord-Brabant",
    "wof:name":"C & C",
    "wof:placetype":"venue"
},
  "geometry": {"coordinates":[5.625265,51.439701],"type":"Point"}
}