{
  "type": "Feature",
  "properties": {
    "iso:country":"NL",
    "sg:address":"Dorpsstr 95",
    "sg:city":"Hazerswoude Dorp",
    "sg:orig_category":"Woninginrichting",
    "sg:phone":"+31 172 589 235",
    "sg:postcode":"2391 BD",
    "sg:province":"Zuid-Holland",
    "wof:name":"Huisman Bv",
    "wof:placetype":"venue"
},
  "geometry": {"coordinates":[4.5929479599,52.0966262817],"type":"Point"}
}