{
  "type": "Feature",
  "properties": {
    "addr:full":"Reinkenstraat 69 'S Gravenhage South Holland 2517 CR",
    "addr:housenumber":"69",
    "addr:postcode":"2517 cr",
    "addr:street":"Reinkenstraat;' S Gravenhage",
    "iso:country":"NL",
    "sg:address":"Reinkenstraat 69",
    "sg:city":"'S Gravenhage",
    "sg:orig_category":"Wasserettes And Stomerijen",
    "sg:phone":"+31 70 361 6314",
    "sg:postcode":"2517 CR",
    "sg:province":"South Holland",
    "wof:name":"Wassalon Reinkenstraat",
    "wof:placetype":"venue"
},
  "geometry": {"coordinates":[4.2834348679,52.0818252563],"type":"Point"}
}