{
  "type": "Feature",
  "properties": {
    "addr:full":"Krayenhofflaan 34 Nijmegen Gelderland 6541 PT",
    "addr:housenumber":"34",
    "addr:postcode":"6541",
    "addr:street":"Krayenhofflaan;Gelderland;Pt",
    "iso:country":"NL",
    "sg:address":"Krayenhofflaan 34",
    "sg:city":"Nijmegen",
    "sg:orig_category":"Technische Studies And Onderzoek",
    "sg:phone":"+31 24 379 1253",
    "sg:postcode":"6541 PT",
    "sg:province":"Gelderland",
    "wof:name":"Modular Ergoprojects",
    "wof:placetype":"venue"
},
  "geometry": {"coordinates":[5.849593,51.847015],"type":"Point"}
}