{
  "type": "Feature",
  "properties": {
    "addr:full":"Bloemaertln 192 Alkmaar North Holland 1816 KG",
    "addr:housenumber":"192",
    "addr:postcode":"1816 kg",
    "iso:country":"NL",
    "sg:address":"Bloemaertln 192",
    "sg:city":"Alkmaar",
    "sg:orig_category":"Zuivel - Groothandel",
    "sg:phone":"+31 72 511 6755",
    "sg:postcode":"1816 KG",
    "sg:province":"North Holland",
    "wof:name":"Beek, R",
    "wof:placetype":"venue"
},
  "geometry": {"coordinates":[4.727561,52.630978],"type":"Point"}
}