{
  "type": "Feature",
  "properties": {
    "addr:full":"Adriaan Stoopplein 17 Overveen Noord-Holland 2051 KB",
    "addr:housenumber":"17",
    "addr:postcode":"2051 kb",
    "addr:street":"Adriaan Stoopplein",
    "iso:country":"NL",
    "sg:address":"Adriaan Stoopplein 17",
    "sg:city":"Overveen",
    "sg:orig_category":"Werving And Selectie Van Vast Personeel",
    "sg:phone":"+31 23 527 5295",
    "sg:postcode":"2051 KB",
    "sg:province":"Noord-Holland",
    "wof:name":"Arte-Consult Vof",
    "wof:placetype":"venue"
},
  "geometry": {"coordinates":[4.6215190887,52.3899345398],"type":"Point"}
}