{
  "type": "Feature",
  "properties": {
    "addr:full":"Ambachtstraat 8 Putten Gelderland 3882 BB",
    "addr:housenumber":"8",
    "addr:postcode":"3882 bb",
    "addr:street":"Ambachtstraat;Gelderland",
    "iso:country":"NL",
    "sg:address":"Ambachtstraat 8",
    "sg:city":"Putten",
    "sg:orig_category":"Meubelzaken, Woning- And Keukeninrichting",
    "sg:phone":"+31 341 357 689",
    "sg:postcode":"3882 BB",
    "sg:province":"Gelderland",
    "wof:name":"De Habbekrats Meubelen Vof",
    "wof:placetype":"venue"
},
  "geometry": {"coordinates":[5.603703,52.254753],"type":"Point"}
}