{
  "type": "Feature",
  "properties": {
    "addr:full":"Wageningenstraat 18 Nieuw Vennep Noord-Holland 2152 AN",
    "addr:housenumber":"18",
    "addr:postcode":"2152 an",
    "addr:street":"Wageningenstraat;Nieuw Vennep",
    "iso:country":"NL",
    "sg:address":"Wageningenstraat 18",
    "sg:city":"Nieuw Vennep",
    "sg:orig_category":"Vertaal- And Tolkenbureaus",
    "sg:phone":"+31 252 673 695",
    "sg:postcode":"2152 AN",
    "sg:province":"Noord-Holland",
    "wof:name":"Vertaalbureau Amrita",
    "wof:placetype":"venue"
},
  "geometry": {"coordinates":[4.634498,52.268963],"type":"Point"}
}