{
  "type": "Feature",
  "properties": {
    "addr:full":"Meerwykwg 6 S Hertogenbosch Noord-Brabant 5236 BM",
    "addr:housenumber":"6",
    "addr:postcode":"5236 bm",
    "addr:street":"Meerwykwg",
    "iso:country":"NL",
    "sg:address":"Meerwykwg 6",
    "sg:city":"S Hertogenbosch",
    "sg:orig_category":"Sportverenigingen En Ontspannings- Verenigingen",
    "sg:phone":"+31 73 642 2429",
    "sg:postcode":"5236 BM",
    "sg:province":"Noord-Brabant",
    "wof:name":"Emplina Voetbalver",
    "wof:placetype":"venue"
},
  "geometry": {"coordinates":[5.327515,51.73003],"type":"Point"}
}