{
  "type": "Feature",
  "properties": {
    "iso:country":"NL",
    "sg:address":"Van Lodensteynstraat 116",
    "sg:city":"Delft",
    "sg:orig_category":"Kappers",
    "sg:phone":"+31 15 284 0558",
    "sg:postcode":"2612 SK",
    "sg:province":"Zuid-Holland",
    "wof:name":"Kapsalon Haarwinkel",
    "wof:placetype":"venue"
},
  "geometry": {"coordinates":[4.372877121,52.0132675171],"type":"Point"}
}