{
  "type": "Feature",
  "properties": {
    "addr:full":"Nieuwevaart 141 Amsterdam North Holland 1018 ZM",
    "addr:housenumber":"141",
    "addr:postcode":"1018 zm",
    "addr:street":"Nieuwevaart",
    "iso:country":"NL",
    "sg:address":"Nieuwevaart 141",
    "sg:city":"Amsterdam",
    "sg:orig_category":"Koeriersdiensten",
    "sg:phone":"+31 20 623 1478",
    "sg:postcode":"1018 ZM",
    "sg:province":"North Holland",
    "wof:name":"Ponky",
    "wof:placetype":"venue"
},
  "geometry": {"coordinates":[4.916482,52.369637],"type":"Point"}
}