{
  "type": "Feature",
  "properties": {
    "addr:full":"Pijlstaartpad 13 Werkendam Noord-Brabant 4251 VM",
    "addr:housenumber":"13",
    "addr:postcode":"4251 vm",
    "addr:street":"Pijlstaartpad",
    "iso:country":"NL",
    "sg:address":"Pijlstaartpad 13",
    "sg:city":"Werkendam",
    "sg:orig_category":"Schilderwerk",
    "sg:phone":"+31 183 501 872",
    "sg:postcode":"4251 VM",
    "sg:province":"Noord-Brabant",
    "wof:name":"Schildersbedrijf Limburg Werkendam Bv",
    "wof:placetype":"venue"
},
  "geometry": {"coordinates":[4.894981,51.805202],"type":"Point"}
}