{
  "type": "Feature",
  "properties": {
    "addr:full":"Bolder 76 Groningen Groningen 9732 PE",
    "addr:housenumber":"76",
    "addr:postcode":"9732 pe",
    "addr:street":"Bolder",
    "iso:country":"NL",
    "sg:address":"Bolder 76",
    "sg:city":"Groningen",
    "sg:orig_category":"Kappers",
    "sg:phone":"+31 50 541 7731",
    "sg:postcode":"9732 PE",
    "sg:province":"Groningen",
    "wof:name":"Katerborg, H",
    "wof:placetype":"venue"
},
  "geometry": {"coordinates":[6.6181659698,53.2325172424],"type":"Point"}
}