{
  "type": "Feature",
  "properties": {
    "addr:full":"Wensenkampsweg 9 Vlagtwedde Groningen 9541 EB",
    "addr:housenumber":"9",
    "addr:postcode":"9541 eb",
    "addr:street":"Wensenkampsweg",
    "iso:country":"NL",
    "sg:address":"Wensenkampsweg 9",
    "sg:city":"Vlagtwedde",
    "sg:orig_category":"Goederenvervoer Over De Weg",
    "sg:phone":"+31 599 312 939",
    "sg:postcode":"9541 EB",
    "sg:province":"Groningen",
    "wof:name":"Meulman Transport C.V.",
    "wof:placetype":"venue"
},
  "geometry": {"coordinates":[7.102504,53.031059],"type":"Point"}
}