{
  "type": "Feature",
  "properties": {
    "addr:full":"Beekstg 21 Haarlem Noord-Holland 2011 CX",
    "addr:housenumber":"21",
    "addr:postcode":"2011 cx",
    "addr:street":"Beekstg",
    "iso:country":"NL",
    "sg:address":"Beekstg 21",
    "sg:city":"Haarlem",
    "sg:classifiers":[
        {
            "category":"Retail",
            "subcategory":"Auto Repair",
            "type":"Services"
        }
    ],
    "sg:phone":"+31 23 535 7715",
    "sg:postcode":"2011 CX",
    "sg:province":"Noord-Holland",
    "sg:tags":[
        "garage"
    ],
    "wof:name":"Jansen En Louwerens Garagebedrijf",
    "wof:placetype":"venue"
},
  "geometry": {"coordinates":[4.641375,52.379265],"type":"Point"}
}