{
  "type": "Feature",
  "properties": {
    "addr:full":"Hinthamerstraat 158 'S Hertogenbosch Noord-Brabant 5211 MV",
    "addr:housenumber":"158 ' s",
    "addr:postcode":"5211 mv",
    "addr:street":"Hinthamerstraat",
    "iso:country":"NL",
    "sg:address":"Hinthamerstraat 158",
    "sg:city":"'S Hertogenbosch",
    "sg:orig_category":"Kappers",
    "sg:phone":"+31 73 613 0454",
    "sg:postcode":"5211 MV",
    "sg:province":"Noord-Brabant",
    "wof:name":"Salon Laurent",
    "wof:placetype":"venue"
},
  "geometry": {"coordinates":[5.31166,51.688637],"type":"Point"}
}