{
  "type": "Feature",
  "properties": {
    "addr:full":"Wolfsesteeg 9 Zwartebroek Gelderland 3785 LN",
    "addr:housenumber":"9",
    "addr:postcode":"3785 ln",
    "addr:street":"Wolfsesteeg;Gelderland",
    "iso:country":"NL",
    "sg:address":"Wolfsesteeg 9",
    "sg:city":"Zwartebroek",
    "sg:orig_category":"Goederenvervoer Over De Weg",
    "sg:phone":"+31 342 461 680",
    "sg:postcode":"3785 LN",
    "sg:province":"Gelderland",
    "wof:name":"J. Kous Transportonderneming Bv",
    "wof:placetype":"venue"
},
  "geometry": {"coordinates":[5.487166,52.182396],"type":"Point"}
}