{
  "type": "Feature",
  "properties": {
    "iso:country":"NL",
    "sg:address":"Wolfsesteeg 9",
    "sg:city":"Zwartebroek",
    "sg:orig_category":"Goederenvervoer Over De Weg",
    "sg:phone":"+31 342 461 680",
    "sg:postcode":"3785 LN",
    "sg:province":"Gelderland",
    "wof:name":"J. Kous Transportonderneming Bv",
    "wof:placetype":"venue"
},
  "geometry": {"coordinates":[5.487166,52.182396],"type":"Point"}
}