{
  "type": "Feature",
  "properties": {
    "addr:full":"F Halsstr 93 Amsterdam North Holland 1072 BP",
    "addr:housenumber":"93",
    "addr:postcode":"1072 bp",
    "iso:country":"NL",
    "sg:address":"F Halsstr 93",
    "sg:city":"Amsterdam",
    "sg:orig_category":"Beeldende Kunstenaars",
    "sg:phone":"+31 20 679 8691",
    "sg:postcode":"1072 BP",
    "sg:province":"North Holland",
    "wof:name":"Krabb?, Mirko",
    "wof:placetype":"venue"
},
  "geometry": {"coordinates":[4.888562,52.354683],"type":"Point"}
}