{
  "type": "Feature",
  "properties": {
    "addr:full":"Lugteren 43 S Hertogenbosch Noord-Brabant 5237 JV",
    "addr:housenumber":"43",
    "addr:postcode":"5237 jv",
    "addr:street":"Lugteren;S Hertogenbosch",
    "iso:country":"NL",
    "sg:address":"Lugteren 43",
    "sg:city":"S Hertogenbosch",
    "sg:orig_category":"Kappers",
    "sg:phone":"+31 73 644 3525",
    "sg:postcode":"5237 JV",
    "sg:province":"Noord-Brabant",
    "wof:name":"Hees, Haarmode Van",
    "wof:placetype":"venue"
},
  "geometry": {"coordinates":[5.2910552025,51.7272338867],"type":"Point"}
}