{
  "type": "Feature",
  "properties": {
    "iso:country":"NL",
    "sg:address":"Louis Davidsstraat 33",
    "sg:city":"Almere",
    "sg:orig_category":"Kinderopvang Behalve Thuis",
    "sg:phone":"+31 36 536 6181",
    "sg:postcode":"1311 LC",
    "sg:province":"NL.",
    "wof:name":"De Vrolijke Noot Ska Naschoolse Opvang",
    "wof:placetype":"venue"
},
  "geometry": {"coordinates":[5.180558,52.371357],"type":"Point"}
}