{
  "type": "Feature",
  "properties": {
    "addr:full":"Nijverheidsweg 22 Wervershoof Noord-Holland 1693 AM",
    "addr:housenumber":"22",
    "addr:postcode":"1693",
    "addr:street":"Nijverheidsweg",
    "iso:country":"NL",
    "sg:address":"Nijverheidsweg 22",
    "sg:city":"Wervershoof",
    "sg:orig_category":"Autokeuringen",
    "sg:phone":"+31 228 584 734",
    "sg:postcode":"1693 AM",
    "sg:province":"Noord-Holland",
    "wof:name":"Vb Dieselservice",
    "wof:placetype":"venue"
},
  "geometry": {"coordinates":[5.162794,52.734989],"type":"Point"}
}