{
  "type": "Feature",
  "properties": {
    "addr:full":"Teisterbant 2 Veendam Groningen 9642 RG",
    "addr:housenumber":"2",
    "addr:postcode":"9642 rg",
    "addr:street":"Teisterbant",
    "iso:country":"NL",
    "sg:address":"Teisterbant 2",
    "sg:city":"Veendam",
    "sg:orig_category":"Fotostudio'S And Fotografen",
    "sg:phone":"+31 598 619 821",
    "sg:postcode":"9642 RG",
    "sg:province":"Groningen",
    "wof:name":"Fotografie B. Woltjes",
    "wof:placetype":"venue"
},
  "geometry": {"coordinates":[6.856369,53.090405],"type":"Point"}
}