{
  "type": "Feature",
  "properties": {
    "iso:country":"NL",
    "sg:address":"Bloemstraat 11",
    "sg:city":"Huissen",
    "sg:orig_category":"Hypotheken And Hypotheekbanken",
    "sg:phone":"+31 26 325 0223",
    "sg:postcode":"6851 CR",
    "sg:province":"Gelderland",
    "wof:name":"F.F.A. De Wit",
    "wof:placetype":"venue"
},
  "geometry": {"coordinates":[5.941197,51.932041],"type":"Point"}
}