{
  "type": "Feature",
  "properties": {
    "addr:full":"Rijperweg 52 Middenbeemster Noord-Holland 1462 ME",
    "addr:housenumber":"52",
    "addr:postcode":"1462 me",
    "addr:street":"Rijperweg",
    "iso:country":"NL",
    "sg:address":"Rijperweg 52",
    "sg:city":"Middenbeemster",
    "sg:orig_category":"Huisdierenfokkers",
    "sg:phone":"+31 224 223 422",
    "sg:postcode":"1462 ME",
    "sg:province":"Noord-Holland",
    "wof:name":"Mantis",
    "wof:placetype":"venue"
},
  "geometry": {"coordinates":[4.910014,52.548977],"type":"Point"}
}