{
  "type": "Feature",
  "properties": {
    "iso:country":"NL",
    "sg:address":"Bovenweg 71",
    "sg:city":"Sint Pancras",
    "sg:orig_category":"Boekenuitgeverijen",
    "sg:phone":"+31 72 564 2557",
    "sg:postcode":"1734  C",
    "sg:province":"Noord-Holland",
    "wof:name":"Bruna",
    "wof:placetype":"venue"
},
  "geometry": {"coordinates":[4.783702,52.661629],"type":"Point"}
}