{
  "type": "Feature",
  "properties": {
    "iso:country":"NL",
    "sg:address":"Johannahoeve 1E",
    "sg:city":"Oosterbeek",
    "sg:orig_category":"Hek- En Rasterwerken",
    "sg:phone":"+31 26 333 8349",
    "sg:postcode":"6861 WJ",
    "sg:province":"Gelderland",
    "wof:name":"Bouwman & Verplak",
    "wof:placetype":"venue"
},
  "geometry": {"coordinates":[5.841684,51.996101],"type":"Point"}
}