{
  "type": "Feature",
  "properties": {
    "addr:full":"Burgemeester Feithplein 18 Voorburg Zuid-Holland 2273 BZ",
    "addr:housenumber":"18",
    "addr:postcode":"2273 bz",
    "addr:street":"Burgemeester Feithplein",
    "iso:country":"NL",
    "sg:address":"Burgemeester Feithplein 18",
    "sg:city":"Voorburg",
    "sg:orig_category":"Werving And Selectie Van Vast Personeel",
    "sg:phone":"+31 70 387 6797",
    "sg:postcode":"2273 BZ",
    "sg:province":"Zuid-Holland",
    "wof:name":"Focus Nederland",
    "wof:placetype":"venue"
},
  "geometry": {"coordinates":[4.3624410629,52.075088501],"type":"Point"}
}