{
  "type": "Feature",
  "properties": {
    "addr:full":"Plechelmusstraat 1 De Lutte NL.08 7587 AL",
    "addr:housenumber":"1",
    "addr:postcode":"nl.08 7587 al",
    "addr:street":"Plechelmusstraat",
    "iso:country":"NL",
    "sg:address":"Plechelmusstraat 1",
    "sg:city":"De Lutte",
    "sg:classifiers":[
        {
            "category":"Education",
            "subcategory":"Preschool",
            "type":"Public Place"
        }
    ],
    "sg:phone":"+31 541 552 282",
    "sg:postcode":"7587 AL",
    "sg:province":"NL.08",
    "sg:tags":[
        "kleuteronderwijs",
        "basis-"
    ],
    "wof:name":"T Kloosterhofke",
    "wof:placetype":"venue"
},
  "geometry": {"coordinates":[6.987255,52.314983],"type":"Point"}
}