{
  "type": "Feature",
  "properties": {
    "addr:full":"Duinoord 2 Katwyk Zh Zuid-Holland 2224 CB",
    "addr:housenumber":"2",
    "addr:postcode":"2224 cb",
    "addr:street":"Duinoord",
    "iso:country":"NL",
    "sg:address":"Duinoord 2",
    "sg:city":"Katwyk Zh",
    "sg:orig_category":"Bloemen En Planten - Groothandel",
    "sg:phone":"+31 71 401 3838",
    "sg:postcode":"2224 CB",
    "sg:province":"Zuid-Holland",
    "wof:name":"Zuijlen, G J Van",
    "wof:placetype":"venue"
},
  "geometry": {"coordinates":[4.410539,52.200878],"type":"Point"}
}