{
  "type": "Feature",
  "properties": {
    "addr:full":"Schoutstr 34 Almere NL. 1315 EX",
    "addr:housenumber":"34",
    "addr:postcode":"1315 ex",
    "addr:street":"Schoutstr;Nl.",
    "iso:country":"NL",
    "sg:address":"Schoutstr 34",
    "sg:city":"Almere",
    "sg:orig_category":"Onroerende Goederen",
    "sg:phone":"+31 36 548 0160",
    "sg:postcode":"1315 EX",
    "sg:province":"NL.",
    "wof:name":"Dynamics Abc Bv",
    "wof:placetype":"venue"
},
  "geometry": {"coordinates":[5.217774,52.374317],"type":"Point"}
}