{
  "type": "Feature",
  "properties": {
    "iso:country":"NL",
    "sg:address":"Oranjelaan 111",
    "sg:city":"Zoetermeer",
    "sg:orig_category":"Bloemen And Planten",
    "sg:phone":"+31 79 316 4330",
    "sg:postcode":"2712 GC",
    "sg:province":"Zuid-Holland",
    "wof:name":"David Nieuwenburg & Zn",
    "wof:placetype":"venue"
},
  "geometry": {"coordinates":[4.496071,52.052185],"type":"Point"}
}