{
  "type": "Feature",
  "properties": {
    "iso:country":"NL",
    "sg:address":"Schubertlaan 26",
    "sg:city":"Naarden",
    "sg:orig_category":"Vertaal- And Tolkenbureaus",
    "sg:phone":"+31 35 694 8045",
    "sg:postcode":"1411 HZ",
    "sg:province":"Noord-Holland",
    "wof:name":"Dr. S. Lobatto",
    "wof:placetype":"venue"
},
  "geometry": {"coordinates":[5.176212,52.290371],"type":"Point"}
}