{
  "type": "Feature",
  "properties": {
    "iso:country":"NL",
    "sg:address":"Kleine Beer 601",
    "sg:city":"Rotterdam",
    "sg:orig_category":"Werving And Selectie Van Tijdelijk Personeel And Uitzendkantoren",
    "sg:phone":"+31 10 455 1811",
    "sg:postcode":"3067 ZW",
    "sg:province":"South Holland",
    "wof:name":"Content",
    "wof:placetype":"venue"
},
  "geometry": {"coordinates":[4.5554060936,51.9497032166],"type":"Point"}
}