{
  "type": "Feature",
  "properties": {
    "iso:country":"NL",
    "sg:address":"Potgietersngl 7",
    "sg:city":"Zwolle",
    "sg:orig_category":"Begrafenisverzorging",
    "sg:phone":"+31 38 421 1933",
    "sg:postcode":"8011 NA",
    "sg:province":"Overijssel",
    "sg:website":"http://www.monuta.nl",
    "wof:name":"Monuta",
    "wof:placetype":"venue"
},
  "geometry": {"coordinates":[6.092171,52.509457],"type":"Point"}
}