{
  "type": "Feature",
  "properties": {
    "addr:full":"Ryksstrwg 165 Hardegaryp Friesland 9254 DE",
    "addr:housenumber":"165;9254",
    "addr:street":"Hardegaryp Friesland;De",
    "iso:country":"NL",
    "sg:address":"Ryksstrwg 165",
    "sg:city":"Hardegaryp",
    "sg:orig_category":"Bejaarden - Verzorgingstehuizen",
    "sg:phone":"+31 511 472 843",
    "sg:postcode":"9254 DE",
    "sg:province":"Friesland",
    "wof:name":"Bennema State",
    "wof:placetype":"venue"
},
  "geometry": {"coordinates":[5.94131,53.215366],"type":"Point"}
}