{
  "type": "Feature",
  "properties": {
    "addr:full":"Koninginnesingel 54 Venlo Limburg 5911 KD",
    "addr:housenumber":"54",
    "addr:postcode":"5911 kd",
    "addr:street":"Koninginnesingel",
    "iso:country":"NL",
    "sg:address":"Koninginnesingel 54",
    "sg:city":"Venlo",
    "sg:orig_category":"Werving And Selectie Van Tijdelijk Personeel And Uitzendkantoren",
    "sg:phone":"+31 77 463 2395",
    "sg:postcode":"5911 KD",
    "sg:province":"Limburg",
    "wof:name":"Aasinca Bv",
    "wof:placetype":"venue"
},
  "geometry": {"coordinates":[6.1696810722,51.3665428162],"type":"Point"}
}