{
  "type": "Feature",
  "properties": {
    "addr:full":"Eremietenstr 12 St Anthonis North Brabant 5845 BM",
    "addr:housenumber":"12",
    "addr:postcode":"5845 bm",
    "addr:street":"Eremietenstr",
    "iso:country":"NL",
    "sg:address":"Eremietenstr 12",
    "sg:city":"St Anthonis",
    "sg:orig_category":"Vertalers",
    "sg:phone":"+31 485 384 635",
    "sg:postcode":"5845 BM",
    "sg:province":"North Brabant",
    "wof:name":"Braks, Jan",
    "wof:placetype":"venue"
},
  "geometry": {"coordinates":[5.885359,51.626091],"type":"Point"}
}