{
  "type": "Feature",
  "properties": {
    "addr:full":"Kerkwg 56 Heemskerk North Holland 1961 JD",
    "addr:housenumber":"56",
    "addr:postcode":"1961 jd",
    "addr:street":"Kerkwg",
    "iso:country":"NL",
    "sg:address":"Kerkwg 56",
    "sg:city":"Heemskerk",
    "sg:orig_category":"Kappers",
    "sg:phone":"+31 251 231 437",
    "sg:postcode":"1961 JD",
    "sg:province":"North Holland",
    "wof:name":"Tunen, Van",
    "wof:placetype":"venue"
},
  "geometry": {"coordinates":[4.669246,52.510777],"type":"Point"}
}