{
  "type": "Feature",
  "properties": {
    "iso:country":"NL",
    "sg:address":"Rubenslaan 1",
    "sg:city":"Bilthoven",
    "sg:orig_category":"Bejaardeninstellingen And Serviceflats",
    "sg:phone":"+31 30 274 4600",
    "sg:postcode":"3723 BM",
    "sg:province":"Utrecht",
    "wof:name":"Ses Huize Het Oosten",
    "wof:placetype":"venue"
},
  "geometry": {"coordinates":[5.200563,52.130615],"type":"Point"}
}