{
  "type": "Feature",
  "properties": {
    "addr:full":"Kastelenpln 167 Eindhoven Noord-Brabant 5653 LX",
    "addr:housenumber":"167",
    "addr:postcode":"5653 lx",
    "iso:country":"NL",
    "sg:address":"Kastelenpln 167",
    "sg:city":"Eindhoven",
    "sg:orig_category":"Kinderopvang",
    "sg:phone":"+31 40 257 3904",
    "sg:postcode":"5653 LX",
    "sg:province":"Noord-Brabant",
    "wof:name":"Bruintje Beer",
    "wof:placetype":"venue"
},
  "geometry": {"coordinates":[5.441429,51.419064],"type":"Point"}
}