{
  "type": "Feature",
  "properties": {
    "addr:full":"Dreef 11 Hengelo Gld Gelderland 7255 WV",
    "addr:housenumber":"11",
    "addr:postcode":"7255 wv",
    "addr:street":"Dreef",
    "iso:country":"NL",
    "sg:address":"Dreef 11",
    "sg:city":"Hengelo Gld",
    "sg:orig_category":"Schoonheidssalons",
    "sg:phone":"+31 575 465 715",
    "sg:postcode":"7255 WV",
    "sg:province":"Gelderland",
    "wof:name":"Martine",
    "wof:placetype":"venue"
},
  "geometry": {"coordinates":[6.310447,52.05249],"type":"Point"}
}