{
  "type": "Feature",
  "properties": {
    "addr:full":"Hazennest 81A Tilburg Noord-Brabant 5012 TA",
    "addr:housenumber":"81a",
    "addr:postcode":"5012 ta",
    "addr:street":"Hazennest",
    "iso:country":"NL",
    "sg:address":"Hazennest 81A",
    "sg:city":"Tilburg",
    "sg:orig_category":"Kantoor- En Secretariaatsservice",
    "sg:phone":"+31 13 547 8080",
    "sg:postcode":"5012 TA",
    "sg:province":"Noord-Brabant",
    "wof:name":"Stand By",
    "wof:placetype":"venue"
},
  "geometry": {"coordinates":[5.1054811478,51.5870056152],"type":"Point"}
}