{
  "type": "Feature",
  "properties": {
    "iso:country":"NL",
    "sg:address":"Regentesselaan 43",
    "sg:city":"Weert",
    "sg:classifiers":[
        {
            "category":"Fast Food",
            "type":"Food & Drink"
        }
    ],
    "sg:phone":"+31 495 539 013",
    "sg:postcode":"6006 AS",
    "sg:province":"Limburg",
    "sg:tags":[
        "afhaal",
        "restaurant"
    ],
    "wof:name":"Snackbar Royaal",
    "wof:placetype":"venue"
},
  "geometry": {"coordinates":[5.705056,51.247482],"type":"Point"}
}