{
  "type": "Feature",
  "properties": {
    "addr:full":"Bovenheigraaf 85 'T Loo Oldebroek Gelderland 8095 PB",
    "addr:housenumber":"85",
    "addr:postcode":"8095 pb",
    "addr:street":"Bovenheigraaf",
    "iso:country":"NL",
    "sg:address":"Bovenheigraaf 85",
    "sg:city":"'T Loo Oldebroek",
    "sg:orig_category":"Binnenhuisarchitecten",
    "sg:phone":"+31 525 630 000",
    "sg:postcode":"8095 PB",
    "sg:province":"Gelderland",
    "wof:name":"Koele Interieurbouw Bv",
    "wof:placetype":"venue"
},
  "geometry": {"coordinates":[5.959862,52.45089],"type":"Point"}
}