{
  "type": "Feature",
  "properties": {
    "addr:full":"Oude Haven 2 Odijk Utrecht 3984 KT",
    "addr:housenumber":"2",
    "addr:postcode":"3984 kt",
    "addr:street":"Oude Haven",
    "iso:country":"NL",
    "sg:address":"Oude Haven 2",
    "sg:city":"Odijk",
    "sg:orig_category":"Kinderopvang Behalve Thuis",
    "sg:phone":"+31 30 657 0116",
    "sg:postcode":"3984 KT",
    "sg:province":"Utrecht",
    "wof:name":"Kinderopvang Stichting Bunnik",
    "wof:placetype":"venue"
},
  "geometry": {"coordinates":[5.236285,52.048473],"type":"Point"}
}