{
  "type": "Feature",
  "properties": {
    "addr:full":"Kerkplein 7 Breukelen Ut Utrecht 3621 BA",
    "addr:housenumber":"7",
    "addr:postcode":"3621 ba",
    "addr:street":"Kerkplein",
    "iso:country":"NL",
    "sg:address":"Kerkplein 7",
    "sg:city":"Breukelen Ut",
    "sg:orig_category":"Architecten",
    "sg:phone":"+31 346 264 048",
    "sg:postcode":"3621 BA",
    "sg:province":"Utrecht",
    "wof:name":"Ir C Hensbergen Architect",
    "wof:placetype":"venue"
},
  "geometry": {"coordinates":[5.001585,52.172958],"type":"Point"}
}