{
  "type": "Feature",
  "properties": {
    "addr:full":"Rosmolenstr 9/B Zaandam Noord-Holland 1502 PA",
    "addr:housenumber":"9 / b",
    "addr:postcode":"1502 pa",
    "addr:street":"Rosmolenstr",
    "iso:country":"NL",
    "sg:address":"Rosmolenstr 9/B",
    "sg:city":"Zaandam",
    "sg:orig_category":"Wassalons",
    "sg:phone":"+31 75 616 7104",
    "sg:postcode":"1502 PA",
    "sg:province":"Noord-Holland",
    "wof:name":"Rosmolen, De",
    "wof:placetype":"venue"
},
  "geometry": {"coordinates":[4.8257269859,52.4461021423],"type":"Point"}
}