{
  "type": "Feature",
  "properties": {
    "addr:full":"Binnenhof 86 Amstelveen Noord-Holland 1181 ZJ",
    "addr:housenumber":"86",
    "addr:postcode":"1181 zj",
    "addr:street":"Binnenhof",
    "iso:country":"NL",
    "sg:address":"Binnenhof 86",
    "sg:city":"Amstelveen",
    "sg:orig_category":"Juweliers",
    "sg:phone":"+31 20 645 4626",
    "sg:postcode":"1181 ZJ",
    "sg:province":"Noord-Holland",
    "wof:name":"Diamond",
    "wof:placetype":"venue"
},
  "geometry": {"coordinates":[4.862126,52.302593],"type":"Point"}
}