{
  "type": "Feature",
  "properties": {
    "iso:country":"NL",
    "sg:address":"Binnenhof 86",
    "sg:city":"Amstelveen",
    "sg:orig_category":"Juweliers",
    "sg:phone":"+31 20 645 4626",
    "sg:postcode":"1181 ZJ",
    "sg:province":"Noord-Holland",
    "wof:name":"Diamond",
    "wof:placetype":"venue"
},
  "geometry": {"coordinates":[4.862126,52.302593],"type":"Point"}
}