{
  "type": "Feature",
  "properties": {
    "iso:country":"NL",
    "sg:address":"Edisonstr 72",
    "sg:city":"Eindhoven",
    "sg:orig_category":"Cafetaria'S",
    "sg:phone":"+31 40 244 8044",
    "sg:postcode":"5621 HS",
    "sg:province":"North Brabant",
    "wof:name":"Edison Vof, De",
    "wof:placetype":"venue"
},
  "geometry": {"coordinates":[5.458344,51.453232],"type":"Point"}
}