{
  "type": "Feature",
  "properties": {
    "addr:full":"Raphaelpln 27 Amsterdam North Holland 1077 PX",
    "addr:housenumber":"27",
    "addr:postcode":"1077 px",
    "addr:street":"Raphaelpln",
    "iso:country":"NL",
    "sg:address":"Raphaelpln 27",
    "sg:city":"Amsterdam",
    "sg:orig_category":"Adviesbureaus Bedrijfsorganisatie",
    "sg:phone":"+31 20 452 8389",
    "sg:postcode":"1077 PX",
    "sg:province":"North Holland",
    "sg:website":"http://www.pentascope.nl",
    "wof:name":"Pentascope",
    "wof:placetype":"venue"
},
  "geometry": {"coordinates":[4.870106,52.348557],"type":"Point"}
}