{
  "type": "Feature",
  "properties": {
    "addr:full":"Hofstad 16 Gilze Noord-Brabant 5126 EV",
    "addr:housenumber":"16",
    "addr:street":"Hofstad",
    "iso:country":"NL",
    "sg:address":"Hofstad 16",
    "sg:city":"Gilze",
    "sg:orig_category":"Adviesbureaus Bedrijfsorganisatie",
    "sg:phone":"+31 161 454 130",
    "sg:postcode":"5126 EV",
    "sg:province":"Noord-Brabant",
    "wof:name":"Jobtrain",
    "wof:placetype":"venue"
},
  "geometry": {"coordinates":[4.947418,51.539482],"type":"Point"}
}