{
  "type": "Feature",
  "properties": {
    "iso:country":"NL",
    "sg:address":"De Lisdodde 4",
    "sg:city":"Zwartsluis",
    "sg:orig_category":"Personenvervoer Zonder Dienstregeling",
    "sg:phone":"+31 38 386 6049",
    "sg:postcode":"8064 HD",
    "sg:province":"Overijssel",
    "wof:name":"Van Egten'S Reisorganisatie",
    "wof:placetype":"venue"
},
  "geometry": {"coordinates":[6.074731,52.646111],"type":"Point"}
}