{
  "type": "Feature",
  "properties": {
    "addr:full":"Techniekweg 19 Leerdam Zuid-Holland 4143 HW",
    "addr:housenumber":"19",
    "addr:postcode":"4143 hw",
    "addr:street":"Techniekweg",
    "iso:country":"NL",
    "sg:address":"Techniekweg 19",
    "sg:city":"Leerdam",
    "sg:orig_category":"Loodgieterswerk, Verwarming And Sanitaire Installaties",
    "sg:phone":"+31 345 618 981",
    "sg:postcode":"4143 HW",
    "sg:province":"Zuid-Holland",
    "wof:name":"Pk-Perfekt Keukenmontage",
    "wof:placetype":"venue"
},
  "geometry": {"coordinates":[5.104083,51.901787],"type":"Point"}
}