{
  "type": "Feature",
  "properties": {
    "addr:full":"Claas Van Maarssenplein 14 Diemen Noord-Holland 1111 JE",
    "addr:housenumber":"14",
    "addr:postcode":"1111 je",
    "addr:street":"Claas;Maarssenplein",
    "iso:country":"NL",
    "sg:address":"Claas Van Maarssenplein 14",
    "sg:city":"Diemen",
    "sg:orig_category":"Juweliers",
    "sg:phone":"+31 20 690 3727",
    "sg:postcode":"1111 JE",
    "sg:province":"Noord-Holland",
    "wof:name":"Puttmann Juweliers",
    "wof:placetype":"venue"
},
  "geometry": {"coordinates":[4.963983,52.342499],"type":"Point"}
}