{
  "type": "Feature",
  "properties": {
    "addr:full":"Dr A Kuyperln 50 Bussum Noord-Holland 1402 SE",
    "addr:housenumber":"50;1402",
    "addr:street":"Dr;Kuyperln;Se",
    "iso:country":"NL",
    "sg:address":"Dr A Kuyperln 50",
    "sg:city":"Bussum",
    "sg:orig_category":"Voetbalverenigingen",
    "sg:phone":"+31 36 537 3404",
    "sg:postcode":"1402 SE",
    "sg:province":"Noord-Holland",
    "wof:name":"Gab",
    "wof:placetype":"venue"
},
  "geometry": {"coordinates":[5.175387,52.269192],"type":"Point"}
}