{
  "type": "Feature",
  "properties": {
    "iso:country":"NL",
    "sg:address":"Parallelweg 234",
    "sg:city":"Almelo",
    "sg:orig_category":"Verhuur Catering-, Feest- En Evenementbenodigdheden",
    "sg:phone":"+31 546 814 800",
    "sg:postcode":"7604 TR",
    "sg:province":"Overijssel",
    "wof:name":"Handelsonderneming Roal",
    "wof:placetype":"venue"
},
  "geometry": {"coordinates":[6.646564,52.36208],"type":"Point"}
}