{
  "type": "Feature",
  "properties": {
    "addr:full":"Het Hag 4 Zenderen Overijssel 7625 ST",
    "addr:housenumber":"4",
    "addr:postcode":"7625 st",
    "addr:street":"Het Hag",
    "iso:country":"NL",
    "sg:address":"Het Hag 4",
    "sg:city":"Zenderen",
    "sg:classifiers":[
        {
            "category":"Recreation",
            "subcategory":"Amusement Park",
            "type":"Entertainment"
        }
    ],
    "sg:phone":"+31 74 266 6056",
    "sg:postcode":"7625 ST",
    "sg:province":"Overijssel",
    "wof:name":"Ijsbaan Zenderen",
    "wof:placetype":"venue"
},
  "geometry": {"coordinates":[6.715616,52.318539],"type":"Point"}
}