{
  "type": "Feature",
  "properties": {
    "addr:full":"Heistr 1C Rysbergen North Brabant 4891 ZG",
    "addr:housenumber":"1c rysbergen",
    "addr:postcode":"4891 zg",
    "addr:street":"Heistr",
    "iso:country":"NL",
    "sg:address":"Heistr 1C",
    "sg:city":"Rysbergen",
    "sg:orig_category":"Fonteinen En Vijvers",
    "sg:phone":"+31 76 596 2107",
    "sg:postcode":"4891 ZG",
    "sg:province":"North Brabant",
    "wof:name":"Frijters, Louis",
    "wof:placetype":"venue"
},
  "geometry": {"coordinates":[4.684177,51.5093],"type":"Point"}
}