{
  "type": "Feature",
  "properties": {
    "addr:full":"Dr A Kuyperstr 80 Brunssum Limburg 6444 XT",
    "addr:housenumber":"80",
    "addr:postcode":"6444 xt",
    "addr:street":"Dr;Kuyperstr",
    "iso:country":"NL",
    "sg:address":"Dr A Kuyperstr 80",
    "sg:city":"Brunssum",
    "sg:orig_category":"Onderhoudswerken",
    "sg:phone":"+31 45 564 2070",
    "sg:postcode":"6444 XT",
    "sg:province":"Limburg",
    "wof:name":"Willems, Servi",
    "wof:placetype":"venue"
},
  "geometry": {"coordinates":[5.95681,50.935478],"type":"Point"}
}