{
  "type": "Feature",
  "properties": {
    "iso:country":"NL",
    "sg:address":"Hemingwayplaats 210",
    "sg:city":"Rotterdam",
    "sg:orig_category":"Onderhoudswerken",
    "sg:phone":"+31 10 420 6038",
    "sg:postcode":"3068 WS",
    "sg:province":"South Holland",
    "wof:name":"Stello, F",
    "wof:placetype":"venue"
},
  "geometry": {"coordinates":[4.553024,51.961765],"type":"Point"}
}