{
  "type": "Feature",
  "properties": {
    "addr:full":"Rutherfordweg 51 Utrecht Utrecht 3542 CN",
    "addr:housenumber":"51",
    "addr:postcode":"3542 cn",
    "addr:street":"Rutherfordweg",
    "iso:country":"NL",
    "sg:address":"Rutherfordweg 51",
    "sg:city":"Utrecht",
    "sg:orig_category":"Verhuisdiensten",
    "sg:phone":"+31 30 247 7300",
    "sg:postcode":"3542 CN",
    "sg:province":"Utrecht",
    "wof:name":"Convoi Europe Bv",
    "wof:placetype":"venue"
},
  "geometry": {"coordinates":[-73.996292,40.613091],"type":"Point"}
}