{
  "type": "Feature",
  "properties": {
    "addr:full":"Meijersplein-Noord 39 Rotterdam South Holland 3053 TE",
    "addr:housenumber":"39",
    "addr:postcode":"3053 te",
    "addr:street":"Meijersplein-Noord",
    "iso:country":"NL",
    "sg:address":"Meijersplein-Noord 39",
    "sg:city":"Rotterdam",
    "sg:classifiers":[
        {
            "category":"Fast Food",
            "type":"Food & Drink"
        }
    ],
    "sg:phone":"+31 10 418 6396",
    "sg:postcode":"3053 TE",
    "sg:province":"South Holland",
    "sg:tags":[
        "afhaal",
        "restaurant"
    ],
    "wof:name":"Cafetaria De Luifel",
    "wof:placetype":"venue"
},
  "geometry": {"coordinates":[4.46681,51.956421],"type":"Point"}
}