{
  "type": "Feature",
  "properties": {
    "addr:full":"Haagweg 18 Limbricht Limburg 6141 LX",
    "addr:housenumber":"18",
    "addr:postcode":"6141 lx",
    "addr:street":"Haagweg",
    "iso:country":"NL",
    "sg:address":"Haagweg 18",
    "sg:city":"Limbricht",
    "sg:orig_category":"Boekhouders",
    "sg:phone":"+31 46 452 1371",
    "sg:postcode":"6141 LX",
    "sg:province":"Limburg",
    "wof:name":"Administratiekantoor Van Sloun",
    "wof:placetype":"venue"
},
  "geometry": {"coordinates":[5.837979,51.009396],"type":"Point"}
}