{
  "type": "Feature",
  "properties": {
    "addr:full":"Europaweg 131 Zoetermeer Zuid-Holland 2711 EP",
    "addr:housenumber":"131",
    "addr:postcode":"2711 ep",
    "addr:street":"Europaweg",
    "iso:country":"NL",
    "sg:address":"Europaweg 131",
    "sg:city":"Zoetermeer",
    "sg:orig_category":"Drukkerijen And Copyshops",
    "sg:phone":"+31 79 342 1754",
    "sg:postcode":"2711 EP",
    "sg:province":"Zuid-Holland",
    "wof:name":"Multicopy",
    "wof:placetype":"venue"
},
  "geometry": {"coordinates":[4.492861,52.063553],"type":"Point"}
}