{
  "type": "Feature",
  "properties": {
    "iso:country":"NL",
    "sg:address":"Straatweg 35",
    "sg:city":"Maarssen",
    "sg:orig_category":"Metaalbekleding And -Behandeling",
    "sg:phone":"+31 346 562 692",
    "sg:postcode":"3603 CW",
    "sg:province":"Utrecht",
    "wof:name":"Geert Mattijssen Bv",
    "wof:placetype":"venue"
},
  "geometry": {"coordinates":[5.032412,52.149536],"type":"Point"}
}