{
  "type": "Feature",
  "properties": {
    "iso:country":"NL",
    "sg:address":"Isla Margaritastr 15",
    "sg:city":"Almere",
    "sg:orig_category":"Grafische Machines",
    "sg:phone":"+31 36 535 3475",
    "sg:postcode":"1339 ML",
    "sg:province":"NL.",
    "wof:name":"Gtt, Bur",
    "wof:placetype":"venue"
},
  "geometry": {"coordinates":[5.314489,52.395775],"type":"Point"}
}