{
  "type": "Feature",
  "properties": {
    "addr:full":"Meerwg 105 Haren Gn Groningen 9752 JE",
    "addr:housenumber":"105",
    "addr:postcode":"9752 je",
    "iso:country":"NL",
    "sg:address":"Meerwg 105",
    "sg:city":"Haren Gn",
    "sg:orig_category":"Autorijscholen",
    "sg:phone":"+31 50 534 9017",
    "sg:postcode":"9752 JE",
    "sg:province":"Groningen",
    "wof:name":"Hoving, T J Van",
    "wof:placetype":"venue"
},
  "geometry": {"coordinates":[6.596225,53.17075],"type":"Point"}
}