{
  "type": "Feature",
  "properties": {
    "addr:full":"Eiberpln 1H Bergschenhoek Zuid-Holland 2661 BP",
    "addr:housenumber":"1h",
    "addr:postcode":"2661 bp",
    "iso:country":"NL",
    "sg:address":"Eiberpln 1H",
    "sg:city":"Bergschenhoek",
    "sg:orig_category":"Verenigingen En Stichtingen",
    "sg:phone":"+31 10 521 9124",
    "sg:postcode":"2661 BP",
    "sg:province":"Zuid-Holland",
    "sg:website":"http://www.anbo.nl",
    "wof:name":"Anbo",
    "wof:placetype":"venue"
},
  "geometry": {"coordinates":[4.501254,51.983238],"type":"Point"}
}