{
  "type": "Feature",
  "properties": {
    "addr:full":"Weteringschans 24 Amsterdam Noord-Holland 1017 SG",
    "addr:housenumber":"24",
    "addr:postcode":"1017 sg",
    "addr:street":"Weteringschans",
    "iso:country":"NL",
    "sg:address":"Weteringschans 24",
    "sg:city":"Amsterdam",
    "sg:orig_category":"Luchtvaart",
    "sg:phone":"+31 20 627 7394",
    "sg:postcode":"1017 SG",
    "sg:province":"Noord-Holland",
    "wof:name":"Malaysian Airlines",
    "wof:placetype":"venue"
},
  "geometry": {"coordinates":[4.886177,52.361206],"type":"Point"}
}