{
  "type": "Feature",
  "properties": {
    "iso:country":"NL",
    "sg:address":"Vechtstr 171Hs",
    "sg:city":"Amsterdam",
    "sg:orig_category":"Vertaalbureaus",
    "sg:phone":"+31 20 644 9437",
    "sg:postcode":"1079 JH",
    "sg:province":"North Holland",
    "wof:name":"Taal & Term",
    "wof:placetype":"venue"
},
  "geometry": {"coordinates":[4.90826,52.341377],"type":"Point"}
}