{
  "type": "Feature",
  "properties": {
    "addr:full":"Pr Bernhardstr 17 Ooltgensplaat Zuid-Holland 3257 AT",
    "addr:housenumber":"17",
    "addr:postcode":"3257",
    "iso:country":"NL",
    "sg:address":"Pr Bernhardstr 17",
    "sg:city":"Ooltgensplaat",
    "sg:orig_category":"Kappers",
    "sg:phone":"+31 187 631 788",
    "sg:postcode":"3257 AT",
    "sg:province":"Zuid-Holland",
    "wof:name":"Suzanne",
    "wof:placetype":"venue"
},
  "geometry": {"coordinates":[4.345289,51.681187],"type":"Point"}
}