{
  "type": "Feature",
  "properties": {
    "addr:full":"Stationsstraat 34 Vleuten Utrecht 3451 BZ",
    "addr:housenumber":"34",
    "addr:postcode":"3451 bz",
    "addr:street":"Stationsstraat",
    "iso:country":"NL",
    "sg:address":"Stationsstraat 34",
    "sg:city":"Vleuten",
    "sg:orig_category":"Kappers",
    "sg:phone":"+31 30 677 1263",
    "sg:postcode":"3451 BZ",
    "sg:province":"Utrecht",
    "wof:name":"A J Van Zoeren",
    "wof:placetype":"venue"
},
  "geometry": {"coordinates":[5.0120081902,52.1039047241],"type":"Point"}
}