{
  "type": "Feature",
  "properties": {
    "addr:full":"Sternstraat 22 Purmerend Noord-Holland 1444 VB",
    "addr:housenumber":"22",
    "addr:postcode":"1444 vb",
    "addr:street":"Sternstraat",
    "iso:country":"NL",
    "sg:address":"Sternstraat 22",
    "sg:city":"Purmerend",
    "sg:orig_category":"Advocaten And Juridische Adviseurs",
    "sg:phone":"+31 299 430 054",
    "sg:postcode":"1444 VB",
    "sg:province":"Noord-Holland",
    "wof:name":"Advocatenkantoor Mr. A. Boerwinkel",
    "wof:placetype":"venue"
},
  "geometry": {"coordinates":[4.958113,52.520256],"type":"Point"}
}