{
  "type": "Feature",
  "properties": {
    "addr:full":"Generaal Snijdersstraat 8 Helmond Noord-Brabant 5703 GS",
    "addr:housenumber":"8",
    "addr:postcode":"5703 gs",
    "addr:street":"Generaal Snijdersstraat",
    "iso:country":"NL",
    "sg:address":"Generaal Snijdersstraat 8",
    "sg:city":"Helmond",
    "sg:orig_category":"Beautyfarms And Sauna'S",
    "sg:phone":"+31 492 524 818",
    "sg:postcode":"5703 GS",
    "sg:province":"Noord-Brabant",
    "wof:name":"Christel",
    "wof:placetype":"venue"
},
  "geometry": {"coordinates":[5.678524,51.483463],"type":"Point"}
}