{
  "type": "Feature",
  "properties": {
    "addr:full":"Provincialewg 101D Heiligerlee Groningen 9677 PC",
    "addr:housenumber":"101d",
    "addr:postcode":"9677 pc",
    "addr:street":"Provincialewg",
    "iso:country":"NL",
    "sg:address":"Provincialewg 101D",
    "sg:city":"Heiligerlee",
    "sg:orig_category":"Banden",
    "sg:phone":"+31 597 413 650",
    "sg:postcode":"9677 PC",
    "sg:province":"Groningen",
    "sg:website":"http://www.kalk-banden.nl",
    "wof:name":"Kalk Banden Bv",
    "wof:placetype":"venue"
},
  "geometry": {"coordinates":[7.012711,53.154793],"type":"Point"}
}