{
  "type": "Feature",
  "properties": {
    "addr:full":"Postbus 310 Lelystad Flevoland 8200 AH",
    "addr:housenumber":"310",
    "addr:postcode":"8200 ah",
    "addr:street":"Postbus;Flevoland",
    "iso:country":"NL",
    "sg:address":"Postbus 310",
    "sg:city":"Lelystad",
    "sg:orig_category":"Luchtvaartelektronica",
    "sg:phone":"+31 320 232 168",
    "sg:postcode":"8200 AH",
    "sg:province":"Flevoland",
    "wof:name":"Dac International Inc",
    "wof:placetype":"venue"
},
  "geometry": {"coordinates":[5.47403,52.50568],"type":"Point"}
}