{
  "type": "Feature",
  "properties": {
    "addr:full":"A Kuyperpk 3 Nieuwegein Utrecht 3437 JA",
    "addr:housenumber":"3",
    "addr:postcode":"3437 ja",
    "iso:country":"NL",
    "sg:address":"A Kuyperpk 3",
    "sg:city":"Nieuwegein",
    "sg:orig_category":"Verzekeringen - Verzekeringskantoren",
    "sg:phone":"+31 30 280 0600",
    "sg:postcode":"3437 JA",
    "sg:province":"Utrecht",
    "wof:name":"Jager, Assurantiekantoor De",
    "wof:placetype":"venue"
},
  "geometry": {"coordinates":[5.080755,52.05394],"type":"Point"}
}