{
  "type": "Feature",
  "properties": {
    "iso:country":"NL",
    "sg:address":"Asingaln 6",
    "sg:city":"Middelstum",
    "sg:orig_category":"Postkantoren",
    "sg:phone":"+31 595 551 960",
    "sg:postcode":"9991 AJ",
    "sg:province":"Groningen",
    "sg:website":"http://www.postkantoor.nl",
    "wof:name":"Postkantoor",
    "wof:placetype":"venue"
},
  "geometry": {"coordinates":[6.644237,53.348579],"type":"Point"}
}