{
  "type": "Feature",
  "properties": {
    "addr:full":"Hoogeinde 22 Waalwyk Noord-Brabant 5142 GC",
    "addr:housenumber":"22",
    "addr:postcode":"5142 gc",
    "addr:street":"Hoogeinde",
    "iso:country":"NL",
    "sg:address":"Hoogeinde 22",
    "sg:city":"Waalwyk",
    "sg:orig_category":"Homeopathie",
    "sg:phone":"+31 416 355 150",
    "sg:postcode":"5142 GC",
    "sg:province":"Noord-Brabant",
    "wof:name":"Karoena",
    "wof:placetype":"venue"
},
  "geometry": {"coordinates":[5.095465,51.693909],"type":"Point"}
}