{
  "type": "Feature",
  "properties": {
    "addr:full":"Groningenhaven 4 Nieuwegein Utrecht 3433 PE",
    "addr:housenumber":"4",
    "addr:postcode":"3433 pe",
    "addr:street":"Groningenhaven",
    "iso:country":"NL",
    "sg:address":"Groningenhaven 4",
    "sg:city":"Nieuwegein",
    "sg:orig_category":"Bedrijfsopleidingen",
    "sg:phone":"+31 30 601 8150",
    "sg:postcode":"3433 PE",
    "sg:province":"Utrecht",
    "sg:website":"http://www.tectum.nl",
    "wof:name":"Tectum",
    "wof:placetype":"venue"
},
  "geometry": {"coordinates":[5.10375,52.019451],"type":"Point"}
}