{
  "type": "Feature",
  "properties": {
    "addr:full":"Pr Beatrixln 31 Apeldoorn Gelderland 7314 KP",
    "addr:housenumber":"31",
    "addr:postcode":"7314 kp",
    "addr:street":"Gelderland",
    "iso:country":"NL",
    "sg:address":"Pr Beatrixln 31",
    "sg:city":"Apeldoorn",
    "sg:orig_category":"Adviesbureaus Bedrijfsorganisatie",
    "sg:phone":"+31 55 578 8648",
    "sg:postcode":"7314 KP",
    "sg:province":"Gelderland",
    "wof:name":"Jong & Breeuwsma Bv, De",
    "wof:placetype":"venue"
},
  "geometry": {"coordinates":[5.947591,52.214497],"type":"Point"}
}