{
  "type": "Feature",
  "properties": {
    "iso:country":"NL",
    "sg:address":"Pasweg 24",
    "sg:city":"Landgraaf",
    "sg:orig_category":"Parfum And Cosmetica Gh",
    "sg:phone":"+31 45 569 0450",
    "sg:postcode":"6371 BN",
    "sg:province":"Limburg",
    "wof:name":"Meurs Trading Cosmetics",
    "wof:placetype":"venue"
},
  "geometry": {"coordinates":[6.01668,50.899555],"type":"Point"}
}