{
  "type": "Feature",
  "properties": {
    "addr:full":"Pasweg 24 Landgraaf Limburg 6371 BN",
    "addr:housenumber":"24",
    "addr:postcode":"6371 bn",
    "addr:street":"Pasweg",
    "iso:country":"NL",
    "sg:address":"Pasweg 24",
    "sg:city":"Landgraaf",
    "sg:orig_category":"Parfum And Cosmetica Gh",
    "sg:phone":"+31 45 569 0450",
    "sg:postcode":"6371 BN",
    "sg:province":"Limburg",
    "wof:name":"Meurs Trading Cosmetics",
    "wof:placetype":"venue"
},
  "geometry": {"coordinates":[6.01668,50.899555],"type":"Point"}
}