{
  "type": "Feature",
  "properties": {
    "addr:full":"Boezelgracht 17 Volendam Noord-Holland 1132 PE",
    "addr:housenumber":"17",
    "addr:postcode":"1132 pe",
    "addr:street":"Boezelgracht",
    "iso:country":"NL",
    "sg:address":"Boezelgracht 17",
    "sg:city":"Volendam",
    "sg:orig_category":"Boekhouders",
    "sg:phone":"+31 299 362 377",
    "sg:postcode":"1132 PE",
    "sg:province":"Noord-Holland",
    "wof:name":"Administratiekantoor H.M. Schilder",
    "wof:placetype":"venue"
},
  "geometry": {"coordinates":[5.062691,52.50359],"type":"Point"}
}