{
  "type": "Feature",
  "properties": {
    "addr:full":"Koolmeeshaag 23 Houten Utrecht 3993 AL",
    "addr:housenumber":"23",
    "addr:postcode":"3993 al",
    "addr:street":"Koolmeeshaag",
    "iso:country":"NL",
    "sg:address":"Koolmeeshaag 23",
    "sg:city":"Houten",
    "sg:orig_category":"Adviesbureaus Bouwkunde",
    "sg:phone":"+31 30 635 1963",
    "sg:postcode":"3993 AL",
    "sg:province":"Utrecht",
    "wof:name":"Faust",
    "wof:placetype":"venue"
},
  "geometry": {"coordinates":[5.167457,52.038403],"type":"Point"}
}