{
  "type": "Feature",
  "properties": {
    "iso:country":"NL",
    "sg:address":"Koningin Emmalaan 20",
    "sg:city":"Leerdam",
    "sg:orig_category":"Notarissen",
    "sg:phone":"+31 345 615 641",
    "sg:postcode":"4141 EC",
    "sg:province":"Zuid-Holland",
    "wof:name":"Mr. H. Beugelink Notariskantoor",
    "wof:placetype":"venue"
},
  "geometry": {"coordinates":[5.09935,51.89312],"type":"Point"}
}