{
  "type": "Feature",
  "properties": {
    "iso:country":"NL",
    "sg:address":"Gerichtenweg 27",
    "sg:city":"Doornspijk",
    "sg:orig_category":"Metaalwerken",
    "sg:phone":"+31 525 682 676",
    "sg:postcode":"8085 PW",
    "sg:province":"Gelderland",
    "wof:name":"Bosch Zonwering / Rolluiken V/H Klobozon",
    "wof:placetype":"venue"
},
  "geometry": {"coordinates":[5.839097,52.431801],"type":"Point"}
}