{
  "type": "Feature",
  "properties": {
    "iso:country":"NL",
    "sg:address":"V Balverenwg 61",
    "sg:city":"Bennekom",
    "sg:orig_category":"Accountants - Administratie- Consulenten En -Kantoren",
    "sg:phone":"+31 318 415 292",
    "sg:postcode":"6721 ZV",
    "sg:province":"Gelderland",
    "wof:name":"Veldhuizen, Van",
    "wof:placetype":"venue"
},
  "geometry": {"coordinates":[5.675792,52.000942],"type":"Point"}
}