{
  "type": "Feature",
  "properties": {
    "addr:full":"Schelluinsestr 1 Gorinchem Zuid-Holland 4203 NJ",
    "addr:housenumber":"1",
    "addr:postcode":"4203 nj",
    "addr:street":"Schelluinsestr",
    "iso:country":"NL",
    "sg:address":"Schelluinsestr 1",
    "sg:city":"Gorinchem",
    "sg:orig_category":"Kunststoffen- Verwerkende Industrie",
    "sg:phone":"+31 183 650 650",
    "sg:postcode":"4203 NJ",
    "sg:province":"Zuid-Holland",
    "sg:website":"http://www.attema.nl",
    "wof:name":"Attema Bv",
    "wof:placetype":"venue"
},
  "geometry": {"coordinates":[4.961937,51.832024],"type":"Point"}
}