{
  "type": "Feature",
  "properties": {
    "iso:country":"NL",
    "sg:address":"Ambachtsplein 115",
    "sg:city":"Rotterdam",
    "sg:orig_category":"Banken And Kredietinstellingen",
    "sg:phone":"+31 10 456 3692",
    "sg:postcode":"3068 GV",
    "sg:province":"South Holland",
    "wof:name":"Postkantoor",
    "wof:placetype":"venue"
},
  "geometry": {"coordinates":[4.569624,51.965298],"type":"Point"}
}