{
  "type": "Feature",
  "properties": {
    "addr:full":"Sevenumsewg 6 Maasbree Limburg 5993 NZ",
    "addr:housenumber":"6",
    "addr:postcode":"5993 nz",
    "addr:street":"Sevenumsewg",
    "iso:country":"NL",
    "sg:address":"Sevenumsewg 6",
    "sg:city":"Maasbree",
    "sg:orig_category":"Organisatiebureaus",
    "sg:phone":"+31 77 465 4377",
    "sg:postcode":"5993 NZ",
    "sg:province":"Limburg",
    "wof:name":"Goeie Zaak",
    "wof:placetype":"venue"
},
  "geometry": {"coordinates":[170.3666381836,-43.5877113342],"type":"Point"}
}