{
  "type": "Feature",
  "properties": {
    "addr:full":"Ekkersryt 4089 Son Texas 5692 DB",
    "addr:postcode":"4089;5692 db",
    "addr:street":"Texas",
    "iso:country":"NL",
    "sg:address":"Ekkersryt 4089",
    "sg:city":"Son",
    "sg:orig_category":"Woninginrichting",
    "sg:phone":"+31 900 2354532",
    "sg:postcode":"5692 DB",
    "sg:province":"Texas",
    "sg:website":"http://www.ikea.nl",
    "wof:name":"Ikea Bv",
    "wof:placetype":"venue"
},
  "geometry": {"coordinates":[-101.93762207029999,35.1896209717],"type":"Point"}
}