{
  "type": "Feature",
  "properties": {
    "addr:full":"Vogelenzang 5 Zaltbommel Gelderland 5301 ER",
    "addr:housenumber":"5",
    "addr:postcode":"5301 er",
    "addr:street":"Vogelenzang;Gelderland",
    "iso:country":"NL",
    "sg:address":"Vogelenzang 5",
    "sg:city":"Zaltbommel",
    "sg:orig_category":"Plafonds",
    "sg:phone":"+31 418 514 729",
    "sg:postcode":"5301 ER",
    "sg:province":"Gelderland",
    "wof:name":"Welsing Zaltbommel",
    "wof:placetype":"venue"
},
  "geometry": {"coordinates":[5.25342,51.812729],"type":"Point"}
}