{
  "type": "Feature",
  "properties": {
    "iso:country":"NL",
    "sg:address":"Oosthoutpln 7",
    "sg:city":"Voorhout",
    "sg:orig_category":"Bloemen En Planten",
    "sg:phone":"+31 252 219 078",
    "sg:postcode":"2215 VM",
    "sg:province":"Zuid-Holland",
    "wof:name":"Vergeet Mij Nietje, Het",
    "wof:placetype":"venue"
},
  "geometry": {"coordinates":[4.491591,52.221718],"type":"Point"}
}