{
  "type": "Feature",
  "properties": {
    "iso:country":"NL",
    "sg:address":"Boerendanserdijk 31",
    "sg:city":"Zwolle",
    "sg:orig_category":"Farmaceutische Producten Gh",
    "sg:phone":"+31 38 455 0646",
    "sg:postcode":"8024 AE",
    "sg:province":"NL.08",
    "wof:name":"A.D. Jansen Zwolle Bv",
    "wof:placetype":"venue"
},
  "geometry": {"coordinates":[6.121246,52.519161],"type":"Point"}
}