{
  "type": "Feature",
  "properties": {
    "addr:full":"Koningsweg 14-16 Groningen Groningen 9731 AT",
    "addr:housenumber":"14-16",
    "addr:postcode":"9731",
    "addr:street":"Koningsweg",
    "iso:country":"NL",
    "sg:address":"Koningsweg 14-16",
    "sg:city":"Groningen",
    "sg:orig_category":"Meubelzaken, Woning- And Keukeninrichting",
    "sg:phone":"+31 50 542 1896",
    "sg:postcode":"9731 AT",
    "sg:province":"Groningen",
    "wof:name":"T Blankhoutenhuis",
    "wof:placetype":"venue"
},
  "geometry": {"coordinates":[6.60527,53.226185],"type":"Point"}
}