{
  "type": "Feature",
  "properties": {
    "iso:country":"NL",
    "sg:address":"Sternstr 21",
    "sg:city":"Uitgeest",
    "sg:orig_category":"Psychotherapeuten",
    "sg:phone":"+31 251 316 539",
    "sg:postcode":"1911 WJ",
    "sg:province":"North Holland",
    "wof:name":"Mw Drs E Mandema, Inzicht-Gerichte Psychotherapie",
    "wof:placetype":"venue"
},
  "geometry": {"coordinates":[4.706731,52.533421],"type":"Point"}
}