{
  "type": "Feature",
  "properties": {
    "addr:full":"Klinkertstr 112 Hoensbroek Limburg 6433 PB",
    "addr:housenumber":"112",
    "addr:postcode":"6433 pb",
    "addr:street":"Hoensbroek Limburg",
    "iso:country":"NL",
    "sg:address":"Klinkertstr 112",
    "sg:city":"Hoensbroek",
    "sg:orig_category":"Ballonvaarten En -Reclame",
    "sg:phone":"+31 45 574 2440",
    "sg:postcode":"6433 PB",
    "sg:province":"Limburg",
    "sg:website":"http://www.europeanballooncompany.com",
    "wof:name":"European Balloon Company",
    "wof:placetype":"venue"
},
  "geometry": {"coordinates":[5.91726,50.916393],"type":"Point"}
}