{
  "type": "Feature",
  "properties": {
    "addr:full":"Papenweg 58 Bunde Limburg 6241 BV",
    "addr:housenumber":"58",
    "addr:postcode":"6241 bv",
    "addr:street":"Papenweg",
    "iso:country":"NL",
    "sg:address":"Papenweg 58",
    "sg:city":"Bunde",
    "sg:orig_category":"Artsen And Specialisten",
    "sg:phone":"+31 43 364 8935",
    "sg:postcode":"6241 BV",
    "sg:province":"Limburg",
    "wof:name":"J.A.I.M. Swaans",
    "wof:placetype":"venue"
},
  "geometry": {"coordinates":[5.733195,50.895042],"type":"Point"}
}