{
  "type": "Feature",
  "properties": {
    "addr:full":"Pastoor Spieringslaan 1 Heeze Noord-Brabant 5591 CT",
    "addr:housenumber":"1",
    "addr:postcode":"5591 ct",
    "addr:street":"Pastoor Spieringslaan",
    "iso:country":"NL",
    "sg:address":"Pastoor Spieringslaan 1",
    "sg:city":"Heeze",
    "sg:orig_category":"Verzekeringen",
    "sg:phone":"+31 40 226 4556",
    "sg:postcode":"5591 CT",
    "sg:province":"Noord-Brabant",
    "wof:name":"Dick Guitjens Assurantien",
    "wof:placetype":"venue"
},
  "geometry": {"coordinates":[5.576045,51.386868],"type":"Point"}
}