{
  "type": "Feature",
  "properties": {
    "addr:full":"Bloemendaalsewg 95 Bloemendaal Noord-Holland 2061 CE",
    "addr:housenumber":"95",
    "addr:postcode":"2061 ce",
    "addr:street":"Bloemendaalsewg",
    "iso:country":"NL",
    "sg:address":"Bloemendaalsewg 95",
    "sg:city":"Bloemendaal",
    "sg:orig_category":"Juweliers",
    "sg:phone":"+31 23 525 2527",
    "sg:postcode":"2061 CE",
    "sg:province":"Noord-Holland",
    "sg:website":"http://www.goud-smederij.nl",
    "wof:name":"Arnold Van Dodewaard, Goudsmederij/Juwelier",
    "wof:placetype":"venue"
},
  "geometry": {"coordinates":[4.62048,52.404278],"type":"Point"}
}