{
  "type": "Feature",
  "properties": {
    "addr:full":"Belt 63 Hippolytushoef North Holland 1777 HG",
    "addr:housenumber":"63",
    "addr:postcode":"1777 hg",
    "addr:street":"Belt",
    "iso:country":"NL",
    "sg:address":"Belt 63",
    "sg:city":"Hippolytushoef",
    "sg:orig_category":"Fruitteelt",
    "sg:phone":"+31 227 593 247",
    "sg:postcode":"1777 HG",
    "sg:province":"North Holland",
    "wof:name":"Mevr. K.A. Bakker-Slagter",
    "wof:placetype":"venue"
},
  "geometry": {"coordinates":[4.954912,52.904957],"type":"Point"}
}