{
  "type": "Feature",
  "properties": {
    "addr:full":"Noordeinde 36 'S Gravenhage Zuid-Holland 2514 GJ",
    "addr:housenumber":"36",
    "addr:postcode":"2514 gj",
    "addr:street":"Noordeinde;' S",
    "iso:country":"NL",
    "sg:address":"Noordeinde 36",
    "sg:city":"'S Gravenhage",
    "sg:orig_category":"Herenmodezaken",
    "sg:phone":"+31 70 346 3512",
    "sg:postcode":"2514 GJ",
    "sg:province":"Zuid-Holland",
    "wof:name":"Z-Mode Bv",
    "wof:placetype":"venue"
},
  "geometry": {"coordinates":[4.307858,52.080032],"type":"Point"}
}