{
  "type": "Feature",
  "properties": {
    "addr:full":"J C Kellerln 22A Hardenberg Overijssel 7772 SG",
    "addr:housenumber":"22a",
    "addr:postcode":"7772 sg",
    "addr:street":"J C Kellerln",
    "iso:country":"NL",
    "sg:address":"J C Kellerln 22A",
    "sg:city":"Hardenberg",
    "sg:orig_category":"Schilders",
    "sg:phone":"+31 523 266 663",
    "sg:postcode":"7772 SG",
    "sg:province":"Overijssel",
    "wof:name":"Dijk Bv, Van",
    "wof:placetype":"venue"
},
  "geometry": {"coordinates":[6.622884,52.57534],"type":"Point"}
}