{
  "type": "Feature",
  "properties": {
    "addr:full":"V Neckstr 9 S Gravenhage Zuid-Holland 2597 SB",
    "addr:housenumber":"9 s",
    "addr:postcode":"2597 sb",
    "addr:street":"Neckstr",
    "iso:country":"NL",
    "sg:address":"V Neckstr 9",
    "sg:city":"S Gravenhage",
    "sg:orig_category":"Adviesbureaus Bedrijfsorganisatie",
    "sg:phone":"+31 70 324 4980",
    "sg:postcode":"2597 SB",
    "sg:province":"Zuid-Holland",
    "wof:name":"Down To Earth",
    "wof:placetype":"venue"
},
  "geometry": {"coordinates":[4.31817,52.11031],"type":"Point"}
}