{
  "type": "Feature",
  "properties": {
    "addr:full":"Kaldebornwg 38 Heerlen Limburg 6416 HC",
    "addr:housenumber":"38",
    "addr:postcode":"6416 hc",
    "addr:street":"Kaldebornwg",
    "iso:country":"NL",
    "sg:address":"Kaldebornwg 38",
    "sg:city":"Heerlen",
    "sg:orig_category":"Accountants - Administratie- Consulenten En -Kantoren",
    "sg:phone":"+31 45 571 1915",
    "sg:postcode":"6416 HC",
    "sg:province":"Limburg",
    "wof:name":"Wilms",
    "wof:placetype":"venue"
},
  "geometry": {"coordinates":[5.991257,50.877609],"type":"Point"}
}