{
  "type": "Feature",
  "properties": {
    "iso:country":"NL",
    "sg:address":"Gravestein 17",
    "sg:city":"Gouda",
    "sg:orig_category":"Bedrijfs- And Managementsconsultants",
    "sg:phone":"+31 6 51157630",
    "sg:postcode":"2804 GR",
    "sg:province":"Zuid-Holland",
    "wof:name":"Liberty Business Solutions",
    "wof:placetype":"venue"
},
  "geometry": {"coordinates":[4.708031,52.030468],"type":"Point"}
}