{
  "type": "Feature",
  "properties": {
    "addr:full":"Wilhelminapark 19 Haarlem North Holland 2012 KB",
    "addr:housenumber":"19",
    "addr:postcode":"2012 kb",
    "addr:street":"Wilhelminapark",
    "iso:country":"NL",
    "sg:address":"Wilhelminapark 19",
    "sg:city":"Haarlem",
    "sg:orig_category":"Werving And Selectie Van Vast Personeel",
    "sg:phone":"+31 23 532 6066",
    "sg:postcode":"2012 KB",
    "sg:province":"North Holland",
    "wof:name":"Joy",
    "wof:placetype":"venue"
},
  "geometry": {"coordinates":[4.6233410835,52.3713531494],"type":"Point"}
}