{
  "type": "Feature",
  "properties": {
    "addr:full":"J J V Goyenstr 10 Nederhorst D Berg Noord-Holland 1394 EP",
    "addr:housenumber":"10",
    "addr:postcode":"1394 ep",
    "addr:street":"Goyenstr;Nederhorst D Berg",
    "iso:country":"NL",
    "sg:address":"J J V Goyenstr 10",
    "sg:city":"Nederhorst D Berg",
    "sg:orig_category":"Verpakkingen En Verpakkingsmaterialen",
    "sg:phone":"+31 294 254 379",
    "sg:postcode":"1394 EP",
    "sg:province":"Noord-Holland",
    "wof:name":"Correct Pack",
    "wof:placetype":"venue"
},
  "geometry": {"coordinates":[-121.624138,39.182121],"type":"Point"}
}