{
  "type": "Feature",
  "properties": {
    "addr:full":"Langewg 34 Apeldoorn Gelderland 7315 CX",
    "addr:housenumber":"34",
    "addr:postcode":"7315 cx",
    "addr:street":"Langewg;Gelderland",
    "iso:country":"NL",
    "sg:address":"Langewg 34",
    "sg:city":"Apeldoorn",
    "sg:orig_category":"Machineonderhoud En -Reparatie",
    "sg:phone":"+31 55 522 6308",
    "sg:postcode":"7315 CX",
    "sg:province":"Gelderland",
    "wof:name":"Clarinda",
    "wof:placetype":"venue"
},
  "geometry": {"coordinates":[5.952361,52.227669],"type":"Point"}
}