{
  "type": "Feature",
  "properties": {
    "addr:full":"Dorpsweg 19 Sommelsdijk Zuid-Holland 3245 VA",
    "addr:housenumber":"19",
    "addr:postcode":"3245",
    "addr:street":"Dorpsweg",
    "iso:country":"NL",
    "sg:address":"Dorpsweg 19",
    "sg:city":"Sommelsdijk",
    "sg:orig_category":"Woningbouwverenigingen",
    "sg:phone":"+31 187 484 110",
    "sg:postcode":"3245 VA",
    "sg:province":"Zuid-Holland",
    "wof:name":"Bouwvereniging Sommelsdijk",
    "wof:placetype":"venue"
},
  "geometry": {"coordinates":[4.1500020027,51.7573814392],"type":"Point"}
}