{
  "type": "Feature",
  "properties": {
    "iso:country":"NL",
    "sg:address":"Centauruswg 119",
    "sg:city":"Tilburg",
    "sg:orig_category":"Sanitaire Artikelen - Fabrieken En Groothandel",
    "sg:phone":"+31 13 458 3300",
    "sg:postcode":"5015 TC",
    "sg:province":"Noord-Brabant",
    "wof:name":"Vegro Bv",
    "wof:placetype":"venue"
},
  "geometry": {"coordinates":[5.10943,51.581661],"type":"Point"}
}