{
  "type": "Feature",
  "properties": {
    "addr:full":"Centaurusstr 20 Zw Haarlem Noord-Holland 2024 VL",
    "addr:housenumber":"20 zw",
    "addr:postcode":"2024 vl",
    "addr:street":"Centaurusstr",
    "iso:country":"NL",
    "sg:address":"Centaurusstr 20 Zw",
    "sg:city":"Haarlem",
    "sg:orig_category":"Parketvloeren",
    "sg:phone":"+31 23 525 8919",
    "sg:postcode":"2024 VL",
    "sg:province":"Noord-Holland",
    "wof:name":"Hoogenraad, W",
    "wof:placetype":"venue"
},
  "geometry": {"coordinates":[4.63761,52.40593],"type":"Point"}
}