{
  "type": "Feature",
  "properties": {
    "addr:full":"Edesew 156 Wekerom Gelderland 6733 AJ",
    "addr:housenumber":"156",
    "addr:postcode":"6733 aj",
    "addr:street":"Gelderland",
    "iso:country":"NL",
    "sg:address":"Edesew 156",
    "sg:city":"Wekerom",
    "sg:orig_category":"Warenhuizen",
    "sg:phone":"+31 318 461 294",
    "sg:postcode":"6733 AJ",
    "sg:province":"Gelderland",
    "wof:name":"Elbertsen, J",
    "wof:placetype":"venue"
},
  "geometry": {"coordinates":[5.7189650536,52.1137580872],"type":"Point"}
}