{
  "type": "Feature",
  "properties": {
    "addr:full":"J Israelsln 361 Ryswyk Zh Zuid-Holland 2282 TJ",
    "addr:housenumber":"361",
    "addr:postcode":"2282 tj",
    "addr:street":"Ryswyk",
    "iso:country":"NL",
    "sg:address":"J Israelsln 361",
    "sg:city":"Ryswyk Zh",
    "sg:orig_category":"Modevakscholen",
    "sg:phone":"+31 70 395 0709",
    "sg:postcode":"2282 TJ",
    "sg:province":"Zuid-Holland",
    "wof:name":"Tonny Vos",
    "wof:placetype":"venue"
},
  "geometry": {"coordinates":[4.33694,52.056503],"type":"Point"}
}