{
  "type": "Feature",
  "properties": {
    "addr:full":"Gruttosingel 30 'S-Gravenhage South Holland 2496 HW",
    "addr:housenumber":"30",
    "addr:postcode":"2496 hw",
    "addr:street":"Gruttosingel",
    "iso:country":"NL",
    "sg:address":"Gruttosingel 30",
    "sg:city":"'S-Gravenhage",
    "sg:orig_category":"Keukens",
    "sg:phone":"+31 6 53790130",
    "sg:postcode":"2496 HW",
    "sg:province":"South Holland",
    "wof:name":"Hofstra",
    "wof:placetype":"venue"
},
  "geometry": {"coordinates":[4.379275,52.050385],"type":"Point"}
}