{
  "type": "Feature",
  "properties": {
    "addr:full":"Rodeschuurderwegje 15 Ermelo Gelderland 3853 LR",
    "addr:housenumber":"15",
    "addr:postcode":"3853 lr",
    "addr:street":"Rodeschuurderwegje;Gelderland",
    "iso:country":"NL",
    "sg:address":"Rodeschuurderwegje 15",
    "sg:city":"Ermelo",
    "sg:orig_category":"Kantoorapparatuur Gh",
    "sg:phone":"+31 341 552 495",
    "sg:postcode":"3853 LR",
    "sg:province":"Gelderland",
    "wof:name":"Holland Business Copiers",
    "wof:placetype":"venue"
},
  "geometry": {"coordinates":[5.5856180191,52.3086280823],"type":"Point"}
}