{
  "type": "Feature",
  "properties": {
    "addr:full":"Spiegelstr 15B Zwolle NL.08 8011 VE",
    "addr:housenumber":"15b",
    "addr:postcode":"8011",
    "addr:street":"Spiegelstr;Ve",
    "iso:country":"NL",
    "sg:address":"Spiegelstr 15B",
    "sg:city":"Zwolle",
    "sg:orig_category":"Zoetwaren - Winkels",
    "sg:phone":"+31 38 421 5841",
    "sg:postcode":"8011 VE",
    "sg:province":"NL.08",
    "wof:name":"Jamin Bv",
    "wof:placetype":"venue"
},
  "geometry": {"coordinates":[6.094285,52.513184],"type":"Point"}
}