{
  "type": "Feature",
  "properties": {
    "iso:country":"NL",
    "sg:address":"Spiegelstr 15B",
    "sg:city":"Zwolle",
    "sg:orig_category":"Zoetwaren - Winkels",
    "sg:phone":"+31 38 421 5841",
    "sg:postcode":"8011 VE",
    "sg:province":"NL.08",
    "wof:name":"Jamin Bv",
    "wof:placetype":"venue"
},
  "geometry": {"coordinates":[6.094285,52.513184],"type":"Point"}
}