{
  "type": "Feature",
  "properties": {
    "addr:full":"G Stephensonstr 4 Zwolle Overijssel 8013 NK",
    "addr:housenumber":"4",
    "addr:postcode":"8013 nk",
    "iso:country":"NL",
    "sg:address":"G Stephensonstr 4",
    "sg:city":"Zwolle",
    "sg:orig_category":"Keukens",
    "sg:phone":"+31 38 460 1440",
    "sg:postcode":"8013 NK",
    "sg:province":"Overijssel",
    "sg:website":"http://www.brugman.nl",
    "wof:name":"Brugman",
    "wof:placetype":"venue"
},
  "geometry": {"coordinates":[6.118439,52.493889],"type":"Point"}
}