{
  "type": "Feature",
  "properties": {
    "addr:full":"Postbus 5 Loosdrecht Noord-Holland 1230 AA",
    "addr:housenumber":"5",
    "addr:postcode":"1230 aa",
    "addr:street":"Postbus",
    "iso:country":"NL",
    "sg:address":"Postbus 5",
    "sg:city":"Loosdrecht",
    "sg:orig_category":"Geluidsopnamestudio'S",
    "sg:phone":"+31 35 582 6583",
    "sg:postcode":"1230 AA",
    "sg:province":"Noord-Holland",
    "wof:name":"Byton Studio'S Bv",
    "wof:placetype":"venue"
},
  "geometry": {"coordinates":[5.13527,52.199959],"type":"Point"}
}