{
  "type": "Feature",
  "properties": {
    "addr:full":"Nw Fellenoord 60 Eindhoven North Brabant 5612 KD",
    "addr:housenumber":"60",
    "addr:postcode":"5612 kd",
    "addr:street":"Nw Fellenoord",
    "iso:country":"NL",
    "sg:address":"Nw Fellenoord 60",
    "sg:city":"Eindhoven",
    "sg:orig_category":"Fotojournalisten Freelance",
    "sg:phone":"+31 40 244 6723",
    "sg:postcode":"5612 KD",
    "sg:province":"North Brabant",
    "wof:name":"Loosbroek, Maarten Van",
    "wof:placetype":"venue"
},
  "geometry": {"coordinates":[5.471986,51.447029],"type":"Point"}
}