{
  "type": "Feature",
  "properties": {
    "addr:full":"M Stokezyde 216 S Gravenhage Zuid-Holland 2543 GM",
    "addr:housenumber":"216;gravenhage",
    "addr:postcode":"2543 gm",
    "addr:street":"S",
    "iso:country":"NL",
    "sg:address":"M Stokezyde 216",
    "sg:city":"S Gravenhage",
    "sg:orig_category":"Administratie- En Boekhoudkantoren",
    "sg:phone":"+31 70 338 9125",
    "sg:postcode":"2543 GM",
    "sg:province":"Zuid-Holland",
    "wof:name":"Feenstra Bv",
    "wof:placetype":"venue"
},
  "geometry": {"coordinates":[4.26264,52.040501],"type":"Point"}
}