{
  "type": "Feature",
  "properties": {
    "iso:country":"NL",
    "sg:address":"Ginnekenweg 161",
    "sg:city":"Breda",
    "sg:orig_category":"Verzekeringen",
    "sg:phone":"+31 76 524 4260",
    "sg:postcode":"4818 JD",
    "sg:province":"Noord-Brabant",
    "wof:name":"Van Der Kolk Hypotheken",
    "wof:placetype":"venue"
},
  "geometry": {"coordinates":[4.783434,51.573887],"type":"Point"}
}