{
  "type": "Feature",
  "properties": {
    "addr:full":"Kranenberg 19 Tilburg Noord-Brabant 5047 TR",
    "addr:housenumber":"19",
    "addr:postcode":"5047 tr",
    "addr:street":"Kranenberg",
    "iso:country":"NL",
    "sg:address":"Kranenberg 19",
    "sg:city":"Tilburg",
    "sg:orig_category":"Zeilmakerijen",
    "sg:phone":"+31 13 571 5229",
    "sg:postcode":"5047 TR",
    "sg:province":"Noord-Brabant",
    "wof:name":"Beerens Zeilmakerij",
    "wof:placetype":"venue"
},
  "geometry": {"coordinates":[5.021498,51.588757],"type":"Point"}
}