{
  "type": "Feature",
  "properties": {
    "iso:country":"NL",
    "sg:address":"Dusartstr 28",
    "sg:city":"Amsterdam",
    "sg:orig_category":"Bedrijfskleding",
    "sg:phone":"+31 20 679 9612",
    "sg:postcode":"1072 HS",
    "sg:province":"Noord-Holland",
    "wof:name":"Titia",
    "wof:placetype":"venue"
},
  "geometry": {"coordinates":[4.889046,52.352161],"type":"Point"}
}