{
  "type": "Feature",
  "properties": {
    "addr:full":"De Genestetstr 98 Leiden Zuid-Holland 2321 XT",
    "addr:housenumber":"98",
    "addr:postcode":"2321 xt",
    "iso:country":"NL",
    "sg:address":"De Genestetstr 98",
    "sg:city":"Leiden",
    "sg:orig_category":"Vertaalbureaus",
    "sg:phone":"+31 71 531 1855",
    "sg:postcode":"2321 XT",
    "sg:province":"Zuid-Holland",
    "wof:name":"Marechal, E G M",
    "wof:placetype":"venue"
},
  "geometry": {"coordinates":[4.476847,52.156944],"type":"Point"}
}