{
  "type": "Feature",
  "properties": {
    "addr:full":"Esdoorn 26B Maastricht Limburg 6226 TA",
    "addr:housenumber":"26b",
    "addr:postcode":"6226 ta",
    "addr:street":"Esdoorn",
    "iso:country":"NL",
    "sg:address":"Esdoorn 26B",
    "sg:city":"Maastricht",
    "sg:orig_category":"Verhuur Audiovisuele Apparatuur",
    "sg:phone":"+31 43 363 7630",
    "sg:postcode":"6226 TA",
    "sg:province":"Limburg",
    "wof:name":"Holiday Disco Shows",
    "wof:placetype":"venue"
},
  "geometry": {"coordinates":[5.733878,50.843887],"type":"Point"}
}