{
  "type": "Feature",
  "properties": {
    "addr:full":"Vierakkerstraat 57 Huissen Gelderland 6851 BD",
    "addr:housenumber":"57",
    "addr:postcode":"6851 bd",
    "addr:street":"Vierakkerstraat;Gelderland",
    "iso:country":"NL",
    "sg:address":"Vierakkerstraat 57",
    "sg:city":"Huissen",
    "sg:orig_category":"Kappers",
    "sg:phone":"+31 26 325 1138",
    "sg:postcode":"6851 BD",
    "sg:province":"Gelderland",
    "wof:name":"Kop-Art",
    "wof:placetype":"venue"
},
  "geometry": {"coordinates":[5.943026,51.936813],"type":"Point"}
}