{
  "type": "Feature",
  "properties": {
    "addr:full":"Vennew 40 Goirle Noord-Brabant 5051 BP",
    "addr:housenumber":"40",
    "addr:postcode":"5051 bp",
    "addr:street":"Vennew",
    "iso:country":"NL",
    "sg:address":"Vennew 40",
    "sg:city":"Goirle",
    "sg:orig_category":"Bejaarden - Verzorgingstehuizen",
    "sg:phone":"+31 13 534 3266",
    "sg:postcode":"5051 BP",
    "sg:province":"Noord-Brabant",
    "wof:name":"Vennerode",
    "wof:placetype":"venue"
},
  "geometry": {"coordinates":[5.058358,51.528175],"type":"Point"}
}