{
  "type": "Feature",
  "properties": {
    "addr:full":"Zeewijkplein 149 Ijmuiden Noord-Holland 1974 PA",
    "addr:housenumber":"149",
    "addr:postcode":"1974 pa",
    "addr:street":"Zeewijkplein",
    "iso:country":"NL",
    "sg:address":"Zeewijkplein 149",
    "sg:city":"Ijmuiden",
    "sg:orig_category":"Bibliotheken And Openbare Archieven",
    "sg:phone":"+31 255 516 046",
    "sg:postcode":"1974 PA",
    "sg:province":"Noord-Holland",
    "wof:name":"Openbare Bibliotheek Zeewijk",
    "wof:placetype":"venue"
},
  "geometry": {"coordinates":[-77.604507,40.99464],"type":"Point"}
}