{
  "type": "Feature",
  "properties": {
    "iso:country":"NL",
    "sg:address":"Wilhelminaplein 3",
    "sg:city":"Heerlen",
    "sg:orig_category":"Opticiens",
    "sg:phone":"+31 45 571 7517",
    "sg:postcode":"6411 KV",
    "sg:province":"Limburg",
    "wof:name":"Piet Van Kempen",
    "wof:placetype":"venue"
},
  "geometry": {"coordinates":[5.9805159569,50.8885154724],"type":"Point"}
}