{
  "type": "Feature",
  "properties": {
    "iso:country":"NL",
    "sg:address":"Gaffelvoorde 16",
    "sg:city":"Spijkenisse",
    "sg:orig_category":"Verhuur Bouwmachines",
    "sg:phone":"+31 181 643 727",
    "sg:postcode":"3204 EB",
    "sg:province":"Zuid-Holland",
    "wof:name":"Sbs Vof",
    "wof:placetype":"venue"
},
  "geometry": {"coordinates":[4.324368,51.836128],"type":"Point"}
}