{
  "type": "Feature",
  "properties": {
    "iso:country":"NL",
    "sg:address":"Bilderdykstr 124",
    "sg:city":"Amsterdam",
    "sg:orig_category":"Bloemen En Planten",
    "sg:phone":"+31 20 683 4687",
    "sg:postcode":"1053 KZ",
    "sg:province":"Noord-Holland",
    "wof:name":"Bouwman, Klaas",
    "wof:placetype":"venue"
},
  "geometry": {"coordinates":[4.871112,52.36832],"type":"Point"}
}