{
  "type": "Feature",
  "properties": {
    "addr:full":"Herenstr 24 Breukelen Ut Utrecht 3621 AR",
    "addr:housenumber":"24",
    "addr:postcode":"3621",
    "addr:street":"Herenstr",
    "iso:country":"NL",
    "sg:address":"Herenstr 24",
    "sg:city":"Breukelen Ut",
    "sg:orig_category":"Kappers",
    "sg:phone":"+31 346 261 651",
    "sg:postcode":"3621 AR",
    "sg:province":"Utrecht",
    "wof:name":"Pleijster",
    "wof:placetype":"venue"
},
  "geometry": {"coordinates":[5.003629,52.172565],"type":"Point"}
}