{
  "type": "Feature",
  "properties": {
    "addr:full":"Steenweg 80 Sittard Limburg 6131 BH",
    "addr:housenumber":"80",
    "addr:postcode":"6131 bh",
    "addr:street":"Steenweg",
    "iso:country":"NL",
    "sg:address":"Steenweg 80",
    "sg:city":"Sittard",
    "sg:orig_category":"Medische Apparatuur And Prothesen Fab",
    "sg:phone":"+31 46 458 6939",
    "sg:postcode":"6131 BH",
    "sg:province":"Limburg",
    "wof:name":"Beter Horen",
    "wof:placetype":"venue"
},
  "geometry": {"coordinates":[5.861808,51.001034],"type":"Point"}
}