{
  "type": "Feature",
  "properties": {
    "iso:country":"NL",
    "sg:address":"Veerplaat 10",
    "sg:city":"Dordrecht",
    "sg:orig_category":"Opslag Inboedels",
    "sg:phone":"+31 78 630 5100",
    "sg:postcode":"3313 LJ",
    "sg:province":"Zuid-Holland",
    "sg:website":"http://www.shurgard.nl",
    "wof:name":"Shurgard Dordrecht",
    "wof:placetype":"venue"
},
  "geometry": {"coordinates":[4.7124400139,51.8186531067],"type":"Point"}
}