{
  "type": "Feature",
  "properties": {
    "iso:country":"NL",
    "sg:address":"St Jorispln 38",
    "sg:city":"Ridderkerk",
    "sg:orig_category":"Opticiens",
    "sg:phone":"+31 180 425 956",
    "sg:postcode":"2981 GC",
    "sg:province":"South Holland",
    "wof:name":"Kind Juwelier-Optiek Bv",
    "wof:placetype":"venue"
},
  "geometry": {"coordinates":[4.6021699905,51.8699188232],"type":"Point"}
}