{
  "type": "Feature",
  "properties": {
    "addr:full":"Janninkswg 161 Enschede Overijssel 7513 DJ",
    "addr:housenumber":"161",
    "addr:postcode":"7513 dj",
    "iso:country":"NL",
    "sg:address":"Janninkswg 161",
    "sg:city":"Enschede",
    "sg:orig_category":"Elektronica - Ontwikkeling En Groothandel",
    "sg:phone":"+31 53 430 4854",
    "sg:postcode":"7513 DJ",
    "sg:province":"Overijssel",
    "wof:name":"Hls Security Systems",
    "wof:placetype":"venue"
},
  "geometry": {"coordinates":[6.878167,52.215759],"type":"Point"}
}