{
  "type": "Feature",
  "properties": {
    "addr:full":"Nobelstr 150 Apeldoorn Gelderland 7316 GR",
    "addr:housenumber":"150",
    "addr:postcode":"7316",
    "addr:street":"Gelderland",
    "iso:country":"NL",
    "sg:address":"Nobelstr 150",
    "sg:city":"Apeldoorn",
    "sg:orig_category":"Webdesign Bureaus",
    "sg:phone":"+31 55 577 5640",
    "sg:postcode":"7316 GR",
    "sg:province":"Gelderland",
    "sg:website":"http://www.catchit.nl",
    "wof:name":"Catch-It",
    "wof:placetype":"venue"
},
  "geometry": {"coordinates":[5.9618020058,52.230091095],"type":"Point"}
}