{
  "type": "Feature",
  "properties": {
    "addr:full":"De Riet 5 Grypskerk Groningen 9843 AR",
    "addr:housenumber":"5",
    "addr:postcode":"9843",
    "addr:street":"De Riet",
    "iso:country":"NL",
    "sg:address":"De Riet 5",
    "sg:city":"Grypskerk",
    "sg:orig_category":"Houtindustrie",
    "sg:phone":"+31 594 213 977",
    "sg:postcode":"9843 AR",
    "sg:province":"Groningen",
    "sg:website":"http://www.hiemstrahoutbouw.nl",
    "wof:name":"Hiemstra Houtbouw Bv",
    "wof:placetype":"venue"
},
  "geometry": {"coordinates":[6.304651,53.26685],"type":"Point"}
}