{
  "type": "Feature",
  "properties": {
    "iso:country":"NL",
    "sg:address":"Haspelstr 1",
    "sg:city":"Zevenaar",
    "sg:orig_category":"Schoenen",
    "sg:phone":"+31 316 340 947",
    "sg:postcode":"6901 EX",
    "sg:province":"Gelderland",
    "sg:website":"http://www.scapino.nl",
    "wof:name":"Scapino",
    "wof:placetype":"venue"
},
  "geometry": {"coordinates":[6.076101,51.930927],"type":"Point"}
}