{
  "type": "Feature",
  "properties": {
    "addr:full":"Eindhovenseweg 30C Best Noord-Brabant 5683 KH",
    "addr:housenumber":"30c",
    "addr:postcode":"5683 kh",
    "addr:street":"Eindhovenseweg",
    "iso:country":"NL",
    "sg:address":"Eindhovenseweg 30C",
    "sg:city":"Best",
    "sg:orig_category":"Meubelzaken, Woning- And Keukeninrichting",
    "sg:phone":"+31 499 397 601",
    "sg:postcode":"5683 KH",
    "sg:province":"Noord-Brabant",
    "wof:name":"Beddenspeciaalzaak Boonman",
    "wof:placetype":"venue"
},
  "geometry": {"coordinates":[5.402838,51.512852],"type":"Point"}
}