{
  "type": "Feature",
  "properties": {
    "addr:full":"Pleimuiden 16E Amsterdam Noord-Holland 1046 AG",
    "addr:housenumber":"16e",
    "addr:postcode":"1046",
    "addr:street":"Pleimuiden",
    "iso:country":"NL",
    "sg:address":"Pleimuiden 16E",
    "sg:city":"Amsterdam",
    "sg:orig_category":"Koffie, Thee And Specerijen Gh",
    "sg:phone":"+31 20 647 3877",
    "sg:postcode":"1046 AG",
    "sg:province":"Noord-Holland",
    "wof:name":"Berkhoff Koffie En Thee Bv",
    "wof:placetype":"venue"
},
  "geometry": {"coordinates":[4.786775,52.390362],"type":"Point"}
}