{
  "type": "Feature",
  "properties": {
    "addr:full":"Steensedijk 43 Hulst Zeeland 4561 GL",
    "addr:housenumber":"43",
    "addr:postcode":"4561 gl",
    "addr:street":"Steensedijk",
    "iso:country":"NL",
    "sg:address":"Steensedijk 43",
    "sg:city":"Hulst",
    "sg:orig_category":"Goederenvervoer Over De Weg",
    "sg:phone":"+31 114 314 863",
    "sg:postcode":"4561 GL",
    "sg:province":"Zeeland",
    "wof:name":"Firma P.B. Everaard & Zonen",
    "wof:placetype":"venue"
},
  "geometry": {"coordinates":[4.049325,51.273655],"type":"Point"}
}