{
  "type": "Feature",
  "properties": {
    "iso:country":"NL",
    "sg:address":"Ravendal 16",
    "sg:city":"Terheyden",
    "sg:orig_category":"Bedrijfskleding",
    "sg:phone":"+31 6 20604652",
    "sg:postcode":"4844 VE",
    "sg:province":"North Brabant",
    "sg:website":"http://www.bedrijfskleding.net",
    "wof:name":"Alltex",
    "wof:placetype":"venue"
},
  "geometry": {"coordinates":[4.759123,51.641102],"type":"Point"}
}