{
  "type": "Feature",
  "properties": {
    "iso:country":"NL",
    "sg:address":"Maaspoort 15",
    "sg:city":"Weert",
    "sg:orig_category":"Meubelzaken, Woning- And Keukeninrichting",
    "sg:phone":"+31 495 540 923",
    "sg:postcode":"6001 BN",
    "sg:province":"Limburg",
    "wof:name":"Paquay Wonen",
    "wof:placetype":"venue"
},
  "geometry": {"coordinates":[5.710965,51.251949],"type":"Point"}
}