{
  "type": "Feature",
  "properties": {
    "addr:full":"Kerkstraat Noord 4 Oeffelt Noord-Brabant 5441 BH",
    "addr:housenumber":"4",
    "addr:postcode":"5441 bh",
    "addr:street":"Kerkstraat Noord",
    "iso:country":"NL",
    "sg:address":"Kerkstraat Noord 4",
    "sg:city":"Oeffelt",
    "sg:orig_category":"Architecten",
    "sg:phone":"+31 485 362 448",
    "sg:postcode":"5441 BH",
    "sg:province":"Noord-Brabant",
    "wof:name":"E Van Amstel",
    "wof:placetype":"venue"
},
  "geometry": {"coordinates":[5.932832,51.699589],"type":"Point"}
}