{
  "type": "Feature",
  "properties": {
    "iso:country":"NL",
    "sg:address":"Pr Beatrixln 1E",
    "sg:city":"Uitgeest",
    "sg:orig_category":"Kinderkleding",
    "sg:phone":"+31 251 312 789",
    "sg:postcode":"1911 HP",
    "sg:province":"Noord-Holland",
    "wof:name":"Young Ones, The",
    "wof:placetype":"venue"
},
  "geometry": {"coordinates":[4.709879,52.525089],"type":"Point"}
}