{
  "type": "Feature",
  "properties": {
    "addr:full":"Stationsstraat 8 Markelo Overijssel 7475 AM",
    "addr:housenumber":"8",
    "addr:postcode":"7475",
    "addr:street":"Stationsstraat",
    "iso:country":"NL",
    "sg:address":"Stationsstraat 8",
    "sg:city":"Markelo",
    "sg:orig_category":"Public Relationbureaus",
    "sg:phone":"+31 547 362 413",
    "sg:postcode":"7475 AM",
    "sg:province":"Overijssel",
    "wof:name":"Marwilsel",
    "wof:placetype":"venue"
},
  "geometry": {"coordinates":[6.495465,52.233341],"type":"Point"}
}