{
  "type": "Feature",
  "properties": {
    "addr:full":"Kwakernaak 6 Nieuwland Zuid-Holland 4243 JK",
    "addr:housenumber":"6",
    "addr:postcode":"4243 jk",
    "addr:street":"Kwakernaak",
    "iso:country":"NL",
    "sg:address":"Kwakernaak 6",
    "sg:city":"Nieuwland",
    "sg:orig_category":"Ongediertebestrijding En Ontsmetting",
    "sg:phone":"+31 183 353 146",
    "sg:postcode":"4243 JK",
    "sg:province":"Zuid-Holland",
    "wof:name":"Boer, A",
    "wof:placetype":"venue"
},
  "geometry": {"coordinates":[5.012075,51.902039],"type":"Point"}
}