{
  "type": "Feature",
  "properties": {
    "addr:full":"Kerkewijk 66 Veenendaal Utrecht 3904 JE",
    "addr:housenumber":"66",
    "addr:postcode":"3904 je",
    "addr:street":"Kerkewijk",
    "iso:country":"NL",
    "sg:address":"Kerkewijk 66",
    "sg:city":"Veenendaal",
    "sg:orig_category":"Kappers",
    "sg:phone":"+31 318 512 251",
    "sg:postcode":"3904 JE",
    "sg:province":"Utrecht",
    "wof:name":"Vof Kapsalon Van De Kraats",
    "wof:placetype":"venue"
},
  "geometry": {"coordinates":[5.54805,52.017078],"type":"Point"}
}