{
  "type": "Feature",
  "properties": {
    "addr:full":"Wilaarderburen 3 Leeuwarden Provincie Friesland 8924 JK",
    "addr:housenumber":"3",
    "addr:postcode":"8924 jk",
    "addr:street":"Wilaarderburen;Provincie Friesland",
    "iso:country":"NL",
    "sg:address":"Wilaarderburen 3",
    "sg:city":"Leeuwarden",
    "sg:orig_category":"Kinderopvang",
    "sg:phone":"+31 58 266 8013",
    "sg:postcode":"8924 JK",
    "sg:province":"Provincie Friesland",
    "wof:name":"Bernestate",
    "wof:placetype":"venue"
},
  "geometry": {"coordinates":[5.831358,53.203304],"type":"Point"}
}