{
  "type": "Feature",
  "properties": {
    "addr:full":"Foekenln 11 Soest Utrecht 3768 BJ",
    "addr:housenumber":"11",
    "addr:postcode":"3768 bj",
    "addr:street":"Foekenln",
    "iso:country":"NL",
    "sg:address":"Foekenln 11",
    "sg:city":"Soest",
    "sg:orig_category":"Adviesbureaus Bouwkunde",
    "sg:phone":"+31 35 602 9137",
    "sg:postcode":"3768 BJ",
    "sg:province":"Utrecht",
    "wof:name":"Eri Bv",
    "wof:placetype":"venue"
},
  "geometry": {"coordinates":[5.30052,52.145535],"type":"Point"}
}