{
  "type": "Feature",
  "properties": {
    "addr:full":"Uitwg 10A Krommenie Noord-Holland 1562 GA",
    "addr:housenumber":"10a",
    "addr:postcode":"1562 ga",
    "addr:street":"Uitwg",
    "iso:country":"NL",
    "sg:address":"Uitwg 10A",
    "sg:city":"Krommenie",
    "sg:orig_category":"Administratie- En Boekhoudkantoren",
    "sg:phone":"+31 75 621 7969",
    "sg:postcode":"1562 GA",
    "sg:province":"Noord-Holland",
    "wof:name":"Dijker, W M L",
    "wof:placetype":"venue"
},
  "geometry": {"coordinates":[4.77058,52.509193],"type":"Point"}
}