{
  "type": "Feature",
  "properties": {
    "addr:full":"Handelskade 4 Urk NL. 8321 KB",
    "addr:housenumber":"4",
    "addr:postcode":"8321 kb",
    "addr:street":"Handelskade;Nl.",
    "iso:country":"NL",
    "sg:address":"Handelskade 4",
    "sg:city":"Urk",
    "sg:orig_category":"Opticiens",
    "sg:phone":"+31 527 682 549",
    "sg:postcode":"8321 KB",
    "sg:province":"NL.",
    "wof:name":"Korf Optiek",
    "wof:placetype":"venue"
},
  "geometry": {"coordinates":[5.5994749069,52.6605300903],"type":"Point"}
}