{
  "type": "Feature",
  "properties": {
    "addr:full":"H Neynensstr 8 Weert Limburg 6001 SW",
    "addr:housenumber":"8;6001",
    "addr:street":"Weert Limburg;Sw",
    "iso:country":"NL",
    "sg:address":"H Neynensstr 8",
    "sg:city":"Weert",
    "sg:orig_category":"Verzekeringen - Verzekeringskantoren",
    "sg:phone":"+31 495 540 149",
    "sg:postcode":"6001 SW",
    "sg:province":"Limburg",
    "wof:name":"Weekers",
    "wof:placetype":"venue"
},
  "geometry": {"coordinates":[5.698055,51.252605],"type":"Point"}
}