{
  "type": "Feature",
  "properties": {
    "iso:country":"NL",
    "sg:address":"H Neynensstr 8",
    "sg:city":"Weert",
    "sg:orig_category":"Verzekeringen - Verzekeringskantoren",
    "sg:phone":"+31 495 540 149",
    "sg:postcode":"6001 SW",
    "sg:province":"Limburg",
    "wof:name":"Weekers",
    "wof:placetype":"venue"
},
  "geometry": {"coordinates":[5.698055,51.252605],"type":"Point"}
}