{
  "type": "Feature",
  "properties": {
    "addr:full":"Nieuwe Tielseweg 69 Tiel Gelderland 4001 JT",
    "addr:housenumber":"69",
    "addr:postcode":"4001 jt",
    "addr:street":"Nieuwe Tielseweg;Gelderland",
    "iso:country":"NL",
    "sg:address":"Nieuwe Tielseweg 69",
    "sg:city":"Tiel",
    "sg:orig_category":"Meubelzaken, Woning- And Keukeninrichting",
    "sg:phone":"+31 344 630 573",
    "sg:postcode":"4001 JT",
    "sg:province":"Gelderland",
    "wof:name":"Sliepen Interieur",
    "wof:placetype":"venue"
},
  "geometry": {"coordinates":[5.429184,51.882309],"type":"Point"}
}