{
  "type": "Feature",
  "properties": {
    "addr:full":"H Mulertstr 22 Ommen Overijssel 7731 CL",
    "addr:housenumber":"22",
    "addr:postcode":"7731",
    "iso:country":"NL",
    "sg:address":"H Mulertstr 22",
    "sg:city":"Ommen",
    "sg:orig_category":"Bejaarden - Verzorgingstehuizen",
    "sg:phone":"+31 529 469 000",
    "sg:postcode":"7731 CL",
    "sg:province":"Overijssel",
    "wof:name":"Oldenhaghen",
    "wof:placetype":"venue"
},
  "geometry": {"coordinates":[6.429512,52.519066],"type":"Point"}
}