{
  "type": "Feature",
  "properties": {
    "addr:full":"Marconiwg 31 Zeewolde Flevoland 3899 BR",
    "addr:housenumber":"31;3899",
    "addr:postcode":"br",
    "addr:street":"Marconiwg;Flevoland",
    "iso:country":"NL",
    "sg:address":"Marconiwg 31",
    "sg:city":"Zeewolde",
    "sg:orig_category":"Organisatiebureaus",
    "sg:phone":"+31 36 535 8020",
    "sg:postcode":"3899 BR",
    "sg:province":"Flevoland",
    "wof:name":"Akubra Bv",
    "wof:placetype":"venue"
},
  "geometry": {"coordinates":[5.5017228127,52.3506889343],"type":"Point"}
}