{
  "type": "Feature",
  "properties": {
    "addr:full":"Op De Klucht 22 Uithoorn Noord-Holland 1422 KT",
    "addr:housenumber":"22",
    "addr:postcode":"1422 kt",
    "addr:street":"Op De Klucht",
    "iso:country":"NL",
    "sg:address":"Op De Klucht 22",
    "sg:city":"Uithoorn",
    "sg:orig_category":"Bloemen And Planten Gh",
    "sg:phone":"+31 297 566 756",
    "sg:postcode":"1422 KT",
    "sg:province":"Noord-Holland",
    "wof:name":"H. Van Buren Handelsonderneming",
    "wof:placetype":"venue"
},
  "geometry": {"coordinates":[4.818697,52.254227],"type":"Point"}
}