{
  "type": "Feature",
  "properties": {
    "addr:full":"Amsterdamstraat 15 Haarlem Noord-Holland 2032 PM",
    "addr:housenumber":"15",
    "addr:postcode":"2032 pm",
    "addr:street":"Amsterdamstraat",
    "iso:country":"NL",
    "sg:address":"Amsterdamstraat 15",
    "sg:city":"Haarlem",
    "sg:orig_category":"Banken And Kredietinstellingen",
    "sg:phone":"+31 23 536 0002",
    "sg:postcode":"2032 PM",
    "sg:province":"Noord-Holland",
    "wof:name":"Postkantoor",
    "wof:placetype":"venue"
},
  "geometry": {"coordinates":[4.647415,52.380035],"type":"Point"}
}