{
  "type": "Feature",
  "properties": {
    "addr:full":"Roermondseweg 175 Weert Limburg 6005 NJ",
    "addr:housenumber":"175",
    "addr:postcode":"6005 nj",
    "addr:street":"Roermondseweg",
    "iso:country":"NL",
    "sg:address":"Roermondseweg 175",
    "sg:city":"Weert",
    "sg:orig_category":"Makelaars In Onroerend Goed",
    "sg:phone":"+31 495 552 012",
    "sg:postcode":"6005 NJ",
    "sg:province":"Limburg",
    "wof:name":"Concordon Belegging Bv Weert",
    "wof:placetype":"venue"
},
  "geometry": {"coordinates":[5.772335,51.239452],"type":"Point"}
}