{
  "type": "Feature",
  "properties": {
    "addr:full":"J Muyskenwg 136 Amsterdam North Holland 1099 CK",
    "addr:housenumber":"136",
    "addr:postcode":"1099 ck",
    "iso:country":"NL",
    "sg:address":"J Muyskenwg 136",
    "sg:city":"Amsterdam",
    "sg:orig_category":"Paardensport",
    "sg:phone":"+31 20 665 4835",
    "sg:postcode":"1099 CK",
    "sg:province":"North Holland",
    "sg:website":"http://www.jumping-amsterdam.nl",
    "wof:name":"Jumping Amsterdam",
    "wof:placetype":"venue"
},
  "geometry": {"coordinates":[4.92788,52.320251],"type":"Point"}
}