{
  "type": "Feature",
  "properties": {
    "addr:full":"Herengracht 407 Amsterdam Noord-Holland 1017 BP",
    "addr:housenumber":"407",
    "addr:postcode":"1017 bp",
    "addr:street":"Herengracht",
    "iso:country":"NL",
    "sg:address":"Herengracht 407",
    "sg:city":"Amsterdam",
    "sg:orig_category":"Architecten",
    "sg:phone":"+31 20 625 1067",
    "sg:postcode":"1017 BP",
    "sg:province":"Noord-Holland",
    "wof:name":"Keek Architectenatelier",
    "wof:placetype":"venue"
},
  "geometry": {"coordinates":[4.887405,52.367668],"type":"Point"}
}