{
  "type": "Feature",
  "properties": {
    "addr:full":"Mr Tydemanstr 14 Tiel Gelderland 4001 CS",
    "addr:housenumber":"14",
    "addr:postcode":"4001 cs",
    "addr:street":"Gelderland",
    "iso:country":"NL",
    "sg:address":"Mr Tydemanstr 14",
    "sg:city":"Tiel",
    "sg:orig_category":"Loodgieters- Benodigdheden",
    "sg:phone":"+31 344 643 544",
    "sg:postcode":"4001 CS",
    "sg:province":"Gelderland",
    "wof:name":"Rom",
    "wof:placetype":"venue"
},
  "geometry": {"coordinates":[5.426075,51.887852],"type":"Point"}
}