{
  "type": "Feature",
  "properties": {
    "addr:full":"V L Stirumstr 30 S Gravenhage Zuid-Holland 2515 PG",
    "addr:housenumber":"30;gravenhage",
    "addr:postcode":"2515 pg",
    "addr:street":"V;S",
    "iso:country":"NL",
    "sg:address":"V L Stirumstr 30",
    "sg:city":"S Gravenhage",
    "sg:orig_category":"Kappers",
    "sg:phone":"+31 70 388 0837",
    "sg:postcode":"2515 PG",
    "sg:province":"Zuid-Holland",
    "wof:name":"Limburg Stirum Salon, Van",
    "wof:placetype":"venue"
},
  "geometry": {"coordinates":[4.31741,52.083988],"type":"Point"}
}