{
  "type": "Feature",
  "properties": {
    "addr:full":"Krayenhoffln 23 Heemskerk Noord-Holland 1965 AD",
    "addr:housenumber":"23",
    "addr:postcode":"1965 ad",
    "addr:street":"Krayenhoffln",
    "iso:country":"NL",
    "sg:address":"Krayenhoffln 23",
    "sg:city":"Heemskerk",
    "sg:orig_category":"Administratie- En Boekhoudkantoren",
    "sg:phone":"+31 251 216 610",
    "sg:postcode":"1965 AD",
    "sg:province":"Noord-Holland",
    "wof:name":"Ck",
    "wof:placetype":"venue"
},
  "geometry": {"coordinates":[4.654775,52.498997],"type":"Point"}
}