{
  "type": "Feature",
  "properties": {
    "addr:full":"Op E Wal 9 Warns Friesland 8721 GJ",
    "addr:housenumber":"9",
    "addr:postcode":"8721 gj",
    "addr:street":"Op E Wal",
    "iso:country":"NL",
    "sg:address":"Op E Wal 9",
    "sg:city":"Warns",
    "sg:orig_category":"Scheepssleep- En Duwvaart",
    "sg:phone":"+31 514 681 291",
    "sg:postcode":"8721 GJ",
    "sg:province":"Friesland",
    "wof:name":"Aqua Power",
    "wof:placetype":"venue"
},
  "geometry": {"coordinates":[-83.884407,34.997856],"type":"Point"}
}