{
  "type": "Feature",
  "properties": {
    "addr:full":"Tydensstr 40 Veendam Groningen 9641 CD",
    "addr:housenumber":"40",
    "addr:postcode":"9641 cd",
    "addr:street":"Tydensstr",
    "iso:country":"NL",
    "sg:address":"Tydensstr 40",
    "sg:city":"Veendam",
    "sg:orig_category":"Zonne-Energie",
    "sg:phone":"+31 598 623 416",
    "sg:postcode":"9641 CD",
    "sg:province":"Groningen",
    "sg:website":"http://www.globalsolarconsulting.nl",
    "wof:name":"Global Solar Consulting",
    "wof:placetype":"venue"
},
  "geometry": {"coordinates":[6.887117,53.108147],"type":"Point"}
}