{
  "type": "Feature",
  "properties": {
    "iso:country":"NL",
    "sg:address":"Friedaln 90",
    "sg:city":"Zwanenburg",
    "sg:orig_category":"Adviesbureaus Bedrijfsorganisatie",
    "sg:phone":"+31 20 497 3077",
    "sg:postcode":"1161 TP",
    "sg:province":"North Holland",
    "wof:name":"Resa Bv",
    "wof:placetype":"venue"
},
  "geometry": {"coordinates":[4.74723,52.376625],"type":"Point"}
}