{
  "type": "Feature",
  "properties": {
    "addr:full":"Sierkersstr 7 Schagen Noord-Holland 1741 SH",
    "addr:housenumber":"7",
    "addr:postcode":"1741 sh",
    "addr:street":"Sierkersstr",
    "iso:country":"NL",
    "sg:address":"Sierkersstr 7",
    "sg:city":"Schagen",
    "sg:orig_category":"Bloemen En Planten - Groothandel",
    "sg:phone":"+31 224 213 719",
    "sg:postcode":"1741 SH",
    "sg:province":"Noord-Holland",
    "wof:name":"Kalisvaart, J",
    "wof:placetype":"venue"
},
  "geometry": {"coordinates":[4.794118,52.793854],"type":"Point"}
}