{
  "type": "Feature",
  "properties": {
    "addr:full":"Elschot 32 Oosterhout Nb Noord-Brabant 4905 AZ",
    "addr:housenumber":"32",
    "addr:postcode":"4905 az",
    "addr:street":"Elschot",
    "iso:country":"NL",
    "sg:address":"Elschot 32",
    "sg:city":"Oosterhout Nb",
    "sg:orig_category":"Verhuur Catering-, Feest- En Evenementbenodigdheden",
    "sg:phone":"+31 162 447 100",
    "sg:postcode":"4905 AZ",
    "sg:province":"Noord-Brabant",
    "wof:name":"Game Works Bv",
    "wof:placetype":"venue"
},
  "geometry": {"coordinates":[4.850983,51.65123],"type":"Point"}
}