{
  "type": "Feature",
  "properties": {
    "iso:country":"NL",
    "sg:address":"Zandzuigerstr 23",
    "sg:city":"S Hertogenbosch",
    "sg:orig_category":"Automaterialen En Gereedschappen",
    "sg:phone":"+31 73 641 4670",
    "sg:postcode":"5222 AH",
    "sg:province":"Noord-Brabant",
    "wof:name":"Heijl, P",
    "wof:placetype":"venue"
},
  "geometry": {"coordinates":[5.28435,51.704948],"type":"Point"}
}