{
  "type": "Feature",
  "properties": {
    "iso:country":"NL",
    "sg:address":"Schiedamsewg 201",
    "sg:city":"Rotterdam",
    "sg:orig_category":"Behangselpapier En Wandbekleding",
    "sg:phone":"+31 10 462 4585",
    "sg:postcode":"3026 AM",
    "sg:province":"Zuid-Holland",
    "wof:name":"Meurs, Van",
    "wof:placetype":"venue"
},
  "geometry": {"coordinates":[4.438218,51.911903],"type":"Point"}
}