{
  "type": "Feature",
  "properties": {
    "addr:full":"Eusebiusbuit Sngl 2 Arnhem Gelderland 6828 HS",
    "addr:housenumber":"2",
    "addr:postcode":"6828 hs",
    "addr:street":"Sngl",
    "iso:country":"NL",
    "sg:address":"Eusebiusbuit Sngl 2",
    "sg:city":"Arnhem",
    "sg:orig_category":"Grafisch Ontwerpers",
    "sg:phone":"+31 26 351 5858",
    "sg:postcode":"6828 HS",
    "sg:province":"Gelderland",
    "wof:name":"Boeijend Ontwerp",
    "wof:placetype":"venue"
},
  "geometry": {"coordinates":[5.915399,51.981724],"type":"Point"}
}