{
  "type": "Feature",
  "properties": {
    "addr:full":"Industriestraat 219 Hengelo Ov Overijssel 7553 CP",
    "addr:housenumber":"219",
    "addr:postcode":"7553 cp",
    "addr:street":"Industriestraat;Ov",
    "iso:country":"NL",
    "sg:address":"Industriestraat 219",
    "sg:city":"Hengelo Ov",
    "sg:orig_category":"Metaalbekleding And -Behandeling",
    "sg:phone":"+31 74 291 2497",
    "sg:postcode":"7553 CP",
    "sg:province":"Overijssel",
    "wof:name":"Target Machine Bouw",
    "wof:placetype":"venue"
},
  "geometry": {"coordinates":[6.777069,52.250858],"type":"Point"}
}