{
  "type": "Feature",
  "properties": {
    "addr:full":"Strandweg 19 'S Gravenhage South Holland 2586 JK",
    "addr:housenumber":"19",
    "addr:postcode":"2586 jk",
    "addr:street":"Strandweg;' S Gravenhage",
    "iso:country":"NL",
    "sg:address":"Strandweg 19",
    "sg:city":"'S Gravenhage",
    "sg:classifiers":[
        {
            "category":"Fast Food",
            "type":"Food & Drink"
        }
    ],
    "sg:phone":"+31 70 354 1729",
    "sg:postcode":"2586 JK",
    "sg:province":"South Holland",
    "sg:tags":[
        "afhaal",
        "restaurant"
    ],
    "wof:name":"Coast To Coast Strandpaviljoen",
    "wof:placetype":"venue"
},
  "geometry": {"coordinates":[4.280049,52.113094],"type":"Point"}
}