{
  "type": "Feature",
  "properties": {
    "addr:full":"Oostmaasstr 69A Rotterdam South Holland 3061 ZR",
    "addr:housenumber":"69a",
    "addr:postcode":"3061 zr",
    "addr:street":"Oostmaasstr",
    "iso:country":"NL",
    "sg:address":"Oostmaasstr 69A",
    "sg:city":"Rotterdam",
    "sg:orig_category":"Grafisch Ontwerpers",
    "sg:phone":"+31 10 213 3230",
    "sg:postcode":"3061 ZR",
    "sg:province":"South Holland",
    "wof:name":"Solutions For Problems",
    "wof:placetype":"venue"
},
  "geometry": {"coordinates":[4.508581,51.923023],"type":"Point"}
}