{
  "type": "Feature",
  "properties": {
    "addr:full":"De Krom 4 Noordwijk Zh South Holland 2201 DB",
    "addr:housenumber":"4",
    "addr:postcode":"zh;2201 db",
    "addr:street":"De Krom",
    "iso:country":"NL",
    "sg:address":"De Krom 4",
    "sg:city":"Noordwijk Zh",
    "sg:orig_category":"Huizensloop And Bouwrijp Maken",
    "sg:phone":"+31 71 403 3397",
    "sg:postcode":"2201 DB",
    "sg:province":"South Holland",
    "wof:name":"J. Jonker En Zonen",
    "wof:placetype":"venue"
},
  "geometry": {"coordinates":[4.43473,52.209431],"type":"Point"}
}