{
  "type": "Feature",
  "properties": {
    "addr:full":"Burggravenln 138 Leiden Zuid-Holland 2313 HZ",
    "addr:housenumber":"138",
    "addr:postcode":"2313 hz",
    "iso:country":"NL",
    "sg:address":"Burggravenln 138",
    "sg:city":"Leiden",
    "sg:orig_category":"Hulpverlening Sociaal",
    "sg:phone":"+31 6 20005938",
    "sg:postcode":"2313 HZ",
    "sg:province":"Zuid-Holland",
    "wof:name":"Centre Aurillange Bv",
    "wof:placetype":"venue"
},
  "geometry": {"coordinates":[4.503141,52.149612],"type":"Point"}
}