{
  "type": "Feature",
  "properties": {
    "addr:full":"De Roef 9 Drachten Friesland 9206 AK",
    "addr:housenumber":"9",
    "addr:postcode":"9206 ak",
    "addr:street":"De Roef",
    "iso:country":"NL",
    "sg:address":"De Roef 9",
    "sg:city":"Drachten",
    "sg:orig_category":"Goederenvervoer Over De Weg",
    "sg:phone":"+31 512 514 700",
    "sg:postcode":"9206 AK",
    "sg:province":"Friesland",
    "wof:name":"Noortman Transport Bv",
    "wof:placetype":"venue"
},
  "geometry": {"coordinates":[6.077153,53.114334],"type":"Point"}
}