{
  "type": "Feature",
  "properties": {
    "iso:country":"NL",
    "sg:address":"Paradysselpk 98",
    "sg:city":"Capelle Ad Yssel",
    "sg:orig_category":"Psychologen",
    "sg:phone":"+31 10 450 1616",
    "sg:postcode":"2904 PA",
    "sg:province":"Zuid-Holland",
    "wof:name":"Gerbrands, Jaqueline",
    "wof:placetype":"venue"
},
  "geometry": {"coordinates":[4.610084,51.926544],"type":"Point"}
}