{
  "type": "Feature",
  "properties": {
    "addr:full":"Burg V Engelenwg 76A Ysselmuiden NL.08 8271 AT",
    "addr:housenumber":"76a",
    "addr:postcode":"8271",
    "addr:street":"Burg V Engelenwg",
    "iso:country":"NL",
    "sg:address":"Burg V Engelenwg 76A",
    "sg:city":"Ysselmuiden",
    "sg:orig_category":"Artsen - Huisartsen",
    "sg:phone":"+31 38 331 4649",
    "sg:postcode":"8271 AT",
    "sg:province":"NL.08",
    "wof:name":"Riet, J M Van De",
    "wof:placetype":"venue"
},
  "geometry": {"coordinates":[5.933985,52.564045],"type":"Point"}
}