{
  "type": "Feature",
  "properties": {
    "addr:full":"Damrak 2830 Amsterdam Noord-Holland 1012 LJ",
    "addr:housenumber":"2830",
    "addr:postcode":"1012 lj",
    "addr:street":"Damrak",
    "iso:country":"NL",
    "sg:address":"Damrak 2830",
    "sg:city":"Amsterdam",
    "sg:orig_category":"Verenigingen En Stichtingen",
    "sg:phone":"+31 20 623 0823",
    "sg:postcode":"1012 LJ",
    "sg:province":"Noord-Holland",
    "sg:website":"http://www.bothends.org",
    "wof:name":"Both Ends",
    "wof:placetype":"venue"
},
  "geometry": {"coordinates":[4.89329,52.373409],"type":"Point"}
}