{
  "type": "Feature",
  "properties": {
    "addr:full":"Estland 5 Delft Zuid-Holland 2613 JX",
    "addr:housenumber":"5",
    "addr:postcode":"2613 jx",
    "addr:street":"Estland",
    "iso:country":"NL",
    "sg:address":"Estland 5",
    "sg:city":"Delft",
    "sg:orig_category":"Meubelzaken, Woning- And Keukeninrichting",
    "sg:phone":"+31 15 212 7133",
    "sg:postcode":"2613 JX",
    "sg:province":"Zuid-Holland",
    "wof:name":"Smits",
    "wof:placetype":"venue"
},
  "geometry": {"coordinates":[4.346961,52.00515],"type":"Point"}
}