{
  "type": "Feature",
  "properties": {
    "addr:full":"Molukkenstraat 115 Amsterdam North Holland 1095 BA",
    "addr:housenumber":"115",
    "addr:postcode":"1095 ba",
    "addr:street":"Molukkenstraat",
    "iso:country":"NL",
    "sg:address":"Molukkenstraat 115",
    "sg:city":"Amsterdam",
    "sg:classifiers":[
        {
            "category":"Bakery",
            "type":"Food & Drink"
        }
    ],
    "sg:phone":"+31 20 665 5982",
    "sg:postcode":"1095 BA",
    "sg:province":"North Holland",
    "sg:tags":[
        "brood",
        "banket"
    ],
    "wof:name":"Nur",
    "wof:placetype":"venue"
},
  "geometry": {"coordinates":[4.939809,52.361923],"type":"Point"}
}