{
  "type": "Feature",
  "properties": {
    "addr:full":"Heiloostr 149 S Gravenhage Zuid-Holland 2547 KC",
    "addr:housenumber":"149;gravenhage",
    "addr:postcode":"2547 kc",
    "addr:street":"S",
    "iso:country":"NL",
    "sg:address":"Heiloostr 149",
    "sg:city":"S Gravenhage",
    "sg:orig_category":"Houtgroothandel",
    "sg:phone":"+31 6 53652680",
    "sg:postcode":"2547 KC",
    "sg:province":"Zuid-Holland",
    "wof:name":"Eurotrade",
    "wof:placetype":"venue"
},
  "geometry": {"coordinates":[4.26694,52.061771],"type":"Point"}
}