{
  "type": "Feature",
  "properties": {
    "addr:full":"Goudoever 13 Bunschoten Spakenb Utrecht 3752 GS",
    "addr:housenumber":"13",
    "addr:postcode":"3752 gs",
    "addr:street":"Goudoever",
    "iso:country":"NL",
    "sg:address":"Goudoever 13",
    "sg:city":"Bunschoten Spakenb",
    "sg:orig_category":"Adviesbureaus",
    "sg:phone":"+31 33 298 6881",
    "sg:postcode":"3752 GS",
    "sg:province":"Utrecht",
    "wof:name":"Windhouwer, E",
    "wof:placetype":"venue"
},
  "geometry": {"coordinates":[5.369356,52.251766],"type":"Point"}
}