{
  "type": "Feature",
  "properties": {
    "addr:full":"Herenwg 182 Noordwykerhout Zuid-Holland 2211 VB",
    "addr:housenumber":"182",
    "addr:postcode":"2211 vb",
    "addr:street":"Noordwykerhout",
    "iso:country":"NL",
    "sg:address":"Herenwg 182",
    "sg:city":"Noordwykerhout",
    "sg:orig_category":"Hijswerktuigen",
    "sg:phone":"+31 252 375 974",
    "sg:postcode":"2211 VB",
    "sg:province":"Zuid-Holland",
    "wof:name":"Naber",
    "wof:placetype":"venue"
},
  "geometry": {"coordinates":[4.505334,52.270573],"type":"Point"}
}