{
  "type": "Feature",
  "properties": {
    "addr:full":"Waagpassage 1 Lelystad NL. 8232 DR",
    "addr:housenumber":"1",
    "addr:postcode":"8232 dr",
    "addr:street":"Waagpassage;Nl.",
    "iso:country":"NL",
    "sg:address":"Waagpassage 1",
    "sg:city":"Lelystad",
    "sg:orig_category":"Verenigingen En Stichtingen",
    "sg:phone":"+31 320 285 481",
    "sg:postcode":"8232 DR",
    "sg:province":"NL.",
    "sg:website":"http://www.st-3d.nl",
    "wof:name":"3D, Sticht",
    "wof:placetype":"venue"
},
  "geometry": {"coordinates":[5.474812,52.51149],"type":"Point"}
}