{
  "type": "Feature",
  "properties": {
    "addr:full":"Dorpsmatenstr 46 Hengelo Ov Overijssel 7551 BP",
    "addr:housenumber":"46",
    "addr:postcode":"7551 bp",
    "addr:street":"Dorpsmatenstr;Ov",
    "iso:country":"NL",
    "sg:address":"Dorpsmatenstr 46",
    "sg:city":"Hengelo Ov",
    "sg:orig_category":"Verenigingsgebouwen",
    "sg:phone":"+31 74 243 3750",
    "sg:postcode":"7551 BP",
    "sg:province":"Overijssel",
    "wof:name":"Da=Bar",
    "wof:placetype":"venue"
},
  "geometry": {"coordinates":[6.789823,52.263683],"type":"Point"}
}