{
  "type": "Feature",
  "properties": {
    "addr:full":"Schouwenaarsstraat 2F Beverwijk Noord-Holland 1945 SW",
    "addr:housenumber":"2f",
    "addr:street":"Schouwenaarsstraat;1945 Sw",
    "iso:country":"NL",
    "sg:address":"Schouwenaarsstraat 2F",
    "sg:city":"Beverwijk",
    "sg:orig_category":"Kantoorartikelen",
    "sg:phone":"+31 251 258 374",
    "sg:postcode":"1945 SW",
    "sg:province":"Noord-Holland",
    "wof:name":"Profficiency",
    "wof:placetype":"venue"
},
  "geometry": {"coordinates":[4.6603770256,52.4919090271],"type":"Point"}
}