{
  "type": "Feature",
  "properties": {
    "addr:full":"Havenkd 14 Bruinisse Zeeland 4311 BA",
    "addr:housenumber":"14",
    "addr:postcode":"4311 ba",
    "addr:street":"Havenkd",
    "iso:country":"NL",
    "sg:address":"Havenkd 14",
    "sg:city":"Bruinisse",
    "sg:orig_category":"Scheepswerven",
    "sg:phone":"+31 111 481 710",
    "sg:postcode":"4311 BA",
    "sg:province":"Zeeland",
    "wof:name":"Maaskant Bv",
    "wof:placetype":"venue"
},
  "geometry": {"coordinates":[4.090815,51.660831],"type":"Point"}
}