{
  "type": "Feature",
  "properties": {
    "addr:full":"Watermanwg 115 Rotterdam Zuid-Holland 3067 GA",
    "addr:housenumber":"115",
    "addr:postcode":"3067 ga",
    "iso:country":"NL",
    "sg:address":"Watermanwg 115",
    "sg:city":"Rotterdam",
    "sg:orig_category":"Bedden En Matrassen",
    "sg:phone":"+31 10 209 5039",
    "sg:postcode":"3067 GA",
    "sg:province":"Zuid-Holland",
    "wof:name":"Droomdomein Bv",
    "wof:placetype":"venue"
},
  "geometry": {"coordinates":[4.559417,51.95134],"type":"Point"}
}