{
  "type": "Feature",
  "properties": {
    "addr:full":"Het Ambacht 72A Westervoort Gelderland 6931 EZ",
    "addr:housenumber":"72a",
    "addr:postcode":"6931 ez",
    "addr:street":"Het Ambacht;Gelderland",
    "iso:country":"NL",
    "sg:address":"Het Ambacht 72A",
    "sg:city":"Westervoort",
    "sg:orig_category":"Zonnebank- En Solariumcentra",
    "sg:phone":"+31 26 311 5616",
    "sg:postcode":"6931 EZ",
    "sg:province":"Gelderland",
    "wof:name":"Ellen",
    "wof:placetype":"venue"
},
  "geometry": {"coordinates":[5.981671,51.957516],"type":"Point"}
}