{
  "type": "Feature",
  "properties": {
    "iso:country":"NL",
    "sg:address":"Ged Oude Gr 24",
    "sg:city":"Haarlem",
    "sg:orig_category":"Kinderkleding",
    "sg:phone":"+31 23 534 0090",
    "sg:postcode":"2011 GR",
    "sg:province":"North Holland",
    "wof:name":"Prisca Kindermode",
    "wof:placetype":"venue"
},
  "geometry": {"coordinates":[4.631869,52.38176],"type":"Point"}
}