{
  "type": "Feature",
  "properties": {
    "addr:full":"J V Ruisdaelstr 89 Utrecht Utrecht 3583 CC",
    "addr:housenumber":"89",
    "addr:postcode":"3583 cc",
    "addr:street":"J;Ruisdaelstr",
    "iso:country":"NL",
    "sg:address":"J V Ruisdaelstr 89",
    "sg:city":"Utrecht",
    "sg:orig_category":"Vertaalbureaus",
    "sg:phone":"+31 30 210 8884",
    "sg:postcode":"3583 CC",
    "sg:province":"Utrecht",
    "sg:website":"http://www.linguaco.nl",
    "wof:name":"Lingua & Co",
    "wof:placetype":"venue"
},
  "geometry": {"coordinates":[5.14371,52.086601],"type":"Point"}
}