{
  "type": "Feature",
  "properties": {
    "addr:full":"Past De Vochtpln 3 Sambeek North Brabant 5836 BE",
    "addr:housenumber":"3",
    "addr:postcode":"5836",
    "addr:street":"Past;Vochtpln",
    "iso:country":"NL",
    "sg:address":"Past De Vochtpln 3",
    "sg:city":"Sambeek",
    "sg:orig_category":"Banken",
    "sg:phone":"+31 485 562 600",
    "sg:postcode":"5836 BE",
    "sg:province":"North Brabant",
    "sg:website":"http://www.rabobank.nl",
    "wof:name":"Rabobank",
    "wof:placetype":"venue"
},
  "geometry": {"coordinates":[5.966336,51.635555],"type":"Point"}
}