{
  "type": "Feature",
  "properties": {
    "addr:full":"Noordzeepassage 27 Katwijk Zh Zuid-Holland 2225 BS",
    "addr:housenumber":"27",
    "addr:postcode":"2225 bs",
    "addr:street":"Noordzeepassage",
    "iso:country":"NL",
    "sg:address":"Noordzeepassage 27",
    "sg:city":"Katwijk Zh",
    "sg:orig_category":"Bloemen And Planten",
    "sg:phone":"+31 71 407 1814",
    "sg:postcode":"2225 BS",
    "sg:province":"Zuid-Holland",
    "wof:name":"Bloemen- En Planten Boetiek Lydia",
    "wof:placetype":"venue"
},
  "geometry": {"coordinates":[4.395195,52.205151],"type":"Point"}
}