{
  "type": "Feature",
  "properties": {
    "iso:country":"NL",
    "sg:address":"Zandweg 151 B",
    "sg:city":"De Meern",
    "sg:orig_category":"Meubels And Huishoudapparatuur Gh",
    "sg:phone":"+31 30 666 7163",
    "sg:postcode":"3454 HB",
    "sg:province":"Utrecht",
    "wof:name":"Imago Mundi Luxe Wereldmeubelen B.V.",
    "wof:placetype":"venue"
},
  "geometry": {"coordinates":[5.033115,52.083771],"type":"Point"}
}