{
  "type": "Feature",
  "properties": {
    "addr:full":"Columbuspln 34 Amsterdam Noord-Holland 1057 VB",
    "addr:housenumber":"34",
    "addr:postcode":"1057 vb",
    "addr:street":"Columbuspln",
    "iso:country":"NL",
    "sg:address":"Columbuspln 34",
    "sg:city":"Amsterdam",
    "sg:orig_category":"Scholen Voor Basisonderwijs",
    "sg:phone":"+31 20 618 0481",
    "sg:postcode":"1057 VB",
    "sg:province":"Noord-Holland",
    "wof:name":"Visser Dr J Th De Prot Chr",
    "wof:placetype":"venue"
},
  "geometry": {"coordinates":[4.855026,52.366753],"type":"Point"}
}