{
  "type": "Feature",
  "properties": {
    "addr:full":"Langeland 25 Midwoud Noord-Holland 1679 WG",
    "addr:housenumber":"25",
    "addr:postcode":"1679 wg",
    "addr:street":"Langeland",
    "iso:country":"NL",
    "sg:address":"Langeland 25",
    "sg:city":"Midwoud",
    "sg:orig_category":"Vertaalbureaus",
    "sg:phone":"+31 229 201 667",
    "sg:postcode":"1679 WG",
    "sg:province":"Noord-Holland",
    "wof:name":"Portugees/Braziliaans Centrum",
    "wof:placetype":"venue"
},
  "geometry": {"coordinates":[5.073649,52.717297],"type":"Point"}
}