{
  "type": "Feature",
  "properties": {
    "addr:full":"Havenweg 3 Kamperland Zeeland 4493 MT",
    "addr:housenumber":"3",
    "addr:postcode":"4493 mt",
    "addr:street":"Havenweg",
    "iso:country":"NL",
    "sg:address":"Havenweg 3",
    "sg:city":"Kamperland",
    "sg:orig_category":"Bedrijfs- And Managementsconsultants",
    "sg:phone":"+31 113 372 109",
    "sg:postcode":"4493 MT",
    "sg:province":"Zeeland",
    "wof:name":"Prins Consultants Bv",
    "wof:placetype":"venue"
},
  "geometry": {"coordinates":[3.69467,51.561867],"type":"Point"}
}