{
  "type": "Feature",
  "properties": {
    "addr:full":"Pr Bernhardln 1A Heelsum Gelderland 6866 BV",
    "addr:housenumber":"1a",
    "addr:postcode":"6866 bv",
    "addr:street":"Gelderland",
    "iso:country":"NL",
    "sg:address":"Pr Bernhardln 1A",
    "sg:city":"Heelsum",
    "sg:orig_category":"Artsen - Huisartsen",
    "sg:phone":"+31 317 313 322",
    "sg:postcode":"6866 BV",
    "sg:province":"Gelderland",
    "wof:name":"Nievaart & J G M Louwers, J K H",
    "wof:placetype":"venue"
},
  "geometry": {"coordinates":[5.75346,51.983845],"type":"Point"}
}