{
  "type": "Feature",
  "properties": {
    "iso:country":"NL",
    "sg:address":"Postbus 10063",
    "sg:city":"Weert",
    "sg:orig_category":"Bejaarden - Verzorgingstehuizen",
    "sg:phone":"+31 495 434 200",
    "sg:postcode":"6000 GB",
    "sg:province":"Limburg",
    "sg:website":"http://www.soweert.nl",
    "wof:name":"Ouderenzorg Weert, Sticht",
    "wof:placetype":"venue"
},
  "geometry": {"coordinates":[5.703781,51.255016],"type":"Point"}
}