{
  "type": "Feature",
  "properties": {
    "addr:full":"Keizerskroon 66 Papendrecht Zuid-Holland 3353 XR",
    "addr:housenumber":"66",
    "addr:postcode":"3353 xr",
    "addr:street":"Keizerskroon",
    "iso:country":"NL",
    "sg:address":"Keizerskroon 66",
    "sg:city":"Papendrecht",
    "sg:orig_category":"Binnenhuisarchitecten",
    "sg:phone":"+31 78 641 2621",
    "sg:postcode":"3353 XR",
    "sg:province":"Zuid-Holland",
    "wof:name":"Johan Verdoes Interieurarchitektuur",
    "wof:placetype":"venue"
},
  "geometry": {"coordinates":[4.69133,51.83403],"type":"Point"}
}