{
  "type": "Feature",
  "properties": {
    "addr:full":"Prinses Mariannestraat 15 Alkmaar North Holland 1814 XG",
    "addr:housenumber":"15",
    "addr:postcode":"1814 xg",
    "addr:street":"Prinses Mariannestraat",
    "iso:country":"NL",
    "sg:address":"Prinses Mariannestraat 15",
    "sg:city":"Alkmaar",
    "sg:orig_category":"Beautyfarms And Sauna'S",
    "sg:phone":"+31 72 511 9287",
    "sg:postcode":"1814 XG",
    "sg:province":"North Holland",
    "wof:name":"R. Ran",
    "wof:placetype":"venue"
},
  "geometry": {"coordinates":[4.737107,52.617138],"type":"Point"}
}