{
  "type": "Feature",
  "properties": {
    "addr:full":"Zaaren 191 Ryen North Brabant 5122 GK",
    "addr:housenumber":"191",
    "addr:postcode":"5122 gk",
    "addr:street":"Zaaren",
    "iso:country":"NL",
    "sg:address":"Zaaren 191",
    "sg:city":"Ryen",
    "sg:orig_category":"Verenigingen En Stichtingen",
    "sg:phone":"+31 161 230 957",
    "sg:postcode":"5122 GK",
    "sg:province":"North Brabant",
    "wof:name":"Imaan, Sticht",
    "wof:placetype":"venue"
},
  "geometry": {"coordinates":[4.92752,51.59277],"type":"Point"}
}