{
  "type": "Feature",
  "properties": {
    "iso:country":"NL",
    "sg:address":"Oldenzaalsestr 161",
    "sg:city":"Enschede",
    "sg:orig_category":"Artsen - Huisartsen",
    "sg:phone":"+31 53 435 8544",
    "sg:postcode":"7523 AA",
    "sg:province":"NL.08",
    "wof:name":"Jansen, J Th W",
    "wof:placetype":"venue"
},
  "geometry": {"coordinates":[6.900125,52.228218],"type":"Point"}
}