{
  "type": "Feature",
  "properties": {
    "addr:full":"Schweitzerstraat 23 Middelburg Zeeland 4336 LJ",
    "addr:housenumber":"23",
    "addr:postcode":"4336 lj",
    "addr:street":"Schweitzerstraat",
    "iso:country":"NL",
    "sg:address":"Schweitzerstraat 23",
    "sg:city":"Middelburg",
    "sg:orig_category":"Binnenhuisarchitecten",
    "sg:phone":"+31 118 639 389",
    "sg:postcode":"4336 LJ",
    "sg:province":"Zeeland",
    "wof:name":"H. Simons",
    "wof:placetype":"venue"
},
  "geometry": {"coordinates":[3.609868,51.485435],"type":"Point"}
}