{
  "type": "Feature",
  "properties": {
    "addr:full":"Hooilandsewg 40 Roodeschool Groningen 9983 PE",
    "addr:housenumber":"40",
    "addr:postcode":"9983 pe",
    "addr:street":"Hooilandsewg",
    "iso:country":"NL",
    "sg:address":"Hooilandsewg 40",
    "sg:city":"Roodeschool",
    "sg:orig_category":"Bedrijfsopleidingen",
    "sg:phone":"+31 595 415 161",
    "sg:postcode":"9983 PE",
    "sg:province":"Groningen",
    "wof:name":"Vervoer En Logistiek, N-Ned Opl Inst Voor",
    "wof:placetype":"venue"
},
  "geometry": {"coordinates":[6.765645,53.419796],"type":"Point"}
}