{
  "type": "Feature",
  "properties": {
    "addr:full":"Grypensteinwg 14 Haarlem Noord-Holland 2014 KX",
    "addr:housenumber":"14",
    "addr:postcode":"2014 kx",
    "addr:street":"Grypensteinwg",
    "iso:country":"NL",
    "sg:address":"Grypensteinwg 14",
    "sg:city":"Haarlem",
    "sg:orig_category":"Keukens",
    "sg:phone":"+31 23 524 8800",
    "sg:postcode":"2014 KX",
    "sg:province":"Noord-Holland",
    "sg:website":"http://www.nouris.nl",
    "wof:name":"Nouris Loodgietersbedrijf Bv",
    "wof:placetype":"venue"
},
  "geometry": {"coordinates":[4.610503,52.364384],"type":"Point"}
}