{
  "type": "Feature",
  "properties": {
    "iso:country":"NL",
    "sg:address":"Laan Van Meerwijk 6",
    "sg:city":"Uithoorn",
    "sg:orig_category":"Politie",
    "sg:phone":"+31 900 8844",
    "sg:postcode":"1423 AJ",
    "sg:province":"North Holland",
    "wof:name":"Politie Amsterdam-Amstelland District 9 Bureau Uit",
    "wof:placetype":"venue"
},
  "geometry": {"coordinates":[4.82672,52.232479],"type":"Point"}
}