{
  "type": "Feature",
  "properties": {
    "addr:full":"Gasthuisring 19K Tilburg Noord-Brabant 5041 DP",
    "addr:housenumber":"19k",
    "addr:postcode":"5041 dp",
    "addr:street":"Gasthuisring",
    "iso:country":"NL",
    "sg:address":"Gasthuisring 19K",
    "sg:city":"Tilburg",
    "sg:orig_category":"Lichtreclame",
    "sg:phone":"+31 13 543 8980",
    "sg:postcode":"5041 DP",
    "sg:province":"Noord-Brabant",
    "wof:name":"Neon Art & Projects",
    "wof:placetype":"venue"
},
  "geometry": {"coordinates":[5.077409,51.563915],"type":"Point"}
}