{
  "type": "Feature",
  "properties": {
    "iso:country":"NL",
    "sg:address":"Roodehaansterweg 9",
    "sg:city":"Warfhuizen",
    "sg:orig_category":"Kampeerterreinen",
    "sg:phone":"+31 595 571 598",
    "sg:postcode":"9963 TC",
    "sg:province":"Groningen",
    "wof:name":"Camping Roodehaan",
    "wof:placetype":"venue"
},
  "geometry": {"coordinates":[6.4264497757,53.3288421631],"type":"Point"}
}