{
  "type": "Feature",
  "properties": {
    "iso:country":"NL",
    "sg:address":"Tulpenstraat 3",
    "sg:city":"Hippolytushoef",
    "sg:orig_category":"Fotostudio'S And Fotografen",
    "sg:phone":"+31 227 591 667",
    "sg:postcode":"1777 EG",
    "sg:province":"North Holland",
    "wof:name":"Mevr J.C. Angevare-De Smit",
    "wof:placetype":"venue"
},
  "geometry": {"coordinates":[4.955415,52.905857],"type":"Point"}
}