{
  "type": "Feature",
  "properties": {
    "addr:full":"Woestijgerweg 7 Amersfoort Utrecht 3817 SB",
    "addr:housenumber":"7",
    "addr:postcode":"3817 sb",
    "addr:street":"Woestijgerweg",
    "iso:country":"NL",
    "sg:address":"Woestijgerweg 7",
    "sg:city":"Amersfoort",
    "sg:orig_category":"Zuivelproducten",
    "sg:phone":"+31 33 461 5039",
    "sg:postcode":"3817 SB",
    "sg:province":"Utrecht",
    "wof:name":"N M Schoonderbeek",
    "wof:placetype":"venue"
},
  "geometry": {"coordinates":[5.384404,52.146584],"type":"Point"}
}