{
  "type": "Feature",
  "properties": {
    "addr:full":"Venbroek 7 Hapert Noord-Brabant 5527 BG",
    "addr:housenumber":"7",
    "addr:postcode":"5527",
    "addr:street":"Venbroek",
    "iso:country":"NL",
    "sg:address":"Venbroek 7",
    "sg:city":"Hapert",
    "sg:orig_category":"Adviesbureaus Bouwkosten",
    "sg:phone":"+31 497 369 604",
    "sg:postcode":"5527 BG",
    "sg:province":"Noord-Brabant",
    "wof:name":"Leeuw, J De",
    "wof:placetype":"venue"
},
  "geometry": {"coordinates":[5.254353,51.372005],"type":"Point"}
}