{
  "type": "Feature",
  "properties": {
    "addr:full":"Kastanjeln 75 Zwanenburg Noord-Holland 1161 VB",
    "addr:housenumber":"75",
    "addr:postcode":"1161 vb",
    "addr:street":"Kastanjeln",
    "iso:country":"NL",
    "sg:address":"Kastanjeln 75",
    "sg:city":"Zwanenburg",
    "sg:orig_category":"Administratie- En Boekhoudkantoren",
    "sg:phone":"+31 20 497 7429",
    "sg:postcode":"1161 VB",
    "sg:province":"Noord-Holland",
    "wof:name":"Overwater",
    "wof:placetype":"venue"
},
  "geometry": {"coordinates":[4.743692,52.381775],"type":"Point"}
}