{
  "type": "Feature",
  "properties": {
    "addr:full":"Middelwg 6 Nieuwkuyk North Brabant 5253 CA",
    "addr:housenumber":"6",
    "addr:postcode":"5253 ca",
    "addr:street":"Middelwg",
    "iso:country":"NL",
    "sg:address":"Middelwg 6",
    "sg:city":"Nieuwkuyk",
    "sg:orig_category":"Boekbinderijen",
    "sg:phone":"+31 73 511 5109",
    "sg:postcode":"5253 CA",
    "sg:province":"North Brabant",
    "wof:name":"Stams Bv",
    "wof:placetype":"venue"
},
  "geometry": {"coordinates":[5.181873,51.694813],"type":"Point"}
}