{
  "type": "Feature",
  "properties": {
    "addr:full":"Kluizerdk 1D Valkenswaard Noord-Brabant 5554 XA",
    "addr:housenumber":"1d",
    "addr:postcode":"5554 xa",
    "iso:country":"NL",
    "sg:address":"Kluizerdk 1D",
    "sg:city":"Valkenswaard",
    "sg:orig_category":"Adviesbureaus Bedrijfsorganisatie",
    "sg:phone":"+31 40 213 0075",
    "sg:postcode":"5554 XA",
    "sg:province":"Noord-Brabant",
    "wof:name":"Euro Management Consultants Nv",
    "wof:placetype":"venue"
},
  "geometry": {"coordinates":[5.459158,51.33979],"type":"Point"}
}