{
  "type": "Feature",
  "properties": {
    "addr:full":"Luchthavenwg 20 Budel Noord-Brabant 6021 PX",
    "addr:housenumber":"20",
    "addr:postcode":"6021 px",
    "addr:street":"Luchthavenwg",
    "iso:country":"NL",
    "sg:address":"Luchthavenwg 20",
    "sg:city":"Budel",
    "sg:orig_category":"Luchthavens En Vliegvelden",
    "sg:phone":"+31 495 697 949",
    "sg:postcode":"6021 PX",
    "sg:province":"Noord-Brabant",
    "sg:website":"http://www.kempenairport.nl",
    "wof:name":"Kempen Airport",
    "wof:placetype":"venue"
},
  "geometry": {"coordinates":[5.600212,51.256741],"type":"Point"}
}