{
  "type": "Feature",
  "properties": {
    "addr:full":"Brasem 49 Huizen Noord-Holland 1275 AJ",
    "addr:housenumber":"49",
    "addr:postcode":"1275 aj",
    "addr:street":"Brasem",
    "iso:country":"NL",
    "sg:address":"Brasem 49",
    "sg:city":"Huizen",
    "sg:orig_category":"Afslankinstituten",
    "sg:phone":"+31 35 526 8204",
    "sg:postcode":"1275 AJ",
    "sg:province":"Noord-Holland",
    "wof:name":"Sietske Vuijst Tti",
    "wof:placetype":"venue"
},
  "geometry": {"coordinates":[5.264627,52.291603],"type":"Point"}
}