{
  "type": "Feature",
  "properties": {
    "addr:full":"Van Bothnialaan 63 Coevorden Drenthe 7742 WE",
    "addr:housenumber":"63",
    "addr:postcode":"7742 we",
    "addr:street":"Van Bothnialaan",
    "iso:country":"NL",
    "sg:address":"Van Bothnialaan 63",
    "sg:city":"Coevorden",
    "sg:orig_category":"Technische Studies And Onderzoek",
    "sg:phone":"+31 524 525 288",
    "sg:postcode":"7742 WE",
    "sg:province":"Drenthe",
    "wof:name":"Marose Lichttechniek",
    "wof:placetype":"venue"
},
  "geometry": {"coordinates":[6.758071,52.666168],"type":"Point"}
}