{
  "type": "Feature",
  "properties": {
    "addr:full":"De Kempenaerstraat 95 Oegstgeest South Holland 2341 GK",
    "addr:housenumber":"95",
    "addr:postcode":"2341 gk",
    "addr:street":"De Kempenaerstraat",
    "iso:country":"NL",
    "sg:address":"De Kempenaerstraat 95",
    "sg:city":"Oegstgeest",
    "sg:orig_category":"Wasserettes And Stomerijen",
    "sg:phone":"+31 71 517 4898",
    "sg:postcode":"2341 GK",
    "sg:province":"South Holland",
    "wof:name":"Chemische Wasserij Edmondo Bv",
    "wof:placetype":"venue"
},
  "geometry": {"coordinates":[4.4729971886,52.1773719788],"type":"Point"}
}