{
  "type": "Feature",
  "properties": {
    "addr:full":"Veenkade 150 Den Haag Zuid-Holland 2513 EL",
    "addr:housenumber":"150",
    "addr:postcode":"2513 el",
    "addr:street":"Veenkade",
    "iso:country":"NL",
    "sg:address":"Veenkade 150",
    "sg:city":"Den Haag",
    "sg:orig_category":"Meubelreparatie And -Restauratie",
    "sg:phone":"+31 70 365 8373",
    "sg:postcode":"2513 EL",
    "sg:province":"Zuid-Holland",
    "wof:name":"Stoffeeratelier Brunink",
    "wof:placetype":"venue"
},
  "geometry": {"coordinates":[4.296922,52.077606],"type":"Point"}
}