{
  "type": "Feature",
  "properties": {
    "iso:country":"NL",
    "sg:address":"Zeddamseweg 8",
    "sg:city":"'S Heerenberg",
    "sg:orig_category":"Huishoudapparatuur, Televisies And Radio'S",
    "sg:phone":"+31 314 662 534",
    "sg:postcode":"7041 CP",
    "sg:province":"Gelderland",
    "wof:name":"Expert 'S Heerenberg",
    "wof:placetype":"venue"
},
  "geometry": {"coordinates":[6.246449,51.876431],"type":"Point"}
}