{
  "type": "Feature",
  "properties": {
    "addr:full":"Reigerskamp 376 Maarssen Utrecht 3607 HW",
    "addr:housenumber":"376",
    "addr:postcode":"3607 hw",
    "addr:street":"Reigerskamp",
    "iso:country":"NL",
    "sg:address":"Reigerskamp 376",
    "sg:city":"Maarssen",
    "sg:orig_category":"Psychosociale Therapeuten",
    "sg:phone":"+31 346 553 563",
    "sg:postcode":"3607 HW",
    "sg:province":"Utrecht",
    "wof:name":"Siksma, H J M",
    "wof:placetype":"venue"
},
  "geometry": {"coordinates":[5.015202,52.133389],"type":"Point"}
}