{
  "type": "Feature",
  "properties": {
    "addr:full":"Westerstraat 2 Purmerend Noord-Holland 1441 AS",
    "addr:housenumber":"2",
    "addr:postcode":"1441 as",
    "addr:street":"Westerstraat",
    "iso:country":"NL",
    "sg:address":"Westerstraat 2",
    "sg:city":"Purmerend",
    "sg:orig_category":"Muziekinstrumenten",
    "sg:phone":"+31 299 428 570",
    "sg:postcode":"1441 AS",
    "sg:province":"Noord-Holland",
    "wof:name":"Muziekhandel De Staar Vof",
    "wof:placetype":"venue"
},
  "geometry": {"coordinates":[4.9442448616,52.5100746155],"type":"Point"}
}