{
  "type": "Feature",
  "properties": {
    "addr:full":"Wederik 68 Uithoorn Noord-Holland 1422 MK",
    "addr:housenumber":"68",
    "addr:postcode":"1422",
    "addr:street":"Wederik",
    "iso:country":"NL",
    "sg:address":"Wederik 68",
    "sg:city":"Uithoorn",
    "sg:orig_category":"Kappers",
    "sg:phone":"+31 297 563 853",
    "sg:postcode":"1422 MK",
    "sg:province":"Noord-Holland",
    "wof:name":"Anja",
    "wof:placetype":"venue"
},
  "geometry": {"coordinates":[4.812871933,52.2466621399],"type":"Point"}
}