{
  "type": "Feature",
  "properties": {
    "addr:full":"Leidsewg 90 Utrecht Utrecht 3531 BG",
    "addr:housenumber":"90",
    "addr:postcode":"3531",
    "addr:street":"Leidsewg",
    "iso:country":"NL",
    "sg:address":"Leidsewg 90",
    "sg:city":"Utrecht",
    "sg:orig_category":"Musea",
    "sg:phone":"+31 30 291 0482",
    "sg:postcode":"3531 BG",
    "sg:province":"Utrecht",
    "sg:website":"http://www.muntmuseum.nl",
    "wof:name":"Muntmuseum, Het Nederlands",
    "wof:placetype":"venue"
},
  "geometry": {"coordinates":[-73.996292,40.613091],"type":"Point"}
}