{
  "type": "Feature",
  "properties": {
    "addr:full":"Industriewg 13A Drunen Noord-Brabant 5151 RV",
    "addr:housenumber":"13a",
    "addr:postcode":"5151 rv",
    "addr:street":"Industriewg",
    "iso:country":"NL",
    "sg:address":"Industriewg 13A",
    "sg:city":"Drunen",
    "sg:orig_category":"Keukens",
    "sg:phone":"+31 416 380 856",
    "sg:postcode":"5151 RV",
    "sg:province":"Noord-Brabant",
    "wof:name":"Hans Verkerk",
    "wof:placetype":"venue"
},
  "geometry": {"coordinates":[5.16029,51.691902],"type":"Point"}
}