{
  "type": "Feature",
  "properties": {
    "addr:full":"Klaproosstraat 12 Bergeyk Noord-Brabant 5571 JG",
    "addr:housenumber":"12",
    "addr:postcode":"5571 jg",
    "addr:street":"Klaproosstraat",
    "iso:country":"NL",
    "sg:address":"Klaproosstraat 12",
    "sg:city":"Bergeyk",
    "sg:orig_category":"Metaalwerken",
    "sg:phone":"+31 497 573 443",
    "sg:postcode":"5571 JG",
    "sg:province":"Noord-Brabant",
    "wof:name":"Dekoninck Montage",
    "wof:placetype":"venue"
},
  "geometry": {"coordinates":[5.351548,51.318691],"type":"Point"}
}