{
  "type": "Feature",
  "properties": {
    "addr:full":"A Dekenstr 4-6 Vlissingen Zeeland 4381 RZ",
    "addr:housenumber":"4-6",
    "addr:postcode":"4381 rz",
    "iso:country":"NL",
    "sg:address":"A Dekenstr 4-6",
    "sg:city":"Vlissingen",
    "sg:classifiers":[
        {
            "category":"Food & Beverages",
            "subcategory":"Bakery",
            "type":"Retail Goods"
        }
    ],
    "sg:phone":"+31 118 415 915",
    "sg:postcode":"4381 RZ",
    "sg:province":"Zeeland",
    "sg:tags":[
        "pizza"
    ],
    "wof:name":"Tavor",
    "wof:placetype":"venue"
},
  "geometry": {"coordinates":[3.572621,51.44545],"type":"Point"}
}