{
  "type": "Feature",
  "properties": {
    "addr:full":"Nw Ebbingestr 88 Groningen Groningen 9712 NP",
    "addr:housenumber":"88",
    "addr:postcode":"9712 np",
    "iso:country":"NL",
    "sg:address":"Nw Ebbingestr 88",
    "sg:city":"Groningen",
    "sg:orig_category":"Zonnebank- En Solariumcentra",
    "sg:phone":"+31 50 312 2121",
    "sg:postcode":"9712 NP",
    "sg:province":"Groningen",
    "wof:name":"Tropics",
    "wof:placetype":"venue"
},
  "geometry": {"coordinates":[6.561325,53.225693],"type":"Point"}
}