{
  "type": "Feature",
  "properties": {
    "addr:full":"Kanaalwg 133 Utrecht Utrecht 3533 HK",
    "addr:housenumber":"133",
    "addr:postcode":"3533 hk",
    "iso:country":"NL",
    "sg:address":"Kanaalwg 133",
    "sg:city":"Utrecht",
    "sg:orig_category":"Accumulatoren - Fabrieken En Groothandel",
    "sg:phone":"+31 30 293 5962",
    "sg:postcode":"3533 HK",
    "sg:province":"Utrecht",
    "wof:name":"Koot-Rite",
    "wof:placetype":"venue"
},
  "geometry": {"coordinates":[5.084153,52.091801],"type":"Point"}
}