{
  "type": "Feature",
  "properties": {
    "addr:full":"V Haexbergenstr 1 Deventer Overijssel 7416 AT",
    "addr:housenumber":"1",
    "addr:postcode":"7416",
    "addr:street":"Haexbergenstr",
    "iso:country":"NL",
    "sg:address":"V Haexbergenstr 1",
    "sg:city":"Deventer",
    "sg:orig_category":"Sportverenigingen En Ontspannings- Verenigingen",
    "sg:phone":"+31 570 622 302",
    "sg:postcode":"7416 AT",
    "sg:province":"Overijssel",
    "wof:name":"Dev Hengelsportver",
    "wof:placetype":"venue"
},
  "geometry": {"coordinates":[6.159899,52.251034],"type":"Point"}
}