{
  "type": "Feature",
  "properties": {
    "addr:full":"Groenendaalsewg 64 Loenen Gld Gelderland 7371 EZ",
    "addr:housenumber":"64",
    "addr:postcode":"7371 ez",
    "addr:street":"Groenendaalsewg;Gld Gelderland",
    "iso:country":"NL",
    "sg:address":"Groenendaalsewg 64",
    "sg:city":"Loenen Gld",
    "sg:orig_category":"Begraafplaatsen",
    "sg:phone":"+31 55 505 1363",
    "sg:postcode":"7371 EZ",
    "sg:province":"Gelderland",
    "wof:name":"Oorlogsgraven Ned Ereveld, Sticht",
    "wof:placetype":"venue"
},
  "geometry": {"coordinates":[5.997527,52.114296],"type":"Point"}
}