{
  "type": "Feature",
  "properties": {
    "iso:country":"NL",
    "sg:address":"Kapittelln 83",
    "sg:city":"Maastricht",
    "sg:orig_category":"Antiquariaten",
    "sg:phone":"+31 43 321 3411",
    "sg:postcode":"6229 TT",
    "sg:province":"Limburg",
    "wof:name":"Vermeulen, Mathieu",
    "wof:placetype":"venue"
},
  "geometry": {"coordinates":[5.70559,50.822762],"type":"Point"}
}