{
  "type": "Feature",
  "properties": {
    "addr:full":"Middelwijkstraat 36 Soest Utrecht 3764 CG",
    "addr:housenumber":"36",
    "addr:postcode":"3764 cg",
    "addr:street":"Middelwijkstraat",
    "iso:country":"NL",
    "sg:address":"Middelwijkstraat 36",
    "sg:city":"Soest",
    "sg:orig_category":"Parfum And Cosmetica Gh",
    "sg:phone":"+31 35 601 0999",
    "sg:postcode":"3764 CG",
    "sg:province":"Utrecht",
    "wof:name":"Arteche Health & Beauty",
    "wof:placetype":"venue"
},
  "geometry": {"coordinates":[5.307413,52.176899],"type":"Point"}
}