{
  "type": "Feature",
  "properties": {
    "addr:full":"Kruisvoort 48 Breda North Brabant 4814 RZ",
    "addr:housenumber":"48",
    "addr:postcode":"4814 rz",
    "addr:street":"Kruisvoort",
    "iso:country":"NL",
    "sg:address":"Kruisvoort 48",
    "sg:city":"Breda",
    "sg:orig_category":"Meubelzaken, Woning- And Keukeninrichting",
    "sg:phone":"+31 76 520 9605",
    "sg:postcode":"4814 RZ",
    "sg:province":"North Brabant",
    "wof:name":"Oase Slaapkamerspeciaalzaken",
    "wof:placetype":"venue"
},
  "geometry": {"coordinates":[4.732307,51.581963],"type":"Point"}
}