{
  "type": "Feature",
  "properties": {
    "addr:full":"Schollevaarwg 81 Zeewolde NL. 3897 LA",
    "addr:housenumber":"81",
    "addr:postcode":"3897",
    "addr:street":"Schollevaarwg;Nl.",
    "iso:country":"NL",
    "sg:address":"Schollevaarwg 81",
    "sg:city":"Zeewolde",
    "sg:orig_category":"Bloemen En Planten",
    "sg:phone":"+31 36 522 8465",
    "sg:postcode":"3897 LA",
    "sg:province":"NL.",
    "wof:name":"Ridderspoor",
    "wof:placetype":"venue"
},
  "geometry": {"coordinates":[5.422079,52.336788],"type":"Point"}
}