{
  "type": "Feature",
  "properties": {
    "iso:country":"NL",
    "sg:address":"Overhorst 1",
    "sg:city":"Helmond",
    "sg:orig_category":"Verzekeringen - Verzekeringskantoren",
    "sg:phone":"+31 492 599 623",
    "sg:postcode":"5707 PP",
    "sg:province":"Noord-Brabant",
    "wof:name":"Florijn",
    "wof:placetype":"venue"
},
  "geometry": {"coordinates":[5.645789,51.490398],"type":"Point"}
}