{
  "type": "Feature",
  "properties": {
    "addr:full":"Jansveld 17Bis Utrecht Utrecht 3512 BD",
    "addr:housenumber":"17bis",
    "addr:postcode":"3512 bd",
    "addr:street":"Jansveld",
    "iso:country":"NL",
    "sg:address":"Jansveld 17Bis",
    "sg:city":"Utrecht",
    "sg:orig_category":"Diverse Grafische Activiteiten",
    "sg:phone":"+31 30 231 1183",
    "sg:postcode":"3512 BD",
    "sg:province":"Utrecht",
    "wof:name":"Digitale Klerken",
    "wof:placetype":"venue"
},
  "geometry": {"coordinates":[5.120052,52.093914],"type":"Point"}
}