{
  "type": "Feature",
  "properties": {
    "addr:full":"Robynring 42 Eindhoven Noord-Brabant 5629 GK",
    "addr:housenumber":"42",
    "addr:postcode":"5629 gk",
    "addr:street":"Robynring",
    "iso:country":"NL",
    "sg:address":"Robynring 42",
    "sg:city":"Eindhoven",
    "sg:orig_category":"Administratie- En Boekhoudkantoren",
    "sg:phone":"+31 40 248 0418",
    "sg:postcode":"5629 GK",
    "sg:province":"Noord-Brabant",
    "wof:name":"Jife",
    "wof:placetype":"venue"
},
  "geometry": {"coordinates":[5.47007,51.4897],"type":"Point"}
}