{
  "type": "Feature",
  "properties": {
    "addr:full":"S Reimerstr 25 Enschede Overijssel 7524 CR",
    "addr:housenumber":"25",
    "addr:postcode":"7524 cr",
    "iso:country":"NL",
    "sg:address":"S Reimerstr 25",
    "sg:city":"Enschede",
    "sg:orig_category":"Verzekeringen - Verzekeringskantoren",
    "sg:phone":"+31 53 433 7199",
    "sg:postcode":"7524 CR",
    "sg:province":"Overijssel",
    "wof:name":"Kleisman",
    "wof:placetype":"venue"
},
  "geometry": {"coordinates":[6.911357,52.249996],"type":"Point"}
}