{
  "type": "Feature",
  "properties": {
    "addr:full":"Kerkstr 137 Sprang-Capelle Noord-Brabant 5161 EC",
    "addr:housenumber":"137",
    "addr:postcode":"sprang-capelle;5161 ec",
    "iso:country":"NL",
    "sg:address":"Kerkstr 137",
    "sg:city":"Sprang-Capelle",
    "sg:orig_category":"Peuterspeelzalen",
    "sg:phone":"+31 416 275 452",
    "sg:postcode":"5161 EC",
    "sg:province":"Noord-Brabant",
    "wof:name":"Kruimeltje",
    "wof:placetype":"venue"
},
  "geometry": {"coordinates":[5.044795,51.668564],"type":"Point"}
}