{
  "type": "Feature",
  "properties": {
    "addr:full":"Wentelploeg 42 Biddinghuizen Flevoland 8256 SN",
    "addr:housenumber":"42",
    "addr:postcode":"8256 sn",
    "addr:street":"Wentelploeg;Flevoland",
    "iso:country":"NL",
    "sg:address":"Wentelploeg 42",
    "sg:city":"Biddinghuizen",
    "sg:orig_category":"Waterbouwkundige Werken",
    "sg:phone":"+31 321 335 563",
    "sg:postcode":"8256 SN",
    "sg:province":"Flevoland",
    "sg:website":"HTTP://www.kwtgroup.nl",
    "wof:name":"Kwt Group Bv",
    "wof:placetype":"venue"
},
  "geometry": {"coordinates":[5.7066149712,52.4591712952],"type":"Point"}
}