{
  "type": "Feature",
  "properties": {
    "iso:country":"NL",
    "sg:address":"Poolsezoom 31",
    "sg:city":"Nieuwerkerk Ad Ijssel",
    "sg:orig_category":"Beautyfarms And Sauna'S",
    "sg:phone":"+31 180 310 676",
    "sg:postcode":"2912 GJ",
    "sg:province":"South Holland",
    "wof:name":"Jolanda",
    "wof:placetype":"venue"
},
  "geometry": {"coordinates":[4.597666,51.964699],"type":"Point"}
}