{
  "type": "Feature",
  "properties": {
    "iso:country":"NL",
    "sg:address":"Strackestr 45",
    "sg:city":"Amsterdam",
    "sg:orig_category":"Koeriersdiensten",
    "sg:phone":"+31 20 773 1078",
    "sg:postcode":"1067 KS",
    "sg:province":"Noord-Holland",
    "wof:name":"Alberto",
    "wof:placetype":"venue"
},
  "geometry": {"coordinates":[4.799546,52.378384],"type":"Point"}
}