{
  "type": "Feature",
  "properties": {
    "iso:country":"NL",
    "sg:address":"Broekgraaf 8A",
    "sg:city":"Almkerk",
    "sg:orig_category":"Grondwerken",
    "sg:phone":"+31 6 51308446",
    "sg:postcode":"4286 LW",
    "sg:province":"Noord-Brabant",
    "wof:name":"Scherff & Vink",
    "wof:placetype":"venue"
},
  "geometry": {"coordinates":[4.997816,51.768204],"type":"Point"}
}