{
  "type": "Feature",
  "properties": {
    "addr:full":"Akerstraat 38 Kerkrade Limburg 6466 HJ",
    "addr:housenumber":"38",
    "addr:postcode":"6466 hj",
    "addr:street":"Akerstraat",
    "iso:country":"NL",
    "sg:address":"Akerstraat 38",
    "sg:city":"Kerkrade",
    "sg:orig_category":"Damesmodezaken",
    "sg:phone":"+31 45 542 0947",
    "sg:postcode":"6466 HJ",
    "sg:province":"Limburg",
    "wof:name":"P. Gulpen-Schaepkens",
    "wof:placetype":"venue"
},
  "geometry": {"coordinates":[6.026717,50.85693],"type":"Point"}
}