{
  "type": "Feature",
  "properties": {
    "addr:full":"Merwedeweg 11 Breukelen Ut Utrecht 3621 LP",
    "addr:housenumber":"11",
    "addr:postcode":"3621 lp",
    "addr:street":"Merwedeweg",
    "iso:country":"NL",
    "sg:address":"Merwedeweg 11",
    "sg:city":"Breukelen Ut",
    "sg:orig_category":"Autokeuringen",
    "sg:phone":"+31 346 266 174",
    "sg:postcode":"3621 LP",
    "sg:province":"Utrecht",
    "wof:name":"A.S.T. (Auto Service Van Tricht)",
    "wof:placetype":"venue"
},
  "geometry": {"coordinates":[4.993594,52.172989],"type":"Point"}
}