{
  "type": "Feature",
  "properties": {
    "iso:country":"NL",
    "sg:address":"Rupel 6",
    "sg:city":"Amstelveen",
    "sg:orig_category":"Vertalers",
    "sg:phone":"+31 20 641 4979",
    "sg:postcode":"1186 LB",
    "sg:province":"Noord-Holland",
    "wof:name":"Overmars-Vovsy, Drs R",
    "wof:placetype":"venue"
},
  "geometry": {"coordinates":[4.863644,52.287842],"type":"Point"}
}