{
  "type": "Feature",
  "properties": {
    "addr:full":"Brugwg 9B Kruisland Noord-Brabant 4756 AG",
    "addr:housenumber":"9b",
    "addr:postcode":"4756",
    "addr:street":"Brugwg",
    "iso:country":"NL",
    "sg:address":"Brugwg 9B",
    "sg:city":"Kruisland",
    "sg:orig_category":"Kousen - Fabrieken En Groothandel",
    "sg:phone":"+31 167 532 948",
    "sg:postcode":"4756 AG",
    "sg:province":"Noord-Brabant",
    "wof:name":"Hits Socks",
    "wof:placetype":"venue"
},
  "geometry": {"coordinates":[4.404048,51.568668],"type":"Point"}
}