{
  "type": "Feature",
  "properties": {
    "iso:country":"NL",
    "sg:address":"St Josephsstr 29",
    "sg:city":"Roosendaal",
    "sg:orig_category":"Kappers",
    "sg:phone":"+31 165 545 209",
    "sg:postcode":"4702 CT",
    "sg:province":"North Brabant",
    "wof:name":"Louise",
    "wof:placetype":"venue"
},
  "geometry": {"coordinates":[4.468792,51.530151],"type":"Point"}
}