{
  "type": "Feature",
  "properties": {
    "addr:full":"Koningshof 14 Rhenen Utrecht 3911 LH",
    "addr:housenumber":"14",
    "addr:postcode":"3911 lh",
    "addr:street":"Koningshof",
    "iso:country":"NL",
    "sg:address":"Koningshof 14",
    "sg:city":"Rhenen",
    "sg:orig_category":"Projectinrichting",
    "sg:phone":"+31 317 616 596",
    "sg:postcode":"3911 LH",
    "sg:province":"Utrecht",
    "sg:website":"http://www.artsize.com",
    "wof:name":"Artsize",
    "wof:placetype":"venue"
},
  "geometry": {"coordinates":[5.563388,51.957317],"type":"Point"}
}