{
  "type": "Feature",
  "properties": {
    "addr:full":"Parklaan 21 Bussum Noord-Holland 1406 KK",
    "addr:housenumber":"21",
    "addr:postcode":"1406 kk",
    "addr:street":"Parklaan",
    "iso:country":"NL",
    "sg:address":"Parklaan 21",
    "sg:city":"Bussum",
    "sg:orig_category":"Verzekeringen",
    "sg:phone":"+31 35 691 4075",
    "sg:postcode":"1406 KK",
    "sg:province":"Noord-Holland",
    "wof:name":"Kampass Assurantien",
    "wof:placetype":"venue"
},
  "geometry": {"coordinates":[5.151502,52.272953],"type":"Point"}
}