{
  "type": "Feature",
  "properties": {
    "addr:full":"Boerhaaveln 59 Doetinchem Gelderland 7002 HV",
    "addr:housenumber":"59",
    "addr:postcode":"7002 hv",
    "addr:street":"Boerhaaveln;Gelderland",
    "iso:country":"NL",
    "sg:address":"Boerhaaveln 59",
    "sg:city":"Doetinchem",
    "sg:orig_category":"Waterbehandeling En Waterzuiverings- Systemen",
    "sg:phone":"+31 314 363 003",
    "sg:postcode":"7002 HV",
    "sg:province":"Gelderland",
    "wof:name":"Aqua Partner",
    "wof:placetype":"venue"
},
  "geometry": {"coordinates":[6.2910552025,51.963596344],"type":"Point"}
}