{
  "type": "Feature",
  "properties": {
    "iso:country":"NL",
    "sg:address":"Kobaltstraat 62",
    "sg:city":"Apeldoorn",
    "sg:orig_category":"Autokeuringen",
    "sg:phone":"+31 55 541 1530",
    "sg:postcode":"7334 AT",
    "sg:province":"Gelderland",
    "wof:name":"G.A. Neuteboom Spijker",
    "wof:placetype":"venue"
},
  "geometry": {"coordinates":[5.957752,52.192783],"type":"Point"}
}