{
  "type": "Feature",
  "properties": {
    "addr:full":"Duitslandstraat 11 Ijsselstein Ut Utrecht 3402 TJ",
    "addr:housenumber":"11",
    "addr:postcode":"3402 tj",
    "addr:street":"Duitslandstraat",
    "iso:country":"NL",
    "sg:address":"Duitslandstraat 11",
    "sg:city":"Ijsselstein Ut",
    "sg:classifiers":[
        {
            "category":"Education",
            "subcategory":"Preschool",
            "type":"Public Place"
        }
    ],
    "sg:phone":"+31 30 688 2725",
    "sg:postcode":"3402 TJ",
    "sg:province":"Utrecht",
    "sg:tags":[
        "kleuteronderwijs",
        "basis-"
    ],
    "wof:name":"Paulusschool School V Kath Basisonderwij",
    "wof:placetype":"venue"
},
  "geometry": {"coordinates":[5.055547,52.022717],"type":"Point"}
}