{
  "type": "Feature",
  "properties": {
    "iso:country":"NL",
    "sg:address":"Hessenbergweg 95",
    "sg:city":"Amsterdam Zuidoost",
    "sg:orig_category":"Elektriciens",
    "sg:phone":"+31 20 686 5798",
    "sg:postcode":"1101 CX",
    "sg:province":"North Holland",
    "wof:name":"Croon Elektrotechniek",
    "wof:placetype":"venue"
},
  "geometry": {"coordinates":[4.945315,52.304634],"type":"Point"}
}