{
  "type": "Feature",
  "properties": {
    "addr:full":"Brinkstraat 45 Losser Overijssel 7581 GB",
    "addr:housenumber":"45",
    "addr:postcode":"7581 gb",
    "addr:street":"Brinkstraat",
    "iso:country":"NL",
    "sg:address":"Brinkstraat 45",
    "sg:city":"Losser",
    "sg:orig_category":"Kappers",
    "sg:phone":"+31 53 538 1810",
    "sg:postcode":"7581 GB",
    "sg:province":"Overijssel",
    "wof:name":"Kapsalon Raymond'S Hairfashion",
    "wof:placetype":"venue"
},
  "geometry": {"coordinates":[7.0075469017,52.2626953125],"type":"Point"}
}