{
  "type": "Feature",
  "properties": {
    "addr:full":"Gideonwg 4 Groningen Groningen 9723 BM",
    "addr:housenumber":"4",
    "addr:postcode":"9723 bm",
    "addr:street":"Gideonwg",
    "iso:country":"NL",
    "sg:address":"Gideonwg 4",
    "sg:city":"Groningen",
    "sg:orig_category":"Autolakken",
    "sg:phone":"+31 50 312 7929",
    "sg:postcode":"9723 BM",
    "sg:province":"Groningen",
    "sg:website":"http://www.metalak.nl",
    "wof:name":"Metalak",
    "wof:placetype":"venue"
},
  "geometry": {"coordinates":[6.597939,53.202751],"type":"Point"}
}