{
  "type": "Feature",
  "properties": {
    "addr:full":"G C Marshallstr 30 Groningen Groningen 9728 WS",
    "addr:housenumber":"30",
    "addr:postcode":"9728 ws",
    "iso:country":"NL",
    "sg:address":"G C Marshallstr 30",
    "sg:city":"Groningen",
    "sg:orig_category":"Organisatiebureaus",
    "sg:phone":"+31 50 526 3338",
    "sg:postcode":"9728 WS",
    "sg:province":"Groningen",
    "wof:name":"Raad & Daad",
    "wof:placetype":"venue"
},
  "geometry": {"coordinates":[6.5537948608,53.1840782166],"type":"Point"}
}