{
  "type": "Feature",
  "properties": {
    "iso:country":"NL",
    "sg:address":"Burgemeester Lemmensstr 271",
    "sg:city":"Geleen",
    "sg:classifiers":[
        {
            "category":"Fast Food",
            "type":"Food & Drink"
        }
    ],
    "sg:phone":"+31 46 474 2215",
    "sg:postcode":"6163 JJ",
    "sg:province":"Limburg",
    "sg:tags":[
        "afhaal",
        "restaurant"
    ],
    "wof:name":"Friture Nico",
    "wof:placetype":"venue"
},
  "geometry": {"coordinates":[5.808298,50.981956],"type":"Point"}
}