{
  "type": "Feature",
  "properties": {
    "addr:full":"Roer 75 Groningen Groningen 9733 AH",
    "addr:housenumber":"75",
    "addr:postcode":"9733 ah",
    "addr:street":"Roer",
    "iso:country":"NL",
    "sg:address":"Roer 75",
    "sg:city":"Groningen",
    "sg:orig_category":"Vertaal- And Tolkenbureaus",
    "sg:phone":"+31 50 541 0158",
    "sg:postcode":"9733 AH",
    "sg:province":"Groningen",
    "wof:name":"Vertaalbureau Maas",
    "wof:placetype":"venue"
},
  "geometry": {"coordinates":[6.628598,53.239162],"type":"Point"}
}