{
  "type": "Feature",
  "properties": {
    "addr:full":"Gerritsenweg 1 Zutphen Gelderland 7202 BP",
    "addr:housenumber":"1",
    "addr:postcode":"7202 bp",
    "addr:street":"Gerritsenweg;Gelderland",
    "iso:country":"NL",
    "sg:address":"Gerritsenweg 1",
    "sg:city":"Zutphen",
    "sg:orig_category":"Wegen And Sportterreinen",
    "sg:phone":"+31 575 519 102",
    "sg:postcode":"7202 BP",
    "sg:province":"Gelderland",
    "wof:name":"De Klinker Bv",
    "wof:placetype":"venue"
},
  "geometry": {"coordinates":[6.1953811646,52.1506881714],"type":"Point"}
}