{
  "type": "Feature",
  "properties": {
    "addr:full":"Amsterdamseweg 24 Amstelveen Noord-Holland 1182 HD",
    "addr:housenumber":"24",
    "addr:postcode":"1182 hd",
    "addr:street":"Amsterdamseweg",
    "iso:country":"NL",
    "sg:address":"Amsterdamseweg 24",
    "sg:city":"Amstelveen",
    "sg:orig_category":"Timmerwerk Van Hout And Kunststof",
    "sg:phone":"+31 20 647 6768",
    "sg:postcode":"1182 HD",
    "sg:province":"Noord-Holland",
    "wof:name":"Finishing Touch Meubelmakerij",
    "wof:placetype":"venue"
},
  "geometry": {"coordinates":[4.84681,52.304962],"type":"Point"}
}