{
  "type": "Feature",
  "properties": {
    "addr:full":"Energieweg 1 Spijkenisse South Holland 3201 LH",
    "addr:housenumber":"1",
    "addr:postcode":"3201 lh",
    "addr:street":"Energieweg",
    "iso:country":"NL",
    "sg:address":"Energieweg 1",
    "sg:city":"Spijkenisse",
    "sg:classifiers":[
        {
            "category":"Retail",
            "subcategory":"Storage",
            "type":"Services"
        }
    ],
    "sg:phone":"+31 181 613 144",
    "sg:postcode":"3201 LH",
    "sg:province":"South Holland",
    "sg:tags":[
        "opslag",
        "bewaring"
    ],
    "wof:name":"Sgs Logistics Services",
    "wof:placetype":"venue"
},
  "geometry": {"coordinates":[4.336368084,51.8493614197],"type":"Point"}
}