{
  "type": "Feature",
  "properties": {
    "addr:full":"Laboratoriumpln 61 Deventer Missouri 7411 CH",
    "addr:housenumber":"61",
    "addr:postcode":"7411",
    "addr:street":"Laboratoriumpln",
    "iso:country":"NL",
    "sg:address":"Laboratoriumpln 61",
    "sg:city":"Deventer",
    "sg:orig_category":"Verenigingen En Stichtingen",
    "sg:phone":"+31 570 611 416",
    "sg:postcode":"7411 CH",
    "sg:province":"Missouri",
    "sg:website":"http://www.cultureleraad.nl",
    "wof:name":"Culturele Raad Deventer",
    "wof:placetype":"venue"
},
  "geometry": {"coordinates":[-89.21163199999999,36.820946],"type":"Point"}
}