{
  "type": "Feature",
  "properties": {
    "addr:full":"G Ter Borchstr 63 Meppel Provincie Drenthe 7944 GM",
    "addr:housenumber":"63",
    "addr:postcode":"7944 gm",
    "addr:street":"G;Provincie Drenthe",
    "iso:country":"NL",
    "sg:address":"G Ter Borchstr 63",
    "sg:city":"Meppel",
    "sg:orig_category":"Grafisch Ontwerpers",
    "sg:phone":"+31 522 260 685",
    "sg:postcode":"7944 GM",
    "sg:province":"Provincie Drenthe",
    "sg:website":"http://www.hoevenberg.nl",
    "wof:name":"Hoevenberg, Bert",
    "wof:placetype":"venue"
},
  "geometry": {"coordinates":[6.178169,52.685799],"type":"Point"}
}