{
  "type": "Feature",
  "properties": {
    "addr:full":"Buitenhofdreef 270 Delft Zuid-Holland 2625 RE",
    "addr:housenumber":"270",
    "addr:postcode":"2625 re",
    "addr:street":"Buitenhofdreef",
    "iso:country":"NL",
    "sg:address":"Buitenhofdreef 270",
    "sg:city":"Delft",
    "sg:orig_category":"Verenigingen En Stichtingen",
    "sg:phone":"+31 15 257 0944",
    "sg:postcode":"2625 RE",
    "sg:province":"Zuid-Holland",
    "wof:name":"Prot Chr Basisond, Sticht",
    "wof:placetype":"venue"
},
  "geometry": {"coordinates":[4.344157,51.991562],"type":"Point"}
}