{
  "type": "Feature",
  "properties": {
    "iso:country":"NL",
    "sg:address":"Rentmeesterslaan 57",
    "sg:city":"Amstelveen",
    "sg:orig_category":"Boekhouders",
    "sg:phone":"+31 20 453 8833",
    "sg:postcode":"1181 DP",
    "sg:province":"North Holland",
    "wof:name":"B.T.C. Bos Trustco",
    "wof:placetype":"venue"
},
  "geometry": {"coordinates":[4.861552,52.318146],"type":"Point"}
}