{
  "type": "Feature",
  "properties": {
    "addr:full":"Oude Singel 24 Leiden Zuid-Holland 2312 RA",
    "addr:housenumber":"24",
    "addr:postcode":"2312 ra",
    "addr:street":"Oude Singel",
    "iso:country":"NL",
    "sg:address":"Oude Singel 24",
    "sg:city":"Leiden",
    "sg:orig_category":"Muziekinstrumenten Fab",
    "sg:phone":"+31 71 512 3564",
    "sg:postcode":"2312 RA",
    "sg:province":"Zuid-Holland",
    "wof:name":"Kerkorgelbouw P.C. Bik",
    "wof:placetype":"venue"
},
  "geometry": {"coordinates":[4.487326,52.162914],"type":"Point"}
}