{
  "type": "Feature",
  "properties": {
    "iso:country":"NL",
    "sg:address":"Lage Gouwe 208",
    "sg:city":"Gouda",
    "sg:orig_category":"Boekhouders",
    "sg:phone":"+31 182 524 552",
    "sg:postcode":"2801 LM",
    "sg:province":"Zuid-Holland",
    "wof:name":"Admini Gouda",
    "wof:placetype":"venue"
},
  "geometry": {"coordinates":[4.70517,52.011482],"type":"Point"}
}