{
  "type": "Feature",
  "properties": {
    "iso:country":"NL",
    "sg:address":"Bergseln 338A",
    "sg:city":"Rotterdam",
    "sg:orig_category":"Behangselpapier En Wandbekleding",
    "sg:phone":"+31 10 466 0995",
    "sg:postcode":"3038 CP",
    "sg:province":"South Holland",
    "wof:name":"Rotterdams Behangpaleis",
    "wof:placetype":"venue"
},
  "geometry": {"coordinates":[4.46465,51.935558],"type":"Point"}
}