{
  "type": "Feature",
  "properties": {
    "addr:full":"Kalmoesstr 13 Lisserbroek Noord-Holland 2165 XJ",
    "addr:housenumber":"13",
    "addr:postcode":"2165 xj",
    "addr:street":"Kalmoesstr",
    "iso:country":"NL",
    "sg:address":"Kalmoesstr 13",
    "sg:city":"Lisserbroek",
    "sg:orig_category":"Verenigingen En Stichtingen",
    "sg:phone":"+31 252 413 222",
    "sg:postcode":"2165 XJ",
    "sg:province":"Noord-Holland",
    "wof:name":"Nhdb",
    "wof:placetype":"venue"
},
  "geometry": {"coordinates":[4.573818,52.259529],"type":"Point"}
}