{
  "type": "Feature",
  "properties": {
    "iso:country":"NL",
    "sg:address":"Kalmoesstr 13",
    "sg:city":"Lisserbroek",
    "sg:orig_category":"Verenigingen En Stichtingen",
    "sg:phone":"+31 252 413 222",
    "sg:postcode":"2165 XJ",
    "sg:province":"Noord-Holland",
    "wof:name":"Nhdb",
    "wof:placetype":"venue"
},
  "geometry": {"coordinates":[4.573818,52.259529],"type":"Point"}
}