{
  "type": "Feature",
  "properties": {
    "addr:full":"F V Adrichemln 80 Haarlem North Holland 2035 VD",
    "addr:housenumber":"80",
    "addr:postcode":"2035 vd",
    "addr:street":"Adrichemln",
    "iso:country":"NL",
    "sg:address":"F V Adrichemln 80",
    "sg:city":"Haarlem",
    "sg:orig_category":"Postkantoren",
    "sg:phone":"+31 23 535 8519",
    "sg:postcode":"2035 VD",
    "sg:province":"North Holland",
    "sg:website":"http://www.postkantoor.nl",
    "wof:name":"Postkantoor",
    "wof:placetype":"venue"
},
  "geometry": {"coordinates":[4.65946,52.365311],"type":"Point"}
}