{
  "type": "Feature",
  "properties": {
    "addr:full":"Spinveld 72 Breda Noord-Brabant 4815 HT",
    "addr:housenumber":"72",
    "addr:postcode":"4815 ht",
    "addr:street":"Spinveld",
    "iso:country":"NL",
    "sg:address":"Spinveld 72",
    "sg:city":"Breda",
    "sg:orig_category":"Autokeuringen",
    "sg:phone":"+31 76 521 8509",
    "sg:postcode":"4815 HT",
    "sg:province":"Noord-Brabant",
    "wof:name":"Garage C. Nuitermans V/H J. Verhulst",
    "wof:placetype":"venue"
},
  "geometry": {"coordinates":[4.751417,51.597836],"type":"Point"}
}