{
  "type": "Feature",
  "properties": {
    "iso:country":"NL",
    "sg:address":"Postbus 2020",
    "sg:city":"Bussum",
    "sg:orig_category":"Verenigingen En Stichtingen",
    "sg:phone":"+31 35 697 8000",
    "sg:postcode":"1400 DA",
    "sg:province":"Noord-Holland",
    "sg:website":"http://www.nierstichting.nl",
    "wof:name":"Nierstichting Nederland",
    "wof:placetype":"venue"
},
  "geometry": {"coordinates":[5.162605,52.276829],"type":"Point"}
}