{
  "type": "Feature",
  "properties": {
    "addr:full":"Hoogstr 17 Abcoude North Holland 1391 BR",
    "addr:housenumber":"17",
    "addr:postcode":"1391 br",
    "addr:street":"Hoogstr",
    "iso:country":"NL",
    "sg:address":"Hoogstr 17",
    "sg:city":"Abcoude",
    "sg:orig_category":"Juweliers",
    "sg:phone":"+31 294 283 206",
    "sg:postcode":"1391 BR",
    "sg:province":"North Holland",
    "wof:name":"Dorrestijn, G C",
    "wof:placetype":"venue"
},
  "geometry": {"coordinates":[4.974467,52.270828],"type":"Point"}
}