{
  "type": "Feature",
  "properties": {
    "addr:full":"Van Stolbergweg 2 Veendam Groningen 9641 HL",
    "addr:housenumber":"2",
    "addr:postcode":"9641 hl",
    "addr:street":"Van Stolbergweg",
    "iso:country":"NL",
    "sg:address":"Van Stolbergweg 2",
    "sg:city":"Veendam",
    "sg:orig_category":"Meubelzaken, Woning- And Keukeninrichting",
    "sg:phone":"+31 598 613 737",
    "sg:postcode":"9641 HL",
    "sg:province":"Groningen",
    "wof:name":"Weijer Wonen",
    "wof:placetype":"venue"
},
  "geometry": {"coordinates":[6.878293,53.10104],"type":"Point"}
}