{
  "type": "Feature",
  "properties": {
    "addr:full":"Het Nw Diep 22 Den Helder Noord-Holland 1781 AC",
    "addr:housenumber":"22",
    "addr:postcode":"1781 ac",
    "addr:street":"Het Nw Diep",
    "iso:country":"NL",
    "sg:address":"Het Nw Diep 22",
    "sg:city":"Den Helder",
    "sg:orig_category":"On- Offshore",
    "sg:phone":"+31 223 684 120",
    "sg:postcode":"1781 AC",
    "sg:province":"Noord-Holland",
    "wof:name":"World Marine Support Bv",
    "wof:placetype":"venue"
},
  "geometry": {"coordinates":[4.775931,52.957447],"type":"Point"}
}