{
  "type": "Feature",
  "properties": {
    "addr:full":"Willem 2 Sngl 10 Roermond Limburg 6041 HS",
    "addr:housenumber":"2;10",
    "addr:postcode":"6041 hs",
    "addr:street":"Willem;Sngl",
    "iso:country":"NL",
    "sg:address":"Willem 2 Sngl 10",
    "sg:city":"Roermond",
    "sg:orig_category":"Kappers",
    "sg:phone":"+31 475 350 767",
    "sg:postcode":"6041 HS",
    "sg:province":"Limburg",
    "wof:name":"Schlicher Kapsalon",
    "wof:placetype":"venue"
},
  "geometry": {"coordinates":[5.991872,51.191574],"type":"Point"}
}