{
  "type": "Feature",
  "properties": {
    "addr:full":"Kerkln 2 Wateringen Zuid-Holland 2291 CG",
    "addr:housenumber":"2",
    "addr:postcode":"2291 cg",
    "addr:street":"Kerkln",
    "iso:country":"NL",
    "sg:address":"Kerkln 2",
    "sg:city":"Wateringen",
    "sg:orig_category":"Fotoreportages",
    "sg:phone":"+31 174 292 826",
    "sg:postcode":"2291 CG",
    "sg:province":"Zuid-Holland",
    "sg:website":"http://www.loch.nl",
    "wof:name":"Loch Combi Foto Bv",
    "wof:placetype":"venue"
},
  "geometry": {"coordinates":[4.2735,52.023331],"type":"Point"}
}