{
  "type": "Feature",
  "properties": {
    "addr:full":"Zoeterwoudsewg 166 Leiden South Holland 2321 GS",
    "addr:housenumber":"166",
    "addr:postcode":"2321 gs",
    "iso:country":"NL",
    "sg:address":"Zoeterwoudsewg 166",
    "sg:city":"Leiden",
    "sg:orig_category":"Psychosociale Therapeuten",
    "sg:phone":"+31 71 576 0578",
    "sg:postcode":"2321 GS",
    "sg:province":"South Holland",
    "wof:name":"Praktijk Voor Psycho-Soc Begeleiding",
    "wof:placetype":"venue"
},
  "geometry": {"coordinates":[4.48672,52.143063],"type":"Point"}
}