{
  "type": "Feature",
  "properties": {
    "addr:full":"K Doormanstr 3 Haastrecht Zuid-Holland 2851 TS",
    "addr:housenumber":"3",
    "addr:postcode":"2851 ts",
    "addr:street":"Doormanstr",
    "iso:country":"NL",
    "sg:address":"K Doormanstr 3",
    "sg:city":"Haastrecht",
    "sg:orig_category":"Bestratingen",
    "sg:phone":"+31 182 501 373",
    "sg:postcode":"2851 TS",
    "sg:province":"Zuid-Holland",
    "wof:name":"Neuteboom, H",
    "wof:placetype":"venue"
},
  "geometry": {"coordinates":[4.771918,52.00317],"type":"Point"}
}