{
  "type": "Feature",
  "properties": {
    "iso:country":"NL",
    "sg:address":"Industriewg Z 30A",
    "sg:city":"Amerongen",
    "sg:orig_category":"Autoschade- Herstelbedrijven",
    "sg:phone":"+31 343 456 956",
    "sg:postcode":"3958 VX",
    "sg:province":"Utrecht",
    "sg:website":"http://www.autoschade-amerongen.nl",
    "wof:name":"Autoschade Amerongen",
    "wof:placetype":"venue"
},
  "geometry": {"coordinates":[5.453417,52.002632],"type":"Point"}
}