{
  "type": "Feature",
  "properties": {
    "addr:full":"Geerln 27B Ridderkerk Zuid-Holland 2981 AP",
    "addr:housenumber":"27b",
    "addr:postcode":"2981 ap",
    "addr:street":"Geerln",
    "iso:country":"NL",
    "sg:address":"Geerln 27B",
    "sg:city":"Ridderkerk",
    "sg:orig_category":"Sauna'S",
    "sg:phone":"+31 180 432 833",
    "sg:postcode":"2981 AP",
    "sg:province":"Zuid-Holland",
    "sg:website":"http://www.thermenridderkerk.nl",
    "wof:name":"Thermen Ridderkerk",
    "wof:placetype":"venue"
},
  "geometry": {"coordinates":[4.598051,51.871727],"type":"Point"}
}