{
  "type": "Feature",
  "properties": {
    "addr:full":"Molenstr 10A Deurne Noord-Brabant 5751 LD",
    "addr:housenumber":"10a",
    "addr:postcode":"5751 ld",
    "addr:street":"Molenstr",
    "iso:country":"NL",
    "sg:address":"Molenstr 10A",
    "sg:city":"Deurne",
    "sg:orig_category":"Meubelstoffering",
    "sg:phone":"+31 493 312 402",
    "sg:postcode":"5751 LD",
    "sg:province":"Noord-Brabant",
    "wof:name":"Keeren, C J W",
    "wof:placetype":"venue"
},
  "geometry": {"coordinates":[5.795853,51.463326],"type":"Point"}
}