{
  "type": "Feature",
  "properties": {
    "addr:full":"Maandereind 11 Ede Gld Gelderland 6711 AA",
    "addr:housenumber":"11",
    "addr:postcode":"6711 aa",
    "addr:street":"Maandereind;Gld Gelderland",
    "iso:country":"NL",
    "sg:address":"Maandereind 11",
    "sg:city":"Ede Gld",
    "sg:orig_category":"Schoenen",
    "sg:phone":"+31 318 617 722",
    "sg:postcode":"6711 AA",
    "sg:province":"Gelderland",
    "wof:name":"Schoenhuis Theo Jansen",
    "wof:placetype":"venue"
},
  "geometry": {"coordinates":[5.669712,52.043152],"type":"Point"}
}