{
  "type": "Feature",
  "properties": {
    "addr:full":"Koningstraat 4 Naaldwijk South Holland 2671 JV",
    "addr:housenumber":"4",
    "addr:postcode":"2671 jv",
    "addr:street":"Koningstraat",
    "iso:country":"NL",
    "sg:address":"Koningstraat 4",
    "sg:city":"Naaldwijk",
    "sg:orig_category":"Gespecialiseerde Bouw",
    "sg:phone":"+31 174 624 382",
    "sg:postcode":"2671 JV",
    "sg:province":"South Holland",
    "wof:name":"A W J M Vogels",
    "wof:placetype":"venue"
},
  "geometry": {"coordinates":[4.207729,51.992432],"type":"Point"}
}