{
  "type": "Feature",
  "properties": {
    "addr:full":"Vierschaarserf 9 Houten Utrecht 3991 KD",
    "addr:housenumber":"9",
    "addr:postcode":"3991 kd",
    "addr:street":"Vierschaarserf",
    "iso:country":"NL",
    "sg:address":"Vierschaarserf 9",
    "sg:city":"Houten",
    "sg:orig_category":"Logopedisten",
    "sg:phone":"+31 30 637 5769",
    "sg:postcode":"3991 KD",
    "sg:province":"Utrecht",
    "wof:name":"Los, Rian",
    "wof:placetype":"venue"
},
  "geometry": {"coordinates":[5.167723,52.02441],"type":"Point"}
}