{
  "type": "Feature",
  "properties": {
    "addr:full":"De Boelelaan 1115 Amsterdam North Holland 1081 HV",
    "addr:housenumber":"1115",
    "addr:postcode":"1081 hv",
    "addr:street":"De Boelelaan",
    "iso:country":"NL",
    "sg:address":"De Boelelaan 1115",
    "sg:city":"Amsterdam",
    "sg:orig_category":"Organisaties And Verenigingen",
    "sg:phone":"+31 20 444 5344",
    "sg:postcode":"1081 HV",
    "sg:province":"North Holland",
    "wof:name":"Vuniverse",
    "wof:placetype":"venue"
},
  "geometry": {"coordinates":[4.8644280434,52.3347816467],"type":"Point"}
}