{
  "type": "Feature",
  "properties": {
    "iso:country":"NL",
    "sg:address":"Bloemerstraat 71",
    "sg:city":"Nijmegen",
    "sg:orig_category":"Werving And Selectie Van Tijdelijk Personeel And Uitzendkantoren",
    "sg:phone":"+31 24 323 6761",
    "sg:postcode":"6511 ED",
    "sg:province":"Gelderland",
    "wof:name":"Content",
    "wof:placetype":"venue"
},
  "geometry": {"coordinates":[5.8606748581,51.8453330994],"type":"Point"}
}