{
  "type": "Feature",
  "properties": {
    "addr:full":"De Boeleln 7 Amsterdam Noord-Holland 1083 HJ",
    "addr:housenumber":"7",
    "addr:postcode":"1083 hj",
    "iso:country":"NL",
    "sg:address":"De Boeleln 7",
    "sg:city":"Amsterdam",
    "sg:classifiers":[
        {
            "category":"Shopping",
            "subcategory":"News",
            "type":"Retail Goods"
        }
    ],
    "sg:phone":"+31 20 504 2800",
    "sg:postcode":"1083 HJ",
    "sg:province":"Noord-Holland",
    "sg:tags":[
        "maandbladen",
        "en",
        "week-"
    ],
    "sg:website":"http://www.autokompas.nl",
    "wof:name":"Autokompas",
    "wof:placetype":"venue"
},
  "geometry": {"coordinates":[4.8892102242,52.330280304],"type":"Point"}
}