{
  "type": "Feature",
  "properties": {
    "iso:country":"NL",
    "sg:address":"Jan Van Arkelstraat 44",
    "sg:city":"Raalte",
    "sg:orig_category":"Drukkerijen And Copyshops",
    "sg:phone":"+31 572 362 096",
    "sg:postcode":"8101 EP",
    "sg:province":"Overijssel",
    "wof:name":"Regio-Druk Raalte",
    "wof:placetype":"venue"
},
  "geometry": {"coordinates":[6.265036,52.381718],"type":"Point"}
}