{
  "type": "Feature",
  "properties": {
    "addr:full":"J Vd Vondelstr 11 Sliedrecht Zuid-Holland 3362 TK",
    "addr:housenumber":"11",
    "addr:postcode":"3362 tk",
    "iso:country":"NL",
    "sg:address":"J Vd Vondelstr 11",
    "sg:city":"Sliedrecht",
    "sg:orig_category":"Adviesbureaus Bouwkunde",
    "sg:phone":"+31 184 411 022",
    "sg:postcode":"3362 TK",
    "sg:province":"Zuid-Holland",
    "wof:name":"Teeuw",
    "wof:placetype":"venue"
},
  "geometry": {"coordinates":[4.776219,51.819366],"type":"Point"}
}