{
  "type": "Feature",
  "properties": {
    "iso:country":"NL",
    "sg:address":"J V W Kooyln 18",
    "sg:city":"Naarden",
    "sg:orig_category":"Bedrijfsopleidingen",
    "sg:phone":"+31 35 695 2230",
    "sg:postcode":"1411 JZ",
    "sg:province":"Noord-Holland",
    "wof:name":"Pto",
    "wof:placetype":"venue"
},
  "geometry": {"coordinates":[5.161848,52.296371],"type":"Point"}
}