{
  "type": "Feature",
  "properties": {
    "addr:full":"Sluisjesdk 110 Rotterdam Zuid-Holland 3087 AJ",
    "addr:housenumber":"110",
    "addr:postcode":"3087 aj",
    "iso:country":"NL",
    "sg:address":"Sluisjesdk 110",
    "sg:city":"Rotterdam",
    "sg:orig_category":"Lichtreclame",
    "sg:phone":"+31 10 428 0065",
    "sg:postcode":"3087 AJ",
    "sg:province":"Zuid-Holland",
    "wof:name":"Bullet",
    "wof:placetype":"venue"
},
  "geometry": {"coordinates":[4.452298,51.896294],"type":"Point"}
}