{
  "type": "Feature",
  "properties": {
    "addr:full":"Planetenln 148 Haarlem Noord-Holland 2024 EW",
    "addr:housenumber":"148",
    "addr:postcode":"2024 ew",
    "iso:country":"NL",
    "sg:address":"Planetenln 148",
    "sg:city":"Haarlem",
    "sg:orig_category":"Satellietontvangst- En Antenne-Installaties",
    "sg:phone":"+31 23 527 3378",
    "sg:postcode":"2024 EW",
    "sg:province":"Noord-Holland",
    "sg:website":"http://www.jansens-elektrotechniek.nl",
    "wof:name":"Jansens Elektrotechn Inst Buro",
    "wof:placetype":"venue"
},
  "geometry": {"coordinates":[4.646131,52.407722],"type":"Point"}
}