{
  "type": "Feature",
  "properties": {
    "addr:full":"Oldenzaalsestraat 223 Enschede Overijssel 7523 AC",
    "addr:housenumber":"223",
    "addr:postcode":"7523 ac",
    "addr:street":"Oldenzaalsestraat",
    "iso:country":"NL",
    "sg:address":"Oldenzaalsestraat 223",
    "sg:city":"Enschede",
    "sg:orig_category":"Artsen And Specialisten",
    "sg:phone":"+31 53 435 8476",
    "sg:postcode":"7523 AC",
    "sg:province":"Overijssel",
    "wof:name":"J.H.J. Ten Brinke",
    "wof:placetype":"venue"
},
  "geometry": {"coordinates":[6.901549,52.230251],"type":"Point"}
}