{
  "type": "Feature",
  "properties": {
    "iso:country":"NL",
    "sg:address":"Kapelstr 2",
    "sg:city":"Rykevoort",
    "sg:orig_category":"Voetbalverenigingen",
    "sg:phone":"+31 485 371 462",
    "sg:postcode":"5447 AB",
    "sg:province":"North Brabant",
    "wof:name":"Rksvw",
    "wof:placetype":"venue"
},
  "geometry": {"coordinates":[5.88379,51.65596],"type":"Point"}
}