{
  "type": "Feature",
  "properties": {
    "addr:full":"Bontekoestr 17 Rhenen Utrecht 3911 KC",
    "addr:housenumber":"17",
    "addr:postcode":"3911 kc",
    "addr:street":"Bontekoestr",
    "iso:country":"NL",
    "sg:address":"Bontekoestr 17",
    "sg:city":"Rhenen",
    "sg:orig_category":"Keukens",
    "sg:phone":"+31 317 613 345",
    "sg:postcode":"3911 KC",
    "sg:province":"Utrecht",
    "wof:name":"Hc",
    "wof:placetype":"venue"
},
  "geometry": {"coordinates":[5.568129,51.956493],"type":"Point"}
}