{
  "type": "Feature",
  "properties": {
    "addr:full":"Icaruswg 8A Leeuwarden Friesland 8938 AX",
    "addr:housenumber":"8a",
    "addr:postcode":"8938 ax",
    "addr:street":"Icaruswg",
    "iso:country":"NL",
    "sg:address":"Icaruswg 8A",
    "sg:city":"Leeuwarden",
    "sg:orig_category":"Bouwbureaus",
    "sg:phone":"+31 58 215 0172",
    "sg:postcode":"8938 AX",
    "sg:province":"Friesland",
    "wof:name":"Bouwma Bouwburo",
    "wof:placetype":"venue"
},
  "geometry": {"coordinates":[5.848504,53.197025],"type":"Point"}
}