{
  "type": "Feature",
  "properties": {
    "iso:country":"NL",
    "sg:address":"Icaruswg 8A",
    "sg:city":"Leeuwarden",
    "sg:orig_category":"Bouwbureaus",
    "sg:phone":"+31 58 215 0172",
    "sg:postcode":"8938 AX",
    "sg:province":"Friesland",
    "wof:name":"Bouwma Bouwburo",
    "wof:placetype":"venue"
},
  "geometry": {"coordinates":[5.848504,53.197025],"type":"Point"}
}