{
  "type": "Feature",
  "properties": {
    "addr:full":"Amperestraat 2 Zevenaar Gelderland 6902 PG",
    "addr:housenumber":"2",
    "addr:postcode":"6902 pg",
    "addr:street":"Amperestraat",
    "iso:country":"NL",
    "sg:address":"Amperestraat 2",
    "sg:city":"Zevenaar",
    "sg:orig_category":"Autokeuringen",
    "sg:phone":"+31 316 331 866",
    "sg:postcode":"6902 PG",
    "sg:province":"Gelderland",
    "wof:name":"W.P.I. Bv",
    "wof:placetype":"venue"
},
  "geometry": {"coordinates":[6.083024,51.936008],"type":"Point"}
}