{
  "type": "Feature",
  "properties": {
    "addr:full":"Raadhuispln 77A Krimpen Ad Yssel South Holland 2922 AH",
    "addr:housenumber":"77a",
    "addr:postcode":"2922 ah",
    "addr:street":"Raadhuispln;Yssel",
    "iso:country":"NL",
    "sg:address":"Raadhuispln 77A",
    "sg:city":"Krimpen Ad Yssel",
    "sg:orig_category":"Banken",
    "sg:phone":"+31 180 530 600",
    "sg:postcode":"2922 AH",
    "sg:province":"South Holland",
    "wof:name":"Rabobank",
    "wof:placetype":"venue"
},
  "geometry": {"coordinates":[4.5884699821,51.9140777588],"type":"Point"}
}