{
  "type": "Feature",
  "properties": {
    "addr:full":"Computerwg 21 Amsterdam Noord-Holland 1033 RH",
    "addr:housenumber":"21",
    "addr:postcode":"1033 rh",
    "addr:street":"Computerwg",
    "iso:country":"NL",
    "sg:address":"Computerwg 21",
    "sg:city":"Amsterdam",
    "sg:orig_category":"Machinefabrieken",
    "sg:phone":"+31 20 697 2411",
    "sg:postcode":"1033 RH",
    "sg:province":"Noord-Holland",
    "sg:website":"http://www.vandammachine.com",
    "wof:name":"Dam Machine Bv, Van",
    "wof:placetype":"venue"
},
  "geometry": {"coordinates":[4.890462,52.406017],"type":"Point"}
}