{
  "type": "Feature",
  "properties": {
    "addr:full":"De Zwanebloem 35 Zwartsluis Overijssel 8064 HK",
    "addr:housenumber":"35",
    "addr:postcode":"8064 hk",
    "addr:street":"De Zwanebloem",
    "iso:country":"NL",
    "sg:address":"De Zwanebloem 35",
    "sg:city":"Zwartsluis",
    "sg:orig_category":"Boekhouders",
    "sg:phone":"+31 38 386 7120",
    "sg:postcode":"8064 HK",
    "sg:province":"Overijssel",
    "wof:name":"Administratiekantoor J H Van Beers",
    "wof:placetype":"venue"
},
  "geometry": {"coordinates":[6.072651,52.646481],"type":"Point"}
}