{
  "type": "Feature",
  "properties": {
    "addr:full":"Ooftstraat 17 Utrecht Utrecht 3572 HR",
    "addr:housenumber":"17",
    "addr:postcode":"3572 hr",
    "addr:street":"Ooftstraat",
    "iso:country":"NL",
    "sg:address":"Ooftstraat 17",
    "sg:city":"Utrecht",
    "sg:orig_category":"Vertaal- And Tolkenbureaus",
    "sg:phone":"+31 30 271 1294",
    "sg:postcode":"3572 HR",
    "sg:province":"Utrecht",
    "wof:name":"Vertaalbureau Van Hoorn",
    "wof:placetype":"venue"
},
  "geometry": {"coordinates":[5.13486,52.09716],"type":"Point"}
}