{
  "type": "Feature",
  "properties": {
    "iso:country":"NL",
    "sg:address":"Meerkoetstraat 37",
    "sg:city":"Capelle A/D Ijssel",
    "sg:orig_category":"Gespecialiseerde Bouw",
    "sg:phone":"+31 10 450 1382",
    "sg:postcode":"2903 EN",
    "sg:province":"Zuid-Holland",
    "wof:name":"A. Van Vliet",
    "wof:placetype":"venue"
},
  "geometry": {"coordinates":[4.594019,51.928905],"type":"Point"}
}