{
  "type": "Feature",
  "properties": {
    "iso:country":"NL",
    "sg:address":"Doelen 36",
    "sg:city":"Breda",
    "sg:orig_category":"Kinderopvang Behalve Thuis",
    "sg:phone":"+31 76 522 3631",
    "sg:postcode":"4813 GR",
    "sg:province":"North Brabant",
    "wof:name":"Nijntje",
    "wof:placetype":"venue"
},
  "geometry": {"coordinates":[4.738531,51.575287],"type":"Point"}
}