{
  "type": "Feature",
  "properties": {
    "addr:full":"F Halsstr 42 Zaandam Noord-Holland 1506 LH",
    "addr:housenumber":"42",
    "addr:postcode":"1506 lh",
    "iso:country":"NL",
    "sg:address":"F Halsstr 42",
    "sg:city":"Zaandam",
    "sg:classifiers":[
        {
            "category":"Retail",
            "subcategory":"Auto Repair",
            "type":"Services"
        }
    ],
    "sg:phone":"+31 75 616 8548",
    "sg:postcode":"1506 LH",
    "sg:province":"Noord-Holland",
    "sg:tags":[
        "garage"
    ],
    "wof:name":"Smit",
    "wof:placetype":"venue"
},
  "geometry": {"coordinates":[4.811331,52.452606],"type":"Point"}
}