{
  "type": "Feature",
  "properties": {
    "addr:full":"Dageraadstr 4 Almere Flevoland 1335 VN",
    "addr:housenumber":"4",
    "addr:postcode":"1335 vn",
    "addr:street":"Dageraadstr;Flevoland",
    "iso:country":"NL",
    "sg:address":"Dageraadstr 4",
    "sg:city":"Almere",
    "sg:orig_category":"Wasmachines En Wasdrogers - Onderhoud En Reparatie",
    "sg:phone":"+31 36 532 2418",
    "sg:postcode":"1335 VN",
    "sg:province":"Flevoland",
    "wof:name":"Almeerse Reparatie Dienst",
    "wof:placetype":"venue"
},
  "geometry": {"coordinates":[5.2981939316,52.406955719],"type":"Point"}
}