{
  "type": "Feature",
  "properties": {
    "addr:full":"Narcislaan 19 Wassenaar Zuid-Holland 2241 VP",
    "addr:housenumber":"19",
    "addr:postcode":"2241 vp",
    "addr:street":"Narcislaan",
    "iso:country":"NL",
    "sg:address":"Narcislaan 19",
    "sg:city":"Wassenaar",
    "sg:orig_category":"Boekhouders",
    "sg:phone":"+31 70 514 1877",
    "sg:postcode":"2241 VP",
    "sg:province":"Zuid-Holland",
    "wof:name":"Gold Finger",
    "wof:placetype":"venue"
},
  "geometry": {"coordinates":[4.416169,52.143517],"type":"Point"}
}