{
  "type": "Feature",
  "properties": {
    "iso:country":"NL",
    "sg:address":"Jan Steenlaan 15",
    "sg:city":"Voorhout",
    "sg:orig_category":"Kinderopvang Behalve Thuis",
    "sg:phone":"+31 252 215 044",
    "sg:postcode":"2215 CD",
    "sg:province":"South Holland",
    "wof:name":"De Bolderberg Voorhout",
    "wof:placetype":"venue"
},
  "geometry": {"coordinates":[4.478424,52.223351],"type":"Point"}
}