{
  "type": "Feature",
  "properties": {
    "addr:full":"Weg En Bos 34 Bergschenhoek Zuid-Holland 2661 DH",
    "addr:housenumber":"34",
    "addr:postcode":"2661 dh",
    "addr:street":"Weg En Bos",
    "iso:country":"NL",
    "sg:address":"Weg En Bos 34",
    "sg:city":"Bergschenhoek",
    "sg:orig_category":"Wegen And Sportterreinen",
    "sg:phone":"+31 10 521 9555",
    "sg:postcode":"2661 DH",
    "sg:province":"Zuid-Holland",
    "wof:name":"Aannemingsbedrijf D. Stuit Bv",
    "wof:placetype":"venue"
},
  "geometry": {"coordinates":[4.5061769485,51.9799079895],"type":"Point"}
}