{
  "type": "Feature",
  "properties": {
    "addr:full":"Rivierdijk 210 Sliedrecht Zuid-Holland 3361 AT",
    "addr:housenumber":"210",
    "addr:postcode":"3361",
    "addr:street":"Rivierdijk",
    "iso:country":"NL",
    "sg:address":"Rivierdijk 210",
    "sg:city":"Sliedrecht",
    "sg:orig_category":"Schilderwerk",
    "sg:phone":"+31 184 412 703",
    "sg:postcode":"3361 AT",
    "sg:province":"Zuid-Holland",
    "wof:name":"Den Breejen En Zoon Schilderwerken Bv",
    "wof:placetype":"venue"
},
  "geometry": {"coordinates":[4.794733,51.819302],"type":"Point"}
}