{
  "type": "Feature",
  "properties": {
    "iso:country":"NL",
    "sg:address":"Kleiweg 6",
    "sg:city":"Anna Paulowna",
    "sg:orig_category":"Verhuur Diversen",
    "sg:phone":"+31 223 535 079",
    "sg:postcode":"1761 LA",
    "sg:province":"Noord-Holland",
    "wof:name":"Ab Promotie & Evenementen",
    "wof:placetype":"venue"
},
  "geometry": {"coordinates":[4.840823,52.870567],"type":"Point"}
}