{
  "type": "Feature",
  "properties": {
    "iso:country":"NL",
    "sg:address":"Borculosewg 34",
    "sg:city":"Neede",
    "sg:orig_category":"Schilders",
    "sg:phone":"+31 545 291 585",
    "sg:postcode":"7161 HA",
    "sg:province":"Gelderland",
    "wof:name":"Emaus",
    "wof:placetype":"venue"
},
  "geometry": {"coordinates":[-121.31706200000001,38.299633],"type":"Point"}
}