{
  "type": "Feature",
  "properties": {
    "addr:full":"Kattegat 6C Woerden Utrecht 3446 CL",
    "addr:housenumber":"6c",
    "addr:postcode":"3446",
    "addr:street":"Kattegat",
    "iso:country":"NL",
    "sg:address":"Kattegat 6C",
    "sg:city":"Woerden",
    "sg:orig_category":"Bouwmachines",
    "sg:phone":"+31 348 502 845",
    "sg:postcode":"3446 CL",
    "sg:province":"Utrecht",
    "wof:name":"Hartog Vof, G Den",
    "wof:placetype":"venue"
},
  "geometry": {"coordinates":[4.906334,52.077221],"type":"Point"}
}