{
  "type": "Feature",
  "properties": {
    "addr:full":"Merelplantsoen 48 Roelofarendsveen South Holland 2371 NX",
    "addr:housenumber":"48",
    "addr:postcode":"2371 nx",
    "addr:street":"Merelplantsoen",
    "iso:country":"NL",
    "sg:address":"Merelplantsoen 48",
    "sg:city":"Roelofarendsveen",
    "sg:orig_category":"Diverse Grafische Activiteiten",
    "sg:phone":"+31 71 331 9579",
    "sg:postcode":"2371 NX",
    "sg:province":"South Holland",
    "wof:name":"Prepresto Dtp",
    "wof:placetype":"venue"
},
  "geometry": {"coordinates":[4.626643,52.205502],"type":"Point"}
}