{
  "type": "Feature",
  "properties": {
    "addr:full":"Valeriaan 4 Nootdorp Zuid-Holland 2631 SP",
    "addr:housenumber":"4",
    "addr:postcode":"2631 sp",
    "addr:street":"Valeriaan",
    "iso:country":"NL",
    "sg:address":"Valeriaan 4",
    "sg:city":"Nootdorp",
    "sg:orig_category":"Loodgieterswerk, Verwarming And Sanitaire Installaties",
    "sg:phone":"+31 15 310 5632",
    "sg:postcode":"2631 SP",
    "sg:province":"Zuid-Holland",
    "wof:name":"G.H.M. V.D. Haar",
    "wof:placetype":"venue"
},
  "geometry": {"coordinates":[4.401429,52.042103],"type":"Point"}
}