{
  "type": "Feature",
  "properties": {
    "addr:full":"Huygendk 31 Oterleek Noord-Holland 1842 GR",
    "addr:housenumber":"31",
    "addr:postcode":"1842",
    "addr:street":"Huygendk",
    "iso:country":"NL",
    "sg:address":"Huygendk 31",
    "sg:city":"Oterleek",
    "sg:orig_category":"Gordijnen",
    "sg:phone":"+31 72 571 6801",
    "sg:postcode":"1842 GR",
    "sg:province":"Noord-Holland",
    "wof:name":"Mart",
    "wof:placetype":"venue"
},
  "geometry": {"coordinates":[4.83096,52.632713],"type":"Point"}
}