{
  "type": "Feature",
  "properties": {
    "iso:country":"NL",
    "sg:address":"Mauritswg 42",
    "sg:city":"Rotterdam",
    "sg:orig_category":"Juridische Adviseurs",
    "sg:phone":"+31 10 270 9267",
    "sg:postcode":"3012 JV",
    "sg:province":"Zuid-Holland",
    "sg:website":"http://www.justion.nl",
    "wof:name":"Justion Bv",
    "wof:placetype":"venue"
},
  "geometry": {"coordinates":[4.47287,51.91827],"type":"Point"}
}