{
  "type": "Feature",
  "properties": {
    "iso:country":"NL",
    "sg:address":"Bellweg 9",
    "sg:city":"Delft",
    "sg:orig_category":"Loodgieterswerk, Verwarming And Sanitaire Installaties",
    "sg:phone":"+31 15 257 0290",
    "sg:postcode":"2627 AW",
    "sg:province":"South Holland",
    "wof:name":"Loodgietersbedrijf W.A. Kuijpers Bv",
    "wof:placetype":"venue"
},
  "geometry": {"coordinates":[4.37151,51.987045],"type":"Point"}
}