{
  "type": "Feature",
  "properties": {
    "addr:full":"Traay 47 Driebergen Rysenb Utrecht 3971 GC",
    "addr:housenumber":"47",
    "addr:postcode":"3971 gc",
    "addr:street":"Traay;Rysenb",
    "iso:country":"NL",
    "sg:address":"Traay 47",
    "sg:city":"Driebergen Rysenb",
    "sg:orig_category":"Keukens",
    "sg:phone":"+31 343 516 724",
    "sg:postcode":"3971 GC",
    "sg:province":"Utrecht",
    "wof:name":"Heger Bv",
    "wof:placetype":"venue"
},
  "geometry": {"coordinates":[5.284855,52.052853],"type":"Point"}
}