{
  "type": "Feature",
  "properties": {
    "addr:full":"Granaatstraat 35 Hengelo Ov Overijssel 7554 TN",
    "addr:housenumber":"35",
    "addr:postcode":"7554",
    "addr:street":"Granaatstraat;Ov",
    "iso:country":"NL",
    "sg:address":"Granaatstraat 35",
    "sg:city":"Hengelo Ov",
    "sg:orig_category":"Farmaceutische Producten Gh",
    "sg:phone":"+31 74 245 5454",
    "sg:postcode":"7554 TN",
    "sg:province":"Overijssel",
    "wof:name":"Revalidatie Service Meyra Bv",
    "wof:placetype":"venue"
},
  "geometry": {"coordinates":[6.772784,52.240513],"type":"Point"}
}