{
  "type": "Feature",
  "properties": {
    "addr:full":"Raadhuisstr 1 Hoogwoud North Holland 1718 BM",
    "addr:housenumber":"1",
    "addr:postcode":"1718 bm",
    "addr:street":"Raadhuisstr",
    "iso:country":"NL",
    "sg:address":"Raadhuisstr 1",
    "sg:city":"Hoogwoud",
    "sg:orig_category":"Belastingconsulenten/ Belastingadviseurs",
    "sg:phone":"+31 226 353 940",
    "sg:postcode":"1718 BM",
    "sg:province":"North Holland",
    "wof:name":"Exalto",
    "wof:placetype":"venue"
},
  "geometry": {"coordinates":[4.935563,52.717373],"type":"Point"}
}