{
  "type": "Feature",
  "properties": {
    "addr:full":"Rozenstr 25 Baarn Utrecht 3742 RR",
    "addr:housenumber":"25",
    "addr:postcode":"3742 rr",
    "addr:street":"Rozenstr",
    "iso:country":"NL",
    "sg:address":"Rozenstr 25",
    "sg:city":"Baarn",
    "sg:orig_category":"Zonnebank- En Solariumcentra",
    "sg:phone":"+31 35 542 5269",
    "sg:postcode":"3742 RR",
    "sg:province":"Utrecht",
    "wof:name":"Salon, De",
    "wof:placetype":"venue"
},
  "geometry": {"coordinates":[5.298782,52.206501],"type":"Point"}
}