{
  "type": "Feature",
  "properties": {
    "addr:full":"Monnickskamp 1 Huizen North Holland 1273 JP",
    "addr:housenumber":"1",
    "addr:postcode":"1273 jp",
    "addr:street":"Monnickskamp",
    "iso:country":"NL",
    "sg:address":"Monnickskamp 1",
    "sg:city":"Huizen",
    "sg:orig_category":"Biljartzalen",
    "sg:phone":"+31 35 685 6456",
    "sg:postcode":"1273 JP",
    "sg:province":"North Holland",
    "wof:name":"Bun, De",
    "wof:placetype":"venue"
},
  "geometry": {"coordinates":[5.262315,52.29483],"type":"Point"}
}