{
  "type": "Feature",
  "properties": {
    "addr:full":"Dwarscamp 2 Houten Utrecht 3992 RM",
    "addr:housenumber":"2",
    "addr:postcode":"3992 rm",
    "addr:street":"Dwarscamp",
    "iso:country":"NL",
    "sg:address":"Dwarscamp 2",
    "sg:city":"Houten",
    "sg:orig_category":"Vertaalbureaus",
    "sg:phone":"+31 30 638 1979",
    "sg:postcode":"3992 RM",
    "sg:province":"Utrecht",
    "wof:name":"J J Mulder",
    "wof:placetype":"venue"
},
  "geometry": {"coordinates":[5.147504,52.034519],"type":"Point"}
}