{
  "type": "Feature",
  "properties": {
    "iso:country":"NL",
    "sg:address":"Postbus 468",
    "sg:city":"Veenendaal",
    "sg:orig_category":"Adviesbureaus Bouwkunde",
    "sg:phone":"+31 6 10929958",
    "sg:postcode":"3900 AL",
    "sg:province":"Utrecht",
    "wof:name":"Utilities Consultancy",
    "wof:placetype":"venue"
},
  "geometry": {"coordinates":[5.55418,52.024902],"type":"Point"}
}