{
  "type": "Feature",
  "properties": {
    "addr:full":"Burg Hoogenboomln 30 Hoogwoud North Holland 1718 BJ",
    "addr:housenumber":"30",
    "addr:postcode":"1718 bj",
    "addr:street":"Burg",
    "iso:country":"NL",
    "sg:address":"Burg Hoogenboomln 30",
    "sg:city":"Hoogwoud",
    "sg:orig_category":"Fotoreportages",
    "sg:phone":"+31 226 353 108",
    "sg:postcode":"1718 BJ",
    "sg:province":"North Holland",
    "wof:name":"Vos, J De",
    "wof:placetype":"venue"
},
  "geometry": {"coordinates":[4.936018,52.717625],"type":"Point"}
}