{
  "type": "Feature",
  "properties": {
    "addr:full":"Het Jaagpad 22 Linschoten Utrecht 3461 HC",
    "addr:housenumber":"22",
    "addr:postcode":"3461 hc",
    "addr:street":"Het Jaagpad",
    "iso:country":"NL",
    "sg:address":"Het Jaagpad 22",
    "sg:city":"Linschoten",
    "sg:orig_category":"Manueel Therapeuten",
    "sg:phone":"+31 348 410 776",
    "sg:postcode":"3461 HC",
    "sg:province":"Utrecht",
    "wof:name":"Kuiper, C",
    "wof:placetype":"venue"
},
  "geometry": {"coordinates":[4.917654,52.064976],"type":"Point"}
}