{
  "type": "Feature",
  "properties": {
    "addr:full":"Van Koppenweg 14 Naaldwijk South Holland 2672 EH",
    "addr:housenumber":"14",
    "addr:postcode":"2672 eh",
    "addr:street":"Van Koppenweg",
    "iso:country":"NL",
    "sg:address":"Van Koppenweg 14",
    "sg:city":"Naaldwijk",
    "sg:classifiers":[
        {
            "category":"Professional",
            "subcategory":"Accounting & Tax Preparation",
            "type":"Services"
        }
    ],
    "sg:phone":"+31 174 631 561",
    "sg:postcode":"2672 EH",
    "sg:province":"South Holland",
    "sg:tags":[
        "accountant"
    ],
    "wof:name":"Van Rijn Accountants Bv",
    "wof:placetype":"venue"
},
  "geometry": {"coordinates":[4.221914,51.99593],"type":"Point"}
}