{
  "type": "Feature",
  "properties": {
    "iso:country":"NL",
    "sg:address":"Zwemmerstraat 10",
    "sg:city":"Leeuwarden",
    "sg:orig_category":"Bouwmaterialen Gh",
    "sg:phone":"+31 58 284 8333",
    "sg:postcode":"8936 AA",
    "sg:province":"Provincie Friesland",
    "wof:name":"Raab Karcher Bouwstoffen Bv",
    "wof:placetype":"venue"
},
  "geometry": {"coordinates":[5.817919,53.193226],"type":"Point"}
}