{
  "type": "Feature",
  "properties": {
    "iso:country":"NL",
    "sg:address":"Maarsbergsew 21",
    "sg:city":"Leersum",
    "sg:orig_category":"Metaalwaren - Fabrieken",
    "sg:phone":"+31 343 451 241",
    "sg:postcode":"3956 KT",
    "sg:province":"Utrecht",
    "wof:name":"Hoogmerk",
    "wof:placetype":"venue"
},
  "geometry": {"coordinates":[5.418324,52.023418],"type":"Point"}
}