{
  "type": "Feature",
  "properties": {
    "addr:full":"Karnemelksloot 110 Gouda Zuid-Holland 2806 BJ",
    "addr:housenumber":"110",
    "addr:postcode":"2806 bj",
    "addr:street":"Karnemelksloot",
    "iso:country":"NL",
    "sg:address":"Karnemelksloot 110",
    "sg:city":"Gouda",
    "sg:orig_category":"Woningbouwverenigingen",
    "sg:phone":"+31 182 520 966",
    "sg:postcode":"2806 BJ",
    "sg:province":"Zuid-Holland",
    "wof:name":"Woningstichting Het Volksbelang",
    "wof:placetype":"venue"
},
  "geometry": {"coordinates":[4.7209911346,52.0141487122],"type":"Point"}
}