{
  "type": "Feature",
  "properties": {
    "iso:country":"NL",
    "sg:address":"Grt Belt 474",
    "sg:city":"Hoofddorp",
    "sg:orig_category":"Modelbouw",
    "sg:phone":"+31 23 562 4074",
    "sg:postcode":"2133 GR",
    "sg:province":"North Holland",
    "wof:name":"Extra Models",
    "wof:placetype":"venue"
},
  "geometry": {"coordinates":[4.663661,52.312931],"type":"Point"}
}