{
  "type": "Feature",
  "properties": {
    "addr:full":"Loskade 9 Middelburg Zeeland 4331 HV",
    "addr:housenumber":"9",
    "addr:postcode":"4331 hv",
    "addr:street":"Loskade",
    "iso:country":"NL",
    "sg:address":"Loskade 9",
    "sg:city":"Middelburg",
    "sg:orig_category":"Kappers",
    "sg:phone":"+31 118 623 043",
    "sg:postcode":"4331 HV",
    "sg:province":"Zeeland",
    "wof:name":"Haarmode Jacqueline",
    "wof:placetype":"venue"
},
  "geometry": {"coordinates":[3.6177949905,51.4966125488],"type":"Point"}
}