{
  "type": "Feature",
  "properties": {
    "addr:full":"Hekendorpstr 18 Rotterdam Zuid-Holland 3079 DX",
    "addr:housenumber":"18",
    "addr:postcode":"3079 dx",
    "addr:street":"Hekendorpstr",
    "iso:country":"NL",
    "sg:address":"Hekendorpstr 18",
    "sg:city":"Rotterdam",
    "sg:orig_category":"Beveiliging",
    "sg:phone":"+31 10 292 1444",
    "sg:postcode":"3079 DX",
    "sg:province":"Zuid-Holland",
    "sg:website":"http://www.sytec.nl",
    "wof:name":"Sytec Bv",
    "wof:placetype":"venue"
},
  "geometry": {"coordinates":[4.542637,51.872036],"type":"Point"}
}