{
  "type": "Feature",
  "properties": {
    "addr:full":"E Heimansstr 19 Zaandam Noord-Holland 1504 JB",
    "addr:housenumber":"19",
    "addr:postcode":"1504 jb",
    "iso:country":"NL",
    "sg:address":"E Heimansstr 19",
    "sg:city":"Zaandam",
    "sg:orig_category":"Autolakken",
    "sg:phone":"+31 75 616 2059",
    "sg:postcode":"1504 JB",
    "sg:province":"Noord-Holland",
    "wof:name":"Kleurlokaal, Het",
    "wof:placetype":"venue"
},
  "geometry": {"coordinates":[4.850194,52.438976],"type":"Point"}
}