{
  "type": "Feature",
  "properties": {
    "iso:country":"NL",
    "sg:address":"Europawg Z 1A",
    "sg:city":"Assen",
    "sg:orig_category":"Orthopedische Artikelen",
    "sg:phone":"+31 592 314 704",
    "sg:postcode":"9401 RK",
    "sg:province":"Provincie Drenthe",
    "wof:name":"Oim",
    "wof:placetype":"venue"
},
  "geometry": {"coordinates":[6.5678071976,52.9858283997],"type":"Point"}
}