{
  "type": "Feature",
  "properties": {
    "addr:full":"Schoondyksewg 1 Groede Zeeland 4503 GK",
    "addr:housenumber":"1",
    "addr:postcode":"4503 gk",
    "addr:street":"Schoondyksewg",
    "iso:country":"NL",
    "sg:address":"Schoondyksewg 1",
    "sg:city":"Groede",
    "sg:classifiers":[
        {
            "category":"Banks & Credit Unions",
            "subcategory":"Investment Brokerage",
            "type":"Services"
        }
    ],
    "sg:phone":"+31 117 371 371",
    "sg:postcode":"4503 GK",
    "sg:province":"Zeeland",
    "sg:tags":[
        "pension"
    ],
    "wof:name":"Eierkurf D' Bed & Breakfast",
    "wof:placetype":"venue"
},
  "geometry": {"coordinates":[3.510615,51.372688],"type":"Point"}
}