{
  "type": "Feature",
  "properties": {
    "addr:full":"Heelsumsewg 57 Wolfheze Gelderland 6874 BB",
    "addr:housenumber":"57",
    "addr:postcode":"6874 bb",
    "addr:street":"Heelsumsewg;Gelderland",
    "iso:country":"NL",
    "sg:address":"Heelsumsewg 57",
    "sg:city":"Wolfheze",
    "sg:orig_category":"Grafisch Ontwerpers",
    "sg:phone":"+31 26 482 2690",
    "sg:postcode":"6874 BB",
    "sg:province":"Gelderland",
    "wof:name":"Hans Vrolijks",
    "wof:placetype":"venue"
},
  "geometry": {"coordinates":[5.791658,51.999386],"type":"Point"}
}