{
  "type": "Feature",
  "properties": {
    "addr:full":"Loniusstraat 1 Hoorn Nh North Holland 1624 CJ",
    "addr:housenumber":"1",
    "addr:postcode":"1624 cj",
    "addr:street":"Loniusstraat;Nh North",
    "iso:country":"NL",
    "sg:address":"Loniusstraat 1",
    "sg:city":"Hoorn Nh",
    "sg:orig_category":"Fitnesscentra",
    "sg:phone":"+31 229 272 787",
    "sg:postcode":"1624 CJ",
    "sg:province":"North Holland",
    "wof:name":"Conditiecentrum Sport-Fit",
    "wof:placetype":"venue"
},
  "geometry": {"coordinates":[5.062632,52.64706],"type":"Point"}
}