{
  "type": "Feature",
  "properties": {
    "iso:country":"NL",
    "sg:address":"Oosterleek 27",
    "sg:city":"Oosterleek",
    "sg:orig_category":"Goederenvervoer Over De Weg",
    "sg:phone":"+31 229 501 384",
    "sg:postcode":"1609 GA",
    "sg:province":"Noord-Holland",
    "wof:name":"Jan Steen Transport Vof",
    "wof:placetype":"venue"
},
  "geometry": {"coordinates":[5.196077,52.63961],"type":"Point"}
}