{
  "type": "Feature",
  "properties": {
    "iso:country":"NL",
    "sg:address":"Voorstr 227",
    "sg:city":"Dordrecht",
    "sg:orig_category":"Meubelen",
    "sg:phone":"+31 78 611 9430",
    "sg:postcode":"3311 EP",
    "sg:province":"Zuid-Holland",
    "wof:name":"Green",
    "wof:placetype":"venue"
},
  "geometry": {"coordinates":[4.66906,51.81604],"type":"Point"}
}