{
  "type": "Feature",
  "properties": {
    "iso:country":"NL",
    "sg:address":"Nw Uilenburgerstr 59A",
    "sg:city":"Amsterdam",
    "sg:orig_category":"Peuterspeelzalen",
    "sg:phone":"+31 20 623 1280",
    "sg:postcode":"1011 LM",
    "sg:province":"Noord-Holland",
    "wof:name":"Aapje, Het",
    "wof:placetype":"venue"
},
  "geometry": {"coordinates":[4.904735,52.370258],"type":"Point"}
}