{
  "type": "Feature",
  "properties": {
    "iso:country":"NL",
    "sg:address":"Postbus 474",
    "sg:city":"Gouda",
    "sg:orig_category":"Sportprijzen, Postzegels And Munten",
    "sg:phone":"+31 79 331 1218",
    "sg:postcode":"2800 AL",
    "sg:province":"Zuid-Holland",
    "wof:name":"De Brievenbeurs",
    "wof:placetype":"venue"
},
  "geometry": {"coordinates":[4.710715,52.010006],"type":"Point"}
}