{
  "type": "Feature",
  "properties": {
    "iso:country":"NL",
    "sg:address":"Hubertusln 9",
    "sg:city":"Breda",
    "sg:orig_category":"Woninginrichting",
    "sg:phone":"+31 76 564 0484",
    "sg:postcode":"4834 SH",
    "sg:province":"North Brabant",
    "wof:name":"Arabesque",
    "wof:placetype":"venue"
},
  "geometry": {"coordinates":[4.8012499809,51.5665397644],"type":"Point"}
}