{
  "type": "Feature",
  "properties": {
    "addr:full":"Merwedestraat 22 Maasdam Zuid-Holland 3299 XD",
    "addr:housenumber":"22",
    "addr:postcode":"3299 xd",
    "addr:street":"Merwedestraat",
    "iso:country":"NL",
    "sg:address":"Merwedestraat 22",
    "sg:city":"Maasdam",
    "sg:orig_category":"Bedrijfsinventaris Gh",
    "sg:phone":"+31 78 676 7101",
    "sg:postcode":"3299 XD",
    "sg:province":"Zuid-Holland",
    "wof:name":"R.E. Droop",
    "wof:placetype":"venue"
},
  "geometry": {"coordinates":[4.554082,51.791439],"type":"Point"}
}