{
  "type": "Feature",
  "properties": {
    "iso:country":"NL",
    "sg:address":"A Vd Leeuwln 904",
    "sg:city":"Delft",
    "sg:orig_category":"Bejaarden - Verzorgingstehuizen",
    "sg:phone":"+31 15 256 0900",
    "sg:postcode":"2624 LW",
    "sg:province":"Zuid-Holland",
    "wof:name":"Stefanna, Wooncentr Rk",
    "wof:placetype":"venue"
},
  "geometry": {"coordinates":[4.35634,51.995491],"type":"Point"}
}