{
  "type": "Feature",
  "properties": {
    "iso:country":"NL",
    "sg:address":"Lekstr 46/48I",
    "sg:city":"Amsterdam",
    "sg:orig_category":"Kappers",
    "sg:phone":"+31 20 644 5565",
    "sg:postcode":"1079 ES",
    "sg:province":"Noord-Holland",
    "wof:name":"Hilkman",
    "wof:placetype":"venue"
},
  "geometry": {"coordinates":[4.9064769745,52.3451843262],"type":"Point"}
}