{
  "type": "Feature",
  "properties": {
    "addr:full":"Klundertseweg 21 Zevenbergen Noord-Brabant 4761 PR",
    "addr:housenumber":"21",
    "addr:postcode":"4761 pr",
    "addr:street":"Klundertseweg",
    "iso:country":"NL",
    "sg:address":"Klundertseweg 21",
    "sg:city":"Zevenbergen",
    "sg:orig_category":"Drukkerijen And Copyshops",
    "sg:phone":"+31 168 324 585",
    "sg:postcode":"4761 PR",
    "sg:province":"Noord-Brabant",
    "wof:name":"Henk Van Muijen Drukwerk",
    "wof:placetype":"venue"
},
  "geometry": {"coordinates":[4.581939,51.644955],"type":"Point"}
}