{
  "type": "Feature",
  "properties": {
    "addr:full":"Atlantis 21 Emmen Drenthe 7821 AX",
    "addr:housenumber":"21",
    "addr:postcode":"7821 ax",
    "addr:street":"Atlantis",
    "iso:country":"NL",
    "sg:address":"Atlantis 21",
    "sg:city":"Emmen",
    "sg:orig_category":"Evenementenverzorging",
    "sg:phone":"+31 591 622 611",
    "sg:postcode":"7821 AX",
    "sg:province":"Drenthe",
    "wof:name":"Dev",
    "wof:placetype":"venue"
},
  "geometry": {"coordinates":[6.914474,52.774693],"type":"Point"}
}