{
  "type": "Feature",
  "properties": {
    "addr:full":"Prinsegr 146 S Gravenhage South Holland 2512 GE",
    "addr:housenumber":"146",
    "addr:postcode":"2512",
    "addr:street":"S Gravenhage",
    "iso:country":"NL",
    "sg:address":"Prinsegr 146",
    "sg:city":"S Gravenhage",
    "sg:orig_category":"Verenigingen En Stichtingen",
    "sg:phone":"+31 70 389 8688",
    "sg:postcode":"2512 GE",
    "sg:province":"South Holland",
    "wof:name":"Schoolstraat, Ver",
    "wof:placetype":"venue"
},
  "geometry": {"coordinates":[4.30618,52.073212],"type":"Point"}
}