{
  "type": "Feature",
  "properties": {
    "iso:country":"NL",
    "sg:address":"Levenkamp 7",
    "sg:city":"Laren Gld",
    "sg:orig_category":"Houtverwerking",
    "sg:phone":"+31 573 401 393",
    "sg:postcode":"7245 RK",
    "sg:province":"Gelderland",
    "wof:name":"H. Leunk",
    "wof:placetype":"venue"
},
  "geometry": {"coordinates":[6.348341,52.223259],"type":"Point"}
}