{
  "type": "Feature",
  "properties": {
    "addr:full":"Middelwaard 36 Zoetermeer Zuid-Holland 2716 CW",
    "addr:housenumber":"36",
    "addr:postcode":"2716 cw",
    "addr:street":"Middelwaard",
    "iso:country":"NL",
    "sg:address":"Middelwaard 36",
    "sg:city":"Zoetermeer",
    "sg:orig_category":"Banken And Kredietinstellingen",
    "sg:phone":"+31 79 321 2800",
    "sg:postcode":"2716 CW",
    "sg:province":"Zuid-Holland",
    "wof:name":"Abn Amro",
    "wof:placetype":"venue"
},
  "geometry": {"coordinates":[4.469319,52.05632],"type":"Point"}
}