{
  "type": "Feature",
  "properties": {
    "addr:full":"Benedendorpsweg 75 Oosterbeek Gelderland 6862 WD",
    "addr:housenumber":"75",
    "addr:postcode":"6862",
    "addr:street":"Benedendorpsweg;Gelderland",
    "iso:country":"NL",
    "sg:address":"Benedendorpsweg 75",
    "sg:city":"Oosterbeek",
    "sg:orig_category":"Diverse Grafische Activiteiten",
    "sg:phone":"+31 26 333 5742",
    "sg:postcode":"6862 WD",
    "sg:province":"Gelderland",
    "wof:name":"Delta Partners",
    "wof:placetype":"venue"
},
  "geometry": {"coordinates":[5.846536,51.979321],"type":"Point"}
}