{
  "type": "Feature",
  "properties": {
    "addr:full":"Hofland 58 Mijdrecht Utrecht 3641 GG",
    "addr:housenumber":"58",
    "addr:postcode":"3641 gg",
    "addr:street":"Hofland",
    "iso:country":"NL",
    "sg:address":"Hofland 58",
    "sg:city":"Mijdrecht",
    "sg:classifiers":[
        {
            "category":"Fast Food",
            "type":"Food & Drink"
        }
    ],
    "sg:phone":"+31 297 281 398",
    "sg:postcode":"3641 GG",
    "sg:province":"Utrecht",
    "sg:tags":[
        "afhaal",
        "restaurant"
    ],
    "wof:name":"Cafetaria Noppy'S",
    "wof:placetype":"venue"
},
  "geometry": {"coordinates":[4.868135,52.211109],"type":"Point"}
}