{
  "type": "Feature",
  "properties": {
    "addr:full":"Californiepln 8 Haarlem North Holland 2037 AL",
    "addr:housenumber":"8",
    "addr:postcode":"2037 al",
    "addr:street":"Californiepln",
    "iso:country":"NL",
    "sg:address":"Californiepln 8",
    "sg:city":"Haarlem",
    "sg:orig_category":"Schoenen",
    "sg:phone":"+31 23 533 4302",
    "sg:postcode":"2037 AL",
    "sg:province":"North Holland",
    "sg:website":"http://www.dolcis.nl",
    "wof:name":"Dolcis",
    "wof:placetype":"venue"
},
  "geometry": {"coordinates":[4.654768,52.357967],"type":"Point"}
}