{
  "type": "Feature",
  "properties": {
    "addr:full":"De Limiet 15 Vianen Zh South Holland 4131 NR",
    "addr:housenumber":"15",
    "addr:postcode":"zh;4131 nr",
    "addr:street":"De Limiet",
    "iso:country":"NL",
    "sg:address":"De Limiet 15",
    "sg:city":"Vianen Zh",
    "sg:orig_category":"Adviesbureaus Bedrijfsorganisatie",
    "sg:phone":"+31 347 357 071",
    "sg:postcode":"4131 NR",
    "sg:province":"South Holland",
    "sg:website":"http://www.managementinmotion.nl",
    "wof:name":"Management In Motion",
    "wof:placetype":"venue"
},
  "geometry": {"coordinates":[5.091063,51.977867],"type":"Point"}
}