{
  "type": "Feature",
  "properties": {
    "addr:full":"Utrechtsewg 10 Weesp Noord-Holland 1381 GP",
    "addr:housenumber":"10",
    "addr:postcode":"1381 gp",
    "addr:street":"Utrechtsewg",
    "iso:country":"NL",
    "sg:address":"Utrechtsewg 10",
    "sg:city":"Weesp",
    "sg:orig_category":"Acupunctuur",
    "sg:phone":"+31 294 419 857",
    "sg:postcode":"1381 GP",
    "sg:province":"Noord-Holland",
    "wof:name":"Oosterwijck, E M Van",
    "wof:placetype":"venue"
},
  "geometry": {"coordinates":[5.046233,52.303902],"type":"Point"}
}