{
  "type": "Feature",
  "properties": {
    "addr:full":"Duurstedestr 30 Breda North Brabant 4834 HL",
    "addr:housenumber":"30",
    "addr:postcode":"4834 hl",
    "addr:street":"Duurstedestr",
    "iso:country":"NL",
    "sg:address":"Duurstedestr 30",
    "sg:city":"Breda",
    "sg:orig_category":"Zonweringen",
    "sg:phone":"+31 76 565 6211",
    "sg:postcode":"4834 HL",
    "sg:province":"North Brabant",
    "sg:website":"http://www.vugtzonwering.nl",
    "wof:name":"Ad Van Vugt",
    "wof:placetype":"venue"
},
  "geometry": {"coordinates":[4.804381,51.570213],"type":"Point"}
}