{
  "type": "Feature",
  "properties": {
    "iso:country":"NL",
    "sg:address":"Oeverzegge 5",
    "sg:city":"Nieuw Lekkerland",
    "sg:orig_category":"Goudsmeden En Zilversmeden",
    "sg:phone":"+31 184 684 711",
    "sg:postcode":"2957 RM",
    "sg:province":"Zuid-Holland",
    "wof:name":"Monique",
    "wof:placetype":"venue"
},
  "geometry": {"coordinates":[4.682044,51.886322],"type":"Point"}
}