{
  "type": "Feature",
  "properties": {
    "addr:full":"Mr P D Fortuynwg 99 S Gravenhage Zuid-Holland 2533 SP",
    "addr:housenumber":"99;gravenhage",
    "addr:postcode":"2533 sp",
    "addr:street":"Mr;S",
    "iso:country":"NL",
    "sg:address":"Mr P D Fortuynwg 99",
    "sg:city":"S Gravenhage",
    "sg:orig_category":"Fitnesscentra",
    "sg:phone":"+31 70 369 9100",
    "sg:postcode":"2533 SP",
    "sg:province":"Zuid-Holland",
    "sg:website":"http://www.fitnessfirst.com",
    "wof:name":"Fitness First Health Clubs",
    "wof:placetype":"venue"
},
  "geometry": {"coordinates":[4.28581,52.05286],"type":"Point"}
}