{
  "type": "Feature",
  "properties": {
    "addr:full":"Postbus 10018 Tilburg North Brabant 5000 JA",
    "addr:housenumber":"10018",
    "addr:postcode":"5000 ja",
    "addr:street":"Postbus",
    "iso:country":"NL",
    "sg:address":"Postbus 10018",
    "sg:city":"Tilburg",
    "sg:orig_category":"Verpleegartikelen - Fabrieken En Groothandel",
    "sg:phone":"+31 13 511 6767",
    "sg:postcode":"5000 JA",
    "sg:province":"North Brabant",
    "wof:name":"Paulson International Bv",
    "wof:placetype":"venue"
},
  "geometry": {"coordinates":[5.10623,51.554878],"type":"Point"}
}