{
  "type": "Feature",
  "properties": {
    "iso:country":"NL",
    "sg:address":"Ackershof 45",
    "sg:city":"Pynacker",
    "sg:orig_category":"Opticiens",
    "sg:phone":"+31 15 369 3741",
    "sg:postcode":"2641 DZ",
    "sg:province":"Zuid-Holland",
    "wof:name":"Leezer",
    "wof:placetype":"venue"
},
  "geometry": {"coordinates":[4.4327712059,52.0190315247],"type":"Point"}
}