{
  "type": "Feature",
  "properties": {
    "iso:country":"NL",
    "sg:address":"Emmapln 204",
    "sg:city":"Zeist",
    "sg:orig_category":"Autoradio'S",
    "sg:phone":"+31 30 697 4600",
    "sg:postcode":"3701 DH",
    "sg:province":"Utrecht",
    "wof:name":"Star",
    "wof:placetype":"venue"
},
  "geometry": {"coordinates":[5.241077,52.086811],"type":"Point"}
}