{
  "type": "Feature",
  "properties": {
    "addr:full":"Willemsbeekwg 80 Ymuiden Noord-Holland 1971 GZ",
    "addr:housenumber":"80",
    "addr:postcode":"1971 gz",
    "addr:street":"Willemsbeekwg",
    "iso:country":"NL",
    "sg:address":"Willemsbeekwg 80",
    "sg:city":"Ymuiden",
    "sg:orig_category":"Scholen Voor Basisonderwijs",
    "sg:phone":"+31 255 514 227",
    "sg:postcode":"1971 GZ",
    "sg:province":"Noord-Holland",
    "sg:website":"http://www.multiweb.net/~boekanier/",
    "wof:name":"Boekanier, De",
    "wof:placetype":"venue"
},
  "geometry": {"coordinates":[4.624048,52.458622],"type":"Point"}
}