{
  "type": "Feature",
  "properties": {
    "addr:full":"V St Aldegondestr 26 Leerdam Zuid-Holland 4142 CB",
    "addr:housenumber":"26",
    "addr:postcode":"4142 cb",
    "addr:street":"V St Aldegondestr",
    "iso:country":"NL",
    "sg:address":"V St Aldegondestr 26",
    "sg:city":"Leerdam",
    "sg:orig_category":"Artsen - Huisartsen",
    "sg:phone":"+31 345 612 780",
    "sg:postcode":"4142 CB",
    "sg:province":"Zuid-Holland",
    "wof:name":"Ferket, K V M",
    "wof:placetype":"venue"
},
  "geometry": {"coordinates":[5.091045,51.890675],"type":"Point"}
}