{
  "type": "Feature",
  "properties": {
    "iso:country":"NL",
    "sg:address":"Haaksbergerstr 418",
    "sg:city":"Enschede",
    "sg:orig_category":"Bloemen En Planten",
    "sg:phone":"+31 53 431 7876",
    "sg:postcode":"7545 GB",
    "sg:province":"Overijssel",
    "wof:name":"Mazereeuw",
    "wof:placetype":"venue"
},
  "geometry": {"coordinates":[6.876684,52.210007],"type":"Point"}
}