{
  "type": "Feature",
  "properties": {
    "iso:country":"NL",
    "sg:address":"Berkelstraat 28",
    "sg:city":"Valkenburg Lb",
    "sg:orig_category":"Juweliers",
    "sg:phone":"+31 43 601 4226",
    "sg:postcode":"6301 CC",
    "sg:province":"Limburg",
    "wof:name":"Vof Pell Mell - Handelsonderneming Brunh",
    "wof:placetype":"venue"
},
  "geometry": {"coordinates":[5.831325,50.862572],"type":"Point"}
}