{
  "type": "Feature",
  "properties": {
    "addr:full":"Westerzicht 320 Vlissingen Zeeland 4385 BL",
    "addr:housenumber":"320",
    "addr:postcode":"4385 bl",
    "addr:street":"Westerzicht",
    "iso:country":"NL",
    "sg:address":"Westerzicht 320",
    "sg:city":"Vlissingen",
    "sg:orig_category":"Fotografie Reclame En Mode",
    "sg:phone":"+31 118 468 838",
    "sg:postcode":"4385 BL",
    "sg:province":"Zeeland",
    "wof:name":"Steenaard, Wies",
    "wof:placetype":"venue"
},
  "geometry": {"coordinates":[3.589823,51.461319],"type":"Point"}
}