{
  "type": "Feature",
  "properties": {
    "iso:country":"NL",
    "sg:address":"Onder De Toren 4",
    "sg:city":"Emmeloord",
    "sg:orig_category":"Verzekeringen - Verzekeringskantoren",
    "sg:phone":"+31 527 612 990",
    "sg:postcode":"8302 BT",
    "sg:province":"Flevoland",
    "wof:name":"Offringa Bv",
    "wof:placetype":"venue"
},
  "geometry": {"coordinates":[5.75047,52.709724],"type":"Point"}
}