{
  "type": "Feature",
  "properties": {
    "iso:country":"NL",
    "sg:address":"Koematen 40",
    "sg:city":"Steenwijk",
    "sg:orig_category":"Technische Studies And Onderzoek",
    "sg:phone":"+31 521 513 310",
    "sg:postcode":"8331 TK",
    "sg:province":"Overijssel",
    "wof:name":"Regionale Arbodiensten Zwolle Eo",
    "wof:placetype":"venue"
},
  "geometry": {"coordinates":[6.096285,52.780308],"type":"Point"}
}