{
  "type": "Feature",
  "properties": {
    "addr:full":"J Deckersstr 19A Heeze North Brabant 5591 HN",
    "addr:housenumber":"19a",
    "addr:postcode":"5591 hn",
    "iso:country":"NL",
    "sg:address":"J Deckersstr 19A",
    "sg:city":"Heeze",
    "sg:orig_category":"Boeken En Tijdschriften",
    "sg:phone":"+31 40 226 5943",
    "sg:postcode":"5591 HN",
    "sg:province":"North Brabant",
    "wof:name":"Boekelier, De",
    "wof:placetype":"venue"
},
  "geometry": {"coordinates":[5.578118,51.378777],"type":"Point"}
}