{
  "type": "Feature",
  "properties": {
    "addr:full":"Pettelaarpk 34 S Hertogenbosch North Brabant 5216 PD",
    "addr:housenumber":"34",
    "addr:postcode":"5216 pd",
    "addr:street":"Pettelaarpk;S Hertogenbosch",
    "iso:country":"NL",
    "sg:address":"Pettelaarpk 34",
    "sg:city":"S Hertogenbosch",
    "sg:orig_category":"Verenigingen En Stichtingen",
    "sg:phone":"+31 800 0231536",
    "sg:postcode":"5216 PD",
    "sg:province":"North Brabant",
    "sg:website":"http://www.radiologen.nl",
    "wof:name":"Ned Ver Voor Radiologie",
    "wof:placetype":"venue"
},
  "geometry": {"coordinates":[5.335481,51.678772],"type":"Point"}
}