{
  "type": "Feature",
  "properties": {
    "iso:country":"NL",
    "sg:address":"Ringbaan 10",
    "sg:city":"Molenhoek Lb",
    "sg:orig_category":"Beeldende Kunstenaars",
    "sg:phone":"+31 24 358 5812",
    "sg:postcode":"6584 BB",
    "sg:province":"Limburg",
    "wof:name":"Klaver, J H",
    "wof:placetype":"venue"
},
  "geometry": {"coordinates":[5.872937,51.769863],"type":"Point"}
}