{
  "type": "Feature",
  "properties": {
    "addr:full":"Uhlenbeckkd 6 Leiden South Holland 2313 EH",
    "addr:housenumber":"6",
    "addr:postcode":"2313 eh",
    "addr:street":"Uhlenbeckkd",
    "iso:country":"NL",
    "sg:address":"Uhlenbeckkd 6",
    "sg:city":"Leiden",
    "sg:orig_category":"Psychologen",
    "sg:phone":"+31 71 513 3620",
    "sg:postcode":"2313 EH",
    "sg:province":"South Holland",
    "wof:name":"Dam, Q D Van",
    "wof:placetype":"venue"
},
  "geometry": {"coordinates":[4.508181,52.151569],"type":"Point"}
}