{
  "type": "Feature",
  "properties": {
    "addr:full":"Schoolstr 26 Venray Limburg 5801 BP",
    "addr:housenumber":"26",
    "addr:postcode":"5801 bp",
    "addr:street":"Schoolstr",
    "iso:country":"NL",
    "sg:address":"Schoolstr 26",
    "sg:city":"Venray",
    "sg:orig_category":"Kantoorbenodigdheden",
    "sg:phone":"+31 478 586 616",
    "sg:postcode":"5801 BP",
    "sg:province":"Limburg",
    "wof:name":"Cuypers Bv, Martin",
    "wof:placetype":"venue"
},
  "geometry": {"coordinates":[5.9742870331,51.5259513855],"type":"Point"}
}