{
  "type": "Feature",
  "properties": {
    "addr:full":"Westeinde 16 Maassluis Zuid-Holland 3146 BZ",
    "addr:housenumber":"16",
    "addr:postcode":"3146 bz",
    "addr:street":"Westeinde",
    "iso:country":"NL",
    "sg:address":"Westeinde 16",
    "sg:city":"Maassluis",
    "sg:orig_category":"Kappers",
    "sg:phone":"+31 10 591 1386",
    "sg:postcode":"3146 BZ",
    "sg:province":"Zuid-Holland",
    "wof:name":"Haan, Aad Den",
    "wof:placetype":"venue"
},
  "geometry": {"coordinates":[4.2277569771,51.9371261597],"type":"Point"}
}