{
  "type": "Feature",
  "properties": {
    "iso:country":"NL",
    "sg:address":"Steenstraat 59",
    "sg:city":"Arnhem",
    "sg:classifiers":[
        {
            "category":"Communications",
            "subcategory":"Television Station",
            "type":"Services"
        }
    ],
    "sg:phone":"+31 26 445 8470",
    "sg:postcode":"6828 CD",
    "sg:province":"Gelderland",
    "sg:tags":[
        "video",
        "audio",
        "verhuur"
    ],
    "wof:name":"Eurovideo",
    "wof:placetype":"venue"
},
  "geometry": {"coordinates":[5.917066,51.984058],"type":"Point"}
}