{
  "type": "Feature",
  "properties": {
    "addr:full":"Markt 1 Brouwershaven Zeeland 4318 AE",
    "addr:housenumber":"1",
    "addr:postcode":"4318 ae",
    "addr:street":"Markt",
    "iso:country":"NL",
    "sg:address":"Markt 1",
    "sg:city":"Brouwershaven",
    "sg:orig_category":"Kappers",
    "sg:phone":"+31 111 692 146",
    "sg:postcode":"4318 AE",
    "sg:province":"Zeeland",
    "wof:name":"Jan Willem Capelle",
    "wof:placetype":"venue"
},
  "geometry": {"coordinates":[3.9118819237,51.7256393433],"type":"Point"}
}