{
  "type": "Feature",
  "properties": {
    "addr:full":"Havenstr 62 Noordwykerhout Zuid-Holland 2211 EJ",
    "addr:housenumber":"62",
    "addr:postcode":"2211 ej",
    "addr:street":"Havenstr",
    "iso:country":"NL",
    "sg:address":"Havenstr 62",
    "sg:city":"Noordwykerhout",
    "sg:orig_category":"Kappers",
    "sg:phone":"+31 252 374 881",
    "sg:postcode":"2211 EJ",
    "sg:province":"Zuid-Holland",
    "wof:name":"Lars",
    "wof:placetype":"venue"
},
  "geometry": {"coordinates":[4.496317,52.26123],"type":"Point"}
}