{
  "type": "Feature",
  "properties": {
    "iso:country":"NL",
    "sg:address":"Generaal Cronjestraat 22",
    "sg:city":"Haarlem",
    "sg:orig_category":"Zuivelproducten",
    "sg:phone":"+31 23 527 6421",
    "sg:postcode":"2021 JH",
    "sg:province":"North Holland",
    "wof:name":"De Kaashoek",
    "wof:placetype":"venue"
},
  "geometry": {"coordinates":[4.641137,52.392796],"type":"Point"}
}