{
  "type": "Feature",
  "properties": {
    "addr:full":"L Groenewg 25 Spykenisse South Holland 3207 JL",
    "addr:housenumber":"25",
    "addr:postcode":"3207 jl",
    "addr:street":"Spykenisse South",
    "iso:country":"NL",
    "sg:address":"L Groenewg 25",
    "sg:city":"Spykenisse",
    "sg:orig_category":"Werving En Selectie",
    "sg:phone":"+31 181 688 085",
    "sg:postcode":"3207 JL",
    "sg:province":"South Holland",
    "sg:website":"http://www.aqcselect.nl",
    "wof:name":"Aqc",
    "wof:placetype":"venue"
},
  "geometry": {"coordinates":[4.3578701019,51.8386688232],"type":"Point"}
}