{
  "type": "Feature",
  "properties": {
    "iso:country":"NL",
    "sg:address":"Papsouwseln 224",
    "sg:city":"Delft",
    "sg:orig_category":"Zonnebanken En Solaria - Fabrieken En Groothandel",
    "sg:phone":"+31 15 262 2888",
    "sg:postcode":"2624 EG",
    "sg:province":"Zuid-Holland",
    "wof:name":"Scope",
    "wof:placetype":"venue"
},
  "geometry": {"coordinates":[4.35634,51.995491],"type":"Point"}
}