{
  "type": "Feature",
  "properties": {
    "iso:country":"NL",
    "sg:address":"Retiefstraat 5",
    "sg:city":"Ermelo",
    "sg:orig_category":"Verzekeringen",
    "sg:phone":"+31 341 558 221",
    "sg:postcode":"3851 AA",
    "sg:province":"Gelderland",
    "wof:name":"Assurantiekantoor R. L'Ortye",
    "wof:placetype":"venue"
},
  "geometry": {"coordinates":[5.614442,52.28973],"type":"Point"}
}