{
  "type": "Feature",
  "properties": {
    "addr:full":"Retiefstraat 5 Ermelo Gelderland 3851 AA",
    "addr:housenumber":"5",
    "addr:postcode":"3851 aa",
    "addr:street":"Retiefstraat;Gelderland",
    "iso:country":"NL",
    "sg:address":"Retiefstraat 5",
    "sg:city":"Ermelo",
    "sg:orig_category":"Verzekeringen",
    "sg:phone":"+31 341 558 221",
    "sg:postcode":"3851 AA",
    "sg:province":"Gelderland",
    "wof:name":"Assurantiekantoor R. L'Ortye",
    "wof:placetype":"venue"
},
  "geometry": {"coordinates":[5.614442,52.28973],"type":"Point"}
}