{
  "type": "Feature",
  "properties": {
    "addr:full":"De Waring 14 Grou Friesland 9001 HZ",
    "addr:housenumber":"14",
    "addr:postcode":"9001 hz",
    "addr:street":"De Waring",
    "iso:country":"NL",
    "sg:address":"De Waring 14",
    "sg:city":"Grou",
    "sg:orig_category":"Administratie- En Boekhoudkantoren",
    "sg:phone":"+31 566 624 142",
    "sg:postcode":"9001 HZ",
    "sg:province":"Friesland",
    "wof:name":"Oosterhof",
    "wof:placetype":"venue"
},
  "geometry": {"coordinates":[-113.611923,43.688873],"type":"Point"}
}