{
  "type": "Feature",
  "properties": {
    "addr:full":"Meijlandstraat 5 Vlissingen Zeeland 4381 JV",
    "addr:housenumber":"5",
    "addr:postcode":"4381 jv",
    "addr:street":"Meijlandstraat",
    "iso:country":"NL",
    "sg:address":"Meijlandstraat 5",
    "sg:city":"Vlissingen",
    "sg:orig_category":"Fotostudio'S And Fotografen",
    "sg:phone":"+31 118 415 982",
    "sg:postcode":"4381 JV",
    "sg:province":"Zeeland",
    "wof:name":"Fotografie Jacob Van Der Linden",
    "wof:placetype":"venue"
},
  "geometry": {"coordinates":[3.571497,51.441048],"type":"Point"}
}