{
  "type": "Feature",
  "properties": {
    "addr:full":"Paaptilsterweg 29 Oldenzijl Groningen 9986 XP",
    "addr:housenumber":"29",
    "addr:postcode":"9986 xp",
    "addr:street":"Paaptilsterweg",
    "iso:country":"NL",
    "sg:address":"Paaptilsterweg 29",
    "sg:city":"Oldenzijl",
    "sg:orig_category":"Landbouwmachines Gh",
    "sg:phone":"+31 595 464 315",
    "sg:postcode":"9986 XP",
    "sg:province":"Groningen",
    "wof:name":"Lourens Landbouwmechanisatie Bedrijf Bv",
    "wof:placetype":"venue"
},
  "geometry": {"coordinates":[6.722887,53.39463],"type":"Point"}
}