{
  "type": "Feature",
  "properties": {
    "addr:full":"Houtstr 43 Echt Limburg 6102 BD",
    "addr:housenumber":"43",
    "addr:postcode":"6102 bd",
    "addr:street":"Houtstr",
    "iso:country":"NL",
    "sg:address":"Houtstr 43",
    "sg:city":"Echt",
    "sg:classifiers":[
        {
            "category":"Food & Beverages",
            "subcategory":"Bakery",
            "type":"Retail Goods"
        }
    ],
    "sg:phone":"+31 475 485 938",
    "sg:postcode":"6102 BD",
    "sg:province":"Limburg",
    "sg:tags":[
        "brood",
        "en",
        "banket"
    ],
    "wof:name":"Jos Puts",
    "wof:placetype":"venue"
},
  "geometry": {"coordinates":[5.87711,51.111141],"type":"Point"}
}