{
  "type": "Feature",
  "properties": {
    "addr:full":"Kloppenland 3 Kerkdriel Gelderland 5331 RZ",
    "addr:housenumber":"3",
    "addr:postcode":"5331 rz",
    "addr:street":"Kloppenland;Gelderland",
    "iso:country":"NL",
    "sg:address":"Kloppenland 3",
    "sg:city":"Kerkdriel",
    "sg:orig_category":"Schilders",
    "sg:phone":"+31 418 631 414",
    "sg:postcode":"5331 RZ",
    "sg:province":"Gelderland",
    "wof:name":"Toppaint",
    "wof:placetype":"venue"
},
  "geometry": {"coordinates":[5.329412,51.766247],"type":"Point"}
}