{
  "type": "Feature",
  "properties": {
    "addr:full":"Hogebrinkerwg 8 Hoevelaken Gelderland 3871 KN",
    "addr:housenumber":"8",
    "addr:postcode":"3871 kn",
    "addr:street":"Hogebrinkerwg;Gelderland",
    "iso:country":"NL",
    "sg:address":"Hogebrinkerwg 8",
    "sg:city":"Hoevelaken",
    "sg:orig_category":"Bedrijfsmechanisatie En -Automatisering",
    "sg:phone":"+31 33 254 4848",
    "sg:postcode":"3871 KN",
    "sg:province":"Gelderland",
    "sg:website":"http://www.regelpartners.nl",
    "wof:name":"Regel Partners Bv",
    "wof:placetype":"venue"
},
  "geometry": {"coordinates":[5.468735,52.176556],"type":"Point"}
}