{
  "type": "Feature",
  "properties": {
    "addr:full":"Hoogstr 2 Haastrecht Zuid-Holland 2851 BA",
    "addr:housenumber":"2",
    "addr:postcode":"2851 ba",
    "addr:street":"Hoogstr",
    "iso:country":"NL",
    "sg:address":"Hoogstr 2",
    "sg:city":"Haastrecht",
    "sg:orig_category":"Wasserijen",
    "sg:phone":"+31 182 501 511",
    "sg:postcode":"2851 BA",
    "sg:province":"Zuid-Holland",
    "wof:name":"Bleeklust Bv",
    "wof:placetype":"venue"
},
  "geometry": {"coordinates":[4.7741298676,52.0004959106],"type":"Point"}
}