{
  "type": "Feature",
  "properties": {
    "addr:full":"Velserkade 1 Velsen-Noord Noord-Holland 1951 NK",
    "addr:housenumber":"1",
    "addr:postcode":"1951 nk",
    "addr:street":"Velserkade",
    "iso:country":"NL",
    "sg:address":"Velserkade 1",
    "sg:city":"Velsen-Noord",
    "sg:orig_category":"Diverse Bedrijfsinstallaties Gh",
    "sg:phone":"+31 251 221 703",
    "sg:postcode":"1951 NK",
    "sg:province":"Noord-Holland",
    "wof:name":"Bmz Bv",
    "wof:placetype":"venue"
},
  "geometry": {"coordinates":[4.664968,52.466652],"type":"Point"}
}