{
  "type": "Feature",
  "properties": {
    "addr:full":"Emiclaerhof 226 Amersfoort Utrecht 3823 ET",
    "addr:housenumber":"226",
    "addr:postcode":"3823 et",
    "addr:street":"Emiclaerhof",
    "iso:country":"NL",
    "sg:address":"Emiclaerhof 226",
    "sg:city":"Amersfoort",
    "sg:orig_category":"Juweliers",
    "sg:phone":"+31 33 455 8425",
    "sg:postcode":"3823 ET",
    "sg:province":"Utrecht",
    "wof:name":"Groenhuizen Emiclaer Juweliers",
    "wof:placetype":"venue"
},
  "geometry": {"coordinates":[5.396938,52.185986],"type":"Point"}
}