{
  "type": "Feature",
  "properties": {
    "addr:full":"Noordmolenstraat 2 Rotterdam Zuid-Holland 3035 RJ",
    "addr:housenumber":"2",
    "addr:postcode":"3035 rj",
    "addr:street":"Noordmolenstraat",
    "iso:country":"NL",
    "sg:address":"Noordmolenstraat 2",
    "sg:city":"Rotterdam",
    "sg:orig_category":"Juweliers",
    "sg:phone":"+31 10 465 2026",
    "sg:postcode":"3035 RJ",
    "sg:province":"Zuid-Holland",
    "wof:name":"Juweliersbedrijf Heenes Bv",
    "wof:placetype":"venue"
},
  "geometry": {"coordinates":[4.484299,51.931],"type":"Point"}
}