{
  "type": "Feature",
  "properties": {
    "addr:full":"Panoramawg 6 Puth Limburg 6155 LZ",
    "addr:housenumber":"6",
    "addr:postcode":"6155 lz",
    "addr:street":"Panoramawg",
    "iso:country":"NL",
    "sg:address":"Panoramawg 6",
    "sg:city":"Puth",
    "sg:orig_category":"Artsen - Huisartsen",
    "sg:phone":"+31 46 443 5333",
    "sg:postcode":"6155 LZ",
    "sg:province":"Limburg",
    "wof:name":"Mulders, J F C H",
    "wof:placetype":"venue"
},
  "geometry": {"coordinates":[12.73821,42.02174],"type":"Point"}
}