{
  "type": "Feature",
  "properties": {
    "iso:country":"NL",
    "sg:address":"Holtropweg 3",
    "sg:city":"Ijlst",
    "sg:orig_category":"Autokeuringen",
    "sg:phone":"+31 515 531 249",
    "sg:postcode":"8651 BH",
    "sg:province":"Friesland",
    "wof:name":"Van Der Zee Autobedrijf",
    "wof:placetype":"venue"
},
  "geometry": {"coordinates":[5.615303,53.011108],"type":"Point"}
}