{
  "type": "Feature",
  "properties": {
    "addr:full":"Holtropweg 3 Ijlst Friesland 8651 BH",
    "addr:housenumber":"3",
    "addr:postcode":"8651 bh",
    "addr:street":"Holtropweg",
    "iso:country":"NL",
    "sg:address":"Holtropweg 3",
    "sg:city":"Ijlst",
    "sg:orig_category":"Autokeuringen",
    "sg:phone":"+31 515 531 249",
    "sg:postcode":"8651 BH",
    "sg:province":"Friesland",
    "wof:name":"Van Der Zee Autobedrijf",
    "wof:placetype":"venue"
},
  "geometry": {"coordinates":[5.615303,53.011108],"type":"Point"}
}