{
  "type": "Feature",
  "properties": {
    "addr:full":"Jan Roelandsestraat 15 Leiderdorp South Holland 2352 SX",
    "addr:housenumber":"15",
    "addr:postcode":"2352 sx",
    "addr:street":"Jan Roelandsestraat",
    "iso:country":"NL",
    "sg:address":"Jan Roelandsestraat 15",
    "sg:city":"Leiderdorp",
    "sg:orig_category":"Verzekeringen",
    "sg:phone":"+31 71 541 0265",
    "sg:postcode":"2352 SX",
    "sg:province":"South Holland",
    "wof:name":"Assurantiekantoor C. V.D. Leek",
    "wof:placetype":"venue"
},
  "geometry": {"coordinates":[4.520278,52.159935],"type":"Point"}
}