{
  "type": "Feature",
  "properties": {
    "addr:full":"Cattepoelsewg 364 Arnhem Gelderland 6815 CL",
    "addr:housenumber":"364",
    "addr:postcode":"6815",
    "iso:country":"NL",
    "sg:address":"Cattepoelsewg 364",
    "sg:city":"Arnhem",
    "sg:orig_category":"Vioolbouw",
    "sg:phone":"+31 26 445 4489",
    "sg:postcode":"6815 CL",
    "sg:province":"Gelderland",
    "wof:name":"Schwarz, M E",
    "wof:placetype":"venue"
},
  "geometry": {"coordinates":[5.908035,52.006046],"type":"Point"}
}