{
  "type": "Feature",
  "properties": {
    "addr:full":"Utrechtseweg 79 Oosterbeek Gelderland 6862 AD",
    "addr:housenumber":"79",
    "addr:postcode":"6862 ad",
    "addr:street":"Utrechtseweg;Gelderland",
    "iso:country":"NL",
    "sg:address":"Utrechtseweg 79",
    "sg:city":"Oosterbeek",
    "sg:classifiers":[
        {
            "category":"Bakery",
            "type":"Food & Drink"
        }
    ],
    "sg:phone":"+31 26 333 3053",
    "sg:postcode":"6862 AD",
    "sg:province":"Gelderland",
    "sg:tags":[
        "brood",
        "banket"
    ],
    "wof:name":"Kwaliteitsbakkerij Fa. P. Hus",
    "wof:placetype":"venue"
},
  "geometry": {"coordinates":[5.849684,51.986744],"type":"Point"}
}