{
  "type": "Feature",
  "properties": {
    "addr:full":"Hoofdstr 54-56 Bergambacht South Holland 2861 AR",
    "addr:housenumber":"54-56",
    "addr:postcode":"2861",
    "iso:country":"NL",
    "sg:address":"Hoofdstr 54-56",
    "sg:city":"Bergambacht",
    "sg:orig_category":"Handwerkartikelen",
    "sg:phone":"+31 182 353 563",
    "sg:postcode":"2861 AR",
    "sg:province":"South Holland",
    "wof:name":"Bonte Schaep, 'T",
    "wof:placetype":"venue"
},
  "geometry": {"coordinates":[4.782759,51.933838],"type":"Point"}
}