{
  "type": "Feature",
  "properties": {
    "addr:full":"Obrechtlaan 166 Assen Drenthe 9402 TM",
    "addr:housenumber":"166",
    "addr:postcode":"9402 tm",
    "addr:street":"Obrechtlaan",
    "iso:country":"NL",
    "sg:address":"Obrechtlaan 166",
    "sg:city":"Assen",
    "sg:orig_category":"Verzekeringen",
    "sg:phone":"+31 592 340 326",
    "sg:postcode":"9402 TM",
    "sg:province":"Drenthe",
    "wof:name":"Ottens Assurantie Adviseurs",
    "wof:placetype":"venue"
},
  "geometry": {"coordinates":[6.567287,53.008999],"type":"Point"}
}