{
  "type": "Feature",
  "properties": {
    "iso:country":"NL",
    "sg:address":"Bilderdykstr 482Hg",
    "sg:city":"Amsterdam",
    "sg:orig_category":"Fotojournalisten Freelance",
    "sg:phone":"+31 20 412 2084",
    "sg:postcode":"1052 NB",
    "sg:province":"Noord-Holland",
    "wof:name":"Kesteren Vof, G Van",
    "wof:placetype":"venue"
},
  "geometry": {"coordinates":[4.87043,52.371021],"type":"Point"}
}