{
  "type": "Feature",
  "properties": {
    "addr:full":"Zuiderwg 27 Groningen Groningen 9745 AA",
    "addr:housenumber":"27",
    "addr:postcode":"9745 aa",
    "addr:street":"Zuiderwg",
    "iso:country":"NL",
    "sg:address":"Zuiderwg 27",
    "sg:city":"Groningen",
    "sg:orig_category":"Postkantoren",
    "sg:phone":"+31 50 556 5225",
    "sg:postcode":"9745 AA",
    "sg:province":"Groningen",
    "sg:website":"http://www.postkantoor.nl",
    "wof:name":"Postkantoor",
    "wof:placetype":"venue"
},
  "geometry": {"coordinates":[6.501307,53.214745],"type":"Point"}
}