{
  "type": "Feature",
  "properties": {
    "addr:full":"Gondel 2217 Lelystad Flevoland 8243 CA",
    "addr:postcode":"2217;8243 ca",
    "addr:street":"Gondel;Flevoland",
    "iso:country":"NL",
    "sg:address":"Gondel 2217",
    "sg:city":"Lelystad",
    "sg:classifiers":[
        {
            "category":"Education",
            "subcategory":"Preschool",
            "type":"Public Place"
        }
    ],
    "sg:phone":"+31 320 222 422",
    "sg:postcode":"8243 CA",
    "sg:province":"Flevoland",
    "sg:tags":[
        "kleuteronderwijs",
        "basis-"
    ],
    "wof:name":"De Grundel",
    "wof:placetype":"venue"
},
  "geometry": {"coordinates":[5.455717,52.510162],"type":"Point"}
}