{
  "type": "Feature",
  "properties": {
    "iso:country":"NL",
    "sg:address":"Sluis 26A",
    "sg:city":"Marknesse",
    "sg:orig_category":"Beautyfarms And Sauna'S",
    "sg:phone":"+31 527 201 490",
    "sg:postcode":"8316 AM",
    "sg:province":"NL.",
    "wof:name":"Salon Wilma",
    "wof:placetype":"venue"
},
  "geometry": {"coordinates":[5.862937,52.707661],"type":"Point"}
}