{
  "type": "Feature",
  "properties": {
    "addr:full":"Euterpedreef 17 Utrecht Utrecht 3561 CV",
    "addr:housenumber":"17",
    "addr:postcode":"3561 cv",
    "addr:street":"Euterpedreef",
    "iso:country":"NL",
    "sg:address":"Euterpedreef 17",
    "sg:city":"Utrecht",
    "sg:classifiers":[
        {
            "category":"Food & Beverages",
            "subcategory":"Fruits & Vegetables",
            "type":"Retail Goods"
        }
    ],
    "sg:phone":"+31 30 262 0747",
    "sg:postcode":"3561 CV",
    "sg:province":"Utrecht",
    "sg:tags":[
        "groenten"
    ],
    "wof:name":"Fa F.M. Broekman",
    "wof:placetype":"venue"
},
  "geometry": {"coordinates":[5.128105,52.115894],"type":"Point"}
}