{
  "type": "Feature",
  "properties": {
    "addr:full":"Zenostraat 14 Rotterdam Zuid-Holland 3076 AV",
    "addr:housenumber":"14",
    "addr:postcode":"3076 av",
    "addr:street":"Zenostraat",
    "iso:country":"NL",
    "sg:address":"Zenostraat 14",
    "sg:city":"Rotterdam",
    "sg:orig_category":"Verhuur Audiovisuele Apparatuur",
    "sg:phone":"+31 10 432 8907",
    "sg:postcode":"3076 AV",
    "sg:province":"Zuid-Holland",
    "wof:name":"A.A. Van Der Schans",
    "wof:placetype":"venue"
},
  "geometry": {"coordinates":[4.527978,51.880581],"type":"Point"}
}