{
  "type": "Feature",
  "properties": {
    "iso:country":"NL",
    "sg:address":"Rozendk 33-37",
    "sg:city":"Den Burg",
    "sg:orig_category":"Vakantieverblijven",
    "sg:phone":"+31 222 314 146",
    "sg:postcode":"1791 PD",
    "sg:province":"Kentucky",
    "sg:website":"http://www.aldubo.nl",
    "wof:name":"Aldubo",
    "wof:placetype":"venue"
},
  "geometry": {"coordinates":[-84.755684,37.725872],"type":"Point"}
}