{
  "type": "Feature",
  "properties": {
    "addr:full":"Bonifaciusstraat 3 Kwadendamme Zeeland 4434 AD",
    "addr:housenumber":"3",
    "addr:postcode":"4434 ad",
    "addr:street":"Bonifaciusstraat",
    "iso:country":"NL",
    "sg:address":"Bonifaciusstraat 3",
    "sg:city":"Kwadendamme",
    "sg:classifiers":[
        {
            "category":"Professional",
            "subcategory":"Accounting & Tax Preparation",
            "type":"Services"
        }
    ],
    "sg:phone":"+31 113 649 603",
    "sg:postcode":"4434 AD",
    "sg:province":"Zeeland",
    "sg:tags":[
        "accountant"
    ],
    "wof:name":"De Pundert Accountants",
    "wof:placetype":"venue"
},
  "geometry": {"coordinates":[3.873787,51.432648],"type":"Point"}
}