{
  "type": "Feature",
  "properties": {
    "iso:country":"NL",
    "sg:address":"Stationswg 416",
    "sg:city":"Scherpenzeel Gld",
    "sg:orig_category":"Bedrijfsmechanisatie En -Automatisering",
    "sg:phone":"+31 33 277 4905",
    "sg:postcode":"3925 CG",
    "sg:province":"Utrecht",
    "sg:website":"http://www.hermac.nl",
    "wof:name":"Hermac, Power Systems Bv",
    "wof:placetype":"venue"
},
  "geometry": {"coordinates":[5.467378,52.081291],"type":"Point"}
}