{
  "type": "Feature",
  "properties": {
    "iso:country":"NL",
    "sg:address":"Boomdijk 29",
    "sg:city":"Klaaswaal",
    "sg:orig_category":"Goederenvervoer Over De Weg",
    "sg:phone":"+31 186 651 398",
    "sg:postcode":"3286 LD",
    "sg:province":"Zuid-Holland",
    "wof:name":"Expeditie Westdijk En Zn",
    "wof:placetype":"venue"
},
  "geometry": {"coordinates":[4.461644,51.759094],"type":"Point"}
}