{
  "type": "Feature",
  "properties": {
    "addr:full":"Kl Kerkstr 35 Leeuwarden Friesland 8911 DL",
    "addr:housenumber":"35",
    "addr:postcode":"8911 dl",
    "iso:country":"NL",
    "sg:address":"Kl Kerkstr 35",
    "sg:city":"Leeuwarden",
    "sg:orig_category":"Kappers",
    "sg:phone":"+31 58 216 0226",
    "sg:postcode":"8911 DL",
    "sg:province":"Friesland",
    "wof:name":"Capaldi Hair & Make-Up",
    "wof:placetype":"venue"
},
  "geometry": {"coordinates":[5.7913661003,53.2025337219],"type":"Point"}
}