{
  "type": "Feature",
  "properties": {
    "iso:country":"NL",
    "sg:address":"Endeldk 18B",
    "sg:city":"Honselersdyk",
    "sg:orig_category":"Logopedisten",
    "sg:phone":"+31 174 610 043",
    "sg:postcode":"2675 CS",
    "sg:province":"South Holland",
    "wof:name":"Gelder, S H Van",
    "wof:placetype":"venue"
},
  "geometry": {"coordinates":[4.231668,52.009415],"type":"Point"}
}