{
  "type": "Feature",
  "properties": {
    "addr:full":"Vlaszak 73 Breda Noord-Brabant 4811 GX",
    "addr:housenumber":"73",
    "addr:postcode":"4811 gx",
    "addr:street":"Vlaszak",
    "iso:country":"NL",
    "sg:address":"Vlaszak 73",
    "sg:city":"Breda",
    "sg:orig_category":"Schoenen - Groothandel",
    "sg:phone":"+31 76 520 5885",
    "sg:postcode":"4811 GX",
    "sg:province":"Noord-Brabant",
    "wof:name":"Clarks Benelux Bv",
    "wof:placetype":"venue"
},
  "geometry": {"coordinates":[4.781221,51.588097],"type":"Point"}
}