{
  "type": "Feature",
  "properties": {
    "addr:full":"Eendrachtstraat 31 Terschuur Gelderland 3784 KA",
    "addr:housenumber":"31",
    "addr:postcode":"3784 ka",
    "addr:street":"Eendrachtstraat;Gelderland",
    "iso:country":"NL",
    "sg:address":"Eendrachtstraat 31",
    "sg:city":"Terschuur",
    "sg:orig_category":"Zuivelproducten And Spijsoli?n Gh",
    "sg:phone":"+31 342 460 020",
    "sg:postcode":"3784 KA",
    "sg:province":"Gelderland",
    "wof:name":"Zonne Ei Farm Bv",
    "wof:placetype":"venue"
},
  "geometry": {"coordinates":[5.517483,52.166927],"type":"Point"}
}