{
  "type": "Feature",
  "properties": {
    "addr:full":"Marsstr 1 Hoofddorp Noord-Holland 2132 HR",
    "addr:housenumber":"1",
    "addr:postcode":"2132 hr",
    "addr:street":"Marsstr",
    "iso:country":"NL",
    "sg:address":"Marsstr 1",
    "sg:city":"Hoofddorp",
    "sg:orig_category":"Benzine En Olie - Groothandel",
    "sg:phone":"+31 23 566 2200",
    "sg:postcode":"2132 HR",
    "sg:province":"Noord-Holland",
    "sg:website":"http://www.bkgas.nl",
    "wof:name":"Bk-Gas Bv",
    "wof:placetype":"venue"
},
  "geometry": {"coordinates":[4.703803,52.29781],"type":"Point"}
}