{
  "type": "Feature",
  "properties": {
    "addr:full":"Seringenlaan 178 Steenbergen Nb Noord-Brabant 4651 KX",
    "addr:housenumber":"178",
    "addr:postcode":"4651 kx",
    "addr:street":"Seringenlaan",
    "iso:country":"NL",
    "sg:address":"Seringenlaan 178",
    "sg:city":"Steenbergen Nb",
    "sg:orig_category":"Landbouwdiensten",
    "sg:phone":"+31 167 563 734",
    "sg:postcode":"4651 KX",
    "sg:province":"Noord-Brabant",
    "wof:name":"G En M Koenraadt",
    "wof:placetype":"venue"
},
  "geometry": {"coordinates":[4.31544,51.572678],"type":"Point"}
}