{
  "type": "Feature",
  "properties": {
    "addr:full":"Kleiwg 225 Rotterdam South Holland 3051 XK",
    "addr:housenumber":"225",
    "addr:postcode":"3051 xk",
    "iso:country":"NL",
    "sg:address":"Kleiwg 225",
    "sg:city":"Rotterdam",
    "sg:orig_category":"Keukenspeciaalzaken",
    "sg:phone":"+31 10 461 0920",
    "sg:postcode":"3051 XK",
    "sg:province":"South Holland",
    "wof:name":"Dometa Bv",
    "wof:placetype":"venue"
},
  "geometry": {"coordinates":[4.471928,51.945065],"type":"Point"}
}