{
  "type": "Feature",
  "properties": {
    "addr:full":"Hengelosestr 565 Enschede NL.08 7521 AG",
    "addr:housenumber":"565",
    "addr:postcode":"7521",
    "iso:country":"NL",
    "sg:address":"Hengelosestr 565",
    "sg:city":"Enschede",
    "sg:orig_category":"Accountants - Administratie- Consulenten En -Kantoren",
    "sg:phone":"+31 53 430 2305",
    "sg:postcode":"7521 AG",
    "sg:province":"NL.08",
    "wof:name":"Jong & Laan, De",
    "wof:placetype":"venue"
},
  "geometry": {"coordinates":[6.850439,52.23724],"type":"Point"}
}