{
  "type": "Feature",
  "properties": {
    "iso:country":"NL",
    "sg:address":"Hoge Biezen 1",
    "sg:city":"Veghel",
    "sg:orig_category":"Hoefdierhouderijen",
    "sg:phone":"+31 413 363 453",
    "sg:postcode":"5465 PP",
    "sg:province":"Noord-Brabant",
    "wof:name":"A.H.M. Van Der Heyden",
    "wof:placetype":"venue"
},
  "geometry": {"coordinates":[5.537873,51.586094],"type":"Point"}
}