{
  "type": "Feature",
  "properties": {
    "addr:full":"Hoge Biezen 1 Veghel Noord-Brabant 5465 PP",
    "addr:housenumber":"1",
    "addr:postcode":"5465 pp",
    "addr:street":"Hoge Biezen",
    "iso:country":"NL",
    "sg:address":"Hoge Biezen 1",
    "sg:city":"Veghel",
    "sg:orig_category":"Hoefdierhouderijen",
    "sg:phone":"+31 413 363 453",
    "sg:postcode":"5465 PP",
    "sg:province":"Noord-Brabant",
    "wof:name":"A.H.M. Van Der Heyden",
    "wof:placetype":"venue"
},
  "geometry": {"coordinates":[5.537873,51.586094],"type":"Point"}
}