{
  "type": "Feature",
  "properties": {
    "addr:full":"Steenstr 101 Boxmeer Noord-Brabant 5831 JD",
    "addr:housenumber":"101",
    "addr:postcode":"5831 jd",
    "iso:country":"NL",
    "sg:address":"Steenstr 101",
    "sg:city":"Boxmeer",
    "sg:classifiers":[
        {
            "category":"Food & Beverages",
            "subcategory":"Fruits & Vegetables",
            "type":"Retail Goods"
        }
    ],
    "sg:phone":"+31 485 571 604",
    "sg:postcode":"5831 JD",
    "sg:province":"Noord-Brabant",
    "sg:tags":[
        "en",
        "groenten"
    ],
    "wof:name":"Chris Cox",
    "wof:placetype":"venue"
},
  "geometry": {"coordinates":[5.947337,51.648773],"type":"Point"}
}