{
  "type": "Feature",
  "properties": {
    "iso:country":"NL",
    "sg:address":"Smalleweg 2",
    "sg:city":"Bunnik",
    "sg:orig_category":"Werving And Selectie Van Tijdelijk Personeel And Uitzendkantoren",
    "sg:phone":"+31 30 656 3437",
    "sg:postcode":"3981 EG",
    "sg:province":"Utrecht",
    "wof:name":"Dactylo",
    "wof:placetype":"venue"
},
  "geometry": {"coordinates":[5.2021799088,52.0676689148],"type":"Point"}
}