{
  "type": "Feature",
  "properties": {
    "iso:country":"NL",
    "sg:address":"K Vd Bergeln 25",
    "sg:city":"Rotterdam",
    "sg:orig_category":"Adviesbureaus Bedrijfsorganisatie",
    "sg:phone":"+31 10 422 6967",
    "sg:postcode":"3054 EN",
    "sg:province":"Zuid-Holland",
    "sg:website":"http://www.waterkring.nl",
    "wof:name":"Waterkring",
    "wof:placetype":"venue"
},
  "geometry": {"coordinates":[4.49284,51.957539],"type":"Point"}
}