{
  "type": "Feature",
  "properties": {
    "addr:full":"Kronenburgpassage 94 Arnhem Gelderland 6831 ER",
    "addr:housenumber":"94",
    "addr:postcode":"6831 er",
    "addr:street":"Kronenburgpassage",
    "iso:country":"NL",
    "sg:address":"Kronenburgpassage 94",
    "sg:city":"Arnhem",
    "sg:orig_category":"Broodjeszaken",
    "sg:phone":"+31 26 327 4525",
    "sg:postcode":"6831 ER",
    "sg:province":"Gelderland",
    "sg:website":"http://www.lunchroom-bonheur.info",
    "wof:name":"Delifrance",
    "wof:placetype":"venue"
},
  "geometry": {"coordinates":[5.897324,51.958195],"type":"Point"}
}