{
  "type": "Feature",
  "properties": {
    "iso:country":"NL",
    "sg:address":"Vaerhorst 20-22",
    "sg:city":"Rotterdam",
    "sg:orig_category":"Feestartikelen",
    "sg:phone":"+31 10 419 2402",
    "sg:postcode":"3085 HT",
    "sg:province":"Zuid-Holland",
    "wof:name":"J. Bout",
    "wof:placetype":"venue"
},
  "geometry": {"coordinates":[4.496007,51.874462],"type":"Point"}
}