{
  "type": "Feature",
  "properties": {
    "addr:full":"Waalstraat 24 Arnhem Gelderland 6826 BP",
    "addr:housenumber":"24",
    "addr:postcode":"6826 bp",
    "addr:street":"Waalstraat",
    "iso:country":"NL",
    "sg:address":"Waalstraat 24",
    "sg:city":"Arnhem",
    "sg:orig_category":"Apothekers",
    "sg:phone":"+31 26 361 4118",
    "sg:postcode":"6826 BP",
    "sg:province":"Gelderland",
    "wof:name":"Kringapotheek Witteveen",
    "wof:placetype":"venue"
},
  "geometry": {"coordinates":[5.942667,51.983635],"type":"Point"}
}