{
  "type": "Feature",
  "properties": {
    "addr:full":"Spakenburgln 124 Tilburg Noord-Brabant 5035 JC",
    "addr:housenumber":"124",
    "addr:postcode":"5035 jc",
    "addr:street":"Tilburg",
    "iso:country":"NL",
    "sg:address":"Spakenburgln 124",
    "sg:city":"Tilburg",
    "sg:orig_category":"Loodgieters",
    "sg:phone":"+31 13 543 1732",
    "sg:postcode":"5035 JC",
    "sg:province":"Noord-Brabant",
    "wof:name":"Erve Loodgieter, F Van",
    "wof:placetype":"venue"
},
  "geometry": {"coordinates":[4.977154,51.579533],"type":"Point"}
}