{
  "type": "Feature",
  "properties": {
    "addr:full":"Broekhovensewg 166 Tilburg Noord-Brabant 5021 LJ",
    "addr:housenumber":"166",
    "addr:postcode":"5021 lj",
    "addr:street":"Tilburg",
    "iso:country":"NL",
    "sg:address":"Broekhovensewg 166",
    "sg:city":"Tilburg",
    "sg:orig_category":"Acupunctuur",
    "sg:phone":"+31 13 542 5140",
    "sg:postcode":"5021 LJ",
    "sg:province":"Noord-Brabant",
    "wof:name":"Nieuwlands Artsen",
    "wof:placetype":"venue"
},
  "geometry": {"coordinates":[5.094038,51.544804],"type":"Point"}
}