{
  "type": "Feature",
  "properties": {
    "addr:full":"Dorpsdijk 18 Lobith Gelderland 6915 AD",
    "addr:housenumber":"18",
    "addr:postcode":"6915 ad",
    "addr:street":"Dorpsdijk;Gelderland",
    "iso:country":"NL",
    "sg:address":"Dorpsdijk 18",
    "sg:city":"Lobith",
    "sg:orig_category":"Glaszetten",
    "sg:phone":"+31 316 541 029",
    "sg:postcode":"6915 AD",
    "sg:province":"Gelderland",
    "wof:name":"Ton Mekelenkamp Schildersbedrijf",
    "wof:placetype":"venue"
},
  "geometry": {"coordinates":[6.12034,51.85936],"type":"Point"}
}