{
  "type": "Feature",
  "properties": {
    "addr:full":"Poststr 9 Krabbendyke Zeeland 4413 CJ",
    "addr:housenumber":"9",
    "addr:postcode":"4413 cj",
    "addr:street":"Poststr;Zeeland",
    "iso:country":"NL",
    "sg:address":"Poststr 9",
    "sg:city":"Krabbendyke",
    "sg:orig_category":"Postkantoren",
    "sg:phone":"+31 113 501 599",
    "sg:postcode":"4413 CJ",
    "sg:province":"Zeeland",
    "sg:website":"http://www.postkantoor.nl",
    "wof:name":"Postkantoor",
    "wof:placetype":"venue"
},
  "geometry": {"coordinates":[4.111545,51.431549],"type":"Point"}
}