{
  "type": "Feature",
  "properties": {
    "addr:full":"Stellingmolen 16 Purmerend Noord-Holland 1444 GW",
    "addr:housenumber":"16",
    "addr:postcode":"1444 gw",
    "addr:street":"Stellingmolen",
    "iso:country":"NL",
    "sg:address":"Stellingmolen 16",
    "sg:city":"Purmerend",
    "sg:orig_category":"Onderhoudswerken",
    "sg:phone":"+31 299 431 450",
    "sg:postcode":"1444 GW",
    "sg:province":"Noord-Holland",
    "wof:name":"Aukema, C N",
    "wof:placetype":"venue"
},
  "geometry": {"coordinates":[4.975071,52.521397],"type":"Point"}
}