{
  "type": "Feature",
  "properties": {
    "addr:full":"Zwet 36 Delfzijl Groningen 9932 AB",
    "addr:housenumber":"36",
    "addr:postcode":"9932 ab",
    "addr:street":"Zwet",
    "iso:country":"NL",
    "sg:address":"Zwet 36",
    "sg:city":"Delfzijl",
    "sg:orig_category":"Sportverenigingen En Ontspannings- Verenigingen",
    "sg:phone":"+31 596 611 764",
    "sg:postcode":"9932 AB",
    "sg:province":"Groningen",
    "wof:name":"Delfzijl Schuttersver",
    "wof:placetype":"venue"
},
  "geometry": {"coordinates":[6.912753,53.320515],"type":"Point"}
}