{
  "type": "Feature",
  "properties": {
    "iso:country":"NL",
    "sg:address":"Oudenoord 182",
    "sg:city":"Utrecht",
    "sg:orig_category":"Onderzoekbureaus",
    "sg:phone":"+31 30 230 4010",
    "sg:postcode":"3513 EV",
    "sg:province":"Utrecht",
    "sg:website":"http://www.nisso.nl",
    "wof:name":"Rutgers Nisso Groep",
    "wof:placetype":"venue"
},
  "geometry": {"coordinates":[5.110614,52.098499],"type":"Point"}
}