{
  "type": "Feature",
  "properties": {
    "addr:full":"Tiendpln 7 Rotterdam Zuid-Holland 3014 BH",
    "addr:housenumber":"7",
    "addr:postcode":"3014 bh",
    "addr:street":"Tiendpln",
    "iso:country":"NL",
    "sg:address":"Tiendpln 7",
    "sg:city":"Rotterdam",
    "sg:orig_category":"Bloemen En Planten",
    "sg:phone":"+31 10 412 6670",
    "sg:postcode":"3014 BH",
    "sg:province":"Zuid-Holland",
    "wof:name":"Flowerman, The",
    "wof:placetype":"venue"
},
  "geometry": {"coordinates":[4.465377,51.919815],"type":"Point"}
}