{
  "type": "Feature",
  "properties": {
    "addr:full":"Noorderbaan 51 Biddinghuizen NL. 8256 PP",
    "addr:housenumber":"51",
    "addr:postcode":"8256 pp",
    "addr:street":"Noorderbaan;Nl.",
    "iso:country":"NL",
    "sg:address":"Noorderbaan 51",
    "sg:city":"Biddinghuizen",
    "sg:orig_category":"Fitnesscentra",
    "sg:phone":"+31 321 332 244",
    "sg:postcode":"8256 PP",
    "sg:province":"NL.",
    "wof:name":"Sporting Fitanatic",
    "wof:placetype":"venue"
},
  "geometry": {"coordinates":[5.696075,52.459957],"type":"Point"}
}