{
  "type": "Feature",
  "properties": {
    "addr:full":"Eendracht 6 Mydrecht Utrecht 3641 ML",
    "addr:housenumber":"6;3641",
    "addr:street":"Eendracht;Ml",
    "iso:country":"NL",
    "sg:address":"Eendracht 6",
    "sg:city":"Mydrecht",
    "sg:orig_category":"Scholen Voor Basisonderwijs",
    "sg:phone":"+31 297 285 688",
    "sg:postcode":"3641 ML",
    "sg:province":"Utrecht",
    "wof:name":"Hoeksteen Prot Chr, De",
    "wof:placetype":"venue"
},
  "geometry": {"coordinates":[4.86178,52.20578],"type":"Point"}
}