{
  "type": "Feature",
  "properties": {
    "addr:full":"Burg Steertstr 1B Oosthuizen Noord-Holland 1474 MN",
    "addr:housenumber":"1b",
    "addr:postcode":"1474 mn",
    "addr:street":"Burg Steertstr",
    "iso:country":"NL",
    "sg:address":"Burg Steertstr 1B",
    "sg:city":"Oosthuizen",
    "sg:orig_category":"Administratie- En Boekhoudkantoren",
    "sg:phone":"+31 299 404 766",
    "sg:postcode":"1474 MN",
    "sg:province":"Noord-Holland",
    "wof:name":"Elk Administratiekantoor, Van",
    "wof:placetype":"venue"
},
  "geometry": {"coordinates":[5.001787,52.576946],"type":"Point"}
}