{
  "type": "Feature",
  "properties": {
    "addr:full":"J V Ruysdaelpln 22 Lisse Zuid-Holland 2162 BH",
    "addr:housenumber":"22",
    "addr:postcode":"2162 bh",
    "addr:street":"J;Ruysdaelpln",
    "iso:country":"NL",
    "sg:address":"J V Ruysdaelpln 22",
    "sg:city":"Lisse",
    "sg:classifiers":[
        {
            "category":"Home & Garden",
            "subcategory":"Garden Supply",
            "type":"Retail Goods"
        }
    ],
    "sg:phone":"+31 252 414 227",
    "sg:postcode":"2162 BH",
    "sg:province":"Zuid-Holland",
    "sg:tags":[
        "zand",
        "en",
        "grind"
    ],
    "wof:name":"Struik Jr, C",
    "wof:placetype":"venue"
},
  "geometry": {"coordinates":[4.552546,52.257221],"type":"Point"}
}