{
  "type": "Feature",
  "properties": {
    "addr:full":"L Beekstr 71 Amersfoort Utrecht 3817 AM",
    "addr:housenumber":"71",
    "addr:postcode":"3817",
    "iso:country":"NL",
    "sg:address":"L Beekstr 71",
    "sg:city":"Amersfoort",
    "sg:orig_category":"Bedrijfsorganisaties",
    "sg:phone":"+31 6 19200136",
    "sg:postcode":"3817 AM",
    "sg:province":"Utrecht",
    "sg:website":"http://www.vdmadvies.nl",
    "wof:name":"Vdm Advies",
    "wof:placetype":"venue"
},
  "geometry": {"coordinates":[5.387041,52.151253],"type":"Point"}
}