{
  "type": "Feature",
  "properties": {
    "addr:full":"Raamstg 55 Leiden Zuid-Holland 2311 PL",
    "addr:housenumber":"55",
    "addr:postcode":"2311 pl",
    "addr:street":"Raamstg",
    "iso:country":"NL",
    "sg:address":"Raamstg 55",
    "sg:city":"Leiden",
    "sg:orig_category":"Adviesbureaus Bedrijfsorganisatie",
    "sg:phone":"+31 71 514 1468",
    "sg:postcode":"2311 PL",
    "sg:province":"Zuid-Holland",
    "sg:website":"http://www.inedebock.nl",
    "wof:name":"Bock, Ine De",
    "wof:placetype":"venue"
},
  "geometry": {"coordinates":[4.491947,52.154648],"type":"Point"}
}