{
  "type": "Feature",
  "properties": {
    "addr:full":"Kon Wilhelminapln 43A Waddinxveen Zuid-Holland 2741 EC",
    "addr:housenumber":"43a",
    "addr:postcode":"2741 ec",
    "addr:street":"Kon",
    "iso:country":"NL",
    "sg:address":"Kon Wilhelminapln 43A",
    "sg:city":"Waddinxveen",
    "sg:orig_category":"Wereldwinkels",
    "sg:phone":"+31 182 632 324",
    "sg:postcode":"2741 EC",
    "sg:province":"Zuid-Holland",
    "wof:name":"Wereldwinkel",
    "wof:placetype":"venue"
},
  "geometry": {"coordinates":[4.6534972191,52.0497322083],"type":"Point"}
}