{
  "type": "Feature",
  "properties": {
    "addr:full":"Postweg 18 Doorn Utrecht 3941 KA",
    "addr:housenumber":"18",
    "addr:postcode":"3941 ka",
    "addr:street":"Postweg",
    "iso:country":"NL",
    "sg:address":"Postweg 18",
    "sg:city":"Doorn",
    "sg:orig_category":"Krantenuitgeverijen",
    "sg:phone":"+31 343 413 300",
    "sg:postcode":"3941 KA",
    "sg:province":"Utrecht",
    "wof:name":"Vereniging Het Zoeklicht",
    "wof:placetype":"venue"
},
  "geometry": {"coordinates":[5.352072,52.031906],"type":"Point"}
}