{
  "type": "Feature",
  "properties": {
    "addr:full":"Heer Halewynstr 12 Amsterdam North Holland 1055 SP",
    "addr:housenumber":"12",
    "addr:postcode":"1055 sp",
    "addr:street":"Heer Halewynstr",
    "iso:country":"NL",
    "sg:address":"Heer Halewynstr 12",
    "sg:city":"Amsterdam",
    "sg:orig_category":"Beeldende Kunstenaars",
    "sg:phone":"+31 20 682 7153",
    "sg:postcode":"1055 SP",
    "sg:province":"North Holland",
    "wof:name":"Snijder, H L",
    "wof:placetype":"venue"
},
  "geometry": {"coordinates":[4.854667,52.377617],"type":"Point"}
}