{
  "type": "Feature",
  "properties": {
    "iso:country":"NL",
    "sg:address":"Van Kleffenslaan 161",
    "sg:city":"Middelburg",
    "sg:orig_category":"Onderhoud And Reparatie Kantoorapparatuur",
    "sg:phone":"+31 118 629 847",
    "sg:postcode":"4334 HE",
    "sg:province":"Zeeland",
    "wof:name":"Da Vinci",
    "wof:placetype":"venue"
},
  "geometry": {"coordinates":[3.590821,51.505421],"type":"Point"}
}