{
  "type": "Feature",
  "properties": {
    "addr:full":"Rompertdreef 58 S Hertogenbosch Noord-Brabant 5233 EL",
    "addr:housenumber":"58",
    "addr:postcode":"5233 el",
    "addr:street":"Rompertdreef;S Hertogenbosch",
    "iso:country":"NL",
    "sg:address":"Rompertdreef 58",
    "sg:city":"S Hertogenbosch",
    "sg:orig_category":"Verloskundigen",
    "sg:phone":"+31 73 641 9339",
    "sg:postcode":"5233 EL",
    "sg:province":"Noord-Brabant",
    "wof:name":"Rebers-Spaargaren, W M",
    "wof:placetype":"venue"
},
  "geometry": {"coordinates":[5.314442,51.7164],"type":"Point"}
}