{
  "type": "Feature",
  "properties": {
    "addr:full":"Staten Bolwerk 22 Haarlem North Holland 2011 ML",
    "addr:housenumber":"22",
    "addr:postcode":"2011 ml",
    "addr:street":"Staten Bolwerk",
    "iso:country":"NL",
    "sg:address":"Staten Bolwerk 22",
    "sg:city":"Haarlem",
    "sg:orig_category":"Makelaars In Onroerend Goed",
    "sg:phone":"+31 23 532 0277",
    "sg:postcode":"2011 ML",
    "sg:province":"North Holland",
    "wof:name":"G. Henstra, Makelaar In Onr. Goederen",
    "wof:placetype":"venue"
},
  "geometry": {"coordinates":[4.635385,52.388939],"type":"Point"}
}