{
  "type": "Feature",
  "properties": {
    "addr:full":"J Marisstr 96 Amsterdam North Holland 1058 JB",
    "addr:housenumber":"96",
    "addr:postcode":"1058 jb",
    "iso:country":"NL",
    "sg:address":"J Marisstr 96",
    "sg:city":"Amsterdam",
    "sg:orig_category":"Vertalers",
    "sg:phone":"+31 20 617 1445",
    "sg:postcode":"1058 JB",
    "sg:province":"North Holland",
    "wof:name":"Wennekendonk-Visser, Drs J",
    "wof:placetype":"venue"
},
  "geometry": {"coordinates":[4.852415,52.356441],"type":"Point"}
}