{
  "type": "Feature",
  "properties": {
    "addr:full":"Zangvogelwg 4 Amersfoort Utrecht 3815 DL",
    "addr:housenumber":"4",
    "addr:postcode":"3815 dl",
    "addr:street":"Zangvogelwg",
    "iso:country":"NL",
    "sg:address":"Zangvogelwg 4",
    "sg:city":"Amersfoort",
    "sg:orig_category":"Scholen Voor Algemeen Voortgezet Onderwijs",
    "sg:phone":"+31 33 470 1126",
    "sg:postcode":"3815 DL",
    "sg:province":"Utrecht",
    "wof:name":"Centr Opvangvoorziening",
    "wof:placetype":"venue"
},
  "geometry": {"coordinates":[5.406454,52.161797],"type":"Point"}
}