{
  "type": "Feature",
  "properties": {
    "addr:full":"Van Diemenstraat 314 Amsterdam North Holland 1013 CR",
    "addr:housenumber":"314",
    "addr:postcode":"1013 cr",
    "addr:street":"Van Diemenstraat",
    "iso:country":"NL",
    "sg:address":"Van Diemenstraat 314",
    "sg:city":"Amsterdam",
    "sg:orig_category":"Bedrijfs- And Managementsconsultants",
    "sg:phone":"+31 20 420 7780",
    "sg:postcode":"1013 CR",
    "sg:province":"North Holland",
    "wof:name":"Tote M Business Architects Bv",
    "wof:placetype":"venue"
},
  "geometry": {"coordinates":[4.887005,52.390293],"type":"Point"}
}