{
  "type": "Feature",
  "properties": {
    "addr:full":"Adolphinepln 6 Ossendrecht Noord-Brabant 4641 EH",
    "addr:housenumber":"6",
    "addr:postcode":"4641 eh",
    "addr:street":"Adolphinepln",
    "iso:country":"NL",
    "sg:address":"Adolphinepln 6",
    "sg:city":"Ossendrecht",
    "sg:orig_category":"Broodjeszaken",
    "sg:phone":"+31 164 674 239",
    "sg:postcode":"4641 EH",
    "sg:province":"Noord-Brabant",
    "wof:name":"Panach?",
    "wof:placetype":"venue"
},
  "geometry": {"coordinates":[4.329856,51.395515],"type":"Point"}
}