{
  "type": "Feature",
  "properties": {
    "iso:country":"NL",
    "sg:address":"Staalstr 163-165",
    "sg:city":"Velsen Noord",
    "sg:orig_category":"Onderhoudswerken",
    "sg:phone":"+31 251 273 032",
    "sg:postcode":"1951 MB",
    "sg:province":"Noord-Holland",
    "sg:website":"http://www.rbmeurope.com",
    "wof:name":"Rbm Europe",
    "wof:placetype":"venue"
},
  "geometry": {"coordinates":[4.62722,52.477566],"type":"Point"}
}