{
  "type": "Feature",
  "properties": {
    "addr:full":"Grt Bickersstr 253 Amsterdam North Holland 1013 KP",
    "addr:housenumber":"253",
    "addr:postcode":"1013 kp",
    "iso:country":"NL",
    "sg:address":"Grt Bickersstr 253",
    "sg:city":"Amsterdam",
    "sg:orig_category":"Onderhoudswerken",
    "sg:phone":"+31 6 53479784",
    "sg:postcode":"1013 KP",
    "sg:province":"North Holland",
    "wof:name":"Hms",
    "wof:placetype":"venue"
},
  "geometry": {"coordinates":[4.889027,52.385677],"type":"Point"}
}