{
  "type": "Feature",
  "properties": {
    "addr:full":"Beurtschipper 14D Nijkerk Gld Gelderland 3861 SC",
    "addr:housenumber":"14d",
    "addr:postcode":"3861",
    "addr:street":"Beurtschipper;Gld Gelderland",
    "iso:country":"NL",
    "sg:address":"Beurtschipper 14D",
    "sg:city":"Nijkerk Gld",
    "sg:orig_category":"Meubelmakerijen",
    "sg:phone":"+31 33 246 5979",
    "sg:postcode":"3861 SC",
    "sg:province":"Gelderland",
    "wof:name":"Spirit Of Wood",
    "wof:placetype":"venue"
},
  "geometry": {"coordinates":[5.46655,52.23053],"type":"Point"}
}