{
  "type": "Feature",
  "properties": {
    "addr:full":"Staalstraat 11 Amsterdam North Holland 1011 JK",
    "addr:housenumber":"11",
    "addr:postcode":"1011 jk",
    "addr:street":"Staalstraat",
    "iso:country":"NL",
    "sg:address":"Staalstraat 11",
    "sg:city":"Amsterdam",
    "sg:orig_category":"Babyartikelen Detailhandel",
    "sg:phone":"+31 20 623 1805",
    "sg:postcode":"1011 JK",
    "sg:province":"North Holland",
    "wof:name":"De Beestenwinkel",
    "wof:placetype":"venue"
},
  "geometry": {"coordinates":[4.897936,52.368256],"type":"Point"}
}