{
  "type": "Feature",
  "properties": {
    "addr:full":"Roos Van Dekama Erf 50 Capelle A/D Ijssel South Holland 2907 EA",
    "addr:housenumber":"50;a / d",
    "addr:postcode":"2907 ea",
    "addr:street":"Roos Van Dekama Erf;Ijssel South",
    "iso:country":"NL",
    "sg:address":"Roos Van Dekama Erf 50",
    "sg:city":"Capelle A/D Ijssel",
    "sg:orig_category":"Technische Studies And Onderzoek",
    "sg:phone":"+31 10 442 5593",
    "sg:postcode":"2907 EA",
    "sg:province":"South Holland",
    "wof:name":"Nederlandse Wasindustrie",
    "wof:placetype":"venue"
},
  "geometry": {"coordinates":[4.577916,51.94722],"type":"Point"}
}