{
  "type": "Feature",
  "properties": {
    "addr:full":"Legmeerdijk 260 Amstelveen North Holland 1187  N",
    "addr:housenumber":"260;1187",
    "addr:street":"Legmeerdijk;N",
    "iso:country":"NL",
    "sg:address":"Legmeerdijk 260",
    "sg:city":"Amstelveen",
    "sg:orig_category":"Autoreparatie And Auto-Onderhoud",
    "sg:phone":"+31 20 645 0792",
    "sg:postcode":"1187  N",
    "sg:province":"North Holland",
    "wof:name":"Van Den Berg Autoschade",
    "wof:placetype":"venue"
},
  "geometry": {"coordinates":[4.800249,52.265282],"type":"Point"}
}