{
  "type": "Feature",
  "properties": {
    "iso:country":"NL",
    "sg:address":"Valkhof 60",
    "sg:city":"Barneveld",
    "sg:orig_category":"Balletscholen",
    "sg:phone":"+31 342 417 965",
    "sg:postcode":"3772 EC",
    "sg:province":"Gelderland",
    "wof:name":"Tomasoa, Y",
    "wof:placetype":"venue"
},
  "geometry": {"coordinates":[5.580106,52.132404],"type":"Point"}
}