{
  "type": "Feature",
  "properties": {
    "addr:full":"Poolsterstraat 106 Capelle Aan Den Ijssel Zuid-Holland 3067 LX",
    "addr:housenumber":"106",
    "addr:postcode":"aan den ijssel;3067 lx",
    "addr:street":"Poolsterstraat",
    "iso:country":"NL",
    "sg:address":"Poolsterstraat 106",
    "sg:city":"Capelle Aan Den Ijssel",
    "sg:orig_category":"Bloemen And Planten",
    "sg:phone":"+31 10 420 4800",
    "sg:postcode":"3067 LX",
    "sg:province":"Zuid-Holland",
    "wof:name":"Slingerland",
    "wof:placetype":"venue"
},
  "geometry": {"coordinates":[4.55193,51.944969],"type":"Point"}
}