{
  "type": "Feature",
  "properties": {
    "iso:country":"NL",
    "sg:address":"Braspenning 15",
    "sg:city":"Mydrecht",
    "sg:orig_category":"Geluidsbanden - Fabrieken En Groothandel",
    "sg:phone":"+31 6 53284458",
    "sg:postcode":"3641 LB",
    "sg:province":"Utrecht",
    "wof:name":"Jutanic",
    "wof:placetype":"venue"
},
  "geometry": {"coordinates":[4.863978,52.210838],"type":"Point"}
}