{
  "type": "Feature",
  "properties": {
    "addr:full":"Minervaln 47 Amsterdam Noord-Holland 1077 NN",
    "addr:housenumber":"47",
    "addr:postcode":"1077 nn",
    "addr:street":"Minervaln",
    "iso:country":"NL",
    "sg:address":"Minervaln 47",
    "sg:city":"Amsterdam",
    "sg:orig_category":"Adviesbureaus Bedrijfsorganisatie",
    "sg:phone":"+31 20 672 2264",
    "sg:postcode":"1077 NN",
    "sg:province":"Noord-Holland",
    "wof:name":"Meekhof Bv",
    "wof:placetype":"venue"
},
  "geometry": {"coordinates":[4.87585,52.345482],"type":"Point"}
}