{
  "type": "Feature",
  "properties": {
    "addr:full":"Burgerhoutsestraat 34 Roosendaal North Brabant 4701 EM",
    "addr:housenumber":"34",
    "addr:postcode":"4701 em",
    "addr:street":"Burgerhoutsestraat",
    "iso:country":"NL",
    "sg:address":"Burgerhoutsestraat 34",
    "sg:city":"Roosendaal",
    "sg:orig_category":"Meubelzaken, Woning- And Keukeninrichting",
    "sg:phone":"+31 165 568 898",
    "sg:postcode":"4701 EM",
    "sg:province":"North Brabant",
    "wof:name":"De Bedstee",
    "wof:placetype":"venue"
},
  "geometry": {"coordinates":[4.464036,51.530037],"type":"Point"}
}