{
  "type": "Feature",
  "properties": {
    "addr:full":"Bovenstrwg 4A Oldebroek Gelderland 8096 PE",
    "addr:housenumber":"4a",
    "addr:postcode":"8096 pe",
    "addr:street":"Bovenstrwg;Gelderland",
    "iso:country":"NL",
    "sg:address":"Bovenstrwg 4A",
    "sg:city":"Oldebroek",
    "sg:orig_category":"Verbouwingen",
    "sg:phone":"+31 525 633 087",
    "sg:postcode":"8096 PE",
    "sg:province":"Gelderland",
    "wof:name":"Schreurs, B",
    "wof:placetype":"venue"
},
  "geometry": {"coordinates":[5.8934,52.445419],"type":"Point"}
}