{
  "type": "Feature",
  "properties": {
    "addr:full":"Beeselseweg 25 Kessel Lb Limburg 5995 AP",
    "addr:housenumber":"25",
    "addr:postcode":"lb;5995 ap",
    "addr:street":"Beeselseweg",
    "iso:country":"NL",
    "sg:address":"Beeselseweg 25",
    "sg:city":"Kessel Lb",
    "sg:orig_category":"Film-, Tv- And Videoproductie",
    "sg:phone":"+31 77 462 1780",
    "sg:postcode":"5995 AP",
    "sg:province":"Limburg",
    "wof:name":"P.J.P. Film Bv",
    "wof:placetype":"venue"
},
  "geometry": {"coordinates":[6.046547,51.288082],"type":"Point"}
}