{
  "type": "Feature",
  "properties": {
    "addr:full":"Voorstr 292B Dordrecht Zuid-Holland 3311 ET",
    "addr:housenumber":"292b",
    "addr:postcode":"3311 et",
    "iso:country":"NL",
    "sg:address":"Voorstr 292B",
    "sg:city":"Dordrecht",
    "sg:classifiers":[
        {
            "category":"Food & Beverages",
            "subcategory":"Bakery",
            "type":"Retail Goods"
        }
    ],
    "sg:phone":"+31 78 614 2691",
    "sg:postcode":"3311 ET",
    "sg:province":"Zuid-Holland",
    "sg:tags":[
        "brood",
        "en",
        "banket"
    ],
    "sg:website":"http://www.breggenbakkers.nl",
    "wof:name":"Breggen, Van Der",
    "wof:placetype":"venue"
},
  "geometry": {"coordinates":[4.665857,51.814114],"type":"Point"}
}