{
  "type": "Feature",
  "properties": {
    "iso:country":"NL",
    "sg:address":"Dianaln 60",
    "sg:city":"Apeldoorn",
    "sg:orig_category":"Bloemisterijartikelen - Fabrieken En Groothandel",
    "sg:phone":"+31 55 366 3712",
    "sg:postcode":"7321 GJ",
    "sg:province":"Gelderland",
    "wof:name":"Nedico",
    "wof:placetype":"venue"
},
  "geometry": {"coordinates":[5.9838,52.209541],"type":"Point"}
}