{
  "type": "Feature",
  "properties": {
    "iso:country":"NL",
    "sg:address":"Zandpad 5",
    "sg:city":"Amsterdam",
    "sg:orig_category":"Jeugdherbergen",
    "sg:phone":"+31 20 589 8996",
    "sg:postcode":"1054 GA",
    "sg:province":"New York",
    "sg:website":"http://www.stayokay.com/amsterdamvondelpark",
    "wof:name":"Stayokay",
    "wof:placetype":"venue"
},
  "geometry": {"coordinates":[-74.114311,42.938435],"type":"Point"}
}