{
  "type": "Feature",
  "properties": {
    "addr:full":"Melkkelder 4 Drachten Friesland 9205 DA",
    "addr:housenumber":"4",
    "addr:postcode":"9205 da",
    "addr:street":"Melkkelder",
    "iso:country":"NL",
    "sg:address":"Melkkelder 4",
    "sg:city":"Drachten",
    "sg:orig_category":"Kappers",
    "sg:phone":"+31 512 540 531",
    "sg:postcode":"9205 DA",
    "sg:province":"Friesland",
    "wof:name":"Esther Kitsz Haarmode",
    "wof:placetype":"venue"
},
  "geometry": {"coordinates":[6.054046154,53.0940971375],"type":"Point"}
}