{
  "type": "Feature",
  "properties": {
    "addr:full":"Montgomerywg 2 Soesterberg Utrecht 3769 BJ",
    "addr:housenumber":"2",
    "addr:postcode":"3769 bj",
    "addr:street":"Montgomerywg",
    "iso:country":"NL",
    "sg:address":"Montgomerywg 2",
    "sg:city":"Soesterberg",
    "sg:orig_category":"Politie",
    "sg:phone":"+31 900 8844",
    "sg:postcode":"3769 BJ",
    "sg:province":"Utrecht",
    "wof:name":"Politie",
    "wof:placetype":"venue"
},
  "geometry": {"coordinates":[5.285344,52.121651],"type":"Point"}
}