{
  "type": "Feature",
  "properties": {
    "iso:country":"NL",
    "sg:address":"Steenbergsestr 12",
    "sg:city":"Bergen Op Zoom",
    "sg:orig_category":"Koffie- En Theehuizen",
    "sg:phone":"+31 164 238 650",
    "sg:postcode":"4611 TE",
    "sg:province":"North Brabant",
    "wof:name":"Feel Good",
    "wof:placetype":"venue"
},
  "geometry": {"coordinates":[4.284651,51.49614],"type":"Point"}
}