{
  "type": "Feature",
  "properties": {
    "addr:full":"Waterloostr 19-23 Rotterdam South Holland 3062 TD",
    "addr:housenumber":"19-23",
    "addr:postcode":"3062 td",
    "iso:country":"NL",
    "sg:address":"Waterloostr 19-23",
    "sg:city":"Rotterdam",
    "sg:orig_category":"Poeliers",
    "sg:phone":"+31 10 411 6521",
    "sg:postcode":"3062 TD",
    "sg:province":"South Holland",
    "wof:name":"Bas Bv, Van Der",
    "wof:placetype":"venue"
},
  "geometry": {"coordinates":[4.515097,51.924305],"type":"Point"}
}