{
  "type": "Feature",
  "properties": {
    "iso:country":"NL",
    "sg:address":"Koggenlaan 20",
    "sg:city":"Medemblik",
    "sg:orig_category":"Diverse Dierenfokkers",
    "sg:phone":"+31 227 541 562",
    "sg:postcode":"1671 KJ",
    "sg:province":"Noord-Holland",
    "wof:name":"A Van Eijk",
    "wof:placetype":"venue"
},
  "geometry": {"coordinates":[5.10744,52.766289],"type":"Point"}
}