{
  "type": "Feature",
  "properties": {
    "addr:full":"Hunneperwg 5 Deventer Overijssel 7418 EH",
    "addr:housenumber":"5",
    "addr:postcode":"7418 eh",
    "addr:street":"Hunneperwg",
    "iso:country":"NL",
    "sg:address":"Hunneperwg 5",
    "sg:city":"Deventer",
    "sg:orig_category":"Fietsen En Bromfietsen",
    "sg:phone":"+31 570 611 659",
    "sg:postcode":"7418 EH",
    "sg:province":"Overijssel",
    "wof:name":"Wk Scooter Centre",
    "wof:placetype":"venue"
},
  "geometry": {"coordinates":[6.197266,52.248768],"type":"Point"}
}