{
  "type": "Feature",
  "properties": {
    "addr:full":"Vd Veldeln 960 Alkmaar Noord-Holland 1816 PZ",
    "addr:housenumber":"960",
    "addr:postcode":"1816 pz",
    "iso:country":"NL",
    "sg:address":"Vd Veldeln 960",
    "sg:city":"Alkmaar",
    "sg:orig_category":"Adviesbureaus Bouwkunde",
    "sg:phone":"+31 72 511 2009",
    "sg:postcode":"1816 PZ",
    "sg:province":"Noord-Holland",
    "wof:name":"Bakker Bv",
    "wof:placetype":"venue"
},
  "geometry": {"coordinates":[4.746258,52.634361],"type":"Point"}
}