{
  "type": "Feature",
  "properties": {
    "iso:country":"NL",
    "sg:address":"St Monulphuswg 3",
    "sg:city":"Maastricht",
    "sg:orig_category":"Administratie- En Boekhoudkantoren",
    "sg:phone":"+31 43 321 3855",
    "sg:postcode":"6212 BG",
    "sg:province":"Limburg",
    "wof:name":"Lahaije",
    "wof:placetype":"venue"
},
  "geometry": {"coordinates":[5.691413,50.840714],"type":"Point"}
}