{
  "type": "Feature",
  "properties": {
    "addr:full":"Nieuwersluisstr 34 S Gravenhage South Holland 2546 RX",
    "addr:housenumber":"34",
    "addr:postcode":"2546 rx",
    "addr:street":"Nieuwersluisstr;S Gravenhage",
    "iso:country":"NL",
    "sg:address":"Nieuwersluisstr 34",
    "sg:city":"S Gravenhage",
    "sg:orig_category":"Scholen Voor Basisonderwijs",
    "sg:phone":"+31 70 329 2952",
    "sg:postcode":"2546 RX",
    "sg:province":"South Holland",
    "wof:name":"Ark Chr, De",
    "wof:placetype":"venue"
},
  "geometry": {"coordinates":[4.274271,52.058716],"type":"Point"}
}