{
  "type": "Feature",
  "properties": {
    "iso:country":"NL",
    "sg:address":"Kerkstraat 11",
    "sg:city":"Kerkrade",
    "sg:orig_category":"Fruit And Groenten Gh",
    "sg:phone":"+31 45 541 1028",
    "sg:postcode":"6466 HS",
    "sg:province":"Limburg",
    "wof:name":"Gebr Scherpenhuizen Bv",
    "wof:placetype":"venue"
},
  "geometry": {"coordinates":[6.025828,50.855701],"type":"Point"}
}