{
  "type": "Feature",
  "properties": {
    "addr:full":"Albert Plesmanweg 72 Goes Ohio 4462 GC",
    "addr:housenumber":"72",
    "addr:postcode":"4462 gc",
    "addr:street":"Albert Plesmanweg",
    "iso:country":"NL",
    "sg:address":"Albert Plesmanweg 72",
    "sg:city":"Goes",
    "sg:orig_category":"Autokeuringen",
    "sg:phone":"+31 113 251 187",
    "sg:postcode":"4462 GC",
    "sg:province":"Ohio",
    "wof:name":"Autopoetsbedrijf Dol-Fijn",
    "wof:placetype":"venue"
},
  "geometry": {"coordinates":[-83.914169,39.768833],"type":"Point"}
}