{
  "type": "Feature",
  "properties": {
    "iso:country":"NL",
    "sg:address":"Stationswg 60",
    "sg:city":"Drachten",
    "sg:orig_category":"Banken",
    "sg:phone":"+31 512 583 007",
    "sg:postcode":"9201 GP",
    "sg:province":"Provincie Friesland",
    "sg:website":"http://www.rabobank.nl",
    "wof:name":"Rabobank",
    "wof:placetype":"venue"
},
  "geometry": {"coordinates":[6.097255,53.111431],"type":"Point"}
}