{
  "type": "Feature",
  "properties": {
    "addr:full":"Korenmolen 7 Weert Limburg 6003 BJ",
    "addr:housenumber":"7",
    "addr:postcode":"6003 bj",
    "addr:street":"Korenmolen",
    "iso:country":"NL",
    "sg:address":"Korenmolen 7",
    "sg:city":"Weert",
    "sg:orig_category":"Beautyfarms And Sauna'S",
    "sg:phone":"+31 495 546 365",
    "sg:postcode":"6003 BJ",
    "sg:province":"Limburg",
    "wof:name":"Natural Beauty",
    "wof:placetype":"venue"
},
  "geometry": {"coordinates":[5.70333,51.262215],"type":"Point"}
}