{
  "type": "Feature",
  "properties": {
    "addr:full":"La Reineln 79 Bovenkarspel Noord-Holland 1611 ZB",
    "addr:housenumber":"79",
    "addr:postcode":"1611 zb",
    "iso:country":"NL",
    "sg:address":"La Reineln 79",
    "sg:city":"Bovenkarspel",
    "sg:orig_category":"Peuterspeelzalen",
    "sg:phone":"+31 228 514 492",
    "sg:postcode":"1611 ZB",
    "sg:province":"Noord-Holland",
    "wof:name":"Nijntje Pluis",
    "wof:placetype":"venue"
},
  "geometry": {"coordinates":[5.247698,52.69173],"type":"Point"}
}