{
  "type": "Feature",
  "properties": {
    "addr:full":"Kruisbergstraat 16 Brunssum Limburg 6444 BE",
    "addr:housenumber":"16",
    "addr:postcode":"6444",
    "addr:street":"Kruisbergstraat",
    "iso:country":"NL",
    "sg:address":"Kruisbergstraat 16",
    "sg:city":"Brunssum",
    "sg:orig_category":"Goederenvervoer Over De Weg",
    "sg:phone":"+31 45 525 2856",
    "sg:postcode":"6444 BE",
    "sg:province":"Limburg",
    "wof:name":"G.L. Schroyen",
    "wof:placetype":"venue"
},
  "geometry": {"coordinates":[5.966577,50.943245],"type":"Point"}
}