{
  "type": "Feature",
  "properties": {
    "addr:full":"Voorstraat 11 Noordwijk Zh South Holland 2201 HJ",
    "addr:housenumber":"11",
    "addr:postcode":"zh;2201 hj",
    "addr:street":"Voorstraat",
    "iso:country":"NL",
    "sg:address":"Voorstraat 11",
    "sg:city":"Noordwijk Zh",
    "sg:orig_category":"Kinderopvang Behalve Thuis",
    "sg:phone":"+31 71 364 7595",
    "sg:postcode":"2201 HJ",
    "sg:province":"South Holland",
    "wof:name":"Kinderdagverblijf Pinokkio",
    "wof:placetype":"venue"
},
  "geometry": {"coordinates":[4.450915,52.234646],"type":"Point"}
}