{
  "type": "Feature",
  "properties": {
    "addr:full":"Burgwal 5 Zaltbommel Gelderland 5301 GC",
    "addr:housenumber":"5",
    "addr:postcode":"5301 gc",
    "addr:street":"Burgwal;Gelderland",
    "iso:country":"NL",
    "sg:address":"Burgwal 5",
    "sg:city":"Zaltbommel",
    "sg:orig_category":"Autorijscholen",
    "sg:phone":"+31 418 514 921",
    "sg:postcode":"5301 GC",
    "sg:province":"Gelderland",
    "wof:name":"Heijden, H Van Der",
    "wof:placetype":"venue"
},
  "geometry": {"coordinates":[5.259226,51.813446],"type":"Point"}
}