{
  "type": "Feature",
  "properties": {
    "addr:full":"Kochstr 5 Hoogeveen Drenthe 7909 AJ",
    "addr:housenumber":"5",
    "addr:postcode":"7909 aj",
    "addr:street":"Kochstr",
    "iso:country":"NL",
    "sg:address":"Kochstr 5",
    "sg:city":"Hoogeveen",
    "sg:classifiers":[
        {
            "category":"Education",
            "subcategory":"School",
            "type":"Public Place"
        }
    ],
    "sg:phone":"+31 528 278 747",
    "sg:postcode":"7909 AJ",
    "sg:province":"Drenthe",
    "sg:tags":[
        "studiebegeleiding",
        "en",
        "school-"
    ],
    "wof:name":"Huiswerkhulp Hoogeveen",
    "wof:placetype":"venue"
},
  "geometry": {"coordinates":[6.462699,52.724724],"type":"Point"}
}