{
  "type": "Feature",
  "properties": {
    "addr:full":"V Vlissingenstr 5 Assen Provincie Drenthe 9403 BB",
    "addr:housenumber":"5",
    "addr:postcode":"9403 bb",
    "addr:street":"Vlissingenstr;Provincie Drenthe",
    "iso:country":"NL",
    "sg:address":"V Vlissingenstr 5",
    "sg:city":"Assen",
    "sg:orig_category":"Pijpleidingen",
    "sg:phone":"+31 592 343 743",
    "sg:postcode":"9403 BB",
    "sg:province":"Provincie Drenthe",
    "wof:name":"Hak Ned Bv Regio Noord, A",
    "wof:placetype":"venue"
},
  "geometry": {"coordinates":[6.559506,52.994041],"type":"Point"}
}