{
  "type": "Feature",
  "properties": {
    "addr:full":"Ramakerspad 3 Heerde Gelderland 8181 KP",
    "addr:housenumber":"3",
    "addr:postcode":"8181 kp",
    "addr:street":"Ramakerspad;Gelderland",
    "iso:country":"NL",
    "sg:address":"Ramakerspad 3",
    "sg:city":"Heerde",
    "sg:orig_category":"Scholen Voor Basisonderwijs",
    "sg:phone":"+31 578 692 926",
    "sg:postcode":"8181 KP",
    "sg:province":"Gelderland",
    "wof:name":"Emmaschool",
    "wof:placetype":"venue"
},
  "geometry": {"coordinates":[6.043542,52.384632],"type":"Point"}
}