{
  "type": "Feature",
  "properties": {
    "iso:country":"NL",
    "sg:address":"Ramakerspad 3",
    "sg:city":"Heerde",
    "sg:orig_category":"Scholen Voor Basisonderwijs",
    "sg:phone":"+31 578 692 926",
    "sg:postcode":"8181 KP",
    "sg:province":"Gelderland",
    "wof:name":"Emmaschool",
    "wof:placetype":"venue"
},
  "geometry": {"coordinates":[6.043542,52.384632],"type":"Point"}
}