{
  "type": "Feature",
  "properties": {
    "iso:country":"NL",
    "sg:address":"Kerkstr 3A",
    "sg:city":"Someren",
    "sg:orig_category":"Handwerkartikelen",
    "sg:phone":"+31 493 494 396",
    "sg:postcode":"5711 GS",
    "sg:province":"Noord-Brabant",
    "wof:name":"Regenboog, De",
    "wof:placetype":"venue"
},
  "geometry": {"coordinates":[5.711272,51.384651],"type":"Point"}
}