{
  "type": "Feature",
  "properties": {
    "addr:full":"Hilversumstr 332 Amsterdam Noord-Holland 1024 MB",
    "addr:housenumber":"332",
    "addr:postcode":"1024 mb",
    "iso:country":"NL",
    "sg:address":"Hilversumstr 332",
    "sg:city":"Amsterdam",
    "sg:orig_category":"Verenigingen En Stichtingen",
    "sg:phone":"+31 20 435 0700",
    "sg:postcode":"1024 MB",
    "sg:province":"Noord-Holland",
    "sg:website":"http://www.nivon.nl",
    "wof:name":"Nivon Amsterdam",
    "wof:placetype":"venue"
},
  "geometry": {"coordinates":[4.963191,52.391006],"type":"Point"}
}