{
  "type": "Feature",
  "properties": {
    "addr:full":"Bergmolen 13 Bleiswyk Zuid-Holland 2665 SL",
    "addr:housenumber":"13",
    "addr:postcode":"2665 sl",
    "addr:street":"Bergmolen",
    "iso:country":"NL",
    "sg:address":"Bergmolen 13",
    "sg:city":"Bleiswyk",
    "sg:orig_category":"Administratie- En Boekhoudkantoren",
    "sg:phone":"+31 10 529 0181",
    "sg:postcode":"2665 SL",
    "sg:province":"Zuid-Holland",
    "wof:name":"Adfidi",
    "wof:placetype":"venue"
},
  "geometry": {"coordinates":[4.546251,52.01416],"type":"Point"}
}