{
  "type": "Feature",
  "properties": {
    "addr:full":"Van Wijngaerdenstraat 33 'S Gravenhage Zuid-Holland 2596 TW",
    "addr:housenumber":"33",
    "addr:postcode":"2596 tw",
    "addr:street":"Van Wijngaerdenstraat;' S",
    "iso:country":"NL",
    "sg:address":"Van Wijngaerdenstraat 33",
    "sg:city":"'S Gravenhage",
    "sg:orig_category":"Marktonderzoekbureaus",
    "sg:phone":"+31 70 324 4720",
    "sg:postcode":"2596 TW",
    "sg:province":"Zuid-Holland",
    "wof:name":"Marketing En Managem. Consultancy Herkem",
    "wof:placetype":"venue"
},
  "geometry": {"coordinates":[4.322032,52.094505],"type":"Point"}
}