{
  "type": "Feature",
  "properties": {
    "iso:country":"NL",
    "sg:address":"Cotherwg 59",
    "sg:city":"Langbroek",
    "sg:orig_category":"Verenigingen En Stichtingen",
    "sg:phone":"+31 343 562 023",
    "sg:postcode":"3947 MR",
    "sg:province":"Utrecht",
    "wof:name":"Bartim\u00e9us Boerderij",
    "wof:placetype":"venue"
},
  "geometry": {"coordinates":[5.31618,52.004391],"type":"Point"}
}