{
  "type": "Feature",
  "properties": {
    "addr:full":"Meidoornhof 24 De Lier Zuid-Holland 2678 RE",
    "addr:housenumber":"24",
    "addr:postcode":"2678 re",
    "addr:street":"Meidoornhof",
    "iso:country":"NL",
    "sg:address":"Meidoornhof 24",
    "sg:city":"De Lier",
    "sg:orig_category":"Onderhoudswerken",
    "sg:phone":"+31 174 515 920",
    "sg:postcode":"2678 RE",
    "sg:province":"Zuid-Holland",
    "wof:name":"Stok, A A Van Der",
    "wof:placetype":"venue"
},
  "geometry": {"coordinates":[4.247694,51.977139],"type":"Point"}
}