{
  "type": "Feature",
  "properties": {
    "iso:country":"NL",
    "sg:address":"Gerberasingel 111",
    "sg:city":"Berkel En Rodenrijs",
    "sg:classifiers":[
        {
            "category":"Education",
            "subcategory":"Preschool",
            "type":"Public Place"
        }
    ],
    "sg:phone":"+31 10 511 5406",
    "sg:postcode":"2651 XZ",
    "sg:province":"South Holland",
    "sg:tags":[
        "kleuteronderwijs",
        "basis-"
    ],
    "wof:name":"Peuterspeelzaal Olleke Bolleke",
    "wof:placetype":"venue"
},
  "geometry": {"coordinates":[4.478555,51.992535],"type":"Point"}
}