{
  "type": "Feature",
  "properties": {
    "addr:full":"Bestevaerweg 21 Katwijk Zh Zuid-Holland 2225 PA",
    "addr:housenumber":"21",
    "addr:postcode":"2225 pa",
    "addr:street":"Bestevaerweg",
    "iso:country":"NL",
    "sg:address":"Bestevaerweg 21",
    "sg:city":"Katwijk Zh",
    "sg:orig_category":"Bloemen And Planten Gh",
    "sg:phone":"+31 71 401 2438",
    "sg:postcode":"2225 PA",
    "sg:province":"Zuid-Holland",
    "wof:name":"W. Verburg Bloemengroothandel",
    "wof:placetype":"venue"
},
  "geometry": {"coordinates":[4.405421,52.201462],"type":"Point"}
}