{
  "type": "Feature",
  "properties": {
    "addr:full":"Ginnekenweg 69 Breda Noord-Brabant 4818 JB",
    "addr:housenumber":"69",
    "addr:postcode":"4818 jb",
    "addr:street":"Ginnekenweg",
    "iso:country":"NL",
    "sg:address":"Ginnekenweg 69",
    "sg:city":"Breda",
    "sg:classifiers":[
        {
            "category":"Fast Food",
            "type":"Food & Drink"
        }
    ],
    "sg:phone":"+31 76 520 6561",
    "sg:postcode":"4818 JB",
    "sg:province":"Noord-Brabant",
    "sg:tags":[
        "afhaal",
        "restaurant"
    ],
    "wof:name":"Pizzeria-Shoarma Shato",
    "wof:placetype":"venue"
},
  "geometry": {"coordinates":[4.78123,51.577072],"type":"Point"}
}