{
  "type": "Feature",
  "properties": {
    "addr:full":"Galgkade 3 Vlaardingen South Holland 3133 KN",
    "addr:housenumber":"3",
    "addr:postcode":"3133 kn",
    "addr:street":"Galgkade",
    "iso:country":"NL",
    "sg:address":"Galgkade 3",
    "sg:city":"Vlaardingen",
    "sg:orig_category":"Boekhouders",
    "sg:phone":"+31 10 460 1493",
    "sg:postcode":"3133 KN",
    "sg:province":"South Holland",
    "wof:name":"Administratiekantoor Perspectief",
    "wof:placetype":"venue"
},
  "geometry": {"coordinates":[4.34676,51.902462],"type":"Point"}
}