{
  "type": "Feature",
  "properties": {
    "iso:country":"NL",
    "sg:address":"Molenwg 73",
    "sg:city":"Wydenes",
    "sg:orig_category":"Banken",
    "sg:phone":"+31 228 566 200",
    "sg:postcode":"1608 ED",
    "sg:province":"North Holland",
    "sg:website":"http://www.rabobank.nl",
    "wof:name":"Rabobank",
    "wof:placetype":"venue"
},
  "geometry": {"coordinates":[5.161965,52.642208],"type":"Point"}
}