{
  "type": "Feature",
  "properties": {
    "addr:full":"Glinderwg 1 Doornspijk Gelderland 8085 SN",
    "addr:housenumber":"1",
    "addr:postcode":"8085 sn",
    "addr:street":"Glinderwg;Gelderland",
    "iso:country":"NL",
    "sg:address":"Glinderwg 1",
    "sg:city":"Doornspijk",
    "sg:orig_category":"Land- En Tuinbouw - Loonbedrijven",
    "sg:phone":"+31 525 661 250",
    "sg:postcode":"8085 SN",
    "sg:province":"Gelderland",
    "wof:name":"Boerendans, W",
    "wof:placetype":"venue"
},
  "geometry": {"coordinates":[5.81365,52.414104],"type":"Point"}
}