{
  "type": "Feature",
  "properties": {
    "iso:country":"NL",
    "sg:address":"Stadserf 32",
    "sg:city":"Schiedam",
    "sg:orig_category":"Makelaars En Adviseurs Onroerende Goederen",
    "sg:phone":"+31 10 426 8135",
    "sg:postcode":"3112 DX",
    "sg:province":"South Holland",
    "sg:website":"http://www.dupont.nl",
    "wof:name":"Dupont Era Makelaars",
    "wof:placetype":"venue"
},
  "geometry": {"coordinates":[4.403817,51.917591],"type":"Point"}
}