{
  "type": "Feature",
  "properties": {
    "addr:full":"Lekkenburg 25 Gouda Zuid-Holland 2804 XC",
    "addr:housenumber":"25",
    "addr:postcode":"2804 xc",
    "addr:street":"Lekkenburg",
    "iso:country":"NL",
    "sg:address":"Lekkenburg 25",
    "sg:city":"Gouda",
    "sg:classifiers":[
        {
            "category":"Communications",
            "subcategory":"Television Station",
            "type":"Services"
        }
    ],
    "sg:phone":"+31 182 539 430",
    "sg:postcode":"2804 XC",
    "sg:province":"Zuid-Holland",
    "sg:tags":[
        "video",
        "audio",
        "verhuur"
    ],
    "wof:name":"Videoland",
    "wof:placetype":"venue"
},
  "geometry": {"coordinates":[4.705287,52.03204],"type":"Point"}
}