{
  "type": "Feature",
  "properties": {
    "addr:full":"Engelseweg 200 Helmond North Brabant 5705 AJ",
    "addr:housenumber":"200",
    "addr:postcode":"5705 aj",
    "addr:street":"Engelseweg",
    "iso:country":"NL",
    "sg:address":"Engelseweg 200",
    "sg:city":"Helmond",
    "sg:orig_category":"Meubelzaken, Woning- And Keukeninrichting",
    "sg:phone":"+31 492 523 791",
    "sg:postcode":"5705 AJ",
    "sg:province":"North Brabant",
    "wof:name":"Logisch Bed",
    "wof:placetype":"venue"
},
  "geometry": {"coordinates":[5.674558,51.473392],"type":"Point"}
}