{
  "type": "Feature",
  "properties": {
    "addr:full":"Postbus 180 Waddinxveen Zuid-Holland 2740 AD",
    "addr:housenumber":"180",
    "addr:postcode":"2740 ad",
    "addr:street":"Postbus",
    "iso:country":"NL",
    "sg:address":"Postbus 180",
    "sg:city":"Waddinxveen",
    "sg:orig_category":"Actuarissen",
    "sg:phone":"+31 182 640 195",
    "sg:postcode":"2740 AD",
    "sg:province":"Zuid-Holland",
    "sg:website":"http://www.hv-p.nl",
    "wof:name":"Hersmis Verdonkschot & Partners",
    "wof:placetype":"venue"
},
  "geometry": {"coordinates":[4.65507,52.044601],"type":"Point"}
}