{
  "type": "Feature",
  "properties": {
    "addr:full":"Pastoor Kuypersstraat 5 Waalwijk Noord-Brabant 5144 RH",
    "addr:housenumber":"5",
    "addr:postcode":"5144 rh",
    "addr:street":"Pastoor Kuypersstraat",
    "iso:country":"NL",
    "sg:address":"Pastoor Kuypersstraat 5",
    "sg:city":"Waalwijk",
    "sg:orig_category":"Metaalwerken",
    "sg:phone":"+31 416 341 866",
    "sg:postcode":"5144 RH",
    "sg:province":"Noord-Brabant",
    "wof:name":"Nijssen Systeembouw Waalwijk",
    "wof:placetype":"venue"
},
  "geometry": {"coordinates":[5.069844,51.681786],"type":"Point"}
}