{
  "type": "Feature",
  "properties": {
    "iso:country":"NL",
    "sg:address":"Pastoor Kuypersstraat 5",
    "sg:city":"Waalwijk",
    "sg:orig_category":"Metaalwerken",
    "sg:phone":"+31 416 341 866",
    "sg:postcode":"5144 RH",
    "sg:province":"Noord-Brabant",
    "wof:name":"Nijssen Systeembouw Waalwijk",
    "wof:placetype":"venue"
},
  "geometry": {"coordinates":[5.069844,51.681786],"type":"Point"}
}