{
  "type": "Feature",
  "properties": {
    "addr:full":"Van Imstenraedtlaan 4 Mheer Limburg 6261 NN",
    "addr:housenumber":"4",
    "addr:postcode":"6261 nn",
    "addr:street":"Van Imstenraedtlaan",
    "iso:country":"NL",
    "sg:address":"Van Imstenraedtlaan 4",
    "sg:city":"Mheer",
    "sg:orig_category":"Verzekeringen",
    "sg:phone":"+31 43 457 2216",
    "sg:postcode":"6261 NN",
    "sg:province":"Limburg",
    "wof:name":"Vof Jean Feij Assurantien",
    "wof:placetype":"venue"
},
  "geometry": {"coordinates":[5.793683,50.781773],"type":"Point"}
}