{
  "type": "Feature",
  "properties": {
    "addr:full":"Voogdenstraat 8 Weert Limburg 6004 HM",
    "addr:housenumber":"8",
    "addr:postcode":"6004 hm",
    "addr:street":"Voogdenstraat",
    "iso:country":"NL",
    "sg:address":"Voogdenstraat 8",
    "sg:city":"Weert",
    "sg:orig_category":"Vertaal- And Tolkenbureaus",
    "sg:phone":"+31 495 542 804",
    "sg:postcode":"6004 HM",
    "sg:province":"Limburg",
    "wof:name":"Vertaalburo L.R. Turlings",
    "wof:placetype":"venue"
},
  "geometry": {"coordinates":[5.716969,51.254189],"type":"Point"}
}