{
  "type": "Feature",
  "properties": {
    "addr:full":"Stationswg 33 Drachten Provincie Friesland 9201 GG",
    "addr:housenumber":"33",
    "addr:postcode":"9201 gg",
    "addr:street":"Stationswg;Provincie Friesland",
    "iso:country":"NL",
    "sg:address":"Stationswg 33",
    "sg:city":"Drachten",
    "sg:orig_category":"Makelaars En Adviseurs Onroerende Goederen",
    "sg:phone":"+31 512 512 325",
    "sg:postcode":"9201 GG",
    "sg:province":"Provincie Friesland",
    "wof:name":"Sluis, Van Der",
    "wof:placetype":"venue"
},
  "geometry": {"coordinates":[6.096863,53.110645],"type":"Point"}
}