{
  "type": "Feature",
  "properties": {
    "iso:country":"NL",
    "sg:address":"Patrimoniumlaan 54",
    "sg:city":"Veenendaal",
    "sg:classifiers":[
        {
            "category":"Bakery",
            "type":"Food & Drink"
        }
    ],
    "sg:phone":"+31 318 512 562",
    "sg:postcode":"3904 AE",
    "sg:province":"Utrecht",
    "sg:tags":[
        "brood",
        "banket"
    ],
    "wof:name":"Imminkhuizen",
    "wof:placetype":"venue"
},
  "geometry": {"coordinates":[5.545689,52.019352],"type":"Point"}
}