{
  "type": "Feature",
  "properties": {
    "addr:full":"Wijnesteijnstraat 17A Nieuwegein Utrecht 3431 EV",
    "addr:housenumber":"17a",
    "addr:postcode":"3431 ev",
    "addr:street":"Wijnesteijnstraat",
    "iso:country":"NL",
    "sg:address":"Wijnesteijnstraat 17A",
    "sg:city":"Nieuwegein",
    "sg:orig_category":"Diverse Opleidingen And Onderwijs",
    "sg:phone":"+31 30 604 2509",
    "sg:postcode":"3431 EV",
    "sg:province":"Utrecht",
    "wof:name":"Bijles En Huiswerkbegeleiding De Schans",
    "wof:placetype":"venue"
},
  "geometry": {"coordinates":[5.089755,52.03632],"type":"Point"}
}