{
  "type": "Feature",
  "properties": {
    "iso:country":"NL",
    "sg:address":"Driebergenstraat 1",
    "sg:city":"'S Gravenhage",
    "sg:orig_category":"Verzekeringen",
    "sg:phone":"+31 70 329 1004",
    "sg:postcode":"2546 BA",
    "sg:province":"Zuid-Holland",
    "wof:name":"Dorno Ass",
    "wof:placetype":"venue"
},
  "geometry": {"coordinates":[4.273359,52.061127],"type":"Point"}
}