{
  "type": "Feature",
  "properties": {
    "iso:country":"NL",
    "sg:address":"Bartokln 3",
    "sg:city":"Raamsdonksveer",
    "sg:orig_category":"Accountants - Administratie- Consulenten En -Kantoren",
    "sg:phone":"+31 162 513 551",
    "sg:postcode":"4941 WG",
    "sg:province":"Noord-Brabant",
    "wof:name":"Goad",
    "wof:placetype":"venue"
},
  "geometry": {"coordinates":[4.87459,51.695774],"type":"Point"}
}