{
  "type": "Feature",
  "properties": {
    "iso:country":"NL",
    "sg:address":"Prins Willem V Oranjestr 40",
    "sg:city":"Woudrichem",
    "sg:orig_category":"Glaszetten",
    "sg:phone":"+31 183 304 554",
    "sg:postcode":"4285 BS",
    "sg:province":"North Brabant",
    "wof:name":"Van Veen Schilderwerken",
    "wof:placetype":"venue"
},
  "geometry": {"coordinates":[4.996881,51.816185],"type":"Point"}
}