{
  "type": "Feature",
  "properties": {
    "addr:full":"Moeder Magdalenastraat 13 Ohe En Laak Limburg 6109 RC",
    "addr:housenumber":"13",
    "addr:postcode":"6109 rc",
    "addr:street":"Moeder Magdalenastraat;Ohe En Laak Limburg",
    "iso:country":"NL",
    "sg:address":"Moeder Magdalenastraat 13",
    "sg:city":"Ohe En Laak",
    "sg:orig_category":"Kampeerterreinen",
    "sg:phone":"+31 475 551 729",
    "sg:postcode":"6109 RC",
    "sg:province":"Limburg",
    "wof:name":"Minicamping De Maashoeve R.A.G. Beunen",
    "wof:placetype":"venue"
},
  "geometry": {"coordinates":[5.8179159164,51.1166763306],"type":"Point"}
}