{
  "type": "Feature",
  "properties": {
    "addr:full":"V L V Pabstln 178 De Meern Utrecht 3453 RC",
    "addr:housenumber":"178",
    "addr:postcode":"3453 rc",
    "addr:street":"V L V Pabstln",
    "iso:country":"NL",
    "sg:address":"V L V Pabstln 178",
    "sg:city":"De Meern",
    "sg:orig_category":"Bloemen En Planten - Decoratie",
    "sg:phone":"+31 6 53766038",
    "sg:postcode":"3453 RC",
    "sg:province":"Utrecht",
    "wof:name":"Bloem & Groen Workshops",
    "wof:placetype":"venue"
},
  "geometry": {"coordinates":[5.0138,52.081131],"type":"Point"}
}