{
  "type": "Feature",
  "properties": {
    "iso:country":"NL",
    "sg:address":"Jan Van Bloisstraat 29",
    "sg:city":"Schoonhoven",
    "sg:orig_category":"Gebouwenafwerking, Renovaties And Reiniging",
    "sg:phone":"+31 182 384 742",
    "sg:postcode":"2871 ST",
    "sg:province":"Zuid-Holland",
    "wof:name":"A. Roos Gevelsanering",
    "wof:placetype":"venue"
},
  "geometry": {"coordinates":[4.848461,51.943653],"type":"Point"}
}