{
  "type": "Feature",
  "properties": {
    "addr:full":"Haagweg 105 Rijswijk Zh Zuid-Holland 2281 AD",
    "addr:housenumber":"105",
    "addr:postcode":"zh;2281 ad",
    "addr:street":"Haagweg",
    "iso:country":"NL",
    "sg:address":"Haagweg 105",
    "sg:city":"Rijswijk Zh",
    "sg:classifiers":[
        {
            "category":"Professional",
            "subcategory":"Accounting & Tax Preparation",
            "type":"Services"
        }
    ],
    "sg:phone":"+31 70 398 8668",
    "sg:postcode":"2281 AD",
    "sg:province":"Zuid-Holland",
    "sg:tags":[
        "accountant"
    ],
    "wof:name":"Accountantskantoor Sies",
    "wof:placetype":"venue"
},
  "geometry": {"coordinates":[4.337823,52.057446],"type":"Point"}
}