{
  "type": "Feature",
  "properties": {
    "addr:full":"Walstr 7 Terneuzen Zeeland 4531 ED",
    "addr:housenumber":"7",
    "addr:postcode":"4531 ed",
    "addr:street":"Walstr",
    "iso:country":"NL",
    "sg:address":"Walstr 7",
    "sg:city":"Terneuzen",
    "sg:orig_category":"Wereldwinkels",
    "sg:phone":"+31 115 617 416",
    "sg:postcode":"4531 ED",
    "sg:province":"Zeeland",
    "wof:name":"Wereldwinkel",
    "wof:placetype":"venue"
},
  "geometry": {"coordinates":[3.8277449608,51.3387985229],"type":"Point"}
}