{
  "type": "Feature",
  "properties": {
    "addr:full":"Martinikerkhof 11 Groningen Groningen 9712 JG",
    "addr:housenumber":"11",
    "addr:postcode":"9712 jg",
    "addr:street":"Martinikerkhof",
    "iso:country":"NL",
    "sg:address":"Martinikerkhof 11",
    "sg:city":"Groningen",
    "sg:orig_category":"Verenigingen En Stichtingen",
    "sg:phone":"+31 50 318 1719",
    "sg:postcode":"9712 JG",
    "sg:province":"Groningen",
    "sg:website":"http://www.thuisfront.net",
    "wof:name":"Project Thuisfront",
    "wof:placetype":"venue"
},
  "geometry": {"coordinates":[6.569383,53.219292],"type":"Point"}
}