{
  "type": "Feature",
  "properties": {
    "addr:full":"Gasfabriekstr 1 Brummen Gelderland 6971 ZK",
    "addr:housenumber":"1",
    "addr:postcode":"6971",
    "addr:street":"Gasfabriekstr;Gelderland",
    "iso:country":"NL",
    "sg:address":"Gasfabriekstr 1",
    "sg:city":"Brummen",
    "sg:orig_category":"Verzekeringen - Verzekeringskantoren",
    "sg:phone":"+31 575 561 888",
    "sg:postcode":"6971 ZK",
    "sg:province":"Gelderland",
    "wof:name":"Kettelarij",
    "wof:placetype":"venue"
},
  "geometry": {"coordinates":[6.158399,52.089493],"type":"Point"}
}