{
  "type": "Feature",
  "properties": {
    "addr:full":"Winkelcentrum 40 Malden Gelderland 6581 BW",
    "addr:housenumber":"40",
    "addr:postcode":"6581 bw",
    "addr:street":"Winkelcentrum;Gelderland",
    "iso:country":"NL",
    "sg:address":"Winkelcentrum 40",
    "sg:city":"Malden",
    "sg:orig_category":"Bloemen And Planten",
    "sg:phone":"+31 24 358 3307",
    "sg:postcode":"6581 BW",
    "sg:province":"Gelderland",
    "wof:name":"De Kluijs Bloemen Malden",
    "wof:placetype":"venue"
},
  "geometry": {"coordinates":[5.85332,51.782398],"type":"Point"}
}