{
  "type": "Feature",
  "properties": {
    "addr:full":"Wolfraamwg 2 Wolvega Friesland 8471 XC",
    "addr:housenumber":"2",
    "addr:postcode":"8471 xc",
    "addr:street":"Wolfraamwg",
    "iso:country":"NL",
    "sg:address":"Wolfraamwg 2",
    "sg:city":"Wolvega",
    "sg:orig_category":"Verf En Lak - Fabrieken En Groothandel",
    "sg:phone":"+31 561 694 400",
    "sg:postcode":"8471 XC",
    "sg:province":"Friesland",
    "sg:website":"http://www.motipdupli.com",
    "wof:name":"Motip Dupli Bv",
    "wof:placetype":"venue"
},
  "geometry": {"coordinates":[5.987254,52.884033],"type":"Point"}
}