{
  "type": "Feature",
  "properties": {
    "addr:full":"Glipperwg 4 Heemstede Noord-Holland 2104 AK",
    "addr:housenumber":"4",
    "addr:postcode":"2104 ak",
    "addr:street":"Glipperwg",
    "iso:country":"NL",
    "sg:address":"Glipperwg 4",
    "sg:city":"Heemstede",
    "sg:classifiers":[
        {
            "category":"Sports & Exercise",
            "subcategory":"Stables",
            "type":"Entertainment"
        }
    ],
    "sg:phone":"+31 23 584 6690",
    "sg:postcode":"2104 AK",
    "sg:province":"Noord-Holland",
    "sg:tags":[
        "maneges"
    ],
    "wof:name":"Rusthof Manege",
    "wof:placetype":"venue"
},
  "geometry": {"coordinates":[4.604624,52.325756],"type":"Point"}
}