{
  "type": "Feature",
  "properties": {
    "iso:country":"NL",
    "sg:address":"R Visscherstr 30",
    "sg:city":"Leiden",
    "sg:orig_category":"Bestratingen",
    "sg:phone":"+31 71 532 0377",
    "sg:postcode":"2332 TW",
    "sg:province":"Zuid-Holland",
    "wof:name":"Vliet & De Graaf, V",
    "wof:placetype":"venue"
},
  "geometry": {"coordinates":[4.467439,52.161118],"type":"Point"}
}