{
  "type": "Feature",
  "properties": {
    "addr:full":"Beerseveld 17 Oirschot Noord-Brabant 5688 JD",
    "addr:housenumber":"17",
    "addr:postcode":"5688 jd",
    "addr:street":"Beerseveld",
    "iso:country":"NL",
    "sg:address":"Beerseveld 17",
    "sg:city":"Oirschot",
    "sg:orig_category":"Land- En Tuinbouw - Loonbedrijven",
    "sg:phone":"+31 499 573 860",
    "sg:postcode":"5688 JD",
    "sg:province":"Noord-Brabant",
    "wof:name":"Schapenservice",
    "wof:placetype":"venue"
},
  "geometry": {"coordinates":[5.267182,51.513195],"type":"Point"}
}