{
  "type": "Feature",
  "properties": {
    "addr:full":"Raadhuisstraat 79 Roosendaal Noord-Brabant 4701 PN",
    "addr:housenumber":"79",
    "addr:postcode":"4701 pn",
    "addr:street":"Raadhuisstraat",
    "iso:country":"NL",
    "sg:address":"Raadhuisstraat 79",
    "sg:city":"Roosendaal",
    "sg:orig_category":"Werving And Selectie Van Tijdelijk Personeel And Uitzendkantoren",
    "sg:phone":"+31 165 538 000",
    "sg:postcode":"4701 PN",
    "sg:province":"Noord-Brabant",
    "wof:name":"Job-Point Uitzendburo",
    "wof:placetype":"venue"
},
  "geometry": {"coordinates":[4.4602708817,51.531463623],"type":"Point"}
}