{
  "type": "Feature",
  "properties": {
    "addr:full":"Roeperssteeg 5 Harlingen Friesland 8861 AR",
    "addr:housenumber":"5",
    "addr:postcode":"8861",
    "addr:street":"Roeperssteeg",
    "iso:country":"NL",
    "sg:address":"Roeperssteeg 5",
    "sg:city":"Harlingen",
    "sg:orig_category":"Zalenexploitatie",
    "sg:phone":"+31 517 417 751",
    "sg:postcode":"8861 AR",
    "sg:province":"Friesland",
    "wof:name":"Frouwktje",
    "wof:placetype":"venue"
},
  "geometry": {"coordinates":[5.419718,53.175076],"type":"Point"}
}