{
  "type": "Feature",
  "properties": {
    "addr:full":"Populierenln 18A Bosch En Duin Utrecht 3735 LH",
    "addr:housenumber":"18a",
    "addr:postcode":"3735 lh",
    "addr:street":"Populierenln",
    "iso:country":"NL",
    "sg:address":"Populierenln 18A",
    "sg:city":"Bosch En Duin",
    "sg:classifiers":[
        {
            "category":"Professional",
            "subcategory":"Accounting & Tax Preparation",
            "type":"Services"
        }
    ],
    "sg:phone":"+31 30 692 1831",
    "sg:postcode":"3735 LH",
    "sg:province":"Utrecht",
    "sg:tags":[
        "accountant",
        "en",
        "-kantoren",
        "register-"
    ],
    "wof:name":"Seventer Accountantskantoor, Van",
    "wof:placetype":"venue"
},
  "geometry": {"coordinates":[5.242126,52.113514],"type":"Point"}
}