{
  "type": "Feature",
  "properties": {
    "addr:full":"Rhododendronln 7 De Lutte Overijssel 7587 NL",
    "addr:housenumber":"7",
    "addr:postcode":"7587 nl",
    "addr:street":"Rhododendronln",
    "iso:country":"NL",
    "sg:address":"Rhododendronln 7",
    "sg:city":"De Lutte",
    "sg:classifiers":[
        {
            "category":"Travel",
            "subcategory":"Hotels & Motels",
            "type":"Entertainment"
        }
    ],
    "sg:phone":"+31 541 585 555",
    "sg:postcode":"7587 NL",
    "sg:province":"Overijssel",
    "sg:website":"http://www.wilmersberg.nl",
    "wof:name":"Wilmersberg, De",
    "wof:placetype":"venue"
},
  "geometry": {"coordinates":[6.96163,52.309982],"type":"Point"}
}