{
  "type": "Feature",
  "properties": {
    "addr:full":"Dykstr 42 Appingedam Groningen 9901 AT",
    "addr:housenumber":"42",
    "addr:postcode":"9901",
    "addr:street":"Dykstr",
    "iso:country":"NL",
    "sg:address":"Dykstr 42",
    "sg:city":"Appingedam",
    "sg:orig_category":"Huishoudelijke Apparaten En Artikelen",
    "sg:phone":"+31 596 680 818",
    "sg:postcode":"9901 AT",
    "sg:province":"Groningen",
    "wof:name":"Marskramer Bv",
    "wof:placetype":"venue"
},
  "geometry": {"coordinates":[6.857888,53.322594],"type":"Point"}
}