{
  "type": "Feature",
  "properties": {
    "iso:country":"NL",
    "sg:address":"J S Ruppertstraat 30",
    "sg:city":"Amsterdam",
    "sg:orig_category":"Diverse Grafische Activiteiten",
    "sg:phone":"+31 20 610 9931",
    "sg:postcode":"1069 KL",
    "sg:province":"Noord-Holland",
    "wof:name":"Bzrk Productions",
    "wof:placetype":"venue"
},
  "geometry": {"coordinates":[4.796716,52.351616],"type":"Point"}
}