{
  "type": "Feature",
  "properties": {
    "addr:full":"Postbus 390 Delft South Holland 2600 AJ",
    "addr:housenumber":"390",
    "addr:postcode":"2600 aj",
    "addr:street":"Postbus",
    "iso:country":"NL",
    "sg:address":"Postbus 390",
    "sg:city":"Delft",
    "sg:orig_category":"Woningbouw- Verenigingen En -Stichtingen",
    "sg:phone":"+31 15 270 2900",
    "sg:postcode":"2600 AJ",
    "sg:province":"South Holland",
    "sg:website":"http://www.vidomes.nl",
    "wof:name":"Vidomes",
    "wof:placetype":"venue"
},
  "geometry": {"coordinates":[4.358689785,52.0115013123],"type":"Point"}
}