{
  "type": "Feature",
  "properties": {
    "iso:country":"NL",
    "sg:address":"Zandpad 56",
    "sg:city":"Middelharnis",
    "sg:orig_category":"Opticiens",
    "sg:phone":"+31 187 483 437",
    "sg:postcode":"3241 GX",
    "sg:province":"Zuid-Holland",
    "wof:name":"Brilcentrum Keuvelaar",
    "wof:placetype":"venue"
},
  "geometry": {"coordinates":[4.1587190628,51.7606887817],"type":"Point"}
}