{
  "type": "Feature",
  "properties": {
    "addr:full":"Minervaplein 22 Amsterdam North Holland 1077 TR",
    "addr:housenumber":"22",
    "addr:postcode":"1077 tr",
    "addr:street":"Minervaplein",
    "iso:country":"NL",
    "sg:address":"Minervaplein 22",
    "sg:city":"Amsterdam",
    "sg:orig_category":"Krantenuitgeverijen",
    "sg:phone":"+31 20 671 1142",
    "sg:postcode":"1077 TR",
    "sg:province":"North Holland",
    "wof:name":"Uitgeverij Disque '67 Bv",
    "wof:placetype":"venue"
},
  "geometry": {"coordinates":[4.871157,52.346783],"type":"Point"}
}