{
  "type": "Feature",
  "properties": {
    "addr:full":"Beekmansgoed 2 Nijkerk Gld Gelderland 3863 XM",
    "addr:housenumber":"2",
    "addr:postcode":"3863 xm",
    "addr:street":"Beekmansgoed;Gld Gelderland",
    "iso:country":"NL",
    "sg:address":"Beekmansgoed 2",
    "sg:city":"Nijkerk Gld",
    "sg:orig_category":"Diverse Grafische Activiteiten",
    "sg:phone":"+31 33 245 8648",
    "sg:postcode":"3863 XM",
    "sg:province":"Gelderland",
    "wof:name":"Dtp-Studio Van Der Hart",
    "wof:placetype":"venue"
},
  "geometry": {"coordinates":[5.464776,52.217472],"type":"Point"}
}