{
  "type": "Feature",
  "properties": {
    "iso:country":"NL",
    "sg:address":"V Diemenstr 410",
    "sg:city":"Amsterdam",
    "sg:orig_category":"Zalenverhuur",
    "sg:phone":"+31 20 620 1200",
    "sg:postcode":"1013 CR",
    "sg:province":"North Holland",
    "sg:website":"http://www.veem.nl",
    "wof:name":"Veem Caf?",
    "wof:placetype":"venue"
},
  "geometry": {"coordinates":[4.893195,52.373119],"type":"Point"}
}