{
  "type": "Feature",
  "properties": {
    "addr:full":"Wynbergsewg 11 Doetinchem Gelderland 7006 AH",
    "addr:housenumber":"11",
    "addr:postcode":"7006 ah",
    "addr:street":"Wynbergsewg;Gelderland",
    "iso:country":"NL",
    "sg:address":"Wynbergsewg 11",
    "sg:city":"Doetinchem",
    "sg:orig_category":"Veilingen En Venduhuizen",
    "sg:phone":"+31 314 342 118",
    "sg:postcode":"7006 AH",
    "sg:province":"Gelderland",
    "wof:name":"Veilinghuis Doetichem",
    "wof:placetype":"venue"
},
  "geometry": {"coordinates":[6.286413,51.961113],"type":"Point"}
}