{
  "type": "Feature",
  "properties": {
    "addr:full":"Longway 19 Terschelling West Friesland 8881 CM",
    "addr:housenumber":"19",
    "addr:postcode":"8881 cm",
    "addr:street":"Longway",
    "iso:country":"NL",
    "sg:address":"Longway 19",
    "sg:city":"Terschelling West",
    "sg:orig_category":"Politie",
    "sg:phone":"+31 900 8844",
    "sg:postcode":"8881 CM",
    "sg:province":"Friesland",
    "wof:name":"Politie",
    "wof:placetype":"venue"
},
  "geometry": {"coordinates":[5.215043,53.366512],"type":"Point"}
}