{
  "type": "Feature",
  "properties": {
    "addr:full":"Vaarselstraat 27 Someren North Brabant 5711 RB",
    "addr:housenumber":"27",
    "addr:postcode":"5711 rb",
    "addr:street":"Vaarselstraat",
    "iso:country":"NL",
    "sg:address":"Vaarselstraat 27",
    "sg:city":"Someren",
    "sg:orig_category":"Verhuur Catering-, Feest- En Evenementbenodigdheden",
    "sg:phone":"+31 493 490 527",
    "sg:postcode":"5711 RB",
    "sg:province":"North Brabant",
    "wof:name":"B & B Toiletwagenverhuur",
    "wof:placetype":"venue"
},
  "geometry": {"coordinates":[5.701078,51.386627],"type":"Point"}
}