{
  "type": "Feature",
  "properties": {
    "addr:full":"Koninginnegr 66 S Gravenhage South Holland 2514 AG",
    "addr:housenumber":"66",
    "addr:postcode":"2514",
    "addr:street":"Koninginnegr;S Gravenhage",
    "iso:country":"NL",
    "sg:address":"Koninginnegr 66",
    "sg:city":"S Gravenhage",
    "sg:orig_category":"Verenigingen En Stichtingen",
    "sg:phone":"+31 70 360 5847",
    "sg:postcode":"2514 AG",
    "sg:province":"South Holland",
    "wof:name":"Kvth",
    "wof:placetype":"venue"
},
  "geometry": {"coordinates":[4.30935,52.084148],"type":"Point"}
}