{
  "type": "Feature",
  "properties": {
    "addr:full":"Vughterstraat 205 'S Hertogenbosch Noord-Brabant 5211 GC",
    "addr:housenumber":"205 ' s",
    "addr:postcode":"5211 gc",
    "addr:street":"Vughterstraat",
    "iso:country":"NL",
    "sg:address":"Vughterstraat 205",
    "sg:city":"'S Hertogenbosch",
    "sg:orig_category":"Paramedische Behandelingen",
    "sg:phone":"+31 73 613 8722",
    "sg:postcode":"5211 GC",
    "sg:province":"Noord-Brabant",
    "wof:name":"Het Centrum Voor Podologie",
    "wof:placetype":"venue"
},
  "geometry": {"coordinates":[5.296587,51.685421],"type":"Point"}
}