{
  "type": "Feature",
  "properties": {
    "addr:full":"Apollolaan 86 Oude Pekela Groningen 9665 CT",
    "addr:housenumber":"86",
    "addr:postcode":"pekela;9665 ct",
    "addr:street":"Apollolaan",
    "iso:country":"NL",
    "sg:address":"Apollolaan 86",
    "sg:city":"Oude Pekela",
    "sg:orig_category":"Artiestenbureaus",
    "sg:phone":"+31 597 613 633",
    "sg:postcode":"9665 CT",
    "sg:province":"Groningen",
    "wof:name":"T Oostgronings Duo",
    "wof:placetype":"venue"
},
  "geometry": {"coordinates":[7.01069,53.109161],"type":"Point"}
}