{
  "type": "Feature",
  "properties": {
    "addr:full":"Vestdijk 9 Eindhoven North Brabant 5611 CA",
    "addr:housenumber":"9",
    "addr:postcode":"5611 ca",
    "addr:street":"Vestdijk",
    "iso:country":"NL",
    "sg:address":"Vestdijk 9",
    "sg:city":"Eindhoven",
    "sg:orig_category":"Werving And Selectie Van Tijdelijk Personeel And Uitzendkantoren",
    "sg:phone":"+31 40 235 8458",
    "sg:postcode":"5611 CA",
    "sg:province":"North Brabant",
    "wof:name":"Quality Select",
    "wof:placetype":"venue"
},
  "geometry": {"coordinates":[5.4803519249,51.4404411316],"type":"Point"}
}