{
  "type": "Feature",
  "properties": {
    "addr:full":"Stephensonwg 20 Coevorden Drenthe 7741 KW",
    "addr:housenumber":"20",
    "addr:postcode":"7741 kw",
    "addr:street":"Stephensonwg",
    "iso:country":"NL",
    "sg:address":"Stephensonwg 20",
    "sg:city":"Coevorden",
    "sg:orig_category":"Scheepsbouw En -Reparatie",
    "sg:phone":"+31 524 514 483",
    "sg:postcode":"7741 KW",
    "sg:province":"Drenthe",
    "wof:name":"Vlijt, De",
    "wof:placetype":"venue"
},
  "geometry": {"coordinates":[6.731846,52.652061],"type":"Point"}
}