{
  "type": "Feature",
  "properties": {
    "iso:country":"NL",
    "sg:address":"Spaarne 8",
    "sg:city":"Haarlem",
    "sg:classifiers":[
        {
            "category":"Travel",
            "subcategory":"Hotels & Motels",
            "type":"Entertainment"
        }
    ],
    "sg:phone":"+31 23 551 1544",
    "sg:postcode":"2011 CH",
    "sg:province":"Noord-Holland",
    "wof:name":"Spaarne 8",
    "wof:placetype":"venue"
},
  "geometry": {"coordinates":[4.640695,52.380421],"type":"Point"}
}