{
  "type": "Feature",
  "properties": {
    "addr:full":"Exportweg 6 Roden Drenthe 9301 ZV",
    "addr:housenumber":"6",
    "addr:postcode":"9301 zv",
    "addr:street":"Exportweg",
    "iso:country":"NL",
    "sg:address":"Exportweg 6",
    "sg:city":"Roden",
    "sg:orig_category":"Airconditioning And Ventilatie",
    "sg:phone":"+31 50 501 8142",
    "sg:postcode":"9301 ZV",
    "sg:province":"Drenthe",
    "wof:name":"Al-Ko Luchttechniek Bv",
    "wof:placetype":"venue"
},
  "geometry": {"coordinates":[6.451194,53.146767],"type":"Point"}
}