{
  "type": "Feature",
  "properties": {
    "addr:full":"Corverlaan 8 Bussum Noord-Holland 1405 AW",
    "addr:housenumber":"8",
    "addr:postcode":"1405 aw",
    "addr:street":"Corverlaan",
    "iso:country":"NL",
    "sg:address":"Corverlaan 8",
    "sg:city":"Bussum",
    "sg:orig_category":"Werving And Selectie Van Vast Personeel",
    "sg:phone":"+31 35 694 2233",
    "sg:postcode":"1405 AW",
    "sg:province":"Noord-Holland",
    "wof:name":"Executive Careers",
    "wof:placetype":"venue"
},
  "geometry": {"coordinates":[5.1513338089,52.2789154053],"type":"Point"}
}