{
  "type": "Feature",
  "properties": {
    "iso:country":"NL",
    "sg:address":"Raadhuisstr 30-30A",
    "sg:city":"Rucphen",
    "sg:orig_category":"Haarden En Kachels",
    "sg:phone":"+31 165 342 750",
    "sg:postcode":"4715 CD",
    "sg:province":"Noord-Brabant",
    "wof:name":"Kachelshop",
    "wof:placetype":"venue"
},
  "geometry": {"coordinates":[4.558815,51.532639],"type":"Point"}
}