{
  "type": "Feature",
  "properties": {
    "addr:full":"Voskuilerdk 2 Woudenberg Utrecht 3931 MZ",
    "addr:housenumber":"2",
    "addr:postcode":"3931 mz",
    "addr:street":"Voskuilerdk",
    "iso:country":"NL",
    "sg:address":"Voskuilerdk 2",
    "sg:city":"Woudenberg",
    "sg:orig_category":"Loonbedrijven",
    "sg:phone":"+31 33 277 1276",
    "sg:postcode":"3931 MZ",
    "sg:province":"Utrecht",
    "wof:name":"Maaten Bv, G Ter",
    "wof:placetype":"venue"
},
  "geometry": {"coordinates":[5.442952,52.105148],"type":"Point"}
}