{
  "type": "Feature",
  "properties": {
    "addr:full":"Aalbessenstraat 20 Almere Flevoland 1326 HT",
    "addr:housenumber":"20",
    "addr:postcode":"1326 ht",
    "addr:street":"Aalbessenstraat;Flevoland",
    "iso:country":"NL",
    "sg:address":"Aalbessenstraat 20",
    "sg:city":"Almere",
    "sg:orig_category":"Metaalwerken",
    "sg:phone":"+31 36 545 1820",
    "sg:postcode":"1326 HT",
    "sg:province":"Flevoland",
    "wof:name":"S.J.H. Interieur Inrichters",
    "wof:placetype":"venue"
},
  "geometry": {"coordinates":[5.25243,52.369972],"type":"Point"}
}