{
  "type": "Feature",
  "properties": {
    "addr:full":"Dorastr 55 Hengelo Overijssel 7555 HT",
    "addr:housenumber":"55",
    "addr:postcode":"7555 ht",
    "addr:street":"Dorastr",
    "iso:country":"NL",
    "sg:address":"Dorastr 55",
    "sg:city":"Hengelo",
    "sg:orig_category":"Verloskundigen",
    "sg:phone":"+31 74 242 1910",
    "sg:postcode":"7555 HT",
    "sg:province":"Overijssel",
    "wof:name":"Dora",
    "wof:placetype":"venue"
},
  "geometry": {"coordinates":[6.774209,52.256268],"type":"Point"}
}