{
  "type": "Feature",
  "properties": {
    "iso:country":"NL",
    "sg:address":"Kleine N 44-46",
    "sg:city":"Hoorn Nh",
    "sg:orig_category":"Fietsen En Bromfietsen",
    "sg:phone":"+31 229 272 007",
    "sg:postcode":"1621 JH",
    "sg:province":"North Holland",
    "wof:name":"All American Bike",
    "wof:placetype":"venue"
},
  "geometry": {"coordinates":[5.052971,52.643639],"type":"Point"}
}