{
  "type": "Feature",
  "properties": {
    "iso:country":"NL",
    "sg:address":"Laan Van Westmolen 53",
    "sg:city":"Mijnsheerenland",
    "sg:orig_category":"Autokeuringen",
    "sg:phone":"+31 186 601 315",
    "sg:postcode":"3271 BJ",
    "sg:province":"Zuid-Holland",
    "wof:name":"W.M. Landman",
    "wof:placetype":"venue"
},
  "geometry": {"coordinates":[4.480221,51.795746],"type":"Point"}
}