{
  "type": "Feature",
  "properties": {
    "addr:full":"Mark 25 Huizen Noord-Holland 1273 PA",
    "addr:housenumber":"25",
    "addr:postcode":"1273 pa",
    "addr:street":"Mark",
    "iso:country":"NL",
    "sg:address":"Mark 25",
    "sg:city":"Huizen",
    "sg:orig_category":"Verenigingen En Stichtingen",
    "sg:phone":"+31 35 525 7028",
    "sg:postcode":"1273 PA",
    "sg:province":"Noord-Holland",
    "wof:name":"Reumapati\u00ebntenver Hilversum",
    "wof:placetype":"venue"
},
  "geometry": {"coordinates":[5.259697,52.303715],"type":"Point"}
}