{
  "type": "Feature",
  "properties": {
    "addr:full":"Gen Diemontstr 2 Eindhoven Noord-Brabant 5623 HT",
    "addr:housenumber":"2",
    "addr:postcode":"5623 ht",
    "iso:country":"NL",
    "sg:address":"Gen Diemontstr 2",
    "sg:city":"Eindhoven",
    "sg:orig_category":"Horeca-Inrichtingen En -Uitrustingen",
    "sg:phone":"+31 40 246 2846",
    "sg:postcode":"5623 HT",
    "sg:province":"Noord-Brabant",
    "wof:name":"Luchtreiniging, Nederland",
    "wof:placetype":"venue"
},
  "geometry": {"coordinates":[5.484963,51.463242],"type":"Point"}
}