{
  "type": "Feature",
  "properties": {
    "iso:country":"NL",
    "sg:address":"Moleneind 2",
    "sg:city":"Oud Gastel",
    "sg:orig_category":"Verzekeringen - Verzekeringskantoren",
    "sg:phone":"+31 165 519 610",
    "sg:postcode":"4751 GP",
    "sg:province":"Noord-Brabant",
    "wof:name":"Brabant Adviesgroep",
    "wof:placetype":"venue"
},
  "geometry": {"coordinates":[4.460218,51.582344],"type":"Point"}
}