{
  "type": "Feature",
  "properties": {
    "iso:country":"NL",
    "sg:address":"Corweide 15",
    "sg:city":"Heeze",
    "sg:orig_category":"Schoonheidssalons",
    "sg:phone":"+31 40 226 0122",
    "sg:postcode":"5591 LR",
    "sg:province":"Noord-Brabant",
    "wof:name":"Art Of Beauty",
    "wof:placetype":"venue"
},
  "geometry": {"coordinates":[5.569451,51.382214],"type":"Point"}
}