{
  "type": "Feature",
  "properties": {
    "iso:country":"NL",
    "sg:address":"Julianalaan 123",
    "sg:city":"Ermelo",
    "sg:orig_category":"Kampeerterreinen",
    "sg:phone":"+31 341 562 000",
    "sg:postcode":"3853 KN",
    "sg:province":"Gelderland",
    "wof:name":"T Zomernest",
    "wof:placetype":"venue"
},
  "geometry": {"coordinates":[5.608689785,52.3153839111],"type":"Point"}
}