{
  "type": "Feature",
  "properties": {
    "addr:full":"Rooiln 2 Valthermond Drenthe 7876 GR",
    "addr:housenumber":"2",
    "addr:postcode":"7876",
    "addr:street":"Rooiln",
    "iso:country":"NL",
    "sg:address":"Rooiln 2",
    "sg:city":"Valthermond",
    "sg:orig_category":"Montagebedrijven",
    "sg:phone":"+31 599 661 043",
    "sg:postcode":"7876 GR",
    "sg:province":"Drenthe",
    "wof:name":"Cate",
    "wof:placetype":"venue"
},
  "geometry": {"coordinates":[6.948975,52.874722],"type":"Point"}
}