{
  "type": "Feature",
  "properties": {
    "addr:full":"F De Boerln 145 Amsterdam Noord-Holland 1019 KV",
    "addr:housenumber":"145",
    "addr:postcode":"1019 kv",
    "addr:street":"F",
    "iso:country":"NL",
    "sg:address":"F De Boerln 145",
    "sg:city":"Amsterdam",
    "sg:orig_category":"Beeldende Kunstenaars",
    "sg:phone":"+31 20 611 3755",
    "sg:postcode":"1019 KV",
    "sg:province":"Noord-Holland",
    "wof:name":"Uzoni, Studio",
    "wof:placetype":"venue"
},
  "geometry": {"coordinates":[4.893195,52.373119],"type":"Point"}
}