{
  "type": "Feature",
  "properties": {
    "addr:full":"Reiger 11-12 Hoorn Nh North Holland 1628 BA",
    "addr:housenumber":"11-12",
    "addr:postcode":"1628 ba",
    "addr:street":"Reiger;Nh North",
    "iso:country":"NL",
    "sg:address":"Reiger 11-12",
    "sg:city":"Hoorn Nh",
    "sg:orig_category":"Kappers",
    "sg:phone":"+31 229 241 053",
    "sg:postcode":"1628 BA",
    "sg:province":"North Holland",
    "wof:name":"Jorrit Haarverzorging",
    "wof:placetype":"venue"
},
  "geometry": {"coordinates":[5.0799927711,52.6543617249],"type":"Point"}
}