{
  "type": "Feature",
  "properties": {
    "addr:full":"Vijf Meilaan 272 Leiden Zuid-Holland 2324 WR",
    "addr:housenumber":"272",
    "addr:postcode":"2324 wr",
    "addr:street":"Vijf Meilaan",
    "iso:country":"NL",
    "sg:address":"Vijf Meilaan 272",
    "sg:city":"Leiden",
    "sg:orig_category":"Wegen And Sportterreinen",
    "sg:phone":"+31 71 532 0761",
    "sg:postcode":"2324 WR",
    "sg:province":"Zuid-Holland",
    "wof:name":"M. De Nijs Bestratingen",
    "wof:placetype":"venue"
},
  "geometry": {"coordinates":[4.4732718468,52.1470565796],"type":"Point"}
}