{
  "type": "Feature",
  "properties": {
    "addr:full":"Baronielaan 1 Breda Noord-Brabant 4818 PA",
    "addr:housenumber":"1",
    "addr:postcode":"4818 pa",
    "addr:street":"Baronielaan",
    "iso:country":"NL",
    "sg:address":"Baronielaan 1",
    "sg:city":"Breda",
    "sg:orig_category":"Meubels And Huishoudapparatuur Gh",
    "sg:phone":"+31 76 521 7716",
    "sg:postcode":"4818 PA",
    "sg:province":"Noord-Brabant",
    "wof:name":"Princess Household Appliances Bv",
    "wof:placetype":"venue"
},
  "geometry": {"coordinates":[4.778509,51.578648],"type":"Point"}
}