{
  "type": "Feature",
  "properties": {
    "addr:full":"Rigtersbleek-Aalten 4 Enschede Overijssel 7521 RB",
    "addr:housenumber":"4",
    "addr:postcode":"7521 rb",
    "addr:street":"Rigtersbleek-Aalten",
    "iso:country":"NL",
    "sg:address":"Rigtersbleek-Aalten 4",
    "sg:city":"Enschede",
    "sg:orig_category":"Bedrijfsinventaris Gh",
    "sg:phone":"+31 53 430 9773",
    "sg:postcode":"7521 RB",
    "sg:province":"Overijssel",
    "wof:name":"Elkaderm Nederland Bv",
    "wof:placetype":"venue"
},
  "geometry": {"coordinates":[6.869243,52.223564],"type":"Point"}
}