{
  "type": "Feature",
  "properties": {
    "iso:country":"NL",
    "sg:address":"Veemarktstr 56",
    "sg:city":"Breda",
    "sg:orig_category":"Kinderkleding",
    "sg:phone":"+31 76 521 6087",
    "sg:postcode":"4811 ZJ",
    "sg:province":"Noord-Brabant",
    "wof:name":"Hann\u00e8l Youngconcept",
    "wof:placetype":"venue"
},
  "geometry": {"coordinates":[4.779527,51.58876],"type":"Point"}
}