{
  "type": "Feature",
  "properties": {
    "addr:full":"Oude Sngl 14D Leiden Zuid-Holland 2312 RA",
    "addr:housenumber":"14d",
    "addr:postcode":"2312 ra",
    "addr:street":"Oude Sngl",
    "iso:country":"NL",
    "sg:address":"Oude Sngl 14D",
    "sg:city":"Leiden",
    "sg:orig_category":"Vertalers",
    "sg:phone":"+31 71 513 3365",
    "sg:postcode":"2312 RA",
    "sg:province":"Zuid-Holland",
    "wof:name":"Boekel, Drs M Van",
    "wof:placetype":"venue"
},
  "geometry": {"coordinates":[4.492032,52.159698],"type":"Point"}
}