{
  "type": "Feature",
  "properties": {
    "addr:full":"Zoom 1524 Lelystad Flevoland 8225 KJ",
    "addr:postcode":"1524;8225 kj",
    "addr:street":"Zoom;Flevoland",
    "iso:country":"NL",
    "sg:address":"Zoom 1524",
    "sg:city":"Lelystad",
    "sg:orig_category":"Schoonheidsinstituten",
    "sg:phone":"+31 320 231 482",
    "sg:postcode":"8225 KJ",
    "sg:province":"Flevoland",
    "wof:name":"Berndsen, Ellie",
    "wof:placetype":"venue"
},
  "geometry": {"coordinates":[5.508441,52.500744],"type":"Point"}
}