{
  "type": "Feature",
  "properties": {
    "addr:full":"Dorpsstr 45 Bleiswyk Zuid-Holland 2665 BG",
    "addr:housenumber":"45",
    "addr:postcode":"2665",
    "addr:street":"Dorpsstr",
    "iso:country":"NL",
    "sg:address":"Dorpsstr 45",
    "sg:city":"Bleiswyk",
    "sg:orig_category":"Bloemen En Planten",
    "sg:phone":"+31 10 521 2873",
    "sg:postcode":"2665 BG",
    "sg:province":"Zuid-Holland",
    "wof:name":"Bloemenvreugd",
    "wof:placetype":"venue"
},
  "geometry": {"coordinates":[23.0145,42.17815],"type":"Point"}
}