{
  "type": "Feature",
  "properties": {
    "addr:full":"Meester Boutenstraat 19 Ooij Gelderland 6576 DG",
    "addr:housenumber":"19",
    "addr:postcode":"6576 dg",
    "addr:street":"Meester Boutenstraat;Gelderland",
    "iso:country":"NL",
    "sg:address":"Meester Boutenstraat 19",
    "sg:city":"Ooij",
    "sg:orig_category":"Paramedische Behandelingen",
    "sg:phone":"+31 24 663 2674",
    "sg:postcode":"6576 DG",
    "sg:province":"Gelderland",
    "wof:name":"A P M Hogenhuis Logopediste",
    "wof:placetype":"venue"
},
  "geometry": {"coordinates":[5.940524,51.851856],"type":"Point"}
}