{
  "type": "Feature",
  "properties": {
    "iso:country":"NL",
    "sg:address":"Zuid Willemsvaart 135",
    "sg:city":"'S Hertogenbosch",
    "sg:orig_category":"Loodgieterswerk, Verwarming And Sanitaire Installaties",
    "sg:phone":"+31 73 613 1050",
    "sg:postcode":"5211 SE",
    "sg:province":"Noord-Brabant",
    "wof:name":"Firma Sanitair Installateurs M.S.I.",
    "wof:placetype":"venue"
},
  "geometry": {"coordinates":[5.309159,51.690769],"type":"Point"}
}