{
  "type": "Feature",
  "properties": {
    "addr:full":"Hilteweg 5 Winterswijk Meddo Gelderland 7104 BC",
    "addr:housenumber":"5",
    "addr:postcode":"7104 bc",
    "addr:street":"Hilteweg",
    "iso:country":"NL",
    "sg:address":"Hilteweg 5",
    "sg:city":"Winterswijk Meddo",
    "sg:orig_category":"Meubelzaken, Woning- And Keukeninrichting",
    "sg:phone":"+31 543 569 213",
    "sg:postcode":"7104 BC",
    "sg:province":"Gelderland",
    "wof:name":"Woninginr. En Stoffeerdijf Lantink Meddo",
    "wof:placetype":"venue"
},
  "geometry": {"coordinates":[6.705387,52.012478],"type":"Point"}
}