{
  "type": "Feature",
  "properties": {
    "iso:country":"NL",
    "sg:address":"Zwaaikom 37",
    "sg:city":"Amersfoort",
    "sg:orig_category":"Ventilatiesystemen",
    "sg:phone":"+31 33 465 2626",
    "sg:postcode":"3812 PS",
    "sg:province":"Utrecht",
    "wof:name":"Bouda Ventilatie Systemen Bv",
    "wof:placetype":"venue"
},
  "geometry": {"coordinates":[5.3705148697,52.1669120789],"type":"Point"}
}