{
  "type": "Feature",
  "properties": {
    "iso:country":"NL",
    "sg:address":"Vriesestr 96",
    "sg:city":"Dordrecht",
    "sg:orig_category":"Opticiens",
    "sg:phone":"+31 78 613 8415",
    "sg:postcode":"3311 NR",
    "sg:province":"Zuid-Holland",
    "sg:website":"http://www.vanderham-optiek.com",
    "wof:name":"Ham Optiek, Van Der",
    "wof:placetype":"venue"
},
  "geometry": {"coordinates":[4.6687178612,51.8132400513],"type":"Point"}
}