{
  "type": "Feature",
  "properties": {
    "addr:full":"Linie 385 Apeldoorn Gelderland 7325 DT",
    "addr:housenumber":"385",
    "addr:postcode":"7325 dt",
    "addr:street":"Linie;Gelderland",
    "iso:country":"NL",
    "sg:address":"Linie 385",
    "sg:city":"Apeldoorn",
    "sg:orig_category":"Huishoudelijke Apparaten En Artikelen",
    "sg:phone":"+31 55 519 0711",
    "sg:postcode":"7325 DT",
    "sg:province":"Gelderland",
    "wof:name":"Blokker Bv",
    "wof:placetype":"venue"
},
  "geometry": {"coordinates":[6.002902,52.216236],"type":"Point"}
}