{
  "type": "Feature",
  "properties": {
    "addr:full":"Berenbroek 6 Helmond North Brabant 5707 DB",
    "addr:housenumber":"6",
    "addr:postcode":"5707 db",
    "addr:street":"Berenbroek",
    "iso:country":"NL",
    "sg:address":"Berenbroek 6",
    "sg:city":"Helmond",
    "sg:orig_category":"Makelaars En Adviseurs Onroerende Goederen",
    "sg:phone":"+31 492 363 028",
    "sg:postcode":"5707 DB",
    "sg:province":"North Brabant",
    "wof:name":"B&S",
    "wof:placetype":"venue"
},
  "geometry": {"coordinates":[5.608721,51.4674],"type":"Point"}
}