{
  "type": "Feature",
  "properties": {
    "addr:full":"Mient 201D S Gravenhage South Holland 2564 KL",
    "addr:housenumber":"201d",
    "addr:postcode":"2564 kl",
    "addr:street":"Mient;S Gravenhage",
    "iso:country":"NL",
    "sg:address":"Mient 201D",
    "sg:city":"S Gravenhage",
    "sg:orig_category":"Bloemen En Planten",
    "sg:phone":"+31 70 386 6747",
    "sg:postcode":"2564 KL",
    "sg:province":"South Holland",
    "wof:name":"Perachja",
    "wof:placetype":"venue"
},
  "geometry": {"coordinates":[4.25946,52.06805],"type":"Point"}
}