{
  "type": "Feature",
  "properties": {
    "addr:full":"Brahmslaan 15 Nijkerk Gld Gelderland 3862 TA",
    "addr:housenumber":"15",
    "addr:postcode":"3862 ta",
    "addr:street":"Brahmslaan;Gld Gelderland",
    "iso:country":"NL",
    "sg:address":"Brahmslaan 15",
    "sg:city":"Nijkerk Gld",
    "sg:orig_category":"Koeriersdiensten",
    "sg:phone":"+31 33 247 0784",
    "sg:postcode":"3862 TA",
    "sg:province":"Gelderland",
    "wof:name":"Thema Vervoer",
    "wof:placetype":"venue"
},
  "geometry": {"coordinates":[5.483762,52.214222],"type":"Point"}
}