{
  "type": "Feature",
  "properties": {
    "addr:full":"Heemraadsngl 13 Ter Aar Zuid-Holland 2461 SP",
    "addr:housenumber":"13",
    "addr:postcode":"aar;2461 sp",
    "addr:street":"Heemraadsngl;Ter",
    "iso:country":"NL",
    "sg:address":"Heemraadsngl 13",
    "sg:city":"Ter Aar",
    "sg:orig_category":"Adviesbureaus Bouwkunde",
    "sg:phone":"+31 172 603 331",
    "sg:postcode":"2461 SP",
    "sg:province":"Zuid-Holland",
    "wof:name":"Egberts, H J",
    "wof:placetype":"venue"
},
  "geometry": {"coordinates":[4.709815,52.19268],"type":"Point"}
}