{
  "type": "Feature",
  "properties": {
    "addr:full":"Kruiskade 72 Rotterdam Zuid-Holland 3012 EH",
    "addr:housenumber":"72",
    "addr:postcode":"3012 eh",
    "addr:street":"Kruiskade",
    "iso:country":"NL",
    "sg:address":"Kruiskade 72",
    "sg:city":"Rotterdam",
    "sg:classifiers":[
        {
            "category":"Fast Food",
            "type":"Food & Drink"
        }
    ],
    "sg:phone":"+31 10 411 7244",
    "sg:postcode":"3012 EH",
    "sg:province":"Zuid-Holland",
    "sg:tags":[
        "afhaal",
        "restaurant"
    ],
    "wof:name":"Raden Mas City Ii Cv",
    "wof:placetype":"venue"
},
  "geometry": {"coordinates":[4.475099,51.922264],"type":"Point"}
}