{
  "type": "Feature",
  "properties": {
    "iso:country":"NL",
    "sg:address":"Vestdk 2",
    "sg:city":"Eindhoven",
    "sg:orig_category":"Arbo- En Bedrijfsgezondheids- Diensten",
    "sg:phone":"+31 40 296 8300",
    "sg:postcode":"5611 CC",
    "sg:province":"Noord-Brabant",
    "wof:name":"Arbo Management Groep",
    "wof:placetype":"venue"
},
  "geometry": {"coordinates":[5.4791,51.440762],"type":"Point"}
}