{
  "type": "Feature",
  "properties": {
    "iso:country":"NL",
    "sg:address":"Aardamsew 49",
    "sg:city":"Ter Aar",
    "sg:orig_category":"Artsen - Huisartsen",
    "sg:phone":"+31 172 603 333",
    "sg:postcode":"2461 CA",
    "sg:province":"South Holland",
    "wof:name":"Sprang, H M Van",
    "wof:placetype":"venue"
},
  "geometry": {"coordinates":[4.705567,52.167698],"type":"Point"}
}