{
  "type": "Feature",
  "properties": {
    "addr:full":"H Droststr 44 Olst NL.08 8121 BJ",
    "addr:housenumber":"44;nl.08",
    "addr:postcode":"8121 bj",
    "iso:country":"NL",
    "sg:address":"H Droststr 44",
    "sg:city":"Olst",
    "sg:orig_category":"Mode-Artikelen Dames En Heren",
    "sg:phone":"+31 570 563 900",
    "sg:postcode":"8121 BJ",
    "sg:province":"NL.08",
    "wof:name":"Santenkraam, De",
    "wof:placetype":"venue"
},
  "geometry": {"coordinates":[6.109007,52.338341],"type":"Point"}
}