{
  "type": "Feature",
  "properties": {
    "iso:country":"NL",
    "sg:address":"H Droststr 44",
    "sg:city":"Olst",
    "sg:orig_category":"Mode-Artikelen Dames En Heren",
    "sg:phone":"+31 570 563 900",
    "sg:postcode":"8121 BJ",
    "sg:province":"NL.08",
    "wof:name":"Santenkraam, De",
    "wof:placetype":"venue"
},
  "geometry": {"coordinates":[6.109007,52.338341],"type":"Point"}
}