{
  "type": "Feature",
  "properties": {
    "addr:full":"Postbus 1071 Delft South Holland 2600 BB",
    "addr:housenumber":"1071",
    "addr:postcode":"2600 bb",
    "addr:street":"Postbus",
    "iso:country":"NL",
    "sg:address":"Postbus 1071",
    "sg:city":"Delft",
    "sg:orig_category":"Organisatiebureaus",
    "sg:phone":"+31 15 257 7965",
    "sg:postcode":"2600 BB",
    "sg:province":"South Holland",
    "wof:name":"Roemburg",
    "wof:placetype":"venue"
},
  "geometry": {"coordinates":[4.358689785,52.0115013123],"type":"Point"}
}