{
  "type": "Feature",
  "properties": {
    "iso:country":"NL",
    "sg:address":"Hessenbergwg 109-119",
    "sg:city":"Amsterdam Zuidoost",
    "sg:orig_category":"Kantoorbenodigdheden",
    "sg:phone":"+31 20 642 1987",
    "sg:postcode":"1101 BS",
    "sg:province":"Noord-Holland",
    "wof:name":"Cba Voor Kantoren",
    "wof:placetype":"venue"
},
  "geometry": {"coordinates":[4.9458041191,52.3047981262],"type":"Point"}
}