{
  "type": "Feature",
  "properties": {
    "addr:full":"Hoofdweg 395 Hoofddorp Noord-Holland 2130 AM",
    "addr:housenumber":"395",
    "addr:postcode":"2130",
    "addr:street":"Hoofdweg",
    "iso:country":"NL",
    "sg:address":"Hoofdweg 395",
    "sg:city":"Hoofddorp",
    "sg:orig_category":"Begrafenisondernemers",
    "sg:phone":"+31 23 561 6098",
    "sg:postcode":"2130 AM",
    "sg:province":"Noord-Holland",
    "wof:name":"Begraafplaats Wilgenhof",
    "wof:placetype":"venue"
},
  "geometry": {"coordinates":[4.72069,52.325481],"type":"Point"}
}