{
  "type": "Feature",
  "properties": {
    "addr:full":"Lieftinckplaats 41A Rotterdam South Holland 3066 XA",
    "addr:housenumber":"41a",
    "addr:postcode":"3066 xa",
    "addr:street":"Lieftinckplaats",
    "iso:country":"NL",
    "sg:address":"Lieftinckplaats 41A",
    "sg:city":"Rotterdam",
    "sg:orig_category":"Voetbalverenigingen",
    "sg:phone":"+31 10 420 6857",
    "sg:postcode":"3066 XA",
    "sg:province":"South Holland",
    "wof:name":"Eds",
    "wof:placetype":"venue"
},
  "geometry": {"coordinates":[4.560132,51.934376],"type":"Point"}
}