{
  "type": "Feature",
  "properties": {
    "addr:full":"Johanna Van Burenlaan 4 Oldenzaal Overijssel 7576 AV",
    "addr:housenumber":"4",
    "addr:postcode":"7576 av",
    "addr:street":"Johanna Van Burenlaan",
    "iso:country":"NL",
    "sg:address":"Johanna Van Burenlaan 4",
    "sg:city":"Oldenzaal",
    "sg:orig_category":"Kinderopvang Behalve Thuis",
    "sg:phone":"+31 541 515 956",
    "sg:postcode":"7576 AV",
    "sg:province":"Overijssel",
    "wof:name":"De Zonnestraal",
    "wof:placetype":"venue"
},
  "geometry": {"coordinates":[6.910522,52.312515],"type":"Point"}
}