{
  "type": "Feature",
  "properties": {
    "iso:country":"NL",
    "sg:address":"Tiber 72",
    "sg:city":"S Gravenhage",
    "sg:orig_category":"Plafonds",
    "sg:phone":"+31 70 320 0108",
    "sg:postcode":"2491 DK",
    "sg:province":"South Holland",
    "wof:name":"Bolleboom, B J M",
    "wof:placetype":"venue"
},
  "geometry": {"coordinates":[4.38382,52.065289],"type":"Point"}
}