{
  "type": "Feature",
  "properties": {
    "addr:full":"Klarenanstelerwg 5D Kerkrade Limburg 6468 EP",
    "addr:housenumber":"5d",
    "addr:postcode":"6468 ep",
    "iso:country":"NL",
    "sg:address":"Klarenanstelerwg 5D",
    "sg:city":"Kerkrade",
    "sg:orig_category":"Automaterialen En Gereedschappen",
    "sg:phone":"+31 45 567 8870",
    "sg:postcode":"6468 EP",
    "sg:province":"Limburg",
    "wof:name":"Otc Europe",
    "wof:placetype":"venue"
},
  "geometry": {"coordinates":[6.041539,50.87632],"type":"Point"}
}