{
  "type": "Feature",
  "properties": {
    "addr:full":"Jhr De Jongestr 15 Hoogeveen Drenthe 7902 HA",
    "addr:housenumber":"15",
    "addr:postcode":"7902 ha",
    "addr:street":"Jhr De Jongestr",
    "iso:country":"NL",
    "sg:address":"Jhr De Jongestr 15",
    "sg:city":"Hoogeveen",
    "sg:orig_category":"Scholen Voor Algemeen Voortgezet Onderwijs",
    "sg:phone":"+31 528 295 230",
    "sg:postcode":"7902 HA",
    "sg:province":"Drenthe",
    "wof:name":"Roelof Van Echten College Chr",
    "wof:placetype":"venue"
},
  "geometry": {"coordinates":[6.479538,52.722553],"type":"Point"}
}