{
  "type": "Feature",
  "properties": {
    "iso:country":"NL",
    "sg:address":"Herengracht 101",
    "sg:city":"Amsterdam",
    "sg:orig_category":"Public Relationbureaus",
    "sg:phone":"+31 20 627 8786",
    "sg:postcode":"1015 BE",
    "sg:province":"North Holland",
    "wof:name":"Meursing & Partners",
    "wof:placetype":"venue"
},
  "geometry": {"coordinates":[4.890426,52.376953],"type":"Point"}
}