{
  "type": "Feature",
  "properties": {
    "iso:country":"NL",
    "sg:address":"Wroetende Mol 4",
    "sg:city":"Bedum",
    "sg:orig_category":"Huizensloop And Bouwrijp Maken",
    "sg:phone":"+31 50 301 2577",
    "sg:postcode":"9781 TC",
    "sg:province":"Groningen",
    "wof:name":"Aannemingsbedrijf A Smedinga En Zonen Bv",
    "wof:placetype":"venue"
},
  "geometry": {"coordinates":[6.596314,53.313496],"type":"Point"}
}