{
  "type": "Feature",
  "properties": {
    "addr:full":"Pr Hendrikln 1 Driebergen Rysenb Utrecht 3972 EV",
    "addr:housenumber":"1",
    "addr:street":"Driebergen Rysenb",
    "iso:country":"NL",
    "sg:address":"Pr Hendrikln 1",
    "sg:city":"Driebergen Rysenb",
    "sg:orig_category":"Boeken Antiquarische En Gebruikte",
    "sg:phone":"+31 343 514 200",
    "sg:postcode":"3972 EV",
    "sg:province":"Utrecht",
    "wof:name":"Anna",
    "wof:placetype":"venue"
},
  "geometry": {"coordinates":[5.283655,52.051552],"type":"Point"}
}