{
  "type": "Feature",
  "properties": {
    "addr:full":"Pimpernelwg 14 Zwolle NL.08 8042 MP",
    "addr:housenumber":"14",
    "addr:postcode":"8042 mp",
    "addr:street":"Pimpernelwg",
    "iso:country":"NL",
    "sg:address":"Pimpernelwg 14",
    "sg:city":"Zwolle",
    "sg:orig_category":"Autolakken",
    "sg:phone":"+31 38 421 6792",
    "sg:postcode":"8042 MP",
    "sg:province":"NL.08",
    "wof:name":"Klompjan, G",
    "wof:placetype":"venue"
},
  "geometry": {"coordinates":[6.044747,52.517796],"type":"Point"}
}