{
  "type": "Feature",
  "properties": {
    "addr:full":"Kraaierslaan 25 Noordwijk Zh Zuid-Holland 2204 AN",
    "addr:housenumber":"25",
    "addr:postcode":"2204 an",
    "addr:street":"Kraaierslaan",
    "iso:country":"NL",
    "sg:address":"Kraaierslaan 25",
    "sg:city":"Noordwijk Zh",
    "sg:orig_category":"Kampeerterreinen",
    "sg:phone":"+31 252 372 826",
    "sg:postcode":"2204 AN",
    "sg:province":"Zuid-Holland",
    "wof:name":"Camping De Wulp",
    "wof:placetype":"venue"
},
  "geometry": {"coordinates":[4.4769749641,52.2744178772],"type":"Point"}
}