{
  "type": "Feature",
  "properties": {
    "iso:country":"NL",
    "sg:address":"Eindhovensew 22",
    "sg:city":"Valkenswaard",
    "sg:orig_category":"Warenhuizen",
    "sg:phone":"+31 40 201 2825",
    "sg:postcode":"5554 AC",
    "sg:province":"Noord-Brabant",
    "wof:name":"Hema",
    "wof:placetype":"venue"
},
  "geometry": {"coordinates":[5.4596438408,51.3519515991],"type":"Point"}
}