{
  "type": "Feature",
  "properties": {
    "addr:full":"Kleine Noorddijk 1 Aalsmeer North Holland 1432 CC",
    "addr:housenumber":"1",
    "addr:postcode":"1432 cc",
    "addr:street":"Kleine Noorddijk",
    "iso:country":"NL",
    "sg:address":"Kleine Noorddijk 1",
    "sg:city":"Aalsmeer",
    "sg:orig_category":"Kampeerterreinen",
    "sg:phone":"+31 20 641 6868",
    "sg:postcode":"1432 CC",
    "sg:province":"North Holland",
    "wof:name":"Camping Amsterdamse Bos",
    "wof:placetype":"venue"
},
  "geometry": {"coordinates":[4.8226499557,52.294719696],"type":"Point"}
}