{
  "type": "Feature",
  "properties": {
    "addr:full":"Zuiderkerkpln 5 Enkhuizen North Holland 1601 HK",
    "addr:housenumber":"5",
    "addr:postcode":"1601 hk",
    "addr:street":"Zuiderkerkpln",
    "iso:country":"NL",
    "sg:address":"Zuiderkerkpln 5",
    "sg:city":"Enkhuizen",
    "sg:orig_category":"Kinderopvang",
    "sg:phone":"+31 228 317 998",
    "sg:postcode":"1601 HK",
    "sg:province":"North Holland",
    "wof:name":"Dijk, Stichting Kindercentrum De",
    "wof:placetype":"venue"
},
  "geometry": {"coordinates":[5.292663,52.703465],"type":"Point"}
}