{
  "type": "Feature",
  "properties": {
    "addr:full":"Amazoneweg 2 Delft Zuid-Holland 2622 DS",
    "addr:housenumber":"2",
    "addr:postcode":"2622 ds",
    "addr:street":"Amazoneweg",
    "iso:country":"NL",
    "sg:address":"Amazoneweg 2",
    "sg:city":"Delft",
    "sg:orig_category":"Diverse Opleidingen And Onderwijs",
    "sg:phone":"+31 15 257 3463",
    "sg:postcode":"2622 DS",
    "sg:province":"Zuid-Holland",
    "wof:name":"Groei",
    "wof:placetype":"venue"
},
  "geometry": {"coordinates":[4.34744,51.985489],"type":"Point"}
}