{
  "type": "Feature",
  "properties": {
    "iso:country":"NL",
    "sg:address":"Westerstukken 45",
    "sg:city":"Eelde",
    "sg:orig_category":"Ingenieursbureaus",
    "sg:phone":"+31 50 309 6273",
    "sg:postcode":"9761 LJ",
    "sg:province":"Drenthe",
    "wof:name":"Mast, Ir W F Van Der",
    "wof:placetype":"venue"
},
  "geometry": {"coordinates":[6.55431,53.134731],"type":"Point"}
}