{
  "type": "Feature",
  "properties": {
    "addr:full":"Hoevensewg 47 Tilburg North Brabant 5017 AD",
    "addr:housenumber":"47",
    "addr:postcode":"5017 ad",
    "addr:street":"Hoevensewg",
    "iso:country":"NL",
    "sg:address":"Hoevensewg 47",
    "sg:city":"Tilburg",
    "sg:orig_category":"Bloemen En Planten",
    "sg:phone":"+31 6 25125716",
    "sg:postcode":"5017 AD",
    "sg:province":"North Brabant",
    "wof:name":"Hoeve, De",
    "wof:placetype":"venue"
},
  "geometry": {"coordinates":[5.105259,51.552864],"type":"Point"}
}