{
  "type": "Feature",
  "properties": {
    "iso:country":"NL",
    "sg:address":"Steekterwg 130I",
    "sg:city":"Alphen Aan Den Ryn",
    "sg:orig_category":"Zuivelindustrie - Apparaten En Installaties",
    "sg:phone":"+31 172 492 706",
    "sg:postcode":"2407 BJ",
    "sg:province":"South Holland",
    "wof:name":"Zijll Vof, Van",
    "wof:placetype":"venue"
},
  "geometry": {"coordinates":[4.693825,52.115952],"type":"Point"}
}