{
  "type": "Feature",
  "properties": {
    "addr:full":"Steekterwg 130I Alphen Aan Den Ryn South Holland 2407 BJ",
    "addr:housenumber":"130i",
    "addr:postcode":"2407 bj",
    "addr:street":"Steekterwg;Aan Den Ryn",
    "iso:country":"NL",
    "sg:address":"Steekterwg 130I",
    "sg:city":"Alphen Aan Den Ryn",
    "sg:orig_category":"Zuivelindustrie - Apparaten En Installaties",
    "sg:phone":"+31 172 492 706",
    "sg:postcode":"2407 BJ",
    "sg:province":"South Holland",
    "wof:name":"Zijll Vof, Van",
    "wof:placetype":"venue"
},
  "geometry": {"coordinates":[4.693825,52.115952],"type":"Point"}
}