{
  "type": "Feature",
  "properties": {
    "addr:full":"Stationsplein 3 Leiden Zuid-Holland 2312 AJ",
    "addr:housenumber":"3",
    "addr:postcode":"2312 aj",
    "addr:street":"Stationsplein",
    "iso:country":"NL",
    "sg:address":"Stationsplein 3",
    "sg:city":"Leiden",
    "sg:orig_category":"Bloemen And Planten",
    "sg:phone":"+31 71 514 6502",
    "sg:postcode":"2312 AJ",
    "sg:province":"Zuid-Holland",
    "wof:name":"W. Langeveld",
    "wof:placetype":"venue"
},
  "geometry": {"coordinates":[4.481092,52.165119],"type":"Point"}
}