{
  "type": "Feature",
  "properties": {
    "iso:country":"NL",
    "sg:address":"L P Boonstr 40",
    "sg:city":"Almere",
    "sg:orig_category":"Binnenhuisarchitectuur",
    "sg:phone":"+31 36 536 3893",
    "sg:postcode":"1321 KC",
    "sg:province":"NL.",
    "sg:website":"http://www.deweerspiegeling.nl",
    "wof:name":"Weerspiegeling, De",
    "wof:placetype":"venue"
},
  "geometry": {"coordinates":[5.190075,52.356987],"type":"Point"}
}