{
  "type": "Feature",
  "properties": {
    "addr:full":"Gerstakker 33 S Hertogenbosch Noord-Brabant 5236 VG",
    "addr:housenumber":"33",
    "addr:postcode":"5236 vg",
    "addr:street":"Gerstakker;S Hertogenbosch",
    "iso:country":"NL",
    "sg:address":"Gerstakker 33",
    "sg:city":"S Hertogenbosch",
    "sg:orig_category":"Nagelstudio'S",
    "sg:phone":"+31 73 641 5683",
    "sg:postcode":"5236 VG",
    "sg:province":"Noord-Brabant",
    "wof:name":"Studio Choice",
    "wof:placetype":"venue"
},
  "geometry": {"coordinates":[5.326129,51.736115],"type":"Point"}
}