{
  "type": "Feature",
  "properties": {
    "iso:country":"NL",
    "sg:address":"Kraneweg 75",
    "sg:city":"Groningen",
    "sg:orig_category":"Artsen And Specialisten",
    "sg:phone":"+31 50 313 4264",
    "sg:postcode":"9718 JK",
    "sg:province":"Groningen",
    "wof:name":"H.J.Th. Hermsen",
    "wof:placetype":"venue"
},
  "geometry": {"coordinates":[6.550438,53.217293],"type":"Point"}
}