{
  "type": "Feature",
  "properties": {
    "addr:full":"Hekstraat 4 Beilen Drenthe 9411 NG",
    "addr:housenumber":"4",
    "addr:postcode":"9411 ng",
    "addr:street":"Hekstraat",
    "iso:country":"NL",
    "sg:address":"Hekstraat 4",
    "sg:city":"Beilen",
    "sg:orig_category":"Kappers",
    "sg:phone":"+31 593 540 198",
    "sg:postcode":"9411 NG",
    "sg:province":"Drenthe",
    "wof:name":"Kapsalon Alice",
    "wof:placetype":"venue"
},
  "geometry": {"coordinates":[6.5172119141,52.8595352173],"type":"Point"}
}