{
  "type": "Feature",
  "properties": {
    "iso:country":"NL",
    "sg:address":"Koningin Julianaweg 132",
    "sg:city":"Leidschendam",
    "sg:orig_category":"Schilderwerk",
    "sg:phone":"+31 70 327 0596",
    "sg:postcode":"2264 BG",
    "sg:province":"Zuid-Holland",
    "wof:name":"Vof Vogelaar Wandafwerking",
    "wof:placetype":"venue"
},
  "geometry": {"coordinates":[4.394179,52.083874],"type":"Point"}
}