{
  "type": "Feature",
  "properties": {
    "addr:full":"Marco Pololaan 111 Utrecht Utrecht 3526 GB",
    "addr:housenumber":"111",
    "addr:postcode":"3526 gb",
    "addr:street":"Marco Pololaan",
    "iso:country":"NL",
    "sg:address":"Marco Pololaan 111",
    "sg:city":"Utrecht",
    "sg:orig_category":"Tandartsen",
    "sg:phone":"+31 30 288 0099",
    "sg:postcode":"3526 GB",
    "sg:province":"Utrecht",
    "wof:name":"J.B.T. The",
    "wof:placetype":"venue"
},
  "geometry": {"coordinates":[5.096421,52.069805],"type":"Point"}
}