{
  "type": "Feature",
  "properties": {
    "addr:full":"Meerstr 4 Duizel Noord-Brabant 5525 AM",
    "addr:housenumber":"4",
    "addr:postcode":"5525",
    "addr:street":"Meerstr",
    "iso:country":"NL",
    "sg:address":"Meerstr 4",
    "sg:city":"Duizel",
    "sg:orig_category":"Accountants - Administratie- Consulenten En -Kantoren",
    "sg:phone":"+31 497 517 191",
    "sg:postcode":"5525 AM",
    "sg:province":"Noord-Brabant",
    "wof:name":"Bam",
    "wof:placetype":"venue"
},
  "geometry": {"coordinates":[5.299588,51.368015],"type":"Point"}
}