{
  "type": "Feature",
  "properties": {
    "addr:full":"Hogezoom 16 Burgh Haamstede Zeeland 4328 EG",
    "addr:housenumber":"16",
    "addr:postcode":"4328 eg",
    "addr:street":"Hogezoom;Haamstede",
    "iso:country":"NL",
    "sg:address":"Hogezoom 16",
    "sg:city":"Burgh Haamstede",
    "sg:classifiers":[
        {
            "category":"Travel",
            "subcategory":"Hotels & Motels",
            "type":"Entertainment"
        }
    ],
    "sg:phone":"+31 111 653 116",
    "sg:postcode":"4328 EG",
    "sg:province":"Zeeland",
    "wof:name":"Pension La Bonette",
    "wof:placetype":"venue"
},
  "geometry": {"coordinates":[3.743759,51.703522],"type":"Point"}
}