{
  "type": "Feature",
  "properties": {
    "addr:full":"Kerklaan 11 Raamsdonk North Brabant 4944 VA",
    "addr:housenumber":"11",
    "addr:postcode":"4944",
    "addr:street":"Kerklaan",
    "iso:country":"NL",
    "sg:address":"Kerklaan 11",
    "sg:city":"Raamsdonk",
    "sg:orig_category":"Bloemen And Planten",
    "sg:phone":"+31 162 521 977",
    "sg:postcode":"4944 VA",
    "sg:province":"North Brabant",
    "wof:name":"J.L. Wagemakers",
    "wof:placetype":"venue"
},
  "geometry": {"coordinates":[4.894583,51.691586],"type":"Point"}
}