{
  "type": "Feature",
  "properties": {
    "addr:full":"Kerkstr 3 Woerden Utrecht 3441 BN",
    "addr:housenumber":"3",
    "addr:postcode":"3441 bn",
    "addr:street":"Kerkstr",
    "iso:country":"NL",
    "sg:address":"Kerkstr 3",
    "sg:city":"Woerden",
    "sg:classifiers":[
        {
            "category":"Shopping",
            "subcategory":"Adult",
            "type":"Retail Goods"
        }
    ],
    "sg:phone":"+31 348 430 833",
    "sg:postcode":"3441 BN",
    "sg:province":"Utrecht",
    "sg:tags":[
        "lingerie",
        "en",
        "tricotage"
    ],
    "wof:name":"Livera",
    "wof:placetype":"venue"
},
  "geometry": {"coordinates":[4.894684,52.111614],"type":"Point"}
}