{
  "type": "Feature",
  "properties": {
    "addr:full":"Den Texstr 32 Amsterdam Noord-Holland 1017 ZB",
    "addr:housenumber":"32",
    "addr:postcode":"1017 zb",
    "iso:country":"NL",
    "sg:address":"Den Texstr 32",
    "sg:city":"Amsterdam",
    "sg:orig_category":"Adviesbureaus Bedrijfsorganisatie",
    "sg:phone":"+31 20 620 1219",
    "sg:postcode":"1017 ZB",
    "sg:province":"Noord-Holland",
    "wof:name":"Bizzo",
    "wof:placetype":"venue"
},
  "geometry": {"coordinates":[4.89453,52.358734],"type":"Point"}
}