{
  "type": "Feature",
  "properties": {
    "addr:full":"V Ostadeln 278 Alkmaar North Holland 1816 JH",
    "addr:housenumber":"278",
    "addr:postcode":"1816 jh",
    "iso:country":"NL",
    "sg:address":"V Ostadeln 278",
    "sg:city":"Alkmaar",
    "sg:orig_category":"Banken",
    "sg:phone":"+31 72 567 4400",
    "sg:postcode":"1816 JH",
    "sg:province":"North Holland",
    "sg:website":"http://www.rabobank.nl",
    "wof:name":"Rabobank",
    "wof:placetype":"venue"
},
  "geometry": {"coordinates":[4.746258,52.634361],"type":"Point"}
}