{
  "type": "Feature",
  "properties": {
    "addr:full":"Economiestraat 6 Sittard Limburg 6135 VV",
    "addr:housenumber":"6",
    "addr:postcode":"6135 vv",
    "addr:street":"Economiestraat",
    "iso:country":"NL",
    "sg:address":"Economiestraat 6",
    "sg:city":"Sittard",
    "sg:orig_category":"Verhuisdiensten",
    "sg:phone":"+31 46 451 2836",
    "sg:postcode":"6135 VV",
    "sg:province":"Limburg",
    "wof:name":"G. Boetzkes En Zoon",
    "wof:placetype":"venue"
},
  "geometry": {"coordinates":[5.840668,50.997334],"type":"Point"}
}