{
  "type": "Feature",
  "properties": {
    "addr:full":"Kalf 61 Zaandam Noord-Holland 1509 AB",
    "addr:housenumber":"61",
    "addr:postcode":"1509 ab",
    "addr:street":"Kalf",
    "iso:country":"NL",
    "sg:address":"Kalf 61",
    "sg:city":"Zaandam",
    "sg:classifiers":[
        {
            "category":"Food & Beverages",
            "subcategory":"Bakery",
            "type":"Retail Goods"
        }
    ],
    "sg:phone":"+31 75 617 0335",
    "sg:postcode":"1509 AB",
    "sg:province":"Noord-Holland",
    "sg:tags":[
        "pizza"
    ],
    "wof:name":"Di Mare",
    "wof:placetype":"venue"
},
  "geometry": {"coordinates":[4.826122,52.469749],"type":"Point"}
}