{
  "type": "Feature",
  "properties": {
    "iso:country":"NL",
    "sg:address":"Chopinln 12",
    "sg:city":"Maarssen",
    "sg:orig_category":"Adviesbureaus Bedrijfsorganisatie",
    "sg:phone":"+31 346 579 964",
    "sg:postcode":"3603 CE",
    "sg:province":"Utrecht",
    "wof:name":"Bumaco Bv",
    "wof:placetype":"venue"
},
  "geometry": {"coordinates":[5.043494,52.137272],"type":"Point"}
}