{
  "type": "Feature",
  "properties": {
    "addr:full":"Hoofdstr 61 Velp Gld Gelderland 6881 TC",
    "addr:housenumber":"61",
    "addr:postcode":"6881 tc",
    "addr:street":"Hoofdstr;Gld Gelderland",
    "iso:country":"NL",
    "sg:address":"Hoofdstr 61",
    "sg:city":"Velp Gld",
    "sg:orig_category":"Makelaars En Adviseurs Onroerende Goederen",
    "sg:phone":"+31 26 361 7923",
    "sg:postcode":"6881 TC",
    "sg:province":"Gelderland",
    "sg:website":"http://www.frankenet.nl",
    "wof:name":"Franke Bv",
    "wof:placetype":"venue"
},
  "geometry": {"coordinates":[5.972043,51.99577],"type":"Point"}
}