{
  "type": "Feature",
  "properties": {
    "addr:full":"Marktplein 282 Hoofddorp Noord-Holland 2132 CZ",
    "addr:housenumber":"282",
    "addr:postcode":"2132",
    "addr:street":"Marktplein",
    "iso:country":"NL",
    "sg:address":"Marktplein 282",
    "sg:city":"Hoofddorp",
    "sg:orig_category":"Fotostudio'S And Fotografen",
    "sg:phone":"+31 23 561 3523",
    "sg:postcode":"2132 CZ",
    "sg:province":"Noord-Holland",
    "wof:name":"Minimax",
    "wof:placetype":"venue"
},
  "geometry": {"coordinates":[4.693412,52.303715],"type":"Point"}
}