{
  "type": "Feature",
  "properties": {
    "addr:full":"Ringdk 8 Reeuwyk Zuid-Holland 2811 PG",
    "addr:housenumber":"8",
    "addr:postcode":"2811 pg",
    "addr:street":"Ringdk",
    "iso:country":"NL",
    "sg:address":"Ringdk 8",
    "sg:city":"Reeuwyk",
    "sg:orig_category":"Loonbedrijven",
    "sg:phone":"+31 182 392 398",
    "sg:postcode":"2811 PG",
    "sg:province":"Zuid-Holland",
    "wof:name":"Vermeulen, M J",
    "wof:placetype":"venue"
},
  "geometry": {"coordinates":[4.722337,52.044903],"type":"Point"}
}