{
  "type": "Feature",
  "properties": {
    "iso:country":"NL",
    "sg:address":"Belleweg 7",
    "sg:city":"Someren",
    "sg:orig_category":"Verhuur Audiovisuele Apparatuur",
    "sg:phone":"+31 493 496 887",
    "sg:postcode":"5711 DH",
    "sg:province":"North Brabant",
    "wof:name":"Audio And Video Services",
    "wof:placetype":"venue"
},
  "geometry": {"coordinates":[5.726228,51.388615],"type":"Point"}
}