{
  "type": "Feature",
  "properties": {
    "addr:full":"Hogeweg 66 Amsterdam Noord-Holland 1098 CG",
    "addr:housenumber":"66",
    "addr:postcode":"1098 cg",
    "addr:street":"Hogeweg",
    "iso:country":"NL",
    "sg:address":"Hogeweg 66",
    "sg:city":"Amsterdam",
    "sg:orig_category":"Bedrijfs- And Managementsconsultants",
    "sg:phone":"+31 20 665 0305",
    "sg:postcode":"1098 CG",
    "sg:province":"Noord-Holland",
    "wof:name":"Core Business Communications",
    "wof:placetype":"venue"
},
  "geometry": {"coordinates":[4.933841,52.355434],"type":"Point"}
}