{
  "type": "Feature",
  "properties": {
    "addr:full":"Palestrinarode 30 Zoetermeer Zuid-Holland 2717 GB",
    "addr:housenumber":"30",
    "addr:postcode":"2717 gb",
    "addr:street":"Palestrinarode",
    "iso:country":"NL",
    "sg:address":"Palestrinarode 30",
    "sg:city":"Zoetermeer",
    "sg:orig_category":"Adviesbureaus Bedrijfsorganisatie",
    "sg:phone":"+31 6 52473468",
    "sg:postcode":"2717 GB",
    "sg:province":"Zuid-Holland",
    "wof:name":"Pietas",
    "wof:placetype":"venue"
},
  "geometry": {"coordinates":[4.48131,52.070057],"type":"Point"}
}