{
  "type": "Feature",
  "properties": {
    "addr:full":"Azielaan 756 Utrecht Utrecht 3526 SZ",
    "addr:housenumber":"756",
    "addr:postcode":"3526 sz",
    "addr:street":"Azielaan",
    "iso:country":"NL",
    "sg:address":"Azielaan 756",
    "sg:city":"Utrecht",
    "sg:orig_category":"Boekhouders",
    "sg:phone":"+31 30 267 2321",
    "sg:postcode":"3526 SZ",
    "sg:province":"Utrecht",
    "wof:name":"B & E",
    "wof:placetype":"venue"
},
  "geometry": {"coordinates":[5.106279,52.065815],"type":"Point"}
}