{
  "type": "Feature",
  "properties": {
    "addr:full":"Kapelstr 8 Maurik Gelderland 4021 AA",
    "addr:housenumber":"8",
    "addr:postcode":"4021 aa",
    "addr:street":"Kapelstr;Gelderland",
    "iso:country":"NL",
    "sg:address":"Kapelstr 8",
    "sg:city":"Maurik",
    "sg:classifiers":[
        {
            "category":"Personal",
            "subcategory":"Nail Salon",
            "type":"Services"
        }
    ],
    "sg:phone":"+31 344 693 339",
    "sg:postcode":"4021 AA",
    "sg:province":"Gelderland",
    "sg:tags":[
        "pedicure"
    ],
    "wof:name":"Ulden-Van Houten, I Van",
    "wof:placetype":"venue"
},
  "geometry": {"coordinates":[5.412721,51.960323],"type":"Point"}
}