{
  "type": "Feature",
  "properties": {
    "addr:full":"Postbus 24 Raamsdonksveer North Brabant 4940 AA",
    "addr:housenumber":"24",
    "addr:postcode":"4940 aa",
    "addr:street":"Postbus",
    "iso:country":"NL",
    "sg:address":"Postbus 24",
    "sg:city":"Raamsdonksveer",
    "sg:orig_category":"Voetbalverenigingen",
    "sg:phone":"+31 162 522 190",
    "sg:postcode":"4940 AA",
    "sg:province":"North Brabant",
    "wof:name":"Good Luck",
    "wof:placetype":"venue"
},
  "geometry": {"coordinates":[4.8749,51.695019],"type":"Point"}
}