{
  "type": "Feature",
  "properties": {
    "addr:full":"Hof Bruheze 412 Helmond Noord-Brabant 5704 NR",
    "addr:housenumber":"412",
    "addr:postcode":"5704 nr",
    "addr:street":"Hof Bruheze",
    "iso:country":"NL",
    "sg:address":"Hof Bruheze 412",
    "sg:city":"Helmond",
    "sg:orig_category":"Meubelen",
    "sg:phone":"+31 492 513 042",
    "sg:postcode":"5704 NR",
    "sg:province":"Noord-Brabant",
    "wof:name":"Heuvel, Van Den",
    "wof:placetype":"venue"
},
  "geometry": {"coordinates":[5.709868,51.468468],"type":"Point"}
}