{
  "type": "Feature",
  "properties": {
    "addr:full":"Sportln 1 Bergambacht Zuid-Holland 2861 GJ",
    "addr:housenumber":"1",
    "addr:postcode":"2861 gj",
    "addr:street":"Sportln",
    "iso:country":"NL",
    "sg:address":"Sportln 1",
    "sg:city":"Bergambacht",
    "sg:orig_category":"Voetbalverenigingen",
    "sg:phone":"+31 182 352 014",
    "sg:postcode":"2861 GJ",
    "sg:province":"Zuid-Holland",
    "wof:name":"Bergambacht Vv",
    "wof:placetype":"venue"
},
  "geometry": {"coordinates":[4.783119,51.936462],"type":"Point"}
}