{
  "type": "Feature",
  "properties": {
    "addr:full":"Diemenln 60 Emmeloord NL. 8304 ED",
    "addr:housenumber":"60",
    "addr:postcode":"8304 ed",
    "addr:street":"Diemenln;Nl.",
    "iso:country":"NL",
    "sg:address":"Diemenln 60",
    "sg:city":"Emmeloord",
    "sg:orig_category":"Onroerende Goederen",
    "sg:phone":"+31 527 615 511",
    "sg:postcode":"8304 ED",
    "sg:province":"NL.",
    "wof:name":"Buro Grondzaken Flevoland",
    "wof:placetype":"venue"
},
  "geometry": {"coordinates":[5.760058,52.700085],"type":"Point"}
}