{
  "type": "Feature",
  "properties": {
    "addr:full":"Hoofdstraat West 33 Noordwolde Fr Provincie Friesland 8391 AL",
    "addr:housenumber":"33",
    "addr:postcode":"8391",
    "addr:street":"Hoofdstraat West;Friesland",
    "iso:country":"NL",
    "sg:address":"Hoofdstraat West 33",
    "sg:city":"Noordwolde Fr",
    "sg:orig_category":"Metselwerken",
    "sg:phone":"+31 6 55304914",
    "sg:postcode":"8391 AL",
    "sg:province":"Provincie Friesland",
    "wof:name":"Walle, Metselwerken Vd",
    "wof:placetype":"venue"
},
  "geometry": {"coordinates":[6.137431,52.889523],"type":"Point"}
}