{
  "type": "Feature",
  "properties": {
    "addr:full":"Balsemienlaan 192 'S Gravenhage Zuid-Holland 2555 RG",
    "addr:housenumber":"192 '",
    "addr:postcode":"2555 rg",
    "addr:street":"Balsemienlaan",
    "iso:country":"NL",
    "sg:address":"Balsemienlaan 192",
    "sg:city":"'S Gravenhage",
    "sg:orig_category":"Boekhouders",
    "sg:phone":"+31 70 368 2029",
    "sg:postcode":"2555 RG",
    "sg:province":"Zuid-Holland",
    "wof:name":"Administratiekantoor Sobczak",
    "wof:placetype":"venue"
},
  "geometry": {"coordinates":[4.234766,52.068916],"type":"Point"}
}