{
  "type": "Feature",
  "properties": {
    "addr:full":"Plasseweg 1 Waarde Zeeland 4414 NC",
    "addr:housenumber":"1",
    "addr:postcode":"4414 nc",
    "addr:street":"Plasseweg",
    "iso:country":"NL",
    "sg:address":"Plasseweg 1",
    "sg:city":"Waarde",
    "sg:orig_category":"Fruit And Groenten Gh",
    "sg:phone":"+31 113 501 469",
    "sg:postcode":"4414 NC",
    "sg:province":"Zeeland",
    "wof:name":"A. Waterman",
    "wof:placetype":"venue"
},
  "geometry": {"coordinates":[4.072777,51.425392],"type":"Point"}
}