{
  "type": "Feature",
  "properties": {
    "addr:full":"Kanaalstraat 9 Roden Provincie Drenthe 9301 LP",
    "addr:housenumber":"9",
    "addr:postcode":"9301 lp",
    "addr:street":"Kanaalstraat;Provincie Drenthe",
    "iso:country":"NL",
    "sg:address":"Kanaalstraat 9",
    "sg:city":"Roden",
    "sg:orig_category":"Banken And Kredietinstellingen",
    "sg:phone":"+31 50 501 9604",
    "sg:postcode":"9301 LP",
    "sg:province":"Provincie Drenthe",
    "wof:name":"Ing Bank",
    "wof:placetype":"venue"
},
  "geometry": {"coordinates":[6.432807,53.138641],"type":"Point"}
}