{
  "type": "Feature",
  "properties": {
    "addr:full":"Duinoordstr 39 Haarlem Noord-Holland 2023 WB",
    "addr:housenumber":"39",
    "addr:postcode":"2023 wb",
    "addr:street":"Duinoordstr",
    "iso:country":"NL",
    "sg:address":"Duinoordstr 39",
    "sg:city":"Haarlem",
    "sg:orig_category":"Advocaten En Advocatenkantoren",
    "sg:phone":"+31 23 525 5438",
    "sg:postcode":"2023 WB",
    "sg:province":"Noord-Holland",
    "wof:name":"Loo, M A A Van Der",
    "wof:placetype":"venue"
},
  "geometry": {"coordinates":[4.633467,52.398727],"type":"Point"}
}