{
  "type": "Feature",
  "properties": {
    "addr:full":"Valeriaan 64 Culemborg Gelderland 4102 VH",
    "addr:housenumber":"64",
    "addr:postcode":"4102 vh",
    "addr:street":"Valeriaan;Gelderland",
    "iso:country":"NL",
    "sg:address":"Valeriaan 64",
    "sg:city":"Culemborg",
    "sg:orig_category":"Verenigingen En Stichtingen",
    "sg:phone":"+31 345 568 506",
    "sg:postcode":"4102 VH",
    "sg:province":"Gelderland",
    "wof:name":"Eva, Sticht",
    "wof:placetype":"venue"
},
  "geometry": {"coordinates":[5.252092,51.953144],"type":"Point"}
}