{
  "type": "Feature",
  "properties": {
    "addr:full":"Spoorstraat 10 Haaksbergen NL.08 7481 HZ",
    "addr:housenumber":"10;nl.08",
    "addr:postcode":"7481 hz",
    "addr:street":"Spoorstraat",
    "iso:country":"NL",
    "sg:address":"Spoorstraat 10",
    "sg:city":"Haaksbergen",
    "sg:orig_category":"Fotostudio'S And Fotografen",
    "sg:phone":"+31 53 572 1526",
    "sg:postcode":"7481 HZ",
    "sg:province":"NL.08",
    "wof:name":"Foto Vaarhorst Bv",
    "wof:placetype":"venue"
},
  "geometry": {"coordinates":[6.741376,52.155518],"type":"Point"}
}