{
  "type": "Feature",
  "properties": {
    "addr:full":"Ringdk 42 Ridderkerk Zuid-Holland 2981 EW",
    "addr:housenumber":"42",
    "addr:postcode":"2981 ew",
    "addr:street":"Ringdk",
    "iso:country":"NL",
    "sg:address":"Ringdk 42",
    "sg:city":"Ridderkerk",
    "sg:orig_category":"Meubelen",
    "sg:phone":"+31 180 412 202",
    "sg:postcode":"2981 EW",
    "sg:province":"Zuid-Holland",
    "wof:name":"Put Wooncomfort",
    "wof:placetype":"venue"
},
  "geometry": {"coordinates":[4.603368,51.871735],"type":"Point"}
}