{
  "type": "Feature",
  "properties": {
    "iso:country":"NL",
    "sg:address":"Westerstraat 15",
    "sg:city":"Sijbekarspel",
    "sg:orig_category":"Fruit And Groenten Gh",
    "sg:phone":"+31 229 591 397",
    "sg:postcode":"1655 LB",
    "sg:province":"Noord-Holland",
    "wof:name":"Jan Schouten",
    "wof:placetype":"venue"
},
  "geometry": {"coordinates":[4.982168,52.711052],"type":"Point"}
}