{
  "type": "Feature",
  "properties": {
    "iso:country":"NL",
    "sg:address":"Heezerwg 294",
    "sg:city":"Eindhoven",
    "sg:orig_category":"Juweliers",
    "sg:phone":"+31 40 211 3489",
    "sg:postcode":"5643 KM",
    "sg:province":"North Brabant",
    "wof:name":"Goldtime",
    "wof:placetype":"venue"
},
  "geometry": {"coordinates":[5.498765,51.423363],"type":"Point"}
}