{
  "type": "Feature",
  "properties": {
    "addr:full":"Van Der Duijnstraat 3 Utrecht Utrecht 3581 JW",
    "addr:housenumber":"3",
    "addr:postcode":"3581 jw",
    "addr:street":"Van Der Duijnstraat",
    "iso:country":"NL",
    "sg:address":"Van Der Duijnstraat 3",
    "sg:city":"Utrecht",
    "sg:orig_category":"Bedrijfs- And Managementsconsultants",
    "sg:phone":"+31 30 251 6143",
    "sg:postcode":"3581 JW",
    "sg:province":"Utrecht",
    "wof:name":"W.F.M.A. Willms",
    "wof:placetype":"venue"
},
  "geometry": {"coordinates":[5.137145,52.08947],"type":"Point"}
}