{
  "type": "Feature",
  "properties": {
    "addr:full":"St. Jorisplein 75 Ridderkerk South Holland 2981 GD",
    "addr:housenumber":"75",
    "addr:postcode":"2981 gd",
    "addr:street":"St. Jorisplein",
    "iso:country":"NL",
    "sg:address":"St. Jorisplein 75",
    "sg:city":"Ridderkerk",
    "sg:orig_category":"Schoenen",
    "sg:phone":"+31 180 433 766",
    "sg:postcode":"2981 GD",
    "sg:province":"South Holland",
    "wof:name":"Dolcis",
    "wof:placetype":"venue"
},
  "geometry": {"coordinates":[4.600164,51.870163],"type":"Point"}
}