{
  "type": "Feature",
  "properties": {
    "iso:country":"NL",
    "sg:address":"Beverstr 38",
    "sg:city":"Utrecht",
    "sg:orig_category":"Psychotherapeuten",
    "sg:phone":"+31 30 231 0389",
    "sg:postcode":"3513 AR",
    "sg:province":"New York",
    "wof:name":"Liedeke Vis",
    "wof:placetype":"venue"
},
  "geometry": {"coordinates":[-73.996292,40.613091],"type":"Point"}
}