{
  "type": "Feature",
  "properties": {
    "addr:full":"Industriewg 25 Ysselstein Ut Utrecht 3401 MA",
    "addr:housenumber":"25",
    "addr:postcode":"3401 ma",
    "addr:street":"Industriewg",
    "iso:country":"NL",
    "sg:address":"Industriewg 25",
    "sg:city":"Ysselstein Ut",
    "sg:orig_category":"Kunstgebitten",
    "sg:phone":"+31 30 688 0324",
    "sg:postcode":"3401 MA",
    "sg:province":"Utrecht",
    "wof:name":"Isseldent",
    "wof:placetype":"venue"
},
  "geometry": {"coordinates":[5.05398,52.014656],"type":"Point"}
}