{
  "type": "Feature",
  "properties": {
    "addr:full":"Breestraat 73 Leiden Zuid-Holland 2311 CJ",
    "addr:housenumber":"73",
    "addr:postcode":"2311 cj",
    "addr:street":"Breestraat",
    "iso:country":"NL",
    "sg:address":"Breestraat 73",
    "sg:city":"Leiden",
    "sg:orig_category":"Antiekzaken",
    "sg:phone":"+31 71 512 2007",
    "sg:postcode":"2311 CJ",
    "sg:province":"Zuid-Holland",
    "wof:name":"Boekhandel J. De Slegte Bv",
    "wof:placetype":"venue"
},
  "geometry": {"coordinates":[4.488857,52.159092],"type":"Point"}
}