{
  "type": "Feature",
  "properties": {
    "addr:full":"Verl V M Kooystr 30 Amsterdam Noord-Holland 1096 BX",
    "addr:housenumber":"30",
    "addr:postcode":"1096 bx",
    "iso:country":"NL",
    "sg:address":"Verl V M Kooystr 30",
    "sg:city":"Amsterdam",
    "sg:classifiers":[
        {
            "category":"Travel",
            "subcategory":"Hotels & Motels",
            "type":"Entertainment"
        }
    ],
    "sg:phone":"+31 20 663 4567",
    "sg:postcode":"1096 BX",
    "sg:province":"Noord-Holland",
    "sg:website":"http://www.bastionhotels.nl",
    "wof:name":"Bastion Amsterdam",
    "wof:placetype":"venue"
},
  "geometry": {"coordinates":[4.89319,52.373119],"type":"Point"}
}