{
  "type": "Feature",
  "properties": {
    "addr:full":"Springweg 8 Utrecht Utrecht 3511 VP",
    "addr:housenumber":"8",
    "addr:postcode":"3511 vp",
    "addr:street":"Springweg",
    "iso:country":"NL",
    "sg:address":"Springweg 8",
    "sg:city":"Utrecht",
    "sg:orig_category":"Geluidsopnamen",
    "sg:phone":"+31 30 231 1909",
    "sg:postcode":"3511 VP",
    "sg:province":"Utrecht",
    "wof:name":"Bernhard Joosten Muziekprodukties Bv",
    "wof:placetype":"venue"
},
  "geometry": {"coordinates":[5.118479,52.089062],"type":"Point"}
}