{
  "type": "Feature",
  "properties": {
    "iso:country":"NL",
    "sg:address":"Gedempte Gracht 43",
    "sg:city":"Schagen",
    "sg:orig_category":"Opticiens",
    "sg:phone":"+31 224 212 367",
    "sg:postcode":"1741 GB",
    "sg:province":"North Holland",
    "wof:name":"Optiek Mulder Bv",
    "wof:placetype":"venue"
},
  "geometry": {"coordinates":[4.7988910675,52.7871170044],"type":"Point"}
}