{
  "type": "Feature",
  "properties": {
    "addr:full":"Euterpeplein 34 Amersfoort Utrecht 3816 NP",
    "addr:housenumber":"34",
    "addr:postcode":"3816 np",
    "addr:street":"Euterpeplein",
    "iso:country":"NL",
    "sg:address":"Euterpeplein 34",
    "sg:city":"Amersfoort",
    "sg:orig_category":"Kappers",
    "sg:phone":"+31 33 472 2271",
    "sg:postcode":"3816 NP",
    "sg:province":"Utrecht",
    "wof:name":"Knipshop Kreatief",
    "wof:placetype":"venue"
},
  "geometry": {"coordinates":[5.406473,52.151154],"type":"Point"}
}