{
  "type": "Feature",
  "properties": {
    "addr:full":"Pelsterstr 43-37 Groningen Groningen 9711 KJ",
    "addr:housenumber":"43-37",
    "addr:postcode":"9711 kj",
    "iso:country":"NL",
    "sg:address":"Pelsterstr 43-37",
    "sg:city":"Groningen",
    "sg:orig_category":"Grafisch Ontwerpers",
    "sg:phone":"+31 50 318 2579",
    "sg:postcode":"9711 KJ",
    "sg:province":"Groningen",
    "wof:name":"Tuin, Van Der",
    "wof:placetype":"venue"
},
  "geometry": {"coordinates":[6.567226,53.21558],"type":"Point"}
}