{
  "type": "Feature",
  "properties": {
    "addr:full":"Pelgrimspad 3 Boxtel Noord-Brabant 5281 AA",
    "addr:housenumber":"3",
    "addr:postcode":"5281 aa",
    "addr:street":"Pelgrimspad",
    "iso:country":"NL",
    "sg:address":"Pelgrimspad 3",
    "sg:city":"Boxtel",
    "sg:orig_category":"Verloskundigen",
    "sg:phone":"+31 411 675 817",
    "sg:postcode":"5281 AA",
    "sg:province":"Noord-Brabant",
    "wof:name":"Maatschap Verloskundigen",
    "wof:placetype":"venue"
},
  "geometry": {"coordinates":[5.327935,51.591354],"type":"Point"}
}