{
  "type": "Feature",
  "properties": {
    "addr:full":"Rijkswegnoord 118 Swalmen Limburg 6071 KZ",
    "addr:housenumber":"118",
    "addr:postcode":"6071 kz",
    "addr:street":"Rijkswegnoord",
    "iso:country":"NL",
    "sg:address":"Rijkswegnoord 118",
    "sg:city":"Swalmen",
    "sg:orig_category":"Autokeuringen",
    "sg:phone":"+31 475 505 045",
    "sg:postcode":"6071 KZ",
    "sg:province":"Limburg",
    "wof:name":"Vakgarage Car-Center",
    "wof:placetype":"venue"
},
  "geometry": {"coordinates":[6.05043,51.243198],"type":"Point"}
}