{
  "type": "Feature",
  "properties": {
    "iso:country":"NL",
    "sg:address":"Margrietstraat 19",
    "sg:city":"Aalsmeer",
    "sg:orig_category":"Boekhouders",
    "sg:phone":"+31 297 322 157",
    "sg:postcode":"1432 HR",
    "sg:province":"North Holland",
    "wof:name":"Administratiekantoor Volman",
    "wof:placetype":"venue"
},
  "geometry": {"coordinates":[4.79943,52.276936],"type":"Point"}
}