{
  "type": "Feature",
  "properties": {
    "addr:full":"Sloterweg 796 Amsterdam Noord-Holland 1066 CN",
    "addr:housenumber":"796",
    "addr:postcode":"1066 cn",
    "addr:street":"Sloterweg",
    "iso:country":"NL",
    "sg:address":"Sloterweg 796",
    "sg:city":"Amsterdam",
    "sg:orig_category":"Makelaars In Onroerend Goed",
    "sg:phone":"+31 20 661 3811",
    "sg:postcode":"1066 CN",
    "sg:province":"Noord-Holland",
    "wof:name":"Abeco Adviseurs En Makelaars Og Bv",
    "wof:placetype":"venue"
},
  "geometry": {"coordinates":[4.817235,52.342018],"type":"Point"}
}