{
  "type": "Feature",
  "properties": {
    "addr:full":"Brouwerspad 22 Lith Noord-Brabant 5397 GG",
    "addr:housenumber":"22",
    "addr:postcode":"5397 gg",
    "addr:street":"Brouwerspad",
    "iso:country":"NL",
    "sg:address":"Brouwerspad 22",
    "sg:city":"Lith",
    "sg:orig_category":"Benzinestations And Brandstoffen",
    "sg:phone":"+31 412 481 838",
    "sg:postcode":"5397 GG",
    "sg:province":"Noord-Brabant",
    "wof:name":"Vof Servicestation Verboven",
    "wof:placetype":"venue"
},
  "geometry": {"coordinates":[-82.170288,27.862659],"type":"Point"}
}