{
  "type": "Feature",
  "properties": {
    "addr:full":"Gen Cronjestr 115 Haarlem North Holland 2021 JE",
    "addr:housenumber":"115",
    "addr:postcode":"2021 je",
    "iso:country":"NL",
    "sg:address":"Gen Cronjestr 115",
    "sg:city":"Haarlem",
    "sg:classifiers":[
        {
            "category":"Shopping",
            "subcategory":"Adult",
            "type":"Retail Goods"
        }
    ],
    "sg:phone":"+31 23 525 6833",
    "sg:postcode":"2021 JE",
    "sg:province":"North Holland",
    "sg:tags":[
        "lingerie",
        "en",
        "tricotage"
    ],
    "sg:website":"http://www.warmer-ondermode.nl",
    "wof:name":"Warmer",
    "wof:placetype":"venue"
},
  "geometry": {"coordinates":[4.642004,52.395393],"type":"Point"}
}