{
  "type": "Feature",
  "properties": {
    "addr:full":"Celsiusstraat 2 Weert Limburg 6003 DG",
    "addr:housenumber":"2",
    "addr:postcode":"6003 dg",
    "addr:street":"Celsiusstraat",
    "iso:country":"NL",
    "sg:address":"Celsiusstraat 2",
    "sg:city":"Weert",
    "sg:orig_category":"Metaalbekleding And -Behandeling",
    "sg:phone":"+31 495 536 586",
    "sg:postcode":"6003 DG",
    "sg:province":"Limburg",
    "wof:name":"Lasco Weert Bv",
    "wof:placetype":"venue"
},
  "geometry": {"coordinates":[5.726769,51.27047],"type":"Point"}
}