{
  "type": "Feature",
  "properties": {
    "iso:country":"NL",
    "sg:address":"Hagensstraat 23",
    "sg:city":"Sweikhuizen",
    "sg:orig_category":"Loodgieterswerk, Verwarming And Sanitaire Installaties",
    "sg:phone":"+31 46 443 1714",
    "sg:postcode":"6174 RM",
    "sg:province":"Limburg",
    "wof:name":"J.H.F. Peters",
    "wof:placetype":"venue"
},
  "geometry": {"coordinates":[5.849826,50.953865],"type":"Point"}
}