{
  "type": "Feature",
  "properties": {
    "iso:country":"NL",
    "sg:address":"Hesselingen 42",
    "sg:city":"Meppel",
    "sg:orig_category":"Pompen And Compressoren Fab",
    "sg:phone":"+31 522 256 060",
    "sg:postcode":"7942 HR",
    "sg:province":"Drenthe",
    "wof:name":"Hiab Accessoires",
    "wof:placetype":"venue"
},
  "geometry": {"coordinates":[6.170139,52.687038],"type":"Point"}
}