{
  "type": "Feature",
  "properties": {
    "iso:country":"NL",
    "sg:address":"Passage 25",
    "sg:city":"Roosendaal",
    "sg:orig_category":"Verlichting And Huishoudartikelen",
    "sg:phone":"+31 165 534 889",
    "sg:postcode":"4701 AN",
    "sg:province":"Noord-Brabant",
    "wof:name":"Beens Exclusieve Verlichting",
    "wof:placetype":"venue"
},
  "geometry": {"coordinates":[4.456736,51.532158],"type":"Point"}
}