{
  "type": "Feature",
  "properties": {
    "addr:full":"Rembrandtgalerij 12 Roosendaal Noord-Brabant 4703 GZ",
    "addr:housenumber":"12",
    "addr:postcode":"4703 gz",
    "addr:street":"Rembrandtgalerij",
    "iso:country":"NL",
    "sg:address":"Rembrandtgalerij 12",
    "sg:city":"Roosendaal",
    "sg:orig_category":"Apotheken",
    "sg:phone":"+31 165 559 159",
    "sg:postcode":"4703 GZ",
    "sg:province":"Noord-Brabant",
    "wof:name":"Westrand",
    "wof:placetype":"venue"
},
  "geometry": {"coordinates":[4.443393,51.535088],"type":"Point"}
}