{
  "type": "Feature",
  "properties": {
    "addr:full":"Wanraay 31C Andelst Gelderland 6673 DM",
    "addr:housenumber":"31c",
    "addr:postcode":"6673 dm",
    "addr:street":"Wanraay;Gelderland",
    "iso:country":"NL",
    "sg:address":"Wanraay 31C",
    "sg:city":"Andelst",
    "sg:orig_category":"Veiligheidsuitrusting En -Kleding",
    "sg:phone":"+31 488 452 445",
    "sg:postcode":"6673 DM",
    "sg:province":"Gelderland",
    "sg:website":"http://www.kcl.de",
    "wof:name":"Kcl Ned Bv",
    "wof:placetype":"venue"
},
  "geometry": {"coordinates":[5.718123,51.913692],"type":"Point"}
}