{
  "type": "Feature",
  "properties": {
    "addr:full":"Rivium Oostln 29 Capelle Ad Yssel South Holland 2909 LL",
    "addr:housenumber":"29;2909",
    "addr:postcode":"ll",
    "addr:street":"Yssel",
    "iso:country":"NL",
    "sg:address":"Rivium Oostln 29",
    "sg:city":"Capelle Ad Yssel",
    "sg:orig_category":"Dtp",
    "sg:phone":"+31 10 447 1422",
    "sg:postcode":"2909 LL",
    "sg:province":"South Holland",
    "wof:name":"Resolutie, De",
    "wof:placetype":"venue"
},
  "geometry": {"coordinates":[4.54677,51.913151],"type":"Point"}
}