{
  "type": "Feature",
  "properties": {
    "addr:full":"Nieuwe Nieuwstraat 17 Amsterdam Noord-Holland 1012 NG",
    "addr:housenumber":"17",
    "addr:postcode":"1012 ng",
    "addr:street":"Nieuwe Nieuwstraat",
    "iso:country":"NL",
    "sg:address":"Nieuwe Nieuwstraat 17",
    "sg:city":"Amsterdam",
    "sg:classifiers":[
        {
            "category":"Travel",
            "subcategory":"Hotels & Motels",
            "type":"Entertainment"
        }
    ],
    "sg:phone":"+31 20 625 2438",
    "sg:postcode":"1012 NG",
    "sg:province":"Noord-Holland",
    "sg:website":"http://www.hostelcosmos.com",
    "wof:name":"Hostel Cosmos Amsterdam",
    "wof:placetype":"venue"
},
  "geometry": {"coordinates":[4.893455,52.375301],"type":"Point"}
}