{
  "type": "Feature",
  "properties": {
    "iso:country":"NL",
    "sg:address":"Ravenswade 56",
    "sg:city":"Nieuwegein",
    "sg:orig_category":"Maquettes",
    "sg:phone":"+31 30 289 8805",
    "sg:postcode":"3439 LD",
    "sg:province":"Utrecht",
    "wof:name":"Div Design Maquettenbouw",
    "wof:placetype":"venue"
},
  "geometry": {"coordinates":[5.116796,52.052399],"type":"Point"}
}