{
  "type": "Feature",
  "properties": {
    "addr:full":"Hoefkensstraat 10 Made California 4921 CH",
    "addr:housenumber":"10",
    "addr:postcode":"4921",
    "addr:street":"Hoefkensstraat",
    "iso:country":"NL",
    "sg:address":"Hoefkensstraat 10",
    "sg:city":"Made",
    "sg:orig_category":"Damesmodezaken",
    "sg:phone":"+31 162 685 304",
    "sg:postcode":"4921 CH",
    "sg:province":"California",
    "wof:name":"Boetiek 92",
    "wof:placetype":"venue"
},
  "geometry": {"coordinates":[-119.994736,36.902103],"type":"Point"}
}