{
  "type": "Feature",
  "properties": {
    "addr:full":"Paddestoelenln 50 Veenendaal Utrecht 3903 GG",
    "addr:housenumber":"50",
    "addr:postcode":"3903 gg",
    "addr:street":"Paddestoelenln",
    "iso:country":"NL",
    "sg:address":"Paddestoelenln 50",
    "sg:city":"Veenendaal",
    "sg:orig_category":"Bloemen En Planten",
    "sg:phone":"+31 318 589 260",
    "sg:postcode":"3903 GG",
    "sg:province":"Utrecht",
    "wof:name":"Wilgenteen, De",
    "wof:placetype":"venue"
},
  "geometry": {"coordinates":[5.555206,52.005585],"type":"Point"}
}