{
  "type": "Feature",
  "properties": {
    "addr:full":"W Barentszstr 5 Utrecht Utrecht 3572 PA",
    "addr:housenumber":"5",
    "addr:postcode":"3572",
    "addr:street":"W",
    "iso:country":"NL",
    "sg:address":"W Barentszstr 5",
    "sg:city":"Utrecht",
    "sg:orig_category":"Verenigingen En Stichtingen",
    "sg:phone":"+31 30 275 3300",
    "sg:postcode":"3572 PA",
    "sg:province":"Utrecht",
    "sg:website":"http://www.nedernet.nl/~hens",
    "wof:name":"Handicap & Studie, Sticht",
    "wof:placetype":"venue"
},
  "geometry": {"coordinates":[5.141273,52.096245],"type":"Point"}
}