{
  "type": "Feature",
  "properties": {
    "iso:country":"NL",
    "sg:address":"Krachtenveld 41",
    "sg:city":"Zeewolde",
    "sg:orig_category":"Loodgieterswerk, Verwarming And Sanitaire Installaties",
    "sg:phone":"+31 36 522 2768",
    "sg:postcode":"3893 CD",
    "sg:province":"NL.",
    "wof:name":"Houtlosser Klussen-En Onderhoudsbedrijf",
    "wof:placetype":"venue"
},
  "geometry": {"coordinates":[5.524413,52.330566],"type":"Point"}
}