{
  "type": "Feature",
  "properties": {
    "addr:full":"Nijverheidsweg 30 Oisterwijk Noord-Brabant 5061 KL",
    "addr:housenumber":"30",
    "addr:postcode":"5061 kl",
    "addr:street":"Nijverheidsweg",
    "iso:country":"NL",
    "sg:address":"Nijverheidsweg 30",
    "sg:city":"Oisterwijk",
    "sg:orig_category":"Medische And Orthopedische Artikelen",
    "sg:phone":"+31 13 523 9380",
    "sg:postcode":"5061 KL",
    "sg:province":"Noord-Brabant",
    "wof:name":"Revato Bv",
    "wof:placetype":"venue"
},
  "geometry": {"coordinates":[5.188562,51.583908],"type":"Point"}
}