{
  "type": "Feature",
  "properties": {
    "iso:country":"NL",
    "sg:address":"Larensewg 12",
    "sg:city":"Holten",
    "sg:orig_category":"Projectontwikkeling",
    "sg:phone":"+31 548 366 001",
    "sg:postcode":"7451 EN",
    "sg:province":"NL.08",
    "wof:name":"Esprit Planontwikkeling Bv",
    "wof:placetype":"venue"
},
  "geometry": {"coordinates":[6.420605,52.281204],"type":"Point"}
}