{
  "type": "Feature",
  "properties": {
    "addr:full":"Merenweg 2 Wintelre Noord-Brabant 5513 NZ",
    "addr:housenumber":"2",
    "addr:postcode":"5513 nz",
    "addr:street":"Merenweg",
    "iso:country":"NL",
    "sg:address":"Merenweg 2",
    "sg:city":"Wintelre",
    "sg:orig_category":"Sportcentra",
    "sg:phone":"+31 40 205 1916",
    "sg:postcode":"5513 NZ",
    "sg:province":"Noord-Brabant",
    "wof:name":"Sportpark De Meren",
    "wof:placetype":"venue"
},
  "geometry": {"coordinates":[170.36663799999999,-43.587711],"type":"Point"}
}