{
  "type": "Feature",
  "properties": {
    "addr:full":"Heerenwg 57-11 Barsingerhorn Noord-Holland 1768 BH",
    "addr:housenumber":"57-11",
    "addr:postcode":"barsingerhorn;1768 bh",
    "iso:country":"NL",
    "sg:address":"Heerenwg 57-11",
    "sg:city":"Barsingerhorn",
    "sg:orig_category":"Psychotherapeuten",
    "sg:phone":"+31 224 533 024",
    "sg:postcode":"1768 BH",
    "sg:province":"Noord-Holland",
    "wof:name":"Gestalttherapie/Lichaamswerk",
    "wof:placetype":"venue"
},
  "geometry": {"coordinates":[4.851749,52.784496],"type":"Point"}
}