{
  "type": "Feature",
  "properties": {
    "addr:full":"De Karekiet 75A Almelo Overijssel 7609 KA",
    "addr:housenumber":"75a",
    "addr:postcode":"7609 ka",
    "addr:street":"De Karekiet",
    "iso:country":"NL",
    "sg:address":"De Karekiet 75A",
    "sg:city":"Almelo",
    "sg:orig_category":"Woningbouw- Verenigingen En -Stichtingen",
    "sg:phone":"+31 546 827 803",
    "sg:postcode":"7609 KA",
    "sg:province":"Overijssel",
    "wof:name":"Wooncentr Windmolenbroek",
    "wof:placetype":"venue"
},
  "geometry": {"coordinates":[6.6307020187,52.3347625732],"type":"Point"}
}