{
  "type": "Feature",
  "properties": {
    "addr:full":"Rysbergsewg 334 Breda Noord-Brabant 4838 EG",
    "addr:housenumber":"334",
    "addr:postcode":"4838 eg",
    "iso:country":"NL",
    "sg:address":"Rysbergsewg 334",
    "sg:city":"Breda",
    "sg:orig_category":"Autorijscholen",
    "sg:phone":"+31 76 514 3377",
    "sg:postcode":"4838 EG",
    "sg:province":"Noord-Brabant",
    "wof:name":"Herba",
    "wof:placetype":"venue"
},
  "geometry": {"coordinates":[4.731552,51.555595],"type":"Point"}
}