{
  "type": "Feature",
  "properties": {
    "iso:country":"NL",
    "sg:address":"Stadhouderskade 18",
    "sg:city":"Schiedam",
    "sg:orig_category":"Koeriersdiensten",
    "sg:phone":"+31 10 473 2551",
    "sg:postcode":"3116 HB",
    "sg:province":"Zuid-Holland",
    "wof:name":"Fast Forward",
    "wof:placetype":"venue"
},
  "geometry": {"coordinates":[4.39962,51.907478],"type":"Point"}
}