{
  "type": "Feature",
  "properties": {
    "addr:full":"Kruisvaardersstr 41 Tilburg Noord-Brabant 5021 BB",
    "addr:housenumber":"41",
    "addr:postcode":"5021 bb",
    "addr:street":"Kruisvaardersstr",
    "iso:country":"NL",
    "sg:address":"Kruisvaardersstr 41",
    "sg:city":"Tilburg",
    "sg:orig_category":"Psychologen",
    "sg:phone":"+31 13 580 1991",
    "sg:postcode":"5021 BB",
    "sg:province":"Noord-Brabant",
    "wof:name":"Advies- En Behandeling",
    "wof:placetype":"venue"
},
  "geometry": {"coordinates":[5.098993,51.550179],"type":"Point"}
}