{
  "type": "Feature",
  "properties": {
    "addr:full":"Adornisdijk 2 Nieuwvliet Zeeland 4504 PW",
    "addr:housenumber":"2",
    "addr:postcode":"4504 pw",
    "addr:street":"Adornisdijk",
    "iso:country":"NL",
    "sg:address":"Adornisdijk 2",
    "sg:city":"Nieuwvliet",
    "sg:orig_category":"Kampeerterreinen",
    "sg:phone":"+31 117 371 660",
    "sg:postcode":"4504 PW",
    "sg:province":"Zeeland",
    "wof:name":"Camping Adornis",
    "wof:placetype":"venue"
},
  "geometry": {"coordinates":[3.4541220665,51.3813285828],"type":"Point"}
}