{
  "type": "Feature",
  "properties": {
    "addr:full":"Dorpsstraat 55 Helmond Noord-Brabant 5708 GD",
    "addr:housenumber":"55",
    "addr:postcode":"5708 gd",
    "addr:street":"Dorpsstraat",
    "iso:country":"NL",
    "sg:address":"Dorpsstraat 55",
    "sg:city":"Helmond",
    "sg:classifiers":[
        {
            "category":"Food & Beverages",
            "subcategory":"Fruits & Vegetables",
            "type":"Retail Goods"
        }
    ],
    "sg:phone":"+31 492 536 013",
    "sg:postcode":"5708 GD",
    "sg:province":"Noord-Brabant",
    "sg:tags":[
        "groenten"
    ],
    "wof:name":"Bertje Manders Groenten En Fruit",
    "wof:placetype":"venue"
},
  "geometry": {"coordinates":[5.62086,51.485752],"type":"Point"}
}