{
  "type": "Feature",
  "properties": {
    "addr:full":"Brandenburglaan 53 Middelburg Zeeland 4333 BX",
    "addr:housenumber":"53",
    "addr:postcode":"4333 bx",
    "addr:street":"Brandenburglaan",
    "iso:country":"NL",
    "sg:address":"Brandenburglaan 53",
    "sg:city":"Middelburg",
    "sg:orig_category":"Bedrijfs- And Managementsconsultants",
    "sg:phone":"+31 118 618 600",
    "sg:postcode":"4333 BX",
    "sg:province":"Zeeland",
    "wof:name":"Pefabo Management Bv",
    "wof:placetype":"venue"
},
  "geometry": {"coordinates":[3.615303,51.511574],"type":"Point"}
}