{
  "type": "Feature",
  "properties": {
    "addr:full":"Nomdenweg 5 Ter Apel Groningen 9561 AM",
    "addr:housenumber":"5",
    "addr:postcode":"9561",
    "addr:street":"Nomdenweg",
    "iso:country":"NL",
    "sg:address":"Nomdenweg 5",
    "sg:city":"Ter Apel",
    "sg:orig_category":"Metaalwerken",
    "sg:phone":"+31 599 589 085",
    "sg:postcode":"9561 AM",
    "sg:province":"Groningen",
    "wof:name":"Have Systeembouw Ter Apel Bv",
    "wof:placetype":"venue"
},
  "geometry": {"coordinates":[7.052188,52.883965],"type":"Point"}
}