{
  "type": "Feature",
  "properties": {
    "addr:full":"C Huygensstr 3 Stryen South Holland 3291 CN",
    "addr:housenumber":"3",
    "addr:postcode":"3291 cn",
    "addr:street":"Stryen South",
    "iso:country":"NL",
    "sg:address":"C Huygensstr 3",
    "sg:city":"Stryen",
    "sg:orig_category":"Meubelen",
    "sg:phone":"+31 78 674 1130",
    "sg:postcode":"3291 CN",
    "sg:province":"South Holland",
    "sg:website":"http://www.trendhopper.nl",
    "wof:name":"Trendhopper",
    "wof:placetype":"venue"
},
  "geometry": {"coordinates":[4.54727,51.750832],"type":"Point"}
}