{
  "type": "Feature",
  "properties": {
    "iso:country":"NL",
    "sg:address":"Berliozstr 19",
    "sg:city":"Waalwyk",
    "sg:orig_category":"Fietsen En Bromfietsen Onderdelen - Fabr. En Grooth",
    "sg:phone":"+31 416 331 113",
    "sg:postcode":"5144 WC",
    "sg:province":"North Brabant",
    "wof:name":"Bink, H",
    "wof:placetype":"venue"
},
  "geometry": {"coordinates":[5.06067,51.675068],"type":"Point"}
}