{
  "type": "Feature",
  "properties": {
    "addr:full":"Onnerwg 75 Haren Gn Groningen 9751 VC",
    "addr:housenumber":"75",
    "addr:postcode":"9751 vc",
    "addr:street":"Onnerwg",
    "iso:country":"NL",
    "sg:address":"Onnerwg 75",
    "sg:city":"Haren Gn",
    "sg:orig_category":"Juridische Adviseurs",
    "sg:phone":"+31 50 534 0280",
    "sg:postcode":"9751 VC",
    "sg:province":"Groningen",
    "wof:name":"Breewer",
    "wof:placetype":"venue"
},
  "geometry": {"coordinates":[6.622269,53.165192],"type":"Point"}
}