{
  "type": "Feature",
  "properties": {
    "iso:country":"NL",
    "sg:address":"Volterbeek 2",
    "sg:city":"Zwolle",
    "sg:orig_category":"Opvangtehuizen",
    "sg:phone":"+31 38 453 7770",
    "sg:postcode":"8033 CZ",
    "sg:province":"Overijssel",
    "wof:name":"Vrouwenopvang Aan De Ijssel",
    "wof:placetype":"venue"
},
  "geometry": {"coordinates":[6.1097412109,52.5354309082],"type":"Point"}
}