{
  "type": "Feature",
  "properties": {
    "iso:country":"NL",
    "sg:address":"Mattenvlechter 2",
    "sg:city":"Veenhuizen",
    "sg:orig_category":"Begrafenisondernemers",
    "sg:phone":"+31 592 388 226",
    "sg:postcode":"9341 CB",
    "sg:province":"Drenthe",
    "wof:name":"Begrafenisver. Veenhuizen",
    "wof:placetype":"venue"
},
  "geometry": {"coordinates":[6.39294,53.030365],"type":"Point"}
}