{
  "type": "Feature",
  "properties": {
    "addr:full":"Industrieweg 8 Den Helder North Holland 1785 AG",
    "addr:housenumber":"8",
    "addr:postcode":"1785",
    "addr:street":"Industrieweg",
    "iso:country":"NL",
    "sg:address":"Industrieweg 8",
    "sg:city":"Den Helder",
    "sg:orig_category":"Bouwmaterialen Gh",
    "sg:phone":"+31 223 632 224",
    "sg:postcode":"1785 AG",
    "sg:province":"North Holland",
    "wof:name":"Bbn Bouwcenter",
    "wof:placetype":"venue"
},
  "geometry": {"coordinates":[4.773278,52.943958],"type":"Point"}
}