{
  "type": "Feature",
  "properties": {
    "addr:full":"Europapln 1 Volendam North Holland 1131 ZK",
    "addr:housenumber":"1",
    "addr:postcode":"1131",
    "addr:street":"Europapln;Zk",
    "iso:country":"NL",
    "sg:address":"Europapln 1",
    "sg:city":"Volendam",
    "sg:orig_category":"Postkantoren",
    "sg:phone":"+31 299 363 640",
    "sg:postcode":"1131 ZK",
    "sg:province":"North Holland",
    "sg:website":"http://www.postkantoor.nl",
    "wof:name":"Postkantoor",
    "wof:placetype":"venue"
},
  "geometry": {"coordinates":[5.073008,52.493896],"type":"Point"}
}