{
  "type": "Feature",
  "properties": {
    "addr:full":"Spijksedijk 14 Gorinchem Zuid-Holland 4207 GN",
    "addr:housenumber":"14",
    "addr:postcode":"4207 gn",
    "addr:street":"Spijksedijk",
    "iso:country":"NL",
    "sg:address":"Spijksedijk 14",
    "sg:city":"Gorinchem",
    "sg:orig_category":"Accountants - Administratie- Consulenten En -Kantoren",
    "sg:phone":"+31 183 356 767",
    "sg:postcode":"4207 GN",
    "sg:province":"Zuid-Holland",
    "wof:name":"Noord Bv, Van",
    "wof:placetype":"venue"
},
  "geometry": {"coordinates":[4.98227,51.83532],"type":"Point"}
}