{
  "type": "Feature",
  "properties": {
    "addr:full":"Schepersweg 5 Well Lb Limburg 5855 GG",
    "addr:housenumber":"5",
    "addr:postcode":"lb;5855 gg",
    "addr:street":"Schepersweg",
    "iso:country":"NL",
    "sg:address":"Schepersweg 5",
    "sg:city":"Well Lb",
    "sg:orig_category":"Verhuur Audiovisuele Apparatuur",
    "sg:phone":"+31 478 501 760",
    "sg:postcode":"5855 GG",
    "sg:province":"Limburg",
    "wof:name":"Koch Geluidsapparatuur Verhuur",
    "wof:placetype":"venue"
},
  "geometry": {"coordinates":[-93.129936,36.705662],"type":"Point"}
}