{
  "type": "Feature",
  "properties": {
    "iso:country":"NL",
    "sg:address":"Dromedarisstr 38",
    "sg:city":"Nymegen",
    "sg:orig_category":"Administratie- En Boekhoudkantoren",
    "sg:phone":"+31 24 355 1696",
    "sg:postcode":"6531 NV",
    "sg:province":"Gelderland",
    "wof:name":"Luiten",
    "wof:placetype":"venue"
},
  "geometry": {"coordinates":[-117.02272000000001,38.50246],"type":"Point"}
}