{
  "type": "Feature",
  "properties": {
    "addr:full":"Berninkholthoek 51 Enschede Overijssel 7546 CD",
    "addr:housenumber":"51",
    "addr:postcode":"7546 cd",
    "addr:street":"Berninkholthoek",
    "iso:country":"NL",
    "sg:address":"Berninkholthoek 51",
    "sg:city":"Enschede",
    "sg:orig_category":"Bloemen And Planten",
    "sg:phone":"+31 53 477 5740",
    "sg:postcode":"7546 CD",
    "sg:province":"Overijssel",
    "wof:name":"Vof A.T. Zijlstra",
    "wof:placetype":"venue"
},
  "geometry": {"coordinates":[6.854728,52.18898],"type":"Point"}
}