{
  "type": "Feature",
  "properties": {
    "iso:country":"NL",
    "sg:address":"Rijsenburgerweg 30",
    "sg:city":"Poeldijk",
    "sg:orig_category":"Makelaars In Onroerend Goed",
    "sg:phone":"+31 174 624 325",
    "sg:postcode":"2685  E",
    "sg:province":"South Holland",
    "wof:name":"Henk Scholtes Onroerend Goed",
    "wof:placetype":"venue"
},
  "geometry": {"coordinates":[4.218725,52.021709],"type":"Point"}
}