{
  "type": "Feature",
  "properties": {
    "addr:full":"Meddosestr 9 Winterswijk Gelderland 7101 CS",
    "addr:housenumber":"9",
    "addr:postcode":"7101 cs",
    "addr:street":"Meddosestr;Gelderland",
    "iso:country":"NL",
    "sg:address":"Meddosestr 9",
    "sg:city":"Winterswijk",
    "sg:orig_category":"Apotheken",
    "sg:phone":"+31 543 520 200",
    "sg:postcode":"7101 CS",
    "sg:province":"Gelderland",
    "wof:name":"Slinge, De",
    "wof:placetype":"venue"
},
  "geometry": {"coordinates":[6.719814,51.972897],"type":"Point"}
}