{
  "type": "Feature",
  "properties": {
    "addr:full":"Strijpestraat 158 Eindhoven North Brabant 5616  G",
    "addr:housenumber":"158;g",
    "addr:postcode":"5616",
    "addr:street":"Strijpestraat",
    "iso:country":"NL",
    "sg:address":"Strijpestraat 158",
    "sg:city":"Eindhoven",
    "sg:orig_category":"Kappers",
    "sg:phone":"+31 40 251 8029",
    "sg:postcode":"5616  G",
    "sg:province":"North Brabant",
    "wof:name":"Peels Haarmode",
    "wof:placetype":"venue"
},
  "geometry": {"coordinates":[5.46007,51.439308],"type":"Point"}
}