{
  "type": "Feature",
  "properties": {
    "iso:country":"NL",
    "sg:address":"Heijermansstraat 20",
    "sg:city":"Utrecht",
    "sg:orig_category":"Partycatering And -Organisatie",
    "sg:phone":"+31 30 293 3931",
    "sg:postcode":"3532 EH",
    "sg:province":"Utrecht",
    "wof:name":"De Thuiskok",
    "wof:placetype":"venue"
},
  "geometry": {"coordinates":[5.092188,52.095459],"type":"Point"}
}