{
  "type": "Feature",
  "properties": {
    "iso:country":"NL",
    "sg:address":"P Calandln 230 Vrouwencentr Xenia",
    "sg:city":"Amsterdam",
    "sg:orig_category":"Verenigingsgebouwen",
    "sg:phone":"+31 20 619 8765",
    "sg:postcode":"1069 LA",
    "sg:province":"Noord-Holland",
    "wof:name":"Xenia",
    "wof:placetype":"venue"
},
  "geometry": {"coordinates":[4.78913,52.35305],"type":"Point"}
}