{
  "type": "Feature",
  "properties": {
    "addr:full":"Spijcklaan 1 Harmelen Utrecht 3481 GZ",
    "addr:housenumber":"1",
    "addr:postcode":"3481 gz",
    "addr:street":"Spijcklaan",
    "iso:country":"NL",
    "sg:address":"Spijcklaan 1",
    "sg:city":"Harmelen",
    "sg:orig_category":"Loodgieterswerk, Verwarming And Sanitaire Installaties",
    "sg:phone":"+31 348 443 889",
    "sg:postcode":"3481 GZ",
    "sg:province":"Utrecht",
    "wof:name":"Klusbedrijf Werring",
    "wof:placetype":"venue"
},
  "geometry": {"coordinates":[4.972389,52.103195],"type":"Point"}
}