{
  "type": "Feature",
  "properties": {
    "addr:full":"Turfkd 13 Almelo NL.08 7602 PA",
    "addr:housenumber":"13;nl.08",
    "addr:postcode":"7602",
    "addr:street":"Turfkd",
    "iso:country":"NL",
    "sg:address":"Turfkd 13",
    "sg:city":"Almelo",
    "sg:orig_category":"Machinefabrieken",
    "sg:phone":"+31 546 488 800",
    "sg:postcode":"7602 PA",
    "sg:province":"NL.08",
    "sg:website":"http://www.boessenkoolbv.nl",
    "wof:name":"Boessenkool Vof",
    "wof:placetype":"venue"
},
  "geometry": {"coordinates":[6.664543,52.354954],"type":"Point"}
}