{
  "type": "Feature",
  "properties": {
    "addr:full":"Stenen Brug 18 Landgraaf Limburg 6372 AP",
    "addr:housenumber":"18",
    "addr:postcode":"6372 ap",
    "addr:street":"Stenen Brug",
    "iso:country":"NL",
    "sg:address":"Stenen Brug 18",
    "sg:city":"Landgraaf",
    "sg:orig_category":"Gordijnstoffen - Fabrieken En Groothandel",
    "sg:phone":"+31 45 531 6448",
    "sg:postcode":"6372 AP",
    "sg:province":"Limburg",
    "wof:name":"Hedefa Bv",
    "wof:placetype":"venue"
},
  "geometry": {"coordinates":[6.02103,50.892117],"type":"Point"}
}