{
  "type": "Feature",
  "properties": {
    "addr:full":"Watercirkel 4 Amstelveen Noord-Holland 1186 LV",
    "addr:housenumber":"4",
    "addr:postcode":"1186",
    "addr:street":"Watercirkel",
    "iso:country":"NL",
    "sg:address":"Watercirkel 4",
    "sg:city":"Amstelveen",
    "sg:orig_category":"Airconditioning And Ventilatie",
    "sg:phone":"+31 20 647 8965",
    "sg:postcode":"1186 LV",
    "sg:province":"Noord-Holland",
    "wof:name":"Tvb",
    "wof:placetype":"venue"
},
  "geometry": {"coordinates":[4.867149,52.28709],"type":"Point"}
}