{
  "type": "Feature",
  "properties": {
    "iso:country":"NL",
    "sg:address":"Buys Ballotstraat 9",
    "sg:city":"Winterswijk",
    "sg:orig_category":"Huisdierenvoer Fab",
    "sg:phone":"+31 543 514 079",
    "sg:postcode":"7102 EA",
    "sg:province":"Gelderland",
    "wof:name":"Mulder Vof Diepvries- Diervoeding En Slachtprodukt",
    "wof:placetype":"venue"
},
  "geometry": {"coordinates":[6.718188,51.960575],"type":"Point"}
}