{
  "type": "Feature",
  "properties": {
    "addr:full":"Spakenburgstr 62 Amsterdam Zuidoost Noord-Holland 1107 WS",
    "addr:housenumber":"62",
    "addr:postcode":"zuidoost;1107 ws",
    "addr:street":"Spakenburgstr",
    "iso:country":"NL",
    "sg:address":"Spakenburgstr 62",
    "sg:city":"Amsterdam Zuidoost",
    "sg:orig_category":"Autorijscholen",
    "sg:phone":"+31 20 696 0899",
    "sg:postcode":"1107 WS",
    "sg:province":"Noord-Holland",
    "wof:name":"Ijsselstein, R",
    "wof:placetype":"venue"
},
  "geometry": {"coordinates":[4.979044,52.291424],"type":"Point"}
}