{
  "type": "Feature",
  "properties": {
    "iso:country":"NL",
    "sg:address":"Badhuisweg 10",
    "sg:city":"Zutphen",
    "sg:orig_category":"Artiesten",
    "sg:phone":"+31 575 519 700",
    "sg:postcode":"7201 GN",
    "sg:province":"Gelderland",
    "wof:name":"J Bos",
    "wof:placetype":"venue"
},
  "geometry": {"coordinates":[6.193145,52.135303],"type":"Point"}
}