{
  "type": "Feature",
  "properties": {
    "addr:full":"J Wattstr 10 Gouda South Holland 2809 PA",
    "addr:housenumber":"10",
    "addr:postcode":"2809 pa",
    "iso:country":"NL",
    "sg:address":"J Wattstr 10",
    "sg:city":"Gouda",
    "sg:orig_category":"Kantoor- En Bedrijfsmeubelen - Fabrieken En Groothandel",
    "sg:phone":"+31 182 615 255",
    "sg:postcode":"2809 PA",
    "sg:province":"South Holland",
    "sg:website":"http://www.buropa.nl",
    "wof:name":"Buropa Projectmeubelen & Int Bv",
    "wof:placetype":"venue"
},
  "geometry": {"coordinates":[4.6903882027,52.0065078735],"type":"Point"}
}