{
  "type": "Feature",
  "properties": {
    "addr:full":"Ooievaarsln 14 Sneek Friesland 8601 XN",
    "addr:housenumber":"14",
    "addr:postcode":"8601 xn",
    "addr:street":"Ooievaarsln",
    "iso:country":"NL",
    "sg:address":"Ooievaarsln 14",
    "sg:city":"Sneek",
    "sg:orig_category":"Directmail",
    "sg:phone":"+31 515 426 826",
    "sg:postcode":"8601 XN",
    "sg:province":"Friesland",
    "sg:website":"http://www.nedart.nl",
    "wof:name":"Nedart Communicatie Bv",
    "wof:placetype":"venue"
},
  "geometry": {"coordinates":[5.66197,53.033459],"type":"Point"}
}