{
  "type": "Feature",
  "properties": {
    "addr:full":"M V Osstr 49 Ede Gld Gelderland 6717 TJ",
    "addr:housenumber":"49",
    "addr:postcode":"6717 tj",
    "addr:street":"Osstr;Gld Gelderland",
    "iso:country":"NL",
    "sg:address":"M V Osstr 49",
    "sg:city":"Ede Gld",
    "sg:orig_category":"Metselwerken",
    "sg:phone":"+31 318 624 428",
    "sg:postcode":"6717 TJ",
    "sg:province":"Gelderland",
    "wof:name":"Pieters, W",
    "wof:placetype":"venue"
},
  "geometry": {"coordinates":[5.66767,52.044979],"type":"Point"}
}