{
  "type": "Feature",
  "properties": {
    "addr:full":"Toom 25 Budel Noord-Brabant 6021 RT",
    "addr:housenumber":"25",
    "addr:postcode":"6021 rt",
    "addr:street":"Toom",
    "iso:country":"NL",
    "sg:address":"Toom 25",
    "sg:city":"Budel",
    "sg:orig_category":"Metaalwerken",
    "sg:phone":"+31 495 494 656",
    "sg:postcode":"6021 RT",
    "sg:province":"Noord-Brabant",
    "wof:name":"Stucadoorsbedrijf Van Moorsel",
    "wof:placetype":"venue"
},
  "geometry": {"coordinates":[5.559459,51.268372],"type":"Point"}
}