{
  "type": "Feature",
  "properties": {
    "addr:full":"Randwg 31 Oud Beyerland Zuid-Holland 3263 RA",
    "addr:housenumber":"31",
    "addr:postcode":"3263 ra",
    "addr:street":"Randwg;Oud Beyerland",
    "iso:country":"NL",
    "sg:address":"Randwg 31",
    "sg:city":"Oud Beyerland",
    "sg:classifiers":[
        {
            "category":"Sports & Exercise",
            "subcategory":"Stables",
            "type":"Entertainment"
        }
    ],
    "sg:phone":"+31 186 617 266",
    "sg:postcode":"3263 RA",
    "sg:province":"Zuid-Holland",
    "sg:tags":[
        "maneges"
    ],
    "sg:website":"http://www.rv-oud-beijerland.nl",
    "wof:name":"Hoeksche Waard, De",
    "wof:placetype":"venue"
},
  "geometry": {"coordinates":[4.389603,51.822243],"type":"Point"}
}