{
  "type": "Feature",
  "properties": {
    "addr:full":"Pannekoekstraat 81 Rotterdam Zuid-Holland 3011 LD",
    "addr:housenumber":"81",
    "addr:postcode":"3011 ld",
    "addr:street":"Pannekoekstraat",
    "iso:country":"NL",
    "sg:address":"Pannekoekstraat 81",
    "sg:city":"Rotterdam",
    "sg:orig_category":"Kappers",
    "sg:phone":"+31 10 412 0155",
    "sg:postcode":"3011 LD",
    "sg:province":"Zuid-Holland",
    "wof:name":"Bizzy Hairfashion C.V.",
    "wof:placetype":"venue"
},
  "geometry": {"coordinates":[4.4885230064,51.9222488403],"type":"Point"}
}