{
  "type": "Feature",
  "properties": {
    "addr:full":"Wg Pln 11 Amsterdam Noord-Holland 1054 RA",
    "addr:housenumber":"11",
    "addr:postcode":"1054 ra",
    "addr:street":"Wg Pln",
    "iso:country":"NL",
    "sg:address":"Wg Pln 11",
    "sg:city":"Amsterdam",
    "sg:orig_category":"Architecten En Architectenbureaus",
    "sg:phone":"+31 20 683 3678",
    "sg:postcode":"1054 RA",
    "sg:province":"Noord-Holland",
    "wof:name":"Evelo Van Den Berg",
    "wof:placetype":"venue"
},
  "geometry": {"coordinates":[4.87137,52.363411],"type":"Point"}
}