{
  "type": "Feature",
  "properties": {
    "addr:full":"Kloosterlaan 25 Sas Van Gent Zeeland 4551 BA",
    "addr:housenumber":"25",
    "addr:postcode":"4551 ba",
    "addr:street":"Kloosterlaan",
    "iso:country":"NL",
    "sg:address":"Kloosterlaan 25",
    "sg:city":"Sas Van Gent",
    "sg:orig_category":"Postorderbedrijven",
    "sg:phone":"+31 800 0220554",
    "sg:postcode":"4551 BA",
    "sg:province":"Zeeland",
    "wof:name":"Euro Nutri Bv",
    "wof:placetype":"venue"
},
  "geometry": {"coordinates":[3.798267,51.228596],"type":"Point"}
}