{
  "type": "Feature",
  "properties": {
    "addr:full":"Rapenburgerstr 109 Amsterdam North Holland 1011 VL",
    "addr:housenumber":"109",
    "addr:postcode":"1011 vl",
    "iso:country":"NL",
    "sg:address":"Rapenburgerstr 109",
    "sg:city":"Amsterdam",
    "sg:orig_category":"Belastingconsulenten/ Belastingadviseurs",
    "sg:phone":"+31 20 627 6367",
    "sg:postcode":"1011 VL",
    "sg:province":"North Holland",
    "wof:name":"Sleutelberg",
    "wof:placetype":"venue"
},
  "geometry": {"coordinates":[4.906954,52.368629],"type":"Point"}
}