{
  "type": "Feature",
  "properties": {
    "addr:full":"Roggeveld 7 Didam Gelderland 6942 MB",
    "addr:housenumber":"7",
    "addr:postcode":"6942 mb",
    "addr:street":"Roggeveld;Gelderland",
    "iso:country":"NL",
    "sg:address":"Roggeveld 7",
    "sg:city":"Didam",
    "sg:orig_category":"Administratie- En Boekhoudkantoren",
    "sg:phone":"+31 316 226 645",
    "sg:postcode":"6942 MB",
    "sg:province":"Gelderland",
    "wof:name":"Caff Office",
    "wof:placetype":"venue"
},
  "geometry": {"coordinates":[6.140224,51.942627],"type":"Point"}
}