{
  "type": "Feature",
  "properties": {
    "addr:full":"Talmastraat 87 Breda North Brabant 4812 KA",
    "addr:housenumber":"87",
    "addr:postcode":"4812 ka",
    "addr:street":"Talmastraat",
    "iso:country":"NL",
    "sg:address":"Talmastraat 87",
    "sg:city":"Breda",
    "sg:orig_category":"Overheidsdiensten",
    "sg:phone":"+31 76 522 6625",
    "sg:postcode":"4812 KA",
    "sg:province":"North Brabant",
    "wof:name":"Sjah Jongerencentrum",
    "wof:placetype":"venue"
},
  "geometry": {"coordinates":[4.7529611588,51.5714988708],"type":"Point"}
}