{
  "type": "Feature",
  "properties": {
    "addr:full":"Noorderveemarkt 1 Hoorn Nh Noord-Holland 1621 JJ",
    "addr:housenumber":"1",
    "addr:postcode":"1621 jj",
    "addr:street":"Noorderveemarkt",
    "iso:country":"NL",
    "sg:address":"Noorderveemarkt 1",
    "sg:city":"Hoorn Nh",
    "sg:orig_category":"Werving And Selectie Van Tijdelijk Personeel And Uitzendkantoren",
    "sg:phone":"+31 229 285 600",
    "sg:postcode":"1621 JJ",
    "sg:province":"Noord-Holland",
    "wof:name":"Randstad Uitzendbureau Bv",
    "wof:placetype":"venue"
},
  "geometry": {"coordinates":[5.0521202087,52.6443061829],"type":"Point"}
}