{
  "type": "Feature",
  "properties": {
    "iso:country":"NL",
    "sg:address":"Ahornstraat 28",
    "sg:city":"Winterswijk",
    "sg:orig_category":"Boekhouders",
    "sg:phone":"+31 543 516 146",
    "sg:postcode":"7101 LB",
    "sg:province":"Gelderland",
    "wof:name":"Administratiekantoor W.I. Pietersz",
    "wof:placetype":"venue"
},
  "geometry": {"coordinates":[6.738251,51.97411],"type":"Point"}
}