{
  "type": "Feature",
  "properties": {
    "addr:full":"Koopmansstr 115 Lelystad NL. 8223 AH",
    "addr:housenumber":"115",
    "addr:postcode":"8223 ah",
    "addr:street":"Koopmansstr;Nl.",
    "iso:country":"NL",
    "sg:address":"Koopmansstr 115",
    "sg:city":"Lelystad",
    "sg:orig_category":"Fitnesscentra",
    "sg:phone":"+31 320 233 377",
    "sg:postcode":"8223 AH",
    "sg:province":"NL.",
    "wof:name":"Medi-Gym",
    "wof:placetype":"venue"
},
  "geometry": {"coordinates":[5.485244,52.520191],"type":"Point"}
}