{
  "type": "Feature",
  "properties": {
    "addr:full":"Nw Hemwg 4D Amsterdam Noord-Holland 1013 BG",
    "addr:housenumber":"4d",
    "addr:postcode":"1013",
    "iso:country":"NL",
    "sg:address":"Nw Hemwg 4D",
    "sg:city":"Amsterdam",
    "sg:orig_category":"Kantoor- En Bedrijfsmeubelen",
    "sg:phone":"+31 20 623 1722",
    "sg:postcode":"1013 BG",
    "sg:province":"Noord-Holland",
    "sg:website":"http://www.zwakenberg.nl",
    "wof:name":"Zwakenberg",
    "wof:placetype":"venue"
},
  "geometry": {"coordinates":[4.8665719032,52.3948440552],"type":"Point"}
}