{
  "type": "Feature",
  "properties": {
    "addr:full":"Poldermolen 10 Molenaarsgraaf Zuid-Holland 2973 AT",
    "addr:housenumber":"10",
    "addr:postcode":"2973",
    "addr:street":"Poldermolen",
    "iso:country":"NL",
    "sg:address":"Poldermolen 10",
    "sg:city":"Molenaarsgraaf",
    "sg:orig_category":"Kantoor- En Secretariaatsservice",
    "sg:phone":"+31 184 691 073",
    "sg:postcode":"2973 AT",
    "sg:province":"Zuid-Holland",
    "wof:name":"Slingerland, J",
    "wof:placetype":"venue"
},
  "geometry": {"coordinates":[4.8211698532,51.8761749268],"type":"Point"}
}