{
  "type": "Feature",
  "properties": {
    "addr:full":"Sweelinckln 55 Ede Gld Gelderland 6711 ET",
    "addr:housenumber":"55",
    "addr:postcode":"6711 et",
    "addr:street":"Sweelinckln;Gld Gelderland",
    "iso:country":"NL",
    "sg:address":"Sweelinckln 55",
    "sg:city":"Ede Gld",
    "sg:orig_category":"Adviesbureaus Bouwkunde",
    "sg:phone":"+31 318 616 449",
    "sg:postcode":"6711 ET",
    "sg:province":"Gelderland",
    "wof:name":"Bbm Bv",
    "wof:placetype":"venue"
},
  "geometry": {"coordinates":[5.682676,52.045628],"type":"Point"}
}