{
  "type": "Feature",
  "properties": {
    "iso:country":"NL",
    "sg:address":"Zydelveld 30",
    "sg:city":"Uithoorn",
    "sg:orig_category":"Marktkramen",
    "sg:phone":"+31 297 561 455",
    "sg:postcode":"1421 TJ",
    "sg:province":"Noord-Holland",
    "wof:name":"Uithol, W G",
    "wof:placetype":"venue"
},
  "geometry": {"coordinates":[4.82607,52.234859],"type":"Point"}
}