{
  "type": "Feature",
  "properties": {
    "addr:full":"Nieuwstr 7 Best Noord-Brabant 5683 KA",
    "addr:housenumber":"7",
    "addr:postcode":"5683 ka",
    "addr:street":"Nieuwstr",
    "iso:country":"NL",
    "sg:address":"Nieuwstr 7",
    "sg:city":"Best",
    "sg:orig_category":"Exploitatie- Maatschappijen",
    "sg:phone":"+31 499 391 618",
    "sg:postcode":"5683 KA",
    "sg:province":"Noord-Brabant",
    "wof:name":"Kievit Tb Bv",
    "wof:placetype":"venue"
},
  "geometry": {"coordinates":[-101.46463799999999,31.196535],"type":"Point"}
}