{
  "type": "Feature",
  "properties": {
    "addr:full":"De Bazellaan 43 Haarlem North Holland 2033 XD",
    "addr:housenumber":"43",
    "addr:postcode":"2033 xd",
    "addr:street":"De Bazellaan",
    "iso:country":"NL",
    "sg:address":"De Bazellaan 43",
    "sg:city":"Haarlem",
    "sg:orig_category":"Film-, Tv- And Videoproductie",
    "sg:phone":"+31 23 545 1075",
    "sg:postcode":"2033 XD",
    "sg:province":"North Holland",
    "wof:name":"Reprezent",
    "wof:placetype":"venue"
},
  "geometry": {"coordinates":[4.666534,52.379005],"type":"Point"}
}