{
  "type": "Feature",
  "properties": {
    "addr:full":"Cornelis Schuytstraat 40 Amsterdam Noord-Holland 1071 JK",
    "addr:housenumber":"40",
    "addr:postcode":"1071 jk",
    "addr:street":"Cornelis Schuytstraat",
    "iso:country":"NL",
    "sg:address":"Cornelis Schuytstraat 40",
    "sg:city":"Amsterdam",
    "sg:orig_category":"Kappers",
    "sg:phone":"+31 20 662 1704",
    "sg:postcode":"1071 JK",
    "sg:province":"Noord-Holland",
    "wof:name":"Kapsalon De Haan",
    "wof:placetype":"venue"
},
  "geometry": {"coordinates":[4.8715119362,52.3546638489],"type":"Point"}
}