{
  "type": "Feature",
  "properties": {
    "iso:country":"NL",
    "sg:address":"Vredehofstr 16",
    "sg:city":"Spijkenisse",
    "sg:classifiers":[
        {
            "category":"Retail",
            "subcategory":"Auto Repair",
            "type":"Services"
        }
    ],
    "sg:phone":"+31 181 616 272",
    "sg:postcode":"3201 CV",
    "sg:province":"Zuid-Holland",
    "sg:tags":[
        "garage"
    ],
    "wof:name":"Herrewijnen, B",
    "wof:placetype":"venue"
},
  "geometry": {"coordinates":[4.321729,51.848328],"type":"Point"}
}