{
  "type": "Feature",
  "properties": {
    "iso:country":"NL",
    "sg:address":"Sombeekwg 23",
    "sg:city":"Denekamp",
    "sg:orig_category":"Kappers",
    "sg:phone":"+31 6 53811651",
    "sg:postcode":"7591 AV",
    "sg:province":"NL.08",
    "wof:name":"Paulien",
    "wof:placetype":"venue"
},
  "geometry": {"coordinates":[7.030899,52.380627],"type":"Point"}
}