{
  "type": "Feature",
  "properties": {
    "addr:full":"Sombeekwg 23 Denekamp NL.08 7591 AV",
    "addr:housenumber":"23;nl.08",
    "addr:postcode":"7591 av",
    "addr:street":"Sombeekwg",
    "iso:country":"NL",
    "sg:address":"Sombeekwg 23",
    "sg:city":"Denekamp",
    "sg:orig_category":"Kappers",
    "sg:phone":"+31 6 53811651",
    "sg:postcode":"7591 AV",
    "sg:province":"NL.08",
    "wof:name":"Paulien",
    "wof:placetype":"venue"
},
  "geometry": {"coordinates":[7.030899,52.380627],"type":"Point"}
}