{
  "type": "Feature",
  "properties": {
    "addr:full":"Hertogensingel 40 Oss Noord-Brabant 5341 AE",
    "addr:housenumber":"40",
    "addr:postcode":"5341 ae",
    "addr:street":"Hertogensingel",
    "iso:country":"NL",
    "sg:address":"Hertogensingel 40",
    "sg:city":"Oss",
    "sg:orig_category":"Beautyfarms And Sauna'S",
    "sg:phone":"+31 412 622 192",
    "sg:postcode":"5341 AE",
    "sg:province":"Noord-Brabant",
    "wof:name":"J.A. Draaisma-Dupont",
    "wof:placetype":"venue"
},
  "geometry": {"coordinates":[-77.235214,38.312599],"type":"Point"}
}