{
  "type": "Feature",
  "properties": {
    "addr:full":"Duitslandln 6 Hazerswoude Dorp South Holland 2391 PA",
    "addr:housenumber":"6",
    "addr:postcode":"2391 pa",
    "addr:street":"Duitslandln;Dorp",
    "iso:country":"NL",
    "sg:address":"Duitslandln 6",
    "sg:city":"Hazerswoude Dorp",
    "sg:orig_category":"Woninginrichting- Fournituren - Fabrieken En Groothandel",
    "sg:phone":"+31 172 420 927",
    "sg:postcode":"2391 PA",
    "sg:province":"South Holland",
    "wof:name":"Rolarco",
    "wof:placetype":"venue"
},
  "geometry": {"coordinates":[4.6285429001,52.0790405273],"type":"Point"}
}