{
  "type": "Feature",
  "properties": {
    "iso:country":"NL",
    "sg:address":"Schaepeboet 42",
    "sg:city":"Landsmeer",
    "sg:orig_category":"Verenigingen En Stichtingen",
    "sg:phone":"+31 20 482 3852",
    "sg:postcode":"1121 JT",
    "sg:province":"Noord-Holland",
    "wof:name":"Stripschap, Het",
    "wof:placetype":"venue"
},
  "geometry": {"coordinates":[4.907973,52.429054],"type":"Point"}
}