{
  "type": "Feature",
  "properties": {
    "addr:full":"Dorpsstr 39 Nunspeet Gelderland 8071 BX",
    "addr:housenumber":"39",
    "addr:postcode":"8071 bx",
    "addr:street":"Dorpsstr;Gelderland",
    "iso:country":"NL",
    "sg:address":"Dorpsstr 39",
    "sg:city":"Nunspeet",
    "sg:orig_category":"Juweliers",
    "sg:phone":"+31 341 252 171",
    "sg:postcode":"8071 BX",
    "sg:province":"Gelderland",
    "wof:name":"Leusink Van Veen",
    "wof:placetype":"venue"
},
  "geometry": {"coordinates":[5.783532,52.375908],"type":"Point"}
}