{
  "type": "Feature",
  "properties": {
    "iso:country":"NL",
    "sg:address":"Provincialewg 112",
    "sg:city":"Opende",
    "sg:orig_category":"Bloemen En Planten - Groothandel",
    "sg:phone":"+31 594 658 382",
    "sg:postcode":"9865 AL",
    "sg:province":"Groningen",
    "wof:name":"Grondsma, A",
    "wof:placetype":"venue"
},
  "geometry": {"coordinates":[6.209111,53.173855],"type":"Point"}
}