{
  "type": "Feature",
  "properties": {
    "addr:full":"Thorbeckestraat 9 Alblasserdam Zuid-Holland 2953 AP",
    "addr:housenumber":"9",
    "addr:postcode":"2953 ap",
    "addr:street":"Thorbeckestraat",
    "iso:country":"NL",
    "sg:address":"Thorbeckestraat 9",
    "sg:city":"Alblasserdam",
    "sg:orig_category":"Metaalafval, Schrootrecycling And Sloperijen",
    "sg:phone":"+31 78 691 8643",
    "sg:postcode":"2953 AP",
    "sg:province":"Zuid-Holland",
    "wof:name":"Autosloperij En Metaalhandel De Brug",
    "wof:placetype":"venue"
},
  "geometry": {"coordinates":[4.651465,51.869324],"type":"Point"}
}