{
  "type": "Feature",
  "properties": {
    "addr:full":"Maliebaan 83 Utrecht Utrecht 3581 CG",
    "addr:housenumber":"83",
    "addr:postcode":"3581 cg",
    "addr:street":"Maliebaan",
    "iso:country":"NL",
    "sg:address":"Maliebaan 83",
    "sg:city":"Utrecht",
    "sg:orig_category":"Boekenuitgeverijen",
    "sg:phone":"+31 30 234 3436",
    "sg:postcode":"3581 CG",
    "sg:province":"Utrecht",
    "wof:name":"Stichting Icodo",
    "wof:placetype":"venue"
},
  "geometry": {"coordinates":[5.135137,52.091927],"type":"Point"}
}