{
  "type": "Feature",
  "properties": {
    "addr:full":"Plakhorstwg 8 Doetinchem Gelderland 7008 AT",
    "addr:housenumber":"8",
    "addr:postcode":"7008",
    "addr:street":"Plakhorstwg;Gelderland",
    "iso:country":"NL",
    "sg:address":"Plakhorstwg 8",
    "sg:city":"Doetinchem",
    "sg:classifiers":[
        {
            "category":"Retail",
            "subcategory":"Auto Repair",
            "type":"Services"
        }
    ],
    "sg:phone":"+31 314 332 851",
    "sg:postcode":"7008 AT",
    "sg:province":"Gelderland",
    "sg:tags":[
        "garage"
    ],
    "sg:website":"http://www.brandon.nl",
    "wof:name":"Brandon Doetinchem Bv",
    "wof:placetype":"venue"
},
  "geometry": {"coordinates":[6.268369,51.974586],"type":"Point"}
}