{
  "type": "Feature",
  "properties": {
    "addr:full":"Schubertdreef 89 Barendrecht Zuid-Holland 2992 EV",
    "addr:housenumber":"89",
    "addr:street":"Schubertdreef",
    "iso:country":"NL",
    "sg:address":"Schubertdreef 89",
    "sg:city":"Barendrecht",
    "sg:orig_category":"Organisatiebureaus",
    "sg:phone":"+31 180 610 293",
    "sg:postcode":"2992 EV",
    "sg:province":"Zuid-Holland",
    "wof:name":"Mv",
    "wof:placetype":"venue"
},
  "geometry": {"coordinates":[4.5225148201,51.852596283],"type":"Point"}
}