{
  "type": "Feature",
  "properties": {
    "addr:full":"Kwikstaarthoek 7 Spykenisse South Holland 3201 JH",
    "addr:housenumber":"7",
    "addr:postcode":"3201 jh",
    "addr:street":"Kwikstaarthoek",
    "iso:country":"NL",
    "sg:address":"Kwikstaarthoek 7",
    "sg:city":"Spykenisse",
    "sg:orig_category":"Schilders",
    "sg:phone":"+31 6 47430363",
    "sg:postcode":"3201 JH",
    "sg:province":"South Holland",
    "wof:name":"Miranda",
    "wof:placetype":"venue"
},
  "geometry": {"coordinates":[4.325045,51.849525],"type":"Point"}
}