{
  "type": "Feature",
  "properties": {
    "iso:country":"NL",
    "sg:address":"Scheldestr 50",
    "sg:city":"Vlissingen",
    "sg:orig_category":"Autorijscholen",
    "sg:phone":"+31 118 464 660",
    "sg:postcode":"4381 RV",
    "sg:province":"Zeeland",
    "wof:name":"Continental",
    "wof:placetype":"venue"
},
  "geometry": {"coordinates":[3.573541,51.447918],"type":"Point"}
}