{
  "type": "Feature",
  "properties": {
    "iso:country":"NL",
    "sg:address":"Zeelandln 15",
    "sg:city":"Vlaardingen",
    "sg:orig_category":"Glazenwasserijen",
    "sg:phone":"+31 10 474 0659",
    "sg:postcode":"3137 EP",
    "sg:province":"South Holland",
    "wof:name":"Hoeven, P Van Der",
    "wof:placetype":"venue"
},
  "geometry": {"coordinates":[4.358734,51.937546],"type":"Point"}
}