{
  "type": "Feature",
  "properties": {
    "iso:country":"NL",
    "sg:address":"Spuiboulev 314",
    "sg:city":"Dordrecht",
    "sg:classifiers":[
        {
            "category":"Building & Trades",
            "subcategory":"Electrical",
            "type":"Services"
        }
    ],
    "sg:phone":"+31 78 649 2999",
    "sg:postcode":"3311 GR",
    "sg:province":"Zuid-Holland",
    "sg:tags":[
        "distributor"
    ],
    "wof:name":"Blue Fox Enterprises Nv",
    "wof:placetype":"venue"
},
  "geometry": {"coordinates":[4.661709,51.811993],"type":"Point"}
}