{
  "type": "Feature",
  "properties": {
    "iso:country":"NL",
    "sg:address":"F B Deurvorststr 16",
    "sg:city":"Ulft",
    "sg:orig_category":"Verzekeringen - Verzekeringskantoren",
    "sg:phone":"+31 315 345 919",
    "sg:postcode":"7071 BJ",
    "sg:province":"Gelderland",
    "wof:name":"Hypotheekadviseur Ulft, De",
    "wof:placetype":"venue"
},
  "geometry": {"coordinates":[6.38456,51.891129],"type":"Point"}
}