{
  "type": "Feature",
  "properties": {
    "addr:full":"Merel 31 Ridderkerk South Holland 2986 BB",
    "addr:housenumber":"31",
    "addr:postcode":"2986 bb",
    "addr:street":"Merel",
    "iso:country":"NL",
    "sg:address":"Merel 31",
    "sg:city":"Ridderkerk",
    "sg:orig_category":"Administratie- En Boekhoudkantoren",
    "sg:phone":"+31 180 429 034",
    "sg:postcode":"2986 BB",
    "sg:province":"South Holland",
    "wof:name":"Avw",
    "wof:placetype":"venue"
},
  "geometry": {"coordinates":[4.608774,51.86359],"type":"Point"}
}