{
  "type": "Feature",
  "properties": {
    "addr:full":"Lepelaar 3 Velserbroek Noord-Holland 1991 VC",
    "addr:housenumber":"3",
    "addr:postcode":"1991 vc",
    "addr:street":"Lepelaar",
    "iso:country":"NL",
    "sg:address":"Lepelaar 3",
    "sg:city":"Velserbroek",
    "sg:orig_category":"Onderhoudswerken",
    "sg:phone":"+31 23 531 3516",
    "sg:postcode":"1991 VC",
    "sg:province":"Noord-Holland",
    "wof:name":"Kuiper, S",
    "wof:placetype":"venue"
},
  "geometry": {"coordinates":[4.670366,52.430901],"type":"Point"}
}