{
  "type": "Feature",
  "properties": {
    "addr:full":"Parallelwg 36 Emmen Provincie Drenthe 7822 GM",
    "addr:housenumber":"36",
    "addr:postcode":"7822 gm",
    "addr:street":"Parallelwg;Provincie Drenthe",
    "iso:country":"NL",
    "sg:address":"Parallelwg 36",
    "sg:city":"Emmen",
    "sg:orig_category":"Kinderopvang",
    "sg:phone":"+31 591 680 802",
    "sg:postcode":"7822 GM",
    "sg:province":"Provincie Drenthe",
    "sg:website":"http://www.alcides.nl",
    "wof:name":"Alcides Emmen",
    "wof:placetype":"venue"
},
  "geometry": {"coordinates":[6.900084,52.788853],"type":"Point"}
}