{
  "type": "Feature",
  "properties": {
    "iso:country":"NL",
    "sg:address":"Harddraversweg 27",
    "sg:city":"Joure",
    "sg:orig_category":"Juweliers",
    "sg:phone":"+31 513 412 848",
    "sg:postcode":"8501 CJ",
    "sg:province":"Friesland",
    "wof:name":"As Relatieringen Bv",
    "wof:placetype":"venue"
},
  "geometry": {"coordinates":[5.789465,52.96711],"type":"Point"}
}