{
  "type": "Feature",
  "properties": {
    "addr:full":"Wijngaardstraat 34 Goes Zeeland 4461 DC",
    "addr:housenumber":"34",
    "addr:postcode":"4461",
    "addr:street":"Wijngaardstraat",
    "iso:country":"NL",
    "sg:address":"Wijngaardstraat 34",
    "sg:city":"Goes",
    "sg:orig_category":"Watersport-, Sport- And Kampeerbenodigdheden Verhuur",
    "sg:phone":"+31 113 230 804",
    "sg:postcode":"4461 DC",
    "sg:province":"Zeeland",
    "wof:name":"Van Beek Tweewielercentrum",
    "wof:placetype":"venue"
},
  "geometry": {"coordinates":[-83.9141693115,39.7688331604],"type":"Point"}
}