{
  "type": "Feature",
  "properties": {
    "addr:full":"Deurningerstraat 160 Hengelo Ov Overijssel 7557 HK",
    "addr:housenumber":"160",
    "addr:postcode":"7557 hk",
    "addr:street":"Deurningerstraat;Ov",
    "iso:country":"NL",
    "sg:address":"Deurningerstraat 160",
    "sg:city":"Hengelo Ov",
    "sg:classifiers":[
        {
            "category":"Communications",
            "subcategory":"Television Station",
            "type":"Services"
        }
    ],
    "sg:phone":"+31 74 250 0037",
    "sg:postcode":"7557 HK",
    "sg:province":"Overijssel",
    "sg:tags":[
        "video",
        "audio",
        "verhuur"
    ],
    "wof:name":"Video-Riks",
    "wof:placetype":"venue"
},
  "geometry": {"coordinates":[6.804193,52.276348],"type":"Point"}
}