{
  "type": "Feature",
  "properties": {
    "addr:full":"Twiskeweg 80 Zaandam North Holland 1504 AE",
    "addr:housenumber":"80",
    "addr:postcode":"1504 ae",
    "addr:street":"Twiskeweg",
    "iso:country":"NL",
    "sg:address":"Twiskeweg 80",
    "sg:city":"Zaandam",
    "sg:orig_category":"Bejaardeninstellingen And Serviceflats",
    "sg:phone":"+31 75 616 8751",
    "sg:postcode":"1504 AE",
    "sg:province":"North Holland",
    "wof:name":"Stichting Het Erasmushuis",
    "wof:placetype":"venue"
},
  "geometry": {"coordinates":[4.84225,52.440891],"type":"Point"}
}