{
  "type": "Feature",
  "properties": {
    "addr:full":"Leuvensbroek 1010 Nijmegen Gelderland 6546 XB",
    "addr:housenumber":"1010",
    "addr:postcode":"6546 xb",
    "addr:street":"Leuvensbroek;Gelderland",
    "iso:country":"NL",
    "sg:address":"Leuvensbroek 1010",
    "sg:city":"Nijmegen",
    "sg:orig_category":"Bloemen And Planten",
    "sg:phone":"+31 24 379 0109",
    "sg:postcode":"6546 XB",
    "sg:province":"Gelderland",
    "wof:name":"De Orangerie",
    "wof:placetype":"venue"
},
  "geometry": {"coordinates":[5.780532,51.831932],"type":"Point"}
}