{
  "type": "Feature",
  "properties": {
    "addr:full":"1E Broekdk 85 Aalten Gelderland 7122 LD",
    "addr:housenumber":"85",
    "addr:postcode":"7122 ld",
    "addr:street":"1E Broekdk;Gelderland",
    "iso:country":"NL",
    "sg:address":"1E Broekdk 85",
    "sg:city":"Aalten",
    "sg:orig_category":"Weverijen En Spinnerijen",
    "sg:phone":"+31 543 490 000",
    "sg:postcode":"7122 LD",
    "sg:province":"Gelderland",
    "wof:name":"Wisselink-Setex Bv",
    "wof:placetype":"venue"
},
  "geometry": {"coordinates":[6.5668540001,51.9162521362],"type":"Point"}
}