{
  "type": "Feature",
  "properties": {
    "addr:full":"Aleidastr 62B Schiedam Zuid-Holland 3117 DK",
    "addr:housenumber":"62b",
    "addr:postcode":"3117 dk",
    "addr:street":"Aleidastr",
    "iso:country":"NL",
    "sg:address":"Aleidastr 62B",
    "sg:city":"Schiedam",
    "sg:orig_category":"Meubelstoffering",
    "sg:phone":"+31 10 426 8581",
    "sg:postcode":"3117 DK",
    "sg:province":"Zuid-Holland",
    "wof:name":"Ruigrok Meubelstoffeerderij",
    "wof:placetype":"venue"
},
  "geometry": {"coordinates":[4.389113,51.913376],"type":"Point"}
}