{
  "type": "Feature",
  "properties": {
    "addr:full":"Californiestr 2 Den Helder Noord-Holland 1781 GN",
    "addr:housenumber":"2",
    "addr:postcode":"1781 gn",
    "addr:street":"Californiestr",
    "iso:country":"NL",
    "sg:address":"Californiestr 2",
    "sg:city":"Den Helder",
    "sg:orig_category":"Kappers",
    "sg:phone":"+31 223 616 162",
    "sg:postcode":"1781 GN",
    "sg:province":"Noord-Holland",
    "wof:name":"Knip It",
    "wof:placetype":"venue"
},
  "geometry": {"coordinates":[4.762997,52.958614],"type":"Point"}
}