{
  "type": "Feature",
  "properties": {
    "addr:full":"Dorpsstraat 134 Wervershoof North Holland 1693 AJ",
    "addr:housenumber":"134",
    "addr:postcode":"1693 aj",
    "addr:street":"Dorpsstraat",
    "iso:country":"NL",
    "sg:address":"Dorpsstraat 134",
    "sg:city":"Wervershoof",
    "sg:orig_category":"Schilderwerk",
    "sg:phone":"+31 228 584 670",
    "sg:postcode":"1693 AJ",
    "sg:province":"North Holland",
    "wof:name":"J.R. Sijm",
    "wof:placetype":"venue"
},
  "geometry": {"coordinates":[5.14762,52.730137],"type":"Point"}
}