{
  "type": "Feature",
  "properties": {
    "addr:full":"Nassastraat 12 Haarlem North Holland 2012 PW",
    "addr:housenumber":"12",
    "addr:postcode":"2012 pw",
    "addr:street":"Nassastraat",
    "iso:country":"NL",
    "sg:address":"Nassastraat 12",
    "sg:city":"Haarlem",
    "sg:orig_category":"Bedrijfshuisvesting",
    "sg:phone":"+31 23 542 5252",
    "sg:postcode":"2012 PW",
    "sg:province":"North Holland",
    "wof:name":"Ogc Bv",
    "wof:placetype":"venue"
},
  "geometry": {"coordinates":[4.635435,52.384373],"type":"Point"}
}