{
  "type": "Feature",
  "properties": {
    "iso:country":"NL",
    "sg:address":"Buntwal 4",
    "sg:city":"Nijkerkerveen",
    "sg:orig_category":"Bloemen And Planten",
    "sg:phone":"+31 33 257 1619",
    "sg:postcode":"3864 MZ",
    "sg:province":"Gelderland",
    "wof:name":"S. Van Soeren Sr.",
    "wof:placetype":"venue"
},
  "geometry": {"coordinates":[5.475626,52.198734],"type":"Point"}
}