{
  "type": "Feature",
  "properties": {
    "addr:full":"Warmoesstr 141 Amsterdam Noord-Holland 1012 JB",
    "addr:housenumber":"141",
    "addr:postcode":"1012 jb",
    "iso:country":"NL",
    "sg:address":"Warmoesstr 141",
    "sg:city":"Amsterdam",
    "sg:orig_category":"Fotografie Reclame En Mode",
    "sg:phone":"+31 20 620 8637",
    "sg:postcode":"1012 JB",
    "sg:province":"Noord-Holland",
    "wof:name":"Koolwijk, R J H Van",
    "wof:placetype":"venue"
},
  "geometry": {"coordinates":[4.895885,52.373749],"type":"Point"}
}