{
  "type": "Feature",
  "properties": {
    "iso:country":"NL",
    "sg:address":"Woldweg 161",
    "sg:city":"Kropswolde",
    "sg:classifiers":[
        {
            "category":"Food & Beverages",
            "subcategory":"Fruits & Vegetables",
            "type":"Retail Goods"
        }
    ],
    "sg:phone":"+31 598 322 507",
    "sg:postcode":"9606 PD",
    "sg:province":"Groningen",
    "sg:tags":[
        "groenten"
    ],
    "wof:name":"Aardappelhandel Heeringa",
    "wof:placetype":"venue"
},
  "geometry": {"coordinates":[6.724054,53.141396],"type":"Point"}
}