{
  "type": "Feature",
  "properties": {
    "addr:full":"Kerkstraat 26 Wamel Gelderland 6659 AC",
    "addr:housenumber":"26",
    "addr:postcode":"6659 ac",
    "addr:street":"Kerkstraat;Gelderland",
    "iso:country":"NL",
    "sg:address":"Kerkstraat 26",
    "sg:city":"Wamel",
    "sg:orig_category":"Schoonheidssalons",
    "sg:phone":"+31 487 501 064",
    "sg:postcode":"6659 AC",
    "sg:province":"Gelderland",
    "wof:name":"Ans Zondag-Verbruggen",
    "wof:placetype":"venue"
},
  "geometry": {"coordinates":[5.475653,51.881477],"type":"Point"}
}