{
  "type": "Feature",
  "properties": {
    "addr:full":"Prinses Christinalaan 149 Uithoorn Noord-Holland 1421 BH",
    "addr:housenumber":"149",
    "addr:postcode":"1421 bh",
    "addr:street":"Prinses Christinalaan",
    "iso:country":"NL",
    "sg:address":"Prinses Christinalaan 149",
    "sg:city":"Uithoorn",
    "sg:orig_category":"Verzekeringen",
    "sg:phone":"+31 297 521 971",
    "sg:postcode":"1421 BH",
    "sg:province":"Noord-Holland",
    "wof:name":"Assurantie- En Adviesburo Verlaan",
    "wof:placetype":"venue"
},
  "geometry": {"coordinates":[4.821828,52.239258],"type":"Point"}
}