{
  "type": "Feature",
  "properties": {
    "iso:country":"NL",
    "sg:address":"Zonnebloemlaan 213",
    "sg:city":"Drunen",
    "sg:orig_category":"Handelsbemiddeling Textiel And Lederwaren",
    "sg:phone":"+31 416 372 953",
    "sg:postcode":"5151 TA",
    "sg:province":"Noord-Brabant",
    "wof:name":"Jac Janssen Isa",
    "wof:placetype":"venue"
},
  "geometry": {"coordinates":[5.139423,51.693874],"type":"Point"}
}