{
  "type": "Feature",
  "properties": {
    "iso:country":"NL",
    "sg:address":"J Smitzln 7",
    "sg:city":"Eindhoven",
    "sg:orig_category":"Acupunctuur",
    "sg:phone":"+31 6 21500862",
    "sg:postcode":"5611 LD",
    "sg:province":"Noord-Brabant",
    "wof:name":"Qian, C",
    "wof:placetype":"venue"
},
  "geometry": {"coordinates":[5.484105,51.434471],"type":"Point"}
}