{
  "type": "Feature",
  "properties": {
    "addr:full":"Olieslagweg 52 Enschede Overijssel 7521 JE",
    "addr:housenumber":"52",
    "addr:postcode":"7521 je",
    "addr:street":"Olieslagweg",
    "iso:country":"NL",
    "sg:address":"Olieslagweg 52",
    "sg:city":"Enschede",
    "sg:classifiers":[
        {
            "category":"Bakery",
            "type":"Food & Drink"
        }
    ],
    "sg:phone":"+31 53 435 8981",
    "sg:postcode":"7521 JE",
    "sg:province":"Overijssel",
    "sg:tags":[
        "brood",
        "banket"
    ],
    "wof:name":"J. Bos",
    "wof:placetype":"venue"
},
  "geometry": {"coordinates":[6.858821,52.232361],"type":"Point"}
}