{
  "type": "Feature",
  "properties": {
    "addr:full":"Tulpenveld 200 Castricum North Holland 1901 LE",
    "addr:housenumber":"200",
    "addr:postcode":"1901 le",
    "addr:street":"Tulpenveld",
    "iso:country":"NL",
    "sg:address":"Tulpenveld 200",
    "sg:city":"Castricum",
    "sg:orig_category":"Onderhoudswerken",
    "sg:phone":"+31 251 656 251",
    "sg:postcode":"1901 LE",
    "sg:province":"North Holland",
    "wof:name":"Ted Baltus",
    "wof:placetype":"venue"
},
  "geometry": {"coordinates":[4.677375,52.557922],"type":"Point"}
}