{
  "type": "Feature",
  "properties": {
    "addr:full":"Pr Willemstr 4 Klundert Paran\u00e1 4791 JR",
    "addr:housenumber":"4",
    "addr:postcode":"4791 jr",
    "addr:street":"Parana\u0301",
    "iso:country":"NL",
    "sg:address":"Pr Willemstr 4",
    "sg:city":"Klundert",
    "sg:orig_category":"Bejaarden - Verzorgingstehuizen",
    "sg:phone":"+31 168 403 150",
    "sg:postcode":"4791 JR",
    "sg:province":"Paran\u00e1",
    "wof:name":"Mauritshof",
    "wof:placetype":"venue"
},
  "geometry": {"coordinates":[-51.314629,-24.61602],"type":"Point"}
}