{
  "type": "Feature",
  "properties": {
    "addr:full":"Vergelt 6 Baarlo Lb Limburg 5991 PK",
    "addr:housenumber":"6",
    "addr:postcode":"lb;5991 pk",
    "addr:street":"Vergelt",
    "iso:country":"NL",
    "sg:address":"Vergelt 6",
    "sg:city":"Baarlo Lb",
    "sg:orig_category":"Fruitteelt",
    "sg:phone":"+31 77 477 3201",
    "sg:postcode":"5991 PK",
    "sg:province":"Limburg",
    "wof:name":"Landbouwbedrijf Gebroeders Gortz Bv",
    "wof:placetype":"venue"
},
  "geometry": {"coordinates":[6.102683,51.331898],"type":"Point"}
}