{
  "type": "Feature",
  "properties": {
    "addr:full":"Schoolstraat 22 Annen South Carolina 9468 BS",
    "addr:housenumber":"22;9468",
    "addr:street":"Schoolstraat;Bs",
    "iso:country":"NL",
    "sg:address":"Schoolstraat 22",
    "sg:city":"Annen",
    "sg:orig_category":"Artsen And Specialisten",
    "sg:phone":"+31 592 272 978",
    "sg:postcode":"9468 BS",
    "sg:province":"South Carolina",
    "wof:name":"C.P. Vogelzang Huisarts",
    "wof:placetype":"venue"
},
  "geometry": {"coordinates":[-79.253815,33.471233],"type":"Point"}
}