{
  "type": "Feature",
  "properties": {
    "iso:country":"NL",
    "sg:address":"De Palmen Grift 481",
    "sg:city":"Veenendaal",
    "sg:orig_category":"Mobiele- En Autotelefoons",
    "sg:phone":"+31 6 28610508",
    "sg:postcode":"3901 NM",
    "sg:province":"Utrecht",
    "wof:name":"Ridder, De",
    "wof:placetype":"venue"
},
  "geometry": {"coordinates":[5.560285,52.02195],"type":"Point"}
}