{
  "type": "Feature",
  "properties": {
    "iso:country":"NL",
    "sg:address":"Nw Rykswg 9",
    "sg:city":"Lexmond",
    "sg:orig_category":"Kinderkleding",
    "sg:phone":"+31 347 344 276",
    "sg:postcode":"4128 BM",
    "sg:province":"Zuid-Holland",
    "wof:name":"Berengoed",
    "wof:placetype":"venue"
},
  "geometry": {"coordinates":[5.038762,51.961292],"type":"Point"}
}