{
  "type": "Feature",
  "properties": {
    "addr:full":"Achterdk 3 Zevenbergen Noord-Brabant 4761 RB",
    "addr:housenumber":"3",
    "addr:postcode":"4761 rb",
    "addr:street":"Achterdk",
    "iso:country":"NL",
    "sg:address":"Achterdk 3",
    "sg:city":"Zevenbergen",
    "sg:classifiers":[
        {
            "category":"Retail",
            "subcategory":"Auto Repair",
            "type":"Services"
        }
    ],
    "sg:phone":"+31 168 329 080",
    "sg:postcode":"4761 RB",
    "sg:province":"Noord-Brabant",
    "sg:tags":[
        "garage"
    ],
    "wof:name":"Eurocar",
    "wof:placetype":"venue"
},
  "geometry": {"coordinates":[4.611395,51.650513],"type":"Point"}
}