{
  "type": "Feature",
  "properties": {
    "addr:full":"Salkhof 19 Hoogeveen Provincie Drenthe 7908 AL",
    "addr:housenumber":"19;7908",
    "addr:street":"Salkhof;Provincie;Al",
    "iso:country":"NL",
    "sg:address":"Salkhof 19",
    "sg:city":"Hoogeveen",
    "sg:orig_category":"Fotostudio'S And Fotografen",
    "sg:phone":"+31 528 263 575",
    "sg:postcode":"7908 AL",
    "sg:province":"Provincie Drenthe",
    "wof:name":"Foto Scholing",
    "wof:placetype":"venue"
},
  "geometry": {"coordinates":[6.458149,52.719566],"type":"Point"}
}