{
  "type": "Feature",
  "properties": {
    "addr:full":"Bernardusdal 9 Valkenswaard North Brabant 5551 CX",
    "addr:housenumber":"9",
    "addr:postcode":"5551 cx",
    "addr:street":"Bernardusdal",
    "iso:country":"NL",
    "sg:address":"Bernardusdal 9",
    "sg:city":"Valkenswaard",
    "sg:orig_category":"Kappers",
    "sg:phone":"+31 40 848 2080",
    "sg:postcode":"5551 CX",
    "sg:province":"North Brabant",
    "sg:website":"http://www.haircarecompany.com",
    "wof:name":"Hair & Care Company",
    "wof:placetype":"venue"
},
  "geometry": {"coordinates":[5.4366588593,51.3579216003],"type":"Point"}
}