{
  "type": "Feature",
  "properties": {
    "addr:full":"Aggemastate 33 Leeuwarden Friesland 8926 PA",
    "addr:housenumber":"33",
    "addr:postcode":"8926 pa",
    "addr:street":"Aggemastate",
    "iso:country":"NL",
    "sg:address":"Aggemastate 33",
    "sg:city":"Leeuwarden",
    "sg:orig_category":"Boeken En Tijdschriften",
    "sg:phone":"+31 58 266 5309",
    "sg:postcode":"8926 PA",
    "sg:province":"Friesland",
    "wof:name":"Frysl?n Nieuwsblad Voor Geschiedenis En Cultuur",
    "wof:placetype":"venue"
},
  "geometry": {"coordinates":[5.830704,53.215572],"type":"Point"}
}