{
  "type": "Feature",
  "properties": {
    "addr:full":"Grote Haag 123 Amersfoort Utrecht 3811 HH",
    "addr:housenumber":"123",
    "addr:postcode":"3811 hh",
    "addr:street":"Grote Haag",
    "iso:country":"NL",
    "sg:address":"Grote Haag 123",
    "sg:city":"Amersfoort",
    "sg:orig_category":"Diverse Grafische Activiteiten",
    "sg:phone":"+31 33 461 1142",
    "sg:postcode":"3811 HH",
    "sg:province":"Utrecht",
    "wof:name":"Hoogerbrug",
    "wof:placetype":"venue"
},
  "geometry": {"coordinates":[5.389855,52.15329],"type":"Point"}
}