{
  "type": "Feature",
  "properties": {
    "addr:full":"Thomsonln 45A S Gravenhage South Holland 2565 HX",
    "addr:housenumber":"45a",
    "addr:postcode":"2565 hx",
    "addr:street":"Thomsonln;S Gravenhage",
    "iso:country":"NL",
    "sg:address":"Thomsonln 45A",
    "sg:city":"S Gravenhage",
    "sg:classifiers":[
        {
            "category":"Food & Beverages",
            "subcategory":"Fruits & Vegetables",
            "type":"Retail Goods"
        }
    ],
    "sg:phone":"+31 6 50458277",
    "sg:postcode":"2565 HX",
    "sg:province":"South Holland",
    "sg:tags":[
        "en",
        "groenten"
    ],
    "wof:name":"A & C Ararat",
    "wof:placetype":"venue"
},
  "geometry": {"coordinates":[4.26129,52.076382],"type":"Point"}
}