{
  "type": "Feature",
  "properties": {
    "addr:full":"Wouwsestr 19 Bergen Op Zoom North Brabant 4611 PK",
    "addr:housenumber":"19",
    "addr:postcode":"4611 pk",
    "addr:street":"Wouwsestr",
    "iso:country":"NL",
    "sg:address":"Wouwsestr 19",
    "sg:city":"Bergen Op Zoom",
    "sg:orig_category":"Opticiens",
    "sg:phone":"+31 164 240 748",
    "sg:postcode":"4611 PK",
    "sg:province":"North Brabant",
    "sg:website":"http://www.eyewish.nl",
    "wof:name":"Eye Wish Groeneveld",
    "wof:placetype":"venue"
},
  "geometry": {"coordinates":[4.2915568352,51.4952507019],"type":"Point"}
}