{
  "type": "Feature",
  "properties": {
    "addr:full":"Goudplevier 50 Leusden Utrecht 3831 GT",
    "addr:housenumber":"50",
    "addr:postcode":"3831 gt",
    "addr:street":"Goudplevier",
    "iso:country":"NL",
    "sg:address":"Goudplevier 50",
    "sg:city":"Leusden",
    "sg:orig_category":"Verzekeringen",
    "sg:phone":"+31 33 494 4887",
    "sg:postcode":"3831 GT",
    "sg:province":"Utrecht",
    "wof:name":"Buurman'S Verzekeringen",
    "wof:placetype":"venue"
},
  "geometry": {"coordinates":[5.445173,52.13467],"type":"Point"}
}