{
  "type": "Feature",
  "properties": {
    "addr:full":"Nieuwstraat 76 Oostburg Zeeland 4501 ND",
    "addr:housenumber":"76",
    "addr:postcode":"4501 nd",
    "addr:street":"Nieuwstraat",
    "iso:country":"NL",
    "sg:address":"Nieuwstraat 76",
    "sg:city":"Oostburg",
    "sg:orig_category":"Goederenvervoer Over De Weg",
    "sg:phone":"+31 117 455 375",
    "sg:postcode":"4501 ND",
    "sg:province":"Zeeland",
    "wof:name":"E.F. Van Hal",
    "wof:placetype":"venue"
},
  "geometry": {"coordinates":[3.479783,51.31982],"type":"Point"}
}