{
  "type": "Feature",
  "properties": {
    "addr:full":"Rozengr 51A Amsterdam Noord-Holland 1016 LS",
    "addr:housenumber":"51a",
    "addr:postcode":"1016 ls",
    "addr:street":"Rozengr",
    "iso:country":"NL",
    "sg:address":"Rozengr 51A",
    "sg:city":"Amsterdam",
    "sg:orig_category":"Kappers",
    "sg:phone":"+31 20 626 6012",
    "sg:postcode":"1016 LS",
    "sg:province":"Noord-Holland",
    "wof:name":"Interline Hairstudio",
    "wof:placetype":"venue"
},
  "geometry": {"coordinates":[4.8812918663,52.3733940125],"type":"Point"}
}