{
  "type": "Feature",
  "properties": {
    "iso:country":"NL",
    "sg:address":"Wildforster 37",
    "sg:city":"Ede Gld",
    "sg:orig_category":"Technische Studies And Onderzoek",
    "sg:phone":"+31 318 624 235",
    "sg:postcode":"6713 KA",
    "sg:province":"Gelderland",
    "wof:name":"Small-Scale Dairy Technology Group",
    "wof:placetype":"venue"
},
  "geometry": {"coordinates":[5.647041,52.033882],"type":"Point"}
}