{
  "type": "Feature",
  "properties": {
    "addr:full":"Vechtln 88 Hengelo Ov Overijssel 7555 JZ",
    "addr:housenumber":"88",
    "addr:postcode":"7555 jz",
    "addr:street":"Vechtln;Ov",
    "iso:country":"NL",
    "sg:address":"Vechtln 88",
    "sg:city":"Hengelo Ov",
    "sg:orig_category":"Balletartikelen",
    "sg:phone":"+31 74 250 8585",
    "sg:postcode":"7555 JZ",
    "sg:province":"Overijssel",
    "wof:name":"Huckriede",
    "wof:placetype":"venue"
},
  "geometry": {"coordinates":[6.75678,52.269199],"type":"Point"}
}