{
  "type": "Feature",
  "properties": {
    "addr:full":"Neerstraat 25 Roermond Limburg 6041 KA",
    "addr:housenumber":"25",
    "addr:postcode":"6041 ka",
    "addr:street":"Neerstraat",
    "iso:country":"NL",
    "sg:address":"Neerstraat 25",
    "sg:city":"Roermond",
    "sg:orig_category":"Kappers",
    "sg:phone":"+31 475 332 674",
    "sg:postcode":"6041 KA",
    "sg:province":"Limburg",
    "wof:name":"Coiffures Riche",
    "wof:placetype":"venue"
},
  "geometry": {"coordinates":[5.9857020378,51.1936302185],"type":"Point"}
}