{
  "type": "Feature",
  "properties": {
    "iso:country":"NL",
    "sg:address":"Oude Provincialeweg 59",
    "sg:city":"Hapert",
    "sg:classifiers":[
        {
            "category":"Communications",
            "subcategory":"Television Station",
            "type":"Services"
        }
    ],
    "sg:phone":"+31 497 385 423",
    "sg:postcode":"5527 BN",
    "sg:province":"Noord-Brabant",
    "sg:tags":[
        "video",
        "audio",
        "verhuur"
    ],
    "wof:name":"First Class",
    "wof:placetype":"venue"
},
  "geometry": {"coordinates":[5.247733,51.371326],"type":"Point"}
}