{
  "type": "Feature",
  "properties": {
    "addr:full":"Zuiderhoofdstraat 1 Krommenie Noord-Holland 1561 AH",
    "addr:housenumber":"1",
    "addr:postcode":"1561 ah",
    "addr:street":"Zuiderhoofdstraat",
    "iso:country":"NL",
    "sg:address":"Zuiderhoofdstraat 1",
    "sg:city":"Krommenie",
    "sg:orig_category":"Kunst And Kunstenaarsbenodigdheden",
    "sg:phone":"+31 75 621 7534",
    "sg:postcode":"1561 AH",
    "sg:province":"Noord-Holland",
    "wof:name":"Jan Slort",
    "wof:placetype":"venue"
},
  "geometry": {"coordinates":[4.766862,52.496555],"type":"Point"}
}