{
  "type": "Feature",
  "properties": {
    "iso:country":"NL",
    "sg:address":"Bazeldijk 16",
    "sg:city":"Hoogblokland",
    "sg:orig_category":"Goederenvervoer Over De Weg",
    "sg:phone":"+31 183 562 436",
    "sg:postcode":"4221 XV",
    "sg:province":"Zuid-Holland",
    "wof:name":"Hans Koomans Transport",
    "wof:placetype":"venue"
},
  "geometry": {"coordinates":[4.995154,51.879364],"type":"Point"}
}