{
  "type": "Feature",
  "properties": {
    "iso:country":"NL",
    "sg:address":"Brugstr 7",
    "sg:city":"Zandvoort",
    "sg:orig_category":"Loodgieters",
    "sg:phone":"+31 23 573 1390",
    "sg:postcode":"2042 LG",
    "sg:province":"North Holland",
    "sg:website":"http://www.dakcentrale.nl",
    "wof:name":"Dakcentrale Amsterdam Zandvoort",
    "wof:placetype":"venue"
},
  "geometry": {"coordinates":[4.529797,52.374538],"type":"Point"}
}