{
  "type": "Feature",
  "properties": {
    "iso:country":"NL",
    "sg:address":"Hooistraat 12",
    "sg:city":"Tilburg",
    "sg:orig_category":"Gebouwenafwerking, Renovaties And Reiniging",
    "sg:phone":"+31 6 22098123",
    "sg:postcode":"5025 KE",
    "sg:province":"North Brabant",
    "wof:name":"Vto Klussenbedrijf",
    "wof:placetype":"venue"
},
  "geometry": {"coordinates":[5.073145,51.553555],"type":"Point"}
}