{
  "type": "Feature",
  "properties": {
    "iso:country":"NL",
    "sg:address":"Meeuwstr 11",
    "sg:city":"Tiel",
    "sg:orig_category":"Bloemen En Planten - Groothandel",
    "sg:phone":"+31 344 612 695",
    "sg:postcode":"4005 VS",
    "sg:province":"Gelderland",
    "wof:name":"Knol Jr, R",
    "wof:placetype":"venue"
},
  "geometry": {"coordinates":[5.447894,51.896065],"type":"Point"}
}