{
  "type": "Feature",
  "properties": {
    "addr:full":"Hamsewg 90 Hoogland Utrecht 3828 AG",
    "addr:housenumber":"90",
    "addr:postcode":"3828",
    "addr:street":"Hamsewg",
    "iso:country":"NL",
    "sg:address":"Hamsewg 90",
    "sg:city":"Hoogland",
    "sg:orig_category":"Drukkerijen",
    "sg:phone":"+31 33 480 6405",
    "sg:postcode":"3828 AG",
    "sg:province":"Utrecht",
    "sg:website":"http://www.t.druk.nl",
    "wof:name":"T Druk Bv Hoogland",
    "wof:placetype":"venue"
},
  "geometry": {"coordinates":[5.375057,52.170883],"type":"Point"}
}