{
  "type": "Feature",
  "properties": {
    "addr:full":"Maasboulev 71 Roermond Limburg 6041 LX",
    "addr:housenumber":"71",
    "addr:postcode":"6041 lx",
    "addr:street":"Maasboulev",
    "iso:country":"NL",
    "sg:address":"Maasboulev 71",
    "sg:city":"Roermond",
    "sg:orig_category":"Onroerende Goederen",
    "sg:phone":"+31 475 339 822",
    "sg:postcode":"6041 LX",
    "sg:province":"Limburg",
    "wof:name":"Midland Bv",
    "wof:placetype":"venue"
},
  "geometry": {"coordinates":[5.980712,51.194679],"type":"Point"}
}