{
  "type": "Feature",
  "properties": {
    "addr:full":"C V Sandeln 1 Odyk Utrecht 3984 KV",
    "addr:housenumber":"1",
    "addr:street":"V Sandeln",
    "iso:country":"NL",
    "sg:address":"C V Sandeln 1",
    "sg:city":"Odyk",
    "sg:orig_category":"Scholen Voor Basisonderwijs",
    "sg:phone":"+31 30 656 1200",
    "sg:postcode":"3984 KV",
    "sg:province":"Utrecht",
    "wof:name":"Bongerd Openb, De",
    "wof:placetype":"venue"
},
  "geometry": {"coordinates":[5.2206,52.04195],"type":"Point"}
}