{
  "type": "Feature",
  "properties": {
    "addr:full":"T Goylaan 72 Utrecht Utrecht 3525 AJ",
    "addr:housenumber":"72",
    "addr:postcode":"3525 aj",
    "addr:street":"T Goylaan",
    "iso:country":"NL",
    "sg:address":"T Goylaan 72",
    "sg:city":"Utrecht",
    "sg:orig_category":"Kappers",
    "sg:phone":"+31 30 288 9544",
    "sg:postcode":"3525 AJ",
    "sg:province":"Utrecht",
    "wof:name":"Lady'S Look",
    "wof:placetype":"venue"
},
  "geometry": {"coordinates":[5.120104,52.066368],"type":"Point"}
}