{
  "type": "Feature",
  "properties": {
    "addr:full":"Vinkenhof 9 Baarn Utrecht 3741 WK",
    "addr:housenumber":"9",
    "addr:postcode":"3741 wk",
    "addr:street":"Vinkenhof",
    "iso:country":"NL",
    "sg:address":"Vinkenhof 9",
    "sg:city":"Baarn",
    "sg:orig_category":"Adviesbureaus Bedrijfsorganisatie",
    "sg:phone":"+31 35 541 3064",
    "sg:postcode":"3741 WK",
    "sg:province":"Utrecht",
    "wof:name":"Verbinding, De",
    "wof:placetype":"venue"
},
  "geometry": {"coordinates":[5.277201,52.217339],"type":"Point"}
}