{
  "type": "Feature",
  "properties": {
    "iso:country":"NL",
    "sg:address":"Kasteel 7A",
    "sg:city":"Coevorden",
    "sg:orig_category":"Verzekerings- Maatschappijen",
    "sg:phone":"+31 900 4500000",
    "sg:postcode":"7741 GC",
    "sg:province":"Drenthe",
    "sg:website":"http://www.accesnet.nl/univehgv",
    "wof:name":"Univ\u00e9 Drenthe-Overijssel",
    "wof:placetype":"venue"
},
  "geometry": {"coordinates":[6.741492,52.661861],"type":"Point"}
}