{
  "type": "Feature",
  "properties": {
    "addr:full":"Van Hogendorplaan 217 Vlaardingen Zuid-Holland 3135 BP",
    "addr:housenumber":"217",
    "addr:postcode":"3135 bp",
    "addr:street":"Van Hogendorplaan",
    "iso:country":"NL",
    "sg:address":"Van Hogendorplaan 217",
    "sg:city":"Vlaardingen",
    "sg:classifiers":[
        {
            "category":"Fast Food",
            "type":"Food & Drink"
        }
    ],
    "sg:phone":"+31 10 434 7470",
    "sg:postcode":"3135 BP",
    "sg:province":"Zuid-Holland",
    "sg:tags":[
        "afhaal",
        "restaurant"
    ],
    "wof:name":"Snackbar Het Oosten",
    "wof:placetype":"venue"
},
  "geometry": {"coordinates":[4.361214,51.911259],"type":"Point"}
}