{
  "type": "Feature",
  "properties": {
    "iso:country":"NL",
    "sg:address":"I Hubertstr 153",
    "sg:city":"Rotterdam",
    "sg:orig_category":"Kinderopvang",
    "sg:phone":"+31 10 414 2891",
    "sg:postcode":"3034 CS",
    "sg:province":"Zuid-Holland",
    "sg:website":"http://www.kinderopvangirene.nl",
    "wof:name":"Irene Stichting Kinderopvang",
    "wof:placetype":"venue"
},
  "geometry": {"coordinates":[4.49123,51.93848],"type":"Point"}
}