{
  "type": "Feature",
  "properties": {
    "iso:country":"NL",
    "sg:address":"Valkenstraat 3",
    "sg:city":"Breda",
    "sg:orig_category":"Krantenuitgeverijen",
    "sg:phone":"+31 76 521 6355",
    "sg:postcode":"4811 EW",
    "sg:province":"Noord-Brabant",
    "wof:name":"Jazzcookin",
    "wof:placetype":"venue"
},
  "geometry": {"coordinates":[4.781736,51.591568],"type":"Point"}
}