{
  "type": "Feature",
  "properties": {
    "addr:full":"Valkenstraat 3 Breda Noord-Brabant 4811 EW",
    "addr:housenumber":"3",
    "addr:postcode":"4811 ew",
    "addr:street":"Valkenstraat",
    "iso:country":"NL",
    "sg:address":"Valkenstraat 3",
    "sg:city":"Breda",
    "sg:orig_category":"Krantenuitgeverijen",
    "sg:phone":"+31 76 521 6355",
    "sg:postcode":"4811 EW",
    "sg:province":"Noord-Brabant",
    "wof:name":"Jazzcookin",
    "wof:placetype":"venue"
},
  "geometry": {"coordinates":[4.781736,51.591568],"type":"Point"}
}