{
  "type": "Feature",
  "properties": {
    "addr:full":"Boeyerstr 14 De Ryp Noord-Holland 1483 TH",
    "addr:housenumber":"14;1483",
    "addr:postcode":"th",
    "addr:street":"Boeyerstr;De Ryp",
    "iso:country":"NL",
    "sg:address":"Boeyerstr 14",
    "sg:city":"De Ryp",
    "sg:orig_category":"Scholen Voor Basisonderwijs",
    "sg:phone":"+31 299 673 396",
    "sg:postcode":"1483 TH",
    "sg:province":"Noord-Holland",
    "wof:name":"Tweemaster, Obs De",
    "wof:placetype":"venue"
},
  "geometry": {"coordinates":[4.846465,52.560177],"type":"Point"}
}