{
  "type": "Feature",
  "properties": {
    "addr:full":"Hoevelakenstr 50 Tilburg Noord-Brabant 5045 GC",
    "addr:housenumber":"50",
    "addr:postcode":"5045 gc",
    "addr:street":"Hoevelakenstr",
    "iso:country":"NL",
    "sg:address":"Hoevelakenstr 50",
    "sg:city":"Tilburg",
    "sg:orig_category":"Scheidingswanden - Fabrieken",
    "sg:phone":"+31 13 570 4363",
    "sg:postcode":"5045 GC",
    "sg:province":"Noord-Brabant",
    "wof:name":"Duplawand",
    "wof:placetype":"venue"
},
  "geometry": {"coordinates":[5.000265,51.58308],"type":"Point"}
}