{
  "type": "Feature",
  "properties": {
    "iso:country":"NL",
    "sg:address":"Tuinbouwstr 138",
    "sg:city":"Groningen",
    "sg:orig_category":"Psychotherapeuten",
    "sg:phone":"+31 50 573 3284",
    "sg:postcode":"9717 JR",
    "sg:province":"Groningen",
    "wof:name":"Willemsen, Drs J E S",
    "wof:placetype":"venue"
},
  "geometry": {"coordinates":[6.552859,53.226582],"type":"Point"}
}