{
  "type": "Feature",
  "properties": {
    "addr:full":"Gondelln 34 Zaandam Noord-Holland 1503 KR",
    "addr:housenumber":"34",
    "addr:postcode":"1503 kr",
    "addr:street":"Gondelln",
    "iso:country":"NL",
    "sg:address":"Gondelln 34",
    "sg:city":"Zaandam",
    "sg:orig_category":"Verenigingen En Stichtingen",
    "sg:phone":"+31 75 616 1129",
    "sg:postcode":"1503 KR",
    "sg:province":"Noord-Holland",
    "wof:name":"Vrienden Van Zuster Berkhout, Sticht",
    "wof:placetype":"venue"
},
  "geometry": {"coordinates":[4.837587,52.447395],"type":"Point"}
}