{
  "type": "Feature",
  "properties": {
    "iso:country":"NL",
    "sg:address":"Horsterwg 147",
    "sg:city":"Ermelo",
    "sg:orig_category":"Vertaalbureaus",
    "sg:phone":"+31 341 493 979",
    "sg:postcode":"3853 JB",
    "sg:province":"Gelderland",
    "wof:name":"Marle, Van",
    "wof:placetype":"venue"
},
  "geometry": {"coordinates":[5.598605,52.307739],"type":"Point"}
}