{
  "type": "Feature",
  "properties": {
    "addr:full":"Terb R Rottekd 137 Rotterdam South Holland 3055 XC",
    "addr:housenumber":"137",
    "addr:postcode":"3055 xc",
    "iso:country":"NL",
    "sg:address":"Terb R Rottekd 137",
    "sg:city":"Rotterdam",
    "sg:orig_category":"Kantoor- En Bedrijfsmeubelen",
    "sg:phone":"+31 10 211 2050",
    "sg:postcode":"3055 XC",
    "sg:province":"South Holland",
    "sg:website":"http://www.sv.nl",
    "wof:name":"Sv Interieurgroep",
    "wof:placetype":"venue"
},
  "geometry": {"coordinates":[4.5068898201,51.9613189697],"type":"Point"}
}