{
  "type": "Feature",
  "properties": {
    "addr:full":"Peppeldreef 25 Bleiswyk Zuid-Holland 2665 GG",
    "addr:housenumber":"25",
    "addr:postcode":"2665 gg",
    "addr:street":"Peppeldreef",
    "iso:country":"NL",
    "sg:address":"Peppeldreef 25",
    "sg:city":"Bleiswyk",
    "sg:orig_category":"Autorijscholen",
    "sg:phone":"+31 10 521 4216",
    "sg:postcode":"2665 GG",
    "sg:province":"Zuid-Holland",
    "wof:name":"Stokman",
    "wof:placetype":"venue"
},
  "geometry": {"coordinates":[4.540258,52.004101],"type":"Point"}
}