{
  "type": "Feature",
  "properties": {
    "addr:full":"Evert Vd Beekstr 20 Luchth Schiphol Noord-Holland 1118 CL",
    "addr:housenumber":"20",
    "addr:postcode":"1118",
    "addr:street":"Evert Vd Beekstr",
    "iso:country":"NL",
    "sg:address":"Evert Vd Beekstr 20",
    "sg:city":"Luchth Schiphol",
    "sg:orig_category":"Makelaars En Adviseurs Onroerende Goederen",
    "sg:phone":"+31 20 405 4040",
    "sg:postcode":"1118 CL",
    "sg:province":"Noord-Holland",
    "sg:website":"http://www.atisweatheralls.com",
    "wof:name":"Weatherall Vastgoed Adviseurs",
    "wof:placetype":"venue"
},
  "geometry": {"coordinates":[4.75221,52.305019],"type":"Point"}
}