{
  "type": "Feature",
  "properties": {
    "addr:full":"Kapoenstr 28 Maastricht Limburg 6211 KW",
    "addr:housenumber":"28",
    "addr:postcode":"6211 kw",
    "addr:street":"Kapoenstr",
    "iso:country":"NL",
    "sg:address":"Kapoenstr 28",
    "sg:city":"Maastricht",
    "sg:classifiers":[
        {
            "category":"Real Estate",
            "subcategory":"Real Estate Operator",
            "type":"Services"
        }
    ],
    "sg:phone":"+31 43 351 2266",
    "sg:postcode":"6211 KW",
    "sg:province":"Limburg",
    "sg:tags":[
        "appartementen",
        "en",
        "flat"
    ],
    "sg:website":"http://www.internationalguesthouse.com",
    "wof:name":"International Guesthouse Serv",
    "wof:placetype":"venue"
},
  "geometry": {"coordinates":[5.689995,50.846733],"type":"Point"}
}