{
  "type": "Feature",
  "properties": {
    "addr:full":"Stadhuisplein 8 Vlissingen Zeeland 4382 LG",
    "addr:housenumber":"8",
    "addr:postcode":"4382 lg",
    "addr:street":"Stadhuisplein",
    "iso:country":"NL",
    "sg:address":"Stadhuisplein 8",
    "sg:city":"Vlissingen",
    "sg:orig_category":"Boekhouders",
    "sg:phone":"+31 118 412 129",
    "sg:postcode":"4382 LG",
    "sg:province":"Zeeland",
    "wof:name":"Administratiekantoor Legemaate",
    "wof:placetype":"venue"
},
  "geometry": {"coordinates":[3.56799,51.447392],"type":"Point"}
}