{
  "type": "Feature",
  "properties": {
    "addr:full":"Orionwg 5 Leeuwarden Friesland 8938 AG",
    "addr:housenumber":"5",
    "addr:postcode":"8938",
    "addr:street":"Orionwg",
    "iso:country":"NL",
    "sg:address":"Orionwg 5",
    "sg:city":"Leeuwarden",
    "sg:orig_category":"Betonijzervlechten",
    "sg:phone":"+31 58 288 6611",
    "sg:postcode":"8938 AG",
    "sg:province":"Friesland",
    "sg:website":"http://www.lbvc.nl",
    "wof:name":"Leeuwarder",
    "wof:placetype":"venue"
},
  "geometry": {"coordinates":[5.840994,53.200123],"type":"Point"}
}