{
  "type": "Feature",
  "properties": {
    "iso:country":"NL",
    "sg:address":"L Dulstr 89",
    "sg:city":"Gouda",
    "sg:orig_category":"Zonweringen",
    "sg:phone":"+31 182 528 282",
    "sg:postcode":"2801 EP",
    "sg:province":"Zuid-Holland",
    "wof:name":"Jong Vof Decorette, De",
    "wof:placetype":"venue"
},
  "geometry": {"coordinates":[4.712718,52.01376],"type":"Point"}
}