{
  "type": "Feature",
  "properties": {
    "addr:full":"Elderveldpln 11 Arnhem Gelderland 6843 JA",
    "addr:housenumber":"11",
    "addr:postcode":"6843 ja",
    "addr:street":"Elderveldpln",
    "iso:country":"NL",
    "sg:address":"Elderveldpln 11",
    "sg:city":"Arnhem",
    "sg:orig_category":"Postkantoren",
    "sg:phone":"+31 26 381 1740",
    "sg:postcode":"6843 JA",
    "sg:province":"Gelderland",
    "sg:website":"http://www.postkantoor.nl",
    "wof:name":"Postkantoor",
    "wof:placetype":"venue"
},
  "geometry": {"coordinates":[5.860025,51.960388],"type":"Point"}
}