{
  "type": "Feature",
  "properties": {
    "addr:full":"Ohmstraat 8 Ede Gld Gelderland 6716 DD",
    "addr:housenumber":"8",
    "addr:postcode":"6716 dd",
    "addr:street":"Ohmstraat;Gld Gelderland",
    "iso:country":"NL",
    "sg:address":"Ohmstraat 8",
    "sg:city":"Ede Gld",
    "sg:orig_category":"Bouwnijverheidsmachines Gh",
    "sg:phone":"+31 318 624 499",
    "sg:postcode":"6716 DD",
    "sg:province":"Gelderland",
    "wof:name":"G.J. Staal Heftruck Service",
    "wof:placetype":"venue"
},
  "geometry": {"coordinates":[5.629227,52.031624],"type":"Point"}
}