{
  "type": "Feature",
  "properties": {
    "addr:full":"Fiifgeawei 39 Offingawier Provincie Friesland 8626 GC",
    "addr:housenumber":"39",
    "addr:postcode":"8626 gc",
    "addr:street":"Fiifgeawei;Provincie Friesland",
    "iso:country":"NL",
    "sg:address":"Fiifgeawei 39",
    "sg:city":"Offingawier",
    "sg:orig_category":"Levende Dieren Gh",
    "sg:phone":"+31 515 413 498",
    "sg:postcode":"8626 GC",
    "sg:province":"Provincie Friesland",
    "wof:name":"A Vd Heide",
    "wof:placetype":"venue"
},
  "geometry": {"coordinates":[5.702273,53.034397],"type":"Point"}
}