{
  "type": "Feature",
  "properties": {
    "addr:full":"Loevesteinsingel 106 Rotterdam Zuid-Holland 3077 HJ",
    "addr:housenumber":"106",
    "addr:postcode":"3077 hj",
    "addr:street":"Loevesteinsingel",
    "iso:country":"NL",
    "sg:address":"Loevesteinsingel 106",
    "sg:city":"Rotterdam",
    "sg:orig_category":"Binnenhuisarchitecten",
    "sg:phone":"+31 10 482 6640",
    "sg:postcode":"3077 HJ",
    "sg:province":"Zuid-Holland",
    "wof:name":"R.A. Kanters Interieur Adviesbureau",
    "wof:placetype":"venue"
},
  "geometry": {"coordinates":[4.567164,51.88987],"type":"Point"}
}