{
  "type": "Feature",
  "properties": {
    "addr:full":"Hof V Londen 50 Doetinchem Gelderland 7007 KT",
    "addr:housenumber":"50",
    "addr:postcode":"7007 kt",
    "addr:street":"Londen;Gelderland",
    "iso:country":"NL",
    "sg:address":"Hof V Londen 50",
    "sg:city":"Doetinchem",
    "sg:orig_category":"Kappers",
    "sg:phone":"+31 314 330 869",
    "sg:postcode":"7007 KT",
    "sg:province":"Gelderland",
    "wof:name":"Angelique",
    "wof:placetype":"venue"
},
  "geometry": {"coordinates":[6.2910552025,51.963596344],"type":"Point"}
}