{
  "type": "Feature",
  "properties": {
    "addr:full":"Rosendaalsestr 323-325 Arnhem Gelderland 6824 CJ",
    "addr:housenumber":"323-325",
    "addr:postcode":"6824 cj",
    "iso:country":"NL",
    "sg:address":"Rosendaalsestr 323-325",
    "sg:city":"Arnhem",
    "sg:classifiers":[
        {
            "category":"Retail",
            "subcategory":"Auto Repair",
            "type":"Services"
        }
    ],
    "sg:phone":"+31 26 443 7282",
    "sg:postcode":"6824 CJ",
    "sg:province":"Gelderland",
    "sg:tags":[
        "garage"
    ],
    "wof:name":"Mierlo, H H A Van",
    "wof:placetype":"venue"
},
  "geometry": {"coordinates":[5.926666,51.989548],"type":"Point"}
}