{
  "type": "Feature",
  "properties": {
    "iso:country":"NL",
    "sg:address":"Oudendk 17",
    "sg:city":"Warffum",
    "sg:orig_category":"Onderhoudswerken",
    "sg:phone":"+31 595 423 542",
    "sg:postcode":"9989 EM",
    "sg:province":"Groningen",
    "wof:name":"Swaagman, N",
    "wof:placetype":"venue"
},
  "geometry": {"coordinates":[6.557944,53.397659],"type":"Point"}
}