{
  "type": "Feature",
  "properties": {
    "iso:country":"NL",
    "sg:address":"Steenstr 64",
    "sg:city":"Arnhem",
    "sg:orig_category":"Juweliers",
    "sg:phone":"+31 26 442 2587",
    "sg:postcode":"6828 CN",
    "sg:province":"Gelderland",
    "wof:name":"Velthuizen",
    "wof:placetype":"venue"
},
  "geometry": {"coordinates":[5.918573,51.984066],"type":"Point"}
}