{
  "type": "Feature",
  "properties": {
    "addr:full":"Zwanestr 2-2 Groningen Groningen 9712 CL",
    "addr:housenumber":"2-2",
    "addr:postcode":"9712",
    "addr:street":"Zwanestr",
    "iso:country":"NL",
    "sg:address":"Zwanestr 2-2",
    "sg:city":"Groningen",
    "sg:orig_category":"Geschenkartikelen",
    "sg:phone":"+31 50 312 4293",
    "sg:postcode":"9712 CL",
    "sg:province":"Groningen",
    "sg:website":"http://www.stadsefratsen.nl",
    "wof:name":"Stadse Fratsen",
    "wof:placetype":"venue"
},
  "geometry": {"coordinates":[6.565195,53.218487],"type":"Point"}
}