{
  "type": "Feature",
  "properties": {
    "addr:full":"Constantijn Huijgenslaan 5 Bussum North Holland 1401 AK",
    "addr:housenumber":"5",
    "addr:postcode":"1401 ak",
    "addr:street":"Constantijn Huijgenslaan",
    "iso:country":"NL",
    "sg:address":"Constantijn Huijgenslaan 5",
    "sg:city":"Bussum",
    "sg:orig_category":"Parfum And Cosmetica Gh",
    "sg:phone":"+31 35 691 2796",
    "sg:postcode":"1401 AK",
    "sg:province":"North Holland",
    "wof:name":"A Roos Bv",
    "wof:placetype":"venue"
},
  "geometry": {"coordinates":[5.166918,52.279881],"type":"Point"}
}