{
  "type": "Feature",
  "properties": {
    "addr:full":"Teteringsedijk 113 Breda Noord-Brabant 4817 MB",
    "addr:housenumber":"113",
    "addr:postcode":"4817 mb",
    "addr:street":"Teteringsedijk",
    "iso:country":"NL",
    "sg:address":"Teteringsedijk 113",
    "sg:city":"Breda",
    "sg:orig_category":"Artsen And Specialisten",
    "sg:phone":"+31 76 521 2573",
    "sg:postcode":"4817 MB",
    "sg:province":"Noord-Brabant",
    "wof:name":"J.A. Oudraad",
    "wof:placetype":"venue"
},
  "geometry": {"coordinates":[4.79826,51.593361],"type":"Point"}
}