{
  "type": "Feature",
  "properties": {
    "iso:country":"NL",
    "sg:address":"S Gravelandseweg 42",
    "sg:city":"Hilversum",
    "sg:orig_category":"Werving And Selectie Van Tijdelijk Personeel And Uitzendkantoren",
    "sg:phone":"+31 35 671 1111",
    "sg:postcode":"1211 BT",
    "sg:province":"North Holland",
    "wof:name":"Randstad Uitzendbureau Bv",
    "wof:placetype":"venue"
},
  "geometry": {"coordinates":[5.1708908081,52.2262077332],"type":"Point"}
}