{
  "type": "Feature",
  "properties": {
    "addr:full":"Zwanenbeemd 33 Helmond Noord-Brabant 5707 PZ",
    "addr:housenumber":"33",
    "addr:postcode":"5707 pz",
    "addr:street":"Zwanenbeemd",
    "iso:country":"NL",
    "sg:address":"Zwanenbeemd 33",
    "sg:city":"Helmond",
    "sg:orig_category":"Architecten",
    "sg:phone":"+31 492 477 477",
    "sg:postcode":"5707 PZ",
    "sg:province":"Noord-Brabant",
    "wof:name":"Bur V Architektuur/Stedebouw Ing. T. V W",
    "wof:placetype":"venue"
},
  "geometry": {"coordinates":[5.64778,51.489826],"type":"Point"}
}