{
  "type": "Feature",
  "properties": {
    "addr:full":"Hg Slagen 237 S Hertogenbosch North Brabant 5233 SK",
    "addr:housenumber":"237",
    "addr:postcode":"5233 sk",
    "addr:street":"Hg Slagen;S Hertogenbosch",
    "iso:country":"NL",
    "sg:address":"Hg Slagen 237",
    "sg:city":"S Hertogenbosch",
    "sg:orig_category":"Fotojournalisten Freelance",
    "sg:phone":"+31 73 641 0329",
    "sg:postcode":"5233 SK",
    "sg:province":"North Brabant",
    "wof:name":"Turi",
    "wof:placetype":"venue"
},
  "geometry": {"coordinates":[5.31934,51.709335],"type":"Point"}
}