{
  "type": "Feature",
  "properties": {
    "iso:country":"NL",
    "sg:address":"Vouershof 1",
    "sg:city":"Geleen",
    "sg:orig_category":"Begrafenisondernemers",
    "sg:phone":"+31 46 475 3030",
    "sg:postcode":"6161 DB",
    "sg:province":"Limburg",
    "wof:name":"Crematorium Nedermaas",
    "wof:placetype":"venue"
},
  "geometry": {"coordinates":[5.809019,50.962288],"type":"Point"}
}