{
  "type": "Feature",
  "properties": {
    "addr:full":"Purcelldreef 2 Tilburg North Brabant 5012 AL",
    "addr:housenumber":"2",
    "addr:postcode":"5012 al",
    "addr:street":"Purcelldreef",
    "iso:country":"NL",
    "sg:address":"Purcelldreef 2",
    "sg:city":"Tilburg",
    "sg:orig_category":"Onderwijsmateriaal",
    "sg:phone":"+31 13 547 0136",
    "sg:postcode":"5012 AL",
    "sg:province":"North Brabant",
    "wof:name":"Buitengewoon Berends Bv",
    "wof:placetype":"venue"
},
  "geometry": {"coordinates":[5.10042,51.578754],"type":"Point"}
}