{
  "type": "Feature",
  "properties": {
    "iso:country":"NL",
    "sg:address":"Kloosterhof 1A",
    "sg:city":"Liessel",
    "sg:orig_category":"Tandartsen",
    "sg:phone":"+31 493 344 038",
    "sg:postcode":"5757 AH",
    "sg:province":"Noord-Brabant",
    "wof:name":"J.A.Th. Driessen",
    "wof:placetype":"venue"
},
  "geometry": {"coordinates":[5.822443,51.415184],"type":"Point"}
}