{
  "type": "Feature",
  "properties": {
    "addr:full":"Scottlaan 280 Eindhoven North Brabant 5623 RE",
    "addr:housenumber":"280",
    "addr:postcode":"5623 re",
    "addr:street":"Scottlaan",
    "iso:country":"NL",
    "sg:address":"Scottlaan 280",
    "sg:city":"Eindhoven",
    "sg:orig_category":"Marktonderzoekbureaus",
    "sg:phone":"+31 40 245 7316",
    "sg:postcode":"5623 RE",
    "sg:province":"North Brabant",
    "wof:name":"Ir A. Van Der Ploeg Bv",
    "wof:placetype":"venue"
},
  "geometry": {"coordinates":[5.479819,51.453213],"type":"Point"}
}