{
  "type": "Feature",
  "properties": {
    "addr:full":"Fresiastr 53 Enschede NL.08 7531 VJ",
    "addr:housenumber":"53",
    "addr:postcode":"7531 vj",
    "addr:street":"Fresiastr",
    "iso:country":"NL",
    "sg:address":"Fresiastr 53",
    "sg:city":"Enschede",
    "sg:orig_category":"Boeken En Tijdschriften",
    "sg:phone":"+31 53 435 1633",
    "sg:postcode":"7531 VJ",
    "sg:province":"NL.08",
    "wof:name":"Sanders, R A M",
    "wof:placetype":"venue"
},
  "geometry": {"coordinates":[6.920762,52.230263],"type":"Point"}
}