{
  "type": "Feature",
  "properties": {
    "addr:full":"Binnenhaven 38A Enschede NL.08 7547 BH",
    "addr:housenumber":"38a",
    "addr:postcode":"7547 bh",
    "addr:street":"Binnenhaven",
    "iso:country":"NL",
    "sg:address":"Binnenhaven 38A",
    "sg:city":"Enschede",
    "sg:orig_category":"Loodgieters",
    "sg:phone":"+31 53 432 6939",
    "sg:postcode":"7547 BH",
    "sg:province":"NL.08",
    "wof:name":"Bimij",
    "wof:placetype":"venue"
},
  "geometry": {"coordinates":[6.85464,52.222137],"type":"Point"}
}