{
  "type": "Feature",
  "properties": {
    "addr:full":"Heerendonkln 36 S Hertogenbosch North Brabant 5223 XZ",
    "addr:housenumber":"36",
    "addr:postcode":"5223 xz",
    "addr:street":"Heerendonkln;S Hertogenbosch",
    "iso:country":"NL",
    "sg:address":"Heerendonkln 36",
    "sg:city":"S Hertogenbosch",
    "sg:classifiers":[
        {
            "category":"Personal",
            "subcategory":"Nail Salon",
            "type":"Services"
        }
    ],
    "sg:phone":"+31 73 621 5289",
    "sg:postcode":"5223 XZ",
    "sg:province":"North Brabant",
    "sg:tags":[
        "pedicure"
    ],
    "wof:name":"Petra",
    "wof:placetype":"venue"
},
  "geometry": {"coordinates":[5.280378,51.690495],"type":"Point"}
}