{
  "type": "Feature",
  "properties": {
    "addr:full":"T Winkelcentrum 21 Brunssum Limburg 6441 BZ",
    "addr:housenumber":"21",
    "addr:postcode":"6441 bz",
    "addr:street":"T Winkelcentrum",
    "iso:country":"NL",
    "sg:address":"T Winkelcentrum 21",
    "sg:city":"Brunssum",
    "sg:orig_category":"Sportschoenen - Winkels",
    "sg:phone":"+31 45 525 7010",
    "sg:postcode":"6441 BZ",
    "sg:province":"Limburg",
    "wof:name":"Gielkens Sport Kleding - Schoenen",
    "wof:placetype":"venue"
},
  "geometry": {"coordinates":[5.972179,50.946522],"type":"Point"}
}