{
  "type": "Feature",
  "properties": {
    "addr:full":"Gewantmakersdreef 100 Maastricht Limburg 6216 EE",
    "addr:housenumber":"100",
    "addr:postcode":"6216 ee",
    "addr:street":"Gewantmakersdreef",
    "iso:country":"NL",
    "sg:address":"Gewantmakersdreef 100",
    "sg:city":"Maastricht",
    "sg:orig_category":"Kappers",
    "sg:phone":"+31 43 347 9644",
    "sg:postcode":"6216 EE",
    "sg:province":"Limburg",
    "wof:name":"Hair By James",
    "wof:placetype":"venue"
},
  "geometry": {"coordinates":[5.6608700752,50.8449249268],"type":"Point"}
}