{
  "type": "Feature",
  "properties": {
    "addr:full":"Nw Teertuinen 17/2 Amsterdam New York 1013 LV",
    "addr:housenumber":"17 / 2;1013",
    "addr:street":"Nw Teertuinen",
    "iso:country":"NL",
    "sg:address":"Nw Teertuinen 17/2",
    "sg:city":"Amsterdam",
    "sg:orig_category":"Beeldende Kunstenaars",
    "sg:phone":"+31 20 638 0285",
    "sg:postcode":"1013 LV",
    "sg:province":"New York",
    "wof:name":"Haar, Bart Ter",
    "wof:placetype":"venue"
},
  "geometry": {"coordinates":[-74.202896,42.97855],"type":"Point"}
}