{
  "type": "Feature",
  "properties": {
    "iso:country":"NL",
    "sg:address":"Nieuwe N 50",
    "sg:city":"Hoorn Nh",
    "sg:orig_category":"Open Haarden",
    "sg:phone":"+31 229 272 542",
    "sg:postcode":"1621 EP",
    "sg:province":"North Holland",
    "wof:name":"Ornament & Interieur",
    "wof:placetype":"venue"
},
  "geometry": {"coordinates":[5.05207,52.642399],"type":"Point"}
}