{
  "type": "Feature",
  "properties": {
    "addr:full":"Lammerhof 63 Warnsveld Gelderland 7232 AS",
    "addr:housenumber":"63",
    "addr:postcode":"7232 as",
    "addr:street":"Lammerhof;Gelderland",
    "iso:country":"NL",
    "sg:address":"Lammerhof 63",
    "sg:city":"Warnsveld",
    "sg:orig_category":"Onderhoudswerken",
    "sg:phone":"+31 575 524 015",
    "sg:postcode":"7232 AS",
    "sg:province":"Gelderland",
    "wof:name":"Blitz, B",
    "wof:placetype":"venue"
},
  "geometry": {"coordinates":[6.229736,52.131947],"type":"Point"}
}