{
  "type": "Feature",
  "properties": {
    "addr:full":"Tjalkstraat 3 Utrecht Utrecht 3534 PA",
    "addr:housenumber":"3",
    "addr:postcode":"3534",
    "addr:street":"Tjalkstraat",
    "iso:country":"NL",
    "sg:address":"Tjalkstraat 3",
    "sg:city":"Utrecht",
    "sg:orig_category":"Schilderwerk",
    "sg:phone":"+31 30 244 8581",
    "sg:postcode":"3534 PA",
    "sg:province":"Utrecht",
    "wof:name":"Hendriks Schildersbedrijf",
    "wof:placetype":"venue"
},
  "geometry": {"coordinates":[5.084755,52.098156],"type":"Point"}
}