{
  "type": "Feature",
  "properties": {
    "addr:full":"Weth. Van Oostveenstraat 43 Baambrugge Utrecht 1396 KT",
    "addr:housenumber":"43",
    "addr:postcode":"1396 kt",
    "addr:street":"Weth. Van Oostveenstraat",
    "iso:country":"NL",
    "sg:address":"Weth. Van Oostveenstraat 43",
    "sg:city":"Baambrugge",
    "sg:orig_category":"Goederenvervoer Over De Weg",
    "sg:phone":"+31 294 291 850",
    "sg:postcode":"1396 KT",
    "sg:province":"Utrecht",
    "wof:name":"Firma Van Voorthuyzen Int. Tanktransport",
    "wof:placetype":"venue"
},
  "geometry": {"coordinates":[4.987536,52.244774],"type":"Point"}
}