{
  "type": "Feature",
  "properties": {
    "addr:full":"Havenstr 74B Doetinchem Gelderland 7005 AG",
    "addr:housenumber":"74b",
    "addr:postcode":"7005",
    "addr:street":"Havenstr;Gelderland",
    "iso:country":"NL",
    "sg:address":"Havenstr 74B",
    "sg:city":"Doetinchem",
    "sg:orig_category":"Verhuur",
    "sg:phone":"+31 314 394 987",
    "sg:postcode":"7005 AG",
    "sg:province":"Gelderland",
    "sg:website":"http://www.boels.nl",
    "wof:name":"Boels Doetinchem Machineverhuur",
    "wof:placetype":"venue"
},
  "geometry": {"coordinates":[6.294766,51.946972],"type":"Point"}
}