{
  "type": "Feature",
  "properties": {
    "addr:full":"Jongkoenstraat 1 Goedereede Zuid-Holland 3252 AV",
    "addr:housenumber":"1",
    "addr:postcode":"3252 av",
    "addr:street":"Jongkoenstraat",
    "iso:country":"NL",
    "sg:address":"Jongkoenstraat 1",
    "sg:city":"Goedereede",
    "sg:orig_category":"Artsen And Specialisten",
    "sg:phone":"+31 187 491 367",
    "sg:postcode":"3252 AV",
    "sg:province":"Zuid-Holland",
    "wof:name":"Huisartsenpraktijk Goedereede",
    "wof:placetype":"venue"
},
  "geometry": {"coordinates":[3.983952,51.819164],"type":"Point"}
}