{
  "type": "Feature",
  "properties": {
    "addr:full":"Sloterkd 58 Amsterdam Noord-Holland 1058 HG",
    "addr:housenumber":"58",
    "addr:postcode":"1058 hg",
    "addr:street":"Sloterkd",
    "iso:country":"NL",
    "sg:address":"Sloterkd 58",
    "sg:city":"Amsterdam",
    "sg:orig_category":"Oud Metaal",
    "sg:phone":"+31 20 615 7942",
    "sg:postcode":"1058 HG",
    "sg:province":"Noord-Holland",
    "wof:name":"Piet Koorn En Zoon",
    "wof:placetype":"venue"
},
  "geometry": {"coordinates":[4.8509402275,52.3576583862],"type":"Point"}
}