{
  "type": "Feature",
  "properties": {
    "addr:full":"Eekhool 28 Hilvarenbeek Noord-Brabant 5081 RR",
    "addr:housenumber":"28",
    "addr:postcode":"5081 rr",
    "addr:street":"Eekhool",
    "iso:country":"NL",
    "sg:address":"Eekhool 28",
    "sg:city":"Hilvarenbeek",
    "sg:orig_category":"Hulpverlening Sociaal",
    "sg:phone":"+31 13 505 4620",
    "sg:postcode":"5081 RR",
    "sg:province":"Noord-Brabant",
    "wof:name":"Loijens",
    "wof:placetype":"venue"
},
  "geometry": {"coordinates":[5.139205,51.492443],"type":"Point"}
}