{
  "type": "Feature",
  "properties": {
    "addr:full":"Vaart Zuidzijde 66 Appelscha Friesland 8426 AG",
    "addr:housenumber":"66",
    "addr:postcode":"8426",
    "addr:street":"Vaart Zuidzijde",
    "iso:country":"NL",
    "sg:address":"Vaart Zuidzijde 66",
    "sg:city":"Appelscha",
    "sg:orig_category":"Bloemen And Planten",
    "sg:phone":"+31 516 431 488",
    "sg:postcode":"8426 AG",
    "sg:province":"Friesland",
    "wof:name":"Bloemen Hoekje J Drenth Vof",
    "wof:placetype":"venue"
},
  "geometry": {"coordinates":[6.35719,52.953869],"type":"Point"}
}