{
  "type": "Feature",
  "properties": {
    "addr:full":"H. Bumapark 13 Drachten Friesland 9203 KW",
    "addr:housenumber":"13",
    "addr:postcode":"9203 kw",
    "iso:country":"NL",
    "sg:address":"H. Bumapark 13",
    "sg:city":"Drachten",
    "sg:orig_category":"Binnenvaart",
    "sg:phone":"+31 512 512 791",
    "sg:postcode":"9203 KW",
    "sg:province":"Friesland",
    "wof:name":"De Harmonie",
    "wof:placetype":"venue"
},
  "geometry": {"coordinates":[6.097164,53.099789],"type":"Point"}
}