{
  "type": "Feature",
  "properties": {
    "addr:full":"Ryksstrwg 37 Ubbergen Gelderland 6574 AC",
    "addr:housenumber":"37",
    "addr:postcode":"6574 ac",
    "addr:street":"Ryksstrwg;Gelderland",
    "iso:country":"NL",
    "sg:address":"Ryksstrwg 37",
    "sg:city":"Ubbergen",
    "sg:classifiers":[
        {
            "category":"Utilities",
            "subcategory":"Cable",
            "type":"Services"
        }
    ],
    "sg:phone":"+31 24 360 3206",
    "sg:postcode":"6574 AC",
    "sg:province":"Gelderland",
    "sg:tags":[
        "masseur",
        "en",
        "heilgymnasten"
    ],
    "wof:name":"Barten, A",
    "wof:placetype":"venue"
},
  "geometry": {"coordinates":[5.899927,51.837234],"type":"Point"}
}