{
  "type": "Feature",
  "properties": {
    "addr:full":"Dynselburgerln 2 Zeist Utrecht 3705 LP",
    "addr:housenumber":"2",
    "addr:postcode":"3705 lp",
    "addr:street":"Dynselburgerln",
    "iso:country":"NL",
    "sg:address":"Dynselburgerln 2",
    "sg:city":"Zeist",
    "sg:orig_category":"Pensioenen",
    "sg:phone":"+31 30 693 0890",
    "sg:postcode":"3705 LP",
    "sg:province":"Utrecht",
    "wof:name":"Aps Bv",
    "wof:placetype":"venue"
},
  "geometry": {"coordinates":[5.254858,52.101795],"type":"Point"}
}