{
  "type": "Feature",
  "properties": {
    "addr:full":"Voorstreek 89 Leeuwarden Friesland 8911 JM",
    "addr:housenumber":"89",
    "addr:postcode":"8911 jm",
    "addr:street":"Voorstreek",
    "iso:country":"NL",
    "sg:address":"Voorstreek 89",
    "sg:city":"Leeuwarden",
    "sg:orig_category":"Psychologen",
    "sg:phone":"+31 58 216 1552",
    "sg:postcode":"8911 JM",
    "sg:province":"Friesland",
    "wof:name":"Niemeijer En De Hoop",
    "wof:placetype":"venue"
},
  "geometry": {"coordinates":[5.800635,53.204933],"type":"Point"}
}