{
  "type": "Feature",
  "properties": {
    "addr:full":"Veenkamp 81A Uddel Gelderland 3888 LH",
    "addr:housenumber":"81a",
    "addr:postcode":"3888 lh",
    "addr:street":"Veenkamp;Gelderland",
    "iso:country":"NL",
    "sg:address":"Veenkamp 81A",
    "sg:city":"Uddel",
    "sg:orig_category":"Hek- En Rasterwerken",
    "sg:phone":"+31 577 401 540",
    "sg:postcode":"3888 LH",
    "sg:province":"Gelderland",
    "sg:website":"http://www.hophekwerken.nl",
    "wof:name":"Hop",
    "wof:placetype":"venue"
},
  "geometry": {"coordinates":[5.779334,52.259521],"type":"Point"}
}