{
  "type": "Feature",
  "properties": {
    "addr:full":"Ridder Robertlaan 18 Doorwerth Gelderland 6865 BS",
    "addr:housenumber":"18",
    "addr:postcode":"6865 bs",
    "addr:street":"Ridder Robertlaan;Gelderland",
    "iso:country":"NL",
    "sg:address":"Ridder Robertlaan 18",
    "sg:city":"Doorwerth",
    "sg:orig_category":"Bedrijfs- And Managementsconsultants",
    "sg:phone":"+31 317 350 777",
    "sg:postcode":"6865 BS",
    "sg:province":"Gelderland",
    "wof:name":"Dejo Holding Bv",
    "wof:placetype":"venue"
},
  "geometry": {"coordinates":[5.782523,51.982967],"type":"Point"}
}