{
  "type": "Feature",
  "properties": {
    "addr:full":"Thorbeckelaan 2 Almelo Overijssel 7604 XP",
    "addr:housenumber":"2",
    "addr:postcode":"7604 xp",
    "addr:street":"Thorbeckelaan",
    "iso:country":"NL",
    "sg:address":"Thorbeckelaan 2",
    "sg:city":"Almelo",
    "sg:orig_category":"Overheidsdiensten",
    "sg:phone":"+31 546 851 485",
    "sg:postcode":"7604 XP",
    "sg:province":"Overijssel",
    "wof:name":"Wijkcentrum De Kerkelanden",
    "wof:placetype":"venue"
},
  "geometry": {"coordinates":[6.6514458656,52.3561248779],"type":"Point"}
}