{
  "type": "Feature",
  "properties": {
    "addr:full":"Rijssensestraat 84 Nijverdal Overijssel 7442 ML",
    "addr:housenumber":"84",
    "addr:postcode":"7442 ml",
    "addr:street":"Rijssensestraat",
    "iso:country":"NL",
    "sg:address":"Rijssensestraat 84",
    "sg:city":"Nijverdal",
    "sg:orig_category":"Werving And Selectie Van Tijdelijk Personeel And Uitzendkantoren",
    "sg:phone":"+31 548 621 180",
    "sg:postcode":"7442 ML",
    "sg:province":"Overijssel",
    "wof:name":"Randstad",
    "wof:placetype":"venue"
},
  "geometry": {"coordinates":[6.4604902267,52.3618202209],"type":"Point"}
}