{
  "type": "Feature",
  "properties": {
    "addr:full":"David Ben Goerionstraat 35 Utrecht Utrecht 3573 XM",
    "addr:housenumber":"35",
    "addr:postcode":"3573 xm",
    "addr:street":"David Ben Goerionstraat",
    "iso:country":"NL",
    "sg:address":"David Ben Goerionstraat 35",
    "sg:city":"Utrecht",
    "sg:orig_category":"Verzekeringen",
    "sg:phone":"+31 30 271 7817",
    "sg:postcode":"3573 XM",
    "sg:province":"Utrecht",
    "wof:name":"S.C. Van Der Burgh",
    "wof:placetype":"venue"
},
  "geometry": {"coordinates":[5.145985,52.113827],"type":"Point"}
}