{
  "type": "Feature",
  "properties": {
    "addr:full":"Ir F W Conradstr 30 Nieuwegein Utrecht 3433 AL",
    "addr:housenumber":"30",
    "addr:postcode":"3433 al",
    "addr:street":"Ir;W",
    "iso:country":"NL",
    "sg:address":"Ir F W Conradstr 30",
    "sg:city":"Nieuwegein",
    "sg:orig_category":"Autorijscholen",
    "sg:phone":"+31 30 606 5692",
    "sg:postcode":"3433 AL",
    "sg:province":"Utrecht",
    "wof:name":"Expres Nieuwegein",
    "wof:placetype":"venue"
},
  "geometry": {"coordinates":[5.102176,52.010513],"type":"Point"}
}