{
  "type": "Feature",
  "properties": {
    "iso:country":"NL",
    "sg:address":"Prinsenpln 27",
    "sg:city":"Meppel",
    "sg:orig_category":"Kappers",
    "sg:phone":"+31 522 252 325",
    "sg:postcode":"7941 KV",
    "sg:province":"Drenthe",
    "wof:name":"Erwie",
    "wof:placetype":"venue"
},
  "geometry": {"coordinates":[6.1934962273,52.6967582703],"type":"Point"}
}