{
  "type": "Feature",
  "properties": {
    "addr:full":"Prinsenpln 27 Meppel Drenthe 7941 KV",
    "addr:housenumber":"27",
    "addr:postcode":"7941 kv",
    "addr:street":"Prinsenpln",
    "iso:country":"NL",
    "sg:address":"Prinsenpln 27",
    "sg:city":"Meppel",
    "sg:orig_category":"Kappers",
    "sg:phone":"+31 522 252 325",
    "sg:postcode":"7941 KV",
    "sg:province":"Drenthe",
    "wof:name":"Erwie",
    "wof:placetype":"venue"
},
  "geometry": {"coordinates":[6.1934962273,52.6967582703],"type":"Point"}
}