{
  "type": "Feature",
  "properties": {
    "addr:full":"Leuvenumseveld 9 Ermelo Gelderland 3852 PE",
    "addr:housenumber":"9",
    "addr:postcode":"3852 pe",
    "addr:street":"Leuvenumseveld;Gelderland",
    "iso:country":"NL",
    "sg:address":"Leuvenumseveld 9",
    "sg:city":"Ermelo",
    "sg:orig_category":"Zuivel - Fabrieken",
    "sg:phone":"+31 577 406 111",
    "sg:postcode":"3852 PE",
    "sg:province":"Gelderland",
    "wof:name":"Klaremelk Bv",
    "wof:placetype":"venue"
},
  "geometry": {"coordinates":[5.71027,52.272419],"type":"Point"}
}