{
  "type": "Feature",
  "properties": {
    "addr:full":"F Haverschmidtwei 2 Leeuwarden Provincie Friesland 8914 BC",
    "addr:housenumber":"2",
    "addr:postcode":"8914 bc",
    "addr:street":"F Haverschmidtwei;Provincie Friesland",
    "iso:country":"NL",
    "sg:address":"F Haverschmidtwei 2",
    "sg:city":"Leeuwarden",
    "sg:orig_category":"Arbo- En Bedrijfsgezondheids- Diensten",
    "sg:phone":"+31 58 253 4300",
    "sg:postcode":"8914 BC",
    "sg:province":"Provincie Friesland",
    "sg:website":"http://www.arboduo.nl",
    "wof:name":"Arboduo Leeuwarden",
    "wof:placetype":"venue"
},
  "geometry": {"coordinates":[5.766599,53.204617],"type":"Point"}
}