{
  "type": "Feature",
  "properties": {
    "addr:full":"Planciusplantsoen 14 Voorschoten Zuid-Holland 2253 TS",
    "addr:housenumber":"14",
    "addr:postcode":"2253 ts",
    "addr:street":"Planciusplantsoen",
    "iso:country":"NL",
    "sg:address":"Planciusplantsoen 14",
    "sg:city":"Voorschoten",
    "sg:orig_category":"Kappers",
    "sg:phone":"+31 71 531 0707",
    "sg:postcode":"2253 TS",
    "sg:province":"Zuid-Holland",
    "wof:name":"Image Hairline",
    "wof:placetype":"venue"
},
  "geometry": {"coordinates":[4.4608039856,52.1419258118],"type":"Point"}
}