{
  "type": "Feature",
  "properties": {
    "addr:full":"Constantijnstraat 29 Nijverdal Overijssel 7442 MP",
    "addr:housenumber":"29",
    "addr:postcode":"7442 mp",
    "addr:street":"Constantijnstraat",
    "iso:country":"NL",
    "sg:address":"Constantijnstraat 29",
    "sg:city":"Nijverdal",
    "sg:classifiers":[
        {
            "category":"Communications",
            "subcategory":"Television Station",
            "type":"Services"
        }
    ],
    "sg:phone":"+31 548 611 482",
    "sg:postcode":"7442 MP",
    "sg:province":"Overijssel",
    "sg:tags":[
        "video",
        "audio",
        "verhuur"
    ],
    "wof:name":"Freetime Videotheek",
    "wof:placetype":"venue"
},
  "geometry": {"coordinates":[6.461322,52.363312],"type":"Point"}
}