{
  "type": "Feature",
  "properties": {
    "addr:full":"Elisabethvloed 11 Honselersdyk South Holland 2675 RD",
    "addr:housenumber":"11",
    "addr:postcode":"2675 rd",
    "addr:street":"Elisabethvloed",
    "iso:country":"NL",
    "sg:address":"Elisabethvloed 11",
    "sg:city":"Honselersdyk",
    "sg:orig_category":"Bijouterie?n",
    "sg:phone":"+31 174 630 817",
    "sg:postcode":"2675 RD",
    "sg:province":"South Holland",
    "wof:name":"Bij Jou Passend",
    "wof:placetype":"venue"
},
  "geometry": {"coordinates":[4.227138,52.009155],"type":"Point"}
}