{
  "type": "Feature",
  "properties": {
    "addr:full":"Voorstr 16 Woudenberg Utrecht 3931 HD",
    "addr:housenumber":"16",
    "addr:postcode":"3931 hd",
    "addr:street":"Voorstr",
    "iso:country":"NL",
    "sg:address":"Voorstr 16",
    "sg:city":"Woudenberg",
    "sg:orig_category":"Parketvloeren",
    "sg:phone":"+31 33 286 4788",
    "sg:postcode":"3931 HD",
    "sg:province":"Utrecht",
    "wof:name":"Rosa Parket",
    "wof:placetype":"venue"
},
  "geometry": {"coordinates":[5.413124,52.082485],"type":"Point"}
}