{
  "type": "Feature",
  "properties": {
    "addr:full":"Haarveen 7 Foxwolde Drenthe 9314 TD",
    "addr:housenumber":"7",
    "addr:postcode":"9314 td",
    "addr:street":"Haarveen",
    "iso:country":"NL",
    "sg:address":"Haarveen 7",
    "sg:city":"Foxwolde",
    "sg:orig_category":"Gehandicapteninformatie",
    "sg:phone":"+31 50 501 4007",
    "sg:postcode":"9314 TD",
    "sg:province":"Drenthe",
    "wof:name":"Brug Provincie Groningen, St De",
    "wof:placetype":"venue"
},
  "geometry": {"coordinates":[6.451906,53.153656],"type":"Point"}
}