{
  "type": "Feature",
  "properties": {
    "addr:full":"Hilvertsweg 144 Hilversum Noord-Holland 1214 JL",
    "addr:housenumber":"144",
    "addr:postcode":"1214 jl",
    "addr:street":"Hilvertsweg",
    "iso:country":"NL",
    "sg:address":"Hilvertsweg 144",
    "sg:city":"Hilversum",
    "sg:orig_category":"Kappers",
    "sg:phone":"+31 35 628 9512",
    "sg:postcode":"1214 JL",
    "sg:province":"Noord-Holland",
    "wof:name":"Rivaldi'S Haarmode",
    "wof:placetype":"venue"
},
  "geometry": {"coordinates":[5.16767,52.21349],"type":"Point"}
}