{
  "type": "Feature",
  "properties": {
    "addr:full":"Fransestraat 30 Nijmegen Gelderland 6524 JC",
    "addr:housenumber":"30",
    "addr:postcode":"6524 jc",
    "addr:street":"Fransestraat;Gelderland",
    "iso:country":"NL",
    "sg:address":"Fransestraat 30",
    "sg:city":"Nijmegen",
    "sg:orig_category":"Diverse Grafische Activiteiten",
    "sg:phone":"+31 24 360 0763",
    "sg:postcode":"6524 JC",
    "sg:province":"Gelderland",
    "wof:name":"Louman En Friso",
    "wof:placetype":"venue"
},
  "geometry": {"coordinates":[5.863187,51.838299],"type":"Point"}
}