{
  "type": "Feature",
  "properties": {
    "addr:full":"De Streekwg 33 Den Andel Groningen 9956 PN",
    "addr:housenumber":"33",
    "addr:postcode":"andel;9956 pn",
    "addr:street":"Den",
    "iso:country":"NL",
    "sg:address":"De Streekwg 33",
    "sg:city":"Den Andel",
    "sg:orig_category":"Verenigingsgebouwen",
    "sg:phone":"+31 595 424 400",
    "sg:postcode":"9956 PN",
    "sg:province":"Groningen",
    "wof:name":"Andel, Den",
    "wof:placetype":"venue"
},
  "geometry": {"coordinates":[6.508264,53.391018],"type":"Point"}
}