{
  "type": "Feature",
  "properties": {
    "addr:full":"Roemer Visscherlaan 9 Roosendaal Noord-Brabant 4707 BX",
    "addr:housenumber":"9",
    "addr:postcode":"4707 bx",
    "addr:street":"Roemer Visscherlaan",
    "iso:country":"NL",
    "sg:address":"Roemer Visscherlaan 9",
    "sg:city":"Roosendaal",
    "sg:orig_category":"Tandartsen",
    "sg:phone":"+31 165 545 930",
    "sg:postcode":"4707 BX",
    "sg:province":"Noord-Brabant",
    "wof:name":"J.B. De Braaf",
    "wof:placetype":"venue"
},
  "geometry": {"coordinates":[4.460319,51.521561],"type":"Point"}
}