{
  "type": "Feature",
  "properties": {
    "addr:full":"Padangstr 5 Enschede NL.08 7535 AA",
    "addr:housenumber":"5",
    "addr:postcode":"7535 aa",
    "addr:street":"Padangstr",
    "iso:country":"NL",
    "sg:address":"Padangstr 5",
    "sg:city":"Enschede",
    "sg:orig_category":"Podotherapeuten",
    "sg:phone":"+31 53 430 5987",
    "sg:postcode":"7535 AA",
    "sg:province":"NL.08",
    "wof:name":"Wakeren, Van",
    "wof:placetype":"venue"
},
  "geometry": {"coordinates":[6.909957,52.213604],"type":"Point"}
}