{
  "type": "Feature",
  "properties": {
    "iso:country":"NL",
    "sg:address":"Hezer Enghwg 72",
    "sg:city":"Den Dolder",
    "sg:orig_category":"Adviesbureaus Beroeps- En Schoolkeuze",
    "sg:phone":"+31 30 280 3217",
    "sg:postcode":"3734 GT",
    "sg:province":"Utrecht",
    "wof:name":"All-Omm",
    "wof:placetype":"venue"
},
  "geometry": {"coordinates":[5.236769,52.137733],"type":"Point"}
}