{
  "type": "Feature",
  "properties": {
    "addr:full":"G V Amstelstr 117 Hilversum Noord-Holland 1214 AW",
    "addr:housenumber":"117",
    "addr:postcode":"1214 aw",
    "addr:street":"V Amstelstr",
    "iso:country":"NL",
    "sg:address":"G V Amstelstr 117",
    "sg:city":"Hilversum",
    "sg:orig_category":"Broodjeszaken",
    "sg:phone":"+31 35 624 4310",
    "sg:postcode":"1214 AW",
    "sg:province":"Noord-Holland",
    "wof:name":"Petit Pain, Le",
    "wof:placetype":"venue"
},
  "geometry": {"coordinates":[5.1695,52.228565],"type":"Point"}
}