{
  "type": "Feature",
  "properties": {
    "addr:full":"Alexanderstr 35 S Gravenhage South Holland 2514 JL",
    "addr:housenumber":"35",
    "addr:postcode":"2514 jl",
    "addr:street":"Alexanderstr;S Gravenhage",
    "iso:country":"NL",
    "sg:address":"Alexanderstr 35",
    "sg:city":"S Gravenhage",
    "sg:orig_category":"Farmaceutische Industrie En Groothandel",
    "sg:phone":"+31 70 302 5700",
    "sg:postcode":"2514 JL",
    "sg:province":"South Holland",
    "sg:website":"http://www.serono.nl/nl/yourhost.htm",
    "wof:name":"Serono Benelux Bv",
    "wof:placetype":"venue"
},
  "geometry": {"coordinates":[4.30935,52.084148],"type":"Point"}
}