{
  "type": "Feature",
  "properties": {
    "addr:full":"Hella Haassestraat 13 Leiderdorp South Holland 2353 LK",
    "addr:housenumber":"13",
    "addr:postcode":"2353 lk",
    "addr:street":"Hella Haassestraat",
    "iso:country":"NL",
    "sg:address":"Hella Haassestraat 13",
    "sg:city":"Leiderdorp",
    "sg:orig_category":"Boekhouders",
    "sg:phone":"+31 71 541 2160",
    "sg:postcode":"2353 LK",
    "sg:province":"South Holland",
    "wof:name":"Drs C Luijtze",
    "wof:placetype":"venue"
},
  "geometry": {"coordinates":[4.530116,52.166439],"type":"Point"}
}