{
  "type": "Feature",
  "properties": {
    "addr:full":"Prometheusstr 32 Rotterdam Zuid-Holland 3054 WD",
    "addr:housenumber":"32",
    "addr:postcode":"3054 wd",
    "addr:street":"Prometheusstr",
    "iso:country":"NL",
    "sg:address":"Prometheusstr 32",
    "sg:city":"Rotterdam",
    "sg:orig_category":"Onderhoudswerken",
    "sg:phone":"+31 10 418 8076",
    "sg:postcode":"3054 WD",
    "sg:province":"Zuid-Holland",
    "wof:name":"Weide, B Van Der",
    "wof:placetype":"venue"
},
  "geometry": {"coordinates":[4.489049,51.965195],"type":"Point"}
}