{
  "type": "Feature",
  "properties": {
    "iso:country":"NL",
    "sg:address":"Prinsenkamp 90",
    "sg:city":"Vroomshoop",
    "sg:orig_category":"Verhuur Bouwmachines",
    "sg:phone":"+31 546 641 961",
    "sg:postcode":"7681 BH",
    "sg:province":"NL.08",
    "wof:name":"Verhuurbedr. V. Grondverzetmach. P.A. V.",
    "wof:placetype":"venue"
},
  "geometry": {"coordinates":[6.571392,52.4543],"type":"Point"}
}