{
  "type": "Feature",
  "properties": {
    "addr:full":"Prinsenkamp 90 Vroomshoop NL.08 7681 BH",
    "addr:housenumber":"90;nl.08",
    "addr:postcode":"7681 bh",
    "addr:street":"Prinsenkamp",
    "iso:country":"NL",
    "sg:address":"Prinsenkamp 90",
    "sg:city":"Vroomshoop",
    "sg:orig_category":"Verhuur Bouwmachines",
    "sg:phone":"+31 546 641 961",
    "sg:postcode":"7681 BH",
    "sg:province":"NL.08",
    "wof:name":"Verhuurbedr. V. Grondverzetmach. P.A. V.",
    "wof:placetype":"venue"
},
  "geometry": {"coordinates":[6.571392,52.4543],"type":"Point"}
}