{
  "type": "Feature",
  "properties": {
    "addr:full":"Buizerdstraat 6 Leerdam Zuid-Holland 4143 BA",
    "addr:housenumber":"6",
    "addr:postcode":"4143 ba",
    "addr:street":"Buizerdstraat",
    "iso:country":"NL",
    "sg:address":"Buizerdstraat 6",
    "sg:city":"Leerdam",
    "sg:orig_category":"Grafologen, Handlezers And Helderzienden",
    "sg:phone":"+31 345 617 220",
    "sg:postcode":"4143 BA",
    "sg:province":"Zuid-Holland",
    "wof:name":"Mevr H J M Hermans",
    "wof:placetype":"venue"
},
  "geometry": {"coordinates":[5.087026,51.895947],"type":"Point"}
}