{
  "type": "Feature",
  "properties": {
    "addr:full":"Kerkstr 4 Huizen Noord-Holland 1271 RL",
    "addr:housenumber":"4",
    "addr:postcode":"1271 rl",
    "addr:street":"Kerkstr",
    "iso:country":"NL",
    "sg:address":"Kerkstr 4",
    "sg:city":"Huizen",
    "sg:orig_category":"Bibliotheken En Leeszalen Openbare",
    "sg:phone":"+31 35 525 1633",
    "sg:postcode":"1271 RL",
    "sg:province":"Noord-Holland",
    "wof:name":"Openb Bibliotheek",
    "wof:placetype":"venue"
},
  "geometry": {"coordinates":[5.232482,52.297211],"type":"Point"}
}