{
  "type": "Feature",
  "properties": {
    "iso:country":"NL",
    "sg:address":"Rodenburgstraat 19",
    "sg:city":"Rotterdam",
    "sg:orig_category":"Verzekeringen",
    "sg:phone":"+31 10 437 8366",
    "sg:postcode":"3043 TS",
    "sg:province":"Zuid-Holland",
    "wof:name":"Chris Borgdorff Assurantie-Adviseur",
    "wof:placetype":"venue"
},
  "geometry": {"coordinates":[4.422594,51.941422],"type":"Point"}
}