{
  "type": "Feature",
  "properties": {
    "addr:full":"Kochspad 12 Blijham Groningen 9697 SV",
    "addr:housenumber":"12",
    "addr:postcode":"9697 sv",
    "addr:street":"Kochspad",
    "iso:country":"NL",
    "sg:address":"Kochspad 12",
    "sg:city":"Blijham",
    "sg:orig_category":"Metselwerken",
    "sg:phone":"+31 597 561 445",
    "sg:postcode":"9697 SV",
    "sg:province":"Groningen",
    "wof:name":"Koolhof Bv",
    "wof:placetype":"venue"
},
  "geometry": {"coordinates":[7.072986,53.111641],"type":"Point"}
}