{
  "type": "Feature",
  "properties": {
    "iso:country":"NL",
    "sg:address":"Arnhemsewg 35",
    "sg:city":"Rheden",
    "sg:orig_category":"Bloemen En Planten",
    "sg:phone":"+31 26 495 2310",
    "sg:postcode":"6991 DK",
    "sg:province":"Gelderland",
    "wof:name":"Broekie",
    "wof:placetype":"venue"
},
  "geometry": {"coordinates":[6.028828,52.005802],"type":"Point"}
}