{
  "type": "Feature",
  "properties": {
    "iso:country":"NL",
    "sg:address":"Nw Bosschewg 22",
    "sg:city":"Tilburg",
    "sg:orig_category":"Adviesbureaus Bedrijfsorganisatie",
    "sg:phone":"+31 13 536 3305",
    "sg:postcode":"5017 JM",
    "sg:province":"North Brabant",
    "sg:website":"http://www.becxenvanloon.nl",
    "wof:name":"Becx & Van Loon",
    "wof:placetype":"venue"
},
  "geometry": {"coordinates":[5.102163,51.559715],"type":"Point"}
}