{
  "type": "Feature",
  "properties": {
    "iso:country":"NL",
    "sg:address":"Pr Hendrikwg 3B",
    "sg:city":"Bennekom",
    "sg:orig_category":"Verzekeringen - Verzekeringskantoren",
    "sg:phone":"+31 318 611 263",
    "sg:postcode":"6721 AD",
    "sg:province":"Gelderland",
    "wof:name":"Stoel Bv",
    "wof:placetype":"venue"
},
  "geometry": {"coordinates":[5.687775,52.002914],"type":"Point"}
}