{
  "type": "Feature",
  "properties": {
    "iso:country":"NL",
    "sg:address":"Zonnebaan 30",
    "sg:city":"Utrecht",
    "sg:orig_category":"Babyartikelen",
    "sg:phone":"+31 30 241 2075",
    "sg:postcode":"3542 EE",
    "sg:province":"Utrecht",
    "wof:name":"Meevam Bv",
    "wof:placetype":"venue"
},
  "geometry": {"coordinates":[5.040106,52.118748],"type":"Point"}
}