{
  "type": "Feature",
  "properties": {
    "addr:full":"Gedempte Turfhaven 50 Hoorn Nh Noord-Holland 1621 HG",
    "addr:housenumber":"50",
    "addr:postcode":"1621 hg",
    "addr:street":"Gedempte Turfhaven",
    "iso:country":"NL",
    "sg:address":"Gedempte Turfhaven 50",
    "sg:city":"Hoorn Nh",
    "sg:orig_category":"Schilderwerk",
    "sg:phone":"+31 229 216 529",
    "sg:postcode":"1621 HG",
    "sg:province":"Noord-Holland",
    "wof:name":"Kalf Schilderwerken",
    "wof:placetype":"venue"
},
  "geometry": {"coordinates":[5.058043,52.642467],"type":"Point"}
}