{
  "type": "Feature",
  "properties": {
    "addr:full":"Groest 54 Hilversum North Holland 1211 EC",
    "addr:housenumber":"54",
    "addr:postcode":"1211 ec",
    "addr:street":"Groest",
    "iso:country":"NL",
    "sg:address":"Groest 54",
    "sg:city":"Hilversum",
    "sg:orig_category":"Opticiens",
    "sg:phone":"+31 35 623 8883",
    "sg:postcode":"1211 EC",
    "sg:province":"North Holland",
    "sg:website":"http://www.specsavers.nl",
    "wof:name":"Specsavers",
    "wof:placetype":"venue"
},
  "geometry": {"coordinates":[5.1773638725,52.2256698608],"type":"Point"}
}