{
  "type": "Feature",
  "properties": {
    "addr:full":"Hoofdweg 134 Westerhaar Vriezenv W Overijssel 7676 AJ",
    "addr:housenumber":"134",
    "addr:postcode":"7676 aj",
    "addr:street":"Hoofdweg;Westerhaar;W",
    "iso:country":"NL",
    "sg:address":"Hoofdweg 134",
    "sg:city":"Westerhaar Vriezenv W",
    "sg:orig_category":"Artsen And Specialisten",
    "sg:phone":"+31 546 659 205",
    "sg:postcode":"7676 AJ",
    "sg:province":"Overijssel",
    "wof:name":"Apotheekhoudend Huisarts J.M.H. Timmer",
    "wof:placetype":"venue"
},
  "geometry": {"coordinates":[6.619952,52.456234],"type":"Point"}
}