{
  "type": "Feature",
  "properties": {
    "addr:full":"Einsteinwg 13A Elst Gld Gelderland 6662 PW",
    "addr:housenumber":"13a",
    "addr:postcode":"6662 pw",
    "addr:street":"Einsteinwg;Gld Gelderland",
    "iso:country":"NL",
    "sg:address":"Einsteinwg 13A",
    "sg:city":"Elst Gld",
    "sg:orig_category":"Medische Installaties En Instrumenten",
    "sg:phone":"+31 481 377 797",
    "sg:postcode":"6662 PW",
    "sg:province":"Gelderland",
    "sg:website":"http://www.plexx.nl",
    "wof:name":"Plexx Bv",
    "wof:placetype":"venue"
},
  "geometry": {"coordinates":[5.865216,51.907654],"type":"Point"}
}