{
  "type": "Feature",
  "properties": {
    "iso:country":"NL",
    "sg:address":"C V Clevepk 52",
    "sg:city":"Amstelveen",
    "sg:orig_category":"Bedrijfsorganisaties",
    "sg:phone":"+31 20 345 4243",
    "sg:postcode":"1181 AV",
    "sg:province":"North Holland",
    "wof:name":"Eldoy",
    "wof:placetype":"venue"
},
  "geometry": {"coordinates":[4.856945,52.303444],"type":"Point"}
}