{
  "type": "Feature",
  "properties": {
    "iso:country":"NL",
    "sg:address":"Generaal Cronjestraat 28",
    "sg:city":"Haarlem",
    "sg:orig_category":"Werving And Selectie Van Tijdelijk Personeel And Uitzendkantoren",
    "sg:phone":"+31 23 527 2070",
    "sg:postcode":"2021 JJ",
    "sg:province":"North Holland",
    "wof:name":"Start",
    "wof:placetype":"venue"
},
  "geometry": {"coordinates":[4.641409874,52.3930702209],"type":"Point"}
}