{
  "type": "Feature",
  "properties": {
    "addr:full":"Reedk 101 Mynsheerenland South Holland 3271 LK",
    "addr:housenumber":"101",
    "addr:postcode":"3271 lk",
    "addr:street":"Mynsheerenland South",
    "iso:country":"NL",
    "sg:address":"Reedk 101",
    "sg:city":"Mynsheerenland",
    "sg:orig_category":"Bedden En Matrassen",
    "sg:phone":"+31 186 603 853",
    "sg:postcode":"3271 LK",
    "sg:province":"South Holland",
    "wof:name":"Chromo Country Home Bv",
    "wof:placetype":"venue"
},
  "geometry": {"coordinates":[4.48532,51.810555],"type":"Point"}
}