{
  "type": "Feature",
  "properties": {
    "addr:full":"Schokker 19 Zeewolde NL. 3891 DL",
    "addr:housenumber":"19",
    "addr:postcode":"3891 dl",
    "addr:street":"Schokker;Nl.",
    "iso:country":"NL",
    "sg:address":"Schokker 19",
    "sg:city":"Zeewolde",
    "sg:orig_category":"Verbouwingen",
    "sg:phone":"+31 6 51274363",
    "sg:postcode":"3891 DL",
    "sg:province":"NL.",
    "wof:name":"Malestein Factotum",
    "wof:placetype":"venue"
},
  "geometry": {"coordinates":[5.531775,52.3344],"type":"Point"}
}