{
  "type": "Feature",
  "properties": {
    "addr:full":"Kerkdwarsln 7 De Bilt Utrecht 3731 EM",
    "addr:housenumber":"7",
    "addr:postcode":"3731 em",
    "addr:street":"Kerkdwarsln",
    "iso:country":"NL",
    "sg:address":"Kerkdwarsln 7",
    "sg:city":"De Bilt",
    "sg:orig_category":"Makelaars En Adviseurs Onroerende Goederen",
    "sg:phone":"+31 30 221 0077",
    "sg:postcode":"3731 EM",
    "sg:province":"Utrecht",
    "wof:name":"Werkhoven",
    "wof:placetype":"venue"
},
  "geometry": {"coordinates":[5.179905,52.108021],"type":"Point"}
}