{
  "type": "Feature",
  "properties": {
    "addr:full":"Sont 16 Veendam Groningen 9642 BX",
    "addr:housenumber":"16",
    "addr:postcode":"9642 bx",
    "addr:street":"Sont",
    "iso:country":"NL",
    "sg:address":"Sont 16",
    "sg:city":"Veendam",
    "sg:orig_category":"Kinderopvang Behalve Thuis",
    "sg:phone":"+31 598 632 505",
    "sg:postcode":"9642 BX",
    "sg:province":"Groningen",
    "wof:name":"Mkd Veendam",
    "wof:placetype":"venue"
},
  "geometry": {"coordinates":[6.862863,53.096958],"type":"Point"}
}