{
  "type": "Feature",
  "properties": {
    "iso:country":"NL",
    "sg:address":"H Dunantwg 128",
    "sg:city":"Lochem",
    "sg:orig_category":"Psychologen",
    "sg:phone":"+31 573 257 247",
    "sg:postcode":"7242 HL",
    "sg:province":"Gelderland",
    "wof:name":"Groothedde",
    "wof:placetype":"venue"
},
  "geometry": {"coordinates":[6.400849,52.15596],"type":"Point"}
}