{
  "type": "Feature",
  "properties": {
    "addr:full":"Palestrinaln 6 Bilthoven Utrecht 3723 KN",
    "addr:housenumber":"6",
    "addr:postcode":"3723 kn",
    "addr:street":"Palestrinaln",
    "iso:country":"NL",
    "sg:address":"Palestrinaln 6",
    "sg:city":"Bilthoven",
    "sg:orig_category":"Adviesbureaus Bedrijfsorganisatie",
    "sg:phone":"+31 30 228 8371",
    "sg:postcode":"3723 KN",
    "sg:province":"Utrecht",
    "wof:name":"Kreuze, M",
    "wof:placetype":"venue"
},
  "geometry": {"coordinates":[5.219905,52.136948],"type":"Point"}
}