{
  "type": "Feature",
  "properties": {
    "iso:country":"NL",
    "sg:address":"Vlierboomstraat 573",
    "sg:city":"Den Haag",
    "sg:orig_category":"Paramedische Behandelingen",
    "sg:phone":"+31 70 325 1296",
    "sg:postcode":"2564 JH",
    "sg:province":"Zuid-Holland",
    "wof:name":"D.P.C Maas",
    "wof:placetype":"venue"
},
  "geometry": {"coordinates":[4.253699,52.067326],"type":"Point"}
}