{
  "type": "Feature",
  "properties": {
    "addr:full":"Marsstr 30 Sittard Limburg 6133 WL",
    "addr:housenumber":"30",
    "addr:postcode":"6133 wl",
    "addr:street":"Marsstr",
    "iso:country":"NL",
    "sg:address":"Marsstr 30",
    "sg:city":"Sittard",
    "sg:orig_category":"Kappers",
    "sg:phone":"+31 46 458 0392",
    "sg:postcode":"6133 WL",
    "sg:province":"Limburg",
    "wof:name":"Gruisen",
    "wof:placetype":"venue"
},
  "geometry": {"coordinates":[5.858341217,50.9842300415],"type":"Point"}
}