{
  "type": "Feature",
  "properties": {
    "addr:full":"Marconiplein 19 Rotterdam Zuid-Holland 3025 AV",
    "addr:housenumber":"19",
    "addr:postcode":"3025 av",
    "addr:street":"Marconiplein",
    "iso:country":"NL",
    "sg:address":"Marconiplein 19",
    "sg:city":"Rotterdam",
    "sg:orig_category":"Fruit And Groenten Gh",
    "sg:phone":"+31 10 476 2205",
    "sg:postcode":"3025 AV",
    "sg:province":"Zuid-Holland",
    "wof:name":"Dtc Fruit & Vegetables Vof",
    "wof:placetype":"venue"
},
  "geometry": {"coordinates":[4.433423,51.913021],"type":"Point"}
}