{
  "type": "Feature",
  "properties": {
    "addr:full":"Schorrenweg 20 Oosterend Nh Noord-Holland 1794 HG",
    "addr:housenumber":"20",
    "addr:postcode":"1794 hg",
    "addr:street":"Schorrenweg",
    "iso:country":"NL",
    "sg:address":"Schorrenweg 20",
    "sg:city":"Oosterend Nh",
    "sg:orig_category":"Bloemen And Planten",
    "sg:phone":"+31 222 318 364",
    "sg:postcode":"1794 HG",
    "sg:province":"Noord-Holland",
    "wof:name":"Tuincentrum Eureka Vof",
    "wof:placetype":"venue"
},
  "geometry": {"coordinates":[4.858908,53.100182],"type":"Point"}
}