{
  "type": "Feature",
  "properties": {
    "addr:full":"Plein 1945 87 Ijmuiden Noord-Holland 1971 GC",
    "addr:housenumber":"87",
    "addr:postcode":"1971 gc",
    "addr:street":"Plein 1945",
    "iso:country":"NL",
    "sg:address":"Plein 1945 87",
    "sg:city":"Ijmuiden",
    "sg:orig_category":"Kinderopvang Behalve Thuis",
    "sg:phone":"+31 255 516 537",
    "sg:postcode":"1971 GC",
    "sg:province":"Noord-Holland",
    "wof:name":"Stichting Kinderopvang Velsen",
    "wof:placetype":"venue"
},
  "geometry": {"coordinates":[4.624393,52.4599],"type":"Point"}
}