{
  "type": "Feature",
  "properties": {
    "addr:full":"Laat 5 Alkmaar North Holland 1811 EA",
    "addr:housenumber":"5",
    "addr:postcode":"1811 ea",
    "addr:street":"Laat",
    "iso:country":"NL",
    "sg:address":"Laat 5",
    "sg:city":"Alkmaar",
    "sg:orig_category":"Behangselpapier En Wandbekleding",
    "sg:phone":"+31 72 511 5354",
    "sg:postcode":"1811 EA",
    "sg:province":"North Holland",
    "wof:name":"Tames",
    "wof:placetype":"venue"
},
  "geometry": {"coordinates":[4.752329,52.628361],"type":"Point"}
}