{
  "type": "Feature",
  "properties": {
    "addr:full":"Meidoornln 14 Dalfsen Overijssel 7721 EZ",
    "addr:housenumber":"14",
    "addr:postcode":"7721 ez",
    "addr:street":"Meidoornln",
    "iso:country":"NL",
    "sg:address":"Meidoornln 14",
    "sg:city":"Dalfsen",
    "sg:orig_category":"Psychotherapeuten",
    "sg:phone":"+31 529 434 234",
    "sg:postcode":"7721 EZ",
    "sg:province":"Overijssel",
    "wof:name":"Emmelkamp En Drs M Emmelkamp-Keizer, Drs H",
    "wof:placetype":"venue"
},
  "geometry": {"coordinates":[6.248376,52.509773],"type":"Point"}
}