{
  "type": "Feature",
  "properties": {
    "addr:full":"Akkeroord 10 Rotterdam Zuid-Holland 3079 ZS",
    "addr:housenumber":"10",
    "addr:postcode":"3079 zs",
    "addr:street":"Akkeroord",
    "iso:country":"NL",
    "sg:address":"Akkeroord 10",
    "sg:city":"Rotterdam",
    "sg:orig_category":"Fitnesscentra",
    "sg:phone":"+31 10 483 6085",
    "sg:postcode":"3079 ZS",
    "sg:province":"Zuid-Holland",
    "sg:website":"http://www.stoker.nu",
    "wof:name":"Stoker",
    "wof:placetype":"venue"
},
  "geometry": {"coordinates":[4.557911,51.883972],"type":"Point"}
}