{
  "type": "Feature",
  "properties": {
    "addr:full":"Fazantstraat 9 Numansdorp South Holland 3281 RL",
    "addr:housenumber":"9",
    "addr:postcode":"3281 rl",
    "addr:street":"Fazantstraat",
    "iso:country":"NL",
    "sg:address":"Fazantstraat 9",
    "sg:city":"Numansdorp",
    "sg:orig_category":"Marketingbureaus",
    "sg:phone":"+31 186 654 004",
    "sg:postcode":"3281 RL",
    "sg:province":"South Holland",
    "wof:name":"Communicatieadviesburo Insert",
    "wof:placetype":"venue"
},
  "geometry": {"coordinates":[4.444778,51.730858],"type":"Point"}
}