{
  "type": "Feature",
  "properties": {
    "addr:full":"Fazantstraat 59 Rotterdam South Holland 3083 ZD",
    "addr:housenumber":"59",
    "addr:postcode":"3083 zd",
    "addr:street":"Fazantstraat",
    "iso:country":"NL",
    "sg:address":"Fazantstraat 59",
    "sg:city":"Rotterdam",
    "sg:orig_category":"Boekhouders",
    "sg:phone":"+31 10 481 5456",
    "sg:postcode":"3083 ZD",
    "sg:province":"South Holland",
    "wof:name":"Pasle",
    "wof:placetype":"venue"
},
  "geometry": {"coordinates":[4.473665,51.887875],"type":"Point"}
}