{
  "type": "Feature",
  "properties": {
    "iso:country":"NL",
    "sg:address":"De Oude Grutmolen 2",
    "sg:city":"Amersfoort",
    "sg:orig_category":"Administratie- En Boekhoudkantoren",
    "sg:phone":"+31 33 455 0469",
    "sg:postcode":"3824 XE",
    "sg:province":"Utrecht",
    "wof:name":"Galjee, Adm En Fin Buro",
    "wof:placetype":"venue"
},
  "geometry": {"coordinates":[5.38201,52.199261],"type":"Point"}
}