{
  "type": "Feature",
  "properties": {
    "iso:country":"NL",
    "sg:address":"Kostverlorenstraat 102",
    "sg:city":"Zandvoort",
    "sg:orig_category":"Juweliers",
    "sg:phone":"+31 23 571 7218",
    "sg:postcode":"2042 PK",
    "sg:province":"North Holland",
    "wof:name":"Pearl Service",
    "wof:placetype":"venue"
},
  "geometry": {"coordinates":[4.540896,52.371277],"type":"Point"}
}