{
  "type": "Feature",
  "properties": {
    "iso:country":"NL",
    "sg:address":"Roermondspln 20",
    "sg:city":"Arnhem",
    "sg:orig_category":"Bodemonderzoek",
    "sg:phone":"+31 26 445 0864",
    "sg:postcode":"6811 JN",
    "sg:province":"Gelderland",
    "sg:website":"http://www.ho-register.nl",
    "wof:name":"Register Historisch Onderzoeksbureau",
    "wof:placetype":"venue"
},
  "geometry": {"coordinates":[5.903057,51.980453],"type":"Point"}
}