{
  "type": "Feature",
  "properties": {
    "iso:country":"NL",
    "sg:address":"W Ten Catestr 56",
    "sg:city":"Hengelo Ov",
    "sg:orig_category":"Accountants - Administratie- Consulenten En -Kantoren",
    "sg:phone":"+31 74 291 3048",
    "sg:postcode":"7551 HZ",
    "sg:province":"Overijssel",
    "wof:name":"Bilanx",
    "wof:placetype":"venue"
},
  "geometry": {"coordinates":[6.789712,52.266361],"type":"Point"}
}