{
  "type": "Feature",
  "properties": {
    "addr:full":"Valkreek 64 Rotterdam Zuid-Holland 3079 AN",
    "addr:housenumber":"64",
    "addr:postcode":"3079 an",
    "addr:street":"Valkreek",
    "iso:country":"NL",
    "sg:address":"Valkreek 64",
    "sg:city":"Rotterdam",
    "sg:orig_category":"Artsen - Huisartsen",
    "sg:phone":"+31 10 483 5578",
    "sg:postcode":"3079 AN",
    "sg:province":"Zuid-Holland",
    "wof:name":"Levin, A I",
    "wof:placetype":"venue"
},
  "geometry": {"coordinates":[4.538486,51.885281],"type":"Point"}
}