{
  "type": "Feature",
  "properties": {
    "addr:full":"Ged Raamgr 13/Zw Haarlem Noord-Holland 2011 WE",
    "addr:housenumber":"13 / zw",
    "addr:postcode":"2011 we",
    "iso:country":"NL",
    "sg:address":"Ged Raamgr 13/Zw",
    "sg:city":"Haarlem",
    "sg:orig_category":"Kappers",
    "sg:phone":"+31 23 542 3565",
    "sg:postcode":"2011 WE",
    "sg:province":"Noord-Holland",
    "wof:name":"Martin",
    "wof:placetype":"venue"
},
  "geometry": {"coordinates":[4.642253,52.380562],"type":"Point"}
}