{
  "type": "Feature",
  "properties": {
    "addr:full":"Uyterschootwg 18 Middelburg Zeeland 4338 PN",
    "addr:housenumber":"18",
    "addr:postcode":"4338 pn",
    "addr:street":"Uyterschootwg",
    "iso:country":"NL",
    "sg:address":"Uyterschootwg 18",
    "sg:city":"Middelburg",
    "sg:orig_category":"Metaalbewerking",
    "sg:phone":"+31 118 625 516",
    "sg:postcode":"4338 PN",
    "sg:province":"Zeeland",
    "wof:name":"Tpu Services Bv",
    "wof:placetype":"venue"
},
  "geometry": {"coordinates":[3.646106,51.501968],"type":"Point"}
}