{
  "type": "Feature",
  "properties": {
    "addr:full":"St Rochusstr 5 Nederweert Limburg 6031 BG",
    "addr:housenumber":"5",
    "addr:postcode":"6031",
    "iso:country":"NL",
    "sg:address":"St Rochusstr 5",
    "sg:city":"Nederweert",
    "sg:classifiers":[
        {
            "category":"Food & Beverages",
            "subcategory":"Bakery",
            "type":"Retail Goods"
        }
    ],
    "sg:phone":"+31 495 631 422",
    "sg:postcode":"6031 BG",
    "sg:province":"Limburg",
    "sg:tags":[
        "brood",
        "en",
        "banket"
    ],
    "wof:name":"Kessels, Tjeu",
    "wof:placetype":"venue"
},
  "geometry": {"coordinates":[5.755608,51.283218],"type":"Point"}
}