{
  "type": "Feature",
  "properties": {
    "addr:full":"Koolmees 40 Ijsselmuiden Overijssel 8271 HM",
    "addr:housenumber":"40",
    "addr:postcode":"8271 hm",
    "addr:street":"Koolmees",
    "iso:country":"NL",
    "sg:address":"Koolmees 40",
    "sg:city":"Ijsselmuiden",
    "sg:orig_category":"Boekhouders",
    "sg:phone":"+31 38 333 0999",
    "sg:postcode":"8271 HM",
    "sg:province":"Overijssel",
    "wof:name":"Administratiekantoor Meuleman",
    "wof:placetype":"venue"
},
  "geometry": {"coordinates":[5.942302,52.563721],"type":"Point"}
}