{
  "type": "Feature",
  "properties": {
    "addr:full":"H De Manstr 6 Ridderkerk Zuid-Holland 2985 TH",
    "addr:housenumber":"6",
    "addr:postcode":"2985 th",
    "iso:country":"NL",
    "sg:address":"H De Manstr 6",
    "sg:city":"Ridderkerk",
    "sg:orig_category":"Schoonheidsinstituten",
    "sg:phone":"+31 180 424 513",
    "sg:postcode":"2985 TH",
    "sg:province":"Zuid-Holland",
    "wof:name":"Farah",
    "wof:placetype":"venue"
},
  "geometry": {"coordinates":[4.6023302078,51.8643798828],"type":"Point"}
}