{
  "type": "Feature",
  "properties": {
    "addr:full":"Schatbeurderlaan 9 Weert Limburg 6002 ED",
    "addr:housenumber":"9",
    "addr:postcode":"6002 ed",
    "addr:street":"Schatbeurderlaan",
    "iso:country":"NL",
    "sg:address":"Schatbeurderlaan 9",
    "sg:city":"Weert",
    "sg:orig_category":"Elektronische Bedrijfsinstallaties",
    "sg:phone":"+31 495 457 555",
    "sg:postcode":"6002 ED",
    "sg:province":"Limburg",
    "wof:name":"Tep",
    "wof:placetype":"venue"
},
  "geometry": {"coordinates":[5.697764,51.25967],"type":"Point"}
}