{
  "type": "Feature",
  "properties": {
    "addr:full":"De Omloop 5 Beilen Provincie Drenthe 9411 KA",
    "addr:housenumber":"5",
    "addr:postcode":"9411 ka",
    "addr:street":"De Omloop;Provincie Drenthe",
    "iso:country":"NL",
    "sg:address":"De Omloop 5",
    "sg:city":"Beilen",
    "sg:orig_category":"Meubelen",
    "sg:phone":"+31 593 524 770",
    "sg:postcode":"9411 KA",
    "sg:province":"Provincie Drenthe",
    "sg:website":"http://www.oostlandwoonland.nl",
    "wof:name":"Oostland Woonland",
    "wof:placetype":"venue"
},
  "geometry": {"coordinates":[6.507667,52.857548],"type":"Point"}
}