{
  "type": "Feature",
  "properties": {
    "addr:full":"De Bleek 72 Venray Limburg 5801 MD",
    "addr:housenumber":"72",
    "addr:postcode":"5801",
    "addr:street":"De Bleek",
    "iso:country":"NL",
    "sg:address":"De Bleek 72",
    "sg:city":"Venray",
    "sg:orig_category":"Verzekerings- Maatschappijen",
    "sg:phone":"+31 77 387 9391",
    "sg:postcode":"5801 MD",
    "sg:province":"Limburg",
    "wof:name":"Vgz",
    "wof:placetype":"venue"
},
  "geometry": {"coordinates":[5.973751,51.525753],"type":"Point"}
}