{
  "type": "Feature",
  "properties": {
    "addr:full":"Voorsterweg 115 Loenen Gld Gelderland 7371 EK",
    "addr:housenumber":"115",
    "addr:postcode":"7371 ek",
    "addr:street":"Voorsterweg;Gld Gelderland",
    "iso:country":"NL",
    "sg:address":"Voorsterweg 115",
    "sg:city":"Loenen Gld",
    "sg:orig_category":"Goederenvervoer Over De Weg",
    "sg:phone":"+31 55 505 1935",
    "sg:postcode":"7371 EK",
    "sg:province":"Gelderland",
    "wof:name":"Transportbedrijf Thomassen Bv",
    "wof:placetype":"venue"
},
  "geometry": {"coordinates":[6.052179,52.137383],"type":"Point"}
}