{
  "type": "Feature",
  "properties": {
    "addr:full":"Breedeplaats 6 Franeker Friesland 8801 LZ",
    "addr:housenumber":"6",
    "addr:postcode":"8801 lz",
    "addr:street":"Breedeplaats",
    "iso:country":"NL",
    "sg:address":"Breedeplaats 6",
    "sg:city":"Franeker",
    "sg:classifiers":[
        {
            "category":"Travel",
            "subcategory":"Hotels & Motels",
            "type":"Entertainment"
        }
    ],
    "sg:phone":"+31 517 392 261",
    "sg:postcode":"8801 LZ",
    "sg:province":"Friesland",
    "wof:name":"Grandcafe De Doelen",
    "wof:placetype":"venue"
},
  "geometry": {"coordinates":[5.544397,53.186134],"type":"Point"}
}