{
  "type": "Feature",
  "properties": {
    "addr:full":"Zonnebaan 18 Utrecht Utrecht 3542 ED",
    "addr:housenumber":"18",
    "addr:postcode":"3542 ed",
    "addr:street":"Zonnebaan",
    "iso:country":"NL",
    "sg:address":"Zonnebaan 18",
    "sg:city":"Utrecht",
    "sg:orig_category":"Product-Promotie",
    "sg:phone":"+31 30 262 6060",
    "sg:postcode":"3542 ED",
    "sg:province":"Utrecht",
    "wof:name":"Amigos",
    "wof:placetype":"venue"
},
  "geometry": {"coordinates":[5.0412549973,52.119644165],"type":"Point"}
}