{
  "type": "Feature",
  "properties": {
    "addr:full":"Ryksstrwg 61 Bennebroek North Holland 2121 AC",
    "addr:housenumber":"61",
    "addr:postcode":"2121 ac",
    "addr:street":"Ryksstrwg",
    "iso:country":"NL",
    "sg:address":"Ryksstrwg 61",
    "sg:city":"Bennebroek",
    "sg:orig_category":"Accountants - Administratie- Consulenten En -Kantoren",
    "sg:phone":"+31 23 584 6587",
    "sg:postcode":"2121 AC",
    "sg:province":"North Holland",
    "wof:name":"Baaren, Van",
    "wof:placetype":"venue"
},
  "geometry": {"coordinates":[4.593208,52.32214],"type":"Point"}
}