{
  "type": "Feature",
  "properties": {
    "addr:full":"Vlinderveen 453 Spijkenisse Zuid-Holland 3205 EE",
    "addr:housenumber":"453",
    "addr:postcode":"3205 ee",
    "addr:street":"Vlinderveen",
    "iso:country":"NL",
    "sg:address":"Vlinderveen 453",
    "sg:city":"Spijkenisse",
    "sg:orig_category":"Kaas",
    "sg:phone":"+31 181 640 486",
    "sg:postcode":"3205 EE",
    "sg:province":"Zuid-Holland",
    "wof:name":"Boernhoeck, In Den",
    "wof:placetype":"venue"
},
  "geometry": {"coordinates":[4.3431248665,51.8331451416],"type":"Point"}
}