{
  "type": "Feature",
  "properties": {
    "addr:full":"Markeweg 23 Blesdijke Provincie Friesland 8398 GK",
    "addr:housenumber":"23",
    "addr:postcode":"8398 gk",
    "addr:street":"Markeweg;Provincie Friesland",
    "iso:country":"NL",
    "sg:address":"Markeweg 23",
    "sg:city":"Blesdijke",
    "sg:orig_category":"Levende Dieren Gh",
    "sg:phone":"+31 561 441 434",
    "sg:postcode":"8398 GK",
    "sg:province":"Provincie Friesland",
    "wof:name":"Bert Sloot Bv",
    "wof:placetype":"venue"
},
  "geometry": {"coordinates":[6.039348,52.840862],"type":"Point"}
}