{
  "type": "Feature",
  "properties": {
    "addr:full":"Wilhelminastr 38 Emmen Drenthe 7811 JC",
    "addr:housenumber":"38",
    "addr:postcode":"7811 jc",
    "addr:street":"Wilhelminastr",
    "iso:country":"NL",
    "sg:address":"Wilhelminastr 38",
    "sg:city":"Emmen",
    "sg:orig_category":"Wasmachines En Wasdrogers - Onderhoud En Reparatie",
    "sg:phone":"+31 591 641 126",
    "sg:postcode":"7811 JC",
    "sg:province":"Drenthe",
    "wof:name":"Onderdelenhuis Vof, Het",
    "wof:placetype":"venue"
},
  "geometry": {"coordinates":[6.8968639374,52.781162262],"type":"Point"}
}