{
  "type": "Feature",
  "properties": {
    "iso:country":"NL",
    "sg:address":"Belenbroekln 65",
    "sg:city":"Heythuysen",
    "sg:orig_category":"Koel- En Vriestransporten",
    "sg:phone":"+31 475 492 384",
    "sg:postcode":"6093 BT",
    "sg:province":"Limburg",
    "wof:name":"Maris, Van",
    "wof:placetype":"venue"
},
  "geometry": {"coordinates":[5.884373,51.249943],"type":"Point"}
}