{
  "type": "Feature",
  "properties": {
    "addr:full":"Marsmanpln 13 Haarlem Noord-Holland 2025 DT",
    "addr:housenumber":"13",
    "addr:postcode":"2025 dt",
    "addr:street":"Marsmanpln",
    "iso:country":"NL",
    "sg:address":"Marsmanpln 13",
    "sg:city":"Haarlem",
    "sg:orig_category":"Kappers",
    "sg:phone":"+31 23 537 5661",
    "sg:postcode":"2025 DT",
    "sg:province":"Noord-Holland",
    "wof:name":"Bert",
    "wof:placetype":"venue"
},
  "geometry": {"coordinates":[4.6477627754,52.4168281555],"type":"Point"}
}