{
  "type": "Feature",
  "properties": {
    "addr:full":"Marktstraat 11 Ootmarsum Overijssel 7631 BX",
    "addr:housenumber":"11",
    "addr:postcode":"7631 bx",
    "addr:street":"Marktstraat",
    "iso:country":"NL",
    "sg:address":"Marktstraat 11",
    "sg:city":"Ootmarsum",
    "sg:orig_category":"Banken And Kredietinstellingen",
    "sg:phone":"+31 541 282 828",
    "sg:postcode":"7631 BX",
    "sg:province":"Overijssel",
    "wof:name":"Rabobank",
    "wof:placetype":"venue"
},
  "geometry": {"coordinates":[6.89736,52.408684],"type":"Point"}
}