{
  "type": "Feature",
  "properties": {
    "addr:full":"Wylrehofwg 11A Venlo Limburg 5912 PM",
    "addr:housenumber":"11a",
    "addr:postcode":"5912 pm",
    "addr:street":"Wylrehofwg",
    "iso:country":"NL",
    "sg:address":"Wylrehofwg 11A",
    "sg:city":"Venlo",
    "sg:orig_category":"Kinderopvang",
    "sg:phone":"+31 77 326 6640",
    "sg:postcode":"5912 PM",
    "sg:province":"Limburg",
    "wof:name":"Petteflet",
    "wof:placetype":"venue"
},
  "geometry": {"coordinates":[6.158362,51.355045],"type":"Point"}
}