{
  "type": "Feature",
  "properties": {
    "addr:full":"Sportweg 24 Ens NL. 8307 AN",
    "addr:housenumber":"24",
    "addr:postcode":"8307 an",
    "addr:street":"Sportweg;Nl.",
    "iso:country":"NL",
    "sg:address":"Sportweg 24",
    "sg:city":"Ens",
    "sg:classifiers":[
        {
            "category":"Education",
            "subcategory":"Preschool",
            "type":"Public Place"
        }
    ],
    "sg:phone":"+31 527 251 712",
    "sg:postcode":"8307 AN",
    "sg:province":"NL.",
    "sg:tags":[
        "kleuteronderwijs",
        "basis-"
    ],
    "wof:name":"Christelijke Basisschool Het Lichtschip",
    "wof:placetype":"venue"
},
  "geometry": {"coordinates":[5.8273119926,52.63829422],"type":"Point"}
}