{
  "type": "Feature",
  "properties": {
    "addr:full":"Langstraat 121 Barneveld Gelderland 3771 BD",
    "addr:housenumber":"121",
    "addr:postcode":"3771 bd",
    "addr:street":"Langstraat;Gelderland",
    "iso:country":"NL",
    "sg:address":"Langstraat 121",
    "sg:city":"Barneveld",
    "sg:orig_category":"Bloemen And Planten",
    "sg:phone":"+31 342 421 442",
    "sg:postcode":"3771 BD",
    "sg:province":"Gelderland",
    "wof:name":"Bloembinderij De Veenbes",
    "wof:placetype":"venue"
},
  "geometry": {"coordinates":[5.589093,52.137764],"type":"Point"}
}