{
  "type": "Feature",
  "properties": {
    "addr:full":"Plesmanstr 54 Veenendaal Utrecht 3905 KZ",
    "addr:housenumber":"54",
    "addr:postcode":"3905",
    "addr:street":"Plesmanstr",
    "iso:country":"NL",
    "sg:address":"Plesmanstr 54",
    "sg:city":"Veenendaal",
    "sg:orig_category":"Sanitaire Artikelen",
    "sg:phone":"+31 318 513 703",
    "sg:postcode":"3905 KZ",
    "sg:province":"Utrecht",
    "sg:website":"http://www.hardeman-sanidrome.nl",
    "wof:name":"Sanidrome",
    "wof:placetype":"venue"
},
  "geometry": {"coordinates":[5.555946,52.040138],"type":"Point"}
}