{
  "type": "Feature",
  "properties": {
    "addr:full":"Bergstr 12 Eindhoven North Brabant 5611 JZ",
    "addr:housenumber":"12",
    "addr:postcode":"5611 jz",
    "addr:street":"Bergstr",
    "iso:country":"NL",
    "sg:address":"Bergstr 12",
    "sg:city":"Eindhoven",
    "sg:orig_category":"Parketvloeren",
    "sg:phone":"+31 40 244 9446",
    "sg:postcode":"5611 JZ",
    "sg:province":"North Brabant",
    "sg:website":"http://www.hemmesparket.nl",
    "wof:name":"Hemmes Parket",
    "wof:placetype":"venue"
},
  "geometry": {"coordinates":[5.484105,51.434471],"type":"Point"}
}