{
  "type": "Feature",
  "properties": {
    "addr:full":"Planckstr 43 Dordrecht Zuid-Holland 3316 GS",
    "addr:housenumber":"43",
    "addr:postcode":"3316 gs",
    "addr:street":"Planckstr",
    "iso:country":"NL",
    "sg:address":"Planckstr 43",
    "sg:city":"Dordrecht",
    "sg:orig_category":"Filters - Fabrieken En Groothandel",
    "sg:phone":"+31 78 617 7766",
    "sg:postcode":"3316 GS",
    "sg:province":"Zuid-Holland",
    "sg:website":"http://www.ifs-uniflow.com",
    "wof:name":"Ifs Uniflow",
    "wof:placetype":"venue"
},
  "geometry": {"coordinates":[4.634799,51.77618],"type":"Point"}
}