{
  "type": "Feature",
  "properties": {
    "iso:country":"NL",
    "sg:address":"Copernicuslaan 30",
    "sg:city":"'S Gravenhage",
    "sg:orig_category":"Kunst And Kunstenaarsbenodigdheden",
    "sg:phone":"+31 70 360 0750",
    "sg:postcode":"2561 VH",
    "sg:province":"Zuid-Holland",
    "wof:name":"S.M. Chu",
    "wof:placetype":"venue"
},
  "geometry": {"coordinates":[4.27213,52.074593],"type":"Point"}
}