{
  "type": "Feature",
  "properties": {
    "addr:full":"Dorpsstr 75 Enschede Overijssel 7524 CE",
    "addr:housenumber":"75",
    "addr:postcode":"7524 ce",
    "addr:street":"Dorpsstr",
    "iso:country":"NL",
    "sg:address":"Dorpsstr 75",
    "sg:city":"Enschede",
    "sg:orig_category":"Kinderkleding",
    "sg:phone":"+31 53 433 7523",
    "sg:postcode":"7524 CE",
    "sg:province":"Overijssel",
    "wof:name":"Annemarijn",
    "wof:placetype":"venue"
},
  "geometry": {"coordinates":[6.912978,52.24799],"type":"Point"}
}