{
  "type": "Feature",
  "properties": {
    "iso:country":"NL",
    "sg:address":"De Corantijn 26D",
    "sg:city":"Zwaag",
    "sg:orig_category":"Voegwerken",
    "sg:phone":"+31 229 210 910",
    "sg:postcode":"1689 AP",
    "sg:province":"North Holland",
    "wof:name":"Eksteen, Restauratie-Voegbedrijf Bv",
    "wof:placetype":"venue"
},
  "geometry": {"coordinates":[5.067314,52.671791],"type":"Point"}
}