{
  "type": "Feature",
  "properties": {
    "addr:full":"Dorpsstr 6 Zuidzande Zeeland 4505 AP",
    "addr:housenumber":"6",
    "addr:postcode":"4505 ap",
    "addr:street":"Dorpsstr",
    "iso:country":"NL",
    "sg:address":"Dorpsstr 6",
    "sg:city":"Zuidzande",
    "sg:orig_category":"Scholen Voor Basisonderwijs",
    "sg:phone":"+31 117 453 030",
    "sg:postcode":"4505 AP",
    "sg:province":"Zeeland",
    "wof:name":"Europa",
    "wof:placetype":"venue"
},
  "geometry": {"coordinates":[3.451502,51.34153],"type":"Point"}
}