{
  "type": "Feature",
  "properties": {
    "addr:full":"Hummerenwg 15 Baarlo Lb Limburg 5991 PR",
    "addr:housenumber":"15",
    "addr:postcode":"lb;5991 pr",
    "addr:street":"Hummerenwg",
    "iso:country":"NL",
    "sg:address":"Hummerenwg 15",
    "sg:city":"Baarlo Lb",
    "sg:orig_category":"Adviesbureaus Bedrijfsorganisatie",
    "sg:phone":"+31 77 477 2732",
    "sg:postcode":"5991 PR",
    "sg:province":"Limburg",
    "wof:name":"Venne",
    "wof:placetype":"venue"
},
  "geometry": {"coordinates":[6.09599,51.317856],"type":"Point"}
}