{
  "type": "Feature",
  "properties": {
    "addr:full":"Evertsenstr 65 Amersfoort Utrecht 3814 SG",
    "addr:housenumber":"65",
    "addr:postcode":"3814 sg",
    "addr:street":"Evertsenstr",
    "iso:country":"NL",
    "sg:address":"Evertsenstr 65",
    "sg:city":"Amersfoort",
    "sg:orig_category":"Adviesbureaus Bedrijfsorganisatie",
    "sg:phone":"+31 6 52453080",
    "sg:postcode":"3814 SG",
    "sg:province":"Utrecht",
    "wof:name":"Du Soleil",
    "wof:placetype":"venue"
},
  "geometry": {"coordinates":[5.395379,52.163864],"type":"Point"}
}