{
  "type": "Feature",
  "properties": {
    "iso:country":"NL",
    "sg:address":"Westzeedijk 92",
    "sg:city":"Rotterdam",
    "sg:orig_category":"Vaste And Vloeibare Brandstoffen",
    "sg:phone":"+31 10 436 0533",
    "sg:postcode":"3016 AG",
    "sg:province":"Zuid-Holland",
    "wof:name":"Associated Bunkeroil Contractors Bv",
    "wof:placetype":"venue"
},
  "geometry": {"coordinates":[4.47494,51.91048],"type":"Point"}
}