{
  "type": "Feature",
  "properties": {
    "addr:full":"Postbus 342 Deventer Overijssel 7400 AH",
    "addr:housenumber":"342",
    "addr:postcode":"7400 ah",
    "addr:street":"Postbus",
    "iso:country":"NL",
    "sg:address":"Postbus 342",
    "sg:city":"Deventer",
    "sg:orig_category":"Adviesbureaus Bedrijfsorganisatie",
    "sg:phone":"+31 570 655 611",
    "sg:postcode":"7400 AH",
    "sg:province":"Overijssel",
    "wof:name":"B & W",
    "wof:placetype":"venue"
},
  "geometry": {"coordinates":[6.15984,52.25354],"type":"Point"}
}