{
  "type": "Feature",
  "properties": {
    "iso:country":"NL",
    "sg:address":"Middelblok 198",
    "sg:city":"Gouderak",
    "sg:orig_category":"Jachthavens - Jachtwerven",
    "sg:phone":"+31 182 523 850",
    "sg:postcode":"2831 BR",
    "sg:province":"South Holland",
    "wof:name":"Bergboat",
    "wof:placetype":"venue"
},
  "geometry": {"coordinates":[4.69362,51.99527],"type":"Point"}
}