{
  "type": "Feature",
  "properties": {
    "iso:country":"NL",
    "sg:address":"Pr Frederikln 14B",
    "sg:city":"Wassenaar",
    "sg:orig_category":"Adviesbureaus Bedrijfsorganisatie",
    "sg:phone":"+31 70 517 9329",
    "sg:postcode":"2243 HW",
    "sg:province":"Zuid-Holland",
    "wof:name":"Hengeveld",
    "wof:placetype":"venue"
},
  "geometry": {"coordinates":[4.357879,52.125671],"type":"Point"}
}