{
  "type": "Feature",
  "properties": {
    "iso:country":"NL",
    "sg:address":"Minderbroedersstraat 18",
    "sg:city":"Den Bosch",
    "sg:orig_category":"Juweliers",
    "sg:phone":"+31 73 613 9046",
    "sg:postcode":"5211 EL",
    "sg:province":"Noord-Brabant",
    "wof:name":"Bert Jewelry",
    "wof:placetype":"venue"
},
  "geometry": {"coordinates":[5.29824,51.69075],"type":"Point"}
}