{
  "type": "Feature",
  "properties": {
    "addr:full":"Albinonistraat 115 Boxtel North Brabant 5283 KL",
    "addr:housenumber":"115",
    "addr:postcode":"5283 kl",
    "addr:street":"Albinonistraat",
    "iso:country":"NL",
    "sg:address":"Albinonistraat 115",
    "sg:city":"Boxtel",
    "sg:orig_category":"Marktonderzoekbureaus",
    "sg:phone":"+31 411 677 089",
    "sg:postcode":"5283 KL",
    "sg:province":"North Brabant",
    "wof:name":"Dgm De Groot Marketing",
    "wof:placetype":"venue"
},
  "geometry": {"coordinates":[5.341516,51.584671],"type":"Point"}
}