{
  "type": "Feature",
  "properties": {
    "addr:full":"Nachtwachtlaan 132 Amsterdam North Holland 1058 EE",
    "addr:housenumber":"132",
    "addr:postcode":"1058 ee",
    "addr:street":"Nachtwachtlaan",
    "iso:country":"NL",
    "sg:address":"Nachtwachtlaan 132",
    "sg:city":"Amsterdam",
    "sg:orig_category":"Boekhouders",
    "sg:phone":"+31 20 689 2796",
    "sg:postcode":"1058 EE",
    "sg:province":"North Holland",
    "wof:name":"Dima Accountancy Bv",
    "wof:placetype":"venue"
},
  "geometry": {"coordinates":[4.843311,52.360512],"type":"Point"}
}