{
  "type": "Feature",
  "properties": {
    "addr:full":"Schubertln 318 Maassluis South Holland 3144 BJ",
    "addr:housenumber":"318",
    "addr:postcode":"3144 bj",
    "iso:country":"NL",
    "sg:address":"Schubertln 318",
    "sg:city":"Maassluis",
    "sg:orig_category":"Kassenonderhoud",
    "sg:phone":"+31 6 54308661",
    "sg:postcode":"3144 BJ",
    "sg:province":"South Holland",
    "wof:name":"Zonneveld",
    "wof:placetype":"venue"
},
  "geometry": {"coordinates":[4.245431,51.927364],"type":"Point"}
}