{
  "type": "Feature",
  "properties": {
    "addr:full":"Lange Voorhout 80 'S Gravenhage Zuid-Holland 2514 EH",
    "addr:housenumber":"80",
    "addr:postcode":"2514 eh",
    "addr:street":"Lange Voorhout;' S",
    "iso:country":"NL",
    "sg:address":"Lange Voorhout 80",
    "sg:city":"'S Gravenhage",
    "sg:orig_category":"Kappers",
    "sg:phone":"+31 70 364 7600",
    "sg:postcode":"2514 EH",
    "sg:province":"Zuid-Holland",
    "wof:name":"Dameskapsalon Rossignol",
    "wof:placetype":"venue"
},
  "geometry": {"coordinates":[4.3143582344,52.0833129883],"type":"Point"}
}