{
  "type": "Feature",
  "properties": {
    "addr:full":"Grutbroek 50 Doetinchem Gelderland 7008 AN",
    "addr:housenumber":"50",
    "addr:postcode":"7008 an",
    "addr:street":"Grutbroek;Gelderland",
    "iso:country":"NL",
    "sg:address":"Grutbroek 50",
    "sg:city":"Doetinchem",
    "sg:orig_category":"Bevestigingsmaterialen",
    "sg:phone":"+31 314 333 441",
    "sg:postcode":"7008 AN",
    "sg:province":"Gelderland",
    "sg:website":"http://www.hjz.nl",
    "wof:name":"Zandvoort Draadindustrie Bv",
    "wof:placetype":"venue"
},
  "geometry": {"coordinates":[6.26592,51.972027],"type":"Point"}
}