{
  "type": "Feature",
  "properties": {
    "addr:full":"Veerstraat 8A Boxmeer Noord-Brabant 5831 IN",
    "addr:housenumber":"8a",
    "addr:postcode":"5831",
    "addr:street":"Veerstraat",
    "iso:country":"NL",
    "sg:address":"Veerstraat 8A",
    "sg:city":"Boxmeer",
    "sg:orig_category":"Film-, Tv- And Videoproductie",
    "sg:phone":"+31 485 520 407",
    "sg:postcode":"5831 IN",
    "sg:province":"Noord-Brabant",
    "wof:name":"It'S Electric Bv",
    "wof:placetype":"venue"
},
  "geometry": {"coordinates":[5.951406,51.648399],"type":"Point"}
}