{
  "type": "Feature",
  "properties": {
    "addr:full":"Sebastiaanplein 10 Apeldoorn Gelderland 7333 BA",
    "addr:housenumber":"10",
    "addr:postcode":"7333 ba",
    "addr:street":"Sebastiaanplein;Gelderland",
    "iso:country":"NL",
    "sg:address":"Sebastiaanplein 10",
    "sg:city":"Apeldoorn",
    "sg:orig_category":"Overheidsdiensten",
    "sg:phone":"+31 55 542 1206",
    "sg:postcode":"7333 BA",
    "sg:province":"Gelderland",
    "wof:name":"De Veste",
    "wof:placetype":"venue"
},
  "geometry": {"coordinates":[5.9626879692,52.1930198669],"type":"Point"}
}