{
  "type": "Feature",
  "properties": {
    "addr:full":"Kastanjelaan 33 Zoeterwoude Zuid-Holland 2382 EJ",
    "addr:housenumber":"33",
    "addr:postcode":"2382 ej",
    "addr:street":"Kastanjelaan",
    "iso:country":"NL",
    "sg:address":"Kastanjelaan 33",
    "sg:city":"Zoeterwoude",
    "sg:orig_category":"Elektronische Bedrijfsinstallaties",
    "sg:phone":"+31 71 589 6360",
    "sg:postcode":"2382 EJ",
    "sg:province":"Zuid-Holland",
    "wof:name":"Van Eekeren Security Consultancy",
    "wof:placetype":"venue"
},
  "geometry": {"coordinates":[4.522603,52.143585],"type":"Point"}
}