{
  "type": "Feature",
  "properties": {
    "addr:full":"Hoogengaardelaan 1 Oosterwolde Fr Provincie Friesland 8431 AD",
    "addr:housenumber":"1",
    "addr:postcode":"8431 ad",
    "addr:street":"Hoogengaardelaan;Friesland",
    "iso:country":"NL",
    "sg:address":"Hoogengaardelaan 1",
    "sg:city":"Oosterwolde Fr",
    "sg:orig_category":"Banken And Kredietinstellingen",
    "sg:phone":"+31 516 438 343",
    "sg:postcode":"8431 AD",
    "sg:province":"Provincie Friesland",
    "wof:name":"Rabobank",
    "wof:placetype":"venue"
},
  "geometry": {"coordinates":[6.289334,52.991096],"type":"Point"}
}