{
  "type": "Feature",
  "properties": {
    "iso:country":"NL",
    "sg:address":"Diepvoorde 2293",
    "sg:city":"Wijchen",
    "sg:orig_category":"Verhuur Audiovisuele Apparatuur",
    "sg:phone":"+31 24 641 4301",
    "sg:postcode":"6605 GK",
    "sg:province":"Gelderland",
    "wof:name":"Royal Karaoke Show",
    "wof:placetype":"venue"
},
  "geometry": {"coordinates":[5.722589,51.80125],"type":"Point"}
}