{
  "type": "Feature",
  "properties": {
    "addr:full":"3E Industrieweg 11 Lopik Utrecht 3411 MD",
    "addr:housenumber":"11",
    "addr:postcode":"3411",
    "addr:street":"3E Industrieweg",
    "iso:country":"NL",
    "sg:address":"3E Industrieweg 11",
    "sg:city":"Lopik",
    "sg:orig_category":"Parfum And Cosmetica Gh",
    "sg:phone":"+31 348 553 199",
    "sg:postcode":"3411 MD",
    "sg:province":"Utrecht",
    "wof:name":"Intervoll Bv",
    "wof:placetype":"venue"
},
  "geometry": {"coordinates":[4.968991,51.986145],"type":"Point"}
}