{
  "type": "Feature",
  "properties": {
    "addr:full":"Staalwijk 53 Dronten Flevoland 8251 JP",
    "addr:housenumber":"53",
    "addr:postcode":"8251 jp",
    "addr:street":"Staalwijk;Flevoland",
    "iso:country":"NL",
    "sg:address":"Staalwijk 53",
    "sg:city":"Dronten",
    "sg:orig_category":"Zuivelproducten And Spijsoli?n Gh",
    "sg:phone":"+31 321 381 155",
    "sg:postcode":"8251 JP",
    "sg:province":"Flevoland",
    "wof:name":"Beneluxvet Bv",
    "wof:placetype":"venue"
},
  "geometry": {"coordinates":[5.732346,52.536724],"type":"Point"}
}