{
  "type": "Feature",
  "properties": {
    "addr:full":"Soetenstg 24 Rotterdam South Holland 3011 GR",
    "addr:housenumber":"24",
    "addr:postcode":"3011",
    "addr:street":"Soetenstg",
    "iso:country":"NL",
    "sg:address":"Soetenstg 24",
    "sg:city":"Rotterdam",
    "sg:orig_category":"Beeldende Kunstenaars",
    "sg:phone":"+31 10 412 5003",
    "sg:postcode":"3011 GR",
    "sg:province":"South Holland",
    "wof:name":"Thomas Hageraats",
    "wof:placetype":"venue"
},
  "geometry": {"coordinates":[4.482674,51.91927],"type":"Point"}
}