{
  "type": "Feature",
  "properties": {
    "iso:country":"NL",
    "sg:address":"Westerwg 413A",
    "sg:city":"Heiloo",
    "sg:orig_category":"Bloemen En Planten - Groothandel",
    "sg:phone":"+31 72 532 1153",
    "sg:postcode":"1852 PS",
    "sg:province":"North Holland",
    "wof:name":"Sprenkeling",
    "wof:placetype":"venue"
},
  "geometry": {"coordinates":[4.68875,52.588013],"type":"Point"}
}