{
  "type": "Feature",
  "properties": {
    "iso:country":"NL",
    "sg:address":"Makado Centrum 87",
    "sg:city":"Schagen",
    "sg:orig_category":"Zoetwaren - Winkels",
    "sg:phone":"+31 224 296 624",
    "sg:postcode":"1741 JA",
    "sg:province":"North Holland",
    "wof:name":"Jamin Bv",
    "wof:placetype":"venue"
},
  "geometry": {"coordinates":[4.797759,52.78772],"type":"Point"}
}