{
  "type": "Feature",
  "properties": {
    "addr:full":"Cornelisstr 40Zw Haarlem Noord-Holland 2023 DH",
    "addr:housenumber":"40zw",
    "addr:postcode":"2023 dh",
    "addr:street":"Cornelisstr",
    "iso:country":"NL",
    "sg:address":"Cornelisstr 40Zw",
    "sg:city":"Haarlem",
    "sg:orig_category":"Loodgieters",
    "sg:phone":"+31 23 525 7454",
    "sg:postcode":"2023 DH",
    "sg:province":"Noord-Holland",
    "wof:name":"Beck Eerste Haarlemse Riolering Service, A J",
    "wof:placetype":"venue"
},
  "geometry": {"coordinates":[4.63033,52.393745],"type":"Point"}
}