{
  "type": "Feature",
  "properties": {
    "addr:full":"Ommerenveldseweg 47 Ommeren Gelderland 4032 NB",
    "addr:housenumber":"47",
    "addr:postcode":"4032 nb",
    "addr:street":"Ommerenveldseweg;Gelderland",
    "iso:country":"NL",
    "sg:address":"Ommerenveldseweg 47",
    "sg:city":"Ommeren",
    "sg:orig_category":"Fotostudio'S And Fotografen",
    "sg:phone":"+31 344 603 042",
    "sg:postcode":"4032 NB",
    "sg:province":"Gelderland",
    "wof:name":"Studio Ruud Willemse",
    "wof:placetype":"venue"
},
  "geometry": {"coordinates":[5.479873,51.93264],"type":"Point"}
}