{
  "type": "Feature",
  "properties": {
    "addr:full":"Bredevoortsestraatweg 118 Bredevoort Gelderland 7126 AA",
    "addr:housenumber":"118",
    "addr:postcode":"7126 aa",
    "addr:street":"Bredevoortsestraatweg;Gelderland",
    "iso:country":"NL",
    "sg:address":"Bredevoortsestraatweg 118",
    "sg:city":"Bredevoort",
    "sg:orig_category":"Bloemen And Planten",
    "sg:phone":"+31 543 451 233",
    "sg:postcode":"7126 AA",
    "sg:province":"Gelderland",
    "wof:name":"Vof Tuincentrum Groenrijk Willy Heinen",
    "wof:placetype":"venue"
},
  "geometry": {"coordinates":[6.628789,51.940571],"type":"Point"}
}