{
  "type": "Feature",
  "properties": {
    "iso:country":"NL",
    "sg:address":"Wulverhorst 151",
    "sg:city":"Montfoort",
    "sg:orig_category":"Diverse Opleidingen And Onderwijs",
    "sg:phone":"+31 348 475 763",
    "sg:postcode":"3417 TK",
    "sg:province":"Utrecht",
    "wof:name":"K Ariens-Schoneveld",
    "wof:placetype":"venue"
},
  "geometry": {"coordinates":[4.949072,52.040012],"type":"Point"}
}