{
  "type": "Feature",
  "properties": {
    "addr:full":"Molenwiek 6 Mijdrecht Utrecht 3642 BR",
    "addr:housenumber":"6",
    "addr:postcode":"3642 br",
    "addr:street":"Molenwiek",
    "iso:country":"NL",
    "sg:address":"Molenwiek 6",
    "sg:city":"Mijdrecht",
    "sg:orig_category":"Fotostudio'S And Fotografen",
    "sg:phone":"+31 297 257 468",
    "sg:postcode":"3642 BR",
    "sg:province":"Utrecht",
    "wof:name":"Robert Leising Fotografie",
    "wof:placetype":"venue"
},
  "geometry": {"coordinates":[4.865071,52.20039],"type":"Point"}
}