{
  "type": "Feature",
  "properties": {
    "iso:country":"NL",
    "sg:address":"Stephensonwg 16-18",
    "sg:city":"Coevorden",
    "sg:orig_category":"Oud Metaal",
    "sg:phone":"+31 524 512 096",
    "sg:postcode":"7741 KW",
    "sg:province":"Drenthe",
    "wof:name":"Bakker Coevorden Bv, Gebr",
    "wof:placetype":"venue"
},
  "geometry": {"coordinates":[6.7325072289,52.6526794434],"type":"Point"}
}