{
  "type": "Feature",
  "properties": {
    "addr:full":"Reeweg Oost 79 Dordrecht Zuid-Holland 3312 CL",
    "addr:housenumber":"79",
    "addr:postcode":"3312",
    "addr:street":"Reeweg Oost",
    "iso:country":"NL",
    "sg:address":"Reeweg Oost 79",
    "sg:city":"Dordrecht",
    "sg:orig_category":"Kunst And Kunstenaarsbenodigdheden",
    "sg:phone":"+31 78 631 7402",
    "sg:postcode":"3312 CL",
    "sg:province":"Zuid-Holland",
    "wof:name":"Prins Lijstenmakerijen",
    "wof:placetype":"venue"
},
  "geometry": {"coordinates":[4.680894,51.808037],"type":"Point"}
}