{
  "type": "Feature",
  "properties": {
    "iso:country":"NL",
    "sg:address":"Kerkhofweg 100",
    "sg:city":"Breda",
    "sg:orig_category":"Timmerwerk Van Hout And Kunststof",
    "sg:phone":"+31 76 560 2749",
    "sg:postcode":"4835 GC",
    "sg:province":"Noord-Brabant",
    "wof:name":"Fa. Maas",
    "wof:placetype":"venue"
},
  "geometry": {"coordinates":[4.791835,51.566101],"type":"Point"}
}