{
  "type": "Feature",
  "properties": {
    "iso:country":"NL",
    "sg:address":"Zaalbergwg 15",
    "sg:city":"Leiden",
    "sg:orig_category":"Medische Installaties En Instrumenten",
    "sg:phone":"+31 71 581 9110",
    "sg:postcode":"2314 XS",
    "sg:province":"Zuid-Holland",
    "sg:website":"http://www.provema.nl",
    "wof:name":"Provema Bv",
    "wof:placetype":"venue"
},
  "geometry": {"coordinates":[4.50438,52.143272],"type":"Point"}
}