{
  "type": "Feature",
  "properties": {
    "addr:full":"Conradstr 87 Amsterdam North Holland 1018 NE",
    "addr:housenumber":"87",
    "addr:postcode":"1018 ne",
    "addr:street":"Conradstr",
    "iso:country":"NL",
    "sg:address":"Conradstr 87",
    "sg:city":"Amsterdam",
    "sg:orig_category":"Vertaalbureaus",
    "sg:phone":"+31 20 638 4972",
    "sg:postcode":"1018 NE",
    "sg:province":"North Holland",
    "wof:name":"Sezinbil",
    "wof:placetype":"venue"
},
  "geometry": {"coordinates":[4.927065,52.369263],"type":"Point"}
}