{
  "type": "Feature",
  "properties": {
    "addr:full":"Dorpsstr 60 Holten NL.08 7451 BW",
    "addr:housenumber":"60;nl.08",
    "addr:postcode":"7451 bw",
    "addr:street":"Dorpsstr",
    "iso:country":"NL",
    "sg:address":"Dorpsstr 60",
    "sg:city":"Holten",
    "sg:orig_category":"Kappers",
    "sg:phone":"+31 548 362 168",
    "sg:postcode":"7451 BW",
    "sg:province":"NL.08",
    "wof:name":"Geenhuizen, W G Van",
    "wof:placetype":"venue"
},
  "geometry": {"coordinates":[6.4174370766,52.2827148438],"type":"Point"}
}