{
  "type": "Feature",
  "properties": {
    "addr:full":"Klaprozenwg 65A Amsterdam North Holland 1032 KK",
    "addr:housenumber":"65a",
    "addr:postcode":"1032 kk",
    "addr:street":"Klaprozenwg",
    "iso:country":"NL",
    "sg:address":"Klaprozenwg 65A",
    "sg:city":"Amsterdam",
    "sg:orig_category":"Autoradio'S",
    "sg:phone":"+31 20 636 2252",
    "sg:postcode":"1032 KK",
    "sg:province":"North Holland",
    "wof:name":"Excellence Tuning",
    "wof:placetype":"venue"
},
  "geometry": {"coordinates":[4.901083,52.400604],"type":"Point"}
}