{
  "type": "Feature",
  "properties": {
    "addr:full":"Kanaalwg 19 Capelle Ad Yssel South Holland 2903 LR",
    "addr:housenumber":"19",
    "addr:postcode":"2903 lr",
    "addr:street":"Kanaalwg;Yssel",
    "iso:country":"NL",
    "sg:address":"Kanaalwg 19",
    "sg:city":"Capelle Ad Yssel",
    "sg:orig_category":"Makelaars En Adviseurs Onroerende Goederen",
    "sg:phone":"+31 10 284 4444",
    "sg:postcode":"2903 LR",
    "sg:province":"South Holland",
    "sg:website":"http://www.stappervastgoed.nl",
    "wof:name":"Stapper Bv",
    "wof:placetype":"venue"
},
  "geometry": {"coordinates":[4.58319,51.934029],"type":"Point"}
}