{
  "type": "Feature",
  "properties": {
    "iso:country":"NL",
    "sg:address":"Kloosterlaan 32",
    "sg:city":"Hoogland",
    "sg:orig_category":"Goederenvervoer Over De Weg",
    "sg:phone":"+31 33 480 7824",
    "sg:postcode":"3828 EG",
    "sg:province":"Utrecht",
    "wof:name":"M.J. Koller",
    "wof:placetype":"venue"
},
  "geometry": {"coordinates":[5.382426,52.191036],"type":"Point"}
}