{
  "type": "Feature",
  "properties": {
    "iso:country":"NL",
    "sg:address":"Postbus 282",
    "sg:city":"Beverwyk",
    "sg:orig_category":"Bedrijfsopleidingen",
    "sg:phone":"+31 251 279 080",
    "sg:postcode":"1940 AG",
    "sg:website":"http://www.demeergroep.nl",
    "wof:name":"Meergroep Opleidings Instituut",
    "wof:placetype":"venue"
},
  "geometry": {"coordinates":[4.6719,52.479191],"type":"Point"}
}