{
  "type": "Feature",
  "properties": {
    "addr:full":"Van Cittersweg 2 Arnemuiden Zeeland 4341 RC",
    "addr:housenumber":"2",
    "addr:postcode":"4341 rc",
    "addr:street":"Van Cittersweg",
    "iso:country":"NL",
    "sg:address":"Van Cittersweg 2",
    "sg:city":"Arnemuiden",
    "sg:orig_category":"Meubelzaken, Woning- And Keukeninrichting",
    "sg:phone":"+31 118 603 075",
    "sg:postcode":"4341 RC",
    "sg:province":"Zeeland",
    "wof:name":"De Schipper Wooncentrum",
    "wof:placetype":"venue"
},
  "geometry": {"coordinates":[3.677472,51.505051],"type":"Point"}
}