{
  "type": "Feature",
  "properties": {
    "iso:country":"NL",
    "sg:address":"Buurtwg 12",
    "sg:city":"Doorn",
    "sg:orig_category":"Kaasgroothandel",
    "sg:phone":"+31 343 414 643",
    "sg:postcode":"3941 MC",
    "sg:province":"Utrecht",
    "wof:name":"Cooten En Zn, Fa W Van",
    "wof:placetype":"venue"
},
  "geometry": {"coordinates":[5.3775568008,52.0232124329],"type":"Point"}
}