{
  "type": "Feature",
  "properties": {
    "iso:country":"NL",
    "sg:address":"Langeplaat 67",
    "sg:city":"Rozenburg Zh",
    "sg:orig_category":"Ongediertebestrijding En Ontsmetting",
    "sg:phone":"+31 6 24514135",
    "sg:postcode":"3181 ZJ",
    "sg:province":"Zuid-Holland",
    "wof:name":"Pb & Wd",
    "wof:placetype":"venue"
},
  "geometry": {"coordinates":[4.255766,51.899296],"type":"Point"}
}