{
  "type": "Feature",
  "properties": {
    "addr:full":"Stationsstraat 91 Ermelo Gelderland 3851 NC",
    "addr:housenumber":"91",
    "addr:postcode":"3851 nc",
    "addr:street":"Stationsstraat;Gelderland",
    "iso:country":"NL",
    "sg:address":"Stationsstraat 91",
    "sg:city":"Ermelo",
    "sg:orig_category":"Architecten",
    "sg:phone":"+31 341 552 427",
    "sg:postcode":"3851 NC",
    "sg:province":"Gelderland",
    "wof:name":"Griffioen Bv",
    "wof:placetype":"venue"
},
  "geometry": {"coordinates":[5.621371,52.299603],"type":"Point"}
}