{
  "type": "Feature",
  "properties": {
    "addr:full":"Hoogstr 31A Abcoude Utrecht 1391 BR",
    "addr:housenumber":"31a",
    "addr:postcode":"1391 br",
    "addr:street":"Hoogstr",
    "iso:country":"NL",
    "sg:address":"Hoogstr 31A",
    "sg:city":"Abcoude",
    "sg:orig_category":"Kappers",
    "sg:phone":"+31 294 285 017",
    "sg:postcode":"1391 BR",
    "sg:province":"Utrecht",
    "wof:name":"Hairpoint",
    "wof:placetype":"venue"
},
  "geometry": {"coordinates":[4.9741249084,52.2702064514],"type":"Point"}
}