{
  "type": "Feature",
  "properties": {
    "iso:country":"NL",
    "sg:address":"Fluessen 39",
    "sg:city":"Heerenveen",
    "sg:orig_category":"Autorijscholen",
    "sg:phone":"+31 513 620 000",
    "sg:postcode":"8446 NS",
    "sg:province":"Provincie Friesland",
    "wof:name":"Breeden, P Van",
    "wof:placetype":"venue"
},
  "geometry": {"coordinates":[5.914884,52.947685],"type":"Point"}
}