{
  "type": "Feature",
  "properties": {
    "addr:full":"Fluessen 39 Heerenveen Provincie Friesland 8446 NS",
    "addr:housenumber":"39",
    "addr:postcode":"8446 ns",
    "addr:street":"Fluessen;Provincie Friesland",
    "iso:country":"NL",
    "sg:address":"Fluessen 39",
    "sg:city":"Heerenveen",
    "sg:orig_category":"Autorijscholen",
    "sg:phone":"+31 513 620 000",
    "sg:postcode":"8446 NS",
    "sg:province":"Provincie Friesland",
    "wof:name":"Breeden, P Van",
    "wof:placetype":"venue"
},
  "geometry": {"coordinates":[5.914884,52.947685],"type":"Point"}
}