{
  "type": "Feature",
  "properties": {
    "addr:full":"Duitslandwg 2 Terneuzen Zeeland 4538 BK",
    "addr:housenumber":"2",
    "addr:postcode":"4538 bk",
    "addr:street":"Duitslandwg",
    "iso:country":"NL",
    "sg:address":"Duitslandwg 2",
    "sg:city":"Terneuzen",
    "sg:orig_category":"Betonmortel",
    "sg:phone":"+31 115 680 326",
    "sg:postcode":"4538 BK",
    "sg:province":"Zeeland",
    "wof:name":"Hoop Terneuzen Bv, De",
    "wof:placetype":"venue"
},
  "geometry": {"coordinates":[3.837385,51.314526],"type":"Point"}
}