{
  "type": "Feature",
  "properties": {
    "addr:full":"Thedemastraat 20 Bedum Groningen 9781 BH",
    "addr:housenumber":"20",
    "addr:postcode":"9781 bh",
    "addr:street":"Thedemastraat",
    "iso:country":"NL",
    "sg:address":"Thedemastraat 20",
    "sg:city":"Bedum",
    "sg:orig_category":"Granen, Zaden And Diervoeders Gh",
    "sg:phone":"+31 50 301 4919",
    "sg:postcode":"9781 BH",
    "sg:province":"Groningen",
    "wof:name":"Firma Theo Bus Fourage",
    "wof:placetype":"venue"
},
  "geometry": {"coordinates":[6.595506,53.301651],"type":"Point"}
}