{
  "type": "Feature",
  "properties": {
    "iso:country":"NL",
    "sg:address":"Hugo De Grootlaan 53",
    "sg:city":"Middelburg",
    "sg:orig_category":"Begrafenisondernemers",
    "sg:phone":"+31 118 616 012",
    "sg:postcode":"4334 AT",
    "sg:province":"Zeeland",
    "wof:name":"J.C.C. Poppe",
    "wof:placetype":"venue"
},
  "geometry": {"coordinates":[3.597593,51.503895],"type":"Point"}
}