{
  "type": "Feature",
  "properties": {
    "addr:full":"Beatrixpark 24 Winterswijk Gelderland 7101 BN",
    "addr:housenumber":"24",
    "addr:postcode":"7101 bn",
    "addr:street":"Beatrixpark;Gelderland",
    "iso:country":"NL",
    "sg:address":"Beatrixpark 24",
    "sg:city":"Winterswijk",
    "sg:orig_category":"Kantoorartikelen",
    "sg:phone":"+31 543 530 003",
    "sg:postcode":"7101 BN",
    "sg:province":"Gelderland",
    "wof:name":"Inia Aalten Winterswijk Bv",
    "wof:placetype":"venue"
},
  "geometry": {"coordinates":[6.7020487785,51.9799118042],"type":"Point"}
}