{
  "type": "Feature",
  "properties": {
    "addr:full":"Plotterweg 33 Amersfoort Utrecht 3821 BB",
    "addr:housenumber":"33",
    "addr:postcode":"3821 bb",
    "addr:street":"Plotterweg",
    "iso:country":"NL",
    "sg:address":"Plotterweg 33",
    "sg:city":"Amersfoort",
    "sg:orig_category":"Banken And Kredietinstellingen",
    "sg:phone":"+31 33 450 3111",
    "sg:postcode":"3821 BB",
    "sg:province":"Utrecht",
    "wof:name":"Cvm Bank",
    "wof:placetype":"venue"
},
  "geometry": {"coordinates":[5.408555,52.173309],"type":"Point"}
}