{
  "type": "Feature",
  "properties": {
    "iso:country":"NL",
    "sg:address":"Abraham Niehuesstraat 12",
    "sg:city":"Hollandscheveld",
    "sg:orig_category":"Metaalwerken",
    "sg:phone":"+31 528 344 156",
    "sg:postcode":"7913 ZW",
    "sg:province":"Provincie Drenthe",
    "wof:name":"Ko Be Vof",
    "wof:placetype":"venue"
},
  "geometry": {"coordinates":[6.532003,52.710686],"type":"Point"}
}