{
  "type": "Feature",
  "properties": {
    "addr:full":"Postwg 5 Doorn Utrecht 3941 KA",
    "addr:housenumber":"5",
    "addr:postcode":"3941 ka",
    "addr:street":"Postwg",
    "iso:country":"NL",
    "sg:address":"Postwg 5",
    "sg:city":"Doorn",
    "sg:orig_category":"Architecten En Architectenbureaus",
    "sg:phone":"+31 343 416 611",
    "sg:postcode":"3941 KA",
    "sg:province":"Utrecht",
    "wof:name":"Aantjes Bv, Ir J",
    "wof:placetype":"venue"
},
  "geometry": {"coordinates":[5.352741,52.032959],"type":"Point"}
}