{
  "type": "Feature",
  "properties": {
    "iso:country":"NL",
    "sg:address":"N Achterwg 62",
    "sg:city":"Wemeldinge",
    "sg:classifiers":[
        {
            "category":"Travel",
            "subcategory":"Hotels & Motels",
            "type":"Entertainment"
        }
    ],
    "sg:phone":"+31 113 621 551",
    "sg:postcode":"4424 EG",
    "sg:province":"Zeeland",
    "wof:name":"Holland Inn Wemeldinge",
    "wof:placetype":"venue"
},
  "geometry": {"coordinates":[3.996982,51.515942],"type":"Point"}
}