{
  "type": "Feature",
  "properties": {
    "addr:full":"Beemterwg 28 Beemte Broekland Gelderland 7341 PB",
    "addr:housenumber":"28",
    "addr:postcode":"7341 pb",
    "addr:street":"Beemterwg",
    "iso:country":"NL",
    "sg:address":"Beemterwg 28",
    "sg:city":"Beemte Broekland",
    "sg:orig_category":"Wapens En Munitie",
    "sg:phone":"+31 55 312 1529",
    "sg:postcode":"7341 PB",
    "sg:province":"Gelderland",
    "wof:name":"Eek, Gradus Van",
    "wof:placetype":"venue"
},
  "geometry": {"coordinates":[5.9900932312,52.2555007935],"type":"Point"}
}