{
  "type": "Feature",
  "properties": {
    "addr:full":"Damaststraat 3 Zeeland Noord-Brabant 5411 AM",
    "addr:housenumber":"3",
    "addr:postcode":"5411",
    "addr:street":"Damaststraat",
    "iso:country":"NL",
    "sg:address":"Damaststraat 3",
    "sg:city":"Zeeland",
    "sg:orig_category":"Goederenvervoer Over De Weg",
    "sg:phone":"+31 486 452 017",
    "sg:postcode":"5411 AM",
    "sg:province":"Noord-Brabant",
    "wof:name":"Wcs Int",
    "wof:placetype":"venue"
},
  "geometry": {"coordinates":[5.677437,51.696369],"type":"Point"}
}