{
  "type": "Feature",
  "properties": {
    "addr:full":"Bierkaaistr 28 Hulst Zeeland 4561 BC",
    "addr:housenumber":"28",
    "addr:postcode":"4561 bc",
    "addr:street":"Bierkaaistr",
    "iso:country":"NL",
    "sg:address":"Bierkaaistr 28",
    "sg:city":"Hulst",
    "sg:orig_category":"Kinderkleding",
    "sg:phone":"+31 114 312 937",
    "sg:postcode":"4561 BC",
    "sg:province":"Zeeland",
    "wof:name":"Scarpe Sergio",
    "wof:placetype":"venue"
},
  "geometry": {"coordinates":[4.05081,51.282635],"type":"Point"}
}