{
  "type": "Feature",
  "properties": {
    "addr:full":"Vechtensteinln 16M Utrecht Utrecht 3555 XS",
    "addr:housenumber":"16m",
    "addr:postcode":"3555 xs",
    "addr:street":"Vechtensteinln",
    "iso:country":"NL",
    "sg:address":"Vechtensteinln 16M",
    "sg:city":"Utrecht",
    "sg:orig_category":"Werving En Selectie",
    "sg:phone":"+31 30 244 7710",
    "sg:postcode":"3555 XS",
    "sg:province":"Utrecht",
    "wof:name":"Meta Morphose International",
    "wof:placetype":"venue"
},
  "geometry": {"coordinates":[5.0810132027,52.1177864075],"type":"Point"}
}