{
  "type": "Feature",
  "properties": {
    "addr:full":"Nieuweweg 9 Melissant Zuid-Holland 3248 BD",
    "addr:housenumber":"9",
    "addr:postcode":"3248 bd",
    "addr:street":"Nieuweweg",
    "iso:country":"NL",
    "sg:address":"Nieuweweg 9",
    "sg:city":"Melissant",
    "sg:orig_category":"Diverse Dierenfokkers",
    "sg:phone":"+31 187 603 764",
    "sg:postcode":"3248 BD",
    "sg:province":"Zuid-Holland",
    "wof:name":"Firma J. Goedegebuur En Zn",
    "wof:placetype":"venue"
},
  "geometry": {"coordinates":[4.068327,51.76852],"type":"Point"}
}