{
  "type": "Feature",
  "properties": {
    "addr:full":"Eesterbrinkweg 3 Gorssel Gelderland 7213 LD",
    "addr:housenumber":"3",
    "addr:postcode":"7213 ld",
    "addr:street":"Eesterbrinkweg;Gelderland",
    "iso:country":"NL",
    "sg:address":"Eesterbrinkweg 3",
    "sg:city":"Gorssel",
    "sg:orig_category":"Bloemen And Planten",
    "sg:phone":"+31 575 493 451",
    "sg:postcode":"7213 LD",
    "sg:province":"Gelderland",
    "wof:name":"G.W. Brummelman",
    "wof:placetype":"venue"
},
  "geometry": {"coordinates":[6.203891,52.181816],"type":"Point"}
}