{
  "type": "Feature",
  "properties": {
    "iso:country":"NL",
    "sg:address":"Oosterduinstr 9A",
    "sg:city":"Terschelling West",
    "sg:orig_category":"Organisatiebureaus",
    "sg:phone":"+31 562 448 380",
    "sg:postcode":"8881 BX",
    "sg:province":"Provincie Friesland",
    "sg:website":"http://www.frissewind.com",
    "wof:name":"Frisse Wind",
    "wof:placetype":"venue"
},
  "geometry": {"coordinates":[5.217110157,53.3625259399],"type":"Point"}
}