{
  "type": "Feature",
  "properties": {
    "addr:full":"Monseigneur De Haasstr 20 Eersel Noord-Brabant 5521 TE",
    "addr:housenumber":"20",
    "addr:postcode":"5521 te",
    "addr:street":"Monseigneur De Haasstr",
    "iso:country":"NL",
    "sg:address":"Monseigneur De Haasstr 20",
    "sg:city":"Eersel",
    "sg:orig_category":"Metaalbekleding And -Behandeling",
    "sg:phone":"+31 497 513 112",
    "sg:postcode":"5521 TE",
    "sg:province":"Noord-Brabant",
    "wof:name":"T A M Klaassen",
    "wof:placetype":"venue"
},
  "geometry": {"coordinates":[5.322925,51.35955],"type":"Point"}
}