{
  "type": "Feature",
  "properties": {
    "iso:country":"NL",
    "sg:address":"Basaltstr 234",
    "sg:city":"Groningen",
    "sg:orig_category":"Webdesign Bureaus",
    "sg:phone":"+31 50 850 1941",
    "sg:postcode":"9743 TX",
    "sg:province":"Groningen",
    "sg:website":"http://www.incredes.com",
    "wof:name":"Incredes",
    "wof:placetype":"venue"
},
  "geometry": {"coordinates":[6.5246200562,53.2203216553],"type":"Point"}
}