{
  "type": "Feature",
  "properties": {
    "addr:full":"Raadhuisplein 8 Tubbergen Overijssel 7651 CV",
    "addr:housenumber":"8",
    "addr:postcode":"7651 cv",
    "addr:street":"Raadhuisplein",
    "iso:country":"NL",
    "sg:address":"Raadhuisplein 8",
    "sg:city":"Tubbergen",
    "sg:orig_category":"Fotostudio'S And Fotografen",
    "sg:phone":"+31 546 622 202",
    "sg:postcode":"7651 CV",
    "sg:province":"Overijssel",
    "wof:name":"Knippers Fotografie",
    "wof:placetype":"venue"
},
  "geometry": {"coordinates":[6.781361,52.407722],"type":"Point"}
}