{
  "type": "Feature",
  "properties": {
    "addr:full":"Rosmolen 30 Leiden Zuid-Holland 2317 SK",
    "addr:housenumber":"30",
    "addr:street":"Rosmolen;2317",
    "iso:country":"NL",
    "sg:address":"Rosmolen 30",
    "sg:city":"Leiden",
    "sg:orig_category":"Bloemen And Planten",
    "sg:phone":"+31 71 522 5762",
    "sg:postcode":"2317 SK",
    "sg:province":"Zuid-Holland",
    "wof:name":"Cupido",
    "wof:placetype":"venue"
},
  "geometry": {"coordinates":[4.504572,52.177307],"type":"Point"}
}