{
  "type": "Feature",
  "properties": {
    "addr:full":"Middenweg 63 Veendam Groningen 9645 BB",
    "addr:housenumber":"63",
    "addr:postcode":"9645 bb",
    "addr:street":"Middenweg",
    "iso:country":"NL",
    "sg:address":"Middenweg 63",
    "sg:city":"Veendam",
    "sg:orig_category":"Goederenvervoer Over De Weg",
    "sg:phone":"+31 598 613 309",
    "sg:postcode":"9645 BB",
    "sg:province":"Groningen",
    "wof:name":"Fa. H. Kamphuis En Zonen",
    "wof:placetype":"venue"
},
  "geometry": {"coordinates":[6.874676,53.121048],"type":"Point"}
}