{
  "type": "Feature",
  "properties": {
    "addr:full":"Meentsestr 68A Giesbeek Gelderland 6987 CP",
    "addr:housenumber":"68a",
    "addr:postcode":"6987 cp",
    "addr:street":"Meentsestr;Gelderland",
    "iso:country":"NL",
    "sg:address":"Meentsestr 68A",
    "sg:city":"Giesbeek",
    "sg:orig_category":"Nagelstudio'S",
    "sg:phone":"+31 313 631 368",
    "sg:postcode":"6987 CP",
    "sg:province":"Gelderland",
    "wof:name":"Marjan",
    "wof:placetype":"venue"
},
  "geometry": {"coordinates":[6.065044,51.993046],"type":"Point"}
}