{
  "type": "Feature",
  "properties": {
    "iso:country":"NL",
    "sg:address":"Raadhuispln 51",
    "sg:city":"Bergen Lb",
    "sg:orig_category":"Opticiens",
    "sg:phone":"+31 485 342 761",
    "sg:postcode":"5854 AW",
    "sg:province":"Limburg",
    "wof:name":"Harry Gooren",
    "wof:placetype":"venue"
},
  "geometry": {"coordinates":[-93.1299362183,36.7056617737],"type":"Point"}
}