{
  "type": "Feature",
  "properties": {
    "addr:full":"Kerkweg 55 Deurningen NL.08 7562 PG",
    "addr:housenumber":"55;nl.08",
    "addr:postcode":"7562 pg",
    "addr:street":"Kerkweg",
    "iso:country":"NL",
    "sg:address":"Kerkweg 55",
    "sg:city":"Deurningen",
    "sg:orig_category":"Levende Dieren Gh",
    "sg:phone":"+31 541 517 227",
    "sg:postcode":"7562 PG",
    "sg:province":"NL.08",
    "wof:name":"R.J.J. Oude Nijhuis",
    "wof:placetype":"venue"
},
  "geometry": {"coordinates":[6.849516,52.301071],"type":"Point"}
}