{
  "type": "Feature",
  "properties": {
    "iso:country":"NL",
    "sg:address":"Kerkweg 55",
    "sg:city":"Deurningen",
    "sg:orig_category":"Levende Dieren Gh",
    "sg:phone":"+31 541 517 227",
    "sg:postcode":"7562 PG",
    "sg:province":"NL.08",
    "wof:name":"R.J.J. Oude Nijhuis",
    "wof:placetype":"venue"
},
  "geometry": {"coordinates":[6.849516,52.301071],"type":"Point"}
}