{
  "type": "Feature",
  "properties": {
    "addr:full":"Engweide 24 Landgraaf Limburg 6372 EV",
    "addr:housenumber":"24",
    "addr:postcode":"6372 ev",
    "addr:street":"Engweide",
    "iso:country":"NL",
    "sg:address":"Engweide 24",
    "sg:city":"Landgraaf",
    "sg:orig_category":"Adviesbureaus Bouwkunde",
    "sg:phone":"+31 45 533 3640",
    "sg:postcode":"6372 EV",
    "sg:province":"Limburg",
    "wof:name":"Foortjes",
    "wof:placetype":"venue"
},
  "geometry": {"coordinates":[6.012892,50.88567],"type":"Point"}
}