{
  "type": "Feature",
  "properties": {
    "addr:full":"Mereveldplein 33 De Meern Utrecht 3454 CK",
    "addr:housenumber":"33",
    "addr:postcode":"3454 ck",
    "addr:street":"Mereveldplein",
    "iso:country":"NL",
    "sg:address":"Mereveldplein 33",
    "sg:city":"De Meern",
    "sg:orig_category":"Boekenuitgeverijen",
    "sg:phone":"+31 30 666 2230",
    "sg:postcode":"3454 CK",
    "sg:province":"Utrecht",
    "wof:name":"Boekhandel Kees Visscher",
    "wof:placetype":"venue"
},
  "geometry": {"coordinates":[5.038715,52.079163],"type":"Point"}
}