{
  "type": "Feature",
  "properties": {
    "addr:full":"Rheezerveensewg 54 Rheezerveen NL.08 7797 HD",
    "addr:housenumber":"54;nl.08",
    "addr:postcode":"7797 hd",
    "addr:street":"Rheezerveensewg",
    "iso:country":"NL",
    "sg:address":"Rheezerveensewg 54",
    "sg:city":"Rheezerveen",
    "sg:orig_category":"Kinderopvang",
    "sg:phone":"+31 523 638 433",
    "sg:postcode":"7797 HD",
    "sg:province":"NL.08",
    "wof:name":"Paddestoel, De",
    "wof:placetype":"venue"
},
  "geometry": {"coordinates":[6.522639,52.565552],"type":"Point"}
}