{
  "type": "Feature",
  "properties": {
    "iso:country":"NL",
    "sg:address":"Kokkeland 17",
    "sg:city":"Elst Gld",
    "sg:orig_category":"Kinderopvang Behalve Thuis",
    "sg:phone":"+31 481 376 423",
    "sg:postcode":"6661 ZV",
    "sg:province":"Gelderland",
    "wof:name":"Kinderdagcentrum Elstine",
    "wof:placetype":"venue"
},
  "geometry": {"coordinates":[5.838577,51.920643],"type":"Point"}
}