{
  "type": "Feature",
  "properties": {
    "addr:full":"Overhandstraat 12 Pernis Rt South Holland 3195 SG",
    "addr:housenumber":"12",
    "addr:postcode":"rt;3195 sg",
    "addr:street":"Overhandstraat",
    "iso:country":"NL",
    "sg:address":"Overhandstraat 12",
    "sg:city":"Pernis Rt",
    "sg:orig_category":"Boekhouders",
    "sg:phone":"+31 10 438 2453",
    "sg:postcode":"3195 SG",
    "sg:province":"South Holland",
    "wof:name":"Svg Administraties",
    "wof:placetype":"venue"
},
  "geometry": {"coordinates":[4.38919,51.890038],"type":"Point"}
}