{
  "type": "Feature",
  "properties": {
    "addr:full":"Nieuwe Ebbingestraat 28 Groningen Groningen 9712 NL",
    "addr:housenumber":"28",
    "addr:postcode":"9712 nl",
    "addr:street":"Nieuwe Ebbingestraat",
    "iso:country":"NL",
    "sg:address":"Nieuwe Ebbingestraat 28",
    "sg:city":"Groningen",
    "sg:orig_category":"Huishoudapparatuur, Televisies And Radio'S",
    "sg:phone":"+31 50 312 8095",
    "sg:postcode":"9712 NL",
    "sg:province":"Groningen",
    "wof:name":"Ypey Radio Expert",
    "wof:placetype":"venue"
},
  "geometry": {"coordinates":[6.563912,53.223011],"type":"Point"}
}