{
  "type": "Feature",
  "properties": {
    "addr:full":"Nachtegaal 13 Ysselmuiden Overijssel 8271 HS",
    "addr:housenumber":"13",
    "addr:postcode":"8271 hs",
    "addr:street":"Nachtegaal;Overijssel",
    "iso:country":"NL",
    "sg:address":"Nachtegaal 13",
    "sg:city":"Ysselmuiden",
    "sg:orig_category":"Keuringsdiensten",
    "sg:phone":"+31 38 332 6000",
    "sg:postcode":"8271 HS",
    "sg:province":"Overijssel",
    "wof:name":"Vermeulen, Drs J Arts",
    "wof:placetype":"venue"
},
  "geometry": {"coordinates":[5.941541,52.562546],"type":"Point"}
}