{
  "type": "Feature",
  "properties": {
    "addr:full":"Goudkd 55 Gouda Zuid-Holland 2802 AA",
    "addr:housenumber":"55",
    "addr:postcode":"2802 aa",
    "addr:street":"Goudkd",
    "iso:country":"NL",
    "sg:address":"Goudkd 55",
    "sg:city":"Gouda",
    "sg:orig_category":"Sportverenigingen En Ontspannings- Verenigingen",
    "sg:phone":"+31 182 520 610",
    "sg:postcode":"2802 AA",
    "sg:province":"Zuid-Holland",
    "wof:name":"Gouda Watersportver",
    "wof:placetype":"venue"
},
  "geometry": {"coordinates":[4.710715,52.010006],"type":"Point"}
}