{
  "type": "Feature",
  "properties": {
    "addr:full":"Kleinhoekje 1 Liempde Noord-Brabant 5298 CG",
    "addr:housenumber":"1",
    "addr:postcode":"5298 cg",
    "addr:street":"Kleinhoekje",
    "iso:country":"NL",
    "sg:address":"Kleinhoekje 1",
    "sg:city":"Liempde",
    "sg:orig_category":"Bedrijfs- And Managementsconsultants",
    "sg:phone":"+31 411 631 773",
    "sg:postcode":"5298 CG",
    "sg:province":"Noord-Brabant",
    "wof:name":"J.H.C. Van Abeelen",
    "wof:placetype":"venue"
},
  "geometry": {"coordinates":[5.3715,51.567226],"type":"Point"}
}