{
  "type": "Feature",
  "properties": {
    "addr:full":"Hoogstraat 181 Landgraaf Limburg 6373 HS",
    "addr:housenumber":"181",
    "addr:postcode":"6373 hs",
    "addr:street":"Hoogstraat",
    "iso:country":"NL",
    "sg:address":"Hoogstraat 181",
    "sg:city":"Landgraaf",
    "sg:orig_category":"Kappers",
    "sg:phone":"+31 45 531 1005",
    "sg:postcode":"6373 HS",
    "sg:province":"Limburg",
    "wof:name":"Dames- En Herenkappersbedrijf C. Logister",
    "wof:placetype":"venue"
},
  "geometry": {"coordinates":[6.0267047882,50.9072227478],"type":"Point"}
}