{
  "type": "Feature",
  "properties": {
    "iso:country":"NL",
    "sg:address":"Tussen De Bruggen 53",
    "sg:city":"Meerssen",
    "sg:classifiers":[
        {
            "category":"Communications",
            "subcategory":"Television Station",
            "type":"Services"
        }
    ],
    "sg:phone":"+31 43 364 0175",
    "sg:postcode":"6231 CB",
    "sg:province":"Limburg",
    "sg:tags":[
        "video",
        "audio",
        "verhuur"
    ],
    "wof:name":"Videopoint Meerssen",
    "wof:placetype":"venue"
},
  "geometry": {"coordinates":[5.74682,50.87981],"type":"Point"}
}