{
  "type": "Feature",
  "properties": {
    "addr:full":"Da Costastraat 16 Vlijmen Noord-Brabant 5251 LV",
    "addr:housenumber":"16",
    "addr:postcode":"5251",
    "addr:street":"Da Costastraat",
    "iso:country":"NL",
    "sg:address":"Da Costastraat 16",
    "sg:city":"Vlijmen",
    "sg:orig_category":"Boekhouders",
    "sg:phone":"+31 73 511 3463",
    "sg:postcode":"5251 LV",
    "sg:province":"Noord-Brabant",
    "wof:name":"W.F.J.M. Jansen-Marijnen",
    "wof:placetype":"venue"
},
  "geometry": {"coordinates":[5.205528,51.690334],"type":"Point"}
}