{
  "type": "Feature",
  "properties": {
    "addr:full":"Zuurvenswg 21 Bergen Nh North Holland 1862 BK",
    "addr:housenumber":"21",
    "addr:postcode":"1862 bk",
    "addr:street":"Zuurvenswg",
    "iso:country":"NL",
    "sg:address":"Zuurvenswg 21",
    "sg:city":"Bergen Nh",
    "sg:orig_category":"Beeldende Kunstenaars",
    "sg:phone":"+31 72 589 5695",
    "sg:postcode":"1862 BK",
    "sg:province":"North Holland",
    "wof:name":"Nicolaidis, O",
    "wof:placetype":"venue"
},
  "geometry": {"coordinates":[4.713285,52.674702],"type":"Point"}
}