{
  "type": "Feature",
  "properties": {
    "addr:full":"Prins Bernhardlaan 14 Alphen A/D Rijn Zuid-Holland 2405 VT",
    "addr:housenumber":"14;2405",
    "addr:street":"Prins Bernhardlaan",
    "iso:country":"NL",
    "sg:address":"Prins Bernhardlaan 14",
    "sg:city":"Alphen A/D Rijn",
    "sg:orig_category":"Marktonderzoekbureaus",
    "sg:phone":"+31 172 424 080",
    "sg:postcode":"2405 VT",
    "sg:province":"Zuid-Holland",
    "wof:name":"Zwart & Partners Bv",
    "wof:placetype":"venue"
},
  "geometry": {"coordinates":[-72.451218,43.871769],"type":"Point"}
}