{
  "type": "Feature",
  "properties": {
    "addr:full":"Overflakkee 58 Emmeloord Flevoland 8302 NX",
    "addr:housenumber":"58",
    "addr:postcode":"8302 nx",
    "addr:street":"Overflakkee;Flevoland",
    "iso:country":"NL",
    "sg:address":"Overflakkee 58",
    "sg:city":"Emmeloord",
    "sg:orig_category":"Adviesbureaus Bedrijfsorganisatie",
    "sg:phone":"+31 527 619 182",
    "sg:postcode":"8302 NX",
    "sg:province":"Flevoland",
    "wof:name":"Rottin\u00e9, Gerrit",
    "wof:placetype":"venue"
},
  "geometry": {"coordinates":[5.722867,52.72263],"type":"Point"}
}