{
  "type": "Feature",
  "properties": {
    "iso:country":"NL",
    "sg:address":"Postbus 16",
    "sg:city":"Almkerk",
    "sg:orig_category":"Schilders",
    "sg:phone":"+31 183 409 173",
    "sg:postcode":"4286 ZG",
    "sg:province":"Noord-Brabant",
    "wof:name":"Midland",
    "wof:placetype":"venue"
},
  "geometry": {"coordinates":[4.9645,51.771969],"type":"Point"}
}