{
  "type": "Feature",
  "properties": {
    "addr:full":"Maastrichterln 42 Vaals Limburg 6291 ES",
    "addr:housenumber":"42",
    "addr:postcode":"6291 es",
    "addr:street":"Maastrichterln",
    "iso:country":"NL",
    "sg:address":"Maastrichterln 42",
    "sg:city":"Vaals",
    "sg:orig_category":"Herenkleding",
    "sg:phone":"+31 43 306 1260",
    "sg:postcode":"6291 ES",
    "sg:province":"Limburg",
    "wof:name":"Fanchamps, Dieter",
    "wof:placetype":"venue"
},
  "geometry": {"coordinates":[6.018025,50.772793],"type":"Point"}
}