{
  "type": "Feature",
  "properties": {
    "iso:country":"NL",
    "sg:address":"Maastrichterln 42",
    "sg:city":"Vaals",
    "sg:orig_category":"Herenkleding",
    "sg:phone":"+31 43 306 1260",
    "sg:postcode":"6291 ES",
    "sg:province":"Limburg",
    "wof:name":"Fanchamps, Dieter",
    "wof:placetype":"venue"
},
  "geometry": {"coordinates":[6.018025,50.772793],"type":"Point"}
}