{
  "type": "Feature",
  "properties": {
    "iso:country":"NL",
    "sg:address":"Lange Viestraat 2",
    "sg:city":"Utrecht",
    "sg:classifiers":[
        {
            "category":"Shopping",
            "subcategory":"Gifts & Souvenirs",
            "type":"Retail Goods"
        }
    ],
    "sg:phone":"+31 30 233 4619",
    "sg:postcode":"3511 BK",
    "sg:province":"Utrecht",
    "sg:tags":[
        "geschenken"
    ],
    "wof:name":"Vieco Bv",
    "wof:placetype":"venue"
},
  "geometry": {"coordinates":[5.116306,52.093166],"type":"Point"}
}