{
  "type": "Feature",
  "properties": {
    "addr:full":"Kl Leliestr 17/19 Groningen Groningen 9712 TD",
    "addr:housenumber":"17 / 19",
    "addr:postcode":"9712 td",
    "iso:country":"NL",
    "sg:address":"Kl Leliestr 17/19",
    "sg:city":"Groningen",
    "sg:orig_category":"Boekbinderijen",
    "sg:phone":"+31 50 312 7104",
    "sg:postcode":"9712 TD",
    "sg:province":"Groningen",
    "wof:name":"Broek, Van Den",
    "wof:placetype":"venue"
},
  "geometry": {"coordinates":[6.560377,53.222363],"type":"Point"}
}