{
  "type": "Feature",
  "properties": {
    "addr:full":"Koperwiek 8 Hardinxveld Giessend Zuid-Holland 3371 JS",
    "addr:housenumber":"8;giessend",
    "addr:postcode":"3371 js",
    "addr:street":"Koperwiek",
    "iso:country":"NL",
    "sg:address":"Koperwiek 8",
    "sg:city":"Hardinxveld Giessend",
    "sg:classifiers":[
        {
            "category":"Professional",
            "subcategory":"Accounting & Tax Preparation",
            "type":"Services"
        }
    ],
    "sg:phone":"+31 184 616 454",
    "sg:postcode":"3371 JS",
    "sg:province":"Zuid-Holland",
    "sg:tags":[
        "accountant"
    ],
    "wof:name":"Accountantskantoor Het Anker Bv",
    "wof:placetype":"venue"
},
  "geometry": {"coordinates":[4.820044,51.826645],"type":"Point"}
}