{
  "type": "Feature",
  "properties": {
    "addr:full":"Kapelaanstraat 62 Gemert Noord-Brabant 5421 DG",
    "addr:housenumber":"62",
    "addr:postcode":"5421 dg",
    "addr:street":"Kapelaanstraat",
    "iso:country":"NL",
    "sg:address":"Kapelaanstraat 62",
    "sg:city":"Gemert",
    "sg:orig_category":"Fietshandelaren",
    "sg:phone":"+31 492 365 776",
    "sg:postcode":"5421 DG",
    "sg:province":"Noord-Brabant",
    "wof:name":"Fietsservice Berkvens",
    "wof:placetype":"venue"
},
  "geometry": {"coordinates":[5.685814,51.55405],"type":"Point"}
}