{
  "type": "Feature",
  "properties": {
    "addr:full":"Magnesiumln 29 Groningen Groningen 9743 TA",
    "addr:housenumber":"29",
    "addr:postcode":"9743 ta",
    "addr:street":"Magnesiumln",
    "iso:country":"NL",
    "sg:address":"Magnesiumln 29",
    "sg:city":"Groningen",
    "sg:orig_category":"Projectinrichting",
    "sg:phone":"+31 50 571 8333",
    "sg:postcode":"9743 TA",
    "sg:province":"Groningen",
    "wof:name":"Birza Bv, Projectinrichting",
    "wof:placetype":"venue"
},
  "geometry": {"coordinates":[6.532199,53.224422],"type":"Point"}
}