{
  "type": "Feature",
  "properties": {
    "addr:full":"Driebergenlaan 3 Rosmalen North Brabant 5242 AM",
    "addr:housenumber":"3",
    "addr:postcode":"5242",
    "addr:street":"Driebergenlaan",
    "iso:country":"NL",
    "sg:address":"Driebergenlaan 3",
    "sg:city":"Rosmalen",
    "sg:orig_category":"Loodgieterswerk, Verwarming And Sanitaire Installaties",
    "sg:phone":"+31 73 521 4352",
    "sg:postcode":"5242 AM",
    "sg:province":"North Brabant",
    "wof:name":"J.W. Pennings",
    "wof:placetype":"venue"
},
  "geometry": {"coordinates":[5.357924,51.706657],"type":"Point"}
}