{
  "type": "Feature",
  "properties": {
    "addr:full":"Het Ruim 32 Dronten Flevoland 8251  E",
    "addr:housenumber":"32;8251 e",
    "addr:street":"Het Ruim;Flevoland",
    "iso:country":"NL",
    "sg:address":"Het Ruim 32",
    "sg:city":"Dronten",
    "sg:orig_category":"Verhuur Catering-, Feest- En Evenementbenodigdheden",
    "sg:phone":"+31 321 312 615",
    "sg:postcode":"8251  E",
    "sg:province":"Flevoland",
    "wof:name":"Klaver Keurslager",
    "wof:placetype":"venue"
},
  "geometry": {"coordinates":[5.719229,52.524719],"type":"Point"}
}