{
  "type": "Feature",
  "properties": {
    "iso:country":"NL",
    "sg:address":"Julianastr 83",
    "sg:city":"Lisse",
    "sg:orig_category":"Kerkorgels - Bouw En Reparatie",
    "sg:phone":"+31 252 414 426",
    "sg:postcode":"2161 RB",
    "sg:province":"Zuid-Holland",
    "wof:name":"Jongh, W N De",
    "wof:placetype":"venue"
},
  "geometry": {"coordinates":[4.561736,52.262394],"type":"Point"}
}