{
  "type": "Feature",
  "properties": {
    "iso:country":"NL",
    "sg:address":"Wal 40",
    "sg:city":"Schoonhoven",
    "sg:orig_category":"Verpakkingen En Verpakkingsmaterialen",
    "sg:phone":"+31 182 380 002",
    "sg:postcode":"2871 BC",
    "sg:province":"Zuid-Holland",
    "wof:name":"Fibope",
    "wof:placetype":"venue"
},
  "geometry": {"coordinates":[4.854915,51.946625],"type":"Point"}
}