{
  "type": "Feature",
  "properties": {
    "addr:full":"Axelsestr 18 Terneuzen Zeeland 4537 AK",
    "addr:housenumber":"18",
    "addr:postcode":"4537 ak",
    "addr:street":"Axelsestr",
    "iso:country":"NL",
    "sg:address":"Axelsestr 18",
    "sg:city":"Terneuzen",
    "sg:classifiers":[
        {
            "category":"Food & Beverages",
            "subcategory":"Bakery",
            "type":"Retail Goods"
        }
    ],
    "sg:phone":"+31 115 612 339",
    "sg:postcode":"4537 AK",
    "sg:province":"Zeeland",
    "sg:tags":[
        "brood",
        "en",
        "banket"
    ],
    "wof:name":"Bruijne Vof, Bakkerij De",
    "wof:placetype":"venue"
},
  "geometry": {"coordinates":[3.830803,51.33371],"type":"Point"}
}