{
  "type": "Feature",
  "properties": {
    "addr:full":"J Kruyverstr 39 Zaandam North Holland 1507 WD",
    "addr:housenumber":"39",
    "addr:postcode":"1507 wd",
    "iso:country":"NL",
    "sg:address":"J Kruyverstr 39",
    "sg:city":"Zaandam",
    "sg:orig_category":"Voetbalverenigingen",
    "sg:phone":"+31 75 631 2848",
    "sg:postcode":"1507 WD",
    "sg:province":"North Holland",
    "wof:name":"Dam'93",
    "wof:placetype":"venue"
},
  "geometry": {"coordinates":[4.799786,52.449245],"type":"Point"}
}