{
  "type": "Feature",
  "properties": {
    "addr:full":"Brinkhorst 2 Haren Gn Groningen 9751 AT",
    "addr:housenumber":"2",
    "addr:postcode":"9751",
    "addr:street":"Brinkhorst",
    "iso:country":"NL",
    "sg:address":"Brinkhorst 2",
    "sg:city":"Haren Gn",
    "sg:orig_category":"Bloemen And Planten",
    "sg:phone":"+31 50 537 0200",
    "sg:postcode":"9751 AT",
    "sg:province":"Groningen",
    "wof:name":"Bloemen Mozaik",
    "wof:placetype":"venue"
},
  "geometry": {"coordinates":[6.604873,53.173332],"type":"Point"}
}