{
  "type": "Feature",
  "properties": {
    "addr:full":"Hessenwg 186 De Bilt Utrecht 3731 JN",
    "addr:housenumber":"186",
    "addr:postcode":"3731 jn",
    "iso:country":"NL",
    "sg:address":"Hessenwg 186",
    "sg:city":"De Bilt",
    "sg:orig_category":"Opticiens",
    "sg:phone":"+31 30 220 3795",
    "sg:postcode":"3731 JN",
    "sg:province":"Utrecht",
    "wof:name":"Eijken Bv, Van",
    "wof:placetype":"venue"
},
  "geometry": {"coordinates":[5.1823348999,52.1111412048],"type":"Point"}
}