{
  "type": "Feature",
  "properties": {
    "iso:country":"NL",
    "sg:address":"Pluimstr 88",
    "sg:city":"Enschede",
    "sg:orig_category":"Postkantoren",
    "sg:phone":"+31 53 431 8517",
    "sg:postcode":"7511 BW",
    "sg:province":"NL.08",
    "sg:website":"http://www.postkantoor.nl",
    "wof:name":"Postkantoor",
    "wof:placetype":"venue"
},
  "geometry": {"coordinates":[6.911777,52.221348],"type":"Point"}
}