{
  "type": "Feature",
  "properties": {
    "addr:full":"Noorderstr 125 Sappemeer Groningen 9611 AC",
    "addr:housenumber":"125",
    "addr:postcode":"9611 ac",
    "iso:country":"NL",
    "sg:address":"Noorderstr 125",
    "sg:city":"Sappemeer",
    "sg:orig_category":"Verlichting",
    "sg:phone":"+31 598 399 265",
    "sg:postcode":"9611 AC",
    "sg:province":"Groningen",
    "wof:name":"Lichtboetiek Sappemeer",
    "wof:placetype":"venue"
},
  "geometry": {"coordinates":[6.788497,53.164242],"type":"Point"}
}