{
  "type": "Feature",
  "properties": {
    "addr:full":"Tulpenstraat 75 Breda Noord-Brabant 4818 GT",
    "addr:housenumber":"75",
    "addr:postcode":"4818 gt",
    "addr:street":"Tulpenstraat",
    "iso:country":"NL",
    "sg:address":"Tulpenstraat 75",
    "sg:city":"Breda",
    "sg:orig_category":"Sportactiviteiten En -Evenementen",
    "sg:phone":"+31 76 514 5372",
    "sg:postcode":"4818 GT",
    "sg:province":"Noord-Brabant",
    "wof:name":"Ad Ballon Ballonvaarten Bv",
    "wof:placetype":"venue"
},
  "geometry": {"coordinates":[4.787594,51.578876],"type":"Point"}
}