{
  "type": "Feature",
  "properties": {
    "iso:country":"NL",
    "sg:address":"Oudedk 7",
    "sg:city":"Maasdyk",
    "sg:orig_category":"Bloemen En Planten - Groothandel",
    "sg:phone":"+31 174 516 049",
    "sg:postcode":"2676 NC",
    "sg:province":"South Holland",
    "wof:name":"Burg, Fa Van Den",
    "wof:placetype":"venue"
},
  "geometry": {"coordinates":[4.217563,51.967922],"type":"Point"}
}