{
  "type": "Feature",
  "properties": {
    "addr:full":"Eem 20 Zeewolde Flevoland 3891 CS",
    "addr:housenumber":"20",
    "addr:postcode":"3891 cs",
    "addr:street":"Eem;Flevoland",
    "iso:country":"NL",
    "sg:address":"Eem 20",
    "sg:city":"Zeewolde",
    "sg:orig_category":"Verlichting And Huishoudartikelen",
    "sg:phone":"+31 36 522 0520",
    "sg:postcode":"3891 CS",
    "sg:province":"Flevoland",
    "wof:name":"Smoll Design",
    "wof:placetype":"venue"
},
  "geometry": {"coordinates":[5.531591,52.331509],"type":"Point"}
}