{
  "type": "Feature",
  "properties": {
    "addr:full":"Kweldergras 35 Spykenisse South Holland 3206 SK",
    "addr:housenumber":"35",
    "addr:street":"Kweldergras;3206",
    "iso:country":"NL",
    "sg:address":"Kweldergras 35",
    "sg:city":"Spykenisse",
    "sg:classifiers":[
        {
            "category":"Personal",
            "subcategory":"Nail Salon",
            "type":"Services"
        }
    ],
    "sg:phone":"+31 181 641 815",
    "sg:postcode":"3206 SK",
    "sg:province":"South Holland",
    "sg:tags":[
        "pedicure"
    ],
    "wof:name":"Verhagen, Karin",
    "wof:placetype":"venue"
},
  "geometry": {"coordinates":[4.32515,51.829128],"type":"Point"}
}