{
  "type": "Feature",
  "properties": {
    "addr:full":"Nieuwlandsekade 13 Ouderkerk A/D Ijssel Zuid-Holland 2935 CG",
    "addr:housenumber":"13;a / d",
    "addr:postcode":"2935 cg",
    "addr:street":"Nieuwlandsekade",
    "iso:country":"NL",
    "sg:address":"Nieuwlandsekade 13",
    "sg:city":"Ouderkerk A/D Ijssel",
    "sg:orig_category":"Goederenvervoer Over De Weg",
    "sg:phone":"+31 180 681 166",
    "sg:postcode":"2935 CG",
    "sg:province":"Zuid-Holland",
    "wof:name":"Aad De Pee Transport",
    "wof:placetype":"venue"
},
  "geometry": {"coordinates":[4.638993,51.965633],"type":"Point"}
}