{
  "type": "Feature",
  "properties": {
    "addr:full":"Berkenwg 43A Baarn Utrecht 3741 BW",
    "addr:housenumber":"43a",
    "addr:postcode":"3741 bw",
    "addr:street":"Berkenwg",
    "iso:country":"NL",
    "sg:address":"Berkenwg 43A",
    "sg:city":"Baarn",
    "sg:orig_category":"Verenigingen En Stichtingen",
    "sg:phone":"+31 35 542 0989",
    "sg:postcode":"3741 BW",
    "sg:province":"Utrecht",
    "wof:name":"Ehbo Afd Baarn, Kon Ned Ver",
    "wof:placetype":"venue"
},
  "geometry": {"coordinates":[5.285252,52.214741],"type":"Point"}
}