{
  "type": "Feature",
  "properties": {
    "addr:full":"Baardmosstr 63 Purmerend North Holland 1441 LV",
    "addr:housenumber":"63",
    "addr:postcode":"1441",
    "addr:street":"Baardmosstr",
    "iso:country":"NL",
    "sg:address":"Baardmosstr 63",
    "sg:city":"Purmerend",
    "sg:orig_category":"Webdesign Bureaus",
    "sg:phone":"+31 299 402 846",
    "sg:postcode":"1441 LV",
    "sg:province":"North Holland",
    "wof:name":"Manilla, Studio",
    "wof:placetype":"venue"
},
  "geometry": {"coordinates":[4.9570879936,52.5000686646],"type":"Point"}
}