{
  "type": "Feature",
  "properties": {
    "addr:full":"Essenstr 19 Haarlem North Holland 2011 DW",
    "addr:housenumber":"19",
    "addr:postcode":"2011 dw",
    "addr:street":"Essenstr",
    "iso:country":"NL",
    "sg:address":"Essenstr 19",
    "sg:city":"Haarlem",
    "sg:orig_category":"Loopbaanbegeleiding",
    "sg:phone":"+31 23 532 7121",
    "sg:postcode":"2011 DW",
    "sg:province":"North Holland",
    "wof:name":"Beweegkunst",
    "wof:placetype":"venue"
},
  "geometry": {"coordinates":[4.637773,52.377056],"type":"Point"}
}