{
  "type": "Feature",
  "properties": {
    "addr:full":"Zandstr 31A St Michielsgestel Noord-Brabant 5271 TH",
    "addr:housenumber":"31a",
    "addr:postcode":"5271 th",
    "addr:street":"Zandstr;St Michielsgestel",
    "iso:country":"NL",
    "sg:address":"Zandstr 31A",
    "sg:city":"St Michielsgestel",
    "sg:orig_category":"Keukens",
    "sg:phone":"+31 73 594 1427",
    "sg:postcode":"5271 TH",
    "sg:province":"Noord-Brabant",
    "sg:website":"http://www.vanboven.nl",
    "wof:name":"Boven Bv, Van",
    "wof:placetype":"venue"
},
  "geometry": {"coordinates":[5.375261,51.654919],"type":"Point"}
}