{
  "type": "Feature",
  "properties": {
    "iso:country":"NL",
    "sg:address":"Vlinkert 82",
    "sg:city":"Heusden Gem Asten",
    "sg:orig_category":"Autokeuringen",
    "sg:phone":"+31 493 691 684",
    "sg:postcode":"5725 AL",
    "sg:province":"Noord-Brabant",
    "wof:name":"Garagebedrijf G Cortooms",
    "wof:placetype":"venue"
},
  "geometry": {"coordinates":[5.766977,51.383312],"type":"Point"}
}