{
  "type": "Feature",
  "properties": {
    "addr:full":"Bisonspoor 8006 Maarssen Utrecht 3605 LW",
    "addr:housenumber":"8006",
    "addr:postcode":"3605 lw",
    "addr:street":"Bisonspoor",
    "iso:country":"NL",
    "sg:address":"Bisonspoor 8006",
    "sg:city":"Maarssen",
    "sg:orig_category":"Werving En Selectie",
    "sg:phone":"+31 346 554 815",
    "sg:postcode":"3605 LW",
    "sg:province":"Utrecht",
    "sg:website":"http://www.lpa.nl",
    "wof:name":"Lpa",
    "wof:placetype":"venue"
},
  "geometry": {"coordinates":[5.0281629562,52.1354560852],"type":"Point"}
}