{
  "type": "Feature",
  "properties": {
    "iso:country":"NL",
    "sg:address":"Zuiderhoofdstr 38",
    "sg:city":"Krommenie",
    "sg:classifiers":[
        {
            "category":"Personal",
            "subcategory":"Nail Salon",
            "type":"Services"
        }
    ],
    "sg:phone":"+31 75 640 9001",
    "sg:postcode":"1561 AM",
    "sg:province":"North Holland",
    "sg:tags":[
        "pedicure"
    ],
    "wof:name":"Time Out",
    "wof:placetype":"venue"
},
  "geometry": {"coordinates":[4.767826,52.497814],"type":"Point"}
}