{
  "type": "Feature",
  "properties": {
    "addr:full":"Richard Wagnerlaan 33 'S Gravenhage Zuid-Holland 2555 WT",
    "addr:housenumber":"33",
    "addr:postcode":"2555 wt",
    "addr:street":"Richard Wagnerlaan;' S",
    "iso:country":"NL",
    "sg:address":"Richard Wagnerlaan 33",
    "sg:city":"'S Gravenhage",
    "sg:orig_category":"Vertaal- And Tolkenbureaus",
    "sg:phone":"+31 70 323 9049",
    "sg:postcode":"2555 WT",
    "sg:province":"Zuid-Holland",
    "wof:name":"C.T. Tromp",
    "wof:placetype":"venue"
},
  "geometry": {"coordinates":[4.237839,52.063717],"type":"Point"}
}