{
  "type": "Feature",
  "properties": {
    "iso:country":"NL",
    "sg:address":"Richard Wagnerlaan 33",
    "sg:city":"'S Gravenhage",
    "sg:orig_category":"Vertaal- And Tolkenbureaus",
    "sg:phone":"+31 70 323 9049",
    "sg:postcode":"2555 WT",
    "sg:province":"Zuid-Holland",
    "wof:name":"C.T. Tromp",
    "wof:placetype":"venue"
},
  "geometry": {"coordinates":[4.237839,52.063717],"type":"Point"}
}