{
  "type": "Feature",
  "properties": {
    "iso:country":"NL",
    "sg:address":"Gemertsewg 36",
    "sg:city":"Oploo",
    "sg:orig_category":"Gehandicapteninformatie",
    "sg:phone":"+31 485 388 911",
    "sg:postcode":"5841 CE",
    "sg:province":"Noord-Brabant",
    "wof:name":"Bronlaak, Instituut",
    "wof:placetype":"venue"
},
  "geometry": {"coordinates":[-39.34277,-5.32226],"type":"Point"}
}