{
  "type": "Feature",
  "properties": {
    "addr:full":"Gemeentewg 55 Staphorst Overijssel 7951 CE",
    "addr:housenumber":"55",
    "addr:postcode":"7951 ce",
    "addr:street":"Gemeentewg",
    "iso:country":"NL",
    "sg:address":"Gemeentewg 55",
    "sg:city":"Staphorst",
    "sg:orig_category":"Meubelmakerijen",
    "sg:phone":"+31 522 461 370",
    "sg:postcode":"7951 CE",
    "sg:province":"Overijssel",
    "wof:name":"Kruidhof",
    "wof:placetype":"venue"
},
  "geometry": {"coordinates":[6.207459,52.645905],"type":"Point"}
}