{
  "type": "Feature",
  "properties": {
    "addr:full":"Noordeinde 329 Boskoop Zuid-Holland 2771 WP",
    "addr:housenumber":"329",
    "addr:postcode":"2771 wp",
    "addr:street":"Noordeinde",
    "iso:country":"NL",
    "sg:address":"Noordeinde 329",
    "sg:city":"Boskoop",
    "sg:orig_category":"Metaalwerken",
    "sg:phone":"+31 172 210 070",
    "sg:postcode":"2771 WP",
    "sg:province":"Zuid-Holland",
    "wof:name":"Degenkamp Zonweringstechniek",
    "wof:placetype":"venue"
},
  "geometry": {"coordinates":[4.636831,52.073727],"type":"Point"}
}