{
  "type": "Feature",
  "properties": {
    "addr:full":"Wilhelminalaan 63 Valkenburg A/D Geul Limburg 6301 GH",
    "addr:housenumber":"63;a / d",
    "addr:postcode":"6301 gh",
    "addr:street":"Wilhelminalaan",
    "iso:country":"NL",
    "sg:address":"Wilhelminalaan 63",
    "sg:city":"Valkenburg A/D Geul",
    "sg:classifiers":[
        {
            "category":"Travel",
            "subcategory":"Hotels & Motels",
            "type":"Entertainment"
        }
    ],
    "sg:phone":"+31 43 601 0601",
    "sg:postcode":"6301 GH",
    "sg:province":"Limburg",
    "sg:website":"http://www.hotel-austen.nl",
    "wof:name":"Hotel Austen",
    "wof:placetype":"venue"
},
  "geometry": {"coordinates":[5.829852,50.864182],"type":"Point"}
}