{
  "type": "Feature",
  "properties": {
    "addr:full":"H R Holst Erf 177 Dordrecht Zuid-Holland 3315 TE",
    "addr:housenumber":"177",
    "addr:postcode":"3315 te",
    "addr:street":"H;Holst Erf",
    "iso:country":"NL",
    "sg:address":"H R Holst Erf 177",
    "sg:city":"Dordrecht",
    "sg:orig_category":"Fotografie Reclame En Mode",
    "sg:phone":"+31 78 621 5527",
    "sg:postcode":"3315 TE",
    "sg:province":"Zuid-Holland",
    "wof:name":"Muller, Herman",
    "wof:placetype":"venue"
},
  "geometry": {"coordinates":[4.656506,51.811916],"type":"Point"}
}