{
  "type": "Feature",
  "properties": {
    "iso:country":"NL",
    "sg:address":"Herenweg 258",
    "sg:city":"Wilnis",
    "sg:orig_category":"Loodgieterswerk, Verwarming And Sanitaire Installaties",
    "sg:phone":"+31 297 287 070",
    "sg:postcode":"3648 CR",
    "sg:province":"Utrecht",
    "wof:name":"Van Den Heuvel Cv Service&Onderhoud",
    "wof:placetype":"venue"
},
  "geometry": {"coordinates":[4.877929,52.198864],"type":"Point"}
}