{
  "type": "Feature",
  "properties": {
    "iso:country":"NL",
    "sg:address":"Saxenkampstraat 11",
    "sg:city":"Venlo",
    "sg:orig_category":"Verzekeringen",
    "sg:phone":"+31 77 351 7464",
    "sg:postcode":"5912 EB",
    "sg:province":"Limburg",
    "wof:name":"Assurantiekantoor J.P. Slijpen",
    "wof:placetype":"venue"
},
  "geometry": {"coordinates":[6.163349,51.361992],"type":"Point"}
}