{
  "type": "Feature",
  "properties": {
    "addr:full":"Hoofdstraat 21A Westerbork Drenthe 9431 AB",
    "addr:housenumber":"21a",
    "addr:postcode":"9431 ab",
    "addr:street":"Hoofdstraat",
    "iso:country":"NL",
    "sg:address":"Hoofdstraat 21A",
    "sg:city":"Westerbork",
    "sg:orig_category":"Overheidsdiensten",
    "sg:phone":"+31 593 332 125",
    "sg:postcode":"9431 AB",
    "sg:province":"Drenthe",
    "wof:name":"Het Kruispunt",
    "wof:placetype":"venue"
},
  "geometry": {"coordinates":[6.6104221344,52.8502616882],"type":"Point"}
}