{
  "type": "Feature",
  "properties": {
    "iso:country":"NL",
    "sg:address":"E Bakkenstr 10",
    "sg:city":"Heerlen",
    "sg:orig_category":"Medische Installaties En Instrumenten",
    "sg:phone":"+31 45 566 8000",
    "sg:postcode":"6422 PJ",
    "sg:province":"Limburg",
    "sg:website":"http://www.medtronic.com",
    "wof:name":"Medtronic Bv",
    "wof:placetype":"venue"
},
  "geometry": {"coordinates":[6.01294,50.841976],"type":"Point"}
}