{
  "type": "Feature",
  "properties": {
    "addr:full":"Voorstraat 31 Ammerzoden Gelderland 5324 AT",
    "addr:housenumber":"31",
    "addr:postcode":"5324",
    "addr:street":"Voorstraat;Gelderland",
    "iso:country":"NL",
    "sg:address":"Voorstraat 31",
    "sg:city":"Ammerzoden",
    "sg:orig_category":"Fotografische And Optische Artikelen Gh",
    "sg:phone":"+31 73 599 7022",
    "sg:postcode":"5324 AT",
    "sg:province":"Gelderland",
    "wof:name":"Hofstede Medical",
    "wof:placetype":"venue"
},
  "geometry": {"coordinates":[5.223578,51.747177],"type":"Point"}
}