{
  "type": "Feature",
  "properties": {
    "addr:full":"Hoofdstraat 25 Kaatsheuvel Noord-Brabant 5171 DJ",
    "addr:housenumber":"25",
    "addr:postcode":"5171 dj",
    "addr:street":"Hoofdstraat",
    "iso:country":"NL",
    "sg:address":"Hoofdstraat 25",
    "sg:city":"Kaatsheuvel",
    "sg:orig_category":"Wasserettes And Stomerijen",
    "sg:phone":"+31 416 273 084",
    "sg:postcode":"5171 DJ",
    "sg:province":"Noord-Brabant",
    "wof:name":"Pico Bello Stomerij",
    "wof:placetype":"venue"
},
  "geometry": {"coordinates":[5.0363578796,51.6612281799],"type":"Point"}
}