{
  "type": "Feature",
  "properties": {
    "addr:full":"Bloemerstraat 95 Nijmegen Gelderland 6511 EG",
    "addr:housenumber":"95",
    "addr:postcode":"6511 eg",
    "addr:street":"Bloemerstraat;Gelderland",
    "iso:country":"NL",
    "sg:address":"Bloemerstraat 95",
    "sg:city":"Nijmegen",
    "sg:orig_category":"Werving And Selectie Van Tijdelijk Personeel And Uitzendkantoren",
    "sg:phone":"+31 24 324 5588",
    "sg:postcode":"6511 EG",
    "sg:province":"Gelderland",
    "wof:name":"Jmw",
    "wof:placetype":"venue"
},
  "geometry": {"coordinates":[5.8608641624,51.8454742432],"type":"Point"}
}