{
  "type": "Feature",
  "properties": {
    "addr:full":"Kastanjelaan 16 Ridderkerk South Holland 2982 CM",
    "addr:housenumber":"16",
    "addr:postcode":"2982 cm",
    "addr:street":"Kastanjelaan",
    "iso:country":"NL",
    "sg:address":"Kastanjelaan 16",
    "sg:city":"Ridderkerk",
    "sg:orig_category":"Bouwnijverheidsmachines Gh",
    "sg:phone":"+31 180 411 977",
    "sg:postcode":"2982 CM",
    "sg:province":"South Holland",
    "wof:name":"Bruderer Nederland",
    "wof:placetype":"venue"
},
  "geometry": {"coordinates":[4.588958,51.876152],"type":"Point"}
}