{
  "type": "Feature",
  "properties": {
    "addr:full":"Gruttostraat 8 Wijchen Gelderland 6601 EP",
    "addr:housenumber":"8",
    "addr:postcode":"6601 ep",
    "addr:street":"Gruttostraat;Gelderland",
    "iso:country":"NL",
    "sg:address":"Gruttostraat 8",
    "sg:city":"Wijchen",
    "sg:orig_category":"Baby- And Kinderkleding",
    "sg:phone":"+31 24 642 2862",
    "sg:postcode":"6601 EP",
    "sg:province":"Gelderland",
    "wof:name":"Just",
    "wof:placetype":"venue"
},
  "geometry": {"coordinates":[5.730547,51.816456],"type":"Point"}
}