{
  "type": "Feature",
  "properties": {
    "iso:country":"NL",
    "sg:address":"Slonninkwg 32",
    "sg:city":"Deventer",
    "sg:orig_category":"Adviesbureaus",
    "sg:phone":"+31 570 658 240",
    "sg:postcode":"7421 EV",
    "sg:province":"Overijssel",
    "wof:name":"Door",
    "wof:placetype":"venue"
},
  "geometry": {"coordinates":[6.227421,52.244652],"type":"Point"}
}