{
  "type": "Feature",
  "properties": {
    "iso:country":"NL",
    "sg:address":"Kluizenaarsbocht 7",
    "sg:city":"Delft",
    "sg:orig_category":"Diverse Grafische Activiteiten",
    "sg:phone":"+31 15 219 2525",
    "sg:postcode":"2614 GT",
    "sg:province":"Zuid-Holland",
    "wof:name":"Drukkerij Nivo Dtp Service",
    "wof:placetype":"venue"
},
  "geometry": {"coordinates":[4.344889,52.003639],"type":"Point"}
}