{
  "type": "Feature",
  "properties": {
    "addr:full":"Herderln 12B Ermelo Gelderland 3851 BD",
    "addr:housenumber":"12b",
    "addr:postcode":"3851 bd",
    "addr:street":"Herderln;Gelderland",
    "iso:country":"NL",
    "sg:address":"Herderln 12B",
    "sg:city":"Ermelo",
    "sg:orig_category":"Verpakkingen En Verpakkingsmaterialen",
    "sg:phone":"+31 341 551 273",
    "sg:postcode":"3851 BD",
    "sg:province":"Gelderland",
    "sg:website":"http://www.zuidam.net",
    "wof:name":"Zuidam Bv",
    "wof:placetype":"venue"
},
  "geometry": {"coordinates":[5.63146,52.297852],"type":"Point"}
}