{
  "type": "Feature",
  "properties": {
    "addr:full":"Postbus 60111 Groningen Limburg 9703 BC",
    "addr:housenumber":"60111",
    "addr:postcode":"9703 bc",
    "addr:street":"Postbus",
    "iso:country":"NL",
    "sg:address":"Postbus 60111",
    "sg:city":"Groningen",
    "sg:orig_category":"Vertaalbureaus",
    "sg:phone":"+31 50 542 5316",
    "sg:postcode":"9703 BC",
    "sg:province":"Limburg",
    "wof:name":"Palantir",
    "wof:placetype":"venue"
},
  "geometry": {"coordinates":[6.56502,53.21645],"type":"Point"}
}