{
  "type": "Feature",
  "properties": {
    "addr:full":"Woonschepenhaven 26 Groningen Groningen 9723 CJ",
    "addr:housenumber":"26",
    "addr:postcode":"9723 cj",
    "addr:street":"Woonschepenhaven",
    "iso:country":"NL",
    "sg:address":"Woonschepenhaven 26",
    "sg:city":"Groningen",
    "sg:orig_category":"Vertalers",
    "sg:phone":"+31 50 542 5340",
    "sg:postcode":"9723 CJ",
    "sg:province":"Groningen",
    "sg:website":"http://www.apt70.com",
    "wof:name":"Apt 70",
    "wof:placetype":"venue"
},
  "geometry": {"coordinates":[6.600834,53.221741],"type":"Point"}
}