{
  "type": "Feature",
  "properties": {
    "iso:country":"NL",
    "sg:address":"Visafslagweg 1",
    "sg:city":"'S Gravenhage",
    "sg:orig_category":"Visspeciaalzaken",
    "sg:phone":"+31 70 352 7800",
    "sg:postcode":"2583 DM",
    "sg:province":"Zuid-Holland",
    "wof:name":"Gemeentelijke Stichting Scheveninger Visafslag",
    "wof:placetype":"venue"
},
  "geometry": {"coordinates":[4.263781,52.099987],"type":"Point"}
}