{
  "type": "Feature",
  "properties": {
    "addr:full":"Schotsmanweg 1 Kamperland Zeeland 4493 CX",
    "addr:housenumber":"1",
    "addr:postcode":"4493 cx",
    "addr:street":"Schotsmanweg",
    "iso:country":"NL",
    "sg:address":"Schotsmanweg 1",
    "sg:city":"Kamperland",
    "sg:orig_category":"Kampeerterreinen",
    "sg:phone":"+31 113 371 751",
    "sg:postcode":"4493 CX",
    "sg:province":"Zeeland",
    "wof:name":"Rcn De Schotsman",
    "wof:placetype":"venue"
},
  "geometry": {"coordinates":[3.6685800552,51.5663337708],"type":"Point"}
}