{
  "type": "Feature",
  "properties": {
    "addr:full":"Achterom 9 Blaricum North Holland 1261 EE",
    "addr:housenumber":"9",
    "addr:postcode":"1261 ee",
    "addr:street":"Achterom",
    "iso:country":"NL",
    "sg:address":"Achterom 9",
    "sg:city":"Blaricum",
    "sg:orig_category":"Antiekzaken",
    "sg:phone":"+31 35 538 1586",
    "sg:postcode":"1261 EE",
    "sg:province":"North Holland",
    "wof:name":"Galerie Bric A Brac",
    "wof:placetype":"venue"
},
  "geometry": {"coordinates":[5.243588,52.274242],"type":"Point"}
}