{
  "type": "Feature",
  "properties": {
    "iso:country":"NL",
    "sg:address":"Koningstr 76",
    "sg:city":"Afferden Gld",
    "sg:orig_category":"Kappers",
    "sg:phone":"+31 487 531 131",
    "sg:postcode":"6654 AH",
    "sg:province":"Gelderland",
    "wof:name":"B-Bop Kapsalon",
    "wof:placetype":"venue"
},
  "geometry": {"coordinates":[5.6328539848,51.8813858032],"type":"Point"}
}