{
  "type": "Feature",
  "properties": {
    "iso:country":"NL",
    "sg:address":"Waterlustln 65",
    "sg:city":"Gouda",
    "sg:orig_category":"Verzekeringen - Verzekeringskantoren",
    "sg:phone":"+31 182 699 585",
    "sg:postcode":"2804 KX",
    "sg:province":"Zuid-Holland",
    "wof:name":"Alom",
    "wof:placetype":"venue"
},
  "geometry": {"coordinates":[4.710584,52.037334],"type":"Point"}
}