{
  "type": "Feature",
  "properties": {
    "addr:full":"Gr Wichmanln 19A Bussum Noord-Holland 1405 GX",
    "addr:housenumber":"19a",
    "addr:postcode":"1405 gx",
    "iso:country":"NL",
    "sg:address":"Gr Wichmanln 19A",
    "sg:city":"Bussum",
    "sg:orig_category":"Scholen Voor Basisonderwijs",
    "sg:phone":"+31 35 691 1150",
    "sg:postcode":"1405 GX",
    "sg:province":"Noord-Holland",
    "wof:name":"Emmaschool, Kon",
    "wof:placetype":"venue"
},
  "geometry": {"coordinates":[5.156301,52.276051],"type":"Point"}
}