{
  "type": "Feature",
  "properties": {
    "addr:full":"Aalsterveld 70 Beuningen Gld Gelderland 6641 SE",
    "addr:housenumber":"70",
    "addr:postcode":"6641 se",
    "addr:street":"Aalsterveld",
    "iso:country":"NL",
    "sg:address":"Aalsterveld 70",
    "sg:city":"Beuningen Gld",
    "sg:orig_category":"Farmaceutische Producten Gh",
    "sg:phone":"+31 24 677 0695",
    "sg:postcode":"6641 SE",
    "sg:province":"Gelderland",
    "wof:name":"Salby Medical Products",
    "wof:placetype":"venue"
},
  "geometry": {"coordinates":[5.755078,51.865311],"type":"Point"}
}