{
  "type": "Feature",
  "properties": {
    "iso:country":"NL",
    "sg:address":"Luchthavenwg 59-Vii",
    "sg:city":"Eindhoven",
    "sg:classifiers":[
        {
            "category":"Professional",
            "type":"Services"
        }
    ],
    "sg:phone":"+31 40 257 2211",
    "sg:postcode":"5657 EA",
    "sg:province":"North Brabant",
    "sg:tags":[
        "leasing"
    ],
    "sg:website":"http://www.interleasing.nl",
    "wof:name":"Interleasing Nederland Bv",
    "wof:placetype":"venue"
},
  "geometry": {"coordinates":[5.39235,51.456921],"type":"Point"}
}