{
  "type": "Feature",
  "properties": {
    "addr:full":"Marsanahof 55 Maastricht Limburg 6215 TR",
    "addr:housenumber":"55",
    "addr:postcode":"6215 tr",
    "addr:street":"Marsanahof",
    "iso:country":"NL",
    "sg:address":"Marsanahof 55",
    "sg:city":"Maastricht",
    "sg:orig_category":"Verzekeringen",
    "sg:phone":"+31 43 347 3294",
    "sg:postcode":"6215 TR",
    "sg:province":"Limburg",
    "wof:name":"Coolen",
    "wof:placetype":"venue"
},
  "geometry": {"coordinates":[5.655262,50.842976],"type":"Point"}
}