{
  "type": "Feature",
  "properties": {
    "iso:country":"NL",
    "sg:address":"Molenpln 10",
    "sg:city":"Heerenveen",
    "sg:orig_category":"Fietsen En Bromfietsen",
    "sg:phone":"+31 513 622 688",
    "sg:postcode":"8442 LM",
    "sg:province":"Friesland",
    "wof:name":"Vries, De",
    "wof:placetype":"venue"
},
  "geometry": {"coordinates":[5.929095,52.95845],"type":"Point"}
}