{
  "type": "Feature",
  "properties": {
    "addr:full":"Goossensstr 16 Aarle Rixtel Noord-Brabant 5735 CJ",
    "addr:housenumber":"16",
    "addr:postcode":"5735 cj",
    "addr:street":"Goossensstr",
    "iso:country":"NL",
    "sg:address":"Goossensstr 16",
    "sg:city":"Aarle Rixtel",
    "sg:orig_category":"Organisatiebureaus",
    "sg:phone":"+31 492 385 642",
    "sg:postcode":"5735 CJ",
    "sg:province":"Noord-Brabant",
    "wof:name":"Peel, De",
    "wof:placetype":"venue"
},
  "geometry": {"coordinates":[5.6425099373,51.51146698],"type":"Point"}
}