{
  "type": "Feature",
  "properties": {
    "addr:full":"Turbinestr 1 Amsterdam Noord-Holland 1014 AV",
    "addr:housenumber":"1",
    "addr:postcode":"1014 av",
    "addr:street":"Turbinestr",
    "iso:country":"NL",
    "sg:address":"Turbinestr 1",
    "sg:city":"Amsterdam",
    "sg:orig_category":"Woninginrichting",
    "sg:phone":"+31 20 400 3377",
    "sg:postcode":"1014 AV",
    "sg:province":"Noord-Holland",
    "sg:website":"http://www.fictura.nl",
    "wof:name":"Fictura",
    "wof:placetype":"venue"
},
  "geometry": {"coordinates":[4.8530797958,52.3896903992],"type":"Point"}
}