{
  "type": "Feature",
  "properties": {
    "iso:country":"NL",
    "sg:address":"Oostdorperweg 32",
    "sg:city":"Wassenaar",
    "sg:classifiers":[
        {
            "category":"Fast Food",
            "type":"Food & Drink"
        }
    ],
    "sg:phone":"+31 70 514 0406",
    "sg:postcode":"2242 NK",
    "sg:province":"South Holland",
    "sg:tags":[
        "afhaal",
        "restaurant"
    ],
    "wof:name":"Pizzeria Guido",
    "wof:placetype":"venue"
},
  "geometry": {"coordinates":[4.395516,52.147774],"type":"Point"}
}