{
  "type": "Feature",
  "properties": {
    "iso:country":"NL",
    "sg:address":"Breevaartstraat 25",
    "sg:city":"Rotterdam",
    "sg:orig_category":"Autokeuringen",
    "sg:phone":"+31 10 415 2211",
    "sg:postcode":"3044 AG",
    "sg:province":"Zuid-Holland",
    "wof:name":"Machinefabriek & Reparatie- Bedrijf J.C. Terlouw B",
    "wof:placetype":"venue"
},
  "geometry": {"coordinates":[4.424544,51.928276],"type":"Point"}
}