{
  "type": "Feature",
  "properties": {
    "addr:full":"Greft 4 Wartena Friesland 9003 XZ",
    "addr:housenumber":"4",
    "addr:postcode":"9003 xz",
    "addr:street":"Greft",
    "iso:country":"NL",
    "sg:address":"Greft 4",
    "sg:city":"Wartena",
    "sg:orig_category":"Paardensport",
    "sg:phone":"+31 58 255 2769",
    "sg:postcode":"9003 XZ",
    "sg:province":"Friesland",
    "wof:name":"Lei, P Van Der",
    "wof:placetype":"venue"
},
  "geometry": {"coordinates":[5.885559,53.138634],"type":"Point"}
}