{
  "type": "Feature",
  "properties": {
    "addr:full":"Slemphutterwg 18 Eibergen Gelderland 7152 CR",
    "addr:housenumber":"18",
    "addr:postcode":"7152 cr",
    "addr:street":"Slemphutterwg;Gelderland",
    "iso:country":"NL",
    "sg:address":"Slemphutterwg 18",
    "sg:city":"Eibergen",
    "sg:orig_category":"Hondenscholen",
    "sg:phone":"+31 545 472 539",
    "sg:postcode":"7152 CR",
    "sg:province":"Gelderland",
    "wof:name":"Holterhook",
    "wof:placetype":"venue"
},
  "geometry": {"coordinates":[6.692223,52.069099],"type":"Point"}
}