{
  "type": "Feature",
  "properties": {
    "addr:full":"Industriestr 3 Haaksbergen NL.08 7482 EW",
    "addr:housenumber":"3;nl.08",
    "addr:postcode":"7482 ew",
    "addr:street":"Industriestr",
    "iso:country":"NL",
    "sg:address":"Industriestr 3",
    "sg:city":"Haaksbergen",
    "sg:orig_category":"Grondwerken",
    "sg:phone":"+31 53 573 5800",
    "sg:postcode":"7482 EW",
    "sg:province":"NL.08",
    "wof:name":"Langezaal Haaksbergen Bv",
    "wof:placetype":"venue"
},
  "geometry": {"coordinates":[6.724519,52.154587],"type":"Point"}
}