{
  "type": "Feature",
  "properties": {
    "addr:full":"Holleweg 1 Venlo Limburg 5926 RK",
    "addr:housenumber":"1",
    "addr:postcode":"5926 rk",
    "addr:street":"Holleweg",
    "iso:country":"NL",
    "sg:address":"Holleweg 1",
    "sg:city":"Venlo",
    "sg:orig_category":"Autoverhuur",
    "sg:phone":"+31 77 382 7070",
    "sg:postcode":"5926 RK",
    "sg:province":"Limburg",
    "wof:name":"Taxi E3",
    "wof:placetype":"venue"
},
  "geometry": {"coordinates":[6.128519,51.358154],"type":"Point"}
}