{
  "type": "Feature",
  "properties": {
    "addr:full":"Dr A H J Coppesstraat 1 Enschede NL.08 7523 EJ",
    "addr:housenumber":"1",
    "addr:postcode":"7523 ej",
    "addr:street":"Dr A H J Coppesstraat",
    "iso:country":"NL",
    "sg:address":"Dr A H J Coppesstraat 1",
    "sg:city":"Enschede",
    "sg:orig_category":"Verlichting And Huishoudartikelen",
    "sg:phone":"+31 53 435 2889",
    "sg:postcode":"7523 EJ",
    "sg:province":"NL.08",
    "wof:name":"Tapijt- En Gordijncentrale Mekkelholt",
    "wof:placetype":"venue"
},
  "geometry": {"coordinates":[6.887036,52.234699],"type":"Point"}
}