{
  "type": "Feature",
  "properties": {
    "addr:full":"Goorsestr 17 Haaksbergen Overijssel 7482 CB",
    "addr:housenumber":"17",
    "addr:postcode":"7482 cb",
    "addr:street":"Goorsestr",
    "iso:country":"NL",
    "sg:address":"Goorsestr 17",
    "sg:city":"Haaksbergen",
    "sg:orig_category":"Kunststoffen- Verwerkende Industrie",
    "sg:phone":"+31 53 572 7900",
    "sg:postcode":"7482 CB",
    "sg:province":"Overijssel",
    "wof:name":"Novatech",
    "wof:placetype":"venue"
},
  "geometry": {"coordinates":[6.73439,52.159031],"type":"Point"}
}