{
  "type": "Feature",
  "properties": {
    "addr:full":"Dirk Van Voornelaan 2 Rockanje Zuid-Holland 3235 AC",
    "addr:housenumber":"2",
    "addr:postcode":"3235 ac",
    "addr:street":"Dirk Van Voornelaan",
    "iso:country":"NL",
    "sg:address":"Dirk Van Voornelaan 2",
    "sg:city":"Rockanje",
    "sg:orig_category":"Tandartsen",
    "sg:phone":"+31 181 402 210",
    "sg:postcode":"3235 AC",
    "sg:province":"Zuid-Holland",
    "wof:name":"J.C. Klok",
    "wof:placetype":"venue"
},
  "geometry": {"coordinates":[4.064271,51.872158],"type":"Point"}
}