{
  "type": "Feature",
  "properties": {
    "addr:full":"Postbus 2017 Deventer Overijssel 7420 AA",
    "addr:housenumber":"2017",
    "addr:postcode":"7420 aa",
    "addr:street":"Postbus",
    "iso:country":"NL",
    "sg:address":"Postbus 2017",
    "sg:city":"Deventer",
    "sg:orig_category":"Landmeetkundige Bureaus",
    "sg:phone":"+31 570 503 250",
    "sg:postcode":"7420 AA",
    "sg:province":"Overijssel",
    "sg:website":"http://www.facto.info",
    "wof:name":"Facto Bv",
    "wof:placetype":"venue"
},
  "geometry": {"coordinates":[6.15984,52.25354],"type":"Point"}
}