{
  "type": "Feature",
  "properties": {
    "addr:full":"Marktstraat 1 Swalmen Limburg 6071 JE",
    "addr:housenumber":"1",
    "addr:postcode":"6071 je",
    "addr:street":"Marktstraat",
    "iso:country":"NL",
    "sg:address":"Marktstraat 1",
    "sg:city":"Swalmen",
    "sg:orig_category":"Juweliers",
    "sg:phone":"+31 475 501 697",
    "sg:postcode":"6071 JE",
    "sg:province":"Limburg",
    "wof:name":"J.J.G. Vallen",
    "wof:placetype":"venue"
},
  "geometry": {"coordinates":[6.035633,51.231613],"type":"Point"}
}