{
  "type": "Feature",
  "properties": {
    "addr:full":"K Hengelosestr 15 Enschede NL.08 7511 JA",
    "addr:housenumber":"15",
    "addr:postcode":"7511 ja",
    "addr:street":"Hengelosestr",
    "iso:country":"NL",
    "sg:address":"K Hengelosestr 15",
    "sg:city":"Enschede",
    "sg:orig_category":"Bloemen En Planten",
    "sg:phone":"+31 53 431 0536",
    "sg:postcode":"7511 JA",
    "sg:province":"NL.08",
    "wof:name":"Marloes",
    "wof:placetype":"venue"
},
  "geometry": {"coordinates":[6.892724,52.221706],"type":"Point"}
}