{
  "type": "Feature",
  "properties": {
    "iso:country":"NL",
    "sg:address":"Verlaat 9",
    "sg:city":"Heerhugowaard",
    "sg:orig_category":"Houtverduurzaming",
    "sg:phone":"+31 226 421 286",
    "sg:postcode":"1704 JN",
    "sg:province":"Noord-Holland",
    "wof:name":"Olympic Stain",
    "wof:placetype":"venue"
},
  "geometry": {"coordinates":[4.856785,52.720486],"type":"Point"}
}