{
  "type": "Feature",
  "properties": {
    "addr:full":"Franz Schubertlaan 64 Heemstede Noord-Holland 2102 EM",
    "addr:housenumber":"64",
    "addr:postcode":"2102 em",
    "addr:street":"Franz Schubertlaan",
    "iso:country":"NL",
    "sg:address":"Franz Schubertlaan 64",
    "sg:city":"Heemstede",
    "sg:orig_category":"Werving And Selectie Van Vast Personeel",
    "sg:phone":"+31 23 528 3612",
    "sg:postcode":"2102 EM",
    "sg:province":"Noord-Holland",
    "wof:name":"Tannemaat Consultancy & Management",
    "wof:placetype":"venue"
},
  "geometry": {"coordinates":[4.626540184,52.3552742004],"type":"Point"}
}