{
  "type": "Feature",
  "properties": {
    "addr:full":"Peperstr 12 Montfoort Utrecht 3417 JB",
    "addr:housenumber":"12",
    "addr:postcode":"3417 jb",
    "addr:street":"Peperstr",
    "iso:country":"NL",
    "sg:address":"Peperstr 12",
    "sg:city":"Montfoort",
    "sg:orig_category":"Pensioenen",
    "sg:phone":"+31 348 470 743",
    "sg:postcode":"3417 JB",
    "sg:province":"Utrecht",
    "wof:name":"Q+W/Cons",
    "wof:placetype":"venue"
},
  "geometry": {"coordinates":[4.949714,52.045662],"type":"Point"}
}