{
  "type": "Feature",
  "properties": {
    "iso:country":"NL",
    "sg:address":"Heliumwg 40A",
    "sg:city":"Amersfoort",
    "sg:orig_category":"Keukens",
    "sg:phone":"+31 33 465 1111",
    "sg:postcode":"3812 RE",
    "sg:province":"Utrecht",
    "sg:website":"http://www.kooikeukens.nl",
    "wof:name":"Kooi, Paul Van Der",
    "wof:placetype":"venue"
},
  "geometry": {"coordinates":[5.355214,52.172298],"type":"Point"}
}