{
  "type": "Feature",
  "properties": {
    "iso:country":"NL",
    "sg:address":"Schoolakkerplein 48",
    "sg:city":"Breda",
    "sg:orig_category":"Diverse Grafische Activiteiten",
    "sg:phone":"+31 76 561 1319",
    "sg:postcode":"4835 EJ",
    "sg:province":"North Brabant",
    "wof:name":"Henk Stolker",
    "wof:placetype":"venue"
},
  "geometry": {"coordinates":[4.788994,51.567551],"type":"Point"}
}