{
  "type": "Feature",
  "properties": {
    "addr:full":"Iepenln 20 Bloemendaal Noord-Holland 2061 GK",
    "addr:housenumber":"20",
    "addr:postcode":"2061 gk",
    "addr:street":"Iepenln",
    "iso:country":"NL",
    "sg:address":"Iepenln 20",
    "sg:city":"Bloemendaal",
    "sg:orig_category":"Architecten En Architectenbureaus",
    "sg:phone":"+31 23 526 7204",
    "sg:postcode":"2061 GK",
    "sg:province":"Noord-Holland",
    "wof:name":"Elsen, Yvonne Van Den",
    "wof:placetype":"venue"
},
  "geometry": {"coordinates":[4.624498,52.399624],"type":"Point"}
}