{
  "type": "Feature",
  "properties": {
    "addr:full":"F V Eedenln 53 Leiden Zuid-Holland 2321 BC",
    "addr:housenumber":"53",
    "addr:postcode":"2321 bc",
    "addr:street":"Eedenln",
    "iso:country":"NL",
    "sg:address":"F V Eedenln 53",
    "sg:city":"Leiden",
    "sg:orig_category":"Voetbalverenigingen",
    "sg:phone":"+31 6 14751616",
    "sg:postcode":"2321 BC",
    "sg:province":"Zuid-Holland",
    "wof:name":"Gol Sport",
    "wof:placetype":"venue"
},
  "geometry": {"coordinates":[4.48449,52.149212],"type":"Point"}
}