{
  "type": "Feature",
  "properties": {
    "addr:full":"Anna Paulownastraat 50 'S Gravenhage Zuid-Holland 2518 BG",
    "addr:housenumber":"50",
    "addr:postcode":"2518",
    "addr:street":"Anna Paulownastraat;' S",
    "iso:country":"NL",
    "sg:address":"Anna Paulownastraat 50",
    "sg:city":"'S Gravenhage",
    "sg:orig_category":"Architecten",
    "sg:phone":"+31 70 345 4041",
    "sg:postcode":"2518 BG",
    "sg:province":"Zuid-Holland",
    "wof:name":"Ing. Kleikamp Bv",
    "wof:placetype":"venue"
},
  "geometry": {"coordinates":[4.299189,52.084991],"type":"Point"}
}