{
  "type": "Feature",
  "properties": {
    "addr:full":"Helftheuv Passage 99 S Hertogenbosch Noord-Brabant 5224 AC",
    "addr:housenumber":"99",
    "addr:postcode":"5224 ac",
    "addr:street":"Passage;S Hertogenbosch",
    "iso:country":"NL",
    "sg:address":"Helftheuv Passage 99",
    "sg:city":"S Hertogenbosch",
    "sg:orig_category":"Schoenen",
    "sg:phone":"+31 73 623 0773",
    "sg:postcode":"5224 AC",
    "sg:province":"Noord-Brabant",
    "sg:website":"http://www.brantano.nl",
    "wof:name":"Brantano",
    "wof:placetype":"venue"
},
  "geometry": {"coordinates":[5.266288,51.695293],"type":"Point"}
}