{
  "type": "Feature",
  "properties": {
    "addr:full":"Langdonk 5 Roosendaal Noord-Brabant 4707 TG",
    "addr:housenumber":"5",
    "addr:postcode":"4707 tg",
    "addr:street":"Langdonk",
    "iso:country":"NL",
    "sg:address":"Langdonk 5",
    "sg:city":"Roosendaal",
    "sg:orig_category":"Psychologen",
    "sg:phone":"+31 165 396 555",
    "sg:postcode":"4707 TG",
    "sg:province":"Noord-Brabant",
    "wof:name":"Remedius",
    "wof:placetype":"venue"
},
  "geometry": {"coordinates":[4.472837,51.521336],"type":"Point"}
}