{
  "type": "Feature",
  "properties": {
    "addr:full":"Postbus 14809 Amsterdam Noord-Holland 1001 LH",
    "addr:housenumber":"14809",
    "addr:postcode":"1001 lh",
    "addr:street":"Postbus",
    "iso:country":"NL",
    "sg:address":"Postbus 14809",
    "sg:city":"Amsterdam",
    "sg:orig_category":"Belastingconsulenten/ Belastingadviseurs",
    "sg:phone":"+31 20 427 7700",
    "sg:postcode":"1001 LH",
    "sg:province":"Noord-Holland",
    "sg:website":"http://www.vatreclaimers.com",
    "wof:name":"European Vat Reclaimers",
    "wof:placetype":"venue"
},
  "geometry": {"coordinates":[4.89319,52.373119],"type":"Point"}
}