{
  "type": "Feature",
  "properties": {
    "addr:full":"Generaal De La Reijstr 25 Haarlem North Holland 2021 XR",
    "addr:housenumber":"25",
    "addr:postcode":"2021 xr",
    "addr:street":"Generaal De La Reijstr",
    "iso:country":"NL",
    "sg:address":"Generaal De La Reijstr 25",
    "sg:city":"Haarlem",
    "sg:orig_category":"Onderhoud And Reparatie Kantoorapparatuur",
    "sg:phone":"+31 23 527 9813",
    "sg:postcode":"2021 XR",
    "sg:province":"North Holland",
    "wof:name":"Relco Ict",
    "wof:placetype":"venue"
},
  "geometry": {"coordinates":[4.642608,52.393387],"type":"Point"}
}