{
  "type": "Feature",
  "properties": {
    "addr:full":"De Vecht 20 Woerden South Holland 3448 CM",
    "addr:housenumber":"20",
    "addr:postcode":"3448 cm",
    "addr:street":"De Vecht",
    "iso:country":"NL",
    "sg:address":"De Vecht 20",
    "sg:city":"Woerden",
    "sg:orig_category":"Boekhouders",
    "sg:phone":"+31 348 411 973",
    "sg:postcode":"3448 CM",
    "sg:province":"South Holland",
    "wof:name":"Administratiekantoor Dece",
    "wof:placetype":"venue"
},
  "geometry": {"coordinates":[4.872355,52.076641],"type":"Point"}
}