{
  "type": "Feature",
  "properties": {
    "addr:full":"Kloosterstr 9 Velden Limburg 5941 ES",
    "addr:housenumber":"9",
    "addr:postcode":"5941 es",
    "addr:street":"Kloosterstr",
    "iso:country":"NL",
    "sg:address":"Kloosterstr 9",
    "sg:city":"Velden",
    "sg:orig_category":"Bejaarden - Verzorgingstehuizen",
    "sg:phone":"+31 77 472 2884",
    "sg:postcode":"5941 ES",
    "sg:province":"Limburg",
    "sg:website":"http://www.zorggroep-noord-limburg.nl",
    "wof:name":"Blaeckhof",
    "wof:placetype":"venue"
},
  "geometry": {"coordinates":[6.163224,51.41637],"type":"Point"}
}