{
  "type": "Feature",
  "properties": {
    "iso:country":"NL",
    "sg:address":"Ln V Rome 63",
    "sg:city":"Alkmaar",
    "sg:orig_category":"Bedrijfsopleidingen",
    "sg:phone":"+31 6 51235616",
    "sg:postcode":"1827 AR",
    "sg:province":"North Holland",
    "sg:website":"http://www.overbruggen.com",
    "wof:name":"Overbruggen",
    "wof:placetype":"venue"
},
  "geometry": {"coordinates":[4.76605,52.671101],"type":"Point"}
}