{
  "type": "Feature",
  "properties": {
    "addr:full":"Koperensteeg 3A Wekerom Gelderland 6733 JA",
    "addr:housenumber":"3a",
    "addr:postcode":"6733 ja",
    "addr:street":"Koperensteeg;Gelderland",
    "iso:country":"NL",
    "sg:address":"Koperensteeg 3A",
    "sg:city":"Wekerom",
    "sg:orig_category":"Huizensloop And Bouwrijp Maken",
    "sg:phone":"+31 318 463 001",
    "sg:postcode":"6733 JA",
    "sg:province":"Gelderland",
    "wof:name":"De Hofstede Bv",
    "wof:placetype":"venue"
},
  "geometry": {"coordinates":[5.709426,52.111881],"type":"Point"}
}