{
  "type": "Feature",
  "properties": {
    "addr:full":"Zilverenberg 27 'S Hertogenbosch Noord-Brabant 5234 GL",
    "addr:housenumber":"27",
    "addr:postcode":"5234 gl",
    "addr:street":"Zilverenberg;' S",
    "iso:country":"NL",
    "sg:address":"Zilverenberg 27",
    "sg:city":"'S Hertogenbosch",
    "sg:orig_category":"Fotostudio'S And Fotografen",
    "sg:phone":"+31 73 642 4484",
    "sg:postcode":"5234 GL",
    "sg:province":"Noord-Brabant",
    "wof:name":"Mark Van Dijk Fotografie",
    "wof:placetype":"venue"
},
  "geometry": {"coordinates":[5.286257,51.724979],"type":"Point"}
}