{
  "type": "Feature",
  "properties": {
    "iso:country":"NL",
    "sg:address":"Oosterhoek 28",
    "sg:city":"Tuk",
    "sg:orig_category":"Homeopathie",
    "sg:phone":"+31 521 513 362",
    "sg:postcode":"8334 RC",
    "sg:province":"Overijssel",
    "wof:name":"Paalman, S I B M",
    "wof:placetype":"venue"
},
  "geometry": {"coordinates":[-122.841599,48.057613],"type":"Point"}
}