{
  "type": "Feature",
  "properties": {
    "iso:country":"NL",
    "sg:address":"Gv Juliana V Stolbergln 789",
    "sg:city":"Leidschendam",
    "sg:orig_category":"Huishoudapparatuur, Televisies And Radio'S",
    "sg:phone":"+31 70 327 7694",
    "sg:postcode":"2263 BA",
    "sg:province":"Zuid-Holland",
    "wof:name":"R.M.F. Communications",
    "wof:placetype":"venue"
},
  "geometry": {"coordinates":[4.41042,52.10218],"type":"Point"}
}