{
  "type": "Feature",
  "properties": {
    "addr:full":"Stadhuisplein 2 Lelystad Flevoland 8232 ZX",
    "addr:housenumber":"2",
    "addr:postcode":"8232 zx",
    "addr:street":"Stadhuisplein;Flevoland",
    "iso:country":"NL",
    "sg:address":"Stadhuisplein 2",
    "sg:city":"Lelystad",
    "sg:orig_category":"Woningbouwverenigingen",
    "sg:phone":"+31 320 278 222",
    "sg:postcode":"8232 ZX",
    "sg:province":"Flevoland",
    "wof:name":"Wooninformatiecentrum Stadhuis",
    "wof:placetype":"venue"
},
  "geometry": {"coordinates":[5.4760870934,52.506816864],"type":"Point"}
}