{
  "type": "Feature",
  "properties": {
    "addr:full":"Beatrixln 30 Posterholt Limburg 6061 BR",
    "addr:housenumber":"30",
    "addr:postcode":"6061 br",
    "addr:street":"Beatrixln",
    "iso:country":"NL",
    "sg:address":"Beatrixln 30",
    "sg:city":"Posterholt",
    "sg:orig_category":"Administratie- En Boekhoudkantoren",
    "sg:phone":"+31 475 402 610",
    "sg:postcode":"6061 BR",
    "sg:province":"Limburg",
    "wof:name":"Geelen Bv, Administratiekantoor J J M",
    "wof:placetype":"venue"
},
  "geometry": {"coordinates":[6.042236,51.121056],"type":"Point"}
}