{
  "type": "Feature",
  "properties": {
    "addr:full":"Kruisstraat 16 Munstergeleen Limburg 6151 BP",
    "addr:housenumber":"16",
    "addr:postcode":"6151 bp",
    "addr:street":"Kruisstraat",
    "iso:country":"NL",
    "sg:address":"Kruisstraat 16",
    "sg:city":"Munstergeleen",
    "sg:orig_category":"Goederenvervoer Over De Weg",
    "sg:phone":"+31 46 458 0265",
    "sg:postcode":"6151 BP",
    "sg:province":"Limburg",
    "wof:name":"Transportbedrijf J Van Daal Bv",
    "wof:placetype":"venue"
},
  "geometry": {"coordinates":[5.870119,50.973091],"type":"Point"}
}