{
  "type": "Feature",
  "properties": {
    "addr:full":"Sasboutstraat 20 Arnhem Gelderland 6824 AT",
    "addr:housenumber":"20",
    "addr:postcode":"6824",
    "addr:street":"Sasboutstraat",
    "iso:country":"NL",
    "sg:address":"Sasboutstraat 20",
    "sg:city":"Arnhem",
    "sg:orig_category":"Fitnesscentra",
    "sg:phone":"+31 26 445 6162",
    "sg:postcode":"6824 AT",
    "sg:province":"Gelderland",
    "wof:name":"Sportschool Kreijtz",
    "wof:placetype":"venue"
},
  "geometry": {"coordinates":[5.928887,51.986347],"type":"Point"}
}