{
  "type": "Feature",
  "properties": {
    "iso:country":"NL",
    "sg:address":"Rijksweg 37",
    "sg:city":"Gulpen",
    "sg:orig_category":"Juweliers",
    "sg:phone":"+31 43 450 1392",
    "sg:postcode":"6271 AC",
    "sg:province":"Limburg",
    "wof:name":"Opticien J. Alberts-Wijers Bv",
    "wof:placetype":"venue"
},
  "geometry": {"coordinates":[5.893122,50.815414],"type":"Point"}
}