{
  "type": "Feature",
  "properties": {
    "addr:full":"Dorpsstraat 24 Bleiswijk Zuid-Holland 2665 BJ",
    "addr:housenumber":"24",
    "addr:postcode":"2665 bj",
    "addr:street":"Dorpsstraat",
    "iso:country":"NL",
    "sg:address":"Dorpsstraat 24",
    "sg:city":"Bleiswijk",
    "sg:orig_category":"Huishoudapparatuur, Televisies And Radio'S",
    "sg:phone":"+31 10 529 0030",
    "sg:postcode":"2665 BJ",
    "sg:province":"Zuid-Holland",
    "wof:name":"Radio Tv Jaco",
    "wof:placetype":"venue"
},
  "geometry": {"coordinates":[4.529647,52.009968],"type":"Point"}
}