{
  "type": "Feature",
  "properties": {
    "addr:full":"Dorpsstr 12 Scharendyke Zeeland 4322 AD",
    "addr:housenumber":"12",
    "addr:postcode":"4322 ad",
    "addr:street":"Dorpsstr;Zeeland",
    "iso:country":"NL",
    "sg:address":"Dorpsstr 12",
    "sg:city":"Scharendyke",
    "sg:classifiers":[
        {
            "category":"Food & Beverages",
            "subcategory":"Bakery",
            "type":"Retail Goods"
        }
    ],
    "sg:phone":"+31 111 671 529",
    "sg:postcode":"4322 AD",
    "sg:province":"Zeeland",
    "sg:tags":[
        "pizza"
    ],
    "wof:name":"Leonardos",
    "wof:placetype":"venue"
},
  "geometry": {"coordinates":[3.840451,51.737804],"type":"Point"}
}