{
  "type": "Feature",
  "properties": {
    "addr:full":"Hadewychplaats 8 Spijkenisse Zuid-Holland 3207 KG",
    "addr:housenumber":"8",
    "addr:postcode":"3207 kg",
    "addr:street":"Hadewychplaats",
    "iso:country":"NL",
    "sg:address":"Hadewychplaats 8",
    "sg:city":"Spijkenisse",
    "sg:orig_category":"Discountwinkels",
    "sg:phone":"+31 181 687 114",
    "sg:postcode":"3207 KG",
    "sg:province":"Zuid-Holland",
    "wof:name":"Zeeman Textielsupers",
    "wof:placetype":"venue"
},
  "geometry": {"coordinates":[4.361305,51.833691],"type":"Point"}
}