{
  "type": "Feature",
  "properties": {
    "addr:full":"Markt 12 Sittard Limburg 6131 EK",
    "addr:housenumber":"12",
    "addr:postcode":"6131 ek",
    "addr:street":"Markt",
    "iso:country":"NL",
    "sg:address":"Markt 12",
    "sg:city":"Sittard",
    "sg:classifiers":[
        {
            "category":"Fast Food",
            "type":"Food & Drink"
        }
    ],
    "sg:phone":"+31 46 458 8884",
    "sg:postcode":"6131 EK",
    "sg:province":"Limburg",
    "sg:tags":[
        "afhaal",
        "restaurant"
    ],
    "wof:name":"De Kiosk",
    "wof:placetype":"venue"
},
  "geometry": {"coordinates":[5.869909,50.998753],"type":"Point"}
}