{
  "type": "Feature",
  "properties": {
    "addr:full":"Duvenvoordestr 19Zw Haarlem Noord-Holland 2013 AB",
    "addr:housenumber":"19zw",
    "addr:postcode":"2013 ab",
    "addr:street":"Duvenvoordestr",
    "iso:country":"NL",
    "sg:address":"Duvenvoordestr 19Zw",
    "sg:city":"Haarlem",
    "sg:orig_category":"Octrooionderzoek- En Exploitatiebureaus",
    "sg:phone":"+31 23 542 4271",
    "sg:postcode":"2013 AB",
    "sg:province":"Noord-Holland",
    "wof:name":"Ideas Bv",
    "wof:placetype":"venue"
},
  "geometry": {"coordinates":[4.62577,52.38652],"type":"Point"}
}