{
  "type": "Feature",
  "properties": {
    "iso:country":"NL",
    "sg:address":"Achillesstraat 12",
    "sg:city":"Amsterdam",
    "sg:orig_category":"Vertaal- And Tolkenbureaus",
    "sg:phone":"+31 20 671 1604",
    "sg:postcode":"1076 RB",
    "sg:province":"Noord-Holland",
    "wof:name":"Context Vertaalbureau",
    "wof:placetype":"venue"
},
  "geometry": {"coordinates":[4.865251,52.347721],"type":"Point"}
}