{
  "type": "Feature",
  "properties": {
    "addr:full":"Vondelln 8 Baarn Utrecht 3743 HZ",
    "addr:housenumber":"8",
    "addr:postcode":"3743 hz",
    "addr:street":"Vondelln",
    "iso:country":"NL",
    "sg:address":"Vondelln 8",
    "sg:city":"Baarn",
    "sg:orig_category":"Administratie- En Boekhoudkantoren",
    "sg:phone":"+31 35 543 1606",
    "sg:postcode":"3743 HZ",
    "sg:province":"Utrecht",
    "wof:name":"Inforad",
    "wof:placetype":"venue"
},
  "geometry": {"coordinates":[5.292121,52.21101],"type":"Point"}
}