{
  "type": "Feature",
  "properties": {
    "addr:full":"Hugo De Grootstraat 71 'S Gravenhage Zuid-Holland 2518 EC",
    "addr:housenumber":"71",
    "addr:postcode":"2518 ec",
    "addr:street":"Hugo De Grootstraat;' S",
    "iso:country":"NL",
    "sg:address":"Hugo De Grootstraat 71",
    "sg:city":"'S Gravenhage",
    "sg:classifiers":[
        {
            "category":"Retail",
            "subcategory":"Photofinishing",
            "type":"Services"
        }
    ],
    "sg:phone":"+31 70 365 0955",
    "sg:postcode":"2518 EC",
    "sg:province":"Zuid-Holland",
    "sg:tags":[
        "foto",
        "film"
    ],
    "wof:name":"Foto- Reclamebureau J.C. Bolier Bv",
    "wof:placetype":"venue"
},
  "geometry": {"coordinates":[4.294955,52.083096],"type":"Point"}
}