{
  "type": "Feature",
  "properties": {
    "iso:country":"NL",
    "sg:address":"Annastraat 3",
    "sg:city":"Velp Gld",
    "sg:classifiers":[
        {
            "category":"Education",
            "subcategory":"Preschool",
            "type":"Public Place"
        }
    ],
    "sg:phone":"+31 26 364 0884",
    "sg:postcode":"6882 BA",
    "sg:province":"Gelderland",
    "sg:tags":[
        "kleuteronderwijs",
        "basis-"
    ],
    "wof:name":"Korenbloem De",
    "wof:placetype":"venue"
},
  "geometry": {"coordinates":[5.966582,51.992111],"type":"Point"}
}