{
  "type": "Feature",
  "properties": {
    "iso:country":"NL",
    "sg:address":"Breughelstr 10",
    "sg:city":"Amsterdam",
    "sg:orig_category":"Haptotherapeuten",
    "sg:phone":"+31 20 671 4545",
    "sg:postcode":"1077 LC",
    "sg:province":"Noord-Holland",
    "wof:name":"Haptonomie, Praktijk Voor",
    "wof:placetype":"venue"
},
  "geometry": {"coordinates":[4.877018,52.350098],"type":"Point"}
}