{
  "type": "Feature",
  "properties": {
    "iso:country":"NL",
    "sg:address":"Luthersestr 9",
    "sg:city":"Arnhem",
    "sg:orig_category":"Discotheken",
    "sg:phone":"+31 26 445 0204",
    "sg:postcode":"6811 GR",
    "sg:province":"Gelderland",
    "wof:name":"O",
    "wof:placetype":"venue"
},
  "geometry": {"coordinates":[5.904936,51.981941],"type":"Point"}
}