{
  "type": "Feature",
  "properties": {
    "addr:full":"H Heyermansweg 3 Amsterdam North Holland 1077 WJ",
    "addr:housenumber":"3",
    "addr:postcode":"1077 wj",
    "addr:street":"Heyermansweg",
    "iso:country":"NL",
    "sg:address":"H Heyermansweg 3",
    "sg:city":"Amsterdam",
    "sg:orig_category":"Partycatering And -Organisatie",
    "sg:phone":"+31 20 679 9354",
    "sg:postcode":"1077 WJ",
    "sg:province":"North Holland",
    "wof:name":"L' Oustaou",
    "wof:placetype":"venue"
},
  "geometry": {"coordinates":[4.885488,52.347237],"type":"Point"}
}