{
  "type": "Feature",
  "properties": {
    "addr:full":"Willemsparkweg 165 Amsterdam Noord-Holland 1071 GZ",
    "addr:housenumber":"165",
    "addr:postcode":"1071 gz",
    "addr:street":"Willemsparkweg",
    "iso:country":"NL",
    "sg:address":"Willemsparkweg 165",
    "sg:city":"Amsterdam",
    "sg:orig_category":"Fotolaboratoria",
    "sg:phone":"+31 20 675 0699",
    "sg:postcode":"1071 GZ",
    "sg:province":"Noord-Holland",
    "wof:name":"Rina'S Sprintprint",
    "wof:placetype":"venue"
},
  "geometry": {"coordinates":[4.870719,52.35598],"type":"Point"}
}