{
  "type": "Feature",
  "properties": {
    "addr:full":"Ijsseldijk Noord 336 Ouderkerk A/D Ijssel Zuid-Holland 2935 CR",
    "addr:housenumber":"336;a / d;2935",
    "addr:postcode":"cr",
    "addr:street":"Ijsseldijk Noord",
    "iso:country":"NL",
    "sg:address":"Ijsseldijk Noord 336",
    "sg:city":"Ouderkerk A/D Ijssel",
    "sg:orig_category":"Loodgieterswerk, Verwarming And Sanitaire Installaties",
    "sg:phone":"+31 6 26214528",
    "sg:postcode":"2935 CR",
    "sg:province":"Zuid-Holland",
    "wof:name":"Zandijk",
    "wof:placetype":"venue"
},
  "geometry": {"coordinates":[4.635266,51.969681],"type":"Point"}
}