{
  "type": "Feature",
  "properties": {
    "addr:full":"Hygieapln 38 Amsterdam North Holland 1076 RW",
    "addr:housenumber":"38",
    "addr:postcode":"1076 rw",
    "addr:street":"Hygieapln",
    "iso:country":"NL",
    "sg:address":"Hygieapln 38",
    "sg:city":"Amsterdam",
    "sg:orig_category":"Grafisch Ontwerpers",
    "sg:phone":"+31 20 679 7044",
    "sg:postcode":"1076 RW",
    "sg:province":"North Holland",
    "sg:website":"http://www.cakedesign.nl",
    "wof:name":"Cakedesign",
    "wof:placetype":"venue"
},
  "geometry": {"coordinates":[4.863482,52.346752],"type":"Point"}
}