{
  "type": "Feature",
  "properties": {
    "iso:country":"NL",
    "sg:address":"Deltastraat 2",
    "sg:city":"Kattendijke",
    "sg:orig_category":"Overheidsdiensten",
    "sg:phone":"+31 113 621 915",
    "sg:postcode":"4474 AK",
    "sg:province":"Zeeland",
    "wof:name":"T Blokhuis",
    "wof:placetype":"venue"
},
  "geometry": {"coordinates":[3.9439179897,51.522644043],"type":"Point"}
}