{
  "type": "Feature",
  "properties": {
    "iso:country":"NL",
    "sg:address":"Roserije 111",
    "sg:city":"Maastricht",
    "sg:orig_category":"Huishoudapparatuur, Televisies And Radio'S",
    "sg:phone":"+31 43 361 5631",
    "sg:postcode":"6228 DK",
    "sg:province":"Limburg",
    "wof:name":"Hameleers Radio Tv",
    "wof:placetype":"venue"
},
  "geometry": {"coordinates":[5.726316,50.827709],"type":"Point"}
}