{
  "type": "Feature",
  "properties": {
    "addr:full":"Lothariusstraat 21 Wijk Bij Duurstede Utrecht 3962 BD",
    "addr:housenumber":"21",
    "addr:postcode":"3962 bd",
    "addr:street":"Lothariusstraat",
    "iso:country":"NL",
    "sg:address":"Lothariusstraat 21",
    "sg:city":"Wijk Bij Duurstede",
    "sg:orig_category":"Artsen And Specialisten",
    "sg:phone":"+31 343 571 870",
    "sg:postcode":"3962 BD",
    "sg:province":"Utrecht",
    "wof:name":"Drs. H. Evers",
    "wof:placetype":"venue"
},
  "geometry": {"coordinates":[5.335817,51.97871],"type":"Point"}
}