{
  "type": "Feature",
  "properties": {
    "iso:country":"NL",
    "sg:address":"Hekven 3",
    "sg:city":"Breda",
    "sg:orig_category":"Loodgieterswerk, Verwarming And Sanitaire Installaties",
    "sg:phone":"+31 76 542 8804",
    "sg:postcode":"4824 AD",
    "sg:province":"North Brabant",
    "wof:name":"Sterling Zwaans (Netherlands)",
    "wof:placetype":"venue"
},
  "geometry": {"coordinates":[4.755196,51.603077],"type":"Point"}
}