{
  "type": "Feature",
  "properties": {
    "addr:full":"Valburgsewg 81 Elst Gld Gelderland 6661 ET",
    "addr:housenumber":"81",
    "addr:postcode":"6661 et",
    "addr:street":"Valburgsewg;Gld Gelderland",
    "iso:country":"NL",
    "sg:address":"Valburgsewg 81",
    "sg:city":"Elst Gld",
    "sg:orig_category":"Onroerende Goederen",
    "sg:phone":"+31 481 375 541",
    "sg:postcode":"6661 ET",
    "sg:province":"Gelderland",
    "wof:name":"Pmb Vof",
    "wof:placetype":"venue"
},
  "geometry": {"coordinates":[5.833713,51.919334],"type":"Point"}
}