{
  "type": "Feature",
  "properties": {
    "addr:full":"Herengr 12 Amsterdam North Holland 1015 BK",
    "addr:housenumber":"12",
    "addr:postcode":"1015 bk",
    "addr:street":"Herengr",
    "iso:country":"NL",
    "sg:address":"Herengr 12",
    "sg:city":"Amsterdam",
    "sg:orig_category":"Webdesign Bureaus",
    "sg:phone":"+31 20 627 5355",
    "sg:postcode":"1015 BK",
    "sg:province":"North Holland",
    "sg:website":"http://www.berserk.nl",
    "wof:name":"Berserk Ernie Jonker",
    "wof:placetype":"venue"
},
  "geometry": {"coordinates":[4.8910222054,52.3787231445],"type":"Point"}
}