{
  "type": "Feature",
  "properties": {
    "addr:full":"Enkwg 21 Olst Overijssel 8121 XE",
    "addr:housenumber":"21",
    "addr:postcode":"8121 xe",
    "addr:street":"Enkwg",
    "iso:country":"NL",
    "sg:address":"Enkwg 21",
    "sg:city":"Olst",
    "sg:orig_category":"Autorijscholen",
    "sg:phone":"+31 570 563 756",
    "sg:postcode":"8121 XE",
    "sg:province":"Overijssel",
    "wof:name":"Buitenhuis",
    "wof:placetype":"venue"
},
  "geometry": {"coordinates":[6.114169,52.341637],"type":"Point"}
}