{
  "type": "Feature",
  "properties": {
    "addr:full":"Montgolfierstr 2 Helmond North Brabant 5703 EC",
    "addr:housenumber":"2",
    "addr:postcode":"5703 ec",
    "addr:street":"Montgolfierstr",
    "iso:country":"NL",
    "sg:address":"Montgolfierstr 2",
    "sg:city":"Helmond",
    "sg:orig_category":"Kinderopvang",
    "sg:phone":"+31 492 549 302",
    "sg:postcode":"5703 EC",
    "sg:province":"North Brabant",
    "wof:name":"Big Town",
    "wof:placetype":"venue"
},
  "geometry": {"coordinates":[5.683156,51.479187],"type":"Point"}
}