{
  "type": "Feature",
  "properties": {
    "addr:full":"Oslostraat 57 Almere Flevoland 1334 CB",
    "addr:housenumber":"57;1334",
    "addr:postcode":"cb",
    "addr:street":"Oslostraat;Flevoland",
    "iso:country":"NL",
    "sg:address":"Oslostraat 57",
    "sg:city":"Almere",
    "sg:orig_category":"Werving And Selectie Van Tijdelijk Personeel And Uitzendkantoren",
    "sg:phone":"+31 36 532 2165",
    "sg:postcode":"1334 CB",
    "sg:province":"Flevoland",
    "wof:name":"Loyalty",
    "wof:placetype":"venue"
},
  "geometry": {"coordinates":[5.2755208015,52.3966789246],"type":"Point"}
}