{
  "type": "Feature",
  "properties": {
    "addr:full":"Capellaln 65 Hoofddorp North Holland 2132 JL",
    "addr:housenumber":"65",
    "addr:postcode":"2132 jl",
    "addr:street":"Capellaln",
    "iso:country":"NL",
    "sg:address":"Capellaln 65",
    "sg:city":"Hoofddorp",
    "sg:orig_category":"Boeken En Tijdschriften",
    "sg:phone":"+31 23 556 5135",
    "sg:postcode":"2132 JL",
    "sg:province":"North Holland",
    "sg:website":"http://www.fancy.nl",
    "wof:name":"Fancy",
    "wof:placetype":"venue"
},
  "geometry": {"coordinates":[4.69296,52.305393],"type":"Point"}
}