{
  "type": "Feature",
  "properties": {
    "addr:full":"T Slag 31 Bemmel Gelderland 6681 GA",
    "addr:housenumber":"31",
    "addr:postcode":"6681 ga",
    "addr:street":"T Slag;Gelderland",
    "iso:country":"NL",
    "sg:address":"T Slag 31",
    "sg:city":"Bemmel",
    "sg:orig_category":"Autorijscholen",
    "sg:phone":"+31 481 464 208",
    "sg:postcode":"6681 GA",
    "sg:province":"Gelderland",
    "wof:name":"Janssen, Frank",
    "wof:placetype":"venue"
},
  "geometry": {"coordinates":[5.900509,51.898308],"type":"Point"}
}