{
  "type": "Feature",
  "properties": {
    "addr:full":"O Voorstr 62 Oud Beyerland South Holland 3262 JG",
    "addr:housenumber":"62",
    "addr:postcode":"3262 jg",
    "addr:street":"Oud Beyerland",
    "iso:country":"NL",
    "sg:address":"O Voorstr 62",
    "sg:city":"Oud Beyerland",
    "sg:orig_category":"Kappers",
    "sg:phone":"+31 186 618 490",
    "sg:postcode":"3262 JG",
    "sg:province":"South Holland",
    "wof:name":"Mara",
    "wof:placetype":"venue"
},
  "geometry": {"coordinates":[4.41701,51.823044],"type":"Point"}
}