{
  "type": "Feature",
  "properties": {
    "addr:full":"Rosa Luxemburgstraat 4 Almelo NL.08 7607 SM",
    "addr:housenumber":"4;nl.08",
    "addr:postcode":"7607 sm",
    "addr:street":"Rosa Luxemburgstraat",
    "iso:country":"NL",
    "sg:address":"Rosa Luxemburgstraat 4",
    "sg:city":"Almelo",
    "sg:orig_category":"Werving And Selectie Van Vast Personeel",
    "sg:phone":"+31 74 255 7590",
    "sg:postcode":"7607 SM",
    "sg:province":"NL.08",
    "wof:name":"Centrum Werk En Inkomen Regio Almelo",
    "wof:placetype":"venue"
},
  "geometry": {"coordinates":[6.6627850533,52.356754303],"type":"Point"}
}