{
  "type": "Feature",
  "properties": {
    "addr:full":"Heliumstraat 8 Rijssen NL.08 7463 PL",
    "addr:housenumber":"8;nl.08",
    "addr:postcode":"7463 pl",
    "addr:street":"Heliumstraat",
    "iso:country":"NL",
    "sg:address":"Heliumstraat 8",
    "sg:city":"Rijssen",
    "sg:orig_category":"Kunststofverpakkingen Fab",
    "sg:phone":"+31 548 514 822",
    "sg:postcode":"7463 PL",
    "sg:province":"NL.08",
    "wof:name":"Gerbri Plastics Bv",
    "wof:placetype":"venue"
},
  "geometry": {"coordinates":[6.499074,52.319641],"type":"Point"}
}