{
  "type": "Feature",
  "properties": {
    "addr:full":"De Netelhorst 11 Hattem Gelderland 8051 KE",
    "addr:housenumber":"11",
    "addr:postcode":"8051 ke",
    "addr:street":"De Netelhorst;Gelderland",
    "iso:country":"NL",
    "sg:address":"De Netelhorst 11",
    "sg:city":"Hattem",
    "sg:orig_category":"Houtverwerking",
    "sg:phone":"+31 38 444 2810",
    "sg:postcode":"8051 KE",
    "sg:province":"Gelderland",
    "wof:name":"Apfa Hout",
    "wof:placetype":"venue"
},
  "geometry": {"coordinates":[6.04312,52.485497],"type":"Point"}
}