{
  "type": "Feature",
  "properties": {
    "addr:full":"Lissabonwg 2-4 Vlaardingen Zuid-Holland 3137 LR",
    "addr:housenumber":"2-4",
    "addr:postcode":"3137 lr",
    "addr:street":"Lissabonwg",
    "iso:country":"NL",
    "sg:address":"Lissabonwg 2-4",
    "sg:city":"Vlaardingen",
    "sg:orig_category":"Kinderopvang",
    "sg:phone":"+31 10 475 4677",
    "sg:postcode":"3137 LR",
    "sg:province":"Zuid-Holland",
    "sg:website":"http://www.skv.nl",
    "wof:name":"Pippi",
    "wof:placetype":"venue"
},
  "geometry": {"coordinates":[4.350608,51.934086],"type":"Point"}
}