{
  "type": "Feature",
  "properties": {
    "addr:full":"B Holidaystr 17 Almere Flevoland 1311 PN",
    "addr:housenumber":"17",
    "addr:postcode":"1311 pn",
    "addr:street":"Flevoland",
    "iso:country":"NL",
    "sg:address":"B Holidaystr 17",
    "sg:city":"Almere",
    "sg:orig_category":"Scholen Voor Basisonderwijs",
    "sg:phone":"+31 36 536 4354",
    "sg:postcode":"1311 PN",
    "sg:province":"Flevoland",
    "wof:name":"Vedelaar Obs, De",
    "wof:placetype":"venue"
},
  "geometry": {"coordinates":[5.181963,52.367599],"type":"Point"}
}