{
  "type": "Feature",
  "properties": {
    "iso:country":"NL",
    "sg:address":"Vondelstraat 172",
    "sg:city":"Amsterdam",
    "sg:orig_category":"Boekenuitgeverijen",
    "sg:phone":"+31 20 664 2141",
    "sg:postcode":"1054 GV",
    "sg:province":"Noord-Holland",
    "wof:name":"Esomar",
    "wof:placetype":"venue"
},
  "geometry": {"coordinates":[4.87062,52.360619],"type":"Point"}
}