{
  "type": "Feature",
  "properties": {
    "addr:full":"Dorpstraat 135 Luyksgestel Noord-Brabant 5575 AG",
    "addr:housenumber":"135",
    "addr:postcode":"5575",
    "addr:street":"Dorpstraat",
    "iso:country":"NL",
    "sg:address":"Dorpstraat 135",
    "sg:city":"Luyksgestel",
    "sg:orig_category":"Goederenvervoer Over De Weg",
    "sg:phone":"+31 497 542 068",
    "sg:postcode":"5575 AG",
    "sg:province":"Noord-Brabant",
    "wof:name":"Joosten",
    "wof:placetype":"venue"
},
  "geometry": {"coordinates":[5.316764,51.285141],"type":"Point"}
}