{
  "type": "Feature",
  "properties": {
    "addr:full":"Emmapark 6 'S Gravenhage Zuid-Holland 2595 ET",
    "addr:housenumber":"6 '",
    "addr:postcode":"2595 et",
    "addr:street":"Emmapark",
    "iso:country":"NL",
    "sg:address":"Emmapark 6",
    "sg:city":"'S Gravenhage",
    "sg:orig_category":"Public Relationbureaus",
    "sg:phone":"+31 70 315 9444",
    "sg:postcode":"2595 ET",
    "sg:province":"Zuid-Holland",
    "wof:name":"Adviesbureau Voor Beleidsmarketing Awareness",
    "wof:placetype":"venue"
},
  "geometry": {"coordinates":[4.330467,52.085007],"type":"Point"}
}