{
  "type": "Feature",
  "properties": {
    "iso:country":"NL",
    "sg:address":"Onze Lieve Vrouwestraat 16",
    "sg:city":"Bentelo",
    "sg:orig_category":"Overheidsdiensten",
    "sg:phone":"+31 547 858 585",
    "sg:postcode":"7497 MA",
    "sg:province":"Overijssel",
    "wof:name":"Gemeente Hof Van Twente",
    "wof:placetype":"venue"
},
  "geometry": {"coordinates":[6.6841249466,52.2248687744],"type":"Point"}
}