{
  "type": "Feature",
  "properties": {
    "addr:full":"Bydorp O 6 Barendrecht Zuid-Holland 2992 LA",
    "addr:housenumber":"6",
    "addr:postcode":"2992 la",
    "iso:country":"NL",
    "sg:address":"Bydorp O 6",
    "sg:city":"Barendrecht",
    "sg:orig_category":"Vakorganisaties",
    "sg:phone":"+31 180 643 843",
    "sg:postcode":"2992 LA",
    "sg:province":"Zuid-Holland",
    "wof:name":"Verhage Franchise Organisatie Bv",
    "wof:placetype":"venue"
},
  "geometry": {"coordinates":[4.54064,51.853176],"type":"Point"}
}