{
  "type": "Feature",
  "properties": {
    "addr:full":"Haarlemmermeerstraat 156 Amsterdam North Holland 1058 KK",
    "addr:housenumber":"156",
    "addr:postcode":"1058 kk",
    "addr:street":"Haarlemmermeerstraat",
    "iso:country":"NL",
    "sg:address":"Haarlemmermeerstraat 156",
    "sg:city":"Amsterdam",
    "sg:orig_category":"Kappers",
    "sg:phone":"+31 20 615 5987",
    "sg:postcode":"1058 KK",
    "sg:province":"North Holland",
    "wof:name":"Kapsalon Lichele",
    "wof:placetype":"venue"
},
  "geometry": {"coordinates":[4.8503351212,52.3516769409],"type":"Point"}
}