{
  "type": "Feature",
  "properties": {
    "addr:full":"Kortryk 171 Amsterdam Noord-Holland 1066 TB",
    "addr:housenumber":"171",
    "addr:postcode":"1066 tb",
    "addr:street":"Kortryk",
    "iso:country":"NL",
    "sg:address":"Kortryk 171",
    "sg:city":"Amsterdam",
    "sg:orig_category":"Adviesbureaus Bedrijfsorganisatie",
    "sg:phone":"+31 20 615 7960",
    "sg:postcode":"1066 TB",
    "sg:province":"Noord-Holland",
    "wof:name":"Rensen",
    "wof:placetype":"venue"
},
  "geometry": {"coordinates":[4.89319,52.373119],"type":"Point"}
}