{
  "type": "Feature",
  "properties": {
    "addr:full":"O Randwg 8A Noord Scharwoude Noord-Holland 1723 LH",
    "addr:housenumber":"8a",
    "addr:postcode":"1723 lh",
    "iso:country":"NL",
    "sg:address":"O Randwg 8A",
    "sg:city":"Noord Scharwoude",
    "sg:orig_category":"Houtindustrie",
    "sg:phone":"+31 226 314 590",
    "sg:postcode":"1723 LH",
    "sg:province":"Noord-Holland",
    "wof:name":"Bruin, De",
    "wof:placetype":"venue"
},
  "geometry": {"coordinates":[4.81024,52.698441],"type":"Point"}
}