{
  "type": "Feature",
  "properties": {
    "iso:country":"NL",
    "sg:address":"Wakkerendk 72A",
    "sg:city":"Eemnes",
    "sg:orig_category":"Land- En Tuinbouw - Loonbedrijven",
    "sg:phone":"+31 35 531 2734",
    "sg:postcode":"3755 DD",
    "sg:province":"Utrecht",
    "wof:name":"Klooster, G T Van 'T",
    "wof:placetype":"venue"
},
  "geometry": {"coordinates":[5.264514,52.246769],"type":"Point"}
}