{
  "type": "Feature",
  "properties": {
    "addr:full":"Valkenboskd 290 S Gravenhage South Holland 2563 HE",
    "addr:housenumber":"290",
    "addr:postcode":"2563 he",
    "addr:street":"S Gravenhage",
    "iso:country":"NL",
    "sg:address":"Valkenboskd 290",
    "sg:city":"S Gravenhage",
    "sg:orig_category":"Vertaalbureaus",
    "sg:phone":"+31 70 346 4200",
    "sg:postcode":"2563 HE",
    "sg:province":"South Holland",
    "wof:name":"Regeer",
    "wof:placetype":"venue"
},
  "geometry": {"coordinates":[4.270956,52.072578],"type":"Point"}
}