{
  "type": "Feature",
  "properties": {
    "addr:full":"Paul Krugerstraat 72 Nijmegen Gelderland 6543 MZ",
    "addr:housenumber":"72",
    "addr:postcode":"6543 mz",
    "addr:street":"Paul Krugerstraat;Gelderland",
    "iso:country":"NL",
    "sg:address":"Paul Krugerstraat 72",
    "sg:city":"Nijmegen",
    "sg:orig_category":"Bloemen And Planten",
    "sg:phone":"+31 24 377 1725",
    "sg:postcode":"6543 MZ",
    "sg:province":"Gelderland",
    "wof:name":"Bloemensalon Corona",
    "wof:placetype":"venue"
},
  "geometry": {"coordinates":[5.824632,51.834225],"type":"Point"}
}