{
  "type": "Feature",
  "properties": {
    "iso:country":"NL",
    "sg:address":"P Ebbenwg 19",
    "sg:city":"St Hubert",
    "sg:classifiers":[
        {
            "category":"Retail",
            "subcategory":"Auto Repair",
            "type":"Services"
        }
    ],
    "sg:phone":"+31 485 454 411",
    "sg:postcode":"5454 NB",
    "sg:province":"Noord-Brabant",
    "sg:tags":[
        "garage"
    ],
    "wof:name":"Sint Hubert",
    "wof:placetype":"venue"
},
  "geometry": {"coordinates":[5.793976,51.669415],"type":"Point"}
}