{
  "type": "Feature",
  "properties": {
    "addr:full":"Winkelhaak 27 Leidschendam South Holland 2267 AP",
    "addr:housenumber":"27",
    "addr:postcode":"2267 ap",
    "addr:street":"Winkelhaak",
    "iso:country":"NL",
    "sg:address":"Winkelhaak 27",
    "sg:city":"Leidschendam",
    "sg:orig_category":"Voeding, Dranken And Tabak Gh",
    "sg:phone":"+31 70 399 0202",
    "sg:postcode":"2267 AP",
    "sg:province":"South Holland",
    "wof:name":"Kleinverpakkingen Brochard Bv",
    "wof:placetype":"venue"
},
  "geometry": {"coordinates":[4.40032,52.07888],"type":"Point"}
}