{
  "type": "Feature",
  "properties": {
    "iso:country":"NL",
    "sg:address":"Lochemseweg 1A",
    "sg:city":"Borculo",
    "sg:orig_category":"Advocaten And Juridische Adviseurs",
    "sg:phone":"+31 545 275 225",
    "sg:postcode":"7271 WB",
    "sg:province":"Gelderland",
    "wof:name":"Steentjes Advocaten",
    "wof:placetype":"venue"
},
  "geometry": {"coordinates":[6.522963,52.119404],"type":"Point"}
}