{
  "type": "Feature",
  "properties": {
    "addr:full":"Arlandawg 24 Amsterdam Noord-Holland 1043 EW",
    "addr:housenumber":"24",
    "addr:postcode":"1043 ew",
    "addr:street":"Arlandawg",
    "iso:country":"NL",
    "sg:address":"Arlandawg 24",
    "sg:city":"Amsterdam",
    "sg:orig_category":"Keuringsdiensten",
    "sg:phone":"+31 20 584 0404",
    "sg:postcode":"1043 EW",
    "sg:province":"Noord-Holland",
    "wof:name":"Rvv",
    "wof:placetype":"venue"
},
  "geometry": {"coordinates":[4.83464,52.385681],"type":"Point"}
}