{
  "type": "Feature",
  "properties": {
    "addr:full":"Amersfoortsewg 25 Apeldoorn Gelderland 7313 AC",
    "addr:housenumber":"25",
    "addr:postcode":"7313 ac",
    "addr:street":"Amersfoortsewg;Gelderland",
    "iso:country":"NL",
    "sg:address":"Amersfoortsewg 25",
    "sg:city":"Apeldoorn",
    "sg:orig_category":"Handelscentra",
    "sg:phone":"+31 55 355 6868",
    "sg:postcode":"7313 AC",
    "sg:province":"Gelderland",
    "wof:name":"Hh Dental",
    "wof:placetype":"venue"
},
  "geometry": {"coordinates":[5.929951,52.226933],"type":"Point"}
}