{
  "type": "Feature",
  "properties": {
    "addr:full":"Steenbokstraat 10 Apeldoorn Gelderland 7324 AX",
    "addr:housenumber":"10",
    "addr:postcode":"7324 ax",
    "addr:street":"Steenbokstraat;Gelderland",
    "iso:country":"NL",
    "sg:address":"Steenbokstraat 10",
    "sg:city":"Apeldoorn",
    "sg:orig_category":"Overheidsdiensten",
    "sg:phone":"+31 55 527 2911",
    "sg:postcode":"7324 AX",
    "sg:province":"Gelderland",
    "wof:name":"Waterschap Veluwe",
    "wof:placetype":"venue"
},
  "geometry": {"coordinates":[5.9778828621,52.2376060486],"type":"Point"}
}