{
  "type": "Feature",
  "properties": {
    "addr:full":"Kompasstr 38 Ymuiden Noord-Holland 1973 PZ",
    "addr:housenumber":"38",
    "addr:postcode":"1973 pz",
    "addr:street":"Kompasstr",
    "iso:country":"NL",
    "sg:address":"Kompasstr 38",
    "sg:city":"Ymuiden",
    "sg:orig_category":"Partyservice",
    "sg:phone":"+31 255 511 857",
    "sg:postcode":"1973 PZ",
    "sg:province":"Noord-Holland",
    "sg:website":"HTTP://www.smulsnacks.nl",
    "wof:name":"Smul Snacks",
    "wof:placetype":"venue"
},
  "geometry": {"coordinates":[4.600972,52.457668],"type":"Point"}
}