{
  "type": "Feature",
  "properties": {
    "iso:country":"NL",
    "sg:address":"Beyerschewg 37",
    "sg:city":"Stolwyk",
    "sg:orig_category":"Beeldende Kunstenaars",
    "sg:phone":"+31 182 517 390",
    "sg:postcode":"2821 NC",
    "sg:province":"Zuid-Holland",
    "wof:name":"Huizer, D",
    "wof:placetype":"venue"
},
  "geometry": {"coordinates":[-80.018333,35.21941],"type":"Point"}
}