{
  "type": "Feature",
  "properties": {
    "addr:full":"Ruitersveldwg 19A Wezep Gelderland 8091 HR",
    "addr:housenumber":"19a",
    "addr:postcode":"8091 hr",
    "addr:street":"Ruitersveldwg",
    "iso:country":"NL",
    "sg:address":"Ruitersveldwg 19A",
    "sg:city":"Wezep",
    "sg:orig_category":"Bloemen En Planten",
    "sg:phone":"+31 38 376 0133",
    "sg:postcode":"8091 HR",
    "sg:province":"Gelderland",
    "wof:name":"4 Jaargetijden, De",
    "wof:placetype":"venue"
},
  "geometry": {"coordinates":[6.000411,52.463959],"type":"Point"}
}