{
  "type": "Feature",
  "properties": {
    "addr:full":"Nw Uitleg 10 Bakel Noord-Brabant 5761 ED",
    "addr:housenumber":"10",
    "addr:postcode":"5761 ed",
    "addr:street":"Nw Uitleg",
    "iso:country":"NL",
    "sg:address":"Nw Uitleg 10",
    "sg:city":"Bakel",
    "sg:orig_category":"Borduurwerken",
    "sg:phone":"+31 492 341 948",
    "sg:postcode":"5761 ED",
    "sg:province":"Noord-Brabant",
    "wof:name":"Almo-Unique",
    "wof:placetype":"venue"
},
  "geometry": {"coordinates":[5.739025,51.501263],"type":"Point"}
}