{
  "type": "Feature",
  "properties": {
    "iso:country":"NL",
    "sg:address":"Kruisweg 33",
    "sg:city":"Bergen Nh",
    "sg:orig_category":"Boekhouders",
    "sg:phone":"+31 72 589 5313",
    "sg:postcode":"1861 LA",
    "sg:province":"Noord-Holland",
    "wof:name":"Komen Bergen Bv",
    "wof:placetype":"venue"
},
  "geometry": {"coordinates":[4.704804,52.666851],"type":"Point"}
}