{
  "type": "Feature",
  "properties": {
    "addr:full":"Stadhoudersln 95 Utrecht Utrecht 3583 JG",
    "addr:housenumber":"95",
    "addr:postcode":"3583 jg",
    "addr:street":"Stadhoudersln",
    "iso:country":"NL",
    "sg:address":"Stadhoudersln 95",
    "sg:city":"Utrecht",
    "sg:orig_category":"Medische Keuringen",
    "sg:phone":"+31 30 251 5333",
    "sg:postcode":"3583 JG",
    "sg:province":"Utrecht",
    "wof:name":"Sleijffers, J A",
    "wof:placetype":"venue"
},
  "geometry": {"coordinates":[5.14371,52.086601],"type":"Point"}
}