{
  "type": "Feature",
  "properties": {
    "iso:country":"NL",
    "sg:address":"Milletstr 19",
    "sg:city":"Amsterdam",
    "sg:orig_category":"Fotoreportages",
    "sg:phone":"+31 20 676 8103",
    "sg:postcode":"1077 ZB",
    "sg:province":"Noord-Holland",
    "wof:name":"Frederikse, Tjeerd",
    "wof:placetype":"venue"
},
  "geometry": {"coordinates":[4.870318,52.345837],"type":"Point"}
}