{
  "type": "Feature",
  "properties": {
    "addr:full":"Nieuwestad 107 Leeuwarden Provincie Friesland 8911 CM",
    "addr:housenumber":"107",
    "addr:postcode":"8911 cm",
    "addr:street":"Nieuwestad;Provincie Friesland",
    "iso:country":"NL",
    "sg:address":"Nieuwestad 107",
    "sg:city":"Leeuwarden",
    "sg:orig_category":"Juweliers",
    "sg:phone":"+31 58 212 4770",
    "sg:postcode":"8911 CM",
    "sg:province":"Provincie Friesland",
    "sg:website":"http://www.juwelierdoro.nl",
    "wof:name":"D'Oro, Juwelier",
    "wof:placetype":"venue"
},
  "geometry": {"coordinates":[5.794529,53.200977],"type":"Point"}
}