{
  "type": "Feature",
  "properties": {
    "addr:full":"Akerstr 6 Heerlen Limburg 6411 HA",
    "addr:housenumber":"6",
    "addr:postcode":"6411 ha",
    "addr:street":"Akerstr",
    "iso:country":"NL",
    "sg:address":"Akerstr 6",
    "sg:city":"Heerlen",
    "sg:orig_category":"Postzegels",
    "sg:phone":"+31 45 571 8806",
    "sg:postcode":"6411 HA",
    "sg:province":"Limburg",
    "sg:website":"http://www.postzegels.nl",
    "wof:name":"Le Timbre Vof",
    "wof:placetype":"venue"
},
  "geometry": {"coordinates":[5.97951,50.886944],"type":"Point"}
}