{
  "type": "Feature",
  "properties": {
    "iso:country":"NL",
    "sg:address":"Nijverheidsweg 40",
    "sg:city":"Hendrik Ido Ambacht",
    "sg:orig_category":"Gespecialiseerde Bouw",
    "sg:phone":"+31 78 683 1800",
    "sg:postcode":"3341 LJ",
    "sg:province":"South Holland",
    "wof:name":"Rpi Componenten Bv",
    "wof:placetype":"venue"
},
  "geometry": {"coordinates":[4.651744,51.849293],"type":"Point"}
}