{
  "type": "Feature",
  "properties": {
    "addr:full":"Gans 6 Genemuiden Overijssel 8281 GN",
    "addr:housenumber":"6",
    "addr:postcode":"8281 gn",
    "addr:street":"Gans",
    "iso:country":"NL",
    "sg:address":"Gans 6",
    "sg:city":"Genemuiden",
    "sg:orig_category":"Scheepvaartmijen",
    "sg:phone":"+31 38 385 5990",
    "sg:postcode":"8281 GN",
    "sg:province":"Overijssel",
    "wof:name":"Steenstra Bv, H",
    "wof:placetype":"venue"
},
  "geometry": {"coordinates":[6.051486,52.619297],"type":"Point"}
}