{
  "type": "Feature",
  "properties": {
    "addr:full":"W Schipperswg 3 Zwyndrecht Zuid-Holland 3334 GN",
    "addr:housenumber":"3",
    "addr:postcode":"zwyndrecht;3334 gn",
    "addr:street":"W",
    "iso:country":"NL",
    "sg:address":"W Schipperswg 3",
    "sg:city":"Zwyndrecht",
    "sg:orig_category":"Administratie- En Boekhoudkantoren",
    "sg:phone":"+31 78 610 1285",
    "sg:postcode":"3334 GN",
    "sg:province":"Zuid-Holland",
    "wof:name":"Porte, La",
    "wof:placetype":"venue"
},
  "geometry": {"coordinates":[4.61027,51.815418],"type":"Point"}
}