{
  "type": "Feature",
  "properties": {
    "addr:full":"Raadhuisplein 2 Lekkerkerk South Holland 2941 BR",
    "addr:housenumber":"2",
    "addr:postcode":"2941 br",
    "addr:street":"Raadhuisplein",
    "iso:country":"NL",
    "sg:address":"Raadhuisplein 2",
    "sg:city":"Lekkerkerk",
    "sg:orig_category":"Kappers",
    "sg:phone":"+31 180 661 207",
    "sg:postcode":"2941 BR",
    "sg:province":"South Holland",
    "wof:name":"Kapsalon Nelly",
    "wof:placetype":"venue"
},
  "geometry": {"coordinates":[4.683991909,51.8962173462],"type":"Point"}
}