{
  "type": "Feature",
  "properties": {
    "addr:full":"Dr V Nieveltwg 20 Castricum Noord-Holland 1901 GD",
    "addr:housenumber":"20",
    "addr:postcode":"1901 gd",
    "addr:street":"Dr;Nieveltwg",
    "iso:country":"NL",
    "sg:address":"Dr V Nieveltwg 20",
    "sg:city":"Castricum",
    "sg:orig_category":"Scholen Voor Basisonderwijs",
    "sg:phone":"+31 251 651 764",
    "sg:postcode":"1901 GD",
    "sg:province":"Noord-Holland",
    "wof:name":"Augustinus Rk",
    "wof:placetype":"venue"
},
  "geometry": {"coordinates":[4.663725,52.546844],"type":"Point"}
}