{
  "type": "Feature",
  "properties": {
    "iso:country":"NL",
    "sg:address":"Van Lijndenlaan 27",
    "sg:city":"Naarden",
    "sg:orig_category":"Boekhouders",
    "sg:phone":"+31 35 694 2930",
    "sg:postcode":"1412 EJ",
    "sg:province":"Noord-Holland",
    "wof:name":"Administratieve Organisatie Adorga Bv",
    "wof:placetype":"venue"
},
  "geometry": {"coordinates":[5.151617,52.283298],"type":"Point"}
}