{
  "type": "Feature",
  "properties": {
    "addr:full":"Korhoenstr 34 Alkmaar North Holland 1826 HW",
    "addr:housenumber":"34",
    "addr:postcode":"1826 hw",
    "addr:street":"Korhoenstr",
    "iso:country":"NL",
    "sg:address":"Korhoenstr 34",
    "sg:city":"Alkmaar",
    "sg:orig_category":"Grafmonumenten",
    "sg:phone":"+31 6 24897259",
    "sg:postcode":"1826 HW",
    "sg:province":"North Holland",
    "wof:name":"Voorman, Jetty",
    "wof:placetype":"venue"
},
  "geometry": {"coordinates":[4.765645,52.662781],"type":"Point"}
}