{
  "type": "Feature",
  "properties": {
    "addr:full":"Pianoweg 110 Almere Flevoland 1312 JJ",
    "addr:housenumber":"110",
    "addr:postcode":"1312 jj",
    "addr:street":"Pianoweg;Flevoland",
    "iso:country":"NL",
    "sg:address":"Pianoweg 110",
    "sg:city":"Almere",
    "sg:orig_category":"Kappers",
    "sg:phone":"+31 36 536 5936",
    "sg:postcode":"1312 JJ",
    "sg:province":"Flevoland",
    "wof:name":"Haarstudio Marijke",
    "wof:placetype":"venue"
},
  "geometry": {"coordinates":[5.1910009384,52.3699150085],"type":"Point"}
}