{
  "type": "Feature",
  "properties": {
    "iso:country":"NL",
    "sg:address":"Klinkerstr 86",
    "sg:city":"Oostwold Scheemda",
    "sg:orig_category":"Webdesign Bureaus",
    "sg:phone":"+31 597 552 230",
    "sg:postcode":"9682 RE",
    "sg:province":"Groningen",
    "wof:name":"Kolk",
    "wof:placetype":"venue"
},
  "geometry": {"coordinates":[7.048910141,53.1974182129],"type":"Point"}
}