{
  "type": "Feature",
  "properties": {
    "addr:full":"Koningsplein 7 Maastricht Limburg 6224 EB",
    "addr:housenumber":"7",
    "addr:postcode":"6224 eb",
    "addr:street":"Koningsplein",
    "iso:country":"NL",
    "sg:address":"Koningsplein 7",
    "sg:city":"Maastricht",
    "sg:orig_category":"Binnenhuisarchitecten",
    "sg:phone":"+31 43 363 6500",
    "sg:postcode":"6224 EB",
    "sg:province":"Limburg",
    "wof:name":"Amorij Architekten En Interieurarchitekten",
    "wof:placetype":"venue"
},
  "geometry": {"coordinates":[5.70955,50.848721],"type":"Point"}
}