{
  "type": "Feature",
  "properties": {
    "addr:full":"Heuvelsepad 62 Ede Gld 6710 BC",
    "addr:housenumber":"62",
    "addr:postcode":"6710 bc",
    "addr:street":"Heuvelsepad;Gld",
    "iso:country":"NL",
    "sg:address":"Heuvelsepad 62",
    "sg:city":"Ede Gld",
    "sg:orig_category":"Drukkerijen And Copyshops",
    "sg:phone":"+31 318 650 720",
    "sg:postcode":"6710 BC",
    "wof:name":"Sealaprint Bv",
    "wof:placetype":"venue"
},
  "geometry": {"coordinates":[5.66767,52.044979],"type":"Point"}
}