{
  "type": "Feature",
  "properties": {
    "addr:full":"Middenweg 241 Amsterdam Noord-Holland 1098 AP",
    "addr:housenumber":"241",
    "addr:postcode":"1098 ap",
    "addr:street":"Middenweg",
    "iso:country":"NL",
    "sg:address":"Middenweg 241",
    "sg:city":"Amsterdam",
    "sg:orig_category":"Banken And Kredietinstellingen",
    "sg:phone":"+31 20 663 3411",
    "sg:postcode":"1098 AP",
    "sg:province":"Noord-Holland",
    "wof:name":"Fortis Bank",
    "wof:placetype":"venue"
},
  "geometry": {"coordinates":[4.938041,52.349285],"type":"Point"}
}