{
  "type": "Feature",
  "properties": {
    "addr:full":"Vlaskamp 18 Hoogeveen Provincie Drenthe 7908 ME",
    "addr:housenumber":"18",
    "addr:postcode":"7908",
    "addr:street":"Vlaskamp;Provincie",
    "iso:country":"NL",
    "sg:address":"Vlaskamp 18",
    "sg:city":"Hoogeveen",
    "sg:orig_category":"Etaleurs And Showroominrichters",
    "sg:phone":"+31 528 264 562",
    "sg:postcode":"7908 ME",
    "sg:province":"Provincie Drenthe",
    "wof:name":"Dijkstra Vof",
    "wof:placetype":"venue"
},
  "geometry": {"coordinates":[6.450772,52.723194],"type":"Point"}
}