{
  "type": "Feature",
  "properties": {
    "addr:full":"Kajuit 7 Huizen Noord-Holland 1276 JM",
    "addr:housenumber":"7",
    "addr:postcode":"1276 jm",
    "addr:street":"Kajuit",
    "iso:country":"NL",
    "sg:address":"Kajuit 7",
    "sg:city":"Huizen",
    "sg:orig_category":"Loodgieterswerk, Verwarming And Sanitaire Installaties",
    "sg:phone":"+31 35 526 6952",
    "sg:postcode":"1276 JM",
    "sg:province":"Noord-Holland",
    "wof:name":"H.J. Mooi",
    "wof:placetype":"venue"
},
  "geometry": {"coordinates":[5.251858,52.288822],"type":"Point"}
}