{
  "type": "Feature",
  "properties": {
    "addr:full":"Promenade 26 Veendam Groningen 9641  A",
    "addr:housenumber":"26;9641 a",
    "addr:street":"Promenade",
    "iso:country":"NL",
    "sg:address":"Promenade 26",
    "sg:city":"Veendam",
    "sg:orig_category":"Boekenuitgeverijen",
    "sg:phone":"+31 598 622 554",
    "sg:postcode":"9641  A",
    "sg:province":"Groningen",
    "wof:name":"Bruna",
    "wof:placetype":"venue"
},
  "geometry": {"coordinates":[6.878591,53.105694],"type":"Point"}
}