{
  "type": "Feature",
  "properties": {
    "addr:full":"Burg De Raadtsngl 93 Dordrecht Zuid-Holland 3311 JG",
    "addr:housenumber":"93",
    "addr:postcode":"3311 jg",
    "iso:country":"NL",
    "sg:address":"Burg De Raadtsngl 93",
    "sg:city":"Dordrecht",
    "sg:classifiers":[
        {
            "category":"Professional",
            "subcategory":"Accounting & Tax Preparation",
            "type":"Services"
        }
    ],
    "sg:phone":"+31 78 613 5066",
    "sg:postcode":"3311 JG",
    "sg:province":"Zuid-Holland",
    "sg:tags":[
        "accountant",
        "en",
        "-kantoren",
        "register-"
    ],
    "wof:name":"Moret",
    "wof:placetype":"venue"
},
  "geometry": {"coordinates":[4.656506,51.811916],"type":"Point"}
}