{
  "type": "Feature",
  "properties": {
    "addr:full":"Havenstraat 8 Middenmeer Noord-Holland 1775 AA",
    "addr:housenumber":"8",
    "addr:postcode":"1775 aa",
    "addr:street":"Havenstraat",
    "iso:country":"NL",
    "sg:address":"Havenstraat 8",
    "sg:city":"Middenmeer",
    "sg:orig_category":"Loodgieterswerk, Verwarming And Sanitaire Installaties",
    "sg:phone":"+31 227 501 817",
    "sg:postcode":"1775 AA",
    "sg:province":"Noord-Holland",
    "wof:name":"Wortel'S Klus- En Onderhoudsbedrijf Vof",
    "wof:placetype":"venue"
},
  "geometry": {"coordinates":[4.991529,52.810574],"type":"Point"}
}