{
  "type": "Feature",
  "properties": {
    "addr:full":"Kerkstraat 5 Assen Drenthe 9401 GV",
    "addr:housenumber":"5",
    "addr:postcode":"9401 gv",
    "addr:street":"Kerkstraat",
    "iso:country":"NL",
    "sg:address":"Kerkstraat 5",
    "sg:city":"Assen",
    "sg:orig_category":"Verzekeringen",
    "sg:phone":"+31 592 317 840",
    "sg:postcode":"9401 GV",
    "sg:province":"Drenthe",
    "wof:name":"Kanninga & Faber",
    "wof:placetype":"venue"
},
  "geometry": {"coordinates":[6.559972,52.992622],"type":"Point"}
}