{
  "type": "Feature",
  "properties": {
    "iso:country":"NL",
    "sg:address":"Keienbergwg 59",
    "sg:city":"Amsterdam Zuidoost",
    "sg:orig_category":"Fotolaboratoria",
    "sg:phone":"+31 20 691 3855",
    "sg:postcode":"1101 GA",
    "sg:province":"Noord-Holland",
    "wof:name":"Huf Het Lab Vof",
    "wof:placetype":"venue"
},
  "geometry": {"coordinates":[4.936249,52.308052],"type":"Point"}
}