{
  "type": "Feature",
  "properties": {
    "addr:full":"Mariapln 6 Veldhoven North Brabant 5503 DA",
    "addr:housenumber":"6",
    "addr:postcode":"5503 da",
    "addr:street":"Mariapln",
    "iso:country":"NL",
    "sg:address":"Mariapln 6",
    "sg:city":"Veldhoven",
    "sg:orig_category":"Hengelsportartikelen",
    "sg:phone":"+31 40 255 4407",
    "sg:postcode":"5503 DA",
    "sg:province":"North Brabant",
    "wof:name":"Kempen, De",
    "wof:placetype":"venue"
},
  "geometry": {"coordinates":[5.415746,51.416035],"type":"Point"}
}