{
  "type": "Feature",
  "properties": {
    "addr:full":"Ryksstrwg 24 Dordrecht Zuid-Holland 3316 EH",
    "addr:housenumber":"24",
    "addr:postcode":"3316 eh",
    "addr:street":"Ryksstrwg",
    "iso:country":"NL",
    "sg:address":"Ryksstrwg 24",
    "sg:city":"Dordrecht",
    "sg:orig_category":"Zonweringen",
    "sg:phone":"+31 78 613 5464",
    "sg:postcode":"3316 EH",
    "sg:province":"Zuid-Holland",
    "sg:website":"http://www.janssenzonwering.nl",
    "wof:name":"Janssen, Zonwering",
    "wof:placetype":"venue"
},
  "geometry": {"coordinates":[4.656506,51.811916],"type":"Point"}
}