{
  "type": "Feature",
  "properties": {
    "addr:full":"Poortmolen 198A Capelle Ad Yssel South Holland 2906 RM",
    "addr:housenumber":"198a;2906",
    "addr:postcode":"rm",
    "addr:street":"Poortmolen;Yssel",
    "iso:country":"NL",
    "sg:address":"Poortmolen 198A",
    "sg:city":"Capelle Ad Yssel",
    "sg:orig_category":"Verloskundigen",
    "sg:phone":"+31 10 458 4060",
    "sg:postcode":"2906 RM",
    "sg:province":"South Holland",
    "wof:name":"Smith En A P Van Der Neut, E",
    "wof:placetype":"venue"
},
  "geometry": {"coordinates":[4.565386,51.94109],"type":"Point"}
}