{
  "type": "Feature",
  "properties": {
    "addr:full":"Veenwg 158D Mydrecht Utrecht 3641 SM",
    "addr:housenumber":"158d;3641",
    "addr:postcode":"sm",
    "addr:street":"Veenwg",
    "iso:country":"NL",
    "sg:address":"Veenwg 158D",
    "sg:city":"Mydrecht",
    "sg:orig_category":"Parketvloeren",
    "sg:phone":"+31 297 254 225",
    "sg:postcode":"3641 SM",
    "sg:province":"Utrecht",
    "sg:website":"http://www.parketplaza.nl",
    "wof:name":"Parket Plaza",
    "wof:placetype":"venue"
},
  "geometry": {"coordinates":[4.86178,52.20578],"type":"Point"}
}