{
  "type": "Feature",
  "properties": {
    "addr:full":"Vlietkade 3 Krimpen A/D Ijssel Zuid-Holland 2924 AA",
    "addr:housenumber":"3;a / d",
    "addr:postcode":"2924 aa",
    "addr:street":"Vlietkade",
    "iso:country":"NL",
    "sg:address":"Vlietkade 3",
    "sg:city":"Krimpen A/D Ijssel",
    "sg:orig_category":"Bedrijfs- And Managementsconsultants",
    "sg:phone":"+31 180 523 725",
    "sg:postcode":"2924 AA",
    "sg:province":"Zuid-Holland",
    "wof:name":"Buro V Man & Inf Ir T Wierenga-Posthumus",
    "wof:placetype":"venue"
},
  "geometry": {"coordinates":[4.620415,51.927197],"type":"Point"}
}