{
  "type": "Feature",
  "properties": {
    "addr:full":"Zwiepsewg 78 Lochem Gelderland 7241 GX",
    "addr:housenumber":"78",
    "addr:postcode":"7241 gx",
    "addr:street":"Zwiepsewg;Gelderland",
    "iso:country":"NL",
    "sg:address":"Zwiepsewg 78",
    "sg:city":"Lochem",
    "sg:orig_category":"Fotoreportages",
    "sg:phone":"+31 573 255 375",
    "sg:postcode":"7241 GX",
    "sg:province":"Gelderland",
    "wof:name":"Antonie",
    "wof:placetype":"venue"
},
  "geometry": {"coordinates":[6.421696,52.155491],"type":"Point"}
}