{
  "type": "Feature",
  "properties": {
    "addr:full":"Vyfhoekstr 17 Huizen Noord-Holland 1271 PL",
    "addr:housenumber":"17",
    "addr:postcode":"1271 pl",
    "addr:street":"Vyfhoekstr",
    "iso:country":"NL",
    "sg:address":"Vyfhoekstr 17",
    "sg:city":"Huizen",
    "sg:orig_category":"Fietsen En Bromfietsen",
    "sg:phone":"+31 35 525 1315",
    "sg:postcode":"1271 PL",
    "sg:province":"Noord-Holland",
    "wof:name":"Visser Tweewielers",
    "wof:placetype":"venue"
},
  "geometry": {"coordinates":[5.239692,52.296677],"type":"Point"}
}