{
  "type": "Feature",
  "properties": {
    "iso:country":"NL",
    "sg:address":"Egelantierstraat 77",
    "sg:city":"'S Gravenhage",
    "sg:orig_category":"Goederenvervoer Over De Weg",
    "sg:phone":"+31 70 363 2378",
    "sg:postcode":"2565 XJ",
    "sg:province":"South Holland",
    "wof:name":"Transportbedrijf Vrolijk & Stoop Bv",
    "wof:placetype":"venue"
},
  "geometry": {"coordinates":[4.266219,52.076801],"type":"Point"}
}