{
  "type": "Feature",
  "properties": {
    "iso:country":"NL",
    "sg:address":"J J Viottastr 47",
    "sg:city":"Amsterdam",
    "sg:orig_category":"Onroerende Goederen",
    "sg:phone":"+31 20 675 1031",
    "sg:postcode":"1071 JP",
    "sg:province":"Noord-Holland",
    "wof:name":"Modalfa Bv",
    "wof:placetype":"venue"
},
  "geometry": {"coordinates":[4.870789,52.352516],"type":"Point"}
}