{
  "type": "Feature",
  "properties": {
    "addr:full":"De Gaffel 3 Lieshout Noord-Brabant 5737 JJ",
    "addr:housenumber":"3",
    "addr:postcode":"5737 jj",
    "addr:street":"De Gaffel",
    "iso:country":"NL",
    "sg:address":"De Gaffel 3",
    "sg:city":"Lieshout",
    "sg:orig_category":"Satellietontvangst- En Antenne-Installaties",
    "sg:phone":"+31 499 463 747",
    "sg:postcode":"5737 JJ",
    "sg:province":"Noord-Brabant",
    "wof:name":"Poulisse",
    "wof:placetype":"venue"
},
  "geometry": {"coordinates":[5.587889,51.516823],"type":"Point"}
}