{
  "type": "Feature",
  "properties": {
    "addr:full":"Langewyk 194 Dedemsvaart NL.08 7701 AK",
    "addr:housenumber":"194;nl.08",
    "addr:postcode":"7701 ak",
    "addr:street":"Langewyk",
    "iso:country":"NL",
    "sg:address":"Langewyk 194",
    "sg:city":"Dedemsvaart",
    "sg:classifiers":[
        {
            "category":"Travel",
            "subcategory":"Hotels & Motels",
            "type":"Entertainment"
        }
    ],
    "sg:phone":"+31 523 613 145",
    "sg:postcode":"7701 AK",
    "sg:province":"NL.08",
    "wof:name":"Roos, De",
    "wof:placetype":"venue"
},
  "geometry": {"coordinates":[6.457315,52.606258],"type":"Point"}
}