{
  "type": "Feature",
  "properties": {
    "iso:country":"NL",
    "sg:address":"Bachstr 49",
    "sg:city":"Sittard",
    "sg:orig_category":"Verenigingen En Stichtingen",
    "sg:phone":"+31 46 452 1930",
    "sg:postcode":"6137 RX",
    "sg:province":"North Rhine-Westphalia",
    "wof:name":"Circolo Sardo Su Naraghe",
    "wof:placetype":"venue"
},
  "geometry": {"coordinates":[5.889299,50.999165],"type":"Point"}
}