{
  "type": "Feature",
  "properties": {
    "addr:full":"Produktiewg 18 Zoeterwoude Zuid-Holland 2382 PB",
    "addr:housenumber":"18",
    "addr:postcode":"2382 pb",
    "addr:street":"Produktiewg",
    "iso:country":"NL",
    "sg:address":"Produktiewg 18",
    "sg:city":"Zoeterwoude",
    "sg:orig_category":"Boeken En Tijdschriften",
    "sg:phone":"+31 71 581 2090",
    "sg:postcode":"2382 PB",
    "sg:province":"Zuid-Holland",
    "sg:website":"http://www.infotrading.nl",
    "wof:name":"Infotrading",
    "wof:placetype":"venue"
},
  "geometry": {"coordinates":[4.517953,52.140156],"type":"Point"}
}