{
  "type": "Feature",
  "properties": {
    "addr:full":"Schiewg 91 Delft Zuid-Holland 2627 AT",
    "addr:housenumber":"91",
    "addr:postcode":"2627",
    "addr:street":"Schiewg",
    "iso:country":"NL",
    "sg:address":"Schiewg 91",
    "sg:city":"Delft",
    "sg:classifiers":[
        {
            "category":"Retail",
            "subcategory":"Auto Repair",
            "type":"Services"
        }
    ],
    "sg:phone":"+31 15 251 2870",
    "sg:postcode":"2627 AT",
    "sg:province":"Zuid-Holland",
    "sg:tags":[
        "garage"
    ],
    "sg:website":"http://www.vandertang.nl",
    "wof:name":"Tang Auto'S Bv, Van Der",
    "wof:placetype":"venue"
},
  "geometry": {"coordinates":[4.372422,51.98262],"type":"Point"}
}