{
  "type": "Feature",
  "properties": {
    "addr:full":"Kapelstr 46 Breda Noord-Brabant 4817 NZ",
    "addr:housenumber":"46",
    "addr:postcode":"4817 nz",
    "addr:street":"Kapelstr",
    "iso:country":"NL",
    "sg:address":"Kapelstr 46",
    "sg:city":"Breda",
    "sg:orig_category":"Verlichtingsartikelen - Groothandel",
    "sg:phone":"+31 76 571 1746",
    "sg:postcode":"4817 NZ",
    "sg:province":"Noord-Brabant",
    "wof:name":"Sf Bv",
    "wof:placetype":"venue"
},
  "geometry": {"coordinates":[-94.976479,42.181561],"type":"Point"}
}