{
  "type": "Feature",
  "properties": {
    "addr:full":"Lg Gouwe 24 Gouda Zuid-Holland 2801 LG",
    "addr:housenumber":"24",
    "addr:postcode":"2801 lg",
    "addr:street":"Lg Gouwe",
    "iso:country":"NL",
    "sg:address":"Lg Gouwe 24",
    "sg:city":"Gouda",
    "sg:orig_category":"Beeldende Kunstenaars",
    "sg:phone":"+31 182 519 840",
    "sg:postcode":"2801 LG",
    "sg:province":"Zuid-Holland",
    "wof:name":"Tempelman, A",
    "wof:placetype":"venue"
},
  "geometry": {"coordinates":[4.709518,52.010254],"type":"Point"}
}