{
  "type": "Feature",
  "properties": {
    "addr:full":"De Lairessestr 8 Amsterdam New York 1071 NZ",
    "addr:housenumber":"8;1071",
    "addr:street":"Nz",
    "iso:country":"NL",
    "sg:address":"De Lairessestr 8",
    "sg:city":"Amsterdam",
    "sg:orig_category":"Verenigingen En Stichtingen",
    "sg:phone":"+31 20 671 7654",
    "sg:postcode":"1071 NZ",
    "sg:province":"New York",
    "sg:website":"http://www.zendingsraad.nl",
    "wof:name":"Ned Zendingsraad",
    "wof:placetype":"venue"
},
  "geometry": {"coordinates":[-74.163521,42.945232],"type":"Point"}
}