{
  "type": "Feature",
  "properties": {
    "addr:full":"Haagdoornstr 74 Arnhem Gelderland 6841 AM",
    "addr:housenumber":"74",
    "addr:postcode":"6841",
    "addr:street":"Haagdoornstr",
    "iso:country":"NL",
    "sg:address":"Haagdoornstr 74",
    "sg:city":"Arnhem",
    "sg:orig_category":"Juweliers",
    "sg:phone":"+31 26 321 7501",
    "sg:postcode":"6841 AM",
    "sg:province":"Gelderland",
    "wof:name":"Weijman, J",
    "wof:placetype":"venue"
},
  "geometry": {"coordinates":[5.903334,51.96983],"type":"Point"}
}