{
  "type": "Feature",
  "properties": {
    "iso:country":"NL",
    "sg:address":"Hermelijnweide 14",
    "sg:city":"Veghel",
    "sg:orig_category":"Kappers",
    "sg:phone":"+31 413 344 338",
    "sg:postcode":"5467 KZ",
    "sg:province":"Noord-Brabant",
    "wof:name":"Erica Sprang",
    "wof:placetype":"venue"
},
  "geometry": {"coordinates":[5.5611329079,51.6235923767],"type":"Point"}
}