{
  "type": "Feature",
  "properties": {
    "addr:full":"Ertveldwg 12 S Hertogenbosch Noord-Brabant 5231 XB",
    "addr:housenumber":"12",
    "addr:postcode":"5231 xb",
    "addr:street":"Ertveldwg;S",
    "iso:country":"NL",
    "sg:address":"Ertveldwg 12",
    "sg:city":"S Hertogenbosch",
    "sg:orig_category":"Horeca-Inrichtingen En -Uitrustingen",
    "sg:phone":"+31 73 643 0474",
    "sg:postcode":"5231 XB",
    "sg:province":"Noord-Brabant",
    "wof:name":"Mierden, Van Der",
    "wof:placetype":"venue"
},
  "geometry": {"coordinates":[5.29819,51.705212],"type":"Point"}
}