{
  "type": "Feature",
  "properties": {
    "addr:full":"Venedie 13 Enkhuizen Noord-Holland 1601 HA",
    "addr:housenumber":"13",
    "addr:postcode":"1601 ha",
    "addr:street":"Venedie",
    "iso:country":"NL",
    "sg:address":"Venedie 13",
    "sg:city":"Enkhuizen",
    "sg:classifiers":[
        {
            "category":"Shopping",
            "subcategory":"Gifts & Souvenirs",
            "type":"Retail Goods"
        }
    ],
    "sg:phone":"+31 228 322 325",
    "sg:postcode":"1601 HA",
    "sg:province":"Noord-Holland",
    "sg:tags":[
        "geschenken"
    ],
    "wof:name":"Souvenirshop 'T Venedie",
    "wof:placetype":"venue"
},
  "geometry": {"coordinates":[5.290368,52.703033],"type":"Point"}
}