{
  "type": "Feature",
  "properties": {
    "iso:country":"NL",
    "sg:address":"Koekoekstraat 66",
    "sg:city":"Sprundel",
    "sg:orig_category":"Kappers",
    "sg:phone":"+31 165 382 714",
    "sg:postcode":"4714 AL",
    "sg:province":"North Brabant",
    "wof:name":"Kapsalon De Bruijn",
    "wof:placetype":"venue"
},
  "geometry": {"coordinates":[4.590113163,51.5402641296],"type":"Point"}
}