{
  "type": "Feature",
  "properties": {
    "iso:country":"NL",
    "sg:address":"Gasthuisstraat 38",
    "sg:city":"Gorinchem",
    "sg:classifiers":[
        {
            "category":"Shopping",
            "subcategory":"Clothing, Apparel, & Fashions",
            "type":"Retail Goods"
        }
    ],
    "sg:phone":"+31 183 631 765",
    "sg:postcode":"4201 JR",
    "sg:province":"Zuid-Holland",
    "sg:tags":[
        "ondergoed",
        "lingerie"
    ],
    "wof:name":"Krimpenfort Foundation Bv",
    "wof:placetype":"venue"
},
  "geometry": {"coordinates":[4.973578,51.830418],"type":"Point"}
}