{
  "type": "Feature",
  "properties": {
    "iso:country":"NL",
    "sg:address":"Den Uitvanck 9F",
    "sg:city":"Oirschot",
    "sg:orig_category":"Verpakkingsbedrijven",
    "sg:phone":"+31 499 577 527",
    "sg:postcode":"5688 XG",
    "sg:province":"North Brabant",
    "sg:website":"http://www.japak.nl",
    "wof:name":"Japak Packing & Mailing",
    "wof:placetype":"venue"
},
  "geometry": {"coordinates":[5.334781,51.501617],"type":"Point"}
}