{
  "type": "Feature",
  "properties": {
    "addr:full":"Schiestr 2 Den Helder Noord-Holland 1784 TP",
    "addr:housenumber":"2",
    "addr:postcode":"1784 tp",
    "addr:street":"Schiestr",
    "iso:country":"NL",
    "sg:address":"Schiestr 2",
    "sg:city":"Den Helder",
    "sg:orig_category":"Koeriersdiensten",
    "sg:phone":"+31 6 26492266",
    "sg:postcode":"1784 TP",
    "sg:province":"Noord-Holland",
    "wof:name":"R En W",
    "wof:placetype":"venue"
},
  "geometry": {"coordinates":[4.741276,52.946606],"type":"Point"}
}