{
  "type": "Feature",
  "properties": {
    "addr:full":"Buikslotermeerpln 162 Amsterdam Noord-Holland 1025 EZ",
    "addr:housenumber":"162",
    "addr:postcode":"1025 ez",
    "iso:country":"NL",
    "sg:address":"Buikslotermeerpln 162",
    "sg:city":"Amsterdam",
    "sg:orig_category":"Kinderkleding",
    "sg:phone":"+31 20 636 2631",
    "sg:postcode":"1025 EZ",
    "sg:province":"Noord-Holland",
    "wof:name":"Hilderink",
    "wof:placetype":"venue"
},
  "geometry": {"coordinates":[4.937173,52.398064],"type":"Point"}
}