{
  "type": "Feature",
  "properties": {
    "addr:full":"Lessingln 12 Utrecht Utrecht 3533 AW",
    "addr:housenumber":"12",
    "addr:postcode":"3533 aw",
    "addr:street":"Lessingln",
    "iso:country":"NL",
    "sg:address":"Lessingln 12",
    "sg:city":"Utrecht",
    "sg:orig_category":"Fotografie Reclame En Mode",
    "sg:phone":"+31 30 290 0290",
    "sg:postcode":"3533 AW",
    "sg:province":"Utrecht",
    "wof:name":"Bouwman Fotografie, Rene",
    "wof:placetype":"venue"
},
  "geometry": {"coordinates":[5.083958,52.091366],"type":"Point"}
}