{
  "type": "Feature",
  "properties": {
    "addr:full":"Bucaillestr 2A Voorburg South Holland 2273 CA",
    "addr:housenumber":"2a",
    "addr:postcode":"2273 ca",
    "addr:street":"Bucaillestr",
    "iso:country":"NL",
    "sg:address":"Bucaillestr 2A",
    "sg:city":"Voorburg",
    "sg:orig_category":"Fitnesscentra",
    "sg:phone":"+31 70 387 6587",
    "sg:postcode":"2273 CA",
    "sg:province":"South Holland",
    "sg:website":"http://www.exercise.nl",
    "wof:name":"Exercise Fitness- En Aerobic Center",
    "wof:placetype":"venue"
},
  "geometry": {"coordinates":[4.359336,52.076015],"type":"Point"}
}