{
  "type": "Feature",
  "properties": {
    "addr:full":"Het Roege Bos 26 Groningen Groningen 9745 DZ",
    "addr:housenumber":"26",
    "addr:postcode":"9745 dz",
    "addr:street":"Het Roege Bos",
    "iso:country":"NL",
    "sg:address":"Het Roege Bos 26",
    "sg:city":"Groningen",
    "sg:classifiers":[
        {
            "category":"Food & Beverages",
            "subcategory":"Fruits & Vegetables",
            "type":"Retail Goods"
        }
    ],
    "sg:phone":"+31 50 571 8055",
    "sg:postcode":"9745 DZ",
    "sg:province":"Groningen",
    "sg:tags":[
        "en",
        "groenten"
    ],
    "wof:name":"Tuin, D W Van Der",
    "wof:placetype":"venue"
},
  "geometry": {"coordinates":[6.517187,53.22274],"type":"Point"}
}