{
  "type": "Feature",
  "properties": {
    "addr:full":"T Ven 44 Duivendrecht Noord-Holland 1115 HB",
    "addr:housenumber":"44",
    "addr:postcode":"1115 hb",
    "addr:street":"T Ven",
    "iso:country":"NL",
    "sg:address":"T Ven 44",
    "sg:city":"Duivendrecht",
    "sg:orig_category":"Adviesbureaus",
    "sg:phone":"+31 20 695 9969",
    "sg:postcode":"1115 HB",
    "sg:province":"Noord-Holland",
    "wof:name":"Synergy & Foods",
    "wof:placetype":"venue"
},
  "geometry": {"coordinates":[4.941441,52.328907],"type":"Point"}
}