{
  "type": "Feature",
  "properties": {
    "addr:full":"J G Heuthorststraat 19 Doetinchem Gelderland 7009 CK",
    "addr:housenumber":"19",
    "addr:postcode":"7009 ck",
    "addr:street":"J G Heuthorststraat;Gelderland",
    "iso:country":"NL",
    "sg:address":"J G Heuthorststraat 19",
    "sg:city":"Doetinchem",
    "sg:orig_category":"Autokeuringen",
    "sg:phone":"+31 314 333 117",
    "sg:postcode":"7009 CK",
    "sg:province":"Gelderland",
    "wof:name":"G.H. Sevink'S Automobiel- En Motorenbedr. Bv",
    "wof:placetype":"venue"
},
  "geometry": {"coordinates":[6.290837,51.978214],"type":"Point"}
}