{
  "type": "Feature",
  "properties": {
    "iso:country":"NL",
    "sg:address":"L Dreef 8",
    "sg:city":"Vianen Zh",
    "sg:orig_category":"Adviesbureaus Bedrijfsorganisatie",
    "sg:phone":"+31 347 322 612",
    "sg:postcode":"4131 NH",
    "sg:province":"Utrecht",
    "wof:name":"Trigon Bv",
    "wof:placetype":"venue"
},
  "geometry": {"coordinates":[5.100703,51.991146],"type":"Point"}
}