{
  "type": "Feature",
  "properties": {
    "iso:country":"NL",
    "sg:address":"Nw Gouw 8",
    "sg:city":"Purmerend",
    "sg:orig_category":"Openbaar Vervoer",
    "sg:phone":"+31 299 456 911",
    "sg:postcode":"1442 LE",
    "sg:province":"Noord-Holland",
    "wof:name":"Connexxion",
    "wof:placetype":"venue"
},
  "geometry": {"coordinates":[4.9866108894,52.5199813843],"type":"Point"}
}