{
  "type": "Feature",
  "properties": {
    "addr:full":"Veenweg 39 Oldebroek Gelderland 8096 PL",
    "addr:housenumber":"39",
    "addr:postcode":"8096 pl",
    "addr:street":"Veenweg;Gelderland",
    "iso:country":"NL",
    "sg:address":"Veenweg 39",
    "sg:city":"Oldebroek",
    "sg:orig_category":"Vaste And Vloeibare Brandstoffen",
    "sg:phone":"+31 525 631 418",
    "sg:postcode":"8096 PL",
    "sg:province":"Gelderland",
    "wof:name":"H. Zandbergen Jr.",
    "wof:placetype":"venue"
},
  "geometry": {"coordinates":[5.900969,52.426559],"type":"Point"}
}