{
  "type": "Feature",
  "properties": {
    "iso:country":"NL",
    "sg:address":"Min Vd Brinkln 30 Afd Friesland",
    "sg:city":"Bergum",
    "sg:orig_category":"Verenigingen En Stichtingen",
    "sg:phone":"+31 511 469 815",
    "sg:postcode":"9251 JG",
    "sg:province":"Provincie Friesland",
    "wof:name":"Msvn Afd Friesland",
    "wof:placetype":"venue"
},
  "geometry": {"coordinates":[5.986921,53.19529],"type":"Point"}
}