{
  "type": "Feature",
  "properties": {
    "iso:country":"NL",
    "sg:address":"Lommerhof 11",
    "sg:city":"Heerhugowaard",
    "sg:orig_category":"Hypnotherapeuten",
    "sg:phone":"+31 72 571 8995",
    "sg:postcode":"1702 VT",
    "sg:province":"Noord-Holland",
    "wof:name":"Visser, Ineke",
    "wof:placetype":"venue"
},
  "geometry": {"coordinates":[4.842658,52.657269],"type":"Point"}
}