{
  "type": "Feature",
  "properties": {
    "iso:country":"NL",
    "sg:address":"Voltawg 14",
    "sg:city":"Delft",
    "sg:orig_category":"Kunststoffen- Verwerkende Industrie",
    "sg:phone":"+31 15 257 3569",
    "sg:postcode":"2627 BB",
    "sg:province":"South Holland",
    "sg:website":"http://www.mafa.nl",
    "wof:name":"Mafa Plastics Bv",
    "wof:placetype":"venue"
},
  "geometry": {"coordinates":[4.374155,51.983444],"type":"Point"}
}