{
  "type": "Feature",
  "properties": {
    "addr:full":"Keizershof 97 Alphen A/D Rijn South Holland 2402 DB",
    "addr:housenumber":"97",
    "addr:postcode":"2402 db",
    "addr:street":"Keizershof",
    "iso:country":"NL",
    "sg:address":"Keizershof 97",
    "sg:city":"Alphen A/D Rijn",
    "sg:orig_category":"Beautyfarms And Sauna'S",
    "sg:phone":"+31 172 437 746",
    "sg:postcode":"2402 DB",
    "sg:province":"South Holland",
    "wof:name":"Sun Beach",
    "wof:placetype":"venue"
},
  "geometry": {"coordinates":[4.67851,52.153549],"type":"Point"}
}