{
  "type": "Feature",
  "properties": {
    "iso:country":"NL",
    "sg:address":"W Buytewechstr 42",
    "sg:city":"Rotterdam",
    "sg:orig_category":"Artiesten/Gezelschappen",
    "sg:phone":"+31 10 276 3039",
    "sg:postcode":"3024 BN",
    "sg:province":"Zuid-Holland",
    "sg:website":"http://www.welcome.to/theatermaatwerk",
    "wof:name":"Theater Maatwerk",
    "wof:placetype":"venue"
},
  "geometry": {"coordinates":[4.460385,51.907223],"type":"Point"}
}