{
  "type": "Feature",
  "properties": {
    "addr:full":"J Dykstraln 4 Groningen Groningen 9744 DD",
    "addr:housenumber":"4",
    "addr:postcode":"9744 dd",
    "iso:country":"NL",
    "sg:address":"J Dykstraln 4",
    "sg:city":"Groningen",
    "sg:orig_category":"Koeriersdiensten",
    "sg:phone":"+31 50 559 0282",
    "sg:postcode":"9744 DD",
    "sg:province":"Groningen",
    "wof:name":"Laan, Van Der",
    "wof:placetype":"venue"
},
  "geometry": {"coordinates":[6.514486,53.20425],"type":"Point"}
}