{
  "type": "Feature",
  "properties": {
    "addr:full":"Varsseveldseweg 18 Lichtenvoorde Gelderland 7131 BJ",
    "addr:housenumber":"18",
    "addr:postcode":"7131 bj",
    "addr:street":"Varsseveldseweg;Gelderland",
    "iso:country":"NL",
    "sg:address":"Varsseveldseweg 18",
    "sg:city":"Lichtenvoorde",
    "sg:orig_category":"Schilderwerk",
    "sg:phone":"+31 544 371 891",
    "sg:postcode":"7131 BJ",
    "sg:province":"Gelderland",
    "wof:name":"Frans Reinders Schildersbedr En Doe Het Zelfwinkel",
    "wof:placetype":"venue"
},
  "geometry": {"coordinates":[6.562167,51.987499],"type":"Point"}
}