{
  "type": "Feature",
  "properties": {
    "addr:full":"Madelinushof 5 Wijk Bij Duurstede Utrecht 3962 DN",
    "addr:housenumber":"5",
    "addr:postcode":"3962 dn",
    "addr:street":"Madelinushof",
    "iso:country":"NL",
    "sg:address":"Madelinushof 5",
    "sg:city":"Wijk Bij Duurstede",
    "sg:classifiers":[
        {
            "category":"Communications",
            "subcategory":"Television Station",
            "type":"Services"
        }
    ],
    "sg:phone":"+31 343 575 999",
    "sg:postcode":"3962 DN",
    "sg:province":"Utrecht",
    "sg:tags":[
        "video",
        "audio",
        "verhuur"
    ],
    "wof:name":"Videotheek Hollywood",
    "wof:placetype":"venue"
},
  "geometry": {"coordinates":[5.340908,51.979195],"type":"Point"}
}