{
  "type": "Feature",
  "properties": {
    "iso:country":"NL",
    "sg:address":"Donkere Spaarne 52",
    "sg:city":"Haarlem",
    "sg:orig_category":"Zalenverhuur",
    "sg:phone":"+31 23 532 5354",
    "sg:postcode":"2011 JH",
    "sg:province":"North Holland",
    "wof:name":"Alfa Events & Spaarnehuys",
    "wof:placetype":"venue"
},
  "geometry": {"coordinates":[4.641837,52.380623],"type":"Point"}
}