{
  "type": "Feature",
  "properties": {
    "addr:full":"Galjoenwg 96 Harlingen Provincie Friesland 8862 XV",
    "addr:housenumber":"96",
    "addr:postcode":"8862 xv",
    "addr:street":"Galjoenwg;Provincie Friesland",
    "iso:country":"NL",
    "sg:address":"Galjoenwg 96",
    "sg:city":"Harlingen",
    "sg:orig_category":"Meubelstoffering",
    "sg:phone":"+31 517 414 144",
    "sg:postcode":"8862 XV",
    "sg:province":"Provincie Friesland",
    "wof:name":"Beukertje, Het",
    "wof:placetype":"venue"
},
  "geometry": {"coordinates":[5.444778,53.165432],"type":"Point"}
}