{
  "type": "Feature",
  "properties": {
    "iso:country":"NL",
    "sg:address":"Berkenln 18",
    "sg:city":"Warnsveld",
    "sg:orig_category":"Keukens",
    "sg:phone":"+31 575 525 749",
    "sg:postcode":"7231 EP",
    "sg:province":"Gelderland",
    "wof:name":"Smale, Anton",
    "wof:placetype":"venue"
},
  "geometry": {"coordinates":[6.231661,52.137016],"type":"Point"}
}