{
  "type": "Feature",
  "properties": {
    "addr:full":"Lindenln 19 Dronten NL. 8253 AB",
    "addr:housenumber":"19",
    "addr:postcode":"8253 ab",
    "addr:street":"Lindenln;Nl.",
    "iso:country":"NL",
    "sg:address":"Lindenln 19",
    "sg:city":"Dronten",
    "sg:orig_category":"Projectontwikkeling",
    "sg:phone":"+31 321 382 985",
    "sg:postcode":"8253 AB",
    "sg:province":"NL.",
    "wof:name":"Geloven, Van",
    "wof:placetype":"venue"
},
  "geometry": {"coordinates":[5.765546,52.577721],"type":"Point"}
}