{
  "type": "Feature",
  "properties": {
    "addr:full":"Hoogravenseweg 136 Utrecht Utrecht 3523 TP",
    "addr:housenumber":"136",
    "addr:postcode":"3523 tp",
    "addr:street":"Hoogravenseweg",
    "iso:country":"NL",
    "sg:address":"Hoogravenseweg 136",
    "sg:city":"Utrecht",
    "sg:orig_category":"Loodgieterswerk, Verwarming And Sanitaire Installaties",
    "sg:phone":"+31 30 289 5327",
    "sg:postcode":"3523 TP",
    "sg:province":"Utrecht",
    "wof:name":"John Van Renswou Bv",
    "wof:placetype":"venue"
},
  "geometry": {"coordinates":[5.120852,52.072807],"type":"Point"}
}