{
  "type": "Feature",
  "properties": {
    "addr:full":"Tuindorpstraat 48 Hengelo Ov Overijssel 7551 AV",
    "addr:housenumber":"48",
    "addr:postcode":"7551 av",
    "addr:street":"Tuindorpstraat;Ov",
    "iso:country":"NL",
    "sg:address":"Tuindorpstraat 48",
    "sg:city":"Hengelo Ov",
    "sg:orig_category":"Public Relationbureaus",
    "sg:phone":"+31 74 245 5252",
    "sg:postcode":"7551 AV",
    "sg:province":"Overijssel",
    "wof:name":"Mediasales Nederland Bv",
    "wof:placetype":"venue"
},
  "geometry": {"coordinates":[6.783401,52.264317],"type":"Point"}
}