{
  "type": "Feature",
  "properties": {
    "addr:full":"Kaneelstraat 17 Cuijk North Brabant 5431 DV",
    "addr:housenumber":"17",
    "addr:postcode":"5431 dv",
    "addr:street":"Kaneelstraat",
    "iso:country":"NL",
    "sg:address":"Kaneelstraat 17",
    "sg:city":"Cuijk",
    "sg:classifiers":[
        {
            "category":"Education",
            "subcategory":"Preschool",
            "type":"Public Place"
        }
    ],
    "sg:phone":"+31 485 321 146",
    "sg:postcode":"5431 DV",
    "sg:province":"North Brabant",
    "sg:tags":[
        "kleuteronderwijs",
        "basis-"
    ],
    "wof:name":"Hans En Grietje",
    "wof:placetype":"venue"
},
  "geometry": {"coordinates":[5.88067,51.727505],"type":"Point"}
}