{
  "type": "Feature",
  "properties": {
    "iso:country":"NL",
    "sg:address":"Industriestraat 36",
    "sg:city":"Klazienaveen",
    "sg:orig_category":"Metaalwerken",
    "sg:phone":"+31 591 393 544",
    "sg:postcode":"7891 GV",
    "sg:province":"Drenthe",
    "wof:name":"Bosman & De Hoop Afbouw Bv",
    "wof:placetype":"venue"
},
  "geometry": {"coordinates":[7.015587,52.721897],"type":"Point"}
}