{
  "type": "Feature",
  "properties": {
    "iso:country":"NL",
    "sg:address":"Westerbaan 2 Westerhof",
    "sg:city":"Vlissingen",
    "sg:orig_category":"Tehuizen",
    "sg:phone":"+31 118 471 517",
    "sg:postcode":"4386 CR",
    "sg:province":"Zeeland",
    "wof:name":"Philadelphia, Sticht",
    "wof:placetype":"venue"
},
  "geometry": {"coordinates":[3.57262,51.442684],"type":"Point"}
}