{
  "type": "Feature",
  "properties": {
    "addr:full":"Onderdendamsterwg 2 Warffum Groningen 9989 TG",
    "addr:housenumber":"2",
    "addr:postcode":"9989 tg",
    "addr:street":"Onderdendamsterwg",
    "iso:country":"NL",
    "sg:address":"Onderdendamsterwg 2",
    "sg:city":"Warffum",
    "sg:orig_category":"Adviesbureaus Bedrijfsorganisatie",
    "sg:phone":"+31 595 426 111",
    "sg:postcode":"9989 TG",
    "sg:province":"Groningen",
    "wof:name":"Deen, Van Der",
    "wof:placetype":"venue"
},
  "geometry": {"coordinates":[6.560621,53.385113],"type":"Point"}
}