{
  "type": "Feature",
  "properties": {
    "addr:full":"Firmawei 11 Joure Friesland 8501 XL",
    "addr:housenumber":"11",
    "addr:postcode":"8501 xl",
    "addr:street":"Firmawei",
    "iso:country":"NL",
    "sg:address":"Firmawei 11",
    "sg:city":"Joure",
    "sg:orig_category":"Voegwerken",
    "sg:phone":"+31 513 411 609",
    "sg:postcode":"8501 XL",
    "sg:province":"Friesland",
    "wof:name":"Svs",
    "wof:placetype":"venue"
},
  "geometry": {"coordinates":[5.822935,52.962421],"type":"Point"}
}