{
  "type": "Feature",
  "properties": {
    "addr:full":"Essenerweg 47 Kootwijkerbroek Gelderland 3774 CA",
    "addr:housenumber":"47",
    "addr:postcode":"3774 ca",
    "addr:street":"Essenerweg;Gelderland",
    "iso:country":"NL",
    "sg:address":"Essenerweg 47",
    "sg:city":"Kootwijkerbroek",
    "sg:orig_category":"Autokeuringen",
    "sg:phone":"+31 342 443 703",
    "sg:postcode":"3774 CA",
    "sg:province":"Gelderland",
    "wof:name":"Plaatwerkerij W. Van Den Brink",
    "wof:placetype":"venue"
},
  "geometry": {"coordinates":[5.666676,52.147533],"type":"Point"}
}