{
  "type": "Feature",
  "properties": {
    "addr:full":"Dalpln 2 T/M 8 Soest Utrecht 3762 BP",
    "addr:housenumber":"2 t / m 8",
    "addr:postcode":"3762 bp",
    "addr:street":"Dalpln",
    "iso:country":"NL",
    "sg:address":"Dalpln 2 T/M 8",
    "sg:city":"Soest",
    "sg:orig_category":"Bejaarden - Verzorgingstehuizen",
    "sg:phone":"+31 35 609 9666",
    "sg:postcode":"3762 BP",
    "sg:province":"Utrecht",
    "wof:name":"Molenschot",
    "wof:placetype":"venue"
},
  "geometry": {"coordinates":[5.300385,52.184044],"type":"Point"}
}