{
  "type": "Feature",
  "properties": {
    "addr:full":"Pr Clausstr 43 Hoensbroek Limburg 6433 JN",
    "addr:housenumber":"43",
    "addr:postcode":"6433 jn",
    "addr:street":"Hoensbroek Limburg",
    "iso:country":"NL",
    "sg:address":"Pr Clausstr 43",
    "sg:city":"Hoensbroek",
    "sg:orig_category":"Glazenwasserijen",
    "sg:phone":"+31 45 522 2377",
    "sg:postcode":"6433 JN",
    "sg:province":"Limburg",
    "wof:name":"Broek, Glazenwasserij - Schoonmaakbedrijf Van Den",
    "wof:placetype":"venue"
},
  "geometry": {"coordinates":[5.931404,50.906811],"type":"Point"}
}