{
  "type": "Feature",
  "properties": {
    "addr:full":"Dirk Hoogenraadstraat 212 Scheveningen Zuid-Holland 2586 TR",
    "addr:housenumber":"212",
    "addr:postcode":"2586 tr",
    "addr:street":"Dirk Hoogenraadstraat",
    "iso:country":"NL",
    "sg:address":"Dirk Hoogenraadstraat 212",
    "sg:city":"Scheveningen",
    "sg:classifiers":[
        {
            "category":"Travel",
            "subcategory":"Hotels & Motels",
            "type":"Entertainment"
        }
    ],
    "sg:phone":"+31 70 355 0884",
    "sg:postcode":"2586 TR",
    "sg:province":"Zuid-Holland",
    "wof:name":"Hotel Pension Meerbeek",
    "wof:placetype":"venue"
},
  "geometry": {"coordinates":[4.282348,52.111168],"type":"Point"}
}