{
  "type": "Feature",
  "properties": {
    "addr:full":"Romp 1 Middelburg Zeeland 4336 JL",
    "addr:housenumber":"1",
    "addr:postcode":"4336 jl",
    "addr:street":"Romp",
    "iso:country":"NL",
    "sg:address":"Romp 1",
    "sg:city":"Middelburg",
    "sg:orig_category":"Parketvloeren",
    "sg:phone":"+31 118 615 257",
    "sg:postcode":"4336 JL",
    "sg:province":"Zeeland",
    "wof:name":"Emelke, Vloerenlegservice",
    "wof:placetype":"venue"
},
  "geometry": {"coordinates":[3.618891,51.479076],"type":"Point"}
}