{
  "type": "Feature",
  "properties": {
    "iso:country":"NL",
    "sg:address":"De Rede 25",
    "sg:city":"Dronten",
    "sg:orig_category":"Drogisterijen",
    "sg:phone":"+31 321 318 698",
    "sg:postcode":"8251 ER",
    "sg:province":"Flevoland",
    "wof:name":"Kruidvat",
    "wof:placetype":"venue"
},
  "geometry": {"coordinates":[5.716265,52.524345],"type":"Point"}
}