{
  "type": "Feature",
  "properties": {
    "addr:full":"Molenwg 77 Harskamp Gelderland 6732 BJ",
    "addr:housenumber":"77",
    "addr:postcode":"6732 bj",
    "addr:street":"Molenwg;Gelderland",
    "iso:country":"NL",
    "sg:address":"Molenwg 77",
    "sg:city":"Harskamp",
    "sg:orig_category":"Metaalbewerking",
    "sg:phone":"+31 318 457 732",
    "sg:postcode":"6732 BJ",
    "sg:province":"Gelderland",
    "wof:name":"Alers Vof",
    "wof:placetype":"venue"
},
  "geometry": {"coordinates":[5.75176,52.125385],"type":"Point"}
}