{
  "type": "Feature",
  "properties": {
    "addr:full":"Van Heemskerckstraat 23 Amsterdam North Holland 1013 NV",
    "addr:housenumber":"23",
    "addr:postcode":"1013 nv",
    "addr:street":"Van Heemskerckstraat",
    "iso:country":"NL",
    "sg:address":"Van Heemskerckstraat 23",
    "sg:city":"Amsterdam",
    "sg:orig_category":"Verhuur Catering-, Feest- En Evenementbenodigdheden",
    "sg:phone":"+31 20 622 8248",
    "sg:postcode":"1013 NV",
    "sg:province":"North Holland",
    "wof:name":"F.D.C. Metz",
    "wof:placetype":"venue"
},
  "geometry": {"coordinates":[4.886208,52.389038],"type":"Point"}
}