{
  "type": "Feature",
  "properties": {
    "addr:full":"Sleeuwijksedk 21A Werkendam Noord-Brabant 4251 XB",
    "addr:housenumber":"21a",
    "addr:postcode":"4251 xb",
    "addr:street":"Sleeuwijksedk",
    "iso:country":"NL",
    "sg:address":"Sleeuwijksedk 21A",
    "sg:city":"Werkendam",
    "sg:orig_category":"Scheepswerven",
    "sg:phone":"+31 183 501 420",
    "sg:postcode":"4251 XB",
    "sg:province":"Noord-Brabant",
    "wof:name":"Jooren Bv, Gebr",
    "wof:placetype":"venue"
},
  "geometry": {"coordinates":[4.904123,51.81834],"type":"Point"}
}