{
  "type": "Feature",
  "properties": {
    "addr:full":"Confuciusplein 3 Amsterdam Noord-Holland 1064 LG",
    "addr:housenumber":"3",
    "addr:postcode":"1064 lg",
    "addr:street":"Confuciusplein",
    "iso:country":"NL",
    "sg:address":"Confuciusplein 3",
    "sg:city":"Amsterdam",
    "sg:orig_category":"Kappers",
    "sg:phone":"+31 20 613 2531",
    "sg:postcode":"1064 LG",
    "sg:province":"Noord-Holland",
    "wof:name":"Marman Coiffures",
    "wof:placetype":"venue"
},
  "geometry": {"coordinates":[4.81226,52.373768],"type":"Point"}
}