{
  "type": "Feature",
  "properties": {
    "addr:full":"Reidkampen 1 Zuidhorn Groningen 9801 JM",
    "addr:housenumber":"1",
    "addr:postcode":"9801 jm",
    "addr:street":"Reidkampen",
    "iso:country":"NL",
    "sg:address":"Reidkampen 1",
    "sg:city":"Zuidhorn",
    "sg:classifiers":[
        {
            "category":"Professional",
            "subcategory":"Accounting & Tax Preparation",
            "type":"Services"
        }
    ],
    "sg:phone":"+31 594 504 809",
    "sg:postcode":"9801 JM",
    "sg:province":"Groningen",
    "sg:tags":[
        "accountant",
        "en",
        "-kantoren",
        "register-"
    ],
    "wof:name":"Jonker Bv, P J",
    "wof:placetype":"venue"
},
  "geometry": {"coordinates":[6.397256,53.246891],"type":"Point"}
}