{
  "type": "Feature",
  "properties": {
    "iso:country":"NL",
    "sg:address":"Nijverheidsweg 2",
    "sg:city":"Mijdrecht",
    "sg:orig_category":"Metaalwerken",
    "sg:phone":"+31 297 256 007",
    "sg:postcode":"3641 RR",
    "sg:province":"Utrecht",
    "wof:name":"F En C Zonweringen",
    "wof:placetype":"venue"
},
  "geometry": {"coordinates":[4.871335,52.206108],"type":"Point"}
}