{
  "type": "Feature",
  "properties": {
    "addr:full":"Nieuwe Hoogstraat 9A Amsterdam North Holland 1011 HC",
    "addr:housenumber":"9a",
    "addr:postcode":"1011 hc",
    "addr:street":"Nieuwe Hoogstraat",
    "iso:country":"NL",
    "sg:address":"Nieuwe Hoogstraat 9A",
    "sg:city":"Amsterdam",
    "sg:orig_category":"Schoenen",
    "sg:phone":"+31 20 622 8100",
    "sg:postcode":"1011 HC",
    "sg:province":"North Holland",
    "wof:name":"T Klompenhuisje",
    "wof:placetype":"venue"
},
  "geometry": {"coordinates":[4.899505,52.370934],"type":"Point"}
}