{
  "type": "Feature",
  "properties": {
    "iso:country":"NL",
    "sg:address":"Nieuwe Hoogstraat 9A",
    "sg:city":"Amsterdam",
    "sg:orig_category":"Schoenen",
    "sg:phone":"+31 20 622 8100",
    "sg:postcode":"1011 HC",
    "sg:province":"North Holland",
    "wof:name":"T Klompenhuisje",
    "wof:placetype":"venue"
},
  "geometry": {"coordinates":[4.899505,52.370934],"type":"Point"}
}