{
  "type": "Feature",
  "properties": {
    "addr:full":"Burgemeester Haitsmalaan 7 Nijeveen Drenthe 7948 AE",
    "addr:housenumber":"7",
    "addr:postcode":"7948 ae",
    "addr:street":"Burgemeester Haitsmalaan",
    "iso:country":"NL",
    "sg:address":"Burgemeester Haitsmalaan 7",
    "sg:city":"Nijeveen",
    "sg:classifiers":[
        {
            "category":"Education",
            "subcategory":"Preschool",
            "type":"Public Place"
        }
    ],
    "sg:phone":"+31 522 491 469",
    "sg:postcode":"7948 AE",
    "sg:province":"Drenthe",
    "sg:tags":[
        "kleuteronderwijs",
        "basis-"
    ],
    "wof:name":"Basisschool De Wel",
    "wof:placetype":"venue"
},
  "geometry": {"coordinates":[6.166513,52.729568],"type":"Point"}
}