{
  "type": "Feature",
  "properties": {
    "iso:country":"NL",
    "sg:address":"Diependaalselaan 268",
    "sg:city":"Hilversum",
    "sg:orig_category":"Loodgieterswerk, Verwarming And Sanitaire Installaties",
    "sg:phone":"+31 35 623 2237",
    "sg:postcode":"1215 KH",
    "sg:province":"Noord-Holland",
    "wof:name":"L.J. Koopmans",
    "wof:placetype":"venue"
},
  "geometry": {"coordinates":[5.162578,52.211479],"type":"Point"}
}