{
  "type": "Feature",
  "properties": {
    "iso:country":"NL",
    "sg:address":"Appensewg 24",
    "sg:city":"Voorst Gem Voorst",
    "sg:orig_category":"Adviesbureaus Bedrijfsorganisatie",
    "sg:phone":"+31 6 22244903",
    "sg:postcode":"7383 BB",
    "sg:province":"Gelderland",
    "sg:website":"http://www.taskventures.com",
    "wof:name":"Weijers, Willem",
    "wof:placetype":"venue"
},
  "geometry": {"coordinates":[6.129003,52.181835],"type":"Point"}
}