{
  "type": "Feature",
  "properties": {
    "addr:full":"Laag Boskoop 19 Boskoop Zuid-Holland 2771 GV",
    "addr:housenumber":"19",
    "addr:postcode":"2771 gv",
    "addr:street":"Laag Boskoop",
    "iso:country":"NL",
    "sg:address":"Laag Boskoop 19",
    "sg:city":"Boskoop",
    "sg:orig_category":"Bloemen And Planten Gh",
    "sg:phone":"+31 172 213 344",
    "sg:postcode":"2771 GV",
    "sg:province":"Zuid-Holland",
    "wof:name":"Rosbergen & Grootendorst Vof",
    "wof:placetype":"venue"
},
  "geometry": {"coordinates":[4.657257,52.082928],"type":"Point"}
}