{
  "type": "Feature",
  "properties": {
    "addr:full":"Amsterdamsestraatweg 284 Utrecht Utrecht 3551 CS",
    "addr:housenumber":"284",
    "addr:postcode":"3551 cs",
    "addr:street":"Amsterdamsestraatweg",
    "iso:country":"NL",
    "sg:address":"Amsterdamsestraatweg 284",
    "sg:city":"Utrecht",
    "sg:orig_category":"Meubelzaken, Woning- And Keukeninrichting",
    "sg:phone":"+31 30 243 6666",
    "sg:postcode":"3551 CS",
    "sg:province":"Utrecht",
    "wof:name":"De Waterbeddenconcurrent",
    "wof:placetype":"venue"
},
  "geometry": {"coordinates":[5.099237,52.10104],"type":"Point"}
}