{
  "type": "Feature",
  "properties": {
    "addr:full":"Grotestr 155 Almelo Overijssel 7607 CJ",
    "addr:housenumber":"155",
    "addr:postcode":"7607 cj",
    "iso:country":"NL",
    "sg:address":"Grotestr 155",
    "sg:city":"Almelo",
    "sg:classifiers":[
        {
            "category":"Shopping",
            "subcategory":"Adult",
            "type":"Retail Goods"
        }
    ],
    "sg:phone":"+31 546 817 160",
    "sg:postcode":"7607 CJ",
    "sg:province":"Overijssel",
    "sg:tags":[
        "lingerie",
        "en",
        "tricotage"
    ],
    "wof:name":"Livera",
    "wof:placetype":"venue"
},
  "geometry": {"coordinates":[6.665794,52.353523],"type":"Point"}
}