{
  "type": "Feature",
  "properties": {
    "iso:country":"NL",
    "sg:address":"Parkweg 127",
    "sg:city":"Ede Gld",
    "sg:orig_category":"Levensmiddelen - Fabrieken En Groothandel",
    "sg:phone":"+31 318 656 777",
    "sg:postcode":"6717 HR",
    "sg:province":"Gelderland",
    "wof:name":"Griekse Partner",
    "wof:placetype":"venue"
},
  "geometry": {"coordinates":[5.66373,52.027176],"type":"Point"}
}