{
  "type": "Feature",
  "properties": {
    "iso:country":"NL",
    "sg:address":"Industriestraat 123",
    "sg:city":"Hengelo Ov",
    "sg:orig_category":"Wapens And Munitie",
    "sg:phone":"+31 74 243 3788",
    "sg:postcode":"7553 CM",
    "sg:province":"Overijssel",
    "wof:name":"Murec",
    "wof:placetype":"venue"
},
  "geometry": {"coordinates":[6.7834968567,52.2551231384],"type":"Point"}
}