{
  "type": "Feature",
  "properties": {
    "addr:full":"Glashorst 94 Scherpenzeel Gld Gelderland 3925 BV",
    "addr:housenumber":"94",
    "addr:postcode":"3925 bv",
    "addr:street":"Glashorst;Gld Gelderland",
    "iso:country":"NL",
    "sg:address":"Glashorst 94",
    "sg:city":"Scherpenzeel Gld",
    "sg:orig_category":"Binnenhuisarchitecten",
    "sg:phone":"+31 33 277 1714",
    "sg:postcode":"3925 BV",
    "sg:province":"Gelderland",
    "wof:name":"Bv Ontwerp- Reclame- En Adviesbureau Wsb",
    "wof:placetype":"venue"
},
  "geometry": {"coordinates":[5.474199,52.081917],"type":"Point"}
}