{
  "type": "Feature",
  "properties": {
    "iso:country":"NL",
    "sg:address":"Past C M V Everdingenstr 13",
    "sg:city":"Rietmolen",
    "sg:orig_category":"Loodgieterswerk, Verwarming And Sanitaire Installaties",
    "sg:phone":"+31 545 221 636",
    "sg:postcode":"7165 AH",
    "sg:province":"Gelderland",
    "wof:name":"Firma H.G. Wildenborg En Zoon",
    "wof:placetype":"venue"
},
  "geometry": {"coordinates":[6.662935,52.141399],"type":"Point"}
}