{
  "type": "Feature",
  "properties": {
    "addr:full":"Kerkstraat 304 Brunssum Limburg 6441 BM",
    "addr:housenumber":"304",
    "addr:postcode":"6441 bm",
    "addr:street":"Kerkstraat",
    "iso:country":"NL",
    "sg:address":"Kerkstraat 304",
    "sg:city":"Brunssum",
    "sg:orig_category":"Verlichting And Huishoudartikelen",
    "sg:phone":"+31 45 525 8485",
    "sg:postcode":"6441 BM",
    "sg:province":"Limburg",
    "wof:name":"Spectra Hoevenaars",
    "wof:placetype":"venue"
},
  "geometry": {"coordinates":[5.972543,50.94833],"type":"Point"}
}