{
  "type": "Feature",
  "properties": {
    "iso:country":"NL",
    "sg:address":"Tadamasingel 51",
    "sg:city":"Zutphen",
    "sg:orig_category":"Werving And Selectie Van Vast Personeel",
    "sg:phone":"+31 575 545 428",
    "sg:postcode":"7201 EL",
    "sg:province":"Gelderland",
    "wof:name":"Diade",
    "wof:placetype":"venue"
},
  "geometry": {"coordinates":[6.200428009,52.1375007629],"type":"Point"}
}