{
  "type": "Feature",
  "properties": {
    "addr:full":"Koningsbergerstr 248 Amsterdam North Holland 1063 AK",
    "addr:housenumber":"248",
    "addr:postcode":"1063 ak",
    "iso:country":"NL",
    "sg:address":"Koningsbergerstr 248",
    "sg:city":"Amsterdam",
    "sg:orig_category":"Accountants - Administratie- Consulenten En -Kantoren",
    "sg:phone":"+31 6 53751408",
    "sg:postcode":"1063 AK",
    "sg:province":"North Holland",
    "wof:name":"Witte, B",
    "wof:placetype":"venue"
},
  "geometry": {"coordinates":[4.837961,52.384075],"type":"Point"}
}