{
  "type": "Feature",
  "properties": {
    "addr:full":"Marktstr 4 Enschede NL.08 7511 GD",
    "addr:housenumber":"4",
    "addr:postcode":"7511 gd",
    "addr:street":"Marktstr",
    "iso:country":"NL",
    "sg:address":"Marktstr 4",
    "sg:city":"Enschede",
    "sg:orig_category":"Piano'S",
    "sg:phone":"+31 53 431 5862",
    "sg:postcode":"7511 GD",
    "sg:province":"NL.08",
    "wof:name":"Schumer Bv, J P",
    "wof:placetype":"venue"
},
  "geometry": {"coordinates":[6.89477,52.221035],"type":"Point"}
}