{
  "type": "Feature",
  "properties": {
    "iso:country":"NL",
    "sg:address":"Vanillestraat 25",
    "sg:city":"Almere",
    "sg:classifiers":[
        {
            "category":"Fast Food",
            "type":"Food & Drink"
        }
    ],
    "sg:phone":"+31 36 530 0155",
    "sg:postcode":"1314 KD",
    "sg:province":"Flevoland",
    "sg:tags":[
        "afhaal",
        "restaurant"
    ],
    "wof:name":"Cafetaria'T Bikkertje",
    "wof:placetype":"venue"
},
  "geometry": {"coordinates":[5.210386,52.379433],"type":"Point"}
}