{
  "type": "Feature",
  "properties": {
    "iso:country":"NL",
    "sg:address":"Verspronckweg 203",
    "sg:city":"Haarlem",
    "sg:orig_category":"Marktonderzoekbureaus",
    "sg:phone":"+31 23 527 1652",
    "sg:postcode":"2023 BG",
    "sg:province":"Noord-Holland",
    "wof:name":"Velu Management Consultancy",
    "wof:placetype":"venue"
},
  "geometry": {"coordinates":[-82.312515,33.415298],"type":"Point"}
}