{
  "type": "Feature",
  "properties": {
    "iso:country":"NL",
    "sg:address":"Voorstraat 12",
    "sg:city":"Franeker",
    "sg:orig_category":"Boekhandels",
    "sg:phone":"+31 517 392 164",
    "sg:postcode":"8801 LC",
    "sg:province":"Provincie Friesland",
    "wof:name":"Firma Haitsma",
    "wof:placetype":"venue"
},
  "geometry": {"coordinates":[5.542807,53.186722],"type":"Point"}
}