{
  "type": "Feature",
  "properties": {
    "addr:full":"Transvaalstr 30A Amsterdam Noord-Holland 1092 HL",
    "addr:housenumber":"30a",
    "addr:postcode":"1092 hl",
    "addr:street":"Transvaalstr",
    "iso:country":"NL",
    "sg:address":"Transvaalstr 30A",
    "sg:city":"Amsterdam",
    "sg:orig_category":"Adviesbureaus",
    "sg:phone":"+31 20 463 1142",
    "sg:postcode":"1092 HL",
    "sg:province":"Noord-Holland",
    "wof:name":"B Organized",
    "wof:placetype":"venue"
},
  "geometry": {"coordinates":[4.926363,52.355461],"type":"Point"}
}