{
  "type": "Feature",
  "properties": {
    "iso:country":"NL",
    "sg:address":"Grachterstraat 56",
    "sg:city":"Kerkrade",
    "sg:classifiers":[
        {
            "category":"Education",
            "subcategory":"Preschool",
            "type":"Public Place"
        }
    ],
    "sg:phone":"+31 45 541 3053",
    "sg:postcode":"6465 AN",
    "sg:province":"Limburg",
    "sg:tags":[
        "kleuteronderwijs",
        "basis-"
    ],
    "wof:name":"Basisschool De Gracht",
    "wof:placetype":"venue"
},
  "geometry": {"coordinates":[6.027895,50.851711],"type":"Point"}
}