{
  "type": "Feature",
  "properties": {
    "addr:full":"Schilbergstr 11 Tilburg Noord-Brabant 5035 HA",
    "addr:housenumber":"11",
    "addr:postcode":"5035 ha",
    "addr:street":"Schilbergstr",
    "iso:country":"NL",
    "sg:address":"Schilbergstr 11",
    "sg:city":"Tilburg",
    "sg:orig_category":"Metselwerken",
    "sg:phone":"+31 13 542 4638",
    "sg:postcode":"5035 HA",
    "sg:province":"Noord-Brabant",
    "wof:name":"Actief",
    "wof:placetype":"venue"
},
  "geometry": {"coordinates":[4.979561,51.582367],"type":"Point"}
}