{
  "type": "Feature",
  "properties": {
    "addr:full":"Taandwstr 60 Amsterdam Noord-Holland 1013 BW",
    "addr:housenumber":"60",
    "addr:postcode":"1013 bw",
    "addr:street":"Taandwstr",
    "iso:country":"NL",
    "sg:address":"Taandwstr 60",
    "sg:city":"Amsterdam",
    "sg:orig_category":"Beeldende Kunstenaars",
    "sg:phone":"+31 20 625 7573",
    "sg:postcode":"1013 BW",
    "sg:province":"Noord-Holland",
    "wof:name":"Rood",
    "wof:placetype":"venue"
},
  "geometry": {"coordinates":[4.888748,52.387627],"type":"Point"}
}