{
  "type": "Feature",
  "properties": {
    "addr:full":"Hurksestr 36C Eindhoven North Brabant 5652 AL",
    "addr:housenumber":"36c",
    "addr:postcode":"5652 al",
    "addr:street":"Hurksestr",
    "iso:country":"NL",
    "sg:address":"Hurksestr 36C",
    "sg:city":"Eindhoven",
    "sg:orig_category":"Verhuur",
    "sg:phone":"+31 40 291 0219",
    "sg:postcode":"5652 AL",
    "sg:province":"North Brabant",
    "sg:website":"http://www.boels.nl",
    "wof:name":"Boels Eindhoven De Hurk",
    "wof:placetype":"venue"
},
  "geometry": {"coordinates":[5.432342,51.43438],"type":"Point"}
}