{
  "type": "Feature",
  "properties": {
    "addr:full":"Beckumerstr 17 Enschede Overijssel 7548 BD",
    "addr:housenumber":"17",
    "addr:postcode":"7548 bd",
    "addr:street":"Beckumerstr",
    "iso:country":"NL",
    "sg:address":"Beckumerstr 17",
    "sg:city":"Enschede",
    "sg:orig_category":"Postkantoren",
    "sg:phone":"+31 53 428 1576",
    "sg:postcode":"7548 BD",
    "sg:province":"Overijssel",
    "sg:website":"http://www.postkantoor.nl",
    "wof:name":"Postkantoor",
    "wof:placetype":"venue"
},
  "geometry": {"coordinates":[6.798375,52.203747],"type":"Point"}
}