{
  "type": "Feature",
  "properties": {
    "addr:full":"Verdistr 76 Alkmaar Noord-Holland 1817 JG",
    "addr:housenumber":"76",
    "addr:postcode":"1817 jg",
    "addr:street":"Verdistr",
    "iso:country":"NL",
    "sg:address":"Verdistr 76",
    "sg:city":"Alkmaar",
    "sg:orig_category":"Makelaars En Adviseurs Onroerende Goederen",
    "sg:phone":"+31 72 511 6828",
    "sg:postcode":"1817 JG",
    "sg:province":"Noord-Holland",
    "wof:name":"Bos, G M J Van Den",
    "wof:placetype":"venue"
},
  "geometry": {"coordinates":[4.735658,52.645435],"type":"Point"}
}