{
  "type": "Feature",
  "properties": {
    "addr:full":"Prinsenstraat 1 Dordrecht Zuid-Holland 3311 JS",
    "addr:housenumber":"1",
    "addr:postcode":"3311 js",
    "addr:street":"Prinsenstraat",
    "iso:country":"NL",
    "sg:address":"Prinsenstraat 1",
    "sg:city":"Dordrecht",
    "sg:orig_category":"Gebouwenafwerking, Renovaties And Reiniging",
    "sg:phone":"+31 78 631 5211",
    "sg:postcode":"3311 JS",
    "sg:province":"Zuid-Holland",
    "wof:name":"Dordtmij Bv",
    "wof:placetype":"venue"
},
  "geometry": {"coordinates":[4.658818,51.813721],"type":"Point"}
}