{
  "type": "Feature",
  "properties": {
    "iso:country":"NL",
    "sg:address":"Voorhaven 18A",
    "sg:city":"Rotterdam",
    "sg:orig_category":"Meubelzaken, Woning- And Keukeninrichting",
    "sg:phone":"+31 10 276 0764",
    "sg:postcode":"3024 RM",
    "sg:province":"South Holland",
    "wof:name":"J Classics Cv",
    "wof:placetype":"venue"
},
  "geometry": {"coordinates":[4.448982,51.908028],"type":"Point"}
}