{
  "type": "Feature",
  "properties": {
    "addr:full":"It Set 7 Goingaryp Provincie Friesland 8511 AK",
    "addr:housenumber":"7",
    "addr:postcode":"8511 ak",
    "addr:street":"It Set;Provincie Friesland",
    "iso:country":"NL",
    "sg:address":"It Set 7",
    "sg:city":"Goingaryp",
    "sg:orig_category":"Watersportartikelen",
    "sg:phone":"+31 566 689 655",
    "sg:postcode":"8511 AK",
    "sg:province":"Provincie Friesland",
    "wof:name":"Pol Trading Vof",
    "wof:placetype":"venue"
},
  "geometry": {"coordinates":[5.7728037834,53.012008667],"type":"Point"}
}