{
  "type": "Feature",
  "properties": {
    "iso:country":"NL",
    "sg:address":"Butewei 4",
    "sg:city":"Ureterp",
    "sg:orig_category":"Webdesign Bureaus",
    "sg:phone":"+31 512 301 790",
    "sg:postcode":"9247 WL",
    "sg:province":"Provincie Friesland",
    "wof:name":"Ijtsma",
    "wof:placetype":"venue"
},
  "geometry": {"coordinates":[6.1349167824,53.0825614929],"type":"Point"}
}