{
  "type": "Feature",
  "properties": {
    "iso:country":"NL",
    "sg:address":"Vleesstraat 74",
    "sg:city":"Venlo",
    "sg:orig_category":"Fotolaboratoria",
    "sg:phone":"+31 77 354 3882",
    "sg:postcode":"5911 JH",
    "sg:province":"Limburg",
    "wof:name":"Funny Foto",
    "wof:placetype":"venue"
},
  "geometry": {"coordinates":[6.167231,51.367783],"type":"Point"}
}