{
  "type": "Feature",
  "properties": {
    "iso:country":"NL",
    "sg:address":"Kruisstraat 19A",
    "sg:city":"Rosmalen",
    "sg:orig_category":"Meubelzaken, Woning- And Keukeninrichting",
    "sg:phone":"+31 73 521 6299",
    "sg:postcode":"5249 RD",
    "sg:province":"Noord-Brabant",
    "wof:name":"New Age Furniture",
    "wof:placetype":"venue"
},
  "geometry": {"coordinates":[5.396401,51.732048],"type":"Point"}
}