{
  "type": "Feature",
  "properties": {
    "addr:full":"Oostendorperstraatweg 75 Oosterwolde Gld Gelderland 8097 PL",
    "addr:housenumber":"75",
    "addr:postcode":"8097 pl",
    "addr:street":"Oostendorperstraatweg",
    "iso:country":"NL",
    "sg:address":"Oostendorperstraatweg 75",
    "sg:city":"Oosterwolde Gld",
    "sg:orig_category":"Kappers",
    "sg:phone":"+31 525 621 600",
    "sg:postcode":"8097 PL",
    "sg:province":"Gelderland",
    "wof:name":"Kapsalon Bea",
    "wof:placetype":"venue"
},
  "geometry": {"coordinates":[5.8902640343,52.4618148804],"type":"Point"}
}