{
  "type": "Feature",
  "properties": {
    "addr:full":"Arnhemseweg 63 Otterlo Gelderland 6731 BP",
    "addr:housenumber":"63",
    "addr:postcode":"6731 bp",
    "addr:street":"Arnhemseweg;Gelderland",
    "iso:country":"NL",
    "sg:address":"Arnhemseweg 63",
    "sg:city":"Otterlo",
    "sg:classifiers":[
        {
            "category":"Travel",
            "subcategory":"Hotels & Motels",
            "type":"Entertainment"
        }
    ],
    "sg:phone":"+31 318 591 306",
    "sg:postcode":"6731 BP",
    "sg:province":"Gelderland",
    "wof:name":"Pension De Veluwe",
    "wof:placetype":"venue"
},
  "geometry": {"coordinates":[5.772603,52.097122],"type":"Point"}
}