{
  "type": "Feature",
  "properties": {
    "addr:full":"Ambachtspln 115 Rotterdam Zuid-Holland 3068 GV",
    "addr:housenumber":"115",
    "addr:postcode":"3068 gv",
    "iso:country":"NL",
    "sg:address":"Ambachtspln 115",
    "sg:city":"Rotterdam",
    "sg:orig_category":"Postkantoren",
    "sg:phone":"+31 10 456 3692",
    "sg:postcode":"3068 GV",
    "sg:province":"Zuid-Holland",
    "sg:website":"http://www.postkantoor.nl",
    "wof:name":"Postkantoor",
    "wof:placetype":"venue"
},
  "geometry": {"coordinates":[4.569624,51.965298],"type":"Point"}
}