{
  "type": "Feature",
  "properties": {
    "addr:full":"Lemiers Rijksweg 33A Lemiers Limburg 6295 AK",
    "addr:housenumber":"33a",
    "addr:postcode":"6295 ak",
    "addr:street":"Rijksweg",
    "iso:country":"NL",
    "sg:address":"Lemiers Rijksweg 33A",
    "sg:city":"Lemiers",
    "sg:orig_category":"Drukkerijen And Copyshops",
    "sg:phone":"+31 43 306 3682",
    "sg:postcode":"6295 AK",
    "sg:province":"Limburg",
    "wof:name":"R & B Rollen Und Bogenoffsetdruck",
    "wof:placetype":"venue"
},
  "geometry": {"coordinates":[5.993802,50.785454],"type":"Point"}
}