{
  "type": "Feature",
  "properties": {
    "addr:full":"Broerestr 1B Tilburg Noord-Brabant 5041 AW",
    "addr:housenumber":"1b",
    "addr:postcode":"5041 aw",
    "addr:street":"Broerestr",
    "iso:country":"NL",
    "sg:address":"Broerestr 1B",
    "sg:city":"Tilburg",
    "sg:orig_category":"Vertalers",
    "sg:phone":"+31 13 467 8059",
    "sg:postcode":"5041 AW",
    "sg:province":"Noord-Brabant",
    "wof:name":"Vetaler Nl/E E/Nl",
    "wof:placetype":"venue"
},
  "geometry": {"coordinates":[5.085775,51.566833],"type":"Point"}
}