{
  "type": "Feature",
  "properties": {
    "iso:country":"NL",
    "sg:address":"Moerdykse Postb 16",
    "sg:city":"Etten Leur",
    "sg:orig_category":"Adviesbureaus Financieel",
    "sg:phone":"+31 76 503 6654",
    "sg:postcode":"4872 LJ",
    "sg:province":"North Brabant",
    "wof:name":"Veste, De",
    "wof:placetype":"venue"
},
  "geometry": {"coordinates":[4.689303,51.578827],"type":"Point"}
}