{
  "type": "Feature",
  "properties": {
    "iso:country":"NL",
    "sg:address":"Loosd Hoofdstr 178",
    "sg:city":"S Gravenhage",
    "sg:orig_category":"Kappers",
    "sg:phone":"+31 70 397 1251",
    "sg:postcode":"2552 AL",
    "sg:province":"Zuid-Holland",
    "wof:name":"New Look",
    "wof:placetype":"venue"
},
  "geometry": {"coordinates":[4.24958,52.053631],"type":"Point"}
}