{
  "type": "Feature",
  "properties": {
    "addr:full":"Gasthuisstr 16 Oldenzaal Overijssel 7571 CC",
    "addr:housenumber":"16",
    "addr:postcode":"7571 cc",
    "addr:street":"Gasthuisstr",
    "iso:country":"NL",
    "sg:address":"Gasthuisstr 16",
    "sg:city":"Oldenzaal",
    "sg:orig_category":"Kinderopvang",
    "sg:phone":"+31 541 514 992",
    "sg:postcode":"7571 CC",
    "sg:province":"Overijssel",
    "wof:name":"Columbus Junior",
    "wof:placetype":"venue"
},
  "geometry": {"coordinates":[6.930123,52.311581],"type":"Point"}
}