{
  "type": "Feature",
  "properties": {
    "addr:full":"Samuel Van Houtensingel 8 Zwijndrecht South Holland 3332 HV",
    "addr:housenumber":"8",
    "addr:postcode":"3332 hv",
    "addr:street":"Samuel Van Houtensingel",
    "iso:country":"NL",
    "sg:address":"Samuel Van Houtensingel 8",
    "sg:city":"Zwijndrecht",
    "sg:orig_category":"Verzekeringen",
    "sg:phone":"+31 78 612 2658",
    "sg:postcode":"3332 HV",
    "sg:province":"South Holland",
    "wof:name":"G.J. Weber Assurantien",
    "wof:placetype":"venue"
},
  "geometry": {"coordinates":[4.660799,51.828087],"type":"Point"}
}