{
  "type": "Feature",
  "properties": {
    "iso:country":"NL",
    "sg:address":"Jan Deckersstraat 29",
    "sg:city":"Heeze",
    "sg:orig_category":"Banken And Kredietinstellingen",
    "sg:phone":"+31 40 226 5547",
    "sg:postcode":"5591 HN",
    "sg:province":"North Brabant",
    "wof:name":"Postkantoor",
    "wof:placetype":"venue"
},
  "geometry": {"coordinates":[5.578417,51.378307],"type":"Point"}
}