{
  "type": "Feature",
  "properties": {
    "addr:full":"Groevewg 1 Oostwold Scheemda Groningen 9682 RP",
    "addr:housenumber":"1",
    "addr:postcode":"9682 rp",
    "addr:street":"Groevewg",
    "iso:country":"NL",
    "sg:address":"Groevewg 1",
    "sg:city":"Oostwold Scheemda",
    "sg:orig_category":"Adviesbureaus Verzekeringen",
    "sg:phone":"+31 597 552 000",
    "sg:postcode":"9682 RP",
    "sg:province":"Groningen",
    "wof:name":"Bodde, T",
    "wof:placetype":"venue"
},
  "geometry": {"coordinates":[7.032381,53.197601],"type":"Point"}
}