{
  "type": "Feature",
  "properties": {
    "addr:full":"Solvaywg 17 Herten Limburg 6049 CP",
    "addr:housenumber":"17",
    "addr:postcode":"6049 cp",
    "addr:street":"Solvaywg",
    "iso:country":"NL",
    "sg:address":"Solvaywg 17",
    "sg:city":"Herten",
    "sg:orig_category":"Machinefabrieken",
    "sg:phone":"+31 475 322 520",
    "sg:postcode":"6049 CP",
    "sg:province":"Limburg",
    "wof:name":"Kiggen Vof",
    "wof:placetype":"venue"
},
  "geometry": {"coordinates":[5.96037,51.168373],"type":"Point"}
}