{
  "type": "Feature",
  "properties": {
    "iso:country":"NL",
    "sg:address":"Oudedijk 141",
    "sg:city":"Rotterdam",
    "sg:orig_category":"Opticiens",
    "sg:phone":"+31 10 412 2327",
    "sg:postcode":"3061 AA",
    "sg:province":"South Holland",
    "wof:name":"Bastiaans Brillen Vof",
    "wof:placetype":"venue"
},
  "geometry": {"coordinates":[4.5102081299,51.9272994995],"type":"Point"}
}