{
  "type": "Feature",
  "properties": {
    "addr:full":"Stationsstr 15 Amstelveen Noord-Holland 1182 JM",
    "addr:housenumber":"15",
    "addr:postcode":"1182 jm",
    "addr:street":"Stationsstr",
    "iso:country":"NL",
    "sg:address":"Stationsstr 15",
    "sg:city":"Amstelveen",
    "sg:orig_category":"Kinderopvang",
    "sg:phone":"+31 20 441 5308",
    "sg:postcode":"1182 JM",
    "sg:province":"Noord-Holland",
    "wof:name":"Eigen Wijsje, 'T",
    "wof:placetype":"venue"
},
  "geometry": {"coordinates":[4.847217,52.301495],"type":"Point"}
}