{
  "type": "Feature",
  "properties": {
    "addr:full":"T Spiker 117 Warnsveld Gelderland 7231 JP",
    "addr:housenumber":"117",
    "addr:postcode":"7231 jp",
    "addr:street":"T Spiker;Gelderland",
    "iso:country":"NL",
    "sg:address":"T Spiker 117",
    "sg:city":"Warnsveld",
    "sg:orig_category":"Autorijscholen",
    "sg:phone":"+31 575 528 184",
    "sg:postcode":"7231 JP",
    "sg:province":"Gelderland",
    "wof:name":"Leussen, Van",
    "wof:placetype":"venue"
},
  "geometry": {"coordinates":[6.222207,52.139179],"type":"Point"}
}