{
  "type": "Feature",
  "properties": {
    "addr:full":"Schoolstraat 11 Warffum Groningen 9989 AG",
    "addr:housenumber":"11",
    "addr:postcode":"9989",
    "addr:street":"Schoolstraat",
    "iso:country":"NL",
    "sg:address":"Schoolstraat 11",
    "sg:city":"Warffum",
    "sg:orig_category":"Kappers",
    "sg:phone":"+31 595 422 419",
    "sg:postcode":"9989 AG",
    "sg:province":"Groningen",
    "wof:name":"Ina Venhuizen",
    "wof:placetype":"venue"
},
  "geometry": {"coordinates":[6.5627560616,53.392539978],"type":"Point"}
}