{
  "type": "Feature",
  "properties": {
    "addr:full":"T Kabel 20 Nieuw Vennep Noord-Holland 2153 MB",
    "addr:housenumber":"20",
    "addr:postcode":"2153 mb",
    "addr:street":"T Kabel;Nieuw Vennep",
    "iso:country":"NL",
    "sg:address":"T Kabel 20",
    "sg:city":"Nieuw Vennep",
    "sg:orig_category":"Elektronische Bedrijfsinstallaties",
    "sg:phone":"+31 252 674 152",
    "sg:postcode":"2153 MB",
    "sg:province":"Noord-Holland",
    "wof:name":"R.V.B.",
    "wof:placetype":"venue"
},
  "geometry": {"coordinates":[4.654494,52.253407],"type":"Point"}
}