{
  "type": "Feature",
  "properties": {
    "iso:country":"NL",
    "sg:address":"Broekerheide 42",
    "sg:city":"Almelo",
    "sg:orig_category":"Metaalwerken",
    "sg:phone":"+31 546 852 423",
    "sg:postcode":"7609 TT",
    "sg:province":"Overijssel",
    "wof:name":"G.W. Finke",
    "wof:placetype":"venue"
},
  "geometry": {"coordinates":[6.6446027756,52.3305854797],"type":"Point"}
}