{
  "type": "Feature",
  "properties": {
    "addr:full":"Mahlerstr 15 Amersfoort Utrecht 3816 LW",
    "addr:housenumber":"15",
    "addr:postcode":"3816 lw",
    "addr:street":"Mahlerstr",
    "iso:country":"NL",
    "sg:address":"Mahlerstr 15",
    "sg:city":"Amersfoort",
    "sg:orig_category":"Adviesbureaus Bedrijfsorganisatie",
    "sg:phone":"+31 33 479 9703",
    "sg:postcode":"3816 LW",
    "sg:province":"Utrecht",
    "wof:name":"Nu'Visie",
    "wof:placetype":"venue"
},
  "geometry": {"coordinates":[5.40429,52.147846],"type":"Point"}
}