{
  "type": "Feature",
  "properties": {
    "addr:full":"Postbus 9239 Rotterdam 3007 AE",
    "addr:housenumber":"9239",
    "addr:postcode":"3007 ae",
    "addr:street":"Postbus",
    "iso:country":"NL",
    "sg:address":"Postbus 9239",
    "sg:city":"Rotterdam",
    "sg:orig_category":"Organisatiebureaus",
    "sg:phone":"+31 10 479 6439",
    "sg:postcode":"3007 AE",
    "wof:name":"Belle, Marco Van",
    "wof:placetype":"venue"
},
  "geometry": {"coordinates":[4.470749855,51.922618866],"type":"Point"}
}