{
  "type": "Feature",
  "properties": {
    "addr:full":"Diepmeerven 46 Eindhoven Noord-Brabant 5646 HB",
    "addr:housenumber":"46",
    "addr:postcode":"5646 hb",
    "addr:street":"Diepmeerven",
    "iso:country":"NL",
    "sg:address":"Diepmeerven 46",
    "sg:city":"Eindhoven",
    "sg:orig_category":"Kantoorartikelen",
    "sg:phone":"+31 40 211 0456",
    "sg:postcode":"5646 HB",
    "sg:province":"Noord-Brabant",
    "wof:name":"P C Heskens",
    "wof:placetype":"venue"
},
  "geometry": {"coordinates":[5.5125331879,51.4224052429],"type":"Point"}
}