{
  "type": "Feature",
  "properties": {
    "iso:country":"NL",
    "sg:address":"Gillis Schoolmeesterlaan 26",
    "sg:city":"Haarlem",
    "sg:orig_category":"Verzekeringen",
    "sg:phone":"+31 23 524 7363",
    "sg:postcode":"2015 EM",
    "sg:province":"Noord-Holland",
    "wof:name":"Regthoek Assurantien Vof",
    "wof:placetype":"venue"
},
  "geometry": {"coordinates":[4.608482,52.383167],"type":"Point"}
}