{
  "type": "Feature",
  "properties": {
    "addr:full":"Strijkviertel 50 De Meern Utrecht 3454 PL",
    "addr:housenumber":"50",
    "addr:postcode":"3454 pl",
    "addr:street":"Strijkviertel",
    "iso:country":"NL",
    "sg:address":"Strijkviertel 50",
    "sg:city":"De Meern",
    "sg:orig_category":"Autokeuringen",
    "sg:phone":"+31 6 22366003",
    "sg:postcode":"3454 PL",
    "sg:province":"Utrecht",
    "wof:name":"Zaffa",
    "wof:placetype":"venue"
},
  "geometry": {"coordinates":[5.059151,52.079998],"type":"Point"}
}