{
  "type": "Feature",
  "properties": {
    "iso:country":"NL",
    "sg:address":"Hillegomstraat 18",
    "sg:city":"Amsterdam",
    "sg:orig_category":"Agenturen En Commissiehandel",
    "sg:phone":"+31 20 615 6567",
    "sg:postcode":"1058 LS",
    "sg:province":"Noord-Holland",
    "wof:name":"Mwila Trading Comp",
    "wof:placetype":"venue"
},
  "geometry": {"coordinates":[4.848078,52.352287],"type":"Point"}
}