{
  "type": "Feature",
  "properties": {
    "addr:full":"Uithoornstr 35 Amsterdam Noord-Holland 1078 ST",
    "addr:housenumber":"35",
    "addr:postcode":"1078 st",
    "addr:street":"Uithoornstr",
    "iso:country":"NL",
    "sg:address":"Uithoornstr 35",
    "sg:city":"Amsterdam",
    "sg:orig_category":"Wasmachines En Wasdrogers - Onderhoud En Reparatie",
    "sg:phone":"+31 20 673 5893",
    "sg:postcode":"1078 ST",
    "sg:province":"Noord-Holland",
    "wof:name":"Aaqua-Matic",
    "wof:placetype":"venue"
},
  "geometry": {"coordinates":[4.9084758759,52.3474006653],"type":"Point"}
}