{
  "type": "Feature",
  "properties": {
    "iso:country":"NL",
    "sg:address":"Marktstraat 14",
    "sg:city":"Roermond",
    "sg:orig_category":"Werving And Selectie Van Tijdelijk Personeel And Uitzendkantoren",
    "sg:phone":"+31 475 319 949",
    "sg:postcode":"6041 EN",
    "sg:province":"Limburg",
    "wof:name":"Dactylo",
    "wof:placetype":"venue"
},
  "geometry": {"coordinates":[5.9850411415,51.1948814392],"type":"Point"}
}