{
  "type": "Feature",
  "properties": {
    "addr:full":"Tamboerynstr 19 Amersfoort Utrecht 3822 DG",
    "addr:housenumber":"19",
    "addr:postcode":"3822 dg",
    "addr:street":"Tamboerynstr",
    "iso:country":"NL",
    "sg:address":"Tamboerynstr 19",
    "sg:city":"Amersfoort",
    "sg:orig_category":"Actuarissen",
    "sg:phone":"+31 33 455 6629",
    "sg:postcode":"3822 DG",
    "sg:province":"Utrecht",
    "wof:name":"Voois-Borst",
    "wof:placetype":"venue"
},
  "geometry": {"coordinates":[5.402893,52.185482],"type":"Point"}
}