{
  "type": "Feature",
  "properties": {
    "iso:country":"NL",
    "sg:address":"Ryksstrwg 231",
    "sg:city":"Leersum",
    "sg:orig_category":"Kappers",
    "sg:phone":"+31 343 454 056",
    "sg:postcode":"3956 CN",
    "sg:province":"Utrecht",
    "wof:name":"Barber Bib?r",
    "wof:placetype":"venue"
},
  "geometry": {"coordinates":[5.3870711327,52.0122070312],"type":"Point"}
}