{
  "type": "Feature",
  "properties": {
    "addr:full":"Ryksstrwg 231 Leersum Utrecht 3956 CN",
    "addr:housenumber":"231",
    "addr:postcode":"3956 cn",
    "addr:street":"Leersum",
    "iso:country":"NL",
    "sg:address":"Ryksstrwg 231",
    "sg:city":"Leersum",
    "sg:orig_category":"Kappers",
    "sg:phone":"+31 343 454 056",
    "sg:postcode":"3956 CN",
    "sg:province":"Utrecht",
    "wof:name":"Barber Bib?r",
    "wof:placetype":"venue"
},
  "geometry": {"coordinates":[5.3870711327,52.0122070312],"type":"Point"}
}