{
  "type": "Feature",
  "properties": {
    "addr:full":"Mylwg 7 S Gravendeel Zuid-Holland 3295 KG",
    "addr:housenumber":"7",
    "addr:postcode":"3295 kg",
    "addr:street":"Mylwg",
    "iso:country":"NL",
    "sg:address":"Mylwg 7",
    "sg:city":"S Gravendeel",
    "sg:orig_category":"Kunststoffen- Verwerkende Industrie",
    "sg:phone":"+31 78 673 8111",
    "sg:postcode":"3295 KG",
    "sg:province":"Zuid-Holland",
    "sg:website":"HTTP://www.wedco.nl",
    "wof:name":"Wedco",
    "wof:placetype":"venue"
},
  "geometry": {"coordinates":[4.61675,51.779362],"type":"Point"}
}