{
  "type": "Feature",
  "properties": {
    "addr:full":"Azieln 59 Drunen Noord-Brabant 5152 JB",
    "addr:housenumber":"59",
    "addr:postcode":"5152 jb",
    "addr:street":"Azieln",
    "iso:country":"NL",
    "sg:address":"Azieln 59",
    "sg:city":"Drunen",
    "sg:orig_category":"Scholen Voor Basisonderwijs",
    "sg:phone":"+31 416 376 924",
    "sg:postcode":"5152 JB",
    "sg:province":"Noord-Brabant",
    "wof:name":"Vlot, Het",
    "wof:placetype":"venue"
},
  "geometry": {"coordinates":[5.12227,51.681889],"type":"Point"}
}