{
  "type": "Feature",
  "properties": {
    "addr:full":"Rykswg 236 Santpoort Noord Noord-Holland 2071 KD",
    "addr:housenumber":"236",
    "addr:postcode":"2071 kd",
    "addr:street":"Santpoort",
    "iso:country":"NL",
    "sg:address":"Rykswg 236",
    "sg:city":"Santpoort Noord",
    "sg:classifiers":[
        {
            "category":"Sports & Exercise",
            "subcategory":"Stables",
            "type":"Entertainment"
        }
    ],
    "sg:phone":"+31 23 537 6540",
    "sg:postcode":"2071 KD",
    "sg:province":"Noord-Holland",
    "sg:tags":[
        "maneges"
    ],
    "wof:name":"Rozenstein",
    "wof:placetype":"venue"
},
  "geometry": {"coordinates":[-121.95871,39.780125],"type":"Point"}
}