{
  "type": "Feature",
  "properties": {
    "addr:full":"Wiekslag 429 Amersfoort Utrecht 3815 GP",
    "addr:housenumber":"429",
    "addr:postcode":"3815 gp",
    "addr:street":"Wiekslag",
    "iso:country":"NL",
    "sg:address":"Wiekslag 429",
    "sg:city":"Amersfoort",
    "sg:orig_category":"Fotografie Reclame En Mode",
    "sg:phone":"+31 33 472 8309",
    "sg:postcode":"3815 GP",
    "sg:province":"Utrecht",
    "sg:website":"http://www.artinfinitum.net",
    "wof:name":"Art Infinitum Mardoe Painter-De Jonge",
    "wof:placetype":"venue"
},
  "geometry": {"coordinates":[5.403707,52.168835],"type":"Point"}
}