{
  "type": "Feature",
  "properties": {
    "addr:full":"Doornburgln 11 Utrecht Utrecht 3554 EP",
    "addr:housenumber":"11",
    "addr:postcode":"3554 ep",
    "addr:street":"Doornburgln",
    "iso:country":"NL",
    "sg:address":"Doornburgln 11",
    "sg:city":"Utrecht",
    "sg:orig_category":"Boekhandels",
    "sg:phone":"+31 30 223 9837",
    "sg:postcode":"3554 EP",
    "sg:province":"Utrecht",
    "sg:website":"http://www.rokade-readshop.nl",
    "wof:name":"Read Shop, The",
    "wof:placetype":"venue"
},
  "geometry": {"coordinates":[5.089475,52.113403],"type":"Point"}
}