{
  "type": "Feature",
  "properties": {
    "addr:full":"Eindhovenstraat 5 Heerlen Limburg 6415 CE",
    "addr:housenumber":"5",
    "addr:postcode":"6415 ce",
    "addr:street":"Eindhovenstraat",
    "iso:country":"NL",
    "sg:address":"Eindhovenstraat 5",
    "sg:city":"Heerlen",
    "sg:orig_category":"Verzekeringen",
    "sg:phone":"+31 45 570 8761",
    "sg:postcode":"6415 CE",
    "sg:province":"Limburg",
    "wof:name":"Rutten Assurantien",
    "wof:placetype":"venue"
},
  "geometry": {"coordinates":[5.994425,50.89489],"type":"Point"}
}