{
  "type": "Feature",
  "properties": {
    "addr:full":"Vliertstraat 3 Vught North Brabant 5261 EJ",
    "addr:housenumber":"3",
    "addr:postcode":"5261 ej",
    "addr:street":"Vliertstraat",
    "iso:country":"NL",
    "sg:address":"Vliertstraat 3",
    "sg:city":"Vught",
    "sg:classifiers":[
        {
            "category":"Fast Food",
            "type":"Food & Drink"
        }
    ],
    "sg:phone":"+31 73 656 9699",
    "sg:postcode":"5261 EJ",
    "sg:province":"North Brabant",
    "sg:tags":[
        "afhaal",
        "restaurant"
    ],
    "wof:name":"Egyptisch Eethuis",
    "wof:placetype":"venue"
},
  "geometry": {"coordinates":[5.298018,51.657303],"type":"Point"}
}