{
  "type": "Feature",
  "properties": {
    "addr:full":"Oudez Voorburgwal 119 Amsterdam Noord-Holland 1012 EN",
    "addr:housenumber":"119",
    "addr:postcode":"1012 en",
    "addr:street":"Oudez Voorburgwal",
    "iso:country":"NL",
    "sg:address":"Oudez Voorburgwal 119",
    "sg:city":"Amsterdam",
    "sg:orig_category":"Zonnebank- En Solariumcentra",
    "sg:phone":"+31 20 638 9261",
    "sg:postcode":"1012 EN",
    "sg:province":"Noord-Holland",
    "wof:name":"Privado Del Sol",
    "wof:placetype":"venue"
},
  "geometry": {"coordinates":[4.897735,52.372963],"type":"Point"}
}