{
  "type": "Feature",
  "properties": {
    "addr:full":"A V Elenstr 12 Maastricht Limburg 6217 JM",
    "addr:housenumber":"12",
    "addr:postcode":"6217 jm",
    "addr:street":"A;Elenstr",
    "iso:country":"NL",
    "sg:address":"A V Elenstr 12",
    "sg:city":"Maastricht",
    "sg:orig_category":"Ziekenvervoer",
    "sg:phone":"+31 43 344 0444",
    "sg:postcode":"6217 JM",
    "sg:province":"Limburg",
    "wof:name":"Ziekenvervoer Maastricht En Heuvelland",
    "wof:placetype":"venue"
},
  "geometry": {"coordinates":[5.68829,50.849831],"type":"Point"}
}