{
  "type": "Feature",
  "properties": {
    "iso:country":"NL",
    "sg:address":"Polarisavenue 1",
    "sg:city":"Hoofddorp",
    "sg:orig_category":"Zalenverhuur",
    "sg:phone":"+31 23 568 5125",
    "sg:postcode":"2132 JH",
    "sg:province":"Noord-Holland",
    "wof:name":"Festival, Le",
    "wof:placetype":"venue"
},
  "geometry": {"coordinates":[4.711398,52.292999],"type":"Point"}
}