{
  "type": "Feature",
  "properties": {
    "iso:country":"NL",
    "sg:address":"Beeklaan 10",
    "sg:city":"Oldebroek",
    "sg:orig_category":"Notarissen",
    "sg:phone":"+31 525 631 335",
    "sg:postcode":"8096 AM",
    "sg:province":"Gelderland",
    "wof:name":"Notariskanaoor De Jongh & Otto",
    "wof:placetype":"venue"
},
  "geometry": {"coordinates":[5.895012,52.445301],"type":"Point"}
}