{
  "type": "Feature",
  "properties": {
    "iso:country":"NL",
    "sg:address":"Lange Dreef 10",
    "sg:city":"Veenendaal",
    "sg:orig_category":"Hoger Onderwijs",
    "sg:phone":"+31 318 515 992",
    "sg:postcode":"3902 AH",
    "sg:province":"Utrecht",
    "wof:name":"G. Hardeman",
    "wof:placetype":"venue"
},
  "geometry": {"coordinates":[5.567331,52.036201],"type":"Point"}
}