{
  "type": "Feature",
  "properties": {
    "iso:country":"NL",
    "sg:address":"Koningin Julianalaan 1D",
    "sg:city":"Delfzijl",
    "sg:orig_category":"Begrafenisondernemers",
    "sg:phone":"+31 596 611 008",
    "sg:postcode":"9934 EB",
    "sg:province":"Groningen",
    "wof:name":"Begraafplaats",
    "wof:placetype":"venue"
},
  "geometry": {"coordinates":[6.917726,53.330105],"type":"Point"}
}