{
  "type": "Feature",
  "properties": {
    "iso:country":"NL",
    "sg:address":"Ranonkelstr 57",
    "sg:city":"Eindhoven",
    "sg:orig_category":"Wasserijen",
    "sg:phone":"+31 40 211 1545",
    "sg:postcode":"5644 LB",
    "sg:province":"Noord-Brabant",
    "wof:name":"Karreman",
    "wof:placetype":"venue"
},
  "geometry": {"coordinates":[5.4873828888,51.4194984436],"type":"Point"}
}