{
  "type": "Feature",
  "properties": {
    "addr:full":"De Dieze 43 Goirle Noord-Brabant 5052 TM",
    "addr:housenumber":"43",
    "addr:postcode":"5052 tm",
    "addr:street":"De Dieze",
    "iso:country":"NL",
    "sg:address":"De Dieze 43",
    "sg:city":"Goirle",
    "sg:orig_category":"Juridische Dienstverlening",
    "sg:phone":"+31 13 530 0007",
    "sg:postcode":"5052 TM",
    "sg:province":"Noord-Brabant",
    "wof:name":"Bureau Grafiet Bv",
    "wof:placetype":"venue"
},
  "geometry": {"coordinates":[5.0465478897,51.5264778137],"type":"Point"}
}