{
  "type": "Feature",
  "properties": {
    "addr:full":"Wolfskuilln 5 Ommen Overijssel 7731 AM",
    "addr:housenumber":"5",
    "addr:postcode":"7731",
    "addr:street":"Wolfskuilln",
    "iso:country":"NL",
    "sg:address":"Wolfskuilln 5",
    "sg:city":"Ommen",
    "sg:orig_category":"Adviesbureaus Bedrijfsorganisatie",
    "sg:phone":"+31 6 53371556",
    "sg:postcode":"7731 AM",
    "sg:province":"Overijssel",
    "wof:name":"Ppims",
    "wof:placetype":"venue"
},
  "geometry": {"coordinates":[6.42297,52.517754],"type":"Point"}
}