{
  "type": "Feature",
  "properties": {
    "iso:country":"NL",
    "sg:address":"Bilderdijkkade 57",
    "sg:city":"Amsterdam",
    "sg:orig_category":"Loodgieterswerk, Verwarming And Sanitaire Installaties",
    "sg:phone":"+31 20 618 1048",
    "sg:postcode":"1053 VJ",
    "sg:province":"Noord-Holland",
    "wof:name":"C.N.A. Kennis",
    "wof:placetype":"venue"
},
  "geometry": {"coordinates":[4.869036,52.370144],"type":"Point"}
}