{
  "type": "Feature",
  "properties": {
    "addr:full":"Burg Mandersln 43 Zundert Noord-Brabant 4881 EH",
    "addr:housenumber":"43",
    "addr:postcode":"4881 eh",
    "addr:street":"Burg",
    "iso:country":"NL",
    "sg:address":"Burg Mandersln 43",
    "sg:city":"Zundert",
    "sg:orig_category":"Video - Faciliteiten En Producties",
    "sg:phone":"+31 76 599 0424",
    "sg:postcode":"4881 EH",
    "sg:province":"Noord-Brabant",
    "sg:website":"http://www.actual.nl",
    "wof:name":"Actual Broadcast Productions",
    "wof:placetype":"venue"
},
  "geometry": {"coordinates":[4.663938,51.469357],"type":"Point"}
}