{
  "type": "Feature",
  "properties": {
    "addr:full":"Parkweg 19 Beesd Gelderland 4153 XK",
    "addr:housenumber":"19",
    "addr:postcode":"4153 xk",
    "addr:street":"Parkweg;Gelderland",
    "iso:country":"NL",
    "sg:address":"Parkweg 19",
    "sg:city":"Beesd",
    "sg:orig_category":"Boekenuitgeverijen",
    "sg:phone":"+31 345 681 774",
    "sg:postcode":"4153 XK",
    "sg:province":"Gelderland",
    "wof:name":"Menuprint",
    "wof:placetype":"venue"
},
  "geometry": {"coordinates":[5.189857,51.893639],"type":"Point"}
}