{
  "type": "Feature",
  "properties": {
    "addr:full":"Grevelingen 56 Alkmaar North Holland 1826 AP",
    "addr:housenumber":"56",
    "addr:postcode":"1826 ap",
    "addr:street":"Grevelingen",
    "iso:country":"NL",
    "sg:address":"Grevelingen 56",
    "sg:city":"Alkmaar",
    "sg:orig_category":"Koeriersdiensten",
    "sg:phone":"+31 72 564 8527",
    "sg:postcode":"1826 AP",
    "sg:province":"North Holland",
    "wof:name":"No Limit Koeriersdiensten",
    "wof:placetype":"venue"
},
  "geometry": {"coordinates":[4.758493,52.650681],"type":"Point"}
}