{
  "type": "Feature",
  "properties": {
    "addr:full":"Luxemburgln 327 Heemskerk Noord-Holland 1966 MC",
    "addr:housenumber":"327;1966",
    "addr:postcode":"heemskerk;mc",
    "iso:country":"NL",
    "sg:address":"Luxemburgln 327",
    "sg:city":"Heemskerk",
    "sg:orig_category":"Elektrotechnische Apparatuur - Fabrieken En Groothandel",
    "sg:phone":"+31 251 254 561",
    "sg:postcode":"1966 MC",
    "sg:province":"Noord-Holland",
    "sg:website":"HTTP://www.fribeko.tk",
    "wof:name":"Fribeko",
    "wof:placetype":"venue"
},
  "geometry": {"coordinates":[4.676497,52.498234],"type":"Point"}
}