{
  "type": "Feature",
  "properties": {
    "addr:full":"Molukkenstr 200 Amsterdam North Holland 1098 TW",
    "addr:housenumber":"200",
    "addr:postcode":"1098 tw",
    "iso:country":"NL",
    "sg:address":"Molukkenstr 200",
    "sg:city":"Amsterdam",
    "sg:orig_category":"Marketingbureaus",
    "sg:phone":"+31 20 663 9977",
    "sg:postcode":"1098 TW",
    "sg:province":"North Holland",
    "sg:website":"http://www.starfish-ec.com",
    "wof:name":"Starfish Events & Communication",
    "wof:placetype":"venue"
},
  "geometry": {"coordinates":[4.940942,52.358059],"type":"Point"}
}