{
  "type": "Feature",
  "properties": {
    "iso:country":"NL",
    "sg:address":"Celsiusstraat 13",
    "sg:city":"Harderwijk",
    "sg:orig_category":"Goederenvervoer Over De Weg",
    "sg:phone":"+31 341 415 120",
    "sg:postcode":"3846 BK",
    "sg:province":"Gelderland",
    "wof:name":"Klomp Transport Bv",
    "wof:placetype":"venue"
},
  "geometry": {"coordinates":[5.645564,52.359306],"type":"Point"}
}