{
  "type": "Feature",
  "properties": {
    "addr:full":"Sterrebosln 11 Bloemendaal Noord-Holland 2061 VT",
    "addr:housenumber":"11",
    "addr:postcode":"2061",
    "addr:street":"Sterrebosln",
    "iso:country":"NL",
    "sg:address":"Sterrebosln 11",
    "sg:city":"Bloemendaal",
    "sg:orig_category":"Beeldende Kunstenaars",
    "sg:phone":"+31 23 525 1105",
    "sg:postcode":"2061 VT",
    "sg:province":"Noord-Holland",
    "wof:name":"Stolk A Fine-Art",
    "wof:placetype":"venue"
},
  "geometry": {"coordinates":[4.617444,52.407566],"type":"Point"}
}