{
  "type": "Feature",
  "properties": {
    "iso:country":"NL",
    "sg:address":"Strevelsweg 692",
    "sg:city":"Rotterdam",
    "sg:orig_category":"Juridische Dienstverlening",
    "sg:phone":"+31 10 410 6677",
    "sg:postcode":"3083 AR",
    "sg:province":"Zuid-Holland",
    "wof:name":"Buro Voor Rechtshulp",
    "wof:placetype":"venue"
},
  "geometry": {"coordinates":[-73.97154999999999,42.786839],"type":"Point"}
}