{
  "type": "Feature",
  "properties": {
    "addr:full":"Kootwykerschans 39 Nieuwegein Utrecht 3432 CX",
    "addr:housenumber":"39",
    "addr:postcode":"3432 cx",
    "addr:street":"Kootwykerschans",
    "iso:country":"NL",
    "sg:address":"Kootwykerschans 39",
    "sg:city":"Nieuwegein",
    "sg:orig_category":"Webdesign Bureaus",
    "sg:phone":"+31 30 608 1001",
    "sg:postcode":"3432 CX",
    "sg:province":"Utrecht",
    "wof:name":"Nozem Productions",
    "wof:placetype":"venue"
},
  "geometry": {"coordinates":[5.0966291428,52.0177497864],"type":"Point"}
}