{
  "type": "Feature",
  "properties": {
    "iso:country":"NL",
    "sg:address":"Bindery 1",
    "sg:city":"Amstelveen",
    "sg:orig_category":"Bedden En Matrassen",
    "sg:phone":"+31 20 645 6921",
    "sg:postcode":"1185 ZH",
    "sg:province":"Noord-Holland",
    "sg:website":"http://www.simondebruin.nl",
    "wof:name":"Bruin Bedden & Waterbedden, Simon De",
    "wof:placetype":"venue"
},
  "geometry": {"coordinates":[4.842342,52.288593],"type":"Point"}
}