{
  "type": "Feature",
  "properties": {
    "addr:full":"Henk Lensenlaan 4 Vogelenzang Noord-Holland 2114 ER",
    "addr:housenumber":"4",
    "addr:postcode":"2114 er",
    "addr:street":"Henk Lensenlaan",
    "iso:country":"NL",
    "sg:address":"Henk Lensenlaan 4",
    "sg:city":"Vogelenzang",
    "sg:orig_category":"Sportclubs",
    "sg:phone":"+31 23 584 8774",
    "sg:postcode":"2114 ER",
    "sg:province":"Noord-Holland",
    "wof:name":"Vogelenzang Tennisvereniging",
    "wof:placetype":"venue"
},
  "geometry": {"coordinates":[4.572374,52.317425],"type":"Point"}
}