{
  "type": "Feature",
  "properties": {
    "addr:full":"Boekweitwg 42 Elspeet Gelderland 8075 CP",
    "addr:housenumber":"42",
    "addr:postcode":"8075 cp",
    "addr:street":"Boekweitwg;Gelderland",
    "iso:country":"NL",
    "sg:address":"Boekweitwg 42",
    "sg:city":"Elspeet",
    "sg:classifiers":[
        {
            "category":"Personal",
            "subcategory":"Nail Salon",
            "type":"Services"
        }
    ],
    "sg:phone":"+31 577 491 491",
    "sg:postcode":"8075 CP",
    "sg:province":"Gelderland",
    "sg:tags":[
        "pedicure"
    ],
    "wof:name":"Lagen, Wilma Van",
    "wof:placetype":"venue"
},
  "geometry": {"coordinates":[5.791936,52.293697],"type":"Point"}
}