{
  "type": "Feature",
  "properties": {
    "iso:country":"NL",
    "sg:address":"Hoofdstraat 8",
    "sg:city":"Veghel",
    "sg:classifiers":[
        {
            "category":"Professional",
            "subcategory":"Accounting & Tax Preparation",
            "type":"Services"
        }
    ],
    "sg:phone":"+31 413 340 403",
    "sg:postcode":"5461 JE",
    "sg:province":"North Brabant",
    "sg:tags":[
        "accountant"
    ],
    "wof:name":"Houtman & Co Registeraccountant",
    "wof:placetype":"venue"
},
  "geometry": {"coordinates":[5.543566,51.616123],"type":"Point"}
}