{
  "type": "Feature",
  "properties": {
    "iso:country":"NL",
    "sg:address":"Boomstede 232",
    "sg:city":"Maarssen",
    "sg:orig_category":"Fotografie Reclame En Mode",
    "sg:phone":"+31 346 554 425",
    "sg:postcode":"3608 AL",
    "sg:province":"Utrecht",
    "wof:name":"Fierst, M",
    "wof:placetype":"venue"
},
  "geometry": {"coordinates":[5.029487,52.124241],"type":"Point"}
}