{
  "type": "Feature",
  "properties": {
    "addr:full":"Kempenaar 2045 Lelystad Flevoland 8231 GA",
    "addr:postcode":"2045;8231 ga",
    "addr:street":"Kempenaar;Flevoland",
    "iso:country":"NL",
    "sg:address":"Kempenaar 2045",
    "sg:city":"Lelystad",
    "sg:orig_category":"Montagebedrijven",
    "sg:phone":"+31 320 231 516",
    "sg:postcode":"8231 GA",
    "sg:province":"Flevoland",
    "wof:name":"Kit",
    "wof:placetype":"venue"
},
  "geometry": {"coordinates":[5.465141,52.519096],"type":"Point"}
}