{
  "type": "Feature",
  "properties": {
    "addr:full":"Past V Beurdenstr 20 Tilburg Noord-Brabant 5046 HL",
    "addr:housenumber":"20",
    "addr:postcode":"5046 hl",
    "addr:street":"Past;Beurdenstr",
    "iso:country":"NL",
    "sg:address":"Past V Beurdenstr 20",
    "sg:city":"Tilburg",
    "sg:orig_category":"Scheepvaart- Agentschappen",
    "sg:phone":"+31 6 10560360",
    "sg:postcode":"5046 HL",
    "sg:province":"Noord-Brabant",
    "wof:name":"Schr\u00f7Der",
    "wof:placetype":"venue"
},
  "geometry": {"coordinates":[5.07823,51.57272],"type":"Point"}
}