{
  "type": "Feature",
  "properties": {
    "addr:full":"Trompenburgstr 111 Amsterdam Noord-Holland 1079 TV",
    "addr:housenumber":"111",
    "addr:postcode":"1079 tv",
    "iso:country":"NL",
    "sg:address":"Trompenburgstr 111",
    "sg:city":"Amsterdam",
    "sg:orig_category":"Muziekinstrumenten En Bladmuziek",
    "sg:phone":"+31 20 644 5767",
    "sg:postcode":"1079 TV",
    "sg:province":"Noord-Holland",
    "wof:name":"Muziekbeurs Amsterdam",
    "wof:placetype":"venue"
},
  "geometry": {"coordinates":[4.906902,52.343952],"type":"Point"}
}