{
  "type": "Feature",
  "properties": {
    "iso:country":"NL",
    "sg:address":"Erica 7",
    "sg:city":"St Oedenrode",
    "sg:orig_category":"Elektrotechnische Apparatuur - Fabrieken En Groothandel",
    "sg:phone":"+31 413 473 750",
    "sg:postcode":"5491 VR",
    "sg:province":"Noord-Brabant",
    "wof:name":"Biemans Bv",
    "wof:placetype":"venue"
},
  "geometry": {"coordinates":[5.435686,51.577892],"type":"Point"}
}