{
  "type": "Feature",
  "properties": {
    "addr:full":"Klompenmakerstr 7 Velserbroek Noord-Holland 1991 JJ",
    "addr:housenumber":"7",
    "addr:postcode":"1991 jj",
    "addr:street":"Klompenmakerstr",
    "iso:country":"NL",
    "sg:address":"Klompenmakerstr 7",
    "sg:city":"Velserbroek",
    "sg:orig_category":"Autoreclame",
    "sg:phone":"+31 23 538 8813",
    "sg:postcode":"1991 JJ",
    "sg:province":"Noord-Holland",
    "wof:name":"Toon-It Reklameatelier",
    "wof:placetype":"venue"
},
  "geometry": {"coordinates":[4.650414,52.432999],"type":"Point"}
}