{
  "type": "Feature",
  "properties": {
    "addr:full":"Postbus 1350 Eindhoven Noord-Brabant 5602 ZA",
    "addr:housenumber":"1350",
    "addr:postcode":"5602",
    "addr:street":"Postbus",
    "iso:country":"NL",
    "sg:address":"Postbus 1350",
    "sg:city":"Eindhoven",
    "sg:orig_category":"Arbo- En Bedrijfsgezondheids- Diensten",
    "sg:phone":"+31 40 239 8429",
    "sg:postcode":"5602 ZA",
    "sg:province":"Noord-Brabant",
    "wof:name":"Arbodienst",
    "wof:placetype":"venue"
},
  "geometry": {"coordinates":[5.48411,51.434471],"type":"Point"}
}