{
  "type": "Feature",
  "properties": {
    "addr:full":"Anholtsewg 49 Gendringen Gelderland 7081 CL",
    "addr:housenumber":"49",
    "addr:postcode":"7081",
    "addr:street":"Anholtsewg;Gelderland",
    "iso:country":"NL",
    "sg:address":"Anholtsewg 49",
    "sg:city":"Gendringen",
    "sg:orig_category":"Betonboringen",
    "sg:phone":"+31 315 686 428",
    "sg:postcode":"7081 CL",
    "sg:province":"Gelderland",
    "sg:website":"http://www.wiha-bv.nl",
    "wof:name":"Wiha Bv",
    "wof:placetype":"venue"
},
  "geometry": {"coordinates":[6.384922,51.867722],"type":"Point"}
}