{
  "type": "Feature",
  "properties": {
    "addr:full":"Maasdijk 42 Poederoijen Gelderland 5307 HP",
    "addr:housenumber":"42",
    "addr:postcode":"5307 hp",
    "addr:street":"Maasdijk;Gelderland",
    "iso:country":"NL",
    "sg:address":"Maasdijk 42",
    "sg:city":"Poederoijen",
    "sg:orig_category":"Overheidsdiensten",
    "sg:phone":"+31 418 673 219",
    "sg:postcode":"5307 HP",
    "sg:province":"Gelderland",
    "wof:name":"De Rank",
    "wof:placetype":"venue"
},
  "geometry": {"coordinates":[5.0808401108,51.785484314],"type":"Point"}
}