{
  "type": "Feature",
  "properties": {
    "addr:full":"Burg V Lyndenpk 8 Valburg \u00c5land 6675 AX",
    "addr:housenumber":"8",
    "addr:postcode":"6675 ax",
    "addr:street":"Burg;Lyndenpk;Aaland",
    "iso:country":"NL",
    "sg:address":"Burg V Lyndenpk 8",
    "sg:city":"Valburg",
    "sg:classifiers":[
        {
            "category":"Personal",
            "subcategory":"Nail Salon",
            "type":"Services"
        }
    ],
    "sg:phone":"+31 488 431 939",
    "sg:postcode":"6675 AX",
    "sg:province":"\u00c5land",
    "sg:tags":[
        "pedicure"
    ],
    "wof:name":"Bugter, Maureen",
    "wof:placetype":"venue"
},
  "geometry": {"coordinates":[20.217291,60.19825],"type":"Point"}
}