{
  "type": "Feature",
  "properties": {
    "addr:full":"Nieuwestad 150 Leeuwarden Friesland 8911 DB",
    "addr:housenumber":"150",
    "addr:postcode":"8911 db",
    "addr:street":"Nieuwestad",
    "iso:country":"NL",
    "sg:address":"Nieuwestad 150",
    "sg:city":"Leeuwarden",
    "sg:orig_category":"Bloemen En Planten",
    "sg:phone":"+31 58 215 0740",
    "sg:postcode":"8911 DB",
    "sg:province":"Friesland",
    "wof:name":"Fleurshop",
    "wof:placetype":"venue"
},
  "geometry": {"coordinates":[5.79586,53.200825],"type":"Point"}
}