{
  "type": "Feature",
  "properties": {
    "iso:country":"NL",
    "sg:address":"Middenstr 60",
    "sg:city":"Weesp",
    "sg:orig_category":"Meubelstoffering",
    "sg:phone":"+31 294 414 932",
    "sg:postcode":"1381 XE",
    "sg:province":"North Holland",
    "wof:name":"Meenink",
    "wof:placetype":"venue"
},
  "geometry": {"coordinates":[5.044166,52.306229],"type":"Point"}
}