{
  "type": "Feature",
  "properties": {
    "addr:full":"Middenweg 200A Heerhugowaard North Holland 1701 GG",
    "addr:housenumber":"200a",
    "addr:postcode":"1701 gg",
    "addr:street":"Middenweg",
    "iso:country":"NL",
    "sg:address":"Middenweg 200A",
    "sg:city":"Heerhugowaard",
    "sg:orig_category":"Bloemen And Planten",
    "sg:phone":"+31 72 574 2152",
    "sg:postcode":"1701 GG",
    "sg:province":"North Holland",
    "wof:name":"Bloemenhuis Sandra",
    "wof:placetype":"venue"
},
  "geometry": {"coordinates":[4.827522,52.665195],"type":"Point"}
}