{
  "type": "Feature",
  "properties": {
    "addr:full":"Zuiderdorpstraat 3 Velsen-Zuid Noord-Holland 1981 BG",
    "addr:housenumber":"3",
    "addr:postcode":"1981",
    "addr:street":"Zuiderdorpstraat",
    "iso:country":"NL",
    "sg:address":"Zuiderdorpstraat 3",
    "sg:city":"Velsen-Zuid",
    "sg:orig_category":"Advocaten And Juridische Adviseurs",
    "sg:phone":"+31 255 538 106",
    "sg:postcode":"1981 BG",
    "sg:province":"Noord-Holland",
    "wof:name":"Allaw Bv",
    "wof:placetype":"venue"
},
  "geometry": {"coordinates":[4.647621,52.461857],"type":"Point"}
}