{
  "type": "Feature",
  "properties": {
    "addr:full":"Polderkade 8 Waddinxveen Zuid-Holland 2742 KW",
    "addr:housenumber":"8",
    "addr:postcode":"2742 kw",
    "addr:street":"Polderkade",
    "iso:country":"NL",
    "sg:address":"Polderkade 8",
    "sg:city":"Waddinxveen",
    "sg:orig_category":"Geluidsinstallaties - Verhuur",
    "sg:phone":"+31 182 619 982",
    "sg:postcode":"2742 KW",
    "sg:province":"Zuid-Holland",
    "wof:name":"Euroflash",
    "wof:placetype":"venue"
},
  "geometry": {"coordinates":[4.639775,52.046844],"type":"Point"}
}