{
  "type": "Feature",
  "properties": {
    "addr:full":"Hoofdstr 45 Ossenzyl Overijssel 8376 HD",
    "addr:housenumber":"45",
    "addr:postcode":"8376 hd",
    "addr:street":"Hoofdstr;Overijssel",
    "iso:country":"NL",
    "sg:address":"Hoofdstr 45",
    "sg:city":"Ossenzyl",
    "sg:orig_category":"Land- En Tuinbouw - Mechanisatie",
    "sg:phone":"+31 561 477 284",
    "sg:postcode":"8376 HD",
    "sg:province":"Overijssel",
    "wof:name":"Rotink Vof",
    "wof:placetype":"venue"
},
  "geometry": {"coordinates":[5.917863,52.808464],"type":"Point"}
}