{
  "type": "Feature",
  "properties": {
    "addr:full":"Thijmstraat 9 A Eindhoven Noord-Brabant 5643 DW",
    "addr:housenumber":"9 a",
    "addr:postcode":"5643 dw",
    "addr:street":"Thijmstraat",
    "iso:country":"NL",
    "sg:address":"Thijmstraat 9 A",
    "sg:city":"Eindhoven",
    "sg:orig_category":"Muziekinstrumenten",
    "sg:phone":"+31 40 211 9776",
    "sg:postcode":"5643 DW",
    "sg:province":"Noord-Brabant",
    "wof:name":"Peters Muziekinstrumenten",
    "wof:placetype":"venue"
},
  "geometry": {"coordinates":[5.496701,51.419472],"type":"Point"}
}