{
  "type": "Feature",
  "properties": {
    "addr:full":"Hoofdstr 44 Diever Provincie Drenthe 7981 AB",
    "addr:housenumber":"44",
    "addr:postcode":"7981 ab",
    "addr:street":"Hoofdstr;Provincie Drenthe",
    "iso:country":"NL",
    "sg:address":"Hoofdstr 44",
    "sg:city":"Diever",
    "sg:orig_category":"Fietsen En Bromfietsen Verhuur",
    "sg:phone":"+31 521 593 085",
    "sg:postcode":"7981 AB",
    "sg:province":"Provincie Drenthe",
    "wof:name":"Kleijberg, Tweewielercentrum",
    "wof:placetype":"venue"
},
  "geometry": {"coordinates":[6.315739,52.855743],"type":"Point"}
}