{
  "type": "Feature",
  "properties": {
    "addr:full":"Nw Wetering 245 Hoogvliet Rt Zuid-Holland 3194 TB",
    "addr:housenumber":"245",
    "addr:postcode":"rt;3194 tb",
    "addr:street":"Nw Wetering",
    "iso:country":"NL",
    "sg:address":"Nw Wetering 245",
    "sg:city":"Hoogvliet Rt",
    "sg:orig_category":"Administratie- En Boekhoudkantoren",
    "sg:phone":"+31 10 416 2564",
    "sg:postcode":"3194 TB",
    "sg:province":"Zuid-Holland",
    "wof:name":"Lange & Partn, De",
    "wof:placetype":"venue"
},
  "geometry": {"coordinates":[4.369455,51.866936],"type":"Point"}
}