{
  "type": "Feature",
  "properties": {
    "addr:full":"Broekheurnerwg 13B Haaksbergen Overijssel 7481 PX",
    "addr:housenumber":"13b",
    "addr:postcode":"7481 px",
    "addr:street":"Broekheurnerwg",
    "iso:country":"NL",
    "sg:address":"Broekheurnerwg 13B",
    "sg:city":"Haaksbergen",
    "sg:orig_category":"Administratie- En Boekhoudkantoren",
    "sg:phone":"+31 53 569 6769",
    "sg:postcode":"7481 PX",
    "sg:province":"Overijssel",
    "wof:name":"Hartgerink",
    "wof:placetype":"venue"
},
  "geometry": {"coordinates":[6.827152,52.146748],"type":"Point"}
}