{
  "type": "Feature",
  "properties": {
    "addr:full":"Langakker 1 Boxtel Noord-Brabant 5283 TE",
    "addr:housenumber":"1",
    "addr:postcode":"5283 te",
    "addr:street":"Langakker",
    "iso:country":"NL",
    "sg:address":"Langakker 1",
    "sg:city":"Boxtel",
    "sg:orig_category":"Koeriersdiensten",
    "sg:phone":"+31 411 674 806",
    "sg:postcode":"5283 TE",
    "sg:province":"Noord-Brabant",
    "wof:name":"De Koerier Boxtel",
    "wof:placetype":"venue"
},
  "geometry": {"coordinates":[5.326722,51.595211],"type":"Point"}
}