{
  "type": "Feature",
  "properties": {
    "addr:full":"Bredasebaan 37 Bladel North Brabant 5531 NC",
    "addr:housenumber":"37",
    "addr:postcode":"5531 nc",
    "addr:street":"Bredasebaan",
    "iso:country":"NL",
    "sg:address":"Bredasebaan 37",
    "sg:city":"Bladel",
    "sg:orig_category":"Huifkarren - Verhuur En Verkoop",
    "sg:phone":"+31 497 385 477",
    "sg:postcode":"5531 NC",
    "sg:province":"North Brabant",
    "wof:name":"Maandonkshoeve",
    "wof:placetype":"venue"
},
  "geometry": {"coordinates":[5.236912,51.34417],"type":"Point"}
}