{
  "type": "Feature",
  "properties": {
    "addr:full":"Klaverblad 48 Halsteren Noord-Brabant 4661 NC",
    "addr:housenumber":"48",
    "addr:postcode":"4661 nc",
    "addr:street":"Klaverblad",
    "iso:country":"NL",
    "sg:address":"Klaverblad 48",
    "sg:city":"Halsteren",
    "sg:orig_category":"Adviesbureaus",
    "sg:phone":"+31 164 682 370",
    "sg:postcode":"4661 NC",
    "sg:province":"Noord-Brabant",
    "wof:name":"Amec",
    "wof:placetype":"venue"
},
  "geometry": {"coordinates":[4.27836,51.524231],"type":"Point"}
}