{
  "type": "Feature",
  "properties": {
    "addr:full":"Tjalkstr 3 Lemelerveld NL.08 8152 CM",
    "addr:housenumber":"3;nl.08",
    "addr:postcode":"8152 cm",
    "addr:street":"Tjalkstr",
    "iso:country":"NL",
    "sg:address":"Tjalkstr 3",
    "sg:city":"Lemelerveld",
    "sg:orig_category":"Sportverenigingen En Ontspannings- Verenigingen",
    "sg:phone":"+31 572 372 917",
    "sg:postcode":"8152 CM",
    "sg:province":"NL.08",
    "wof:name":"Ewijk Lhc Handbalver Van",
    "wof:placetype":"venue"
},
  "geometry": {"coordinates":[6.329578,52.445671],"type":"Point"}
}