{
  "type": "Feature",
  "properties": {
    "addr:full":"Kakertswg 124 Landgraaf Limburg 6371 GE",
    "addr:housenumber":"124",
    "addr:postcode":"6371",
    "iso:country":"NL",
    "sg:address":"Kakertswg 124",
    "sg:city":"Landgraaf",
    "sg:orig_category":"Verenigingen En Stichtingen",
    "sg:phone":"+31 45 531 2333",
    "sg:postcode":"6371 GE",
    "sg:province":"Limburg",
    "wof:name":"Ehbo",
    "wof:placetype":"venue"
},
  "geometry": {"coordinates":[6.005938,50.903088],"type":"Point"}
}