{
  "type": "Feature",
  "properties": {
    "iso:country":"NL",
    "sg:address":"Reaumurstraat 3",
    "sg:city":"Terneuzen",
    "sg:classifiers":[
        {
            "category":"Fast Food",
            "type":"Food & Drink"
        }
    ],
    "sg:phone":"+31 115 648 557",
    "sg:postcode":"4532 KJ",
    "sg:province":"Zeeland",
    "sg:tags":[
        "afhaal",
        "restaurant"
    ],
    "wof:name":"M.J. De Braal-Bijman",
    "wof:placetype":"venue"
},
  "geometry": {"coordinates":[3.854367,51.331776],"type":"Point"}
}