{
  "type": "Feature",
  "properties": {
    "addr:full":"Waver 51A Ouderkerk Amstel North Holland 1191 KJ",
    "addr:housenumber":"51a",
    "addr:postcode":"1191 kj",
    "addr:street":"Waver;Amstel",
    "iso:country":"NL",
    "sg:address":"Waver 51A",
    "sg:city":"Ouderkerk Amstel",
    "sg:orig_category":"Grondwerken",
    "sg:phone":"+31 294 283 683",
    "sg:postcode":"1191 KJ",
    "sg:province":"North Holland",
    "wof:name":"Erkelens, J J E F",
    "wof:placetype":"venue"
},
  "geometry": {"coordinates":[4.923879,52.266125],"type":"Point"}
}