{
  "type": "Feature",
  "properties": {
    "iso:country":"NL",
    "sg:address":"A Frankstr 2",
    "sg:city":"Lisse",
    "sg:classifiers":[
        {
            "category":"Professional",
            "subcategory":"Management & Consulting",
            "type":"Services"
        }
    ],
    "sg:phone":"+31 252 418 689",
    "sg:postcode":"2162 JP",
    "sg:province":"Zuid-Holland",
    "sg:tags":[
        "relation",
        "adviesbureaus",
        "public"
    ],
    "wof:name":"X-Pr Lisse Bv",
    "wof:placetype":"venue"
},
  "geometry": {"coordinates":[4.553399,52.241589],"type":"Point"}
}