{
  "type": "Feature",
  "properties": {
    "addr:full":"Paradijslaan 24 Eindhoven North Brabant 5611 KN",
    "addr:housenumber":"24",
    "addr:postcode":"5611 kn",
    "addr:street":"Paradijslaan",
    "iso:country":"NL",
    "sg:address":"Paradijslaan 24",
    "sg:city":"Eindhoven",
    "sg:orig_category":"Werving And Selectie Van Vast Personeel",
    "sg:phone":"+31 40 246 8056",
    "sg:postcode":"5611 KN",
    "sg:province":"North Brabant",
    "wof:name":"Limbourg & Partners Bv",
    "wof:placetype":"venue"
},
  "geometry": {"coordinates":[5.4780888557,51.4351844788],"type":"Point"}
}