{
  "type": "Feature",
  "properties": {
    "addr:full":"Falckstr 53 Amsterdam Noord-Holland 1017 VV",
    "addr:housenumber":"53",
    "addr:postcode":"1017 vv",
    "addr:street":"Falckstr",
    "iso:country":"NL",
    "sg:address":"Falckstr 53",
    "sg:city":"Amsterdam",
    "sg:orig_category":"Verenigingen En Stichtingen",
    "sg:phone":"+31 20 427 3752",
    "sg:postcode":"1017 VV",
    "sg:province":"Noord-Holland",
    "wof:name":"Uitgeverij, De",
    "wof:placetype":"venue"
},
  "geometry": {"coordinates":[4.897669,52.360806],"type":"Point"}
}