{
  "type": "Feature",
  "properties": {
    "iso:country":"NL",
    "sg:address":"J Ligthartpln 26",
    "sg:city":"Zeist",
    "sg:orig_category":"Adviesbureaus Bedrijfsorganisatie",
    "sg:phone":"+31 30 699 2071",
    "sg:postcode":"3706 VD",
    "sg:province":"Utrecht",
    "wof:name":"Esobee",
    "wof:placetype":"venue"
},
  "geometry": {"coordinates":[5.220739,52.101727],"type":"Point"}
}