{
  "type": "Feature",
  "properties": {
    "iso:country":"NL",
    "sg:address":"Plesmanwg 16",
    "sg:city":"Almelo",
    "sg:classifiers":[
        {
            "category":"Retail",
            "subcategory":"Auto Repair",
            "type":"Services"
        }
    ],
    "sg:phone":"+31 546 870 200",
    "sg:postcode":"7602 PE",
    "sg:province":"Overijssel",
    "sg:tags":[
        "garage"
    ],
    "wof:name":"Hondebrink, H",
    "wof:placetype":"venue"
},
  "geometry": {"coordinates":[6.641107,52.371624],"type":"Point"}
}