{
  "type": "Feature",
  "properties": {
    "addr:full":"Kanaalstraat 205 Lisse Zuid-Holland 2161 JH",
    "addr:housenumber":"205",
    "addr:postcode":"2161 jh",
    "addr:street":"Kanaalstraat",
    "iso:country":"NL",
    "sg:address":"Kanaalstraat 205",
    "sg:city":"Lisse",
    "sg:orig_category":"Bloemen And Planten Gh",
    "sg:phone":"+31 252 417 115",
    "sg:postcode":"2161 JH",
    "sg:province":"Zuid-Holland",
    "wof:name":"J.P.W. Schoone",
    "wof:placetype":"venue"
},
  "geometry": {"coordinates":[4.565408,52.257385],"type":"Point"}
}