{
  "type": "Feature",
  "properties": {
    "addr:full":"Geleenstr 34 Amsterdam Noord-Holland 1078 LG",
    "addr:housenumber":"34",
    "addr:postcode":"1078 lg",
    "addr:street":"Geleenstr",
    "iso:country":"NL",
    "sg:address":"Geleenstr 34",
    "sg:city":"Amsterdam",
    "sg:orig_category":"Acupunctuur",
    "sg:phone":"+31 20 676 0517",
    "sg:postcode":"1078 LG",
    "sg:province":"Noord-Holland",
    "sg:website":"http://www.aikikaiamsterdam.nl",
    "wof:name":"Joyce Vlaarkamp",
    "wof:placetype":"venue"
},
  "geometry": {"coordinates":[4.893256,52.344398],"type":"Point"}
}