{
  "type": "Feature",
  "properties": {
    "addr:full":"Schubertlaan 21 Groningen Groningen 9722 LA",
    "addr:housenumber":"21",
    "addr:postcode":"9722 la",
    "addr:street":"Schubertlaan",
    "iso:country":"NL",
    "sg:address":"Schubertlaan 21",
    "sg:city":"Groningen",
    "sg:orig_category":"Vertaal- And Tolkenbureaus",
    "sg:phone":"+31 50 525 7032",
    "sg:postcode":"9722 LA",
    "sg:province":"Groningen",
    "wof:name":"Vertaalbureau A J Winsemius",
    "wof:placetype":"venue"
},
  "geometry": {"coordinates":[6.590878,53.198112],"type":"Point"}
}