{
  "type": "Feature",
  "properties": {
    "addr:full":"Klaverstr 24 Dokkum Provincie Friesland 9101 EA",
    "addr:housenumber":"24",
    "addr:postcode":"9101 ea",
    "addr:street":"Klaverstr;Provincie Friesland",
    "iso:country":"NL",
    "sg:address":"Klaverstr 24",
    "sg:city":"Dokkum",
    "sg:orig_category":"Beeldende Kunstenaars",
    "sg:phone":"+31 519 297 097",
    "sg:postcode":"9101 EA",
    "sg:province":"Provincie Friesland",
    "sg:website":"http://www.nunique.com",
    "wof:name":"Nunique",
    "wof:placetype":"venue"
},
  "geometry": {"coordinates":[6.003086,53.318966],"type":"Point"}
}