{
  "type": "Feature",
  "properties": {
    "addr:full":"J Vd Waalssngl 61 Apeldoorn Gelderland 7321 JN",
    "addr:housenumber":"61",
    "addr:postcode":"7321 jn",
    "addr:street":"Gelderland",
    "iso:country":"NL",
    "sg:address":"J Vd Waalssngl 61",
    "sg:city":"Apeldoorn",
    "sg:orig_category":"Adviesbureaus Bedrijfsorganisatie",
    "sg:phone":"+31 55 360 2642",
    "sg:postcode":"7321 JN",
    "sg:province":"Gelderland",
    "wof:name":"Halm Bv",
    "wof:placetype":"venue"
},
  "geometry": {"coordinates":[5.98598,52.21265],"type":"Point"}
}