{
  "type": "Feature",
  "properties": {
    "addr:full":"Atalanta 110 Zeewolde NL. 3892 EJ",
    "addr:housenumber":"110",
    "addr:postcode":"3892 ej",
    "addr:street":"Atalanta;Nl.",
    "iso:country":"NL",
    "sg:address":"Atalanta 110",
    "sg:city":"Zeewolde",
    "sg:orig_category":"Kantoor- En Secretariaatsservice",
    "sg:phone":"+31 36 522 1048",
    "sg:postcode":"3892 EJ",
    "sg:province":"NL.",
    "sg:website":"http://www.uitdebrand.nl",
    "wof:name":"Uit De Brand",
    "wof:placetype":"venue"
},
  "geometry": {"coordinates":[5.5479130745,52.3216438293],"type":"Point"}
}