{
  "type": "Feature",
  "properties": {
    "addr:full":"Winkelcentrum 6 Etten Leur North Brabant 4873 AA",
    "addr:housenumber":"6",
    "addr:postcode":"4873 aa",
    "addr:street":"Winkelcentrum",
    "iso:country":"NL",
    "sg:address":"Winkelcentrum 6",
    "sg:city":"Etten Leur",
    "sg:orig_category":"Linnenshops",
    "sg:phone":"+31 76 501 7337",
    "sg:postcode":"4873 AA",
    "sg:province":"North Brabant",
    "wof:name":"Linnenboetiek, De",
    "wof:placetype":"venue"
},
  "geometry": {"coordinates":[4.63551,51.568321],"type":"Point"}
}