{
  "type": "Feature",
  "properties": {
    "addr:full":"Bladergroenstraat 2 Tiel Gelderland 4002 AZ",
    "addr:housenumber":"2",
    "addr:postcode":"4002",
    "addr:street":"Bladergroenstraat;Gelderland",
    "iso:country":"NL",
    "sg:address":"Bladergroenstraat 2",
    "sg:city":"Tiel",
    "sg:orig_category":"Boekhouders",
    "sg:phone":"+31 344 619 728",
    "sg:postcode":"4002 AZ",
    "sg:province":"Gelderland",
    "wof:name":"Administratie- Assurantiekantoor M.Wille",
    "wof:placetype":"venue"
},
  "geometry": {"coordinates":[5.424753,51.894543],"type":"Point"}
}