{
  "type": "Feature",
  "properties": {
    "addr:full":"Appelsteeg 1 Alkmaar North Holland 1811 NA",
    "addr:housenumber":"1",
    "addr:postcode":"1811 na",
    "addr:street":"Appelsteeg",
    "iso:country":"NL",
    "sg:address":"Appelsteeg 1",
    "sg:city":"Alkmaar",
    "sg:orig_category":"Glaszetten",
    "sg:phone":"+31 72 515 2160",
    "sg:postcode":"1811 NA",
    "sg:province":"North Holland",
    "wof:name":"De Alkmaarse Glazenier",
    "wof:placetype":"venue"
},
  "geometry": {"coordinates":[4.751627,52.630775],"type":"Point"}
}