{
  "type": "Feature",
  "properties": {
    "addr:full":"Herenstr 103 Wateringen Zuid-Holland 2291 BE",
    "addr:housenumber":"103",
    "addr:postcode":"2291",
    "iso:country":"NL",
    "sg:address":"Herenstr 103",
    "sg:city":"Wateringen",
    "sg:orig_category":"Watersportartikelen",
    "sg:phone":"+31 174 295 350",
    "sg:postcode":"2291 BE",
    "sg:province":"Zuid-Holland",
    "sg:website":"http://www.johnmeeuwisse.nl",
    "wof:name":"Meeuw, De",
    "wof:placetype":"venue"
},
  "geometry": {"coordinates":[4.2785692215,52.0245323181],"type":"Point"}
}