{
  "type": "Feature",
  "properties": {
    "addr:full":"Hogesteeg 5 Rhenen Utrecht 3911 VT",
    "addr:housenumber":"5",
    "addr:postcode":"3911",
    "addr:street":"Hogesteeg",
    "iso:country":"NL",
    "sg:address":"Hogesteeg 5",
    "sg:city":"Rhenen",
    "sg:orig_category":"Goederenvervoer Over De Weg",
    "sg:phone":"+31 317 615 099",
    "sg:postcode":"3911 VT",
    "sg:province":"Utrecht",
    "wof:name":"Hendriks",
    "wof:placetype":"venue"
},
  "geometry": {"coordinates":[5.590249,51.973835],"type":"Point"}
}