{
  "type": "Feature",
  "properties": {
    "addr:full":"Hoofdwg 96 Blyham Groningen 9697 NN",
    "addr:housenumber":"96",
    "addr:postcode":"9697 nn",
    "addr:street":"Hoofdwg",
    "iso:country":"NL",
    "sg:address":"Hoofdwg 96",
    "sg:city":"Blyham",
    "sg:orig_category":"Orthopedische Artikelen",
    "sg:phone":"+31 597 561 681",
    "sg:postcode":"9697 NN",
    "sg:province":"Groningen",
    "wof:name":"Boekweg",
    "wof:placetype":"venue"
},
  "geometry": {"coordinates":[7.0753660202,53.104850769],"type":"Point"}
}