{
  "type": "Feature",
  "properties": {
    "addr:full":"Leijsenhoek 34 Oosterhout Nb Noord-Brabant 4901 EV",
    "addr:housenumber":"34",
    "addr:postcode":"4901 ev",
    "addr:street":"Leijsenhoek",
    "iso:country":"NL",
    "sg:address":"Leijsenhoek 34",
    "sg:city":"Oosterhout Nb",
    "sg:orig_category":"Meubelzaken, Woning- And Keukeninrichting",
    "sg:phone":"+31 162 454 438",
    "sg:postcode":"4901 EV",
    "sg:province":"Noord-Brabant",
    "wof:name":"Woninginrichting Victor Boeren Oosterhout Bv",
    "wof:placetype":"venue"
},
  "geometry": {"coordinates":[4.865191,51.644989],"type":"Point"}
}