{
  "type": "Feature",
  "properties": {
    "addr:full":"Overakkerstr 204 Breda North Brabant 4834 XP",
    "addr:housenumber":"204",
    "addr:postcode":"4834 xp",
    "iso:country":"NL",
    "sg:address":"Overakkerstr 204",
    "sg:city":"Breda",
    "sg:orig_category":"Verenigingsgebouwen",
    "sg:phone":"+31 76 565 0370",
    "sg:postcode":"4834 XP",
    "sg:province":"North Brabant",
    "wof:name":"Gemeenschapshuis Overakker",
    "wof:placetype":"venue"
},
  "geometry": {"coordinates":[4.8017,51.568016],"type":"Point"}
}