{
  "type": "Feature",
  "properties": {
    "addr:full":"Wagenwg 8A Haarlem Noord-Holland 2012 ND",
    "addr:housenumber":"8a",
    "addr:postcode":"2012 nd",
    "addr:street":"Wagenwg",
    "iso:country":"NL",
    "sg:address":"Wagenwg 8A",
    "sg:city":"Haarlem",
    "sg:orig_category":"Kansspelen",
    "sg:phone":"+31 23 532 1931",
    "sg:postcode":"2012 ND",
    "sg:province":"Noord-Holland",
    "wof:name":"Champions",
    "wof:placetype":"venue"
},
  "geometry": {"coordinates":[4.6294322014,52.3742141724],"type":"Point"}
}