{
  "type": "Feature",
  "properties": {
    "addr:full":"Langestraat 32 Winschoten Groningen 9671 PH",
    "addr:housenumber":"32",
    "addr:postcode":"9671",
    "addr:street":"Langestraat",
    "iso:country":"NL",
    "sg:address":"Langestraat 32",
    "sg:city":"Winschoten",
    "sg:orig_category":"Opticiens",
    "sg:phone":"+31 597 421 661",
    "sg:postcode":"9671 PH",
    "sg:province":"Groningen",
    "wof:name":"Pearle Opticiens",
    "wof:placetype":"venue"
},
  "geometry": {"coordinates":[7.0368690491,53.1442451477],"type":"Point"}
}