{
  "type": "Feature",
  "properties": {
    "addr:full":"Provincienbaan 1 Ryen Noord-Brabant 5121 DK",
    "addr:housenumber":"1",
    "addr:postcode":"5121 dk",
    "addr:street":"Provincienbaan",
    "iso:country":"NL",
    "sg:address":"Provincienbaan 1",
    "sg:city":"Ryen",
    "sg:orig_category":"Plafonds",
    "sg:phone":"+31 161 232 623",
    "sg:postcode":"5121 DK",
    "sg:province":"Noord-Brabant",
    "wof:name":"Syco Bv",
    "wof:placetype":"venue"
},
  "geometry": {"coordinates":[4.9197,51.588017],"type":"Point"}
}