{
  "type": "Feature",
  "properties": {
    "addr:full":"Kalkweg 3 Someren Noord-Brabant 5712 TB",
    "addr:housenumber":"3",
    "addr:postcode":"5712 tb",
    "addr:street":"Kalkweg",
    "iso:country":"NL",
    "sg:address":"Kalkweg 3",
    "sg:city":"Someren",
    "sg:orig_category":"Bloemen And Planten",
    "sg:phone":"+31 493 496 969",
    "sg:postcode":"5712 TB",
    "sg:province":"Noord-Brabant",
    "wof:name":"Plantenkwekerij M. Loeffen",
    "wof:placetype":"venue"
},
  "geometry": {"coordinates":[5.74231,51.363853],"type":"Point"}
}