{
  "type": "Feature",
  "properties": {
    "addr:full":"Nieuwstr 74 Purmerend North Holland 1441 CN",
    "addr:housenumber":"74",
    "addr:postcode":"1441 cn",
    "addr:street":"Nieuwstr",
    "iso:country":"NL",
    "sg:address":"Nieuwstr 74",
    "sg:city":"Purmerend",
    "sg:orig_category":"Verzekeringen - Verzekeringskantoren",
    "sg:phone":"+31 299 436 293",
    "sg:postcode":"1441 CN",
    "sg:province":"North Holland",
    "sg:website":"http://www.sopar.nl",
    "wof:name":"Sopar/Woud/Kauwen",
    "wof:placetype":"venue"
},
  "geometry": {"coordinates":[4.947001,52.507736],"type":"Point"}
}