{
  "type": "Feature",
  "properties": {
    "addr:full":"B Hurenkampstr 21 Wilp Gld Gelderland 7384 BA",
    "addr:housenumber":"21",
    "addr:postcode":"7384 ba",
    "addr:street":"Gld Gelderland",
    "iso:country":"NL",
    "sg:address":"B Hurenkampstr 21",
    "sg:city":"Wilp Gld",
    "sg:orig_category":"Metselwerken",
    "sg:phone":"+31 6 20626733",
    "sg:postcode":"7384 BA",
    "sg:province":"Gelderland",
    "wof:name":"Gero Vof",
    "wof:placetype":"venue"
},
  "geometry": {"coordinates":[6.150088,52.219906],"type":"Point"}
}