{
  "type": "Feature",
  "properties": {
    "iso:country":"NL",
    "sg:address":"Zomerklokje 15",
    "sg:city":"Breukelen Ut",
    "sg:orig_category":"Verzekeringen",
    "sg:phone":"+31 346 266 443",
    "sg:postcode":"3621 TA",
    "sg:province":"Utrecht",
    "wof:name":"Ijsbrandy & Partners Bv",
    "wof:placetype":"venue"
},
  "geometry": {"coordinates":[5.007111,52.166492],"type":"Point"}
}