{
  "type": "Feature",
  "properties": {
    "iso:country":"NL",
    "sg:address":"Barnsteenhorst 472",
    "sg:city":"S Gravenhage",
    "sg:orig_category":"Psychologen",
    "sg:phone":"+31 70 347 5822",
    "sg:postcode":"2592 ET",
    "sg:province":"Zuid-Holland",
    "wof:name":"Fiege",
    "wof:placetype":"venue"
},
  "geometry": {"coordinates":[4.35298,52.089199],"type":"Point"}
}