{
  "type": "Feature",
  "properties": {
    "iso:country":"NL",
    "sg:address":"Landaulettestr 2A",
    "sg:city":"Rotterdam",
    "sg:orig_category":"Kappers",
    "sg:phone":"+31 10 453 1930",
    "sg:postcode":"3063 NR",
    "sg:province":"Zuid-Holland",
    "wof:name":"Strada",
    "wof:placetype":"venue"
},
  "geometry": {"coordinates":[4.536952,51.909248],"type":"Point"}
}