{
  "type": "Feature",
  "properties": {
    "addr:full":"Marco Polostraat 173 Amsterdam Noord-Holland 1057 WJ",
    "addr:housenumber":"173",
    "addr:postcode":"1057 wj",
    "addr:street":"Marco Polostraat",
    "iso:country":"NL",
    "sg:address":"Marco Polostraat 173",
    "sg:city":"Amsterdam",
    "sg:orig_category":"Werving And Selectie Van Tijdelijk Personeel And Uitzendkantoren",
    "sg:phone":"+31 20 616 6665",
    "sg:postcode":"1057 WJ",
    "sg:province":"Noord-Holland",
    "wof:name":"R&R",
    "wof:placetype":"venue"
},
  "geometry": {"coordinates":[4.8556108475,52.369468689],"type":"Point"}
}