{
  "type": "Feature",
  "properties": {
    "addr:full":"Wageningseln 66 Veenendaal Utrecht 3903 LA",
    "addr:housenumber":"66",
    "addr:postcode":"3903 la",
    "addr:street":"Wageningseln",
    "iso:country":"NL",
    "sg:address":"Wageningseln 66",
    "sg:city":"Veenendaal",
    "sg:orig_category":"Meubelen",
    "sg:phone":"+31 318 542 566",
    "sg:postcode":"3903 LA",
    "sg:province":"Utrecht",
    "sg:website":"http://www.poppeliers.com",
    "wof:name":"Poppeliers, Meubelen",
    "wof:placetype":"venue"
},
  "geometry": {"coordinates":[5.580484,52.006096],"type":"Point"}
}