{
  "type": "Feature",
  "properties": {
    "addr:full":"Willem Ruysplein 26 Zwijndrecht South Holland 3333 BX",
    "addr:housenumber":"26",
    "addr:postcode":"3333 bx",
    "addr:street":"Willem Ruysplein",
    "iso:country":"NL",
    "sg:address":"Willem Ruysplein 26",
    "sg:city":"Zwijndrecht",
    "sg:classifiers":[
        {
            "category":"Fast Food",
            "type":"Food & Drink"
        }
    ],
    "sg:phone":"+31 78 619 6239",
    "sg:postcode":"3333 BX",
    "sg:province":"South Holland",
    "sg:tags":[
        "afhaal",
        "restaurant"
    ],
    "wof:name":"Netanya/La Toscana",
    "wof:placetype":"venue"
},
  "geometry": {"coordinates":[4.6328,51.807816],"type":"Point"}
}