{
  "type": "Feature",
  "properties": {
    "iso:country":"NL",
    "sg:address":"Hoofdstr 147",
    "sg:city":"Driebergen Rysenb",
    "sg:orig_category":"Loodgieters",
    "sg:phone":"+31 343 512 616",
    "sg:postcode":"3971 KJ",
    "sg:province":"Utrecht",
    "wof:name":"Blooi, W",
    "wof:placetype":"venue"
},
  "geometry": {"coordinates":[5.285246,52.051144],"type":"Point"}
}