{
  "type": "Feature",
  "properties": {
    "addr:full":"Economiestraat 13 Hoensbroek Limburg 6433 KC",
    "addr:housenumber":"13",
    "addr:postcode":"6433 kc",
    "addr:street":"Economiestraat",
    "iso:country":"NL",
    "sg:address":"Economiestraat 13",
    "sg:city":"Hoensbroek",
    "sg:orig_category":"Gebouwenafwerking, Renovaties And Reiniging",
    "sg:phone":"+31 45 522 2979",
    "sg:postcode":"6433 KC",
    "sg:province":"Limburg",
    "wof:name":"Stubbe Glas- En Gevelreiniging",
    "wof:placetype":"venue"
},
  "geometry": {"coordinates":[5.931557,50.905632],"type":"Point"}
}