{
  "type": "Feature",
  "properties": {
    "addr:full":"Somerweide 27 Breda North Brabant 4824 EV",
    "addr:housenumber":"27",
    "addr:postcode":"4824 ev",
    "addr:street":"Somerweide",
    "iso:country":"NL",
    "sg:address":"Somerweide 27",
    "sg:city":"Breda",
    "sg:orig_category":"Loodgieterswerk, Verwarming And Sanitaire Installaties",
    "sg:phone":"+31 76 541 0636",
    "sg:postcode":"4824 EV",
    "sg:province":"North Brabant",
    "wof:name":"Mwd Breda",
    "wof:placetype":"venue"
},
  "geometry": {"coordinates":[4.747777,51.611374],"type":"Point"}
}