{
  "type": "Feature",
  "properties": {
    "iso:country":"NL",
    "sg:address":"Rijperweg 38A",
    "sg:city":"Sint Maarten",
    "sg:orig_category":"Loodgieterswerk, Verwarming And Sanitaire Installaties",
    "sg:phone":"+31 226 392 931",
    "sg:postcode":"1744 HL",
    "sg:province":"Noord-Holland",
    "wof:name":"Dijkstra Schilder- En Afwerkingsbedrijf",
    "wof:placetype":"venue"
},
  "geometry": {"coordinates":[4.747696,52.751621],"type":"Point"}
}