{
  "type": "Feature",
  "properties": {
    "addr:full":"Bloemluststraat 74 Wassenaar South Holland 2242 VN",
    "addr:housenumber":"74",
    "addr:postcode":"2242 vn",
    "addr:street":"Bloemluststraat",
    "iso:country":"NL",
    "sg:address":"Bloemluststraat 74",
    "sg:city":"Wassenaar",
    "sg:orig_category":"Loodgieterswerk, Verwarming And Sanitaire Installaties",
    "sg:phone":"+31 70 511 1501",
    "sg:postcode":"2242 VN",
    "sg:province":"South Holland",
    "wof:name":"B.W.M. Wisse",
    "wof:placetype":"venue"
},
  "geometry": {"coordinates":[4.393779,52.150299],"type":"Point"}
}