{
  "type": "Feature",
  "properties": {
    "addr:full":"Beethovenstraat 7 Amsterdam Noord-Holland 1077 HK",
    "addr:housenumber":"7",
    "addr:postcode":"1077 hk",
    "addr:street":"Beethovenstraat",
    "iso:country":"NL",
    "sg:address":"Beethovenstraat 7",
    "sg:city":"Amsterdam",
    "sg:orig_category":"Ambassades And Consulaten",
    "sg:phone":"+31 20 676 4844",
    "sg:postcode":"1077 HK",
    "sg:province":"Noord-Holland",
    "wof:name":"Consulaat Van Haiti",
    "wof:placetype":"venue"
},
  "geometry": {"coordinates":[4.878304,52.349869],"type":"Point"}
}