{
  "type": "Feature",
  "properties": {
    "addr:full":"Dorpsstr 18 Bleiswyk South Holland 2665 BJ",
    "addr:housenumber":"18",
    "addr:postcode":"2665 bj",
    "addr:street":"Dorpsstr",
    "iso:country":"NL",
    "sg:address":"Dorpsstr 18",
    "sg:city":"Bleiswyk",
    "sg:orig_category":"Kappers",
    "sg:phone":"+31 10 521 8682",
    "sg:postcode":"2665 BJ",
    "sg:province":"South Holland",
    "wof:name":"Simone",
    "wof:placetype":"venue"
},
  "geometry": {"coordinates":[4.52967,52.009933],"type":"Point"}
}