{
  "type": "Feature",
  "properties": {
    "addr:full":"Brouwersdk 151 Dordrecht South Holland 3314 GK",
    "addr:housenumber":"151",
    "addr:postcode":"3314 gk",
    "iso:country":"NL",
    "sg:address":"Brouwersdk 151",
    "sg:city":"Dordrecht",
    "sg:orig_category":"Kappers",
    "sg:phone":"+31 78 614 1247",
    "sg:postcode":"3314 GK",
    "sg:province":"South Holland",
    "wof:name":"Peter",
    "wof:placetype":"venue"
},
  "geometry": {"coordinates":[4.659501,51.801247],"type":"Point"}
}