{
  "type": "Feature",
  "properties": {
    "iso:country":"NL",
    "sg:address":"Van Zuijtland 11",
    "sg:city":"Benthuizen",
    "sg:orig_category":"Bloemen And Planten",
    "sg:phone":"+31 79 341 9412",
    "sg:postcode":"2731 GN",
    "sg:province":"Zuid-Holland",
    "wof:name":"W.K. Visser",
    "wof:placetype":"venue"
},
  "geometry": {"coordinates":[4.547525,52.074272],"type":"Point"}
}