{
  "type": "Feature",
  "properties": {
    "addr:full":"Ridderspoor 47 Zwaag Noord-Holland 1689 TG",
    "addr:housenumber":"47",
    "addr:postcode":"1689 tg",
    "addr:street":"Ridderspoor",
    "iso:country":"NL",
    "sg:address":"Ridderspoor 47",
    "sg:city":"Zwaag",
    "sg:orig_category":"Afzuiginstallaties",
    "sg:phone":"+31 229 233 140",
    "sg:postcode":"1689 TG",
    "sg:province":"Noord-Holland",
    "wof:name":"Jawo",
    "wof:placetype":"venue"
},
  "geometry": {"coordinates":[5.042406,52.663372],"type":"Point"}
}