{
  "type": "Feature",
  "properties": {
    "iso:country":"NL",
    "sg:address":"Ridderspoor 47",
    "sg:city":"Zwaag",
    "sg:orig_category":"Afzuiginstallaties",
    "sg:phone":"+31 229 233 140",
    "sg:postcode":"1689 TG",
    "sg:province":"Noord-Holland",
    "wof:name":"Jawo",
    "wof:placetype":"venue"
},
  "geometry": {"coordinates":[5.042406,52.663372],"type":"Point"}
}