{
  "type": "Feature",
  "properties": {
    "iso:country":"NL",
    "sg:address":"Rielerwg 83-85",
    "sg:city":"Deventer",
    "sg:orig_category":"Gelegenheidskleding",
    "sg:phone":"+31 570 624 614",
    "sg:postcode":"7416 ZC",
    "sg:province":"Overijssel",
    "wof:name":"Bessels, Grime Atelier",
    "wof:placetype":"venue"
},
  "geometry": {"coordinates":[6.170653,52.257851],"type":"Point"}
}