{
  "type": "Feature",
  "properties": {
    "addr:full":"Lijnbaansgracht 166 Amsterdam North Holland 1016 VX",
    "addr:housenumber":"166",
    "addr:postcode":"1016 vx",
    "addr:street":"Lijnbaansgracht",
    "iso:country":"NL",
    "sg:address":"Lijnbaansgracht 166",
    "sg:city":"Amsterdam",
    "sg:orig_category":"Dansscholen",
    "sg:phone":"+31 20 627 4245",
    "sg:postcode":"1016 VX",
    "sg:province":"North Holland",
    "wof:name":"Wladimir Dance Studios",
    "wof:placetype":"venue"
},
  "geometry": {"coordinates":[4.877926,52.369934],"type":"Point"}
}