{
  "type": "Feature",
  "properties": {
    "iso:country":"NL",
    "sg:address":"Albrandswaardsedijk 101",
    "sg:city":"Poortugaal",
    "sg:orig_category":"Verzekeringen",
    "sg:phone":"+31 10 501 3937",
    "sg:postcode":"3172 TG",
    "sg:province":"South Holland",
    "wof:name":"P A H Commissaris",
    "wof:placetype":"venue"
},
  "geometry": {"coordinates":[4.398439,51.849148],"type":"Point"}
}