{
  "type": "Feature",
  "properties": {
    "addr:full":"Winkelcentrum 11 Etten-Leur Noord-Brabant 4873 AA",
    "addr:housenumber":"11",
    "addr:postcode":"4873 aa",
    "addr:street":"Winkelcentrum",
    "iso:country":"NL",
    "sg:address":"Winkelcentrum 11",
    "sg:city":"Etten-Leur",
    "sg:orig_category":"Juweliers",
    "sg:phone":"+31 76 501 2941",
    "sg:postcode":"4873 AA",
    "sg:province":"Noord-Brabant",
    "wof:name":"Juwelier Mekes",
    "wof:placetype":"venue"
},
  "geometry": {"coordinates":[4.63559,51.568317],"type":"Point"}
}