{
  "type": "Feature",
  "properties": {
    "addr:full":"Drukkersweg 6 Haarlem Noord-Holland 2031 EE",
    "addr:housenumber":"6",
    "addr:postcode":"2031 ee",
    "addr:street":"Drukkersweg",
    "iso:country":"NL",
    "sg:address":"Drukkersweg 6",
    "sg:city":"Haarlem",
    "sg:orig_category":"Huishoudapparatuur, Televisies And Radio'S",
    "sg:phone":"+31 23 534 3484",
    "sg:postcode":"2031 EE",
    "sg:province":"Noord-Holland",
    "wof:name":"Showtechnic Nederland",
    "wof:placetype":"venue"
},
  "geometry": {"coordinates":[4.660221,52.398811],"type":"Point"}
}