{
  "type": "Feature",
  "properties": {
    "addr:full":"Nuisveen 4 Borger Drenthe 9531 TB",
    "addr:housenumber":"4",
    "addr:postcode":"9531 tb",
    "addr:street":"Nuisveen",
    "iso:country":"NL",
    "sg:address":"Nuisveen 4",
    "sg:city":"Borger",
    "sg:orig_category":"Autokeuringen",
    "sg:phone":"+31 599 236 214",
    "sg:postcode":"9531 TB",
    "sg:province":"Drenthe",
    "wof:name":"Koops Autoschade",
    "wof:placetype":"venue"
},
  "geometry": {"coordinates":[6.776842,52.921345],"type":"Point"}
}