{
  "type": "Feature",
  "properties": {
    "addr:full":"Postbus Arnhem Gelderland 6825 MR",
    "addr:postcode":"6825 mr",
    "addr:street":"Postbus",
    "iso:country":"NL",
    "sg:address":"Postbus",
    "sg:city":"Arnhem",
    "sg:orig_category":"Bedrijfsinventaris Gh",
    "sg:phone":"+31 26 384 3838",
    "sg:postcode":"6825 MR",
    "sg:province":"Gelderland",
    "wof:name":"Gelpa Verpakkingen",
    "wof:placetype":"venue"
},
  "geometry": {"coordinates":[5.96984,51.981522],"type":"Point"}
}