{
  "type": "Feature",
  "properties": {
    "addr:full":"De Passaazje 6 Bergum Provincie Friesland 9251 CX",
    "addr:housenumber":"6",
    "addr:postcode":"9251 cx",
    "addr:street":"De Passaazje;Provincie Friesland",
    "iso:country":"NL",
    "sg:address":"De Passaazje 6",
    "sg:city":"Bergum",
    "sg:orig_category":"Poeliers",
    "sg:phone":"+31 511 469 512",
    "sg:postcode":"9251 CX",
    "sg:province":"Provincie Friesland",
    "wof:name":"Johannes Bosma",
    "wof:placetype":"venue"
},
  "geometry": {"coordinates":[5.992096,53.19212],"type":"Point"}
}