{
  "type": "Feature",
  "properties": {
    "iso:country":"NL",
    "sg:address":"Lomanstraat 66/2",
    "sg:city":"Amsterdam",
    "sg:orig_category":"Artsen And Specialisten",
    "sg:phone":"+31 20 471 3628",
    "sg:postcode":"1075 RE",
    "sg:province":"Noord-Holland",
    "wof:name":"J.E. Pleiter",
    "wof:placetype":"venue"
},
  "geometry": {"coordinates":[4.859154,52.351231],"type":"Point"}
}