{
  "type": "Feature",
  "properties": {
    "iso:country":"NL",
    "sg:address":"Slotlaan 278",
    "sg:city":"Zeist",
    "sg:orig_category":"Damesmodezaken",
    "sg:phone":"+31 30 691 6175",
    "sg:postcode":"3701 GW",
    "sg:province":"Utrecht",
    "wof:name":"Modehuis Vrooland",
    "wof:placetype":"venue"
},
  "geometry": {"coordinates":[5.24771,52.087952],"type":"Point"}
}