{
  "type": "Feature",
  "properties": {
    "addr:full":"3 Decembersngl 12 Venlo Limburg 5922 BD",
    "addr:housenumber":"3;12",
    "addr:postcode":"5922 bd",
    "addr:street":"Decembersngl",
    "iso:country":"NL",
    "sg:address":"3 Decembersngl 12",
    "sg:city":"Venlo",
    "sg:orig_category":"Postkantoren",
    "sg:phone":"+31 77 382 1468",
    "sg:postcode":"5922 BD",
    "sg:province":"Limburg",
    "sg:website":"http://www.postkantoor.nl",
    "wof:name":"Postkantoor",
    "wof:placetype":"venue"
},
  "geometry": {"coordinates":[6.140462,51.373749],"type":"Point"}
}