{
  "type": "Feature",
  "properties": {
    "addr:full":"Hoofdweg 97 Froombosch Groningen 9619 PC",
    "addr:housenumber":"97",
    "addr:postcode":"9619 pc",
    "addr:street":"Hoofdweg",
    "iso:country":"NL",
    "sg:address":"Hoofdweg 97",
    "sg:city":"Froombosch",
    "sg:orig_category":"Meubelreparatie And -Restauratie",
    "sg:phone":"+31 598 393 945",
    "sg:postcode":"9619 PC",
    "sg:province":"Groningen",
    "wof:name":"R Zuur",
    "wof:placetype":"venue"
},
  "geometry": {"coordinates":[6.77701,53.19154],"type":"Point"}
}