{
  "type": "Feature",
  "properties": {
    "iso:country":"NL",
    "sg:address":"Van Hogendorpstraat 45",
    "sg:city":"Rijen",
    "sg:orig_category":"Loodgieterswerk, Verwarming And Sanitaire Installaties",
    "sg:phone":"+31 161 224 262",
    "sg:postcode":"5121 HJ",
    "sg:province":"Noord-Brabant",
    "wof:name":"C.B.M. Bar",
    "wof:placetype":"venue"
},
  "geometry": {"coordinates":[4.915437,51.596573],"type":"Point"}
}