{
  "type": "Feature",
  "properties": {
    "addr:full":"Bantuinweg 43 Rhenen Utrecht 3911 MV",
    "addr:housenumber":"43",
    "addr:postcode":"3911 mv",
    "addr:street":"Bantuinweg",
    "iso:country":"NL",
    "sg:address":"Bantuinweg 43",
    "sg:city":"Rhenen",
    "sg:classifiers":[
        {
            "category":"Education",
            "subcategory":"Preschool",
            "type":"Public Place"
        }
    ],
    "sg:phone":"+31 317 612 161",
    "sg:postcode":"3911 MV",
    "sg:province":"Utrecht",
    "sg:tags":[
        "kleuteronderwijs",
        "basis-"
    ],
    "wof:name":"Openbare Basisschool De Driesprong",
    "wof:placetype":"venue"
},
  "geometry": {"coordinates":[5.563688,51.959316],"type":"Point"}
}