{
  "type": "Feature",
  "properties": {
    "addr:full":"Kerkedijk 7 Bergen Nh Noord-Holland 1862 BD",
    "addr:housenumber":"7",
    "addr:postcode":"1862 bd",
    "addr:street":"Kerkedijk",
    "iso:country":"NL",
    "sg:address":"Kerkedijk 7",
    "sg:city":"Bergen Nh",
    "sg:orig_category":"Diverse Grafische Activiteiten",
    "sg:phone":"+31 72 589 4733",
    "sg:postcode":"1862 BD",
    "sg:province":"Noord-Holland",
    "wof:name":"Dieuwke Groet Grafisch Ontwerpburo",
    "wof:placetype":"venue"
},
  "geometry": {"coordinates":[4.705012,52.67347],"type":"Point"}
}