{
  "type": "Feature",
  "properties": {
    "addr:full":"Hoofdstr 7 Epe Gelderland 8162 AA",
    "addr:housenumber":"7",
    "addr:postcode":"8162 aa",
    "addr:street":"Hoofdstr;Gelderland",
    "iso:country":"NL",
    "sg:address":"Hoofdstr 7",
    "sg:city":"Epe",
    "sg:orig_category":"Kappers",
    "sg:phone":"+31 578 614 020",
    "sg:postcode":"8162 AA",
    "sg:province":"Gelderland",
    "wof:name":"Maassen Hairstyling, F",
    "wof:placetype":"venue"
},
  "geometry": {"coordinates":[5.985044,52.350513],"type":"Point"}
}