{
  "type": "Feature",
  "properties": {
    "iso:country":"NL",
    "sg:address":"Oudegr 245Bis",
    "sg:city":"Utrecht",
    "sg:orig_category":"Artiesten/Gezelschappen",
    "sg:phone":"+31 30 231 0397",
    "sg:postcode":"3511 NL",
    "sg:province":"Utrecht",
    "wof:name":"U-Pop Popservicebureau",
    "wof:placetype":"venue"
},
  "geometry": {"coordinates":[5.115405,52.088932],"type":"Point"}
}