{
  "type": "Feature",
  "properties": {
    "addr:full":"Plantage 88 Lelystad NL. 8212 VG",
    "addr:housenumber":"88",
    "addr:postcode":"8212 vg",
    "addr:street":"Plantage;Nl.",
    "iso:country":"NL",
    "sg:address":"Plantage 88",
    "sg:city":"Lelystad",
    "sg:orig_category":"Meubelreparatie And -Restauratie",
    "sg:phone":"+31 320 227 819",
    "sg:postcode":"8212 VG",
    "sg:province":"NL.",
    "wof:name":"Woningstoffeerdersbedrijf Uniek",
    "wof:placetype":"venue"
},
  "geometry": {"coordinates":[5.501396,52.511208],"type":"Point"}
}