{
  "type": "Feature",
  "properties": {
    "addr:full":"Venraysewg 126 Venlo Limburg 5928 RH",
    "addr:housenumber":"126",
    "addr:postcode":"5928 rh",
    "iso:country":"NL",
    "sg:address":"Venraysewg 126",
    "sg:city":"Venlo",
    "sg:classifiers":[
        {
            "category":"Retail",
            "subcategory":"Storage",
            "type":"Services"
        }
    ],
    "sg:phone":"+31 77 389 7210",
    "sg:postcode":"5928 RH",
    "sg:province":"Limburg",
    "sg:tags":[
        "op-",
        "en",
        "overslagbedrijven"
    ],
    "wof:name":"Laadgoed Bv",
    "wof:placetype":"venue"
},
  "geometry": {"coordinates":[6.148613,51.37785],"type":"Point"}
}