{
  "type": "Feature",
  "properties": {
    "addr:full":"Zwolseweg 221 Apeldoorn Gelderland 7315 GK",
    "addr:housenumber":"221",
    "addr:postcode":"7315 gk",
    "addr:street":"Zwolseweg;Gelderland",
    "iso:country":"NL",
    "sg:address":"Zwolseweg 221",
    "sg:city":"Apeldoorn",
    "sg:classifiers":[
        {
            "category":"Shopping",
            "subcategory":"Bicycles & Sporting Goods",
            "type":"Retail Goods"
        }
    ],
    "sg:phone":"+31 55 522 3035",
    "sg:postcode":"7315 GK",
    "sg:province":"Gelderland",
    "sg:tags":[
        "sport-",
        "kampeerartikelen"
    ],
    "wof:name":"Vrielink Ruitersport, Zadelmakerij, Dier",
    "wof:placetype":"venue"
},
  "geometry": {"coordinates":[5.95732,52.235596],"type":"Point"}
}