{
  "type": "Feature",
  "properties": {
    "iso:country":"NL",
    "sg:address":"Industrieweg 3",
    "sg:city":"Bladel",
    "sg:orig_category":"Hout Gh",
    "sg:phone":"+31 497 381 795",
    "sg:postcode":"5531 AD",
    "sg:province":"North Brabant",
    "wof:name":"Fixet Bladel",
    "wof:placetype":"venue"
},
  "geometry": {"coordinates":[5.20149,51.361618],"type":"Point"}
}