{
  "type": "Feature",
  "properties": {
    "addr:full":"Gerard Ter Borchstraat 25 Roosendaal North Brabant 4703 NK",
    "addr:housenumber":"25",
    "addr:postcode":"4703 nk",
    "addr:street":"Gerard Ter Borchstraat",
    "iso:country":"NL",
    "sg:address":"Gerard Ter Borchstraat 25",
    "sg:city":"Roosendaal",
    "sg:orig_category":"Boekhouders",
    "sg:phone":"+31 165 536 295",
    "sg:postcode":"4703 NK",
    "sg:province":"North Brabant",
    "wof:name":"Administratiekantoor C.J. Broos",
    "wof:placetype":"venue"
},
  "geometry": {"coordinates":[4.438249,51.536564],"type":"Point"}
}