{
  "type": "Feature",
  "properties": {
    "iso:country":"NL",
    "sg:address":"J Tooropstr 3",
    "sg:city":"Weesp",
    "sg:orig_category":"Manueel Therapeuten",
    "sg:phone":"+31 294 410 978",
    "sg:postcode":"1382 TZ",
    "sg:province":"Noord-Holland",
    "wof:name":"Koolhaas-Wilke, Arts",
    "wof:placetype":"venue"
},
  "geometry": {"coordinates":[5.037322,52.311165],"type":"Point"}
}