{
  "type": "Feature",
  "properties": {
    "addr:full":"Ketenstr 185 Rotterdam Zuid-Holland 3061 MH",
    "addr:housenumber":"185",
    "addr:postcode":"3061 mh",
    "iso:country":"NL",
    "sg:address":"Ketenstr 185",
    "sg:city":"Rotterdam",
    "sg:orig_category":"Marketingbureaus",
    "sg:phone":"+31 10 242 7237",
    "sg:postcode":"3061 MH",
    "sg:province":"Zuid-Holland",
    "wof:name":"Assuxtend Vof",
    "wof:placetype":"venue"
},
  "geometry": {"coordinates":[4.499509,51.927372],"type":"Point"}
}