{
  "type": "Feature",
  "properties": {
    "iso:country":"NL",
    "sg:address":"Hoofdweg 107",
    "sg:city":"Rotterdam",
    "sg:orig_category":"Metaalafval, Schrootrecycling And Sloperijen",
    "sg:phone":"+31 10 421 6581",
    "sg:postcode":"3067 GC",
    "sg:province":"South Holland",
    "wof:name":"C.A. Romein",
    "wof:placetype":"venue"
},
  "geometry": {"coordinates":[4.536182,51.946705],"type":"Point"}
}