{
  "type": "Feature",
  "properties": {
    "addr:full":"Haparandaweg 9 Amsterdam Noord-Holland 1013 BD",
    "addr:housenumber":"9",
    "addr:postcode":"1013 bd",
    "addr:street":"Haparandaweg",
    "iso:country":"NL",
    "sg:address":"Haparandaweg 9",
    "sg:city":"Amsterdam",
    "sg:orig_category":"Aannemers Woningbouw",
    "sg:phone":"+31 20 688 1141",
    "sg:postcode":"1013 BD",
    "sg:province":"Noord-Holland",
    "wof:name":"Selie Bv Bouwbedrijf",
    "wof:placetype":"venue"
},
  "geometry": {"coordinates":[4.876416,52.39473],"type":"Point"}
}