{
  "type": "Feature",
  "properties": {
    "addr:full":"Tolakkerwg 74 Hollandsche Rading Utrecht 3739 JR",
    "addr:housenumber":"74",
    "addr:postcode":"rading;3739 jr",
    "addr:street":"Tolakkerwg",
    "iso:country":"NL",
    "sg:address":"Tolakkerwg 74",
    "sg:city":"Hollandsche Rading",
    "sg:orig_category":"Bedrijfsopleidingen",
    "sg:phone":"+31 35 577 1946",
    "sg:postcode":"3739 JR",
    "sg:province":"Utrecht",
    "wof:name":"Roi Bv",
    "wof:placetype":"venue"
},
  "geometry": {"coordinates":[5.174053,52.174587],"type":"Point"}
}