{
  "type": "Feature",
  "properties": {
    "addr:full":"Yselstr 26 Amsterdam Noord-Holland 1078 CJ",
    "addr:housenumber":"26",
    "addr:postcode":"1078 cj",
    "addr:street":"Yselstr",
    "iso:country":"NL",
    "sg:address":"Yselstr 26",
    "sg:city":"Amsterdam",
    "sg:orig_category":"Fotostudio'S",
    "sg:phone":"+31 20 471 0013",
    "sg:postcode":"1078 CJ",
    "sg:province":"Noord-Holland",
    "wof:name":"Piek",
    "wof:placetype":"venue"
},
  "geometry": {"coordinates":[4.90082,52.347458],"type":"Point"}
}