{
  "type": "Feature",
  "properties": {
    "iso:country":"NL",
    "sg:address":"Rivieradreef 42",
    "sg:city":"Haarlem",
    "sg:orig_category":"Boekhandels",
    "sg:phone":"+31 23 535 2813",
    "sg:postcode":"2037 AH",
    "sg:province":"Noord-Holland",
    "wof:name":"Bruna",
    "wof:placetype":"venue"
},
  "geometry": {"coordinates":[4.653684,52.35815],"type":"Point"}
}