{
  "type": "Feature",
  "properties": {
    "addr:full":"Provincialeweg 184 Zaandam Noord-Holland 1506 MG",
    "addr:housenumber":"184",
    "addr:postcode":"1506 mg",
    "addr:street":"Provincialeweg",
    "iso:country":"NL",
    "sg:address":"Provincialeweg 184",
    "sg:city":"Zaandam",
    "sg:orig_category":"Wegen And Sportterreinen",
    "sg:phone":"+31 75 750 7500",
    "sg:postcode":"1506 MG",
    "sg:province":"Noord-Holland",
    "wof:name":"Nbm Noord West Bv",
    "wof:placetype":"venue"
},
  "geometry": {"coordinates":[4.8128900528,52.4420776367],"type":"Point"}
}