{
  "type": "Feature",
  "properties": {
    "iso:country":"NL",
    "sg:address":"Pelikaanhof 30",
    "sg:city":"Leidschendam",
    "sg:orig_category":"Schilders",
    "sg:phone":"+31 70 320 3188",
    "sg:postcode":"2264 JJ",
    "sg:province":"Zuid-Holland",
    "wof:name":"Miog Vof, M",
    "wof:placetype":"venue"
},
  "geometry": {"coordinates":[4.409942,52.095097],"type":"Point"}
}