{
  "type": "Feature",
  "properties": {
    "addr:full":"Pelikaanhof 30 Leidschendam Zuid-Holland 2264 JJ",
    "addr:housenumber":"30",
    "addr:postcode":"2264 jj",
    "addr:street":"Pelikaanhof",
    "iso:country":"NL",
    "sg:address":"Pelikaanhof 30",
    "sg:city":"Leidschendam",
    "sg:orig_category":"Schilders",
    "sg:phone":"+31 70 320 3188",
    "sg:postcode":"2264 JJ",
    "sg:province":"Zuid-Holland",
    "wof:name":"Miog Vof, M",
    "wof:placetype":"venue"
},
  "geometry": {"coordinates":[4.409942,52.095097],"type":"Point"}
}