{
  "type": "Feature",
  "properties": {
    "addr:full":"Alkmaarsewg 31 Middenmeer Noord-Holland 1775 PR",
    "addr:housenumber":"31",
    "addr:postcode":"1775 pr",
    "addr:street":"Alkmaarsewg",
    "iso:country":"NL",
    "sg:address":"Alkmaarsewg 31",
    "sg:city":"Middenmeer",
    "sg:orig_category":"Voetbalverenigingen",
    "sg:phone":"+31 6 21865032",
    "sg:postcode":"1775 PR",
    "sg:province":"Noord-Holland",
    "wof:name":"Agsv",
    "wof:placetype":"venue"
},
  "geometry": {"coordinates":[4.948261,52.760818],"type":"Point"}
}