{
  "type": "Feature",
  "properties": {
    "addr:full":"Borrekuilstr 85 Geleen Limburg 6163 AB",
    "addr:housenumber":"85",
    "addr:postcode":"6163 ab",
    "addr:street":"Borrekuilstr",
    "iso:country":"NL",
    "sg:address":"Borrekuilstr 85",
    "sg:city":"Geleen",
    "sg:orig_category":"Kappers",
    "sg:phone":"+31 46 474 0150",
    "sg:postcode":"6163 AB",
    "sg:province":"Limburg",
    "wof:name":"Philomena",
    "wof:placetype":"venue"
},
  "geometry": {"coordinates":[5.82461,50.978821],"type":"Point"}
}