{
  "type": "Feature",
  "properties": {
    "addr:full":"De Heerd 38 Hoevelaken Gelderland 3871 RV",
    "addr:housenumber":"38",
    "addr:postcode":"3871 rv",
    "addr:street":"De Heerd;Gelderland",
    "iso:country":"NL",
    "sg:address":"De Heerd 38",
    "sg:city":"Hoevelaken",
    "sg:orig_category":"Accountants - Administratie- Consulenten En -Kantoren",
    "sg:phone":"+31 33 258 2428",
    "sg:postcode":"3871 RV",
    "sg:province":"Gelderland",
    "wof:name":"Bruijn Bv, R H De",
    "wof:placetype":"venue"
},
  "geometry": {"coordinates":[5.466496,52.176231],"type":"Point"}
}