{
  "type": "Feature",
  "properties": {
    "iso:country":"NL",
    "sg:address":"Sontwg 17",
    "sg:city":"Groningen",
    "sg:orig_category":"Machinefabrieken",
    "sg:phone":"+31 50 314 2615",
    "sg:postcode":"9723 AT",
    "sg:province":"Groningen",
    "wof:name":"Edo-Bode Apparatenbouw",
    "wof:placetype":"venue"
},
  "geometry": {"coordinates":[6.590814,53.218578],"type":"Point"}
}