{
  "type": "Feature",
  "properties": {
    "iso:country":"NL",
    "sg:address":"Raboes 6",
    "sg:city":"Laren Nh",
    "sg:orig_category":"Effectenmakelaars And Fondsenbeheer",
    "sg:phone":"+31 35 538 2638",
    "sg:postcode":"1251 AL",
    "sg:province":"Noord-Holland",
    "wof:name":"3De Jonge & Co Bv",
    "wof:placetype":"venue"
},
  "geometry": {"coordinates":[5.223823,52.268738],"type":"Point"}
}