{
  "type": "Feature",
  "properties": {
    "addr:full":"Hogewerf 54 Vlaardingen South Holland 3131 BZ",
    "addr:housenumber":"54",
    "addr:postcode":"3131 bz",
    "addr:street":"Hogewerf",
    "iso:country":"NL",
    "sg:address":"Hogewerf 54",
    "sg:city":"Vlaardingen",
    "sg:orig_category":"Verzekeringen - Verzekeringskantoren",
    "sg:phone":"+31 10 232 7482",
    "sg:postcode":"3131 BZ",
    "sg:province":"South Holland",
    "wof:name":"Soek, A J",
    "wof:placetype":"venue"
},
  "geometry": {"coordinates":[4.344014,51.912086],"type":"Point"}
}