{
  "type": "Feature",
  "properties": {
    "iso:country":"NL",
    "sg:address":"Burg Murisstr 112",
    "sg:city":"Meerssen",
    "sg:orig_category":"Bestratingen",
    "sg:phone":"+31 43 364 3351",
    "sg:postcode":"6231 GM",
    "sg:province":"Limburg",
    "wof:name":"Verhees, N",
    "wof:placetype":"venue"
},
  "geometry": {"coordinates":[5.74873,50.888603],"type":"Point"}
}