{
  "type": "Feature",
  "properties": {
    "iso:country":"NL",
    "sg:address":"Overschiestraat 184",
    "sg:city":"Amsterdam",
    "sg:orig_category":"Juridische Dienstverlening",
    "sg:phone":"+31 20 669 4432",
    "sg:postcode":"1062 XK",
    "sg:province":"Noord-Holland",
    "wof:name":"De Vries & Metman",
    "wof:placetype":"venue"
},
  "geometry": {"coordinates":[4.839113,52.343952],"type":"Point"}
}