{
  "type": "Feature",
  "properties": {
    "addr:full":"Willemskade 81 Leeuwarden Provincie Friesland 8911 AZ",
    "addr:housenumber":"81",
    "addr:postcode":"8911",
    "addr:street":"Willemskade;Provincie Friesland",
    "iso:country":"NL",
    "sg:address":"Willemskade 81",
    "sg:city":"Leeuwarden",
    "sg:orig_category":"Organisatiebureaus",
    "sg:phone":"+31 58 215 0991",
    "sg:postcode":"8911 AZ",
    "sg:province":"Provincie Friesland",
    "wof:name":"Buog",
    "wof:placetype":"venue"
},
  "geometry": {"coordinates":[5.7943739891,53.1982879639],"type":"Point"}
}