{
  "type": "Feature",
  "properties": {
    "addr:full":"Hendrikahoeve 4 Hoofddorp North Holland 2131 MV",
    "addr:housenumber":"4",
    "addr:postcode":"2131 mv",
    "addr:street":"Hendrikahoeve",
    "iso:country":"NL",
    "sg:address":"Hendrikahoeve 4",
    "sg:city":"Hoofddorp",
    "sg:orig_category":"Verzekeringen",
    "sg:phone":"+31 23 562 1678",
    "sg:postcode":"2131 MV",
    "sg:province":"North Holland",
    "wof:name":"Assurantiekantoor Oldenburg",
    "wof:placetype":"venue"
},
  "geometry": {"coordinates":[4.677797,52.317741],"type":"Point"}
}