{
  "type": "Feature",
  "properties": {
    "addr:full":"Dammenln 7 S Hertogenbosch Noord-Brabant 5224 KV",
    "addr:housenumber":"7",
    "addr:postcode":"5224 kv",
    "addr:street":"Dammenln",
    "iso:country":"NL",
    "sg:address":"Dammenln 7",
    "sg:city":"S Hertogenbosch",
    "sg:orig_category":"Adviesbureaus",
    "sg:phone":"+31 73 621 1552",
    "sg:postcode":"5224 KV",
    "sg:province":"Noord-Brabant",
    "wof:name":"Ami Bv",
    "wof:placetype":"venue"
},
  "geometry": {"coordinates":[5.2603,51.705219],"type":"Point"}
}