{
  "type": "Feature",
  "properties": {
    "addr:full":"Westgaag 4 Maasland Zuid-Holland 3155 DE",
    "addr:housenumber":"4",
    "addr:postcode":"3155 de",
    "addr:street":"Westgaag",
    "iso:country":"NL",
    "sg:address":"Westgaag 4",
    "sg:city":"Maasland",
    "sg:orig_category":"Bloemen And Planten Gh",
    "sg:phone":"+31 10 591 2008",
    "sg:postcode":"3155 DE",
    "sg:province":"Zuid-Holland",
    "wof:name":"Van Der Gaag Potgrond Bv",
    "wof:placetype":"venue"
},
  "geometry": {"coordinates":[4.273502,51.950169],"type":"Point"}
}