{
  "type": "Feature",
  "properties": {
    "addr:full":"J Catskd 32 Amsterdam North Holland 1052 BZ",
    "addr:housenumber":"32",
    "addr:postcode":"1052 bz",
    "iso:country":"NL",
    "sg:address":"J Catskd 32",
    "sg:city":"Amsterdam",
    "sg:classifiers":[
        {
            "category":"Personal",
            "subcategory":"Nail Salon",
            "type":"Services"
        }
    ],
    "sg:phone":"+31 20 686 1165",
    "sg:postcode":"1052 BZ",
    "sg:province":"North Holland",
    "sg:tags":[
        "pedicure"
    ],
    "wof:name":"Ruijter, M",
    "wof:placetype":"venue"
},
  "geometry": {"coordinates":[4.87379,52.377899],"type":"Point"}
}