{
  "type": "Feature",
  "properties": {
    "addr:full":"Waalzicht 4 Ochten Gelderland 4051 BL",
    "addr:housenumber":"4",
    "addr:postcode":"4051 bl",
    "addr:street":"Waalzicht;Gelderland",
    "iso:country":"NL",
    "sg:address":"Waalzicht 4",
    "sg:city":"Ochten",
    "sg:orig_category":"Sportaccommodaties - Aanleg En Onderhoud",
    "sg:phone":"+31 344 643 525",
    "sg:postcode":"4051 BL",
    "sg:province":"Gelderland",
    "sg:website":"http://www.sportvloeren.nl",
    "wof:name":"Interline Bv",
    "wof:placetype":"venue"
},
  "geometry": {"coordinates":[5.567408,51.905144],"type":"Point"}
}