{
  "type": "Feature",
  "properties": {
    "addr:full":"Weltertuijnstraat 38 Heerlen Limburg 6419 CT",
    "addr:housenumber":"38",
    "addr:postcode":"6419 ct",
    "addr:street":"Weltertuijnstraat",
    "iso:country":"NL",
    "sg:address":"Weltertuijnstraat 38",
    "sg:city":"Heerlen",
    "sg:orig_category":"Kappers",
    "sg:phone":"+31 45 571 4805",
    "sg:postcode":"6419 CT",
    "sg:province":"Limburg",
    "wof:name":"Ecoupe",
    "wof:placetype":"venue"
},
  "geometry": {"coordinates":[5.9677081108,50.8763923645],"type":"Point"}
}