{
  "type": "Feature",
  "properties": {
    "addr:full":"Dennenweg 9 Doetinchem Gelderland 7004 BP",
    "addr:housenumber":"9",
    "addr:postcode":"7004 bp",
    "addr:street":"Dennenweg;Gelderland",
    "iso:country":"NL",
    "sg:address":"Dennenweg 9",
    "sg:city":"Doetinchem",
    "sg:classifiers":[
        {
            "category":"Fast Food",
            "type":"Food & Drink"
        }
    ],
    "sg:phone":"+31 314 323 154",
    "sg:postcode":"7004 BP",
    "sg:province":"Gelderland",
    "sg:tags":[
        "afhaal",
        "restaurant"
    ],
    "wof:name":"Eetcafe-Cafetaria De Heksenkettel",
    "wof:placetype":"venue"
},
  "geometry": {"coordinates":[6.308562,51.950001],"type":"Point"}
}