{
  "type": "Feature",
  "properties": {
    "addr:full":"Thomsonln 167 S Gravenhage South Holland 2565 JB",
    "addr:housenumber":"167",
    "addr:postcode":"2565 jb",
    "addr:street":"S Gravenhage",
    "iso:country":"NL",
    "sg:address":"Thomsonln 167",
    "sg:city":"S Gravenhage",
    "sg:orig_category":"Verenigingen En Stichtingen",
    "sg:phone":"+31 70 361 6764",
    "sg:postcode":"2565 JB",
    "sg:province":"South Holland",
    "sg:website":"http://www.smlzwemmen.nl",
    "wof:name":"Sml Zwemvereniging",
    "wof:placetype":"venue"
},
  "geometry": {"coordinates":[4.26129,52.076382],"type":"Point"}
}