{
  "type": "Feature",
  "properties": {
    "addr:full":"Kastelenakkers 10 Zuidlaren Drenthe 9472 PL",
    "addr:housenumber":"10",
    "addr:postcode":"9472 pl",
    "addr:street":"Kastelenakkers",
    "iso:country":"NL",
    "sg:address":"Kastelenakkers 10",
    "sg:city":"Zuidlaren",
    "sg:orig_category":"Schilders",
    "sg:phone":"+31 50 409 2825",
    "sg:postcode":"9472 PL",
    "sg:province":"Drenthe",
    "wof:name":"Arends",
    "wof:placetype":"venue"
},
  "geometry": {"coordinates":[6.700271,53.072124],"type":"Point"}
}