{
  "type": "Feature",
  "properties": {
    "addr:full":"J P Sweelinckstraat 67 Purmerend North Holland 1443 MB",
    "addr:housenumber":"67",
    "addr:postcode":"1443 mb",
    "addr:street":"J P Sweelinckstraat",
    "iso:country":"NL",
    "sg:address":"J P Sweelinckstraat 67",
    "sg:city":"Purmerend",
    "sg:orig_category":"Fotostudio'S And Fotografen",
    "sg:phone":"+31 299 426 004",
    "sg:postcode":"1443 MB",
    "sg:province":"North Holland",
    "wof:name":"Fotobureau Van Gool",
    "wof:placetype":"venue"
},
  "geometry": {"coordinates":[4.97056,52.505943],"type":"Point"}
}