{
  "type": "Feature",
  "properties": {
    "addr:full":"Bisschop Zwijsenstraat 72 Tilburg Noord-Brabant 5021 KC",
    "addr:housenumber":"72",
    "addr:postcode":"5021 kc",
    "addr:street":"Bisschop Zwijsenstraat",
    "iso:country":"NL",
    "sg:address":"Bisschop Zwijsenstraat 72",
    "sg:city":"Tilburg",
    "sg:orig_category":"Meubelzaken, Woning- And Keukeninrichting",
    "sg:phone":"+31 13 542 1666",
    "sg:postcode":"5021 KC",
    "sg:province":"Noord-Brabant",
    "wof:name":"Stijlmeubelen Victor Boeren Tilburg Bv",
    "wof:placetype":"venue"
},
  "geometry": {"coordinates":[5.08748,51.550869],"type":"Point"}
}