{
  "type": "Feature",
  "properties": {
    "iso:country":"NL",
    "sg:address":"Groenstraat 17",
    "sg:city":"Prinsenbeek",
    "sg:orig_category":"Juweliers",
    "sg:phone":"+31 76 541 4232",
    "sg:postcode":"4841 BA",
    "sg:province":"Noord-Brabant",
    "wof:name":"P. Kawaler",
    "wof:placetype":"venue"
},
  "geometry": {"coordinates":[4.716866,51.598652],"type":"Point"}
}