{
  "type": "Feature",
  "properties": {
    "addr:full":"Kroonpassage 5 Lelystad Flevoland 8232 VP",
    "addr:housenumber":"5",
    "addr:postcode":"8232 vp",
    "addr:street":"Kroonpassage;Flevoland",
    "iso:country":"NL",
    "sg:address":"Kroonpassage 5",
    "sg:city":"Lelystad",
    "sg:orig_category":"Feestartikelen",
    "sg:phone":"+31 320 232 214",
    "sg:postcode":"8232 VP",
    "sg:province":"Flevoland",
    "wof:name":"Feesthoek, De",
    "wof:placetype":"venue"
},
  "geometry": {"coordinates":[5.475171,52.507229],"type":"Point"}
}