{
  "type": "Feature",
  "properties": {
    "iso:country":"NL",
    "sg:address":"Prinsenstraat 7",
    "sg:city":"Hoensbroek",
    "sg:orig_category":"Sportclubs",
    "sg:phone":"+31 45 521 3441",
    "sg:postcode":"6433 GG",
    "sg:province":"Limburg",
    "wof:name":"Voetbalvereniging Hoensbroek",
    "wof:placetype":"venue"
},
  "geometry": {"coordinates":[5.927542,50.910442],"type":"Point"}
}