{
  "type": "Feature",
  "properties": {
    "iso:country":"NL",
    "sg:address":"Beemsterstr 25",
    "sg:city":"Assendelft",
    "sg:orig_category":"Bejaarden - Verzorgingstehuizen",
    "sg:phone":"+31 75 687 1751",
    "sg:postcode":"1566 WP",
    "sg:province":"Noord-Holland",
    "wof:name":"Festina Lente",
    "wof:placetype":"venue"
},
  "geometry": {"coordinates":[4.744702,52.466537],"type":"Point"}
}