{
  "type": "Feature",
  "properties": {
    "addr:full":"Wasbloem 5 Venray Limburg 5803 LR",
    "addr:housenumber":"5",
    "addr:postcode":"5803 lr",
    "addr:street":"Wasbloem",
    "iso:country":"NL",
    "sg:address":"Wasbloem 5",
    "sg:city":"Venray",
    "sg:orig_category":"Chemische Producten Gh",
    "sg:phone":"+31 478 584 845",
    "sg:postcode":"5803 LR",
    "sg:province":"Limburg",
    "wof:name":"Olba Products",
    "wof:placetype":"venue"
},
  "geometry": {"coordinates":[5.995494,51.536148],"type":"Point"}
}