{
  "type": "Feature",
  "properties": {
    "addr:full":"De Kempenaerstr 77 Oegstgeest South Holland 2341 GJ",
    "addr:housenumber":"77",
    "addr:postcode":"2341 gj",
    "iso:country":"NL",
    "sg:address":"De Kempenaerstr 77",
    "sg:city":"Oegstgeest",
    "sg:orig_category":"Modelbouw",
    "sg:phone":"+31 71 517 2977",
    "sg:postcode":"2341 GJ",
    "sg:province":"South Holland",
    "wof:name":"Tombe, De",
    "wof:placetype":"venue"
},
  "geometry": {"coordinates":[4.471935,52.1777],"type":"Point"}
}