{
  "type": "Feature",
  "properties": {
    "addr:full":"Prinsengracht 252 Amsterdam Noord-Holland 1016 HG",
    "addr:housenumber":"252",
    "addr:postcode":"1016 hg",
    "addr:street":"Prinsengracht",
    "iso:country":"NL",
    "sg:address":"Prinsengracht 252",
    "sg:city":"Amsterdam",
    "sg:orig_category":"Kindermeubelen",
    "sg:phone":"+31 20 622 5599",
    "sg:postcode":"1016 HG",
    "sg:province":"Noord-Holland",
    "wof:name":"Fakkeldij Groep",
    "wof:placetype":"venue"
},
  "geometry": {"coordinates":[4.88255,52.372036],"type":"Point"}
}