{
  "type": "Feature",
  "properties": {
    "addr:full":"Malderburchtstr 13 Nymegen Gelderland 6535 ND",
    "addr:housenumber":"13",
    "addr:postcode":"6535 nd",
    "addr:street":"Malderburchtstr;Gelderland",
    "iso:country":"NL",
    "sg:address":"Malderburchtstr 13",
    "sg:city":"Nymegen",
    "sg:orig_category":"Onderzoekbureaus",
    "sg:phone":"+31 24 355 8822",
    "sg:postcode":"6535 ND",
    "sg:province":"Gelderland",
    "sg:website":"http://www.inop.nl",
    "wof:name":"Instituut Voor Nationale Onderwijspromotie",
    "wof:placetype":"venue"
},
  "geometry": {"coordinates":[-100.30171199999999,47.467731],"type":"Point"}
}