{
  "type": "Feature",
  "properties": {
    "iso:country":"NL",
    "sg:address":"Burgemeester Vd Veldestr 27",
    "sg:city":"'S Gravenhage",
    "sg:orig_category":"Kinderopvang Behalve Thuis",
    "sg:phone":"+31 70 391 0324",
    "sg:postcode":"2552 TE",
    "sg:province":"Zuid-Holland",
    "wof:name":"Kinderdagverblijf Bibeledons",
    "wof:placetype":"venue"
},
  "geometry": {"coordinates":[4.245099,52.0555],"type":"Point"}
}