{
  "type": "Feature",
  "properties": {
    "addr:full":"Veldhofstraat 150 Eygelshoven Limburg 6471 CM",
    "addr:housenumber":"150",
    "addr:postcode":"6471 cm",
    "addr:street":"Veldhofstraat",
    "iso:country":"NL",
    "sg:address":"Veldhofstraat 150",
    "sg:city":"Eygelshoven",
    "sg:classifiers":[
        {
            "category":"Fast Food",
            "type":"Food & Drink"
        }
    ],
    "sg:phone":"+31 45 546 4121",
    "sg:postcode":"6471 CM",
    "sg:province":"Limburg",
    "sg:tags":[
        "afhaal",
        "restaurant"
    ],
    "wof:name":"Pj",
    "wof:placetype":"venue"
},
  "geometry": {"coordinates":[6.06536,50.890675],"type":"Point"}
}