{
  "type": "Feature",
  "properties": {
    "addr:full":"Dordtseln 67-69 Rotterdam Zuid-Holland 3081 BG",
    "addr:housenumber":"67-69",
    "addr:postcode":"rotterdam;3081",
    "iso:country":"NL",
    "sg:address":"Dordtseln 67-69",
    "sg:city":"Rotterdam",
    "sg:orig_category":"Banket",
    "sg:phone":"+31 10 290 9130",
    "sg:postcode":"3081 BG",
    "sg:province":"Zuid-Holland",
    "sg:website":"http://www.cake.nl",
    "wof:name":"Ina'S Cake Fantasies",
    "wof:placetype":"venue"
},
  "geometry": {"coordinates":[4.48229,51.893768],"type":"Point"}
}