{
  "type": "Feature",
  "properties": {
    "addr:full":"Hoofdstraat 83 Landgraaf Limburg 6372 CR",
    "addr:housenumber":"83",
    "addr:postcode":"6372 cr",
    "addr:street":"Hoofdstraat",
    "iso:country":"NL",
    "sg:address":"Hoofdstraat 83",
    "sg:city":"Landgraaf",
    "sg:orig_category":"Kappers",
    "sg:phone":"+31 45 531 5072",
    "sg:postcode":"6372 CR",
    "sg:province":"Limburg",
    "wof:name":"Kapsalon Frans",
    "wof:placetype":"venue"
},
  "geometry": {"coordinates":[6.0156049728,50.8926429749],"type":"Point"}
}