{
  "type": "Feature",
  "properties": {
    "iso:country":"NL",
    "sg:address":"M Pololn 6",
    "sg:city":"Utrecht",
    "sg:orig_category":"Politie",
    "sg:phone":"+31 900 8844",
    "sg:postcode":"3526 GJ",
    "sg:province":"Utrecht",
    "wof:name":"Politie",
    "wof:placetype":"venue"
},
  "geometry": {"coordinates":[5.09982,52.063389],"type":"Point"}
}