{
  "type": "Feature",
  "properties": {
    "iso:country":"NL",
    "sg:address":"Vordingstr 27",
    "sg:city":"Ewyk",
    "sg:orig_category":"Psychotherapeuten",
    "sg:phone":"+31 487 522 591",
    "sg:postcode":"6644 BG",
    "sg:province":"Gelderland",
    "wof:name":"Kessel-Feddema, Drs B J M Van",
    "wof:placetype":"venue"
},
  "geometry": {"coordinates":[25.4387,41.614849],"type":"Point"}
}