{
  "type": "Feature",
  "properties": {
    "iso:country":"NL",
    "sg:address":"Koningsweg 30",
    "sg:city":"Winterswijk",
    "sg:orig_category":"Partycatering And -Organisatie",
    "sg:phone":"+31 543 520 136",
    "sg:postcode":"7102 DV",
    "sg:province":"Gelderland",
    "wof:name":"Roy'S Bedrijfscatering",
    "wof:placetype":"venue"
},
  "geometry": {"coordinates":[6.711358,51.963943],"type":"Point"}
}