{
  "type": "Feature",
  "properties": {
    "addr:full":"Terborgseweg 73 Silvolde Gelderland 7064 AB",
    "addr:housenumber":"73",
    "addr:postcode":"7064 ab",
    "addr:street":"Terborgseweg;Gelderland",
    "iso:country":"NL",
    "sg:address":"Terborgseweg 73",
    "sg:city":"Silvolde",
    "sg:orig_category":"Meubelzaken, Woning- And Keukeninrichting",
    "sg:phone":"+31 315 326 117",
    "sg:postcode":"7064 AB",
    "sg:province":"Gelderland",
    "wof:name":"Hans Van Den Hurk'S Woonhuis",
    "wof:placetype":"venue"
},
  "geometry": {"coordinates":[6.374698,51.916603],"type":"Point"}
}