{
  "type": "Feature",
  "properties": {
    "addr:full":"Voordijk 3A Schelluinen South Holland 4209 SB",
    "addr:housenumber":"3a",
    "addr:postcode":"4209 sb",
    "addr:street":"Voordijk",
    "iso:country":"NL",
    "sg:address":"Voordijk 3A",
    "sg:city":"Schelluinen",
    "sg:orig_category":"Bloemen And Planten",
    "sg:phone":"+31 183 620 188",
    "sg:postcode":"4209 SB",
    "sg:province":"South Holland",
    "wof:name":"De Oleander",
    "wof:placetype":"venue"
},
  "geometry": {"coordinates":[4.924775,51.843002],"type":"Point"}
}