{
  "type": "Feature",
  "properties": {
    "addr:full":"Pastorielaan 1 Heerenveen Friesland 8441 AA",
    "addr:housenumber":"1",
    "addr:postcode":"8441 aa",
    "addr:street":"Pastorielaan",
    "iso:country":"NL",
    "sg:address":"Pastorielaan 1",
    "sg:city":"Heerenveen",
    "sg:orig_category":"Paramedische Behandelingen",
    "sg:phone":"+31 513 610 117",
    "sg:postcode":"8441 AA",
    "sg:province":"Friesland",
    "wof:name":"B.A. Noordhoek",
    "wof:placetype":"venue"
},
  "geometry": {"coordinates":[5.925945,52.965828],"type":"Point"}
}