{
  "type": "Feature",
  "properties": {
    "addr:full":"Oranje Nassaustraat 13 Heerlen Limburg 6411 LE",
    "addr:housenumber":"13",
    "addr:postcode":"6411 le",
    "addr:street":"Oranje Nassaustraat",
    "iso:country":"NL",
    "sg:address":"Oranje Nassaustraat 13",
    "sg:city":"Heerlen",
    "sg:orig_category":"Herenmodezaken",
    "sg:phone":"+31 45 571 6637",
    "sg:postcode":"6411 LE",
    "sg:province":"Limburg",
    "wof:name":"Inizio Uomo",
    "wof:placetype":"venue"
},
  "geometry": {"coordinates":[5.978695,50.88892],"type":"Point"}
}