{
  "type": "Feature",
  "properties": {
    "addr:full":"Budapestlaan 9 Utrecht Utrecht 3584 CD",
    "addr:housenumber":"9",
    "addr:postcode":"3584 cd",
    "addr:street":"Budapestlaan",
    "iso:country":"NL",
    "sg:address":"Budapestlaan 9",
    "sg:city":"Utrecht",
    "sg:orig_category":"Boekhouders",
    "sg:phone":"+31 30 254 3041",
    "sg:postcode":"3584 CD",
    "sg:province":"Utrecht",
    "wof:name":"M.C. Van Kilsdonk",
    "wof:placetype":"venue"
},
  "geometry": {"coordinates":[5.169024,52.086933],"type":"Point"}
}