{
  "type": "Feature",
  "properties": {
    "iso:country":"NL",
    "sg:address":"Rendiermos 18",
    "sg:city":"Bergschenhoek",
    "sg:orig_category":"Kappers",
    "sg:phone":"+31 10 521 5179",
    "sg:postcode":"2661 MP",
    "sg:province":"South Holland",
    "wof:name":"Marian",
    "wof:placetype":"venue"
},
  "geometry": {"coordinates":[4.495854,51.9935],"type":"Point"}
}