{
  "type": "Feature",
  "properties": {
    "iso:country":"NL",
    "sg:address":"Rijksweg 12",
    "sg:city":"Eede Zld",
    "sg:orig_category":"Discountwinkels",
    "sg:phone":"+31 117 494 053",
    "sg:postcode":"4529 JC",
    "sg:province":"Zeeland",
    "wof:name":"D. Van Tilburg",
    "wof:placetype":"venue"
},
  "geometry": {"coordinates":[3.448644,51.241676],"type":"Point"}
}