{
  "type": "Feature",
  "properties": {
    "addr:full":"Orleanspln 20 Maastricht Limburg 6217 LB",
    "addr:housenumber":"20",
    "addr:postcode":"6217 lb",
    "addr:street":"Orleanspln",
    "iso:country":"NL",
    "sg:address":"Orleanspln 20",
    "sg:city":"Maastricht",
    "sg:orig_category":"Bierbrouwerijen",
    "sg:phone":"+31 6 29052700",
    "sg:postcode":"6217 LB",
    "sg:province":"Limburg",
    "sg:website":"http://www.bierbrouwerijdekeyzer.nl",
    "wof:name":"Keyzer Bv, De",
    "wof:placetype":"venue"
},
  "geometry": {"coordinates":[5.673668,50.851196],"type":"Point"}
}