{
  "type": "Feature",
  "properties": {
    "addr:full":"Broekwegzyde 159 Zoetermeer Zuid-Holland 2725 PD",
    "addr:housenumber":"159",
    "addr:postcode":"2725 pd",
    "iso:country":"NL",
    "sg:address":"Broekwegzyde 159",
    "sg:city":"Zoetermeer",
    "sg:orig_category":"Wijnkoperijen En -Groothandel",
    "sg:phone":"+31 79 593 9107",
    "sg:postcode":"2725 PD",
    "sg:province":"Zuid-Holland",
    "wof:name":"Greenfield",
    "wof:placetype":"venue"
},
  "geometry": {"coordinates":[4.5051598549,52.0816116333],"type":"Point"}
}