{
  "type": "Feature",
  "properties": {
    "addr:full":"Erberveltstr 27 Berkel En Rodenrys Zuid-Holland 2651 GE",
    "addr:housenumber":"27",
    "addr:postcode":"2651",
    "addr:street":"Erberveltstr;Berkel",
    "iso:country":"NL",
    "sg:address":"Erberveltstr 27",
    "sg:city":"Berkel En Rodenrys",
    "sg:orig_category":"Omroep",
    "sg:phone":"+31 10 519 0316",
    "sg:postcode":"2651 GE",
    "sg:province":"Zuid-Holland",
    "wof:name":"Broadcast Partn",
    "wof:placetype":"venue"
},
  "geometry": {"coordinates":[4.485399,51.999172],"type":"Point"}
}