{
  "type": "Feature",
  "properties": {
    "addr:full":"Gronausestr 489 Enschede Overijssel 7534 AA",
    "addr:housenumber":"489",
    "addr:postcode":"7534 aa",
    "iso:country":"NL",
    "sg:address":"Gronausestr 489",
    "sg:city":"Enschede",
    "sg:orig_category":"Kampeerartikelen",
    "sg:phone":"+31 53 461 1768",
    "sg:postcode":"7534 AA",
    "sg:province":"Overijssel",
    "sg:website":"http://www.oostcampingtotaal.nl",
    "wof:name":"Oost Camping Totaal",
    "wof:placetype":"venue"
},
  "geometry": {"coordinates":[6.9388389587,52.2177505493],"type":"Point"}
}