{
  "type": "Feature",
  "properties": {
    "iso:country":"NL",
    "sg:address":"Varrolaan 80",
    "sg:city":"Utrecht",
    "sg:orig_category":"Technische Studies And Onderzoek",
    "sg:phone":"+31 30 258 6586",
    "sg:postcode":"3584 BW",
    "sg:province":"Utrecht",
    "wof:name":"Maetis Arbo",
    "wof:placetype":"venue"
},
  "geometry": {"coordinates":[5.151627,52.091789],"type":"Point"}
}