{
  "type": "Feature",
  "properties": {
    "addr:full":"T Hiddesstr 5 Leeuwarden Friesland 8921 NM",
    "addr:housenumber":"5",
    "addr:postcode":"8921",
    "iso:country":"NL",
    "sg:address":"T Hiddesstr 5",
    "sg:city":"Leeuwarden",
    "sg:orig_category":"Verenigingsgebouwen",
    "sg:phone":"+31 58 213 9899",
    "sg:postcode":"8921 NM",
    "sg:province":"Friesland",
    "wof:name":"Tjerk Hiddes",
    "wof:placetype":"venue"
},
  "geometry": {"coordinates":[5.807088,53.207375],"type":"Point"}
}