{
  "type": "Feature",
  "properties": {
    "addr:full":"Scheldepln 4 Amsterdam North Holland 1078 GR",
    "addr:housenumber":"4",
    "addr:postcode":"1078",
    "addr:street":"Scheldepln",
    "iso:country":"NL",
    "sg:address":"Scheldepln 4",
    "sg:city":"Amsterdam",
    "sg:classifiers":[
        {
            "category":"Restaurant",
            "type":"Food & Drink"
        }
    ],
    "sg:phone":"+31 20 675 1583",
    "sg:postcode":"1078 GR",
    "sg:province":"North Holland",
    "sg:website":"http://www.visaandeschelde.nl",
    "wof:name":"Vis Aan De Schelde",
    "wof:placetype":"venue"
},
  "geometry": {"coordinates":[4.890448,52.344738],"type":"Point"}
}