{
  "type": "Feature",
  "properties": {
    "addr:full":"Dorpsstr 28 Amstelveen Noord-Holland 1182 JD",
    "addr:housenumber":"28",
    "addr:postcode":"1182 jd",
    "addr:street":"Dorpsstr",
    "iso:country":"NL",
    "sg:address":"Dorpsstr 28",
    "sg:city":"Amstelveen",
    "sg:orig_category":"Adviesbureaus Bedrijfsorganisatie",
    "sg:phone":"+31 20 547 0101",
    "sg:postcode":"1182 JD",
    "sg:province":"Noord-Holland",
    "sg:website":"http://www.fijlstrawullings.nl",
    "wof:name":"Fijlstra En Wullings",
    "wof:placetype":"venue"
},
  "geometry": {"coordinates":[4.84671,52.302696],"type":"Point"}
}