{
  "type": "Feature",
  "properties": {
    "addr:full":"Ruttensngl 59 Maastricht Limburg 6214 SL",
    "addr:housenumber":"59",
    "addr:postcode":"6214 sl",
    "addr:street":"Ruttensngl",
    "iso:country":"NL",
    "sg:address":"Ruttensngl 59",
    "sg:city":"Maastricht",
    "sg:orig_category":"Fietsen En Bromfietsen",
    "sg:phone":"+31 43 325 0662",
    "sg:postcode":"6214 SL",
    "sg:province":"Limburg",
    "wof:name":"Walstock, G",
    "wof:placetype":"venue"
},
  "geometry": {"coordinates":[5.68829,50.849831],"type":"Point"}
}