{
  "type": "Feature",
  "properties": {
    "addr:full":"Kr Boomssloot 55M Amsterdam North Holland 1011 GS",
    "addr:housenumber":"55m",
    "addr:postcode":"1011 gs",
    "addr:street":"Kr Boomssloot",
    "iso:country":"NL",
    "sg:address":"Kr Boomssloot 55M",
    "sg:city":"Amsterdam",
    "sg:orig_category":"Fotoreportages",
    "sg:phone":"+31 6 25087778",
    "sg:postcode":"1011 GS",
    "sg:province":"North Holland",
    "wof:name":"Parinussa, Paul",
    "wof:placetype":"venue"
},
  "geometry": {"coordinates":[4.902444,52.371197],"type":"Point"}
}