{
  "type": "Feature",
  "properties": {
    "addr:full":"Hommelsewg 243A Arnhem Gelderland 6821 LH",
    "addr:housenumber":"243a",
    "addr:postcode":"6821 lh",
    "iso:country":"NL",
    "sg:address":"Hommelsewg 243A",
    "sg:city":"Arnhem",
    "sg:orig_category":"Projectinrichting",
    "sg:phone":"+31 26 442 9200",
    "sg:postcode":"6821 LH",
    "sg:province":"Gelderland",
    "wof:name":"Kimberley",
    "wof:placetype":"venue"
},
  "geometry": {"coordinates":[5.916712,51.990715],"type":"Point"}
}