{
  "type": "Feature",
  "properties": {
    "addr:full":"Postbus 565 Assen Drenthe 9400 AN",
    "addr:housenumber":"565",
    "addr:postcode":"9400 an",
    "addr:street":"Postbus",
    "iso:country":"NL",
    "sg:address":"Postbus 565",
    "sg:city":"Assen",
    "sg:orig_category":"Voetbalverenigingen",
    "sg:phone":"+31 592 310 202",
    "sg:postcode":"9400 AN",
    "sg:province":"Drenthe",
    "wof:name":"Achilles 1894",
    "wof:placetype":"venue"
},
  "geometry": {"coordinates":[6.559506,52.994041],"type":"Point"}
}