{
  "type": "Feature",
  "properties": {
    "addr:full":"Schubertln 14 Apeldoorn Gelderland 7333 CV",
    "addr:housenumber":"14",
    "addr:postcode":"7333 cv",
    "addr:street":"Schubertln;Gelderland",
    "iso:country":"NL",
    "sg:address":"Schubertln 14",
    "sg:city":"Apeldoorn",
    "sg:orig_category":"Postkantoren",
    "sg:phone":"+31 55 533 2071",
    "sg:postcode":"7333 CV",
    "sg:province":"Gelderland",
    "sg:website":"http://www.postkantoor.nl",
    "wof:name":"Postkantoor",
    "wof:placetype":"venue"
},
  "geometry": {"coordinates":[5.965189,52.189873],"type":"Point"}
}