{
  "type": "Feature",
  "properties": {
    "addr:full":"Brecklenkamp 7 Almelo NL.08 7608 AA",
    "addr:housenumber":"7;nl.08",
    "addr:postcode":"7608 aa",
    "addr:street":"Brecklenkamp",
    "iso:country":"NL",
    "sg:address":"Brecklenkamp 7",
    "sg:city":"Almelo",
    "sg:orig_category":"Beeldende Kunstenaars",
    "sg:phone":"+31 546 865 264",
    "sg:postcode":"7608 AA",
    "sg:province":"NL.08",
    "wof:name":"Surrea-Design",
    "wof:placetype":"venue"
},
  "geometry": {"coordinates":[6.686619,52.379101],"type":"Point"}
}