{
  "type": "Feature",
  "properties": {
    "addr:full":"Baronieln 321 Breda North Brabant 4835 JN",
    "addr:housenumber":"321",
    "addr:postcode":"4835 jn",
    "iso:country":"NL",
    "sg:address":"Baronieln 321",
    "sg:city":"Breda",
    "sg:orig_category":"Webdesign Bureaus",
    "sg:phone":"+31 76 561 5474",
    "sg:postcode":"4835 JN",
    "sg:province":"North Brabant",
    "wof:name":"Kubits",
    "wof:placetype":"venue"
},
  "geometry": {"coordinates":[4.7850899696,51.5692481995],"type":"Point"}
}