{
  "type": "Feature",
  "properties": {
    "iso:country":"NL",
    "sg:address":"Nw Bosschewg 1",
    "sg:city":"Tilburg",
    "sg:orig_category":"Verzekeringen - Verzekeringskantoren",
    "sg:phone":"+31 13 542 3197",
    "sg:postcode":"5017 JJ",
    "sg:province":"Noord-Brabant",
    "wof:name":"Moerenburg",
    "wof:placetype":"venue"
},
  "geometry": {"coordinates":[5.1036329269,51.5602645874],"type":"Point"}
}