{
  "type": "Feature",
  "properties": {
    "addr:full":"Prof Teldersln 89 Delft South Holland 2628 VZ",
    "addr:housenumber":"89",
    "addr:postcode":"2628 vz",
    "iso:country":"NL",
    "sg:address":"Prof Teldersln 89",
    "sg:city":"Delft",
    "sg:orig_category":"Verenigingen En Stichtingen",
    "sg:phone":"+31 15 256 6108",
    "sg:postcode":"2628 VZ",
    "sg:province":"South Holland",
    "wof:name":"Interaccess, Sticht",
    "wof:placetype":"venue"
},
  "geometry": {"coordinates":[4.379627,52.003609],"type":"Point"}
}