{
  "type": "Feature",
  "properties": {
    "addr:full":"Thorbeckestr 1 Vlaardingen South Holland 3131 HP",
    "addr:housenumber":"1",
    "addr:postcode":"3131 hp",
    "addr:street":"Thorbeckestr",
    "iso:country":"NL",
    "sg:address":"Thorbeckestr 1",
    "sg:city":"Vlaardingen",
    "sg:orig_category":"Kinderopvang",
    "sg:phone":"+31 10 435 3009",
    "sg:postcode":"3131 HP",
    "sg:province":"South Holland",
    "sg:website":"http://www.skv.nl",
    "wof:name":"Pino",
    "wof:placetype":"venue"
},
  "geometry": {"coordinates":[4.338146,51.914097],"type":"Point"}
}