{
  "type": "Feature",
  "properties": {
    "addr:full":"Julianastr 41 Leiderdorp Zuid-Holland 2351 GW",
    "addr:housenumber":"41",
    "addr:postcode":"2351 gw",
    "addr:street":"Julianastr",
    "iso:country":"NL",
    "sg:address":"Julianastr 41",
    "sg:city":"Leiderdorp",
    "sg:orig_category":"Verenigingen En Stichtingen",
    "sg:phone":"+31 71 541 6516",
    "sg:postcode":"2351 GW",
    "sg:province":"Zuid-Holland",
    "sg:website":"http://www.blauw.demon.nl/tamarco",
    "wof:name":"Tamarco",
    "wof:placetype":"venue"
},
  "geometry": {"coordinates":[4.531626,52.146626],"type":"Point"}
}