{
  "type": "Feature",
  "properties": {
    "addr:full":"Gedempte Oude Gracht 127 Haarlem North Holland 2011 GP",
    "addr:housenumber":"127",
    "addr:postcode":"2011 gp",
    "addr:street":"Gedempte Oude Gracht",
    "iso:country":"NL",
    "sg:address":"Gedempte Oude Gracht 127",
    "sg:city":"Haarlem",
    "sg:classifiers":[
        {
            "category":"Bars & Pubs",
            "type":"Food & Drink"
        }
    ],
    "sg:phone":"+31 23 532 4052",
    "sg:postcode":"2011 GP",
    "sg:province":"North Holland",
    "wof:name":"Cafe La Justesse",
    "wof:placetype":"venue"
},
  "geometry": {"coordinates":[4.636188,52.378017],"type":"Point"}
}