{
  "type": "Feature",
  "properties": {
    "iso:country":"NL",
    "sg:address":"Molenstraat 3",
    "sg:city":"Naaldwijk",
    "sg:orig_category":"Herenmodezaken",
    "sg:phone":"+31 174 623 121",
    "sg:postcode":"2671 EV",
    "sg:province":"South Holland",
    "wof:name":"Nuovo Mode",
    "wof:placetype":"venue"
},
  "geometry": {"coordinates":[4.205974,51.993858],"type":"Point"}
}