{
  "type": "Feature",
  "properties": {
    "addr:full":"Laapersveld 53B Hilversum North Holland 1213 VB",
    "addr:housenumber":"53b",
    "addr:postcode":"1213 vb",
    "addr:street":"Laapersveld",
    "iso:country":"NL",
    "sg:address":"Laapersveld 53B",
    "sg:city":"Hilversum",
    "sg:orig_category":"Bedrijfs- And Managementsconsultants",
    "sg:phone":"+31 35 640 0646",
    "sg:postcode":"1213 VB",
    "sg:province":"North Holland",
    "wof:name":"Addition",
    "wof:placetype":"venue"
},
  "geometry": {"coordinates":[5.183985,52.211754],"type":"Point"}
}