{
  "type": "Feature",
  "properties": {
    "addr:full":"Heeswykstr 61 Voorburg Zuid-Holland 2275 EB",
    "addr:housenumber":"61",
    "addr:postcode":"2275 eb",
    "addr:street":"Heeswykstr",
    "iso:country":"NL",
    "sg:address":"Heeswykstr 61",
    "sg:city":"Voorburg",
    "sg:orig_category":"Loodgieters",
    "sg:phone":"+31 70 387 2397",
    "sg:postcode":"2275 EB",
    "sg:province":"Zuid-Holland",
    "wof:name":"Spa, Gebr W En J",
    "wof:placetype":"venue"
},
  "geometry": {"coordinates":[4.352661,52.062847],"type":"Point"}
}