{
  "type": "Feature",
  "properties": {
    "addr:full":"Standerdmolen 20 Houten Utrecht 3995 AA",
    "addr:housenumber":"20",
    "addr:postcode":"3995 aa",
    "addr:street":"Standerdmolen",
    "iso:country":"NL",
    "sg:address":"Standerdmolen 20",
    "sg:city":"Houten",
    "sg:orig_category":"Podotherapeuten",
    "sg:phone":"+31 30 634 1198",
    "sg:postcode":"3995 AA",
    "sg:province":"Utrecht",
    "sg:website":"http://www.podo-therapie.com",
    "wof:name":"Saskia De Waal",
    "wof:placetype":"venue"
},
  "geometry": {"coordinates":[5.172159,52.029762],"type":"Point"}
}