{
  "type": "Feature",
  "properties": {
    "addr:full":"Laan Van Meerdervoort 194 'S Gravenhage Zuid-Holland 2517 BJ",
    "addr:housenumber":"194 '",
    "addr:postcode":"2517 bj",
    "addr:street":"Laan Van Meerdervoort",
    "iso:country":"NL",
    "sg:address":"Laan Van Meerdervoort 194",
    "sg:city":"'S Gravenhage",
    "sg:orig_category":"Boekenuitgeverijen",
    "sg:phone":"+31 70 345 9594",
    "sg:postcode":"2517 BJ",
    "sg:province":"Zuid-Holland",
    "wof:name":"Vdlc Van Der Linden Communications",
    "wof:placetype":"venue"
},
  "geometry": {"coordinates":[4.286407,52.080963],"type":"Point"}
}