{
  "type": "Feature",
  "properties": {
    "iso:country":"NL",
    "sg:address":"Baarnsche Dk 8",
    "sg:city":"Baarn",
    "sg:orig_category":"Webdesign Bureaus",
    "sg:phone":"+31 800 3633423",
    "sg:postcode":"3741 LR",
    "sg:province":"Utrecht",
    "sg:website":"http://www.d-office.nl",
    "wof:name":"D-Office Baarn",
    "wof:placetype":"venue"
},
  "geometry": {"coordinates":[5.3017258644,52.2179107666],"type":"Point"}
}