{
  "type": "Feature",
  "properties": {
    "addr:full":"Terneuzensestraat 27 Zaamslag Zeeland 4543 BM",
    "addr:housenumber":"27",
    "addr:postcode":"4543 bm",
    "addr:street":"Terneuzensestraat",
    "iso:country":"NL",
    "sg:address":"Terneuzensestraat 27",
    "sg:city":"Zaamslag",
    "sg:orig_category":"Loodgieterswerk, Verwarming And Sanitaire Installaties",
    "sg:phone":"+31 115 431 235",
    "sg:postcode":"4543 BM",
    "sg:province":"Zeeland",
    "wof:name":"Fa. Dekker En Zn Aannemingsbedrijf En Ij",
    "wof:placetype":"venue"
},
  "geometry": {"coordinates":[3.908225,51.312729],"type":"Point"}
}