{
  "type": "Feature",
  "properties": {
    "addr:full":"Dorpsstr 51 Harskamp Gelderland 6732 AB",
    "addr:housenumber":"51",
    "addr:postcode":"6732 ab",
    "addr:street":"Dorpsstr;Gelderland",
    "iso:country":"NL",
    "sg:address":"Dorpsstr 51",
    "sg:city":"Harskamp",
    "sg:orig_category":"Tekstschrijversters",
    "sg:phone":"+31 318 457 910",
    "sg:postcode":"6732 AB",
    "sg:province":"Gelderland",
    "wof:name":"Maasland, Arie",
    "wof:placetype":"venue"
},
  "geometry": {"coordinates":[5.753777,52.128845],"type":"Point"}
}