{
  "type": "Feature",
  "properties": {
    "addr:full":"Geldropsewg 61B Eindhoven Noord-Brabant 5611 SE",
    "addr:housenumber":"61b",
    "addr:postcode":"5611 se",
    "addr:street":"Geldropsewg",
    "iso:country":"NL",
    "sg:address":"Geldropsewg 61B",
    "sg:city":"Eindhoven",
    "sg:orig_category":"Galeries",
    "sg:phone":"+31 40 293 0270",
    "sg:postcode":"5611 SE",
    "sg:province":"Noord-Brabant",
    "wof:name":"Pennings",
    "wof:placetype":"venue"
},
  "geometry": {"coordinates":[5.488413,51.433872],"type":"Point"}
}