{
  "type": "Feature",
  "properties": {
    "addr:full":"Fabriekswg 5 Bladel Noord-Brabant 5531 PP",
    "addr:housenumber":"5",
    "addr:postcode":"5531 pp",
    "addr:street":"Fabriekswg",
    "iso:country":"NL",
    "sg:address":"Fabriekswg 5",
    "sg:city":"Bladel",
    "sg:orig_category":"Meubelmakerijen",
    "sg:phone":"+31 497 384 917",
    "sg:postcode":"5531 PP",
    "sg:province":"Noord-Brabant",
    "sg:website":"http://www.ikm-meubeldesign.nl",
    "wof:name":"Ikm Meubeldesign Bv",
    "wof:placetype":"venue"
},
  "geometry": {"coordinates":[5.202355,51.359818],"type":"Point"}
}