{
  "type": "Feature",
  "properties": {
    "addr:full":"De Heurne 39 Enschede Overijssel 7511 GZ",
    "addr:housenumber":"39",
    "addr:postcode":"7511 gz",
    "addr:street":"De Heurne",
    "iso:country":"NL",
    "sg:address":"De Heurne 39",
    "sg:city":"Enschede",
    "sg:orig_category":"Fotolaboratoria",
    "sg:phone":"+31 53 430 7304",
    "sg:postcode":"7511 GZ",
    "sg:province":"Overijssel",
    "wof:name":"Fotoprintshop",
    "wof:placetype":"venue"
},
  "geometry": {"coordinates":[6.898763,52.221279],"type":"Point"}
}