{
  "type": "Feature",
  "properties": {
    "addr:full":"Marskramerstraat 69 Amsterdam North Holland 1033 WJ",
    "addr:housenumber":"69",
    "addr:postcode":"1033 wj",
    "addr:street":"Marskramerstraat",
    "iso:country":"NL",
    "sg:address":"Marskramerstraat 69",
    "sg:city":"Amsterdam",
    "sg:orig_category":"Koeriersdiensten",
    "sg:phone":"+31 20 492 0591",
    "sg:postcode":"1033 WJ",
    "sg:province":"North Holland",
    "wof:name":"Fast Personal Delivery Courier",
    "wof:placetype":"venue"
},
  "geometry": {"coordinates":[4.883532,52.420021],"type":"Point"}
}