{
  "type": "Feature",
  "properties": {
    "addr:full":"Nieuweburen 79 Leeuwarden Provincie Friesland 8911 EX",
    "addr:housenumber":"79",
    "addr:postcode":"8911 ex",
    "addr:street":"Nieuweburen;Provincie Friesland",
    "iso:country":"NL",
    "sg:address":"Nieuweburen 79",
    "sg:city":"Leeuwarden",
    "sg:orig_category":"Haptotherapeuten",
    "sg:phone":"+31 58 215 9172",
    "sg:postcode":"8911 EX",
    "sg:province":"Provincie Friesland",
    "wof:name":"Persoonlijke Ontw & Haptonomie, Prakt",
    "wof:placetype":"venue"
},
  "geometry": {"coordinates":[5.797576,53.205013],"type":"Point"}
}