{
  "type": "Feature",
  "properties": {
    "addr:full":"Grotestraat 46 Haren Nb Noord-Brabant 5368 AK",
    "addr:housenumber":"46",
    "addr:postcode":"5368 ak",
    "addr:street":"Grotestraat",
    "iso:country":"NL",
    "sg:address":"Grotestraat 46",
    "sg:city":"Haren Nb",
    "sg:classifiers":[
        {
            "category":"Fast Food",
            "type":"Food & Drink"
        }
    ],
    "sg:phone":"+31 412 462 216",
    "sg:postcode":"5368 AK",
    "sg:province":"Noord-Brabant",
    "sg:tags":[
        "afhaal",
        "restaurant"
    ],
    "wof:name":"Vof Verhoeven-Bergers",
    "wof:placetype":"venue"
},
  "geometry": {"coordinates":[5.584386,51.801853],"type":"Point"}
}