{
  "type": "Feature",
  "properties": {
    "addr:full":"Timorstr 4 Meppel Drenthe 7941 VE",
    "addr:housenumber":"4",
    "addr:postcode":"7941",
    "addr:street":"Timorstr;Ve",
    "iso:country":"NL",
    "sg:address":"Timorstr 4",
    "sg:city":"Meppel",
    "sg:orig_category":"Wasserijen",
    "sg:phone":"+31 522 251 238",
    "sg:postcode":"7941 VE",
    "sg:province":"Drenthe",
    "wof:name":"Lelie Vof, De",
    "wof:placetype":"venue"
},
  "geometry": {"coordinates":[6.1930551529,52.6993675232],"type":"Point"}
}