{
  "type": "Feature",
  "properties": {
    "iso:country":"NL",
    "sg:address":"Postbus 3227",
    "sg:city":"Soest",
    "sg:orig_category":"Adviesbureaus Land- En Tuinbouw",
    "sg:phone":"+31 35 602 3214",
    "sg:postcode":"3760 DE",
    "sg:province":"Zuid-Holland",
    "wof:name":"Agro Cons Bv",
    "wof:placetype":"venue"
},
  "geometry": {"coordinates":[5.3003849983,52.1840438843],"type":"Point"}
}