{
  "type": "Feature",
  "properties": {
    "addr:full":"Postbus 3227 Soest Zuid-Holland 3760 DE",
    "addr:housenumber":"3227",
    "addr:postcode":"soest;3760 de",
    "addr:street":"Postbus",
    "iso:country":"NL",
    "sg:address":"Postbus 3227",
    "sg:city":"Soest",
    "sg:orig_category":"Adviesbureaus Land- En Tuinbouw",
    "sg:phone":"+31 35 602 3214",
    "sg:postcode":"3760 DE",
    "sg:province":"Zuid-Holland",
    "wof:name":"Agro Cons Bv",
    "wof:placetype":"venue"
},
  "geometry": {"coordinates":[5.3003849983,52.1840438843],"type":"Point"}
}