{
  "type": "Feature",
  "properties": {
    "addr:full":"Urkhovenseweg 10 Eindhoven Noord-Brabant 5641 KE",
    "addr:housenumber":"10",
    "addr:postcode":"5641 ke",
    "addr:street":"Urkhovenseweg",
    "iso:country":"NL",
    "sg:address":"Urkhovenseweg 10",
    "sg:city":"Eindhoven",
    "sg:orig_category":"Overheidsdiensten",
    "sg:phone":"+31 40 281 1698",
    "sg:postcode":"5641 KE",
    "sg:province":"Noord-Brabant",
    "wof:name":"Evenementenacc. 'T Karregat Bv",
    "wof:placetype":"venue"
},
  "geometry": {"coordinates":[5.5220417976,51.4451217651],"type":"Point"}
}