{
  "type": "Feature",
  "properties": {
    "iso:country":"NL",
    "sg:address":"Galopstr 76",
    "sg:city":"Almere",
    "sg:orig_category":"Verhuur",
    "sg:phone":"+31 36 537 9825",
    "sg:postcode":"1326 RR",
    "sg:province":"Flevoland",
    "wof:name":"Tapper, De",
    "wof:placetype":"venue"
},
  "geometry": {"coordinates":[5.256436,52.362114],"type":"Point"}
}