{
  "type": "Feature",
  "properties": {
    "iso:country":"NL",
    "sg:address":"Bisschop Bekkerslaan 111",
    "sg:city":"Tilburg",
    "sg:orig_category":"Bedrijfs- And Managementsconsultants",
    "sg:phone":"+31 13 543 9644",
    "sg:postcode":"5046 JW",
    "sg:province":"Noord-Brabant",
    "wof:name":"Mutsaers Privacyadvies",
    "wof:placetype":"venue"
},
  "geometry": {"coordinates":[5.081689,51.570801],"type":"Point"}
}