{
  "type": "Feature",
  "properties": {
    "iso:country":"NL",
    "sg:address":"De Stoven 37",
    "sg:city":"Zutphen",
    "sg:classifiers":[
        {
            "category":"Travel",
            "subcategory":"Hotels & Motels",
            "type":"Entertainment"
        }
    ],
    "sg:phone":"+31 575 525 555",
    "sg:postcode":"7206 AZ",
    "sg:province":"Gelderland",
    "sg:website":"http://www.hotelinntel.com",
    "wof:name":"Inntel Hotel",
    "wof:placetype":"venue"
},
  "geometry": {"coordinates":[6.213019,52.124611],"type":"Point"}
}