{
  "type": "Feature",
  "properties": {
    "addr:full":"Dorpsstr 45 Bergharen Gelderland 6617 AC",
    "addr:housenumber":"45",
    "addr:postcode":"6617 ac",
    "addr:street":"Dorpsstr;Gelderland",
    "iso:country":"NL",
    "sg:address":"Dorpsstr 45",
    "sg:city":"Bergharen",
    "sg:orig_category":"Elektrotechnische Installatiebureaus",
    "sg:phone":"+31 487 531 516",
    "sg:postcode":"6617 AC",
    "sg:province":"Gelderland",
    "wof:name":"Aalbers",
    "wof:placetype":"venue"
},
  "geometry": {"coordinates":[5.665605,51.85099],"type":"Point"}
}