{
  "type": "Feature",
  "properties": {
    "iso:country":"NL",
    "sg:address":"Meeuwenln 16",
    "sg:city":"Noordwykerhout",
    "sg:orig_category":"Loonbedrijven",
    "sg:phone":"+31 252 370 547",
    "sg:postcode":"2211 KP",
    "sg:province":"South Holland",
    "wof:name":"Hage, A T Van",
    "wof:placetype":"venue"
},
  "geometry": {"coordinates":[4.496009,52.25658],"type":"Point"}
}