{
  "type": "Feature",
  "properties": {
    "addr:full":"Dorpstraat 50D Rosmalen North Brabant 5241 ED",
    "addr:housenumber":"50d",
    "addr:postcode":"5241 ed",
    "addr:street":"Dorpstraat",
    "iso:country":"NL",
    "sg:address":"Dorpstraat 50D",
    "sg:city":"Rosmalen",
    "sg:orig_category":"Werving And Selectie Van Tijdelijk Personeel And Uitzendkantoren",
    "sg:phone":"+31 73 523 6777",
    "sg:postcode":"5241 ED",
    "sg:province":"North Brabant",
    "wof:name":"Content",
    "wof:placetype":"venue"
},
  "geometry": {"coordinates":[5.3629288673,51.7164344788],"type":"Point"}
}