{
  "type": "Feature",
  "properties": {
    "addr:full":"Raam 6 Kaatsheuvel North Brabant 5172 DD",
    "addr:housenumber":"6",
    "addr:postcode":"5172 dd",
    "addr:street":"Raam",
    "iso:country":"NL",
    "sg:address":"Raam 6",
    "sg:city":"Kaatsheuvel",
    "sg:orig_category":"Fotografie Reclame En Mode",
    "sg:phone":"+31 416 281 819",
    "sg:postcode":"5172 DD",
    "sg:province":"North Brabant",
    "wof:name":"Kort, Leo De",
    "wof:placetype":"venue"
},
  "geometry": {"coordinates":[5.017145,51.650673],"type":"Point"}
}