{
  "type": "Feature",
  "properties": {
    "iso:country":"NL",
    "sg:address":"Kerkstraat 28",
    "sg:city":"Westervoort",
    "sg:classifiers":[
        {
            "category":"Communications",
            "subcategory":"Television Station",
            "type":"Services"
        }
    ],
    "sg:phone":"+31 26 311 8875",
    "sg:postcode":"6931 DT",
    "sg:province":"Gelderland",
    "sg:tags":[
        "video",
        "audio",
        "verhuur"
    ],
    "wof:name":"Videomarkt",
    "wof:placetype":"venue"
},
  "geometry": {"coordinates":[5.966484,51.961826],"type":"Point"}
}