{
  "type": "Feature",
  "properties": {
    "addr:full":"Troelstralaan 134A Almelo NL.08 7604 VP",
    "addr:housenumber":"134a;nl.08",
    "addr:postcode":"7604 vp",
    "addr:street":"Troelstralaan",
    "iso:country":"NL",
    "sg:address":"Troelstralaan 134A",
    "sg:city":"Almelo",
    "sg:orig_category":"Kinderopvang Behalve Thuis",
    "sg:phone":"+31 546 853 003",
    "sg:postcode":"7604 VP",
    "sg:province":"NL.08",
    "wof:name":"Kinderdagverblijf De Vlinders",
    "wof:placetype":"venue"
},
  "geometry": {"coordinates":[6.647373,52.358143],"type":"Point"}
}