{
  "type": "Feature",
  "properties": {
    "addr:full":"Wilhelmina Boulevard Noordwijk Zh South Holland 2202 GR",
    "addr:postcode":"zh;2202",
    "addr:street":"Wilhelmina Boulevard",
    "iso:country":"NL",
    "sg:address":"Wilhelmina Boulevard",
    "sg:city":"Noordwijk Zh",
    "sg:orig_category":"Overheidsdiensten",
    "sg:phone":"+31 71 361 7287",
    "sg:postcode":"2202 GR",
    "sg:province":"South Holland",
    "wof:name":"Zeilvereniging Noordwijk",
    "wof:placetype":"venue"
},
  "geometry": {"coordinates":[4.435614109,52.2488365173],"type":"Point"}
}