{
  "type": "Feature",
  "properties": {
    "addr:full":"Wielewaalstr 1 Borne British Columbia 7622 BC",
    "addr:housenumber":"1",
    "addr:postcode":"7622 bc",
    "addr:street":"Wielewaalstr",
    "iso:country":"NL",
    "sg:address":"Wielewaalstr 1",
    "sg:city":"Borne",
    "sg:orig_category":"Adviesbureaus Bedrijfsorganisatie",
    "sg:phone":"+31 74 267 1889",
    "sg:postcode":"7622 BC",
    "sg:province":"British Columbia",
    "wof:name":"Voorde, Arno Ten",
    "wof:placetype":"venue"
},
  "geometry": {"coordinates":[-126.555511,54.485668],"type":"Point"}
}