{
  "type": "Feature",
  "properties": {
    "addr:full":"Kapelstraat 42 Chaam Noord-Brabant 4861 SC",
    "addr:housenumber":"42",
    "addr:postcode":"4861 sc",
    "addr:street":"Kapelstraat",
    "iso:country":"NL",
    "sg:address":"Kapelstraat 42",
    "sg:city":"Chaam",
    "sg:orig_category":"Bloemen And Planten",
    "sg:phone":"+31 161 492 612",
    "sg:postcode":"4861 SC",
    "sg:province":"Noord-Brabant",
    "wof:name":"T Bloemenvrouwke",
    "wof:placetype":"venue"
},
  "geometry": {"coordinates":[4.856011,51.505573],"type":"Point"}
}