{
  "type": "Feature",
  "properties": {
    "addr:full":"Concordialaan 201 Etten-Leur Noord-Brabant 4871 ZA",
    "addr:housenumber":"201",
    "addr:postcode":"4871",
    "addr:street":"Concordialaan",
    "iso:country":"NL",
    "sg:address":"Concordialaan 201",
    "sg:city":"Etten-Leur",
    "sg:classifiers":[
        {
            "category":"Fast Food",
            "type":"Food & Drink"
        }
    ],
    "sg:phone":"+31 76 502 1549",
    "sg:postcode":"4871 ZA",
    "sg:province":"Noord-Brabant",
    "sg:tags":[
        "afhaal",
        "restaurant"
    ],
    "wof:name":"Vof Cafetaria De Guust",
    "wof:placetype":"venue"
},
  "geometry": {"coordinates":[4.644007,51.580631],"type":"Point"}
}