{
  "type": "Feature",
  "properties": {
    "addr:full":"Nyverheidstr 30 Enschede Overijssel 7511 JM",
    "addr:housenumber":"30",
    "addr:postcode":"7511 jm",
    "addr:street":"Nyverheidstr",
    "iso:country":"NL",
    "sg:address":"Nyverheidstr 30",
    "sg:city":"Enschede",
    "sg:orig_category":"Pensioenfondsen",
    "sg:phone":"+31 53 482 2851",
    "sg:postcode":"7511 JM",
    "sg:province":"Overijssel",
    "wof:name":"Achmea",
    "wof:placetype":"venue"
},
  "geometry": {"coordinates":[6.891689,52.218807],"type":"Point"}
}