{
  "type": "Feature",
  "properties": {
    "addr:full":"Vaarselstraat 46 Someren Noord-Brabant 5711 RE",
    "addr:housenumber":"46",
    "addr:postcode":"5711 re",
    "addr:street":"Vaarselstraat",
    "iso:country":"NL",
    "sg:address":"Vaarselstraat 46",
    "sg:city":"Someren",
    "sg:orig_category":"Bloemen And Planten",
    "sg:phone":"+31 493 496 843",
    "sg:postcode":"5711 RE",
    "sg:province":"Noord-Brabant",
    "wof:name":"Frank En Toos Vd Wortel",
    "wof:placetype":"venue"
},
  "geometry": {"coordinates":[5.697159,51.386654],"type":"Point"}
}