{
  "type": "Feature",
  "properties": {
    "iso:country":"NL",
    "sg:address":"Liebeek 77",
    "sg:city":"Ede Gld",
    "sg:classifiers":[
        {
            "category":"Building & Trades",
            "subcategory":"Electrical",
            "type":"Services"
        }
    ],
    "sg:phone":"+31 318 625 548",
    "sg:postcode":"6715 HP",
    "sg:province":"Gelderland",
    "sg:tags":[
        "distributor"
    ],
    "wof:name":"Eka Bv",
    "wof:placetype":"venue"
},
  "geometry": {"coordinates":[5.630991,52.039238],"type":"Point"}
}