{
  "type": "Feature",
  "properties": {
    "addr:full":"Prins Hendrikstraat 43 Bodegraven Zuid-Holland 2411 CS",
    "addr:housenumber":"43",
    "addr:postcode":"2411 cs",
    "addr:street":"Prins Hendrikstraat",
    "iso:country":"NL",
    "sg:address":"Prins Hendrikstraat 43",
    "sg:city":"Bodegraven",
    "sg:orig_category":"Hypotheken And Hypotheekbanken",
    "sg:phone":"+31 172 617 907",
    "sg:postcode":"2411 CS",
    "sg:province":"Zuid-Holland",
    "wof:name":"De Hypotheekshop",
    "wof:placetype":"venue"
},
  "geometry": {"coordinates":[4.74569,52.082359],"type":"Point"}
}