{
  "type": "Feature",
  "properties": {
    "addr:full":"Zuiderdiep 63 Nieuw Buinen Drenthe 9521 AB",
    "addr:housenumber":"63",
    "addr:postcode":"buinen;9521 ab",
    "addr:street":"Zuiderdiep",
    "iso:country":"NL",
    "sg:address":"Zuiderdiep 63",
    "sg:city":"Nieuw Buinen",
    "sg:orig_category":"Autoverhuur",
    "sg:phone":"+31 599 212 372",
    "sg:postcode":"9521 AB",
    "sg:province":"Drenthe",
    "wof:name":"Sijpkes Autorijschool & Autoverhuurinric",
    "wof:placetype":"venue"
},
  "geometry": {"coordinates":[6.90651,52.945236],"type":"Point"}
}