{
  "type": "Feature",
  "properties": {
    "addr:full":"Einsteinstraat 77 Purmerend Noord-Holland 1446 VE",
    "addr:housenumber":"77",
    "addr:postcode":"1446",
    "addr:street":"Einsteinstraat;Ve",
    "iso:country":"NL",
    "sg:address":"Einsteinstraat 77",
    "sg:city":"Purmerend",
    "sg:orig_category":"Bloemen And Planten Gh",
    "sg:phone":"+31 299 667 138",
    "sg:postcode":"1446 VE",
    "sg:province":"Noord-Holland",
    "wof:name":"The Twins",
    "wof:placetype":"venue"
},
  "geometry": {"coordinates":[4.997075,52.512417],"type":"Point"}
}