{
  "type": "Feature",
  "properties": {
    "addr:full":"Mangroveln 2 Ryen North Brabant 5121 CT",
    "addr:housenumber":"2",
    "addr:postcode":"5121 ct",
    "addr:street":"Mangroveln",
    "iso:country":"NL",
    "sg:address":"Mangroveln 2",
    "sg:city":"Ryen",
    "sg:orig_category":"Kantoor- En Secretariaatsservice",
    "sg:phone":"+31 161 232 717",
    "sg:postcode":"5121 CT",
    "sg:province":"North Brabant",
    "sg:website":"http://www.quintverhaag.nl",
    "wof:name":"Quint & Verhaag",
    "wof:placetype":"venue"
},
  "geometry": {"coordinates":[4.9197001457,51.58801651],"type":"Point"}
}