{
  "type": "Feature",
  "properties": {
    "addr:full":"Hoogstraat 88 Schiedam Zuid-Holland 3111 HL",
    "addr:housenumber":"88",
    "addr:postcode":"3111 hl",
    "addr:street":"Hoogstraat",
    "iso:country":"NL",
    "sg:address":"Hoogstraat 88",
    "sg:city":"Schiedam",
    "sg:classifiers":[
        {
            "category":"Shopping",
            "subcategory":"Gifts & Souvenirs",
            "type":"Retail Goods"
        }
    ],
    "sg:phone":"+31 10 426 6463",
    "sg:postcode":"3111 HL",
    "sg:province":"Zuid-Holland",
    "sg:tags":[
        "geschenken"
    ],
    "wof:name":"Kunsthandel Modern",
    "wof:placetype":"venue"
},
  "geometry": {"coordinates":[4.39816,51.918472],"type":"Point"}
}