{
  "type": "Feature",
  "properties": {
    "addr:full":"Oldenzaalsestraat 30 Losser Overijssel 7581 AV",
    "addr:housenumber":"30",
    "addr:postcode":"7581 av",
    "addr:street":"Oldenzaalsestraat",
    "iso:country":"NL",
    "sg:address":"Oldenzaalsestraat 30",
    "sg:city":"Losser",
    "sg:orig_category":"Verenigingsgebouwen",
    "sg:phone":"+31 53 538 2256",
    "sg:postcode":"7581 AV",
    "sg:province":"Overijssel",
    "sg:website":"http://www.ariensgroep.nl",
    "wof:name":"Welp, De",
    "wof:placetype":"venue"
},
  "geometry": {"coordinates":[7.001259,52.264675],"type":"Point"}
}