{
  "type": "Feature",
  "properties": {
    "addr:full":"De Riemsdk 4 Tiel Gelderland 4004 LC",
    "addr:housenumber":"4",
    "addr:postcode":"4004 lc",
    "addr:street":"Gelderland",
    "iso:country":"NL",
    "sg:address":"De Riemsdk 4",
    "sg:city":"Tiel",
    "sg:orig_category":"Verf En Lak - Fabrieken En Groothandel",
    "sg:phone":"+31 344 620 662",
    "sg:postcode":"4004 LC",
    "sg:province":"Gelderland",
    "wof:name":"Euro Lacke Bv",
    "wof:placetype":"venue"
},
  "geometry": {"coordinates":[5.443778,51.918831],"type":"Point"}
}