{
  "type": "Feature",
  "properties": {
    "iso:country":"NL",
    "sg:address":"Verboomstr 124B",
    "sg:city":"Rotterdam",
    "sg:orig_category":"Onderhoudswerken",
    "sg:phone":"+31 10 495 5341",
    "sg:postcode":"3082 JS",
    "sg:province":"South Holland",
    "wof:name":"Arcoiris",
    "wof:placetype":"venue"
},
  "geometry": {"coordinates":[4.463129,51.888042],"type":"Point"}
}