{
  "type": "Feature",
  "properties": {
    "addr:full":"Splytbakwg 25 Almere NL. 1333 HC",
    "addr:housenumber":"25",
    "addr:postcode":"1333 hc",
    "addr:street":"Splytbakwg;Nl.",
    "iso:country":"NL",
    "sg:address":"Splytbakwg 25",
    "sg:city":"Almere",
    "sg:orig_category":"Woninginrichting",
    "sg:phone":"+31 36 532 9301",
    "sg:postcode":"1333 HC",
    "sg:province":"NL.",
    "sg:website":"http://www.marmoplus.nl",
    "wof:name":"Marmo Plus",
    "wof:placetype":"venue"
},
  "geometry": {"coordinates":[5.2660908699,52.4026260376],"type":"Point"}
}