{
  "type": "Feature",
  "properties": {
    "addr:full":"Derksstr 160 Emmen Drenthe 7811 AJ",
    "addr:housenumber":"160",
    "addr:postcode":"7811 aj",
    "iso:country":"NL",
    "sg:address":"Derksstr 160",
    "sg:city":"Emmen",
    "sg:orig_category":"Juweliers",
    "sg:phone":"+31 591 643 040",
    "sg:postcode":"7811 AJ",
    "sg:province":"Drenthe",
    "wof:name":"Sanna S Goud En Zilver Smederij",
    "wof:placetype":"venue"
},
  "geometry": {"coordinates":[6.893166,52.788006],"type":"Point"}
}