{
  "type": "Feature",
  "properties": {
    "addr:full":"S Meyerstr 10 Driesum Friesland 9114 RX",
    "addr:housenumber":"10",
    "addr:postcode":"9114 rx",
    "addr:street":"Driesum Friesland",
    "iso:country":"NL",
    "sg:address":"S Meyerstr 10",
    "sg:city":"Driesum",
    "sg:orig_category":"Schilders",
    "sg:phone":"+31 511 423 538",
    "sg:postcode":"9114 RX",
    "sg:province":"Friesland",
    "wof:name":"Dellen, Van",
    "wof:placetype":"venue"
},
  "geometry": {"coordinates":[6.045692,53.294571],"type":"Point"}
}