{
  "type": "Feature",
  "properties": {
    "addr:full":"Mercurion 3 Zevenaar Gelderland 6903 PX",
    "addr:housenumber":"3",
    "addr:postcode":"6903 px",
    "addr:street":"Mercurion",
    "iso:country":"NL",
    "sg:address":"Mercurion 3",
    "sg:city":"Zevenaar",
    "sg:orig_category":"Accountants - Administratie- Consulenten En -Kantoren",
    "sg:phone":"+31 316 582 600",
    "sg:postcode":"6903 PX",
    "sg:province":"Gelderland",
    "sg:website":"http://www.dales-groep.com",
    "wof:name":"Dales Zevenaar Bv",
    "wof:placetype":"venue"
},
  "geometry": {"coordinates":[6.079005,51.94297],"type":"Point"}
}