{
  "type": "Feature",
  "properties": {
    "iso:country":"NL",
    "sg:address":"Gemeenschapspolderweg 42",
    "sg:city":"Weesp",
    "sg:orig_category":"Houten Verpakkingen Fab",
    "sg:phone":"+31 294 416 892",
    "sg:postcode":"1382 GR",
    "sg:province":"North Holland",
    "wof:name":"Koertse Verpakkingsmaterialen B. V.",
    "wof:placetype":"venue"
},
  "geometry": {"coordinates":[5.022867,52.313931],"type":"Point"}
}