{
  "type": "Feature",
  "properties": {
    "iso:country":"NL",
    "sg:address":"Smaragdplein 252",
    "sg:city":"Utrecht",
    "sg:orig_category":"Bibliotheken And Openbare Archieven",
    "sg:phone":"+31 30 286 1915",
    "sg:postcode":"3523 EJ",
    "sg:province":"Utrecht",
    "wof:name":"Bibliotheken Openbare",
    "wof:placetype":"venue"
},
  "geometry": {"coordinates":[5.125434,52.072678],"type":"Point"}
}