{
  "type": "Feature",
  "properties": {
    "addr:full":"Apennijnenweg 16 Tilburg North Brabant 5022 DV",
    "addr:housenumber":"16",
    "addr:postcode":"5022 dv",
    "addr:street":"Apennijnenweg",
    "iso:country":"NL",
    "sg:address":"Apennijnenweg 16",
    "sg:city":"Tilburg",
    "sg:classifiers":[
        {
            "category":"Professional",
            "subcategory":"Accounting & Tax Preparation",
            "type":"Services"
        }
    ],
    "sg:phone":"+31 13 544 2233",
    "sg:postcode":"5022 DV",
    "sg:province":"North Brabant",
    "sg:tags":[
        "accountant"
    ],
    "wof:name":"Abab Accountants",
    "wof:placetype":"venue"
},
  "geometry": {"coordinates":[5.077939,51.54258],"type":"Point"}
}