{
  "type": "Feature",
  "properties": {
    "addr:full":"Stadsweg 34 Wirdum Gn Groningen 9917 PW",
    "addr:housenumber":"34",
    "addr:postcode":"gn;9917 pw",
    "addr:street":"Stadsweg",
    "iso:country":"NL",
    "sg:address":"Stadsweg 34",
    "sg:city":"Wirdum Gn",
    "sg:orig_category":"Muziekinstrumenten Fab",
    "sg:phone":"+31 596 571 659",
    "sg:postcode":"9917 PW",
    "sg:province":"Groningen",
    "wof:name":"S A De Vries",
    "wof:placetype":"venue"
},
  "geometry": {"coordinates":[6.796335,53.314644],"type":"Point"}
}