{
  "type": "Feature",
  "properties": {
    "addr:full":"Spoorstraat 4 Weesp North Holland 1382 AC",
    "addr:housenumber":"4",
    "addr:postcode":"1382 ac",
    "addr:street":"Spoorstraat",
    "iso:country":"NL",
    "sg:address":"Spoorstraat 4",
    "sg:city":"Weesp",
    "sg:orig_category":"Loodgieterswerk, Verwarming And Sanitaire Installaties",
    "sg:phone":"+31 294 412 715",
    "sg:postcode":"1382 AC",
    "sg:province":"North Holland",
    "wof:name":"Reparatie & Montage Van Der Laan",
    "wof:placetype":"venue"
},
  "geometry": {"coordinates":[5.045999,52.310616],"type":"Point"}
}