{
  "type": "Feature",
  "properties": {
    "addr:full":"Heuvelenweg 5 Lochem Gelderland 7241 HX",
    "addr:housenumber":"5",
    "addr:postcode":"7241 hx",
    "addr:street":"Heuvelenweg;Gelderland",
    "iso:country":"NL",
    "sg:address":"Heuvelenweg 5",
    "sg:city":"Lochem",
    "sg:orig_category":"Schoonheidssalons",
    "sg:phone":"+31 573 258 909",
    "sg:postcode":"7241 HX",
    "sg:province":"Gelderland",
    "wof:name":"Marta Van Oene",
    "wof:placetype":"venue"
},
  "geometry": {"coordinates":[6.424458,52.153744],"type":"Point"}
}