{
  "type": "Feature",
  "properties": {
    "iso:country":"NL",
    "sg:address":"Oostdk 4",
    "sg:city":"Hellevoetsluis",
    "sg:orig_category":"Open Haarden",
    "sg:phone":"+31 181 321 130",
    "sg:postcode":"3223 CB",
    "sg:province":"Zuid-Holland",
    "sg:website":"http://www.open-haarden.nl",
    "wof:name":"Pierre & Jeanette Openhaarden",
    "wof:placetype":"venue"
},
  "geometry": {"coordinates":[4.139743,51.844997],"type":"Point"}
}