{
  "type": "Feature",
  "properties": {
    "addr:full":"Christinelaan 4 Weert Limburg 6006 CJ",
    "addr:housenumber":"4",
    "addr:postcode":"6006 cj",
    "addr:street":"Christinelaan",
    "iso:country":"NL",
    "sg:address":"Christinelaan 4",
    "sg:city":"Weert",
    "sg:orig_category":"Boekhouders",
    "sg:phone":"+31 495 524 503",
    "sg:postcode":"6006 CJ",
    "sg:province":"Limburg",
    "wof:name":"Administratiekantoor M. Peeters",
    "wof:placetype":"venue"
},
  "geometry": {"coordinates":[5.710749,51.244827],"type":"Point"}
}