{
  "type": "Feature",
  "properties": {
    "addr:full":"Dr Berlageln 13 Eindhoven Noord-Brabant 5622 HA",
    "addr:housenumber":"13",
    "addr:postcode":"5622 ha",
    "iso:country":"NL",
    "sg:address":"Dr Berlageln 13",
    "sg:city":"Eindhoven",
    "sg:orig_category":"Scholen Voor Algemeen Voortgezet Onderwijs",
    "sg:phone":"+31 40 237 9700",
    "sg:postcode":"5622 HA",
    "sg:province":"Noord-Brabant",
    "wof:name":"Regionaal Educatief Centrum",
    "wof:placetype":"venue"
},
  "geometry": {"coordinates":[5.46291,51.459381],"type":"Point"}
}