{
  "type": "Feature",
  "properties": {
    "iso:country":"NL",
    "sg:address":"Zevenhuizen 18",
    "sg:city":"Hattem",
    "sg:orig_category":"Verzekeringen - Verzekeringskantoren",
    "sg:phone":"+31 38 444 5248",
    "sg:postcode":"8051 VP",
    "sg:province":"Gelderland",
    "wof:name":"Karsten",
    "wof:placetype":"venue"
},
  "geometry": {"coordinates":[6.061092,52.475552],"type":"Point"}
}