{
  "type": "Feature",
  "properties": {
    "addr:full":"Drielsedijk 17 Arnhem Gelderland 6841 HJ",
    "addr:housenumber":"17",
    "addr:postcode":"6841 hj",
    "addr:street":"Drielsedijk",
    "iso:country":"NL",
    "sg:address":"Drielsedijk 17",
    "sg:city":"Arnhem",
    "sg:orig_category":"Voetbalverenigingen",
    "sg:phone":"+31 26 381 4718",
    "sg:postcode":"6841 HJ",
    "sg:province":"Gelderland",
    "wof:name":"Asv Az 2000",
    "wof:placetype":"venue"
},
  "geometry": {"coordinates":[5.861187,51.96769],"type":"Point"}
}