{
  "type": "Feature",
  "properties": {
    "iso:country":"NL",
    "sg:address":"Zeven Eikenlaan 24",
    "sg:city":"Veghel",
    "sg:orig_category":"Makelaars In Onroerend Goed",
    "sg:phone":"+31 413 352 720",
    "sg:postcode":"5461 ED",
    "sg:province":"Noord-Brabant",
    "wof:name":"Korsten Makelaardij",
    "wof:placetype":"venue"
},
  "geometry": {"coordinates":[5.548771,51.619362],"type":"Point"}
}