{
  "type": "Feature",
  "properties": {
    "addr:full":"Westwagenstr 63 Gorinchem Zuid-Holland 4201 HE",
    "addr:housenumber":"63",
    "addr:postcode":"4201 he",
    "addr:street":"Westwagenstr",
    "iso:country":"NL",
    "sg:address":"Westwagenstr 63",
    "sg:city":"Gorinchem",
    "sg:orig_category":"Loodgieters",
    "sg:phone":"+31 183 630 405",
    "sg:postcode":"4201 HE",
    "sg:province":"Zuid-Holland",
    "wof:name":"Merwestreek",
    "wof:placetype":"venue"
},
  "geometry": {"coordinates":[4.970844,51.830418],"type":"Point"}
}