{
  "type": "Feature",
  "properties": {
    "addr:full":"Oude Delft 128 Delft Zuid-Holland 2611 CG",
    "addr:housenumber":"128",
    "addr:postcode":"2611 cg",
    "addr:street":"Oude Delft",
    "iso:country":"NL",
    "sg:address":"Oude Delft 128",
    "sg:city":"Delft",
    "sg:orig_category":"Werving And Selectie Van Tijdelijk Personeel And Uitzendkantoren",
    "sg:phone":"+31 15 212 6748",
    "sg:postcode":"2611 CG",
    "sg:province":"Zuid-Holland",
    "wof:name":"De Talentendatabank",
    "wof:placetype":"venue"
},
  "geometry": {"coordinates":[4.3561239243,52.0118331909],"type":"Point"}
}