{
  "type": "Feature",
  "properties": {
    "addr:full":"Kloosterwandstraat 30 Roermond Limburg 6041 HJ",
    "addr:housenumber":"30",
    "addr:postcode":"6041 hj",
    "addr:street":"Kloosterwandstraat",
    "iso:country":"NL",
    "sg:address":"Kloosterwandstraat 30",
    "sg:city":"Roermond",
    "sg:classifiers":[
        {
            "category":"Shopping",
            "subcategory":"Clothing, Apparel, & Fashions",
            "type":"Retail Goods"
        }
    ],
    "sg:phone":"+31 475 332 471",
    "sg:postcode":"6041 HJ",
    "sg:province":"Limburg",
    "sg:tags":[
        "ondergoed",
        "lingerie"
    ],
    "wof:name":"Rob Adriaans Lindessa",
    "wof:placetype":"venue"
},
  "geometry": {"coordinates":[5.990726,51.192616],"type":"Point"}
}