{
  "type": "Feature",
  "properties": {
    "addr:full":"Kiplingstr 105 Rotterdam South Holland 3076 TC",
    "addr:housenumber":"105",
    "addr:postcode":"3076 tc",
    "iso:country":"NL",
    "sg:address":"Kiplingstr 105",
    "sg:city":"Rotterdam",
    "sg:orig_category":"Autorijscholen",
    "sg:phone":"+31 10 492 1934",
    "sg:postcode":"3076 TC",
    "sg:province":"South Holland",
    "sg:website":"http://www.verkeersschooldezwaan.nl",
    "wof:name":"Zwaan Verkeersschool, De",
    "wof:placetype":"venue"
},
  "geometry": {"coordinates":[4.517928,51.874058],"type":"Point"}
}