{
  "type": "Feature",
  "properties": {
    "addr:full":"Weth Ventewg 171 Gouda Zuid-Holland 2805 JN",
    "addr:housenumber":"171",
    "addr:postcode":"2805 jn",
    "addr:street":"Weth Ventewg",
    "iso:country":"NL",
    "sg:address":"Weth Ventewg 171",
    "sg:city":"Gouda",
    "sg:orig_category":"Open Haarden",
    "sg:phone":"+31 182 511 117",
    "sg:postcode":"2805 JN",
    "sg:province":"Zuid-Holland",
    "sg:website":"http://www.tibas-openhaarden.nl",
    "wof:name":"Tibas",
    "wof:placetype":"venue"
},
  "geometry": {"coordinates":[4.721294,52.02198],"type":"Point"}
}