{
  "type": "Feature",
  "properties": {
    "iso:country":"NL",
    "sg:address":"Engelberterwg 38",
    "sg:city":"Groningen",
    "sg:orig_category":"Scholen Voor Basisonderwijs",
    "sg:phone":"+31 50 549 0522",
    "sg:postcode":"9723 EM",
    "sg:province":"Groningen",
    "wof:name":"Driebond, De",
    "wof:placetype":"venue"
},
  "geometry": {"coordinates":[6.647184,53.208469],"type":"Point"}
}