{
  "type": "Feature",
  "properties": {
    "addr:full":"Oudewerfslaan 121 Winschoten Groningen 9675 ES",
    "addr:housenumber":"121",
    "addr:postcode":"9675 es",
    "addr:street":"Oudewerfslaan",
    "iso:country":"NL",
    "sg:address":"Oudewerfslaan 121",
    "sg:city":"Winschoten",
    "sg:orig_category":"Hypotheken And Hypotheekbanken",
    "sg:phone":"+31 597 412 208",
    "sg:postcode":"9675 ES",
    "sg:province":"Groningen",
    "wof:name":"Hypotheek- En Assurantiekantoor Hisken",
    "wof:placetype":"venue"
},
  "geometry": {"coordinates":[7.029141,53.152264],"type":"Point"}
}