{
  "type": "Feature",
  "properties": {
    "iso:country":"NL",
    "sg:address":"Westwaarts 40",
    "sg:city":"Zoetermeer",
    "sg:orig_category":"Hypotheken",
    "sg:phone":"+31 79 320 0112",
    "sg:postcode":"2711 AC",
    "sg:province":"Zuid-Holland",
    "sg:website":"http://www.zoetermeer.hypotheekshop.nl/1115",
    "wof:name":"Hypotheekshop, De",
    "wof:placetype":"venue"
},
  "geometry": {"coordinates":[4.486546,52.061134],"type":"Point"}
}