{
  "type": "Feature",
  "properties": {
    "addr:full":"Meidoornhof 26 Leusden Utrecht 3831 XS",
    "addr:housenumber":"26",
    "addr:postcode":"3831 xs",
    "addr:street":"Meidoornhof",
    "iso:country":"NL",
    "sg:address":"Meidoornhof 26",
    "sg:city":"Leusden",
    "sg:orig_category":"Postzegels",
    "sg:phone":"+31 33 494 6980",
    "sg:postcode":"3831 XS",
    "sg:province":"Utrecht",
    "wof:name":"Breedt Bruijn, M",
    "wof:placetype":"venue"
},
  "geometry": {"coordinates":[5.432744,52.137058],"type":"Point"}
}