{
  "type": "Feature",
  "properties": {
    "iso:country":"NL",
    "sg:address":"Heemskerckstr 16",
    "sg:city":"Oudeschild",
    "sg:orig_category":"Touringcars",
    "sg:phone":"+31 222 315 555",
    "sg:postcode":"1792 AB",
    "sg:province":"Noord-Holland",
    "wof:name":"Texel",
    "wof:placetype":"venue"
},
  "geometry": {"coordinates":[4.847566,53.039471],"type":"Point"}
}