{
  "type": "Feature",
  "properties": {
    "addr:full":"B Keatonstr 59 Almere Flevoland 1325 CK",
    "addr:housenumber":"59",
    "addr:postcode":"1325 ck",
    "addr:street":"Flevoland",
    "iso:country":"NL",
    "sg:address":"B Keatonstr 59",
    "sg:city":"Almere",
    "sg:orig_category":"Architecten En Architectenbureaus",
    "sg:phone":"+31 36 537 9139",
    "sg:postcode":"1325 CK",
    "sg:province":"Flevoland",
    "wof:name":"Ren\u00e9 Van Zuuk Bv",
    "wof:placetype":"venue"
},
  "geometry": {"coordinates":[5.230966,52.375942],"type":"Point"}
}