{
  "type": "Feature",
  "properties": {
    "addr:full":"Ossekop 12 Leeuwarden Provincie Friesland 8911 LE",
    "addr:housenumber":"12",
    "addr:postcode":"8911 le",
    "addr:street":"Ossekop;Provincie Friesland",
    "iso:country":"NL",
    "sg:address":"Ossekop 12",
    "sg:city":"Leeuwarden",
    "sg:orig_category":"Verenigingen En Stichtingen",
    "sg:phone":"+31 58 212 9056",
    "sg:postcode":"8911 LE",
    "sg:province":"Provincie Friesland",
    "wof:name":"Pal-Groen Links",
    "wof:placetype":"venue"
},
  "geometry": {"coordinates":[5.798863,53.200226],"type":"Point"}
}