{
  "type": "Feature",
  "properties": {
    "iso:country":"NL",
    "sg:address":"Het Erf 52",
    "sg:city":"Bovenkarspel",
    "sg:orig_category":"Projectinrichting",
    "sg:phone":"+31 228 514 265",
    "sg:postcode":"1611 KL",
    "sg:province":"North Holland",
    "wof:name":"Ton Ruiter, Vloeren",
    "wof:placetype":"venue"
},
  "geometry": {"coordinates":[5.234019,52.699501],"type":"Point"}
}