{
  "type": "Feature",
  "properties": {
    "addr:full":"Julianaweg 9 Lochem Gelderland 7241 BM",
    "addr:housenumber":"9",
    "addr:postcode":"7241 bm",
    "addr:street":"Julianaweg;Gelderland",
    "iso:country":"NL",
    "sg:address":"Julianaweg 9",
    "sg:city":"Lochem",
    "sg:orig_category":"Fietshandelaren",
    "sg:phone":"+31 573 257 361",
    "sg:postcode":"7241 BM",
    "sg:province":"Gelderland",
    "wof:name":"Vof Ron Van Slingerland Tweewielers",
    "wof:placetype":"venue"
},
  "geometry": {"coordinates":[6.41329,52.163082],"type":"Point"}
}