{
  "type": "Feature",
  "properties": {
    "addr:full":"Veenhoeksweg 19 Klazienaveen Provincie Drenthe 7891 NW",
    "addr:housenumber":"19;7891",
    "addr:postcode":"nw",
    "addr:street":"Veenhoeksweg;Provincie Drenthe",
    "iso:country":"NL",
    "sg:address":"Veenhoeksweg 19",
    "sg:city":"Klazienaveen",
    "sg:orig_category":"Wegen And Sportterreinen",
    "sg:phone":"+31 591 393 373",
    "sg:postcode":"7891 NW",
    "sg:province":"Provincie Drenthe",
    "wof:name":"Plasman",
    "wof:placetype":"venue"
},
  "geometry": {"coordinates":[6.9803371429,52.7043914795],"type":"Point"}
}