{
  "type": "Feature",
  "properties": {
    "addr:full":"Willem Kroezestraat 3 Waskemeer Friesland 8434 NN",
    "addr:housenumber":"3",
    "addr:postcode":"8434 nn",
    "addr:street":"Willem Kroezestraat",
    "iso:country":"NL",
    "sg:address":"Willem Kroezestraat 3",
    "sg:city":"Waskemeer",
    "sg:classifiers":[
        {
            "category":"Education",
            "subcategory":"Preschool",
            "type":"Public Place"
        }
    ],
    "sg:phone":"+31 516 421 075",
    "sg:postcode":"8434 NN",
    "sg:province":"Friesland",
    "sg:tags":[
        "kleuteronderwijs",
        "basis-"
    ],
    "wof:name":"Christelijke Basisschool De Paadwizer",
    "wof:placetype":"venue"
},
  "geometry": {"coordinates":[6.279404,53.055336],"type":"Point"}
}