{
  "type": "Feature",
  "properties": {
    "addr:full":"Havenstraat 14 Maasbracht Limburg 6051 CR",
    "addr:housenumber":"14",
    "addr:postcode":"6051 cr",
    "addr:street":"Havenstraat",
    "iso:country":"NL",
    "sg:address":"Havenstraat 14",
    "sg:city":"Maasbracht",
    "sg:orig_category":"Kappers",
    "sg:phone":"+31 475 461 699",
    "sg:postcode":"6051 CR",
    "sg:province":"Limburg",
    "wof:name":"J.H.G.L. Kolgen",
    "wof:placetype":"venue"
},
  "geometry": {"coordinates":[5.8863239288,51.1469841003],"type":"Point"}
}