{
  "type": "Feature",
  "properties": {
    "iso:country":"NL",
    "sg:address":"J Baldwinstr 5",
    "sg:city":"Groningen",
    "sg:orig_category":"Beeldende Kunstenaars",
    "sg:phone":"+31 50 579 1129",
    "sg:postcode":"9746 AE",
    "sg:province":"Groningen",
    "wof:name":"Zadorin, A G",
    "wof:placetype":"venue"
},
  "geometry": {"coordinates":[6.514091,53.228893],"type":"Point"}
}