{
  "type": "Feature",
  "properties": {
    "addr:full":"Sud 112-116 Workum Provincie Friesland 8711 CX",
    "addr:housenumber":"112-116",
    "addr:postcode":"8711 cx",
    "addr:street":"Provincie Friesland",
    "iso:country":"NL",
    "sg:address":"Sud 112-116",
    "sg:city":"Workum",
    "sg:orig_category":"Keukens",
    "sg:phone":"+31 515 541 925",
    "sg:postcode":"8711 CX",
    "sg:province":"Provincie Friesland",
    "sg:website":"http://www.zwhkeukens.nl",
    "wof:name":"Zuid West Hoek",
    "wof:placetype":"venue"
},
  "geometry": {"coordinates":[5.43904,52.976543],"type":"Point"}
}