{
  "type": "Feature",
  "properties": {
    "addr:full":"Paterstr 15 Evertsoord Limburg 5977 NM",
    "addr:housenumber":"15",
    "addr:postcode":"5977",
    "addr:street":"Paterstr",
    "iso:country":"NL",
    "sg:address":"Paterstr 15",
    "sg:city":"Evertsoord",
    "sg:orig_category":"Verenigingen En Stichtingen",
    "sg:phone":"+31 77 464 1974",
    "sg:postcode":"5977 NM",
    "sg:province":"Limburg",
    "wof:name":"Patrijs, Sticht De",
    "wof:placetype":"venue"
},
  "geometry": {"coordinates":[5.958859,51.402863],"type":"Point"}
}