{
  "type": "Feature",
  "properties": {
    "iso:country":"NL",
    "sg:address":"Halvemaanstg 12",
    "sg:city":"Amsterdam",
    "sg:orig_category":"Webdesign Bureaus",
    "sg:phone":"+31 20 776 8121",
    "sg:postcode":"1017 CR",
    "sg:province":"North Holland",
    "sg:website":"http://www.mushroomgalaxy.com",
    "wof:name":"Mushroom Galaxy",
    "wof:placetype":"venue"
},
  "geometry": {"coordinates":[4.8956050873,52.366558075],"type":"Point"}
}