{
  "type": "Feature",
  "properties": {
    "addr:full":"Hoogstraat 20 Hasselt Overijssel 8061 HC",
    "addr:housenumber":"20",
    "addr:postcode":"8061 hc",
    "addr:street":"Hoogstraat",
    "iso:country":"NL",
    "sg:address":"Hoogstraat 20",
    "sg:city":"Hasselt",
    "sg:orig_category":"Autokeuringen",
    "sg:phone":"+31 38 477 2724",
    "sg:postcode":"8061 HC",
    "sg:province":"Overijssel",
    "wof:name":"Motorenrevisie Henk Melenhorst",
    "wof:placetype":"venue"
},
  "geometry": {"coordinates":[6.088611,52.59161],"type":"Point"}
}