{
  "type": "Feature",
  "properties": {
    "iso:country":"NL",
    "sg:address":"Vestdykln 16",
    "sg:city":"Heerhugowaard",
    "sg:orig_category":"Beveiliging",
    "sg:phone":"+31 72 574 3806",
    "sg:postcode":"1703 SK",
    "sg:province":"Noord-Holland",
    "wof:name":"Boer, De",
    "wof:placetype":"venue"
},
  "geometry": {"coordinates":[4.829801,52.665485],"type":"Point"}
}