{
  "type": "Feature",
  "properties": {
    "addr:full":"Houtse Pad 3 Den Hout Nb North Brabant 4911 AS",
    "addr:housenumber":"3",
    "addr:postcode":"4911 as",
    "addr:street":"Houtse Pad",
    "iso:country":"NL",
    "sg:address":"Houtse Pad 3",
    "sg:city":"Den Hout Nb",
    "sg:orig_category":"Verzekeringen - Verzekeringskantoren",
    "sg:phone":"+31 162 429 569",
    "sg:postcode":"4911 AS",
    "sg:province":"North Brabant",
    "wof:name":"Halters",
    "wof:placetype":"venue"
},
  "geometry": {"coordinates":[4.808203,51.661221],"type":"Point"}
}