{
  "type": "Feature",
  "properties": {
    "addr:full":"Mgr Zwysenln 24 Budel North Brabant 6021 XG",
    "addr:housenumber":"24",
    "addr:postcode":"6021 xg",
    "addr:street":"Zwysenln",
    "iso:country":"NL",
    "sg:address":"Mgr Zwysenln 24",
    "sg:city":"Budel",
    "sg:orig_category":"Autorijscholen",
    "sg:phone":"+31 495 494 478",
    "sg:postcode":"6021 XG",
    "sg:province":"North Brabant",
    "wof:name":"Budel",
    "wof:placetype":"venue"
},
  "geometry": {"coordinates":[5.576494,51.274277],"type":"Point"}
}