{
  "type": "Feature",
  "properties": {
    "addr:full":"Landpoortstraat 13 Ravenstein Noord-Brabant 5371 BT",
    "addr:housenumber":"13",
    "addr:postcode":"5371 bt",
    "addr:street":"Landpoortstraat",
    "iso:country":"NL",
    "sg:address":"Landpoortstraat 13",
    "sg:city":"Ravenstein",
    "sg:orig_category":"Fotostudio'S And Fotografen",
    "sg:phone":"+31 486 413 830",
    "sg:postcode":"5371 BT",
    "sg:province":"Noord-Brabant",
    "wof:name":"Fotostudio Stefan Prinssen",
    "wof:placetype":"venue"
},
  "geometry": {"coordinates":[5.650705,51.795406],"type":"Point"}
}