{
  "type": "Feature",
  "properties": {
    "addr:full":"Alkmaarderstraatweg 75 Castricum Noord-Holland 1901 DA",
    "addr:housenumber":"75;1901",
    "addr:postcode":"da",
    "addr:street":"Alkmaarderstraatweg",
    "iso:country":"NL",
    "sg:address":"Alkmaarderstraatweg 75",
    "sg:city":"Castricum",
    "sg:orig_category":"Film-, Tv- And Videoproductie",
    "sg:phone":"+31 251 652 350",
    "sg:postcode":"1901 DA",
    "sg:province":"Noord-Holland",
    "wof:name":"B.G. Van Den Boogaard Music Productions",
    "wof:placetype":"venue"
},
  "geometry": {"coordinates":[4.671839,52.551033],"type":"Point"}
}