{
  "type": "Feature",
  "properties": {
    "addr:full":"Neptunusweg 9 Leeuwarden Friesland 8938 AA",
    "addr:housenumber":"9",
    "addr:postcode":"8938 aa",
    "addr:street":"Neptunusweg",
    "iso:country":"NL",
    "sg:address":"Neptunusweg 9",
    "sg:city":"Leeuwarden",
    "sg:orig_category":"Autokeuringen",
    "sg:phone":"+31 58 288 2807",
    "sg:postcode":"8938 AA",
    "sg:province":"Friesland",
    "wof:name":"Leeuwarder Motoren-Revisiebedrijf",
    "wof:placetype":"venue"
},
  "geometry": {"coordinates":[5.836579,53.196503],"type":"Point"}
}