{
  "type": "Feature",
  "properties": {
    "addr:full":"Putselaan 58 Rotterdam South Holland 3074 JC",
    "addr:housenumber":"58",
    "addr:postcode":"3074 jc",
    "addr:street":"Putselaan",
    "iso:country":"NL",
    "sg:address":"Putselaan 58",
    "sg:city":"Rotterdam",
    "sg:orig_category":"Metaalbekleding And -Behandeling",
    "sg:phone":"+31 10 484 1194",
    "sg:postcode":"3074 JC",
    "sg:province":"South Holland",
    "wof:name":"Euro Akin",
    "wof:placetype":"venue"
},
  "geometry": {"coordinates":[4.506784,51.898113],"type":"Point"}
}