{
  "type": "Feature",
  "properties": {
    "addr:full":"Vossenbergselaan 11 Kaatsheuvel North Brabant 5171 CA",
    "addr:housenumber":"11",
    "addr:postcode":"5171 ca",
    "addr:street":"Vossenbergselaan",
    "iso:country":"NL",
    "sg:address":"Vossenbergselaan 11",
    "sg:city":"Kaatsheuvel",
    "sg:orig_category":"Zuivelproducten And Spijsoli?n Gh",
    "sg:phone":"+31 416 272 756",
    "sg:postcode":"5171 CA",
    "sg:province":"North Brabant",
    "wof:name":"Rombouts Bv",
    "wof:placetype":"venue"
},
  "geometry": {"coordinates":[5.02768,51.660141],"type":"Point"}
}