{
  "type": "Feature",
  "properties": {
    "addr:full":"Prinsenkade 2 Breda North Brabant 4811 VB",
    "addr:housenumber":"2",
    "addr:postcode":"4811 vb",
    "addr:street":"Prinsenkade",
    "iso:country":"NL",
    "sg:address":"Prinsenkade 2",
    "sg:city":"Breda",
    "sg:classifiers":[
        {
            "category":"Bakery",
            "type":"Food & Drink"
        }
    ],
    "sg:phone":"+31 76 514 6020",
    "sg:postcode":"4811 VB",
    "sg:province":"North Brabant",
    "sg:tags":[
        "brood",
        "banket"
    ],
    "wof:name":"La Boheme Bv",
    "wof:placetype":"venue"
},
  "geometry": {"coordinates":[4.771213,51.588722],"type":"Point"}
}