{
  "type": "Feature",
  "properties": {
    "iso:country":"NL",
    "sg:address":"Stationsweg 109",
    "sg:city":"Wezep",
    "sg:orig_category":"Goederenvervoer Over De Weg",
    "sg:phone":"+31 38 376 5112",
    "sg:postcode":"8091 AC",
    "sg:province":"Gelderland",
    "wof:name":"Transport- En Handelsondern. H.J. Overke",
    "wof:placetype":"venue"
},
  "geometry": {"coordinates":[6.002694,52.453602],"type":"Point"}
}