{
  "type": "Feature",
  "properties": {
    "iso:country":"NL",
    "sg:address":"Kyckerwg 115",
    "sg:city":"De Lier",
    "sg:classifiers":[
        {
            "category":"Manufacturing",
            "subcategory":"Textiles",
            "type":"Manufacturing & Wholesale Goods"
        }
    ],
    "sg:phone":"+31 174 517 727",
    "sg:postcode":"2678 AC",
    "sg:province":"South Holland",
    "sg:tags":[
        "polyester"
    ],
    "wof:name":"J & A Polymat",
    "wof:placetype":"venue"
},
  "geometry": {"coordinates":[4.231983,51.974255],"type":"Point"}
}