{
  "type": "Feature",
  "properties": {
    "addr:full":"Seringwg 16 Ermelo Gelderland 3852 GS",
    "addr:housenumber":"16",
    "addr:postcode":"3852 gs",
    "addr:street":"Seringwg;Gelderland",
    "iso:country":"NL",
    "sg:address":"Seringwg 16",
    "sg:city":"Ermelo",
    "sg:orig_category":"Schoenen - Groothandel",
    "sg:phone":"+31 341 561 325",
    "sg:postcode":"3852 GS",
    "sg:province":"Gelderland",
    "wof:name":"Cherr?",
    "wof:placetype":"venue"
},
  "geometry": {"coordinates":[5.638908,52.296215],"type":"Point"}
}