{
  "type": "Feature",
  "properties": {
    "addr:full":"Bastionstr 13 Breda Noord-Brabant 4817 LD",
    "addr:housenumber":"13",
    "addr:postcode":"4817 ld",
    "addr:street":"Bastionstr",
    "iso:country":"NL",
    "sg:address":"Bastionstr 13",
    "sg:city":"Breda",
    "sg:orig_category":"Webdesign Bureaus",
    "sg:phone":"+31 76 522 3202",
    "sg:postcode":"4817 LD",
    "sg:province":"Noord-Brabant",
    "sg:website":"http://www.100hertz.com",
    "wof:name":"100Hertz",
    "wof:placetype":"venue"
},
  "geometry": {"coordinates":[4.7920689583,51.5916366577],"type":"Point"}
}