{
  "type": "Feature",
  "properties": {
    "addr:full":"C B De Millestr 49 Almere Flevoland 1325 RX",
    "addr:housenumber":"49",
    "addr:postcode":"1325 rx",
    "addr:street":"Flevoland",
    "iso:country":"NL",
    "sg:address":"C B De Millestr 49",
    "sg:city":"Almere",
    "sg:orig_category":"Grafisch Ontwerpers",
    "sg:phone":"+31 36 540 9130",
    "sg:postcode":"1325 RX",
    "sg:province":"Flevoland",
    "sg:website":"http://www.vorminbeeld.nl",
    "wof:name":"Vorm In Beeld",
    "wof:placetype":"venue"
},
  "geometry": {"coordinates":[5.246941,52.360104],"type":"Point"}
}