{
  "type": "Feature",
  "properties": {
    "iso:country":"NL",
    "sg:address":"Graanmarkt 11",
    "sg:city":"Zwaagdyk",
    "sg:orig_category":"Wasmachines En Wasdrogers",
    "sg:phone":"+31 228 350 760",
    "sg:postcode":"1681 PA",
    "sg:province":"Noord-Holland",
    "wof:name":"Beerpoot, E P",
    "wof:placetype":"venue"
},
  "geometry": {"coordinates":[-77.6045074463,40.9946403503],"type":"Point"}
}