{
  "type": "Feature",
  "properties": {
    "addr:full":"Wattstraat 12 Barneveld Gelderland 3771 AG",
    "addr:housenumber":"12",
    "addr:postcode":"3771",
    "addr:street":"Wattstraat;Gelderland",
    "iso:country":"NL",
    "sg:address":"Wattstraat 12",
    "sg:city":"Barneveld",
    "sg:orig_category":"Kantoorartikelen",
    "sg:phone":"+31 342 420 600",
    "sg:postcode":"3771 AG",
    "sg:province":"Gelderland",
    "wof:name":"Brinkplan",
    "wof:placetype":"venue"
},
  "geometry": {"coordinates":[5.5985488892,52.135799408],"type":"Point"}
}