{
  "type": "Feature",
  "properties": {
    "addr:full":"Schinkeldk 9A Reeuwyk Zuid-Holland 2811 PA",
    "addr:housenumber":"9a",
    "addr:postcode":"2811 pa",
    "addr:street":"Schinkeldk",
    "iso:country":"NL",
    "sg:address":"Schinkeldk 9A",
    "sg:city":"Reeuwyk",
    "sg:orig_category":"Bloemen En Planten - Groothandel",
    "sg:phone":"+31 182 392 244",
    "sg:postcode":"2811 PA",
    "sg:province":"Zuid-Holland",
    "wof:name":"Buren Bv, Van",
    "wof:placetype":"venue"
},
  "geometry": {"coordinates":[4.710121,52.062302],"type":"Point"}
}