{
  "type": "Feature",
  "properties": {
    "addr:full":"Stationsstr 81 Putten Gelderland 3881 AB",
    "addr:housenumber":"81",
    "addr:postcode":"3881 ab",
    "addr:street":"Stationsstr;Gelderland",
    "iso:country":"NL",
    "sg:address":"Stationsstr 81",
    "sg:city":"Putten",
    "sg:orig_category":"Administratie- En Boekhoudkantoren",
    "sg:phone":"+31 341 358 102",
    "sg:postcode":"3881 AB",
    "sg:province":"Gelderland",
    "wof:name":"Fido",
    "wof:placetype":"venue"
},
  "geometry": {"coordinates":[5.587172,52.26281],"type":"Point"}
}