{
  "type": "Feature",
  "properties": {
    "iso:country":"NL",
    "sg:address":"Voeghouten 2",
    "sg:city":"Slochteren",
    "sg:orig_category":"Goederenvervoer Over De Weg",
    "sg:phone":"+31 598 421 621",
    "sg:postcode":"9621 DB",
    "sg:province":"Groningen",
    "wof:name":"S Dijkman Bv",
    "wof:placetype":"venue"
},
  "geometry": {"coordinates":[6.79962,53.221981],"type":"Point"}
}