{
  "type": "Feature",
  "properties": {
    "addr:full":"Lavendelberg 28 Roosendaal Noord-Brabant 4708 LE",
    "addr:housenumber":"28",
    "addr:postcode":"4708 le",
    "addr:street":"Lavendelberg",
    "iso:country":"NL",
    "sg:address":"Lavendelberg 28",
    "sg:city":"Roosendaal",
    "sg:orig_category":"Verzekerings- Maatschappijen",
    "sg:phone":"+31 165 567 335",
    "sg:postcode":"4708 LE",
    "sg:province":"Noord-Brabant",
    "wof:name":"Zlm",
    "wof:placetype":"venue"
},
  "geometry": {"coordinates":[4.432156,51.516521],"type":"Point"}
}