{
  "type": "Feature",
  "properties": {
    "addr:full":"Middel Broekweg 79 Honselersdijk South Holland 2675 KJ",
    "addr:housenumber":"79",
    "addr:postcode":"2675 kj",
    "addr:street":"Middel Broekweg",
    "iso:country":"NL",
    "sg:address":"Middel Broekweg 79",
    "sg:city":"Honselersdijk",
    "sg:orig_category":"Verhuur Bouwmachines",
    "sg:phone":"+31 174 623 223",
    "sg:postcode":"2675 KJ",
    "sg:province":"South Holland",
    "wof:name":"P.J. Den Haan, Machineverhuur",
    "wof:placetype":"venue"
},
  "geometry": {"coordinates":[4.240295,52.006222],"type":"Point"}
}