{
  "type": "Feature",
  "properties": {
    "addr:full":"Oosthaven 48 Gouda Zuid-Holland 2801 PE",
    "addr:housenumber":"48",
    "addr:postcode":"2801 pe",
    "addr:street":"Oosthaven",
    "iso:country":"NL",
    "sg:address":"Oosthaven 48",
    "sg:city":"Gouda",
    "sg:orig_category":"Psychologen",
    "sg:phone":"+31 182 678 809",
    "sg:postcode":"2801 PE",
    "sg:province":"Zuid-Holland",
    "wof:name":"Hartog, Drs H Den",
    "wof:placetype":"venue"
},
  "geometry": {"coordinates":[4.712992,52.00835],"type":"Point"}
}