{
  "type": "Feature",
  "properties": {
    "addr:full":"Europaln N 33 Budel Noord-Brabant 6021 EE",
    "addr:postcode":"6021 ee",
    "addr:street":"N 33",
    "iso:country":"NL",
    "sg:address":"Europaln N 33",
    "sg:city":"Budel",
    "sg:orig_category":"Hoortoestellen",
    "sg:phone":"+31 495 494 006",
    "sg:postcode":"6021 EE",
    "sg:province":"Noord-Brabant",
    "wof:name":"Mierlo, Van",
    "wof:placetype":"venue"
},
  "geometry": {"coordinates":[5.576494,51.274277],"type":"Point"}
}