{
  "type": "Feature",
  "properties": {
    "addr:full":"Javalaan 6 Apeldoorn Gelderland 7314 BX",
    "addr:housenumber":"6",
    "addr:postcode":"7314 bx",
    "addr:street":"Javalaan;Gelderland",
    "iso:country":"NL",
    "sg:address":"Javalaan 6",
    "sg:city":"Apeldoorn",
    "sg:orig_category":"Vertaal- And Tolkenbureaus",
    "sg:phone":"+31 55 522 4175",
    "sg:postcode":"7314 BX",
    "sg:province":"Gelderland",
    "wof:name":"Tt 80",
    "wof:placetype":"venue"
},
  "geometry": {"coordinates":[5.948571,52.221294],"type":"Point"}
}