{
  "type": "Feature",
  "properties": {
    "addr:full":"Kapittelstraat 13 Groessen Gelderland 6923 AV",
    "addr:housenumber":"13",
    "addr:postcode":"6923 av",
    "addr:street":"Kapittelstraat;Gelderland",
    "iso:country":"NL",
    "sg:address":"Kapittelstraat 13",
    "sg:city":"Groessen",
    "sg:orig_category":"Bouwmaterialen Gh",
    "sg:phone":"+31 316 341 167",
    "sg:postcode":"6923 AV",
    "sg:province":"Gelderland",
    "wof:name":"Berendsen Vof",
    "wof:placetype":"venue"
},
  "geometry": {"coordinates":[6.025657,51.930901],"type":"Point"}
}