{
  "type": "Feature",
  "properties": {
    "addr:full":"Vloeiveld 12 Gilze Noord-Brabant 5126 RG",
    "addr:housenumber":"12",
    "addr:postcode":"5126 rg",
    "addr:street":"Vloeiveld",
    "iso:country":"NL",
    "sg:address":"Vloeiveld 12",
    "sg:city":"Gilze",
    "sg:orig_category":"Kunststoffen- Verwerkende Industrie",
    "sg:phone":"+31 161 454 677",
    "sg:postcode":"5126 RG",
    "sg:province":"Noord-Brabant",
    "sg:website":"http://www.mbplastics.co.uk",
    "wof:name":"Mb Plastics Holland",
    "wof:placetype":"venue"
},
  "geometry": {"coordinates":[4.944259,51.546154],"type":"Point"}
}