{
  "type": "Feature",
  "properties": {
    "addr:full":"Schopenhauerstr 42 Apeldoorn Gelderland 7323 MD",
    "addr:housenumber":"42",
    "addr:postcode":"7323",
    "addr:street":"Schopenhauerstr;Gelderland",
    "iso:country":"NL",
    "sg:address":"Schopenhauerstr 42",
    "sg:city":"Apeldoorn",
    "sg:orig_category":"Verenigingen En Stichtingen",
    "sg:phone":"+31 55 366 0404",
    "sg:postcode":"7323 MD",
    "sg:province":"Gelderland",
    "wof:name":"Huurdersver Zevenhuizen",
    "wof:placetype":"venue"
},
  "geometry": {"coordinates":[6.002823,52.225399],"type":"Point"}
}