{
  "type": "Feature",
  "properties": {
    "addr:full":"Fahrenheitstraat 48 Ijmuiden North Holland 1973 RL",
    "addr:housenumber":"48",
    "addr:postcode":"1973 rl",
    "addr:street":"Fahrenheitstraat",
    "iso:country":"NL",
    "sg:address":"Fahrenheitstraat 48",
    "sg:city":"Ijmuiden",
    "sg:orig_category":"Makelaars In Onroerend Goed",
    "sg:phone":"+31 255 517 682",
    "sg:postcode":"1973 RL",
    "sg:province":"North Holland",
    "wof:name":"Gravemaker En Van Den Oord",
    "wof:placetype":"venue"
},
  "geometry": {"coordinates":[4.603045,52.457245],"type":"Point"}
}