{
  "type": "Feature",
  "properties": {
    "iso:country":"NL",
    "sg:address":"Varkensmarkt 10",
    "sg:city":"Ijzendijke",
    "sg:orig_category":"Fotostudio'S And Fotografen",
    "sg:phone":"+31 117 302 196",
    "sg:postcode":"4515 AK",
    "sg:province":"Zeeland",
    "wof:name":"Folklife Photography",
    "wof:placetype":"venue"
},
  "geometry": {"coordinates":[3.618545,51.321865],"type":"Point"}
}