{
  "type": "Feature",
  "properties": {
    "addr:full":"Van Anrooystraat 54 'S Gravenhage Zuid-Holland 2551 RC",
    "addr:housenumber":"54",
    "addr:postcode":"2551 rc",
    "addr:street":"Van Anrooystraat;' S",
    "iso:country":"NL",
    "sg:address":"Van Anrooystraat 54",
    "sg:city":"'S Gravenhage",
    "sg:orig_category":"Metaalbekleding And -Behandeling",
    "sg:phone":"+31 70 397 3042",
    "sg:postcode":"2551 RC",
    "sg:province":"Zuid-Holland",
    "wof:name":"M.H. De Graaf",
    "wof:placetype":"venue"
},
  "geometry": {"coordinates":[4.234453,52.056248],"type":"Point"}
}