{
  "type": "Feature",
  "properties": {
    "addr:full":"Min. Cremerstraat 7 Zeijerveld Drenthe 9488 TA",
    "addr:housenumber":"7",
    "addr:postcode":"9488 ta",
    "addr:street":"Min. Cremerstraat",
    "iso:country":"NL",
    "sg:address":"Min. Cremerstraat 7",
    "sg:city":"Zeijerveld",
    "sg:orig_category":"Werving And Selectie Van Tijdelijk Personeel And Uitzendkantoren",
    "sg:phone":"+31 592 291 555",
    "sg:postcode":"9488 TA",
    "sg:province":"Drenthe",
    "wof:name":"Sterk",
    "wof:placetype":"venue"
},
  "geometry": {"coordinates":[6.527946949,53.0370635986],"type":"Point"}
}