{
  "type": "Feature",
  "properties": {
    "iso:country":"NL",
    "sg:address":"Kerkweg 21",
    "sg:city":"Maarssen",
    "sg:orig_category":"Diverse Opleidingen And Onderwijs",
    "sg:phone":"+31 346 570 350",
    "sg:postcode":"3603 CL",
    "sg:province":"Utrecht",
    "wof:name":"Douma Studiebegeleidingsinstituut",
    "wof:placetype":"venue"
},
  "geometry": {"coordinates":[5.042111,52.138168],"type":"Point"}
}