{
  "type": "Feature",
  "properties": {
    "addr:full":"Stadionweg 149 Amsterdam Noord-Holland 1076 NM",
    "addr:housenumber":"149",
    "addr:postcode":"1076",
    "addr:street":"Stadionweg",
    "iso:country":"NL",
    "sg:address":"Stadionweg 149",
    "sg:city":"Amsterdam",
    "sg:orig_category":"Zuivelproducten",
    "sg:phone":"+31 20 671 3278",
    "sg:postcode":"1076 NM",
    "sg:province":"Noord-Holland",
    "wof:name":"J.W.D. Van Wijk",
    "wof:placetype":"venue"
},
  "geometry": {"coordinates":[4.864486,52.345928],"type":"Point"}
}