{
  "type": "Feature",
  "properties": {
    "iso:country":"NL",
    "sg:address":"Vioolhof 18",
    "sg:city":"Barendrecht",
    "sg:orig_category":"Administratie- En Boekhoudkantoren",
    "sg:phone":"+31 180 619 303",
    "sg:postcode":"2992 GJ",
    "sg:province":"Zuid-Holland",
    "wof:name":"Avh",
    "wof:placetype":"venue"
},
  "geometry": {"coordinates":[4.522564,51.855057],"type":"Point"}
}