{
  "type": "Feature",
  "properties": {
    "addr:full":"Paemhofstr 19 Maastricht Limburg 6227 XR",
    "addr:housenumber":"19",
    "addr:postcode":"6227 xr",
    "addr:street":"Paemhofstr",
    "iso:country":"NL",
    "sg:address":"Paemhofstr 19",
    "sg:city":"Maastricht",
    "sg:orig_category":"Administratie- En Boekhoudkantoren",
    "sg:phone":"+31 43 361 5785",
    "sg:postcode":"6227 XR",
    "sg:province":"Limburg",
    "wof:name":"Escla",
    "wof:placetype":"venue"
},
  "geometry": {"coordinates":[5.736464,50.841019],"type":"Point"}
}