{
  "type": "Feature",
  "properties": {
    "addr:full":"Burgemeester Merkusstr 18 Delfgauw Zuid-Holland 2645 NJ",
    "addr:housenumber":"18",
    "addr:postcode":"2645 nj",
    "addr:street":"Burgemeester Merkusstr",
    "iso:country":"NL",
    "sg:address":"Burgemeester Merkusstr 18",
    "sg:city":"Delfgauw",
    "sg:orig_category":"Wegen And Sportterreinen",
    "sg:phone":"+31 6 22932618",
    "sg:postcode":"2645 NJ",
    "sg:province":"Zuid-Holland",
    "wof:name":"O De Vries Bestratingen",
    "wof:placetype":"venue"
},
  "geometry": {"coordinates":[4.3972620964,52.0093002319],"type":"Point"}
}