{
  "type": "Feature",
  "properties": {
    "iso:country":"NL",
    "sg:address":"Alpenln 259",
    "sg:city":"Tilburg",
    "sg:orig_category":"Plafonds",
    "sg:phone":"+31 13 514 4875",
    "sg:postcode":"5022 LK",
    "sg:province":"Noord-Brabant",
    "wof:name":"Coplamon",
    "wof:placetype":"venue"
},
  "geometry": {"coordinates":[5.09431,51.541271],"type":"Point"}
}