{
  "type": "Feature",
  "properties": {
    "iso:country":"NL",
    "sg:address":"2E Van Leyden Gaelstraat 43",
    "sg:city":"Vlaardingen",
    "sg:orig_category":"Pleziervaartuigen And Reparatie",
    "sg:phone":"+31 10 434 9502",
    "sg:postcode":"3134 LH",
    "sg:province":"Zuid-Holland",
    "wof:name":"Moretec Int",
    "wof:placetype":"venue"
},
  "geometry": {"coordinates":[4.354214,51.90749],"type":"Point"}
}