{
  "type": "Feature",
  "properties": {
    "addr:full":"Rooversbroekdijk 109 Lisse Zuid-Holland 2161 LP",
    "addr:housenumber":"109",
    "addr:postcode":"2161 lp",
    "addr:street":"Rooversbroekdijk",
    "iso:country":"NL",
    "sg:address":"Rooversbroekdijk 109",
    "sg:city":"Lisse",
    "sg:orig_category":"Bloemen And Planten",
    "sg:phone":"+31 252 414 659",
    "sg:postcode":"2161 LP",
    "sg:province":"Zuid-Holland",
    "wof:name":"Tuin- En Bloemencentrum Piet Baars Vof",
    "wof:placetype":"venue"
},
  "geometry": {"coordinates":[4.554412,52.241009],"type":"Point"}
}