{
  "type": "Feature",
  "properties": {
    "addr:full":"Korvelseweg 114 Tilburg North Brabant 5025 JK",
    "addr:housenumber":"114",
    "addr:postcode":"5025 jk",
    "addr:street":"Korvelseweg",
    "iso:country":"NL",
    "sg:address":"Korvelseweg 114",
    "sg:city":"Tilburg",
    "sg:orig_category":"Naai- And Breimachines",
    "sg:phone":"+31 13 535 5414",
    "sg:postcode":"5025 JK",
    "sg:province":"North Brabant",
    "wof:name":"Habotex Naaimachines",
    "wof:placetype":"venue"
},
  "geometry": {"coordinates":[5.075117,51.551189],"type":"Point"}
}