{
  "type": "Feature",
  "properties": {
    "addr:full":"Kruisstraat 10 Munstergeleen Limburg 6151 BP",
    "addr:housenumber":"10",
    "addr:postcode":"6151 bp",
    "addr:street":"Kruisstraat",
    "iso:country":"NL",
    "sg:address":"Kruisstraat 10",
    "sg:city":"Munstergeleen",
    "sg:orig_category":"Bedrijfs- And Managementsconsultants",
    "sg:phone":"+31 46 452 4155",
    "sg:postcode":"6151 BP",
    "sg:province":"Limburg",
    "wof:name":"Fimab Bv",
    "wof:placetype":"venue"
},
  "geometry": {"coordinates":[5.869395,50.972881],"type":"Point"}
}