{
  "type": "Feature",
  "properties": {
    "addr:full":"Raadhuisstr 63 Roosendaal Noord-Brabant 4701 PM",
    "addr:housenumber":"63",
    "addr:postcode":"4701 pm",
    "addr:street":"Raadhuisstr",
    "iso:country":"NL",
    "sg:address":"Raadhuisstr 63",
    "sg:city":"Roosendaal",
    "sg:orig_category":"Notarissen En Notariskantoren",
    "sg:phone":"+31 165 544 930",
    "sg:postcode":"4701 PM",
    "sg:province":"Noord-Brabant",
    "sg:website":"http://www.haansbeijsens.nl",
    "wof:name":"Haans Beijsens",
    "wof:placetype":"venue"
},
  "geometry": {"coordinates":[4.459745,51.531693],"type":"Point"}
}