{
  "type": "Feature",
  "properties": {
    "addr:full":"J W Hagemanstr 8 Eibergen Gelderland 7151 AG",
    "addr:housenumber":"8",
    "addr:postcode":"7151",
    "addr:street":"Gelderland",
    "iso:country":"NL",
    "sg:address":"J W Hagemanstr 8",
    "sg:city":"Eibergen",
    "sg:orig_category":"Bloemen En Planten",
    "sg:phone":"+31 545 472 058",
    "sg:postcode":"7151 AG",
    "sg:province":"Gelderland",
    "wof:name":"All Seasons",
    "wof:placetype":"venue"
},
  "geometry": {"coordinates":[6.650613,52.102413],"type":"Point"}
}