{
  "type": "Feature",
  "properties": {
    "addr:full":"Gr Florisstr 60B Rotterdam Zuid-Holland 3021 CJ",
    "addr:housenumber":"60b",
    "addr:postcode":"3021 cj",
    "iso:country":"NL",
    "sg:address":"Gr Florisstr 60B",
    "sg:city":"Rotterdam",
    "sg:orig_category":"Webdesign Bureaus",
    "sg:phone":"+31 10 476 6060",
    "sg:postcode":"3021 CJ",
    "sg:province":"Zuid-Holland",
    "wof:name":"Klik Prod",
    "wof:placetype":"venue"
},
  "geometry": {"coordinates":[4.4582509995,51.919960022],"type":"Point"}
}