{
  "type": "Feature",
  "properties": {
    "addr:full":"Westduinweg 206 'S Gravenhage Zuid-Holland 2583 AJ",
    "addr:housenumber":"206 '",
    "addr:postcode":"2583 aj",
    "addr:street":"Westduinweg",
    "iso:country":"NL",
    "sg:address":"Westduinweg 206",
    "sg:city":"'S Gravenhage",
    "sg:orig_category":"Schilderwerk",
    "sg:phone":"+31 70 355 2573",
    "sg:postcode":"2583 AJ",
    "sg:province":"Zuid-Holland",
    "wof:name":"Bv Schildersbedrijf V/H Fa A. Van Der Stal En Zoon",
    "wof:placetype":"venue"
},
  "geometry": {"coordinates":[4.27264,52.100311],"type":"Point"}
}