{
  "type": "Feature",
  "properties": {
    "addr:full":"Amerikaring 58 Amersfoort Utrecht 3823 HT",
    "addr:housenumber":"58",
    "addr:postcode":"3823 ht",
    "addr:street":"Amerikaring",
    "iso:country":"NL",
    "sg:address":"Amerikaring 58",
    "sg:city":"Amersfoort",
    "sg:classifiers":[
        {
            "category":"Professional",
            "subcategory":"Management & Consulting",
            "type":"Services"
        }
    ],
    "sg:phone":"+31 6 11151556",
    "sg:postcode":"3823 HT",
    "sg:province":"Utrecht",
    "sg:tags":[
        "relation",
        "adviesbureaus",
        "public"
    ],
    "sg:website":"http://www.firstview.nl",
    "wof:name":"First View",
    "wof:placetype":"venue"
},
  "geometry": {"coordinates":[5.391271,52.192478],"type":"Point"}
}