{
  "type": "Feature",
  "properties": {
    "iso:country":"NL",
    "sg:address":"Westerstr 294",
    "sg:city":"Enkhuizen",
    "sg:classifiers":[
        {
            "category":"Travel",
            "subcategory":"Hotels & Motels",
            "type":"Entertainment"
        }
    ],
    "sg:phone":"+31 228 314 966",
    "sg:postcode":"1601 AS",
    "sg:province":"North Holland",
    "wof:name":"Koepoort, De",
    "wof:placetype":"venue"
},
  "geometry": {"coordinates":[5.277398,52.701706],"type":"Point"}
}