{
  "type": "Feature",
  "properties": {
    "addr:full":"Osdorppln 142 Amsterdam Noord-Holland 1068 EN",
    "addr:housenumber":"142",
    "addr:postcode":"1068 en",
    "iso:country":"NL",
    "sg:address":"Osdorppln 142",
    "sg:city":"Amsterdam",
    "sg:orig_category":"Woningbureaus",
    "sg:phone":"+31 20 410 1220",
    "sg:postcode":"1068 EN",
    "sg:province":"Noord-Holland",
    "sg:website":"http://www.expatapartments.nl",
    "wof:name":"Expat Apartment Service",
    "wof:placetype":"venue"
},
  "geometry": {"coordinates":[4.8058009148,52.3602104187],"type":"Point"}
}