{
  "type": "Feature",
  "properties": {
    "addr:full":"Sonderdankstraat 2 'S Gravenhage Zuid-Holland 2596 SE",
    "addr:housenumber":"2 ';2596",
    "addr:street":"Sonderdankstraat;Se",
    "iso:country":"NL",
    "sg:address":"Sonderdankstraat 2",
    "sg:city":"'S Gravenhage",
    "sg:orig_category":"Technische Studies And Onderzoek",
    "sg:phone":"+31 70 328 1260",
    "sg:postcode":"2596 SE",
    "sg:province":"Zuid-Holland",
    "wof:name":"Ir J L Klei Raadgevend Ing",
    "wof:placetype":"venue"
},
  "geometry": {"coordinates":[4.319009,52.099228],"type":"Point"}
}