{
  "type": "Feature",
  "properties": {
    "addr:full":"Waalbandk 24 Nieuwaal Gelderland 5313 AL",
    "addr:housenumber":"24",
    "addr:postcode":"5313",
    "addr:street":"Waalbandk;Gelderland",
    "iso:country":"NL",
    "sg:address":"Waalbandk 24",
    "sg:city":"Nieuwaal",
    "sg:orig_category":"Fietsen En Bromfietsen",
    "sg:phone":"+31 418 562 221",
    "sg:postcode":"5313 AL",
    "sg:province":"Gelderland",
    "wof:name":"Timmer, G C",
    "wof:placetype":"venue"
},
  "geometry": {"coordinates":[5.17467,51.81089],"type":"Point"}
}