{
  "type": "Feature",
  "properties": {
    "addr:full":"Alouette Erf 14 Capelle Ad Yssel South Holland 2907 BA",
    "addr:housenumber":"14",
    "addr:postcode":"2907 ba",
    "addr:street":"Alouette Erf;Yssel",
    "iso:country":"NL",
    "sg:address":"Alouette Erf 14",
    "sg:city":"Capelle Ad Yssel",
    "sg:orig_category":"Video - Faciliteiten En Producties",
    "sg:phone":"+31 10 450 9322",
    "sg:postcode":"2907 BA",
    "sg:province":"South Holland",
    "wof:name":"Exposure",
    "wof:placetype":"venue"
},
  "geometry": {"coordinates":[4.573667,51.949734],"type":"Point"}
}