{
  "type": "Feature",
  "properties": {
    "addr:full":"Wilhelminastraat 22 Mijnsheerenland Zuid-Holland 3271 BZ",
    "addr:housenumber":"22",
    "addr:postcode":"3271 bz",
    "addr:street":"Wilhelminastraat",
    "iso:country":"NL",
    "sg:address":"Wilhelminastraat 22",
    "sg:city":"Mijnsheerenland",
    "sg:orig_category":"Postkantoren",
    "sg:phone":"+31 186 601 847",
    "sg:postcode":"3271 BZ",
    "sg:province":"Zuid-Holland",
    "wof:name":"Ptt Post",
    "wof:placetype":"venue"
},
  "geometry": {"coordinates":[4.49268,51.797401],"type":"Point"}
}