{
  "type": "Feature",
  "properties": {
    "iso:country":"NL",
    "sg:address":"Pompmolenln 43B",
    "sg:city":"Woerden",
    "sg:orig_category":"Kantoorbenodigdheden",
    "sg:phone":"+31 348 424 416",
    "sg:postcode":"3447 GK",
    "sg:province":"Utrecht",
    "wof:name":"Lint, Van",
    "wof:placetype":"venue"
},
  "geometry": {"coordinates":[4.8866329193,52.0753707886],"type":"Point"}
}