{
  "type": "Feature",
  "properties": {
    "addr:full":"Hoekbeemden 12 Terheijden Noord-Brabant 4844 VL",
    "addr:housenumber":"12",
    "addr:postcode":"4844 vl",
    "addr:street":"Hoekbeemden",
    "iso:country":"NL",
    "sg:address":"Hoekbeemden 12",
    "sg:city":"Terheijden",
    "sg:orig_category":"Boekhouders",
    "sg:phone":"+31 76 593 3922",
    "sg:postcode":"4844 VL",
    "sg:province":"Noord-Brabant",
    "wof:name":"R. Jansen",
    "wof:placetype":"venue"
},
  "geometry": {"coordinates":[4.759296,51.64138],"type":"Point"}
}