{
  "type": "Feature",
  "properties": {
    "addr:full":"Gerard Doustraat 72 Zutphen Gelderland 7204 EV",
    "addr:housenumber":"72",
    "addr:postcode":"7204 ev",
    "addr:street":"Gerard Doustraat;Gelderland",
    "iso:country":"NL",
    "sg:address":"Gerard Doustraat 72",
    "sg:city":"Zutphen",
    "sg:orig_category":"Kappers",
    "sg:phone":"+31 575 516 872",
    "sg:postcode":"7204 EV",
    "sg:province":"Gelderland",
    "wof:name":"Dameskapsalon Calot",
    "wof:placetype":"venue"
},
  "geometry": {"coordinates":[6.2095599174,52.1373023987],"type":"Point"}
}