{
  "type": "Feature",
  "properties": {
    "addr:full":"Kweekgrasstr 23 Almere NL. 1313 BZ",
    "addr:housenumber":"23",
    "addr:postcode":"1313 bz",
    "addr:street":"Kweekgrasstr;Nl.",
    "iso:country":"NL",
    "sg:address":"Kweekgrasstr 23",
    "sg:city":"Almere",
    "sg:orig_category":"Gordijnen",
    "sg:phone":"+31 36 531 1584",
    "sg:postcode":"1313 BZ",
    "sg:province":"NL.",
    "sg:website":"http://www.hautecoutureinwooncultuur.nl",
    "wof:name":"Haute Couture In Wooncultuur",
    "wof:placetype":"venue"
},
  "geometry": {"coordinates":[5.200901,52.386353],"type":"Point"}
}