{
  "type": "Feature",
  "properties": {
    "addr:full":"Stettinwg 9 Groningen Groningen 9723 HD",
    "addr:housenumber":"9",
    "addr:postcode":"9723 hd",
    "addr:street":"Stettinwg",
    "iso:country":"NL",
    "sg:address":"Stettinwg 9",
    "sg:city":"Groningen",
    "sg:orig_category":"Kunststoffen - Fabrieken En Groothandel",
    "sg:phone":"+31 50 547 2180",
    "sg:postcode":"9723 HD",
    "sg:province":"Groningen",
    "wof:name":"Beuker",
    "wof:placetype":"venue"
},
  "geometry": {"coordinates":[6.604005,53.21875],"type":"Point"}
}