{
  "type": "Feature",
  "properties": {
    "iso:country":"NL",
    "sg:address":"Dwarskd 13",
    "sg:city":"Nootdorp",
    "sg:orig_category":"Webdesign Bureaus",
    "sg:phone":"+31 15 310 1035",
    "sg:postcode":"2631 NA",
    "sg:province":"Zuid-Holland",
    "wof:name":"Area 52",
    "wof:placetype":"venue"
},
  "geometry": {"coordinates":[4.3920249939,52.0427017212],"type":"Point"}
}