{
  "type": "Feature",
  "properties": {
    "addr:full":"Langeraarsewg 34A Ter Aar South Holland 2461 CK",
    "addr:housenumber":"34a",
    "addr:postcode":"2461 ck",
    "addr:street":"Langeraarsewg",
    "iso:country":"NL",
    "sg:address":"Langeraarsewg 34A",
    "sg:city":"Ter Aar",
    "sg:orig_category":"Ballonvaarten En -Reclame",
    "sg:phone":"+31 6 53761794",
    "sg:postcode":"2461 CK",
    "sg:province":"South Holland",
    "sg:website":"http://www.luchtkastelen.nl",
    "wof:name":"Nog Bv",
    "wof:placetype":"venue"
},
  "geometry": {"coordinates":[4.71726,52.194359],"type":"Point"}
}