{
  "type": "Feature",
  "properties": {
    "addr:full":"Doonweg 7 Eerbeek Gelderland 6961 LK",
    "addr:housenumber":"7",
    "addr:postcode":"6961 lk",
    "addr:street":"Doonweg;Gelderland",
    "iso:country":"NL",
    "sg:address":"Doonweg 7",
    "sg:city":"Eerbeek",
    "sg:orig_category":"Bedrijfs- And Managementsconsultants",
    "sg:phone":"+31 313 654 345",
    "sg:postcode":"6961 LK",
    "sg:province":"Gelderland",
    "wof:name":"Adviesbureau Van Zadelhoff",
    "wof:placetype":"venue"
},
  "geometry": {"coordinates":[6.067121,52.095726],"type":"Point"}
}