{
  "type": "Feature",
  "properties": {
    "addr:full":"H V Borsselenkd 1 Amstelveen Noord-Holland 1181 AW",
    "addr:housenumber":"1",
    "addr:postcode":"1181 aw",
    "addr:street":"H;Borsselenkd",
    "iso:country":"NL",
    "sg:address":"H V Borsselenkd 1",
    "sg:city":"Amstelveen",
    "sg:classifiers":[
        {
            "category":"Personal",
            "subcategory":"Nail Salon",
            "type":"Services"
        }
    ],
    "sg:phone":"+31 20 640 4075",
    "sg:postcode":"1181 AW",
    "sg:province":"Noord-Holland",
    "sg:tags":[
        "pedicure"
    ],
    "wof:name":"Nelemans, Cockie",
    "wof:placetype":"venue"
},
  "geometry": {"coordinates":[4.856945,52.303444],"type":"Point"}
}