{
  "type": "Feature",
  "properties": {
    "addr:full":"Burensedk 34 Buurmalsen Gelderland 4197 RJ",
    "addr:housenumber":"34",
    "addr:postcode":"4197 rj",
    "addr:street":"Burensedk;Gelderland",
    "iso:country":"NL",
    "sg:address":"Burensedk 34",
    "sg:city":"Buurmalsen",
    "sg:orig_category":"Fotoreportages",
    "sg:phone":"+31 345 577 019",
    "sg:postcode":"4197 RJ",
    "sg:province":"Gelderland",
    "sg:website":"http://www.fotopix.nl",
    "wof:name":"Fotopix",
    "wof:placetype":"venue"
},
  "geometry": {"coordinates":[5.295759,51.892559],"type":"Point"}
}