{
  "type": "Feature",
  "properties": {
    "addr:full":"Kortestreek 12 Lemmer Friesland 8531 JE",
    "addr:housenumber":"12",
    "addr:postcode":"8531 je",
    "addr:street":"Kortestreek",
    "iso:country":"NL",
    "sg:address":"Kortestreek 12",
    "sg:city":"Lemmer",
    "sg:orig_category":"Banken",
    "sg:phone":"+31 514 568 311",
    "sg:postcode":"8531 JE",
    "sg:province":"Friesland",
    "sg:website":"http://www.sns.nl",
    "wof:name":"Sns",
    "wof:placetype":"venue"
},
  "geometry": {"coordinates":[5.709921,52.84531],"type":"Point"}
}