{
  "type": "Feature",
  "properties": {
    "addr:full":"Dorsmolen 13 Wieringerwerf Noord-Holland 1771 PA",
    "addr:housenumber":"13",
    "addr:postcode":"1771 pa",
    "addr:street":"Dorsmolen",
    "iso:country":"NL",
    "sg:address":"Dorsmolen 13",
    "sg:city":"Wieringerwerf",
    "sg:orig_category":"Woninginrichting",
    "sg:phone":"+31 227 603 435",
    "sg:postcode":"1771 PA",
    "sg:province":"Noord-Holland",
    "wof:name":"Rien Deijkers Bv",
    "wof:placetype":"venue"
},
  "geometry": {"coordinates":[5.0278019905,52.843372345],"type":"Point"}
}