{
  "type": "Feature",
  "properties": {
    "addr:full":"Slotwg 17 Egmond Ad Hoef Noord-Holland 1934 CM",
    "addr:housenumber":"17",
    "addr:postcode":"1934 cm",
    "addr:street":"Slotwg",
    "iso:country":"NL",
    "sg:address":"Slotwg 17",
    "sg:city":"Egmond Ad Hoef",
    "sg:orig_category":"Galeries",
    "sg:phone":"+31 72 506 2645",
    "sg:postcode":"1934 CM",
    "sg:province":"Noord-Holland",
    "wof:name":"Kapberg, De",
    "wof:placetype":"venue"
},
  "geometry": {"coordinates":[4.651809,52.621254],"type":"Point"}
}