{
  "type": "Feature",
  "properties": {
    "addr:full":"Grote Markt 12 Goes Ohio 4461 AJ",
    "addr:housenumber":"12",
    "addr:postcode":"4461 aj",
    "addr:street":"Grote Markt",
    "iso:country":"NL",
    "sg:address":"Grote Markt 12",
    "sg:city":"Goes",
    "sg:orig_category":"Werving And Selectie Van Tijdelijk Personeel And Uitzendkantoren",
    "sg:phone":"+31 113 223 220",
    "sg:postcode":"4461 AJ",
    "sg:province":"Ohio",
    "wof:name":"Vedior",
    "wof:placetype":"venue"
},
  "geometry": {"coordinates":[-83.9141693115,39.7688331604],"type":"Point"}
}