{
  "type": "Feature",
  "properties": {
    "addr:full":"Walenburghof 17 Rotterdam Zuid-Holland 3033  H",
    "addr:housenumber":"17;3033 h",
    "addr:street":"Walenburghof",
    "iso:country":"NL",
    "sg:address":"Walenburghof 17",
    "sg:city":"Rotterdam",
    "sg:orig_category":"Autoverhuur",
    "sg:phone":"+31 10 465 6400",
    "sg:postcode":"3033  H",
    "sg:province":"Zuid-Holland",
    "wof:name":"Europcar",
    "wof:placetype":"venue"
},
  "geometry": {"coordinates":[4.463708,51.925121],"type":"Point"}
}