{
  "type": "Feature",
  "properties": {
    "addr:full":"Kerkln Zunderdorp 25 Amsterdam Noord-Holland 1027 AN",
    "addr:housenumber":"25",
    "addr:postcode":"1027 an",
    "addr:street":"Kerkln Zunderdorp",
    "iso:country":"NL",
    "sg:address":"Kerkln Zunderdorp 25",
    "sg:city":"Amsterdam",
    "sg:orig_category":"Kampeerartikelen",
    "sg:phone":"+31 20 632 5030",
    "sg:postcode":"1027 AN",
    "sg:province":"Noord-Holland",
    "wof:name":"Tatteljee",
    "wof:placetype":"venue"
},
  "geometry": {"coordinates":[4.9662709236,52.4069976807],"type":"Point"}
}