{
  "type": "Feature",
  "properties": {
    "iso:country":"NL",
    "sg:address":"Raadhuispln 58-60",
    "sg:city":"Wervershoof",
    "sg:orig_category":"Cafetaria'S",
    "sg:phone":"+31 228 584 659",
    "sg:postcode":"1693 EA",
    "sg:province":"Noord-Holland",
    "wof:name":"Molenhoek, De",
    "wof:placetype":"venue"
},
  "geometry": {"coordinates":[5.150684,52.728378],"type":"Point"}
}