{
  "type": "Feature",
  "properties": {
    "addr:full":"Karveel 48-77 Lelystad NL. 8242 VM",
    "addr:postcode":"48-77;8242 vm",
    "addr:street":"Karveel;Nl.",
    "iso:country":"NL",
    "sg:address":"Karveel 48-77",
    "sg:city":"Lelystad",
    "sg:orig_category":"Architecten",
    "sg:phone":"+31 320 231 806",
    "sg:postcode":"8242 VM",
    "sg:province":"NL.",
    "wof:name":"Rehdeco",
    "wof:placetype":"venue"
},
  "geometry": {"coordinates":[5.45982,52.523998],"type":"Point"}
}