{
  "type": "Feature",
  "properties": {
    "addr:full":"Raalterwg 54 Holten NL.08 7451 KV",
    "addr:housenumber":"54;nl.08",
    "addr:postcode":"7451 kv",
    "addr:street":"Raalterwg",
    "iso:country":"NL",
    "sg:address":"Raalterwg 54",
    "sg:city":"Holten",
    "sg:orig_category":"Kantoor- En Secretariaatsservice",
    "sg:phone":"+31 572 328 111",
    "sg:postcode":"7451 KV",
    "sg:province":"NL.08",
    "wof:name":"Ajp",
    "wof:placetype":"venue"
},
  "geometry": {"coordinates":[6.3562731743,52.3174171448],"type":"Point"}
}