{
  "type": "Feature",
  "properties": {
    "addr:full":"Fransenstraat 25 Vlaardingen South Holland 3131 CC",
    "addr:housenumber":"25",
    "addr:postcode":"3131 cc",
    "addr:street":"Fransenstraat",
    "iso:country":"NL",
    "sg:address":"Fransenstraat 25",
    "sg:city":"Vlaardingen",
    "sg:orig_category":"Drukkerijen And Copyshops",
    "sg:phone":"+31 10 434 0978",
    "sg:postcode":"3131 CC",
    "sg:province":"South Holland",
    "wof:name":"Drukwinkel En Kaartengalerie Pervelle",
    "wof:placetype":"venue"
},
  "geometry": {"coordinates":[4.34093,51.909058],"type":"Point"}
}