{
  "type": "Feature",
  "properties": {
    "addr:full":"Noorderkade 8 Blokzijl Overijssel 8356 DC",
    "addr:housenumber":"8",
    "addr:postcode":"8356",
    "addr:street":"Noorderkade",
    "iso:country":"NL",
    "sg:address":"Noorderkade 8",
    "sg:city":"Blokzijl",
    "sg:orig_category":"Artsen And Specialisten",
    "sg:phone":"+31 527 291 312",
    "sg:postcode":"8356 DC",
    "sg:province":"Overijssel",
    "wof:name":"Huisartsenpraktijk W.J. Van Wijk & J.H.G. Scholte",
    "wof:placetype":"venue"
},
  "geometry": {"coordinates":[5.958569,52.726826],"type":"Point"}
}