{
  "type": "Feature",
  "properties": {
    "addr:full":"Ons Limburgstr 57 Kerkrade Limburg 6466 CA",
    "addr:housenumber":"57",
    "addr:postcode":"6466 ca",
    "iso:country":"NL",
    "sg:address":"Ons Limburgstr 57",
    "sg:city":"Kerkrade",
    "sg:orig_category":"Verenigingsgebouwen",
    "sg:phone":"+31 45 541 0927",
    "sg:postcode":"6466 CA",
    "sg:province":"Limburg",
    "wof:name":"Heilust, Sticht",
    "wof:placetype":"venue"
},
  "geometry": {"coordinates":[6.031353,50.859833],"type":"Point"}
}