{
  "type": "Feature",
  "properties": {
    "addr:full":"Johannes Vermeerstraat 28 Oosterhout Nb Noord-Brabant 4907 PS",
    "addr:housenumber":"28",
    "addr:postcode":"4907 ps",
    "addr:street":"Johannes Vermeerstraat",
    "iso:country":"NL",
    "sg:address":"Johannes Vermeerstraat 28",
    "sg:city":"Oosterhout Nb",
    "sg:orig_category":"Film-, Tv- And Videoproductie",
    "sg:phone":"+31 162 425 220",
    "sg:postcode":"4907 PS",
    "sg:province":"Noord-Brabant",
    "wof:name":"Video Studio Oosterhout",
    "wof:placetype":"venue"
},
  "geometry": {"coordinates":[4.874468,51.657692],"type":"Point"}
}