{
  "type": "Feature",
  "properties": {
    "addr:full":"Kloosterstraat 2 Oijen Noord-Brabant 5394 AK",
    "addr:housenumber":"2",
    "addr:postcode":"5394 ak",
    "addr:street":"Kloosterstraat",
    "iso:country":"NL",
    "sg:address":"Kloosterstraat 2",
    "sg:city":"Oijen",
    "sg:orig_category":"Sportclubs",
    "sg:phone":"+31 412 492 781",
    "sg:postcode":"5394 AK",
    "sg:province":"Noord-Brabant",
    "wof:name":"Dios Drumfanfare",
    "wof:placetype":"venue"
},
  "geometry": {"coordinates":[5.50321,51.824718],"type":"Point"}
}