{
  "type": "Feature",
  "properties": {
    "addr:full":"Kerkweg 3 Zeddam Gelderland 7038 CE",
    "addr:housenumber":"3",
    "addr:postcode":"7038 ce",
    "addr:street":"Kerkweg;Gelderland",
    "iso:country":"NL",
    "sg:address":"Kerkweg 3",
    "sg:city":"Zeddam",
    "sg:classifiers":[
        {
            "category":"Professional",
            "subcategory":"Accounting & Tax Preparation",
            "type":"Services"
        }
    ],
    "sg:phone":"+31 314 650 111",
    "sg:postcode":"7038 CE",
    "sg:province":"Gelderland",
    "sg:tags":[
        "accountant"
    ],
    "wof:name":"Lion'S Accountancy & Advice",
    "wof:placetype":"venue"
},
  "geometry": {"coordinates":[6.256368,51.900345],"type":"Point"}
}