{
  "type": "Feature",
  "properties": {
    "addr:full":"Hoofdstraat 98 Apeldoorn Gelderland 7311 KH",
    "addr:housenumber":"98",
    "addr:postcode":"7311 kh",
    "addr:street":"Hoofdstraat;Gelderland",
    "iso:country":"NL",
    "sg:address":"Hoofdstraat 98",
    "sg:city":"Apeldoorn",
    "sg:classifiers":[
        {
            "category":"Shopping",
            "subcategory":"Gifts & Souvenirs",
            "type":"Retail Goods"
        }
    ],
    "sg:phone":"+31 55 578 8885",
    "sg:postcode":"7311 KH",
    "sg:province":"Gelderland",
    "sg:tags":[
        "geschenken"
    ],
    "wof:name":"Invito",
    "wof:placetype":"venue"
},
  "geometry": {"coordinates":[5.962562,52.21434],"type":"Point"}
}