{
  "type": "Feature",
  "properties": {
    "iso:country":"NL",
    "sg:address":"Brinkstr 7",
    "sg:city":"Bennekom",
    "sg:orig_category":"Herenkleding",
    "sg:phone":"+31 318 418 022",
    "sg:postcode":"6721 WR",
    "sg:province":"Gelderland",
    "wof:name":"Eijgenraam",
    "wof:placetype":"venue"
},
  "geometry": {"coordinates":[5.674844,51.99905],"type":"Point"}
}