{
  "type": "Feature",
  "properties": {
    "addr:full":"Kuifmees 50 Nieuwegein Utrecht 3435 RG",
    "addr:housenumber":"50",
    "addr:postcode":"3435 rg",
    "addr:street":"Kuifmees",
    "iso:country":"NL",
    "sg:address":"Kuifmees 50",
    "sg:city":"Nieuwegein",
    "sg:orig_category":"Goederenvervoer Over De Weg",
    "sg:phone":"+31 30 605 1800",
    "sg:postcode":"3435 RG",
    "sg:province":"Utrecht",
    "wof:name":"Dcp Dutch Cargo Purchase Bv",
    "wof:placetype":"venue"
},
  "geometry": {"coordinates":[5.070332,52.027718],"type":"Point"}
}