{
  "type": "Feature",
  "properties": {
    "iso:country":"NL",
    "sg:address":"Geer 26",
    "sg:city":"Nieuwland",
    "sg:orig_category":"Zand En Grind - Vervoer",
    "sg:phone":"+31 183 352 430",
    "sg:postcode":"4243 JS",
    "sg:province":"Zuid-Holland",
    "wof:name":"Haag, John",
    "wof:placetype":"venue"
},
  "geometry": {"coordinates":[5.026292,51.901176],"type":"Point"}
}