{
  "type": "Feature",
  "properties": {
    "iso:country":"NL",
    "sg:address":"Achteres 2A",
    "sg:city":"Den Ham Ov",
    "sg:orig_category":"Handwerkartikelen",
    "sg:phone":"+31 546 671 794",
    "sg:postcode":"7683 SW",
    "sg:province":"Overijssel",
    "wof:name":"Wolschuur, De",
    "wof:placetype":"venue"
},
  "geometry": {"coordinates":[6.496274,52.462387],"type":"Point"}
}