{
  "type": "Feature",
  "properties": {
    "addr:full":"Gentiaan 8 Noordwijkerhout Zuid-Holland 2211 NH",
    "addr:housenumber":"8",
    "addr:postcode":"2211 nh",
    "addr:street":"Gentiaan",
    "iso:country":"NL",
    "sg:address":"Gentiaan 8",
    "sg:city":"Noordwijkerhout",
    "sg:classifiers":[
        {
            "category":"Personal",
            "subcategory":"Nail Salon",
            "type":"Services"
        }
    ],
    "sg:phone":"+31 252 373 755",
    "sg:postcode":"2211 NH",
    "sg:province":"Zuid-Holland",
    "sg:tags":[
        "pedicure"
    ],
    "wof:name":"Brauckmann-Strietman, W",
    "wof:placetype":"venue"
},
  "geometry": {"coordinates":[-71.632828,44.001301],"type":"Point"}
}