{
  "type": "Feature",
  "properties": {
    "addr:full":"Stationsstraat 5 Etten-Leur Noord-Brabant 4872 TA",
    "addr:housenumber":"5",
    "addr:postcode":"4872 ta",
    "addr:street":"Stationsstraat",
    "iso:country":"NL",
    "sg:address":"Stationsstraat 5",
    "sg:city":"Etten-Leur",
    "sg:classifiers":[
        {
            "category":"Fast Food",
            "type":"Food & Drink"
        }
    ],
    "sg:phone":"+31 76 503 1191",
    "sg:postcode":"4872 TA",
    "sg:province":"Noord-Brabant",
    "sg:tags":[
        "afhaal",
        "restaurant"
    ],
    "wof:name":"Doner Ankara",
    "wof:placetype":"venue"
},
  "geometry": {"coordinates":[4.635584,51.571198],"type":"Point"}
}