{
  "type": "Feature",
  "properties": {
    "addr:full":"Kwadk 23 Kwadyk Noord-Holland 1471 CB",
    "addr:housenumber":"23",
    "addr:postcode":"1471 cb",
    "addr:street":"Kwadk",
    "iso:country":"NL",
    "sg:address":"Kwadk 23",
    "sg:city":"Kwadyk",
    "sg:orig_category":"Schilders",
    "sg:phone":"+31 299 623 269",
    "sg:postcode":"1471 CB",
    "sg:province":"Noord-Holland",
    "wof:name":"Kwadijk, Schilder- Timmerbedrijf",
    "wof:placetype":"venue"
},
  "geometry": {"coordinates":[4.970729,52.52985],"type":"Point"}
}