{
  "type": "Feature",
  "properties": {
    "addr:full":"Postbus 27 Malden Gelderland 6580 AA",
    "addr:housenumber":"27",
    "addr:postcode":"6580 aa",
    "addr:street":"Postbus;Gelderland",
    "iso:country":"NL",
    "sg:address":"Postbus 27",
    "sg:city":"Malden",
    "sg:orig_category":"Kinderopvang",
    "sg:phone":"+31 24 329 5618",
    "sg:postcode":"6580 AA",
    "sg:province":"Gelderland",
    "sg:website":"http://www.satellite-partner.nl",
    "wof:name":"Satellite Partner",
    "wof:placetype":"venue"
},
  "geometry": {"coordinates":[5.85371,51.780411],"type":"Point"}
}