{
  "type": "Feature",
  "properties": {
    "addr:full":"Nes 122 Wervershoof North Holland 1693 CK",
    "addr:housenumber":"122",
    "addr:postcode":"1693 ck",
    "addr:street":"Nes",
    "iso:country":"NL",
    "sg:address":"Nes 122",
    "sg:city":"Wervershoof",
    "sg:orig_category":"Kappers",
    "sg:phone":"+31 228 584 488",
    "sg:postcode":"1693 CK",
    "sg:province":"North Holland",
    "wof:name":"Haarverzorging Irene",
    "wof:placetype":"venue"
},
  "geometry": {"coordinates":[5.1428852081,52.7398262024],"type":"Point"}
}