{
  "type": "Feature",
  "properties": {
    "iso:country":"NL",
    "sg:address":"Rosmolenstraat 12",
    "sg:city":"Sittard",
    "sg:orig_category":"Werving And Selectie Van Tijdelijk Personeel And Uitzendkantoren",
    "sg:phone":"+31 46 451 5190",
    "sg:postcode":"6131 HX",
    "sg:province":"Limburg",
    "wof:name":"Dactylo",
    "wof:placetype":"venue"
},
  "geometry": {"coordinates":[5.8692741394,50.9967155457],"type":"Point"}
}