{
  "type": "Feature",
  "properties": {
    "addr:full":"Baroniewg 5 Polsbroek Utrecht 3415 PK",
    "addr:housenumber":"5",
    "addr:postcode":"3415 pk",
    "addr:street":"Baroniewg",
    "iso:country":"NL",
    "sg:address":"Baroniewg 5",
    "sg:city":"Polsbroek",
    "sg:orig_category":"Loonbedrijven",
    "sg:phone":"+31 182 309 286",
    "sg:postcode":"3415 PK",
    "sg:province":"Utrecht",
    "wof:name":"Meerkerk & Sipsma Vof",
    "wof:placetype":"venue"
},
  "geometry": {"coordinates":[4.8532,51.978279],"type":"Point"}
}