{
  "type": "Feature",
  "properties": {
    "iso:country":"NL",
    "sg:address":"Oranjestraat 19",
    "sg:city":"Schiedam",
    "sg:orig_category":"Medische Apparatuur And Prothesen Fab",
    "sg:phone":"+31 10 473 8700",
    "sg:postcode":"3111 AM",
    "sg:province":"Zuid-Holland",
    "wof:name":"Het Huis Argus",
    "wof:placetype":"venue"
},
  "geometry": {"coordinates":[4.400356,51.912979],"type":"Point"}
}