{
  "type": "Feature",
  "properties": {
    "addr:full":"Beumeesweg 83 Alteveer Gn Groningen 9661 AC",
    "addr:housenumber":"83",
    "addr:postcode":"gn;9661 ac",
    "addr:street":"Beumeesweg",
    "iso:country":"NL",
    "sg:address":"Beumeesweg 83",
    "sg:city":"Alteveer Gn",
    "sg:orig_category":"Goederenvervoer Over De Weg",
    "sg:phone":"+31 599 332 529",
    "sg:postcode":"9661 AC",
    "sg:province":"Groningen",
    "wof:name":"Hat Internationaal Transport Bv",
    "wof:placetype":"venue"
},
  "geometry": {"coordinates":[7.009705,53.048546],"type":"Point"}
}