{
  "type": "Feature",
  "properties": {
    "addr:full":"Herengracht 115 Amsterdam Noord-Holland 1015 BE",
    "addr:housenumber":"115",
    "addr:postcode":"1015",
    "addr:street":"Herengracht",
    "iso:country":"NL",
    "sg:address":"Herengracht 115",
    "sg:city":"Amsterdam",
    "sg:orig_category":"Beautyfarms And Sauna'S",
    "sg:phone":"+31 20 623 8215",
    "sg:postcode":"1015 BE",
    "sg:province":"Noord-Holland",
    "wof:name":"Sauna Deco Bv",
    "wof:placetype":"venue"
},
  "geometry": {"coordinates":[4.889837,52.376278],"type":"Point"}
}