{
  "type": "Feature",
  "properties": {
    "addr:full":"Hoofdstraat 71 Landgraaf Limburg 6372 CP",
    "addr:housenumber":"71",
    "addr:postcode":"6372 cp",
    "addr:street":"Hoofdstraat",
    "iso:country":"NL",
    "sg:address":"Hoofdstraat 71",
    "sg:city":"Landgraaf",
    "sg:orig_category":"Boekhandels",
    "sg:phone":"+31 45 533 0361",
    "sg:postcode":"6372 CP",
    "sg:province":"Limburg",
    "wof:name":"Kantoorboekhandel Funcken",
    "wof:placetype":"venue"
},
  "geometry": {"coordinates":[6.015669,50.893063],"type":"Point"}
}