{
  "type": "Feature",
  "properties": {
    "addr:full":"Kalverstraat 203 Amsterdam North Holland 1012 XC",
    "addr:housenumber":"203",
    "addr:postcode":"1012 xc",
    "addr:street":"Kalverstraat",
    "iso:country":"NL",
    "sg:address":"Kalverstraat 203",
    "sg:city":"Amsterdam",
    "sg:orig_category":"Verzekeringen",
    "sg:phone":"+31 20 625 3679",
    "sg:postcode":"1012 XC",
    "sg:province":"North Holland",
    "wof:name":"Vendopolis",
    "wof:placetype":"venue"
},
  "geometry": {"coordinates":[4.892491,52.367558],"type":"Point"}
}