{
  "type": "Feature",
  "properties": {
    "addr:full":"Weissenbruchstr 31 Amsterdam North Holland 1058 KL",
    "addr:housenumber":"31",
    "addr:postcode":"1058 kl",
    "addr:street":"Weissenbruchstr",
    "iso:country":"NL",
    "sg:address":"Weissenbruchstr 31",
    "sg:city":"Amsterdam",
    "sg:orig_category":"Woninginrichting",
    "sg:phone":"+31 20 617 7138",
    "sg:postcode":"1058 KL",
    "sg:province":"North Holland",
    "wof:name":"Decork Vof",
    "wof:placetype":"venue"
},
  "geometry": {"coordinates":[4.850880146,52.3532104492],"type":"Point"}
}