{
  "type": "Feature",
  "properties": {
    "addr:full":"Mozartln 204 Zwyndrecht Zuid-Holland 3335 AJ",
    "addr:housenumber":"204",
    "addr:postcode":"3335 aj",
    "iso:country":"NL",
    "sg:address":"Mozartln 204",
    "sg:city":"Zwyndrecht",
    "sg:orig_category":"Keukens",
    "sg:phone":"+31 78 629 9910",
    "sg:postcode":"3335 AJ",
    "sg:province":"Zuid-Holland",
    "wof:name":"Villa Toscana",
    "wof:placetype":"venue"
},
  "geometry": {"coordinates":[4.60712,51.827839],"type":"Point"}
}