{
  "type": "Feature",
  "properties": {
    "addr:full":"Zesstedenweg 206 Grootebroek Noord-Holland 1613 KE",
    "addr:housenumber":"206",
    "addr:postcode":"1613 ke",
    "addr:street":"Zesstedenweg",
    "iso:country":"NL",
    "sg:address":"Zesstedenweg 206",
    "sg:city":"Grootebroek",
    "sg:orig_category":"Bedrijfsamusement",
    "sg:phone":"+31 228 511 498",
    "sg:postcode":"1613 KE",
    "sg:province":"Noord-Holland",
    "sg:website":"http://www.wapen.nl",
    "wof:name":"Het Wapen Van Grootebroek",
    "wof:placetype":"venue"
},
  "geometry": {"coordinates":[5.219229,52.697865],"type":"Point"}
}