{
  "type": "Feature",
  "properties": {
    "addr:full":"Grt Marktstr 50 S Gravenhage South Holland 2511 BJ",
    "addr:housenumber":"50",
    "addr:postcode":"2511 bj",
    "addr:street":"S Gravenhage",
    "iso:country":"NL",
    "sg:address":"Grt Marktstr 50",
    "sg:city":"S Gravenhage",
    "sg:orig_category":"Keukens",
    "sg:phone":"+31 70 365 9895",
    "sg:postcode":"2511 BJ",
    "sg:province":"South Holland",
    "wof:name":"Vendoplan",
    "wof:placetype":"venue"
},
  "geometry": {"coordinates":[4.31627,52.07896],"type":"Point"}
}