{
  "type": "Feature",
  "properties": {
    "addr:full":"Breestraat 114 Beverwijk Noord-Holland 1941 EL",
    "addr:housenumber":"114;1941",
    "addr:postcode":"el",
    "addr:street":"Breestraat",
    "iso:country":"NL",
    "sg:address":"Breestraat 114",
    "sg:city":"Beverwijk",
    "sg:orig_category":"Opticiens",
    "sg:phone":"+31 251 215 645",
    "sg:postcode":"1941 EL",
    "sg:province":"Noord-Holland",
    "wof:name":"Brilservice Bv",
    "wof:placetype":"venue"
},
  "geometry": {"coordinates":[4.6586289406,52.4823989868],"type":"Point"}
}