{
  "type": "Feature",
  "properties": {
    "addr:full":"Langbree 6 Assen Drenthe 9403 GB",
    "addr:housenumber":"6",
    "addr:postcode":"9403 gb",
    "addr:street":"Langbree",
    "iso:country":"NL",
    "sg:address":"Langbree 6",
    "sg:city":"Assen",
    "sg:orig_category":"Verslagbureaus",
    "sg:phone":"+31 592 342 316",
    "sg:postcode":"9403 GB",
    "sg:province":"Drenthe",
    "wof:name":"Notuleerbureau Wvttk",
    "wof:placetype":"venue"
},
  "geometry": {"coordinates":[6.57518,53.019611],"type":"Point"}
}