{
  "type": "Feature",
  "properties": {
    "addr:full":"Nijverheidsweg 12 Etten-Leur Noord-Brabant 4879 AR",
    "addr:housenumber":"12",
    "addr:postcode":"4879",
    "addr:street":"Nijverheidsweg",
    "iso:country":"NL",
    "sg:address":"Nijverheidsweg 12",
    "sg:city":"Etten-Leur",
    "sg:orig_category":"Elektriciens",
    "sg:phone":"+31 76 501 3473",
    "sg:postcode":"4879 AR",
    "sg:province":"Noord-Brabant",
    "wof:name":"De Bruin Techniek Etten Bv",
    "wof:placetype":"venue"
},
  "geometry": {"coordinates":[4.62034,51.565929],"type":"Point"}
}