{
  "type": "Feature",
  "properties": {
    "addr:full":"Irislaan 239 Vlissingen Zeeland 4383 VV",
    "addr:housenumber":"239",
    "addr:postcode":"4383 vv",
    "addr:street":"Irislaan",
    "iso:country":"NL",
    "sg:address":"Irislaan 239",
    "sg:city":"Vlissingen",
    "sg:orig_category":"Sportclubs",
    "sg:phone":"+31 118 460 259",
    "sg:postcode":"4383 VV",
    "sg:province":"Zeeland",
    "wof:name":"Stichting Vlissingen Voetbalclub",
    "wof:placetype":"venue"
},
  "geometry": {"coordinates":[3.577585,51.457577],"type":"Point"}
}