{
  "type": "Feature",
  "properties": {
    "addr:full":"Rodenrysewg 179 Berkel En Rodenrys Zuid-Holland 2651 BP",
    "addr:housenumber":"179",
    "addr:postcode":"2651 bp",
    "addr:street":"Berkel",
    "iso:country":"NL",
    "sg:address":"Rodenrysewg 179",
    "sg:city":"Berkel En Rodenrys",
    "sg:orig_category":"Postorderbedrijven",
    "sg:phone":"+31 6 15437685",
    "sg:postcode":"2651 BP",
    "sg:province":"Zuid-Holland",
    "sg:website":"http://www.fietswielen.nl",
    "wof:name":"Fietswielen.Nl",
    "wof:placetype":"venue"
},
  "geometry": {"coordinates":[4.47659,51.994122],"type":"Point"}
}