{
  "type": "Feature",
  "properties": {
    "iso:country":"NL",
    "sg:address":"Voltastraat 56",
    "sg:city":"Doetinchem",
    "sg:orig_category":"Beautyfarms And Sauna'S",
    "sg:phone":"+31 314 332 637",
    "sg:postcode":"7006 RW",
    "sg:province":"Gelderland",
    "wof:name":"Cocon",
    "wof:placetype":"venue"
},
  "geometry": {"coordinates":[6.258399,51.969627],"type":"Point"}
}