{
  "type": "Feature",
  "properties": {
    "addr:full":"Rhijnvis Feithlaan 26 Zwolle Overijssel 8021 AK",
    "addr:housenumber":"26",
    "addr:postcode":"8021 ak",
    "addr:street":"Rhijnvis Feithlaan",
    "iso:country":"NL",
    "sg:address":"Rhijnvis Feithlaan 26",
    "sg:city":"Zwolle",
    "sg:orig_category":"Technische Studies And Onderzoek",
    "sg:phone":"+31 38 455 1435",
    "sg:postcode":"8021 AK",
    "sg:province":"Overijssel",
    "wof:name":"Volteck Lumiere",
    "wof:placetype":"venue"
},
  "geometry": {"coordinates":[6.106623,52.51458],"type":"Point"}
}