{
  "type": "Feature",
  "properties": {
    "iso:country":"NL",
    "sg:address":"F Halspln 4",
    "sg:city":"Haarlem",
    "sg:orig_category":"Administratie- En Boekhoudkantoren",
    "sg:phone":"+31 23 527 3639",
    "sg:postcode":"2021 DL",
    "sg:province":"Noord-Holland",
    "wof:name":"Bedrijfsadministraties Haarlem Bv",
    "wof:placetype":"venue"
},
  "geometry": {"coordinates":[4.640117,52.390724],"type":"Point"}
}