{
  "type": "Feature",
  "properties": {
    "addr:full":"Bovenbeekstraat 15 Arnhem Gelderland 6811 CV",
    "addr:housenumber":"15",
    "addr:postcode":"6811 cv",
    "addr:street":"Bovenbeekstraat",
    "iso:country":"NL",
    "sg:address":"Bovenbeekstraat 15",
    "sg:city":"Arnhem",
    "sg:orig_category":"Sportprijzen, Postzegels And Munten",
    "sg:phone":"+31 26 389 2248",
    "sg:postcode":"6811 CV",
    "sg:province":"Gelderland",
    "wof:name":"Sport Gifts",
    "wof:placetype":"venue"
},
  "geometry": {"coordinates":[5.910195,51.98246],"type":"Point"}
}