{
  "type": "Feature",
  "properties": {
    "iso:country":"NL",
    "sg:address":"Nieuwe Binnenweg 42",
    "sg:city":"Rotterdam",
    "sg:orig_category":"Boekenuitgeverijen",
    "sg:phone":"+31 10 436 1752",
    "sg:postcode":"3015 BA",
    "sg:province":"South Holland",
    "wof:name":"De Boekelier",
    "wof:placetype":"venue"
},
  "geometry": {"coordinates":[4.46944,51.916115],"type":"Point"}
}