{
  "type": "Feature",
  "properties": {
    "addr:full":"Spieringweg 488A Vijfhuizen Noord-Holland 2141 EA",
    "addr:housenumber":"488a",
    "addr:postcode":"2141 ea",
    "addr:street":"Spieringweg",
    "iso:country":"NL",
    "sg:address":"Spieringweg 488A",
    "sg:city":"Vijfhuizen",
    "sg:classifiers":[
        {
            "category":"Retail",
            "subcategory":"Storage",
            "type":"Services"
        }
    ],
    "sg:phone":"+31 23 558 3212",
    "sg:postcode":"2141 EA",
    "sg:province":"Noord-Holland",
    "sg:tags":[
        "opslag",
        "bewaring"
    ],
    "wof:name":"Magnoflex Bv",
    "wof:placetype":"venue"
},
  "geometry": {"coordinates":[4.6760082245,52.3482322693],"type":"Point"}
}