{
  "type": "Feature",
  "properties": {
    "addr:full":"Mezenplein 3 Groningen Groningen 9713 PT",
    "addr:housenumber":"3",
    "addr:postcode":"9713 pt",
    "addr:street":"Mezenplein",
    "iso:country":"NL",
    "sg:address":"Mezenplein 3",
    "sg:city":"Groningen",
    "sg:orig_category":"Fotostudio'S And Fotografen",
    "sg:phone":"+31 50 312 3472",
    "sg:postcode":"9713 PT",
    "sg:province":"Groningen",
    "wof:name":"Fotofun",
    "wof:placetype":"venue"
},
  "geometry": {"coordinates":[6.583701,53.229156],"type":"Point"}
}