{
  "type": "Feature",
  "properties": {
    "addr:full":"Lange Reksestraat 10 Terneuzen Zeeland 4538 AZ",
    "addr:housenumber":"10",
    "addr:postcode":"4538",
    "addr:street":"Lange Reksestraat",
    "iso:country":"NL",
    "sg:address":"Lange Reksestraat 10",
    "sg:city":"Terneuzen",
    "sg:classifiers":[
        {
            "category":"Retail",
            "subcategory":"Storage",
            "type":"Services"
        }
    ],
    "sg:phone":"+31 115 612 714",
    "sg:postcode":"4538 AZ",
    "sg:province":"Zeeland",
    "sg:tags":[
        "opslag",
        "bewaring"
    ],
    "wof:name":"Firma Klouwers",
    "wof:placetype":"venue"
},
  "geometry": {"coordinates":[3.8505399227,51.3042793274],"type":"Point"}
}