{
  "type": "Feature",
  "properties": {
    "addr:full":"Stuyvesantplein 55 'S Gravenhage Zuid-Holland 2593 EM",
    "addr:housenumber":"55",
    "addr:postcode":"2593 em",
    "addr:street":"Stuyvesantplein;' S",
    "iso:country":"NL",
    "sg:address":"Stuyvesantplein 55",
    "sg:city":"'S Gravenhage",
    "sg:orig_category":"Bloemen And Planten",
    "sg:phone":"+31 70 385 8353",
    "sg:postcode":"2593 EM",
    "sg:province":"Zuid-Holland",
    "wof:name":"Bloemenhuis De Narcis",
    "wof:placetype":"venue"
},
  "geometry": {"coordinates":[4.343102,52.085144],"type":"Point"}
}