{
  "type": "Feature",
  "properties": {
    "addr:full":"Kranepoort 12 Gouderak Zuid-Holland 2831 AK",
    "addr:housenumber":"12",
    "addr:postcode":"2831 ak",
    "addr:street":"Kranepoort",
    "iso:country":"NL",
    "sg:address":"Kranepoort 12",
    "sg:city":"Gouderak",
    "sg:classifiers":[
        {
            "category":"Food & Beverages",
            "subcategory":"Fruits & Vegetables",
            "type":"Retail Goods"
        }
    ],
    "sg:phone":"+31 182 372 227",
    "sg:postcode":"2831 AK",
    "sg:province":"Zuid-Holland",
    "sg:tags":[
        "groenten"
    ],
    "wof:name":"J J Den Hertog",
    "wof:placetype":"venue"
},
  "geometry": {"coordinates":[4.676288,51.984993],"type":"Point"}
}