{
  "type": "Feature",
  "properties": {
    "addr:full":"Kanariestraat 8 Mill West Virginia 5451 VL",
    "addr:housenumber":"8",
    "addr:postcode":"5451 vl",
    "addr:street":"Kanariestraat",
    "iso:country":"NL",
    "sg:address":"Kanariestraat 8",
    "sg:city":"Mill",
    "sg:orig_category":"Goederenvervoer Over De Weg",
    "sg:phone":"+31 485 455 323",
    "sg:postcode":"5451 VL",
    "sg:province":"West Virginia",
    "wof:name":"Vd Boom Transport Vof",
    "wof:placetype":"venue"
},
  "geometry": {"coordinates":[-80.147682,38.16378],"type":"Point"}
}