{
  "type": "Feature",
  "properties": {
    "addr:full":"K Kapoeniestr 11 Doetinchem Gelderland 7001 CA",
    "addr:housenumber":"11",
    "addr:postcode":"7001 ca",
    "addr:street":"Kapoeniestr;Gelderland",
    "iso:country":"NL",
    "sg:address":"K Kapoeniestr 11",
    "sg:city":"Doetinchem",
    "sg:orig_category":"Broodjeszaken",
    "sg:phone":"+31 314 362 516",
    "sg:postcode":"7001 CA",
    "sg:province":"Gelderland",
    "wof:name":"Joop",
    "wof:placetype":"venue"
},
  "geometry": {"coordinates":[6.286857,51.965317],"type":"Point"}
}