{
  "type": "Feature",
  "properties": {
    "addr:full":"Past Petersstr 180 Eindhoven North Brabant 5612 LW",
    "addr:housenumber":"180",
    "addr:postcode":"5612 lw",
    "iso:country":"NL",
    "sg:address":"Past Petersstr 180",
    "sg:city":"Eindhoven",
    "sg:orig_category":"Balletscholen",
    "sg:phone":"+31 40 216 3200",
    "sg:postcode":"5612 LW",
    "sg:province":"North Brabant",
    "sg:website":"http://www.cke.nl",
    "wof:name":"Cke-Balletschool",
    "wof:placetype":"venue"
},
  "geometry": {"coordinates":[5.474512,51.445148],"type":"Point"}
}