{
  "type": "Feature",
  "properties": {
    "addr:full":"1E J C Mensingln 38 Aalsmeer Noord-Holland 1431 RW",
    "addr:housenumber":"38",
    "addr:postcode":"1431 rw",
    "addr:street":"1E J C Mensingln",
    "iso:country":"NL",
    "sg:address":"1E J C Mensingln 38",
    "sg:city":"Aalsmeer",
    "sg:orig_category":"Bloemen En Planten - Decoratie",
    "sg:phone":"+31 297 368 425",
    "sg:postcode":"1431 RW",
    "sg:province":"Noord-Holland",
    "wof:name":"Ges Deco",
    "wof:placetype":"venue"
},
  "geometry": {"coordinates":[4.749068,52.266991],"type":"Point"}
}