{
  "type": "Feature",
  "properties": {
    "addr:full":"Cremerstr 41 Voorburg Zuid-Holland 2274 HG",
    "addr:housenumber":"41",
    "addr:postcode":"2274 hg",
    "addr:street":"Cremerstr",
    "iso:country":"NL",
    "sg:address":"Cremerstr 41",
    "sg:city":"Voorburg",
    "sg:orig_category":"Kantoor- En Bedrijfsmeubelen",
    "sg:phone":"+31 70 335 1414",
    "sg:postcode":"2274 HG",
    "sg:province":"Zuid-Holland",
    "sg:website":"http://www.tmfacilities.nl",
    "wof:name":"Tm Facilities",
    "wof:placetype":"venue"
},
  "geometry": {"coordinates":[4.3613848686,52.0731201172],"type":"Point"}
}