{
  "type": "Feature",
  "properties": {
    "iso:country":"NL",
    "sg:address":"Schaarwg 41",
    "sg:city":"Huizen",
    "sg:orig_category":"Administratie- En Boekhoudkantoren",
    "sg:phone":"+31 35 525 2173",
    "sg:postcode":"1276 AE",
    "sg:province":"North Holland",
    "wof:name":"Aab",
    "wof:placetype":"venue"
},
  "geometry": {"coordinates":[5.250219,52.294701],"type":"Point"}
}