{
  "type": "Feature",
  "properties": {
    "iso:country":"NL",
    "sg:address":"Ln V Meerdervoort 489",
    "sg:city":"S Gravenhage",
    "sg:orig_category":"Verenigingen En Stichtingen",
    "sg:phone":"+31 70 360 8212",
    "sg:postcode":"2563 AT",
    "sg:province":"Zuid-Holland",
    "wof:name":"Buitenlands Pensioen Belang, Sticht",
    "wof:placetype":"venue"
},
  "geometry": {"coordinates":[4.270956,52.072578],"type":"Point"}
}