{
  "type": "Feature",
  "properties": {
    "addr:full":"Beethovenstraat 8 Venlo Limburg 5914 BN",
    "addr:housenumber":"8",
    "addr:postcode":"5914 bn",
    "addr:street":"Beethovenstraat",
    "iso:country":"NL",
    "sg:address":"Beethovenstraat 8",
    "sg:city":"Venlo",
    "sg:classifiers":[
        {
            "category":"Professional",
            "subcategory":"Accounting & Tax Preparation",
            "type":"Services"
        }
    ],
    "sg:phone":"+31 77 351 5020",
    "sg:postcode":"5914 BN",
    "sg:province":"Limburg",
    "sg:tags":[
        "accountant"
    ],
    "wof:name":"Reijnen",
    "wof:placetype":"venue"
},
  "geometry": {"coordinates":[6.176366,51.379707],"type":"Point"}
}