{
  "type": "Feature",
  "properties": {
    "addr:full":"Magalhaeswg 2 Venlo Limburg 5928 LN",
    "addr:housenumber":"2",
    "addr:postcode":"5928 ln",
    "addr:street":"Magalhaeswg",
    "iso:country":"NL",
    "sg:address":"Magalhaeswg 2",
    "sg:city":"Venlo",
    "sg:orig_category":"Woninginrichting- Fournituren - Fabrieken En Groothandel",
    "sg:phone":"+31 77 387 5080",
    "sg:postcode":"5928 LN",
    "sg:province":"Limburg",
    "sg:website":"http://www.cj.nl",
    "wof:name":"Cj'S Collection",
    "wof:placetype":"venue"
},
  "geometry": {"coordinates":[6.0950980186,51.392364502],"type":"Point"}
}