{
  "type": "Feature",
  "properties": {
    "addr:full":"Spoorlaan 376 Tilburg Noord-Brabant 5038 CD",
    "addr:housenumber":"376",
    "addr:postcode":"5038 cd",
    "addr:street":"Spoorlaan",
    "iso:country":"NL",
    "sg:address":"Spoorlaan 376",
    "sg:city":"Tilburg",
    "sg:orig_category":"Vuilnisophaal And Afvoerdiensten",
    "sg:phone":"+31 13 580 0400",
    "sg:postcode":"5038 CD",
    "sg:province":"Noord-Brabant",
    "wof:name":"Afvalsturing Brabant Nv",
    "wof:placetype":"venue"
},
  "geometry": {"coordinates":[5.085919,51.559822],"type":"Point"}
}