{
  "type": "Feature",
  "properties": {
    "addr:full":"Scharmbarg 105 Assen Provincie Drenthe 9407 EC",
    "addr:housenumber":"105",
    "addr:postcode":"9407 ec",
    "addr:street":"Scharmbarg;Provincie Drenthe",
    "iso:country":"NL",
    "sg:address":"Scharmbarg 105",
    "sg:city":"Assen",
    "sg:orig_category":"Boeken En Tijdschriften",
    "sg:phone":"+31 592 373 992",
    "sg:postcode":"9407 EC",
    "sg:province":"Provincie Drenthe",
    "wof:name":"Boekelier, De",
    "wof:placetype":"venue"
},
  "geometry": {"coordinates":[6.56137,53.017014],"type":"Point"}
}