{
  "type": "Feature",
  "properties": {
    "addr:full":"Von Zesenstraat 176 Amsterdam Noord-Holland 1093 BJ",
    "addr:housenumber":"176",
    "addr:postcode":"1093 bj",
    "addr:street":"Von Zesenstraat",
    "iso:country":"NL",
    "sg:address":"Von Zesenstraat 176",
    "sg:city":"Amsterdam",
    "sg:orig_category":"Vaste And Vloeibare Brandstoffen",
    "sg:phone":"+31 20 665 0874",
    "sg:postcode":"1093 BJ",
    "sg:province":"Noord-Holland",
    "wof:name":"Fa. Goed",
    "wof:placetype":"venue"
},
  "geometry": {"coordinates":[4.925184,52.363934],"type":"Point"}
}