{
  "type": "Feature",
  "properties": {
    "addr:full":"Belgieln 15 Heerlen Limburg 6414 HM",
    "addr:housenumber":"15",
    "addr:postcode":"6414 hm",
    "addr:street":"Belgieln",
    "iso:country":"NL",
    "sg:address":"Belgieln 15",
    "sg:city":"Heerlen",
    "sg:orig_category":"Grondwerken",
    "sg:phone":"+31 45 528 6401",
    "sg:postcode":"6414 HM",
    "sg:province":"Limburg",
    "wof:name":"Smeets, N A",
    "wof:placetype":"venue"
},
  "geometry": {"coordinates":[5.98098,50.885506],"type":"Point"}
}