{
  "type": "Feature",
  "properties": {
    "addr:full":"Diezerstr 73 Zwolle NL.08 8011 RC",
    "addr:housenumber":"73",
    "addr:postcode":"8011 rc",
    "addr:street":"Diezerstr",
    "iso:country":"NL",
    "sg:address":"Diezerstr 73",
    "sg:city":"Zwolle",
    "sg:orig_category":"Drogisterijen",
    "sg:phone":"+31 38 421 4449",
    "sg:postcode":"8011 RC",
    "sg:province":"NL.08",
    "wof:name":"Euroshop",
    "wof:placetype":"venue"
},
  "geometry": {"coordinates":[6.096495,52.512836],"type":"Point"}
}