{
  "type": "Feature",
  "properties": {
    "addr:full":"Hoofdstraat 127 Velp Gld Gelderland 6881 TG",
    "addr:housenumber":"127;6881",
    "addr:postcode":"tg",
    "addr:street":"Hoofdstraat;Gld Gelderland",
    "iso:country":"NL",
    "sg:address":"Hoofdstraat 127",
    "sg:city":"Velp Gld",
    "sg:orig_category":"Medische Apparatuur And Prothesen Fab",
    "sg:phone":"+31 26 361 9393",
    "sg:postcode":"6881 TG",
    "sg:province":"Gelderland",
    "wof:name":"Acousticon",
    "wof:placetype":"venue"
},
  "geometry": {"coordinates":[5.968722,51.995667],"type":"Point"}
}