{
  "type": "Feature",
  "properties": {
    "iso:country":"NL",
    "sg:address":"De S Lohmanpln 22",
    "sg:city":"S Gravenhage",
    "sg:orig_category":"Boeken En Tijdschriften",
    "sg:phone":"+31 70 323 6879",
    "sg:postcode":"2566 AC",
    "sg:province":"South Holland",
    "wof:name":"Carla'S",
    "wof:placetype":"venue"
},
  "geometry": {"coordinates":[4.25553,52.079128],"type":"Point"}
}