{
  "type": "Feature",
  "properties": {
    "addr:full":"Graham Bellstraat 13 Zwolle NL.08 8013 PL",
    "addr:housenumber":"13",
    "addr:postcode":"8013 pl",
    "addr:street":"Graham Bellstraat",
    "iso:country":"NL",
    "sg:address":"Graham Bellstraat 13",
    "sg:city":"Zwolle",
    "sg:orig_category":"Metaalafval, Schrootrecycling And Sloperijen",
    "sg:phone":"+31 38 465 5323",
    "sg:postcode":"8013 PL",
    "sg:province":"NL.08",
    "wof:name":"Autodemontagebedrijf De Mars",
    "wof:placetype":"venue"
},
  "geometry": {"coordinates":[6.13331,52.485664],"type":"Point"}
}