{
  "type": "Feature",
  "properties": {
    "addr:full":"Franse Akker 4 Breda North Brabant 4824 AK",
    "addr:housenumber":"4",
    "addr:postcode":"4824 ak",
    "addr:street":"Franse Akker",
    "iso:country":"NL",
    "sg:address":"Franse Akker 4",
    "sg:city":"Breda",
    "sg:orig_category":"Behangers",
    "sg:phone":"+31 76 541 0489",
    "sg:postcode":"4824 AK",
    "sg:province":"North Brabant",
    "wof:name":"Man Bv, De",
    "wof:placetype":"venue"
},
  "geometry": {"coordinates":[4.75512,51.608078],"type":"Point"}
}