{
  "type": "Feature",
  "properties": {
    "iso:country":"NL",
    "sg:address":"Delflandpln 29",
    "sg:city":"Amsterdam",
    "sg:orig_category":"Drogisterijen",
    "sg:phone":"+31 20 614 3720",
    "sg:postcode":"1062 HP",
    "sg:province":"Noord-Holland",
    "wof:name":"Kruidvat",
    "wof:placetype":"venue"
},
  "geometry": {"coordinates":[4.840361,52.34874],"type":"Point"}
}