{
  "type": "Feature",
  "properties": {
    "addr:full":"Kerkstr 95 Zeeland Noord-Brabant 5411 CK",
    "addr:housenumber":"95",
    "addr:postcode":"5411 ck",
    "addr:street":"Kerkstr",
    "iso:country":"NL",
    "sg:address":"Kerkstr 95",
    "sg:city":"Zeeland",
    "sg:orig_category":"Loonbedrijven",
    "sg:phone":"+31 486 453 767",
    "sg:postcode":"5411 CK",
    "sg:province":"Noord-Brabant",
    "wof:name":"Schonenberg, L H",
    "wof:placetype":"venue"
},
  "geometry": {"coordinates":[5.675566,51.702255],"type":"Point"}
}