{
  "type": "Feature",
  "properties": {
    "iso:country":"NL",
    "sg:address":"Grote Kerkhof 4",
    "sg:city":"Deventer",
    "sg:orig_category":"Overheidsdiensten",
    "sg:phone":"+31 570 693 911",
    "sg:postcode":"7411 KT",
    "sg:province":"NL.08",
    "wof:name":"Gemeente Deventer",
    "wof:placetype":"venue"
},
  "geometry": {"coordinates":[6.1555638313,52.2515296936],"type":"Point"}
}