{
  "type": "Feature",
  "properties": {
    "addr:full":"Grote Kerkhof 4 Deventer NL.08 7411 KT",
    "addr:housenumber":"4;nl.08",
    "addr:postcode":"7411 kt",
    "addr:street":"Grote Kerkhof",
    "iso:country":"NL",
    "sg:address":"Grote Kerkhof 4",
    "sg:city":"Deventer",
    "sg:orig_category":"Overheidsdiensten",
    "sg:phone":"+31 570 693 911",
    "sg:postcode":"7411 KT",
    "sg:province":"NL.08",
    "wof:name":"Gemeente Deventer",
    "wof:placetype":"venue"
},
  "geometry": {"coordinates":[6.1555638313,52.2515296936],"type":"Point"}
}