{
  "type": "Feature",
  "properties": {
    "addr:full":"Nettelhorst 72 Alphen A/D Rijn Zuid-Holland 2402 LS",
    "addr:housenumber":"72;2402",
    "addr:postcode":"ls",
    "addr:street":"Nettelhorst",
    "iso:country":"NL",
    "sg:address":"Nettelhorst 72",
    "sg:city":"Alphen A/D Rijn",
    "sg:orig_category":"Boekhouders",
    "sg:phone":"+31 172 410 191",
    "sg:postcode":"2402 LS",
    "sg:province":"Zuid-Holland",
    "wof:name":"Hasta La Vista",
    "wof:placetype":"venue"
},
  "geometry": {"coordinates":[4.669546,52.14922],"type":"Point"}
}