{
  "type": "Feature",
  "properties": {
    "addr:full":"De Ruter 11 Sneek Provincie Friesland 8604 VP",
    "addr:housenumber":"11",
    "addr:postcode":"8604 vp",
    "addr:street":"De Ruter;Provincie Friesland",
    "iso:country":"NL",
    "sg:address":"De Ruter 11",
    "sg:city":"Sneek",
    "sg:orig_category":"Orgelbouw",
    "sg:phone":"+31 515 423 010",
    "sg:postcode":"8604 VP",
    "sg:province":"Provincie Friesland",
    "wof:name":"Groen, W J Te",
    "wof:placetype":"venue"
},
  "geometry": {"coordinates":[5.6840281487,53.0424346924],"type":"Point"}
}