{
  "type": "Feature",
  "properties": {
    "iso:country":"NL",
    "sg:address":"Woldpromenade 21",
    "sg:city":"Steenwijk",
    "sg:orig_category":"Herenmodezaken",
    "sg:phone":"+31 521 512 297",
    "sg:postcode":"8331 JD",
    "sg:province":"Overijssel",
    "wof:name":"Ten Oever Bv",
    "wof:placetype":"venue"
},
  "geometry": {"coordinates":[6.113449,52.786503],"type":"Point"}
}