{
  "type": "Feature",
  "properties": {
    "iso:country":"NL",
    "sg:address":"Kl Houtwg 54",
    "sg:city":"Heemskerk",
    "sg:classifiers":[
        {
            "category":"Retail",
            "subcategory":"Auto Repair",
            "type":"Services"
        }
    ],
    "sg:phone":"+31 251 230 430",
    "sg:postcode":"1969 KT",
    "sg:province":"Noord-Holland",
    "sg:tags":[
        "garage"
    ],
    "wof:name":"Timmer, M",
    "wof:placetype":"venue"
},
  "geometry": {"coordinates":[101.707611,3.1501],"type":"Point"}
}