{
  "type": "Feature",
  "properties": {
    "addr:full":"Veldzigt 8 De Meern Utrecht 3454 PW",
    "addr:housenumber":"8",
    "addr:postcode":"3454 pw",
    "addr:street":"Veldzigt",
    "iso:country":"NL",
    "sg:address":"Veldzigt 8",
    "sg:city":"De Meern",
    "sg:orig_category":"Kalligrafische Ateliers",
    "sg:phone":"+31 30 666 6336",
    "sg:postcode":"3454 PW",
    "sg:province":"Utrecht",
    "sg:website":"http://www.tekstpaint.nl",
    "wof:name":"Tekstpaint",
    "wof:placetype":"venue"
},
  "geometry": {"coordinates":[5.048678875,52.0732841492],"type":"Point"}
}