{
  "type": "Feature",
  "properties": {
    "iso:country":"NL",
    "sg:address":"Nijverheidsweg 13",
    "sg:city":"Neede",
    "sg:orig_category":"Koeriersdiensten",
    "sg:phone":"+31 545 292 619",
    "sg:postcode":"7161 AA",
    "sg:province":"California",
    "wof:name":"K D N Koeriers Vof",
    "wof:placetype":"venue"
},
  "geometry": {"coordinates":[-121.31706200000001,38.299633],"type":"Point"}
}