{
  "type": "Feature",
  "properties": {
    "addr:full":"Postbus 447 Hengelo Ov 7550 AK",
    "addr:housenumber":"447",
    "addr:postcode":"7550 ak",
    "addr:street":"Postbus;Ov",
    "iso:country":"NL",
    "sg:address":"Postbus 447",
    "sg:city":"Hengelo Ov",
    "sg:orig_category":"Waterleidingbedrijven",
    "sg:phone":"+31 74 851 5151",
    "sg:postcode":"7550 AK",
    "sg:website":"http://www.vitens.nl",
    "wof:name":"Vitens Overijssel",
    "wof:placetype":"venue"
},
  "geometry": {"coordinates":[6.7897100449,52.266330719],"type":"Point"}
}