{
  "type": "Feature",
  "properties": {
    "addr:full":"Ganzerikveld 65 Woerden Utrecht 3448 GT",
    "addr:housenumber":"65",
    "addr:postcode":"3448 gt",
    "addr:street":"Ganzerikveld",
    "iso:country":"NL",
    "sg:address":"Ganzerikveld 65",
    "sg:city":"Woerden",
    "sg:orig_category":"Diverse Grafische Activiteiten",
    "sg:phone":"+31 348 480 425",
    "sg:postcode":"3448 GT",
    "sg:province":"Utrecht",
    "wof:name":"Cmf Design",
    "wof:placetype":"venue"
},
  "geometry": {"coordinates":[4.857617,52.082153],"type":"Point"}
}