{
  "type": "Feature",
  "properties": {
    "addr:full":"Tinnegieterstraat 10 Alkmaar North Holland 1825 DS",
    "addr:housenumber":"10",
    "addr:postcode":"1825 ds",
    "addr:street":"Tinnegieterstraat",
    "iso:country":"NL",
    "sg:address":"Tinnegieterstraat 10",
    "sg:city":"Alkmaar",
    "sg:orig_category":"Boekhouders",
    "sg:phone":"+31 72 561 8876",
    "sg:postcode":"1825 DS",
    "sg:province":"North Holland",
    "wof:name":"Adminifisc",
    "wof:placetype":"venue"
},
  "geometry": {"coordinates":[4.744579,52.653522],"type":"Point"}
}