{
  "type": "Feature",
  "properties": {
    "addr:full":"Zakkendragersstg 12 Utrecht Utrecht 3511 AA",
    "addr:housenumber":"12",
    "addr:postcode":"3511 aa",
    "addr:street":"Zakkendragersstg",
    "iso:country":"NL",
    "sg:address":"Zakkendragersstg 12",
    "sg:city":"Utrecht",
    "sg:orig_category":"Kantoorbenodigdheden",
    "sg:phone":"+31 30 230 0629",
    "sg:postcode":"3511 AA",
    "sg:province":"Utrecht",
    "wof:name":"Bureaubewust",
    "wof:placetype":"venue"
},
  "geometry": {"coordinates":[5.1158781052,52.0924835205],"type":"Point"}
}