{
  "type": "Feature",
  "properties": {
    "iso:country":"NL",
    "sg:address":"Stormsweg 12",
    "sg:city":"Krimpen A/D Ijssel",
    "sg:orig_category":"Algemene Werktuigbouw",
    "sg:phone":"+31 180 551 513",
    "sg:postcode":"2921 LZ",
    "sg:province":"Zuid-Holland",
    "wof:name":"Velaco Balkonhekken",
    "wof:placetype":"venue"
},
  "geometry": {"coordinates":[4.575385,51.908634],"type":"Point"}
}