{
  "type": "Feature",
  "properties": {
    "addr:full":"Stormsweg 12 Krimpen A/D Ijssel Zuid-Holland 2921 LZ",
    "addr:housenumber":"12;a / d",
    "addr:postcode":"2921 lz",
    "addr:street":"Stormsweg",
    "iso:country":"NL",
    "sg:address":"Stormsweg 12",
    "sg:city":"Krimpen A/D Ijssel",
    "sg:orig_category":"Algemene Werktuigbouw",
    "sg:phone":"+31 180 551 513",
    "sg:postcode":"2921 LZ",
    "sg:province":"Zuid-Holland",
    "wof:name":"Velaco Balkonhekken",
    "wof:placetype":"venue"
},
  "geometry": {"coordinates":[4.575385,51.908634],"type":"Point"}
}