{
  "type": "Feature",
  "properties": {
    "addr:full":"Oosterbleek 58 Lochem Gelderland 7241 DK",
    "addr:housenumber":"58",
    "addr:postcode":"7241 dk",
    "addr:street":"Oosterbleek;Gelderland",
    "iso:country":"NL",
    "sg:address":"Oosterbleek 58",
    "sg:city":"Lochem",
    "sg:orig_category":"Podotherapeuten",
    "sg:phone":"+31 573 255 055",
    "sg:postcode":"7241 DK",
    "sg:province":"Gelderland",
    "wof:name":"Hofacker, A W",
    "wof:placetype":"venue"
},
  "geometry": {"coordinates":[6.418011,52.162117],"type":"Point"}
}