{
  "type": "Feature",
  "properties": {
    "addr:full":"Groenstr 11 Prinsenbeek North Brabant 4841 BA",
    "addr:housenumber":"11",
    "addr:postcode":"4841 ba",
    "addr:street":"Groenstr",
    "iso:country":"NL",
    "sg:address":"Groenstr 11",
    "sg:city":"Prinsenbeek",
    "sg:orig_category":"Accountants - Administratie- Consulenten En -Kantoren",
    "sg:phone":"+31 76 541 8941",
    "sg:postcode":"4841 BA",
    "sg:province":"North Brabant",
    "wof:name":"Berg & Van Oosten Accountants- En Belastingadvieskantoor Bv, V/D",
    "wof:placetype":"venue"
},
  "geometry": {"coordinates":[4.717293,51.598972],"type":"Point"}
}