{
  "type": "Feature",
  "properties": {
    "iso:country":"NL",
    "sg:address":"Sophiastraat 10",
    "sg:city":"Pijnacker",
    "sg:orig_category":"Loodgieterswerk, Verwarming And Sanitaire Installaties",
    "sg:phone":"+31 15 361 0186",
    "sg:postcode":"2641 HN",
    "sg:province":"Zuid-Holland",
    "wof:name":"Van Schijndel Klussenbedrijf",
    "wof:placetype":"venue"
},
  "geometry": {"coordinates":[4.434957,52.017387],"type":"Point"}
}