{
  "type": "Feature",
  "properties": {
    "addr:full":"Plein 1945 81 Ymuiden North Holland 1971 GC",
    "addr:housenumber":"81",
    "addr:postcode":"1971 gc",
    "addr:street":"Plein 1945",
    "iso:country":"NL",
    "sg:address":"Plein 1945 81",
    "sg:city":"Ymuiden",
    "sg:orig_category":"Bloemen En Planten",
    "sg:phone":"+31 255 514 241",
    "sg:postcode":"1971 GC",
    "sg:province":"North Holland",
    "wof:name":"Krab, Jan",
    "wof:placetype":"venue"
},
  "geometry": {"coordinates":[4.617625,52.458279],"type":"Point"}
}