{
  "type": "Feature",
  "properties": {
    "iso:country":"NL",
    "sg:address":"Lavendelheide 9",
    "sg:city":"Drachten",
    "sg:orig_category":"Bedrijfsorganisaties",
    "sg:phone":"+31 512 305 000",
    "sg:postcode":"9202 PD",
    "sg:province":"Friesland",
    "sg:website":"http://www.nlto.nl",
    "wof:name":"Nlto",
    "wof:placetype":"venue"
},
  "geometry": {"coordinates":[6.129661,53.104519],"type":"Point"}
}