{
  "type": "Feature",
  "properties": {
    "addr:full":"Ploeglaan 26 Eemnes Utrecht 3755 HT",
    "addr:housenumber":"26",
    "addr:postcode":"3755 ht",
    "addr:street":"Ploeglaan",
    "iso:country":"NL",
    "sg:address":"Ploeglaan 26",
    "sg:city":"Eemnes",
    "sg:orig_category":"Loodgieterswerk, Verwarming And Sanitaire Installaties",
    "sg:phone":"+31 35 538 7461",
    "sg:postcode":"3755 HT",
    "sg:province":"Utrecht",
    "wof:name":"Kok Onderhoud",
    "wof:placetype":"venue"
},
  "geometry": {"coordinates":[5.258261,52.250267],"type":"Point"}
}