{
  "type": "Feature",
  "properties": {
    "addr:full":"L Veerstr 12 Haarlem North Holland 2011 DB",
    "addr:housenumber":"12",
    "addr:postcode":"2011 db",
    "iso:country":"NL",
    "sg:address":"L Veerstr 12",
    "sg:city":"Haarlem",
    "sg:orig_category":"Meubelen Gebruikte",
    "sg:phone":"+31 23 532 3282",
    "sg:postcode":"2011 DB",
    "sg:province":"North Holland",
    "wof:name":"Collector, The",
    "wof:placetype":"venue"
},
  "geometry": {"coordinates":[4.637689,52.38028],"type":"Point"}
}