{
  "type": "Feature",
  "properties": {
    "addr:full":"Randstad 2126 Almere NL. 1314 BM",
    "addr:housenumber":"2126",
    "addr:postcode":"1314 bm",
    "addr:street":"Nl.",
    "iso:country":"NL",
    "sg:address":"Randstad 2126",
    "sg:city":"Almere",
    "sg:orig_category":"Grafische Bedrijven",
    "sg:phone":"+31 36 548 2020",
    "sg:postcode":"1314 BM",
    "sg:province":"NL.",
    "wof:name":"Ppc",
    "wof:placetype":"venue"
},
  "geometry": {"coordinates":[5.223281,52.377781],"type":"Point"}
}