{
  "type": "Feature",
  "properties": {
    "iso:country":"NL",
    "sg:address":"St Catharinastr 24",
    "sg:city":"Eindhoven",
    "sg:orig_category":"Architecten En Architectenbureaus",
    "sg:phone":"+31 40 296 0255",
    "sg:postcode":"5611 JC",
    "sg:province":"North Brabant",
    "wof:name":"Hs",
    "wof:placetype":"venue"
},
  "geometry": {"coordinates":[5.471593,51.436611],"type":"Point"}
}