{
  "type": "Feature",
  "properties": {
    "addr:full":"Kapelstr 39 Veghel Noord-Brabant 5466 PA",
    "addr:housenumber":"39",
    "addr:postcode":"5466 pa",
    "addr:street":"Kapelstr",
    "iso:country":"NL",
    "sg:address":"Kapelstr 39",
    "sg:city":"Veghel",
    "sg:orig_category":"Geluidsinstallaties - Verhuur",
    "sg:phone":"+31 413 319 233",
    "sg:postcode":"5466 PA",
    "sg:province":"Noord-Brabant",
    "wof:name":"Profi Power",
    "wof:placetype":"venue"
},
  "geometry": {"coordinates":[5.49692,51.604317],"type":"Point"}
}