{
  "type": "Feature",
  "properties": {
    "addr:full":"De Passage 5 Papendrecht Zuid-Holland 3351 HJ",
    "addr:housenumber":"5",
    "addr:postcode":"3351 hj",
    "addr:street":"De Passage",
    "iso:country":"NL",
    "sg:address":"De Passage 5",
    "sg:city":"Papendrecht",
    "sg:orig_category":"Accountants - Administratie- Consulenten En -Kantoren",
    "sg:phone":"+31 78 615 5170",
    "sg:postcode":"3351 HJ",
    "sg:province":"Zuid-Holland",
    "wof:name":"Kok, Accountantskantoor",
    "wof:placetype":"venue"
},
  "geometry": {"coordinates":[4.682844,51.82571],"type":"Point"}
}