{
  "type": "Feature",
  "properties": {
    "addr:full":"De Louwstraat 9 Schaijk North Brabant 5374 CE",
    "addr:housenumber":"9",
    "addr:postcode":"5374 ce",
    "addr:street":"De Louwstraat",
    "iso:country":"NL",
    "sg:address":"De Louwstraat 9",
    "sg:city":"Schaijk",
    "sg:orig_category":"Mobiele Service Aan Motorvoertuigen",
    "sg:phone":"+31 486 461 845",
    "sg:postcode":"5374 CE",
    "sg:province":"North Brabant",
    "wof:name":"Kraanverhuur & Transport Van Grinsven Bv",
    "wof:placetype":"venue"
},
  "geometry": {"coordinates":[5.643192,51.739594],"type":"Point"}
}