{
  "type": "Feature",
  "properties": {
    "addr:full":"Grindwg 68 Rotterdam South Holland 3055 VC",
    "addr:housenumber":"68",
    "addr:postcode":"3055 vc",
    "addr:street":"Grindwg",
    "iso:country":"NL",
    "sg:address":"Grindwg 68",
    "sg:city":"Rotterdam",
    "sg:orig_category":"Logopedisten",
    "sg:phone":"+31 10 422 1931",
    "sg:postcode":"3055 VC",
    "sg:province":"South Holland",
    "wof:name":"Rijkeboer, E",
    "wof:placetype":"venue"
},
  "geometry": {"coordinates":[4.49537,51.963791],"type":"Point"}
}