{
  "type": "Feature",
  "properties": {
    "addr:full":"Markthoek 102 Winterswijk Gelderland 7101 DC",
    "addr:housenumber":"102",
    "addr:postcode":"7101",
    "addr:street":"Markthoek;Gelderland",
    "iso:country":"NL",
    "sg:address":"Markthoek 102",
    "sg:city":"Winterswijk",
    "sg:orig_category":"Kansspelen",
    "sg:phone":"+31 543 520 269",
    "sg:postcode":"7101 DC",
    "sg:province":"Gelderland",
    "wof:name":"Fair Play Winterswijk",
    "wof:placetype":"venue"
},
  "geometry": {"coordinates":[6.7209172249,51.9720115662],"type":"Point"}
}