{
  "type": "Feature",
  "properties": {
    "iso:country":"NL",
    "sg:address":"Markthoek 102",
    "sg:city":"Winterswijk",
    "sg:orig_category":"Kansspelen",
    "sg:phone":"+31 543 520 269",
    "sg:postcode":"7101 DC",
    "sg:province":"Gelderland",
    "wof:name":"Fair Play Winterswijk",
    "wof:placetype":"venue"
},
  "geometry": {"coordinates":[6.7209172249,51.9720115662],"type":"Point"}
}