{
  "type": "Feature",
  "properties": {
    "addr:full":"Keulsveld 6 Roosendaal Noord-Brabant 4705 RS",
    "addr:housenumber":"6",
    "addr:postcode":"4705 rs",
    "addr:street":"Keulsveld",
    "iso:country":"NL",
    "sg:address":"Keulsveld 6",
    "sg:city":"Roosendaal",
    "sg:orig_category":"Autoschade- Herstelbedrijven",
    "sg:phone":"+31 165 533 815",
    "sg:postcode":"4705 RS",
    "sg:province":"Noord-Brabant",
    "wof:name":"Gerritsma Autoschade",
    "wof:placetype":"venue"
},
  "geometry": {"coordinates":[4.500275,51.544174],"type":"Point"}
}