{
  "type": "Feature",
  "properties": {
    "addr:full":"Noorderplein 6 Deventer Overijssel 7412 VS",
    "addr:housenumber":"6",
    "addr:postcode":"7412 vs",
    "addr:street":"Noorderplein",
    "iso:country":"NL",
    "sg:address":"Noorderplein 6",
    "sg:city":"Deventer",
    "sg:orig_category":"Advocaten And Juridische Adviseurs",
    "sg:phone":"+31 570 612 900",
    "sg:postcode":"7412 VS",
    "sg:province":"Overijssel",
    "wof:name":"Advocatenkantoor Lanting & Akkerman",
    "wof:placetype":"venue"
},
  "geometry": {"coordinates":[-89.21163199999999,36.820946],"type":"Point"}
}