{
  "type": "Feature",
  "properties": {
    "addr:full":"Rottekade 172 Bergschenhoek Zuid-Holland 2661 JT",
    "addr:housenumber":"172",
    "addr:postcode":"2661 jt",
    "addr:street":"Rottekade",
    "iso:country":"NL",
    "sg:address":"Rottekade 172",
    "sg:city":"Bergschenhoek",
    "sg:orig_category":"Aanvullende Diensten Watertransport",
    "sg:phone":"+31 10 521 7823",
    "sg:postcode":"2661 JT",
    "sg:province":"Zuid-Holland",
    "wof:name":"Jachtwerf S Van Logchem",
    "wof:placetype":"venue"
},
  "geometry": {"coordinates":[4.526227,51.965405],"type":"Point"}
}