{
  "type": "Feature",
  "properties": {
    "addr:full":"Ringln . Eerbeek Gelderland 6961 KJ",
    "addr:postcode":"6961 kj",
    "addr:street":"Gelderland",
    "iso:country":"NL",
    "sg:address":"Ringln .",
    "sg:city":"Eerbeek",
    "sg:orig_category":"Duiven En Duivensport - Artikelen",
    "sg:phone":"+31 313 652 224",
    "sg:postcode":"6961 KJ",
    "sg:province":"Gelderland",
    "wof:name":"Ons Vermaak Duivensportver",
    "wof:placetype":"venue"
},
  "geometry": {"coordinates":[6.008903,52.071884],"type":"Point"}
}