{
  "type": "Feature",
  "properties": {
    "addr:full":"Nijreesdwarsweg 8 Almelo Overijssel 7609 PD",
    "addr:housenumber":"8",
    "addr:postcode":"7609 pd",
    "addr:street":"Nijreesdwarsweg",
    "iso:country":"NL",
    "sg:address":"Nijreesdwarsweg 8",
    "sg:city":"Almelo",
    "sg:orig_category":"Loodgieterswerk, Verwarming And Sanitaire Installaties",
    "sg:phone":"+31 6 51590520",
    "sg:postcode":"7609 PD",
    "sg:province":"Overijssel",
    "wof:name":"Prima",
    "wof:placetype":"venue"
},
  "geometry": {"coordinates":[6.664749,52.338734],"type":"Point"}
}