{
  "type": "Feature",
  "properties": {
    "addr:full":"Impuls 153 Purmerend Noord-Holland 1446 WE",
    "addr:housenumber":"153",
    "addr:postcode":"1446 we",
    "addr:street":"Impuls",
    "iso:country":"NL",
    "sg:address":"Impuls 153",
    "sg:city":"Purmerend",
    "sg:orig_category":"Koeltechniek",
    "sg:phone":"+31 299 622 022",
    "sg:postcode":"1446 WE",
    "sg:province":"Noord-Holland",
    "wof:name":"Ksb",
    "wof:placetype":"venue"
},
  "geometry": {"coordinates":[5.006594,52.51091],"type":"Point"}
}