{
  "type": "Feature",
  "properties": {
    "addr:full":"Broekslagen 11 Steenwijk Overijssel 8331 TJ",
    "addr:housenumber":"11",
    "addr:postcode":"8331 tj",
    "addr:street":"Broekslagen",
    "iso:country":"NL",
    "sg:address":"Broekslagen 11",
    "sg:city":"Steenwijk",
    "sg:orig_category":"Behang Gh",
    "sg:phone":"+31 521 514 114",
    "sg:postcode":"8331 TJ",
    "sg:province":"Overijssel",
    "wof:name":"Intervos Bv",
    "wof:placetype":"venue"
},
  "geometry": {"coordinates":[6.095137,52.778214],"type":"Point"}
}