{
  "type": "Feature",
  "properties": {
    "addr:full":"Hettenheuvelwg 12 Amsterdam Zuidoost North Holland 1101 BN",
    "addr:housenumber":"12",
    "addr:postcode":"1101 bn",
    "addr:street":"Hettenheuvelwg",
    "iso:country":"NL",
    "sg:address":"Hettenheuvelwg 12",
    "sg:city":"Amsterdam Zuidoost",
    "sg:orig_category":"Kantoor- En Bedrijfsmeubelen",
    "sg:phone":"+31 20 342 0000",
    "sg:postcode":"1101 BN",
    "sg:province":"North Holland",
    "sg:website":"http://www.voko.nl",
    "wof:name":"Voko Nederland Bv",
    "wof:placetype":"venue"
},
  "geometry": {"coordinates":[4.9464149475,52.3037986755],"type":"Point"}
}