{
  "type": "Feature",
  "properties": {
    "addr:full":"Gooierserf 384 Huizen North Holland 1276 KT",
    "addr:housenumber":"384",
    "addr:postcode":"1276 kt",
    "addr:street":"Gooierserf",
    "iso:country":"NL",
    "sg:address":"Gooierserf 384",
    "sg:city":"Huizen",
    "sg:orig_category":"Balletscholen",
    "sg:phone":"+31 35 526 9991",
    "sg:postcode":"1276 KT",
    "sg:province":"North Holland",
    "wof:name":"Carry Schomper",
    "wof:placetype":"venue"
},
  "geometry": {"coordinates":[5.25805,52.295609],"type":"Point"}
}