{
  "type": "Feature",
  "properties": {
    "addr:full":"Nazarethln 29 Eindhoven Noord-Brabant 5625 PM",
    "addr:housenumber":"29",
    "addr:postcode":"5625 pm",
    "addr:street":"Nazarethln",
    "iso:country":"NL",
    "sg:address":"Nazarethln 29",
    "sg:city":"Eindhoven",
    "sg:orig_category":"Voetbalverenigingen",
    "sg:phone":"+31 40 241 9395",
    "sg:postcode":"5625 PM",
    "sg:province":"Noord-Brabant",
    "wof:name":"Capax",
    "wof:placetype":"venue"
},
  "geometry": {"coordinates":[5.480615,51.47501],"type":"Point"}
}