{
  "type": "Feature",
  "properties": {
    "addr:full":"Midslandstr 43 Tilburg Noord-Brabant 5045 DK",
    "addr:housenumber":"43",
    "addr:postcode":"5045 dk",
    "addr:street":"Midslandstr",
    "iso:country":"NL",
    "sg:address":"Midslandstr 43",
    "sg:city":"Tilburg",
    "sg:orig_category":"Webdesign Bureaus",
    "sg:phone":"+31 13 455 9792",
    "sg:postcode":"5045 DK",
    "sg:province":"Noord-Brabant",
    "wof:name":"E-Trick",
    "wof:placetype":"venue"
},
  "geometry": {"coordinates":[4.9850640297,51.5951042175],"type":"Point"}
}