{
  "type": "Feature",
  "properties": {
    "iso:country":"NL",
    "sg:address":"Schans 17",
    "sg:city":"Stavoren",
    "sg:classifiers":[
        {
            "category":"Fast Food",
            "type":"Food & Drink"
        }
    ],
    "sg:phone":"+31 514 681 201",
    "sg:postcode":"8715 JP",
    "sg:province":"Friesland",
    "sg:tags":[
        "afhaal",
        "restaurant"
    ],
    "wof:name":"J.A.T. Smits-Kemker",
    "wof:placetype":"venue"
},
  "geometry": {"coordinates":[5.360667,52.884014],"type":"Point"}
}