{
  "type": "Feature",
  "properties": {
    "addr:full":"Herenstraat 98 Nieuwegein Utrecht 3431 CB",
    "addr:housenumber":"98",
    "addr:postcode":"3431 cb",
    "addr:street":"Herenstraat",
    "iso:country":"NL",
    "sg:address":"Herenstraat 98",
    "sg:city":"Nieuwegein",
    "sg:orig_category":"Farmaceutische Producten Gh",
    "sg:phone":"+31 30 609 0686",
    "sg:postcode":"3431 CB",
    "sg:province":"Utrecht",
    "wof:name":"Afp Medical Nederland",
    "wof:placetype":"venue"
},
  "geometry": {"coordinates":[5.089011,52.030617],"type":"Point"}
}