{
  "type": "Feature",
  "properties": {
    "addr:full":"Binnenpad 54 Giethoorn Overijssel 8355 BT",
    "addr:housenumber":"54",
    "addr:postcode":"8355 bt",
    "addr:street":"Binnenpad",
    "iso:country":"NL",
    "sg:address":"Binnenpad 54",
    "sg:city":"Giethoorn",
    "sg:orig_category":"Binnenvaart",
    "sg:phone":"+31 521 361 270",
    "sg:postcode":"8355 BT",
    "sg:province":"Overijssel",
    "wof:name":"Firma Smit Recreatie Giethoorn",
    "wof:placetype":"venue"
},
  "geometry": {"coordinates":[6.037198,52.724377],"type":"Point"}
}