{
  "type": "Feature",
  "properties": {
    "addr:full":"Opera 5 Zaandam North Holland 1507 VG",
    "addr:housenumber":"5",
    "addr:postcode":"1507 vg",
    "addr:street":"Opera",
    "iso:country":"NL",
    "sg:address":"Opera 5",
    "sg:city":"Zaandam",
    "sg:orig_category":"Verzekeringen - Verzekeringskantoren",
    "sg:phone":"+31 75 616 4800",
    "sg:postcode":"1507 VG",
    "sg:province":"North Holland",
    "wof:name":"Steffhaan",
    "wof:placetype":"venue"
},
  "geometry": {"coordinates":[4.808401,52.440388],"type":"Point"}
}