{
  "type": "Feature",
  "properties": {
    "addr:full":"Dr V Stratenwg 15 Gorinchem South Holland 4205 LA",
    "addr:housenumber":"15",
    "addr:postcode":"4205 la",
    "addr:street":"Dr;Stratenwg",
    "iso:country":"NL",
    "sg:address":"Dr V Stratenwg 15",
    "sg:city":"Gorinchem",
    "sg:classifiers":[
        {
            "category":"Professional",
            "subcategory":"Accounting & Tax Preparation",
            "type":"Services"
        }
    ],
    "sg:phone":"+31 183 629 589",
    "sg:postcode":"4205 LA",
    "sg:province":"South Holland",
    "sg:tags":[
        "accountant",
        "en",
        "-kantoren",
        "register-"
    ],
    "wof:name":"Ottevanger",
    "wof:placetype":"venue"
},
  "geometry": {"coordinates":[4.969185,51.830631],"type":"Point"}
}