{
  "type": "Feature",
  "properties": {
    "iso:country":"NL",
    "sg:address":"Stationsweg 2",
    "sg:city":"Meppel",
    "sg:orig_category":"Verzekeringen",
    "sg:phone":"+31 522 252 580",
    "sg:postcode":"7941 HD",
    "sg:province":"Drenthe",
    "wof:name":"Nieuwenhuis En Soer Assurantien Bv",
    "wof:placetype":"venue"
},
  "geometry": {"coordinates":[6.196295,52.699615],"type":"Point"}
}