{
  "type": "Feature",
  "properties": {
    "addr:full":"Kemenadehoek 41 Enschede NL.08 7546 ER",
    "addr:housenumber":"41",
    "addr:postcode":"7546",
    "addr:street":"Kemenadehoek;Er",
    "iso:country":"NL",
    "sg:address":"Kemenadehoek 41",
    "sg:city":"Enschede",
    "sg:orig_category":"Leesportefeuilles",
    "sg:phone":"+31 53 477 2857",
    "sg:postcode":"7546 ER",
    "sg:province":"NL.08",
    "wof:name":"Slb",
    "wof:placetype":"venue"
},
  "geometry": {"coordinates":[6.855878,52.1936],"type":"Point"}
}