{
  "type": "Feature",
  "properties": {
    "addr:full":"Ophelialn 151 Aalsmeer North Holland 1431 HD",
    "addr:housenumber":"151",
    "addr:postcode":"1431 hd",
    "iso:country":"NL",
    "sg:address":"Ophelialn 151",
    "sg:city":"Aalsmeer",
    "sg:orig_category":"Boekhandels",
    "sg:phone":"+31 297 324 117",
    "sg:postcode":"1431 HD",
    "sg:province":"North Holland",
    "wof:name":"Read Shop, The",
    "wof:placetype":"venue"
},
  "geometry": {"coordinates":[4.749068,52.266991],"type":"Point"}
}