{
  "type": "Feature",
  "properties": {
    "addr:full":"Koppeldk 16A-B Nieuwegein Utrecht 3439 LP",
    "addr:housenumber":"16a-b",
    "addr:postcode":"3439 lp",
    "addr:street":"Koppeldk",
    "iso:country":"NL",
    "sg:address":"Koppeldk 16A-B",
    "sg:city":"Nieuwegein",
    "sg:orig_category":"Horecabenodigdheden",
    "sg:phone":"+31 30 636 0163",
    "sg:postcode":"3439 LP",
    "sg:province":"Utrecht",
    "sg:website":"http://www.bayram.nl",
    "wof:name":"Bayram International Trading",
    "wof:placetype":"venue"
},
  "geometry": {"coordinates":[5.082197,52.027325],"type":"Point"}
}