{
  "type": "Feature",
  "properties": {
    "addr:full":"Havikshof 37 Ermelo Gelderland 3853 BA",
    "addr:housenumber":"37",
    "addr:postcode":"3853 ba",
    "addr:street":"Havikshof;Gelderland",
    "iso:country":"NL",
    "sg:address":"Havikshof 37",
    "sg:city":"Ermelo",
    "sg:orig_category":"Adviesbureaus Bedrijfsorganisatie",
    "sg:phone":"+31 341 561 244",
    "sg:postcode":"3853 BA",
    "sg:province":"Gelderland",
    "wof:name":"Chakra",
    "wof:placetype":"venue"
},
  "geometry": {"coordinates":[5.610723,52.297874],"type":"Point"}
}