{
  "type": "Feature",
  "properties": {
    "iso:country":"NL",
    "sg:address":"Havikshof 37",
    "sg:city":"Ermelo",
    "sg:orig_category":"Adviesbureaus Bedrijfsorganisatie",
    "sg:phone":"+31 341 561 244",
    "sg:postcode":"3853 BA",
    "sg:province":"Gelderland",
    "wof:name":"Chakra",
    "wof:placetype":"venue"
},
  "geometry": {"coordinates":[5.610723,52.297874],"type":"Point"}
}