{
  "type": "Feature",
  "properties": {
    "iso:country":"NL",
    "sg:address":"Azaleaweg 13",
    "sg:city":"Paterswolde",
    "sg:orig_category":"Paramedische Behandelingen",
    "sg:phone":"+31 50 309 2303",
    "sg:postcode":"9765 HT",
    "sg:province":"Provincie Drenthe",
    "wof:name":"K. Junius-Koster",
    "wof:placetype":"venue"
},
  "geometry": {"coordinates":[6.557353,53.144222],"type":"Point"}
}