{
  "type": "Feature",
  "properties": {
    "addr:full":"Haarlemmerpln 1 Amsterdam Noord-Holland 1013 HP",
    "addr:housenumber":"1",
    "addr:postcode":"1013 hp",
    "addr:street":"Haarlemmerpln",
    "iso:country":"NL",
    "sg:address":"Haarlemmerpln 1",
    "sg:city":"Amsterdam",
    "sg:orig_category":"Beeldende Kunstenaars",
    "sg:phone":"+31 20 622 8899",
    "sg:postcode":"1013 HP",
    "sg:province":"Noord-Holland",
    "wof:name":"Turion, M M",
    "wof:placetype":"venue"
},
  "geometry": {"coordinates":[4.884202,52.384285],"type":"Point"}
}