{
  "type": "Feature",
  "properties": {
    "addr:full":"Huis Ter Heidewg 22 Zeist Utrecht 3705 LZ",
    "addr:housenumber":"22",
    "addr:postcode":"3705 lz",
    "addr:street":"Huis Ter Heidewg",
    "iso:country":"NL",
    "sg:address":"Huis Ter Heidewg 22",
    "sg:city":"Zeist",
    "sg:orig_category":"Kantoorbenodigdheden",
    "sg:phone":"+31 30 697 0079",
    "sg:postcode":"3705 LZ",
    "sg:province":"Utrecht",
    "wof:name":"Workplace",
    "wof:placetype":"venue"
},
  "geometry": {"coordinates":[5.255437851,52.1037521362],"type":"Point"}
}