{
  "type": "Feature",
  "properties": {
    "iso:country":"NL",
    "sg:address":"Wilhelminastr 3",
    "sg:city":"Nuth",
    "sg:orig_category":"Verenigingsgebouwen",
    "sg:phone":"+31 45 524 2174",
    "sg:postcode":"6361 CA",
    "sg:province":"Limburg",
    "wof:name":"Trefcentr",
    "wof:placetype":"venue"
},
  "geometry": {"coordinates":[5.885999,50.918785],"type":"Point"}
}