{
  "type": "Feature",
  "properties": {
    "iso:country":"NL",
    "sg:address":"Koopmansplein 8",
    "sg:city":"Assen",
    "sg:classifiers":[
        {
            "category":"Retail",
            "subcategory":"Photofinishing",
            "type":"Services"
        }
    ],
    "sg:phone":"+31 592 311 404",
    "sg:postcode":"9401 EL",
    "sg:province":"Provincie Drenthe",
    "sg:tags":[
        "foto",
        "film"
    ],
    "wof:name":"Super Photo Snelservice",
    "wof:placetype":"venue"
},
  "geometry": {"coordinates":[6.561116,52.995247],"type":"Point"}
}