{
  "type": "Feature",
  "properties": {
    "addr:full":"Hanzewg 52010 Deventer Overijssel 7418 AW",
    "addr:postcode":"52010;7418 aw",
    "addr:street":"Hanzewg",
    "iso:country":"NL",
    "sg:address":"Hanzewg 52010",
    "sg:city":"Deventer",
    "sg:orig_category":"Scheepvaartservice- Bureaus",
    "sg:phone":"+31 570 640 642",
    "sg:postcode":"7418 AW",
    "sg:province":"Overijssel",
    "wof:name":"Salland Services",
    "wof:placetype":"venue"
},
  "geometry": {"coordinates":[6.175708,52.248123],"type":"Point"}
}