{
  "type": "Feature",
  "properties": {
    "addr:full":"Groenstr 160 Geleen Limburg 6162 ET",
    "addr:housenumber":"160",
    "addr:postcode":"6162 et",
    "addr:street":"Geleen Limburg",
    "iso:country":"NL",
    "sg:address":"Groenstr 160",
    "sg:city":"Geleen",
    "sg:orig_category":"Logopedisten",
    "sg:phone":"+31 46 474 5828",
    "sg:postcode":"6162 ET",
    "sg:province":"Limburg",
    "wof:name":"Niemann-Keulen, Y S P M",
    "wof:placetype":"venue"
},
  "geometry": {"coordinates":[5.826838,50.973686],"type":"Point"}
}