{
  "type": "Feature",
  "properties": {
    "addr:full":"Hoofdstr 87A Kaatsheuvel Noord-Brabant 5171 DK",
    "addr:housenumber":"87a",
    "addr:postcode":"5171 dk",
    "addr:street":"Hoofdstr",
    "iso:country":"NL",
    "sg:address":"Hoofdstr 87A",
    "sg:city":"Kaatsheuvel",
    "sg:orig_category":"Opticiens",
    "sg:phone":"+31 416 272 360",
    "sg:postcode":"5171 DK",
    "sg:province":"Noord-Brabant",
    "wof:name":"Musters",
    "wof:placetype":"venue"
},
  "geometry": {"coordinates":[5.0323209763,51.6616249084],"type":"Point"}
}