{
  "type": "Feature",
  "properties": {
    "addr:full":"Bilderdijkstraat 69 Amsterdam North Holland 1053 KM",
    "addr:housenumber":"69",
    "addr:postcode":"1053 km",
    "addr:street":"Bilderdijkstraat",
    "iso:country":"NL",
    "sg:address":"Bilderdijkstraat 69",
    "sg:city":"Amsterdam",
    "sg:orig_category":"Schoenen",
    "sg:phone":"+31 20 612 9465",
    "sg:postcode":"1053 KM",
    "sg:province":"North Holland",
    "wof:name":"Cees Tak Bv",
    "wof:placetype":"venue"
},
  "geometry": {"coordinates":[4.870695,52.369831],"type":"Point"}
}