{
  "type": "Feature",
  "properties": {
    "iso:country":"NL",
    "sg:address":"Dorpsstraat 23",
    "sg:city":"Bergschenhoek",
    "sg:orig_category":"Banken And Kredietinstellingen",
    "sg:phone":"+31 10 521 2285",
    "sg:postcode":"2661 CD",
    "sg:province":"Zuid-Holland",
    "wof:name":"Postkantoor",
    "wof:placetype":"venue"
},
  "geometry": {"coordinates":[4.49989,51.988827],"type":"Point"}
}