{
  "type": "Feature",
  "properties": {
    "addr:full":"Rijksstraatweg 58 Haren Gn Groningen 9752 AG",
    "addr:housenumber":"58",
    "addr:postcode":"9752",
    "addr:street":"Rijksstraatweg",
    "iso:country":"NL",
    "sg:address":"Rijksstraatweg 58",
    "sg:city":"Haren Gn",
    "sg:orig_category":"Verzekeringen",
    "sg:phone":"+31 50 534 6458",
    "sg:postcode":"9752 AG",
    "sg:province":"Groningen",
    "wof:name":"Van Hemmen Assurantien",
    "wof:placetype":"venue"
},
  "geometry": {"coordinates":[6.595563,53.17984],"type":"Point"}
}