{
  "type": "Feature",
  "properties": {
    "addr:full":"Molenplein 1 Ter Apel Groningen 9561 KS",
    "addr:housenumber":"1",
    "addr:postcode":"9561 ks",
    "addr:street":"Molenplein",
    "iso:country":"NL",
    "sg:address":"Molenplein 1",
    "sg:city":"Ter Apel",
    "sg:orig_category":"Banken And Kredietinstellingen",
    "sg:phone":"+31 599 589 589",
    "sg:postcode":"9561 KS",
    "sg:province":"Groningen",
    "wof:name":"Rabobank",
    "wof:placetype":"venue"
},
  "geometry": {"coordinates":[7.062262,52.874756],"type":"Point"}
}