{
  "type": "Feature",
  "properties": {
    "addr:full":"Postbus 77 Wateringen Zuid-Holland 2290 AB",
    "addr:housenumber":"77",
    "addr:postcode":"2290 ab",
    "addr:street":"Postbus",
    "iso:country":"NL",
    "sg:address":"Postbus 77",
    "sg:city":"Wateringen",
    "sg:orig_category":"Artiesten/Gezelschappen",
    "sg:phone":"+31 174 220 429",
    "sg:postcode":"2290 AB",
    "sg:province":"Zuid-Holland",
    "sg:website":"http://www.go.to/popkoor-timeless",
    "wof:name":"Timeless",
    "wof:placetype":"venue"
},
  "geometry": {"coordinates":[4.27447,52.02372],"type":"Point"}
}