{
  "type": "Feature",
  "properties": {
    "addr:full":"Kerkstraat 1 Haren Gn Groningen 9751 BA",
    "addr:housenumber":"1",
    "addr:postcode":"9751 ba",
    "addr:street":"Kerkstraat",
    "iso:country":"NL",
    "sg:address":"Kerkstraat 1",
    "sg:city":"Haren Gn",
    "sg:orig_category":"Fietshandelaren",
    "sg:phone":"+31 50 534 6936",
    "sg:postcode":"9751 BA",
    "sg:province":"Groningen",
    "wof:name":"Rijwielhandel Alberts Vof",
    "wof:placetype":"venue"
},
  "geometry": {"coordinates":[6.60487,53.172184],"type":"Point"}
}