{
  "type": "Feature",
  "properties": {
    "iso:country":"NL",
    "sg:address":"Korteweide 23",
    "sg:city":"Zuid-Scharwoude",
    "sg:orig_category":"Kappers",
    "sg:phone":"+31 226 320 386",
    "sg:postcode":"1722 VA",
    "sg:province":"Virginia",
    "wof:name":"Kapsalon Ellen",
    "wof:placetype":"venue"
},
  "geometry": {"coordinates":[-79.771446228,38.0033493042],"type":"Point"}
}