{
  "type": "Feature",
  "properties": {
    "addr:full":"Taag 85 S Gravenhage 2491 CS",
    "addr:housenumber":"85",
    "addr:postcode":"2491 cs",
    "addr:street":"Taag;S Gravenhage",
    "iso:country":"NL",
    "sg:address":"Taag 85",
    "sg:city":"S Gravenhage",
    "sg:orig_category":"Geluidsinstallaties - Verhuur",
    "sg:phone":"+31 70 327 7664",
    "sg:postcode":"2491 CS",
    "wof:name":"Jpl",
    "wof:placetype":"venue"
},
  "geometry": {"coordinates":[4.38382,52.065289],"type":"Point"}
}