{
  "type": "Feature",
  "properties": {
    "addr:full":"Buitenruststr 4 Middelburg Zeeland 4337 EH",
    "addr:housenumber":"4",
    "addr:postcode":"4337 eh",
    "addr:street":"Buitenruststr",
    "iso:country":"NL",
    "sg:address":"Buitenruststr 4",
    "sg:city":"Middelburg",
    "sg:classifiers":[
        {
            "category":"Professional",
            "subcategory":"Accounting & Tax Preparation",
            "type":"Services"
        }
    ],
    "sg:phone":"+31 118 685 500",
    "sg:postcode":"4337 EH",
    "sg:province":"Zeeland",
    "sg:tags":[
        "accountant",
        "en",
        "-kantoren",
        "register-"
    ],
    "sg:website":"http://www.deloitte.nl",
    "wof:name":"Deloitte & Touche",
    "wof:placetype":"venue"
},
  "geometry": {"coordinates":[3.616943,51.492985],"type":"Point"}
}