{
  "type": "Feature",
  "properties": {
    "iso:country":"NL",
    "sg:address":"Koestr 31-33",
    "sg:city":"Amersfoort",
    "sg:orig_category":"Kappers",
    "sg:phone":"+31 33 465 2219",
    "sg:postcode":"3811 HK",
    "sg:province":"Utrecht",
    "wof:name":"Team Kapsalon",
    "wof:placetype":"venue"
},
  "geometry": {"coordinates":[5.386085,52.152325],"type":"Point"}
}