{
  "type": "Feature",
  "properties": {
    "iso:country":"NL",
    "sg:address":"Valkenhof 10",
    "sg:city":"Ermelo",
    "sg:orig_category":"Verenigingen En Stichtingen",
    "sg:phone":"+31 341 550 168",
    "sg:postcode":"3853 BR",
    "sg:province":"Gelderland",
    "wof:name":"Touch And Impact The Nations",
    "wof:placetype":"venue"
},
  "geometry": {"coordinates":[5.599559,52.297955],"type":"Point"}
}