{
  "type": "Feature",
  "properties": {
    "addr:full":"Stationsstraat 27 Gieten Provincie Drenthe 9461 GP",
    "addr:housenumber":"27",
    "addr:postcode":"9461 gp",
    "addr:street":"Stationsstraat;Provincie Drenthe",
    "iso:country":"NL",
    "sg:address":"Stationsstraat 27",
    "sg:city":"Gieten",
    "sg:orig_category":"Huishoudapparatuur, Televisies And Radio'S",
    "sg:phone":"+31 592 261 201",
    "sg:postcode":"9461 GP",
    "sg:province":"Provincie Drenthe",
    "wof:name":"Dragt Beeld En Geluid",
    "wof:placetype":"venue"
},
  "geometry": {"coordinates":[6.76435,53.002457],"type":"Point"}
}