{
  "type": "Feature",
  "properties": {
    "addr:full":"V Veldekekd 10 S Hertogenbosch Noord-Brabant 5216 KS",
    "addr:housenumber":"10",
    "addr:postcode":"5216 ks",
    "addr:street":"S",
    "iso:country":"NL",
    "sg:address":"V Veldekekd 10",
    "sg:city":"S Hertogenbosch",
    "sg:orig_category":"Fotoreportages",
    "sg:phone":"+31 73 642 4926",
    "sg:postcode":"5216 KS",
    "sg:province":"Noord-Brabant",
    "sg:website":"http://www.studiojpdegroot.nl",
    "wof:name":"Groot, Fotostudio Jan Paul De",
    "wof:placetype":"venue"
},
  "geometry": {"coordinates":[5.29824,51.69075],"type":"Point"}
}