{
  "type": "Feature",
  "properties": {
    "addr:full":"Dollard 74 Zwijndrecht South Holland 3332 EE",
    "addr:housenumber":"74",
    "addr:postcode":"3332 ee",
    "addr:street":"Dollard",
    "iso:country":"NL",
    "sg:address":"Dollard 74",
    "sg:city":"Zwijndrecht",
    "sg:orig_category":"Schoenen",
    "sg:phone":"+31 78 619 5080",
    "sg:postcode":"3332 EE",
    "sg:province":"South Holland",
    "wof:name":"Handelsonderneming P.W. Kerkhof-Dongen B",
    "wof:placetype":"venue"
},
  "geometry": {"coordinates":[4.652668,51.823177],"type":"Point"}
}