{
  "type": "Feature",
  "properties": {
    "addr:full":"Straat Van Welgelegen 17 Leeuwarden Provincie Friesland 8921 CP",
    "addr:housenumber":"17",
    "addr:postcode":"8921 cp",
    "addr:street":"Straat Van Welgelegen;Provincie Friesland",
    "iso:country":"NL",
    "sg:address":"Straat Van Welgelegen 17",
    "sg:city":"Leeuwarden",
    "sg:orig_category":"Visspeciaalzaken",
    "sg:phone":"+31 58 212 9126",
    "sg:postcode":"8921 CP",
    "sg:province":"Provincie Friesland",
    "wof:name":"Vishandel W. Visser",
    "wof:placetype":"venue"
},
  "geometry": {"coordinates":[5.812324,53.201775],"type":"Point"}
}