{
  "type": "Feature",
  "properties": {
    "addr:full":"Spykerboor 56 Sneek Friesland 8607 KC",
    "addr:housenumber":"56",
    "addr:postcode":"8607 kc",
    "addr:street":"Spykerboor",
    "iso:country":"NL",
    "sg:address":"Spykerboor 56",
    "sg:city":"Sneek",
    "sg:orig_category":"Bodemsanering",
    "sg:phone":"+31 515 433 991",
    "sg:postcode":"8607 KC",
    "sg:province":"Friesland",
    "wof:name":"T & K Service",
    "wof:placetype":"venue"
},
  "geometry": {"coordinates":[5.674919,53.01701],"type":"Point"}
}