{
  "type": "Feature",
  "properties": {
    "addr:full":"Kleverskerkseweg 73 Middelburg Zeeland 4338 PM",
    "addr:housenumber":"73",
    "addr:postcode":"4338 pm",
    "addr:street":"Kleverskerkseweg",
    "iso:country":"NL",
    "sg:address":"Kleverskerkseweg 73",
    "sg:city":"Middelburg",
    "sg:classifiers":[
        {
            "category":"Retail",
            "subcategory":"Storage",
            "type":"Services"
        }
    ],
    "sg:phone":"+31 118 650 650",
    "sg:postcode":"4338 PM",
    "sg:province":"Zeeland",
    "sg:tags":[
        "opslag",
        "bewaring"
    ],
    "wof:name":"Sealake Terminal Bv",
    "wof:placetype":"venue"
},
  "geometry": {"coordinates":[3.6402819157,51.5026779175],"type":"Point"}
}