{
  "type": "Feature",
  "properties": {
    "iso:country":"NL",
    "sg:address":"Pr Ireneln 326",
    "sg:city":"Ryswyk Zh",
    "sg:orig_category":"Bloemen En Planten",
    "sg:phone":"+31 70 394 1102",
    "sg:postcode":"2285 GD",
    "sg:province":"Zuid-Holland",
    "sg:website":"http://www.arlisa.nl",
    "wof:name":"Arlisa",
    "wof:placetype":"venue"
},
  "geometry": {"coordinates":[4.32436,52.037251],"type":"Point"}
}