{
  "type": "Feature",
  "properties": {
    "addr:full":"Rampwg 16-18 Noordwelle Zeeland 4326 LK",
    "addr:housenumber":"16-18",
    "addr:postcode":"4326 lk",
    "iso:country":"NL",
    "sg:address":"Rampwg 16-18",
    "sg:city":"Noordwelle",
    "sg:classifiers":[
        {
            "category":"Travel",
            "subcategory":"Hotels & Motels",
            "type":"Entertainment"
        }
    ],
    "sg:phone":"+31 111 461 214",
    "sg:postcode":"4326 LK",
    "sg:province":"Zeeland",
    "sg:website":"http://www.renesse.com/klokje",
    "wof:name":"Klokje, Hotel Restaurant 'T",
    "wof:placetype":"venue"
},
  "geometry": {"coordinates":[3.801933,51.739101],"type":"Point"}
}