{
  "type": "Feature",
  "properties": {
    "addr:full":"T Rond 2 Woudrichem Noord-Brabant 4285 DE",
    "addr:housenumber":"2",
    "addr:postcode":"4285 de",
    "addr:street":"T Rond",
    "iso:country":"NL",
    "sg:address":"T Rond 2",
    "sg:city":"Woudrichem",
    "sg:orig_category":"Mensendieck - Oefentherapeuten",
    "sg:phone":"+31 6 55533313",
    "sg:postcode":"4285 DE",
    "sg:province":"Noord-Brabant",
    "sg:website":"http://mensendieck.wolweb.nl",
    "wof:name":"Oefenther Mensendieck",
    "wof:placetype":"venue"
},
  "geometry": {"coordinates":[4.999451,51.810509],"type":"Point"}
}