{
  "type": "Feature",
  "properties": {
    "addr:full":"Mattelierstraat 1 Groenlo Gelderland 7141 BP",
    "addr:housenumber":"1",
    "addr:postcode":"7141 bp",
    "addr:street":"Mattelierstraat;Gelderland",
    "iso:country":"NL",
    "sg:address":"Mattelierstraat 1",
    "sg:city":"Groenlo",
    "sg:orig_category":"Drukkerijen And Copyshops",
    "sg:phone":"+31 544 464 911",
    "sg:postcode":"7141 BP",
    "sg:province":"Gelderland",
    "wof:name":"Reko Reklame & Publiciteitsvormgeving",
    "wof:placetype":"venue"
},
  "geometry": {"coordinates":[6.617824,52.041962],"type":"Point"}
}