{
  "type": "Feature",
  "properties": {
    "iso:country":"NL",
    "sg:address":"Saffier 19",
    "sg:city":"S Hertogenbosch",
    "sg:orig_category":"Sportverenigingen En Ontspannings- Verenigingen",
    "sg:phone":"+31 73 641 1871",
    "sg:postcode":"5231 KG",
    "sg:province":"Noord-Brabant",
    "wof:name":"Dageraad Kon Erk Handboogschutterij, De",
    "wof:placetype":"venue"
},
  "geometry": {"coordinates":[5.303458,51.713337],"type":"Point"}
}