{
  "type": "Feature",
  "properties": {
    "iso:country":"NL",
    "sg:address":"Tanneskampke 15",
    "sg:city":"S Hertogenbosch",
    "sg:orig_category":"Bloemen En Planten - Decoratie",
    "sg:phone":"+31 73 631 1475",
    "sg:postcode":"5221 BT",
    "sg:province":"Noord-Brabant",
    "wof:name":"Scenery Home Decoration",
    "wof:placetype":"venue"
},
  "geometry": {"coordinates":[5.26671,51.721546],"type":"Point"}
}