{
  "type": "Feature",
  "properties": {
    "addr:full":"Pley 1 Noorbeek Limburg 6255 AG",
    "addr:housenumber":"1",
    "addr:postcode":"6255",
    "addr:street":"Pley",
    "iso:country":"NL",
    "sg:address":"Pley 1",
    "sg:city":"Noorbeek",
    "sg:orig_category":"Verhuur Huishoudartikelen",
    "sg:phone":"+31 43 457 2144",
    "sg:postcode":"6255 AG",
    "sg:province":"Limburg",
    "wof:name":"Medicarent Bv",
    "wof:placetype":"venue"
},
  "geometry": {"coordinates":[5.808728,50.768379],"type":"Point"}
}