{
  "type": "Feature",
  "properties": {
    "addr:full":"Bedryfswg 16 Grootebroek Noord-Holland 1613 DX",
    "addr:housenumber":"16",
    "addr:postcode":"1613 dx",
    "addr:street":"Bedryfswg",
    "iso:country":"NL",
    "sg:address":"Bedryfswg 16",
    "sg:city":"Grootebroek",
    "sg:orig_category":"Ingenieursbureaus",
    "sg:phone":"+31 228 322 070",
    "sg:postcode":"1613 DX",
    "sg:province":"Noord-Holland",
    "wof:name":"Genie Techni Bv",
    "wof:placetype":"venue"
},
  "geometry": {"coordinates":[5.225203,52.692856],"type":"Point"}
}