{
  "type": "Feature",
  "properties": {
    "addr:full":"Industriestraat 11A Doetinchem Gelderland 7005 AN",
    "addr:housenumber":"11a",
    "addr:postcode":"7005 an",
    "addr:street":"Industriestraat;Gelderland",
    "iso:country":"NL",
    "sg:address":"Industriestraat 11A",
    "sg:city":"Doetinchem",
    "sg:orig_category":"Partycatering And -Organisatie",
    "sg:phone":"+31 314 360 751",
    "sg:postcode":"7005 AN",
    "sg:province":"Gelderland",
    "wof:name":"Joop'S Catering",
    "wof:placetype":"venue"
},
  "geometry": {"coordinates":[6.294187,51.955795],"type":"Point"}
}