{
  "type": "Feature",
  "properties": {
    "addr:full":"De Kroonstr 15 Tilburg Noord-Brabant 5048 AP",
    "addr:housenumber":"15",
    "addr:postcode":"5048 ap",
    "iso:country":"NL",
    "sg:address":"De Kroonstr 15",
    "sg:city":"Tilburg",
    "sg:orig_category":"Machinehandel",
    "sg:phone":"+31 13 467 0479",
    "sg:postcode":"5048 AP",
    "sg:province":"Noord-Brabant",
    "wof:name":"Dutch Saws Bv",
    "wof:placetype":"venue"
},
  "geometry": {"coordinates":[5.061687,51.585941],"type":"Point"}
}