{
  "type": "Feature",
  "properties": {
    "addr:full":"C Kieboompln 131 Rotterdam South Holland 3077 MK",
    "addr:housenumber":"131",
    "addr:postcode":"3077",
    "iso:country":"NL",
    "sg:address":"C Kieboompln 131",
    "sg:city":"Rotterdam",
    "sg:classifiers":[
        {
            "category":"Professional",
            "type":"Services"
        }
    ],
    "sg:phone":"+31 10 483 4794",
    "sg:postcode":"3077 MK",
    "sg:province":"South Holland",
    "sg:tags":[
        "leasing"
    ],
    "wof:name":"Cashwheelz",
    "wof:placetype":"venue"
},
  "geometry": {"coordinates":[4.52388,51.896889],"type":"Point"}
}