{
  "type": "Feature",
  "properties": {
    "iso:country":"NL",
    "sg:address":"Berlageln 29",
    "sg:city":"S Gravenhage",
    "sg:orig_category":"Adviesbureaus Bedrijfsorganisatie",
    "sg:phone":"+31 70 391 4183",
    "sg:postcode":"2552 ZN",
    "sg:province":"Zuid-Holland",
    "wof:name":"Traject Informatie Advies",
    "wof:placetype":"venue"
},
  "geometry": {"coordinates":[4.24958,52.053631],"type":"Point"}
}