{
  "type": "Feature",
  "properties": {
    "addr:full":"Karnstr 1 Purmerend Noord-Holland 1445 KT",
    "addr:housenumber":"1",
    "addr:postcode":"1445 kt",
    "addr:street":"Karnstr",
    "iso:country":"NL",
    "sg:address":"Karnstr 1",
    "sg:city":"Purmerend",
    "sg:orig_category":"Adviesbureaus Bedrijfsorganisatie",
    "sg:phone":"+31 299 460 580",
    "sg:postcode":"1445 KT",
    "sg:province":"Noord-Holland",
    "wof:name":"Croes En Partn",
    "wof:placetype":"venue"
},
  "geometry": {"coordinates":[4.9861,52.501194],"type":"Point"}
}