{
  "type": "Feature",
  "properties": {
    "addr:full":"Oude Turfvaartsestr 27 Nispen North Brabant 4709 RN",
    "addr:housenumber":"27",
    "addr:postcode":"4709 rn",
    "addr:street":"Oude Turfvaartsestr",
    "iso:country":"NL",
    "sg:address":"Oude Turfvaartsestr 27",
    "sg:city":"Nispen",
    "sg:classifiers":[
        {
            "category":"Sports & Exercise",
            "subcategory":"Stables",
            "type":"Entertainment"
        }
    ],
    "sg:phone":"+31 165 365 090",
    "sg:postcode":"4709 RN",
    "sg:province":"North Brabant",
    "sg:tags":[
        "maneges"
    ],
    "wof:name":"Borteldonk",
    "wof:placetype":"venue"
},
  "geometry": {"coordinates":[4.473426,51.49432],"type":"Point"}
}