{
  "type": "Feature",
  "properties": {
    "addr:full":"De Wetstein Pfisterlaan 13 Driebergen-Rijsenburg Utrecht 3971 BT",
    "addr:housenumber":"13",
    "addr:postcode":"3971 bt",
    "addr:street":"De Wetstein Pfisterlaan",
    "iso:country":"NL",
    "sg:address":"De Wetstein Pfisterlaan 13",
    "sg:city":"Driebergen-Rijsenburg",
    "sg:orig_category":"Film-, Tv- And Videoproductie",
    "sg:phone":"+31 343 533 301",
    "sg:postcode":"3971 BT",
    "sg:province":"Utrecht",
    "wof:name":"Insignis Produkties",
    "wof:placetype":"venue"
},
  "geometry": {"coordinates":[5.296822,52.059841],"type":"Point"}
}