{
  "type": "Feature",
  "properties": {
    "addr:full":"Looermark 51 Bathmen Overijssel 7437 SK",
    "addr:housenumber":"51",
    "addr:street":"Looermark;7437",
    "iso:country":"NL",
    "sg:address":"Looermark 51",
    "sg:city":"Bathmen",
    "sg:orig_category":"Onroerende Goederen",
    "sg:phone":"+31 570 543 834",
    "sg:postcode":"7437 SK",
    "sg:province":"Overijssel",
    "wof:name":"Loohuis Bathmen Bv",
    "wof:placetype":"venue"
},
  "geometry": {"coordinates":[6.338425,52.252998],"type":"Point"}
}