{
  "type": "Feature",
  "properties": {
    "addr:full":"Lorentzplein 33 Badhoevedorp Noord-Holland 1171 BB",
    "addr:housenumber":"33",
    "addr:postcode":"1171 bb",
    "addr:street":"Lorentzplein",
    "iso:country":"NL",
    "sg:address":"Lorentzplein 33",
    "sg:city":"Badhoevedorp",
    "sg:orig_category":"Kappers",
    "sg:phone":"+31 20 659 5821",
    "sg:postcode":"1171 BB",
    "sg:province":"Noord-Holland",
    "wof:name":"Coiffeur Int",
    "wof:placetype":"venue"
},
  "geometry": {"coordinates":[4.7781581879,52.3395652771],"type":"Point"}
}