{
  "type": "Feature",
  "properties": {
    "iso:country":"NL",
    "sg:address":"Veerdam 9",
    "sg:city":"Aalst Gld",
    "sg:orig_category":"Houtgroothandel",
    "sg:phone":"+31 418 677 090",
    "sg:postcode":"5308 JH",
    "sg:province":"Gelderland",
    "wof:name":"Timmerman",
    "wof:placetype":"venue"
},
  "geometry": {"coordinates":[5.117451,51.782001],"type":"Point"}
}