{
  "type": "Feature",
  "properties": {
    "addr:full":"Eerste Oosterparkstraat 137 Amsterdam North Holland 1091 GZ",
    "addr:housenumber":"137",
    "addr:postcode":"1091 gz",
    "addr:street":"Eerste Oosterparkstraat",
    "iso:country":"NL",
    "sg:address":"Eerste Oosterparkstraat 137",
    "sg:city":"Amsterdam",
    "sg:orig_category":"Verlichting And Huishoudartikelen",
    "sg:phone":"+31 20 694 8674",
    "sg:postcode":"1091 GZ",
    "sg:province":"North Holland",
    "wof:name":"Firma Lichtbron Oost",
    "wof:placetype":"venue"
},
  "geometry": {"coordinates":[4.911786,52.356743],"type":"Point"}
}