{
  "type": "Feature",
  "properties": {
    "iso:country":"NL",
    "sg:address":"Remkettingwg 2",
    "sg:city":"Echteld",
    "sg:orig_category":"Adviesbureaus",
    "sg:phone":"+31 344 612 437",
    "sg:postcode":"4054 MH",
    "sg:province":"Gelderland",
    "wof:name":"Etd Poland Bv",
    "wof:placetype":"venue"
},
  "geometry": {"coordinates":[5.474259,51.901917],"type":"Point"}
}