{
  "type": "Feature",
  "properties": {
    "addr:full":"Dorpsstraat 55 Aarle Rixtel North Brabant 5735 EB",
    "addr:housenumber":"55",
    "addr:postcode":"5735 eb",
    "addr:street":"Dorpsstraat",
    "iso:country":"NL",
    "sg:address":"Dorpsstraat 55",
    "sg:city":"Aarle Rixtel",
    "sg:classifiers":[
        {
            "category":"Fast Food",
            "type":"Food & Drink"
        }
    ],
    "sg:phone":"+31 492 383 782",
    "sg:postcode":"5735 EB",
    "sg:province":"North Brabant",
    "sg:tags":[
        "afhaal",
        "restaurant"
    ],
    "wof:name":"Shoarma Pizzeria Alanya",
    "wof:placetype":"venue"
},
  "geometry": {"coordinates":[5.643246,51.51104],"type":"Point"}
}