{
  "type": "Feature",
  "properties": {
    "addr:full":"Meindert Van Der Thijnensingel 10 B Coevorden Drenthe 7741 GB",
    "addr:housenumber":"10 b",
    "addr:postcode":"7741 gb",
    "addr:street":"Meindert Van Der Thijnensingel",
    "iso:country":"NL",
    "sg:address":"Meindert Van Der Thijnensingel 10 B",
    "sg:city":"Coevorden",
    "sg:orig_category":"Public Relationbureaus",
    "sg:phone":"+31 524 534 094",
    "sg:postcode":"7741 GB",
    "sg:province":"Drenthe",
    "wof:name":"Verhoef Communicatie",
    "wof:placetype":"venue"
},
  "geometry": {"coordinates":[6.742753,52.662872],"type":"Point"}
}