{
  "type": "Feature",
  "properties": {
    "addr:full":"Hamarplein 2 Belfeld Limburg 5951 CD",
    "addr:housenumber":"2",
    "addr:postcode":"5951 cd",
    "addr:street":"Hamarplein",
    "iso:country":"NL",
    "sg:address":"Hamarplein 2",
    "sg:city":"Belfeld",
    "sg:orig_category":"Overheidsdiensten",
    "sg:phone":"+31 77 475 1960",
    "sg:postcode":"5951 CD",
    "sg:province":"Limburg",
    "wof:name":"Stichting De Hamar",
    "wof:placetype":"venue"
},
  "geometry": {"coordinates":[6.114771843,51.3105010986],"type":"Point"}
}