{
  "type": "Feature",
  "properties": {
    "addr:full":"Industrieweg 42 Swifterbant Flevoland 8255 PB",
    "addr:housenumber":"42",
    "addr:postcode":"8255 pb",
    "addr:street":"Industrieweg;Flevoland",
    "iso:country":"NL",
    "sg:address":"Industrieweg 42",
    "sg:city":"Swifterbant",
    "sg:orig_category":"Metaalwerken",
    "sg:phone":"+31 321 321 786",
    "sg:postcode":"8255 PB",
    "sg:province":"Flevoland",
    "wof:name":"Aluminium Industrie Swifterbant",
    "wof:placetype":"venue"
},
  "geometry": {"coordinates":[5.65047,52.565231],"type":"Point"}
}