{
  "type": "Feature",
  "properties": {
    "iso:country":"NL",
    "sg:address":"Hoogveld 25",
    "sg:city":"Heyen",
    "sg:orig_category":"Verpleegartikelen",
    "sg:phone":"+31 485 497 200",
    "sg:postcode":"6598 BL",
    "sg:province":"Limburg",
    "wof:name":"Sca",
    "wof:placetype":"venue"
},
  "geometry": {"coordinates":[5.97571,51.676868],"type":"Point"}
}