{
  "type": "Feature",
  "properties": {
    "addr:full":"Hoge Wal 1 Tilburg Noord-Brabant 5022 KH",
    "addr:housenumber":"1",
    "addr:postcode":"5022 kh",
    "addr:street":"Hoge Wal",
    "iso:country":"NL",
    "sg:address":"Hoge Wal 1",
    "sg:city":"Tilburg",
    "sg:classifiers":[
        {
            "category":"Retail",
            "subcategory":"Auto Repair",
            "type":"Services"
        }
    ],
    "sg:phone":"+31 13 543 0935",
    "sg:postcode":"5022 KH",
    "sg:province":"Noord-Brabant",
    "sg:tags":[
        "garage"
    ],
    "wof:name":"Brouwer, Jac De",
    "wof:placetype":"venue"
},
  "geometry": {"coordinates":[5.083598,51.531494],"type":"Point"}
}