{
  "type": "Feature",
  "properties": {
    "addr:full":"Laan Van Meerdervoort 7F 'S Gravenhage Zuid-Holland 2517 AB",
    "addr:housenumber":"7f '",
    "addr:postcode":"2517 ab",
    "addr:street":"Laan Van Meerdervoort",
    "iso:country":"NL",
    "sg:address":"Laan Van Meerdervoort 7F",
    "sg:city":"'S Gravenhage",
    "sg:orig_category":"Musea And Historische Gebouwen",
    "sg:phone":"+31 70 362 1434",
    "sg:postcode":"2517 AB",
    "sg:province":"Zuid-Holland",
    "wof:name":"Museum Mesdag",
    "wof:placetype":"venue"
},
  "geometry": {"coordinates":[4.291452,52.08353],"type":"Point"}
}