{
  "type": "Feature",
  "properties": {
    "addr:full":"Strawinskypad 74 Leiden South Holland 2324 DA",
    "addr:housenumber":"74",
    "addr:postcode":"2324 da",
    "addr:street":"Strawinskypad",
    "iso:country":"NL",
    "sg:address":"Strawinskypad 74",
    "sg:city":"Leiden",
    "sg:orig_category":"Webdesign Bureaus",
    "sg:phone":"+31 71 523 2929",
    "sg:postcode":"2324 DA",
    "sg:province":"South Holland",
    "wof:name":"Roncreations",
    "wof:placetype":"venue"
},
  "geometry": {"coordinates":[4.4676351547,52.140083313],"type":"Point"}
}