{
  "type": "Feature",
  "properties": {
    "addr:full":"Kl Kerkstr 3 Leeuwarden Friesland 8911 DK",
    "addr:housenumber":"3",
    "addr:postcode":"8911 dk",
    "iso:country":"NL",
    "sg:address":"Kl Kerkstr 3",
    "sg:city":"Leeuwarden",
    "sg:orig_category":"Broodjeszaken",
    "sg:phone":"+31 58 216 9747",
    "sg:postcode":"8911 DK",
    "sg:province":"Friesland",
    "wof:name":"Broadtsje Bakker, De",
    "wof:placetype":"venue"
},
  "geometry": {"coordinates":[5.791482,53.201736],"type":"Point"}
}