{
  "type": "Feature",
  "properties": {
    "addr:full":"Haarsteegsestr 42 Haarsteeg North Brabant 5254 JS",
    "addr:housenumber":"42",
    "addr:postcode":"5254 js",
    "addr:street":"Haarsteegsestr",
    "iso:country":"NL",
    "sg:address":"Haarsteegsestr 42",
    "sg:city":"Haarsteeg",
    "sg:orig_category":"Fietsen En Bromfietsen",
    "sg:phone":"+31 73 511 6201",
    "sg:postcode":"5254 JS",
    "sg:province":"North Brabant",
    "wof:name":"Bart Van Ooyen, Bart Van",
    "wof:placetype":"venue"
},
  "geometry": {"coordinates":[5.194815,51.709614],"type":"Point"}
}