{
  "type": "Feature",
  "properties": {
    "iso:country":"NL",
    "sg:address":"Nijverdalsestraat 97",
    "sg:city":"Wierden",
    "sg:orig_category":"Kappers",
    "sg:phone":"+31 546 571 644",
    "sg:postcode":"7642 AC",
    "sg:province":"NL.08",
    "wof:name":"Salon Jose",
    "wof:placetype":"venue"
},
  "geometry": {"coordinates":[6.579882,52.360142],"type":"Point"}
}