{
  "type": "Feature",
  "properties": {
    "iso:country":"NL",
    "sg:address":"P V M Geld Blauw 5",
    "sg:city":"Heteren",
    "sg:orig_category":"Autorijscholen",
    "sg:phone":"+31 26 472 2563",
    "sg:postcode":"6666 LR",
    "sg:province":"Gelderland",
    "wof:name":"Timmer, G J",
    "wof:placetype":"venue"
},
  "geometry": {"coordinates":[5.75695,51.958275],"type":"Point"}
}