{
  "type": "Feature",
  "properties": {
    "iso:country":"NL",
    "sg:address":"Kerkbrink 29",
    "sg:city":"Hilversum",
    "sg:orig_category":"Fietsen En Bromfietsen Stalling",
    "sg:phone":"+31 35 628 9291",
    "sg:postcode":"1211 BW",
    "sg:province":"Noord-Holland",
    "wof:name":"Tomingroep Bv",
    "wof:placetype":"venue"
},
  "geometry": {"coordinates":[5.1695,52.228565],"type":"Point"}
}