{
  "type": "Feature",
  "properties": {
    "iso:country":"NL",
    "sg:address":"Boterdiep 28",
    "sg:city":"Rotterdam",
    "sg:orig_category":"Bouwmaterialen Gh",
    "sg:phone":"+31 10 482 5353",
    "sg:postcode":"3077 AW",
    "sg:province":"Zuid-Holland",
    "wof:name":"Bouwmaat Rotterdam Zuid",
    "wof:placetype":"venue"
},
  "geometry": {"coordinates":[4.528655,51.896282],"type":"Point"}
}