{
  "type": "Feature",
  "properties": {
    "addr:full":"Postbus 51 Krabbendyke Zeeland 4413 ZH",
    "addr:housenumber":"51",
    "addr:postcode":"4413",
    "addr:street":"Postbus;Zeeland",
    "iso:country":"NL",
    "sg:address":"Postbus 51",
    "sg:city":"Krabbendyke",
    "sg:orig_category":"Artsen - Huisartsen",
    "sg:phone":"+31 113 501 444",
    "sg:postcode":"4413 ZH",
    "sg:province":"Zeeland",
    "wof:name":"Balans",
    "wof:placetype":"venue"
},
  "geometry": {"coordinates":[4.113008,51.430157],"type":"Point"}
}