{
  "type": "Feature",
  "properties": {
    "addr:full":"Vondelstr 98 Amsterdam North Holland 1054 GP",
    "addr:housenumber":"98",
    "addr:postcode":"1054 gp",
    "addr:street":"Vondelstr",
    "iso:country":"NL",
    "sg:address":"Vondelstr 98",
    "sg:city":"Amsterdam",
    "sg:orig_category":"Bedrijfsopleidingen",
    "sg:phone":"+31 20 618 8348",
    "sg:postcode":"1054 GP",
    "sg:province":"North Holland",
    "sg:website":"http://www.mediawise.nl",
    "wof:name":"Media Wise",
    "wof:placetype":"venue"
},
  "geometry": {"coordinates":[4.874428,52.361633],"type":"Point"}
}