{
  "type": "Feature",
  "properties": {
    "addr:full":"Havenstraat 24 Erica Provincie Drenthe 7887 BP",
    "addr:housenumber":"24",
    "addr:postcode":"7887 bp",
    "addr:street":"Havenstraat;Provincie Drenthe",
    "iso:country":"NL",
    "sg:address":"Havenstraat 24",
    "sg:city":"Erica",
    "sg:orig_category":"Bibliotheken And Openbare Archieven",
    "sg:phone":"+31 591 301 340",
    "sg:postcode":"7887 BP",
    "sg:province":"Provincie Drenthe",
    "wof:name":"Bibliotheek",
    "wof:placetype":"venue"
},
  "geometry": {"coordinates":[6.926005,52.711594],"type":"Point"}
}