{
  "type": "Feature",
  "properties": {
    "iso:country":"NL",
    "sg:address":"Gedempte Singel 23",
    "sg:city":"Assen",
    "sg:orig_category":"Schoenen",
    "sg:phone":"+31 592 300 243",
    "sg:postcode":"9401 JN",
    "sg:province":"Provincie Drenthe",
    "wof:name":"Dolcis",
    "wof:placetype":"venue"
},
  "geometry": {"coordinates":[6.561693,52.995071],"type":"Point"}
}