{
  "type": "Feature",
  "properties": {
    "addr:full":"Meester Iman Caustraat 17 Stellendam Zuid-Holland 3251 AP",
    "addr:housenumber":"17",
    "addr:postcode":"3251 ap",
    "addr:street":"Meester Iman Caustraat",
    "iso:country":"NL",
    "sg:address":"Meester Iman Caustraat 17",
    "sg:city":"Stellendam",
    "sg:orig_category":"Makelaars In Onroerend Goed",
    "sg:phone":"+31 187 492 384",
    "sg:postcode":"3251 AP",
    "sg:province":"Zuid-Holland",
    "wof:name":"Van Veen Onroerend Goed Bemiddeling",
    "wof:placetype":"venue"
},
  "geometry": {"coordinates":[4.028856,51.804214],"type":"Point"}
}