{
  "type": "Feature",
  "properties": {
    "addr:full":"Markt 43 Etten Leur Noord-Brabant 4875 CC",
    "addr:housenumber":"43",
    "addr:postcode":"4875 cc",
    "addr:street":"Markt",
    "iso:country":"NL",
    "sg:address":"Markt 43",
    "sg:city":"Etten Leur",
    "sg:orig_category":"Wereldwinkels",
    "sg:phone":"+31 76 501 4631",
    "sg:postcode":"4875 CC",
    "sg:province":"Noord-Brabant",
    "wof:name":"Wereldwinkel",
    "wof:placetype":"venue"
},
  "geometry": {"coordinates":[4.6344599724,51.5709915161],"type":"Point"}
}