{
  "type": "Feature",
  "properties": {
    "addr:full":"Philipsln 84 Roosendaal Noord-Brabant 4702 NS",
    "addr:housenumber":"84",
    "addr:postcode":"4702 ns",
    "addr:street":"Philipsln",
    "iso:country":"NL",
    "sg:address":"Philipsln 84",
    "sg:city":"Roosendaal",
    "sg:orig_category":"Artsen - Huisartsen",
    "sg:phone":"+31 165 561 916",
    "sg:postcode":"4702 NS",
    "sg:province":"Noord-Brabant",
    "wof:name":"Buijsen, C J A P",
    "wof:placetype":"venue"
},
  "geometry": {"coordinates":[4.45767,51.531403],"type":"Point"}
}