{
  "type": "Feature",
  "properties": {
    "addr:full":"Leliestr 4 Hoogeveen Provincie Drenthe 7906 PC",
    "addr:housenumber":"4",
    "addr:postcode":"7906 pc",
    "addr:street":"Leliestr;Provincie",
    "iso:country":"NL",
    "sg:address":"Leliestr 4",
    "sg:city":"Hoogeveen",
    "sg:orig_category":"Tehuizen",
    "sg:phone":"+31 528 230 794",
    "sg:postcode":"7906 PC",
    "sg:province":"Provincie Drenthe",
    "wof:name":"Philadelphia",
    "wof:placetype":"venue"
},
  "geometry": {"coordinates":[6.486388,52.716408],"type":"Point"}
}