{
  "type": "Feature",
  "properties": {
    "addr:full":"Becanusstr 15 Maastricht Limburg 6216 BX",
    "addr:housenumber":"15",
    "addr:postcode":"6216 bx",
    "addr:street":"Becanusstr",
    "iso:country":"NL",
    "sg:address":"Becanusstr 15",
    "sg:city":"Maastricht",
    "sg:orig_category":"Huidtherapeuten",
    "sg:phone":"+31 43 347 6598",
    "sg:postcode":"6216 BX",
    "sg:province":"Limburg",
    "wof:name":"Beers, Vera Van",
    "wof:placetype":"venue"
},
  "geometry": {"coordinates":[5.66971,50.849476],"type":"Point"}
}