{
  "type": "Feature",
  "properties": {
    "addr:full":"Ruurlosewg 80A Hengelo Gld Gelderland 7255 MA",
    "addr:housenumber":"80a",
    "addr:postcode":"7255 ma",
    "addr:street":"Ruurlosewg",
    "iso:country":"NL",
    "sg:address":"Ruurlosewg 80A",
    "sg:city":"Hengelo Gld",
    "sg:orig_category":"Metaalbewerking",
    "sg:phone":"+31 575 468 211",
    "sg:postcode":"7255 MA",
    "sg:province":"Gelderland",
    "wof:name":"Goma Bv",
    "wof:placetype":"venue"
},
  "geometry": {"coordinates":[6.343277,52.060085],"type":"Point"}
}