{
  "type": "Feature",
  "properties": {
    "addr:full":"Nieuwe Tiendweg 11F Krimpen A/D Ijssel Zuid-Holland 2922 EN",
    "addr:housenumber":"11f;a / d",
    "addr:postcode":"2922 en",
    "addr:street":"Nieuwe Tiendweg",
    "iso:country":"NL",
    "sg:address":"Nieuwe Tiendweg 11F",
    "sg:city":"Krimpen A/D Ijssel",
    "sg:orig_category":"Werving And Selectie Van Tijdelijk Personeel And Uitzendkantoren",
    "sg:phone":"+31 180 518 544",
    "sg:postcode":"2922 EN",
    "sg:province":"Zuid-Holland",
    "wof:name":"Randstad",
    "wof:placetype":"venue"
},
  "geometry": {"coordinates":[4.5871520042,51.9144515991],"type":"Point"}
}