{
  "type": "Feature",
  "properties": {
    "addr:full":"Langelaar 34 Teteringen Noord-Brabant 4847 EM",
    "addr:housenumber":"34",
    "addr:postcode":"4847 em",
    "addr:street":"Langelaar",
    "iso:country":"NL",
    "sg:address":"Langelaar 34",
    "sg:city":"Teteringen",
    "sg:orig_category":"Adviesbureaus Bedrijfsorganisatie",
    "sg:phone":"+31 76 587 7475",
    "sg:postcode":"4847 EM",
    "sg:province":"Noord-Brabant",
    "wof:name":"Bos Bv, J J",
    "wof:placetype":"venue"
},
  "geometry": {"coordinates":[4.823036,51.608086],"type":"Point"}
}