{
  "type": "Feature",
  "properties": {
    "addr:full":"Homoet 24 Veenendaal Utrecht 3905 WN",
    "addr:housenumber":"24",
    "addr:postcode":"3905 wn",
    "addr:street":"Homoet",
    "iso:country":"NL",
    "sg:address":"Homoet 24",
    "sg:city":"Veenendaal",
    "sg:orig_category":"Autorijscholen",
    "sg:phone":"+31 318 511 273",
    "sg:postcode":"3905 WN",
    "sg:province":"Utrecht",
    "wof:name":"Eck, Frans Van",
    "wof:placetype":"venue"
},
  "geometry": {"coordinates":[5.537646,52.031746],"type":"Point"}
}