{
  "type": "Feature",
  "properties": {
    "iso:country":"NL",
    "sg:address":"Persoonshaven 181",
    "sg:city":"Rotterdam",
    "sg:orig_category":"Loodgieterswerk, Verwarming And Sanitaire Installaties",
    "sg:phone":"+31 10 215 1511",
    "sg:postcode":"3071 CJ",
    "sg:province":"South Holland",
    "wof:name":"J.S. Landveld",
    "wof:placetype":"venue"
},
  "geometry": {"coordinates":[4.511589,51.905193],"type":"Point"}
}