{
  "type": "Feature",
  "properties": {
    "addr:full":"Donkerstraat 17 Ravenswaaij Gelderland 4119 LX",
    "addr:housenumber":"17",
    "addr:postcode":"4119 lx",
    "addr:street":"Donkerstraat;Gelderland",
    "iso:country":"NL",
    "sg:address":"Donkerstraat 17",
    "sg:city":"Ravenswaaij",
    "sg:orig_category":"Goederenvervoer Over De Weg",
    "sg:phone":"+31 345 501 219",
    "sg:postcode":"4119 LX",
    "sg:province":"Gelderland",
    "wof:name":"Transportbedrijf A.C. Baauw En Zoon Bv",
    "wof:placetype":"venue"
},
  "geometry": {"coordinates":[5.314478,51.944427],"type":"Point"}
}