{
  "type": "Feature",
  "properties": {
    "addr:full":"Kortewykstr 81 Hoogeveen Drenthe 7906 BS",
    "addr:housenumber":"81",
    "addr:postcode":"7906 bs",
    "addr:street":"Kortewykstr",
    "iso:country":"NL",
    "sg:address":"Kortewykstr 81",
    "sg:city":"Hoogeveen",
    "sg:orig_category":"Woningbouw- Verenigingen En -Stichtingen",
    "sg:phone":"+31 528 229 800",
    "sg:postcode":"7906 BS",
    "sg:province":"Drenthe",
    "wof:name":"Domesta Woonstichting",
    "wof:placetype":"venue"
},
  "geometry": {"coordinates":[6.4788818359,52.7187004089],"type":"Point"}
}