{
  "type": "Feature",
  "properties": {
    "addr:full":"Donkse Dreef 20B S Hertogenbosch North Brabant 5233 HE",
    "addr:housenumber":"20b",
    "addr:postcode":"5233 he",
    "addr:street":"Donkse Dreef;S Hertogenbosch",
    "iso:country":"NL",
    "sg:address":"Donkse Dreef 20B",
    "sg:city":"S Hertogenbosch",
    "sg:orig_category":"Peuterspeelzalen",
    "sg:phone":"+31 73 642 4841",
    "sg:postcode":"5233 HE",
    "sg:province":"North Brabant",
    "wof:name":"Darteldonk, De",
    "wof:placetype":"venue"
},
  "geometry": {"coordinates":[5.322803,51.716824],"type":"Point"}
}