{
  "type": "Feature",
  "properties": {
    "addr:full":"Steegjesdk 6 Piershil Zuid-Holland 3265 AE",
    "addr:housenumber":"6",
    "addr:postcode":"3265 ae",
    "addr:street":"Steegjesdk",
    "iso:country":"NL",
    "sg:address":"Steegjesdk 6",
    "sg:city":"Piershil",
    "sg:orig_category":"Waterbehandeling En Waterzuiverings- Systemen",
    "sg:phone":"+31 186 691 022",
    "sg:postcode":"3265 AE",
    "sg:province":"Zuid-Holland",
    "wof:name":"Bosman Bv",
    "wof:placetype":"venue"
},
  "geometry": {"coordinates":[4.313065052,51.7911491394],"type":"Point"}
}