{
  "type": "Feature",
  "properties": {
    "iso:country":"NL",
    "sg:address":"Hoogstr 72A",
    "sg:city":"Nieuwpoort",
    "sg:orig_category":"Onroerende Goederen",
    "sg:phone":"+31 184 602 963",
    "sg:postcode":"2965 AM",
    "sg:province":"Zuid-Holland",
    "wof:name":"Jg Bv",
    "wof:placetype":"venue"
},
  "geometry": {"coordinates":[4.866164,51.935242],"type":"Point"}
}