{
  "type": "Feature",
  "properties": {
    "addr:full":"Charlottestraat 5 Wassenaar Zuid-Holland 2245 VW",
    "addr:housenumber":"5",
    "addr:postcode":"2245 vw",
    "addr:street":"Charlottestraat",
    "iso:country":"NL",
    "sg:address":"Charlottestraat 5",
    "sg:city":"Wassenaar",
    "sg:orig_category":"Overheidsdiensten",
    "sg:phone":"+31 70 517 9093",
    "sg:postcode":"2245 VW",
    "sg:province":"Zuid-Holland",
    "wof:name":"Kerkehout",
    "wof:placetype":"venue"
},
  "geometry": {"coordinates":[4.3733382225,52.1096000671],"type":"Point"}
}