{
  "type": "Feature",
  "properties": {
    "addr:full":"Pres Kennedyln 15 Amsterdam Noord-Holland 1079 MC",
    "addr:housenumber":"15;1079",
    "addr:postcode":"mc",
    "iso:country":"NL",
    "sg:address":"Pres Kennedyln 15",
    "sg:city":"Amsterdam",
    "sg:orig_category":"Kappers",
    "sg:phone":"+31 20 642 6297",
    "sg:postcode":"1079 MC",
    "sg:province":"Noord-Holland",
    "wof:name":"Tromp",
    "wof:placetype":"venue"
},
  "geometry": {"coordinates":[4.89319,52.373119],"type":"Point"}
}