{
  "type": "Feature",
  "properties": {
    "iso:country":"NL",
    "sg:address":"Rykswg 114",
    "sg:city":"Velden",
    "sg:orig_category":"Postkantoren",
    "sg:phone":"+31 77 472 1261",
    "sg:postcode":"5941 AH",
    "sg:province":"Limburg",
    "sg:website":"http://www.postkantoor.nl",
    "wof:name":"Postkantoor",
    "wof:placetype":"venue"
},
  "geometry": {"coordinates":[6.165295,51.413952],"type":"Point"}
}