{
  "type": "Feature",
  "properties": {
    "addr:full":"Boswg 87 Geleen Limburg 6163 AN",
    "addr:housenumber":"87",
    "addr:postcode":"6163 an",
    "addr:street":"Boswg",
    "iso:country":"NL",
    "sg:address":"Boswg 87",
    "sg:city":"Geleen",
    "sg:orig_category":"Schilders",
    "sg:phone":"+31 46 474 2622",
    "sg:postcode":"6163 AN",
    "sg:province":"Limburg",
    "wof:name":"Cabo",
    "wof:placetype":"venue"
},
  "geometry": {"coordinates":[5.815094,50.989227],"type":"Point"}
}