{
  "type": "Feature",
  "properties": {
    "addr:full":"Thorbeckeln 6 Velsen Zuid Noord-Holland 1981 CJ",
    "addr:housenumber":"6",
    "addr:postcode":"1981 cj",
    "addr:street":"Thorbeckeln;Velsen",
    "iso:country":"NL",
    "sg:address":"Thorbeckeln 6",
    "sg:city":"Velsen Zuid",
    "sg:orig_category":"Adviesbureaus Bedrijfsorganisatie",
    "sg:phone":"+31 255 540 354",
    "sg:postcode":"1981 CJ",
    "sg:province":"Noord-Holland",
    "wof:name":"Zwan, Van Der",
    "wof:placetype":"venue"
},
  "geometry": {"coordinates":[4.649327,52.45961],"type":"Point"}
}