{
  "type": "Feature",
  "properties": {
    "addr:full":"Westerdorpsstr 68 Hoevelaken Gelderland 3871 AZ",
    "addr:housenumber":"68",
    "addr:postcode":"3871",
    "addr:street":"Westerdorpsstr;Gelderland",
    "iso:country":"NL",
    "sg:address":"Westerdorpsstr 68",
    "sg:city":"Hoevelaken",
    "sg:orig_category":"Projectontwikkeling",
    "sg:phone":"+31 33 253 9535",
    "sg:postcode":"3871 AZ",
    "sg:province":"Gelderland",
    "sg:website":"http://www.boei.nl",
    "wof:name":"Boei Bv",
    "wof:placetype":"venue"
},
  "geometry": {"coordinates":[5.457737,52.175831],"type":"Point"}
}