{
  "type": "Feature",
  "properties": {
    "addr:full":"Annevillelaan 75 Ulvenhout North Brabant 4851 CB",
    "addr:housenumber":"75",
    "addr:postcode":"4851 cb",
    "addr:street":"Annevillelaan",
    "iso:country":"NL",
    "sg:address":"Annevillelaan 75",
    "sg:city":"Ulvenhout",
    "sg:orig_category":"Bloemen And Planten",
    "sg:phone":"+31 76 565 9912",
    "sg:postcode":"4851 CB",
    "sg:province":"North Brabant",
    "wof:name":"Bloemleven",
    "wof:placetype":"venue"
},
  "geometry": {"coordinates":[4.80792,51.547169],"type":"Point"}
}