{
  "type": "Feature",
  "properties": {
    "addr:full":"Westhavenkd 86 Vlaardingen South Holland 3133 AV",
    "addr:housenumber":"86",
    "addr:postcode":"3133 av",
    "addr:street":"Westhavenkd",
    "iso:country":"NL",
    "sg:address":"Westhavenkd 86",
    "sg:city":"Vlaardingen",
    "sg:orig_category":"On- Offshore",
    "sg:phone":"+31 10 204 1166",
    "sg:postcode":"3133 AV",
    "sg:province":"South Holland",
    "sg:website":"http://www.macartney.com",
    "wof:name":"Macartney Benelux Bv",
    "wof:placetype":"venue"
},
  "geometry": {"coordinates":[4.346938,51.902294],"type":"Point"}
}