{
  "type": "Feature",
  "properties": {
    "iso:country":"NL",
    "sg:address":"Droevendaalsestg 1",
    "sg:city":"Wageningen",
    "sg:orig_category":"Onderzoekbureaus",
    "sg:phone":"+31 317 477 001",
    "sg:postcode":"6708 PB",
    "sg:province":"Gelderland",
    "sg:website":"http://www.plant.wageningen-ur.nl",
    "wof:name":"Plant Research International",
    "wof:placetype":"venue"
},
  "geometry": {"coordinates":[5.662865,51.98629],"type":"Point"}
}