{
  "type": "Feature",
  "properties": {
    "addr:full":"Mariastraat 154 Schiedam Zuid-Holland 3117 NS",
    "addr:housenumber":"154",
    "addr:postcode":"3117 ns",
    "addr:street":"Mariastraat",
    "iso:country":"NL",
    "sg:address":"Mariastraat 154",
    "sg:city":"Schiedam",
    "sg:orig_category":"Metaalwerken",
    "sg:phone":"+31 10 426 5220",
    "sg:postcode":"3117 NS",
    "sg:province":"Zuid-Holland",
    "wof:name":"Peter Stierman & Zn. Plafondsystemen",
    "wof:placetype":"venue"
},
  "geometry": {"coordinates":[4.390592,51.914722],"type":"Point"}
}