{
  "type": "Feature",
  "properties": {
    "addr:full":"Beekstr 70 Panningen Limburg 5981 NV",
    "addr:housenumber":"70",
    "addr:postcode":"5981 nv",
    "addr:street":"Beekstr",
    "iso:country":"NL",
    "sg:address":"Beekstr 70",
    "sg:city":"Panningen",
    "sg:classifiers":[
        {
            "category":"Food & Beverages",
            "subcategory":"Fruits & Vegetables",
            "type":"Retail Goods"
        }
    ],
    "sg:phone":"+31 77 307 5756",
    "sg:postcode":"5981 NV",
    "sg:province":"Limburg",
    "sg:tags":[
        "en",
        "groenten"
    ],
    "wof:name":"Kessels-Joosten Mts",
    "wof:placetype":"venue"
},
  "geometry": {"coordinates":[5.983877,51.328011],"type":"Point"}
}