{
  "type": "Feature",
  "properties": {
    "addr:full":"Hasseltstr 242 Tilburg North Brabant 5046 LR",
    "addr:housenumber":"242",
    "addr:postcode":"5046 lr",
    "iso:country":"NL",
    "sg:address":"Hasseltstr 242",
    "sg:city":"Tilburg",
    "sg:orig_category":"Meubelen",
    "sg:phone":"+31 13 542 2838",
    "sg:postcode":"5046 LR",
    "sg:province":"North Brabant",
    "wof:name":"Boeren Hasseltstraat Vof, Stijlmeubelen",
    "wof:placetype":"venue"
},
  "geometry": {"coordinates":[5.074147,51.569534],"type":"Point"}
}