{
  "type": "Feature",
  "properties": {
    "addr:full":"Gutenbergweg 8 Culemborg Gelderland 4104 BA",
    "addr:housenumber":"8",
    "addr:postcode":"4104 ba",
    "addr:street":"Gutenbergweg;Gelderland",
    "iso:country":"NL",
    "sg:address":"Gutenbergweg 8",
    "sg:city":"Culemborg",
    "sg:orig_category":"Meubels And Huishoudapparatuur Gh",
    "sg:phone":"+31 345 530 690",
    "sg:postcode":"4104 BA",
    "sg:province":"Gelderland",
    "wof:name":"Meubeltoonzalen Meublo Bv",
    "wof:placetype":"venue"
},
  "geometry": {"coordinates":[5.205811,51.941795],"type":"Point"}
}