{
  "type": "Feature",
  "properties": {
    "addr:full":"Dorpsstraat 39 Castricum Noord-Holland 1901 EJ",
    "addr:housenumber":"39",
    "addr:postcode":"1901 ej",
    "addr:street":"Dorpsstraat",
    "iso:country":"NL",
    "sg:address":"Dorpsstraat 39",
    "sg:city":"Castricum",
    "sg:orig_category":"Makelaars In Onroerend Goed",
    "sg:phone":"+31 251 657 700",
    "sg:postcode":"1901 EJ",
    "sg:province":"Noord-Holland",
    "wof:name":"Hopman Era Makelaars",
    "wof:placetype":"venue"
},
  "geometry": {"coordinates":[4.662616,52.546471],"type":"Point"}
}