{
  "type": "Feature",
  "properties": {
    "addr:full":"Charlotte Van Pallandtln 19 Castricum Noord-Holland 1902 MR",
    "addr:housenumber":"19",
    "addr:postcode":"1902 mr",
    "addr:street":"Charlotte Van Pallandtln",
    "iso:country":"NL",
    "sg:address":"Charlotte Van Pallandtln 19",
    "sg:city":"Castricum",
    "sg:orig_category":"Werving And Selectie Van Vast Personeel",
    "sg:phone":"+31 6 24210516",
    "sg:postcode":"1902 MR",
    "sg:province":"Noord-Holland",
    "wof:name":"De Arbeidsdesk Bv",
    "wof:placetype":"venue"
},
  "geometry": {"coordinates":[4.689745903,52.5481071472],"type":"Point"}
}