{
  "type": "Feature",
  "properties": {
    "iso:country":"NL",
    "sg:address":"Marius Bauerstraat 399",
    "sg:city":"Amsterdam",
    "sg:orig_category":"Verlichting And Huishoudartikelen",
    "sg:phone":"+31 20 617 0835",
    "sg:postcode":"1062 AP",
    "sg:province":"Noord-Holland",
    "wof:name":"Unitex Bv",
    "wof:placetype":"venue"
},
  "geometry": {"coordinates":[4.832951,52.36253],"type":"Point"}
}