{
  "type": "Feature",
  "properties": {
    "addr:full":"Hunzewg 1 Hoorn Nh Noord-Holland 1628 JJ",
    "addr:housenumber":"1",
    "addr:postcode":"1628 jj",
    "addr:street":"Hunzewg",
    "iso:country":"NL",
    "sg:address":"Hunzewg 1",
    "sg:city":"Hoorn Nh",
    "sg:orig_category":"Peuterspeelzalen",
    "sg:phone":"+31 229 247 576",
    "sg:postcode":"1628 JJ",
    "sg:province":"Noord-Holland",
    "wof:name":"Zonnelicht, Sticht",
    "wof:placetype":"venue"
},
  "geometry": {"coordinates":[5.080266,52.650101],"type":"Point"}
}