{
  "type": "Feature",
  "properties": {
    "iso:country":"NL",
    "sg:address":"Hunzewg 1",
    "sg:city":"Hoorn Nh",
    "sg:orig_category":"Peuterspeelzalen",
    "sg:phone":"+31 229 247 576",
    "sg:postcode":"1628 JJ",
    "sg:province":"Noord-Holland",
    "wof:name":"Zonnelicht, Sticht",
    "wof:placetype":"venue"
},
  "geometry": {"coordinates":[5.080266,52.650101],"type":"Point"}
}