{
  "type": "Feature",
  "properties": {
    "iso:country":"NL",
    "sg:address":"Graafsebaan 61E",
    "sg:city":"Rosmalen",
    "sg:orig_category":"Adviesbureaus Bouwkosten",
    "sg:phone":"+31 73 523 0570",
    "sg:postcode":"5248 JT",
    "sg:province":"North Brabant",
    "wof:name":"Leeuwen Bv, Van",
    "wof:placetype":"venue"
},
  "geometry": {"coordinates":[5.359786,51.702747],"type":"Point"}
}