{
  "type": "Feature",
  "properties": {
    "addr:full":"Harmonieplein 4 Maarssen Utrecht 3603 BM",
    "addr:housenumber":"4",
    "addr:postcode":"3603 bm",
    "addr:street":"Harmonieplein",
    "iso:country":"NL",
    "sg:address":"Harmonieplein 4",
    "sg:city":"Maarssen",
    "sg:orig_category":"Kinderopvang Behalve Thuis",
    "sg:phone":"+31 346 567 375",
    "sg:postcode":"3603 BM",
    "sg:province":"Utrecht",
    "wof:name":"Peuterspeelzaal 'T Opstapje",
    "wof:placetype":"venue"
},
  "geometry": {"coordinates":[5.038697,52.138584],"type":"Point"}
}