{
  "type": "Feature",
  "properties": {
    "addr:full":"Industriestr 22 Sittard Limburg 6135 KH",
    "addr:housenumber":"22",
    "addr:postcode":"6135 kh",
    "addr:street":"Industriestr",
    "iso:country":"NL",
    "sg:address":"Industriestr 22",
    "sg:city":"Sittard",
    "sg:orig_category":"Boekhandels",
    "sg:phone":"+31 46 451 4646",
    "sg:postcode":"6135 KH",
    "sg:province":"Limburg",
    "wof:name":"Alberts-Nienhuis Bv",
    "wof:placetype":"venue"
},
  "geometry": {"coordinates":[5.844751,51.00333],"type":"Point"}
}