{
  "type": "Feature",
  "properties": {
    "iso:country":"NL",
    "sg:address":"Sportlaan 112",
    "sg:city":"Purmerend",
    "sg:orig_category":"Paramedische Behandelingen",
    "sg:phone":"+31 299 424 018",
    "sg:postcode":"1442 EG",
    "sg:province":"North Holland",
    "wof:name":"D. Vlieger-Jacobs",
    "wof:placetype":"venue"
},
  "geometry": {"coordinates":[4.968416,52.514645],"type":"Point"}
}