{
  "type": "Feature",
  "properties": {
    "addr:full":"Kanaaldijk Zuid 7 Eindhoven North Brabant 5611 VA",
    "addr:housenumber":"7",
    "addr:postcode":"5611",
    "addr:street":"Kanaaldijk Zuid",
    "iso:country":"NL",
    "sg:address":"Kanaaldijk Zuid 7",
    "sg:city":"Eindhoven",
    "sg:orig_category":"Meubelreparatie And -Restauratie",
    "sg:phone":"+31 40 211 1277",
    "sg:postcode":"5611 VA",
    "sg:province":"North Brabant",
    "wof:name":"Meubelstoffeerderij Werner Neumann",
    "wof:placetype":"venue"
},
  "geometry": {"coordinates":[5.488301,51.436855],"type":"Point"}
}