{
  "type": "Feature",
  "properties": {
    "addr:full":"Karrewg N 20 Kessel Lb Limburg 5995 ME",
    "addr:postcode":"lb;5995 me",
    "addr:street":"N 20",
    "iso:country":"NL",
    "sg:address":"Karrewg N 20",
    "sg:city":"Kessel Lb",
    "sg:orig_category":"Koeriersdiensten",
    "sg:phone":"+31 77 462 2786",
    "sg:postcode":"5995 ME",
    "sg:province":"Limburg",
    "wof:name":"D & I",
    "wof:placetype":"venue"
},
  "geometry": {"coordinates":[6.04894,51.291866],"type":"Point"}
}