{
  "type": "Feature",
  "properties": {
    "addr:full":"Bredaseweg 92 Oosterhout Nb North Brabant 4902 NS",
    "addr:housenumber":"92;nb",
    "addr:postcode":"4902 ns",
    "addr:street":"Bredaseweg",
    "iso:country":"NL",
    "sg:address":"Bredaseweg 92",
    "sg:city":"Oosterhout Nb",
    "sg:orig_category":"Fotostudio'S And Fotografen",
    "sg:phone":"+31 162 460 882",
    "sg:postcode":"4902 NS",
    "sg:province":"North Brabant",
    "wof:name":"Black & White Studios",
    "wof:placetype":"venue"
},
  "geometry": {"coordinates":[4.849152,51.640411],"type":"Point"}
}