{
  "type": "Feature",
  "properties": {
    "addr:full":"Schoolstr 46 Herten Limburg 6049 BN",
    "addr:housenumber":"46",
    "addr:postcode":"6049 bn",
    "addr:street":"Schoolstr",
    "iso:country":"NL",
    "sg:address":"Schoolstr 46",
    "sg:city":"Herten",
    "sg:orig_category":"Jachthavens - Jachtwerven",
    "sg:phone":"+31 475 315 888",
    "sg:postcode":"6049 BN",
    "sg:province":"Limburg",
    "wof:name":"Rosslag, De",
    "wof:placetype":"venue"
},
  "geometry": {"coordinates":[5.961828,51.183189],"type":"Point"}
}