{
  "type": "Feature",
  "properties": {
    "addr:full":"Textielwg 6 Apeldoorn Gelderland 7311 GH",
    "addr:housenumber":"6",
    "addr:postcode":"7311 gh",
    "addr:street":"Textielwg;Gelderland",
    "iso:country":"NL",
    "sg:address":"Textielwg 6",
    "sg:city":"Apeldoorn",
    "sg:orig_category":"Schilders",
    "sg:phone":"+31 55 521 5120",
    "sg:postcode":"7311 GH",
    "sg:province":"Gelderland",
    "wof:name":"Grip, C J De",
    "wof:placetype":"venue"
},
  "geometry": {"coordinates":[5.951266,52.210995],"type":"Point"}
}