{
  "type": "Feature",
  "properties": {
    "addr:full":"Noorddammerlaan 29 Amstelveen North Holland 1185 XZ",
    "addr:housenumber":"29",
    "addr:postcode":"1185 xz",
    "addr:street":"Noorddammerlaan",
    "iso:country":"NL",
    "sg:address":"Noorddammerlaan 29",
    "sg:city":"Amstelveen",
    "sg:orig_category":"Bedrijfs- And Managementsconsultants",
    "sg:phone":"+31 20 496 5566",
    "sg:postcode":"1185 XZ",
    "sg:province":"North Holland",
    "wof:name":"Caps Communicatie & Actiemarketing Bv",
    "wof:placetype":"venue"
},
  "geometry": {"coordinates":[4.840584,52.291988],"type":"Point"}
}