{
  "type": "Feature",
  "properties": {
    "addr:full":"Willemstr 58D Eindhoven Noord-Brabant 5616 GE",
    "addr:housenumber":"58d",
    "addr:postcode":"5616",
    "addr:street":"Willemstr",
    "iso:country":"NL",
    "sg:address":"Willemstr 58D",
    "sg:city":"Eindhoven",
    "sg:orig_category":"Letters - Fabrieken En Groothandel",
    "sg:phone":"+31 40 251 7102",
    "sg:postcode":"5616 GE",
    "sg:province":"Noord-Brabant",
    "wof:name":"Bosman",
    "wof:placetype":"venue"
},
  "geometry": {"coordinates":[5.484105,51.434471],"type":"Point"}
}