{
  "type": "Feature",
  "properties": {
    "addr:full":"Everwynstr 23 Culemborg Gelderland 4101 CE",
    "addr:housenumber":"23",
    "addr:postcode":"4101 ce",
    "addr:street":"Everwynstr;Gelderland",
    "iso:country":"NL",
    "sg:address":"Everwynstr 23",
    "sg:city":"Culemborg",
    "sg:orig_category":"Cafetaria'S",
    "sg:phone":"+31 345 519 111",
    "sg:postcode":"4101 CE",
    "sg:province":"Gelderland",
    "wof:name":"Meyer Vof",
    "wof:placetype":"venue"
},
  "geometry": {"coordinates":[5.225496,51.956348],"type":"Point"}
}