{
  "type": "Feature",
  "properties": {
    "addr:full":"Ereprys 33 Oldenzaal NL.08 7577 BH",
    "addr:housenumber":"33;nl.08",
    "addr:postcode":"7577 bh",
    "addr:street":"Ereprys",
    "iso:country":"NL",
    "sg:address":"Ereprys 33",
    "sg:city":"Oldenzaal",
    "sg:orig_category":"Bloemen En Planten",
    "sg:phone":"+31 541 521 314",
    "sg:postcode":"7577 BH",
    "sg:province":"NL.08",
    "wof:name":"Nijland, Jan",
    "wof:placetype":"venue"
},
  "geometry": {"coordinates":[6.921749,52.324463],"type":"Point"}
}