{
  "type": "Feature",
  "properties": {
    "addr:full":"Dapperplein 45 Amsterdam North Holland 1093 GP",
    "addr:housenumber":"45",
    "addr:postcode":"1093 gp",
    "addr:street":"Dapperplein",
    "iso:country":"NL",
    "sg:address":"Dapperplein 45",
    "sg:city":"Amsterdam",
    "sg:orig_category":"Schoenen",
    "sg:phone":"+31 20 663 1110",
    "sg:postcode":"1093 GP",
    "sg:province":"North Holland",
    "wof:name":"Himtex-Shoepoint",
    "wof:placetype":"venue"
},
  "geometry": {"coordinates":[4.92834,52.362034],"type":"Point"}
}