{
  "type": "Feature",
  "properties": {
    "iso:country":"NL",
    "sg:address":"Pr Marykewg 16",
    "sg:city":"Geldermalsen",
    "sg:orig_category":"Onteigening",
    "sg:phone":"+31 345 570 011",
    "sg:postcode":"4191 XL",
    "sg:province":"Gelderland",
    "wof:name":"Wellner",
    "wof:placetype":"venue"
},
  "geometry": {"coordinates":[5.301463,51.882946],"type":"Point"}
}