{
  "type": "Feature",
  "properties": {
    "addr:full":"Martinikerkhof 24 Groningen Groningen 9712 JH",
    "addr:housenumber":"24",
    "addr:postcode":"9712 jh",
    "addr:street":"Martinikerkhof",
    "iso:country":"NL",
    "sg:address":"Martinikerkhof 24",
    "sg:city":"Groningen",
    "sg:orig_category":"Public Relationbureaus",
    "sg:phone":"+31 50 313 4954",
    "sg:postcode":"9712 JH",
    "sg:province":"Groningen",
    "wof:name":"Vogel & Mulder Bv",
    "wof:placetype":"venue"
},
  "geometry": {"coordinates":[6.569887,53.220001],"type":"Point"}
}