{
  "type": "Feature",
  "properties": {
    "addr:full":"Benraatshoef 247 Raamsdonksveer Noord-Brabant 4941 TK",
    "addr:housenumber":"247",
    "addr:postcode":"4941 tk",
    "addr:street":"Benraatshoef",
    "iso:country":"NL",
    "sg:address":"Benraatshoef 247",
    "sg:city":"Raamsdonksveer",
    "sg:orig_category":"Koeriersdiensten",
    "sg:phone":"+31 6 53731733",
    "sg:postcode":"4941 TK",
    "sg:province":"Noord-Brabant",
    "wof:name":"Gst",
    "wof:placetype":"venue"
},
  "geometry": {"coordinates":[4.884795,51.700184],"type":"Point"}
}