{
  "type": "Feature",
  "properties": {
    "addr:full":"Julianaln 256 Bilthoven Utrecht 3722 GW",
    "addr:housenumber":"256",
    "addr:postcode":"3722 gw",
    "addr:street":"Bilthoven",
    "iso:country":"NL",
    "sg:address":"Julianaln 256",
    "sg:city":"Bilthoven",
    "sg:orig_category":"Honden- En Kattentrimsalons",
    "sg:phone":"+31 30 228 4256",
    "sg:postcode":"3722 GW",
    "sg:province":"Utrecht",
    "wof:name":"Nicky Hondentrimsalon",
    "wof:placetype":"venue"
},
  "geometry": {"coordinates":[5.225084,52.132587],"type":"Point"}
}