{
  "type": "Feature",
  "properties": {
    "addr:full":"St Antoniesb Str 88 Amsterdam Noord-Holland 1011 HB",
    "addr:housenumber":"88",
    "addr:postcode":"1011 hb",
    "addr:street":"Str",
    "iso:country":"NL",
    "sg:address":"St Antoniesb Str 88",
    "sg:city":"Amsterdam",
    "sg:orig_category":"Kantoor- En Bedrijfsmeubelen",
    "sg:phone":"+31 20 623 1706",
    "sg:postcode":"1011 HB",
    "sg:province":"Noord-Holland",
    "wof:name":"Ergo-Zit",
    "wof:placetype":"venue"
},
  "geometry": {"coordinates":[4.9003400803,52.3709945679],"type":"Point"}
}