{
  "type": "Feature",
  "properties": {
    "addr:full":"Kromhout 120 Dordrecht Zuid-Holland 3311 RH",
    "addr:housenumber":"120",
    "addr:postcode":"3311 rh",
    "addr:street":"Kromhout",
    "iso:country":"NL",
    "sg:address":"Kromhout 120",
    "sg:city":"Dordrecht",
    "sg:orig_category":"Hulpverlening Sociaal",
    "sg:phone":"+31 78 633 4700",
    "sg:postcode":"3311 RH",
    "sg:province":"Zuid-Holland",
    "wof:name":"Jeugdzorg, Sticht",
    "wof:placetype":"venue"
},
  "geometry": {"coordinates":[4.673107,51.813202],"type":"Point"}
}