{
  "type": "Feature",
  "properties": {
    "addr:full":"Adelheidstr 74 S Gravenhage Zuid-Holland 2595 EE",
    "addr:housenumber":"74;gravenhage",
    "addr:postcode":"2595 ee",
    "addr:street":"Adelheidstr;S",
    "iso:country":"NL",
    "sg:address":"Adelheidstr 74",
    "sg:city":"S Gravenhage",
    "sg:orig_category":"Advocaten En Advocatenkantoren",
    "sg:phone":"+31 70 381 8915",
    "sg:postcode":"2595 EE",
    "sg:province":"Zuid-Holland",
    "sg:website":"http://www.wgk-advocaten.nl",
    "wof:name":"Wigman Gijsberts & Kaya",
    "wof:placetype":"venue"
},
  "geometry": {"coordinates":[4.33507,52.081421],"type":"Point"}
}