{
  "type": "Feature",
  "properties": {
    "addr:full":"Gouwe 27 Hoogwoud Noord-Holland 1718 LK",
    "addr:housenumber":"27",
    "addr:postcode":"1718 lk",
    "addr:street":"Gouwe",
    "iso:country":"NL",
    "sg:address":"Gouwe 27",
    "sg:city":"Hoogwoud",
    "sg:orig_category":"Weegwerktuigen - Fabrieken En Groothandel",
    "sg:phone":"+31 229 582 426",
    "sg:postcode":"1718 LK",
    "sg:province":"Noord-Holland",
    "sg:website":"http://www.kassasenweegschalen.nl",
    "wof:name":"Heijne Handelsonderneming",
    "wof:placetype":"venue"
},
  "geometry": {"coordinates":[4.9606342316,52.7292480469],"type":"Point"}
}