{
  "type": "Feature",
  "properties": {
    "iso:country":"NL",
    "sg:address":"Sint Agnietenstraat 17",
    "sg:city":"Tiel",
    "sg:orig_category":"Artsen And Specialisten",
    "sg:phone":"+31 344 613 890",
    "sg:postcode":"4001 NB",
    "sg:province":"Gelderland",
    "wof:name":"J.C. Taris R. Van Drie",
    "wof:placetype":"venue"
},
  "geometry": {"coordinates":[5.436414,51.885921],"type":"Point"}
}