{
  "type": "Feature",
  "properties": {
    "iso:country":"NL",
    "sg:address":"Zwarteweg 12",
    "sg:city":"Voorst Gem Voorst",
    "sg:orig_category":"Huisdierenfokkers",
    "sg:phone":"+31 575 501 474",
    "sg:postcode":"7383 AK",
    "sg:province":"Gelderland",
    "wof:name":"H W Korten En Zn",
    "wof:placetype":"venue"
},
  "geometry": {"coordinates":[6.133118,52.184231],"type":"Point"}
}