{
  "type": "Feature",
  "properties": {
    "addr:full":"Akkerwal 23 A Thorn Limburg 6017 AW",
    "addr:housenumber":"23 a",
    "addr:postcode":"6017 aw",
    "addr:street":"Akkerwal",
    "iso:country":"NL",
    "sg:address":"Akkerwal 23 A",
    "sg:city":"Thorn",
    "sg:orig_category":"Postorderbedrijven",
    "sg:phone":"+31 475 560 666",
    "sg:postcode":"6017 AW",
    "sg:province":"Limburg",
    "wof:name":"Verzendhuis Postina Bv",
    "wof:placetype":"venue"
},
  "geometry": {"coordinates":[5.840536,51.162682],"type":"Point"}
}