{
  "type": "Feature",
  "properties": {
    "iso:country":"NL",
    "sg:address":"Morswg 55C2",
    "sg:city":"Leiden",
    "sg:orig_category":"Autoschade- Herstelbedrijven",
    "sg:phone":"+31 71 566 1371",
    "sg:postcode":"2312 AB",
    "sg:province":"South Holland",
    "wof:name":"Fixit",
    "wof:placetype":"venue"
},
  "geometry": {"coordinates":[4.477356,52.160851],"type":"Point"}
}