{
  "type": "Feature",
  "properties": {
    "addr:full":"Bronnenstr 1 Heerlen Limburg 6418 EA",
    "addr:housenumber":"1",
    "addr:postcode":"6418 ea",
    "addr:street":"Bronnenstr",
    "iso:country":"NL",
    "sg:address":"Bronnenstr 1",
    "sg:city":"Heerlen",
    "sg:orig_category":"Schoenen - Reparaties",
    "sg:phone":"+31 45 541 3043",
    "sg:postcode":"6418 EA",
    "sg:province":"Limburg",
    "wof:name":"Heusschen",
    "wof:placetype":"venue"
},
  "geometry": {"coordinates":[6.005833,50.869549],"type":"Point"}
}