{
  "type": "Feature",
  "properties": {
    "addr:full":"Stationsstraat 59 Pijnacker Zuid-Holland 2641 GK",
    "addr:housenumber":"59",
    "addr:postcode":"2641 gk",
    "addr:street":"Stationsstraat",
    "iso:country":"NL",
    "sg:address":"Stationsstraat 59",
    "sg:city":"Pijnacker",
    "sg:orig_category":"Juweliers",
    "sg:phone":"+31 15 369 2560",
    "sg:postcode":"2641 GK",
    "sg:province":"Zuid-Holland",
    "wof:name":"Firma R.J. Westerhof",
    "wof:placetype":"venue"
},
  "geometry": {"coordinates":[4.434886,52.01886],"type":"Point"}
}