{
  "type": "Feature",
  "properties": {
    "addr:full":"Kerkstraat 40 Oss Noord-Brabant 5341 BL",
    "addr:housenumber":"40",
    "addr:postcode":"5341 bl",
    "addr:street":"Kerkstraat",
    "iso:country":"NL",
    "sg:address":"Kerkstraat 40",
    "sg:city":"Oss",
    "sg:orig_category":"Kappers",
    "sg:phone":"+31 412 642 318",
    "sg:postcode":"5341 BL",
    "sg:province":"Noord-Brabant",
    "wof:name":"Schoonheidssalon Marcel",
    "wof:placetype":"venue"
},
  "geometry": {"coordinates":[-77.235214,38.312599],"type":"Point"}
}