{
  "type": "Feature",
  "properties": {
    "addr:full":"Industrierondwg 21C Urk NL. 8321 EB",
    "addr:housenumber":"21c",
    "addr:postcode":"8321 eb",
    "addr:street":"Industrierondwg;Nl.",
    "iso:country":"NL",
    "sg:address":"Industrierondwg 21C",
    "sg:city":"Urk",
    "sg:orig_category":"Fitnesscentra",
    "sg:phone":"+31 527 685 199",
    "sg:postcode":"8321 EB",
    "sg:province":"NL.",
    "wof:name":"Sport- & Gezondheidscentrum Urk",
    "wof:placetype":"venue"
},
  "geometry": {"coordinates":[5.608763,52.658707],"type":"Point"}
}