{
  "type": "Feature",
  "properties": {
    "addr:full":"Hoogeindsestr 19 Tiel Gelderland 4001 AA",
    "addr:housenumber":"19",
    "addr:postcode":"4001 aa",
    "addr:street":"Hoogeindsestr;Gelderland",
    "iso:country":"NL",
    "sg:address":"Hoogeindsestr 19",
    "sg:city":"Tiel",
    "sg:orig_category":"Sportschoenen - Winkels",
    "sg:phone":"+31 344 611 407",
    "sg:postcode":"4001 AA",
    "sg:province":"Gelderland",
    "sg:website":"http://www.intersport.nl",
    "wof:name":"Intersport",
    "wof:placetype":"venue"
},
  "geometry": {"coordinates":[5.431724,51.88813],"type":"Point"}
}