{
  "type": "Feature",
  "properties": {
    "addr:full":"De Aarhof 21 Alphen Aan Den Ryn Zuid-Holland 2406 BT",
    "addr:housenumber":"21",
    "addr:postcode":"2406 bt",
    "addr:street":"De Aarhof;Aan Den Ryn",
    "iso:country":"NL",
    "sg:address":"De Aarhof 21",
    "sg:city":"Alphen Aan Den Ryn",
    "sg:orig_category":"Huishoudelijke Apparaten En Artikelen",
    "sg:phone":"+31 172 472 787",
    "sg:postcode":"2406 BT",
    "sg:province":"Zuid-Holland",
    "wof:name":"Woerdman",
    "wof:placetype":"venue"
},
  "geometry": {"coordinates":[4.665358,52.130024],"type":"Point"}
}