{
  "type": "Feature",
  "properties": {
    "addr:full":"Nw Binnenwg 460 Rotterdam South Holland 3023 EZ",
    "addr:housenumber":"460",
    "addr:postcode":"3023 ez",
    "iso:country":"NL",
    "sg:address":"Nw Binnenwg 460",
    "sg:city":"Rotterdam",
    "sg:orig_category":"Kantoorbenodigdheden",
    "sg:phone":"+31 10 477 3000",
    "sg:postcode":"3023 EZ",
    "sg:province":"South Holland",
    "wof:name":"Spek Vof, J Van Der",
    "wof:placetype":"venue"
},
  "geometry": {"coordinates":[4.4507408142,51.9100799561],"type":"Point"}
}