{
  "type": "Feature",
  "properties": {
    "addr:full":"B Bastiaansestr 6 Bemmel Gelderland 6681 XJ",
    "addr:housenumber":"6",
    "addr:postcode":"6681 xj",
    "addr:street":"Gelderland",
    "iso:country":"NL",
    "sg:address":"B Bastiaansestr 6",
    "sg:city":"Bemmel",
    "sg:orig_category":"Geluidsopnamestudio'S",
    "sg:phone":"+31 481 465 907",
    "sg:postcode":"6681 XJ",
    "sg:province":"Gelderland",
    "wof:name":"Aarden Prod, Rob",
    "wof:placetype":"venue"
},
  "geometry": {"coordinates":[5.905737,51.892578],"type":"Point"}
}