{
  "type": "Feature",
  "properties": {
    "addr:full":"Galjoenwg 49 Maastricht Limburg 6222 NS",
    "addr:housenumber":"49",
    "addr:postcode":"6222 ns",
    "addr:street":"Galjoenwg",
    "iso:country":"NL",
    "sg:address":"Galjoenwg 49",
    "sg:city":"Maastricht",
    "sg:orig_category":"Webdesign Bureaus",
    "sg:phone":"+31 6 55740527",
    "sg:postcode":"6222 NS",
    "sg:province":"Limburg",
    "sg:website":"http://www.becom-it.nl",
    "wof:name":"Becom",
    "wof:placetype":"venue"
},
  "geometry": {"coordinates":[5.7100319862,50.8741073608],"type":"Point"}
}