{
  "type": "Feature",
  "properties": {
    "iso:country":"NL",
    "sg:address":"V Bruhezedal 3",
    "sg:city":"Valkenswaard",
    "sg:orig_category":"Cafetaria'S",
    "sg:phone":"+31 40 201 5068",
    "sg:postcode":"5551 EW",
    "sg:province":"Noord-Brabant",
    "wof:name":"Dommel, De",
    "wof:placetype":"venue"
},
  "geometry": {"coordinates":[5.435406,51.349888],"type":"Point"}
}