{
  "type": "Feature",
  "properties": {
    "addr:full":"Byzantiumstr 26-28 Haarlem Noord-Holland 2033 EK",
    "addr:housenumber":"26-28",
    "addr:postcode":"2033 ek",
    "iso:country":"NL",
    "sg:address":"Byzantiumstr 26-28",
    "sg:city":"Haarlem",
    "sg:orig_category":"Fietsen En Bromfietsen",
    "sg:phone":"+31 23 535 0235",
    "sg:postcode":"2033 EK",
    "sg:province":"Noord-Holland",
    "sg:website":"http://www.puttweewielers.nl",
    "wof:name":"Put Tweewielers Bv",
    "wof:placetype":"venue"
},
  "geometry": {"coordinates":[4.645097,52.375046],"type":"Point"}
}