{
  "type": "Feature",
  "properties": {
    "addr:full":"Hondecoeterstr 6 Amsterdam North Holland 1071 LR",
    "addr:housenumber":"6",
    "addr:postcode":"1071 lr",
    "addr:street":"Hondecoeterstr",
    "iso:country":"NL",
    "sg:address":"Hondecoeterstr 6",
    "sg:city":"Amsterdam",
    "sg:orig_category":"Peuterspeelzalen",
    "sg:phone":"+31 20 676 0625",
    "sg:postcode":"1071 LR",
    "sg:province":"North Holland",
    "wof:name":"Impe Dimpe",
    "wof:placetype":"venue"
},
  "geometry": {"coordinates":[4.877869,52.354794],"type":"Point"}
}