{
  "type": "Feature",
  "properties": {
    "iso:country":"NL",
    "sg:address":"De Heurne 8",
    "sg:city":"Enschede",
    "sg:orig_category":"Verlichting And Huishoudartikelen",
    "sg:phone":"+31 53 430 5998",
    "sg:postcode":"7511 GX",
    "sg:province":"NL.08",
    "wof:name":"Knaakland Enschede",
    "wof:placetype":"venue"
},
  "geometry": {"coordinates":[6.898953,52.220062],"type":"Point"}
}