{
  "type": "Feature",
  "properties": {
    "addr:full":"Dorpstr 21 Waddinxveen South Holland 2742 AP",
    "addr:housenumber":"21",
    "addr:postcode":"2742 ap",
    "addr:street":"Dorpstr",
    "iso:country":"NL",
    "sg:address":"Dorpstr 21",
    "sg:city":"Waddinxveen",
    "sg:orig_category":"Kappers",
    "sg:phone":"+31 182 632 339",
    "sg:postcode":"2742 AP",
    "sg:province":"South Holland",
    "wof:name":"Marna",
    "wof:placetype":"venue"
},
  "geometry": {"coordinates":[4.641658,52.045891],"type":"Point"}
}