{
  "type": "Feature",
  "properties": {
    "addr:full":"Kooimeerln 17 Alkmaar North Holland 1814 GN",
    "addr:housenumber":"17",
    "addr:postcode":"1814 gn",
    "addr:street":"Kooimeerln",
    "iso:country":"NL",
    "sg:address":"Kooimeerln 17",
    "sg:city":"Alkmaar",
    "sg:orig_category":"Woninginrichting",
    "sg:phone":"+31 72 515 5256",
    "sg:postcode":"1814 GN",
    "sg:province":"North Holland",
    "sg:website":"http://www.dintrainterieur.nl",
    "wof:name":"Dintra Interieur Bv",
    "wof:placetype":"venue"
},
  "geometry": {"coordinates":[4.746257782,52.6343612671],"type":"Point"}
}