{
  "type": "Feature",
  "properties": {
    "addr:full":"Postbus 659 Heemstede Noord-Holland 2100 AR",
    "addr:housenumber":"659",
    "addr:postcode":"2100",
    "addr:street":"Postbus",
    "iso:country":"NL",
    "sg:address":"Postbus 659",
    "sg:city":"Heemstede",
    "sg:orig_category":"Verkeersbureaus",
    "sg:phone":"+31 23 528 7548",
    "sg:postcode":"2100 AR",
    "sg:province":"Noord-Holland",
    "sg:website":"HTTP://www.jersey.com",
    "wof:name":"Kanaaleilanden",
    "wof:placetype":"venue"
},
  "geometry": {"coordinates":[4.621248,52.345287],"type":"Point"}
}