{
  "type": "Feature",
  "properties": {
    "iso:country":"NL",
    "sg:address":"Wilhelminastr 45",
    "sg:city":"Breukelen Ut",
    "sg:orig_category":"Verenigingen En Stichtingen",
    "sg:phone":"+31 346 262 286",
    "sg:postcode":"3621 VG",
    "sg:province":"Utrecht",
    "sg:website":"http://www.harry-bacon.nl/",
    "wof:name":"Harry Bacon, Ned Stomaver",
    "wof:placetype":"venue"
},
  "geometry": {"coordinates":[5.001585,52.172958],"type":"Point"}
}