{
  "type": "Feature",
  "properties": {
    "addr:full":"Elsbeekweg 29 Hengelo Ov Overijssel 7557 CA",
    "addr:housenumber":"29",
    "addr:postcode":"7557 ca",
    "addr:street":"Elsbeekweg;Ov",
    "iso:country":"NL",
    "sg:address":"Elsbeekweg 29",
    "sg:city":"Hengelo Ov",
    "sg:orig_category":"Bloemen And Planten",
    "sg:phone":"+31 74 291 0975",
    "sg:postcode":"7557 CA",
    "sg:province":"Overijssel",
    "wof:name":"Kwekerij Ter Heegde",
    "wof:placetype":"venue"
},
  "geometry": {"coordinates":[6.802995,52.26693],"type":"Point"}
}