{
  "type": "Feature",
  "properties": {
    "addr:full":"Hoevense Kanaaldijk 83 Tilburg Noord-Brabant 5018 EB",
    "addr:housenumber":"83",
    "addr:postcode":"5018 eb",
    "addr:street":"Kanaaldijk",
    "iso:country":"NL",
    "sg:address":"Hoevense Kanaaldijk 83",
    "sg:city":"Tilburg",
    "sg:orig_category":"Krantenuitgeverijen",
    "sg:phone":"+31 13 544 6935",
    "sg:postcode":"5018 EB",
    "sg:province":"Noord-Brabant",
    "wof:name":"Fado Press",
    "wof:placetype":"venue"
},
  "geometry": {"coordinates":[5.110217,51.55891],"type":"Point"}
}