{
  "type": "Feature",
  "properties": {
    "addr:full":"C Gerritsmastr 49 Heerenveen Friesland 8442 GZ",
    "addr:housenumber":"49",
    "addr:postcode":"8442 gz",
    "iso:country":"NL",
    "sg:address":"C Gerritsmastr 49",
    "sg:city":"Heerenveen",
    "sg:orig_category":"Onderhoudswerken",
    "sg:phone":"+31 513 646 621",
    "sg:postcode":"8442 GZ",
    "sg:province":"Friesland",
    "wof:name":"Woudstra, Wim",
    "wof:placetype":"venue"
},
  "geometry": {"coordinates":[5.93212,52.957527],"type":"Point"}
}