{
  "type": "Feature",
  "properties": {
    "addr:full":"Markstraat 1 Opheusden Gelderland 4043 JX",
    "addr:housenumber":"1",
    "addr:postcode":"4043 jx",
    "addr:street":"Markstraat;Gelderland",
    "iso:country":"NL",
    "sg:address":"Markstraat 1",
    "sg:city":"Opheusden",
    "sg:orig_category":"Kampeerterreinen",
    "sg:phone":"+31 488 482 731",
    "sg:postcode":"4043 JX",
    "sg:province":"Gelderland",
    "wof:name":"Camping De Markplas",
    "wof:placetype":"venue"
},
  "geometry": {"coordinates":[5.5979309082,51.939289093],"type":"Point"}
}