{
  "type": "Feature",
  "properties": {
    "iso:country":"NL",
    "sg:address":"Molenweide 48",
    "sg:city":"Castricum",
    "sg:orig_category":"Juridische Dienstverlening",
    "sg:phone":"+31 251 655 768",
    "sg:postcode":"1902 CJ",
    "sg:province":"North Holland",
    "wof:name":"De Brug Consultancy",
    "wof:placetype":"venue"
},
  "geometry": {"coordinates":[4.6752758026,52.5528297424],"type":"Point"}
}