{
  "type": "Feature",
  "properties": {
    "addr:full":"Ereprysstr 45 Uden Noord-Brabant 5402 GA",
    "addr:housenumber":"45",
    "addr:postcode":"5402 ga",
    "addr:street":"Ereprysstr",
    "iso:country":"NL",
    "sg:address":"Ereprysstr 45",
    "sg:city":"Uden",
    "sg:orig_category":"Galeries",
    "sg:phone":"+31 413 259 884",
    "sg:postcode":"5402 GA",
    "sg:province":"Noord-Brabant",
    "wof:name":"Horizon",
    "wof:placetype":"venue"
},
  "geometry": {"coordinates":[-83.222931,32.678131],"type":"Point"}
}