{
  "type": "Feature",
  "properties": {
    "addr:full":"Toulonseln 79 Dordrecht Zuid-Holland 3311 LT",
    "addr:housenumber":"79",
    "addr:postcode":"3311 lt",
    "addr:street":"Toulonseln",
    "iso:country":"NL",
    "sg:address":"Toulonseln 79",
    "sg:city":"Dordrecht",
    "sg:orig_category":"Adviesbureaus Scheepsbouwkunde",
    "sg:phone":"+31 78 613 3822",
    "sg:postcode":"3311 LT",
    "sg:province":"Zuid-Holland",
    "sg:website":"HTTP://www.cor-d-rover.com",
    "wof:name":"Cor De Rover Design Bv",
    "wof:placetype":"venue"
},
  "geometry": {"coordinates":[4.675846,51.808483],"type":"Point"}
}