{
  "type": "Feature",
  "properties": {
    "addr:full":"Baansestr 7B Overloon Noord-Brabant 5825 BW",
    "addr:housenumber":"7b",
    "addr:postcode":"5825 bw",
    "addr:street":"Baansestr",
    "iso:country":"NL",
    "sg:address":"Baansestr 7B",
    "sg:city":"Overloon",
    "sg:classifiers":[
        {
            "category":"Food & Beverages",
            "subcategory":"Fruits & Vegetables",
            "type":"Retail Goods"
        }
    ],
    "sg:phone":"+31 478 642 486",
    "sg:postcode":"5825 BW",
    "sg:province":"Noord-Brabant",
    "sg:tags":[
        "en",
        "groenten"
    ],
    "wof:name":"Eeuwijk, Van",
    "wof:placetype":"venue"
},
  "geometry": {"coordinates":[5.937846,51.572395],"type":"Point"}
}