{
  "type": "Feature",
  "properties": {
    "addr:full":"Polstraat 52 Wijk En Aalburg North Brabant 4261 BV",
    "addr:housenumber":"52",
    "addr:postcode":"4261 bv",
    "addr:street":"Polstraat",
    "iso:country":"NL",
    "sg:address":"Polstraat 52",
    "sg:city":"Wijk En Aalburg",
    "sg:orig_category":"Diverse Grafische Activiteiten",
    "sg:phone":"+31 416 691 610",
    "sg:postcode":"4261 BV",
    "sg:province":"North Brabant",
    "wof:name":"Boek Design",
    "wof:placetype":"venue"
},
  "geometry": {"coordinates":[5.122884,51.750229],"type":"Point"}
}