{
  "type": "Feature",
  "properties": {
    "addr:full":"Steurweg 7 Raamsdonksveer Noord-Brabant 4941 VP",
    "addr:housenumber":"7",
    "addr:postcode":"4941 vp",
    "addr:street":"Steurweg",
    "iso:country":"NL",
    "sg:address":"Steurweg 7",
    "sg:city":"Raamsdonksveer",
    "sg:orig_category":"Zuivelproducten And Spijsoli?n Gh",
    "sg:phone":"+31 162 582 600",
    "sg:postcode":"4941 VP",
    "sg:province":"Noord-Brabant",
    "wof:name":"Frico Cheese Packaging",
    "wof:placetype":"venue"
},
  "geometry": {"coordinates":[4.882699,51.712227],"type":"Point"}
}