{
  "type": "Feature",
  "properties": {
    "addr:full":"Goyergracht Zuid 1 Eemnes Utrecht 3755 MX",
    "addr:housenumber":"1",
    "addr:postcode":"3755 mx",
    "addr:street":"Goyergracht Zuid",
    "iso:country":"NL",
    "sg:address":"Goyergracht Zuid 1",
    "sg:city":"Eemnes",
    "sg:orig_category":"Bloemen And Planten",
    "sg:phone":"+31 35 538 2872",
    "sg:postcode":"3755 MX",
    "sg:province":"Utrecht",
    "wof:name":"Plantenmarkt Boskoop",
    "wof:placetype":"venue"
},
  "geometry": {"coordinates":[5.236085,52.240536],"type":"Point"}
}