{
  "type": "Feature",
  "properties": {
    "addr:full":"Aristoteleshof 33 Arnhem Gelderland 6836 GJ",
    "addr:housenumber":"33",
    "addr:postcode":"6836 gj",
    "addr:street":"Aristoteleshof",
    "iso:country":"NL",
    "sg:address":"Aristoteleshof 33",
    "sg:city":"Arnhem",
    "sg:orig_category":"Autorijscholen",
    "sg:phone":"+31 26 321 6803",
    "sg:postcode":"6836 GJ",
    "sg:province":"Gelderland",
    "wof:name":"Kaplan",
    "wof:placetype":"venue"
},
  "geometry": {"coordinates":[5.893249,51.946087],"type":"Point"}
}