{
  "type": "Feature",
  "properties": {
    "iso:country":"NL",
    "sg:address":"Geenstr 32A",
    "sg:city":"Geleen",
    "sg:orig_category":"Peuterspeelzalen",
    "sg:phone":"+31 46 474 0928",
    "sg:postcode":"6162 XZ",
    "sg:province":"Limburg",
    "wof:name":"Joepie Joepie",
    "wof:placetype":"venue"
},
  "geometry": {"coordinates":[5.828962,50.975937],"type":"Point"}
}