{
  "type": "Feature",
  "properties": {
    "addr:full":"Lopikerweg Oost 103F Lopik Utrecht 3411 LW",
    "addr:housenumber":"103f",
    "addr:postcode":"3411 lw",
    "addr:street":"Lopikerweg Oost",
    "iso:country":"NL",
    "sg:address":"Lopikerweg Oost 103F",
    "sg:city":"Lopik",
    "sg:orig_category":"Autokeuringen",
    "sg:phone":"+31 348 553 236",
    "sg:postcode":"3411 LW",
    "sg:province":"Utrecht",
    "wof:name":"Tebo Metaal & Polyesterwerken",
    "wof:placetype":"venue"
},
  "geometry": {"coordinates":[4.998357,51.986244],"type":"Point"}
}