{
  "type": "Feature",
  "properties": {
    "iso:country":"NL",
    "sg:address":"Hengeveldstr 34",
    "sg:city":"Utrecht",
    "sg:orig_category":"Journalisten Freelance",
    "sg:phone":"+31 30 273 5042",
    "sg:postcode":"3572 KJ",
    "sg:province":"Utrecht",
    "wof:name":"Bouman, Hans",
    "wof:placetype":"venue"
},
  "geometry": {"coordinates":[5.130455,52.101761],"type":"Point"}
}