{
  "type": "Feature",
  "properties": {
    "addr:full":"Homeruspln 5A Heerlen Limburg 6411 AW",
    "addr:housenumber":"5a",
    "addr:postcode":"6411 aw",
    "addr:street":"Homeruspln",
    "iso:country":"NL",
    "sg:address":"Homeruspln 5A",
    "sg:city":"Heerlen",
    "sg:orig_category":"Herenkleding",
    "sg:phone":"+31 45 571 6109",
    "sg:postcode":"6411 AW",
    "sg:province":"Limburg",
    "wof:name":"Vrancken",
    "wof:placetype":"venue"
},
  "geometry": {"coordinates":[5.97111,50.886345],"type":"Point"}
}