{
  "type": "Feature",
  "properties": {
    "addr:full":"Kennedystr 31 Ulestraten Limburg 6235 CG",
    "addr:housenumber":"31",
    "addr:postcode":"6235 cg",
    "addr:street":"Kennedystr",
    "iso:country":"NL",
    "sg:address":"Kennedystr 31",
    "sg:city":"Ulestraten",
    "sg:orig_category":"Schoonheidsinstituten",
    "sg:phone":"+31 6 29536527",
    "sg:postcode":"6235 CG",
    "sg:province":"Limburg",
    "wof:name":"Face & Bodycare",
    "wof:placetype":"venue"
},
  "geometry": {"coordinates":[5.778306,50.906807],"type":"Point"}
}