{
  "type": "Feature",
  "properties": {
    "addr:full":"Sprokkelveld 56 Milsbeek North Brabant 6596 DM",
    "addr:housenumber":"56",
    "addr:postcode":"6596 dm",
    "addr:street":"Sprokkelveld",
    "iso:country":"NL",
    "sg:address":"Sprokkelveld 56",
    "sg:city":"Milsbeek",
    "sg:orig_category":"Goederenvervoer Over De Weg",
    "sg:phone":"+31 485 516 110",
    "sg:postcode":"6596 DM",
    "sg:province":"North Brabant",
    "wof:name":"Intern Transportbedrijf Firma Den Ouden",
    "wof:placetype":"venue"
},
  "geometry": {"coordinates":[5.941582,51.719158],"type":"Point"}
}