{
  "type": "Feature",
  "properties": {
    "addr:full":"Wingerd 44 Beverwyk North Holland 1944 ND",
    "addr:housenumber":"44",
    "addr:postcode":"1944 nd",
    "addr:street":"Wingerd;North",
    "iso:country":"NL",
    "sg:address":"Wingerd 44",
    "sg:city":"Beverwyk",
    "sg:orig_category":"Verzekeringen - Verzekeringskantoren",
    "sg:phone":"+31 251 237 444",
    "sg:postcode":"1944 ND",
    "sg:province":"North Holland",
    "wof:name":"Scheerman, M",
    "wof:placetype":"venue"
},
  "geometry": {"coordinates":[4.648003,52.493484],"type":"Point"}
}