{
  "type": "Feature",
  "properties": {
    "addr:full":"Levie Vorstkade 41 Rotterdam South Holland 3071 AG",
    "addr:housenumber":"41",
    "addr:postcode":"3071",
    "addr:street":"Levie Vorstkade",
    "iso:country":"NL",
    "sg:address":"Levie Vorstkade 41",
    "sg:city":"Rotterdam",
    "sg:orig_category":"Artsen And Specialisten",
    "sg:phone":"+31 10 290 9907",
    "sg:postcode":"3071 AG",
    "sg:province":"South Holland",
    "wof:name":"Drs. M.J. Nijholt Individ/Groepspsychotherap",
    "wof:placetype":"venue"
},
  "geometry": {"coordinates":[4.497518,51.908344],"type":"Point"}
}