{
  "type": "Feature",
  "properties": {
    "addr:full":"Brinkln 9 Blaricum Noord-Holland 1261 ER",
    "addr:housenumber":"9",
    "addr:postcode":"1261 er",
    "addr:street":"Brinkln",
    "iso:country":"NL",
    "sg:address":"Brinkln 9",
    "sg:city":"Blaricum",
    "sg:orig_category":"Kappers",
    "sg:phone":"+31 35 538 6832",
    "sg:postcode":"1261 ER",
    "sg:province":"Noord-Holland",
    "wof:name":"G?bert, Haute Coiffure",
    "wof:placetype":"venue"
},
  "geometry": {"coordinates":[5.2434391975,52.2732772827],"type":"Point"}
}