{
  "type": "Feature",
  "properties": {
    "addr:full":"Commandeurslaan 48 Katwijk Zh Zuid-Holland 2223 BA",
    "addr:housenumber":"48",
    "addr:postcode":"2223 ba",
    "addr:street":"Commandeurslaan",
    "iso:country":"NL",
    "sg:address":"Commandeurslaan 48",
    "sg:city":"Katwijk Zh",
    "sg:orig_category":"Verzekeringen",
    "sg:phone":"+31 71 403 0105",
    "sg:postcode":"2223 BA",
    "sg:province":"Zuid-Holland",
    "wof:name":"Ass Kant J De Winter",
    "wof:placetype":"venue"
},
  "geometry": {"coordinates":[4.420421,52.195831],"type":"Point"}
}