{
  "type": "Feature",
  "properties": {
    "addr:full":"Nw Rielsewg 12 Goirle North Brabant 5051 PD",
    "addr:housenumber":"12",
    "addr:postcode":"5051 pd",
    "iso:country":"NL",
    "sg:address":"Nw Rielsewg 12",
    "sg:city":"Goirle",
    "sg:orig_category":"Kunststoffen - Fabrieken En Groothandel",
    "sg:phone":"+31 13 534 9046",
    "sg:postcode":"5051 PD",
    "sg:province":"North Brabant",
    "wof:name":"Snij-Unie",
    "wof:placetype":"venue"
},
  "geometry": {"coordinates":[5.05719,51.523327],"type":"Point"}
}