{
  "type": "Feature",
  "properties": {
    "addr:full":"Houtrakgr 211 Utrecht Utrecht 3544 SC",
    "addr:housenumber":"211",
    "addr:postcode":"3544",
    "iso:country":"NL",
    "sg:address":"Houtrakgr 211",
    "sg:city":"Utrecht",
    "sg:orig_category":"Kinderopvang",
    "sg:phone":"+31 30 662 0005",
    "sg:postcode":"3544 SC",
    "sg:province":"Utrecht",
    "wof:name":"Lepelaar, De",
    "wof:placetype":"venue"
},
  "geometry": {"coordinates":[5.05383,52.085571],"type":"Point"}
}