{
  "type": "Feature",
  "properties": {
    "addr:full":"Lochemsewg 1 Markelo Overijssel 7475 PA",
    "addr:housenumber":"1",
    "addr:postcode":"7475 pa",
    "addr:street":"Lochemsewg",
    "iso:country":"NL",
    "sg:address":"Lochemsewg 1",
    "sg:city":"Markelo",
    "sg:classifiers":[
        {
            "category":"Restaurant",
            "type":"Food & Drink"
        }
    ],
    "sg:phone":"+31 547 351 224",
    "sg:postcode":"7475 PA",
    "sg:province":"Overijssel",
    "wof:name":"Viersprong, De",
    "wof:placetype":"venue"
},
  "geometry": {"coordinates":[6.517628,52.197193],"type":"Point"}
}