{
  "type": "Feature",
  "properties": {
    "addr:full":"Grootestr 19 Oldenzaal NL.08 7571 EJ",
    "addr:housenumber":"19;nl.08",
    "addr:postcode":"7571 ej",
    "addr:street":"Grootestr",
    "iso:country":"NL",
    "sg:address":"Grootestr 19",
    "sg:city":"Oldenzaal",
    "sg:orig_category":"Opticiens",
    "sg:phone":"+31 541 518 222",
    "sg:postcode":"7571 EJ",
    "sg:province":"NL.08",
    "sg:website":"http://www.moekotte-opticiens.nl",
    "wof:name":"Huis Ben Moekotte, Het",
    "wof:placetype":"venue"
},
  "geometry": {"coordinates":[6.9280772209,52.3127822876],"type":"Point"}
}