{
  "type": "Feature",
  "properties": {
    "addr:full":"Hoogoord 50 Amsterdam Zuidoost North Holland 1102 CB",
    "addr:housenumber":"50",
    "addr:postcode":"1102 cb",
    "addr:street":"Hoogoord",
    "iso:country":"NL",
    "sg:address":"Hoogoord 50",
    "sg:city":"Amsterdam Zuidoost",
    "sg:orig_category":"Kappers",
    "sg:phone":"+31 20 695 7506",
    "sg:postcode":"1102 CB",
    "sg:province":"North Holland",
    "wof:name":"Ismene Hairstudio",
    "wof:placetype":"venue"
},
  "geometry": {"coordinates":[4.9551110268,52.3128356934],"type":"Point"}
}