{
  "type": "Feature",
  "properties": {
    "iso:country":"NL",
    "sg:address":"Centralewg 12",
    "sg:city":"Geertruidenberg",
    "sg:orig_category":"Geluidshinderbestrijding",
    "sg:phone":"+31 162 519 703",
    "sg:postcode":"4931 NB",
    "sg:province":"Noord-Brabant",
    "sg:website":"http://www.geluid.com",
    "wof:name":"Acoustical Bv",
    "wof:placetype":"venue"
},
  "geometry": {"coordinates":[4.847403,51.696144],"type":"Point"}
}