{
  "type": "Feature",
  "properties": {
    "addr:full":"Seerob 7 Stiens Friesland 9051 VA",
    "addr:housenumber":"7",
    "addr:postcode":"9051",
    "addr:street":"Seerob",
    "iso:country":"NL",
    "sg:address":"Seerob 7",
    "sg:city":"Stiens",
    "sg:orig_category":"Verhuizingen",
    "sg:phone":"+31 58 257 3435",
    "sg:postcode":"9051 VA",
    "sg:province":"Friesland",
    "wof:name":"Swart Stiens-Hijum",
    "wof:placetype":"venue"
},
  "geometry": {"coordinates":[5.752933,53.267792],"type":"Point"}
}