{
  "type": "Feature",
  "properties": {
    "iso:country":"NL",
    "sg:address":"Oostzyde 161",
    "sg:city":"Zaandam",
    "sg:orig_category":"Sportverenigingen En Ontspannings- Verenigingen",
    "sg:phone":"+31 75 614 0605",
    "sg:postcode":"1502 BC",
    "sg:province":"North Holland",
    "wof:name":"Adrie",
    "wof:placetype":"venue"
},
  "geometry": {"coordinates":[4.82731,52.447559],"type":"Point"}
}