{
  "type": "Feature",
  "properties": {
    "addr:full":"Krommenbeemd 52 Eindhoven Noord-Brabant 5641 JX",
    "addr:housenumber":"52",
    "addr:postcode":"5641 jx",
    "addr:street":"Krommenbeemd",
    "iso:country":"NL",
    "sg:address":"Krommenbeemd 52",
    "sg:city":"Eindhoven",
    "sg:orig_category":"Meel - Fabrieken En Groothandel",
    "sg:phone":"+31 40 281 2146",
    "sg:postcode":"5641 JX",
    "sg:province":"Noord-Brabant",
    "wof:name":"Collse Watermolen",
    "wof:placetype":"venue"
},
  "geometry": {"coordinates":[5.523383,51.451809],"type":"Point"}
}