{
  "type": "Feature",
  "properties": {
    "iso:country":"NL",
    "sg:address":"Postbus 8056",
    "sg:city":"Posterholt",
    "sg:orig_category":"Voetbalverenigingen",
    "sg:phone":"+31 475 401 332",
    "sg:postcode":"6060 AB",
    "sg:province":"Limburg",
    "wof:name":"Psv'35",
    "wof:placetype":"venue"
},
  "geometry": {"coordinates":[6.03276,51.122669],"type":"Point"}
}