{
  "type": "Feature",
  "properties": {
    "iso:country":"NL",
    "sg:address":"Churchillweg 36 A",
    "sg:city":"Wageningen",
    "sg:classifiers":[
        {
            "category":"Fast Food",
            "type":"Food & Drink"
        }
    ],
    "sg:phone":"+31 17313131",
    "sg:postcode":"6706  A",
    "sg:province":"Gelderland",
    "sg:tags":[
        "afhaal",
        "restaurant"
    ],
    "wof:name":"United Pizza",
    "wof:placetype":"venue"
},
  "geometry": {"coordinates":[5.670154,51.971062],"type":"Point"}
}