{
  "type": "Feature",
  "properties": {
    "addr:full":"Biersteeg 17 Hilversum Noord-Holland 1211 GC",
    "addr:housenumber":"17",
    "addr:postcode":"1211 gc",
    "addr:street":"Biersteeg",
    "iso:country":"NL",
    "sg:address":"Biersteeg 17",
    "sg:city":"Hilversum",
    "sg:orig_category":"Kappers",
    "sg:phone":"+31 35 621 4057",
    "sg:postcode":"1211 GC",
    "sg:province":"Noord-Holland",
    "wof:name":"Stok'S Kappers",
    "wof:placetype":"venue"
},
  "geometry": {"coordinates":[5.17839,52.225079],"type":"Point"}
}