{
  "type": "Feature",
  "properties": {
    "addr:full":"Vragenderwg 70 Vragender Gelderland 7134 NA",
    "addr:housenumber":"70",
    "addr:postcode":"7134 na",
    "addr:street":"Vragenderwg;Gelderland",
    "iso:country":"NL",
    "sg:address":"Vragenderwg 70",
    "sg:city":"Vragender",
    "sg:orig_category":"Kunststof Ramen",
    "sg:phone":"+31 6 53642181",
    "sg:postcode":"7134 NA",
    "sg:province":"Gelderland",
    "wof:name":"Hiddink Vof",
    "wof:placetype":"venue"
},
  "geometry": {"coordinates":[6.593966,51.988503],"type":"Point"}
}