{
  "type": "Feature",
  "properties": {
    "addr:full":"Nunhemseweg 50 Haelen Limburg 6081 GJ",
    "addr:housenumber":"50",
    "addr:postcode":"6081 gj",
    "addr:street":"Nunhemseweg",
    "iso:country":"NL",
    "sg:address":"Nunhemseweg 50",
    "sg:city":"Haelen",
    "sg:orig_category":"Bloemen And Planten",
    "sg:phone":"+31 475 591 995",
    "sg:postcode":"6081 GJ",
    "sg:province":"Limburg",
    "wof:name":"Bloemenhuis Chris Clerkx Haelen",
    "wof:placetype":"venue"
},
  "geometry": {"coordinates":[5.959223,51.239658],"type":"Point"}
}