{
  "type": "Feature",
  "properties": {
    "addr:full":"Voorsterallee 114 Zutphen Gelderland 7203 DR",
    "addr:housenumber":"114",
    "addr:postcode":"7203 dr",
    "addr:street":"Voorsterallee;Gelderland",
    "iso:country":"NL",
    "sg:address":"Voorsterallee 114",
    "sg:city":"Zutphen",
    "sg:orig_category":"Houtvezelperserijen",
    "sg:phone":"+31 575 510 333",
    "sg:postcode":"7203 DR",
    "sg:province":"Gelderland",
    "sg:website":"http://www.rettenmaier.nl",
    "wof:name":"Rettemaier, J",
    "wof:placetype":"venue"
},
  "geometry": {"coordinates":[6.223985,52.150204],"type":"Point"}
}