{
  "type": "Feature",
  "properties": {
    "addr:full":"Molenstr 11 Etten Gld Gelderland 7075 BB",
    "addr:housenumber":"11",
    "addr:postcode":"7075 bb",
    "addr:street":"Molenstr;Gld Gelderland",
    "iso:country":"NL",
    "sg:address":"Molenstr 11",
    "sg:city":"Etten Gld",
    "sg:orig_category":"Plafonds",
    "sg:phone":"+31 315 323 053",
    "sg:postcode":"7075 BB",
    "sg:province":"Gelderland",
    "wof:name":"Kemperman, H",
    "wof:placetype":"venue"
},
  "geometry": {"coordinates":[6.334096,51.918282],"type":"Point"}
}