{
  "type": "Feature",
  "properties": {
    "addr:full":"Kooikersweg 9 'S Hertogenbosch Noord-Brabant 5223 KE",
    "addr:housenumber":"9 ' s",
    "addr:postcode":"5223 ke",
    "addr:street":"Kooikersweg",
    "iso:country":"NL",
    "sg:address":"Kooikersweg 9",
    "sg:city":"'S Hertogenbosch",
    "sg:orig_category":"Volwassenenonderwijs",
    "sg:phone":"+31 73 621 5400",
    "sg:postcode":"5223 KE",
    "sg:province":"Noord-Brabant",
    "wof:name":"Frederik Hendrik College",
    "wof:placetype":"venue"
},
  "geometry": {"coordinates":[5.272476,51.694855],"type":"Point"}
}