{
  "type": "Feature",
  "properties": {
    "iso:country":"NL",
    "sg:address":"Vredehagen 1/11Hg",
    "sg:city":"Rotterdam",
    "sg:orig_category":"Maatschappelijk Werk",
    "sg:phone":"+31 10 479 6635",
    "sg:postcode":"3078 BR",
    "sg:province":"South Holland",
    "wof:name":"M & M Consult",
    "wof:placetype":"venue"
},
  "geometry": {"coordinates":[4.56024,51.888489],"type":"Point"}
}