{
  "type": "Feature",
  "properties": {
    "addr:full":"3E Oosterparkstr 244 Amsterdam North Holland 1092 EL",
    "addr:housenumber":"244",
    "addr:postcode":"1092 el",
    "addr:street":"3E Oosterparkstr",
    "iso:country":"NL",
    "sg:address":"3E Oosterparkstr 244",
    "sg:city":"Amsterdam",
    "sg:orig_category":"Grafisch Ontwerpers",
    "sg:phone":"+31 20 668 2638",
    "sg:postcode":"1092 EL",
    "sg:province":"North Holland",
    "wof:name":"Nieuwenhuizen",
    "wof:placetype":"venue"
},
  "geometry": {"coordinates":[4.923301,52.35815],"type":"Point"}
}