{
  "type": "Feature",
  "properties": {
    "addr:full":"Kranenhoutlaan 2 Oostvoorne South Holland 3233 KC",
    "addr:housenumber":"2",
    "addr:postcode":"3233 kc",
    "addr:street":"Kranenhoutlaan",
    "iso:country":"NL",
    "sg:address":"Kranenhoutlaan 2",
    "sg:city":"Oostvoorne",
    "sg:orig_category":"Boekenuitgeverijen",
    "sg:phone":"+31 181 482 587",
    "sg:postcode":"3233 KC",
    "sg:province":"South Holland",
    "wof:name":"Uitgeverij De Klokkestoel",
    "wof:placetype":"venue"
},
  "geometry": {"coordinates":[4.095645,51.900871],"type":"Point"}
}