{
  "type": "Feature",
  "properties": {
    "addr:full":"C Slegersstr 2 Zandvoort Noord-Holland 2042 GP",
    "addr:housenumber":"2",
    "addr:postcode":"2042 gp",
    "addr:street":"Zandvoort",
    "iso:country":"NL",
    "sg:address":"C Slegersstr 2",
    "sg:city":"Zandvoort",
    "sg:orig_category":"Schoenen - Reparaties",
    "sg:phone":"+31 23 571 5449",
    "sg:postcode":"2042 GP",
    "sg:province":"Noord-Holland",
    "wof:name":"Footcare",
    "wof:placetype":"venue"
},
  "geometry": {"coordinates":[4.532294,52.371593],"type":"Point"}
}