{
  "type": "Feature",
  "properties": {
    "addr:full":"Ambachtsweg 6 Tynaarlo Provincie Drenthe 9482 WD",
    "addr:housenumber":"6",
    "addr:postcode":"9482",
    "addr:street":"Ambachtsweg;Provincie Drenthe",
    "iso:country":"NL",
    "sg:address":"Ambachtsweg 6",
    "sg:city":"Tynaarlo",
    "sg:orig_category":"Verhuur Catering-, Feest- En Evenementbenodigdheden",
    "sg:phone":"+31 592 544 496",
    "sg:postcode":"9482 WD",
    "sg:province":"Provincie Drenthe",
    "wof:name":"Amusement Automaten Starplay",
    "wof:placetype":"venue"
},
  "geometry": {"coordinates":[6.599252,53.081837],"type":"Point"}
}