{
  "type": "Feature",
  "properties": {
    "addr:full":"Voorstraat 56 Harlingen Provincie Friesland 8861 BM",
    "addr:housenumber":"56",
    "addr:postcode":"8861 bm",
    "addr:street":"Voorstraat;Provincie Friesland",
    "iso:country":"NL",
    "sg:address":"Voorstraat 56",
    "sg:city":"Harlingen",
    "sg:orig_category":"Musea And Historische Gebouwen",
    "sg:phone":"+31 517 413 658",
    "sg:postcode":"8861 BM",
    "sg:province":"Provincie Friesland",
    "wof:name":"Museum Het Hannemahuis",
    "wof:placetype":"venue"
},
  "geometry": {"coordinates":[5.419297,53.174664],"type":"Point"}
}