{
  "type": "Feature",
  "properties": {
    "iso:country":"NL",
    "sg:address":"Benedenrywg 160",
    "sg:city":"Ridderkerk",
    "sg:orig_category":"Kampeerauto'S",
    "sg:phone":"+31 180 416 253",
    "sg:postcode":"2987 VB",
    "sg:province":"Zuid-Holland",
    "wof:name":"Picomyo",
    "wof:placetype":"venue"
},
  "geometry": {"coordinates":[4.5849609375,51.8942337036],"type":"Point"}
}