{
  "type": "Feature",
  "properties": {
    "addr:full":"Rijckevorsel V Kesselln 2 Sint Oedenrode Noord-Brabant 5491 GE",
    "addr:housenumber":"2;oedenrode",
    "addr:postcode":"5491",
    "addr:street":"Rijckevorsel;Kesselln",
    "iso:country":"NL",
    "sg:address":"Rijckevorsel V Kesselln 2",
    "sg:city":"Sint Oedenrode",
    "sg:classifiers":[
        {
            "category":"Education",
            "subcategory":"Preschool",
            "type":"Public Place"
        }
    ],
    "sg:phone":"+31 413 472 517",
    "sg:postcode":"5491 GE",
    "sg:province":"Noord-Brabant",
    "sg:tags":[
        "kleuteronderwijs",
        "basis-"
    ],
    "wof:name":"Odaschool Voor Basisonderwijs",
    "wof:placetype":"venue"
},
  "geometry": {"coordinates":[5.407185,51.580475],"type":"Point"}
}