{
  "type": "Feature",
  "properties": {
    "addr:full":"Surinamestraat 7 Leiden Zuid-Holland 2315 XC",
    "addr:housenumber":"7",
    "addr:postcode":"2315 xc",
    "addr:street":"Surinamestraat",
    "iso:country":"NL",
    "sg:address":"Surinamestraat 7",
    "sg:city":"Leiden",
    "sg:orig_category":"Apothekers",
    "sg:phone":"+31 71 521 4060",
    "sg:postcode":"2315 XC",
    "sg:province":"Zuid-Holland",
    "wof:name":"Kooi Apotheek Bv",
    "wof:placetype":"venue"
},
  "geometry": {"coordinates":[4.508361,52.166565],"type":"Point"}
}