{
  "type": "Feature",
  "properties": {
    "iso:country":"NL",
    "sg:address":"Maasdijk 34",
    "sg:city":"Rijswijk Nb",
    "sg:orig_category":"Verhuur Voertuigen Behalve Auto'S",
    "sg:phone":"+31 183 443 400",
    "sg:postcode":"4284 VB",
    "sg:province":"Noord-Brabant",
    "wof:name":"Supporter-Aanhangwagenverhuur",
    "wof:placetype":"venue"
},
  "geometry": {"coordinates":[5.02305,51.800587],"type":"Point"}
}