{
  "type": "Feature",
  "properties": {
    "addr:full":"Rysbergsebaan 9 Rysbergen North Brabant 4891 PZ",
    "addr:housenumber":"9",
    "addr:postcode":"4891 pz",
    "addr:street":"Rysbergsebaan",
    "iso:country":"NL",
    "sg:address":"Rysbergsebaan 9",
    "sg:city":"Rysbergen",
    "sg:orig_category":"Partyservice",
    "sg:phone":"+31 76 596 2068",
    "sg:postcode":"4891 PZ",
    "sg:province":"North Brabant",
    "wof:name":"Galderzicht, Hoeve",
    "wof:placetype":"venue"
},
  "geometry": {"coordinates":[4.70113,51.51572],"type":"Point"}
}