{
  "type": "Feature",
  "properties": {
    "addr:full":"Postbus 1 Maastricht Airport 6199 ZG",
    "addr:housenumber":"1;6199",
    "addr:postcode":"zg",
    "addr:street":"Postbus",
    "iso:country":"NL",
    "sg:address":"Postbus 1",
    "sg:city":"Maastricht Airport",
    "sg:orig_category":"Luchthavens En Vliegvelden",
    "sg:phone":"+31 43 358 9999",
    "sg:postcode":"6199 ZG",
    "sg:website":"http://www.maa.nl",
    "wof:name":"Maastricht Aachen Airport",
    "wof:placetype":"venue"
},
  "geometry": {"coordinates":[5.778855,50.924934],"type":"Point"}
}