{
  "type": "Feature",
  "properties": {
    "addr:full":"Burg De Grauwstr 4 Baarle Nassau Noord-Brabant 5111 VB",
    "addr:housenumber":"4",
    "addr:postcode":"5111 vb",
    "addr:street":"Baarle Nassau",
    "iso:country":"NL",
    "sg:address":"Burg De Grauwstr 4",
    "sg:city":"Baarle Nassau",
    "sg:orig_category":"Fotozaken",
    "sg:phone":"+31 13 507 7377",
    "sg:postcode":"5111 VB",
    "sg:province":"Noord-Brabant",
    "wof:name":"Spector",
    "wof:placetype":"venue"
},
  "geometry": {"coordinates":[4.931368,51.444317],"type":"Point"}
}