{
  "type": "Feature",
  "properties": {
    "addr:full":"Krabbendijkestraat 81 Rotterdam Zuid-Holland 3086 LP",
    "addr:housenumber":"81",
    "addr:postcode":"3086 lp",
    "addr:street":"Krabbendijkestraat",
    "iso:country":"NL",
    "sg:address":"Krabbendijkestraat 81",
    "sg:city":"Rotterdam",
    "sg:orig_category":"Schoenen",
    "sg:phone":"+31 10 480 3690",
    "sg:postcode":"3086 LP",
    "sg:province":"Zuid-Holland",
    "wof:name":"J.J. Van Liesdonk",
    "wof:placetype":"venue"
},
  "geometry": {"coordinates":[4.466336,51.874256],"type":"Point"}
}