{
  "type": "Feature",
  "properties": {
    "addr:full":"Handelswg 5 Andyk Noord-Holland 1619 BJ",
    "addr:housenumber":"5",
    "addr:postcode":"1619 bj",
    "addr:street":"Handelswg",
    "iso:country":"NL",
    "sg:address":"Handelswg 5",
    "sg:city":"Andyk",
    "sg:orig_category":"Land- En Tuinbouw - Mechanisatie",
    "sg:phone":"+31 228 597 777",
    "sg:postcode":"1619 BJ",
    "sg:province":"Noord-Holland",
    "wof:name":"All Round Bv",
    "wof:placetype":"venue"
},
  "geometry": {"coordinates":[5.22648,52.740311],"type":"Point"}
}