{
  "type": "Feature",
  "properties": {
    "addr:full":"Oranjeln 83 Ryswyk Zh Zuid-Holland 2281 GC",
    "addr:housenumber":"83",
    "addr:postcode":"2281 gc",
    "addr:street":"Oranjeln",
    "iso:country":"NL",
    "sg:address":"Oranjeln 83",
    "sg:city":"Ryswyk Zh",
    "sg:orig_category":"Beeldende Kunstenaars",
    "sg:phone":"+31 70 398 8849",
    "sg:postcode":"2281 GC",
    "sg:province":"Zuid-Holland",
    "wof:name":"Kempen-Jarnicka, Iska Van",
    "wof:placetype":"venue"
},
  "geometry": {"coordinates":[4.341704,52.056934],"type":"Point"}
}