{
  "type": "Feature",
  "properties": {
    "iso:country":"NL",
    "sg:address":"Leeuwerikenveld 10",
    "sg:city":"Emmen",
    "sg:orig_category":"Kinderopvang",
    "sg:phone":"+31 591 679 196",
    "sg:postcode":"7827 DZ",
    "sg:province":"Drenthe",
    "wof:name":"Speeldoos, De",
    "wof:placetype":"venue"
},
  "geometry": {"coordinates":[6.896693,52.745533],"type":"Point"}
}