{
  "type": "Feature",
  "properties": {
    "addr:full":"Raadhuisplein 1 Landgraaf Limburg 6371 LA",
    "addr:housenumber":"1",
    "addr:postcode":"6371 la",
    "addr:street":"Raadhuisplein",
    "iso:country":"NL",
    "sg:address":"Raadhuisplein 1",
    "sg:city":"Landgraaf",
    "sg:orig_category":"Overheidsdiensten",
    "sg:phone":"+31 45 569 5222",
    "sg:postcode":"6371 LA",
    "sg:province":"Limburg",
    "wof:name":"Gemeente Landgraaf",
    "wof:placetype":"venue"
},
  "geometry": {"coordinates":[6.024189949,50.9054489136],"type":"Point"}
}