{
  "type": "Feature",
  "properties": {
    "addr:full":"Weteringschans 159K Amsterdam North Holland 1017 SE",
    "addr:housenumber":"159k",
    "addr:postcode":"1017 se",
    "addr:street":"Weteringschans",
    "iso:country":"NL",
    "sg:address":"Weteringschans 159K",
    "sg:city":"Amsterdam",
    "sg:orig_category":"Grafisch Ontwerpers",
    "sg:phone":"+31 20 671 8326",
    "sg:postcode":"1017 SE",
    "sg:province":"North Holland",
    "wof:name":"Kindt Studio",
    "wof:placetype":"venue"
},
  "geometry": {"coordinates":[4.890294,52.359783],"type":"Point"}
}