{
  "type": "Feature",
  "properties": {
    "addr:full":"Rotterdamseweg 37 Zwijndrecht South Holland 3332 AC",
    "addr:housenumber":"37",
    "addr:postcode":"3332 ac",
    "addr:street":"Rotterdamseweg",
    "iso:country":"NL",
    "sg:address":"Rotterdamseweg 37",
    "sg:city":"Zwijndrecht",
    "sg:classifiers":[
        {
            "category":"Shopping",
            "subcategory":"Gifts & Souvenirs",
            "type":"Retail Goods"
        }
    ],
    "sg:phone":"+31 78 612 9136",
    "sg:postcode":"3332 AC",
    "sg:province":"South Holland",
    "sg:tags":[
        "geschenken"
    ],
    "wof:name":"Wereldwinkel",
    "wof:placetype":"venue"
},
  "geometry": {"coordinates":[4.655788,51.818596],"type":"Point"}
}