{
  "type": "Feature",
  "properties": {
    "addr:full":"1E Graaf Van Loonstraat 56 Venlo Limburg 5921 JC",
    "addr:housenumber":"56",
    "addr:postcode":"5921 jc",
    "addr:street":"1E Graaf Van Loonstraat",
    "iso:country":"NL",
    "sg:address":"1E Graaf Van Loonstraat 56",
    "sg:city":"Venlo",
    "sg:orig_category":"Kappers",
    "sg:phone":"+31 77 382 1361",
    "sg:postcode":"5921 JC",
    "sg:province":"Limburg",
    "wof:name":"Kapsalon Simais",
    "wof:placetype":"venue"
},
  "geometry": {"coordinates":[6.1527152061,51.3684616089],"type":"Point"}
}