{
  "type": "Feature",
  "properties": {
    "addr:full":"De Kiel 30 Drachten Friesland 9206 BG",
    "addr:housenumber":"30",
    "addr:postcode":"9206",
    "addr:street":"De Kiel",
    "iso:country":"NL",
    "sg:address":"De Kiel 30",
    "sg:city":"Drachten",
    "sg:orig_category":"Drukkerijen",
    "sg:phone":"+31 512 544 504",
    "sg:postcode":"9206 BG",
    "sg:province":"Friesland",
    "wof:name":"Pk 84",
    "wof:placetype":"venue"
},
  "geometry": {"coordinates":[6.068481,53.112881],"type":"Point"}
}