{
  "type": "Feature",
  "properties": {
    "addr:full":"Mariastraat 28 Apeldoorn Gelderland 7311 HL",
    "addr:housenumber":"28",
    "addr:postcode":"7311 hl",
    "addr:street":"Mariastraat;Gelderland",
    "iso:country":"NL",
    "sg:address":"Mariastraat 28",
    "sg:city":"Apeldoorn",
    "sg:orig_category":"Warenhuizen",
    "sg:phone":"+31 55 576 1738",
    "sg:postcode":"7311 HL",
    "sg:province":"Gelderland",
    "wof:name":"Giraffe Bv",
    "wof:placetype":"venue"
},
  "geometry": {"coordinates":[5.9608721733,52.2137489319],"type":"Point"}
}