{
  "type": "Feature",
  "properties": {
    "addr:full":"Wilhelminasngl 10 Weert Limburg 6001 GT",
    "addr:housenumber":"10",
    "addr:postcode":"6001 gt",
    "addr:street":"Wilhelminasngl",
    "iso:country":"NL",
    "sg:address":"Wilhelminasngl 10",
    "sg:city":"Weert",
    "sg:orig_category":"Postkantoren",
    "sg:phone":"+31 495 533 909",
    "sg:postcode":"6001 GT",
    "sg:province":"Limburg",
    "sg:website":"http://www.postkantoor.nl",
    "wof:name":"Postkantoor",
    "wof:placetype":"venue"
},
  "geometry": {"coordinates":[5.703781,51.255016],"type":"Point"}
}