{
  "type": "Feature",
  "properties": {
    "addr:full":"M Wibautstr 11 Groningen Groningen 9728 MH",
    "addr:housenumber":"11",
    "addr:postcode":"9728 mh",
    "iso:country":"NL",
    "sg:address":"M Wibautstr 11",
    "sg:city":"Groningen",
    "sg:orig_category":"Woningtextiel - Fabrieken En Groothandel",
    "sg:phone":"+31 50 526 7597",
    "sg:postcode":"9728 MH",
    "sg:province":"Groningen",
    "wof:name":"Cletex",
    "wof:placetype":"venue"
},
  "geometry": {"coordinates":[6.5456409454,53.1854515076],"type":"Point"}
}