{
  "type": "Feature",
  "properties": {
    "iso:country":"NL",
    "sg:address":"Weypoort 68",
    "sg:city":"Nieuwerbrug",
    "sg:orig_category":"Pluimveebedrijven En -Handelaren",
    "sg:phone":"+31 6 51398787",
    "sg:postcode":"2415 BZ",
    "sg:province":"Zuid-Holland",
    "wof:name":"Elten, Van",
    "wof:placetype":"venue"
},
  "geometry": {"coordinates":[4.812501,52.077511],"type":"Point"}
}