{
  "type": "Feature",
  "properties": {
    "addr:full":"Oeverwal 3 Maastricht Limburg 6221 EN",
    "addr:housenumber":"3",
    "addr:postcode":"6221 en",
    "addr:street":"Oeverwal",
    "iso:country":"NL",
    "sg:address":"Oeverwal 3",
    "sg:city":"Maastricht",
    "sg:orig_category":"Bierproductie And Brouwerijen",
    "sg:phone":"+31 43 321 6057",
    "sg:postcode":"6221 EN",
    "sg:province":"Limburg",
    "wof:name":"Stadsbrouwerij De Ridder",
    "wof:placetype":"venue"
},
  "geometry": {"coordinates":[5.697626,50.8503],"type":"Point"}
}