{
  "type": "Feature",
  "properties": {
    "addr:full":"Hanzewg 50 Deventer Overijssel 7418 AT",
    "addr:housenumber":"50",
    "addr:postcode":"7418",
    "addr:street":"Hanzewg",
    "iso:country":"NL",
    "sg:address":"Hanzewg 50",
    "sg:city":"Deventer",
    "sg:orig_category":"Bliksembeveiliging",
    "sg:phone":"+31 570 622 507",
    "sg:postcode":"7418 AT",
    "sg:province":"Overijssel",
    "sg:website":"http://www.schaapbliksem.nl",
    "wof:name":"Schaap Bliksembeveiliging",
    "wof:placetype":"venue"
},
  "geometry": {"coordinates":[6.180267,52.25164],"type":"Point"}
}