{
  "type": "Feature",
  "properties": {
    "addr:full":"Duinweg 9 Schoorl Noord-Holland 1871 AC",
    "addr:housenumber":"9",
    "addr:postcode":"1871 ac",
    "addr:street":"Duinweg",
    "iso:country":"NL",
    "sg:address":"Duinweg 9",
    "sg:city":"Schoorl",
    "sg:classifiers":[
        {
            "category":"Retail",
            "subcategory":"Photofinishing",
            "type":"Services"
        }
    ],
    "sg:phone":"+31 72 509 1547",
    "sg:postcode":"1871 AC",
    "sg:province":"Noord-Holland",
    "sg:tags":[
        "foto",
        "film"
    ],
    "wof:name":"Foto Tabak Nettie Evers",
    "wof:placetype":"venue"
},
  "geometry": {"coordinates":[4.694291,52.69968],"type":"Point"}
}