{
  "type": "Feature",
  "properties": {
    "addr:full":"Maasstraat 17 Wessem Limburg 6019 BA",
    "addr:housenumber":"17",
    "addr:postcode":"6019 ba",
    "addr:street":"Maasstraat",
    "iso:country":"NL",
    "sg:address":"Maasstraat 17",
    "sg:city":"Wessem",
    "sg:orig_category":"Dierenspeciaalzaken",
    "sg:phone":"+31 475 561 383",
    "sg:postcode":"6019 BA",
    "sg:province":"Limburg",
    "wof:name":"Dierenspeciaalzaak Gielen",
    "wof:placetype":"venue"
},
  "geometry": {"coordinates":[5.882838,51.159412],"type":"Point"}
}