{
  "type": "Feature",
  "properties": {
    "addr:full":"Beusichemseweg 58 'T Goy Utrecht 3997 MK",
    "addr:housenumber":"58",
    "addr:postcode":"3997",
    "addr:street":"Beusichemseweg;T",
    "iso:country":"NL",
    "sg:address":"Beusichemseweg 58",
    "sg:city":"'T Goy",
    "sg:orig_category":"Goederenvervoer Over De Weg",
    "sg:phone":"+31 30 601 2024",
    "sg:postcode":"3997 MK",
    "sg:province":"Utrecht",
    "wof:name":"Vof De Rooy",
    "wof:placetype":"venue"
},
  "geometry": {"coordinates":[5.21678,52.004368],"type":"Point"}
}