{
  "type": "Feature",
  "properties": {
    "addr:full":"Oppenheimstraat 2 Leiden Zuid-Holland 2313 JE",
    "addr:housenumber":"2",
    "addr:postcode":"2313 je",
    "addr:street":"Oppenheimstraat",
    "iso:country":"NL",
    "sg:address":"Oppenheimstraat 2",
    "sg:city":"Leiden",
    "sg:classifiers":[
        {
            "category":"Education",
            "subcategory":"Preschool",
            "type":"Public Place"
        }
    ],
    "sg:phone":"+31 71 513 1061",
    "sg:postcode":"2313 JE",
    "sg:province":"Zuid-Holland",
    "sg:tags":[
        "kleuteronderwijs",
        "basis-"
    ],
    "wof:name":"Peuterspeelzaal Olleke Bolleke",
    "wof:placetype":"venue"
},
  "geometry": {"coordinates":[4.505671,52.150848],"type":"Point"}
}