{
  "type": "Feature",
  "properties": {
    "addr:full":"C Porterhof 24 Hoorn Nh North Holland 1628 TG",
    "addr:housenumber":"24",
    "addr:postcode":"1628 tg",
    "addr:street":"C Porterhof;Nh North",
    "iso:country":"NL",
    "sg:address":"C Porterhof 24",
    "sg:city":"Hoorn Nh",
    "sg:orig_category":"Hoefsmederijen",
    "sg:phone":"+31 229 211 750",
    "sg:postcode":"1628 TG",
    "sg:province":"North Holland",
    "wof:name":"Werf, G Van Der",
    "wof:placetype":"venue"
},
  "geometry": {"coordinates":[5.099078,52.652607],"type":"Point"}
}