{
  "type": "Feature",
  "properties": {
    "addr:full":"Bongerd 9 Lelystad Flevoland 8212 BA",
    "addr:housenumber":"9",
    "addr:postcode":"8212 ba",
    "addr:street":"Bongerd;Flevoland",
    "iso:country":"NL",
    "sg:address":"Bongerd 9",
    "sg:city":"Lelystad",
    "sg:orig_category":"Jachten - Schilderwerken En Onderhoud",
    "sg:phone":"+31 320 234 398",
    "sg:postcode":"8212 BA",
    "sg:province":"Flevoland",
    "wof:name":"Wansinck, R",
    "wof:placetype":"venue"
},
  "geometry": {"coordinates":[5.496891,52.514423],"type":"Point"}
}