{
  "type": "Feature",
  "properties": {
    "addr:full":"Korenbloemweg 34 Alphen A/D Rijn Zuid-Holland 2403 GC",
    "addr:housenumber":"34",
    "addr:postcode":"2403 gc",
    "addr:street":"Korenbloemweg",
    "iso:country":"NL",
    "sg:address":"Korenbloemweg 34",
    "sg:city":"Alphen A/D Rijn",
    "sg:orig_category":"Bedrijfs- And Managementsconsultants",
    "sg:phone":"+31 172 436 682",
    "sg:postcode":"2403 GC",
    "sg:province":"Zuid-Holland",
    "wof:name":"Indispekt",
    "wof:placetype":"venue"
},
  "geometry": {"coordinates":[4.685064,52.147152],"type":"Point"}
}