{
  "type": "Feature",
  "properties": {
    "iso:country":"NL",
    "sg:address":"De Schoppe 84",
    "sg:city":"Almelo",
    "sg:orig_category":"Verzekeringen",
    "sg:phone":"+31 546 826 000",
    "sg:postcode":"7609 CC",
    "sg:province":"NL.08",
    "wof:name":"H.J.G. Rohring Assurantie- En Bemidd. Bu",
    "wof:placetype":"venue"
},
  "geometry": {"coordinates":[6.6289000511,52.3412513733],"type":"Point"}
}