{
  "type": "Feature",
  "properties": {
    "iso:country":"NL",
    "sg:address":"Oosterhamrikkd 80",
    "sg:city":"Groningen",
    "sg:orig_category":"Goudsmeden En Zilversmeden",
    "sg:phone":"+31 50 577 1658",
    "sg:postcode":"9714 BG",
    "sg:province":"Groningen",
    "wof:name":"Venema, Fa",
    "wof:placetype":"venue"
},
  "geometry": {"coordinates":[6.576583,53.23032],"type":"Point"}
}