{
  "type": "Feature",
  "properties": {
    "addr:full":"Bemuurde Weerd Oz 13 Utrecht Utrecht 3514 AN",
    "addr:housenumber":"13",
    "addr:postcode":"3514 an",
    "addr:street":"Bemuurde Weerd Oz",
    "iso:country":"NL",
    "sg:address":"Bemuurde Weerd Oz 13",
    "sg:city":"Utrecht",
    "sg:orig_category":"Zalenverhuur",
    "sg:phone":"+31 30 272 4806",
    "sg:postcode":"3514 AN",
    "sg:province":"Utrecht",
    "sg:website":"http://www.sophie'splace.nl",
    "wof:name":"Sophie'S Palace",
    "wof:placetype":"venue"
},
  "geometry": {"coordinates":[5.115408,52.097404],"type":"Point"}
}