{
  "type": "Feature",
  "properties": {
    "iso:country":"NL",
    "sg:address":"Emmakd 159",
    "sg:city":"Leeuwarden",
    "sg:orig_category":"Adviesbureaus Bedrijfsorganisatie",
    "sg:phone":"+31 58 212 2237",
    "sg:postcode":"8921 CB",
    "sg:province":"Friesland",
    "sg:website":"http://www.oporde.nl",
    "wof:name":"Op Orde",
    "wof:placetype":"venue"
},
  "geometry": {"coordinates":[5.81099,53.205589],"type":"Point"}
}