{
  "type": "Feature",
  "properties": {
    "iso:country":"NL",
    "sg:address":"Spaarnwouderwg 1155",
    "sg:city":"Vyfhuizen",
    "sg:orig_category":"Keukens",
    "sg:phone":"+31 23 558 3242",
    "sg:postcode":"2141 BN",
    "sg:province":"Noord-Holland",
    "wof:name":"Finesse Keukens",
    "wof:placetype":"venue"
},
  "geometry": {"coordinates":[4.700494,52.373943],"type":"Point"}
}