{
  "type": "Feature",
  "properties": {
    "iso:country":"NL",
    "sg:address":"Prins Hendrikkade 12",
    "sg:city":"Broek Op Langedijk",
    "sg:orig_category":"Discountwinkels",
    "sg:phone":"+31 226 320 007",
    "sg:postcode":"1721 AK",
    "sg:province":"North Holland",
    "wof:name":"Anja Boon-Blokker",
    "wof:placetype":"venue"
},
  "geometry": {"coordinates":[4.808155,52.674171],"type":"Point"}
}