{
  "type": "Feature",
  "properties": {
    "addr:full":"Plantage Badlaan 24/1 Amsterdam Noord-Holland 1018 TJ",
    "addr:housenumber":"24 / 1",
    "addr:postcode":"1018 tj",
    "addr:street":"Plantage Badlaan",
    "iso:country":"NL",
    "sg:address":"Plantage Badlaan 24/1",
    "sg:city":"Amsterdam",
    "sg:orig_category":"Chemische Producten Gh",
    "sg:phone":"+31 20 427 1323",
    "sg:postcode":"1018 TJ",
    "sg:province":"Noord-Holland",
    "wof:name":"Kramer Plastics En Polymeren",
    "wof:placetype":"venue"
},
  "geometry": {"coordinates":[4.917092,52.364277],"type":"Point"}
}