{
  "type": "Feature",
  "properties": {
    "addr:full":"Vd Clusenstr 6 Valkenswaard Noord-Brabant 5553 EL",
    "addr:housenumber":"6",
    "addr:postcode":"5553 el",
    "iso:country":"NL",
    "sg:address":"Vd Clusenstr 6",
    "sg:city":"Valkenswaard",
    "sg:orig_category":"Machinefabrieken",
    "sg:phone":"+31 40 204 9402",
    "sg:postcode":"5553 EL",
    "sg:province":"Noord-Brabant",
    "wof:name":"Techpro Ltd",
    "wof:placetype":"venue"
},
  "geometry": {"coordinates":[5.470421,51.355766],"type":"Point"}
}