{
  "type": "Feature",
  "properties": {
    "addr:full":"De Kluft 7 Spyk Gn Groningen 9909 CA",
    "addr:housenumber":"7",
    "addr:postcode":"gn;9909 ca",
    "addr:street":"De Kluft",
    "iso:country":"NL",
    "sg:address":"De Kluft 7",
    "sg:city":"Spyk Gn",
    "sg:orig_category":"Administratie- En Boekhoudkantoren",
    "sg:phone":"+31 596 591 966",
    "sg:postcode":"9909 CA",
    "sg:province":"Groningen",
    "wof:name":"Falcom",
    "wof:placetype":"venue"
},
  "geometry": {"coordinates":[6.83624,53.388969],"type":"Point"}
}