{
  "type": "Feature",
  "properties": {
    "addr:full":"Nyverheidswg 29 Elst Gld Gelderland 6662 NG",
    "addr:housenumber":"29",
    "addr:postcode":"6662 ng",
    "addr:street":"Nyverheidswg;Gld Gelderland",
    "iso:country":"NL",
    "sg:address":"Nyverheidswg 29",
    "sg:city":"Elst Gld",
    "sg:orig_category":"Munten En Penningen",
    "sg:phone":"+31 481 366 392",
    "sg:postcode":"6662 NG",
    "sg:province":"Gelderland",
    "wof:name":"Vip Europe Bv",
    "wof:placetype":"venue"
},
  "geometry": {"coordinates":[5.867452,51.913685],"type":"Point"}
}