{
  "type": "Feature",
  "properties": {
    "addr:full":"Schinkelwaard 20 Alkmaar North Holland 1824 DS",
    "addr:housenumber":"20",
    "addr:postcode":"1824 ds",
    "addr:street":"Schinkelwaard",
    "iso:country":"NL",
    "sg:address":"Schinkelwaard 20",
    "sg:city":"Alkmaar",
    "sg:orig_category":"Overheidsdiensten",
    "sg:phone":"+31 72 518 7600",
    "sg:postcode":"1824 DS",
    "sg:province":"North Holland",
    "wof:name":"Stigas Guo Uvi Bv",
    "wof:placetype":"venue"
},
  "geometry": {"coordinates":[4.7618589401,52.6448554993],"type":"Point"}
}