{
  "type": "Feature",
  "properties": {
    "addr:full":"Postbus 36 Zwaag North Holland 1689 ZG",
    "addr:housenumber":"36;1689",
    "addr:postcode":"zg",
    "addr:street":"Postbus;Holland",
    "iso:country":"NL",
    "sg:address":"Postbus 36",
    "sg:city":"Zwaag",
    "sg:orig_category":"Groepsaccommodaties",
    "sg:phone":"+31 6 55325751",
    "sg:postcode":"1689 ZG",
    "sg:province":"North Holland",
    "sg:website":"http://www.vita-nova.nl",
    "wof:name":"Vita Nova",
    "wof:placetype":"venue"
},
  "geometry": {"coordinates":[5.074855,52.668491],"type":"Point"}
}