{
  "type": "Feature",
  "properties": {
    "addr:full":"St Pieterstr 43 Kerkrade Limburg 6463 CR",
    "addr:housenumber":"43",
    "addr:postcode":"6463 cr",
    "iso:country":"NL",
    "sg:address":"St Pieterstr 43",
    "sg:city":"Kerkrade",
    "sg:orig_category":"Kappers",
    "sg:phone":"+31 45 535 1736",
    "sg:postcode":"6463 CR",
    "sg:province":"Limburg",
    "wof:name":"Lascala Hairfashion",
    "wof:placetype":"venue"
},
  "geometry": {"coordinates":[6.065447,50.875248],"type":"Point"}
}