{
  "type": "Feature",
  "properties": {
    "iso:country":"NL",
    "sg:address":"Middenwg 156",
    "sg:city":"Middenbeemster",
    "sg:orig_category":"Schilders",
    "sg:phone":"+31 299 683 220",
    "sg:postcode":"1462 HL",
    "sg:province":"Noord-Holland",
    "wof:name":"Clous, T",
    "wof:placetype":"venue"
},
  "geometry": {"coordinates":[4.912619,52.547688],"type":"Point"}
}