{
  "type": "Feature",
  "properties": {
    "iso:country":"NL",
    "sg:address":"F Bolstr 91",
    "sg:city":"Amsterdam",
    "sg:orig_category":"Warenhuizen",
    "sg:phone":"+31 900 9800",
    "sg:postcode":"1072 LD",
    "sg:province":"Noord-Holland",
    "sg:website":"http://www.kijkshop.nl",
    "wof:name":"Kijkshop",
    "wof:placetype":"venue"
},
  "geometry": {"coordinates":[4.8906698227,52.3540115356],"type":"Point"}
}