{
  "type": "Feature",
  "properties": {
    "addr:full":"Voorstr 72 Katwyk Zh South Holland 2225 ES",
    "addr:housenumber":"72;zh",
    "addr:postcode":"2225 es",
    "addr:street":"Voorstr",
    "iso:country":"NL",
    "sg:address":"Voorstr 72",
    "sg:city":"Katwyk Zh",
    "sg:orig_category":"Verenigingsgebouwen",
    "sg:phone":"+31 71 401 2784",
    "sg:postcode":"2225 ES",
    "sg:province":"South Holland",
    "wof:name":"Jeugdhuis Van De Ned Herv Gem",
    "wof:placetype":"venue"
},
  "geometry": {"coordinates":[4.399164,52.203297],"type":"Point"}
}