{
  "type": "Feature",
  "properties": {
    "addr:full":"Stationsstraat 64 Deurne North Brabant 5751 HG",
    "addr:housenumber":"64",
    "addr:postcode":"5751 hg",
    "addr:street":"Stationsstraat",
    "iso:country":"NL",
    "sg:address":"Stationsstraat 64",
    "sg:city":"Deurne",
    "sg:classifiers":[
        {
            "category":"Fast Food",
            "type":"Food & Drink"
        }
    ],
    "sg:phone":"+31 493 317 581",
    "sg:postcode":"5751 HG",
    "sg:province":"North Brabant",
    "sg:tags":[
        "afhaal",
        "restaurant"
    ],
    "wof:name":"Vof Van Veghel",
    "wof:placetype":"venue"
},
  "geometry": {"coordinates":[5.790084,51.461079],"type":"Point"}
}