{
  "type": "Feature",
  "properties": {
    "iso:country":"NL",
    "sg:address":"V Woustr 12",
    "sg:city":"Amsterdam",
    "sg:orig_category":"Verlichting",
    "sg:phone":"+31 20 679 1829",
    "sg:postcode":"1073 LL",
    "sg:province":"North Holland",
    "wof:name":"Gloria",
    "wof:placetype":"venue"
},
  "geometry": {"coordinates":[4.8984,52.353001],"type":"Point"}
}