{
  "type": "Feature",
  "properties": {
    "addr:full":"Piazza 5 Eindhoven North Brabant 5611 AE",
    "addr:housenumber":"5",
    "addr:postcode":"5611 ae",
    "addr:street":"Piazza",
    "iso:country":"NL",
    "sg:address":"Piazza 5",
    "sg:city":"Eindhoven",
    "sg:orig_category":"Makelaars In Onroerend Goed",
    "sg:phone":"+31 40 244 2233",
    "sg:postcode":"5611 AE",
    "sg:province":"North Brabant",
    "wof:name":"Piazza Center Rodamco Retail Nederland",
    "wof:placetype":"venue"
},
  "geometry": {"coordinates":[5.476389,51.442017],"type":"Point"}
}