{
  "type": "Feature",
  "properties": {
    "addr:full":"Rademarkt 7 Groningen Groningen 9711 CS",
    "addr:housenumber":"7",
    "addr:postcode":"9711 cs",
    "addr:street":"Rademarkt",
    "iso:country":"NL",
    "sg:address":"Rademarkt 7",
    "sg:city":"Groningen",
    "sg:classifiers":[
        {
            "category":"Fast Food",
            "type":"Food & Drink"
        }
    ],
    "sg:phone":"+31 50 312 9883",
    "sg:postcode":"9711 CS",
    "sg:province":"Groningen",
    "sg:tags":[
        "afhaal",
        "restaurant"
    ],
    "wof:name":"Rademarkt Cafetaria",
    "wof:placetype":"venue"
},
  "geometry": {"coordinates":[6.57135,53.215714],"type":"Point"}
}