{
  "type": "Feature",
  "properties": {
    "addr:full":"Dotterbloemstr 21 Rotterdam Zuid-Holland 3053 JV",
    "addr:housenumber":"21",
    "addr:postcode":"3053 jv",
    "addr:street":"Dotterbloemstr",
    "iso:country":"NL",
    "sg:address":"Dotterbloemstr 21",
    "sg:city":"Rotterdam",
    "sg:orig_category":"Geluidsinstallaties - Verhuur",
    "sg:phone":"+31 10 522 0908",
    "sg:postcode":"3053 JV",
    "sg:province":"Zuid-Holland",
    "wof:name":"Haine Bv",
    "wof:placetype":"venue"
},
  "geometry": {"coordinates":[4.466587,51.968185],"type":"Point"}
}