{
  "type": "Feature",
  "properties": {
    "addr:full":"Couwenhoven 3220 Zeist Utrecht 3703 HC",
    "addr:housenumber":"3220",
    "addr:postcode":"3703 hc",
    "addr:street":"Couwenhoven",
    "iso:country":"NL",
    "sg:address":"Couwenhoven 3220",
    "sg:city":"Zeist",
    "sg:orig_category":"Grafisch Ontwerpers",
    "sg:phone":"+31 30 695 0924",
    "sg:postcode":"3703 HC",
    "sg:province":"Utrecht",
    "wof:name":"Koman, A E",
    "wof:placetype":"venue"
},
  "geometry": {"coordinates":[5.222198,52.080208],"type":"Point"}
}