{
  "type": "Feature",
  "properties": {
    "addr:full":"Capriwg 30 Amsterdam Noord-Holland 1044 AL",
    "addr:housenumber":"30",
    "addr:postcode":"1044 al",
    "addr:street":"Capriwg",
    "iso:country":"NL",
    "sg:address":"Capriwg 30",
    "sg:city":"Amsterdam",
    "sg:orig_category":"Havenbedrijven",
    "sg:phone":"+31 20 448 7090",
    "sg:postcode":"1044 AL",
    "sg:province":"Noord-Holland",
    "wof:name":"Koperen Ploeg, De",
    "wof:placetype":"venue"
},
  "geometry": {"coordinates":[4.806142,52.415848],"type":"Point"}
}