{
  "type": "Feature",
  "properties": {
    "iso:country":"NL",
    "sg:address":"Franckenastr 33",
    "sg:city":"Oldeholtpade",
    "sg:orig_category":"Geluidsinstallaties - Verhuur",
    "sg:phone":"+31 561 688 217",
    "sg:postcode":"8474 CZ",
    "sg:province":"Friesland",
    "wof:name":"Delfsma",
    "wof:placetype":"venue"
},
  "geometry": {"coordinates":[6.04965,52.893318],"type":"Point"}
}