{
  "type": "Feature",
  "properties": {
    "addr:full":"Herenstr 52 Ryswyk Zh South Holland 2282 BW",
    "addr:housenumber":"52;zh",
    "addr:postcode":"2282 bw",
    "addr:street":"Herenstr",
    "iso:country":"NL",
    "sg:address":"Herenstr 52",
    "sg:city":"Ryswyk Zh",
    "sg:classifiers":[
        {
            "category":"Wholesale",
            "subcategory":"Meat",
            "type":"Manufacturing & Wholesale Goods"
        }
    ],
    "sg:phone":"+31 70 390 3455",
    "sg:postcode":"2282 BW",
    "sg:province":"South Holland",
    "sg:tags":[
        "regeltechniek",
        "en",
        "meet-"
    ],
    "wof:name":"Aqua-Matic",
    "wof:placetype":"venue"
},
  "geometry": {"coordinates":[4.33694,52.056503],"type":"Point"}
}