{
  "type": "Feature",
  "properties": {
    "addr:full":"Weelsedk 26 Stryen Zuid-Holland 3291 LS",
    "addr:housenumber":"26",
    "addr:postcode":"3291 ls",
    "addr:street":"Weelsedk",
    "iso:country":"NL",
    "sg:address":"Weelsedk 26",
    "sg:city":"Stryen",
    "sg:orig_category":"Adviesbureaus Financieel",
    "sg:phone":"+31 78 676 0974",
    "sg:postcode":"3291 LS",
    "sg:province":"Zuid-Holland",
    "wof:name":"Vermogenshuys, Het",
    "wof:placetype":"venue"
},
  "geometry": {"coordinates":[4.54727,51.750832],"type":"Point"}
}