{
  "type": "Feature",
  "properties": {
    "addr:full":"Zwartewg 81 S Gravenhage Zuid-Holland 2511 VV",
    "addr:housenumber":"81;gravenhage",
    "addr:postcode":"2511 vv",
    "addr:street":"Zwartewg;S",
    "iso:country":"NL",
    "sg:address":"Zwartewg 81",
    "sg:city":"S Gravenhage",
    "sg:orig_category":"Beeldende Kunstenaars",
    "sg:phone":"+31 70 363 6166",
    "sg:postcode":"2511 VV",
    "sg:province":"Zuid-Holland",
    "wof:name":"Schildkamp, S M",
    "wof:placetype":"venue"
},
  "geometry": {"coordinates":[4.31627,52.07896],"type":"Point"}
}