{
  "type": "Feature",
  "properties": {
    "addr:full":"Verlengde Hereweg 83 Groningen Groningen 9721 AH",
    "addr:housenumber":"83",
    "addr:postcode":"9721 ah",
    "addr:street":"Verlengde Hereweg",
    "iso:country":"NL",
    "sg:address":"Verlengde Hereweg 83",
    "sg:city":"Groningen",
    "sg:orig_category":"Bloemen And Planten",
    "sg:phone":"+31 50 526 2187",
    "sg:postcode":"9721 AH",
    "sg:province":"Groningen",
    "wof:name":"Bloemen De Vink",
    "wof:placetype":"venue"
},
  "geometry": {"coordinates":[6.580001,53.197727],"type":"Point"}
}