{
  "type": "Feature",
  "properties": {
    "iso:country":"NL",
    "sg:address":"Coolsestraat 138",
    "sg:city":"Rotterdam",
    "sg:orig_category":"Kansspelen",
    "sg:phone":"+31 10 213 2013",
    "sg:postcode":"3014 LN",
    "sg:province":"Zuid-Holland",
    "wof:name":"Spendid Amusementsautomaten Bv",
    "wof:placetype":"venue"
},
  "geometry": {"coordinates":[4.4662089348,51.9205741882],"type":"Point"}
}