{
  "type": "Feature",
  "properties": {
    "addr:full":"Benoordenhoutseweg 227 'S Gravenhage Zuid-Holland 2596 BE",
    "addr:housenumber":"227 '",
    "addr:postcode":"2596",
    "addr:street":"Benoordenhoutseweg",
    "iso:country":"NL",
    "sg:address":"Benoordenhoutseweg 227",
    "sg:city":"'S Gravenhage",
    "sg:orig_category":"Verzekeringen",
    "sg:phone":"+31 70 324 4010",
    "sg:postcode":"2596 BE",
    "sg:province":"Zuid-Holland",
    "wof:name":"Pso Wassenaar",
    "wof:placetype":"venue"
},
  "geometry": {"coordinates":[4.329988,52.092377],"type":"Point"}
}