{
  "type": "Feature",
  "properties": {
    "addr:full":"Bomenryk 5 Diemen North Holland 1112 EL",
    "addr:housenumber":"5",
    "addr:postcode":"1112 el",
    "addr:street":"Bomenryk",
    "iso:country":"NL",
    "sg:address":"Bomenryk 5",
    "sg:city":"Diemen",
    "sg:orig_category":"Bewakingsdiensten",
    "sg:phone":"+31 20 600 3487",
    "sg:postcode":"1112 EL",
    "sg:province":"North Holland",
    "sg:website":"http://www.bewakingsdienst-amsterdam.nl",
    "wof:name":"Bewakingsdienst Amsterdam Bv",
    "wof:placetype":"venue"
},
  "geometry": {"coordinates":[4.964805,52.34132],"type":"Point"}
}