{
  "type": "Feature",
  "properties": {
    "addr:full":"K Haaksbergerstr 42 Enschede Overijssel 7511 JS",
    "addr:housenumber":"42",
    "addr:postcode":"7511 js",
    "addr:street":"Haaksbergerstr",
    "iso:country":"NL",
    "sg:address":"K Haaksbergerstr 42",
    "sg:city":"Enschede",
    "sg:orig_category":"Kappers",
    "sg:phone":"+31 53 431 5010",
    "sg:postcode":"7511 JS",
    "sg:province":"Overijssel",
    "wof:name":"Isco",
    "wof:placetype":"venue"
},
  "geometry": {"coordinates":[6.8922381401,52.2198143005],"type":"Point"}
}