{
  "type": "Feature",
  "properties": {
    "addr:full":"Heresingel 10 Groningen Groningen 9711 ES",
    "addr:housenumber":"10",
    "addr:postcode":"9711 es",
    "addr:street":"Heresingel",
    "iso:country":"NL",
    "sg:address":"Heresingel 10",
    "sg:city":"Groningen",
    "sg:orig_category":"Kinderopvang Behalve Thuis",
    "sg:phone":"+31 50 313 9815",
    "sg:postcode":"9711 ES",
    "sg:province":"Groningen",
    "wof:name":"Stichting Beak Accommodatiebeheer",
    "wof:placetype":"venue"
},
  "geometry": {"coordinates":[6.570785,53.213844],"type":"Point"}
}