{
  "type": "Feature",
  "properties": {
    "addr:full":"Bunderstraat 12 Meerssen Limburg 6231 EL",
    "addr:housenumber":"12",
    "addr:postcode":"6231 el",
    "addr:street":"Bunderstraat",
    "iso:country":"NL",
    "sg:address":"Bunderstraat 12",
    "sg:city":"Meerssen",
    "sg:orig_category":"Kappers",
    "sg:phone":"+31 43 358 0756",
    "sg:postcode":"6231 EL",
    "sg:province":"Limburg",
    "wof:name":"Headquarters",
    "wof:placetype":"venue"
},
  "geometry": {"coordinates":[5.7522711754,50.8852539062],"type":"Point"}
}