{
  "type": "Feature",
  "properties": {
    "addr:full":"Merel 3B Boxmeer Noord-Brabant 5831 MS",
    "addr:housenumber":"3b",
    "addr:postcode":"5831 ms",
    "addr:street":"Merel",
    "iso:country":"NL",
    "sg:address":"Merel 3B",
    "sg:city":"Boxmeer",
    "sg:orig_category":"Handenarbeidartikelen - Fabrieken En Groothandel",
    "sg:phone":"+31 485 571 879",
    "sg:postcode":"5831 MS",
    "sg:province":"Noord-Brabant",
    "wof:name":"Cruijsen, Fa",
    "wof:placetype":"venue"
},
  "geometry": {"coordinates":[5.947072,51.638641],"type":"Point"}
}