{
  "type": "Feature",
  "properties": {
    "addr:full":"Ierlandstr 4 Alphen Aan Den Ryn Zuid-Holland 2408 CM",
    "addr:housenumber":"4",
    "addr:postcode":"2408 cm",
    "addr:street":"Ierlandstr;Aan Den Ryn",
    "iso:country":"NL",
    "sg:address":"Ierlandstr 4",
    "sg:city":"Alphen Aan Den Ryn",
    "sg:orig_category":"Hondenscholen",
    "sg:phone":"+31 6 18530084",
    "sg:postcode":"2408 CM",
    "sg:province":"Zuid-Holland",
    "sg:website":"http://www.blafenco.nl",
    "wof:name":"Blaf & Co",
    "wof:placetype":"venue"
},
  "geometry": {"coordinates":[4.646855,52.123623],"type":"Point"}
}