{
  "type": "Feature",
  "properties": {
    "iso:country":"NL",
    "sg:address":"Doctor J Van Der Haarln 8",
    "sg:city":"Mijdrecht",
    "sg:orig_category":"Bibliotheken And Openbare Archieven",
    "sg:phone":"+31 297 281 476",
    "sg:postcode":"3641 JW",
    "sg:province":"Utrecht",
    "wof:name":"Openbare Bibliotheken",
    "wof:placetype":"venue"
},
  "geometry": {"coordinates":[4.85696,52.207661],"type":"Point"}
}