{
  "type": "Feature",
  "properties": {
    "addr:full":"Raamstr 16A Amsterdam North Holland 1016 XM",
    "addr:housenumber":"16a",
    "addr:postcode":"1016 xm",
    "addr:street":"Raamstr",
    "iso:country":"NL",
    "sg:address":"Raamstr 16A",
    "sg:city":"Amsterdam",
    "sg:orig_category":"Fotografie Reclame En Mode",
    "sg:phone":"+31 20 622 7073",
    "sg:postcode":"1016 XM",
    "sg:province":"North Holland",
    "wof:name":"Jong, C De",
    "wof:placetype":"venue"
},
  "geometry": {"coordinates":[4.881569,52.366505],"type":"Point"}
}