{
  "type": "Feature",
  "properties": {
    "addr:full":"Euphoniumweg 1 Almere NL. 1312 XK",
    "addr:housenumber":"1",
    "addr:postcode":"1312 xk",
    "addr:street":"Euphoniumweg;Nl.",
    "iso:country":"NL",
    "sg:address":"Euphoniumweg 1",
    "sg:city":"Almere",
    "sg:orig_category":"Kinderopvang Behalve Thuis",
    "sg:phone":"+31 36 535 0214",
    "sg:postcode":"1312 XK",
    "sg:province":"NL.",
    "wof:name":"Kindercentrum De Muzikantjes",
    "wof:placetype":"venue"
},
  "geometry": {"coordinates":[5.17677,52.373913],"type":"Point"}
}