{
  "type": "Feature",
  "properties": {
    "addr:full":"Slotln 239 Zeist Utrecht 3701 GE",
    "addr:housenumber":"239",
    "addr:postcode":"3701",
    "iso:country":"NL",
    "sg:address":"Slotln 239",
    "sg:city":"Zeist",
    "sg:orig_category":"Opticiens",
    "sg:phone":"+31 30 691 8334",
    "sg:postcode":"3701 GE",
    "sg:province":"Utrecht",
    "wof:name":"Brilservice",
    "wof:placetype":"venue"
},
  "geometry": {"coordinates":[5.2438697815,52.0854797363],"type":"Point"}
}