{
  "type": "Feature",
  "properties": {
    "addr:full":"Professor Zernikestraat 8 Sneek Provincie Friesland 8606 JV",
    "addr:housenumber":"8",
    "addr:postcode":"8606 jv",
    "addr:street":"Professor Zernikestraat;Provincie Friesland",
    "iso:country":"NL",
    "sg:address":"Professor Zernikestraat 8",
    "sg:city":"Sneek",
    "sg:orig_category":"Pompen And Compressoren Fab",
    "sg:phone":"+31 515 418 445",
    "sg:postcode":"8606 JV",
    "sg:province":"Provincie Friesland",
    "wof:name":"Hovap Bv",
    "wof:placetype":"venue"
},
  "geometry": {"coordinates":[5.685885,53.020672],"type":"Point"}
}