{
  "type": "Feature",
  "properties": {
    "addr:full":"Vondelwende 3 Hillegom Zuid-Holland 2182 VT",
    "addr:housenumber":"3",
    "addr:postcode":"2182",
    "addr:street":"Vondelwende",
    "iso:country":"NL",
    "sg:address":"Vondelwende 3",
    "sg:city":"Hillegom",
    "sg:orig_category":"Glazenwasserijen",
    "sg:phone":"+31 252 517 540",
    "sg:postcode":"2182 VT",
    "sg:province":"Zuid-Holland",
    "wof:name":"Bakel, J G Van",
    "wof:placetype":"venue"
},
  "geometry": {"coordinates":[4.58626,52.284084],"type":"Point"}
}