{
  "type": "Feature",
  "properties": {
    "iso:country":"NL",
    "sg:address":"J Cookstr 1",
    "sg:city":"Alkmaar",
    "sg:orig_category":"Adviesbureaus Bedrijfsorganisatie",
    "sg:phone":"+31 72 562 2257",
    "sg:postcode":"1827 PZ",
    "sg:province":"North Holland",
    "wof:name":"Woerkom Bv Van",
    "wof:placetype":"venue"
},
  "geometry": {"coordinates":[4.76501,52.673824],"type":"Point"}
}