{
  "type": "Feature",
  "properties": {
    "iso:country":"NL",
    "sg:address":"Kanariesprenk 423",
    "sg:city":"Vlissingen",
    "sg:classifiers":[
        {
            "category":"Shopping",
            "subcategory":"Gifts & Souvenirs",
            "type":"Retail Goods"
        }
    ],
    "sg:phone":"+31 118 462 311",
    "sg:postcode":"4386 DR",
    "sg:province":"Zeeland",
    "sg:tags":[
        "wens-",
        "en",
        "prentbriefkaarten"
    ],
    "wof:name":"Cannoo",
    "wof:placetype":"venue"
},
  "geometry": {"coordinates":[3.5807459354,51.4660453796],"type":"Point"}
}