{
  "type": "Feature",
  "properties": {
    "addr:full":"St Odastr 22 Weert Limburg 6002 BD",
    "addr:housenumber":"22",
    "addr:postcode":"6002 bd",
    "addr:street":"Weert Limburg",
    "iso:country":"NL",
    "sg:address":"St Odastr 22",
    "sg:city":"Weert",
    "sg:orig_category":"Artsen - Huisartsen",
    "sg:phone":"+31 495 533 393",
    "sg:postcode":"6002 BD",
    "sg:province":"Limburg",
    "wof:name":"Heyse, P M",
    "wof:placetype":"venue"
},
  "geometry": {"coordinates":[5.686,51.259426],"type":"Point"}
}