{
  "type": "Feature",
  "properties": {
    "addr:full":"Oeverpad 449 Amsterdam Noord-Holland 1068 PM",
    "addr:housenumber":"449",
    "addr:postcode":"1068 pm",
    "addr:street":"Oeverpad",
    "iso:country":"NL",
    "sg:address":"Oeverpad 449",
    "sg:city":"Amsterdam",
    "sg:orig_category":"Binnenhuisarchitectuur",
    "sg:phone":"+31 6 10097046",
    "sg:postcode":"1068 PM",
    "sg:province":"Noord-Holland",
    "wof:name":"Neovorm",
    "wof:placetype":"venue"
},
  "geometry": {"coordinates":[4.807597,52.364056],"type":"Point"}
}