{
  "type": "Feature",
  "properties": {
    "addr:full":"Gruttostr 60 Wormer Noord-Holland 1531 WS",
    "addr:housenumber":"60",
    "addr:postcode":"1531 ws",
    "addr:street":"Gruttostr",
    "iso:country":"NL",
    "sg:address":"Gruttostr 60",
    "sg:city":"Wormer",
    "sg:orig_category":"Autorijscholen",
    "sg:phone":"+31 75 642 4917",
    "sg:postcode":"1531 WS",
    "sg:province":"Noord-Holland",
    "wof:name":"Boer, De",
    "wof:placetype":"venue"
},
  "geometry": {"coordinates":[4.813,52.501163],"type":"Point"}
}