{
  "type": "Feature",
  "properties": {
    "addr:full":"Koningsstr 7A Opheusden Gelderland 4043 JA",
    "addr:housenumber":"7a",
    "addr:postcode":"4043 ja",
    "addr:street":"Koningsstr;Gelderland",
    "iso:country":"NL",
    "sg:address":"Koningsstr 7A",
    "sg:city":"Opheusden",
    "sg:orig_category":"Boomverzorging",
    "sg:phone":"+31 488 441 294",
    "sg:postcode":"4043 JA",
    "sg:province":"Gelderland",
    "wof:name":"Koningslaak, De",
    "wof:placetype":"venue"
},
  "geometry": {"coordinates":[5.637606,51.936165],"type":"Point"}
}