{
  "type": "Feature",
  "properties": {
    "addr:full":"Jonkerlaan 22 Wassenaar South Holland 2242 GD",
    "addr:housenumber":"22",
    "addr:postcode":"2242 gd",
    "addr:street":"Jonkerlaan",
    "iso:country":"NL",
    "sg:address":"Jonkerlaan 22",
    "sg:city":"Wassenaar",
    "sg:orig_category":"Verzekeringen",
    "sg:phone":"+31 70 511 7042",
    "sg:postcode":"2242 GD",
    "sg:province":"South Holland",
    "wof:name":"Ass Kant A J M Gransjean",
    "wof:placetype":"venue"
},
  "geometry": {"coordinates":[4.395447,52.139835],"type":"Point"}
}