{
  "type": "Feature",
  "properties": {
    "iso:country":"NL",
    "sg:address":"Klarendalsewg 138D",
    "sg:city":"Arnhem",
    "sg:orig_category":"Postkantoren",
    "sg:phone":"+31 26 443 5109",
    "sg:postcode":"6822 GG",
    "sg:province":"Gelderland",
    "sg:website":"http://www.postkantoor.nl",
    "wof:name":"Postkantoor",
    "wof:placetype":"venue"
},
  "geometry": {"coordinates":[5.922128,51.988831],"type":"Point"}
}