{
  "type": "Feature",
  "properties": {
    "addr:full":"Bloemstede 79 Maarssen Utrecht 3608 TG",
    "addr:housenumber":"79",
    "addr:postcode":"3608 tg",
    "addr:street":"Bloemstede",
    "iso:country":"NL",
    "sg:address":"Bloemstede 79",
    "sg:city":"Maarssen",
    "sg:orig_category":"Administratie- En Boekhoudkantoren",
    "sg:phone":"+31 346 555 431",
    "sg:postcode":"3608 TG",
    "sg:province":"Utrecht",
    "wof:name":"Abd Maarssen Bv",
    "wof:placetype":"venue"
},
  "geometry": {"coordinates":[5.031832,52.125187],"type":"Point"}
}