{
  "type": "Feature",
  "properties": {
    "addr:full":"Jan Heinsstraat 4 'S Hertogenbosch Noord-Brabant 5211 TD",
    "addr:housenumber":"4 ' s",
    "addr:postcode":"5211 td",
    "addr:street":"Jan Heinsstraat",
    "iso:country":"NL",
    "sg:address":"Jan Heinsstraat 4",
    "sg:city":"'S Hertogenbosch",
    "sg:orig_category":"Bioscopen",
    "sg:phone":"+31 73 614 7755",
    "sg:postcode":"5211 TD",
    "sg:province":"Noord-Brabant",
    "wof:name":"Euro Cinema 1 T/M 5",
    "wof:placetype":"venue"
},
  "geometry": {"coordinates":[5.301372,51.693085],"type":"Point"}
}