{
  "type": "Feature",
  "properties": {
    "iso:country":"NL",
    "sg:address":"Hoefkade 637",
    "sg:city":"'S Gravenhage",
    "sg:classifiers":[
        {
            "category":"Fast Food",
            "type":"Food & Drink"
        }
    ],
    "sg:phone":"+31 70 380 7938",
    "sg:postcode":"2525 LD",
    "sg:province":"South Holland",
    "sg:tags":[
        "afhaal",
        "restaurant"
    ],
    "wof:name":"Cafetaria De Hoef",
    "wof:placetype":"venue"
},
  "geometry": {"coordinates":[4.303428,52.063869],"type":"Point"}
}