{
  "type": "Feature",
  "properties": {
    "addr:full":"W Vaardeke 96B Oudenbosch Noord-Brabant 4731 ME",
    "addr:housenumber":"96b",
    "addr:postcode":"4731 me",
    "addr:street":"W Vaardeke",
    "iso:country":"NL",
    "sg:address":"W Vaardeke 96B",
    "sg:city":"Oudenbosch",
    "sg:orig_category":"Vuilnisafvoer",
    "sg:phone":"+31 165 316 098",
    "sg:postcode":"4731 ME",
    "sg:province":"Noord-Brabant",
    "wof:name":"Milieustraat Halderberge",
    "wof:placetype":"venue"
},
  "geometry": {"coordinates":[4.522363,51.594009],"type":"Point"}
}