{
  "type": "Feature",
  "properties": {
    "addr:full":"Stadionwg 190 Amsterdam Noord-Holland 1077 TC",
    "addr:housenumber":"190",
    "addr:postcode":"1077 tc",
    "iso:country":"NL",
    "sg:address":"Stadionwg 190",
    "sg:city":"Amsterdam",
    "sg:orig_category":"Vertalers",
    "sg:phone":"+31 20 662 3207",
    "sg:postcode":"1077 TC",
    "sg:province":"Noord-Holland",
    "wof:name":"Ietswaart-Blahova, J",
    "wof:placetype":"venue"
},
  "geometry": {"coordinates":[4.870242,52.346783],"type":"Point"}
}