{
  "type": "Feature",
  "properties": {
    "addr:full":"Haatlanderdk 26 Kampen Overijssel 8263 AR",
    "addr:housenumber":"26",
    "addr:postcode":"8263",
    "addr:street":"Haatlanderdk",
    "iso:country":"NL",
    "sg:address":"Haatlanderdk 26",
    "sg:city":"Kampen",
    "sg:classifiers":[
        {
            "category":"Retail",
            "subcategory":"Auto Repair",
            "type":"Services"
        }
    ],
    "sg:phone":"+31 38 332 3134",
    "sg:postcode":"8263 AR",
    "sg:province":"Overijssel",
    "sg:tags":[
        "garage"
    ],
    "wof:name":"Cobus Descendre, Autobedrijf J F",
    "wof:placetype":"venue"
},
  "geometry": {"coordinates":[-92.131348,34.751888],"type":"Point"}
}