{
  "type": "Feature",
  "properties": {
    "addr:full":"Stationsstraat 10 Amstelveen Noord-Holland 1182 JN",
    "addr:housenumber":"10",
    "addr:postcode":"1182 jn",
    "addr:street":"Stationsstraat",
    "iso:country":"NL",
    "sg:address":"Stationsstraat 10",
    "sg:city":"Amstelveen",
    "sg:orig_category":"Verzekeringen",
    "sg:phone":"+31 20 647 1819",
    "sg:postcode":"1182 JN",
    "sg:province":"Noord-Holland",
    "wof:name":"J.M.H. Bruijntjes Assurantien",
    "wof:placetype":"venue"
},
  "geometry": {"coordinates":[4.846828,52.30183],"type":"Point"}
}