{
  "type": "Feature",
  "properties": {
    "addr:full":"Dampln 1 Middelburg Zeeland 4331 GC",
    "addr:housenumber":"1",
    "addr:postcode":"4331 gc",
    "addr:street":"Dampln",
    "iso:country":"NL",
    "sg:address":"Dampln 1",
    "sg:city":"Middelburg",
    "sg:orig_category":"Hypotheken",
    "sg:phone":"+31 118 642 007",
    "sg:postcode":"4331 GC",
    "sg:province":"Zeeland",
    "sg:website":"http://www.middelburg.hypotheekshop.nl/1570",
    "wof:name":"Hypotheekshop, De",
    "wof:placetype":"venue"
},
  "geometry": {"coordinates":[3.616845,51.500141],"type":"Point"}
}