{
  "type": "Feature",
  "properties": {
    "addr:full":"Stationspln 29 Almere NL. 1315 KT",
    "addr:housenumber":"29",
    "addr:postcode":"1315 kt",
    "addr:street":"Stationspln;Nl.",
    "iso:country":"NL",
    "sg:address":"Stationspln 29",
    "sg:city":"Almere",
    "sg:orig_category":"Bloemen En Planten",
    "sg:phone":"+31 36 534 1709",
    "sg:postcode":"1315 KT",
    "sg:province":"NL.",
    "wof:name":"Bloem-Idee",
    "wof:placetype":"venue"
},
  "geometry": {"coordinates":[5.219119,52.37487],"type":"Point"}
}