{
  "type": "Feature",
  "properties": {
    "addr:full":"Salmstraat 14 Geleen Limburg 6161 EM",
    "addr:housenumber":"14",
    "addr:postcode":"6161 em",
    "addr:street":"Salmstraat",
    "iso:country":"NL",
    "sg:address":"Salmstraat 14",
    "sg:city":"Geleen",
    "sg:orig_category":"Damesmodezaken",
    "sg:phone":"+31 46 474 1491",
    "sg:postcode":"6161 EM",
    "sg:province":"Limburg",
    "wof:name":"Modehuis Claudette Bv",
    "wof:placetype":"venue"
},
  "geometry": {"coordinates":[5.828283,50.969128],"type":"Point"}
}