{
  "type": "Feature",
  "properties": {
    "iso:country":"NL",
    "sg:address":"Basicweg 24",
    "sg:city":"Amersfoort",
    "sg:orig_category":"Kantoorapparatuur Gh",
    "sg:phone":"+31 33 450 7811",
    "sg:postcode":"3821 BR",
    "sg:province":"Utrecht",
    "wof:name":"Ricoh Nederland Bv",
    "wof:placetype":"venue"
},
  "geometry": {"coordinates":[5.4176898003,52.1734428406],"type":"Point"}
}