{
  "type": "Feature",
  "properties": {
    "addr:full":"Pr Hendrikstr 76 S Gravenhage Zuid-Holland 2518 HV",
    "addr:housenumber":"76;gravenhage",
    "addr:postcode":"2518 hv",
    "addr:street":"S",
    "iso:country":"NL",
    "sg:address":"Pr Hendrikstr 76",
    "sg:city":"S Gravenhage",
    "sg:orig_category":"Zeefdrukkerijen",
    "sg:phone":"+31 70 345 4905",
    "sg:postcode":"2518 HV",
    "sg:province":"Zuid-Holland",
    "wof:name":"Knaap, Kees",
    "wof:placetype":"venue"
},
  "geometry": {"coordinates":[4.29348,52.080318],"type":"Point"}
}