{
  "type": "Feature",
  "properties": {
    "addr:full":"Fregatstr 99 Utrecht Utrecht 3534 RC",
    "addr:housenumber":"99",
    "addr:postcode":"3534 rc",
    "addr:street":"Fregatstr",
    "iso:country":"NL",
    "sg:address":"Fregatstr 99",
    "sg:city":"Utrecht",
    "sg:orig_category":"Verpleegartikelen",
    "sg:phone":"+31 30 242 1519",
    "sg:postcode":"3534 RC",
    "sg:province":"Utrecht",
    "wof:name":"Memos Int Bv",
    "wof:placetype":"venue"
},
  "geometry": {"coordinates":[5.081709,52.099159],"type":"Point"}
}