{
  "type": "Feature",
  "properties": {
    "addr:full":"Oranjestr 36 Sliedrecht Zuid-Holland 3361 HR",
    "addr:housenumber":"36",
    "addr:postcode":"3361 hr",
    "addr:street":"Oranjestr",
    "iso:country":"NL",
    "sg:address":"Oranjestr 36",
    "sg:city":"Sliedrecht",
    "sg:orig_category":"Waterbouwkundige Werken",
    "sg:phone":"+31 184 420 285",
    "sg:postcode":"3361 HR",
    "sg:province":"Zuid-Holland",
    "wof:name":"Kazen, M A",
    "wof:placetype":"venue"
},
  "geometry": {"coordinates":[4.771818161,51.8197898865],"type":"Point"}
}