{
  "type": "Feature",
  "properties": {
    "iso:country":"NL",
    "sg:address":"Damsewg 99",
    "sg:city":"Brandwyk",
    "sg:orig_category":"Fietsen En Bromfietsen",
    "sg:phone":"+31 184 641 483",
    "sg:postcode":"2974 VB",
    "sg:province":"South Holland",
    "wof:name":"Goof Ijzerman",
    "wof:placetype":"venue"
},
  "geometry": {"coordinates":[4.848111,51.883636],"type":"Point"}
}