{
  "type": "Feature",
  "properties": {
    "addr:full":"Wiltonstraat 59 Veenendaal Utrecht 3905 KW",
    "addr:housenumber":"59",
    "addr:postcode":"3905 kw",
    "addr:street":"Wiltonstraat",
    "iso:country":"NL",
    "sg:address":"Wiltonstraat 59",
    "sg:city":"Veenendaal",
    "sg:orig_category":"Loodgieterswerk, Verwarming And Sanitaire Installaties",
    "sg:phone":"+31 318 500 800",
    "sg:postcode":"3905 KW",
    "sg:province":"Utrecht",
    "wof:name":"Van Harten",
    "wof:placetype":"venue"
},
  "geometry": {"coordinates":[5.563993,52.039345],"type":"Point"}
}