{
  "type": "Feature",
  "properties": {
    "addr:full":"Oosterwg 28 Valkenburg Lb Limburg 6301 PX",
    "addr:housenumber":"28",
    "addr:postcode":"lb;6301 px",
    "addr:street":"Oosterwg",
    "iso:country":"NL",
    "sg:address":"Oosterwg 28",
    "sg:city":"Valkenburg Lb",
    "sg:orig_category":"Sportverenigingen En Ontspannings- Verenigingen",
    "sg:phone":"+31 43 601 4219",
    "sg:postcode":"6301 PX",
    "sg:province":"Limburg",
    "wof:name":"Ltc Valkenburg Tennisver",
    "wof:placetype":"venue"
},
  "geometry": {"coordinates":[5.837648,50.865101],"type":"Point"}
}