{
  "type": "Feature",
  "properties": {
    "addr:full":"Heimanswg 26 Amsterdam North Holland 1031 VB",
    "addr:housenumber":"26",
    "addr:postcode":"1031 vb",
    "addr:street":"Heimanswg",
    "iso:country":"NL",
    "sg:address":"Heimanswg 26",
    "sg:city":"Amsterdam",
    "sg:orig_category":"Postzegels",
    "sg:phone":"+31 20 636 0783",
    "sg:postcode":"1031 VB",
    "sg:province":"North Holland",
    "wof:name":"Neuhaus, J G",
    "wof:placetype":"venue"
},
  "geometry": {"coordinates":[4.908764,52.389355],"type":"Point"}
}