{
  "type": "Feature",
  "properties": {
    "addr:full":"F Hendrikplnts 25 Leiderdorp Zuid-Holland 2351 GK",
    "addr:housenumber":"25",
    "addr:postcode":"2351 gk",
    "iso:country":"NL",
    "sg:address":"F Hendrikplnts 25",
    "sg:city":"Leiderdorp",
    "sg:orig_category":"Administratie- En Boekhoudkantoren",
    "sg:phone":"+31 71 572 3640",
    "sg:postcode":"2351 GK",
    "sg:province":"Zuid-Holland",
    "wof:name":"Breedeveld",
    "wof:placetype":"venue"
},
  "geometry": {"coordinates":[4.530109,52.145939],"type":"Point"}
}