{
  "type": "Feature",
  "properties": {
    "addr:full":"Touwslagersbaan 114 Gendringen Gelderland 7081 EN",
    "addr:housenumber":"114",
    "addr:postcode":"7081 en",
    "addr:street":"Touwslagersbaan;Gelderland",
    "iso:country":"NL",
    "sg:address":"Touwslagersbaan 114",
    "sg:city":"Gendringen",
    "sg:orig_category":"Loonbedrijven",
    "sg:phone":"+31 6 23634068",
    "sg:postcode":"7081 EN",
    "sg:province":"Gelderland",
    "wof:name":"Sevink",
    "wof:placetype":"venue"
},
  "geometry": {"coordinates":[6.375921,51.868458],"type":"Point"}
}