{
  "type": "Feature",
  "properties": {
    "addr:full":"Steupelstr 40 Rotterdam Zuid-Holland 3065 JE",
    "addr:housenumber":"40",
    "addr:postcode":"3065 je",
    "addr:street":"Steupelstr",
    "iso:country":"NL",
    "sg:address":"Steupelstr 40",
    "sg:city":"Rotterdam",
    "sg:orig_category":"Webdesign Bureaus",
    "sg:phone":"+31 10 235 5544",
    "sg:postcode":"3065 JE",
    "sg:province":"Zuid-Holland",
    "wof:name":"Up-Front",
    "wof:placetype":"venue"
},
  "geometry": {"coordinates":[4.5405678749,51.9261360168],"type":"Point"}
}