{
  "type": "Feature",
  "properties": {
    "addr:full":"T Kofschip 109 Veenendaal Utrecht 3904 RP",
    "addr:housenumber":"109",
    "addr:postcode":"3904 rp",
    "addr:street":"T Kofschip",
    "iso:country":"NL",
    "sg:address":"T Kofschip 109",
    "sg:city":"Veenendaal",
    "sg:orig_category":"Verhuur Catering-, Feest- En Evenementbenodigdheden",
    "sg:phone":"+31 318 529 696",
    "sg:postcode":"3904 RP",
    "sg:province":"Utrecht",
    "wof:name":"Arthur Eltink Agencies",
    "wof:placetype":"venue"
},
  "geometry": {"coordinates":[5.534298,52.02388],"type":"Point"}
}