{
  "type": "Feature",
  "properties": {
    "iso:country":"NL",
    "sg:address":"Kerkstr 59",
    "sg:city":"Oisterwyk",
    "sg:orig_category":"Antiquiteiten",
    "sg:phone":"+31 13 528 3238",
    "sg:postcode":"5061 EH",
    "sg:province":"Noord-Brabant",
    "wof:name":"Oude Pastorie, De",
    "wof:placetype":"venue"
},
  "geometry": {"coordinates":[5.187327,51.579151],"type":"Point"}
}