{
  "type": "Feature",
  "properties": {
    "iso:country":"NL",
    "sg:address":"Rijnkade 60",
    "sg:city":"Arnhem",
    "sg:orig_category":"Kantoorartikelen",
    "sg:phone":"+31 26 442 3672",
    "sg:postcode":"6811 HC",
    "sg:province":"Gelderland",
    "wof:name":"Bv Groothandel Lodiers V/H Buddingh",
    "wof:placetype":"venue"
},
  "geometry": {"coordinates":[5.9066982269,51.9774284363],"type":"Point"}
}