{
  "type": "Feature",
  "properties": {
    "addr:full":"De Schans 5 Zaltbommel Gelderland 5301 DL",
    "addr:housenumber":"5",
    "addr:postcode":"5301 dl",
    "addr:street":"De Schans;Gelderland",
    "iso:country":"NL",
    "sg:address":"De Schans 5",
    "sg:city":"Zaltbommel",
    "sg:classifiers":[
        {
            "category":"Communications",
            "subcategory":"Television Station",
            "type":"Services"
        }
    ],
    "sg:phone":"+31 418 514 242",
    "sg:postcode":"5301 DL",
    "sg:province":"Gelderland",
    "sg:tags":[
        "video",
        "audio",
        "verhuur"
    ],
    "wof:name":"Videotheek De Schans",
    "wof:placetype":"venue"
},
  "geometry": {"coordinates":[5.232568,51.804253],"type":"Point"}
}