{
  "type": "Feature",
  "properties": {
    "addr:full":"Speenkruid 47 Asten North Brabant 5721 RH",
    "addr:housenumber":"47",
    "addr:postcode":"5721 rh",
    "addr:street":"Speenkruid",
    "iso:country":"NL",
    "sg:address":"Speenkruid 47",
    "sg:city":"Asten",
    "sg:orig_category":"Loodgieterswerk, Verwarming And Sanitaire Installaties",
    "sg:phone":"+31 493 695 579",
    "sg:postcode":"5721 RH",
    "sg:province":"North Brabant",
    "wof:name":"Van Den Burg",
    "wof:placetype":"venue"
},
  "geometry": {"coordinates":[5.762163,51.403645],"type":"Point"}
}