{
  "type": "Feature",
  "properties": {
    "addr:full":"Middenweg 9 Huizen Noord-Holland 1271 AS",
    "addr:housenumber":"9",
    "addr:postcode":"1271 as",
    "addr:street":"Middenweg",
    "iso:country":"NL",
    "sg:address":"Middenweg 9",
    "sg:city":"Huizen",
    "sg:orig_category":"Zuivelproducten And Spijsoli?n Gh",
    "sg:phone":"+31 35 526 7485",
    "sg:postcode":"1271 AS",
    "sg:province":"Noord-Holland",
    "wof:name":"Jeroen Noe Kaas Bv",
    "wof:placetype":"venue"
},
  "geometry": {"coordinates":[5.236199,52.29874],"type":"Point"}
}