{
  "type": "Feature",
  "properties": {
    "iso:country":"NL",
    "sg:address":"Bos En Duin 14",
    "sg:city":"Steenbergen Dr",
    "sg:orig_category":"Technische Studies And Onderzoek",
    "sg:phone":"+31 592 656 628",
    "sg:postcode":"9307 PH",
    "sg:province":"Drenthe",
    "wof:name":"Noback",
    "wof:placetype":"venue"
},
  "geometry": {"coordinates":[6.410196,53.095257],"type":"Point"}
}