{
  "type": "Feature",
  "properties": {
    "addr:full":"Caumerstr 11 Kerkrade Limburg 6467 GH",
    "addr:housenumber":"11",
    "addr:postcode":"6467 gh",
    "addr:street":"Caumerstr",
    "iso:country":"NL",
    "sg:address":"Caumerstr 11",
    "sg:city":"Kerkrade",
    "sg:orig_category":"Apotheken",
    "sg:phone":"+31 45 566 7066",
    "sg:postcode":"6467 GH",
    "sg:province":"Limburg",
    "wof:name":"Maar -Terwinselen, De",
    "wof:placetype":"venue"
},
  "geometry": {"coordinates":[6.021006,50.864902],"type":"Point"}
}