{
  "type": "Feature",
  "properties": {
    "addr:full":"Harderwykerwg 224 Ermelo Gelderland 3852 AK",
    "addr:housenumber":"224",
    "addr:postcode":"3852 ak",
    "addr:street":"Gelderland",
    "iso:country":"NL",
    "sg:address":"Harderwykerwg 224",
    "sg:city":"Ermelo",
    "sg:orig_category":"Sanitaire Artikelen - Fabrieken En Groothandel",
    "sg:phone":"+31 341 417 718",
    "sg:postcode":"3852 AK",
    "sg:province":"Gelderland",
    "sg:website":"http://www.cameco.nl",
    "wof:name":"Cameco Internationaal Bv",
    "wof:placetype":"venue"
},
  "geometry": {"coordinates":[5.621911,52.324261],"type":"Point"}
}