{
  "type": "Feature",
  "properties": {
    "addr:full":"Spoorhaven 2 Geertruidenberg Noord-Brabant 4931 BZ",
    "addr:housenumber":"2",
    "addr:postcode":"4931 bz",
    "addr:street":"Spoorhaven",
    "iso:country":"NL",
    "sg:address":"Spoorhaven 2",
    "sg:city":"Geertruidenberg",
    "sg:orig_category":"Jachthavens - Jachtwerven",
    "sg:phone":"+31 162 512 714",
    "sg:postcode":"4931 BZ",
    "sg:province":"Noord-Brabant",
    "sg:website":"http://www.altena-yachting.nl",
    "wof:name":"Altena Bv",
    "wof:placetype":"venue"
},
  "geometry": {"coordinates":[4.858335,51.701351],"type":"Point"}
}