{
  "type": "Feature",
  "properties": {
    "iso:country":"NL",
    "sg:address":"Laan Van Poot 353",
    "sg:city":"'S Gravenhage",
    "sg:classifiers":[
        {
            "category":"Education",
            "subcategory":"Preschool",
            "type":"Public Place"
        }
    ],
    "sg:phone":"+31 70 323 1311",
    "sg:postcode":"2566 DA",
    "sg:province":"Zuid-Holland",
    "sg:tags":[
        "kleuteronderwijs",
        "basis-"
    ],
    "wof:name":"Eerste Nederlandse Montessorischool",
    "wof:placetype":"venue"
},
  "geometry": {"coordinates":[4.245235,52.076565],"type":"Point"}
}