{
  "type": "Feature",
  "properties": {
    "addr:full":"Zwanenhoek 82 Spijkenisse South Holland 3201 HS",
    "addr:housenumber":"82",
    "addr:postcode":"3201 hs",
    "addr:street":"Zwanenhoek",
    "iso:country":"NL",
    "sg:address":"Zwanenhoek 82",
    "sg:city":"Spijkenisse",
    "sg:classifiers":[
        {
            "category":"Fast Food",
            "type":"Food & Drink"
        }
    ],
    "sg:phone":"+31 181 619 055",
    "sg:postcode":"3201 HS",
    "sg:province":"South Holland",
    "sg:tags":[
        "afhaal",
        "restaurant"
    ],
    "wof:name":"Chinees-Indisch Restaurant Zilver Maas",
    "wof:placetype":"venue"
},
  "geometry": {"coordinates":[4.316889,51.843761],"type":"Point"}
}