{
  "type": "Feature",
  "properties": {
    "addr:full":"Walstro 20 Sprang-Capelle Noord-Brabant 5161 WK",
    "addr:housenumber":"20",
    "addr:postcode":"5161 wk",
    "addr:street":"Walstro",
    "iso:country":"NL",
    "sg:address":"Walstro 20",
    "sg:city":"Sprang-Capelle",
    "sg:orig_category":"Boekhouders",
    "sg:phone":"+31 416 283 381",
    "sg:postcode":"5161 WK",
    "sg:province":"Noord-Brabant",
    "wof:name":"Raad Waalwijk",
    "wof:placetype":"venue"
},
  "geometry": {"coordinates":[5.022182,51.677456],"type":"Point"}
}