{
  "type": "Feature",
  "properties": {
    "addr:full":"Constructieweg 7 Emmeloord Flevoland 8305 AA",
    "addr:housenumber":"7",
    "addr:postcode":"8305 aa",
    "addr:street":"Constructieweg;Flevoland",
    "iso:country":"NL",
    "sg:address":"Constructieweg 7",
    "sg:city":"Emmeloord",
    "sg:orig_category":"Metaalwerken",
    "sg:phone":"+31 527 618 014",
    "sg:postcode":"8305 AA",
    "sg:province":"Flevoland",
    "wof:name":"Jack Staal",
    "wof:placetype":"venue"
},
  "geometry": {"coordinates":[5.777637,52.710148],"type":"Point"}
}