{
  "type": "Feature",
  "properties": {
    "addr:full":"Stationswg 56 Ede Gld Gelderland 6711 PT",
    "addr:housenumber":"56",
    "addr:postcode":"6711",
    "addr:street":"Stationswg;Gld Gelderland;Pt",
    "iso:country":"NL",
    "sg:address":"Stationswg 56",
    "sg:city":"Ede Gld",
    "sg:orig_category":"Artsen - Huisartsen",
    "sg:phone":"+31 318 610 636",
    "sg:postcode":"6711 PT",
    "sg:province":"Gelderland",
    "wof:name":"Berg, J P B Van Den",
    "wof:placetype":"venue"
},
  "geometry": {"coordinates":[5.668569,52.037777],"type":"Point"}
}