{
  "type": "Feature",
  "properties": {
    "addr:full":"Spalstr 7-9 Hengelo Gld Gelderland 7255 AA",
    "addr:housenumber":"7-9",
    "addr:postcode":"7255 aa",
    "addr:street":"Spalstr",
    "iso:country":"NL",
    "sg:address":"Spalstr 7-9",
    "sg:city":"Hengelo Gld",
    "sg:orig_category":"Herenkleding",
    "sg:phone":"+31 575 461 383",
    "sg:postcode":"7255 AA",
    "sg:province":"Gelderland",
    "wof:name":"Lentferink",
    "wof:placetype":"venue"
},
  "geometry": {"coordinates":[6.310447,52.05249],"type":"Point"}
}