{
  "type": "Feature",
  "properties": {
    "iso:country":"NL",
    "sg:address":"Amerongerwetering 2",
    "sg:city":"Amerongen",
    "sg:orig_category":"Zuivelproducten",
    "sg:phone":"+31 343 451 757",
    "sg:postcode":"3958 MD",
    "sg:province":"Utrecht",
    "wof:name":"Zuivelboerderij De Boterbloem",
    "wof:placetype":"venue"
},
  "geometry": {"coordinates":[5.414108,51.995922],"type":"Point"}
}