{
  "type": "Feature",
  "properties": {
    "addr:full":"Amerongerwetering 2 Amerongen Utrecht 3958 MD",
    "addr:housenumber":"2",
    "addr:postcode":"3958",
    "addr:street":"Amerongerwetering",
    "iso:country":"NL",
    "sg:address":"Amerongerwetering 2",
    "sg:city":"Amerongen",
    "sg:orig_category":"Zuivelproducten",
    "sg:phone":"+31 343 451 757",
    "sg:postcode":"3958 MD",
    "sg:province":"Utrecht",
    "wof:name":"Zuivelboerderij De Boterbloem",
    "wof:placetype":"venue"
},
  "geometry": {"coordinates":[5.414108,51.995922],"type":"Point"}
}