{
  "type": "Feature",
  "properties": {
    "addr:full":"Zandbank 86 Lelystad Flevoland 8224 ZE",
    "addr:housenumber":"86",
    "addr:postcode":"8224",
    "addr:street":"Zandbank;Flevoland",
    "iso:country":"NL",
    "sg:address":"Zandbank 86",
    "sg:city":"Lelystad",
    "sg:orig_category":"Glazenwasserijen",
    "sg:phone":"+31 320 232 225",
    "sg:postcode":"8224 ZE",
    "sg:province":"Flevoland",
    "wof:name":"Maten Lelystad, Ter",
    "wof:placetype":"venue"
},
  "geometry": {"coordinates":[5.482364,52.514721],"type":"Point"}
}