{
  "type": "Feature",
  "properties": {
    "addr:full":"V Boshuizenstr 12 Amsterdam Noord-Holland 1083 BA",
    "addr:housenumber":"12",
    "addr:postcode":"1083 ba",
    "iso:country":"NL",
    "sg:address":"V Boshuizenstr 12",
    "sg:city":"Amsterdam",
    "sg:orig_category":"Papier - Fabrieken En Groothandel",
    "sg:phone":"+31 20 572 7000",
    "sg:postcode":"1083 BA",
    "sg:province":"Noord-Holland",
    "sg:website":"http://www.m-real.com",
    "wof:name":"M-Real Benelux Bv",
    "wof:placetype":"venue"
},
  "geometry": {"coordinates":[4.88921,52.33028],"type":"Point"}
}