{
  "type": "Feature",
  "properties": {
    "addr:full":"Westpln 50 Utrecht Utrecht 3531 BL",
    "addr:housenumber":"50",
    "addr:postcode":"3531 bl",
    "addr:street":"Westpln",
    "iso:country":"NL",
    "sg:address":"Westpln 50",
    "sg:city":"Utrecht",
    "sg:classifiers":[
        {
            "category":"Travel",
            "subcategory":"Hotels & Motels",
            "type":"Entertainment"
        }
    ],
    "sg:phone":"+31 30 292 5200",
    "sg:postcode":"3531 BL",
    "sg:province":"Utrecht",
    "wof:name":"Park Plaza Utrecht",
    "wof:placetype":"venue"
},
  "geometry": {"coordinates":[5.105763,52.091099],"type":"Point"}
}