{
  "type": "Feature",
  "properties": {
    "addr:full":"Kerkpln 69 Voerendaal Limburg 6367 EP",
    "addr:housenumber":"69",
    "addr:postcode":"6367 ep",
    "addr:street":"Kerkpln",
    "iso:country":"NL",
    "sg:address":"Kerkpln 69",
    "sg:city":"Voerendaal",
    "sg:orig_category":"Kappers",
    "sg:phone":"+31 45 575 4904",
    "sg:postcode":"6367 EP",
    "sg:province":"Limburg",
    "wof:name":"Nicowa Voerendaal, Kappers",
    "wof:placetype":"venue"
},
  "geometry": {"coordinates":[5.92928,50.882854],"type":"Point"}
}