{
  "type": "Feature",
  "properties": {
    "addr:full":"Lange Broekweg 17 Naaldwijk South Holland 2671 DT",
    "addr:housenumber":"17",
    "addr:postcode":"2671 dt",
    "addr:street":"Lange Broekweg",
    "iso:country":"NL",
    "sg:address":"Lange Broekweg 17",
    "sg:city":"Naaldwijk",
    "sg:orig_category":"Bloemen And Planten",
    "sg:phone":"+31 174 625 895",
    "sg:postcode":"2671 DT",
    "sg:province":"South Holland",
    "wof:name":"G. Van Der Arend En Zoon Bv",
    "wof:placetype":"venue"
},
  "geometry": {"coordinates":[4.228406,51.990028],"type":"Point"}
}