{
  "type": "Feature",
  "properties": {
    "iso:country":"NL",
    "sg:address":"Fernandelstrook 3",
    "sg:city":"Zoetermeer",
    "sg:orig_category":"Adviesbureaus Bedrijfsorganisatie",
    "sg:phone":"+31 79 343 9183",
    "sg:postcode":"2726 TC",
    "sg:province":"Zuid-Holland",
    "wof:name":"Avance",
    "wof:placetype":"venue"
},
  "geometry": {"coordinates":[4.489141,52.072697],"type":"Point"}
}