{
  "type": "Feature",
  "properties": {
    "addr:full":"Dr Schaepmanstr 52 Brunssum Limburg 6444 XZ",
    "addr:housenumber":"52",
    "addr:postcode":"6444 xz",
    "iso:country":"NL",
    "sg:address":"Dr Schaepmanstr 52",
    "sg:city":"Brunssum",
    "sg:orig_category":"Onderhoudswerken",
    "sg:phone":"+31 45 525 2054",
    "sg:postcode":"6444 XZ",
    "sg:province":"Limburg",
    "wof:name":"Schruijren, Charles",
    "wof:placetype":"venue"
},
  "geometry": {"coordinates":[5.95762,50.934963],"type":"Point"}
}