{
  "type": "Feature",
  "properties": {
    "addr:full":"Jan Steenstraat 49 Woerden Utrecht 3443 GR",
    "addr:housenumber":"49",
    "addr:postcode":"3443",
    "addr:street":"Jan Steenstraat",
    "iso:country":"NL",
    "sg:address":"Jan Steenstraat 49",
    "sg:city":"Woerden",
    "sg:orig_category":"Wegen And Sportterreinen",
    "sg:phone":"+31 348 411 942",
    "sg:postcode":"3443 GR",
    "sg:province":"Utrecht",
    "wof:name":"L.P. Pijnakker",
    "wof:placetype":"venue"
},
  "geometry": {"coordinates":[4.8746027946,52.0907859802],"type":"Point"}
}