{
  "type": "Feature",
  "properties": {
    "addr:full":"Eindsestr 43A Balgoy Gelderland 6613 AR",
    "addr:housenumber":"43a",
    "addr:postcode":"6613",
    "addr:street":"Eindsestr;Gelderland",
    "iso:country":"NL",
    "sg:address":"Eindsestr 43A",
    "sg:city":"Balgoy",
    "sg:orig_category":"Sportverenigingen En Ontspannings- Verenigingen",
    "sg:phone":"+31 24 641 5549",
    "sg:postcode":"6613 AR",
    "sg:province":"Gelderland",
    "wof:name":"Diosa Voetbalver & Korfbal",
    "wof:placetype":"venue"
},
  "geometry": {"coordinates":[5.7236,51.77718],"type":"Point"}
}