{
  "type": "Feature",
  "properties": {
    "addr:full":"Doornbossewg 11 Kruisland Noord-Brabant 4756 SP",
    "addr:housenumber":"11",
    "addr:postcode":"4756 sp",
    "addr:street":"Doornbossewg",
    "iso:country":"NL",
    "sg:address":"Doornbossewg 11",
    "sg:city":"Kruisland",
    "sg:orig_category":"Lasbedrijven",
    "sg:phone":"+31 167 532 128",
    "sg:postcode":"4756 SP",
    "sg:province":"Noord-Brabant",
    "wof:name":"Elteren, C Van",
    "wof:placetype":"venue"
},
  "geometry": {"coordinates":[-48.635078,-22.5149],"type":"Point"}
}