{
  "type": "Feature",
  "properties": {
    "addr:full":"Heggerank 119 Lochem Gelderland 7242 MH",
    "addr:housenumber":"119",
    "addr:postcode":"7242 mh",
    "addr:street":"Heggerank;Gelderland",
    "iso:country":"NL",
    "sg:address":"Heggerank 119",
    "sg:city":"Lochem",
    "sg:orig_category":"Adviesbureaus Bouwkunde",
    "sg:phone":"+31 573 255 275",
    "sg:postcode":"7242 MH",
    "sg:province":"Gelderland",
    "wof:name":"Kapper",
    "wof:placetype":"venue"
},
  "geometry": {"coordinates":[6.394884,52.155571],"type":"Point"}
}