{
  "type": "Feature",
  "properties": {
    "addr:full":"Kazernestr 38B S Gravenhage South Holland 2514 CT",
    "addr:housenumber":"38b",
    "addr:postcode":"2514 ct",
    "addr:street":"Kazernestr;S Gravenhage",
    "iso:country":"NL",
    "sg:address":"Kazernestr 38B",
    "sg:city":"S Gravenhage",
    "sg:orig_category":"Verenigingsgebouwen",
    "sg:phone":"+31 70 364 3142",
    "sg:postcode":"2514 CT",
    "sg:province":"South Holland",
    "wof:name":"Vereniging Soci\u00ebteit, De",
    "wof:placetype":"venue"
},
  "geometry": {"coordinates":[4.30935,52.084148],"type":"Point"}
}