{
  "type": "Feature",
  "properties": {
    "addr:full":"Van Oldenbarneveldtweg 9 Castricum North Holland 1901 KA",
    "addr:housenumber":"9",
    "addr:postcode":"1901 ka",
    "iso:country":"NL",
    "sg:address":"Van Oldenbarneveldtweg 9",
    "sg:city":"Castricum",
    "sg:classifiers":[
        {
            "category":"Fast Food",
            "type":"Food & Drink"
        }
    ],
    "sg:phone":"+31 251 654 319",
    "sg:postcode":"1901 KA",
    "sg:province":"North Holland",
    "sg:tags":[
        "afhaal",
        "restaurant"
    ],
    "wof:name":"Chinees Indisch Restaurant Oceaan",
    "wof:placetype":"venue"
},
  "geometry": {"coordinates":[4.663725,52.546844],"type":"Point"}
}