{
  "type": "Feature",
  "properties": {
    "addr:full":"Minnemastr 1 Leeuwarden Provincie Friesland 8911 GW",
    "addr:housenumber":"1",
    "addr:postcode":"8911 gw",
    "addr:street":"Minnemastr;Provincie Friesland",
    "iso:country":"NL",
    "sg:address":"Minnemastr 1",
    "sg:city":"Leeuwarden",
    "sg:orig_category":"Postzegels",
    "sg:phone":"+31 58 212 9204",
    "sg:postcode":"8911 GW",
    "sg:province":"Provincie Friesland",
    "wof:name":"Vries, B De",
    "wof:placetype":"venue"
},
  "geometry": {"coordinates":[5.798952,53.202084],"type":"Point"}
}