{
  "type": "Feature",
  "properties": {
    "iso:country":"NL",
    "sg:address":"H Scholtenstr 16",
    "sg:city":"Budel",
    "sg:orig_category":"Zonweringen",
    "sg:phone":"+31 495 492 873",
    "sg:postcode":"6021 XN",
    "sg:province":"Noord-Brabant",
    "wof:name":"Houben, L G M",
    "wof:placetype":"venue"
},
  "geometry": {"coordinates":[5.568221,51.268318],"type":"Point"}
}