{
  "type": "Feature",
  "properties": {
    "addr:full":"H Kasselstr 1 Eindhoven Noord-Brabant 5615 SM",
    "addr:housenumber":"1",
    "addr:postcode":"5615 sm",
    "iso:country":"NL",
    "sg:address":"H Kasselstr 1",
    "sg:city":"Eindhoven",
    "sg:orig_category":"Montagebedrijven",
    "sg:phone":"+31 40 252 3277",
    "sg:postcode":"5615 SM",
    "sg:province":"Noord-Brabant",
    "wof:name":"Labre",
    "wof:placetype":"venue"
},
  "geometry": {"coordinates":[5.46542,51.430851],"type":"Point"}
}