{
  "type": "Feature",
  "properties": {
    "addr:full":"R Feithln 12 Bussum Noord-Holland 1401 AV",
    "addr:housenumber":"12;1401",
    "addr:postcode":"av",
    "iso:country":"NL",
    "sg:address":"R Feithln 12",
    "sg:city":"Bussum",
    "sg:orig_category":"Adviesbureaus Bedrijfsorganisatie",
    "sg:phone":"+31 35 692 0276",
    "sg:postcode":"1401 AV",
    "sg:province":"Noord-Holland",
    "wof:name":"Arisconsult Bv",
    "wof:placetype":"venue"
},
  "geometry": {"coordinates":[5.162605,52.276829],"type":"Point"}
}