{
  "type": "Feature",
  "properties": {
    "addr:full":"St Vitusstr 29A Bussum Noord-Holland 1404 HR",
    "addr:housenumber":"29a",
    "addr:postcode":"1404 hr",
    "iso:country":"NL",
    "sg:address":"St Vitusstr 29A",
    "sg:city":"Bussum",
    "sg:orig_category":"Nagelstudio'S",
    "sg:phone":"+31 35 691 2816",
    "sg:postcode":"1404 HR",
    "sg:province":"Noord-Holland",
    "wof:name":"An Durivou",
    "wof:placetype":"venue"
},
  "geometry": {"coordinates":[5.164606,52.272774],"type":"Point"}
}