{
  "type": "Feature",
  "properties": {
    "addr:full":"Primulabeemd 10 Maastricht Limburg 6229 ZC",
    "addr:housenumber":"10",
    "addr:postcode":"6229 zc",
    "addr:street":"Primulabeemd",
    "iso:country":"NL",
    "sg:address":"Primulabeemd 10",
    "sg:city":"Maastricht",
    "sg:orig_category":"Honden- En Kattentrimsalons",
    "sg:phone":"+31 43 361 3874",
    "sg:postcode":"6229 ZC",
    "sg:province":"Limburg",
    "wof:name":"Bianca",
    "wof:placetype":"venue"
},
  "geometry": {"coordinates":[5.709826,50.823212],"type":"Point"}
}