{
  "type": "Feature",
  "properties": {
    "iso:country":"NL",
    "sg:address":"Barendsestr 20",
    "sg:city":"Haarlem",
    "sg:orig_category":"Maaltijdbezorging",
    "sg:phone":"+31 23 531 1309",
    "sg:postcode":"2012 VP",
    "sg:province":"Noord-Holland",
    "wof:name":"Namra",
    "wof:placetype":"venue"
},
  "geometry": {"coordinates":[4.638189,52.374756],"type":"Point"}
}