{
  "type": "Feature",
  "properties": {
    "addr:full":"Hoedemakersweg 64 Dokkum Provincie Friesland 9101 BZ",
    "addr:housenumber":"64",
    "addr:postcode":"9101 bz",
    "addr:street":"Hoedemakersweg;Provincie Friesland",
    "iso:country":"NL",
    "sg:address":"Hoedemakersweg 64",
    "sg:city":"Dokkum",
    "sg:orig_category":"Kinderopvang Behalve Thuis",
    "sg:phone":"+31 519 297 959",
    "sg:postcode":"9101 BZ",
    "sg:province":"Provincie Friesland",
    "wof:name":"Peuterspeelzaal De Kleine Wereld",
    "wof:placetype":"venue"
},
  "geometry": {"coordinates":[5.993202,53.323406],"type":"Point"}
}