{
  "type": "Feature",
  "properties": {
    "addr:full":"C Huygensstr 5 Bleiswyk Zuid-Holland 2665 KX",
    "addr:housenumber":"5",
    "addr:postcode":"bleiswyk;2665 kx",
    "iso:country":"NL",
    "sg:address":"C Huygensstr 5",
    "sg:city":"Bleiswyk",
    "sg:orig_category":"Meubelen",
    "sg:phone":"+31 10 521 4400",
    "sg:postcode":"2665 KX",
    "sg:province":"Zuid-Holland",
    "wof:name":"Bergers Bv, H",
    "wof:placetype":"venue"
},
  "geometry": {"coordinates":[4.531235,52.012997],"type":"Point"}
}