{
  "type": "Feature",
  "properties": {
    "addr:full":"Dr V Ringersstr 14 Ried Friesland 8811 HN",
    "addr:housenumber":"14",
    "addr:postcode":"8811 hn",
    "addr:street":"Dr;Ringersstr",
    "iso:country":"NL",
    "sg:address":"Dr V Ringersstr 14",
    "sg:city":"Ried",
    "sg:orig_category":"Dieselmotoren",
    "sg:phone":"+31 517 269 301",
    "sg:postcode":"8811 HN",
    "sg:province":"Friesland",
    "wof:name":"Veen Vof, Van Der",
    "wof:placetype":"venue"
},
  "geometry": {"coordinates":[5.592285,53.22332],"type":"Point"}
}