{
  "type": "Feature",
  "properties": {
    "addr:full":"Noorderstat Str 77 Zwaagwesteinde Friesland 9271 CJ",
    "addr:postcode":"9271 cj",
    "addr:street":"Str 77",
    "iso:country":"NL",
    "sg:address":"Noorderstat Str 77",
    "sg:city":"Zwaagwesteinde",
    "sg:orig_category":"Verzekeringen - Verzekeringskantoren",
    "sg:phone":"+31 511 444 340",
    "sg:postcode":"9271 CJ",
    "sg:province":"Friesland",
    "wof:name":"Zutphen, Peter Van",
    "wof:placetype":"venue"
},
  "geometry": {"coordinates":[6.036835,53.249138],"type":"Point"}
}