{
  "type": "Feature",
  "properties": {
    "addr:full":"Colynpln 43 Ysselstein Ut Utrecht 3404 JM",
    "addr:housenumber":"43",
    "addr:postcode":"3404 jm",
    "addr:street":"Colynpln",
    "iso:country":"NL",
    "sg:address":"Colynpln 43",
    "sg:city":"Ysselstein Ut",
    "sg:orig_category":"Webdesign Bureaus",
    "sg:phone":"+31 30 687 7788",
    "sg:postcode":"3404 JM",
    "sg:province":"Utrecht",
    "sg:website":"http://www.lucos.nl",
    "wof:name":"Lucos",
    "wof:placetype":"venue"
},
  "geometry": {"coordinates":[5.0281000137,52.0266304016],"type":"Point"}
}