{
  "type": "Feature",
  "properties": {
    "addr:full":"Poortwg 21 Bergen Op Zoom Noord-Brabant 4613 BW",
    "addr:housenumber":"21",
    "addr:postcode":"4613 bw",
    "addr:street":"Poortwg",
    "iso:country":"NL",
    "sg:address":"Poortwg 21",
    "sg:city":"Bergen Op Zoom",
    "sg:orig_category":"Machinefabrieken",
    "sg:phone":"+31 164 233 041",
    "sg:postcode":"4613 BW",
    "sg:province":"Noord-Brabant",
    "wof:name":"Bedaf Bv, Van",
    "wof:placetype":"venue"
},
  "geometry": {"coordinates":[4.277472,51.502296],"type":"Point"}
}