{
  "type": "Feature",
  "properties": {
    "addr:full":"Randweg 5 Roermond Limburg 6045 JK",
    "addr:housenumber":"5",
    "addr:postcode":"6045 jk",
    "addr:street":"Randweg",
    "iso:country":"NL",
    "sg:address":"Randweg 5",
    "sg:city":"Roermond",
    "sg:orig_category":"Meubelreparatie And -Restauratie",
    "sg:phone":"+31 475 324 040",
    "sg:postcode":"6045 JK",
    "sg:province":"Limburg",
    "wof:name":"Stoffeerderij Van Der Beek Bv",
    "wof:placetype":"venue"
},
  "geometry": {"coordinates":[6.057498,51.164024],"type":"Point"}
}