{
  "type": "Feature",
  "properties": {
    "addr:full":"Noorderbuurt 76 Drachten Friesland 9203 AM",
    "addr:housenumber":"76",
    "addr:postcode":"9203",
    "addr:street":"Noorderbuurt",
    "iso:country":"NL",
    "sg:address":"Noorderbuurt 76",
    "sg:city":"Drachten",
    "sg:orig_category":"Beveiliging",
    "sg:phone":"+31 512 537 575",
    "sg:postcode":"9203 AM",
    "sg:province":"Friesland",
    "sg:website":"http://www.secusys.nl",
    "wof:name":"Secusys Beveiliging",
    "wof:placetype":"venue"
},
  "geometry": {"coordinates":[6.097375,53.109455],"type":"Point"}
}