{
  "type": "Feature",
  "properties": {
    "addr:full":"Nieuwewg 6-A Den Helder Noord-Holland 1784 PG",
    "addr:housenumber":"6-a",
    "addr:postcode":"1784 pg",
    "addr:street":"Nieuwewg",
    "iso:country":"NL",
    "sg:address":"Nieuwewg 6-A",
    "sg:city":"Den Helder",
    "sg:orig_category":"Geluidsinstallaties - Verhuur",
    "sg:phone":"+31 6 53220198",
    "sg:postcode":"1784 PG",
    "sg:province":"Noord-Holland",
    "sg:website":"http://www.dirkszadmiraal.nl",
    "wof:name":"Solid Studio",
    "wof:placetype":"venue"
},
  "geometry": {"coordinates":[4.754145,52.944286],"type":"Point"}
}