{
  "type": "Feature",
  "properties": {
    "addr:full":"Vrouwenstg 14 Leiden South Holland 2311 EB",
    "addr:housenumber":"14",
    "addr:postcode":"2311 eb",
    "addr:street":"Vrouwenstg",
    "iso:country":"NL",
    "sg:address":"Vrouwenstg 14",
    "sg:city":"Leiden",
    "sg:orig_category":"Parketvloeren",
    "sg:phone":"+31 71 513 0496",
    "sg:postcode":"2311 EB",
    "sg:province":"South Holland",
    "wof:name":"Starket Leiden",
    "wof:placetype":"venue"
},
  "geometry": {"coordinates":[4.488651,52.159882],"type":"Point"}
}