{
  "type": "Feature",
  "properties": {
    "addr:full":"Steenakkers 11 Tynaarlo Drenthe 9482 RA",
    "addr:housenumber":"11",
    "addr:postcode":"9482 ra",
    "addr:street":"Steenakkers",
    "iso:country":"NL",
    "sg:address":"Steenakkers 11",
    "sg:city":"Tynaarlo",
    "sg:orig_category":"Kamerverhuur En -Bemiddeling",
    "sg:phone":"+31 592 542 668",
    "sg:postcode":"9482 RA",
    "sg:province":"Drenthe",
    "wof:name":"Penning",
    "wof:placetype":"venue"
},
  "geometry": {"coordinates":[6.6177101135,53.0763206482],"type":"Point"}
}