{
  "type": "Feature",
  "properties": {
    "addr:full":"Julianasngl 33B Venray Limburg 5802 AT",
    "addr:housenumber":"33b",
    "addr:postcode":"5802",
    "addr:street":"Julianasngl",
    "iso:country":"NL",
    "sg:address":"Julianasngl 33B",
    "sg:city":"Venray",
    "sg:orig_category":"Werving En Selectie",
    "sg:phone":"+31 478 630 930",
    "sg:postcode":"5802 AT",
    "sg:province":"Limburg",
    "wof:name":"Topjop",
    "wof:placetype":"venue"
},
  "geometry": {"coordinates":[5.9770731926,51.5271568298],"type":"Point"}
}