{
  "type": "Feature",
  "properties": {
    "addr:full":"Melkweg 3 Langerak Zh Zuid-Holland 2967 LA",
    "addr:housenumber":"3",
    "addr:postcode":"2967 la",
    "addr:street":"Melkweg",
    "iso:country":"NL",
    "sg:address":"Melkweg 3",
    "sg:city":"Langerak Zh",
    "sg:orig_category":"Granen, Zaden And Diervoeders Gh",
    "sg:phone":"+31 184 602 672",
    "sg:postcode":"2967 LA",
    "sg:province":"Zuid-Holland",
    "wof:name":"Romijn Fourage",
    "wof:placetype":"venue"
},
  "geometry": {"coordinates":[4.899714,51.920361],"type":"Point"}
}