{
  "type": "Feature",
  "properties": {
    "addr:full":"De Gaffel 7 Lieshout Noord-Brabant 5737 JJ",
    "addr:housenumber":"7",
    "addr:postcode":"5737 jj",
    "addr:street":"De Gaffel",
    "iso:country":"NL",
    "sg:address":"De Gaffel 7",
    "sg:city":"Lieshout",
    "sg:orig_category":"Binnenhuisarchitecten",
    "sg:phone":"+31 6 22395818",
    "sg:postcode":"5737 JJ",
    "sg:province":"Noord-Brabant",
    "wof:name":"Demonet",
    "wof:placetype":"venue"
},
  "geometry": {"coordinates":[5.587577,51.516644],"type":"Point"}
}