{
  "type": "Feature",
  "properties": {
    "addr:full":"Molenstraat 52 Cuijk Noord-Brabant 5431 BZ",
    "addr:housenumber":"52",
    "addr:postcode":"5431 bz",
    "addr:street":"Molenstraat",
    "iso:country":"NL",
    "sg:address":"Molenstraat 52",
    "sg:city":"Cuijk",
    "sg:orig_category":"Herenmodezaken",
    "sg:phone":"+31 485 322 549",
    "sg:postcode":"5431 BZ",
    "sg:province":"Noord-Brabant",
    "wof:name":"Palettie Mannenmode",
    "wof:placetype":"venue"
},
  "geometry": {"coordinates":[5.875916,51.729267],"type":"Point"}
}