{
  "type": "Feature",
  "properties": {
    "addr:full":"Robynstr 68 Leiden Zuid-Holland 2332 KV",
    "addr:housenumber":"68",
    "addr:postcode":"2332 kv",
    "addr:street":"Robynstr",
    "iso:country":"NL",
    "sg:address":"Robynstr 68",
    "sg:city":"Leiden",
    "sg:orig_category":"Bedrijfsopleidingen",
    "sg:phone":"+31 71 576 5048",
    "sg:postcode":"2332 KV",
    "sg:province":"Zuid-Holland",
    "wof:name":"Averz",
    "wof:placetype":"venue"
},
  "geometry": {"coordinates":[4.463368,52.155754],"type":"Point"}
}