{
  "type": "Feature",
  "properties": {
    "addr:full":"Keerberg 98 Voerendaal Limburg 6367 EL",
    "addr:housenumber":"98",
    "addr:postcode":"6367 el",
    "addr:street":"Keerberg",
    "iso:country":"NL",
    "sg:address":"Keerberg 98",
    "sg:city":"Voerendaal",
    "sg:orig_category":"Fitnesscentra",
    "sg:phone":"+31 45 562 0062",
    "sg:postcode":"6367 EL",
    "sg:province":"Limburg",
    "wof:name":"Rosalie",
    "wof:placetype":"venue"
},
  "geometry": {"coordinates":[5.930255,50.877552],"type":"Point"}
}