{
  "type": "Feature",
  "properties": {
    "addr:full":"Krytwal 27 Nieuwegein Utrecht 3432 ZT",
    "addr:housenumber":"27",
    "addr:postcode":"3432 zt",
    "addr:street":"Krytwal",
    "iso:country":"NL",
    "sg:address":"Krytwal 27",
    "sg:city":"Nieuwegein",
    "sg:orig_category":"Grafisch Ontwerpers",
    "sg:phone":"+31 30 603 3501",
    "sg:postcode":"3432 ZT",
    "sg:province":"Utrecht",
    "sg:website":"http://www.bauschgd.nl",
    "wof:name":"Bgd",
    "wof:placetype":"venue"
},
  "geometry": {"coordinates":[5.088468,52.027466],"type":"Point"}
}