{
  "type": "Feature",
  "properties": {
    "addr:full":"Duizelsewg 4B Eersel Noord-Brabant 5521 AC",
    "addr:housenumber":"4b",
    "addr:postcode":"5521 ac",
    "addr:street":"Duizelsewg",
    "iso:country":"NL",
    "sg:address":"Duizelsewg 4B",
    "sg:city":"Eersel",
    "sg:orig_category":"Herenkleding",
    "sg:phone":"+31 497 512 849",
    "sg:postcode":"5521 AC",
    "sg:province":"Noord-Brabant",
    "wof:name":"Woerkum Speciaalzaak Herenkleding, Gebr Van",
    "wof:placetype":"venue"
},
  "geometry": {"coordinates":[5.307794,51.360332],"type":"Point"}
}