{
  "type": "Feature",
  "properties": {
    "iso:country":"NL",
    "sg:address":"Bremstr 253",
    "sg:city":"Assen",
    "sg:orig_category":"Verenigingen En Stichtingen",
    "sg:phone":"+31 592 291 083",
    "sg:postcode":"9404 GD",
    "sg:province":"Provincie Drenthe",
    "wof:name":"Hulp Macedoni\u00eb, Sticht",
    "wof:placetype":"venue"
},
  "geometry": {"coordinates":[6.583661,52.986256],"type":"Point"}
}