{
  "type": "Feature",
  "properties": {
    "addr:full":"Bremstr 253 Assen Provincie Drenthe 9404 GD",
    "addr:housenumber":"253",
    "addr:postcode":"9404 gd",
    "addr:street":"Provincie Drenthe",
    "iso:country":"NL",
    "sg:address":"Bremstr 253",
    "sg:city":"Assen",
    "sg:orig_category":"Verenigingen En Stichtingen",
    "sg:phone":"+31 592 291 083",
    "sg:postcode":"9404 GD",
    "sg:province":"Provincie Drenthe",
    "wof:name":"Hulp Macedoni\u00eb, Sticht",
    "wof:placetype":"venue"
},
  "geometry": {"coordinates":[6.583661,52.986256],"type":"Point"}
}