{
  "type": "Feature",
  "properties": {
    "iso:country":"NL",
    "sg:address":"Zonnepln 30",
    "sg:city":"Amsterdam",
    "sg:orig_category":"Geluidsinstallaties - Verhuur",
    "sg:phone":"+31 20 633 0043",
    "sg:postcode":"1033 EK",
    "sg:province":"Noord-Holland",
    "wof:name":"Radio Astrolight, Sticht",
    "wof:placetype":"venue"
},
  "geometry": {"coordinates":[4.8912,52.413242],"type":"Point"}
}