{
  "type": "Feature",
  "properties": {
    "addr:full":"Looiersgracht 14 Amsterdam Noord-Holland 1016 VS",
    "addr:housenumber":"14",
    "addr:postcode":"1016 vs",
    "addr:street":"Looiersgracht",
    "iso:country":"NL",
    "sg:address":"Looiersgracht 14",
    "sg:city":"Amsterdam",
    "sg:orig_category":"Glaszetten",
    "sg:phone":"+31 20 623 6214",
    "sg:postcode":"1016 VS",
    "sg:province":"Noord-Holland",
    "wof:name":"Zaansche Glas In Loodzetterij",
    "wof:placetype":"venue"
},
  "geometry": {"coordinates":[-74.170609,42.972134],"type":"Point"}
}