{
  "type": "Feature",
  "properties": {
    "addr:full":"Julianastr 2 Zwartsluis Overijssel 8064 CD",
    "addr:housenumber":"2",
    "addr:postcode":"8064 cd",
    "addr:street":"Julianastr",
    "iso:country":"NL",
    "sg:address":"Julianastr 2",
    "sg:city":"Zwartsluis",
    "sg:orig_category":"Scholen Voor Basisonderwijs",
    "sg:phone":"+31 38 386 7520",
    "sg:postcode":"8064 CD",
    "sg:province":"Overijssel",
    "wof:name":"Aremberg Openbaar",
    "wof:placetype":"venue"
},
  "geometry": {"coordinates":[6.069472,52.64389],"type":"Point"}
}