{
  "type": "Feature",
  "properties": {
    "addr:full":"Schoolstr 38 St Philipsland Zeeland 4675 BM",
    "addr:housenumber":"38",
    "addr:postcode":"4675 bm",
    "addr:street":"Schoolstr;St Philipsland",
    "iso:country":"NL",
    "sg:address":"Schoolstr 38",
    "sg:city":"St Philipsland",
    "sg:orig_category":"Grafisch Ontwerpers",
    "sg:phone":"+31 167 572 606",
    "sg:postcode":"4675 BM",
    "sg:province":"Zeeland",
    "wof:name":"Kunst, Atelier",
    "wof:placetype":"venue"
},
  "geometry": {"coordinates":[4.165127,51.617264],"type":"Point"}
}