{
  "type": "Feature",
  "properties": {
    "addr:full":"S Gravendykwal 130 Rotterdam Zuid-Holland 3015 CC",
    "addr:housenumber":"130",
    "addr:postcode":"3015 cc",
    "iso:country":"NL",
    "sg:address":"S Gravendykwal 130",
    "sg:city":"Rotterdam",
    "sg:orig_category":"Sauna'S",
    "sg:phone":"+31 10 436 6285",
    "sg:postcode":"3015 CC",
    "sg:province":"Zuid-Holland",
    "wof:name":"Spartacus",
    "wof:placetype":"venue"
},
  "geometry": {"coordinates":[4.464117,51.913574],"type":"Point"}
}