{
  "type": "Feature",
  "properties": {
    "addr:full":"Staartmeeslaan 2 Bilthoven Utrecht 3722 CR",
    "addr:housenumber":"2",
    "addr:postcode":"3722 cr",
    "addr:street":"Staartmeeslaan",
    "iso:country":"NL",
    "sg:address":"Staartmeeslaan 2",
    "sg:city":"Bilthoven",
    "sg:orig_category":"Boekhouders",
    "sg:phone":"+31 30 228 6538",
    "sg:postcode":"3722 CR",
    "sg:province":"Utrecht",
    "wof:name":"Administratiekantoor Bleeker",
    "wof:placetype":"venue"
},
  "geometry": {"coordinates":[5.21417,52.126183],"type":"Point"}
}