{
  "type": "Feature",
  "properties": {
    "addr:full":"Burg Grothestr 80 Soest Utrecht 3761 CN",
    "addr:housenumber":"80",
    "addr:postcode":"3761 cn",
    "addr:street":"Burg;Soest",
    "iso:country":"NL",
    "sg:address":"Burg Grothestr 80",
    "sg:city":"Soest",
    "sg:orig_category":"Bejaarden - Verzorgingstehuizen",
    "sg:phone":"+31 35 602 2044",
    "sg:postcode":"3761 CN",
    "sg:province":"Utrecht",
    "wof:name":"Mari?nburg",
    "wof:placetype":"venue"
},
  "geometry": {"coordinates":[5.284792,52.187901],"type":"Point"}
}