{
  "type": "Feature",
  "properties": {
    "iso:country":"NL",
    "sg:address":"Loopkantstr 1A",
    "sg:city":"Uden",
    "sg:orig_category":"Accountants - Administratie- Consulenten En -Kantoren",
    "sg:phone":"+31 413 262 655",
    "sg:postcode":"5405 NB",
    "sg:province":"North Brabant",
    "wof:name":"Gibo Groep",
    "wof:placetype":"venue"
},
  "geometry": {"coordinates":[5.628518,51.655361],"type":"Point"}
}