{
  "type": "Feature",
  "properties": {
    "addr:full":"Loopkantstr 1A Uden North Brabant 5405 NB",
    "addr:housenumber":"1a",
    "addr:postcode":"5405 nb",
    "addr:street":"Loopkantstr",
    "iso:country":"NL",
    "sg:address":"Loopkantstr 1A",
    "sg:city":"Uden",
    "sg:orig_category":"Accountants - Administratie- Consulenten En -Kantoren",
    "sg:phone":"+31 413 262 655",
    "sg:postcode":"5405 NB",
    "sg:province":"North Brabant",
    "wof:name":"Gibo Groep",
    "wof:placetype":"venue"
},
  "geometry": {"coordinates":[5.628518,51.655361],"type":"Point"}
}