{
  "type": "Feature",
  "properties": {
    "addr:full":"Nazareth 4 Wolphaartsdijk Zeeland 4471 AC",
    "addr:housenumber":"4",
    "addr:postcode":"4471 ac",
    "addr:street":"Nazareth",
    "iso:country":"NL",
    "sg:address":"Nazareth 4",
    "sg:city":"Wolphaartsdijk",
    "sg:orig_category":"Zalenexploitatie",
    "sg:phone":"+31 113 581 152",
    "sg:postcode":"4471 AC",
    "sg:province":"Zeeland",
    "wof:name":"Galerie De Hoekweide",
    "wof:placetype":"venue"
},
  "geometry": {"coordinates":[3.8232,51.532829],"type":"Point"}
}