{
  "type": "Feature",
  "properties": {
    "iso:country":"NL",
    "sg:address":"Laag Boskoop 106",
    "sg:city":"Boskoop",
    "sg:orig_category":"Fruitteelt",
    "sg:phone":"+31 172 213 306",
    "sg:postcode":"2771 GZ",
    "sg:province":"Zuid-Holland",
    "wof:name":"Handelskwekerij J Bos",
    "wof:placetype":"venue"
},
  "geometry": {"coordinates":[4.643692,52.082382],"type":"Point"}
}