{
  "type": "Feature",
  "properties": {
    "addr:full":"K Boswg 33 T Zand Nh North Holland 1756 CA",
    "addr:housenumber":"33",
    "addr:postcode":"1756 ca",
    "addr:street":"Boswg;Zand Nh North",
    "iso:country":"NL",
    "sg:address":"K Boswg 33",
    "sg:city":"T Zand Nh",
    "sg:orig_category":"Begrafenisverzorging",
    "sg:phone":"+31 224 593 116",
    "sg:postcode":"1756 CA",
    "sg:province":"North Holland",
    "wof:name":"Joseph Uitvaartver, St",
    "wof:placetype":"venue"
},
  "geometry": {"coordinates":[4.756705,52.83548],"type":"Point"}
}