{
  "type": "Feature",
  "properties": {
    "iso:country":"NL",
    "sg:address":"Edisonstr 18A",
    "sg:city":"Leeuwarden",
    "sg:orig_category":"Automaterialen En Gereedschappen",
    "sg:phone":"+31 58 295 8970",
    "sg:postcode":"8912 AW",
    "sg:province":"Friesland",
    "wof:name":"Buren Hallum Bv",
    "wof:placetype":"venue"
},
  "geometry": {"coordinates":[5.771206,53.190144],"type":"Point"}
}