{
  "type": "Feature",
  "properties": {
    "addr:full":"Voorwg 18 Oostvoorne Zuid-Holland 3233 SK",
    "addr:housenumber":"18",
    "addr:street":"Voorwg;3233",
    "iso:country":"NL",
    "sg:address":"Voorwg 18",
    "sg:city":"Oostvoorne",
    "sg:orig_category":"Administratie- En Boekhoudkantoren",
    "sg:phone":"+31 181 482 725",
    "sg:postcode":"3233 SK",
    "sg:province":"Zuid-Holland",
    "wof:name":"Bruin, J De",
    "wof:placetype":"venue"
},
  "geometry": {"coordinates":[4.102117,51.912868],"type":"Point"}
}