{
  "type": "Feature",
  "properties": {
    "addr:full":"Oranjestr 11 Heeswyk Dinther North Brabant 5473 EV",
    "addr:housenumber":"11",
    "addr:postcode":"5473 ev",
    "addr:street":"Oranjestr",
    "iso:country":"NL",
    "sg:address":"Oranjestr 11",
    "sg:city":"Heeswyk Dinther",
    "sg:orig_category":"Montagebedrijven",
    "sg:phone":"+31 413 293 260",
    "sg:postcode":"5473 EV",
    "sg:province":"North Brabant",
    "wof:name":"Verwi Vof",
    "wof:placetype":"venue"
},
  "geometry": {"coordinates":[5.482252,51.650639],"type":"Point"}
}