{
  "type": "Feature",
  "properties": {
    "addr:full":"Poeldyksepad 5 Honselersdyk Zuid-Holland 2675 CL",
    "addr:housenumber":"5",
    "addr:postcode":"2675",
    "addr:street":"Poeldyksepad",
    "iso:country":"NL",
    "sg:address":"Poeldyksepad 5",
    "sg:city":"Honselersdyk",
    "sg:orig_category":"Onroerende Goederen",
    "sg:phone":"+31 174 631 131",
    "sg:postcode":"2675 CL",
    "sg:province":"Zuid-Holland",
    "sg:website":"http://www.volbar.nl",
    "wof:name":"Vollebregt-Barten",
    "wof:placetype":"venue"
},
  "geometry": {"coordinates":[4.22951,52.008755],"type":"Point"}
}