{
  "type": "Feature",
  "properties": {
    "addr:full":"Hof V Sonoy 4 Alkmaar North Holland 1811 LD",
    "addr:housenumber":"4",
    "addr:postcode":"1811 ld",
    "addr:street":"Sonoy",
    "iso:country":"NL",
    "sg:address":"Hof V Sonoy 4",
    "sg:city":"Alkmaar",
    "sg:orig_category":"Kappers",
    "sg:phone":"+31 72 511 7374",
    "sg:postcode":"1811 LD",
    "sg:province":"North Holland",
    "wof:name":"Neverland Haarstudio",
    "wof:placetype":"venue"
},
  "geometry": {"coordinates":[4.746258,52.634361],"type":"Point"}
}