{
  "type": "Feature",
  "properties": {
    "addr:full":"Geestbrugweg 74 Rijswijk Zh Zuid-Holland 2281 CP",
    "addr:housenumber":"74",
    "addr:postcode":"zh;2281 cp",
    "addr:street":"Geestbrugweg",
    "iso:country":"NL",
    "sg:address":"Geestbrugweg 74",
    "sg:city":"Rijswijk Zh",
    "sg:orig_category":"Boekhouders",
    "sg:phone":"+31 70 390 7868",
    "sg:postcode":"2281 CP",
    "sg:province":"Zuid-Holland",
    "wof:name":"Mevisco",
    "wof:placetype":"venue"
},
  "geometry": {"coordinates":[4.342776,52.058594],"type":"Point"}
}