{
  "type": "Feature",
  "properties": {
    "iso:country":"NL",
    "sg:address":"Postbus 46",
    "sg:city":"Wychen",
    "sg:orig_category":"Bakkerijbenodigdheden En -Grondstoffen",
    "sg:phone":"+31 24 641 5304",
    "sg:postcode":"6600 AA",
    "wof:name":"Orafti Bv",
    "wof:placetype":"venue"
},
  "geometry": {"coordinates":[5.69934,51.820381],"type":"Point"}
}