{
  "type": "Feature",
  "properties": {
    "addr:full":"Bachstraat 52 Oirsbeek Limburg 6438 KM",
    "addr:housenumber":"52",
    "addr:postcode":"6438 km",
    "addr:street":"Bachstraat",
    "iso:country":"NL",
    "sg:address":"Bachstraat 52",
    "sg:city":"Oirsbeek",
    "sg:orig_category":"Boekhouders",
    "sg:phone":"+31 46 442 2730",
    "sg:postcode":"6438 KM",
    "sg:province":"Limburg",
    "wof:name":"Administratiekantoor B. Dackus",
    "wof:placetype":"venue"
},
  "geometry": {"coordinates":[5.91453,50.947109],"type":"Point"}
}