{
  "type": "Feature",
  "properties": {
    "addr:full":"Selma Lagerlof-Erf 8 Dordrecht South Holland 3315 AP",
    "addr:housenumber":"8",
    "addr:postcode":"3315 ap",
    "iso:country":"NL",
    "sg:address":"Selma Lagerlof-Erf 8",
    "sg:city":"Dordrecht",
    "sg:orig_category":"Boekenuitgeverijen",
    "sg:phone":"+31 78 621 5871",
    "sg:postcode":"3315 AP",
    "sg:province":"South Holland",
    "wof:name":"Liverse",
    "wof:placetype":"venue"
},
  "geometry": {"coordinates":[4.724035,51.799534],"type":"Point"}
}