{
  "type": "Feature",
  "properties": {
    "addr:full":"Kapelstraat 12 Lisse Zuid-Holland 2161 HD",
    "addr:housenumber":"12",
    "addr:postcode":"2161 hd",
    "addr:street":"Kapelstraat",
    "iso:country":"NL",
    "sg:address":"Kapelstraat 12",
    "sg:city":"Lisse",
    "sg:classifiers":[
        {
            "category":"Bakery",
            "type":"Food & Drink"
        }
    ],
    "sg:phone":"+31 252 418 113",
    "sg:postcode":"2161 HD",
    "sg:province":"Zuid-Holland",
    "sg:tags":[
        "brood",
        "banket"
    ],
    "wof:name":"Le Bonbon",
    "wof:placetype":"venue"
},
  "geometry": {"coordinates":[4.556235,52.259228],"type":"Point"}
}