{
  "type": "Feature",
  "properties": {
    "iso:country":"NL",
    "sg:address":"J Barneveldstr 17",
    "sg:city":"Linschoten",
    "sg:orig_category":"Verenigingsgebouwen",
    "sg:phone":"+31 348 422 295",
    "sg:postcode":"3461 GA",
    "sg:province":"Utrecht",
    "wof:name":"Trefpunt",
    "wof:placetype":"venue"
},
  "geometry": {"coordinates":[4.916606,52.063572],"type":"Point"}
}