{
  "type": "Feature",
  "properties": {
    "iso:country":"NL",
    "sg:address":"Padoxln 23",
    "sg:city":"Warmond",
    "sg:orig_category":"Makelaars En Adviseurs Onroerende Goederen",
    "sg:phone":"+31 71 301 1015",
    "sg:postcode":"2361 KT",
    "sg:province":"South Holland",
    "sg:website":"http://www.vanoostrum.nu",
    "wof:name":"Oostrum Makelaardij, Van",
    "wof:placetype":"venue"
},
  "geometry": {"coordinates":[4.50471,52.198509],"type":"Point"}
}