{
  "type": "Feature",
  "properties": {
    "iso:country":"NL",
    "sg:address":"Bloemenstr 13",
    "sg:city":"Ridderkerk",
    "sg:orig_category":"Koeriersdiensten",
    "sg:phone":"+31 180 432 009",
    "sg:postcode":"2981 BD",
    "sg:province":"Zuid-Holland",
    "wof:name":"Levering",
    "wof:placetype":"venue"
},
  "geometry": {"coordinates":[4.593355,51.863613],"type":"Point"}
}