{
  "type": "Feature",
  "properties": {
    "addr:full":"Sud 62 Workum Provincie Friesland 8711 CW",
    "addr:housenumber":"62",
    "addr:postcode":"8711 cw",
    "addr:street":"Provincie Friesland",
    "iso:country":"NL",
    "sg:address":"Sud 62",
    "sg:city":"Workum",
    "sg:orig_category":"Bloemen And Planten",
    "sg:phone":"+31 515 541 075",
    "sg:postcode":"8711 CW",
    "sg:province":"Provincie Friesland",
    "wof:name":"Bloemenboetiek Stengels",
    "wof:placetype":"venue"
},
  "geometry": {"coordinates":[5.439767,52.977116],"type":"Point"}
}