{
  "type": "Feature",
  "properties": {
    "addr:full":"Churchilllaan 156 Utrecht Utrecht 3527 GX",
    "addr:housenumber":"156",
    "addr:postcode":"3527 gx",
    "addr:street":"Churchilllaan",
    "iso:country":"NL",
    "sg:address":"Churchilllaan 156",
    "sg:city":"Utrecht",
    "sg:orig_category":"Fitnesscentra",
    "sg:phone":"+31 30 280 3301",
    "sg:postcode":"3527 GX",
    "sg:province":"Utrecht",
    "wof:name":"Sportcentrum Frans Jansen",
    "wof:placetype":"venue"
},
  "geometry": {"coordinates":[5.09091,52.072186],"type":"Point"}
}