{
  "type": "Feature",
  "properties": {
    "addr:full":"V Meterenstr 31 Tilburg Noord-Brabant 5014 KC",
    "addr:housenumber":"31",
    "addr:postcode":"5014 kc",
    "iso:country":"NL",
    "sg:address":"V Meterenstr 31",
    "sg:city":"Tilburg",
    "sg:orig_category":"Journalisten Freelance",
    "sg:phone":"+31 13 542 5123",
    "sg:postcode":"5014 KC",
    "sg:province":"Noord-Brabant",
    "wof:name":"Knapen & Pen",
    "wof:placetype":"venue"
},
  "geometry": {"coordinates":[5.106271,51.554928],"type":"Point"}
}