{
  "type": "Feature",
  "properties": {
    "addr:full":"Burgemeester Smitweg 97 Hazerswoude Dorp Zuid-Holland 2391 NG",
    "addr:housenumber":"97",
    "addr:postcode":"2391 ng",
    "addr:street":"Burgemeester Smitweg",
    "iso:country":"NL",
    "sg:address":"Burgemeester Smitweg 97",
    "sg:city":"Hazerswoude Dorp",
    "sg:orig_category":"Bloemen And Planten",
    "sg:phone":"+31 172 588 403",
    "sg:postcode":"2391 NG",
    "sg:province":"Zuid-Holland",
    "wof:name":"A.P. Straathof Bv",
    "wof:placetype":"venue"
},
  "geometry": {"coordinates":[4.637009,52.098217],"type":"Point"}
}