{
  "type": "Feature",
  "properties": {
    "iso:country":"NL",
    "sg:address":"Duistervoordsewg 87",
    "sg:city":"Twello",
    "sg:orig_category":"Kappers",
    "sg:phone":"+31 571 271 245",
    "sg:postcode":"7391 CC",
    "sg:province":"Gelderland",
    "wof:name":"H?? Barbier",
    "wof:placetype":"venue"
},
  "geometry": {"coordinates":[6.0950431824,52.2329673767],"type":"Point"}
}