{
  "type": "Feature",
  "properties": {
    "addr:full":"Eibergsestr 180 Haaksbergen NL.08 7481 HP",
    "addr:housenumber":"180;nl.08",
    "addr:postcode":"7481 hp",
    "iso:country":"NL",
    "sg:address":"Eibergsestr 180",
    "sg:city":"Haaksbergen",
    "sg:orig_category":"Oldtimers",
    "sg:phone":"+31 53 572 7920",
    "sg:postcode":"7481 HP",
    "sg:province":"NL.08",
    "wof:name":"Hietbrink",
    "wof:placetype":"venue"
},
  "geometry": {"coordinates":[6.724223,52.150566],"type":"Point"}
}