{
  "type": "Feature",
  "properties": {
    "addr:full":"Reinkenstr 69 S Gravenhage South Holland 2517 CR",
    "addr:housenumber":"69",
    "addr:postcode":"2517 cr",
    "addr:street":"Reinkenstr;S Gravenhage",
    "iso:country":"NL",
    "sg:address":"Reinkenstr 69",
    "sg:city":"S Gravenhage",
    "sg:orig_category":"Wassalons",
    "sg:phone":"+31 70 361 6314",
    "sg:postcode":"2517 CR",
    "sg:province":"South Holland",
    "wof:name":"Reinken Wassalon",
    "wof:placetype":"venue"
},
  "geometry": {"coordinates":[4.2870798111,52.0866699219],"type":"Point"}
}