{
  "type": "Feature",
  "properties": {
    "addr:full":"Telefoonweg 13 Ede Gld Gelderland 6712 GA",
    "addr:housenumber":"13",
    "addr:postcode":"6712 ga",
    "addr:street":"Telefoonweg;Gld Gelderland",
    "iso:country":"NL",
    "sg:address":"Telefoonweg 13",
    "sg:city":"Ede Gld",
    "sg:orig_category":"Paramedische Behandelingen",
    "sg:phone":"+31 318 612 554",
    "sg:postcode":"6712 GA",
    "sg:province":"Gelderland",
    "wof:name":"Verloskundig Team Ede",
    "wof:placetype":"venue"
},
  "geometry": {"coordinates":[5.666696,52.047775],"type":"Point"}
}