{
  "type": "Feature",
  "properties": {
    "iso:country":"NL",
    "sg:address":"Achillesln 66",
    "sg:city":"Eindhoven",
    "sg:orig_category":"Marktkramen",
    "sg:phone":"+31 40 243 0367",
    "sg:postcode":"5631 BV",
    "sg:province":"Noord-Brabant",
    "wof:name":"Waarden, M L Van Der",
    "wof:placetype":"venue"
},
  "geometry": {"coordinates":[5.50844,51.45776],"type":"Point"}
}