{
  "type": "Feature",
  "properties": {
    "addr:full":"Breukelaarweg 27 Varsseveld Gelderland 7051 DW",
    "addr:housenumber":"27",
    "addr:postcode":"7051 dw",
    "addr:street":"Breukelaarweg;Gelderland",
    "iso:country":"NL",
    "sg:address":"Breukelaarweg 27",
    "sg:city":"Varsseveld",
    "sg:orig_category":"Wegen And Sportterreinen",
    "sg:phone":"+31 315 243 194",
    "sg:postcode":"7051 DW",
    "sg:province":"Gelderland",
    "wof:name":"Vriezen Leidinginspektie Bv",
    "wof:placetype":"venue"
},
  "geometry": {"coordinates":[6.4735851288,51.9403419495],"type":"Point"}
}