{
  "type": "Feature",
  "properties": {
    "iso:country":"NL",
    "sg:address":"Industrieweg 26 A",
    "sg:city":"Den Helder",
    "sg:classifiers":[
        {
            "category":"Recreation",
            "subcategory":"Amusement Park",
            "type":"Entertainment"
        }
    ],
    "sg:phone":"+31 223 635 444",
    "sg:postcode":"1785 AG",
    "sg:province":"Noord-Holland",
    "wof:name":"Lasergame Den Helder",
    "wof:placetype":"venue"
},
  "geometry": {"coordinates":[4.781504,52.945026],"type":"Point"}
}