{
  "type": "Feature",
  "properties": {
    "addr:full":"De Kempenaerstr 85 Oegstgeest Zuid-Holland 2341 GJ",
    "addr:housenumber":"85",
    "addr:postcode":"2341 gj",
    "iso:country":"NL",
    "sg:address":"De Kempenaerstr 85",
    "sg:city":"Oegstgeest",
    "sg:classifiers":[
        {
            "category":"Food & Beverages",
            "subcategory":"Bakery",
            "type":"Retail Goods"
        }
    ],
    "sg:phone":"+31 71 517 3661",
    "sg:postcode":"2341 GJ",
    "sg:province":"Zuid-Holland",
    "sg:tags":[
        "pizza"
    ],
    "sg:website":"http://www.pizzaonline.nl/nannopiza",
    "wof:name":"Nano'S Pizza",
    "wof:placetype":"venue"
},
  "geometry": {"coordinates":[4.472288,52.177628],"type":"Point"}
}