{
  "type": "Feature",
  "properties": {
    "iso:country":"NL",
    "sg:address":"Heuvelwg 5",
    "sg:city":"Ossendrecht",
    "sg:orig_category":"Bloemen En Planten",
    "sg:phone":"+31 164 672 050",
    "sg:postcode":"4641 SC",
    "sg:province":"North Brabant",
    "wof:name":"Wilde Bosrank, De",
    "wof:placetype":"venue"
},
  "geometry": {"coordinates":[4.344222,51.390194],"type":"Point"}
}