{
  "type": "Feature",
  "properties": {
    "addr:full":"Ossenzijlerweg 1 Ossenzijl Overijssel 8376 HT",
    "addr:housenumber":"1",
    "addr:postcode":"8376 ht",
    "addr:street":"Ossenzijlerweg",
    "iso:country":"NL",
    "sg:address":"Ossenzijlerweg 1",
    "sg:city":"Ossenzijl",
    "sg:orig_category":"Juridische Dienstverlening",
    "sg:phone":"+31 561 477 677",
    "sg:postcode":"8376 HT",
    "sg:province":"Overijssel",
    "wof:name":"Juridisch Adviesbureau Somer & Somer",
    "wof:placetype":"venue"
},
  "geometry": {"coordinates":[5.931375,52.816162],"type":"Point"}
}