{
  "type": "Feature",
  "properties": {
    "iso:country":"NL",
    "sg:address":"Kanaal Oz 19",
    "sg:city":"Drijber",
    "sg:orig_category":"Kampeerterreinen",
    "sg:phone":"+31 528 331 326",
    "sg:postcode":"9419 TK",
    "sg:province":"Drenthe",
    "wof:name":"De Svr Stal",
    "wof:placetype":"venue"
},
  "geometry": {"coordinates":[6.5566210747,52.7735671997],"type":"Point"}
}