{
  "type": "Feature",
  "properties": {
    "iso:country":"NL",
    "sg:address":"Schonauwen 2",
    "sg:city":"Roden",
    "sg:orig_category":"Scholen Voor Basisonderwijs",
    "sg:phone":"+31 50 501 7300",
    "sg:postcode":"9301 SP",
    "sg:province":"Drenthe",
    "wof:name":"Valkhof Openb, Het",
    "wof:placetype":"venue"
},
  "geometry": {"coordinates":[6.410701,53.137871],"type":"Point"}
}