{
  "type": "Feature",
  "properties": {
    "addr:full":"Heyermansstr 30 Zaandam Noord-Holland 1502 DN",
    "addr:housenumber":"30",
    "addr:postcode":"1502 dn",
    "addr:street":"Heyermansstr",
    "iso:country":"NL",
    "sg:address":"Heyermansstr 30",
    "sg:city":"Zaandam",
    "sg:orig_category":"Onderhoudswerken",
    "sg:phone":"+31 75 612 1256",
    "sg:postcode":"1502 DN",
    "sg:province":"Noord-Holland",
    "wof:name":"Cimen",
    "wof:placetype":"venue"
},
  "geometry": {"coordinates":[4.82731,52.447559],"type":"Point"}
}