{
  "type": "Feature",
  "properties": {
    "iso:country":"NL",
    "sg:address":"Kerkln 242",
    "sg:city":"Ryswyk Zh",
    "sg:orig_category":"Acupunctuur",
    "sg:phone":"+31 70 399 5727",
    "sg:postcode":"2282 CS",
    "sg:province":"Zuid-Holland",
    "wof:name":"Spruit-De Mos, M C P",
    "wof:placetype":"venue"
},
  "geometry": {"coordinates":[4.33694,52.056503],"type":"Point"}
}