{
  "type": "Feature",
  "properties": {
    "addr:full":"Abbenbroekstr 10 Zaandam North Holland 1507 KE",
    "addr:housenumber":"10",
    "addr:postcode":"1507 ke",
    "addr:street":"Abbenbroekstr",
    "iso:country":"NL",
    "sg:address":"Abbenbroekstr 10",
    "sg:city":"Zaandam",
    "sg:orig_category":"Adviesbureaus Bedrijfsorganisatie",
    "sg:phone":"+31 75 670 9388",
    "sg:postcode":"1507 KE",
    "sg:province":"North Holland",
    "sg:website":"http://www.vansvision.nl",
    "wof:name":"Vansvision",
    "wof:placetype":"venue"
},
  "geometry": {"coordinates":[4.805666,52.449707],"type":"Point"}
}