{
  "type": "Feature",
  "properties": {
    "addr:full":"Blariacumstr 1 Venlo Limburg 5922 VV",
    "addr:housenumber":"1",
    "addr:postcode":"5922 vv",
    "addr:street":"Blariacumstr",
    "iso:country":"NL",
    "sg:address":"Blariacumstr 1",
    "sg:city":"Venlo",
    "sg:orig_category":"Zonweringen",
    "sg:phone":"+31 77 382 9694",
    "sg:postcode":"5922 VV",
    "sg:province":"Limburg",
    "wof:name":"Zonnehukske, 'T",
    "wof:placetype":"venue"
},
  "geometry": {"coordinates":[6.147613,51.37376],"type":"Point"}
}