{
  "type": "Feature",
  "properties": {
    "iso:country":"NL",
    "sg:address":"Kleiwg 151",
    "sg:city":"Rotterdam",
    "sg:orig_category":"Makelaars En Adviseurs Onroerende Goederen",
    "sg:phone":"+31 10 218 0280",
    "sg:postcode":"3051 GN",
    "sg:province":"South Holland",
    "sg:website":"http://WWW.WOONVISIE.NL",
    "wof:name":"Woonvisie",
    "wof:placetype":"venue"
},
  "geometry": {"coordinates":[4.475849,51.945389],"type":"Point"}
}