{
  "type": "Feature",
  "properties": {
    "addr:full":"Waleweinln 110 Geldrop Noord-Brabant 5665 CL",
    "addr:housenumber":"110",
    "addr:postcode":"5665",
    "iso:country":"NL",
    "sg:address":"Waleweinln 110",
    "sg:city":"Geldrop",
    "sg:orig_category":"Podotherapeuten",
    "sg:phone":"+31 40 285 8794",
    "sg:postcode":"5665 CL",
    "sg:province":"Noord-Brabant",
    "wof:name":"D\u00fasar",
    "wof:placetype":"venue"
},
  "geometry": {"coordinates":[5.56963,51.415894],"type":"Point"}
}