{
  "type": "Feature",
  "properties": {
    "addr:full":"Schaalbergerwg 26 Ter Apelkanaal Groningen 9563 TE",
    "addr:housenumber":"26",
    "addr:postcode":"9563 te",
    "addr:street":"Schaalbergerwg",
    "iso:country":"NL",
    "sg:address":"Schaalbergerwg 26",
    "sg:city":"Ter Apelkanaal",
    "sg:orig_category":"Houtgroothandel",
    "sg:phone":"+31 599 412 778",
    "sg:postcode":"9563 TE",
    "sg:province":"Groningen",
    "wof:name":"Folkers",
    "wof:placetype":"venue"
},
  "geometry": {"coordinates":[7.060127,52.913559],"type":"Point"}
}