{
  "type": "Feature",
  "properties": {
    "addr:full":"Burgemeester J G Legrowg 13 Paterswolde Drenthe 9765 AD",
    "addr:housenumber":"13",
    "addr:postcode":"9765 ad",
    "addr:street":"Burgemeester J G Legrowg",
    "iso:country":"NL",
    "sg:address":"Burgemeester J G Legrowg 13",
    "sg:city":"Paterswolde",
    "sg:orig_category":"Artsen And Specialisten",
    "sg:phone":"+31 50 309 1785",
    "sg:postcode":"9765 AD",
    "sg:province":"Drenthe",
    "wof:name":"H.H. Wit",
    "wof:placetype":"venue"
},
  "geometry": {"coordinates":[6.568193,53.144112],"type":"Point"}
}