{
  "type": "Feature",
  "properties": {
    "addr:full":"Zytocht 6 Zaandam Noord-Holland 1507 CD",
    "addr:housenumber":"6",
    "addr:postcode":"1507 cd",
    "addr:street":"Zytocht",
    "iso:country":"NL",
    "sg:address":"Zytocht 6",
    "sg:city":"Zaandam",
    "sg:orig_category":"Bestratingen",
    "sg:phone":"+31 75 616 0028",
    "sg:postcode":"1507 CD",
    "sg:province":"Noord-Holland",
    "wof:name":"Spruit Bestratingen, Gebrs",
    "wof:placetype":"venue"
},
  "geometry": {"coordinates":[4.809725,52.428291],"type":"Point"}
}