{
  "type": "Feature",
  "properties": {
    "addr:full":"Pres Rooseveltln 238 Vlissingen Zeeland 4382 KZ",
    "addr:housenumber":"238",
    "addr:postcode":"4382",
    "iso:country":"NL",
    "sg:address":"Pres Rooseveltln 238",
    "sg:city":"Vlissingen",
    "sg:classifiers":[
        {
            "category":"Shopping",
            "subcategory":"Gifts & Souvenirs",
            "type":"Retail Goods"
        }
    ],
    "sg:phone":"+31 118 413 528",
    "sg:postcode":"4382 KZ",
    "sg:province":"Zeeland",
    "sg:tags":[
        "wens-",
        "en",
        "prentbriefkaarten"
    ],
    "wof:name":"Kaart, F A De",
    "wof:placetype":"venue"
},
  "geometry": {"coordinates":[3.5684950352,51.4554710388],"type":"Point"}
}