{
  "type": "Feature",
  "properties": {
    "addr:full":"Ledderwg 17 Epe Gelderland 8161 SZ",
    "addr:housenumber":"17",
    "addr:postcode":"8161 sz",
    "addr:street":"Ledderwg;Gelderland",
    "iso:country":"NL",
    "sg:address":"Ledderwg 17",
    "sg:city":"Epe",
    "sg:orig_category":"Administratie- En Boekhoudkantoren",
    "sg:phone":"+31 578 629 860",
    "sg:postcode":"8161 SZ",
    "sg:province":"Gelderland",
    "wof:name":"Kerkelyk Bureau",
    "wof:placetype":"venue"
},
  "geometry": {"coordinates":[5.997822,52.334225],"type":"Point"}
}