{
  "type": "Feature",
  "properties": {
    "addr:full":"Radboudweg 3 Rhenen Utrecht 3911 BE",
    "addr:housenumber":"3",
    "addr:postcode":"3911",
    "addr:street":"Radboudweg",
    "iso:country":"NL",
    "sg:address":"Radboudweg 3",
    "sg:city":"Rhenen",
    "sg:orig_category":"Technische Studies And Onderzoek",
    "sg:phone":"+31 317 619 121",
    "sg:postcode":"3911 BE",
    "sg:province":"Utrecht",
    "wof:name":"Interstructure Bv Research En Development",
    "wof:placetype":"venue"
},
  "geometry": {"coordinates":[5.581215,51.960011],"type":"Point"}
}