{
  "type": "Feature",
  "properties": {
    "iso:country":"NL",
    "sg:address":"Dorpbroekstr 1",
    "sg:city":"Meerlo",
    "sg:orig_category":"Tuingereedschappen En Tuinmachines",
    "sg:phone":"+31 478 698 080",
    "sg:postcode":"5864 CP",
    "sg:province":"Limburg",
    "wof:name":"Kusters, Frans",
    "wof:placetype":"venue"
},
  "geometry": {"coordinates":[6.089539,51.512405],"type":"Point"}
}