{
  "type": "Feature",
  "properties": {
    "addr:full":"Bremenwg 2 Deventer Overijssel 7418 EJ",
    "addr:housenumber":"2",
    "addr:postcode":"7418 ej",
    "addr:street":"Bremenwg",
    "iso:country":"NL",
    "sg:address":"Bremenwg 2",
    "sg:city":"Deventer",
    "sg:orig_category":"Gasapparaten En -Artikelen - Reparatie En Onderhoud",
    "sg:phone":"+31 570 676 350",
    "sg:postcode":"7418 EJ",
    "sg:province":"Overijssel",
    "wof:name":"Essent",
    "wof:placetype":"venue"
},
  "geometry": {"coordinates":[6.196796,52.242393],"type":"Point"}
}