{
  "type": "Feature",
  "properties": {
    "iso:country":"NL",
    "sg:address":"Postbus 42",
    "sg:city":"Balk",
    "sg:orig_category":"Adviesbureaus Bouwkunde",
    "sg:phone":"+31 514 605 017",
    "sg:postcode":"8560 AA",
    "sg:province":"Oklahoma",
    "wof:name":"Dijk, Van",
    "wof:placetype":"venue"
},
  "geometry": {"coordinates":[-100.82858299999999,36.608829],"type":"Point"}
}