{
  "type": "Feature",
  "properties": {
    "iso:country":"NL",
    "sg:address":"Dalsteindreef 59",
    "sg:city":"Diemen",
    "sg:orig_category":"Krantenuitgeverijen",
    "sg:phone":"+31 20 522 2444",
    "sg:postcode":"1112 XC",
    "sg:province":"North Holland",
    "wof:name":"Aktu Publishing Group",
    "wof:placetype":"venue"
},
  "geometry": {"coordinates":[4.954848,52.328442],"type":"Point"}
}