{
  "type": "Feature",
  "properties": {
    "iso:country":"NL",
    "sg:address":"Broekhem 78",
    "sg:city":"Valkenburg Lb",
    "sg:classifiers":[
        {
            "category":"Travel",
            "subcategory":"Hotels & Motels",
            "type":"Entertainment"
        }
    ],
    "sg:phone":"+31 43 601 6994",
    "sg:postcode":"6301 HK",
    "sg:province":"Limburg",
    "wof:name":"Roo",
    "wof:placetype":"venue"
},
  "geometry": {"coordinates":[5.822714,50.871304],"type":"Point"}
}