{
  "type": "Feature",
  "properties": {
    "iso:country":"NL",
    "sg:address":"Stationsstraat 37A",
    "sg:city":"Ermelo",
    "sg:classifiers":[
        {
            "category":"Retail",
            "subcategory":"Photofinishing",
            "type":"Services"
        }
    ],
    "sg:phone":"+31 341 550 094",
    "sg:postcode":"3851 NA",
    "sg:province":"Gelderland",
    "sg:tags":[
        "foto",
        "film"
    ],
    "wof:name":"`T Combi Jelle Paulus En Dochter",
    "wof:placetype":"venue"
},
  "geometry": {"coordinates":[5.626832,52.300365],"type":"Point"}
}