{
  "type": "Feature",
  "properties": {
    "addr:full":"Delta 54 Arnhem Gelderland 6825 MS",
    "addr:housenumber":"54",
    "addr:postcode":"6825 ms",
    "addr:street":"Delta",
    "iso:country":"NL",
    "sg:address":"Delta 54",
    "sg:city":"Arnhem",
    "sg:orig_category":"Milieu",
    "sg:phone":"+31 26 376 0250",
    "sg:postcode":"6825 MS",
    "sg:province":"Gelderland",
    "sg:website":"http://www.optimumenvitech.nl",
    "wof:name":"Optimum",
    "wof:placetype":"venue"
},
  "geometry": {"coordinates":[5.972239,51.97654],"type":"Point"}
}