{
  "type": "Feature",
  "properties": {
    "addr:full":"Rijksweg-Zuid 93 Rucphen North Brabant 4715 TA",
    "addr:housenumber":"93",
    "addr:postcode":"4715 ta",
    "addr:street":"Rijksweg-Zuid",
    "iso:country":"NL",
    "sg:address":"Rijksweg-Zuid 93",
    "sg:city":"Rucphen",
    "sg:orig_category":"Metaalvrije Afvalrecycling",
    "sg:phone":"+31 165 346 440",
    "sg:postcode":"4715 TA",
    "sg:province":"North Brabant",
    "wof:name":"Lignac Cv",
    "wof:placetype":"venue"
},
  "geometry": {"coordinates":[4.528101,51.547016],"type":"Point"}
}