{
  "type": "Feature",
  "properties": {
    "addr:full":"Maaseikstraat 55 Breda Noord-Brabant 4826 LR",
    "addr:housenumber":"55",
    "addr:postcode":"4826 lr",
    "addr:street":"Maaseikstraat",
    "iso:country":"NL",
    "sg:address":"Maaseikstraat 55",
    "sg:city":"Breda",
    "sg:orig_category":"Juweliers",
    "sg:phone":"+31 76 587 2910",
    "sg:postcode":"4826 LR",
    "sg:province":"Noord-Brabant",
    "wof:name":"Goud En Zilversmederij Abc",
    "wof:placetype":"venue"
},
  "geometry": {"coordinates":[4.78237,51.605888],"type":"Point"}
}