{
  "type": "Feature",
  "properties": {
    "addr:full":"Breukelsestraat 5A Boxtel North Brabant 5281 HA",
    "addr:housenumber":"5a",
    "addr:postcode":"5281 ha",
    "addr:street":"Breukelsestraat",
    "iso:country":"NL",
    "sg:address":"Breukelsestraat 5A",
    "sg:city":"Boxtel",
    "sg:orig_category":"Kinderkleding",
    "sg:phone":"+31 411 685 231",
    "sg:postcode":"5281 HA",
    "sg:province":"North Brabant",
    "wof:name":"Hannes En Ko",
    "wof:placetype":"venue"
},
  "geometry": {"coordinates":[5.320923,51.587032],"type":"Point"}
}