{
  "type": "Feature",
  "properties": {
    "iso:country":"NL",
    "sg:address":"Frankeneng 18",
    "sg:city":"Ede Gld",
    "sg:orig_category":"Voeding, Dranken And Tabak Gh",
    "sg:phone":"+31 318 678 911",
    "sg:postcode":"6716 AA",
    "sg:province":"Gelderland",
    "wof:name":"Grootverbruik Ahold Bv",
    "wof:placetype":"venue"
},
  "geometry": {"coordinates":[5.637134,52.033813],"type":"Point"}
}