{
  "type": "Feature",
  "properties": {
    "addr:full":"Transitoweg 9 Moerdijk Noord-Brabant 4782 SM",
    "addr:housenumber":"9",
    "addr:postcode":"4782 sm",
    "addr:street":"Transitoweg",
    "iso:country":"NL",
    "sg:address":"Transitoweg 9",
    "sg:city":"Moerdijk",
    "sg:classifiers":[
        {
            "category":"Retail",
            "subcategory":"Storage",
            "type":"Services"
        }
    ],
    "sg:phone":"+31 168 380 484",
    "sg:postcode":"4782 SM",
    "sg:province":"Noord-Brabant",
    "sg:tags":[
        "opslag",
        "bewaring"
    ],
    "wof:name":"Talke Forwarding Nederland Bv",
    "wof:placetype":"venue"
},
  "geometry": {"coordinates":[4.6099390984,51.6783180237],"type":"Point"}
}