{
  "type": "Feature",
  "properties": {
    "iso:country":"NL",
    "sg:address":"Anna Paulownastraat 5",
    "sg:city":"Geldermalsen",
    "sg:orig_category":"Diverse Grafische Activiteiten",
    "sg:phone":"+31 345 581 454",
    "sg:postcode":"4191 GJ",
    "sg:province":"Gelderland",
    "wof:name":"Bejo",
    "wof:placetype":"venue"
},
  "geometry": {"coordinates":[5.292309,51.880436],"type":"Point"}
}