{
  "type": "Feature",
  "properties": {
    "addr:full":"Sorghvlietlaan 50 Andijk North Holland 1619 XC",
    "addr:housenumber":"50",
    "addr:postcode":"1619 xc",
    "addr:street":"Sorghvlietlaan",
    "iso:country":"NL",
    "sg:address":"Sorghvlietlaan 50",
    "sg:city":"Andijk",
    "sg:orig_category":"Bejaardeninstellingen And Serviceflats",
    "sg:phone":"+31 228 593 751",
    "sg:postcode":"1619 XC",
    "sg:province":"North Holland",
    "wof:name":"Dagverzorging Ouderen Andijk",
    "wof:placetype":"venue"
},
  "geometry": {"coordinates":[5.220125,52.746567],"type":"Point"}
}