{
  "type": "Feature",
  "properties": {
    "iso:country":"NL",
    "sg:address":"Sorghvlietlaan 50",
    "sg:city":"Andijk",
    "sg:orig_category":"Bejaardeninstellingen And Serviceflats",
    "sg:phone":"+31 228 593 751",
    "sg:postcode":"1619 XC",
    "sg:province":"North Holland",
    "wof:name":"Dagverzorging Ouderen Andijk",
    "wof:placetype":"venue"
},
  "geometry": {"coordinates":[5.220125,52.746567],"type":"Point"}
}