{
  "type": "Feature",
  "properties": {
    "addr:full":"Prins Bernhardlaan 32 Soest Utrecht 3761 AC",
    "addr:housenumber":"32",
    "addr:postcode":"3761 ac",
    "addr:street":"Prins Bernhardlaan",
    "iso:country":"NL",
    "sg:address":"Prins Bernhardlaan 32",
    "sg:city":"Soest",
    "sg:orig_category":"Verzekeringen",
    "sg:phone":"+31 35 601 2928",
    "sg:postcode":"3761 AC",
    "sg:province":"Utrecht",
    "wof:name":"Assurantieadviesburo Rajemar",
    "wof:placetype":"venue"
},
  "geometry": {"coordinates":[5.29534,52.182583],"type":"Point"}
}