{
  "type": "Feature",
  "properties": {
    "addr:full":"Mollerusstraat 1 Baarn Utrecht 3743 BW",
    "addr:housenumber":"1",
    "addr:postcode":"3743 bw",
    "addr:street":"Mollerusstraat",
    "iso:country":"NL",
    "sg:address":"Mollerusstraat 1",
    "sg:city":"Baarn",
    "sg:orig_category":"Diverse Consumentenartikelen Gh",
    "sg:phone":"+31 35 541 8800",
    "sg:postcode":"3743 BW",
    "sg:province":"Utrecht",
    "wof:name":"Israel Economic & Trade Center Bv",
    "wof:placetype":"venue"
},
  "geometry": {"coordinates":[5.289514,52.211727],"type":"Point"}
}