{
  "type": "Feature",
  "properties": {
    "addr:full":"Utrechtseweg 178 Oosterbeek Gelderland 6862 AV",
    "addr:housenumber":"178",
    "addr:postcode":"6862 av",
    "addr:street":"Utrechtseweg;Gelderland",
    "iso:country":"NL",
    "sg:address":"Utrechtseweg 178",
    "sg:city":"Oosterbeek",
    "sg:orig_category":"Damesmodezaken",
    "sg:phone":"+31 26 334 2913",
    "sg:postcode":"6862 AV",
    "sg:province":"Gelderland",
    "wof:name":"Modehuis La Dame",
    "wof:placetype":"venue"
},
  "geometry": {"coordinates":[5.840557,51.987572],"type":"Point"}
}