{
  "type": "Feature",
  "properties": {
    "iso:country":"NL",
    "sg:address":"Winkelwg 32",
    "sg:city":"Posterholt",
    "sg:orig_category":"Makelaars En Adviseurs Onroerende Goederen",
    "sg:phone":"+31 475 407 044",
    "sg:postcode":"6061 AE",
    "sg:province":"Limburg",
    "wof:name":"Roerstreek Vastgoed",
    "wof:placetype":"venue"
},
  "geometry": {"coordinates":[6.034341,51.114838],"type":"Point"}
}