{
  "type": "Feature",
  "properties": {
    "addr:full":"Provincialeweg 4 Amsterdam Zuidoost Noord-Holland 1108 AA",
    "addr:housenumber":"4",
    "addr:postcode":"zuidoost;1108 aa",
    "addr:street":"Provincialeweg",
    "iso:country":"NL",
    "sg:address":"Provincialeweg 4",
    "sg:city":"Amsterdam Zuidoost",
    "sg:orig_category":"Vertaal- And Tolkenbureaus",
    "sg:phone":"+31 294 416 695",
    "sg:postcode":"1108 AA",
    "sg:province":"Noord-Holland",
    "wof:name":"Vertaalburo Wiering",
    "wof:placetype":"venue"
},
  "geometry": {"coordinates":[4.998471,52.312206],"type":"Point"}
}