{
  "type": "Feature",
  "properties": {
    "addr:full":"Gen Simondsstr 12 Bergen Op Zoom Noord-Brabant 4624 GX",
    "addr:housenumber":"12",
    "addr:postcode":"4624 gx",
    "iso:country":"NL",
    "sg:address":"Gen Simondsstr 12",
    "sg:city":"Bergen Op Zoom",
    "sg:orig_category":"Kappers",
    "sg:phone":"+31 164 237 783",
    "sg:postcode":"4624 GX",
    "sg:province":"Noord-Brabant",
    "wof:name":"Markiezin, De",
    "wof:placetype":"venue"
},
  "geometry": {"coordinates":[4.297448,51.487869],"type":"Point"}
}