{
  "type": "Feature",
  "properties": {
    "iso:country":"NL",
    "sg:address":"De Mossel 7",
    "sg:city":"Noord Scharwoude",
    "sg:orig_category":"Accountants - Administratie- Consulenten En -Kantoren",
    "sg:phone":"+31 226 313 376",
    "sg:postcode":"1723 HZ",
    "sg:province":"North Holland",
    "sg:website":"http://www.vanderlaangroep.nl",
    "wof:name":"Vanderlaangroep",
    "wof:placetype":"venue"
},
  "geometry": {"coordinates":[4.804574,52.704292],"type":"Point"}
}