{
  "type": "Feature",
  "properties": {
    "addr:full":"Louis Bouwmeesterstraat 1 A Rijswijk Zh South Holland 2284 XM",
    "addr:housenumber":"1 a",
    "addr:postcode":"2284 xm",
    "addr:street":"Louis Bouwmeesterstraat",
    "iso:country":"NL",
    "sg:address":"Louis Bouwmeesterstraat 1 A",
    "sg:city":"Rijswijk Zh",
    "sg:orig_category":"Kinderopvang Behalve Thuis",
    "sg:phone":"+31 70 396 3081",
    "sg:postcode":"2284 XM",
    "sg:province":"South Holland",
    "wof:name":"Kinderdagverblijf De Blauwe Uil",
    "wof:placetype":"venue"
},
  "geometry": {"coordinates":[4.31947,52.037743],"type":"Point"}
}