{
  "type": "Feature",
  "properties": {
    "addr:full":"Burg V Waningln 56 Leek Groningen 9351 LV",
    "addr:housenumber":"56",
    "addr:postcode":"9351",
    "addr:street":"Burg V Waningln",
    "iso:country":"NL",
    "sg:address":"Burg V Waningln 56",
    "sg:city":"Leek",
    "sg:classifiers":[
        {
            "category":"Shopping",
            "subcategory":"News",
            "type":"Retail Goods"
        }
    ],
    "sg:phone":"+31 594 514 637",
    "sg:postcode":"9351 LV",
    "sg:province":"Groningen",
    "sg:tags":[
        "maandbladen",
        "en",
        "week-"
    ],
    "wof:name":"Motorsport News",
    "wof:placetype":"venue"
},
  "geometry": {"coordinates":[6.3926949501,53.1625213623],"type":"Point"}
}