{
  "type": "Feature",
  "properties": {
    "addr:full":"Vrymark 87 Almere NL. 1355 GH",
    "addr:housenumber":"87",
    "addr:postcode":"1355 gh",
    "addr:street":"Vrymark;Nl.",
    "iso:country":"NL",
    "sg:address":"Vrymark 87",
    "sg:city":"Almere",
    "sg:orig_category":"Fotojournalisten Freelance",
    "sg:phone":"+31 36 531 6851",
    "sg:postcode":"1355 GH",
    "sg:province":"NL.",
    "wof:name":"Duijser, Ron",
    "wof:placetype":"venue"
},
  "geometry": {"coordinates":[5.225556,52.343212],"type":"Point"}
}