{
  "type": "Feature",
  "properties": {
    "addr:full":"Oceanenwg 1 Amsterdam Noord-Holland 1047 BA",
    "addr:housenumber":"1",
    "addr:postcode":"1047 ba",
    "addr:street":"Oceanenwg",
    "iso:country":"NL",
    "sg:address":"Oceanenwg 1",
    "sg:city":"Amsterdam",
    "sg:orig_category":"Zoetwaren - Fabrieken En Groothandel",
    "sg:phone":"+31 20 407 0540",
    "sg:postcode":"1047 BA",
    "sg:province":"Noord-Holland",
    "sg:website":"http://www.continentalchocolate.nl",
    "wof:name":"Continental Chocolate Bv",
    "wof:placetype":"venue"
},
  "geometry": {"coordinates":[4.763517,52.410103],"type":"Point"}
}