{
  "type": "Feature",
  "properties": {
    "addr:full":"Rijnstraat 2 Tilburg Noord-Brabant 5046 AN",
    "addr:housenumber":"2",
    "addr:postcode":"5046 an",
    "addr:street":"Rijnstraat",
    "iso:country":"NL",
    "sg:address":"Rijnstraat 2",
    "sg:city":"Tilburg",
    "sg:orig_category":"Gespecialiseerde Bouw",
    "sg:phone":"+31 13 543 3730",
    "sg:postcode":"5046 AN",
    "sg:province":"Noord-Brabant",
    "wof:name":"Constructiebedrijf Van De Camp Bv",
    "wof:placetype":"venue"
},
  "geometry": {"coordinates":[5.0823,51.578022],"type":"Point"}
}