{
  "type": "Feature",
  "properties": {
    "iso:country":"NL",
    "sg:address":"De Pinckart 5-7",
    "sg:city":"Nuenen",
    "sg:orig_category":"Keukens",
    "sg:phone":"+31 40 283 5735",
    "sg:postcode":"5674 CB",
    "sg:province":"Noord-Brabant",
    "sg:website":"http://www.erbeekeukens.nl",
    "wof:name":"Erbee Keukens",
    "wof:placetype":"venue"
},
  "geometry": {"coordinates":[5.534952,51.46714],"type":"Point"}
}