{
  "type": "Feature",
  "properties": {
    "addr:full":"Narcisstraat 45 Kerkrade Limburg 6466 RT",
    "addr:housenumber":"45",
    "addr:postcode":"6466 rt",
    "addr:street":"Narcisstraat",
    "iso:country":"NL",
    "sg:address":"Narcisstraat 45",
    "sg:city":"Kerkrade",
    "sg:orig_category":"Artsen And Specialisten",
    "sg:phone":"+31 45 541 2717",
    "sg:postcode":"6466 RT",
    "sg:province":"Limburg",
    "wof:name":"J.B.M. Stolte Huisarts",
    "wof:placetype":"venue"
},
  "geometry": {"coordinates":[6.025017,50.859695],"type":"Point"}
}