{
  "type": "Feature",
  "properties": {
    "addr:full":"Moorsterwg 18 Woudenberg Utrecht 3931 NC",
    "addr:housenumber":"18",
    "addr:postcode":"3931 nc",
    "addr:street":"Moorsterwg",
    "iso:country":"NL",
    "sg:address":"Moorsterwg 18",
    "sg:city":"Woudenberg",
    "sg:orig_category":"Pluimveebedrijven En -Handelaren",
    "sg:phone":"+31 342 451 264",
    "sg:postcode":"3931 NC",
    "sg:province":"Utrecht",
    "wof:name":"Hee, G Van De",
    "wof:placetype":"venue"
},
  "geometry": {"coordinates":[5.478127,52.115772],"type":"Point"}
}