{
  "type": "Feature",
  "properties": {
    "addr:full":"Terraswg 13 Santpoort Noord Noord-Holland 2071 BA",
    "addr:housenumber":"13",
    "addr:postcode":"2071 ba",
    "addr:street":"Terraswg",
    "iso:country":"NL",
    "sg:address":"Terraswg 13",
    "sg:city":"Santpoort Noord",
    "sg:orig_category":"Betonijzervlechten",
    "sg:phone":"+31 23 538 6426",
    "sg:postcode":"2071 BA",
    "sg:province":"Noord-Holland",
    "wof:name":"Haak Vof",
    "wof:placetype":"venue"
},
  "geometry": {"coordinates":[-121.95871,39.780125],"type":"Point"}
}