{
  "type": "Feature",
  "properties": {
    "iso:country":"NL",
    "sg:address":"Markt 2",
    "sg:city":"Hengelo Ov",
    "sg:orig_category":"Boeken En Tijdschriften",
    "sg:phone":"+31 74 259 4334",
    "sg:postcode":"7551 CG",
    "sg:province":"NL.08",
    "wof:name":"Bruna",
    "wof:placetype":"venue"
},
  "geometry": {"coordinates":[6.793265,52.264515],"type":"Point"}
}