{
  "type": "Feature",
  "properties": {
    "iso:country":"NL",
    "sg:address":"Sandelandstr 2",
    "sg:city":"Wassenaar",
    "sg:orig_category":"Begrafenisverzorging",
    "sg:phone":"+31 70 511 1917",
    "sg:postcode":"2241 TP",
    "sg:province":"South Holland",
    "wof:name":"Kuster-Kortekaas, C A J",
    "wof:placetype":"venue"
},
  "geometry": {"coordinates":[4.410833,52.147968],"type":"Point"}
}