{
  "type": "Feature",
  "properties": {
    "addr:full":"Sandelandstr 2 Wassenaar South Holland 2241 TP",
    "addr:housenumber":"2",
    "addr:postcode":"2241 tp",
    "addr:street":"Sandelandstr",
    "iso:country":"NL",
    "sg:address":"Sandelandstr 2",
    "sg:city":"Wassenaar",
    "sg:orig_category":"Begrafenisverzorging",
    "sg:phone":"+31 70 511 1917",
    "sg:postcode":"2241 TP",
    "sg:province":"South Holland",
    "wof:name":"Kuster-Kortekaas, C A J",
    "wof:placetype":"venue"
},
  "geometry": {"coordinates":[4.410833,52.147968],"type":"Point"}
}