{
  "type": "Feature",
  "properties": {
    "addr:full":"Passage 1 Beverwijk Noord-Holland 1941 ER",
    "addr:housenumber":"1",
    "addr:postcode":"1941 er",
    "addr:street":"Passage",
    "iso:country":"NL",
    "sg:address":"Passage 1",
    "sg:city":"Beverwijk",
    "sg:orig_category":"Bioscopen",
    "sg:phone":"+31 251 223 435",
    "sg:postcode":"1941 ER",
    "sg:province":"Noord-Holland",
    "wof:name":"Luxor 1 En 2",
    "wof:placetype":"venue"
},
  "geometry": {"coordinates":[4.65458,52.479149],"type":"Point"}
}