{
  "type": "Feature",
  "properties": {
    "iso:country":"NL",
    "sg:address":"Passage 1",
    "sg:city":"Beverwijk",
    "sg:orig_category":"Bioscopen",
    "sg:phone":"+31 251 223 435",
    "sg:postcode":"1941 ER",
    "sg:province":"Noord-Holland",
    "wof:name":"Luxor 1 En 2",
    "wof:placetype":"venue"
},
  "geometry": {"coordinates":[4.65458,52.479149],"type":"Point"}
}