{
  "type": "Feature",
  "properties": {
    "addr:full":"V Hasseltkd 20 Maastricht Limburg 6211 CD",
    "addr:housenumber":"20",
    "addr:postcode":"6211 cd",
    "iso:country":"NL",
    "sg:address":"V Hasseltkd 20",
    "sg:city":"Maastricht",
    "sg:orig_category":"Banken",
    "sg:phone":"+31 43 328 1888",
    "sg:postcode":"6211 CD",
    "sg:province":"Limburg",
    "sg:website":"http://www.rabobank.nl",
    "wof:name":"Rabobank",
    "wof:placetype":"venue"
},
  "geometry": {"coordinates":[5.68829,50.849831],"type":"Point"}
}