{
  "type": "Feature",
  "properties": {
    "iso:country":"NL",
    "sg:address":"Maastrichterlaan 132",
    "sg:city":"Vaals",
    "sg:classifiers":[
        {
            "category":"Fast Food",
            "type":"Food & Drink"
        }
    ],
    "sg:phone":"+31 43 306 6444",
    "sg:postcode":"6291 EV",
    "sg:province":"Limburg",
    "sg:tags":[
        "afhaal",
        "restaurant"
    ],
    "wof:name":"Grill-Room Jeruzalem",
    "wof:placetype":"venue"
},
  "geometry": {"coordinates":[6.016667,50.773014],"type":"Point"}
}