{
  "type": "Feature",
  "properties": {
    "addr:full":"Nyverheidsln 2B Ryen Noord-Brabant 5121 MN",
    "addr:housenumber":"2b",
    "addr:postcode":"5121 mn",
    "addr:street":"Nyverheidsln",
    "iso:country":"NL",
    "sg:address":"Nyverheidsln 2B",
    "sg:city":"Ryen",
    "sg:orig_category":"Kunststof Ramen",
    "sg:phone":"+31 161 225 771",
    "sg:postcode":"5121 MN",
    "sg:province":"Noord-Brabant",
    "wof:name":"Seku Plastics",
    "wof:placetype":"venue"
},
  "geometry": {"coordinates":[4.9197,51.588017],"type":"Point"}
}