{
  "type": "Feature",
  "properties": {
    "addr:full":"Stirlingwg 5 Veghel Noord-Brabant 5466 AV",
    "addr:housenumber":"5",
    "addr:postcode":"5466 av",
    "addr:street":"Stirlingwg",
    "iso:country":"NL",
    "sg:address":"Stirlingwg 5",
    "sg:city":"Veghel",
    "sg:orig_category":"Meubelen - Fabrieken En Groothandel",
    "sg:phone":"+31 413 366 791",
    "sg:postcode":"5466 AV",
    "sg:province":"Noord-Brabant",
    "wof:name":"Prima Bv",
    "wof:placetype":"venue"
},
  "geometry": {"coordinates":[5.507096,51.618282],"type":"Point"}
}