{
  "type": "Feature",
  "properties": {
    "iso:country":"NL",
    "sg:address":"Beukenbosweg 39",
    "sg:city":"Kerkrade",
    "sg:orig_category":"Goederenvervoer Over De Weg",
    "sg:phone":"+31 45 567 1133",
    "sg:postcode":"6464 AA",
    "sg:province":"Limburg",
    "wof:name":"J.A.M. Handels",
    "wof:placetype":"venue"
},
  "geometry": {"coordinates":[6.067892,50.879852],"type":"Point"}
}