{
  "type": "Feature",
  "properties": {
    "addr:full":"Noordeinde 98 S Gravenhage South Holland 2514 GM",
    "addr:housenumber":"98",
    "addr:postcode":"2514 gm",
    "addr:street":"Noordeinde;S Gravenhage",
    "iso:country":"NL",
    "sg:address":"Noordeinde 98",
    "sg:city":"S Gravenhage",
    "sg:orig_category":"Boeken En Tijdschriften",
    "sg:phone":"+31 70 365 2845",
    "sg:postcode":"2514 GM",
    "sg:province":"South Holland",
    "sg:website":"http://www.hoogstraten.nl",
    "wof:name":"Hoogstraten Bv, W J Van",
    "wof:placetype":"venue"
},
  "geometry": {"coordinates":[4.30935,52.084148],"type":"Point"}
}