{
  "type": "Feature",
  "properties": {
    "addr:full":"Ginnekenstr 115 Breda North Brabant 4811 JE",
    "addr:housenumber":"115",
    "addr:postcode":"4811 je",
    "iso:country":"NL",
    "sg:address":"Ginnekenstr 115",
    "sg:city":"Breda",
    "sg:orig_category":"Herenkleding",
    "sg:phone":"+31 76 531 0287",
    "sg:postcode":"4811 JE",
    "sg:province":"North Brabant",
    "sg:website":"http://www.wefashion.com",
    "wof:name":"We",
    "wof:placetype":"venue"
},
  "geometry": {"coordinates":[4.777166,51.584389],"type":"Point"}
}