{
  "type": "Feature",
  "properties": {
    "iso:country":"NL",
    "sg:address":"Meerstg 32",
    "sg:city":"Tricht",
    "sg:orig_category":"Banden - Fabrieken En Groothandel",
    "sg:phone":"+31 345 581 146",
    "sg:postcode":"4196 JR",
    "sg:province":"Gelderland",
    "wof:name":"Hcw",
    "wof:placetype":"venue"
},
  "geometry": {"coordinates":[5.273969,51.895412],"type":"Point"}
}