{
  "type": "Feature",
  "properties": {
    "addr:full":"Sleeuwijksedijk 7 Werkendam Noord-Brabant 4251 XA",
    "addr:housenumber":"7",
    "addr:postcode":"4251 xa",
    "addr:street":"Sleeuwijksedijk",
    "iso:country":"NL",
    "sg:address":"Sleeuwijksedijk 7",
    "sg:city":"Werkendam",
    "sg:orig_category":"Goederenvervoer Over De Weg",
    "sg:phone":"+31 183 502 132",
    "sg:postcode":"4251 XA",
    "sg:province":"Noord-Brabant",
    "wof:name":"A.H. Smits",
    "wof:placetype":"venue"
},
  "geometry": {"coordinates":[4.908113,51.820366],"type":"Point"}
}