{
  "type": "Feature",
  "properties": {
    "iso:country":"NL",
    "sg:address":"Opwettensewg 195",
    "sg:city":"Nuenen",
    "sg:orig_category":"Voegwerken",
    "sg:phone":"+31 6 51475182",
    "sg:postcode":"5674 AC",
    "sg:province":"North Brabant",
    "wof:name":"Griensven Voegersbedrijf, Van",
    "wof:placetype":"venue"
},
  "geometry": {"coordinates":[5.531657,51.461006],"type":"Point"}
}