{
  "type": "Feature",
  "properties": {
    "addr:full":"Chopinln 9 Baarn Utrecht 3741 HE",
    "addr:housenumber":"9",
    "addr:postcode":"3741 he",
    "addr:street":"Chopinln",
    "iso:country":"NL",
    "sg:address":"Chopinln 9",
    "sg:city":"Baarn",
    "sg:orig_category":"Accountants - Administratie- Consulenten En -Kantoren",
    "sg:phone":"+31 35 541 5940",
    "sg:postcode":"3741 HE",
    "sg:province":"Utrecht",
    "wof:name":"Vogelzang",
    "wof:placetype":"venue"
},
  "geometry": {"coordinates":[5.263308,52.218987],"type":"Point"}
}