{
  "type": "Feature",
  "properties": {
    "addr:full":"Arendstr 35 Oosterhout Nb Noord-Brabant 4901 JJ",
    "addr:housenumber":"35",
    "addr:postcode":"4901 jj",
    "addr:street":"Arendstr",
    "iso:country":"NL",
    "sg:address":"Arendstr 35",
    "sg:city":"Oosterhout Nb",
    "sg:orig_category":"Verenigingen En Stichtingen",
    "sg:phone":"+31 162 452 222",
    "sg:postcode":"4901 JJ",
    "sg:province":"Noord-Brabant",
    "wof:name":"Stilte Centr In De Oude Toren, Sticht",
    "wof:placetype":"venue"
},
  "geometry": {"coordinates":[4.857208,51.643295],"type":"Point"}
}