{
  "type": "Feature",
  "properties": {
    "addr:full":"W Van De Brinkstraat 33 Purmerend North Holland 1444 HB",
    "addr:housenumber":"33",
    "addr:postcode":"1444 hb",
    "addr:street":"W Van De Brinkstraat",
    "iso:country":"NL",
    "sg:address":"W Van De Brinkstraat 33",
    "sg:city":"Purmerend",
    "sg:orig_category":"Kappers",
    "sg:phone":"+31 299 426 785",
    "sg:postcode":"1444 HB",
    "sg:province":"North Holland",
    "wof:name":"J. Eikeboom",
    "wof:placetype":"venue"
},
  "geometry": {"coordinates":[4.9683990479,52.5207252502],"type":"Point"}
}