{
  "type": "Feature",
  "properties": {
    "addr:full":"Gronausestr 1301 Enschede NL.08 7534 AK",
    "addr:housenumber":"1301",
    "addr:postcode":"7534 ak",
    "iso:country":"NL",
    "sg:address":"Gronausestr 1301",
    "sg:city":"Enschede",
    "sg:orig_category":"Modelbouw",
    "sg:phone":"+31 53 461 1217",
    "sg:postcode":"7534 AK",
    "sg:province":"NL.08",
    "sg:website":"http://www.qualityscales.nl",
    "wof:name":"Quality Scales",
    "wof:placetype":"venue"
},
  "geometry": {"coordinates":[6.95548,52.21645],"type":"Point"}
}