{
  "type": "Feature",
  "properties": {
    "addr:full":"Boterbloem 32 Beilen Provincie Drenthe 9411 CD",
    "addr:housenumber":"32",
    "addr:postcode":"9411 cd",
    "addr:street":"Boterbloem;Provincie Drenthe",
    "iso:country":"NL",
    "sg:address":"Boterbloem 32",
    "sg:city":"Beilen",
    "sg:orig_category":"Voetbalverenigingen",
    "sg:phone":"+31 593 525 530",
    "sg:postcode":"9411 CD",
    "sg:province":"Provincie Drenthe",
    "wof:name":"Beilen Vv",
    "wof:placetype":"venue"
},
  "geometry": {"coordinates":[6.504225,52.854855],"type":"Point"}
}