{
  "type": "Feature",
  "properties": {
    "addr:full":"Talmastr 23 Waalwyk Noord-Brabant 5142 VC",
    "addr:housenumber":"23",
    "addr:postcode":"5142 vc",
    "addr:street":"Talmastr",
    "iso:country":"NL",
    "sg:address":"Talmastr 23",
    "sg:city":"Waalwyk",
    "sg:orig_category":"Keukens",
    "sg:phone":"+31 416 342 106",
    "sg:postcode":"5142 VC",
    "sg:province":"Noord-Brabant",
    "wof:name":"Pullens",
    "wof:placetype":"venue"
},
  "geometry": {"coordinates":[5.083348,51.692303],"type":"Point"}
}