{
  "type": "Feature",
  "properties": {
    "iso:country":"NL",
    "sg:address":"Bloempotstg 8",
    "sg:city":"Gorinchem",
    "sg:orig_category":"Biljartzalen",
    "sg:phone":"+31 183 633 302",
    "sg:postcode":"4201 JT",
    "sg:province":"Zuid-Holland",
    "wof:name":"Upstairs",
    "wof:placetype":"venue"
},
  "geometry": {"coordinates":[4.974665,51.830791],"type":"Point"}
}