{
  "type": "Feature",
  "properties": {
    "addr:full":"Doezastr 27 Leiden South Holland 2311 HA",
    "addr:housenumber":"27",
    "addr:postcode":"2311 ha",
    "addr:street":"Doezastr",
    "iso:country":"NL",
    "sg:address":"Doezastr 27",
    "sg:city":"Leiden",
    "sg:orig_category":"Orthopedische Artikelen",
    "sg:phone":"+31 71 513 2745",
    "sg:postcode":"2311 HA",
    "sg:province":"South Holland",
    "sg:website":"http://www.mediambulant.nl",
    "wof:name":"Medi Ambulant",
    "wof:placetype":"venue"
},
  "geometry": {"coordinates":[4.4892997742,52.1542930603],"type":"Point"}
}