{
  "type": "Feature",
  "properties": {
    "addr:full":"Vlaardingwg 2628 Rotterdam South Holland 3044 CK",
    "addr:housenumber":"2628",
    "addr:postcode":"3044 ck",
    "iso:country":"NL",
    "sg:address":"Vlaardingwg 2628",
    "sg:city":"Rotterdam",
    "sg:orig_category":"Houtbewerking",
    "sg:phone":"+31 10 415 7250",
    "sg:postcode":"3044 CK",
    "sg:province":"South Holland",
    "wof:name":"Krukkert Atlas Bv",
    "wof:placetype":"venue"
},
  "geometry": {"coordinates":[4.41103,51.929913],"type":"Point"}
}