{
  "type": "Feature",
  "properties": {
    "addr:full":"Westerwg 198D Heiloo North Holland 1852 AP",
    "addr:housenumber":"198d",
    "addr:postcode":"1852 ap",
    "addr:street":"Westerwg",
    "iso:country":"NL",
    "sg:address":"Westerwg 198D",
    "sg:city":"Heiloo",
    "sg:orig_category":"Open Haarden",
    "sg:phone":"+31 72 533 6418",
    "sg:postcode":"1852 AP",
    "sg:province":"North Holland",
    "wof:name":"Milan Bv",
    "wof:placetype":"venue"
},
  "geometry": {"coordinates":[4.702124,52.602737],"type":"Point"}
}