{
  "type": "Feature",
  "properties": {
    "addr:full":"Vriezenveenseweg 97 Almelo NL.08 7602 AC",
    "addr:housenumber":"97;nl.08",
    "addr:postcode":"7602 ac",
    "addr:street":"Vriezenveenseweg",
    "iso:country":"NL",
    "sg:address":"Vriezenveenseweg 97",
    "sg:city":"Almelo",
    "sg:orig_category":"Verhuisdiensten",
    "sg:phone":"+31 546 865 721",
    "sg:postcode":"7602 AC",
    "sg:province":"NL.08",
    "wof:name":"Jan Hofman Erkende Verhuizers",
    "wof:placetype":"venue"
},
  "geometry": {"coordinates":[6.667305,52.369377],"type":"Point"}
}