{
  "type": "Feature",
  "properties": {
    "addr:full":"R De Vosstr 17Hs Amsterdam Noord-Holland 1055 CL",
    "addr:postcode":"1055",
    "iso:country":"NL",
    "sg:address":"R De Vosstr 17Hs",
    "sg:city":"Amsterdam",
    "sg:orig_category":"Vakorganisaties",
    "sg:phone":"+31 20 688 1671",
    "sg:postcode":"1055 CL",
    "sg:province":"Noord-Holland",
    "wof:name":"Nieuwe Unie 91",
    "wof:placetype":"venue"
},
  "geometry": {"coordinates":[4.855576,52.37867],"type":"Point"}
}