{
  "type": "Feature",
  "properties": {
    "addr:full":"Rykswg 2 Eede Zld Zeeland 4529 JC",
    "addr:housenumber":"2",
    "addr:postcode":"4529 jc",
    "addr:street":"Rykswg",
    "iso:country":"NL",
    "sg:address":"Rykswg 2",
    "sg:city":"Eede Zld",
    "sg:orig_category":"Farmaceutische Industrie En Groothandel",
    "sg:phone":"+31 117 492 656",
    "sg:postcode":"4529 JC",
    "sg:province":"Zeeland",
    "wof:name":"Eko Bio Bv",
    "wof:placetype":"venue"
},
  "geometry": {"coordinates":[3.442334,51.24762],"type":"Point"}
}