{
  "type": "Feature",
  "properties": {
    "addr:full":"Torenlaan 12 Blaricum North Holland 1261 GD",
    "addr:housenumber":"12",
    "addr:postcode":"1261 gd",
    "addr:street":"Torenlaan",
    "iso:country":"NL",
    "sg:address":"Torenlaan 12",
    "sg:city":"Blaricum",
    "sg:orig_category":"Kappers",
    "sg:phone":"+31 35 538 3501",
    "sg:postcode":"1261 GD",
    "sg:province":"North Holland",
    "wof:name":"Patrice Coiffure La Boutique",
    "wof:placetype":"venue"
},
  "geometry": {"coordinates":[5.242005,52.272465],"type":"Point"}
}