{
  "type": "Feature",
  "properties": {
    "addr:full":"Rouwkoopln 8 Voorschoten South Holland 2251 AP",
    "addr:housenumber":"8",
    "addr:postcode":"2251 ap",
    "addr:street":"Rouwkoopln",
    "iso:country":"NL",
    "sg:address":"Rouwkoopln 8",
    "sg:city":"Voorschoten",
    "sg:classifiers":[
        {
            "category":"Wholesale",
            "subcategory":"Meat",
            "type":"Manufacturing & Wholesale Goods"
        }
    ],
    "sg:phone":"+31 71 560 1234",
    "sg:postcode":"2251 AP",
    "sg:province":"South Holland",
    "sg:tags":[
        "regeltechniek",
        "en",
        "meet-"
    ],
    "wof:name":"Sensor Ned Bv",
    "wof:placetype":"venue"
},
  "geometry": {"coordinates":[4.439461,52.119278],"type":"Point"}
}