{
  "type": "Feature",
  "properties": {
    "addr:full":"De Genestetstr 4 Schiedam South Holland 3117 TA",
    "addr:housenumber":"4",
    "addr:postcode":"3117 ta",
    "iso:country":"NL",
    "sg:address":"De Genestetstr 4",
    "sg:city":"Schiedam",
    "sg:orig_category":"Cafetaria'S",
    "sg:phone":"+31 10 273 2708",
    "sg:postcode":"3117 TA",
    "sg:province":"South Holland",
    "wof:name":"Willson Cafetaria",
    "wof:placetype":"venue"
},
  "geometry": {"coordinates":[4.384403,51.912746],"type":"Point"}
}