{
  "type": "Feature",
  "properties": {
    "addr:full":"K P Vd Mandeleln 41 Rotterdam South Holland 3062 MB",
    "addr:housenumber":"41",
    "addr:postcode":"3062 mb",
    "addr:street":"K P",
    "iso:country":"NL",
    "sg:address":"K P Vd Mandeleln 41",
    "sg:city":"Rotterdam",
    "sg:classifiers":[
        {
            "category":"Professional",
            "subcategory":"Accounting & Tax Preparation",
            "type":"Services"
        }
    ],
    "sg:phone":"+31 10 453 4111",
    "sg:postcode":"3062 MB",
    "sg:province":"South Holland",
    "sg:tags":[
        "accountant",
        "en",
        "-kantoren",
        "register-"
    ],
    "sg:website":"http://www.kpmg.nl",
    "wof:name":"Kpmg Accountants",
    "wof:placetype":"venue"
},
  "geometry": {"coordinates":[4.51759,51.931339],"type":"Point"}
}