{
  "type": "Feature",
  "properties": {
    "addr:full":"Faunastraat 107 Wormer Noord-Holland 1531 WD",
    "addr:housenumber":"107",
    "addr:postcode":"1531 wd",
    "addr:street":"Faunastraat",
    "iso:country":"NL",
    "sg:address":"Faunastraat 107",
    "sg:city":"Wormer",
    "sg:orig_category":"Opticiens",
    "sg:phone":"+31 75 642 7442",
    "sg:postcode":"1531 WD",
    "sg:province":"Noord-Holland",
    "wof:name":"E.A.P. Van Dijk Optiek Bv",
    "wof:placetype":"venue"
},
  "geometry": {"coordinates":[4.812130928,52.498840332],"type":"Point"}
}