{
  "type": "Feature",
  "properties": {
    "addr:full":"Van Der Zandtstraat 7 Velp Gld Gelderland 6882 AZ",
    "addr:housenumber":"7",
    "addr:postcode":"6882",
    "addr:street":"Van Der Zandtstraat;Gld Gelderland",
    "iso:country":"NL",
    "sg:address":"Van Der Zandtstraat 7",
    "sg:city":"Velp Gld",
    "sg:orig_category":"Boekhouders",
    "sg:phone":"+31 26 363 7445",
    "sg:postcode":"6882 AZ",
    "sg:province":"Gelderland",
    "wof:name":"Administratie- En Advieskantoor Jan Musc",
    "wof:placetype":"venue"
},
  "geometry": {"coordinates":[5.96643,51.992908],"type":"Point"}
}