{
  "type": "Feature",
  "properties": {
    "iso:country":"NL",
    "sg:address":"Industriewg 68",
    "sg:city":"Berkel En Rodenrys",
    "sg:classifiers":[
        {
            "category":"Retail",
            "subcategory":"Auto Repair",
            "type":"Services"
        }
    ],
    "sg:phone":"+31 10 512 0222",
    "sg:postcode":"2651 BD",
    "sg:province":"Zuid-Holland",
    "sg:tags":[
        "garage"
    ],
    "wof:name":"W & R",
    "wof:placetype":"venue"
},
  "geometry": {"coordinates":[4.454922,51.982529],"type":"Point"}
}