{
  "type": "Feature",
  "properties": {
    "addr:full":"Hugo De Grootstraat 41 Arnhem Gelderland 6828 TP",
    "addr:housenumber":"41",
    "addr:postcode":"6828 tp",
    "addr:street":"Hugo De Grootstraat",
    "iso:country":"NL",
    "sg:address":"Hugo De Grootstraat 41",
    "sg:city":"Arnhem",
    "sg:classifiers":[
        {
            "category":"Fast Food",
            "type":"Food & Drink"
        }
    ],
    "sg:phone":"+31 26 445 1811",
    "sg:postcode":"6828 TP",
    "sg:province":"Gelderland",
    "sg:tags":[
        "afhaal",
        "restaurant"
    ],
    "wof:name":"De Schnitzel Vof",
    "wof:placetype":"venue"
},
  "geometry": {"coordinates":[5.931439,51.98016],"type":"Point"}
}