{
  "type": "Feature",
  "properties": {
    "addr:full":"Wilhelminastr 5 Wateringen Zuid-Holland 2291 TX",
    "addr:housenumber":"5",
    "addr:street":"Wilhelminastr",
    "iso:country":"NL",
    "sg:address":"Wilhelminastr 5",
    "sg:city":"Wateringen",
    "sg:orig_category":"Betonwerken",
    "sg:phone":"+31 174 292 104",
    "sg:postcode":"2291 TX",
    "sg:province":"Zuid-Holland",
    "wof:name":"Helderman, C G M",
    "wof:placetype":"venue"
},
  "geometry": {"coordinates":[4.270982,52.026875],"type":"Point"}
}