{
  "type": "Feature",
  "properties": {
    "addr:full":"Eversbergwg 76 Nyverdal Overijssel 7443 PE",
    "addr:housenumber":"76",
    "addr:postcode":"7443 pe",
    "addr:street":"Eversbergwg;Overijssel",
    "iso:country":"NL",
    "sg:address":"Eversbergwg 76",
    "sg:city":"Nyverdal",
    "sg:orig_category":"Adviesbureaus Bedrijfsorganisatie",
    "sg:phone":"+31 548 624 923",
    "sg:postcode":"7443 PE",
    "sg:province":"Overijssel",
    "wof:name":"Intervias Management En Advies",
    "wof:placetype":"venue"
},
  "geometry": {"coordinates":[-38.083542,-8.37738],"type":"Point"}
}