{
  "type": "Feature",
  "properties": {
    "addr:full":"Ketellapperstr 26 Assen Drenthe 9403 VR",
    "addr:housenumber":"26",
    "addr:postcode":"9403 vr",
    "addr:street":"Ketellapperstr",
    "iso:country":"NL",
    "sg:address":"Ketellapperstr 26",
    "sg:city":"Assen",
    "sg:orig_category":"Parketvloeren",
    "sg:phone":"+31 592 346 049",
    "sg:postcode":"9403 VR",
    "sg:province":"Drenthe",
    "wof:name":"Multi Vloer Assen",
    "wof:placetype":"venue"
},
  "geometry": {"coordinates":[6.594166,53.011192],"type":"Point"}
}