{
  "type": "Feature",
  "properties": {
    "addr:full":"Deimoslaan 7 Heerhugowaard North Holland 1702 CK",
    "addr:housenumber":"7",
    "addr:postcode":"1702 ck",
    "addr:street":"Deimoslaan",
    "iso:country":"NL",
    "sg:address":"Deimoslaan 7",
    "sg:city":"Heerhugowaard",
    "sg:orig_category":"Bedrijfs- And Managementsconsultants",
    "sg:phone":"+31 72 572 4124",
    "sg:postcode":"1702 CK",
    "sg:province":"North Holland",
    "wof:name":"Ro Ad Consultants Administraties Mgt",
    "wof:placetype":"venue"
},
  "geometry": {"coordinates":[4.83399,52.673237],"type":"Point"}
}