{
  "type": "Feature",
  "properties": {
    "addr:full":"Bergsedk 6 Raamsdonksveer Noord-Brabant 4941 GA",
    "addr:housenumber":"6",
    "addr:postcode":"4941 ga",
    "addr:street":"Bergsedk",
    "iso:country":"NL",
    "sg:address":"Bergsedk 6",
    "sg:city":"Raamsdonksveer",
    "sg:classifiers":[
        {
            "category":"Retail",
            "subcategory":"Storage",
            "type":"Services"
        }
    ],
    "sg:phone":"+31 162 511 537",
    "sg:postcode":"4941 GA",
    "sg:province":"Noord-Brabant",
    "sg:tags":[
        "op-",
        "en",
        "overslagbedrijven"
    ],
    "wof:name":"Peters Bv",
    "wof:placetype":"venue"
},
  "geometry": {"coordinates":[4.868532,51.699894],"type":"Point"}
}