{
  "type": "Feature",
  "properties": {
    "addr:full":"Beekln 39-45 S Gravenhage Zuid-Holland 2562 AA",
    "addr:housenumber":"39-45;gravenhage",
    "addr:postcode":"2562 aa",
    "addr:street":"S",
    "iso:country":"NL",
    "sg:address":"Beekln 39-45",
    "sg:city":"S Gravenhage",
    "sg:orig_category":"Verf En Lak",
    "sg:phone":"+31 70 346 9626",
    "sg:postcode":"2562 AA",
    "sg:province":"Zuid-Holland",
    "wof:name":"Bodegom Bv, Van",
    "wof:placetype":"venue"
},
  "geometry": {"coordinates":[4.28326,52.075001],"type":"Point"}
}