{
  "type": "Feature",
  "properties": {
    "addr:full":"Tinelstraat 3 Eindhoven North Brabant 5654 LS",
    "addr:housenumber":"3",
    "addr:postcode":"5654 ls",
    "addr:street":"Tinelstraat",
    "iso:country":"NL",
    "sg:address":"Tinelstraat 3",
    "sg:city":"Eindhoven",
    "sg:orig_category":"Overheidsdiensten",
    "sg:phone":"+31 40 251 1999",
    "sg:postcode":"5654 LS",
    "sg:province":"North Brabant",
    "wof:name":"De Nieuwe Ketting",
    "wof:placetype":"venue"
},
  "geometry": {"coordinates":[5.4568657875,51.4198608398],"type":"Point"}
}