{
  "type": "Feature",
  "properties": {
    "iso:country":"NL",
    "sg:address":"Hoofdwg 9",
    "sg:city":"Capelle Ad Yssel",
    "sg:orig_category":"Bloemen En Planten",
    "sg:phone":"+31 10 284 7350",
    "sg:postcode":"2908 LB",
    "sg:province":"Zuid-Holland",
    "wof:name":"Trends & Plants",
    "wof:placetype":"venue"
},
  "geometry": {"coordinates":[4.57136,51.954269],"type":"Point"}
}