{
  "type": "Feature",
  "properties": {
    "iso:country":"NL",
    "sg:address":"Voorstraat 37",
    "sg:city":"Brielle",
    "sg:orig_category":"Juweliers",
    "sg:phone":"+31 181 413 461",
    "sg:postcode":"3231 BE",
    "sg:province":"South Holland",
    "wof:name":"Firma W. Hoogvliet",
    "wof:placetype":"venue"
},
  "geometry": {"coordinates":[4.167875,51.90406],"type":"Point"}
}