{
  "type": "Feature",
  "properties": {
    "addr:full":"Postbus 100 Oosterbeek Gelderland 6860 AC",
    "addr:housenumber":"100",
    "addr:postcode":"6860 ac",
    "addr:street":"Postbus;Gelderland",
    "iso:country":"NL",
    "sg:address":"Postbus 100",
    "sg:city":"Oosterbeek",
    "sg:orig_category":"Exploitatie- Maatschappijen",
    "sg:phone":"+31 26 339 0088",
    "sg:postcode":"6860 AC",
    "sg:province":"Gelderland",
    "wof:name":"Capitol Rem",
    "wof:placetype":"venue"
},
  "geometry": {"coordinates":[5.84188,51.987652],"type":"Point"}
}