{
  "type": "Feature",
  "properties": {
    "addr:full":"Ouddiemerlaan 202 Diemen Amsterdam Noord-Holland 1111 HN",
    "addr:housenumber":"202",
    "addr:postcode":"1111 hn",
    "addr:street":"Ouddiemerlaan",
    "iso:country":"NL",
    "sg:address":"Ouddiemerlaan 202",
    "sg:city":"Diemen Amsterdam",
    "sg:orig_category":"Loodgieterswerk, Verwarming And Sanitaire Installaties",
    "sg:phone":"+31 900 7002175",
    "sg:postcode":"1111 HN",
    "sg:province":"Noord-Holland",
    "wof:name":"Revet Instalatieservice",
    "wof:placetype":"venue"
},
  "geometry": {"coordinates":[4.970432,52.35461],"type":"Point"}
}