{
  "type": "Feature",
  "properties": {
    "addr:full":"Waleweinstr 25 Eindhoven Noord-Brabant 5625 EH",
    "addr:housenumber":"25",
    "addr:postcode":"5625 eh",
    "addr:street":"Waleweinstr",
    "iso:country":"NL",
    "sg:address":"Waleweinstr 25",
    "sg:city":"Eindhoven",
    "sg:orig_category":"Oppascentrales",
    "sg:phone":"+31 40 844 0302",
    "sg:postcode":"5625 EH",
    "sg:province":"Noord-Brabant",
    "sg:website":"http://www.oppasservice.com",
    "wof:name":"Oppasservice Zuid Oost Brabant",
    "wof:placetype":"venue"
},
  "geometry": {"coordinates":[5.4693078995,51.4720115662],"type":"Point"}
}