{
  "type": "Feature",
  "properties": {
    "addr:full":"Berflowg 65 Hengelo Ov Overijssel 7553 JM",
    "addr:housenumber":"65",
    "addr:postcode":"7553 jm",
    "addr:street":"Berflowg;Ov",
    "iso:country":"NL",
    "sg:address":"Berflowg 65",
    "sg:city":"Hengelo Ov",
    "sg:orig_category":"Bloemen En Planten",
    "sg:phone":"+31 74 250 5401",
    "sg:postcode":"7553 JM",
    "sg:province":"Overijssel",
    "wof:name":"Geja",
    "wof:placetype":"venue"
},
  "geometry": {"coordinates":[6.796937,52.256134],"type":"Point"}
}