{
  "type": "Feature",
  "properties": {
    "iso:country":"NL",
    "sg:address":"Houtse Heuvel 57",
    "sg:city":"Den Hout Nb",
    "sg:orig_category":"Verzekeringen",
    "sg:phone":"+31 162 455 070",
    "sg:postcode":"4911 AV",
    "sg:province":"Noord-Brabant",
    "wof:name":"Halters Assurantien",
    "wof:placetype":"venue"
},
  "geometry": {"coordinates":[4.812553,51.661606],"type":"Point"}
}