{
  "type": "Feature",
  "properties": {
    "iso:country":"NL",
    "sg:address":"Postbus 1754",
    "sg:city":"Groningen",
    "sg:orig_category":"Organisatiebureaus",
    "sg:phone":"+31 50 573 5694",
    "sg:postcode":"9701 BT",
    "sg:province":"Groningen",
    "wof:name":"Prime Nieuwe Muziek, Sticht",
    "wof:placetype":"venue"
},
  "geometry": {"coordinates":[6.5650200844,53.2164497375],"type":"Point"}
}