{
  "type": "Feature",
  "properties": {
    "iso:country":"NL",
    "sg:address":"Oude Binnenwg 45",
    "sg:city":"Rotterdam",
    "sg:orig_category":"Juweliers",
    "sg:phone":"+31 10 411 6615",
    "sg:postcode":"3012 JA",
    "sg:province":"Zuid-Holland",
    "wof:name":"Brunott Bv",
    "wof:placetype":"venue"
},
  "geometry": {"coordinates":[4.47649,51.917957],"type":"Point"}
}