{
  "type": "Feature",
  "properties": {
    "addr:full":"Berkdijksestraat 94 Tilburg Noord-Brabant 5025 VH",
    "addr:housenumber":"94",
    "addr:postcode":"5025 vh",
    "addr:street":"Berkdijksestraat",
    "iso:country":"NL",
    "sg:address":"Berkdijksestraat 94",
    "sg:city":"Tilburg",
    "sg:orig_category":"Kappers",
    "sg:phone":"+31 13 468 2579",
    "sg:postcode":"5025 VH",
    "sg:province":"Noord-Brabant",
    "wof:name":"Kapsalon Marielle",
    "wof:placetype":"venue"
},
  "geometry": {"coordinates":[5.0625767708,51.5489501953],"type":"Point"}
}