{
  "type": "Feature",
  "properties": {
    "addr:full":"Schoterstraat 7 Zevenhoven South Holland 2435 XK",
    "addr:housenumber":"7",
    "addr:postcode":"2435 xk",
    "addr:street":"Schoterstraat",
    "iso:country":"NL",
    "sg:address":"Schoterstraat 7",
    "sg:city":"Zevenhoven",
    "sg:orig_category":"Kappers",
    "sg:phone":"+31 172 538 878",
    "sg:postcode":"2435 XK",
    "sg:province":"South Holland",
    "wof:name":"Haarmode Is Thuismode",
    "wof:placetype":"venue"
},
  "geometry": {"coordinates":[4.7789969444,52.1823654175],"type":"Point"}
}