{
  "type": "Feature",
  "properties": {
    "addr:full":"Aagje Dekenlaan 19 Delft Zuid-Holland 2624 CB",
    "addr:housenumber":"19",
    "addr:postcode":"2624 cb",
    "addr:street":"Aagje Dekenlaan",
    "iso:country":"NL",
    "sg:address":"Aagje Dekenlaan 19",
    "sg:city":"Delft",
    "sg:orig_category":"Loodgieterswerk, Verwarming And Sanitaire Installaties",
    "sg:phone":"+31 15 257 4070",
    "sg:postcode":"2624 CB",
    "sg:province":"Zuid-Holland",
    "wof:name":"G En F Bv",
    "wof:placetype":"venue"
},
  "geometry": {"coordinates":[4.358711,51.995686],"type":"Point"}
}