{
  "type": "Feature",
  "properties": {
    "addr:full":"Brenner 87 Amsterdam Noord-Holland 1060 NT",
    "addr:housenumber":"87",
    "addr:postcode":"1060 nt",
    "addr:street":"Brenner",
    "iso:country":"NL",
    "sg:address":"Brenner 87",
    "sg:city":"Amsterdam",
    "sg:orig_category":"Boekhouders",
    "sg:phone":"+31 20 619 6358",
    "sg:postcode":"1060 NT",
    "sg:province":"Noord-Holland",
    "wof:name":"J.E.H. Smit",
    "wof:placetype":"venue"
},
  "geometry": {"coordinates":[4.773817,52.351978],"type":"Point"}
}