{
  "type": "Feature",
  "properties": {
    "addr:full":"Laan Vd Mensenrechten 312 Apeldoorn Gelderland 7331 VX",
    "addr:housenumber":"312",
    "addr:postcode":"7331 vx",
    "addr:street":"Laan Vd Mensenrechten;Gelderland",
    "iso:country":"NL",
    "sg:address":"Laan Vd Mensenrechten 312",
    "sg:city":"Apeldoorn",
    "sg:orig_category":"Boekhouders",
    "sg:phone":"+31 55 533 4654",
    "sg:postcode":"7331 VX",
    "sg:province":"Gelderland",
    "wof:name":"M E Van Essen",
    "wof:placetype":"venue"
},
  "geometry": {"coordinates":[5.9686,52.208805],"type":"Point"}
}