{
  "type": "Feature",
  "properties": {
    "addr:full":"Kuiperstr 68 Vlaardingen South Holland 3131 CH",
    "addr:housenumber":"68",
    "addr:postcode":"3131",
    "addr:street":"Kuiperstr",
    "iso:country":"NL",
    "sg:address":"Kuiperstr 68",
    "sg:city":"Vlaardingen",
    "sg:orig_category":"Cafetaria'S",
    "sg:phone":"+31 10 434 6000",
    "sg:postcode":"3131 CH",
    "sg:province":"South Holland",
    "wof:name":"Mega Snack",
    "wof:placetype":"venue"
},
  "geometry": {"coordinates":[4.341833,51.908943],"type":"Point"}
}