{
  "type": "Feature",
  "properties": {
    "addr:full":"Korvelseweg 24 Tilburg Noord-Brabant 5025 JH",
    "addr:housenumber":"24",
    "addr:postcode":"5025 jh",
    "addr:street":"Korvelseweg",
    "iso:country":"NL",
    "sg:address":"Korvelseweg 24",
    "sg:city":"Tilburg",
    "sg:orig_category":"Meubelzaken, Woning- And Keukeninrichting",
    "sg:phone":"+31 13 536 0134",
    "sg:postcode":"5025 JH",
    "sg:province":"Noord-Brabant",
    "wof:name":"De Rietenwereld H. Dikmans",
    "wof:placetype":"venue"
},
  "geometry": {"coordinates":[5.078299,51.552658],"type":"Point"}
}