{
  "type": "Feature",
  "properties": {
    "addr:full":"Middelweg 96 Uitgeest North Holland 1911 EJ",
    "addr:housenumber":"96",
    "addr:postcode":"1911 ej",
    "addr:street":"Middelweg",
    "iso:country":"NL",
    "sg:address":"Middelweg 96",
    "sg:city":"Uitgeest",
    "sg:orig_category":"Verzekeringen",
    "sg:phone":"+31 251 314 892",
    "sg:postcode":"1911 EJ",
    "sg:province":"North Holland",
    "wof:name":"N.H.M. Beentjes Bv",
    "wof:placetype":"venue"
},
  "geometry": {"coordinates":[4.709739,52.524342],"type":"Point"}
}