{
  "type": "Feature",
  "properties": {
    "addr:full":"Dorpsstr 97 Helmond North Brabant 5708 GE",
    "addr:housenumber":"97",
    "addr:postcode":"5708",
    "addr:street":"Dorpsstr",
    "iso:country":"NL",
    "sg:address":"Dorpsstr 97",
    "sg:city":"Helmond",
    "sg:orig_category":"Binnenhuisarchitectuur",
    "sg:phone":"+31 492 475 242",
    "sg:postcode":"5708 GE",
    "sg:province":"North Brabant",
    "wof:name":"Blauwe Kamer, De",
    "wof:placetype":"venue"
},
  "geometry": {"coordinates":[5.622804,51.484447],"type":"Point"}
}