{
  "type": "Feature",
  "properties": {
    "addr:full":"Braakmanstg 10 Bathmen NL.08 7437 PV",
    "addr:housenumber":"10;nl.08",
    "addr:postcode":"7437 pv",
    "addr:street":"Braakmanstg",
    "iso:country":"NL",
    "sg:address":"Braakmanstg 10",
    "sg:city":"Bathmen",
    "sg:orig_category":"Vioolbouw",
    "sg:phone":"+31 570 541 123",
    "sg:postcode":"7437 PV",
    "sg:province":"NL.08",
    "wof:name":"Jaap Timmer",
    "wof:placetype":"venue"
},
  "geometry": {"coordinates":[6.324135,52.228912],"type":"Point"}
}