{
  "type": "Feature",
  "properties": {
    "iso:country":"NL",
    "sg:address":"Molendijk 36",
    "sg:city":"Sliedrecht",
    "sg:orig_category":"Kantoorartikelen",
    "sg:phone":"+31 184 416 675",
    "sg:postcode":"3361 EN",
    "sg:province":"Zuid-Holland",
    "wof:name":"Handelsonderneming De Veldkraai",
    "wof:placetype":"venue"
},
  "geometry": {"coordinates":[4.7636461258,51.8248558044],"type":"Point"}
}