{
  "type": "Feature",
  "properties": {
    "addr:full":"Birdaarderstrwg 70 Dokkum Friesland 9101 DC",
    "addr:housenumber":"70",
    "addr:postcode":"9101",
    "addr:street":"Birdaarderstrwg",
    "iso:country":"NL",
    "sg:address":"Birdaarderstrwg 70",
    "sg:city":"Dokkum",
    "sg:orig_category":"Artsen - Huisartsen",
    "sg:phone":"+31 519 294 310",
    "sg:postcode":"9101 DC",
    "sg:province":"Friesland",
    "wof:name":"Huisartsen Laboratorium",
    "wof:placetype":"venue"
},
  "geometry": {"coordinates":[6.001321,53.323975],"type":"Point"}
}