{
  "type": "Feature",
  "properties": {
    "iso:country":"NL",
    "sg:address":"Birdaarderstrwg 70",
    "sg:city":"Dokkum",
    "sg:orig_category":"Artsen - Huisartsen",
    "sg:phone":"+31 519 294 310",
    "sg:postcode":"9101 DC",
    "sg:province":"Friesland",
    "wof:name":"Huisartsen Laboratorium",
    "wof:placetype":"venue"
},
  "geometry": {"coordinates":[6.001321,53.323975],"type":"Point"}
}