{
  "type": "Feature",
  "properties": {
    "addr:full":"Rondwg 26 Bladel Noord-Brabant 5531 AJ",
    "addr:housenumber":"26",
    "addr:postcode":"5531 aj",
    "addr:street":"Rondwg",
    "iso:country":"NL",
    "sg:address":"Rondwg 26",
    "sg:city":"Bladel",
    "sg:orig_category":"Ziekenhuizen, Sanatoria, Verpleeghuizen",
    "sg:phone":"+31 497 382 626",
    "sg:postcode":"5531 AJ",
    "sg:province":"Noord-Brabant",
    "wof:name":"Rk Kempisch Verpleegtehuis",
    "wof:placetype":"venue"
},
  "geometry": {"coordinates":[5.214658,51.361473],"type":"Point"}
}