{
  "type": "Feature",
  "properties": {
    "addr:full":"Ryperwg 58 Middenbeemster Noord-Holland 1462 ME",
    "addr:housenumber":"58",
    "addr:postcode":"1462 me",
    "addr:street":"Ryperwg",
    "iso:country":"NL",
    "sg:address":"Ryperwg 58",
    "sg:city":"Middenbeemster",
    "sg:orig_category":"Babyartikelen",
    "sg:phone":"+31 299 681 725",
    "sg:postcode":"1462 ME",
    "sg:province":"Noord-Holland",
    "wof:name":"Jonker, Drogisterij",
    "wof:placetype":"venue"
},
  "geometry": {"coordinates":[4.910562,52.548855],"type":"Point"}
}