{
  "type": "Feature",
  "properties": {
    "addr:full":"Veldhovenring 105 Tilburg Noord-Brabant 5041 BB",
    "addr:housenumber":"105",
    "addr:postcode":"5041 bb",
    "addr:street":"Veldhovenring",
    "iso:country":"NL",
    "sg:address":"Veldhovenring 105",
    "sg:city":"Tilburg",
    "sg:orig_category":"Boekenuitgeverijen",
    "sg:phone":"+31 13 577 1698",
    "sg:postcode":"5041 BB",
    "sg:province":"Noord-Brabant",
    "wof:name":"Dutch University Press Bv",
    "wof:placetype":"venue"
},
  "geometry": {"coordinates":[5.082173,51.567451],"type":"Point"}
}