{
  "type": "Feature",
  "properties": {
    "iso:country":"NL",
    "sg:address":"Past Claassenstr 15",
    "sg:city":"S Hertogenbosch",
    "sg:orig_category":"Adviesbureaus Bedrijfsorganisatie",
    "sg:phone":"+31 73 648 0960",
    "sg:postcode":"5236 XE",
    "sg:province":"Noord-Brabant",
    "wof:name":"Goossens, J",
    "wof:placetype":"venue"
},
  "geometry": {"coordinates":[5.321172,51.729317],"type":"Point"}
}