{
  "type": "Feature",
  "properties": {
    "iso:country":"NL",
    "sg:address":"Boven Vredenburg 23",
    "sg:city":"Utrecht",
    "sg:orig_category":"Parkeergarages",
    "sg:phone":"+31 30 239 9000",
    "sg:postcode":"3511 CW",
    "sg:province":"Utrecht",
    "wof:name":"Corio Nederland",
    "wof:placetype":"venue"
},
  "geometry": {"coordinates":[5.113563,52.091877],"type":"Point"}
}