{
  "type": "Feature",
  "properties": {
    "addr:full":"Het Lg Holt 18 Hoogeveen Drenthe 7909 BN",
    "addr:housenumber":"18",
    "addr:postcode":"7909 bn",
    "addr:street":"Lg Holt",
    "iso:country":"NL",
    "sg:address":"Het Lg Holt 18",
    "sg:city":"Hoogeveen",
    "sg:orig_category":"Adviesbureaus Bedrijfsorganisatie",
    "sg:phone":"+31 528 235 216",
    "sg:postcode":"7909 BN",
    "sg:province":"Drenthe",
    "wof:name":"Engelsma",
    "wof:placetype":"venue"
},
  "geometry": {"coordinates":[6.445932,52.724892],"type":"Point"}
}