{
  "type": "Feature",
  "properties": {
    "addr:full":"V Houten Ind Pk 21 Weesp North Holland 1381 MZ",
    "addr:postcode":"1381 mz",
    "addr:street":"V;Pk 21",
    "iso:country":"NL",
    "sg:address":"V Houten Ind Pk 21",
    "sg:city":"Weesp",
    "sg:orig_category":"Optische Instrumenten",
    "sg:phone":"+31 294 496 666",
    "sg:postcode":"1381 MZ",
    "sg:province":"North Holland",
    "wof:name":"Carl Zeiss Bv",
    "wof:placetype":"venue"
},
  "geometry": {"coordinates":[5.0382800102,52.3083152771],"type":"Point"}
}