{
  "type": "Feature",
  "properties": {
    "iso:country":"NL",
    "sg:address":"Veersesingel 15",
    "sg:city":"Middelburg",
    "sg:orig_category":"Diverse Grafische Activiteiten",
    "sg:phone":"+31 118 635 277",
    "sg:postcode":"4332 TA",
    "sg:province":"Zeeland",
    "wof:name":"Boekbinderij Zeeland",
    "wof:placetype":"venue"
},
  "geometry": {"coordinates":[3.624887,51.501762],"type":"Point"}
}