{
  "type": "Feature",
  "properties": {
    "iso:country":"NL",
    "sg:address":"Maaslaan 117",
    "sg:city":"Helmond",
    "sg:orig_category":"Meubels And Huishoudapparatuur Gh",
    "sg:phone":"+31 6 54617782",
    "sg:postcode":"5704 LC",
    "sg:province":"North Brabant",
    "wof:name":"A.J. Buitendijk",
    "wof:placetype":"venue"
},
  "geometry": {"coordinates":[5.706321,51.46426],"type":"Point"}
}