{
  "type": "Feature",
  "properties": {
    "addr:full":"H Westerstr 62-63 Oude Pekela Groningen 9665 AN",
    "addr:housenumber":"62-63",
    "addr:postcode":"pekela;9665 an",
    "addr:street":"Oude",
    "iso:country":"NL",
    "sg:address":"H Westerstr 62-63",
    "sg:city":"Oude Pekela",
    "sg:orig_category":"Farmaceutische Industrie En Groothandel",
    "sg:phone":"+31 597 612 749",
    "sg:postcode":"9665 AN",
    "sg:province":"Groningen",
    "wof:name":"Zuidema & Zoutman Fa",
    "wof:placetype":"venue"
},
  "geometry": {"coordinates":[7.016031,53.104809],"type":"Point"}
}