{
  "type": "Feature",
  "properties": {
    "addr:full":"Postbus 1037 Giessenburg South Holland 3380 AA",
    "addr:housenumber":"1037",
    "addr:postcode":"3380 aa",
    "addr:street":"Postbus",
    "iso:country":"NL",
    "sg:address":"Postbus 1037",
    "sg:city":"Giessenburg",
    "sg:orig_category":"Lasbedrijven",
    "sg:phone":"+31 184 612 329",
    "sg:postcode":"3380 AA",
    "sg:province":"South Holland",
    "wof:name":"Alert",
    "wof:placetype":"venue"
},
  "geometry": {"coordinates":[4.88866,51.851799],"type":"Point"}
}