{
  "type": "Feature",
  "properties": {
    "addr:full":"Maasdamsedk 5 Puttershoek Zuid-Holland 3297 AK",
    "addr:housenumber":"5",
    "addr:postcode":"3297 ak",
    "addr:street":"Maasdamsedk",
    "iso:country":"NL",
    "sg:address":"Maasdamsedk 5",
    "sg:city":"Puttershoek",
    "sg:orig_category":"Zonweringen",
    "sg:phone":"+31 78 676 3802",
    "sg:postcode":"3297 AK",
    "sg:province":"Zuid-Holland",
    "wof:name":"Woord Zonweringen",
    "wof:placetype":"venue"
},
  "geometry": {"coordinates":[4.571554,51.801926],"type":"Point"}
}