{
  "type": "Feature",
  "properties": {
    "addr:full":"Herenwg 47 Utrecht Utrecht 3513 CB",
    "addr:housenumber":"47",
    "addr:postcode":"3513 cb",
    "addr:street":"Herenwg",
    "iso:country":"NL",
    "sg:address":"Herenwg 47",
    "sg:city":"Utrecht",
    "sg:orig_category":"Woningbureaus",
    "sg:phone":"+31 30 231 9721",
    "sg:postcode":"3513 CB",
    "sg:province":"Utrecht",
    "sg:website":"http://www.rentalservices.nl",
    "wof:name":"Rental Services Bv",
    "wof:placetype":"venue"
},
  "geometry": {"coordinates":[5.1099991798,52.0969467163],"type":"Point"}
}