{
  "type": "Feature",
  "properties": {
    "addr:full":"Hoofdstraat 22 Hoensbroek Limburg 6431 LC",
    "addr:housenumber":"22",
    "addr:postcode":"6431 lc",
    "addr:street":"Hoofdstraat",
    "iso:country":"NL",
    "sg:address":"Hoofdstraat 22",
    "sg:city":"Hoensbroek",
    "sg:orig_category":"Beautyfarms And Sauna'S",
    "sg:phone":"+31 45 522 8365",
    "sg:postcode":"6431 LC",
    "sg:province":"Limburg",
    "wof:name":"Sun Love",
    "wof:placetype":"venue"
},
  "geometry": {"coordinates":[5.925667,50.924675],"type":"Point"}
}