{
  "type": "Feature",
  "properties": {
    "addr:full":"Waldeck Pyrmontstraat 15 Weert Limburg 6006 HG",
    "addr:housenumber":"15",
    "addr:postcode":"6006 hg",
    "addr:street":"Waldeck Pyrmontstraat",
    "iso:country":"NL",
    "sg:address":"Waldeck Pyrmontstraat 15",
    "sg:city":"Weert",
    "sg:orig_category":"Drukkerijen And Copyshops",
    "sg:phone":"+31 495 531 524",
    "sg:postcode":"6006 HG",
    "sg:province":"Limburg",
    "wof:name":"Sidonia",
    "wof:placetype":"venue"
},
  "geometry": {"coordinates":[5.714257,51.239906],"type":"Point"}
}