{
  "type": "Feature",
  "properties": {
    "addr:full":"A J Ernststr 595 A Amsterdam Noord-Holland 1082 LD",
    "addr:housenumber":"595 a",
    "addr:postcode":"1082 ld",
    "addr:street":"A",
    "iso:country":"NL",
    "sg:address":"A J Ernststr 595 A",
    "sg:city":"Amsterdam",
    "sg:orig_category":"Makelaars En Adviseurs Onroerende Goederen",
    "sg:phone":"+31 20 301 9595",
    "sg:postcode":"1082 LD",
    "sg:province":"Noord-Holland",
    "sg:website":"http://www.poelwijck-sweers.nl",
    "wof:name":"Poelwijck Sweers",
    "wof:placetype":"venue"
},
  "geometry": {"coordinates":[4.87756,52.330521],"type":"Point"}
}