{
  "type": "Feature",
  "properties": {
    "iso:country":"NL",
    "sg:address":"Hoofdweg 126",
    "sg:city":"Hellum",
    "sg:orig_category":"Fotostudio'S And Fotografen",
    "sg:phone":"+31 598 431 915",
    "sg:postcode":"9627 PG",
    "sg:province":"Groningen",
    "wof:name":"Foto Kobus Rarekiek",
    "wof:placetype":"venue"
},
  "geometry": {"coordinates":[6.843639,53.240669],"type":"Point"}
}