{
  "type": "Feature",
  "properties": {
    "addr:full":"Ludinge 6 Zuidlaren Provincie Drenthe 9471 JD",
    "addr:housenumber":"6",
    "addr:postcode":"9471 jd",
    "addr:street":"Ludinge;Provincie Drenthe",
    "iso:country":"NL",
    "sg:address":"Ludinge 6",
    "sg:city":"Zuidlaren",
    "sg:classifiers":[
        {
            "category":"Education",
            "subcategory":"Preschool",
            "type":"Public Place"
        }
    ],
    "sg:phone":"+31 50 409 2079",
    "sg:postcode":"9471 JD",
    "sg:province":"Provincie Drenthe",
    "sg:tags":[
        "kleuteronderwijs",
        "basis-"
    ],
    "wof:name":"Christelijke Basisschool Jonglaren",
    "wof:placetype":"venue"
},
  "geometry": {"coordinates":[6.663835,53.091816],"type":"Point"}
}