{
  "type": "Feature",
  "properties": {
    "addr:full":"Stratingplnts 95 Velsen Noord Noord-Holland 1951 ES",
    "addr:housenumber":"95",
    "addr:postcode":"1951 es",
    "addr:street":"Stratingplnts;Velsen",
    "iso:country":"NL",
    "sg:address":"Stratingplnts 95",
    "sg:city":"Velsen Noord",
    "sg:orig_category":"Fotoreportages",
    "sg:phone":"+31 251 221 660",
    "sg:postcode":"1951 ES",
    "sg:province":"Noord-Holland",
    "sg:website":"http://www.reuver.nl",
    "wof:name":"Reuver, John De",
    "wof:placetype":"venue"
},
  "geometry": {"coordinates":[4.644924,52.471874],"type":"Point"}
}