{
  "type": "Feature",
  "properties": {
    "addr:full":"Hg Der A 18 Groningen Groningen 9712 AD",
    "addr:housenumber":"18",
    "addr:postcode":"9712 ad",
    "addr:street":"A",
    "iso:country":"NL",
    "sg:address":"Hg Der A 18",
    "sg:city":"Groningen",
    "sg:orig_category":"Adviesbureaus Bedrijfsorganisatie",
    "sg:phone":"+31 50 527 6557",
    "sg:postcode":"9712 AD",
    "sg:province":"Groningen",
    "sg:website":"http://www.wagnergroup.nl",
    "wof:name":"Wagner",
    "wof:placetype":"venue"
},
  "geometry": {"coordinates":[6.55943,53.218048],"type":"Point"}
}