{
  "type": "Feature",
  "properties": {
    "iso:country":"NL",
    "sg:address":"Dr W Beckmansngl 7",
    "sg:city":"Vlaardingen",
    "sg:orig_category":"Bloemen En Planten",
    "sg:phone":"+31 10 434 1901",
    "sg:postcode":"3132 CL",
    "sg:province":"South Holland",
    "wof:name":"Steenbergen, Ton",
    "wof:placetype":"venue"
},
  "geometry": {"coordinates":[4.317528,51.910126],"type":"Point"}
}