{
  "type": "Feature",
  "properties": {
    "addr:full":"A V Renessepln 29 Uitgeest North Holland 1911 KT",
    "addr:housenumber":"29",
    "addr:postcode":"1911 kt",
    "addr:street":"A;Renessepln",
    "iso:country":"NL",
    "sg:address":"A V Renessepln 29",
    "sg:city":"Uitgeest",
    "sg:orig_category":"Voetbalverenigingen",
    "sg:phone":"+31 251 310 877",
    "sg:postcode":"1911 KT",
    "sg:province":"North Holland",
    "wof:name":"Atc",
    "wof:placetype":"venue"
},
  "geometry": {"coordinates":[4.713915,52.528736],"type":"Point"}
}