{
  "type": "Feature",
  "properties": {
    "addr:full":"Hoendiep 185 Groningen Groningen 9745 EC",
    "addr:housenumber":"185",
    "addr:postcode":"9745 ec",
    "addr:street":"Hoendiep",
    "iso:country":"NL",
    "sg:address":"Hoendiep 185",
    "sg:city":"Groningen",
    "sg:orig_category":"Kappers",
    "sg:phone":"+31 50 556 6404",
    "sg:postcode":"9745 EC",
    "sg:province":"Groningen",
    "wof:name":"Kopzorg",
    "wof:placetype":"venue"
},
  "geometry": {"coordinates":[6.504849,53.216625],"type":"Point"}
}