{
  "type": "Feature",
  "properties": {
    "addr:full":"Breitnerln 8 S Gravenhage South Holland 2596 HC",
    "addr:housenumber":"8 s",
    "addr:postcode":"2596 hc",
    "addr:street":"Breitnerln",
    "iso:country":"NL",
    "sg:address":"Breitnerln 8",
    "sg:city":"S Gravenhage",
    "sg:orig_category":"Verf En Lak",
    "sg:phone":"+31 70 324 6341",
    "sg:postcode":"2596 HC",
    "sg:province":"South Holland",
    "sg:website":"http://www.koolewoondecoratie.nl",
    "wof:name":"Koole Woondecoratie",
    "wof:placetype":"venue"
},
  "geometry": {"coordinates":[4.31846,52.093311],"type":"Point"}
}