{
  "type": "Feature",
  "properties": {
    "addr:full":"Dorresteinsewg 33 Amersfoort Utrecht 3817 GA",
    "addr:housenumber":"33",
    "addr:postcode":"3817 ga",
    "addr:street":"Dorresteinsewg",
    "iso:country":"NL",
    "sg:address":"Dorresteinsewg 33",
    "sg:city":"Amersfoort",
    "sg:orig_category":"Wijnkoperijen En -Groothandel",
    "sg:phone":"+31 33 463 3310",
    "sg:postcode":"3817 GA",
    "sg:province":"Utrecht",
    "wof:name":"Jellema, S",
    "wof:placetype":"venue"
},
  "geometry": {"coordinates":[5.3988480568,52.1409988403],"type":"Point"}
}