{
  "type": "Feature",
  "properties": {
    "addr:full":"Dr R J Fruinstr 8 S Gravenhage Zuid-Holland 2552 LD",
    "addr:housenumber":"8 s",
    "addr:postcode":"2552 ld",
    "addr:street":"Dr R;Fruinstr",
    "iso:country":"NL",
    "sg:address":"Dr R J Fruinstr 8",
    "sg:city":"S Gravenhage",
    "sg:orig_category":"Kappers",
    "sg:phone":"+31 70 389 2853",
    "sg:postcode":"2552 LD",
    "sg:province":"Zuid-Holland",
    "wof:name":"Elsina, Coiffure",
    "wof:placetype":"venue"
},
  "geometry": {"coordinates":[4.2495799065,52.0536308289],"type":"Point"}
}