{
  "type": "Feature",
  "properties": {
    "addr:full":"Margrietstraat 61 Mierlo Noord-Brabant 5731 BN",
    "addr:housenumber":"61",
    "addr:postcode":"5731 bn",
    "addr:street":"Margrietstraat",
    "iso:country":"NL",
    "sg:address":"Margrietstraat 61",
    "sg:city":"Mierlo",
    "sg:orig_category":"Opticiens",
    "sg:phone":"+31 492 664 028",
    "sg:postcode":"5731 BN",
    "sg:province":"Noord-Brabant",
    "wof:name":"Blic Optiek",
    "wof:placetype":"venue"
},
  "geometry": {"coordinates":[5.6186327934,51.4429206848],"type":"Point"}
}