{
  "type": "Feature",
  "properties": {
    "addr:full":"Kruisweg 365A Rozenburg Nh Noord-Holland 1437 CG",
    "addr:housenumber":"365a",
    "addr:postcode":"1437 cg",
    "addr:street":"Kruisweg",
    "iso:country":"NL",
    "sg:address":"Kruisweg 365A",
    "sg:city":"Rozenburg Nh",
    "sg:orig_category":"Werving And Selectie Van Tijdelijk Personeel And Uitzendkantoren",
    "sg:phone":"+31 20 449 1005",
    "sg:postcode":"1437 CG",
    "sg:province":"Noord-Holland",
    "wof:name":"Mi-Jey",
    "wof:placetype":"venue"
},
  "geometry": {"coordinates":[4.7335348129,52.2838096619],"type":"Point"}
}