{
  "type": "Feature",
  "properties": {
    "addr:full":"Keiwg 91 Oosterhout Nb Noord-Brabant 4902 PC",
    "addr:housenumber":"91",
    "addr:postcode":"4902 pc",
    "addr:street":"Keiwg",
    "iso:country":"NL",
    "sg:address":"Keiwg 91",
    "sg:city":"Oosterhout Nb",
    "sg:orig_category":"Honden- En Kattentrimsalons",
    "sg:phone":"+31 162 437 723",
    "sg:postcode":"4902 PC",
    "sg:province":"Noord-Brabant",
    "wof:name":"Adul?re",
    "wof:placetype":"venue"
},
  "geometry": {"coordinates":[4.863807,51.640266],"type":"Point"}
}