{
  "type": "Feature",
  "properties": {
    "iso:country":"NL",
    "sg:address":"Van Nispenstraat 128",
    "sg:city":"Nijmegen",
    "sg:orig_category":"Schilderwerk",
    "sg:phone":"+31 24 323 0741",
    "sg:postcode":"6521 KR",
    "sg:province":"Gelderland",
    "wof:name":"W.G. Te Kiefte Ho Schild.Bedr.W.G. Te Ki",
    "wof:placetype":"venue"
},
  "geometry": {"coordinates":[5.874829,51.84108],"type":"Point"}
}