{
  "type": "Feature",
  "properties": {
    "iso:country":"NL",
    "sg:address":"Grt Wielen 111",
    "sg:city":"Rotterdam",
    "sg:orig_category":"Onderhoudswerken",
    "sg:phone":"+31 10 455 3604",
    "sg:postcode":"3068 PT",
    "sg:province":"Zuid-Holland",
    "wof:name":"Smeman Onderhoudsbedrijf, M J",
    "wof:placetype":"venue"
},
  "geometry": {"coordinates":[4.578172,51.963669],"type":"Point"}
}