{
  "type": "Feature",
  "properties": {
    "addr:full":"Keizersdijk 73 Raamsdonksveer Noord-Brabant 4941 GD",
    "addr:housenumber":"73",
    "addr:postcode":"4941 gd",
    "addr:street":"Keizersdijk",
    "iso:country":"NL",
    "sg:address":"Keizersdijk 73",
    "sg:city":"Raamsdonksveer",
    "sg:classifiers":[
        {
            "category":"Retail",
            "subcategory":"Photofinishing",
            "type":"Services"
        }
    ],
    "sg:phone":"+31 162 512 858",
    "sg:postcode":"4941 GD",
    "sg:province":"Noord-Brabant",
    "sg:tags":[
        "foto",
        "film"
    ],
    "wof:name":"Foto Hageman (C.C.Kieboom)",
    "wof:placetype":"venue"
},
  "geometry": {"coordinates":[4.872194,51.698544],"type":"Point"}
}