{
  "type": "Feature",
  "properties": {
    "iso:country":"NL",
    "sg:address":"Zeebruggestr 3",
    "sg:city":"Eindhoven",
    "sg:orig_category":"Yoga-Instituten",
    "sg:phone":"+31 40 241 0982",
    "sg:postcode":"5628 NH",
    "sg:province":"North Brabant",
    "wof:name":"Louise Van Der Put Yoga-Studio",
    "wof:placetype":"venue"
},
  "geometry": {"coordinates":[5.475569,51.477489],"type":"Point"}
}