{
  "type": "Feature",
  "properties": {
    "iso:country":"NL",
    "sg:address":"Peperstr 13",
    "sg:city":"Buren Gld",
    "sg:orig_category":"Meubelen - Fabrieken En Groothandel",
    "sg:phone":"+31 344 661 050",
    "sg:postcode":"4116 BG",
    "sg:province":"Gelderland",
    "wof:name":"Schieder-Ims Benelux/Interflair Bv",
    "wof:placetype":"venue"
},
  "geometry": {"coordinates":[5.335016,51.910896],"type":"Point"}
}