{
  "type": "Feature",
  "properties": {
    "addr:full":"Venekoterweg 13 Oosterwolde Fr Friesland 8431 HG",
    "addr:housenumber":"13",
    "addr:postcode":"8431 hg",
    "addr:street":"Venekoterweg",
    "iso:country":"NL",
    "sg:address":"Venekoterweg 13",
    "sg:city":"Oosterwolde Fr",
    "sg:orig_category":"Goederenvervoer Over De Weg",
    "sg:phone":"+31 516 520 478",
    "sg:postcode":"8431 HG",
    "sg:province":"Friesland",
    "wof:name":"A Hoekstra Transport En Handelsondernemi",
    "wof:placetype":"venue"
},
  "geometry": {"coordinates":[6.297936,52.983273],"type":"Point"}
}