{
  "type": "Feature",
  "properties": {
    "addr:full":"Lumeystr 5 Amsterdam New York 1056 VS",
    "addr:housenumber":"5;1056",
    "addr:postcode":"vs",
    "addr:street":"Lumeystr",
    "iso:country":"NL",
    "sg:address":"Lumeystr 5",
    "sg:city":"Amsterdam",
    "sg:orig_category":"Onderhoudswerken",
    "sg:phone":"+31 20 612 1271",
    "sg:postcode":"1056 VS",
    "sg:province":"New York",
    "wof:name":"Crovatto",
    "wof:placetype":"venue"
},
  "geometry": {"coordinates":[-74.201813,42.929234],"type":"Point"}
}