{
  "type": "Feature",
  "properties": {
    "addr:full":"Anemonenstr 12 Lisse Zuid-Holland 2161 WL",
    "addr:housenumber":"12",
    "addr:postcode":"2161 wl",
    "addr:street":"Anemonenstr",
    "iso:country":"NL",
    "sg:address":"Anemonenstr 12",
    "sg:city":"Lisse",
    "sg:orig_category":"Hydrocultuur",
    "sg:phone":"+31 252 415 520",
    "sg:postcode":"2161 WL",
    "sg:province":"Zuid-Holland",
    "wof:name":"Lb",
    "wof:placetype":"venue"
},
  "geometry": {"coordinates":[4.563295,52.25473],"type":"Point"}
}