{
  "type": "Feature",
  "properties": {
    "addr:full":"Kerkstraat 32 Milsbeek Limburg 6596 AL",
    "addr:housenumber":"32",
    "addr:postcode":"6596 al",
    "addr:street":"Kerkstraat",
    "iso:country":"NL",
    "sg:address":"Kerkstraat 32",
    "sg:city":"Milsbeek",
    "sg:orig_category":"Verlichting And Huishoudartikelen",
    "sg:phone":"+31 485 516 312",
    "sg:postcode":"6596 AL",
    "sg:province":"Limburg",
    "wof:name":"Firma W. Meeuwssen",
    "wof:placetype":"venue"
},
  "geometry": {"coordinates":[5.951151,51.72501],"type":"Point"}
}