{
  "type": "Feature",
  "properties": {
    "iso:country":"NL",
    "sg:address":"Boekelosestraat 53",
    "sg:city":"Enschede",
    "sg:orig_category":"Metaalbekleding And -Behandeling",
    "sg:phone":"+31 53 428 3502",
    "sg:postcode":"7548 AS",
    "sg:province":"Overijssel",
    "wof:name":"Van Duinen Indutech",
    "wof:placetype":"venue"
},
  "geometry": {"coordinates":[6.82417,52.204632],"type":"Point"}
}