{
  "type": "Feature",
  "properties": {
    "iso:country":"NL",
    "sg:address":"Rochussenstr 335",
    "sg:city":"Rotterdam",
    "sg:orig_category":"Adviesbureaus Bedrijfsorganisatie",
    "sg:phone":"+31 10 477 5733",
    "sg:postcode":"3023 DH",
    "sg:province":"Zuid-Holland",
    "wof:name":"Ncm",
    "wof:placetype":"venue"
},
  "geometry": {"coordinates":[4.453782,51.909176],"type":"Point"}
}