{
  "type": "Feature",
  "properties": {
    "iso:country":"NL",
    "sg:address":"Nijverheidstraat 7",
    "sg:city":"Nederhemert",
    "sg:classifiers":[
        {
            "category":"Retail",
            "subcategory":"Storage",
            "type":"Services"
        }
    ],
    "sg:phone":"+31 418 552 579",
    "sg:postcode":"5317 NL",
    "sg:province":"Gelderland",
    "sg:tags":[
        "opslag",
        "bewaring"
    ],
    "wof:name":"De Haas Transport Bv",
    "wof:placetype":"venue"
},
  "geometry": {"coordinates":[5.1636891365,51.7676506042],"type":"Point"}
}