{
  "type": "Feature",
  "properties": {
    "addr:full":"Ballumerwg 16 Nes Ameland Friesland 9163 GB",
    "addr:housenumber":"16",
    "addr:postcode":"9163 gb",
    "addr:street":"Ballumerwg",
    "iso:country":"NL",
    "sg:address":"Ballumerwg 16",
    "sg:city":"Nes Ameland",
    "sg:orig_category":"Administratie- En Boekhoudkantoren",
    "sg:phone":"+31 519 543 535",
    "sg:postcode":"9163 GB",
    "sg:province":"Friesland",
    "wof:name":"Nijenhuis",
    "wof:placetype":"venue"
},
  "geometry": {"coordinates":[5.766429,53.446262],"type":"Point"}
}