{
  "type": "Feature",
  "properties": {
    "addr:full":"Buitenom 22D S Gravenhage Zuid-Holland 2512 XA",
    "addr:housenumber":"22d;gravenhage",
    "addr:postcode":"2512 xa",
    "addr:street":"Buitenom;S",
    "iso:country":"NL",
    "sg:address":"Buitenom 22D",
    "sg:city":"S Gravenhage",
    "sg:orig_category":"Adviesbureaus Bedrijfsorganisatie",
    "sg:phone":"+31 70 388 4488",
    "sg:postcode":"2512 XA",
    "sg:province":"Zuid-Holland",
    "sg:website":"http://www.vanderkeur.nl",
    "wof:name":"Keur Services, Van Der",
    "wof:placetype":"venue"
},
  "geometry": {"coordinates":[4.30618,52.073212],"type":"Point"}
}