{
  "type": "Feature",
  "properties": {
    "addr:full":"De Hammen 13 , (Ind Terr De Bulk) Ravenstein North Brabant 5371 MK",
    "addr:housenumber":"13",
    "addr:postcode":"5371",
    "addr:street":"De Hammen;Terr De Bulk",
    "iso:country":"NL",
    "sg:address":"De Hammen 13 , (Ind Terr De Bulk)",
    "sg:city":"Ravenstein",
    "sg:orig_category":"Verhuur",
    "sg:phone":"+31 486 412 246",
    "sg:postcode":"5371 MK",
    "sg:province":"North Brabant",
    "wof:name":"Broek, Van Den",
    "wof:placetype":"venue"
},
  "geometry": {"coordinates":[5.650885,51.783592],"type":"Point"}
}