{
  "type": "Feature",
  "properties": {
    "addr:full":"Dr Honigstr 3 Zevenaar Gelderland 6901 AP",
    "addr:housenumber":"3",
    "addr:postcode":"6901 ap",
    "iso:country":"NL",
    "sg:address":"Dr Honigstr 3",
    "sg:city":"Zevenaar",
    "sg:orig_category":"Verenigingsgebouwen",
    "sg:phone":"+31 316 523 690",
    "sg:postcode":"6901 AP",
    "sg:province":"Gelderland",
    "wof:name":"Ons Huis",
    "wof:placetype":"venue"
},
  "geometry": {"coordinates":[6.076878,51.931618],"type":"Point"}
}