{
  "type": "Feature",
  "properties": {
    "addr:full":"Conradstr 26 Rotterdam South Holland 3013 AP",
    "addr:housenumber":"26",
    "addr:postcode":"3013 ap",
    "addr:street":"Conradstr",
    "iso:country":"NL",
    "sg:address":"Conradstr 26",
    "sg:city":"Rotterdam",
    "sg:orig_category":"Metaalgroothandel",
    "sg:phone":"+31 10 414 8381",
    "sg:postcode":"3013 AP",
    "sg:province":"South Holland",
    "wof:name":"Miko Bv",
    "wof:placetype":"venue"
},
  "geometry": {"coordinates":[4.467239,51.923302],"type":"Point"}
}