{
  "type": "Feature",
  "properties": {
    "addr:full":"Gasthuisstr 1 Kaatsheuvel Noord-Brabant 5171 GC",
    "addr:housenumber":"1",
    "addr:postcode":"5171 gc",
    "addr:street":"Gasthuisstr",
    "iso:country":"NL",
    "sg:address":"Gasthuisstr 1",
    "sg:city":"Kaatsheuvel",
    "sg:orig_category":"Cafetaria'S",
    "sg:phone":"+31 416 543 930",
    "sg:postcode":"5171 GC",
    "sg:province":"Noord-Brabant",
    "wof:name":"Markt, De",
    "wof:placetype":"venue"
},
  "geometry": {"coordinates":[5.033903,51.659801],"type":"Point"}
}