{
  "type": "Feature",
  "properties": {
    "addr:full":"Veerdyksewg 6 Scherpenisse Zeeland 4694 RD",
    "addr:housenumber":"6",
    "addr:postcode":"4694 rd",
    "addr:street":"Veerdyksewg",
    "iso:country":"NL",
    "sg:address":"Veerdyksewg 6",
    "sg:city":"Scherpenisse",
    "sg:orig_category":"Veilingen En Venduhuizen",
    "sg:phone":"+31 166 662 360",
    "sg:postcode":"4694 RD",
    "sg:province":"Zeeland",
    "wof:name":"Veilingver Scherpenisse Eo",
    "wof:placetype":"venue"
},
  "geometry": {"coordinates":[4.105608,51.547337],"type":"Point"}
}