{
  "type": "Feature",
  "properties": {
    "addr:full":"Gezichtslaan 276 Bilthoven Utrecht 3723 MA",
    "addr:housenumber":"276",
    "addr:postcode":"3723 ma",
    "addr:street":"Gezichtslaan",
    "iso:country":"NL",
    "sg:address":"Gezichtslaan 276",
    "sg:city":"Bilthoven",
    "sg:orig_category":"Wegen And Sportterreinen",
    "sg:phone":"+31 30 228 4755",
    "sg:postcode":"3723 MA",
    "sg:province":"Utrecht",
    "wof:name":"J. Meijerink & Zoon Bv",
    "wof:placetype":"venue"
},
  "geometry": {"coordinates":[5.2005472183,52.1558609009],"type":"Point"}
}