{
  "type": "Feature",
  "properties": {
    "addr:full":"St Josephpln 1 Bergen Op Zoom Noord-Brabant 4611 MH",
    "addr:housenumber":"1",
    "addr:postcode":"4611 mh",
    "iso:country":"NL",
    "sg:address":"St Josephpln 1",
    "sg:city":"Bergen Op Zoom",
    "sg:orig_category":"Warenhuizen",
    "sg:phone":"+31 164 241 454",
    "sg:postcode":"4611 MH",
    "sg:province":"Noord-Brabant",
    "wof:name":"Hema",
    "wof:placetype":"venue"
},
  "geometry": {"coordinates":[4.2924480438,51.4950714111],"type":"Point"}
}