{
  "type": "Feature",
  "properties": {
    "iso:country":"NL",
    "sg:address":"W Spaanstr 25",
    "sg:city":"Rotterdam",
    "sg:classifiers":[
        {
            "category":"Professional",
            "subcategory":"Management & Consulting",
            "type":"Services"
        }
    ],
    "sg:phone":"+31 10 242 0823",
    "sg:postcode":"3062 XL",
    "sg:province":"Zuid-Holland",
    "sg:tags":[
        "relation",
        "adviesbureaus",
        "public"
    ],
    "wof:name":"Witte Spaan Bv",
    "wof:placetype":"venue"
},
  "geometry": {"coordinates":[4.529801,51.923042],"type":"Point"}
}