{
  "type": "Feature",
  "properties": {
    "iso:country":"NL",
    "sg:address":"Oosteinde 21",
    "sg:city":"Hardenberg",
    "sg:orig_category":"Werving And Selectie Van Vast Personeel",
    "sg:phone":"+31 523 280 180",
    "sg:postcode":"7772 CA",
    "sg:province":"NL.08",
    "wof:name":"Centrum Werk & Inkomen Noordoost Overijssel",
    "wof:placetype":"venue"
},
  "geometry": {"coordinates":[6.6228837967,52.575340271],"type":"Point"}
}