{
  "type": "Feature",
  "properties": {
    "addr:full":"Trompetstraat 15 Arnhem Gelderland 6811 HK",
    "addr:housenumber":"15",
    "addr:postcode":"6811 hk",
    "addr:street":"Trompetstraat",
    "iso:country":"NL",
    "sg:address":"Trompetstraat 15",
    "sg:city":"Arnhem",
    "sg:orig_category":"Huishoudapparatuur, Televisies And Radio'S",
    "sg:phone":"+31 26 445 2845",
    "sg:postcode":"6811 HK",
    "sg:province":"Gelderland",
    "wof:name":"Handelsmaatschappij Besselink-Spaan Bv",
    "wof:placetype":"venue"
},
  "geometry": {"coordinates":[5.908251,51.978134],"type":"Point"}
}