{
  "type": "Feature",
  "properties": {
    "iso:country":"NL",
    "sg:address":"Wouter Berthoutlaan 49",
    "sg:city":"Etten-Leur",
    "sg:orig_category":"Boekhouders",
    "sg:phone":"+31 76 503 8199",
    "sg:postcode":"4871 AK",
    "sg:province":"North Brabant",
    "wof:name":"C.A.M.J. Mol En M.J.C. Mol-De Vries",
    "wof:placetype":"venue"
},
  "geometry": {"coordinates":[4.64085,51.583172],"type":"Point"}
}