{
  "type": "Feature",
  "properties": {
    "iso:country":"NL",
    "sg:address":"Peperstr 22",
    "sg:city":"Kaatsheuvel",
    "sg:orig_category":"Verloskundigen",
    "sg:phone":"+31 416 273 666",
    "sg:postcode":"5171 EC",
    "sg:province":"North Brabant",
    "wof:name":"Bollebuik, Prakt",
    "wof:placetype":"venue"
},
  "geometry": {"coordinates":[5.032641,51.660419],"type":"Point"}
}