{
  "type": "Feature",
  "properties": {
    "addr:full":"Oudewerfsln 32 Winschoten Groningen 9675 ET",
    "addr:housenumber":"32",
    "addr:postcode":"9675 et",
    "addr:street":"Oudewerfsln",
    "iso:country":"NL",
    "sg:address":"Oudewerfsln 32",
    "sg:city":"Winschoten",
    "sg:orig_category":"Beveiliging",
    "sg:phone":"+31 597 431 845",
    "sg:postcode":"9675 ET",
    "sg:province":"Groningen",
    "wof:name":"Nuus",
    "wof:placetype":"venue"
},
  "geometry": {"coordinates":[7.045145,53.14658],"type":"Point"}
}