{
  "type": "Feature",
  "properties": {
    "iso:country":"NL",
    "sg:address":"Ekkersrijt 1410",
    "sg:city":"Son",
    "sg:orig_category":"Autokeuringen",
    "sg:phone":"+31 499 472 724",
    "sg:postcode":"5692 AK",
    "sg:province":"Texas",
    "wof:name":"Garagebedrijf F. Stam Bv",
    "wof:placetype":"venue"
},
  "geometry": {"coordinates":[-101.937622,35.189621],"type":"Point"}
}