{
  "type": "Feature",
  "properties": {
    "addr:full":"Markt 1 Hattem Gelderland 8051 EZ",
    "addr:housenumber":"1",
    "addr:postcode":"8051 ez",
    "addr:street":"Markt;Gelderland",
    "iso:country":"NL",
    "sg:address":"Markt 1",
    "sg:city":"Hattem",
    "sg:orig_category":"Overheidsdiensten",
    "sg:phone":"+31 38 443 1616",
    "sg:postcode":"8051 EZ",
    "sg:province":"Gelderland",
    "wof:name":"Gemeente Hattem",
    "wof:placetype":"venue"
},
  "geometry": {"coordinates":[6.0698451996,52.4741668701],"type":"Point"}
}