{
  "type": "Feature",
  "properties": {
    "addr:full":"Poeldijk 8 Breukelen Ut Utrecht 3621 CZ",
    "addr:housenumber":"8",
    "addr:postcode":"3621",
    "addr:street":"Poeldijk",
    "iso:country":"NL",
    "sg:address":"Poeldijk 8",
    "sg:city":"Breukelen Ut",
    "sg:orig_category":"Kantoor- And Schoolbenodigdheden Gh",
    "sg:phone":"+31 346 261 044",
    "sg:postcode":"3621 CZ",
    "sg:province":"Utrecht",
    "wof:name":"Argus Etiketten Bv",
    "wof:placetype":"venue"
},
  "geometry": {"coordinates":[4.9977531433,52.1686019897],"type":"Point"}
}