{
  "type": "Feature",
  "properties": {
    "addr:full":"De Boeg 12 Drachten Provincie Friesland 9206 BB",
    "addr:housenumber":"12",
    "addr:postcode":"9206 bb",
    "addr:street":"De Boeg;Provincie Friesland",
    "iso:country":"NL",
    "sg:address":"De Boeg 12",
    "sg:city":"Drachten",
    "sg:orig_category":"Wegenbouw",
    "sg:phone":"+31 512 547 619",
    "sg:postcode":"9206 BB",
    "sg:province":"Provincie Friesland",
    "wof:name":"Reef Bv",
    "wof:placetype":"venue"
},
  "geometry": {"coordinates":[6.0639371872,53.1156921387],"type":"Point"}
}