{
  "type": "Feature",
  "properties": {
    "addr:full":"Brab Turfmarkt 88 Delft South Holland 2611 CP",
    "addr:housenumber":"88",
    "addr:postcode":"2611 cp",
    "addr:street":"Turfmarkt",
    "iso:country":"NL",
    "sg:address":"Brab Turfmarkt 88",
    "sg:city":"Delft",
    "sg:orig_category":"Opticiens",
    "sg:phone":"+31 15 213 7639",
    "sg:postcode":"2611 CP",
    "sg:province":"South Holland",
    "wof:name":"Huis Rinck, Het",
    "wof:placetype":"venue"
},
  "geometry": {"coordinates":[4.3606939316,52.0106544495],"type":"Point"}
}