{
  "type": "Feature",
  "properties": {
    "addr:full":"Opstal 10 Ravenswaaij Gelderland 4119 KX",
    "addr:housenumber":"10",
    "addr:postcode":"4119 kx",
    "addr:street":"Opstal;Gelderland",
    "iso:country":"NL",
    "sg:address":"Opstal 10",
    "sg:city":"Ravenswaaij",
    "sg:orig_category":"Bedrijfs- And Managementsconsultants",
    "sg:phone":"+31 345 502 359",
    "sg:postcode":"4119 KX",
    "sg:province":"Gelderland",
    "wof:name":"Auctor Bv",
    "wof:placetype":"venue"
},
  "geometry": {"coordinates":[5.3102498055,51.9437484741],"type":"Point"}
}