{
  "type": "Feature",
  "properties": {
    "addr:full":"Hoefstraat 175 Tilburg North Brabant 5014 NK",
    "addr:housenumber":"175",
    "addr:postcode":"5014 nk",
    "addr:street":"Hoefstraat",
    "iso:country":"NL",
    "sg:address":"Hoefstraat 175",
    "sg:city":"Tilburg",
    "sg:orig_category":"Overheidsdiensten",
    "sg:phone":"+31 13 543 5909",
    "sg:postcode":"5014 NK",
    "sg:province":"North Brabant",
    "wof:name":"De Baselaer",
    "wof:placetype":"venue"
},
  "geometry": {"coordinates":[5.0909090042,51.5705986023],"type":"Point"}
}