{
  "type": "Feature",
  "properties": {
    "addr:full":"Bloemenweg 90 Maastricht Limburg 6221 TW",
    "addr:housenumber":"90",
    "addr:postcode":"6221 tw",
    "addr:street":"Bloemenweg",
    "iso:country":"NL",
    "sg:address":"Bloemenweg 90",
    "sg:city":"Maastricht",
    "sg:orig_category":"Loodgieterswerk, Verwarming And Sanitaire Installaties",
    "sg:phone":"+31 43 321 8440",
    "sg:postcode":"6221 TW",
    "sg:province":"Limburg",
    "wof:name":"Hub Servicebedrijf",
    "wof:placetype":"venue"
},
  "geometry": {"coordinates":[5.71069,50.843384],"type":"Point"}
}