{
  "type": "Feature",
  "properties": {
    "addr:full":"Veldhoek 16 Lunteren Gelderland 6741 MP",
    "addr:housenumber":"16",
    "addr:postcode":"6741 mp",
    "addr:street":"Veldhoek;Gelderland",
    "iso:country":"NL",
    "sg:address":"Veldhoek 16",
    "sg:city":"Lunteren",
    "sg:orig_category":"Goederenvervoer Over De Weg",
    "sg:phone":"+31 6 53310138",
    "sg:postcode":"6741 MP",
    "sg:province":"Gelderland",
    "wof:name":"W Folmer",
    "wof:placetype":"venue"
},
  "geometry": {"coordinates":[5.572826,52.109493],"type":"Point"}
}