{
  "type": "Feature",
  "properties": {
    "iso:country":"NL",
    "sg:address":"Hitzumerweg 12",
    "sg:city":"Franeker",
    "sg:orig_category":"Bloemen And Planten",
    "sg:phone":"+31 517 452 244",
    "sg:postcode":"8801 PX",
    "sg:province":"Provincie Friesland",
    "wof:name":"Bloemenboetiek Zijlstra",
    "wof:placetype":"venue"
},
  "geometry": {"coordinates":[5.539651,53.167469],"type":"Point"}
}