{
  "type": "Feature",
  "properties": {
    "iso:country":"NL",
    "sg:address":"Grotestr 315",
    "sg:city":"Waalwijk",
    "sg:orig_category":"Verenigingen En Stichtingen",
    "sg:phone":"+31 416 340 304",
    "sg:postcode":"5142 CA",
    "sg:province":"North Brabant",
    "wof:name":"Turkse Islam Cult Ver",
    "wof:placetype":"venue"
},
  "geometry": {"coordinates":[5.070357,51.690952],"type":"Point"}
}