{
  "type": "Feature",
  "properties": {
    "addr:full":"Zaanwg 75-76 Wormerveer Noord-Holland 1521 DN",
    "addr:housenumber":"75-76",
    "addr:postcode":"wormerveer;1521 dn",
    "iso:country":"NL",
    "sg:address":"Zaanwg 75-76",
    "sg:city":"Wormerveer",
    "sg:orig_category":"Accountants - Administratie- Consulenten En -Kantoren",
    "sg:phone":"+31 75 622 5511",
    "sg:postcode":"1521 DN",
    "sg:province":"Noord-Holland",
    "wof:name":"Jager Accountantskantoor",
    "wof:placetype":"venue"
},
  "geometry": {"coordinates":[4.794289,52.490318],"type":"Point"}
}