{
  "type": "Feature",
  "properties": {
    "iso:country":"NL",
    "sg:address":"Zaanwg 75-76",
    "sg:city":"Wormerveer",
    "sg:orig_category":"Accountants - Administratie- Consulenten En -Kantoren",
    "sg:phone":"+31 75 622 5511",
    "sg:postcode":"1521 DN",
    "sg:province":"Noord-Holland",
    "wof:name":"Jager Accountantskantoor",
    "wof:placetype":"venue"
},
  "geometry": {"coordinates":[4.794289,52.490318],"type":"Point"}
}