{
  "type": "Feature",
  "properties": {
    "iso:country":"NL",
    "sg:address":"Hunze 52",
    "sg:city":"Rotterdam",
    "sg:orig_category":"Tuinaanleg En -Onderhoud",
    "sg:phone":"+31 6 24688370",
    "sg:postcode":"3068 GL",
    "sg:province":"Zuid-Holland",
    "sg:website":"http://www.archiecrea-hoveniers.nl",
    "wof:name":"Archie Crea R'Dam-Wassenaar",
    "wof:placetype":"venue"
},
  "geometry": {"coordinates":[4.567402,51.960491],"type":"Point"}
}