{
  "type": "Feature",
  "properties": {
    "addr:full":"Promenade 25 Zoetermeer Zuid-Holland 2711 AL",
    "addr:housenumber":"25",
    "addr:postcode":"2711 al",
    "addr:street":"Promenade",
    "iso:country":"NL",
    "sg:address":"Promenade 25",
    "sg:city":"Zoetermeer",
    "sg:orig_category":"Opticiens",
    "sg:phone":"+31 79 351 1545",
    "sg:postcode":"2711 AL",
    "sg:province":"Zuid-Holland",
    "wof:name":"Rinck Opticiens Het Huis",
    "wof:placetype":"venue"
},
  "geometry": {"coordinates":[4.4883189201,52.0611572266],"type":"Point"}
}