{
  "type": "Feature",
  "properties": {
    "addr:full":"Poortkampen 52 Zuidhorn Groningen 9801 JD",
    "addr:housenumber":"52",
    "addr:postcode":"9801 jd",
    "addr:street":"Poortkampen",
    "iso:country":"NL",
    "sg:address":"Poortkampen 52",
    "sg:city":"Zuidhorn",
    "sg:orig_category":"Boekenuitgeverijen",
    "sg:phone":"+31 594 507 736",
    "sg:postcode":"9801 JD",
    "sg:province":"Groningen",
    "wof:name":"De Rode Planeet",
    "wof:placetype":"venue"
},
  "geometry": {"coordinates":[6.402185,53.246365],"type":"Point"}
}