{
  "type": "Feature",
  "properties": {
    "addr:full":"Irislaan 67 Oegstgeest South Holland 2343 CH",
    "addr:housenumber":"67",
    "addr:postcode":"2343",
    "addr:street":"Irislaan",
    "iso:country":"NL",
    "sg:address":"Irislaan 67",
    "sg:city":"Oegstgeest",
    "sg:classifiers":[
        {
            "category":"Shopping",
            "subcategory":"Clothing, Apparel, & Fashions",
            "type":"Retail Goods"
        }
    ],
    "sg:phone":"+31 71 517 5397",
    "sg:postcode":"2343 CH",
    "sg:province":"South Holland",
    "sg:tags":[
        "ondergoed",
        "lingerie"
    ],
    "wof:name":"Body Fashion",
    "wof:placetype":"venue"
},
  "geometry": {"coordinates":[4.471278,52.186256],"type":"Point"}
}