{
  "type": "Feature",
  "properties": {
    "addr:full":"De Zodde 2 Loosdrecht North Holland 1231 MB",
    "addr:housenumber":"2",
    "addr:postcode":"1231 mb",
    "addr:street":"De Zodde",
    "iso:country":"NL",
    "sg:address":"De Zodde 2",
    "sg:city":"Loosdrecht",
    "sg:orig_category":"Kantoormachines",
    "sg:phone":"+31 35 656 2722",
    "sg:postcode":"1231 MB",
    "sg:province":"North Holland",
    "wof:name":"Two X Ned",
    "wof:placetype":"venue"
},
  "geometry": {"coordinates":[5.1122879982,52.2085227966],"type":"Point"}
}