{
  "type": "Feature",
  "properties": {
    "iso:country":"NL",
    "sg:address":"Kerkweg 29A",
    "sg:city":"Limmen",
    "sg:orig_category":"Apothekers",
    "sg:phone":"+31 72 505 2620",
    "sg:postcode":"1906 AV",
    "sg:province":"Noord-Holland",
    "wof:name":"Limmen Apotheek",
    "wof:placetype":"venue"
},
  "geometry": {"coordinates":[4.696844,52.572079],"type":"Point"}
}