{
  "type": "Feature",
  "properties": {
    "iso:country":"NL",
    "sg:address":"Zilverschoonplein 18",
    "sg:city":"Zaandam",
    "sg:classifiers":[
        {
            "category":"Bakery",
            "type":"Food & Drink"
        }
    ],
    "sg:phone":"+31 75 635 4018",
    "sg:postcode":"1508 CK",
    "sg:province":"Noord-Holland",
    "sg:tags":[
        "brood",
        "banket"
    ],
    "wof:name":"Lekkere Dingen Bakkerij",
    "wof:placetype":"venue"
},
  "geometry": {"coordinates":[4.82018,52.459824],"type":"Point"}
}