{
  "type": "Feature",
  "properties": {
    "addr:full":"Weststraat 20 Ouddorp Zh South Holland 3253 AR",
    "addr:housenumber":"20",
    "addr:postcode":"zh;3253",
    "addr:street":"Weststraat",
    "iso:country":"NL",
    "sg:address":"Weststraat 20",
    "sg:city":"Ouddorp Zh",
    "sg:orig_category":"Kansspelen",
    "sg:phone":"+31 187 683 327",
    "sg:postcode":"3253 AR",
    "sg:province":"South Holland",
    "wof:name":"Fun Land",
    "wof:placetype":"venue"
},
  "geometry": {"coordinates":[3.9341080189,51.8086929321],"type":"Point"}
}