{
  "type": "Feature",
  "properties": {
    "addr:full":"Schoolstraat 18 Uffelte Drenthe 7975 AC",
    "addr:housenumber":"18",
    "addr:postcode":"7975 ac",
    "addr:street":"Schoolstraat",
    "iso:country":"NL",
    "sg:address":"Schoolstraat 18",
    "sg:city":"Uffelte",
    "sg:orig_category":"Huishoudapparatuur, Televisies And Radio'S",
    "sg:phone":"+31 521 351 242",
    "sg:postcode":"7975 AC",
    "sg:province":"Drenthe",
    "wof:name":"C . Bruinenberg",
    "wof:placetype":"venue"
},
  "geometry": {"coordinates":[6.277867,52.788857],"type":"Point"}
}