{
  "type": "Feature",
  "properties": {
    "addr:full":"Postbus 56 Hardenberg Overijssel 7770 AB",
    "addr:housenumber":"56",
    "addr:postcode":"7770 ab",
    "addr:street":"Postbus",
    "iso:country":"NL",
    "sg:address":"Postbus 56",
    "sg:city":"Hardenberg",
    "sg:orig_category":"Keukens",
    "sg:phone":"+31 523 262 596",
    "sg:postcode":"7770 AB",
    "sg:province":"Overijssel",
    "sg:website":"http://www.veltkamp.nu",
    "wof:name":"Veltkamp Bv",
    "wof:placetype":"venue"
},
  "geometry": {"coordinates":[6.622884,52.57534],"type":"Point"}
}