{
  "type": "Feature",
  "properties": {
    "iso:country":"NL",
    "sg:address":"De Linge 29",
    "sg:city":"Woerden",
    "sg:orig_category":"Zuivelproducten And Spijsoli?n Gh",
    "sg:phone":"+31 348 414 593",
    "sg:postcode":"3448 CT",
    "sg:province":"Utrecht",
    "wof:name":"A.M. Karsemeijer Kaashandel",
    "wof:placetype":"venue"
},
  "geometry": {"coordinates":[4.870985,52.077526],"type":"Point"}
}