{
  "type": "Feature",
  "properties": {
    "addr:full":"Mr W M Oppedijk V Veenwg 16 C Burgum Friesland 9251 GA",
    "addr:housenumber":"16 c",
    "addr:postcode":"9251 ga",
    "addr:street":"W;Oppedijk;Veenwg",
    "iso:country":"NL",
    "sg:address":"Mr W M Oppedijk V Veenwg 16 C",
    "sg:city":"Burgum",
    "sg:orig_category":"Bruidskleding",
    "sg:phone":"+31 511 465 618",
    "sg:postcode":"9251 GA",
    "sg:province":"Friesland",
    "wof:name":"Fidelity Bruidsmode",
    "wof:placetype":"venue"
},
  "geometry": {"coordinates":[-83.222931,32.678131],"type":"Point"}
}