{
  "type": "Feature",
  "properties": {
    "addr:full":"Overbosch 2 Renswoude Gelderland 3927 GA",
    "addr:housenumber":"2",
    "addr:postcode":"3927 ga",
    "addr:street":"Overbosch;Gelderland",
    "iso:country":"NL",
    "sg:address":"Overbosch 2",
    "sg:city":"Renswoude",
    "sg:orig_category":"Adviesbureaus Bedrijfsorganisatie",
    "sg:phone":"+31 318 500 988",
    "sg:postcode":"3927 GA",
    "sg:province":"Gelderland",
    "wof:name":"Gmh",
    "wof:placetype":"venue"
},
  "geometry": {"coordinates":[5.546939,52.072178],"type":"Point"}
}