{
  "type": "Feature",
  "properties": {
    "addr:full":"De Markerichter 35 Borculo Gelderland 7271 ZJ",
    "addr:housenumber":"35",
    "addr:postcode":"7271 zj",
    "addr:street":"De Markerichter;Gelderland",
    "iso:country":"NL",
    "sg:address":"De Markerichter 35",
    "sg:city":"Borculo",
    "sg:orig_category":"Kappers",
    "sg:phone":"+31 545 271 332",
    "sg:postcode":"7271 ZJ",
    "sg:province":"Gelderland",
    "wof:name":"Maaike",
    "wof:placetype":"venue"
},
  "geometry": {"coordinates":[6.513453,52.122185],"type":"Point"}
}