{
  "type": "Feature",
  "properties": {
    "addr:full":"Goud-Es 4 Krimpen A/D Ijssel Zuid-Holland 2925 CD",
    "addr:housenumber":"4;a / d",
    "addr:postcode":"2925 cd",
    "addr:street":"Goud-Es",
    "iso:country":"NL",
    "sg:address":"Goud-Es 4",
    "sg:city":"Krimpen A/D Ijssel",
    "sg:classifiers":[
        {
            "category":"Shopping",
            "subcategory":"Gifts & Souvenirs",
            "type":"Retail Goods"
        }
    ],
    "sg:phone":"+31 180 524 453",
    "sg:postcode":"2925 CD",
    "sg:province":"Zuid-Holland",
    "sg:tags":[
        "geschenken"
    ],
    "wof:name":"Nova Line",
    "wof:placetype":"venue"
},
  "geometry": {"coordinates":[4.621208,51.914562],"type":"Point"}
}