{
  "type": "Feature",
  "properties": {
    "addr:full":"N Beetsstr 12 Papendrecht Zuid-Holland 3351 EC",
    "addr:housenumber":"12",
    "addr:postcode":"3351 ec",
    "addr:street":"N;Papendrecht",
    "iso:country":"NL",
    "sg:address":"N Beetsstr 12",
    "sg:city":"Papendrecht",
    "sg:orig_category":"Adviesbureaus Bouwkunde",
    "sg:phone":"+31 78 641 4288",
    "sg:postcode":"3351 EC",
    "sg:province":"Zuid-Holland",
    "wof:name":"Roderik",
    "wof:placetype":"venue"
},
  "geometry": {"coordinates":[4.674001,51.831802],"type":"Point"}
}