{
  "type": "Feature",
  "properties": {
    "addr:full":"Nieuwezijds Voorburgwal 46 Amsterdam Noord-Holland 1012 SC",
    "addr:housenumber":"46",
    "addr:postcode":"1012 sc",
    "addr:street":"Nieuwezijds Voorburgwal",
    "iso:country":"NL",
    "sg:address":"Nieuwezijds Voorburgwal 46",
    "sg:city":"Amsterdam",
    "sg:orig_category":"Film-, Tv- And Videoproductie",
    "sg:phone":"+31 20 620 8601",
    "sg:postcode":"1012 SC",
    "sg:province":"Noord-Holland",
    "wof:name":"Czar Film Company Bv",
    "wof:placetype":"venue"
},
  "geometry": {"coordinates":[4.893954,52.37664],"type":"Point"}
}