{
  "type": "Feature",
  "properties": {
    "addr:full":"V Goghstr 61 Reeuwyk South Holland 2811 VZ",
    "addr:housenumber":"61",
    "addr:postcode":"2811 vz",
    "addr:street":"Reeuwyk South",
    "iso:country":"NL",
    "sg:address":"V Goghstr 61",
    "sg:city":"Reeuwyk",
    "sg:orig_category":"Hypotheken",
    "sg:phone":"+31 182 393 898",
    "sg:postcode":"2811 VZ",
    "sg:province":"South Holland",
    "wof:name":"Groene Huys, Het",
    "wof:placetype":"venue"
},
  "geometry": {"coordinates":[4.722337,52.044903],"type":"Point"}
}