{
  "type": "Feature",
  "properties": {
    "addr:full":"Julianaln 14 Gennep Limburg 6591 AS",
    "addr:housenumber":"14",
    "addr:postcode":"6591 as",
    "addr:street":"Julianaln",
    "iso:country":"NL",
    "sg:address":"Julianaln 14",
    "sg:city":"Gennep",
    "sg:orig_category":"Verenigingen En Stichtingen",
    "sg:phone":"+31 485 517 489",
    "sg:postcode":"6591 AS",
    "sg:province":"Limburg",
    "wof:name":"Ark Bejaardenbond, De",
    "wof:placetype":"venue"
},
  "geometry": {"coordinates":[5.97119,51.699299],"type":"Point"}
}