{
  "type": "Feature",
  "properties": {
    "addr:full":"Aldegondestr 12 Vlissingen Zeeland 4386 BA",
    "addr:housenumber":"12",
    "addr:postcode":"4386 ba",
    "addr:street":"Aldegondestr",
    "iso:country":"NL",
    "sg:address":"Aldegondestr 12",
    "sg:city":"Vlissingen",
    "sg:orig_category":"Vertalers",
    "sg:phone":"+31 118 470 273",
    "sg:postcode":"4386 BA",
    "sg:province":"Zeeland",
    "wof:name":"Westveer, L A P",
    "wof:placetype":"venue"
},
  "geometry": {"coordinates":[3.590771,51.467644],"type":"Point"}
}