{
  "type": "Feature",
  "properties": {
    "addr:full":"V Gynstr 17 Ryswyk Zh Zuid-Holland 2288 GB",
    "addr:housenumber":"17",
    "addr:postcode":"2288 gb",
    "addr:street":"Ryswyk",
    "iso:country":"NL",
    "sg:address":"V Gynstr 17",
    "sg:city":"Ryswyk Zh",
    "sg:orig_category":"Adviesbureaus Bedrijfsorganisatie",
    "sg:phone":"+31 70 307 0684",
    "sg:postcode":"2288 GB",
    "sg:province":"Zuid-Holland",
    "sg:website":"http://www.logimark.nl",
    "wof:name":"Logimark Bv",
    "wof:placetype":"venue"
},
  "geometry": {"coordinates":[4.32436,52.037251],"type":"Point"}
}