{
  "type": "Feature",
  "properties": {
    "addr:full":"Ceresln 7 Veendam Groningen 9641 MJ",
    "addr:housenumber":"7",
    "addr:postcode":"9641 mj",
    "addr:street":"Ceresln",
    "iso:country":"NL",
    "sg:address":"Ceresln 7",
    "sg:city":"Veendam",
    "sg:orig_category":"Elektrotechnische Apparatuur - Fabrieken En Groothandel",
    "sg:phone":"+31 598 618 866",
    "sg:postcode":"9641 MJ",
    "sg:province":"Groningen",
    "wof:name":"Vries Bv, Jan De",
    "wof:placetype":"venue"
},
  "geometry": {"coordinates":[6.880442,53.106426],"type":"Point"}
}