{
  "type": "Feature",
  "properties": {
    "addr:full":"Haaksbergerstraat 303 Enschede Overijssel 7545 GJ",
    "addr:housenumber":"303",
    "addr:postcode":"7545 gj",
    "addr:street":"Haaksbergerstraat",
    "iso:country":"NL",
    "sg:address":"Haaksbergerstraat 303",
    "sg:city":"Enschede",
    "sg:classifiers":[
        {
            "category":"Fast Food",
            "type":"Food & Drink"
        }
    ],
    "sg:phone":"+31 53 432 3071",
    "sg:postcode":"7545 GJ",
    "sg:province":"Overijssel",
    "sg:tags":[
        "afhaal",
        "restaurant"
    ],
    "wof:name":"Cafetaria Sorrento",
    "wof:placetype":"venue"
},
  "geometry": {"coordinates":[6.875765,52.209309],"type":"Point"}
}