{
  "type": "Feature",
  "properties": {
    "addr:full":"Koningin Wilhelminastr 3 Piershil Zuid-Holland 3265 BH",
    "addr:housenumber":"3",
    "addr:postcode":"3265 bh",
    "addr:street":"Koningin Wilhelminastr",
    "iso:country":"NL",
    "sg:address":"Koningin Wilhelminastr 3",
    "sg:city":"Piershil",
    "sg:orig_category":"Kinderopvang Behalve Thuis",
    "sg:phone":"+31 186 692 893",
    "sg:postcode":"3265 BH",
    "sg:province":"Zuid-Holland",
    "wof:name":"Kinderopvang Korendijk Stichting",
    "wof:placetype":"venue"
},
  "geometry": {"coordinates":[4.315943,51.794815],"type":"Point"}
}