{
  "type": "Feature",
  "properties": {
    "addr:full":"Breestr 1D St Anthonis Noord-Brabant 5845 AX",
    "addr:housenumber":"1d",
    "addr:postcode":"5845 ax",
    "addr:street":"St",
    "iso:country":"NL",
    "sg:address":"Breestr 1D",
    "sg:city":"St Anthonis",
    "sg:orig_category":"Omroep",
    "sg:phone":"+31 485 381 777",
    "sg:postcode":"5845 AX",
    "sg:province":"Noord-Brabant",
    "wof:name":"Sticht St Anthonis",
    "wof:placetype":"venue"
},
  "geometry": {"coordinates":[5.878685,51.629509],"type":"Point"}
}