{
  "type": "Feature",
  "properties": {
    "addr:full":"P Heinstr 37 S Gravenhage Zuid-Holland 2518 CB",
    "addr:housenumber":"37;gravenhage;2518",
    "addr:postcode":"cb",
    "addr:street":"P;S",
    "iso:country":"NL",
    "sg:address":"P Heinstr 37",
    "sg:city":"S Gravenhage",
    "sg:orig_category":"Schoenen",
    "sg:phone":"+31 70 345 4562",
    "sg:postcode":"2518 CB",
    "sg:province":"Zuid-Holland",
    "sg:website":"http://www.vanasperen.nl",
    "wof:name":"Asperen, Van",
    "wof:placetype":"venue"
},
  "geometry": {"coordinates":[4.29348,52.080318],"type":"Point"}
}