{
  "type": "Feature",
  "properties": {
    "iso:country":"NL",
    "sg:address":"Dordtseln 19",
    "sg:city":"Rotterdam",
    "sg:classifiers":[
        {
            "category":"Food & Beverages",
            "subcategory":"Bakery",
            "type":"Retail Goods"
        }
    ],
    "sg:phone":"+31 10 486 0144",
    "sg:postcode":"3081 BB",
    "sg:province":"Zuid-Holland",
    "sg:tags":[
        "pizza"
    ],
    "wof:name":"Bella Pronto",
    "wof:placetype":"venue"
},
  "geometry": {"coordinates":[4.48229,51.893768],"type":"Point"}
}