{
  "type": "Feature",
  "properties": {
    "addr:full":"Kalkovenweg 204 Alphen A/D Rijn Zuid-Holland 2401 MC",
    "addr:housenumber":"204;2401",
    "addr:postcode":"mc",
    "addr:street":"Kalkovenweg",
    "iso:country":"NL",
    "sg:address":"Kalkovenweg 204",
    "sg:city":"Alphen A/D Rijn",
    "sg:orig_category":"Schoonheidssalons",
    "sg:phone":"+31 172 445 353",
    "sg:postcode":"2401 MC",
    "sg:province":"Zuid-Holland",
    "wof:name":"Schoonheidssalon Bjoetie",
    "wof:placetype":"venue"
},
  "geometry": {"coordinates":[4.651002,52.157108],"type":"Point"}
}