{
  "type": "Feature",
  "properties": {
    "addr:full":"Kotter 5 Alphen Aan Den Ryn Zuid-Holland 2401 MV",
    "addr:housenumber":"5",
    "addr:postcode":"2401 mv",
    "addr:street":"Kotter;Aan Den Ryn",
    "iso:country":"NL",
    "sg:address":"Kotter 5",
    "sg:city":"Alphen Aan Den Ryn",
    "sg:orig_category":"Adviesbureaus Bedrijfsorganisatie",
    "sg:phone":"+31 172 437 927",
    "sg:postcode":"2401 MV",
    "sg:province":"Zuid-Holland",
    "wof:name":"Graaff, G A De",
    "wof:placetype":"venue"
},
  "geometry": {"coordinates":[4.646916,52.157082],"type":"Point"}
}