{
  "type": "Feature",
  "properties": {
    "addr:full":"Van Trojenweg 4 Haren Gn Groningen 9751 VL",
    "addr:housenumber":"4",
    "addr:postcode":"9751 vl",
    "addr:street":"Van Trojenweg",
    "iso:country":"NL",
    "sg:address":"Van Trojenweg 4",
    "sg:city":"Haren Gn",
    "sg:orig_category":"Schilderwerk",
    "sg:phone":"+31 50 534 7364",
    "sg:postcode":"9751 VL",
    "sg:province":"Groningen",
    "wof:name":"T Adema",
    "wof:placetype":"venue"
},
  "geometry": {"coordinates":[6.618653,53.167828],"type":"Point"}
}