{
  "type": "Feature",
  "properties": {
    "addr:full":"Ruys De Beerenbrouckstr 18 Hoogezand Groningen 9602 XK",
    "addr:housenumber":"18",
    "addr:postcode":"9602 xk",
    "addr:street":"Ruys De Beerenbrouckstr",
    "iso:country":"NL",
    "sg:address":"Ruys De Beerenbrouckstr 18",
    "sg:city":"Hoogezand",
    "sg:orig_category":"Verzekeringen",
    "sg:phone":"+31 598 322 475",
    "sg:postcode":"9602 XK",
    "sg:province":"Groningen",
    "wof:name":"Bouwmeester",
    "wof:placetype":"venue"
},
  "geometry": {"coordinates":[6.752951,53.154823],"type":"Point"}
}