{
  "type": "Feature",
  "properties": {
    "addr:full":"Garst 20 Winschoten Groningen 9673 AE",
    "addr:housenumber":"20",
    "addr:postcode":"9673 ae",
    "addr:street":"Garst",
    "iso:country":"NL",
    "sg:address":"Garst 20",
    "sg:city":"Winschoten",
    "sg:classifiers":[
        {
            "category":"Farming",
            "subcategory":"Fish & Marine Products",
            "type":"Manufacturing & Wholesale Goods"
        }
    ],
    "sg:phone":"+31 597 416 104",
    "sg:postcode":"9673 AE",
    "sg:province":"Groningen",
    "sg:tags":[
        "vi"
    ],
    "wof:name":"Lich, P",
    "wof:placetype":"venue"
},
  "geometry": {"coordinates":[7.02925,53.138939],"type":"Point"}
}