{
  "type": "Feature",
  "properties": {
    "addr:full":"Zoutkeetsingel 116 'S Gravenhage Zuid-Holland 2512 HR",
    "addr:housenumber":"116 '",
    "addr:postcode":"2512 hr",
    "addr:street":"Zoutkeetsingel",
    "iso:country":"NL",
    "sg:address":"Zoutkeetsingel 116",
    "sg:city":"'S Gravenhage",
    "sg:orig_category":"Metaalwerken",
    "sg:phone":"+31 70 389 9660",
    "sg:postcode":"2512 HR",
    "sg:province":"Zuid-Holland",
    "wof:name":"W.W. V.D. Vet",
    "wof:placetype":"venue"
},
  "geometry": {"coordinates":[4.299057,52.072281],"type":"Point"}
}