{
  "type": "Feature",
  "properties": {
    "iso:country":"NL",
    "sg:address":"Kronenburgpassage 124",
    "sg:city":"Arnhem",
    "sg:orig_category":"Huishoudelijke Apparaten En Artikelen",
    "sg:phone":"+31 26 327 2709",
    "sg:postcode":"6831 ES",
    "sg:province":"Gelderland",
    "sg:website":"http://www.blokker.nl",
    "wof:name":"Blokker Bv",
    "wof:placetype":"venue"
},
  "geometry": {"coordinates":[5.897118,51.958206],"type":"Point"}
}