{
  "type": "Feature",
  "properties": {
    "addr:full":"Rijksweg 5A Margraten Limburg 6269 AA",
    "addr:housenumber":"5a",
    "addr:postcode":"6269 aa",
    "addr:street":"Rijksweg",
    "iso:country":"NL",
    "sg:address":"Rijksweg 5A",
    "sg:city":"Margraten",
    "sg:orig_category":"Fietshandelaren",
    "sg:phone":"+31 43 458 9089",
    "sg:postcode":"6269 AA",
    "sg:province":"Limburg",
    "wof:name":"Broqua Rijwiel- En Bromfietsenhandel",
    "wof:placetype":"venue"
},
  "geometry": {"coordinates":[5.750145,50.839668],"type":"Point"}
}