{
  "type": "Feature",
  "properties": {
    "iso:country":"NL",
    "sg:address":"Raadhuisstr 9",
    "sg:city":"Rucphen",
    "sg:orig_category":"Kappers",
    "sg:phone":"+31 165 341 261",
    "sg:postcode":"4715 CB",
    "sg:province":"Noord-Brabant",
    "sg:website":"http://www.hairmaxx.nl",
    "wof:name":"Hairmaxx",
    "wof:placetype":"venue"
},
  "geometry": {"coordinates":[4.557694912,51.5327835083],"type":"Point"}
}