{
  "type": "Feature",
  "properties": {
    "iso:country":"NL",
    "sg:address":"Calslaan 5",
    "sg:city":"Enschede",
    "sg:orig_category":"Vertaal- And Tolkenbureaus",
    "sg:phone":"+31 53 435 0834",
    "sg:postcode":"7522 MH",
    "sg:province":"Overijssel",
    "wof:name":"Linetec",
    "wof:placetype":"venue"
},
  "geometry": {"coordinates":[6.84567,52.241901],"type":"Point"}
}