{
  "type": "Feature",
  "properties": {
    "iso:country":"NL",
    "sg:address":"Westerdijk 56",
    "sg:city":"Leimuiden",
    "sg:orig_category":"Boekhouders",
    "sg:phone":"+31 71 331 9396",
    "sg:postcode":"2451 VC",
    "sg:province":"Zuid-Holland",
    "wof:name":"J J Van Spronsen",
    "wof:placetype":"venue"
},
  "geometry": {"coordinates":[4.64894,52.20929],"type":"Point"}
}