{
  "type": "Feature",
  "properties": {
    "addr:full":"Krommenieerpad 76 Wormerveer North Holland 1521 HB",
    "addr:housenumber":"76",
    "addr:postcode":"1521 hb",
    "addr:street":"Krommenieerpad",
    "iso:country":"NL",
    "sg:address":"Krommenieerpad 76",
    "sg:city":"Wormerveer",
    "sg:orig_category":"Zuivelproducten And Spijsoli?n Gh",
    "sg:phone":"+31 75 621 7180",
    "sg:postcode":"1521 HB",
    "sg:province":"North Holland",
    "wof:name":"Zaanse Eierhandel",
    "wof:placetype":"venue"
},
  "geometry": {"coordinates":[4.789546,52.494358],"type":"Point"}
}