{
  "type": "Feature",
  "properties": {
    "addr:full":"Ettensestraat 19 Terborg Gelderland 7061 AA",
    "addr:housenumber":"19",
    "addr:postcode":"7061 aa",
    "addr:street":"Ettensestraat;Gelderland",
    "iso:country":"NL",
    "sg:address":"Ettensestraat 19",
    "sg:city":"Terborg",
    "sg:orig_category":"Fitnesscentra",
    "sg:phone":"+31 315 329 606",
    "sg:postcode":"7061 AA",
    "sg:province":"Gelderland",
    "wof:name":"Fitness Sport Gezondheidscentr Physique",
    "wof:placetype":"venue"
},
  "geometry": {"coordinates":[6.349401,51.916996],"type":"Point"}
}