{
  "type": "Feature",
  "properties": {
    "addr:full":"Antillenwg 21 Almere Flevoland 1339 KD",
    "addr:housenumber":"21",
    "addr:postcode":"1339 kd",
    "addr:street":"Antillenwg;Flevoland",
    "iso:country":"NL",
    "sg:address":"Antillenwg 21",
    "sg:city":"Almere",
    "sg:orig_category":"Hypotheken",
    "sg:phone":"+31 36 537 8795",
    "sg:postcode":"1339 KD",
    "sg:province":"Flevoland",
    "sg:website":"http://www.wijdenes.net",
    "wof:name":"Wijdenes, M",
    "wof:placetype":"venue"
},
  "geometry": {"coordinates":[5.306933,52.394775],"type":"Point"}
}