{
  "type": "Feature",
  "properties": {
    "addr:full":"J Luykenln 270 Leiden Zuid-Holland 2332 DH",
    "addr:housenumber":"270",
    "addr:postcode":"2332 dh",
    "iso:country":"NL",
    "sg:address":"J Luykenln 270",
    "sg:city":"Leiden",
    "sg:classifiers":[
        {
            "category":"Manufacturing",
            "subcategory":"Electronics",
            "type":"Manufacturing & Wholesale Goods"
        }
    ],
    "sg:phone":"+31 71 532 3811",
    "sg:postcode":"2332 DH",
    "sg:province":"Zuid-Holland",
    "sg:tags":[
        "en",
        "laser",
        "lasertechniek"
    ],
    "sg:website":"http://www.laserfreaks.com",
    "wof:name":"Absurd Laser Freaks",
    "wof:placetype":"venue"
},
  "geometry": {"coordinates":[4.464539,52.16264],"type":"Point"}
}