{
  "type": "Feature",
  "properties": {
    "iso:country":"NL",
    "sg:address":"Van Diemenstraat 38 (Graansilo)",
    "sg:city":"Amsterdam",
    "sg:orig_category":"Fotostudio'S And Fotografen",
    "sg:phone":"+31 20 689 2443",
    "sg:postcode":"1057 GT",
    "sg:province":"North Holland",
    "wof:name":"Hans Petersen",
    "wof:placetype":"venue"
},
  "geometry": {"coordinates":[4.888728,52.390072],"type":"Point"}
}