{
  "type": "Feature",
  "properties": {
    "addr:full":"Postbus 41176 Groningen Gelderland 9701 CD",
    "addr:housenumber":"41176",
    "addr:postcode":"9701 cd",
    "addr:street":"Postbus",
    "iso:country":"NL",
    "sg:address":"Postbus 41176",
    "sg:city":"Groningen",
    "sg:orig_category":"Onderzoekbureaus",
    "sg:phone":"+31 50 318 4055",
    "sg:postcode":"9701 CD",
    "sg:province":"Gelderland",
    "sg:website":"http://www.boponderzoek.nl",
    "wof:name":"Bop",
    "wof:placetype":"venue"
},
  "geometry": {"coordinates":[6.56502,53.21645],"type":"Point"}
}