{
  "type": "Feature",
  "properties": {
    "addr:full":"Flierstr 81E Lage Zwaluwe North Brabant 4926 AB",
    "addr:housenumber":"81e",
    "addr:postcode":"4926 ab",
    "addr:street":"Flierstr",
    "iso:country":"NL",
    "sg:address":"Flierstr 81E",
    "sg:city":"Lage Zwaluwe",
    "sg:orig_category":"Keukens",
    "sg:phone":"+31 168 483 578",
    "sg:postcode":"4926 AB",
    "sg:province":"North Brabant",
    "wof:name":"Leest, Van",
    "wof:placetype":"venue"
},
  "geometry": {"coordinates":[4.685379,51.713585],"type":"Point"}
}