{
  "type": "Feature",
  "properties": {
    "addr:full":"Vreewykstr 26 Leiden Zuid-Holland 2311 XH",
    "addr:housenumber":"26",
    "addr:postcode":"2311 xh",
    "addr:street":"Vreewykstr",
    "iso:country":"NL",
    "sg:address":"Vreewykstr 26",
    "sg:city":"Leiden",
    "sg:orig_category":"Fotoapparatuur En Filmapparatuur - Reparatie",
    "sg:phone":"+31 71 514 9324",
    "sg:postcode":"2311 XH",
    "sg:province":"Zuid-Holland",
    "sg:website":"http://www.danilos-camera-service.nl",
    "wof:name":"Danilo'S, Camera Service",
    "wof:placetype":"venue"
},
  "geometry": {"coordinates":[4.48443,52.153156],"type":"Point"}
}