{
  "type": "Feature",
  "properties": {
    "iso:country":"NL",
    "sg:address":"Grt Beerstr 1",
    "sg:city":"Alkmaar",
    "sg:orig_category":"Adviesbureaus Bedrijfsorganisatie",
    "sg:phone":"+31 72 520 8690",
    "sg:postcode":"1814 KN",
    "sg:province":"Noord-Holland",
    "sg:website":"http://www.shbadvies.nl",
    "wof:name":"Shb",
    "wof:placetype":"venue"
},
  "geometry": {"coordinates":[4.742676,52.622669],"type":"Point"}
}