{
  "type": "Feature",
  "properties": {
    "addr:full":"Kaarder 45 Hoorn Nh Noord-Holland 1625 TK",
    "addr:housenumber":"45",
    "addr:postcode":"1625 tk",
    "addr:street":"Kaarder",
    "iso:country":"NL",
    "sg:address":"Kaarder 45",
    "sg:city":"Hoorn Nh",
    "sg:orig_category":"Fietsen En Bromfietsen",
    "sg:phone":"+31 229 234 001",
    "sg:postcode":"1625 TK",
    "sg:province":"Noord-Holland",
    "wof:name":"Proost, Ferry",
    "wof:placetype":"venue"
},
  "geometry": {"coordinates":[5.051823,52.658161],"type":"Point"}
}