{
  "type": "Feature",
  "properties": {
    "addr:full":"Wikkestr 66 Alphen Aan Den Ryn Zuid-Holland 2403 ET",
    "addr:housenumber":"66",
    "addr:postcode":"2403 et",
    "addr:street":"Wikkestr;Aan Den Ryn",
    "iso:country":"NL",
    "sg:address":"Wikkestr 66",
    "sg:city":"Alphen Aan Den Ryn",
    "sg:orig_category":"Verenigingen En Stichtingen",
    "sg:phone":"+31 172 416 588",
    "sg:postcode":"2403 ET",
    "sg:province":"Zuid-Holland",
    "sg:website":"http://www.eurosafety.org",
    "wof:name":"Eurosafety",
    "wof:placetype":"venue"
},
  "geometry": {"coordinates":[4.684025,52.145435],"type":"Point"}
}