{
  "type": "Feature",
  "properties": {
    "addr:full":"Patersstraat 3 Venray Limburg 5801 AT",
    "addr:housenumber":"3",
    "addr:postcode":"5801",
    "addr:street":"Patersstraat",
    "iso:country":"NL",
    "sg:address":"Patersstraat 3",
    "sg:city":"Venray",
    "sg:orig_category":"Hypotheken And Hypotheekbanken",
    "sg:phone":"+31 478 515 755",
    "sg:postcode":"5801 AT",
    "sg:province":"Limburg",
    "wof:name":"De Hypotheekshop",
    "wof:placetype":"venue"
},
  "geometry": {"coordinates":[5.975645,51.524357],"type":"Point"}
}