{
  "type": "Feature",
  "properties": {
    "iso:country":"NL",
    "sg:address":"Papenburghlaan 14",
    "sg:city":"Santpoort-Zuid",
    "sg:orig_category":"Verzekeringen",
    "sg:phone":"+31 23 537 4639",
    "sg:postcode":"2082 HR",
    "sg:province":"North Holland",
    "wof:name":"Assurantie-En Administratiekantoor Risseeuw",
    "wof:placetype":"venue"
},
  "geometry": {"coordinates":[4.633833,52.423248],"type":"Point"}
}