{
  "type": "Feature",
  "properties": {
    "addr:full":"Neherkd T/O 106 S Gravenhage South Holland 2521 VC",
    "addr:housenumber":"106",
    "addr:postcode":"2521 vc",
    "addr:street":"S Gravenhage",
    "iso:country":"NL",
    "sg:address":"Neherkd T/O 106",
    "sg:city":"S Gravenhage",
    "sg:orig_category":"Zalenverhuur",
    "sg:phone":"+31 70 394 6802",
    "sg:postcode":"2521 VC",
    "sg:province":"South Holland",
    "wof:name":"Partyboat",
    "wof:placetype":"venue"
},
  "geometry": {"coordinates":[4.32071,52.062988],"type":"Point"}
}