{
  "type": "Feature",
  "properties": {
    "addr:full":"Bisonspoor 1003 Maarssen Utrecht 3605 KA",
    "addr:housenumber":"1003",
    "addr:postcode":"3605 ka",
    "addr:street":"Bisonspoor",
    "iso:country":"NL",
    "sg:address":"Bisonspoor 1003",
    "sg:city":"Maarssen",
    "sg:orig_category":"Boekhandels",
    "sg:phone":"+31 346 571 206",
    "sg:postcode":"3605 KA",
    "sg:province":"Utrecht",
    "wof:name":"Jan Van Nes Vof",
    "wof:placetype":"venue"
},
  "geometry": {"coordinates":[5.029133,52.135475],"type":"Point"}
}