{
  "type": "Feature",
  "properties": {
    "iso:country":"NL",
    "sg:address":"Herengr 248D",
    "sg:city":"Amsterdam",
    "sg:orig_category":"Architecten En Architectenbureaus",
    "sg:phone":"+31 20 627 0082",
    "sg:postcode":"1016 BV",
    "sg:province":"Noord-Holland",
    "wof:name":"Berg, P T Van Den",
    "wof:placetype":"venue"
},
  "geometry": {"coordinates":[4.886551,52.371727],"type":"Point"}
}