{
  "type": "Feature",
  "properties": {
    "addr:full":"Herengr 248D Amsterdam Noord-Holland 1016 BV",
    "addr:housenumber":"248d",
    "addr:postcode":"1016 bv",
    "addr:street":"Herengr",
    "iso:country":"NL",
    "sg:address":"Herengr 248D",
    "sg:city":"Amsterdam",
    "sg:orig_category":"Architecten En Architectenbureaus",
    "sg:phone":"+31 20 627 0082",
    "sg:postcode":"1016 BV",
    "sg:province":"Noord-Holland",
    "wof:name":"Berg, P T Van Den",
    "wof:placetype":"venue"
},
  "geometry": {"coordinates":[4.886551,52.371727],"type":"Point"}
}