{
  "type": "Feature",
  "properties": {
    "addr:full":"Paul Rodenkolaan 68 Zutphen Michigan 7207 CH",
    "addr:housenumber":"68",
    "addr:postcode":"7207",
    "addr:street":"Paul Rodenkolaan",
    "iso:country":"NL",
    "sg:address":"Paul Rodenkolaan 68",
    "sg:city":"Zutphen",
    "sg:orig_category":"Boekhouders",
    "sg:phone":"+31 575 572 098",
    "sg:postcode":"7207 CH",
    "sg:province":"Michigan",
    "wof:name":"D. Wiersma",
    "wof:placetype":"venue"
},
  "geometry": {"coordinates":[-85.97782100000001,42.812248],"type":"Point"}
}