{
  "type": "Feature",
  "properties": {
    "addr:full":"Nieuwstr 83-85 Oldenzaal Overijssel 7572 BZ",
    "addr:housenumber":"83-85",
    "addr:postcode":"7572 bz",
    "iso:country":"NL",
    "sg:address":"Nieuwstr 83-85",
    "sg:city":"Oldenzaal",
    "sg:orig_category":"Fietsen En Bromfietsen",
    "sg:phone":"+31 541 512 906",
    "sg:postcode":"7572 BZ",
    "sg:province":"Overijssel",
    "sg:website":"http://www.camerontweewielers.nl",
    "wof:name":"Cameron Tweewielers Bv",
    "wof:placetype":"venue"
},
  "geometry": {"coordinates":[6.92509,52.310913],"type":"Point"}
}