{
  "type": "Feature",
  "properties": {
    "addr:full":"Gramsbergerwg 52B Hardenberg Overijssel 7772 PB",
    "addr:housenumber":"52b",
    "addr:postcode":"7772 pb",
    "addr:street":"Gramsbergerwg",
    "iso:country":"NL",
    "sg:address":"Gramsbergerwg 52B",
    "sg:city":"Hardenberg",
    "sg:orig_category":"Sportverenigingen En Ontspannings- Verenigingen",
    "sg:phone":"+31 523 266 965",
    "sg:postcode":"7772 PB",
    "sg:province":"Overijssel",
    "wof:name":"Eendracht Muziekver, De",
    "wof:placetype":"venue"
},
  "geometry": {"coordinates":[6.630942,52.575844],"type":"Point"}
}