{
  "type": "Feature",
  "properties": {
    "addr:full":"Balatonmeerln 55 Amsterdam North Holland 1060 RD",
    "addr:housenumber":"55",
    "addr:postcode":"1060 rd",
    "addr:street":"Balatonmeerln",
    "iso:country":"NL",
    "sg:address":"Balatonmeerln 55",
    "sg:city":"Amsterdam",
    "sg:orig_category":"Verbouwingen",
    "sg:phone":"+31 20 667 1024",
    "sg:postcode":"1060 RD",
    "sg:province":"North Holland",
    "wof:name":"Herka, Timmerbedrijf",
    "wof:placetype":"venue"
},
  "geometry": {"coordinates":[4.781965,52.347363],"type":"Point"}
}