{
  "type": "Feature",
  "properties": {
    "addr:full":"Willemspln 9 Arnhem Gelderland 6811 KB",
    "addr:housenumber":"9",
    "addr:postcode":"6811 kb",
    "addr:street":"Willemspln",
    "iso:country":"NL",
    "sg:address":"Willemspln 9",
    "sg:city":"Arnhem",
    "sg:orig_category":"Administratie- En Boekhoudkantoren",
    "sg:phone":"+31 26 351 0076",
    "sg:postcode":"6811 KB",
    "sg:province":"Gelderland",
    "wof:name":"Albers Accountants",
    "wof:placetype":"venue"
},
  "geometry": {"coordinates":[5.90374,51.98333],"type":"Point"}
}