{
  "type": "Feature",
  "properties": {
    "iso:country":"NL",
    "sg:address":"Gortelsewg 18",
    "sg:city":"Vaassen",
    "sg:orig_category":"Wasserijen",
    "sg:phone":"+31 578 571 111",
    "sg:postcode":"8171 RA",
    "sg:province":"Gelderland",
    "wof:name":"Rentex Interlin Jaspers Bv",
    "wof:placetype":"venue"
},
  "geometry": {"coordinates":[5.9433188438,52.2895812988],"type":"Point"}
}