{
  "type": "Feature",
  "properties": {
    "addr:full":"Koningshoek 92355 Maassluis South Holland 3144 BA",
    "addr:housenumber":"92355",
    "addr:postcode":"3144 ba",
    "addr:street":"Koningshoek",
    "iso:country":"NL",
    "sg:address":"Koningshoek 92355",
    "sg:city":"Maassluis",
    "sg:orig_category":"Juweliers",
    "sg:phone":"+31 10 591 8099",
    "sg:postcode":"3144 BA",
    "sg:province":"South Holland",
    "wof:name":"Juwelier Den Houter",
    "wof:placetype":"venue"
},
  "geometry": {"coordinates":[4.239934,51.927906],"type":"Point"}
}