{
  "type": "Feature",
  "properties": {
    "addr:full":"Ysselmeerwg 3 Naarden North Holland 1411 AA",
    "addr:housenumber":"3",
    "addr:postcode":"1411 aa",
    "addr:street":"Ysselmeerwg",
    "iso:country":"NL",
    "sg:address":"Ysselmeerwg 3",
    "sg:city":"Naarden",
    "sg:classifiers":[
        {
            "category":"Travel",
            "subcategory":"Hotels & Motels",
            "type":"Entertainment"
        }
    ],
    "sg:phone":"+31 35 695 1514",
    "sg:postcode":"1411 AA",
    "sg:province":"North Holland",
    "sg:website":"http://www.nh-hotels.com",
    "wof:name":"Nh Naarden",
    "wof:placetype":"venue"
},
  "geometry": {"coordinates":[5.141997,52.309643],"type":"Point"}
}