{
  "type": "Feature",
  "properties": {
    "addr:full":"Keizersberg 20 Elsendorp Noord-Brabant 5424 SH",
    "addr:housenumber":"20",
    "addr:postcode":"5424 sh",
    "addr:street":"Keizersberg",
    "iso:country":"NL",
    "sg:address":"Keizersberg 20",
    "sg:city":"Elsendorp",
    "sg:orig_category":"Huisdierenvoer Fab",
    "sg:phone":"+31 492 352 311",
    "sg:postcode":"5424 SH",
    "sg:province":"Noord-Brabant",
    "wof:name":"Keizersberg Diervoeders",
    "wof:placetype":"venue"
},
  "geometry": {"coordinates":[5.770687,51.585945],"type":"Point"}
}