{
  "type": "Feature",
  "properties": {
    "addr:full":"Nassaupln 14 Zundert North Brabant 4881 CL",
    "addr:housenumber":"14",
    "addr:postcode":"4881",
    "addr:street":"Nassaupln",
    "iso:country":"NL",
    "sg:address":"Nassaupln 14",
    "sg:city":"Zundert",
    "sg:orig_category":"Verzekeringen - Verzekeringskantoren",
    "sg:phone":"+31 76 597 2248",
    "sg:postcode":"4881 CL",
    "sg:province":"North Brabant",
    "wof:name":"Westenburg Groep",
    "wof:placetype":"venue"
},
  "geometry": {"coordinates":[4.666793,51.474838],"type":"Point"}
}