{
  "type": "Feature",
  "properties": {
    "addr:full":"De Scheifelaar 20 Veghel Noord-Brabant 5463 HL",
    "addr:housenumber":"20",
    "addr:postcode":"5463 hl",
    "addr:street":"De Scheifelaar",
    "iso:country":"NL",
    "sg:address":"De Scheifelaar 20",
    "sg:city":"Veghel",
    "sg:orig_category":"Werving En Selectie",
    "sg:phone":"+31 413 365 783",
    "sg:postcode":"5463 HL",
    "sg:province":"Noord-Brabant",
    "wof:name":"Jacq Visser Personeelsmanagement",
    "wof:placetype":"venue"
},
  "geometry": {"coordinates":[5.5511398315,51.6069107056],"type":"Point"}
}