{
  "type": "Feature",
  "properties": {
    "addr:full":"Vrijenban 12 Delfgauw Zuid-Holland 2645 AS",
    "addr:housenumber":"12",
    "addr:postcode":"2645 as",
    "addr:street":"Vrijenban",
    "iso:country":"NL",
    "sg:address":"Vrijenban 12",
    "sg:city":"Delfgauw",
    "sg:orig_category":"Goederenvervoer Over De Weg",
    "sg:phone":"+31 15 261 9925",
    "sg:postcode":"2645 AS",
    "sg:province":"Zuid-Holland",
    "wof:name":"D. Van Buijtene",
    "wof:placetype":"venue"
},
  "geometry": {"coordinates":[4.395469,52.011536],"type":"Point"}
}