{
  "type": "Feature",
  "properties": {
    "iso:country":"NL",
    "sg:address":"Grotestraat 21",
    "sg:city":"Ede Gld",
    "sg:orig_category":"Baby- And Kinderkleding",
    "sg:phone":"+31 318 693 179",
    "sg:postcode":"6711 AH",
    "sg:province":"Gelderland",
    "wof:name":"We Men",
    "wof:placetype":"venue"
},
  "geometry": {"coordinates":[5.66986,52.044415],"type":"Point"}
}