{
  "type": "Feature",
  "properties": {
    "iso:country":"NL",
    "sg:address":"Hees 15",
    "sg:city":"Gieten",
    "sg:classifiers":[
        {
            "category":"Food & Beverages",
            "subcategory":"Fruits & Vegetables",
            "type":"Retail Goods"
        }
    ],
    "sg:phone":"+31 592 263 922",
    "sg:postcode":"9461 HM",
    "sg:province":"Drenthe",
    "sg:tags":[
        "groenten"
    ],
    "wof:name":"Zuivelhandel H. Haandrikman",
    "wof:placetype":"venue"
},
  "geometry": {"coordinates":[6.769063,52.994705],"type":"Point"}
}