{
  "type": "Feature",
  "properties": {
    "iso:country":"NL",
    "sg:address":"Werkmansbeemd 8B",
    "sg:city":"Oosterhout Nb",
    "sg:classifiers":[
        {
            "category":"Wholesale",
            "subcategory":"Meat",
            "type":"Manufacturing & Wholesale Goods"
        }
    ],
    "sg:phone":"+31 162 462 793",
    "sg:postcode":"4907 EW",
    "sg:province":"Noord-Brabant",
    "sg:tags":[
        "regeltechniek",
        "en",
        "meet-"
    ],
    "sg:website":"http://www.aptechnology.nl",
    "wof:name":"Ap Technology",
    "wof:placetype":"venue"
},
  "geometry": {"coordinates":[4.855951,51.661617],"type":"Point"}
}