{
  "type": "Feature",
  "properties": {
    "iso:country":"NL",
    "sg:address":"Nieuwezijds Voorburgwal 92",
    "sg:city":"Amsterdam",
    "sg:classifiers":[
        {
            "category":"Travel",
            "subcategory":"Hotels & Motels",
            "type":"Entertainment"
        }
    ],
    "sg:phone":"+31 20 623 0063",
    "sg:postcode":"1012 SG",
    "sg:province":"Noord-Holland",
    "wof:name":"Bob'S Youth Hostel",
    "wof:placetype":"venue"
},
  "geometry": {"coordinates":[4.892582,52.375694],"type":"Point"}
}