{
  "type": "Feature",
  "properties": {
    "iso:country":"NL",
    "sg:address":"Hoefkade 268",
    "sg:city":"'S Gravenhage",
    "sg:orig_category":"Juridische Dienstverlening",
    "sg:phone":"+31 70 380 1184",
    "sg:postcode":"2526 CE",
    "sg:province":"Zuid-Holland",
    "wof:name":"Acte (M L Vd Harst)",
    "wof:placetype":"venue"
},
  "geometry": {"coordinates":[4.3111600876,52.0674591064],"type":"Point"}
}