{
  "type": "Feature",
  "properties": {
    "addr:full":"Gagelveld 5 Milsbeek Limburg 6596 CC",
    "addr:housenumber":"5",
    "addr:postcode":"6596 cc",
    "addr:street":"Gagelveld",
    "iso:country":"NL",
    "sg:address":"Gagelveld 5",
    "sg:city":"Milsbeek",
    "sg:orig_category":"Yoga-Instituten",
    "sg:phone":"+31 485 513 701",
    "sg:postcode":"6596 CC",
    "sg:province":"Limburg",
    "wof:name":"Ottenheim-Neutelings, C",
    "wof:placetype":"venue"
},
  "geometry": {"coordinates":[5.945132,51.7313],"type":"Point"}
}