{
  "type": "Feature",
  "properties": {
    "addr:full":"Goorsestraat 17 Haaksbergen Overijssel 7482 CB",
    "addr:housenumber":"17",
    "addr:postcode":"7482 cb",
    "addr:street":"Goorsestraat",
    "iso:country":"NL",
    "sg:address":"Goorsestraat 17",
    "sg:city":"Haaksbergen",
    "sg:orig_category":"Diverse Consumentenartikelen Gh",
    "sg:phone":"+31 53 572 4666",
    "sg:postcode":"7482 CB",
    "sg:province":"Overijssel",
    "wof:name":"Bv Chemietechniek Trans-World",
    "wof:placetype":"venue"
},
  "geometry": {"coordinates":[6.734389782,52.1590309143],"type":"Point"}
}