{
  "type": "Feature",
  "properties": {
    "addr:full":"Pr Bernhardwg 7 Schalkhaar NL.08 7433 CZ",
    "addr:housenumber":"7;nl.08",
    "addr:postcode":"7433",
    "iso:country":"NL",
    "sg:address":"Pr Bernhardwg 7",
    "sg:city":"Schalkhaar",
    "sg:orig_category":"Projectinrichting",
    "sg:phone":"+31 570 608 804",
    "sg:postcode":"7433 CZ",
    "sg:province":"NL.08",
    "sg:website":"http://www.opdemuuren.nl",
    "wof:name":"Muuren, Op De",
    "wof:placetype":"venue"
},
  "geometry": {"coordinates":[6.187511,52.269108],"type":"Point"}
}