{
  "type": "Feature",
  "properties": {
    "addr:full":"Grt Voort 84 Zwolle Overijssel 8041 BH",
    "addr:housenumber":"84",
    "addr:postcode":"8041 bh",
    "addr:street":"Voort",
    "iso:country":"NL",
    "sg:address":"Grt Voort 84",
    "sg:city":"Zwolle",
    "sg:orig_category":"Bedden En Matrassen",
    "sg:phone":"+31 38 422 5991",
    "sg:postcode":"8041 BH",
    "sg:province":"Overijssel",
    "wof:name":"Dorma?l",
    "wof:placetype":"venue"
},
  "geometry": {"coordinates":[6.0667,52.510605],"type":"Point"}
}