{
  "type": "Feature",
  "properties": {
    "iso:country":"NL",
    "sg:address":"Punterhof 24",
    "sg:city":"Lisse",
    "sg:orig_category":"Webdesign Bureaus",
    "sg:phone":"+31 252 422 468",
    "sg:postcode":"2162 LC",
    "sg:province":"Zuid-Holland",
    "sg:website":"http://www.e-movement.nl",
    "wof:name":"Emovement",
    "wof:placetype":"venue"
},
  "geometry": {"coordinates":[4.5598740578,52.242931366],"type":"Point"}
}