{
  "type": "Feature",
  "properties": {
    "addr:full":"Oostwal 15 Volendam Noord-Holland 1132 BJ",
    "addr:housenumber":"15",
    "addr:postcode":"1132 bj",
    "addr:street":"Oostwal",
    "iso:country":"NL",
    "sg:address":"Oostwal 15",
    "sg:city":"Volendam",
    "sg:orig_category":"Montagebedrijven",
    "sg:phone":"+31 299 365 808",
    "sg:postcode":"1132 BJ",
    "sg:province":"Noord-Holland",
    "wof:name":"Aris",
    "wof:placetype":"venue"
},
  "geometry": {"coordinates":[5.055522,52.496586],"type":"Point"}
}