{
  "type": "Feature",
  "properties": {
    "addr:full":"Herestraat 25 Grijpskerk Groningen 9843 AH",
    "addr:housenumber":"25",
    "addr:postcode":"9843 ah",
    "addr:street":"Herestraat",
    "iso:country":"NL",
    "sg:address":"Herestraat 25",
    "sg:city":"Grijpskerk",
    "sg:orig_category":"Kappers",
    "sg:phone":"+31 594 213 215",
    "sg:postcode":"9843 AH",
    "sg:province":"Groningen",
    "wof:name":"Rogier Verhoef Haarmode",
    "wof:placetype":"venue"
},
  "geometry": {"coordinates":[6.308168,53.26384],"type":"Point"}
}