{
  "type": "Feature",
  "properties": {
    "iso:country":"NL",
    "sg:address":"Posthoornsewg 6",
    "sg:city":"Oisterwyk",
    "sg:orig_category":"Vakantieverblijven",
    "sg:phone":"+31 13 528 3838",
    "sg:postcode":"5062 SZ",
    "sg:province":"Noord-Brabant",
    "sg:website":"http://www.do.nl/delork",
    "wof:name":"Lork Stacaravanpark, De",
    "wof:placetype":"venue"
},
  "geometry": {"coordinates":[5.229434,51.57576],"type":"Point"}
}