{
  "type": "Feature",
  "properties": {
    "addr:full":"Brandwijksedijk 15 Brandwijk Zuid-Holland 2974 LB",
    "addr:housenumber":"15",
    "addr:postcode":"2974 lb",
    "addr:street":"Brandwijksedijk",
    "iso:country":"NL",
    "sg:address":"Brandwijksedijk 15",
    "sg:city":"Brandwijk",
    "sg:orig_category":"Hout Gh",
    "sg:phone":"+31 184 641 344",
    "sg:postcode":"2974 LB",
    "sg:province":"Zuid-Holland",
    "wof:name":"Sloop Houthandel J Vlot",
    "wof:placetype":"venue"
},
  "geometry": {"coordinates":[4.811708,51.888699],"type":"Point"}
}