{
  "type": "Feature",
  "properties": {
    "addr:full":"Bosgouw 212 Almere NL. 1352 GV",
    "addr:housenumber":"212",
    "addr:postcode":"1352 gv",
    "addr:street":"Bosgouw;Nl.",
    "iso:country":"NL",
    "sg:address":"Bosgouw 212",
    "sg:city":"Almere",
    "sg:orig_category":"Kappers",
    "sg:phone":"+31 36 534 8343",
    "sg:postcode":"1352 GV",
    "sg:province":"NL.",
    "wof:name":"Kapsalon Gallery",
    "wof:placetype":"venue"
},
  "geometry": {"coordinates":[5.2104687691,52.3442077637],"type":"Point"}
}