{
  "type": "Feature",
  "properties": {
    "iso:country":"NL",
    "sg:address":"Westelijke Havendijk 25",
    "sg:city":"Roosendaal",
    "sg:orig_category":"Airconditioning And Ventilatie",
    "sg:phone":"+31 165 536 880",
    "sg:postcode":"4703 RG",
    "sg:province":"Noord-Brabant",
    "wof:name":"Cooltec",
    "wof:placetype":"venue"
},
  "geometry": {"coordinates":[4.448785,51.545498],"type":"Point"}
}