{
  "type": "Feature",
  "properties": {
    "addr:full":"Haardijk 3 Hardenberg NL.08 7771 PZ",
    "addr:housenumber":"3;nl.08",
    "addr:postcode":"7771 pz",
    "addr:street":"Haardijk",
    "iso:country":"NL",
    "sg:address":"Haardijk 3",
    "sg:city":"Hardenberg",
    "sg:orig_category":"Autokeuringen",
    "sg:phone":"+31 523 261 488",
    "sg:postcode":"7771 PZ",
    "sg:province":"NL.08",
    "wof:name":"Mastebroek'S Automobielbedrijven Bv",
    "wof:placetype":"venue"
},
  "geometry": {"coordinates":[6.602825,52.574249],"type":"Point"}
}