{
  "type": "Feature",
  "properties": {
    "iso:country":"NL",
    "sg:address":"Juliana Bernh Ln 89",
    "sg:city":"Hoensbroek",
    "sg:orig_category":"Schilders",
    "sg:phone":"+31 45 522 3286",
    "sg:postcode":"6432 GV",
    "sg:province":"Limburg",
    "wof:name":"Debije En Zn Schilderwerken Bv",
    "wof:placetype":"venue"
},
  "geometry": {"coordinates":[5.921788,50.920998],"type":"Point"}
}