{
  "type": "Feature",
  "properties": {
    "addr:full":"L Costerstr 2-6 Deurne Noord-Brabant 5753 AM",
    "addr:housenumber":"2-6",
    "addr:postcode":"5753",
    "iso:country":"NL",
    "sg:address":"L Costerstr 2-6",
    "sg:city":"Deurne",
    "sg:orig_category":"Kartonnage - Fabrieken En Groothandel",
    "sg:phone":"+31 493 310 655",
    "sg:postcode":"5753 AM",
    "sg:province":"Noord-Brabant",
    "wof:name":"Nies Bv, Gebr",
    "wof:placetype":"venue"
},
  "geometry": {"coordinates":[5.784786,51.451756],"type":"Point"}
}