{
  "type": "Feature",
  "properties": {
    "iso:country":"NL",
    "sg:address":"Adrianaln 101A",
    "sg:city":"Rotterdam",
    "sg:orig_category":"Kasregisters",
    "sg:phone":"+31 10 418 6405",
    "sg:postcode":"3053 MA",
    "sg:province":"Zuid-Holland",
    "sg:website":"http://www.coin-masters.com",
    "wof:name":"Coinmasters Bv",
    "wof:placetype":"venue"
},
  "geometry": {"coordinates":[4.476931,51.960812],"type":"Point"}
}