{
  "type": "Feature",
  "properties": {
    "addr:full":"Ommelanderwyk 158 Veendam Groningen 9644 TR",
    "addr:housenumber":"158",
    "addr:postcode":"9644 tr",
    "addr:street":"Veendam",
    "iso:country":"NL",
    "sg:address":"Ommelanderwyk 158",
    "sg:city":"Veendam",
    "sg:orig_category":"Metselwerken",
    "sg:phone":"+31 598 617 325",
    "sg:postcode":"9644 TR",
    "sg:province":"Groningen",
    "wof:name":"Berendsen, J A",
    "wof:placetype":"venue"
},
  "geometry": {"coordinates":[6.916579,53.081223],"type":"Point"}
}