{
  "type": "Feature",
  "properties": {
    "addr:full":"Westergeest 10 Den Burg Noord-Holland 1791 LJ",
    "addr:housenumber":"10",
    "addr:postcode":"1791 lj",
    "addr:street":"Westergeest",
    "iso:country":"NL",
    "sg:address":"Westergeest 10",
    "sg:city":"Den Burg",
    "sg:orig_category":"Bloembollen - Groothandel",
    "sg:phone":"+31 222 313 461",
    "sg:postcode":"1791 LJ",
    "sg:province":"Noord-Holland",
    "wof:name":"Dijt Bv",
    "wof:placetype":"venue"
},
  "geometry": {"coordinates":[4.813919,53.034061],"type":"Point"}
}