{
  "type": "Feature",
  "properties": {
    "addr:full":"Van Utrechtweg 33 Krimpen A/D Ijssel Zuid-Holland 2921 LN",
    "addr:housenumber":"33;a / d",
    "addr:postcode":"2921 ln",
    "addr:street":"Van Utrechtweg",
    "iso:country":"NL",
    "sg:address":"Van Utrechtweg 33",
    "sg:city":"Krimpen A/D Ijssel",
    "sg:orig_category":"Autokeuringen",
    "sg:phone":"+31 180 518 102",
    "sg:postcode":"2921 LN",
    "sg:province":"Zuid-Holland",
    "wof:name":"Ronal Garage Bv",
    "wof:placetype":"venue"
},
  "geometry": {"coordinates":[4.577272,51.907261],"type":"Point"}
}