{
  "type": "Feature",
  "properties": {
    "addr:full":"J E Bylhof 8 Waarder Zuid-Holland 3466 NW",
    "addr:housenumber":"8",
    "addr:postcode":"3466 nw",
    "iso:country":"NL",
    "sg:address":"J E Bylhof 8",
    "sg:city":"Waarder",
    "sg:orig_category":"Bestratingen",
    "sg:phone":"+31 6 20013203",
    "sg:postcode":"3466 NW",
    "sg:province":"Zuid-Holland",
    "wof:name":"Kastelein",
    "wof:placetype":"venue"
},
  "geometry": {"coordinates":[4.81998,52.061287],"type":"Point"}
}