{
  "type": "Feature",
  "properties": {
    "iso:country":"NL",
    "sg:address":"Steenakkerplein 22",
    "sg:city":"Gilze",
    "sg:classifiers":[
        {
            "category":"Shopping",
            "subcategory":"Clothing, Apparel, & Fashions",
            "type":"Retail Goods"
        }
    ],
    "sg:phone":"+31 161 452 169",
    "sg:postcode":"5126 AW",
    "sg:province":"Noord-Brabant",
    "sg:tags":[
        "ondergoed",
        "lingerie"
    ],
    "wof:name":"Monique'S Lingerie",
    "wof:placetype":"venue"
},
  "geometry": {"coordinates":[4.938846,51.544617],"type":"Point"}
}