{
  "type": "Feature",
  "properties": {
    "addr:full":"Parallelweg Zuid 117 Nieuwerkerk Ad Ijssel Zuid-Holland 2914 LE",
    "addr:housenumber":"117",
    "addr:postcode":"ijssel;2914 le",
    "addr:street":"Parallelweg Zuid",
    "iso:country":"NL",
    "sg:address":"Parallelweg Zuid 117",
    "sg:city":"Nieuwerkerk Ad Ijssel",
    "sg:orig_category":"Autokeuringen",
    "sg:phone":"+31 180 319 660",
    "sg:postcode":"2914 LE",
    "sg:province":"Zuid-Holland",
    "wof:name":"G Hoogendoorn En Zoon",
    "wof:placetype":"venue"
},
  "geometry": {"coordinates":[4.612273,51.975018],"type":"Point"}
}