{
  "type": "Feature",
  "properties": {
    "addr:full":"Eidereend 20 Lok Eendenveld Emmen Provincie Drenthe 7827 LD",
    "addr:housenumber":"20 lok",
    "addr:postcode":"7827 ld",
    "addr:street":"Eidereend;Eendenveld;Provincie Drenthe",
    "iso:country":"NL",
    "sg:address":"Eidereend 20 Lok Eendenveld",
    "sg:city":"Emmen",
    "sg:orig_category":"Scholen Voor Basisonderwijs",
    "sg:phone":"+31 591 631 980",
    "sg:postcode":"7827 LD",
    "sg:province":"Provincie Drenthe",
    "wof:name":"Regenboog Prot Chr Jenaplan, De",
    "wof:placetype":"venue"
},
  "geometry": {"coordinates":[6.89235,52.742371],"type":"Point"}
}