{
  "type": "Feature",
  "properties": {
    "addr:full":"V H Kasselstr 33 Tilburg North Brabant 5021 EP",
    "addr:housenumber":"33",
    "addr:postcode":"5021 ep",
    "iso:country":"NL",
    "sg:address":"V H Kasselstr 33",
    "sg:city":"Tilburg",
    "sg:orig_category":"Kunsthandel",
    "sg:phone":"+31 13 536 9286",
    "sg:postcode":"5021 EP",
    "sg:province":"North Brabant",
    "wof:name":"Brabantse Land, Sticht Het",
    "wof:placetype":"venue"
},
  "geometry": {"coordinates":[5.09061,51.548569],"type":"Point"}
}