{
  "type": "Feature",
  "properties": {
    "addr:full":"Pleimuiden 16 Amsterdam North Holland 1046 AG",
    "addr:housenumber":"16",
    "addr:postcode":"1046",
    "addr:street":"Pleimuiden",
    "iso:country":"NL",
    "sg:address":"Pleimuiden 16",
    "sg:city":"Amsterdam",
    "sg:orig_category":"Meubelen",
    "sg:phone":"+31 20 411 8834",
    "sg:postcode":"1046 AG",
    "sg:province":"North Holland",
    "wof:name":"Seminck, Jan",
    "wof:placetype":"venue"
},
  "geometry": {"coordinates":[4.786775,52.390362],"type":"Point"}
}