{
  "type": "Feature",
  "properties": {
    "addr:full":"Haviksdk 7A Grootschermer Noord-Holland 1843 JG",
    "addr:housenumber":"7a",
    "addr:postcode":"1843 jg",
    "addr:street":"Haviksdk",
    "iso:country":"NL",
    "sg:address":"Haviksdk 7A",
    "sg:city":"Grootschermer",
    "sg:orig_category":"Beeldende Kunstenaars",
    "sg:phone":"+31 299 673 764",
    "sg:postcode":"1843 JG",
    "sg:province":"Noord-Holland",
    "wof:name":"Barbara",
    "wof:placetype":"venue"
},
  "geometry": {"coordinates":[4.853344,52.591621],"type":"Point"}
}