{
  "type": "Feature",
  "properties": {
    "addr:full":"Dorsvlegel 10 Breda Noord-Brabant 4822 AR",
    "addr:housenumber":"10",
    "addr:postcode":"4822",
    "addr:street":"Dorsvlegel",
    "iso:country":"NL",
    "sg:address":"Dorsvlegel 10",
    "sg:city":"Breda",
    "sg:orig_category":"Beveiliging",
    "sg:phone":"+31 76 542 2115",
    "sg:postcode":"4822 AR",
    "sg:province":"Noord-Brabant",
    "sg:website":"http://www.bssecurity.nl",
    "wof:name":"Bs Security Systems",
    "wof:placetype":"venue"
},
  "geometry": {"coordinates":[4.743966,51.62167],"type":"Point"}
}