{
  "type": "Feature",
  "properties": {
    "addr:full":"Nei De Feart 33 Warns Friesland 8721 EP",
    "addr:housenumber":"33",
    "addr:postcode":"8721 ep",
    "addr:street":"Nei De Feart",
    "iso:country":"NL",
    "sg:address":"Nei De Feart 33",
    "sg:city":"Warns",
    "sg:orig_category":"Tekstschrijversters",
    "sg:phone":"+31 514 682 441",
    "sg:postcode":"8721 EP",
    "sg:province":"Friesland",
    "sg:website":"http://www.linqua.nl",
    "wof:name":"Linqua",
    "wof:placetype":"venue"
},
  "geometry": {"coordinates":[-83.884407,34.997856],"type":"Point"}
}