{
  "type": "Feature",
  "properties": {
    "iso:country":"NL",
    "sg:address":"Philip Vingboonsstraat 25",
    "sg:city":"Amsterdam",
    "sg:orig_category":"Meubelreparatie And -Restauratie",
    "sg:phone":"+31 20 684 4483",
    "sg:postcode":"1067 BG",
    "sg:province":"Noord-Holland",
    "wof:name":"W.F.A. Kabel Woningstoffeerdersbedrijf",
    "wof:placetype":"venue"
},
  "geometry": {"coordinates":[4.795732975,52.3833961487],"type":"Point"}
}