{
  "type": "Feature",
  "properties": {
    "addr:full":"Spikweien 70 Lomm Limburg 5943 AD",
    "addr:housenumber":"70",
    "addr:postcode":"5943 ad",
    "addr:street":"Spikweien",
    "iso:country":"NL",
    "sg:address":"Spikweien 70",
    "sg:city":"Lomm",
    "sg:orig_category":"Hang- En Sluitwerk - Fabrieken En Groothandel",
    "sg:phone":"+31 77 473 7475",
    "sg:postcode":"5943 AD",
    "sg:province":"Limburg",
    "wof:name":"Ami Bv",
    "wof:placetype":"venue"
},
  "geometry": {"coordinates":[6.17642,51.447109],"type":"Point"}
}