{
  "type": "Feature",
  "properties": {
    "addr:full":"Schoolpad 1 Weesp Noord-Holland 1383 EA",
    "addr:housenumber":"1",
    "addr:postcode":"1383 ea",
    "addr:street":"Schoolpad",
    "iso:country":"NL",
    "sg:address":"Schoolpad 1",
    "sg:city":"Weesp",
    "sg:classifiers":[
        {
            "category":"Education",
            "subcategory":"Preschool",
            "type":"Public Place"
        }
    ],
    "sg:phone":"+31 294 418 755",
    "sg:postcode":"1383 EA",
    "sg:province":"Noord-Holland",
    "sg:tags":[
        "kleuteronderwijs",
        "basis-"
    ],
    "wof:name":"De Terp",
    "wof:placetype":"venue"
},
  "geometry": {"coordinates":[5.042757,52.300007],"type":"Point"}
}