{
  "type": "Feature",
  "properties": {
    "addr:full":"Schouwburgring 22 Tilburg North Brabant 5038 TL",
    "addr:housenumber":"22",
    "addr:postcode":"5038 tl",
    "addr:street":"Schouwburgring",
    "iso:country":"NL",
    "sg:address":"Schouwburgring 22",
    "sg:city":"Tilburg",
    "sg:orig_category":"Warenhuizen",
    "sg:phone":"+31 900 9800",
    "sg:postcode":"5038 TL",
    "sg:province":"North Brabant",
    "wof:name":"Kijkshop",
    "wof:placetype":"venue"
},
  "geometry": {"coordinates":[5.0807390213,51.5548057556],"type":"Point"}
}