{
  "type": "Feature",
  "properties": {
    "iso:country":"NL",
    "sg:address":"Pr Hendrikln 132",
    "sg:city":"Brunssum",
    "sg:orig_category":"Fietsen En Bromfietsen",
    "sg:phone":"+31 45 525 3445",
    "sg:postcode":"6441 AC",
    "sg:province":"Limburg",
    "wof:name":"Smokey",
    "wof:placetype":"venue"
},
  "geometry": {"coordinates":[5.97619,50.948593],"type":"Point"}
}