{
  "type": "Feature",
  "properties": {
    "addr:full":"Vosboerweg 20 Hengelo Ov Overijssel 7556 BS",
    "addr:housenumber":"20",
    "addr:postcode":"7556 bs",
    "addr:street":"Vosboerweg;Ov",
    "iso:country":"NL",
    "sg:address":"Vosboerweg 20",
    "sg:city":"Hengelo Ov",
    "sg:orig_category":"Huishoudapparatuur, Televisies And Radio'S",
    "sg:phone":"+31 74 250 1770",
    "sg:postcode":"7556 BS",
    "sg:province":"Overijssel",
    "wof:name":"Decilux Lease Bv",
    "wof:placetype":"venue"
},
  "geometry": {"coordinates":[6.773668,52.283257],"type":"Point"}
}