{
  "type": "Feature",
  "properties": {
    "iso:country":"NL",
    "sg:address":"Mozartstr 20A",
    "sg:city":"Venray",
    "sg:orig_category":"Fitnesscentra",
    "sg:phone":"+31 478 589 574",
    "sg:postcode":"5802 HP",
    "sg:province":"Limburg",
    "wof:name":"Centrum Venray",
    "wof:placetype":"venue"
},
  "geometry": {"coordinates":[5.986853,51.518372],"type":"Point"}
}