{
  "type": "Feature",
  "properties": {
    "addr:full":"Noordeinde 149 Almere Flevoland 1334 AN",
    "addr:housenumber":"149",
    "addr:postcode":"1334 an",
    "addr:street":"Noordeinde;Flevoland",
    "iso:country":"NL",
    "sg:address":"Noordeinde 149",
    "sg:city":"Almere",
    "sg:orig_category":"Juweliers",
    "sg:phone":"+31 36 532 7737",
    "sg:postcode":"1334 AN",
    "sg:province":"Flevoland",
    "wof:name":"Dijkema, Wim",
    "wof:placetype":"venue"
},
  "geometry": {"coordinates":[5.277258,52.395107],"type":"Point"}
}