{
  "type": "Feature",
  "properties": {
    "addr:full":"Oudeschans 30 Amsterdam North Holland 1011 LB",
    "addr:housenumber":"30",
    "addr:postcode":"1011 lb",
    "addr:street":"Oudeschans",
    "iso:country":"NL",
    "sg:address":"Oudeschans 30",
    "sg:city":"Amsterdam",
    "sg:orig_category":"Fitnesscentra",
    "sg:phone":"+31 20 624 5858",
    "sg:postcode":"1011 LB",
    "sg:province":"North Holland",
    "wof:name":"Panatta Gym",
    "wof:placetype":"venue"
},
  "geometry": {"coordinates":[4.904025,52.371574],"type":"Point"}
}