{
  "type": "Feature",
  "properties": {
    "addr:full":"Gulicksestraat 2 Sittard Limburg 6133 VX",
    "addr:housenumber":"2",
    "addr:postcode":"6133 vx",
    "addr:street":"Gulicksestraat",
    "iso:country":"NL",
    "sg:address":"Gulicksestraat 2",
    "sg:city":"Sittard",
    "sg:classifiers":[
        {
            "category":"Fast Food",
            "type":"Food & Drink"
        }
    ],
    "sg:phone":"+31 46 451 7351",
    "sg:postcode":"6133 VX",
    "sg:province":"Limburg",
    "sg:tags":[
        "afhaal",
        "restaurant"
    ],
    "wof:name":"Friture Ophoven",
    "wof:placetype":"venue"
},
  "geometry": {"coordinates":[5.857967,50.987976],"type":"Point"}
}