{
  "type": "Feature",
  "properties": {
    "addr:full":"Noordersngl 67 Berkel En Rodenrys Zuid-Holland 2651 LS",
    "addr:housenumber":"67",
    "addr:postcode":"2651 ls",
    "addr:street":"Noordersngl;Berkel",
    "iso:country":"NL",
    "sg:address":"Noordersngl 67",
    "sg:city":"Berkel En Rodenrys",
    "sg:orig_category":"Loonbedrijven",
    "sg:phone":"+31 10 511 7162",
    "sg:postcode":"2651 LS",
    "sg:province":"Zuid-Holland",
    "wof:name":"Verkerk, Ruud",
    "wof:placetype":"venue"
},
  "geometry": {"coordinates":[4.47659,51.994122],"type":"Point"}
}