{
  "type": "Feature",
  "properties": {
    "addr:full":"Dorpsstr 29 Amstelveen Noord-Holland 1182 JA",
    "addr:housenumber":"29",
    "addr:postcode":"1182 ja",
    "addr:street":"Dorpsstr",
    "iso:country":"NL",
    "sg:address":"Dorpsstr 29",
    "sg:city":"Amstelveen",
    "sg:orig_category":"Pottenbakkerijen",
    "sg:phone":"+31 20 647 2403",
    "sg:postcode":"1182 JA",
    "sg:province":"Noord-Holland",
    "wof:name":"Oude Dorp, Het",
    "wof:placetype":"venue"
},
  "geometry": {"coordinates":[4.84635,52.30262],"type":"Point"}
}