{
  "type": "Feature",
  "properties": {
    "addr:full":"Hoofdstr 135 Sassenheim Zuid-Holland 2171 BA",
    "addr:housenumber":"135",
    "addr:postcode":"sassenheim;2171 ba",
    "iso:country":"NL",
    "sg:address":"Hoofdstr 135",
    "sg:city":"Sassenheim",
    "sg:orig_category":"Honden- En Kattentrimsalons",
    "sg:phone":"+31 252 216 301",
    "sg:postcode":"2171 BA",
    "sg:province":"Zuid-Holland",
    "wof:name":"Bassie",
    "wof:placetype":"venue"
},
  "geometry": {"coordinates":[4.516214,52.222504],"type":"Point"}
}