{
  "type": "Feature",
  "properties": {
    "addr:full":"Heemraadlaan 67 Leiderdorp Zuid-Holland 2352 RG",
    "addr:housenumber":"67",
    "addr:postcode":"2352 rg",
    "addr:street":"Heemraadlaan",
    "iso:country":"NL",
    "sg:address":"Heemraadlaan 67",
    "sg:city":"Leiderdorp",
    "sg:orig_category":"Overheidsdiensten",
    "sg:phone":"+31 71 589 3135",
    "sg:postcode":"2352 RG",
    "sg:province":"Zuid-Holland",
    "wof:name":"Sjelter",
    "wof:placetype":"venue"
},
  "geometry": {"coordinates":[4.5226860046,52.1595726013],"type":"Point"}
}