{
  "type": "Feature",
  "properties": {
    "addr:full":"Meidoornplein 67 Wezep Gelderland 8091 JZ",
    "addr:housenumber":"67",
    "addr:postcode":"8091 jz",
    "addr:street":"Meidoornplein",
    "iso:country":"NL",
    "sg:address":"Meidoornplein 67",
    "sg:city":"Wezep",
    "sg:orig_category":"Drogisterijen",
    "sg:phone":"+31 38 376 1365",
    "sg:postcode":"8091 JZ",
    "sg:province":"Gelderland",
    "wof:name":"Fa. D.A. Drogisterij-Parfumerie Kalf",
    "wof:placetype":"venue"
},
  "geometry": {"coordinates":[6.000822,52.461281],"type":"Point"}
}