{
  "type": "Feature",
  "properties": {
    "addr:full":"Kerkstraat 43 Baarn Utrecht 3741 AJ",
    "addr:housenumber":"43",
    "addr:postcode":"3741 aj",
    "addr:street":"Kerkstraat",
    "iso:country":"NL",
    "sg:address":"Kerkstraat 43",
    "sg:city":"Baarn",
    "sg:orig_category":"Bedrijfs- And Managementsconsultants",
    "sg:phone":"+31 35 543 0200",
    "sg:postcode":"3741 AJ",
    "sg:province":"Utrecht",
    "wof:name":"Ing. E.D. Teekman",
    "wof:placetype":"venue"
},
  "geometry": {"coordinates":[5.312465,52.224945],"type":"Point"}
}