{
  "type": "Feature",
  "properties": {
    "addr:full":"Eendenparkwg 43-9 Ermelo Gelderland 3852 LG",
    "addr:housenumber":"43-9",
    "addr:postcode":"3852 lg",
    "addr:street":"Gelderland",
    "iso:country":"NL",
    "sg:address":"Eendenparkwg 43-9",
    "sg:city":"Ermelo",
    "sg:orig_category":"Loodgieters",
    "sg:phone":"+31 6 27041228",
    "sg:postcode":"3852 LG",
    "sg:province":"Gelderland",
    "wof:name":"Fb Service",
    "wof:placetype":"venue"
},
  "geometry": {"coordinates":[5.638644,52.314739],"type":"Point"}
}