{
  "type": "Feature",
  "properties": {
    "addr:full":"W De Zwygerln 48 S Gravenhage Zuid-Holland 2582 ER",
    "addr:housenumber":"48;gravenhage",
    "addr:postcode":"2582 er",
    "addr:street":"W De Zwygerln;S",
    "iso:country":"NL",
    "sg:address":"W De Zwygerln 48",
    "sg:city":"S Gravenhage",
    "sg:orig_category":"Meubelen",
    "sg:phone":"+31 70 355 3177",
    "sg:postcode":"2582 ER",
    "sg:province":"Zuid-Holland",
    "wof:name":"Living",
    "wof:placetype":"venue"
},
  "geometry": {"coordinates":[4.27852,52.092411],"type":"Point"}
}