{
  "type": "Feature",
  "properties": {
    "iso:country":"NL",
    "sg:address":"Jan Sluiterstraat 73",
    "sg:city":"Volendam",
    "sg:orig_category":"Koeriersdiensten",
    "sg:phone":"+31 299 364 661",
    "sg:postcode":"1132 XW",
    "sg:province":"Noord-Holland",
    "wof:name":"P. Klein",
    "wof:placetype":"venue"
},
  "geometry": {"coordinates":[5.057871,52.498734],"type":"Point"}
}