{
  "type": "Feature",
  "properties": {
    "addr:full":"Koningin Wilhelminaplein 48 Waddinxveen South Holland 2741 EC",
    "addr:housenumber":"48",
    "addr:postcode":"2741 ec",
    "addr:street":"Koningin Wilhelminaplein",
    "iso:country":"NL",
    "sg:address":"Koningin Wilhelminaplein 48",
    "sg:city":"Waddinxveen",
    "sg:orig_category":"Juweliers",
    "sg:phone":"+31 182 612 077",
    "sg:postcode":"2741 EC",
    "sg:province":"South Holland",
    "wof:name":"Juwelier J F Spruijtenburg",
    "wof:placetype":"venue"
},
  "geometry": {"coordinates":[4.653549,52.051628],"type":"Point"}
}