{
  "type": "Feature",
  "properties": {
    "addr:full":"Spyksedk 16 Gorinchem Zuid-Holland 4207 GN",
    "addr:housenumber":"16",
    "addr:postcode":"4207 gn",
    "addr:street":"Spyksedk",
    "iso:country":"NL",
    "sg:address":"Spyksedk 16",
    "sg:city":"Gorinchem",
    "sg:orig_category":"Verhuur Bouwmachines",
    "sg:phone":"+31 183 625 000",
    "sg:postcode":"4207 GN",
    "sg:province":"Zuid-Holland",
    "wof:name":"Klop Verkoop Bv",
    "wof:placetype":"venue"
},
  "geometry": {"coordinates":[4.982365,51.835606],"type":"Point"}
}