{
  "type": "Feature",
  "properties": {
    "addr:full":"Janspln 39A Arnhem Gelderland 6811 GD",
    "addr:housenumber":"39a",
    "addr:postcode":"6811 gd",
    "addr:street":"Janspln",
    "iso:country":"NL",
    "sg:address":"Janspln 39A",
    "sg:city":"Arnhem",
    "sg:orig_category":"Biljartzalen",
    "sg:phone":"+31 26 445 0383",
    "sg:postcode":"6811 GD",
    "sg:province":"Gelderland",
    "wof:name":"Cue Action Arnhem",
    "wof:placetype":"venue"
},
  "geometry": {"coordinates":[5.907587,51.983139],"type":"Point"}
}