{
  "type": "Feature",
  "properties": {
    "addr:full":"Stinzenflora 106 Leeuwarden Provincie Friesland 8935 NN",
    "addr:housenumber":"106",
    "addr:postcode":"8935 nn",
    "addr:street":"Stinzenflora;Provincie Friesland",
    "iso:country":"NL",
    "sg:address":"Stinzenflora 106",
    "sg:city":"Leeuwarden",
    "sg:orig_category":"Fotoreportages",
    "sg:phone":"+31 58 215 9730",
    "sg:postcode":"8935 NN",
    "sg:province":"Provincie Friesland",
    "sg:website":"http://www.simonvanderwoude.nl",
    "wof:name":"Simon V/D Woude, Fotografie",
    "wof:placetype":"venue"
},
  "geometry": {"coordinates":[5.833552,53.189163],"type":"Point"}
}