{
  "type": "Feature",
  "properties": {
    "addr:full":"Pastoor Van Laakstraat 36 Lent Gelderland 6663 CA",
    "addr:housenumber":"36",
    "addr:postcode":"6663 ca",
    "addr:street":"Pastoor Van Laakstraat;Gelderland",
    "iso:country":"NL",
    "sg:address":"Pastoor Van Laakstraat 36",
    "sg:city":"Lent",
    "sg:orig_category":"Kunst And Kunstenaarsbenodigdheden",
    "sg:phone":"+31 24 360 6186",
    "sg:postcode":"6663 CA",
    "sg:province":"Gelderland",
    "wof:name":"S. V.D. Veen",
    "wof:placetype":"venue"
},
  "geometry": {"coordinates":[-77.241432,38.151344],"type":"Point"}
}