{
  "type": "Feature",
  "properties": {
    "addr:full":"Hoofdvaart 134 Dedemsvaart Overijssel 7701 JP",
    "addr:housenumber":"134",
    "addr:postcode":"7701 jp",
    "addr:street":"Hoofdvaart",
    "iso:country":"NL",
    "sg:address":"Hoofdvaart 134",
    "sg:city":"Dedemsvaart",
    "sg:orig_category":"Verzekeringen",
    "sg:phone":"+31 523 613 365",
    "sg:postcode":"7701 JP",
    "sg:province":"Overijssel",
    "wof:name":"Assurantiekantoor Haverkort",
    "wof:placetype":"venue"
},
  "geometry": {"coordinates":[6.441661,52.597588],"type":"Point"}
}