{
  "type": "Feature",
  "properties": {
    "addr:full":"Jekerstr 15 Amsterdam North Holland 1078 LW",
    "addr:housenumber":"15",
    "addr:postcode":"1078 lw",
    "addr:street":"Jekerstr",
    "iso:country":"NL",
    "sg:address":"Jekerstr 15",
    "sg:city":"Amsterdam",
    "sg:orig_category":"Bouwbureaus",
    "sg:phone":"+31 20 676 8071",
    "sg:postcode":"1078 LW",
    "sg:province":"North Holland",
    "wof:name":"Schiering",
    "wof:placetype":"venue"
},
  "geometry": {"coordinates":[4.89892,52.345833],"type":"Point"}
}