{
  "type": "Feature",
  "properties": {
    "iso:country":"NL",
    "sg:address":"Jekerstr 15",
    "sg:city":"Amsterdam",
    "sg:orig_category":"Bouwbureaus",
    "sg:phone":"+31 20 676 8071",
    "sg:postcode":"1078 LW",
    "sg:province":"North Holland",
    "wof:name":"Schiering",
    "wof:placetype":"venue"
},
  "geometry": {"coordinates":[4.89892,52.345833],"type":"Point"}
}