{
  "type": "Feature",
  "properties": {
    "addr:full":"Gildelaan 57 Medemblik North Holland 1671 LZ",
    "addr:housenumber":"57",
    "addr:postcode":"1671 lz",
    "addr:street":"Gildelaan",
    "iso:country":"NL",
    "sg:address":"Gildelaan 57",
    "sg:city":"Medemblik",
    "sg:orig_category":"Boekhouders",
    "sg:phone":"+31 227 547 630",
    "sg:postcode":"1671 LZ",
    "sg:province":"North Holland",
    "wof:name":"Gildehuis Administraties",
    "wof:placetype":"venue"
},
  "geometry": {"coordinates":[5.108536,52.760841],"type":"Point"}
}