{
  "type": "Feature",
  "properties": {
    "addr:full":"Calandwg 44 Arnemuiden Zeeland 4341 RA",
    "addr:housenumber":"44",
    "addr:postcode":"4341 ra",
    "addr:street":"Calandwg",
    "iso:country":"NL",
    "sg:address":"Calandwg 44",
    "sg:city":"Arnemuiden",
    "sg:orig_category":"Luchthavens En Vliegvelden",
    "sg:phone":"+31 113 612 910",
    "sg:postcode":"4341 RA",
    "sg:province":"Zeeland",
    "sg:website":"http://www.skydive-zeeland.nl",
    "wof:name":"Paracentrum Zeeland Bv",
    "wof:placetype":"venue"
},
  "geometry": {"coordinates":[3.74028,51.513302],"type":"Point"}
}