{
  "type": "Feature",
  "properties": {
    "addr:full":"Kinderdijk 50 Middelburg Zeeland 4331 HH",
    "addr:housenumber":"50",
    "addr:postcode":"4331 hh",
    "addr:street":"Kinderdijk",
    "iso:country":"NL",
    "sg:address":"Kinderdijk 50",
    "sg:city":"Middelburg",
    "sg:orig_category":"Makelaars In Onroerend Goed",
    "sg:phone":"+31 118 626 138",
    "sg:postcode":"4331 HH",
    "sg:province":"Zeeland",
    "wof:name":"G.N.A. Roovers Beedigd Taxateur & Makelaar",
    "wof:placetype":"venue"
},
  "geometry": {"coordinates":[3.621044,51.499363],"type":"Point"}
}