{
  "type": "Feature",
  "properties": {
    "iso:country":"NL",
    "sg:address":"T Boonrak 7",
    "sg:city":"Valkenburg Zh",
    "sg:orig_category":"Bloemen And Planten Gh",
    "sg:phone":"+31 71 407 3036",
    "sg:postcode":"2235 ED",
    "sg:province":"Zuid-Holland",
    "wof:name":"Fa A. Van Dijk & Zn",
    "wof:placetype":"venue"
},
  "geometry": {"coordinates":[4.436646,52.179756],"type":"Point"}
}