{
  "type": "Feature",
  "properties": {
    "addr:full":"W De Withstr 18 Groningen Groningen 9726 ED",
    "addr:housenumber":"18",
    "addr:postcode":"9726 ed",
    "addr:street":"W De Withstr",
    "iso:country":"NL",
    "sg:address":"W De Withstr 18",
    "sg:city":"Groningen",
    "sg:orig_category":"Kinderopvang",
    "sg:phone":"+31 50 318 8071",
    "sg:postcode":"9726 ED",
    "sg:province":"Groningen",
    "wof:name":"Dolfijn",
    "wof:placetype":"venue"
},
  "geometry": {"coordinates":[6.554087,53.213135],"type":"Point"}
}