{
  "type": "Feature",
  "properties": {
    "addr:full":"Waverstr 30-32 Amsterdam North Holland 1079 VM",
    "addr:housenumber":"30-32",
    "addr:postcode":"1079 vm",
    "iso:country":"NL",
    "sg:address":"Waverstr 30-32",
    "sg:city":"Amsterdam",
    "sg:orig_category":"Oldtimers",
    "sg:phone":"+31 20 644 5060",
    "sg:postcode":"1079 VM",
    "sg:province":"North Holland",
    "wof:name":"Foley",
    "wof:placetype":"venue"
},
  "geometry": {"coordinates":[4.909941,52.346272],"type":"Point"}
}