{
  "type": "Feature",
  "properties": {
    "iso:country":"NL",
    "sg:address":"Sassenheimstr 63-2H",
    "sg:city":"Amsterdam",
    "sg:orig_category":"Vertalers",
    "sg:phone":"+31 6 15422806",
    "sg:postcode":"1059 BD",
    "sg:province":"Noord-Holland",
    "wof:name":"Magnificent Media",
    "wof:placetype":"venue"
},
  "geometry": {"coordinates":[4.847097,52.348549],"type":"Point"}
}