{
  "type": "Feature",
  "properties": {
    "addr:full":"Schorpioen 20 Lisse Zuid-Holland 2163 BS",
    "addr:housenumber":"20",
    "addr:postcode":"2163 bs",
    "addr:street":"Schorpioen",
    "iso:country":"NL",
    "sg:address":"Schorpioen 20",
    "sg:city":"Lisse",
    "sg:orig_category":"Webdesign Bureaus",
    "sg:phone":"+31 252 370 926",
    "sg:postcode":"2163 BS",
    "sg:province":"Zuid-Holland",
    "sg:website":"http://www.bmp.nl",
    "wof:name":"Brama",
    "wof:placetype":"venue"
},
  "geometry": {"coordinates":[4.5661787987,52.2649002075],"type":"Point"}
}