{
  "type": "Feature",
  "properties": {
    "addr:full":"Mauritslaan 17 Geleen Limburg 6161 HN",
    "addr:housenumber":"17",
    "addr:postcode":"6161 hn",
    "addr:street":"Mauritslaan",
    "iso:country":"NL",
    "sg:address":"Mauritslaan 17",
    "sg:city":"Geleen",
    "sg:orig_category":"Artsen And Specialisten",
    "sg:phone":"+31 46 474 3717",
    "sg:postcode":"6161 HN",
    "sg:province":"Limburg",
    "wof:name":"Huisartspraktijk T. Van Westrik",
    "wof:placetype":"venue"
},
  "geometry": {"coordinates":[5.825766,50.968082],"type":"Point"}
}