{
  "type": "Feature",
  "properties": {
    "addr:full":"Oppad 30 Loosdrecht Noord-Holland 1231 PJ",
    "addr:housenumber":"30",
    "addr:postcode":"1231 pj",
    "addr:street":"Oppad",
    "iso:country":"NL",
    "sg:address":"Oppad 30",
    "sg:city":"Loosdrecht",
    "sg:orig_category":"Administratie- En Boekhoudkantoren",
    "sg:phone":"+31 35 582 8700",
    "sg:postcode":"1231 PJ",
    "sg:province":"Noord-Holland",
    "wof:name":"Marcibo",
    "wof:placetype":"venue"
},
  "geometry": {"coordinates":[5.086496,52.207909],"type":"Point"}
}