{
  "type": "Feature",
  "properties": {
    "iso:country":"NL",
    "sg:address":"Gildenweg 9",
    "sg:city":"Woerden",
    "sg:orig_category":"Zuivelproducten And Spijsoli?n Gh",
    "sg:phone":"+31 348 416 638",
    "sg:postcode":"3449 HT",
    "sg:province":"Utrecht",
    "wof:name":"Bv Keurmeester Natuurkaas",
    "wof:placetype":"venue"
},
  "geometry": {"coordinates":[4.858077,52.083694],"type":"Point"}
}