{
  "type": "Feature",
  "properties": {
    "addr:full":"Padlaan 13 Krommenie Noord-Holland 1561 ZA",
    "addr:housenumber":"13",
    "addr:postcode":"1561",
    "addr:street":"Padlaan",
    "iso:country":"NL",
    "sg:address":"Padlaan 13",
    "sg:city":"Krommenie",
    "sg:orig_category":"Artsen And Specialisten",
    "sg:phone":"+31 75 628 2391",
    "sg:postcode":"1561 ZA",
    "sg:province":"Noord-Holland",
    "wof:name":"J.H. Walburg",
    "wof:placetype":"venue"
},
  "geometry": {"coordinates":[4.770324,52.498638],"type":"Point"}
}