{
  "type": "Feature",
  "properties": {
    "addr:full":"Maasdk 39 S Gravenzande South Holland 2691 PA",
    "addr:housenumber":"39",
    "addr:postcode":"2691 pa",
    "addr:street":"Maasdk;S Gravenzande",
    "iso:country":"NL",
    "sg:address":"Maasdk 39",
    "sg:city":"S Gravenzande",
    "sg:orig_category":"Bloemen En Planten - Decoratie",
    "sg:phone":"+31 174 418 735",
    "sg:postcode":"2691 PA",
    "sg:province":"South Holland",
    "wof:name":"Spronsen, M J Van",
    "wof:placetype":"venue"
},
  "geometry": {"coordinates":[4.158625,51.988758],"type":"Point"}
}