{
  "type": "Feature",
  "properties": {
    "addr:full":"Langstr 37 Tricht Gelderland 4196 JA",
    "addr:housenumber":"37",
    "addr:postcode":"4196 ja",
    "addr:street":"Langstr;Gelderland",
    "iso:country":"NL",
    "sg:address":"Langstr 37",
    "sg:city":"Tricht",
    "sg:orig_category":"Pottenbakkerijen",
    "sg:phone":"+31 345 573 579",
    "sg:postcode":"4196 JA",
    "sg:province":"Gelderland",
    "wof:name":"Craquel\u00e9",
    "wof:placetype":"venue"
},
  "geometry": {"coordinates":[5.259933,51.898495],"type":"Point"}
}