{
  "type": "Feature",
  "properties": {
    "addr:full":"Victoriestr 33 Waalwijk North Brabant 5142 RG",
    "addr:housenumber":"33",
    "addr:postcode":"5142 rg",
    "addr:street":"Victoriestr",
    "iso:country":"NL",
    "sg:address":"Victoriestr 33",
    "sg:city":"Waalwijk",
    "sg:orig_category":"Kappers",
    "sg:phone":"+31 416 334 772",
    "sg:postcode":"5142 RG",
    "sg:province":"North Brabant",
    "wof:name":"Heesbeen",
    "wof:placetype":"venue"
},
  "geometry": {"coordinates":[5.0728549957,51.6871643066],"type":"Point"}
}