{
  "type": "Feature",
  "properties": {
    "addr:full":"De Genestetweg 25 Bloemendaal Noord-Holland 2061 VA",
    "addr:housenumber":"25",
    "addr:postcode":"2061",
    "addr:street":"De Genestetweg",
    "iso:country":"NL",
    "sg:address":"De Genestetweg 25",
    "sg:city":"Bloemendaal",
    "sg:orig_category":"Wasserettes And Stomerijen",
    "sg:phone":"+31 23 527 4497",
    "sg:postcode":"2061 VA",
    "sg:province":"Noord-Holland",
    "wof:name":"Wasserette- Stomerette-Bloemendaal",
    "wof:placetype":"venue"
},
  "geometry": {"coordinates":[4.6209611893,52.4052963257],"type":"Point"}
}