{
  "type": "Feature",
  "properties": {
    "addr:full":"Jacob Marisstraat 216 'S Gravenhage South Holland 2526 AZ",
    "addr:housenumber":"216 '",
    "addr:postcode":"2526 az",
    "addr:street":"Jacob Marisstraat",
    "iso:country":"NL",
    "sg:address":"Jacob Marisstraat 216",
    "sg:city":"'S Gravenhage",
    "sg:orig_category":"Werving And Selectie Van Tijdelijk Personeel And Uitzendkantoren",
    "sg:phone":"+31 70 380 2981",
    "sg:postcode":"2526 AZ",
    "sg:province":"South Holland",
    "wof:name":"Oznavruz/Kavak",
    "wof:placetype":"venue"
},
  "geometry": {"coordinates":[4.3113670349,52.064289093],"type":"Point"}
}