{
  "type": "Feature",
  "properties": {
    "addr:full":"Industriewg 110 Rotterdam Zuid-Holland 3044 AT",
    "addr:housenumber":"110",
    "addr:postcode":"3044",
    "iso:country":"NL",
    "sg:address":"Industriewg 110",
    "sg:city":"Rotterdam",
    "sg:classifiers":[
        {
            "category":"Home & Garden",
            "subcategory":"Hardware",
            "type":"Retail Goods"
        }
    ],
    "sg:phone":"+31 10 415 2788",
    "sg:postcode":"3044 AT",
    "sg:province":"Zuid-Holland",
    "sg:tags":[
        "machine",
        "-",
        "metaalbewerking"
    ],
    "wof:name":"Esmeijer Bv",
    "wof:placetype":"venue"
},
  "geometry": {"coordinates":[4.419948,51.92902],"type":"Point"}
}