{
  "type": "Feature",
  "properties": {
    "addr:full":"Nobelstr 12 Heerlen Limburg 6411 EM",
    "addr:housenumber":"12",
    "addr:postcode":"6411 em",
    "addr:street":"Nobelstr",
    "iso:country":"NL",
    "sg:address":"Nobelstr 12",
    "sg:city":"Heerlen",
    "sg:orig_category":"Orthopedisch Schoeisel",
    "sg:phone":"+31 45 574 2071",
    "sg:postcode":"6411 EM",
    "sg:province":"Limburg",
    "wof:name":"Pascal Pouwels",
    "wof:placetype":"venue"
},
  "geometry": {"coordinates":[5.979804039,50.8856048584],"type":"Point"}
}