{
  "type": "Feature",
  "properties": {
    "addr:full":"Sjalotpad 3 Almere Flevoland 1313 JC",
    "addr:housenumber":"3",
    "addr:postcode":"1313 jc",
    "addr:street":"Sjalotpad;Flevoland",
    "iso:country":"NL",
    "sg:address":"Sjalotpad 3",
    "sg:city":"Almere",
    "sg:orig_category":"Schilders",
    "sg:phone":"+31 36 530 2111",
    "sg:postcode":"1313 JC",
    "sg:province":"Flevoland",
    "wof:name":"Almegro Schildersbedrijf",
    "wof:placetype":"venue"
},
  "geometry": {"coordinates":[5.192917,52.38084],"type":"Point"}
}