{
  "type": "Feature",
  "properties": {
    "addr:full":"Jaap Edenweg 10 'S-Gravenhage South Holland 2544 NL",
    "addr:housenumber":"10",
    "addr:postcode":"2544 nl",
    "addr:street":"Jaap Edenweg",
    "iso:country":"NL",
    "sg:address":"Jaap Edenweg 10",
    "sg:city":"'S-Gravenhage",
    "sg:classifiers":[
        {
            "category":"Arena",
            "subcategory":"Auto Racetrack",
            "type":"Entertainment"
        }
    ],
    "sg:phone":"+31 70 359 8564",
    "sg:postcode":"2544 NL",
    "sg:province":"South Holland",
    "sg:tags":[
        "en",
        "racebanen",
        "kart-"
    ],
    "sg:website":"http://www.coronel-enterteinment.nl",
    "wof:name":"Coronel",
    "wof:placetype":"venue"
},
  "geometry": {"coordinates":[4.24084,52.038979],"type":"Point"}
}