{
  "type": "Feature",
  "properties": {
    "iso:country":"NL",
    "sg:address":"Markerkant 1011",
    "sg:city":"Almere",
    "sg:orig_category":"Meubelreparatie And -Restauratie",
    "sg:phone":"+31 36 533 4976",
    "sg:postcode":"1316 AA",
    "sg:province":"NL.",
    "wof:name":"Stoffeerderij Hermes",
    "wof:placetype":"venue"
},
  "geometry": {"coordinates":[5.218901,52.386593],"type":"Point"}
}