{
  "type": "Feature",
  "properties": {
    "iso:country":"NL",
    "sg:address":"Vd Wateringeln 276",
    "sg:city":"Voorburg",
    "sg:orig_category":"Autorijscholen",
    "sg:phone":"+31 70 385 8090",
    "sg:postcode":"2274 CP",
    "sg:province":"Zuid-Holland",
    "wof:name":"Intercity",
    "wof:placetype":"venue"
},
  "geometry": {"coordinates":[4.345693,52.078217],"type":"Point"}
}