{
  "type": "Feature",
  "properties": {
    "addr:full":"Goilberdingerdk 32 Culemborg Gelderland 4105 LB",
    "addr:housenumber":"32",
    "addr:postcode":"4105 lb",
    "addr:street":"Goilberdingerdk;Gelderland",
    "iso:country":"NL",
    "sg:address":"Goilberdingerdk 32",
    "sg:city":"Culemborg",
    "sg:classifiers":[
        {
            "category":"Retail",
            "subcategory":"Auto Repair",
            "type":"Services"
        }
    ],
    "sg:phone":"+31 345 518 580",
    "sg:postcode":"4105 LB",
    "sg:province":"Gelderland",
    "sg:tags":[
        "garage"
    ],
    "wof:name":"Wammes, H",
    "wof:placetype":"venue"
},
  "geometry": {"coordinates":[5.198921,51.958134],"type":"Point"}
}