{
  "type": "Feature",
  "properties": {
    "addr:full":"Jagerskamp 80 Wageningen Gelderland 6706 EP",
    "addr:housenumber":"80",
    "addr:postcode":"6706 ep",
    "addr:street":"Jagerskamp;Gelderland",
    "iso:country":"NL",
    "sg:address":"Jagerskamp 80",
    "sg:city":"Wageningen",
    "sg:orig_category":"Gelegenheidskleding",
    "sg:phone":"+31 317 416 632",
    "sg:postcode":"6706 EP",
    "sg:province":"Gelderland",
    "wof:name":"Riet Driever",
    "wof:placetype":"venue"
},
  "geometry": {"coordinates":[5.679364,51.975716],"type":"Point"}
}