{
  "type": "Feature",
  "properties": {
    "addr:full":"Vd Veldeplnts 9 Soest Utrecht 3764 BP",
    "addr:housenumber":"9",
    "addr:postcode":"3764 bp",
    "addr:street":"Soest",
    "iso:country":"NL",
    "sg:address":"Vd Veldeplnts 9",
    "sg:city":"Soest",
    "sg:orig_category":"Voetbalverenigingen",
    "sg:phone":"+31 6 28272793",
    "sg:postcode":"3764 BP",
    "sg:province":"Utrecht",
    "wof:name":"Firtina'93",
    "wof:placetype":"venue"
},
  "geometry": {"coordinates":[5.300385,52.184044],"type":"Point"}
}