{
  "type": "Feature",
  "properties": {
    "addr:full":"Bergambachtstraat 2 Rotterdam Zuid-Holland 3079 DA",
    "addr:housenumber":"2",
    "addr:postcode":"3079 da",
    "addr:street":"Bergambachtstraat",
    "iso:country":"NL",
    "sg:address":"Bergambachtstraat 2",
    "sg:city":"Rotterdam",
    "sg:orig_category":"Drukkerijen And Copyshops",
    "sg:phone":"+31 10 482 9044",
    "sg:postcode":"3079 DA",
    "sg:province":"Zuid-Holland",
    "wof:name":"Drukkerij Van Driel Bv",
    "wof:placetype":"venue"
},
  "geometry": {"coordinates":[4.541257,51.87402],"type":"Point"}
}