{
  "type": "Feature",
  "properties": {
    "addr:full":"Johannes Xxiii Singel 44 Heerlen Limburg 6416 GH",
    "addr:housenumber":"44",
    "addr:postcode":"6416 gh",
    "addr:street":"Johannes Xxiii Singel",
    "iso:country":"NL",
    "sg:address":"Johannes Xxiii Singel 44",
    "sg:city":"Heerlen",
    "sg:orig_category":"Advocaten And Juridische Adviseurs",
    "sg:phone":"+31 45 542 1188",
    "sg:postcode":"6416 GH",
    "sg:province":"Limburg",
    "wof:name":"Advocatenkantoor Montfort-Schoutissen",
    "wof:placetype":"venue"
},
  "geometry": {"coordinates":[5.995878,50.878658],"type":"Point"}
}