{
  "type": "Feature",
  "properties": {
    "addr:full":"Smyrnastraat 5 Deventer Overijssel 7413 BA",
    "addr:housenumber":"5",
    "addr:postcode":"7413 ba",
    "addr:street":"Smyrnastraat",
    "iso:country":"NL",
    "sg:address":"Smyrnastraat 5",
    "sg:city":"Deventer",
    "sg:orig_category":"Boekenuitgeverijen",
    "sg:phone":"+31 570 678 900",
    "sg:postcode":"7413 BA",
    "sg:province":"Overijssel",
    "wof:name":"Ankh Hermes Bv",
    "wof:placetype":"venue"
},
  "geometry": {"coordinates":[6.162779,52.261116],"type":"Point"}
}