{
  "type": "Feature",
  "properties": {
    "addr:full":"Biezenstraat 30 Wouw Noord-Brabant 4724 SK",
    "addr:housenumber":"30",
    "addr:street":"Biezenstraat;4724",
    "iso:country":"NL",
    "sg:address":"Biezenstraat 30",
    "sg:city":"Wouw",
    "sg:orig_category":"Autokeuringen",
    "sg:phone":"+31 165 302 556",
    "sg:postcode":"4724 SK",
    "sg:province":"Noord-Brabant",
    "wof:name":"L.P.M. Koolen",
    "wof:placetype":"venue"
},
  "geometry": {"coordinates":[4.407295,51.547516],"type":"Point"}
}