{
  "type": "Feature",
  "properties": {
    "addr:full":"Don Boscostr 4 Eindhoven Noord-Brabant 5611 KW",
    "addr:housenumber":"4",
    "addr:postcode":"5611 kw",
    "iso:country":"NL",
    "sg:address":"Don Boscostr 4",
    "sg:city":"Eindhoven",
    "sg:orig_category":"Gehandicapten - Hulpmiddelen",
    "sg:phone":"+31 40 238 5900",
    "sg:postcode":"5611 KW",
    "sg:province":"Noord-Brabant",
    "wof:name":"Unit Voorzieningen Gehandicapten",
    "wof:placetype":"venue"
},
  "geometry": {"coordinates":[5.47651,51.434593],"type":"Point"}
}