{
  "type": "Feature",
  "properties": {
    "iso:country":"NL",
    "sg:address":"Polstr 35",
    "sg:city":"Didam",
    "sg:orig_category":"Adviesbureaus Werktuigbouwkunde",
    "sg:phone":"+31 316 223 335",
    "sg:postcode":"6942 VK",
    "sg:province":"Gelderland",
    "wof:name":"Acr",
    "wof:placetype":"venue"
},
  "geometry": {"coordinates":[6.131848,51.945316],"type":"Point"}
}