{
  "type": "Feature",
  "properties": {
    "iso:country":"NL",
    "sg:address":"L Marktstr 11",
    "sg:city":"Leeuwarden",
    "sg:orig_category":"Pensioenfondsen",
    "sg:phone":"+31 58 213 4069",
    "sg:postcode":"8911 AD",
    "sg:province":"Friesland",
    "wof:name":"Vov, Sticht",
    "wof:placetype":"venue"
},
  "geometry": {"coordinates":[5.789978,53.197575],"type":"Point"}
}