{
  "type": "Feature",
  "properties": {
    "iso:country":"NL",
    "sg:address":"Eikenln 263",
    "sg:city":"Alphen Aan Den Ryn",
    "sg:orig_category":"Organisatiebureaus",
    "sg:phone":"+31 172 419 689",
    "sg:postcode":"2404 BP",
    "sg:province":"Zuid-Holland",
    "sg:website":"http://www.bijeen.net",
    "wof:name":"Bijeen",
    "wof:placetype":"venue"
},
  "geometry": {"coordinates":[4.6589207649,52.1271896362],"type":"Point"}
}