{
  "type": "Feature",
  "properties": {
    "addr:full":"Zylstr 22 Haarlem Noord-Holland 2011 TN",
    "addr:housenumber":"22",
    "addr:postcode":"2011",
    "addr:street":"Zylstr",
    "iso:country":"NL",
    "sg:address":"Zylstr 22",
    "sg:city":"Haarlem",
    "sg:orig_category":"Honden- En Kattentrimsalons",
    "sg:phone":"+31 23 531 5425",
    "sg:postcode":"2011 TN",
    "sg:province":"Noord-Holland",
    "wof:name":"Monique",
    "wof:placetype":"venue"
},
  "geometry": {"coordinates":[4.642253,52.380562],"type":"Point"}
}