{
  "type": "Feature",
  "properties": {
    "iso:country":"NL",
    "sg:address":"Scholtenswg 37",
    "sg:city":"Wesepe",
    "sg:orig_category":"Postzegels",
    "sg:phone":"+31 570 532 285",
    "sg:postcode":"8124 AG",
    "sg:province":"Overijssel",
    "wof:name":"World Stamp Centre Bv",
    "wof:placetype":"venue"
},
  "geometry": {"coordinates":[6.215427,52.330574],"type":"Point"}
}