{
  "type": "Feature",
  "properties": {
    "iso:country":"NL",
    "sg:address":"Vermeerstr 38",
    "sg:city":"Bleiswyk",
    "sg:orig_category":"Telecommunicatie - Apparatuur",
    "sg:phone":"+31 10 521 9378",
    "sg:postcode":"2665 XH",
    "sg:province":"Zuid-Holland",
    "wof:name":"Bredeborg",
    "wof:placetype":"venue"
},
  "geometry": {"coordinates":[4.526623,52.010899],"type":"Point"}
}