{
  "type": "Feature",
  "properties": {
    "addr:full":"Heuvel Galerie 185 Eindhoven Noord-Brabant 5611 DK",
    "addr:housenumber":"185",
    "addr:postcode":"5611 dk",
    "addr:street":"Heuvel Galerie",
    "iso:country":"NL",
    "sg:address":"Heuvel Galerie 185",
    "sg:city":"Eindhoven",
    "sg:orig_category":"Verlichting",
    "sg:phone":"+31 40 296 1458",
    "sg:postcode":"5611 DK",
    "sg:province":"Noord-Brabant",
    "wof:name":"Lampenier",
    "wof:placetype":"venue"
},
  "geometry": {"coordinates":[5.480391,51.438828],"type":"Point"}
}