{
  "type": "Feature",
  "properties": {
    "addr:full":"Gerard Dousingel 106 Papendrecht Zuid-Holland 3351 JJ",
    "addr:housenumber":"106",
    "addr:postcode":"3351 jj",
    "addr:street":"Gerard Dousingel",
    "iso:country":"NL",
    "sg:address":"Gerard Dousingel 106",
    "sg:city":"Papendrecht",
    "sg:orig_category":"Fitnesscentra",
    "sg:phone":"+31 78 641 1064",
    "sg:postcode":"3351 JJ",
    "sg:province":"Zuid-Holland",
    "wof:name":"Lahey Budo Sport",
    "wof:placetype":"venue"
},
  "geometry": {"coordinates":[4.686589,51.836906],"type":"Point"}
}