{
  "type": "Feature",
  "properties": {
    "iso:country":"NL",
    "sg:address":"Gerard Dousingel 106",
    "sg:city":"Papendrecht",
    "sg:orig_category":"Fitnesscentra",
    "sg:phone":"+31 78 641 1064",
    "sg:postcode":"3351 JJ",
    "sg:province":"Zuid-Holland",
    "wof:name":"Lahey Budo Sport",
    "wof:placetype":"venue"
},
  "geometry": {"coordinates":[4.686589,51.836906],"type":"Point"}
}