{
  "type": "Feature",
  "properties": {
    "addr:full":"Kerkstr 29 Hattem Gelderland 8051 GK",
    "addr:housenumber":"29",
    "addr:postcode":"8051 gk",
    "addr:street":"Kerkstr;Gelderland",
    "iso:country":"NL",
    "sg:address":"Kerkstr 29",
    "sg:city":"Hattem",
    "sg:orig_category":"Huishoudelijke Apparaten En Artikelen",
    "sg:phone":"+31 38 444 8639",
    "sg:postcode":"8051 GK",
    "sg:province":"Gelderland",
    "wof:name":"Blokker Bv",
    "wof:placetype":"venue"
},
  "geometry": {"coordinates":[6.067876,52.474621],"type":"Point"}
}