{
  "type": "Feature",
  "properties": {
    "iso:country":"NL",
    "sg:address":"Koningsbergen 28",
    "sg:city":"Wormer",
    "sg:orig_category":"Keukens",
    "sg:phone":"+31 75 642 5198",
    "sg:postcode":"1531 RB",
    "sg:province":"Noord-Holland",
    "wof:name":"Lohuizen, T Van",
    "wof:placetype":"venue"
},
  "geometry": {"coordinates":[4.805471,52.492741],"type":"Point"}
}