{
  "type": "Feature",
  "properties": {
    "addr:full":"Pieter Kiesstraat 28 Haarlem Noord-Holland 2013 BJ",
    "addr:housenumber":"28",
    "addr:postcode":"2013 bj",
    "addr:street":"Pieter Kiesstraat",
    "iso:country":"NL",
    "sg:address":"Pieter Kiesstraat 28",
    "sg:city":"Haarlem",
    "sg:orig_category":"Zuivelproducten",
    "sg:phone":"+31 23 531 4526",
    "sg:postcode":"2013 BJ",
    "sg:province":"Noord-Holland",
    "wof:name":"Vof W.G. Noom",
    "wof:placetype":"venue"
},
  "geometry": {"coordinates":[4.627601,52.385567],"type":"Point"}
}