{
  "type": "Feature",
  "properties": {
    "iso:country":"NL",
    "sg:address":"Achterste Loo 4",
    "sg:city":"Bergeyk",
    "sg:orig_category":"Levende Dieren Gh",
    "sg:phone":"+31 497 572 168",
    "sg:postcode":"5571 TA",
    "sg:province":"Noord-Brabant",
    "wof:name":"Varkenshandel Gebrs Vervest Bv",
    "wof:placetype":"venue"
},
  "geometry": {"coordinates":[5.344223,51.308426],"type":"Point"}
}