{
  "type": "Feature",
  "properties": {
    "iso:country":"NL",
    "sg:address":"Meiveldpad 55",
    "sg:city":"Middelburg",
    "sg:orig_category":"Recreatie",
    "sg:phone":"+31 118 627 142",
    "sg:postcode":"4336 XW",
    "sg:province":"Zeeland",
    "wof:name":"Klepperhoeve, De",
    "wof:placetype":"venue"
},
  "geometry": {"coordinates":[3.620948,51.487099],"type":"Point"}
}