{
  "type": "Feature",
  "properties": {
    "addr:full":"Gerdina S Hof 65 Geldermalsen Gelderland 4191 MX",
    "addr:housenumber":"65",
    "addr:postcode":"4191 mx",
    "addr:street":"Hof;Gelderland",
    "iso:country":"NL",
    "sg:address":"Gerdina S Hof 65",
    "sg:city":"Geldermalsen",
    "sg:orig_category":"Metaalbewerking",
    "sg:phone":"+31 345 576 655",
    "sg:postcode":"4191 MX",
    "sg:province":"Gelderland",
    "wof:name":"Keijzer, R B De",
    "wof:placetype":"venue"
},
  "geometry": {"coordinates":[5.299271,51.874374],"type":"Point"}
}