{
  "type": "Feature",
  "properties": {
    "addr:full":"Ged Vaart 24 Surhuisterveen Friesland 9231 AV",
    "addr:housenumber":"24",
    "addr:postcode":"9231 av",
    "addr:street":"Vaart",
    "iso:country":"NL",
    "sg:address":"Ged Vaart 24",
    "sg:city":"Surhuisterveen",
    "sg:orig_category":"Kegelbanen",
    "sg:phone":"+31 512 361 780",
    "sg:postcode":"9231 AV",
    "sg:province":"Friesland",
    "wof:name":"Dikke Draai Bv, De",
    "wof:placetype":"venue"
},
  "geometry": {"coordinates":[6.160756,53.180912],"type":"Point"}
}