{
  "type": "Feature",
  "properties": {
    "addr:full":"Johan Berkstraat 35 Zuid-Beijerland Zuid-Holland 3284 XD",
    "addr:housenumber":"35",
    "addr:postcode":"3284 xd",
    "addr:street":"Johan Berkstraat",
    "iso:country":"NL",
    "sg:address":"Johan Berkstraat 35",
    "sg:city":"Zuid-Beijerland",
    "sg:classifiers":[
        {
            "category":"Education",
            "subcategory":"Preschool",
            "type":"Public Place"
        }
    ],
    "sg:phone":"+31 186 661 343",
    "sg:postcode":"3284 XD",
    "sg:province":"Zuid-Holland",
    "sg:tags":[
        "kleuteronderwijs",
        "basis-"
    ],
    "wof:name":"Christelijke Basisschool De Regenboog",
    "wof:placetype":"venue"
},
  "geometry": {"coordinates":[4.368255,51.752693],"type":"Point"}
}