{
  "type": "Feature",
  "properties": {
    "addr:full":"Kaatsbaan 33 Maarssen Utrecht 3601 EB",
    "addr:housenumber":"33",
    "addr:postcode":"3601 eb",
    "addr:street":"Kaatsbaan",
    "iso:country":"NL",
    "sg:address":"Kaatsbaan 33",
    "sg:city":"Maarssen",
    "sg:orig_category":"Beautyfarms And Sauna'S",
    "sg:phone":"+31 346 568 408",
    "sg:postcode":"3601 EB",
    "sg:province":"Utrecht",
    "wof:name":"Zonnestudio Maarssen",
    "wof:placetype":"venue"
},
  "geometry": {"coordinates":[5.039952,52.141724],"type":"Point"}
}