{
  "type": "Feature",
  "properties": {
    "addr:full":"Postbus 8025 Amstelveen North Holland 1180 LA",
    "addr:housenumber":"8025",
    "addr:postcode":"1180 la",
    "addr:street":"Postbus",
    "iso:country":"NL",
    "sg:address":"Postbus 8025",
    "sg:city":"Amstelveen",
    "sg:orig_category":"Makelaars En Adviseurs Onroerende Goederen",
    "sg:phone":"+31 20 645 1480",
    "sg:postcode":"1180 LA",
    "sg:province":"North Holland",
    "wof:name":"Winners",
    "wof:placetype":"venue"
},
  "geometry": {"coordinates":[4.856945,52.303444],"type":"Point"}
}