{
  "type": "Feature",
  "properties": {
    "addr:full":"Gr Floris 4 Wg 4 Lopik Utrecht 3411 NC",
    "addr:housenumber":"4;4",
    "addr:postcode":"3411 nc",
    "addr:street":"Gr Floris;Wg",
    "iso:country":"NL",
    "sg:address":"Gr Floris 4 Wg 4",
    "sg:city":"Lopik",
    "sg:orig_category":"Goud En Zilver",
    "sg:phone":"+31 182 385 543",
    "sg:postcode":"3411 NC",
    "sg:province":"Utrecht",
    "wof:name":"Blanken, Marianne",
    "wof:placetype":"venue"
},
  "geometry": {"coordinates":[4.883535,51.941357],"type":"Point"}
}