{
  "type": "Feature",
  "properties": {
    "addr:full":"Grensweg 1A Ommen Overijssel 7731 SP",
    "addr:housenumber":"1a",
    "addr:postcode":"7731 sp",
    "addr:street":"Grensweg",
    "iso:country":"NL",
    "sg:address":"Grensweg 1A",
    "sg:city":"Ommen",
    "sg:orig_category":"Autokeuringen",
    "sg:phone":"+31 529 450 984",
    "sg:postcode":"7731 SP",
    "sg:province":"Overijssel",
    "wof:name":"N.J. Oosterhuis",
    "wof:placetype":"venue"
},
  "geometry": {"coordinates":[6.431554,52.542244],"type":"Point"}
}