{
  "type": "Feature",
  "properties": {
    "addr:full":"Keizerstr 2 Gouda Zuid-Holland 2801 NL",
    "addr:housenumber":"2",
    "addr:postcode":"2801 nl",
    "addr:street":"Keizerstr",
    "iso:country":"NL",
    "sg:address":"Keizerstr 2",
    "sg:city":"Gouda",
    "sg:orig_category":"Adviesbureaus Bouwkunde",
    "sg:phone":"+31 182 581 740",
    "sg:postcode":"2801 NL",
    "sg:province":"Zuid-Holland",
    "wof:name":"Verwey",
    "wof:placetype":"venue"
},
  "geometry": {"coordinates":[4.708421,52.009266],"type":"Point"}
}