{
  "type": "Feature",
  "properties": {
    "addr:full":"Beltstraat 80 Hippolytushoef North Holland 1777 HD",
    "addr:housenumber":"80",
    "addr:postcode":"1777 hd",
    "addr:street":"Beltstraat",
    "iso:country":"NL",
    "sg:address":"Beltstraat 80",
    "sg:city":"Hippolytushoef",
    "sg:classifiers":[
        {
            "category":"Fast Food",
            "type":"Food & Drink"
        }
    ],
    "sg:phone":"+31 227 591 243",
    "sg:postcode":"1777 HD",
    "sg:province":"North Holland",
    "sg:tags":[
        "afhaal",
        "restaurant"
    ],
    "wof:name":"Hip Snacks",
    "wof:placetype":"venue"
},
  "geometry": {"coordinates":[4.9555,52.905182],"type":"Point"}
}