{
  "type": "Feature",
  "properties": {
    "addr:full":"Zwartemeerweg 14 Ens Flevoland 8307 RP",
    "addr:housenumber":"14",
    "addr:postcode":"8307",
    "addr:street":"Zwartemeerweg;Flevoland",
    "iso:country":"NL",
    "sg:address":"Zwartemeerweg 14",
    "sg:city":"Ens",
    "sg:orig_category":"Bloemen And Planten",
    "sg:phone":"+31 527 253 305",
    "sg:postcode":"8307 RP",
    "sg:province":"Flevoland",
    "wof:name":"Bloembinderij L' Epine",
    "wof:placetype":"venue"
},
  "geometry": {"coordinates":[5.865539,52.626339],"type":"Point"}
}