{
  "type": "Feature",
  "properties": {
    "addr:full":"Pr Mauritsln 43 Beek Lb Limburg 6191 EC",
    "addr:housenumber":"43",
    "addr:postcode":"lb;6191 ec",
    "iso:country":"NL",
    "sg:address":"Pr Mauritsln 43",
    "sg:city":"Beek Lb",
    "sg:orig_category":"Kappers",
    "sg:phone":"+31 46 435 1740",
    "sg:postcode":"6191 EC",
    "sg:province":"Limburg",
    "wof:name":"Jenico",
    "wof:placetype":"venue"
},
  "geometry": {"coordinates":[-93.1299362183,36.7056617737],"type":"Point"}
}