{
  "type": "Feature",
  "properties": {
    "addr:full":"Ir V Muylwykstr 210 Arnhem Gelderland 6828 BZ",
    "addr:housenumber":"210",
    "addr:postcode":"6828 bz",
    "addr:street":"Ir V Muylwykstr",
    "iso:country":"NL",
    "sg:address":"Ir V Muylwykstr 210",
    "sg:city":"Arnhem",
    "sg:orig_category":"Meubelstoffering",
    "sg:phone":"+31 26 442 4779",
    "sg:postcode":"6828 BZ",
    "sg:province":"Gelderland",
    "wof:name":"Brinker, Jan",
    "wof:placetype":"venue"
},
  "geometry": {"coordinates":[5.92598,51.98053],"type":"Point"}
}