{
  "type": "Feature",
  "properties": {
    "addr:full":"Industrieweg 3 Bruinisse Zeeland 4311 RM",
    "addr:housenumber":"3",
    "addr:postcode":"4311 rm",
    "addr:street":"Industrieweg",
    "iso:country":"NL",
    "sg:address":"Industrieweg 3",
    "sg:city":"Bruinisse",
    "sg:orig_category":"Metaalbekleding And -Behandeling",
    "sg:phone":"+31 111 483 616",
    "sg:postcode":"4311 RM",
    "sg:province":"Zeeland",
    "wof:name":"Bruinisse",
    "wof:placetype":"venue"
},
  "geometry": {"coordinates":[4.090922,51.655251],"type":"Point"}
}