{
  "type": "Feature",
  "properties": {
    "iso:country":"NL",
    "sg:address":"Beitel 15",
    "sg:city":"Heerlen",
    "sg:orig_category":"Metaalwaren - Fabrieken",
    "sg:phone":"+31 45 566 5600",
    "sg:postcode":"6422 PA",
    "sg:province":"Limburg",
    "wof:name":"Licom",
    "wof:placetype":"venue"
},
  "geometry": {"coordinates":[6.005938,50.847416],"type":"Point"}
}