{
  "type": "Feature",
  "properties": {
    "addr:full":"Tweede Nassaustraat 34 Amsterdam North Holland 1052 BP",
    "addr:housenumber":"34",
    "addr:postcode":"1052 bp",
    "addr:street":"Tweede Nassaustraat",
    "iso:country":"NL",
    "sg:address":"Tweede Nassaustraat 34",
    "sg:city":"Amsterdam",
    "sg:orig_category":"Verlichting And Huishoudartikelen",
    "sg:phone":"+31 20 684 4820",
    "sg:postcode":"1052 BP",
    "sg:province":"North Holland",
    "wof:name":"Vof Sportief",
    "wof:placetype":"venue"
},
  "geometry": {"coordinates":[4.87781,52.382812],"type":"Point"}
}