{
  "type": "Feature",
  "properties": {
    "iso:country":"NL",
    "sg:address":"Bredeweg 42",
    "sg:city":"Amsterdam",
    "sg:orig_category":"Autokeuringen",
    "sg:phone":"+31 20 694 6291",
    "sg:postcode":"1098 BS",
    "sg:province":"Noord-Holland",
    "wof:name":"Van Vliet Garage",
    "wof:placetype":"venue"
},
  "geometry": {"coordinates":[4.931286,52.354549],"type":"Point"}
}