{
  "type": "Feature",
  "properties": {
    "addr:full":"Bernadotteln 3A Haarlem North Holland 2037 GK",
    "addr:housenumber":"3a",
    "addr:postcode":"2037 gk",
    "addr:street":"Bernadotteln",
    "iso:country":"NL",
    "sg:address":"Bernadotteln 3A",
    "sg:city":"Haarlem",
    "sg:orig_category":"Bloemen En Planten",
    "sg:phone":"+31 23 533 5522",
    "sg:postcode":"2037 GK",
    "sg:province":"North Holland",
    "wof:name":"Joop Wijkhuizen Bloembinderij",
    "wof:placetype":"venue"
},
  "geometry": {"coordinates":[4.66426,52.353531],"type":"Point"}
}