{
  "type": "Feature",
  "properties": {
    "iso:country":"NL",
    "sg:address":"Saenredamstr 25",
    "sg:city":"Amsterdam",
    "sg:orig_category":"Glazenwasserijen",
    "sg:phone":"+31 6 22104211",
    "sg:postcode":"1072 CB",
    "sg:province":"North Holland",
    "wof:name":"Asseper",
    "wof:placetype":"venue"
},
  "geometry": {"coordinates":[4.887981,52.355904],"type":"Point"}
}