{
  "type": "Feature",
  "properties": {
    "iso:country":"NL",
    "sg:address":"Bosboomstr 77",
    "sg:city":"Eindhoven",
    "sg:orig_category":"Koffie- En Theehuizen",
    "sg:phone":"+31 40 244 6712",
    "sg:postcode":"5613 KD",
    "sg:province":"Noord-Brabant",
    "wof:name":"Highlander",
    "wof:placetype":"venue"
},
  "geometry": {"coordinates":[5.498331,51.4389],"type":"Point"}
}