{
  "type": "Feature",
  "properties": {
    "addr:full":"Weg Vd Buitenlandse Pers 1 A Ouwerkerk Zeeland 4305 RJ",
    "addr:housenumber":"1 a",
    "addr:postcode":"4305 rj",
    "addr:street":"Weg Vd Buitenlandse Pers",
    "iso:country":"NL",
    "sg:address":"Weg Vd Buitenlandse Pers 1 A",
    "sg:city":"Ouwerkerk",
    "sg:orig_category":"Kampeerterreinen",
    "sg:phone":"+31 111 642 044",
    "sg:postcode":"4305 RJ",
    "sg:province":"Zeeland",
    "wof:name":"Paviljoen De Vierbannen",
    "wof:placetype":"venue"
},
  "geometry": {"coordinates":[-42.9211997986,-22.0671596527],"type":"Point"}
}