{
  "type": "Feature",
  "properties": {
    "addr:full":"2E De Riemerstr 172 S Gravenhage Zuid-Holland 2513 CZ",
    "addr:housenumber":"172;gravenhage;2513",
    "addr:street":"2E De Riemerstr;S",
    "iso:country":"NL",
    "sg:address":"2E De Riemerstr 172",
    "sg:city":"S Gravenhage",
    "sg:orig_category":"Psychologen",
    "sg:phone":"+31 70 346 3676",
    "sg:postcode":"2513 CZ",
    "sg:province":"Zuid-Holland",
    "wof:name":"Kuhlemeier",
    "wof:placetype":"venue"
},
  "geometry": {"coordinates":[4.30339,52.078442],"type":"Point"}
}