{
  "type": "Feature",
  "properties": {
    "addr:full":"Doctor Plesmanlaan 176 Maarssen Utrecht 3601 DG",
    "addr:housenumber":"176",
    "addr:postcode":"3601 dg",
    "addr:street":"Doctor Plesmanlaan",
    "iso:country":"NL",
    "sg:address":"Doctor Plesmanlaan 176",
    "sg:city":"Maarssen",
    "sg:classifiers":[
        {
            "category":"Fast Food",
            "type":"Food & Drink"
        }
    ],
    "sg:phone":"+31 346 562 191",
    "sg:postcode":"3601 DG",
    "sg:province":"Utrecht",
    "sg:tags":[
        "afhaal",
        "restaurant"
    ],
    "wof:name":"De Lantaarn",
    "wof:placetype":"venue"
},
  "geometry": {"coordinates":[5.044743,52.143913],"type":"Point"}
}