{
  "type": "Feature",
  "properties": {
    "addr:full":"Walstr 29 Vlissingen Zeeland 4381 ED",
    "addr:housenumber":"29",
    "addr:postcode":"4381 ed",
    "addr:street":"Walstr",
    "iso:country":"NL",
    "sg:address":"Walstr 29",
    "sg:city":"Vlissingen",
    "sg:orig_category":"Kappers",
    "sg:phone":"+31 118 414 170",
    "sg:postcode":"4381 ED",
    "sg:province":"Zeeland",
    "wof:name":"Avenue",
    "wof:placetype":"venue"
},
  "geometry": {"coordinates":[3.5762939453,51.4430961609],"type":"Point"}
}