{
  "type": "Feature",
  "properties": {
    "addr:full":"Drenthehof 69 Helmond Noord-Brabant 5709 CK",
    "addr:housenumber":"69",
    "addr:postcode":"5709 ck",
    "addr:street":"Drenthehof",
    "iso:country":"NL",
    "sg:address":"Drenthehof 69",
    "sg:city":"Helmond",
    "sg:orig_category":"Architecten",
    "sg:phone":"+31 492 513 584",
    "sg:postcode":"5709 CK",
    "sg:province":"Noord-Brabant",
    "wof:name":"Architectenburo C.J.A. Lambooij",
    "wof:placetype":"venue"
},
  "geometry": {"coordinates":[5.707672,51.476925],"type":"Point"}
}