{
  "type": "Feature",
  "properties": {
    "addr:full":"Van Zuylen V Nyeveltstr 31 Wassenaar Zuid-Holland 2242 AJ",
    "addr:housenumber":"31",
    "addr:postcode":"2242 aj",
    "addr:street":"Van Zuylen V Nyeveltstr",
    "iso:country":"NL",
    "sg:address":"Van Zuylen V Nyeveltstr 31",
    "sg:city":"Wassenaar",
    "sg:orig_category":"Bedrijfs- And Managementsconsultants",
    "sg:phone":"+31 70 511 9079",
    "sg:postcode":"2242 AJ",
    "sg:province":"Zuid-Holland",
    "wof:name":"Struijk & Partner",
    "wof:placetype":"venue"
},
  "geometry": {"coordinates":[4.406296,52.140179],"type":"Point"}
}