{
  "type": "Feature",
  "properties": {
    "addr:full":"Marktpln 91 Broek Op Langedyk Noord-Holland 1721 CK",
    "addr:housenumber":"91",
    "addr:postcode":"1721 ck",
    "addr:street":"Marktpln;Op Langedyk",
    "iso:country":"NL",
    "sg:address":"Marktpln 91",
    "sg:city":"Broek Op Langedyk",
    "sg:orig_category":"Bloemen En Planten",
    "sg:phone":"+31 226 424 077",
    "sg:postcode":"1721 CK",
    "sg:province":"Noord-Holland",
    "sg:website":"http://www.greenroom.nl",
    "wof:name":"Allure Green Room, The",
    "wof:placetype":"venue"
},
  "geometry": {"coordinates":[4.803366,52.678886],"type":"Point"}
}