{
  "type": "Feature",
  "properties": {
    "iso:country":"NL",
    "sg:address":"Brinkstr 5",
    "sg:city":"Lienden",
    "sg:orig_category":"Grafisch Ontwerpers",
    "sg:phone":"+31 344 601 162",
    "sg:postcode":"4033 CW",
    "sg:province":"Gelderland",
    "wof:name":"Burgers, Bureau Annet",
    "wof:placetype":"venue"
},
  "geometry": {"coordinates":[5.515947,51.950596],"type":"Point"}
}