{
  "type": "Feature",
  "properties": {
    "addr:full":"Slotlaan 292 Zeist Utrecht 3701 GW",
    "addr:housenumber":"292",
    "addr:postcode":"3701 gw",
    "addr:street":"Slotlaan",
    "iso:country":"NL",
    "sg:address":"Slotlaan 292",
    "sg:city":"Zeist",
    "sg:orig_category":"Kappers",
    "sg:phone":"+31 30 691 7241",
    "sg:postcode":"3701 GW",
    "sg:province":"Utrecht",
    "wof:name":"Haarmode 2000",
    "wof:placetype":"venue"
},
  "geometry": {"coordinates":[5.2479867935,52.088142395],"type":"Point"}
}