{
  "type": "Feature",
  "properties": {
    "addr:full":"Waterzolder 19 Wormer North Holland 1531 NT",
    "addr:housenumber":"19",
    "addr:postcode":"1531 nt",
    "addr:street":"Waterzolder",
    "iso:country":"NL",
    "sg:address":"Waterzolder 19",
    "sg:city":"Wormer",
    "sg:orig_category":"Schoonheidssalons",
    "sg:phone":"+31 75 642 3332",
    "sg:postcode":"1531 NT",
    "sg:province":"North Holland",
    "wof:name":"Schoonheidsinstituut Sylvia Leurs-Van Ku",
    "wof:placetype":"venue"
},
  "geometry": {"coordinates":[4.811662,52.492157],"type":"Point"}
}