{
  "type": "Feature",
  "properties": {
    "addr:full":"J V Speykstr 11 S Hertogenbosch Noord-Brabant 5224 DC",
    "addr:housenumber":"11",
    "addr:postcode":"5224",
    "addr:street":"J;Speykstr;S",
    "iso:country":"NL",
    "sg:address":"J V Speykstr 11",
    "sg:city":"S Hertogenbosch",
    "sg:orig_category":"Scheidingswanden - Fabrieken",
    "sg:phone":"+31 73 621 1755",
    "sg:postcode":"5224 DC",
    "sg:province":"Noord-Brabant",
    "wof:name":"Teulings",
    "wof:placetype":"venue"
},
  "geometry": {"coordinates":[5.25958,51.698631],"type":"Point"}
}