{
  "type": "Feature",
  "properties": {
    "addr:full":"Vledderstr 16 Denekamp Overijssel 7591 DJ",
    "addr:housenumber":"16",
    "addr:postcode":"7591 dj",
    "addr:street":"Vledderstr",
    "iso:country":"NL",
    "sg:address":"Vledderstr 16",
    "sg:city":"Denekamp",
    "sg:orig_category":"Kappers",
    "sg:phone":"+31 541 354 556",
    "sg:postcode":"7591 DJ",
    "sg:province":"Overijssel",
    "wof:name":"Arthur",
    "wof:placetype":"venue"
},
  "geometry": {"coordinates":[7.0057010651,52.3759155273],"type":"Point"}
}