{
  "type": "Feature",
  "properties": {
    "addr:full":"Gedempte Turfhaven 3 Hoorn Nh Noord-Holland 1621 HC",
    "addr:housenumber":"3",
    "addr:postcode":"1621 hc",
    "addr:street":"Gedempte Turfhaven",
    "iso:country":"NL",
    "sg:address":"Gedempte Turfhaven 3",
    "sg:city":"Hoorn Nh",
    "sg:orig_category":"Wasserettes And Stomerijen",
    "sg:phone":"+31 229 219 670",
    "sg:postcode":"1621 HC",
    "sg:province":"Noord-Holland",
    "wof:name":"Azea Bv",
    "wof:placetype":"venue"
},
  "geometry": {"coordinates":[5.0576868057,52.642780304],"type":"Point"}
}