{
  "type": "Feature",
  "properties": {
    "iso:country":"NL",
    "sg:address":"Eendracht 3",
    "sg:city":"Hansweert",
    "sg:classifiers":[
        {
            "category":"Education",
            "subcategory":"Preschool",
            "type":"Public Place"
        }
    ],
    "sg:phone":"+31 113 320 090",
    "sg:postcode":"4417 CA",
    "sg:province":"Zeeland",
    "sg:tags":[
        "kleuteronderwijs",
        "basis-"
    ],
    "wof:name":"Openbare Basisschool De Eendracht",
    "wof:placetype":"venue"
},
  "geometry": {"coordinates":[4.001213,51.449574],"type":"Point"}
}