{
  "type": "Feature",
  "properties": {
    "addr:full":"Satellietbaan 20G Hillegom Zuid-Holland 2181 MH",
    "addr:housenumber":"20g",
    "addr:postcode":"2181 mh",
    "addr:street":"Satellietbaan",
    "iso:country":"NL",
    "sg:address":"Satellietbaan 20G",
    "sg:city":"Hillegom",
    "sg:orig_category":"Keukens",
    "sg:phone":"+31 252 534 074",
    "sg:postcode":"2181 MH",
    "sg:province":"Zuid-Holland",
    "wof:name":"Hillegom, Keukenstudio",
    "wof:placetype":"venue"
},
  "geometry": {"coordinates":[4.58894,52.299957],"type":"Point"}
}