{
  "type": "Feature",
  "properties": {
    "addr:full":"Nw Hoefwg 4 Zoetermeer Zuid-Holland 2722 PA",
    "addr:housenumber":"4",
    "addr:postcode":"2722 pa",
    "addr:street":"Hoefwg",
    "iso:country":"NL",
    "sg:address":"Nw Hoefwg 4",
    "sg:city":"Zoetermeer",
    "sg:orig_category":"Magazijninrichtingen",
    "sg:phone":"+31 79 593 6426",
    "sg:postcode":"2722 PA",
    "sg:province":"Zuid-Holland",
    "sg:website":"http://www.vandermeermagazijninrichtingen.nl",
    "wof:name":"Meer, Van Der",
    "wof:placetype":"venue"
},
  "geometry": {"coordinates":[4.547646,52.051041],"type":"Point"}
}