{
  "type": "Feature",
  "properties": {
    "addr:full":"Ziepseweg 98 Didam Gelderland 6941 BA",
    "addr:housenumber":"98",
    "addr:postcode":"6941 ba",
    "addr:street":"Ziepseweg;Gelderland",
    "iso:country":"NL",
    "sg:address":"Ziepseweg 98",
    "sg:city":"Didam",
    "sg:orig_category":"Verenigingen En Stichtingen",
    "sg:phone":"+31 316 294 633",
    "sg:postcode":"6941 BA",
    "sg:province":"Gelderland",
    "wof:name":"Fatima",
    "wof:placetype":"venue"
},
  "geometry": {"coordinates":[6.127579,51.943432],"type":"Point"}
}