{
  "type": "Feature",
  "properties": {
    "iso:country":"NL",
    "sg:address":"Emdenstraat 16",
    "sg:city":"Deventer",
    "sg:orig_category":"Gebouwenafwerking, Renovaties And Reiniging",
    "sg:phone":"+31 570 635 454",
    "sg:postcode":"7418 BR",
    "sg:province":"Overijssel",
    "wof:name":"Asito",
    "wof:placetype":"venue"
},
  "geometry": {"coordinates":[6.198544,52.24128],"type":"Point"}
}