{
  "type": "Feature",
  "properties": {
    "addr:full":"Zuidlarenstr 203 S Gravenhage Zuid-Holland 2545 VT",
    "addr:housenumber":"203;gravenhage;2545",
    "addr:street":"S",
    "iso:country":"NL",
    "sg:address":"Zuidlarenstr 203",
    "sg:city":"S Gravenhage",
    "sg:orig_category":"Kunststof Ramen",
    "sg:phone":"+31 70 329 4145",
    "sg:postcode":"2545 VT",
    "sg:province":"Zuid-Holland",
    "wof:name":"Beduplast Vof",
    "wof:placetype":"venue"
},
  "geometry": {"coordinates":[4.27049,52.05093],"type":"Point"}
}