{
  "type": "Feature",
  "properties": {
    "addr:full":"Ouvertureln 23 Krimpen Ad Yssel Zuid-Holland 2926 PT",
    "addr:housenumber":"23",
    "addr:postcode":"2926 pt",
    "addr:street":"Ouvertureln",
    "iso:country":"NL",
    "sg:address":"Ouvertureln 23",
    "sg:city":"Krimpen Ad Yssel",
    "sg:orig_category":"Adviesbureaus Bedrijfsorganisatie",
    "sg:phone":"+31 180 554 287",
    "sg:postcode":"2926 PT",
    "sg:province":"Zuid-Holland",
    "wof:name":"Cauwels",
    "wof:placetype":"venue"
},
  "geometry": {"coordinates":[4.603732,51.910366],"type":"Point"}
}