{
  "type": "Feature",
  "properties": {
    "addr:full":"Gareelwg 28 Moerstraten North Brabant 4727 TB",
    "addr:housenumber":"28",
    "addr:postcode":"4727 tb",
    "addr:street":"Gareelwg",
    "iso:country":"NL",
    "sg:address":"Gareelwg 28",
    "sg:city":"Moerstraten",
    "sg:orig_category":"Verhuur",
    "sg:phone":"+31 165 302 451",
    "sg:postcode":"4727 TB",
    "sg:province":"North Brabant",
    "wof:name":"Bartels",
    "wof:placetype":"venue"
},
  "geometry": {"coordinates":[4.342385,51.54121],"type":"Point"}
}