{
  "type": "Feature",
  "properties": {
    "addr:full":"F Rietveldpad 56 Schiedam Zuid-Holland 3123 CD",
    "addr:housenumber":"56",
    "addr:postcode":"3123 cd",
    "addr:street":"Rietveldpad",
    "iso:country":"NL",
    "sg:address":"F Rietveldpad 56",
    "sg:city":"Schiedam",
    "sg:orig_category":"Hypotheken",
    "sg:phone":"+31 10 247 7462",
    "sg:postcode":"3123 CD",
    "sg:province":"Zuid-Holland",
    "wof:name":"Schiedam",
    "wof:placetype":"venue"
},
  "geometry": {"coordinates":[4.36664,51.942181],"type":"Point"}
}