{
  "type": "Feature",
  "properties": {
    "addr:full":"Badhuiswg 7 S Gravenhage South Holland 2587 CA",
    "addr:housenumber":"7 s",
    "addr:postcode":"2587 ca",
    "addr:street":"Badhuiswg",
    "iso:country":"NL",
    "sg:address":"Badhuiswg 7",
    "sg:city":"S Gravenhage",
    "sg:orig_category":"Octrooionderzoek- En Exploitatiebureaus",
    "sg:phone":"+31 70 358 9616",
    "sg:postcode":"2587 CA",
    "sg:province":"South Holland",
    "sg:website":"http://www.livesavernow.com",
    "wof:name":"Lifesaver Bv",
    "wof:placetype":"venue"
},
  "geometry": {"coordinates":[4.29118,52.112942],"type":"Point"}
}