{
  "type": "Feature",
  "properties": {
    "addr:full":"Leistertwg 2 Roggel Limburg 6088 NW",
    "addr:housenumber":"2",
    "addr:postcode":"6088 nw",
    "addr:street":"Leistertwg",
    "iso:country":"NL",
    "sg:address":"Leistertwg 2",
    "sg:city":"Roggel",
    "sg:classifiers":[
        {
            "category":"Sports & Exercise",
            "subcategory":"Stables",
            "type":"Entertainment"
        }
    ],
    "sg:phone":"+31 475 496 000",
    "sg:postcode":"6088 NW",
    "sg:province":"Limburg",
    "sg:tags":[
        "maneges"
    ],
    "wof:name":"Leistert, De",
    "wof:placetype":"venue"
},
  "geometry": {"coordinates":[5.933009,51.276279],"type":"Point"}
}