{
  "type": "Feature",
  "properties": {
    "iso:country":"NL",
    "sg:address":"Galgenvenstraat 250",
    "sg:city":"Tegelen",
    "sg:classifiers":[
        {
            "category":"Education",
            "subcategory":"Preschool",
            "type":"Public Place"
        }
    ],
    "sg:phone":"+31 77 373 3318",
    "sg:postcode":"5932 SW",
    "sg:province":"Limburg",
    "sg:tags":[
        "kleuteronderwijs",
        "basis-"
    ],
    "wof:name":"Basisschool De Kleiberg",
    "wof:placetype":"venue"
},
  "geometry": {"coordinates":[6.153516,51.331158],"type":"Point"}
}