{
  "type": "Feature",
  "properties": {
    "addr:full":"Hertog Van Beijerenstr 17 Ter Aar South Holland 2461 EM",
    "addr:housenumber":"17",
    "addr:postcode":"2461 em",
    "addr:street":"Hertog Van Beijerenstr",
    "iso:country":"NL",
    "sg:address":"Hertog Van Beijerenstr 17",
    "sg:city":"Ter Aar",
    "sg:orig_category":"Bouwmaterialen Gh",
    "sg:phone":"+31 172 602 349",
    "sg:postcode":"2461 EM",
    "sg:province":"South Holland",
    "wof:name":"Handelsonderneming Besemer Van Beek",
    "wof:placetype":"venue"
},
  "geometry": {"coordinates":[4.713651,52.178719],"type":"Point"}
}