{
  "type": "Feature",
  "properties": {
    "addr:full":"Liede 1 Zwolle Overijssel 8032 AD",
    "addr:housenumber":"1",
    "addr:postcode":"8032 ad",
    "addr:street":"Liede",
    "iso:country":"NL",
    "sg:address":"Liede 1",
    "sg:city":"Zwolle",
    "sg:orig_category":"Administratie- En Boekhoudkantoren",
    "sg:phone":"+31 38 452 8529",
    "sg:postcode":"8032 AD",
    "sg:province":"Overijssel",
    "wof:name":"Croesinsky Vof",
    "wof:placetype":"venue"
},
  "geometry": {"coordinates":[6.099926,52.524868],"type":"Point"}
}