{
  "type": "Feature",
  "properties": {
    "addr:full":"Zouwendijk 109 Meerkerk South Holland 4231 CC",
    "addr:housenumber":"109",
    "addr:postcode":"4231 cc",
    "addr:street":"Zouwendijk",
    "iso:country":"NL",
    "sg:address":"Zouwendijk 109",
    "sg:city":"Meerkerk",
    "sg:orig_category":"Pompen And Compressoren Fab",
    "sg:phone":"+31 183 352 088",
    "sg:postcode":"4231 CC",
    "sg:province":"South Holland",
    "wof:name":"W.T.A. Worldwide Technical Assistance",
    "wof:placetype":"venue"
},
  "geometry": {"coordinates":[4.996288,51.932976],"type":"Point"}
}