{
  "type": "Feature",
  "properties": {
    "addr:full":"Mauritswg 44 Rotterdam South Holland 3012 JV",
    "addr:housenumber":"44",
    "addr:postcode":"3012 jv",
    "addr:street":"Mauritswg",
    "iso:country":"NL",
    "sg:address":"Mauritswg 44",
    "sg:city":"Rotterdam",
    "sg:orig_category":"Belastingconsulenten/ Belastingadviseurs",
    "sg:phone":"+31 10 243 9657",
    "sg:postcode":"3012 JV",
    "sg:province":"South Holland",
    "wof:name":"Huibers & Van Eersel",
    "wof:placetype":"venue"
},
  "geometry": {"coordinates":[4.472898,51.918186],"type":"Point"}
}