{
  "type": "Feature",
  "properties": {
    "addr:full":"Raadhuisstraat 97 Alphen A/D Rijn Zuid-Holland 2406 AB",
    "addr:housenumber":"97",
    "addr:postcode":"2406 ab",
    "addr:street":"Raadhuisstraat",
    "iso:country":"NL",
    "sg:address":"Raadhuisstraat 97",
    "sg:city":"Alphen A/D Rijn",
    "sg:orig_category":"Meubelreparatie And -Restauratie",
    "sg:phone":"+31 172 475 735",
    "sg:postcode":"2406 AB",
    "sg:province":"Zuid-Holland",
    "wof:name":"M Koetsier",
    "wof:placetype":"venue"
},
  "geometry": {"coordinates":[4.664659,52.123009],"type":"Point"}
}