{
  "type": "Feature",
  "properties": {
    "addr:full":"Emmasingel 8 Weert Limburg 6001 BC",
    "addr:housenumber":"8",
    "addr:postcode":"6001 bc",
    "addr:street":"Emmasingel",
    "iso:country":"NL",
    "sg:address":"Emmasingel 8",
    "sg:city":"Weert",
    "sg:orig_category":"Verzekeringen",
    "sg:phone":"+31 495 545 895",
    "sg:postcode":"6001 BC",
    "sg:province":"Limburg",
    "wof:name":"De Pensioendesk",
    "wof:placetype":"venue"
},
  "geometry": {"coordinates":[5.709096,51.25473],"type":"Point"}
}