{
  "type": "Feature",
  "properties": {
    "iso:country":"NL",
    "sg:address":"Teresjkowastraat 12",
    "sg:city":"Krommenie",
    "sg:orig_category":"Elektrische Apparatuur Gh",
    "sg:phone":"+31 75 628 3717",
    "sg:postcode":"1562 BW",
    "sg:province":"North Holland",
    "wof:name":"Hoog Frequent Technology Gorter",
    "wof:placetype":"venue"
},
  "geometry": {"coordinates":[4.753802,52.506592],"type":"Point"}
}