{
  "type": "Feature",
  "properties": {
    "iso:country":"NL",
    "sg:address":"Broeierdweg 71",
    "sg:city":"Enschede",
    "sg:orig_category":"Bloemen And Planten",
    "sg:phone":"+31 53 430 5167",
    "sg:postcode":"7547 SG",
    "sg:province":"Overijssel",
    "wof:name":"H.F.M. Kuipers",
    "wof:placetype":"venue"
},
  "geometry": {"coordinates":[6.83083,52.239689],"type":"Point"}
}