{
  "type": "Feature",
  "properties": {
    "addr:full":"M H Trompstraat 5 De Lier Zuid-Holland 2678 GH",
    "addr:housenumber":"5",
    "addr:postcode":"2678 gh",
    "addr:street":"M;Trompstraat",
    "iso:country":"NL",
    "sg:address":"M H Trompstraat 5",
    "sg:city":"De Lier",
    "sg:orig_category":"Juridische Dienstverlening",
    "sg:phone":"+31 174 513 163",
    "sg:postcode":"2678 GH",
    "sg:province":"Zuid-Holland",
    "wof:name":"Merkenadviesbureau P. Van Berkel",
    "wof:placetype":"venue"
},
  "geometry": {"coordinates":[4.257232,51.975456],"type":"Point"}
}