{
  "type": "Feature",
  "properties": {
    "addr:full":"Planetenbaan 15/A Bilthoven Utrecht 3721 KA",
    "addr:housenumber":"15 / a",
    "addr:postcode":"3721 ka",
    "addr:street":"Planetenbaan",
    "iso:country":"NL",
    "sg:address":"Planetenbaan 15/A",
    "sg:city":"Bilthoven",
    "sg:orig_category":"Kaas",
    "sg:phone":"+31 30 228 1744",
    "sg:postcode":"3721 KA",
    "sg:province":"Utrecht",
    "wof:name":"Kaasspecialist, De",
    "wof:placetype":"venue"
},
  "geometry": {"coordinates":[5.1850547791,52.1199226379],"type":"Point"}
}