{
  "type": "Feature",
  "properties": {
    "addr:full":"Zandpad Driemond 6 Amsterdam Zuidoost Noord-Holland 1109 AG",
    "addr:housenumber":"6",
    "addr:postcode":"zuidoost;1109",
    "addr:street":"Zandpad Driemond",
    "iso:country":"NL",
    "sg:address":"Zandpad Driemond 6",
    "sg:city":"Amsterdam Zuidoost",
    "sg:orig_category":"Fietsen En Bromfietsen",
    "sg:phone":"+31 294 419 034",
    "sg:postcode":"1109 AG",
    "sg:province":"Noord-Holland",
    "wof:name":"Aanloop, De",
    "wof:placetype":"venue"
},
  "geometry": {"coordinates":[5.014584,52.30397],"type":"Point"}
}