{
  "type": "Feature",
  "properties": {
    "iso:country":"NL",
    "sg:address":"Van Karnebeekstraat 101",
    "sg:city":"Amsterdam",
    "sg:orig_category":"Artiesten",
    "sg:phone":"+31 20 613 2502",
    "sg:postcode":"1067 RJ",
    "sg:province":"Noord-Holland",
    "wof:name":"Wera Van Den Berg",
    "wof:placetype":"venue"
},
  "geometry": {"coordinates":[4.79402,52.37492],"type":"Point"}
}