{
  "type": "Feature",
  "properties": {
    "addr:full":"Loosduinse Hoofdstraat 300 'S Gravenhage Zuid-Holland 2552 AN",
    "addr:housenumber":"300 '",
    "addr:postcode":"2552 an",
    "addr:street":"Loosduinse Hoofdstraat",
    "iso:country":"NL",
    "sg:address":"Loosduinse Hoofdstraat 300",
    "sg:city":"'S Gravenhage",
    "sg:orig_category":"Boekenuitgeverijen",
    "sg:phone":"+31 70 397 7731",
    "sg:postcode":"2552 AN",
    "sg:province":"Zuid-Holland",
    "wof:name":"Boekhandel J.L. Kroon",
    "wof:placetype":"venue"
},
  "geometry": {"coordinates":[4.240445,52.054844],"type":"Point"}
}