{
  "type": "Feature",
  "properties": {
    "iso:country":"NL",
    "sg:address":"Sitioln 6",
    "sg:city":"Doorn",
    "sg:classifiers":[
        {
            "category":"Personal",
            "subcategory":"Nail Salon",
            "type":"Services"
        }
    ],
    "sg:phone":"+31 343 415 361",
    "sg:postcode":"3941 PN",
    "sg:province":"Utrecht",
    "sg:tags":[
        "pedicure"
    ],
    "wof:name":"Lievense-Bogert",
    "wof:placetype":"venue"
},
  "geometry": {"coordinates":[5.346976,52.033321],"type":"Point"}
}