{
  "type": "Feature",
  "properties": {
    "iso:country":"NL",
    "sg:address":"Bernadottelaan 3",
    "sg:city":"Haarlem",
    "sg:orig_category":"Autokeuringen",
    "sg:phone":"+31 23 533 0660",
    "sg:postcode":"2037 GK",
    "sg:province":"Noord-Holland",
    "wof:name":"Van Lammeren Servicestations Bv",
    "wof:placetype":"venue"
},
  "geometry": {"coordinates":[4.665004,52.359142],"type":"Point"}
}