{
  "type": "Feature",
  "properties": {
    "addr:full":"Bernadottelaan 3 Haarlem Noord-Holland 2037 GK",
    "addr:housenumber":"3",
    "addr:postcode":"2037 gk",
    "addr:street":"Bernadottelaan",
    "iso:country":"NL",
    "sg:address":"Bernadottelaan 3",
    "sg:city":"Haarlem",
    "sg:orig_category":"Autokeuringen",
    "sg:phone":"+31 23 533 0660",
    "sg:postcode":"2037 GK",
    "sg:province":"Noord-Holland",
    "wof:name":"Van Lammeren Servicestations Bv",
    "wof:placetype":"venue"
},
  "geometry": {"coordinates":[4.665004,52.359142],"type":"Point"}
}