{
  "type": "Feature",
  "properties": {
    "addr:full":"Kraakstr 11 Hunsel Limburg 6013 RR",
    "addr:housenumber":"11",
    "addr:postcode":"6013 rr",
    "addr:street":"Kraakstr",
    "iso:country":"NL",
    "sg:address":"Kraakstr 11",
    "sg:city":"Hunsel",
    "sg:orig_category":"Kappers",
    "sg:phone":"+31 475 565 436",
    "sg:postcode":"6013 RR",
    "sg:province":"Limburg",
    "sg:website":"http://www.kapsalon-wietzentjens.nl",
    "wof:name":"Wiet Zentjens Kapsalon",
    "wof:placetype":"venue"
},
  "geometry": {"coordinates":[5.811753,51.191219],"type":"Point"}
}