{
  "type": "Feature",
  "properties": {
    "iso:country":"NL",
    "sg:address":"Kl Zand 4",
    "sg:city":"Breda",
    "sg:orig_category":"Administratie- En Boekhoudkantoren",
    "sg:phone":"+31 76 542 5036",
    "sg:postcode":"4823 HZ",
    "sg:province":"Noord-Brabant",
    "wof:name":"Jong, De",
    "wof:placetype":"venue"
},
  "geometry": {"coordinates":[4.740889,51.626968],"type":"Point"}
}