{
  "type": "Feature",
  "properties": {
    "iso:country":"NL",
    "sg:address":"Guisweg 37",
    "sg:city":"Zaandijk",
    "sg:classifiers":[
        {
            "category":"Fast Food",
            "type":"Food & Drink"
        }
    ],
    "sg:phone":"+31 75 628 0721",
    "sg:postcode":"1544 AG",
    "sg:province":"North Holland",
    "sg:tags":[
        "afhaal",
        "restaurant"
    ],
    "wof:name":"New Ka Ho",
    "wof:placetype":"venue"
},
  "geometry": {"coordinates":[4.80929,52.471275],"type":"Point"}
}