{
  "type": "Feature",
  "properties": {
    "iso:country":"NL",
    "sg:address":"Professor Aalberselaan 7",
    "sg:city":"Noordwijkerhout",
    "sg:orig_category":"Bedrijfs- And Managementsconsultants",
    "sg:phone":"+31 252 376 475",
    "sg:postcode":"2211 BG",
    "sg:province":"Sofiya",
    "wof:name":"Rob Kool Training & Advies",
    "wof:placetype":"venue"
},
  "geometry": {"coordinates":[23.104,42.79105],"type":"Point"}
}