{
  "type": "Feature",
  "properties": {
    "iso:country":"NL",
    "sg:address":"W G Witteveenpln 56",
    "sg:city":"Rotterdam",
    "sg:orig_category":"Webdesign Bureaus",
    "sg:phone":"+31 10 486 3406",
    "sg:postcode":"3071 MA",
    "sg:province":"Zuid-Holland",
    "sg:website":"http://www.presta.nl",
    "wof:name":"Presta",
    "wof:placetype":"venue"
},
  "geometry": {"coordinates":[4.5017328262,51.9066581726],"type":"Point"}
}