{
  "type": "Feature",
  "properties": {
    "addr:full":"Nieuwe Beestenmarkt 23 Leiden Zuid-Holland 2312 CG",
    "addr:housenumber":"23",
    "addr:postcode":"2312 cg",
    "addr:street":"Nieuwe Beestenmarkt",
    "iso:country":"NL",
    "sg:address":"Nieuwe Beestenmarkt 23",
    "sg:city":"Leiden",
    "sg:orig_category":"Fotolaboratoria",
    "sg:phone":"+31 71 512 5377",
    "sg:postcode":"2312 CG",
    "sg:province":"Zuid-Holland",
    "wof:name":"Super Photo Snelservice",
    "wof:placetype":"venue"
},
  "geometry": {"coordinates":[4.486197,52.163574],"type":"Point"}
}