{
  "type": "Feature",
  "properties": {
    "iso:country":"NL",
    "sg:address":"Westkade 69",
    "sg:city":"Sas Van Gent",
    "sg:orig_category":"Banken And Kredietinstellingen",
    "sg:phone":"+31 115 458 800",
    "sg:postcode":"4551 CD",
    "sg:province":"BE.08",
    "wof:name":"Ing Bank",
    "wof:placetype":"venue"
},
  "geometry": {"coordinates":[3.790558,51.226383],"type":"Point"}
}