{
  "type": "Feature",
  "properties": {
    "addr:full":"Tsjerkebuorren 2 Boazum Friesland 8635 MC",
    "addr:housenumber":"2",
    "addr:postcode":"8635 mc",
    "addr:street":"Tsjerkebuorren",
    "iso:country":"NL",
    "sg:address":"Tsjerkebuorren 2",
    "sg:city":"Boazum",
    "sg:orig_category":"Beeldende Kunstenaars",
    "sg:phone":"+31 515 521 115",
    "sg:postcode":"8635 MC",
    "sg:province":"Friesland",
    "wof:name":"Oranjerie, De",
    "wof:placetype":"venue"
},
  "geometry": {"coordinates":[5.695818,53.090096],"type":"Point"}
}