{
  "type": "Feature",
  "properties": {
    "iso:country":"NL",
    "sg:address":"Jacob Geelstraat 1",
    "sg:city":"Amsterdam",
    "sg:orig_category":"Kappers",
    "sg:phone":"+31 20 615 0397",
    "sg:postcode":"1065 VL",
    "sg:province":"Noord-Holland",
    "wof:name":"Dameskapsalon Helen",
    "wof:placetype":"venue"
},
  "geometry": {"coordinates":[4.8312878609,52.3626289368],"type":"Point"}
}