{
  "type": "Feature",
  "properties": {
    "iso:country":"NL",
    "sg:address":"Zworrelstraat 69A",
    "sg:city":"Herwijnen",
    "sg:orig_category":"Huisdierenfokkers",
    "sg:phone":"+31 418 584 044",
    "sg:postcode":"4171 AH",
    "sg:province":"Gelderland",
    "wof:name":"Brouwer'S Handelsmij",
    "wof:placetype":"venue"
},
  "geometry": {"coordinates":[5.129807,51.827724],"type":"Point"}
}