{
  "type": "Feature",
  "properties": {
    "addr:full":"Keienbergweg 73 Amsterdam Zuidoost North Holland 1101 GE",
    "addr:housenumber":"73",
    "addr:postcode":"1101",
    "addr:street":"Keienbergweg",
    "iso:country":"NL",
    "sg:address":"Keienbergweg 73",
    "sg:city":"Amsterdam Zuidoost",
    "sg:orig_category":"Wegen And Sportterreinen",
    "sg:phone":"+31 20 691 0406",
    "sg:postcode":"1101 GE",
    "sg:province":"North Holland",
    "wof:name":"Ricochet Benelux Bv",
    "wof:placetype":"venue"
},
  "geometry": {"coordinates":[4.9353289604,52.3085021973],"type":"Point"}
}