{
  "type": "Feature",
  "properties": {
    "addr:full":"Scholekster 3 Mydrecht Utrecht 3641 TT",
    "addr:housenumber":"3;3641",
    "addr:postcode":"tt",
    "addr:street":"Scholekster",
    "iso:country":"NL",
    "sg:address":"Scholekster 3",
    "sg:city":"Mydrecht",
    "sg:orig_category":"Adviesbureaus Bedrijfsorganisatie",
    "sg:phone":"+31 297 255 881",
    "sg:postcode":"3641 TT",
    "sg:province":"Utrecht",
    "wof:name":"Valk Bv, Van Der",
    "wof:placetype":"venue"
},
  "geometry": {"coordinates":[4.854732,52.200966],"type":"Point"}
}