{
  "type": "Feature",
  "properties": {
    "iso:country":"NL",
    "sg:address":"Lovense Kanaaldijk 165",
    "sg:city":"Tilburg",
    "sg:orig_category":"Verhuur Gereedschapsmachines And Gereedschappen",
    "sg:phone":"+31 13 543 8527",
    "sg:postcode":"5013 BJ",
    "sg:province":"Noord-Brabant",
    "wof:name":"Boels Verhuur",
    "wof:placetype":"venue"
},
  "geometry": {"coordinates":[5.107348,51.56377],"type":"Point"}
}