{
  "type": "Feature",
  "properties": {
    "addr:full":"Heerlerwg 158 Hoensbroek Limburg 6433 HX",
    "addr:housenumber":"158",
    "addr:postcode":"6433 hx",
    "addr:street":"Hoensbroek Limburg",
    "iso:country":"NL",
    "sg:address":"Heerlerwg 158",
    "sg:city":"Hoensbroek",
    "sg:orig_category":"Verzekeringen - Verzekeringskantoren",
    "sg:phone":"+31 45 528 5878",
    "sg:postcode":"6433 HX",
    "sg:province":"Limburg",
    "wof:name":"Geijn Bv, Van",
    "wof:placetype":"venue"
},
  "geometry": {"coordinates":[5.937383,50.907867],"type":"Point"}
}