{
  "type": "Feature",
  "properties": {
    "iso:country":"NL",
    "sg:address":"Torenstr 52",
    "sg:city":"Castricum",
    "sg:orig_category":"Herenkleding",
    "sg:phone":"+31 251 652 580",
    "sg:postcode":"1901 EG",
    "sg:province":"Noord-Holland",
    "wof:name":"Keulen Vof, Rob Van",
    "wof:placetype":"venue"
},
  "geometry": {"coordinates":[4.66368,52.550266],"type":"Point"}
}