{
  "type": "Feature",
  "properties": {
    "iso:country":"NL",
    "sg:address":"Rodenbachstr 22",
    "sg:city":"Etten Leur",
    "sg:orig_category":"Verzekeringen - Verzekeringskantoren",
    "sg:phone":"+31 76 501 3100",
    "sg:postcode":"4873 BB",
    "sg:province":"Noord-Brabant",
    "wof:name":"Tijs, G M M",
    "wof:placetype":"venue"
},
  "geometry": {"coordinates":[4.643153,51.566154],"type":"Point"}
}