{
  "type": "Feature",
  "properties": {
    "addr:full":"Het Rond 67 Zoetermeer South Holland 2711 BX",
    "addr:housenumber":"67",
    "addr:postcode":"2711 bx",
    "addr:street":"Het Rond",
    "iso:country":"NL",
    "sg:address":"Het Rond 67",
    "sg:city":"Zoetermeer",
    "sg:orig_category":"Boeken En Tijdschriften",
    "sg:phone":"+31 79 341 2451",
    "sg:postcode":"2711 BX",
    "sg:province":"South Holland",
    "sg:website":"http://www.bruna.nl/",
    "wof:name":"Bruna",
    "wof:placetype":"venue"
},
  "geometry": {"coordinates":[4.488925,52.06308],"type":"Point"}
}