{
  "type": "Feature",
  "properties": {
    "addr:full":"Stormwg 15 Hellevoetsluis South Holland 3222 EM",
    "addr:housenumber":"15",
    "addr:postcode":"3222 em",
    "addr:street":"Stormwg",
    "iso:country":"NL",
    "sg:address":"Stormwg 15",
    "sg:city":"Hellevoetsluis",
    "sg:classifiers":[
        {
            "category":"Personal",
            "subcategory":"Nail Salon",
            "type":"Services"
        }
    ],
    "sg:phone":"+31 181 326 115",
    "sg:postcode":"3222 EM",
    "sg:province":"South Holland",
    "sg:tags":[
        "pedicure"
    ],
    "wof:name":"Uit De Sokken",
    "wof:placetype":"venue"
},
  "geometry": {"coordinates":[4.125485,51.840889],"type":"Point"}
}