{
  "type": "Feature",
  "properties": {
    "addr:full":"W Beekmanstr 2 Gulpen Limburg 6271 CZ",
    "addr:housenumber":"2;6271",
    "addr:street":"W;Gulpen Limburg",
    "iso:country":"NL",
    "sg:address":"W Beekmanstr 2",
    "sg:city":"Gulpen",
    "sg:orig_category":"Bejaarden - Verzorgingstehuizen",
    "sg:phone":"+31 43 450 1542",
    "sg:postcode":"6271 CZ",
    "sg:province":"Limburg",
    "wof:name":"Ackenshuis, Dr",
    "wof:placetype":"venue"
},
  "geometry": {"coordinates":[5.883529,50.814194],"type":"Point"}
}