{
  "type": "Feature",
  "properties": {
    "addr:full":"Julianastr 64 Oud Beyerland Zuid-Holland 3262 SJ",
    "addr:housenumber":"64",
    "addr:postcode":"3262",
    "addr:street":"Julianastr;Oud Beyerland",
    "iso:country":"NL",
    "sg:address":"Julianastr 64",
    "sg:city":"Oud Beyerland",
    "sg:orig_category":"Projectontwikkeling",
    "sg:phone":"+31 6 53720731",
    "sg:postcode":"3262 SJ",
    "sg:province":"Zuid-Holland",
    "wof:name":"Berg",
    "wof:placetype":"venue"
},
  "geometry": {"coordinates":[4.415329,51.823334],"type":"Point"}
}