{
  "type": "Feature",
  "properties": {
    "addr:full":"Morssingel 306 Leiden South Holland 2312 AZ",
    "addr:housenumber":"306",
    "addr:postcode":"2312 az",
    "addr:street":"Morssingel",
    "iso:country":"NL",
    "sg:address":"Morssingel 306",
    "sg:city":"Leiden",
    "sg:orig_category":"Pleziervaartuigen And Reparatie",
    "sg:phone":"+31 71 512 3029",
    "sg:postcode":"2312 AZ",
    "sg:province":"South Holland",
    "wof:name":"Bolier Jachtbouw",
    "wof:placetype":"venue"
},
  "geometry": {"coordinates":[4.484176,52.163998],"type":"Point"}
}