{
  "type": "Feature",
  "properties": {
    "iso:country":"NL",
    "sg:address":"Zworrelstr 44",
    "sg:city":"Herwijnen",
    "sg:orig_category":"Administratie- En Boekhoudkantoren",
    "sg:phone":"+31 418 581 693",
    "sg:postcode":"4171 AJ",
    "sg:province":"Gelderland",
    "sg:website":"HTTP://www.kuyntjesjj.nl",
    "wof:name":"Kuyntjes, J J",
    "wof:placetype":"venue"
},
  "geometry": {"coordinates":[5.126751,51.827621],"type":"Point"}
}