{
  "type": "Feature",
  "properties": {
    "addr:full":"Lytse Dk 5 Sneek Friesland 8601 ZJ",
    "addr:housenumber":"5",
    "addr:postcode":"8601 zj",
    "addr:street":"Lytse Dk",
    "iso:country":"NL",
    "sg:address":"Lytse Dk 5",
    "sg:city":"Sneek",
    "sg:orig_category":"Onderhoudswerken",
    "sg:phone":"+31 515 433 420",
    "sg:postcode":"8601 ZJ",
    "sg:province":"Friesland",
    "wof:name":"Dgs",
    "wof:placetype":"venue"
},
  "geometry": {"coordinates":[5.640964,53.030994],"type":"Point"}
}