{
  "type": "Feature",
  "properties": {
    "addr:full":"Amstelpln 411 Uithoorn North Holland 1421 SH",
    "addr:housenumber":"411",
    "addr:postcode":"1421 sh",
    "iso:country":"NL",
    "sg:address":"Amstelpln 411",
    "sg:city":"Uithoorn",
    "sg:orig_category":"Adviesbureaus Gezondheidszorg",
    "sg:phone":"+31 297 525 299",
    "sg:postcode":"1421 SH",
    "sg:province":"North Holland",
    "wof:name":"Johnson & Walters Bv",
    "wof:placetype":"venue"
},
  "geometry": {"coordinates":[4.8275,52.232868],"type":"Point"}
}