{
  "type": "Feature",
  "properties": {
    "addr:full":"Haaksbergerstr 10 Diepenheim Overijssel 7478 AW",
    "addr:housenumber":"10",
    "addr:postcode":"7478 aw",
    "addr:street":"Haaksbergerstr",
    "iso:country":"NL",
    "sg:address":"Haaksbergerstr 10",
    "sg:city":"Diepenheim",
    "sg:orig_category":"Sportverenigingen En Ontspannings- Verenigingen",
    "sg:phone":"+31 547 351 724",
    "sg:postcode":"7478 AW",
    "sg:province":"Overijssel",
    "wof:name":"Golf Events Services",
    "wof:placetype":"venue"
},
  "geometry": {"coordinates":[6.555191,52.198891],"type":"Point"}
}