{
  "type": "Feature",
  "properties": {
    "addr:full":"Staalwyk 16 Dronten Flevoland 8251 JX",
    "addr:housenumber":"16",
    "addr:postcode":"8251 jx",
    "addr:street":"Staalwyk;Flevoland",
    "iso:country":"NL",
    "sg:address":"Staalwyk 16",
    "sg:city":"Dronten",
    "sg:orig_category":"Houtindustrie",
    "sg:phone":"+31 321 336 699",
    "sg:postcode":"8251 JX",
    "sg:province":"Flevoland",
    "sg:website":"http://www.jacabo.nl",
    "wof:name":"Jacabo Bv",
    "wof:placetype":"venue"
},
  "geometry": {"coordinates":[5.714939,52.5238],"type":"Point"}
}