{
  "type": "Feature",
  "properties": {
    "addr:full":"Stuyvesantstraat 351 'S Gravenhage South Holland 2593 GK",
    "addr:housenumber":"351 '",
    "addr:postcode":"2593 gk",
    "addr:street":"Stuyvesantstraat",
    "iso:country":"NL",
    "sg:address":"Stuyvesantstraat 351",
    "sg:city":"'S Gravenhage",
    "sg:orig_category":"Autokeuringen",
    "sg:phone":"+31 70 347 0235",
    "sg:postcode":"2593 GK",
    "sg:province":"South Holland",
    "wof:name":"Matheu Int Enterprise Mie",
    "wof:placetype":"venue"
},
  "geometry": {"coordinates":[4.344096,52.088165],"type":"Point"}
}