{
  "type": "Feature",
  "properties": {
    "addr:full":"Meerlosebaan 26 Wanssum Limburg 5861 CP",
    "addr:housenumber":"26",
    "addr:postcode":"5861 cp",
    "addr:street":"Meerlosebaan",
    "iso:country":"NL",
    "sg:address":"Meerlosebaan 26",
    "sg:city":"Wanssum",
    "sg:orig_category":"Adviesbureaus Personeel",
    "sg:phone":"+31 478 539 170",
    "sg:postcode":"5861 CP",
    "sg:province":"Limburg",
    "wof:name":"Course",
    "wof:placetype":"venue"
},
  "geometry": {"coordinates":[6.068814,51.534451],"type":"Point"}
}