{
  "type": "Feature",
  "properties": {
    "addr:full":"Beatrijsstraat 28B Rotterdam Zuid-Holland 3021 RE",
    "addr:housenumber":"28b",
    "addr:postcode":"3021 re",
    "addr:street":"Beatrijsstraat",
    "iso:country":"NL",
    "sg:address":"Beatrijsstraat 28B",
    "sg:city":"Rotterdam",
    "sg:orig_category":"Paramedische Behandelingen",
    "sg:phone":"+31 10 476 6196",
    "sg:postcode":"3021 RE",
    "sg:province":"Zuid-Holland",
    "wof:name":"E.I. Van De Maal",
    "wof:placetype":"venue"
},
  "geometry": {"coordinates":[4.457895,51.920689],"type":"Point"}
}