{
  "type": "Feature",
  "properties": {
    "addr:full":"Nachtegaalwg 14 Soest Utrecht 3762 TK",
    "addr:housenumber":"14",
    "addr:postcode":"3762 tk",
    "addr:street":"Nachtegaalwg",
    "iso:country":"NL",
    "sg:address":"Nachtegaalwg 14",
    "sg:city":"Soest",
    "sg:orig_category":"Adviesbureaus Bedrijfsorganisatie",
    "sg:phone":"+31 35 588 1690",
    "sg:postcode":"3762 TK",
    "sg:province":"Utrecht",
    "wof:name":"Braun, Danielle",
    "wof:placetype":"venue"
},
  "geometry": {"coordinates":[5.279876,52.182594],"type":"Point"}
}