{
  "type": "Feature",
  "properties": {
    "addr:full":"Heusdenhoutsewg 32 Breda Noord-Brabant 4817 NC",
    "addr:housenumber":"32",
    "addr:postcode":"4817 nc",
    "addr:street":"Heusdenhoutsewg",
    "iso:country":"NL",
    "sg:address":"Heusdenhoutsewg 32",
    "sg:city":"Breda",
    "sg:orig_category":"Peuterspeelzalen",
    "sg:phone":"+31 76 587 7849",
    "sg:postcode":"4817 NC",
    "sg:province":"Noord-Brabant",
    "wof:name":"Lentehof",
    "wof:placetype":"venue"
},
  "geometry": {"coordinates":[4.819595,51.589451],"type":"Point"}
}