{
  "type": "Feature",
  "properties": {
    "addr:full":"Binnenveld 40 Huissen Gelderland 6851 NE",
    "addr:housenumber":"40",
    "addr:postcode":"6851",
    "addr:street":"Binnenveld;Gelderland;Ne",
    "iso:country":"NL",
    "sg:address":"Binnenveld 40",
    "sg:city":"Huissen",
    "sg:orig_category":"Natuurvoeding En Reformartikelen",
    "sg:phone":"+31 26 325 7669",
    "sg:postcode":"6851 NE",
    "sg:province":"Gelderland",
    "wof:name":"Personal Touch",
    "wof:placetype":"venue"
},
  "geometry": {"coordinates":[5.935687,51.932251],"type":"Point"}
}