{
  "type": "Feature",
  "properties": {
    "iso:country":"NL",
    "sg:address":"Stationswg 2A",
    "sg:city":"Oude Tonge",
    "sg:orig_category":"Waterbouwkundige Werken",
    "sg:phone":"+31 187 641 733",
    "sg:postcode":"3255 BL",
    "sg:province":"Zuid-Holland",
    "wof:name":"Osseweijer Oude-Tonge Bv",
    "wof:placetype":"venue"
},
  "geometry": {"coordinates":[4.2187948227,51.6933937073],"type":"Point"}
}