{
  "type": "Feature",
  "properties": {
    "addr:full":"Ruisvoorn 16 Raamsdonksveer North Brabant 4941 SB",
    "addr:housenumber":"16",
    "addr:postcode":"4941 sb",
    "addr:street":"Ruisvoorn",
    "iso:country":"NL",
    "sg:address":"Ruisvoorn 16",
    "sg:city":"Raamsdonksveer",
    "sg:orig_category":"Lasbedrijven",
    "sg:phone":"+31 162 522 665",
    "sg:postcode":"4941 SB",
    "sg:province":"North Brabant",
    "wof:name":"Faros Bv",
    "wof:placetype":"venue"
},
  "geometry": {"coordinates":[4.87865,51.713299],"type":"Point"}
}