{
  "type": "Feature",
  "properties": {
    "addr:full":"Pannenweg 325 Nederweert Limburg 6031 RK",
    "addr:housenumber":"325",
    "addr:postcode":"6031 rk",
    "addr:street":"Pannenweg",
    "iso:country":"NL",
    "sg:address":"Pannenweg 325",
    "sg:city":"Nederweert",
    "sg:orig_category":"Meubeltextiel Fab",
    "sg:phone":"+31 495 625 707",
    "sg:postcode":"6031 RK",
    "sg:province":"Limburg",
    "wof:name":"Camp Zeilmakerij Vof",
    "wof:placetype":"venue"
},
  "geometry": {"coordinates":[5.751583,51.276093],"type":"Point"}
}