{
  "type": "Feature",
  "properties": {
    "iso:country":"NL",
    "sg:address":"Mathenesserwg 58A",
    "sg:city":"Rotterdam",
    "sg:orig_category":"Kappers",
    "sg:phone":"+31 10 437 9901",
    "sg:postcode":"3026 HD",
    "sg:province":"Zuid-Holland",
    "wof:name":"Exotica, Dames- En Herenkapsalon",
    "wof:placetype":"venue"
},
  "geometry": {"coordinates":[4.4404540062,51.9152297974],"type":"Point"}
}