{
  "type": "Feature",
  "properties": {
    "addr:full":"De Olmen 32 Spykenisse Zuid-Holland 3203 AD",
    "addr:housenumber":"32",
    "addr:postcode":"3203 ad",
    "addr:street":"De Olmen",
    "iso:country":"NL",
    "sg:address":"De Olmen 32",
    "sg:city":"Spykenisse",
    "sg:orig_category":"Logopedisten",
    "sg:phone":"+31 181 613 626",
    "sg:postcode":"3203 AD",
    "sg:province":"Zuid-Holland",
    "wof:name":"Mangnus, C",
    "wof:placetype":"venue"
},
  "geometry": {"coordinates":[4.333289,51.839935],"type":"Point"}
}