{
  "type": "Feature",
  "properties": {
    "addr:full":"Middenstr 9 S Gravenpolder Zeeland 4431 BS",
    "addr:housenumber":"9 s;4431",
    "addr:postcode":"bs",
    "addr:street":"Middenstr;Zeeland",
    "iso:country":"NL",
    "sg:address":"Middenstr 9",
    "sg:city":"S Gravenpolder",
    "sg:orig_category":"Adviesbureaus Beveiliging",
    "sg:phone":"+31 113 222 613",
    "sg:postcode":"4431 BS",
    "sg:province":"Zeeland",
    "wof:name":"Secunique",
    "wof:placetype":"venue"
},
  "geometry": {"coordinates":[3.899956,51.460968],"type":"Point"}
}