{
  "type": "Feature",
  "properties": {
    "addr:full":"Vlietplein 97 Ridderkerk Zuid-Holland 2986 GJ",
    "addr:housenumber":"97",
    "addr:postcode":"2986 gj",
    "addr:street":"Vlietplein",
    "iso:country":"NL",
    "sg:address":"Vlietplein 97",
    "sg:city":"Ridderkerk",
    "sg:classifiers":[
        {
            "category":"Shopping",
            "subcategory":"Gifts & Souvenirs",
            "type":"Retail Goods"
        }
    ],
    "sg:phone":"+31 180 426 195",
    "sg:postcode":"2986 GJ",
    "sg:province":"Zuid-Holland",
    "sg:tags":[
        "geschenken"
    ],
    "wof:name":"Onder De Toren",
    "wof:placetype":"venue"
},
  "geometry": {"coordinates":[4.619594,51.865864],"type":"Point"}
}