{
  "type": "Feature",
  "properties": {
    "addr:full":"Uiterdk 8E Zaandam Noord-Holland 1505 GW",
    "addr:housenumber":"8e",
    "addr:postcode":"1505 gw",
    "addr:street":"Uiterdk",
    "iso:country":"NL",
    "sg:address":"Uiterdk 8E",
    "sg:city":"Zaandam",
    "sg:orig_category":"Kunststoffen- Verwerkende Industrie",
    "sg:phone":"+31 75 614 5677",
    "sg:postcode":"1505 GW",
    "sg:province":"Noord-Holland",
    "sg:website":"http://www.runplastics.com",
    "wof:name":"Run Plastics Bv",
    "wof:placetype":"venue"
},
  "geometry": {"coordinates":[4.841343,52.423645],"type":"Point"}
}