{
  "type": "Feature",
  "properties": {
    "addr:full":"Tweede Emmastraat 9 Haarlem Noord-Holland 2012 GH",
    "addr:housenumber":"9",
    "addr:postcode":"2012 gh",
    "addr:street":"Tweede Emmastraat",
    "iso:country":"NL",
    "sg:address":"Tweede Emmastraat 9",
    "sg:city":"Haarlem",
    "sg:orig_category":"Schilderwerk",
    "sg:phone":"+31 23 542 5338",
    "sg:postcode":"2012 GH",
    "sg:province":"Noord-Holland",
    "wof:name":"Pr",
    "wof:placetype":"venue"
},
  "geometry": {"coordinates":[4.623278,52.375347],"type":"Point"}
}