{
  "type": "Feature",
  "properties": {
    "iso:country":"NL",
    "sg:address":"Vt Santstr 182",
    "sg:city":"Nymegen",
    "sg:orig_category":"Fotojournalisten Freelance",
    "sg:phone":"+31 24 360 4774",
    "sg:postcode":"6523 BL",
    "sg:province":"Vermont",
    "wof:name":"Kraal, Maruschka",
    "wof:placetype":"venue"
},
  "geometry": {"coordinates":[-72.451218,43.871769],"type":"Point"}
}