{
  "type": "Feature",
  "properties": {
    "addr:full":"Pastoor Schrijnenstraat 3 Velden Limburg 5941 BP",
    "addr:housenumber":"3",
    "addr:postcode":"5941 bp",
    "addr:street":"Pastoor Schrijnenstraat",
    "iso:country":"NL",
    "sg:address":"Pastoor Schrijnenstraat 3",
    "sg:city":"Velden",
    "sg:orig_category":"Loodgieterswerk, Verwarming And Sanitaire Installaties",
    "sg:phone":"+31 77 472 2853",
    "sg:postcode":"5941 BP",
    "sg:province":"Limburg",
    "wof:name":"Jopo",
    "wof:placetype":"venue"
},
  "geometry": {"coordinates":[6.169876,51.41354],"type":"Point"}
}