{
  "type": "Feature",
  "properties": {
    "iso:country":"NL",
    "sg:address":"Buitenhavenstr 5",
    "sg:city":"Oud Beyerland",
    "sg:orig_category":"Watersportartikelen",
    "sg:phone":"+31 186 619 660",
    "sg:postcode":"3262 AC",
    "sg:province":"South Holland",
    "sg:website":"http://www.katswatersport.nl",
    "wof:name":"Kats",
    "wof:placetype":"venue"
},
  "geometry": {"coordinates":[4.4112238884,51.8286476135],"type":"Point"}
}