{
  "type": "Feature",
  "properties": {
    "addr:full":"Zonnebaan 1 Utrecht Utrecht 3542 EA",
    "addr:housenumber":"1",
    "addr:postcode":"3542 ea",
    "addr:street":"Zonnebaan",
    "iso:country":"NL",
    "sg:address":"Zonnebaan 1",
    "sg:city":"Utrecht",
    "sg:orig_category":"Kabelexploitanten",
    "sg:phone":"+31 30 242 8700",
    "sg:postcode":"3542 EA",
    "sg:province":"Utrecht",
    "wof:name":"Telecai Utrecht Vof",
    "wof:placetype":"venue"
},
  "geometry": {"coordinates":[5.0396351814,52.1176872253],"type":"Point"}
}