{
  "type": "Feature",
  "properties": {
    "addr:full":"Goeman Borgesiuslaan 13 Baarn Utrecht 3741 CP",
    "addr:housenumber":"13",
    "addr:postcode":"3741 cp",
    "addr:street":"Goeman Borgesiuslaan",
    "iso:country":"NL",
    "sg:address":"Goeman Borgesiuslaan 13",
    "sg:city":"Baarn",
    "sg:orig_category":"Meubels And Huishoudapparatuur Gh",
    "sg:phone":"+31 35 542 3910",
    "sg:postcode":"3741 CP",
    "sg:province":"Utrecht",
    "wof:name":"Bv Some Vena",
    "wof:placetype":"venue"
},
  "geometry": {"coordinates":[5.285568,52.219139],"type":"Point"}
}