{
  "type": "Feature",
  "properties": {
    "addr:full":"Schouwstraat 8 Rijsenhout Noord-Holland 1435 KN",
    "addr:housenumber":"8",
    "addr:postcode":"1435 kn",
    "addr:street":"Schouwstraat",
    "iso:country":"NL",
    "sg:address":"Schouwstraat 8",
    "sg:city":"Rijsenhout",
    "sg:orig_category":"Diverse Consumentenartikelen Gh",
    "sg:phone":"+31 297 327 282",
    "sg:postcode":"1435 KN",
    "sg:province":"Noord-Holland",
    "wof:name":"Sea & Sky Supply Bv",
    "wof:placetype":"venue"
},
  "geometry": {"coordinates":[4.716269,52.258263],"type":"Point"}
}