{
  "type": "Feature",
  "properties": {
    "addr:full":"Kapelstr 43B Bussum Noord-Holland 1404 HW",
    "addr:housenumber":"43b",
    "addr:postcode":"1404 hw",
    "addr:street":"Kapelstr",
    "iso:country":"NL",
    "sg:address":"Kapelstr 43B",
    "sg:city":"Bussum",
    "sg:orig_category":"Vertalers",
    "sg:phone":"+31 35 693 9514",
    "sg:postcode":"1404 HW",
    "sg:province":"Noord-Holland",
    "wof:name":"Bella Lingua",
    "wof:placetype":"venue"
},
  "geometry": {"coordinates":[5.165332,52.273209],"type":"Point"}
}