{
  "type": "Feature",
  "properties": {
    "iso:country":"NL",
    "sg:address":"V Deysselln 55",
    "sg:city":"Groningen",
    "sg:orig_category":"Adviesbureaus Werktuigbouwkunde",
    "sg:phone":"+31 50 527 9420",
    "sg:postcode":"9721 WT",
    "sg:province":"Groningen",
    "sg:website":"http://www.etrade.nl/cad00004",
    "wof:name":"Cadence Design",
    "wof:placetype":"venue"
},
  "geometry": {"coordinates":[6.57473,53.194111],"type":"Point"}
}