{
  "type": "Feature",
  "properties": {
    "iso:country":"NL",
    "sg:address":"Wevelgemstr 9",
    "sg:city":"Amsterdam",
    "sg:orig_category":"Vertaalbureaus",
    "sg:phone":"+31 20 669 6534",
    "sg:postcode":"1066 TM",
    "sg:province":"North Holland",
    "wof:name":"Pools Collectief",
    "wof:placetype":"venue"
},
  "geometry": {"coordinates":[4.80181,52.345825],"type":"Point"}
}