{
  "type": "Feature",
  "properties": {
    "addr:full":"Asselsestraat 261 Apeldoorn Gelderland 7312 CT",
    "addr:housenumber":"261",
    "addr:postcode":"7312 ct",
    "addr:street":"Asselsestraat;Gelderland",
    "iso:country":"NL",
    "sg:address":"Asselsestraat 261",
    "sg:city":"Apeldoorn",
    "sg:orig_category":"Postkantoren",
    "sg:phone":"+31 55 355 3001",
    "sg:postcode":"7312 CT",
    "sg:province":"Gelderland",
    "wof:name":"Sigarenmagazijn Primera Biemolt",
    "wof:placetype":"venue"
},
  "geometry": {"coordinates":[5.941645,52.208572],"type":"Point"}
}