{
  "type": "Feature",
  "properties": {
    "iso:country":"NL",
    "sg:address":"Bukkumweg 17",
    "sg:city":"Hilvarenbeek",
    "sg:orig_category":"Autokeuringen",
    "sg:phone":"+31 13 505 4145",
    "sg:postcode":"5081 CT",
    "sg:province":"Noord-Brabant",
    "wof:name":"J. Abrahams Auto Elektro Bv",
    "wof:placetype":"venue"
},
  "geometry": {"coordinates":[5.143694,51.487682],"type":"Point"}
}