{
  "type": "Feature",
  "properties": {
    "iso:country":"NL",
    "sg:address":"J Van Tuinenstrjitte 32",
    "sg:city":"Berlikum Fr",
    "sg:orig_category":"Fruit And Groenten Gh",
    "sg:phone":"+31 518 462 399",
    "sg:postcode":"9041 CL",
    "sg:province":"Friesland",
    "wof:name":"K. Smits",
    "wof:placetype":"venue"
},
  "geometry": {"coordinates":[5.651869,53.2425],"type":"Point"}
}