{
  "type": "Feature",
  "properties": {
    "iso:country":"NL",
    "sg:address":"Orionstraat 55",
    "sg:city":"Tilburg",
    "sg:orig_category":"Metaalbekleding And -Behandeling",
    "sg:phone":"+31 13 544 6162",
    "sg:postcode":"5015 BR",
    "sg:province":"Noord-Brabant",
    "wof:name":"Hamers Verspanings Techniek",
    "wof:placetype":"venue"
},
  "geometry": {"coordinates":[5.112179,51.571331],"type":"Point"}
}