{
  "type": "Feature",
  "properties": {
    "addr:full":"De Star 6 Enkhuizen Noord-Holland 1601 MH",
    "addr:housenumber":"6",
    "addr:postcode":"1601 mh",
    "addr:street":"De Star",
    "iso:country":"NL",
    "sg:address":"De Star 6",
    "sg:city":"Enkhuizen",
    "sg:orig_category":"Wasmachines En Wasdrogers - Onderhoud En Reparatie",
    "sg:phone":"+31 228 530 430",
    "sg:postcode":"1601 MH",
    "sg:province":"Noord-Holland",
    "sg:website":"http://www.alfo.nl",
    "wof:name":"Alfo Service Centrale",
    "wof:placetype":"venue"
},
  "geometry": {"coordinates":[5.2693638802,52.6953620911],"type":"Point"}
}