{
  "type": "Feature",
  "properties": {
    "addr:full":"Roggelsew 55 Haelen Limburg 6081 NP",
    "addr:housenumber":"55",
    "addr:postcode":"6081 np",
    "addr:street":"Roggelsew",
    "iso:country":"NL",
    "sg:address":"Roggelsew 55",
    "sg:city":"Haelen",
    "sg:orig_category":"Groepsaccommodaties",
    "sg:phone":"+31 475 591 782",
    "sg:postcode":"6081 NP",
    "sg:province":"Limburg",
    "wof:name":"Spar, De",
    "wof:placetype":"venue"
},
  "geometry": {"coordinates":[5.94141,51.241489],"type":"Point"}
}