{
  "type": "Feature",
  "properties": {
    "addr:full":"Dilleveld 57 Veghel North Brabant 5467 KM",
    "addr:housenumber":"57",
    "addr:postcode":"5467 km",
    "addr:street":"Dilleveld",
    "iso:country":"NL",
    "sg:address":"Dilleveld 57",
    "sg:city":"Veghel",
    "sg:orig_category":"Webdesign Bureaus",
    "sg:phone":"+31 413 310 959",
    "sg:postcode":"5467 KM",
    "sg:province":"North Brabant",
    "sg:website":"http://www.reclamers.nl",
    "wof:name":"Reclamers",
    "wof:placetype":"venue"
},
  "geometry": {"coordinates":[5.5604410172,51.627407074],"type":"Point"}
}