{
  "type": "Feature",
  "properties": {
    "addr:full":"Plechelmusstr 16 Tegelen Limburg 5931 LE",
    "addr:housenumber":"16",
    "addr:postcode":"5931 le",
    "addr:street":"Plechelmusstr",
    "iso:country":"NL",
    "sg:address":"Plechelmusstr 16",
    "sg:city":"Tegelen",
    "sg:orig_category":"Voegwerken",
    "sg:phone":"+31 6 22600009",
    "sg:postcode":"5931 LE",
    "sg:province":"Limburg",
    "wof:name":"Heijnen Voeg & Restauratiewerken",
    "wof:placetype":"venue"
},
  "geometry": {"coordinates":[6.144107,51.342983],"type":"Point"}
}