{
  "type": "Feature",
  "properties": {
    "addr:full":"Broekermeerdk 39 Broek In Waterland North Holland 1151 CZ",
    "addr:housenumber":"39",
    "addr:postcode":"1151",
    "addr:street":"Broekermeerdk",
    "iso:country":"NL",
    "sg:address":"Broekermeerdk 39",
    "sg:city":"Broek In Waterland",
    "sg:orig_category":"Fitnessapparatuur",
    "sg:phone":"+31 20 403 3118",
    "sg:postcode":"1151 CZ",
    "sg:province":"North Holland",
    "sg:website":"http://www.biotrans.com",
    "wof:name":"Biotrans",
    "wof:placetype":"venue"
},
  "geometry": {"coordinates":[4.976631,52.428719],"type":"Point"}
}