{
  "type": "Feature",
  "properties": {
    "addr:full":"Bloeme Weide 14 Haarle Gem Hellend Overijssel 7448 PX",
    "addr:housenumber":"14",
    "addr:postcode":"7448 px",
    "addr:street":"Bloeme Weide;Overijssel",
    "iso:country":"NL",
    "sg:address":"Bloeme Weide 14",
    "sg:city":"Haarle Gem Hellend",
    "sg:orig_category":"Metaalbewerking",
    "sg:phone":"+31 548 595 817",
    "sg:postcode":"7448 PX",
    "sg:province":"Overijssel",
    "wof:name":"Beumer",
    "wof:placetype":"venue"
},
  "geometry": {"coordinates":[6.37823,52.360195],"type":"Point"}
}