{
  "type": "Feature",
  "properties": {
    "addr:full":"Costerweg 3 Culemborg Gelderland 4104 AJ",
    "addr:housenumber":"3",
    "addr:postcode":"4104 aj",
    "addr:street":"Costerweg;Gelderland",
    "iso:country":"NL",
    "sg:address":"Costerweg 3",
    "sg:city":"Culemborg",
    "sg:orig_category":"Boekenuitgeverijen",
    "sg:phone":"+31 345 520 709",
    "sg:postcode":"4104 AJ",
    "sg:province":"Gelderland",
    "wof:name":"Interbike Publications Bv",
    "wof:placetype":"venue"
},
  "geometry": {"coordinates":[5.205036,51.943478],"type":"Point"}
}