{
  "type": "Feature",
  "properties": {
    "addr:full":"Hoevelakenstraat 6 Tilburg Noord-Brabant 5045 GC",
    "addr:housenumber":"6",
    "addr:postcode":"5045 gc",
    "addr:street":"Hoevelakenstraat",
    "iso:country":"NL",
    "sg:address":"Hoevelakenstraat 6",
    "sg:city":"Tilburg",
    "sg:orig_category":"Wegen And Sportterreinen",
    "sg:phone":"+31 6 22571147",
    "sg:postcode":"5045 GC",
    "sg:province":"Noord-Brabant",
    "wof:name":"Van Hoof En Aarts",
    "wof:placetype":"venue"
},
  "geometry": {"coordinates":[5.0008621216,51.5846786499],"type":"Point"}
}