{
  "type": "Feature",
  "properties": {
    "addr:full":"Huizermaatwg 400 Huizen Noord-Holland 1276 LL",
    "addr:housenumber":"400",
    "addr:postcode":"1276 ll",
    "iso:country":"NL",
    "sg:address":"Huizermaatwg 400",
    "sg:city":"Huizen",
    "sg:orig_category":"Fitnesscentra",
    "sg:phone":"+31 35 526 5755",
    "sg:postcode":"1276 LL",
    "sg:province":"Noord-Holland",
    "sg:website":"http://www.betterbodies.nl",
    "wof:name":"Better Bodies Healthclubs",
    "wof:placetype":"venue"
},
  "geometry": {"coordinates":[5.25378,52.296928],"type":"Point"}
}