{
  "type": "Feature",
  "properties": {
    "addr:full":"Teteringsedk 1 Breda Noord-Brabant 4817 MA",
    "addr:housenumber":"1",
    "addr:postcode":"4817 ma",
    "addr:street":"Teteringsedk",
    "iso:country":"NL",
    "sg:address":"Teteringsedk 1",
    "sg:city":"Breda",
    "sg:orig_category":"Adviesbureaus Bedrijfsorganisatie",
    "sg:phone":"+31 76 522 2110",
    "sg:postcode":"4817 MA",
    "sg:province":"Noord-Brabant",
    "wof:name":"Nbs & D Bv",
    "wof:placetype":"venue"
},
  "geometry": {"coordinates":[4.79163,51.594219],"type":"Point"}
}