{
  "type": "Feature",
  "properties": {
    "iso:country":"NL",
    "sg:address":"Paleisweg 5",
    "sg:city":"Garderen",
    "sg:orig_category":"Farmaceutische Producten Gh",
    "sg:phone":"+31 577 461 927",
    "sg:postcode":"3886 LC",
    "sg:province":"Gelderland",
    "wof:name":"Supracom Bv",
    "wof:placetype":"venue"
},
  "geometry": {"coordinates":[5.711354,52.237877],"type":"Point"}
}