{
  "type": "Feature",
  "properties": {
    "addr:full":"Raadhuisstraat 81 Rucphen North Brabant 4715 CC",
    "addr:housenumber":"81",
    "addr:postcode":"4715 cc",
    "addr:street":"Raadhuisstraat",
    "iso:country":"NL",
    "sg:address":"Raadhuisstraat 81",
    "sg:city":"Rucphen",
    "sg:orig_category":"Autokeuringen",
    "sg:phone":"+31 165 343 776",
    "sg:postcode":"4715 CC",
    "sg:province":"North Brabant",
    "wof:name":"Garage- En Benzinestation Verbraak Vof",
    "wof:placetype":"venue"
},
  "geometry": {"coordinates":[4.564727,51.532421],"type":"Point"}
}