{
  "type": "Feature",
  "properties": {
    "addr:full":"Mastenmakerswg 1 Den Helder Noord-Holland 1786 PB",
    "addr:housenumber":"1",
    "addr:postcode":"1786 pb",
    "addr:street":"Mastenmakerswg",
    "iso:country":"NL",
    "sg:address":"Mastenmakerswg 1",
    "sg:city":"Den Helder",
    "sg:orig_category":"On- Offshore",
    "sg:phone":"+31 223 670 000",
    "sg:postcode":"1786 PB",
    "sg:province":"Noord-Holland",
    "wof:name":"Frank Int Bv",
    "wof:placetype":"venue"
},
  "geometry": {"coordinates":[4.778196,52.913616],"type":"Point"}
}