{
  "type": "Feature",
  "properties": {
    "iso:country":"NL",
    "sg:address":"Essendreef 74",
    "sg:city":"Gouderak",
    "sg:orig_category":"Fotoreportages",
    "sg:phone":"+31 182 372 135",
    "sg:postcode":"2831 XN",
    "sg:province":"South Holland",
    "wof:name":"Breen, Ilse",
    "wof:placetype":"venue"
},
  "geometry": {"coordinates":[4.679894,51.983196],"type":"Point"}
}