{
  "type": "Feature",
  "properties": {
    "addr:full":"Helftheuvelweg 95 'S Hertogenbosch Noord-Brabant 5224 AS",
    "addr:housenumber":"95",
    "addr:postcode":"5224 as",
    "addr:street":"Helftheuvelweg;' S",
    "iso:country":"NL",
    "sg:address":"Helftheuvelweg 95",
    "sg:city":"'S Hertogenbosch",
    "sg:orig_category":"Autokeuringen",
    "sg:phone":"+31 73 621 3748",
    "sg:postcode":"5224 AS",
    "sg:province":"Noord-Brabant",
    "wof:name":"Shell",
    "wof:placetype":"venue"
},
  "geometry": {"coordinates":[5.261355,51.69355],"type":"Point"}
}