{
  "type": "Feature",
  "properties": {
    "addr:full":"Broederenstr 47 Deventer NL.08 7411 LB",
    "addr:housenumber":"47;nl.08",
    "addr:postcode":"7411 lb",
    "addr:street":"Broederenstr",
    "iso:country":"NL",
    "sg:address":"Broederenstr 47",
    "sg:city":"Deventer",
    "sg:orig_category":"Verlichting",
    "sg:phone":"+31 570 618 500",
    "sg:postcode":"7411 LB",
    "sg:province":"NL.08",
    "wof:name":"Lampenier",
    "wof:placetype":"venue"
},
  "geometry": {"coordinates":[6.1564,52.25404],"type":"Point"}
}