{
  "type": "Feature",
  "properties": {
    "addr:full":"Warmoesstr 65 Zwolle Overijssel 8021 BX",
    "addr:housenumber":"65",
    "addr:postcode":"8021 bx",
    "addr:street":"Warmoesstr",
    "iso:country":"NL",
    "sg:address":"Warmoesstr 65",
    "sg:city":"Zwolle",
    "sg:orig_category":"Webdesign Bureaus",
    "sg:phone":"+31 38 454 3576",
    "sg:postcode":"8021 BX",
    "sg:province":"Overijssel",
    "sg:website":"http://www.mcwdesign.nl",
    "wof:name":"`Mcw Design",
    "wof:placetype":"venue"
},
  "geometry": {"coordinates":[6.1038341522,52.5179481506],"type":"Point"}
}