{
  "type": "Feature",
  "properties": {
    "addr:full":"Den Sliem 41 Groenlo Gelderland 7141 JE",
    "addr:housenumber":"41",
    "addr:postcode":"7141 je",
    "addr:street":"Den Sliem;Gelderland",
    "iso:country":"NL",
    "sg:address":"Den Sliem 41",
    "sg:city":"Groenlo",
    "sg:orig_category":"Machinefabrieken",
    "sg:phone":"+31 544 461 294",
    "sg:postcode":"7141 JE",
    "sg:province":"Gelderland",
    "wof:name":"Smidse Groenlo, De",
    "wof:placetype":"venue"
},
  "geometry": {"coordinates":[6.604695,52.041557],"type":"Point"}
}