{
  "type": "Feature",
  "properties": {
    "iso:country":"NL",
    "sg:address":"Wieder 21",
    "sg:city":"De Goorn",
    "sg:orig_category":"Loodgieterswerk, Verwarming And Sanitaire Installaties",
    "sg:phone":"+31 229 542 304",
    "sg:postcode":"1648 GA",
    "sg:province":"Noord-Holland",
    "wof:name":"Installatieburo Beuling Blom Bv",
    "wof:placetype":"venue"
},
  "geometry": {"coordinates":[4.959868,52.624424],"type":"Point"}
}