{
  "type": "Feature",
  "properties": {
    "addr:full":"Dorpsstraat 1 Twello Gelderland 7391 DC",
    "addr:housenumber":"1",
    "addr:postcode":"7391",
    "addr:street":"Dorpsstraat;Gelderland",
    "iso:country":"NL",
    "sg:address":"Dorpsstraat 1",
    "sg:city":"Twello",
    "sg:orig_category":"Vers Brood And Banket Fab",
    "sg:phone":"+31 571 273 974",
    "sg:postcode":"7391 DC",
    "sg:province":"Gelderland",
    "wof:name":"Euro Patisserie Producties Twello Bv",
    "wof:placetype":"venue"
},
  "geometry": {"coordinates":[6.107192,52.238556],"type":"Point"}
}