{
  "type": "Feature",
  "properties": {
    "iso:country":"NL",
    "sg:address":"Dillenburgln 6",
    "sg:city":"Groningen",
    "sg:orig_category":"Adviesbureaus Bedrijfsorganisatie",
    "sg:phone":"+31 50 311 2212",
    "sg:postcode":"9717 CA",
    "sg:province":"Groningen",
    "wof:name":"Boer, G P De",
    "wof:placetype":"venue"
},
  "geometry": {"coordinates":[6.552214,53.220535],"type":"Point"}
}