{
  "type": "Feature",
  "properties": {
    "addr:full":"Westeinde 43 Zevenaar Gelderland 6904 AB",
    "addr:housenumber":"43",
    "addr:postcode":"6904 ab",
    "addr:street":"Westeinde",
    "iso:country":"NL",
    "sg:address":"Westeinde 43",
    "sg:city":"Zevenaar",
    "sg:orig_category":"Kunststofverpakkingen Fab",
    "sg:phone":"+31 316 343 343",
    "sg:postcode":"6904 AB",
    "sg:province":"Gelderland",
    "wof:name":"Aeroplas Bv",
    "wof:placetype":"venue"
},
  "geometry": {"coordinates":[6.076878,51.931618],"type":"Point"}
}