{
  "type": "Feature",
  "properties": {
    "addr:full":"Valkstr 39 Wormer Noord-Holland 1531 CX",
    "addr:housenumber":"39",
    "addr:postcode":"1531 cx",
    "addr:street":"Valkstr",
    "iso:country":"NL",
    "sg:address":"Valkstr 39",
    "sg:city":"Wormer",
    "sg:orig_category":"Beveiliging",
    "sg:phone":"+31 75 642 2706",
    "sg:postcode":"1531 CX",
    "sg:province":"Noord-Holland",
    "sg:website":"http://www.dogsecurityholland.nl",
    "wof:name":"Dog Holland",
    "wof:placetype":"venue"
},
  "geometry": {"coordinates":[4.811902,52.496059],"type":"Point"}
}