{
  "type": "Feature",
  "properties": {
    "addr:full":"Oudegr 60Bis Utrecht Utrecht 3511 AS",
    "addr:housenumber":"60bis",
    "addr:postcode":"3511 as",
    "iso:country":"NL",
    "sg:address":"Oudegr 60Bis",
    "sg:city":"Utrecht",
    "sg:orig_category":"Administratie- En Boekhoudkantoren",
    "sg:phone":"+31 30 231 5508",
    "sg:postcode":"3511 AS",
    "sg:province":"Utrecht",
    "wof:name":"Obbens, A",
    "wof:placetype":"venue"
},
  "geometry": {"coordinates":[5.116603,52.094704],"type":"Point"}
}