{
  "type": "Feature",
  "properties": {
    "addr:full":"Beethovenstraat 65 Amsterdam Noord-Holland 1077 HN",
    "addr:housenumber":"65",
    "addr:postcode":"1077 hn",
    "addr:street":"Beethovenstraat",
    "iso:country":"NL",
    "sg:address":"Beethovenstraat 65",
    "sg:city":"Amsterdam",
    "sg:classifiers":[
        {
            "category":"Retail",
            "subcategory":"Photofinishing",
            "type":"Services"
        }
    ],
    "sg:phone":"+31 20 679 0635",
    "sg:postcode":"1077 HN",
    "sg:province":"Noord-Holland",
    "sg:tags":[
        "foto",
        "film"
    ],
    "wof:name":"Super Photo Snelservice",
    "wof:placetype":"venue"
},
  "geometry": {"coordinates":[4.877049,52.347534],"type":"Point"}
}