{
  "type": "Feature",
  "properties": {
    "addr:full":"Tiendstr 8 St Geertruid Limburg 6265 AP",
    "addr:housenumber":"8",
    "addr:postcode":"6265 ap",
    "addr:street":"Tiendstr",
    "iso:country":"NL",
    "sg:address":"Tiendstr 8",
    "sg:city":"St Geertruid",
    "sg:orig_category":"Kappers",
    "sg:phone":"+31 43 408 3302",
    "sg:postcode":"6265 AP",
    "sg:province":"Limburg",
    "wof:name":"Nicole",
    "wof:placetype":"venue"
},
  "geometry": {"coordinates":[5.769564,50.795296],"type":"Point"}
}