{
  "type": "Feature",
  "properties": {
    "addr:full":"Delftsewallen 18 Zoetermeer Zuid-Holland 2712 AS",
    "addr:housenumber":"18",
    "addr:postcode":"2712 as",
    "addr:street":"Delftsewallen",
    "iso:country":"NL",
    "sg:address":"Delftsewallen 18",
    "sg:city":"Zoetermeer",
    "sg:orig_category":"Onroerende Goederen",
    "sg:phone":"+31 79 316 5452",
    "sg:postcode":"2712 AS",
    "sg:province":"Zuid-Holland",
    "wof:name":"Boezem Bv",
    "wof:placetype":"venue"
},
  "geometry": {"coordinates":[4.494893,52.05592],"type":"Point"}
}