{
  "type": "Feature",
  "properties": {
    "addr:full":"De Trompet 1344 Heemskerk Noord-Holland 1967 DA",
    "addr:housenumber":"1344",
    "addr:postcode":"heemskerk;1967 da",
    "addr:street":"De Trompet",
    "iso:country":"NL",
    "sg:address":"De Trompet 1344",
    "sg:city":"Heemskerk",
    "sg:orig_category":"Geluidsinstallaties",
    "sg:phone":"+31 251 211 622",
    "sg:postcode":"1967 DA",
    "sg:province":"Noord-Holland",
    "sg:website":"http://www.m-sound.com",
    "wof:name":"M-Sound",
    "wof:placetype":"venue"
},
  "geometry": {"coordinates":[4.701124,52.50378],"type":"Point"}
}