{
  "type": "Feature",
  "properties": {
    "addr:full":"J Kwastln 70 Wognum Noord-Holland 1687 BN",
    "addr:housenumber":"70",
    "addr:postcode":"1687 bn",
    "iso:country":"NL",
    "sg:address":"J Kwastln 70",
    "sg:city":"Wognum",
    "sg:orig_category":"Vertaalbureaus",
    "sg:phone":"+31 229 575 237",
    "sg:postcode":"1687 BN",
    "sg:province":"Noord-Holland",
    "wof:name":"Pevodu",
    "wof:placetype":"venue"
},
  "geometry": {"coordinates":[5.017532,52.685684],"type":"Point"}
}