{
  "type": "Feature",
  "properties": {
    "iso:country":"NL",
    "sg:address":"Kruisstr 68",
    "sg:city":"Veldhoven",
    "sg:orig_category":"Montagebedrijven",
    "sg:phone":"+31 6 22496515",
    "sg:postcode":"5502 JG",
    "sg:province":"Noord-Brabant",
    "wof:name":"Swinkels, Montagebedrijf",
    "wof:placetype":"venue"
},
  "geometry": {"coordinates":[5.418154,51.427876],"type":"Point"}
}