{
  "type": "Feature",
  "properties": {
    "addr:full":"Eerselsedk 2 Bergeyk North Brabant 5571 CM",
    "addr:housenumber":"2",
    "addr:postcode":"5571 cm",
    "addr:street":"Eerselsedk",
    "iso:country":"NL",
    "sg:address":"Eerselsedk 2",
    "sg:city":"Bergeyk",
    "sg:orig_category":"Bejaarden - Verzorgingstehuizen",
    "sg:phone":"+31 497 579 300",
    "sg:postcode":"5571 CM",
    "sg:province":"North Brabant",
    "wof:name":"Joseph Zorgcentr, St",
    "wof:placetype":"venue"
},
  "geometry": {"coordinates":[5.359703,51.32383],"type":"Point"}
}