{
  "type": "Feature",
  "properties": {
    "addr:full":"Bijlandseweg 30 Tolkamer Gelderland 6916 BJ",
    "addr:housenumber":"30",
    "addr:postcode":"6916 bj",
    "addr:street":"Bijlandseweg;Gelderland",
    "iso:country":"NL",
    "sg:address":"Bijlandseweg 30",
    "sg:city":"Tolkamer",
    "sg:orig_category":"Pleziervaartuigen And Reparatie",
    "sg:phone":"+31 316 541 041",
    "sg:postcode":"6916 BJ",
    "sg:province":"Gelderland",
    "wof:name":"Reparatiebedrijf Markerink Bv",
    "wof:placetype":"venue"
},
  "geometry": {"coordinates":[6.093736,51.856686],"type":"Point"}
}