{
  "type": "Feature",
  "properties": {
    "iso:country":"NL",
    "sg:address":"Brouwersgr 68",
    "sg:city":"Amsterdam",
    "sg:orig_category":"Verlichting",
    "sg:phone":"+31 20 638 1047",
    "sg:postcode":"1013 GX",
    "sg:province":"North Holland",
    "wof:name":"Vanderhee",
    "wof:placetype":"venue"
},
  "geometry": {"coordinates":[4.891115,52.379631],"type":"Point"}
}