{
  "type": "Feature",
  "properties": {
    "addr:full":"Ijsseldijk Noord 172 Ouderkerk A/D Ijssel Zuid-Holland 2935 BM",
    "addr:housenumber":"172;a / d",
    "addr:postcode":"2935 bm",
    "addr:street":"Ijsseldijk Noord",
    "iso:country":"NL",
    "sg:address":"Ijsseldijk Noord 172",
    "sg:city":"Ouderkerk A/D Ijssel",
    "sg:orig_category":"Hout Gh",
    "sg:phone":"+31 180 688 688",
    "sg:postcode":"2935 BM",
    "sg:province":"Zuid-Holland",
    "wof:name":"Houthandel H. En P.H. Heuvelman Bv",
    "wof:placetype":"venue"
},
  "geometry": {"coordinates":[4.642594,51.95171],"type":"Point"}
}