{
  "type": "Feature",
  "properties": {
    "addr:full":"Bilderdijkkd 50 Amsterdam Noord-Holland 1053 VN",
    "addr:housenumber":"50",
    "addr:postcode":"1053 vn",
    "addr:street":"Bilderdijkkd",
    "iso:country":"NL",
    "sg:address":"Bilderdijkkd 50",
    "sg:city":"Amsterdam",
    "sg:orig_category":"Oud Metaal",
    "sg:phone":"+31 20 616 9538",
    "sg:postcode":"1053 VN",
    "sg:province":"Noord-Holland",
    "wof:name":"Kapteijn Sr",
    "wof:placetype":"venue"
},
  "geometry": {"coordinates":[4.8673300743,52.3666381836],"type":"Point"}
}