{
  "type": "Feature",
  "properties": {
    "addr:full":"Grt Wade 21C Nieuwegein Utrecht 3439 NX",
    "addr:housenumber":"21c",
    "addr:postcode":"3439 nx",
    "addr:street":"Wade",
    "iso:country":"NL",
    "sg:address":"Grt Wade 21C",
    "sg:city":"Nieuwegein",
    "sg:orig_category":"Administratie- En Boekhoudkantoren",
    "sg:phone":"+31 30 267 2321",
    "sg:postcode":"3439 NX",
    "sg:province":"Utrecht",
    "wof:name":"B & E Partners In Adm Verbetering",
    "wof:placetype":"venue"
},
  "geometry": {"coordinates":[5.112533,52.048363],"type":"Point"}
}