{
  "type": "Feature",
  "properties": {
    "addr:full":"Laan 1914 35 Amersfoort Utrecht 3818 EX",
    "addr:housenumber":"35",
    "addr:postcode":"3818 ex",
    "addr:street":"Laan 1914",
    "iso:country":"NL",
    "sg:address":"Laan 1914 35",
    "sg:city":"Amersfoort",
    "sg:orig_category":"Architecten",
    "sg:phone":"+31 33 468 2700",
    "sg:postcode":"3818 EX",
    "sg:province":"Utrecht",
    "wof:name":"Dhv Milieu & Infrastructuur Bv",
    "wof:placetype":"venue"
},
  "geometry": {"coordinates":[5.367721,52.132854],"type":"Point"}
}