{
  "type": "Feature",
  "properties": {
    "addr:full":"De S Lohmanln 56 Papendrecht South Holland 3354 AS",
    "addr:housenumber":"56",
    "addr:postcode":"3354 as",
    "addr:street":"De",
    "iso:country":"NL",
    "sg:address":"De S Lohmanln 56",
    "sg:city":"Papendrecht",
    "sg:orig_category":"Fietsen En Bromfietsen",
    "sg:phone":"+31 78 641 1018",
    "sg:postcode":"3354 AS",
    "sg:province":"South Holland",
    "wof:name":"Nedbike",
    "wof:placetype":"venue"
},
  "geometry": {"coordinates":[4.699596,51.828571],"type":"Point"}
}