{
  "type": "Feature",
  "properties": {
    "addr:full":"Hamersveldsewg 141 Leusden Utrecht 3833 GN",
    "addr:housenumber":"141",
    "addr:postcode":"3833 gn",
    "iso:country":"NL",
    "sg:address":"Hamersveldsewg 141",
    "sg:city":"Leusden",
    "sg:orig_category":"Biljarts - Fabrieken",
    "sg:phone":"+31 33 432 5096",
    "sg:postcode":"3833 GN",
    "sg:province":"Utrecht",
    "wof:name":"Biljartsport West- En Midden-, Nederland",
    "wof:placetype":"venue"
},
  "geometry": {"coordinates":[5.422402,52.11742],"type":"Point"}
}