{
  "type": "Feature",
  "properties": {
    "addr:full":"Hartogsweg 25 Ijsselmuiden NL.08 8271 PE",
    "addr:housenumber":"25;nl.08",
    "addr:postcode":"8271 pe",
    "addr:street":"Hartogsweg",
    "iso:country":"NL",
    "sg:address":"Hartogsweg 25",
    "sg:city":"Ijsselmuiden",
    "sg:orig_category":"Granen, Zaden And Diervoeders Gh",
    "sg:phone":"+31 38 344 6410",
    "sg:postcode":"8271 PE",
    "sg:province":"NL.08",
    "wof:name":"Firma Van De Belt Fourages",
    "wof:placetype":"venue"
},
  "geometry": {"coordinates":[5.959281,52.582584],"type":"Point"}
}