{
  "type": "Feature",
  "properties": {
    "addr:full":"St Agnetenwg 42 Nymegen Gelderland 6545 AW",
    "addr:housenumber":"42",
    "addr:postcode":"6545 aw",
    "addr:street":"Nymegen Gelderland",
    "iso:country":"NL",
    "sg:address":"St Agnetenwg 42",
    "sg:city":"Nymegen",
    "sg:orig_category":"Verzekeringen - Verzekeringskantoren",
    "sg:phone":"+31 24 373 4545",
    "sg:postcode":"6545 AW",
    "sg:province":"Gelderland",
    "wof:name":"Goeij, De",
    "wof:placetype":"venue"
},
  "geometry": {"coordinates":[5.804684,51.832024],"type":"Point"}
}