{
  "type": "Feature",
  "properties": {
    "addr:full":"Nassauhaven 168 Rotterdam Zuid-Holland 3071 JK",
    "addr:housenumber":"168",
    "addr:postcode":"3071 jk",
    "addr:street":"Nassauhaven",
    "iso:country":"NL",
    "sg:address":"Nassauhaven 168",
    "sg:city":"Rotterdam",
    "sg:orig_category":"Drogisterijen",
    "sg:phone":"+31 10 485 9429",
    "sg:postcode":"3071 JK",
    "sg:province":"Zuid-Holland",
    "wof:name":"Expolease",
    "wof:placetype":"venue"
},
  "geometry": {"coordinates":[4.505924,51.912605],"type":"Point"}
}