{
  "type": "Feature",
  "properties": {
    "addr:full":"Op De Heugden 10 Landgraaf Limburg 6371 XM",
    "addr:housenumber":"10",
    "addr:postcode":"6371 xm",
    "addr:street":"Op De Heugden",
    "iso:country":"NL",
    "sg:address":"Op De Heugden 10",
    "sg:city":"Landgraaf",
    "sg:orig_category":"Boekhouders",
    "sg:phone":"+31 45 532 3565",
    "sg:postcode":"6371 XM",
    "sg:province":"Limburg",
    "wof:name":"D & P Administratie",
    "wof:placetype":"venue"
},
  "geometry": {"coordinates":[6.017522,50.899391],"type":"Point"}
}