{
  "type": "Feature",
  "properties": {
    "addr:full":"Pastoor Van Laakstraat 92 Lent Virginia 6663 CC",
    "addr:housenumber":"92",
    "addr:postcode":"6663 cc",
    "addr:street":"Pastoor Van Laakstraat",
    "iso:country":"NL",
    "sg:address":"Pastoor Van Laakstraat 92",
    "sg:city":"Lent",
    "sg:orig_category":"Autokeuringen",
    "sg:phone":"+31 24 360 5959",
    "sg:postcode":"6663 CC",
    "sg:province":"Virginia",
    "wof:name":"Automobielbedrijf De Waalsprong",
    "wof:placetype":"venue"
},
  "geometry": {"coordinates":[-77.241432,38.151344],"type":"Point"}
}