{
  "type": "Feature",
  "properties": {
    "addr:full":"Ubaksland 10 Staphorst Overijssel 7951 GL",
    "addr:housenumber":"10",
    "addr:postcode":"7951 gl",
    "addr:street":"Ubaksland",
    "iso:country":"NL",
    "sg:address":"Ubaksland 10",
    "sg:city":"Staphorst",
    "sg:orig_category":"Webdesign Bureaus",
    "sg:phone":"+31 522 461 721",
    "sg:postcode":"7951 GL",
    "sg:province":"Overijssel",
    "wof:name":"Schraa",
    "wof:placetype":"venue"
},
  "geometry": {"coordinates":[6.2147388458,52.6445274353],"type":"Point"}
}