{
  "type": "Feature",
  "properties": {
    "addr:full":"Rykswg 127A Limmen Noord-Holland 1906 BG",
    "addr:housenumber":"127a",
    "addr:postcode":"1906",
    "iso:country":"NL",
    "sg:address":"Rykswg 127A",
    "sg:city":"Limmen",
    "sg:orig_category":"Woninginrichting",
    "sg:phone":"+31 72 505 1602",
    "sg:postcode":"1906 BG",
    "sg:province":"Noord-Holland",
    "wof:name":"Gerton Limmen",
    "wof:placetype":"venue"
},
  "geometry": {"coordinates":[25.4915904999,42.7297592163],"type":"Point"}
}