{
  "type": "Feature",
  "properties": {
    "addr:full":"Postbus 25000 Hilversum Noord-Holland 1202 HB",
    "addr:postcode":"25000;1202 hb",
    "addr:street":"Postbus",
    "iso:country":"NL",
    "sg:address":"Postbus 25000",
    "sg:city":"Hilversum",
    "sg:orig_category":"Omroep",
    "sg:phone":"+31 35 671 9911",
    "sg:postcode":"1202 HB",
    "sg:province":"Noord-Holland",
    "sg:website":"http://www.omroep.nl/ncrv",
    "wof:name":"Ncrv",
    "wof:placetype":"venue"
},
  "geometry": {"coordinates":[5.171,52.223991],"type":"Point"}
}