{
  "type": "Feature",
  "properties": {
    "addr:full":"Laan Van Welgelegen 127 Werkendam North Brabant 4251 KL",
    "addr:housenumber":"127",
    "addr:postcode":"4251 kl",
    "addr:street":"Laan Van Welgelegen",
    "iso:country":"NL",
    "sg:address":"Laan Van Welgelegen 127",
    "sg:city":"Werkendam",
    "sg:orig_category":"Verhuur Bouwmachines",
    "sg:phone":"+31 183 502 466",
    "sg:postcode":"4251 KL",
    "sg:province":"North Brabant",
    "wof:name":"J.H. Kapel",
    "wof:placetype":"venue"
},
  "geometry": {"coordinates":[4.883612,51.804962],"type":"Point"}
}