{
  "type": "Feature",
  "properties": {
    "iso:country":"NL",
    "sg:address":"Zuidzydsedk 98",
    "sg:city":"Hoogvliet Rt",
    "sg:orig_category":"Grafisch Ontwerpers",
    "sg:phone":"+31 10 416 2330",
    "sg:postcode":"3194 ND",
    "sg:province":"South Holland",
    "sg:website":"http://www.fransformatie.nl",
    "wof:name":"Fransformatie",
    "wof:placetype":"venue"
},
  "geometry": {"coordinates":[4.37092,51.864979],"type":"Point"}
}