{
  "type": "Feature",
  "properties": {
    "addr:full":"Solwerderstraat 51 Appingedam Groningen 9901 BB",
    "addr:housenumber":"51",
    "addr:postcode":"9901 bb",
    "addr:street":"Solwerderstraat",
    "iso:country":"NL",
    "sg:address":"Solwerderstraat 51",
    "sg:city":"Appingedam",
    "sg:classifiers":[
        {
            "category":"Retail",
            "subcategory":"Photofinishing",
            "type":"Services"
        }
    ],
    "sg:phone":"+31 596 622 404",
    "sg:postcode":"9901 BB",
    "sg:province":"Groningen",
    "sg:tags":[
        "foto",
        "film"
    ],
    "wof:name":"Foto-Video De Vries",
    "wof:placetype":"venue"
},
  "geometry": {"coordinates":[6.85928,53.321606],"type":"Point"}
}