{
  "type": "Feature",
  "properties": {
    "addr:full":"Ratumsestr 146 Winterswijk Gelderland 7101 MV",
    "addr:housenumber":"146",
    "addr:postcode":"7101 mv",
    "addr:street":"Gelderland",
    "iso:country":"NL",
    "sg:address":"Ratumsestr 146",
    "sg:city":"Winterswijk",
    "sg:orig_category":"Verenigingsgebouwen",
    "sg:phone":"+31 543 515 078",
    "sg:postcode":"7101 MV",
    "sg:province":"Gelderland",
    "wof:name":"Irene",
    "wof:placetype":"venue"
},
  "geometry": {"coordinates":[6.723831,51.971889],"type":"Point"}
}