{
  "type": "Feature",
  "properties": {
    "addr:full":"Pesthuisln 30 Amsterdam North Holland 1054 RL",
    "addr:housenumber":"30",
    "addr:postcode":"1054 rl",
    "addr:street":"Pesthuisln",
    "iso:country":"NL",
    "sg:address":"Pesthuisln 30",
    "sg:city":"Amsterdam",
    "sg:orig_category":"Verenigingen En Stichtingen",
    "sg:phone":"+31 20 612 9271",
    "sg:postcode":"1054 RL",
    "sg:province":"North Holland",
    "wof:name":"Lachende Beer, Sticht De",
    "wof:placetype":"venue"
},
  "geometry": {"coordinates":[4.86857,52.361408],"type":"Point"}
}