{
  "type": "Feature",
  "properties": {
    "addr:full":"Paul Krugerweg 50 Ermelo Gelderland 3851 ZJ",
    "addr:housenumber":"50",
    "addr:postcode":"3851 zj",
    "addr:street":"Paul Krugerweg;Gelderland",
    "iso:country":"NL",
    "sg:address":"Paul Krugerweg 50",
    "sg:city":"Ermelo",
    "sg:orig_category":"Volwassenenonderwijs",
    "sg:phone":"+31 341 551 753",
    "sg:postcode":"3851 ZJ",
    "sg:province":"Gelderland",
    "wof:name":"Christelijk College Groevenbeek",
    "wof:placetype":"venue"
},
  "geometry": {"coordinates":[5.621805,52.289005],"type":"Point"}
}