{
  "type": "Feature",
  "properties": {
    "addr:full":"Alard Du Hamelstraat 33 Eindhoven Noord-Brabant 5622 CC",
    "addr:housenumber":"33",
    "addr:postcode":"5622 cc",
    "addr:street":"Alard Du Hamelstraat",
    "iso:country":"NL",
    "sg:address":"Alard Du Hamelstraat 33",
    "sg:city":"Eindhoven",
    "sg:orig_category":"Artsen And Specialisten",
    "sg:phone":"+31 40 243 3300",
    "sg:postcode":"5622 CC",
    "sg:province":"Noord-Brabant",
    "wof:name":"H.J.M. Jentjens",
    "wof:placetype":"venue"
},
  "geometry": {"coordinates":[5.460354,51.459599],"type":"Point"}
}