{
  "type": "Feature",
  "properties": {
    "addr:full":"Stadsmolen 155 Maassluis Zuid-Holland 3146 CV",
    "addr:housenumber":"155",
    "addr:postcode":"3146 cv",
    "addr:street":"Stadsmolen",
    "iso:country":"NL",
    "sg:address":"Stadsmolen 155",
    "sg:city":"Maassluis",
    "sg:orig_category":"Goederenvervoer Over De Weg",
    "sg:phone":"+31 10 592 6782",
    "sg:postcode":"3146 CV",
    "sg:province":"Zuid-Holland",
    "wof:name":"Rdb",
    "wof:placetype":"venue"
},
  "geometry": {"coordinates":[4.225898,51.94083],"type":"Point"}
}