{
  "type": "Feature",
  "properties": {
    "iso:country":"NL",
    "sg:address":"Antoniusstraat 14",
    "sg:city":"Ell",
    "sg:orig_category":"Goederenvervoer Over De Weg",
    "sg:phone":"+31 495 551 988",
    "sg:postcode":"6011 SE",
    "sg:province":"Texas",
    "wof:name":"F. Vries Transport",
    "wof:placetype":"venue"
},
  "geometry": {"coordinates":[-98.101067,27.527],"type":"Point"}
}