{
  "type": "Feature",
  "properties": {
    "addr:full":"Hoofdstr 89 Valkenburg Zh Zuid-Holland 2235 CD",
    "addr:housenumber":"89",
    "addr:postcode":"2235 cd",
    "addr:street":"Hoofdstr",
    "iso:country":"NL",
    "sg:address":"Hoofdstr 89",
    "sg:city":"Valkenburg Zh",
    "sg:orig_category":"Poetsmaterialen - Fabrieken En Groothandel",
    "sg:phone":"+31 71 407 5964",
    "sg:postcode":"2235 CD",
    "sg:province":"Zuid-Holland",
    "wof:name":"Clean Formule",
    "wof:placetype":"venue"
},
  "geometry": {"coordinates":[4.437215,52.177273],"type":"Point"}
}