{
  "type": "Feature",
  "properties": {
    "addr:full":"St Lambertuswg 54 Gemonde Noord-Brabant 5291 AC",
    "addr:housenumber":"54",
    "addr:postcode":"5291 ac",
    "iso:country":"NL",
    "sg:address":"St Lambertuswg 54",
    "sg:city":"Gemonde",
    "sg:orig_category":"Begrafenisverzorging",
    "sg:phone":"+31 73 551 4227",
    "sg:postcode":"5291 AC",
    "sg:province":"Noord-Brabant",
    "wof:name":"Lbu",
    "wof:placetype":"venue"
},
  "geometry": {"coordinates":[5.354525,51.615467],"type":"Point"}
}