{
  "type": "Feature",
  "properties": {
    "addr:full":"Stationsstr 20 Tiel Gelderland 4001 CE",
    "addr:housenumber":"20",
    "addr:postcode":"4001 ce",
    "addr:street":"Stationsstr;Gelderland",
    "iso:country":"NL",
    "sg:address":"Stationsstr 20",
    "sg:city":"Tiel",
    "sg:orig_category":"Beeldende Kunstenaars",
    "sg:phone":"+31 344 613 572",
    "sg:postcode":"4001 CE",
    "sg:province":"Gelderland",
    "wof:name":"Graaf-Van Der Gaag, A De",
    "wof:placetype":"venue"
},
  "geometry": {"coordinates":[5.430696,51.888096],"type":"Point"}
}