{
  "type": "Feature",
  "properties": {
    "addr:full":"Westerblokker 179 Blokker Noord-Holland 1695 AE",
    "addr:housenumber":"179",
    "addr:postcode":"1695 ae",
    "addr:street":"Westerblokker",
    "iso:country":"NL",
    "sg:address":"Westerblokker 179",
    "sg:city":"Blokker",
    "sg:orig_category":"Huizensloop And Bouwrijp Maken",
    "sg:phone":"+31 229 232 845",
    "sg:postcode":"1695 AE",
    "sg:province":"Noord-Holland",
    "wof:name":"Hans Visser Machinale Grondbewerking",
    "wof:placetype":"venue"
},
  "geometry": {"coordinates":[5.075538,52.656719],"type":"Point"}
}