{
  "type": "Feature",
  "properties": {
    "addr:full":"Reijckenborg 51 Maastricht Limburg 6228 CT",
    "addr:housenumber":"51",
    "addr:postcode":"6228 ct",
    "addr:street":"Reijckenborg",
    "iso:country":"NL",
    "sg:address":"Reijckenborg 51",
    "sg:city":"Maastricht",
    "sg:orig_category":"Verzekeringen",
    "sg:phone":"+31 43 361 6395",
    "sg:postcode":"6228 CT",
    "sg:province":"Limburg",
    "wof:name":"Maaf-Assurantien",
    "wof:placetype":"venue"
},
  "geometry": {"coordinates":[5.724347,50.823898],"type":"Point"}
}