{
  "type": "Feature",
  "properties": {
    "iso:country":"NL",
    "sg:address":"Boendermakerstr 19",
    "sg:city":"Breukelen Ut",
    "sg:orig_category":"Fotoarchieven",
    "sg:phone":"+31 346 264 852",
    "sg:postcode":"3621 CX",
    "sg:province":"Utrecht",
    "wof:name":"Leijen, Henk",
    "wof:placetype":"venue"
},
  "geometry": {"coordinates":[4.997171,52.169842],"type":"Point"}
}