{
  "type": "Feature",
  "properties": {
    "addr:full":"Robrechtstraat 19 Heusden Gem Heusden Noord-Brabant 5256 GN",
    "addr:housenumber":"19",
    "addr:postcode":"5256 gn",
    "addr:street":"Robrechtstraat",
    "iso:country":"NL",
    "sg:address":"Robrechtstraat 19",
    "sg:city":"Heusden Gem Heusden",
    "sg:orig_category":"Fotografische And Optische Artikelen Gh",
    "sg:phone":"+31 416 662 484",
    "sg:postcode":"5256 GN",
    "sg:province":"Noord-Brabant",
    "wof:name":"Rife Optical Instruments",
    "wof:placetype":"venue"
},
  "geometry": {"coordinates":[5.137429,51.72374],"type":"Point"}
}