{
  "type": "Feature",
  "properties": {
    "addr:full":"Staalwg 15 Culemborg Gelderland 4104 AS",
    "addr:housenumber":"15",
    "addr:postcode":"4104 as",
    "addr:street":"Staalwg;Gelderland",
    "iso:country":"NL",
    "sg:address":"Staalwg 15",
    "sg:city":"Culemborg",
    "sg:orig_category":"Meubellakkerijen En -Spuiterijen",
    "sg:phone":"+31 345 519 222",
    "sg:postcode":"4104 AS",
    "sg:province":"Gelderland",
    "wof:name":"Zuidam Bv, Van",
    "wof:placetype":"venue"
},
  "geometry": {"coordinates":[5.218338,51.943684],"type":"Point"}
}