{
  "type": "Feature",
  "properties": {
    "addr:full":"Trapveld 67 Nootdorp Zuid-Holland 2632 AC",
    "addr:housenumber":"67",
    "addr:postcode":"2632 ac",
    "addr:street":"Trapveld",
    "iso:country":"NL",
    "sg:address":"Trapveld 67",
    "sg:city":"Nootdorp",
    "sg:orig_category":"Adviesbureaus Waterbouwkunde",
    "sg:phone":"+31 6 22779469",
    "sg:postcode":"2632 AC",
    "sg:province":"Zuid-Holland",
    "wof:name":"Janssen, P",
    "wof:placetype":"venue"
},
  "geometry": {"coordinates":[4.402526,52.048809],"type":"Point"}
}