{
  "type": "Feature",
  "properties": {
    "addr:full":"Terborgsewg 13 Azewyn Gelderland 7045 AK",
    "addr:housenumber":"13",
    "addr:postcode":"7045 ak",
    "addr:street":"Terborgsewg;Gelderland",
    "iso:country":"NL",
    "sg:address":"Terborgsewg 13",
    "sg:city":"Azewyn",
    "sg:orig_category":"Elektrotechnische Installatiebureaus",
    "sg:phone":"+31 314 650 010",
    "sg:postcode":"7045 AK",
    "sg:province":"Gelderland",
    "wof:name":"Bruins Elektrotechniek",
    "wof:placetype":"venue"
},
  "geometry": {"coordinates":[6.28766,51.897739],"type":"Point"}
}