{
  "type": "Feature",
  "properties": {
    "addr:full":"J Thyssedomein 9 Maastricht Limburg 6229 EA",
    "addr:housenumber":"9",
    "addr:postcode":"6229 ea",
    "iso:country":"NL",
    "sg:address":"J Thyssedomein 9",
    "sg:city":"Maastricht",
    "sg:orig_category":"Luchtfotografie",
    "sg:phone":"+31 43 367 0660",
    "sg:postcode":"6229 EA",
    "sg:province":"Limburg",
    "wof:name":"Netten Airphoto Maastricht",
    "wof:placetype":"venue"
},
  "geometry": {"coordinates":[5.710867,50.836475],"type":"Point"}
}