{
  "type": "Feature",
  "properties": {
    "addr:full":"Schurinklaan 18 Eefde Gelderland 7211 DG",
    "addr:housenumber":"18",
    "addr:postcode":"7211 dg",
    "addr:street":"Schurinklaan;Gelderland",
    "iso:country":"NL",
    "sg:address":"Schurinklaan 18",
    "sg:city":"Eefde",
    "sg:orig_category":"Banken And Kredietinstellingen",
    "sg:phone":"+31 575 540 005",
    "sg:postcode":"7211 DG",
    "sg:province":"Gelderland",
    "wof:name":"Rabobank",
    "wof:placetype":"venue"
},
  "geometry": {"coordinates":[6.227835,52.170921],"type":"Point"}
}