{
  "type": "Feature",
  "properties": {
    "addr:full":"Nieuwstr 16 Budel Noord-Brabant 6021 HS",
    "addr:housenumber":"16",
    "addr:postcode":"6021 hs",
    "addr:street":"Nieuwstr",
    "iso:country":"NL",
    "sg:address":"Nieuwstr 16",
    "sg:city":"Budel",
    "sg:orig_category":"Verzekeringen - Verzekeringskantoren",
    "sg:phone":"+31 495 497 811",
    "sg:postcode":"6021 HS",
    "sg:province":"Noord-Brabant",
    "wof:name":"Assuplan Bv",
    "wof:placetype":"venue"
},
  "geometry": {"coordinates":[5.573372,51.272858],"type":"Point"}
}