{
  "type": "Feature",
  "properties": {
    "addr:full":"Zuiderkruis 23 Oosterhout Nb North Brabant 4907 VE",
    "addr:housenumber":"23;nb",
    "addr:postcode":"4907",
    "addr:street":"Zuiderkruis;Ve",
    "iso:country":"NL",
    "sg:address":"Zuiderkruis 23",
    "sg:city":"Oosterhout Nb",
    "sg:orig_category":"Technische Studies And Onderzoek",
    "sg:phone":"+31 162 431 171",
    "sg:postcode":"4907 VE",
    "sg:province":"North Brabant",
    "wof:name":"Marine Support Consultancy Schouffoer",
    "wof:placetype":"venue"
},
  "geometry": {"coordinates":[4.868449,51.654591],"type":"Point"}
}