{
  "type": "Feature",
  "properties": {
    "addr:full":"Staverdensewg 283 Ermelo Gelderland 3852 NV",
    "addr:housenumber":"283",
    "addr:postcode":"3852 nv",
    "addr:street":"Gelderland",
    "iso:country":"NL",
    "sg:address":"Staverdensewg 283",
    "sg:city":"Ermelo",
    "sg:orig_category":"Bedrijfsopleidingen",
    "sg:phone":"+31 577 407 158",
    "sg:postcode":"3852 NV",
    "sg:province":"Gelderland",
    "sg:website":"http://www.nios.nl",
    "wof:name":"Nios Bv",
    "wof:placetype":"venue"
},
  "geometry": {"coordinates":[5.7391,52.285805],"type":"Point"}
}