{
  "type": "Feature",
  "properties": {
    "addr:full":"Venne 1 Winschoten Groningen 9671 DA",
    "addr:housenumber":"1",
    "addr:postcode":"9671 da",
    "addr:street":"Venne",
    "iso:country":"NL",
    "sg:address":"Venne 1",
    "sg:city":"Winschoten",
    "sg:classifiers":[
        {
            "category":"Fast Food",
            "type":"Food & Drink"
        }
    ],
    "sg:phone":"+31 597 424 749",
    "sg:postcode":"9671 DA",
    "sg:province":"Groningen",
    "sg:tags":[
        "afhaal",
        "restaurant"
    ],
    "wof:name":"Smickel In",
    "wof:placetype":"venue"
},
  "geometry": {"coordinates":[7.033718,53.145439],"type":"Point"}
}