{
  "type": "Feature",
  "properties": {
    "iso:country":"NL",
    "sg:address":"Burgemeester Reigerstr 24A",
    "sg:city":"Utrecht",
    "sg:classifiers":[
        {
            "category":"Food & Beverages",
            "subcategory":"Fruits & Vegetables",
            "type":"Retail Goods"
        }
    ],
    "sg:phone":"+31 30 252 2810",
    "sg:postcode":"3581 KS",
    "sg:province":"Utrecht",
    "sg:tags":[
        "groenten"
    ],
    "wof:name":"Agterberg Groenten En Fruit",
    "wof:placetype":"venue"
},
  "geometry": {"coordinates":[5.134955,52.090076],"type":"Point"}
}