{
  "type": "Feature",
  "properties": {
    "addr:full":"Hoofdstr 116 Heeswyk Dinther Noord-Brabant 5473 AT",
    "addr:housenumber":"116",
    "addr:postcode":"5473",
    "addr:street":"Heeswyk Dinther",
    "iso:country":"NL",
    "sg:address":"Hoofdstr 116",
    "sg:city":"Heeswyk Dinther",
    "sg:orig_category":"Autorijscholen",
    "sg:phone":"+31 413 293 174",
    "sg:postcode":"5473 AT",
    "sg:province":"Noord-Brabant",
    "wof:name":"Berg, Rien V/D",
    "wof:placetype":"venue"
},
  "geometry": {"coordinates":[5.45889,51.65292],"type":"Point"}
}