{
  "type": "Feature",
  "properties": {
    "addr:full":"Parallelwg 12 Maasbree Limburg 5993 BG",
    "addr:housenumber":"12",
    "addr:postcode":"5993",
    "addr:street":"Parallelwg",
    "iso:country":"NL",
    "sg:address":"Parallelwg 12",
    "sg:city":"Maasbree",
    "sg:classifiers":[
        {
            "category":"Retail",
            "subcategory":"Auto Repair",
            "type":"Services"
        }
    ],
    "sg:phone":"+31 77 465 1445",
    "sg:postcode":"5993 BG",
    "sg:province":"Limburg",
    "sg:tags":[
        "garage"
    ],
    "wof:name":"Broekmans",
    "wof:placetype":"venue"
},
  "geometry": {"coordinates":[24.020149,43.22657],"type":"Point"}
}