{
  "type": "Feature",
  "properties": {
    "iso:country":"NL",
    "sg:address":"Stompwyksewg 7",
    "sg:city":"Leidschendam",
    "sg:orig_category":"Loonbedrijven",
    "sg:phone":"+31 70 327 9659",
    "sg:postcode":"2266 GC",
    "sg:province":"Zuid-Holland",
    "wof:name":"Roeling Bv, C",
    "wof:placetype":"venue"
},
  "geometry": {"coordinates":[4.410577,52.0784],"type":"Point"}
}