{
  "type": "Feature",
  "properties": {
    "addr:full":"Haarlemmerstraatweg 12 Oegstgeest Zuid-Holland 2343 LB",
    "addr:housenumber":"12",
    "addr:postcode":"2343 lb",
    "addr:street":"Haarlemmerstraatweg",
    "iso:country":"NL",
    "sg:address":"Haarlemmerstraatweg 12",
    "sg:city":"Oegstgeest",
    "sg:orig_category":"Diensten Voor Huisdieren",
    "sg:phone":"+31 71 517 4141",
    "sg:postcode":"2343 LB",
    "sg:province":"Zuid-Holland",
    "wof:name":"Dierenambulance-Vogelasiel Regio Leiden",
    "wof:placetype":"venue"
},
  "geometry": {"coordinates":[4.470474,52.195892],"type":"Point"}
}