{
  "type": "Feature",
  "properties": {
    "addr:full":"Lekkenburg 31 Gouda South Holland 2804 XB",
    "addr:housenumber":"31",
    "addr:postcode":"2804 xb",
    "addr:street":"Lekkenburg",
    "iso:country":"NL",
    "sg:address":"Lekkenburg 31",
    "sg:city":"Gouda",
    "sg:orig_category":"Kaas",
    "sg:phone":"+31 182 532 397",
    "sg:postcode":"2804 XB",
    "sg:province":"South Holland",
    "wof:name":"Kaasspecialist, De",
    "wof:placetype":"venue"
},
  "geometry": {"coordinates":[4.7052631378,52.0320243835],"type":"Point"}
}