{
  "type": "Feature",
  "properties": {
    "iso:country":"NL",
    "sg:address":"Pallaesstraat 3",
    "sg:city":"Utrecht",
    "sg:classifiers":[
        {
            "category":"Education",
            "subcategory":"Preschool",
            "type":"Public Place"
        }
    ],
    "sg:phone":"+31 30 236 9971",
    "sg:postcode":"3581 RP",
    "sg:province":"Utrecht",
    "sg:tags":[
        "kleuteronderwijs",
        "basis-"
    ],
    "wof:name":"Peuterspeelzaal De Petteflet",
    "wof:placetype":"venue"
},
  "geometry": {"coordinates":[5.133184,52.093983],"type":"Point"}
}