{
  "type": "Feature",
  "properties": {
    "addr:full":"Leijsenhoek 47 Oosterhout Nb North Brabant 4901 ER",
    "addr:housenumber":"47;nb",
    "addr:postcode":"4901 er",
    "addr:street":"Leijsenhoek",
    "iso:country":"NL",
    "sg:address":"Leijsenhoek 47",
    "sg:city":"Oosterhout Nb",
    "sg:orig_category":"Verlichting And Huishoudartikelen",
    "sg:phone":"+31 162 424 618",
    "sg:postcode":"4901 ER",
    "sg:province":"North Brabant",
    "wof:name":"Uniek Woonidee Oosterhout",
    "wof:placetype":"venue"
},
  "geometry": {"coordinates":[4.864467,51.645111],"type":"Point"}
}