{
  "type": "Feature",
  "properties": {
    "addr:full":"Zeisterwg 23A Woudenberg Utrecht 3931 ME",
    "addr:housenumber":"23a",
    "addr:postcode":"3931",
    "addr:street":"Zeisterwg",
    "iso:country":"NL",
    "sg:address":"Zeisterwg 23A",
    "sg:city":"Woudenberg",
    "sg:orig_category":"Verkeersbureaus",
    "sg:phone":"+31 33 286 4546",
    "sg:postcode":"3931 ME",
    "sg:province":"Utrecht",
    "sg:website":"http://www.rijvaardigheid.nl",
    "wof:name":"Adviesbureau Rijvaardigheid Ned",
    "wof:placetype":"venue"
},
  "geometry": {"coordinates":[5.397658,52.083309],"type":"Point"}
}