{
  "type": "Feature",
  "properties": {
    "addr:full":"Dorpsstr 75 Loenen Ad Vecht Utrecht 3632 AS",
    "addr:housenumber":"75",
    "addr:postcode":"3632 as",
    "addr:street":"Dorpsstr;Vecht",
    "iso:country":"NL",
    "sg:address":"Dorpsstr 75",
    "sg:city":"Loenen Ad Vecht",
    "sg:orig_category":"Kunstbemiddeling",
    "sg:phone":"+31 294 234 830",
    "sg:postcode":"3632 AS",
    "sg:province":"Utrecht",
    "wof:name":"Artevisie",
    "wof:placetype":"venue"
},
  "geometry": {"coordinates":[5.026713,52.209999],"type":"Point"}
}