{
  "type": "Feature",
  "properties": {
    "iso:country":"NL",
    "sg:address":"Dorpsstr 75",
    "sg:city":"Loenen Ad Vecht",
    "sg:orig_category":"Kunstbemiddeling",
    "sg:phone":"+31 294 234 830",
    "sg:postcode":"3632 AS",
    "sg:province":"Utrecht",
    "wof:name":"Artevisie",
    "wof:placetype":"venue"
},
  "geometry": {"coordinates":[5.026713,52.209999],"type":"Point"}
}