{
  "type": "Feature",
  "properties": {
    "iso:country":"NL",
    "sg:address":"Zuiderhoofdstraat 12",
    "sg:city":"Krommenie",
    "sg:orig_category":"Huishoudapparatuur, Televisies And Radio'S",
    "sg:phone":"+31 75 628 8872",
    "sg:postcode":"1561 AL",
    "sg:province":"Noord-Holland",
    "wof:name":"Elektro Technisch Bureau Frankfort",
    "wof:placetype":"venue"
},
  "geometry": {"coordinates":[4.767241,52.496838],"type":"Point"}
}