{
  "type": "Feature",
  "properties": {
    "addr:full":"Noordereinde 147 S Graveland Noord-Holland 1243 JM",
    "addr:housenumber":"147",
    "addr:postcode":"1243 jm",
    "addr:street":"Noordereinde;S Graveland",
    "iso:country":"NL",
    "sg:address":"Noordereinde 147",
    "sg:city":"S Graveland",
    "sg:orig_category":"Projectinrichting",
    "sg:phone":"+31 35 623 0551",
    "sg:postcode":"1243 JM",
    "sg:province":"Noord-Holland",
    "wof:name":"Artifax",
    "wof:placetype":"venue"
},
  "geometry": {"coordinates":[5.121158,52.244148],"type":"Point"}
}