{
  "type": "Feature",
  "properties": {
    "addr:full":"Aalmarkt 15 Leiden Zuid-Holland 2311 EC",
    "addr:housenumber":"15",
    "addr:postcode":"2311 ec",
    "addr:street":"Aalmarkt",
    "iso:country":"NL",
    "sg:address":"Aalmarkt 15",
    "sg:city":"Leiden",
    "sg:orig_category":"Architecten",
    "sg:phone":"+31 71 514 0014",
    "sg:postcode":"2311 EC",
    "sg:province":"Zuid-Holland",
    "wof:name":"Architectural Video Audio Bv",
    "wof:placetype":"venue"
},
  "geometry": {"coordinates":[4.489794,52.159653],"type":"Point"}
}