{
  "type": "Feature",
  "properties": {
    "addr:full":"Postbus 166 Spykenisse 3200 AD",
    "addr:housenumber":"166",
    "addr:postcode":"3200 ad",
    "addr:street":"Postbus",
    "iso:country":"NL",
    "sg:address":"Postbus 166",
    "sg:city":"Spykenisse",
    "sg:orig_category":"Bedrijfsopleidingen",
    "sg:phone":"+31 181 674 442",
    "sg:postcode":"3200 AD",
    "sg:website":"http://www.mind-ace.nl",
    "wof:name":"Mind-Ace",
    "wof:placetype":"venue"
},
  "geometry": {"coordinates":[4.35844,51.837879],"type":"Point"}
}