{
  "type": "Feature",
  "properties": {
    "addr:full":"Westeinde 66 Noordwijkerhout Zuid-Holland 2211 XR",
    "addr:housenumber":"66",
    "addr:postcode":"2211 xr",
    "addr:street":"Westeinde",
    "iso:country":"NL",
    "sg:address":"Westeinde 66",
    "sg:city":"Noordwijkerhout",
    "sg:orig_category":"Bloemen And Planten",
    "sg:phone":"+31 252 375 485",
    "sg:postcode":"2211 XR",
    "sg:province":"Zuid-Holland",
    "wof:name":"Vof C. Klinkenberg",
    "wof:placetype":"venue"
},
  "geometry": {"coordinates":[4.467227,52.250992],"type":"Point"}
}