{
  "type": "Feature",
  "properties": {
    "addr:full":"Vlindermeent 35 Hilversum Noord-Holland 1218 CT",
    "addr:housenumber":"35",
    "addr:postcode":"1218 ct",
    "addr:street":"Vlindermeent",
    "iso:country":"NL",
    "sg:address":"Vlindermeent 35",
    "sg:city":"Hilversum",
    "sg:orig_category":"Koffie-Automaten",
    "sg:phone":"+31 35 693 7010",
    "sg:postcode":"1218 CT",
    "sg:province":"Noord-Holland",
    "wof:name":"Hertog, Den",
    "wof:placetype":"venue"
},
  "geometry": {"coordinates":[5.139306,52.268837],"type":"Point"}
}