{
  "type": "Feature",
  "properties": {
    "addr:full":"Faberstr 16 Dieren Gelderland 6951 BJ",
    "addr:housenumber":"16",
    "addr:postcode":"6951 bj",
    "addr:street":"Faberstr;Gelderland",
    "iso:country":"NL",
    "sg:address":"Faberstr 16",
    "sg:city":"Dieren",
    "sg:orig_category":"Kappers",
    "sg:phone":"+31 313 414 738",
    "sg:postcode":"6951 BJ",
    "sg:province":"Gelderland",
    "wof:name":"Scheerder, Leo En Ria",
    "wof:placetype":"venue"
},
  "geometry": {"coordinates":[6.098762,52.050037],"type":"Point"}
}