{
  "type": "Feature",
  "properties": {
    "addr:full":"Dr W Dreeswg 82 Amstelveen North Holland 1188 KP",
    "addr:housenumber":"82",
    "addr:postcode":"1188 kp",
    "addr:street":"Dr W Dreeswg",
    "iso:country":"NL",
    "sg:address":"Dr W Dreeswg 82",
    "sg:city":"Amstelveen",
    "sg:orig_category":"Bedrijfsopleidingen",
    "sg:phone":"+31 20 647 9129",
    "sg:postcode":"1188 KP",
    "sg:province":"North Holland",
    "wof:name":"H\u00f7Cker, Jacqueline",
    "wof:placetype":"venue"
},
  "geometry": {"coordinates":[4.844688,52.280121],"type":"Point"}
}