{
  "type": "Feature",
  "properties": {
    "iso:country":"NL",
    "sg:address":"Akkerwinde 13",
    "sg:city":"Hulst",
    "sg:orig_category":"Adviesbureaus Bouwkunde",
    "sg:phone":"+31 114 320 909",
    "sg:postcode":"4561 ZJ",
    "sg:province":"Zeeland",
    "wof:name":"Bouwkoepel Bv",
    "wof:placetype":"venue"
},
  "geometry": {"coordinates":[4.071724,51.290073],"type":"Point"}
}