{
  "type": "Feature",
  "properties": {
    "addr:full":"Bunkerhaven 24 Maasbracht Limburg 6051 LR",
    "addr:housenumber":"24",
    "addr:postcode":"6051 lr",
    "addr:street":"Bunkerhaven",
    "iso:country":"NL",
    "sg:address":"Bunkerhaven 24",
    "sg:city":"Maasbracht",
    "sg:orig_category":"Pleziervaartuigen And Reparatie",
    "sg:phone":"+31 475 461 748",
    "sg:postcode":"6051 LR",
    "sg:province":"Limburg",
    "wof:name":"K.A.G. Van Oost",
    "wof:placetype":"venue"
},
  "geometry": {"coordinates":[5.883697,51.148968],"type":"Point"}
}