{
  "type": "Feature",
  "properties": {
    "addr:full":"Kolveniershof 6 B Goes Ohio 4461 DB",
    "addr:housenumber":"6 b",
    "addr:postcode":"4461 db",
    "addr:street":"Kolveniershof",
    "iso:country":"NL",
    "sg:address":"Kolveniershof 6 B",
    "sg:city":"Goes",
    "sg:orig_category":"Bedrijfsopleidingen",
    "sg:phone":"+31 113 212 607",
    "sg:postcode":"4461 DB",
    "sg:province":"Ohio",
    "sg:website":"http://www.rovae.nl",
    "wof:name":"Rovae",
    "wof:placetype":"venue"
},
  "geometry": {"coordinates":[-83.914169,39.768833],"type":"Point"}
}