{
  "type": "Feature",
  "properties": {
    "addr:full":"Kaldenkerkerweg 30 Venlo Limburg 5913 AE",
    "addr:housenumber":"30",
    "addr:postcode":"5913 ae",
    "addr:street":"Kaldenkerkerweg",
    "iso:country":"NL",
    "sg:address":"Kaldenkerkerweg 30",
    "sg:city":"Venlo",
    "sg:classifiers":[
        {
            "category":"Travel",
            "subcategory":"Hotels & Motels",
            "type":"Entertainment"
        }
    ],
    "sg:phone":"+31 77 354 2543",
    "sg:postcode":"5913 AE",
    "sg:province":"Limburg",
    "wof:name":"Hotel Restaurant Rembrandt",
    "wof:placetype":"venue"
},
  "geometry": {"coordinates":[6.174822,51.363403],"type":"Point"}
}