{
  "type": "Feature",
  "properties": {
    "addr:full":"Transvaalkade 16 Amsterdam Noord-Holland 1092 JK",
    "addr:housenumber":"16",
    "addr:postcode":"1092 jk",
    "addr:street":"Transvaalkade",
    "iso:country":"NL",
    "sg:address":"Transvaalkade 16",
    "sg:city":"Amsterdam",
    "sg:orig_category":"Verzekeringen",
    "sg:phone":"+31 20 668 5313",
    "sg:postcode":"1092 JK",
    "sg:province":"Noord-Holland",
    "wof:name":"Flinkenflogel Assurantien",
    "wof:placetype":"venue"
},
  "geometry": {"coordinates":[4.926537,52.354885],"type":"Point"}
}