{
  "type": "Feature",
  "properties": {
    "iso:country":"NL",
    "sg:address":"Wanveld 2",
    "sg:city":"Houten",
    "sg:classifiers":[
        {
            "category":"Professional",
            "subcategory":"Accounting & Tax Preparation",
            "type":"Services"
        }
    ],
    "sg:phone":"+31 30 637 6755",
    "sg:postcode":"3993 SG",
    "sg:province":"Utrecht",
    "sg:tags":[
        "accountant"
    ],
    "wof:name":"Restore Houten",
    "wof:placetype":"venue"
},
  "geometry": {"coordinates":[5.180148,52.042641],"type":"Point"}
}