{
  "type": "Feature",
  "properties": {
    "addr:full":"Westpln 3 Rotterdam South Holland 3016 BL",
    "addr:housenumber":"3",
    "addr:postcode":"3016 bl",
    "addr:street":"Westpln",
    "iso:country":"NL",
    "sg:address":"Westpln 3",
    "sg:city":"Rotterdam",
    "sg:orig_category":"Keukens",
    "sg:phone":"+31 10 240 0633",
    "sg:postcode":"3016 BL",
    "sg:province":"South Holland",
    "sg:website":"http://www.bulthauprotterdam.nl",
    "wof:name":"Maas, De",
    "wof:placetype":"venue"
},
  "geometry": {"coordinates":[4.478786,51.909176],"type":"Point"}
}