{
  "type": "Feature",
  "properties": {
    "addr:full":"Generaal Bothastraat 15 Haarlem Noord-Holland 2021 JP",
    "addr:housenumber":"15",
    "addr:postcode":"2021 jp",
    "addr:street":"Generaal Bothastraat",
    "iso:country":"NL",
    "sg:address":"Generaal Bothastraat 15",
    "sg:city":"Haarlem",
    "sg:orig_category":"Kappers",
    "sg:phone":"+31 23 526 0237",
    "sg:postcode":"2021 JP",
    "sg:province":"Noord-Holland",
    "wof:name":"Coiffure Voiture",
    "wof:placetype":"venue"
},
  "geometry": {"coordinates":[4.6417589188,52.3931808472],"type":"Point"}
}