{
  "type": "Feature",
  "properties": {
    "iso:country":"NL",
    "sg:address":"Geldestr 11",
    "sg:city":"Someren",
    "sg:orig_category":"Projectontwikkeling",
    "sg:phone":"+31 493 491 202",
    "sg:postcode":"5711 XE",
    "sg:province":"Noord-Brabant",
    "wof:name":"Bukkems, Henk",
    "wof:placetype":"venue"
},
  "geometry": {"coordinates":[5.716044,51.387619],"type":"Point"}
}