{
  "type": "Feature",
  "properties": {
    "addr:full":"Karnemelksloot 39 Gouda South Holland 2806 BB",
    "addr:housenumber":"39",
    "addr:postcode":"2806 bb",
    "addr:street":"Karnemelksloot",
    "iso:country":"NL",
    "sg:address":"Karnemelksloot 39",
    "sg:city":"Gouda",
    "sg:orig_category":"Verzekeringen",
    "sg:phone":"+31 182 511 810",
    "sg:postcode":"2806 BB",
    "sg:province":"South Holland",
    "wof:name":"Hubeve",
    "wof:placetype":"venue"
},
  "geometry": {"coordinates":[4.716205,52.013332],"type":"Point"}
}