{
  "type": "Feature",
  "properties": {
    "addr:full":"Breedstraat 33 Purmerend Noord-Holland 1441 CB",
    "addr:housenumber":"33",
    "addr:postcode":"1441 cb",
    "addr:street":"Breedstraat",
    "iso:country":"NL",
    "sg:address":"Breedstraat 33",
    "sg:city":"Purmerend",
    "sg:orig_category":"Schoenen",
    "sg:phone":"+31 299 413 463",
    "sg:postcode":"1441 CB",
    "sg:province":"Noord-Holland",
    "wof:name":"Eccolet",
    "wof:placetype":"venue"
},
  "geometry": {"coordinates":[4.947553,52.509441],"type":"Point"}
}