{
  "type": "Feature",
  "properties": {
    "addr:full":"Wilde Zwaan 91 Bunschoten Utrecht 3752 KC",
    "addr:housenumber":"91",
    "addr:postcode":"3752 kc",
    "addr:street":"Wilde Zwaan",
    "iso:country":"NL",
    "sg:address":"Wilde Zwaan 91",
    "sg:city":"Bunschoten",
    "sg:orig_category":"Bloemen And Planten",
    "sg:phone":"+31 33 298 5229",
    "sg:postcode":"3752 KC",
    "sg:province":"Utrecht",
    "wof:name":"Charlottes Zijdendecoraties",
    "wof:placetype":"venue"
},
  "geometry": {"coordinates":[5.362555,52.243202],"type":"Point"}
}