{
  "type": "Feature",
  "properties": {
    "addr:full":"De Wittenkade 75 Amsterdam Noord-Holland 1052 AE",
    "addr:housenumber":"75",
    "addr:postcode":"1052 ae",
    "addr:street":"De Wittenkade",
    "iso:country":"NL",
    "sg:address":"De Wittenkade 75",
    "sg:city":"Amsterdam",
    "sg:orig_category":"Kinderopvang Behalve Thuis",
    "sg:phone":"+31 20 686 8852",
    "sg:postcode":"1052 AE",
    "sg:province":"Noord-Holland",
    "wof:name":"Kinderdagverblijf Het Kwetternest",
    "wof:placetype":"venue"
},
  "geometry": {"coordinates":[4.878182,52.383492],"type":"Point"}
}