{
  "type": "Feature",
  "properties": {
    "addr:full":"Javastraat 37 Amsterdam Noord-Holland 1094 GZ",
    "addr:housenumber":"37",
    "addr:postcode":"1094 gz",
    "addr:street":"Javastraat",
    "iso:country":"NL",
    "sg:address":"Javastraat 37",
    "sg:city":"Amsterdam",
    "sg:classifiers":[
        {
            "category":"Retail",
            "subcategory":"Photofinishing",
            "type":"Services"
        }
    ],
    "sg:phone":"+31 20 693 8114",
    "sg:postcode":"1094 GZ",
    "sg:province":"Noord-Holland",
    "sg:tags":[
        "foto",
        "film"
    ],
    "wof:name":"Foto Niestadt",
    "wof:placetype":"venue"
},
  "geometry": {"coordinates":[4.933124,52.363739],"type":"Point"}
}