{
  "type": "Feature",
  "properties": {
    "iso:country":"NL",
    "sg:address":"Danzigerkd 24",
    "sg:city":"Amsterdam",
    "sg:classifiers":[
        {
            "category":"Retail",
            "subcategory":"Storage",
            "type":"Services"
        }
    ],
    "sg:phone":"+31 20 682 5905",
    "sg:postcode":"1013 AP",
    "sg:province":"North Holland",
    "sg:tags":[
        "op-",
        "en",
        "overslagbedrijven"
    ],
    "wof:name":"Hoogland & Zn Bv",
    "wof:placetype":"venue"
},
  "geometry": {"coordinates":[4.893195,52.373119],"type":"Point"}
}