{
  "type": "Feature",
  "properties": {
    "addr:full":"Begoniahof 7 Voorhout South Holland 2215 MP",
    "addr:housenumber":"7",
    "addr:postcode":"2215 mp",
    "addr:street":"Begoniahof",
    "iso:country":"NL",
    "sg:address":"Begoniahof 7",
    "sg:city":"Voorhout",
    "sg:orig_category":"Verenigingen En Stichtingen",
    "sg:phone":"+31 252 220 743",
    "sg:postcode":"2215 MP",
    "sg:province":"South Holland",
    "wof:name":"Foreholte Vv",
    "wof:placetype":"venue"
},
  "geometry": {"coordinates":[4.491694,52.218319],"type":"Point"}
}