{
  "type": "Feature",
  "properties": {
    "addr:full":"Verdiln 48 Heesch Noord-Brabant 5384 CJ",
    "addr:housenumber":"48",
    "addr:postcode":"5384 cj",
    "addr:street":"Verdiln",
    "iso:country":"NL",
    "sg:address":"Verdiln 48",
    "sg:city":"Heesch",
    "sg:orig_category":"Fitnesscentra",
    "sg:phone":"+31 412 457 067",
    "sg:postcode":"5384 CJ",
    "sg:province":"Noord-Brabant",
    "wof:name":"Fysiofit",
    "wof:placetype":"venue"
},
  "geometry": {"coordinates":[5.52822,51.735455],"type":"Point"}
}