{
  "type": "Feature",
  "properties": {
    "addr:full":"Chrysantenhof 18 Berkel En Rodenrijs South Holland 2651 XK",
    "addr:housenumber":"18",
    "addr:postcode":"2651 xk",
    "addr:street":"Chrysantenhof",
    "iso:country":"NL",
    "sg:address":"Chrysantenhof 18",
    "sg:city":"Berkel En Rodenrijs",
    "sg:classifiers":[
        {
            "category":"Education",
            "subcategory":"Preschool",
            "type":"Public Place"
        }
    ],
    "sg:phone":"+31 10 511 2043",
    "sg:postcode":"2651 XK",
    "sg:province":"South Holland",
    "sg:tags":[
        "kleuteronderwijs",
        "basis-"
    ],
    "wof:name":"Chr Nationale School Prins Willem Alexander",
    "wof:placetype":"venue"
},
  "geometry": {"coordinates":[4.461977,51.982502],"type":"Point"}
}