{
  "type": "Feature",
  "properties": {
    "addr:full":"Siriusdreef 10 Hoofddorp Noord-Holland 2132 WT",
    "addr:housenumber":"10",
    "addr:postcode":"2132 wt",
    "addr:street":"Siriusdreef",
    "iso:country":"NL",
    "sg:address":"Siriusdreef 10",
    "sg:city":"Hoofddorp",
    "sg:orig_category":"Juridische Adviseurs",
    "sg:phone":"+31 23 549 9006",
    "sg:postcode":"2132 WT",
    "sg:province":"Noord-Holland",
    "sg:website":"HTTP://www.arsint.com",
    "wof:name":"Arsenal Int Ltd",
    "wof:placetype":"venue"
},
  "geometry": {"coordinates":[4.69296,52.305393],"type":"Point"}
}