{
  "type": "Feature",
  "properties": {
    "iso:country":"NL",
    "sg:address":"Kranenburgweg 79",
    "sg:city":"'S Gravenhage",
    "sg:orig_category":"Bloemen And Planten",
    "sg:phone":"+31 70 358 8294",
    "sg:postcode":"2581 XT",
    "sg:province":"South Holland",
    "wof:name":"R. Wols",
    "wof:placetype":"venue"
},
  "geometry": {"coordinates":[4.266933,52.091042],"type":"Point"}
}