{
  "type": "Feature",
  "properties": {
    "iso:country":"NL",
    "sg:address":"Sikkelstraat 75",
    "sg:city":"Amsterdam",
    "sg:orig_category":"Veren - Fabrieken En Groothandel",
    "sg:phone":"+31 20 625 9170",
    "sg:postcode":"1097 ZD",
    "sg:province":"Noord-Holland",
    "wof:name":"Nafrema",
    "wof:placetype":"venue"
},
  "geometry": {"coordinates":[4.948742,52.339748],"type":"Point"}
}