{
  "type": "Feature",
  "properties": {
    "iso:country":"NL",
    "sg:address":"Leemzeulder 21",
    "sg:city":"Laren Nh",
    "sg:orig_category":"Psychotherapeuten",
    "sg:phone":"+31 35 538 8877",
    "sg:postcode":"1251 AM",
    "sg:province":"North Holland",
    "sg:website":"http://www.hsk.nl",
    "wof:name":"Hsk Van Bavoort, Instituut",
    "wof:placetype":"venue"
},
  "geometry": {"coordinates":[5.22387,52.256741],"type":"Point"}
}