{
  "type": "Feature",
  "properties": {
    "addr:full":"Prins Bernhardstraat 3 Ooij Gelderland 6576 BB",
    "addr:housenumber":"3",
    "addr:postcode":"6576 bb",
    "addr:street":"Prins Bernhardstraat;Gelderland",
    "iso:country":"NL",
    "sg:address":"Prins Bernhardstraat 3",
    "sg:city":"Ooij",
    "sg:orig_category":"Bibliotheken And Openbare Archieven",
    "sg:phone":"+31 24 663 1935",
    "sg:postcode":"6576 BB",
    "sg:province":"Gelderland",
    "wof:name":"Openbare Bibliotheek Ubbergen-Millingen",
    "wof:placetype":"venue"
},
  "geometry": {"coordinates":[5.940278,51.855099],"type":"Point"}
}