{
  "type": "Feature",
  "properties": {
    "iso:country":"NL",
    "sg:address":"Lagelandsewg 53",
    "sg:city":"Nymegen",
    "sg:orig_category":"Autoruiten",
    "sg:phone":"+31 24 373 2344",
    "sg:postcode":"6545 CC",
    "sg:province":"Gelderland",
    "sg:website":"http://www.carglass.nl",
    "wof:name":"Carglass",
    "wof:placetype":"venue"
},
  "geometry": {"coordinates":[5.808184,51.840458],"type":"Point"}
}