{
  "type": "Feature",
  "properties": {
    "addr:full":"Lanciersstraat 73 Tilburg Noord-Brabant 5017 CR",
    "addr:housenumber":"73",
    "addr:postcode":"5017 cr",
    "addr:street":"Lanciersstraat",
    "iso:country":"NL",
    "sg:address":"Lanciersstraat 73",
    "sg:city":"Tilburg",
    "sg:orig_category":"Kinderopvang Behalve Thuis",
    "sg:phone":"+31 13 543 7478",
    "sg:postcode":"5017 CR",
    "sg:province":"Noord-Brabant",
    "wof:name":"Kinderdagverblijf Duimelijntje",
    "wof:placetype":"venue"
},
  "geometry": {"coordinates":[5.097952,51.552834],"type":"Point"}
}