{
  "type": "Feature",
  "properties": {
    "addr:full":"Hengevelderstr 40 Goor Overijssel 7471 CH",
    "addr:housenumber":"40",
    "addr:postcode":"7471",
    "addr:street":"Hengevelderstr",
    "iso:country":"NL",
    "sg:address":"Hengevelderstr 40",
    "sg:city":"Goor",
    "sg:orig_category":"Verpleegartikelen",
    "sg:phone":"+31 547 386 444",
    "sg:postcode":"7471 CH",
    "sg:province":"Overijssel",
    "wof:name":"Carint",
    "wof:placetype":"venue"
},
  "geometry": {"coordinates":[6.590228,52.234951],"type":"Point"}
}