{
  "type": "Feature",
  "properties": {
    "iso:country":"NL",
    "sg:address":"Koekoeksbloem 11",
    "sg:city":"Swifterbant",
    "sg:orig_category":"Webdesign Bureaus",
    "sg:phone":"+31 321 843 340",
    "sg:postcode":"8255 KH",
    "sg:province":"NL.",
    "sg:website":"http://www.multi-graphics.nl",
    "wof:name":"Multi Graphics",
    "wof:placetype":"venue"
},
  "geometry": {"coordinates":[5.6416201591,52.5605773926],"type":"Point"}
}