{
  "type": "Feature",
  "properties": {
    "addr:full":"Twentepoort O 33 Almelo Overijssel 7609 RG",
    "addr:housenumber":"33",
    "addr:postcode":"7609 rg",
    "addr:street":"Twentepoort O",
    "iso:country":"NL",
    "sg:address":"Twentepoort O 33",
    "sg:city":"Almelo",
    "sg:orig_category":"Lichtkranten En Scoreborden",
    "sg:phone":"+31 546 808 111",
    "sg:postcode":"7609 RG",
    "sg:province":"Overijssel",
    "sg:website":"http://www.besamu.nl",
    "wof:name":"Besamu Bv",
    "wof:placetype":"venue"
},
  "geometry": {"coordinates":[6.652254,52.327168],"type":"Point"}
}