{
  "type": "Feature",
  "properties": {
    "iso:country":"NL",
    "sg:address":"Past Bressersstr 24",
    "sg:city":"Oosterhout Nb",
    "sg:orig_category":"Gordijnen",
    "sg:phone":"+31 162 437 001",
    "sg:postcode":"4901 HZ",
    "sg:province":"North Brabant",
    "wof:name":"Elga Design",
    "wof:placetype":"venue"
},
  "geometry": {"coordinates":[4.864599,51.641739],"type":"Point"}
}