{
  "type": "Feature",
  "properties": {
    "addr:full":"V Boetzelaerln 209 S Gravenhage Zuid-Holland 2581 AV",
    "addr:housenumber":"209;gravenhage",
    "addr:postcode":"2581 av",
    "addr:street":"S",
    "iso:country":"NL",
    "sg:address":"V Boetzelaerln 209",
    "sg:city":"S Gravenhage",
    "sg:orig_category":"Kunstgebitten",
    "sg:phone":"+31 70 354 6510",
    "sg:postcode":"2581 AV",
    "sg:province":"Zuid-Holland",
    "wof:name":"Ham, F Van Der",
    "wof:placetype":"venue"
},
  "geometry": {"coordinates":[4.270359,52.091347],"type":"Point"}
}