{
  "type": "Feature",
  "properties": {
    "addr:full":"Bornsestraat 67 Almelo NL.08 7607 KK",
    "addr:housenumber":"67;nl.08",
    "addr:postcode":"7607 kk",
    "addr:street":"Bornsestraat",
    "iso:country":"NL",
    "sg:address":"Bornsestraat 67",
    "sg:city":"Almelo",
    "sg:orig_category":"Schoenen",
    "sg:phone":"+31 546 812 905",
    "sg:postcode":"7607 KK",
    "sg:province":"NL.08",
    "wof:name":"Gert De Olde Schoenen Bv",
    "wof:placetype":"venue"
},
  "geometry": {"coordinates":[6.667263,52.350876],"type":"Point"}
}