{
  "type": "Feature",
  "properties": {
    "addr:full":"Meerenakkerweg 1 Eindhoven Noord-Brabant 5652 AR",
    "addr:housenumber":"1",
    "addr:postcode":"5652",
    "addr:street":"Meerenakkerweg",
    "iso:country":"NL",
    "sg:address":"Meerenakkerweg 1",
    "sg:city":"Eindhoven",
    "sg:orig_category":"Technische Studies And Onderzoek",
    "sg:phone":"+31 40 250 3797",
    "sg:postcode":"5652 AR",
    "sg:province":"Noord-Brabant",
    "wof:name":"Re Gent Bv",
    "wof:placetype":"venue"
},
  "geometry": {"coordinates":[5.439507,51.427654],"type":"Point"}
}