{
  "type": "Feature",
  "properties": {
    "addr:full":"Postbus 40013 Zwolle Gelderland 8004 DA",
    "addr:postcode":"40013;8004 da",
    "addr:street":"Postbus;Gelderland",
    "iso:country":"NL",
    "sg:address":"Postbus 40013",
    "sg:city":"Zwolle",
    "sg:orig_category":"Elektrotechnische Artikelen",
    "sg:phone":"+31 38 469 8200",
    "sg:postcode":"8004 DA",
    "sg:province":"Gelderland",
    "wof:name":"Hemmink",
    "wof:placetype":"venue"
},
  "geometry": {"coordinates":[6.09243,52.51223],"type":"Point"}
}