{
  "type": "Feature",
  "properties": {
    "addr:full":"J Obrechtstr 51 Amsterdam Noord-Holland 1071 KJ",
    "addr:housenumber":"51",
    "addr:postcode":"1071 kj",
    "iso:country":"NL",
    "sg:address":"J Obrechtstr 51",
    "sg:city":"Amsterdam",
    "sg:orig_category":"Verenigingen En Stichtingen",
    "sg:phone":"+31 20 664 4003",
    "sg:postcode":"1071 KJ",
    "sg:province":"Noord-Holland",
    "wof:name":"Vrienden Concertgebouw",
    "wof:placetype":"venue"
},
  "geometry": {"coordinates":[4.876518,52.354706],"type":"Point"}
}