{
  "type": "Feature",
  "properties": {
    "addr:full":"Dalenk 12 Loenen Gld Gelderland 7371 DE",
    "addr:housenumber":"12;7371",
    "addr:street":"Dalenk;Gld Gelderland;De",
    "iso:country":"NL",
    "sg:address":"Dalenk 12",
    "sg:city":"Loenen Gld",
    "sg:orig_category":"Hoefdierhouderijen",
    "sg:phone":"+31 55 505 2711",
    "sg:postcode":"7371 DE",
    "sg:province":"Gelderland",
    "wof:name":"Alfsengi",
    "wof:placetype":"venue"
},
  "geometry": {"coordinates":[6.024615,52.10503],"type":"Point"}
}