{
  "type": "Feature",
  "properties": {
    "addr:full":"Westkadk 10 Nykerk Gld Gelderland 3861 MB",
    "addr:housenumber":"10",
    "addr:postcode":"3861 mb",
    "addr:street":"Westkadk;Gld Gelderland",
    "iso:country":"NL",
    "sg:address":"Westkadk 10",
    "sg:city":"Nykerk Gld",
    "sg:orig_category":"Bedden En Matrassen",
    "sg:phone":"+31 33 247 0606",
    "sg:postcode":"3861 MB",
    "sg:province":"Gelderland",
    "wof:name":"Dreams",
    "wof:placetype":"venue"
},
  "geometry": {"coordinates":[5.480132,52.228149],"type":"Point"}
}