{
  "type": "Feature",
  "properties": {
    "addr:full":"Reestplantsoen 14 Meppel Provincie Drenthe 7944 BE",
    "addr:housenumber":"14",
    "addr:postcode":"7944",
    "addr:street":"Reestplantsoen;Provincie Drenthe",
    "iso:country":"NL",
    "sg:address":"Reestplantsoen 14",
    "sg:city":"Meppel",
    "sg:orig_category":"Kinderopvang Behalve Thuis",
    "sg:phone":"+31 522 253 879",
    "sg:postcode":"7944 BE",
    "sg:province":"Provincie Drenthe",
    "wof:name":"Boemeltje",
    "wof:placetype":"venue"
},
  "geometry": {"coordinates":[6.193126,52.686012],"type":"Point"}
}