{
  "type": "Feature",
  "properties": {
    "addr:full":"Kanaalstr 57 Utrecht Utrecht 3531 CB",
    "addr:housenumber":"57",
    "addr:postcode":"3531 cb",
    "addr:street":"Kanaalstr",
    "iso:country":"NL",
    "sg:address":"Kanaalstr 57",
    "sg:city":"Utrecht",
    "sg:orig_category":"Kaas",
    "sg:phone":"+31 30 293 6651",
    "sg:postcode":"3531 CB",
    "sg:province":"Utrecht",
    "wof:name":"Kaasboer, R De",
    "wof:placetype":"venue"
},
  "geometry": {"coordinates":[5.1033401489,52.0917320251],"type":"Point"}
}