{
  "type": "Feature",
  "properties": {
    "addr:full":"Zuiderwg 18 Huizen North Holland 1271 LZ",
    "addr:housenumber":"18",
    "addr:postcode":"1271 lz",
    "addr:street":"Zuiderwg",
    "iso:country":"NL",
    "sg:address":"Zuiderwg 18",
    "sg:city":"Huizen",
    "sg:orig_category":"Betonwerken",
    "sg:phone":"+31 35 526 4784",
    "sg:postcode":"1271 LZ",
    "sg:province":"North Holland",
    "wof:name":"Artech",
    "wof:placetype":"venue"
},
  "geometry": {"coordinates":[5.240895,52.291122],"type":"Point"}
}