{
  "type": "Feature",
  "properties": {
    "addr:full":"De Were 1A Zwijndrecht South Holland 3332 KC",
    "addr:housenumber":"1a",
    "addr:postcode":"3332 kc",
    "addr:street":"De Were",
    "iso:country":"NL",
    "sg:address":"De Were 1A",
    "sg:city":"Zwijndrecht",
    "sg:orig_category":"Kinderopvang Behalve Thuis",
    "sg:phone":"+31 78 612 1330",
    "sg:postcode":"3332 KC",
    "sg:province":"South Holland",
    "wof:name":"Kinderdagverblijf Bobo",
    "wof:placetype":"venue"
},
  "geometry": {"coordinates":[4.647053,51.824741],"type":"Point"}
}