{
  "type": "Feature",
  "properties": {
    "addr:full":"Maaibeemd 48 Breda Noord-Brabant 4824 NH",
    "addr:housenumber":"48",
    "addr:postcode":"4824 nh",
    "addr:street":"Maaibeemd",
    "iso:country":"NL",
    "sg:address":"Maaibeemd 48",
    "sg:city":"Breda",
    "sg:orig_category":"Parfum And Cosmetica Gh",
    "sg:phone":"+31 76 541 9154",
    "sg:postcode":"4824 NH",
    "sg:province":"Noord-Brabant",
    "wof:name":"Alpina Vof",
    "wof:placetype":"venue"
},
  "geometry": {"coordinates":[4.740169,51.606945],"type":"Point"}
}