{
  "type": "Feature",
  "properties": {
    "iso:country":"NL",
    "sg:address":"Zandstraat 27",
    "sg:city":"Venlo",
    "sg:orig_category":"Vertaal- And Tolkenbureaus",
    "sg:phone":"+31 77 354 3221",
    "sg:postcode":"5913 TG",
    "sg:province":"Limburg",
    "wof:name":"Tsjechie Consult",
    "wof:placetype":"venue"
},
  "geometry": {"coordinates":[6.176806,51.363544],"type":"Point"}
}