{
  "type": "Feature",
  "properties": {
    "addr:full":"Gelderstraat 6 Hilvarenbeek Noord-Brabant 5081 AC",
    "addr:housenumber":"6",
    "addr:postcode":"5081 ac",
    "addr:street":"Gelderstraat",
    "iso:country":"NL",
    "sg:address":"Gelderstraat 6",
    "sg:city":"Hilvarenbeek",
    "sg:orig_category":"Bloemen And Planten",
    "sg:phone":"+31 13 505 2651",
    "sg:postcode":"5081 AC",
    "sg:province":"Noord-Brabant",
    "wof:name":"Bloemisterij Op 'T Hoog",
    "wof:placetype":"venue"
},
  "geometry": {"coordinates":[5.136533,51.484562],"type":"Point"}
}