{
  "type": "Feature",
  "properties": {
    "addr:full":"Daalder 16 Dronten Flevoland 8253 CN",
    "addr:housenumber":"16",
    "addr:postcode":"8253 cn",
    "addr:street":"Daalder;Flevoland",
    "iso:country":"NL",
    "sg:address":"Daalder 16",
    "sg:city":"Dronten",
    "sg:orig_category":"Boekhouders",
    "sg:phone":"+31 321 337 550",
    "sg:postcode":"8253 CN",
    "sg:province":"Flevoland",
    "wof:name":"Daalder",
    "wof:placetype":"venue"
},
  "geometry": {"coordinates":[5.709071,52.530643],"type":"Point"}
}