{
  "type": "Feature",
  "properties": {
    "addr:full":"Frankenln 47 Tilburg North Brabant 5037 KE",
    "addr:housenumber":"47",
    "addr:postcode":"5037 ke",
    "addr:street":"Frankenln",
    "iso:country":"NL",
    "sg:address":"Frankenln 47",
    "sg:city":"Tilburg",
    "sg:classifiers":[
        {
            "category":"Education",
            "subcategory":"School",
            "type":"Public Place"
        }
    ],
    "sg:phone":"+31 13 463 4526",
    "sg:postcode":"5037 KE",
    "sg:province":"North Brabant",
    "sg:tags":[
        "studiebegeleiding",
        "en",
        "school-"
    ],
    "wof:name":"Herder",
    "wof:placetype":"venue"
},
  "geometry": {"coordinates":[5.05094,51.556992],"type":"Point"}
}