{
  "type": "Feature",
  "properties": {
    "addr:full":"Blokdijk 32 Wijdenes Noord-Holland 1608 HG",
    "addr:housenumber":"32",
    "addr:postcode":"1608 hg",
    "addr:street":"Blokdijk",
    "iso:country":"NL",
    "sg:address":"Blokdijk 32",
    "sg:city":"Wijdenes",
    "sg:orig_category":"Fruitteelt",
    "sg:phone":"+31 229 501 316",
    "sg:postcode":"1608 HG",
    "sg:province":"Noord-Holland",
    "wof:name":"Fa J. & S. Broertjes",
    "wof:placetype":"venue"
},
  "geometry": {"coordinates":[5.145625,52.657524],"type":"Point"}
}