{
  "type": "Feature",
  "properties": {
    "iso:country":"NL",
    "sg:address":"Energiewg 43/A",
    "sg:city":"Zoeterwoude",
    "sg:orig_category":"Product-Promotie",
    "sg:phone":"+31 71 541 0901",
    "sg:postcode":"2382 NC",
    "sg:province":"Zuid-Holland",
    "wof:name":"Buurman Bv, Hans",
    "wof:placetype":"venue"
},
  "geometry": {"coordinates":[4.527732,52.139053],"type":"Point"}
}