{
  "type": "Feature",
  "properties": {
    "iso:country":"NL",
    "sg:address":"Doniastr 2",
    "sg:city":"Beetgum",
    "sg:orig_category":"Loonbedrijven",
    "sg:phone":"+31 58 253 1272",
    "sg:postcode":"9044 ND",
    "sg:province":"Friesland",
    "wof:name":"Jong, De",
    "wof:placetype":"venue"
},
  "geometry": {"coordinates":[5.690349,53.234894],"type":"Point"}
}