{
  "type": "Feature",
  "properties": {
    "addr:full":"Albrandwaardsedk 28 Poortugaal Zuid-Holland 3171 TH",
    "addr:housenumber":"28",
    "addr:postcode":"3171 th",
    "addr:street":"Albrandwaardsedk",
    "iso:country":"NL",
    "sg:address":"Albrandwaardsedk 28",
    "sg:city":"Poortugaal",
    "sg:orig_category":"Beeldende Kunstenaars",
    "sg:phone":"+31 10 501 7208",
    "sg:postcode":"3171 TH",
    "sg:province":"Zuid-Holland",
    "wof:name":"Kemper, B",
    "wof:placetype":"venue"
},
  "geometry": {"coordinates":[4.393029,51.854202],"type":"Point"}
}