{
  "type": "Feature",
  "properties": {
    "addr:full":"Postbus 77 Leiden Zuid-Holland 2300 AB",
    "addr:housenumber":"77",
    "addr:postcode":"2300 ab",
    "addr:street":"Postbus",
    "iso:country":"NL",
    "sg:address":"Postbus 77",
    "sg:city":"Leiden",
    "sg:orig_category":"Adviesbureaus Bedrijfsorganisatie",
    "sg:phone":"+31 6 52036207",
    "sg:postcode":"2300 AB",
    "sg:province":"Zuid-Holland",
    "sg:website":"http://www.exportiser.com",
    "wof:name":"Dignus",
    "wof:placetype":"venue"
},
  "geometry": {"coordinates":[4.49015,52.161091],"type":"Point"}
}