{
  "type": "Feature",
  "properties": {
    "iso:country":"NL",
    "sg:address":"Westhavenkd 47",
    "sg:city":"Vlaardingen",
    "sg:orig_category":"Wasserijen",
    "sg:phone":"+31 10 232 2666",
    "sg:postcode":"3131 AE",
    "sg:province":"South Holland",
    "wof:name":"Lips Bv",
    "wof:placetype":"venue"
},
  "geometry": {"coordinates":[4.3449859619,51.9061775208],"type":"Point"}
}