{
  "type": "Feature",
  "properties": {
    "addr:full":"Schuitendiep 17 Groningen Groningen 9712 KD",
    "addr:housenumber":"17",
    "addr:postcode":"9712 kd",
    "addr:street":"Schuitendiep",
    "iso:country":"NL",
    "sg:address":"Schuitendiep 17",
    "sg:city":"Groningen",
    "sg:orig_category":"Kopieerservice",
    "sg:phone":"+31 50 318 5357",
    "sg:postcode":"9712 KD",
    "sg:province":"Groningen",
    "wof:name":"Copy Center",
    "wof:placetype":"venue"
},
  "geometry": {"coordinates":[6.571965,53.218925],"type":"Point"}
}