{
  "type": "Feature",
  "properties": {
    "addr:full":"Postbus 41 Bolsward Friesland 8700 AA",
    "addr:housenumber":"41",
    "addr:postcode":"8700 aa",
    "addr:street":"Postbus",
    "iso:country":"NL",
    "sg:address":"Postbus 41",
    "sg:city":"Bolsward",
    "sg:orig_category":"Makelaars En Adviseurs Onroerende Goederen",
    "sg:phone":"+31 515 576 555",
    "sg:postcode":"8700 AA",
    "sg:province":"Friesland",
    "wof:name":"Wind, S F",
    "wof:placetype":"venue"
},
  "geometry": {"coordinates":[5.52312,53.061871],"type":"Point"}
}