{
  "type": "Feature",
  "properties": {
    "iso:country":"NL",
    "sg:address":"Het Zwanevlot 313 Zonneoord",
    "sg:city":"Zutphen",
    "sg:orig_category":"Tehuizen",
    "sg:phone":"+31 575 521 239",
    "sg:postcode":"7206 CS",
    "sg:province":"Gelderland",
    "wof:name":"Philadelphia Voorzieningen, Sticht",
    "wof:placetype":"venue"
},
  "geometry": {"coordinates":[6.191525,52.140202],"type":"Point"}
}