{
  "type": "Feature",
  "properties": {
    "iso:country":"NL",
    "sg:address":"Secretaris L Jansenstr 5",
    "sg:city":"Best",
    "sg:classifiers":[
        {
            "category":"Education",
            "subcategory":"Preschool",
            "type":"Public Place"
        }
    ],
    "sg:phone":"+31 499 371 297",
    "sg:postcode":"5682 AC",
    "sg:province":"Noord-Brabant",
    "sg:tags":[
        "kleuteronderwijs",
        "basis-"
    ],
    "wof:name":"Bernardus School",
    "wof:placetype":"venue"
},
  "geometry": {"coordinates":[-101.46472199999999,31.19459],"type":"Point"}
}