{
  "type": "Feature",
  "properties": {
    "iso:country":"NL",
    "sg:address":"Lakenblekerstr 49",
    "sg:city":"Aalsmeer",
    "sg:orig_category":"Organisatiebureaus",
    "sg:phone":"+31 297 388 030",
    "sg:postcode":"1431 GE",
    "sg:province":"North Holland",
    "sg:website":"http://www.atp.nl",
    "wof:name":"Atp Destination Organisers",
    "wof:placetype":"venue"
},
  "geometry": {"coordinates":[4.7784528732,52.2563514709],"type":"Point"}
}