{
  "type": "Feature",
  "properties": {
    "iso:country":"NL",
    "sg:address":"D D Eisenhowerstraat 60",
    "sg:city":"Groningen",
    "sg:orig_category":"Vertaal- And Tolkenbureaus",
    "sg:phone":"+31 50 527 2220",
    "sg:postcode":"9728 RX",
    "sg:province":"Groningen",
    "wof:name":"English Ink !",
    "wof:placetype":"venue"
},
  "geometry": {"coordinates":[6.557478,53.189919],"type":"Point"}
}