{
  "type": "Feature",
  "properties": {
    "addr:full":"St. Jorisplein 77 Ridderkerk Zuid-Holland 2981 GD",
    "addr:housenumber":"77",
    "addr:postcode":"2981 gd",
    "addr:street":"St. Jorisplein",
    "iso:country":"NL",
    "sg:address":"St. Jorisplein 77",
    "sg:city":"Ridderkerk",
    "sg:orig_category":"Bibliotheken And Openbare Archieven",
    "sg:phone":"+31 180 425 504",
    "sg:postcode":"2981 GD",
    "sg:province":"Zuid-Holland",
    "wof:name":"Stichting Openbare Bibliotheek Ridderkerk",
    "wof:placetype":"venue"
},
  "geometry": {"coordinates":[4.600159,51.870174],"type":"Point"}
}