{
  "type": "Feature",
  "properties": {
    "iso:country":"NL",
    "sg:address":"Julianastr 32",
    "sg:city":"Wissenkerke",
    "sg:orig_category":"Kinderopvang",
    "sg:phone":"+31 113 371 689",
    "sg:postcode":"4491 GB",
    "sg:province":"Zeeland",
    "wof:name":"Ziezo",
    "wof:placetype":"venue"
},
  "geometry": {"coordinates":[3.745575,51.583328],"type":"Point"}
}