{
  "type": "Feature",
  "properties": {
    "addr:full":"Vlaswg 4 Moerdyk Noord-Brabant 4782 PW",
    "addr:housenumber":"4",
    "addr:postcode":"4782 pw",
    "addr:street":"Vlaswg",
    "iso:country":"NL",
    "sg:address":"Vlaswg 4",
    "sg:city":"Moerdyk",
    "sg:orig_category":"Verpakkingen En Verpakkingsmaterialen",
    "sg:phone":"+31 168 356 666",
    "sg:postcode":"4782 PW",
    "sg:province":"Noord-Brabant",
    "wof:name":"Chemie-Pack Bv",
    "wof:placetype":"venue"
},
  "geometry": {"coordinates":[4.605323,51.691555],"type":"Point"}
}