{
  "type": "Feature",
  "properties": {
    "addr:full":"Vd Capellenstr 147 Zwolle Overijssel 8014 VW",
    "addr:housenumber":"147",
    "addr:postcode":"8014 vw",
    "iso:country":"NL",
    "sg:address":"Vd Capellenstr 147",
    "sg:city":"Zwolle",
    "sg:orig_category":"Fietsen En Bromfietsen",
    "sg:phone":"+31 38 466 2895",
    "sg:postcode":"8014 VW",
    "sg:province":"Overijssel",
    "wof:name":"Grobb\u00e9e, Fietsspeciaalzaak",
    "wof:placetype":"venue"
},
  "geometry": {"coordinates":[6.110857,52.482822],"type":"Point"}
}