{
  "type": "Feature",
  "properties": {
    "addr:full":"Hoogkana 19 Ingen Gelderland 4031 MK",
    "addr:housenumber":"19",
    "addr:postcode":"4031",
    "addr:street":"Hoogkana;Gelderland",
    "iso:country":"NL",
    "sg:address":"Hoogkana 19",
    "sg:city":"Ingen",
    "sg:orig_category":"Boekhouders",
    "sg:phone":"+31 344 663 585",
    "sg:postcode":"4031 MK",
    "sg:province":"Gelderland",
    "wof:name":"Hatek Technical Development",
    "wof:placetype":"venue"
},
  "geometry": {"coordinates":[21.751289,41.60281],"type":"Point"}
}