{
  "type": "Feature",
  "properties": {
    "addr:full":"Edisonbaan 4 Nieuwegein Utrecht 3439 MN",
    "addr:housenumber":"4",
    "addr:postcode":"3439 mn",
    "addr:street":"Edisonbaan",
    "iso:country":"NL",
    "sg:address":"Edisonbaan 4",
    "sg:city":"Nieuwegein",
    "sg:orig_category":"Directmail",
    "sg:phone":"+31 30 600 2500",
    "sg:postcode":"3439 MN",
    "sg:province":"Utrecht",
    "wof:name":"Wegener Bv",
    "wof:placetype":"venue"
},
  "geometry": {"coordinates":[5.101602,52.034363],"type":"Point"}
}