{
  "type": "Feature",
  "properties": {
    "addr:full":"Weesperzijde 115 Amsterdam Noord-Holland 1091 EN",
    "addr:housenumber":"115",
    "addr:postcode":"1091 en",
    "addr:street":"Weesperzijde",
    "iso:country":"NL",
    "sg:address":"Weesperzijde 115",
    "sg:city":"Amsterdam",
    "sg:orig_category":"Fitnesscentra",
    "sg:phone":"+31 20 665 8896",
    "sg:postcode":"1091 EN",
    "sg:province":"Noord-Holland",
    "wof:name":"Kops Sportcentrum",
    "wof:placetype":"venue"
},
  "geometry": {"coordinates":[4.912165,52.350723],"type":"Point"}
}