{
  "type": "Feature",
  "properties": {
    "iso:country":"NL",
    "sg:address":"Het Rond 71",
    "sg:city":"Houten",
    "sg:orig_category":"Hypotheken",
    "sg:phone":"+31 30 637 5566",
    "sg:postcode":"3995 DL",
    "sg:province":"Utrecht",
    "sg:website":"http://www.geldxpert.nl",
    "wof:name":"Geldxpert",
    "wof:placetype":"venue"
},
  "geometry": {"coordinates":[5.168971,52.035099],"type":"Point"}
}