{
  "type": "Feature",
  "properties": {
    "iso:country":"NL",
    "sg:address":"Molenmakershoek 13",
    "sg:city":"Apeldoorn",
    "sg:orig_category":"Puien",
    "sg:phone":"+31 55 542 0235",
    "sg:postcode":"7328 JK",
    "sg:province":"Gelderland",
    "sg:website":"http://www.spijkers.nl",
    "wof:name":"Spijkers & Brink",
    "wof:placetype":"venue"
},
  "geometry": {"coordinates":[5.981757,52.206249],"type":"Point"}
}