{
  "type": "Feature",
  "properties": {
    "iso:country":"NL",
    "sg:address":"Mr Dr Jonkerln 22",
    "sg:city":"Anna Paulowna",
    "sg:orig_category":"Pianostemmen En -Reparatie",
    "sg:phone":"+31 223 532 468",
    "sg:postcode":"1761 GD",
    "sg:province":"Noord-Holland",
    "wof:name":"Arends",
    "wof:placetype":"venue"
},
  "geometry": {"coordinates":[4.83282,52.86256],"type":"Point"}
}