{
  "type": "Feature",
  "properties": {
    "addr:full":"Postbus 480 Aalsmeer North Holland 1430 AL",
    "addr:housenumber":"480",
    "addr:postcode":"1430 al",
    "addr:street":"Postbus",
    "iso:country":"NL",
    "sg:address":"Postbus 480",
    "sg:city":"Aalsmeer",
    "sg:orig_category":"Verenigingen En Stichtingen",
    "sg:phone":"+31 297 346 682",
    "sg:postcode":"1430 AL",
    "sg:province":"North Holland",
    "wof:name":"Vluchtelingen Werk Sova, Sticht",
    "wof:placetype":"venue"
},
  "geometry": {"coordinates":[4.749068,52.266991],"type":"Point"}
}