{
  "type": "Feature",
  "properties": {
    "addr:full":"Gijsbrecht Van Amstelstr 107 Hilversum Noord-Holland 1214 AW",
    "addr:housenumber":"107",
    "addr:postcode":"1214 aw",
    "addr:street":"Gijsbrecht Van Amstelstr",
    "iso:country":"NL",
    "sg:address":"Gijsbrecht Van Amstelstr 107",
    "sg:city":"Hilversum",
    "sg:orig_category":"Diverse Consumentenartikelen Gh",
    "sg:phone":"+31 35 623 1155",
    "sg:postcode":"1214 AW",
    "sg:province":"Noord-Holland",
    "wof:name":"Elisha Bv",
    "wof:placetype":"venue"
},
  "geometry": {"coordinates":[5.171363,52.215794],"type":"Point"}
}