{
  "type": "Feature",
  "properties": {
    "iso:country":"NL",
    "sg:address":"Winkelcentrum 1",
    "sg:city":"Etten Leur",
    "sg:orig_category":"Poeliers",
    "sg:phone":"+31 76 503 7025",
    "sg:postcode":"4873 AA",
    "sg:province":"Noord-Brabant",
    "sg:website":"http://www.poelier.com",
    "wof:name":"Schrauwen",
    "wof:placetype":"venue"
},
  "geometry": {"coordinates":[4.635431,51.568344],"type":"Point"}
}