{
  "type": "Feature",
  "properties": {
    "addr:full":"2E Loosterln 7 Vriescheloo Groningen 9699 PR",
    "addr:housenumber":"7",
    "addr:postcode":"9699 pr",
    "addr:street":"2E Loosterln",
    "iso:country":"NL",
    "sg:address":"2E Loosterln 7",
    "sg:city":"Vriescheloo",
    "sg:orig_category":"Beeldende Kunstenaars",
    "sg:phone":"+31 597 541 457",
    "sg:postcode":"9699 PR",
    "sg:province":"Groningen",
    "wof:name":"Seyferth, Joan",
    "wof:placetype":"venue"
},
  "geometry": {"coordinates":[7.113417,53.069839],"type":"Point"}
}