{
  "type": "Feature",
  "properties": {
    "addr:full":"Hoofdstr 1 Hoogeveen Drenthe 7902 EA",
    "addr:housenumber":"1",
    "addr:postcode":"7902 ea",
    "addr:street":"Hoofdstr",
    "iso:country":"NL",
    "sg:address":"Hoofdstr 1",
    "sg:city":"Hoogeveen",
    "sg:orig_category":"Makelaars En Adviseurs Onroerende Goederen",
    "sg:phone":"+31 528 267 088",
    "sg:postcode":"7902 EA",
    "sg:province":"Drenthe",
    "wof:name":"Woonaccent",
    "wof:placetype":"venue"
},
  "geometry": {"coordinates":[6.477609,52.728756],"type":"Point"}
}