{
  "type": "Feature",
  "properties": {
    "addr:full":"J C Beetsln 167 Hoofddorp Noord-Holland 2131 AL",
    "addr:housenumber":"167",
    "addr:postcode":"2131 al",
    "addr:street":"J C Beetsln",
    "iso:country":"NL",
    "sg:address":"J C Beetsln 167",
    "sg:city":"Hoofddorp",
    "sg:orig_category":"Machinefabrieken",
    "sg:phone":"+31 23 562 3633",
    "sg:postcode":"2131 AL",
    "sg:province":"Noord-Holland",
    "wof:name":"Slootweg Bv",
    "wof:placetype":"venue"
},
  "geometry": {"coordinates":[4.70066,52.322971],"type":"Point"}
}