{
  "type": "Feature",
  "properties": {
    "addr:full":"Azurietdk 49 Roosendaal Noord-Brabant 4706 BL",
    "addr:housenumber":"49",
    "addr:postcode":"4706 bl",
    "addr:street":"Azurietdk",
    "iso:country":"NL",
    "sg:address":"Azurietdk 49",
    "sg:city":"Roosendaal",
    "sg:orig_category":"Artsen - Huisartsen",
    "sg:phone":"+31 165 537 926",
    "sg:postcode":"4706 BL",
    "sg:province":"Noord-Brabant",
    "sg:website":"http://drcjgeijer.huisartsen.nl",
    "wof:name":"Geijer, C J A M",
    "wof:placetype":"venue"
},
  "geometry": {"coordinates":[4.486388,51.524254],"type":"Point"}
}