{
  "type": "Feature",
  "properties": {
    "iso:country":"NL",
    "sg:address":"Egchelsewg 36",
    "sg:city":"Egchel",
    "sg:orig_category":"Vakantieverblijven",
    "sg:phone":"+31 77 307 1736",
    "sg:postcode":"5987 AB",
    "sg:province":"Limburg",
    "sg:website":"http://www.catharina-hoeve.nl",
    "wof:name":"Catharina Hoeve",
    "wof:placetype":"venue"
},
  "geometry": {"coordinates":[5.971888,51.319283],"type":"Point"}
}