{
  "type": "Feature",
  "properties": {
    "addr:full":"V Dykstr 13 Hilversum North Holland 1222 CX",
    "addr:housenumber":"13",
    "addr:postcode":"1222 cx",
    "addr:street":"V Dykstr",
    "iso:country":"NL",
    "sg:address":"V Dykstr 13",
    "sg:city":"Hilversum",
    "sg:orig_category":"Pianostemmen En -Reparatie",
    "sg:phone":"+31 35 624 2059",
    "sg:postcode":"1222 CX",
    "sg:province":"North Holland",
    "wof:name":"Bouwmeester, Namle-D",
    "wof:placetype":"venue"
},
  "geometry": {"coordinates":[5.18488,52.2495],"type":"Point"}
}