{
  "type": "Feature",
  "properties": {
    "iso:country":"NL",
    "sg:address":"Van Alewijkstraat 36",
    "sg:city":"Beerzerveld",
    "sg:orig_category":"Overheidsdiensten",
    "sg:phone":"+31 523 252 204",
    "sg:postcode":"7685 PH",
    "sg:province":"Overijssel",
    "wof:name":"De Tuba",
    "wof:placetype":"venue"
},
  "geometry": {"coordinates":[6.5728139877,52.4954872131],"type":"Point"}
}