{
  "type": "Feature",
  "properties": {
    "addr:full":"Landschapstr 15 Delft Zuid-Holland 2614 WZ",
    "addr:housenumber":"15",
    "addr:postcode":"2614 wz",
    "addr:street":"Landschapstr",
    "iso:country":"NL",
    "sg:address":"Landschapstr 15",
    "sg:city":"Delft",
    "sg:orig_category":"Adviesbureaus Bedrijfsorganisatie",
    "sg:phone":"+31 15 214 7890",
    "sg:postcode":"2614 WZ",
    "sg:province":"Zuid-Holland",
    "wof:name":"Cocon",
    "wof:placetype":"venue"
},
  "geometry": {"coordinates":[4.340362,52.005802],"type":"Point"}
}