{
  "type": "Feature",
  "properties": {
    "addr:full":"Kon Wilhelminapln 2 Krimpen Ad Yssel Zuid-Holland 2921 AB",
    "addr:housenumber":"2",
    "addr:postcode":"2921 ab",
    "addr:street":"Kon Wilhelminapln",
    "iso:country":"NL",
    "sg:address":"Kon Wilhelminapln 2",
    "sg:city":"Krimpen Ad Yssel",
    "sg:classifiers":[
        {
            "category":"Food & Beverages",
            "subcategory":"Bakery",
            "type":"Retail Goods"
        }
    ],
    "sg:phone":"+31 180 512 532",
    "sg:postcode":"2921 AB",
    "sg:province":"Zuid-Holland",
    "sg:tags":[
        "brood",
        "en",
        "banket"
    ],
    "wof:name":"Casteleijn",
    "wof:placetype":"venue"
},
  "geometry": {"coordinates":[4.58483,51.913734],"type":"Point"}
}