{
  "type": "Feature",
  "properties": {
    "iso:country":"NL",
    "sg:address":"Grevelingen 29",
    "sg:city":"Heemstede",
    "sg:orig_category":"Adviesbureaus",
    "sg:phone":"+31 23 547 8077",
    "sg:postcode":"2105 ZE",
    "sg:province":"Noord-Holland",
    "wof:name":"Overflow",
    "wof:placetype":"venue"
},
  "geometry": {"coordinates":[4.602345,52.341782],"type":"Point"}
}