{
  "type": "Feature",
  "properties": {
    "iso:country":"NL",
    "sg:address":"Kerkstraat 107",
    "sg:city":"Reutum",
    "sg:orig_category":"Metaalwerken",
    "sg:phone":"+31 541 670 415",
    "sg:postcode":"7667 PW",
    "sg:province":"NL.08",
    "wof:name":"H.J.O. Deterink",
    "wof:placetype":"venue"
},
  "geometry": {"coordinates":[6.847576,52.38953],"type":"Point"}
}