{
  "type": "Feature",
  "properties": {
    "addr:full":"Hooftstr 93 Alphen Aan Den Ryn Zuid-Holland 2406 GE",
    "addr:housenumber":"93",
    "addr:postcode":"2406",
    "addr:street":"Hooftstr;Aan Den Ryn",
    "iso:country":"NL",
    "sg:address":"Hooftstr 93",
    "sg:city":"Alphen Aan Den Ryn",
    "sg:orig_category":"Bloemen En Planten",
    "sg:phone":"+31 172 474 942",
    "sg:postcode":"2406 GE",
    "sg:province":"Zuid-Holland",
    "sg:website":"http://www.hofmakerij.nl",
    "wof:name":"Hofmakerij, De",
    "wof:placetype":"venue"
},
  "geometry": {"coordinates":[4.663479,52.132488],"type":"Point"}
}