{
  "type": "Feature",
  "properties": {
    "iso:country":"NL",
    "sg:address":"Bouwstraat 48",
    "sg:city":"Rijssen",
    "sg:orig_category":"Kappers",
    "sg:phone":"+31 548 517 986",
    "sg:postcode":"7462 AZ",
    "sg:province":"Overijssel",
    "wof:name":"Hair By Henk-Jan",
    "wof:placetype":"venue"
},
  "geometry": {"coordinates":[6.5188398361,52.307308197],"type":"Point"}
}