{
  "type": "Feature",
  "properties": {
    "addr:full":"Mierennesthofje 3 Leiden Zuid-Holland 2312 HW",
    "addr:housenumber":"3",
    "addr:postcode":"2312 hw",
    "addr:street":"Mierennesthofje",
    "iso:country":"NL",
    "sg:address":"Mierennesthofje 3",
    "sg:city":"Leiden",
    "sg:orig_category":"Beeldende Kunstenaars",
    "sg:phone":"+31 71 514 1329",
    "sg:postcode":"2312 HW",
    "sg:province":"Zuid-Holland",
    "wof:name":"Houwelingen & Prins, Atelier Van",
    "wof:placetype":"venue"
},
  "geometry": {"coordinates":[4.494565,52.158901],"type":"Point"}
}