{
  "type": "Feature",
  "properties": {
    "addr:full":"Rijksweg Centrum 18 Geleen Limburg 6161 EE",
    "addr:housenumber":"18",
    "addr:postcode":"6161 ee",
    "addr:street":"Rijksweg Centrum",
    "iso:country":"NL",
    "sg:address":"Rijksweg Centrum 18",
    "sg:city":"Geleen",
    "sg:classifiers":[
        {
            "category":"Retail",
            "subcategory":"Photofinishing",
            "type":"Services"
        }
    ],
    "sg:phone":"+31 46 475 2637",
    "sg:postcode":"6161 EE",
    "sg:province":"Limburg",
    "sg:tags":[
        "foto",
        "film"
    ],
    "wof:name":"Foto Lassan",
    "wof:placetype":"venue"
},
  "geometry": {"coordinates":[5.830503,50.969734],"type":"Point"}
}