{
  "type": "Feature",
  "properties": {
    "addr:full":"Broederenstr 25 Deventer NL.08 7411 LA",
    "addr:housenumber":"25;nl.08",
    "addr:postcode":"7411 la",
    "addr:street":"Broederenstr",
    "iso:country":"NL",
    "sg:address":"Broederenstr 25",
    "sg:city":"Deventer",
    "sg:orig_category":"Schoenen",
    "sg:phone":"+31 570 612 651",
    "sg:postcode":"7411 LA",
    "sg:province":"NL.08",
    "sg:website":"http://www.articshoe.nl",
    "wof:name":"Artic",
    "wof:placetype":"venue"
},
  "geometry": {"coordinates":[6.157125,52.253803],"type":"Point"}
}