{
  "type": "Feature",
  "properties": {
    "iso:country":"NL",
    "sg:address":"Jacob Catsstraat 19",
    "sg:city":"Krimpen A/D Lek",
    "sg:orig_category":"Bibliotheken And Openbare Archieven",
    "sg:phone":"+31 180 521 951",
    "sg:postcode":"2931 XD",
    "sg:province":"Zuid-Holland",
    "wof:name":"Bibliotheken",
    "wof:placetype":"venue"
},
  "geometry": {"coordinates":[4.631714,51.895145],"type":"Point"}
}