{
  "type": "Feature",
  "properties": {
    "addr:full":"Lopikerstr 44 Schoonhoven Zuid-Holland 2871 BZ",
    "addr:housenumber":"44",
    "addr:postcode":"2871 bz",
    "addr:street":"Lopikerstr",
    "iso:country":"NL",
    "sg:address":"Lopikerstr 44",
    "sg:city":"Schoonhoven",
    "sg:orig_category":"Dierenvoeder - Fabrieken",
    "sg:phone":"+31 182 384 767",
    "sg:postcode":"2871 BZ",
    "sg:province":"Zuid-Holland",
    "sg:website":"http://www.uitdekunst.nl",
    "wof:name":"Uit De Kunst Vof",
    "wof:placetype":"venue"
},
  "geometry": {"coordinates":[4.853902,51.946541],"type":"Point"}
}