{
  "type": "Feature",
  "properties": {
    "addr:full":"3E Pynackerstr 5 Rotterdam Zuid-Holland 3035 CK",
    "addr:housenumber":"5",
    "addr:postcode":"3035 ck",
    "addr:street":"3E Pynackerstr",
    "iso:country":"NL",
    "sg:address":"3E Pynackerstr 5",
    "sg:city":"Rotterdam",
    "sg:orig_category":"Artiestenbenodigdheden",
    "sg:phone":"+31 10 465 5976",
    "sg:postcode":"3035 CK",
    "sg:province":"Zuid-Holland",
    "wof:name":"Party Starter",
    "wof:placetype":"venue"
},
  "geometry": {"coordinates":[4.478339,51.93383],"type":"Point"}
}