{
  "type": "Feature",
  "properties": {
    "addr:full":"Sportlaan 10 Emmeloord Flevoland 8302 AZ",
    "addr:housenumber":"10",
    "addr:postcode":"8302",
    "addr:street":"Sportlaan;Flevoland",
    "iso:country":"NL",
    "sg:address":"Sportlaan 10",
    "sg:city":"Emmeloord",
    "sg:orig_category":"Verzekeringen",
    "sg:phone":"+31 527 613 555",
    "sg:postcode":"8302 AZ",
    "sg:province":"Flevoland",
    "wof:name":"Assurantiekantoor A. De Lange Bv",
    "wof:placetype":"venue"
},
  "geometry": {"coordinates":[5.763489,52.713005],"type":"Point"}
}