{
  "type": "Feature",
  "properties": {
    "addr:full":"Visstraat 37 'S Hertogenbosch Noord-Brabant 5211 DM",
    "addr:housenumber":"37",
    "addr:postcode":"5211 dm",
    "addr:street":"Visstraat;' S",
    "iso:country":"NL",
    "sg:address":"Visstraat 37",
    "sg:city":"'S Hertogenbosch",
    "sg:orig_category":"Werving And Selectie Van Tijdelijk Personeel And Uitzendkantoren",
    "sg:phone":"+31 73 692 8000",
    "sg:postcode":"5211 DM",
    "sg:province":"Noord-Brabant",
    "wof:name":"Short Track Bv",
    "wof:placetype":"venue"
},
  "geometry": {"coordinates":[5.2996058464,51.6904830933],"type":"Point"}
}