{
  "type": "Feature",
  "properties": {
    "addr:full":"Brugstraat 8 Almkerk Noord-Brabant 4286 AW",
    "addr:housenumber":"8",
    "addr:postcode":"4286 aw",
    "addr:street":"Brugstraat",
    "iso:country":"NL",
    "sg:address":"Brugstraat 8",
    "sg:city":"Almkerk",
    "sg:orig_category":"Algemene Werktuigbouw",
    "sg:phone":"+31 183 405 091",
    "sg:postcode":"4286 AW",
    "sg:province":"Noord-Brabant",
    "wof:name":"Romeijn Betonijzerlaswerken",
    "wof:placetype":"venue"
},
  "geometry": {"coordinates":[4.964883,51.771049],"type":"Point"}
}