{
  "type": "Feature",
  "properties": {
    "addr:full":"Raat 13 Blaricum Noord-Holland 1261 LX",
    "addr:housenumber":"13",
    "addr:postcode":"1261 lx",
    "addr:street":"Raat",
    "iso:country":"NL",
    "sg:address":"Raat 13",
    "sg:city":"Blaricum",
    "sg:orig_category":"Stukadoorsbedrijven",
    "sg:phone":"+31 35 526 1589",
    "sg:postcode":"1261 LX",
    "sg:province":"Noord-Holland",
    "wof:name":"Floris",
    "wof:placetype":"venue"
},
  "geometry": {"coordinates":[5.267872,52.284775],"type":"Point"}
}