{
  "type": "Feature",
  "properties": {
    "addr:full":"Warmoezierskade 1 Gouda South Holland 2805 PR",
    "addr:housenumber":"1",
    "addr:postcode":"2805 pr",
    "addr:street":"Warmoezierskade",
    "iso:country":"NL",
    "sg:address":"Warmoezierskade 1",
    "sg:city":"Gouda",
    "sg:orig_category":"Keramiek - Fabrieken En Groothandel",
    "sg:phone":"+31 182 512 950",
    "sg:postcode":"2805 PR",
    "sg:province":"South Holland",
    "wof:name":"Bonaparte",
    "wof:placetype":"venue"
},
  "geometry": {"coordinates":[4.718247,52.018188],"type":"Point"}
}