{
  "type": "Feature",
  "properties": {
    "addr:full":"1E Welplaatdwwg 2 Botlek Rt Zuid-Holland 3197 KT",
    "addr:housenumber":"2",
    "addr:postcode":"rt;3197 kt",
    "addr:street":"1E Welplaatdwwg",
    "iso:country":"NL",
    "sg:address":"1E Welplaatdwwg 2",
    "sg:city":"Botlek Rt",
    "sg:orig_category":"Margarine, Olie En Vet - Industrie",
    "sg:phone":"+31 10 416 6145",
    "sg:postcode":"3197 KT",
    "sg:province":"Zuid-Holland",
    "wof:name":"Maasfood Bv",
    "wof:placetype":"venue"
},
  "geometry": {"coordinates":[4.287971,51.881996],"type":"Point"}
}