{
  "type": "Feature",
  "properties": {
    "iso:country":"NL",
    "sg:address":"Dresdenln 31",
    "sg:city":"Rotterdam",
    "sg:orig_category":"Werving En Selectie",
    "sg:phone":"+31 10 218 9066",
    "sg:postcode":"3055 WD",
    "sg:province":"Zuid-Holland",
    "sg:website":"http://www.arbeidswens.nl",
    "wof:name":"Arbeidswens",
    "wof:placetype":"venue"
},
  "geometry": {"coordinates":[4.5000700951,51.9670944214],"type":"Point"}
}