{
  "type": "Feature",
  "properties": {
    "addr:full":"Kapoenstraat 18 Maastricht Limburg 6211 KW",
    "addr:housenumber":"18",
    "addr:postcode":"6211 kw",
    "addr:street":"Kapoenstraat",
    "iso:country":"NL",
    "sg:address":"Kapoenstraat 18",
    "sg:city":"Maastricht",
    "sg:orig_category":"Binnenhuisarchitecten",
    "sg:phone":"+31 43 325 3045",
    "sg:postcode":"6211 KW",
    "sg:province":"Limburg",
    "wof:name":"Pieter Spruyt Ontwerpburo Binnendingen",
    "wof:placetype":"venue"
},
  "geometry": {"coordinates":[5.689742,50.847042],"type":"Point"}
}