{
  "type": "Feature",
  "properties": {
    "iso:country":"NL",
    "sg:address":"Paradijsselpark 7",
    "sg:city":"Capelle Aan Den Ijssel",
    "sg:orig_category":"Vertaalbureaus",
    "sg:phone":"+31 10 450 4906",
    "sg:postcode":"2904 PA",
    "sg:province":"South Holland",
    "wof:name":"Common Sense",
    "wof:placetype":"venue"
},
  "geometry": {"coordinates":[4.607062,51.928162],"type":"Point"}
}