{
  "type": "Feature",
  "properties": {
    "addr:full":"Nieuwendammerkd 60 Amsterdam North Holland 1025 LZ",
    "addr:housenumber":"60",
    "addr:postcode":"1025 lz",
    "addr:street":"Nieuwendammerkd",
    "iso:country":"NL",
    "sg:address":"Nieuwendammerkd 60",
    "sg:city":"Amsterdam",
    "sg:orig_category":"Fotografie Reclame En Mode",
    "sg:phone":"+31 20 419 1010",
    "sg:postcode":"1025 LZ",
    "sg:province":"North Holland",
    "wof:name":"Tabak, Kees",
    "wof:placetype":"venue"
},
  "geometry": {"coordinates":[4.9373,52.400349],"type":"Point"}
}