{
  "type": "Feature",
  "properties": {
    "addr:full":"Helmusseln 12 Roermond Limburg 6041 AW",
    "addr:housenumber":"12",
    "addr:postcode":"6041 aw",
    "addr:street":"Helmusseln",
    "iso:country":"NL",
    "sg:address":"Helmusseln 12",
    "sg:city":"Roermond",
    "sg:orig_category":"Muziekinstrumenten - Fabrieken En Groothandel",
    "sg:phone":"+31 475 336 195",
    "sg:postcode":"6041 AW",
    "sg:province":"Limburg",
    "sg:website":"http://www.prolinemusic.nl",
    "wof:name":"Pro Line Music Bv",
    "wof:placetype":"venue"
},
  "geometry": {"coordinates":[5.991103,51.189888],"type":"Point"}
}