{
  "type": "Feature",
  "properties": {
    "addr:full":"Randweg 6 Culemborg Gelderland 4104 AC",
    "addr:housenumber":"6",
    "addr:postcode":"4104 ac",
    "addr:street":"Randweg;Gelderland",
    "iso:country":"NL",
    "sg:address":"Randweg 6",
    "sg:city":"Culemborg",
    "sg:orig_category":"Meubelreparatie And -Restauratie",
    "sg:phone":"+31 345 530 643",
    "sg:postcode":"4104 AC",
    "sg:province":"Gelderland",
    "wof:name":"Euromeubel",
    "wof:placetype":"venue"
},
  "geometry": {"coordinates":[5.220801,51.945171],"type":"Point"}
}