{
  "type": "Feature",
  "properties": {
    "iso:country":"NL",
    "sg:address":"Weidelaan 124",
    "sg:city":"Raalte",
    "sg:orig_category":"Verhuur Catering-, Feest- En Evenementbenodigdheden",
    "sg:phone":"+31 572 357 398",
    "sg:postcode":"8103 ET",
    "sg:province":"NL.08",
    "wof:name":"Schottman Industries Bv",
    "wof:placetype":"venue"
},
  "geometry": {"coordinates":[6.286634,52.395901],"type":"Point"}
}