{
  "type": "Feature",
  "properties": {
    "addr:full":"S Gravelandsewg 39 Weesp North Holland 1381 HK",
    "addr:housenumber":"39",
    "addr:postcode":"1381 hk",
    "iso:country":"NL",
    "sg:address":"S Gravelandsewg 39",
    "sg:city":"Weesp",
    "sg:orig_category":"Grondwerken",
    "sg:phone":"+31 6 53864210",
    "sg:postcode":"1381 HK",
    "sg:province":"North Holland",
    "wof:name":"Gwa",
    "wof:placetype":"venue"
},
  "geometry": {"coordinates":[5.075354,52.298721],"type":"Point"}
}