{
  "type": "Feature",
  "properties": {
    "addr:full":"1E Vd Kunstr 292 S Gravenhage Zuid-Holland 2521 AV",
    "addr:housenumber":"292;gravenhage",
    "addr:postcode":"2521 av",
    "addr:street":"1E Vd;S",
    "iso:country":"NL",
    "sg:address":"1E Vd Kunstr 292",
    "sg:city":"S Gravenhage",
    "sg:orig_category":"Verenigingen En Stichtingen",
    "sg:phone":"+31 70 330 0608",
    "sg:postcode":"2521 AV",
    "sg:province":"Zuid-Holland",
    "sg:website":"http://www.worldunited.com",
    "wof:name":"World United",
    "wof:placetype":"venue"
},
  "geometry": {"coordinates":[4.32071,52.062988],"type":"Point"}
}