{
  "type": "Feature",
  "properties": {
    "addr:full":"Kempenaar 148 Lelystad NL. 8242 BA",
    "addr:housenumber":"148",
    "addr:postcode":"8242 ba",
    "addr:street":"Kempenaar;Nl.",
    "iso:country":"NL",
    "sg:address":"Kempenaar 148",
    "sg:city":"Lelystad",
    "sg:orig_category":"Autoruiten",
    "sg:phone":"+31 320 226 969",
    "sg:postcode":"8242 BA",
    "sg:province":"NL.",
    "sg:website":"http://www.polderzicht.nl",
    "wof:name":"Polderzicht Autoruitenservice",
    "wof:placetype":"venue"
},
  "geometry": {"coordinates":[5.45996,52.518116],"type":"Point"}
}