{
  "type": "Feature",
  "properties": {
    "addr:full":"Bregebuorren 11 Easterlittens Provincie Friesland 8835 XD",
    "addr:housenumber":"11",
    "addr:postcode":"8835 xd",
    "addr:street":"Bregebuorren;Provincie Friesland",
    "iso:country":"NL",
    "sg:address":"Bregebuorren 11",
    "sg:city":"Easterlittens",
    "sg:orig_category":"Glaszetten",
    "sg:phone":"+31 517 342 495",
    "sg:postcode":"8835 XD",
    "sg:province":"Provincie Friesland",
    "wof:name":"Froni Minkema - Langhout",
    "wof:placetype":"venue"
},
  "geometry": {"coordinates":[5.64954,53.134571],"type":"Point"}
}