{
  "type": "Feature",
  "properties": {
    "addr:full":"Hessenweg 34 De Bilt Utrecht 3731 JK",
    "addr:housenumber":"34",
    "addr:postcode":"3731 jk",
    "addr:street":"Hessenweg",
    "iso:country":"NL",
    "sg:address":"Hessenweg 34",
    "sg:city":"De Bilt",
    "sg:orig_category":"Zuivelproducten",
    "sg:phone":"+31 30 220 2852",
    "sg:postcode":"3731 JK",
    "sg:province":"Utrecht",
    "wof:name":"Kreugel Kaas Vof",
    "wof:placetype":"venue"
},
  "geometry": {"coordinates":[5.179599,52.107231],"type":"Point"}
}