{
  "type": "Feature",
  "properties": {
    "addr:full":"Pannerdenstr 21 Rotterdam Zuid-Holland 3087 CH",
    "addr:housenumber":"21",
    "addr:postcode":"3087",
    "addr:street":"Pannerdenstr",
    "iso:country":"NL",
    "sg:address":"Pannerdenstr 21",
    "sg:city":"Rotterdam",
    "sg:orig_category":"Hydraulische Apparaten En Installaties",
    "sg:phone":"+31 10 487 3500",
    "sg:postcode":"3087 CH",
    "sg:province":"Zuid-Holland",
    "sg:website":"http://www.stork-dks-wissekerke.nl",
    "wof:name":"Stork Tools & Services",
    "wof:placetype":"venue"
},
  "geometry": {"coordinates":[-73.97154999999999,42.786839],"type":"Point"}
}