{
  "type": "Feature",
  "properties": {
    "iso:country":"NL",
    "sg:address":"Zeeanemoonwg 4B",
    "sg:city":"Renesse",
    "sg:orig_category":"Onroerende Goederen",
    "sg:phone":"+31 111 461 294",
    "sg:postcode":"4325 BZ",
    "sg:province":"Zeeland",
    "wof:name":"Patrisan Bv",
    "wof:placetype":"venue"
},
  "geometry": {"coordinates":[3.770824,51.732193],"type":"Point"}
}