{
  "type": "Feature",
  "properties": {
    "addr:full":"Zeeanemoonwg 4B Renesse Zeeland 4325 BZ",
    "addr:housenumber":"4b",
    "addr:postcode":"4325 bz",
    "addr:street":"Zeeanemoonwg",
    "iso:country":"NL",
    "sg:address":"Zeeanemoonwg 4B",
    "sg:city":"Renesse",
    "sg:orig_category":"Onroerende Goederen",
    "sg:phone":"+31 111 461 294",
    "sg:postcode":"4325 BZ",
    "sg:province":"Zeeland",
    "wof:name":"Patrisan Bv",
    "wof:placetype":"venue"
},
  "geometry": {"coordinates":[3.770824,51.732193],"type":"Point"}
}