{
  "type": "Feature",
  "properties": {
    "addr:full":"Weverstr 2 Oosterbeek Gelderland 6862 DP",
    "addr:housenumber":"2",
    "addr:postcode":"6862 dp",
    "addr:street":"Weverstr;Gelderland",
    "iso:country":"NL",
    "sg:address":"Weverstr 2",
    "sg:city":"Oosterbeek",
    "sg:orig_category":"Verhuur",
    "sg:phone":"+31 26 446 1222",
    "sg:postcode":"6862 DP",
    "sg:province":"Gelderland",
    "wof:name":"Verhoef, R",
    "wof:placetype":"venue"
},
  "geometry": {"coordinates":[5.844195,51.986244],"type":"Point"}
}