{
  "type": "Feature",
  "properties": {
    "iso:country":"NL",
    "sg:address":"De Bieslook 27",
    "sg:city":"Rozenburg Zh",
    "sg:orig_category":"Kantoor- En Secretariaatsservice",
    "sg:phone":"+31 181 218 923",
    "sg:postcode":"3181 RG",
    "sg:province":"South Holland",
    "wof:name":"Typhone",
    "wof:placetype":"venue"
},
  "geometry": {"coordinates":[4.2320752144,51.9038925171],"type":"Point"}
}