{
  "type": "Feature",
  "properties": {
    "addr:full":"Hoeveveld 6 Molenhoek Lb Limburg 6584 GG",
    "addr:housenumber":"6",
    "addr:postcode":"lb;6584 gg",
    "addr:street":"Hoeveveld",
    "iso:country":"NL",
    "sg:address":"Hoeveveld 6",
    "sg:city":"Molenhoek Lb",
    "sg:orig_category":"Autoreclame",
    "sg:phone":"+31 24 358 1405",
    "sg:postcode":"6584 GG",
    "sg:province":"Limburg",
    "wof:name":"Apart",
    "wof:placetype":"venue"
},
  "geometry": {"coordinates":[5.874851,51.76144],"type":"Point"}
}