{
  "type": "Feature",
  "properties": {
    "addr:full":"Nassaustr 2 St Annaparochie Provincie Friesland 9076 CE",
    "addr:housenumber":"2",
    "addr:postcode":"9076 ce",
    "addr:street":"Nassaustr;Friesland",
    "iso:country":"NL",
    "sg:address":"Nassaustr 2",
    "sg:city":"St Annaparochie",
    "sg:orig_category":"Adviesbureaus Bouwkunde",
    "sg:phone":"+31 518 401 250",
    "sg:postcode":"9076 CE",
    "sg:province":"Provincie Friesland",
    "wof:name":"Sloots, J H",
    "wof:placetype":"venue"
},
  "geometry": {"coordinates":[5.65791,53.27314],"type":"Point"}
}