{
  "type": "Feature",
  "properties": {
    "addr:full":"Esschebaan 60 Oisterwyk Noord-Brabant 5062 BD",
    "addr:housenumber":"60",
    "addr:postcode":"5062 bd",
    "addr:street":"Esschebaan",
    "iso:country":"NL",
    "sg:address":"Esschebaan 60",
    "sg:city":"Oisterwyk",
    "sg:orig_category":"Bejaarden - Verzorgingstehuizen",
    "sg:phone":"+31 13 523 3700",
    "sg:postcode":"5062 BD",
    "sg:province":"Noord-Brabant",
    "wof:name":"Burghtweide, Service Flat",
    "wof:placetype":"venue"
},
  "geometry": {"coordinates":[5.2082390785,51.5804481506],"type":"Point"}
}