{
  "type": "Feature",
  "properties": {
    "iso:country":"NL",
    "sg:address":"Langewg 115",
    "sg:city":"Gennep",
    "sg:classifiers":[
        {
            "category":"Personal",
            "subcategory":"Nail Salon",
            "type":"Services"
        }
    ],
    "sg:phone":"+31 485 513 244",
    "sg:postcode":"6591 XW",
    "sg:province":"Limburg",
    "sg:tags":[
        "pedicure"
    ],
    "wof:name":"Sijstermanns, A S F",
    "wof:placetype":"venue"
},
  "geometry": {"coordinates":[5.97119,51.699299],"type":"Point"}
}