{
  "type": "Feature",
  "properties": {
    "addr:full":"J Israelsstr 12 Oisterwyk Noord-Brabant 5062 LR",
    "addr:housenumber":"12",
    "addr:postcode":"5062 lr",
    "addr:street":"Oisterwyk",
    "iso:country":"NL",
    "sg:address":"J Israelsstr 12",
    "sg:city":"Oisterwyk",
    "sg:orig_category":"Meubelen - Fabrieken En Groothandel",
    "sg:phone":"+31 13 523 0930",
    "sg:postcode":"5062 LR",
    "sg:province":"Noord-Brabant",
    "wof:name":"Smit, Henk",
    "wof:placetype":"venue"
},
  "geometry": {"coordinates":[5.18371,51.572472],"type":"Point"}
}