{
  "type": "Feature",
  "properties": {
    "addr:full":"Gevers Deynootplein 185 'S Gravenhage Zuid-Holland 2586 CS",
    "addr:housenumber":"185 '",
    "addr:postcode":"2586 cs",
    "addr:street":"Gevers Deynootplein",
    "iso:country":"NL",
    "sg:address":"Gevers Deynootplein 185",
    "sg:city":"'S Gravenhage",
    "sg:classifiers":[
        {
            "category":"Fast Food",
            "type":"Food & Drink"
        }
    ],
    "sg:phone":"+31 70 355 7505",
    "sg:postcode":"2586 CS",
    "sg:province":"Zuid-Holland",
    "sg:tags":[
        "afhaal",
        "restaurant"
    ],
    "wof:name":"Egyptische Grill-Room Echnaton",
    "wof:placetype":"venue"
},
  "geometry": {"coordinates":[4.28158,52.112328],"type":"Point"}
}