{
  "type": "Feature",
  "properties": {
    "addr:full":"Dr Poelsstr 63C Oldenzaal NL.08 7572 ZV",
    "addr:housenumber":"63c;nl.08",
    "addr:postcode":"7572 zv",
    "iso:country":"NL",
    "sg:address":"Dr Poelsstr 63C",
    "sg:city":"Oldenzaal",
    "sg:orig_category":"Administratie- En Boekhoudkantoren",
    "sg:phone":"+31 541 356 555",
    "sg:postcode":"7572 ZV",
    "sg:province":"NL.08",
    "sg:website":"http://www.batist.com",
    "wof:name":"Batist",
    "wof:placetype":"venue"
},
  "geometry": {"coordinates":[6.928605,52.318897],"type":"Point"}
}