{
  "type": "Feature",
  "properties": {
    "iso:country":"NL",
    "sg:address":"Doctor Poelstraat 22",
    "sg:city":"Hulsberg",
    "sg:orig_category":"Koeriersdiensten",
    "sg:phone":"+31 45 405 2935",
    "sg:postcode":"6336 TS",
    "sg:province":"Limburg",
    "sg:website":"http://www.freelancechauffeur.nl",
    "wof:name":"Attent Koerier",
    "wof:placetype":"venue"
},
  "geometry": {"coordinates":[5.857316,50.88813],"type":"Point"}
}