{
  "type": "Feature",
  "properties": {
    "addr:full":"A Frankkd 24 Alphen Aan Den Ryn Zuid-Holland 2406 DH",
    "addr:housenumber":"24",
    "addr:postcode":"2406 dh",
    "addr:street":"Aan Den Ryn",
    "iso:country":"NL",
    "sg:address":"A Frankkd 24",
    "sg:city":"Alphen Aan Den Ryn",
    "sg:orig_category":"Bijouterie?n",
    "sg:phone":"+31 172 426 392",
    "sg:postcode":"2406 DH",
    "sg:province":"Zuid-Holland",
    "wof:name":"Clips",
    "wof:placetype":"venue"
},
  "geometry": {"coordinates":[4.664228,52.130581],"type":"Point"}
}