{
  "type": "Feature",
  "properties": {
    "addr:full":"Zijpe 16 Emmeloord NL. 8302 MB",
    "addr:housenumber":"16",
    "addr:postcode":"8302 mb",
    "addr:street":"Zijpe;Nl.",
    "iso:country":"NL",
    "sg:address":"Zijpe 16",
    "sg:city":"Emmeloord",
    "sg:orig_category":"Goederenvervoer Over De Weg",
    "sg:phone":"+31 527 616 958",
    "sg:postcode":"8302 MB",
    "sg:province":"NL.",
    "wof:name":"Top Transport",
    "wof:placetype":"venue"
},
  "geometry": {"coordinates":[5.731692,52.721359],"type":"Point"}
}