{
  "type": "Feature",
  "properties": {
    "addr:full":"Newtonstr 1 Tiel Gelderland 4004 KD",
    "addr:housenumber":"1",
    "addr:postcode":"4004 kd",
    "addr:street":"Newtonstr;Gelderland",
    "iso:country":"NL",
    "sg:address":"Newtonstr 1",
    "sg:city":"Tiel",
    "sg:orig_category":"Bedrijfsmechanisatie En -Automatisering",
    "sg:phone":"+31 344 634 245",
    "sg:postcode":"4004 KD",
    "sg:province":"Gelderland",
    "wof:name":"Bolhuis Bv",
    "wof:placetype":"venue"
},
  "geometry": {"coordinates":[5.43447,51.915119],"type":"Point"}
}