{
  "type": "Feature",
  "properties": {
    "iso:country":"NL",
    "sg:address":"De Meerpaal 11",
    "sg:city":"Drachten",
    "sg:orig_category":"Wegen And Sportterreinen",
    "sg:phone":"+31 512 586 210",
    "sg:postcode":"9206 AJ",
    "sg:province":"Provincie Friesland",
    "wof:name":"Van Der Wiel Infra & Milieu Bv",
    "wof:placetype":"venue"
},
  "geometry": {"coordinates":[6.0588722229,53.1104278564],"type":"Point"}
}