{
  "type": "Feature",
  "properties": {
    "addr:full":"Dijkstr 25 Appingedam Groningen 9901 AM",
    "addr:housenumber":"25",
    "addr:postcode":"9901",
    "addr:street":"Dijkstr",
    "iso:country":"NL",
    "sg:address":"Dijkstr 25",
    "sg:city":"Appingedam",
    "sg:classifiers":[
        {
            "category":"Shopping",
            "subcategory":"Adult",
            "type":"Retail Goods"
        }
    ],
    "sg:phone":"+31 596 622 981",
    "sg:postcode":"9901 AM",
    "sg:province":"Groningen",
    "sg:tags":[
        "lingerie",
        "en",
        "tricotage"
    ],
    "wof:name":"Rebelle, Fa",
    "wof:placetype":"venue"
},
  "geometry": {"coordinates":[6.857371,53.320778],"type":"Point"}
}