{
  "type": "Feature",
  "properties": {
    "addr:full":"Weijerbeemd 6 Weert Limburg 6004 MC",
    "addr:housenumber":"6",
    "addr:postcode":"6004 mc",
    "addr:street":"Weijerbeemd",
    "iso:country":"NL",
    "sg:address":"Weijerbeemd 6",
    "sg:city":"Weert",
    "sg:orig_category":"Metaalafval, Schrootrecycling And Sloperijen",
    "sg:phone":"+31 495 520 828",
    "sg:postcode":"6004 MC",
    "sg:province":"Limburg",
    "wof:name":"J.F. Pruijmboom",
    "wof:placetype":"venue"
},
  "geometry": {"coordinates":[5.740028,51.248215],"type":"Point"}
}