{
  "type": "Feature",
  "properties": {
    "addr:full":"Veenenburg 38 Gouda Zuid-Holland 2804 WZ",
    "addr:housenumber":"38",
    "addr:postcode":"2804 wz",
    "addr:street":"Veenenburg",
    "iso:country":"NL",
    "sg:address":"Veenenburg 38",
    "sg:city":"Gouda",
    "sg:orig_category":"Adviesbureaus Bedrijfsorganisatie",
    "sg:phone":"+31 182 699 460",
    "sg:postcode":"2804 WZ",
    "sg:province":"Zuid-Holland",
    "wof:name":"Kelfra Beheer Bv",
    "wof:placetype":"venue"
},
  "geometry": {"coordinates":[4.707232,52.033081],"type":"Point"}
}