{
  "type": "Feature",
  "properties": {
    "addr:full":"Grote Belt 14 Delfzijl Groningen 9934 RD",
    "addr:housenumber":"14",
    "addr:postcode":"9934 rd",
    "addr:street":"Grote Belt",
    "iso:country":"NL",
    "sg:address":"Grote Belt 14",
    "sg:city":"Delfzijl",
    "sg:orig_category":"Werving And Selectie Van Tijdelijk Personeel And Uitzendkantoren",
    "sg:phone":"+31 596 615 196",
    "sg:postcode":"9934 RD",
    "sg:province":"Groningen",
    "wof:name":"Dactylo",
    "wof:placetype":"venue"
},
  "geometry": {"coordinates":[6.911151886,53.3388900757],"type":"Point"}
}