{
  "type": "Feature",
  "properties": {
    "addr:full":"Bossenwaard 1 Zoetermeer South Holland 2716 DM",
    "addr:housenumber":"1",
    "addr:postcode":"2716 dm",
    "addr:street":"Bossenwaard",
    "iso:country":"NL",
    "sg:address":"Bossenwaard 1",
    "sg:city":"Zoetermeer",
    "sg:orig_category":"Bloemen En Planten",
    "sg:phone":"+31 79 352 1275",
    "sg:postcode":"2716 DM",
    "sg:province":"South Holland",
    "wof:name":"Gentiaan, De",
    "wof:placetype":"venue"
},
  "geometry": {"coordinates":[4.467755,52.055702],"type":"Point"}
}