{
  "type": "Feature",
  "properties": {
    "iso:country":"NL",
    "sg:address":"Seringenstraat 5",
    "sg:city":"Vlaardingen",
    "sg:classifiers":[
        {
            "category":"Education",
            "subcategory":"Preschool",
            "type":"Public Place"
        }
    ],
    "sg:phone":"+31 10 470 9589",
    "sg:postcode":"3135 ER",
    "sg:province":"Zuid-Holland",
    "sg:tags":[
        "kleuteronderwijs",
        "basis-"
    ],
    "wof:name":"T Palet Oost",
    "wof:placetype":"venue"
},
  "geometry": {"coordinates":[4.35888,51.918442],"type":"Point"}
}