{
  "type": "Feature",
  "properties": {
    "addr:full":"Putteweye 14 Heenvliet South Holland 3218 XM",
    "addr:housenumber":"14",
    "addr:postcode":"3218 xm",
    "addr:street":"Putteweye",
    "iso:country":"NL",
    "sg:address":"Putteweye 14",
    "sg:city":"Heenvliet",
    "sg:orig_category":"Zuivelproducten And Spijsoli?n Gh",
    "sg:phone":"+31 181 662 508",
    "sg:postcode":"3218 XM",
    "sg:province":"South Holland",
    "wof:name":"De Stans Bv",
    "wof:placetype":"venue"
},
  "geometry": {"coordinates":[4.237801,51.863029],"type":"Point"}
}