{
  "type": "Feature",
  "properties": {
    "addr:full":"Spuiweg 23 Dordrecht South Holland 3311 GT",
    "addr:housenumber":"23",
    "addr:postcode":"3311 gt",
    "addr:street":"Spuiweg",
    "iso:country":"NL",
    "sg:address":"Spuiweg 23",
    "sg:city":"Dordrecht",
    "sg:orig_category":"Kappers",
    "sg:phone":"+31 78 614 5046",
    "sg:postcode":"3311 GT",
    "sg:province":"South Holland",
    "wof:name":"De Hoofdzaak Haarmode",
    "wof:placetype":"venue"
},
  "geometry": {"coordinates":[4.6630959511,51.8112335205],"type":"Point"}
}