{
  "type": "Feature",
  "properties": {
    "addr:full":"Normerwg 6 Hippolytushoef North Holland 1777 JL",
    "addr:housenumber":"6",
    "addr:postcode":"1777 jl",
    "addr:street":"Normerwg",
    "iso:country":"NL",
    "sg:address":"Normerwg 6",
    "sg:city":"Hippolytushoef",
    "sg:orig_category":"Muziekdrukkerijen En -Uitgeverijen",
    "sg:phone":"+31 227 591 136",
    "sg:postcode":"1777 JL",
    "sg:province":"North Holland",
    "sg:website":"http://www.venonza.com",
    "wof:name":"Venonza Records",
    "wof:placetype":"venue"
},
  "geometry": {"coordinates":[4.944225,52.901485],"type":"Point"}
}