{
  "type": "Feature",
  "properties": {
    "addr:full":"Pr Hendrikln 44 Bilthoven Utrecht 3721 AT",
    "addr:housenumber":"44",
    "addr:postcode":"3721",
    "iso:country":"NL",
    "sg:address":"Pr Hendrikln 44",
    "sg:city":"Bilthoven",
    "sg:orig_category":"Yoga-Instituten",
    "sg:phone":"+31 30 225 0616",
    "sg:postcode":"3721 AT",
    "sg:province":"Utrecht",
    "sg:website":"http://www.samsara.nl",
    "wof:name":"Samsara Yoga Opleidingen",
    "wof:placetype":"venue"
},
  "geometry": {"coordinates":[5.199885,52.12532],"type":"Point"}
}