{
  "type": "Feature",
  "properties": {
    "iso:country":"NL",
    "sg:address":"Fokkerstr 42",
    "sg:city":"Zoetermeer",
    "sg:orig_category":"Mobiele- En Autotelefoons",
    "sg:phone":"+31 79 342 8015",
    "sg:postcode":"2722 NK",
    "sg:province":"Zuid-Holland",
    "sg:website":"http://www.boscar.nl",
    "wof:name":"Bos",
    "wof:placetype":"venue"
},
  "geometry": {"coordinates":[4.511461,52.052425],"type":"Point"}
}