{
  "type": "Feature",
  "properties": {
    "iso:country":"NL",
    "sg:address":"De Waaier 3 A",
    "sg:city":"Leimuiden",
    "sg:orig_category":"Schilderwerk",
    "sg:phone":"+31 172 507 096",
    "sg:postcode":"2451 VV",
    "sg:province":"Zuid-Holland",
    "sg:website":"http://www.vanderwolf.nl",
    "wof:name":"Meubelspuiterij Van Der Wolf",
    "wof:placetype":"venue"
},
  "geometry": {"coordinates":[4.68222,52.22282],"type":"Point"}
}