{
  "type": "Feature",
  "properties": {
    "iso:country":"NL",
    "sg:address":"Veenkampenweg 10",
    "sg:city":"Emmen",
    "sg:orig_category":"Hypotheken And Hypotheekbanken",
    "sg:phone":"+31 591 610 010",
    "sg:postcode":"7822 GS",
    "sg:province":"Drenthe",
    "wof:name":"Gepken Emmen",
    "wof:placetype":"venue"
},
  "geometry": {"coordinates":[6.901683,52.789139],"type":"Point"}
}