{
  "type": "Feature",
  "properties": {
    "addr:full":"R De Beerenb Wg 257 Dordrecht South Holland 3317 LM",
    "addr:housenumber":"257",
    "addr:postcode":"3317 lm",
    "addr:street":"Wg",
    "iso:country":"NL",
    "sg:address":"R De Beerenb Wg 257",
    "sg:city":"Dordrecht",
    "sg:orig_category":"Kinderopvang",
    "sg:phone":"+31 78 654 0070",
    "sg:postcode":"3317 LM",
    "sg:province":"South Holland",
    "wof:name":"Plons",
    "wof:placetype":"venue"
},
  "geometry": {"coordinates":[4.656506,51.811916],"type":"Point"}
}