{
  "type": "Feature",
  "properties": {
    "addr:full":"Dam 10 Zierikzee Zeeland 4301 JB",
    "addr:housenumber":"10",
    "addr:postcode":"4301 jb",
    "addr:street":"Dam",
    "iso:country":"NL",
    "sg:address":"Dam 10",
    "sg:city":"Zierikzee",
    "sg:orig_category":"Kappers",
    "sg:phone":"+31 111 481 666",
    "sg:postcode":"4301 JB",
    "sg:province":"Zeeland",
    "wof:name":"Take Off",
    "wof:placetype":"venue"
},
  "geometry": {"coordinates":[3.919691,51.650219],"type":"Point"}
}