{
  "type": "Feature",
  "properties": {
    "addr:full":"Marterhoeve 58 Leusden Utrecht 3831 TB",
    "addr:housenumber":"58",
    "addr:postcode":"3831 tb",
    "addr:street":"Marterhoeve",
    "iso:country":"NL",
    "sg:address":"Marterhoeve 58",
    "sg:city":"Leusden",
    "sg:orig_category":"Administratie- En Boekhoudkantoren",
    "sg:phone":"+31 33 465 0097",
    "sg:postcode":"3831 TB",
    "sg:province":"Utrecht",
    "wof:name":"Hurk-Gorter, Van Den",
    "wof:placetype":"venue"
},
  "geometry": {"coordinates":[5.432736,52.132175],"type":"Point"}
}