{
  "type": "Feature",
  "properties": {
    "addr:full":"Berkelstr 72 Utrecht Utrecht 3522 ER",
    "addr:housenumber":"72",
    "addr:postcode":"3522 er",
    "addr:street":"Berkelstr",
    "iso:country":"NL",
    "sg:address":"Berkelstr 72",
    "sg:city":"Utrecht",
    "sg:orig_category":"Schilders",
    "sg:phone":"+31 30 230 2936",
    "sg:postcode":"3522 ER",
    "sg:province":"Utrecht",
    "wof:name":"Aarendonk Schilderwerken",
    "wof:placetype":"venue"
},
  "geometry": {"coordinates":[5.114347,52.069283],"type":"Point"}
}