{
  "type": "Feature",
  "properties": {
    "addr:full":"Dorpsstr 140 Mierlo Noord-Brabant 5731 JL",
    "addr:housenumber":"140",
    "addr:postcode":"5731 jl",
    "iso:country":"NL",
    "sg:address":"Dorpsstr 140",
    "sg:city":"Mierlo",
    "sg:classifiers":[
        {
            "category":"Retail",
            "subcategory":"Auto Repair",
            "type":"Services"
        }
    ],
    "sg:phone":"+31 492 663 530",
    "sg:postcode":"5731 JL",
    "sg:province":"Noord-Brabant",
    "sg:tags":[
        "garage"
    ],
    "wof:name":"Raaijmakers, H P",
    "wof:placetype":"venue"
},
  "geometry": {"coordinates":[5.616414,51.443043],"type":"Point"}
}