{
  "type": "Feature",
  "properties": {
    "addr:full":"Kievitweide 51 Houten Utrecht 3993 DB",
    "addr:housenumber":"51",
    "addr:postcode":"3993 db",
    "addr:street":"Kievitweide",
    "iso:country":"NL",
    "sg:address":"Kievitweide 51",
    "sg:city":"Houten",
    "sg:orig_category":"Wasserettes And Stomerijen",
    "sg:phone":"+31 30 637 5311",
    "sg:postcode":"3993 DB",
    "sg:province":"Utrecht",
    "wof:name":"Jacobs-R Vd Werf",
    "wof:placetype":"venue"
},
  "geometry": {"coordinates":[5.1734519005,52.0390167236],"type":"Point"}
}