{
  "type": "Feature",
  "properties": {
    "addr:full":"Rykswg 119 Velden Limburg 5941 AC",
    "addr:housenumber":"119",
    "addr:postcode":"5941 ac",
    "iso:country":"NL",
    "sg:address":"Rykswg 119",
    "sg:city":"Velden",
    "sg:orig_category":"Opticiens",
    "sg:phone":"+31 77 472 1417",
    "sg:postcode":"5941 AC",
    "sg:province":"Limburg",
    "wof:name":"Schreven",
    "wof:placetype":"venue"
},
  "geometry": {"coordinates":[6.1658520699,51.4130783081],"type":"Point"}
}