{
  "type": "Feature",
  "properties": {
    "addr:full":"Amsterdamsewg 380A Amstelveen North Holland 1182 HS",
    "addr:housenumber":"380a",
    "addr:postcode":"1182 hs",
    "iso:country":"NL",
    "sg:address":"Amsterdamsewg 380A",
    "sg:city":"Amstelveen",
    "sg:orig_category":"Wijnkoperijen En -Groothandel",
    "sg:phone":"+31 20 647 8587",
    "sg:postcode":"1182 HS",
    "sg:province":"North Holland",
    "wof:name":"Broekhuizen, Van",
    "wof:placetype":"venue"
},
  "geometry": {"coordinates":[4.8554491997,52.3153648376],"type":"Point"}
}