{
  "type": "Feature",
  "properties": {
    "addr:full":"Langeviele 65 Middelburg Zeeland 4331 LS",
    "addr:housenumber":"65",
    "addr:postcode":"4331 ls",
    "addr:street":"Langeviele",
    "iso:country":"NL",
    "sg:address":"Langeviele 65",
    "sg:city":"Middelburg",
    "sg:orig_category":"Wolartikelen En Breiwol",
    "sg:phone":"+31 118 613 904",
    "sg:postcode":"4331 LS",
    "sg:province":"Zeeland",
    "wof:name":"Wolboog, De",
    "wof:placetype":"venue"
},
  "geometry": {"coordinates":[3.6078789234,51.497379303],"type":"Point"}
}