{
  "type": "Feature",
  "properties": {
    "iso:country":"NL",
    "sg:address":"Tolberterstr 105",
    "sg:city":"Leek",
    "sg:classifiers":[
        {
            "category":"Retail",
            "subcategory":"Auto Repair",
            "type":"Services"
        }
    ],
    "sg:phone":"+31 594 519 500",
    "sg:postcode":"9351 BE",
    "sg:province":"Groningen",
    "sg:tags":[
        "garage"
    ],
    "sg:website":"http://www.hhinterauto.nl",
    "wof:name":"H & H Bv",
    "wof:placetype":"venue"
},
  "geometry": {"coordinates":[6.381802,53.166584],"type":"Point"}
}