{
  "type": "Feature",
  "properties": {
    "iso:country":"NL",
    "sg:address":"Kalverstr 40-42",
    "sg:city":"Amsterdam",
    "sg:orig_category":"Babyartikelen",
    "sg:phone":"+31 20 626 6392",
    "sg:postcode":"1012 PE",
    "sg:province":"North Holland",
    "wof:name":"Pr?natal",
    "wof:placetype":"venue"
},
  "geometry": {"coordinates":[4.891839,52.371593],"type":"Point"}
}