{
  "type": "Feature",
  "properties": {
    "iso:country":"NL",
    "sg:address":"Het Zwanevlot 325",
    "sg:city":"Zutphen",
    "sg:orig_category":"Kinderopvang Behalve Thuis",
    "sg:phone":"+31 575 525 100",
    "sg:postcode":"7206 CS",
    "sg:province":"Gelderland",
    "wof:name":"Stichting Kinderdagopvang De Blokkentoren",
    "wof:placetype":"venue"
},
  "geometry": {"coordinates":[6.203822,52.125603],"type":"Point"}
}