{
  "type": "Feature",
  "properties": {
    "addr:full":"Kamperstr 24 Zwolle Overijssel 8011 LM",
    "addr:housenumber":"24",
    "addr:postcode":"8011 lm",
    "addr:street":"Kamperstr",
    "iso:country":"NL",
    "sg:address":"Kamperstr 24",
    "sg:city":"Zwolle",
    "sg:orig_category":"Kappers",
    "sg:phone":"+31 38 421 8905",
    "sg:postcode":"8011 LM",
    "sg:province":"Overijssel",
    "wof:name":"Les Ciseaux",
    "wof:placetype":"venue"
},
  "geometry": {"coordinates":[6.089444,52.511703],"type":"Point"}
}