{
  "type": "Feature",
  "properties": {
    "addr:full":"Kon Julianaln 46 Voorschoten Zuid-Holland 2251 EA",
    "addr:housenumber":"46",
    "addr:postcode":"2251 ea",
    "addr:street":"Kon",
    "iso:country":"NL",
    "sg:address":"Kon Julianaln 46",
    "sg:city":"Voorschoten",
    "sg:orig_category":"Keukens",
    "sg:phone":"+31 71 561 5927",
    "sg:postcode":"2251 EA",
    "sg:province":"Zuid-Holland",
    "sg:website":"http://www.houtwerfkeukenstudio.nl",
    "wof:name":"Keukenstudio Voorschoten",
    "wof:placetype":"venue"
},
  "geometry": {"coordinates":[4.447601,52.127022],"type":"Point"}
}