{
  "type": "Feature",
  "properties": {
    "addr:full":"Zaanwg 39 Wormerveer Noord-Holland 1521 DL",
    "addr:housenumber":"39",
    "addr:postcode":"1521 dl",
    "addr:street":"Zaanwg",
    "iso:country":"NL",
    "sg:address":"Zaanwg 39",
    "sg:city":"Wormerveer",
    "sg:orig_category":"Beveiliging",
    "sg:phone":"+31 6 27043666",
    "sg:postcode":"1521 DL",
    "sg:province":"Noord-Holland",
    "wof:name":"Davelaar",
    "wof:placetype":"venue"
},
  "geometry": {"coordinates":[4.79903,52.490414],"type":"Point"}
}