{
  "type": "Feature",
  "properties": {
    "iso:country":"NL",
    "sg:address":"Veldensteinln 9",
    "sg:city":"Jaarsveld",
    "sg:orig_category":"Voegwerken",
    "sg:phone":"+31 348 557 003",
    "sg:postcode":"3413 MK",
    "sg:province":"Utrecht",
    "wof:name":"Schaik, Van",
    "wof:placetype":"venue"
},
  "geometry": {"coordinates":[4.974346,51.969379],"type":"Point"}
}