{
  "type": "Feature",
  "properties": {
    "addr:full":"Schubertstraat 4 Zutphen Gelderland 7204 PT",
    "addr:housenumber":"4",
    "addr:postcode":"7204",
    "addr:street":"Schubertstraat;Gelderland;Pt",
    "iso:country":"NL",
    "sg:address":"Schubertstraat 4",
    "sg:city":"Zutphen",
    "sg:orig_category":"Verzekeringen",
    "sg:phone":"+31 575 523 785",
    "sg:postcode":"7204 PT",
    "sg:province":"Gelderland",
    "wof:name":"E Huttinga",
    "wof:placetype":"venue"
},
  "geometry": {"coordinates":[6.200851,52.131062],"type":"Point"}
}