{
  "type": "Feature",
  "properties": {
    "addr:full":"De Hennepe 502 Tiel Gelderland 4003 BN",
    "addr:housenumber":"502",
    "addr:postcode":"4003 bn",
    "addr:street":"De Hennepe;Gelderland",
    "iso:country":"NL",
    "sg:address":"De Hennepe 502",
    "sg:city":"Tiel",
    "sg:orig_category":"Dumpgoederen",
    "sg:phone":"+31 344 623 535",
    "sg:postcode":"4003 BN",
    "sg:province":"Gelderland",
    "wof:name":"Verbeek, Anton",
    "wof:placetype":"venue"
},
  "geometry": {"coordinates":[5.43208,51.898216],"type":"Point"}
}