{
  "type": "Feature",
  "properties": {
    "iso:country":"NL",
    "sg:address":"Smeekweg 53",
    "sg:city":"Laren Nh",
    "sg:orig_category":"Loodgieterswerk, Verwarming And Sanitaire Installaties",
    "sg:phone":"+31 35 538 9430",
    "sg:postcode":"1251 VK",
    "sg:province":"Noord-Holland",
    "wof:name":"Onderhoudsbedrijf Adrie Kaarsgaren",
    "wof:placetype":"venue"
},
  "geometry": {"coordinates":[5.237003,52.246613],"type":"Point"}
}