{
  "type": "Feature",
  "properties": {
    "addr:full":"Koperwiek 61-63 Fil Winkelc Capelle Ad Yssel Zuid-Holland 2903 AD",
    "addr:housenumber":"61-63",
    "addr:postcode":"2903 ad",
    "addr:street":"Koperwiek;Winkelc",
    "iso:country":"NL",
    "sg:address":"Koperwiek 61-63 Fil Winkelc",
    "sg:city":"Capelle Ad Yssel",
    "sg:orig_category":"Boeken En Tijdschriften",
    "sg:phone":"+31 10 450 3251",
    "sg:postcode":"2903 AD",
    "sg:province":"Zuid-Holland",
    "wof:name":"Koperwiek, De",
    "wof:placetype":"venue"
},
  "geometry": {"coordinates":[4.59189,51.931591],"type":"Point"}
}