{
  "type": "Feature",
  "properties": {
    "addr:full":"Hekbootkade 19 Zoetermeer Zuid-Holland 2725 AP",
    "addr:housenumber":"19",
    "addr:postcode":"2725 ap",
    "addr:street":"Hekbootkade",
    "iso:country":"NL",
    "sg:address":"Hekbootkade 19",
    "sg:city":"Zoetermeer",
    "sg:orig_category":"Verzekeringen",
    "sg:phone":"+31 79 341 1309",
    "sg:postcode":"2725 AP",
    "sg:province":"Zuid-Holland",
    "wof:name":"Labrie Ass",
    "wof:placetype":"venue"
},
  "geometry": {"coordinates":[4.49403,52.073086],"type":"Point"}
}