{
  "type": "Feature",
  "properties": {
    "iso:country":"NL",
    "sg:address":"West Vlisterdijk 71",
    "sg:city":"Vlist",
    "sg:orig_category":"Fietshandelaren",
    "sg:phone":"+31 182 382 572",
    "sg:postcode":"2855 AK",
    "sg:province":"South Holland",
    "wof:name":"L. Rietveld",
    "wof:placetype":"venue"
},
  "geometry": {"coordinates":[4.824113,51.972927],"type":"Point"}
}