{
  "type": "Feature",
  "properties": {
    "iso:country":"NL",
    "sg:address":"Heuvel 5",
    "sg:city":"Nuenen",
    "sg:orig_category":"Scholen Voor Basisonderwijs",
    "sg:phone":"+31 40 283 1261",
    "sg:postcode":"5674 RR",
    "sg:province":"Noord-Brabant",
    "wof:name":"Clemens Rk, St",
    "wof:placetype":"venue"
},
  "geometry": {"coordinates":[5.564111,51.488396],"type":"Point"}
}