{
  "type": "Feature",
  "properties": {
    "addr:full":"Brink 69 Amstelveen Noord-Holland 1188 0N",
    "addr:housenumber":"69",
    "addr:postcode":"1188 0n",
    "addr:street":"Brink",
    "iso:country":"NL",
    "sg:address":"Brink 69",
    "sg:city":"Amstelveen",
    "sg:orig_category":"Kinderopvang Behalve Thuis",
    "sg:phone":"+31 20 640 4291",
    "sg:postcode":"1188 0N",
    "sg:province":"Noord-Holland",
    "wof:name":"De Dolfijn",
    "wof:placetype":"venue"
},
  "geometry": {"coordinates":[4.856945,52.303444],"type":"Point"}
}