{
  "type": "Feature",
  "properties": {
    "iso:country":"NL",
    "sg:address":"Brink 69",
    "sg:city":"Amstelveen",
    "sg:orig_category":"Kinderopvang Behalve Thuis",
    "sg:phone":"+31 20 640 4291",
    "sg:postcode":"1188 0N",
    "sg:province":"Noord-Holland",
    "wof:name":"De Dolfijn",
    "wof:placetype":"venue"
},
  "geometry": {"coordinates":[4.856945,52.303444],"type":"Point"}
}