{
  "type": "Feature",
  "properties": {
    "addr:full":"G Vd Molenstr 16 Pynacker Zuid-Holland 2642 CV",
    "addr:housenumber":"16",
    "addr:postcode":"2642 cv",
    "addr:street":"Pynacker",
    "iso:country":"NL",
    "sg:address":"G Vd Molenstr 16",
    "sg:city":"Pynacker",
    "sg:orig_category":"Administratie- En Boekhoudkantoren",
    "sg:phone":"+31 15 364 0800",
    "sg:postcode":"2642 CV",
    "sg:province":"Zuid-Holland",
    "wof:name":"Hooven, Van Den",
    "wof:placetype":"venue"
},
  "geometry": {"coordinates":[4.45025,52.008888],"type":"Point"}
}