{
  "type": "Feature",
  "properties": {
    "iso:country":"NL",
    "sg:address":"Veluwewg 35",
    "sg:city":"Waarland",
    "sg:orig_category":"Verzekeringen - Verzekeringskantoren",
    "sg:phone":"+31 226 421 215",
    "sg:postcode":"1738 BD",
    "sg:province":"Noord-Holland",
    "wof:name":"Jaspers, H B",
    "wof:placetype":"venue"
},
  "geometry": {"coordinates":[4.836666,52.726906],"type":"Point"}
}