{
  "type": "Feature",
  "properties": {
    "addr:full":"Braambergseweg 2 Drempt Gelderland 6996 AL",
    "addr:housenumber":"2",
    "addr:postcode":"6996",
    "addr:street":"Braambergseweg;Gelderland",
    "iso:country":"NL",
    "sg:address":"Braambergseweg 2",
    "sg:city":"Drempt",
    "sg:orig_category":"Metaalwerken",
    "sg:phone":"+31 313 484 949",
    "sg:postcode":"6996 AL",
    "sg:province":"Gelderland",
    "wof:name":"E&S Zonweringen En Rolluiken",
    "wof:placetype":"venue"
},
  "geometry": {"coordinates":[6.173659,52.006153],"type":"Point"}
}