{
  "type": "Feature",
  "properties": {
    "addr:full":"Vivaldistr 35 S Hertogenbosch North Brabant 5216 EK",
    "addr:housenumber":"35",
    "addr:postcode":"5216 ek",
    "addr:street":"Vivaldistr;S Hertogenbosch",
    "iso:country":"NL",
    "sg:address":"Vivaldistr 35",
    "sg:city":"S Hertogenbosch",
    "sg:orig_category":"Adviesbureaus Bouwkunde",
    "sg:phone":"+31 6 53967484",
    "sg:postcode":"5216 EK",
    "sg:province":"North Brabant",
    "sg:website":"http://www.jbconsult.nl",
    "wof:name":"J B Consult",
    "wof:placetype":"venue"
},
  "geometry": {"coordinates":[5.318819,51.680721],"type":"Point"}
}