{
  "type": "Feature",
  "properties": {
    "addr:full":"Randk 6 Nieuwegein Utrecht 3435 PC",
    "addr:housenumber":"6",
    "addr:postcode":"3435 pc",
    "addr:street":"Randk",
    "iso:country":"NL",
    "sg:address":"Randk 6",
    "sg:city":"Nieuwegein",
    "sg:orig_category":"Metselwerken",
    "sg:phone":"+31 6 25033453",
    "sg:postcode":"3435 PC",
    "sg:province":"Utrecht",
    "wof:name":"Cees Wilting",
    "wof:placetype":"venue"
},
  "geometry": {"coordinates":[5.079701,52.023743],"type":"Point"}
}