{
  "type": "Feature",
  "properties": {
    "addr:full":"V Rhemenmarke 8 Zwolle Overijssel 8016 KP",
    "addr:housenumber":"8",
    "addr:postcode":"8016 kp",
    "addr:street":"Rhemenmarke",
    "iso:country":"NL",
    "sg:address":"V Rhemenmarke 8",
    "sg:city":"Zwolle",
    "sg:orig_category":"Administratie- En Boekhoudkantoren",
    "sg:phone":"+31 38 460 4920",
    "sg:postcode":"8016 KP",
    "sg:province":"Overijssel",
    "wof:name":"Optima",
    "wof:placetype":"venue"
},
  "geometry": {"coordinates":[6.094208,52.484478],"type":"Point"}
}