{
  "type": "Feature",
  "properties": {
    "addr:full":"Ganzenstraat 15 Amersfoort Utrecht 3815 JA",
    "addr:housenumber":"15",
    "addr:postcode":"3815 ja",
    "addr:street":"Ganzenstraat",
    "iso:country":"NL",
    "sg:address":"Ganzenstraat 15",
    "sg:city":"Amersfoort",
    "sg:orig_category":"Meubelreparatie And -Restauratie",
    "sg:phone":"+31 33 472 5664",
    "sg:postcode":"3815 JA",
    "sg:province":"Utrecht",
    "wof:name":"Woning- En Meubelstoffering H. Hardeman",
    "wof:placetype":"venue"
},
  "geometry": {"coordinates":[5.406194,52.163963],"type":"Point"}
}