{
  "type": "Feature",
  "properties": {
    "iso:country":"NL",
    "sg:address":"Inkarnaatklaver 11",
    "sg:city":"Rotterdam",
    "sg:orig_category":"Ovenbouw",
    "sg:phone":"+31 10 220 2124",
    "sg:postcode":"3069 DN",
    "sg:province":"South Holland",
    "wof:name":"Furnace Linings Services",
    "wof:placetype":"venue"
},
  "geometry": {"coordinates":[4.5335569382,51.965259552],"type":"Point"}
}