{
  "type": "Feature",
  "properties": {
    "iso:country":"NL",
    "sg:address":"Methardusstraat 43",
    "sg:city":"Munnekezijl",
    "sg:classifiers":[
        {
            "category":"Education",
            "subcategory":"Preschool",
            "type":"Public Place"
        }
    ],
    "sg:phone":"+31 594 688 254",
    "sg:postcode":"9853 PD",
    "sg:province":"Friesland",
    "sg:tags":[
        "kleuteronderwijs",
        "basis-"
    ],
    "wof:name":"Christelijke Basisschool 'T Oegh",
    "wof:placetype":"venue"
},
  "geometry": {"coordinates":[6.272792,53.303562],"type":"Point"}
}