{
  "type": "Feature",
  "properties": {
    "addr:full":"Spaanderstraat 17 Oss Noord-Brabant 5348 LA",
    "addr:housenumber":"17",
    "addr:postcode":"5348 la",
    "addr:street":"Spaanderstraat",
    "iso:country":"NL",
    "sg:address":"Spaanderstraat 17",
    "sg:city":"Oss",
    "sg:orig_category":"Metaalbekleding And -Behandeling",
    "sg:phone":"+31 412 626 872",
    "sg:postcode":"5348 LA",
    "sg:province":"Noord-Brabant",
    "wof:name":"Van Den Broek Techniek Oss Bv",
    "wof:placetype":"venue"
},
  "geometry": {"coordinates":[-91.12979900000001,44.578667],"type":"Point"}
}