{
  "type": "Feature",
  "properties": {
    "addr:full":"Hof V Parys 99 Doetinchem Gelderland 7007 JD",
    "addr:housenumber":"99",
    "addr:postcode":"7007 jd",
    "addr:street":"Parys;Gelderland",
    "iso:country":"NL",
    "sg:address":"Hof V Parys 99",
    "sg:city":"Doetinchem",
    "sg:orig_category":"Betonboringen",
    "sg:phone":"+31 314 653 077",
    "sg:postcode":"7007 JD",
    "sg:province":"Gelderland",
    "wof:name":"Bbb Blickmann Betonboor Bedrijf",
    "wof:placetype":"venue"
},
  "geometry": {"coordinates":[6.291055,51.963596],"type":"Point"}
}