{
  "type": "Feature",
  "properties": {
    "addr:full":"Olympiade 84 Etten Leur North Brabant 4873 DA",
    "addr:housenumber":"84",
    "addr:postcode":"4873 da",
    "addr:street":"Olympiade",
    "iso:country":"NL",
    "sg:address":"Olympiade 84",
    "sg:city":"Etten Leur",
    "sg:orig_category":"Adviesbureaus Marketing",
    "sg:phone":"+31 76 504 1060",
    "sg:postcode":"4873 DA",
    "sg:province":"North Brabant",
    "wof:name":"Wiegerinck, V J J",
    "wof:placetype":"venue"
},
  "geometry": {"coordinates":[4.656345,51.565872],"type":"Point"}
}