{
  "type": "Feature",
  "properties": {
    "iso:country":"NL",
    "sg:address":"Industrieweg 3",
    "sg:city":"Meppel",
    "sg:orig_category":"Autokeuringen",
    "sg:phone":"+31 522 260 485",
    "sg:postcode":"7944 HT",
    "sg:province":"Provincie Drenthe",
    "wof:name":"Abc Trade Bv",
    "wof:placetype":"venue"
},
  "geometry": {"coordinates":[6.182724,52.693684],"type":"Point"}
}