{
  "type": "Feature",
  "properties": {
    "iso:country":"NL",
    "sg:address":"2E Brandenburg Wg 24",
    "sg:city":"Bilthoven",
    "sg:orig_category":"Fotografie Reclame En Mode",
    "sg:phone":"+31 30 229 4018",
    "sg:postcode":"3721 CH",
    "sg:province":"Utrecht",
    "sg:website":"http://www.fotografiek.nl",
    "wof:name":"Fotografiek",
    "wof:placetype":"venue"
},
  "geometry": {"coordinates":[5.194613,52.124252],"type":"Point"}
}