{
  "type": "Feature",
  "properties": {
    "addr:full":"Enschedesestr 32 Losser Overijssel 7582 AG",
    "addr:housenumber":"32",
    "addr:postcode":"7582",
    "addr:street":"Enschedesestr",
    "iso:country":"NL",
    "sg:address":"Enschedesestr 32",
    "sg:city":"Losser",
    "sg:orig_category":"Autoschade- Herstelbedrijven",
    "sg:phone":"+31 53 538 1331",
    "sg:postcode":"7582 AG",
    "sg:province":"Overijssel",
    "wof:name":"Brilman Bv",
    "wof:placetype":"venue"
},
  "geometry": {"coordinates":[6.999297,52.263229],"type":"Point"}
}