{
  "type": "Feature",
  "properties": {
    "addr:full":"Hulte 1 Oirschot Noord-Brabant 5688 BZ",
    "addr:housenumber":"1",
    "addr:postcode":"5688 bz",
    "addr:street":"Hulte",
    "iso:country":"NL",
    "sg:address":"Hulte 1",
    "sg:city":"Oirschot",
    "sg:orig_category":"Discotheken",
    "sg:phone":"+31 499 573 813",
    "sg:postcode":"5688 BZ",
    "sg:province":"Noord-Brabant",
    "wof:name":"Smetsers",
    "wof:placetype":"venue"
},
  "geometry": {"coordinates":[5.306225,51.511021],"type":"Point"}
}