{
  "type": "Feature",
  "properties": {
    "addr:full":"Egypteneinde 9-11 Veendam Groningen 9645 LC",
    "addr:housenumber":"9-11",
    "addr:postcode":"9645 lc",
    "addr:street":"Egypteneinde",
    "iso:country":"NL",
    "sg:address":"Egypteneinde 9-11",
    "sg:city":"Veendam",
    "sg:orig_category":"Keukens",
    "sg:phone":"+31 598 690 484",
    "sg:postcode":"9645 LC",
    "sg:province":"Groningen",
    "wof:name":"Pronk",
    "wof:placetype":"venue"
},
  "geometry": {"coordinates":[6.889535,53.120209],"type":"Point"}
}