{
  "type": "Feature",
  "properties": {
    "iso:country":"NL",
    "sg:address":"Griftdijk Zuid 45",
    "sg:city":"Lent",
    "sg:orig_category":"Kappers",
    "sg:phone":"+31 24 324 1517",
    "sg:postcode":"6663 BA",
    "sg:province":"Gelderland",
    "wof:name":"Dameskapsalon Dernice",
    "wof:placetype":"venue"
},
  "geometry": {"coordinates":[-77.2414321899,38.1513442993],"type":"Point"}
}