{
  "type": "Feature",
  "properties": {
    "addr:full":"Sniederslaan 11 Bladel Noord-Brabant 5531 EG",
    "addr:housenumber":"11",
    "addr:postcode":"5531 eg",
    "addr:street":"Sniederslaan",
    "iso:country":"NL",
    "sg:address":"Sniederslaan 11",
    "sg:city":"Bladel",
    "sg:orig_category":"Discountwinkels",
    "sg:phone":"+31 497 360 501",
    "sg:postcode":"5531 EG",
    "sg:province":"Noord-Brabant",
    "wof:name":"Zeeman Textielsupers",
    "wof:placetype":"venue"
},
  "geometry": {"coordinates":[5.216819,51.366745],"type":"Point"}
}