{
  "type": "Feature",
  "properties": {
    "addr:full":"Honigmanstraat 37 Heerlen Limburg 6411 LJ",
    "addr:housenumber":"37",
    "addr:postcode":"6411 lj",
    "addr:street":"Honigmanstraat",
    "iso:country":"NL",
    "sg:address":"Honigmanstraat 37",
    "sg:city":"Heerlen",
    "sg:orig_category":"Opticiens",
    "sg:phone":"+31 45 571 6705",
    "sg:postcode":"6411 LJ",
    "sg:province":"Limburg",
    "wof:name":"Henssen Heerlen",
    "wof:placetype":"venue"
},
  "geometry": {"coordinates":[5.9755730629,50.8879699707],"type":"Point"}
}