{
  "type": "Feature",
  "properties": {
    "addr:full":"Trappistenweg 6 Tegelen Limburg 5932 NB",
    "addr:housenumber":"6",
    "addr:postcode":"5932 nb",
    "addr:street":"Trappistenweg",
    "iso:country":"NL",
    "sg:address":"Trappistenweg 6",
    "sg:city":"Tegelen",
    "sg:orig_category":"Kantoorapparatuur Gh",
    "sg:phone":"+31 77 373 1551",
    "sg:postcode":"5932 NB",
    "sg:province":"Limburg",
    "wof:name":"Elba Ordner Fabrieken Bv",
    "wof:placetype":"venue"
},
  "geometry": {"coordinates":[6.1582541466,51.3365974426],"type":"Point"}
}