{
  "type": "Feature",
  "properties": {
    "iso:country":"NL",
    "sg:address":"Adm Helfrichwg 12",
    "sg:city":"Leiden",
    "sg:orig_category":"Oud Papier",
    "sg:phone":"+31 71 522 2613",
    "sg:postcode":"2315 VC",
    "sg:province":"South Holland",
    "wof:name":"Kluivers",
    "wof:placetype":"venue"
},
  "geometry": {"coordinates":[4.512693882,52.1602554321],"type":"Point"}
}