{
  "type": "Feature",
  "properties": {
    "addr:full":"Twekkelerwg 176 Hengelo Ov Overijssel 7553 LR",
    "addr:housenumber":"176",
    "addr:postcode":"7553 lr",
    "addr:street":"Ov",
    "iso:country":"NL",
    "sg:address":"Twekkelerwg 176",
    "sg:city":"Hengelo Ov",
    "sg:orig_category":"Kappers",
    "sg:phone":"+31 74 291 9190",
    "sg:postcode":"7553 LR",
    "sg:province":"Overijssel",
    "wof:name":"Bas - Kappers",
    "wof:placetype":"venue"
},
  "geometry": {"coordinates":[6.8010258675,52.2528686523],"type":"Point"}
}