{
  "type": "Feature",
  "properties": {
    "addr:full":"Torenstraat 24 Noordhorn Groningen 9804 PV",
    "addr:housenumber":"24",
    "addr:postcode":"9804 pv",
    "addr:street":"Torenstraat",
    "iso:country":"NL",
    "sg:address":"Torenstraat 24",
    "sg:city":"Noordhorn",
    "sg:orig_category":"Zalenexploitatie",
    "sg:phone":"+31 594 505 033",
    "sg:postcode":"9804 PV",
    "sg:province":"Groningen",
    "wof:name":"Galerie Mebius",
    "wof:placetype":"venue"
},
  "geometry": {"coordinates":[6.396079,53.261345],"type":"Point"}
}