{
  "type": "Feature",
  "properties": {
    "iso:country":"NL",
    "sg:address":"Zeedistelwg 1",
    "sg:city":"Haarlem",
    "sg:orig_category":"Fitnesscentra",
    "sg:phone":"+31 23 524 5777",
    "sg:postcode":"2015 KT",
    "sg:province":"North Holland",
    "wof:name":"Life Fit Centre",
    "wof:placetype":"venue"
},
  "geometry": {"coordinates":[4.608445,52.371857],"type":"Point"}
}