{
  "type": "Feature",
  "properties": {
    "iso:country":"NL",
    "sg:address":"Fregatstr 91",
    "sg:city":"Utrecht",
    "sg:orig_category":"Kappers",
    "sg:phone":"+31 30 243 8143",
    "sg:postcode":"3534 RC",
    "sg:province":"Utrecht",
    "wof:name":"B & B",
    "wof:placetype":"venue"
},
  "geometry": {"coordinates":[5.0819969177,52.0991363525],"type":"Point"}
}