{
  "type": "Feature",
  "properties": {
    "addr:full":"Noordeinde 8 Lambertschaag Noord-Holland 1658 CB",
    "addr:housenumber":"8",
    "addr:postcode":"1658 cb",
    "addr:street":"Noordeinde",
    "iso:country":"NL",
    "sg:address":"Noordeinde 8",
    "sg:city":"Lambertschaag",
    "sg:orig_category":"Vaste And Vloeibare Brandstoffen",
    "sg:phone":"+31 229 581 354",
    "sg:postcode":"1658 CB",
    "sg:province":"Noord-Holland",
    "wof:name":"Oliehandel Tensen Bv",
    "wof:placetype":"venue"
},
  "geometry": {"coordinates":[5.015795,52.749805],"type":"Point"}
}