{
  "type": "Feature",
  "properties": {
    "iso:country":"NL",
    "sg:address":"Acacialn 40",
    "sg:city":"Groningen",
    "sg:orig_category":"Woninginrichting",
    "sg:phone":"+31 50 577 1948",
    "sg:postcode":"9741 KZ",
    "sg:province":"Groningen",
    "wof:name":"Wijk Vof, Douwe Van Der",
    "wof:placetype":"venue"
},
  "geometry": {"coordinates":[6.5506801605,53.2325401306],"type":"Point"}
}