{
  "type": "Feature",
  "properties": {
    "addr:full":"Burgemeester Van Veenln 24 Nijeveen Drenthe 7948 AC",
    "addr:housenumber":"24",
    "addr:postcode":"7948 ac",
    "addr:street":"Burgemeester Van Veenln",
    "iso:country":"NL",
    "sg:address":"Burgemeester Van Veenln 24",
    "sg:city":"Nijeveen",
    "sg:orig_category":"Goederenvervoer Over De Weg",
    "sg:phone":"+31 522 492 527",
    "sg:postcode":"7948 AC",
    "sg:province":"Drenthe",
    "wof:name":"Firma Hoorn Transport",
    "wof:placetype":"venue"
},
  "geometry": {"coordinates":[6.165388,52.730659],"type":"Point"}
}