{
  "type": "Feature",
  "properties": {
    "iso:country":"NL",
    "sg:address":"Kerkln 96",
    "sg:city":"Nieuwerkerk Yssel",
    "sg:orig_category":"Zoetwaren - Winkels",
    "sg:phone":"+31 180 316 265",
    "sg:postcode":"2912 CL",
    "sg:province":"Zuid-Holland",
    "wof:name":"Winkeltje, 'T",
    "wof:placetype":"venue"
},
  "geometry": {"coordinates":[4.6028,51.963692],"type":"Point"}
}