{
  "type": "Feature",
  "properties": {
    "iso:country":"NL",
    "sg:address":"Ellerweg 17",
    "sg:city":"Kelpen-Oler",
    "sg:orig_category":"Drukkerijen And Copyshops",
    "sg:phone":"+31 495 657 710",
    "sg:postcode":"6037 RR",
    "sg:province":"Limburg",
    "wof:name":"Drukkerij Uitgeverij Hub Tonnaer Bv",
    "wof:placetype":"venue"
},
  "geometry": {"coordinates":[-61.766769,1.84229],"type":"Point"}
}