{
  "type": "Feature",
  "properties": {
    "addr:full":"Vondelstr 25 Alkmaar Noord-Holland 1813 AA",
    "addr:housenumber":"25",
    "addr:postcode":"1813 aa",
    "addr:street":"Vondelstr",
    "iso:country":"NL",
    "sg:address":"Vondelstr 25",
    "sg:city":"Alkmaar",
    "sg:orig_category":"Partyservice",
    "sg:phone":"+31 72 540 4405",
    "sg:postcode":"1813 AA",
    "sg:province":"Noord-Holland",
    "wof:name":"Gerard",
    "wof:placetype":"venue"
},
  "geometry": {"coordinates":[4.752462,52.625546],"type":"Point"}
}