{
  "type": "Feature",
  "properties": {
    "addr:full":"Van Bienemalaan 15 Oudeschoot Provincie Friesland 8451 KE",
    "addr:housenumber":"15",
    "addr:postcode":"8451 ke",
    "addr:street":"Van Bienemalaan;Provincie Friesland",
    "iso:country":"NL",
    "sg:address":"Van Bienemalaan 15",
    "sg:city":"Oudeschoot",
    "sg:orig_category":"Kampeerterreinen",
    "sg:phone":"+31 513 681 192",
    "sg:postcode":"8451 KE",
    "sg:province":"Provincie Friesland",
    "wof:name":"T Woutersbergje",
    "wof:placetype":"venue"
},
  "geometry": {"coordinates":[5.9610948563,52.9346351624],"type":"Point"}
}