{
  "type": "Feature",
  "properties": {
    "addr:full":"Smidsweg 9A Noordwelle Zeeland 4326 AE",
    "addr:housenumber":"9a",
    "addr:postcode":"4326 ae",
    "addr:street":"Smidsweg",
    "iso:country":"NL",
    "sg:address":"Smidsweg 9A",
    "sg:city":"Noordwelle",
    "sg:orig_category":"Bedrijfs- And Werkgeversorganisaties",
    "sg:phone":"+31 111 461 629",
    "sg:postcode":"4326 AE",
    "sg:province":"Zeeland",
    "wof:name":"Kantine Dorpshuis Noordwelle",
    "wof:placetype":"venue"
},
  "geometry": {"coordinates":[3.794585,51.718147],"type":"Point"}
}