{
  "type": "Feature",
  "properties": {
    "addr:full":"Vyfkampln 4 Eindhoven Noord-Brabant 5624 EB",
    "addr:housenumber":"4",
    "addr:postcode":"5624 eb",
    "addr:street":"Vyfkampln",
    "iso:country":"NL",
    "sg:address":"Vyfkampln 4",
    "sg:city":"Eindhoven",
    "sg:orig_category":"Sportverenigingen En Ontspannings- Verenigingen",
    "sg:phone":"+31 40 242 1247",
    "sg:postcode":"5624 EB",
    "sg:province":"Noord-Brabant",
    "wof:name":"Dsc Korfbalver",
    "wof:placetype":"venue"
},
  "geometry": {"coordinates":[5.455981,51.478115],"type":"Point"}
}