{
  "type": "Feature",
  "properties": {
    "addr:full":"Thujapk 1 Beuningen Gld Gelderland 6642 CB",
    "addr:housenumber":"1",
    "addr:postcode":"6642 cb",
    "addr:street":"Thujapk",
    "iso:country":"NL",
    "sg:address":"Thujapk 1",
    "sg:city":"Beuningen Gld",
    "sg:orig_category":"Psychologen",
    "sg:phone":"+31 24 677 0689",
    "sg:postcode":"6642 CB",
    "sg:province":"Gelderland",
    "wof:name":"Psychol Prakt V Kind En Volwassenen",
    "wof:placetype":"venue"
},
  "geometry": {"coordinates":[5.763621,51.852821],"type":"Point"}
}