{
  "type": "Feature",
  "properties": {
    "addr:full":"Goudse Rypad 4 Alphen Aan Den Ryn Zuid-Holland 2407 BN",
    "addr:housenumber":"4",
    "addr:postcode":"2407 bn",
    "addr:street":"Rypad;Aan Den Ryn",
    "iso:country":"NL",
    "sg:address":"Goudse Rypad 4",
    "sg:city":"Alphen Aan Den Ryn",
    "sg:orig_category":"Poeliers",
    "sg:phone":"+31 172 472 900",
    "sg:postcode":"2407 BN",
    "sg:province":"Zuid-Holland",
    "wof:name":"Ton Overes",
    "wof:placetype":"venue"
},
  "geometry": {"coordinates":[4.694692,52.11454],"type":"Point"}
}