{
  "type": "Feature",
  "properties": {
    "addr:full":"Nieuwegracht 29 Utrecht Utrecht 3512 LD",
    "addr:housenumber":"29",
    "addr:postcode":"3512 ld",
    "addr:street":"Nieuwegracht",
    "iso:country":"NL",
    "sg:address":"Nieuwegracht 29",
    "sg:city":"Utrecht",
    "sg:orig_category":"Bedrijfsinventaris Gh",
    "sg:phone":"+31 30 231 3101",
    "sg:postcode":"3512 LD",
    "sg:province":"Utrecht",
    "wof:name":"Orka Koeltechnisch Platform",
    "wof:placetype":"venue"
},
  "geometry": {"coordinates":[5.124063,52.088726],"type":"Point"}
}