{
  "type": "Feature",
  "properties": {
    "addr:full":"Arbeidstraat 3 Apeldoorn Gelderland 7311 CS",
    "addr:housenumber":"3",
    "addr:postcode":"7311 cs",
    "addr:street":"Arbeidstraat;Gelderland",
    "iso:country":"NL",
    "sg:address":"Arbeidstraat 3",
    "sg:city":"Apeldoorn",
    "sg:orig_category":"Gebouwenafwerking, Renovaties And Reiniging",
    "sg:phone":"+31 55 521 7275",
    "sg:postcode":"7311 CS",
    "sg:province":"Gelderland",
    "wof:name":"F. Koldenhof",
    "wof:placetype":"venue"
},
  "geometry": {"coordinates":[5.952086,52.212879],"type":"Point"}
}