{
  "type": "Feature",
  "properties": {
    "addr:full":"Meerwedesingel 39 Barendrecht Zuid-Holland 2993 RB",
    "addr:housenumber":"39",
    "addr:postcode":"2993 rb",
    "addr:street":"Meerwedesingel",
    "iso:country":"NL",
    "sg:address":"Meerwedesingel 39",
    "sg:city":"Barendrecht",
    "sg:orig_category":"Advocaten And Juridische Adviseurs",
    "sg:phone":"+31 181 627 193",
    "sg:postcode":"2993 RB",
    "sg:province":"Zuid-Holland",
    "wof:name":"Advocatenkantoor Mr. G.H.I. Helwig-Voll",
    "wof:placetype":"venue"
},
  "geometry": {"coordinates":[4.499772,51.851856],"type":"Point"}
}