{
  "type": "Feature",
  "properties": {
    "addr:full":"Beenhouwerssingel 3 Middelburg Zeeland 4331 MD",
    "addr:housenumber":"3",
    "addr:postcode":"4331",
    "addr:street":"Beenhouwerssingel",
    "iso:country":"NL",
    "sg:address":"Beenhouwerssingel 3",
    "sg:city":"Middelburg",
    "sg:orig_category":"Huishoudapparatuur, Televisies And Radio'S",
    "sg:phone":"+31 118 614 406",
    "sg:postcode":"4331 MD",
    "sg:province":"Zeeland",
    "wof:name":"Mikro Electro Bv",
    "wof:placetype":"venue"
},
  "geometry": {"coordinates":[3.610678,51.495632],"type":"Point"}
}