{
  "type": "Feature",
  "properties": {
    "iso:country":"NL",
    "sg:address":"Zuidpolderdk 1",
    "sg:city":"Baarland",
    "sg:orig_category":"Natuurvoeding En Reformartikelen",
    "sg:phone":"+31 113 544 544",
    "sg:postcode":"4435 PW",
    "sg:province":"Zeeland",
    "wof:name":"Ph Int",
    "wof:placetype":"venue"
},
  "geometry": {"coordinates":[3.878759,51.401985],"type":"Point"}
}