{
  "type": "Feature",
  "properties": {
    "addr:full":"Zuidpolderdk 1 Baarland Zeeland 4435 PW",
    "addr:housenumber":"1",
    "addr:postcode":"4435 pw",
    "addr:street":"Zuidpolderdk",
    "iso:country":"NL",
    "sg:address":"Zuidpolderdk 1",
    "sg:city":"Baarland",
    "sg:orig_category":"Natuurvoeding En Reformartikelen",
    "sg:phone":"+31 113 544 544",
    "sg:postcode":"4435 PW",
    "sg:province":"Zeeland",
    "wof:name":"Ph Int",
    "wof:placetype":"venue"
},
  "geometry": {"coordinates":[3.878759,51.401985],"type":"Point"}
}