{
  "type": "Feature",
  "properties": {
    "addr:full":"Westeindseweg 23 Zoeterwoude Zuid-Holland 2381 EC",
    "addr:housenumber":"23",
    "addr:postcode":"2381 ec",
    "addr:street":"Westeindseweg",
    "iso:country":"NL",
    "sg:address":"Westeindseweg 23",
    "sg:city":"Zoeterwoude",
    "sg:orig_category":"Kampeerterreinen",
    "sg:phone":"+31 71 580 1321",
    "sg:postcode":"2381 EC",
    "sg:province":"Zuid-Holland",
    "wof:name":"Camping Zoeterwoude",
    "wof:placetype":"venue"
},
  "geometry": {"coordinates":[4.4806208611,52.1117744446],"type":"Point"}
}