{
  "type": "Feature",
  "properties": {
    "addr:full":"Oude Koemarkt 67 Sneek Friesland 8601 EJ",
    "addr:housenumber":"67",
    "addr:postcode":"8601 ej",
    "addr:street":"Oude Koemarkt",
    "iso:country":"NL",
    "sg:address":"Oude Koemarkt 67",
    "sg:city":"Sneek",
    "sg:orig_category":"Hypotheken And Hypotheekbanken",
    "sg:phone":"+31 515 412 800",
    "sg:postcode":"8601 EJ",
    "sg:province":"Friesland",
    "wof:name":"Hypotheek Visie Sneek",
    "wof:placetype":"venue"
},
  "geometry": {"coordinates":[5.6594052315,53.0299301147],"type":"Point"}
}