{
  "type": "Feature",
  "properties": {
    "addr:full":"Riekeschot 19 Ulvenhout North Brabant 4851 WB",
    "addr:housenumber":"19",
    "addr:postcode":"4851 wb",
    "addr:street":"Riekeschot",
    "iso:country":"NL",
    "sg:address":"Riekeschot 19",
    "sg:city":"Ulvenhout",
    "sg:orig_category":"Onteigening",
    "sg:phone":"+31 76 561 2670",
    "sg:postcode":"4851 WB",
    "sg:province":"North Brabant",
    "wof:name":"Miert Bv, Van",
    "wof:placetype":"venue"
},
  "geometry": {"coordinates":[4.809941,51.544952],"type":"Point"}
}