{
  "type": "Feature",
  "properties": {
    "addr:full":"Schiekd 658 Rotterdam Zuid-Holland 3032 AK",
    "addr:housenumber":"658",
    "addr:postcode":"3032 ak",
    "iso:country":"NL",
    "sg:address":"Schiekd 658",
    "sg:city":"Rotterdam",
    "sg:classifiers":[
        {
            "category":"Travel",
            "subcategory":"Hotels & Motels",
            "type":"Entertainment"
        }
    ],
    "sg:phone":"+31 10 466 3344",
    "sg:postcode":"3032 AK",
    "sg:province":"Zuid-Holland",
    "wof:name":"Best Western Pax",
    "wof:placetype":"venue"
},
  "geometry": {"coordinates":[4.470867,51.931068],"type":"Point"}
}