{
  "type": "Feature",
  "properties": {
    "addr:full":"Op Den Hoogen Boom 3 Beek Lb Limburg 6191 PE",
    "addr:housenumber":"3",
    "addr:postcode":"lb;6191 pe",
    "addr:street":"Op Den Hoogen Boom",
    "iso:country":"NL",
    "sg:address":"Op Den Hoogen Boom 3",
    "sg:city":"Beek Lb",
    "sg:orig_category":"Verzekeringen",
    "sg:phone":"+31 46 437 5037",
    "sg:postcode":"6191 PE",
    "sg:province":"Limburg",
    "wof:name":"Assurantiekantoor Starmans",
    "wof:placetype":"venue"
},
  "geometry": {"coordinates":[-38.083542,-8.37738],"type":"Point"}
}