{
  "type": "Feature",
  "properties": {
    "addr:full":"Zwolsestraat 63 Raalte Overijssel 8101 AB",
    "addr:housenumber":"63",
    "addr:postcode":"8101 ab",
    "addr:street":"Zwolsestraat",
    "iso:country":"NL",
    "sg:address":"Zwolsestraat 63",
    "sg:city":"Raalte",
    "sg:orig_category":"Hoefdierhouderijen",
    "sg:phone":"+31 572 351 268",
    "sg:postcode":"8101 AB",
    "sg:province":"Overijssel",
    "wof:name":"Manege Dekstation Tivoli",
    "wof:placetype":"venue"
},
  "geometry": {"coordinates":[6.267642,52.394356],"type":"Point"}
}