{
  "type": "Feature",
  "properties": {
    "addr:full":"Zandstr 1 Gemert Noord-Brabant 5421 WK",
    "addr:housenumber":"1",
    "addr:postcode":"5421 wk",
    "addr:street":"Zandstr",
    "iso:country":"NL",
    "sg:address":"Zandstr 1",
    "sg:city":"Gemert",
    "sg:orig_category":"Dierenvoeder - Fabrieken",
    "sg:phone":"+31 492 366 698",
    "sg:postcode":"5421 WK",
    "sg:province":"Noord-Brabant",
    "wof:name":"Stulti?ns",
    "wof:placetype":"venue"
},
  "geometry": {"coordinates":[5.695111,51.543823],"type":"Point"}
}