{
  "type": "Feature",
  "properties": {
    "addr:full":"Lemelerveldseweg 100 Lemelerveld NL.08 8152 DE",
    "addr:housenumber":"100;nl.08",
    "addr:postcode":"8152 de",
    "addr:street":"Lemelerveldseweg",
    "iso:country":"NL",
    "sg:address":"Lemelerveldseweg 100",
    "sg:city":"Lemelerveld",
    "sg:classifiers":[
        {
            "category":"Education",
            "subcategory":"Preschool",
            "type":"Public Place"
        }
    ],
    "sg:phone":"+31 572 371 984",
    "sg:postcode":"8152 DE",
    "sg:province":"NL.08",
    "sg:tags":[
        "kleuteronderwijs",
        "basis-"
    ],
    "wof:name":"Hervormde Basisschool Doktersbrug",
    "wof:placetype":"venue"
},
  "geometry": {"coordinates":[6.303389,52.446945],"type":"Point"}
}