{
  "type": "Feature",
  "properties": {
    "addr:full":"Kooistr 3 Afferden Gld Gelderland 6654 KH",
    "addr:housenumber":"3",
    "addr:postcode":"6654 kh",
    "addr:street":"Kooistr;Gld Gelderland",
    "iso:country":"NL",
    "sg:address":"Kooistr 3",
    "sg:city":"Afferden Gld",
    "sg:orig_category":"Kaas",
    "sg:phone":"+31 487 512 364",
    "sg:postcode":"6654 KH",
    "sg:province":"Gelderland",
    "wof:name":"Ravenswaard Vof",
    "wof:placetype":"venue"
},
  "geometry": {"coordinates":[5.6504631042,51.8700790405],"type":"Point"}
}