{
  "type": "Feature",
  "properties": {
    "addr:full":"Vrijheidstraat 3 Raamsdonksveer Noord-Brabant 4941 DX",
    "addr:housenumber":"3",
    "addr:postcode":"4941 dx",
    "addr:street":"Vrijheidstraat",
    "iso:country":"NL",
    "sg:address":"Vrijheidstraat 3",
    "sg:city":"Raamsdonksveer",
    "sg:orig_category":"Public Relationbureaus",
    "sg:phone":"+31 162 403 886",
    "sg:postcode":"4941 DX",
    "sg:province":"Noord-Brabant",
    "wof:name":"Reach Reclame",
    "wof:placetype":"venue"
},
  "geometry": {"coordinates":[4.873345,51.694695],"type":"Point"}
}