{
  "type": "Feature",
  "properties": {
    "addr:full":"Damveld 29 Almere Flevoland 1359 HG",
    "addr:housenumber":"29",
    "addr:postcode":"1359 hg",
    "addr:street":"Damveld;Flevoland",
    "iso:country":"NL",
    "sg:address":"Damveld 29",
    "sg:city":"Almere",
    "sg:orig_category":"Administratie- En Boekhoudkantoren",
    "sg:phone":"+31 36 538 6991",
    "sg:postcode":"1359 HG",
    "sg:province":"Flevoland",
    "wof:name":"Dln Tax & Accountancy Bv",
    "wof:placetype":"venue"
},
  "geometry": {"coordinates":[5.1876487732,52.3393325806],"type":"Point"}
}