{
  "type": "Feature",
  "properties": {
    "addr:full":"Zuidweg 12 Rijpwetering South Holland 2375 AP",
    "addr:housenumber":"12",
    "addr:postcode":"2375 ap",
    "addr:street":"Zuidweg",
    "iso:country":"NL",
    "sg:address":"Zuidweg 12",
    "sg:city":"Rijpwetering",
    "sg:orig_category":"Bloemen And Planten",
    "sg:phone":"+31 71 501 8493",
    "sg:postcode":"2375 AP",
    "sg:province":"South Holland",
    "wof:name":"Fa. J.G. & A.N.J. Wortman",
    "wof:placetype":"venue"
},
  "geometry": {"coordinates":[4.588855,52.184189],"type":"Point"}
}