{
  "type": "Feature",
  "properties": {
    "addr:full":"Lethmaetstr 4951 Gouda Zuid-Holland 2802 KB",
    "addr:housenumber":"4951",
    "addr:postcode":"gouda;2802 kb",
    "iso:country":"NL",
    "sg:address":"Lethmaetstr 4951",
    "sg:city":"Gouda",
    "sg:orig_category":"Bloemen En Planten",
    "sg:phone":"+31 182 517 876",
    "sg:postcode":"2802 KB",
    "sg:province":"Zuid-Holland",
    "wof:name":"Futselaar & Zn, H",
    "wof:placetype":"venue"
},
  "geometry": {"coordinates":[4.70038,52.006908],"type":"Point"}
}