{
  "type": "Feature",
  "properties": {
    "addr:full":"Gr Florisstr 58 Rotterdam South Holland 3021 CJ",
    "addr:housenumber":"58",
    "addr:postcode":"3021 cj",
    "iso:country":"NL",
    "sg:address":"Gr Florisstr 58",
    "sg:city":"Rotterdam",
    "sg:orig_category":"Scholen Voor Basisonderwijs",
    "sg:phone":"+31 10 476 8253",
    "sg:postcode":"3021 CJ",
    "sg:province":"South Holland",
    "wof:name":"Concordia Ebg",
    "wof:placetype":"venue"
},
  "geometry": {"coordinates":[4.458297,51.919994],"type":"Point"}
}