{
  "type": "Feature",
  "properties": {
    "addr:full":"Postbus 10 Ovezande Zeeland 4440 AA",
    "addr:housenumber":"10",
    "addr:postcode":"4440 aa",
    "addr:street":"Postbus",
    "iso:country":"NL",
    "sg:address":"Postbus 10",
    "sg:city":"Ovezande",
    "sg:orig_category":"Verenigingsgebouwen",
    "sg:phone":"+31 113 655 494",
    "sg:postcode":"4440 AA",
    "sg:province":"Zeeland",
    "wof:name":"Klomp, De",
    "wof:placetype":"venue"
},
  "geometry": {"coordinates":[3.8226,51.42828],"type":"Point"}
}