{
  "type": "Feature",
  "properties": {
    "addr:full":"1E Loosterwg 25 Hillegom Zuid-Holland 2182 BL",
    "addr:housenumber":"25",
    "addr:postcode":"2182 bl",
    "addr:street":"1E Loosterwg",
    "iso:country":"NL",
    "sg:address":"1E Loosterwg 25",
    "sg:city":"Hillegom",
    "sg:orig_category":"Bloembollen - Groothandel",
    "sg:phone":"+31 252 517 503",
    "sg:postcode":"2182 BL",
    "sg:province":"Zuid-Holland",
    "wof:name":"Heemskerk, Fa Gebr J En A",
    "wof:placetype":"venue"
},
  "geometry": {"coordinates":[4.570668,52.309349],"type":"Point"}
}