{
  "type": "Feature",
  "properties": {
    "addr:full":"Stroeerwg 43A Stroe Gelderland 3776 MG",
    "addr:housenumber":"43a",
    "addr:postcode":"3776 mg",
    "addr:street":"Stroeerwg;Gelderland",
    "iso:country":"NL",
    "sg:address":"Stroeerwg 43A",
    "sg:city":"Stroe",
    "sg:orig_category":"Bloemen En Planten - Decoratie",
    "sg:phone":"+31 342 442 909",
    "sg:postcode":"3776 MG",
    "sg:province":"Gelderland",
    "wof:name":"Buitenzorg Kwekerij",
    "wof:placetype":"venue"
},
  "geometry": {"coordinates":[5.686379,52.179123],"type":"Point"}
}