{
  "type": "Feature",
  "properties": {
    "addr:full":"Scharenburg 8 Druten Gelderland 6651 KJ",
    "addr:housenumber":"8",
    "addr:postcode":"6651 kj",
    "addr:street":"Scharenburg",
    "iso:country":"NL",
    "sg:address":"Scharenburg 8",
    "sg:city":"Druten",
    "sg:orig_category":"Kappers",
    "sg:phone":"+31 487 512 601",
    "sg:postcode":"6651 KJ",
    "sg:province":"Gelderland",
    "wof:name":"A.J. Kuijpers",
    "wof:placetype":"venue"
},
  "geometry": {"coordinates":[5.6101350784,51.8809204102],"type":"Point"}
}