{
  "type": "Feature",
  "properties": {
    "addr:full":"F Ruyschstr 2 Leeuwarden Friesland 8921 VT",
    "addr:housenumber":"2",
    "addr:postcode":"8921",
    "addr:street":"Ruyschstr",
    "iso:country":"NL",
    "sg:address":"F Ruyschstr 2",
    "sg:city":"Leeuwarden",
    "sg:classifiers":[
        {
            "category":"Personal",
            "subcategory":"Nail Salon",
            "type":"Services"
        }
    ],
    "sg:phone":"+31 58 212 7155",
    "sg:postcode":"8921 VT",
    "sg:province":"Friesland",
    "sg:tags":[
        "pedicure"
    ],
    "wof:name":"Meter, A",
    "wof:placetype":"venue"
},
  "geometry": {"coordinates":[5.813897,53.20715],"type":"Point"}
}