{
  "type": "Feature",
  "properties": {
    "addr:full":"Rostockstr 6 Deventer NL.08 7418 EL",
    "addr:housenumber":"6;nl.08",
    "addr:postcode":"7418 el",
    "addr:street":"Rostockstr",
    "iso:country":"NL",
    "sg:address":"Rostockstr 6",
    "sg:city":"Deventer",
    "sg:orig_category":"Koffiebranderijen",
    "sg:phone":"+31 570 630 900",
    "sg:postcode":"7418 EL",
    "sg:province":"NL.08",
    "wof:name":"Have Bv, K Ten",
    "wof:placetype":"venue"
},
  "geometry": {"coordinates":[6.1996,52.242004],"type":"Point"}
}