{
  "type": "Feature",
  "properties": {
    "iso:country":"NL",
    "sg:address":"Bosstr 12",
    "sg:city":"Driebergen Rysenb",
    "sg:orig_category":"Adviesbureaus Marketing",
    "sg:phone":"+31 343 520 201",
    "sg:postcode":"3971 XE",
    "sg:province":"Utrecht",
    "wof:name":"Diamand Leisure Cl Bv",
    "wof:placetype":"venue"
},
  "geometry": {"coordinates":[5.281734,52.05341],"type":"Point"}
}