{
  "type": "Feature",
  "properties": {
    "addr:full":"Capitool 20 Enschede Overijssel 7521 PL",
    "addr:housenumber":"20",
    "addr:postcode":"7521 pl",
    "addr:street":"Capitool",
    "iso:country":"NL",
    "sg:address":"Capitool 20",
    "sg:city":"Enschede",
    "sg:orig_category":"Pensioenen",
    "sg:phone":"+31 53 480 9320",
    "sg:postcode":"7521 PL",
    "sg:province":"Overijssel",
    "wof:name":"Financieel Compleet Enschede",
    "wof:placetype":"venue"
},
  "geometry": {"coordinates":[6.842593,52.236885],"type":"Point"}
}