{
  "type": "Feature",
  "properties": {
    "addr:full":"Groeneln 85-89 Schiedam Zuid-Holland 3114 CC",
    "addr:housenumber":"85-89",
    "addr:postcode":"3114 cc",
    "iso:country":"NL",
    "sg:address":"Groeneln 85-89",
    "sg:city":"Schiedam",
    "sg:orig_category":"Huishoudelijke Apparaten En Artikelen",
    "sg:phone":"+31 10 426 6008",
    "sg:postcode":"3114 CC",
    "sg:province":"Zuid-Holland",
    "wof:name":"Vlies, Fa A & G Van Der",
    "wof:placetype":"venue"
},
  "geometry": {"coordinates":[4.40289,51.906776],"type":"Point"}
}