{
  "type": "Feature",
  "properties": {
    "addr:full":"Glennstraat 20 Hilvarenbeek Noord-Brabant 5081 TK",
    "addr:housenumber":"20",
    "addr:postcode":"5081 tk",
    "addr:street":"Glennstraat",
    "iso:country":"NL",
    "sg:address":"Glennstraat 20",
    "sg:city":"Hilvarenbeek",
    "sg:orig_category":"Paramedische Behandelingen",
    "sg:phone":"+31 13 505 6465",
    "sg:postcode":"5081 TK",
    "sg:province":"Noord-Brabant",
    "wof:name":"Zorgwerkt Particuliere Thuiszorg",
    "wof:placetype":"venue"
},
  "geometry": {"coordinates":[5.133164,51.492397],"type":"Point"}
}