{
  "type": "Feature",
  "properties": {
    "addr:full":"Damstraat 43Bis Utrecht Utrecht 3531 BS",
    "addr:housenumber":"43bis",
    "addr:postcode":"3531 bs",
    "addr:street":"Damstraat",
    "iso:country":"NL",
    "sg:address":"Damstraat 43Bis",
    "sg:city":"Utrecht",
    "sg:orig_category":"Fotostudio'S And Fotografen",
    "sg:phone":"+31 30 294 2304",
    "sg:postcode":"3531 BS",
    "sg:province":"Utrecht",
    "wof:name":"Picture 7 F H Colder",
    "wof:placetype":"venue"
},
  "geometry": {"coordinates":[5.103719,52.091999],"type":"Point"}
}