{
  "type": "Feature",
  "properties": {
    "addr:full":"Boekenrodestr 1 Haarlem Noord-Holland 2012 LD",
    "addr:housenumber":"1",
    "addr:postcode":"2012 ld",
    "addr:street":"Boekenrodestr",
    "iso:country":"NL",
    "sg:address":"Boekenrodestr 1",
    "sg:city":"Haarlem",
    "sg:orig_category":"Geluidsinstallaties",
    "sg:phone":"+31 6 24249299",
    "sg:postcode":"2012 LD",
    "sg:province":"Noord-Holland",
    "sg:website":"http://www.prohow.nl",
    "wof:name":"Prohow",
    "wof:placetype":"venue"
},
  "geometry": {"coordinates":[4.620214,52.370132],"type":"Point"}
}