{
  "type": "Feature",
  "properties": {
    "addr:full":"Ganzetrek 39 Soest Utrecht 3766 XD",
    "addr:housenumber":"39",
    "addr:postcode":"3766 xd",
    "addr:street":"Ganzetrek",
    "iso:country":"NL",
    "sg:address":"Ganzetrek 39",
    "sg:city":"Soest",
    "sg:orig_category":"Adviesbureaus Bedrijfsorganisatie",
    "sg:phone":"+31 6 53634687",
    "sg:postcode":"3766 XD",
    "sg:province":"Utrecht",
    "wof:name":"Goosetrail Bv",
    "wof:placetype":"venue"
},
  "geometry": {"coordinates":[5.278934,52.163494],"type":"Point"}
}