{
  "type": "Feature",
  "properties": {
    "iso:country":"NL",
    "sg:address":"Olmenln 10",
    "sg:city":"Heerhugowaard",
    "sg:orig_category":"Kappers",
    "sg:phone":"+31 72 571 2262",
    "sg:postcode":"1702 KB",
    "sg:province":"Noord-Holland",
    "wof:name":"Cc Coiffures",
    "wof:placetype":"venue"
},
  "geometry": {"coordinates":[4.827521801,52.6651954651],"type":"Point"}
}