{
  "type": "Feature",
  "properties": {
    "addr:full":"Miggelenbergweg 65 Hoenderloo Gelderland 7351 BP",
    "addr:housenumber":"65",
    "addr:postcode":"7351 bp",
    "addr:street":"Miggelenbergweg;Gelderland",
    "iso:country":"NL",
    "sg:address":"Miggelenbergweg 65",
    "sg:city":"Hoenderloo",
    "sg:orig_category":"Bungalowparken And Vakantiedorpen",
    "sg:phone":"+31 55 378 1251",
    "sg:postcode":"7351 BP",
    "sg:province":"Gelderland",
    "wof:name":"Landal Greenparks",
    "wof:placetype":"venue"
},
  "geometry": {"coordinates":[5.902962,52.128845],"type":"Point"}
}