{
  "type": "Feature",
  "properties": {
    "addr:full":"Professor Vd Scheerstr 257 Haarlem Noord-Holland 2035 AP",
    "addr:housenumber":"257",
    "addr:postcode":"2035 ap",
    "addr:street":"Professor",
    "iso:country":"NL",
    "sg:address":"Professor Vd Scheerstr 257",
    "sg:city":"Haarlem",
    "sg:orig_category":"Diverse Grafische Activiteiten",
    "sg:phone":"+31 23 535 9989",
    "sg:postcode":"2035 AP",
    "sg:province":"Noord-Holland",
    "wof:name":"R. Van Boxel",
    "wof:placetype":"venue"
},
  "geometry": {"coordinates":[4.665569,52.361019],"type":"Point"}
}