{
  "type": "Feature",
  "properties": {
    "addr:full":"Geerweg 7 Sittard Limburg 6135 KB",
    "addr:housenumber":"7",
    "addr:postcode":"6135 kb",
    "addr:street":"Geerweg",
    "iso:country":"NL",
    "sg:address":"Geerweg 7",
    "sg:city":"Sittard",
    "sg:classifiers":[
        {
            "category":"Professional",
            "subcategory":"Accounting & Tax Preparation",
            "type":"Services"
        }
    ],
    "sg:phone":"+31 46 451 8351",
    "sg:postcode":"6135 KB",
    "sg:province":"Limburg",
    "sg:tags":[
        "accountant"
    ],
    "wof:name":"Zr Registeraccountants En Belastingadviseurs",
    "wof:placetype":"venue"
},
  "geometry": {"coordinates":[5.857172,51.003105],"type":"Point"}
}