{
  "type": "Feature",
  "properties": {
    "addr:full":"Seinpostduin 15 S Gravenhage Zuid-Holland 2586 EA",
    "addr:housenumber":"15;gravenhage",
    "addr:postcode":"2586 ea",
    "addr:street":"Seinpostduin;S",
    "iso:country":"NL",
    "sg:address":"Seinpostduin 15",
    "sg:city":"S Gravenhage",
    "sg:classifiers":[
        {
            "category":"Travel",
            "subcategory":"Hotels & Motels",
            "type":"Entertainment"
        }
    ],
    "sg:phone":"+31 70 355 7891",
    "sg:postcode":"2586 EA",
    "sg:province":"Zuid-Holland",
    "wof:name":"Seinduin",
    "wof:placetype":"venue"
},
  "geometry": {"coordinates":[4.277215,52.10672],"type":"Point"}
}