{
  "type": "Feature",
  "properties": {
    "iso:country":"NL",
    "sg:address":"Paul Krugerlaan 134",
    "sg:city":"'S Gravenhage",
    "sg:orig_category":"Huishoudapparatuur, Televisies And Radio'S",
    "sg:phone":"+31 70 345 5629",
    "sg:postcode":"2571 HM",
    "sg:province":"Zuid-Holland",
    "wof:name":"Torpedo",
    "wof:placetype":"venue"
},
  "geometry": {"coordinates":[4.288851,52.069229],"type":"Point"}
}