{
  "type": "Feature",
  "properties": {
    "addr:full":"Westblaak 4 Rotterdam Zuid-Holland 3012 KK",
    "addr:housenumber":"4",
    "addr:postcode":"3012 kk",
    "addr:street":"Westblaak",
    "iso:country":"NL",
    "sg:address":"Westblaak 4",
    "sg:city":"Rotterdam",
    "sg:orig_category":"Banken",
    "sg:phone":"+31 10 281 8182",
    "sg:postcode":"3012 KK",
    "sg:province":"Zuid-Holland",
    "sg:website":"http://www.dhbbank.com",
    "wof:name":"Dhb",
    "wof:placetype":"venue"
},
  "geometry": {"coordinates":[4.479666,51.917282],"type":"Point"}
}