{
  "type": "Feature",
  "properties": {
    "addr:full":"Brinkstr 2 Beilen Drenthe 9411 KM",
    "addr:housenumber":"2",
    "addr:postcode":"9411 km",
    "addr:street":"Brinkstr",
    "iso:country":"NL",
    "sg:address":"Brinkstr 2",
    "sg:city":"Beilen",
    "sg:orig_category":"Opticiens",
    "sg:phone":"+31 593 543 154",
    "sg:postcode":"9411 KM",
    "sg:province":"Drenthe",
    "sg:website":"HTTP://www.hansanders.nl",
    "wof:name":"Hans Anders",
    "wof:placetype":"venue"
},
  "geometry": {"coordinates":[6.5124220848,52.8589706421],"type":"Point"}
}