{
  "type": "Feature",
  "properties": {
    "addr:full":"Kapt De Langestr 235 Almere Flevoland 1318 DL",
    "addr:housenumber":"235",
    "addr:postcode":"1318 dl",
    "addr:street":"Kapt;Flevoland",
    "iso:country":"NL",
    "sg:address":"Kapt De Langestr 235",
    "sg:city":"Almere",
    "sg:orig_category":"Vertaalbureaus",
    "sg:phone":"+31 36 545 1699",
    "sg:postcode":"1318 DL",
    "sg:province":"Flevoland",
    "wof:name":"Interpret",
    "wof:placetype":"venue"
},
  "geometry": {"coordinates":[5.244171,52.378872],"type":"Point"}
}