{
  "type": "Feature",
  "properties": {
    "addr:full":"De Heze 52 Apeldoorn Gelderland 7335 BD",
    "addr:housenumber":"52",
    "addr:postcode":"7335 bd",
    "addr:street":"De Heze;Gelderland",
    "iso:country":"NL",
    "sg:address":"De Heze 52",
    "sg:city":"Apeldoorn",
    "sg:orig_category":"Cafetaria'S",
    "sg:phone":"+31 55 533 4482",
    "sg:postcode":"7335 BD",
    "sg:province":"Gelderland",
    "wof:name":"Eendracht, De",
    "wof:placetype":"venue"
},
  "geometry": {"coordinates":[5.949634,52.199062],"type":"Point"}
}