{
  "type": "Feature",
  "properties": {
    "addr:full":"Hoofdstr 74B Gorredyk Friesland 8401 CB",
    "addr:housenumber":"74b gorredyk",
    "addr:postcode":"8401 cb",
    "addr:street":"Hoofdstr",
    "iso:country":"NL",
    "sg:address":"Hoofdstr 74B",
    "sg:city":"Gorredyk",
    "sg:orig_category":"Psychologen",
    "sg:phone":"+31 513 464 957",
    "sg:postcode":"8401 CB",
    "sg:province":"Friesland",
    "wof:name":"Psychologen Prakt Gorredijk",
    "wof:placetype":"venue"
},
  "geometry": {"coordinates":[6.062989,53.002068],"type":"Point"}
}