{
  "type": "Feature",
  "properties": {
    "addr:full":"Raadhuisstr 1 Leeuwarden Friesland 8932 GX",
    "addr:housenumber":"1",
    "addr:postcode":"8932 gx",
    "addr:street":"Raadhuisstr",
    "iso:country":"NL",
    "sg:address":"Raadhuisstr 1",
    "sg:city":"Leeuwarden",
    "sg:orig_category":"Hulpverlening Sociaal",
    "sg:phone":"+31 58 244 9123",
    "sg:postcode":"8932 GX",
    "sg:province":"Friesland",
    "wof:name":"Nidos, Sticht",
    "wof:placetype":"venue"
},
  "geometry": {"coordinates":[5.798186,53.195724],"type":"Point"}
}