{
  "type": "Feature",
  "properties": {
    "iso:country":"NL",
    "sg:address":"Gaardenweg 6",
    "sg:city":"Enter",
    "sg:orig_category":"Zuivelproducten",
    "sg:phone":"+31 547 381 801",
    "sg:postcode":"7468 EX",
    "sg:province":"Pennsylvania",
    "wof:name":"Zuivelhandel M.E. Slot",
    "wof:placetype":"venue"
},
  "geometry": {"coordinates":[-76.841904,40.463078],"type":"Point"}
}