{
  "type": "Feature",
  "properties": {
    "addr:full":"Hooftstraat 269 Alphen A/D Rijn Zuid-Holland 2406 GJ",
    "addr:housenumber":"269",
    "addr:postcode":"2406 gj",
    "addr:street":"Hooftstraat",
    "iso:country":"NL",
    "sg:address":"Hooftstraat 269",
    "sg:city":"Alphen A/D Rijn",
    "sg:orig_category":"Loodgieterswerk, Verwarming And Sanitaire Installaties",
    "sg:phone":"+31 172 473 119",
    "sg:postcode":"2406 GJ",
    "sg:province":"Zuid-Holland",
    "wof:name":"Gebr. Rozestraten",
    "wof:placetype":"venue"
},
  "geometry": {"coordinates":[4.663543,52.137478],"type":"Point"}
}