{
  "type": "Feature",
  "properties": {
    "iso:country":"NL",
    "sg:address":"Meesenbroekwg 46",
    "sg:city":"Maastricht",
    "sg:orig_category":"Modevakscholen",
    "sg:phone":"+31 43 326 3761",
    "sg:postcode":"6212 HH",
    "sg:province":"Limburg",
    "wof:name":"Dekkers, Modevakschool",
    "wof:placetype":"venue"
},
  "geometry": {"coordinates":[5.679186,50.837837],"type":"Point"}
}