{
  "type": "Feature",
  "properties": {
    "addr:full":"Amsterdamsestrwg 540 Utrecht Utrecht 3553 EN",
    "addr:housenumber":"540",
    "addr:postcode":"3553 en",
    "iso:country":"NL",
    "sg:address":"Amsterdamsestrwg 540",
    "sg:city":"Utrecht",
    "sg:orig_category":"Makelaars En Adviseurs Verzekeringen",
    "sg:phone":"+31 30 246 8008",
    "sg:postcode":"3553 EN",
    "sg:province":"Utrecht",
    "wof:name":"Gruter & Partners",
    "wof:placetype":"venue"
},
  "geometry": {"coordinates":[5.083884,52.109901],"type":"Point"}
}