{
  "type": "Feature",
  "properties": {
    "addr:full":"Flessenbergerwg 43 Wapenveld Gelderland 8191 LH",
    "addr:housenumber":"43",
    "addr:postcode":"8191 lh",
    "addr:street":"Flessenbergerwg;Gelderland",
    "iso:country":"NL",
    "sg:address":"Flessenbergerwg 43",
    "sg:city":"Wapenveld",
    "sg:orig_category":"Psychologen",
    "sg:phone":"+31 38 447 8189",
    "sg:postcode":"8191 LH",
    "sg:province":"Gelderland",
    "wof:name":"Verkade, Drs A G",
    "wof:placetype":"venue"
},
  "geometry": {"coordinates":[6.07377,52.424999],"type":"Point"}
}