{
  "type": "Feature",
  "properties": {
    "iso:country":"NL",
    "sg:address":"Werststg 25",
    "sg:city":"Berlicum Nb",
    "sg:orig_category":"Antiquiteiten",
    "sg:phone":"+31 73 503 2552",
    "sg:postcode":"5258 TA",
    "sg:province":"North Brabant",
    "wof:name":"Panhoeve, De",
    "wof:placetype":"venue"
},
  "geometry": {"coordinates":[5.411447,51.682568],"type":"Point"}
}