{
  "type": "Feature",
  "properties": {
    "addr:full":"Rechterstraat 19 Boxtel Noord-Brabant 5281  B",
    "addr:housenumber":"19;5281 b",
    "addr:street":"Rechterstraat",
    "iso:country":"NL",
    "sg:address":"Rechterstraat 19",
    "sg:city":"Boxtel",
    "sg:orig_category":"Boekenuitgeverijen",
    "sg:phone":"+31 411 673 577",
    "sg:postcode":"5281  B",
    "sg:province":"Noord-Brabant",
    "wof:name":"Bruna",
    "wof:placetype":"venue"
},
  "geometry": {"coordinates":[5.326374,51.588001],"type":"Point"}
}