{
  "type": "Feature",
  "properties": {
    "addr:full":"Decanyewg 3 Vorden Gelderland 7251 BP",
    "addr:housenumber":"3",
    "addr:postcode":"7251 bp",
    "addr:street":"Decanyewg;Gelderland",
    "iso:country":"NL",
    "sg:address":"Decanyewg 3",
    "sg:city":"Vorden",
    "sg:orig_category":"Pensioenen",
    "sg:phone":"+31 575 553 050",
    "sg:postcode":"7251 BP",
    "sg:province":"Gelderland",
    "wof:name":"Perspectief Harmsen",
    "wof:placetype":"venue"
},
  "geometry": {"coordinates":[6.310253,52.105072],"type":"Point"}
}