{
  "type": "Feature",
  "properties": {
    "addr:full":"Meyerbeerstr 23 Waalwyk Noord-Brabant 5144 GN",
    "addr:housenumber":"23",
    "addr:postcode":"5144 gn",
    "addr:street":"Meyerbeerstr",
    "iso:country":"NL",
    "sg:address":"Meyerbeerstr 23",
    "sg:city":"Waalwyk",
    "sg:orig_category":"Parketvloeren",
    "sg:phone":"+31 6 53535997",
    "sg:postcode":"5144 GN",
    "sg:province":"Noord-Brabant",
    "wof:name":"Jw",
    "wof:placetype":"venue"
},
  "geometry": {"coordinates":[5.066499,51.682365],"type":"Point"}
}