{
  "type": "Feature",
  "properties": {
    "addr:full":"Langestr 41 Nykerk Gld Gelderland 3861 BM",
    "addr:housenumber":"41",
    "addr:postcode":"3861 bm",
    "addr:street":"Langestr;Gld Gelderland",
    "iso:country":"NL",
    "sg:address":"Langestr 41",
    "sg:city":"Nykerk Gld",
    "sg:orig_category":"Natuurvoeding En Reformartikelen",
    "sg:phone":"+31 33 245 7766",
    "sg:postcode":"3861 BM",
    "sg:province":"Gelderland",
    "sg:website":"http://www.denatuurwinkel.nl",
    "wof:name":"Natuurwinkel, De",
    "wof:placetype":"venue"
},
  "geometry": {"coordinates":[5.4831,52.221569],"type":"Point"}
}