{
  "type": "Feature",
  "properties": {
    "addr:full":"Borgercompagnie 186A Borgercompagnie Groningen 9631 TM",
    "addr:housenumber":"186a",
    "addr:postcode":"9631 tm",
    "addr:street":"Borgercompagnie",
    "iso:country":"NL",
    "sg:address":"Borgercompagnie 186A",
    "sg:city":"Borgercompagnie",
    "sg:orig_category":"Koeltechniek",
    "sg:phone":"+31 598 614 068",
    "sg:postcode":"9631 TM",
    "sg:province":"Groningen",
    "wof:name":"Boer, De",
    "wof:placetype":"venue"
},
  "geometry": {"coordinates":[6.824295,53.108906],"type":"Point"}
}