{
  "type": "Feature",
  "properties": {
    "iso:country":"NL",
    "sg:address":"Bentelosestraat 40",
    "sg:city":"Bentelo",
    "sg:orig_category":"Aannemers Woningbouw",
    "sg:phone":"+31 547 292 523",
    "sg:postcode":"7497 MR",
    "sg:province":"Overijssel",
    "wof:name":"Fa Nijland En Bos Aannemings- Bedrijf &",
    "wof:placetype":"venue"
},
  "geometry": {"coordinates":[6.681271,52.226387],"type":"Point"}
}