{
  "type": "Feature",
  "properties": {
    "addr:full":"Najaarsweg 26 Enschede Overijssel 7532 SK",
    "addr:housenumber":"26",
    "addr:street":"Najaarsweg;7532",
    "iso:country":"NL",
    "sg:address":"Najaarsweg 26",
    "sg:city":"Enschede",
    "sg:orig_category":"Koeriersdiensten",
    "sg:phone":"+31 53 461 7470",
    "sg:postcode":"7532 SK",
    "sg:province":"Overijssel",
    "wof:name":"Hessing Koeriers & Sneldienst",
    "wof:placetype":"venue"
},
  "geometry": {"coordinates":[6.957224,52.223469],"type":"Point"}
}