{
  "type": "Feature",
  "properties": {
    "addr:full":"Lichtenhorststr 13 Didam Gelderland 6942 GS",
    "addr:housenumber":"13",
    "addr:postcode":"6942 gs",
    "addr:street":"Lichtenhorststr;Gelderland",
    "iso:country":"NL",
    "sg:address":"Lichtenhorststr 13",
    "sg:city":"Didam",
    "sg:orig_category":"Schilders",
    "sg:phone":"+31 316 223 169",
    "sg:postcode":"6942 GS",
    "sg:province":"Gelderland",
    "wof:name":"Wessel, Van",
    "wof:placetype":"venue"
},
  "geometry": {"coordinates":[6.141532,51.93428],"type":"Point"}
}