{
  "type": "Feature",
  "properties": {
    "iso:country":"NL",
    "sg:address":"Oude Graafseweg 3",
    "sg:city":"Nijmegen",
    "sg:orig_category":"Fitnesscentra",
    "sg:phone":"+31 24 378 4260",
    "sg:postcode":"6543 PN",
    "sg:province":"Gelderland",
    "wof:name":"Aerobic Studio Heavenly Bodies",
    "wof:placetype":"venue"
},
  "geometry": {"coordinates":[5.838949,51.835682],"type":"Point"}
}