{
  "type": "Feature",
  "properties": {
    "iso:country":"NL",
    "sg:address":"Marconistr 8",
    "sg:city":"Tiel",
    "sg:orig_category":"Schilders",
    "sg:phone":"+31 344 610 484",
    "sg:postcode":"4004 JM",
    "sg:province":"Gelderland",
    "wof:name":"Midden-Ned Bv",
    "wof:placetype":"venue"
},
  "geometry": {"coordinates":[5.432778,51.906464],"type":"Point"}
}