{
  "type": "Feature",
  "properties": {
    "iso:country":"NL",
    "sg:address":"H Ter Kuilestr 191",
    "sg:city":"Enschede",
    "sg:classifiers":[
        {
            "category":"Home & Garden",
            "subcategory":"Hardware",
            "type":"Retail Goods"
        }
    ],
    "sg:phone":"+31 53 430 8888",
    "sg:postcode":"7547 SK",
    "sg:province":"NL.08",
    "sg:tags":[
        "machine",
        "-",
        "metaalbewerking"
    ],
    "sg:website":"http://www.zaagmachines.nl",
    "wof:name":"Klaassen Bv",
    "wof:placetype":"venue"
},
  "geometry": {"coordinates":[6.847808,52.218952],"type":"Point"}
}