{
  "type": "Feature",
  "properties": {
    "iso:country":"NL",
    "sg:address":"P A Van Meverstraat 1",
    "sg:city":"Zaandam",
    "sg:classifiers":[
        {
            "category":"Education",
            "subcategory":"Preschool",
            "type":"Public Place"
        }
    ],
    "sg:phone":"+31 75 635 4699",
    "sg:postcode":"1507 XE",
    "sg:province":"Noord-Holland",
    "sg:tags":[
        "kleuteronderwijs",
        "basis-"
    ],
    "wof:name":"Eiland Het Openbaar",
    "wof:placetype":"venue"
},
  "geometry": {"coordinates":[4.800949,52.448204],"type":"Point"}
}