{
  "type": "Feature",
  "properties": {
    "iso:country":"NL",
    "sg:address":"Zwaanstraat 8",
    "sg:city":"Amersfoort",
    "sg:orig_category":"Meubelreparatie And -Restauratie",
    "sg:phone":"+31 33 475 1670",
    "sg:postcode":"3816 AR",
    "sg:province":"Utrecht",
    "wof:name":"Meubelstoffeerderij Astrid Dudok Van Hee",
    "wof:placetype":"venue"
},
  "geometry": {"coordinates":[5.397439,52.15303],"type":"Point"}
}