{
  "type": "Feature",
  "properties": {
    "addr:full":"Wilhelminalaan 1 Hoorn Nh North Holland 1623 MA",
    "addr:housenumber":"1",
    "addr:postcode":"1623 ma",
    "addr:street":"Wilhelminalaan;Nh North",
    "iso:country":"NL",
    "sg:address":"Wilhelminalaan 1",
    "sg:city":"Hoorn Nh",
    "sg:classifiers":[
        {
            "category":"Education",
            "subcategory":"Preschool",
            "type":"Public Place"
        }
    ],
    "sg:phone":"+31 229 216 793",
    "sg:postcode":"1623 MA",
    "sg:province":"North Holland",
    "sg:tags":[
        "kleuteronderwijs",
        "basis-"
    ],
    "wof:name":"Oecumenische School Voor Speciaal Basisonderwijs",
    "wof:placetype":"venue"
},
  "geometry": {"coordinates":[5.067267,52.645592],"type":"Point"}
}