{
  "type": "Feature",
  "properties": {
    "addr:full":"Peelstr 30 Kronenberg Limburg 5976 NL",
    "addr:housenumber":"30",
    "addr:postcode":"5976 nl",
    "addr:street":"Peelstr",
    "iso:country":"NL",
    "sg:address":"Peelstr 30",
    "sg:city":"Kronenberg",
    "sg:orig_category":"Bloemen En Planten",
    "sg:phone":"+31 77 467 1563",
    "sg:postcode":"5976 NL",
    "sg:province":"Limburg",
    "wof:name":"Billekens",
    "wof:placetype":"venue"
},
  "geometry": {"coordinates":[5.996374,51.416698],"type":"Point"}
}