{
  "type": "Feature",
  "properties": {
    "iso:country":"NL",
    "sg:address":"Den Bulk 5",
    "sg:city":"Gilze",
    "sg:orig_category":"Machinehandel",
    "sg:phone":"+31 161 452 516",
    "sg:postcode":"5126 PW",
    "sg:province":"Noord-Brabant",
    "wof:name":"Koenen, Henk",
    "wof:placetype":"venue"
},
  "geometry": {"coordinates":[4.9468998909,51.5476989746],"type":"Point"}
}