{
  "type": "Feature",
  "properties": {
    "iso:country":"NL",
    "sg:address":"Maerten V Heemskerckstr 69",
    "sg:city":"Haarlem",
    "sg:orig_category":"Fitnesscentra",
    "sg:phone":"+31 23 526 5599",
    "sg:postcode":"2021 ZH",
    "sg:province":"Noord-Holland",
    "wof:name":"Henny",
    "wof:placetype":"venue"
},
  "geometry": {"coordinates":[4.63528,52.39241],"type":"Point"}
}