{
  "type": "Feature",
  "properties": {
    "iso:country":"NL",
    "sg:address":"Toldk 21",
    "sg:city":"Hoogeveen",
    "sg:orig_category":"Vuilnisafvoer",
    "sg:phone":"+31 528 262 147",
    "sg:postcode":"7901 TA",
    "sg:province":"Provincie Drenthe",
    "wof:name":"Dutch Waste Solution Bv",
    "wof:placetype":"venue"
},
  "geometry": {"coordinates":[6.473344,52.74033],"type":"Point"}
}