{
  "type": "Feature",
  "properties": {
    "addr:full":"Sweelinckhof 34 Waddinxveen Zuid-Holland 2742 CA",
    "addr:housenumber":"34",
    "addr:postcode":"2742 ca",
    "addr:street":"Sweelinckhof",
    "iso:country":"NL",
    "sg:address":"Sweelinckhof 34",
    "sg:city":"Waddinxveen",
    "sg:orig_category":"Afzuiginstallaties",
    "sg:phone":"+31 182 610 394",
    "sg:postcode":"2742 CA",
    "sg:province":"Zuid-Holland",
    "wof:name":"Versteeg",
    "wof:placetype":"venue"
},
  "geometry": {"coordinates":[4.645923,52.048435],"type":"Point"}
}