{
  "type": "Feature",
  "properties": {
    "addr:full":"Oegstgeesterwg 202A Rynsburg South Holland 2231 BD",
    "addr:housenumber":"202a",
    "addr:postcode":"2231 bd",
    "addr:street":"Rynsburg South",
    "iso:country":"NL",
    "sg:address":"Oegstgeesterwg 202A",
    "sg:city":"Rynsburg",
    "sg:orig_category":"Bloemen En Planten",
    "sg:phone":"+31 71 408 1471",
    "sg:postcode":"2231 BD",
    "sg:province":"South Holland",
    "sg:website":"http://www.vletterdenhaan.nl",
    "wof:name":"Vletter En Den Haan, Gebrs",
    "wof:placetype":"venue"
},
  "geometry": {"coordinates":[4.447846,52.189789],"type":"Point"}
}