{
  "type": "Feature",
  "properties": {
    "addr:full":"Hatertseweg 168 Nijmegen Gelderland 6533 AT",
    "addr:housenumber":"168",
    "addr:postcode":"6533",
    "addr:street":"Hatertseweg;Gelderland",
    "iso:country":"NL",
    "sg:address":"Hatertseweg 168",
    "sg:city":"Nijmegen",
    "sg:orig_category":"Metaalbekleding And -Behandeling",
    "sg:phone":"+31 24 355 0631",
    "sg:postcode":"6533 AT",
    "sg:province":"Gelderland",
    "wof:name":"Van Der Velden S Machinefabriek",
    "wof:placetype":"venue"
},
  "geometry": {"coordinates":[5.850322,51.823025],"type":"Point"}
}