{
  "type": "Feature",
  "properties": {
    "addr:full":"Staalstr 28 Amsterdam North Holland 1011 JM",
    "addr:housenumber":"28",
    "addr:postcode":"1011 jm",
    "addr:street":"Staalstr",
    "iso:country":"NL",
    "sg:address":"Staalstr 28",
    "sg:city":"Amsterdam",
    "sg:orig_category":"Organisatiebureaus",
    "sg:phone":"+31 20 625 9303",
    "sg:postcode":"1011 JM",
    "sg:province":"North Holland",
    "sg:website":"http://www.arttra.com",
    "wof:name":"Arttra Cultureel Organisatiebureau",
    "wof:placetype":"venue"
},
  "geometry": {"coordinates":[4.8982839584,52.3681221008],"type":"Point"}
}