{
  "type": "Feature",
  "properties": {
    "addr:full":"Stevinstr 6 Schoonhoven Zuid-Holland 2871 XG",
    "addr:housenumber":"6",
    "addr:postcode":"2871 xg",
    "addr:street":"Stevinstr",
    "iso:country":"NL",
    "sg:address":"Stevinstr 6",
    "sg:city":"Schoonhoven",
    "sg:orig_category":"Voegwerken",
    "sg:phone":"+31 182 387 555",
    "sg:postcode":"2871 XG",
    "sg:province":"Zuid-Holland",
    "wof:name":"Zaal, Van",
    "wof:placetype":"venue"
},
  "geometry": {"coordinates":[4.84101,51.953907],"type":"Point"}
}