{
  "type": "Feature",
  "properties": {
    "iso:country":"NL",
    "sg:address":"Vlietln 44B",
    "sg:city":"Bussum",
    "sg:orig_category":"Kinderkleding",
    "sg:phone":"+31 35 582 7130",
    "sg:postcode":"1404 CC",
    "sg:province":"North Holland",
    "wof:name":"Sonanz",
    "wof:placetype":"venue"
},
  "geometry": {"coordinates":[5.162605,52.276829],"type":"Point"}
}