{
  "type": "Feature",
  "properties": {
    "addr:full":"Overtoom 207 Amsterdam Noord-Holland 1054 HT",
    "addr:housenumber":"207",
    "addr:postcode":"1054 ht",
    "addr:street":"Overtoom",
    "iso:country":"NL",
    "sg:address":"Overtoom 207",
    "sg:city":"Amsterdam",
    "sg:orig_category":"Psychotherapeuten",
    "sg:phone":"+31 20 685 0426",
    "sg:postcode":"1054 HT",
    "sg:province":"Noord-Holland",
    "wof:name":"Overtoom, Praktijk",
    "wof:placetype":"venue"
},
  "geometry": {"coordinates":[4.870124,52.361221],"type":"Point"}
}