{
  "type": "Feature",
  "properties": {
    "addr:full":"Zeearend 72 Heerhugowaard Noord-Holland 1704 TE",
    "addr:housenumber":"72",
    "addr:postcode":"1704 te",
    "addr:street":"Zeearend",
    "iso:country":"NL",
    "sg:address":"Zeearend 72",
    "sg:city":"Heerhugowaard",
    "sg:orig_category":"Adviesbureaus Elektrotechniek",
    "sg:phone":"+31 72 534 7445",
    "sg:postcode":"1704 TE",
    "sg:province":"Noord-Holland",
    "sg:website":"http://www.dematek.nl",
    "wof:name":"Dematek",
    "wof:placetype":"venue"
},
  "geometry": {"coordinates":[4.813644,52.655144],"type":"Point"}
}