{
  "type": "Feature",
  "properties": {
    "iso:country":"NL",
    "sg:address":"Noorderhaven 85",
    "sg:city":"Harlingen",
    "sg:orig_category":"Watersportartikelen",
    "sg:phone":"+31 517 412 227",
    "sg:postcode":"8861 AM",
    "sg:province":"Friesland",
    "sg:website":"http://www.tenbeaufort.nl",
    "wof:name":"Ten Beaufort",
    "wof:placetype":"venue"
},
  "geometry": {"coordinates":[5.418806076,53.1761627197],"type":"Point"}
}