{
  "type": "Feature",
  "properties": {
    "iso:country":"NL",
    "sg:address":"Havenstr 1",
    "sg:city":"Monster",
    "sg:orig_category":"Verenigingsgebouwen",
    "sg:phone":"+31 174 212 698",
    "sg:postcode":"2681 LB",
    "sg:province":"Ohio",
    "wof:name":"Haven, De",
    "wof:placetype":"venue"
},
  "geometry": {"coordinates":[-84.369049,40.363762],"type":"Point"}
}