{
  "type": "Feature",
  "properties": {
    "addr:full":"Distelveld 42 Bavel Noord-Brabant 4854 MC",
    "addr:housenumber":"42",
    "addr:postcode":"4854 mc",
    "addr:street":"Distelveld",
    "iso:country":"NL",
    "sg:address":"Distelveld 42",
    "sg:city":"Bavel",
    "sg:orig_category":"Hoger Onderwijs",
    "sg:phone":"+31 161 433 232",
    "sg:postcode":"4854 MC",
    "sg:province":"Noord-Brabant",
    "wof:name":"H.A.M. Klomp-V.D. Velden",
    "wof:placetype":"venue"
},
  "geometry": {"coordinates":[4.831906,51.571815],"type":"Point"}
}