{
  "type": "Feature",
  "properties": {
    "addr:full":"Wijkstraat 71 Appingedam Groningen 9901 AH",
    "addr:housenumber":"71",
    "addr:postcode":"9901 ah",
    "addr:street":"Wijkstraat",
    "iso:country":"NL",
    "sg:address":"Wijkstraat 71",
    "sg:city":"Appingedam",
    "sg:orig_category":"Herenmodezaken",
    "sg:phone":"+31 596 681 314",
    "sg:postcode":"9901 AH",
    "sg:province":"Groningen",
    "wof:name":"Switch Herenmode",
    "wof:placetype":"venue"
},
  "geometry": {"coordinates":[6.860865,53.320484],"type":"Point"}
}