{
  "type": "Feature",
  "properties": {
    "addr:full":"Waddenwg 8 Amsterdam Noord-Holland 1025 PV",
    "addr:housenumber":"8",
    "addr:postcode":"1025 pv",
    "addr:street":"Waddenwg",
    "iso:country":"NL",
    "sg:address":"Waddenwg 8",
    "sg:city":"Amsterdam",
    "sg:orig_category":"Wasserijen",
    "sg:phone":"+31 20 636 0280",
    "sg:postcode":"1025 PV",
    "sg:province":"Noord-Holland",
    "wof:name":"Eerste Volharding Bv",
    "wof:placetype":"venue"
},
  "geometry": {"coordinates":[4.9259982109,52.3914985657],"type":"Point"}
}