{
  "type": "Feature",
  "properties": {
    "addr:full":"Sparrenstr 46 Ymuiden Noord-Holland 1971 NP",
    "addr:housenumber":"46",
    "addr:postcode":"1971 np",
    "addr:street":"Sparrenstr",
    "iso:country":"NL",
    "sg:address":"Sparrenstr 46",
    "sg:city":"Ymuiden",
    "sg:orig_category":"Kunstgebitten",
    "sg:phone":"+31 255 524 221",
    "sg:postcode":"1971 NP",
    "sg:province":"Noord-Holland",
    "wof:name":"Nierop, Tandprotheticus",
    "wof:placetype":"venue"
},
  "geometry": {"coordinates":[4.631131,52.457752],"type":"Point"}
}