{
  "type": "Feature",
  "properties": {
    "addr:full":"Vierhavensstraat 1/U110 Rotterdam South Holland 3029 BB",
    "addr:housenumber":"1 / u110",
    "addr:postcode":"3029 bb",
    "addr:street":"Vierhavensstraat",
    "iso:country":"NL",
    "sg:address":"Vierhavensstraat 1/U110",
    "sg:city":"Rotterdam",
    "sg:orig_category":"Binnenhuisarchitecten",
    "sg:phone":"+31 10 244 0226",
    "sg:postcode":"3029 BB",
    "sg:province":"South Holland",
    "wof:name":"Het Ruimtelab",
    "wof:placetype":"venue"
},
  "geometry": {"coordinates":[4.434218,51.908192],"type":"Point"}
}