{
  "type": "Feature",
  "properties": {
    "iso:country":"NL",
    "sg:address":"Meester Broerensingel 49",
    "sg:city":"Rosmalen",
    "sg:orig_category":"Glaszetten",
    "sg:phone":"+31 73 644 0974",
    "sg:postcode":"5246 RB",
    "sg:province":"North Brabant",
    "wof:name":"Rb Glas Rosmalen",
    "wof:placetype":"venue"
},
  "geometry": {"coordinates":[5.341429,51.704487],"type":"Point"}
}