{
  "type": "Feature",
  "properties": {
    "iso:country":"NL",
    "sg:address":"S Burgerstr 461",
    "sg:city":"S Gravenhage",
    "sg:orig_category":"Beveiliging",
    "sg:phone":"+31 6 24661820",
    "sg:postcode":"2572 TD",
    "sg:province":"Zuid-Holland",
    "wof:name":"C-E",
    "wof:placetype":"venue"
},
  "geometry": {"coordinates":[4.29421,52.06422],"type":"Point"}
}