{
  "type": "Feature",
  "properties": {
    "addr:full":"Lemelerw 74 Lemele Overijssel 8148 PD",
    "addr:housenumber":"74",
    "addr:postcode":"8148 pd",
    "addr:street":"Lemelerw",
    "iso:country":"NL",
    "sg:address":"Lemelerw 74",
    "sg:city":"Lemele",
    "sg:orig_category":"Verenigingsgebouwen",
    "sg:phone":"+31 572 331 350",
    "sg:postcode":"8148 PD",
    "sg:province":"Overijssel",
    "wof:name":"Herv Jeugdgebouw",
    "wof:placetype":"venue"
},
  "geometry": {"coordinates":[6.415347,52.45248],"type":"Point"}
}