{
  "type": "Feature",
  "properties": {
    "addr:full":"Nieuwendk 217A Amsterdam Noord-Holland 1012 MH",
    "addr:housenumber":"217a",
    "addr:postcode":"1012 mh",
    "iso:country":"NL",
    "sg:address":"Nieuwendk 217A",
    "sg:city":"Amsterdam",
    "sg:classifiers":[
        {
            "category":"Food & Beverages",
            "subcategory":"Bakery",
            "type":"Retail Goods"
        }
    ],
    "sg:phone":"+31 20 624 1107",
    "sg:postcode":"1012 MH",
    "sg:province":"Noord-Holland",
    "sg:tags":[
        "brood",
        "en",
        "banket"
    ],
    "wof:name":"Outmaijer",
    "wof:placetype":"venue"
},
  "geometry": {"coordinates":[4.893314,52.374138],"type":"Point"}
}