{
  "type": "Feature",
  "properties": {
    "iso:country":"NL",
    "sg:address":"J Israelstr 4",
    "sg:city":"Schagen",
    "sg:orig_category":"Scholen Voor Basisonderwijs",
    "sg:phone":"+31 224 212 933",
    "sg:postcode":"1741 JP",
    "sg:province":"North Holland",
    "wof:name":"Ark Prot Chr, De",
    "wof:placetype":"venue"
},
  "geometry": {"coordinates":[4.795939,52.790028],"type":"Point"}
}