{
  "type": "Feature",
  "properties": {
    "addr:full":"Hiddemaheerd 170 Groningen Groningen 9737 JK",
    "addr:housenumber":"170",
    "addr:postcode":"9737 jk",
    "addr:street":"Hiddemaheerd",
    "iso:country":"NL",
    "sg:address":"Hiddemaheerd 170",
    "sg:city":"Groningen",
    "sg:orig_category":"Autorijscholen",
    "sg:phone":"+31 50 542 6841",
    "sg:postcode":"9737 JK",
    "sg:province":"Groningen",
    "sg:website":"http://www.rijschoolvanderheide.nl",
    "wof:name":"Heide Rijschool, Van Der",
    "wof:placetype":"venue"
},
  "geometry": {"coordinates":[6.589164,53.253059],"type":"Point"}
}