{
  "type": "Feature",
  "properties": {
    "addr:full":"Thyswg 19 Aalten Gelderland 7122 KH",
    "addr:housenumber":"19",
    "addr:postcode":"7122 kh",
    "addr:street":"Thyswg;Gelderland",
    "iso:country":"NL",
    "sg:address":"Thyswg 19",
    "sg:city":"Aalten",
    "sg:orig_category":"Verenigingsgebouwen",
    "sg:phone":"+31 543 466 282",
    "sg:postcode":"7122 KH",
    "sg:province":"Gelderland",
    "wof:name":"Dorpshuus, 'T",
    "wof:placetype":"venue"
},
  "geometry": {"coordinates":[6.54098,51.892849],"type":"Point"}
}