{
  "type": "Feature",
  "properties": {
    "iso:country":"NL",
    "sg:address":"Spuiweg 93",
    "sg:city":"Dordrecht",
    "sg:classifiers":[
        {
            "category":"Education",
            "subcategory":"Preschool",
            "type":"Public Place"
        }
    ],
    "sg:phone":"+31 78 631 1322",
    "sg:postcode":"3311 GT",
    "sg:province":"Zuid-Holland",
    "sg:tags":[
        "kleuteronderwijs",
        "basis-"
    ],
    "wof:name":"Stichting Peuterspeelzalen Dordrecht",
    "wof:placetype":"venue"
},
  "geometry": {"coordinates":[4.662707,51.809818],"type":"Point"}
}