{
  "type": "Feature",
  "properties": {
    "addr:full":"De Raetsingel 14 Boxmeer Noord-Brabant 5831 KC",
    "addr:housenumber":"14",
    "addr:postcode":"5831 kc",
    "addr:street":"De Raetsingel",
    "iso:country":"NL",
    "sg:address":"De Raetsingel 14",
    "sg:city":"Boxmeer",
    "sg:orig_category":"Advocaten And Juridische Adviseurs",
    "sg:phone":"+31 485 572 344",
    "sg:postcode":"5831 KC",
    "sg:province":"Noord-Brabant",
    "wof:name":"Advocatenkantoor Mr. A.H.J. Barten",
    "wof:placetype":"venue"
},
  "geometry": {"coordinates":[5.947823,51.650883],"type":"Point"}
}