{
  "type": "Feature",
  "properties": {
    "addr:full":"Prins Hendrikstraat 161 Hoek Van Holland South Holland 3151 AE",
    "addr:housenumber":"161",
    "addr:postcode":"3151 ae",
    "addr:street":"Prins Hendrikstraat",
    "iso:country":"NL",
    "sg:address":"Prins Hendrikstraat 161",
    "sg:city":"Hoek Van Holland",
    "sg:orig_category":"Overheidsdiensten",
    "sg:phone":"+31 174 315 131",
    "sg:postcode":"3151 AE",
    "sg:province":"South Holland",
    "wof:name":"Deelgemeentehuis Hoek Van Holland",
    "wof:placetype":"venue"
},
  "geometry": {"coordinates":[4.1345319748,51.9755172729],"type":"Point"}
}