{
  "type": "Feature",
  "properties": {
    "addr:full":"Lloydstr 15A Rotterdam South Holland 3024 EA",
    "addr:housenumber":"15a",
    "addr:postcode":"3024 ea",
    "addr:street":"Lloydstr",
    "iso:country":"NL",
    "sg:address":"Lloydstr 15A",
    "sg:city":"Rotterdam",
    "sg:orig_category":"Video - Faciliteiten En Producties",
    "sg:phone":"+31 10 425 4046",
    "sg:postcode":"3024 EA",
    "sg:province":"South Holland",
    "sg:website":"http://www.steddy.com",
    "wof:name":"Steddy",
    "wof:placetype":"venue"
},
  "geometry": {"coordinates":[4.459969,51.903416],"type":"Point"}
}