{
  "type": "Feature",
  "properties": {
    "addr:full":"Stoepertweg 5 Valkenburg Lb Limburg 6301 WP",
    "addr:housenumber":"5",
    "addr:postcode":"lb;6301 wp",
    "addr:street":"Stoepertweg",
    "iso:country":"NL",
    "sg:address":"Stoepertweg 5",
    "sg:city":"Valkenburg Lb",
    "sg:orig_category":"Kampeerterreinen",
    "sg:phone":"+31 45 405 9292",
    "sg:postcode":"6301 WP",
    "sg:province":"Limburg",
    "wof:name":"Cafe Camping De Bron",
    "wof:placetype":"venue"
},
  "geometry": {"coordinates":[5.832326889,50.8740921021],"type":"Point"}
}