{
  "type": "Feature",
  "properties": {
    "addr:full":"Zandhofsestr 39 Utrecht Utrecht 3572 GB",
    "addr:housenumber":"39",
    "addr:postcode":"3572 gb",
    "addr:street":"Zandhofsestr",
    "iso:country":"NL",
    "sg:address":"Zandhofsestr 39",
    "sg:city":"Utrecht",
    "sg:orig_category":"Grafisch Ontwerpers",
    "sg:phone":"+31 30 271 5236",
    "sg:postcode":"3572 GB",
    "sg:province":"Utrecht",
    "wof:name":"Kok",
    "wof:placetype":"venue"
},
  "geometry": {"coordinates":[5.130895,52.098438],"type":"Point"}
}