{
  "type": "Feature",
  "properties": {
    "addr:full":"Beethovenlaan 37 Nijverdal Overijssel 7442 HC",
    "addr:housenumber":"37",
    "addr:postcode":"7442 hc",
    "addr:street":"Beethovenlaan",
    "iso:country":"NL",
    "sg:address":"Beethovenlaan 37",
    "sg:city":"Nijverdal",
    "sg:orig_category":"Boekhouders",
    "sg:phone":"+31 548 614 774",
    "sg:postcode":"7442 HC",
    "sg:province":"Overijssel",
    "wof:name":"A.H.J. Oogink Veldkamp",
    "wof:placetype":"venue"
},
  "geometry": {"coordinates":[6.482381,52.35598],"type":"Point"}
}