{
  "type": "Feature",
  "properties": {
    "addr:full":"Kamillehof 58 Tilburg North Brabant 5044 AN",
    "addr:housenumber":"58",
    "addr:postcode":"5044 an",
    "addr:street":"Kamillehof",
    "iso:country":"NL",
    "sg:address":"Kamillehof 58",
    "sg:city":"Tilburg",
    "sg:orig_category":"Graniet-, Granito- En Terrazzowerken",
    "sg:phone":"+31 13 468 3964",
    "sg:postcode":"5044 AN",
    "sg:province":"North Brabant",
    "wof:name":"Goewie, J A",
    "wof:placetype":"venue"
},
  "geometry": {"coordinates":[5.041447,51.577026],"type":"Point"}
}