{
  "type": "Feature",
  "properties": {
    "iso:country":"NL",
    "sg:address":"Nieuwstr 24",
    "sg:city":"Oostburg",
    "sg:orig_category":"Banken",
    "sg:phone":"+31 117 440 402",
    "sg:postcode":"4501 BD",
    "sg:province":"Zeeland",
    "wof:name":"Regio Bank",
    "wof:placetype":"venue"
},
  "geometry": {"coordinates":[3.487122,51.326],"type":"Point"}
}