{
  "type": "Feature",
  "properties": {
    "addr:full":"Christinastraat 1 Lisse Zuid-Holland 2161 SB",
    "addr:housenumber":"1",
    "addr:postcode":"2161 sb",
    "addr:street":"Christinastraat",
    "iso:country":"NL",
    "sg:address":"Christinastraat 1",
    "sg:city":"Lisse",
    "sg:orig_category":"Autokeuringen",
    "sg:phone":"+31 252 413 613",
    "sg:postcode":"2161 SB",
    "sg:province":"Zuid-Holland",
    "wof:name":"P.J. De Klerk'S Automobielbedrijf",
    "wof:placetype":"venue"
},
  "geometry": {"coordinates":[4.560428,52.262939],"type":"Point"}
}