{
  "type": "Feature",
  "properties": {
    "addr:full":"Baarlosestraat 277 Venlo Limburg 5926 PM",
    "addr:housenumber":"277",
    "addr:postcode":"5926 pm",
    "addr:street":"Baarlosestraat",
    "iso:country":"NL",
    "sg:address":"Baarlosestraat 277",
    "sg:city":"Venlo",
    "sg:orig_category":"Goederenvervoer Over De Weg",
    "sg:phone":"+31 77 382 2652",
    "sg:postcode":"5926 PM",
    "sg:province":"Limburg",
    "wof:name":"G. Crienen",
    "wof:placetype":"venue"
},
  "geometry": {"coordinates":[6.124877,51.354134],"type":"Point"}
}