{
  "type": "Feature",
  "properties": {
    "addr:full":"Glacisw 55 Maastricht Limburg 6212 BM",
    "addr:housenumber":"55",
    "addr:postcode":"6212 bm",
    "addr:street":"Glacisw",
    "iso:country":"NL",
    "sg:address":"Glacisw 55",
    "sg:city":"Maastricht",
    "sg:orig_category":"Bloemen En Planten",
    "sg:phone":"+31 43 321 4405",
    "sg:postcode":"6212 BM",
    "sg:province":"Limburg",
    "wof:name":"Belinda",
    "wof:placetype":"venue"
},
  "geometry": {"coordinates":[5.689773,50.839584],"type":"Point"}
}