{
  "type": "Feature",
  "properties": {
    "addr:full":"Van Poelgeestlaan 22 Koudekerk A/D Rijn Zuid-Holland 2396 BD",
    "addr:housenumber":"22;a / d",
    "addr:postcode":"2396 bd",
    "addr:street":"Van Poelgeestlaan",
    "iso:country":"NL",
    "sg:address":"Van Poelgeestlaan 22",
    "sg:city":"Koudekerk A/D Rijn",
    "sg:orig_category":"Zuivelproducten",
    "sg:phone":"+31 71 341 3460",
    "sg:postcode":"2396 BD",
    "sg:province":"Zuid-Holland",
    "wof:name":"Ammerlaan'S Zuivelbedrijf Bv",
    "wof:placetype":"venue"
},
  "geometry": {"coordinates":[4.603768,52.13205],"type":"Point"}
}