{
  "type": "Feature",
  "properties": {
    "iso:country":"NL",
    "sg:address":"Kerkstraat 22",
    "sg:city":"Groot Ammers",
    "sg:orig_category":"Binnenhuisarchitecten",
    "sg:phone":"+31 184 661 238",
    "sg:postcode":"2964 BV",
    "sg:province":"Zuid-Holland",
    "wof:name":"Architektenburo Bikker Bv",
    "wof:placetype":"venue"
},
  "geometry": {"coordinates":[4.818135,51.923016],"type":"Point"}
}