{
  "type": "Feature",
  "properties": {
    "addr:full":"Meidoornstraat 19 Stadskanaal Groningen 9501 VX",
    "addr:housenumber":"19",
    "addr:postcode":"9501 vx",
    "addr:street":"Meidoornstraat",
    "iso:country":"NL",
    "sg:address":"Meidoornstraat 19",
    "sg:city":"Stadskanaal",
    "sg:classifiers":[
        {
            "category":"Education",
            "subcategory":"Preschool",
            "type":"Public Place"
        }
    ],
    "sg:phone":"+31 599 617 111",
    "sg:postcode":"9501 VX",
    "sg:province":"Groningen",
    "sg:tags":[
        "kleuteronderwijs",
        "basis-"
    ],
    "wof:name":"De Oleander",
    "wof:placetype":"venue"
},
  "geometry": {"coordinates":[6.933115,53.001179],"type":"Point"}
}