{
  "type": "Feature",
  "properties": {
    "addr:full":"Noordenveld 29 Lelystad Flevoland 8245 CP",
    "addr:housenumber":"29",
    "addr:postcode":"8245 cp",
    "addr:street":"Noordenveld;Flevoland",
    "iso:country":"NL",
    "sg:address":"Noordenveld 29",
    "sg:city":"Lelystad",
    "sg:orig_category":"Graveerbedrijven",
    "sg:phone":"+31 6 22910086",
    "sg:postcode":"8245 CP",
    "sg:province":"Flevoland",
    "wof:name":"Tgc",
    "wof:placetype":"venue"
},
  "geometry": {"coordinates":[5.466607,52.496693],"type":"Point"}
}