{
  "type": "Feature",
  "properties": {
    "iso:country":"NL",
    "sg:address":"Chopinstr 160",
    "sg:city":"Alkmaar",
    "sg:orig_category":"Artsen - Huisartsen",
    "sg:phone":"+31 72 511 5444",
    "sg:postcode":"1817 GD",
    "sg:province":"Noord-Holland",
    "wof:name":"Bruin, J J F",
    "wof:placetype":"venue"
},
  "geometry": {"coordinates":[4.738335,52.641727],"type":"Point"}
}