{
  "type": "Feature",
  "properties": {
    "addr:full":"Zeggeln 110 Terheyden Noord-Brabant 4844 SK",
    "addr:housenumber":"110",
    "addr:street":"Terheyden;4844",
    "iso:country":"NL",
    "sg:address":"Zeggeln 110",
    "sg:city":"Terheyden",
    "sg:orig_category":"Gezondheidszorg Geestelijke -",
    "sg:phone":"+31 76 593 7114",
    "sg:postcode":"4844 SK",
    "sg:province":"Noord-Brabant",
    "wof:name":"Sovak, Sticht",
    "wof:placetype":"venue"
},
  "geometry": {"coordinates":[4.75427,51.641541],"type":"Point"}
}