{
  "type": "Feature",
  "properties": {
    "iso:country":"NL",
    "sg:address":"Sandelingstr 45",
    "sg:city":"Rotterdam",
    "sg:orig_category":"Juweliers",
    "sg:phone":"+31 10 484 1751",
    "sg:postcode":"3073 AN",
    "sg:province":"Zuid-Holland",
    "wof:name":"Cees Maasbach Goudsmederij",
    "wof:placetype":"venue"
},
  "geometry": {"coordinates":[4.503618,51.891735],"type":"Point"}
}