{
  "type": "Feature",
  "properties": {
    "addr:full":"Kr Elleboog 44 Haren Gn Groningen 9751 RE",
    "addr:housenumber":"44",
    "addr:postcode":"9751 re",
    "addr:street":"Kr Elleboog",
    "iso:country":"NL",
    "sg:address":"Kr Elleboog 44",
    "sg:city":"Haren Gn",
    "sg:orig_category":"Verf En Lak",
    "sg:phone":"+31 50 534 4863",
    "sg:postcode":"9751 RE",
    "sg:province":"Groningen",
    "wof:name":"Ploeger",
    "wof:placetype":"venue"
},
  "geometry": {"coordinates":[6.60632,53.170658],"type":"Point"}
}