{
  "type": "Feature",
  "properties": {
    "addr:full":"Nw Koolw 14 Zierikzee Zeeland 4301 SC",
    "addr:housenumber":"14",
    "addr:postcode":"4301",
    "addr:street":"Koolw",
    "iso:country":"NL",
    "sg:address":"Nw Koolw 14",
    "sg:city":"Zierikzee",
    "sg:orig_category":"Pluimveebedrijven En -Handelaren",
    "sg:phone":"+31 111 412 232",
    "sg:postcode":"4301 SC",
    "sg:province":"Zeeland",
    "wof:name":"Schouls, D",
    "wof:placetype":"venue"
},
  "geometry": {"coordinates":[3.91706,51.65007],"type":"Point"}
}