{
  "type": "Feature",
  "properties": {
    "addr:full":"Toscaninistr 45 S Gravenhage South Holland 2551 LT",
    "addr:housenumber":"45",
    "addr:postcode":"2551 lt",
    "addr:street":"Toscaninistr;S Gravenhage",
    "iso:country":"NL",
    "sg:address":"Toscaninistr 45",
    "sg:city":"S Gravenhage",
    "sg:orig_category":"Autoschade- Herstelbedrijven",
    "sg:phone":"+31 70 325 5779",
    "sg:postcode":"2551 LT",
    "sg:province":"South Holland",
    "wof:name":"Car Restyle",
    "wof:placetype":"venue"
},
  "geometry": {"coordinates":[4.23775,52.058601],"type":"Point"}
}