{
  "type": "Feature",
  "properties": {
    "addr:full":"Oranjelaan 18 Ermelo Gelderland 3851 RK",
    "addr:housenumber":"18",
    "addr:postcode":"3851 rk",
    "addr:street":"Oranjelaan;Gelderland",
    "iso:country":"NL",
    "sg:address":"Oranjelaan 18",
    "sg:city":"Ermelo",
    "sg:orig_category":"Werving And Selectie Van Vast Personeel",
    "sg:phone":"+31 341 563 930",
    "sg:postcode":"3851 RK",
    "sg:province":"Gelderland",
    "wof:name":"Bureau Baars",
    "wof:placetype":"venue"
},
  "geometry": {"coordinates":[5.6257171631,52.3121604919],"type":"Point"}
}