{
  "type": "Feature",
  "properties": {
    "addr:full":"Kruysenstr 18 Gilze Noord-Brabant 5126 GM",
    "addr:housenumber":"18",
    "addr:postcode":"5126 gm",
    "addr:street":"Kruysenstr",
    "iso:country":"NL",
    "sg:address":"Kruysenstr 18",
    "sg:city":"Gilze",
    "sg:orig_category":"Verzekeringen - Verzekeringskantoren",
    "sg:phone":"+31 161 226 302",
    "sg:postcode":"5126 GM",
    "sg:province":"Noord-Brabant",
    "wof:name":"Eekhout",
    "wof:placetype":"venue"
},
  "geometry": {"coordinates":[4.935379,51.541492],"type":"Point"}
}