{
  "type": "Feature",
  "properties": {
    "addr:full":"Broodmarkt 5 Hulst Zeeland 4561 CC",
    "addr:housenumber":"5",
    "addr:postcode":"4561 cc",
    "addr:street":"Broodmarkt",
    "iso:country":"NL",
    "sg:address":"Broodmarkt 5",
    "sg:city":"Hulst",
    "sg:orig_category":"Honden- En Kattentrimsalons",
    "sg:phone":"+31 114 310 810",
    "sg:postcode":"4561 CC",
    "sg:province":"Zeeland",
    "wof:name":"Kristel",
    "wof:placetype":"venue"
},
  "geometry": {"coordinates":[4.053377,51.281593],"type":"Point"}
}