{
  "type": "Feature",
  "properties": {
    "iso:country":"NL",
    "sg:address":"Industrieweg 37",
    "sg:city":"Zoeterwoude",
    "sg:orig_category":"Autokeuringen",
    "sg:phone":"+31 71 541 0452",
    "sg:postcode":"2382 NS",
    "sg:province":"Zuid-Holland",
    "wof:name":"M. Boer",
    "wof:placetype":"venue"
},
  "geometry": {"coordinates":[4.528392,52.13765],"type":"Point"}
}