{
  "type": "Feature",
  "properties": {
    "iso:country":"NL",
    "sg:address":"Eimeren 103",
    "sg:city":"'S Hertogenbosch",
    "sg:classifiers":[
        {
            "category":"Communications",
            "subcategory":"Television Station",
            "type":"Services"
        }
    ],
    "sg:phone":"+31 73 642 7433",
    "sg:postcode":"5235 DS",
    "sg:province":"Noord-Brabant",
    "sg:tags":[
        "video",
        "audio",
        "verhuur"
    ],
    "wof:name":"Video Hollywood Bv",
    "wof:placetype":"venue"
},
  "geometry": {"coordinates":[5.310937,51.727097],"type":"Point"}
}