{
  "type": "Feature",
  "properties": {
    "iso:country":"NL",
    "sg:address":"De Biezen 29",
    "sg:city":"Papendrecht",
    "sg:orig_category":"Mobiele- En Autotelefoons",
    "sg:phone":"+31 78 644 1888",
    "sg:postcode":"3355 ER",
    "sg:province":"Zuid-Holland",
    "sg:website":"http://www.westrade.nl",
    "wof:name":"Westrade Bv",
    "wof:placetype":"venue"
},
  "geometry": {"coordinates":[4.700054,51.84166],"type":"Point"}
}