{
  "type": "Feature",
  "properties": {
    "addr:full":"Postbus 274 Wijchen Gelderland 6600 AG",
    "addr:housenumber":"274",
    "addr:postcode":"6600",
    "addr:street":"Postbus;Gelderland",
    "iso:country":"NL",
    "sg:address":"Postbus 274",
    "sg:city":"Wijchen",
    "sg:orig_category":"Wasserettes, Stomerijen And Reiniging",
    "sg:phone":"+31 24 642 3228",
    "sg:postcode":"6600 AG",
    "sg:province":"Gelderland",
    "wof:name":"Chemdry",
    "wof:placetype":"venue"
},
  "geometry": {"coordinates":[5.7308502197,51.8083953857],"type":"Point"}
}