{
  "type": "Feature",
  "properties": {
    "addr:full":"Kalorama 27 Hoofddorp Noord-Holland 2132 RA",
    "addr:housenumber":"27",
    "addr:postcode":"2132 ra",
    "addr:street":"Kalorama",
    "iso:country":"NL",
    "sg:address":"Kalorama 27",
    "sg:city":"Hoofddorp",
    "sg:orig_category":"Boekenuitgeverijen",
    "sg:phone":"+31 23 561 5213",
    "sg:postcode":"2132 RA",
    "sg:province":"Noord-Holland",
    "wof:name":"Helgo Bv",
    "wof:placetype":"venue"
},
  "geometry": {"coordinates":[4.707467,52.299988],"type":"Point"}
}