{
  "type": "Feature",
  "properties": {
    "addr:full":"Nutsln 18 Mydrecht Utrecht 3641 RJ",
    "addr:housenumber":"18;3641",
    "addr:postcode":"rj",
    "addr:street":"Nutsln",
    "iso:country":"NL",
    "sg:address":"Nutsln 18",
    "sg:city":"Mydrecht",
    "sg:orig_category":"Waterbouwkundige Werken",
    "sg:phone":"+31 297 284 149",
    "sg:postcode":"3641 RJ",
    "sg:province":"Utrecht",
    "wof:name":"Verbruggen & Zn, Krijn",
    "wof:placetype":"venue"
},
  "geometry": {"coordinates":[4.8617801666,52.2057800293],"type":"Point"}
}