{
  "type": "Feature",
  "properties": {
    "addr:full":"Neptunus 71 Wyk By Duurstede Utrecht 3962 KX",
    "addr:housenumber":"71",
    "addr:postcode":"3962 kx",
    "addr:street":"Neptunus;Duurstede",
    "iso:country":"NL",
    "sg:address":"Neptunus 71",
    "sg:city":"Wyk By Duurstede",
    "sg:orig_category":"Journalisten Freelance",
    "sg:phone":"+31 343 578 278",
    "sg:postcode":"3962 KX",
    "sg:province":"Utrecht",
    "wof:name":"Dekker-Klinkenberg, M",
    "wof:placetype":"venue"
},
  "geometry": {"coordinates":[5.330832,51.981915],"type":"Point"}
}