{
  "type": "Feature",
  "properties": {
    "addr:full":"Dr De Quaywg 101 Elsendorp Noord-Brabant 5424 SP",
    "addr:housenumber":"101",
    "addr:postcode":"5424 sp",
    "addr:street":"Dr",
    "iso:country":"NL",
    "sg:address":"Dr De Quaywg 101",
    "sg:city":"Elsendorp",
    "sg:orig_category":"Sportaccommodaties - Aanleg En Onderhoud",
    "sg:phone":"+31 492 319 254",
    "sg:postcode":"5424 SP",
    "sg:province":"Noord-Brabant",
    "wof:name":"Elco",
    "wof:placetype":"venue"
},
  "geometry": {"coordinates":[5.77816,51.55563],"type":"Point"}
}