{
  "type": "Feature",
  "properties": {
    "addr:full":"Achtergr 17 Amsterdam North Holland 1017 WL",
    "addr:housenumber":"17",
    "addr:postcode":"1017 wl",
    "addr:street":"Achtergr",
    "iso:country":"NL",
    "sg:address":"Achtergr 17",
    "sg:city":"Amsterdam",
    "sg:orig_category":"Webdesign Bureaus",
    "sg:phone":"+31 20 620 9103",
    "sg:postcode":"1017 WL",
    "sg:province":"North Holland",
    "sg:website":"http://www.F27.nl",
    "wof:name":"F27",
    "wof:placetype":"venue"
},
  "geometry": {"coordinates":[4.9013018608,52.3615531921],"type":"Point"}
}