{
  "type": "Feature",
  "properties": {
    "iso:country":"NL",
    "sg:address":"Dillehof 73",
    "sg:city":"Oosterhout Nb",
    "sg:classifiers":[
        {
            "category":"Education",
            "subcategory":"School",
            "type":"Public Place"
        }
    ],
    "sg:phone":"+31 162 458 000",
    "sg:postcode":"4907 BG",
    "sg:province":"North Brabant",
    "sg:tags":[
        "studiebegeleiding",
        "en",
        "school-"
    ],
    "sg:website":"http://www.obdbreda.nl",
    "wof:name":"Obd Breda",
    "wof:placetype":"venue"
},
  "geometry": {"coordinates":[4.872346,51.654778],"type":"Point"}
}