{
  "type": "Feature",
  "properties": {
    "addr:full":"J A Wincklerhof 13 Kortenhoef North Holland 1241 CC",
    "addr:housenumber":"13",
    "addr:postcode":"1241 cc",
    "addr:street":"J A Wincklerhof",
    "iso:country":"NL",
    "sg:address":"J A Wincklerhof 13",
    "sg:city":"Kortenhoef",
    "sg:orig_category":"Administratie- En Boekhoudkantoren",
    "sg:phone":"+31 35 656 2647",
    "sg:postcode":"1241 CC",
    "sg:province":"North Holland",
    "wof:name":"Beek, Van",
    "wof:placetype":"venue"
},
  "geometry": {"coordinates":[5.12022,52.240768],"type":"Point"}
}