{
  "type": "Feature",
  "properties": {
    "addr:full":"Huizerweg 46 Bussum Noord-Holland 1402  A",
    "addr:housenumber":"46;1402 a",
    "addr:street":"Huizerweg",
    "iso:country":"NL",
    "sg:address":"Huizerweg 46",
    "sg:city":"Bussum",
    "sg:orig_category":"Bloemen And Planten",
    "sg:phone":"+31 35 693 2963",
    "sg:postcode":"1402  A",
    "sg:province":"Noord-Holland",
    "wof:name":"Bloembinderij Lavendel",
    "wof:placetype":"venue"
},
  "geometry": {"coordinates":[5.170241,52.27425],"type":"Point"}
}