{
  "type": "Feature",
  "properties": {
    "addr:full":"Marktln 6-26 Hoofddorp North Holland 2132 DM",
    "addr:housenumber":"6-26",
    "addr:postcode":"2132 dm",
    "iso:country":"NL",
    "sg:address":"Marktln 6-26",
    "sg:city":"Hoofddorp",
    "sg:orig_category":"Opticiens",
    "sg:phone":"+31 23 561 6847",
    "sg:postcode":"2132 DM",
    "sg:province":"North Holland",
    "sg:website":"http://www.oostman.nl",
    "wof:name":"Oostman Optiek Bv",
    "wof:placetype":"venue"
},
  "geometry": {"coordinates":[4.6929597855,52.305393219],"type":"Point"}
}