{
  "type": "Feature",
  "properties": {
    "addr:full":"Lange Haven 129 Schiedam South Holland 3111 CD",
    "addr:housenumber":"129",
    "addr:postcode":"3111 cd",
    "addr:street":"Lange Haven",
    "iso:country":"NL",
    "sg:address":"Lange Haven 129",
    "sg:city":"Schiedam",
    "sg:orig_category":"Overheidsdiensten",
    "sg:phone":"+31 10 426 4057",
    "sg:postcode":"3111 CD",
    "sg:province":"South Holland",
    "wof:name":"Cjv",
    "wof:placetype":"venue"
},
  "geometry": {"coordinates":[4.3970069885,51.9173049927],"type":"Point"}
}