{
  "type": "Feature",
  "properties": {
    "addr:full":"Nyverheidsstr 1 Sittard Limburg 6135 KJ",
    "addr:housenumber":"1",
    "addr:postcode":"6135 kj",
    "addr:street":"Nyverheidsstr",
    "iso:country":"NL",
    "sg:address":"Nyverheidsstr 1",
    "sg:city":"Sittard",
    "sg:orig_category":"Pneumatische Gereedschappen",
    "sg:phone":"+31 46 458 2299",
    "sg:postcode":"6135 KJ",
    "sg:province":"Limburg",
    "wof:name":"Rodac Int Bv",
    "wof:placetype":"venue"
},
  "geometry": {"coordinates":[5.842079,50.998772],"type":"Point"}
}