{
  "type": "Feature",
  "properties": {
    "addr:full":"Zandbergwg 131 Breda Noord-Brabant 4818 LK",
    "addr:housenumber":"131",
    "addr:postcode":"4818 lk",
    "iso:country":"NL",
    "sg:address":"Zandbergwg 131",
    "sg:city":"Breda",
    "sg:orig_category":"Wasserijen",
    "sg:phone":"+31 76 521 6797",
    "sg:postcode":"4818 LK",
    "sg:province":"Noord-Brabant",
    "wof:name":"Superwas",
    "wof:placetype":"venue"
},
  "geometry": {"coordinates":[4.7803688049,51.5745582581],"type":"Point"}
}