{
  "type": "Feature",
  "properties": {
    "addr:full":"St Antoniusbank 32 Bemelen Limburg 6268 NP",
    "addr:housenumber":"32",
    "addr:postcode":"6268 np",
    "addr:street":"St Antoniusbank",
    "iso:country":"NL",
    "sg:address":"St Antoniusbank 32",
    "sg:city":"Bemelen",
    "sg:orig_category":"Orthopedagogen",
    "sg:phone":"+31 43 407 3505",
    "sg:postcode":"6268 NP",
    "sg:province":"Limburg",
    "wof:name":"Steunpunt Integratie En Ontwikkeling",
    "wof:placetype":"venue"
},
  "geometry": {"coordinates":[5.763586998,50.8436965942],"type":"Point"}
}