{
  "type": "Feature",
  "properties": {
    "addr:full":"Buurtweg 11 Ermelo Gelderland 3852 PA",
    "addr:housenumber":"11",
    "addr:postcode":"3852",
    "addr:street":"Buurtweg;Gelderland",
    "iso:country":"NL",
    "sg:address":"Buurtweg 11",
    "sg:city":"Ermelo",
    "sg:orig_category":"Metaalwerken",
    "sg:phone":"+31 577 407 634",
    "sg:postcode":"3852 PA",
    "sg:province":"Gelderland",
    "wof:name":"Montagebedrijf B.S.B.",
    "wof:placetype":"venue"
},
  "geometry": {"coordinates":[5.711882,52.268242],"type":"Point"}
}