{
  "type": "Feature",
  "properties": {
    "addr:full":"Duivenkamp 708 Maarssen Utrecht 3607 VC",
    "addr:housenumber":"708",
    "addr:postcode":"3607 vc",
    "addr:street":"Duivenkamp",
    "iso:country":"NL",
    "sg:address":"Duivenkamp 708",
    "sg:city":"Maarssen",
    "sg:orig_category":"Adviesbureaus Bedrijfsorganisatie",
    "sg:phone":"+31 346 551 741",
    "sg:postcode":"3607 VC",
    "sg:province":"Utrecht",
    "wof:name":"Dea",
    "wof:placetype":"venue"
},
  "geometry": {"coordinates":[5.024081,52.132732],"type":"Point"}
}