{
  "type": "Feature",
  "properties": {
    "iso:country":"NL",
    "sg:address":"Steegoversloot 70",
    "sg:city":"Dordrecht",
    "sg:orig_category":"Paramedische Behandelingen",
    "sg:phone":"+31 78 613 8963",
    "sg:postcode":"3311 PR",
    "sg:province":"South Holland",
    "wof:name":"H.L. Winterswijk",
    "wof:placetype":"venue"
},
  "geometry": {"coordinates":[4.67294,51.815258],"type":"Point"}
}