{
  "type": "Feature",
  "properties": {
    "addr:full":"Steegoversloot 70 Dordrecht South Holland 3311 PR",
    "addr:housenumber":"70",
    "addr:postcode":"3311 pr",
    "addr:street":"Steegoversloot",
    "iso:country":"NL",
    "sg:address":"Steegoversloot 70",
    "sg:city":"Dordrecht",
    "sg:orig_category":"Paramedische Behandelingen",
    "sg:phone":"+31 78 613 8963",
    "sg:postcode":"3311 PR",
    "sg:province":"South Holland",
    "wof:name":"H.L. Winterswijk",
    "wof:placetype":"venue"
},
  "geometry": {"coordinates":[4.67294,51.815258],"type":"Point"}
}