{
  "type": "Feature",
  "properties": {
    "addr:full":"Langewg 17 Sluiskil Zeeland 4541 PC",
    "addr:housenumber":"17",
    "addr:postcode":"4541 pc",
    "addr:street":"Langewg",
    "iso:country":"NL",
    "sg:address":"Langewg 17",
    "sg:city":"Sluiskil",
    "sg:orig_category":"Loonbedrijven",
    "sg:phone":"+31 115 491 813",
    "sg:postcode":"4541 PC",
    "sg:province":"Zeeland",
    "wof:name":"Guiljam Vof",
    "wof:placetype":"venue"
},
  "geometry": {"coordinates":[3.807504,51.290665],"type":"Point"}
}