{
  "type": "Feature",
  "properties": {
    "addr:full":"Ln V Vollenhove 3047 Zeist Utrecht 3706 AM",
    "addr:housenumber":"3047",
    "addr:postcode":"3706",
    "addr:street":"Ln;Vollenhove",
    "iso:country":"NL",
    "sg:address":"Ln V Vollenhove 3047",
    "sg:city":"Zeist",
    "sg:orig_category":"Makelaars En Adviseurs Onroerende Goederen",
    "sg:phone":"+31 30 693 1543",
    "sg:postcode":"3706 AM",
    "sg:province":"Utrecht",
    "wof:name":"Robam Cv",
    "wof:placetype":"venue"
},
  "geometry": {"coordinates":[5.24387,52.08548],"type":"Point"}
}