{
  "type": "Feature",
  "properties": {
    "addr:full":"Tolakkerwg 154 Hollandsche Rading Utrecht 3739 JT",
    "addr:housenumber":"154",
    "addr:postcode":"3739 jt",
    "addr:street":"Hollandsche",
    "iso:country":"NL",
    "sg:address":"Tolakkerwg 154",
    "sg:city":"Hollandsche Rading",
    "sg:orig_category":"Organisatiebureaus",
    "sg:phone":"+31 35 577 1734",
    "sg:postcode":"3739 JT",
    "sg:province":"Utrecht",
    "wof:name":"Pafort Bv",
    "wof:placetype":"venue"
},
  "geometry": {"coordinates":[5.1732358932,52.1721572876],"type":"Point"}
}