{
  "type": "Feature",
  "properties": {
    "addr:full":"Ligusterstr 19 Echt Limburg 6101 MD",
    "addr:housenumber":"19",
    "addr:postcode":"6101",
    "addr:street":"Ligusterstr",
    "iso:country":"NL",
    "sg:address":"Ligusterstr 19",
    "sg:city":"Echt",
    "sg:orig_category":"Kappers",
    "sg:phone":"+31 475 486 929",
    "sg:postcode":"6101 MD",
    "sg:province":"Limburg",
    "wof:name":"Miss Men",
    "wof:placetype":"venue"
},
  "geometry": {"coordinates":[28.8797,46.1231],"type":"Point"}
}