{
  "type": "Feature",
  "properties": {
    "iso:country":"NL",
    "sg:address":"Akkerwg 1",
    "sg:city":"Wintelre",
    "sg:orig_category":"Verenigingsgebouwen",
    "sg:phone":"+31 40 205 1444",
    "sg:postcode":"5513 AR",
    "sg:province":"Noord-Brabant",
    "wof:name":"Rosdoek, De",
    "wof:placetype":"venue"
},
  "geometry": {"coordinates":[-68.74018100000001,-32.959919],"type":"Point"}
}