{
  "type": "Feature",
  "properties": {
    "addr:full":"Markt 2A Bredevoort Gelderland 7126 AZ",
    "addr:housenumber":"2a",
    "addr:postcode":"7126",
    "addr:street":"Markt;Gelderland",
    "iso:country":"NL",
    "sg:address":"Markt 2A",
    "sg:city":"Bredevoort",
    "sg:orig_category":"Verenigingsgebouwen",
    "sg:phone":"+31 543 451 553",
    "sg:postcode":"7126 AZ",
    "sg:province":"Gelderland",
    "wof:name":"Jongerencentr 'T Centrum, Sticht",
    "wof:placetype":"venue"
},
  "geometry": {"coordinates":[6.617507,51.943542],"type":"Point"}
}