{
  "type": "Feature",
  "properties": {
    "addr:full":"Weijerbeemd 2 Weert Limburg 6004 MC",
    "addr:housenumber":"2",
    "addr:postcode":"6004 mc",
    "addr:street":"Weijerbeemd",
    "iso:country":"NL",
    "sg:address":"Weijerbeemd 2",
    "sg:city":"Weert",
    "sg:orig_category":"Metaalafval, Schrootrecycling And Sloperijen",
    "sg:phone":"+31 495 542 674",
    "sg:postcode":"6004 MC",
    "sg:province":"Limburg",
    "wof:name":"D.T. Pruymboom Oud Ijzer- En Sloopwagenhandel",
    "wof:placetype":"venue"
},
  "geometry": {"coordinates":[5.739955,51.248291],"type":"Point"}
}