{
  "type": "Feature",
  "properties": {
    "addr:full":"Steenwykln 322 S Gravenhage South Holland 2541 RT",
    "addr:housenumber":"322",
    "addr:postcode":"2541 rt",
    "addr:street":"S Gravenhage",
    "iso:country":"NL",
    "sg:address":"Steenwykln 322",
    "sg:city":"S Gravenhage",
    "sg:orig_category":"Onderhoudswerken",
    "sg:phone":"+31 70 366 6151",
    "sg:postcode":"2541 RT",
    "sg:province":"South Holland",
    "wof:name":"Doorn, J M Van",
    "wof:placetype":"venue"
},
  "geometry": {"coordinates":[4.28115,52.04451],"type":"Point"}
}