{
  "type": "Feature",
  "properties": {
    "iso:country":"NL",
    "sg:address":"Mercuriusstraat 8",
    "sg:city":"Hardinxveld Giessend",
    "sg:orig_category":"Fysiotherapeuten",
    "sg:phone":"+31 184 670 969",
    "sg:postcode":"3371 TG",
    "sg:province":"Zuid-Holland",
    "wof:name":"Peter Brandwijk",
    "wof:placetype":"venue"
},
  "geometry": {"coordinates":[4.822161,51.822693],"type":"Point"}
}