{
  "type": "Feature",
  "properties": {
    "addr:full":"Scottstr 12 Rotterdam Zuid-Holland 3076 GZ",
    "addr:housenumber":"12",
    "addr:postcode":"3076 gz",
    "addr:street":"Scottstr",
    "iso:country":"NL",
    "sg:address":"Scottstr 12",
    "sg:city":"Rotterdam",
    "sg:orig_category":"Scheepsmotoren - Reparatie",
    "sg:phone":"+31 10 419 4510",
    "sg:postcode":"3076 GZ",
    "sg:province":"Zuid-Holland",
    "wof:name":"Manen, Van",
    "wof:placetype":"venue"
},
  "geometry": {"coordinates":[4.514239,51.874504],"type":"Point"}
}