{
  "type": "Feature",
  "properties": {
    "addr:full":"C V Sandeln 11 Odyk Utrecht 3984 KV",
    "addr:housenumber":"11",
    "addr:street":"V Sandeln",
    "iso:country":"NL",
    "sg:address":"C V Sandeln 11",
    "sg:city":"Odyk",
    "sg:orig_category":"Administratie- En Boekhoudkantoren",
    "sg:phone":"+31 30 656 4203",
    "sg:postcode":"3984 KV",
    "sg:province":"Utrecht",
    "wof:name":"Hupkes, L",
    "wof:placetype":"venue"
},
  "geometry": {"coordinates":[5.23238,52.050835],"type":"Point"}
}