{
  "type": "Feature",
  "properties": {
    "addr:full":"Pickepln 1 Noordwyk Zh Zuid-Holland 2202 CK",
    "addr:housenumber":"1",
    "addr:postcode":"2202 ck",
    "addr:street":"Pickepln",
    "iso:country":"NL",
    "sg:address":"Pickepln 1",
    "sg:city":"Noordwyk Zh",
    "sg:orig_category":"Verenigingen En Stichtingen",
    "sg:phone":"+31 71 361 8671",
    "sg:postcode":"2202 CK",
    "sg:province":"Zuid-Holland",
    "wof:name":"Ark, Sticht De",
    "wof:placetype":"venue"
},
  "geometry": {"coordinates":[4.43223,52.240868],"type":"Point"}
}