{
  "type": "Feature",
  "properties": {
    "addr:full":"Industrieweg 9 Oostburg Zeeland 4501 PM",
    "addr:housenumber":"9",
    "addr:postcode":"4501 pm",
    "addr:street":"Industrieweg",
    "iso:country":"NL",
    "sg:address":"Industrieweg 9",
    "sg:city":"Oostburg",
    "sg:orig_category":"Mobiele Service Aan Motorvoertuigen",
    "sg:phone":"+31 117 452 608",
    "sg:postcode":"4501 PM",
    "sg:province":"Zeeland",
    "wof:name":"C. Schout En Zn",
    "wof:placetype":"venue"
},
  "geometry": {"coordinates":[3.497408,51.331783],"type":"Point"}
}