{
  "type": "Feature",
  "properties": {
    "iso:country":"NL",
    "sg:address":"Van Hogendorplaan 95 A",
    "sg:city":"Vlaardingen",
    "sg:orig_category":"Boekenuitgeverijen",
    "sg:phone":"+31 10 247 0293",
    "sg:postcode":"3135  B",
    "sg:province":"Zuid-Holland",
    "wof:name":"Bruna",
    "wof:placetype":"venue"
},
  "geometry": {"coordinates":[4.359605,51.916115],"type":"Point"}
}