{
  "type": "Feature",
  "properties": {
    "addr:full":"Badhuisstraat 152 'S Gravenhage Zuid-Holland 2584 HL",
    "addr:housenumber":"152 '",
    "addr:postcode":"2584 hl",
    "addr:street":"Badhuisstraat",
    "iso:country":"NL",
    "sg:address":"Badhuisstraat 152",
    "sg:city":"'S Gravenhage",
    "sg:orig_category":"Bloemen And Planten",
    "sg:phone":"+31 70 358 4477",
    "sg:postcode":"2584 HL",
    "sg:province":"Zuid-Holland",
    "wof:name":"Bloemen-En Kadocentrum Ariba",
    "wof:placetype":"venue"
},
  "geometry": {"coordinates":[4.279339,52.104553],"type":"Point"}
}