{
  "type": "Feature",
  "properties": {
    "addr:full":"Anjelierstr 42 Almelo Overijssel 7601 BL",
    "addr:housenumber":"42",
    "addr:postcode":"7601 bl",
    "addr:street":"Anjelierstr",
    "iso:country":"NL",
    "sg:address":"Anjelierstr 42",
    "sg:city":"Almelo",
    "sg:orig_category":"Voegwerken",
    "sg:phone":"+31 6 29403373",
    "sg:postcode":"7601 BL",
    "sg:province":"Overijssel",
    "wof:name":"Tummers Voegersbedrijf",
    "wof:placetype":"venue"
},
  "geometry": {"coordinates":[6.661962,52.345028],"type":"Point"}
}