{
  "type": "Feature",
  "properties": {
    "iso:country":"NL",
    "sg:address":"W Alexanderstr 29",
    "sg:city":"Zegveld",
    "sg:orig_category":"Onderhoudswerken",
    "sg:phone":"+31 348 691 580",
    "sg:postcode":"3474 JS",
    "sg:province":"Utrecht",
    "wof:name":"Ronald De Vries",
    "wof:placetype":"venue"
},
  "geometry": {"coordinates":[4.8316,52.115719],"type":"Point"}
}