{
  "type": "Feature",
  "properties": {
    "addr:full":"Kerkstraat 44 Loon Op Zand Noord-Brabant 5175 BB",
    "addr:housenumber":"44",
    "addr:postcode":"5175 bb",
    "addr:street":"Kerkstraat",
    "iso:country":"NL",
    "sg:address":"Kerkstraat 44",
    "sg:city":"Loon Op Zand",
    "sg:orig_category":"Fietshandelaren",
    "sg:phone":"+31 416 361 322",
    "sg:postcode":"5175 BB",
    "sg:province":"Noord-Brabant",
    "wof:name":"Rekreatief",
    "wof:placetype":"venue"
},
  "geometry": {"coordinates":[5.076348,51.627399],"type":"Point"}
}