{
  "type": "Feature",
  "properties": {
    "addr:full":"Postbus 1995 Rotterdam 3000 BZ",
    "addr:housenumber":"1995",
    "addr:postcode":"3000 bz",
    "addr:street":"Postbus",
    "iso:country":"NL",
    "sg:address":"Postbus 1995",
    "sg:city":"Rotterdam",
    "sg:orig_category":"Verenigingen En Stichtingen",
    "sg:phone":"+31 10 412 7828",
    "sg:postcode":"3000 BZ",
    "wof:name":"Skar Sticht Kunstaccommodatie Rotterdam",
    "wof:placetype":"venue"
},
  "geometry": {"coordinates":[4.47075,51.922619],"type":"Point"}
}