{
  "type": "Feature",
  "properties": {
    "addr:full":"Didamsestr 19 Zevenaar Gelderland 6901 HB",
    "addr:housenumber":"19",
    "addr:postcode":"6901 hb",
    "addr:street":"Didamsestr",
    "iso:country":"NL",
    "sg:address":"Didamsestr 19",
    "sg:city":"Zevenaar",
    "sg:orig_category":"Bloemen En Planten",
    "sg:phone":"+31 316 344 600",
    "sg:postcode":"6901 HB",
    "sg:province":"Gelderland",
    "wof:name":"Remmelien Vof",
    "wof:placetype":"venue"
},
  "geometry": {"coordinates":[6.077783,51.928181],"type":"Point"}
}