{
  "type": "Feature",
  "properties": {
    "addr:full":"Zeevangstr 3 Purmerend North Holland 1441 WZ",
    "addr:housenumber":"3",
    "addr:postcode":"1441 wz",
    "addr:street":"Zeevangstr",
    "iso:country":"NL",
    "sg:address":"Zeevangstr 3",
    "sg:city":"Purmerend",
    "sg:orig_category":"Werving En Selectie",
    "sg:phone":"+31 299 473 998",
    "sg:postcode":"1441 WZ",
    "sg:province":"North Holland",
    "sg:website":"http://www.avotek.nl/jenj",
    "wof:name":"J En J Bv",
    "wof:placetype":"venue"
},
  "geometry": {"coordinates":[4.9588828087,52.5050392151],"type":"Point"}
}