{
  "type": "Feature",
  "properties": {
    "addr:full":"Bergse Dorpsstraat 71 Rotterdam Zuid-Holland 3054 GB",
    "addr:housenumber":"71",
    "addr:postcode":"3054 gb",
    "addr:street":"Bergse Dorpsstraat",
    "iso:country":"NL",
    "sg:address":"Bergse Dorpsstraat 71",
    "sg:city":"Rotterdam",
    "sg:orig_category":"Herenmodezaken",
    "sg:phone":"+31 10 461 2639",
    "sg:postcode":"3054 GB",
    "sg:province":"Zuid-Holland",
    "wof:name":"Quattro Company Bv",
    "wof:placetype":"venue"
},
  "geometry": {"coordinates":[4.494609,51.956944],"type":"Point"}
}