{
  "type": "Feature",
  "properties": {
    "addr:full":"Anklaarsewg 334E Apeldoorn Gelderland 7317 AS",
    "addr:housenumber":"334e",
    "addr:postcode":"7317 as",
    "addr:street":"Anklaarsewg;Gelderland",
    "iso:country":"NL",
    "sg:address":"Anklaarsewg 334E",
    "sg:city":"Apeldoorn",
    "sg:orig_category":"Verf En Lak - Fabrieken En Groothandel",
    "sg:phone":"+31 55 579 0995",
    "sg:postcode":"7317 AS",
    "sg:province":"Gelderland",
    "wof:name":"Eijkelkamp Bv, H H",
    "wof:placetype":"venue"
},
  "geometry": {"coordinates":[5.974902,52.235062],"type":"Point"}
}