{
  "type": "Feature",
  "properties": {
    "addr:full":"Warmeerweg 137 Emmen Drenthe 7815 HD",
    "addr:housenumber":"137",
    "addr:postcode":"7815 hd",
    "addr:street":"Warmeerweg",
    "iso:country":"NL",
    "sg:address":"Warmeerweg 137",
    "sg:city":"Emmen",
    "sg:classifiers":[
        {
            "category":"Food & Beverages",
            "subcategory":"Fruits & Vegetables",
            "type":"Retail Goods"
        }
    ],
    "sg:phone":"+31 591 643 563",
    "sg:postcode":"7815 HD",
    "sg:province":"Drenthe",
    "sg:tags":[
        "groenten"
    ],
    "wof:name":"Fa. Kleefman",
    "wof:placetype":"venue"
},
  "geometry": {"coordinates":[6.89456,52.802784],"type":"Point"}
}