{
  "type": "Feature",
  "properties": {
    "addr:full":"Lynbaan 56 Rotterdam Zuid-Holland 3012 EP",
    "addr:housenumber":"56",
    "addr:postcode":"3012 ep",
    "addr:street":"Lynbaan",
    "iso:country":"NL",
    "sg:address":"Lynbaan 56",
    "sg:city":"Rotterdam",
    "sg:orig_category":"Kappers",
    "sg:phone":"+31 10 413 1653",
    "sg:postcode":"3012 EP",
    "sg:province":"Zuid-Holland",
    "sg:website":"http://www.mario-s.nl",
    "wof:name":"Mario",
    "wof:placetype":"venue"
},
  "geometry": {"coordinates":[4.478455,51.922836],"type":"Point"}
}