{
  "type": "Feature",
  "properties": {
    "addr:full":"De Hofstee 14 Weesp North Holland 1383 BX",
    "addr:housenumber":"14",
    "addr:postcode":"1383 bx",
    "addr:street":"De Hofstee",
    "iso:country":"NL",
    "sg:address":"De Hofstee 14",
    "sg:city":"Weesp",
    "sg:orig_category":"Adviesbureaus Bouwkunde",
    "sg:phone":"+31 6 51636068",
    "sg:postcode":"1383 BX",
    "sg:province":"North Holland",
    "wof:name":"Perlee Bouwbegeleiding",
    "wof:placetype":"venue"
},
  "geometry": {"coordinates":[5.04206,52.300392],"type":"Point"}
}