{
  "type": "Feature",
  "properties": {
    "addr:full":"Vockerswg 6 Hengelo Ov NL.08 7554 RK",
    "addr:housenumber":"6",
    "addr:postcode":"7554 rk",
    "addr:street":"Vockerswg;Ov",
    "iso:country":"NL",
    "sg:address":"Vockerswg 6",
    "sg:city":"Hengelo Ov",
    "sg:orig_category":"Kunststof Ramen",
    "sg:phone":"+31 74 242 5252",
    "sg:postcode":"7554 RK",
    "sg:province":"NL.08",
    "wof:name":"Contiplan",
    "wof:placetype":"venue"
},
  "geometry": {"coordinates":[6.756812,52.250378],"type":"Point"}
}