{
  "type": "Feature",
  "properties": {
    "addr:full":"Hollandiastraat 46 Scharsterbrug Friesland 8517 HG",
    "addr:housenumber":"46",
    "addr:postcode":"8517 hg",
    "addr:street":"Hollandiastraat",
    "iso:country":"NL",
    "sg:address":"Hollandiastraat 46",
    "sg:city":"Scharsterbrug",
    "sg:orig_category":"Loodgieterswerk, Verwarming And Sanitaire Installaties",
    "sg:phone":"+31 513 416 882",
    "sg:postcode":"8517 HG",
    "sg:province":"Friesland",
    "wof:name":"Tijs Klussenbedrijf",
    "wof:placetype":"venue"
},
  "geometry": {"coordinates":[5.779771,52.945065],"type":"Point"}
}