{
  "type": "Feature",
  "properties": {
    "addr:full":"Postbus 451 Nijmegen Gelderland 6500 AL",
    "addr:housenumber":"451",
    "addr:postcode":"6500",
    "addr:street":"Postbus;Gelderland",
    "iso:country":"NL",
    "sg:address":"Postbus 451",
    "sg:city":"Nijmegen",
    "sg:classifiers":[
        {
            "category":"Professional",
            "subcategory":"Accounting & Tax Preparation",
            "type":"Services"
        }
    ],
    "sg:phone":"+31 24 372 5400",
    "sg:postcode":"6500 AL",
    "sg:province":"Gelderland",
    "sg:tags":[
        "accountant"
    ],
    "wof:name":"De Zeeuw & De Keizer Acc & Belastingadv.",
    "wof:placetype":"venue"
},
  "geometry": {"coordinates":[5.85759,51.841202],"type":"Point"}
}