{
  "type": "Feature",
  "properties": {
    "iso:country":"NL",
    "sg:address":"Veemkade 1092",
    "sg:city":"Amsterdam",
    "sg:orig_category":"Marktonderzoekbureaus",
    "sg:phone":"+31 20 419 2972",
    "sg:postcode":"1019 BX",
    "sg:province":"North Holland",
    "wof:name":"Eijlingen Travel Engineering Services",
    "wof:placetype":"venue"
},
  "geometry": {"coordinates":[4.933109,52.375],"type":"Point"}
}