{
  "type": "Feature",
  "properties": {
    "iso:country":"NL",
    "sg:address":"Dreef 1",
    "sg:city":"Lamswaarde",
    "sg:orig_category":"Fietshandelaren",
    "sg:phone":"+31 114 690 262",
    "sg:postcode":"4586 AL",
    "sg:province":"Zeeland",
    "wof:name":"Th. Kindt En Zonen",
    "wof:placetype":"venue"
},
  "geometry": {"coordinates":[4.054944,51.34306],"type":"Point"}
}