{
  "type": "Feature",
  "properties": {
    "iso:country":"NL",
    "sg:address":"Dubbelmonde 53",
    "sg:city":"Zevenbergen",
    "sg:orig_category":"Schilders",
    "sg:phone":"+31 168 325 632",
    "sg:postcode":"4761 NP",
    "sg:province":"North Brabant",
    "wof:name":"Afwerkingsbedrijf West Brabant",
    "wof:placetype":"venue"
},
  "geometry": {"coordinates":[4.59319,51.643864],"type":"Point"}
}