{
  "type": "Feature",
  "properties": {
    "addr:full":"Liedeweg 63 Haarlemmerliede Noord-Holland 2065 AL",
    "addr:housenumber":"63",
    "addr:postcode":"2065 al",
    "addr:street":"Liedeweg",
    "iso:country":"NL",
    "sg:address":"Liedeweg 63",
    "sg:city":"Haarlemmerliede",
    "sg:orig_category":"Kappers",
    "sg:phone":"+31 23 532 6839",
    "sg:postcode":"2065 AL",
    "sg:province":"Noord-Holland",
    "wof:name":"Kapsalon Marijke",
    "wof:placetype":"venue"
},
  "geometry": {"coordinates":[4.6872010231,52.3889465332],"type":"Point"}
}