{
  "type": "Feature",
  "properties": {
    "addr:full":"Energieweg 16 Harmelen Utrecht 3481 MC",
    "addr:housenumber":"16",
    "addr:postcode":"3481 mc",
    "addr:street":"Energieweg",
    "iso:country":"NL",
    "sg:address":"Energieweg 16",
    "sg:city":"Harmelen",
    "sg:orig_category":"Wegen And Sportterreinen",
    "sg:phone":"+31 348 441 895",
    "sg:postcode":"3481 MC",
    "sg:province":"Utrecht",
    "wof:name":"Gebroeders Van Leeuwen Harmelen Bv",
    "wof:placetype":"venue"
},
  "geometry": {"coordinates":[4.9460721016,52.0993232727],"type":"Point"}
}