{
  "type": "Feature",
  "properties": {
    "addr:full":"Roolvinkpark 6 Ede Gld Gelderland 6716 EG",
    "addr:housenumber":"6",
    "addr:postcode":"6716 eg",
    "addr:street":"Roolvinkpark;Gld Gelderland",
    "iso:country":"NL",
    "sg:address":"Roolvinkpark 6",
    "sg:city":"Ede Gld",
    "sg:orig_category":"Juridische Dienstverlening",
    "sg:phone":"+31 318 625 376",
    "sg:postcode":"6716 EG",
    "sg:province":"Gelderland",
    "wof:name":"Adviesburo Burgers",
    "wof:placetype":"venue"
},
  "geometry": {"coordinates":[5.640053,52.024479],"type":"Point"}
}