{
  "type": "Feature",
  "properties": {
    "addr:full":"Viaductweg 100 Maastricht Limburg 6222 AB",
    "addr:housenumber":"100",
    "addr:postcode":"6222 ab",
    "addr:street":"Viaductweg",
    "iso:country":"NL",
    "sg:address":"Viaductweg 100",
    "sg:city":"Maastricht",
    "sg:orig_category":"Benzinestations And Brandstoffen",
    "sg:phone":"+31 43 363 1427",
    "sg:postcode":"6222 AB",
    "sg:province":"Limburg",
    "wof:name":"Esso",
    "wof:placetype":"venue"
},
  "geometry": {"coordinates":[5.705399,50.860836],"type":"Point"}
}