{
  "type": "Feature",
  "properties": {
    "addr:full":"Singelwg 5 Kerkrade Limburg 6467 CE",
    "addr:housenumber":"5",
    "addr:postcode":"6467 ce",
    "addr:street":"Singelwg",
    "iso:country":"NL",
    "sg:address":"Singelwg 5",
    "sg:city":"Kerkrade",
    "sg:orig_category":"Kinderopvang",
    "sg:phone":"+31 45 542 9654",
    "sg:postcode":"6467 CE",
    "sg:province":"Limburg",
    "wof:name":"Pinkeltje",
    "wof:placetype":"venue"
},
  "geometry": {"coordinates":[6.026219,50.866428],"type":"Point"}
}