{
  "type": "Feature",
  "properties": {
    "addr:full":"Molendijk 6 Sliedrecht Zuid-Holland 3361 EN",
    "addr:housenumber":"6",
    "addr:postcode":"3361 en",
    "addr:street":"Molendijk",
    "iso:country":"NL",
    "sg:address":"Molendijk 6",
    "sg:city":"Sliedrecht",
    "sg:orig_category":"Vloer- And Wandbedekkingen",
    "sg:phone":"+31 184 411 192",
    "sg:postcode":"3361 EN",
    "sg:province":"Zuid-Holland",
    "wof:name":"Verhey Bestratingen Bv",
    "wof:placetype":"venue"
},
  "geometry": {"coordinates":[4.764309,51.824905],"type":"Point"}
}