{
  "type": "Feature",
  "properties": {
    "addr:full":"Noordeinde 128/D Landsmeer Noord-Holland 1121 AL",
    "addr:housenumber":"128 / d",
    "addr:postcode":"1121 al",
    "addr:street":"Noordeinde",
    "iso:country":"NL",
    "sg:address":"Noordeinde 128/D",
    "sg:city":"Landsmeer",
    "sg:orig_category":"Verzekeringen - Verzekeringskantoren",
    "sg:phone":"+31 20 482 2048",
    "sg:postcode":"1121 AL",
    "sg:province":"Noord-Holland",
    "sg:website":"http://www.accesnet.nl/univehgv",
    "wof:name":"Univ\u00e9",
    "wof:placetype":"venue"
},
  "geometry": {"coordinates":[4.913653,52.436401],"type":"Point"}
}