{
  "type": "Feature",
  "properties": {
    "addr:full":"Tiendwg 10 Naaldwyk Zuid-Holland 2671 SB",
    "addr:housenumber":"10",
    "addr:postcode":"2671 sb",
    "addr:street":"Tiendwg",
    "iso:country":"NL",
    "sg:address":"Tiendwg 10",
    "sg:city":"Naaldwyk",
    "sg:orig_category":"Hypotheken",
    "sg:phone":"+31 174 620 244",
    "sg:postcode":"2671 SB",
    "sg:province":"Zuid-Holland",
    "sg:website":"http://www.naaldwijk.hypotheekshop.nl/1160",
    "wof:name":"Hypotheekshop, De",
    "wof:placetype":"venue"
},
  "geometry": {"coordinates":[4.219974,51.99102],"type":"Point"}
}