{
  "type": "Feature",
  "properties": {
    "iso:country":"NL",
    "sg:address":"Zuiderwg 40",
    "sg:city":"Groningen",
    "sg:orig_category":"Woninginrichting",
    "sg:phone":"+31 50 556 5987",
    "sg:postcode":"9745 AD",
    "sg:province":"Groningen",
    "sg:website":"http://www.tjammevis.nl",
    "wof:name":"Tjamme Vis, Woonstyle",
    "wof:placetype":"venue"
},
  "geometry": {"coordinates":[6.5021090508,53.2142715454],"type":"Point"}
}