{
  "type": "Feature",
  "properties": {
    "addr:full":"Reggestr 28 Amsterdam North Holland 1078 DA",
    "addr:housenumber":"28",
    "addr:postcode":"1078 da",
    "addr:street":"Reggestr",
    "iso:country":"NL",
    "sg:address":"Reggestr 28",
    "sg:city":"Amsterdam",
    "sg:orig_category":"Verzekeringen - Verzekeringskantoren",
    "sg:phone":"+31 20 679 7953",
    "sg:postcode":"1078 DA",
    "sg:province":"North Holland",
    "wof:name":"Feenstra",
    "wof:placetype":"venue"
},
  "geometry": {"coordinates":[4.901735,52.347183],"type":"Point"}
}