{
  "type": "Feature",
  "properties": {
    "addr:full":"Brouwersgracht 115F Amsterdam Noord-Holland 1015 GD",
    "addr:housenumber":"115f",
    "addr:postcode":"1015 gd",
    "addr:street":"Brouwersgracht",
    "iso:country":"NL",
    "sg:address":"Brouwersgracht 115F",
    "sg:city":"Amsterdam",
    "sg:orig_category":"Artsen And Specialisten",
    "sg:phone":"+31 20 639 1302",
    "sg:postcode":"1015 GD",
    "sg:province":"Noord-Holland",
    "wof:name":"H.J. Meijer",
    "wof:placetype":"venue"
},
  "geometry": {"coordinates":[4.887057,52.380882],"type":"Point"}
}