{
  "type": "Feature",
  "properties": {
    "addr:full":"Wolborgenmate 108 Doetinchem Gelderland 7006 DL",
    "addr:housenumber":"108",
    "addr:postcode":"7006 dl",
    "addr:street":"Wolborgenmate;Gelderland",
    "iso:country":"NL",
    "sg:address":"Wolborgenmate 108",
    "sg:city":"Doetinchem",
    "sg:orig_category":"Pianostemmen En -Reparatie",
    "sg:phone":"+31 314 327 464",
    "sg:postcode":"7006 DL",
    "sg:province":"Gelderland",
    "wof:name":"Tijman, F",
    "wof:placetype":"venue"
},
  "geometry": {"coordinates":[6.270288,51.960503],"type":"Point"}
}