{
  "type": "Feature",
  "properties": {
    "iso:country":"NL",
    "sg:address":"Hogeweg 88",
    "sg:city":"Burgh Haamstede",
    "sg:classifiers":[
        {
            "category":"Fast Food",
            "type":"Food & Drink"
        }
    ],
    "sg:phone":"+31 111 651 919",
    "sg:postcode":"4328 PJ",
    "sg:province":"Zeeland",
    "sg:tags":[
        "afhaal",
        "restaurant"
    ],
    "wof:name":"P Duinhouwer-Oosterling",
    "wof:placetype":"venue"
},
  "geometry": {"coordinates":[3.717751,51.680805],"type":"Point"}
}