{
  "type": "Feature",
  "properties": {
    "addr:full":"Californiepln 18 Haarlem Noord-Holland 2037 AL",
    "addr:housenumber":"18",
    "addr:postcode":"2037 al",
    "addr:street":"Californiepln",
    "iso:country":"NL",
    "sg:address":"Californiepln 18",
    "sg:city":"Haarlem",
    "sg:orig_category":"Fitnesscentra",
    "sg:phone":"+31 23 540 1144",
    "sg:postcode":"2037 AL",
    "sg:province":"Noord-Holland",
    "wof:name":"Jordan Sports",
    "wof:placetype":"venue"
},
  "geometry": {"coordinates":[4.656235,52.35738],"type":"Point"}
}