{
  "type": "Feature",
  "properties": {
    "addr:full":"Voltaweg 20 Bunschoten Spakenburg Utrecht 3752 LP",
    "addr:housenumber":"20",
    "addr:postcode":"3752 lp",
    "addr:street":"Voltaweg",
    "iso:country":"NL",
    "sg:address":"Voltaweg 20",
    "sg:city":"Bunschoten Spakenburg",
    "sg:orig_category":"Houten Verpakkingen Fab",
    "sg:phone":"+31 527 262 080",
    "sg:postcode":"3752 LP",
    "sg:province":"Utrecht",
    "wof:name":"Vof Pallethandel T. Vermeer",
    "wof:placetype":"venue"
},
  "geometry": {"coordinates":[5.359539,52.231926],"type":"Point"}
}