{
  "type": "Feature",
  "properties": {
    "addr:full":"Cuneraln 50 Rhenen Utrecht 3911 AD",
    "addr:housenumber":"50",
    "addr:postcode":"3911 ad",
    "addr:street":"Cuneraln",
    "iso:country":"NL",
    "sg:address":"Cuneraln 50",
    "sg:city":"Rhenen",
    "sg:orig_category":"Adviesbureaus",
    "sg:phone":"+31 317 614 008",
    "sg:postcode":"3911 AD",
    "sg:province":"Utrecht",
    "sg:website":"http://www.haasart.nl",
    "wof:name":"Haas Grafisch Ontwerp",
    "wof:placetype":"venue"
},
  "geometry": {"coordinates":[5.567005,51.957603],"type":"Point"}
}