{
  "type": "Feature",
  "properties": {
    "addr:full":"Woldwg 112 Kropswolde Groningen 9606 PH",
    "addr:housenumber":"112",
    "addr:postcode":"9606",
    "addr:street":"Kropswolde",
    "iso:country":"NL",
    "sg:address":"Woldwg 112",
    "sg:city":"Kropswolde",
    "sg:orig_category":"Organisatiebureaus",
    "sg:phone":"+31 598 352 122",
    "sg:postcode":"9606 PH",
    "sg:province":"Groningen",
    "wof:name":"Langeland, Winny",
    "wof:placetype":"venue"
},
  "geometry": {"coordinates":[6.7232999802,53.1521186829],"type":"Point"}
}