{
  "type": "Feature",
  "properties": {
    "iso:country":"NL",
    "sg:address":"Trasmolenln 8D",
    "sg:city":"Woerden",
    "sg:orig_category":"Biogasinstallaties",
    "sg:phone":"+31 348 408 263",
    "sg:postcode":"3447 GZ",
    "sg:province":"Utrecht",
    "wof:name":"Wise Use Int Bv",
    "wof:placetype":"venue"
},
  "geometry": {"coordinates":[4.893032,52.076687],"type":"Point"}
}