{
  "type": "Feature",
  "properties": {
    "addr:full":"De Oude Molen 2 Amstelveen Noord-Holland 1184 VW",
    "addr:housenumber":"2",
    "addr:postcode":"1184 vw",
    "addr:street":"De Oude Molen",
    "iso:country":"NL",
    "sg:address":"De Oude Molen 2",
    "sg:city":"Amstelveen",
    "sg:orig_category":"Kantoor- En Bedrijfsmeubelen",
    "sg:phone":"+31 20 517 4444",
    "sg:postcode":"1184 VW",
    "sg:province":"Noord-Holland",
    "sg:website":"http://www.vitra.com",
    "wof:name":"Vitra Nederland Bv",
    "wof:placetype":"venue"
},
  "geometry": {"coordinates":[4.8885498047,52.2937736511],"type":"Point"}
}