{
  "type": "Feature",
  "properties": {
    "addr:full":"Willem Fenengastraat 39 Amsterdam Noord-Holland 1096 BM",
    "addr:housenumber":"39",
    "addr:postcode":"1096 bm",
    "addr:street":"Willem Fenengastraat",
    "iso:country":"NL",
    "sg:address":"Willem Fenengastraat 39",
    "sg:city":"Amsterdam",
    "sg:orig_category":"Geluidsopnamen",
    "sg:phone":"+31 20 568 5411",
    "sg:postcode":"1096 BM",
    "sg:province":"Noord-Holland",
    "wof:name":"Cineco Bv",
    "wof:placetype":"venue"
},
  "geometry": {"coordinates":[4.91755,52.33226],"type":"Point"}
}