{
  "type": "Feature",
  "properties": {
    "addr:full":"Peperstraat 33 Oosterhout Gld Gelderland 6678 AL",
    "addr:housenumber":"33;6678",
    "addr:postcode":"al",
    "addr:street":"Peperstraat;Gld Gelderland",
    "iso:country":"NL",
    "sg:address":"Peperstraat 33",
    "sg:city":"Oosterhout Gld",
    "sg:orig_category":"Fotostudio'S And Fotografen",
    "sg:phone":"+31 481 482 148",
    "sg:postcode":"6678 AL",
    "sg:province":"Gelderland",
    "wof:name":"Henriette Hoffs Fotografie",
    "wof:placetype":"venue"
},
  "geometry": {"coordinates":[5.821464,51.879612],"type":"Point"}
}