{
  "type": "Feature",
  "properties": {
    "addr:full":"Meindert Vd Thijnensngl 12 Coevorden Drenthe 7741 GB",
    "addr:housenumber":"12",
    "addr:postcode":"7741 gb",
    "addr:street":"Meindert Vd Thijnensngl",
    "iso:country":"NL",
    "sg:address":"Meindert Vd Thijnensngl 12",
    "sg:city":"Coevorden",
    "sg:classifiers":[
        {
            "category":"Professional",
            "subcategory":"Accounting & Tax Preparation",
            "type":"Services"
        }
    ],
    "sg:phone":"+31 524 517 007",
    "sg:postcode":"7741 GB",
    "sg:province":"Drenthe",
    "sg:tags":[
        "accountant"
    ],
    "wof:name":"Adbeco",
    "wof:placetype":"venue"
},
  "geometry": {"coordinates":[6.742779,52.662895],"type":"Point"}
}