{
  "type": "Feature",
  "properties": {
    "iso:country":"NL",
    "sg:address":"Dross. Saldenstraat 19",
    "sg:city":"Elsloo Lb",
    "sg:orig_category":"Meubeltextiel Fab",
    "sg:phone":"+31 46 437 3161",
    "sg:postcode":"6181 ER",
    "sg:province":"BE.05",
    "wof:name":"Sales Promotion Products Wiggerman - Imp",
    "wof:placetype":"venue"
},
  "geometry": {"coordinates":[5.738695,50.960476],"type":"Point"}
}