{
  "type": "Feature",
  "properties": {
    "addr:full":"Vermeerstraat 8 'S Gravenhage Zuid-Holland 2525 VL",
    "addr:housenumber":"8 '",
    "addr:postcode":"2525 vl",
    "addr:street":"Vermeerstraat",
    "iso:country":"NL",
    "sg:address":"Vermeerstraat 8",
    "sg:city":"'S Gravenhage",
    "sg:orig_category":"Werving And Selectie Van Tijdelijk Personeel And Uitzendkantoren",
    "sg:phone":"+31 70 393 6438",
    "sg:postcode":"2525 VL",
    "sg:province":"Zuid-Holland",
    "wof:name":"Aksi",
    "wof:placetype":"venue"
},
  "geometry": {"coordinates":[4.3039660454,52.0620994568],"type":"Point"}
}