{
  "type": "Feature",
  "properties": {
    "addr:full":"Akersteenwg 16 Maastricht Limburg 6227 AA",
    "addr:housenumber":"16",
    "addr:postcode":"6227 aa",
    "addr:street":"Akersteenwg",
    "iso:country":"NL",
    "sg:address":"Akersteenwg 16",
    "sg:city":"Maastricht",
    "sg:orig_category":"Horeca-Inrichtingen En -Uitrustingen",
    "sg:phone":"+31 43 356 7900",
    "sg:postcode":"6227 AA",
    "sg:province":"Limburg",
    "sg:website":"http://www.gorissenbedrijfskeukens.nl",
    "wof:name":"Gorissen Bv",
    "wof:placetype":"venue"
},
  "geometry": {"coordinates":[5.73144,50.837471],"type":"Point"}
}