{
  "type": "Feature",
  "properties": {
    "iso:country":"NL",
    "sg:address":"Ridderhof",
    "sg:city":"Ridderkerk",
    "sg:orig_category":"Winkelcentra",
    "sg:phone":"+31 257",
    "sg:postcode":"2981 ET",
    "sg:province":"Zuid-Holland",
    "wof:name":"Ridderkerk Binnenstad",
    "wof:placetype":"venue"
},
  "geometry": {"coordinates":[4.5986552238,51.8694648743],"type":"Point"}
}