{
  "type": "Feature",
  "properties": {
    "addr:full":"Honswijkpolder 40 De Meern Utrecht 3453 NT",
    "addr:housenumber":"40",
    "addr:postcode":"3453 nt",
    "addr:street":"Honswijkpolder",
    "iso:country":"NL",
    "sg:address":"Honswijkpolder 40",
    "sg:city":"De Meern",
    "sg:orig_category":"Film-, Tv- And Videoproductie",
    "sg:phone":"+31 30 662 0010",
    "sg:postcode":"3453 NT",
    "sg:province":"Utrecht",
    "wof:name":"Jet Ned",
    "wof:placetype":"venue"
},
  "geometry": {"coordinates":[5.015512,52.085529],"type":"Point"}
}