{
  "type": "Feature",
  "properties": {
    "addr:full":"Minden 32 Apeldoorn Gelderland 7327 AW",
    "addr:housenumber":"32",
    "addr:postcode":"7327 aw",
    "addr:street":"Minden;Gelderland",
    "iso:country":"NL",
    "sg:address":"Minden 32",
    "sg:city":"Apeldoorn",
    "sg:orig_category":"Fotolaboratoria",
    "sg:phone":"+31 55 534 2477",
    "sg:postcode":"7327 AW",
    "sg:province":"Gelderland",
    "wof:name":"Amvl Apeldoorns Mini Vak Lab",
    "wof:placetype":"venue"
},
  "geometry": {"coordinates":[5.993054,52.187187],"type":"Point"}
}