{
  "type": "Feature",
  "properties": {
    "addr:full":"De Steven 49 Drachten Friesland 9206 AX",
    "addr:housenumber":"49",
    "addr:postcode":"9206 ax",
    "addr:street":"De Steven",
    "iso:country":"NL",
    "sg:address":"De Steven 49",
    "sg:city":"Drachten",
    "sg:orig_category":"Betonindustrie",
    "sg:phone":"+31 512 570 007",
    "sg:postcode":"9206 AX",
    "sg:province":"Friesland",
    "wof:name":"Smallingerland",
    "wof:placetype":"venue"
},
  "geometry": {"coordinates":[6.05283,53.114029],"type":"Point"}
}