{
  "type": "Feature",
  "properties": {
    "addr:full":"Statenln 4 Appingedam Groningen 9901 HB",
    "addr:housenumber":"4",
    "addr:postcode":"9901 hb",
    "addr:street":"Statenln",
    "iso:country":"NL",
    "sg:address":"Statenln 4",
    "sg:city":"Appingedam",
    "sg:orig_category":"Kantoor- En Secretariaatsservice",
    "sg:phone":"+31 596 680 277",
    "sg:postcode":"9901 HB",
    "sg:province":"Groningen",
    "wof:name":"Klara Westra",
    "wof:placetype":"venue"
},
  "geometry": {"coordinates":[6.8578882217,53.322593689],"type":"Point"}
}