{
  "type": "Feature",
  "properties": {
    "iso:country":"NL",
    "sg:address":"Grevelingen 30",
    "sg:city":"Pynacker",
    "sg:orig_category":"Letselschadespecialisten",
    "sg:phone":"+31 15 369 4708",
    "sg:postcode":"2641 XZ",
    "sg:province":"South Holland",
    "wof:name":"Mooyman & Partners, Letselexpertises Bv",
    "wof:placetype":"venue"
},
  "geometry": {"coordinates":[4.434985,52.008041],"type":"Point"}
}