{
  "type": "Feature",
  "properties": {
    "addr:full":"Gele Lisstr 58 Wormer Noord-Holland 1531 SG",
    "addr:housenumber":"58",
    "addr:postcode":"1531 sg",
    "addr:street":"Gele Lisstr",
    "iso:country":"NL",
    "sg:address":"Gele Lisstr 58",
    "sg:city":"Wormer",
    "sg:orig_category":"Scheepssleep- En Duwvaart",
    "sg:phone":"+31 75 642 1675",
    "sg:postcode":"1531 SG",
    "sg:province":"Noord-Holland",
    "wof:name":"Doorn, G Van",
    "wof:placetype":"venue"
},
  "geometry": {"coordinates":[4.802658,52.498367],"type":"Point"}
}