{
  "type": "Feature",
  "properties": {
    "addr:full":"Botter 2709 Lelystad NL. 8232 KM",
    "addr:postcode":"2709;8232",
    "addr:street":"Botter;Nl.;Km",
    "iso:country":"NL",
    "sg:address":"Botter 2709",
    "sg:city":"Lelystad",
    "sg:orig_category":"Bloemen And Planten Gh",
    "sg:phone":"+31 320 252 673",
    "sg:postcode":"8232 KM",
    "sg:province":"NL.",
    "wof:name":"Ton Mills",
    "wof:placetype":"venue"
},
  "geometry": {"coordinates":[5.464742,52.504475],"type":"Point"}
}