{
  "type": "Feature",
  "properties": {
    "addr:full":"Nieuwstr 29 Bussum Noord-Holland 1402 AR",
    "addr:housenumber":"29;1402",
    "addr:street":"Nieuwstr",
    "iso:country":"NL",
    "sg:address":"Nieuwstr 29",
    "sg:city":"Bussum",
    "sg:orig_category":"Zoetwaren - Winkels",
    "sg:phone":"+31 35 697 5263",
    "sg:postcode":"1402 AR",
    "sg:province":"Noord-Holland",
    "wof:name":"Snoepie",
    "wof:placetype":"venue"
},
  "geometry": {"coordinates":[5.165582,52.272099],"type":"Point"}
}