{
  "type": "Feature",
  "properties": {
    "addr:full":"Nieuweweg 48 Soest Utrecht 3765 GE",
    "addr:housenumber":"48",
    "addr:postcode":"3765",
    "addr:street":"Nieuweweg",
    "iso:country":"NL",
    "sg:address":"Nieuweweg 48",
    "sg:city":"Soest",
    "sg:orig_category":"Diverse Consumentenartikelen Gh",
    "sg:phone":"+31 35 601 6352",
    "sg:postcode":"3765 GE",
    "sg:province":"Utrecht",
    "wof:name":"C. Petersen",
    "wof:placetype":"venue"
},
  "geometry": {"coordinates":[5.290955,52.168781],"type":"Point"}
}