{
  "type": "Feature",
  "properties": {
    "iso:country":"NL",
    "sg:address":"Voorstraat 3",
    "sg:city":"Asperen",
    "sg:orig_category":"Overheidsdiensten",
    "sg:phone":"+31 345 614 625",
    "sg:postcode":"4147 CA",
    "sg:province":"Gelderland",
    "wof:name":"Salem",
    "wof:placetype":"venue"
},
  "geometry": {"coordinates":[5.1122760773,51.8812446594],"type":"Point"}
}