{
  "type": "Feature",
  "properties": {
    "addr:full":"Brandakkerstr 4 Assendelft Noord-Holland 1566 XD",
    "addr:housenumber":"4",
    "addr:postcode":"1566 xd",
    "addr:street":"Brandakkerstr",
    "iso:country":"NL",
    "sg:address":"Brandakkerstr 4",
    "sg:city":"Assendelft",
    "sg:orig_category":"Scholen Voor Basisonderwijs",
    "sg:phone":"+31 75 687 4208",
    "sg:postcode":"1566 XD",
    "sg:province":"Noord-Holland",
    "wof:name":"Assendelft Openb",
    "wof:placetype":"venue"
},
  "geometry": {"coordinates":[4.746632,52.467934],"type":"Point"}
}