{
  "type": "Feature",
  "properties": {
    "addr:full":"Burg Viezeeln 16 Streefkerk Zuid-Holland 2959 CM",
    "addr:housenumber":"16",
    "addr:postcode":"2959 cm",
    "addr:street":"Burg",
    "iso:country":"NL",
    "sg:address":"Burg Viezeeln 16",
    "sg:city":"Streefkerk",
    "sg:orig_category":"Loodgieters",
    "sg:phone":"+31 184 684 140",
    "sg:postcode":"2959 CM",
    "sg:province":"Zuid-Holland",
    "wof:name":"Liefhebber",
    "wof:placetype":"venue"
},
  "geometry": {"coordinates":[4.743335,51.901997],"type":"Point"}
}