{
  "type": "Feature",
  "properties": {
    "iso:country":"NL",
    "sg:address":"Burg Viezeeln 16",
    "sg:city":"Streefkerk",
    "sg:orig_category":"Loodgieters",
    "sg:phone":"+31 184 684 140",
    "sg:postcode":"2959 CM",
    "sg:province":"Zuid-Holland",
    "wof:name":"Liefhebber",
    "wof:placetype":"venue"
},
  "geometry": {"coordinates":[4.743335,51.901997],"type":"Point"}
}