{
  "type": "Feature",
  "properties": {
    "addr:full":"Englumstr 10 Oldehove Groningen 9883 PE",
    "addr:housenumber":"10",
    "addr:postcode":"9883 pe",
    "addr:street":"Englumstr",
    "iso:country":"NL",
    "sg:address":"Englumstr 10",
    "sg:city":"Oldehove",
    "sg:orig_category":"Zalenverhuur",
    "sg:phone":"+31 594 591 220",
    "sg:postcode":"9883 PE",
    "sg:province":"Groningen",
    "wof:name":"Humsterland, 'T",
    "wof:placetype":"venue"
},
  "geometry": {"coordinates":[6.395115,53.304871],"type":"Point"}
}