{
  "type": "Feature",
  "properties": {
    "iso:country":"NL",
    "sg:address":"M G De Bruinln 2",
    "sg:city":"Utrecht",
    "sg:orig_category":"Werving En Selectie",
    "sg:phone":"+31 30 261 3988",
    "sg:postcode":"3571 VE",
    "sg:province":"Utrecht",
    "wof:name":"Tannhauser",
    "wof:placetype":"venue"
},
  "geometry": {"coordinates":[5.1291699409,52.1081809998],"type":"Point"}
}