{
  "type": "Feature",
  "properties": {
    "iso:country":"NL",
    "sg:address":"Laan Van Meerdervoort 516",
    "sg:city":"'S Gravenhage",
    "sg:orig_category":"Verzekeringen",
    "sg:phone":"+31 70 363 1973",
    "sg:postcode":"2563 BK",
    "sg:province":"South Holland",
    "wof:name":"Kievit Assurantien Bv",
    "wof:placetype":"venue"
},
  "geometry": {"coordinates":[4.267386,52.075008],"type":"Point"}
}