{
  "type": "Feature",
  "properties": {
    "addr:full":"Pluto 30 Den Helder Noord-Holland 1785 AP",
    "addr:housenumber":"30",
    "addr:postcode":"1785 ap",
    "addr:street":"Pluto",
    "iso:country":"NL",
    "sg:address":"Pluto 30",
    "sg:city":"Den Helder",
    "sg:orig_category":"Makelaars En Adviseurs Schepen En Jachten",
    "sg:phone":"+31 223 636 814",
    "sg:postcode":"1785 AP",
    "sg:province":"Noord-Holland",
    "wof:name":"Boatex Den Helder",
    "wof:placetype":"venue"
},
  "geometry": {"coordinates":[4.777393,52.946171],"type":"Point"}
}