{
  "type": "Feature",
  "properties": {
    "addr:full":"Looierij 4 Zevenbergen Noord-Brabant 4762 AM",
    "addr:housenumber":"4",
    "addr:postcode":"4762",
    "addr:street":"Looierij",
    "iso:country":"NL",
    "sg:address":"Looierij 4",
    "sg:city":"Zevenbergen",
    "sg:orig_category":"Glas",
    "sg:phone":"+31 168 452 631",
    "sg:postcode":"4762 AM",
    "sg:province":"Noord-Brabant",
    "wof:name":"Aabes Nl",
    "wof:placetype":"venue"
},
  "geometry": {"coordinates":[4.613797,51.644688],"type":"Point"}
}