{
  "type": "Feature",
  "properties": {
    "addr:full":"Kortewg 32 Dirksland Zuid-Holland 3247 BJ",
    "addr:housenumber":"32",
    "addr:postcode":"3247 bj",
    "addr:street":"Kortewg",
    "iso:country":"NL",
    "sg:address":"Kortewg 32",
    "sg:city":"Dirksland",
    "sg:orig_category":"Artsen - Huisartsen",
    "sg:phone":"+31 187 601 262",
    "sg:postcode":"3247 BJ",
    "sg:province":"Zuid-Holland",
    "wof:name":"Kooij, J A",
    "wof:placetype":"venue"
},
  "geometry": {"coordinates":[4.109138,51.748325],"type":"Point"}
}