{
  "type": "Feature",
  "properties": {
    "addr:full":"Schyfwg N 1B Kessel Lb Limburg 5995 BM",
    "addr:housenumber":"1b",
    "addr:postcode":"lb;5995 bm",
    "addr:street":"N",
    "iso:country":"NL",
    "sg:address":"Schyfwg N 1B",
    "sg:city":"Kessel Lb",
    "sg:orig_category":"Verenigingsgebouwen",
    "sg:phone":"+31 77 462 2187",
    "sg:postcode":"5995 BM",
    "sg:province":"Limburg",
    "wof:name":"Hubertus, St",
    "wof:placetype":"venue"
},
  "geometry": {"coordinates":[6.04894,51.291866],"type":"Point"}
}