{
  "type": "Feature",
  "properties": {
    "iso:country":"NL",
    "sg:address":"Rigelstraat 34",
    "sg:city":"Hilversum",
    "sg:orig_category":"Huishoudapparatuur, Televisies And Radio'S",
    "sg:phone":"+31 35 685 4517",
    "sg:postcode":"1223 AT",
    "sg:province":"Noord-Holland",
    "wof:name":"Van Den Brink",
    "wof:placetype":"venue"
},
  "geometry": {"coordinates":[5.198801,52.232529],"type":"Point"}
}