{
  "type": "Feature",
  "properties": {
    "addr:full":"Menistenplein 1 Stadskanaal Groningen 9501 XN",
    "addr:housenumber":"1",
    "addr:postcode":"9501 xn",
    "addr:street":"Menistenplein",
    "iso:country":"NL",
    "sg:address":"Menistenplein 1",
    "sg:city":"Stadskanaal",
    "sg:orig_category":"Visspeciaalzaken",
    "sg:phone":"+31 599 621 190",
    "sg:postcode":"9501 XN",
    "sg:province":"Groningen",
    "wof:name":"Vishandel Boels",
    "wof:placetype":"venue"
},
  "geometry": {"coordinates":[6.951238,52.989155],"type":"Point"}
}