{
  "type": "Feature",
  "properties": {
    "addr:full":"P Calandln 511 Amsterdam North Holland 1068 NN",
    "addr:housenumber":"511",
    "addr:postcode":"1068 nn",
    "addr:street":"P",
    "iso:country":"NL",
    "sg:address":"P Calandln 511",
    "sg:city":"Amsterdam",
    "sg:orig_category":"Psychotherapeuten",
    "sg:phone":"+31 20 619 3192",
    "sg:postcode":"1068 NN",
    "sg:province":"North Holland",
    "wof:name":"Beta-Gamma",
    "wof:placetype":"venue"
},
  "geometry": {"coordinates":[4.804763,52.35281],"type":"Point"}
}