{
  "type": "Feature",
  "properties": {
    "iso:country":"NL",
    "sg:address":"Oude Diepenh Wg 37",
    "sg:city":"Geesteren Gld",
    "sg:orig_category":"Meubelmakerijen",
    "sg:phone":"+31 545 481 289",
    "sg:postcode":"7274 AB",
    "sg:province":"Gelderland",
    "wof:name":"Groot Landeweer",
    "wof:placetype":"venue"
},
  "geometry": {"coordinates":[6.527005,52.138981],"type":"Point"}
}