{
  "type": "Feature",
  "properties": {
    "iso:country":"NL",
    "sg:address":"Hoofdvaart 3",
    "sg:city":"Dedemsvaart",
    "sg:orig_category":"Fitnesscentra",
    "sg:phone":"+31 523 612 852",
    "sg:postcode":"7701 JE",
    "sg:province":"Overijssel",
    "wof:name":"Sport Fit Vof",
    "wof:placetype":"venue"
},
  "geometry": {"coordinates":[6.455784,52.599686],"type":"Point"}
}