{
  "type": "Feature",
  "properties": {
    "iso:country":"NL",
    "sg:address":"Carmelitessenstr 4",
    "sg:city":"Eindhoven",
    "sg:orig_category":"Homeopathie",
    "sg:phone":"+31 40 212 1861",
    "sg:postcode":"5652 EW",
    "sg:province":"Noord-Brabant",
    "wof:name":"Smits, T",
    "wof:placetype":"venue"
},
  "geometry": {"coordinates":[5.440178,51.43819],"type":"Point"}
}