{
  "type": "Feature",
  "properties": {
    "addr:full":"Fellenoord 15 Eindhoven North Brabant 5612 AA",
    "addr:housenumber":"15",
    "addr:postcode":"5612 aa",
    "addr:street":"Fellenoord",
    "iso:country":"NL",
    "sg:address":"Fellenoord 15",
    "sg:city":"Eindhoven",
    "sg:orig_category":"Makelaars In Onroerend Goed",
    "sg:phone":"+31 40 217 6440",
    "sg:postcode":"5612 AA",
    "sg:province":"North Brabant",
    "wof:name":"Rabo Onroerend Goed Nederland Bv",
    "wof:placetype":"venue"
},
  "geometry": {"coordinates":[5.478588,51.444836],"type":"Point"}
}