{
  "type": "Feature",
  "properties": {
    "iso:country":"NL",
    "sg:address":"Noorderwg 18",
    "sg:city":"Noordhorn",
    "sg:classifiers":[
        {
            "category":"Wholesale",
            "subcategory":"Petroleum",
            "type":"Manufacturing & Wholesale Goods"
        }
    ],
    "sg:phone":"+31 594 500 413",
    "sg:postcode":"9804 RM",
    "sg:province":"Groningen",
    "wof:name":"Kamphuis Petroleum",
    "wof:placetype":"venue"
},
  "geometry": {"coordinates":[6.394177,53.26339],"type":"Point"}
}