{
  "type": "Feature",
  "properties": {
    "addr:full":"Abdissenln 1 Landgraaf Limburg 6374 BJ",
    "addr:housenumber":"1",
    "addr:postcode":"6374 bj",
    "addr:street":"Abdissenln",
    "iso:country":"NL",
    "sg:address":"Abdissenln 1",
    "sg:city":"Landgraaf",
    "sg:orig_category":"Baggerwerken",
    "sg:phone":"+31 45 532 1466",
    "sg:postcode":"6374 BJ",
    "sg:province":"Limburg",
    "wof:name":"Abdissenbosch, Slibbedrijf",
    "wof:placetype":"venue"
},
  "geometry": {"coordinates":[6.035226,50.924282],"type":"Point"}
}