{
  "type": "Feature",
  "properties": {
    "iso:country":"NL",
    "sg:address":"Stationsweg 62",
    "sg:city":"Heerhugowaard",
    "sg:orig_category":"Personenvervoer Zonder Dienstregeling",
    "sg:phone":"+31 72 571 2000",
    "sg:postcode":"1702 AH",
    "sg:province":"North Holland",
    "wof:name":"Taxi Van Diepen",
    "wof:placetype":"venue"
},
  "geometry": {"coordinates":[4.827522,52.665195],"type":"Point"}
}