{
  "type": "Feature",
  "properties": {
    "addr:full":"Obrechthof 22 Alphen Aan Den Ryn Zuid-Holland 2402 EB",
    "addr:housenumber":"22",
    "addr:postcode":"2402 eb",
    "addr:street":"Obrechthof;Aan Den Ryn",
    "iso:country":"NL",
    "sg:address":"Obrechthof 22",
    "sg:city":"Alphen Aan Den Ryn",
    "sg:orig_category":"Administratie- En Boekhoudkantoren",
    "sg:phone":"+31 172 417 408",
    "sg:postcode":"2402 EB",
    "sg:province":"Zuid-Holland",
    "wof:name":"Had",
    "wof:placetype":"venue"
},
  "geometry": {"coordinates":[4.667829,52.144905],"type":"Point"}
}