{
  "type": "Feature",
  "properties": {
    "addr:full":"Vosseln 51 Woudsend Friesland 8551 ML",
    "addr:housenumber":"51",
    "addr:postcode":"8551 ml",
    "addr:street":"Vosseln",
    "iso:country":"NL",
    "sg:address":"Vosseln 51",
    "sg:city":"Woudsend",
    "sg:orig_category":"Jachten - Schilderwerken En Onderhoud",
    "sg:phone":"+31 515 419 990",
    "sg:postcode":"8551 ML",
    "sg:province":"Friesland",
    "wof:name":"Aalderen Vof, Rick Van",
    "wof:placetype":"venue"
},
  "geometry": {"coordinates":[5.6206,52.948154],"type":"Point"}
}