{
  "type": "Feature",
  "properties": {
    "iso:country":"NL",
    "sg:address":"Kl Johannesstr 7",
    "sg:city":"Gouda",
    "sg:orig_category":"Beeldende Kunstenaars",
    "sg:phone":"+31 182 522 863",
    "sg:postcode":"2801 SZ",
    "sg:province":"Zuid-Holland",
    "wof:name":"Tredgett, A W P",
    "wof:placetype":"venue"
},
  "geometry": {"coordinates":[4.699294,52.015125],"type":"Point"}
}