{
  "type": "Feature",
  "properties": {
    "addr:full":"Loerikseweg 7A Houten Utrecht 3991 AA",
    "addr:housenumber":"7a",
    "addr:postcode":"3991 aa",
    "addr:street":"Loerikseweg",
    "iso:country":"NL",
    "sg:address":"Loerikseweg 7A",
    "sg:city":"Houten",
    "sg:orig_category":"Muziekinstrumenten",
    "sg:phone":"+31 30 637 8919",
    "sg:postcode":"3991 AA",
    "sg:province":"Utrecht",
    "wof:name":"Pianostem- Vleugel Jef Slijderink",
    "wof:placetype":"venue"
},
  "geometry": {"coordinates":[5.162979,52.026764],"type":"Point"}
}