{
  "type": "Feature",
  "properties": {
    "addr:full":"Compagnonspln 1 Drachten Friesland 9202 NN",
    "addr:housenumber":"1",
    "addr:postcode":"9202 nn",
    "addr:street":"Compagnonspln",
    "iso:country":"NL",
    "sg:address":"Compagnonspln 1",
    "sg:city":"Drachten",
    "sg:orig_category":"Podotherapeuten",
    "sg:phone":"+31 512 525 211",
    "sg:postcode":"9202 NN",
    "sg:province":"Friesland",
    "wof:name":"Ewoldt",
    "wof:placetype":"venue"
},
  "geometry": {"coordinates":[6.111814,53.09922],"type":"Point"}
}