{
  "type": "Feature",
  "properties": {
    "iso:country":"NL",
    "sg:address":"Burg. Prinsensingel 87",
    "sg:city":"Roosendaal",
    "sg:classifiers":[
        {
            "category":"Education",
            "subcategory":"Preschool",
            "type":"Public Place"
        }
    ],
    "sg:phone":"+31 165 536 760",
    "sg:postcode":"4701 HL",
    "sg:province":"North Brabant",
    "sg:tags":[
        "kleuteronderwijs",
        "basis-"
    ],
    "wof:name":"Openbare Basisschool De Singel",
    "wof:placetype":"venue"
},
  "geometry": {"coordinates":[4.461418,51.53334],"type":"Point"}
}