{
  "type": "Feature",
  "properties": {
    "iso:country":"NL",
    "sg:address":"Grote Houtstraat 102",
    "sg:city":"Haarlem",
    "sg:orig_category":"Schoenen",
    "sg:phone":"+31 23 531 2215",
    "sg:postcode":"2011 ST",
    "sg:province":"Noord-Holland",
    "wof:name":"Invito",
    "wof:placetype":"venue"
},
  "geometry": {"coordinates":[4.632293,52.378422],"type":"Point"}
}