{
  "type": "Feature",
  "properties": {
    "iso:country":"NL",
    "sg:address":"Aa Stroom 48",
    "sg:city":"Oude Pekela",
    "sg:orig_category":"Paardensport",
    "sg:phone":"+31 597 613 500",
    "sg:postcode":"9665 SK",
    "sg:province":"Groningen",
    "wof:name":"Dsd Bv",
    "wof:placetype":"venue"
},
  "geometry": {"coordinates":[7.022884,53.105343],"type":"Point"}
}