{
  "type": "Feature",
  "properties": {
    "addr:full":"Dinkel 120 Leidschendam Zuid-Holland 2267 DJ",
    "addr:housenumber":"120",
    "addr:postcode":"2267 dj",
    "addr:street":"Dinkel",
    "iso:country":"NL",
    "sg:address":"Dinkel 120",
    "sg:city":"Leidschendam",
    "sg:orig_category":"Fruit And Groenten Gh",
    "sg:phone":"+31 70 317 8789",
    "sg:postcode":"2267 DJ",
    "sg:province":"Zuid-Holland",
    "wof:name":"Groothandel Kosterman Bv",
    "wof:placetype":"venue"
},
  "geometry": {"coordinates":[4.40032,52.07888],"type":"Point"}
}