{
  "type": "Feature",
  "properties": {
    "addr:full":"Randwycksngl 20 Maastricht Limburg 6229 EE",
    "addr:housenumber":"20",
    "addr:postcode":"6229 ee",
    "addr:street":"Randwycksngl",
    "iso:country":"NL",
    "sg:address":"Randwycksngl 20",
    "sg:city":"Maastricht",
    "sg:orig_category":"Verzekerings- Maatschappijen",
    "sg:phone":"+31 43 350 1212",
    "sg:postcode":"6229 EE",
    "sg:province":"Limburg",
    "wof:name":"Vgz",
    "wof:placetype":"venue"
},
  "geometry": {"coordinates":[5.70559,50.822762],"type":"Point"}
}