{
  "type": "Feature",
  "properties": {
    "addr:full":"Lelievaart 31 Zoetermeer Zuid-Holland 2724 SB",
    "addr:housenumber":"31",
    "addr:postcode":"2724 sb",
    "addr:street":"Lelievaart",
    "iso:country":"NL",
    "sg:address":"Lelievaart 31",
    "sg:city":"Zoetermeer",
    "sg:orig_category":"Adviesbureaus Bedrijfsorganisatie",
    "sg:phone":"+31 79 341 4016",
    "sg:postcode":"2724 SB",
    "sg:province":"Zuid-Holland",
    "wof:name":"Omc",
    "wof:placetype":"venue"
},
  "geometry": {"coordinates":[4.502608,52.067024],"type":"Point"}
}