{
  "type": "Feature",
  "properties": {
    "addr:full":"Driftwg 6 Huizen Noord-Holland 1271 BX",
    "addr:housenumber":"6",
    "addr:postcode":"1271 bx",
    "addr:street":"Driftwg",
    "iso:country":"NL",
    "sg:address":"Driftwg 6",
    "sg:city":"Huizen",
    "sg:orig_category":"Kaas",
    "sg:phone":"+31 35 526 0093",
    "sg:postcode":"1271 BX",
    "sg:province":"Noord-Holland",
    "wof:name":"Kos, W",
    "wof:placetype":"venue"
},
  "geometry": {"coordinates":[5.2301239967,52.3017959595],"type":"Point"}
}