{
  "type": "Feature",
  "properties": {
    "addr:full":"Zuiderstek 30 Alblasserdam South Holland 2952 AZ",
    "addr:housenumber":"30",
    "addr:postcode":"2952 az",
    "addr:street":"Zuiderstek",
    "iso:country":"NL",
    "sg:address":"Zuiderstek 30",
    "sg:city":"Alblasserdam",
    "sg:orig_category":"Scheepswerven",
    "sg:phone":"+31 78 691 3700",
    "sg:postcode":"2952 AZ",
    "sg:province":"South Holland",
    "wof:name":"Werf Alblasserdam Bv",
    "wof:placetype":"venue"
},
  "geometry": {"coordinates":[4.656361,51.860352],"type":"Point"}
}