{
  "type": "Feature",
  "properties": {
    "addr:full":"Binnenban 19-21 Hoogvliet Rt South Holland 3191 CA",
    "addr:postcode":"19-21;3191 ca",
    "addr:street":"Binnenban;Rt South",
    "iso:country":"NL",
    "sg:address":"Binnenban 19-21",
    "sg:city":"Hoogvliet Rt",
    "sg:orig_category":"Juweliers",
    "sg:phone":"+31 10 416 2871",
    "sg:postcode":"3191 CA",
    "sg:province":"South Holland",
    "wof:name":"Mostert",
    "wof:placetype":"venue"
},
  "geometry": {"coordinates":[4.354141,51.866009],"type":"Point"}
}