{
  "type": "Feature",
  "properties": {
    "iso:country":"NL",
    "sg:address":"Lieuwenburg 180",
    "sg:city":"Leeuwarden",
    "sg:orig_category":"Woninginrichting",
    "sg:phone":"+31 58 266 5290",
    "sg:postcode":"8925 CL",
    "sg:province":"Friesland",
    "wof:name":"Boer, De",
    "wof:placetype":"venue"
},
  "geometry": {"coordinates":[5.8385782242,53.2112541199],"type":"Point"}
}