{
  "type": "Feature",
  "properties": {
    "addr:full":"Gestelsestraat 4 Eindhoven North Brabant 5615 LE",
    "addr:housenumber":"4",
    "addr:postcode":"5615 le",
    "addr:street":"Gestelsestraat",
    "iso:country":"NL",
    "sg:address":"Gestelsestraat 4",
    "sg:city":"Eindhoven",
    "sg:orig_category":"Opticiens",
    "sg:phone":"+31 40 244 9014",
    "sg:postcode":"5615 LE",
    "sg:province":"North Brabant",
    "wof:name":"Buisman Optiek",
    "wof:placetype":"venue"
},
  "geometry": {"coordinates":[5.4716510773,51.4334144592],"type":"Point"}
}