{
  "type": "Feature",
  "properties": {
    "iso:country":"NL",
    "sg:address":"Boulevard 132",
    "sg:city":"Roosendaal",
    "sg:orig_category":"Autorijscholen",
    "sg:phone":"+31 165 541 399",
    "sg:postcode":"4701 EZ",
    "sg:province":"Noord-Brabant",
    "sg:website":"http://www.rijschoolsuccess.nl",
    "wof:name":"Success Autorijschool",
    "wof:placetype":"venue"
},
  "geometry": {"coordinates":[4.465912,51.532543],"type":"Point"}
}