{
  "type": "Feature",
  "properties": {
    "addr:full":"De Waard 48 Heiloo Noord-Holland 1851 RE",
    "addr:housenumber":"48",
    "addr:postcode":"1851 re",
    "addr:street":"De Waard",
    "iso:country":"NL",
    "sg:address":"De Waard 48",
    "sg:city":"Heiloo",
    "sg:orig_category":"Webdesign Bureaus",
    "sg:phone":"+31 72 533 8078",
    "sg:postcode":"1851 RE",
    "sg:province":"Noord-Holland",
    "wof:name":"Boer, De",
    "wof:placetype":"venue"
},
  "geometry": {"coordinates":[4.7141299248,52.5927314758],"type":"Point"}
}