{
  "type": "Feature",
  "properties": {
    "addr:full":"Waterloweg 30 Ede Gelderland 6713 AS",
    "addr:housenumber":"30",
    "addr:postcode":"6713 as",
    "addr:street":"Waterloweg;Gelderland",
    "iso:country":"NL",
    "sg:address":"Waterloweg 30",
    "sg:city":"Ede",
    "sg:orig_category":"Diverse Grafische Activiteiten",
    "sg:phone":"+31 318 693 111",
    "sg:postcode":"6713 AS",
    "sg:province":"Gelderland",
    "wof:name":"Bos E-Commerce & I-Services",
    "wof:placetype":"venue"
},
  "geometry": {"coordinates":[5.6652569771,52.0433654785],"type":"Point"}
}