{
  "type": "Feature",
  "properties": {
    "iso:country":"NL",
    "sg:address":"Bakkerstr 16",
    "sg:city":"Utrecht",
    "sg:orig_category":"Herenkleding",
    "sg:phone":"+31 30 231 1821",
    "sg:postcode":"3511 JW",
    "sg:province":"Utrecht",
    "wof:name":"London City Club",
    "wof:placetype":"venue"
},
  "geometry": {"coordinates":[5.117087,52.09137],"type":"Point"}
}