{
  "type": "Feature",
  "properties": {
    "iso:country":"NL",
    "sg:address":"Dorpsweg 44",
    "sg:city":"Rockanje",
    "sg:orig_category":"Verlichting And Huishoudartikelen",
    "sg:phone":"+31 181 401 472",
    "sg:postcode":"3235 AG",
    "sg:province":"South Holland",
    "wof:name":"Vof Novalux",
    "wof:placetype":"venue"
},
  "geometry": {"coordinates":[4.071605,51.874668],"type":"Point"}
}