{
  "type": "Feature",
  "properties": {
    "addr:full":"Willem Hedastraat 9 Alkmaar North Holland 1816 KC",
    "addr:housenumber":"9",
    "addr:postcode":"1816 kc",
    "addr:street":"Willem Hedastraat",
    "iso:country":"NL",
    "sg:address":"Willem Hedastraat 9",
    "sg:city":"Alkmaar",
    "sg:orig_category":"Autokeuringen",
    "sg:phone":"+31 72 515 5513",
    "sg:postcode":"1816 KC",
    "sg:province":"North Holland",
    "wof:name":"Uas Alkmaar",
    "wof:placetype":"venue"
},
  "geometry": {"coordinates":[4.730101,52.63327],"type":"Point"}
}