{
  "type": "Feature",
  "properties": {
    "addr:full":"Nieuwstraat 39 Leidschendam South Holland 2266 AB",
    "addr:housenumber":"39",
    "addr:postcode":"2266 ab",
    "addr:street":"Nieuwstraat",
    "iso:country":"NL",
    "sg:address":"Nieuwstraat 39",
    "sg:city":"Leidschendam",
    "sg:orig_category":"Goederenvervoer Over De Weg",
    "sg:phone":"+31 70 327 4667",
    "sg:postcode":"2266 AB",
    "sg:province":"South Holland",
    "wof:name":"Vervoersbedr N Remmerswaal Joh Zn",
    "wof:placetype":"venue"
},
  "geometry": {"coordinates":[4.396604,52.078732],"type":"Point"}
}