{
  "type": "Feature",
  "properties": {
    "addr:full":"L Nering 61 Emmeloord Flevoland 8302 EB",
    "addr:housenumber":"61",
    "addr:postcode":"8302 eb",
    "addr:street":"Nering;Flevoland",
    "iso:country":"NL",
    "sg:address":"L Nering 61",
    "sg:city":"Emmeloord",
    "sg:orig_category":"Boeken En Tijdschriften",
    "sg:phone":"+31 527 618 635",
    "sg:postcode":"8302 EB",
    "sg:province":"Flevoland",
    "wof:name":"Boekenvoordeel Bv",
    "wof:placetype":"venue"
},
  "geometry": {"coordinates":[5.757094,52.711494],"type":"Point"}
}