{
  "type": "Feature",
  "properties": {
    "addr:full":"Jan Ligthartstraat 4 Alkmaar Noord-Holland 1817 MR",
    "addr:housenumber":"4",
    "addr:postcode":"1817 mr",
    "addr:street":"Jan Ligthartstraat",
    "iso:country":"NL",
    "sg:address":"Jan Ligthartstraat 4",
    "sg:city":"Alkmaar",
    "sg:orig_category":"Overheidsdiensten",
    "sg:phone":"+31 72 888 0000",
    "sg:postcode":"1817 MR",
    "sg:province":"Noord-Holland",
    "wof:name":"Gemeente Bergen Nh",
    "wof:placetype":"venue"
},
  "geometry": {"coordinates":[4.7274541855,52.6457061768],"type":"Point"}
}