{
  "type": "Feature",
  "properties": {
    "addr:full":"Oosterlaan 4 Schraard Provincie Friesland 8746 ND",
    "addr:housenumber":"4",
    "addr:postcode":"8746 nd",
    "addr:street":"Oosterlaan;Provincie Friesland",
    "iso:country":"NL",
    "sg:address":"Oosterlaan 4",
    "sg:city":"Schraard",
    "sg:orig_category":"Hout Gh",
    "sg:phone":"+31 517 532 134",
    "sg:postcode":"8746 ND",
    "sg:province":"Provincie Friesland",
    "wof:name":"De Boer Hout Bv",
    "wof:placetype":"venue"
},
  "geometry": {"coordinates":[5.458444,53.079575],"type":"Point"}
}