{
  "type": "Feature",
  "properties": {
    "addr:full":"Kerkstraat 38 Noordwijk Zh Zuid-Holland 2201 KN",
    "addr:housenumber":"38",
    "addr:postcode":"2201 kn",
    "addr:street":"Kerkstraat",
    "iso:country":"NL",
    "sg:address":"Kerkstraat 38",
    "sg:city":"Noordwijk Zh",
    "sg:classifiers":[
        {
            "category":"Bakery",
            "type":"Food & Drink"
        }
    ],
    "sg:phone":"+31 71 361 2491",
    "sg:postcode":"2201 KN",
    "sg:province":"Zuid-Holland",
    "sg:tags":[
        "brood",
        "banket"
    ],
    "wof:name":"J.M. Van Westerop",
    "wof:placetype":"venue"
},
  "geometry": {"coordinates":[4.445974,52.234802],"type":"Point"}
}