{
  "type": "Feature",
  "properties": {
    "addr:full":"Conradhof 24 Tilburg North Brabant 5025 DV",
    "addr:housenumber":"24",
    "addr:postcode":"5025 dv",
    "addr:street":"Conradhof",
    "iso:country":"NL",
    "sg:address":"Conradhof 24",
    "sg:city":"Tilburg",
    "sg:orig_category":"Journalisten Freelance",
    "sg:phone":"+31 6 28857665",
    "sg:postcode":"5025 DV",
    "sg:province":"North Brabant",
    "wof:name":"Bijlmakers, Mari?lle",
    "wof:placetype":"venue"
},
  "geometry": {"coordinates":[5.074077,51.549755],"type":"Point"}
}