{
  "type": "Feature",
  "properties": {
    "addr:full":"Waterstr 146 Nymegen Tennessee 6541 TN",
    "addr:housenumber":"146",
    "addr:postcode":"6541",
    "addr:street":"Nymegen Tennessee",
    "iso:country":"NL",
    "sg:address":"Waterstr 146",
    "sg:city":"Nymegen",
    "sg:orig_category":"Verenigingsgebouwen",
    "sg:phone":"+31 24 377 4719",
    "sg:postcode":"6541 TN",
    "sg:province":"Tennessee",
    "wof:name":"Waterkwartier Buurtcentr",
    "wof:placetype":"venue"
},
  "geometry": {"coordinates":[-85.978554,35.83062],"type":"Point"}
}