{
  "type": "Feature",
  "properties": {
    "addr:full":"Burghoffwg 1 Roermond Limburg 6042 EX",
    "addr:housenumber":"1",
    "addr:postcode":"6042 ex",
    "addr:street":"Burghoffwg",
    "iso:country":"NL",
    "sg:address":"Burghoffwg 1",
    "sg:city":"Roermond",
    "sg:classifiers":[
        {
            "category":"Retail",
            "subcategory":"Auto Repair",
            "type":"Services"
        }
    ],
    "sg:phone":"+31 475 325 001",
    "sg:postcode":"6042 EX",
    "sg:province":"Limburg",
    "sg:tags":[
        "garage"
    ],
    "wof:name":"Fit",
    "wof:placetype":"venue"
},
  "geometry": {"coordinates":[6.015141,51.211098],"type":"Point"}
}