{
  "type": "Feature",
  "properties": {
    "addr:full":"Gasthuisvest 15 Haarlem North Holland 2011 ET",
    "addr:housenumber":"15",
    "addr:postcode":"2011 et",
    "addr:street":"Gasthuisvest",
    "iso:country":"NL",
    "sg:address":"Gasthuisvest 15",
    "sg:city":"Haarlem",
    "sg:orig_category":"Verf En Lak",
    "sg:phone":"+31 6 55192221",
    "sg:postcode":"2011 ET",
    "sg:province":"North Holland",
    "wof:name":"Auro",
    "wof:placetype":"venue"
},
  "geometry": {"coordinates":[4.632037,52.376289],"type":"Point"}
}