{
  "type": "Feature",
  "properties": {
    "iso:country":"NL",
    "sg:address":"Meester Th Heemskerklaan 18",
    "sg:city":"Amersfoort",
    "sg:orig_category":"Paramedische Behandelingen",
    "sg:phone":"+31 33 465 7720",
    "sg:postcode":"3818 KL",
    "sg:province":"Utrecht",
    "wof:name":"R.T. Plantinga",
    "wof:placetype":"venue"
},
  "geometry": {"coordinates":[5.358756,52.149567],"type":"Point"}
}