{
  "type": "Feature",
  "properties": {
    "addr:full":"I Dalessngl 11 Zutphen Gelderland 7207 LA",
    "addr:housenumber":"11;7207",
    "addr:street":"Gelderland",
    "iso:country":"NL",
    "sg:address":"I Dalessngl 11",
    "sg:city":"Zutphen",
    "sg:orig_category":"Belastingconsulenten/ Belastingadviseurs",
    "sg:phone":"+31 575 521 487",
    "sg:postcode":"7207 LA",
    "sg:province":"Gelderland",
    "wof:name":"Advisie",
    "wof:placetype":"venue"
},
  "geometry": {"coordinates":[6.191525,52.140202],"type":"Point"}
}