{
  "type": "Feature",
  "properties": {
    "iso:country":"NL",
    "sg:address":"Voorthuizerstr 5",
    "sg:city":"Putten",
    "sg:orig_category":"Logopedisten",
    "sg:phone":"+31 341 360 367",
    "sg:postcode":"3881 SB",
    "sg:province":"Gelderland",
    "wof:name":"Bosman, J E M",
    "wof:placetype":"venue"
},
  "geometry": {"coordinates":[5.609337,52.229198],"type":"Point"}
}