{
  "type": "Feature",
  "properties": {
    "addr:full":"De Sterke Arm 2A Veenendaal Utrecht 3901 ER",
    "addr:housenumber":"2a",
    "addr:postcode":"3901 er",
    "addr:street":"De Sterke Arm",
    "iso:country":"NL",
    "sg:address":"De Sterke Arm 2A",
    "sg:city":"Veenendaal",
    "sg:orig_category":"Kinderopvang",
    "sg:phone":"+31 318 523 856",
    "sg:postcode":"3901 ER",
    "sg:province":"Utrecht",
    "wof:name":"Balou",
    "wof:placetype":"venue"
},
  "geometry": {"coordinates":[5.555346,52.022327],"type":"Point"}
}