{
  "type": "Feature",
  "properties": {
    "addr:full":"Postbus 258 Veldhoven North Brabant 5500 AG",
    "addr:housenumber":"258",
    "addr:postcode":"5500",
    "addr:street":"Postbus",
    "iso:country":"NL",
    "sg:address":"Postbus 258",
    "sg:city":"Veldhoven",
    "sg:orig_category":"Projectontwikkeling",
    "sg:phone":"+31 40 253 5847",
    "sg:postcode":"5500 AG",
    "sg:province":"North Brabant",
    "wof:name":"Maashof Bv",
    "wof:placetype":"venue"
},
  "geometry": {"coordinates":[5.404554,51.421745],"type":"Point"}
}