{
  "type": "Feature",
  "properties": {
    "addr:full":"Blijhamsterweg 35 Winschoten Groningen 9673 GL",
    "addr:housenumber":"35",
    "addr:postcode":"9673 gl",
    "addr:street":"Blijhamsterweg",
    "iso:country":"NL",
    "sg:address":"Blijhamsterweg 35",
    "sg:city":"Winschoten",
    "sg:orig_category":"Bejaardeninstellingen And Serviceflats",
    "sg:phone":"+31 597 422 406",
    "sg:postcode":"9673 GL",
    "sg:province":"Groningen",
    "wof:name":"Pension Juliana",
    "wof:placetype":"venue"
},
  "geometry": {"coordinates":[7.042686,53.135578],"type":"Point"}
}