{
  "type": "Feature",
  "properties": {
    "iso:country":"NL",
    "sg:address":"Meeuwenlaan 311Hs",
    "sg:city":"Amsterdam",
    "sg:orig_category":"Binnenhuisarchitecten",
    "sg:phone":"+31 20 636 9985",
    "sg:postcode":"1022 AK",
    "sg:province":"Noord-Holland",
    "wof:name":"H. Van Broekhuijsen",
    "wof:placetype":"venue"
},
  "geometry": {"coordinates":[4.924486,52.389812],"type":"Point"}
}