{
  "type": "Feature",
  "properties": {
    "iso:country":"NL",
    "sg:address":"Crommelinln 41",
    "sg:city":"Delft",
    "sg:orig_category":"Woningstoffeerders",
    "sg:phone":"+31 15 256 5022",
    "sg:postcode":"2627 AD",
    "sg:province":"South Holland",
    "wof:name":"Buuren, Robert Van",
    "wof:placetype":"venue"
},
  "geometry": {"coordinates":[4.3592967987,52.0034255981],"type":"Point"}
}