{
  "type": "Feature",
  "properties": {
    "addr:full":"Crommelinln 41 Delft South Holland 2627 AD",
    "addr:housenumber":"41",
    "addr:postcode":"2627 ad",
    "addr:street":"Crommelinln",
    "iso:country":"NL",
    "sg:address":"Crommelinln 41",
    "sg:city":"Delft",
    "sg:orig_category":"Woningstoffeerders",
    "sg:phone":"+31 15 256 5022",
    "sg:postcode":"2627 AD",
    "sg:province":"South Holland",
    "wof:name":"Buuren, Robert Van",
    "wof:placetype":"venue"
},
  "geometry": {"coordinates":[4.3592967987,52.0034255981],"type":"Point"}
}