{
  "type": "Feature",
  "properties": {
    "addr:full":"Nw Zeewg 68 Noordwyk Zh Zuid-Holland 2202 HB",
    "addr:housenumber":"68",
    "addr:postcode":"2202 hb",
    "addr:street":"Noordwyk",
    "iso:country":"NL",
    "sg:address":"Nw Zeewg 68",
    "sg:city":"Noordwyk Zh",
    "sg:orig_category":"Notarissen En Notariskantoren",
    "sg:phone":"+31 71 364 0133",
    "sg:postcode":"2202 HB",
    "sg:province":"Zuid-Holland",
    "wof:name":"Hoeken & Janbroers, Van",
    "wof:placetype":"venue"
},
  "geometry": {"coordinates":[4.4477,52.234261],"type":"Point"}
}