{
  "type": "Feature",
  "properties": {
    "addr:full":"Venesluis 5 Dwingeloo Drenthe 7991 TG",
    "addr:housenumber":"5",
    "addr:postcode":"7991 tg",
    "addr:street":"Venesluis",
    "iso:country":"NL",
    "sg:address":"Venesluis 5",
    "sg:city":"Dwingeloo",
    "sg:orig_category":"Land- En Tuinbouw - Loonbedrijven",
    "sg:phone":"+31 521 592 380",
    "sg:postcode":"7991 TG",
    "sg:province":"Drenthe",
    "wof:name":"Kiers, L R",
    "wof:placetype":"venue"
},
  "geometry": {"coordinates":[6.373037,52.874779],"type":"Point"}
}