{
  "type": "Feature",
  "properties": {
    "iso:country":"NL",
    "sg:address":"Stroveer 180",
    "sg:city":"Rotterdam",
    "sg:orig_category":"Boekhouders",
    "sg:phone":"+31 10 467 0832",
    "sg:postcode":"3032 GA",
    "sg:province":"Zuid-Holland",
    "wof:name":"Administratiekantoor S Gadjoe",
    "wof:placetype":"venue"
},
  "geometry": {"coordinates":[4.482341,51.926479],"type":"Point"}
}