{
  "type": "Feature",
  "properties": {
    "iso:country":"NL",
    "sg:address":"De Schans 36",
    "sg:city":"Leek",
    "sg:orig_category":"Broodjeszaken",
    "sg:phone":"+31 594 513 864",
    "sg:postcode":"9351 AZ",
    "sg:province":"Groningen",
    "wof:name":"Plateau, Le",
    "wof:placetype":"venue"
},
  "geometry": {"coordinates":[6.391106,53.161167],"type":"Point"}
}