{
  "type": "Feature",
  "properties": {
    "addr:full":"De Schans 36 Leek Groningen 9351 AZ",
    "addr:housenumber":"36",
    "addr:postcode":"9351 az",
    "addr:street":"De Schans",
    "iso:country":"NL",
    "sg:address":"De Schans 36",
    "sg:city":"Leek",
    "sg:orig_category":"Broodjeszaken",
    "sg:phone":"+31 594 513 864",
    "sg:postcode":"9351 AZ",
    "sg:province":"Groningen",
    "wof:name":"Plateau, Le",
    "wof:placetype":"venue"
},
  "geometry": {"coordinates":[6.391106,53.161167],"type":"Point"}
}