{
  "type": "Feature",
  "properties": {
    "addr:full":"Gramserweg 18 Austerlitz Utrecht 3711 AW",
    "addr:housenumber":"18",
    "addr:postcode":"3711 aw",
    "addr:street":"Gramserweg",
    "iso:country":"NL",
    "sg:address":"Gramserweg 18",
    "sg:city":"Austerlitz",
    "sg:orig_category":"Verhuur Catering-, Feest- En Evenementbenodigdheden",
    "sg:phone":"+31 343 491 583",
    "sg:postcode":"3711 AW",
    "sg:province":"Utrecht",
    "wof:name":"Van Beek Toiletcabinesverhuur",
    "wof:placetype":"venue"
},
  "geometry": {"coordinates":[5.31215,52.078487],"type":"Point"}
}