{
  "type": "Feature",
  "properties": {
    "addr:full":"Bilderdijkstraat 26 Leeuwarden Provincie Friesland 8914 AC",
    "addr:housenumber":"26",
    "addr:postcode":"8914 ac",
    "addr:street":"Bilderdijkstraat;Provincie Friesland",
    "iso:country":"NL",
    "sg:address":"Bilderdijkstraat 26",
    "sg:city":"Leeuwarden",
    "sg:orig_category":"Watersport-, Sport- And Kampeerbenodigdheden Verhuur",
    "sg:phone":"+31 58 213 0806",
    "sg:postcode":"8914 AC",
    "sg:province":"Provincie Friesland",
    "wof:name":"De Oldehove",
    "wof:placetype":"venue"
},
  "geometry": {"coordinates":[5.7729430199,53.2050857544],"type":"Point"}
}