{
  "type": "Feature",
  "properties": {
    "addr:full":"Schoolstr 6 Halsteren Noord-Brabant 4661 JL",
    "addr:housenumber":"6",
    "addr:postcode":"4661 jl",
    "addr:street":"Schoolstr",
    "iso:country":"NL",
    "sg:address":"Schoolstr 6",
    "sg:city":"Halsteren",
    "sg:orig_category":"Verenigingsgebouwen",
    "sg:phone":"+31 164 682 698",
    "sg:postcode":"4661 JL",
    "sg:province":"Noord-Brabant",
    "wof:name":"Wittenhorst, De",
    "wof:placetype":"venue"
},
  "geometry": {"coordinates":[4.268916,51.528252],"type":"Point"}
}