{
  "type": "Feature",
  "properties": {
    "addr:full":"Kloosterstraat 24 Simpelveld Limburg 6369 AD",
    "addr:housenumber":"24",
    "addr:postcode":"6369 ad",
    "addr:street":"Kloosterstraat",
    "iso:country":"NL",
    "sg:address":"Kloosterstraat 24",
    "sg:city":"Simpelveld",
    "sg:classifiers":[
        {
            "category":"Bakery",
            "type":"Food & Drink"
        }
    ],
    "sg:phone":"+31 45 544 1259",
    "sg:postcode":"6369 AD",
    "sg:province":"Limburg",
    "sg:tags":[
        "brood",
        "banket"
    ],
    "wof:name":"J.H.J. Gorissen",
    "wof:placetype":"venue"
},
  "geometry": {"coordinates":[5.984021,50.83424],"type":"Point"}
}