{
  "type": "Feature",
  "properties": {
    "addr:full":"Fenacoliusln 2 Maassluis Zuid-Holland 3143 AC",
    "addr:housenumber":"2",
    "addr:postcode":"3143 ac",
    "addr:street":"Fenacoliusln",
    "iso:country":"NL",
    "sg:address":"Fenacoliusln 2",
    "sg:city":"Maassluis",
    "sg:orig_category":"Acupunctuur",
    "sg:phone":"+31 10 592 6788",
    "sg:postcode":"3143 AC",
    "sg:province":"Zuid-Holland",
    "wof:name":"Setyo-Arts",
    "wof:placetype":"venue"
},
  "geometry": {"coordinates":[4.254736,51.920338],"type":"Point"}
}