{
  "type": "Feature",
  "properties": {
    "iso:country":"NL",
    "sg:address":"De Sillestr 28",
    "sg:city":"S Gravenhage",
    "sg:orig_category":"Elektrotechnische Installatiebureaus",
    "sg:phone":"+31 70 383 4744",
    "sg:postcode":"2593 TZ",
    "sg:province":"South Holland",
    "wof:name":"Besteman & Zn",
    "wof:placetype":"venue"
},
  "geometry": {"coordinates":[4.34266,52.086121],"type":"Point"}
}