{
  "type": "Feature",
  "properties": {
    "addr:full":"Bergstr 29A Groningen Groningen 9717 LR",
    "addr:housenumber":"29a",
    "addr:postcode":"9717 lr",
    "addr:street":"Bergstr",
    "iso:country":"NL",
    "sg:address":"Bergstr 29A",
    "sg:city":"Groningen",
    "sg:orig_category":"Verenigingsgebouwen",
    "sg:phone":"+31 50 573 0836",
    "sg:postcode":"9717 LR",
    "sg:province":"Groningen",
    "wof:name":"Bethel",
    "wof:placetype":"venue"
},
  "geometry": {"coordinates":[6.553698,53.224632],"type":"Point"}
}