{
  "type": "Feature",
  "properties": {
    "iso:country":"NL",
    "sg:address":"Zilverstr 23-25",
    "sg:city":"S Gravenhage",
    "sg:orig_category":"Horecabenodigdheden",
    "sg:phone":"+31 70 366 3060",
    "sg:postcode":"2544 EJ",
    "sg:province":"Zuid-Holland",
    "wof:name":"Groot Grootverbruik, De",
    "wof:placetype":"venue"
},
  "geometry": {"coordinates":[4.25157,52.039551],"type":"Point"}
}