{
  "type": "Feature",
  "properties": {
    "addr:full":"Gr Walramhof 9 Nieuwegein Utrecht 3434 SE",
    "addr:housenumber":"9",
    "addr:postcode":"3434 se",
    "addr:street":"Gr Walramhof",
    "iso:country":"NL",
    "sg:address":"Gr Walramhof 9",
    "sg:city":"Nieuwegein",
    "sg:orig_category":"Adviesbureaus Bedrijfsorganisatie",
    "sg:phone":"+31 30 606 5342",
    "sg:postcode":"3434 SE",
    "sg:province":"Utrecht",
    "wof:name":"Blonk, Drs C J",
    "wof:placetype":"venue"
},
  "geometry": {"coordinates":[5.093158,52.012215],"type":"Point"}
}