{
  "type": "Feature",
  "properties": {
    "addr:full":"Kuyperln 23 Doetinchem Gelderland 7003 DC",
    "addr:housenumber":"23",
    "addr:postcode":"7003",
    "addr:street":"Kuyperln;Gelderland",
    "iso:country":"NL",
    "sg:address":"Kuyperln 23",
    "sg:city":"Doetinchem",
    "sg:orig_category":"Kappers",
    "sg:phone":"+31 314 384 170",
    "sg:postcode":"7003 DC",
    "sg:province":"Gelderland",
    "wof:name":"Pernou, Haarmode",
    "wof:placetype":"venue"
},
  "geometry": {"coordinates":[6.311511,51.963058],"type":"Point"}
}