{
  "type": "Feature",
  "properties": {
    "addr:full":"Koopmanstraat 78 Aalten Gelderland 7121 VW",
    "addr:housenumber":"78",
    "addr:postcode":"7121",
    "addr:street":"Koopmanstraat;Gelderland;Vw",
    "iso:country":"NL",
    "sg:address":"Koopmanstraat 78",
    "sg:city":"Aalten",
    "sg:orig_category":"Paramedische Behandelingen",
    "sg:phone":"+31 543 476 555",
    "sg:postcode":"7121 VW",
    "sg:province":"Gelderland",
    "wof:name":"D.M. Meulman",
    "wof:placetype":"venue"
},
  "geometry": {"coordinates":[6.58749,51.919811],"type":"Point"}
}