{
  "type": "Feature",
  "properties": {
    "iso:country":"NL",
    "sg:address":"Andreas Schelfhoutstraat 1",
    "sg:city":"Amsterdam",
    "sg:orig_category":"Vertaal- And Tolkenbureaus",
    "sg:phone":"+31 20 617 3100",
    "sg:postcode":"1058 HP",
    "sg:province":"Noord-Holland",
    "wof:name":"Emy Giphart Vertaalburo",
    "wof:placetype":"venue"
},
  "geometry": {"coordinates":[4.85376,52.357063],"type":"Point"}
}