{
  "type": "Feature",
  "properties": {
    "addr:full":"Amersfoortsewg 59 Nykerkerveen Gelderland 3864 NB",
    "addr:housenumber":"59",
    "addr:postcode":"3864 nb",
    "addr:street":"Amersfoortsewg;Gelderland",
    "iso:country":"NL",
    "sg:address":"Amersfoortsewg 59",
    "sg:city":"Nykerkerveen",
    "sg:orig_category":"Onderhoudswerken",
    "sg:phone":"+31 33 257 1550",
    "sg:postcode":"3864 NB",
    "sg:province":"Gelderland",
    "wof:name":"Dusschoten, A Van",
    "wof:placetype":"venue"
},
  "geometry": {"coordinates":[5.460644,52.202122],"type":"Point"}
}