{
  "type": "Feature",
  "properties": {
    "addr:full":"Noorderwg 60 Vroomshoop Overijssel 7681 CE",
    "addr:housenumber":"60",
    "addr:postcode":"7681 ce",
    "addr:street":"Noorderwg",
    "iso:country":"NL",
    "sg:address":"Noorderwg 60",
    "sg:city":"Vroomshoop",
    "sg:orig_category":"Luchtbehandelings- Apparaten",
    "sg:phone":"+31 6 51124667",
    "sg:postcode":"7681 CE",
    "sg:province":"Overijssel",
    "wof:name":"Ariba",
    "wof:placetype":"venue"
},
  "geometry": {"coordinates":[6.571411,52.470966],"type":"Point"}
}