{
  "type": "Feature",
  "properties": {
    "iso:country":"NL",
    "sg:address":"Markt 36",
    "sg:city":"Etten-Leur",
    "sg:classifiers":[
        {
            "category":"Fast Food",
            "type":"Food & Drink"
        }
    ],
    "sg:phone":"+31 76 503 4205",
    "sg:postcode":"4875 CE",
    "sg:province":"North Brabant",
    "sg:tags":[
        "afhaal",
        "restaurant"
    ],
    "wof:name":"Chinees Indisch Restaurant Yang'S Garden",
    "wof:placetype":"venue"
},
  "geometry": {"coordinates":[4.635733,51.57045],"type":"Point"}
}