{
  "type": "Feature",
  "properties": {
    "addr:full":"Strawinskylaan 45 Amsterdam North Holland 1077 XW",
    "addr:housenumber":"45",
    "addr:postcode":"1077 xw",
    "addr:street":"Strawinskylaan",
    "iso:country":"NL",
    "sg:address":"Strawinskylaan 45",
    "sg:city":"Amsterdam",
    "sg:orig_category":"Kinderopvang Behalve Thuis",
    "sg:phone":"+31 20 575 3301",
    "sg:postcode":"1077 XW",
    "sg:province":"North Holland",
    "wof:name":"De Blauwe Bengel",
    "wof:placetype":"venue"
},
  "geometry": {"coordinates":[4.872579,52.340607],"type":"Point"}
}