{
  "type": "Feature",
  "properties": {
    "addr:full":"Rozenstr 244 Amsterdam Noord-Holland 1016 PB",
    "addr:housenumber":"244",
    "addr:postcode":"1016 pb",
    "iso:country":"NL",
    "sg:address":"Rozenstr 244",
    "sg:city":"Amsterdam",
    "sg:orig_category":"Fotografie Reclame En Mode",
    "sg:phone":"+31 20 420 0663",
    "sg:postcode":"1016 PB",
    "sg:province":"Noord-Holland",
    "sg:website":"http://www.boudewijn-smit.nl",
    "wof:name":"Smit Bv, Boudewijn",
    "wof:placetype":"venue"
},
  "geometry": {"coordinates":[4.877033,52.371887],"type":"Point"}
}