{
  "type": "Feature",
  "properties": {
    "addr:full":"Johan Jongkindstraat 99 Amsterdam Noord-Holland 1062 CR",
    "addr:housenumber":"99",
    "addr:postcode":"1062 cr",
    "addr:street":"Johan Jongkindstraat",
    "iso:country":"NL",
    "sg:address":"Johan Jongkindstraat 99",
    "sg:city":"Amsterdam",
    "sg:orig_category":"Handelsbemiddeling Textiel And Lederwaren",
    "sg:phone":"+31 20 614 0001",
    "sg:postcode":"1062 CR",
    "sg:province":"Noord-Holland",
    "wof:name":"Steinkuhler Import Export Bv",
    "wof:placetype":"venue"
},
  "geometry": {"coordinates":[4.836904,52.359257],"type":"Point"}
}