{
  "type": "Feature",
  "properties": {
    "addr:full":"Nijverheidstraat 28 Enschede NL.08 7511 JM",
    "addr:housenumber":"28",
    "addr:postcode":"7511 jm",
    "addr:street":"Nijverheidstraat",
    "iso:country":"NL",
    "sg:address":"Nijverheidstraat 28",
    "sg:city":"Enschede",
    "sg:orig_category":"Overheidsdiensten",
    "sg:phone":"+31 53 483 2811",
    "sg:postcode":"7511 JM",
    "sg:province":"NL.08",
    "wof:name":"Cadans",
    "wof:placetype":"venue"
},
  "geometry": {"coordinates":[6.8917341232,52.2188720703],"type":"Point"}
}