{
  "type": "Feature",
  "properties": {
    "addr:full":"Grotestr 28 Beers Nb North Brabant 5437 AS",
    "addr:housenumber":"28",
    "addr:postcode":"5437 as",
    "addr:street":"Grotestr",
    "iso:country":"NL",
    "sg:address":"Grotestr 28",
    "sg:city":"Beers Nb",
    "sg:orig_category":"Zalenverhuur",
    "sg:phone":"+31 485 312 937",
    "sg:postcode":"5437 AS",
    "sg:province":"North Brabant",
    "wof:name":"Marang",
    "wof:placetype":"venue"
},
  "geometry": {"coordinates":[5.829188,51.724785],"type":"Point"}
}