{
  "type": "Feature",
  "properties": {
    "addr:full":"Haarstr 65 Gorinchem South Holland 4201 JB",
    "addr:housenumber":"65",
    "addr:postcode":"4201 jb",
    "addr:street":"Haarstr",
    "iso:country":"NL",
    "sg:address":"Haarstr 65",
    "sg:city":"Gorinchem",
    "sg:orig_category":"Banken",
    "sg:phone":"+31 183 669 444",
    "sg:postcode":"4201 JB",
    "sg:province":"South Holland",
    "sg:website":"http://www.rabobank.nl",
    "wof:name":"Rabobank",
    "wof:placetype":"venue"
},
  "geometry": {"coordinates":[4.974721,51.832172],"type":"Point"}
}