{
  "type": "Feature",
  "properties": {
    "iso:country":"NL",
    "sg:address":"Rynaakkd 10",
    "sg:city":"Venlo",
    "sg:orig_category":"Waterleidingbedrijven",
    "sg:phone":"+31 800 0233040",
    "sg:postcode":"5928 PT",
    "sg:province":"Limburg",
    "wof:name":"Wml",
    "wof:placetype":"venue"
},
  "geometry": {"coordinates":[6.1195502281,51.3953094482],"type":"Point"}
}