{
  "type": "Feature",
  "properties": {
    "iso:country":"NL",
    "sg:address":"Da Costastraat 3",
    "sg:city":"Venlo",
    "sg:orig_category":"Artsen And Specialisten",
    "sg:phone":"+31 77 382 1573",
    "sg:postcode":"5922 TA",
    "sg:province":"Limburg",
    "wof:name":"C.M. Harthoorn",
    "wof:placetype":"venue"
},
  "geometry": {"coordinates":[6.14281,51.371235],"type":"Point"}
}