{
  "type": "Feature",
  "properties": {
    "addr:full":"Kastanjeln 32 Borculo Gelderland 7271 JB",
    "addr:housenumber":"32",
    "addr:postcode":"7271 jb",
    "addr:street":"Kastanjeln;Gelderland",
    "iso:country":"NL",
    "sg:address":"Kastanjeln 32",
    "sg:city":"Borculo",
    "sg:orig_category":"Adviesbureaus Bedrijfsorganisatie",
    "sg:phone":"+31 545 274 597",
    "sg:postcode":"7271 JB",
    "sg:province":"Gelderland",
    "wof:name":"Huinink",
    "wof:placetype":"venue"
},
  "geometry": {"coordinates":[6.530845,52.116055],"type":"Point"}
}