{
  "type": "Feature",
  "properties": {
    "iso:country":"NL",
    "sg:address":"Emmastraat 7",
    "sg:city":"Zuidland",
    "sg:classifiers":[
        {
            "category":"Education",
            "subcategory":"Preschool",
            "type":"Public Place"
        }
    ],
    "sg:phone":"+31 181 451 860",
    "sg:postcode":"3214 CC",
    "sg:province":"South Holland",
    "sg:tags":[
        "kleuteronderwijs",
        "basis-"
    ],
    "wof:name":"Openbare Basisschool De Wissel",
    "wof:placetype":"venue"
},
  "geometry": {"coordinates":[4.256245,51.823582],"type":"Point"}
}