{
  "type": "Feature",
  "properties": {
    "addr:full":"Verbindingswg 12 Wieringerwerf Noord-Holland 1771 BC",
    "addr:housenumber":"12",
    "addr:postcode":"1771 bc",
    "addr:street":"Verbindingswg",
    "iso:country":"NL",
    "sg:address":"Verbindingswg 12",
    "sg:city":"Wieringerwerf",
    "sg:orig_category":"Beveiliging",
    "sg:phone":"+31 227 600 599",
    "sg:postcode":"1771 BC",
    "sg:province":"Noord-Holland",
    "wof:name":"T Dew",
    "wof:placetype":"venue"
},
  "geometry": {"coordinates":[5.030556,52.851807],"type":"Point"}
}