{
  "type": "Feature",
  "properties": {
    "addr:full":"Kruiswg 1221 Hoofddorp Noord-Holland 2131 MD",
    "addr:housenumber":"1221",
    "addr:postcode":"hoofddorp;2131",
    "iso:country":"NL",
    "sg:address":"Kruiswg 1221",
    "sg:city":"Hoofddorp",
    "sg:orig_category":"Verzekeringen - Verzekeringskantoren",
    "sg:phone":"+31 23 562 3565",
    "sg:postcode":"2131 MD",
    "sg:province":"Noord-Holland",
    "wof:name":"Awp",
    "wof:placetype":"venue"
},
  "geometry": {"coordinates":[4.679003,52.313259],"type":"Point"}
}