{
  "type": "Feature",
  "properties": {
    "addr:full":"Driehoekstr 25 Roosendaal Noord-Brabant 4706 NC",
    "addr:housenumber":"25",
    "addr:postcode":"4706 nc",
    "addr:street":"Driehoekstr",
    "iso:country":"NL",
    "sg:address":"Driehoekstr 25",
    "sg:city":"Roosendaal",
    "sg:orig_category":"Banden",
    "sg:phone":"+31 165 562 626",
    "sg:postcode":"4706 NC",
    "sg:province":"Noord-Brabant",
    "sg:website":"http://www.brabobanden.nl",
    "wof:name":"Brabo Autobanden Bv",
    "wof:placetype":"venue"
},
  "geometry": {"coordinates":[4.494367,51.534718],"type":"Point"}
}