{
  "type": "Feature",
  "properties": {
    "iso:country":"NL",
    "sg:address":"Ridderhof 9",
    "sg:city":"Ede Gld",
    "sg:classifiers":[
        {
            "category":"Education",
            "subcategory":"Preschool",
            "type":"Public Place"
        }
    ],
    "sg:phone":"+31 318 638 625",
    "sg:postcode":"6715 EL",
    "sg:province":"Gelderland",
    "sg:tags":[
        "kleuteronderwijs",
        "basis-"
    ],
    "wof:name":"Openbare Basisschool De Delta Locatie De Prinsenho",
    "wof:placetype":"venue"
},
  "geometry": {"coordinates":[5.63239,52.042072],"type":"Point"}
}