{
  "type": "Feature",
  "properties": {
    "addr:full":"Frankenslag 317 Den Haag South Holland 2582 HM",
    "addr:housenumber":"317",
    "addr:postcode":"2582 hm",
    "addr:street":"Frankenslag",
    "iso:country":"NL",
    "sg:address":"Frankenslag 317",
    "sg:city":"Den Haag",
    "sg:orig_category":"Verloskundigen",
    "sg:phone":"+31 70 355 2287",
    "sg:postcode":"2582 HM",
    "sg:province":"South Holland",
    "wof:name":"Ketterl\u00e9, Sylvie",
    "wof:placetype":"venue"
},
  "geometry": {"coordinates":[4.272385,52.092678],"type":"Point"}
}