{
  "type": "Feature",
  "properties": {
    "addr:full":"Strawinskyln 1251 Amsterdam North Holland 1077 XX",
    "addr:housenumber":"1251",
    "addr:postcode":"1077 xx",
    "iso:country":"NL",
    "sg:address":"Strawinskyln 1251",
    "sg:city":"Amsterdam",
    "sg:orig_category":"Filmstudio'S En -Productie",
    "sg:phone":"+31 20 575 2014",
    "sg:postcode":"1077 XX",
    "sg:province":"North Holland",
    "wof:name":"Nippon Europe Bv",
    "wof:placetype":"venue"
},
  "geometry": {"coordinates":[4.874167,52.34066],"type":"Point"}
}