{
  "type": "Feature",
  "properties": {
    "addr:full":"Termyen 46 Heiloo Noord-Holland 1852 TC",
    "addr:housenumber":"46",
    "addr:postcode":"1852 tc",
    "addr:street":"Termyen",
    "iso:country":"NL",
    "sg:address":"Termyen 46",
    "sg:city":"Heiloo",
    "sg:orig_category":"Journalisten Freelance",
    "sg:phone":"+31 72 533 0358",
    "sg:postcode":"1852 TC",
    "sg:province":"Noord-Holland",
    "wof:name":"Voorberg, Marjolein",
    "wof:placetype":"venue"
},
  "geometry": {"coordinates":[4.713702,52.604191],"type":"Point"}
}