{
  "type": "Feature",
  "properties": {
    "addr:full":"Het Oelbred 7 Zuidlaren Provincie Drenthe 9472 WK",
    "addr:housenumber":"7",
    "addr:postcode":"9472 wk",
    "addr:street":"Het Oelbred;Provincie Drenthe",
    "iso:country":"NL",
    "sg:address":"Het Oelbred 7",
    "sg:city":"Zuidlaren",
    "sg:classifiers":[
        {
            "category":"Building & Trades",
            "subcategory":"Electrical",
            "type":"Services"
        }
    ],
    "sg:phone":"+31 50 409 4757",
    "sg:postcode":"9472 WK",
    "sg:province":"Provincie Drenthe",
    "sg:tags":[
        "distributor"
    ],
    "wof:name":"Life Logics",
    "wof:placetype":"venue"
},
  "geometry": {"coordinates":[6.692791,53.077412],"type":"Point"}
}