{
  "type": "Feature",
  "properties": {
    "iso:country":"NL",
    "sg:address":"Steentilstraat 48",
    "sg:city":"Groningen",
    "sg:orig_category":"Architecten",
    "sg:phone":"+31 50 312 9922",
    "sg:postcode":"9711 GP",
    "sg:province":"Groningen",
    "wof:name":"G'92 Tuininrichting",
    "wof:placetype":"venue"
},
  "geometry": {"coordinates":[6.573466,53.216885],"type":"Point"}
}