{
  "type": "Feature",
  "properties": {
    "addr:full":"Sterrenbergwg 7 Soesterberg Utrecht 3769 BS",
    "addr:housenumber":"7",
    "addr:postcode":"3769 bs",
    "addr:street":"Sterrenbergwg",
    "iso:country":"NL",
    "sg:address":"Sterrenbergwg 7",
    "sg:city":"Soesterberg",
    "sg:orig_category":"Keukens",
    "sg:phone":"+31 346 354 711",
    "sg:postcode":"3769 BS",
    "sg:province":"Utrecht",
    "sg:website":"http://www.lustig-keukenstudio.nl",
    "wof:name":"Lustig Keukenstudio",
    "wof:placetype":"venue"
},
  "geometry": {"coordinates":[5.278649,52.121506],"type":"Point"}
}