{
  "type": "Feature",
  "properties": {
    "addr:full":"Velpsestraat 209 'S Gravenhage Zuid-Holland 2573 SJ",
    "addr:housenumber":"209 ';2573",
    "addr:street":"Velpsestraat",
    "iso:country":"NL",
    "sg:address":"Velpsestraat 209",
    "sg:city":"'S Gravenhage",
    "sg:orig_category":"Artsen And Specialisten",
    "sg:phone":"+31 70 345 6967",
    "sg:postcode":"2573 SJ",
    "sg:province":"Zuid-Holland",
    "wof:name":"J.G. Wierda",
    "wof:placetype":"venue"
},
  "geometry": {"coordinates":[4.283652,52.063465],"type":"Point"}
}