{
  "type": "Feature",
  "properties": {
    "iso:country":"NL",
    "sg:address":"Oranjeln 36",
    "sg:city":"Amersfoort",
    "sg:orig_category":"Acupunctuur",
    "sg:phone":"+31 33 461 7309",
    "sg:postcode":"3818 GR",
    "sg:province":"Utrecht",
    "wof:name":"Trompert-Nauta, M G",
    "wof:placetype":"venue"
},
  "geometry": {"coordinates":[5.361548,52.145027],"type":"Point"}
}