{
  "type": "Feature",
  "properties": {
    "addr:full":"Kadijksplein 15 Amsterdam Noord-Holland 1018 AC",
    "addr:housenumber":"15",
    "addr:postcode":"1018 ac",
    "addr:street":"Kadijksplein",
    "iso:country":"NL",
    "sg:address":"Kadijksplein 15",
    "sg:city":"Amsterdam",
    "sg:orig_category":"Binnenhuisarchitecten",
    "sg:phone":"+31 20 623 2317",
    "sg:postcode":"1018 AC",
    "sg:province":"Noord-Holland",
    "wof:name":"Henk De Kievit Binnenhuisarchitekt",
    "wof:placetype":"venue"
},
  "geometry": {"coordinates":[4.912687,52.370251],"type":"Point"}
}