{
  "type": "Feature",
  "properties": {
    "addr:full":"Groene Zoom 76 Ten Boer Groningen 9791 BD",
    "addr:housenumber":"76",
    "addr:postcode":"boer;9791 bd",
    "addr:street":"Groene Zoom",
    "iso:country":"NL",
    "sg:address":"Groene Zoom 76",
    "sg:city":"Ten Boer",
    "sg:orig_category":"Jachten - Schilderwerken En Onderhoud",
    "sg:phone":"+31 50 302 3090",
    "sg:postcode":"9791 BD",
    "sg:province":"Groningen",
    "wof:name":"Kuilman",
    "wof:placetype":"venue"
},
  "geometry": {"coordinates":[6.688239,53.273308],"type":"Point"}
}