{
  "type": "Feature",
  "properties": {
    "addr:full":"Nw Zandw 12 Linschoten Utrecht 3461 AH",
    "addr:housenumber":"12",
    "addr:postcode":"3461 ah",
    "addr:street":"Zandw",
    "iso:country":"NL",
    "sg:address":"Nw Zandw 12",
    "sg:city":"Linschoten",
    "sg:orig_category":"Verenigingsgebouwen",
    "sg:phone":"+31 348 410 545",
    "sg:postcode":"3461 AH",
    "sg:province":"Utrecht",
    "wof:name":"Tol, Bij De",
    "wof:placetype":"venue"
},
  "geometry": {"coordinates":[4.917766,52.060287],"type":"Point"}
}