{
  "type": "Feature",
  "properties": {
    "addr:full":"Veenbesstraat 12 Uffelte Drenthe 7975 BD",
    "addr:housenumber":"12",
    "addr:postcode":"7975 bd",
    "addr:street":"Veenbesstraat",
    "iso:country":"NL",
    "sg:address":"Veenbesstraat 12",
    "sg:city":"Uffelte",
    "sg:orig_category":"Onderhoud And Reparatie Kantoorapparatuur",
    "sg:phone":"+31 521 351 733",
    "sg:postcode":"7975 BD",
    "sg:province":"Drenthe",
    "wof:name":"D & S Systems",
    "wof:placetype":"venue"
},
  "geometry": {"coordinates":[6.2806,52.79031],"type":"Point"}
}