{
  "type": "Feature",
  "properties": {
    "iso:country":"NL",
    "sg:address":"Spoorstr 15",
    "sg:city":"Borculo",
    "sg:orig_category":"Cafetaria'S",
    "sg:phone":"+31 545 275 122",
    "sg:postcode":"7271 CA",
    "sg:province":"Gelderland",
    "wof:name":"Vierspan, 'T",
    "wof:placetype":"venue"
},
  "geometry": {"coordinates":[6.522943,52.118141],"type":"Point"}
}