{
  "type": "Feature",
  "properties": {
    "addr:full":"Pr Bernhardstr 2 Hilversum Noord-Holland 1211 GK",
    "addr:housenumber":"2",
    "addr:postcode":"1211 gk",
    "iso:country":"NL",
    "sg:address":"Pr Bernhardstr 2",
    "sg:city":"Hilversum",
    "sg:orig_category":"Juridische Adviseurs",
    "sg:phone":"+31 35 624 1757",
    "sg:postcode":"1211 GK",
    "sg:province":"Noord-Holland",
    "wof:name":"Geurten Cs, Fiscaal Juristen",
    "wof:placetype":"venue"
},
  "geometry": {"coordinates":[5.1695,52.228565],"type":"Point"}
}