{
  "type": "Feature",
  "properties": {
    "addr:full":"Achter De Kerk 7 Leerdam Zuid-Holland 4141 CJ",
    "addr:housenumber":"7",
    "addr:postcode":"4141 cj",
    "addr:street":"Achter De Kerk",
    "iso:country":"NL",
    "sg:address":"Achter De Kerk 7",
    "sg:city":"Leerdam",
    "sg:orig_category":"Kappers",
    "sg:phone":"+31 6 54683114",
    "sg:postcode":"4141 CJ",
    "sg:province":"Zuid-Holland",
    "wof:name":"Coiffeuse, La",
    "wof:placetype":"venue"
},
  "geometry": {"coordinates":[5.0924019814,51.8909988403],"type":"Point"}
}