{
  "type": "Feature",
  "properties": {
    "addr:full":"Generaal Vetterstraat 71 Amsterdam North Holland 1059 BT",
    "addr:housenumber":"71",
    "addr:postcode":"1059 bt",
    "addr:street":"Generaal Vetterstraat",
    "iso:country":"NL",
    "sg:address":"Generaal Vetterstraat 71",
    "sg:city":"Amsterdam",
    "sg:orig_category":"Film-, Tv- And Videoproductie",
    "sg:phone":"+31 20 615 0207",
    "sg:postcode":"1059 BT",
    "sg:province":"North Holland",
    "wof:name":"Vbc Video Broadcast Centre",
    "wof:placetype":"venue"
},
  "geometry": {"coordinates":[4.846965,52.344315],"type":"Point"}
}