{
  "type": "Feature",
  "properties": {
    "addr:full":"Westerdreef 1 Nieuw Vennep North Holland 2152 CS",
    "addr:housenumber":"1",
    "addr:postcode":"2152 cs",
    "addr:street":"Westerdreef;Nieuw Vennep North",
    "iso:country":"NL",
    "sg:address":"Westerdreef 1",
    "sg:city":"Nieuw Vennep",
    "sg:orig_category":"Verzekeringen",
    "sg:phone":"+31 252 621 232",
    "sg:postcode":"2152 CS",
    "sg:province":"North Holland",
    "wof:name":"Evident Advies Groep",
    "wof:placetype":"venue"
},
  "geometry": {"coordinates":[4.630491,52.271763],"type":"Point"}
}