{
  "type": "Feature",
  "properties": {
    "addr:full":"Kempenaar 2433 Lelystad NL. 8231 GJ",
    "addr:postcode":"2433;8231 gj",
    "addr:street":"Kempenaar;Nl.",
    "iso:country":"NL",
    "sg:address":"Kempenaar 2433",
    "sg:city":"Lelystad",
    "sg:orig_category":"Administratie- En Boekhoudkantoren",
    "sg:phone":"+31 320 234 440",
    "sg:postcode":"8231 GJ",
    "sg:province":"NL.",
    "wof:name":"Admi-Account",
    "wof:placetype":"venue"
},
  "geometry": {"coordinates":[5.468061,52.51749],"type":"Point"}
}