{
  "type": "Feature",
  "properties": {
    "addr:full":"Nummer 4 Nijhuizum Friesland 8775 XD",
    "addr:postcode":"8775 xd",
    "iso:country":"NL",
    "sg:address":"Nummer 4",
    "sg:city":"Nijhuizum",
    "sg:orig_category":"Kampeerterreinen",
    "sg:phone":"+31 515 542 281",
    "sg:postcode":"8775 XD",
    "sg:province":"Friesland",
    "wof:name":"Minicamping Sathe Landzicht",
    "wof:placetype":"venue"
},
  "geometry": {"coordinates":[5.4844450951,52.9788742065],"type":"Point"}
}