{
  "type": "Feature",
  "properties": {
    "addr:full":"Gaspeldoorn 22 Bladel Noord-Brabant 5531 CH",
    "addr:housenumber":"22",
    "addr:postcode":"5531",
    "addr:street":"Gaspeldoorn",
    "iso:country":"NL",
    "sg:address":"Gaspeldoorn 22",
    "sg:city":"Bladel",
    "sg:orig_category":"Wasmachines En Wasdrogers - Onderhoud En Reparatie",
    "sg:phone":"+31 497 386 124",
    "sg:postcode":"5531 CH",
    "sg:province":"Noord-Brabant",
    "wof:name":"Maas, Elektra",
    "wof:placetype":"venue"
},
  "geometry": {"coordinates":[5.2271509171,51.3680534363],"type":"Point"}
}