{
  "type": "Feature",
  "properties": {
    "addr:full":"Sir W Churchillln 231A Ryswyk Zh South Holland 2282 JS",
    "addr:housenumber":"231a;zh",
    "addr:postcode":"2282 js",
    "addr:street":"Sir W Churchillln",
    "iso:country":"NL",
    "sg:address":"Sir W Churchillln 231A",
    "sg:city":"Ryswyk Zh",
    "sg:orig_category":"Bloemen En Planten - Decoratie",
    "sg:phone":"+31 70 415 5566",
    "sg:postcode":"2282 JS",
    "sg:province":"South Holland",
    "wof:name":"Tuinwinkel Ryswyk",
    "wof:placetype":"venue"
},
  "geometry": {"coordinates":[4.33694,52.056503],"type":"Point"}
}