{
  "type": "Feature",
  "properties": {
    "addr:full":"Duivenpad 12 Rotterdam Zuid-Holland 3055 VE",
    "addr:housenumber":"12",
    "addr:postcode":"3055",
    "addr:street":"Duivenpad;Ve",
    "iso:country":"NL",
    "sg:address":"Duivenpad 12",
    "sg:city":"Rotterdam",
    "sg:orig_category":"Fitnesscentra",
    "sg:phone":"+31 10 218 0035",
    "sg:postcode":"3055 VE",
    "sg:province":"Zuid-Holland",
    "wof:name":"Bodystudio",
    "wof:placetype":"venue"
},
  "geometry": {"coordinates":[4.498368,51.965034],"type":"Point"}
}