{
  "type": "Feature",
  "properties": {
    "addr:full":"Van Delftstraat 27 Wildervank Groningen 9648 CM",
    "addr:housenumber":"27",
    "addr:postcode":"9648 cm",
    "addr:street":"Van Delftstraat",
    "iso:country":"NL",
    "sg:address":"Van Delftstraat 27",
    "sg:city":"Wildervank",
    "sg:orig_category":"Fitnesscentra",
    "sg:phone":"+31 598 615 827",
    "sg:postcode":"9648 CM",
    "sg:province":"Groningen",
    "wof:name":"Sportcentrum Tors-Gijm",
    "wof:placetype":"venue"
},
  "geometry": {"coordinates":[6.864215,53.083775],"type":"Point"}
}