{
  "type": "Feature",
  "properties": {
    "iso:country":"NL",
    "sg:address":"Vd Helstpln 4",
    "sg:city":"Amsterdam",
    "sg:orig_category":"Hoeden",
    "sg:phone":"+31 20 664 7748",
    "sg:postcode":"1072 PH",
    "sg:province":"Noord-Holland",
    "sg:website":"http://www.madhatter.nl",
    "wof:name":"Madhatter, The",
    "wof:placetype":"venue"
},
  "geometry": {"coordinates":[-74.11945299999999,42.944771],"type":"Point"}
}