{
  "type": "Feature",
  "properties": {
    "iso:country":"NL",
    "sg:address":"Geldersestraat 21",
    "sg:city":"Amersfoort",
    "sg:classifiers":[
        {
            "category":"Retail",
            "subcategory":"Storage",
            "type":"Services"
        }
    ],
    "sg:phone":"+31 33 463 8630",
    "sg:postcode":"3812 PP",
    "sg:province":"Utrecht",
    "sg:tags":[
        "opslag",
        "bewaring"
    ],
    "wof:name":"Meubeltransportonderneming H. Bunk & Zn Bv",
    "wof:placetype":"venue"
},
  "geometry": {"coordinates":[5.3740978241,52.1615867615],"type":"Point"}
}