{
  "type": "Feature",
  "properties": {
    "iso:country":"NL",
    "sg:address":"Binnenhaven 50",
    "sg:city":"Den Helder",
    "sg:orig_category":"Bedrijfsinventaris Gh",
    "sg:phone":"+31 223 669 255",
    "sg:postcode":"1781 BL",
    "sg:province":"North Holland",
    "wof:name":"Nus Cool",
    "wof:placetype":"venue"
},
  "geometry": {"coordinates":[4.775709,52.954315],"type":"Point"}
}