{
  "type": "Feature",
  "properties": {
    "iso:country":"NL",
    "sg:address":"Pastoor Meijndersstraat 11",
    "sg:city":"Tuitjenhorn",
    "sg:orig_category":"Bedrijfs- And Managementsconsultants",
    "sg:phone":"+31 226 393 756",
    "sg:postcode":"1747 ER",
    "sg:province":"North Holland",
    "wof:name":"E Van Lierop-Beemsterboer",
    "wof:placetype":"venue"
},
  "geometry": {"coordinates":[4.7545,52.73962],"type":"Point"}
}