{
  "type": "Feature",
  "properties": {
    "addr:full":"Helvoirtseweg 146 Vught Noord-Brabant 5263 EH",
    "addr:housenumber":"146",
    "addr:postcode":"5263 eh",
    "addr:street":"Helvoirtseweg",
    "iso:country":"NL",
    "sg:address":"Helvoirtseweg 146",
    "sg:city":"Vught",
    "sg:orig_category":"Verhuur Kantoorapparatuur",
    "sg:phone":"+31 73 657 9050",
    "sg:postcode":"5263 EH",
    "sg:province":"Noord-Brabant",
    "wof:name":"Equi Rent Bv",
    "wof:placetype":"venue"
},
  "geometry": {"coordinates":[5.285778,51.655231],"type":"Point"}
}