{
  "type": "Feature",
  "properties": {
    "addr:full":"Flamingowg 48 Luchth Schiphol North Holland 1118 EE",
    "addr:housenumber":"48",
    "addr:postcode":"1118 ee",
    "addr:street":"Flamingowg",
    "iso:country":"NL",
    "sg:address":"Flamingowg 48",
    "sg:city":"Luchth Schiphol",
    "sg:orig_category":"Luchtvaart- Maatschappijen",
    "sg:phone":"+31 20 653 6152",
    "sg:postcode":"1118 EE",
    "sg:province":"North Holland",
    "wof:name":"Air Algerie",
    "wof:placetype":"venue"
},
  "geometry": {"coordinates":[4.735026,52.29171],"type":"Point"}
}