{
  "type": "Feature",
  "properties": {
    "addr:full":"Bongerd 4 Capelle A/D Ijssel Zuid-Holland 2906 VK",
    "addr:housenumber":"4;a / d",
    "addr:postcode":"2906 vk",
    "addr:street":"Bongerd",
    "iso:country":"NL",
    "sg:address":"Bongerd 4",
    "sg:city":"Capelle A/D Ijssel",
    "sg:classifiers":[
        {
            "category":"Education",
            "subcategory":"Preschool",
            "type":"Public Place"
        }
    ],
    "sg:phone":"+31 10 450 8968",
    "sg:postcode":"2906 VK",
    "sg:province":"Zuid-Holland",
    "sg:tags":[
        "kleuteronderwijs",
        "basis-"
    ],
    "wof:name":"Gereformeerde Basisschool De Triangel",
    "wof:placetype":"venue"
},
  "geometry": {"coordinates":[4.566161,51.933426],"type":"Point"}
}