{
  "type": "Feature",
  "properties": {
    "addr:full":"Amaliastein 155 Vianen Zh South Holland 4133 JL",
    "addr:housenumber":"155",
    "addr:postcode":"zh;4133 jl",
    "addr:street":"Amaliastein",
    "iso:country":"NL",
    "sg:address":"Amaliastein 155",
    "sg:city":"Vianen Zh",
    "sg:orig_category":"Dansscholen",
    "sg:phone":"+31 347 374 980",
    "sg:postcode":"4133 JL",
    "sg:province":"South Holland",
    "wof:name":"Sylvia'S Jazz, Keep-Fit",
    "wof:placetype":"venue"
},
  "geometry": {"coordinates":[5.072724,51.988102],"type":"Point"}
}