{
  "type": "Feature",
  "properties": {
    "addr:full":"L Biesakkerswg 3 Numansdorp Zuid-Holland 3281 NA",
    "addr:housenumber":"3",
    "addr:postcode":"3281 na",
    "iso:country":"NL",
    "sg:address":"L Biesakkerswg 3",
    "sg:city":"Numansdorp",
    "sg:orig_category":"Ongediertebestrijding En Ontsmetting",
    "sg:phone":"+31 186 651 766",
    "sg:postcode":"3281 NA",
    "sg:province":"Zuid-Holland",
    "wof:name":"Bogaerds Bv, Harry",
    "wof:placetype":"venue"
},
  "geometry": {"coordinates":[4.455408,51.752026],"type":"Point"}
}