{
  "type": "Feature",
  "properties": {
    "addr:full":"Venekoterweg 3 Oosterwolde Fr Friesland 8431 HG",
    "addr:housenumber":"3",
    "addr:postcode":"8431 hg",
    "addr:street":"Venekoterweg",
    "iso:country":"NL",
    "sg:address":"Venekoterweg 3",
    "sg:city":"Oosterwolde Fr",
    "sg:orig_category":"Voeding, Dranken And Tabak Gh",
    "sg:phone":"+31 516 568 899",
    "sg:postcode":"8431 HG",
    "sg:province":"Friesland",
    "wof:name":"Fanofinefood Bv",
    "wof:placetype":"venue"
},
  "geometry": {"coordinates":[6.301853,52.985741],"type":"Point"}
}