{
  "type": "Feature",
  "properties": {
    "addr:full":"Stougjesdijk 290 Oud Beijerland South Holland 3261 KW",
    "addr:housenumber":"290",
    "addr:postcode":"3261 kw",
    "addr:street":"Stougjesdijk;Oud Beijerland",
    "iso:country":"NL",
    "sg:address":"Stougjesdijk 290",
    "sg:city":"Oud Beijerland",
    "sg:classifiers":[
        {
            "category":"Sports & Exercise",
            "subcategory":"Stables",
            "type":"Entertainment"
        }
    ],
    "sg:phone":"+31 186 619 771",
    "sg:postcode":"3261 KW",
    "sg:province":"South Holland",
    "sg:tags":[
        "maneges"
    ],
    "wof:name":"Greup, De",
    "wof:placetype":"venue"
},
  "geometry": {"coordinates":[4.44102,51.81987],"type":"Point"}
}