{
  "type": "Feature",
  "properties": {
    "iso:country":"NL",
    "sg:address":"Alberdingk Thijmstraat 31",
    "sg:city":"Venlo",
    "sg:orig_category":"Kappers",
    "sg:phone":"+31 77 382 1668",
    "sg:postcode":"5921 BA",
    "sg:province":"Limburg",
    "wof:name":"Vof Kapsalon Hutjens",
    "wof:placetype":"venue"
},
  "geometry": {"coordinates":[6.145912,51.366959],"type":"Point"}
}