{
  "type": "Feature",
  "properties": {
    "addr:full":"Rossinistr 103 Tilburg Noord-Brabant 5049 KB",
    "addr:housenumber":"103",
    "addr:postcode":"5049 kb",
    "addr:street":"Tilburg",
    "iso:country":"NL",
    "sg:address":"Rossinistr 103",
    "sg:city":"Tilburg",
    "sg:orig_category":"Woningtextiel",
    "sg:phone":"+31 13 456 2585",
    "sg:postcode":"5049 KB",
    "sg:province":"Noord-Brabant",
    "wof:name":"Fullyat",
    "wof:placetype":"venue"
},
  "geometry": {"coordinates":[5.078327179,51.5925559998],"type":"Point"}
}