{
  "type": "Feature",
  "properties": {
    "addr:full":"Griendtsveenstr 150 Erica Drenthe 7887 TK",
    "addr:housenumber":"150",
    "addr:postcode":"7887 tk",
    "addr:street":"Erica Drenthe",
    "iso:country":"NL",
    "sg:address":"Griendtsveenstr 150",
    "sg:city":"Erica",
    "sg:orig_category":"Musea",
    "sg:phone":"+31 6 11111188",
    "sg:postcode":"7887 TK",
    "sg:province":"Drenthe",
    "sg:website":"http://www.smalspoorcentrum.nl",
    "wof:name":"Industrieel Smalspoor Museum",
    "wof:placetype":"venue"
},
  "geometry": {"coordinates":[6.949344,52.67783],"type":"Point"}
}