{
  "type": "Feature",
  "properties": {
    "addr:full":"Boterstraat 9 Joure Provincie Friesland 8501 BS",
    "addr:housenumber":"9",
    "addr:postcode":"8501 bs",
    "addr:street":"Boterstraat;Provincie Friesland",
    "iso:country":"NL",
    "sg:address":"Boterstraat 9",
    "sg:city":"Joure",
    "sg:orig_category":"Drukkerijen And Copyshops",
    "sg:phone":"+31 513 416 535",
    "sg:postcode":"8501 BS",
    "sg:province":"Provincie Friesland",
    "wof:name":"Sneldrukkerij Print Shop",
    "wof:placetype":"venue"
},
  "geometry": {"coordinates":[5.794462,52.969563],"type":"Point"}
}