{
  "type": "Feature",
  "properties": {
    "addr:full":"Raadhuisstr 21 Leerbroek South Holland 4245 KG",
    "addr:housenumber":"21",
    "addr:postcode":"4245 kg",
    "addr:street":"Raadhuisstr",
    "iso:country":"NL",
    "sg:address":"Raadhuisstr 21",
    "sg:city":"Leerbroek",
    "sg:orig_category":"Woningstoffeerders",
    "sg:phone":"+31 345 599 572",
    "sg:postcode":"4245 KG",
    "sg:province":"South Holland",
    "wof:name":"Berg, Guus Van Den",
    "wof:placetype":"venue"
},
  "geometry": {"coordinates":[5.050593853,51.9092254639],"type":"Point"}
}