{
  "type": "Feature",
  "properties": {
    "addr:full":"Prins Hendriklaan 29 Amsterdam Noord-Holland 1075 AZ",
    "addr:housenumber":"29",
    "addr:postcode":"1075 az",
    "addr:street":"Prins Hendriklaan",
    "iso:country":"NL",
    "sg:address":"Prins Hendriklaan 29",
    "sg:city":"Amsterdam",
    "sg:orig_category":"Werving And Selectie Van Vast Personeel",
    "sg:phone":"+31 20 572 5725",
    "sg:postcode":"1075 AZ",
    "sg:province":"Noord-Holland",
    "wof:name":"Kpmg Ebbinge",
    "wof:placetype":"venue"
},
  "geometry": {"coordinates":[4.862185955,52.3536148071],"type":"Point"}
}