{
  "type": "Feature",
  "properties": {
    "addr:full":"Hildebrandlaan 29 Soest Utrecht 3768 GV",
    "addr:housenumber":"29",
    "addr:postcode":"3768 gv",
    "addr:street":"Hildebrandlaan",
    "iso:country":"NL",
    "sg:address":"Hildebrandlaan 29",
    "sg:city":"Soest",
    "sg:orig_category":"Juridische Dienstverlening",
    "sg:phone":"+31 35 601 5476",
    "sg:postcode":"3768 GV",
    "sg:province":"Utrecht",
    "wof:name":"Buro V Zak. Rechtsbyst. Mr.Drs. E.A. Barki",
    "wof:placetype":"venue"
},
  "geometry": {"coordinates":[5.314062,52.159073],"type":"Point"}
}