{
  "type": "Feature",
  "properties": {
    "iso:country":"NL",
    "sg:address":"Nyverheidswg 4",
    "sg:city":"Nyeveen",
    "sg:orig_category":"Kisten - Fabrieken En Groothandel",
    "sg:phone":"+31 522 281 670",
    "sg:postcode":"7948 NE",
    "sg:province":"Drenthe",
    "wof:name":"Robox Klusbedr & Expkisten Vof",
    "wof:placetype":"venue"
},
  "geometry": {"coordinates":[6.160105,52.725842],"type":"Point"}
}