{
  "type": "Feature",
  "properties": {
    "iso:country":"NL",
    "sg:address":"Paul Krugerstraat 22",
    "sg:city":"Katwijk Zh",
    "sg:classifiers":[
        {
            "category":"Travel",
            "subcategory":"Hotels & Motels",
            "type":"Entertainment"
        }
    ],
    "sg:phone":"+31 71 407 7821",
    "sg:postcode":"2225 ZK",
    "sg:province":"South Holland",
    "wof:name":"Pension Janine",
    "wof:placetype":"venue"
},
  "geometry": {"coordinates":[4.398293,52.206326],"type":"Point"}
}