{
  "type": "Feature",
  "properties": {
    "addr:full":"Prins Hendrikkade 170 Amsterdam North Holland 1011 TC",
    "addr:housenumber":"170",
    "addr:postcode":"1011 tc",
    "addr:street":"Prins Hendrikkade",
    "iso:country":"NL",
    "sg:address":"Prins Hendrikkade 170",
    "sg:city":"Amsterdam",
    "sg:orig_category":"Film-, Tv- And Videoproductie",
    "sg:phone":"+31 20 427 4871",
    "sg:postcode":"1011 TC",
    "sg:province":"North Holland",
    "wof:name":"Avitors",
    "wof:placetype":"venue"
},
  "geometry": {"coordinates":[4.909671,52.371742],"type":"Point"}
}