{
  "type": "Feature",
  "properties": {
    "addr:full":"Zwaluw 4 Boxmeer Noord-Brabant 5831 ML",
    "addr:housenumber":"4",
    "addr:postcode":"5831 ml",
    "addr:street":"Zwaluw",
    "iso:country":"NL",
    "sg:address":"Zwaluw 4",
    "sg:city":"Boxmeer",
    "sg:orig_category":"Diverse Grafische Activiteiten",
    "sg:phone":"+31 485 573 681",
    "sg:postcode":"5831 ML",
    "sg:province":"Noord-Brabant",
    "wof:name":"M. Ermers",
    "wof:placetype":"venue"
},
  "geometry": {"coordinates":[5.951107,51.641022],"type":"Point"}
}