{
  "type": "Feature",
  "properties": {
    "addr:full":"Ribeslaan 5 Wageningen Gelderland 6706 CG",
    "addr:housenumber":"5",
    "addr:postcode":"6706 cg",
    "addr:street":"Ribeslaan;Gelderland",
    "iso:country":"NL",
    "sg:address":"Ribeslaan 5",
    "sg:city":"Wageningen",
    "sg:orig_category":"Kappers",
    "sg:phone":"+31 317 425 515",
    "sg:postcode":"6706 CG",
    "sg:province":"Gelderland",
    "wof:name":"De Huiskapper",
    "wof:placetype":"venue"
},
  "geometry": {"coordinates":[5.679901123,51.9722099304],"type":"Point"}
}