{
  "type": "Feature",
  "properties": {
    "iso:country":"NL",
    "sg:address":"Debussystr 33",
    "sg:city":"Culemborg",
    "sg:orig_category":"Adviesbureaus Bedrijfsorganisatie",
    "sg:phone":"+31 345 558 747",
    "sg:postcode":"4102 AR",
    "sg:province":"Gelderland",
    "sg:website":"http://www.es-intermark.nl",
    "wof:name":"Es-Intermark",
    "wof:placetype":"venue"
},
  "geometry": {"coordinates":[5.236804,51.952713],"type":"Point"}
}