{
  "type": "Feature",
  "properties": {
    "addr:full":"Bergseln 200 Rotterdam Zuid-Holland 3037 CL",
    "addr:housenumber":"200",
    "addr:postcode":"3037",
    "iso:country":"NL",
    "sg:address":"Bergseln 200",
    "sg:city":"Rotterdam",
    "sg:orig_category":"Makelaars En Adviseurs Onroerende Goederen",
    "sg:phone":"+31 10 467 6363",
    "sg:postcode":"3037 CL",
    "sg:province":"Zuid-Holland",
    "sg:website":"http://www.beleggingsmakelaar.nl",
    "wof:name":"Riverstate",
    "wof:placetype":"venue"
},
  "geometry": {"coordinates":[4.47342,51.938129],"type":"Point"}
}