{
  "type": "Feature",
  "properties": {
    "addr:full":"Langstraat 7 Wassenaar Zuid-Holland 2242 KJ",
    "addr:housenumber":"7",
    "addr:postcode":"2242 kj",
    "addr:street":"Langstraat",
    "iso:country":"NL",
    "sg:address":"Langstraat 7",
    "sg:city":"Wassenaar",
    "sg:orig_category":"Opticiens",
    "sg:phone":"+31 70 511 4396",
    "sg:postcode":"2242 KJ",
    "sg:province":"Zuid-Holland",
    "wof:name":"Bril 58",
    "wof:placetype":"venue"
},
  "geometry": {"coordinates":[4.3921880722,52.1449317932],"type":"Point"}
}