{
  "type": "Feature",
  "properties": {
    "addr:full":"K Promenade 5 Almere NL. 1315 HM",
    "addr:housenumber":"5",
    "addr:postcode":"1315 hm",
    "addr:street":"K Promenade;Nl.",
    "iso:country":"NL",
    "sg:address":"K Promenade 5",
    "sg:city":"Almere",
    "sg:orig_category":"Broodjeszaken",
    "sg:phone":"+31 36 533 3852",
    "sg:postcode":"1315 HM",
    "sg:province":"NL.",
    "wof:name":"Delifrance",
    "wof:placetype":"venue"
},
  "geometry": {"coordinates":[5.21998,52.374531],"type":"Point"}
}