{
  "type": "Feature",
  "properties": {
    "addr:full":"Kerkln 28 Lopik Utrecht 3411 EN",
    "addr:housenumber":"28",
    "addr:postcode":"3411 en",
    "addr:street":"Kerkln",
    "iso:country":"NL",
    "sg:address":"Kerkln 28",
    "sg:city":"Lopik",
    "sg:orig_category":"Wasmachines En Wasdrogers - Onderhoud En Reparatie",
    "sg:phone":"+31 348 553 590",
    "sg:postcode":"3411 EN",
    "sg:province":"Utrecht",
    "wof:name":"Straver",
    "wof:placetype":"venue"
},
  "geometry": {"coordinates":[4.9452857971,51.9746704102],"type":"Point"}
}