{
  "type": "Feature",
  "properties": {
    "addr:full":"Fornheselaan 162 Den Dolder Utrecht 3734 GE",
    "addr:housenumber":"162",
    "addr:postcode":"3734",
    "addr:street":"Fornheselaan",
    "iso:country":"NL",
    "sg:address":"Fornheselaan 162",
    "sg:city":"Den Dolder",
    "sg:orig_category":"Autokeuringen",
    "sg:phone":"+31 30 228 8383",
    "sg:postcode":"3734 GE",
    "sg:province":"Utrecht",
    "wof:name":"Harley Davidson Parts For Sale",
    "wof:placetype":"venue"
},
  "geometry": {"coordinates":[5.248972,52.140701],"type":"Point"}
}