{
  "type": "Feature",
  "properties": {
    "addr:full":"Bleyenbeek 2 Roden Drenthe 9301 XR",
    "addr:housenumber":"2",
    "addr:postcode":"9301 xr",
    "addr:street":"Bleyenbeek",
    "iso:country":"NL",
    "sg:address":"Bleyenbeek 2",
    "sg:city":"Roden",
    "sg:orig_category":"Vakorganisaties",
    "sg:phone":"+31 50 501 0326",
    "sg:postcode":"9301 XR",
    "sg:province":"Drenthe",
    "wof:name":"Fnv",
    "wof:placetype":"venue"
},
  "geometry": {"coordinates":[6.432945,53.137001],"type":"Point"}
}