{
  "type": "Feature",
  "properties": {
    "iso:country":"NL",
    "sg:address":"Grt Mydrechtstr 42",
    "sg:city":"Mydrecht",
    "sg:orig_category":"Horecabenodigdheden",
    "sg:phone":"+31 297 282 341",
    "sg:postcode":"3641 RW",
    "sg:province":"Utrecht",
    "sg:website":"http://www.emga.com",
    "wof:name":"Emga International Bv",
    "wof:placetype":"venue"
},
  "geometry": {"coordinates":[4.86178,52.20578],"type":"Point"}
}