{
  "type": "Feature",
  "properties": {
    "addr:full":"Kerkebreek 7 Landsmeer Noord-Holland 1121 KB",
    "addr:housenumber":"7",
    "addr:postcode":"1121 kb",
    "addr:street":"Kerkebreek",
    "iso:country":"NL",
    "sg:address":"Kerkebreek 7",
    "sg:city":"Landsmeer",
    "sg:orig_category":"Airconditioning",
    "sg:phone":"+31 20 463 5377",
    "sg:postcode":"1121 KB",
    "sg:province":"Noord-Holland",
    "sg:website":"http://www.dcwinstallatietechniek.nl",
    "wof:name":"Dcw, Installatietechniek",
    "wof:placetype":"venue"
},
  "geometry": {"coordinates":[4.910736,52.427006],"type":"Point"}
}