{
  "type": "Feature",
  "properties": {
    "addr:full":"Heeswyk 101B Montfoort Utrecht 3417 GP",
    "addr:housenumber":"101b",
    "addr:postcode":"3417 gp",
    "iso:country":"NL",
    "sg:address":"Heeswyk 101B",
    "sg:city":"Montfoort",
    "sg:orig_category":"Airconditioning",
    "sg:phone":"+31 348 472 247",
    "sg:postcode":"3417 GP",
    "sg:province":"Utrecht",
    "sg:website":"http://www.blr-bimon.nl",
    "wof:name":"Blr & Bimon Bv",
    "wof:placetype":"venue"
},
  "geometry": {"coordinates":[4.946729,52.044067],"type":"Point"}
}