{
  "type": "Feature",
  "properties": {
    "addr:full":"Stocreve 15 Goor Overijssel 7471 TN",
    "addr:housenumber":"15",
    "addr:postcode":"7471",
    "addr:street":"Stocreve",
    "iso:country":"NL",
    "sg:address":"Stocreve 15",
    "sg:city":"Goor",
    "sg:orig_category":"Schilders",
    "sg:phone":"+31 547 261 505",
    "sg:postcode":"7471 TN",
    "sg:province":"Overijssel",
    "wof:name":"Doorn-Meesterschilders, Van",
    "wof:placetype":"venue"
},
  "geometry": {"coordinates":[6.596746,52.242489],"type":"Point"}
}