{
  "type": "Feature",
  "properties": {
    "iso:country":"NL",
    "sg:address":"Stocreve 15",
    "sg:city":"Goor",
    "sg:orig_category":"Schilders",
    "sg:phone":"+31 547 261 505",
    "sg:postcode":"7471 TN",
    "sg:province":"Overijssel",
    "wof:name":"Doorn-Meesterschilders, Van",
    "wof:placetype":"venue"
},
  "geometry": {"coordinates":[6.596746,52.242489],"type":"Point"}
}