{
  "type": "Feature",
  "properties": {
    "addr:full":"Torenstr 26 Drachten Friesland 9203 BG",
    "addr:housenumber":"26",
    "addr:postcode":"9203",
    "addr:street":"Torenstr",
    "iso:country":"NL",
    "sg:address":"Torenstr 26",
    "sg:city":"Drachten",
    "sg:orig_category":"Projectontwikkeling",
    "sg:phone":"+31 512 524 355",
    "sg:postcode":"9203 BG",
    "sg:province":"Friesland",
    "wof:name":"Isopr\u00e9 Bv",
    "wof:placetype":"venue"
},
  "geometry": {"coordinates":[6.100561,53.109737],"type":"Point"}
}