{
  "type": "Feature",
  "properties": {
    "addr:full":"Vooronder 12 Elburg Gelderland 8081 NK",
    "addr:housenumber":"12",
    "addr:postcode":"8081 nk",
    "addr:street":"Vooronder;Gelderland",
    "iso:country":"NL",
    "sg:address":"Vooronder 12",
    "sg:city":"Elburg",
    "sg:orig_category":"Verlichting And Huishoudartikelen",
    "sg:phone":"+31 525 685 675",
    "sg:postcode":"8081 NK",
    "sg:province":"Gelderland",
    "wof:name":"De Kleine Huishoudbeurs",
    "wof:placetype":"venue"
},
  "geometry": {"coordinates":[5.854188,52.451962],"type":"Point"}
}