{
  "type": "Feature",
  "properties": {
    "addr:full":"Steegoversloot 26 Dordrecht South Holland 3311 PP",
    "addr:housenumber":"26",
    "addr:postcode":"3311 pp",
    "addr:street":"Steegoversloot",
    "iso:country":"NL",
    "sg:address":"Steegoversloot 26",
    "sg:city":"Dordrecht",
    "sg:orig_category":"Fotostudio'S And Fotografen",
    "sg:phone":"+31 78 614 8752",
    "sg:postcode":"3311 PP",
    "sg:province":"South Holland",
    "wof:name":"Atelier Evelyn Jansen",
    "wof:placetype":"venue"
},
  "geometry": {"coordinates":[4.670474,51.815823],"type":"Point"}
}