{
  "type": "Feature",
  "properties": {
    "iso:country":"NL",
    "sg:address":"Drieslagstraat 45",
    "sg:city":"Weert",
    "sg:orig_category":"Metaalwerken",
    "sg:phone":"+31 495 538 939",
    "sg:postcode":"6004 CP",
    "sg:province":"Limburg",
    "wof:name":"G.A.J. Slenders",
    "wof:placetype":"venue"
},
  "geometry": {"coordinates":[5.732842,51.251675],"type":"Point"}
}