{
  "type": "Feature",
  "properties": {
    "iso:country":"NL",
    "sg:address":"Vd Hoopstr 1",
    "sg:city":"Groningen",
    "sg:orig_category":"Verhuur",
    "sg:phone":"+31 50 575 7120",
    "sg:postcode":"9716 JK",
    "sg:province":"Groningen",
    "wof:name":"Reisiger",
    "wof:placetype":"venue"
},
  "geometry": {"coordinates":[6.564721,53.237904],"type":"Point"}
}