{
  "type": "Feature",
  "properties": {
    "iso:country":"NL",
    "sg:address":"Weperpolder 26",
    "sg:city":"Oosterwolde Fr",
    "sg:orig_category":"Huizensloop And Bouwrijp Maken",
    "sg:phone":"+31 516 588 324",
    "sg:postcode":"8431 RM",
    "sg:province":"Friesland",
    "wof:name":"K J De Groot",
    "wof:placetype":"venue"
},
  "geometry": {"coordinates":[6.36266,53.03273],"type":"Point"}
}