{
  "type": "Feature",
  "properties": {
    "addr:full":"Achterbos 1 Vinkeveen Utrecht 3645 CA",
    "addr:housenumber":"1",
    "addr:postcode":"3645 ca",
    "addr:street":"Achterbos",
    "iso:country":"NL",
    "sg:address":"Achterbos 1",
    "sg:city":"Vinkeveen",
    "sg:orig_category":"Schoenen",
    "sg:phone":"+31 297 264 002",
    "sg:postcode":"3645 CA",
    "sg:province":"Utrecht",
    "wof:name":"J.M. Janssen",
    "wof:placetype":"venue"
},
  "geometry": {"coordinates":[4.929025,52.223049],"type":"Point"}
}