{
  "type": "Feature",
  "properties": {
    "addr:full":"Pieter Langendijkstraat 33 'S Gravenhage Zuid-Holland 2533 TD",
    "addr:housenumber":"33",
    "addr:postcode":"2533 td",
    "addr:street":"Pieter Langendijkstraat;' S",
    "iso:country":"NL",
    "sg:address":"Pieter Langendijkstraat 33",
    "sg:city":"'S Gravenhage",
    "sg:orig_category":"Schilderwerk",
    "sg:phone":"+31 70 389 3409",
    "sg:postcode":"2533 TD",
    "sg:province":"Zuid-Holland",
    "wof:name":"Fa Nieuwkoop & Van Leeuwen",
    "wof:placetype":"venue"
},
  "geometry": {"coordinates":[4.297996,52.051071],"type":"Point"}
}