{
  "type": "Feature",
  "properties": {
    "addr:full":"Sportln 25 Wolvega Provincie Friesland 8471 NP",
    "addr:housenumber":"25",
    "addr:postcode":"8471 np",
    "addr:street":"Sportln;Provincie Friesland",
    "iso:country":"NL",
    "sg:address":"Sportln 25",
    "sg:city":"Wolvega",
    "sg:orig_category":"Scholen Voor Algemeen Voortgezet Onderwijs",
    "sg:phone":"+31 561 691 050",
    "sg:postcode":"8471 NP",
    "sg:province":"Provincie Friesland",
    "wof:name":"Bornego College",
    "wof:placetype":"venue"
},
  "geometry": {"coordinates":[5.99809,52.87521],"type":"Point"}
}