{
  "type": "Feature",
  "properties": {
    "addr:full":"Westerstr 238 Amsterdam Missouri 1015 MT",
    "addr:housenumber":"238;1015",
    "addr:street":"Mt",
    "iso:country":"NL",
    "sg:address":"Westerstr 238",
    "sg:city":"Amsterdam",
    "sg:orig_category":"Mensendieck - Oefentherapeuten",
    "sg:phone":"+31 20 623 9109",
    "sg:postcode":"1015 MT",
    "sg:province":"Missouri",
    "wof:name":"Bouwman, M M",
    "wof:placetype":"venue"
},
  "geometry": {"coordinates":[-94.58503,38.350479],"type":"Point"}
}