{
  "type": "Feature",
  "properties": {
    "addr:full":"Burg Cortenstr 18 Maastricht Limburg 6226 GV",
    "addr:housenumber":"18",
    "addr:postcode":"6226 gv",
    "addr:street":"Burg",
    "iso:country":"NL",
    "sg:address":"Burg Cortenstr 18",
    "sg:city":"Maastricht",
    "sg:orig_category":"Feestartikelen",
    "sg:phone":"+31 43 363 6778",
    "sg:postcode":"6226 GV",
    "sg:province":"Limburg",
    "wof:name":"Hoenjet",
    "wof:placetype":"venue"
},
  "geometry": {"coordinates":[5.727751,50.845005],"type":"Point"}
}