{
  "type": "Feature",
  "properties": {
    "addr:full":"Provincialeweg 63 Schalkwijk Utrecht 3998 JK",
    "addr:housenumber":"63",
    "addr:postcode":"3998 jk",
    "addr:street":"Provincialeweg",
    "iso:country":"NL",
    "sg:address":"Provincialeweg 63",
    "sg:city":"Schalkwijk",
    "sg:orig_category":"Zuivelproducten And Spijsoli?n Gh",
    "sg:phone":"+31 30 601 1458",
    "sg:postcode":"3998 JK",
    "sg:province":"Utrecht",
    "wof:name":"Pluimveebedrijf Fa. S. De Gier En Zn.",
    "wof:placetype":"venue"
},
  "geometry": {"coordinates":[5.222118,51.982578],"type":"Point"}
}