{
  "type": "Feature",
  "properties": {
    "addr:full":"De Hoef 10 Hoogeloon Noord-Brabant 5528 CA",
    "addr:housenumber":"10",
    "addr:postcode":"5528 ca",
    "addr:street":"De Hoef",
    "iso:country":"NL",
    "sg:address":"De Hoef 10",
    "sg:city":"Hoogeloon",
    "sg:orig_category":"Bloemen And Planten",
    "sg:phone":"+31 497 681 390",
    "sg:postcode":"5528 CA",
    "sg:province":"Noord-Brabant",
    "wof:name":"De Hennekooi",
    "wof:placetype":"venue"
},
  "geometry": {"coordinates":[5.266008,51.400379],"type":"Point"}
}