{
  "type": "Feature",
  "properties": {
    "addr:full":"Goudse Rywg 523 Rotterdam South Holland 3031 CG",
    "addr:housenumber":"523",
    "addr:postcode":"3031 cg",
    "iso:country":"NL",
    "sg:address":"Goudse Rywg 523",
    "sg:city":"Rotterdam",
    "sg:orig_category":"Fotojournalisten Freelance",
    "sg:phone":"+31 10 213 6295",
    "sg:postcode":"3031 CG",
    "sg:province":"South Holland",
    "wof:name":"Herfst, Walter",
    "wof:placetype":"venue"
},
  "geometry": {"coordinates":[4.492626,51.928699],"type":"Point"}
}