{
  "type": "Feature",
  "properties": {
    "addr:full":"Manpadsln 4 Vogelenzang North Holland 2114 BJ",
    "addr:housenumber":"4",
    "addr:postcode":"2114 bj",
    "addr:street":"Manpadsln",
    "iso:country":"NL",
    "sg:address":"Manpadsln 4",
    "sg:city":"Vogelenzang",
    "sg:orig_category":"Organisatiebureaus",
    "sg:phone":"+31 23 584 1539",
    "sg:postcode":"2114 BJ",
    "sg:province":"North Holland",
    "wof:name":"Festival Prod",
    "wof:placetype":"venue"
},
  "geometry": {"coordinates":[4.591794014,52.336063385],"type":"Point"}
}