{
  "type": "Feature",
  "properties": {
    "addr:full":"V Ghentstr 27 Twello Gelderland 7390 AC",
    "addr:housenumber":"27",
    "addr:postcode":"7390 ac",
    "addr:street":"Gelderland",
    "iso:country":"NL",
    "sg:address":"V Ghentstr 27",
    "sg:city":"Twello",
    "sg:orig_category":"Boekhouders",
    "sg:phone":"+31 571 279 120",
    "sg:postcode":"7390 AC",
    "sg:province":"Gelderland",
    "wof:name":"Easy Quality Administraties",
    "wof:placetype":"venue"
},
  "geometry": {"coordinates":[6.10329,52.237049],"type":"Point"}
}