{
  "type": "Feature",
  "properties": {
    "iso:country":"NL",
    "sg:address":"Klarendalsewg 76",
    "sg:city":"Arnhem",
    "sg:orig_category":"Schilders",
    "sg:phone":"+31 26 351 5825",
    "sg:postcode":"6822 GC",
    "sg:province":"Gelderland",
    "wof:name":"Limbeek, Van",
    "wof:placetype":"venue"
},
  "geometry": {"coordinates":[5.917948,51.987331],"type":"Point"}
}