{
  "type": "Feature",
  "properties": {
    "addr:full":"Bierstg 8 Hilversum Noord-Holland 1211 GC",
    "addr:housenumber":"8",
    "addr:postcode":"1211 gc",
    "addr:street":"Bierstg",
    "iso:country":"NL",
    "sg:address":"Bierstg 8",
    "sg:city":"Hilversum",
    "sg:orig_category":"Zoetwaren - Fabrieken En Groothandel",
    "sg:phone":"+31 35 628 4500",
    "sg:postcode":"1211 GC",
    "sg:province":"Noord-Holland",
    "wof:name":"Studuo Vof",
    "wof:placetype":"venue"
},
  "geometry": {"coordinates":[5.178029,52.224846],"type":"Point"}
}