{
  "type": "Feature",
  "properties": {
    "iso:country":"NL",
    "sg:address":"Postbus 49",
    "sg:city":"Den Helder",
    "sg:orig_category":"Werving And Selectie Van Tijdelijk Personeel And Uitzendkantoren",
    "sg:phone":"+31 223 660 052",
    "sg:postcode":"1780 AA",
    "sg:province":"North Holland",
    "wof:name":"C&M Labour Supply Bv",
    "wof:placetype":"venue"
},
  "geometry": {"coordinates":[4.7588248253,52.958190918],"type":"Point"}
}