{
  "type": "Feature",
  "properties": {
    "addr:full":"Kreeft 21 Aalten Gelderland 7122 TB",
    "addr:housenumber":"21",
    "addr:postcode":"7122 tb",
    "addr:street":"Kreeft;Gelderland",
    "iso:country":"NL",
    "sg:address":"Kreeft 21",
    "sg:city":"Aalten",
    "sg:orig_category":"Boekenuitgeverijen",
    "sg:phone":"+31 543 473 930",
    "sg:postcode":"7122 TB",
    "sg:province":"Gelderland",
    "wof:name":"Spring '94",
    "wof:placetype":"venue"
},
  "geometry": {"coordinates":[6.573547,51.924622],"type":"Point"}
}