{
  "type": "Feature",
  "properties": {
    "addr:full":"Kruisstr 2 Rosmalen Noord-Brabant 5247 RE",
    "addr:housenumber":"2",
    "addr:postcode":"5247 re",
    "addr:street":"Kruisstr",
    "iso:country":"NL",
    "sg:address":"Kruisstr 2",
    "sg:city":"Rosmalen",
    "sg:classifiers":[
        {
            "category":"Sports & Exercise",
            "subcategory":"Stables",
            "type":"Entertainment"
        }
    ],
    "sg:phone":"+31 73 521 4419",
    "sg:postcode":"5247 RE",
    "sg:province":"Noord-Brabant",
    "sg:tags":[
        "maneges"
    ],
    "wof:name":"Ruitersport, Sticht",
    "wof:placetype":"venue"
},
  "geometry": {"coordinates":[5.377346,51.726376],"type":"Point"}
}