{
  "type": "Feature",
  "properties": {
    "iso:country":"NL",
    "sg:address":"Elzenln 12",
    "sg:city":"Wierden",
    "sg:orig_category":"Machineonderhoud En -Reparatie",
    "sg:phone":"+31 546 572 468",
    "sg:postcode":"7642 TX",
    "sg:province":"NL.08",
    "wof:name":"Lent Hzn, J Van",
    "wof:placetype":"venue"
},
  "geometry": {"coordinates":[6.590784,52.356815],"type":"Point"}
}