{
  "type": "Feature",
  "properties": {
    "addr:full":"Badhoeveln 115-117 Badhoevedorp North Holland 1171 DC",
    "addr:postcode":"115-117;1171",
    "iso:country":"NL",
    "sg:address":"Badhoeveln 115-117",
    "sg:city":"Badhoevedorp",
    "sg:orig_category":"Muziekinstrumenten En Bladmuziek",
    "sg:phone":"+31 20 659 6858",
    "sg:postcode":"1171 DC",
    "sg:province":"North Holland",
    "sg:website":"http://www.terpstra-muziek.nl",
    "wof:name":"Terpstra Muziek Badhoevedorp",
    "wof:placetype":"venue"
},
  "geometry": {"coordinates":[4.77827,52.338509],"type":"Point"}
}