{
  "type": "Feature",
  "properties": {
    "addr:full":"Burggravenlaan 9 Leiden South Holland 2313 HM",
    "addr:housenumber":"9",
    "addr:postcode":"2313 hm",
    "addr:street":"Burggravenlaan",
    "iso:country":"NL",
    "sg:address":"Burggravenlaan 9",
    "sg:city":"Leiden",
    "sg:orig_category":"Bedrijfs- And Managementsconsultants",
    "sg:phone":"+31 71 566 3005",
    "sg:postcode":"2313 HM",
    "sg:province":"South Holland",
    "wof:name":"Mast",
    "wof:placetype":"venue"
},
  "geometry": {"coordinates":[4.506849,52.153553],"type":"Point"}
}