{
  "type": "Feature",
  "properties": {
    "addr:full":"Speenkruidstr 40 Groningen Groningen 9731 GV",
    "addr:housenumber":"40",
    "addr:postcode":"9731 gv",
    "addr:street":"Speenkruidstr",
    "iso:country":"NL",
    "sg:address":"Speenkruidstr 40",
    "sg:city":"Groningen",
    "sg:orig_category":"Adviesbureaus Bedrijfsorganisatie",
    "sg:phone":"+31 50 549 6752",
    "sg:postcode":"9731 GV",
    "sg:province":"Groningen",
    "wof:name":"Boost",
    "wof:placetype":"venue"
},
  "geometry": {"coordinates":[6.599117,53.230225],"type":"Point"}
}