{
  "type": "Feature",
  "properties": {
    "iso:country":"NL",
    "sg:address":"De Leeuwerik 1",
    "sg:city":"Zevenhuizen Zh",
    "sg:orig_category":"Kappers",
    "sg:phone":"+31 180 632 577",
    "sg:postcode":"2761 SB",
    "sg:province":"Zuid-Holland",
    "wof:name":"Kapsalon Thuiszorg",
    "wof:placetype":"venue"
},
  "geometry": {"coordinates":[4.5826320648,52.0059738159],"type":"Point"}
}