{
  "type": "Feature",
  "properties": {
    "addr:full":"Dorpsstraat 78 Bergen Nh Noord-Holland 1861 KZ",
    "addr:housenumber":"78",
    "addr:postcode":"1861 kz",
    "addr:street":"Dorpsstraat",
    "iso:country":"NL",
    "sg:address":"Dorpsstraat 78",
    "sg:city":"Bergen Nh",
    "sg:classifiers":[
        {
            "category":"Travel",
            "subcategory":"Hotels & Motels",
            "type":"Entertainment"
        }
    ],
    "sg:phone":"+31 72 581 2401",
    "sg:postcode":"1861 KZ",
    "sg:province":"Noord-Holland",
    "wof:name":"Hotel De Elzenhof",
    "wof:placetype":"venue"
},
  "geometry": {"coordinates":[4.707469,52.666794],"type":"Point"}
}