{
  "type": "Feature",
  "properties": {
    "iso:country":"NL",
    "sg:address":"Laanstr 27",
    "sg:city":"Baarn",
    "sg:orig_category":"Opticiens",
    "sg:phone":"+31 35 542 1259",
    "sg:postcode":"3743 BA",
    "sg:province":"Utrecht",
    "sg:website":"http://www.hansanders.nl",
    "wof:name":"Hans Anders",
    "wof:placetype":"venue"
},
  "geometry": {"coordinates":[5.2905130386,52.21144104],"type":"Point"}
}