{
  "type": "Feature",
  "properties": {
    "iso:country":"NL",
    "sg:address":"Dorpsstraat 51",
    "sg:city":"Lieshout",
    "sg:classifiers":[
        {
            "category":"Fast Food",
            "type":"Food & Drink"
        }
    ],
    "sg:phone":"+31 499 421 914",
    "sg:postcode":"5737 GA",
    "sg:province":"Noord-Brabant",
    "sg:tags":[
        "afhaal",
        "restaurant"
    ],
    "wof:name":"Cafetaria De Koekoek",
    "wof:placetype":"venue"
},
  "geometry": {"coordinates":[5.593468,51.52314],"type":"Point"}
}