{
  "type": "Feature",
  "properties": {
    "addr:full":"Grote Dk 33 Breda Noord-Brabant 4823 EE",
    "addr:housenumber":"33",
    "addr:postcode":"4823 ee",
    "addr:street":"Grote Dk",
    "iso:country":"NL",
    "sg:address":"Grote Dk 33",
    "sg:city":"Breda",
    "sg:orig_category":"Honden- En Kattentrimsalons",
    "sg:phone":"+31 76 541 6076",
    "sg:postcode":"4823 EE",
    "sg:province":"Noord-Brabant",
    "wof:name":"Canis",
    "wof:placetype":"venue"
},
  "geometry": {"coordinates":[4.74816,51.624599],"type":"Point"}
}