{
  "type": "Feature",
  "properties": {
    "addr:full":"Wenckebachstr 2 Kerkrade Limburg 6466 NC",
    "addr:housenumber":"2",
    "addr:postcode":"6466 nc",
    "addr:street":"Wenckebachstr",
    "iso:country":"NL",
    "sg:address":"Wenckebachstr 2",
    "sg:city":"Kerkrade",
    "sg:orig_category":"Metaalwaren - Fabrieken",
    "sg:phone":"+31 45 566 6000",
    "sg:postcode":"6466 NC",
    "sg:province":"Limburg",
    "wof:name":"Licom",
    "wof:placetype":"venue"
},
  "geometry": {"coordinates":[6.010565,50.859814],"type":"Point"}
}