{
  "type": "Feature",
  "properties": {
    "addr:full":"Rosmolen 16 Ridderkerk South Holland 2986 EA",
    "addr:housenumber":"16",
    "addr:postcode":"2986 ea",
    "addr:street":"Rosmolen",
    "iso:country":"NL",
    "sg:address":"Rosmolen 16",
    "sg:city":"Ridderkerk",
    "sg:orig_category":"Bakkerijbenodigdheden En -Grondstoffen",
    "sg:phone":"+31 180 430 646",
    "sg:postcode":"2986 EA",
    "sg:province":"South Holland",
    "wof:name":"Daily Fresh Bv",
    "wof:placetype":"venue"
},
  "geometry": {"coordinates":[4.616026,51.865997],"type":"Point"}
}