{
  "type": "Feature",
  "properties": {
    "addr:full":"Walcherseweg 210 Middelburg Zeeland 4334 NB",
    "addr:housenumber":"210",
    "addr:postcode":"4334 nb",
    "addr:street":"Walcherseweg",
    "iso:country":"NL",
    "sg:address":"Walcherseweg 210",
    "sg:city":"Middelburg",
    "sg:orig_category":"Autokeuringen",
    "sg:phone":"+31 118 613 045",
    "sg:postcode":"4334 NB",
    "sg:province":"Zeeland",
    "wof:name":"F. De Bruijn",
    "wof:placetype":"venue"
},
  "geometry": {"coordinates":[3.596511,51.506588],"type":"Point"}
}