{
  "type": "Feature",
  "properties": {
    "addr:full":"Overakkerstr 188 Breda Noord-Brabant 4834 XP",
    "addr:housenumber":"188",
    "addr:postcode":"4834 xp",
    "iso:country":"NL",
    "sg:address":"Overakkerstr 188",
    "sg:city":"Breda",
    "sg:orig_category":"Bedrijfsopleidingen",
    "sg:phone":"+31 76 522 0067",
    "sg:postcode":"4834 XP",
    "sg:province":"Noord-Brabant",
    "wof:name":"Mansal Ned Bv",
    "wof:placetype":"venue"
},
  "geometry": {"coordinates":[4.800406,51.568565],"type":"Point"}
}