{
  "type": "Feature",
  "properties": {
    "iso:country":"NL",
    "sg:address":"Seringenln 10",
    "sg:city":"Breda",
    "sg:orig_category":"Koeriersdiensten",
    "sg:phone":"+31 76 522 4515",
    "sg:postcode":"4814 JZ",
    "sg:province":"Noord-Brabant",
    "wof:name":"Omme, Van",
    "wof:placetype":"venue"
},
  "geometry": {"coordinates":[4.75068,51.589191],"type":"Point"}
}