{
  "type": "Feature",
  "properties": {
    "addr:full":"Langewyk 131 Drachten Friesland 9202 CN",
    "addr:housenumber":"131",
    "addr:postcode":"9202 cn",
    "addr:street":"Langewyk",
    "iso:country":"NL",
    "sg:address":"Langewyk 131",
    "sg:city":"Drachten",
    "sg:orig_category":"Visspeciaalzaken",
    "sg:phone":"+31 512 515 817",
    "sg:postcode":"9202 CN",
    "sg:province":"Friesland",
    "wof:name":"G. Van Keulen",
    "wof:placetype":"venue"
},
  "geometry": {"coordinates":[6.116109,53.113869],"type":"Point"}
}