{
  "type": "Feature",
  "properties": {
    "iso:country":"NL",
    "sg:address":"Postjeskade 200",
    "sg:city":"Amsterdam",
    "sg:orig_category":"Overheidsdiensten",
    "sg:phone":"+31 20 612 5642",
    "sg:postcode":"1058 DW",
    "sg:province":"Noord-Holland",
    "wof:name":"Buurthuis De Tulp",
    "wof:placetype":"venue"
},
  "geometry": {"coordinates":[4.8498239517,52.3607444763],"type":"Point"}
}