{
  "type": "Feature",
  "properties": {
    "addr:full":"Haagwg 4 Leiden Zuid-Holland 2311 AA",
    "addr:housenumber":"4",
    "addr:postcode":"2311 aa",
    "addr:street":"Haagwg",
    "iso:country":"NL",
    "sg:address":"Haagwg 4",
    "sg:city":"Leiden",
    "sg:orig_category":"Beeldende Kunstenaars",
    "sg:phone":"+31 71 514 8800",
    "sg:postcode":"2311 AA",
    "sg:province":"Zuid-Holland",
    "sg:website":"http://www.4rt.nl",
    "wof:name":"Kunstcentr Haagweg 4",
    "wof:placetype":"venue"
},
  "geometry": {"coordinates":[4.479146,52.159622],"type":"Point"}
}