{
  "type": "Feature",
  "properties": {
    "addr:full":"Dorpsstr 1014 Assendelft North Holland 1566 JK",
    "addr:housenumber":"1014",
    "addr:postcode":"1566 jk",
    "iso:country":"NL",
    "sg:address":"Dorpsstr 1014",
    "sg:city":"Assendelft",
    "sg:orig_category":"Wasmachines En Wasdrogers - Onderhoud En Reparatie",
    "sg:phone":"+31 75 621 9275",
    "sg:postcode":"1566 JK",
    "sg:province":"North Holland",
    "wof:name":"Sp Saenservice",
    "wof:placetype":"venue"
},
  "geometry": {"coordinates":[4.7619829178,52.4911689758],"type":"Point"}
}