{
  "type": "Feature",
  "properties": {
    "addr:full":"Hollewal 2 Den Burg North Holland 1791 GH",
    "addr:housenumber":"2",
    "addr:postcode":"1791 gh",
    "addr:street":"Hollewal",
    "iso:country":"NL",
    "sg:address":"Hollewal 2",
    "sg:city":"Den Burg",
    "sg:orig_category":"Bejaardeninstellingen And Serviceflats",
    "sg:phone":"+31 222 314 144",
    "sg:postcode":"1791 GH",
    "sg:province":"North Holland",
    "wof:name":"Stichting Zorgcentrum Texel Verpleeghuis Texel",
    "wof:placetype":"venue"
},
  "geometry": {"coordinates":[4.794425,53.054096],"type":"Point"}
}