{
  "type": "Feature",
  "properties": {
    "addr:full":"Gerstekamp 13 Hoogland Utrecht 3828 HP",
    "addr:housenumber":"13",
    "addr:postcode":"3828 hp",
    "addr:street":"Gerstekamp",
    "iso:country":"NL",
    "sg:address":"Gerstekamp 13",
    "sg:city":"Hoogland",
    "sg:orig_category":"Autorijscholen",
    "sg:phone":"+31 33 480 3865",
    "sg:postcode":"3828 HP",
    "sg:province":"Utrecht",
    "wof:name":"Hermans",
    "wof:placetype":"venue"
},
  "geometry": {"coordinates":[5.372924,52.185318],"type":"Point"}
}