{
  "type": "Feature",
  "properties": {
    "addr:full":"Akelei 25 Tiel Gelderland 4007 TC",
    "addr:housenumber":"25",
    "addr:postcode":"4007 tc",
    "addr:street":"Akelei;Gelderland",
    "iso:country":"NL",
    "sg:address":"Akelei 25",
    "sg:city":"Tiel",
    "sg:orig_category":"Adviesbureaus",
    "sg:phone":"+31 344 653 149",
    "sg:postcode":"4007 TC",
    "sg:province":"Gelderland",
    "wof:name":"Wissen, H P Van",
    "wof:placetype":"venue"
},
  "geometry": {"coordinates":[5.405413,51.869392],"type":"Point"}
}