{
  "type": "Feature",
  "properties": {
    "addr:full":"Postjeskd 200 Amsterdam Noord-Holland 1058 DW",
    "addr:housenumber":"200",
    "addr:postcode":"1058 dw",
    "iso:country":"NL",
    "sg:address":"Postjeskd 200",
    "sg:city":"Amsterdam",
    "sg:orig_category":"Verenigingsgebouwen",
    "sg:phone":"+31 20 612 5642",
    "sg:postcode":"1058 DW",
    "sg:province":"Noord-Holland",
    "wof:name":"Tulp, De",
    "wof:placetype":"venue"
},
  "geometry": {"coordinates":[4.849824,52.360744],"type":"Point"}
}