{
  "type": "Feature",
  "properties": {
    "addr:full":"Middenweg 152 Den Helder Noord-Holland 1782 BL",
    "addr:housenumber":"152",
    "addr:postcode":"1782 bl",
    "addr:street":"Middenweg",
    "iso:country":"NL",
    "sg:address":"Middenweg 152",
    "sg:city":"Den Helder",
    "sg:orig_category":"Verzekeringen",
    "sg:phone":"+31 223 614 818",
    "sg:postcode":"1782 BL",
    "sg:province":"Noord-Holland",
    "wof:name":"Assurantiekantoor Atlas Bv",
    "wof:placetype":"venue"
},
  "geometry": {"coordinates":[4.756855,52.956135],"type":"Point"}
}