{
  "type": "Feature",
  "properties": {
    "iso:country":"NL",
    "sg:address":"It West 3",
    "sg:city":"Oudega Gem Small",
    "sg:orig_category":"Verzekeringen - Verzekeringskantoren",
    "sg:phone":"+31 512 371 296",
    "sg:postcode":"9216 XD",
    "sg:province":"North Carolina",
    "wof:name":"Sibma",
    "wof:placetype":"venue"
},
  "geometry": {"coordinates":[-76.85424,35.284199],"type":"Point"}
}