{
  "type": "Feature",
  "properties": {
    "iso:country":"NL",
    "sg:address":"Raadhuisstr 97A",
    "sg:city":"Dirkshorn",
    "sg:orig_category":"Vakantieverblijven",
    "sg:phone":"+31 224 552 936",
    "sg:postcode":"1746 BJ",
    "sg:province":"North Holland",
    "wof:name":"Groenhart",
    "wof:placetype":"venue"
},
  "geometry": {"coordinates":[4.770223,52.749905],"type":"Point"}
}