{
  "type": "Feature",
  "properties": {
    "addr:full":"Wattstraat 19D Zoetermeer Zuid-Holland 2723 RA",
    "addr:housenumber":"19d",
    "addr:postcode":"2723 ra",
    "addr:street":"Wattstraat",
    "iso:country":"NL",
    "sg:address":"Wattstraat 19D",
    "sg:city":"Zoetermeer",
    "sg:orig_category":"Schilders",
    "sg:phone":"+31 79 343 7176",
    "sg:postcode":"2723 RA",
    "sg:province":"Zuid-Holland",
    "wof:name":"Profect",
    "wof:placetype":"venue"
},
  "geometry": {"coordinates":[4.525518,52.060848],"type":"Point"}
}