{
  "type": "Feature",
  "properties": {
    "addr:full":"Kruisstraat 103-105 Heerlen Limburg 6411 BS",
    "addr:housenumber":"103-105",
    "addr:postcode":"6411 bs",
    "addr:street":"Kruisstraat",
    "iso:country":"NL",
    "sg:address":"Kruisstraat 103-105",
    "sg:city":"Heerlen",
    "sg:orig_category":"Werving And Selectie Van Vast Personeel",
    "sg:phone":"+31 45 400 7500",
    "sg:postcode":"6411 BS",
    "sg:province":"Limburg",
    "wof:name":"Arbeidsbureau Van De Toekomst",
    "wof:placetype":"venue"
},
  "geometry": {"coordinates":[5.9809799194,50.8855056763],"type":"Point"}
}