{
  "type": "Feature",
  "properties": {
    "addr:full":"Van Swinderenstraat 16 Balk Friesland 8561 AP",
    "addr:housenumber":"16",
    "addr:postcode":"8561 ap",
    "addr:street":"Van Swinderenstraat",
    "iso:country":"NL",
    "sg:address":"Van Swinderenstraat 16",
    "sg:city":"Balk",
    "sg:orig_category":"Juweliers",
    "sg:phone":"+31 514 602 232",
    "sg:postcode":"8561 AP",
    "sg:province":"Friesland",
    "wof:name":"Arie De Koning",
    "wof:placetype":"venue"
},
  "geometry": {"coordinates":[-100.82858299999999,36.608829],"type":"Point"}
}