{
  "type": "Feature",
  "properties": {
    "iso:country":"NL",
    "sg:address":"Buitenpepersdreef 180",
    "sg:city":"S Hertogenbosch",
    "sg:orig_category":"Vertalers",
    "sg:phone":"+31 73 641 1212",
    "sg:postcode":"5231 HK",
    "sg:province":"Noord-Brabant",
    "wof:name":"Willebois Frans & Russisch, I M De",
    "wof:placetype":"venue"
},
  "geometry": {"coordinates":[5.314742,51.703945],"type":"Point"}
}