{
  "type": "Feature",
  "properties": {
    "iso:country":"NL",
    "sg:address":"De Dieze 9",
    "sg:city":"Best",
    "sg:orig_category":"Verpakkingsmachines",
    "sg:phone":"+31 499 379 080",
    "sg:postcode":"5684 PR",
    "sg:province":"Noord-Brabant",
    "wof:name":"Breedewegh Bv",
    "wof:placetype":"venue"
},
  "geometry": {"coordinates":[-101.46455400000001,31.198549],"type":"Point"}
}