{
  "type": "Feature",
  "properties": {
    "addr:full":"Bratislavahof 34 S Gravenhage Zuid-Holland 2548 TG",
    "addr:housenumber":"34;gravenhage",
    "addr:postcode":"2548 tg",
    "addr:street":"Bratislavahof;S",
    "iso:country":"NL",
    "sg:address":"Bratislavahof 34",
    "sg:city":"S Gravenhage",
    "sg:orig_category":"Onderhoudswerken",
    "sg:phone":"+31 70 399 9183",
    "sg:postcode":"2548 TG",
    "sg:province":"Zuid-Holland",
    "wof:name":"Mfb",
    "wof:placetype":"venue"
},
  "geometry": {"coordinates":[4.2901,52.029888],"type":"Point"}
}