{
  "type": "Feature",
  "properties": {
    "addr:full":"St Annaln 52 Maastricht Limburg 6217 KB",
    "addr:housenumber":"52",
    "addr:postcode":"6217 kb",
    "iso:country":"NL",
    "sg:address":"St Annaln 52",
    "sg:city":"Maastricht",
    "sg:orig_category":"Boeken En Tijdschriften",
    "sg:phone":"+31 43 347 2199",
    "sg:postcode":"6217 KB",
    "sg:province":"Limburg",
    "wof:name":"Erick",
    "wof:placetype":"venue"
},
  "geometry": {"coordinates":[5.673757,50.849144],"type":"Point"}
}