{
  "type": "Feature",
  "properties": {
    "iso:country":"NL",
    "sg:address":"Ringvaartdk 62",
    "sg:city":"Amsterdam",
    "sg:orig_category":"Fotoarchieven",
    "sg:phone":"+31 20 388 0110",
    "sg:postcode":"1066 DE",
    "sg:province":"Noord-Holland",
    "sg:website":"http://www.maaykederidderproducties.com",
    "wof:name":"Maayke De Ridder",
    "wof:placetype":"venue"
},
  "geometry": {"coordinates":[4.79577,52.338039],"type":"Point"}
}