{
  "type": "Feature",
  "properties": {
    "addr:full":"Brinkstraat 7 Hengelo Ov NL.08 7551 CB",
    "addr:housenumber":"7;7551",
    "addr:postcode":"cb",
    "addr:street":"Brinkstraat;Ov",
    "iso:country":"NL",
    "sg:address":"Brinkstraat 7",
    "sg:city":"Hengelo Ov",
    "sg:orig_category":"Kappers",
    "sg:phone":"+31 74 243 8133",
    "sg:postcode":"7551 CB",
    "sg:province":"NL.08",
    "wof:name":"Bibob Vof",
    "wof:placetype":"venue"
},
  "geometry": {"coordinates":[6.7928700447,52.2647094727],"type":"Point"}
}