{
  "type": "Feature",
  "properties": {
    "addr:full":"Kerkstraat 13 Oldenzaal NL.08 7571 EE",
    "addr:housenumber":"13;nl.08",
    "addr:postcode":"7571 ee",
    "addr:street":"Kerkstraat",
    "iso:country":"NL",
    "sg:address":"Kerkstraat 13",
    "sg:city":"Oldenzaal",
    "sg:orig_category":"Kappers",
    "sg:phone":"+31 541 516 716",
    "sg:postcode":"7571 EE",
    "sg:province":"NL.08",
    "wof:name":"Interhair Freddy",
    "wof:placetype":"venue"
},
  "geometry": {"coordinates":[6.9294500351,52.312953949],"type":"Point"}
}