{
  "type": "Feature",
  "properties": {
    "addr:full":"H Seghersln 32 Heerhugowaard North Holland 1701 XB",
    "addr:housenumber":"32",
    "addr:postcode":"1701 xb",
    "iso:country":"NL",
    "sg:address":"H Seghersln 32",
    "sg:city":"Heerhugowaard",
    "sg:orig_category":"Webdesign Bureaus",
    "sg:phone":"+31 72 571 4024",
    "sg:postcode":"1701 XB",
    "sg:province":"North Holland",
    "sg:website":"http://www.rademakerswebdesign.nl",
    "wof:name":"Rademakers",
    "wof:placetype":"venue"
},
  "geometry": {"coordinates":[4.827521801,52.6651954651],"type":"Point"}
}