{
  "type": "Feature",
  "properties": {
    "iso:country":"NL",
    "sg:address":"Vd Meulenwg 1",
    "sg:city":"Emmen",
    "sg:orig_category":"Verenigingen En Stichtingen",
    "sg:phone":"+31 591 612 550",
    "sg:postcode":"7814 TK",
    "sg:province":"Drenthe",
    "wof:name":"Ark, De",
    "wof:placetype":"venue"
},
  "geometry": {"coordinates":[6.88206,52.801495],"type":"Point"}
}