{
  "type": "Feature",
  "properties": {
    "addr:full":"Helleneind 7 Bladel North Brabant 5531 BS",
    "addr:housenumber":"7",
    "addr:postcode":"5531 bs",
    "addr:street":"Helleneind",
    "iso:country":"NL",
    "sg:address":"Helleneind 7",
    "sg:city":"Bladel",
    "sg:orig_category":"Loodgieterswerk, Verwarming And Sanitaire Installaties",
    "sg:phone":"+31 497 382 541",
    "sg:postcode":"5531 BS",
    "sg:province":"North Brabant",
    "wof:name":"V. Es. J.P.M.",
    "wof:placetype":"venue"
},
  "geometry": {"coordinates":[5.21263,51.370548],"type":"Point"}
}