{
  "type": "Feature",
  "properties": {
    "addr:full":"Keimpemastins 45 Leeuwarden Friesland 8925 JS",
    "addr:housenumber":"45",
    "addr:postcode":"8925 js",
    "addr:street":"Keimpemastins",
    "iso:country":"NL",
    "sg:address":"Keimpemastins 45",
    "sg:city":"Leeuwarden",
    "sg:orig_category":"Cafetaria'S",
    "sg:phone":"+31 58 267 4829",
    "sg:postcode":"8925 JS",
    "sg:province":"Friesland",
    "wof:name":"Minh Tan Vof",
    "wof:placetype":"venue"
},
  "geometry": {"coordinates":[5.850504,53.207706],"type":"Point"}
}