{
  "type": "Feature",
  "properties": {
    "iso:country":"NL",
    "sg:address":"Haaksbergerstraat 231",
    "sg:city":"Enschede",
    "sg:orig_category":"Begrafenisondernemers",
    "sg:phone":"+31 53 432 3693",
    "sg:postcode":"7545 GH",
    "sg:province":"Overijssel",
    "wof:name":"Begrafenisvereniging Doodenzorg",
    "wof:placetype":"venue"
},
  "geometry": {"coordinates":[6.879303,52.210976],"type":"Point"}
}