{
  "type": "Feature",
  "properties": {
    "addr:full":"Grypskerkstr 18 Arnhem Gelderland 6835 DH",
    "addr:housenumber":"18",
    "addr:postcode":"6835 dh",
    "addr:street":"Grypskerkstr",
    "iso:country":"NL",
    "sg:address":"Grypskerkstr 18",
    "sg:city":"Arnhem",
    "sg:orig_category":"Autorijscholen",
    "sg:phone":"+31 26 323 5555",
    "sg:postcode":"6835 DH",
    "sg:province":"Gelderland",
    "wof:name":"Start & Finish",
    "wof:placetype":"venue"
},
  "geometry": {"coordinates":[5.900571,51.950508],"type":"Point"}
}