{
  "type": "Feature",
  "properties": {
    "addr:full":"T V Berkhoutstr 18 Baarn Utrecht 3743 BV",
    "addr:housenumber":"18",
    "addr:postcode":"3743 bv",
    "addr:street":"T;Berkhoutstr",
    "iso:country":"NL",
    "sg:address":"T V Berkhoutstr 18",
    "sg:city":"Baarn",
    "sg:orig_category":"Grafisch Ontwerpers",
    "sg:phone":"+31 35 541 1950",
    "sg:postcode":"3743 BV",
    "sg:province":"Utrecht",
    "wof:name":"Broeksma, Melle",
    "wof:placetype":"venue"
},
  "geometry": {"coordinates":[5.292121,52.21101],"type":"Point"}
}