{
  "type": "Feature",
  "properties": {
    "addr:full":"Handelskd 75 Deventer NL.08 7417 DH",
    "addr:housenumber":"75;nl.08",
    "addr:postcode":"7417 dh",
    "addr:street":"Handelskd",
    "iso:country":"NL",
    "sg:address":"Handelskd 75",
    "sg:city":"Deventer",
    "sg:orig_category":"Boekhandels",
    "sg:phone":"+31 570 677 477",
    "sg:postcode":"7417 DH",
    "sg:province":"NL.08",
    "wof:name":"Praamstra",
    "wof:placetype":"venue"
},
  "geometry": {"coordinates":[6.159899,52.251034],"type":"Point"}
}