{
  "type": "Feature",
  "properties": {
    "addr:full":"Vanadiumweg 9 Amersfoort Utrecht 3812 PX",
    "addr:housenumber":"9",
    "addr:postcode":"3812 px",
    "addr:street":"Vanadiumweg",
    "iso:country":"NL",
    "sg:address":"Vanadiumweg 9",
    "sg:city":"Amersfoort",
    "sg:orig_category":"Drukkerijen And Copyshops",
    "sg:phone":"+31 33 469 9500",
    "sg:postcode":"3812 PX",
    "sg:province":"Utrecht",
    "wof:name":"Drukkerij Wilco Bv",
    "wof:placetype":"venue"
},
  "geometry": {"coordinates":[5.361345,52.170479],"type":"Point"}
}