{
  "type": "Feature",
  "properties": {
    "addr:full":"Hoofdkd 18 Ter Apel Groningen 9561 JG",
    "addr:housenumber":"18",
    "addr:postcode":"9561 jg",
    "addr:street":"Hoofdkd",
    "iso:country":"NL",
    "sg:address":"Hoofdkd 18",
    "sg:city":"Ter Apel",
    "sg:orig_category":"Meubelen - Fabrieken En Groothandel",
    "sg:phone":"+31 599 587 809",
    "sg:postcode":"9561 JG",
    "sg:province":"Groningen",
    "wof:name":"Meubelnet",
    "wof:placetype":"venue"
},
  "geometry": {"coordinates":[7.05645,52.873894],"type":"Point"}
}