{
  "type": "Feature",
  "properties": {
    "addr:full":"Wagnerln 55 Arnhem Gelderland 6815 AD",
    "addr:housenumber":"55",
    "addr:postcode":"6815 ad",
    "addr:street":"Wagnerln",
    "iso:country":"NL",
    "sg:address":"Wagnerln 55",
    "sg:city":"Arnhem",
    "sg:orig_category":"Hoortoestellen",
    "sg:phone":"+31 26 351 2470",
    "sg:postcode":"6815 AD",
    "sg:province":"Gelderland",
    "wof:name":"Beter Horen",
    "wof:placetype":"venue"
},
  "geometry": {"coordinates":[5.909449,52.000568],"type":"Point"}
}