{
  "type": "Feature",
  "properties": {
    "addr:full":"Bruggestraat 34 Harderwijk Gelderland 3841 CP",
    "addr:housenumber":"34",
    "addr:postcode":"3841 cp",
    "addr:street":"Bruggestraat;Gelderland",
    "iso:country":"NL",
    "sg:address":"Bruggestraat 34",
    "sg:city":"Harderwijk",
    "sg:orig_category":"Opticiens",
    "sg:phone":"+31 341 413 320",
    "sg:postcode":"3841 CP",
    "sg:province":"Gelderland",
    "wof:name":"Speciaal Optiek Stutvoet Bv",
    "wof:placetype":"venue"
},
  "geometry": {"coordinates":[5.6173558235,52.3502731323],"type":"Point"}
}