{
  "type": "Feature",
  "properties": {
    "iso:country":"NL",
    "sg:address":"Hoekenrode 7",
    "sg:city":"Amsterdam Zuidoost",
    "sg:orig_category":"Werving And Selectie Van Tijdelijk Personeel And Uitzendkantoren",
    "sg:phone":"+31 20 565 9080",
    "sg:postcode":"1102 BR",
    "sg:province":"North Holland",
    "wof:name":"Randstad Uitzendbureau Bv",
    "wof:placetype":"venue"
},
  "geometry": {"coordinates":[4.949452877,52.3125267029],"type":"Point"}
}