{
  "type": "Feature",
  "properties": {
    "addr:full":"Elandstr 101 S Gravenhage Zuid-Holland 2513 GN",
    "addr:housenumber":"101;gravenhage",
    "addr:postcode":"2513 gn",
    "addr:street":"S",
    "iso:country":"NL",
    "sg:address":"Elandstr 101",
    "sg:city":"S Gravenhage",
    "sg:orig_category":"Wassalons",
    "sg:phone":"+31 6 22805287",
    "sg:postcode":"2513 GN",
    "sg:province":"Zuid-Holland",
    "sg:website":"http://www.celam.nl",
    "wof:name":"Celam",
    "wof:placetype":"venue"
},
  "geometry": {"coordinates":[4.3033900261,52.0784416199],"type":"Point"}
}