{
  "type": "Feature",
  "properties": {
    "addr:full":"De Ruyterstr 53 Leerdam Zuid-Holland 4142 XE",
    "addr:housenumber":"53",
    "addr:postcode":"4142 xe",
    "iso:country":"NL",
    "sg:address":"De Ruyterstr 53",
    "sg:city":"Leerdam",
    "sg:orig_category":"Onderhoudswerken",
    "sg:phone":"+31 345 633 903",
    "sg:postcode":"4142 XE",
    "sg:province":"Zuid-Holland",
    "wof:name":"Dmv",
    "wof:placetype":"venue"
},
  "geometry": {"coordinates":[5.083846,51.887478],"type":"Point"}
}