{
  "type": "Feature",
  "properties": {
    "addr:full":"Meidoornstr 16 Bleskensgraaf Ca South Holland 2971 BK",
    "addr:housenumber":"16",
    "addr:postcode":"ca;2971 bk",
    "addr:street":"Meidoornstr",
    "iso:country":"NL",
    "sg:address":"Meidoornstr 16",
    "sg:city":"Bleskensgraaf Ca",
    "sg:orig_category":"Vaarscholen",
    "sg:phone":"+31 184 691 076",
    "sg:postcode":"2971 BK",
    "sg:province":"South Holland",
    "sg:website":"http://www.sasyachtcharter.com",
    "wof:name":"Sas Yachtcharter",
    "wof:placetype":"venue"
},
  "geometry": {"coordinates":[4.786845,51.872211],"type":"Point"}
}