{
  "type": "Feature",
  "properties": {
    "addr:full":"Postbus 272 Bergen Nh 1860 AG",
    "addr:housenumber":"272",
    "addr:postcode":"1860",
    "addr:street":"Postbus;Nh",
    "iso:country":"NL",
    "sg:address":"Postbus 272",
    "sg:city":"Bergen Nh",
    "sg:orig_category":"Adviesbureaus Bedrijfsorganisatie",
    "sg:phone":"+31 72 581 4392",
    "sg:postcode":"1860 AG",
    "sg:website":"http://www.cns-solutions.com",
    "wof:name":"Cns Solutions Bv",
    "wof:placetype":"venue"
},
  "geometry": {"coordinates":[4.70139,52.669979],"type":"Point"}
}