{
  "type": "Feature",
  "properties": {
    "addr:full":"Orseleindstraat 25 Oss North Brabant 5346 SJ",
    "addr:housenumber":"25",
    "addr:postcode":"5346",
    "addr:street":"Orseleindstraat",
    "iso:country":"NL",
    "sg:address":"Orseleindstraat 25",
    "sg:city":"Oss",
    "sg:orig_category":"Kunst And Kunstenaarsbenodigdheden",
    "sg:phone":"+31 412 622 201",
    "sg:postcode":"5346 SJ",
    "sg:province":"North Brabant",
    "wof:name":"De Overvloed",
    "wof:placetype":"venue"
},
  "geometry": {"coordinates":[5.517764,51.772881],"type":"Point"}
}