{
  "type": "Feature",
  "properties": {
    "addr:full":"Eibergsestraat 44 Haaksbergen NL.08 7481 HL",
    "addr:housenumber":"44;nl.08",
    "addr:postcode":"7481 hl",
    "addr:street":"Eibergsestraat",
    "iso:country":"NL",
    "sg:address":"Eibergsestraat 44",
    "sg:city":"Haaksbergen",
    "sg:orig_category":"Werving And Selectie Van Tijdelijk Personeel And Uitzendkantoren",
    "sg:phone":"+31 53 572 4545",
    "sg:postcode":"7481 HL",
    "sg:province":"NL.08",
    "wof:name":"In Person",
    "wof:placetype":"venue"
},
  "geometry": {"coordinates":[6.738161087,52.1527748108],"type":"Point"}
}