{
  "type": "Feature",
  "properties": {
    "addr:full":"Dorpsstr 51 Oegstgeest South Holland 2343 AX",
    "addr:housenumber":"51",
    "addr:postcode":"2343 ax",
    "addr:street":"Dorpsstr",
    "iso:country":"NL",
    "sg:address":"Dorpsstr 51",
    "sg:city":"Oegstgeest",
    "sg:orig_category":"Adviesbureaus Bedrijfsorganisatie",
    "sg:phone":"+31 71 517 6024",
    "sg:postcode":"2343 AX",
    "sg:province":"South Holland",
    "wof:name":"Boorn, Van Den",
    "wof:placetype":"venue"
},
  "geometry": {"coordinates":[4.467205,52.190502],"type":"Point"}
}