{
  "type": "Feature",
  "properties": {
    "addr:full":"Leidsestr 37 Amsterdam Noord-Holland 1017 NV",
    "addr:housenumber":"37",
    "addr:postcode":"1017 nv",
    "addr:street":"Leidsestr",
    "iso:country":"NL",
    "sg:address":"Leidsestr 37",
    "sg:city":"Amsterdam",
    "sg:orig_category":"Herenkleding",
    "sg:phone":"+31 20 423 6700",
    "sg:postcode":"1017 NV",
    "sg:province":"Noord-Holland",
    "wof:name":"Gentle Men'S Casuals",
    "wof:placetype":"venue"
},
  "geometry": {"coordinates":[4.886156,52.365734],"type":"Point"}
}