{
  "type": "Feature",
  "properties": {
    "addr:full":"Langestr 48 Huissen Gelderland 6851 AS",
    "addr:housenumber":"48",
    "addr:postcode":"6851 as",
    "addr:street":"Langestr;Gelderland",
    "iso:country":"NL",
    "sg:address":"Langestr 48",
    "sg:city":"Huissen",
    "sg:orig_category":"Verzekeringen - Verzekeringskantoren",
    "sg:phone":"+31 26 325 8380",
    "sg:postcode":"6851 AS",
    "sg:province":"Gelderland",
    "sg:website":"http://www.dingemansmakelaardij.com",
    "wof:name":"Dingemans Bv, H",
    "wof:placetype":"venue"
},
  "geometry": {"coordinates":[5.94233,51.938644],"type":"Point"}
}