{
  "type": "Feature",
  "properties": {
    "iso:country":"NL",
    "sg:address":"Nordhornsestraat 62",
    "sg:city":"Denekamp",
    "sg:orig_category":"Politie",
    "sg:phone":"+31 900 8844",
    "sg:postcode":"7591 BH",
    "sg:province":"NL.08",
    "wof:name":"Politie Denekamp",
    "wof:placetype":"venue"
},
  "geometry": {"coordinates":[7.02859,52.397209],"type":"Point"}
}