{
  "type": "Feature",
  "properties": {
    "addr:full":"Blauwe Hoef 41 Bergeyk Noord-Brabant 5571 JZ",
    "addr:housenumber":"41",
    "addr:postcode":"5571 jz",
    "addr:street":"Blauwe Hoef",
    "iso:country":"NL",
    "sg:address":"Blauwe Hoef 41",
    "sg:city":"Bergeyk",
    "sg:orig_category":"Administratie- En Boekhoudkantoren",
    "sg:phone":"+31 497 575 483",
    "sg:postcode":"5571 JZ",
    "sg:province":"Noord-Brabant",
    "wof:name":"Nuland, Van",
    "wof:placetype":"venue"
},
  "geometry": {"coordinates":[5.355425,51.314713],"type":"Point"}
}