{
  "type": "Feature",
  "properties": {
    "iso:country":"NL",
    "sg:address":"Grutterystr 12",
    "sg:city":"S Gravenmoer",
    "sg:orig_category":"Kappers",
    "sg:phone":"+31 162 321 727",
    "sg:postcode":"5109 TG",
    "sg:province":"North Brabant",
    "wof:name":"Mondrian",
    "wof:placetype":"venue"
},
  "geometry": {"coordinates":[4.940699,51.658627],"type":"Point"}
}