{
  "type": "Feature",
  "properties": {
    "addr:full":"Hoeksestr 2 Montfoort Utrecht 3417 AT",
    "addr:housenumber":"2",
    "addr:postcode":"3417",
    "addr:street":"Hoeksestr",
    "iso:country":"NL",
    "sg:address":"Hoeksestr 2",
    "sg:city":"Montfoort",
    "sg:orig_category":"Scholen Voor Basisonderwijs",
    "sg:phone":"+31 348 471 769",
    "sg:postcode":"3417 AT",
    "sg:province":"Utrecht",
    "wof:name":"Heeswijk",
    "wof:placetype":"venue"
},
  "geometry": {"coordinates":[4.952964,52.049809],"type":"Point"}
}