{
  "type": "Feature",
  "properties": {
    "addr:full":"Rumpsterwg 9 Bunnik Utrecht 3981 AK",
    "addr:housenumber":"9",
    "addr:postcode":"3981 ak",
    "addr:street":"Rumpsterwg",
    "iso:country":"NL",
    "sg:address":"Rumpsterwg 9",
    "sg:city":"Bunnik",
    "sg:orig_category":"Poeliers",
    "sg:phone":"+31 30 688 2193",
    "sg:postcode":"3981 AK",
    "sg:province":"Utrecht",
    "sg:website":"http://www.rutting.nl",
    "wof:name":"Rutting & Znn",
    "wof:placetype":"venue"
},
  "geometry": {"coordinates":[5.215592,52.061771],"type":"Point"}
}