{
  "type": "Feature",
  "properties": {
    "addr:full":"Beeksewg 41 Babberich Gelderland 6909 DN",
    "addr:housenumber":"41",
    "addr:postcode":"6909 dn",
    "addr:street":"Beeksewg;Gelderland",
    "iso:country":"NL",
    "sg:address":"Beeksewg 41",
    "sg:city":"Babberich",
    "sg:orig_category":"Verzekeringen - Verzekeringskantoren",
    "sg:phone":"+31 316 527 925",
    "sg:postcode":"6909 DN",
    "sg:province":"Gelderland",
    "wof:name":"Koning, P J M",
    "wof:placetype":"venue"
},
  "geometry": {"coordinates":[6.141819,51.910015],"type":"Point"}
}