{
  "type": "Feature",
  "properties": {
    "addr:full":"J V Eyckln 2 Bilthoven Utrecht 3723 BC",
    "addr:housenumber":"2",
    "addr:postcode":"3723 bc",
    "addr:street":"J;Eyckln",
    "iso:country":"NL",
    "sg:address":"J V Eyckln 2",
    "sg:city":"Bilthoven",
    "sg:orig_category":"Adviesbureaus Marketing",
    "sg:phone":"+31 30 228 8559",
    "sg:postcode":"3723 BC",
    "sg:province":"Utrecht",
    "wof:name":"Fontein",
    "wof:placetype":"venue"
},
  "geometry": {"coordinates":[5.205415,52.13023],"type":"Point"}
}