{
  "type": "Feature",
  "properties": {
    "iso:country":"NL",
    "sg:address":"Brugstraat 2",
    "sg:city":"Scheemda",
    "sg:orig_category":"Overheidsdiensten",
    "sg:phone":"+31 597 595 200",
    "sg:postcode":"9679 BR",
    "sg:province":"Groningen",
    "wof:name":"Gemeente Scheemda",
    "wof:placetype":"venue"
},
  "geometry": {"coordinates":[6.9717059135,53.1760940552],"type":"Point"}
}