{
  "type": "Feature",
  "properties": {
    "addr:full":"Velingspad 6 Stadskanaal Groningen 9502 RA",
    "addr:housenumber":"6",
    "addr:postcode":"9502 ra",
    "addr:street":"Velingspad",
    "iso:country":"NL",
    "sg:address":"Velingspad 6",
    "sg:city":"Stadskanaal",
    "sg:classifiers":[
        {
            "category":"Fast Food",
            "type":"Food & Drink"
        }
    ],
    "sg:phone":"+31 599 616 395",
    "sg:postcode":"9502 RA",
    "sg:province":"Groningen",
    "sg:tags":[
        "afhaal",
        "restaurant"
    ],
    "wof:name":"Snackbar Succes",
    "wof:placetype":"venue"
},
  "geometry": {"coordinates":[6.965109,52.996983],"type":"Point"}
}