{
  "type": "Feature",
  "properties": {
    "addr:full":"Zwartsluizerwg 7 Hasselt Overijssel 8061 AB",
    "addr:housenumber":"7",
    "addr:postcode":"8061 ab",
    "addr:street":"Zwartsluizerwg",
    "iso:country":"NL",
    "sg:address":"Zwartsluizerwg 7",
    "sg:city":"Hasselt",
    "sg:orig_category":"Grondwerken",
    "sg:phone":"+31 38 477 1711",
    "sg:postcode":"8061 AB",
    "sg:province":"Overijssel",
    "wof:name":"Klooster, Wim Ten",
    "wof:placetype":"venue"
},
  "geometry": {"coordinates":[6.097029,52.599018],"type":"Point"}
}