{
  "type": "Feature",
  "properties": {
    "addr:full":"P Krugerln 118 S Gravenhage South Holland 2571 HM",
    "addr:housenumber":"118",
    "addr:postcode":"2571 hm",
    "addr:street":"S Gravenhage",
    "iso:country":"NL",
    "sg:address":"P Krugerln 118",
    "sg:city":"S Gravenhage",
    "sg:orig_category":"Kappers",
    "sg:phone":"+31 70 345 7811",
    "sg:postcode":"2571 HM",
    "sg:province":"South Holland",
    "wof:name":"Vatan",
    "wof:placetype":"venue"
},
  "geometry": {"coordinates":[4.29037,52.06884],"type":"Point"}
}