{
  "type": "Feature",
  "properties": {
    "iso:country":"NL",
    "sg:address":"Brugstr 4",
    "sg:city":"Grathem",
    "sg:orig_category":"Administratie- En Boekhoudkantoren",
    "sg:phone":"+31 475 452 786",
    "sg:postcode":"6096 AB",
    "sg:province":"Limburg",
    "wof:name":"Greefkens",
    "wof:placetype":"venue"
},
  "geometry": {"coordinates":[5.861153,51.186832],"type":"Point"}
}