{
  "type": "Feature",
  "properties": {
    "addr:full":"Industriewg 1 Eindhoven North Brabant 5627 BS",
    "addr:housenumber":"1",
    "addr:postcode":"5627 bs",
    "addr:street":"Industriewg",
    "iso:country":"NL",
    "sg:address":"Industriewg 1",
    "sg:city":"Eindhoven",
    "sg:orig_category":"Houtgroothandel",
    "sg:phone":"+31 40 242 7525",
    "sg:postcode":"5627 BS",
    "sg:province":"North Brabant",
    "sg:website":"http://www.henchout.nl",
    "wof:name":"H & C Hout En Plaatmaterialen",
    "wof:placetype":"venue"
},
  "geometry": {"coordinates":[5.439679,51.480003],"type":"Point"}
}