{
  "type": "Feature",
  "properties": {
    "iso:country":"NL",
    "sg:address":"Nieuwendammerdijk 359",
    "sg:city":"Amsterdam",
    "sg:orig_category":"Autokeuringen",
    "sg:phone":"+31 20 636 1025",
    "sg:postcode":"1023 BK",
    "sg:province":"Noord-Holland",
    "wof:name":"All Round Autoplaatwerkerij",
    "wof:placetype":"venue"
},
  "geometry": {"coordinates":[4.941869,52.390781],"type":"Point"}
}