{
  "type": "Feature",
  "properties": {
    "iso:country":"NL",
    "sg:address":"Heuvel 3",
    "sg:city":"Vught",
    "sg:orig_category":"Opticiens",
    "sg:phone":"+31 73 656 0073",
    "sg:postcode":"5261 EE",
    "sg:province":"Noord-Brabant",
    "wof:name":"Optiek Van De Kamp Bv",
    "wof:placetype":"venue"
},
  "geometry": {"coordinates":[5.2987718582,51.6582870483],"type":"Point"}
}