{
  "type": "Feature",
  "properties": {
    "addr:full":"L Marktstr 22 Leeuwarden Friesland 8911 AD",
    "addr:housenumber":"22",
    "addr:postcode":"8911 ad",
    "iso:country":"NL",
    "sg:address":"L Marktstr 22",
    "sg:city":"Leeuwarden",
    "sg:orig_category":"Octrooigemachtigden- Bureaus",
    "sg:phone":"+31 58 212 4366",
    "sg:postcode":"8911 AD",
    "sg:province":"Friesland",
    "wof:name":"Arnold & Siedsma",
    "wof:placetype":"venue"
},
  "geometry": {"coordinates":[5.790662,53.197884],"type":"Point"}
}