{
  "type": "Feature",
  "properties": {
    "iso:country":"NL",
    "sg:address":"Stationswg 24",
    "sg:city":"Weesp",
    "sg:orig_category":"Kappers",
    "sg:phone":"+31 294 457 068",
    "sg:postcode":"1382 AB",
    "sg:province":"Noord-Holland",
    "wof:name":"Nieberg, Gebr",
    "wof:placetype":"venue"
},
  "geometry": {"coordinates":[5.045441,52.310822],"type":"Point"}
}