{
  "type": "Feature",
  "properties": {
    "iso:country":"NL",
    "sg:address":"Melkkelder 83",
    "sg:city":"Drachten",
    "sg:orig_category":"Psychologen",
    "sg:phone":"+31 512 549 990",
    "sg:postcode":"9205 DE",
    "sg:province":"Provincie Friesland",
    "wof:name":"Eerstelijnspsychologie, Praktijk Voor",
    "wof:placetype":"venue"
},
  "geometry": {"coordinates":[6.054437,53.094322],"type":"Point"}
}