{
  "type": "Feature",
  "properties": {
    "addr:full":"Haagdijk 141 Breda Noord-Brabant 4811 TR",
    "addr:housenumber":"141",
    "addr:postcode":"4811 tr",
    "addr:street":"Haagdijk",
    "iso:country":"NL",
    "sg:address":"Haagdijk 141",
    "sg:city":"Breda",
    "sg:classifiers":[
        {
            "category":"Shopping",
            "subcategory":"Gifts & Souvenirs",
            "type":"Retail Goods"
        }
    ],
    "sg:phone":"+31 76 514 6184",
    "sg:postcode":"4811 TR",
    "sg:province":"Noord-Brabant",
    "sg:tags":[
        "geschenken"
    ],
    "wof:name":"Conscious Dreams",
    "wof:placetype":"venue"
},
  "geometry": {"coordinates":[4.768395,51.587166],"type":"Point"}
}