{
  "type": "Feature",
  "properties": {
    "iso:country":"NL",
    "sg:address":"Den Dam 39A",
    "sg:city":"Breedenbroek",
    "sg:orig_category":"Facilitaire Dienstverlening",
    "sg:phone":"+31 315 642 020",
    "sg:postcode":"7084 BL",
    "sg:province":"Gelderland",
    "wof:name":"Klein Hesselink",
    "wof:placetype":"venue"
},
  "geometry": {"coordinates":[6.467901,51.877068],"type":"Point"}
}