{
  "type": "Feature",
  "properties": {
    "addr:full":"Lynbaansgr 115 Amsterdam North Holland 1016 KT",
    "addr:housenumber":"115",
    "addr:postcode":"1016 kt",
    "iso:country":"NL",
    "sg:address":"Lynbaansgr 115",
    "sg:city":"Amsterdam",
    "sg:orig_category":"Werving En Selectie",
    "sg:phone":"+31 6 50500146",
    "sg:postcode":"1016 KT",
    "sg:province":"North Holland",
    "sg:website":"http://www.innergy-recruitment.nl",
    "wof:name":"Innergy Recruitment",
    "wof:placetype":"venue"
},
  "geometry": {"coordinates":[4.8767261505,52.3724861145],"type":"Point"}
}