{
  "type": "Feature",
  "properties": {
    "addr:full":"Evertsmaad 39 Oosterwolde Fr Provincie Friesland 8431 TC",
    "addr:housenumber":"39",
    "addr:postcode":"8431 tc",
    "addr:street":"Evertsmaad;Friesland",
    "iso:country":"NL",
    "sg:address":"Evertsmaad 39",
    "sg:city":"Oosterwolde Fr",
    "sg:orig_category":"Natuurvoeding En Reformartikelen - Fabrieken En Groothandel",
    "sg:phone":"+31 516 522 243",
    "sg:postcode":"8431 TC",
    "sg:province":"Provincie Friesland",
    "wof:name":"Nfe",
    "wof:placetype":"venue"
},
  "geometry": {"coordinates":[6.280791,52.998924],"type":"Point"}
}