{
  "type": "Feature",
  "properties": {
    "addr:full":"Schoterweg 26 Haarlem Noord-Holland 2021 HM",
    "addr:housenumber":"26",
    "addr:postcode":"2021 hm",
    "addr:street":"Schoterweg",
    "iso:country":"NL",
    "sg:address":"Schoterweg 26",
    "sg:city":"Haarlem",
    "sg:classifiers":[
        {
            "category":"Bakery",
            "type":"Food & Drink"
        }
    ],
    "sg:phone":"+31 23 526 1367",
    "sg:postcode":"2021 HM",
    "sg:province":"Noord-Holland",
    "sg:tags":[
        "brood",
        "banket"
    ],
    "wof:name":"Echte Bakker Verkerk",
    "wof:placetype":"venue"
},
  "geometry": {"coordinates":[4.640739,52.39098],"type":"Point"}
}