{
  "type": "Feature",
  "properties": {
    "addr:full":"Marconistraat 4 Zwolle Overijssel 8013 PK",
    "addr:housenumber":"4",
    "addr:postcode":"8013 pk",
    "addr:street":"Marconistraat",
    "iso:country":"NL",
    "sg:address":"Marconistraat 4",
    "sg:city":"Zwolle",
    "sg:orig_category":"Metalen And Ertsen Gh",
    "sg:phone":"+31 38 465 5953",
    "sg:postcode":"8013 PK",
    "sg:province":"Overijssel",
    "wof:name":"Hekkert Aluminium",
    "wof:placetype":"venue"
},
  "geometry": {"coordinates":[6.124783,52.497772],"type":"Point"}
}