{
  "type": "Feature",
  "properties": {
    "addr:full":"Postbus 10502 Amsterdam Noord-Holland 1001 EM",
    "addr:housenumber":"10502",
    "addr:postcode":"1001 em",
    "addr:street":"Postbus",
    "iso:country":"NL",
    "sg:address":"Postbus 10502",
    "sg:city":"Amsterdam",
    "sg:orig_category":"Verenigingen En Stichtingen",
    "sg:phone":"+31 20 626 9602",
    "sg:postcode":"1001 EM",
    "sg:province":"Noord-Holland",
    "sg:website":"http://www.euronet.nl/~advaya/index.htm",
    "wof:name":"Advayavada Infocenter",
    "wof:placetype":"venue"
},
  "geometry": {"coordinates":[4.89319,52.373119],"type":"Point"}
}