{
  "type": "Feature",
  "properties": {
    "addr:full":"Faktorij 129 Alkmaar Noord-Holland 1825 HC",
    "addr:housenumber":"129",
    "addr:postcode":"1825 hc",
    "addr:street":"Faktorij",
    "iso:country":"NL",
    "sg:address":"Faktorij 129",
    "sg:city":"Alkmaar",
    "sg:orig_category":"Kinderopvang",
    "sg:phone":"+31 72 566 9028",
    "sg:postcode":"1825 HC",
    "sg:province":"Noord-Holland",
    "sg:website":"http://www.kdv-rollebol.nl",
    "wof:name":"Rollebol, Kinderdagverblijf",
    "wof:placetype":"venue"
},
  "geometry": {"coordinates":[4.759195,52.660374],"type":"Point"}
}