{
  "type": "Feature",
  "properties": {
    "addr:full":"Jasperskamp 4 Deventer Overijssel 7418 GE",
    "addr:housenumber":"4",
    "addr:postcode":"7418",
    "addr:street":"Jasperskamp",
    "iso:country":"NL",
    "sg:address":"Jasperskamp 4",
    "sg:city":"Deventer",
    "sg:orig_category":"Adviesbureaus Bedrijfsorganisatie",
    "sg:phone":"+31 570 516 562",
    "sg:postcode":"7418 GE",
    "sg:province":"Overijssel",
    "wof:name":"Converging Facets",
    "wof:placetype":"venue"
},
  "geometry": {"coordinates":[6.195897,52.249641],"type":"Point"}
}