{
  "type": "Feature",
  "properties": {
    "addr:full":"Spangenhof 23 Amsterdam Noord-Holland 1083 JJ",
    "addr:housenumber":"23",
    "addr:postcode":"1083 jj",
    "addr:street":"Spangenhof",
    "iso:country":"NL",
    "sg:address":"Spangenhof 23",
    "sg:city":"Amsterdam",
    "sg:orig_category":"Koffers And Tassen Fab",
    "sg:phone":"+31 20 442 0846",
    "sg:postcode":"1083 JJ",
    "sg:province":"Noord-Holland",
    "wof:name":"Co-Productions",
    "wof:placetype":"venue"
},
  "geometry": {"coordinates":[4.881983,52.333462],"type":"Point"}
}