{
  "type": "Feature",
  "properties": {
    "addr:full":"G J Van Heekstraat 139 Enschede Overijssel 7521 EC",
    "addr:housenumber":"139",
    "addr:postcode":"7521 ec",
    "addr:street":"G J Van Heekstraat",
    "iso:country":"NL",
    "sg:address":"G J Van Heekstraat 139",
    "sg:city":"Enschede",
    "sg:orig_category":"Apothekers",
    "sg:phone":"+31 53 435 0371",
    "sg:postcode":"7521 EC",
    "sg:province":"Overijssel",
    "wof:name":"Apotheek Maatschap Eekmaat Tromp Twekkel",
    "wof:placetype":"venue"
},
  "geometry": {"coordinates":[6.863873,52.228107],"type":"Point"}
}