{
  "type": "Feature",
  "properties": {
    "addr:full":"Stationsstr 10 Amstelveen Noord-Holland 1182 JN",
    "addr:housenumber":"10",
    "addr:postcode":"1182 jn",
    "addr:street":"Stationsstr",
    "iso:country":"NL",
    "sg:address":"Stationsstr 10",
    "sg:city":"Amstelveen",
    "sg:orig_category":"Verzekeringen - Verzekeringskantoren",
    "sg:phone":"+31 20 456 2345",
    "sg:postcode":"1182 JN",
    "sg:province":"Noord-Holland",
    "wof:name":"Bruyntjes Bv, J M H",
    "wof:placetype":"venue"
},
  "geometry": {"coordinates":[4.846828,52.30183],"type":"Point"}
}