{
  "type": "Feature",
  "properties": {
    "addr:full":"Hamburgerstraat 42 Doetinchem Gelderland 7001 AL",
    "addr:housenumber":"42;7001",
    "addr:postcode":"al",
    "addr:street":"Hamburgerstraat;Gelderland",
    "iso:country":"NL",
    "sg:address":"Hamburgerstraat 42",
    "sg:city":"Doetinchem",
    "sg:orig_category":"Damesmodezaken",
    "sg:phone":"+31 314 345 122",
    "sg:postcode":"7001 AL",
    "sg:province":"Gelderland",
    "wof:name":"Boetiek 32",
    "wof:placetype":"venue"
},
  "geometry": {"coordinates":[6.29002,51.964203],"type":"Point"}
}