{
  "type": "Feature",
  "properties": {
    "iso:country":"NL",
    "sg:address":"Meer En Duin 37",
    "sg:city":"Lisse",
    "sg:orig_category":"Openbaar Vervoer",
    "sg:phone":"+31 252 425 671",
    "sg:postcode":"2163 HB",
    "sg:province":"Zuid-Holland",
    "wof:name":"Connexxion",
    "wof:placetype":"venue"
},
  "geometry": {"coordinates":[4.5676698685,52.2684288025],"type":"Point"}
}