{
  "type": "Feature",
  "properties": {
    "addr:full":"Eperweg 35 Epe Gelderland 8162 RZ",
    "addr:housenumber":"35",
    "addr:postcode":"8162 rz",
    "addr:street":"Eperweg;Gelderland",
    "iso:country":"NL",
    "sg:address":"Eperweg 35",
    "sg:city":"Epe",
    "sg:orig_category":"Architecten",
    "sg:phone":"+31 578 613 288",
    "sg:postcode":"8162 RZ",
    "sg:province":"Gelderland",
    "wof:name":"Casal Open Vuur Architectuur Bv",
    "wof:placetype":"venue"
},
  "geometry": {"coordinates":[5.980514,52.334999],"type":"Point"}
}