{
  "type": "Feature",
  "properties": {
    "addr:full":"Gouwestr 13 Apeldoorn Gelderland 7333 MZ",
    "addr:housenumber":"13",
    "addr:postcode":"7333 mz",
    "addr:street":"Gouwestr;Gelderland",
    "iso:country":"NL",
    "sg:address":"Gouwestr 13",
    "sg:city":"Apeldoorn",
    "sg:orig_category":"Fotoreportages",
    "sg:phone":"+31 55 541 2864",
    "sg:postcode":"7333 MZ",
    "sg:province":"Gelderland",
    "wof:name":"Peter Lous",
    "wof:placetype":"venue"
},
  "geometry": {"coordinates":[5.971549,52.187046],"type":"Point"}
}