{
  "type": "Feature",
  "properties": {
    "addr:full":"G Schalckenstr 34 Made Noord-Brabant 4921 CR",
    "addr:housenumber":"34",
    "addr:postcode":"4921 cr",
    "iso:country":"NL",
    "sg:address":"G Schalckenstr 34",
    "sg:city":"Made",
    "sg:classifiers":[
        {
            "category":"Food & Beverages",
            "subcategory":"Bakery",
            "type":"Retail Goods"
        }
    ],
    "sg:phone":"+31 162 682 326",
    "sg:postcode":"4921 CR",
    "sg:province":"Noord-Brabant",
    "sg:tags":[
        "brood",
        "en",
        "banket"
    ],
    "wof:name":"Steen, A Van Der",
    "wof:placetype":"venue"
},
  "geometry": {"coordinates":[-119.921257,36.939281],"type":"Point"}
}