{
  "type": "Feature",
  "properties": {
    "iso:country":"NL",
    "sg:address":"Brouwersdk 345",
    "sg:city":"Dordrecht",
    "sg:orig_category":"Verf En Lak - Fabrieken En Groothandel",
    "sg:phone":"+31 78 614 8986",
    "sg:postcode":"3314 GP",
    "sg:province":"Zuid-Holland",
    "wof:name":"Broeders Beheer Bv, J",
    "wof:placetype":"venue"
},
  "geometry": {"coordinates":[4.665339,51.798832],"type":"Point"}
}