{
  "type": "Feature",
  "properties": {
    "addr:full":"Stikkelwaard 110 Alkmaar Noord-Holland 1824 VM",
    "addr:housenumber":"110",
    "addr:postcode":"1824 vm",
    "addr:street":"Stikkelwaard",
    "iso:country":"NL",
    "sg:address":"Stikkelwaard 110",
    "sg:city":"Alkmaar",
    "sg:orig_category":"Woningstoffeerders",
    "sg:phone":"+31 72 561 2677",
    "sg:postcode":"1824 VM",
    "sg:province":"Noord-Holland",
    "wof:name":"Schuiten, D",
    "wof:placetype":"venue"
},
  "geometry": {"coordinates":[4.7519111633,52.6425476074],"type":"Point"}
}