{
  "type": "Feature",
  "properties": {
    "addr:full":"Paauwenburgweg 131 Vlissingen Zeeland 4384 JD",
    "addr:housenumber":"131",
    "addr:postcode":"4384 jd",
    "addr:street":"Paauwenburgweg",
    "iso:country":"NL",
    "sg:address":"Paauwenburgweg 131",
    "sg:city":"Vlissingen",
    "sg:orig_category":"Onderhoud And Reparatie Kantoorapparatuur",
    "sg:phone":"+31 118 479 908",
    "sg:postcode":"4384 JD",
    "sg:province":"Zeeland",
    "wof:name":"Apl",
    "wof:placetype":"venue"
},
  "geometry": {"coordinates":[3.550612,51.462543],"type":"Point"}
}