{
  "type": "Feature",
  "properties": {
    "addr:full":"Wijzendweg 18 Sint Maarten Noord-Holland 1744 HJ",
    "addr:housenumber":"18",
    "addr:postcode":"maarten;1744 hj",
    "addr:street":"Wijzendweg",
    "iso:country":"NL",
    "sg:address":"Wijzendweg 18",
    "sg:city":"Sint Maarten",
    "sg:orig_category":"Hoefdierhouderijen",
    "sg:phone":"+31 224 561 673",
    "sg:postcode":"1744 HJ",
    "sg:province":"Noord-Holland",
    "wof:name":"Vof C. Barsingerhorn",
    "wof:placetype":"venue"
},
  "geometry": {"coordinates":[4.742948,52.764194],"type":"Point"}
}