{
  "type": "Feature",
  "properties": {
    "iso:country":"NL",
    "sg:address":"Netwerk 147",
    "sg:city":"Purmerend",
    "sg:orig_category":"Gasapparaten En -Artikelen - Reparatie En Onderhoud",
    "sg:phone":"+31 299 432 111",
    "sg:postcode":"1446 WV",
    "sg:province":"Noord-Holland",
    "sg:website":"http://www.gasservice-nh.nl",
    "wof:name":"Gasservice Noord-Holland Bv",
    "wof:placetype":"venue"
},
  "geometry": {"coordinates":[4.99376,52.511002],"type":"Point"}
}