{
  "type": "Feature",
  "properties": {
    "addr:full":"S Gravelandseveer 3 Amsterdam Noord-Holland 1011 KM",
    "addr:housenumber":"3",
    "addr:street":"1011 Km",
    "iso:country":"NL",
    "sg:address":"S Gravelandseveer 3",
    "sg:city":"Amsterdam",
    "sg:classifiers":[
        {
            "category":"Travel",
            "subcategory":"Hotels & Motels",
            "type":"Entertainment"
        }
    ],
    "sg:phone":"+31 20 624 6607",
    "sg:postcode":"1011 KM",
    "sg:province":"Noord-Holland",
    "sg:website":"http://www.amsterdamhouse.com",
    "wof:name":"Amsterdam Househotel",
    "wof:placetype":"venue"
},
  "geometry": {"coordinates":[4.896328,52.367832],"type":"Point"}
}