{
  "type": "Feature",
  "properties": {
    "iso:country":"NL",
    "sg:address":"Westeind 4C",
    "sg:city":"Rosmalen",
    "sg:orig_category":"Accountants - Administratie- Consulenten En -Kantoren",
    "sg:phone":"+31 73 522 4927",
    "sg:postcode":"5245 NL",
    "sg:province":"Noord-Brabant",
    "sg:website":"http://www.hulshofkroonen.nl",
    "wof:name":"Hulshof Kroonen Bv",
    "wof:placetype":"venue"
},
  "geometry": {"coordinates":[5.349313,51.722588],"type":"Point"}
}