{
  "type": "Feature",
  "properties": {
    "addr:full":"Leeuwarderwg 30 Sneek Friesland 8605 AH",
    "addr:housenumber":"30",
    "addr:postcode":"8605 ah",
    "addr:street":"Leeuwarderwg",
    "iso:country":"NL",
    "sg:address":"Leeuwarderwg 30",
    "sg:city":"Sneek",
    "sg:orig_category":"Scholen Voor Basisonderwijs",
    "sg:phone":"+31 515 412 719",
    "sg:postcode":"8605 AH",
    "sg:province":"Friesland",
    "wof:name":"Bonifatius Rk",
    "wof:placetype":"venue"
},
  "geometry": {"coordinates":[5.668242,53.035065],"type":"Point"}
}