{
  "type": "Feature",
  "properties": {
    "iso:country":"NL",
    "sg:address":"Meidoornstraat 9",
    "sg:city":"Venlo",
    "sg:orig_category":"Platenmaatschappijen",
    "sg:phone":"+31 6 25030519",
    "sg:postcode":"5922 XM",
    "sg:province":"Limburg",
    "wof:name":"Level-D",
    "wof:placetype":"venue"
},
  "geometry": {"coordinates":[6.139768,51.377918],"type":"Point"}
}