{
  "type": "Feature",
  "properties": {
    "addr:full":"Einsteinstraat 19 Reeuwijk Zuid-Holland 2811 EP",
    "addr:housenumber":"19",
    "addr:postcode":"2811 ep",
    "addr:street":"Einsteinstraat",
    "iso:country":"NL",
    "sg:address":"Einsteinstraat 19",
    "sg:city":"Reeuwijk",
    "sg:orig_category":"Wegen And Sportterreinen",
    "sg:phone":"+31 182 395 094",
    "sg:postcode":"2811 EP",
    "sg:province":"Zuid-Holland",
    "wof:name":"Service Dienst Reeuwijk Bv",
    "wof:placetype":"venue"
},
  "geometry": {"coordinates":[4.7183461189,52.0399208069],"type":"Point"}
}