{
  "type": "Feature",
  "properties": {
    "iso:country":"NL",
    "sg:address":"Asselsestr 87",
    "sg:city":"Apeldoorn",
    "sg:orig_category":"Makelaars En Adviseurs Onroerende Goederen",
    "sg:phone":"+31 55 521 2613",
    "sg:postcode":"7311 EE",
    "sg:province":"Gelderland",
    "wof:name":"Postma Era",
    "wof:placetype":"venue"
},
  "geometry": {"coordinates":[5.954975,52.212658],"type":"Point"}
}