{
  "type": "Feature",
  "properties": {
    "addr:full":"Kooikersdreef 610 Apeldoorn Gelderland 7328 BR",
    "addr:housenumber":"610",
    "addr:postcode":"7328 br",
    "addr:street":"Kooikersdreef;Gelderland",
    "iso:country":"NL",
    "sg:address":"Kooikersdreef 610",
    "sg:city":"Apeldoorn",
    "sg:orig_category":"Fotostudio'S And Fotografen",
    "sg:phone":"+31 55 541 7550",
    "sg:postcode":"7328 BR",
    "sg:province":"Gelderland",
    "wof:name":"Foto Jan De Koning",
    "wof:placetype":"venue"
},
  "geometry": {"coordinates":[5.988192,52.196758],"type":"Point"}
}