{
  "type": "Feature",
  "properties": {
    "addr:full":"Vennenbergwg 8A Dalfsen Overijssel 7722 JE",
    "addr:housenumber":"8a",
    "addr:postcode":"7722 je",
    "addr:street":"Vennenbergwg",
    "iso:country":"NL",
    "sg:address":"Vennenbergwg 8A",
    "sg:city":"Dalfsen",
    "sg:orig_category":"Land- En Tuinbouw - Loonbedrijven",
    "sg:phone":"+31 529 458 443",
    "sg:postcode":"7722 JE",
    "sg:province":"Overijssel",
    "wof:name":"Niens",
    "wof:placetype":"venue"
},
  "geometry": {"coordinates":[6.333181,52.47879],"type":"Point"}
}