{
  "type": "Feature",
  "properties": {
    "addr:full":"Braakvoortweg 21 T Harde Gelderland 8084 EP",
    "addr:housenumber":"21 t",
    "addr:postcode":"8084 ep",
    "addr:street":"Braakvoortweg;Harde Gelderland",
    "iso:country":"NL",
    "sg:address":"Braakvoortweg 21",
    "sg:city":"T Harde",
    "sg:orig_category":"Huishoudapparatuur, Televisies And Radio'S",
    "sg:phone":"+31 6 21230282",
    "sg:postcode":"8084 EP",
    "sg:province":"Gelderland",
    "wof:name":"Kaoz Audio Licht En Geluid",
    "wof:placetype":"venue"
},
  "geometry": {"coordinates":[5.875105,52.418037],"type":"Point"}
}