{
  "type": "Feature",
  "properties": {
    "addr:full":"Benedenberg 32 Bergambacht South Holland 2861 LG",
    "addr:housenumber":"32",
    "addr:postcode":"2861 lg",
    "addr:street":"Benedenberg",
    "iso:country":"NL",
    "sg:address":"Benedenberg 32",
    "sg:city":"Bergambacht",
    "sg:orig_category":"Bedrijfs- And Managementsconsultants",
    "sg:phone":"+31 182 357 515",
    "sg:postcode":"2861 LG",
    "sg:province":"South Holland",
    "wof:name":"Dekkers' Management Bv",
    "wof:placetype":"venue"
},
  "geometry": {"coordinates":[4.775177,51.936172],"type":"Point"}
}