{
  "type": "Feature",
  "properties": {
    "addr:full":"Antwerpsestraatweg 112 Bergen Op Zoom North Brabant 4615 AV",
    "addr:housenumber":"112",
    "addr:postcode":"4615 av",
    "addr:street":"Antwerpsestraatweg",
    "iso:country":"NL",
    "sg:address":"Antwerpsestraatweg 112",
    "sg:city":"Bergen Op Zoom",
    "sg:orig_category":"Fotostudio'S And Fotografen",
    "sg:phone":"+31 164 234 322",
    "sg:postcode":"4615 AV",
    "sg:province":"North Brabant",
    "wof:name":"Gerrit De Heus",
    "wof:placetype":"venue"
},
  "geometry": {"coordinates":[4.291826,51.485718],"type":"Point"}
}