{
  "type": "Feature",
  "properties": {
    "iso:country":"NL",
    "sg:address":"A Spenglerstr 81",
    "sg:city":"Amsterdam",
    "sg:orig_category":"Beurzen",
    "sg:phone":"+31 20 612 2593",
    "sg:postcode":"1054 NH",
    "sg:province":"Noord-Holland",
    "wof:name":"Publica Bureau",
    "wof:placetype":"venue"
},
  "geometry": {"coordinates":[4.869725,52.363255],"type":"Point"}
}