{
  "type": "Feature",
  "properties": {
    "addr:full":"Schoolstraat 1 Heerenveen Provincie Friesland 8441 AV",
    "addr:housenumber":"1;8441",
    "addr:postcode":"av",
    "addr:street":"Schoolstraat;Provincie Friesland",
    "iso:country":"NL",
    "sg:address":"Schoolstraat 1",
    "sg:city":"Heerenveen",
    "sg:orig_category":"Kinderopvang Behalve Thuis",
    "sg:phone":"+31 513 627 551",
    "sg:postcode":"8441 AV",
    "sg:province":"Provincie Friesland",
    "wof:name":"T Peuterspeelzalen Drokke Hus",
    "wof:placetype":"venue"
},
  "geometry": {"coordinates":[6.125067,53.006874],"type":"Point"}
}