{
  "type": "Feature",
  "properties": {
    "addr:full":"Weiersloop 6 Assen Drenthe 9401 DZ",
    "addr:housenumber":"6",
    "addr:postcode":"9401 dz",
    "addr:street":"Weiersloop",
    "iso:country":"NL",
    "sg:address":"Weiersloop 6",
    "sg:city":"Assen",
    "sg:orig_category":"Opticiens",
    "sg:phone":"+31 592 313 023",
    "sg:postcode":"9401 DZ",
    "sg:province":"Drenthe",
    "wof:name":"Speciaal Optiek",
    "wof:placetype":"venue"
},
  "geometry": {"coordinates":[6.5604171753,52.994342804],"type":"Point"}
}