{
  "type": "Feature",
  "properties": {
    "addr:full":"Stationsstraat 4 Wormerveer Noord-Holland 1521 DT",
    "addr:housenumber":"4",
    "addr:postcode":"1521 dt",
    "addr:street":"Stationsstraat",
    "iso:country":"NL",
    "sg:address":"Stationsstraat 4",
    "sg:city":"Wormerveer",
    "sg:orig_category":"Boekenuitgeverijen",
    "sg:phone":"+31 75 621 8010",
    "sg:postcode":"1521 DT",
    "sg:province":"Noord-Holland",
    "wof:name":"Boekhandel Schuurman",
    "wof:placetype":"venue"
},
  "geometry": {"coordinates":[4.793432,52.490307],"type":"Point"}
}