{
  "type": "Feature",
  "properties": {
    "addr:full":"Keverdk 18 Weesp Noord-Holland 1381 HM",
    "addr:housenumber":"18",
    "addr:postcode":"1381 hm",
    "addr:street":"Keverdk",
    "iso:country":"NL",
    "sg:address":"Keverdk 18",
    "sg:city":"Weesp",
    "sg:orig_category":"Machineonderhoud En -Reparatie",
    "sg:phone":"+31 35 691 2323",
    "sg:postcode":"1381 HM",
    "sg:province":"Noord-Holland",
    "wof:name":"Vree",
    "wof:placetype":"venue"
},
  "geometry": {"coordinates":[5.09485,52.307816],"type":"Point"}
}