{
  "type": "Feature",
  "properties": {
    "iso:country":"NL",
    "sg:address":"Paradyswg 34",
    "sg:city":"Almelo",
    "sg:orig_category":"Autoschade- Herstelbedrijven",
    "sg:phone":"+31 546 819 641",
    "sg:postcode":"7607 TT",
    "sg:province":"Overijssel",
    "wof:name":"Even",
    "wof:placetype":"venue"
},
  "geometry": {"coordinates":[6.680833,52.348415],"type":"Point"}
}