{
  "type": "Feature",
  "properties": {
    "iso:country":"NL",
    "sg:address":"Hazenspoor 5",
    "sg:city":"Maasbracht",
    "sg:orig_category":"Houtplaatmaterialen",
    "sg:phone":"+31 475 463 178",
    "sg:postcode":"6051 AB",
    "sg:province":"Limburg",
    "wof:name":"Smeets Bv",
    "wof:placetype":"venue"
},
  "geometry": {"coordinates":[5.894594,51.151363],"type":"Point"}
}