{
  "type": "Feature",
  "properties": {
    "iso:country":"NL",
    "sg:address":"Middelberg 30",
    "sg:city":"Veldhoven",
    "sg:orig_category":"Loodgieterswerk, Verwarming And Sanitaire Installaties",
    "sg:phone":"+31 40 254 1369",
    "sg:postcode":"5508 DR",
    "sg:province":"North Brabant",
    "wof:name":"H. Heinemans",
    "wof:placetype":"venue"
},
  "geometry": {"coordinates":[5.384825,51.424934],"type":"Point"}
}