{
  "type": "Feature",
  "properties": {
    "addr:full":"J Vermeerstr 2 Amsterdam Noord-Holland 1071 DR",
    "addr:housenumber":"2",
    "addr:postcode":"1071 dr",
    "iso:country":"NL",
    "sg:address":"J Vermeerstr 2",
    "sg:city":"Amsterdam",
    "sg:classifiers":[
        {
            "category":"Shopping",
            "subcategory":"News",
            "type":"Retail Goods"
        }
    ],
    "sg:phone":"+31 20 662 0150",
    "sg:postcode":"1071 DR",
    "sg:province":"Noord-Holland",
    "sg:tags":[
        "maandbladen",
        "en",
        "week-"
    ],
    "wof:name":"Ned Tijdschrift Voor Geneeskunde",
    "wof:placetype":"venue"
},
  "geometry": {"coordinates":[4.8837561607,52.3571434021],"type":"Point"}
}