{
  "type": "Feature",
  "properties": {
    "addr:full":"Ooipoortstr 15 Doesburg Gelderland 6981 DS",
    "addr:housenumber":"15",
    "addr:postcode":"6981 ds",
    "addr:street":"Ooipoortstr;Gelderland",
    "iso:country":"NL",
    "sg:address":"Ooipoortstr 15",
    "sg:city":"Doesburg",
    "sg:orig_category":"Keukens",
    "sg:phone":"+31 313 483 282",
    "sg:postcode":"6981 DS",
    "sg:province":"Gelderland",
    "sg:website":"http://www.ryans.nl",
    "wof:name":"Ryan",
    "wof:placetype":"venue"
},
  "geometry": {"coordinates":[6.136385,52.012913],"type":"Point"}
}