{
  "type": "Feature",
  "properties": {
    "addr:full":"Jan Tooropstraat 30 Katwijk Zh South Holland 2225 XV",
    "addr:housenumber":"30",
    "addr:postcode":"zh;2225 xv",
    "addr:street":"Jan Tooropstraat",
    "iso:country":"NL",
    "sg:address":"Jan Tooropstraat 30",
    "sg:city":"Katwijk Zh",
    "sg:classifiers":[
        {
            "category":"Education",
            "subcategory":"Preschool",
            "type":"Public Place"
        }
    ],
    "sg:phone":"+31 71 401 6919",
    "sg:postcode":"2225 XV",
    "sg:province":"South Holland",
    "sg:tags":[
        "kleuteronderwijs",
        "basis-"
    ],
    "wof:name":"Hervormde Basisschool Dominee R.P.A. Rutgers",
    "wof:placetype":"venue"
},
  "geometry": {"coordinates":[4.399769,52.207947],"type":"Point"}
}