{
  "type": "Feature",
  "properties": {
    "addr:full":"Postbus 482 Lelystad Flevoland 8200 AL",
    "addr:housenumber":"482",
    "addr:postcode":"8200",
    "addr:street":"Postbus;Flevoland",
    "iso:country":"NL",
    "sg:address":"Postbus 482",
    "sg:city":"Lelystad",
    "sg:orig_category":"Bedrijfsamusement",
    "sg:phone":"+31 320 256 046",
    "sg:postcode":"8200 AL",
    "sg:province":"Flevoland",
    "sg:website":"http://www.r-i-p.nl",
    "wof:name":"Recre-Actief In De Polder",
    "wof:placetype":"venue"
},
  "geometry": {"coordinates":[5.47403,52.50568],"type":"Point"}
}