{
  "type": "Feature",
  "properties": {
    "addr:full":"Klooster 19 Vianen Ut Utrecht 4132 BM",
    "addr:housenumber":"19",
    "addr:postcode":"4132 bm",
    "addr:street":"Klooster",
    "iso:country":"NL",
    "sg:address":"Klooster 19",
    "sg:city":"Vianen Ut",
    "sg:orig_category":"Geluidsinstallaties - Verhuur",
    "sg:phone":"+31 347 377 843",
    "sg:postcode":"4132 BM",
    "sg:province":"Utrecht",
    "sg:website":"http://www.starlightentertainment.nl",
    "wof:name":"Starlight",
    "wof:placetype":"venue"
},
  "geometry": {"coordinates":[5.095426,51.992683],"type":"Point"}
}