{
  "type": "Feature",
  "properties": {
    "addr:full":"Katwoudestraat 11 Tilburg Noord-Brabant 5045 NA",
    "addr:housenumber":"11",
    "addr:postcode":"5045 na",
    "addr:street":"Katwoudestraat",
    "iso:country":"NL",
    "sg:address":"Katwoudestraat 11",
    "sg:city":"Tilburg",
    "sg:orig_category":"Webdesign Bureaus",
    "sg:phone":"+31 6 51291376",
    "sg:postcode":"5045 NA",
    "sg:province":"Noord-Brabant",
    "sg:website":"http://www.ixces.com",
    "wof:name":"Ixces",
    "wof:placetype":"venue"
},
  "geometry": {"coordinates":[4.9958062172,51.5753250122],"type":"Point"}
}