{
  "type": "Feature",
  "properties": {
    "iso:country":"NL",
    "sg:address":"Paterslaan 9",
    "sg:city":"Amsterdam",
    "sg:orig_category":"Bloemen And Planten",
    "sg:phone":"+31 20 490 4220",
    "sg:postcode":"1023 NZ",
    "sg:province":"Noord-Holland",
    "wof:name":"Muller Garden Life Bv",
    "wof:placetype":"venue"
},
  "geometry": {"coordinates":[-74.146004,42.953442],"type":"Point"}
}