{
  "type": "Feature",
  "properties": {
    "addr:full":"Hassinkstr 20 Beltrum Gelderland 7156 LZ",
    "addr:housenumber":"20",
    "addr:postcode":"7156 lz",
    "addr:street":"Hassinkstr;Gelderland",
    "iso:country":"NL",
    "sg:address":"Hassinkstr 20",
    "sg:city":"Beltrum",
    "sg:orig_category":"Artiesten/Gezelschappen",
    "sg:phone":"+31 544 482 123",
    "sg:postcode":"7156 LZ",
    "sg:province":"Gelderland",
    "wof:name":"Wissink, T A M",
    "wof:placetype":"venue"
},
  "geometry": {"coordinates":[6.561632,52.065224],"type":"Point"}
}