{
  "type": "Feature",
  "properties": {
    "iso:country":"NL",
    "sg:address":"Keizersgr 1",
    "sg:city":"Edam",
    "sg:classifiers":[
        {
            "category":"Travel",
            "subcategory":"Hotels & Motels",
            "type":"Entertainment"
        }
    ],
    "sg:phone":"+31 299 371 766",
    "sg:postcode":"1135 AZ",
    "sg:province":"Noord-Holland",
    "wof:name":"Damhotel",
    "wof:placetype":"venue"
},
  "geometry": {"coordinates":[5.048958,52.512329],"type":"Point"}
}