{
  "type": "Feature",
  "properties": {
    "addr:full":"Achter De Kamp 30 Amersfoort Utrecht 3811 JG",
    "addr:housenumber":"30",
    "addr:postcode":"3811 jg",
    "addr:street":"Achter De Kamp",
    "iso:country":"NL",
    "sg:address":"Achter De Kamp 30",
    "sg:city":"Amersfoort",
    "sg:orig_category":"Kappers",
    "sg:phone":"+31 33 495 3200",
    "sg:postcode":"3811 JG",
    "sg:province":"Utrecht",
    "wof:name":"Sura Kapsalon",
    "wof:placetype":"venue"
},
  "geometry": {"coordinates":[5.396354,52.157455],"type":"Point"}
}