{
  "type": "Feature",
  "properties": {
    "addr:full":"Horstermeerstraat 15 Hoofddorp North Holland 2131 DL",
    "addr:housenumber":"15",
    "addr:postcode":"2131 dl",
    "addr:street":"Horstermeerstraat",
    "iso:country":"NL",
    "sg:address":"Horstermeerstraat 15",
    "sg:city":"Hoofddorp",
    "sg:orig_category":"Bloemen And Planten Gh",
    "sg:phone":"+31 23 561 6471",
    "sg:postcode":"2131 DL",
    "sg:province":"North Holland",
    "wof:name":"Zwambach",
    "wof:placetype":"venue"
},
  "geometry": {"coordinates":[4.687389,52.312416],"type":"Point"}
}