{
  "type": "Feature",
  "properties": {
    "addr:full":"Verlengde Stationsstraat 46 Zwaagwesteinde Friesland 9271 CE",
    "addr:housenumber":"46",
    "addr:postcode":"9271 ce",
    "addr:street":"Verlengde Stationsstraat",
    "iso:country":"NL",
    "sg:address":"Verlengde Stationsstraat 46",
    "sg:city":"Zwaagwesteinde",
    "sg:orig_category":"Meubelzaken, Woning- And Keukeninrichting",
    "sg:phone":"+31 511 442 121",
    "sg:postcode":"9271 CE",
    "sg:province":"Friesland",
    "wof:name":"Visser Woninginrichting",
    "wof:placetype":"venue"
},
  "geometry": {"coordinates":[6.039956,53.257977],"type":"Point"}
}