{
  "type": "Feature",
  "properties": {
    "addr:full":"Overtoom 299 Amsterdam North Holland 1054 HW",
    "addr:housenumber":"299",
    "addr:postcode":"1054 hw",
    "addr:street":"Overtoom",
    "iso:country":"NL",
    "sg:address":"Overtoom 299",
    "sg:city":"Amsterdam",
    "sg:orig_category":"Huishoudapparatuur, Televisies And Radio'S",
    "sg:phone":"+31 20 618 2662",
    "sg:postcode":"1054 HW",
    "sg:province":"North Holland",
    "wof:name":"Radio Centro",
    "wof:placetype":"venue"
},
  "geometry": {"coordinates":[4.864553,52.359932],"type":"Point"}
}