{
  "type": "Feature",
  "properties": {
    "iso:country":"NL",
    "sg:address":"Raadhuisstr 4",
    "sg:city":"Ouddorp Zh",
    "sg:orig_category":"Musea",
    "sg:phone":"+31 187 684 419",
    "sg:postcode":"3253 AN",
    "sg:province":"Zuid-Holland",
    "wof:name":"Ouddorps Raad En Polderhuis",
    "wof:placetype":"venue"
},
  "geometry": {"coordinates":[3.935973,51.809109],"type":"Point"}
}