{
  "type": "Feature",
  "properties": {
    "iso:country":"NL",
    "sg:address":"Tweevoren 1",
    "sg:city":"Nuenen",
    "sg:orig_category":"Homeopathie",
    "sg:phone":"+31 40 284 0215",
    "sg:postcode":"5672 SB",
    "sg:province":"Noord-Brabant",
    "wof:name":"Antoinette Van Hees",
    "wof:placetype":"venue"
},
  "geometry": {"coordinates":[5.555201,51.463493],"type":"Point"}
}