{
  "type": "Feature",
  "properties": {
    "addr:full":"Eisterwg 2 Heerlen Limburg 6422 PN",
    "addr:housenumber":"2",
    "addr:postcode":"6422 pn",
    "addr:street":"Eisterwg",
    "iso:country":"NL",
    "sg:address":"Eisterwg 2",
    "sg:city":"Heerlen",
    "sg:orig_category":"Waterleidingbedrijven",
    "sg:phone":"+31 45 566 1414",
    "sg:postcode":"6422 PN",
    "sg:province":"Limburg",
    "wof:name":"Wml",
    "wof:placetype":"venue"
},
  "geometry": {"coordinates":[5.992454052,50.852973938],"type":"Point"}
}