{
  "type": "Feature",
  "properties": {
    "addr:full":"F Hendrikstr 20 Utrecht Utrecht 3583 VM",
    "addr:housenumber":"20",
    "addr:postcode":"3583 vm",
    "iso:country":"NL",
    "sg:address":"F Hendrikstr 20",
    "sg:city":"Utrecht",
    "sg:orig_category":"Onderwijsmateriaal",
    "sg:phone":"+31 30 251 7252",
    "sg:postcode":"3583 VM",
    "sg:province":"Utrecht",
    "wof:name":"Bodde-Alderlieste",
    "wof:placetype":"venue"
},
  "geometry": {"coordinates":[5.143619,52.086586],"type":"Point"}
}