{
  "type": "Feature",
  "properties": {
    "addr:full":"Klaas Katerstraat 1 Ridderkerk South Holland 2982 XE",
    "addr:housenumber":"1",
    "addr:postcode":"2982 xe",
    "addr:street":"Klaas Katerstraat",
    "iso:country":"NL",
    "sg:address":"Klaas Katerstraat 1",
    "sg:city":"Ridderkerk",
    "sg:classifiers":[
        {
            "category":"Education",
            "subcategory":"Preschool",
            "type":"Public Place"
        }
    ],
    "sg:phone":"+31 180 428 862",
    "sg:postcode":"2982 XE",
    "sg:province":"South Holland",
    "sg:tags":[
        "kleuteronderwijs",
        "basis-"
    ],
    "wof:name":"Ds. G.H. Kerstenschool",
    "wof:placetype":"venue"
},
  "geometry": {"coordinates":[4.600475,51.872501],"type":"Point"}
}