{
  "type": "Feature",
  "properties": {
    "iso:country":"NL",
    "sg:address":"W De Withstr 86",
    "sg:city":"Ede Gld",
    "sg:orig_category":"Kantoor- En Secretariaatsservice",
    "sg:phone":"+31 318 610 422",
    "sg:postcode":"6712 HE",
    "sg:province":"Gelderland",
    "sg:website":"http://www.orgburo-telstar.nl",
    "wof:name":"Telstar",
    "wof:placetype":"venue"
},
  "geometry": {"coordinates":[5.6593728065,52.0469665527],"type":"Point"}
}