{
  "type": "Feature",
  "properties": {
    "iso:country":"NL",
    "sg:address":"Schuilenburgerpln 1",
    "sg:city":"Amersfoort",
    "sg:classifiers":[
        {
            "category":"Real Estate",
            "subcategory":"Real Estate Operator",
            "type":"Services"
        }
    ],
    "sg:phone":"+31 33 472 3800",
    "sg:postcode":"3816 TD",
    "sg:province":"Utrecht",
    "sg:tags":[
        "appartementen",
        "en",
        "flat"
    ],
    "wof:name":"Schuilenburght, De",
    "wof:placetype":"venue"
},
  "geometry": {"coordinates":[5.415095,52.153099],"type":"Point"}
}