{
  "type": "Feature",
  "properties": {
    "addr:full":"J Perkln 1 Heemstede Noord-Holland 2106 EN",
    "addr:housenumber":"1",
    "addr:postcode":"2106 en",
    "iso:country":"NL",
    "sg:address":"J Perkln 1",
    "sg:city":"Heemstede",
    "sg:orig_category":"Adviesbureaus Bedrijfsorganisatie",
    "sg:phone":"+31 23 542 3839",
    "sg:postcode":"2106 EN",
    "sg:province":"Noord-Holland",
    "sg:website":"http://www.oxfordservices.nl",
    "wof:name":"Oxford Services Bv",
    "wof:placetype":"venue"
},
  "geometry": {"coordinates":[4.621248,52.345287],"type":"Point"}
}