{
  "type": "Feature",
  "properties": {
    "addr:full":"Westerparallelweg 18 Staphorst Overijssel 7951 LL",
    "addr:housenumber":"18",
    "addr:postcode":"7951 ll",
    "addr:street":"Westerparallelweg",
    "iso:country":"NL",
    "sg:address":"Westerparallelweg 18",
    "sg:city":"Staphorst",
    "sg:orig_category":"Autokeuringen",
    "sg:phone":"+31 522 462 811",
    "sg:postcode":"7951 LL",
    "sg:province":"Overijssel",
    "wof:name":"W Bloemert",
    "wof:placetype":"venue"
},
  "geometry": {"coordinates":[6.223714,52.64127],"type":"Point"}
}