{
  "type": "Feature",
  "properties": {
    "iso:country":"NL",
    "sg:address":"Wg Naar Vierakker 37",
    "sg:city":"Zutphen",
    "sg:orig_category":"Verzekeringen - Verzekeringskantoren",
    "sg:phone":"+31 575 524 216",
    "sg:postcode":"7204 LA",
    "sg:province":"Gelderland",
    "wof:name":"Heca",
    "wof:placetype":"venue"
},
  "geometry": {"coordinates":[6.204283,52.129734],"type":"Point"}
}