{
  "type": "Feature",
  "properties": {
    "addr:full":"Tiendevry 7 Wouw Noord-Brabant 4724 DN",
    "addr:housenumber":"7",
    "addr:postcode":"4724 dn",
    "addr:street":"Tiendevry",
    "iso:country":"NL",
    "sg:address":"Tiendevry 7",
    "sg:city":"Wouw",
    "sg:orig_category":"Metselwerken",
    "sg:phone":"+31 165 303 178",
    "sg:postcode":"4724 DN",
    "sg:province":"Noord-Brabant",
    "wof:name":"Snepvangers, Bouw- & Aannemersbedrijf",
    "wof:placetype":"venue"
},
  "geometry": {"coordinates":[4.396625,51.51973],"type":"Point"}
}