{
  "type": "Feature",
  "properties": {
    "addr:full":"Hogestraat 7 Druten Gelderland 6651 BD",
    "addr:housenumber":"7",
    "addr:postcode":"6651 bd",
    "addr:street":"Hogestraat",
    "iso:country":"NL",
    "sg:address":"Hogestraat 7",
    "sg:city":"Druten",
    "sg:orig_category":"Wasserettes And Stomerijen",
    "sg:phone":"+31 487 514 827",
    "sg:postcode":"6651 BD",
    "sg:province":"Gelderland",
    "wof:name":"Stomerij Odinette Midden Maas En Waal Vo",
    "wof:placetype":"venue"
},
  "geometry": {"coordinates":[5.6052598953,51.8856697083],"type":"Point"}
}