{
  "type": "Feature",
  "properties": {
    "iso:country":"NL",
    "sg:address":"Bloemendaalseweg 14",
    "sg:city":"Bloemendaal",
    "sg:orig_category":"Paramedische Behandelingen",
    "sg:phone":"+31 23 526 1811",
    "sg:postcode":"2061 CK",
    "sg:province":"Noord-Holland",
    "wof:name":"Tom Van Weijer Podotherapie",
    "wof:placetype":"venue"
},
  "geometry": {"coordinates":[4.621284,52.405567],"type":"Point"}
}