{
  "type": "Feature",
  "properties": {
    "addr:full":"1E V Swindenstr 389 Amsterdam Noord-Holland 1093 GB",
    "addr:housenumber":"389",
    "addr:postcode":"1093 gb",
    "addr:street":"1E V Swindenstr",
    "iso:country":"NL",
    "sg:address":"1E V Swindenstr 389",
    "sg:city":"Amsterdam",
    "sg:orig_category":"Haarwerken",
    "sg:phone":"+31 20 663 4783",
    "sg:postcode":"1093 GB",
    "sg:province":"Noord-Holland",
    "wof:name":"Combe Afro",
    "wof:placetype":"venue"
},
  "geometry": {"coordinates":[4.927891,52.362877],"type":"Point"}
}