{
  "type": "Feature",
  "properties": {
    "addr:full":"Brinkkanterwg 17A Woudenberg Utrecht 3931 PJ",
    "addr:housenumber":"17a",
    "addr:postcode":"3931 pj",
    "addr:street":"Brinkkanterwg",
    "iso:country":"NL",
    "sg:address":"Brinkkanterwg 17A",
    "sg:city":"Woudenberg",
    "sg:orig_category":"Geluidsinstallaties - Verhuur",
    "sg:phone":"+31 33 277 0810",
    "sg:postcode":"3931 PJ",
    "sg:province":"Utrecht",
    "wof:name":"Hotline",
    "wof:placetype":"venue"
},
  "geometry": {"coordinates":[5.458554,52.075718],"type":"Point"}
}