{
  "type": "Feature",
  "properties": {
    "addr:full":"Schagerwg 91 Schagerbrug Noord-Holland 1751 CB",
    "addr:housenumber":"91;1751",
    "addr:postcode":"cb",
    "addr:street":"Schagerwg",
    "iso:country":"NL",
    "sg:address":"Schagerwg 91",
    "sg:city":"Schagerbrug",
    "sg:orig_category":"Onderhoudswerken",
    "sg:phone":"+31 224 571 568",
    "sg:postcode":"1751 CB",
    "sg:province":"Noord-Holland",
    "wof:name":"Jonkhout, R",
    "wof:placetype":"venue"
},
  "geometry": {"coordinates":[4.765547,52.800041],"type":"Point"}
}