{
  "type": "Feature",
  "properties": {
    "iso:country":"NL",
    "sg:address":"Smalgoorn 1",
    "sg:city":"Assen",
    "sg:orig_category":"Arbo- En Bedrijfsgezondheids- Diensten",
    "sg:phone":"+31 592 347 085",
    "sg:postcode":"9403 NZ",
    "sg:province":"Drenthe",
    "wof:name":"Isc Bv",
    "wof:placetype":"venue"
},
  "geometry": {"coordinates":[6.585702,53.01368],"type":"Point"}
}