{
  "type": "Feature",
  "properties": {
    "addr:full":"Lionstr 12B Boxmeer Noord-Brabant 5831 AK",
    "addr:housenumber":"12b",
    "addr:postcode":"5831 ak",
    "addr:street":"Lionstr",
    "iso:country":"NL",
    "sg:address":"Lionstr 12B",
    "sg:city":"Boxmeer",
    "sg:orig_category":"Autorijscholen",
    "sg:phone":"+31 485 575 078",
    "sg:postcode":"5831 AK",
    "sg:province":"Noord-Brabant",
    "wof:name":"Beumers",
    "wof:placetype":"venue"
},
  "geometry": {"coordinates":[5.936791,51.634815],"type":"Point"}
}