{
  "type": "Feature",
  "properties": {
    "addr:full":"A Cuypstr 152 Amsterdam Noord-Holland 1073 BK",
    "addr:housenumber":"152",
    "addr:postcode":"1073 bk",
    "iso:country":"NL",
    "sg:address":"A Cuypstr 152",
    "sg:city":"Amsterdam",
    "sg:orig_category":"Woninginrichting",
    "sg:phone":"+31 20 675 5789",
    "sg:postcode":"1073 BK",
    "sg:province":"Noord-Holland",
    "wof:name":"Via Reggio",
    "wof:placetype":"venue"
},
  "geometry": {"coordinates":[4.8944020271,52.3556175232],"type":"Point"}
}