{
  "type": "Feature",
  "properties": {
    "addr:full":"Kleinpolderkd 16 Rotterdam South Holland 3043 CX",
    "addr:housenumber":"16",
    "addr:postcode":"3043 cx",
    "addr:street":"Kleinpolderkd",
    "iso:country":"NL",
    "sg:address":"Kleinpolderkd 16",
    "sg:city":"Rotterdam",
    "sg:orig_category":"Kinderhuizen",
    "sg:phone":"+31 10 245 9721",
    "sg:postcode":"3043 CX",
    "sg:province":"South Holland",
    "wof:name":"Kinderhuis Der Herv Gem Rotterdam, Sticht",
    "wof:placetype":"venue"
},
  "geometry": {"coordinates":[4.422165,51.940559],"type":"Point"}
}