{
  "type": "Feature",
  "properties": {
    "addr:full":"Kroonstraat 12 Stramproy Limburg 6039 AE",
    "addr:housenumber":"12",
    "addr:postcode":"6039 ae",
    "addr:street":"Kroonstraat",
    "iso:country":"NL",
    "sg:address":"Kroonstraat 12",
    "sg:city":"Stramproy",
    "sg:orig_category":"Kappers",
    "sg:phone":"+31 495 562 196",
    "sg:postcode":"6039 AE",
    "sg:province":"Limburg",
    "wof:name":"M H G Sniekers",
    "wof:placetype":"venue"
},
  "geometry": {"coordinates":[5.723595,51.196102],"type":"Point"}
}