{
  "type": "Feature",
  "properties": {
    "addr:full":"Oosthaven 34 Gouda Zuid-Holland 2801 PD",
    "addr:housenumber":"34",
    "addr:postcode":"2801 pd",
    "addr:street":"Oosthaven",
    "iso:country":"NL",
    "sg:address":"Oosthaven 34",
    "sg:city":"Gouda",
    "sg:classifiers":[
        {
            "category":"Fast Food",
            "type":"Food & Drink"
        }
    ],
    "sg:phone":"+31 182 516 570",
    "sg:postcode":"2801 PD",
    "sg:province":"Zuid-Holland",
    "sg:tags":[
        "afhaal",
        "restaurant"
    ],
    "wof:name":"Broodjessalon De Posthoorn",
    "wof:placetype":"venue"
},
  "geometry": {"coordinates":[4.712382,52.00898],"type":"Point"}
}