{
  "type": "Feature",
  "properties": {
    "addr:full":"Entinge 1 Roden Drenthe 9301 TT",
    "addr:housenumber":"1",
    "addr:postcode":"9301 tt",
    "addr:street":"Entinge",
    "iso:country":"NL",
    "sg:address":"Entinge 1",
    "sg:city":"Roden",
    "sg:orig_category":"Hypotheken And Hypotheekbanken",
    "sg:phone":"+31 50 501 1199",
    "sg:postcode":"9301 TT",
    "sg:province":"Drenthe",
    "wof:name":"Klinker",
    "wof:placetype":"venue"
},
  "geometry": {"coordinates":[6.410339,53.134399],"type":"Point"}
}