{
  "type": "Feature",
  "properties": {
    "iso:country":"NL",
    "sg:address":"Entinge 1",
    "sg:city":"Roden",
    "sg:orig_category":"Hypotheken And Hypotheekbanken",
    "sg:phone":"+31 50 501 1199",
    "sg:postcode":"9301 TT",
    "sg:province":"Drenthe",
    "wof:name":"Klinker",
    "wof:placetype":"venue"
},
  "geometry": {"coordinates":[6.410339,53.134399],"type":"Point"}
}