{
  "type": "Feature",
  "properties": {
    "iso:country":"NL",
    "sg:address":"Spoorstr 98",
    "sg:city":"Roosendaal",
    "sg:classifiers":[
        {
            "category":"Building & Trades",
            "subcategory":"Electrical",
            "type":"Services"
        }
    ],
    "sg:phone":"+31 165 562 257",
    "sg:postcode":"4702 VM",
    "sg:province":"Noord-Brabant",
    "sg:tags":[
        "distributor"
    ],
    "wof:name":"Fun Video",
    "wof:placetype":"venue"
},
  "geometry": {"coordinates":[4.464368,51.542389],"type":"Point"}
}