{
  "type": "Feature",
  "properties": {
    "addr:full":"Postbus 59236 Rotterdam Limburg 3008 PE",
    "addr:housenumber":"59236",
    "addr:postcode":"3008 pe",
    "addr:street":"Postbus",
    "iso:country":"NL",
    "sg:address":"Postbus 59236",
    "sg:city":"Rotterdam",
    "sg:orig_category":"Voetbalverenigingen",
    "sg:phone":"+31 78 641 3600",
    "sg:postcode":"3008 PE",
    "sg:province":"Limburg",
    "wof:name":"Dcl",
    "wof:placetype":"venue"
},
  "geometry": {"coordinates":[4.47075,51.922619],"type":"Point"}
}