{
  "type": "Feature",
  "properties": {
    "addr:full":"Zijlstraat 23 Haarlem Noord-Holland 2011 TJ",
    "addr:housenumber":"23",
    "addr:postcode":"2011 tj",
    "addr:street":"Zijlstraat",
    "iso:country":"NL",
    "sg:address":"Zijlstraat 23",
    "sg:city":"Haarlem",
    "sg:orig_category":"Verlichting And Huishoudartikelen",
    "sg:phone":"+31 23 551 2352",
    "sg:postcode":"2011 TJ",
    "sg:province":"Noord-Holland",
    "wof:name":"Zijlstraat Gordijnmode",
    "wof:placetype":"venue"
},
  "geometry": {"coordinates":[4.63103,52.382919],"type":"Point"}
}