{
  "type": "Feature",
  "properties": {
    "iso:country":"NL",
    "sg:address":"Touwbaan 21-23",
    "sg:city":"Gorinchem",
    "sg:orig_category":"Werving And Selectie Van Tijdelijk Personeel And Uitzendkantoren",
    "sg:phone":"+31 183 694 300",
    "sg:postcode":"4205 AB",
    "sg:province":"South Holland",
    "wof:name":"Randstad Uitzendbureau Bv",
    "wof:placetype":"venue"
},
  "geometry": {"coordinates":[4.9665031433,51.8329772949],"type":"Point"}
}