{
  "type": "Feature",
  "properties": {
    "addr:full":"Milletstr 21 Amsterdam Noord-Holland 1077 ZB",
    "addr:housenumber":"21",
    "addr:postcode":"1077 zb",
    "addr:street":"Milletstr",
    "iso:country":"NL",
    "sg:address":"Milletstr 21",
    "sg:city":"Amsterdam",
    "sg:orig_category":"Herenkleding",
    "sg:phone":"+31 20 679 6040",
    "sg:postcode":"1077 ZB",
    "sg:province":"Noord-Holland",
    "wof:name":"Pieter Arnold",
    "wof:placetype":"venue"
},
  "geometry": {"coordinates":[4.870241,52.345833],"type":"Point"}
}