{
  "type": "Feature",
  "properties": {
    "addr:full":"Brinkln 104 Bussum Noord-Holland 1404 GS",
    "addr:housenumber":"104",
    "addr:postcode":"1404 gs",
    "iso:country":"NL",
    "sg:address":"Brinkln 104",
    "sg:city":"Bussum",
    "sg:orig_category":"Golfbanen",
    "sg:phone":"+31 35 691 2773",
    "sg:postcode":"1404 GS",
    "sg:province":"Noord-Holland",
    "sg:website":"http://www.golfcompany.nl",
    "wof:name":"Golf Company, The",
    "wof:placetype":"venue"
},
  "geometry": {"coordinates":[5.162668,52.27261],"type":"Point"}
}