{
  "type": "Feature",
  "properties": {
    "addr:full":"Doetinchemseweg 41 Varsseveld Gelderland 7051 AB",
    "addr:housenumber":"41",
    "addr:postcode":"7051 ab",
    "addr:street":"Doetinchemseweg;Gelderland",
    "iso:country":"NL",
    "sg:address":"Doetinchemseweg 41",
    "sg:city":"Varsseveld",
    "sg:orig_category":"Kappers",
    "sg:phone":"+31 315 241 467",
    "sg:postcode":"7051 AB",
    "sg:province":"Gelderland",
    "wof:name":"Antony Wensink",
    "wof:placetype":"venue"
},
  "geometry": {"coordinates":[6.4574818611,51.9443778992],"type":"Point"}
}