{
  "type": "Feature",
  "properties": {
    "addr:full":"Weth Ebbenln 135 Helmond North Brabant 5701 AH",
    "addr:housenumber":"135",
    "addr:postcode":"5701 ah",
    "addr:street":"Weth Ebbenln",
    "iso:country":"NL",
    "sg:address":"Weth Ebbenln 135",
    "sg:city":"Helmond",
    "sg:orig_category":"Verenigingen En Stichtingen",
    "sg:phone":"+31 492 535 772",
    "sg:postcode":"5701 AH",
    "sg:province":"North Brabant",
    "sg:website":"http://www.homobelangen.nl",
    "wof:name":"Homobelangen, Sticht",
    "wof:placetype":"venue"
},
  "geometry": {"coordinates":[5.658284,51.482239],"type":"Point"}
}