{
  "type": "Feature",
  "properties": {
    "addr:full":"Thujaln 1 Exloo Drenthe 7875 EM",
    "addr:housenumber":"1",
    "addr:postcode":"7875 em",
    "addr:street":"Thujaln",
    "iso:country":"NL",
    "sg:address":"Thujaln 1",
    "sg:city":"Exloo",
    "sg:orig_category":"Autorijscholen",
    "sg:phone":"+31 591 549 032",
    "sg:postcode":"7875 EM",
    "sg:province":"Drenthe",
    "wof:name":"Stuiver, Henk",
    "wof:placetype":"venue"
},
  "geometry": {"coordinates":[6.863554,52.88245],"type":"Point"}
}