{
  "type": "Feature",
  "properties": {
    "addr:full":"Koelemei 42 Breda Noord-Brabant 4816 JD",
    "addr:housenumber":"42",
    "addr:postcode":"4816 jd",
    "addr:street":"Koelemei",
    "iso:country":"NL",
    "sg:address":"Koelemei 42",
    "sg:city":"Breda",
    "sg:orig_category":"Diverse Grafische Activiteiten",
    "sg:phone":"+31 76 587 7450",
    "sg:postcode":"4816 JD",
    "sg:province":"Noord-Brabant",
    "wof:name":"Hoenke Pre Press Bv",
    "wof:placetype":"venue"
},
  "geometry": {"coordinates":[4.796871,51.597256],"type":"Point"}
}