{
  "type": "Feature",
  "properties": {
    "addr:full":"Ds P H Wolfertstr 8 Marienberg Overijssel 7692 AJ",
    "addr:housenumber":"8",
    "addr:postcode":"7692 aj",
    "addr:street":"Ds P H Wolfertstr",
    "iso:country":"NL",
    "sg:address":"Ds P H Wolfertstr 8",
    "sg:city":"Marienberg",
    "sg:orig_category":"Bibliotheken En Leeszalen Openbare",
    "sg:phone":"+31 523 251 666",
    "sg:postcode":"7692 AJ",
    "sg:province":"Overijssel",
    "wof:name":"Openb Bibliotheek",
    "wof:placetype":"venue"
},
  "geometry": {"coordinates":[6.57304,52.511547],"type":"Point"}
}