{
  "type": "Feature",
  "properties": {
    "iso:country":"NL",
    "sg:address":"De Zodde 16",
    "sg:city":"Loosdrecht",
    "sg:orig_category":"Fotostudio'S",
    "sg:phone":"+31 35 582 8226",
    "sg:postcode":"1231 MB",
    "sg:province":"North Holland",
    "wof:name":"Guus Pauka Fotografie",
    "wof:placetype":"venue"
},
  "geometry": {"coordinates":[5.113396,52.209629],"type":"Point"}
}