{
  "type": "Feature",
  "properties": {
    "iso:country":"NL",
    "sg:address":"Hoogstraat 42",
    "sg:city":"Harderwijk",
    "sg:orig_category":"Zuivelproducten",
    "sg:phone":"+31 341 412 580",
    "sg:postcode":"3841 BS",
    "sg:province":"Gelderland",
    "wof:name":"Bruinink",
    "wof:placetype":"venue"
},
  "geometry": {"coordinates":[5.619497,52.350719],"type":"Point"}
}