{
  "type": "Feature",
  "properties": {
    "iso:country":"NL",
    "sg:address":"Bagynestr 64",
    "sg:city":"Leeuwarden",
    "sg:orig_category":"Grafisch Ontwerpers",
    "sg:phone":"+31 58 216 0403",
    "sg:postcode":"8911 DS",
    "sg:province":"Provincie Friesland",
    "wof:name":"Rudi Stuve Grafische Vormgeving",
    "wof:placetype":"venue"
},
  "geometry": {"coordinates":[5.794041,53.201599],"type":"Point"}
}