{
  "type": "Feature",
  "properties": {
    "addr:full":"Daalderweg 1 Zaandam Noord-Holland 1507 DS",
    "addr:housenumber":"1",
    "addr:postcode":"1507 ds",
    "addr:street":"Daalderweg",
    "iso:country":"NL",
    "sg:address":"Daalderweg 1",
    "sg:city":"Zaandam",
    "sg:orig_category":"Goederenvervoer Over De Weg",
    "sg:phone":"+31 75 650 1601",
    "sg:postcode":"1507 DS",
    "sg:province":"Noord-Holland",
    "wof:name":"Fiege Kalf Bv",
    "wof:placetype":"venue"
},
  "geometry": {"coordinates":[4.78868,52.427738],"type":"Point"}
}