{
  "type": "Feature",
  "properties": {
    "addr:full":"Postbus 6546 Nymegen Gelderland 6503 GA",
    "addr:housenumber":"6546",
    "addr:postcode":"6503 ga",
    "addr:street":"Postbus;Gelderland",
    "iso:country":"NL",
    "sg:address":"Postbus 6546",
    "sg:city":"Nymegen",
    "sg:orig_category":"Adviesbureaus Bedrijfsorganisatie",
    "sg:phone":"+31 24 379 2039",
    "sg:postcode":"6503 GA",
    "sg:province":"Gelderland",
    "wof:name":"Ftc",
    "wof:placetype":"venue"
},
  "geometry": {"coordinates":[-83.222931,32.678131],"type":"Point"}
}