{
  "type": "Feature",
  "properties": {
    "addr:full":"Dalfsenstr 30 S Gravenhage Zuid-Holland 2541 VS",
    "addr:housenumber":"30;gravenhage",
    "addr:postcode":"2541 vs",
    "addr:street":"Dalfsenstr;S",
    "iso:country":"NL",
    "sg:address":"Dalfsenstr 30",
    "sg:city":"S Gravenhage",
    "sg:orig_category":"Administratie- En Boekhoudkantoren",
    "sg:phone":"+31 6 22910847",
    "sg:postcode":"2541 VS",
    "sg:province":"Zuid-Holland",
    "wof:name":"B\u00e9j\u00e9",
    "wof:placetype":"venue"
},
  "geometry": {"coordinates":[4.28115,52.04451],"type":"Point"}
}