{
  "type": "Feature",
  "properties": {
    "addr:full":"Zuideinde 19 Naaldwyk Zuid-Holland 2671 MG",
    "addr:housenumber":"19",
    "addr:postcode":"2671 mg",
    "addr:street":"Zuideinde",
    "iso:country":"NL",
    "sg:address":"Zuideinde 19",
    "sg:city":"Naaldwyk",
    "sg:orig_category":"Fietsen En Bromfietsen",
    "sg:phone":"+31 174 624 089",
    "sg:postcode":"2671 MG",
    "sg:province":"Zuid-Holland",
    "wof:name":"Hoogkamer, A & J",
    "wof:placetype":"venue"
},
  "geometry": {"coordinates":[4.206669,51.990971],"type":"Point"}
}