{
  "type": "Feature",
  "properties": {
    "addr:full":"Cannenburgerweg 51B Ankeveen Noord-Holland 1244 RG",
    "addr:housenumber":"51b",
    "addr:postcode":"1244 rg",
    "addr:street":"Cannenburgerweg",
    "iso:country":"NL",
    "sg:address":"Cannenburgerweg 51B",
    "sg:city":"Ankeveen",
    "sg:orig_category":"Autokeuringen",
    "sg:phone":"+31 35 656 4721",
    "sg:postcode":"1244 RG",
    "sg:province":"Noord-Holland",
    "wof:name":"Gooise Vw Club",
    "wof:placetype":"venue"
},
  "geometry": {"coordinates":[5.119882,52.25526],"type":"Point"}
}