{
  "type": "Feature",
  "properties": {
    "iso:country":"NL",
    "sg:address":"V Starkenborghhof 90",
    "sg:city":"Utrecht",
    "sg:orig_category":"Huishoudelijke Apparaten En Artikelen",
    "sg:phone":"+31 30 293 6559",
    "sg:postcode":"3527 HB",
    "sg:province":"Utrecht",
    "wof:name":"Expert Schuurman",
    "wof:placetype":"venue"
},
  "geometry": {"coordinates":[5.093115,52.075066],"type":"Point"}
}