{
  "type": "Feature",
  "properties": {
    "addr:full":"Midslandstr 84 Tilburg Noord-Brabant 5045 DL",
    "addr:housenumber":"84",
    "addr:postcode":"5045 dl",
    "addr:street":"Midslandstr",
    "iso:country":"NL",
    "sg:address":"Midslandstr 84",
    "sg:city":"Tilburg",
    "sg:orig_category":"Kappers",
    "sg:phone":"+31 13 543 3543",
    "sg:postcode":"5045 DL",
    "sg:province":"Noord-Brabant",
    "wof:name":"Mo'S",
    "wof:placetype":"venue"
},
  "geometry": {"coordinates":[4.983651,51.594791],"type":"Point"}
}