{
  "type": "Feature",
  "properties": {
    "addr:full":"S Gravenwg 244 Capelle Ad Yssel Zuid-Holland 2903 LW",
    "addr:housenumber":"244",
    "addr:postcode":"2903 lw",
    "iso:country":"NL",
    "sg:address":"S Gravenwg 244",
    "sg:city":"Capelle Ad Yssel",
    "sg:orig_category":"Onroerende Goederen",
    "sg:phone":"+31 182 630 277",
    "sg:postcode":"2903 LW",
    "sg:province":"Zuid-Holland",
    "wof:name":"Rehorst Krimpen Beheer Bv",
    "wof:placetype":"venue"
},
  "geometry": {"coordinates":[4.589838,51.938217],"type":"Point"}
}