{
  "type": "Feature",
  "properties": {
    "iso:country":"NL",
    "sg:address":"Strausslaan 36",
    "sg:city":"Voorthuizen",
    "sg:orig_category":"Bloemen And Planten Gh",
    "sg:phone":"+31 342 473 751",
    "sg:postcode":"3781 HN",
    "sg:province":"Gelderland",
    "wof:name":"Fleurosa Blumengrosshandel",
    "wof:placetype":"venue"
},
  "geometry": {"coordinates":[5.606088,52.181652],"type":"Point"}
}