{
  "type": "Feature",
  "properties": {
    "addr:full":"Ranonkelstraat 25 Amersfoort Utrecht 3812 XP",
    "addr:housenumber":"25",
    "addr:postcode":"3812 xp",
    "addr:street":"Ranonkelstraat",
    "iso:country":"NL",
    "sg:address":"Ranonkelstraat 25",
    "sg:city":"Amersfoort",
    "sg:orig_category":"Autokeuringen",
    "sg:phone":"+31 33 463 8056",
    "sg:postcode":"3812 XP",
    "sg:province":"Utrecht",
    "wof:name":"Hendriks",
    "wof:placetype":"venue"
},
  "geometry": {"coordinates":[5.356236,52.159477],"type":"Point"}
}