{
  "type": "Feature",
  "properties": {
    "addr:full":"V Coothpln 49 Breda Noord-Brabant 4811 ND",
    "addr:housenumber":"49",
    "addr:postcode":"4811 nd",
    "iso:country":"NL",
    "sg:address":"V Coothpln 49",
    "sg:city":"Breda",
    "sg:orig_category":"Werving En Selectie",
    "sg:phone":"+31 76 514 3947",
    "sg:postcode":"4811 ND",
    "sg:province":"Noord-Brabant",
    "sg:website":"http://www.creyfsintersales.nl",
    "wof:name":"Creyf'S Intersales",
    "wof:placetype":"venue"
},
  "geometry": {"coordinates":[4.7716851234,51.5913505554],"type":"Point"}
}