{
  "type": "Feature",
  "properties": {
    "addr:full":"Keizerswaard 56 Rotterdam South Holland 3078 AM",
    "addr:housenumber":"56",
    "addr:postcode":"3078",
    "addr:street":"Keizerswaard",
    "iso:country":"NL",
    "sg:address":"Keizerswaard 56",
    "sg:city":"Rotterdam",
    "sg:orig_category":"Fotolaboratoria",
    "sg:phone":"+31 10 479 2655",
    "sg:postcode":"3078 AM",
    "sg:province":"South Holland",
    "wof:name":"Foto Een Uur Service V & V",
    "wof:placetype":"venue"
},
  "geometry": {"coordinates":[4.547701,51.886349],"type":"Point"}
}