{
  "type": "Feature",
  "properties": {
    "addr:full":"Spaarndammerplnts 42-44 Amsterdam Noord-Holland 1013 XT",
    "addr:housenumber":"42-44",
    "addr:postcode":"1013 xt",
    "iso:country":"NL",
    "sg:address":"Spaarndammerplnts 42-44",
    "sg:city":"Amsterdam",
    "sg:orig_category":"Verenigingen En Stichtingen",
    "sg:phone":"+31 20 682 7614",
    "sg:postcode":"1013 XT",
    "sg:province":"Noord-Holland",
    "wof:name":"Vakvrouw, Sticht",
    "wof:placetype":"venue"
},
  "geometry": {"coordinates":[4.893195,52.373119],"type":"Point"}
}