{
  "type": "Feature",
  "properties": {
    "iso:country":"NL",
    "sg:address":"Willem Ii Straat 82",
    "sg:city":"Tilburg",
    "sg:orig_category":"Kappers",
    "sg:phone":"+31 13 542 2896",
    "sg:postcode":"5038 BJ",
    "sg:province":"North Brabant",
    "wof:name":"Fa J.P. Lejeune",
    "wof:placetype":"venue"
},
  "geometry": {"coordinates":[5.0868048668,51.5569114685],"type":"Point"}
}