{
  "type": "Feature",
  "properties": {
    "iso:country":"NL",
    "sg:address":"Van Tuldenstraat 25",
    "sg:city":"'S Hertogenbosch",
    "sg:classifiers":[
        {
            "category":"Shopping",
            "subcategory":"Gifts & Souvenirs",
            "type":"Retail Goods"
        }
    ],
    "sg:phone":"+31 73 614 5613",
    "sg:postcode":"5211 TG",
    "sg:province":"Noord-Brabant",
    "sg:tags":[
        "geschenken"
    ],
    "wof:name":"Marij'S Kadoshop",
    "wof:placetype":"venue"
},
  "geometry": {"coordinates":[5.302607,51.693604],"type":"Point"}
}