{
  "type": "Feature",
  "properties": {
    "iso:country":"NL",
    "sg:address":"Zydelry 8",
    "sg:city":"Uithoorn",
    "sg:orig_category":"Postkantoren",
    "sg:phone":"+31 297 567 146",
    "sg:postcode":"1422 BV",
    "sg:province":"Noord-Holland",
    "sg:website":"http://www.postkantoor.nl",
    "wof:name":"Postkantoor",
    "wof:placetype":"venue"
},
  "geometry": {"coordinates":[4.828947,52.233421],"type":"Point"}
}