{
  "type": "Feature",
  "properties": {
    "addr:full":"Bovendwwg 98 Oldebroek Gelderland 8096 PS",
    "addr:housenumber":"98",
    "addr:postcode":"8096 ps",
    "addr:street":"Bovendwwg;Gelderland",
    "iso:country":"NL",
    "sg:address":"Bovendwwg 98",
    "sg:city":"Oldebroek",
    "sg:orig_category":"Hek- En Rasterwerken",
    "sg:phone":"+31 525 651 883",
    "sg:postcode":"8096 PS",
    "sg:province":"Gelderland",
    "wof:name":"Esaz Vof",
    "wof:placetype":"venue"
},
  "geometry": {"coordinates":[5.918585,52.42733],"type":"Point"}
}