{
  "type": "Feature",
  "properties": {
    "addr:full":"Straat V Sicilie 22 Amstelveen North Holland 1183 GN",
    "addr:housenumber":"22",
    "addr:postcode":"1183 gn",
    "addr:street":"Straat V Sicilie",
    "iso:country":"NL",
    "sg:address":"Straat V Sicilie 22",
    "sg:city":"Amstelveen",
    "sg:orig_category":"Accountants - Administratie- Consulenten En -Kantoren",
    "sg:phone":"+31 20 643 3044",
    "sg:postcode":"1183 GN",
    "sg:province":"North Holland",
    "wof:name":"Slof & Co",
    "wof:placetype":"venue"
},
  "geometry": {"coordinates":[4.856945,52.303444],"type":"Point"}
}