{
  "type": "Feature",
  "properties": {
    "addr:full":"Langstraat 18 Geldrop North Brabant 5664 GG",
    "addr:housenumber":"18",
    "addr:postcode":"5664 gg",
    "addr:street":"Langstraat",
    "iso:country":"NL",
    "sg:address":"Langstraat 18",
    "sg:city":"Geldrop",
    "sg:orig_category":"Kappers",
    "sg:phone":"+31 40 285 4214",
    "sg:postcode":"5664 GG",
    "sg:province":"North Brabant",
    "wof:name":"Videoland Geldrop Bv",
    "wof:placetype":"venue"
},
  "geometry": {"coordinates":[5.559988,51.421268],"type":"Point"}
}