{
  "type": "Feature",
  "properties": {
    "iso:country":"NL",
    "sg:address":"Molenwerf 16",
    "sg:city":"Gouda",
    "sg:orig_category":"Partycatering And -Organisatie",
    "sg:phone":"+31 182 510 442",
    "sg:postcode":"2801 PP",
    "sg:province":"Zuid-Holland",
    "wof:name":"Restaurant De Bottelaar",
    "wof:placetype":"venue"
},
  "geometry": {"coordinates":[4.712153,52.009983],"type":"Point"}
}