{
  "type": "Feature",
  "properties": {
    "addr:full":"Leidsewg 117 Voorschoten South Holland 2253 AA",
    "addr:housenumber":"117",
    "addr:postcode":"2253 aa",
    "iso:country":"NL",
    "sg:address":"Leidsewg 117",
    "sg:city":"Voorschoten",
    "sg:orig_category":"Loodgieters",
    "sg:phone":"+31 71 561 6133",
    "sg:postcode":"2253 AA",
    "sg:province":"South Holland",
    "wof:name":"Deursen Bv, J A Van",
    "wof:placetype":"venue"
},
  "geometry": {"coordinates":[4.454465,52.130367],"type":"Point"}
}