{
  "type": "Feature",
  "properties": {
    "addr:full":"Ysselrust 2 Westervoort Gelderland 6932  D",
    "addr:housenumber":"2;6932 d",
    "addr:street":"Ysselrust;Gelderland",
    "iso:country":"NL",
    "sg:address":"Ysselrust 2",
    "sg:city":"Westervoort",
    "sg:orig_category":"Partycatering And -Organisatie",
    "sg:phone":"+31 26 446 4989",
    "sg:postcode":"6932  D",
    "sg:province":"Gelderland",
    "wof:name":"Catering Senang",
    "wof:placetype":"venue"
},
  "geometry": {"coordinates":[5.984441,51.950417],"type":"Point"}
}