{
  "type": "Feature",
  "properties": {
    "iso:country":"NL",
    "sg:address":"Slingerwg 70A",
    "sg:city":"Hippolytushoef",
    "sg:orig_category":"Oud Metaal",
    "sg:phone":"+31 227 591 990",
    "sg:postcode":"1777 AK",
    "sg:province":"North Holland",
    "wof:name":"Boer, J De",
    "wof:placetype":"venue"
},
  "geometry": {"coordinates":[4.9673790932,52.9098205566],"type":"Point"}
}