{
  "type": "Feature",
  "properties": {
    "addr:full":"Nautiluserf 27 Heerlen Limburg 6413 LR",
    "addr:housenumber":"27",
    "addr:postcode":"6413 lr",
    "addr:street":"Nautiluserf",
    "iso:country":"NL",
    "sg:address":"Nautiluserf 27",
    "sg:city":"Heerlen",
    "sg:orig_category":"Webdesign Bureaus",
    "sg:phone":"+31 45 522 0997",
    "sg:postcode":"6413 LR",
    "sg:province":"Limburg",
    "sg:website":"http://www.jerema.nl",
    "wof:name":"Jerema",
    "wof:placetype":"venue"
},
  "geometry": {"coordinates":[5.952188015,50.9132957458],"type":"Point"}
}