{
  "type": "Feature",
  "properties": {
    "addr:full":"Amelinkhorst 38 Enschede Overijssel 7531 GN",
    "addr:housenumber":"38",
    "addr:postcode":"7531 gn",
    "addr:street":"Amelinkhorst",
    "iso:country":"NL",
    "sg:address":"Amelinkhorst 38",
    "sg:city":"Enschede",
    "sg:orig_category":"Logopedisten",
    "sg:phone":"+31 53 432 7004",
    "sg:postcode":"7531 GN",
    "sg:province":"Overijssel",
    "wof:name":"Ludden-Nobbe, Wilma",
    "wof:placetype":"venue"
},
  "geometry": {"coordinates":[6.92298,52.226997],"type":"Point"}
}