{
  "type": "Feature",
  "properties": {
    "addr:full":"Kerkakkerstraat 118 Veldhoven Noord-Brabant 5504 GS",
    "addr:housenumber":"118",
    "addr:postcode":"5504 gs",
    "addr:street":"Kerkakkerstraat",
    "iso:country":"NL",
    "sg:address":"Kerkakkerstraat 118",
    "sg:city":"Veldhoven",
    "sg:orig_category":"Koeriersdiensten",
    "sg:phone":"+31 40 253 8790",
    "sg:postcode":"5504 GS",
    "sg:province":"Noord-Brabant",
    "wof:name":"Pranger Koeriersdienst",
    "wof:placetype":"venue"
},
  "geometry": {"coordinates":[5.406231,51.408752],"type":"Point"}
}