{
  "type": "Feature",
  "properties": {
    "iso:country":"NL",
    "sg:address":"Franekertrekvaart 12",
    "sg:city":"Harlingen",
    "sg:orig_category":"Onderhoudswerken",
    "sg:phone":"+31 517 413 270",
    "sg:postcode":"8861 HE",
    "sg:province":"Friesland",
    "wof:name":"Bouw 2000",
    "wof:placetype":"venue"
},
  "geometry": {"coordinates":[5.426264,53.173847],"type":"Point"}
}