{
  "type": "Feature",
  "properties": {
    "iso:country":"NL",
    "sg:address":"O Wellesstr 12",
    "sg:city":"Almere",
    "sg:orig_category":"Kantoor- En Secretariaatsservice",
    "sg:phone":"+31 36 537 6295",
    "sg:postcode":"1325 HB",
    "sg:province":"Flevoland",
    "sg:website":"http://www.sbb.nl",
    "wof:name":"Flevoland",
    "wof:placetype":"venue"
},
  "geometry": {"coordinates":[5.2283229828,52.371181488],"type":"Point"}
}