{
  "type": "Feature",
  "properties": {
    "iso:country":"NL",
    "sg:address":"Boomcateweg 92",
    "sg:city":"Nijverdal",
    "sg:orig_category":"Bloemen And Planten",
    "sg:phone":"+31 548 612 513",
    "sg:postcode":"7442 BL",
    "sg:province":"NL.08",
    "wof:name":"Garden Master Zonnebeld",
    "wof:placetype":"venue"
},
  "geometry": {"coordinates":[6.493334,52.353733],"type":"Point"}
}