{
  "type": "Feature",
  "properties": {
    "addr:full":"Kerkwg 78 Heemskerk Noord-Holland 1961 JE",
    "addr:housenumber":"78",
    "addr:postcode":"1961 je",
    "addr:street":"Kerkwg",
    "iso:country":"NL",
    "sg:address":"Kerkwg 78",
    "sg:city":"Heemskerk",
    "sg:orig_category":"Kinderkleding",
    "sg:phone":"+31 251 252 971",
    "sg:postcode":"1961 JE",
    "sg:province":"Noord-Holland",
    "wof:name":"Outfit",
    "wof:placetype":"venue"
},
  "geometry": {"coordinates":[4.667307,52.511292],"type":"Point"}
}