{
  "type": "Feature",
  "properties": {
    "addr:full":"Rhijngeesterstraatweg 13 Oegstgeest South Holland 2342 AN",
    "addr:housenumber":"13",
    "addr:postcode":"2342 an",
    "addr:street":"Rhijngeesterstraatweg",
    "iso:country":"NL",
    "sg:address":"Rhijngeesterstraatweg 13",
    "sg:city":"Oegstgeest",
    "sg:orig_category":"Overheidsdiensten",
    "sg:phone":"+31 71 519 1793",
    "sg:postcode":"2342 AN",
    "sg:province":"South Holland",
    "wof:name":"Gemeente Oegstgeest",
    "wof:placetype":"venue"
},
  "geometry": {"coordinates":[4.463198185,52.1780281067],"type":"Point"}
}