{
  "type": "Feature",
  "properties": {
    "addr:full":"Veerweg 4 Waspik Noord-Brabant 5165 NK",
    "addr:housenumber":"4",
    "addr:postcode":"5165 nk",
    "addr:street":"Veerweg",
    "iso:country":"NL",
    "sg:address":"Veerweg 4",
    "sg:city":"Waspik",
    "sg:orig_category":"Pleziervaartuigen And Reparatie",
    "sg:phone":"+31 416 312 181",
    "sg:postcode":"5165 NK",
    "sg:province":"Noord-Brabant",
    "wof:name":"De Toekomst J.J. Loose Bv",
    "wof:placetype":"venue"
},
  "geometry": {"coordinates":[4.943742,51.704174],"type":"Point"}
}