{
  "type": "Feature",
  "properties": {
    "addr:full":"Wilhelminastr 26 Stramproy Limburg 6039 AD",
    "addr:housenumber":"26",
    "addr:postcode":"6039 ad",
    "addr:street":"Wilhelminastr",
    "iso:country":"NL",
    "sg:address":"Wilhelminastr 26",
    "sg:city":"Stramproy",
    "sg:orig_category":"Vertaalbureaus",
    "sg:phone":"+31 495 563 669",
    "sg:postcode":"6039 AD",
    "sg:province":"Limburg",
    "wof:name":"Techno Trans Tro",
    "wof:placetype":"venue"
},
  "geometry": {"coordinates":[5.724026,51.19632],"type":"Point"}
}