{
  "type": "Feature",
  "properties": {
    "addr:full":"Acaciastraat 18 Malden Gelderland 6581 AN",
    "addr:housenumber":"18",
    "addr:postcode":"6581 an",
    "addr:street":"Acaciastraat;Gelderland",
    "iso:country":"NL",
    "sg:address":"Acaciastraat 18",
    "sg:city":"Malden",
    "sg:classifiers":[
        {
            "category":"Shopping",
            "subcategory":"Gifts & Souvenirs",
            "type":"Retail Goods"
        }
    ],
    "sg:phone":"+31 24 358 5391",
    "sg:postcode":"6581 AN",
    "sg:province":"Gelderland",
    "sg:tags":[
        "geschenken"
    ],
    "wof:name":"Van Verseveld",
    "wof:placetype":"venue"
},
  "geometry": {"coordinates":[5.847844,51.784084],"type":"Point"}
}