{
  "type": "Feature",
  "properties": {
    "addr:full":"Alerderbrink 22 Emmen Provincie Drenthe 7812 RV",
    "addr:housenumber":"22",
    "addr:postcode":"7812 rv",
    "addr:street":"Alerderbrink;Provincie Drenthe",
    "iso:country":"NL",
    "sg:address":"Alerderbrink 22",
    "sg:city":"Emmen",
    "sg:orig_category":"Verlichting And Huishoudartikelen",
    "sg:phone":"+31 591 619 483",
    "sg:postcode":"7812 RV",
    "sg:province":"Provincie Drenthe",
    "wof:name":"A Woltmeyer Luxe- Huish. Art. En Speelgo",
    "wof:placetype":"venue"
},
  "geometry": {"coordinates":[6.886205,52.764343],"type":"Point"}
}