{
  "type": "Feature",
  "properties": {
    "addr:full":"Buitenklingen 25 'S Gravenhage South Holland 2554 BT",
    "addr:housenumber":"25",
    "addr:postcode":"2554 bt",
    "addr:street":"Buitenklingen;' S Gravenhage",
    "iso:country":"NL",
    "sg:address":"Buitenklingen 25",
    "sg:city":"'S Gravenhage",
    "sg:orig_category":"Fitnesscentra",
    "sg:phone":"+31 70 325 6912",
    "sg:postcode":"2554 BT",
    "sg:province":"South Holland",
    "wof:name":"Fitnesscentrum On Top Sports",
    "wof:placetype":"venue"
},
  "geometry": {"coordinates":[4.222323,52.064892],"type":"Point"}
}