{
  "type": "Feature",
  "properties": {
    "iso:country":"NL",
    "sg:address":"Conradln 10",
    "sg:city":"Delft",
    "sg:orig_category":"Adviesbureaus Bouwkunde",
    "sg:phone":"+31 15 257 2255",
    "sg:postcode":"2627 BT",
    "sg:province":"South Holland",
    "sg:website":"http://www.jvanasten.nl",
    "wof:name":"Asten, J H M Van",
    "wof:placetype":"venue"
},
  "geometry": {"coordinates":[4.361281,52.003174],"type":"Point"}
}