{
  "type": "Feature",
  "properties": {
    "addr:full":"Garderbroekerwg 150 Kootwykerbroek Gelderland 3774 JH",
    "addr:housenumber":"150",
    "addr:postcode":"3774 jh",
    "addr:street":"Kootwykerbroek Gelderland",
    "iso:country":"NL",
    "sg:address":"Garderbroekerwg 150",
    "sg:city":"Kootwykerbroek",
    "sg:orig_category":"Machineonderhoud En -Reparatie",
    "sg:phone":"+31 6 10394781",
    "sg:postcode":"3774 JH",
    "sg:province":"Gelderland",
    "wof:name":"Brink, G Van Den",
    "wof:placetype":"venue"
},
  "geometry": {"coordinates":[5.674577,52.164307],"type":"Point"}
}