{
  "type": "Feature",
  "properties": {
    "addr:full":"Margrietstraat 32 Doesburg Gelderland 6981 GJ",
    "addr:housenumber":"32",
    "addr:postcode":"6981 gj",
    "addr:street":"Margrietstraat;Gelderland",
    "iso:country":"NL",
    "sg:address":"Margrietstraat 32",
    "sg:city":"Doesburg",
    "sg:orig_category":"Schilderwerk",
    "sg:phone":"+31 313 473 940",
    "sg:postcode":"6981 GJ",
    "sg:province":"Gelderland",
    "wof:name":"Doesburgs Schildersbedrijf Hans Nijland",
    "wof:placetype":"venue"
},
  "geometry": {"coordinates":[6.145606,52.012215],"type":"Point"}
}