{
  "type": "Feature",
  "properties": {
    "iso:country":"NL",
    "sg:address":"Ravensbos 21",
    "sg:city":"Hoofddorp",
    "sg:orig_category":"Juridische Adviseurs",
    "sg:phone":"+31 23 563 6796",
    "sg:postcode":"2134 TN",
    "sg:province":"Noord-Holland",
    "wof:name":"Pardaan",
    "wof:placetype":"venue"
},
  "geometry": {"coordinates":[4.660567,52.320637],"type":"Point"}
}