{
  "type": "Feature",
  "properties": {
    "addr:full":"Rozenstraat 66 Tilburg Noord-Brabant 5014 AL",
    "addr:housenumber":"66",
    "addr:postcode":"5014 al",
    "addr:street":"Rozenstraat",
    "iso:country":"NL",
    "sg:address":"Rozenstraat 66",
    "sg:city":"Tilburg",
    "sg:orig_category":"Loodgieterswerk, Verwarming And Sanitaire Installaties",
    "sg:phone":"+31 13 542 7655",
    "sg:postcode":"5014 AL",
    "sg:province":"Noord-Brabant",
    "wof:name":"Jurgen Hamer",
    "wof:placetype":"venue"
},
  "geometry": {"coordinates":[5.095019,51.560627],"type":"Point"}
}