{
  "type": "Feature",
  "properties": {
    "addr:full":"Dorpsstraat 132 Halsteren Noord-Brabant 4661 HT",
    "addr:housenumber":"132",
    "addr:postcode":"4661 ht",
    "addr:street":"Dorpsstraat",
    "iso:country":"NL",
    "sg:address":"Dorpsstraat 132",
    "sg:city":"Halsteren",
    "sg:orig_category":"Wasserettes And Stomerijen",
    "sg:phone":"+31 164 685 692",
    "sg:postcode":"4661 HT",
    "sg:province":"Noord-Brabant",
    "wof:name":"Wassalon 'T Centrum",
    "wof:placetype":"venue"
},
  "geometry": {"coordinates":[4.2702670097,51.5241737366],"type":"Point"}
}