{
  "type": "Feature",
  "properties": {
    "addr:full":"Zuideinde 400 Amsterdam Noord-Holland 1035 PR",
    "addr:housenumber":"400",
    "addr:postcode":"1035 pr",
    "addr:street":"Zuideinde",
    "iso:country":"NL",
    "sg:address":"Zuideinde 400",
    "sg:city":"Amsterdam",
    "sg:orig_category":"Schilderwerk",
    "sg:phone":"+31 20 631 6558",
    "sg:postcode":"1035 PR",
    "sg:province":"Noord-Holland",
    "wof:name":"Schildersbedrijf M.B. Huijbrechts",
    "wof:placetype":"venue"
},
  "geometry": {"coordinates":[4.894785,52.417946],"type":"Point"}
}