{
  "type": "Feature",
  "properties": {
    "addr:full":"Burgemeester Godwaldtstr 4 Hooge Zwaluwe North Brabant 4927 BB",
    "addr:housenumber":"4",
    "addr:postcode":"4927 bb",
    "addr:street":"Burgemeester Godwaldtstr",
    "iso:country":"NL",
    "sg:address":"Burgemeester Godwaldtstr 4",
    "sg:city":"Hooge Zwaluwe",
    "sg:classifiers":[
        {
            "category":"Education",
            "subcategory":"Preschool",
            "type":"Public Place"
        }
    ],
    "sg:phone":"+31 168 483 368",
    "sg:postcode":"4927 BB",
    "sg:province":"North Brabant",
    "sg:tags":[
        "kleuteronderwijs",
        "basis-"
    ],
    "wof:name":"Basisschool St. Jan",
    "wof:placetype":"venue"
},
  "geometry": {"coordinates":[4.747715,51.684608],"type":"Point"}
}