{
  "type": "Feature",
  "properties": {
    "iso:country":"NL",
    "sg:address":"Oosterhoutsestraat 89A",
    "sg:city":"Oosterhout Gld",
    "sg:orig_category":"Bloemen And Planten",
    "sg:phone":"+31 481 482 203",
    "sg:postcode":"6678 PG",
    "sg:province":"Gelderland",
    "wof:name":"J.W. Eeuwes",
    "wof:placetype":"venue"
},
  "geometry": {"coordinates":[5.817175,51.882111],"type":"Point"}
}