{
  "type": "Feature",
  "properties": {
    "addr:full":"Nettenboetsterstraat 1 Vlaardingen Zuid-Holland 3133 EP",
    "addr:housenumber":"1",
    "addr:postcode":"3133 ep",
    "addr:street":"Nettenboetsterstraat",
    "iso:country":"NL",
    "sg:address":"Nettenboetsterstraat 1",
    "sg:city":"Vlaardingen",
    "sg:orig_category":"Meubelzaken, Woning- And Keukeninrichting",
    "sg:phone":"+31 10 234 0189",
    "sg:postcode":"3133 EP",
    "sg:province":"Zuid-Holland",
    "wof:name":"Leenbakker",
    "wof:placetype":"venue"
},
  "geometry": {"coordinates":[4.332702,51.905628],"type":"Point"}
}