{
  "type": "Feature",
  "properties": {
    "addr:full":"Smithilsewg 8 Hellevoetsluis South Holland 3223 BR",
    "addr:housenumber":"8",
    "addr:postcode":"3223 br",
    "addr:street":"Smithilsewg",
    "iso:country":"NL",
    "sg:address":"Smithilsewg 8",
    "sg:city":"Hellevoetsluis",
    "sg:orig_category":"Loodgieters",
    "sg:phone":"+31 181 312 083",
    "sg:postcode":"3223 BR",
    "sg:province":"South Holland",
    "wof:name":"Postma, A J",
    "wof:placetype":"venue"
},
  "geometry": {"coordinates":[4.147081,51.855072],"type":"Point"}
}