{
  "type": "Feature",
  "properties": {
    "addr:full":"Hobbemaln 31 Helmond Noord-Brabant 5702 VV",
    "addr:housenumber":"31",
    "addr:postcode":"5702 vv",
    "addr:street":"Hobbemaln",
    "iso:country":"NL",
    "sg:address":"Hobbemaln 31",
    "sg:city":"Helmond",
    "sg:orig_category":"Vertaalbureaus",
    "sg:phone":"+31 492 590 874",
    "sg:postcode":"5702 VV",
    "sg:province":"Noord-Brabant",
    "sg:website":"http://www.omnitaal.nl",
    "wof:name":"Omnitaal",
    "wof:placetype":"venue"
},
  "geometry": {"coordinates":[5.675927,51.489822],"type":"Point"}
}