{
  "type": "Feature",
  "properties": {
    "iso:country":"NL",
    "sg:address":"Godsweerderstraat 27",
    "sg:city":"Roermond",
    "sg:orig_category":"Overheidsdiensten",
    "sg:phone":"+31 475 395 700",
    "sg:postcode":"6041 GH",
    "sg:province":"Limburg",
    "wof:name":"Belastingdienst Registratie En Successie 'S Hertog",
    "wof:placetype":"venue"
},
  "geometry": {"coordinates":[5.9924678802,51.1953659058],"type":"Point"}
}