{
  "type": "Feature",
  "properties": {
    "addr:full":"Achterbaan 23 Huizen North Holland 1271 TX",
    "addr:housenumber":"23",
    "addr:postcode":"1271 tx",
    "addr:street":"Achterbaan",
    "iso:country":"NL",
    "sg:address":"Achterbaan 23",
    "sg:city":"Huizen",
    "sg:orig_category":"Opticiens",
    "sg:phone":"+31 35 525 8932",
    "sg:postcode":"1271 TX",
    "sg:province":"North Holland",
    "sg:website":"http://www.hansanders.nl",
    "wof:name":"Hans Anders",
    "wof:placetype":"venue"
},
  "geometry": {"coordinates":[5.2348461151,52.2987480164],"type":"Point"}
}