{
  "type": "Feature",
  "properties": {
    "addr:full":"Patrimoniumlaan 50A Veenendaal Utrecht 3904 AE",
    "addr:housenumber":"50a",
    "addr:postcode":"3904 ae",
    "addr:street":"Patrimoniumlaan",
    "iso:country":"NL",
    "sg:address":"Patrimoniumlaan 50A",
    "sg:city":"Veenendaal",
    "sg:classifiers":[
        {
            "category":"Fast Food",
            "type":"Food & Drink"
        }
    ],
    "sg:phone":"+31 318 589 937",
    "sg:postcode":"3904 AE",
    "sg:province":"Utrecht",
    "sg:tags":[
        "afhaal",
        "restaurant"
    ],
    "wof:name":"T Veen",
    "wof:placetype":"venue"
},
  "geometry": {"coordinates":[5.545918,52.019337],"type":"Point"}
}