{
  "type": "Feature",
  "properties": {
    "addr:full":"Postbus 2168 Amersfoort Utrecht 3800 CD",
    "addr:housenumber":"2168",
    "addr:postcode":"3800 cd",
    "addr:street":"Postbus",
    "iso:country":"NL",
    "sg:address":"Postbus 2168",
    "sg:city":"Amersfoort",
    "sg:classifiers":[
        {
            "category":"Professional",
            "subcategory":"Management & Consulting",
            "type":"Services"
        }
    ],
    "sg:phone":"+31 33 477 9392",
    "sg:postcode":"3800 CD",
    "sg:province":"Utrecht",
    "sg:tags":[
        "relation",
        "adviesbureaus",
        "public"
    ],
    "sg:website":"http://www.breuls.nl",
    "wof:name":"Breuls Creatieve Communicatie",
    "wof:placetype":"venue"
},
  "geometry": {"coordinates":[5.38959,52.156101],"type":"Point"}
}