{
  "type": "Feature",
  "properties": {
    "addr:full":"Brabantstraat 1 Deurne Noord-Brabant 5751 AL",
    "addr:housenumber":"1",
    "addr:postcode":"5751 al",
    "addr:street":"Brabantstraat",
    "iso:country":"NL",
    "sg:address":"Brabantstraat 1",
    "sg:city":"Deurne",
    "sg:orig_category":"Kunst And Kunstenaarsbenodigdheden",
    "sg:phone":"+31 493 315 183",
    "sg:postcode":"5751 AL",
    "sg:province":"Noord-Brabant",
    "wof:name":"J.J.M. Van Der Zwaan",
    "wof:placetype":"venue"
},
  "geometry": {"coordinates":[5.799515,51.464298],"type":"Point"}
}