{
  "type": "Feature",
  "properties": {
    "addr:full":"Aalscholverln 75 Nykerk Gld Gelderland 3862 KK",
    "addr:housenumber":"75",
    "addr:postcode":"3862 kk",
    "addr:street":"Aalscholverln;Gld Gelderland",
    "iso:country":"NL",
    "sg:address":"Aalscholverln 75",
    "sg:city":"Nykerk Gld",
    "sg:orig_category":"Graveerbedrijven",
    "sg:phone":"+31 33 245 2499",
    "sg:postcode":"3862 KK",
    "sg:province":"Gelderland",
    "wof:name":"Koudijs",
    "wof:placetype":"venue"
},
  "geometry": {"coordinates":[5.62297,52.20557],"type":"Point"}
}