{
  "type": "Feature",
  "properties": {
    "addr:full":"W Rosestr 1B Eindhoven Noord-Brabant 5622 GH",
    "addr:housenumber":"1b",
    "addr:postcode":"5622 gh",
    "addr:street":"W",
    "iso:country":"NL",
    "sg:address":"W Rosestr 1B",
    "sg:city":"Eindhoven",
    "sg:orig_category":"Adviesbureaus Bouwkosten",
    "sg:phone":"+31 40 212 7084",
    "sg:postcode":"5622 GH",
    "sg:province":"Noord-Brabant",
    "wof:name":"Bumec Bouwkosten Support",
    "wof:placetype":"venue"
},
  "geometry": {"coordinates":[5.466802,51.465809],"type":"Point"}
}