{
  "type": "Feature",
  "properties": {
    "addr:full":"Oude Rykswg 236 Rouveen NL.08 7954 DR",
    "addr:housenumber":"236;nl.08 7954",
    "addr:street":"Oude Rykswg;Dr",
    "iso:country":"NL",
    "sg:address":"Oude Rykswg 236",
    "sg:city":"Rouveen",
    "sg:orig_category":"Fietsen En Bromfietsen",
    "sg:phone":"+31 522 291 732",
    "sg:postcode":"7954 DR",
    "sg:province":"NL.08",
    "sg:website":"http://www.4-strokebikecentre.com",
    "wof:name":"Four Stroke Bike Centre",
    "wof:placetype":"venue"
},
  "geometry": {"coordinates":[6.186416,52.615215],"type":"Point"}
}