{
  "type": "Feature",
  "properties": {
    "addr:full":"Zwanenburgerdijk 328 Zwanenburg North Holland 1161 NN",
    "addr:housenumber":"328",
    "addr:postcode":"1161 nn",
    "addr:street":"Zwanenburgerdijk",
    "iso:country":"NL",
    "sg:address":"Zwanenburgerdijk 328",
    "sg:city":"Zwanenburg",
    "sg:orig_category":"Pompen And Compressoren Fab",
    "sg:phone":"+31 20 497 6780",
    "sg:postcode":"1161 NN",
    "sg:province":"North Holland",
    "wof:name":"Spraybest Europe Bv",
    "wof:placetype":"venue"
},
  "geometry": {"coordinates":[4.737078,52.384949],"type":"Point"}
}