{
  "type": "Feature",
  "properties": {
    "addr:full":"Waldeck Pyrmontkade 872G 'S-Gravenhage Zuid-Holland 2518 JS",
    "addr:housenumber":"872g",
    "addr:postcode":"s-gravenhage;2518 js",
    "addr:street":"Waldeck Pyrmontkade",
    "iso:country":"NL",
    "sg:address":"Waldeck Pyrmontkade 872G",
    "sg:city":"'S-Gravenhage",
    "sg:orig_category":"Verkeersbureaus",
    "sg:phone":"+31 70 346 9998",
    "sg:postcode":"2518 JS",
    "sg:province":"Zuid-Holland",
    "wof:name":"Turks Nationaal",
    "wof:placetype":"venue"
},
  "geometry": {"coordinates":[4.29348,52.080318],"type":"Point"}
}