{
  "type": "Feature",
  "properties": {
    "addr:full":"Westermeerweg 47 Espel Minnesota 8311 PG",
    "addr:housenumber":"47",
    "addr:postcode":"8311",
    "addr:street":"Westermeerweg;Minnesota;Pg",
    "iso:country":"NL",
    "sg:address":"Westermeerweg 47",
    "sg:city":"Espel",
    "sg:orig_category":"Artiestenbureaus",
    "sg:phone":"+31 527 271 398",
    "sg:postcode":"8311 PG",
    "sg:province":"Minnesota",
    "wof:name":"Vincu Zigeunermuziek",
    "wof:placetype":"venue"
},
  "geometry": {"coordinates":[-95.71624799999999,48.223763],"type":"Point"}
}