{
  "type": "Feature",
  "properties": {
    "addr:full":"Grt Hoogstr 3 Leeuwarden Friesland 8911 GZ",
    "addr:housenumber":"3",
    "addr:postcode":"8911 gz",
    "addr:street":"Hoogstr",
    "iso:country":"NL",
    "sg:address":"Grt Hoogstr 3",
    "sg:city":"Leeuwarden",
    "sg:orig_category":"Onroerende Goederen",
    "sg:phone":"+31 58 213 3205",
    "sg:postcode":"8911 GZ",
    "sg:province":"Friesland",
    "wof:name":"Kem Bv",
    "wof:placetype":"venue"
},
  "geometry": {"coordinates":[5.797208,53.201897],"type":"Point"}
}