{
  "type": "Feature",
  "properties": {
    "addr:full":"Industriestr 33 Hoensbroek Limburg 6433 JW",
    "addr:housenumber":"33",
    "addr:postcode":"6433 jw",
    "addr:street":"Industriestr",
    "iso:country":"NL",
    "sg:address":"Industriestr 33",
    "sg:city":"Hoensbroek",
    "sg:orig_category":"Bodemonderzoek",
    "sg:phone":"+31 45 522 6633",
    "sg:postcode":"6433 JW",
    "sg:province":"Limburg",
    "sg:website":"http://www.geo-consult.nl",
    "wof:name":"Geoconsult Geo & Milieutechniek",
    "wof:placetype":"venue"
},
  "geometry": {"coordinates":[5.939121,50.904903],"type":"Point"}
}