{
  "type": "Feature",
  "properties": {
    "addr:full":"Jacob Cremerstr 36 Arnhem Gelderland 6821 DE",
    "addr:housenumber":"36",
    "addr:postcode":"6821 de",
    "iso:country":"NL",
    "sg:address":"Jacob Cremerstr 36",
    "sg:city":"Arnhem",
    "sg:orig_category":"Kappers",
    "sg:phone":"+31 26 442 7660",
    "sg:postcode":"6821 DE",
    "sg:province":"Gelderland",
    "wof:name":"Drent, Ria",
    "wof:placetype":"venue"
},
  "geometry": {"coordinates":[5.9100561142,51.9885253906],"type":"Point"}
}