{
  "type": "Feature",
  "properties": {
    "addr:full":"Dr Kuyperstr 3 Kaatsheuvel Noord-Brabant 5171 KB",
    "addr:housenumber":"3",
    "addr:postcode":"5171 kb",
    "iso:country":"NL",
    "sg:address":"Dr Kuyperstr 3",
    "sg:city":"Kaatsheuvel",
    "sg:classifiers":[
        {
            "category":"Personal",
            "subcategory":"Nail Salon",
            "type":"Services"
        }
    ],
    "sg:phone":"+31 416 276 106",
    "sg:postcode":"5171 KB",
    "sg:province":"Noord-Brabant",
    "sg:tags":[
        "pedicure"
    ],
    "wof:name":"Vrijhoeven-Van Dongen, E J H",
    "wof:placetype":"venue"
},
  "geometry": {"coordinates":[5.043803,51.657295],"type":"Point"}
}