{
  "type": "Feature",
  "properties": {
    "iso:country":"NL",
    "sg:address":"Westzeedk 116",
    "sg:city":"Rotterdam",
    "sg:orig_category":"Verenigingen En Stichtingen",
    "sg:phone":"+31 10 436 9590",
    "sg:postcode":"3016 AH",
    "sg:province":"South Holland",
    "wof:name":"Exodus",
    "wof:placetype":"venue"
},
  "geometry": {"coordinates":[4.474499,51.910187],"type":"Point"}
}