{
  "type": "Feature",
  "properties": {
    "iso:country":"NL",
    "sg:address":"P Koppesstr 37",
    "sg:city":"Spierdyk",
    "sg:classifiers":[
        {
            "category":"Personal",
            "subcategory":"Nail Salon",
            "type":"Services"
        }
    ],
    "sg:phone":"+31 229 561 527",
    "sg:postcode":"1641 LT",
    "sg:province":"North Holland",
    "sg:tags":[
        "pedicure"
    ],
    "wof:name":"Gouw, A",
    "wof:placetype":"venue"
},
  "geometry": {"coordinates":[4.942872,52.650074],"type":"Point"}
}