{
  "type": "Feature",
  "properties": {
    "addr:full":"Halve Morgen 73 Westervoort Gelderland 6931 XH",
    "addr:housenumber":"73",
    "addr:postcode":"6931 xh",
    "addr:street":"Halve Morgen;Gelderland",
    "iso:country":"NL",
    "sg:address":"Halve Morgen 73",
    "sg:city":"Westervoort",
    "sg:orig_category":"Kantoorartikelen",
    "sg:phone":"+31 26 311 4662",
    "sg:postcode":"6931 XH",
    "sg:province":"Gelderland",
    "wof:name":"Digit Elektronika",
    "wof:placetype":"venue"
},
  "geometry": {"coordinates":[5.975757122,51.9534492493],"type":"Point"}
}