{
  "type": "Feature",
  "properties": {
    "addr:full":"Schildwg 2E Eemshaven Groningen 9979 XR",
    "addr:housenumber":"2e",
    "addr:postcode":"9979 xr",
    "addr:street":"Schildwg",
    "iso:country":"NL",
    "sg:address":"Schildwg 2E",
    "sg:city":"Eemshaven",
    "sg:orig_category":"Adviesbureaus Verzekeringen",
    "sg:phone":"+31 596 516 091",
    "sg:postcode":"9979 XR",
    "sg:province":"Groningen",
    "wof:name":"Beaureaal Bv",
    "wof:placetype":"venue"
},
  "geometry": {"coordinates":[6.816575,53.444576],"type":"Point"}
}