{
  "type": "Feature",
  "properties": {
    "iso:country":"NL",
    "sg:address":"Schildwg 2E",
    "sg:city":"Eemshaven",
    "sg:orig_category":"Adviesbureaus Verzekeringen",
    "sg:phone":"+31 596 516 091",
    "sg:postcode":"9979 XR",
    "sg:province":"Groningen",
    "wof:name":"Beaureaal Bv",
    "wof:placetype":"venue"
},
  "geometry": {"coordinates":[6.816575,53.444576],"type":"Point"}
}