{
  "type": "Feature",
  "properties": {
    "iso:country":"NL",
    "sg:address":"Van Noortlaan 40",
    "sg:city":"Harderwijk",
    "sg:orig_category":"Loodgieterswerk, Verwarming And Sanitaire Installaties",
    "sg:phone":"+31 341 426 407",
    "sg:postcode":"3843 HC",
    "sg:province":"Gelderland",
    "wof:name":"H.A.A. Beijersbergen Van Henegouwen",
    "wof:placetype":"venue"
},
  "geometry": {"coordinates":[5.641316,52.339481],"type":"Point"}
}