{
  "type": "Feature",
  "properties": {
    "addr:full":"Dr Cuypersstr 1 Oudenbosch Noord-Brabant 4731 GA",
    "addr:housenumber":"1",
    "addr:postcode":"4731 ga",
    "iso:country":"NL",
    "sg:address":"Dr Cuypersstr 1",
    "sg:city":"Oudenbosch",
    "sg:orig_category":"Artsen - Huisartsen",
    "sg:phone":"+31 165 313 511",
    "sg:postcode":"4731 GA",
    "sg:province":"Noord-Brabant",
    "wof:name":"Eysbouts, J H H",
    "wof:placetype":"venue"
},
  "geometry": {"coordinates":[4.543086,51.59127],"type":"Point"}
}