{
  "type": "Feature",
  "properties": {
    "iso:country":"NL",
    "sg:address":"Mathenessestraat 37",
    "sg:city":"Breda",
    "sg:orig_category":"Diverse Consumentenartikelen Gh",
    "sg:phone":"+31 76 565 6626",
    "sg:postcode":"4834 EA",
    "sg:province":"Noord-Brabant",
    "wof:name":"Wester Delta Firma",
    "wof:placetype":"venue"
},
  "geometry": {"coordinates":[4.800298,51.573071],"type":"Point"}
}