{
  "type": "Feature",
  "properties": {
    "addr:full":"Eemskanaal Noordzijde 48 Groningen Groningen 9713 AB",
    "addr:housenumber":"48",
    "addr:postcode":"9713 ab",
    "addr:street":"Eemskanaal Noordzijde",
    "iso:country":"NL",
    "sg:address":"Eemskanaal Noordzijde 48",
    "sg:city":"Groningen",
    "sg:orig_category":"Metaalafval, Schrootrecycling And Sloperijen",
    "sg:phone":"+31 50 318 5496",
    "sg:postcode":"9713 AB",
    "sg:province":"Groningen",
    "wof:name":"Autosloperij Noord",
    "wof:placetype":"venue"
},
  "geometry": {"coordinates":[6.58174,53.21777],"type":"Point"}
}