{
  "type": "Feature",
  "properties": {
    "addr:full":"Hyacintenln 9 Hillegom Zuid-Holland 2182 DE",
    "addr:housenumber":"9",
    "addr:postcode":"2182 de",
    "addr:street":"Hyacintenln",
    "iso:country":"NL",
    "sg:address":"Hyacintenln 9",
    "sg:city":"Hillegom",
    "sg:orig_category":"Bloemen En Planten - Groothandel",
    "sg:phone":"+31 252 518 752",
    "sg:postcode":"2182 DE",
    "sg:province":"Zuid-Holland",
    "wof:name":"Aanhane-Duivenvoorden, Fa",
    "wof:placetype":"venue"
},
  "geometry": {"coordinates":[4.570428,52.277943],"type":"Point"}
}