{
  "type": "Feature",
  "properties": {
    "addr:full":"Utrechtse Jaagpad 76 Leiden South Holland 2314 AR",
    "addr:housenumber":"76",
    "addr:postcode":"2314",
    "addr:street":"Utrechtse Jaagpad",
    "iso:country":"NL",
    "sg:address":"Utrechtse Jaagpad 76",
    "sg:city":"Leiden",
    "sg:orig_category":"Autokeuringen",
    "sg:phone":"+31 71 541 9988",
    "sg:postcode":"2314 AR",
    "sg:province":"South Holland",
    "wof:name":"Aegon Van Den Berg",
    "wof:placetype":"venue"
},
  "geometry": {"coordinates":[4.515286,52.15519],"type":"Point"}
}