{
  "type": "Feature",
  "properties": {
    "iso:country":"NL",
    "sg:address":"Trilgras 6",
    "sg:city":"Gouda",
    "sg:orig_category":"Advocaten En Advocatenkantoren",
    "sg:phone":"+31 182 532 039",
    "sg:postcode":"2804 NL",
    "sg:province":"Zuid-Holland",
    "wof:name":"Hilhes Bv",
    "wof:placetype":"venue"
},
  "geometry": {"coordinates":[4.712695,52.031536],"type":"Point"}
}