{
  "type": "Feature",
  "properties": {
    "addr:full":"T Hoekske 4 Ulvenhout Noord-Brabant 4851 SZ",
    "addr:housenumber":"4",
    "addr:postcode":"4851 sz",
    "addr:street":"T Hoekske",
    "iso:country":"NL",
    "sg:address":"T Hoekske 4",
    "sg:city":"Ulvenhout",
    "sg:classifiers":[
        {
            "category":"Education",
            "subcategory":"Special Training",
            "type":"Public Place"
        }
    ],
    "sg:phone":"+31 76 564 0804",
    "sg:postcode":"4851 SZ",
    "sg:province":"Noord-Brabant",
    "sg:tags":[
        "expertise"
    ],
    "sg:website":"http://www.objectief.com",
    "wof:name":"Objectief",
    "wof:placetype":"venue"
},
  "geometry": {"coordinates":[4.797575,51.539387],"type":"Point"}
}