{
  "type": "Feature",
  "properties": {
    "addr:full":"Ruychaverstr 16Zw Haarlem Noord-Holland 2013 GE",
    "addr:housenumber":"16zw",
    "addr:postcode":"2013",
    "addr:street":"Ruychaverstr",
    "iso:country":"NL",
    "sg:address":"Ruychaverstr 16Zw",
    "sg:city":"Haarlem",
    "sg:orig_category":"Beeldende Kunstenaars",
    "sg:phone":"+31 23 531 1757",
    "sg:postcode":"2013 GE",
    "sg:province":"Noord-Holland",
    "wof:name":"Gugten, R Van Der",
    "wof:placetype":"venue"
},
  "geometry": {"coordinates":[4.627909,52.383377],"type":"Point"}
}