{
  "type": "Feature",
  "properties": {
    "addr:full":"Barteljorisstr 8 Haarlem Noord-Holland 2011 RB",
    "addr:housenumber":"8",
    "addr:postcode":"2011 rb",
    "addr:street":"Barteljorisstr",
    "iso:country":"NL",
    "sg:address":"Barteljorisstr 8",
    "sg:city":"Haarlem",
    "sg:orig_category":"Gordijnen",
    "sg:phone":"+31 23 531 0537",
    "sg:postcode":"2011 RB",
    "sg:province":"Noord-Holland",
    "wof:name":"Barteljoris Bv",
    "wof:placetype":"venue"
},
  "geometry": {"coordinates":[4.635002,52.382652],"type":"Point"}
}