{
  "type": "Feature",
  "properties": {
    "addr:full":"De Loper 56-58 Vlaardingen South Holland 3137 DD",
    "addr:housenumber":"56-58",
    "addr:postcode":"3137 dd",
    "addr:street":"De Loper",
    "iso:country":"NL",
    "sg:address":"De Loper 56-58",
    "sg:city":"Vlaardingen",
    "sg:orig_category":"Herenkleding",
    "sg:phone":"+31 10 474 7350",
    "sg:postcode":"3137 DD",
    "sg:province":"South Holland",
    "wof:name":"Halkes",
    "wof:placetype":"venue"
},
  "geometry": {"coordinates":[4.346701,51.931107],"type":"Point"}
}