{
  "type": "Feature",
  "properties": {
    "addr:full":"Energiewg 18 Mydrecht Utrecht 3641 RT",
    "addr:housenumber":"18;3641",
    "addr:street":"Energiewg;Rt",
    "iso:country":"NL",
    "sg:address":"Energiewg 18",
    "sg:city":"Mydrecht",
    "sg:orig_category":"Betonijzervlechten",
    "sg:phone":"+31 297 289 252",
    "sg:postcode":"3641 RT",
    "sg:province":"Utrecht",
    "sg:website":"http://www.oudenallen.nl",
    "wof:name":"Oudenallen Bv, Van",
    "wof:placetype":"venue"
},
  "geometry": {"coordinates":[4.86178,52.20578],"type":"Point"}
}