{
  "type": "Feature",
  "properties": {
    "addr:full":"Kanaalstraat 100 Lisse North Holland 2161 JR",
    "addr:housenumber":"100",
    "addr:postcode":"2161 jr",
    "addr:street":"Kanaalstraat",
    "iso:country":"NL",
    "sg:address":"Kanaalstraat 100",
    "sg:city":"Lisse",
    "sg:orig_category":"Werving And Selectie Van Tijdelijk Personeel And Uitzendkantoren",
    "sg:phone":"+31 252 419 140",
    "sg:postcode":"2161 JR",
    "sg:province":"North Holland",
    "wof:name":"Randstad Uitzendbureau Bv",
    "wof:placetype":"venue"
},
  "geometry": {"coordinates":[4.5602769852,52.2592430115],"type":"Point"}
}