{
  "type": "Feature",
  "properties": {
    "addr:full":"Dorpsstr 73 Warmond South Holland 2361 AV",
    "addr:housenumber":"73",
    "addr:postcode":"2361 av",
    "addr:street":"Dorpsstr",
    "iso:country":"NL",
    "sg:address":"Dorpsstr 73",
    "sg:city":"Warmond",
    "sg:orig_category":"Makelaars En Adviseurs Onroerende Goederen",
    "sg:phone":"+31 71 301 1621",
    "sg:postcode":"2361 AV",
    "sg:province":"South Holland",
    "sg:website":"http://www.vansoest.nl",
    "wof:name":"Soest Warmond, Van",
    "wof:placetype":"venue"
},
  "geometry": {"coordinates":[4.505933,52.197937],"type":"Point"}
}