{
  "type": "Feature",
  "properties": {
    "addr:full":"Struytse Hoeck 142 Hellevoetsluis South Holland 3224 HB",
    "addr:housenumber":"142",
    "addr:postcode":"3224 hb",
    "addr:street":"Struytse Hoeck",
    "iso:country":"NL",
    "sg:address":"Struytse Hoeck 142",
    "sg:city":"Hellevoetsluis",
    "sg:orig_category":"Fotostudio'S And Fotografen",
    "sg:phone":"+31 181 318 340",
    "sg:postcode":"3224 HB",
    "sg:province":"South Holland",
    "wof:name":"Theo",
    "wof:placetype":"venue"
},
  "geometry": {"coordinates":[4.146577,51.830696],"type":"Point"}
}