{
  "type": "Feature",
  "properties": {
    "iso:country":"NL",
    "sg:address":"Damstr 25",
    "sg:city":"Haarlem",
    "sg:orig_category":"Adviesbureaus Financieel",
    "sg:phone":"+31 23 526 0441",
    "sg:postcode":"2011 HA",
    "sg:province":"Noord-Holland",
    "wof:name":"Objectief Advies Bv",
    "wof:placetype":"venue"
},
  "geometry": {"coordinates":[4.639415,52.380402],"type":"Point"}
}