{
  "type": "Feature",
  "properties": {
    "addr:full":"Havik 63 Etten Leur Noord-Brabant 4872 WX",
    "addr:housenumber":"63",
    "addr:postcode":"4872 wx",
    "addr:street":"Havik",
    "iso:country":"NL",
    "sg:address":"Havik 63",
    "sg:city":"Etten Leur",
    "sg:orig_category":"Behangselpapier En Wandbekleding",
    "sg:phone":"+31 76 503 5054",
    "sg:postcode":"4872 WX",
    "sg:province":"Noord-Brabant",
    "wof:name":"Blom",
    "wof:placetype":"venue"
},
  "geometry": {"coordinates":[4.653416,51.572636],"type":"Point"}
}