{
  "type": "Feature",
  "properties": {
    "addr:full":"Meppelrade 173 S Gravenhage Zuid-Holland 2544 XP",
    "addr:housenumber":"173;gravenhage",
    "addr:postcode":"2544 xp",
    "addr:street":"Meppelrade;S",
    "iso:country":"NL",
    "sg:address":"Meppelrade 173",
    "sg:city":"S Gravenhage",
    "sg:orig_category":"Organisatiebureaus",
    "sg:phone":"+31 70 367 5351",
    "sg:postcode":"2544 XP",
    "sg:province":"Zuid-Holland",
    "wof:name":"Direct Action",
    "wof:placetype":"venue"
},
  "geometry": {"coordinates":[4.2515702248,52.0395507812],"type":"Point"}
}