{
  "type": "Feature",
  "properties": {
    "addr:full":"Zwart Janstraat 26 Rotterdam Zuid-Holland 3035 AT",
    "addr:housenumber":"26",
    "addr:postcode":"3035",
    "addr:street":"Zwart Janstraat",
    "iso:country":"NL",
    "sg:address":"Zwart Janstraat 26",
    "sg:city":"Rotterdam",
    "sg:classifiers":[
        {
            "category":"Fast Food",
            "type":"Food & Drink"
        }
    ],
    "sg:phone":"+31 10 465 2530",
    "sg:postcode":"3035 AT",
    "sg:province":"Zuid-Holland",
    "sg:tags":[
        "afhaal",
        "restaurant"
    ],
    "wof:name":"Lon Sin Chinees-Indisch Restaurant",
    "wof:placetype":"venue"
},
  "geometry": {"coordinates":[4.479565,51.932724],"type":"Point"}
}