{
  "type": "Feature",
  "properties": {
    "addr:full":"Rabenhauptstr 45 Groningen Groningen 9725 CC",
    "addr:housenumber":"45",
    "addr:postcode":"9725 cc",
    "addr:street":"Rabenhauptstr",
    "iso:country":"NL",
    "sg:address":"Rabenhauptstr 45",
    "sg:city":"Groningen",
    "sg:orig_category":"Verenigingen En Stichtingen",
    "sg:phone":"+31 50 526 1379",
    "sg:postcode":"9725 CC",
    "sg:province":"Groningen",
    "wof:name":"Reuma Pati\u00ebnten Ver",
    "wof:placetype":"venue"
},
  "geometry": {"coordinates":[6.568812,53.20919],"type":"Point"}
}