{
  "type": "Feature",
  "properties": {
    "addr:full":"H Boexstr 9 Eindhoven Noord-Brabant 5611 AH",
    "addr:housenumber":"9",
    "addr:postcode":"5611 ah",
    "iso:country":"NL",
    "sg:address":"H Boexstr 9",
    "sg:city":"Eindhoven",
    "sg:orig_category":"Kinderkleding",
    "sg:phone":"+31 40 296 1400",
    "sg:postcode":"5611 AH",
    "sg:province":"Noord-Brabant",
    "wof:name":"Ko & Flo Baby- & Kinderkleding",
    "wof:placetype":"venue"
},
  "geometry": {"coordinates":[5.478311,51.440693],"type":"Point"}
}