{
  "type": "Feature",
  "properties": {
    "addr:full":"L Veerstr 32 Haarlem North Holland 2011 DB",
    "addr:housenumber":"32",
    "addr:postcode":"2011 db",
    "iso:country":"NL",
    "sg:address":"L Veerstr 32",
    "sg:city":"Haarlem",
    "sg:orig_category":"Poppen - Reparatie",
    "sg:phone":"+31 23 532 7384",
    "sg:postcode":"2011 DB",
    "sg:province":"North Holland",
    "wof:name":"Muynck, Eric De",
    "wof:placetype":"venue"
},
  "geometry": {"coordinates":[4.637365,52.379906],"type":"Point"}
}