{
  "type": "Feature",
  "properties": {
    "addr:full":"Parallelweg 68 Bergen Op Zoom Noord-Brabant 4621 JS",
    "addr:housenumber":"68",
    "addr:postcode":"4621 js",
    "addr:street":"Parallelweg",
    "iso:country":"NL",
    "sg:address":"Parallelweg 68",
    "sg:city":"Bergen Op Zoom",
    "sg:orig_category":"Werving And Selectie Van Vast Personeel",
    "sg:phone":"+31 164 247 547",
    "sg:postcode":"4621 JS",
    "sg:province":"Noord-Brabant",
    "wof:name":"Kaspermann Engineering Services Bv",
    "wof:placetype":"venue"
},
  "geometry": {"coordinates":[4.2967162132,51.4931755066],"type":"Point"}
}