{
  "type": "Feature",
  "properties": {
    "addr:full":"Postbus 1473 Groningen Noord-Holland 9701 BL",
    "addr:housenumber":"1473",
    "addr:postcode":"9701 bl",
    "addr:street":"Postbus",
    "iso:country":"NL",
    "sg:address":"Postbus 1473",
    "sg:city":"Groningen",
    "sg:orig_category":"Verenigingen En Stichtingen",
    "sg:phone":"+31 50 312 9794",
    "sg:postcode":"9701 BL",
    "sg:province":"Noord-Holland",
    "wof:name":"Zeilsticht Aeolus",
    "wof:placetype":"venue"
},
  "geometry": {"coordinates":[6.56502,53.21645],"type":"Point"}
}