{
  "type": "Feature",
  "properties": {
    "addr:full":"J Tooropstr 23 Eindhoven North Brabant 5642 AJ",
    "addr:housenumber":"23",
    "addr:postcode":"5642 aj",
    "iso:country":"NL",
    "sg:address":"J Tooropstr 23",
    "sg:city":"Eindhoven",
    "sg:orig_category":"Kappers",
    "sg:phone":"+31 40 212 9002",
    "sg:postcode":"5642 AJ",
    "sg:province":"North Brabant",
    "wof:name":"Harrie",
    "wof:placetype":"venue"
},
  "geometry": {"coordinates":[5.5064291954,51.4400177002],"type":"Point"}
}