{
  "type": "Feature",
  "properties": {
    "iso:country":"NL",
    "sg:address":"Sloterweg 22",
    "sg:city":"Badhoevedorp",
    "sg:orig_category":"Bruidskleding",
    "sg:phone":"+31 20 659 7411",
    "sg:postcode":"1171 CR",
    "sg:province":"Noord-Holland",
    "wof:name":"Portamento",
    "wof:placetype":"venue"
},
  "geometry": {"coordinates":[4.784518,52.341564],"type":"Point"}
}