{
  "type": "Feature",
  "properties": {
    "addr:full":"Jan Evertsenstraat 403 Amsterdam Noord-Holland 1061 XW",
    "addr:housenumber":"403",
    "addr:postcode":"1061 xw",
    "addr:street":"Jan Evertsenstraat",
    "iso:country":"NL",
    "sg:address":"Jan Evertsenstraat 403",
    "sg:city":"Amsterdam",
    "sg:orig_category":"Boekhouders",
    "sg:phone":"+31 20 614 8918",
    "sg:postcode":"1061 XW",
    "sg:province":"Noord-Holland",
    "wof:name":"Menting Administraties",
    "wof:placetype":"venue"
},
  "geometry": {"coordinates":[4.839407,52.36927],"type":"Point"}
}