{
  "type": "Feature",
  "properties": {
    "addr:full":"Aalbes 3 Zeewolde NL. 3892 XS",
    "addr:housenumber":"3",
    "addr:postcode":"3892 xs",
    "addr:street":"Aalbes;Nl.",
    "iso:country":"NL",
    "sg:address":"Aalbes 3",
    "sg:city":"Zeewolde",
    "sg:orig_category":"Hoortoestellen",
    "sg:phone":"+31 36 522 9026",
    "sg:postcode":"3892 XS",
    "sg:province":"NL.",
    "wof:name":"Hoor Plus, Sticht",
    "wof:placetype":"venue"
},
  "geometry": {"coordinates":[5.539381,52.325214],"type":"Point"}
}