{
  "type": "Feature",
  "properties": {
    "addr:full":"Sperwerlaan 33 Amsterdam North Holland 1021 EM",
    "addr:housenumber":"33",
    "addr:postcode":"1021 em",
    "addr:street":"Sperwerlaan",
    "iso:country":"NL",
    "sg:address":"Sperwerlaan 33",
    "sg:city":"Amsterdam",
    "sg:orig_category":"Loodgieterswerk, Verwarming And Sanitaire Installaties",
    "sg:phone":"+31 20 636 0860",
    "sg:postcode":"1021 EM",
    "sg:province":"North Holland",
    "wof:name":"Hubo Kemi V.O.F.",
    "wof:placetype":"venue"
},
  "geometry": {"coordinates":[4.914221,52.38578],"type":"Point"}
}