{
  "type": "Feature",
  "properties": {
    "addr:full":"Bar V Asbeckwg 7 Warfhuizen Groningen 9963 PA",
    "addr:housenumber":"7",
    "addr:postcode":"9963 pa",
    "addr:street":"Asbeckwg",
    "iso:country":"NL",
    "sg:address":"Bar V Asbeckwg 7",
    "sg:city":"Warfhuizen",
    "sg:orig_category":"Kalligrafische Ateliers",
    "sg:phone":"+31 595 572 686",
    "sg:postcode":"9963 PA",
    "sg:province":"Groningen",
    "wof:name":"Zoutewelle, S",
    "wof:placetype":"venue"
},
  "geometry": {"coordinates":[6.4255080223,53.3403358459],"type":"Point"}
}