{
  "type": "Feature",
  "properties": {
    "addr:full":"Beekstr 23 Limbricht Limburg 6141 BD",
    "addr:housenumber":"23",
    "addr:postcode":"6141 bd",
    "addr:street":"Beekstr",
    "iso:country":"NL",
    "sg:address":"Beekstr 23",
    "sg:city":"Limbricht",
    "sg:orig_category":"Huidverzorgingsartikelen",
    "sg:phone":"+31 46 411 0815",
    "sg:postcode":"6141 BD",
    "sg:province":"Limburg",
    "wof:name":"Kuipers, Christine",
    "wof:placetype":"venue"
},
  "geometry": {"coordinates":[5.837771,51.014137],"type":"Point"}
}