{
  "type": "Feature",
  "properties": {
    "addr:full":"Slotlaan 16 'S Heerenberg Gelderland 7041 BJ",
    "addr:housenumber":"16",
    "addr:postcode":"7041 bj",
    "addr:street":"Slotlaan;' S Heerenberg Gelderland",
    "iso:country":"NL",
    "sg:address":"Slotlaan 16",
    "sg:city":"'S Heerenberg",
    "sg:orig_category":"Verzekeringen",
    "sg:phone":"+31 314 667 744",
    "sg:postcode":"7041 BJ",
    "sg:province":"Gelderland",
    "wof:name":"G.J.J. Booms Assurantien",
    "wof:placetype":"venue"
},
  "geometry": {"coordinates":[6.240129,51.876648],"type":"Point"}
}