{
  "type": "Feature",
  "properties": {
    "iso:country":"NL",
    "sg:address":"Driestedenweg 55",
    "sg:city":"De Weere",
    "sg:orig_category":"Meubelzaken, Woning- And Keukeninrichting",
    "sg:phone":"+31 229 581 314",
    "sg:postcode":"1662 BG",
    "sg:province":"North Holland",
    "wof:name":"M. Wenker",
    "wof:placetype":"venue"
},
  "geometry": {"coordinates":[4.996379,52.72649],"type":"Point"}
}