{
  "type": "Feature",
  "properties": {
    "addr:full":"Stationsweg 7 Colmschate NL.08 7429 AC",
    "addr:housenumber":"7;nl.08",
    "addr:postcode":"7429 ac",
    "addr:street":"Stationsweg",
    "iso:country":"NL",
    "sg:address":"Stationsweg 7",
    "sg:city":"Colmschate",
    "sg:orig_category":"Juridische Dienstverlening",
    "sg:phone":"+31 570 656 191",
    "sg:postcode":"7429 AC",
    "sg:province":"NL.08",
    "wof:name":"Boersma-Milieuadviesburo",
    "wof:placetype":"venue"
},
  "geometry": {"coordinates":[6.217962,52.249062],"type":"Point"}
}