{
  "type": "Feature",
  "properties": {
    "iso:country":"NL",
    "sg:address":"V Hovellstr 65",
    "sg:city":"Helden",
    "sg:orig_category":"Kappers",
    "sg:phone":"+31 6 27046556",
    "sg:postcode":"5988 AG",
    "sg:province":"Illinois",
    "wof:name":"Curly Curly",
    "wof:placetype":"venue"
},
  "geometry": {"coordinates":[-89.4168395996,41.772731781],"type":"Point"}
}