{
  "type": "Feature",
  "properties": {
    "addr:full":"Vleutenseweg 22 Utrecht Utrecht 3532 HL",
    "addr:housenumber":"22",
    "addr:postcode":"3532 hl",
    "addr:street":"Vleutenseweg",
    "iso:country":"NL",
    "sg:address":"Vleutenseweg 22",
    "sg:city":"Utrecht",
    "sg:orig_category":"Wasserettes And Stomerijen",
    "sg:phone":"+31 30 283 3396",
    "sg:postcode":"3532 HL",
    "sg:province":"Utrecht",
    "wof:name":"A V/D Berg Stomerij",
    "wof:placetype":"venue"
},
  "geometry": {"coordinates":[5.103579998,52.0926856995],"type":"Point"}
}