{
  "type": "Feature",
  "properties": {
    "iso:country":"NL",
    "sg:address":"Bylakker 26",
    "sg:city":"Mierlo",
    "sg:orig_category":"Bedden En Matrassen",
    "sg:phone":"+31 492 432 118",
    "sg:postcode":"5731 EE",
    "sg:province":"North Brabant",
    "wof:name":"Nowm Sahij",
    "wof:placetype":"venue"
},
  "geometry": {"coordinates":[5.619782,51.4436],"type":"Point"}
}