{
  "type": "Feature",
  "properties": {
    "iso:country":"NL",
    "sg:address":"Retsinagaard 25",
    "sg:city":"Woerden",
    "sg:orig_category":"Organisatiebureaus",
    "sg:phone":"+31 348 688 089",
    "sg:postcode":"3446 WH",
    "sg:province":"Utrecht",
    "wof:name":"Alpha Consult",
    "wof:placetype":"venue"
},
  "geometry": {"coordinates":[4.9087347984,52.0811347961],"type":"Point"}
}