{
  "type": "Feature",
  "properties": {
    "addr:full":"Raadhuisln 47 Oude Pekela Groningen 9665 JA",
    "addr:housenumber":"47",
    "addr:postcode":"pekela;9665 ja",
    "addr:street":"Raadhuisln",
    "iso:country":"NL",
    "sg:address":"Raadhuisln 47",
    "sg:city":"Oude Pekela",
    "sg:orig_category":"Politie",
    "sg:phone":"+31 900 8844",
    "sg:postcode":"9665 JA",
    "sg:province":"Groningen",
    "wof:name":"Politie",
    "wof:placetype":"venue"
},
  "geometry": {"coordinates":[7.00891,53.103069],"type":"Point"}
}