{
  "type": "Feature",
  "properties": {
    "iso:country":"NL",
    "sg:address":"Kerkstr 2",
    "sg:city":"Ruurlo",
    "sg:orig_category":"Banken",
    "sg:phone":"+31 573 451 485",
    "sg:postcode":"7261 GG",
    "sg:province":"Gelderland",
    "wof:name":"Regio Bank",
    "wof:placetype":"venue"
},
  "geometry": {"coordinates":[6.447876,52.086143],"type":"Point"}
}