{
  "type": "Feature",
  "properties": {
    "addr:full":"Handelskd 5 Gorinchem South Holland 4205 AC",
    "addr:housenumber":"5",
    "addr:postcode":"4205 ac",
    "addr:street":"Handelskd",
    "iso:country":"NL",
    "sg:address":"Handelskd 5",
    "sg:city":"Gorinchem",
    "sg:orig_category":"Begrafenisverzorging",
    "sg:phone":"+31 183 622 815",
    "sg:postcode":"4205 AC",
    "sg:province":"South Holland",
    "wof:name":"Alg Belang",
    "wof:placetype":"venue"
},
  "geometry": {"coordinates":[4.969185,51.830631],"type":"Point"}
}