{
  "type": "Feature",
  "properties": {
    "addr:full":"Kerkstr 17A Zeeland Noord-Brabant 5411 CJ",
    "addr:housenumber":"17a",
    "addr:postcode":"5411 cj",
    "addr:street":"Kerkstr",
    "iso:country":"NL",
    "sg:address":"Kerkstr 17A",
    "sg:city":"Zeeland",
    "sg:orig_category":"Kappers",
    "sg:phone":"+31 486 451 260",
    "sg:postcode":"5411 CJ",
    "sg:province":"Noord-Brabant",
    "wof:name":"Laar, P C Van Der",
    "wof:placetype":"venue"
},
  "geometry": {"coordinates":[5.672247,51.694641],"type":"Point"}
}