{
  "type": "Feature",
  "properties": {
    "addr:full":"Grt Overstr 13-15 Deventer Overijssel 7411 JA",
    "addr:housenumber":"13-15",
    "addr:postcode":"7411 ja",
    "iso:country":"NL",
    "sg:address":"Grt Overstr 13-15",
    "sg:city":"Deventer",
    "sg:orig_category":"Gelegenheidskleding",
    "sg:phone":"+31 570 616 545",
    "sg:postcode":"7411 JA",
    "sg:province":"Overijssel",
    "sg:website":"http://www.clochard.nl",
    "wof:name":"Clochard",
    "wof:placetype":"venue"
},
  "geometry": {"coordinates":[6.157778,52.253132],"type":"Point"}
}