{
  "type": "Feature",
  "properties": {
    "addr:full":"Vosplnts 13 Almere NL. 1338 BC",
    "addr:housenumber":"13",
    "addr:postcode":"1338 bc",
    "addr:street":"Vosplnts;Nl.",
    "iso:country":"NL",
    "sg:address":"Vosplnts 13",
    "sg:city":"Almere",
    "sg:orig_category":"Onderhoudswerken",
    "sg:phone":"+31 36 532 1094",
    "sg:postcode":"1338 BC",
    "sg:province":"NL.",
    "wof:name":"Boxtel, G M Van",
    "wof:placetype":"venue"
},
  "geometry": {"coordinates":[5.27846,52.386421],"type":"Point"}
}