{
  "type": "Feature",
  "properties": {
    "addr:full":"Reigerstr 21 Putten Gelderland 3882 JB",
    "addr:housenumber":"21",
    "addr:postcode":"3882 jb",
    "addr:street":"Reigerstr;Gelderland",
    "iso:country":"NL",
    "sg:address":"Reigerstr 21",
    "sg:city":"Putten",
    "sg:orig_category":"Telecommunicatie - Apparatuur",
    "sg:phone":"+31 6 28777774",
    "sg:postcode":"3882 JB",
    "sg:province":"Gelderland",
    "sg:website":"http://www.bertgsm.nl",
    "wof:name":"Bert",
    "wof:placetype":"venue"
},
  "geometry": {"coordinates":[5.586842,52.258537],"type":"Point"}
}