{
  "type": "Feature",
  "properties": {
    "addr:full":"Vogelzankwg 155 Landgraaf Limburg 6374 AC",
    "addr:housenumber":"155",
    "addr:postcode":"6374 ac",
    "iso:country":"NL",
    "sg:address":"Vogelzankwg 155",
    "sg:city":"Landgraaf",
    "sg:orig_category":"Boekhandels",
    "sg:phone":"+31 45 531 0734",
    "sg:postcode":"6374 AC",
    "sg:province":"Limburg",
    "wof:name":"Media Expresse",
    "wof:placetype":"venue"
},
  "geometry": {"coordinates":[6.030685,50.916874],"type":"Point"}
}