{
  "type": "Feature",
  "properties": {
    "iso:country":"NL",
    "sg:address":"Clitexwg 19",
    "sg:city":"Clinge",
    "sg:orig_category":"Oud Metaal",
    "sg:phone":"+31 114 315 553",
    "sg:postcode":"4567 BN",
    "sg:province":"Zeeland",
    "wof:name":"Zemetha",
    "wof:placetype":"venue"
},
  "geometry": {"coordinates":[4.0903167725,51.2698097229],"type":"Point"}
}