{
  "type": "Feature",
  "properties": {
    "addr:full":"Marconistraat 38 Heerhugowaard North Holland 1704 RG",
    "addr:housenumber":"38",
    "addr:postcode":"1704 rg",
    "addr:street":"Marconistraat",
    "iso:country":"NL",
    "sg:address":"Marconistraat 38",
    "sg:city":"Heerhugowaard",
    "sg:orig_category":"Begrafenisondernemers",
    "sg:phone":"+31 72 571 9237",
    "sg:postcode":"1704 RG",
    "sg:province":"North Holland",
    "wof:name":"Dfw Europe Bv",
    "wof:placetype":"venue"
},
  "geometry": {"coordinates":[4.834406,52.683502],"type":"Point"}
}