{
  "type": "Feature",
  "properties": {
    "addr:full":"Irmstr 5 Simpelveld Limburg 6369 VL",
    "addr:housenumber":"5",
    "addr:postcode":"6369 vl",
    "addr:street":"Irmstr",
    "iso:country":"NL",
    "sg:address":"Irmstr 5",
    "sg:city":"Simpelveld",
    "sg:orig_category":"Bedrijfsmechanisatie En -Automatisering",
    "sg:phone":"+31 45 544 2343",
    "sg:postcode":"6369 VL",
    "sg:province":"Limburg",
    "sg:website":"http://www.pcdata.nl",
    "wof:name":"Pcdata Bv",
    "wof:placetype":"venue"
},
  "geometry": {"coordinates":[5.980689,50.833344],"type":"Point"}
}