{
  "type": "Feature",
  "properties": {
    "addr:full":"Sniedersln 17A Bladel North Brabant 5531 EG",
    "addr:housenumber":"17a",
    "addr:postcode":"5531 eg",
    "addr:street":"Sniedersln",
    "iso:country":"NL",
    "sg:address":"Sniedersln 17A",
    "sg:city":"Bladel",
    "sg:orig_category":"Juweliers",
    "sg:phone":"+31 497 387 936",
    "sg:postcode":"5531 EG",
    "sg:province":"North Brabant",
    "wof:name":"Edelsmidse Bv, De",
    "wof:placetype":"venue"
},
  "geometry": {"coordinates":[5.217294,51.366879],"type":"Point"}
}