{
  "type": "Feature",
  "properties": {
    "addr:full":"Ariensstraat 39 Westervoort Gelderland 6931 DW",
    "addr:housenumber":"39",
    "addr:postcode":"6931 dw",
    "addr:street":"Ariensstraat;Gelderland",
    "iso:country":"NL",
    "sg:address":"Ariensstraat 39",
    "sg:city":"Westervoort",
    "sg:orig_category":"Schilderwerk",
    "sg:phone":"+31 26 311 5619",
    "sg:postcode":"6931 DW",
    "sg:province":"Gelderland",
    "wof:name":"Frans Bongers Schildersbedrijf",
    "wof:placetype":"venue"
},
  "geometry": {"coordinates":[5.967596,51.959702],"type":"Point"}
}