{
  "type": "Feature",
  "properties": {
    "addr:full":"Kerkstr 42 Bodegraven Zuid-Holland 2411 AE",
    "addr:housenumber":"42",
    "addr:postcode":"2411 ae",
    "addr:street":"Kerkstr",
    "iso:country":"NL",
    "sg:address":"Kerkstr 42",
    "sg:city":"Bodegraven",
    "sg:orig_category":"Administratie- En Boekhoudkantoren",
    "sg:phone":"+31 172 612 489",
    "sg:postcode":"2411 AE",
    "sg:province":"Zuid-Holland",
    "wof:name":"Groenendijk",
    "wof:placetype":"venue"
},
  "geometry": {"coordinates":[4.747547,52.085552],"type":"Point"}
}