{
  "type": "Feature",
  "properties": {
    "addr:full":"Zwaanstr 17 Berkel Enschot Noord-Brabant 5056 EN",
    "addr:housenumber":"17",
    "addr:postcode":"5056 en",
    "addr:street":"Zwaanstr",
    "iso:country":"NL",
    "sg:address":"Zwaanstr 17",
    "sg:city":"Berkel Enschot",
    "sg:orig_category":"Honden- En Kattentrimsalons",
    "sg:phone":"+31 13 533 6913",
    "sg:postcode":"5056 EN",
    "sg:province":"Noord-Brabant",
    "sg:website":"http://www.hondentrim-salon.nl",
    "wof:name":"Djerbo'S Trimsalon",
    "wof:placetype":"venue"
},
  "geometry": {"coordinates":[5.1366271973,51.5813903809],"type":"Point"}
}