{
  "type": "Feature",
  "properties": {
    "addr:full":"Langstraat 26 Wijhe NL.08 8131 BC",
    "addr:housenumber":"26;nl.08",
    "addr:postcode":"8131 bc",
    "addr:street":"Langstraat",
    "iso:country":"NL",
    "sg:address":"Langstraat 26",
    "sg:city":"Wijhe",
    "sg:orig_category":"Autokeuringen",
    "sg:phone":"+31 570 521 357",
    "sg:postcode":"8131 BC",
    "sg:province":"NL.08",
    "wof:name":"L'Etagere",
    "wof:placetype":"venue"
},
  "geometry": {"coordinates":[6.135212,52.388802],"type":"Point"}
}