{
  "type": "Feature",
  "properties": {
    "addr:full":"Afrikalaan 13 'S Hertogenbosch North Brabant 5232 BD",
    "addr:housenumber":"13",
    "addr:postcode":"5232 bd",
    "addr:street":"Afrikalaan;' S Hertogenbosch",
    "iso:country":"NL",
    "sg:address":"Afrikalaan 13",
    "sg:city":"'S Hertogenbosch",
    "sg:orig_category":"Autokeuringen",
    "sg:phone":"+31 73 642 7510",
    "sg:postcode":"5232 BD",
    "sg:province":"North Brabant",
    "wof:name":"Autoschadeherstelbedrijf Carlux Bv",
    "wof:placetype":"venue"
},
  "geometry": {"coordinates":[5.33735,51.706459],"type":"Point"}
}