{
  "type": "Feature",
  "properties": {
    "addr:full":"Dwergvinvisstr 4 Amsterdam North Holland 1035 HP",
    "addr:housenumber":"4",
    "addr:postcode":"1035 hp",
    "addr:street":"Dwergvinvisstr",
    "iso:country":"NL",
    "sg:address":"Dwergvinvisstr 4",
    "sg:city":"Amsterdam",
    "sg:orig_category":"Verzekeringen - Verzekeringskantoren",
    "sg:phone":"+31 20 633 4297",
    "sg:postcode":"1035 HP",
    "sg:province":"North Holland",
    "wof:name":"Wijnsma",
    "wof:placetype":"venue"
},
  "geometry": {"coordinates":[4.884802,52.422115],"type":"Point"}
}