{
  "type": "Feature",
  "properties": {
    "iso:country":"NL",
    "sg:address":"Dwergvinvisstr 4",
    "sg:city":"Amsterdam",
    "sg:orig_category":"Verzekeringen - Verzekeringskantoren",
    "sg:phone":"+31 20 633 4297",
    "sg:postcode":"1035 HP",
    "sg:province":"North Holland",
    "wof:name":"Wijnsma",
    "wof:placetype":"venue"
},
  "geometry": {"coordinates":[4.884802,52.422115],"type":"Point"}
}