{
  "type": "Feature",
  "properties": {
    "addr:full":"Melbournestraat 38 Rotterdam Zuid-Holland 3047 BJ",
    "addr:housenumber":"38",
    "addr:postcode":"3047 bj",
    "addr:street":"Melbournestraat",
    "iso:country":"NL",
    "sg:address":"Melbournestraat 38",
    "sg:city":"Rotterdam",
    "sg:orig_category":"Huishoudapparatuur, Televisies And Radio'S",
    "sg:phone":"+31 10 245 7324",
    "sg:postcode":"3047 BJ",
    "sg:province":"Zuid-Holland",
    "wof:name":"Promise Home Care",
    "wof:placetype":"venue"
},
  "geometry": {"coordinates":[4.407132,51.940731],"type":"Point"}
}