{
  "type": "Feature",
  "properties": {
    "addr:full":"Burg V Geusauwg 24 Geldermalsen Gelderland 4191 KW",
    "addr:housenumber":"24",
    "addr:postcode":"4191 kw",
    "addr:street":"Burg V Geusauwg;Gelderland",
    "iso:country":"NL",
    "sg:address":"Burg V Geusauwg 24",
    "sg:city":"Geldermalsen",
    "sg:orig_category":"Winkelinrichting",
    "sg:phone":"+31 345 581 752",
    "sg:postcode":"4191 KW",
    "sg:province":"Gelderland",
    "wof:name":"Biz",
    "wof:placetype":"venue"
},
  "geometry": {"coordinates":[5.2898988724,51.8828125],"type":"Point"}
}