{
  "type": "Feature",
  "properties": {
    "addr:full":"Nieuwstraat 88 Deventer NL.08 7411 LP",
    "addr:housenumber":"88;nl.08",
    "addr:postcode":"7411 lp",
    "addr:street":"Nieuwstraat",
    "iso:country":"NL",
    "sg:address":"Nieuwstraat 88",
    "sg:city":"Deventer",
    "sg:orig_category":"Werving And Selectie Van Tijdelijk Personeel And Uitzendkantoren",
    "sg:phone":"+31 570 665 880",
    "sg:postcode":"7411 LP",
    "sg:province":"NL.08",
    "wof:name":"Creyf'S Interim",
    "wof:placetype":"venue"
},
  "geometry": {"coordinates":[6.1598992348,52.251033783],"type":"Point"}
}