{
  "type": "Feature",
  "properties": {
    "addr:full":"Oranjestr 30 Holten Overijssel 7451 CC",
    "addr:housenumber":"30",
    "addr:postcode":"7451 cc",
    "addr:street":"Oranjestr",
    "iso:country":"NL",
    "sg:address":"Oranjestr 30",
    "sg:city":"Holten",
    "sg:classifiers":[
        {
            "category":"Retail",
            "subcategory":"Auto Repair",
            "type":"Services"
        }
    ],
    "sg:phone":"+31 548 361 363",
    "sg:postcode":"7451 CC",
    "sg:province":"Overijssel",
    "sg:tags":[
        "garage"
    ],
    "sg:website":"http://www.stukker.nl",
    "wof:name":"Stukker",
    "wof:placetype":"venue"
},
  "geometry": {"coordinates":[6.425362,52.280029],"type":"Point"}
}