{
  "type": "Feature",
  "properties": {
    "addr:full":"Wissewekken 11 Burgh Haamstede Zeeland 4328 PX",
    "addr:housenumber":"11",
    "addr:postcode":"4328 px",
    "addr:street":"Wissewekken;Haamstede",
    "iso:country":"NL",
    "sg:address":"Wissewekken 11",
    "sg:city":"Burgh Haamstede",
    "sg:orig_category":"Vertalers",
    "sg:phone":"+31 111 651 786",
    "sg:postcode":"4328 PX",
    "sg:province":"Zeeland",
    "wof:name":"Kenters-Verton, P C A",
    "wof:placetype":"venue"
},
  "geometry": {"coordinates":[3.717998,51.676266],"type":"Point"}
}