{
  "type": "Feature",
  "properties": {
    "iso:country":"NL",
    "sg:address":"Chevalleraustr 10",
    "sg:city":"Ommen",
    "sg:orig_category":"Verenigingen En Stichtingen",
    "sg:phone":"+31 529 450 827",
    "sg:postcode":"7731 EE",
    "sg:province":"NL.08",
    "sg:website":"HTTP://www.jongerencentrumpunt.nl",
    "wof:name":"Open Jongeren Centrum Punt",
    "wof:placetype":"venue"
},
  "geometry": {"coordinates":[6.419056,52.525272],"type":"Point"}
}