{
  "type": "Feature",
  "properties": {
    "iso:country":"NL",
    "sg:address":"Hoofddiep 66",
    "sg:city":"Zevenhuizen Gn",
    "sg:classifiers":[
        {
            "category":"Food & Beverages",
            "subcategory":"Bakery",
            "type":"Retail Goods"
        }
    ],
    "sg:phone":"+31 594 631 543",
    "sg:postcode":"9354 AS",
    "sg:province":"Groningen",
    "sg:tags":[
        "pizza"
    ],
    "sg:website":"http://www.horecacentrumaubergine.nl",
    "wof:name":"Aubergine",
    "wof:placetype":"venue"
},
  "geometry": {"coordinates":[6.350243,53.126343],"type":"Point"}
}