{
  "type": "Feature",
  "properties": {
    "iso:country":"NL",
    "sg:address":"Langewijk 232",
    "sg:city":"Dedemsvaart",
    "sg:orig_category":"Kappers",
    "sg:phone":"+31 523 615 023",
    "sg:postcode":"7701 AM",
    "sg:province":"NL.08",
    "wof:name":"Kapsalon La Coupe",
    "wof:placetype":"venue"
},
  "geometry": {"coordinates":[6.4670610428,52.6064872742],"type":"Point"}
}