{
  "type": "Feature",
  "properties": {
    "addr:full":"De Stelling 1036 Lelystad NL. 8232 EC",
    "addr:postcode":"1036;8232 ec",
    "addr:street":"De Stelling;Nl.",
    "iso:country":"NL",
    "sg:address":"De Stelling 1036",
    "sg:city":"Lelystad",
    "sg:orig_category":"Vertalers",
    "sg:phone":"+31 320 227 780",
    "sg:postcode":"8232 EC",
    "sg:province":"NL.",
    "wof:name":"Kuipers, Y",
    "wof:placetype":"venue"
},
  "geometry": {"coordinates":[5.473709,52.512264],"type":"Point"}
}