{
  "type": "Feature",
  "properties": {
    "addr:full":"Thorbeckelaan 525 'S Gravenhage South Holland 2564 CD",
    "addr:housenumber":"525 '",
    "addr:postcode":"2564 cd",
    "addr:street":"Thorbeckelaan",
    "iso:country":"NL",
    "sg:address":"Thorbeckelaan 525",
    "sg:city":"'S Gravenhage",
    "sg:orig_category":"Diverse Grafische Activiteiten",
    "sg:phone":"+31 70 323 4451",
    "sg:postcode":"2564 CD",
    "sg:province":"South Holland",
    "wof:name":"Advies Ontwerpbureau",
    "wof:placetype":"venue"
},
  "geometry": {"coordinates":[4.250113,52.065727],"type":"Point"}
}