{
  "type": "Feature",
  "properties": {
    "iso:country":"NL",
    "sg:address":"Zaanwg 105",
    "sg:city":"Wormerveer",
    "sg:orig_category":"Optische Instrumenten",
    "sg:phone":"+31 75 622 4711",
    "sg:postcode":"1521 DP",
    "sg:province":"Noord-Holland",
    "sg:website":"http://www.vandijkoptiek.nl",
    "wof:name":"Dijk Bv, E A P Van",
    "wof:placetype":"venue"
},
  "geometry": {"coordinates":[4.7909312248,52.4913063049],"type":"Point"}
}