{
  "type": "Feature",
  "properties": {
    "addr:full":"Vrystr 20 Eindhoven Noord-Brabant 5611 AV",
    "addr:housenumber":"20",
    "addr:postcode":"5611 av",
    "addr:street":"Vrystr",
    "iso:country":"NL",
    "sg:address":"Vrystr 20",
    "sg:city":"Eindhoven",
    "sg:orig_category":"Sportschoenen - Winkels",
    "sg:phone":"+31 40 246 2217",
    "sg:postcode":"5611 AV",
    "sg:province":"Noord-Brabant",
    "wof:name":"Coach Eindhoven",
    "wof:placetype":"venue"
},
  "geometry": {"coordinates":[5.484105,51.434471],"type":"Point"}
}