{
  "type": "Feature",
  "properties": {
    "addr:full":"Noarderfinne 4 Oosterlittens Friesland 8835 XT",
    "addr:housenumber":"4",
    "addr:postcode":"8835 xt",
    "addr:street":"Noarderfinne",
    "iso:country":"NL",
    "sg:address":"Noarderfinne 4",
    "sg:city":"Oosterlittens",
    "sg:orig_category":"Adviesbureaus Bouwkunde",
    "sg:phone":"+31 517 341 211",
    "sg:postcode":"8835 XT",
    "sg:province":"Friesland",
    "wof:name":"Venema",
    "wof:placetype":"venue"
},
  "geometry": {"coordinates":[5.65011,53.13522],"type":"Point"}
}