{
  "type": "Feature",
  "properties": {
    "iso:country":"NL",
    "sg:address":"Aarperstraat 16",
    "sg:city":"Westerhoven",
    "sg:orig_category":"Marktonderzoekbureaus",
    "sg:phone":"+31 40 204 4962",
    "sg:postcode":"5563 BK",
    "sg:province":"North Brabant",
    "wof:name":"Gleijm & Van Der Waart Marketing Service",
    "wof:placetype":"venue"
},
  "geometry": {"coordinates":[5.393191,51.332672],"type":"Point"}
}