{
  "type": "Feature",
  "properties": {
    "iso:country":"NL",
    "sg:address":"Ohmstr 1",
    "sg:city":"S Gravenhage",
    "sg:orig_category":"Verenigingen En Stichtingen",
    "sg:phone":"+31 70 365 3544",
    "sg:postcode":"2561 RZ",
    "sg:province":"Zuid-Holland",
    "wof:name":"Fuerza Union Antilliano 2000, Sticht",
    "wof:placetype":"venue"
},
  "geometry": {"coordinates":[4.27581,52.074532],"type":"Point"}
}