{
  "type": "Feature",
  "properties": {
    "addr:full":"Schonberglaan 47 Utrecht Utrecht 3533 JC",
    "addr:housenumber":"47",
    "addr:postcode":"3533 jc",
    "addr:street":"Schonberglaan",
    "iso:country":"NL",
    "sg:address":"Schonberglaan 47",
    "sg:city":"Utrecht",
    "sg:orig_category":"Autokeuringen",
    "sg:phone":"+31 30 293 0568",
    "sg:postcode":"3533 JC",
    "sg:province":"Utrecht",
    "wof:name":"Autoschade En Verhuur Van Batenburg",
    "wof:placetype":"venue"
},
  "geometry": {"coordinates":[5.092001,52.084034],"type":"Point"}
}