{
  "type": "Feature",
  "properties": {
    "addr:full":"Croylaan 10 Aarle Rixtel Noord-Brabant 5735 PC",
    "addr:housenumber":"10",
    "addr:postcode":"5735 pc",
    "addr:street":"Croylaan",
    "iso:country":"NL",
    "sg:address":"Croylaan 10",
    "sg:city":"Aarle Rixtel",
    "sg:orig_category":"Kantoorartikelen",
    "sg:phone":"+31 492 382 920",
    "sg:postcode":"5735 PC",
    "sg:province":"Noord-Brabant",
    "wof:name":"Projection Office Equipment Bv",
    "wof:placetype":"venue"
},
  "geometry": {"coordinates":[5.6257610321,51.4993896484],"type":"Point"}
}