{
  "type": "Feature",
  "properties": {
    "iso:country":"NL",
    "sg:address":"Croylaan 10",
    "sg:city":"Aarle Rixtel",
    "sg:orig_category":"Kantoorartikelen",
    "sg:phone":"+31 492 382 920",
    "sg:postcode":"5735 PC",
    "sg:province":"Noord-Brabant",
    "wof:name":"Projection Office Equipment Bv",
    "wof:placetype":"venue"
},
  "geometry": {"coordinates":[5.6257610321,51.4993896484],"type":"Point"}
}