{
  "type": "Feature",
  "properties": {
    "addr:full":"Torenstraat 7 Drunen Noord-Brabant 5151 JJ",
    "addr:housenumber":"7",
    "addr:postcode":"5151 jj",
    "addr:street":"Torenstraat",
    "iso:country":"NL",
    "sg:address":"Torenstraat 7",
    "sg:city":"Drunen",
    "sg:orig_category":"Beveiliging",
    "sg:phone":"+31 416 320 340",
    "sg:postcode":"5151 JJ",
    "sg:province":"Noord-Brabant",
    "wof:name":"Griendt Beveiliging, Hans Van De",
    "wof:placetype":"venue"
},
  "geometry": {"coordinates":[5.140105,51.686749],"type":"Point"}
}