{
  "type": "Feature",
  "properties": {
    "addr:full":"Schweibergerweg 46 Mechelen Limburg 6281 NH",
    "addr:housenumber":"46",
    "addr:postcode":"6281 nh",
    "addr:street":"Schweibergerweg",
    "iso:country":"NL",
    "sg:address":"Schweibergerweg 46",
    "sg:city":"Mechelen",
    "sg:classifiers":[
        {
            "category":"Travel",
            "subcategory":"Hotels & Motels",
            "type":"Entertainment"
        }
    ],
    "sg:phone":"+31 43 455 1574",
    "sg:postcode":"6281 NH",
    "sg:province":"Limburg",
    "wof:name":"Pension Vouwere",
    "wof:placetype":"venue"
},
  "geometry": {"coordinates":[5.904319,50.78471],"type":"Point"}
}