{
  "type": "Feature",
  "properties": {
    "addr:full":"Lisserdijk 357 Lisserbroek Noord-Holland 2165 AC",
    "addr:housenumber":"357",
    "addr:postcode":"2165 ac",
    "addr:street":"Lisserdijk",
    "iso:country":"NL",
    "sg:address":"Lisserdijk 357",
    "sg:city":"Lisserbroek",
    "sg:orig_category":"Bloemen- And Plantenteelt",
    "sg:phone":"+31 252 412 924",
    "sg:postcode":"2165 AC",
    "sg:province":"Noord-Holland",
    "wof:name":"C J De Graaf Vof",
    "wof:placetype":"venue"
},
  "geometry": {"coordinates":[4.567362,52.245861],"type":"Point"}
}