{
  "type": "Feature",
  "properties": {
    "iso:country":"NL",
    "sg:address":"Voorerf 13",
    "sg:city":"Breda",
    "sg:orig_category":"Kantoorapparatuur Gh",
    "sg:phone":"+31 76 542 4555",
    "sg:postcode":"4824 GM",
    "sg:province":"Noord-Brabant",
    "wof:name":"Subox Trading Vof",
    "wof:placetype":"venue"
},
  "geometry": {"coordinates":[4.7518658638,51.6138381958],"type":"Point"}
}