{
  "type": "Feature",
  "properties": {
    "addr:full":"Luxemburgstraat 46 Geleen Limburg 6164 BT",
    "addr:housenumber":"46",
    "addr:postcode":"6164 bt",
    "addr:street":"Luxemburgstraat",
    "iso:country":"NL",
    "sg:address":"Luxemburgstraat 46",
    "sg:city":"Geleen",
    "sg:orig_category":"Wasserettes, Stomerijen And Reiniging",
    "sg:phone":"+31 46 474 4931",
    "sg:postcode":"6164 BT",
    "sg:province":"Limburg",
    "wof:name":"Chemdry",
    "wof:placetype":"venue"
},
  "geometry": {"coordinates":[5.8260259628,50.9514846802],"type":"Point"}
}