{
  "type": "Feature",
  "properties": {
    "addr:full":"Damsterwg 5A Steendam Groningen 9629 PB",
    "addr:housenumber":"5a",
    "addr:postcode":"9629 pb",
    "addr:street":"Damsterwg",
    "iso:country":"NL",
    "sg:address":"Damsterwg 5A",
    "sg:city":"Steendam",
    "sg:orig_category":"Kabels",
    "sg:phone":"+31 598 431 220",
    "sg:postcode":"9629 PB",
    "sg:province":"Groningen",
    "wof:name":"European Blowing Crews Bv",
    "wof:placetype":"venue"
},
  "geometry": {"coordinates":[6.8451170921,53.2713508606],"type":"Point"}
}