{
  "type": "Feature",
  "properties": {
    "addr:full":"Katwolderwg 5 Zwolle NL.08 8041 AC",
    "addr:housenumber":"5",
    "addr:postcode":"8041 ac",
    "addr:street":"Katwolderwg",
    "iso:country":"NL",
    "sg:address":"Katwolderwg 5",
    "sg:city":"Zwolle",
    "sg:orig_category":"Koeltechniek",
    "sg:phone":"+31 38 423 3176",
    "sg:postcode":"8041 AC",
    "sg:province":"NL.08",
    "wof:name":"Service Equipe Bv",
    "wof:placetype":"venue"
},
  "geometry": {"coordinates":[6.075913,52.518028],"type":"Point"}
}