{
  "type": "Feature",
  "properties": {
    "addr:full":"Nusseleinstr 38 America Limburg 5966 NK",
    "addr:housenumber":"38",
    "addr:postcode":"5966 nk",
    "addr:street":"Nusseleinstr",
    "iso:country":"NL",
    "sg:address":"Nusseleinstr 38",
    "sg:city":"America",
    "sg:orig_category":"Honden- En Kattentrimsalons",
    "sg:phone":"+31 77 464 1678",
    "sg:postcode":"5966 NK",
    "sg:province":"Limburg",
    "wof:name":"Marjo Reinders",
    "wof:placetype":"venue"
},
  "geometry": {"coordinates":[5.983388,51.436829],"type":"Point"}
}