{
  "type": "Feature",
  "properties": {
    "addr:full":"Van Der Hoevensstraat 116 Westervoort Gelderland 6931 DE",
    "addr:housenumber":"116",
    "addr:postcode":"6931 de",
    "addr:street":"Van Der Hoevensstraat;Gelderland",
    "iso:country":"NL",
    "sg:address":"Van Der Hoevensstraat 116",
    "sg:city":"Westervoort",
    "sg:orig_category":"Fotostudio'S And Fotografen",
    "sg:phone":"+31 26 312 1285",
    "sg:postcode":"6931 DE",
    "sg:province":"Gelderland",
    "wof:name":"Bvp. Bachrach Video Produkties",
    "wof:placetype":"venue"
},
  "geometry": {"coordinates":[5.964207,51.956867],"type":"Point"}
}