{
  "type": "Feature",
  "properties": {
    "addr:full":"Langestr 41 Winschoten Groningen 9671 PB",
    "addr:housenumber":"41",
    "addr:postcode":"9671 pb",
    "addr:street":"Langestr",
    "iso:country":"NL",
    "sg:address":"Langestr 41",
    "sg:city":"Winschoten",
    "sg:orig_category":"Touringcars",
    "sg:phone":"+31 597 431 653",
    "sg:postcode":"9671 PB",
    "sg:province":"Groningen",
    "sg:website":"http://www.kloosterreizen.nl",
    "wof:name":"Klooster Reizen Bv",
    "wof:placetype":"venue"
},
  "geometry": {"coordinates":[7.037552,53.144176],"type":"Point"}
}