{
  "type": "Feature",
  "properties": {
    "addr:full":"Hanzestraat 167 Arnhem Gelderland 6826 MJ",
    "addr:housenumber":"167",
    "addr:postcode":"6826 mj",
    "addr:street":"Hanzestraat",
    "iso:country":"NL",
    "sg:address":"Hanzestraat 167",
    "sg:city":"Arnhem",
    "sg:orig_category":"Huishoudapparatuur, Televisies And Radio'S",
    "sg:phone":"+31 26 361 3205",
    "sg:postcode":"6826 MJ",
    "sg:province":"Gelderland",
    "wof:name":"Audio Video Fotobouw",
    "wof:placetype":"venue"
},
  "geometry": {"coordinates":[5.951645,51.983475],"type":"Point"}
}