{
  "type": "Feature",
  "properties": {
    "addr:full":"De Singel 3 Hallum Friesland 9074 CZ",
    "addr:housenumber":"3",
    "addr:postcode":"9074",
    "addr:street":"De Singel",
    "iso:country":"NL",
    "sg:address":"De Singel 3",
    "sg:city":"Hallum",
    "sg:orig_category":"Bibliotheken En Leeszalen Openbare",
    "sg:phone":"+31 518 432 310",
    "sg:postcode":"9074 CZ",
    "sg:province":"Friesland",
    "wof:name":"Openb Bibliotheek",
    "wof:placetype":"venue"
},
  "geometry": {"coordinates":[15.47527,49.803791],"type":"Point"}
}