{
  "type": "Feature",
  "properties": {
    "addr:full":"J F Kennedyln 32 Apeldoorn Gelderland 7314 PS",
    "addr:housenumber":"32",
    "addr:postcode":"7314 ps",
    "addr:street":"J F Kennedyln;Gelderland",
    "iso:country":"NL",
    "sg:address":"J F Kennedyln 32",
    "sg:city":"Apeldoorn",
    "sg:orig_category":"Verzekeringen - Verzekeringskantoren",
    "sg:phone":"+31 55 357 6677",
    "sg:postcode":"7314 PS",
    "sg:province":"Gelderland",
    "wof:name":"Pensioen & Verzekeringskamer",
    "wof:placetype":"venue"
},
  "geometry": {"coordinates":[5.96566,52.216518],"type":"Point"}
}