{
  "type": "Feature",
  "properties": {
    "addr:full":"De Leeuwerikstr 14 Best Texas 5683 BP",
    "addr:housenumber":"14",
    "addr:postcode":"5683 bp",
    "iso:country":"NL",
    "sg:address":"De Leeuwerikstr 14",
    "sg:city":"Best",
    "sg:orig_category":"Honden- En Kattentrimsalons",
    "sg:phone":"+31 499 374 492",
    "sg:postcode":"5683 BP",
    "sg:province":"Texas",
    "wof:name":"Daisy, Hondentrimsalon",
    "wof:placetype":"venue"
},
  "geometry": {"coordinates":[-101.618134,31.224251],"type":"Point"}
}