{
  "type": "Feature",
  "properties": {
    "addr:full":"Hoofdstr 57 Tolbert Groningen 9356 AV",
    "addr:housenumber":"57",
    "addr:postcode":"9356 av",
    "addr:street":"Hoofdstr",
    "iso:country":"NL",
    "sg:address":"Hoofdstr 57",
    "sg:city":"Tolbert",
    "sg:orig_category":"Architecten En Architectenbureaus",
    "sg:phone":"+31 594 514 823",
    "sg:postcode":"9356 AV",
    "sg:province":"Groningen",
    "wof:name":"Kouwen, R",
    "wof:placetype":"venue"
},
  "geometry": {"coordinates":[-99.414536,34.226662],"type":"Point"}
}