{
  "type": "Feature",
  "properties": {
    "addr:full":"Vondellaan 43 Oosterhout Nb North Brabant 4904 BA",
    "addr:housenumber":"43;nb",
    "addr:postcode":"4904 ba",
    "addr:street":"Vondellaan",
    "iso:country":"NL",
    "sg:address":"Vondellaan 43",
    "sg:city":"Oosterhout Nb",
    "sg:orig_category":"Marketingbureaus",
    "sg:phone":"+31 162 469 290",
    "sg:postcode":"4904 BA",
    "sg:province":"North Brabant",
    "wof:name":"The Direct Mail Agency",
    "wof:placetype":"venue"
},
  "geometry": {"coordinates":[4.860848,51.625717],"type":"Point"}
}