{
  "type": "Feature",
  "properties": {
    "iso:country":"NL",
    "sg:address":"Reggestraat 8",
    "sg:city":"Amsterdam",
    "sg:orig_category":"Kappers",
    "sg:phone":"+31 20 671 4122",
    "sg:postcode":"1078 CZ",
    "sg:province":"North Holland",
    "wof:name":"Hairstudio No Name",
    "wof:placetype":"venue"
},
  "geometry": {"coordinates":[4.9016041756,52.3480796814],"type":"Point"}
}