{
  "type": "Feature",
  "properties": {
    "addr:full":"Thaborwei 1 Tirns Provincie Friesland 8632 WG",
    "addr:housenumber":"1",
    "addr:postcode":"8632 wg",
    "addr:street":"Thaborwei;Provincie Friesland",
    "iso:country":"NL",
    "sg:address":"Thaborwei 1",
    "sg:city":"Tirns",
    "sg:orig_category":"Verenigingsgebouwen",
    "sg:phone":"+31 515 569 630",
    "sg:postcode":"8632 WG",
    "sg:province":"Provincie Friesland",
    "wof:name":"Us Boppeslach",
    "wof:placetype":"venue"
},
  "geometry": {"coordinates":[5.628569,53.058277],"type":"Point"}
}