{
  "type": "Feature",
  "properties": {
    "iso:country":"NL",
    "sg:address":"Postbus 28",
    "sg:city":"Roelofarendsveen",
    "sg:orig_category":"Bloemen En Planten",
    "sg:phone":"+31 71 332 0011",
    "sg:postcode":"2370 AA",
    "sg:province":"Zuid-Holland",
    "sg:website":"http://www.bouquet.nl",
    "wof:name":"Bouquet Expressions",
    "wof:placetype":"venue"
},
  "geometry": {"coordinates":[4.6314,52.203491],"type":"Point"}
}