{
  "type": "Feature",
  "properties": {
    "iso:country":"NL",
    "sg:address":"Westplein 5",
    "sg:city":"Rotterdam",
    "sg:orig_category":"Diverse Bedrijfsinstallaties Gh",
    "sg:phone":"+31 10 436 4533",
    "sg:postcode":"3016 BM",
    "sg:province":"Zuid-Holland",
    "wof:name":"Marine Superintendents International Bv",
    "wof:placetype":"venue"
},
  "geometry": {"coordinates":[4.478027,51.906483],"type":"Point"}
}