{
  "type": "Feature",
  "properties": {
    "addr:full":"T Schip 12 Katwijk Zh Zuid-Holland 2224 RW",
    "addr:housenumber":"12",
    "addr:postcode":"2224 rw",
    "addr:street":"T Schip",
    "iso:country":"NL",
    "sg:address":"T Schip 12",
    "sg:city":"Katwijk Zh",
    "sg:orig_category":"Bloemen And Planten Gh",
    "sg:phone":"+31 71 408 4255",
    "sg:postcode":"2224 RW",
    "sg:province":"Zuid-Holland",
    "wof:name":"G.F. Vroegindeweij",
    "wof:placetype":"venue"
},
  "geometry": {"coordinates":[4.415351,52.20425],"type":"Point"}
}