{
  "type": "Feature",
  "properties": {
    "addr:full":"Hamburgerwg 137 Ermelo Gelderland 3851 EJ",
    "addr:housenumber":"137",
    "addr:postcode":"3851 ej",
    "addr:street":"Gelderland",
    "iso:country":"NL",
    "sg:address":"Hamburgerwg 137",
    "sg:city":"Ermelo",
    "sg:orig_category":"Pluimveebedrijven En -Handelaren",
    "sg:phone":"+31 341 279 100",
    "sg:postcode":"3851 EJ",
    "sg:province":"Gelderland",
    "wof:name":"Vikser",
    "wof:placetype":"venue"
},
  "geometry": {"coordinates":[5.617632,52.295437],"type":"Point"}
}