{
  "type": "Feature",
  "properties": {
    "addr:full":"Dokter Stapenseastraat 16 Leimuiden South Holland 2451 AD",
    "addr:housenumber":"16",
    "addr:postcode":"2451 ad",
    "addr:street":"Dokter Stapenseastraat",
    "iso:country":"NL",
    "sg:address":"Dokter Stapenseastraat 16",
    "sg:city":"Leimuiden",
    "sg:orig_category":"Woningbouwverenigingen",
    "sg:phone":"+31 172 503 555",
    "sg:postcode":"2451 AD",
    "sg:province":"South Holland",
    "wof:name":"Woningstichting Jacobswoude",
    "wof:placetype":"venue"
},
  "geometry": {"coordinates":[4.6734638214,52.2249679565],"type":"Point"}
}