{
  "type": "Feature",
  "properties": {
    "iso:country":"NL",
    "sg:address":"Lindeboom 1",
    "sg:city":"Mook",
    "sg:orig_category":"Goederenvervoer Over De Weg",
    "sg:phone":"+31 24 696 2111",
    "sg:postcode":"6585 BC",
    "sg:province":"Limburg",
    "wof:name":"A J M Vos Transportbedrijf Mook Vof",
    "wof:placetype":"venue"
},
  "geometry": {"coordinates":[5.887018,51.74773],"type":"Point"}
}