{
  "type": "Feature",
  "properties": {
    "addr:full":"Past Vd Boomstr 10A Berlicum Nb Noord-Brabant 5258 GE",
    "addr:housenumber":"10a",
    "addr:postcode":"5258",
    "addr:street":"Past",
    "iso:country":"NL",
    "sg:address":"Past Vd Boomstr 10A",
    "sg:city":"Berlicum Nb",
    "sg:orig_category":"Omroep",
    "sg:phone":"+31 73 503 7036",
    "sg:postcode":"5258 GE",
    "sg:province":"Noord-Brabant",
    "wof:name":"Lok Omroep St Michielsgestel",
    "wof:placetype":"venue"
},
  "geometry": {"coordinates":[5.418169,51.663883],"type":"Point"}
}