{
  "type": "Feature",
  "properties": {
    "addr:full":"Griekenlandstr 27 Bergen Op Zoom Noord-Brabant 4614 KX",
    "addr:housenumber":"27",
    "addr:postcode":"4614 kx",
    "addr:street":"Griekenlandstr",
    "iso:country":"NL",
    "sg:address":"Griekenlandstr 27",
    "sg:city":"Bergen Op Zoom",
    "sg:orig_category":"Verenigingen En Stichtingen",
    "sg:phone":"+31 164 260 601",
    "sg:postcode":"4614 KX",
    "sg:province":"Noord-Brabant",
    "wof:name":"Amaone, Sticht",
    "wof:placetype":"venue"
},
  "geometry": {"coordinates":[4.289455,51.509338],"type":"Point"}
}