{
  "type": "Feature",
  "properties": {
    "addr:full":"Middel Broekweg 36 Honselersdijk South Holland 2675 KB",
    "addr:housenumber":"36",
    "addr:postcode":"2675 kb",
    "addr:street":"Middel Broekweg",
    "iso:country":"NL",
    "sg:address":"Middel Broekweg 36",
    "sg:city":"Honselersdijk",
    "sg:orig_category":"Bloemen And Planten",
    "sg:phone":"+31 174 641 803",
    "sg:postcode":"2675 KB",
    "sg:province":"South Holland",
    "wof:name":"Fa J.A.G. Van Leeuwen En Zoon",
    "wof:placetype":"venue"
},
  "geometry": {"coordinates":[4.227959,51.996056],"type":"Point"}
}