{
  "type": "Feature",
  "properties": {
    "addr:full":"Kerkdreef 7 Chaam North Brabant 4861 PW",
    "addr:housenumber":"7",
    "addr:postcode":"4861 pw",
    "addr:street":"Kerkdreef",
    "iso:country":"NL",
    "sg:address":"Kerkdreef 7",
    "sg:city":"Chaam",
    "sg:orig_category":"Verzekeringen",
    "sg:phone":"+31 161 492 626",
    "sg:postcode":"4861 PW",
    "sg:province":"North Brabant",
    "wof:name":"J.H.M. Leijten",
    "wof:placetype":"venue"
},
  "geometry": {"coordinates":[4.876055,51.507156],"type":"Point"}
}