{
  "type": "Feature",
  "properties": {
    "addr:full":"Peter Van Anrooylaan 44 Eindhoven North Brabant 5654 MD",
    "addr:housenumber":"44",
    "addr:postcode":"5654",
    "addr:street":"Peter Van Anrooylaan",
    "iso:country":"NL",
    "sg:address":"Peter Van Anrooylaan 44",
    "sg:city":"Eindhoven",
    "sg:orig_category":"Fotostudio'S And Fotografen",
    "sg:phone":"+31 40 251 9682",
    "sg:postcode":"5654 MD",
    "sg:province":"North Brabant",
    "wof:name":"W. Bisschops",
    "wof:placetype":"venue"
},
  "geometry": {"coordinates":[5.454878,51.420753],"type":"Point"}
}