{
  "type": "Feature",
  "properties": {
    "addr:full":"Eekboerstraat 10 Oldenzaal NL.08 7575 AX",
    "addr:housenumber":"10;nl.08",
    "addr:postcode":"7575 ax",
    "addr:street":"Eekboerstraat",
    "iso:country":"NL",
    "sg:address":"Eekboerstraat 10",
    "sg:city":"Oldenzaal",
    "sg:orig_category":"Verhuur Catering-, Feest- En Evenementbenodigdheden",
    "sg:phone":"+31 541 533 480",
    "sg:postcode":"7575 AX",
    "sg:province":"NL.08",
    "wof:name":"Huisken Horeca",
    "wof:placetype":"venue"
},
  "geometry": {"coordinates":[6.929431,52.30098],"type":"Point"}
}