{
  "type": "Feature",
  "properties": {
    "addr:full":"Wattstraat 6 Venlo Limburg 5928 PB",
    "addr:housenumber":"6",
    "addr:postcode":"5928 pb",
    "addr:street":"Wattstraat",
    "iso:country":"NL",
    "sg:address":"Wattstraat 6",
    "sg:city":"Venlo",
    "sg:classifiers":[
        {
            "category":"Fast Food",
            "type":"Food & Drink"
        }
    ],
    "sg:phone":"+31 77 387 2139",
    "sg:postcode":"5928 PB",
    "sg:province":"Limburg",
    "sg:tags":[
        "afhaal",
        "restaurant"
    ],
    "wof:name":"Eethuis Groot Boller",
    "wof:placetype":"venue"
},
  "geometry": {"coordinates":[6.14044,51.382942],"type":"Point"}
}