{
  "type": "Feature",
  "properties": {
    "addr:full":"Weena 290 Rotterdam South Holland 3012 NJ",
    "addr:housenumber":"290",
    "addr:postcode":"3012 nj",
    "addr:street":"Weena",
    "iso:country":"NL",
    "sg:address":"Weena 290",
    "sg:city":"Rotterdam",
    "sg:orig_category":"Bedrijfshuisvesting",
    "sg:phone":"+31 10 282 1200",
    "sg:postcode":"3012 NJ",
    "sg:province":"South Holland",
    "sg:website":"http://www.regus.nl",
    "wof:name":"Regus Business Centres",
    "wof:placetype":"venue"
},
  "geometry": {"coordinates":[4.47376,51.923367],"type":"Point"}
}