{
  "type": "Feature",
  "properties": {
    "addr:full":"Mijnsherenlaan 223 Rotterdam South Holland 3081 GR",
    "addr:housenumber":"223",
    "addr:postcode":"3081",
    "addr:street":"Mijnsherenlaan",
    "iso:country":"NL",
    "sg:address":"Mijnsherenlaan 223",
    "sg:city":"Rotterdam",
    "sg:orig_category":"Bloemen And Planten",
    "sg:phone":"+31 10 486 2111",
    "sg:postcode":"3081 GR",
    "sg:province":"South Holland",
    "wof:name":"Centraflor Bv",
    "wof:placetype":"venue"
},
  "geometry": {"coordinates":[4.488174,51.890484],"type":"Point"}
}