{
  "type": "Feature",
  "properties": {
    "addr:full":"Amsteldk N 160 Uithoorn North Holland 1422 XZ",
    "addr:housenumber":"160",
    "addr:postcode":"1422 xz",
    "addr:street":"N",
    "iso:country":"NL",
    "sg:address":"Amsteldk N 160",
    "sg:city":"Uithoorn",
    "sg:orig_category":"Metaalbewerking",
    "sg:phone":"+31 6 53530187",
    "sg:postcode":"1422 XZ",
    "sg:province":"North Holland",
    "wof:name":"Kuit",
    "wof:placetype":"venue"
},
  "geometry": {"coordinates":[4.850637,52.241127],"type":"Point"}
}