{
  "type": "Feature",
  "properties": {
    "addr:full":"Gersthove 24 Diemen Noord-Holland 1112 HP",
    "addr:housenumber":"24",
    "addr:postcode":"1112 hp",
    "addr:street":"Gersthove",
    "iso:country":"NL",
    "sg:address":"Gersthove 24",
    "sg:city":"Diemen",
    "sg:orig_category":"Huizensloop And Bouwrijp Maken",
    "sg:phone":"+31 20 690 0609",
    "sg:postcode":"1112 HP",
    "sg:province":"Noord-Holland",
    "wof:name":"Handelsonderneming S Broer",
    "wof:placetype":"venue"
},
  "geometry": {"coordinates":[4.952751,52.334728],"type":"Point"}
}