{
  "type": "Feature",
  "properties": {
    "addr:full":"Enschedesestraat 50 Hengelo Ov NL.08 7551 EN",
    "addr:housenumber":"50",
    "addr:postcode":"7551 en",
    "addr:street":"Enschedesestraat;Ov",
    "iso:country":"NL",
    "sg:address":"Enschedesestraat 50",
    "sg:city":"Hengelo Ov",
    "sg:orig_category":"Hypotheken And Hypotheekbanken",
    "sg:phone":"+31 74 250 3434",
    "sg:postcode":"7551 EN",
    "sg:province":"NL.08",
    "wof:name":"Leverink & Assen Makelaars Og",
    "wof:placetype":"venue"
},
  "geometry": {"coordinates":[6.796245,52.264091],"type":"Point"}
}