{
  "type": "Feature",
  "properties": {
    "iso:country":"NL",
    "sg:address":"Ekkersryt 4026",
    "sg:city":"Son",
    "sg:orig_category":"Verlichting",
    "sg:phone":"+31 499 474 000",
    "sg:postcode":"5692 DA",
    "sg:province":"Texas",
    "sg:website":"http://www.vandenheuvelverlichting.nl",
    "wof:name":"Heuvel, Van Den",
    "wof:placetype":"venue"
},
  "geometry": {"coordinates":[-101.937622,35.189621],"type":"Point"}
}