{
  "type": "Feature",
  "properties": {
    "iso:country":"NL",
    "sg:address":"2E Helmersstr 4",
    "sg:city":"Amsterdam",
    "sg:classifiers":[
        {
            "category":"Travel",
            "subcategory":"Hotels & Motels",
            "type":"Entertainment"
        }
    ],
    "sg:phone":"+31 20 616 0125",
    "sg:postcode":"1054 CH",
    "sg:province":"Noord-Holland",
    "sg:website":"http://www.hoteldamsterdam.com",
    "wof:name":"Amsterdam, D'",
    "wof:placetype":"venue"
},
  "geometry": {"coordinates":[-74.17935199999999,42.939522],"type":"Point"}
}