{
  "type": "Feature",
  "properties": {
    "addr:full":"2E Helmersstr 4 Amsterdam Noord-Holland 1054 CH",
    "addr:housenumber":"4",
    "addr:postcode":"1054",
    "addr:street":"2E Helmersstr",
    "iso:country":"NL",
    "sg:address":"2E Helmersstr 4",
    "sg:city":"Amsterdam",
    "sg:classifiers":[
        {
            "category":"Travel",
            "subcategory":"Hotels & Motels",
            "type":"Entertainment"
        }
    ],
    "sg:phone":"+31 20 616 0125",
    "sg:postcode":"1054 CH",
    "sg:province":"Noord-Holland",
    "sg:website":"http://www.hoteldamsterdam.com",
    "wof:name":"Amsterdam, D'",
    "wof:placetype":"venue"
},
  "geometry": {"coordinates":[-74.17935199999999,42.939522],"type":"Point"}
}