{
  "type": "Feature",
  "properties": {
    "addr:full":"Lijsterbesstraat 18 Waddinxveen Zuid-Holland 2742 XS",
    "addr:housenumber":"18",
    "addr:postcode":"2742 xs",
    "addr:street":"Lijsterbesstraat",
    "iso:country":"NL",
    "sg:address":"Lijsterbesstraat 18",
    "sg:city":"Waddinxveen",
    "sg:orig_category":"Overheidsdiensten",
    "sg:phone":"+31 182 612 276",
    "sg:postcode":"2742 XS",
    "sg:province":"Zuid-Holland",
    "wof:name":"De Paddestoel",
    "wof:placetype":"venue"
},
  "geometry": {"coordinates":[4.6462168694,52.0428848267],"type":"Point"}
}