{
  "type": "Feature",
  "properties": {
    "iso:country":"NL",
    "sg:address":"Rijndijk 238",
    "sg:city":"Leiden",
    "sg:orig_category":"Autokeuringen",
    "sg:phone":"+31 71 576 9437",
    "sg:postcode":"2331 AM",
    "sg:province":"South Holland",
    "wof:name":"Garage De Wit",
    "wof:placetype":"venue"
},
  "geometry": {"coordinates":[4.453072,52.156708],"type":"Point"}
}