{
  "type": "Feature",
  "properties": {
    "addr:full":"Ijsselkade 28 Zutphen Gelderland 7201 HD",
    "addr:housenumber":"28",
    "addr:postcode":"7201 hd",
    "addr:street":"Ijsselkade;Gelderland",
    "iso:country":"NL",
    "sg:address":"Ijsselkade 28",
    "sg:city":"Zutphen",
    "sg:orig_category":"Verzekeringen",
    "sg:phone":"+31 575 516 433",
    "sg:postcode":"7201 HD",
    "sg:province":"Gelderland",
    "wof:name":"Mulderije Groep",
    "wof:placetype":"venue"
},
  "geometry": {"coordinates":[6.191919,52.13966],"type":"Point"}
}