{
  "type": "Feature",
  "properties": {
    "addr:full":"Vlie 19 Huizen North Holland 1273 WK",
    "addr:housenumber":"19",
    "addr:postcode":"1273 wk",
    "addr:street":"Vlie",
    "iso:country":"NL",
    "sg:address":"Vlie 19",
    "sg:city":"Huizen",
    "sg:orig_category":"Autorijscholen",
    "sg:phone":"+31 35 526 1550",
    "sg:postcode":"1273 WK",
    "sg:province":"North Holland",
    "wof:name":"Gooijer",
    "wof:placetype":"venue"
},
  "geometry": {"coordinates":[5.258749,52.302227],"type":"Point"}
}