{
  "type": "Feature",
  "properties": {
    "addr:full":"Van Der Duyn V Maasdamln 19 Huizen Noord-Holland 1272 EL",
    "addr:housenumber":"19;1272",
    "addr:postcode":"el",
    "addr:street":"Van Der Duyn V Maasdamln",
    "iso:country":"NL",
    "sg:address":"Van Der Duyn V Maasdamln 19",
    "sg:city":"Huizen",
    "sg:orig_category":"Fotostudio'S And Fotografen",
    "sg:phone":"+31 35 524 1006",
    "sg:postcode":"1272 EL",
    "sg:province":"Noord-Holland",
    "wof:name":"Martin Kers Photography",
    "wof:placetype":"venue"
},
  "geometry": {"coordinates":[5.23421,52.29504],"type":"Point"}
}