{
  "type": "Feature",
  "properties": {
    "addr:full":"Deurningerstr 28 Enschede Overijssel 7514 BJ",
    "addr:housenumber":"28",
    "addr:postcode":"7514 bj",
    "addr:street":"Deurningerstr",
    "iso:country":"NL",
    "sg:address":"Deurningerstr 28",
    "sg:city":"Enschede",
    "sg:orig_category":"Automaterialen En Gereedschappen",
    "sg:phone":"+31 53 435 6415",
    "sg:postcode":"7514 BJ",
    "sg:province":"Overijssel",
    "wof:name":"Mobi Markt Bv",
    "wof:placetype":"venue"
},
  "geometry": {"coordinates":[6.891339,52.225994],"type":"Point"}
}