{
  "type": "Feature",
  "properties": {
    "addr:full":"Middenwg 32 Ysselstein Ut Utrecht 3401 MB",
    "addr:housenumber":"32",
    "addr:postcode":"3401 mb",
    "addr:street":"Middenwg",
    "iso:country":"NL",
    "sg:address":"Middenwg 32",
    "sg:city":"Ysselstein Ut",
    "sg:orig_category":"Gassen Industrieel En Medisch",
    "sg:phone":"+31 30 688 4876",
    "sg:postcode":"3401 MB",
    "sg:province":"Utrecht",
    "wof:name":"Lastechniek Holland Bv",
    "wof:placetype":"venue"
},
  "geometry": {"coordinates":[5.055558,52.013908],"type":"Point"}
}