{
  "type": "Feature",
  "properties": {
    "addr:full":"Leidseweg 46 Oud Ade Zuid-Holland 2374 AR",
    "addr:housenumber":"46",
    "addr:postcode":"ade;2374",
    "addr:street":"Leidseweg",
    "iso:country":"NL",
    "sg:address":"Leidseweg 46",
    "sg:city":"Oud Ade",
    "sg:orig_category":"Meubelreparatie And -Restauratie",
    "sg:phone":"+31 71 501 2270",
    "sg:postcode":"2374 AR",
    "sg:province":"Zuid-Holland",
    "wof:name":"Pro Sedis",
    "wof:placetype":"venue"
},
  "geometry": {"coordinates":[4.546583,52.188816],"type":"Point"}
}