{
  "type": "Feature",
  "properties": {
    "addr:full":"Boekelstraat 16 Hoofddorp North Holland 2131 WT",
    "addr:housenumber":"16",
    "addr:postcode":"2131 wt",
    "addr:street":"Boekelstraat",
    "iso:country":"NL",
    "sg:address":"Boekelstraat 16",
    "sg:city":"Hoofddorp",
    "sg:orig_category":"Boekhouders",
    "sg:phone":"+31 23 565 0864",
    "sg:postcode":"2131 WT",
    "sg:province":"North Holland",
    "wof:name":"C. Verhulst",
    "wof:placetype":"venue"
},
  "geometry": {"coordinates":[4.686812,52.305172],"type":"Point"}
}