{
  "type": "Feature",
  "properties": {
    "addr:full":"Postbus 6045 Leeuwarden Limburg 8902 HA",
    "addr:housenumber":"6045",
    "addr:postcode":"8902 ha",
    "addr:street":"Postbus",
    "iso:country":"NL",
    "sg:address":"Postbus 6045",
    "sg:city":"Leeuwarden",
    "sg:orig_category":"Vertaalbureaus",
    "sg:phone":"+31 58 267 5378",
    "sg:postcode":"8902 HA",
    "sg:province":"Limburg",
    "wof:name":"Cvt",
    "wof:placetype":"venue"
},
  "geometry": {"coordinates":[5.79143,53.203049],"type":"Point"}
}