{
  "type": "Feature",
  "properties": {
    "addr:full":"Handelstraat 58 Stadskanaal Groningen 9501  E",
    "addr:housenumber":"58;9501",
    "addr:street":"Handelstraat;E",
    "iso:country":"NL",
    "sg:address":"Handelstraat 58",
    "sg:city":"Stadskanaal",
    "sg:orig_category":"Meubelzaken, Woning- And Keukeninrichting",
    "sg:phone":"+31 599 613 412",
    "sg:postcode":"9501  E",
    "sg:province":"Groningen",
    "wof:name":"Dobken Design",
    "wof:placetype":"venue"
},
  "geometry": {"coordinates":[6.938479,52.996357],"type":"Point"}
}