{
  "type": "Feature",
  "properties": {
    "addr:full":"Boekweitstr 44 Nieuw Vennep Noord-Holland 2153 GL",
    "addr:housenumber":"44",
    "addr:postcode":"2153 gl",
    "addr:street":"Boekweitstr;Nieuw Vennep",
    "iso:country":"NL",
    "sg:address":"Boekweitstr 44",
    "sg:city":"Nieuw Vennep",
    "sg:orig_category":"Autoruiten",
    "sg:phone":"+31 252 422 887",
    "sg:postcode":"2153 GL",
    "sg:province":"Noord-Holland",
    "wof:name":"Autoglas",
    "wof:placetype":"venue"
},
  "geometry": {"coordinates":[4.649629,52.266293],"type":"Point"}
}