{
  "type": "Feature",
  "properties": {
    "addr:full":"Oplosedk 4 Overloon Noord-Brabant 5825 HZ",
    "addr:housenumber":"4",
    "addr:postcode":"5825 hz",
    "addr:street":"Oplosedk",
    "iso:country":"NL",
    "sg:address":"Oplosedk 4",
    "sg:city":"Overloon",
    "sg:orig_category":"Loonbedrijven",
    "sg:phone":"+31 478 641 280",
    "sg:postcode":"5825 HZ",
    "sg:province":"Noord-Brabant",
    "wof:name":"Hubers En Zn, Fa",
    "wof:placetype":"venue"
},
  "geometry": {"coordinates":[5.928807,51.578133],"type":"Point"}
}