{
  "type": "Feature",
  "properties": {
    "addr:full":"Jan Bijhouwerstraat 28 Ijsselstein (Ut) Utrecht 3404 AM",
    "addr:housenumber":"28",
    "addr:postcode":"3404",
    "addr:street":"Jan Bijhouwerstraat",
    "iso:country":"NL",
    "sg:address":"Jan Bijhouwerstraat 28",
    "sg:city":"Ijsselstein (Ut)",
    "sg:orig_category":"Verpakkingsbedrijven",
    "sg:phone":"+31 30 687 4324",
    "sg:postcode":"3404 AM",
    "sg:province":"Utrecht",
    "wof:name":"Non-Food Inpakservice J. Stam",
    "wof:placetype":"venue"
},
  "geometry": {"coordinates":[5.045321,52.011787],"type":"Point"}
}