{
  "type": "Feature",
  "properties": {
    "addr:full":"Koninginneln 80 Apeldoorn Gelderland 7315 BV",
    "addr:housenumber":"80",
    "addr:postcode":"7315 bv",
    "addr:street":"Koninginneln;Gelderland",
    "iso:country":"NL",
    "sg:address":"Koninginneln 80",
    "sg:city":"Apeldoorn",
    "sg:orig_category":"Leesportefeuilles",
    "sg:phone":"+31 55 521 7903",
    "sg:postcode":"7315 BV",
    "sg:province":"Gelderland",
    "wof:name":"Nederlandse Leeskring",
    "wof:placetype":"venue"
},
  "geometry": {"coordinates":[5.957549,52.226768],"type":"Point"}
}