{
  "type": "Feature",
  "properties": {
    "addr:full":"Zuiderzeestrwg 492 Wezep Gelderland 8091 CS",
    "addr:housenumber":"492",
    "addr:postcode":"8091 cs",
    "iso:country":"NL",
    "sg:address":"Zuiderzeestrwg 492",
    "sg:city":"Wezep",
    "sg:orig_category":"Omroep",
    "sg:phone":"+31 38 376 2981",
    "sg:postcode":"8091 CS",
    "sg:province":"Gelderland",
    "wof:name":"Loco Groep",
    "wof:placetype":"venue"
},
  "geometry": {"coordinates":[5.99888,52.458267],"type":"Point"}
}