{
  "type": "Feature",
  "properties": {
    "iso:country":"NL",
    "sg:address":"Postbus 330",
    "sg:city":"Nymegen",
    "sg:orig_category":"Postzegels",
    "sg:phone":"+31 24 377 7730",
    "sg:postcode":"6500 AH",
    "sg:province":"Gelderland",
    "wof:name":"Haarlem, J Van",
    "wof:placetype":"venue"
},
  "geometry": {"coordinates":[5.83296,51.842651],"type":"Point"}
}