{
  "type": "Feature",
  "properties": {
    "addr:full":"Burg U De Vrieswg 29 T Harde Gelderland 8084 AR",
    "addr:housenumber":"29",
    "addr:postcode":"8084",
    "addr:street":"Burg U De Vrieswg",
    "iso:country":"NL",
    "sg:address":"Burg U De Vrieswg 29",
    "sg:city":"T Harde",
    "sg:orig_category":"Journalisten Freelance",
    "sg:phone":"+31 525 651 452",
    "sg:postcode":"8084 AR",
    "sg:province":"Gelderland",
    "wof:name":"Moor, Janny De",
    "wof:placetype":"venue"
},
  "geometry": {"coordinates":[5.878539,52.408886],"type":"Point"}
}