{
  "type": "Feature",
  "properties": {
    "addr:full":"Dolomietenlaan 30 Tilburg Noord-Brabant 5022 JK",
    "addr:housenumber":"30",
    "addr:postcode":"5022 jk",
    "addr:street":"Dolomietenlaan",
    "iso:country":"NL",
    "sg:address":"Dolomietenlaan 30",
    "sg:city":"Tilburg",
    "sg:orig_category":"Verzekeringen",
    "sg:phone":"+31 13 543 3849",
    "sg:postcode":"5022 JK",
    "sg:province":"Noord-Brabant",
    "wof:name":"P Joosten, Verzekeringen En Financieringen",
    "wof:placetype":"venue"
},
  "geometry": {"coordinates":[5.086583,51.538719],"type":"Point"}
}