{
  "type": "Feature",
  "properties": {
    "addr:full":"De Panoven 25 Geldermalsen Gelderland 4191 GW",
    "addr:housenumber":"25",
    "addr:postcode":"4191 gw",
    "addr:street":"De Panoven;Gelderland",
    "iso:country":"NL",
    "sg:address":"De Panoven 25",
    "sg:city":"Geldermalsen",
    "sg:classifiers":[
        {
            "category":"Professional",
            "subcategory":"Accounting & Tax Preparation",
            "type":"Services"
        }
    ],
    "sg:phone":"+31 345 575 195",
    "sg:postcode":"4191 GW",
    "sg:province":"Gelderland",
    "sg:tags":[
        "accountant"
    ],
    "wof:name":"Accountantskantoor Hilhorst",
    "wof:placetype":"venue"
},
  "geometry": {"coordinates":[5.301057,51.881203],"type":"Point"}
}