{
  "type": "Feature",
  "properties": {
    "addr:full":"Noordeinde 14 'S Gravenhage Zuid-Holland 2514 GH",
    "addr:housenumber":"14",
    "addr:postcode":"2514 gh",
    "addr:street":"Noordeinde;' S",
    "iso:country":"NL",
    "sg:address":"Noordeinde 14",
    "sg:city":"'S Gravenhage",
    "sg:orig_category":"Overheidsdiensten",
    "sg:phone":"+31 70 364 4197",
    "sg:postcode":"2514 GH",
    "sg:province":"Zuid-Holland",
    "wof:name":"Societeit De Pijpela",
    "wof:placetype":"venue"
},
  "geometry": {"coordinates":[4.3093500137,52.084148407],"type":"Point"}
}