{
  "type": "Feature",
  "properties": {
    "iso:country":"NL",
    "sg:address":"Rotterdamsewg 205",
    "sg:city":"Delft",
    "sg:orig_category":"Verenigingen En Stichtingen",
    "sg:phone":"+31 15 256 5589",
    "sg:postcode":"2629 HD",
    "sg:province":"Zuid-Holland",
    "wof:name":"World Art Delft",
    "wof:placetype":"venue"
},
  "geometry": {"coordinates":[4.380797,51.980431],"type":"Point"}
}