{
  "type": "Feature",
  "properties": {
    "addr:full":"Zelhemseweg 24 Hengelo Gld Gelderland 7255 PT",
    "addr:housenumber":"24",
    "addr:postcode":"7255 pt",
    "addr:street":"Zelhemseweg",
    "iso:country":"NL",
    "sg:address":"Zelhemseweg 24",
    "sg:city":"Hengelo Gld",
    "sg:orig_category":"Paardensport",
    "sg:phone":"+31 575 467 258",
    "sg:postcode":"7255 PT",
    "sg:province":"Gelderland",
    "sg:website":"http://www.homac.nl",
    "wof:name":"Homac",
    "wof:placetype":"venue"
},
  "geometry": {"coordinates":[6.309492,52.043774],"type":"Point"}
}