{
  "type": "Feature",
  "properties": {
    "addr:full":"Oostmaasln 862 Rotterdam Zuid-Holland 3063 DL",
    "addr:housenumber":"862",
    "addr:postcode":"3063 dl",
    "iso:country":"NL",
    "sg:address":"Oostmaasln 862",
    "sg:city":"Rotterdam",
    "sg:orig_category":"Adviesbureaus Bedrijfsorganisatie",
    "sg:phone":"+31 10 242 7450",
    "sg:postcode":"3063 DL",
    "sg:province":"Zuid-Holland",
    "wof:name":"Kb Bv",
    "wof:placetype":"venue"
},
  "geometry": {"coordinates":[4.515774,51.917118],"type":"Point"}
}