{
  "type": "Feature",
  "properties": {
    "addr:full":"Dwarswg 13 Zegveld Utrecht 3474 KW",
    "addr:housenumber":"13",
    "addr:postcode":"3474 kw",
    "addr:street":"Dwarswg",
    "iso:country":"NL",
    "sg:address":"Dwarswg 13",
    "sg:city":"Zegveld",
    "sg:orig_category":"Onderhoudswerken",
    "sg:phone":"+31 348 691 183",
    "sg:postcode":"3474 KW",
    "sg:province":"Utrecht",
    "wof:name":"Leeuw, L De",
    "wof:placetype":"venue"
},
  "geometry": {"coordinates":[4.816107,52.119396],"type":"Point"}
}