{
  "type": "Feature",
  "properties": {
    "addr:full":"Tudderenderweg 303 Sittard North Rhine-Westphalia 6137 LA",
    "addr:housenumber":"303",
    "addr:postcode":"6137 la",
    "addr:street":"Tudderenderweg",
    "iso:country":"NL",
    "sg:address":"Tudderenderweg 303",
    "sg:city":"Sittard",
    "sg:classifiers":[
        {
            "category":"Food & Beverages",
            "subcategory":"Fruits & Vegetables",
            "type":"Retail Goods"
        }
    ],
    "sg:phone":"+31 46 420 0515",
    "sg:postcode":"6137 LA",
    "sg:province":"North Rhine-Westphalia",
    "sg:tags":[
        "groenten"
    ],
    "wof:name":"Jetten",
    "wof:placetype":"venue"
},
  "geometry": {"coordinates":[5.889878,51.009499],"type":"Point"}
}