{
  "type": "Feature",
  "properties": {
    "addr:full":"Vestdk 52 Eindhoven Noord-Brabant 5611 CE",
    "addr:housenumber":"52",
    "addr:postcode":"5611 ce",
    "addr:street":"Vestdk",
    "iso:country":"NL",
    "sg:address":"Vestdk 52",
    "sg:city":"Eindhoven",
    "sg:orig_category":"Kappers",
    "sg:phone":"+31 40 269 1752",
    "sg:postcode":"5611 CE",
    "sg:province":"Noord-Brabant",
    "wof:name":"Pop",
    "wof:placetype":"venue"
},
  "geometry": {"coordinates":[5.481924,51.438244],"type":"Point"}
}