{
  "type": "Feature",
  "properties": {
    "iso:country":"NL",
    "sg:address":"Van Vollenhovenlaan 679",
    "sg:city":"Utrecht",
    "sg:orig_category":"Werving En Selectie",
    "sg:phone":"+31 30 281 7161",
    "sg:postcode":"3527 JP",
    "sg:province":"Utrecht",
    "wof:name":"3 Pm Associates",
    "wof:placetype":"venue"
},
  "geometry": {"coordinates":[5.0976748466,52.074848175],"type":"Point"}
}