{
  "type": "Feature",
  "properties": {
    "addr:full":"Langegr 39 Amersfoort Utrecht 3811 BW",
    "addr:housenumber":"39",
    "addr:postcode":"3811 bw",
    "addr:street":"Langegr",
    "iso:country":"NL",
    "sg:address":"Langegr 39",
    "sg:city":"Amersfoort",
    "sg:orig_category":"Adviesbureaus Bedrijfsorganisatie",
    "sg:phone":"+31 33 465 3049",
    "sg:postcode":"3811 BW",
    "sg:province":"Utrecht",
    "wof:name":"Hayes",
    "wof:placetype":"venue"
},
  "geometry": {"coordinates":[5.386085,52.152325],"type":"Point"}
}