{
  "type": "Feature",
  "properties": {
    "iso:country":"NL",
    "sg:address":"Ommoordseweg 35",
    "sg:city":"Rotterdam",
    "sg:orig_category":"Bloemen And Planten",
    "sg:phone":"+31 10 455 2051",
    "sg:postcode":"3056 JN",
    "sg:province":"South Holland",
    "wof:name":"Tuincentrum Ommoordse Hof",
    "wof:placetype":"venue"
},
  "geometry": {"coordinates":[4.525658,51.954517],"type":"Point"}
}