{
  "type": "Feature",
  "properties": {
    "addr:full":"Giekerkstr 45A Tilburg Noord-Brabant 5043 MX",
    "addr:housenumber":"45a",
    "addr:postcode":"5043 mx",
    "addr:street":"Giekerkstr",
    "iso:country":"NL",
    "sg:address":"Giekerkstr 45A",
    "sg:city":"Tilburg",
    "sg:orig_category":"Kinderopvang",
    "sg:phone":"+31 13 571 2316",
    "sg:postcode":"5043 MX",
    "sg:province":"Noord-Brabant",
    "wof:name":"Kionki",
    "wof:placetype":"venue"
},
  "geometry": {"coordinates":[5.007963,51.582012],"type":"Point"}
}