{
  "type": "Feature",
  "properties": {
    "addr:full":"Bredasewg 108A Oosterhout Nb North Brabant 4902 NS",
    "addr:housenumber":"108a;nb",
    "addr:postcode":"4902 ns",
    "iso:country":"NL",
    "sg:address":"Bredasewg 108A",
    "sg:city":"Oosterhout Nb",
    "sg:orig_category":"Werving En Selectie",
    "sg:phone":"+31 162 453 561",
    "sg:postcode":"4902 NS",
    "sg:province":"North Brabant",
    "wof:name":"Bkv",
    "wof:placetype":"venue"
},
  "geometry": {"coordinates":[4.8484020233,51.6395568848],"type":"Point"}
}