{
  "type": "Feature",
  "properties": {
    "addr:full":"Meentweg 81 Eemnes Utrecht 3755 PB",
    "addr:housenumber":"81",
    "addr:postcode":"3755 pb",
    "addr:street":"Meentweg",
    "iso:country":"NL",
    "sg:address":"Meentweg 81",
    "sg:city":"Eemnes",
    "sg:orig_category":"Marktonderzoekbureaus",
    "sg:phone":"+31 35 531 7622",
    "sg:postcode":"3755 PB",
    "sg:province":"Utrecht",
    "wof:name":"Ruhe Asset Management Bv",
    "wof:placetype":"venue"
},
  "geometry": {"coordinates":[5.270657,52.262108],"type":"Point"}
}