{
  "type": "Feature",
  "properties": {
    "addr:full":"Hanzeplein 1 Groningen Groningen 9713 GZ",
    "addr:housenumber":"1",
    "addr:postcode":"9713 gz",
    "addr:street":"Hanzeplein",
    "iso:country":"NL",
    "sg:address":"Hanzeplein 1",
    "sg:city":"Groningen",
    "sg:orig_category":"Opticiens",
    "sg:phone":"+31 50 361 3992",
    "sg:postcode":"9713 GZ",
    "sg:province":"Groningen",
    "wof:name":"Oculenti Contactlenzen",
    "wof:placetype":"venue"
},
  "geometry": {"coordinates":[6.5770430565,53.220993042],"type":"Point"}
}