{
  "type": "Feature",
  "properties": {
    "addr:full":"Dadelstraat 8 Utrecht Utrecht 3572 TE",
    "addr:housenumber":"8",
    "addr:postcode":"3572 te",
    "addr:street":"Dadelstraat",
    "iso:country":"NL",
    "sg:address":"Dadelstraat 8",
    "sg:city":"Utrecht",
    "sg:orig_category":"Public Relationbureaus",
    "sg:phone":"+31 30 273 3997",
    "sg:postcode":"3572 TE",
    "sg:province":"Utrecht",
    "wof:name":"C.W. Coolsma",
    "wof:placetype":"venue"
},
  "geometry": {"coordinates":[5.13325,52.097389],"type":"Point"}
}