{
  "type": "Feature",
  "properties": {
    "addr:full":"Waterstr 46 Delfzyl Groningen 9934 AW",
    "addr:housenumber":"46",
    "addr:postcode":"9934 aw",
    "addr:street":"Waterstr",
    "iso:country":"NL",
    "sg:address":"Waterstr 46",
    "sg:city":"Delfzyl",
    "sg:orig_category":"Kaas",
    "sg:phone":"+31 596 612 612",
    "sg:postcode":"9934 AW",
    "sg:province":"Groningen",
    "sg:website":"http://www.j-vandijk.nl",
    "wof:name":"Dijk'S Kaashuis, J Van",
    "wof:placetype":"venue"
},
  "geometry": {"coordinates":[6.9269948006,53.3320655823],"type":"Point"}
}