{
  "type": "Feature",
  "properties": {
    "addr:full":"Willem Barentszstraat 23 Leiden Zuid-Holland 2315 TZ",
    "addr:housenumber":"23",
    "addr:postcode":"2315 tz",
    "addr:street":"Willem Barentszstraat",
    "iso:country":"NL",
    "sg:address":"Willem Barentszstraat 23",
    "sg:city":"Leiden",
    "sg:orig_category":"Onderhoud And Reparatie Kantoorapparatuur",
    "sg:phone":"+31 71 568 2555",
    "sg:postcode":"2315 TZ",
    "sg:province":"Zuid-Holland",
    "wof:name":"Microfix Nv",
    "wof:placetype":"venue"
},
  "geometry": {"coordinates":[4.511372,52.160675],"type":"Point"}
}