{
  "type": "Feature",
  "properties": {
    "addr:full":"Ruysstr 24D Bussum North Holland 1403 SJ",
    "addr:housenumber":"24d",
    "addr:postcode":"1403",
    "addr:street":"Ruysstr",
    "iso:country":"NL",
    "sg:address":"Ruysstr 24D",
    "sg:city":"Bussum",
    "sg:orig_category":"Verbouwingen",
    "sg:phone":"+31 35 642 2707",
    "sg:postcode":"1403 SJ",
    "sg:province":"North Holland",
    "wof:name":"Tap Onderhoud Renovatiebedrijf",
    "wof:placetype":"venue"
},
  "geometry": {"coordinates":[5.172179,52.265156],"type":"Point"}
}