{
  "type": "Feature",
  "properties": {
    "iso:country":"NL",
    "sg:address":"Nyverheidswg 12",
    "sg:city":"T Harde",
    "sg:classifiers":[
        {
            "category":"Home & Garden",
            "subcategory":"Hardware",
            "type":"Retail Goods"
        }
    ],
    "sg:phone":"+31 525 654 800",
    "sg:postcode":"8084 GW",
    "sg:province":"Gelderland",
    "sg:tags":[
        "machine",
        "-",
        "metaalbewerking"
    ],
    "wof:name":"Mogema Bv",
    "wof:placetype":"venue"
},
  "geometry": {"coordinates":[5.875674,52.419693],"type":"Point"}
}