{
  "type": "Feature",
  "properties": {
    "addr:full":"Nyverheidswg 12 T Harde Gelderland 8084 GW",
    "addr:housenumber":"12 t",
    "addr:postcode":"8084 gw",
    "addr:street":"Nyverheidswg;Harde Gelderland",
    "iso:country":"NL",
    "sg:address":"Nyverheidswg 12",
    "sg:city":"T Harde",
    "sg:classifiers":[
        {
            "category":"Home & Garden",
            "subcategory":"Hardware",
            "type":"Retail Goods"
        }
    ],
    "sg:phone":"+31 525 654 800",
    "sg:postcode":"8084 GW",
    "sg:province":"Gelderland",
    "sg:tags":[
        "machine",
        "-",
        "metaalbewerking"
    ],
    "wof:name":"Mogema Bv",
    "wof:placetype":"venue"
},
  "geometry": {"coordinates":[5.875674,52.419693],"type":"Point"}
}