{
  "type": "Feature",
  "properties": {
    "addr:full":"Kastanjelaan 1 Raalte NL.08 8102 JE",
    "addr:housenumber":"1;nl.08",
    "addr:postcode":"8102 je",
    "addr:street":"Kastanjelaan",
    "iso:country":"NL",
    "sg:address":"Kastanjelaan 1",
    "sg:city":"Raalte",
    "sg:orig_category":"Werving And Selectie Van Vast Personeel",
    "sg:phone":"+31 572 360 903",
    "sg:postcode":"8102 JE",
    "sg:province":"NL.08",
    "wof:name":"Arbeidsbureau Raalte",
    "wof:placetype":"venue"
},
  "geometry": {"coordinates":[6.2733840942,52.3798332214],"type":"Point"}
}