{
  "type": "Feature",
  "properties": {
    "addr:full":"Everlostr 16 Rossum Ov Overijssel 7596 MR",
    "addr:housenumber":"16",
    "addr:postcode":"7596 mr",
    "addr:street":"Everlostr;Ov",
    "iso:country":"NL",
    "sg:address":"Everlostr 16",
    "sg:city":"Rossum Ov",
    "sg:orig_category":"Zalenverhuur",
    "sg:phone":"+31 541 625 244",
    "sg:postcode":"7596 MR",
    "sg:province":"Overijssel",
    "wof:name":"Everloo, Havezathe 'T",
    "wof:placetype":"venue"
},
  "geometry": {"coordinates":[6.951026,52.358341],"type":"Point"}
}