{
  "type": "Feature",
  "properties": {
    "addr:full":"Kastanjeln 1 Aalsmeer Noord-Holland 1431 JB",
    "addr:housenumber":"1",
    "addr:postcode":"1431 jb",
    "addr:street":"Kastanjeln",
    "iso:country":"NL",
    "sg:address":"Kastanjeln 1",
    "sg:city":"Aalsmeer",
    "sg:orig_category":"Kinderkleding",
    "sg:phone":"+31 297 345 925",
    "sg:postcode":"1431 JB",
    "sg:province":"Noord-Holland",
    "wof:name":"Kortjakje",
    "wof:placetype":"venue"
},
  "geometry": {"coordinates":[4.763744,52.264915],"type":"Point"}
}