{
  "type": "Feature",
  "properties": {
    "iso:country":"NL",
    "sg:address":"Houtmanstr 20",
    "sg:city":"Amsterdam",
    "sg:orig_category":"Vertalers",
    "sg:phone":"+31 20 627 3121",
    "sg:postcode":"1013 MN",
    "sg:province":"North Holland",
    "wof:name":"Japan Translation Office",
    "wof:placetype":"venue"
},
  "geometry": {"coordinates":[4.884595,52.387318],"type":"Point"}
}