{
  "type": "Feature",
  "properties": {
    "iso:country":"NL",
    "sg:address":"Walt Disneyplantsoen 92",
    "sg:city":"Almere",
    "sg:orig_category":"Kinderopvang Behalve Thuis",
    "sg:phone":"+31 36 537 7395",
    "sg:postcode":"1325 SX",
    "sg:province":"Flevoland",
    "wof:name":"Buitenschoolse Opvang Oscar",
    "wof:placetype":"venue"
},
  "geometry": {"coordinates":[5.244117,52.360348],"type":"Point"}
}