{
  "type": "Feature",
  "properties": {
    "addr:full":"Grotestraat 20 Baarlo Lb Limburg 5991 AW",
    "addr:housenumber":"20",
    "addr:postcode":"lb;5991 aw",
    "addr:street":"Grotestraat",
    "iso:country":"NL",
    "sg:address":"Grotestraat 20",
    "sg:city":"Baarlo Lb",
    "sg:classifiers":[
        {
            "category":"Fast Food",
            "type":"Food & Drink"
        }
    ],
    "sg:phone":"+31 77 477 3139",
    "sg:postcode":"5991 AW",
    "sg:province":"Limburg",
    "sg:tags":[
        "afhaal",
        "restaurant"
    ],
    "wof:name":"Cafetaria De Lekkerbek",
    "wof:placetype":"venue"
},
  "geometry": {"coordinates":[6.094444,51.331516],"type":"Point"}
}