{
  "type": "Feature",
  "properties": {
    "iso:country":"NL",
    "sg:address":"Stationsweg 11",
    "sg:city":"Gorredijk",
    "sg:orig_category":"Loodgieterswerk, Verwarming And Sanitaire Installaties",
    "sg:phone":"+31 513 463 341",
    "sg:postcode":"8401 DK",
    "sg:province":"Friesland",
    "wof:name":"G. Rienstra",
    "wof:placetype":"venue"
},
  "geometry": {"coordinates":[6.063623,53.006329],"type":"Point"}
}