{
  "type": "Feature",
  "properties": {
    "iso:country":"NL",
    "sg:address":"Boezemweg 26",
    "sg:city":"Pijnacker",
    "sg:classifiers":[
        {
            "category":"Retail",
            "subcategory":"Storage",
            "type":"Services"
        }
    ],
    "sg:phone":"+31 15 369 4170",
    "sg:postcode":"2641 KH",
    "sg:province":"Zuid-Holland",
    "sg:tags":[
        "opslag",
        "bewaring"
    ],
    "wof:name":"Sovella Nederland Bv",
    "wof:placetype":"venue"
},
  "geometry": {"coordinates":[4.4387769699,52.0250587463],"type":"Point"}
}