{
  "type": "Feature",
  "properties": {
    "addr:full":"Simmerdyk 1 Sneek Friesland 8601 ZP",
    "addr:housenumber":"1",
    "addr:postcode":"8601 zp",
    "addr:street":"Simmerdyk",
    "iso:country":"NL",
    "sg:address":"Simmerdyk 1",
    "sg:city":"Sneek",
    "sg:orig_category":"Paramedische Behandelingen",
    "sg:phone":"+31 515 428 100",
    "sg:postcode":"8601 ZP",
    "sg:province":"Friesland",
    "wof:name":"Stichting Thuiszorg Zuid-West Friesland",
    "wof:placetype":"venue"
},
  "geometry": {"coordinates":[5.643056,53.032677],"type":"Point"}
}