{
  "type": "Feature",
  "properties": {
    "addr:full":"Lloydstr 15J Rotterdam Zuid-Holland 3024 EA",
    "addr:housenumber":"15j",
    "addr:postcode":"3024 ea",
    "addr:street":"Lloydstr",
    "iso:country":"NL",
    "sg:address":"Lloydstr 15J",
    "sg:city":"Rotterdam",
    "sg:orig_category":"Video - Faciliteiten En Producties",
    "sg:phone":"+31 10 425 9616",
    "sg:postcode":"3024 EA",
    "sg:province":"Zuid-Holland",
    "sg:website":"http://www.rvmpost.com",
    "wof:name":"Rvm Bv",
    "wof:placetype":"venue"
},
  "geometry": {"coordinates":[4.459969,51.903416],"type":"Point"}
}