{
  "type": "Feature",
  "properties": {
    "addr:full":"Roerdomp 19 Eemnes Utrecht 3755 GG",
    "addr:housenumber":"19",
    "addr:postcode":"3755 gg",
    "addr:street":"Roerdomp",
    "iso:country":"NL",
    "sg:address":"Roerdomp 19",
    "sg:city":"Eemnes",
    "sg:orig_category":"Damesmodezaken",
    "sg:phone":"+31 35 531 2101",
    "sg:postcode":"3755 GG",
    "sg:province":"Utrecht",
    "wof:name":"Bon-Trio Bonneterie En Kleinconfectie",
    "wof:placetype":"venue"
},
  "geometry": {"coordinates":[5.264279,52.25853],"type":"Point"}
}