{
  "type": "Feature",
  "properties": {
    "addr:full":"G B Shawplaats 2 Rotterdam Zuid-Holland 3068 WB",
    "addr:housenumber":"2",
    "addr:postcode":"3068 wb",
    "addr:street":"Shawplaats",
    "iso:country":"NL",
    "sg:address":"G B Shawplaats 2",
    "sg:city":"Rotterdam",
    "sg:orig_category":"Bejaarden - Verzorgingstehuizen",
    "sg:phone":"+31 10 289 8100",
    "sg:postcode":"3068 WB",
    "sg:province":"Zuid-Holland",
    "wof:name":"Nijeveld",
    "wof:placetype":"venue"
},
  "geometry": {"coordinates":[4.551249,51.961491],"type":"Point"}
}