{
  "type": "Feature",
  "properties": {
    "addr:full":"Oranje Nassaustraat 11 Kaatsheuvel Noord-Brabant 5171 EB",
    "addr:housenumber":"11",
    "addr:postcode":"5171 eb",
    "addr:street":"Oranje Nassaustraat",
    "iso:country":"NL",
    "sg:address":"Oranje Nassaustraat 11",
    "sg:city":"Kaatsheuvel",
    "sg:orig_category":"Kappers",
    "sg:phone":"+31 416 272 687",
    "sg:postcode":"5171 EB",
    "sg:province":"Noord-Brabant",
    "wof:name":"Marielle Van Brouwershaven - Timmers",
    "wof:placetype":"venue"
},
  "geometry": {"coordinates":[5.028915,51.658253],"type":"Point"}
}