{
  "type": "Feature",
  "properties": {
    "addr:full":"Capittenweg 25 Blaricum Noord-Holland 1261 JK",
    "addr:housenumber":"25",
    "addr:postcode":"1261 jk",
    "addr:street":"Capittenweg",
    "iso:country":"NL",
    "sg:address":"Capittenweg 25",
    "sg:city":"Blaricum",
    "sg:orig_category":"Vertaal- And Tolkenbureaus",
    "sg:phone":"+31 35 531 8921",
    "sg:postcode":"1261 JK",
    "sg:province":"Noord-Holland",
    "wof:name":"Hilbrink Vertaalservice International",
    "wof:placetype":"venue"
},
  "geometry": {"coordinates":[5.24635,52.268707],"type":"Point"}
}