{
  "type": "Feature",
  "properties": {
    "addr:full":"Beemdstr 1 Eindhoven Noord-Brabant 5653 MA",
    "addr:housenumber":"1",
    "addr:postcode":"5653 ma",
    "addr:street":"Beemdstr",
    "iso:country":"NL",
    "sg:address":"Beemdstr 1",
    "sg:city":"Eindhoven",
    "sg:orig_category":"Adviesbureaus Bedrijfsorganisatie",
    "sg:phone":"+31 40 250 2353",
    "sg:postcode":"5653 MA",
    "sg:province":"Noord-Brabant",
    "sg:website":"http://www.kpmgconsulting.nl/fpiqm",
    "wof:name":"Kpmg Frits Philips Inst",
    "wof:placetype":"venue"
},
  "geometry": {"coordinates":[5.452792,51.430859],"type":"Point"}
}