{
  "type": "Feature",
  "properties": {
    "addr:full":"Willeskop 57 Montfoort Utrecht 3417 MB",
    "addr:housenumber":"57",
    "addr:postcode":"3417 mb",
    "addr:street":"Willeskop",
    "iso:country":"NL",
    "sg:address":"Willeskop 57",
    "sg:city":"Montfoort",
    "sg:orig_category":"Verzekeringen",
    "sg:phone":"+31 348 472 745",
    "sg:postcode":"3417 MB",
    "sg:province":"Utrecht",
    "wof:name":"Ond. Brandwaarborg Mij Montfoort En Omstr.Ua",
    "wof:placetype":"venue"
},
  "geometry": {"coordinates":[4.945842,52.042816],"type":"Point"}
}