{
  "type": "Feature",
  "properties": {
    "addr:full":"Dykstr 33 Zwolle NL.08 8011 XS",
    "addr:housenumber":"33",
    "addr:postcode":"8011 xs",
    "addr:street":"Dykstr",
    "iso:country":"NL",
    "sg:address":"Dykstr 33",
    "sg:city":"Zwolle",
    "sg:orig_category":"Juridische Adviseurs",
    "sg:phone":"+31 38 423 1637",
    "sg:postcode":"8011 XS",
    "sg:province":"NL.08",
    "wof:name":"Molen, Mr S Van Der",
    "wof:placetype":"venue"
},
  "geometry": {"coordinates":[6.088738,52.512566],"type":"Point"}
}