{
  "type": "Feature",
  "properties": {
    "addr:full":"Saarskampen 15 Wamel Gelderland 6659 CS",
    "addr:housenumber":"15",
    "addr:postcode":"6659 cs",
    "addr:street":"Saarskampen;Gelderland",
    "iso:country":"NL",
    "sg:address":"Saarskampen 15",
    "sg:city":"Wamel",
    "sg:orig_category":"Loodgieterswerk, Verwarming And Sanitaire Installaties",
    "sg:phone":"+31 487 501 917",
    "sg:postcode":"6659 CS",
    "sg:province":"Gelderland",
    "wof:name":"S.P. Dirks",
    "wof:placetype":"venue"
},
  "geometry": {"coordinates":[5.457718,51.877502],"type":"Point"}
}