{
  "type": "Feature",
  "properties": {
    "addr:full":"Overslagweg 1 Delfgauw Zuid-Holland 2645 EK",
    "addr:housenumber":"1",
    "addr:postcode":"2645 ek",
    "addr:street":"Overslagweg",
    "iso:country":"NL",
    "sg:address":"Overslagweg 1",
    "sg:city":"Delfgauw",
    "sg:orig_category":"Wijnkoperijen En -Groothandel",
    "sg:phone":"+31 15 380 5034",
    "sg:postcode":"2645 EK",
    "sg:province":"Zuid-Holland",
    "sg:website":"http://www.wijnkoperijdegeus.nl",
    "wof:name":"Geus Wijnkoperij, R M De",
    "wof:placetype":"venue"
},
  "geometry": {"coordinates":[4.4033441544,51.9956741333],"type":"Point"}
}