{
  "type": "Feature",
  "properties": {
    "addr:full":"Rolweg 29 Culemborg Gelderland 4104 AV",
    "addr:housenumber":"29",
    "addr:postcode":"4104 av",
    "addr:street":"Rolweg;Gelderland",
    "iso:country":"NL",
    "sg:address":"Rolweg 29",
    "sg:city":"Culemborg",
    "sg:orig_category":"Bloemen And Planten Gh",
    "sg:phone":"+31 345 516 464",
    "sg:postcode":"4104 AV",
    "sg:province":"Gelderland",
    "wof:name":"Jiffy Products Nederland Bv",
    "wof:placetype":"venue"
},
  "geometry": {"coordinates":[5.217988,51.938755],"type":"Point"}
}