{
  "type": "Feature",
  "properties": {
    "iso:country":"NL",
    "sg:address":"Hoogravenseweg 98",
    "sg:city":"Utrecht",
    "sg:orig_category":"Meubelzaken, Woning- And Keukeninrichting",
    "sg:phone":"+31 30 288 4759",
    "sg:postcode":"3523 TP",
    "sg:province":"Utrecht",
    "wof:name":"Woninginrichting Van Der Hijden",
    "wof:placetype":"venue"
},
  "geometry": {"coordinates":[5.120437,52.071804],"type":"Point"}
}