{
  "type": "Feature",
  "properties": {
    "addr:full":"J Steenstr 1A Schiedam South Holland 3117 TB",
    "addr:housenumber":"1a",
    "addr:postcode":"3117 tb",
    "iso:country":"NL",
    "sg:address":"J Steenstr 1A",
    "sg:city":"Schiedam",
    "sg:classifiers":[
        {
            "category":"Food & Beverages",
            "subcategory":"Bakery",
            "type":"Retail Goods"
        }
    ],
    "sg:phone":"+31 10 426 5180",
    "sg:postcode":"3117 TB",
    "sg:province":"South Holland",
    "sg:tags":[
        "brood",
        "en",
        "banket"
    ],
    "wof:name":"Wakkere Bakker, De",
    "wof:placetype":"venue"
},
  "geometry": {"coordinates":[4.383407,51.91198],"type":"Point"}
}