{
  "type": "Feature",
  "properties": {
    "iso:country":"NL",
    "sg:address":"Visseringweg 2",
    "sg:city":"Diemen",
    "sg:orig_category":"Mobiele Service Aan Motorvoertuigen",
    "sg:phone":"+31 20 695 0088",
    "sg:postcode":"1112 AS",
    "sg:province":"North Holland",
    "wof:name":"Firma Bergingsbedrijf Kloek Vof",
    "wof:placetype":"venue"
},
  "geometry": {"coordinates":[4.96498,52.333656],"type":"Point"}
}