{
  "type": "Feature",
  "properties": {
    "addr:full":"Leeghwaterstr 43 Kudelstaart North Holland 1433 BK",
    "addr:housenumber":"43",
    "addr:postcode":"1433 bk",
    "addr:street":"Leeghwaterstr",
    "iso:country":"NL",
    "sg:address":"Leeghwaterstr 43",
    "sg:city":"Kudelstaart",
    "sg:orig_category":"Onderhoudswerken",
    "sg:phone":"+31 297 328 903",
    "sg:postcode":"1433 BK",
    "sg:province":"North Holland",
    "wof:name":"Janmaat",
    "wof:placetype":"venue"
},
  "geometry": {"coordinates":[4.759858,52.236156],"type":"Point"}
}