{
  "type": "Feature",
  "properties": {
    "addr:full":"Meeuwenln 7 Lisse Zuid-Holland 2162 HD",
    "addr:housenumber":"7",
    "addr:postcode":"2162 hd",
    "addr:street":"Meeuwenln",
    "iso:country":"NL",
    "sg:address":"Meeuwenln 7",
    "sg:city":"Lisse",
    "sg:orig_category":"Parketvloeren",
    "sg:phone":"+31 252 421 570",
    "sg:postcode":"2162 HD",
    "sg:province":"Zuid-Holland",
    "wof:name":"Fn Lisse",
    "wof:placetype":"venue"
},
  "geometry": {"coordinates":[4.559657,52.251949],"type":"Point"}
}