{
  "type": "Feature",
  "properties": {
    "iso:country":"NL",
    "sg:address":"Oosterhoutstr 30",
    "sg:city":"Assen",
    "sg:orig_category":"Verzekeringen - Verzekeringskantoren",
    "sg:phone":"+31 592 300 487",
    "sg:postcode":"9401 NE",
    "sg:province":"Drenthe",
    "sg:website":"http://www.hdbassen.nl",
    "wof:name":"Hdb Assen Uitvaartverzekering",
    "wof:placetype":"venue"
},
  "geometry": {"coordinates":[6.564175,52.990932],"type":"Point"}
}