{
  "type": "Feature",
  "properties": {
    "addr:full":"Karrewg N 14 Kessel Lb Limburg 5995 ME",
    "addr:postcode":"lb;5995 me",
    "addr:street":"N 14",
    "iso:country":"NL",
    "sg:address":"Karrewg N 14",
    "sg:city":"Kessel Lb",
    "sg:orig_category":"Oldtimers",
    "sg:phone":"+31 77 462 2750",
    "sg:postcode":"5995 ME",
    "sg:province":"Limburg",
    "wof:name":"Deursen, Pedro Van",
    "wof:placetype":"venue"
},
  "geometry": {"coordinates":[6.04894,51.291866],"type":"Point"}
}