{
  "type": "Feature",
  "properties": {
    "addr:full":"Haarlemmerdijk 1 Amsterdam Noord-Holland 1013 JZ",
    "addr:housenumber":"1",
    "addr:postcode":"1013 jz",
    "addr:street":"Haarlemmerdijk",
    "iso:country":"NL",
    "sg:address":"Haarlemmerdijk 1",
    "sg:city":"Amsterdam",
    "sg:orig_category":"Zuivelproducten",
    "sg:phone":"+31 20 625 7945",
    "sg:postcode":"1013 JZ",
    "sg:province":"Noord-Holland",
    "wof:name":"Kaasland Haarlemmerdijk",
    "wof:placetype":"venue"
},
  "geometry": {"coordinates":[4.888979,52.381588],"type":"Point"}
}