{
  "type": "Feature",
  "properties": {
    "addr:full":"Rusthofstr 78 Rotterdam South Holland 3034 TS",
    "addr:housenumber":"78",
    "addr:postcode":"3034 ts",
    "addr:street":"Rusthofstr",
    "iso:country":"NL",
    "sg:address":"Rusthofstr 78",
    "sg:city":"Rotterdam",
    "sg:orig_category":"Loonbedrijven",
    "sg:phone":"+31 6 20352822",
    "sg:postcode":"3034 TS",
    "sg:province":"South Holland",
    "wof:name":"Ram Vof, Loonbedrijf",
    "wof:placetype":"venue"
},
  "geometry": {"coordinates":[4.493317,51.936165],"type":"Point"}
}