{
  "type": "Feature",
  "properties": {
    "addr:full":"Brummelkant 4 Stadskanaal Groningen 9502 BB",
    "addr:housenumber":"4",
    "addr:postcode":"9502 bb",
    "addr:street":"Brummelkant",
    "iso:country":"NL",
    "sg:address":"Brummelkant 4",
    "sg:city":"Stadskanaal",
    "sg:orig_category":"Loopbaanbegeleiding",
    "sg:phone":"+31 599 651 424",
    "sg:postcode":"9502 BB",
    "sg:province":"Groningen",
    "sg:website":"http://www.stichtingbaanderij.nl",
    "wof:name":"Baanderij, Stichting",
    "wof:placetype":"venue"
},
  "geometry": {"coordinates":[6.960461,52.996246],"type":"Point"}
}