{
  "type": "Feature",
  "properties": {
    "addr:full":"Koninginnewg 44 Elst Ut Utrecht 3921 CV",
    "addr:housenumber":"44",
    "addr:postcode":"ut;3921 cv",
    "addr:street":"Koninginnewg",
    "iso:country":"NL",
    "sg:address":"Koninginnewg 44",
    "sg:city":"Elst Ut",
    "sg:orig_category":"Metselwerken",
    "sg:phone":"+31 6 20245818",
    "sg:postcode":"3921 CV",
    "sg:province":"Utrecht",
    "wof:name":"Ommeren, A Van",
    "wof:placetype":"venue"
},
  "geometry": {"coordinates":[5.505504,51.985577],"type":"Point"}
}