{
  "type": "Feature",
  "properties": {
    "iso:country":"NL",
    "sg:address":"Brink 32A",
    "sg:city":"Laren Nh",
    "sg:orig_category":"Juweliers",
    "sg:phone":"+31 36 538 9550",
    "sg:postcode":"1251 KW",
    "sg:province":"North Holland",
    "wof:name":"Ren? Kahl?",
    "wof:placetype":"venue"
},
  "geometry": {"coordinates":[5.226221,52.255611],"type":"Point"}
}