{
  "type": "Feature",
  "properties": {
    "iso:country":"NL",
    "sg:address":"Romerkerkwg 125",
    "sg:city":"Beverwyk",
    "sg:orig_category":"Autoreclame",
    "sg:phone":"+31 251 220 374",
    "sg:postcode":"1943 EX",
    "sg:province":"North Holland",
    "wof:name":"Sticky Colors",
    "wof:placetype":"venue"
},
  "geometry": {"coordinates":[4.648648,52.484962],"type":"Point"}
}