{
  "type": "Feature",
  "properties": {
    "addr:full":"Van Ruysdaellaan 46 Leidschendam Zuid-Holland 2264 TL",
    "addr:housenumber":"46",
    "addr:postcode":"2264 tl",
    "addr:street":"Van Ruysdaellaan",
    "iso:country":"NL",
    "sg:address":"Van Ruysdaellaan 46",
    "sg:city":"Leidschendam",
    "sg:orig_category":"Medische Apparatuur And Prothesen Fab",
    "sg:phone":"+31 70 320 1124",
    "sg:postcode":"2264 TL",
    "sg:province":"Zuid-Holland",
    "wof:name":"Wareman Metaal Keramiek",
    "wof:placetype":"venue"
},
  "geometry": {"coordinates":[4.390261,52.088089],"type":"Point"}
}