{
  "type": "Feature",
  "properties": {
    "iso:country":"NL",
    "sg:address":"Brink 30",
    "sg:city":"Amsterdam",
    "sg:classifiers":[
        {
            "category":"Food & Beverages",
            "subcategory":"Fruits & Vegetables",
            "type":"Retail Goods"
        }
    ],
    "sg:phone":"+31 20 665 4542",
    "sg:postcode":"1097 TW",
    "sg:province":"North Holland",
    "sg:tags":[
        "groenten"
    ],
    "sg:website":"http://www.etrade.nl/vanderkolkgroenten",
    "wof:name":"Van Der Kolk",
    "wof:placetype":"venue"
},
  "geometry": {"coordinates":[4.942849,52.340107],"type":"Point"}
}