{
  "type": "Feature",
  "properties": {
    "addr:full":"Rijkesluisstraat 52 Oirschot Noord-Brabant 5688 ED",
    "addr:housenumber":"52",
    "addr:postcode":"5688 ed",
    "addr:street":"Rijkesluisstraat",
    "iso:country":"NL",
    "sg:address":"Rijkesluisstraat 52",
    "sg:city":"Oirschot",
    "sg:orig_category":"Meubelzaken, Woning- And Keukeninrichting",
    "sg:phone":"+31 499 572 139",
    "sg:postcode":"5688 ED",
    "sg:province":"Noord-Brabant",
    "wof:name":"Meubelstyling Oirschot Bv",
    "wof:placetype":"venue"
},
  "geometry": {"coordinates":[5.313294,51.503555],"type":"Point"}
}