{
  "type": "Feature",
  "properties": {
    "addr:full":"Hoogty 191 Noordwyk Zh Zuid-Holland 2201 VX",
    "addr:housenumber":"191",
    "addr:postcode":"2201 vx",
    "addr:street":"Noordwyk",
    "iso:country":"NL",
    "sg:address":"Hoogty 191",
    "sg:city":"Noordwyk Zh",
    "sg:orig_category":"Verenigingen En Stichtingen",
    "sg:phone":"+31 71 361 7417",
    "sg:postcode":"2201 VX",
    "sg:province":"Zuid-Holland",
    "wof:name":"Theosophical Society, The",
    "wof:placetype":"venue"
},
  "geometry": {"coordinates":[4.447704,52.234268],"type":"Point"}
}