{
  "type": "Feature",
  "properties": {
    "addr:full":"Yzerhof 19 Amsterdam Noord-Holland 1066 WN",
    "addr:housenumber":"19",
    "addr:postcode":"1066 wn",
    "addr:street":"Yzerhof",
    "iso:country":"NL",
    "sg:address":"Yzerhof 19",
    "sg:city":"Amsterdam",
    "sg:orig_category":"Autorijscholen",
    "sg:phone":"+31 20 617 1737",
    "sg:postcode":"1066 WN",
    "sg:province":"Noord-Holland",
    "wof:name":"Lucardie",
    "wof:placetype":"venue"
},
  "geometry": {"coordinates":[4.806061,52.343826],"type":"Point"}
}