{
  "type": "Feature",
  "properties": {
    "iso:country":"NL",
    "sg:address":"V Loghemstr 54",
    "sg:city":"Groningen",
    "sg:orig_category":"Adviesbureaus Bedrijfsorganisatie",
    "sg:phone":"+31 50 541 9602",
    "sg:postcode":"9731 MC",
    "sg:province":"Groningen",
    "wof:name":"Corbijn Van Willenswaard Bv, G C",
    "wof:placetype":"venue"
},
  "geometry": {"coordinates":[6.5966,53.235031],"type":"Point"}
}