{
  "type": "Feature",
  "properties": {
    "addr:full":"Dennenln 48 Fil Zwanenburg Noord-Holland 1161 CS",
    "addr:housenumber":"48",
    "addr:postcode":"1161 cs",
    "addr:street":"Dennenln",
    "iso:country":"NL",
    "sg:address":"Dennenln 48 Fil",
    "sg:city":"Zwanenburg",
    "sg:orig_category":"Kaas",
    "sg:phone":"+31 20 497 2338",
    "sg:postcode":"1161 CS",
    "sg:province":"Noord-Holland",
    "wof:name":"Osdorper, De",
    "wof:placetype":"venue"
},
  "geometry": {"coordinates":[4.7472300529,52.376625061],"type":"Point"}
}