{
  "type": "Feature",
  "properties": {
    "iso:country":"NL",
    "sg:address":"Vd Muyssenbergstr 36",
    "sg:city":"Hoofdplaat",
    "sg:orig_category":"Voetbalverenigingen",
    "sg:phone":"+31 117 348 632",
    "sg:postcode":"4513 AV",
    "sg:province":"Zeeland",
    "wof:name":"Hoofdplaat",
    "wof:placetype":"venue"
},
  "geometry": {"coordinates":[3.658048,51.367332],"type":"Point"}
}