{
  "type": "Feature",
  "properties": {
    "iso:country":"NL",
    "sg:address":"Doormanln 6",
    "sg:city":"Wassenaar",
    "sg:orig_category":"Boekbinderijen",
    "sg:phone":"+31 70 511 1718",
    "sg:postcode":"2243 AL",
    "sg:province":"Zuid-Holland",
    "wof:name":"Son",
    "wof:placetype":"venue"
},
  "geometry": {"coordinates":[4.393863,52.14307],"type":"Point"}
}