{
  "type": "Feature",
  "properties": {
    "iso:country":"NL",
    "sg:address":"Batjanstr 84",
    "sg:city":"Amsterdam",
    "sg:orig_category":"Scholen Voor Basisonderwijs",
    "sg:phone":"+31 20 463 8900",
    "sg:postcode":"1094 RC",
    "sg:province":"North Holland",
    "wof:name":"Faroeq-Omar, El",
    "wof:placetype":"venue"
},
  "geometry": {"coordinates":[4.938667,52.359303],"type":"Point"}
}