{
  "type": "Feature",
  "properties": {
    "addr:full":"Jan Teulingslaan 9 Amstelveen North Holland 1187 SG",
    "addr:housenumber":"9",
    "addr:postcode":"1187 sg",
    "addr:street":"Jan Teulingslaan",
    "iso:country":"NL",
    "sg:address":"Jan Teulingslaan 9",
    "sg:city":"Amstelveen",
    "sg:orig_category":"Bedrijfs- And Managementsconsultants",
    "sg:phone":"+31 20 645 5433",
    "sg:postcode":"1187 SG",
    "sg:province":"North Holland",
    "wof:name":"Think Fbs Origin",
    "wof:placetype":"venue"
},
  "geometry": {"coordinates":[4.831622,52.280521],"type":"Point"}
}