{
  "type": "Feature",
  "properties": {
    "iso:country":"NL",
    "sg:address":"Bokkedk 2",
    "sg:city":"Renkum",
    "sg:orig_category":"Waterschappen",
    "sg:phone":"+31 317 315 875",
    "sg:postcode":"6871 CJ",
    "sg:province":"Gelderland",
    "wof:name":"Rioolwaterzuivering Renkum",
    "wof:placetype":"venue"
},
  "geometry": {"coordinates":[5.719783783,51.9681053162],"type":"Point"}
}