{
  "type": "Feature",
  "properties": {
    "addr:full":"Warande 105 Marknesse Flevoland 8316 CN",
    "addr:housenumber":"105",
    "addr:postcode":"8316 cn",
    "addr:street":"Warande;Flevoland",
    "iso:country":"NL",
    "sg:address":"Warande 105",
    "sg:city":"Marknesse",
    "sg:orig_category":"Adviesbureaus Bedrijfsorganisatie",
    "sg:phone":"+31 527 203 919",
    "sg:postcode":"8316 CN",
    "sg:province":"Flevoland",
    "wof:name":"Fleco",
    "wof:placetype":"venue"
},
  "geometry": {"coordinates":[5.8648,52.71262],"type":"Point"}
}