{
  "type": "Feature",
  "properties": {
    "addr:full":"2E Lindendwstr 19 Amsterdam Noord-Holland 1015 LH",
    "addr:housenumber":"19",
    "addr:postcode":"1015 lh",
    "addr:street":"2E Lindendwstr",
    "iso:country":"NL",
    "sg:address":"2E Lindendwstr 19",
    "sg:city":"Amsterdam",
    "sg:orig_category":"Adviesbureaus",
    "sg:phone":"+31 20 770 2628",
    "sg:postcode":"1015 LH",
    "sg:province":"Noord-Holland",
    "wof:name":"Doruff, Sher",
    "wof:placetype":"venue"
},
  "geometry": {"coordinates":[4.882938,52.379391],"type":"Point"}
}