{
  "type": "Feature",
  "properties": {
    "addr:full":"Wijkermeerstraat 46 Hoofddorp Noord-Holland 2131 HA",
    "addr:housenumber":"46",
    "addr:postcode":"2131 ha",
    "addr:street":"Wijkermeerstraat",
    "iso:country":"NL",
    "sg:address":"Wijkermeerstraat 46",
    "sg:city":"Hoofddorp",
    "sg:orig_category":"Wegen And Sportterreinen",
    "sg:phone":"+31 23 561 3660",
    "sg:postcode":"2131 HA",
    "sg:province":"Noord-Holland",
    "wof:name":"Aannemersbedrijf Ketting Bv",
    "wof:placetype":"venue"
},
  "geometry": {"coordinates":[4.6955428123,52.3127937317],"type":"Point"}
}