{
  "type": "Feature",
  "properties": {
    "addr:full":"Groenlandsekd 23 Vinkeveen Utrecht 3645 BA",
    "addr:housenumber":"23",
    "addr:postcode":"3645 ba",
    "addr:street":"Groenlandsekd",
    "iso:country":"NL",
    "sg:address":"Groenlandsekd 23",
    "sg:city":"Vinkeveen",
    "sg:orig_category":"Projectinrichting",
    "sg:phone":"+31 6 53178231",
    "sg:postcode":"3645 BA",
    "sg:province":"Utrecht",
    "wof:name":"Platerink, E",
    "wof:placetype":"venue"
},
  "geometry": {"coordinates":[4.979937,52.226955],"type":"Point"}
}