{
  "type": "Feature",
  "properties": {
    "addr:full":"Slachterystr 5 Weert Limburg 6001 HP",
    "addr:housenumber":"5",
    "addr:postcode":"6001 hp",
    "addr:street":"Slachterystr",
    "iso:country":"NL",
    "sg:address":"Slachterystr 5",
    "sg:city":"Weert",
    "sg:classifiers":[
        {
            "category":"Retail",
            "subcategory":"Auto Repair",
            "type":"Services"
        }
    ],
    "sg:phone":"+31 495 536 728",
    "sg:postcode":"6001 HP",
    "sg:province":"Limburg",
    "sg:tags":[
        "garage"
    ],
    "wof:name":"Kruijs, Harrie Van De",
    "wof:placetype":"venue"
},
  "geometry": {"coordinates":[5.69572,51.249962],"type":"Point"}
}