{
  "type": "Feature",
  "properties": {
    "addr:full":"Libiestr 8 Delft Zuid-Holland 2622 CB",
    "addr:housenumber":"8",
    "addr:postcode":"2622 cb",
    "addr:street":"Libiestr",
    "iso:country":"NL",
    "sg:address":"Libiestr 8",
    "sg:city":"Delft",
    "sg:orig_category":"Administratie- En Boekhoudkantoren",
    "sg:phone":"+31 15 261 3738",
    "sg:postcode":"2622 CB",
    "sg:province":"Zuid-Holland",
    "wof:name":"M & A",
    "wof:placetype":"venue"
},
  "geometry": {"coordinates":[4.345397,51.983185],"type":"Point"}
}