{
  "type": "Feature",
  "properties": {
    "addr:full":"Herenweg 34 Oosterzee Friesland 8536 TN",
    "addr:housenumber":"34",
    "addr:postcode":"8536",
    "addr:street":"Herenweg",
    "iso:country":"NL",
    "sg:address":"Herenweg 34",
    "sg:city":"Oosterzee",
    "sg:orig_category":"Bloemen And Planten",
    "sg:phone":"+31 514 541 433",
    "sg:postcode":"8536 TN",
    "sg:province":"Friesland",
    "wof:name":"De Biedermeier",
    "wof:placetype":"venue"
},
  "geometry": {"coordinates":[-85.978554,35.83062],"type":"Point"}
}