{
  "type": "Feature",
  "properties": {
    "addr:full":"A Banckertstr 9 Geldrop Noord-Brabant 5666 GG",
    "addr:housenumber":"9",
    "addr:postcode":"5666 gg",
    "iso:country":"NL",
    "sg:address":"A Banckertstr 9",
    "sg:city":"Geldrop",
    "sg:orig_category":"Kinderkleding",
    "sg:phone":"+31 40 286 0356",
    "sg:postcode":"5666 GG",
    "sg:province":"Noord-Brabant",
    "wof:name":"Boomhut, De",
    "wof:placetype":"venue"
},
  "geometry": {"coordinates":[5.574941,51.423737],"type":"Point"}
}