{
  "type": "Feature",
  "properties": {
    "addr:full":"Kerkebuurt 166 Berkhout Noord-Holland 1647 ME",
    "addr:housenumber":"166",
    "addr:postcode":"1647 me",
    "addr:street":"Kerkebuurt",
    "iso:country":"NL",
    "sg:address":"Kerkebuurt 166",
    "sg:city":"Berkhout",
    "sg:orig_category":"Artsen - Huisartsen",
    "sg:phone":"+31 229 551 264",
    "sg:postcode":"1647 ME",
    "sg:province":"Noord-Holland",
    "wof:name":"Sturris En H A Bergmeijer, J",
    "wof:placetype":"venue"
},
  "geometry": {"coordinates":[5.00145,52.653267],"type":"Point"}
}