{
  "type": "Feature",
  "properties": {
    "iso:country":"NL",
    "sg:address":"Poststraat 38",
    "sg:city":"Assen",
    "sg:orig_category":"Autokeuringen",
    "sg:phone":"+31 592 312 096",
    "sg:postcode":"9401 BT",
    "sg:province":"Provincie Drenthe",
    "wof:name":"Van 'T Spijker Autoservice",
    "wof:placetype":"venue"
},
  "geometry": {"coordinates":[6.565445,52.997013],"type":"Point"}
}