{
  "type": "Feature",
  "properties": {
    "iso:country":"NL",
    "sg:address":"Weversbaan 11A",
    "sg:city":"Leiderdorp",
    "sg:orig_category":"Adviesbureaus Bouwkunde",
    "sg:phone":"+31 71 589 9858",
    "sg:postcode":"2352 BZ",
    "sg:province":"Zuid-Holland",
    "wof:name":"Bewag",
    "wof:placetype":"venue"
},
  "geometry": {"coordinates":[4.521512,52.163059],"type":"Point"}
}