{
  "type": "Feature",
  "properties": {
    "addr:full":"Geerseswg 6 Middelburg Zeeland 4332 RA",
    "addr:housenumber":"6",
    "addr:postcode":"4332 ra",
    "addr:street":"Geerseswg",
    "iso:country":"NL",
    "sg:address":"Geerseswg 6",
    "sg:city":"Middelburg",
    "sg:classifiers":[
        {
            "category":"Shopping",
            "subcategory":"Gifts & Souvenirs",
            "type":"Retail Goods"
        }
    ],
    "sg:phone":"+31 118 635 011",
    "sg:postcode":"4332 RA",
    "sg:province":"Zeeland",
    "sg:tags":[
        "wens-",
        "en",
        "prentbriefkaarten"
    ],
    "wof:name":"Zeeuwsche Kaartenhdl, De",
    "wof:placetype":"venue"
},
  "geometry": {"coordinates":[3.6272010803,51.5123634338],"type":"Point"}
}