{
  "type": "Feature",
  "properties": {
    "addr:full":"Bilderdykkd 17 Amsterdam Noord-Holland 1053 VB",
    "addr:housenumber":"17",
    "addr:postcode":"1053 vb",
    "addr:street":"Bilderdykkd",
    "iso:country":"NL",
    "sg:address":"Bilderdykkd 17",
    "sg:city":"Amsterdam",
    "sg:orig_category":"Poliklinieken",
    "sg:phone":"+31 20 616 5446",
    "sg:postcode":"1053 VB",
    "sg:province":"Noord-Holland",
    "wof:name":"Bilderdijkkade",
    "wof:placetype":"venue"
},
  "geometry": {"coordinates":[4.86733,52.366638],"type":"Point"}
}