{
  "type": "Feature",
  "properties": {
    "addr:full":"Achterweg 69 Heusden Gem Heusden Noord-Brabant 5256 NL",
    "addr:housenumber":"69",
    "addr:postcode":"5256 nl",
    "addr:street":"Achterweg",
    "iso:country":"NL",
    "sg:address":"Achterweg 69",
    "sg:city":"Heusden Gem Heusden",
    "sg:orig_category":"Goederenvervoer Over De Weg",
    "sg:phone":"+31 416 661 470",
    "sg:postcode":"5256 NL",
    "sg:province":"Noord-Brabant",
    "wof:name":"Jac. Schreuders Transport Bv",
    "wof:placetype":"venue"
},
  "geometry": {"coordinates":[5.13727,51.733074],"type":"Point"}
}