{
  "type": "Feature",
  "properties": {
    "addr:full":"Canadezenln 7 Leeuwarden Provincie Friesland 8923 AA",
    "addr:housenumber":"7",
    "addr:postcode":"8923 aa",
    "addr:street":"Canadezenln;Provincie Friesland",
    "iso:country":"NL",
    "sg:address":"Canadezenln 7",
    "sg:city":"Leeuwarden",
    "sg:orig_category":"Verenigingsgebouwen",
    "sg:phone":"+31 58 266 4937",
    "sg:postcode":"8923 AA",
    "sg:province":"Provincie Friesland",
    "wof:name":"Blokkendoos, Wijkgebouw De",
    "wof:placetype":"venue"
},
  "geometry": {"coordinates":[5.820156,53.215782],"type":"Point"}
}