{
  "type": "Feature",
  "properties": {
    "addr:full":"Muurhuizen 23 Amersfoort Utrecht 3811 EC",
    "addr:housenumber":"23",
    "addr:postcode":"3811 ec",
    "addr:street":"Muurhuizen",
    "iso:country":"NL",
    "sg:address":"Muurhuizen 23",
    "sg:city":"Amersfoort",
    "sg:orig_category":"Meubelstoffering",
    "sg:phone":"+31 33 465 3133",
    "sg:postcode":"3811 EC",
    "sg:province":"Utrecht",
    "wof:name":"Firooze De Lange",
    "wof:placetype":"venue"
},
  "geometry": {"coordinates":[5.391343,52.1544],"type":"Point"}
}