{
  "type": "Feature",
  "properties": {
    "addr:full":"Kievitlaan 6 Ijmuiden Noord-Holland 1971 KX",
    "addr:housenumber":"6",
    "addr:postcode":"1971 kx",
    "addr:street":"Kievitlaan",
    "iso:country":"NL",
    "sg:address":"Kievitlaan 6",
    "sg:city":"Ijmuiden",
    "sg:orig_category":"Kappers",
    "sg:phone":"+31 255 513 623",
    "sg:postcode":"1971 KX",
    "sg:province":"Noord-Holland",
    "wof:name":"Van Westerop-Nooy",
    "wof:placetype":"venue"
},
  "geometry": {"coordinates":[4.631505,52.451916],"type":"Point"}
}