{
  "type": "Feature",
  "properties": {
    "addr:full":"Badhuisweg 91 'S Gravenhage Zuid-Holland 2587 CE",
    "addr:housenumber":"91",
    "addr:postcode":"2587 ce",
    "addr:street":"Badhuisweg;' S",
    "iso:country":"NL",
    "sg:address":"Badhuisweg 91",
    "sg:city":"'S Gravenhage",
    "sg:orig_category":"Public Relationbureaus",
    "sg:phone":"+31 70 352 8528",
    "sg:postcode":"2587 CE",
    "sg:province":"Zuid-Holland",
    "wof:name":"Stichting Maatschappij En Onderneming",
    "wof:placetype":"venue"
},
  "geometry": {"coordinates":[4.290425,52.108051],"type":"Point"}
}