{
  "type": "Feature",
  "properties": {
    "iso:country":"NL",
    "sg:address":"Govert Flinckstraat 171",
    "sg:city":"Amsterdam",
    "sg:orig_category":"Kinderopvang Behalve Thuis",
    "sg:phone":"+31 20 676 8432",
    "sg:postcode":"1073 BT",
    "sg:province":"Noord-Holland",
    "wof:name":"De Boefjes Kinderdagverblijf",
    "wof:placetype":"venue"
},
  "geometry": {"coordinates":[4.89454,52.355431],"type":"Point"}
}