{
  "type": "Feature",
  "properties": {
    "iso:country":"NL",
    "sg:address":"Sint Catharinaplantsoen 4",
    "sg:city":"Grevenbicht",
    "sg:classifiers":[
        {
            "category":"Education",
            "subcategory":"Preschool",
            "type":"Public Place"
        }
    ],
    "sg:phone":"+31 46 485 7261",
    "sg:postcode":"6127 BC",
    "sg:province":"BE.05",
    "sg:tags":[
        "kleuteronderwijs",
        "basis-"
    ],
    "wof:name":"Basisschool Pastoor Franck",
    "wof:placetype":"venue"
},
  "geometry": {"coordinates":[5.775667,51.040249],"type":"Point"}
}