{
  "type": "Feature",
  "properties": {
    "iso:country":"NL",
    "sg:address":"Pastorieweg 10",
    "sg:city":"Gelselaar",
    "sg:classifiers":[
        {
            "category":"Education",
            "subcategory":"Preschool",
            "type":"Public Place"
        }
    ],
    "sg:phone":"+31 545 481 647",
    "sg:postcode":"7275 AH",
    "sg:province":"Gelderland",
    "sg:tags":[
        "kleuteronderwijs",
        "basis-"
    ],
    "wof:name":"Nijntje Pluis",
    "wof:placetype":"venue"
},
  "geometry": {"coordinates":[6.525616,52.168591],"type":"Point"}
}