{
  "type": "Feature",
  "properties": {
    "addr:full":"Vismarkt 26 Den Helder North Holland 1781 TA",
    "addr:housenumber":"26",
    "addr:postcode":"1781 ta",
    "addr:street":"Vismarkt",
    "iso:country":"NL",
    "sg:address":"Vismarkt 26",
    "sg:city":"Den Helder",
    "sg:orig_category":"Hout Gh",
    "sg:phone":"+31 223 612 541",
    "sg:postcode":"1781 TA",
    "sg:province":"North Holland",
    "wof:name":"De Houthal",
    "wof:placetype":"venue"
},
  "geometry": {"coordinates":[4.770135,52.956074],"type":"Point"}
}