{
  "type": "Feature",
  "properties": {
    "iso:country":"NL",
    "sg:address":"Reiger 51",
    "sg:city":"Sprang-Capelle",
    "sg:orig_category":"Boekhouders",
    "sg:phone":"+31 416 279 270",
    "sg:postcode":"5161 TX",
    "sg:province":"North Brabant",
    "wof:name":"C. De Reus",
    "wof:placetype":"venue"
},
  "geometry": {"coordinates":[5.019924,51.67823],"type":"Point"}
}