{
  "type": "Feature",
  "properties": {
    "iso:country":"NL",
    "sg:address":"Keizerwg 40",
    "sg:city":"Enschede",
    "sg:orig_category":"Banken",
    "sg:phone":"+31 53 428 2909",
    "sg:postcode":"7548 PX",
    "sg:province":"NL.08",
    "wof:name":"Regio Bank",
    "wof:placetype":"venue"
},
  "geometry": {"coordinates":[6.781364,52.211658],"type":"Point"}
}