{
  "type": "Feature",
  "properties": {
    "iso:country":"NL",
    "sg:address":"Jagerln 35",
    "sg:city":"Zeist",
    "sg:orig_category":"Kopieerservice",
    "sg:phone":"+31 30 692 4350",
    "sg:postcode":"3701 XH",
    "sg:province":"Utrecht",
    "sg:website":"http://www.tempofix.nl",
    "wof:name":"Tempofix",
    "wof:placetype":"venue"
},
  "geometry": {"coordinates":[5.24387,52.08548],"type":"Point"}
}