{
  "type": "Feature",
  "properties": {
    "addr:full":"Achteres 8C Den Ham Ov NL.08 7683 SW",
    "addr:housenumber":"8c;7683",
    "addr:street":"Achteres;Ov;Sw",
    "iso:country":"NL",
    "sg:address":"Achteres 8C",
    "sg:city":"Den Ham Ov",
    "sg:orig_category":"Meubelmakerijen",
    "sg:phone":"+31 546 671 812",
    "sg:postcode":"7683 SW",
    "sg:province":"NL.08",
    "wof:name":"Valk",
    "wof:placetype":"venue"
},
  "geometry": {"coordinates":[6.496274,52.462387],"type":"Point"}
}