{
  "type": "Feature",
  "properties": {
    "addr:full":"De Stroet 11-13 Lunteren Gelderland 6741 PT",
    "addr:housenumber":"11-13",
    "addr:postcode":"6741",
    "addr:street":"De Stroet;Gelderland;Pt",
    "iso:country":"NL",
    "sg:address":"De Stroet 11-13",
    "sg:city":"Lunteren",
    "sg:classifiers":[
        {
            "category":"Retail",
            "subcategory":"Storage",
            "type":"Services"
        }
    ],
    "sg:phone":"+31 318 485 494",
    "sg:postcode":"6741 PT",
    "sg:province":"Gelderland",
    "sg:tags":[
        "opslag",
        "bewaring"
    ],
    "wof:name":"E. Vlastuin",
    "wof:placetype":"venue"
},
  "geometry": {"coordinates":[5.599615097,52.0853996277],"type":"Point"}
}