{
  "type": "Feature",
  "properties": {
    "iso:country":"NL",
    "sg:address":"Akerstraat 94",
    "sg:city":"Kerkrade",
    "sg:orig_category":"Diverse Consumentenartikelen Gh",
    "sg:phone":"+31 45 541 3438",
    "sg:postcode":"6466 HM",
    "sg:province":"Limburg",
    "wof:name":"Muziekcentrale Hanssen Bv",
    "wof:placetype":"venue"
},
  "geometry": {"coordinates":[6.025104,50.85891],"type":"Point"}
}