{
  "type": "Feature",
  "properties": {
    "iso:country":"NL",
    "sg:address":"Oosthavendk 1/A",
    "sg:city":"Wilhelminadorp",
    "sg:orig_category":"Hengelsportartikelen",
    "sg:phone":"+31 113 250 403",
    "sg:postcode":"4475 AA",
    "sg:province":"Zeeland",
    "wof:name":"Topsy Baits",
    "wof:placetype":"venue"
},
  "geometry": {"coordinates":[3.910369,51.534248],"type":"Point"}
}