{
  "type": "Feature",
  "properties": {
    "addr:full":"Hoge Steenweg 19 Breda Noord-Brabant 4811 CG",
    "addr:housenumber":"19",
    "addr:postcode":"4811 cg",
    "addr:street":"Hoge Steenweg",
    "iso:country":"NL",
    "sg:address":"Hoge Steenweg 19",
    "sg:city":"Breda",
    "sg:orig_category":"Beveiligingsdiensten And Bewakingsbedrijven",
    "sg:phone":"+31 162 459 756",
    "sg:postcode":"4811 CG",
    "sg:province":"Noord-Brabant",
    "wof:name":"Inst Bedrijfsbeveiliging En Bewaking Ivbb",
    "wof:placetype":"venue"
},
  "geometry": {"coordinates":[4.790779,51.595036],"type":"Point"}
}