{
  "type": "Feature",
  "properties": {
    "addr:full":"Frisaxstraat 12 Wolvega Provincie Friesland 8471 ZW",
    "addr:housenumber":"12",
    "addr:postcode":"8471 zw",
    "addr:street":"Frisaxstraat;Provincie Friesland",
    "iso:country":"NL",
    "sg:address":"Frisaxstraat 12",
    "sg:city":"Wolvega",
    "sg:orig_category":"Meubelzaken, Woning- And Keukeninrichting",
    "sg:phone":"+31 561 614 373",
    "sg:postcode":"8471 ZW",
    "sg:province":"Provincie Friesland",
    "wof:name":"Rotanland",
    "wof:placetype":"venue"
},
  "geometry": {"coordinates":[5.994084,52.886833],"type":"Point"}
}