{
  "type": "Feature",
  "properties": {
    "addr:full":"Diepenbroekstr 16 Zaandam Noord-Holland 1507 KH",
    "addr:housenumber":"16",
    "addr:postcode":"1507 kh",
    "addr:street":"Diepenbroekstr",
    "iso:country":"NL",
    "sg:address":"Diepenbroekstr 16",
    "sg:city":"Zaandam",
    "sg:orig_category":"Horeca-Inrichtingen En -Uitrustingen",
    "sg:phone":"+31 6 53769560",
    "sg:postcode":"1507 KH",
    "sg:province":"Noord-Holland",
    "wof:name":"Bos",
    "wof:placetype":"venue"
},
  "geometry": {"coordinates":[4.803591,52.450222],"type":"Point"}
}