{
  "type": "Feature",
  "properties": {
    "addr:full":"Bergweg 169 A Zeist Utrecht 3707  A",
    "addr:housenumber":"169 a;3707 a",
    "addr:street":"Bergweg",
    "iso:country":"NL",
    "sg:address":"Bergweg 169 A",
    "sg:city":"Zeist",
    "sg:orig_category":"Autoverhuur",
    "sg:phone":"+31 30 693 1481",
    "sg:postcode":"3707  A",
    "sg:province":"Utrecht",
    "sg:website":"http://www.budget.nl",
    "wof:name":"Budget Rent A Car",
    "wof:placetype":"venue"
},
  "geometry": {"coordinates":[5.24387,52.08548],"type":"Point"}
}