{
  "type": "Feature",
  "properties": {
    "addr:full":"Molsln 134 Delft Zuid-Holland 2611 RP",
    "addr:housenumber":"134",
    "addr:postcode":"delft;2611 rp",
    "iso:country":"NL",
    "sg:address":"Molsln 134",
    "sg:city":"Delft",
    "sg:orig_category":"Bloemen En Planten",
    "sg:phone":"+31 15 215 8467",
    "sg:postcode":"2611 RP",
    "sg:province":"Zuid-Holland",
    "wof:name":"Regenboog Bloem & Blad",
    "wof:placetype":"venue"
},
  "geometry": {"coordinates":[4.35869,52.011505],"type":"Point"}
}