{
  "type": "Feature",
  "properties": {
    "iso:country":"NL",
    "sg:address":"Rottekd 244",
    "sg:city":"Bergschenhoek",
    "sg:orig_category":"Adviesbureaus",
    "sg:phone":"+31 10 511 3445",
    "sg:postcode":"2661 JX",
    "sg:province":"Zuid-Holland",
    "wof:name":"Sciencegraphics",
    "wof:placetype":"venue"
},
  "geometry": {"coordinates":[4.500133,51.989536],"type":"Point"}
}