{
  "type": "Feature",
  "properties": {
    "addr:full":"Elzenlaan 47 Hoevelaken Gelderland 3871 BL",
    "addr:housenumber":"47",
    "addr:postcode":"3871 bl",
    "addr:street":"Elzenlaan;Gelderland",
    "iso:country":"NL",
    "sg:address":"Elzenlaan 47",
    "sg:city":"Hoevelaken",
    "sg:orig_category":"Vertaal- And Tolkenbureaus",
    "sg:phone":"+31 33 253 4198",
    "sg:postcode":"3871 BL",
    "sg:province":"Gelderland",
    "wof:name":"Vertaalbureau J.M.M. Boere",
    "wof:placetype":"venue"
},
  "geometry": {"coordinates":[5.450806,52.171402],"type":"Point"}
}