{
  "type": "Feature",
  "properties": {
    "iso:country":"NL",
    "sg:address":"Geldersepoort 17",
    "sg:city":"Venlo",
    "sg:classifiers":[
        {
            "category":"Farming",
            "subcategory":"Fish & Marine Products",
            "type":"Manufacturing & Wholesale Goods"
        }
    ],
    "sg:phone":"+31 77 321 0020",
    "sg:postcode":"5911 GJ",
    "sg:province":"Limburg",
    "sg:tags":[
        "vi"
    ],
    "wof:name":"Visscher, De",
    "wof:placetype":"venue"
},
  "geometry": {"coordinates":[6.171009,51.371883],"type":"Point"}
}