{
  "type": "Feature",
  "properties": {
    "addr:full":"Zeilbergsestr 80 Deurne Noord-Brabant 5751 LN",
    "addr:housenumber":"80",
    "addr:postcode":"5751 ln",
    "addr:street":"Zeilbergsestr",
    "iso:country":"NL",
    "sg:address":"Zeilbergsestr 80",
    "sg:city":"Deurne",
    "sg:classifiers":[
        {
            "category":"Wholesale",
            "subcategory":"Motor Vehicles",
            "type":"Manufacturing & Wholesale Goods"
        }
    ],
    "sg:phone":"+31 493 313 980",
    "sg:postcode":"5751 LN",
    "sg:province":"Noord-Brabant",
    "sg:tags":[
        "scooter",
        "en"
    ],
    "wof:name":"Dirks",
    "wof:placetype":"venue"
},
  "geometry": {"coordinates":[5.813327,51.45705],"type":"Point"}
}