{
  "type": "Feature",
  "properties": {
    "addr:full":"Hoofdstraat 80 Schimmert Limburg 6333 BK",
    "addr:housenumber":"80",
    "addr:postcode":"6333 bk",
    "addr:street":"Hoofdstraat",
    "iso:country":"NL",
    "sg:address":"Hoofdstraat 80",
    "sg:city":"Schimmert",
    "sg:classifiers":[
        {
            "category":"Fast Food",
            "type":"Food & Drink"
        }
    ],
    "sg:phone":"+31 45 404 2474",
    "sg:postcode":"6333 BK",
    "sg:province":"Limburg",
    "sg:tags":[
        "afhaal",
        "restaurant"
    ],
    "wof:name":"Tropical",
    "wof:placetype":"venue"
},
  "geometry": {"coordinates":[5.8261852264,50.9065628052],"type":"Point"}
}