{
  "type": "Feature",
  "properties": {
    "addr:full":"Anjerln 34 Haren Gn Groningen 9753 GC",
    "addr:housenumber":"34",
    "addr:postcode":"9753 gc",
    "addr:street":"Anjerln",
    "iso:country":"NL",
    "sg:address":"Anjerln 34",
    "sg:city":"Haren Gn",
    "sg:orig_category":"Fitnesscentra",
    "sg:phone":"+31 50 534 0002",
    "sg:postcode":"9753 GC",
    "sg:province":"Groningen",
    "sg:website":"http://www.bodyfitharen.nl",
    "wof:name":"Body Fit Haren",
    "wof:placetype":"venue"
},
  "geometry": {"coordinates":[6.60632,53.170658],"type":"Point"}
}