{
  "type": "Feature",
  "properties": {
    "addr:full":"Bunsenstr 38 Dordrecht Zuid-Holland 3316 GC",
    "addr:housenumber":"38",
    "addr:postcode":"3316 gc",
    "addr:street":"Bunsenstr",
    "iso:country":"NL",
    "sg:address":"Bunsenstr 38",
    "sg:city":"Dordrecht",
    "sg:orig_category":"Verpakkingsbedrijven",
    "sg:phone":"+31 78 617 7666",
    "sg:postcode":"3316 GC",
    "sg:province":"Zuid-Holland",
    "sg:website":"http://www.weidenhammer.de",
    "wof:name":"Dorpak Bv",
    "wof:placetype":"venue"
},
  "geometry": {"coordinates":[4.631985,51.778316],"type":"Point"}
}