{
  "type": "Feature",
  "properties": {
    "addr:full":"Spuiboulevard 50 Dordrecht South Holland 3311 GR",
    "addr:housenumber":"50",
    "addr:postcode":"3311",
    "addr:street":"Spuiboulevard",
    "iso:country":"NL",
    "sg:address":"Spuiboulevard 50",
    "sg:city":"Dordrecht",
    "sg:orig_category":"Boekenuitgeverijen",
    "sg:phone":"+31 78 639 2392",
    "sg:postcode":"3311 GR",
    "sg:province":"South Holland",
    "wof:name":"Kluwer Academic Publishers Bv",
    "wof:placetype":"venue"
},
  "geometry": {"coordinates":[4.667266,51.811157],"type":"Point"}
}