{
  "type": "Feature",
  "properties": {
    "addr:full":"Weerd 1 Leeuwarden Provincie Friesland 8911 HL",
    "addr:housenumber":"1",
    "addr:postcode":"8911 hl",
    "addr:street":"Weerd;Provincie Friesland",
    "iso:country":"NL",
    "sg:address":"Weerd 1",
    "sg:city":"Leeuwarden",
    "sg:orig_category":"Kappers",
    "sg:phone":"+31 58 215 3258",
    "sg:postcode":"8911 HL",
    "sg:province":"Provincie Friesland",
    "wof:name":"Vries, G De",
    "wof:placetype":"venue"
},
  "geometry": {"coordinates":[5.794969,53.200954],"type":"Point"}
}