{
  "type": "Feature",
  "properties": {
    "addr:full":"Huijsmansstraat 3 Schiedam South Holland 3117 KJ",
    "addr:housenumber":"3",
    "addr:postcode":"3117 kj",
    "addr:street":"Huijsmansstraat",
    "iso:country":"NL",
    "sg:address":"Huijsmansstraat 3",
    "sg:city":"Schiedam",
    "sg:orig_category":"Muziekinstrumenten Fab",
    "sg:phone":"+31 10 473 7169",
    "sg:postcode":"3117 KJ",
    "sg:province":"South Holland",
    "wof:name":"Sander De Gier Gitaarbouw",
    "wof:placetype":"venue"
},
  "geometry": {"coordinates":[4.391761,51.912243],"type":"Point"}
}