{
  "type": "Feature",
  "properties": {
    "addr:full":"De R V Zuidewynln 22 Breda Noord-Brabant 4818 GB",
    "addr:housenumber":"22",
    "addr:postcode":"4818 gb",
    "addr:street":"De R V Zuidewynln",
    "iso:country":"NL",
    "sg:address":"De R V Zuidewynln 22",
    "sg:city":"Breda",
    "sg:orig_category":"Podotherapeuten",
    "sg:phone":"+31 76 521 0069",
    "sg:postcode":"4818 GB",
    "sg:province":"Noord-Brabant",
    "wof:name":"Albers F A H & Eijden W H M",
    "wof:placetype":"venue"
},
  "geometry": {"coordinates":[4.771685,51.591351],"type":"Point"}
}