{
  "type": "Feature",
  "properties": {
    "addr:full":"Chaamsewg 8 Alphen Nb North Brabant 5131 NG",
    "addr:housenumber":"8;nb",
    "addr:postcode":"5131 ng",
    "addr:street":"Chaamsewg",
    "iso:country":"NL",
    "sg:address":"Chaamsewg 8",
    "sg:city":"Alphen Nb",
    "sg:orig_category":"Balletscholen",
    "sg:phone":"+31 13 508 6070",
    "sg:postcode":"5131 NG",
    "sg:province":"North Brabant",
    "wof:name":"Butterman, Greetje",
    "wof:placetype":"venue"
},
  "geometry": {"coordinates":[4.950817,51.484028],"type":"Point"}
}