{
  "type": "Feature",
  "properties": {
    "addr:full":"Kruisweg 755 Hoofddorp North Holland 2132 NE",
    "addr:housenumber":"755",
    "addr:postcode":"2132 ne",
    "addr:street":"Kruisweg",
    "iso:country":"NL",
    "sg:address":"Kruisweg 755",
    "sg:city":"Hoofddorp",
    "sg:orig_category":"Kantoor- And Schoolbenodigdheden Gh",
    "sg:phone":"+31 20 655 6390",
    "sg:postcode":"2132 NE",
    "sg:province":"North Holland",
    "wof:name":"Deltafix International Bv",
    "wof:placetype":"venue"
},
  "geometry": {"coordinates":[4.7104158401,52.2963867188],"type":"Point"}
}