{
  "type": "Feature",
  "properties": {
    "addr:full":"Wolbrandsstr 16 Dordrecht Zuid-Holland 3312 PW",
    "addr:housenumber":"16",
    "addr:postcode":"3312 pw",
    "addr:street":"Wolbrandsstr",
    "iso:country":"NL",
    "sg:address":"Wolbrandsstr 16",
    "sg:city":"Dordrecht",
    "sg:orig_category":"Schilders",
    "sg:phone":"+31 78 614 6370",
    "sg:postcode":"3312 PW",
    "sg:province":"Zuid-Holland",
    "wof:name":"Laleyne, De",
    "wof:placetype":"venue"
},
  "geometry": {"coordinates":[4.680294,51.804756],"type":"Point"}
}