{
  "type": "Feature",
  "properties": {
    "addr:full":"Gubbelstr 38 Maastricht Limburg 6211 CE",
    "addr:housenumber":"38",
    "addr:postcode":"6211 ce",
    "addr:street":"Gubbelstr",
    "iso:country":"NL",
    "sg:address":"Gubbelstr 38",
    "sg:city":"Maastricht",
    "sg:orig_category":"Zonnebank- En Solariumcentra",
    "sg:phone":"+31 43 326 0181",
    "sg:postcode":"6211 CE",
    "sg:province":"Limburg",
    "sg:website":"http://www.sundays.nl",
    "wof:name":"Sundays Zonnestudio",
    "wof:placetype":"venue"
},
  "geometry": {"coordinates":[5.691644,50.852077],"type":"Point"}
}