{
  "type": "Feature",
  "properties": {
    "addr:full":"Bosschebaan 22 Velp Nb North Brabant 5363 SX",
    "addr:housenumber":"22;nb",
    "addr:postcode":"5363 sx",
    "addr:street":"Bosschebaan",
    "iso:country":"NL",
    "sg:address":"Bosschebaan 22",
    "sg:city":"Velp Nb",
    "sg:orig_category":"Granen, Zaden And Diervoeders Gh",
    "sg:phone":"+31 486 476 290",
    "sg:postcode":"5363 SX",
    "sg:province":"North Brabant",
    "wof:name":"Verstappen Speciaal Voeders Velp Vof",
    "wof:placetype":"venue"
},
  "geometry": {"coordinates":[5.706317,51.743202],"type":"Point"}
}