{
  "type": "Feature",
  "properties": {
    "addr:full":"Vlaswg 2 Moerdyk North Brabant 4782 PW",
    "addr:housenumber":"2",
    "addr:postcode":"4782 pw",
    "addr:street":"Vlaswg",
    "iso:country":"NL",
    "sg:address":"Vlaswg 2",
    "sg:city":"Moerdyk",
    "sg:orig_category":"On- Offshore",
    "sg:phone":"+31 168 332 702",
    "sg:postcode":"4782 PW",
    "sg:province":"North Brabant",
    "wof:name":"Oilfield International",
    "wof:placetype":"venue"
},
  "geometry": {"coordinates":[4.607043,51.691296],"type":"Point"}
}