{
  "type": "Feature",
  "properties": {
    "iso:country":"NL",
    "sg:address":"Bloemgr 64Huis",
    "sg:city":"Amsterdam",
    "sg:orig_category":"Adviesbureaus",
    "sg:phone":"+31 20 622 0072",
    "sg:postcode":"1015 TL",
    "sg:province":"Noord-Holland",
    "wof:name":"Samson",
    "wof:placetype":"venue"
},
  "geometry": {"coordinates":[4.881573,52.375126],"type":"Point"}
}