{
  "type": "Feature",
  "properties": {
    "addr:full":"Postbus 999 Assen Provincie Drenthe 9400 AZ",
    "addr:housenumber":"999",
    "addr:postcode":"9400",
    "addr:street":"Postbus;Provincie Drenthe",
    "iso:country":"NL",
    "sg:address":"Postbus 999",
    "sg:city":"Assen",
    "sg:orig_category":"Omroep",
    "sg:phone":"+31 592 338 080",
    "sg:postcode":"9400 AZ",
    "sg:province":"Provincie Drenthe",
    "sg:website":"http://www.rtvdrenthe.nl",
    "wof:name":"Rtv Drenthe",
    "wof:placetype":"venue"
},
  "geometry": {"coordinates":[6.559506,52.994041],"type":"Point"}
}