{
  "type": "Feature",
  "properties": {
    "addr:full":"P V Anrooyln 3 Arnhem Gelderland 6815 GT",
    "addr:housenumber":"3",
    "addr:postcode":"6815 gt",
    "addr:street":"Anrooyln",
    "iso:country":"NL",
    "sg:address":"P V Anrooyln 3",
    "sg:city":"Arnhem",
    "sg:orig_category":"Scholen Voor Basisonderwijs",
    "sg:phone":"+31 26 442 2401",
    "sg:postcode":"6815 GT",
    "sg:province":"Gelderland",
    "wof:name":"Emmaus",
    "wof:placetype":"venue"
},
  "geometry": {"coordinates":[5.904585,51.985519],"type":"Point"}
}