{
  "type": "Feature",
  "properties": {
    "addr:full":"Beemsterboerstr 8 Huizen Noord-Holland 1271 SE",
    "addr:housenumber":"8",
    "addr:postcode":"1271 se",
    "addr:street":"Beemsterboerstr",
    "iso:country":"NL",
    "sg:address":"Beemsterboerstr 8",
    "sg:city":"Huizen",
    "sg:orig_category":"Begrafenisverzorging",
    "sg:phone":"+31 35 525 3067",
    "sg:postcode":"1271 SE",
    "sg:province":"Noord-Holland",
    "sg:website":"http://www.rebel-uitvaart.nl",
    "wof:name":"Rebel'S Begrafenisonderneming",
    "wof:placetype":"venue"
},
  "geometry": {"coordinates":[5.232335,52.300133],"type":"Point"}
}