{
  "type": "Feature",
  "properties": {
    "addr:full":"Thorbeckestraat 3 Zuidhorn Groningen 9801 KA",
    "addr:housenumber":"3",
    "addr:postcode":"9801 ka",
    "addr:street":"Thorbeckestraat",
    "iso:country":"NL",
    "sg:address":"Thorbeckestraat 3",
    "sg:city":"Zuidhorn",
    "sg:orig_category":"Boekhouders",
    "sg:phone":"+31 594 505 928",
    "sg:postcode":"9801 KA",
    "sg:province":"Groningen",
    "wof:name":"Administratiekantoor Baarveld",
    "wof:placetype":"venue"
},
  "geometry": {"coordinates":[6.398006,53.247971],"type":"Point"}
}