{
  "type": "Feature",
  "properties": {
    "iso:country":"NL",
    "sg:address":"Schiedamsewg 282",
    "sg:city":"Rotterdam",
    "sg:orig_category":"Scholen Voor Basisonderwijs",
    "sg:phone":"+31 10 476 2477",
    "sg:postcode":"3025 AS",
    "sg:province":"Zuid-Holland",
    "wof:name":"Henry Dunant Sbo",
    "wof:placetype":"venue"
},
  "geometry": {"coordinates":[4.435954,51.912182],"type":"Point"}
}