{
  "type": "Feature",
  "properties": {
    "addr:full":"Graswg 71 Amsterdam Noord-Holland 1031 HX",
    "addr:housenumber":"71",
    "addr:postcode":"1031 hx",
    "addr:street":"Graswg",
    "iso:country":"NL",
    "sg:address":"Graswg 71",
    "sg:city":"Amsterdam",
    "sg:orig_category":"Bloembollen - Groothandel",
    "sg:phone":"+31 20 694 4171",
    "sg:postcode":"1031 HX",
    "sg:province":"Noord-Holland",
    "sg:website":"http://www.tulipworld.com",
    "wof:name":"Tulipworld Bv",
    "wof:placetype":"venue"
},
  "geometry": {"coordinates":[4.897731,52.393768],"type":"Point"}
}