{
  "type": "Feature",
  "properties": {
    "addr:full":"Scheggertdijk 7 Almen Gelderland 7218 MS",
    "addr:housenumber":"7",
    "addr:postcode":"7218",
    "addr:street":"Scheggertdijk;Gelderland",
    "iso:country":"NL",
    "sg:address":"Scheggertdijk 7",
    "sg:city":"Almen",
    "sg:orig_category":"Hout Gh",
    "sg:phone":"+31 575 432 060",
    "sg:postcode":"7218 MS",
    "sg:province":"Gelderland",
    "wof:name":"Topwood Bv",
    "wof:placetype":"venue"
},
  "geometry": {"coordinates":[-92.011841,45.459785],"type":"Point"}
}