{
  "type": "Feature",
  "properties": {
    "iso:country":"NL",
    "sg:address":"Het Woud 4A",
    "sg:city":"Nibbixwoud",
    "sg:orig_category":"Acupunctuur",
    "sg:phone":"+31 229 573 053",
    "sg:postcode":"1688 JE",
    "sg:province":"North Holland",
    "wof:name":"Vreede, F",
    "wof:placetype":"venue"
},
  "geometry": {"coordinates":[5.055196,52.694115],"type":"Point"}
}