{
  "type": "Feature",
  "properties": {
    "addr:full":"Damstr 22 Amsterdam North Holland 1012 JM",
    "addr:housenumber":"22",
    "addr:postcode":"1012 jm",
    "addr:street":"Damstr",
    "iso:country":"NL",
    "sg:address":"Damstr 22",
    "sg:city":"Amsterdam",
    "sg:classifiers":[
        {
            "category":"Travel",
            "subcategory":"Hotels & Motels",
            "type":"Entertainment"
        }
    ],
    "sg:phone":"+31 20 624 1367",
    "sg:postcode":"1012 JM",
    "sg:province":"North Holland",
    "wof:name":"Gerstekorrel, De",
    "wof:placetype":"venue"
},
  "geometry": {"coordinates":[4.894806,52.372154],"type":"Point"}
}