{
  "type": "Feature",
  "properties": {
    "iso:country":"NL",
    "sg:address":"Schoutstr 9",
    "sg:city":"Ryen",
    "sg:orig_category":"Schilders",
    "sg:phone":"+31 161 293 790",
    "sg:postcode":"5121 KA",
    "sg:province":"Noord-Brabant",
    "wof:name":"Loon, Ronald Van",
    "wof:placetype":"venue"
},
  "geometry": {"coordinates":[4.9197,51.588017],"type":"Point"}
}