{
  "type": "Feature",
  "properties": {
    "addr:full":"Honingraat 2325 Leersum Utrecht 3956 HG",
    "addr:postcode":"2325;3956 hg",
    "addr:street":"Honingraat",
    "iso:country":"NL",
    "sg:address":"Honingraat 2325",
    "sg:city":"Leersum",
    "sg:orig_category":"Apotheken",
    "sg:phone":"+31 343 453 855",
    "sg:postcode":"3956 HG",
    "sg:province":"Utrecht",
    "wof:name":"Drie Lelie\u00ebn, De",
    "wof:placetype":"venue"
},
  "geometry": {"coordinates":[5.43246,52.010406],"type":"Point"}
}