{
  "type": "Feature",
  "properties": {
    "iso:country":"NL",
    "sg:address":"Looistr 36",
    "sg:city":"Heumen",
    "sg:classifiers":[
        {
            "category":"Food & Beverages",
            "subcategory":"Fruits & Vegetables",
            "type":"Retail Goods"
        }
    ],
    "sg:phone":"+31 24 358 0739",
    "sg:postcode":"6582 BC",
    "sg:province":"Gelderland",
    "sg:tags":[
        "en",
        "groenten"
    ],
    "wof:name":"Dijk Vof, J Van",
    "wof:placetype":"venue"
},
  "geometry": {"coordinates":[5.840323,51.773968],"type":"Point"}
}