{
  "type": "Feature",
  "properties": {
    "addr:full":"Hoofdweg 5 Buren Fr Friesland 9164 KL",
    "addr:housenumber":"5",
    "addr:postcode":"9164 kl",
    "addr:street":"Hoofdweg",
    "iso:country":"NL",
    "sg:address":"Hoofdweg 5",
    "sg:city":"Buren Fr",
    "sg:orig_category":"Bloemen And Planten",
    "sg:phone":"+31 519 543 031",
    "sg:postcode":"9164 KL",
    "sg:province":"Friesland",
    "wof:name":"T Koebloemke",
    "wof:placetype":"venue"
},
  "geometry": {"coordinates":[5.797578,53.447437],"type":"Point"}
}