{
  "type": "Feature",
  "properties": {
    "addr:full":"Burg Wuitewg 39B Drachten Friesland 9203 KA",
    "addr:housenumber":"39b",
    "addr:postcode":"9203 ka",
    "addr:street":"Burg Wuitewg",
    "iso:country":"NL",
    "sg:address":"Burg Wuitewg 39B",
    "sg:city":"Drachten",
    "sg:orig_category":"Accountants - Administratie- Consulenten En -Kantoren",
    "sg:phone":"+31 512 586 898",
    "sg:postcode":"9203 KA",
    "sg:province":"Friesland",
    "wof:name":"Wolting & De Jong Bv",
    "wof:placetype":"venue"
},
  "geometry": {"coordinates":[6.098843,53.102161],"type":"Point"}
}