{
  "type": "Feature",
  "properties": {
    "addr:full":"Huibert Van Eijkenstraat 45 Naarden Noord-Holland 1411 TK",
    "addr:housenumber":"45",
    "addr:postcode":"1411 tk",
    "addr:street":"Huibert Van Eijkenstraat",
    "iso:country":"NL",
    "sg:address":"Huibert Van Eijkenstraat 45",
    "sg:city":"Naarden",
    "sg:orig_category":"Verzekeringen",
    "sg:phone":"+31 35 694 4804",
    "sg:postcode":"1411 TK",
    "sg:province":"Noord-Holland",
    "wof:name":"Assurantiekantoor J.M. Boots",
    "wof:placetype":"venue"
},
  "geometry": {"coordinates":[5.150603,52.298561],"type":"Point"}
}