{
  "type": "Feature",
  "properties": {
    "addr:full":"Paulus Potterlaan 48 Woudenberg Utrecht 3931 TG",
    "addr:housenumber":"48",
    "addr:postcode":"3931 tg",
    "addr:street":"Paulus Potterlaan",
    "iso:country":"NL",
    "sg:address":"Paulus Potterlaan 48",
    "sg:city":"Woudenberg",
    "sg:orig_category":"Verzekeringen",
    "sg:phone":"+31 33 286 1485",
    "sg:postcode":"3931 TG",
    "sg:province":"Utrecht",
    "wof:name":"Assurantiekantoor Vlot",
    "wof:placetype":"venue"
},
  "geometry": {"coordinates":[5.423619,52.076488],"type":"Point"}
}