{
  "type": "Feature",
  "properties": {
    "iso:country":"NL",
    "sg:address":"Wilhelminastraat 39",
    "sg:city":"Zwijndrecht",
    "sg:orig_category":"Diverse Opleidingen And Onderwijs",
    "sg:phone":"+31 78 612 5877",
    "sg:postcode":"3332 BT",
    "sg:province":"South Holland",
    "wof:name":"Atelier 'T Pandje",
    "wof:placetype":"venue"
},
  "geometry": {"coordinates":[4.65647,51.822247],"type":"Point"}
}