{
  "type": "Feature",
  "properties": {
    "iso:country":"NL",
    "sg:address":"Rembrandtln 15",
    "sg:city":"Voorschoten",
    "sg:orig_category":"Architecten En Architectenbureaus",
    "sg:phone":"+31 71 561 7427",
    "sg:postcode":"2251 GT",
    "sg:province":"Zuid-Holland",
    "wof:name":"Luiten, B J M",
    "wof:placetype":"venue"
},
  "geometry": {"coordinates":[4.454619,52.122707],"type":"Point"}
}