{
  "type": "Feature",
  "properties": {
    "iso:country":"NL",
    "sg:address":"Derde Looiersdwarsstraat 57",
    "sg:city":"Amsterdam",
    "sg:orig_category":"Artiesten",
    "sg:phone":"+31 20 625 4177",
    "sg:postcode":"1016 VD",
    "sg:province":"Noord-Holland",
    "wof:name":"Hooker",
    "wof:placetype":"venue"
},
  "geometry": {"coordinates":[4.879716,52.368393],"type":"Point"}
}