{
  "type": "Feature",
  "properties": {
    "addr:full":"Oosterparkwg 21 Harlingen Friesland 8862 BA",
    "addr:housenumber":"21",
    "addr:postcode":"8862 ba",
    "addr:street":"Oosterparkwg",
    "iso:country":"NL",
    "sg:address":"Oosterparkwg 21",
    "sg:city":"Harlingen",
    "sg:classifiers":[
        {
            "category":"Retail",
            "subcategory":"Auto Repair",
            "type":"Services"
        }
    ],
    "sg:phone":"+31 517 430 035",
    "sg:postcode":"8862 BA",
    "sg:province":"Friesland",
    "sg:tags":[
        "garage"
    ],
    "wof:name":"Westra Auto Occasions",
    "wof:placetype":"venue"
},
  "geometry": {"coordinates":[5.435699,53.167828],"type":"Point"}
}