{
  "type": "Feature",
  "properties": {
    "addr:full":"Bilderdykpln To 23 Voorburg Zuid-Holland 2274 LW",
    "addr:housenumber":"23",
    "addr:postcode":"2274 lw",
    "iso:country":"NL",
    "sg:address":"Bilderdykpln To 23",
    "sg:city":"Voorburg",
    "sg:orig_category":"Bloemen En Planten",
    "sg:phone":"+31 70 386 7097",
    "sg:postcode":"2274 LW",
    "sg:province":"Zuid-Holland",
    "wof:name":"Baatenburg, H",
    "wof:placetype":"venue"
},
  "geometry": {"coordinates":[4.34952,52.073792],"type":"Point"}
}