{
  "type": "Feature",
  "properties": {
    "addr:full":"Stationspln 17A Hoogeveen Drenthe 7901 AA",
    "addr:housenumber":"17a",
    "addr:postcode":"7901 aa",
    "addr:street":"Stationspln",
    "iso:country":"NL",
    "sg:address":"Stationspln 17A",
    "sg:city":"Hoogeveen",
    "sg:orig_category":"Vakorganisaties",
    "sg:phone":"+31 528 231 865",
    "sg:postcode":"7901 AA",
    "sg:province":"Drenthe",
    "sg:website":"http://www.hbbcnv.nl",
    "wof:name":"Cnv",
    "wof:placetype":"venue"
},
  "geometry": {"coordinates":[6.473696,52.733166],"type":"Point"}
}