{
  "type": "Feature",
  "properties": {
    "addr:full":"Noordhaven 46-48 Zevenbergen Noord-Brabant 4761 DB",
    "addr:housenumber":"46-48",
    "addr:postcode":"4761 db",
    "addr:street":"Noordhaven",
    "iso:country":"NL",
    "sg:address":"Noordhaven 46-48",
    "sg:city":"Zevenbergen",
    "sg:orig_category":"Kantoorbenodigdheden",
    "sg:phone":"+31 168 323 572",
    "sg:postcode":"4761 DB",
    "sg:province":"Noord-Brabant",
    "wof:name":"Geleijns Kantoorvakhandel",
    "wof:placetype":"venue"
},
  "geometry": {"coordinates":[4.6060628891,51.6457519531],"type":"Point"}
}