{
  "type": "Feature",
  "properties": {
    "iso:country":"NL",
    "sg:address":"Herensingel 99",
    "sg:city":"Haarlem",
    "sg:orig_category":"Elektriciens",
    "sg:phone":"+31 23 540 3062",
    "sg:postcode":"2032 RV",
    "sg:province":"Noord-Holland",
    "wof:name":"Van Dijk & Zn Electrotechnisch Installatiebureau",
    "wof:placetype":"venue"
},
  "geometry": {"coordinates":[4.644445,52.378441],"type":"Point"}
}