{
  "type": "Feature",
  "properties": {
    "iso:country":"NL",
    "sg:address":"Veemarktstr 63A",
    "sg:city":"Breda",
    "sg:orig_category":"Glazenwasserijen",
    "sg:phone":"+31 76 522 7068",
    "sg:postcode":"4811 ZD",
    "sg:province":"Noord-Brabant",
    "sg:website":"http://www.ibw.nl/loomans",
    "wof:name":"Loomans Cleaning",
    "wof:placetype":"venue"
},
  "geometry": {"coordinates":[4.779589,51.589165],"type":"Point"}
}