{
  "type": "Feature",
  "properties": {
    "iso:country":"NL",
    "sg:address":"Hoofddiep 61",
    "sg:city":"Zevenhuizen Gn",
    "sg:classifiers":[
        {
            "category":"Retail",
            "subcategory":"Auto Repair",
            "type":"Services"
        }
    ],
    "sg:phone":"+31 594 631 813",
    "sg:postcode":"9354 AM",
    "sg:province":"Groningen",
    "sg:tags":[
        "garage"
    ],
    "wof:name":"Hoekstra, Theo",
    "wof:placetype":"venue"
},
  "geometry": {"coordinates":[6.350801,53.126373],"type":"Point"}
}