{
  "type": "Feature",
  "properties": {
    "addr:full":"Amperestr 1 Doetinchem Gelderland 7006 RX",
    "addr:housenumber":"1",
    "addr:postcode":"7006 rx",
    "addr:street":"Amperestr;Gelderland",
    "iso:country":"NL",
    "sg:address":"Amperestr 1",
    "sg:city":"Doetinchem",
    "sg:orig_category":"Horecabenodigdheden",
    "sg:phone":"+31 314 330 021",
    "sg:postcode":"7006 RX",
    "sg:province":"Gelderland",
    "sg:website":"http://www.ubbink-sesink.nl",
    "wof:name":"Ubbink-Sesink Bv",
    "wof:placetype":"venue"
},
  "geometry": {"coordinates":[6.258099,51.97073],"type":"Point"}
}