{
  "type": "Feature",
  "properties": {
    "addr:full":"Belcantodreef 25 Krimpen Ad Yssel South Holland 2926 PB",
    "addr:housenumber":"25",
    "addr:postcode":"2926 pb",
    "addr:street":"Belcantodreef;Yssel",
    "iso:country":"NL",
    "sg:address":"Belcantodreef 25",
    "sg:city":"Krimpen Ad Yssel",
    "sg:orig_category":"Keuken- Groot-Installaties",
    "sg:phone":"+31 180 550 956",
    "sg:postcode":"2926 PB",
    "sg:province":"South Holland",
    "wof:name":"Velde, D D J Van De",
    "wof:placetype":"venue"
},
  "geometry": {"coordinates":[4.603177,51.908592],"type":"Point"}
}