{
  "type": "Feature",
  "properties": {
    "iso:country":"NL",
    "sg:address":"K Molenstr 6",
    "sg:city":"S Gravenhage",
    "sg:orig_category":"Psychologen",
    "sg:phone":"+31 70 365 3556",
    "sg:postcode":"2513 BM",
    "sg:province":"Zuid-Holland",
    "sg:website":"http://www.pccnederland.nl",
    "wof:name":"Psychologisch Coaching Consult Den Haag Bv",
    "wof:placetype":"venue"
},
  "geometry": {"coordinates":[4.30339,52.078442],"type":"Point"}
}