{
  "type": "Feature",
  "properties": {
    "addr:full":"A Rousselstr 1 S Gravenhage South Holland 2551 ZN",
    "addr:housenumber":"1",
    "addr:postcode":"2551 zn",
    "addr:street":"S Gravenhage",
    "iso:country":"NL",
    "sg:address":"A Rousselstr 1",
    "sg:city":"S Gravenhage",
    "sg:orig_category":"Loodgieters",
    "sg:phone":"+31 70 323 2696",
    "sg:postcode":"2551 ZN",
    "sg:province":"South Holland",
    "sg:website":"http://www.delangerioolservice.nl",
    "wof:name":"Lange Rioolservice, De",
    "wof:placetype":"venue"
},
  "geometry": {"coordinates":[4.23775,52.058601],"type":"Point"}
}