{
  "type": "Feature",
  "properties": {
    "addr:full":"Treubstr 1E Ryswyk Zh Zuid-Holland 2288 EG",
    "addr:postcode":"2288 eg",
    "addr:street":"Treubstr",
    "iso:country":"NL",
    "sg:address":"Treubstr 1E",
    "sg:city":"Ryswyk Zh",
    "sg:orig_category":"Elektrotechnische Installatiebureaus",
    "sg:phone":"+31 70 307 4750",
    "sg:postcode":"2288 EG",
    "sg:province":"Zuid-Holland",
    "wof:name":"Gti Bv",
    "wof:placetype":"venue"
},
  "geometry": {"coordinates":[4.32436,52.037251],"type":"Point"}
}