{
  "type": "Feature",
  "properties": {
    "iso:country":"NL",
    "sg:address":"Noordeinde 142",
    "sg:city":"Oostzaan",
    "sg:orig_category":"Verbouwingen",
    "sg:phone":"+31 75 684 6761",
    "sg:postcode":"1511 AH",
    "sg:province":"Noord-Holland",
    "wof:name":"Househealing",
    "wof:placetype":"venue"
},
  "geometry": {"coordinates":[4.868878,52.453602],"type":"Point"}
}