{
  "type": "Feature",
  "properties": {
    "iso:country":"NL",
    "sg:address":"Beukenln 15A",
    "sg:city":"Soest",
    "sg:orig_category":"Bloemen En Planten - Verhuur",
    "sg:phone":"+31 35 602 7108",
    "sg:postcode":"3762 AE",
    "sg:province":"Utrecht",
    "wof:name":"Lizzyli",
    "wof:placetype":"venue"
},
  "geometry": {"coordinates":[5.287676,52.177288],"type":"Point"}
}