{
  "type": "Feature",
  "properties": {
    "iso:country":"NL",
    "sg:address":"Hofstraat 14",
    "sg:city":"Doetinchem",
    "sg:orig_category":"Apothekers",
    "sg:phone":"+31 314 333 948",
    "sg:postcode":"7001 CD",
    "sg:province":"Gelderland",
    "wof:name":"Hof Apotheek Bv",
    "wof:placetype":"venue"
},
  "geometry": {"coordinates":[6.288426,51.968166],"type":"Point"}
}