{
  "type": "Feature",
  "properties": {
    "addr:full":"Ginnekenwg 140 Breda Noord-Brabant 4818 JK",
    "addr:housenumber":"140",
    "addr:postcode":"4818 jk",
    "iso:country":"NL",
    "sg:address":"Ginnekenwg 140",
    "sg:city":"Breda",
    "sg:orig_category":"Wereldwinkels",
    "sg:phone":"+31 76 522 8871",
    "sg:postcode":"4818 JK",
    "sg:province":"Noord-Brabant",
    "wof:name":"Unicef",
    "wof:placetype":"venue"
},
  "geometry": {"coordinates":[4.7831177711,51.5741043091],"type":"Point"}
}