{
  "type": "Feature",
  "properties": {
    "iso:country":"NL",
    "sg:address":"Van Alkemadelaan 700",
    "sg:city":"'S Gravenhage",
    "sg:classifiers":[
        {
            "category":"Professional",
            "subcategory":"Accounting & Tax Preparation",
            "type":"Services"
        }
    ],
    "sg:phone":"+31 70 326 4701",
    "sg:postcode":"2597 AW",
    "sg:province":"South Holland",
    "sg:tags":[
        "accountant"
    ],
    "wof:name":"Deloitte & Touche",
    "wof:placetype":"venue"
},
  "geometry": {"coordinates":[4.31741,52.103645],"type":"Point"}
}