{
  "type": "Feature",
  "properties": {
    "iso:country":"NL",
    "sg:address":"Herenweg 6",
    "sg:city":"Wilnis",
    "sg:orig_category":"Fietshandelaren",
    "sg:phone":"+31 297 288 733",
    "sg:postcode":"3648 CJ",
    "sg:province":"Utrecht",
    "wof:name":"Vof F. Van Den Berg & Partner",
    "wof:placetype":"venue"
},
  "geometry": {"coordinates":[4.900984,52.194981],"type":"Point"}
}