{
  "type": "Feature",
  "properties": {
    "addr:full":"Legedyk 51 Scharnegoutum Friesland 8629 RL",
    "addr:housenumber":"51",
    "addr:postcode":"8629 rl",
    "addr:street":"Legedyk",
    "iso:country":"NL",
    "sg:address":"Legedyk 51",
    "sg:city":"Scharnegoutum",
    "sg:orig_category":"Levende Dieren Gh",
    "sg:phone":"+31 515 412 629",
    "sg:postcode":"8629 RL",
    "sg:province":"Friesland",
    "wof:name":"S Posthuma",
    "wof:placetype":"venue"
},
  "geometry": {"coordinates":[5.680239,53.058277],"type":"Point"}
}