{
  "type": "Feature",
  "properties": {
    "addr:full":"Damsterdiep 66 Groningen Groningen 9713 EJ",
    "addr:housenumber":"66",
    "addr:postcode":"9713 ej",
    "addr:street":"Damsterdiep",
    "iso:country":"NL",
    "sg:address":"Damsterdiep 66",
    "sg:city":"Groningen",
    "sg:orig_category":"Adviesbureaus Bouwkunde",
    "sg:phone":"+31 50 579 2500",
    "sg:postcode":"9713 EJ",
    "sg:province":"Groningen",
    "wof:name":"Woonresearch",
    "wof:placetype":"venue"
},
  "geometry": {"coordinates":[6.578585,53.218674],"type":"Point"}
}