{
  "type": "Feature",
  "properties": {
    "iso:country":"NL",
    "sg:address":"Singel 15",
    "sg:city":"Jubbega",
    "sg:orig_category":"Fietsen En Bromfietsen",
    "sg:phone":"+31 516 463 722",
    "sg:postcode":"8411 CJ",
    "sg:province":"Friesland",
    "wof:name":"Singel, De",
    "wof:placetype":"venue"
},
  "geometry": {"coordinates":[6.106168,52.998039],"type":"Point"}
}