{
  "type": "Feature",
  "properties": {
    "addr:full":"Emmapln 8 Bilthoven Utrecht 3722 AD",
    "addr:housenumber":"8",
    "addr:postcode":"3722 ad",
    "addr:street":"Emmapln",
    "iso:country":"NL",
    "sg:address":"Emmapln 8",
    "sg:city":"Bilthoven",
    "sg:orig_category":"Goudsmeden En Zilversmeden",
    "sg:phone":"+31 30 229 3815",
    "sg:postcode":"3722 AD",
    "sg:province":"Utrecht",
    "wof:name":"Heleen Hoogenboom Edelsmid",
    "wof:placetype":"venue"
},
  "geometry": {"coordinates":[5.205125,52.129272],"type":"Point"}
}