{
  "type": "Feature",
  "properties": {
    "addr:full":"Voortseweg 15 Eersel North Brabant 5521 JB",
    "addr:housenumber":"15",
    "addr:postcode":"5521 jb",
    "addr:street":"Voortseweg",
    "iso:country":"NL",
    "sg:address":"Voortseweg 15",
    "sg:city":"Eersel",
    "sg:orig_category":"Kinderopvang Behalve Thuis",
    "sg:phone":"+31 497 517 814",
    "sg:postcode":"5521 JB",
    "sg:province":"North Brabant",
    "wof:name":"Duimelot Bv",
    "wof:placetype":"venue"
},
  "geometry": {"coordinates":[5.309267,51.355053],"type":"Point"}
}