{
  "type": "Feature",
  "properties": {
    "iso:country":"NL",
    "sg:address":"Kleine Jonkvrouwstraat 23",
    "sg:city":"Ijzendijke",
    "sg:classifiers":[
        {
            "category":"Professional",
            "subcategory":"Accounting & Tax Preparation",
            "type":"Services"
        }
    ],
    "sg:phone":"+31 117 302 241",
    "sg:postcode":"4515 EJ",
    "sg:province":"Zeeland",
    "sg:tags":[
        "accountant"
    ],
    "wof:name":"Adm.- & Belastingadviesbureau B.A. Neyt",
    "wof:placetype":"venue"
},
  "geometry": {"coordinates":[3.612997,51.31926],"type":"Point"}
}