{
  "type": "Feature",
  "properties": {
    "addr:full":"Industriewg 24 Maarssen Utrecht 3606 AS",
    "addr:housenumber":"24",
    "addr:postcode":"3606 as",
    "addr:street":"Industriewg",
    "iso:country":"NL",
    "sg:address":"Industriewg 24",
    "sg:city":"Maarssen",
    "sg:classifiers":[
        {
            "category":"Retail",
            "subcategory":"Storage",
            "type":"Services"
        }
    ],
    "sg:phone":"+31 346 559 770",
    "sg:postcode":"3606 AS",
    "sg:province":"Utrecht",
    "sg:tags":[
        "op-",
        "en",
        "overslagbedrijven"
    ],
    "wof:name":"Tnt",
    "wof:placetype":"venue"
},
  "geometry": {"coordinates":[5.040829,52.12867],"type":"Point"}
}