{
  "type": "Feature",
  "properties": {
    "addr:full":"Energiewg 8A Huizen North Holland 1271 ED",
    "addr:housenumber":"8a",
    "addr:postcode":"1271 ed",
    "addr:street":"Energiewg",
    "iso:country":"NL",
    "sg:address":"Energiewg 8A",
    "sg:city":"Huizen",
    "sg:orig_category":"Machinehandel",
    "sg:phone":"+31 35 526 1489",
    "sg:postcode":"1271 ED",
    "sg:province":"North Holland",
    "sg:website":"http://www.mmi-bv.com",
    "wof:name":"Mmi Bv",
    "wof:placetype":"venue"
},
  "geometry": {"coordinates":[5.243383,52.30711],"type":"Point"}
}