{
  "type": "Feature",
  "properties": {
    "addr:full":"Hoge Hondstraat 48 Deventer Overijssel 7413 CB",
    "addr:housenumber":"48",
    "addr:postcode":"7413 cb",
    "addr:street":"Hoge Hondstraat",
    "iso:country":"NL",
    "sg:address":"Hoge Hondstraat 48",
    "sg:city":"Deventer",
    "sg:orig_category":"Kappers",
    "sg:phone":"+31 570 623 467",
    "sg:postcode":"7413 CB",
    "sg:province":"Overijssel",
    "wof:name":"L J Korten",
    "wof:placetype":"venue"
},
  "geometry": {"coordinates":[6.160541,52.262012],"type":"Point"}
}