{
  "type": "Feature",
  "properties": {
    "iso:country":"NL",
    "sg:address":"Geubel 47",
    "sg:city":"Oosterhesselen",
    "sg:orig_category":"Schilders",
    "sg:phone":"+31 524 582 503",
    "sg:postcode":"7861 CK",
    "sg:province":"Provincie Drenthe",
    "wof:name":"Bol, Kees",
    "wof:placetype":"venue"
},
  "geometry": {"coordinates":[6.722372,52.752102],"type":"Point"}
}