{
  "type": "Feature",
  "properties": {
    "addr:full":"Hogenkampswg 39A Zwolle NL.08 8022 DA",
    "addr:housenumber":"39a",
    "addr:postcode":"8022 da",
    "addr:street":"Hogenkampswg",
    "iso:country":"NL",
    "sg:address":"Hogenkampswg 39A",
    "sg:city":"Zwolle",
    "sg:orig_category":"Wasserijen",
    "sg:phone":"+31 38 453 3435",
    "sg:postcode":"8022 DA",
    "sg:province":"NL.08",
    "wof:name":"Rontex",
    "wof:placetype":"venue"
},
  "geometry": {"coordinates":[6.1053037643,52.5213394165],"type":"Point"}
}