{
  "type": "Feature",
  "properties": {
    "iso:country":"NL",
    "sg:address":"Hogenkampswg 39A",
    "sg:city":"Zwolle",
    "sg:orig_category":"Wasserijen",
    "sg:phone":"+31 38 453 3435",
    "sg:postcode":"8022 DA",
    "sg:province":"NL.08",
    "wof:name":"Rontex",
    "wof:placetype":"venue"
},
  "geometry": {"coordinates":[6.1053037643,52.5213394165],"type":"Point"}
}