{
  "type": "Feature",
  "properties": {
    "addr:full":"Europa Ring 239 Wierden Overijssel 7641 DN",
    "addr:housenumber":"239",
    "addr:postcode":"7641 dn",
    "addr:street":"Europa Ring",
    "iso:country":"NL",
    "sg:address":"Europa Ring 239",
    "sg:city":"Wierden",
    "sg:orig_category":"Partyservice",
    "sg:phone":"+31 546 575 154",
    "sg:postcode":"7641 DN",
    "sg:province":"Overijssel",
    "wof:name":"Tijhof, Partyservice",
    "wof:placetype":"venue"
},
  "geometry": {"coordinates":[6.6062,52.364738],"type":"Point"}
}