{
  "type": "Feature",
  "properties": {
    "addr:full":"Parelstr 21 Hengelo Ov NL.08 7554 TL",
    "addr:housenumber":"21",
    "addr:postcode":"7554 tl",
    "addr:street":"Parelstr;Ov",
    "iso:country":"NL",
    "sg:address":"Parelstr 21",
    "sg:city":"Hengelo Ov",
    "sg:orig_category":"Oud Papier",
    "sg:phone":"+31 74 247 0171",
    "sg:postcode":"7554 TL",
    "sg:province":"NL.08",
    "wof:name":"Pol Papier Recycling",
    "wof:placetype":"venue"
},
  "geometry": {"coordinates":[6.7827568054,52.2376213074],"type":"Point"}
}