{
  "type": "Feature",
  "properties": {
    "addr:full":"Omschoorwg 4 Raamsdonksveer Noord-Brabant 4941 KP",
    "addr:housenumber":"4",
    "addr:postcode":"4941 kp",
    "addr:street":"Omschoorwg",
    "iso:country":"NL",
    "sg:address":"Omschoorwg 4",
    "sg:city":"Raamsdonksveer",
    "sg:orig_category":"Betonijzervlechten",
    "sg:phone":"+31 162 513 441",
    "sg:postcode":"4941 KP",
    "sg:province":"Noord-Brabant",
    "wof:name":"Luppens Bv",
    "wof:placetype":"venue"
},
  "geometry": {"coordinates":[4.883196,51.694874],"type":"Point"}
}