{
  "type": "Feature",
  "properties": {
    "addr:full":"Paul Krugerstraat 3 Apeldoorn Gelderland 7311 AN",
    "addr:housenumber":"3",
    "addr:postcode":"7311 an",
    "addr:street":"Paul Krugerstraat;Gelderland",
    "iso:country":"NL",
    "sg:address":"Paul Krugerstraat 3",
    "sg:city":"Apeldoorn",
    "sg:orig_category":"Verzekeringen",
    "sg:phone":"+31 55 521 4772",
    "sg:postcode":"7311 AN",
    "sg:province":"Gelderland",
    "wof:name":"Ass.- En Financieringskantoor Turkmenill",
    "wof:placetype":"venue"
},
  "geometry": {"coordinates":[5.957657,52.217487],"type":"Point"}
}