{
  "type": "Feature",
  "properties": {
    "iso:country":"NL",
    "sg:address":"Kanaaldijk 63",
    "sg:city":"Watergang",
    "sg:classifiers":[
        {
            "category":"Education",
            "subcategory":"Preschool",
            "type":"Public Place"
        }
    ],
    "sg:phone":"+31 20 436 3228",
    "sg:postcode":"1454 AB",
    "sg:province":"Noord-Holland",
    "sg:tags":[
        "kleuteronderwijs",
        "basis-"
    ],
    "wof:name":"Tiede Bijlsmaschool",
    "wof:placetype":"venue"
},
  "geometry": {"coordinates":[4.951562,52.433739],"type":"Point"}
}