{
  "type": "Feature",
  "properties": {
    "addr:full":"Anemoonstr 1 Scheemda Groningen 9679 EL",
    "addr:housenumber":"1",
    "addr:postcode":"9679 el",
    "addr:street":"Anemoonstr",
    "iso:country":"NL",
    "sg:address":"Anemoonstr 1",
    "sg:city":"Scheemda",
    "sg:orig_category":"Scholen Voor Basisonderwijs",
    "sg:phone":"+31 597 592 917",
    "sg:postcode":"9679 EL",
    "sg:province":"Groningen",
    "wof:name":"Eexter",
    "wof:placetype":"venue"
},
  "geometry": {"coordinates":[6.975522,53.172459],"type":"Point"}
}