{
  "type": "Feature",
  "properties": {
    "addr:full":"Hendrik Veenemanstraat 1 Son Texas 5691 BA",
    "addr:housenumber":"1",
    "addr:postcode":"5691 ba",
    "addr:street":"Hendrik Veenemanstraat;Texas",
    "iso:country":"NL",
    "sg:address":"Hendrik Veenemanstraat 1",
    "sg:city":"Son",
    "sg:orig_category":"Boekhouders",
    "sg:phone":"+31 499 474 155",
    "sg:postcode":"5691 BA",
    "sg:province":"Texas",
    "wof:name":"Adm.-Belastingadviesburo C.M. Lathouwers",
    "wof:placetype":"venue"
},
  "geometry": {"coordinates":[-101.937622,35.189621],"type":"Point"}
}