{
  "type": "Feature",
  "properties": {
    "addr:full":"Eifel 25 Helmond North Brabant 5706 RN",
    "addr:housenumber":"25",
    "addr:postcode":"5706 rn",
    "addr:street":"Eifel",
    "iso:country":"NL",
    "sg:address":"Eifel 25",
    "sg:city":"Helmond",
    "sg:orig_category":"Boekhouders",
    "sg:phone":"+31 492 540 812",
    "sg:postcode":"5706 RN",
    "sg:province":"North Brabant",
    "wof:name":"Administratiekantoor Arts",
    "wof:placetype":"venue"
},
  "geometry": {"coordinates":[5.643324,51.466415],"type":"Point"}
}