{
  "type": "Feature",
  "properties": {
    "addr:full":"J Evertsenwg 34 Schiedam Zuid-Holland 3115 JA",
    "addr:housenumber":"34",
    "addr:postcode":"3115 ja",
    "iso:country":"NL",
    "sg:address":"J Evertsenwg 34",
    "sg:city":"Schiedam",
    "sg:orig_category":"Timmerwerken",
    "sg:phone":"+31 10 273 0083",
    "sg:postcode":"3115 JA",
    "sg:province":"Zuid-Holland",
    "wof:name":"Seybel",
    "wof:placetype":"venue"
},
  "geometry": {"coordinates":[4.380746,51.909294],"type":"Point"}
}