{
  "type": "Feature",
  "properties": {
    "iso:country":"NL",
    "sg:address":"Zuiderdreef 4",
    "sg:city":"Nieuw Vennep",
    "sg:orig_category":"Autokeuringen",
    "sg:phone":"+31 252 689 918",
    "sg:postcode":"2151 CM",
    "sg:province":"Noord-Holland",
    "wof:name":"Langenkamp & Van Steen",
    "wof:placetype":"venue"
},
  "geometry": {"coordinates":[4.627407,52.260967],"type":"Point"}
}