{
  "type": "Feature",
  "properties": {
    "addr:full":"Coevorderstraatweg 11 Noordscheschut Drenthe 7914 TK",
    "addr:housenumber":"11",
    "addr:postcode":"7914 tk",
    "addr:street":"Coevorderstraatweg",
    "iso:country":"NL",
    "sg:address":"Coevorderstraatweg 11",
    "sg:city":"Noordscheschut",
    "sg:orig_category":"Goederenvervoer Over De Weg",
    "sg:phone":"+31 528 341 552",
    "sg:postcode":"7914 TK",
    "sg:province":"Drenthe",
    "wof:name":"J. Bouwmeester Jr.",
    "wof:placetype":"venue"
},
  "geometry": {"coordinates":[6.527899,52.721264],"type":"Point"}
}