{
  "type": "Feature",
  "properties": {
    "addr:full":"Oude Kleefsebaan 84 Berg En Dal Gelderland 6571 BJ",
    "addr:housenumber":"84",
    "addr:postcode":"6571 bj",
    "addr:street":"Oude Kleefsebaan",
    "iso:country":"NL",
    "sg:address":"Oude Kleefsebaan 84",
    "sg:city":"Berg En Dal",
    "sg:orig_category":"Cafetaria'S",
    "sg:phone":"+31 24 684 3856",
    "sg:postcode":"6571 BJ",
    "sg:province":"Gelderland",
    "wof:name":"Yes",
    "wof:placetype":"venue"
},
  "geometry": {"coordinates":[5.920904,51.819874],"type":"Point"}
}