{
  "type": "Feature",
  "properties": {
    "addr:full":"L Bisschopstr 80 Deventer NL.08 7411 KN",
    "addr:housenumber":"80;nl.08",
    "addr:postcode":"7411 kn",
    "iso:country":"NL",
    "sg:address":"L Bisschopstr 80",
    "sg:city":"Deventer",
    "sg:classifiers":[
        {
            "category":"Farming",
            "subcategory":"Fish & Marine Products",
            "type":"Manufacturing & Wholesale Goods"
        }
    ],
    "sg:phone":"+31 570 615 566",
    "sg:postcode":"7411 KN",
    "sg:province":"NL.08",
    "sg:tags":[
        "vi"
    ],
    "wof:name":"Gamba",
    "wof:placetype":"venue"
},
  "geometry": {"coordinates":[6.158609,52.253998],"type":"Point"}
}