{
  "type": "Feature",
  "properties": {
    "addr:full":"Energiewg 2 Harmelen Utrecht 3481 MC",
    "addr:housenumber":"2",
    "addr:postcode":"3481 mc",
    "addr:street":"Energiewg",
    "iso:country":"NL",
    "sg:address":"Energiewg 2",
    "sg:city":"Harmelen",
    "sg:orig_category":"Adviesbureaus Waterbouwkunde",
    "sg:phone":"+31 348 443 408",
    "sg:postcode":"3481 MC",
    "sg:province":"Utrecht",
    "wof:name":"Projekt Engineering",
    "wof:placetype":"venue"
},
  "geometry": {"coordinates":[4.947888,52.100098],"type":"Point"}
}