{
  "type": "Feature",
  "properties": {
    "addr:full":"Topaasstraat 19 Hengelo Ov NL.08 7554 TJ",
    "addr:housenumber":"19",
    "addr:postcode":"7554 tj",
    "addr:street":"Topaasstraat;Ov",
    "iso:country":"NL",
    "sg:address":"Topaasstraat 19",
    "sg:city":"Hengelo Ov",
    "sg:orig_category":"Diverse Bedrijfsinstallaties Gh",
    "sg:phone":"+31 74 243 9080",
    "sg:postcode":"7554 TJ",
    "sg:province":"NL.08",
    "wof:name":"Boensma Brandbeveiliging",
    "wof:placetype":"venue"
},
  "geometry": {"coordinates":[6.777525,52.23798],"type":"Point"}
}