{
  "type": "Feature",
  "properties": {
    "addr:full":"Haltestraat 56 Rilland Zeeland 4411 NH",
    "addr:housenumber":"56",
    "addr:postcode":"4411 nh",
    "addr:street":"Haltestraat",
    "iso:country":"NL",
    "sg:address":"Haltestraat 56",
    "sg:city":"Rilland",
    "sg:orig_category":"Aannemers Woningbouw",
    "sg:phone":"+31 113 552 433",
    "sg:postcode":"4411 NH",
    "sg:province":"Zeeland",
    "wof:name":"Aannemingsbedrijf J.W.J. Goossens",
    "wof:placetype":"venue"
},
  "geometry": {"coordinates":[4.161164,51.422401],"type":"Point"}
}