{
  "type": "Feature",
  "properties": {
    "addr:full":"Dinkelln 14A Heemstede Noord-Holland 2105 VL",
    "addr:housenumber":"14a",
    "addr:postcode":"2105 vl",
    "addr:street":"Dinkelln",
    "iso:country":"NL",
    "sg:address":"Dinkelln 14A",
    "sg:city":"Heemstede",
    "sg:orig_category":"Adviesbureaus Bouwkunde",
    "sg:phone":"+31 23 547 6251",
    "sg:postcode":"2105 VL",
    "sg:province":"Noord-Holland",
    "wof:name":"Think Global Bv",
    "wof:placetype":"venue"
},
  "geometry": {"coordinates":[4.621248,52.345287],"type":"Point"}
}