{
  "type": "Feature",
  "properties": {
    "addr:full":"Beatrixstr 10 Oude Tonge South Holland 3255 BA",
    "addr:housenumber":"10",
    "addr:postcode":"3255 ba",
    "addr:street":"Beatrixstr",
    "iso:country":"NL",
    "sg:address":"Beatrixstr 10",
    "sg:city":"Oude Tonge",
    "sg:orig_category":"Afslankinstituten",
    "sg:phone":"+31 187 642 893",
    "sg:postcode":"3255 BA",
    "sg:province":"South Holland",
    "wof:name":"Slank In Ned",
    "wof:placetype":"venue"
},
  "geometry": {"coordinates":[4.216191,51.691231],"type":"Point"}
}