{
  "type": "Feature",
  "properties": {
    "addr:full":"Brinkzicht 3 Baarn Utrecht 3743 EX",
    "addr:housenumber":"3",
    "addr:postcode":"3743 ex",
    "addr:street":"Brinkzicht",
    "iso:country":"NL",
    "sg:address":"Brinkzicht 3",
    "sg:city":"Baarn",
    "sg:orig_category":"Yoga-Instituten",
    "sg:phone":"+31 35 541 5182",
    "sg:postcode":"3743 EX",
    "sg:province":"Utrecht",
    "wof:name":"Ster, Yoga School De",
    "wof:placetype":"venue"
},
  "geometry": {"coordinates":[5.29263,52.211891],"type":"Point"}
}