{
  "type": "Feature",
  "properties": {
    "addr:full":"Nieuwe Gr 37 Haarlem Noord-Holland 2011 NC",
    "addr:housenumber":"37",
    "addr:postcode":"2011 nc",
    "addr:street":"Nieuwe Gr",
    "iso:country":"NL",
    "sg:address":"Nieuwe Gr 37",
    "sg:city":"Haarlem",
    "sg:orig_category":"Advocaten En Advocatenkantoren",
    "sg:phone":"+31 23 553 4969",
    "sg:postcode":"2011 NC",
    "sg:province":"Noord-Holland",
    "sg:website":"http://www.goppeladvocaten.nl",
    "wof:name":"Goppel Advocaten",
    "wof:placetype":"venue"
},
  "geometry": {"coordinates":[4.63429,52.384853],"type":"Point"}
}