{
  "type": "Feature",
  "properties": {
    "addr:full":"Beemdwg 5 Oud Alblas South Holland 2969 CD",
    "addr:housenumber":"5",
    "addr:postcode":"2969 cd",
    "addr:street":"Beemdwg;Oud Alblas",
    "iso:country":"NL",
    "sg:address":"Beemdwg 5",
    "sg:city":"Oud Alblas",
    "sg:orig_category":"Kinderopvang",
    "sg:phone":"+31 184 691 943",
    "sg:postcode":"2969 CD",
    "sg:province":"South Holland",
    "wof:name":"Regenboog, De",
    "wof:placetype":"venue"
},
  "geometry": {"coordinates":[4.703875,51.85862],"type":"Point"}
}