{
  "type": "Feature",
  "properties": {
    "addr:full":"Reeweg 78 Hendrik Ido Ambacht Zuid-Holland 3342 AC",
    "addr:housenumber":"78",
    "addr:postcode":"ido ambacht;3342 ac",
    "addr:street":"Reeweg",
    "iso:country":"NL",
    "sg:address":"Reeweg 78",
    "sg:city":"Hendrik Ido Ambacht",
    "sg:orig_category":"Kappers",
    "sg:phone":"+31 78 681 7508",
    "sg:postcode":"3342 AC",
    "sg:province":"Zuid-Holland",
    "wof:name":"Vof Herenkapsalon Breur",
    "wof:placetype":"venue"
},
  "geometry": {"coordinates":[4.630628,51.845619],"type":"Point"}
}