{
  "type": "Feature",
  "properties": {
    "addr:full":"O L Vrouwestr 21 Zegge Noord-Brabant 4735 SL",
    "addr:housenumber":"21",
    "addr:postcode":"4735 sl",
    "addr:street":"O;Zegge",
    "iso:country":"NL",
    "sg:address":"O L Vrouwestr 21",
    "sg:city":"Zegge",
    "sg:orig_category":"Adviesbureaus Elektrotechniek",
    "sg:phone":"+31 165 570 401",
    "sg:postcode":"4735 SL",
    "sg:province":"Noord-Brabant",
    "wof:name":"Pesman, Engineering",
    "wof:placetype":"venue"
},
  "geometry": {"coordinates":[4.512649,51.54768],"type":"Point"}
}