{
  "type": "Feature",
  "properties": {
    "addr:full":"Keizerstr 3 Bis Utrecht Utrecht 3512 EA",
    "addr:housenumber":"3 bis",
    "addr:postcode":"3512 ea",
    "addr:street":"Keizerstr",
    "iso:country":"NL",
    "sg:address":"Keizerstr 3 Bis",
    "sg:city":"Utrecht",
    "sg:orig_category":"Verenigingen En Stichtingen",
    "sg:phone":"+31 30 230 0331",
    "sg:postcode":"3512 EA",
    "sg:province":"Utrecht",
    "wof:name":"Yaoyi, Sticht",
    "wof:placetype":"venue"
},
  "geometry": {"coordinates":[5.124814,52.09317],"type":"Point"}
}