{
  "type": "Feature",
  "properties": {
    "iso:country":"NL",
    "sg:address":"Mycene 1",
    "sg:city":"Amersfoort",
    "sg:orig_category":"Adviesbureaus Bedrijfsorganisatie",
    "sg:phone":"+31 33 456 2513",
    "sg:postcode":"3823 KS",
    "sg:province":"Utrecht",
    "wof:name":"Pmd",
    "wof:placetype":"venue"
},
  "geometry": {"coordinates":[5.388883,52.188663],"type":"Point"}
}