{
  "type": "Feature",
  "properties": {
    "addr:full":"Pallietergaarde 232 Apeldoorn Gelderland 7329 HC",
    "addr:housenumber":"232",
    "addr:postcode":"7329 hc",
    "addr:street":"Pallietergaarde;Gelderland",
    "iso:country":"NL",
    "sg:address":"Pallietergaarde 232",
    "sg:city":"Apeldoorn",
    "sg:orig_category":"Verenigingen En Stichtingen",
    "sg:phone":"+31 55 542 1619",
    "sg:postcode":"7329 HC",
    "sg:province":"Gelderland",
    "wof:name":"Avwo",
    "wof:placetype":"venue"
},
  "geometry": {"coordinates":[5.999985,52.199741],"type":"Point"}
}