{
  "type": "Feature",
  "properties": {
    "addr:full":"Populierenlaan 3 Hattem Gelderland 8051 DA",
    "addr:housenumber":"3",
    "addr:postcode":"8051 da",
    "addr:street":"Populierenlaan;Gelderland",
    "iso:country":"NL",
    "sg:address":"Populierenlaan 3",
    "sg:city":"Hattem",
    "sg:orig_category":"Accountants - Administratie- Consulenten En -Kantoren",
    "sg:phone":"+31 38 444 7206",
    "sg:postcode":"8051 DA",
    "sg:province":"Gelderland",
    "wof:name":"Holt Associates, L Van'T",
    "wof:placetype":"venue"
},
  "geometry": {"coordinates":[6.072562,52.466702],"type":"Point"}
}