{
  "type": "Feature",
  "properties": {
    "addr:full":"Groenewg 77 S Gravenzande South Holland 2691 MK",
    "addr:housenumber":"77",
    "addr:postcode":"2691",
    "addr:street":"Groenewg;S Gravenzande",
    "iso:country":"NL",
    "sg:address":"Groenewg 77",
    "sg:city":"S Gravenzande",
    "sg:orig_category":"Bloemen En Planten",
    "sg:phone":"+31 174 614 473",
    "sg:postcode":"2691 MK",
    "sg:province":"South Holland",
    "wof:name":"Uffelen, Firma Van",
    "wof:placetype":"venue"
},
  "geometry": {"coordinates":[4.197482,51.980949],"type":"Point"}
}