{
  "type": "Feature",
  "properties": {
    "addr:full":"Nyverheidswg 10 Harmelen Utrecht 3481 MB",
    "addr:housenumber":"10",
    "addr:postcode":"3481 mb",
    "addr:street":"Nyverheidswg",
    "iso:country":"NL",
    "sg:address":"Nyverheidswg 10",
    "sg:city":"Harmelen",
    "sg:orig_category":"Kunststof Ramen",
    "sg:phone":"+31 348 443 514",
    "sg:postcode":"3481 MB",
    "sg:province":"Utrecht",
    "sg:website":"http://www.bermon.nl",
    "wof:name":"Bermon",
    "wof:placetype":"venue"
},
  "geometry": {"coordinates":[4.94498,52.101292],"type":"Point"}
}