{
  "type": "Feature",
  "properties": {
    "addr:full":"Holterbergweide 32 Helmond Noord-Brabant 5709 MP",
    "addr:housenumber":"32",
    "addr:postcode":"5709 mp",
    "addr:street":"Holterbergweide",
    "iso:country":"NL",
    "sg:address":"Holterbergweide 32",
    "sg:city":"Helmond",
    "sg:orig_category":"Adviesbureaus Bouwkunde",
    "sg:phone":"+31 492 511 642",
    "sg:postcode":"5709 MP",
    "sg:province":"Noord-Brabant",
    "wof:name":"Bloks, Architectenbureau A J M",
    "wof:placetype":"venue"
},
  "geometry": {"coordinates":[5.688554,51.490299],"type":"Point"}
}