{
  "type": "Feature",
  "properties": {
    "iso:country":"NL",
    "sg:address":"Laakkd 317",
    "sg:city":"S Gravenhage",
    "sg:orig_category":"Onderhoudswerken",
    "sg:phone":"+31 70 396 8079",
    "sg:postcode":"2521 XR",
    "sg:province":"South Holland",
    "wof:name":"Nideco",
    "wof:placetype":"venue"
},
  "geometry": {"coordinates":[4.32071,52.062988],"type":"Point"}
}