{
  "type": "Feature",
  "properties": {
    "iso:country":"NL",
    "sg:address":"Rykel 21",
    "sg:city":"Beesel",
    "sg:orig_category":"Verenigingen En Stichtingen",
    "sg:phone":"+31 77 476 2913",
    "sg:postcode":"5954 NJ",
    "sg:province":"Limburg",
    "sg:website":"http://www.slowfood.nl",
    "wof:name":"Slow Food Limburg",
    "wof:placetype":"venue"
},
  "geometry": {"coordinates":[6.020865,51.256229],"type":"Point"}
}