{
  "type": "Feature",
  "properties": {
    "addr:full":"Aaltensewg 11D Zelhem Gelderland 7021 HR",
    "addr:housenumber":"11d",
    "addr:postcode":"7021 hr",
    "addr:street":"Aaltensewg;Gelderland",
    "iso:country":"NL",
    "sg:address":"Aaltensewg 11D",
    "sg:city":"Zelhem",
    "sg:orig_category":"Jeugdherbergen",
    "sg:phone":"+31 314 627 282",
    "sg:postcode":"7021 HR",
    "sg:province":"Gelderland",
    "sg:website":"http://www.dewitteherberg.nl",
    "wof:name":"Witte Herberg, De",
    "wof:placetype":"venue"
},
  "geometry": {"coordinates":[6.388183,52.011047],"type":"Point"}
}