{
  "type": "Feature",
  "properties": {
    "addr:full":"Neptunus 13 Ulft Gelderland 7071 VH",
    "addr:housenumber":"13",
    "addr:postcode":"7071 vh",
    "addr:street":"Neptunus;Gelderland",
    "iso:country":"NL",
    "sg:address":"Neptunus 13",
    "sg:city":"Ulft",
    "sg:orig_category":"Adviesbureaus Bouwkunde",
    "sg:phone":"+31 315 683 087",
    "sg:postcode":"7071 VH",
    "sg:province":"Gelderland",
    "wof:name":"Wanders Bv",
    "wof:placetype":"venue"
},
  "geometry": {"coordinates":[6.379923,51.884254],"type":"Point"}
}