{
  "type": "Feature",
  "properties": {
    "addr:full":"Adelbert Van Scharnln D 2 Maastricht Limburg 6226 EG",
    "addr:housenumber":"2",
    "addr:postcode":"6226 eg",
    "addr:street":"Adelbert Van Scharnln D",
    "iso:country":"NL",
    "sg:address":"Adelbert Van Scharnln D 2",
    "sg:city":"Maastricht",
    "sg:orig_category":"Autoverhuur",
    "sg:phone":"+31 43 362 2200",
    "sg:postcode":"6226 EG",
    "sg:province":"Limburg",
    "wof:name":"Bert Van Slijpe Autoverhuur",
    "wof:placetype":"venue"
},
  "geometry": {"coordinates":[5.727111,50.845894],"type":"Point"}
}