{
  "type": "Feature",
  "properties": {
    "addr:full":"Hortensiastraat 49 Wolvega Friesland 8471 KK",
    "addr:housenumber":"49",
    "addr:postcode":"8471 kk",
    "addr:street":"Hortensiastraat",
    "iso:country":"NL",
    "sg:address":"Hortensiastraat 49",
    "sg:city":"Wolvega",
    "sg:orig_category":"Bejaardeninstellingen And Serviceflats",
    "sg:phone":"+31 561 614 715",
    "sg:postcode":"8471 KK",
    "sg:province":"Friesland",
    "wof:name":"Stichting Lindestede Lokatie Verzorgingshuis",
    "wof:placetype":"venue"
},
  "geometry": {"coordinates":[5.99809,52.87521],"type":"Point"}
}