{
  "type": "Feature",
  "properties": {
    "iso:country":"NL",
    "sg:address":"Zuiderdorpstr 7",
    "sg:city":"Velsen Zuid",
    "sg:orig_category":"Architecten En Architectenbureaus",
    "sg:phone":"+31 255 517 871",
    "sg:postcode":"1981 BG",
    "sg:province":"Noord-Holland",
    "wof:name":"Schaafsma Bv, Siem",
    "wof:placetype":"venue"
},
  "geometry": {"coordinates":[4.647471,52.461796],"type":"Point"}
}