{
  "type": "Feature",
  "properties": {
    "addr:full":"Vlasakkerlaan 28 Hellevoetsluis Zuid-Holland 3224 VK",
    "addr:housenumber":"28",
    "addr:postcode":"3224 vk",
    "addr:street":"Vlasakkerlaan",
    "iso:country":"NL",
    "sg:address":"Vlasakkerlaan 28",
    "sg:city":"Hellevoetsluis",
    "sg:orig_category":"Elektronische Bedrijfsinstallaties",
    "sg:phone":"+31 181 314 786",
    "sg:postcode":"3224 VK",
    "sg:province":"Zuid-Holland",
    "wof:name":"Van Duuren Security",
    "wof:placetype":"venue"
},
  "geometry": {"coordinates":[4.144996,51.825562],"type":"Point"}
}