{
  "type": "Feature",
  "properties": {
    "iso:country":"NL",
    "sg:address":"Vijverlaan 53",
    "sg:city":"Epe",
    "sg:orig_category":"Bedrijfs- And Managementsconsultants",
    "sg:phone":"+31 578 620 781",
    "sg:postcode":"8162 NB",
    "sg:province":"Gelderland",
    "wof:name":"Demaris Bv",
    "wof:placetype":"venue"
},
  "geometry": {"coordinates":[5.976725,52.368927],"type":"Point"}
}