{
  "type": "Feature",
  "properties": {
    "addr:full":"Westewagenstraat 66 Rotterdam South Holland 3011 AT",
    "addr:housenumber":"66",
    "addr:postcode":"3011",
    "addr:street":"Westewagenstraat",
    "iso:country":"NL",
    "sg:address":"Westewagenstraat 66",
    "sg:city":"Rotterdam",
    "sg:orig_category":"Hoger Onderwijs",
    "sg:phone":"+31 10 240 0986",
    "sg:postcode":"3011 AT",
    "sg:province":"South Holland",
    "wof:name":"Doc",
    "wof:placetype":"venue"
},
  "geometry": {"coordinates":[4.483008,51.921211],"type":"Point"}
}