{
  "type": "Feature",
  "properties": {
    "addr:full":"Eindhovensewg 102 Waalre Noord-Brabant 5582 HW",
    "addr:housenumber":"102",
    "addr:postcode":"5582 hw",
    "iso:country":"NL",
    "sg:address":"Eindhovensewg 102",
    "sg:city":"Waalre",
    "sg:orig_category":"Meubelmakerijen",
    "sg:phone":"+31 6 51197976",
    "sg:postcode":"5582 HW",
    "sg:province":"Noord-Brabant",
    "wof:name":"Maris",
    "wof:placetype":"venue"
},
  "geometry": {"coordinates":[5.478328,51.397812],"type":"Point"}
}