{
  "type": "Feature",
  "properties": {
    "addr:full":"Wheeweg 33 Goor Overijssel 7471 EV",
    "addr:housenumber":"33",
    "addr:postcode":"7471 ev",
    "addr:street":"Wheeweg",
    "iso:country":"NL",
    "sg:address":"Wheeweg 33",
    "sg:city":"Goor",
    "sg:orig_category":"Metaalbekleding And -Behandeling",
    "sg:phone":"+31 547 275 972",
    "sg:postcode":"7471 EV",
    "sg:province":"Overijssel",
    "wof:name":"Esge Verspaning",
    "wof:placetype":"venue"
},
  "geometry": {"coordinates":[6.580076,52.243149],"type":"Point"}
}