{
  "type": "Feature",
  "properties": {
    "addr:full":"Ringstr 75 Schoonoord Drenthe 7848 EA",
    "addr:housenumber":"75",
    "addr:postcode":"7848 ea",
    "addr:street":"Ringstr",
    "iso:country":"NL",
    "sg:address":"Ringstr 75",
    "sg:city":"Schoonoord",
    "sg:orig_category":"Montagebedrijven",
    "sg:phone":"+31 591 387 177",
    "sg:postcode":"7848 EA",
    "sg:province":"Drenthe",
    "wof:name":"Boegheim Montagebedrijf",
    "wof:placetype":"venue"
},
  "geometry": {"coordinates":[6.749227,52.847595],"type":"Point"}
}