{
  "type": "Feature",
  "properties": {
    "iso:country":"NL",
    "sg:address":"Grotestraat 238",
    "sg:city":"Nijverdal",
    "sg:orig_category":"Damesmodezaken",
    "sg:phone":"+31 548 612 316",
    "sg:postcode":"7443 BV",
    "sg:province":"Overijssel",
    "wof:name":"Modehuis J.H. Konijnenbelt Bv",
    "wof:placetype":"venue"
},
  "geometry": {"coordinates":[6.455876,52.365807],"type":"Point"}
}