{
  "type": "Feature",
  "properties": {
    "iso:country":"NL",
    "sg:address":"Noorderhaven Nz 31",
    "sg:city":"Groningen",
    "sg:orig_category":"Kunsthandel",
    "sg:phone":"+31 50 313 2121",
    "sg:postcode":"9712 VG",
    "sg:province":"Groningen",
    "sg:website":"http://www.artdunoord.nl",
    "wof:name":"Art Du Nord",
    "wof:placetype":"venue"
},
  "geometry": {"coordinates":[6.559779,53.22533],"type":"Point"}
}