{
  "type": "Feature",
  "properties": {
    "addr:full":"Bosschendk 209 Oudenbosch Noord-Brabant 4731 DD",
    "addr:housenumber":"209",
    "addr:postcode":"4731 dd",
    "iso:country":"NL",
    "sg:address":"Bosschendk 209",
    "sg:city":"Oudenbosch",
    "sg:orig_category":"Glas, Porselein En Aardewerk",
    "sg:phone":"+31 165 320 388",
    "sg:postcode":"4731 DD",
    "sg:province":"Noord-Brabant",
    "wof:name":"Marians Glas Galerie",
    "wof:placetype":"venue"
},
  "geometry": {"coordinates":[4.556216,51.588932],"type":"Point"}
}