{
  "type": "Feature",
  "properties": {
    "addr:full":"Prof Teldersstr 10 Vlaardingen Zuid-Holland 3132 AZ",
    "addr:housenumber":"10",
    "addr:postcode":"3132 az",
    "iso:country":"NL",
    "sg:address":"Prof Teldersstr 10",
    "sg:city":"Vlaardingen",
    "sg:orig_category":"Verenigingen En Stichtingen",
    "sg:phone":"+31 10 435 9514",
    "sg:postcode":"3132 AZ",
    "sg:province":"Zuid-Holland",
    "wof:name":"Telder Wijkcentr, De",
    "wof:placetype":"venue"
},
  "geometry": {"coordinates":[4.319654,51.90752],"type":"Point"}
}