{
  "type": "Feature",
  "properties": {
    "addr:full":"Akeleiwg 113 Groningen Groningen 9731 JC",
    "addr:housenumber":"113",
    "addr:postcode":"9731 jc",
    "iso:country":"NL",
    "sg:address":"Akeleiwg 113",
    "sg:city":"Groningen",
    "sg:classifiers":[
        {
            "category":"Retail",
            "subcategory":"Auto Repair",
            "type":"Services"
        }
    ],
    "sg:phone":"+31 50 549 0188",
    "sg:postcode":"9731 JC",
    "sg:province":"Groningen",
    "sg:tags":[
        "garage"
    ],
    "wof:name":"Groenendal",
    "wof:placetype":"venue"
},
  "geometry": {"coordinates":[6.600483,53.233807],"type":"Point"}
}