{
  "type": "Feature",
  "properties": {
    "iso:country":"NL",
    "sg:address":"Dwingelowg 68",
    "sg:city":"Winschoten",
    "sg:orig_category":"Fietsen En Bromfietsen Onderdelen - Fabr. En Grooth",
    "sg:phone":"+31 597 416 002",
    "sg:postcode":"9671 KG",
    "sg:province":"Groningen",
    "wof:name":"Blaauw",
    "wof:placetype":"venue"
},
  "geometry": {"coordinates":[7.025928,53.145939],"type":"Point"}
}