{
  "type": "Feature",
  "properties": {
    "iso:country":"NL",
    "sg:address":"Stationsstraat 38",
    "sg:city":"Schinnen",
    "sg:orig_category":"Autokeuringen",
    "sg:phone":"+31 46 443 1815",
    "sg:postcode":"6365 CK",
    "sg:province":"Limburg",
    "wof:name":"Jetten Motorenrevisie",
    "wof:placetype":"venue"
},
  "geometry": {"coordinates":[5.881022,50.938694],"type":"Point"}
}