{
  "type": "Feature",
  "properties": {
    "addr:full":"Barlosewg 2A Aalten Gelderland 7122 PT",
    "addr:housenumber":"2a",
    "addr:postcode":"7122",
    "addr:street":"Barlosewg;Gelderland;Pt",
    "iso:country":"NL",
    "sg:address":"Barlosewg 2A",
    "sg:city":"Aalten",
    "sg:orig_category":"Voetverzorging",
    "sg:phone":"+31 543 475 212",
    "sg:postcode":"7122 PT",
    "sg:province":"Gelderland",
    "wof:name":"Grotenhuis, M",
    "wof:placetype":"venue"
},
  "geometry": {"coordinates":[6.577638,51.933079],"type":"Point"}
}