{
  "type": "Feature",
  "properties": {
    "iso:country":"NL",
    "sg:address":"Langs De Baan 16",
    "sg:city":"Uithoorn",
    "sg:orig_category":"Bloemen En Planten - Decoratie",
    "sg:phone":"+31 297 531 078",
    "sg:postcode":"1422 KX",
    "sg:province":"Noord-Holland",
    "wof:name":"Fluks, Patricia",
    "wof:placetype":"venue"
},
  "geometry": {"coordinates":[4.815653,52.25333],"type":"Point"}
}