{
  "type": "Feature",
  "properties": {
    "addr:full":"Salmstr 2/A Geleen Limburg 6161 EM",
    "addr:housenumber":"2 / a",
    "addr:postcode":"6161 em",
    "addr:street":"Salmstr",
    "iso:country":"NL",
    "sg:address":"Salmstr 2/A",
    "sg:city":"Geleen",
    "sg:orig_category":"Boeken En Tijdschriften",
    "sg:phone":"+31 46 474 0111",
    "sg:postcode":"6161 EM",
    "sg:province":"Limburg",
    "wof:name":"Pandora",
    "wof:placetype":"venue"
},
  "geometry": {"coordinates":[5.828226,50.968964],"type":"Point"}
}