{
  "type": "Feature",
  "properties": {
    "addr:full":"Kon Wilhelminastr 21 Borculo Gelderland 7271 GS",
    "addr:housenumber":"21",
    "addr:postcode":"7271 gs",
    "addr:street":"Kon Wilhelminastr;Gelderland",
    "iso:country":"NL",
    "sg:address":"Kon Wilhelminastr 21",
    "sg:city":"Borculo",
    "sg:orig_category":"Kermisexploitatie",
    "sg:phone":"+31 545 273 503",
    "sg:postcode":"7271 GS",
    "sg:province":"Gelderland",
    "wof:name":"Suikerspin, De",
    "wof:placetype":"venue"
},
  "geometry": {"coordinates":[6.515405,52.11438],"type":"Point"}
}