{
  "type": "Feature",
  "properties": {
    "iso:country":"NL",
    "sg:address":"Willibrordusstr 1",
    "sg:city":"Buren Fr",
    "sg:orig_category":"Vakantieverblijven",
    "sg:phone":"+31 519 543 100",
    "sg:postcode":"9164 KT",
    "sg:province":"Provincie Friesland",
    "wof:name":"Metz, Fa A C En J",
    "wof:placetype":"venue"
},
  "geometry": {"coordinates":[5.797406,53.446903],"type":"Point"}
}