{
  "type": "Feature",
  "properties": {
    "addr:full":"Veenstr 9 Ysselmuiden Overijssel 8271 VP",
    "addr:housenumber":"9",
    "addr:postcode":"8271 vp",
    "addr:street":"Veenstr;Overijssel",
    "iso:country":"NL",
    "sg:address":"Veenstr 9",
    "sg:city":"Ysselmuiden",
    "sg:orig_category":"Lijstenmakerijen",
    "sg:phone":"+31 38 332 1990",
    "sg:postcode":"8271 VP",
    "sg:province":"Overijssel",
    "wof:name":"Kanis Vof, H J",
    "wof:placetype":"venue"
},
  "geometry": {"coordinates":[5.928244,52.566532],"type":"Point"}
}