{
  "type": "Feature",
  "properties": {
    "addr:full":"Bedryfswg 3 Maasbommel Gelderland 6627 BC",
    "addr:housenumber":"3",
    "addr:postcode":"6627 bc",
    "addr:street":"Bedryfswg;Gelderland",
    "iso:country":"NL",
    "sg:address":"Bedryfswg 3",
    "sg:city":"Maasbommel",
    "sg:orig_category":"Loodgieters",
    "sg:phone":"+31 487 562 523",
    "sg:postcode":"6627 BC",
    "sg:province":"Gelderland",
    "wof:name":"Vuister",
    "wof:placetype":"venue"
},
  "geometry": {"coordinates":[5.532789,51.823971],"type":"Point"}
}