{
  "type": "Feature",
  "properties": {
    "iso:country":"NL",
    "sg:address":"Bedryfswg 3",
    "sg:city":"Maasbommel",
    "sg:orig_category":"Loodgieters",
    "sg:phone":"+31 487 562 523",
    "sg:postcode":"6627 BC",
    "sg:province":"Gelderland",
    "wof:name":"Vuister",
    "wof:placetype":"venue"
},
  "geometry": {"coordinates":[5.532789,51.823971],"type":"Point"}
}