{
  "type": "Feature",
  "properties": {
    "iso:country":"NL",
    "sg:address":"Dorpsstraat 224",
    "sg:city":"Scherpenzeel Gld",
    "sg:orig_category":"Kunst And Kunstenaarsbenodigdheden",
    "sg:phone":"+31 33 277 1933",
    "sg:postcode":"3925 KJ",
    "sg:province":"Gelderland",
    "wof:name":"Kunsthandel G. En G.",
    "wof:placetype":"venue"
},
  "geometry": {"coordinates":[5.485625,52.079552],"type":"Point"}
}