{
  "type": "Feature",
  "properties": {
    "addr:full":"De Lind 20 Oisterwyk North Brabant 5061 HW",
    "addr:housenumber":"20",
    "addr:postcode":"5061 hw",
    "addr:street":"De Lind",
    "iso:country":"NL",
    "sg:address":"De Lind 20",
    "sg:city":"Oisterwyk",
    "sg:orig_category":"Pensioenen",
    "sg:phone":"+31 13 523 3111",
    "sg:postcode":"5061 HW",
    "sg:province":"North Brabant",
    "sg:website":"http://www.pensioendesk.nl",
    "wof:name":"Pensioendesk",
    "wof:placetype":"venue"
},
  "geometry": {"coordinates":[5.196512,51.580631],"type":"Point"}
}