{
  "type": "Feature",
  "properties": {
    "addr:full":"D Dekkerln 1B Papendrecht South Holland 3351 CH",
    "addr:housenumber":"1b",
    "addr:postcode":"3351",
    "iso:country":"NL",
    "sg:address":"D Dekkerln 1B",
    "sg:city":"Papendrecht",
    "sg:orig_category":"Fitnesscentra",
    "sg:phone":"+31 78 641 1758",
    "sg:postcode":"3351 CH",
    "sg:province":"South Holland",
    "sg:website":"http://www.fitvision.nl",
    "wof:name":"Fitvision",
    "wof:placetype":"venue"
},
  "geometry": {"coordinates":[4.683685,51.826294],"type":"Point"}
}