{
  "type": "Feature",
  "properties": {
    "iso:country":"NL",
    "sg:address":"Handelscentrum 12",
    "sg:city":"Winterswijk",
    "sg:orig_category":"Woningbouwverenigingen",
    "sg:phone":"+31 543 546 363",
    "sg:postcode":"7102 AL",
    "sg:province":"Gelderland",
    "wof:name":"Stichting De Woonplaats",
    "wof:placetype":"venue"
},
  "geometry": {"coordinates":[6.7098808289,51.9704551697],"type":"Point"}
}