{
  "type": "Feature",
  "properties": {
    "addr:full":"Juniusstraat 62 Hoorn Nh North Holland 1624 XE",
    "addr:housenumber":"62",
    "addr:postcode":"1624 xe",
    "addr:street":"Juniusstraat;Nh North",
    "iso:country":"NL",
    "sg:address":"Juniusstraat 62",
    "sg:city":"Hoorn Nh",
    "sg:orig_category":"Verzekeringen",
    "sg:phone":"+31 229 210 679",
    "sg:postcode":"1624 XE",
    "sg:province":"North Holland",
    "wof:name":"Secar",
    "wof:placetype":"venue"
},
  "geometry": {"coordinates":[5.05898,52.649296],"type":"Point"}
}