{
  "type": "Feature",
  "properties": {
    "addr:full":"Hugo De Vrieslaan 25 Amsterdam North Holland 1097 EE",
    "addr:housenumber":"25",
    "addr:postcode":"1097 ee",
    "addr:street":"Hugo De Vrieslaan",
    "iso:country":"NL",
    "sg:address":"Hugo De Vrieslaan 25",
    "sg:city":"Amsterdam",
    "sg:orig_category":"Kappers",
    "sg:phone":"+31 20 694 2418",
    "sg:postcode":"1097 EE",
    "sg:province":"North Holland",
    "wof:name":"Professional Hairstyling M.H.A. Van Der Horst",
    "wof:placetype":"venue"
},
  "geometry": {"coordinates":[4.934423,52.349991],"type":"Point"}
}