{
  "type": "Feature",
  "properties": {
    "addr:full":"Schrans 100 Leeuwarden Friesland 8932 NH",
    "addr:housenumber":"100",
    "addr:postcode":"8932 nh",
    "addr:street":"Schrans",
    "iso:country":"NL",
    "sg:address":"Schrans 100",
    "sg:city":"Leeuwarden",
    "sg:orig_category":"Metaalwerken",
    "sg:phone":"+31 58 213 6862",
    "sg:postcode":"8932 NH",
    "sg:province":"Friesland",
    "wof:name":"* Jansma Gordijnen En Zonwering",
    "wof:placetype":"venue"
},
  "geometry": {"coordinates":[5.796878,53.189331],"type":"Point"}
}