{
  "type": "Feature",
  "properties": {
    "addr:full":"Den Hof 106 Waalre North Brabant 5582 JZ",
    "addr:housenumber":"106",
    "addr:postcode":"5582 jz",
    "addr:street":"Den Hof",
    "iso:country":"NL",
    "sg:address":"Den Hof 106",
    "sg:city":"Waalre",
    "sg:classifiers":[
        {
            "category":"Shopping",
            "subcategory":"Adult",
            "type":"Retail Goods"
        }
    ],
    "sg:phone":"+31 40 221 7008",
    "sg:postcode":"5582 JZ",
    "sg:province":"North Brabant",
    "sg:tags":[
        "lingerie",
        "en",
        "tricotage"
    ],
    "wof:name":"Middelink Textiel",
    "wof:placetype":"venue"
},
  "geometry": {"coordinates":[5.476466,51.395416],"type":"Point"}
}