{
  "type": "Feature",
  "properties": {
    "addr:full":"Rooseveltstr 57 Leiden South Holland 2321 BL",
    "addr:housenumber":"57",
    "addr:postcode":"2321 bl",
    "addr:street":"Rooseveltstr",
    "iso:country":"NL",
    "sg:address":"Rooseveltstr 57",
    "sg:city":"Leiden",
    "sg:orig_category":"Levensmiddelen - Fabrieken En Groothandel",
    "sg:phone":"+31 71 572 1460",
    "sg:postcode":"2321 BL",
    "sg:province":"South Holland",
    "wof:name":"Sligro Bv",
    "wof:placetype":"venue"
},
  "geometry": {"coordinates":[4.481496,52.143372],"type":"Point"}
}