{
  "type": "Feature",
  "properties": {
    "iso:country":"NL",
    "sg:address":"Rooseveltstr 57",
    "sg:city":"Leiden",
    "sg:orig_category":"Levensmiddelen - Fabrieken En Groothandel",
    "sg:phone":"+31 71 572 1460",
    "sg:postcode":"2321 BL",
    "sg:province":"South Holland",
    "wof:name":"Sligro Bv",
    "wof:placetype":"venue"
},
  "geometry": {"coordinates":[4.481496,52.143372],"type":"Point"}
}