{
  "type": "Feature",
  "properties": {
    "addr:full":"Kerkstr 69 Renkum Gelderland 6871 BJ",
    "addr:housenumber":"69",
    "addr:postcode":"6871 bj",
    "addr:street":"Kerkstr;Gelderland",
    "iso:country":"NL",
    "sg:address":"Kerkstr 69",
    "sg:city":"Renkum",
    "sg:orig_category":"Automaterialen En Gereedschappen",
    "sg:phone":"+31 317 316 784",
    "sg:postcode":"6871 BJ",
    "sg:province":"Gelderland",
    "wof:name":"Renkumse Automaterialen",
    "wof:placetype":"venue"
},
  "geometry": {"coordinates":[5.731074,51.976059],"type":"Point"}
}