{
  "type": "Feature",
  "properties": {
    "addr:full":"Titus Brandsmastraat 73 Oldenzaal Overijssel 7572 CH",
    "addr:housenumber":"73",
    "addr:postcode":"7572",
    "addr:street":"Titus Brandsmastraat",
    "iso:country":"NL",
    "sg:address":"Titus Brandsmastraat 73",
    "sg:city":"Oldenzaal",
    "sg:orig_category":"Bedrijfs- And Managementsconsultants",
    "sg:phone":"+31 541 521 011",
    "sg:postcode":"7572 CH",
    "sg:province":"Overijssel",
    "wof:name":"Werk Aan De Winkel",
    "wof:placetype":"venue"
},
  "geometry": {"coordinates":[6.919594,52.307995],"type":"Point"}
}