{
  "type": "Feature",
  "properties": {
    "iso:country":"NL",
    "sg:address":"Brederoln 112",
    "sg:city":"Eindhoven",
    "sg:orig_category":"Psychosociale Therapeuten",
    "sg:phone":"+31 40 257 3013",
    "sg:postcode":"5615 KK",
    "sg:province":"Noord-Brabant",
    "wof:name":"Tilborg, Mevr T Van",
    "wof:placetype":"venue"
},
  "geometry": {"coordinates":[5.467838,51.427582],"type":"Point"}
}