{
  "type": "Feature",
  "properties": {
    "iso:country":"NL",
    "sg:address":"Hemstukken 36",
    "sg:city":"Eelde",
    "sg:orig_category":"Psychologen",
    "sg:phone":"+31 50 309 5533",
    "sg:postcode":"9761 KM",
    "sg:province":"Provincie Drenthe",
    "wof:name":"Groot, P De",
    "wof:placetype":"venue"
},
  "geometry": {"coordinates":[6.550878,53.141327],"type":"Point"}
}