{
  "type": "Feature",
  "properties": {
    "iso:country":"NL",
    "sg:address":"Grt Staat 5",
    "sg:city":"Maastricht",
    "sg:orig_category":"Verzekeringen - Verzekeringskantoren",
    "sg:phone":"+31 43 329 0580",
    "sg:postcode":"6211 CT",
    "sg:province":"Limburg",
    "wof:name":"Vendopolis Bv",
    "wof:placetype":"venue"
},
  "geometry": {"coordinates":[5.692074,50.849739],"type":"Point"}
}