{
  "type": "Feature",
  "properties": {
    "addr:full":"De Gouwe 26 B Dronten Flevoland 8253 PA",
    "addr:housenumber":"26 b",
    "addr:postcode":"8253",
    "addr:street":"De Gouwe;Flevoland",
    "iso:country":"NL",
    "sg:address":"De Gouwe 26 B",
    "sg:city":"Dronten",
    "sg:orig_category":"Horren",
    "sg:phone":"+31 321 339 867",
    "sg:postcode":"8253 PA",
    "sg:province":"Flevoland",
    "wof:name":"Keje Bv",
    "wof:placetype":"venue"
},
  "geometry": {"coordinates":[5.6981,52.53915],"type":"Point"}
}