{
  "type": "Feature",
  "properties": {
    "addr:full":"Wolphaertsbocht 105 Rotterdam Zuid-Holland 3082 AG",
    "addr:housenumber":"105",
    "addr:postcode":"3082",
    "addr:street":"Wolphaertsbocht",
    "iso:country":"NL",
    "sg:address":"Wolphaertsbocht 105",
    "sg:city":"Rotterdam",
    "sg:orig_category":"Apotheken",
    "sg:phone":"+31 10 429 0983",
    "sg:postcode":"3082 AG",
    "sg:province":"Zuid-Holland",
    "sg:website":"http://www.charloische-apotheek.nl",
    "wof:name":"Charloische Apotheek",
    "wof:placetype":"venue"
},
  "geometry": {"coordinates":[4.470503,51.892212],"type":"Point"}
}