{
  "type": "Feature",
  "properties": {
    "addr:full":"Haarlemmerstr 218 Leiden Zuid-Holland 2312 GJ",
    "addr:housenumber":"218",
    "addr:postcode":"2312 gj",
    "iso:country":"NL",
    "sg:address":"Haarlemmerstr 218",
    "sg:city":"Leiden",
    "sg:orig_category":"Acupunctuur",
    "sg:phone":"+31 71 513 2101",
    "sg:postcode":"2312 GJ",
    "sg:province":"Zuid-Holland",
    "wof:name":"Wenmaster Euro Bv",
    "wof:placetype":"venue"
},
  "geometry": {"coordinates":[4.495992,52.160698],"type":"Point"}
}