{
  "type": "Feature",
  "properties": {
    "addr:full":"Stapelerweg 12 De Wijk Provincie Drenthe 7957 NB",
    "addr:housenumber":"12",
    "addr:postcode":"7957 nb",
    "addr:street":"Stapelerweg;Drenthe",
    "iso:country":"NL",
    "sg:address":"Stapelerweg 12",
    "sg:city":"De Wijk",
    "sg:orig_category":"Loodgieterswerk, Verwarming And Sanitaire Installaties",
    "sg:phone":"+31 522 443 206",
    "sg:postcode":"7957 NB",
    "sg:province":"Provincie Drenthe",
    "wof:name":"J. Stille",
    "wof:placetype":"venue"
},
  "geometry": {"coordinates":[6.33273,52.663231],"type":"Point"}
}