{
  "type": "Feature",
  "properties": {
    "addr:full":"Heemraadsweide 5-7 Nieuwegein Utrecht 3437 CA",
    "addr:housenumber":"5-7",
    "addr:postcode":"3437 ca",
    "addr:street":"Heemraadsweide",
    "iso:country":"NL",
    "sg:address":"Heemraadsweide 5-7",
    "sg:city":"Nieuwegein",
    "sg:orig_category":"Scholen Voor Basisonderwijs",
    "sg:phone":"+31 30 603 5935",
    "sg:postcode":"3437 CA",
    "sg:province":"Utrecht",
    "sg:website":"http://www.pen.nl/onderwijs/veldakker.nl",
    "wof:name":"Veldrakker, De",
    "wof:placetype":"venue"
},
  "geometry": {"coordinates":[5.073852,52.040997],"type":"Point"}
}