{
  "type": "Feature",
  "properties": {
    "addr:full":"Wilhelminaln 3 De Bilt Utrecht 3732 GJ",
    "addr:housenumber":"3",
    "addr:postcode":"3732 gj",
    "addr:street":"Wilhelminaln",
    "iso:country":"NL",
    "sg:address":"Wilhelminaln 3",
    "sg:city":"De Bilt",
    "sg:orig_category":"Woningbouw- Verenigingen En -Stichtingen",
    "sg:phone":"+31 30 220 4704",
    "sg:postcode":"3732 GJ",
    "sg:province":"Utrecht",
    "sg:website":"http://www.habion.nl",
    "wof:name":"Habion",
    "wof:placetype":"venue"
},
  "geometry": {"coordinates":[5.1778321266,52.1027183533],"type":"Point"}
}