{
  "type": "Feature",
  "properties": {
    "iso:country":"NL",
    "sg:address":"Vliet 12",
    "sg:city":"Tiel",
    "sg:orig_category":"Journalisten Freelance",
    "sg:phone":"+31 6 20086171",
    "sg:postcode":"4007 RH",
    "sg:province":"Gelderland",
    "wof:name":"Js",
    "wof:placetype":"venue"
},
  "geometry": {"coordinates":[5.389422,51.868164],"type":"Point"}
}