{
  "type": "Feature",
  "properties": {
    "addr:full":"Dorpsstr 12A Doorn Utrecht 3941 JM",
    "addr:housenumber":"12a",
    "addr:postcode":"3941 jm",
    "addr:street":"Dorpsstr",
    "iso:country":"NL",
    "sg:address":"Dorpsstr 12A",
    "sg:city":"Doorn",
    "sg:orig_category":"Koel- En Vriestransporten",
    "sg:phone":"+31 343 415 020",
    "sg:postcode":"3941 JM",
    "sg:province":"Utrecht",
    "wof:name":"Baltictrans Bv",
    "wof:placetype":"venue"
},
  "geometry": {"coordinates":[5.346412,52.033192],"type":"Point"}
}