{
  "type": "Feature",
  "properties": {
    "iso:country":"NL",
    "sg:address":"Noodweg 52",
    "sg:city":"Hilversum",
    "sg:classifiers":[
        {
            "category":"Fast Food",
            "type":"Food & Drink"
        }
    ],
    "sg:phone":"+31 35 577 1696",
    "sg:postcode":"1213 PZ",
    "sg:province":"North Holland",
    "sg:tags":[
        "afhaal",
        "restaurant"
    ],
    "wof:name":"Egelshoek Bv",
    "wof:placetype":"venue"
},
  "geometry": {"coordinates":[5.155242,52.193226],"type":"Point"}
}