{
  "type": "Feature",
  "properties": {
    "addr:full":"Drechtstr 97 Leiden South Holland 2314 TC",
    "addr:housenumber":"97",
    "addr:postcode":"2314 tc",
    "addr:street":"Drechtstr",
    "iso:country":"NL",
    "sg:address":"Drechtstr 97",
    "sg:city":"Leiden",
    "sg:orig_category":"Kunsthandel",
    "sg:phone":"+31 71 541 2835",
    "sg:postcode":"2314 TC",
    "sg:province":"South Holland",
    "wof:name":"Feijt",
    "wof:placetype":"venue"
},
  "geometry": {"coordinates":[4.519334,52.151814],"type":"Point"}
}