{
  "type": "Feature",
  "properties": {
    "iso:country":"NL",
    "sg:address":"Drechtstr 97",
    "sg:city":"Leiden",
    "sg:orig_category":"Kunsthandel",
    "sg:phone":"+31 71 541 2835",
    "sg:postcode":"2314 TC",
    "sg:province":"South Holland",
    "wof:name":"Feijt",
    "wof:placetype":"venue"
},
  "geometry": {"coordinates":[4.519334,52.151814],"type":"Point"}
}