{
  "type": "Feature",
  "properties": {
    "iso:country":"NL",
    "sg:address":"1E Keucheniusstr 13 Hs",
    "sg:city":"Amsterdam",
    "sg:orig_category":"Beeldende Kunstenaars",
    "sg:phone":"+31 20 486 7722",
    "sg:postcode":"1051 HN",
    "sg:province":"Noord-Holland",
    "wof:name":"Stel, Peter",
    "wof:placetype":"venue"
},
  "geometry": {"coordinates":[4.87107,52.37925],"type":"Point"}
}