{
  "type": "Feature",
  "properties": {
    "iso:country":"NL",
    "sg:address":"Cattenbroekerdk 13B",
    "sg:city":"Woerden",
    "sg:classifiers":[
        {
            "category":"Home & Garden",
            "subcategory":"Garden Supply",
            "type":"Retail Goods"
        }
    ],
    "sg:phone":"+31 348 434 240",
    "sg:postcode":"3446 HA",
    "sg:province":"Utrecht",
    "sg:tags":[
        "zand",
        "en",
        "grind"
    ],
    "wof:name":"Laurum",
    "wof:placetype":"venue"
},
  "geometry": {"coordinates":[4.915484,52.077747],"type":"Point"}
}