{
  "type": "Feature",
  "properties": {
    "addr:full":"Eindhovenseweg 57 Geldrop Noord-Brabant 5664 HD",
    "addr:housenumber":"57",
    "addr:postcode":"5664 hd",
    "addr:street":"Eindhovenseweg",
    "iso:country":"NL",
    "sg:address":"Eindhovenseweg 57",
    "sg:city":"Geldrop",
    "sg:orig_category":"Kappers",
    "sg:phone":"+31 40 285 9253",
    "sg:postcode":"5664 HD",
    "sg:province":"Noord-Brabant",
    "wof:name":"Kapsalon Colinda",
    "wof:placetype":"venue"
},
  "geometry": {"coordinates":[5.5474758148,51.4243774414],"type":"Point"}
}