{
  "type": "Feature",
  "properties": {
    "iso:country":"NL",
    "sg:address":"Joop Den Uyllaan 5",
    "sg:city":"Leiden",
    "sg:orig_category":"Boekhouders",
    "sg:phone":"+31 71 589 9033",
    "sg:postcode":"2314 GC",
    "sg:province":"Zuid-Holland",
    "wof:name":"Evh",
    "wof:placetype":"venue"
},
  "geometry": {"coordinates":[4.516434,52.157581],"type":"Point"}
}