{
  "type": "Feature",
  "properties": {
    "addr:full":"Bevryding 43 Aalten Gelderland 7121 WP",
    "addr:housenumber":"43",
    "addr:postcode":"7121 wp",
    "addr:street":"Bevryding;Gelderland",
    "iso:country":"NL",
    "sg:address":"Bevryding 43",
    "sg:city":"Aalten",
    "sg:orig_category":"Koel- En Vriestransporten",
    "sg:phone":"+31 543 476 136",
    "sg:postcode":"7121 WP",
    "sg:province":"Gelderland",
    "wof:name":"Soyer",
    "wof:placetype":"venue"
},
  "geometry": {"coordinates":[6.594242,51.922523],"type":"Point"}
}