{
  "type": "Feature",
  "properties": {
    "addr:full":"Europaweg 26 Vleuten Utrecht 3451 HG",
    "addr:housenumber":"26",
    "addr:postcode":"3451 hg",
    "addr:street":"Europaweg",
    "iso:country":"NL",
    "sg:address":"Europaweg 26",
    "sg:city":"Vleuten",
    "sg:orig_category":"Bloemen And Planten",
    "sg:phone":"+31 30 677 1922",
    "sg:postcode":"3451 HG",
    "sg:province":"Utrecht",
    "wof:name":"G.P.J. Den Hollander Potplanten Bv",
    "wof:placetype":"venue"
},
  "geometry": {"coordinates":[5.016528,52.097267],"type":"Point"}
}