{
  "type": "Feature",
  "properties": {
    "addr:full":"Havenstr 28 Schiedam South Holland 3115 HD",
    "addr:housenumber":"28",
    "addr:postcode":"3115 hd",
    "addr:street":"Havenstr",
    "iso:country":"NL",
    "sg:address":"Havenstr 28",
    "sg:city":"Schiedam",
    "sg:orig_category":"Watersportartikelen",
    "sg:phone":"+31 10 473 9897",
    "sg:postcode":"3115 HD",
    "sg:province":"South Holland",
    "sg:website":"http://www.jetsports.nl",
    "wof:name":"Jet Sports Europe",
    "wof:placetype":"venue"
},
  "geometry": {"coordinates":[4.3981351852,51.9012718201],"type":"Point"}
}