{
  "type": "Feature",
  "properties": {
    "addr:full":"Westerstraat 41 Enkhuizen Noord-Holland 1601 AB",
    "addr:housenumber":"41",
    "addr:postcode":"1601 ab",
    "addr:street":"Westerstraat",
    "iso:country":"NL",
    "sg:address":"Westerstraat 41",
    "sg:city":"Enkhuizen",
    "sg:orig_category":"Opticiens",
    "sg:phone":"+31 228 312 002",
    "sg:postcode":"1601 AB",
    "sg:province":"Noord-Holland",
    "wof:name":"Van Der Klei Opticiens",
    "wof:placetype":"venue"
},
  "geometry": {"coordinates":[5.2919988632,52.7042312622],"type":"Point"}
}