{
  "type": "Feature",
  "properties": {
    "addr:full":"Roothaanstr 19 Eindhoven Noord-Brabant 5643 PW",
    "addr:housenumber":"19",
    "addr:postcode":"5643 pw",
    "addr:street":"Roothaanstr",
    "iso:country":"NL",
    "sg:address":"Roothaanstr 19",
    "sg:city":"Eindhoven",
    "sg:orig_category":"Verzekeringen - Verzekeringskantoren",
    "sg:phone":"+31 40 211 4385",
    "sg:postcode":"5643 PW",
    "sg:province":"Noord-Brabant",
    "wof:name":"Plompen, R G C",
    "wof:placetype":"venue"
},
  "geometry": {"coordinates":[5.501509,51.425404],"type":"Point"}
}