{
  "type": "Feature",
  "properties": {
    "addr:full":"Industrieterrein 1201 Bergen Lb Missouri 5854 NE",
    "addr:housenumber":"1201",
    "addr:postcode":"5854 ne",
    "addr:street":"Industrieterrein",
    "iso:country":"NL",
    "sg:address":"Industrieterrein 1201",
    "sg:city":"Bergen Lb",
    "sg:orig_category":"Kantoorartikelen",
    "sg:phone":"+31 485 342 102",
    "sg:postcode":"5854 NE",
    "sg:province":"Missouri",
    "wof:name":"Maro Kantoormeubelen",
    "wof:placetype":"venue"
},
  "geometry": {"coordinates":[-93.1299362183,36.7056617737],"type":"Point"}
}