{
  "type": "Feature",
  "properties": {
    "addr:full":"Industriew 6 Moergestel Noord-Brabant 5066 XJ",
    "addr:housenumber":"6",
    "addr:postcode":"5066 xj",
    "addr:street":"Industriew",
    "iso:country":"NL",
    "sg:address":"Industriew 6",
    "sg:city":"Moergestel",
    "sg:orig_category":"Schoenen - Fabrieken",
    "sg:phone":"+31 13 513 2233",
    "sg:postcode":"5066 XJ",
    "sg:province":"Noord-Brabant",
    "wof:name":"Berkelmans Bv",
    "wof:placetype":"venue"
},
  "geometry": {"coordinates":[5.178399,51.548779],"type":"Point"}
}