{
  "type": "Feature",
  "properties": {
    "addr:full":"V Schuylenb Str 64 Delft Zuid-Holland 2614 CB",
    "addr:housenumber":"64",
    "addr:postcode":"2614 cb",
    "addr:street":"Str",
    "iso:country":"NL",
    "sg:address":"V Schuylenb Str 64",
    "sg:city":"Delft",
    "sg:orig_category":"Kappers",
    "sg:phone":"+31 15 212 3192",
    "sg:postcode":"2614 CB",
    "sg:province":"Zuid-Holland",
    "wof:name":"Velden, Van Der",
    "wof:placetype":"venue"
},
  "geometry": {"coordinates":[4.35869,52.011505],"type":"Point"}
}