{
  "type": "Feature",
  "properties": {
    "addr:full":"Sportlaan 147 Purmerend Noord-Holland 1442 EC",
    "addr:housenumber":"147",
    "addr:postcode":"1442 ec",
    "addr:street":"Sportlaan",
    "iso:country":"NL",
    "sg:address":"Sportlaan 147",
    "sg:city":"Purmerend",
    "sg:orig_category":"Diverse Opleidingen And Onderwijs",
    "sg:phone":"+31 299 471 936",
    "sg:postcode":"1442 EC",
    "sg:province":"Noord-Holland",
    "wof:name":"Avo-Bedrijf Opleidingen",
    "wof:placetype":"venue"
},
  "geometry": {"coordinates":[4.965831,52.51458],"type":"Point"}
}