{
  "type": "Feature",
  "properties": {
    "iso:country":"NL",
    "sg:address":"Nieuwe Nonnendaalseweg 153",
    "sg:city":"Nijmegen",
    "sg:orig_category":"Wegen And Sportterreinen",
    "sg:phone":"+31 24 373 0068",
    "sg:postcode":"6542 PE",
    "sg:province":"Gelderland",
    "wof:name":"Ronnie Tel Bestratingen",
    "wof:placetype":"venue"
},
  "geometry": {"coordinates":[5.8432297707,51.8404159546],"type":"Point"}
}