{
  "type": "Feature",
  "properties": {
    "addr:full":"Postbaan 50 Prinsenbeek Noord-Brabant 4841 KL",
    "addr:housenumber":"50",
    "addr:postcode":"4841 kl",
    "addr:street":"Postbaan",
    "iso:country":"NL",
    "sg:address":"Postbaan 50",
    "sg:city":"Prinsenbeek",
    "sg:orig_category":"Adviesbureaus Bedrijfsorganisatie",
    "sg:phone":"+31 76 543 9383",
    "sg:postcode":"4841 KL",
    "sg:province":"Noord-Brabant",
    "wof:name":"Vomc",
    "wof:placetype":"venue"
},
  "geometry": {"coordinates":[4.709913,51.610443],"type":"Point"}
}