{
  "type": "Feature",
  "properties": {
    "addr:full":"Karperveen 541 Spijkenisse South Holland 3205 HE",
    "addr:housenumber":"541",
    "addr:postcode":"3205 he",
    "addr:street":"Karperveen",
    "iso:country":"NL",
    "sg:address":"Karperveen 541",
    "sg:city":"Spijkenisse",
    "sg:orig_category":"Boekhouders",
    "sg:phone":"+31 181 641 246",
    "sg:postcode":"3205 HE",
    "sg:province":"South Holland",
    "wof:name":"Administratie- En Advieskantoor J.M. Tro",
    "wof:placetype":"venue"
},
  "geometry": {"coordinates":[4.348855,51.831745],"type":"Point"}
}