{
  "type": "Feature",
  "properties": {
    "addr:full":"Beijerlandsestraat 37 Rotterdam South Holland 3074 RB",
    "addr:housenumber":"37",
    "addr:postcode":"3074 rb",
    "addr:street":"Beijerlandsestraat",
    "iso:country":"NL",
    "sg:address":"Beijerlandsestraat 37",
    "sg:city":"Rotterdam",
    "sg:orig_category":"Werving And Selectie Van Tijdelijk Personeel And Uitzendkantoren",
    "sg:phone":"+31 10 432 8858",
    "sg:postcode":"3074 RB",
    "sg:province":"South Holland",
    "wof:name":"Dio",
    "wof:placetype":"venue"
},
  "geometry": {"coordinates":[4.5132060051,51.8963127136],"type":"Point"}
}