{
  "type": "Feature",
  "properties": {
    "addr:full":"Industriestraat 42 Haaksbergen Overijssel 7482 EZ",
    "addr:housenumber":"42",
    "addr:postcode":"7482 ez",
    "addr:street":"Industriestraat",
    "iso:country":"NL",
    "sg:address":"Industriestraat 42",
    "sg:city":"Haaksbergen",
    "sg:orig_category":"Fotostudio'S And Fotografen",
    "sg:phone":"+31 53 572 6154",
    "sg:postcode":"7482 EZ",
    "sg:province":"Overijssel",
    "wof:name":"Michiel Ter Haar",
    "wof:placetype":"venue"
},
  "geometry": {"coordinates":[6.719201,52.151142],"type":"Point"}
}