{
  "type": "Feature",
  "properties": {
    "iso:country":"NL",
    "sg:address":"Bachstr 155",
    "sg:city":"Capelle Ad Yssel",
    "sg:orig_category":"Administratie- En Boekhoudkantoren",
    "sg:phone":"+31 10 447 2333",
    "sg:postcode":"2901 JZ",
    "sg:province":"Zuid-Holland",
    "wof:name":"Brug Cv, De",
    "wof:placetype":"venue"
},
  "geometry": {"coordinates":[4.56571,51.921383],"type":"Point"}
}