{
  "type": "Feature",
  "properties": {
    "addr:full":"Pottenbakkersweg 3 Woerden Utrecht 3449 HZ",
    "addr:housenumber":"3",
    "addr:postcode":"3449 hz",
    "addr:street":"Pottenbakkersweg",
    "iso:country":"NL",
    "sg:address":"Pottenbakkersweg 3",
    "sg:city":"Woerden",
    "sg:orig_category":"Meubelzaken, Woning- And Keukeninrichting",
    "sg:phone":"+31 348 410 877",
    "sg:postcode":"3449 HZ",
    "sg:province":"Utrecht",
    "wof:name":"Banz Bord International",
    "wof:placetype":"venue"
},
  "geometry": {"coordinates":[4.857801,52.086147],"type":"Point"}
}