{
  "type": "Feature",
  "properties": {
    "iso:country":"NL",
    "sg:address":"E Du Perronstraat 10",
    "sg:city":"Weesp",
    "sg:orig_category":"Reinigingsdiensten",
    "sg:phone":"+31 294 412 712",
    "sg:postcode":"1382 TA",
    "sg:province":"North Holland",
    "wof:name":"Brouwer & Gerard",
    "wof:placetype":"venue"
},
  "geometry": {"coordinates":[5.040773,52.312653],"type":"Point"}
}