{
  "type": "Feature",
  "properties": {
    "addr:full":"Dijkgraafplein 181 Amsterdam Noord-Holland 1069 EN",
    "addr:housenumber":"181",
    "addr:postcode":"1069 en",
    "addr:street":"Dijkgraafplein",
    "iso:country":"NL",
    "sg:address":"Dijkgraafplein 181",
    "sg:city":"Amsterdam",
    "sg:classifiers":[
        {
            "category":"Fast Food",
            "type":"Food & Drink"
        }
    ],
    "sg:phone":"+31 20 610 1333",
    "sg:postcode":"1069 EN",
    "sg:province":"Noord-Holland",
    "sg:tags":[
        "afhaal",
        "restaurant"
    ],
    "wof:name":"Restaurant Royal City",
    "wof:placetype":"venue"
},
  "geometry": {"coordinates":[4.786191,52.355137],"type":"Point"}
}