{
  "type": "Feature",
  "properties": {
    "addr:full":"Juliana Van Stolbergstr 56 Castricum North Holland 1901 CH",
    "addr:housenumber":"56",
    "addr:postcode":"1901",
    "addr:street":"Juliana Van Stolbergstr",
    "iso:country":"NL",
    "sg:address":"Juliana Van Stolbergstr 56",
    "sg:city":"Castricum",
    "sg:orig_category":"Loodgieterswerk, Verwarming And Sanitaire Installaties",
    "sg:phone":"+31 251 652 924",
    "sg:postcode":"1901 CH",
    "sg:province":"North Holland",
    "wof:name":"Loodgietersbedrijf Lammers En Toepoel Vof",
    "wof:placetype":"venue"
},
  "geometry": {"coordinates":[4.670209,52.551872],"type":"Point"}
}