{
  "type": "Feature",
  "properties": {
    "addr:full":"Dordrechtweg 31016 Deventer Missouri 7418 CH",
    "addr:postcode":"31016;7418",
    "addr:street":"Dordrechtweg",
    "iso:country":"NL",
    "sg:address":"Dordrechtweg 31016",
    "sg:city":"Deventer",
    "sg:orig_category":"Goederenvervoer Over De Weg",
    "sg:phone":"+31 570 623 091",
    "sg:postcode":"7418 CH",
    "sg:province":"Missouri",
    "wof:name":"De Roos Internationaal Transport Bv",
    "wof:placetype":"venue"
},
  "geometry": {"coordinates":[-89.21163199999999,36.820946],"type":"Point"}
}