{
  "type": "Feature",
  "properties": {
    "iso:country":"NL",
    "sg:address":"Ringdijk 402",
    "sg:city":"Ridderkerk",
    "sg:orig_category":"Hek- En Rasterwerken",
    "sg:phone":"+31 180 413 908",
    "sg:postcode":"2983 GS",
    "sg:province":"South Holland",
    "sg:website":"http://www.hekenpoort.nl",
    "wof:name":"Hek En Poort Bv",
    "wof:placetype":"venue"
},
  "geometry": {"coordinates":[4.615294,51.887379],"type":"Point"}
}