{
  "type": "Feature",
  "properties": {
    "iso:country":"NL",
    "sg:address":"Rembrandtln 18A",
    "sg:city":"Bilthoven",
    "sg:orig_category":"Elektronica - Ontwikkeling En Groothandel",
    "sg:phone":"+31 30 229 1504",
    "sg:postcode":"3723 BJ",
    "sg:province":"Utrecht",
    "wof:name":"El-Contronic Bv",
    "wof:placetype":"venue"
},
  "geometry": {"coordinates":[5.200787,52.130032],"type":"Point"}
}