{
  "type": "Feature",
  "properties": {
    "addr:full":"Dreef 8 Zutphen Gelderland 7202 AG",
    "addr:housenumber":"8",
    "addr:postcode":"7202",
    "addr:street":"Dreef;Gelderland",
    "iso:country":"NL",
    "sg:address":"Dreef 8",
    "sg:city":"Zutphen",
    "sg:orig_category":"Metaalvrije Afvalrecycling",
    "sg:phone":"+31 575 516 979",
    "sg:postcode":"7202 AG",
    "sg:province":"Gelderland",
    "wof:name":"Van Gansewinkel Papier Bv",
    "wof:placetype":"venue"
},
  "geometry": {"coordinates":[6.195705,52.147747],"type":"Point"}
}