{
  "type": "Feature",
  "properties": {
    "addr:full":"Sarphatistraat 54 Amsterdam North Holland 1018 GP",
    "addr:housenumber":"54",
    "addr:postcode":"1018 gp",
    "addr:street":"Sarphatistraat",
    "iso:country":"NL",
    "sg:address":"Sarphatistraat 54",
    "sg:city":"Amsterdam",
    "sg:orig_category":"Boekenuitgeverijen",
    "sg:phone":"+31 20 427 5146",
    "sg:postcode":"1018 GP",
    "sg:province":"North Holland",
    "wof:name":"Info-Cruise",
    "wof:placetype":"venue"
},
  "geometry": {"coordinates":[4.908154,52.361115],"type":"Point"}
}