{
  "type": "Feature",
  "properties": {
    "iso:country":"NL",
    "sg:address":"Gedempte Nieuwesloot 115",
    "sg:city":"Alkmaar",
    "sg:classifiers":[
        {
            "category":"Fast Food",
            "type":"Food & Drink"
        }
    ],
    "sg:phone":"+31 72 520 2630",
    "sg:postcode":"1811 KR",
    "sg:province":"Noord-Holland",
    "sg:tags":[
        "afhaal",
        "restaurant"
    ],
    "wof:name":"Chada Thai",
    "wof:placetype":"venue"
},
  "geometry": {"coordinates":[4.746764,52.632286],"type":"Point"}
}