{
  "type": "Feature",
  "properties": {
    "addr:full":"Industriewg 79 Berkel En Rodenrys South Holland 2651 BC",
    "addr:housenumber":"79",
    "addr:postcode":"2651 bc",
    "addr:street":"Industriewg;Berkel",
    "iso:country":"NL",
    "sg:address":"Industriewg 79",
    "sg:city":"Berkel En Rodenrys",
    "sg:orig_category":"Elektrotechnische Installatiebureaus",
    "sg:phone":"+31 10 511 3766",
    "sg:postcode":"2651 BC",
    "sg:province":"South Holland",
    "wof:name":"Pruisken Bv, H H",
    "wof:placetype":"venue"
},
  "geometry": {"coordinates":[4.454691,51.982098],"type":"Point"}
}