{
  "type": "Feature",
  "properties": {
    "iso:country":"NL",
    "sg:address":"Oeverkruid 18",
    "sg:city":"Raamsdonksveer",
    "sg:orig_category":"Chemische Producten Gh",
    "sg:phone":"+31 162 577 170",
    "sg:postcode":"4941 VV",
    "sg:province":"Noord-Brabant",
    "wof:name":"Nychem Benelux",
    "wof:placetype":"venue"
},
  "geometry": {"coordinates":[4.884629,51.709183],"type":"Point"}
}