{
  "type": "Feature",
  "properties": {
    "addr:full":"Rode Klaver 79 Sneek Friesland 8607 EK",
    "addr:housenumber":"79",
    "addr:postcode":"8607 ek",
    "addr:street":"Rode Klaver",
    "iso:country":"NL",
    "sg:address":"Rode Klaver 79",
    "sg:city":"Sneek",
    "sg:orig_category":"Wijnkoperijen En -Groothandel",
    "sg:phone":"+31 515 411 336",
    "sg:postcode":"8607 EK",
    "sg:province":"Friesland",
    "wof:name":"Pfneisel, J F",
    "wof:placetype":"venue"
},
  "geometry": {"coordinates":[5.6613240242,53.0210266113],"type":"Point"}
}