{
  "type": "Feature",
  "properties": {
    "addr:full":"Heelsumseweg 24 Bennekom Gelderland 6721 GS",
    "addr:housenumber":"24",
    "addr:postcode":"6721 gs",
    "addr:street":"Heelsumseweg;Gelderland",
    "iso:country":"NL",
    "sg:address":"Heelsumseweg 24",
    "sg:city":"Bennekom",
    "sg:orig_category":"Farmaceutische Producten Gh",
    "sg:phone":"+31 318 418 441",
    "sg:postcode":"6721 GS",
    "sg:province":"Gelderland",
    "wof:name":"Vermeulen Farmacie Vof",
    "wof:placetype":"venue"
},
  "geometry": {"coordinates":[5.681828,51.996231],"type":"Point"}
}