{
  "type": "Feature",
  "properties": {
    "iso:country":"NL",
    "sg:address":"De Mildestraat 13",
    "sg:city":"'S Gravenhage",
    "sg:orig_category":"Juridische Dienstverlening",
    "sg:phone":"+31 70 324 5272",
    "sg:postcode":"2596 SV",
    "sg:province":"Zuid-Holland",
    "wof:name":"Mr. Th.W.J.M. Van Nierop Bv",
    "wof:placetype":"venue"
},
  "geometry": {"coordinates":[4.32141,52.097256],"type":"Point"}
}