{
  "type": "Feature",
  "properties": {
    "addr:full":"A De Oudeln 1 Voorburg Zuid-Holland 2273 CW",
    "addr:housenumber":"1",
    "addr:postcode":"2273 cw",
    "addr:street":"A;Oudeln",
    "iso:country":"NL",
    "sg:address":"A De Oudeln 1",
    "sg:city":"Voorburg",
    "sg:orig_category":"Hulpverlening Sociaal",
    "sg:phone":"+31 70 386 3436",
    "sg:postcode":"2273 CW",
    "sg:province":"Zuid-Holland",
    "wof:name":"Kleine Loo, 'T",
    "wof:placetype":"venue"
},
  "geometry": {"coordinates":[4.35977,52.07848],"type":"Point"}
}