{
  "type": "Feature",
  "properties": {
    "addr:full":"Reguliersgr 80 Amsterdam Noord-Holland 1017 LV",
    "addr:housenumber":"80",
    "addr:postcode":"1017",
    "addr:street":"Reguliersgr",
    "iso:country":"NL",
    "sg:address":"Reguliersgr 80",
    "sg:city":"Amsterdam",
    "sg:orig_category":"Kunsthandel",
    "sg:phone":"+31 20 623 7027",
    "sg:postcode":"1017 LV",
    "sg:province":"Noord-Holland",
    "sg:website":"http://www.gallery-lemaire.com",
    "wof:name":"Lemaire Tribal Art",
    "wof:placetype":"venue"
},
  "geometry": {"coordinates":[4.895658,52.362106],"type":"Point"}
}