{
  "type": "Feature",
  "properties": {
    "iso:country":"NL",
    "sg:address":"De Dintel 21",
    "sg:city":"Best",
    "sg:orig_category":"Fruit And Groenten Gh",
    "sg:phone":"+31 499 396 952",
    "sg:postcode":"5684 PS",
    "sg:province":"Noord-Brabant",
    "wof:name":"Groente- En Fruit Tonny Van Rooy",
    "wof:placetype":"venue"
},
  "geometry": {"coordinates":[-101.618134,31.224251],"type":"Point"}
}