{
  "type": "Feature",
  "properties": {
    "iso:country":"NL",
    "sg:address":"Raadhuispln 3",
    "sg:city":"Castricum",
    "sg:orig_category":"Fietsen En Bromfietsen",
    "sg:phone":"+31 251 671 092",
    "sg:postcode":"1902 CA",
    "sg:province":"Noord-Holland",
    "wof:name":"Profile Pro Castricum",
    "wof:placetype":"venue"
},
  "geometry": {"coordinates":[4.6722,52.549461],"type":"Point"}
}