{
  "type": "Feature",
  "properties": {
    "addr:full":"Mauritsln 105 Geleen Limburg 6161 HT",
    "addr:housenumber":"105",
    "addr:postcode":"6161 ht",
    "addr:street":"Geleen Limburg",
    "iso:country":"NL",
    "sg:address":"Mauritsln 105",
    "sg:city":"Geleen",
    "sg:orig_category":"Adviesbureaus",
    "sg:phone":"+31 46 478 9300",
    "sg:postcode":"6161 HT",
    "sg:province":"Limburg",
    "sg:website":"http://www.data4.com",
    "wof:name":"Data 4 Limburg Bv",
    "wof:placetype":"venue"
},
  "geometry": {"coordinates":[5.828143,50.967567],"type":"Point"}
}