{
  "type": "Feature",
  "properties": {
    "iso:country":"NL",
    "sg:address":"Stationsstr 2-4",
    "sg:city":"Middelburg",
    "sg:orig_category":"Verzekeringen - Verzekeringskantoren",
    "sg:phone":"+31 118 615 151",
    "sg:postcode":"4331 JB",
    "sg:province":"Zeeland",
    "sg:website":"http://www.don-risicobeheer.nl",
    "wof:name":"Don Risicobeheer",
    "wof:placetype":"venue"
},
  "geometry": {"coordinates":[3.617433,51.496094],"type":"Point"}
}