{
  "type": "Feature",
  "properties": {
    "addr:full":"Vd Kasteelestr 56 S Gravenzande Zuid-Holland 2691 ZP",
    "addr:housenumber":"56;gravenzande",
    "addr:postcode":"2691 zp",
    "addr:street":"S",
    "iso:country":"NL",
    "sg:address":"Vd Kasteelestr 56",
    "sg:city":"S Gravenzande",
    "sg:orig_category":"Kappers",
    "sg:phone":"+31 174 413 318",
    "sg:postcode":"2691 ZP",
    "sg:province":"Zuid-Holland",
    "wof:name":"Florida",
    "wof:placetype":"venue"
},
  "geometry": {"coordinates":[4.1651439667,52.0020370483],"type":"Point"}
}