{
  "type": "Feature",
  "properties": {
    "addr:full":"Poelenburg 408B Zaandam North Holland 1504 NT",
    "addr:housenumber":"408b",
    "addr:postcode":"1504 nt",
    "addr:street":"Poelenburg",
    "iso:country":"NL",
    "sg:address":"Poelenburg 408B",
    "sg:city":"Zaandam",
    "sg:orig_category":"Verenigingen En Stichtingen",
    "sg:phone":"+31 75 612 1323",
    "sg:postcode":"1504 NT",
    "sg:province":"North Holland",
    "wof:name":"Hicret",
    "wof:placetype":"venue"
},
  "geometry": {"coordinates":[4.854693,52.433655],"type":"Point"}
}