{
  "type": "Feature",
  "properties": {
    "addr:full":"Krachtenveld 1-03 Zeewolde Flevoland 3893 CD",
    "addr:housenumber":"1-03",
    "addr:postcode":"3893 cd",
    "addr:street":"Krachtenveld;Flevoland",
    "iso:country":"NL",
    "sg:address":"Krachtenveld 1-03",
    "sg:city":"Zeewolde",
    "sg:orig_category":"Artsen - Huisartsen",
    "sg:phone":"+31 36 522 3224",
    "sg:postcode":"3893 CD",
    "sg:province":"Flevoland",
    "wof:name":"Bulte, C H",
    "wof:placetype":"venue"
},
  "geometry": {"coordinates":[5.525572,52.331715],"type":"Point"}
}