{
  "type": "Feature",
  "properties": {
    "iso:country":"NL",
    "sg:address":"Buitensngl 90",
    "sg:city":"Oldehove",
    "sg:orig_category":"Adviesbureaus Bedrijfsorganisatie",
    "sg:phone":"+31 594 591 668",
    "sg:postcode":"9883 SK",
    "sg:province":"Groningen",
    "wof:name":"Lowlands",
    "wof:placetype":"venue"
},
  "geometry": {"coordinates":[6.3918,53.300114],"type":"Point"}
}