{
  "type": "Feature",
  "properties": {
    "addr:full":"Boerdamsterweg 19 Middelstum Groningen 9991 BM",
    "addr:housenumber":"19",
    "addr:postcode":"9991 bm",
    "addr:street":"Boerdamsterweg",
    "iso:country":"NL",
    "sg:address":"Boerdamsterweg 19",
    "sg:city":"Middelstum",
    "sg:orig_category":"Verhuur Diversen",
    "sg:phone":"+31 595 552 631",
    "sg:postcode":"9991 BM",
    "sg:province":"Groningen",
    "wof:name":"Untied Attractieverhuur",
    "wof:placetype":"venue"
},
  "geometry": {"coordinates":[6.640461,53.344608],"type":"Point"}
}