{
  "type": "Feature",
  "properties": {
    "iso:country":"NL",
    "sg:address":"Chevalleraustraat 8",
    "sg:city":"Ommen",
    "sg:classifiers":[
        {
            "category":"Education",
            "subcategory":"Preschool",
            "type":"Public Place"
        }
    ],
    "sg:phone":"+31 529 454 102",
    "sg:postcode":"7731 EE",
    "sg:province":"NL.08",
    "sg:tags":[
        "kleuteronderwijs",
        "basis-"
    ],
    "wof:name":"Peuterspeelzaal Peuterleut",
    "wof:placetype":"venue"
},
  "geometry": {"coordinates":[6.419403,52.525352],"type":"Point"}
}