{
  "type": "Feature",
  "properties": {
    "iso:country":"NL",
    "sg:address":"Molendijk 156",
    "sg:city":"Krimpen Aan De Lek",
    "sg:classifiers":[
        {
            "category":"Retail",
            "subcategory":"Auto Repair",
            "type":"Services"
        }
    ],
    "sg:phone":"+31 180 512 361",
    "sg:postcode":"2931 SG",
    "sg:province":"Zuid-Holland",
    "sg:tags":[
        "garage"
    ],
    "wof:name":"Hoogendoorn Bv",
    "wof:placetype":"venue"
},
  "geometry": {"coordinates":[4.599892,51.898937],"type":"Point"}
}