{
  "type": "Feature",
  "properties": {
    "iso:country":"NL",
    "sg:address":"Molenstr 8",
    "sg:city":"Bathmen",
    "sg:orig_category":"Kappers",
    "sg:phone":"+31 570 541 336",
    "sg:postcode":"7437 AH",
    "sg:province":"NL.08",
    "wof:name":"Worp, De",
    "wof:placetype":"venue"
},
  "geometry": {"coordinates":[6.288187,52.250267],"type":"Point"}
}