{
  "type": "Feature",
  "properties": {
    "addr:full":"De Singel 4 Drachten Friesland 9203 XX",
    "addr:housenumber":"4",
    "addr:postcode":"9203 xx",
    "addr:street":"De Singel",
    "iso:country":"NL",
    "sg:address":"De Singel 4",
    "sg:city":"Drachten",
    "sg:orig_category":"Gehandicapten - Hulpmiddelen",
    "sg:phone":"+31 512 522 566",
    "sg:postcode":"9203 XX",
    "sg:province":"Friesland",
    "wof:name":"Boemeltje, Het",
    "wof:placetype":"venue"
},
  "geometry": {"coordinates":[6.106115,53.107029],"type":"Point"}
}