{
  "type": "Feature",
  "properties": {
    "addr:full":"Deurningerstr 171 Hengelo Ov NL.08 7557 HE",
    "addr:housenumber":"171",
    "addr:postcode":"7557 he",
    "addr:street":"Ov",
    "iso:country":"NL",
    "sg:address":"Deurningerstr 171",
    "sg:city":"Hengelo Ov",
    "sg:orig_category":"Kunststof Ramen",
    "sg:phone":"+31 74 250 6430",
    "sg:postcode":"7557 HE",
    "sg:province":"NL.08",
    "wof:name":"Kurebo",
    "wof:placetype":"venue"
},
  "geometry": {"coordinates":[6.807885,52.278969],"type":"Point"}
}