{
  "type": "Feature",
  "properties": {
    "iso:country":"NL",
    "sg:address":"G Bildersstr 2",
    "sg:city":"Deurne",
    "sg:orig_category":"Verpakkingen En Verpakkingsmaterialen",
    "sg:phone":"+31 493 321 471",
    "sg:postcode":"5753 DE",
    "sg:province":"Noord-Brabant",
    "wof:name":"Buck Design",
    "wof:placetype":"venue"
},
  "geometry": {"coordinates":[5.792191,51.453239],"type":"Point"}
}