{
  "type": "Feature",
  "properties": {
    "addr:full":"Leijsenhoek 45-B Oosterhout Nb North Brabant 4901 ER",
    "addr:housenumber":"45-b;nb",
    "addr:postcode":"4901 er",
    "addr:street":"Leijsenhoek",
    "iso:country":"NL",
    "sg:address":"Leijsenhoek 45-B",
    "sg:city":"Oosterhout Nb",
    "sg:orig_category":"Werving And Selectie Van Tijdelijk Personeel And Uitzendkantoren",
    "sg:phone":"+31 162 430 500",
    "sg:postcode":"4901 ER",
    "sg:province":"North Brabant",
    "wof:name":"Multiservice Uitzendbureau",
    "wof:placetype":"venue"
},
  "geometry": {"coordinates":[4.8562498093,51.6430511475],"type":"Point"}
}