{
  "type": "Feature",
  "properties": {
    "iso:country":"NL",
    "sg:address":"Harderwijkerwg 2",
    "sg:city":"Uddel",
    "sg:orig_category":"Kappers",
    "sg:phone":"+31 577 401 436",
    "sg:postcode":"3888 LR",
    "sg:province":"Gelderland",
    "wof:name":"Willy",
    "wof:placetype":"venue"
},
  "geometry": {"coordinates":[5.782448,52.257797],"type":"Point"}
}