{
  "type": "Feature",
  "properties": {
    "addr:full":"Dr Barentsenstr 53A Bergeyk North Brabant 5571 DE",
    "addr:housenumber":"53a",
    "addr:postcode":"5571 de",
    "addr:street":"Bergeyk North",
    "iso:country":"NL",
    "sg:address":"Dr Barentsenstr 53A",
    "sg:city":"Bergeyk",
    "sg:orig_category":"Kunststof Ramen",
    "sg:phone":"+31 497 571 065",
    "sg:postcode":"5571 DE",
    "sg:province":"North Brabant",
    "wof:name":"Freestyle",
    "wof:placetype":"venue"
},
  "geometry": {"coordinates":[5.365268,51.318378],"type":"Point"}
}