{
  "type": "Feature",
  "properties": {
    "iso:country":"NL",
    "sg:address":"Bohrweg 31",
    "sg:city":"Spijkenisse",
    "sg:orig_category":"Goederenvervoer Over De Weg",
    "sg:phone":"+31 181 613 907",
    "sg:postcode":"3208 KP",
    "sg:province":"Zuid-Holland",
    "wof:name":"Fred Bouw International Bv",
    "wof:placetype":"venue"
},
  "geometry": {"coordinates":[4.304352,51.851372],"type":"Point"}
}