{
  "type": "Feature",
  "properties": {
    "addr:full":"Rynsburgstr 72 Amsterdam Noord-Holland 1059 AX",
    "addr:housenumber":"72",
    "addr:postcode":"1059 ax",
    "addr:street":"Rynsburgstr",
    "iso:country":"NL",
    "sg:address":"Rynsburgstr 72",
    "sg:city":"Amsterdam",
    "sg:orig_category":"Meubelmakerijen",
    "sg:phone":"+31 20 694 7272",
    "sg:postcode":"1059 AX",
    "sg:province":"Noord-Holland",
    "wof:name":"Kn\u00f6cke",
    "wof:placetype":"venue"
},
  "geometry": {"coordinates":[4.848352,52.347137],"type":"Point"}
}