{
  "type": "Feature",
  "properties": {
    "addr:full":"3E Rompert 13 S Hertogenbosch Noord-Brabant 5233 AE",
    "addr:housenumber":"13",
    "addr:postcode":"5233 ae",
    "addr:street":"3E Rompert;S",
    "iso:country":"NL",
    "sg:address":"3E Rompert 13",
    "sg:city":"S Hertogenbosch",
    "sg:orig_category":"Adviesbureaus Bedrijfsorganisatie",
    "sg:phone":"+31 73 644 0910",
    "sg:postcode":"5233 AE",
    "sg:province":"Noord-Brabant",
    "sg:website":"http://www.uitkomst.org",
    "wof:name":"Uitkomst",
    "wof:placetype":"venue"
},
  "geometry": {"coordinates":[5.316101,51.714737],"type":"Point"}
}