{
  "type": "Feature",
  "properties": {
    "addr:full":"Raadhuisstr 98A Heemstede North Holland 2101 HJ",
    "addr:housenumber":"98a",
    "addr:postcode":"2101 hj",
    "addr:street":"Raadhuisstr",
    "iso:country":"NL",
    "sg:address":"Raadhuisstr 98A",
    "sg:city":"Heemstede",
    "sg:orig_category":"Bloemen En Planten",
    "sg:phone":"+31 23 528 5522",
    "sg:postcode":"2101 HJ",
    "sg:province":"North Holland",
    "wof:name":"Bloemenhof",
    "wof:placetype":"venue"
},
  "geometry": {"coordinates":[4.621353,52.349602],"type":"Point"}
}