{
  "type": "Feature",
  "properties": {
    "iso:country":"NL",
    "sg:address":"Lekdijk West 30",
    "sg:city":"Wijk Bij Duurstede",
    "sg:classifiers":[
        {
            "category":"Retail",
            "subcategory":"Storage",
            "type":"Services"
        }
    ],
    "sg:phone":"+31 343 571 435",
    "sg:postcode":"3961 MD",
    "sg:province":"Utrecht",
    "sg:tags":[
        "opslag",
        "bewaring"
    ],
    "wof:name":"Gebr Van De Guchte",
    "wof:placetype":"venue"
},
  "geometry": {"coordinates":[5.31021595,51.9622268677],"type":"Point"}
}