{
  "type": "Feature",
  "properties": {
    "addr:full":"Hooidk 11 Vasse Overijssel 7661 RA",
    "addr:housenumber":"11",
    "addr:postcode":"7661 ra",
    "addr:street":"Hooidk",
    "iso:country":"NL",
    "sg:address":"Hooidk 11",
    "sg:city":"Vasse",
    "sg:orig_category":"Bibliotheken En Leeszalen Openbare",
    "sg:phone":"+31 541 680 460",
    "sg:postcode":"7661 RA",
    "sg:province":"Overijssel",
    "wof:name":"Openb Bibliotheek",
    "wof:placetype":"venue"
},
  "geometry": {"coordinates":[-79.281837,35.257744],"type":"Point"}
}