{
  "type": "Feature",
  "properties": {
    "addr:full":"Turftorenstraat 22 Groningen Groningen 9712 BR",
    "addr:housenumber":"22",
    "addr:postcode":"9712 br",
    "addr:street":"Turftorenstraat",
    "iso:country":"NL",
    "sg:address":"Turftorenstraat 22",
    "sg:city":"Groningen",
    "sg:orig_category":"Architecten",
    "sg:phone":"+31 50 314 0023",
    "sg:postcode":"9712 BR",
    "sg:province":"Groningen",
    "wof:name":"Skets Architectuurstudio",
    "wof:placetype":"venue"
},
  "geometry": {"coordinates":[6.56104,53.217979],"type":"Point"}
}