{
  "type": "Feature",
  "properties": {
    "addr:full":"Prunus 12 De Kwakel Noord-Holland 1424 LD",
    "addr:housenumber":"12",
    "addr:postcode":"1424 ld",
    "addr:street":"Prunus",
    "iso:country":"NL",
    "sg:address":"Prunus 12",
    "sg:city":"De Kwakel",
    "sg:orig_category":"Bloemen En Planten - Groothandel",
    "sg:phone":"+31 297 232 623",
    "sg:postcode":"1424 LD",
    "sg:province":"Noord-Holland",
    "wof:name":"Leliveld Groep",
    "wof:placetype":"venue"
},
  "geometry": {"coordinates":[4.7951197624,52.2560844421],"type":"Point"}
}