{
  "type": "Feature",
  "properties": {
    "addr:full":"Langestr 233 Klazienaveen Drenthe 7891 GP",
    "addr:housenumber":"233",
    "addr:postcode":"7891 gp",
    "iso:country":"NL",
    "sg:address":"Langestr 233",
    "sg:city":"Klazienaveen",
    "sg:orig_category":"Bestratingen",
    "sg:phone":"+31 591 312 214",
    "sg:postcode":"7891 GP",
    "sg:province":"Drenthe",
    "wof:name":"Doek, H",
    "wof:placetype":"venue"
},
  "geometry": {"coordinates":[7.014515,52.723499],"type":"Point"}
}