{
  "type": "Feature",
  "properties": {
    "iso:country":"NL",
    "sg:address":"Hengelosestraat 148",
    "sg:city":"Enschede",
    "sg:orig_category":"Meubelzaken, Woning- And Keukeninrichting",
    "sg:phone":"+31 53 431 6301",
    "sg:postcode":"7521 AJ",
    "sg:province":"Overijssel",
    "wof:name":"Waterbed & Boxspringcentrum",
    "wof:placetype":"venue"
},
  "geometry": {"coordinates":[6.879671,52.226864],"type":"Point"}
}