{
  "type": "Feature",
  "properties": {
    "addr:full":"Putstraat 87 Waalwijk Noord-Brabant 5142 RK",
    "addr:housenumber":"87",
    "addr:postcode":"5142 rk",
    "addr:street":"Putstraat",
    "iso:country":"NL",
    "sg:address":"Putstraat 87",
    "sg:city":"Waalwijk",
    "sg:orig_category":"Metaalwerken",
    "sg:phone":"+31 416 564 889",
    "sg:postcode":"5142 RK",
    "sg:province":"Noord-Brabant",
    "wof:name":"Jans Afbouw",
    "wof:placetype":"venue"
},
  "geometry": {"coordinates":[5.075741,51.687916],"type":"Point"}
}