{
  "type": "Feature",
  "properties": {
    "addr:full":"Australiewg 2 Assen Drenthe 9407 TE",
    "addr:housenumber":"2",
    "addr:postcode":"9407 te",
    "addr:street":"Australiewg",
    "iso:country":"NL",
    "sg:address":"Australiewg 2",
    "sg:city":"Assen",
    "sg:orig_category":"Grafisch Ontwerpers",
    "sg:phone":"+31 592 346 846",
    "sg:postcode":"9407 TE",
    "sg:province":"Drenthe",
    "wof:name":"Go Grafisch",
    "wof:placetype":"venue"
},
  "geometry": {"coordinates":[6.569818,53.02496],"type":"Point"}
}