{
  "type": "Feature",
  "properties": {
    "addr:full":"Spanjeweg 28 Bodegraven South Holland 2411 PX",
    "addr:housenumber":"28",
    "addr:postcode":"2411 px",
    "addr:street":"Spanjeweg",
    "iso:country":"NL",
    "sg:address":"Spanjeweg 28",
    "sg:city":"Bodegraven",
    "sg:orig_category":"Bedrijfsinventaris Gh",
    "sg:phone":"+31 172 651 215",
    "sg:postcode":"2411 PX",
    "sg:province":"South Holland",
    "wof:name":"Van Schothorst Food Bv",
    "wof:placetype":"venue"
},
  "geometry": {"coordinates":[4.759503,52.072224],"type":"Point"}
}