{
  "type": "Feature",
  "properties": {
    "iso:country":"NL",
    "sg:address":"Herenweg 105",
    "sg:city":"Zwolle",
    "sg:orig_category":"Auto'S And Voertuigen",
    "sg:phone":"+31 38 454 2910",
    "sg:postcode":"8025 AC",
    "sg:province":"Overijssel",
    "wof:name":"A. Meijer",
    "wof:placetype":"venue"
},
  "geometry": {"coordinates":[6.120402,52.509342],"type":"Point"}
}