{
  "type": "Feature",
  "properties": {
    "addr:full":"Beatrixstr 3 Ryen North Brabant 5121 XG",
    "addr:housenumber":"3",
    "addr:postcode":"5121 xg",
    "addr:street":"Beatrixstr",
    "iso:country":"NL",
    "sg:address":"Beatrixstr 3",
    "sg:city":"Ryen",
    "sg:orig_category":"Kinderactiviteiten",
    "sg:phone":"+31 162 458 413",
    "sg:postcode":"5121 XG",
    "sg:province":"North Brabant",
    "wof:name":"Potpoerie",
    "wof:placetype":"venue"
},
  "geometry": {"coordinates":[4.9197,51.588017],"type":"Point"}
}