{
  "type": "Feature",
  "properties": {
    "addr:full":"De Hg Bongert 1 Zevenaar Gelderland 6903 DA",
    "addr:housenumber":"1",
    "addr:postcode":"6903 da",
    "addr:street":"De Hg Bongert",
    "iso:country":"NL",
    "sg:address":"De Hg Bongert 1",
    "sg:city":"Zevenaar",
    "sg:orig_category":"Bibliotheken En Leeszalen Openbare",
    "sg:phone":"+31 316 523 819",
    "sg:postcode":"6903 DA",
    "sg:province":"Gelderland",
    "sg:website":"http://www.pbcg.nl",
    "wof:name":"Openb Bibliotheek",
    "wof:placetype":"venue"
},
  "geometry": {"coordinates":[6.073811,51.933876],"type":"Point"}
}