{
  "type": "Feature",
  "properties": {
    "addr:full":"Weegbree 21 Reeuwijk Zuid-Holland 2811 RP",
    "addr:housenumber":"21",
    "addr:postcode":"2811 rp",
    "addr:street":"Weegbree",
    "iso:country":"NL",
    "sg:address":"Weegbree 21",
    "sg:city":"Reeuwijk",
    "sg:orig_category":"Boekhouders",
    "sg:phone":"+31 182 395 816",
    "sg:postcode":"2811 RP",
    "sg:province":"Zuid-Holland",
    "wof:name":"Administratiekantoor C.P. Swanenburg",
    "wof:placetype":"venue"
},
  "geometry": {"coordinates":[4.731301,52.048401],"type":"Point"}
}