{
  "type": "Feature",
  "properties": {
    "addr:full":"Schanswg 67 Rotterdam Zuid-Holland 3042 HT",
    "addr:housenumber":"67",
    "addr:postcode":"3042 ht",
    "addr:street":"Schanswg",
    "iso:country":"NL",
    "sg:address":"Schanswg 67",
    "sg:city":"Rotterdam",
    "sg:orig_category":"Meubelmakerijen",
    "sg:phone":"+31 10 437 6341",
    "sg:postcode":"3042 HT",
    "sg:province":"Zuid-Holland",
    "wof:name":"Zijp, S M",
    "wof:placetype":"venue"
},
  "geometry": {"coordinates":[4.4435,51.93362],"type":"Point"}
}