{
  "type": "Feature",
  "properties": {
    "iso:country":"NL",
    "sg:address":"Rotterdamsewg 1",
    "sg:city":"Delft",
    "sg:orig_category":"Psychotherapeuten",
    "sg:phone":"+31 6 23755228",
    "sg:postcode":"2628 AH",
    "sg:province":"Zuid-Holland",
    "wof:name":"Hoogenkamp, Drs S G",
    "wof:placetype":"venue"
},
  "geometry": {"coordinates":[4.362714,52.005932],"type":"Point"}
}