{
  "type": "Feature",
  "properties": {
    "iso:country":"NL",
    "sg:address":"Dalwg 5",
    "sg:city":"Oostvoorne",
    "sg:orig_category":"Wasserijen",
    "sg:phone":"+31 181 481 644",
    "sg:postcode":"3233 KK",
    "sg:province":"South Holland",
    "wof:name":"Meijer, Wasserij",
    "wof:placetype":"venue"
},
  "geometry": {"coordinates":[4.1164941788,51.9112663269],"type":"Point"}
}