{
  "type": "Feature",
  "properties": {
    "iso:country":"NL",
    "sg:address":"Rendementswg 18",
    "sg:city":"Mydrecht",
    "sg:orig_category":"Accountants - Administratie- Consulenten En -Kantoren",
    "sg:phone":"+31 297 283 201",
    "sg:postcode":"3641 SL",
    "sg:province":"Utrecht",
    "wof:name":"Vries Arends En Partn Bv, De",
    "wof:placetype":"venue"
},
  "geometry": {"coordinates":[4.885355,52.208355],"type":"Point"}
}