{
  "type": "Feature",
  "properties": {
    "addr:full":"Raadhuisstraat 28 Hoogerheide Noord-Brabant 4631 NE",
    "addr:housenumber":"28",
    "addr:postcode":"4631 ne",
    "addr:street":"Raadhuisstraat",
    "iso:country":"NL",
    "sg:address":"Raadhuisstraat 28",
    "sg:city":"Hoogerheide",
    "sg:orig_category":"Zuivelproducten",
    "sg:phone":"+31 164 612 364",
    "sg:postcode":"4631 NE",
    "sg:province":"Noord-Brabant",
    "wof:name":"`T Lekker Plekske Kaatje Jans",
    "wof:placetype":"venue"
},
  "geometry": {"coordinates":[4.320345,51.427505],"type":"Point"}
}