{
  "type": "Feature",
  "properties": {
    "iso:country":"NL",
    "sg:address":"Kanaaldk 5",
    "sg:city":"Waddinxveen",
    "sg:orig_category":"Verenigingsgebouwen",
    "sg:phone":"+31 182 610 589",
    "sg:postcode":"2741 PA",
    "sg:province":"South Holland",
    "wof:name":"Gemaal, Het",
    "wof:placetype":"venue"
},
  "geometry": {"coordinates":[4.653095,52.0415],"type":"Point"}
}