{
  "type": "Feature",
  "properties": {
    "addr:full":"Veemarkt 22A Zwolle Overijssel 8011 AH",
    "addr:housenumber":"22a",
    "addr:postcode":"8011 ah",
    "addr:street":"Veemarkt",
    "iso:country":"NL",
    "sg:address":"Veemarkt 22A",
    "sg:city":"Zwolle",
    "sg:orig_category":"Visspeciaalzaken",
    "sg:phone":"+31 38 421 1409",
    "sg:postcode":"8011 AH",
    "sg:province":"Overijssel",
    "wof:name":"G Timmerman",
    "wof:placetype":"venue"
},
  "geometry": {"coordinates":[6.083671,52.510715],"type":"Point"}
}