{
  "type": "Feature",
  "properties": {
    "iso:country":"NL",
    "sg:address":"Symfoniestraat 156",
    "sg:city":"Nijmegen",
    "sg:orig_category":"Dierenspeciaalzaken",
    "sg:phone":"+31 24 377 5533",
    "sg:postcode":"6544 TM",
    "sg:province":"Gelderland",
    "wof:name":"Dierenspeciaalzaak Het Honk",
    "wof:placetype":"venue"
},
  "geometry": {"coordinates":[5.813174,51.830448],"type":"Point"}
}