{
  "type": "Feature",
  "properties": {
    "addr:full":"Burg Hermansstr 2 Landgraaf Limburg 6374 TS",
    "addr:housenumber":"2",
    "addr:postcode":"6374 ts",
    "addr:street":"Burg Hermansstr",
    "iso:country":"NL",
    "sg:address":"Burg Hermansstr 2",
    "sg:city":"Landgraaf",
    "sg:orig_category":"Adviesbureaus Bedrijfsorganisatie",
    "sg:phone":"+31 45 531 4018",
    "sg:postcode":"6374 TS",
    "sg:province":"Limburg",
    "wof:name":"Gebon Bv",
    "wof:placetype":"venue"
},
  "geometry": {"coordinates":[6.05097,50.911919],"type":"Point"}
}