{
  "type": "Feature",
  "properties": {
    "iso:country":"NL",
    "sg:address":"Stemhuisstr 1",
    "sg:city":"Brantgum",
    "sg:orig_category":"Scholen Voor Basisonderwijs",
    "sg:phone":"+31 519 562 292",
    "sg:postcode":"9153 BH",
    "sg:province":"Provincie Friesland",
    "wof:name":"Ids Wiersma Openb",
    "wof:placetype":"venue"
},
  "geometry": {"coordinates":[5.933037,53.352436],"type":"Point"}
}