{
  "type": "Feature",
  "properties": {
    "addr:full":"Stephan Zoetmulderdreef 6 Waalre North Brabant 5581 TD",
    "addr:housenumber":"6",
    "addr:postcode":"5581 td",
    "addr:street":"Zoetmulderdreef",
    "iso:country":"NL",
    "sg:address":"Stephan Zoetmulderdreef 6",
    "sg:city":"Waalre",
    "sg:orig_category":"Meubelzaken, Woning- And Keukeninrichting",
    "sg:phone":"+31 40 221 5483",
    "sg:postcode":"5581 TD",
    "sg:province":"North Brabant",
    "wof:name":"Handelsonderneming Van Oss",
    "wof:placetype":"venue"
},
  "geometry": {"coordinates":[5.43601,51.389294],"type":"Point"}
}