{
  "type": "Feature",
  "properties": {
    "iso:country":"NL",
    "sg:address":"Limburgsngl 4",
    "sg:city":"Arnhem",
    "sg:orig_category":"Adviesbureaus Bedrijfsorganisatie",
    "sg:phone":"+31 26 383 0302",
    "sg:postcode":"6845 DT",
    "sg:province":"Gelderland",
    "wof:name":"Jongbloed",
    "wof:placetype":"venue"
},
  "geometry": {"coordinates":[5.864675,51.945145],"type":"Point"}
}