{
  "type": "Feature",
  "properties": {
    "addr:full":"De Reede 3 Veendam Groningen 9642 MA",
    "addr:housenumber":"3",
    "addr:postcode":"9642 ma",
    "addr:street":"De Reede",
    "iso:country":"NL",
    "sg:address":"De Reede 3",
    "sg:city":"Veendam",
    "sg:classifiers":[
        {
            "category":"Communications",
            "subcategory":"Television Station",
            "type":"Services"
        }
    ],
    "sg:phone":"+31 598 624 386",
    "sg:postcode":"9642 MA",
    "sg:province":"Groningen",
    "sg:tags":[
        "video",
        "audio",
        "verhuur"
    ],
    "wof:name":"Videotheek Sorghvliet",
    "wof:placetype":"venue"
},
  "geometry": {"coordinates":[6.859243,53.094986],"type":"Point"}
}