{
  "type": "Feature",
  "properties": {
    "addr:full":"Dorpsstr 17 Eckelrade Limburg 6251 NA",
    "addr:housenumber":"17",
    "addr:postcode":"6251 na",
    "addr:street":"Dorpsstr",
    "iso:country":"NL",
    "sg:address":"Dorpsstr 17",
    "sg:city":"Eckelrade",
    "sg:orig_category":"Adviesbureaus",
    "sg:phone":"+31 43 408 3221",
    "sg:postcode":"6251 NA",
    "sg:province":"Limburg",
    "wof:name":"Synergy International",
    "wof:placetype":"venue"
},
  "geometry": {"coordinates":[5.761717,50.805149],"type":"Point"}
}