{
  "type": "Feature",
  "properties": {
    "addr:full":"Goorwg 4B Riel North Brabant 5133 NK",
    "addr:housenumber":"4b",
    "addr:postcode":"5133 nk",
    "addr:street":"Goorwg",
    "iso:country":"NL",
    "sg:address":"Goorwg 4B",
    "sg:city":"Riel",
    "sg:classifiers":[
        {
            "category":"Personal",
            "subcategory":"Nail Salon",
            "type":"Services"
        }
    ],
    "sg:phone":"+31 13 518 2352",
    "sg:postcode":"5133 NK",
    "sg:province":"North Brabant",
    "sg:tags":[
        "pedicure"
    ],
    "wof:name":"Bresser, Ingrid De",
    "wof:placetype":"venue"
},
  "geometry": {"coordinates":[5.013613,51.53133],"type":"Point"}
}