{
  "type": "Feature",
  "properties": {
    "addr:full":"Rokerywg 28 Huizen Noord-Holland 1271 AH",
    "addr:housenumber":"28",
    "addr:postcode":"1271 ah",
    "addr:street":"Rokerywg",
    "iso:country":"NL",
    "sg:address":"Rokerywg 28",
    "sg:city":"Huizen",
    "sg:orig_category":"Verf En Lak - Fabrieken En Groothandel",
    "sg:phone":"+31 35 525 6085",
    "sg:postcode":"1271 AH",
    "sg:province":"Noord-Holland",
    "wof:name":"Bouwman Bv",
    "wof:placetype":"venue"
},
  "geometry": {"coordinates":[5.244362,52.300873],"type":"Point"}
}