{
  "type": "Feature",
  "properties": {
    "iso:country":"NL",
    "sg:address":"Rokerywg 28",
    "sg:city":"Huizen",
    "sg:orig_category":"Verf En Lak - Fabrieken En Groothandel",
    "sg:phone":"+31 35 525 6085",
    "sg:postcode":"1271 AH",
    "sg:province":"Noord-Holland",
    "wof:name":"Bouwman Bv",
    "wof:placetype":"venue"
},
  "geometry": {"coordinates":[5.244362,52.300873],"type":"Point"}
}