{
  "type": "Feature",
  "properties": {
    "addr:full":"Hoofdstraat 3 Bergambacht South Holland 2861 AK",
    "addr:housenumber":"3",
    "addr:postcode":"2861 ak",
    "addr:street":"Hoofdstraat",
    "iso:country":"NL",
    "sg:address":"Hoofdstraat 3",
    "sg:city":"Bergambacht",
    "sg:orig_category":"Verlichting And Huishoudartikelen",
    "sg:phone":"+31 182 352 044",
    "sg:postcode":"2861 AK",
    "sg:province":"South Holland",
    "wof:name":"Marskramer Van Eijk Bergambacht Bv",
    "wof:placetype":"venue"
},
  "geometry": {"coordinates":[4.783049,51.932858],"type":"Point"}
}