{
  "type": "Feature",
  "properties": {
    "iso:country":"NL",
    "sg:address":"Heyhoefpromenade 23",
    "sg:city":"Tilburg",
    "sg:orig_category":"Warenhuizen",
    "sg:phone":"+31 13 571 0164",
    "sg:postcode":"5043 RA",
    "sg:province":"Noord-Brabant",
    "wof:name":"Hema",
    "wof:placetype":"venue"
},
  "geometry": {"coordinates":[5.0062408447,51.5780258179],"type":"Point"}
}