{
  "type": "Feature",
  "properties": {
    "iso:country":"NL",
    "sg:address":"Koningslaan 39",
    "sg:city":"Amsterdam",
    "sg:orig_category":"Krantenuitgeverijen",
    "sg:phone":"+31 20 679 2121",
    "sg:postcode":"1075 AB",
    "sg:province":"Noord-Holland",
    "wof:name":"Brooker & Friend Limited",
    "wof:placetype":"venue"
},
  "geometry": {"coordinates":[4.861033,52.354511],"type":"Point"}
}