{
  "type": "Feature",
  "properties": {
    "addr:full":"Boschstraat 22 Breda Noord-Brabant 4811 GH",
    "addr:housenumber":"22",
    "addr:postcode":"4811 gh",
    "addr:street":"Boschstraat",
    "iso:country":"NL",
    "sg:address":"Boschstraat 22",
    "sg:city":"Breda",
    "sg:orig_category":"Organisaties And Verenigingen",
    "sg:phone":"+31 76 514 7676",
    "sg:postcode":"4811 GH",
    "sg:province":"Noord-Brabant",
    "wof:name":"Artotheek Breda",
    "wof:placetype":"venue"
},
  "geometry": {"coordinates":[4.7810659409,51.5896148682],"type":"Point"}
}