{
  "type": "Feature",
  "properties": {
    "iso:country":"NL",
    "sg:address":"Vaartwg 129A",
    "sg:city":"Hilversum",
    "sg:orig_category":"Modellenbureaus En Modellen Freelance",
    "sg:phone":"+31 35 672 9000",
    "sg:postcode":"1217 SN",
    "sg:province":"Noord-Holland",
    "sg:website":"http://www.benfcasting.nl",
    "wof:name":"B & F Casting",
    "wof:placetype":"venue"
},
  "geometry": {"coordinates":[5.158351,52.223026],"type":"Point"}
}