{
  "type": "Feature",
  "properties": {
    "addr:full":"Van Musschenbroekstraat 10 'S Gravenhage Zuid-Holland 2522 AP",
    "addr:housenumber":"10",
    "addr:postcode":"2522 ap",
    "addr:street":"Van Musschenbroekstraat;' S",
    "iso:country":"NL",
    "sg:address":"Van Musschenbroekstraat 10",
    "sg:city":"'S Gravenhage",
    "sg:orig_category":"Kappers",
    "sg:phone":"+31 70 395 4473",
    "sg:postcode":"2522 AP",
    "sg:province":"Zuid-Holland",
    "wof:name":"Anneke'S Haarmode",
    "wof:placetype":"venue"
},
  "geometry": {"coordinates":[4.3296351433,52.0644874573],"type":"Point"}
}