{
  "type": "Feature",
  "properties": {
    "addr:full":"Joan Coststraat 9A Enschede Overijssel 7514 AT",
    "addr:housenumber":"9a",
    "addr:postcode":"7514",
    "addr:street":"Joan Coststraat",
    "iso:country":"NL",
    "sg:address":"Joan Coststraat 9A",
    "sg:city":"Enschede",
    "sg:orig_category":"Verhuur Catering-, Feest- En Evenementbenodigdheden",
    "sg:phone":"+31 53 432 0101",
    "sg:postcode":"7514 AT",
    "sg:province":"Overijssel",
    "wof:name":"M. Sterk Tentenreparaties",
    "wof:placetype":"venue"
},
  "geometry": {"coordinates":[6.885728,52.22538],"type":"Point"}
}