{
  "type": "Feature",
  "properties": {
    "addr:full":"Tauber 39-41 S Gravenhage 2491 DB",
    "addr:housenumber":"39-41",
    "addr:postcode":"2491 db",
    "addr:street":"Tauber;S Gravenhage",
    "iso:country":"NL",
    "sg:address":"Tauber 39-41",
    "sg:city":"S Gravenhage",
    "sg:orig_category":"Verhuizingen",
    "sg:phone":"+31 70 327 2826",
    "sg:postcode":"2491 DB",
    "wof:name":"Wansem, Fa P J V/D",
    "wof:placetype":"venue"
},
  "geometry": {"coordinates":[4.38382,52.065289],"type":"Point"}
}