{
  "type": "Feature",
  "properties": {
    "iso:country":"NL",
    "sg:address":"Larenwg 48",
    "sg:city":"S Hertogenbosch",
    "sg:orig_category":"Kousen - Fabrieken En Groothandel",
    "sg:phone":"+31 73 521 1238",
    "sg:postcode":"5234 KA",
    "sg:province":"Noord-Brabant",
    "sg:website":"http://www.sockshouse.nl",
    "wof:name":"Socks House",
    "wof:placetype":"venue"
},
  "geometry": {"coordinates":[5.28789,51.725601],"type":"Point"}
}