{
  "type": "Feature",
  "properties": {
    "iso:country":"NL",
    "sg:address":"Veldstraat 6",
    "sg:city":"Baarlo Lb",
    "sg:orig_category":"Verlichting And Huishoudartikelen",
    "sg:phone":"+31 77 477 1404",
    "sg:postcode":"5991 AD",
    "sg:province":"Limburg",
    "wof:name":"H.M.A. Crienen",
    "wof:placetype":"venue"
},
  "geometry": {"coordinates":[6.097194,51.332214],"type":"Point"}
}