{
  "type": "Feature",
  "properties": {
    "addr:full":"Vijzelstraat 137 Amsterdam Noord-Holland 1017 HJ",
    "addr:housenumber":"137",
    "addr:postcode":"1017 hj",
    "addr:street":"Vijzelstraat",
    "iso:country":"NL",
    "sg:address":"Vijzelstraat 137",
    "sg:city":"Amsterdam",
    "sg:classifiers":[
        {
            "category":"Restaurant",
            "type":"Food & Drink"
        }
    ],
    "sg:phone":"+31 20 427 2213",
    "sg:postcode":"1017 HJ",
    "sg:province":"Noord-Holland",
    "wof:name":"Village Bagels",
    "wof:placetype":"venue"
},
  "geometry": {"coordinates":[4.891891,52.362389],"type":"Point"}
}