{
  "type": "Feature",
  "properties": {
    "iso:country":"NL",
    "sg:address":"Sluiswg 21A",
    "sg:city":"Waalwyk",
    "sg:orig_category":"Automaterialen En Gereedschappen",
    "sg:phone":"+31 416 337 855",
    "sg:postcode":"5145 PE",
    "sg:province":"Noord-Brabant",
    "wof:name":"Lasaulec Waalwijk",
    "wof:placetype":"venue"
},
  "geometry": {"coordinates":[5.053218,51.696434],"type":"Point"}
}