{
  "type": "Feature",
  "properties": {
    "addr:full":"Haagwg 377 Breda Noord-Brabant 4813 XC",
    "addr:housenumber":"377",
    "addr:postcode":"4813 xc",
    "iso:country":"NL",
    "sg:address":"Haagwg 377",
    "sg:city":"Breda",
    "sg:orig_category":"Koffers En Tassen - Fabrieken En Groothandel",
    "sg:phone":"+31 162 515 858",
    "sg:postcode":"4813 XC",
    "sg:province":"Noord-Brabant",
    "wof:name":"Dakota, Flightcases",
    "wof:placetype":"venue"
},
  "geometry": {"coordinates":[4.743744,51.578259],"type":"Point"}
}