{
  "type": "Feature",
  "properties": {
    "addr:full":"Akerkhof 4 - Zuidzijde Groningen Groningen 9711 JB",
    "addr:housenumber":"4",
    "addr:postcode":"9711 jb",
    "addr:street":"Akerkhof",
    "iso:country":"NL",
    "sg:address":"Akerkhof 4 - Zuidzijde",
    "sg:city":"Groningen",
    "sg:orig_category":"Zalenverhuur",
    "sg:phone":"+31 50 312 0333",
    "sg:postcode":"9711 JB",
    "sg:province":"Groningen",
    "sg:website":"http://www.huisdebeurs.nl",
    "wof:name":"Huis De Beurs, Caf? Restaurant",
    "wof:placetype":"venue"
},
  "geometry": {"coordinates":[6.574715,53.217144],"type":"Point"}
}