{
  "type": "Feature",
  "properties": {
    "iso:country":"NL",
    "sg:address":"Parkwg 24",
    "sg:city":"Boxtel",
    "sg:orig_category":"Accountants - Administratie- Consulenten En -Kantoren",
    "sg:phone":"+31 411 612 753",
    "sg:postcode":"5282 SM",
    "sg:province":"Noord-Brabant",
    "wof:name":"Putter & De Boer Bv",
    "wof:placetype":"venue"
},
  "geometry": {"coordinates":[5.315661,51.602024],"type":"Point"}
}