{
  "type": "Feature",
  "properties": {
    "addr:full":"Rapenburg 24 Leeuwarden Zuid-Holland 2311 EW",
    "addr:housenumber":"24",
    "addr:postcode":"2311 ew",
    "addr:street":"Rapenburg",
    "iso:country":"NL",
    "sg:address":"Rapenburg 24",
    "sg:city":"Leeuwarden",
    "sg:orig_category":"Organisaties And Verenigingen",
    "sg:phone":"+31 71 514 9697",
    "sg:postcode":"2311 EW",
    "sg:province":"Zuid-Holland",
    "wof:name":"Studentenvereniging Augustinus",
    "wof:placetype":"venue"
},
  "geometry": {"coordinates":[4.4946298599,52.1545715332],"type":"Point"}
}