{
  "type": "Feature",
  "properties": {
    "addr:full":"Laanstr 2 Soest Utrecht 3762 KD",
    "addr:housenumber":"2",
    "addr:postcode":"3762 kd",
    "addr:street":"Laanstr",
    "iso:country":"NL",
    "sg:address":"Laanstr 2",
    "sg:city":"Soest",
    "sg:orig_category":"Adviesbureaus Bedrijfsorganisatie",
    "sg:phone":"+31 35 602 0139",
    "sg:postcode":"3762 KD",
    "sg:province":"Utrecht",
    "wof:name":"Shift Work Consultancy",
    "wof:placetype":"venue"
},
  "geometry": {"coordinates":[5.275561,52.181496],"type":"Point"}
}