{
  "type": "Feature",
  "properties": {
    "addr:full":"Mari Andriessenerf 15 'S Gravenhage South Holland 2552 KL",
    "addr:housenumber":"15",
    "addr:postcode":"2552 kl",
    "addr:street":"Mari Andriessenerf;' S Gravenhage",
    "iso:country":"NL",
    "sg:address":"Mari Andriessenerf 15",
    "sg:city":"'S Gravenhage",
    "sg:classifiers":[
        {
            "category":"Education",
            "subcategory":"Preschool",
            "type":"Public Place"
        }
    ],
    "sg:phone":"+31 70 397 4065",
    "sg:postcode":"2552 KL",
    "sg:province":"South Holland",
    "sg:tags":[
        "kleuteronderwijs",
        "basis-"
    ],
    "wof:name":"Christelijke Basisschool De Eshof",
    "wof:placetype":"venue"
},
  "geometry": {"coordinates":[4.248007,52.054199],"type":"Point"}
}