{
  "type": "Feature",
  "properties": {
    "addr:full":"Jacob Van Campenplein 63 Rotterdam South Holland 3067 LA",
    "addr:housenumber":"63",
    "addr:postcode":"3067 la",
    "addr:street":"Jacob Van Campenplein",
    "iso:country":"NL",
    "sg:address":"Jacob Van Campenplein 63",
    "sg:city":"Rotterdam",
    "sg:classifiers":[
        {
            "category":"Fast Food",
            "type":"Food & Drink"
        }
    ],
    "sg:phone":"+31 10 455 5780",
    "sg:postcode":"3067 LA",
    "sg:province":"South Holland",
    "sg:tags":[
        "afhaal",
        "restaurant"
    ],
    "wof:name":"Grillroom Alexandria",
    "wof:placetype":"venue"
},
  "geometry": {"coordinates":[4.536782,51.944172],"type":"Point"}
}