{
  "type": "Feature",
  "properties": {
    "addr:full":"Lange Zelke 9 Vlissingen Zeeland 4381 EW",
    "addr:housenumber":"9",
    "addr:postcode":"4381 ew",
    "addr:street":"Lange Zelke",
    "iso:country":"NL",
    "sg:address":"Lange Zelke 9",
    "sg:city":"Vlissingen",
    "sg:orig_category":"Discountwinkels",
    "sg:phone":"+31 118 418 900",
    "sg:postcode":"4381 EW",
    "sg:province":"Zeeland",
    "wof:name":"Zeeman Textielsupers Bv",
    "wof:placetype":"venue"
},
  "geometry": {"coordinates":[3.573671,51.443409],"type":"Point"}
}