{
  "type": "Feature",
  "properties": {
    "iso:country":"NL",
    "sg:address":"Pr Hendrikln 154",
    "sg:city":"Brunssum",
    "sg:orig_category":"Kappers",
    "sg:phone":"+31 45 525 4666",
    "sg:postcode":"6441 AC",
    "sg:province":"Limburg",
    "wof:name":"Madame",
    "wof:placetype":"venue"
},
  "geometry": {"coordinates":[5.97657,50.948391],"type":"Point"}
}