{
  "type": "Feature",
  "properties": {
    "iso:country":"NL",
    "sg:address":"Rynlust 4244",
    "sg:city":"Gouda",
    "sg:orig_category":"Scholen Voor Basisonderwijs",
    "sg:phone":"+31 182 533 560",
    "sg:postcode":"2804 LC",
    "sg:province":"South Holland",
    "wof:name":"Cirkel, De",
    "wof:placetype":"venue"
},
  "geometry": {"coordinates":[4.71103,52.034592],"type":"Point"}
}