{
  "type": "Feature",
  "properties": {
    "addr:full":"Regenbeemd 18 Breda Noord-Brabant 4825 AT",
    "addr:housenumber":"18",
    "addr:postcode":"4825",
    "addr:street":"Regenbeemd",
    "iso:country":"NL",
    "sg:address":"Regenbeemd 18",
    "sg:city":"Breda",
    "sg:orig_category":"Drukkerijen And Copyshops",
    "sg:phone":"+31 76 581 2010",
    "sg:postcode":"4825 AT",
    "sg:province":"Noord-Brabant",
    "wof:name":"Grafimix Breda",
    "wof:placetype":"venue"
},
  "geometry": {"coordinates":[4.768243,51.616501],"type":"Point"}
}