{
  "type": "Feature",
  "properties": {
    "iso:country":"NL",
    "sg:address":"Hoonhorst 15",
    "sg:city":"Lattrop Breklenk",
    "sg:orig_category":"Voetbalverenigingen",
    "sg:phone":"+31 541 229 717",
    "sg:postcode":"7635 NW",
    "sg:province":"Overijssel",
    "wof:name":"Dinkelland",
    "wof:placetype":"venue"
},
  "geometry": {"coordinates":[6.974513,52.426151],"type":"Point"}
}