{
  "type": "Feature",
  "properties": {
    "addr:full":"Helftheuv Passage 252 S Hertogenbosch North Brabant 5224 AP",
    "addr:housenumber":"252",
    "addr:postcode":"5224 ap",
    "addr:street":"Passage;S Hertogenbosch",
    "iso:country":"NL",
    "sg:address":"Helftheuv Passage 252",
    "sg:city":"S Hertogenbosch",
    "sg:orig_category":"Zoetwaren - Winkels",
    "sg:phone":"+31 73 622 2233",
    "sg:postcode":"5224 AP",
    "sg:province":"North Brabant",
    "wof:name":"Drop-Inn",
    "wof:placetype":"venue"
},
  "geometry": {"coordinates":[5.266576,51.695087],"type":"Point"}
}