{
  "type": "Feature",
  "properties": {
    "iso:country":"NL",
    "sg:address":"Onderwg 91A",
    "sg:city":"Waddinxveen",
    "sg:orig_category":"Grondwerken",
    "sg:phone":"+31 182 613 234",
    "sg:postcode":"2742 LB",
    "sg:province":"South Holland",
    "wof:name":"Vliet, Gebr Van",
    "wof:placetype":"venue"
},
  "geometry": {"coordinates":[4.635609,52.045689],"type":"Point"}
}