{
  "type": "Feature",
  "properties": {
    "addr:full":"Breede Plat 4 Broek Op Langedijk Noord-Holland 1721 PS",
    "addr:housenumber":"4",
    "addr:postcode":"1721 ps",
    "addr:street":"Breede Plat",
    "iso:country":"NL",
    "sg:address":"Breede Plat 4",
    "sg:city":"Broek Op Langedijk",
    "sg:orig_category":"Autokeuringen",
    "sg:phone":"+31 226 312 165",
    "sg:postcode":"1721 PS",
    "sg:province":"Noord-Holland",
    "wof:name":"Garagebedrijf Ton Sneek",
    "wof:placetype":"venue"
},
  "geometry": {"coordinates":[4.794418,52.676697],"type":"Point"}
}