{
  "type": "Feature",
  "properties": {
    "addr:full":"Polderstr 1 Alblasserdam South Holland 2952 AK",
    "addr:housenumber":"1",
    "addr:postcode":"2952 ak",
    "addr:street":"Polderstr",
    "iso:country":"NL",
    "sg:address":"Polderstr 1",
    "sg:city":"Alblasserdam",
    "sg:orig_category":"Verzekeringen - Verzekeringskantoren",
    "sg:phone":"+31 78 691 5107",
    "sg:postcode":"2952 AK",
    "sg:province":"South Holland",
    "sg:website":"http://www.van-tol.nl",
    "wof:name":"Tol Adviesgroep, Van",
    "wof:placetype":"venue"
},
  "geometry": {"coordinates":[4.660254,51.860126],"type":"Point"}
}