{
  "type": "Feature",
  "properties": {
    "addr:full":"Fuut 2 Ouderkerk Amstel North Holland 1191 SH",
    "addr:housenumber":"2;1191",
    "addr:postcode":"sh",
    "addr:street":"Fuut;Ouderkerk Amstel",
    "iso:country":"NL",
    "sg:address":"Fuut 2",
    "sg:city":"Ouderkerk Amstel",
    "sg:classifiers":[
        {
            "category":"Home & Garden",
            "subcategory":"Garden Supply",
            "type":"Retail Goods"
        }
    ],
    "sg:phone":"+31 20 496 1476",
    "sg:postcode":"1191 SH",
    "sg:province":"North Holland",
    "sg:tags":[
        "zand",
        "en",
        "grind"
    ],
    "wof:name":"Leurs",
    "wof:placetype":"venue"
},
  "geometry": {"coordinates":[4.914726,52.2924],"type":"Point"}
}