{
  "type": "Feature",
  "properties": {
    "addr:full":"Heistr 52 Valkenswaard Noord-Brabant 5554 ER",
    "addr:housenumber":"52",
    "addr:postcode":"5554 er",
    "addr:street":"Heistr",
    "iso:country":"NL",
    "sg:address":"Heistr 52",
    "sg:city":"Valkenswaard",
    "sg:orig_category":"Loopbaanbegeleiding",
    "sg:phone":"+31 40 201 0251",
    "sg:postcode":"5554 ER",
    "sg:province":"Noord-Brabant",
    "wof:name":"Liss",
    "wof:placetype":"venue"
},
  "geometry": {"coordinates":[5.463273,51.342533],"type":"Point"}
}