{
  "type": "Feature",
  "properties": {
    "addr:full":"Ceintuurbaan 18 Huizen North Holland 1271 BH",
    "addr:housenumber":"18",
    "addr:postcode":"1271 bh",
    "addr:street":"Ceintuurbaan",
    "iso:country":"NL",
    "sg:address":"Ceintuurbaan 18",
    "sg:city":"Huizen",
    "sg:classifiers":[
        {
            "category":"Fast Food",
            "type":"Food & Drink"
        }
    ],
    "sg:phone":"+31 35 525 9790",
    "sg:postcode":"1271 BH",
    "sg:province":"North Holland",
    "sg:tags":[
        "afhaal",
        "restaurant"
    ],
    "wof:name":"La Strada",
    "wof:placetype":"venue"
},
  "geometry": {"coordinates":[5.234104,52.294876],"type":"Point"}
}