{
  "type": "Feature",
  "properties": {
    "iso:country":"NL",
    "sg:address":"Trommelaarshoeve 233",
    "sg:city":"Apeldoorn",
    "sg:orig_category":"Goederenvervoer Over De Weg",
    "sg:phone":"+31 55 540 9460",
    "sg:postcode":"7326 VW",
    "sg:province":"Gelderland",
    "wof:name":"K.G.F. Kroos",
    "wof:placetype":"venue"
},
  "geometry": {"coordinates":[6.004807,52.190777],"type":"Point"}
}