{
  "type": "Feature",
  "properties": {
    "addr:full":"K Leidsedwstr 17 Amsterdam North Holland 1017 PV",
    "addr:housenumber":"17",
    "addr:postcode":"1017 pv",
    "addr:street":"Leidsedwstr",
    "iso:country":"NL",
    "sg:address":"K Leidsedwstr 17",
    "sg:city":"Amsterdam",
    "sg:orig_category":"Vakorganisaties",
    "sg:phone":"+31 20 623 4296",
    "sg:postcode":"1017 PV",
    "sg:province":"North Holland",
    "sg:website":"http://www.netwerkscenario.nl",
    "wof:name":"Netwerk Scenarioschrijvers",
    "wof:placetype":"venue"
},
  "geometry": {"coordinates":[4.88745,52.366261],"type":"Point"}
}