{
  "type": "Feature",
  "properties": {
    "addr:full":"Oostumerweg 11 Garnwerd Groningen 9893 TB",
    "addr:housenumber":"11",
    "addr:postcode":"9893 tb",
    "addr:street":"Oostumerweg",
    "iso:country":"NL",
    "sg:address":"Oostumerweg 11",
    "sg:city":"Garnwerd",
    "sg:orig_category":"Diverse Grafische Activiteiten",
    "sg:phone":"+31 50 403 2290",
    "sg:postcode":"9893 TB",
    "sg:province":"Groningen",
    "wof:name":"Irene Verbeek",
    "wof:placetype":"venue"
},
  "geometry": {"coordinates":[6.493975,53.291973],"type":"Point"}
}