{
  "type": "Feature",
  "properties": {
    "addr:full":"De Star 36 Enkhuizen Noord-Holland 1601 MH",
    "addr:housenumber":"36",
    "addr:postcode":"1601 mh",
    "addr:street":"De Star",
    "iso:country":"NL",
    "sg:address":"De Star 36",
    "sg:city":"Enkhuizen",
    "sg:orig_category":"Meubelmakerijen",
    "sg:phone":"+31 228 520 603",
    "sg:postcode":"1601 MH",
    "sg:province":"Noord-Holland",
    "wof:name":"Reudenroos",
    "wof:placetype":"venue"
},
  "geometry": {"coordinates":[5.266395,52.69519],"type":"Point"}
}