{
  "type": "Feature",
  "properties": {
    "addr:full":"Hoeveveld 36 Molenhoek Lb Limburg 6584 GG",
    "addr:housenumber":"36",
    "addr:postcode":"lb;6584 gg",
    "addr:street":"Hoeveveld",
    "iso:country":"NL",
    "sg:address":"Hoeveveld 36",
    "sg:city":"Molenhoek Lb",
    "sg:orig_category":"Optiehandel",
    "sg:phone":"+31 24 388 0687",
    "sg:postcode":"6584 GG",
    "sg:province":"Limburg",
    "wof:name":"Options Bv",
    "wof:placetype":"venue"
},
  "geometry": {"coordinates":[5.8756690025,51.7645454407],"type":"Point"}
}