{
  "type": "Feature",
  "properties": {
    "addr:full":"Zeswegenln 281 Heerlen Limburg 6412 HK",
    "addr:housenumber":"281",
    "addr:postcode":"6412 hk",
    "iso:country":"NL",
    "sg:address":"Zeswegenln 281",
    "sg:city":"Heerlen",
    "sg:orig_category":"Kappers",
    "sg:phone":"+31 45 570 8491",
    "sg:postcode":"6412 HK",
    "sg:province":"Limburg",
    "wof:name":"Hairpoint",
    "wof:placetype":"venue"
},
  "geometry": {"coordinates":[5.9606747627,50.899066925],"type":"Point"}
}