{
  "type": "Feature",
  "properties": {
    "iso:country":"NL",
    "sg:address":"Prinsessesngl 911",
    "sg:city":"Venlo",
    "sg:orig_category":"Gordijnen",
    "sg:phone":"+31 77 354 7975",
    "sg:postcode":"5911 HS",
    "sg:province":"Limburg",
    "wof:name":"Saskia",
    "wof:placetype":"venue"
},
  "geometry": {"coordinates":[6.17286,51.372421],"type":"Point"}
}