{
  "type": "Feature",
  "properties": {
    "iso:country":"NL",
    "sg:address":"H Dunantln 45",
    "sg:city":"Diemen",
    "sg:orig_category":"Verzekeringen - Verzekeringskantoren",
    "sg:phone":"+31 20 690 7711",
    "sg:postcode":"1111 ZH",
    "sg:province":"Noord-Holland",
    "wof:name":"Schipper, H",
    "wof:placetype":"venue"
},
  "geometry": {"coordinates":[4.968487,52.341934],"type":"Point"}
}