{
  "type": "Feature",
  "properties": {
    "addr:full":"Van Leijenberghlaan 401 Amsterdam Noord-Holland 1082 GK",
    "addr:housenumber":"401",
    "addr:postcode":"1082 gk",
    "addr:street":"Van Leijenberghlaan",
    "iso:country":"NL",
    "sg:address":"Van Leijenberghlaan 401",
    "sg:city":"Amsterdam",
    "sg:orig_category":"Diverse Grafische Activiteiten",
    "sg:phone":"+31 20 642 9464",
    "sg:postcode":"1082 GK",
    "sg:province":"Noord-Holland",
    "wof:name":"A.G. Schillemans",
    "wof:placetype":"venue"
},
  "geometry": {"coordinates":[4.879913,52.325577],"type":"Point"}
}