{
  "type": "Feature",
  "properties": {
    "addr:full":"Voorpeel 1 Odiliapeel Noord-Brabant 5409 TX",
    "addr:housenumber":"1",
    "addr:postcode":"5409 tx",
    "addr:street":"Voorpeel",
    "iso:country":"NL",
    "sg:address":"Voorpeel 1",
    "sg:city":"Odiliapeel",
    "sg:classifiers":[
        {
            "category":"Sports & Exercise",
            "subcategory":"Stables",
            "type":"Entertainment"
        }
    ],
    "sg:phone":"+31 486 432 039",
    "sg:postcode":"5409 TX",
    "sg:province":"Noord-Brabant",
    "sg:tags":[
        "maneges"
    ],
    "wof:name":"Verstegen Paardenpension",
    "wof:placetype":"venue"
},
  "geometry": {"coordinates":[5.72311,51.670357],"type":"Point"}
}