{
  "type": "Feature",
  "properties": {
    "addr:full":"Schakelstraat 12 Amsterdam Noord-Holland 1014 AW",
    "addr:housenumber":"12",
    "addr:postcode":"1014 aw",
    "addr:street":"Schakelstraat",
    "iso:country":"NL",
    "sg:address":"Schakelstraat 12",
    "sg:city":"Amsterdam",
    "sg:orig_category":"Binnenhuisarchitecten",
    "sg:phone":"+31 20 681 3776",
    "sg:postcode":"1014 AW",
    "sg:province":"Noord-Holland",
    "wof:name":"Siersema Interieur & Home Officing Bv",
    "wof:placetype":"venue"
},
  "geometry": {"coordinates":[4.84942,52.390423],"type":"Point"}
}