{
  "type": "Feature",
  "properties": {
    "addr:full":"Jansweg 1 Haarlem North Holland 2011 KL",
    "addr:housenumber":"1",
    "addr:postcode":"2011 kl",
    "addr:street":"Jansweg",
    "iso:country":"NL",
    "sg:address":"Jansweg 1",
    "sg:city":"Haarlem",
    "sg:orig_category":"Werving And Selectie Van Tijdelijk Personeel And Uitzendkantoren",
    "sg:phone":"+31 23 532 3215",
    "sg:postcode":"2011 KL",
    "sg:province":"North Holland",
    "wof:name":"Content",
    "wof:placetype":"venue"
},
  "geometry": {"coordinates":[4.6407270432,52.3883628845],"type":"Point"}
}