{
  "type": "Feature",
  "properties": {
    "addr:full":"De Kempenaerpk 7 Nieuwegein Utrecht 3437 JE",
    "addr:housenumber":"7",
    "addr:postcode":"3437 je",
    "iso:country":"NL",
    "sg:address":"De Kempenaerpk 7",
    "sg:city":"Nieuwegein",
    "sg:orig_category":"Apotheken",
    "sg:phone":"+31 30 600 0543",
    "sg:postcode":"3437 JE",
    "sg:province":"Utrecht",
    "wof:name":"Galecop, De",
    "wof:placetype":"venue"
},
  "geometry": {"coordinates":[5.081134,52.053658],"type":"Point"}
}