{
  "type": "Feature",
  "properties": {
    "addr:full":"Titanenhof 21 Maastricht Limburg 6215 EA",
    "addr:housenumber":"21",
    "addr:postcode":"6215 ea",
    "addr:street":"Titanenhof",
    "iso:country":"NL",
    "sg:address":"Titanenhof 21",
    "sg:city":"Maastricht",
    "sg:orig_category":"Verzekeringen - Verzekeringskantoren",
    "sg:phone":"+31 43 354 0460",
    "sg:postcode":"6215 EA",
    "sg:province":"Limburg",
    "wof:name":"Extra",
    "wof:placetype":"venue"
},
  "geometry": {"coordinates":[5.64238,50.842445],"type":"Point"}
}