{
  "type": "Feature",
  "properties": {
    "addr:full":"Liendenhof 163 Amsterdam Zuidoost North Holland 1108 HK",
    "addr:housenumber":"163",
    "addr:postcode":"1108 hk",
    "addr:street":"Liendenhof",
    "iso:country":"NL",
    "sg:address":"Liendenhof 163",
    "sg:city":"Amsterdam Zuidoost",
    "sg:orig_category":"Adviesbureaus Bedrijfsorganisatie",
    "sg:phone":"+31 20 696 4648",
    "sg:postcode":"1108 HK",
    "sg:province":"North Holland",
    "wof:name":"Kreetz Bv",
    "wof:placetype":"venue"
},
  "geometry": {"coordinates":[4.985007,52.307785],"type":"Point"}
}