{
  "type": "Feature",
  "properties": {
    "addr:full":"Amsterdamse Vaart 260 Haarlem North Holland 2032 EK",
    "addr:housenumber":"260",
    "addr:postcode":"2032 ek",
    "addr:street":"Amsterdamse Vaart",
    "iso:country":"NL",
    "sg:address":"Amsterdamse Vaart 260",
    "sg:city":"Haarlem",
    "sg:orig_category":"Verhuur Diversen",
    "sg:phone":"+31 23 533 3104",
    "sg:postcode":"2032 EK",
    "sg:province":"North Holland",
    "wof:name":"H. Brouwer Hollandse Gebakskraam",
    "wof:placetype":"venue"
},
  "geometry": {"coordinates":[4.659728,52.381218],"type":"Point"}
}