{
  "type": "Feature",
  "properties": {
    "addr:full":"Remmingwg 24B Almere Flevoland 1332 BG",
    "addr:housenumber":"24b",
    "addr:postcode":"1332",
    "addr:street":"Remmingwg;Flevoland",
    "iso:country":"NL",
    "sg:address":"Remmingwg 24B",
    "sg:city":"Almere",
    "sg:classifiers":[
        {
            "category":"Retail",
            "subcategory":"Auto Repair",
            "type":"Services"
        }
    ],
    "sg:phone":"+31 36 532 5267",
    "sg:postcode":"1332 BG",
    "sg:province":"Flevoland",
    "sg:tags":[
        "garage"
    ],
    "wof:name":"Vitess",
    "wof:placetype":"venue"
},
  "geometry": {"coordinates":[5.252817,52.409489],"type":"Point"}
}