{
  "type": "Feature",
  "properties": {
    "addr:full":"R Visscherstr 182Hg Amsterdam Noord-Holland 1054 EX",
    "addr:housenumber":"182hg",
    "addr:postcode":"1054 ex",
    "iso:country":"NL",
    "sg:address":"R Visscherstr 182Hg",
    "sg:city":"Amsterdam",
    "sg:orig_category":"Verenigingen En Stichtingen",
    "sg:phone":"+31 20 662 3664",
    "sg:postcode":"1054 EX",
    "sg:province":"Noord-Holland",
    "wof:name":"Ewppp",
    "wof:placetype":"venue"
},
  "geometry": {"coordinates":[4.8756,52.360661],"type":"Point"}
}