{
  "type": "Feature",
  "properties": {
    "addr:full":"S Gravesandepln 19 Amsterdam Noord-Holland 1091 BB",
    "addr:housenumber":"19",
    "addr:postcode":"1091 bb",
    "iso:country":"NL",
    "sg:address":"S Gravesandepln 19",
    "sg:city":"Amsterdam",
    "sg:orig_category":"Scholen Voor Basisonderwijs",
    "sg:phone":"+31 20 468 5909",
    "sg:postcode":"1091 BB",
    "sg:province":"Noord-Holland",
    "wof:name":"Aldoende",
    "wof:placetype":"venue"
},
  "geometry": {"coordinates":[4.915686,52.359596],"type":"Point"}
}