{
  "type": "Feature",
  "properties": {
    "addr:full":"Ged Gracht 52 Schagen Noord-Holland 1741 GD",
    "addr:housenumber":"52",
    "addr:postcode":"1741 gd",
    "addr:street":"Ged Gracht",
    "iso:country":"NL",
    "sg:address":"Ged Gracht 52",
    "sg:city":"Schagen",
    "sg:classifiers":[
        {
            "category":"Shopping",
            "subcategory":"Adult",
            "type":"Retail Goods"
        }
    ],
    "sg:phone":"+31 224 212 633",
    "sg:postcode":"1741 GD",
    "sg:province":"Noord-Holland",
    "sg:tags":[
        "lingerie",
        "en",
        "tricotage"
    ],
    "wof:name":"Westerveld-Rus, Fa",
    "wof:placetype":"venue"
},
  "geometry": {"coordinates":[4.799775,52.787113],"type":"Point"}
}