{
  "type": "Feature",
  "properties": {
    "addr:full":"De Botter 14-20 Lelystad Flevoland 8232 JR",
    "addr:housenumber":"14-20",
    "addr:postcode":"8232 jr",
    "addr:street":"De Botter;Flevoland",
    "iso:country":"NL",
    "sg:address":"De Botter 14-20",
    "sg:city":"Lelystad",
    "sg:orig_category":"Fitnesscentra",
    "sg:phone":"+31 320 267 761",
    "sg:postcode":"8232 JR",
    "sg:province":"Flevoland",
    "wof:name":"Topfit",
    "wof:placetype":"venue"
},
  "geometry": {"coordinates":[5.470223,52.506134],"type":"Point"}
}