{
  "type": "Feature",
  "properties": {
    "addr:full":"Burgemeester Vd Pollstr 82 Amsterdam Noord-Holland 1064 AT",
    "addr:housenumber":"82",
    "addr:postcode":"1064",
    "addr:street":"Burgemeester Vd Pollstr",
    "iso:country":"NL",
    "sg:address":"Burgemeester Vd Pollstr 82",
    "sg:city":"Amsterdam",
    "sg:orig_category":"Kantoorartikelen",
    "sg:phone":"+31 20 447 0086",
    "sg:postcode":"1064 AT",
    "sg:province":"Noord-Holland",
    "wof:name":"B De Groot",
    "wof:placetype":"venue"
},
  "geometry": {"coordinates":[-94.58502960209999,38.350479126],"type":"Point"}
}