{
  "type": "Feature",
  "properties": {
    "iso:country":"NL",
    "sg:address":"Noordvliet 3",
    "sg:city":"Maassluis",
    "sg:classifiers":[
        {
            "category":"Farming",
            "subcategory":"Fish & Marine Products",
            "type":"Manufacturing & Wholesale Goods"
        }
    ],
    "sg:phone":"+31 10 591 2221",
    "sg:postcode":"3142 CH",
    "sg:province":"Zuid-Holland",
    "sg:tags":[
        "vi"
    ],
    "wof:name":"Viswinkel, De",
    "wof:placetype":"venue"
},
  "geometry": {"coordinates":[4.254547,51.922832],"type":"Point"}
}