{
  "type": "Feature",
  "properties": {
    "addr:full":"Beyersstr 105 S Gravenhage Zuid-Holland 2572 BD",
    "addr:housenumber":"105;gravenhage",
    "addr:postcode":"2572 bd",
    "addr:street":"S",
    "iso:country":"NL",
    "sg:address":"Beyersstr 105",
    "sg:city":"S Gravenhage",
    "sg:orig_category":"Verenigingsgebouwen",
    "sg:phone":"+31 70 364 8188",
    "sg:postcode":"2572 BD",
    "sg:province":"Zuid-Holland",
    "wof:name":"Loods, De",
    "wof:placetype":"venue"
},
  "geometry": {"coordinates":[4.29421,52.06422],"type":"Point"}
}