{
  "type": "Feature",
  "properties": {
    "addr:full":"Haagdijk 18 Breda Noord-Brabant 4811 TT",
    "addr:housenumber":"18",
    "addr:postcode":"4811 tt",
    "addr:street":"Haagdijk",
    "iso:country":"NL",
    "sg:address":"Haagdijk 18",
    "sg:city":"Breda",
    "sg:orig_category":"Metaalwerken",
    "sg:phone":"+31 76 521 3332",
    "sg:postcode":"4811 TT",
    "sg:province":"Noord-Brabant",
    "wof:name":"Alzon Zonwering",
    "wof:placetype":"venue"
},
  "geometry": {"coordinates":[4.770388,51.588562],"type":"Point"}
}