{
  "type": "Feature",
  "properties": {
    "addr:full":"Keizersgr 734D Amsterdam Noord-Holland 1017 EW",
    "addr:housenumber":"734d",
    "addr:postcode":"1017 ew",
    "addr:street":"Keizersgr",
    "iso:country":"NL",
    "sg:address":"Keizersgr 734D",
    "sg:city":"Amsterdam",
    "sg:orig_category":"Administratie- En Boekhoudkantoren",
    "sg:phone":"+31 20 623 4702",
    "sg:postcode":"1017 EW",
    "sg:province":"Noord-Holland",
    "wof:name":"Accuraat",
    "wof:placetype":"venue"
},
  "geometry": {"coordinates":[4.897105,52.363255],"type":"Point"}
}