{
  "type": "Feature",
  "properties": {
    "iso:country":"NL",
    "sg:address":"Meerkoet 18",
    "sg:city":"Diemen",
    "sg:orig_category":"Adviesbureaus Bedrijfsorganisatie",
    "sg:phone":"+31 20 698 0792",
    "sg:postcode":"1111 WB",
    "sg:province":"Noord-Holland",
    "wof:name":"Vliet Bv, F J Van",
    "wof:placetype":"venue"
},
  "geometry": {"coordinates":[4.976844,52.351776],"type":"Point"}
}