{
  "type": "Feature",
  "properties": {
    "addr:full":"Spoorhaag 164 Houten Utrecht 3995 EA",
    "addr:housenumber":"164",
    "addr:postcode":"3995 ea",
    "addr:street":"Spoorhaag",
    "iso:country":"NL",
    "sg:address":"Spoorhaag 164",
    "sg:city":"Houten",
    "sg:orig_category":"Wereldwinkels",
    "sg:phone":"+31 30 635 2248",
    "sg:postcode":"3995 EA",
    "sg:province":"Utrecht",
    "wof:name":"Wereldwinkel",
    "wof:placetype":"venue"
},
  "geometry": {"coordinates":[5.1681208611,52.0361022949],"type":"Point"}
}