{
  "type": "Feature",
  "properties": {
    "addr:full":"Louis Davidsstraat 17 Zandvoort North Holland 2042 LS",
    "addr:housenumber":"17",
    "addr:postcode":"2042 ls",
    "addr:street":"Louis Davidsstraat",
    "iso:country":"NL",
    "sg:address":"Louis Davidsstraat 17",
    "sg:city":"Zandvoort",
    "sg:orig_category":"Overheidsdiensten",
    "sg:phone":"+31 23 571 4085",
    "sg:postcode":"2042 LS",
    "sg:province":"North Holland",
    "wof:name":"Stichting Gemeenschapshuis Zandvoort",
    "wof:placetype":"venue"
},
  "geometry": {"coordinates":[4.5315799713,52.372543335],"type":"Point"}
}