{
  "type": "Feature",
  "properties": {
    "addr:full":"Sagenlaan 23 Amersfoort Utrecht 3813 WK",
    "addr:housenumber":"23",
    "addr:postcode":"3813 wk",
    "addr:street":"Sagenlaan",
    "iso:country":"NL",
    "sg:address":"Sagenlaan 23",
    "sg:city":"Amersfoort",
    "sg:orig_category":"Loodgieterswerk, Verwarming And Sanitaire Installaties",
    "sg:phone":"+31 33 480 8676",
    "sg:postcode":"3813 WK",
    "sg:province":"Utrecht",
    "wof:name":"W. Groen",
    "wof:placetype":"venue"
},
  "geometry": {"coordinates":[5.39543,52.173317],"type":"Point"}
}