{
  "type": "Feature",
  "properties": {
    "addr:full":"Pastoor Jutenlaan 6 Bergen Op Zoom North Brabant 4624 GS",
    "addr:housenumber":"6",
    "addr:postcode":"4624 gs",
    "addr:street":"Pastoor Jutenlaan",
    "iso:country":"NL",
    "sg:address":"Pastoor Jutenlaan 6",
    "sg:city":"Bergen Op Zoom",
    "sg:classifiers":[
        {
            "category":"Fast Food",
            "type":"Food & Drink"
        }
    ],
    "sg:phone":"+31 164 259 468",
    "sg:postcode":"4624 GS",
    "sg:province":"North Brabant",
    "sg:tags":[
        "afhaal",
        "restaurant"
    ],
    "wof:name":"Ni Hao Chinees Afhaalcentrum",
    "wof:placetype":"venue"
},
  "geometry": {"coordinates":[4.297875,51.488586],"type":"Point"}
}