{
  "type": "Feature",
  "properties": {
    "addr:full":"Berg En Dalseweg 34 Nijmegen Gelderland 6521 JJ",
    "addr:housenumber":"34",
    "addr:postcode":"6521 jj",
    "addr:street":"Berg En Dalseweg;Gelderland",
    "iso:country":"NL",
    "sg:address":"Berg En Dalseweg 34",
    "sg:city":"Nijmegen",
    "sg:orig_category":"Kinderopvang Behalve Thuis",
    "sg:phone":"+31 24 360 7264",
    "sg:postcode":"6521 JJ",
    "sg:province":"Gelderland",
    "wof:name":"Sterre En Tijl",
    "wof:placetype":"venue"
},
  "geometry": {"coordinates":[5.872897,51.842834],"type":"Point"}
}