{
  "type": "Feature",
  "properties": {
    "addr:full":"Stationspln 14 Veenendaal Utrecht 3901 ES",
    "addr:housenumber":"14",
    "addr:postcode":"3901 es",
    "addr:street":"Stationspln",
    "iso:country":"NL",
    "sg:address":"Stationspln 14",
    "sg:city":"Veenendaal",
    "sg:orig_category":"Kopieerservice",
    "sg:phone":"+31 318 518 900",
    "sg:postcode":"3901 ES",
    "sg:province":"Utrecht",
    "sg:website":"http://www.multicopy.nl",
    "wof:name":"Multicopy Veenendaal",
    "wof:placetype":"venue"
},
  "geometry": {"coordinates":[5.549157,52.02042],"type":"Point"}
}