{
  "type": "Feature",
  "properties": {
    "addr:full":"Basicweg 19 Amersfoort Utrecht 3821 BR",
    "addr:housenumber":"19",
    "addr:postcode":"3821 br",
    "addr:street":"Basicweg",
    "iso:country":"NL",
    "sg:address":"Basicweg 19",
    "sg:city":"Amersfoort",
    "sg:orig_category":"Kantoorapparatuur Gh",
    "sg:phone":"+31 33 456 0910",
    "sg:postcode":"3821 BR",
    "sg:province":"Utrecht",
    "wof:name":"Grahl Nederland Bv",
    "wof:placetype":"venue"
},
  "geometry": {"coordinates":[5.4187421799,52.1739196777],"type":"Point"}
}