{
  "type": "Feature",
  "properties": {
    "addr:full":"Marconistraat 2 Volendam North Holland 1131 JW",
    "addr:housenumber":"2",
    "addr:postcode":"1131 jw",
    "addr:street":"Marconistraat",
    "iso:country":"NL",
    "sg:address":"Marconistraat 2",
    "sg:city":"Volendam",
    "sg:orig_category":"Wegen And Sportterreinen",
    "sg:phone":"+31 299 363 305",
    "sg:postcode":"1131 JW",
    "sg:province":"North Holland",
    "wof:name":"Mastenbroek En Tuyp Bv",
    "wof:placetype":"venue"
},
  "geometry": {"coordinates":[5.0787467957,52.5032272339],"type":"Point"}
}