{
  "type": "Feature",
  "properties": {
    "addr:full":"Winkler Prinsstraat 10 Veendam Groningen 9641 AD",
    "addr:housenumber":"10",
    "addr:postcode":"9641 ad",
    "addr:street":"Winkler Prinsstraat",
    "iso:country":"NL",
    "sg:address":"Winkler Prinsstraat 10",
    "sg:city":"Veendam",
    "sg:orig_category":"Werving And Selectie Van Tijdelijk Personeel And Uitzendkantoren",
    "sg:phone":"+31 598 632 929",
    "sg:postcode":"9641 AD",
    "sg:province":"Groningen",
    "wof:name":"Adecco",
    "wof:placetype":"venue"
},
  "geometry": {"coordinates":[6.8781251907,53.1062507629],"type":"Point"}
}