{
  "type": "Feature",
  "properties": {
    "addr:full":"Eilandsgr 8 Edam Noord-Holland 1135 XN",
    "addr:housenumber":"8",
    "addr:postcode":"1135 xn",
    "addr:street":"Eilandsgr",
    "iso:country":"NL",
    "sg:address":"Eilandsgr 8",
    "sg:city":"Edam",
    "sg:classifiers":[
        {
            "category":"Utilities",
            "subcategory":"Cable",
            "type":"Services"
        }
    ],
    "sg:phone":"+31 299 372 304",
    "sg:postcode":"1135 XN",
    "sg:province":"Noord-Holland",
    "sg:tags":[
        "masseur",
        "en",
        "heilgymnasten"
    ],
    "wof:name":"Hoop, Louise De",
    "wof:placetype":"venue"
},
  "geometry": {"coordinates":[5.049387,52.513599],"type":"Point"}
}