{
  "type": "Feature",
  "properties": {
    "iso:country":"NL",
    "sg:address":"Griftstr 105",
    "sg:city":"Utrecht",
    "sg:orig_category":"Verenigingen En Stichtingen",
    "sg:phone":"+31 30 273 1129",
    "sg:postcode":"3572 GS",
    "sg:province":"Utrecht",
    "wof:name":"Vele Handjes, Sticht",
    "wof:placetype":"venue"
},
  "geometry": {"coordinates":[5.133968,52.098583],"type":"Point"}
}