{
  "type": "Feature",
  "properties": {
    "addr:full":"Oostergoweg 3 Dokkum Friesland 9101 PL",
    "addr:housenumber":"3",
    "addr:postcode":"9101 pl",
    "addr:street":"Oostergoweg",
    "iso:country":"NL",
    "sg:address":"Oostergoweg 3",
    "sg:city":"Dokkum",
    "sg:orig_category":"Goederenvervoer Over De Weg",
    "sg:phone":"+31 519 292 183",
    "sg:postcode":"9101 PL",
    "sg:province":"Friesland",
    "wof:name":"Vof Klaas Westra Transport",
    "wof:placetype":"venue"
},
  "geometry": {"coordinates":[5.978187,53.326748],"type":"Point"}
}