{
  "type": "Feature",
  "properties": {
    "addr:full":"Hallant 9 Hoogvliet Rt Zuid-Holland 3191 SG",
    "addr:housenumber":"9",
    "addr:postcode":"rt;3191 sg",
    "addr:street":"Hallant",
    "iso:country":"NL",
    "sg:address":"Hallant 9",
    "sg:city":"Hoogvliet Rt",
    "sg:orig_category":"Paramedische Behandelingen",
    "sg:phone":"+31 10 416 9313",
    "sg:postcode":"3191 SG",
    "sg:province":"Zuid-Holland",
    "wof:name":"N.G. Van Veen",
    "wof:placetype":"venue"
},
  "geometry": {"coordinates":[4.364061,51.862934],"type":"Point"}
}