{
  "type": "Feature",
  "properties": {
    "addr:full":"De Zonnebaars 50 Bergschenhoek Zuid-Holland 2661 KJ",
    "addr:housenumber":"50",
    "addr:postcode":"2661 kj",
    "addr:street":"De Zonnebaars",
    "iso:country":"NL",
    "sg:address":"De Zonnebaars 50",
    "sg:city":"Bergschenhoek",
    "sg:orig_category":"Diverse Consumentenartikelen Gh",
    "sg:phone":"+31 10 521 4272",
    "sg:postcode":"2661 KJ",
    "sg:province":"Zuid-Holland",
    "wof:name":"Handelsonderneming L.A. Wooning",
    "wof:placetype":"venue"
},
  "geometry": {"coordinates":[4.493215,51.99258],"type":"Point"}
}