{
  "type": "Feature",
  "properties": {
    "addr:full":"Postbus 211 Hoensbroek Limburg 6430 AE",
    "addr:housenumber":"211",
    "addr:postcode":"6430 ae",
    "addr:street":"Postbus",
    "iso:country":"NL",
    "sg:address":"Postbus 211",
    "sg:city":"Hoensbroek",
    "sg:orig_category":"Zalenverhuur",
    "sg:phone":"+31 45 563 6333",
    "sg:postcode":"6430 AE",
    "sg:province":"Limburg",
    "sg:website":"http://www.vanmelick.nl",
    "wof:name":"Kasteelzalen Hoensbroek",
    "wof:placetype":"venue"
},
  "geometry": {"coordinates":[5.92649,50.921539],"type":"Point"}
}