{
  "type": "Feature",
  "properties": {
    "iso:country":"NL",
    "sg:address":"Hekendorpse Buurt 8",
    "sg:city":"Hekendorp",
    "sg:orig_category":"Zuivelproducten And Spijsoli?n Gh",
    "sg:phone":"+31 182 501 468",
    "sg:postcode":"3467 PD",
    "sg:province":"Utrecht",
    "wof:name":"P Th Wiltenburg Pluimveebedrijf",
    "wof:placetype":"venue"
},
  "geometry": {"coordinates":[4.820461,52.017643],"type":"Point"}
}