{
  "type": "Feature",
  "properties": {
    "iso:country":"NL",
    "sg:address":"Industrieweg 11",
    "sg:city":"Vorden",
    "sg:orig_category":"Airconditioning And Ventilatie",
    "sg:phone":"+31 575 557 155",
    "sg:postcode":"7251 JT",
    "sg:province":"Gelderland",
    "wof:name":"Emsbroek Installatietechniek Bv",
    "wof:placetype":"venue"
},
  "geometry": {"coordinates":[6.324009,52.105808],"type":"Point"}
}