{
  "type": "Feature",
  "properties": {
    "addr:full":"T G Gibsonstr 6 Deventer Overijssel 7411 RR",
    "addr:housenumber":"6",
    "addr:postcode":"7411 rr",
    "addr:street":"T;Gibsonstr",
    "iso:country":"NL",
    "sg:address":"T G Gibsonstr 6",
    "sg:city":"Deventer",
    "sg:orig_category":"Postkantoren",
    "sg:phone":"+31 570 641 642",
    "sg:postcode":"7411 RR",
    "sg:province":"Overijssel",
    "sg:website":"http://www.postkantoor.nl",
    "wof:name":"Postkantoor",
    "wof:placetype":"venue"
},
  "geometry": {"coordinates":[6.152702,52.255817],"type":"Point"}
}