{
  "type": "Feature",
  "properties": {
    "addr:full":"Jacob Marisstraat 80 Dordrecht Zuid-Holland 3314 TK",
    "addr:housenumber":"80",
    "addr:postcode":"3314 tk",
    "addr:street":"Jacob Marisstraat",
    "iso:country":"NL",
    "sg:address":"Jacob Marisstraat 80",
    "sg:city":"Dordrecht",
    "sg:classifiers":[
        {
            "category":"Education",
            "subcategory":"Preschool",
            "type":"Public Place"
        }
    ],
    "sg:phone":"+31 78 613 0936",
    "sg:postcode":"3314 TK",
    "sg:province":"Zuid-Holland",
    "sg:tags":[
        "kleuteronderwijs",
        "basis-"
    ],
    "wof:name":"Mondriaan Obs",
    "wof:placetype":"venue"
},
  "geometry": {"coordinates":[4.660173,51.798237],"type":"Point"}
}