{
  "type": "Feature",
  "properties": {
    "iso:country":"NL",
    "sg:address":"Jongkoenstraat 1",
    "sg:city":"Goedereede",
    "sg:orig_category":"Overheidsdiensten",
    "sg:phone":"+31 187 492 321",
    "sg:postcode":"3252 AV",
    "sg:province":"Zuid-Holland",
    "wof:name":"Oostdam",
    "wof:placetype":"venue"
},
  "geometry": {"coordinates":[3.9839520454,51.8191642761],"type":"Point"}
}