{
  "type": "Feature",
  "properties": {
    "addr:full":"Koetserstr 4 Wormer Noord-Holland 1531 NX",
    "addr:housenumber":"4",
    "addr:postcode":"1531 nx",
    "addr:street":"Koetserstr",
    "iso:country":"NL",
    "sg:address":"Koetserstr 4",
    "sg:city":"Wormer",
    "sg:orig_category":"Kantoorbenodigdheden - Fabrieken En Groothandel",
    "sg:phone":"+31 75 642 0256",
    "sg:postcode":"1531 NX",
    "sg:province":"Noord-Holland",
    "wof:name":"Arteur Bv",
    "wof:placetype":"venue"
},
  "geometry": {"coordinates":[4.8112850189,52.4980545044],"type":"Point"}
}