{
  "type": "Feature",
  "properties": {
    "iso:country":"NL",
    "sg:address":"Achterzeedk 57Unit 41",
    "sg:city":"Barendrecht",
    "sg:orig_category":"Wegenbouw",
    "sg:phone":"+31 180 629 111",
    "sg:postcode":"2992 SB",
    "sg:province":"Zuid-Holland",
    "wof:name":"Infra Holland Bv",
    "wof:placetype":"venue"
},
  "geometry": {"coordinates":[4.529279232,51.8352279663],"type":"Point"}
}