{
  "type": "Feature",
  "properties": {
    "addr:full":"Hoenderparklaan 54 Kwintsheul Zuid-Holland 2295 NG",
    "addr:housenumber":"54",
    "addr:postcode":"2295 ng",
    "addr:street":"Hoenderparklaan",
    "iso:country":"NL",
    "sg:address":"Hoenderparklaan 54",
    "sg:city":"Kwintsheul",
    "sg:orig_category":"Huizensloop And Bouwrijp Maken",
    "sg:phone":"+31 174 294 951",
    "sg:postcode":"2295 NG",
    "sg:province":"Zuid-Holland",
    "wof:name":"Aad Van Der Helm Sloopwerken Bv",
    "wof:placetype":"venue"
},
  "geometry": {"coordinates":[4.254905,52.013134],"type":"Point"}
}