{
  "type": "Feature",
  "properties": {
    "addr:full":"K Hoogstr 22 Rotterdam Zuid-Holland 3011 GL",
    "addr:housenumber":"22",
    "addr:postcode":"3011 gl",
    "addr:street":"Hoogstr",
    "iso:country":"NL",
    "sg:address":"K Hoogstr 22",
    "sg:city":"Rotterdam",
    "sg:orig_category":"Glas, Porselein En Aardewerk",
    "sg:phone":"+31 10 411 3338",
    "sg:postcode":"3011 GL",
    "sg:province":"Zuid-Holland",
    "wof:name":"Dille & Kamille",
    "wof:placetype":"venue"
},
  "geometry": {"coordinates":[4.494168,51.922886],"type":"Point"}
}