{
  "type": "Feature",
  "properties": {
    "iso:country":"NL",
    "sg:address":"Dammekant 35A",
    "sg:city":"Bodegraven",
    "sg:orig_category":"Wegenbouw",
    "sg:phone":"+31 172 651 156",
    "sg:postcode":"2411 CA",
    "sg:province":"Zuid-Holland",
    "wof:name":"Wijk Bv, Van",
    "wof:placetype":"venue"
},
  "geometry": {"coordinates":[4.736869812,52.0953865051],"type":"Point"}
}