{
  "type": "Feature",
  "properties": {
    "addr:full":"Dammekant 35A Bodegraven Zuid-Holland 2411 CA",
    "addr:housenumber":"35a",
    "addr:postcode":"2411 ca",
    "addr:street":"Dammekant",
    "iso:country":"NL",
    "sg:address":"Dammekant 35A",
    "sg:city":"Bodegraven",
    "sg:orig_category":"Wegenbouw",
    "sg:phone":"+31 172 651 156",
    "sg:postcode":"2411 CA",
    "sg:province":"Zuid-Holland",
    "wof:name":"Wijk Bv, Van",
    "wof:placetype":"venue"
},
  "geometry": {"coordinates":[4.736869812,52.0953865051],"type":"Point"}
}