{
  "type": "Feature",
  "properties": {
    "addr:full":"Zonnehof 2 Amersfoort Utrecht 3811 NC",
    "addr:housenumber":"2",
    "addr:postcode":"3811 nc",
    "addr:street":"Zonnehof",
    "iso:country":"NL",
    "sg:address":"Zonnehof 2",
    "sg:city":"Amersfoort",
    "sg:orig_category":"Werving And Selectie Van Tijdelijk Personeel And Uitzendkantoren",
    "sg:phone":"+31 33 465 1806",
    "sg:postcode":"3811 NC",
    "sg:province":"Utrecht",
    "wof:name":"Staff Planning Nederland Bv",
    "wof:placetype":"venue"
},
  "geometry": {"coordinates":[5.3833918571,52.1523780823],"type":"Point"}
}