{
  "type": "Feature",
  "properties": {
    "addr:full":"Meuserstr 16 Kerkrade Limburg 6464 EG",
    "addr:housenumber":"16",
    "addr:postcode":"6464 eg",
    "addr:street":"Meuserstr",
    "iso:country":"NL",
    "sg:address":"Meuserstr 16",
    "sg:city":"Kerkrade",
    "sg:orig_category":"Kunststof Ramen",
    "sg:phone":"+31 45 545 7889",
    "sg:postcode":"6464 EG",
    "sg:province":"Limburg",
    "sg:website":"http://www.bodderkad.com",
    "wof:name":"B\u00f6dder Kunststof",
    "wof:placetype":"venue"
},
  "geometry": {"coordinates":[6.08265,50.87735],"type":"Point"}
}