{
  "type": "Feature",
  "properties": {
    "addr:full":"Arendshof 57 Oosterhout Nb Noord-Brabant 4901 LK",
    "addr:housenumber":"57",
    "addr:postcode":"4901 lk",
    "addr:street":"Arendshof",
    "iso:country":"NL",
    "sg:address":"Arendshof 57",
    "sg:city":"Oosterhout Nb",
    "sg:classifiers":[
        {
            "category":"Shopping",
            "subcategory":"Clothing, Apparel, & Fashions",
            "type":"Retail Goods"
        }
    ],
    "sg:phone":"+31 162 455 666",
    "sg:postcode":"4901 LK",
    "sg:province":"Noord-Brabant",
    "sg:tags":[
        "ondergoed",
        "lingerie"
    ],
    "wof:name":"Jambelle Beenmode",
    "wof:placetype":"venue"
},
  "geometry": {"coordinates":[4.854751,51.643845],"type":"Point"}
}