{
  "type": "Feature",
  "properties": {
    "iso:country":"NL",
    "sg:address":"Kempenaar 3307",
    "sg:city":"Lelystad",
    "sg:orig_category":"Bedrijfs- And Managementsconsultants",
    "sg:phone":"+31 320 232 848",
    "sg:postcode":"8231 DH",
    "sg:province":"NL.",
    "wof:name":"J.M. Klok",
    "wof:placetype":"venue"
},
  "geometry": {"coordinates":[5.466698,52.515152],"type":"Point"}
}