{
  "type": "Feature",
  "properties": {
    "addr:full":"Flemingstr 36 Zandvoort Noord-Holland 2041 VJ",
    "addr:housenumber":"36",
    "addr:postcode":"2041 vj",
    "addr:street":"Flemingstr",
    "iso:country":"NL",
    "sg:address":"Flemingstr 36",
    "sg:city":"Zandvoort",
    "sg:orig_category":"Autorijscholen",
    "sg:phone":"+31 6 54357575",
    "sg:postcode":"2041 VJ",
    "sg:province":"Noord-Holland",
    "wof:name":"Simone",
    "wof:placetype":"venue"
},
  "geometry": {"coordinates":[4.54755,52.377888],"type":"Point"}
}