{
  "type": "Feature",
  "properties": {
    "addr:full":"Grootschoterweg 127 Budel Schoot Noord-Brabant 6023 AR",
    "addr:housenumber":"127",
    "addr:postcode":"6023",
    "addr:street":"Grootschoterweg",
    "iso:country":"NL",
    "sg:address":"Grootschoterweg 127",
    "sg:city":"Budel Schoot",
    "sg:orig_category":"Kappers",
    "sg:phone":"+31 495 495 402",
    "sg:postcode":"6023 AR",
    "sg:province":"Noord-Brabant",
    "wof:name":"Jolanda'S Curl & Color",
    "wof:placetype":"venue"
},
  "geometry": {"coordinates":[5.5662469864,51.250629425],"type":"Point"}
}