{
  "type": "Feature",
  "properties": {
    "addr:full":"Kastanjeln 6 Ridderkerk Zuid-Holland 2982 CM",
    "addr:housenumber":"6",
    "addr:postcode":"2982 cm",
    "addr:street":"Kastanjeln",
    "iso:country":"NL",
    "sg:address":"Kastanjeln 6",
    "sg:city":"Ridderkerk",
    "sg:orig_category":"Adviesbureaus Bouwkunde",
    "sg:phone":"+31 180 413 266",
    "sg:postcode":"2982 CM",
    "sg:province":"Zuid-Holland",
    "wof:name":"Ven Bv, Van Der",
    "wof:placetype":"venue"
},
  "geometry": {"coordinates":[4.589058,51.876858],"type":"Point"}
}