{
  "type": "Feature",
  "properties": {
    "addr:full":"Groenewg 7 Hattem Gelderland 8051 KJ",
    "addr:housenumber":"7",
    "addr:postcode":"8051 kj",
    "addr:street":"Groenewg;Gelderland",
    "iso:country":"NL",
    "sg:address":"Groenewg 7",
    "sg:city":"Hattem",
    "sg:classifiers":[
        {
            "category":"Sports & Exercise",
            "subcategory":"Stables",
            "type":"Entertainment"
        }
    ],
    "sg:phone":"+31 38 444 5224",
    "sg:postcode":"8051 KJ",
    "sg:province":"Gelderland",
    "sg:tags":[
        "maneges"
    ],
    "wof:name":"Klock",
    "wof:placetype":"venue"
},
  "geometry": {"coordinates":[6.037554,52.477917],"type":"Point"}
}