{
  "type": "Feature",
  "properties": {
    "addr:full":"Buitenveldertseln 174 Amsterdam Noord-Holland 1081 AC",
    "addr:housenumber":"174",
    "addr:postcode":"1081 ac",
    "iso:country":"NL",
    "sg:address":"Buitenveldertseln 174",
    "sg:city":"Amsterdam",
    "sg:orig_category":"Poeliers",
    "sg:phone":"+31 20 642 2699",
    "sg:postcode":"1081 AC",
    "sg:province":"Noord-Holland",
    "wof:name":"Poelier-Traiteur",
    "wof:placetype":"venue"
},
  "geometry": {"coordinates":[4.868413,52.324921],"type":"Point"}
}