{
  "type": "Feature",
  "properties": {
    "addr:full":"Steenbakkersweg 25 Hengelo Ov Overijssel 7553 EH",
    "addr:housenumber":"25",
    "addr:postcode":"7553 eh",
    "addr:street":"Steenbakkersweg;Ov",
    "iso:country":"NL",
    "sg:address":"Steenbakkersweg 25",
    "sg:city":"Hengelo Ov",
    "sg:orig_category":"Bedrijfs- And Managementsconsultants",
    "sg:phone":"+31 74 243 1962",
    "sg:postcode":"7553 EH",
    "sg:province":"Overijssel",
    "wof:name":"Pas & Rosenboom Organisatie Adviseurs",
    "wof:placetype":"venue"
},
  "geometry": {"coordinates":[6.785261,52.255184],"type":"Point"}
}