{
  "type": "Feature",
  "properties": {
    "addr:full":"Sint Jozefstraat 1 Best Texas 5684 TS",
    "addr:housenumber":"1",
    "addr:postcode":"5684 ts",
    "addr:street":"Sint Jozefstraat",
    "iso:country":"NL",
    "sg:address":"Sint Jozefstraat 1",
    "sg:city":"Best",
    "sg:orig_category":"Overheidsdiensten",
    "sg:phone":"+31 499 371 783",
    "sg:postcode":"5684 TS",
    "sg:province":"Texas",
    "wof:name":"Kadans",
    "wof:placetype":"venue"
},
  "geometry": {"coordinates":[-101.46484375,31.1906394958],"type":"Point"}
}