{
  "type": "Feature",
  "properties": {
    "addr:full":"Schoonoord 66 Voorhout Zuid-Holland 2215 EH",
    "addr:housenumber":"66",
    "addr:postcode":"2215 eh",
    "addr:street":"Schoonoord",
    "iso:country":"NL",
    "sg:address":"Schoonoord 66",
    "sg:city":"Voorhout",
    "sg:orig_category":"Beeldende Kunstenaars",
    "sg:phone":"+31 252 212 757",
    "sg:postcode":"2215 EH",
    "sg:province":"Zuid-Holland",
    "wof:name":"Ende, L Van Den",
    "wof:placetype":"venue"
},
  "geometry": {"coordinates":[4.47737,52.221752],"type":"Point"}
}