{
  "type": "Feature",
  "properties": {
    "addr:full":"Echterstr 9 Maasbracht Limburg 6051 EW",
    "addr:housenumber":"9",
    "addr:postcode":"6051 ew",
    "addr:street":"Echterstr",
    "iso:country":"NL",
    "sg:address":"Echterstr 9",
    "sg:city":"Maasbracht",
    "sg:orig_category":"Scheepsmotoren - Reparatie",
    "sg:phone":"+31 475 463 483",
    "sg:postcode":"6051 EW",
    "sg:province":"Limburg",
    "wof:name":"Hair Vof, W De",
    "wof:placetype":"venue"
},
  "geometry": {"coordinates":[5.8904,51.141666],"type":"Point"}
}