{
  "type": "Feature",
  "properties": {
    "addr:full":"Langs De Kreek 2 Terneuzen Zeeland 4535 CC",
    "addr:housenumber":"2",
    "addr:postcode":"4535 cc",
    "addr:street":"Langs De Kreek",
    "iso:country":"NL",
    "sg:address":"Langs De Kreek 2",
    "sg:city":"Terneuzen",
    "sg:orig_category":"Scheepvaartmijen",
    "sg:phone":"+31 115 612 869",
    "sg:postcode":"4535 CC",
    "sg:province":"Zeeland",
    "wof:name":"Re-Intrade Vof",
    "wof:placetype":"venue"
},
  "geometry": {"coordinates":[3.856963,51.320023],"type":"Point"}
}