{
  "type": "Feature",
  "properties": {
    "addr:full":"Innsbruckwg 72 Rotterdam Zuid-Holland 3047 AH",
    "addr:housenumber":"72",
    "addr:postcode":"3047 ah",
    "addr:street":"Innsbruckwg",
    "iso:country":"NL",
    "sg:address":"Innsbruckwg 72",
    "sg:city":"Rotterdam",
    "sg:orig_category":"Verkoopautomaten",
    "sg:phone":"+31 10 290 6522",
    "sg:postcode":"3047 AH",
    "sg:province":"Zuid-Holland",
    "wof:name":"Vitomatics",
    "wof:placetype":"venue"
},
  "geometry": {"coordinates":[4.413337,51.945225],"type":"Point"}
}