{
  "type": "Feature",
  "properties": {
    "iso:country":"NL",
    "sg:address":"W Barentszwg 101",
    "sg:city":"Heerlen",
    "sg:orig_category":"Zalenverhuur",
    "sg:phone":"+31 45 521 1353",
    "sg:postcode":"6413 TC",
    "sg:province":"Limburg",
    "sg:website":"http://www.hitjesvijver.nl",
    "wof:name":"Hitjesvijver",
    "wof:placetype":"venue"
},
  "geometry": {"coordinates":[5.958549,50.920967],"type":"Point"}
}