{
  "type": "Feature",
  "properties": {
    "addr:full":"Loefzijde 4 Groningen Groningen 9733 EA",
    "addr:housenumber":"4",
    "addr:postcode":"9733 ea",
    "addr:street":"Loefzijde",
    "iso:country":"NL",
    "sg:address":"Loefzijde 4",
    "sg:city":"Groningen",
    "sg:orig_category":"Kinderopvang Behalve Thuis",
    "sg:phone":"+31 50 541 8589",
    "sg:postcode":"9733 EA",
    "sg:province":"Groningen",
    "wof:name":"Kinderdagverblijf Paddeltje (Voik)",
    "wof:placetype":"venue"
},
  "geometry": {"coordinates":[6.616139,53.237835],"type":"Point"}
}