{
  "type": "Feature",
  "properties": {
    "addr:full":"Spaarpot 36 Geldrop Noord-Brabant 5667 KX",
    "addr:housenumber":"36",
    "addr:postcode":"5667 kx",
    "addr:street":"Spaarpot",
    "iso:country":"NL",
    "sg:address":"Spaarpot 36",
    "sg:city":"Geldrop",
    "sg:orig_category":"Metaalbewerking",
    "sg:phone":"+31 40 285 4708",
    "sg:postcode":"5667 KX",
    "sg:province":"Noord-Brabant",
    "wof:name":"Geldrop Bv",
    "wof:placetype":"venue"
},
  "geometry": {"coordinates":[5.556718,51.434235],"type":"Point"}
}