{
  "type": "Feature",
  "properties": {
    "addr:full":"Nijverheidsweg 13 Oudenbosch Noord-Brabant 4731 CZ",
    "addr:housenumber":"13",
    "addr:postcode":"4731",
    "addr:street":"Nijverheidsweg",
    "iso:country":"NL",
    "sg:address":"Nijverheidsweg 13",
    "sg:city":"Oudenbosch",
    "sg:classifiers":[
        {
            "category":"Food & Beverages",
            "subcategory":"Fruits & Vegetables",
            "type":"Retail Goods"
        }
    ],
    "sg:phone":"+31 165 312 606",
    "sg:postcode":"4731 CZ",
    "sg:province":"Noord-Brabant",
    "sg:tags":[
        "groenten"
    ],
    "wof:name":"Q. Teunissen",
    "wof:placetype":"venue"
},
  "geometry": {"coordinates":[4.52967,51.588776],"type":"Point"}
}