{
  "type": "Feature",
  "properties": {
    "iso:country":"NL",
    "sg:address":"Kameraarsweide 6",
    "sg:city":"Nieuwegein",
    "sg:orig_category":"Adviesbureaus Bedrijfsorganisatie",
    "sg:phone":"+31 6 53554551",
    "sg:postcode":"3437 CB",
    "sg:province":"Utrecht",
    "sg:website":"http://www.kingma.biz",
    "wof:name":"Kima Bv",
    "wof:placetype":"venue"
},
  "geometry": {"coordinates":[5.071336,52.041317],"type":"Point"}
}