{
  "type": "Feature",
  "properties": {
    "addr:full":"Herenstr 17 Buren Gld Gelderland 4116 BK",
    "addr:housenumber":"17",
    "addr:postcode":"4116 bk",
    "addr:street":"Herenstr;Gld Gelderland",
    "iso:country":"NL",
    "sg:address":"Herenstr 17",
    "sg:city":"Buren Gld",
    "sg:orig_category":"Adviesbureaus Bedrijfsorganisatie",
    "sg:phone":"+31 344 570 110",
    "sg:postcode":"4116 BK",
    "sg:province":"Gelderland",
    "wof:name":"Lautenbach Bv",
    "wof:placetype":"venue"
},
  "geometry": {"coordinates":[5.334399,51.911972],"type":"Point"}
}