{
  "type": "Feature",
  "properties": {
    "addr:full":"Kon Wilhelminaln 21 Amersfoort Utrecht 3818 HN",
    "addr:housenumber":"21",
    "addr:postcode":"3818 hn",
    "addr:street":"Kon",
    "iso:country":"NL",
    "sg:address":"Kon Wilhelminaln 21",
    "sg:city":"Amersfoort",
    "sg:orig_category":"Adviesbureaus Bedrijfsorganisatie",
    "sg:phone":"+31 33 422 8255",
    "sg:postcode":"3818 HN",
    "sg:province":"Utrecht",
    "sg:website":"http://www.ptg-advies.nl",
    "wof:name":"Pieterse Terwel Grevink Advies Bv",
    "wof:placetype":"venue"
},
  "geometry": {"coordinates":[5.386085,52.152325],"type":"Point"}
}