{
  "type": "Feature",
  "properties": {
    "addr:full":"Hammarskjoldln 617 Ryswyk Zh South Holland 2286 HS",
    "addr:housenumber":"617",
    "addr:postcode":"2286 hs",
    "addr:street":"Ryswyk Zh",
    "iso:country":"NL",
    "sg:address":"Hammarskjoldln 617",
    "sg:city":"Ryswyk Zh",
    "sg:orig_category":"Kappers",
    "sg:phone":"+31 70 396 7705",
    "sg:postcode":"2286 HS",
    "sg:province":"South Holland",
    "wof:name":"Allurage",
    "wof:placetype":"venue"
},
  "geometry": {"coordinates":[4.3243598938,52.0372505188],"type":"Point"}
}