{
  "type": "Feature",
  "properties": {
    "addr:full":"Stationspln 18 Gouda South Holland 2801 AK",
    "addr:housenumber":"18",
    "addr:postcode":"2801 ak",
    "addr:street":"Stationspln",
    "iso:country":"NL",
    "sg:address":"Stationspln 18",
    "sg:city":"Gouda",
    "sg:orig_category":"Bloemen En Planten",
    "sg:phone":"+31 182 515 080",
    "sg:postcode":"2801 AK",
    "sg:province":"South Holland",
    "wof:name":"Bloemenlust",
    "wof:placetype":"venue"
},
  "geometry": {"coordinates":[4.707612,52.017075],"type":"Point"}
}