{
  "type": "Feature",
  "properties": {
    "addr:full":"Boerenbondsweg 2 Bornerbroek Overijssel 7627 LK",
    "addr:housenumber":"2",
    "addr:postcode":"7627 lk",
    "addr:street":"Boerenbondsweg",
    "iso:country":"NL",
    "sg:address":"Boerenbondsweg 2",
    "sg:city":"Bornerbroek",
    "sg:orig_category":"Metaalwerken",
    "sg:phone":"+31 74 384 2089",
    "sg:postcode":"7627 LK",
    "sg:province":"Overijssel",
    "wof:name":"P. Hoekwater",
    "wof:placetype":"venue"
},
  "geometry": {"coordinates":[6.653303,52.309139],"type":"Point"}
}