{
  "type": "Feature",
  "properties": {
    "addr:full":"Dykshoornsewg 17 Den Hoorn Zh South Holland 2635 EJ",
    "addr:housenumber":"17",
    "addr:postcode":"2635 ej",
    "addr:street":"Dykshoornsewg",
    "iso:country":"NL",
    "sg:address":"Dykshoornsewg 17",
    "sg:city":"Den Hoorn Zh",
    "sg:orig_category":"Kappers",
    "sg:phone":"+31 15 262 8227",
    "sg:postcode":"2635 EJ",
    "sg:province":"South Holland",
    "wof:name":"Crijns, Rob",
    "wof:placetype":"venue"
},
  "geometry": {"coordinates":[4.3301639557,52.0003166199],"type":"Point"}
}