{
  "type": "Feature",
  "properties": {
    "addr:full":"Ginnekenstraat 9 Breda Noord-Brabant 4811 JD",
    "addr:housenumber":"9",
    "addr:postcode":"4811 jd",
    "addr:street":"Ginnekenstraat",
    "iso:country":"NL",
    "sg:address":"Ginnekenstraat 9",
    "sg:city":"Breda",
    "sg:orig_category":"Verlichting And Huishoudartikelen",
    "sg:phone":"+31 76 531 0332",
    "sg:postcode":"4811 JD",
    "sg:province":"Noord-Brabant",
    "wof:name":"Xenos Bv",
    "wof:placetype":"venue"
},
  "geometry": {"coordinates":[4.77675,51.585667],"type":"Point"}
}