{
  "type": "Feature",
  "properties": {
    "addr:full":"Heyhoefpromenade 1 Tilburg North Brabant 5043 RA",
    "addr:housenumber":"1",
    "addr:postcode":"5043 ra",
    "addr:street":"Heyhoefpromenade",
    "iso:country":"NL",
    "sg:address":"Heyhoefpromenade 1",
    "sg:city":"Tilburg",
    "sg:orig_category":"Banken",
    "sg:phone":"+31 13 537 9911",
    "sg:postcode":"5043 RA",
    "sg:province":"North Brabant",
    "sg:website":"http://www.rabobank.nl",
    "wof:name":"Rabobank",
    "wof:placetype":"venue"
},
  "geometry": {"coordinates":[5.006351,51.578022],"type":"Point"}
}