{
  "type": "Feature",
  "properties": {
    "iso:country":"NL",
    "sg:address":"Emmastr 22",
    "sg:city":"Amsterdam",
    "sg:orig_category":"Webdesign Bureaus",
    "sg:phone":"+31 20 670 2306",
    "sg:postcode":"1075 HV",
    "sg:province":"Noord-Holland",
    "sg:website":"http://www.3x3.biz",
    "wof:name":"3 X 3",
    "wof:placetype":"venue"
},
  "geometry": {"coordinates":[4.8692851067,52.3535766602],"type":"Point"}
}