{
  "type": "Feature",
  "properties": {
    "addr:full":"Sumatrakd 937 Amsterdam Noord-Holland 1019 RB",
    "addr:housenumber":"937",
    "addr:postcode":"1019 rb",
    "iso:country":"NL",
    "sg:address":"Sumatrakd 937",
    "sg:city":"Amsterdam",
    "sg:classifiers":[
        {
            "category":"Travel",
            "subcategory":"Hotels & Motels",
            "type":"Entertainment"
        }
    ],
    "sg:phone":"+31 20 620 1545",
    "sg:postcode":"1019 RB",
    "sg:province":"Noord-Holland",
    "sg:website":"http://www.flatmates.nl",
    "wof:name":"Flatmates Amsterdam",
    "wof:placetype":"venue"
},
  "geometry": {"coordinates":[4.928483,52.379005],"type":"Point"}
}