{
  "type": "Feature",
  "properties": {
    "addr:full":"Wilhelminastraat 6 Sint Nicolaasga Friesland 8521 JK",
    "addr:housenumber":"6",
    "addr:postcode":"8521 jk",
    "addr:street":"Wilhelminastraat",
    "iso:country":"NL",
    "sg:address":"Wilhelminastraat 6",
    "sg:city":"Sint Nicolaasga",
    "sg:orig_category":"Artiestenbureaus",
    "sg:phone":"+31 513 434 383",
    "sg:postcode":"8521 JK",
    "sg:province":"Friesland",
    "wof:name":"Wigle Ruiter Theater & Evenementen",
    "wof:placetype":"venue"
},
  "geometry": {"coordinates":[5.73816,52.921413],"type":"Point"}
}