{
  "type": "Feature",
  "properties": {
    "addr:full":"Amstel 107 Amsterdam Noord-Holland 1018 EM",
    "addr:housenumber":"107",
    "addr:postcode":"1018 em",
    "addr:street":"Amstel",
    "iso:country":"NL",
    "sg:address":"Amstel 107",
    "sg:city":"Amsterdam",
    "sg:classifiers":[
        {
            "category":"Travel",
            "subcategory":"Hotels & Motels",
            "type":"Entertainment"
        }
    ],
    "sg:phone":"+31 20 623 7068",
    "sg:postcode":"1018 EM",
    "sg:province":"Noord-Holland",
    "sg:website":"http://www.thebridgehotel.nl",
    "wof:name":"Bridge, The",
    "wof:placetype":"venue"
},
  "geometry": {"coordinates":[4.90382,52.362656],"type":"Point"}
}