{
  "type": "Feature",
  "properties": {
    "addr:full":"Kleindorp 26 Merselo Limburg 5815 CL",
    "addr:housenumber":"26",
    "addr:postcode":"5815",
    "addr:street":"Kleindorp",
    "iso:country":"NL",
    "sg:address":"Kleindorp 26",
    "sg:city":"Merselo",
    "sg:orig_category":"Architecten En Architectenbureaus",
    "sg:phone":"+31 478 546 255",
    "sg:postcode":"5815 CL",
    "sg:province":"Limburg",
    "wof:name":"Dijck, A Van",
    "wof:placetype":"venue"
},
  "geometry": {"coordinates":[5.92989,51.53299],"type":"Point"}
}