{
  "type": "Feature",
  "properties": {
    "addr:full":"Postbus 44016 Rotterdam Gelderland 3006 HA",
    "addr:housenumber":"44016",
    "addr:postcode":"3006 ha",
    "addr:street":"Postbus",
    "iso:country":"NL",
    "sg:address":"Postbus 44016",
    "sg:city":"Rotterdam",
    "sg:orig_category":"Webdesign Bureaus",
    "sg:phone":"+31 10 212 1041",
    "sg:postcode":"3006 HA",
    "sg:province":"Gelderland",
    "sg:website":"http://www.webciters.com",
    "wof:name":"Webciters",
    "wof:placetype":"venue"
},
  "geometry": {"coordinates":[4.470749855,51.922618866],"type":"Point"}
}