{
  "type": "Feature",
  "properties": {
    "iso:country":"NL",
    "sg:address":"Hommerterwg 271",
    "sg:city":"Amstenrade",
    "sg:orig_category":"Adviesbureaus Bedrijfsorganisatie",
    "sg:phone":"+31 46 442 5682",
    "sg:postcode":"6436 AK",
    "sg:province":"Limburg",
    "wof:name":"Oals",
    "wof:placetype":"venue"
},
  "geometry": {"coordinates":[5.918746,50.934273],"type":"Point"}
}