{
  "type": "Feature",
  "properties": {
    "addr:full":"Paradijspoort 2 Delft Zuid-Holland 2611 MB",
    "addr:housenumber":"2",
    "addr:postcode":"2611 mb",
    "addr:street":"Paradijspoort",
    "iso:country":"NL",
    "sg:address":"Paradijspoort 2",
    "sg:city":"Delft",
    "sg:classifiers":[
        {
            "category":"Fast Food",
            "type":"Food & Drink"
        }
    ],
    "sg:phone":"+31 15 213 2574",
    "sg:postcode":"2611 MB",
    "sg:province":"Zuid-Holland",
    "sg:tags":[
        "afhaal",
        "restaurant"
    ],
    "wof:name":"Haphoek Bv",
    "wof:placetype":"venue"
},
  "geometry": {"coordinates":[4.362098,52.010387],"type":"Point"}
}