{
  "type": "Feature",
  "properties": {
    "addr:full":"Geldropseweg 59 Eindhoven North Brabant 5611 SC",
    "addr:housenumber":"59",
    "addr:postcode":"5611 sc",
    "addr:street":"Geldropseweg",
    "iso:country":"NL",
    "sg:address":"Geldropseweg 59",
    "sg:city":"Eindhoven",
    "sg:orig_category":"Kunst And Kunstenaarsbenodigdheden",
    "sg:phone":"+31 40 211 3107",
    "sg:postcode":"5611 SC",
    "sg:province":"North Brabant",
    "wof:name":"Frames & Things",
    "wof:placetype":"venue"
},
  "geometry": {"coordinates":[5.488313,51.433895],"type":"Point"}
}