{
  "type": "Feature",
  "properties": {
    "addr:full":"Groenendaal 495 Rotterdam Zuid-Holland 3011 ZW",
    "addr:housenumber":"495",
    "addr:postcode":"3011 zw",
    "addr:street":"Groenendaal",
    "iso:country":"NL",
    "sg:address":"Groenendaal 495",
    "sg:city":"Rotterdam",
    "sg:orig_category":"Kappers",
    "sg:phone":"+31 10 411 9911",
    "sg:postcode":"3011 ZW",
    "sg:province":"Zuid-Holland",
    "sg:website":"http://www.whoopskappers.nl",
    "wof:name":"Whoops",
    "wof:placetype":"venue"
},
  "geometry": {"coordinates":[4.492561,51.921574],"type":"Point"}
}