{
  "type": "Feature",
  "properties": {
    "addr:full":"Rotterdamsewg 248 Delft Zuid-Holland 2628 AS",
    "addr:housenumber":"248",
    "addr:postcode":"delft;2628 as",
    "iso:country":"NL",
    "sg:address":"Rotterdamsewg 248",
    "sg:city":"Delft",
    "sg:orig_category":"Verpakkingsbedrijven",
    "sg:phone":"+31 15 251 1151",
    "sg:postcode":"2628 AS",
    "sg:province":"Zuid-Holland",
    "sg:website":"http://www.hordijk.nl",
    "wof:name":"Hordijk Verpakkingsindustrie Bv",
    "wof:placetype":"venue"
},
  "geometry": {"coordinates":[4.36868,51.999062],"type":"Point"}
}