{
  "type": "Feature",
  "properties": {
    "addr:full":"Heinsbergerweg 66 Melick Limburg 6074 AE",
    "addr:housenumber":"66",
    "addr:postcode":"6074 ae",
    "addr:street":"Heinsbergerweg",
    "iso:country":"NL",
    "sg:address":"Heinsbergerweg 66",
    "sg:city":"Melick",
    "sg:classifiers":[
        {
            "category":"Professional",
            "subcategory":"Accounting & Tax Preparation",
            "type":"Services"
        }
    ],
    "sg:phone":"+31 475 536 276",
    "sg:postcode":"6074 AE",
    "sg:province":"Limburg",
    "sg:tags":[
        "accountant"
    ],
    "wof:name":"Administratiekantoor A.J.J.M. Van Hoof",
    "wof:placetype":"venue"
},
  "geometry": {"coordinates":[6.00641,51.154839],"type":"Point"}
}