{
  "type": "Feature",
  "properties": {
    "addr:full":"Waalstr 44 Utrecht Utrecht 3522 SK",
    "addr:housenumber":"44",
    "addr:postcode":"3522 sk",
    "addr:street":"Waalstr",
    "iso:country":"NL",
    "sg:address":"Waalstr 44",
    "sg:city":"Utrecht",
    "sg:orig_category":"Loodgieters",
    "sg:phone":"+31 30 288 0948",
    "sg:postcode":"3522 SK",
    "sg:province":"Utrecht",
    "wof:name":"Dick Doorn",
    "wof:placetype":"venue"
},
  "geometry": {"coordinates":[5.117261,52.073517],"type":"Point"}
}