{
  "type": "Feature",
  "properties": {
    "addr:full":"Laan Copes V Cattenburch 127 'S Gravenhage Zuid-Holland 2585 EZ",
    "addr:housenumber":"127 '",
    "addr:postcode":"2585 ez",
    "addr:street":"Laan Copes V Cattenburch",
    "iso:country":"NL",
    "sg:address":"Laan Copes V Cattenburch 127",
    "sg:city":"'S Gravenhage",
    "sg:orig_category":"Verzekeringen",
    "sg:phone":"+31 70 360 0913",
    "sg:postcode":"2585 EZ",
    "sg:province":"Zuid-Holland",
    "wof:name":"Van Der Horst Verzekeringen Bv",
    "wof:placetype":"venue"
},
  "geometry": {"coordinates":[4.308103,52.091766],"type":"Point"}
}