{
  "type": "Feature",
  "properties": {
    "addr:full":"Hillevliet 96 Rotterdam Zuid-Holland 3074 KD",
    "addr:housenumber":"96",
    "addr:postcode":"3074 kd",
    "addr:street":"Hillevliet",
    "iso:country":"NL",
    "sg:address":"Hillevliet 96",
    "sg:city":"Rotterdam",
    "sg:classifiers":[
        {
            "category":"Education",
            "subcategory":"Preschool",
            "type":"Public Place"
        }
    ],
    "sg:phone":"+31 10 484 9228",
    "sg:postcode":"3074 KD",
    "sg:province":"Zuid-Holland",
    "sg:tags":[
        "kleuteronderwijs",
        "basis-"
    ],
    "wof:name":"Basisschool Blijvliet",
    "wof:placetype":"venue"
},
  "geometry": {"coordinates":[4.507048,51.895283],"type":"Point"}
}