{
  "type": "Feature",
  "properties": {
    "iso:country":"NL",
    "sg:address":"Stadhoudersln 72",
    "sg:city":"Hoogezand",
    "sg:orig_category":"Autorijscholen",
    "sg:phone":"+31 598 394 336",
    "sg:postcode":"9602 GD",
    "sg:province":"Groningen",
    "wof:name":"Hindriks",
    "wof:placetype":"venue"
},
  "geometry": {"coordinates":[6.754265,53.15551],"type":"Point"}
}