{
  "type": "Feature",
  "properties": {
    "addr:full":"Vyfhuizerdk 208A Vyfhuizen North Holland 2141 BK",
    "addr:housenumber":"208a",
    "addr:postcode":"2141 bk",
    "addr:street":"Vyfhuizen North",
    "iso:country":"NL",
    "sg:address":"Vyfhuizerdk 208A",
    "sg:city":"Vyfhuizen",
    "sg:orig_category":"Onderhoudswerken",
    "sg:phone":"+31 23 540 2040",
    "sg:postcode":"2141 BK",
    "sg:province":"North Holland",
    "wof:name":"Renoplan Vof",
    "wof:placetype":"venue"
},
  "geometry": {"coordinates":[4.679655,52.352299],"type":"Point"}
}