{
  "type": "Feature",
  "properties": {
    "addr:full":"Hamerstr 105 Heerlen Limburg 6411 CV",
    "addr:housenumber":"105",
    "addr:postcode":"6411 cv",
    "iso:country":"NL",
    "sg:address":"Hamerstr 105",
    "sg:city":"Heerlen",
    "sg:orig_category":"Acupunctuur",
    "sg:phone":"+31 45 571 4778",
    "sg:postcode":"6411 CV",
    "sg:province":"Limburg",
    "wof:name":"Cremers, J H H",
    "wof:placetype":"venue"
},
  "geometry": {"coordinates":[5.976906,50.881027],"type":"Point"}
}