{
  "type": "Feature",
  "properties": {
    "addr:full":"Elzenstraat 31 Zundert Noord-Brabant 4881 AT",
    "addr:housenumber":"31",
    "addr:postcode":"4881",
    "addr:street":"Elzenstraat",
    "iso:country":"NL",
    "sg:address":"Elzenstraat 31",
    "sg:city":"Zundert",
    "sg:classifiers":[
        {
            "category":"Communications",
            "subcategory":"Television Station",
            "type":"Services"
        }
    ],
    "sg:phone":"+31 76 597 3203",
    "sg:postcode":"4881 AT",
    "sg:province":"Noord-Brabant",
    "sg:tags":[
        "video",
        "audio",
        "verhuur"
    ],
    "wof:name":"Videotheek Premiere",
    "wof:placetype":"venue"
},
  "geometry": {"coordinates":[4.659071,51.473843],"type":"Point"}
}