{
  "type": "Feature",
  "properties": {
    "addr:full":"Geulstr 98 Terneuzen Zeeland 4535 CZ",
    "addr:housenumber":"98",
    "addr:postcode":"4535",
    "addr:street":"Geulstr",
    "iso:country":"NL",
    "sg:address":"Geulstr 98",
    "sg:city":"Terneuzen",
    "sg:orig_category":"Kappers",
    "sg:phone":"+31 115 621 717",
    "sg:postcode":"4535 CZ",
    "sg:province":"Zeeland",
    "wof:name":"Kapperij, De",
    "wof:placetype":"venue"
},
  "geometry": {"coordinates":[3.8574130535,51.3139915466],"type":"Point"}
}