{
  "type": "Feature",
  "properties": {
    "addr:full":"Paganinistraat 44 Oss Noord-Brabant 5344 CP",
    "addr:housenumber":"44",
    "addr:postcode":"5344 cp",
    "addr:street":"Paganinistraat",
    "iso:country":"NL",
    "sg:address":"Paganinistraat 44",
    "sg:city":"Oss",
    "sg:orig_category":"Juweliers",
    "sg:phone":"+31 412 624 783",
    "sg:postcode":"5344 CP",
    "sg:province":"Noord-Brabant",
    "wof:name":"H. Timmers-V.D. Valk",
    "wof:placetype":"venue"
},
  "geometry": {"coordinates":[-77.235214,38.312599],"type":"Point"}
}