{
  "type": "Feature",
  "properties": {
    "addr:full":"Curacao 18 Apeldoorn Gelderland 7332 BM",
    "addr:housenumber":"18",
    "addr:postcode":"7332 bm",
    "addr:street":"Curacao;Gelderland",
    "iso:country":"NL",
    "sg:address":"Curacao 18",
    "sg:city":"Apeldoorn",
    "sg:orig_category":"Keukens",
    "sg:phone":"+31 55 533 0162",
    "sg:postcode":"7332 BM",
    "sg:province":"Gelderland",
    "wof:name":"Hans Verkerk",
    "wof:placetype":"venue"
},
  "geometry": {"coordinates":[5.986688,52.18375],"type":"Point"}
}