{
  "type": "Feature",
  "properties": {
    "addr:full":"Haling 5 Andijk North Holland 1619 PT",
    "addr:housenumber":"5",
    "addr:postcode":"1619 pt",
    "addr:street":"Haling",
    "iso:country":"NL",
    "sg:address":"Haling 5",
    "sg:city":"Andijk",
    "sg:orig_category":"Bloemen And Planten",
    "sg:phone":"+31 228 597 675",
    "sg:postcode":"1619 PT",
    "sg:province":"North Holland",
    "wof:name":"Kwekerij Jos En Willy",
    "wof:placetype":"venue"
},
  "geometry": {"coordinates":[5.254651,52.719788],"type":"Point"}
}