{
  "type": "Feature",
  "properties": {
    "addr:full":"Franciscuswg 221 Hilversum Noord-Holland 1216 SE",
    "addr:housenumber":"221",
    "addr:postcode":"hilversum;1216 se",
    "iso:country":"NL",
    "sg:address":"Franciscuswg 221",
    "sg:city":"Hilversum",
    "sg:orig_category":"Elektrotechnische Apparatuur - Fabrieken En Groothandel",
    "sg:phone":"+31 35 626 1261",
    "sg:postcode":"1216 SE",
    "sg:province":"Noord-Holland",
    "wof:name":"Weidm\u00fcller Bv",
    "wof:placetype":"venue"
},
  "geometry": {"coordinates":[5.146637,52.214249],"type":"Point"}
}