{
  "type": "Feature",
  "properties": {
    "addr:full":"Manderseweg 82 Vasse Overijssel 7661 RD",
    "addr:housenumber":"82",
    "addr:postcode":"7661 rd",
    "addr:street":"Manderseweg",
    "iso:country":"NL",
    "sg:address":"Manderseweg 82",
    "sg:city":"Vasse",
    "sg:orig_category":"Verlichting And Huishoudartikelen",
    "sg:phone":"+31 541 680 275",
    "sg:postcode":"7661 RD",
    "sg:province":"Overijssel",
    "wof:name":"Firma Rozendaal",
    "wof:placetype":"venue"
},
  "geometry": {"coordinates":[-79.281837,35.257744],"type":"Point"}
}