{
  "type": "Feature",
  "properties": {
    "addr:full":"Lindeldijk 8 Radewijk Overijssel 7791 RC",
    "addr:housenumber":"8",
    "addr:postcode":"7791 rc",
    "addr:street":"Lindeldijk",
    "iso:country":"NL",
    "sg:address":"Lindeldijk 8",
    "sg:city":"Radewijk",
    "sg:orig_category":"Kappers",
    "sg:phone":"+31 523 216 594",
    "sg:postcode":"7791 RC",
    "sg:province":"Overijssel",
    "wof:name":"Annie Veneman",
    "wof:placetype":"venue"
},
  "geometry": {"coordinates":[6.7206802368,52.5750007629],"type":"Point"}
}