{
  "type": "Feature",
  "properties": {
    "iso:country":"NL",
    "sg:address":"Berthradisstr 4",
    "sg:city":"Kerkrade",
    "sg:orig_category":"Geluidsopnamestudio'S",
    "sg:phone":"+31 45 566 1892",
    "sg:postcode":"6467 AW",
    "sg:province":"Limburg",
    "wof:name":"Ab, .",
    "wof:placetype":"venue"
},
  "geometry": {"coordinates":[6.037639,50.865547],"type":"Point"}
}