{
  "type": "Feature",
  "properties": {
    "addr:full":"Pr Hendrikln 45 Amsterdam Noord-Holland 1075 BA",
    "addr:housenumber":"45",
    "addr:postcode":"1075 ba",
    "iso:country":"NL",
    "sg:address":"Pr Hendrikln 45",
    "sg:city":"Amsterdam",
    "sg:orig_category":"Verzekeringen - Verzekeringskantoren",
    "sg:phone":"+31 20 673 5811",
    "sg:postcode":"1075 BA",
    "sg:province":"Noord-Holland",
    "wof:name":"Lippmann Bv, W B D",
    "wof:placetype":"venue"
},
  "geometry": {"coordinates":[4.860975,52.353287],"type":"Point"}
}