{
  "type": "Feature",
  "properties": {
    "addr:full":"Postbus 213 Winschoten Groningen 9670 AE",
    "addr:housenumber":"213",
    "addr:postcode":"9670 ae",
    "addr:street":"Postbus",
    "iso:country":"NL",
    "sg:address":"Postbus 213",
    "sg:city":"Winschoten",
    "sg:orig_category":"Verbouwingen",
    "sg:phone":"+31 597 431 063",
    "sg:postcode":"9670 AE",
    "sg:province":"Groningen",
    "wof:name":"Omb",
    "wof:placetype":"venue"
},
  "geometry": {"coordinates":[7.045145,53.14658],"type":"Point"}
}