{
  "type": "Feature",
  "properties": {
    "addr:full":"Oudemansstr 1 S Gravenhage Zuid-Holland 2522 SB",
    "addr:housenumber":"1;gravenhage",
    "addr:postcode":"2522 sb",
    "addr:street":"Oudemansstr;S",
    "iso:country":"NL",
    "sg:address":"Oudemansstr 1",
    "sg:city":"S Gravenhage",
    "sg:orig_category":"Kappers",
    "sg:phone":"+31 70 399 6325",
    "sg:postcode":"2522 SB",
    "sg:province":"Zuid-Holland",
    "wof:name":"Hoeven, D M Van Der",
    "wof:placetype":"venue"
},
  "geometry": {"coordinates":[4.3272900581,52.0608482361],"type":"Point"}
}