{
  "type": "Feature",
  "properties": {
    "addr:full":"Professor Vd Waalsln 26 Voorschoten Zuid-Holland 2251 GH",
    "addr:housenumber":"26",
    "addr:postcode":"2251 gh",
    "addr:street":"Professor",
    "iso:country":"NL",
    "sg:address":"Professor Vd Waalsln 26",
    "sg:city":"Voorschoten",
    "sg:orig_category":"Kinderopvang Behalve Thuis",
    "sg:phone":"+31 71 561 6202",
    "sg:postcode":"2251 GH",
    "sg:province":"Zuid-Holland",
    "wof:name":"Peuterspeelzaal Pippeloentje",
    "wof:placetype":"venue"
},
  "geometry": {"coordinates":[4.451967,52.124306],"type":"Point"}
}