{
  "type": "Feature",
  "properties": {
    "iso:country":"NL",
    "sg:address":"Zuiddk 109-111",
    "sg:city":"Zaandam",
    "sg:orig_category":"Meubelen",
    "sg:phone":"+31 75 616 3985",
    "sg:postcode":"1501 CD",
    "sg:province":"North Holland",
    "wof:name":"Elswijk Wooncomfort",
    "wof:placetype":"venue"
},
  "geometry": {"coordinates":[4.830471,52.437782],"type":"Point"}
}