{
  "type": "Feature",
  "properties": {
    "addr:full":"Noorderbuurt 11 Drachten Friesland 9203 AK",
    "addr:housenumber":"11",
    "addr:postcode":"9203 ak",
    "addr:street":"Noorderbuurt",
    "iso:country":"NL",
    "sg:address":"Noorderbuurt 11",
    "sg:city":"Drachten",
    "sg:orig_category":"Opticiens",
    "sg:phone":"+31 512 513 495",
    "sg:postcode":"9203 AK",
    "sg:province":"Friesland",
    "wof:name":"Optiek Bangma",
    "wof:placetype":"venue"
},
  "geometry": {"coordinates":[6.0978741646,53.1070632935],"type":"Point"}
}