{
  "type": "Feature",
  "properties": {
    "addr:full":"Groenestr 265 Nymegen Gelderland 6531 HK",
    "addr:housenumber":"265",
    "addr:postcode":"6531 hk",
    "addr:street":"Nymegen Gelderland",
    "iso:country":"NL",
    "sg:address":"Groenestr 265",
    "sg:city":"Nymegen",
    "sg:orig_category":"Gasapparaten En -Artikelen - Fabrieken En Groothandel",
    "sg:phone":"+31 24 352 3100",
    "sg:postcode":"6531 HK",
    "sg:province":"Gelderland",
    "wof:name":"Smit Bv",
    "wof:placetype":"venue"
},
  "geometry": {"coordinates":[114.153542,22.411249],"type":"Point"}
}