{
  "type": "Feature",
  "properties": {
    "iso:country":"NL",
    "sg:address":"H Stokstr 2A",
    "sg:city":"Heeswyk Dinther",
    "sg:orig_category":"Kappers",
    "sg:phone":"+31 413 292 897",
    "sg:postcode":"5473 GL",
    "sg:province":"Noord-Brabant",
    "wof:name":"Mirelle Hairstyling",
    "wof:placetype":"venue"
},
  "geometry": {"coordinates":[5.46889,51.650845],"type":"Point"}
}