{
  "type": "Feature",
  "properties": {
    "iso:country":"NL",
    "sg:address":"Roerdompln 104",
    "sg:city":"Aalsmeer",
    "sg:orig_category":"Mensendieck - Oefentherapeuten",
    "sg:phone":"+31 297 344 547",
    "sg:postcode":"1431 WL",
    "sg:province":"Noord-Holland",
    "wof:name":"Roeleveld, C M",
    "wof:placetype":"venue"
},
  "geometry": {"coordinates":[4.759831,52.254906],"type":"Point"}
}