{
  "type": "Feature",
  "properties": {
    "addr:full":"Ruttensingel 59 Maastricht Limburg 6214 SL",
    "addr:housenumber":"59",
    "addr:postcode":"6214 sl",
    "addr:street":"Ruttensingel",
    "iso:country":"NL",
    "sg:address":"Ruttensingel 59",
    "sg:city":"Maastricht",
    "sg:orig_category":"Fietshandelaren",
    "sg:phone":"+31 43 325 0662",
    "sg:postcode":"6214 SL",
    "sg:province":"Limburg",
    "wof:name":"Rijwielhandel George Walstock",
    "wof:placetype":"venue"
},
  "geometry": {"coordinates":[5.673866,50.84647],"type":"Point"}
}