{
  "type": "Feature",
  "properties": {
    "iso:country":"NL",
    "sg:address":"Markt 9",
    "sg:city":"Lichtenvoorde",
    "sg:orig_category":"Fotolaboratoria",
    "sg:phone":"+31 544 374 636",
    "sg:postcode":"7131 DG",
    "sg:province":"Gelderland",
    "wof:name":"Primeur Printing",
    "wof:placetype":"venue"
},
  "geometry": {"coordinates":[6.567517,51.987152],"type":"Point"}
}