{
  "type": "Feature",
  "properties": {
    "addr:full":"Schumannstr 18 Hengelo Ov NL.08 7557 VB",
    "addr:housenumber":"18",
    "addr:postcode":"7557 vb",
    "addr:street":"Schumannstr;Ov",
    "iso:country":"NL",
    "sg:address":"Schumannstr 18",
    "sg:city":"Hengelo Ov",
    "sg:orig_category":"Modevakscholen",
    "sg:phone":"+31 74 243 2397",
    "sg:postcode":"7557 VB",
    "sg:province":"NL.08",
    "wof:name":"Will",
    "wof:placetype":"venue"
},
  "geometry": {"coordinates":[6.820137,52.271484],"type":"Point"}
}