{
  "type": "Feature",
  "properties": {
    "iso:country":"NL",
    "sg:address":"Bilgaardpassage 49",
    "sg:city":"Leeuwarden",
    "sg:classifiers":[
        {
            "category":"Fast Food",
            "type":"Food & Drink"
        }
    ],
    "sg:phone":"+31 58 266 6589",
    "sg:postcode":"8918 HT",
    "sg:province":"Friesland",
    "sg:tags":[
        "afhaal",
        "restaurant"
    ],
    "wof:name":"Eatcorner Bilgaard",
    "wof:placetype":"venue"
},
  "geometry": {"coordinates":[5.794489,53.215351],"type":"Point"}
}