{
  "type": "Feature",
  "properties": {
    "iso:country":"NL",
    "sg:address":"Berkenln 20 Sec",
    "sg:city":"St Michielsgestel",
    "sg:orig_category":"Verenigingen En Stichtingen",
    "sg:phone":"+31 73 551 4045",
    "sg:postcode":"5271 NH",
    "sg:province":"North Brabant",
    "wof:name":"Nvvh Afdeling Vught/Den Bosch",
    "wof:placetype":"venue"
},
  "geometry": {"coordinates":[5.35092,51.638424],"type":"Point"}
}