{
  "type": "Feature",
  "properties": {
    "addr:full":"W De Zwygerln 126 Castricum North Holland 1901 CT",
    "addr:housenumber":"126",
    "addr:postcode":"1901 ct",
    "addr:street":"W De Zwygerln",
    "iso:country":"NL",
    "sg:address":"W De Zwygerln 126",
    "sg:city":"Castricum",
    "sg:classifiers":[
        {
            "category":"Retail",
            "subcategory":"Auto Repair",
            "type":"Services"
        }
    ],
    "sg:phone":"+31 251 653 119",
    "sg:postcode":"1901 CT",
    "sg:province":"North Holland",
    "sg:tags":[
        "garage"
    ],
    "wof:name":"Riet, J Van",
    "wof:placetype":"venue"
},
  "geometry": {"coordinates":[4.663725,52.546844],"type":"Point"}
}