{
  "type": "Feature",
  "properties": {
    "addr:full":"Commelinstr 217 Amsterdam Noord-Holland 1093 TP",
    "addr:housenumber":"217",
    "addr:postcode":"1093 tp",
    "iso:country":"NL",
    "sg:address":"Commelinstr 217",
    "sg:city":"Amsterdam",
    "sg:orig_category":"Natuurvoeding En Reformartikelen",
    "sg:phone":"+31 20 692 4584",
    "sg:postcode":"1093 TP",
    "sg:province":"Noord-Holland",
    "sg:website":"http://www.life.nl",
    "wof:name":"New Life Development",
    "wof:placetype":"venue"
},
  "geometry": {"coordinates":[4.92917,52.364456],"type":"Point"}
}