{
  "type": "Feature",
  "properties": {
    "iso:country":"NL",
    "sg:address":"Nieuwstr 23",
    "sg:city":"S Hertogenbosch",
    "sg:orig_category":"Geluidsopnamestudio'S",
    "sg:phone":"+31 73 612 7016",
    "sg:postcode":"5211 NL",
    "sg:province":"Noord-Brabant",
    "sg:website":"http://www.adkonline.nl",
    "wof:name":"Adk Studio",
    "wof:placetype":"venue"
},
  "geometry": {"coordinates":[5.29824,51.69075],"type":"Point"}
}