{
  "type": "Feature",
  "properties": {
    "addr:full":"Groenepad 18 Kwintsheul Zuid-Holland 2295 LZ",
    "addr:housenumber":"18",
    "addr:postcode":"2295 lz",
    "addr:street":"Groenepad",
    "iso:country":"NL",
    "sg:address":"Groenepad 18",
    "sg:city":"Kwintsheul",
    "sg:orig_category":"Fruit And Groenten Gh",
    "sg:phone":"+31 174 247 275",
    "sg:postcode":"2295 LZ",
    "sg:province":"Zuid-Holland",
    "wof:name":"A.C. Reygersberg Bv",
    "wof:placetype":"venue"
},
  "geometry": {"coordinates":[4.254787,52.026104],"type":"Point"}
}