{
  "type": "Feature",
  "properties": {
    "iso:country":"NL",
    "sg:address":"Pearl S Buckstraat 5",
    "sg:city":"Haarlem",
    "sg:orig_category":"Verzekeringen",
    "sg:phone":"+31 23 533 8035",
    "sg:postcode":"2037 MG",
    "sg:province":"North Holland",
    "wof:name":"E.H. Van Der Groef Verzekeringsadviseur",
    "wof:placetype":"venue"
},
  "geometry": {"coordinates":[4.669081,52.355518],"type":"Point"}
}