{
  "type": "Feature",
  "properties": {
    "addr:full":"Wilhelminalaan 1 Helmond Noord-Brabant 5707 BS",
    "addr:housenumber":"1",
    "addr:postcode":"5707 bs",
    "addr:street":"Wilhelminalaan",
    "iso:country":"NL",
    "sg:address":"Wilhelminalaan 1",
    "sg:city":"Helmond",
    "sg:orig_category":"Artsen And Specialisten",
    "sg:phone":"+31 492 522 217",
    "sg:postcode":"5707 BS",
    "sg:province":"Noord-Brabant",
    "wof:name":"G. Attalla Huisarts",
    "wof:placetype":"venue"
},
  "geometry": {"coordinates":[5.646218,51.477924],"type":"Point"}
}