{
  "type": "Feature",
  "properties": {
    "addr:full":"Luykenln 9 Roosendaal North Brabant 4707 BT",
    "addr:housenumber":"9",
    "addr:postcode":"4707 bt",
    "addr:street":"Luykenln",
    "iso:country":"NL",
    "sg:address":"Luykenln 9",
    "sg:city":"Roosendaal",
    "sg:orig_category":"Adviesbureaus Automatisering",
    "sg:phone":"+31 165 599 142",
    "sg:postcode":"4707 BT",
    "sg:province":"North Brabant",
    "wof:name":"Proconsult Nederland Bv",
    "wof:placetype":"venue"
},
  "geometry": {"coordinates":[4.458192,51.521458],"type":"Point"}
}