{
  "type": "Feature",
  "properties": {
    "iso:country":"NL",
    "sg:address":"De Havik 75",
    "sg:city":"Denekamp",
    "sg:orig_category":"Modevakscholen",
    "sg:phone":"+31 541 352 700",
    "sg:postcode":"7591 JW",
    "sg:province":"Overijssel",
    "wof:name":"Westerhoff-Kuilder, R",
    "wof:placetype":"venue"
},
  "geometry": {"coordinates":[7.007398,52.385883],"type":"Point"}
}