{
  "type": "Feature",
  "properties": {
    "addr:full":"Herenweg 16 Sittard North Rhine-Westphalia 6132 HR",
    "addr:housenumber":"16",
    "addr:postcode":"6132 hr",
    "addr:street":"Herenweg",
    "iso:country":"NL",
    "sg:address":"Herenweg 16",
    "sg:city":"Sittard",
    "sg:orig_category":"Fotostudio'S And Fotografen",
    "sg:phone":"+31 46 452 8449",
    "sg:postcode":"6132 HR",
    "sg:province":"North Rhine-Westphalia",
    "wof:name":"Studio 51 Fotografie & Modelagency",
    "wof:placetype":"venue"
},
  "geometry": {"coordinates":[5.901738,50.993095],"type":"Point"}
}