{
  "type": "Feature",
  "properties": {
    "addr:full":"Molenstraat 3 Oudewater Utrecht 3421 CL",
    "addr:housenumber":"3",
    "addr:postcode":"3421",
    "addr:street":"Molenstraat",
    "iso:country":"NL",
    "sg:address":"Molenstraat 3",
    "sg:city":"Oudewater",
    "sg:classifiers":[
        {
            "category":"Shopping",
            "subcategory":"Music",
            "type":"Retail Goods"
        }
    ],
    "sg:phone":"+31 348 563 988",
    "sg:postcode":"3421 CL",
    "sg:province":"Utrecht",
    "sg:tags":[
        "-import",
        "autotussenhandel"
    ],
    "wof:name":"Autobedrijf Colje",
    "wof:placetype":"venue"
},
  "geometry": {"coordinates":[4.871121,52.02042],"type":"Point"}
}