{
  "type": "Feature",
  "properties": {
    "iso:country":"NL",
    "sg:address":"Boergoensestraat 17",
    "sg:city":"Rotterdam",
    "sg:orig_category":"Verlichting And Huishoudartikelen",
    "sg:phone":"+31 10 429 2003",
    "sg:postcode":"3082 KA",
    "sg:province":"Zuid-Holland",
    "wof:name":"Bikalux Bv",
    "wof:placetype":"venue"
},
  "geometry": {"coordinates":[4.469902,51.891655],"type":"Point"}
}