{
  "type": "Feature",
  "properties": {
    "addr:full":"De Clomp 3316 Zeist Utrecht 3704 KB",
    "addr:housenumber":"3316",
    "addr:postcode":"3704 kb",
    "addr:street":"De Clomp",
    "iso:country":"NL",
    "sg:address":"De Clomp 3316",
    "sg:city":"Zeist",
    "sg:orig_category":"Zuivelproducten",
    "sg:phone":"+31 30 695 5333",
    "sg:postcode":"3704 KB",
    "sg:province":"Utrecht",
    "wof:name":"Peterse Kaas",
    "wof:placetype":"venue"
},
  "geometry": {"coordinates":[5.220578,52.083828],"type":"Point"}
}