{
  "type": "Feature",
  "properties": {
    "iso:country":"NL",
    "sg:address":"Heuvelpoort 308E",
    "sg:city":"Tilburg",
    "sg:orig_category":"Architecten",
    "sg:phone":"+31 13 536 6028",
    "sg:postcode":"5038 DT",
    "sg:province":"Noord-Brabant",
    "wof:name":"Architectenburo F. Jongen",
    "wof:placetype":"venue"
},
  "geometry": {"coordinates":[5.090747,51.556881],"type":"Point"}
}