{
  "type": "Feature",
  "properties": {
    "addr:full":"1E Lulofsdwstr 106 S Gravenhage Zuid-Holland 2521 AZ",
    "addr:housenumber":"106;gravenhage",
    "addr:postcode":"2521 az",
    "addr:street":"1E Lulofsdwstr;S",
    "iso:country":"NL",
    "sg:address":"1E Lulofsdwstr 106",
    "sg:city":"S Gravenhage",
    "sg:classifiers":[
        {
            "category":"Retail",
            "subcategory":"Auto Repair",
            "type":"Services"
        }
    ],
    "sg:phone":"+31 70 389 4707",
    "sg:postcode":"2521 AZ",
    "sg:province":"Zuid-Holland",
    "sg:tags":[
        "garage"
    ],
    "wof:name":"Alicar",
    "wof:placetype":"venue"
},
  "geometry": {"coordinates":[4.32071,52.062988],"type":"Point"}
}