{
  "type": "Feature",
  "properties": {
    "addr:full":"Egelstr 2 Eindhoven North Brabant 5622 AK",
    "addr:housenumber":"2",
    "addr:postcode":"5622 ak",
    "addr:street":"Egelstr",
    "iso:country":"NL",
    "sg:address":"Egelstr 2",
    "sg:city":"Eindhoven",
    "sg:orig_category":"Adviesbureaus Bouwkunde",
    "sg:phone":"+31 40 246 1729",
    "sg:postcode":"5622 AK",
    "sg:province":"North Brabant",
    "wof:name":"Watering, Van De",
    "wof:placetype":"venue"
},
  "geometry": {"coordinates":[5.467158,51.454273],"type":"Point"}
}