{
  "type": "Feature",
  "properties": {
    "addr:full":"Onder Zeil 27 Enkhuizen Noord-Holland 1602 HZ",
    "addr:housenumber":"27",
    "addr:postcode":"1602 hz",
    "addr:street":"Onder Zeil",
    "iso:country":"NL",
    "sg:address":"Onder Zeil 27",
    "sg:city":"Enkhuizen",
    "sg:orig_category":"Webdesign Bureaus",
    "sg:phone":"+31 6 13630823",
    "sg:postcode":"1602 HZ",
    "sg:province":"Noord-Holland",
    "sg:website":"http://www.skillwebdesgin.nl",
    "wof:name":"Skill",
    "wof:placetype":"venue"
},
  "geometry": {"coordinates":[5.2723097801,52.7189445496],"type":"Point"}
}