{
  "type": "Feature",
  "properties": {
    "addr:full":"St Hubertusstr 6 Venlo Limburg 5921 GW",
    "addr:housenumber":"6",
    "addr:postcode":"5921 gw",
    "iso:country":"NL",
    "sg:address":"St Hubertusstr 6",
    "sg:city":"Venlo",
    "sg:orig_category":"Webdesign Bureaus",
    "sg:phone":"+31 77 387 1840",
    "sg:postcode":"5921 GW",
    "sg:province":"Limburg",
    "sg:website":"http://www.compuhosting.nl",
    "wof:name":"Compuhosting",
    "wof:placetype":"venue"
},
  "geometry": {"coordinates":[6.152493,51.3655548096],"type":"Point"}
}