{
  "type": "Feature",
  "properties": {
    "addr:full":"Da Costastr 3-11 Papendrecht Zuid-Holland 3351 EA",
    "addr:housenumber":"3-11",
    "addr:postcode":"papendrecht;3351 ea",
    "iso:country":"NL",
    "sg:address":"Da Costastr 3-11",
    "sg:city":"Papendrecht",
    "sg:orig_category":"Montagebedrijven",
    "sg:phone":"+31 78 642 9986",
    "sg:postcode":"3351 EA",
    "sg:province":"Zuid-Holland",
    "sg:website":"http://www.keukenstarter.nl",
    "wof:name":"Berg En Frank Montage, Van Den",
    "wof:placetype":"venue"
},
  "geometry": {"coordinates":[4.67725,51.829845],"type":"Point"}
}