{
  "type": "Feature",
  "properties": {
    "addr:full":"Melkpad 22 Hilversum North Holland 1217 KD",
    "addr:housenumber":"22",
    "addr:postcode":"1217 kd",
    "addr:street":"Melkpad",
    "iso:country":"NL",
    "sg:address":"Melkpad 22",
    "sg:city":"Hilversum",
    "sg:orig_category":"Verzekeringen - Verzekeringskantoren",
    "sg:phone":"+31 35 622 2080",
    "sg:postcode":"1217 KD",
    "sg:province":"North Holland",
    "sg:website":"http://www.vlra.nl",
    "wof:name":"Lanschot Rosenthal Holding Bv, Van",
    "wof:placetype":"venue"
},
  "geometry": {"coordinates":[5.172375,52.227592],"type":"Point"}
}