{
  "type": "Feature",
  "properties": {
    "addr:full":"Tolick 72 Hoogland Utrecht 3828 HG",
    "addr:housenumber":"72",
    "addr:postcode":"3828 hg",
    "addr:street":"Tolick",
    "iso:country":"NL",
    "sg:address":"Tolick 72",
    "sg:city":"Hoogland",
    "sg:orig_category":"Feestartikelen",
    "sg:phone":"+31 33 480 3871",
    "sg:postcode":"3828 HG",
    "sg:province":"Utrecht",
    "wof:name":"Ballonnetje, Het",
    "wof:placetype":"venue"
},
  "geometry": {"coordinates":[5.371496,52.184883],"type":"Point"}
}