{
  "type": "Feature",
  "properties": {
    "addr:full":"Zandzuigerstraat 83 Almere Flevoland 1333 MX",
    "addr:housenumber":"83",
    "addr:postcode":"1333 mx",
    "addr:street":"Zandzuigerstraat;Flevoland",
    "iso:country":"NL",
    "sg:address":"Zandzuigerstraat 83",
    "sg:city":"Almere",
    "sg:classifiers":[
        {
            "category":"Shopping",
            "subcategory":"Gifts & Souvenirs",
            "type":"Retail Goods"
        }
    ],
    "sg:phone":"+31 36 532 1580",
    "sg:postcode":"1333 MX",
    "sg:province":"Flevoland",
    "sg:tags":[
        "geschenken"
    ],
    "wof:name":"Inzicht Vof",
    "wof:placetype":"venue"
},
  "geometry": {"coordinates":[5.26536,52.402523],"type":"Point"}
}