{
  "type": "Feature",
  "properties": {
    "addr:full":"Zwaluwenwg 11 Soest Utrecht 3762 VC",
    "addr:housenumber":"11",
    "addr:postcode":"3762 vc",
    "addr:street":"Zwaluwenwg",
    "iso:country":"NL",
    "sg:address":"Zwaluwenwg 11",
    "sg:city":"Soest",
    "sg:orig_category":"Bedrijfsopleidingen",
    "sg:phone":"+31 35 602 2437",
    "sg:postcode":"3762 VC",
    "sg:province":"Utrecht",
    "wof:name":"Hove, Ten",
    "wof:placetype":"venue"
},
  "geometry": {"coordinates":[5.280151,52.18034],"type":"Point"}
}