{
  "type": "Feature",
  "properties": {
    "addr:full":"Heemskerckstraat 20 Oudeschild Noord-Holland 1792 AB",
    "addr:housenumber":"20",
    "addr:postcode":"1792 ab",
    "addr:street":"Heemskerckstraat",
    "iso:country":"NL",
    "sg:address":"Heemskerckstraat 20",
    "sg:city":"Oudeschild",
    "sg:orig_category":"Meubeltextiel Fab",
    "sg:phone":"+31 222 313 272",
    "sg:postcode":"1792 AB",
    "sg:province":"Noord-Holland",
    "wof:name":"Zeilmakerij Texel",
    "wof:placetype":"venue"
},
  "geometry": {"coordinates":[4.846975,53.039562],"type":"Point"}
}