{
  "type": "Feature",
  "properties": {
    "addr:full":"Voorstr 7 Sommelsdyk Zuid-Holland 3245 BG",
    "addr:housenumber":"7",
    "addr:postcode":"3245",
    "addr:street":"Voorstr",
    "iso:country":"NL",
    "sg:address":"Voorstr 7",
    "sg:city":"Sommelsdyk",
    "sg:orig_category":"Keuringsdiensten",
    "sg:phone":"+31 187 484 150",
    "sg:postcode":"3245 BG",
    "sg:province":"Zuid-Holland",
    "wof:name":"Tielec Bv",
    "wof:placetype":"venue"
},
  "geometry": {"coordinates":[4.151291,51.76078],"type":"Point"}
}