{
  "type": "Feature",
  "properties": {
    "addr:full":"Maliskampsestr 35 Rosmalen Noord-Brabant 5248 AC",
    "addr:housenumber":"35",
    "addr:postcode":"5248 ac",
    "addr:street":"Maliskampsestr",
    "iso:country":"NL",
    "sg:address":"Maliskampsestr 35",
    "sg:city":"Rosmalen",
    "sg:orig_category":"Administratie- En Boekhoudkantoren",
    "sg:phone":"+31 73 521 5608",
    "sg:postcode":"5248 AC",
    "sg:province":"Noord-Brabant",
    "wof:name":"Kitslaar",
    "wof:placetype":"venue"
},
  "geometry": {"coordinates":[5.382469,51.705528],"type":"Point"}
}