{
  "type": "Feature",
  "properties": {
    "addr:full":"Veemarktkade 8 'S Hertogenbosch Noord-Brabant 5222 AE",
    "addr:housenumber":"8 ' s",
    "addr:postcode":"5222 ae",
    "addr:street":"Veemarktkade",
    "iso:country":"NL",
    "sg:address":"Veemarktkade 8",
    "sg:city":"'S Hertogenbosch",
    "sg:orig_category":"Koeriersdiensten",
    "sg:phone":"+31 73 641 8108",
    "sg:postcode":"5222 AE",
    "sg:province":"Noord-Brabant",
    "wof:name":"A. Kentie & Zoon Vof",
    "wof:placetype":"venue"
},
  "geometry": {"coordinates":[5.286376,51.70314],"type":"Point"}
}