{
  "type": "Feature",
  "properties": {
    "iso:country":"NL",
    "sg:address":"Dillenburg 5",
    "sg:city":"Leerdam",
    "sg:orig_category":"Adviesbureaus Bedrijfsorganisatie",
    "sg:phone":"+31 345 614 951",
    "sg:postcode":"4141 JL",
    "sg:province":"Zuid-Holland",
    "wof:name":"Ave International Management Consultancy Bv",
    "wof:placetype":"venue"
},
  "geometry": {"coordinates":[5.106026,51.89315],"type":"Point"}
}