{
  "type": "Feature",
  "properties": {
    "addr:full":"Henegouwen 47 Leusden Utrecht 3831 AD",
    "addr:housenumber":"47",
    "addr:postcode":"3831 ad",
    "addr:street":"Henegouwen",
    "iso:country":"NL",
    "sg:address":"Henegouwen 47",
    "sg:city":"Leusden",
    "sg:orig_category":"Helikopters",
    "sg:phone":"+31 33 432 1775",
    "sg:postcode":"3831 AD",
    "sg:province":"Utrecht",
    "wof:name":"Helitech",
    "wof:placetype":"venue"
},
  "geometry": {"coordinates":[5.436747,52.135563],"type":"Point"}
}