{
  "type": "Feature",
  "properties": {
    "addr:full":"Van Heemstraweg 9 Ewijk Gelderland 6644 KE",
    "addr:housenumber":"9",
    "addr:postcode":"6644 ke",
    "addr:street":"Van Heemstraweg;Gelderland",
    "iso:country":"NL",
    "sg:address":"Van Heemstraweg 9",
    "sg:city":"Ewijk",
    "sg:orig_category":"Levende Dieren Gh",
    "sg:phone":"+31 487 521 314",
    "sg:postcode":"6644 KE",
    "sg:province":"Gelderland",
    "wof:name":"Ruud Cobussen Schapenhandel",
    "wof:placetype":"venue"
},
  "geometry": {"coordinates":[5.740267,51.873154],"type":"Point"}
}