{
  "type": "Feature",
  "properties": {
    "iso:country":"NL",
    "sg:address":"Rysbergsewg 354",
    "sg:city":"Breda",
    "sg:orig_category":"Verenigingsgebouwen",
    "sg:phone":"+31 76 514 1086",
    "sg:postcode":"4838 EG",
    "sg:province":"North Brabant",
    "wof:name":"Kievitslaar",
    "wof:placetype":"venue"
},
  "geometry": {"coordinates":[4.730764,51.554642],"type":"Point"}
}