{
  "type": "Feature",
  "properties": {
    "addr:full":"Maalbroek 116 Roermond Limburg 6042 KN",
    "addr:housenumber":"116",
    "addr:postcode":"6042 kn",
    "addr:street":"Maalbroek",
    "iso:country":"NL",
    "sg:address":"Maalbroek 116",
    "sg:city":"Roermond",
    "sg:orig_category":"Verenigingen En Stichtingen",
    "sg:phone":"+31 475 326 426",
    "sg:postcode":"6042 KN",
    "sg:province":"Limburg",
    "wof:name":"Greijhounds In Nood, Nederlandse Sticht",
    "wof:placetype":"venue"
},
  "geometry": {"coordinates":[6.0447,51.19907],"type":"Point"}
}