{
  "type": "Feature",
  "properties": {
    "addr:full":"Zuidzijde 54 Bodegraven South Holland 2411 RS",
    "addr:housenumber":"54",
    "addr:postcode":"2411 rs",
    "addr:street":"Zuidzijde",
    "iso:country":"NL",
    "sg:address":"Zuidzijde 54",
    "sg:city":"Bodegraven",
    "sg:orig_category":"Houten Verpakkingen Fab",
    "sg:phone":"+31 172 611 680",
    "sg:postcode":"2411 RS",
    "sg:province":"South Holland",
    "wof:name":"Pallethandel Ton Van Pelt Vof",
    "wof:placetype":"venue"
},
  "geometry": {"coordinates":[4.747547,52.085552],"type":"Point"}
}