{
  "type": "Feature",
  "properties": {
    "addr:full":"Ceintuurbaan 25 Huizen Noord-Holland 1271 BE",
    "addr:housenumber":"25",
    "addr:postcode":"1271",
    "addr:street":"Ceintuurbaan",
    "iso:country":"NL",
    "sg:address":"Ceintuurbaan 25",
    "sg:city":"Huizen",
    "sg:orig_category":"Kantoorartikelen",
    "sg:phone":"+31 35 524 4499",
    "sg:postcode":"1271 BE",
    "sg:province":"Noord-Holland",
    "wof:name":"Cires",
    "wof:placetype":"venue"
},
  "geometry": {"coordinates":[5.2339801788,52.2956008911],"type":"Point"}
}