{
  "type": "Feature",
  "properties": {
    "addr:full":"Burg Lemmensstr 3 Geleen Limburg 6163 JA",
    "addr:housenumber":"3",
    "addr:postcode":"6163 ja",
    "addr:street":"Burg Lemmensstr",
    "iso:country":"NL",
    "sg:address":"Burg Lemmensstr 3",
    "sg:city":"Geleen",
    "sg:orig_category":"Woninginrichting",
    "sg:phone":"+31 46 474 8444",
    "sg:postcode":"6163 JA",
    "sg:province":"Limburg",
    "wof:name":"Dreams Bv",
    "wof:placetype":"venue"
},
  "geometry": {"coordinates":[5.8188948631,50.9777259827],"type":"Point"}
}