{
  "type": "Feature",
  "properties": {
    "iso:country":"NL",
    "sg:address":"Jhr D Savornin Lohmanstr 91",
    "sg:city":"Zuidland",
    "sg:orig_category":"Boekhouders",
    "sg:phone":"+31 181 452 996",
    "sg:postcode":"3214 XA",
    "sg:province":"South Holland",
    "wof:name":"Adviesbureau L. Van Der Hoeven",
    "wof:placetype":"venue"
},
  "geometry": {"coordinates":[4.265547,51.819054],"type":"Point"}
}