{
  "type": "Feature",
  "properties": {
    "iso:country":"NL",
    "sg:address":"Kempstr 159",
    "sg:city":"S Gravenhage",
    "sg:orig_category":"Kappers",
    "sg:phone":"+31 70 360 0219",
    "sg:postcode":"2572 GD",
    "sg:province":"Zuid-Holland",
    "wof:name":"Elvan Abaci Kapsalon",
    "wof:placetype":"venue"
},
  "geometry": {"coordinates":[4.2942099571,52.0642204285],"type":"Point"}
}