{
  "type": "Feature",
  "properties": {
    "addr:full":"Grebbeweg 4 Rhenen Utrecht 3911 AW",
    "addr:housenumber":"4",
    "addr:postcode":"3911 aw",
    "addr:street":"Grebbeweg",
    "iso:country":"NL",
    "sg:address":"Grebbeweg 4",
    "sg:city":"Rhenen",
    "sg:classifiers":[
        {
            "category":"Sports & Exercise",
            "subcategory":"Skate Park",
            "type":"Entertainment"
        }
    ],
    "sg:phone":"+31 317 612 983",
    "sg:postcode":"3911 AW",
    "sg:province":"Utrecht",
    "sg:tags":[
        "zandwinning",
        "grind-"
    ],
    "wof:name":"Coop Zand- En Grindbedrijf Ba",
    "wof:placetype":"venue"
},
  "geometry": {"coordinates":[5.579956,51.956978],"type":"Point"}
}