{
  "type": "Feature",
  "properties": {
    "addr:full":"Geuzenweg 267 Hilversum Noord-Holland 1221 BS",
    "addr:housenumber":"267",
    "addr:postcode":"1221 bs",
    "addr:street":"Geuzenweg",
    "iso:country":"NL",
    "sg:address":"Geuzenweg 267",
    "sg:city":"Hilversum",
    "sg:orig_category":"Loodgieterswerk, Verwarming And Sanitaire Installaties",
    "sg:phone":"+31 35 683 1181",
    "sg:postcode":"1221 BS",
    "sg:province":"Noord-Holland",
    "wof:name":"P. Mafait",
    "wof:placetype":"venue"
},
  "geometry": {"coordinates":[5.18799,52.233604],"type":"Point"}
}