{
  "type": "Feature",
  "properties": {
    "iso:country":"NL",
    "sg:address":"Herenbosstraat 13",
    "sg:city":"Schagen",
    "sg:orig_category":"Kinderopvang Behalve Thuis",
    "sg:phone":"+31 224 217 163",
    "sg:postcode":"1741 CG",
    "sg:province":"Noord-Holland",
    "wof:name":"Kindercentrum De Speeltrommel",
    "wof:placetype":"venue"
},
  "geometry": {"coordinates":[4.798789,52.785912],"type":"Point"}
}