{
  "type": "Feature",
  "properties": {
    "iso:country":"NL",
    "sg:address":"Westduinwg 48",
    "sg:city":"S Gravenhage",
    "sg:orig_category":"Kappers",
    "sg:phone":"+31 70 354 2026",
    "sg:postcode":"2583 EH",
    "sg:province":"Zuid-Holland",
    "wof:name":"Martha",
    "wof:placetype":"venue"
},
  "geometry": {"coordinates":[4.25526,52.09124],"type":"Point"}
}