{
  "type": "Feature",
  "properties": {
    "addr:full":"Vemderdwarsweg 11 Epe Gelderland 8161 NL",
    "addr:housenumber":"11",
    "addr:postcode":"8161",
    "addr:street":"Vemderdwarsweg;Gelderland",
    "iso:country":"NL",
    "sg:address":"Vemderdwarsweg 11",
    "sg:city":"Epe",
    "sg:orig_category":"Goederenvervoer Over De Weg",
    "sg:phone":"+31 578 694 071",
    "sg:postcode":"8161 NL",
    "sg:province":"Gelderland",
    "wof:name":"H. Van Den Belt",
    "wof:placetype":"venue"
},
  "geometry": {"coordinates":[6.028111,52.365005],"type":"Point"}
}