{
  "type": "Feature",
  "properties": {
    "addr:full":"Zwaanshals 355 Rotterdam South Holland 3035 KL",
    "addr:housenumber":"355",
    "addr:postcode":"3035 kl",
    "addr:street":"Zwaanshals",
    "iso:country":"NL",
    "sg:address":"Zwaanshals 355",
    "sg:city":"Rotterdam",
    "sg:classifiers":[
        {
            "category":"Farming",
            "subcategory":"Fish & Marine Products",
            "type":"Manufacturing & Wholesale Goods"
        }
    ],
    "sg:phone":"+31 10 466 3020",
    "sg:postcode":"3035 KL",
    "sg:province":"South Holland",
    "sg:tags":[
        "vi"
    ],
    "sg:website":"http://www.de-oester.nl",
    "wof:name":"Oester, De",
    "wof:placetype":"venue"
},
  "geometry": {"coordinates":[4.484797,51.931526],"type":"Point"}
}