{
  "type": "Feature",
  "properties": {
    "addr:full":"Kempenaar 20 Wyk By Duurstede Utrecht 3961 KM",
    "addr:street":"Kempenaar 20 Wyk;Duurstede;3961 Km",
    "iso:country":"NL",
    "sg:address":"Kempenaar 20",
    "sg:city":"Wyk By Duurstede",
    "sg:orig_category":"Horeca-Inrichtingen En -Uitrustingen",
    "sg:phone":"+31 343 577 066",
    "sg:postcode":"3961 KM",
    "sg:province":"Utrecht",
    "wof:name":"Eurosia",
    "wof:placetype":"venue"
},
  "geometry": {"coordinates":[5.330718,51.970905],"type":"Point"}
}