{
  "type": "Feature",
  "properties": {
    "addr:full":"Opweg 86 Schoonhoven South Holland 2871 NG",
    "addr:housenumber":"86",
    "addr:postcode":"2871 ng",
    "addr:street":"Opweg",
    "iso:country":"NL",
    "sg:address":"Opweg 86",
    "sg:city":"Schoonhoven",
    "sg:orig_category":"Boekhouders",
    "sg:phone":"+31 182 381 010",
    "sg:postcode":"2871 NG",
    "sg:province":"South Holland",
    "wof:name":"Administratiekantoor Boom",
    "wof:placetype":"venue"
},
  "geometry": {"coordinates":[4.845359,51.956051],"type":"Point"}
}