{
  "type": "Feature",
  "properties": {
    "addr:full":"Martenshofstede 3 Vaassen Gelderland 8171 JS",
    "addr:housenumber":"3",
    "addr:postcode":"8171 js",
    "addr:street":"Martenshofstede;Gelderland",
    "iso:country":"NL",
    "sg:address":"Martenshofstede 3",
    "sg:city":"Vaassen",
    "sg:classifiers":[
        {
            "category":"Shopping",
            "subcategory":"Adult",
            "type":"Retail Goods"
        }
    ],
    "sg:phone":"+31 578 577 440",
    "sg:postcode":"8171 JS",
    "sg:province":"Gelderland",
    "sg:tags":[
        "lingerie",
        "en",
        "tricotage"
    ],
    "wof:name":"Body Basics",
    "wof:placetype":"venue"
},
  "geometry": {"coordinates":[5.981703,52.286732],"type":"Point"}
}