{
  "type": "Feature",
  "properties": {
    "addr:full":"Voorstraat 39 Franeker Provincie Friesland 8801 LA",
    "addr:housenumber":"39;8801",
    "addr:street":"Voorstraat;Provincie Friesland",
    "iso:country":"NL",
    "sg:address":"Voorstraat 39",
    "sg:city":"Franeker",
    "sg:orig_category":"Meubelen",
    "sg:phone":"+31 517 392 277",
    "sg:postcode":"8801 LA",
    "sg:province":"Provincie Friesland",
    "sg:website":"http://www.bangahuis.nl",
    "wof:name":"Banga Huis",
    "wof:placetype":"venue"
},
  "geometry": {"coordinates":[5.541742,53.186489],"type":"Point"}
}