{
  "type": "Feature",
  "properties": {
    "addr:full":"Postbus 1138 Hilversum Noord-Holland 1200 BC",
    "addr:housenumber":"1138",
    "addr:postcode":"hilversum;1200 bc",
    "addr:street":"Postbus",
    "iso:country":"NL",
    "sg:address":"Postbus 1138",
    "sg:city":"Hilversum",
    "sg:orig_category":"Omroep",
    "sg:phone":"+31 35 623 8183",
    "sg:postcode":"1200 BC",
    "sg:province":"Noord-Holland",
    "sg:website":"http://www.omroephilversum.nl",
    "wof:name":"Omroep Hilversum",
    "wof:placetype":"venue"
},
  "geometry": {"coordinates":[5.171,52.223991],"type":"Point"}
}