{
  "type": "Feature",
  "properties": {
    "addr:full":"Alsteedsewg 71 Haaksbergen NL.08 7481 RT",
    "addr:housenumber":"71;nl.08",
    "addr:postcode":"7481 rt",
    "addr:street":"Alsteedsewg",
    "iso:country":"NL",
    "sg:address":"Alsteedsewg 71",
    "sg:city":"Haaksbergen",
    "sg:classifiers":[
        {
            "category":"Animal Shelter",
            "type":"Public Place"
        }
    ],
    "sg:phone":"+31 53 569 6298",
    "sg:postcode":"7481 RT",
    "sg:province":"NL.08",
    "sg:tags":[
        "kennel"
    ],
    "wof:name":"Oalde Broam, De",
    "wof:placetype":"venue"
},
  "geometry": {"coordinates":[6.852125,52.137207],"type":"Point"}
}