{
  "type": "Feature",
  "properties": {
    "addr:full":"Hamelweide 13 Nieuwegein Utrecht 3437 CD",
    "addr:housenumber":"13",
    "addr:postcode":"3437 cd",
    "addr:street":"Hamelweide",
    "iso:country":"NL",
    "sg:address":"Hamelweide 13",
    "sg:city":"Nieuwegein",
    "sg:orig_category":"Voetbalverenigingen",
    "sg:phone":"+31 30 603 3579",
    "sg:postcode":"3437 CD",
    "sg:province":"Utrecht",
    "wof:name":"Kds",
    "wof:placetype":"venue"
},
  "geometry": {"coordinates":[5.072566,52.042091],"type":"Point"}
}