{
  "type": "Feature",
  "properties": {
    "addr:full":"Oude Trekwg 84 Harlingen Friesland 8861 KT",
    "addr:housenumber":"84",
    "addr:postcode":"8861 kt",
    "addr:street":"Oude Trekwg",
    "iso:country":"NL",
    "sg:address":"Oude Trekwg 84",
    "sg:city":"Harlingen",
    "sg:orig_category":"Motoren - Fabrieken",
    "sg:phone":"+31 517 418 133",
    "sg:postcode":"8861 KT",
    "sg:province":"Friesland",
    "sg:website":"http://www.sjp-engineering.nl",
    "wof:name":"Sjp Engineering Bv",
    "wof:placetype":"venue"
},
  "geometry": {"coordinates":[5.445927,53.172188],"type":"Point"}
}