{
  "type": "Feature",
  "properties": {
    "addr:full":"Kerkstr 94A Almere Flevoland 1354 AC",
    "addr:housenumber":"94a",
    "addr:postcode":"1354 ac",
    "addr:street":"Kerkstr;Flevoland",
    "iso:country":"NL",
    "sg:address":"Kerkstr 94A",
    "sg:city":"Almere",
    "sg:orig_category":"Adviesbureaus Elektrotechniek",
    "sg:phone":"+31 36 531 5050",
    "sg:postcode":"1354 AC",
    "sg:province":"Flevoland",
    "wof:name":"Btec Engineering & Consultancy",
    "wof:placetype":"venue"
},
  "geometry": {"coordinates":[5.220692,52.335266],"type":"Point"}
}