{
  "type": "Feature",
  "properties": {
    "addr:full":"Gerrit Bolkade 3 Zaandam North Holland 1507 BR",
    "addr:housenumber":"3",
    "addr:postcode":"1507 br",
    "addr:street":"Gerrit Bolkade",
    "iso:country":"NL",
    "sg:address":"Gerrit Bolkade 3",
    "sg:city":"Zaandam",
    "sg:orig_category":"Metaalbekleding And -Behandeling",
    "sg:phone":"+31 75 617 4355",
    "sg:postcode":"1507 BR",
    "sg:province":"North Holland",
    "wof:name":"Kalfsvel Metaalcoating Bv",
    "wof:placetype":"venue"
},
  "geometry": {"coordinates":[4.818091,52.432247],"type":"Point"}
}