{
  "type": "Feature",
  "properties": {
    "iso:country":"NL",
    "sg:address":"Brinkstr 8",
    "sg:city":"Denekamp",
    "sg:orig_category":"Kappers",
    "sg:phone":"+31 541 352 706",
    "sg:postcode":"7591 DP",
    "sg:province":"Overijssel",
    "wof:name":"Nicole, Chez",
    "wof:placetype":"venue"
},
  "geometry": {"coordinates":[7.004442,52.376068],"type":"Point"}
}