{
  "type": "Feature",
  "properties": {
    "iso:country":"NL",
    "sg:address":"Coulisse 11",
    "sg:city":"Zeewolde",
    "sg:orig_category":"Modeontwerpen",
    "sg:phone":"+31 36 522 4193",
    "sg:postcode":"3893 BW",
    "sg:province":"Flevoland",
    "wof:name":"Vision Vtm",
    "wof:placetype":"venue"
},
  "geometry": {"coordinates":[5.523949,52.334103],"type":"Point"}
}