{
  "type": "Feature",
  "properties": {
    "addr:full":"Hessenwg 20/A De Bilt Utrecht 3731 JK",
    "addr:housenumber":"20 / a",
    "addr:postcode":"3731 jk",
    "addr:street":"Hessenwg",
    "iso:country":"NL",
    "sg:address":"Hessenwg 20/A",
    "sg:city":"De Bilt",
    "sg:orig_category":"Bloemen En Planten",
    "sg:phone":"+31 30 220 0439",
    "sg:postcode":"3731 JK",
    "sg:province":"Utrecht",
    "wof:name":"Henk Wansink",
    "wof:placetype":"venue"
},
  "geometry": {"coordinates":[5.179232,52.10672],"type":"Point"}
}