{
  "type": "Feature",
  "properties": {
    "iso:country":"NL",
    "sg:address":"P C Hooftstr 53",
    "sg:city":"Amsterdam",
    "sg:orig_category":"Kunsthandel",
    "sg:phone":"+31 20 675 1701",
    "sg:postcode":"1071 BN",
    "sg:province":"North Holland",
    "wof:name":"Schlichte Bergen",
    "wof:placetype":"venue"
},
  "geometry": {"coordinates":[4.88177,52.360394],"type":"Point"}
}