{
  "type": "Feature",
  "properties": {
    "addr:full":"Valkstr 2 Didam Gelderland 6942 KR",
    "addr:housenumber":"2",
    "addr:postcode":"6942 kr",
    "addr:street":"Valkstr;Gelderland",
    "iso:country":"NL",
    "sg:address":"Valkstr 2",
    "sg:city":"Didam",
    "sg:orig_category":"Homeopathie",
    "sg:phone":"+31 316 224 055",
    "sg:postcode":"6942 KR",
    "sg:province":"Gelderland",
    "wof:name":"Ans Peters",
    "wof:placetype":"venue"
},
  "geometry": {"coordinates":[6.125156,51.931946],"type":"Point"}
}