{
  "type": "Feature",
  "properties": {
    "addr:full":"Hoogstr 5 Bergen Op Zoom Noord-Brabant 4611 MR",
    "addr:housenumber":"5",
    "addr:postcode":"4611 mr",
    "addr:street":"Hoogstr",
    "iso:country":"NL",
    "sg:address":"Hoogstr 5",
    "sg:city":"Bergen Op Zoom",
    "sg:orig_category":"Schietsportartikelen",
    "sg:phone":"+31 164 250 590",
    "sg:postcode":"4611 MR",
    "sg:province":"Noord-Brabant",
    "wof:name":"Peperbus Jachthuis, De",
    "wof:placetype":"venue"
},
  "geometry": {"coordinates":[4.2881,51.493954],"type":"Point"}
}