{
  "type": "Feature",
  "properties": {
    "iso:country":"NL",
    "sg:address":"Welbergswegje 8",
    "sg:city":"Steenbergen Nb",
    "sg:orig_category":"Motoren - Onderdelen",
    "sg:phone":"+31 167 540 330",
    "sg:postcode":"4651 TH",
    "sg:province":"Noord-Brabant",
    "sg:website":"http://www.dph.de",
    "wof:name":"Dichtungspartner Hamburg Gmbh",
    "wof:placetype":"venue"
},
  "geometry": {"coordinates":[4.343128,51.582779],"type":"Point"}
}