{
  "type": "Feature",
  "properties": {
    "addr:full":"Zuid Willemsvaart 2 'S Hertogenbosch North Brabant 5211 NW",
    "addr:housenumber":"2 ' s",
    "addr:postcode":"5211 nw",
    "addr:street":"Zuid Willemsvaart;Hertogenbosch",
    "iso:country":"NL",
    "sg:address":"Zuid Willemsvaart 2",
    "sg:city":"'S Hertogenbosch",
    "sg:orig_category":"Bibliotheken And Openbare Archieven",
    "sg:phone":"+31 73 681 8500",
    "sg:postcode":"5211 NW",
    "sg:province":"North Brabant",
    "wof:name":"Rijksarchief In Noord Brabant",
    "wof:placetype":"venue"
},
  "geometry": {"coordinates":[5.305202,51.693405],"type":"Point"}
}