{
  "type": "Feature",
  "properties": {
    "addr:full":"S Blomln 31 Maarsbergen Utrecht 3953 CB",
    "addr:housenumber":"31",
    "addr:postcode":"3953 cb",
    "iso:country":"NL",
    "sg:address":"S Blomln 31",
    "sg:city":"Maarsbergen",
    "sg:orig_category":"Horecabenodigdheden",
    "sg:phone":"+31 343 575 916",
    "sg:postcode":"3953 CB",
    "sg:province":"Utrecht",
    "wof:name":"Gastroma Bv",
    "wof:placetype":"venue"
},
  "geometry": {"coordinates":[5.40323,52.057564],"type":"Point"}
}