{
  "type": "Feature",
  "properties": {
    "addr:full":"J Wattwg 2 Vlaardingen Zuid-Holland 3133 KK",
    "addr:housenumber":"2",
    "addr:postcode":"3133 kk",
    "iso:country":"NL",
    "sg:address":"J Wattwg 2",
    "sg:city":"Vlaardingen",
    "sg:orig_category":"Verf En Lak - Fabrieken En Groothandel",
    "sg:phone":"+31 10 445 4000",
    "sg:postcode":"3133 KK",
    "sg:province":"Zuid-Holland",
    "sg:website":"http://www.hempel.com",
    "wof:name":"Hempel Bv",
    "wof:placetype":"venue"
},
  "geometry": {"coordinates":[4.317764,51.902508],"type":"Point"}
}