{
  "type": "Feature",
  "properties": {
    "addr:full":"Dr. Huber Noodtstraat 40 Doetinchem Gelderland 7001 DX",
    "addr:housenumber":"40",
    "addr:postcode":"7001 dx",
    "addr:street":"Noodtstraat;Gelderland",
    "iso:country":"NL",
    "sg:address":"Dr. Huber Noodtstraat 40",
    "sg:city":"Doetinchem",
    "sg:orig_category":"Koeriersdiensten",
    "sg:phone":"+31 314 334 444",
    "sg:postcode":"7001 DX",
    "sg:province":"Gelderland",
    "wof:name":"Setax / Doetax Bv",
    "wof:placetype":"venue"
},
  "geometry": {"coordinates":[6.293597,51.966496],"type":"Point"}
}