{
  "type": "Feature",
  "properties": {
    "addr:full":"Keizerstr 23/A Gorinchem South Holland 4201 XM",
    "addr:housenumber":"23 / a",
    "addr:postcode":"4201 xm",
    "addr:street":"Keizerstr",
    "iso:country":"NL",
    "sg:address":"Keizerstr 23/A",
    "sg:city":"Gorinchem",
    "sg:orig_category":"Onderhoudswerken",
    "sg:phone":"+31 183 635 974",
    "sg:postcode":"4201 XM",
    "sg:province":"South Holland",
    "wof:name":"Wormgoor",
    "wof:placetype":"venue"
},
  "geometry": {"coordinates":[4.978398,51.830524],"type":"Point"}
}