{
  "type": "Feature",
  "properties": {
    "addr:full":"Rykswg 90 Gronsveld Limburg 6247 AK",
    "addr:housenumber":"90",
    "addr:postcode":"6247 ak",
    "addr:street":"Rykswg",
    "iso:country":"NL",
    "sg:address":"Rykswg 90",
    "sg:city":"Gronsveld",
    "sg:orig_category":"Kinderopvang",
    "sg:phone":"+31 43 408 3657",
    "sg:postcode":"6247 AK",
    "sg:province":"Limburg",
    "wof:name":"Kr\u00f6ppelk\u00f6tsje, 'T",
    "wof:placetype":"venue"
},
  "geometry": {"coordinates":[5.731033,50.810665],"type":"Point"}
}