{
  "type": "Feature",
  "properties": {
    "addr:full":"Merenwg 7 Bleiswyk South Holland 2665 KM",
    "addr:housenumber":"7",
    "addr:postcode":"2665 km",
    "addr:street":"Merenwg",
    "iso:country":"NL",
    "sg:address":"Merenwg 7",
    "sg:city":"Bleiswyk",
    "sg:orig_category":"Bloemen En Planten",
    "sg:phone":"+31 10 521 4872",
    "sg:postcode":"2665 KM",
    "sg:province":"South Holland",
    "wof:name":"Rekrea Bv",
    "wof:placetype":"venue"
},
  "geometry": {"coordinates":[4.531687,52.001575],"type":"Point"}
}