{
  "type": "Feature",
  "properties": {
    "addr:full":"De Loper 9 Vlaardingen South Holland 3136 CM",
    "addr:housenumber":"9",
    "addr:postcode":"3136 cm",
    "addr:street":"De Loper",
    "iso:country":"NL",
    "sg:address":"De Loper 9",
    "sg:city":"Vlaardingen",
    "sg:orig_category":"Wasserettes And Stomerijen",
    "sg:phone":"+31 10 474 4725",
    "sg:postcode":"3136 CM",
    "sg:province":"South Holland",
    "wof:name":"Wsh",
    "wof:placetype":"venue"
},
  "geometry": {"coordinates":[4.3468728065,51.9299430847],"type":"Point"}
}