{
  "type": "Feature",
  "properties": {
    "addr:full":"Hogewg 271 Amersfoort Utrecht 3816 BT",
    "addr:housenumber":"271",
    "addr:postcode":"3816 bt",
    "iso:country":"NL",
    "sg:address":"Hogewg 271",
    "sg:city":"Amersfoort",
    "sg:orig_category":"Bestratingen",
    "sg:phone":"+31 33 472 6600",
    "sg:postcode":"3816 BT",
    "sg:province":"Utrecht",
    "wof:name":"Smink, Straatmakersbedrijf Bv",
    "wof:placetype":"venue"
},
  "geometry": {"coordinates":[5.386085,52.152325],"type":"Point"}
}