{
  "type": "Feature",
  "properties": {
    "addr:full":"Pr Bernhardln 12 Beverwyk Noord-Holland 1942 AA",
    "addr:housenumber":"12",
    "addr:postcode":"1942 aa",
    "addr:street":"Beverwyk Noord-Holland",
    "iso:country":"NL",
    "sg:address":"Pr Bernhardln 12",
    "sg:city":"Beverwyk",
    "sg:orig_category":"Verzekeringen - Verzekeringskantoren",
    "sg:phone":"+31 251 276 276",
    "sg:postcode":"1942 AA",
    "sg:province":"Noord-Holland",
    "sg:website":"http://www.fibeko.nl",
    "wof:name":"Lanschot Fibeko Groep Bv, Van",
    "wof:placetype":"venue"
},
  "geometry": {"coordinates":[4.64718,52.48101],"type":"Point"}
}