{
  "type": "Feature",
  "properties": {
    "addr:full":"Herenwg 11 Houten Utrecht 3991 DR",
    "addr:housenumber":"11",
    "addr:postcode":"3991 dr",
    "addr:street":"Herenwg",
    "iso:country":"NL",
    "sg:address":"Herenwg 11",
    "sg:city":"Houten",
    "sg:orig_category":"Hypotheken",
    "sg:phone":"+31 30 638 0979",
    "sg:postcode":"3991 DR",
    "sg:province":"Utrecht",
    "sg:website":"http://www.pjvw.nl",
    "wof:name":"Wijngaarden, P J Van",
    "wof:placetype":"venue"
},
  "geometry": {"coordinates":[5.160662,52.028412],"type":"Point"}
}