{
  "type": "Feature",
  "properties": {
    "addr:full":"Pieter Ghijsenlaan 5 Zaandam Noord-Holland 1506 PW",
    "addr:housenumber":"5",
    "addr:postcode":"1506 pw",
    "addr:street":"Pieter Ghijsenlaan",
    "iso:country":"NL",
    "sg:address":"Pieter Ghijsenlaan 5",
    "sg:city":"Zaandam",
    "sg:orig_category":"Autokeuringen",
    "sg:phone":"+31 75 650 4526",
    "sg:postcode":"1506 PW",
    "sg:province":"Noord-Holland",
    "wof:name":"Winkel Personenwagens Bv",
    "wof:placetype":"venue"
},
  "geometry": {"coordinates":[4.824115,52.429901],"type":"Point"}
}