{
  "type": "Feature",
  "properties": {
    "addr:full":"Turfbaan 1 Steenbergen Nb North Brabant 4651 TZ",
    "addr:housenumber":"1;nb",
    "addr:postcode":"4651 tz",
    "addr:street":"Turfbaan",
    "iso:country":"NL",
    "sg:address":"Turfbaan 1",
    "sg:city":"Steenbergen Nb",
    "sg:orig_category":"Land- En Tuinbouw - Mechanisatie",
    "sg:phone":"+31 167 563 666",
    "sg:postcode":"4651 TZ",
    "sg:province":"North Brabant",
    "wof:name":"Bruyn, A De",
    "wof:placetype":"venue"
},
  "geometry": {"coordinates":[4.333964,51.554192],"type":"Point"}
}