{
  "type": "Feature",
  "properties": {
    "addr:full":"Teugestraat 19 Amsterdam Zuidoost Noord-Holland 1107 SB",
    "addr:housenumber":"19",
    "addr:postcode":"zuidoost;1107 sb",
    "addr:street":"Teugestraat",
    "iso:country":"NL",
    "sg:address":"Teugestraat 19",
    "sg:city":"Amsterdam Zuidoost",
    "sg:orig_category":"Verzekeringen",
    "sg:phone":"+31 20 696 5504",
    "sg:postcode":"1107 SB",
    "sg:province":"Noord-Holland",
    "wof:name":"Inter Golf Assurantien",
    "wof:placetype":"venue"
},
  "geometry": {"coordinates":[4.970694,52.294498],"type":"Point"}
}