{
  "type": "Feature",
  "properties": {
    "iso:country":"NL",
    "sg:address":"Vrijthof 17",
    "sg:city":"Maastricht",
    "sg:orig_category":"Banken And Kredietinstellingen",
    "sg:phone":"+31 43 350 3400",
    "sg:postcode":"6211 LD",
    "sg:province":"Limburg",
    "wof:name":"Banque Paribas Nederland Nv",
    "wof:placetype":"venue"
},
  "geometry": {"coordinates":[5.688965,50.848335],"type":"Point"}
}