{
  "type": "Feature",
  "properties": {
    "addr:full":"Oude Deventerwg 2 Olst Overijssel 8121 RL",
    "addr:housenumber":"2",
    "addr:postcode":"8121 rl",
    "addr:street":"Oude Deventerwg",
    "iso:country":"NL",
    "sg:address":"Oude Deventerwg 2",
    "sg:city":"Olst",
    "sg:classifiers":[
        {
            "category":"Retail",
            "subcategory":"Auto Repair",
            "type":"Services"
        }
    ],
    "sg:phone":"+31 570 531 232",
    "sg:postcode":"8121 RL",
    "sg:province":"Overijssel",
    "sg:tags":[
        "garage"
    ],
    "wof:name":"Voskes, R",
    "wof:placetype":"venue"
},
  "geometry": {"coordinates":[6.182477,52.347424],"type":"Point"}
}