{
  "type": "Feature",
  "properties": {
    "addr:full":"C De Gaullestr 17 Rotterdam Zuid-Holland 3066 VG",
    "addr:housenumber":"17",
    "addr:postcode":"3066 vg",
    "addr:street":"C",
    "iso:country":"NL",
    "sg:address":"C De Gaullestr 17",
    "sg:city":"Rotterdam",
    "sg:orig_category":"Medische Keuringen",
    "sg:phone":"+31 6 51211081",
    "sg:postcode":"3066 VG",
    "sg:province":"Zuid-Holland",
    "wof:name":"Roan",
    "wof:placetype":"venue"
},
  "geometry": {"coordinates":[4.555446,51.931606],"type":"Point"}
}