{
  "type": "Feature",
  "properties": {
    "iso:country":"NL",
    "sg:address":"C Gelderblomln 64",
    "sg:city":"S Gravenhage",
    "sg:orig_category":"Adviesbureaus Bedrijfsorganisatie",
    "sg:phone":"+31 70 368 8836",
    "sg:postcode":"2545 ES",
    "sg:province":"Zuid-Holland",
    "wof:name":"Raateland",
    "wof:placetype":"venue"
},
  "geometry": {"coordinates":[4.27049,52.05093],"type":"Point"}
}