{
  "type": "Feature",
  "properties": {
    "addr:full":"Stoofweg 10 Ouddorp Zh Zuid-Holland 3253 MA",
    "addr:housenumber":"10",
    "addr:postcode":"3253 ma",
    "addr:street":"Stoofweg",
    "iso:country":"NL",
    "sg:address":"Stoofweg 10",
    "sg:city":"Ouddorp Zh",
    "sg:classifiers":[
        {
            "category":"Bakery",
            "type":"Food & Drink"
        }
    ],
    "sg:phone":"+31 187 688 555",
    "sg:postcode":"3253 MA",
    "sg:province":"Zuid-Holland",
    "sg:tags":[
        "brood",
        "banket"
    ],
    "wof:name":"Nipius Banket Bv",
    "wof:placetype":"venue"
},
  "geometry": {"coordinates":[3.930704,51.800117],"type":"Point"}
}