{
  "type": "Feature",
  "properties": {
    "addr:full":"Coenhavenweg 7 Amsterdam North Holland 1013 BK",
    "addr:housenumber":"7",
    "addr:postcode":"1013 bk",
    "addr:street":"Coenhavenweg",
    "iso:country":"NL",
    "sg:address":"Coenhavenweg 7",
    "sg:city":"Amsterdam",
    "sg:classifiers":[
        {
            "category":"Retail",
            "subcategory":"Storage",
            "type":"Services"
        }
    ],
    "sg:phone":"+31 20 555 1444",
    "sg:postcode":"1013 BK",
    "sg:province":"North Holland",
    "sg:tags":[
        "opslag",
        "bewaring"
    ],
    "wof:name":"Nedveem Bv",
    "wof:placetype":"venue"
},
  "geometry": {"coordinates":[4.8628249168,52.4028396606],"type":"Point"}
}