{
  "type": "Feature",
  "properties": {
    "iso:country":"NL",
    "sg:address":"De Kiel 71",
    "sg:city":"Hoogeveen",
    "sg:orig_category":"Wegen And Sportterreinen",
    "sg:phone":"+31 528 265 753",
    "sg:postcode":"7908 LC",
    "sg:province":"Drenthe",
    "wof:name":"Tenko",
    "wof:placetype":"venue"
},
  "geometry": {"coordinates":[6.4442877769,52.7134094238],"type":"Point"}
}