{
  "type": "Feature",
  "properties": {
    "addr:full":"Overlanderstraat 503 Purmerend North Holland 1445 CP",
    "addr:housenumber":"503",
    "addr:postcode":"1445 cp",
    "addr:street":"Overlanderstraat",
    "iso:country":"NL",
    "sg:address":"Overlanderstraat 503",
    "sg:city":"Purmerend",
    "sg:orig_category":"Kappers",
    "sg:phone":"+31 299 640 701",
    "sg:postcode":"1445 CP",
    "sg:province":"North Holland",
    "wof:name":"Jacqueline Middelink Bv",
    "wof:placetype":"venue"
},
  "geometry": {"coordinates":[4.9838438034,52.5054397583],"type":"Point"}
}