{
  "type": "Feature",
  "properties": {
    "addr:full":"Spoorstr 15 Tiel Gelderland 4001 CN",
    "addr:housenumber":"15",
    "addr:postcode":"4001 cn",
    "addr:street":"Spoorstr;Gelderland",
    "iso:country":"NL",
    "sg:address":"Spoorstr 15",
    "sg:city":"Tiel",
    "sg:orig_category":"Woningbouw- Verenigingen En -Stichtingen",
    "sg:phone":"+31 344 614 106",
    "sg:postcode":"4001 CN",
    "sg:province":"Gelderland",
    "wof:name":"Scw Tiel",
    "wof:placetype":"venue"
},
  "geometry": {"coordinates":[5.4190878868,51.8870315552],"type":"Point"}
}