{
  "type": "Feature",
  "properties": {
    "iso:country":"NL",
    "sg:address":"Kamp 50",
    "sg:city":"Amersfoort",
    "sg:orig_category":"Meubelen",
    "sg:phone":"+31 33 475 3118",
    "sg:postcode":"3811 AS",
    "sg:province":"Utrecht",
    "wof:name":"Stijlkamer, De",
    "wof:placetype":"venue"
},
  "geometry": {"coordinates":[5.395361,52.158051],"type":"Point"}
}