{
  "type": "Feature",
  "properties": {
    "addr:full":"Buerwg 51 Bergen Nh Noord-Holland 1861 CH",
    "addr:housenumber":"51",
    "addr:postcode":"1861",
    "addr:street":"Buerwg",
    "iso:country":"NL",
    "sg:address":"Buerwg 51",
    "sg:city":"Bergen Nh",
    "sg:orig_category":"Organisatiebureaus",
    "sg:phone":"+31 72 589 9062",
    "sg:postcode":"1861 CH",
    "sg:province":"Noord-Holland",
    "wof:name":"Moorga",
    "wof:placetype":"venue"
},
  "geometry": {"coordinates":[4.6756567955,52.6664237976],"type":"Point"}
}