{
  "type": "Feature",
  "properties": {
    "addr:full":"Schenkeldk 71 S Gravendeel Zuid-Holland 3295 ED",
    "addr:housenumber":"71",
    "addr:postcode":"3295 ed",
    "addr:street":"Schenkeldk;S Gravendeel",
    "iso:country":"NL",
    "sg:address":"Schenkeldk 71",
    "sg:city":"S Gravendeel",
    "sg:orig_category":"Adviesbureaus Kunststoffen",
    "sg:phone":"+31 78 673 5288",
    "sg:postcode":"3295 ED",
    "sg:province":"Zuid-Holland",
    "wof:name":"Bureau Landbouwcommunicatie",
    "wof:placetype":"venue"
},
  "geometry": {"coordinates":[4.599654,51.743206],"type":"Point"}
}