{
  "type": "Feature",
  "properties": {
    "iso:country":"NL",
    "sg:address":"Holkerweg 24",
    "sg:city":"Nijkerk Gld",
    "sg:orig_category":"Verzekeringen",
    "sg:phone":"+31 33 245 1488",
    "sg:postcode":"3861 PB",
    "sg:province":"Gelderland",
    "wof:name":"Assurantiekantoor Van Der Stelt",
    "wof:placetype":"venue"
},
  "geometry": {"coordinates":[5.472441,52.222633],"type":"Point"}
}