{
  "type": "Feature",
  "properties": {
    "iso:country":"NL",
    "sg:address":"Vlaardingenstr 43",
    "sg:city":"Almere",
    "sg:orig_category":"Oldtimers",
    "sg:phone":"+31 36 534 6729",
    "sg:postcode":"1324 LB",
    "sg:province":"NL.",
    "wof:name":"Cpr Klassieke Porsches",
    "wof:placetype":"venue"
},
  "geometry": {"coordinates":[5.201298,52.361809],"type":"Point"}
}