{
  "type": "Feature",
  "properties": {
    "addr:full":"Enschedesestr 27 Haaksbergen Overijssel 7481 CK",
    "addr:housenumber":"27",
    "addr:postcode":"7481 ck",
    "addr:street":"Enschedesestr",
    "iso:country":"NL",
    "sg:address":"Enschedesestr 27",
    "sg:city":"Haaksbergen",
    "sg:orig_category":"Vertalers",
    "sg:phone":"+31 53 572 4316",
    "sg:postcode":"7481 CK",
    "sg:province":"Overijssel",
    "wof:name":"Freeve-De Vrijer, Drs L",
    "wof:placetype":"venue"
},
  "geometry": {"coordinates":[6.746309,52.156139],"type":"Point"}
}