{
  "type": "Feature",
  "properties": {
    "iso:country":"NL",
    "sg:address":"Churchillsngl 414",
    "sg:city":"Vlaardingen",
    "sg:orig_category":"Beurzen",
    "sg:phone":"+31 10 474 4497",
    "sg:postcode":"3137 XB",
    "sg:province":"South Holland",
    "wof:name":"Intraservice Bv",
    "wof:placetype":"venue"
},
  "geometry": {"coordinates":[4.340359,51.910442],"type":"Point"}
}