{
  "type": "Feature",
  "properties": {
    "addr:full":"Het Hoge 52 Vorden Gelderland 7251 XZ",
    "addr:housenumber":"52",
    "addr:postcode":"7251 xz",
    "addr:street":"Het Hoge;Gelderland",
    "iso:country":"NL",
    "sg:address":"Het Hoge 52",
    "sg:city":"Vorden",
    "sg:orig_category":"Adviesbureaus",
    "sg:phone":"+31 575 553 707",
    "sg:postcode":"7251 XZ",
    "sg:province":"Gelderland",
    "wof:name":"Afima Bv",
    "wof:placetype":"venue"
},
  "geometry": {"coordinates":[6.30913,52.10321],"type":"Point"}
}