{
  "type": "Feature",
  "properties": {
    "addr:full":"Burgemeester De Zeeuwstr 11 Numansdorp Zuid-Holland 3281 AD",
    "addr:housenumber":"11",
    "addr:postcode":"3281 ad",
    "addr:street":"Burgemeester De Zeeuwstr",
    "iso:country":"NL",
    "sg:address":"Burgemeester De Zeeuwstr 11",
    "sg:city":"Numansdorp",
    "sg:classifiers":[
        {
            "category":"Shopping",
            "subcategory":"Gifts & Souvenirs",
            "type":"Retail Goods"
        }
    ],
    "sg:phone":"+31 186 654 910",
    "sg:postcode":"3281 AD",
    "sg:province":"Zuid-Holland",
    "sg:tags":[
        "geschenken"
    ],
    "wof:name":"La Boule",
    "wof:placetype":"venue"
},
  "geometry": {"coordinates":[4.437938,51.729618],"type":"Point"}
}