{
  "type": "Feature",
  "properties": {
    "addr:full":"Achillesstr 41 Amsterdam Noord-Holland 1076 PV",
    "addr:housenumber":"41",
    "addr:postcode":"1076 pv",
    "addr:street":"Achillesstr",
    "iso:country":"NL",
    "sg:address":"Achillesstr 41",
    "sg:city":"Amsterdam",
    "sg:orig_category":"Fietsen En Bromfietsen Stalling",
    "sg:phone":"+31 20 662 1197",
    "sg:postcode":"1076 PV",
    "sg:province":"Noord-Holland",
    "wof:name":"Jansen",
    "wof:placetype":"venue"
},
  "geometry": {"coordinates":[4.864366,52.346542],"type":"Point"}
}