{
  "type": "Feature",
  "properties": {
    "addr:full":"Haelerweg 56 Horn Limburg 6085 EC",
    "addr:housenumber":"56",
    "addr:postcode":"6085 ec",
    "addr:street":"Haelerweg",
    "iso:country":"NL",
    "sg:address":"Haelerweg 56",
    "sg:city":"Horn",
    "sg:orig_category":"Kappers",
    "sg:phone":"+31 475 581 942",
    "sg:postcode":"6085 EC",
    "sg:province":"Limburg",
    "wof:name":"Kapsalon N. Teeuwen-Peeters",
    "wof:placetype":"venue"
},
  "geometry": {"coordinates":[-77.5950469971,42.3507461548],"type":"Point"}
}