{
  "type": "Feature",
  "properties": {
    "addr:full":"Venestr 103A Leidschendam South Holland 2266 AZ",
    "addr:housenumber":"103a",
    "addr:postcode":"2266 az",
    "iso:country":"NL",
    "sg:address":"Venestr 103A",
    "sg:city":"Leidschendam",
    "sg:orig_category":"Loopbaanbegeleiding",
    "sg:phone":"+31 70 444 2100",
    "sg:postcode":"2266 AZ",
    "sg:province":"South Holland",
    "wof:name":"Break Consultancy",
    "wof:placetype":"venue"
},
  "geometry": {"coordinates":[4.40239,52.078461],"type":"Point"}
}