{
  "type": "Feature",
  "properties": {
    "addr:full":"Berkenhof 27 Nootdorp Zuid-Holland 2631 GJ",
    "addr:housenumber":"27",
    "addr:postcode":"2631 gj",
    "addr:street":"Berkenhof",
    "iso:country":"NL",
    "sg:address":"Berkenhof 27",
    "sg:city":"Nootdorp",
    "sg:orig_category":"Adviesbureaus Bedrijfsorganisatie",
    "sg:phone":"+31 15 310 6806",
    "sg:postcode":"2631 GJ",
    "sg:province":"Zuid-Holland",
    "wof:name":"Vries, De",
    "wof:placetype":"venue"
},
  "geometry": {"coordinates":[4.395487,52.047733],"type":"Point"}
}