{
  "type": "Feature",
  "properties": {
    "addr:full":"Streekweg 83 Hoogkarspel North Holland 1616 AB",
    "addr:housenumber":"83",
    "addr:postcode":"1616 ab",
    "addr:street":"Streekweg",
    "iso:country":"NL",
    "sg:address":"Streekweg 83",
    "sg:city":"Hoogkarspel",
    "sg:classifiers":[
        {
            "category":"Food & Beverages",
            "subcategory":"Fruits & Vegetables",
            "type":"Retail Goods"
        }
    ],
    "sg:phone":"+31 228 564 055",
    "sg:postcode":"1616 AB",
    "sg:province":"North Holland",
    "sg:tags":[
        "groenten"
    ],
    "wof:name":"M. Koopman-Van Baar",
    "wof:placetype":"venue"
},
  "geometry": {"coordinates":[5.165571,52.692703],"type":"Point"}
}