{
  "type": "Feature",
  "properties": {
    "addr:full":"Prinses Margrietlaan 86 Uithoorn Noord-Holland 1421 XJ",
    "addr:housenumber":"86",
    "addr:postcode":"1421 xj",
    "addr:street":"Prinses Margrietlaan",
    "iso:country":"NL",
    "sg:address":"Prinses Margrietlaan 86",
    "sg:city":"Uithoorn",
    "sg:orig_category":"Paramedische Behandelingen",
    "sg:phone":"+31 297 530 566",
    "sg:postcode":"1421 XJ",
    "sg:province":"Noord-Holland",
    "wof:name":"Logopediepraktijk M. Van De Werff",
    "wof:placetype":"venue"
},
  "geometry": {"coordinates":[4.828194,52.23579],"type":"Point"}
}