{
  "type": "Feature",
  "properties": {
    "addr:full":"Kleibultwg 101 Oldenzaal Overijssel 7575 BW",
    "addr:housenumber":"101",
    "addr:postcode":"7575 bw",
    "iso:country":"NL",
    "sg:address":"Kleibultwg 101",
    "sg:city":"Oldenzaal",
    "sg:orig_category":"Kunststoffen- Verwerkende Industrie",
    "sg:phone":"+31 541 530 509",
    "sg:postcode":"7575 BW",
    "sg:province":"Overijssel",
    "wof:name":"Menla, Kunststoftechniek",
    "wof:placetype":"venue"
},
  "geometry": {"coordinates":[6.916373,52.297714],"type":"Point"}
}