{
  "type": "Feature",
  "properties": {
    "iso:country":"NL",
    "sg:address":"Dorpsstraat 12",
    "sg:city":"Casteren",
    "sg:orig_category":"Boekhouders",
    "sg:phone":"+31 497 684 107",
    "sg:postcode":"5529 AW",
    "sg:province":"North Brabant",
    "wof:name":"A. De Vries Boekhoudbureau",
    "wof:placetype":"venue"
},
  "geometry": {"coordinates":[5.240026,51.39518],"type":"Point"}
}