{
  "type": "Feature",
  "properties": {
    "addr:full":"Herenwg 79 Warmond South Holland 2361 EJ",
    "addr:housenumber":"79",
    "addr:postcode":"2361 ej",
    "addr:street":"Herenwg",
    "iso:country":"NL",
    "sg:address":"Herenwg 79",
    "sg:city":"Warmond",
    "sg:orig_category":"Adviesbureaus Bedrijfsorganisatie",
    "sg:phone":"+31 71 301 2081",
    "sg:postcode":"2361 EJ",
    "sg:province":"South Holland",
    "wof:name":"Cam\u00e9e Consult",
    "wof:placetype":"venue"
},
  "geometry": {"coordinates":[4.503595,52.197487],"type":"Point"}
}