{
  "type": "Feature",
  "properties": {
    "addr:full":"Beilervaart 108A Beilen Drenthe 9411 VH",
    "addr:housenumber":"108a",
    "addr:postcode":"9411 vh",
    "addr:street":"Beilervaart",
    "iso:country":"NL",
    "sg:address":"Beilervaart 108A",
    "sg:city":"Beilen",
    "sg:orig_category":"Adviesbureaus",
    "sg:phone":"+31 592 459 961",
    "sg:postcode":"9411 VH",
    "sg:province":"Drenthe",
    "wof:name":"Grijs, De",
    "wof:placetype":"venue"
},
  "geometry": {"coordinates":[6.41945,52.886154],"type":"Point"}
}