{
  "type": "Feature",
  "properties": {
    "addr:full":"Hekstr 50 Beilen Drenthe 9411 NH",
    "addr:housenumber":"50",
    "addr:postcode":"9411 nh",
    "addr:street":"Hekstr",
    "iso:country":"NL",
    "sg:address":"Hekstr 50",
    "sg:city":"Beilen",
    "sg:orig_category":"Homeopathie",
    "sg:phone":"+31 593 541 959",
    "sg:postcode":"9411 NH",
    "sg:province":"Drenthe",
    "wof:name":"Klein, J",
    "wof:placetype":"venue"
},
  "geometry": {"coordinates":[6.517222,52.860462],"type":"Point"}
}