{
  "type": "Feature",
  "properties": {
    "addr:full":"Beurswg 11 Huizen North Holland 1271 BT",
    "addr:housenumber":"11",
    "addr:postcode":"1271 bt",
    "addr:street":"Beurswg",
    "iso:country":"NL",
    "sg:address":"Beurswg 11",
    "sg:city":"Huizen",
    "sg:orig_category":"Meubelstoffering",
    "sg:phone":"+31 35 525 3513",
    "sg:postcode":"1271 BT",
    "sg:province":"North Holland",
    "wof:name":"Arreslee, De",
    "wof:placetype":"venue"
},
  "geometry": {"coordinates":[5.236618,52.294468],"type":"Point"}
}