{
  "type": "Feature",
  "properties": {
    "addr:full":"Isarwg Amsterdam Noord-Holland 1043 AK",
    "addr:postcode":"1043 ak",
    "iso:country":"NL",
    "sg:address":"Isarwg",
    "sg:city":"Amsterdam",
    "sg:orig_category":"Hondenscholen",
    "sg:phone":"+31 20 638 9096",
    "sg:postcode":"1043 AK",
    "sg:province":"Noord-Holland",
    "wof:name":"Aemstelle, Den",
    "wof:placetype":"venue"
},
  "geometry": {"coordinates":[4.829135,52.392872],"type":"Point"}
}