{
  "type": "Feature",
  "properties": {
    "addr:full":"Beemdgras 20 Gouda Zuid-Holland 2804 NT",
    "addr:housenumber":"20",
    "addr:postcode":"2804 nt",
    "addr:street":"Beemdgras",
    "iso:country":"NL",
    "sg:address":"Beemdgras 20",
    "sg:city":"Gouda",
    "sg:orig_category":"Acupunctuur",
    "sg:phone":"+31 182 535 278",
    "sg:postcode":"2804 NT",
    "sg:province":"Zuid-Holland",
    "wof:name":"Cirk, C",
    "wof:placetype":"venue"
},
  "geometry": {"coordinates":[4.716792,52.031982],"type":"Point"}
}