{
  "type": "Feature",
  "properties": {
    "addr:full":"Buitenhaven 27A S Hertogenbosch Noord-Brabant 5211 TP",
    "addr:housenumber":"27a",
    "addr:postcode":"5211 tp",
    "addr:street":"Buitenhaven;S Hertogenbosch",
    "iso:country":"NL",
    "sg:address":"Buitenhaven 27A",
    "sg:city":"S Hertogenbosch",
    "sg:orig_category":"Adviesbureaus",
    "sg:phone":"+31 73 692 5151",
    "sg:postcode":"5211 TP",
    "sg:province":"Noord-Brabant",
    "wof:name":"Geodan Bv",
    "wof:placetype":"venue"
},
  "geometry": {"coordinates":[5.299558,51.691704],"type":"Point"}
}