{
  "type": "Feature",
  "properties": {
    "addr:full":"Oosterstraat 48 Groningen Groningen 9711 NW",
    "addr:housenumber":"48",
    "addr:postcode":"9711 nw",
    "addr:street":"Oosterstraat",
    "iso:country":"NL",
    "sg:address":"Oosterstraat 48",
    "sg:city":"Groningen",
    "sg:orig_category":"Meubelzaken, Woning- And Keukeninrichting",
    "sg:phone":"+31 50 313 9013",
    "sg:postcode":"9711 NW",
    "sg:province":"Groningen",
    "wof:name":"R.A. Kamphuis En Zonen Bv",
    "wof:placetype":"venue"
},
  "geometry": {"coordinates":[6.570268,53.21693],"type":"Point"}
}