{
  "type": "Feature",
  "properties": {
    "addr:full":"Pr Bernhardln 30 Bunde Limburg 6241 EM",
    "addr:housenumber":"30",
    "addr:postcode":"6241 em",
    "iso:country":"NL",
    "sg:address":"Pr Bernhardln 30",
    "sg:city":"Bunde",
    "sg:orig_category":"Adviesbureaus",
    "sg:phone":"+31 43 364 1702",
    "sg:postcode":"6241 EM",
    "sg:province":"Limburg",
    "wof:name":"Hartog, P C Den",
    "wof:placetype":"venue"
},
  "geometry": {"coordinates":[5.732364,50.896702],"type":"Point"}
}