{
  "type": "Feature",
  "properties": {
    "addr:full":"Westkadijk 10 Nijkerk Gld Gelderland 3861 MB",
    "addr:housenumber":"10",
    "addr:postcode":"3861 mb",
    "addr:street":"Westkadijk;Gld Gelderland",
    "iso:country":"NL",
    "sg:address":"Westkadijk 10",
    "sg:city":"Nijkerk Gld",
    "sg:orig_category":"Meubelzaken, Woning- And Keukeninrichting",
    "sg:phone":"+31 33 247 1010",
    "sg:postcode":"3861 MB",
    "sg:province":"Gelderland",
    "wof:name":"Inter Select Trading",
    "wof:placetype":"venue"
},
  "geometry": {"coordinates":[5.480132,52.228149],"type":"Point"}
}