{
  "type": "Feature",
  "properties": {
    "addr:full":"Geerweg 18 Ter Aar Zuid-Holland 2461 EA",
    "addr:housenumber":"18",
    "addr:postcode":"aar;2461 ea",
    "addr:street":"Geerweg;Ter",
    "iso:country":"NL",
    "sg:address":"Geerweg 18",
    "sg:city":"Ter Aar",
    "sg:orig_category":"Kampeerterreinen",
    "sg:phone":"+31 172 538 277",
    "sg:postcode":"2461 EA",
    "sg:province":"Zuid-Holland",
    "wof:name":"Mimosa Camping",
    "wof:placetype":"venue"
},
  "geometry": {"coordinates":[4.72747612,52.197593689],"type":"Point"}
}