{
  "type": "Feature",
  "properties": {
    "addr:full":"Valleiwg 16A Rhenen Utrecht 3911 DD",
    "addr:housenumber":"16a",
    "addr:postcode":"3911 dd",
    "addr:street":"Valleiwg",
    "iso:country":"NL",
    "sg:address":"Valleiwg 16A",
    "sg:city":"Rhenen",
    "sg:orig_category":"Bloemen En Planten - Decoratie",
    "sg:phone":"+31 317 451 818",
    "sg:postcode":"3911 DD",
    "sg:province":"Utrecht",
    "wof:name":"Bloemenkamer, De",
    "wof:placetype":"venue"
},
  "geometry": {"coordinates":[5.574009,51.964352],"type":"Point"}
}