{
  "type": "Feature",
  "properties": {
    "addr:full":"Groene Kruisstraat 4 Spijkenisse South Holland 3201 CA",
    "addr:housenumber":"4",
    "addr:postcode":"3201 ca",
    "addr:street":"Groene Kruisstraat",
    "iso:country":"NL",
    "sg:address":"Groene Kruisstraat 4",
    "sg:city":"Spijkenisse",
    "sg:orig_category":"Verlichting And Huishoudartikelen",
    "sg:phone":"+31 181 610 211",
    "sg:postcode":"3201 CA",
    "sg:province":"South Holland",
    "wof:name":"Bv Meubel D & C",
    "wof:placetype":"venue"
},
  "geometry": {"coordinates":[4.324391,51.848305],"type":"Point"}
}