{
  "type": "Feature",
  "properties": {
    "addr:full":"Ruiterwg 24 Darp Drenthe 7973 JT",
    "addr:housenumber":"24",
    "addr:postcode":"7973 jt",
    "addr:street":"Ruiterwg",
    "iso:country":"NL",
    "sg:address":"Ruiterwg 24",
    "sg:city":"Darp",
    "sg:orig_category":"Schilders",
    "sg:phone":"+31 521 342 628",
    "sg:postcode":"7973 JT",
    "sg:province":"Drenthe",
    "sg:website":"http://www.vandebelt.nl",
    "wof:name":"Belt, Van De",
    "wof:placetype":"venue"
},
  "geometry": {"coordinates":[6.20469,52.776367],"type":"Point"}
}