{
  "type": "Feature",
  "properties": {
    "addr:full":"Juliana Van Stolbergstr 25 Dordrecht South Holland 3314 PG",
    "addr:housenumber":"25",
    "addr:postcode":"3314 pg",
    "addr:street":"Juliana Van Stolbergstr",
    "iso:country":"NL",
    "sg:address":"Juliana Van Stolbergstr 25",
    "sg:city":"Dordrecht",
    "sg:orig_category":"Loodgieterswerk, Verwarming And Sanitaire Installaties",
    "sg:phone":"+31 78 614 0270",
    "sg:postcode":"3314 PG",
    "sg:province":"South Holland",
    "wof:name":"F. Van Der Rest & Zn",
    "wof:placetype":"venue"
},
  "geometry": {"coordinates":[4.668101,51.800709],"type":"Point"}
}