{
  "type": "Feature",
  "properties": {
    "iso:country":"NL",
    "sg:address":"Sterkenburg 2",
    "sg:city":"Eindhoven",
    "sg:orig_category":"Bejaarden - Verzorgingstehuizen",
    "sg:phone":"+31 40 252 0311",
    "sg:postcode":"5653 ND",
    "sg:province":"North Brabant",
    "wof:name":"Genderhof",
    "wof:placetype":"venue"
},
  "geometry": {"coordinates":[5.43487,51.420349],"type":"Point"}
}