{
  "type": "Feature",
  "properties": {
    "addr:full":"Tweede Walstraat 37 Nijmegen Gelderland 6511 LP",
    "addr:housenumber":"37",
    "addr:postcode":"6511 lp",
    "addr:street":"Tweede Walstraat;Gelderland",
    "iso:country":"NL",
    "sg:address":"Tweede Walstraat 37",
    "sg:city":"Nijmegen",
    "sg:orig_category":"Drukkerijen And Copyshops",
    "sg:phone":"+31 24 323 1638",
    "sg:postcode":"6511 LP",
    "sg:province":"Gelderland",
    "wof:name":"Drukkerij Uitgeverij Nijmegen Bv",
    "wof:placetype":"venue"
},
  "geometry": {"coordinates":[5.865094,51.843857],"type":"Point"}
}