{
  "type": "Feature",
  "properties": {
    "addr:full":"Oosterland 6 Paterswolde Drenthe 9765 BM",
    "addr:housenumber":"6",
    "addr:postcode":"9765 bm",
    "addr:street":"Oosterland",
    "iso:country":"NL",
    "sg:address":"Oosterland 6",
    "sg:city":"Paterswolde",
    "sg:orig_category":"Acupunctuur",
    "sg:phone":"+31 50 309 4323",
    "sg:postcode":"9765 BM",
    "sg:province":"Drenthe",
    "wof:name":"Ridder, B C A De",
    "wof:placetype":"venue"
},
  "geometry": {"coordinates":[6.573057,53.150703],"type":"Point"}
}