{
  "type": "Feature",
  "properties": {
    "iso:country":"NL",
    "sg:address":"Hg Zand 10",
    "sg:city":"Breda",
    "sg:orig_category":"Adviesbureaus Bedrijfsorganisatie",
    "sg:phone":"+31 76 542 4897",
    "sg:postcode":"4823 HS",
    "sg:province":"Noord-Brabant",
    "sg:website":"http://www.pm2advies.nl",
    "wof:name":"Personeel Management 2",
    "wof:placetype":"venue"
},
  "geometry": {"coordinates":[4.741265,51.628555],"type":"Point"}
}