{
  "type": "Feature",
  "properties": {
    "iso:country":"NL",
    "sg:address":"Wilhelminastraat 54",
    "sg:city":"Emmen",
    "sg:orig_category":"Boekhandels",
    "sg:phone":"+31 591 640 619",
    "sg:postcode":"7811 JE",
    "sg:province":"Drenthe",
    "wof:name":"Evangelisch Boekwinkel Sola Scriptura",
    "wof:placetype":"venue"
},
  "geometry": {"coordinates":[6.896722,52.782806],"type":"Point"}
}