{
  "type": "Feature",
  "properties": {
    "addr:full":"Merwedestr 86 Dordrecht South Holland 3313 CS",
    "addr:housenumber":"86",
    "addr:postcode":"3313 cs",
    "addr:street":"Merwedestr",
    "iso:country":"NL",
    "sg:address":"Merwedestr 86",
    "sg:city":"Dordrecht",
    "sg:orig_category":"Dieselmotoren",
    "sg:phone":"+31 78 639 5777",
    "sg:postcode":"3313 CS",
    "sg:province":"South Holland",
    "sg:website":"http://www.mdb-roodenburg.nl",
    "wof:name":"Mdb-Roodenburg",
    "wof:placetype":"venue"
},
  "geometry": {"coordinates":[4.703388,51.817276],"type":"Point"}
}