{
  "type": "Feature",
  "properties": {
    "iso:country":"NL",
    "sg:address":"Dominee Talmastraat 7",
    "sg:city":"Wolvega",
    "sg:orig_category":"Meubelreparatie And -Restauratie",
    "sg:phone":"+31 561 615 201",
    "sg:postcode":"8471 LM",
    "sg:province":"Provincie Friesland",
    "wof:name":"G.W. De Lange",
    "wof:placetype":"venue"
},
  "geometry": {"coordinates":[6.004445,52.872681],"type":"Point"}
}