{
  "type": "Feature",
  "properties": {
    "addr:full":"Avelingen Oost 5 Gorinchem South Holland 4202 MN",
    "addr:housenumber":"5",
    "addr:postcode":"4202 mn",
    "addr:street":"Avelingen Oost",
    "iso:country":"NL",
    "sg:address":"Avelingen Oost 5",
    "sg:city":"Gorinchem",
    "sg:orig_category":"Metalen And Ertsen Gh",
    "sg:phone":"+31 183 633 877",
    "sg:postcode":"4202 MN",
    "sg:province":"South Holland",
    "wof:name":"Impex Staal Bv",
    "wof:placetype":"venue"
},
  "geometry": {"coordinates":[4.948765,51.832214],"type":"Point"}
}