{
  "type": "Feature",
  "properties": {
    "iso:country":"NL",
    "sg:address":"Boezemsingel 131",
    "sg:city":"Rotterdam",
    "sg:orig_category":"Fotostudio'S And Fotografen",
    "sg:phone":"+31 10 214 1675",
    "sg:postcode":"3031 CA",
    "sg:province":"Zuid-Holland",
    "wof:name":"M.S. Leutscher",
    "wof:placetype":"venue"
},
  "geometry": {"coordinates":[4.49627,51.928741],"type":"Point"}
}