{
  "type": "Feature",
  "properties": {
    "addr:full":"Torenstr 31 Sambeek Noord-Brabant 5836 AJ",
    "addr:housenumber":"31",
    "addr:postcode":"5836 aj",
    "addr:street":"Torenstr",
    "iso:country":"NL",
    "sg:address":"Torenstr 31",
    "sg:city":"Sambeek",
    "sg:orig_category":"Honden- En Kattentrimsalons",
    "sg:phone":"+31 485 575 621",
    "sg:postcode":"5836 AJ",
    "sg:province":"Noord-Brabant",
    "wof:name":"Monique Trimsalon",
    "wof:placetype":"venue"
},
  "geometry": {"coordinates":[5.962081,51.638813],"type":"Point"}
}