{
  "type": "Feature",
  "properties": {
    "addr:full":"Rooye Hoefsedk 27 Gemert Noord-Brabant 5421 XP",
    "addr:housenumber":"27",
    "addr:postcode":"5421 xp",
    "iso:country":"NL",
    "sg:address":"Rooye Hoefsedk 27",
    "sg:city":"Gemert",
    "sg:orig_category":"Melktransporten",
    "sg:phone":"+31 492 323 460",
    "sg:postcode":"5421 XP",
    "sg:province":"Noord-Brabant",
    "wof:name":"Nuenen, J Van",
    "wof:placetype":"venue"
},
  "geometry": {"coordinates":[5.709449,51.556377],"type":"Point"}
}