{
  "type": "Feature",
  "properties": {
    "addr:full":"Hespelaar 30 Den Hout Nb Noord-Brabant 4911 AE",
    "addr:housenumber":"30",
    "addr:postcode":"4911 ae",
    "addr:street":"Hespelaar",
    "iso:country":"NL",
    "sg:address":"Hespelaar 30",
    "sg:city":"Den Hout Nb",
    "sg:orig_category":"Fruit And Groenten Gh",
    "sg:phone":"+31 162 431 613",
    "sg:postcode":"4911 AE",
    "sg:province":"Noord-Brabant",
    "wof:name":"P.J.A. Kuijpers",
    "wof:placetype":"venue"
},
  "geometry": {"coordinates":[4.803913,51.665348],"type":"Point"}
}