{
  "type": "Feature",
  "properties": {
    "addr:full":"Brouwersgracht 226 A Amsterdam Noord-Holland 1013 HE",
    "addr:housenumber":"226 a",
    "addr:postcode":"1013 he",
    "addr:street":"Brouwersgracht",
    "iso:country":"NL",
    "sg:address":"Brouwersgracht 226 A",
    "sg:city":"Amsterdam",
    "sg:orig_category":"Vertaal- And Tolkenbureaus",
    "sg:phone":"+31 20 622 3027",
    "sg:postcode":"1013 HE",
    "sg:province":"Noord-Holland",
    "wof:name":"Stv Translations Bv",
    "wof:placetype":"venue"
},
  "geometry": {"coordinates":[4.886348,52.382103],"type":"Point"}
}