{
  "type": "Feature",
  "properties": {
    "addr:full":"Splitting 51 Emmen Drenthe 7826 CP",
    "addr:housenumber":"51",
    "addr:postcode":"7826 cp",
    "addr:street":"Splitting",
    "iso:country":"NL",
    "sg:address":"Splitting 51",
    "sg:city":"Emmen",
    "sg:orig_category":"Meubelzaken, Woning- And Keukeninrichting",
    "sg:phone":"+31 591 623 062",
    "sg:postcode":"7826 CP",
    "sg:province":"Drenthe",
    "wof:name":"Berens",
    "wof:placetype":"venue"
},
  "geometry": {"coordinates":[6.960073,52.772926],"type":"Point"}
}