{
  "type": "Feature",
  "properties": {
    "addr:full":"Scheldestraat 16A Oss Noord-Brabant 5347 JD",
    "addr:housenumber":"16a",
    "addr:postcode":"5347 jd",
    "addr:street":"Scheldestraat",
    "iso:country":"NL",
    "sg:address":"Scheldestraat 16A",
    "sg:city":"Oss",
    "sg:orig_category":"Autokeuringen",
    "sg:phone":"+31 412 650 582",
    "sg:postcode":"5347 JD",
    "sg:province":"Noord-Brabant",
    "wof:name":"Marcellis Autoschade",
    "wof:placetype":"venue"
},
  "geometry": {"coordinates":[-77.235214,38.312599],"type":"Point"}
}