{
  "type": "Feature",
  "properties": {
    "iso:country":"NL",
    "sg:address":"Lekdk 385",
    "sg:city":"Nieuw Lekkerland",
    "sg:orig_category":"Hoefsmederijen",
    "sg:phone":"+31 184 685 326",
    "sg:postcode":"2957 VA",
    "sg:province":"Zuid-Holland",
    "wof:name":"Zanten, D Van",
    "wof:placetype":"venue"
},
  "geometry": {"coordinates":[4.665429,51.88728],"type":"Point"}
}