{
  "type": "Feature",
  "properties": {
    "addr:full":"J Tooropln 4 Veendam Groningen 9646 DG",
    "addr:housenumber":"4",
    "addr:postcode":"9646 dg",
    "addr:street":"Veendam",
    "iso:country":"NL",
    "sg:address":"J Tooropln 4",
    "sg:city":"Veendam",
    "sg:orig_category":"Energiebesparing",
    "sg:phone":"+31 598 626 633",
    "sg:postcode":"9646 DG",
    "sg:province":"Groningen",
    "wof:name":"Hmo",
    "wof:placetype":"venue"
},
  "geometry": {"coordinates":[6.866827,53.115189],"type":"Point"}
}