{
  "type": "Feature",
  "properties": {
    "iso:country":"NL",
    "sg:address":"J Tooropln 4",
    "sg:city":"Veendam",
    "sg:orig_category":"Energiebesparing",
    "sg:phone":"+31 598 626 633",
    "sg:postcode":"9646 DG",
    "sg:province":"Groningen",
    "wof:name":"Hmo",
    "wof:placetype":"venue"
},
  "geometry": {"coordinates":[6.866827,53.115189],"type":"Point"}
}