{
  "type": "Feature",
  "properties": {
    "addr:full":"Koelmaln 67 Alkmaar Noord-Holland 1812 PR",
    "addr:housenumber":"67",
    "addr:postcode":"1812 pr",
    "addr:street":"Koelmaln",
    "iso:country":"NL",
    "sg:address":"Koelmaln 67",
    "sg:city":"Alkmaar",
    "sg:orig_category":"Autoschade- Herstelbedrijven",
    "sg:phone":"+31 72 515 5513",
    "sg:postcode":"1812 PR",
    "sg:province":"Noord-Holland",
    "sg:website":"http://www.nefkens.noord-holland.peugeot.nl",
    "wof:name":"Uas Alkmaar",
    "wof:placetype":"venue"
},
  "geometry": {"coordinates":[4.76596,52.609928],"type":"Point"}
}