{
  "type": "Feature",
  "properties": {
    "addr:full":"Graetheideln 37A Urmond Limburg 6129 GC",
    "addr:housenumber":"37a",
    "addr:postcode":"6129 gc",
    "addr:street":"Graetheideln",
    "iso:country":"NL",
    "sg:address":"Graetheideln 37A",
    "sg:city":"Urmond",
    "sg:classifiers":[
        {
            "category":"Food & Beverages",
            "subcategory":"Bakery",
            "type":"Retail Goods"
        }
    ],
    "sg:phone":"+31 46 433 6188",
    "sg:postcode":"6129 GC",
    "sg:province":"Limburg",
    "sg:tags":[
        "brood",
        "en",
        "banket"
    ],
    "wof:name":"Steevens Bv",
    "wof:placetype":"venue"
},
  "geometry": {"coordinates":[5.770395,51.004822],"type":"Point"}
}