{
  "type": "Feature",
  "properties": {
    "addr:full":"Twekkeler Es 5 Enschede NL.08 7547 ST",
    "addr:housenumber":"5",
    "addr:postcode":"7547",
    "addr:street":"Twekkeler Es;St",
    "iso:country":"NL",
    "sg:address":"Twekkeler Es 5",
    "sg:city":"Enschede",
    "sg:orig_category":"Koeriersdiensten",
    "sg:phone":"+31 53 431 7071",
    "sg:postcode":"7547 ST",
    "sg:province":"NL.08",
    "wof:name":"Bannink",
    "wof:placetype":"venue"
},
  "geometry": {"coordinates":[6.840208,52.218594],"type":"Point"}
}