{
  "type": "Feature",
  "properties": {
    "addr:full":"Rembrandtwg 364 Amstelveen Noord-Holland 1181 HC",
    "addr:housenumber":"364",
    "addr:postcode":"1181 hc",
    "iso:country":"NL",
    "sg:address":"Rembrandtwg 364",
    "sg:city":"Amstelveen",
    "sg:orig_category":"Kappers",
    "sg:phone":"+31 20 641 6981",
    "sg:postcode":"1181 HC",
    "sg:province":"Noord-Holland",
    "wof:name":"Geerlings",
    "wof:placetype":"venue"
},
  "geometry": {"coordinates":[4.8635158539,52.3098869324],"type":"Point"}
}