{
  "type": "Feature",
  "properties": {
    "addr:full":"Stelpswyk 32 Drachten Friesland 9202 BH",
    "addr:housenumber":"32",
    "addr:postcode":"9202 bh",
    "addr:street":"Stelpswyk",
    "iso:country":"NL",
    "sg:address":"Stelpswyk 32",
    "sg:city":"Drachten",
    "sg:orig_category":"Autorijscholen",
    "sg:phone":"+31 512 523 425",
    "sg:postcode":"9202 BH",
    "sg:province":"Friesland",
    "wof:name":"Alert",
    "wof:placetype":"venue"
},
  "geometry": {"coordinates":[6.10965,53.114071],"type":"Point"}
}