{
  "type": "Feature",
  "properties": {
    "addr:full":"T Inne 30/A Budel North Brabant 6021 DA",
    "addr:housenumber":"30 / a",
    "addr:postcode":"6021 da",
    "addr:street":"T Inne",
    "iso:country":"NL",
    "sg:address":"T Inne 30/A",
    "sg:city":"Budel",
    "sg:orig_category":"Meubelreparatie And -Restauratie",
    "sg:phone":"+31 495 492 197",
    "sg:postcode":"6021 DA",
    "sg:province":"North Brabant",
    "wof:name":"Mera",
    "wof:placetype":"venue"
},
  "geometry": {"coordinates":[5.577675,51.266201],"type":"Point"}
}