{
  "type": "Feature",
  "properties": {
    "iso:country":"NL",
    "sg:address":"T Inne 30/A",
    "sg:city":"Budel",
    "sg:orig_category":"Meubelreparatie And -Restauratie",
    "sg:phone":"+31 495 492 197",
    "sg:postcode":"6021 DA",
    "sg:province":"North Brabant",
    "wof:name":"Mera",
    "wof:placetype":"venue"
},
  "geometry": {"coordinates":[5.577675,51.266201],"type":"Point"}
}