{
  "type": "Feature",
  "properties": {
    "addr:full":"Gastakker 284 Breda Noord-Brabant 4817 XH",
    "addr:housenumber":"284",
    "addr:postcode":"4817 xh",
    "addr:street":"Gastakker",
    "iso:country":"NL",
    "sg:address":"Gastakker 284",
    "sg:city":"Breda",
    "sg:orig_category":"Accountants - Administratie- Consulenten En -Kantoren",
    "sg:phone":"+31 76 587 5804",
    "sg:postcode":"4817 XH",
    "sg:province":"Noord-Brabant",
    "wof:name":"Hoek, J Van",
    "wof:placetype":"venue"
},
  "geometry": {"coordinates":[4.816349,51.591373],"type":"Point"}
}