{
  "type": "Feature",
  "properties": {
    "addr:full":"Korenstr 111 Purmerend Noord-Holland 1446 DR",
    "addr:housenumber":"111",
    "addr:postcode":"1446 dr",
    "iso:country":"NL",
    "sg:address":"Korenstr 111",
    "sg:city":"Purmerend",
    "sg:orig_category":"Adviesbureaus Bouwkunde",
    "sg:phone":"+31 299 647 595",
    "sg:postcode":"1446 DR",
    "sg:province":"Noord-Holland",
    "wof:name":"Uileman",
    "wof:placetype":"venue"
},
  "geometry": {"coordinates":[4.991583,52.511574],"type":"Point"}
}