{
  "type": "Feature",
  "properties": {
    "addr:full":"M Veningastr 107 Hoogezand Groningen 9601 KE",
    "addr:housenumber":"107",
    "addr:postcode":"9601 ke",
    "iso:country":"NL",
    "sg:address":"M Veningastr 107",
    "sg:city":"Hoogezand",
    "sg:orig_category":"Artsen - Huisartsen",
    "sg:phone":"+31 598 392 086",
    "sg:postcode":"9601 KE",
    "sg:province":"Groningen",
    "wof:name":"Vries, R P M De",
    "wof:placetype":"venue"
},
  "geometry": {"coordinates":[6.752643,53.163708],"type":"Point"}
}