{
  "type": "Feature",
  "properties": {
    "addr:full":"Rubenslaan 1 Lopik Utrecht 3411 VN",
    "addr:housenumber":"1",
    "addr:postcode":"3411 vn",
    "addr:street":"Rubenslaan",
    "iso:country":"NL",
    "sg:address":"Rubenslaan 1",
    "sg:city":"Lopik",
    "sg:orig_category":"Farmaceutische Producten Gh",
    "sg:phone":"+31 348 553 538",
    "sg:postcode":"3411 VN",
    "sg:province":"Utrecht",
    "wof:name":"Travipharma Bv",
    "wof:placetype":"venue"
},
  "geometry": {"coordinates":[4.940795,51.97105],"type":"Point"}
}