{
  "type": "Feature",
  "properties": {
    "iso:country":"NL",
    "sg:address":"Ringfeart 20",
    "sg:city":"Sintjohannesga",
    "sg:orig_category":"Koeriersdiensten",
    "sg:phone":"+31 513 551 855",
    "sg:postcode":"8464 PD",
    "sg:province":"Provincie Friesland",
    "wof:name":"Bakker",
    "wof:placetype":"venue"
},
  "geometry": {"coordinates":[5.855306,52.933613],"type":"Point"}
}