{
  "type": "Feature",
  "properties": {
    "iso:country":"NL",
    "sg:address":"Witte Paal 201",
    "sg:city":"Schagen",
    "sg:orig_category":"Hout Gh",
    "sg:phone":"+31 224 214 555",
    "sg:postcode":"1742 LA",
    "sg:province":"Noord-Holland",
    "wof:name":"Gamma",
    "wof:placetype":"venue"
},
  "geometry": {"coordinates":[4.811818,52.781223],"type":"Point"}
}