{
  "type": "Feature",
  "properties": {
    "addr:full":"Galvanistraat 15 Rotterdam Zuid-Holland 3029 AD",
    "addr:housenumber":"15",
    "addr:postcode":"3029 ad",
    "addr:street":"Galvanistraat",
    "iso:country":"NL",
    "sg:address":"Galvanistraat 15",
    "sg:city":"Rotterdam",
    "sg:orig_category":"Kappers",
    "sg:phone":"+31 10 425 7160",
    "sg:postcode":"3029 AD",
    "sg:province":"Zuid-Holland",
    "wof:name":"T Kapperijtje",
    "wof:placetype":"venue"
},
  "geometry": {"coordinates":[4.4305620193,51.9116744995],"type":"Point"}
}