{
  "type": "Feature",
  "properties": {
    "addr:full":"Scherpenzeelsewg 53 Leersum Utrecht 3956 KD",
    "addr:housenumber":"53",
    "addr:postcode":"3956 kd",
    "addr:street":"Scherpenzeelsewg",
    "iso:country":"NL",
    "sg:address":"Scherpenzeelsewg 53",
    "sg:city":"Leersum",
    "sg:orig_category":"Vakantieverblijven",
    "sg:phone":"+31 343 481 324",
    "sg:postcode":"3956 KD",
    "sg:province":"Utrecht",
    "sg:website":"http://www.ginkelduin.nl",
    "wof:name":"Zilverberk Park Ginkelduin",
    "wof:placetype":"venue"
},
  "geometry": {"coordinates":[5.440266,52.018368],"type":"Point"}
}