{
  "type": "Feature",
  "properties": {
    "addr:full":"Krommewg 24 Soest Utrecht 3762 DP",
    "addr:housenumber":"24",
    "addr:postcode":"3762 dp",
    "addr:street":"Krommewg",
    "iso:country":"NL",
    "sg:address":"Krommewg 24",
    "sg:city":"Soest",
    "sg:orig_category":"Koeriersdiensten",
    "sg:phone":"+31 35 602 9646",
    "sg:postcode":"3762 DP",
    "sg:province":"Utrecht",
    "wof:name":"Kalee",
    "wof:placetype":"venue"
},
  "geometry": {"coordinates":[5.27217,52.183064],"type":"Point"}
}