{
  "type": "Feature",
  "properties": {
    "addr:full":"Noordwg 77 Pynacker Zuid-Holland 2641 ZA",
    "addr:housenumber":"77",
    "addr:postcode":"2641",
    "addr:street":"Noordwg",
    "iso:country":"NL",
    "sg:address":"Noordwg 77",
    "sg:city":"Pynacker",
    "sg:orig_category":"Fitnesscentra",
    "sg:phone":"+31 15 369 9332",
    "sg:postcode":"2641 ZA",
    "sg:province":"Zuid-Holland",
    "wof:name":"Viergang, De",
    "wof:placetype":"venue"
},
  "geometry": {"coordinates":[4.423621,52.024494],"type":"Point"}
}