{
  "type": "Feature",
  "properties": {
    "addr:full":"Parkln 22 C3 S Hertogenbosch Noord-Brabant 5211 JJ",
    "addr:housenumber":"22 c3 s",
    "addr:postcode":"5211 jj",
    "addr:street":"Parkln",
    "iso:country":"NL",
    "sg:address":"Parkln 22 C3",
    "sg:city":"S Hertogenbosch",
    "sg:orig_category":"Plastificeren",
    "sg:phone":"+31 73 622 1206",
    "sg:postcode":"5211 JJ",
    "sg:province":"Noord-Brabant",
    "sg:website":"http://www.plastificeren.nl",
    "wof:name":"Uniek Laminations",
    "wof:placetype":"venue"
},
  "geometry": {"coordinates":[5.29824,51.69075],"type":"Point"}
}