{
  "type": "Feature",
  "properties": {
    "addr:full":"Ridderhof 32 Oss Noord-Brabant 5341 HS",
    "addr:housenumber":"32",
    "addr:postcode":"5341 hs",
    "addr:street":"Ridderhof",
    "iso:country":"NL",
    "sg:address":"Ridderhof 32",
    "sg:city":"Oss",
    "sg:orig_category":"Kansspelen",
    "sg:phone":"+31 412 644 121",
    "sg:postcode":"5341 HS",
    "sg:province":"Noord-Brabant",
    "wof:name":"Heinz Hock",
    "wof:placetype":"venue"
},
  "geometry": {"coordinates":[-77.2352142334,38.3125991821],"type":"Point"}
}