{
  "type": "Feature",
  "properties": {
    "addr:full":"Kerkstr 5 Almere Flevoland 1354 AA",
    "addr:housenumber":"5",
    "addr:postcode":"1354 aa",
    "addr:street":"Kerkstr;Flevoland",
    "iso:country":"NL",
    "sg:address":"Kerkstr 5",
    "sg:city":"Almere",
    "sg:orig_category":"Verzekeringen - Verzekeringskantoren",
    "sg:phone":"+31 36 547 4441",
    "sg:postcode":"1354 AA",
    "sg:province":"Flevoland",
    "sg:website":"http://www.plls.com",
    "wof:name":"Premier Services",
    "wof:placetype":"venue"
},
  "geometry": {"coordinates":[5.21914,52.335876],"type":"Point"}
}