{
  "type": "Feature",
  "properties": {
    "addr:full":"Akkersestr 48 Ophemert Gelderland 4061 BJ",
    "addr:housenumber":"48",
    "addr:postcode":"4061 bj",
    "addr:street":"Akkersestr;Gelderland",
    "iso:country":"NL",
    "sg:address":"Akkersestr 48",
    "sg:city":"Ophemert",
    "sg:orig_category":"Meubelmakerijen",
    "sg:phone":"+31 344 652 088",
    "sg:postcode":"4061 BJ",
    "sg:province":"Gelderland",
    "wof:name":"Hans Vernooij Originals",
    "wof:placetype":"venue"
},
  "geometry": {"coordinates":[5.379981,51.841354],"type":"Point"}
}