{
  "type": "Feature",
  "properties": {
    "iso:country":"NL",
    "sg:address":"Langestraat 40",
    "sg:city":"Hengelo Ov",
    "sg:orig_category":"Werving And Selectie Van Tijdelijk Personeel And Uitzendkantoren",
    "sg:phone":"+31 74 242 2067",
    "sg:postcode":"7551 DZ",
    "sg:province":"Overijssel",
    "wof:name":"Adecco",
    "wof:placetype":"venue"
},
  "geometry": {"coordinates":[6.7897119522,52.2663612366],"type":"Point"}
}