{
  "type": "Feature",
  "properties": {
    "iso:country":"NL",
    "sg:address":"Einsteinstraat 39",
    "sg:city":"Purmerend",
    "sg:orig_category":"Glaszetten",
    "sg:phone":"+31 299 647 593",
    "sg:postcode":"1446 VE",
    "sg:province":"Noord-Holland",
    "wof:name":"Excellent Glas Bouw",
    "wof:placetype":"venue"
},
  "geometry": {"coordinates":[4.998345,52.511963],"type":"Point"}
}