{
  "type": "Feature",
  "properties": {
    "addr:full":"Oudebildtdk 1032 Westhoek Friesland 9075 NK",
    "addr:housenumber":"1032",
    "addr:postcode":"westhoek;9075 nk",
    "iso:country":"NL",
    "sg:address":"Oudebildtdk 1032",
    "sg:city":"Westhoek",
    "sg:orig_category":"Wasmachines En Wasdrogers - Onderhoud En Reparatie",
    "sg:phone":"+31 518 491 725",
    "sg:postcode":"9075 NK",
    "sg:province":"Friesland",
    "wof:name":"Weide, P Van Der",
    "wof:placetype":"venue"
},
  "geometry": {"coordinates":[5.5770368576,53.2788963318],"type":"Point"}
}