{
  "type": "Feature",
  "properties": {
    "addr:full":"R Kuipersstr 7 Montfoort Utrecht 3417 CP",
    "addr:housenumber":"7",
    "addr:postcode":"3417 cp",
    "iso:country":"NL",
    "sg:address":"R Kuipersstr 7",
    "sg:city":"Montfoort",
    "sg:orig_category":"Bodemonderzoek",
    "sg:phone":"+31 348 688 677",
    "sg:postcode":"3417 CP",
    "sg:province":"Utrecht",
    "wof:name":"Bottomline",
    "wof:placetype":"venue"
},
  "geometry": {"coordinates":[4.956336,52.048729],"type":"Point"}
}