{
  "type": "Feature",
  "properties": {
    "addr:full":"Raadhuisstraat 1 Landsmeer Noord-Holland 1121 XC",
    "addr:housenumber":"1",
    "addr:postcode":"1121 xc",
    "addr:street":"Raadhuisstraat",
    "iso:country":"NL",
    "sg:address":"Raadhuisstraat 1",
    "sg:city":"Landsmeer",
    "sg:orig_category":"Overheidsdiensten",
    "sg:phone":"+31 20 487 7111",
    "sg:postcode":"1121 XC",
    "sg:province":"Noord-Holland",
    "wof:name":"Gemeente Landsmeer",
    "wof:placetype":"venue"
},
  "geometry": {"coordinates":[4.9148888588,52.4321022034],"type":"Point"}
}