{
  "type": "Feature",
  "properties": {
    "addr:full":"Grt Wade 19 K Nieuwegein Utrecht 3439 NX",
    "addr:housenumber":"19 k",
    "addr:postcode":"3439 nx",
    "addr:street":"Wade",
    "iso:country":"NL",
    "sg:address":"Grt Wade 19 K",
    "sg:city":"Nieuwegein",
    "sg:orig_category":"Landmeetkundige Bureaus",
    "sg:phone":"+31 30 267 0500",
    "sg:postcode":"3439 NX",
    "sg:province":"Utrecht",
    "sg:website":"http://www.delta-surveys.nl",
    "wof:name":"Delta Surveys",
    "wof:placetype":"venue"
},
  "geometry": {"coordinates":[5.082197,52.027325],"type":"Point"}
}