{
  "type": "Feature",
  "properties": {
    "iso:country":"NL",
    "sg:address":"Hantumerwg 28",
    "sg:city":"Dokkum",
    "sg:orig_category":"Scholen Voor Basisonderwijs",
    "sg:phone":"+31 519 221 440",
    "sg:postcode":"9101 AB",
    "sg:province":"Friesland",
    "wof:name":"Eben-Ha?zer Prot Chr",
    "wof:placetype":"venue"
},
  "geometry": {"coordinates":[5.99846,53.331039],"type":"Point"}
}