{
  "type": "Feature",
  "properties": {
    "iso:country":"NL",
    "sg:address":"Hunsstraat 25",
    "sg:city":"Voerendaal",
    "sg:orig_category":"Goederenvervoer Over De Weg",
    "sg:phone":"+31 45 575 2594",
    "sg:postcode":"6367 JJ",
    "sg:province":"Limburg",
    "wof:name":"J J M Offermans",
    "wof:placetype":"venue"
},
  "geometry": {"coordinates":[5.951442,50.854073],"type":"Point"}
}