{
  "type": "Feature",
  "properties": {
    "addr:full":"Kr Spieringwg 453 Vyfhuizen Noord-Holland 2141 AH",
    "addr:housenumber":"453",
    "addr:postcode":"2141 ah",
    "addr:street":"Vyfhuizen Noord-Holland",
    "iso:country":"NL",
    "sg:address":"Kr Spieringwg 453",
    "sg:city":"Vyfhuizen",
    "sg:orig_category":"Honden- En Kattentrimsalons",
    "sg:phone":"+31 23 558 3391",
    "sg:postcode":"2141 AH",
    "sg:province":"Noord-Holland",
    "wof:name":"Inge Honden En Katten Trimsalon",
    "wof:placetype":"venue"
},
  "geometry": {"coordinates":[4.679655,52.352299],"type":"Point"}
}