{
  "type": "Feature",
  "properties": {
    "addr:full":"Dorpsstraat 29 Zoeterwoude Zuid-Holland 2381 EK",
    "addr:housenumber":"29",
    "addr:postcode":"2381 ek",
    "addr:street":"Dorpsstraat",
    "iso:country":"NL",
    "sg:address":"Dorpsstraat 29",
    "sg:city":"Zoeterwoude",
    "sg:orig_category":"Schoenen",
    "sg:phone":"+31 71 580 1942",
    "sg:postcode":"2381 EK",
    "sg:province":"Zuid-Holland",
    "wof:name":"2-14 Zoeterwoude",
    "wof:placetype":"venue"
},
  "geometry": {"coordinates":[4.496106,52.120518],"type":"Point"}
}