{
  "type": "Feature",
  "properties": {
    "iso:country":"NL",
    "sg:address":"Het Kasteel 691",
    "sg:city":"Apeldoorn",
    "sg:orig_category":"Webdesign Bureaus",
    "sg:phone":"+31 55 360 6395",
    "sg:postcode":"7325 PK",
    "sg:province":"Gelderland",
    "wof:name":"Wanted 4U",
    "wof:placetype":"venue"
},
  "geometry": {"coordinates":[6.0106430054,52.2125701904],"type":"Point"}
}