{
  "type": "Feature",
  "properties": {
    "addr:full":"Handwg 103D Amstelveen Noord-Holland 1185 TV",
    "addr:housenumber":"103d",
    "addr:postcode":"1185 tv",
    "addr:street":"Handwg",
    "iso:country":"NL",
    "sg:address":"Handwg 103D",
    "sg:city":"Amstelveen",
    "sg:orig_category":"Mode Artikelen Dames En Heren - Fabrieken En Groothandel",
    "sg:phone":"+31 20 445 4305",
    "sg:postcode":"1185 TV",
    "sg:province":"Noord-Holland",
    "wof:name":"Mercurius",
    "wof:placetype":"venue"
},
  "geometry": {"coordinates":[4.844229,52.295227],"type":"Point"}
}