{
  "type": "Feature",
  "properties": {
    "addr:full":"Sluisstraat 63 Amsterdam North Holland 1075 TD",
    "addr:housenumber":"63",
    "addr:postcode":"1075 td",
    "addr:street":"Sluisstraat",
    "iso:country":"NL",
    "sg:address":"Sluisstraat 63",
    "sg:city":"Amsterdam",
    "sg:orig_category":"Glaszetten",
    "sg:phone":"+31 20 671 6347",
    "sg:postcode":"1075 TD",
    "sg:province":"North Holland",
    "wof:name":"P. Terpstra",
    "wof:placetype":"venue"
},
  "geometry": {"coordinates":[4.853422,52.351757],"type":"Point"}
}