{
  "type": "Feature",
  "properties": {
    "addr:full":"Hoofdpoortstraat 37 Zierikzee Zeeland 4301 AS",
    "addr:housenumber":"37",
    "addr:postcode":"4301 as",
    "addr:street":"Hoofdpoortstraat",
    "iso:country":"NL",
    "sg:address":"Hoofdpoortstraat 37",
    "sg:city":"Zierikzee",
    "sg:orig_category":"Fitnesscentra",
    "sg:phone":"+31 111 414 020",
    "sg:postcode":"4301 AS",
    "sg:province":"Zeeland",
    "wof:name":"Sportschool Knulst",
    "wof:placetype":"venue"
},
  "geometry": {"coordinates":[3.91688,51.647232],"type":"Point"}
}