{
  "type": "Feature",
  "properties": {
    "iso:country":"NL",
    "sg:address":"Houtweg 60",
    "sg:city":"Ter Aar",
    "sg:orig_category":"Metaalwerken",
    "sg:phone":"+31 6 29008992",
    "sg:postcode":"2461 GR",
    "sg:province":"Zuid-Holland",
    "wof:name":"J.M. Garage-En Bedrijfsdeuren",
    "wof:placetype":"venue"
},
  "geometry": {"coordinates":[4.712922,52.177288],"type":"Point"}
}