{
  "type": "Feature",
  "properties": {
    "addr:full":"Dorpsstr 66 Putten Gelderland 3881 BE",
    "addr:housenumber":"66",
    "addr:postcode":"3881",
    "addr:street":"Dorpsstr;Gelderland",
    "iso:country":"NL",
    "sg:address":"Dorpsstr 66",
    "sg:city":"Putten",
    "sg:orig_category":"Verzekeringen - Verzekeringskantoren",
    "sg:phone":"+31 341 354 937",
    "sg:postcode":"3881 BE",
    "sg:province":"Gelderland",
    "sg:website":"http://www.accesnet.nl/univehgv",
    "wof:name":"Univ\u00e9 Midden-Ned",
    "wof:placetype":"venue"
},
  "geometry": {"coordinates":[5.60265,52.26012],"type":"Point"}
}