{
  "type": "Feature",
  "properties": {
    "addr:full":"Jacob Schorerlaan 131 'S Gravenhage Zuid-Holland 2525 ZR",
    "addr:housenumber":"131 '",
    "addr:postcode":"2525 zr",
    "addr:street":"Jacob Schorerlaan",
    "iso:country":"NL",
    "sg:address":"Jacob Schorerlaan 131",
    "sg:city":"'S Gravenhage",
    "sg:orig_category":"Artsen And Specialisten",
    "sg:phone":"+31 70 389 4211",
    "sg:postcode":"2525 ZR",
    "sg:province":"Zuid-Holland",
    "wof:name":"Drs. G. De Jong",
    "wof:placetype":"venue"
},
  "geometry": {"coordinates":[4.300675,52.060577],"type":"Point"}
}