{
  "type": "Feature",
  "properties": {
    "iso:country":"NL",
    "sg:address":"Wilhelminastr 32",
    "sg:city":"Oosterbeek",
    "sg:orig_category":"Stukadoorsbedrijven",
    "sg:phone":"+31 26 333 4768",
    "sg:postcode":"6862 HD",
    "sg:province":"Gelderland",
    "sg:website":"http://www.stukadoorsbedrijfgelderland.nl",
    "wof:name":"Gelderland Stukadoorsbedrijf",
    "wof:placetype":"venue"
},
  "geometry": {"coordinates":[5.84738,51.984062],"type":"Point"}
}