{
  "type": "Feature",
  "properties": {
    "addr:full":"Keizersdam 47 Oosterhout Nb North Brabant 4908 BD",
    "addr:housenumber":"47;nb",
    "addr:postcode":"4908 bd",
    "addr:street":"Keizersdam",
    "iso:country":"NL",
    "sg:address":"Keizersdam 47",
    "sg:city":"Oosterhout Nb",
    "sg:orig_category":"Honden- En Kattentrimsalons",
    "sg:phone":"+31 162 433 032",
    "sg:postcode":"4908 BD",
    "sg:province":"North Brabant",
    "wof:name":"Claudia",
    "wof:placetype":"venue"
},
  "geometry": {"coordinates":[4.859733,51.66679],"type":"Point"}
}