{
  "type": "Feature",
  "properties": {
    "addr:full":"Burg Juckemastr 33 Franeker Friesland 8801 GL",
    "addr:housenumber":"33",
    "addr:postcode":"8801 gl",
    "addr:street":"Burg",
    "iso:country":"NL",
    "sg:address":"Burg Juckemastr 33",
    "sg:city":"Franeker",
    "sg:orig_category":"Administratie- En Boekhoudkantoren",
    "sg:phone":"+31 517 398 120",
    "sg:postcode":"8801 GL",
    "sg:province":"Friesland",
    "sg:website":"http://www.ibw.nl",
    "wof:name":"L & R, Administratie",
    "wof:placetype":"venue"
},
  "geometry": {"coordinates":[5.538215,53.18536],"type":"Point"}
}