{
  "type": "Feature",
  "properties": {
    "iso:country":"NL",
    "sg:address":"Boxbergerwg 27-29",
    "sg:city":"Deventer",
    "sg:orig_category":"Boeken En Tijdschriften",
    "sg:phone":"+31 570 614 393",
    "sg:postcode":"7412 BB",
    "sg:province":"Overijssel",
    "wof:name":"Rensink",
    "wof:placetype":"venue"
},
  "geometry": {"coordinates":[6.149771,52.259178],"type":"Point"}
}