{
  "type": "Feature",
  "properties": {
    "addr:full":"Brinkstraat 6 Oosterwolde Fr Friesland 8431 LC",
    "addr:housenumber":"6",
    "addr:postcode":"8431 lc",
    "addr:street":"Brinkstraat",
    "iso:country":"NL",
    "sg:address":"Brinkstraat 6",
    "sg:city":"Oosterwolde Fr",
    "sg:orig_category":"Dierenspeciaalzaken",
    "sg:phone":"+31 516 512 769",
    "sg:postcode":"8431 LC",
    "sg:province":"Friesland",
    "wof:name":"Dierenspeciaalzaak Dijkstra",
    "wof:placetype":"venue"
},
  "geometry": {"coordinates":[6.293175,52.992401],"type":"Point"}
}