{
  "type": "Feature",
  "properties": {
    "iso:country":"NL",
    "sg:address":"Kasteel Schaloenstraat 54",
    "sg:city":"Maastricht",
    "sg:classifiers":[
        {
            "category":"Shopping",
            "subcategory":"Gifts & Souvenirs",
            "type":"Retail Goods"
        }
    ],
    "sg:phone":"+31 43 362 2721",
    "sg:postcode":"6222 TP",
    "sg:province":"Limburg",
    "sg:tags":[
        "geschenken"
    ],
    "wof:name":"Ratena",
    "wof:placetype":"venue"
},
  "geometry": {"coordinates":[5.715565,50.863869],"type":"Point"}
}