{
  "type": "Feature",
  "properties": {
    "addr:full":"Leutherweg 31 Venlo Limburg 5915 CA",
    "addr:housenumber":"31",
    "addr:postcode":"5915 ca",
    "addr:street":"Leutherweg",
    "iso:country":"NL",
    "sg:address":"Leutherweg 31",
    "sg:city":"Venlo",
    "sg:orig_category":"Kappers",
    "sg:phone":"+31 77 351 3754",
    "sg:postcode":"5915 CA",
    "sg:province":"Limburg",
    "wof:name":"La Coupe Kappers",
    "wof:placetype":"venue"
},
  "geometry": {"coordinates":[6.181971,51.358829],"type":"Point"}
}