{
  "type": "Feature",
  "properties": {
    "addr:full":"Beatrixln 27 Ruurlo Gelderland 7261 XW",
    "addr:housenumber":"27",
    "addr:postcode":"7261 xw",
    "addr:street":"Beatrixln;Gelderland",
    "iso:country":"NL",
    "sg:address":"Beatrixln 27",
    "sg:city":"Ruurlo",
    "sg:orig_category":"Scholen Voor Basisonderwijs",
    "sg:phone":"+31 573 451 254",
    "sg:postcode":"7261 XW",
    "sg:province":"Gelderland",
    "wof:name":"Rehoboth",
    "wof:placetype":"venue"
},
  "geometry": {"coordinates":[6.448096,52.089642],"type":"Point"}
}