{
  "type": "Feature",
  "properties": {
    "addr:full":"Bretagnehof 7 Eindhoven Noord-Brabant 5627 HX",
    "addr:housenumber":"7",
    "addr:postcode":"5627 hx",
    "addr:street":"Bretagnehof",
    "iso:country":"NL",
    "sg:address":"Bretagnehof 7",
    "sg:city":"Eindhoven",
    "sg:orig_category":"Boekhouders",
    "sg:phone":"+31 40 241 8136",
    "sg:postcode":"5627 HX",
    "sg:province":"Noord-Brabant",
    "wof:name":"Administratiekantoor Frans Verhallen",
    "wof:placetype":"venue"
},
  "geometry": {"coordinates":[5.452731,51.481655],"type":"Point"}
}