{
  "type": "Feature",
  "properties": {
    "addr:full":"M Krusemanpk 2 Heemskerk North Holland 1963 EK",
    "addr:housenumber":"2",
    "addr:postcode":"1963 ek",
    "iso:country":"NL",
    "sg:address":"M Krusemanpk 2",
    "sg:city":"Heemskerk",
    "sg:orig_category":"Koel- En Vriestransporten",
    "sg:phone":"+31 297 348 060",
    "sg:postcode":"1963 EK",
    "sg:province":"North Holland",
    "wof:name":"Freshtrans Bv, J & B",
    "wof:placetype":"venue"
},
  "geometry": {"coordinates":[4.682382,52.521904],"type":"Point"}
}