{
  "type": "Feature",
  "properties": {
    "iso:country":"NL",
    "sg:address":"Nw Burg 14-16",
    "sg:city":"Middelburg",
    "sg:orig_category":"Juweliers",
    "sg:phone":"+31 118 635 275",
    "sg:postcode":"4331 AH",
    "sg:province":"Zeeland",
    "wof:name":"Gouddoppertje, 'T",
    "wof:placetype":"venue"
},
  "geometry": {"coordinates":[3.609615,51.495415],"type":"Point"}
}