{
  "type": "Feature",
  "properties": {
    "iso:country":"NL",
    "sg:address":"Parallelwg 49",
    "sg:city":"Beverwyk",
    "sg:orig_category":"Schoenen",
    "sg:phone":"+31 251 273 030",
    "sg:postcode":"1948 NK",
    "sg:province":"North Holland",
    "wof:name":"Dc Doci",
    "wof:placetype":"venue"
},
  "geometry": {"coordinates":[4.66457,52.479458],"type":"Point"}
}