{
  "type": "Feature",
  "properties": {
    "addr:full":"Entinghewg 8 Dwingeloo Drenthe 7991 CB",
    "addr:housenumber":"8",
    "addr:postcode":"7991 cb",
    "addr:street":"Entinghewg",
    "iso:country":"NL",
    "sg:address":"Entinghewg 8",
    "sg:city":"Dwingeloo",
    "sg:orig_category":"Schilders",
    "sg:phone":"+31 6 25052565",
    "sg:postcode":"7991 CB",
    "sg:province":"Drenthe",
    "wof:name":"Eggink",
    "wof:placetype":"venue"
},
  "geometry": {"coordinates":[6.365428,52.835819],"type":"Point"}
}