{
  "type": "Feature",
  "properties": {
    "addr:full":"G V Amstelstr 72 Hilversum Noord-Holland 1214 BB",
    "addr:housenumber":"72",
    "addr:postcode":"1214 bb",
    "addr:street":"V Amstelstr",
    "iso:country":"NL",
    "sg:address":"G V Amstelstr 72",
    "sg:city":"Hilversum",
    "sg:classifiers":[
        {
            "category":"Retail",
            "subcategory":"Auto Repair",
            "type":"Services"
        }
    ],
    "sg:phone":"+31 35 621 0338",
    "sg:postcode":"1214 BB",
    "sg:province":"Noord-Holland",
    "sg:tags":[
        "garage"
    ],
    "sg:website":"http://www.garagezuid.nl",
    "wof:name":"Garage Zuid",
    "wof:placetype":"venue"
},
  "geometry": {"coordinates":[5.1695,52.228565],"type":"Point"}
}