{
  "type": "Feature",
  "properties": {
    "addr:full":"Lynbaan 7 Oudewater Utrecht 3421 JG",
    "addr:housenumber":"7",
    "addr:postcode":"3421 jg",
    "addr:street":"Lynbaan",
    "iso:country":"NL",
    "sg:address":"Lynbaan 7",
    "sg:city":"Oudewater",
    "sg:orig_category":"Accountants - Administratie- Consulenten En -Kantoren",
    "sg:phone":"+31 348 564 523",
    "sg:postcode":"3421 JG",
    "sg:province":"Utrecht",
    "wof:name":"Nederhof",
    "wof:placetype":"venue"
},
  "geometry": {"coordinates":[4.871934,52.021961],"type":"Point"}
}