{
  "type": "Feature",
  "properties": {
    "addr:full":"Zandwg 220 De Meern Utrecht 3454 HE",
    "addr:housenumber":"220",
    "addr:postcode":"3454 he",
    "iso:country":"NL",
    "sg:address":"Zandwg 220",
    "sg:city":"De Meern",
    "sg:orig_category":"Bloemen En Planten",
    "sg:phone":"+31 30 666 7093",
    "sg:postcode":"3454 HE",
    "sg:province":"Utrecht",
    "wof:name":"Groene Bedrijfsdecoratie",
    "wof:placetype":"venue"
},
  "geometry": {"coordinates":[5.014328,52.087055],"type":"Point"}
}