{
  "type": "Feature",
  "properties": {
    "iso:country":"NL",
    "sg:address":"Hoogstad 701",
    "sg:city":"Vlaardingen",
    "sg:orig_category":"Verzekeringen - Verzekeringskantoren",
    "sg:phone":"+31 10 434 9111",
    "sg:postcode":"3131 KX",
    "sg:province":"Zuid-Holland",
    "wof:name":"Rodenberg En Thijssen",
    "wof:placetype":"venue"
},
  "geometry": {"coordinates":[4.3371,51.916313],"type":"Point"}
}