{
  "type": "Feature",
  "properties": {
    "iso:country":"NL",
    "sg:address":"Westersngl 20",
    "sg:city":"Rotterdam",
    "sg:orig_category":"Biljartzalen",
    "sg:phone":"+31 10 436 3719",
    "sg:postcode":"3014 GP",
    "sg:province":"Zuid-Holland",
    "wof:name":"Thurston",
    "wof:placetype":"venue"
},
  "geometry": {"coordinates":[4.478455,51.922836],"type":"Point"}
}