{
  "type": "Feature",
  "properties": {
    "iso:country":"NL",
    "sg:address":"Oosterpaasloerweg 19",
    "sg:city":"Paasloo",
    "sg:classifiers":[
        {
            "category":"Travel",
            "subcategory":"Hotels & Motels",
            "type":"Entertainment"
        }
    ],
    "sg:phone":"+31 561 452 323",
    "sg:postcode":"8378 JC",
    "sg:province":"Provincie Friesland",
    "wof:name":"Bed & Breakfast Paasloo",
    "wof:placetype":"venue"
},
  "geometry": {"coordinates":[6.021416,52.820267],"type":"Point"}
}