{
  "type": "Feature",
  "properties": {
    "addr:full":"Havenplein 12 Naaldwijk South Holland 2671 GV",
    "addr:housenumber":"12",
    "addr:postcode":"2671 gv",
    "addr:street":"Havenplein",
    "iso:country":"NL",
    "sg:address":"Havenplein 12",
    "sg:city":"Naaldwijk",
    "sg:classifiers":[
        {
            "category":"Retail",
            "subcategory":"Photofinishing",
            "type":"Services"
        }
    ],
    "sg:phone":"+31 174 622 865",
    "sg:postcode":"2671 GV",
    "sg:province":"South Holland",
    "sg:tags":[
        "foto",
        "film"
    ],
    "wof:name":"Rideco Foto",
    "wof:placetype":"venue"
},
  "geometry": {"coordinates":[4.208657,51.993404],"type":"Point"}
}