{
  "type": "Feature",
  "properties": {
    "addr:full":"V Duvenvoordeln 123 Voorburg Zuid-Holland 2274 SX",
    "addr:housenumber":"123",
    "addr:postcode":"2274 sx",
    "addr:street":"V Duvenvoordeln",
    "iso:country":"NL",
    "sg:address":"V Duvenvoordeln 123",
    "sg:city":"Voorburg",
    "sg:orig_category":"Psychologen",
    "sg:phone":"+31 70 385 5923",
    "sg:postcode":"2274 SX",
    "sg:province":"Zuid-Holland",
    "wof:name":"Broer, R",
    "wof:placetype":"venue"
},
  "geometry": {"coordinates":[4.349416,52.073563],"type":"Point"}
}