{
  "type": "Feature",
  "properties": {
    "iso:country":"NL",
    "sg:address":"Azurietdk 108",
    "sg:city":"Roosendaal",
    "sg:orig_category":"Onderhoudswerken",
    "sg:phone":"+31 165 551 068",
    "sg:postcode":"4706 BW",
    "sg:province":"Noord-Brabant",
    "wof:name":"Dareon",
    "wof:placetype":"venue"
},
  "geometry": {"coordinates":[4.487861,51.52433],"type":"Point"}
}