{
  "type": "Feature",
  "properties": {
    "addr:full":"Fugelikkers 2 Workum Friesland 8711 DB",
    "addr:housenumber":"2",
    "addr:postcode":"8711 db",
    "addr:street":"Fugelikkers",
    "iso:country":"NL",
    "sg:address":"Fugelikkers 2",
    "sg:city":"Workum",
    "sg:classifiers":[
        {
            "category":"Education",
            "subcategory":"Preschool",
            "type":"Public Place"
        }
    ],
    "sg:phone":"+31 515 542 224",
    "sg:postcode":"8711 DB",
    "sg:province":"Friesland",
    "sg:tags":[
        "kleuteronderwijs",
        "basis-"
    ],
    "wof:name":"Christelijke Basisschool It Finster",
    "wof:placetype":"venue"
},
  "geometry": {"coordinates":[5.443647,52.974541],"type":"Point"}
}