{
  "type": "Feature",
  "properties": {
    "addr:full":"Lokhorstweg 8 Ermelo Gelderland 3851 SE",
    "addr:housenumber":"8",
    "addr:postcode":"3851",
    "addr:street":"Lokhorstweg;Gelderland;Se",
    "iso:country":"NL",
    "sg:address":"Lokhorstweg 8",
    "sg:city":"Ermelo",
    "sg:orig_category":"Drukkerijen And Copyshops",
    "sg:phone":"+31 341 560 460",
    "sg:postcode":"3851 SE",
    "sg:province":"Gelderland",
    "wof:name":"Vof Inter-Visie",
    "wof:placetype":"venue"
},
  "geometry": {"coordinates":[5.620775,52.319332],"type":"Point"}
}