{
  "type": "Feature",
  "properties": {
    "addr:full":"Commelinstr 12 Amsterdam North Holland 1093 TR",
    "addr:housenumber":"12",
    "addr:postcode":"1093 tr",
    "addr:street":"Commelinstr",
    "iso:country":"NL",
    "sg:address":"Commelinstr 12",
    "sg:city":"Amsterdam",
    "sg:orig_category":"Psychotherapeuten",
    "sg:phone":"+31 20 663 4438",
    "sg:postcode":"1093 TR",
    "sg:province":"North Holland",
    "wof:name":"Kontekst, De",
    "wof:placetype":"venue"
},
  "geometry": {"coordinates":[4.924001,52.363102],"type":"Point"}
}