{
  "type": "Feature",
  "properties": {
    "addr:full":"Wijkersloot 13 Wijk Bij Duurstede Utrecht 3961 MN",
    "addr:housenumber":"13",
    "addr:postcode":"3961 mn",
    "addr:street":"Wijkersloot",
    "iso:country":"NL",
    "sg:address":"Wijkersloot 13",
    "sg:city":"Wijk Bij Duurstede",
    "sg:orig_category":"Fruit And Groenten Gh",
    "sg:phone":"+31 343 562 404",
    "sg:postcode":"3961 MN",
    "sg:province":"Utrecht",
    "wof:name":"Van Rooijens Fruithandelsbedrijf",
    "wof:placetype":"venue"
},
  "geometry": {"coordinates":[5.312096,51.978283],"type":"Point"}
}