{
  "type": "Feature",
  "properties": {
    "iso:country":"NL",
    "sg:address":"Larkstr 8",
    "sg:city":"Rijsenhout",
    "sg:orig_category":"Bloemen En Planten - Groothandel",
    "sg:phone":"+31 297 329 394",
    "sg:postcode":"1435 NC",
    "sg:province":"North Holland",
    "wof:name":"Peters, J N",
    "wof:placetype":"venue"
},
  "geometry": {"coordinates":[4.71467,52.262821],"type":"Point"}
}