{
  "type": "Feature",
  "properties": {
    "addr:full":"Schouw 4 Lemmer Friesland 8531 BJ",
    "addr:housenumber":"4",
    "addr:postcode":"8531 bj",
    "addr:street":"Schouw",
    "iso:country":"NL",
    "sg:address":"Schouw 4",
    "sg:city":"Lemmer",
    "sg:classifiers":[
        {
            "category":"Food & Beverages",
            "subcategory":"Bakery",
            "type":"Retail Goods"
        }
    ],
    "sg:phone":"+31 514 562 614",
    "sg:postcode":"8531 BJ",
    "sg:province":"Friesland",
    "sg:tags":[
        "pizza"
    ],
    "wof:name":"Delizia",
    "wof:placetype":"venue"
},
  "geometry": {"coordinates":[5.712385,52.844051],"type":"Point"}
}