{
  "type": "Feature",
  "properties": {
    "addr:full":"Hoofdstr O 5 Noordwolde Fr Provincie Friesland 8391 AS",
    "addr:housenumber":"5",
    "addr:postcode":"8391 as",
    "addr:street":"Friesland",
    "iso:country":"NL",
    "sg:address":"Hoofdstr O 5",
    "sg:city":"Noordwolde Fr",
    "sg:orig_category":"Omroep",
    "sg:phone":"+31 561 432 222",
    "sg:postcode":"8391 AS",
    "sg:province":"Provincie Friesland",
    "wof:name":"Weststellingwerf Centraal, Radio",
    "wof:placetype":"venue"
},
  "geometry": {"coordinates":[6.14197,52.891758],"type":"Point"}
}