{
  "type": "Feature",
  "properties": {
    "iso:country":"NL",
    "sg:address":"Reeuwijkse Poort 103",
    "sg:city":"Reeuwijk",
    "sg:orig_category":"Huishoudapparatuur, Televisies And Radio'S",
    "sg:phone":"+31 182 300 000",
    "sg:postcode":"2811 MX",
    "sg:province":"South Holland",
    "wof:name":"Sirabo Bv",
    "wof:placetype":"venue"
},
  "geometry": {"coordinates":[4.72588,52.054642],"type":"Point"}
}