{
  "type": "Feature",
  "properties": {
    "addr:full":"Landbouwweg 27 Zeewolde NL. 3899 BB",
    "addr:housenumber":"27",
    "addr:postcode":"3899 bb",
    "addr:street":"Landbouwweg;Nl.",
    "iso:country":"NL",
    "sg:address":"Landbouwweg 27",
    "sg:city":"Zeewolde",
    "sg:orig_category":"Pompen And Compressoren Fab",
    "sg:phone":"+31 36 522 6456",
    "sg:postcode":"3899 BB",
    "sg:province":"NL.",
    "wof:name":"Flevo Transportmiddelen Zeewolde Bv",
    "wof:placetype":"venue"
},
  "geometry": {"coordinates":[5.496394,52.352291],"type":"Point"}
}