{
  "type": "Feature",
  "properties": {
    "addr:full":"Hoofdw 32 Bellingwolde Groningen 9695 AK",
    "addr:housenumber":"32",
    "addr:postcode":"9695 ak",
    "addr:street":"Hoofdw",
    "iso:country":"NL",
    "sg:address":"Hoofdw 32",
    "sg:city":"Bellingwolde",
    "sg:orig_category":"Kinderkleding",
    "sg:phone":"+31 597 531 274",
    "sg:postcode":"9695 AK",
    "sg:province":"Groningen",
    "wof:name":"Koolhof, Fa",
    "wof:placetype":"venue"
},
  "geometry": {"coordinates":[7.146085,53.101124],"type":"Point"}
}