{
  "type": "Feature",
  "properties": {
    "addr:full":"Veestr 32 Helmond North Brabant 5701 RD",
    "addr:housenumber":"32",
    "addr:postcode":"5701 rd",
    "addr:street":"Veestr",
    "iso:country":"NL",
    "sg:address":"Veestr 32",
    "sg:city":"Helmond",
    "sg:orig_category":"Boekhandels",
    "sg:phone":"+31 492 554 269",
    "sg:postcode":"5701 RD",
    "sg:province":"North Brabant",
    "wof:name":"Witte Boekenmarkt, De",
    "wof:placetype":"venue"
},
  "geometry": {"coordinates":[5.652854,51.479118],"type":"Point"}
}