{
  "type": "Feature",
  "properties": {
    "addr:full":"Oud Loosd Dk 25A Loosdrecht North Holland 1231 LN",
    "addr:housenumber":"25a",
    "addr:postcode":"1231 ln",
    "addr:street":"Oud;Dk",
    "iso:country":"NL",
    "sg:address":"Oud Loosd Dk 25A",
    "sg:city":"Loosdrecht",
    "sg:orig_category":"Bedrijfsorganisaties",
    "sg:phone":"+31 35 582 5869",
    "sg:postcode":"1231 LN",
    "sg:province":"North Holland",
    "wof:name":"Zeldenrijk, C",
    "wof:placetype":"venue"
},
  "geometry": {"coordinates":[5.121356,52.206577],"type":"Point"}
}