{
  "type": "Feature",
  "properties": {
    "iso:country":"NL",
    "sg:address":"Pastoorskuilenwg 1",
    "sg:city":"Hoensbroek",
    "sg:orig_category":"Opticiens",
    "sg:phone":"+31 45 521 2587",
    "sg:postcode":"6432 AA",
    "sg:province":"Limburg",
    "wof:name":"Martens",
    "wof:placetype":"venue"
},
  "geometry": {"coordinates":[5.9239292145,50.9239349365],"type":"Point"}
}