{
  "type": "Feature",
  "properties": {
    "addr:full":"Dommel 35 Gemert Noord-Brabant 5422 VH",
    "addr:housenumber":"35",
    "addr:postcode":"5422 vh",
    "addr:street":"Dommel",
    "iso:country":"NL",
    "sg:address":"Dommel 35",
    "sg:city":"Gemert",
    "sg:orig_category":"Goederenvervoer Over De Weg",
    "sg:phone":"+31 492 361 243",
    "sg:postcode":"5422 VH",
    "sg:province":"Noord-Brabant",
    "wof:name":"W.Ij. Van Heugten",
    "wof:placetype":"venue"
},
  "geometry": {"coordinates":[5.705301,51.563057],"type":"Point"}
}