{
  "type": "Feature",
  "properties": {
    "addr:full":"Kerkstraat 15 Huizen Noord-Holland 1271 RJ",
    "addr:housenumber":"15",
    "addr:postcode":"1271 rj",
    "addr:street":"Kerkstraat",
    "iso:country":"NL",
    "sg:address":"Kerkstraat 15",
    "sg:city":"Huizen",
    "sg:classifiers":[
        {
            "category":"Shopping",
            "subcategory":"Clothing, Apparel, & Fashions",
            "type":"Retail Goods"
        }
    ],
    "sg:phone":"+31 35 525 4641",
    "sg:postcode":"1271 RJ",
    "sg:province":"Noord-Holland",
    "sg:tags":[
        "ondergoed",
        "lingerie"
    ],
    "wof:name":"Livera",
    "wof:placetype":"venue"
},
  "geometry": {"coordinates":[5.236529,52.298454],"type":"Point"}
}