{
  "type": "Feature",
  "properties": {
    "addr:full":"Westelijke Kanaalweg 57 Wemeldinge Zeeland 4424 BG",
    "addr:housenumber":"57",
    "addr:postcode":"4424",
    "addr:street":"Westelijke Kanaalweg",
    "iso:country":"NL",
    "sg:address":"Westelijke Kanaalweg 57",
    "sg:city":"Wemeldinge",
    "sg:orig_category":"Loodgieterswerk, Verwarming And Sanitaire Installaties",
    "sg:phone":"+31 113 621 532",
    "sg:postcode":"4424 BG",
    "sg:province":"Zeeland",
    "wof:name":"Kloosterman",
    "wof:placetype":"venue"
},
  "geometry": {"coordinates":[4.002669,51.514523],"type":"Point"}
}