{
  "type": "Feature",
  "properties": {
    "addr:full":"Willem Ii Straat 39 Tilburg Noord-Brabant 5038 BC",
    "addr:housenumber":"39",
    "addr:postcode":"5038 bc",
    "addr:street":"Willem Ii Straat",
    "iso:country":"NL",
    "sg:address":"Willem Ii Straat 39",
    "sg:city":"Tilburg",
    "sg:orig_category":"Advocaten And Juridische Adviseurs",
    "sg:phone":"+31 13 535 5035",
    "sg:postcode":"5038 BC",
    "sg:province":"Noord-Brabant",
    "wof:name":"Mr Den Boer Bv",
    "wof:placetype":"venue"
},
  "geometry": {"coordinates":[5.086267,51.557636],"type":"Point"}
}