{
  "type": "Feature",
  "properties": {
    "iso:country":"NL",
    "sg:address":"Einsteinstr 67",
    "sg:city":"Dordrecht",
    "sg:orig_category":"Beveiliging",
    "sg:phone":"+31 78 641 5544",
    "sg:postcode":"3316 GG",
    "sg:province":"South Holland",
    "wof:name":"Geer",
    "wof:placetype":"venue"
},
  "geometry": {"coordinates":[4.636215,51.775417],"type":"Point"}
}