{
  "type": "Feature",
  "properties": {
    "addr:full":"Rorikstraat 3 Holten Overijssel 7451 GA",
    "addr:housenumber":"3",
    "addr:postcode":"7451 ga",
    "addr:street":"Rorikstraat",
    "iso:country":"NL",
    "sg:address":"Rorikstraat 3",
    "sg:city":"Holten",
    "sg:orig_category":"Bibliotheken And Openbare Archieven",
    "sg:phone":"+31 548 366 414",
    "sg:postcode":"7451 GA",
    "sg:province":"Overijssel",
    "wof:name":"Bibliotheek Holten",
    "wof:placetype":"venue"
},
  "geometry": {"coordinates":[6.423493,52.279598],"type":"Point"}
}