{
  "type": "Feature",
  "properties": {
    "addr:full":"Molenstr 98 Helmond Noord-Brabant 5701 KJ",
    "addr:housenumber":"98",
    "addr:postcode":"5701 kj",
    "addr:street":"Molenstr",
    "iso:country":"NL",
    "sg:address":"Molenstr 98",
    "sg:city":"Helmond",
    "sg:orig_category":"Zalenverhuur",
    "sg:phone":"+31 492 522 462",
    "sg:postcode":"5701 KJ",
    "sg:province":"Noord-Brabant",
    "wof:name":"Herbergh, De",
    "wof:placetype":"venue"
},
  "geometry": {"coordinates":[5.665318,51.47842],"type":"Point"}
}