{
  "type": "Feature",
  "properties": {
    "addr:full":"Troelstraplein 5 Zwijndrecht Zuid-Holland 3332 JB",
    "addr:housenumber":"5",
    "addr:postcode":"3332 jb",
    "addr:street":"Troelstraplein",
    "iso:country":"NL",
    "sg:address":"Troelstraplein 5",
    "sg:city":"Zwijndrecht",
    "sg:classifiers":[
        {
            "category":"Fast Food",
            "type":"Food & Drink"
        }
    ],
    "sg:phone":"+31 78 619 0229",
    "sg:postcode":"3332 JB",
    "sg:province":"Zuid-Holland",
    "sg:tags":[
        "afhaal",
        "restaurant"
    ],
    "wof:name":"Chinees Afhaalcentrum Kapoley",
    "wof:placetype":"venue"
},
  "geometry": {"coordinates":[4.6567587852,51.8275794983],"type":"Point"}
}