{
  "type": "Feature",
  "properties": {
    "iso:country":"NL",
    "sg:address":"Zeilstraat 3",
    "sg:city":"Volendam",
    "sg:orig_category":"Huishoudapparatuur, Televisies And Radio'S",
    "sg:phone":"+31 299 363 897",
    "sg:postcode":"1131 ED",
    "sg:province":"North Holland",
    "wof:name":"Tom Deen Bv",
    "wof:placetype":"venue"
},
  "geometry": {"coordinates":[5.075464,52.496334],"type":"Point"}
}