{
  "type": "Feature",
  "properties": {
    "addr:full":"Heijtsveld 145 Gemert North Brabant 5421 GZ",
    "addr:housenumber":"145",
    "addr:postcode":"5421 gz",
    "addr:street":"Heijtsveld",
    "iso:country":"NL",
    "sg:address":"Heijtsveld 145",
    "sg:city":"Gemert",
    "sg:orig_category":"Boekhouders",
    "sg:phone":"+31 492 366 391",
    "sg:postcode":"5421 GZ",
    "sg:province":"North Brabant",
    "wof:name":"Adviesburo Vrijsen",
    "wof:placetype":"venue"
},
  "geometry": {"coordinates":[5.698092,51.550629],"type":"Point"}
}