{
  "type": "Feature",
  "properties": {
    "addr:full":"Spechtstr 11 Leiderdorp Zuid-Holland 2352 EX",
    "addr:housenumber":"11",
    "addr:postcode":"2352 ex",
    "addr:street":"Spechtstr",
    "iso:country":"NL",
    "sg:address":"Spechtstr 11",
    "sg:city":"Leiderdorp",
    "sg:orig_category":"Kantoormachines",
    "sg:phone":"+31 71 589 5500",
    "sg:postcode":"2352 EX",
    "sg:province":"Zuid-Holland",
    "wof:name":"Resat",
    "wof:placetype":"venue"
},
  "geometry": {"coordinates":[4.526473999,52.160533905],"type":"Point"}
}