{
  "type": "Feature",
  "properties": {
    "addr:full":"Comeniusstr 663 Amsterdam Noord-Holland 1065 CC",
    "addr:housenumber":"663",
    "addr:postcode":"1065 cc",
    "iso:country":"NL",
    "sg:address":"Comeniusstr 663",
    "sg:city":"Amsterdam",
    "sg:orig_category":"Bedrijfsopleidingen",
    "sg:phone":"+31 6 22564448",
    "sg:postcode":"1065 CC",
    "sg:province":"Noord-Holland",
    "wof:name":"Systematic Communication & Defence",
    "wof:placetype":"venue"
},
  "geometry": {"coordinates":[4.825385,52.358746],"type":"Point"}
}