{
  "type": "Feature",
  "properties": {
    "iso:country":"NL",
    "sg:address":"Archerpad 8-10",
    "sg:city":"Almere",
    "sg:orig_category":"Zeilscholen",
    "sg:phone":"+31 36 533 0646",
    "sg:postcode":"1324 ZZ",
    "sg:province":"NL.",
    "sg:website":"http://www.haddockwatersport.nl",
    "wof:name":"Haddock Watersport",
    "wof:placetype":"venue"
},
  "geometry": {"coordinates":[5.22356,52.356441],"type":"Point"}
}