{
  "type": "Feature",
  "properties": {
    "iso:country":"NL",
    "sg:address":"Taludwg 10",
    "sg:city":"Oosterbeek",
    "sg:orig_category":"Adviesbureaus Planologie",
    "sg:phone":"+31 26 495 0415",
    "sg:postcode":"6861 ZL",
    "sg:province":"Gelderland",
    "wof:name":"Koning, Robbert De",
    "wof:placetype":"venue"
},
  "geometry": {"coordinates":[5.84855,51.989838],"type":"Point"}
}