{
  "type": "Feature",
  "properties": {
    "addr:full":"Wyenburg 90/A Amsterdam Noord-Holland 1082 VW",
    "addr:housenumber":"90 / a",
    "addr:postcode":"1082 vw",
    "addr:street":"Wyenburg",
    "iso:country":"NL",
    "sg:address":"Wyenburg 90/A",
    "sg:city":"Amsterdam",
    "sg:orig_category":"Kappers",
    "sg:phone":"+31 20 644 2926",
    "sg:postcode":"1082 VW",
    "sg:province":"Noord-Holland",
    "wof:name":"Hair Fit",
    "wof:placetype":"venue"
},
  "geometry": {"coordinates":[4.8775601387,52.3305206299],"type":"Point"}
}