{
  "type": "Feature",
  "properties": {
    "addr:full":"Industriewg 26 Waalwyk North Brabant 5145 PV",
    "addr:housenumber":"26",
    "addr:postcode":"5145 pv",
    "addr:street":"Industriewg",
    "iso:country":"NL",
    "sg:address":"Industriewg 26",
    "sg:city":"Waalwyk",
    "sg:orig_category":"Meubelmakerijen",
    "sg:phone":"+31 416 344 081",
    "sg:postcode":"5145 PV",
    "sg:province":"North Brabant",
    "wof:name":"Staelon Bv",
    "wof:placetype":"venue"
},
  "geometry": {"coordinates":[5.062136,51.696289],"type":"Point"}
}