{
  "type": "Feature",
  "properties": {
    "addr:full":"Den Heikop 5 Elsendorp North Brabant 5424 SV",
    "addr:housenumber":"5",
    "addr:postcode":"5424 sv",
    "addr:street":"Den Heikop",
    "iso:country":"NL",
    "sg:address":"Den Heikop 5",
    "sg:city":"Elsendorp",
    "sg:orig_category":"Koeriersdiensten",
    "sg:phone":"+31 492 352 098",
    "sg:postcode":"5424 SV",
    "sg:province":"North Brabant",
    "sg:website":"http://www.mkgkoeriers.nl",
    "wof:name":"Mkg Bv",
    "wof:placetype":"venue"
},
  "geometry": {"coordinates":[5.77463,51.577774],"type":"Point"}
}