{
  "type": "Feature",
  "properties": {
    "addr:full":"Rotgansstr 39 S Gravenhage Zuid-Holland 2533 LC",
    "addr:housenumber":"39;gravenhage",
    "addr:postcode":"2533 lc",
    "addr:street":"Rotgansstr;S",
    "iso:country":"NL",
    "sg:address":"Rotgansstr 39",
    "sg:city":"S Gravenhage",
    "sg:orig_category":"Metselwerken",
    "sg:phone":"+31 70 380 2683",
    "sg:postcode":"2533 LC",
    "sg:province":"Zuid-Holland",
    "wof:name":"Bunschoten, P J",
    "wof:placetype":"venue"
},
  "geometry": {"coordinates":[4.28581,52.05286],"type":"Point"}
}