{
  "type": "Feature",
  "properties": {
    "addr:full":"Burgemeester Simonsstr 1 Halfweg Nh Noord-Holland 1165 LS",
    "addr:housenumber":"1",
    "addr:postcode":"1165 ls",
    "addr:street":"Burgemeester Simonsstr",
    "iso:country":"NL",
    "sg:address":"Burgemeester Simonsstr 1",
    "sg:city":"Halfweg Nh",
    "sg:orig_category":"Loodgieterswerk, Verwarming And Sanitaire Installaties",
    "sg:phone":"+31 20 497 3770",
    "sg:postcode":"1165 LS",
    "sg:province":"Noord-Holland",
    "wof:name":"J. Heeren",
    "wof:placetype":"venue"
},
  "geometry": {"coordinates":[4.758729,52.383587],"type":"Point"}
}