{
  "type": "Feature",
  "properties": {
    "addr:full":"Handijksweg 4A Deurningen NL.08 7561 PD",
    "addr:housenumber":"4a;nl.08",
    "addr:postcode":"7561 pd",
    "addr:street":"Handijksweg",
    "iso:country":"NL",
    "sg:address":"Handijksweg 4A",
    "sg:city":"Deurningen",
    "sg:orig_category":"Pluimveehouderijen",
    "sg:phone":"+31 74 277 1944",
    "sg:postcode":"7561 PD",
    "sg:province":"NL.08",
    "wof:name":"F.J.J. Deterd Oude Weme",
    "wof:placetype":"venue"
},
  "geometry": {"coordinates":[6.845793,52.31926],"type":"Point"}
}