{
  "type": "Feature",
  "properties": {
    "iso:country":"NL",
    "sg:address":"Nicolaas Verschoorstraat 12",
    "sg:city":"Hellevoetsluis",
    "sg:orig_category":"Boekhouders",
    "sg:phone":"+31 181 326 137",
    "sg:postcode":"3223 RK",
    "sg:province":"South Holland",
    "wof:name":"Administratiekantoor H. Benner",
    "wof:placetype":"venue"
},
  "geometry": {"coordinates":[4.149203,51.843998],"type":"Point"}
}