{
  "type": "Feature",
  "properties": {
    "addr:full":"Houtlaan 18B Groesbeek Gelderland 6562 ZZ",
    "addr:housenumber":"18b",
    "addr:postcode":"6562 zz",
    "addr:street":"Houtlaan;Gelderland",
    "iso:country":"NL",
    "sg:address":"Houtlaan 18B",
    "sg:city":"Groesbeek",
    "sg:orig_category":"Chemische Producten Gh",
    "sg:phone":"+31 24 397 6507",
    "sg:postcode":"6562 ZZ",
    "sg:province":"Gelderland",
    "wof:name":"J.H.S. Sluis",
    "wof:placetype":"venue"
},
  "geometry": {"coordinates":[5.93249,51.776745],"type":"Point"}
}