{
  "type": "Feature",
  "properties": {
    "addr:full":"Capucynengang 10 Maastricht Limburg 6211 RV",
    "addr:housenumber":"10",
    "addr:postcode":"6211 rv",
    "addr:street":"Capucynengang",
    "iso:country":"NL",
    "sg:address":"Capucynengang 10",
    "sg:city":"Maastricht",
    "sg:orig_category":"Kinderopvang",
    "sg:phone":"+31 43 321 5200",
    "sg:postcode":"6211 RV",
    "sg:province":"Limburg",
    "wof:name":"Plons",
    "wof:placetype":"venue"
},
  "geometry": {"coordinates":[5.686995,50.85128],"type":"Point"}
}