{
  "type": "Feature",
  "properties": {
    "addr:full":"Thierensstr 1B Bussum Noord-Holland 1404 CZ",
    "addr:housenumber":"1b",
    "addr:postcode":"1404",
    "addr:street":"Thierensstr",
    "iso:country":"NL",
    "sg:address":"Thierensstr 1B",
    "sg:city":"Bussum",
    "sg:orig_category":"Meubelen",
    "sg:phone":"+31 35 693 9735",
    "sg:postcode":"1404 CZ",
    "sg:province":"Noord-Holland",
    "sg:website":"http://www.passing.nl",
    "wof:name":"Passing",
    "wof:placetype":"venue"
},
  "geometry": {"coordinates":[5.164297,52.274235],"type":"Point"}
}