{
  "type": "Feature",
  "properties": {
    "addr:full":"Straatwg 53 Breukelen Ut Utrecht 3621 BH",
    "addr:housenumber":"53",
    "addr:postcode":"3621 bh",
    "addr:street":"Straatwg",
    "iso:country":"NL",
    "sg:address":"Straatwg 53",
    "sg:city":"Breukelen Ut",
    "sg:orig_category":"Banken",
    "sg:phone":"+31 346 269 411",
    "sg:postcode":"3621 BH",
    "sg:province":"Utrecht",
    "sg:website":"http://www.rabobank.nl",
    "wof:name":"Rabobank",
    "wof:placetype":"venue"
},
  "geometry": {"coordinates":[5.002286,52.170818],"type":"Point"}
}