{
  "type": "Feature",
  "properties": {
    "addr:full":"Kerkstr 35 S Gravendeel Zuid-Holland 3295 BD",
    "addr:housenumber":"35",
    "addr:postcode":"3295 bd",
    "addr:street":"Kerkstr;S Gravendeel",
    "iso:country":"NL",
    "sg:address":"Kerkstr 35",
    "sg:city":"S Gravendeel",
    "sg:orig_category":"Bloemen En Planten",
    "sg:phone":"+31 78 673 6431",
    "sg:postcode":"3295 BD",
    "sg:province":"Zuid-Holland",
    "wof:name":"Beijersehof",
    "wof:placetype":"venue"
},
  "geometry": {"coordinates":[4.615964,51.778721],"type":"Point"}
}