{
  "type": "Feature",
  "properties": {
    "addr:full":"Waterkant 22 Diemen Noord-Holland 1112 RD",
    "addr:housenumber":"22",
    "addr:postcode":"1112 rd",
    "addr:street":"Waterkant",
    "iso:country":"NL",
    "sg:address":"Waterkant 22",
    "sg:city":"Diemen",
    "sg:orig_category":"Autorijscholen",
    "sg:phone":"+31 20 690 2931",
    "sg:postcode":"1112 RD",
    "sg:province":"Noord-Holland",
    "wof:name":"Vis-Je Rijbewijs",
    "wof:placetype":"venue"
},
  "geometry": {"coordinates":[4.954886,52.331165],"type":"Point"}
}