{
  "type": "Feature",
  "properties": {
    "addr:full":"Rakkersveld 4 Zoetermeer South Holland 2722 BM",
    "addr:housenumber":"4",
    "addr:postcode":"2722 bm",
    "addr:street":"Rakkersveld",
    "iso:country":"NL",
    "sg:address":"Rakkersveld 4",
    "sg:city":"Zoetermeer",
    "sg:classifiers":[
        {
            "category":"Education",
            "subcategory":"Preschool",
            "type":"Public Place"
        }
    ],
    "sg:phone":"+31 79 331 1169",
    "sg:postcode":"2722 BM",
    "sg:province":"South Holland",
    "sg:tags":[
        "kleuteronderwijs",
        "basis-"
    ],
    "wof:name":"De Meerpaal Openbare Basisschool",
    "wof:placetype":"venue"
},
  "geometry": {"coordinates":[4.507212,52.056732],"type":"Point"}
}