{
  "type": "Feature",
  "properties": {
    "addr:full":"Rijksstraatweg 48 Heemskerk Noord-Holland 1964 LJ",
    "addr:housenumber":"48",
    "addr:postcode":"1964 lj",
    "addr:street":"Rijksstraatweg",
    "iso:country":"NL",
    "sg:address":"Rijksstraatweg 48",
    "sg:city":"Heemskerk",
    "sg:orig_category":"Fruit And Groenten Gh",
    "sg:phone":"+31 251 247 004",
    "sg:postcode":"1964 LJ",
    "sg:province":"Noord-Holland",
    "wof:name":"Vof N.J. De Vries En Zn.",
    "wof:placetype":"venue"
},
  "geometry": {"coordinates":[4.654841,52.506187],"type":"Point"}
}