{
  "type": "Feature",
  "properties": {
    "addr:full":"Rivium Quadrant 81 Capelle Ad Yssel Zuid-Holland 2909 LC",
    "addr:housenumber":"81",
    "addr:postcode":"2909 lc",
    "addr:street":"Rivium Quadrant",
    "iso:country":"NL",
    "sg:address":"Rivium Quadrant 81",
    "sg:city":"Capelle Ad Yssel",
    "sg:orig_category":"Werving En Selectie",
    "sg:phone":"+31 10 288 0088",
    "sg:postcode":"2909 LC",
    "sg:province":"Zuid-Holland",
    "sg:website":"http://www.secretaryjobs.nl",
    "wof:name":"Bouwer Werving & Selectie",
    "wof:placetype":"venue"
},
  "geometry": {"coordinates":[4.5391321182,51.9138717651],"type":"Point"}
}