{
  "type": "Feature",
  "properties": {
    "addr:full":"Hoogstad 209 Vlaardingen Zuid-Holland 3131 KX",
    "addr:housenumber":"209",
    "addr:postcode":"3131 kx",
    "addr:street":"Hoogstad",
    "iso:country":"NL",
    "sg:address":"Hoogstad 209",
    "sg:city":"Vlaardingen",
    "sg:orig_category":"Woningstoffeerders",
    "sg:phone":"+31 10 435 2704",
    "sg:postcode":"3131 KX",
    "sg:province":"Zuid-Holland",
    "wof:name":"L'Interieur Decorative",
    "wof:placetype":"venue"
},
  "geometry": {"coordinates":[4.3360748291,51.9183235168],"type":"Point"}
}