{
  "type": "Feature",
  "properties": {
    "iso:country":"NL",
    "sg:address":"Zanglijster 42",
    "sg:city":"Venhuizen",
    "sg:orig_category":"Sportclubs",
    "sg:phone":"+31 228 543 097",
    "sg:postcode":"1606 CP",
    "sg:province":"Noord-Holland",
    "wof:name":"Svh Gymvereniging",
    "wof:placetype":"venue"
},
  "geometry": {"coordinates":[5.207193,52.66526],"type":"Point"}
}