{
  "type": "Feature",
  "properties": {
    "iso:country":"NL",
    "sg:address":"Postbus 20136",
    "sg:city":"Apeldoorn",
    "sg:orig_category":"Schilders",
    "sg:phone":"+31 55 541 2327",
    "sg:postcode":"7302 HC",
    "sg:province":"Noord-Holland",
    "wof:name":"Stichting Schilderwerken",
    "wof:placetype":"venue"
},
  "geometry": {"coordinates":[5.96246,52.214329],"type":"Point"}
}