{
  "type": "Feature",
  "properties": {
    "addr:full":"De Schans 76A Hoornaar Zuid-Holland 4223 NW",
    "addr:housenumber":"76a",
    "addr:postcode":"4223 nw",
    "addr:street":"De Schans",
    "iso:country":"NL",
    "sg:address":"De Schans 76A",
    "sg:city":"Hoornaar",
    "sg:orig_category":"Kinderopvang Behalve Thuis",
    "sg:phone":"+31 183 582 390",
    "sg:postcode":"4223 NW",
    "sg:province":"Zuid-Holland",
    "wof:name":"Peuterspeelzaal De Boskabouter",
    "wof:placetype":"venue"
},
  "geometry": {"coordinates":[4.949539,51.876637],"type":"Point"}
}