{
  "type": "Feature",
  "properties": {
    "addr:full":"Pleiaden 8 Hoogezand Groningen 9602 KD",
    "addr:housenumber":"8",
    "addr:postcode":"9602 kd",
    "addr:street":"Pleiaden",
    "iso:country":"NL",
    "sg:address":"Pleiaden 8",
    "sg:city":"Hoogezand",
    "sg:orig_category":"Kappers",
    "sg:phone":"+31 598 326 539",
    "sg:postcode":"9602 KD",
    "sg:province":"Groningen",
    "wof:name":"Headmasters",
    "wof:placetype":"venue"
},
  "geometry": {"coordinates":[6.7417078018,53.1489143372],"type":"Point"}
}