{
  "type": "Feature",
  "properties": {
    "addr:full":"Oude Rijksweg 207 Staphorst NL.08 7951 EE",
    "addr:housenumber":"207;nl.08",
    "addr:postcode":"7951 ee",
    "addr:street":"Oude Rijksweg",
    "iso:country":"NL",
    "sg:address":"Oude Rijksweg 207",
    "sg:city":"Staphorst",
    "sg:orig_category":"Autokeuringen",
    "sg:phone":"+31 522 461 817",
    "sg:postcode":"7951 EE",
    "sg:province":"NL.08",
    "wof:name":"Autobedrijf Hilboezen",
    "wof:placetype":"venue"
},
  "geometry": {"coordinates":[6.1895,52.635593],"type":"Point"}
}