{
  "type": "Feature",
  "properties": {
    "iso:country":"NL",
    "sg:address":"Wilhelminastraat 36",
    "sg:city":"Didam",
    "sg:orig_category":"Opticiens",
    "sg:phone":"+31 316 221 820",
    "sg:postcode":"6942 BM",
    "sg:province":"Gelderland",
    "wof:name":"Wim Coenraadts Optiek",
    "wof:placetype":"venue"
},
  "geometry": {"coordinates":[6.1282148361,51.9367103577],"type":"Point"}
}