{
  "type": "Feature",
  "properties": {
    "iso:country":"NL",
    "sg:address":"Kerklaan 22",
    "sg:city":"De Kwakel",
    "sg:classifiers":[
        {
            "category":"Fast Food",
            "type":"Food & Drink"
        }
    ],
    "sg:phone":"+31 297 564 737",
    "sg:postcode":"1424 BK",
    "sg:province":"North Holland",
    "sg:tags":[
        "afhaal",
        "restaurant"
    ],
    "wof:name":"Snackbar Het Trefpunt",
    "wof:placetype":"venue"
},
  "geometry": {"coordinates":[4.79357,52.23859],"type":"Point"}
}