{
  "type": "Feature",
  "properties": {
    "addr:full":"Gangetje 12 Leiden Zuid-Holland 2311 ER",
    "addr:housenumber":"12",
    "addr:postcode":"2311 er",
    "addr:street":"Gangetje",
    "iso:country":"NL",
    "sg:address":"Gangetje 12",
    "sg:city":"Leiden",
    "sg:orig_category":"Hypotheken And Hypotheekbanken",
    "sg:phone":"+31 71 514 0447",
    "sg:postcode":"2311 ER",
    "sg:province":"Zuid-Holland",
    "wof:name":"Fdc Hypotheekadviseurs Leiden Bv",
    "wof:placetype":"venue"
},
  "geometry": {"coordinates":[4.493657,52.156666],"type":"Point"}
}