{
  "type": "Feature",
  "properties": {
    "addr:full":"Neerlandstr 30 Geldrop North Brabant 5662 JC",
    "addr:housenumber":"30",
    "addr:postcode":"5662 jc",
    "addr:street":"Neerlandstr",
    "iso:country":"NL",
    "sg:address":"Neerlandstr 30",
    "sg:city":"Geldrop",
    "sg:orig_category":"Woningbureaus",
    "sg:phone":"+31 40 285 0030",
    "sg:postcode":"5662 JC",
    "sg:province":"North Brabant",
    "wof:name":"Claassens, K G J",
    "wof:placetype":"venue"
},
  "geometry": {"coordinates":[5.5514988899,51.4252243042],"type":"Point"}
}