{
  "type": "Feature",
  "properties": {
    "addr:full":"Harsweg 29 Ter Aar South Holland 2461 EZ",
    "addr:housenumber":"29",
    "addr:postcode":"2461 ez",
    "addr:street":"Harsweg",
    "iso:country":"NL",
    "sg:address":"Harsweg 29",
    "sg:city":"Ter Aar",
    "sg:orig_category":"Beveiliging",
    "sg:phone":"+31 172 614 344",
    "sg:postcode":"2461 EZ",
    "sg:province":"South Holland",
    "sg:website":"http://www.avsh.nl",
    "wof:name":"Avsh",
    "wof:placetype":"venue"
},
  "geometry": {"coordinates":[4.712071,52.17638],"type":"Point"}
}