{
  "type": "Feature",
  "properties": {
    "addr:full":"Amstelplein 225 Uithoorn Noord-Holland 1421 SE",
    "addr:housenumber":"225",
    "addr:postcode":"1421 se",
    "addr:street":"Amstelplein",
    "iso:country":"NL",
    "sg:address":"Amstelplein 225",
    "sg:city":"Uithoorn",
    "sg:orig_category":"Woningbouwverenigingen",
    "sg:phone":"+31 297 577 111",
    "sg:postcode":"1421 SE",
    "sg:province":"Noord-Holland",
    "wof:name":"Woongroep Holland",
    "wof:placetype":"venue"
},
  "geometry": {"coordinates":[4.8277001381,52.2328338623],"type":"Point"}
}