{
  "type": "Feature",
  "properties": {
    "addr:full":"Heringaweg 4 Haarlem Noord-Holland 2031 BW",
    "addr:housenumber":"4",
    "addr:postcode":"2031 bw",
    "addr:street":"Heringaweg",
    "iso:country":"NL",
    "sg:address":"Heringaweg 4",
    "sg:city":"Haarlem",
    "sg:orig_category":"Verhuur Bouwmachines",
    "sg:phone":"+31 23 532 2240",
    "sg:postcode":"2031 BW",
    "sg:province":"Noord-Holland",
    "wof:name":"Van Santen'S Hijskranen Maatschappij Bv",
    "wof:placetype":"venue"
},
  "geometry": {"coordinates":[4.655646,52.393963],"type":"Point"}
}