{
  "type": "Feature",
  "properties": {
    "addr:full":"Dorpsstraat 30 Wilnis Utrecht 3648 AH",
    "addr:housenumber":"30",
    "addr:postcode":"3648 ah",
    "addr:street":"Dorpsstraat",
    "iso:country":"NL",
    "sg:address":"Dorpsstraat 30",
    "sg:city":"Wilnis",
    "sg:orig_category":"Banken And Kredietinstellingen",
    "sg:phone":"+31 297 281 411",
    "sg:postcode":"3648 AH",
    "sg:province":"Utrecht",
    "wof:name":"Postkantoor",
    "wof:placetype":"venue"
},
  "geometry": {"coordinates":[4.90379,52.195156],"type":"Point"}
}