{
  "type": "Feature",
  "properties": {
    "iso:country":"NL",
    "sg:address":"Schuur 149",
    "sg:city":"Drachten",
    "sg:orig_category":"Hek- En Rasterwerken",
    "sg:phone":"+31 512 540 406",
    "sg:postcode":"9205 BH",
    "sg:province":"Friesland",
    "wof:name":"Bijlsma",
    "wof:placetype":"venue"
},
  "geometry": {"coordinates":[6.058491,53.09388],"type":"Point"}
}