{
  "type": "Feature",
  "properties": {
    "iso:country":"NL",
    "sg:address":"Stationsstr 15",
    "sg:city":"Tynaarlo",
    "sg:orig_category":"Hondenscholen",
    "sg:phone":"+31 592 544 088",
    "sg:postcode":"9482 TX",
    "sg:province":"Provincie Drenthe",
    "wof:name":"Xenofon, Hondenschool",
    "wof:placetype":"venue"
},
  "geometry": {"coordinates":[6.62852,53.077583],"type":"Point"}
}