{
  "type": "Feature",
  "properties": {
    "addr:full":"Sloetstraat 69 Arnhem Gelderland 6821 CP",
    "addr:housenumber":"69",
    "addr:postcode":"6821 cp",
    "addr:street":"Sloetstraat",
    "iso:country":"NL",
    "sg:address":"Sloetstraat 69",
    "sg:city":"Arnhem",
    "sg:orig_category":"Advocaten And Juridische Adviseurs",
    "sg:phone":"+31 26 445 4442",
    "sg:postcode":"6821 CP",
    "sg:province":"Gelderland",
    "wof:name":"Advokatenkollektief Sloetstraat",
    "wof:placetype":"venue"
},
  "geometry": {"coordinates":[5.913072,51.98888],"type":"Point"}
}