{
  "type": "Feature",
  "properties": {
    "addr:full":"Baken 107 Groningen Groningen 9732 BE",
    "addr:housenumber":"107",
    "addr:postcode":"9732",
    "addr:street":"Baken",
    "iso:country":"NL",
    "sg:address":"Baken 107",
    "sg:city":"Groningen",
    "sg:orig_category":"Kappers",
    "sg:phone":"+31 6 28914605",
    "sg:postcode":"9732 BE",
    "sg:province":"Groningen",
    "wof:name":"Knip-Out",
    "wof:placetype":"venue"
},
  "geometry": {"coordinates":[6.625366,53.233253],"type":"Point"}
}