{
  "type": "Feature",
  "properties": {
    "addr:full":"Jacob Gerritstraat 16 Delft Zuid-Holland 2611 ES",
    "addr:housenumber":"16",
    "addr:postcode":"2611 es",
    "addr:street":"Jacob Gerritstraat",
    "iso:country":"NL",
    "sg:address":"Jacob Gerritstraat 16",
    "sg:city":"Delft",
    "sg:orig_category":"Juweliers",
    "sg:phone":"+31 15 215 9720",
    "sg:postcode":"2611 ES",
    "sg:province":"Zuid-Holland",
    "wof:name":"Juwelier Sies",
    "wof:placetype":"venue"
},
  "geometry": {"coordinates":[4.359994,52.011173],"type":"Point"}
}