{
  "type": "Feature",
  "properties": {
    "addr:full":"Bredaseweg 28 Chaam Noord-Brabant 4861 AJ",
    "addr:housenumber":"28",
    "addr:postcode":"4861 aj",
    "addr:street":"Bredaseweg",
    "iso:country":"NL",
    "sg:address":"Bredaseweg 28",
    "sg:city":"Chaam",
    "sg:orig_category":"Meubelreparatie And -Restauratie",
    "sg:phone":"+31 161 492 465",
    "sg:postcode":"4861 AJ",
    "sg:province":"Noord-Brabant",
    "wof:name":"De Stoffeerder Vof",
    "wof:placetype":"venue"
},
  "geometry": {"coordinates":[4.856644,51.507751],"type":"Point"}
}