{
  "type": "Feature",
  "properties": {
    "addr:full":"Stieltjesstraat 78 Rotterdam Zuid-Holland 3071 JX",
    "addr:housenumber":"78",
    "addr:postcode":"3071 jx",
    "addr:street":"Stieltjesstraat",
    "iso:country":"NL",
    "sg:address":"Stieltjesstraat 78",
    "sg:city":"Rotterdam",
    "sg:orig_category":"Zalenexploitatie",
    "sg:phone":"+31 10 484 1740",
    "sg:postcode":"3071 JX",
    "sg:province":"Zuid-Holland",
    "wof:name":"One To Z Interieur Architectuur",
    "wof:placetype":"venue"
},
  "geometry": {"coordinates":[4.494981,51.909428],"type":"Point"}
}