{
  "type": "Feature",
  "properties": {
    "iso:country":"NL",
    "sg:address":"Ter Hooge 11",
    "sg:city":"Almelo",
    "sg:orig_category":"Adviesbureaus Bedrijfsorganisatie",
    "sg:phone":"+31 546 867 994",
    "sg:postcode":"7608 LJ",
    "sg:province":"NL.08",
    "wof:name":"Wima",
    "wof:placetype":"venue"
},
  "geometry": {"coordinates":[6.672537,52.37191],"type":"Point"}
}