{
  "type": "Feature",
  "properties": {
    "addr:full":"Oranjepln 203 Maastricht Limburg 6224 KV",
    "addr:housenumber":"203",
    "addr:postcode":"6224 kv",
    "iso:country":"NL",
    "sg:address":"Oranjepln 203",
    "sg:city":"Maastricht",
    "sg:orig_category":"Verzekeringen - Verzekeringskantoren",
    "sg:phone":"+31 43 363 4166",
    "sg:postcode":"6224 KV",
    "sg:province":"Limburg",
    "wof:name":"Kalse Br\u00fcggemann Verzekeringen",
    "wof:placetype":"venue"
},
  "geometry": {"coordinates":[5.711395,50.847382],"type":"Point"}
}