{
  "type": "Feature",
  "properties": {
    "addr:full":"Overschiesewg 222 Schiedam Zuid-Holland 3112 NB",
    "addr:housenumber":"222",
    "addr:postcode":"3112 nb",
    "iso:country":"NL",
    "sg:address":"Overschiesewg 222",
    "sg:city":"Schiedam",
    "sg:orig_category":"On- Offshore",
    "sg:phone":"+31 10 246 6940",
    "sg:postcode":"3112 NB",
    "sg:province":"Zuid-Holland",
    "sg:website":"http://www.mscoffshore.nl",
    "wof:name":"Msc Bv",
    "wof:placetype":"venue"
},
  "geometry": {"coordinates":[4.407749,51.922749],"type":"Point"}
}