{
  "type": "Feature",
  "properties": {
    "addr:full":"Zomerweg 180 Enschede Overijssel 7532 RV",
    "addr:housenumber":"180",
    "addr:postcode":"7532 rv",
    "addr:street":"Zomerweg",
    "iso:country":"NL",
    "sg:address":"Zomerweg 180",
    "sg:city":"Enschede",
    "sg:orig_category":"Zuivelproducten And Spijsoli?n Gh",
    "sg:phone":"+31 53 461 2399",
    "sg:postcode":"7532 RV",
    "sg:province":"Overijssel",
    "wof:name":"Haro Enschede",
    "wof:placetype":"venue"
},
  "geometry": {"coordinates":[6.944923,52.223137],"type":"Point"}
}