{
  "type": "Feature",
  "properties": {
    "addr:full":"Hoofdweg 166 Bovensmilde Drenthe 9421 PC",
    "addr:housenumber":"166",
    "addr:postcode":"9421 pc",
    "addr:street":"Hoofdweg",
    "iso:country":"NL",
    "sg:address":"Hoofdweg 166",
    "sg:city":"Bovensmilde",
    "sg:orig_category":"Fotografische And Optische Artikelen Gh",
    "sg:phone":"+31 592 412 893",
    "sg:postcode":"9421 PC",
    "sg:province":"Drenthe",
    "wof:name":"T.H. De Groot",
    "wof:placetype":"venue"
},
  "geometry": {"coordinates":[6.477121,52.978348],"type":"Point"}
}