{
  "type": "Feature",
  "properties": {
    "addr:full":"Abdystr 6 Heeswyk Dinther North Brabant 5473 AE",
    "addr:housenumber":"6",
    "addr:postcode":"5473 ae",
    "addr:street":"Abdystr",
    "iso:country":"NL",
    "sg:address":"Abdystr 6",
    "sg:city":"Heeswyk Dinther",
    "sg:orig_category":"Boekbinderijen",
    "sg:phone":"+31 413 293 902",
    "sg:postcode":"5473 AE",
    "sg:province":"North Brabant",
    "sg:website":"http://www.boekenlegger.nl",
    "wof:name":"Boekenlegger, De",
    "wof:placetype":"venue"
},
  "geometry": {"coordinates":[5.46889,51.650845],"type":"Point"}
}