{
  "type": "Feature",
  "properties": {
    "addr:full":"Nieuwemeerdk 294 Badhoevedorp Noord-Holland 1171 NS",
    "addr:housenumber":"294",
    "addr:postcode":"badhoevedorp;1171 ns",
    "iso:country":"NL",
    "sg:address":"Nieuwemeerdk 294",
    "sg:city":"Badhoevedorp",
    "sg:orig_category":"Verenigingsgebouwen",
    "sg:phone":"+31 20 601 0616",
    "sg:postcode":"1171 NS",
    "sg:province":"Noord-Holland",
    "wof:name":"Rehoboth",
    "wof:placetype":"venue"
},
  "geometry": {"coordinates":[4.813964,52.327991],"type":"Point"}
}