{
  "type": "Feature",
  "properties": {
    "addr:full":"Dorpsstr 84 Chaam North Brabant 4861 AD",
    "addr:housenumber":"84",
    "addr:postcode":"4861 ad",
    "addr:street":"Dorpsstr",
    "iso:country":"NL",
    "sg:address":"Dorpsstr 84",
    "sg:city":"Chaam",
    "sg:orig_category":"Fietsen En Bromfietsen Onderdelen - Fabr. En Grooth",
    "sg:phone":"+31 161 491 272",
    "sg:postcode":"4861 AD",
    "sg:province":"North Brabant",
    "wof:name":"Smeekens, F R",
    "wof:placetype":"venue"
},
  "geometry": {"coordinates":[4.859586,51.506393],"type":"Point"}
}