{
  "type": "Feature",
  "properties": {
    "iso:country":"NL",
    "sg:address":"Roerdomp 15",
    "sg:city":"'S Hertogenbosch",
    "sg:orig_category":"Marktonderzoekbureaus",
    "sg:phone":"+31 73 633 0153",
    "sg:postcode":"5221 HL",
    "sg:province":"North Brabant",
    "wof:name":"1 A 4",
    "wof:placetype":"venue"
},
  "geometry": {"coordinates":[5.260402,51.720634],"type":"Point"}
}