{
  "type": "Feature",
  "properties": {
    "addr:full":"V Beethovensngl 48A Rotterdam Zuid-Holland 3055 JK",
    "addr:housenumber":"48a",
    "addr:postcode":"3055 jk",
    "iso:country":"NL",
    "sg:address":"V Beethovensngl 48A",
    "sg:city":"Rotterdam",
    "sg:orig_category":"Zonnebank- En Solariumcentra",
    "sg:phone":"+31 10 418 8555",
    "sg:postcode":"3055 JK",
    "sg:province":"Zuid-Holland",
    "wof:name":"California Beautycenter",
    "wof:placetype":"venue"
},
  "geometry": {"coordinates":[4.50689,51.961319],"type":"Point"}
}