{
  "type": "Feature",
  "properties": {
    "iso:country":"NL",
    "sg:address":"J P Heyestr 86",
    "sg:city":"Amsterdam",
    "sg:orig_category":"Kappers",
    "sg:phone":"+31 20 616 5914",
    "sg:postcode":"1053 GS",
    "sg:province":"North Holland",
    "wof:name":"Pieter Bas",
    "wof:placetype":"venue"
},
  "geometry": {"coordinates":[4.86733,52.366638],"type":"Point"}
}