{
  "type": "Feature",
  "properties": {
    "iso:country":"NL",
    "sg:address":"Pannerdensedijk 10",
    "sg:city":"Aerdt",
    "sg:orig_category":"Verhuur Voertuigen Behalve Auto'S",
    "sg:phone":"+31 316 371 881",
    "sg:postcode":"6913 KK",
    "sg:province":"Gelderland",
    "wof:name":"G & S",
    "wof:placetype":"venue"
},
  "geometry": {"coordinates":[6.08872,51.884781],"type":"Point"}
}