{
  "type": "Feature",
  "properties": {
    "addr:full":"Nieuwgraaf 24 Duiven Rio de Janeiro 6921 RJ",
    "addr:housenumber":"24;6921",
    "addr:postcode":"rj",
    "addr:street":"Nieuwgraaf;Rio De Janeiro",
    "iso:country":"NL",
    "sg:address":"Nieuwgraaf 24",
    "sg:city":"Duiven",
    "sg:orig_category":"Kantoorapparatuur Gh",
    "sg:phone":"+31 26 311 6888",
    "sg:postcode":"6921 RJ",
    "sg:province":"Rio de Janeiro",
    "wof:name":"Office Centre",
    "wof:placetype":"venue"
},
  "geometry": {"coordinates":[-42.9211997986,-22.0671596527],"type":"Point"}
}