{
  "type": "Feature",
  "properties": {
    "addr:full":"Ritsevoort 37 Alkmaar Noord-Holland 1811 DM",
    "addr:housenumber":"37",
    "addr:postcode":"1811 dm",
    "addr:street":"Ritsevoort",
    "iso:country":"NL",
    "sg:address":"Ritsevoort 37",
    "sg:city":"Alkmaar",
    "sg:orig_category":"Metaalwerken",
    "sg:phone":"+31 72 511 2814",
    "sg:postcode":"1811 DM",
    "sg:province":"Noord-Holland",
    "wof:name":"Wim Van Der Werff'S Tapijt- En Gordijnvoordeel Bv",
    "wof:placetype":"venue"
},
  "geometry": {"coordinates":[4.742806,52.630085],"type":"Point"}
}