{
  "type": "Feature",
  "properties": {
    "iso:country":"NL",
    "sg:address":"Larixplantsoen 28",
    "sg:city":"Heerhugowaard",
    "sg:orig_category":"Gebouwenafwerking, Renovaties And Reiniging",
    "sg:phone":"+31 72 571 5573",
    "sg:postcode":"1702 XH",
    "sg:province":"Noord-Holland",
    "wof:name":"Aannemingsbedrijf Rudeka Bv",
    "wof:placetype":"venue"
},
  "geometry": {"coordinates":[4.839004,52.659077],"type":"Point"}
}