{
  "type": "Feature",
  "properties": {
    "addr:full":"Bernsestr 6 Heusden Gem Heusd North Brabant 5256 ND",
    "addr:housenumber":"6",
    "addr:postcode":"5256 nd",
    "addr:street":"Bernsestr",
    "iso:country":"NL",
    "sg:address":"Bernsestr 6",
    "sg:city":"Heusden Gem Heusd",
    "sg:orig_category":"Kunstnijverheidsateliers",
    "sg:phone":"+31 416 662 367",
    "sg:postcode":"5256 ND",
    "sg:province":"North Brabant",
    "wof:name":"Maoske, 'T",
    "wof:placetype":"venue"
},
  "geometry": {"coordinates":[5.158118,51.733044],"type":"Point"}
}