{
  "type": "Feature",
  "properties": {
    "addr:full":"Ambachtstr 1A Montfoort Utrecht 3417 EX",
    "addr:housenumber":"1a",
    "addr:postcode":"3417 ex",
    "addr:street":"Ambachtstr",
    "iso:country":"NL",
    "sg:address":"Ambachtstr 1A",
    "sg:city":"Montfoort",
    "sg:orig_category":"Onderhoudswerken",
    "sg:phone":"+31 348 472 491",
    "sg:postcode":"3417 EX",
    "sg:province":"Utrecht",
    "wof:name":"Jong, J W De",
    "wof:placetype":"venue"
},
  "geometry": {"coordinates":[4.953672,52.046539],"type":"Point"}
}