{
  "type": "Feature",
  "properties": {
    "iso:country":"NL",
    "sg:address":"Entstr 46",
    "sg:city":"Oudenbosch",
    "sg:orig_category":"Vertaalbureaus",
    "sg:phone":"+31 165 317 255",
    "sg:postcode":"4731 XH",
    "sg:province":"North Brabant",
    "wof:name":"T & T",
    "wof:placetype":"venue"
},
  "geometry": {"coordinates":[4.535363,51.585251],"type":"Point"}
}