{
  "type": "Feature",
  "properties": {
    "iso:country":"NL",
    "sg:address":"Weteringsngl 6",
    "sg:city":"Papendrecht",
    "sg:orig_category":"Airconditioning",
    "sg:phone":"+31 78 615 0000",
    "sg:postcode":"3353 GZ",
    "sg:province":"Zuid-Holland",
    "sg:website":"http://www.alklima.nl",
    "wof:name":"Alklima Bv",
    "wof:placetype":"venue"
},
  "geometry": {"coordinates":[4.68521,51.826385],"type":"Point"}
}