{
  "type": "Feature",
  "properties": {
    "addr:full":"Lammermarkt 9 Leiden Zuid-Holland 2312 CK",
    "addr:housenumber":"9",
    "addr:postcode":"2312 ck",
    "addr:street":"Lammermarkt",
    "iso:country":"NL",
    "sg:address":"Lammermarkt 9",
    "sg:city":"Leiden",
    "sg:orig_category":"Gespecialiseerde Voeding",
    "sg:phone":"+31 71 513 4372",
    "sg:postcode":"2312 CK",
    "sg:province":"Zuid-Holland",
    "wof:name":"Iboe Tjilik",
    "wof:placetype":"venue"
},
  "geometry": {"coordinates":[4.487175,52.163765],"type":"Point"}
}