{
  "type": "Feature",
  "properties": {
    "addr:full":"M Meustr 17 Breda North Brabant 4818 LV",
    "addr:housenumber":"17",
    "addr:postcode":"4818",
    "iso:country":"NL",
    "sg:address":"M Meustr 17",
    "sg:city":"Breda",
    "sg:orig_category":"Beeldende Kunstenaars",
    "sg:phone":"+31 76 514 6847",
    "sg:postcode":"4818 LV",
    "sg:province":"North Brabant",
    "wof:name":"Spekman, G",
    "wof:placetype":"venue"
},
  "geometry": {"coordinates":[4.779214,51.57362],"type":"Point"}
}