{
  "type": "Feature",
  "properties": {
    "addr:full":"Ouverture 4 Eindhoven North Brabant 5629 PV",
    "addr:housenumber":"4",
    "addr:postcode":"5629 pv",
    "addr:street":"Ouverture",
    "iso:country":"NL",
    "sg:address":"Ouverture 4",
    "sg:city":"Eindhoven",
    "sg:orig_category":"Kinderopvang",
    "sg:phone":"+31 40 264 5855",
    "sg:postcode":"5629 PV",
    "sg:province":"North Brabant",
    "wof:name":"Boschbeertje, 'T",
    "wof:placetype":"venue"
},
  "geometry": {"coordinates":[5.473962,51.488121],"type":"Point"}
}