{
  "type": "Feature",
  "properties": {
    "addr:full":"Ruurlosewg 1416 Vorden Gelderland 7251 LK",
    "addr:housenumber":"1416",
    "addr:postcode":"7251 lk",
    "addr:street":"Gelderland",
    "iso:country":"NL",
    "sg:address":"Ruurlosewg 1416",
    "sg:city":"Vorden",
    "sg:orig_category":"Binnenhuisarchitectuur",
    "sg:phone":"+31 575 553 515",
    "sg:postcode":"7251 LK",
    "sg:province":"Gelderland",
    "wof:name":"Kip, Willy",
    "wof:placetype":"venue"
},
  "geometry": {"coordinates":[6.39141,52.096931],"type":"Point"}
}