{
  "type": "Feature",
  "properties": {
    "addr:full":"Dennenlaan 58 Zwanenburg Noord-Holland 1161 CS",
    "addr:housenumber":"58",
    "addr:postcode":"1161 cs",
    "addr:street":"Dennenlaan",
    "iso:country":"NL",
    "sg:address":"Dennenlaan 58",
    "sg:city":"Zwanenburg",
    "sg:orig_category":"Verlichting And Huishoudartikelen",
    "sg:phone":"+31 20 497 4317",
    "sg:postcode":"1161 CS",
    "sg:province":"Noord-Holland",
    "wof:name":"Marskramer",
    "wof:placetype":"venue"
},
  "geometry": {"coordinates":[4.750975,52.378994],"type":"Point"}
}