{
  "type": "Feature",
  "properties": {
    "iso:country":"NL",
    "sg:address":"Eikenbosch 4",
    "sg:city":"Berkel-Enschot",
    "sg:orig_category":"Opticiens",
    "sg:phone":"+31 13 533 3377",
    "sg:postcode":"5056 GB",
    "sg:province":"Noord-Brabant",
    "wof:name":"Centrum Optiek",
    "wof:placetype":"venue"
},
  "geometry": {"coordinates":[5.1393289566,51.5845832825],"type":"Point"}
}