{
  "type": "Feature",
  "properties": {
    "addr:full":"Schoolstraat 19 Oldehove Groningen 9883 PG",
    "addr:housenumber":"19",
    "addr:postcode":"9883 pg",
    "addr:street":"Schoolstraat",
    "iso:country":"NL",
    "sg:address":"Schoolstraat 19",
    "sg:city":"Oldehove",
    "sg:classifiers":[
        {
            "category":"Education",
            "subcategory":"Preschool",
            "type":"Public Place"
        }
    ],
    "sg:phone":"+31 594 591 247",
    "sg:postcode":"9883 PG",
    "sg:province":"Groningen",
    "sg:tags":[
        "kleuteronderwijs",
        "basis-"
    ],
    "wof:name":"Openbare Basisschool Jan Bierma",
    "wof:placetype":"venue"
},
  "geometry": {"coordinates":[6.393063,53.30442],"type":"Point"}
}