{
  "type": "Feature",
  "properties": {
    "addr:full":"Hoepel 16 Sliedrecht South Holland 3362 JB",
    "addr:housenumber":"16",
    "addr:postcode":"3362 jb",
    "addr:street":"Hoepel",
    "iso:country":"NL",
    "sg:address":"Hoepel 16",
    "sg:city":"Sliedrecht",
    "sg:orig_category":"Boekhouders",
    "sg:phone":"+31 184 414 683",
    "sg:postcode":"3362 JB",
    "sg:province":"South Holland",
    "wof:name":"Administratiekantoor De Grienden",
    "wof:placetype":"venue"
},
  "geometry": {"coordinates":[4.794499,51.823051],"type":"Point"}
}