{
  "type": "Feature",
  "properties": {
    "iso:country":"NL",
    "sg:address":"Tuinstraat 14",
    "sg:city":"Someren",
    "sg:orig_category":"Pluimveehouderijen",
    "sg:phone":"+31 493 493 703",
    "sg:postcode":"5711 AG",
    "sg:province":"Noord-Brabant",
    "wof:name":"W.J.A. V.D. Laar",
    "wof:placetype":"venue"
},
  "geometry": {"coordinates":[5.708854,51.385818],"type":"Point"}
}