{
  "type": "Feature",
  "properties": {
    "iso:country":"NL",
    "sg:address":"Nijverheidsweg 17",
    "sg:city":"Medemblik",
    "sg:orig_category":"Pleziervaartuigen And Reparatie",
    "sg:phone":"+31 227 543 493",
    "sg:postcode":"1671 GC",
    "sg:province":"Noord-Holland",
    "wof:name":"Jachtbouw Onderhoud- En Reparatiebedrijf Dudink",
    "wof:placetype":"venue"
},
  "geometry": {"coordinates":[5.091814,52.765301],"type":"Point"}
}