{
  "type": "Feature",
  "properties": {
    "addr:full":"Wolfsberg 10 Montfort Limburg 6065 CS",
    "addr:housenumber":"10",
    "addr:postcode":"6065 cs",
    "addr:street":"Wolfsberg",
    "iso:country":"NL",
    "sg:address":"Wolfsberg 10",
    "sg:city":"Montfort",
    "sg:orig_category":"Wegen And Sportterreinen",
    "sg:phone":"+31 475 542 013",
    "sg:postcode":"6065 CS",
    "sg:province":"Limburg",
    "wof:name":"F. Peeters-Mertens",
    "wof:placetype":"venue"
},
  "geometry": {"coordinates":[5.9423527718,51.1315917969],"type":"Point"}
}