{
  "type": "Feature",
  "properties": {
    "iso:country":"NL",
    "sg:address":"Voorstr 409",
    "sg:city":"Lelystad",
    "sg:orig_category":"Artsen - Huisartsen",
    "sg:phone":"+31 320 252 993",
    "sg:postcode":"8226 KC",
    "sg:province":"Flevoland",
    "wof:name":"Munneke, R H",
    "wof:placetype":"venue"
},
  "geometry": {"coordinates":[5.493223,52.49416],"type":"Point"}
}