{
  "type": "Feature",
  "properties": {
    "iso:country":"NL",
    "sg:address":"Het Zwin 14",
    "sg:city":"Amersfoort",
    "sg:orig_category":"Onroerende Goederen",
    "sg:phone":"+31 33 455 8613",
    "sg:postcode":"3823 GT",
    "sg:province":"Utrecht",
    "wof:name":"Multi-Trade Bv",
    "wof:placetype":"venue"
},
  "geometry": {"coordinates":[5.400415,52.190514],"type":"Point"}
}