{
  "type": "Feature",
  "properties": {
    "addr:full":"Van Harenstraat 15 Wolvega Friesland 8471 JA",
    "addr:housenumber":"15",
    "addr:postcode":"8471 ja",
    "addr:street":"Van Harenstraat",
    "iso:country":"NL",
    "sg:address":"Van Harenstraat 15",
    "sg:city":"Wolvega",
    "sg:orig_category":"Schoenen",
    "sg:phone":"+31 561 612 438",
    "sg:postcode":"8471 JA",
    "sg:province":"Friesland",
    "wof:name":"Nobach Schoenen",
    "wof:placetype":"venue"
},
  "geometry": {"coordinates":[6.001106,52.876156],"type":"Point"}
}