{
  "type": "Feature",
  "properties": {
    "iso:country":"NL",
    "sg:address":"Zwarteweg 48",
    "sg:city":"Hall",
    "sg:orig_category":"Muziekinstrumenten Fab",
    "sg:phone":"+31 313 654 152",
    "sg:postcode":"6964 AE",
    "sg:province":"Montana",
    "wof:name":"P. De Koningh, Historical Music Instrume",
    "wof:placetype":"venue"
},
  "geometry": {"coordinates":[-113.196388,46.589054],"type":"Point"}
}