{
  "type": "Feature",
  "properties": {
    "addr:full":"Huis Ter Heideweg 8 Zeist Utrecht 3705 LZ",
    "addr:housenumber":"8",
    "addr:postcode":"3705 lz",
    "addr:street":"Huis Ter Heideweg",
    "iso:country":"NL",
    "sg:address":"Huis Ter Heideweg 8",
    "sg:city":"Zeist",
    "sg:orig_category":"Personenvervoer Zonder Dienstregeling",
    "sg:phone":"+31 30 692 6599",
    "sg:postcode":"3705 LZ",
    "sg:province":"Utrecht",
    "wof:name":"Midnet Tours Bolderman Reizen",
    "wof:placetype":"venue"
},
  "geometry": {"coordinates":[5.25444,52.102962],"type":"Point"}
}