{
  "type": "Feature",
  "properties": {
    "addr:full":"Ceintuurbaan N 108 Roden Drenthe 9301 NZ",
    "addr:housenumber":"108",
    "addr:postcode":"9301 nz",
    "addr:street":"Ceintuurbaan N",
    "iso:country":"NL",
    "sg:address":"Ceintuurbaan N 108",
    "sg:city":"Roden",
    "sg:orig_category":"Accountants - Administratie- Consulenten En -Kantoren",
    "sg:phone":"+31 50 501 1614",
    "sg:postcode":"9301 NZ",
    "sg:province":"Drenthe",
    "wof:name":"Diertens Accountantskantoor",
    "wof:placetype":"venue"
},
  "geometry": {"coordinates":[6.430315,53.14563],"type":"Point"}
}