{
  "type": "Feature",
  "properties": {
    "iso:country":"NL",
    "sg:address":"Mosselsepad 28",
    "sg:city":"Otterlo",
    "sg:classifiers":[
        {
            "category":"Sports & Exercise",
            "subcategory":"Stables",
            "type":"Entertainment"
        }
    ],
    "sg:phone":"+31 318 591 844",
    "sg:postcode":"6731 SM",
    "sg:province":"Gelderland",
    "sg:tags":[
        "maneges"
    ],
    "sg:website":"http://www.manegedemossel.nl",
    "wof:name":"Mossel, De",
    "wof:placetype":"venue"
},
  "geometry": {"coordinates":[5.76824,52.093422],"type":"Point"}
}