{
  "type": "Feature",
  "properties": {
    "iso:country":"NL",
    "sg:address":"Volmerlaan 12",
    "sg:city":"Rijswijk Zh",
    "sg:orig_category":"Zalenexploitatie",
    "sg:phone":"+31 70 319 4902",
    "sg:postcode":"2288 GD",
    "sg:province":"South Holland",
    "wof:name":"Darling Market",
    "wof:placetype":"venue"
},
  "geometry": {"coordinates":[4.330892,52.036205],"type":"Point"}
}