{
  "type": "Feature",
  "properties": {
    "addr:full":"Wirdumerwg 5 Loppersum Groningen 9919 HA",
    "addr:housenumber":"5",
    "addr:postcode":"9919 ha",
    "addr:street":"Wirdumerwg",
    "iso:country":"NL",
    "sg:address":"Wirdumerwg 5",
    "sg:city":"Loppersum",
    "sg:orig_category":"Verenigingsgebouwen",
    "sg:phone":"+31 596 571 674",
    "sg:postcode":"9919 HA",
    "sg:province":"Groningen",
    "wof:name":"Flits",
    "wof:placetype":"venue"
},
  "geometry": {"coordinates":[6.747441,53.332481],"type":"Point"}
}