{
  "type": "Feature",
  "properties": {
    "iso:country":"NL",
    "sg:address":"Wirdumerwg 5",
    "sg:city":"Loppersum",
    "sg:orig_category":"Verenigingsgebouwen",
    "sg:phone":"+31 596 571 674",
    "sg:postcode":"9919 HA",
    "sg:province":"Groningen",
    "wof:name":"Flits",
    "wof:placetype":"venue"
},
  "geometry": {"coordinates":[6.747441,53.332481],"type":"Point"}
}