{
  "type": "Feature",
  "properties": {
    "addr:full":"Poolsterplein 155 Rotterdam South Holland 3067 LW",
    "addr:housenumber":"155",
    "addr:postcode":"3067 lw",
    "addr:street":"Poolsterplein",
    "iso:country":"NL",
    "sg:address":"Poolsterplein 155",
    "sg:city":"Rotterdam",
    "sg:orig_category":"Banken And Kredietinstellingen",
    "sg:phone":"+31 10 289 4100",
    "sg:postcode":"3067 LW",
    "sg:province":"South Holland",
    "wof:name":"Abn Amro",
    "wof:placetype":"venue"
},
  "geometry": {"coordinates":[4.555625,51.947411],"type":"Point"}
}