{
  "type": "Feature",
  "properties": {
    "addr:full":"Damrak 31 Amsterdam North Holland 1012 LJ",
    "addr:housenumber":"31",
    "addr:postcode":"1012 lj",
    "addr:street":"Damrak",
    "iso:country":"NL",
    "sg:address":"Damrak 31",
    "sg:city":"Amsterdam",
    "sg:classifiers":[
        {
            "category":"Travel",
            "subcategory":"Hotels & Motels",
            "type":"Entertainment"
        }
    ],
    "sg:phone":"+31 20 624 0945",
    "sg:postcode":"1012 LJ",
    "sg:province":"North Holland",
    "wof:name":"Damhotel",
    "wof:placetype":"venue"
},
  "geometry": {"coordinates":[4.896576,52.376129],"type":"Point"}
}