{
  "type": "Feature",
  "properties": {
    "addr:full":"Planetenwg 80M Hoofddorp Noord-Holland 2132 HP",
    "addr:housenumber":"80m",
    "addr:postcode":"2132 hp",
    "addr:street":"Planetenwg",
    "iso:country":"NL",
    "sg:address":"Planetenwg 80M",
    "sg:city":"Hoofddorp",
    "sg:orig_category":"Adviesbureaus Bedrijfsorganisatie",
    "sg:phone":"+31 23 562 5610",
    "sg:postcode":"2132 HP",
    "sg:province":"Noord-Holland",
    "wof:name":"Gelder & Partners Bv, Van",
    "wof:placetype":"venue"
},
  "geometry": {"coordinates":[4.701675,52.296089],"type":"Point"}
}