{
  "type": "Feature",
  "properties": {
    "iso:country":"NL",
    "sg:address":"Catharinastr 42",
    "sg:city":"Meppel",
    "sg:orig_category":"Adviesbureaus Bedrijfsorganisatie",
    "sg:phone":"+31 522 246 585",
    "sg:postcode":"7941 JG",
    "sg:province":"Drenthe",
    "sg:website":"http://www.questcompany.nl",
    "wof:name":"Quest Company",
    "wof:placetype":"venue"
},
  "geometry": {"coordinates":[6.192129,52.69368],"type":"Point"}
}