{
  "type": "Feature",
  "properties": {
    "addr:full":"T Brandsmahove 8 Zoetermeer South Holland 2717 TG",
    "addr:housenumber":"8",
    "addr:postcode":"2717 tg",
    "addr:street":"T Brandsmahove",
    "iso:country":"NL",
    "sg:address":"T Brandsmahove 8",
    "sg:city":"Zoetermeer",
    "sg:orig_category":"Opticiens",
    "sg:phone":"+31 79 329 0358",
    "sg:postcode":"2717 TG",
    "sg:province":"South Holland",
    "wof:name":"Rembrandt",
    "wof:placetype":"venue"
},
  "geometry": {"coordinates":[4.4786539078,52.0654640198],"type":"Point"}
}