{
  "type": "Feature",
  "properties": {
    "addr:full":"Molenstraat 54 Zundert North Brabant 4881 CT",
    "addr:housenumber":"54",
    "addr:postcode":"4881 ct",
    "addr:street":"Molenstraat",
    "iso:country":"NL",
    "sg:address":"Molenstraat 54",
    "sg:city":"Zundert",
    "sg:orig_category":"Babyartikelen Detailhandel",
    "sg:phone":"+31 76 597 3010",
    "sg:postcode":"4881 CT",
    "sg:province":"North Brabant",
    "wof:name":"Teddy",
    "wof:placetype":"venue"
},
  "geometry": {"coordinates":[4.662049,51.470875],"type":"Point"}
}