{
  "type": "Feature",
  "properties": {
    "addr:full":"L Wateringkd 14 Kwintsheul Zuid-Holland 2295 RM",
    "addr:housenumber":"14",
    "addr:postcode":"2295 rm",
    "iso:country":"NL",
    "sg:address":"L Wateringkd 14",
    "sg:city":"Kwintsheul",
    "sg:orig_category":"Autoreclame",
    "sg:phone":"+31 174 294 494",
    "sg:postcode":"2295 RM",
    "sg:province":"Zuid-Holland",
    "wof:name":"Zuijderwijk, Jac",
    "wof:placetype":"venue"
},
  "geometry": {"coordinates":[4.257781,52.015083],"type":"Point"}
}