{
  "type": "Feature",
  "properties": {
    "iso:country":"NL",
    "sg:address":"Tinweg 3",
    "sg:city":"Wolvega",
    "sg:orig_category":"Grafische Bedrijven",
    "sg:phone":"+31 561 614 523",
    "sg:postcode":"8471 XK",
    "sg:province":"Provincie Friesland",
    "wof:name":"Prepressmediapartners Bv",
    "wof:placetype":"venue"
},
  "geometry": {"coordinates":[5.986969,52.883259],"type":"Point"}
}