{
  "type": "Feature",
  "properties": {
    "iso:country":"NL",
    "sg:address":"Marksngl 40",
    "sg:city":"Breda",
    "sg:orig_category":"Wasserijen",
    "sg:phone":"+31 76 522 5303",
    "sg:postcode":"4811 NW",
    "sg:province":"North Rhine-Westphalia",
    "wof:name":"Rentex Fortex",
    "wof:placetype":"venue"
},
  "geometry": {"coordinates":[8.8929796219,52.0710296631],"type":"Point"}
}