{
  "type": "Feature",
  "properties": {
    "iso:country":"NL",
    "sg:address":"Heuvelwg 8",
    "sg:city":"Heerlen",
    "sg:orig_category":"Kunsthandel",
    "sg:phone":"+31 45 572 4907",
    "sg:postcode":"6415 XX",
    "sg:province":"Limburg",
    "wof:name":"Kleine Kunsthandel, De",
    "wof:placetype":"venue"
},
  "geometry": {"coordinates":[5.985259,50.890549],"type":"Point"}
}