{
  "type": "Feature",
  "properties": {
    "addr:full":"Saasvelderlaan 62 Oldenzaal NL.08 7576 EE",
    "addr:housenumber":"62;nl.08",
    "addr:postcode":"7576 ee",
    "addr:street":"Saasvelderlaan",
    "iso:country":"NL",
    "sg:address":"Saasvelderlaan 62",
    "sg:city":"Oldenzaal",
    "sg:orig_category":"Chemische Producten Gh",
    "sg:phone":"+31 541 511 796",
    "sg:postcode":"7576 EE",
    "sg:province":"NL.08",
    "wof:name":"Ha-Ra",
    "wof:placetype":"venue"
},
  "geometry": {"coordinates":[6.896008,52.31554],"type":"Point"}
}