{
  "type": "Feature",
  "properties": {
    "addr:full":"Grt Visserystr 84 Rotterdam South Holland 3026 CM",
    "addr:housenumber":"84",
    "addr:postcode":"3026 cm",
    "iso:country":"NL",
    "sg:address":"Grt Visserystr 84",
    "sg:city":"Rotterdam",
    "sg:orig_category":"Behangselpapier En Wandbekleding",
    "sg:phone":"+31 10 476 1555",
    "sg:postcode":"3026 CM",
    "sg:province":"South Holland",
    "wof:name":"Alper",
    "wof:placetype":"venue"
},
  "geometry": {"coordinates":[4.441784,51.913692],"type":"Point"}
}