{
  "type": "Feature",
  "properties": {
    "addr:full":"Koopmansgracht 30 Sneek Friesland 8606 AB",
    "addr:housenumber":"30",
    "addr:postcode":"8606 ab",
    "addr:street":"Koopmansgracht",
    "iso:country":"NL",
    "sg:address":"Koopmansgracht 30",
    "sg:city":"Sneek",
    "sg:orig_category":"Bouwmaterialen Gh",
    "sg:phone":"+31 515 423 810",
    "sg:postcode":"8606 AB",
    "sg:province":"Friesland",
    "wof:name":"H.B. Jongejans",
    "wof:placetype":"venue"
},
  "geometry": {"coordinates":[5.66284,53.0294],"type":"Point"}
}