{
  "type": "Feature",
  "properties": {
    "addr:full":"Meeuwenhoek 21 Monnickendam Noord-Holland 1141 DV",
    "addr:housenumber":"21",
    "addr:postcode":"1141 dv",
    "addr:street":"Meeuwenhoek",
    "iso:country":"NL",
    "sg:address":"Meeuwenhoek 21",
    "sg:city":"Monnickendam",
    "sg:orig_category":"Webdesign Bureaus",
    "sg:phone":"+31 299 655 092",
    "sg:postcode":"1141 DV",
    "sg:province":"Noord-Holland",
    "sg:website":"http://www.close29er.com",
    "wof:name":"Close29Er",
    "wof:placetype":"venue"
},
  "geometry": {"coordinates":[5.0393810272,52.4492454529],"type":"Point"}
}