{
  "type": "Feature",
  "properties": {
    "addr:full":"Havenstr 48 Vlaardingen Zuid-Holland 3131 BD",
    "addr:housenumber":"48",
    "addr:postcode":"3131 bd",
    "addr:street":"Havenstr",
    "iso:country":"NL",
    "sg:address":"Havenstr 48",
    "sg:city":"Vlaardingen",
    "sg:orig_category":"Beeldende Kunstenaars",
    "sg:phone":"+31 10 234 3774",
    "sg:postcode":"3131 BD",
    "sg:province":"Zuid-Holland",
    "wof:name":"Hagen, Ineke",
    "wof:placetype":"venue"
},
  "geometry": {"coordinates":[4.344265,51.911736],"type":"Point"}
}