{
  "type": "Feature",
  "properties": {
    "addr:full":"L Zylpln 7 Amsterdam Noord-Holland 1067 JR",
    "addr:housenumber":"7",
    "addr:postcode":"1067 jr",
    "iso:country":"NL",
    "sg:address":"L Zylpln 7",
    "sg:city":"Amsterdam",
    "sg:orig_category":"Woninginrichting",
    "sg:phone":"+31 20 613 1921",
    "sg:postcode":"1067 JR",
    "sg:province":"Noord-Holland",
    "wof:name":"Interdecor",
    "wof:placetype":"venue"
},
  "geometry": {"coordinates":[4.7835302353,52.3677215576],"type":"Point"}
}