{
  "type": "Feature",
  "properties": {
    "addr:full":"Heer Danielstr 53 Rotterdam Zuid-Holland 3073 DC",
    "addr:housenumber":"53",
    "addr:postcode":"3073",
    "addr:street":"Heer Danielstr",
    "iso:country":"NL",
    "sg:address":"Heer Danielstr 53",
    "sg:city":"Rotterdam",
    "sg:orig_category":"Kinderopvang",
    "sg:phone":"+31 10 290 0006",
    "sg:postcode":"3073 DC",
    "sg:province":"Zuid-Holland",
    "wof:name":"Pino",
    "wof:placetype":"venue"
},
  "geometry": {"coordinates":[4.503074,51.890247],"type":"Point"}
}