{
  "type": "Feature",
  "properties": {
    "addr:full":"Randweg 1 Someren North Brabant 5711 DJ",
    "addr:housenumber":"1",
    "addr:postcode":"5711 dj",
    "addr:street":"Randweg",
    "iso:country":"NL",
    "sg:address":"Randweg 1",
    "sg:city":"Someren",
    "sg:orig_category":"Drukkerijen And Copyshops",
    "sg:phone":"+31 493 441 441",
    "sg:postcode":"5711 DJ",
    "sg:province":"North Brabant",
    "wof:name":"Drukkerij Haerkens Someren Bv",
    "wof:placetype":"venue"
},
  "geometry": {"coordinates":[5.723793,51.389465],"type":"Point"}
}