{
  "type": "Feature",
  "properties": {
    "addr:full":"Emmawg 24C Kortenhoef Noord-Holland 1241 LG",
    "addr:housenumber":"24c",
    "addr:postcode":"1241 lg",
    "addr:street":"Emmawg",
    "iso:country":"NL",
    "sg:address":"Emmawg 24C",
    "sg:city":"Kortenhoef",
    "sg:orig_category":"Adviesbureaus Bouwkunde",
    "sg:phone":"+31 35 656 5111",
    "sg:postcode":"1241 LG",
    "sg:province":"Noord-Holland",
    "sg:website":"http://www.teduits.nl",
    "wof:name":"Duits Bv, Buro Te",
    "wof:placetype":"venue"
},
  "geometry": {"coordinates":[5.121064,52.235573],"type":"Point"}
}