{
  "type": "Feature",
  "properties": {
    "addr:full":"Kastanjeplein 188 Amsterdam Noord-Holland 1092 LC",
    "addr:housenumber":"188",
    "addr:postcode":"1092 lc",
    "addr:street":"Kastanjeplein",
    "iso:country":"NL",
    "sg:address":"Kastanjeplein 188",
    "sg:city":"Amsterdam",
    "sg:orig_category":"Muziekinstrumenten",
    "sg:phone":"+31 20 665 8035",
    "sg:postcode":"1092 LC",
    "sg:province":"Noord-Holland",
    "wof:name":"F.C.M. Wouda",
    "wof:placetype":"venue"
},
  "geometry": {"coordinates":[4.923623,52.358322],"type":"Point"}
}