{
  "type": "Feature",
  "properties": {
    "addr:full":"Kerkstr 12-14 Beesel Limburg 5954 BC",
    "addr:housenumber":"12-14",
    "addr:postcode":"5954 bc",
    "iso:country":"NL",
    "sg:address":"Kerkstr 12-14",
    "sg:city":"Beesel",
    "sg:orig_category":"Scholen Voor Basisonderwijs",
    "sg:phone":"+31 77 474 3057",
    "sg:postcode":"5954 BC",
    "sg:province":"Limburg",
    "wof:name":"Spick Rk, Het",
    "wof:placetype":"venue"
},
  "geometry": {"coordinates":[6.036489,51.26823],"type":"Point"}
}