{
  "type": "Feature",
  "properties": {
    "addr:full":"Provincienbaan 21 Ryen North Brabant 5121 DK",
    "addr:housenumber":"21",
    "addr:postcode":"5121 dk",
    "addr:street":"Provincienbaan",
    "iso:country":"NL",
    "sg:address":"Provincienbaan 21",
    "sg:city":"Ryen",
    "sg:orig_category":"Kunststoffen - Fabrieken En Groothandel",
    "sg:phone":"+31 161 222 330",
    "sg:postcode":"5121 DK",
    "sg:province":"North Brabant",
    "wof:name":"Plasti-Ned Bv",
    "wof:placetype":"venue"
},
  "geometry": {"coordinates":[4.9197,51.588017],"type":"Point"}
}