{
  "type": "Feature",
  "properties": {
    "addr:full":"Parkwg 29 Groningen Groningen 9725 EB",
    "addr:housenumber":"29",
    "addr:postcode":"9725 eb",
    "addr:street":"Parkwg",
    "iso:country":"NL",
    "sg:address":"Parkwg 29",
    "sg:city":"Groningen",
    "sg:orig_category":"Artiesten/Gezelschappen",
    "sg:phone":"+31 50 526 1465",
    "sg:postcode":"9725 EB",
    "sg:province":"Groningen",
    "sg:website":"http://www.samiera.nl",
    "wof:name":"Samiera Buikdanseres-Fakir",
    "wof:placetype":"venue"
},
  "geometry": {"coordinates":[6.566296,53.208633],"type":"Point"}
}