{
  "type": "Feature",
  "properties": {
    "addr:full":"Venrayseweg 214 Venlo Limburg 5928 RJ",
    "addr:housenumber":"214",
    "addr:postcode":"5928 rj",
    "addr:street":"Venrayseweg",
    "iso:country":"NL",
    "sg:address":"Venrayseweg 214",
    "sg:city":"Venlo",
    "sg:orig_category":"Bloemen En Planten",
    "sg:phone":"+31 77 387 2874",
    "sg:postcode":"5928 RJ",
    "sg:province":"Limburg",
    "wof:name":"Geer Vof, J Van Der",
    "wof:placetype":"venue"
},
  "geometry": {"coordinates":[6.152396,51.376213],"type":"Point"}
}