{
  "type": "Feature",
  "properties": {
    "addr:full":"Versterstraat 12 Gilze Noord-Brabant 5126 BT",
    "addr:housenumber":"12",
    "addr:postcode":"5126 bt",
    "addr:street":"Versterstraat",
    "iso:country":"NL",
    "sg:address":"Versterstraat 12",
    "sg:city":"Gilze",
    "sg:orig_category":"Bloemen- And Plantenteelt",
    "sg:phone":"+31 161 451 278",
    "sg:postcode":"5126 BT",
    "sg:province":"Noord-Brabant",
    "wof:name":"Bloemenkwekerij Jos Oprins",
    "wof:placetype":"venue"
},
  "geometry": {"coordinates":[4.936166,51.537991],"type":"Point"}
}