{
  "type": "Feature",
  "properties": {
    "addr:full":"C Trooststr 17 Amsterdam North Holland 1072 JA",
    "addr:housenumber":"17",
    "addr:postcode":"1072 ja",
    "iso:country":"NL",
    "sg:address":"C Trooststr 17",
    "sg:city":"Amsterdam",
    "sg:orig_category":"Woningbureaus",
    "sg:phone":"+31 20 685 3308",
    "sg:postcode":"1072 JA",
    "sg:province":"North Holland",
    "wof:name":"Corporate Apartments",
    "wof:placetype":"venue"
},
  "geometry": {"coordinates":[4.8870692253,52.3505363464],"type":"Point"}
}