{
  "type": "Feature",
  "properties": {
    "addr:full":"Dr Poelsstr 3 Weert Limburg 6006 ZD",
    "addr:housenumber":"3",
    "addr:postcode":"6006 zd",
    "addr:street":"Weert Limburg",
    "iso:country":"NL",
    "sg:address":"Dr Poelsstr 3",
    "sg:city":"Weert",
    "sg:orig_category":"Drukkerijen",
    "sg:phone":"+31 495 453 300",
    "sg:postcode":"6006 ZD",
    "sg:province":"Limburg",
    "wof:name":"Peter Printservice",
    "wof:placetype":"venue"
},
  "geometry": {"coordinates":[5.702904,51.241241],"type":"Point"}
}