{
  "type": "Feature",
  "properties": {
    "addr:full":"T Inne 1 Budel Noord-Brabant 6021 DA",
    "addr:housenumber":"1",
    "addr:postcode":"6021 da",
    "addr:street":"T Inne",
    "iso:country":"NL",
    "sg:address":"T Inne 1",
    "sg:city":"Budel",
    "sg:orig_category":"Schilders",
    "sg:phone":"+31 495 493 603",
    "sg:postcode":"6021 DA",
    "sg:province":"Noord-Brabant",
    "wof:name":"Budel Bv",
    "wof:placetype":"venue"
},
  "geometry": {"coordinates":[5.582511,51.267879],"type":"Point"}
}