{
  "type": "Feature",
  "properties": {
    "addr:full":"Rokin 124 Amsterdam Noord-Holland 1012 LC",
    "addr:housenumber":"124",
    "addr:postcode":"1012 lc",
    "addr:street":"Rokin",
    "iso:country":"NL",
    "sg:address":"Rokin 124",
    "sg:city":"Amsterdam",
    "sg:orig_category":"Glas, Porselein En Aardewerk",
    "sg:phone":"+31 20 638 2736",
    "sg:postcode":"1012 LC",
    "sg:province":"Noord-Holland",
    "sg:website":"http://www.hogendoorn-kaufman.com",
    "wof:name":"Hogendoorn & Kaufman",
    "wof:placetype":"venue"
},
  "geometry": {"coordinates":[4.891938,52.368595],"type":"Point"}
}