{
  "type": "Feature",
  "properties": {
    "addr:full":"Mr V Coothstr 33 Waalwyk North Brabant 5141 EP",
    "addr:housenumber":"33",
    "addr:postcode":"5141 ep",
    "addr:street":"Coothstr",
    "iso:country":"NL",
    "sg:address":"Mr V Coothstr 33",
    "sg:city":"Waalwyk",
    "sg:orig_category":"Banken",
    "sg:phone":"+31 416 672 111",
    "sg:postcode":"5141 EP",
    "sg:province":"North Brabant",
    "wof:name":"Lanschot Nv, F Van",
    "wof:placetype":"venue"
},
  "geometry": {"coordinates":[5.062876,51.689789],"type":"Point"}
}