{
  "type": "Feature",
  "properties": {
    "addr:full":"B De Haanwg 20 Rotterdam Zuid-Holland 3076 DC",
    "addr:housenumber":"20",
    "addr:postcode":"3076",
    "addr:street":"B",
    "iso:country":"NL",
    "sg:address":"B De Haanwg 20",
    "sg:city":"Rotterdam",
    "sg:orig_category":"Kappers",
    "sg:phone":"+31 10 419 6506",
    "sg:postcode":"3076 DC",
    "sg:province":"Zuid-Holland",
    "wof:name":"Tates, J",
    "wof:placetype":"venue"
},
  "geometry": {"coordinates":[4.517168,51.878029],"type":"Point"}
}