{
  "type": "Feature",
  "properties": {
    "addr:full":"Vossenburchstraat 12 Voorburg Zuid-Holland 2271 VV",
    "addr:housenumber":"12",
    "addr:postcode":"2271 vv",
    "addr:street":"Vossenburchstraat",
    "iso:country":"NL",
    "sg:address":"Vossenburchstraat 12",
    "sg:city":"Voorburg",
    "sg:orig_category":"Schilderwerk",
    "sg:phone":"+31 70 386 4569",
    "sg:postcode":"2271 VV",
    "sg:province":"Zuid-Holland",
    "wof:name":"R Reitsma",
    "wof:placetype":"venue"
},
  "geometry": {"coordinates":[4.361969,52.071251],"type":"Point"}
}