{
  "type": "Feature",
  "properties": {
    "addr:full":"Pleinstraat 23 B Bergambacht Zuid-Holland 2861 XG",
    "addr:housenumber":"23 b",
    "addr:postcode":"2861 xg",
    "addr:street":"Pleinstraat",
    "iso:country":"NL",
    "sg:address":"Pleinstraat 23 B",
    "sg:city":"Bergambacht",
    "sg:orig_category":"Architecten",
    "sg:phone":"+31 182 352 888",
    "sg:postcode":"2861 XG",
    "sg:province":"Zuid-Holland",
    "wof:name":"Interbouw",
    "wof:placetype":"venue"
},
  "geometry": {"coordinates":[4.786804,51.935154],"type":"Point"}
}