{
  "type": "Feature",
  "properties": {
    "addr:full":"Aalscholverln 40 Zeist Utrecht 3704 HN",
    "addr:housenumber":"40",
    "addr:postcode":"3704 hn",
    "addr:street":"Aalscholverln",
    "iso:country":"NL",
    "sg:address":"Aalscholverln 40",
    "sg:city":"Zeist",
    "sg:orig_category":"Automaterialen En Gereedschappen",
    "sg:phone":"+31 30 695 0970",
    "sg:postcode":"3704 HN",
    "sg:province":"Utrecht",
    "wof:name":"Prima Parts",
    "wof:placetype":"venue"
},
  "geometry": {"coordinates":[5.24387,52.08548],"type":"Point"}
}