{
  "type": "Feature",
  "properties": {
    "iso:country":"NL",
    "sg:address":"Zandheuvel 1",
    "sg:city":"Oosterhout Nb",
    "sg:orig_category":"Diverse Grafische Activiteiten",
    "sg:phone":"+31 162 436 583",
    "sg:postcode":"4901 HT",
    "sg:province":"North Brabant",
    "wof:name":"Cees Veldhoen Lithografie Drukwerkverzor",
    "wof:placetype":"venue"
},
  "geometry": {"coordinates":[4.865133,51.642666],"type":"Point"}
}