{
  "type": "Feature",
  "properties": {
    "addr:full":"T Leantsje 20 Hemelum Friesland 8584 VH",
    "addr:housenumber":"20",
    "addr:postcode":"8584 vh",
    "addr:street":"T Leantsje",
    "iso:country":"NL",
    "sg:address":"T Leantsje 20",
    "sg:city":"Hemelum",
    "sg:orig_category":"Bedrijfs- And Managementsconsultants",
    "sg:phone":"+31 514 581 691",
    "sg:postcode":"8584 VH",
    "sg:province":"Friesland",
    "wof:name":"Penning & Partners Bv",
    "wof:placetype":"venue"
},
  "geometry": {"coordinates":[5.457603,52.882484],"type":"Point"}
}