{
  "type": "Feature",
  "properties": {
    "iso:country":"NL",
    "sg:address":"Ringdijk 4",
    "sg:city":"De Kwakel",
    "sg:orig_category":"Bloemen And Planten",
    "sg:phone":"+31 297 565 563",
    "sg:postcode":"1424 AW",
    "sg:province":"North Holland",
    "wof:name":"Firma Gebrs. Buskermolen",
    "wof:placetype":"venue"
},
  "geometry": {"coordinates":[4.792063,52.241081],"type":"Point"}
}