{
  "type": "Feature",
  "properties": {
    "addr:full":"Rustenburgerstr 10 Amsterdam North Holland 1074 ET",
    "addr:housenumber":"10",
    "addr:postcode":"1074 et",
    "addr:street":"Rustenburgerstr",
    "iso:country":"NL",
    "sg:address":"Rustenburgerstr 10",
    "sg:city":"Amsterdam",
    "sg:orig_category":"Offsetdrukkerijen",
    "sg:phone":"+31 20 610 3808",
    "sg:postcode":"1074 ET",
    "sg:province":"North Holland",
    "wof:name":"Babeliowsky & Zn, J",
    "wof:placetype":"venue"
},
  "geometry": {"coordinates":[4.90588,52.354141],"type":"Point"}
}