{
  "type": "Feature",
  "properties": {
    "iso:country":"NL",
    "sg:address":"Sweelinckstraat 11",
    "sg:city":"Eerbeek",
    "sg:classifiers":[
        {
            "category":"Education",
            "subcategory":"Preschool",
            "type":"Public Place"
        }
    ],
    "sg:phone":"+31 313 651 451",
    "sg:postcode":"6961 BH",
    "sg:province":"Gelderland",
    "sg:tags":[
        "kleuteronderwijs",
        "basis-"
    ],
    "wof:name":"Openbare Basisschool Corn. Jetses",
    "wof:placetype":"venue"
},
  "geometry": {"coordinates":[6.054751,52.107468],"type":"Point"}
}