{
  "type": "Feature",
  "properties": {
    "iso:country":"NL",
    "sg:address":"Lindelauf Gewande 9A",
    "sg:city":"Voerendaal",
    "sg:orig_category":"Touringcars",
    "sg:phone":"+31 45 575 3636",
    "sg:postcode":"6367 AZ",
    "sg:province":"Limburg",
    "sg:website":"http://www.lindetours.nl",
    "wof:name":"Linde Tours",
    "wof:placetype":"venue"
},
  "geometry": {"coordinates":[5.922598,50.874863],"type":"Point"}
}