{
  "type": "Feature",
  "properties": {
    "addr:full":"Zeestr 100 Zevenbergen Noord-Brabant 4761 HN",
    "addr:housenumber":"100",
    "addr:postcode":"4761 hn",
    "addr:street":"Zevenbergen",
    "iso:country":"NL",
    "sg:address":"Zeestr 100",
    "sg:city":"Zevenbergen",
    "sg:orig_category":"Administratie- En Boekhoudkantoren",
    "sg:phone":"+31 168 327 600",
    "sg:postcode":"4761 HN",
    "sg:province":"Noord-Brabant",
    "wof:name":"Huijgen, Administratieburo W",
    "wof:placetype":"venue"
},
  "geometry": {"coordinates":[4.59894,51.651031],"type":"Point"}
}