{
  "type": "Feature",
  "properties": {
    "addr:full":"W Beukelsstr 35 Amsterdam Noord-Holland 1097 CR",
    "addr:housenumber":"35;1097",
    "addr:postcode":"cr",
    "addr:street":"W",
    "iso:country":"NL",
    "sg:address":"W Beukelsstr 35",
    "sg:city":"Amsterdam",
    "sg:orig_category":"New Age-Artikelen En -Diensten",
    "sg:phone":"+31 20 468 1354",
    "sg:postcode":"1097 CR",
    "sg:province":"Noord-Holland",
    "wof:name":"Amethist Pers",
    "wof:placetype":"venue"
},
  "geometry": {"coordinates":[4.926865,52.352917],"type":"Point"}
}