{
  "type": "Feature",
  "properties": {
    "addr:full":"Lindenlaan 145 Amstelveen Noord-Holland 1185 LG",
    "addr:housenumber":"145",
    "addr:postcode":"1185 lg",
    "addr:street":"Lindenlaan",
    "iso:country":"NL",
    "sg:address":"Lindenlaan 145",
    "sg:city":"Amstelveen",
    "sg:orig_category":"Verlichting And Huishoudartikelen",
    "sg:phone":"+31 20 441 6133",
    "sg:postcode":"1185 LG",
    "sg:province":"Noord-Holland",
    "wof:name":"Al Forno Kookaccessoires",
    "wof:placetype":"venue"
},
  "geometry": {"coordinates":[4.85422,52.293098],"type":"Point"}
}