{
  "type": "Feature",
  "properties": {
    "addr:full":"Kanaalstraat 22 Leiden Zuid-Holland 2313 NS",
    "addr:housenumber":"22",
    "addr:postcode":"2313 ns",
    "addr:street":"Kanaalstraat",
    "iso:country":"NL",
    "sg:address":"Kanaalstraat 22",
    "sg:city":"Leiden",
    "sg:orig_category":"Geluidsinstallaties - Verhuur",
    "sg:phone":"+31 71 522 5772",
    "sg:postcode":"2313 NS",
    "sg:province":"Zuid-Holland",
    "wof:name":"Farley Gene",
    "wof:placetype":"venue"
},
  "geometry": {"coordinates":[4.510685,52.153763],"type":"Point"}
}