{
  "type": "Feature",
  "properties": {
    "addr:full":"Kerstendk 5 Rotterdam Zuid-Holland 3079 ET",
    "addr:housenumber":"5",
    "addr:postcode":"3079 et",
    "addr:street":"Kerstendk",
    "iso:country":"NL",
    "sg:address":"Kerstendk 5",
    "sg:city":"Rotterdam",
    "sg:orig_category":"Postkantoren",
    "sg:phone":"+31 10 483 0936",
    "sg:postcode":"3079 ET",
    "sg:province":"Zuid-Holland",
    "sg:website":"http://www.postkantoor.nl",
    "wof:name":"Postkantoor",
    "wof:placetype":"venue"
},
  "geometry": {"coordinates":[4.543703,51.881393],"type":"Point"}
}