{
  "type": "Feature",
  "properties": {
    "addr:full":"Gravestein 810 Amsterdam Zuidoost Noord-Holland 1103 BH",
    "addr:housenumber":"810",
    "addr:postcode":"zuidoost;1103 bh",
    "addr:street":"Gravestein",
    "iso:country":"NL",
    "sg:address":"Gravestein 810",
    "sg:city":"Amsterdam Zuidoost",
    "sg:orig_category":"Wasserijen",
    "sg:phone":"+31 20 695 9226",
    "sg:postcode":"1103 BH",
    "sg:province":"Noord-Holland",
    "wof:name":"A1",
    "wof:placetype":"venue"
},
  "geometry": {"coordinates":[4.9686398506,52.3248405457],"type":"Point"}
}