{
  "type": "Feature",
  "properties": {
    "addr:full":"Van Lennepweg 2/F001 Zandvoort Noord-Holland 2041 LG",
    "addr:housenumber":"2 / f001 zandvoort",
    "addr:postcode":"2041 lg",
    "addr:street":"Van Lennepweg",
    "iso:country":"NL",
    "sg:address":"Van Lennepweg 2/F001",
    "sg:city":"Zandvoort",
    "sg:orig_category":"Kantoor- And Schoolbenodigdheden Gh",
    "sg:phone":"+31 23 571 7207",
    "sg:postcode":"2041 LG",
    "sg:province":"Noord-Holland",
    "wof:name":"E. Markhof",
    "wof:placetype":"venue"
},
  "geometry": {"coordinates":[4.5272898674,52.3707466125],"type":"Point"}
}