{
  "type": "Feature",
  "properties": {
    "addr:full":"Erasstr 32 Kaatsheuvel North Brabant 5171 VH",
    "addr:housenumber":"32",
    "addr:postcode":"5171 vh",
    "addr:street":"Erasstr",
    "iso:country":"NL",
    "sg:address":"Erasstr 32",
    "sg:city":"Kaatsheuvel",
    "sg:orig_category":"Veiligheidsuitrusting En -Kleding",
    "sg:phone":"+31 416 275 304",
    "sg:postcode":"5171 VH",
    "sg:province":"North Brabant",
    "wof:name":"Kemmeren, F G C",
    "wof:placetype":"venue"
},
  "geometry": {"coordinates":[5.011102,51.656132],"type":"Point"}
}