{
  "type": "Feature",
  "properties": {
    "addr:full":"Overdiemerwg 2 Diemen North Holland 1111 PN",
    "addr:housenumber":"2",
    "addr:postcode":"1111 pn",
    "addr:street":"Overdiemerwg",
    "iso:country":"NL",
    "sg:address":"Overdiemerwg 2",
    "sg:city":"Diemen",
    "sg:orig_category":"Jachthavens - Jachtwerven",
    "sg:phone":"+31 20 699 4078",
    "sg:postcode":"1111 PN",
    "sg:province":"North Holland",
    "wof:name":"Grote Zomer, De",
    "wof:placetype":"venue"
},
  "geometry": {"coordinates":[4.982539,52.336777],"type":"Point"}
}