{
  "type": "Feature",
  "properties": {
    "addr:full":"Beethovensingel 3 Alkmaar Noord-Holland 1817 HJ",
    "addr:housenumber":"3",
    "addr:postcode":"1817 hj",
    "addr:street":"Beethovensingel",
    "iso:country":"NL",
    "sg:address":"Beethovensingel 3",
    "sg:city":"Alkmaar",
    "sg:orig_category":"Kinderopvang Behalve Thuis",
    "sg:phone":"+31 72 515 4090",
    "sg:postcode":"1817 HJ",
    "sg:province":"Noord-Holland",
    "wof:name":"Kinderdagverblijf Rapsodie",
    "wof:placetype":"venue"
},
  "geometry": {"coordinates":[4.734544,52.640152],"type":"Point"}
}