{
  "type": "Feature",
  "properties": {
    "addr:full":"Marktstraat 44 Made Noord-Brabant 4921 BG",
    "addr:housenumber":"44",
    "addr:postcode":"4921",
    "addr:street":"Marktstraat",
    "iso:country":"NL",
    "sg:address":"Marktstraat 44",
    "sg:city":"Made",
    "sg:orig_category":"Fotostudio'S And Fotografen",
    "sg:phone":"+31 162 686 098",
    "sg:postcode":"4921 BG",
    "sg:province":"Noord-Brabant",
    "wof:name":"Fotografie Anneke Moerenhout",
    "wof:placetype":"venue"
},
  "geometry": {"coordinates":[24.972,41.56765],"type":"Point"}
}