{
  "type": "Feature",
  "properties": {
    "addr:full":"P Cornelisz Hooftstr 20 Amsterdam North Holland 1071 BX",
    "addr:housenumber":"20",
    "addr:postcode":"1071 bx",
    "addr:street":"P Cornelisz Hooftstr",
    "iso:country":"NL",
    "sg:address":"P Cornelisz Hooftstr 20",
    "sg:city":"Amsterdam",
    "sg:classifiers":[
        {
            "category":"Professional",
            "subcategory":"Accounting & Tax Preparation",
            "type":"Services"
        }
    ],
    "sg:phone":"+31 20 675 7567",
    "sg:postcode":"1071 BX",
    "sg:province":"North Holland",
    "sg:tags":[
        "accountant"
    ],
    "wof:name":"Accountantskantoor Blok & Van De Boogaard",
    "wof:placetype":"venue"
},
  "geometry": {"coordinates":[4.883344,52.361107],"type":"Point"}
}