{
  "type": "Feature",
  "properties": {
    "addr:full":"Park 32 Nuenen North Brabant 5671 GA",
    "addr:housenumber":"32",
    "addr:postcode":"5671 ga",
    "addr:street":"Park",
    "iso:country":"NL",
    "sg:address":"Park 32",
    "sg:city":"Nuenen",
    "sg:orig_category":"Makelaars En Adviseurs Onroerende Goederen",
    "sg:phone":"+31 40 290 7000",
    "sg:postcode":"5671 GA",
    "sg:province":"North Brabant",
    "wof:name":"Lommers & P Van Den Buijs, Rob",
    "wof:placetype":"venue"
},
  "geometry": {"coordinates":[5.548977,51.474831],"type":"Point"}
}