{
  "type": "Feature",
  "properties": {
    "addr:full":"Noordeinde 150B Waddinxveen Zuid-Holland 2742 WH",
    "addr:housenumber":"150b",
    "addr:postcode":"2742 wh",
    "addr:street":"Noordeinde",
    "iso:country":"NL",
    "sg:address":"Noordeinde 150B",
    "sg:city":"Waddinxveen",
    "sg:orig_category":"Diverse Dierenfokkers",
    "sg:phone":"+31 172 217 077",
    "sg:postcode":"2742 WH",
    "sg:province":"Zuid-Holland",
    "wof:name":"A. De Jong",
    "wof:placetype":"venue"
},
  "geometry": {"coordinates":[4.626476,52.064865],"type":"Point"}
}