{
  "type": "Feature",
  "properties": {
    "addr:full":"Linkensweg 64 Oss Noord-Brabant 5341 CC",
    "addr:housenumber":"64",
    "addr:postcode":"5341 cc",
    "addr:street":"Linkensweg",
    "iso:country":"NL",
    "sg:address":"Linkensweg 64",
    "sg:city":"Oss",
    "sg:orig_category":"Huishoudapparatuur, Televisies And Radio'S",
    "sg:phone":"+31 412 624 243",
    "sg:postcode":"5341 CC",
    "sg:province":"Noord-Brabant",
    "wof:name":"Elektron",
    "wof:placetype":"venue"
},
  "geometry": {"coordinates":[-77.235214,38.312599],"type":"Point"}
}