{
  "type": "Feature",
  "properties": {
    "iso:country":"NL",
    "sg:address":"De Loper 63",
    "sg:city":"Vlaardingen",
    "sg:orig_category":"Kinderkleding",
    "sg:phone":"+31 10 249 9325",
    "sg:postcode":"3137 DD",
    "sg:province":"Zuid-Holland",
    "sg:website":"http://www.isazoe.nl",
    "wof:name":"Isazoe Kids",
    "wof:placetype":"venue"
},
  "geometry": {"coordinates":[4.346311,51.931122],"type":"Point"}
}