{
  "type": "Feature",
  "properties": {
    "iso:country":"NL",
    "sg:address":"Voltastr 47",
    "sg:city":"Purmerend",
    "sg:orig_category":"Sanitaire Artikelen",
    "sg:phone":"+31 299 461 668",
    "sg:postcode":"1446 VB",
    "sg:province":"Noord-Holland",
    "wof:name":"Hendriks Bv, Gebr",
    "wof:placetype":"venue"
},
  "geometry": {"coordinates":[5.002216,52.514618],"type":"Point"}
}