{
  "type": "Feature",
  "properties": {
    "addr:full":"Nicolaas Maesstraat 7 Ede Gld Gelderland 6717 ST",
    "addr:housenumber":"7;6717",
    "addr:street":"Nicolaas Maesstraat;Gld Gelderland",
    "iso:country":"NL",
    "sg:address":"Nicolaas Maesstraat 7",
    "sg:city":"Ede Gld",
    "sg:classifiers":[
        {
            "category":"Education",
            "subcategory":"Preschool",
            "type":"Public Place"
        }
    ],
    "sg:phone":"+31 318 636 179",
    "sg:postcode":"6717 ST",
    "sg:province":"Gelderland",
    "sg:tags":[
        "kleuteronderwijs",
        "basis-"
    ],
    "wof:name":"Openbare Basisschool De Elskamp",
    "wof:placetype":"venue"
},
  "geometry": {"coordinates":[5.653748,52.017776],"type":"Point"}
}