{
  "type": "Feature",
  "properties": {
    "addr:full":"Biesboschstr 81 Amsterdam Noord-Holland 1078 MR",
    "addr:housenumber":"81",
    "addr:postcode":"1078 mr",
    "addr:street":"Biesboschstr",
    "iso:country":"NL",
    "sg:address":"Biesboschstr 81",
    "sg:city":"Amsterdam",
    "sg:orig_category":"Verlichting",
    "sg:phone":"+31 20 671 2800",
    "sg:postcode":"1078 MR",
    "sg:province":"Noord-Holland",
    "wof:name":"Rapido Lights",
    "wof:placetype":"venue"
},
  "geometry": {"coordinates":[4.896424,52.344894],"type":"Point"}
}