{
  "type": "Feature",
  "properties": {
    "addr:full":"Kortestreek 3 Lemmer Friesland 8531 JE",
    "addr:housenumber":"3",
    "addr:postcode":"8531 je",
    "addr:street":"Kortestreek",
    "iso:country":"NL",
    "sg:address":"Kortestreek 3",
    "sg:city":"Lemmer",
    "sg:orig_category":"Visspeciaalzaken",
    "sg:phone":"+31 514 561 258",
    "sg:postcode":"8531 JE",
    "sg:province":"Friesland",
    "wof:name":"Vof De Lemster Vishal",
    "wof:placetype":"venue"
},
  "geometry": {"coordinates":[5.71077,52.844925],"type":"Point"}
}