{
  "type": "Feature",
  "properties": {
    "addr:full":"Taveernelaan 17 Bosch En Duin Utrecht 3735 KA",
    "addr:housenumber":"17",
    "addr:postcode":"en duin;3735 ka",
    "addr:street":"Taveernelaan",
    "iso:country":"NL",
    "sg:address":"Taveernelaan 17",
    "sg:city":"Bosch En Duin",
    "sg:orig_category":"Adviesbureaus Bedrijfsorganisatie",
    "sg:phone":"+31 30 229 2816",
    "sg:postcode":"3735 KA",
    "sg:province":"Utrecht",
    "wof:name":"Obimo",
    "wof:placetype":"venue"
},
  "geometry": {"coordinates":[5.244313,52.128654],"type":"Point"}
}