{
  "type": "Feature",
  "properties": {
    "addr:full":"Langewyk 436 Dedemsvaart NL.08 7701 AT",
    "addr:housenumber":"436;nl.08",
    "addr:postcode":"7701",
    "addr:street":"Langewyk",
    "iso:country":"NL",
    "sg:address":"Langewyk 436",
    "sg:city":"Dedemsvaart",
    "sg:orig_category":"Scholen Voor Basisonderwijs",
    "sg:phone":"+31 523 612 881",
    "sg:postcode":"7701 AT",
    "sg:province":"NL.08",
    "sg:website":"HTTP://www.rendo.dekooi.nl/~groenvpr",
    "wof:name":"Groen Van Prinsterer",
    "wof:placetype":"venue"
},
  "geometry": {"coordinates":[6.457315,52.606258],"type":"Point"}
}