{
  "type": "Feature",
  "properties": {
    "addr:full":"Wildemanstr 64 Oisterwijk Noord-Brabant 5062 HC",
    "addr:housenumber":"64",
    "addr:postcode":"5062 hc",
    "addr:street":"Wildemanstr",
    "iso:country":"NL",
    "sg:address":"Wildemanstr 64",
    "sg:city":"Oisterwijk",
    "sg:orig_category":"Artsen - Huisartsen",
    "sg:phone":"+31 13 528 2210",
    "sg:postcode":"5062 HC",
    "sg:province":"Noord-Brabant",
    "wof:name":"Vermue, J C",
    "wof:placetype":"venue"
},
  "geometry": {"coordinates":[5.193049,51.57362],"type":"Point"}
}