{
  "type": "Feature",
  "properties": {
    "addr:full":"De Clercqstraat 17 Amsterdam Noord-Holland 1053 AA",
    "addr:housenumber":"17",
    "addr:postcode":"1053 aa",
    "addr:street":"De Clercqstraat",
    "iso:country":"NL",
    "sg:address":"De Clercqstraat 17",
    "sg:city":"Amsterdam",
    "sg:orig_category":"Verlichting And Huishoudartikelen",
    "sg:phone":"+31 20 683 8277",
    "sg:postcode":"1053 AA",
    "sg:province":"Noord-Holland",
    "wof:name":"Lilipaly Verlichtingsatelier",
    "wof:placetype":"venue"
},
  "geometry": {"coordinates":[4.873155,52.37151],"type":"Point"}
}