{
  "type": "Feature",
  "properties": {
    "addr:full":"Kon Wilhelminapln 131 07 17 Amsterdam Noord-Holland 1062 HH",
    "addr:housenumber":"17",
    "addr:postcode":"131;1062 hh",
    "addr:street":"Kon",
    "iso:country":"NL",
    "sg:address":"Kon Wilhelminapln 131 07 17",
    "sg:city":"Amsterdam",
    "sg:orig_category":"Kinderkleding - Fabrieken En Groothandel",
    "sg:phone":"+31 20 617 3141",
    "sg:postcode":"1062 HH",
    "sg:province":"Noord-Holland",
    "wof:name":"Wieske Bv",
    "wof:placetype":"venue"
},
  "geometry": {"coordinates":[4.83975,52.351082],"type":"Point"}
}