{
  "type": "Feature",
  "properties": {
    "addr:full":"Galvaniwg 12 Nunspeet Gelderland 8071 SC",
    "addr:housenumber":"12",
    "addr:postcode":"8071",
    "addr:street":"Galvaniwg;Gelderland",
    "iso:country":"NL",
    "sg:address":"Galvaniwg 12",
    "sg:city":"Nunspeet",
    "sg:orig_category":"Verpakkingsbedrijven",
    "sg:phone":"+31 341 257 966",
    "sg:postcode":"8071 SC",
    "sg:province":"Gelderland",
    "wof:name":"Abivo",
    "wof:placetype":"venue"
},
  "geometry": {"coordinates":[5.765987,52.375648],"type":"Point"}
}