{
  "type": "Feature",
  "properties": {
    "addr:full":"Amstellandlaan 64 Amstelveen Noord-Holland 1182 CE",
    "addr:housenumber":"64",
    "addr:postcode":"1182 ce",
    "addr:street":"Amstellandlaan",
    "iso:country":"NL",
    "sg:address":"Amstellandlaan 64",
    "sg:city":"Amstelveen",
    "sg:orig_category":"Antiekzaken",
    "sg:phone":"+31 20 640 2575",
    "sg:postcode":"1182 CE",
    "sg:province":"Noord-Holland",
    "wof:name":"Anitquariaat Oskam En Neeven",
    "wof:placetype":"venue"
},
  "geometry": {"coordinates":[4.849542,52.309608],"type":"Point"}
}