{
  "type": "Feature",
  "properties": {
    "iso:country":"NL",
    "sg:address":"Astrastr 1",
    "sg:city":"Oudorp Nh",
    "sg:orig_category":"Huidtherapeuten",
    "sg:phone":"+31 72 515 7939",
    "sg:postcode":"1829 JA",
    "sg:province":"Noord-Holland",
    "wof:name":"Nehpos, De",
    "wof:placetype":"venue"
},
  "geometry": {"coordinates":[4.775327,52.627468],"type":"Point"}
}