{
  "type": "Feature",
  "properties": {
    "addr:full":"De Wilgen 4 Veenwouden Friesland 9269 SR",
    "addr:housenumber":"4",
    "addr:postcode":"9269 sr",
    "addr:street":"De Wilgen",
    "iso:country":"NL",
    "sg:address":"De Wilgen 4",
    "sg:city":"Veenwouden",
    "sg:orig_category":"Accountants - Administratie- Consulenten En -Kantoren",
    "sg:phone":"+31 511 476 706",
    "sg:postcode":"9269 SR",
    "sg:province":"Friesland",
    "wof:name":"Dunnebier",
    "wof:placetype":"venue"
},
  "geometry": {"coordinates":[5.993369,53.241737],"type":"Point"}
}