{
  "type": "Feature",
  "properties": {
    "addr:full":"Javaln 57 Zwyndrecht Zuid-Holland 3333 AH",
    "addr:housenumber":"57",
    "addr:postcode":"3333 ah",
    "addr:street":"Javaln",
    "iso:country":"NL",
    "sg:address":"Javaln 57",
    "sg:city":"Zwyndrecht",
    "sg:orig_category":"Natuurvoeding En Reformartikelen",
    "sg:phone":"+31 6 15305342",
    "sg:postcode":"3333 AH",
    "sg:province":"Zuid-Holland",
    "wof:name":"Patricia",
    "wof:placetype":"venue"
},
  "geometry": {"coordinates":[4.63394,51.81358],"type":"Point"}
}