{
  "type": "Feature",
  "properties": {
    "addr:full":"Plantage Badlaan 19 Amsterdam North Holland 1018 TG",
    "addr:housenumber":"19",
    "addr:postcode":"1018 tg",
    "addr:street":"Plantage Badlaan",
    "iso:country":"NL",
    "sg:address":"Plantage Badlaan 19",
    "sg:city":"Amsterdam",
    "sg:orig_category":"Loodgieterswerk, Verwarming And Sanitaire Installaties",
    "sg:phone":"+31 20 624 6575",
    "sg:postcode":"1018 TG",
    "sg:province":"North Holland",
    "wof:name":"J.M. Vossen",
    "wof:placetype":"venue"
},
  "geometry": {"coordinates":[4.916703,52.364403],"type":"Point"}
}