{
  "type": "Feature",
  "properties": {
    "addr:full":"Winkelc Woensel 83D Eindhoven Noord-Brabant 5625 AE",
    "addr:housenumber":"83d",
    "addr:postcode":"5625 ae",
    "addr:street":"Winkelc Woensel",
    "iso:country":"NL",
    "sg:address":"Winkelc Woensel 83D",
    "sg:city":"Eindhoven",
    "sg:orig_category":"Artsen - Huisartsen",
    "sg:phone":"+31 40 264 6025",
    "sg:postcode":"5625 AE",
    "sg:province":"Noord-Brabant",
    "wof:name":"Schouten, O T M",
    "wof:placetype":"venue"
},
  "geometry": {"coordinates":[5.475628,51.470615],"type":"Point"}
}