{
  "type": "Feature",
  "properties": {
    "addr:full":"Brederostr 39 Breda North Brabant 4819 HG",
    "addr:housenumber":"39",
    "addr:postcode":"4819 hg",
    "addr:street":"Brederostr",
    "iso:country":"NL",
    "sg:address":"Brederostr 39",
    "sg:city":"Breda",
    "sg:orig_category":"Kasregisters",
    "sg:phone":"+31 76 521 8747",
    "sg:postcode":"4819 HG",
    "sg:province":"North Brabant",
    "wof:name":"Ehs",
    "wof:placetype":"venue"
},
  "geometry": {"coordinates":[4.76515,51.57737],"type":"Point"}
}