{
  "type": "Feature",
  "properties": {
    "addr:full":"Rivium Westlaan 142 Capelle A/D Ijssel South Holland 2909 LD",
    "addr:housenumber":"142;a / d",
    "addr:postcode":"2909 ld",
    "addr:street":"Rivium Westlaan;Ijssel South",
    "iso:country":"NL",
    "sg:address":"Rivium Westlaan 142",
    "sg:city":"Capelle A/D Ijssel",
    "sg:orig_category":"Farmaceutische Producten Gh",
    "sg:phone":"+31 10 406 4200",
    "sg:postcode":"2909 LD",
    "sg:province":"South Holland",
    "wof:name":"Pfizer Bv",
    "wof:placetype":"venue"
},
  "geometry": {"coordinates":[4.54231,51.91246],"type":"Point"}
}