{
  "type": "Feature",
  "properties": {
    "addr:full":"Seinedreef 110 Utrecht Utrecht 3562 KT",
    "addr:housenumber":"110",
    "addr:postcode":"3562 kt",
    "addr:street":"Seinedreef",
    "iso:country":"NL",
    "sg:address":"Seinedreef 110",
    "sg:city":"Utrecht",
    "sg:orig_category":"Fietshandelaren",
    "sg:phone":"+31 30 261 4818",
    "sg:postcode":"3562 KT",
    "sg:province":"Utrecht",
    "wof:name":"Banierhuis Nv",
    "wof:placetype":"venue"
},
  "geometry": {"coordinates":[5.111311,52.11282],"type":"Point"}
}