{
  "type": "Feature",
  "properties": {
    "addr:full":"Pijlkruid 11 Nijverdal NL.08 7443 LT",
    "addr:housenumber":"11;nl.08",
    "addr:postcode":"7443 lt",
    "addr:street":"Pijlkruid",
    "iso:country":"NL",
    "sg:address":"Pijlkruid 11",
    "sg:city":"Nijverdal",
    "sg:orig_category":"Fotostudio'S And Fotografen",
    "sg:phone":"+31 548 620 225",
    "sg:postcode":"7443 LT",
    "sg:province":"NL.08",
    "wof:name":"Liesbeth Reklame En Fotografie",
    "wof:placetype":"venue"
},
  "geometry": {"coordinates":[6.484761,52.380173],"type":"Point"}
}