{
  "type": "Feature",
  "properties": {
    "addr:full":"Nieuwez Voorburgw 294I Amsterdam Noord-Holland 1012 RT",
    "addr:housenumber":"294i",
    "addr:postcode":"1012 rt",
    "addr:street":"Voorburgw",
    "iso:country":"NL",
    "sg:address":"Nieuwez Voorburgw 294I",
    "sg:city":"Amsterdam",
    "sg:orig_category":"Pianostemmen En -Reparatie",
    "sg:phone":"+31 20 626 6748",
    "sg:postcode":"1012 RT",
    "sg:province":"Noord-Holland",
    "wof:name":"Lagaaij, Paul",
    "wof:placetype":"venue"
},
  "geometry": {"coordinates":[4.889922,52.370842],"type":"Point"}
}