{
  "type": "Feature",
  "properties": {
    "iso:country":"NL",
    "sg:address":"J Voetstr 2",
    "sg:city":"Eindhoven",
    "sg:classifiers":[
        {
            "category":"Food & Beverages",
            "subcategory":"Bakery",
            "type":"Retail Goods"
        }
    ],
    "sg:phone":"+31 40 251 3730",
    "sg:postcode":"5652 GS",
    "sg:province":"Noord-Brabant",
    "sg:tags":[
        "brood",
        "en",
        "banket"
    ],
    "wof:name":"Bruin, M De",
    "wof:placetype":"venue"
},
  "geometry": {"coordinates":[5.440797,51.439556],"type":"Point"}
}