{
  "type": "Feature",
  "properties": {
    "iso:country":"NL",
    "sg:address":"Brinkstraat 57",
    "sg:city":"Beilen",
    "sg:orig_category":"Kappers",
    "sg:phone":"+31 593 525 671",
    "sg:postcode":"9411 KL",
    "sg:province":"Drenthe",
    "wof:name":"Kapsalon Marilyn",
    "wof:placetype":"venue"
},
  "geometry": {"coordinates":[6.5163788795,52.8594512939],"type":"Point"}
}