{
  "type": "Feature",
  "properties": {
    "addr:full":"Rooseveltstraat 18 Leiden South Holland 2321 BM",
    "addr:housenumber":"18",
    "addr:postcode":"2321 bm",
    "addr:street":"Rooseveltstraat",
    "iso:country":"NL",
    "sg:address":"Rooseveltstraat 18",
    "sg:city":"Leiden",
    "sg:orig_category":"Bouwmaterialen Gh",
    "sg:phone":"+31 71 531 0111",
    "sg:postcode":"2321 BM",
    "sg:province":"South Holland",
    "wof:name":"Keek Coatings Bv",
    "wof:placetype":"venue"
},
  "geometry": {"coordinates":[4.481651,52.144287],"type":"Point"}
}