{
  "type": "Feature",
  "properties": {
    "addr:full":"Jasmijnstraat 14 Sint Oedenrode Noord-Brabant 5492 JT",
    "addr:housenumber":"14;oedenrode",
    "addr:postcode":"5492 jt",
    "addr:street":"Jasmijnstraat",
    "iso:country":"NL",
    "sg:address":"Jasmijnstraat 14",
    "sg:city":"Sint Oedenrode",
    "sg:orig_category":"Binnenhuisarchitecten",
    "sg:phone":"+31 413 490 428",
    "sg:postcode":"5492 JT",
    "sg:province":"Noord-Brabant",
    "wof:name":"Studio In-Art",
    "wof:placetype":"venue"
},
  "geometry": {"coordinates":[5.486349,51.551594],"type":"Point"}
}