{
  "type": "Feature",
  "properties": {
    "addr:full":"Mr P Moggestr 5 Dreischor Zeeland 4315 AA",
    "addr:housenumber":"5",
    "addr:postcode":"4315 aa",
    "addr:street":"Mr P Moggestr",
    "iso:country":"NL",
    "sg:address":"Mr P Moggestr 5",
    "sg:city":"Dreischor",
    "sg:orig_category":"Verenigingsgebouwen",
    "sg:phone":"+31 111 401 232",
    "sg:postcode":"4315 AA",
    "sg:province":"Zeeland",
    "sg:website":"http://www.dorpshuisdreischor.nl",
    "wof:name":"Dorpshuis",
    "wof:placetype":"venue"
},
  "geometry": {"coordinates":[3.981568,51.689163],"type":"Point"}
}