{
  "type": "Feature",
  "properties": {
    "addr:full":"Hoofdstr O 14 Winsum Gn Groningen 9951 AH",
    "addr:housenumber":"14",
    "addr:postcode":"gn;9951 ah",
    "iso:country":"NL",
    "sg:address":"Hoofdstr O 14",
    "sg:city":"Winsum Gn",
    "sg:orig_category":"Wereldwinkels",
    "sg:phone":"+31 595 442 900",
    "sg:postcode":"9951 AH",
    "sg:province":"Groningen",
    "wof:name":"Wereldwinkel",
    "wof:placetype":"venue"
},
  "geometry": {"coordinates":[6.5173950195,53.3344116211],"type":"Point"}
}