{
  "type": "Feature",
  "properties": {
    "addr:full":"Johannes Vermeerstraat 21 Best Texas 5684 AT",
    "addr:housenumber":"21",
    "addr:postcode":"5684",
    "addr:street":"Johannes Vermeerstraat",
    "iso:country":"NL",
    "sg:address":"Johannes Vermeerstraat 21",
    "sg:city":"Best",
    "sg:classifiers":[
        {
            "category":"Education",
            "subcategory":"Preschool",
            "type":"Public Place"
        }
    ],
    "sg:phone":"+31 499 373 843",
    "sg:postcode":"5684 AT",
    "sg:province":"Texas",
    "sg:tags":[
        "kleuteronderwijs",
        "basis-"
    ],
    "wof:name":"Basisschool De Schakel",
    "wof:placetype":"venue"
},
  "geometry": {"coordinates":[-101.618134,31.224251],"type":"Point"}
}