{
  "type": "Feature",
  "properties": {
    "addr:full":"Asserring 196-198 Amstelveen North Holland 1187 KL",
    "addr:housenumber":"196-198",
    "addr:postcode":"1187 kl",
    "addr:street":"Asserring",
    "iso:country":"NL",
    "sg:address":"Asserring 196-198",
    "sg:city":"Amstelveen",
    "sg:orig_category":"Kinderopvang Behalve Thuis",
    "sg:phone":"+31 20 640 3327",
    "sg:postcode":"1187 KL",
    "sg:province":"North Holland",
    "wof:name":"Zuidwester Kinderdagverblijf",
    "wof:placetype":"venue"
},
  "geometry": {"coordinates":[4.826581,52.2803],"type":"Point"}
}