{
  "type": "Feature",
  "properties": {
    "iso:country":"NL",
    "sg:address":"Asserring 196-198",
    "sg:city":"Amstelveen",
    "sg:orig_category":"Kinderopvang Behalve Thuis",
    "sg:phone":"+31 20 640 3327",
    "sg:postcode":"1187 KL",
    "sg:province":"North Holland",
    "wof:name":"Zuidwester Kinderdagverblijf",
    "wof:placetype":"venue"
},
  "geometry": {"coordinates":[4.826581,52.2803],"type":"Point"}
}