{
  "type": "Feature",
  "properties": {
    "addr:full":"Vossiuslaan 63 Bussum Noord-Holland 1401 RS",
    "addr:housenumber":"63",
    "addr:postcode":"1401 rs",
    "addr:street":"Vossiuslaan",
    "iso:country":"NL",
    "sg:address":"Vossiuslaan 63",
    "sg:city":"Bussum",
    "sg:orig_category":"Grafologen, Handlezers And Helderzienden",
    "sg:phone":"+31 35 691 7769",
    "sg:postcode":"1401 RS",
    "sg:province":"Noord-Holland",
    "wof:name":"Astrografica",
    "wof:placetype":"venue"
},
  "geometry": {"coordinates":[5.165189,52.279461],"type":"Point"}
}