{
  "type": "Feature",
  "properties": {
    "addr:full":"Voorstr 11 Stellendam Zuid-Holland 3251 BB",
    "addr:housenumber":"11",
    "addr:postcode":"3251 bb",
    "addr:street":"Voorstr",
    "iso:country":"NL",
    "sg:address":"Voorstr 11",
    "sg:city":"Stellendam",
    "sg:orig_category":"Artiesten/Gezelschappen",
    "sg:phone":"+31 187 493 249",
    "sg:postcode":"3251 BB",
    "sg:province":"Zuid-Holland",
    "sg:website":"http://www.kabora.nl",
    "wof:name":"Kabora",
    "wof:placetype":"venue"
},
  "geometry": {"coordinates":[4.029347,51.80513],"type":"Point"}
}