{
  "type": "Feature",
  "properties": {
    "addr:full":"Thystr 45 Rossum Ov Overijssel 7596 KJ",
    "addr:housenumber":"45",
    "addr:postcode":"7596 kj",
    "addr:street":"Thystr;Ov",
    "iso:country":"NL",
    "sg:address":"Thystr 45",
    "sg:city":"Rossum Ov",
    "sg:orig_category":"Adviesbureaus Bedrijfsorganisatie",
    "sg:phone":"+31 541 626 500",
    "sg:postcode":"7596 KJ",
    "sg:province":"Overijssel",
    "sg:website":"http://www.bgjh.nl",
    "wof:name":"Bgjh",
    "wof:placetype":"venue"
},
  "geometry": {"coordinates":[6.92388,52.351894],"type":"Point"}
}