{
  "type": "Feature",
  "properties": {
    "addr:full":"Nieuwstr 41 Purmerend North Holland 1441 CK",
    "addr:housenumber":"41",
    "addr:postcode":"1441 ck",
    "addr:street":"Nieuwstr",
    "iso:country":"NL",
    "sg:address":"Nieuwstr 41",
    "sg:city":"Purmerend",
    "sg:orig_category":"Schoenen",
    "sg:phone":"+31 299 420 613",
    "sg:postcode":"1441 CK",
    "sg:province":"North Holland",
    "wof:name":"Capri Shoes",
    "wof:placetype":"venue"
},
  "geometry": {"coordinates":[4.945496,52.508347],"type":"Point"}
}