{
  "type": "Feature",
  "properties": {
    "addr:full":"Akkermolenweg 27 Zundert North Brabant 4881 BL",
    "addr:housenumber":"27",
    "addr:postcode":"4881 bl",
    "addr:street":"Akkermolenweg",
    "iso:country":"NL",
    "sg:address":"Akkermolenweg 27",
    "sg:city":"Zundert",
    "sg:orig_category":"Goederenvervoer Over De Weg",
    "sg:phone":"+31 76 597 2630",
    "sg:postcode":"4881 BL",
    "sg:province":"North Brabant",
    "wof:name":"Transportbedrijf Tax Gebr.",
    "wof:placetype":"venue"
},
  "geometry": {"coordinates":[4.671288,51.480614],"type":"Point"}
}