{
  "type": "Feature",
  "properties": {
    "addr:full":"Edisonwg 26 Bunschoten Spakenb Utrecht 3752 LV",
    "addr:housenumber":"26",
    "addr:postcode":"3752",
    "addr:street":"Edisonwg",
    "iso:country":"NL",
    "sg:address":"Edisonwg 26",
    "sg:city":"Bunschoten Spakenb",
    "sg:orig_category":"Fournituren - Fabrieken En Groothandel",
    "sg:phone":"+31 33 298 1244",
    "sg:postcode":"3752 LV",
    "sg:province":"Utrecht",
    "wof:name":"Qps, Quality Pad Support",
    "wof:placetype":"venue"
},
  "geometry": {"coordinates":[5.361211,52.230972],"type":"Point"}
}