{
  "type": "Feature",
  "properties": {
    "iso:country":"NL",
    "sg:address":"Middenhof 1",
    "sg:city":"Lekkerkerk",
    "sg:orig_category":"Koppensnellen",
    "sg:phone":"+31 180 661 680",
    "sg:postcode":"2941 HA",
    "sg:province":"South Holland",
    "wof:name":"Ouwerkerk",
    "wof:placetype":"venue"
},
  "geometry": {"coordinates":[4.68578,51.895603],"type":"Point"}
}