{
  "type": "Feature",
  "properties": {
    "addr:full":"Middenhof 1 Lekkerkerk South Holland 2941 HA",
    "addr:housenumber":"1",
    "addr:postcode":"2941 ha",
    "addr:street":"Middenhof",
    "iso:country":"NL",
    "sg:address":"Middenhof 1",
    "sg:city":"Lekkerkerk",
    "sg:orig_category":"Koppensnellen",
    "sg:phone":"+31 180 661 680",
    "sg:postcode":"2941 HA",
    "sg:province":"South Holland",
    "wof:name":"Ouwerkerk",
    "wof:placetype":"venue"
},
  "geometry": {"coordinates":[4.68578,51.895603],"type":"Point"}
}