{
  "type": "Feature",
  "properties": {
    "addr:full":"Boompjes 655 Rotterdam Zuid-Holland 3011 XZ",
    "addr:housenumber":"655",
    "addr:postcode":"3011 xz",
    "addr:street":"Boompjes",
    "iso:country":"NL",
    "sg:address":"Boompjes 655",
    "sg:city":"Rotterdam",
    "sg:orig_category":"Diverse Opleidingen And Onderwijs",
    "sg:phone":"+31 10 465 5030",
    "sg:postcode":"3011 XZ",
    "sg:province":"Zuid-Holland",
    "wof:name":"Deskhelp",
    "wof:placetype":"venue"
},
  "geometry": {"coordinates":[4.484961,51.913109],"type":"Point"}
}