{
  "type": "Feature",
  "properties": {
    "addr:full":"Langewg 31A Apeldoorn Gelderland 7315 CR",
    "addr:housenumber":"31a;7315",
    "addr:postcode":"cr",
    "addr:street":"Langewg;Gelderland",
    "iso:country":"NL",
    "sg:address":"Langewg 31A",
    "sg:city":"Apeldoorn",
    "sg:orig_category":"Adviesbureaus Bedrijfsorganisatie",
    "sg:phone":"+31 55 522 2415",
    "sg:postcode":"7315 CR",
    "sg:province":"Gelderland",
    "wof:name":"Smit Ned",
    "wof:placetype":"venue"
},
  "geometry": {"coordinates":[5.950614,52.227634],"type":"Point"}
}