{
  "type": "Feature",
  "properties": {
    "iso:country":"NL",
    "sg:address":"Bonksel 3A",
    "sg:city":"Asten",
    "sg:orig_category":"Machinefabrieken",
    "sg:phone":"+31 493 699 595",
    "sg:postcode":"5721 TP",
    "sg:province":"Noord-Brabant",
    "sg:website":"http://www.kootautomation.nl",
    "wof:name":"Koot",
    "wof:placetype":"venue"
},
  "geometry": {"coordinates":[5.749823,51.414078],"type":"Point"}
}