{
  "type": "Feature",
  "properties": {
    "addr:full":"Kruisstraat 57 Stein Lb BE.05 6171 GD",
    "addr:housenumber":"57",
    "addr:postcode":"6171 gd",
    "addr:street":"Kruisstraat;Lb",
    "iso:country":"NL",
    "sg:address":"Kruisstraat 57",
    "sg:city":"Stein Lb",
    "sg:orig_category":"Huishoudapparatuur, Televisies And Radio'S",
    "sg:phone":"+31 46 426 8010",
    "sg:postcode":"6171 GD",
    "sg:province":"BE.05",
    "wof:name":"Jack Waaijen Vof",
    "wof:placetype":"venue"
},
  "geometry": {"coordinates":[5.759459,50.968334],"type":"Point"}
}