{
  "type": "Feature",
  "properties": {
    "iso:country":"NL",
    "sg:address":"V Oldenbarnev Pln 3",
    "sg:city":"Amsterdam",
    "sg:orig_category":"Schoonheidsinstituten",
    "sg:phone":"+31 20 686 2923",
    "sg:postcode":"1052 JK",
    "sg:province":"Noord-Holland",
    "wof:name":"Face- And Bodycare",
    "wof:placetype":"venue"
},
  "geometry": {"coordinates":[4.87379,52.377899],"type":"Point"}
}