{
  "type": "Feature",
  "properties": {
    "iso:country":"NL",
    "sg:address":"Wesseler-Nering 19",
    "sg:city":"Enschede",
    "sg:orig_category":"Kappers",
    "sg:phone":"+31 53 476 2871",
    "sg:postcode":"7544 JB",
    "sg:province":"NL.08",
    "wof:name":"Jacob'S Hairstudio",
    "wof:placetype":"venue"
},
  "geometry": {"coordinates":[6.882244,52.19154],"type":"Point"}
}