{
  "type": "Feature",
  "properties": {
    "iso:country":"NL",
    "sg:address":"Daam Fockemalaan 22",
    "sg:city":"Amersfoort",
    "sg:orig_category":"Kinderopvang Behalve Thuis",
    "sg:phone":"+31 33 461 1510",
    "sg:postcode":"3818 KG",
    "sg:province":"Utrecht",
    "wof:name":"Kindercentrum Panta Rhei",
    "wof:placetype":"venue"
},
  "geometry": {"coordinates":[5.35594,52.146404],"type":"Point"}
}