{
  "type": "Feature",
  "properties": {
    "addr:full":"Eperweg 55 'T Harde Gelderland 8084 HB",
    "addr:housenumber":"55",
    "addr:postcode":"8084 hb",
    "addr:street":"Eperweg",
    "iso:country":"NL",
    "sg:address":"Eperweg 55",
    "sg:city":"'T Harde",
    "sg:classifiers":[
        {
            "category":"Retail",
            "subcategory":"Photofinishing",
            "type":"Services"
        }
    ],
    "sg:phone":"+31 525 651 612",
    "sg:postcode":"8084 HB",
    "sg:province":"Gelderland",
    "sg:tags":[
        "foto",
        "film"
    ],
    "wof:name":"Foto Cine Hup",
    "wof:placetype":"venue"
},
  "geometry": {"coordinates":[5.884048,52.415695],"type":"Point"}
}