{
  "type": "Feature",
  "properties": {
    "addr:full":"Burgemeester Houtkoperwg 24 Lienden Gelderland 4033 BK",
    "addr:housenumber":"24",
    "addr:postcode":"4033 bk",
    "addr:street":"Burgemeester Houtkoperwg;Gelderland",
    "iso:country":"NL",
    "sg:address":"Burgemeester Houtkoperwg 24",
    "sg:city":"Lienden",
    "sg:orig_category":"Goederenvervoer Over De Weg",
    "sg:phone":"+31 488 481 535",
    "sg:postcode":"4033 BK",
    "sg:province":"Gelderland",
    "wof:name":"Vof Meijering Transport",
    "wof:placetype":"venue"
},
  "geometry": {"coordinates":[5.540085,51.934582],"type":"Point"}
}