{
  "type": "Feature",
  "properties": {
    "addr:full":"Willem De Zwijgerstraat 16 Noord-Scharwoude North Holland 1723 KG",
    "addr:housenumber":"16",
    "addr:postcode":"1723 kg",
    "addr:street":"Willem De Zwijgerstraat",
    "iso:country":"NL",
    "sg:address":"Willem De Zwijgerstraat 16",
    "sg:city":"Noord-Scharwoude",
    "sg:orig_category":"Zuivelproducten",
    "sg:phone":"+31 226 344 080",
    "sg:postcode":"1723 KG",
    "sg:province":"North Holland",
    "wof:name":"De Kaasmarkt",
    "wof:placetype":"venue"
},
  "geometry": {"coordinates":[4.813963,52.703087],"type":"Point"}
}