{
  "type": "Feature",
  "properties": {
    "addr:full":"Kl Houtstraat 2-4 Zw Haarlem North Holland 2011 DM",
    "addr:housenumber":"2-4 zw",
    "addr:postcode":"2011 dm",
    "addr:street":"Houtstraat",
    "iso:country":"NL",
    "sg:address":"Kl Houtstraat 2-4 Zw",
    "sg:city":"Haarlem",
    "sg:orig_category":"Partycatering And -Organisatie",
    "sg:phone":"+31 23 531 9731",
    "sg:postcode":"2011 DM",
    "sg:province":"North Holland",
    "wof:name":"Dionsysos",
    "wof:placetype":"venue"
},
  "geometry": {"coordinates":[4.642253,52.380562],"type":"Point"}
}