{
  "type": "Feature",
  "properties": {
    "addr:full":"Plein 23 Almere Flevoland 1354 LH",
    "addr:housenumber":"23",
    "addr:postcode":"1354 lh",
    "addr:street":"Plein;Flevoland",
    "iso:country":"NL",
    "sg:address":"Plein 23",
    "sg:city":"Almere",
    "sg:orig_category":"Balletscholen",
    "sg:phone":"+31 36 531 4445",
    "sg:postcode":"1354 LH",
    "sg:province":"Flevoland",
    "wof:name":"Almere, Balletschool",
    "wof:placetype":"venue"
},
  "geometry": {"coordinates":[5.219301,52.335133],"type":"Point"}
}