{
  "type": "Feature",
  "properties": {
    "addr:full":"Gasthuisstr 6B Oisterwyk Noord-Brabant 5061 PB",
    "addr:housenumber":"6b",
    "addr:postcode":"5061 pb",
    "addr:street":"Gasthuisstr",
    "iso:country":"NL",
    "sg:address":"Gasthuisstr 6B",
    "sg:city":"Oisterwyk",
    "sg:orig_category":"Autoschade- Herstelbedrijven",
    "sg:phone":"+31 13 528 4950",
    "sg:postcode":"5061 PB",
    "sg:province":"Noord-Brabant",
    "wof:name":"Heessels",
    "wof:placetype":"venue"
},
  "geometry": {"coordinates":[5.184032,51.580341],"type":"Point"}
}