{
  "type": "Feature",
  "properties": {
    "addr:full":"Anthony Fokkerweg 43 Amsterdam North Holland 1059 CN",
    "addr:housenumber":"43",
    "addr:postcode":"1059 cn",
    "addr:street":"Anthony Fokkerweg",
    "iso:country":"NL",
    "sg:address":"Anthony Fokkerweg 43",
    "sg:city":"Amsterdam",
    "sg:orig_category":"Meubelzaken, Woning- And Keukeninrichting",
    "sg:phone":"+31 20 408 0538",
    "sg:postcode":"1059 CN",
    "sg:province":"North Holland",
    "wof:name":"Beter Bed",
    "wof:placetype":"venue"
},
  "geometry": {"coordinates":[4.842078,52.34293],"type":"Point"}
}