{
  "type": "Feature",
  "properties": {
    "addr:full":"S V Ravesteynstr 58 Almere Flevoland 1333 JS",
    "addr:housenumber":"58",
    "addr:postcode":"1333 js",
    "addr:street":"Ravesteynstr;Flevoland",
    "iso:country":"NL",
    "sg:address":"S V Ravesteynstr 58",
    "sg:city":"Almere",
    "sg:orig_category":"Hulpverlening Sociaal",
    "sg:phone":"+31 36 549 9563",
    "sg:postcode":"1333 JS",
    "sg:province":"Flevoland",
    "wof:name":"Arcuris",
    "wof:placetype":"venue"
},
  "geometry": {"coordinates":[5.265875,52.396851],"type":"Point"}
}