{
  "type": "Feature",
  "properties": {
    "addr:full":"Veenweg 1A Deventer Overijssel 7416 BA",
    "addr:housenumber":"1a",
    "addr:postcode":"7416 ba",
    "addr:street":"Veenweg",
    "iso:country":"NL",
    "sg:address":"Veenweg 1A",
    "sg:city":"Deventer",
    "sg:orig_category":"Modellenbureaus",
    "sg:phone":"+31 570 636 313",
    "sg:postcode":"7416 BA",
    "sg:province":"Overijssel",
    "wof:name":"Inter Eastern Agency",
    "wof:placetype":"venue"
},
  "geometry": {"coordinates":[6.169869,52.260067],"type":"Point"}
}