{
  "type": "Feature",
  "properties": {
    "addr:full":"Hoofdwg N 9 Spyk Gn Groningen 9909 AC",
    "addr:housenumber":"9",
    "addr:postcode":"gn;9909 ac",
    "addr:street":"N",
    "iso:country":"NL",
    "sg:address":"Hoofdwg N 9",
    "sg:city":"Spyk Gn",
    "sg:orig_category":"Bloemen En Planten",
    "sg:phone":"+31 596 572 767",
    "sg:postcode":"9909 AC",
    "sg:province":"Groningen",
    "wof:name":"Ieneke Bloem Atelier",
    "wof:placetype":"venue"
},
  "geometry": {"coordinates":[6.83624,53.388969],"type":"Point"}
}