{
  "type": "Feature",
  "properties": {
    "addr:full":"Pretoriusstraat 90 Amsterdam Noord-Holland 1092 GL",
    "addr:housenumber":"90",
    "addr:postcode":"1092 gl",
    "addr:street":"Pretoriusstraat",
    "iso:country":"NL",
    "sg:address":"Pretoriusstraat 90",
    "sg:city":"Amsterdam",
    "sg:classifiers":[
        {
            "category":"Bakery",
            "type":"Food & Drink"
        }
    ],
    "sg:phone":"+31 20 693 6199",
    "sg:postcode":"1092 GL",
    "sg:province":"Noord-Holland",
    "sg:tags":[
        "brood",
        "banket"
    ],
    "wof:name":"El Kasmi",
    "wof:placetype":"venue"
},
  "geometry": {"coordinates":[4.921077,52.354694],"type":"Point"}
}