{
  "type": "Feature",
  "properties": {
    "addr:full":"Tjadenwg 37 Wydewormer Noord-Holland 1456 AL",
    "addr:housenumber":"37",
    "addr:postcode":"1456 al",
    "addr:street":"Tjadenwg",
    "iso:country":"NL",
    "sg:address":"Tjadenwg 37",
    "sg:city":"Wydewormer",
    "sg:orig_category":"Wegenbouw",
    "sg:phone":"+31 299 436 617",
    "sg:postcode":"1456 AL",
    "sg:province":"Noord-Holland",
    "wof:name":"Veldt, Fa Ren?",
    "wof:placetype":"venue"
},
  "geometry": {"coordinates":[4.9131150246,52.5088615417],"type":"Point"}
}