{
  "type": "Feature",
  "properties": {
    "addr:full":"Binnen Bant Str 20 Amsterdam North Holland 1011 CL",
    "addr:housenumber":"20",
    "addr:postcode":"1011",
    "addr:street":"Binnen Bant Str",
    "iso:country":"NL",
    "sg:address":"Binnen Bant Str 20",
    "sg:city":"Amsterdam",
    "sg:orig_category":"Psychologen",
    "sg:phone":"+31 20 626 7390",
    "sg:postcode":"1011 CL",
    "sg:province":"North Holland",
    "wof:name":"Santen, Drs H Van",
    "wof:placetype":"venue"
},
  "geometry": {"coordinates":[4.902319,52.373596],"type":"Point"}
}