{
  "type": "Feature",
  "properties": {
    "addr:full":"Albert Einsteinstraat 10 Oud Beijerland Zuid-Holland 3261 LP",
    "addr:housenumber":"10",
    "addr:postcode":"3261 lp",
    "addr:street":"Albert Einsteinstraat;Beijerland",
    "iso:country":"NL",
    "sg:address":"Albert Einsteinstraat 10",
    "sg:city":"Oud Beijerland",
    "sg:orig_category":"Kantoor- And Schoolbenodigdheden Gh",
    "sg:phone":"+31 186 619 088",
    "sg:postcode":"3261 LP",
    "sg:province":"Zuid-Holland",
    "wof:name":"Unimark Marking Bv",
    "wof:placetype":"venue"
},
  "geometry": {"coordinates":[4.433588028,51.8254089355],"type":"Point"}
}