{
  "type": "Feature",
  "properties": {
    "iso:country":"NL",
    "sg:address":"Park Weldam 14",
    "sg:city":"Hoevelaken",
    "sg:orig_category":"Glaszetten",
    "sg:phone":"+31 33 253 5012",
    "sg:postcode":"3871 BN",
    "sg:province":"Gelderland",
    "wof:name":"Schildersbedrijf J. Van Der Horst En Klok Bv",
    "wof:placetype":"venue"
},
  "geometry": {"coordinates":[5.450871,52.176708],"type":"Point"}
}