{
  "type": "Feature",
  "properties": {
    "addr:full":"Atjehweg 9 Noordwijk Zh Zuid-Holland 2202 AM",
    "addr:housenumber":"9",
    "addr:postcode":"2202",
    "addr:street":"Atjehweg",
    "iso:country":"NL",
    "sg:address":"Atjehweg 9",
    "sg:city":"Noordwijk Zh",
    "sg:orig_category":"Architecten",
    "sg:phone":"+31 71 361 7200",
    "sg:postcode":"2202 AM",
    "sg:province":"Zuid-Holland",
    "wof:name":"Architectenbureau Van Manen Bv",
    "wof:placetype":"venue"
},
  "geometry": {"coordinates":[4.431356,52.236897],"type":"Point"}
}