{
  "type": "Feature",
  "properties": {
    "addr:full":"Hertenln 37 Den Dolder Utrecht 3734 CE",
    "addr:housenumber":"37",
    "addr:postcode":"3734 ce",
    "addr:street":"Hertenln",
    "iso:country":"NL",
    "sg:address":"Hertenln 37",
    "sg:city":"Den Dolder",
    "sg:orig_category":"Adviesbureaus Bouwkunde",
    "sg:phone":"+31 30 225 1901",
    "sg:postcode":"3734 CE",
    "sg:province":"Utrecht",
    "sg:website":"http://www.vice.nl",
    "wof:name":"Vice International",
    "wof:placetype":"venue"
},
  "geometry": {"coordinates":[5.251625,52.136681],"type":"Point"}
}