{
  "type": "Feature",
  "properties": {
    "addr:full":"Jo Vincentlaan 28 Amstelveen Noord-Holland 1187 HD",
    "addr:housenumber":"28",
    "addr:postcode":"1187 hd",
    "addr:street":"Jo Vincentlaan",
    "iso:country":"NL",
    "sg:address":"Jo Vincentlaan 28",
    "sg:city":"Amstelveen",
    "sg:orig_category":"Geluidsopnamen",
    "sg:phone":"+31 20 647 8915",
    "sg:postcode":"1187 HD",
    "sg:province":"Noord-Holland",
    "wof:name":"Opnamestudio Jan Slabbers",
    "wof:placetype":"venue"
},
  "geometry": {"coordinates":[4.831089,52.286167],"type":"Point"}
}