{
  "type": "Feature",
  "properties": {
    "addr:full":"Erasmusstr 21 Balk Oklahoma 8561 BW",
    "addr:housenumber":"21",
    "addr:postcode":"8561 bw",
    "addr:street":"Erasmusstr",
    "iso:country":"NL",
    "sg:address":"Erasmusstr 21",
    "sg:city":"Balk",
    "sg:orig_category":"Politie",
    "sg:phone":"+31 900 8844",
    "sg:postcode":"8561 BW",
    "sg:province":"Oklahoma",
    "wof:name":"Politie",
    "wof:placetype":"venue"
},
  "geometry": {"coordinates":[-100.82858299999999,36.608829],"type":"Point"}
}