{
  "type": "Feature",
  "properties": {
    "addr:full":"Stedekestr 10A Tilburg North Brabant 5041 DN",
    "addr:housenumber":"10a",
    "addr:postcode":"5041 dn",
    "addr:street":"Stedekestr",
    "iso:country":"NL",
    "sg:address":"Stedekestr 10A",
    "sg:city":"Tilburg",
    "sg:orig_category":"Vertaalbureaus",
    "sg:phone":"+31 13 544 4265",
    "sg:postcode":"5041 DN",
    "sg:province":"North Brabant",
    "sg:website":"http://www.doggersbank-vertalingen.nl",
    "wof:name":"Doggersbank",
    "wof:placetype":"venue"
},
  "geometry": {"coordinates":[5.080436,51.565807],"type":"Point"}
}