{
  "type": "Feature",
  "properties": {
    "iso:country":"NL",
    "sg:address":"Margrietstraat 19",
    "sg:city":"Mierlo",
    "sg:orig_category":"Metaalbekleding And -Behandeling",
    "sg:phone":"+31 492 664 600",
    "sg:postcode":"5731 BM",
    "sg:province":"Noord-Brabant",
    "wof:name":"G. Van Gerven",
    "wof:placetype":"venue"
},
  "geometry": {"coordinates":[5.61792,51.441257],"type":"Point"}
}