{
  "type": "Feature",
  "properties": {
    "addr:full":"Kromme Stg 6A Kapel Avezaath Gelderland 4013 NJ",
    "addr:housenumber":"6a",
    "addr:postcode":"4013 nj",
    "addr:street":"Kromme Stg",
    "iso:country":"NL",
    "sg:address":"Kromme Stg 6A",
    "sg:city":"Kapel Avezaath",
    "sg:orig_category":"Adviesbureaus Bedrijfsorganisatie",
    "sg:phone":"+31 344 661 930",
    "sg:postcode":"4013 NJ",
    "sg:province":"Gelderland",
    "wof:name":"Lodder",
    "wof:placetype":"venue"
},
  "geometry": {"coordinates":[5.380531,51.881023],"type":"Point"}
}