{
  "type": "Feature",
  "properties": {
    "iso:country":"NL",
    "sg:address":"Hoenderkamp 4",
    "sg:city":"Emmen",
    "sg:orig_category":"Autoruiten",
    "sg:phone":"+31 591 659 210",
    "sg:postcode":"7812 VZ",
    "sg:province":"Provincie Drenthe",
    "wof:name":"Autotaalglas",
    "wof:placetype":"venue"
},
  "geometry": {"coordinates":[6.897447,52.771099],"type":"Point"}
}