{
  "type": "Feature",
  "properties": {
    "addr:full":"Denneweg 65 'S Gravenhage Zuid-Holland 2514 CD",
    "addr:housenumber":"65",
    "addr:postcode":"2514 cd",
    "addr:street":"Denneweg;' S",
    "iso:country":"NL",
    "sg:address":"Denneweg 65",
    "sg:city":"'S Gravenhage",
    "sg:orig_category":"Herenmodezaken",
    "sg:phone":"+31 70 363 9809",
    "sg:postcode":"2514 CD",
    "sg:province":"Zuid-Holland",
    "wof:name":"Men Herenmode",
    "wof:placetype":"venue"
},
  "geometry": {"coordinates":[4.311946,52.086048],"type":"Point"}
}