{
  "type": "Feature",
  "properties": {
    "addr:full":"Drieplassenwg 9 Katwyk Zh Zuid-Holland 2225 JH",
    "addr:housenumber":"9",
    "addr:postcode":"2225 jh",
    "addr:street":"Drieplassenwg",
    "iso:country":"NL",
    "sg:address":"Drieplassenwg 9",
    "sg:city":"Katwyk Zh",
    "sg:orig_category":"Kinderkleding",
    "sg:phone":"+31 71 401 7749",
    "sg:postcode":"2225 JH",
    "sg:province":"Zuid-Holland",
    "wof:name":"Hobbelpaardje, 'T",
    "wof:placetype":"venue"
},
  "geometry": {"coordinates":[4.392028,52.199722],"type":"Point"}
}