{
  "type": "Feature",
  "properties": {
    "addr:full":"H Dunantln 86-88 Ryswyk Zh South Holland 2286 GE",
    "addr:housenumber":"86-88",
    "addr:postcode":"2286",
    "addr:street":"Ryswyk Zh",
    "iso:country":"NL",
    "sg:address":"H Dunantln 86-88",
    "sg:city":"Ryswyk Zh",
    "sg:orig_category":"Postkantoren",
    "sg:phone":"+31 70 393 4920",
    "sg:postcode":"2286 GE",
    "sg:province":"South Holland",
    "sg:website":"http://www.postkantoor.nl",
    "wof:name":"Postkantoor",
    "wof:placetype":"venue"
},
  "geometry": {"coordinates":[4.32436,52.037251],"type":"Point"}
}