{
  "type": "Feature",
  "properties": {
    "addr:full":"Bisschopsmolenstraat 91 Etten Leur Noord-Brabant 4876 AJ",
    "addr:housenumber":"91",
    "addr:postcode":"4876 aj",
    "addr:street":"Bisschopsmolenstraat",
    "iso:country":"NL",
    "sg:address":"Bisschopsmolenstraat 91",
    "sg:city":"Etten Leur",
    "sg:orig_category":"Dierenspeciaalzaken",
    "sg:phone":"+31 76 501 5169",
    "sg:postcode":"4876 AJ",
    "sg:province":"Noord-Brabant",
    "wof:name":"Dierenspeciaalzaak Joop Verhoef",
    "wof:placetype":"venue"
},
  "geometry": {"coordinates":[4.636333,51.566502],"type":"Point"}
}