{
  "type": "Feature",
  "properties": {
    "addr:full":"Zeedk 10 Lemmer Friesland 8531 DK",
    "addr:housenumber":"10",
    "addr:postcode":"8531 dk",
    "addr:street":"Zeedk",
    "iso:country":"NL",
    "sg:address":"Zeedk 10",
    "sg:city":"Lemmer",
    "sg:orig_category":"Administratie- En Boekhoudkantoren",
    "sg:phone":"+31 514 533 678",
    "sg:postcode":"8531 DK",
    "sg:province":"Friesland",
    "wof:name":"Jwb Consultancy Bv",
    "wof:placetype":"venue"
},
  "geometry": {"coordinates":[5.719718,52.845432],"type":"Point"}
}