{
  "type": "Feature",
  "properties": {
    "addr:full":"Plompetorengr 18E Utrecht Utrecht 3512 CD",
    "addr:housenumber":"18e",
    "addr:postcode":"3512 cd",
    "addr:street":"Plompetorengr",
    "iso:country":"NL",
    "sg:address":"Plompetorengr 18E",
    "sg:city":"Utrecht",
    "sg:orig_category":"Webdesign Bureaus",
    "sg:phone":"+31 30 230 0030",
    "sg:postcode":"3512 CD",
    "sg:province":"Utrecht",
    "sg:website":"http://www.visualessence.nl",
    "wof:name":"Visual Essence",
    "wof:placetype":"venue"
},
  "geometry": {"coordinates":[5.1233930588,52.096282959],"type":"Point"}
}