{
  "type": "Feature",
  "properties": {
    "addr:full":"Erve Effinck 4 Enter Overijssel 7468 JE",
    "addr:housenumber":"4",
    "addr:postcode":"7468 je",
    "addr:street":"Erve Effinck",
    "iso:country":"NL",
    "sg:address":"Erve Effinck 4",
    "sg:city":"Enter",
    "sg:orig_category":"Afslankinstituten",
    "sg:phone":"+31 547 381 681",
    "sg:postcode":"7468 JE",
    "sg:province":"Overijssel",
    "wof:name":"Jl",
    "wof:placetype":"venue"
},
  "geometry": {"coordinates":[-76.841904,40.463078],"type":"Point"}
}