{
  "type": "Feature",
  "properties": {
    "addr:full":"Kerkeinde 21 Sleeuwyk Noord-Brabant 4254 LD",
    "addr:housenumber":"21",
    "addr:postcode":"4254 ld",
    "addr:street":"Kerkeinde",
    "iso:country":"NL",
    "sg:address":"Kerkeinde 21",
    "sg:city":"Sleeuwyk",
    "sg:classifiers":[
        {
            "category":"Sports & Exercise",
            "subcategory":"Stables",
            "type":"Entertainment"
        }
    ],
    "sg:phone":"+31 183 304 607",
    "sg:postcode":"4254 LD",
    "sg:province":"Noord-Brabant",
    "sg:tags":[
        "maneges"
    ],
    "wof:name":"Hippiesch Centr",
    "wof:placetype":"venue"
},
  "geometry": {"coordinates":[4.938572,51.823166],"type":"Point"}
}