{
  "type": "Feature",
  "properties": {
    "iso:country":"NL",
    "sg:address":"Parkweg 4",
    "sg:city":"De Steeg",
    "sg:classifiers":[
        {
            "category":"Education",
            "subcategory":"Preschool",
            "type":"Public Place"
        }
    ],
    "sg:phone":"+31 26 495 2533",
    "sg:postcode":"6994 CN",
    "sg:province":"Gelderland",
    "sg:tags":[
        "kleuteronderwijs",
        "basis-"
    ],
    "wof:name":"Openbare Basisschool De Lappendeken",
    "wof:placetype":"venue"
},
  "geometry": {"coordinates":[-122.325462,37.915234],"type":"Point"}
}