{
  "type": "Feature",
  "properties": {
    "addr:full":"Noordzydsewg 145 Polsbroek Utrecht 3415 RB",
    "addr:housenumber":"145",
    "addr:postcode":"3415 rb",
    "addr:street":"Polsbroek",
    "iso:country":"NL",
    "sg:address":"Noordzydsewg 145",
    "sg:city":"Polsbroek",
    "sg:orig_category":"Administratie- En Boekhoudkantoren",
    "sg:phone":"+31 182 309 824",
    "sg:postcode":"3415 RB",
    "sg:province":"Utrecht",
    "wof:name":"H & J Bv",
    "wof:placetype":"venue"
},
  "geometry": {"coordinates":[4.872839,51.984997],"type":"Point"}
}