{
  "type": "Feature",
  "properties": {
    "addr:full":"Graafland 32 Laren Nh Noord-Holland 1251 NJ",
    "addr:housenumber":"32",
    "addr:postcode":"1251 nj",
    "addr:street":"Graafland",
    "iso:country":"NL",
    "sg:address":"Graafland 32",
    "sg:city":"Laren Nh",
    "sg:orig_category":"Verzekeringen - Verzekeringskantoren",
    "sg:phone":"+31 35 538 4201",
    "sg:postcode":"1251 NJ",
    "sg:province":"Noord-Holland",
    "wof:name":"Suttorp",
    "wof:placetype":"venue"
},
  "geometry": {"coordinates":[5.2401428223,52.2536811829],"type":"Point"}
}