{
  "type": "Feature",
  "properties": {
    "addr:full":"Boswg 6 Wyk Aan Zee North Holland 1949 AZ",
    "addr:housenumber":"6",
    "addr:postcode":"1949 az",
    "addr:street":"Boswg",
    "iso:country":"NL",
    "sg:address":"Boswg 6",
    "sg:city":"Wyk Aan Zee",
    "sg:orig_category":"Havenbedrijven",
    "sg:phone":"+31 251 375 409",
    "sg:postcode":"1949 AZ",
    "sg:province":"North Holland",
    "wof:name":"Holst, W",
    "wof:placetype":"venue"
},
  "geometry": {"coordinates":[4.594696,52.491993],"type":"Point"}
}