{
  "type": "Feature",
  "properties": {
    "addr:full":"Oude Haagwg 126 S Gravenhage Zuid-Holland 2552 GS",
    "addr:housenumber":"126;gravenhage",
    "addr:postcode":"2552 gs",
    "addr:street":"Oude Haagwg;S",
    "iso:country":"NL",
    "sg:address":"Oude Haagwg 126",
    "sg:city":"S Gravenhage",
    "sg:orig_category":"Acupunctuur",
    "sg:phone":"+31 70 397 6593",
    "sg:postcode":"2552 GS",
    "sg:province":"Zuid-Holland",
    "wof:name":"Hulbert, R A",
    "wof:placetype":"venue"
},
  "geometry": {"coordinates":[4.24958,52.053631],"type":"Point"}
}