{
  "type": "Feature",
  "properties": {
    "addr:full":"Stationsstraat 36 Alphen A/D Rijn South Holland 2405 BN",
    "addr:housenumber":"36",
    "addr:postcode":"2405 bn",
    "addr:street":"Stationsstraat",
    "iso:country":"NL",
    "sg:address":"Stationsstraat 36",
    "sg:city":"Alphen A/D Rijn",
    "sg:orig_category":"Werving And Selectie Van Vast Personeel",
    "sg:phone":"+31 172 426 088",
    "sg:postcode":"2405 BN",
    "sg:province":"South Holland",
    "wof:name":"Primera",
    "wof:placetype":"venue"
},
  "geometry": {"coordinates":[4.6600251198,52.1255264282],"type":"Point"}
}