{
  "type": "Feature",
  "properties": {
    "addr:full":"Witherenstraat 27 Ter Apel Groningen 9561 KK",
    "addr:housenumber":"27",
    "addr:postcode":"9561 kk",
    "addr:street":"Witherenstraat",
    "iso:country":"NL",
    "sg:address":"Witherenstraat 27",
    "sg:city":"Ter Apel",
    "sg:orig_category":"Banken And Kredietinstellingen",
    "sg:phone":"+31 599 587 555",
    "sg:postcode":"9561 KK",
    "sg:province":"Groningen",
    "wof:name":"Regiobank/Assurantiekantoor Foekens",
    "wof:placetype":"venue"
},
  "geometry": {"coordinates":[7.06241,52.875542],"type":"Point"}
}