{
  "type": "Feature",
  "properties": {
    "addr:full":"Hoofdstraat 18 Noordwijk Zh Zuid-Holland 2202 GD",
    "addr:housenumber":"18",
    "addr:postcode":"2202 gd",
    "addr:street":"Hoofdstraat",
    "iso:country":"NL",
    "sg:address":"Hoofdstraat 18",
    "sg:city":"Noordwijk Zh",
    "sg:orig_category":"Bloemen And Planten",
    "sg:phone":"+31 71 361 7880",
    "sg:postcode":"2202 GD",
    "sg:province":"Zuid-Holland",
    "wof:name":"Garde N House",
    "wof:placetype":"venue"
},
  "geometry": {"coordinates":[4.434493,52.242977],"type":"Point"}
}