{
  "type": "Feature",
  "properties": {
    "addr:full":"Pynswg 91 Heerlen Limburg 6419 CK",
    "addr:housenumber":"91",
    "addr:postcode":"6419 ck",
    "addr:street":"Pynswg",
    "iso:country":"NL",
    "sg:address":"Pynswg 91",
    "sg:city":"Heerlen",
    "sg:orig_category":"Makelaars En Adviseurs Onroerende Goederen",
    "sg:phone":"+31 45 579 0469",
    "sg:postcode":"6419 CK",
    "sg:province":"Limburg",
    "sg:website":"http://www.leobeckers.nl",
    "wof:name":"Beckers, L",
    "wof:placetype":"venue"
},
  "geometry": {"coordinates":[5.969387,50.877552],"type":"Point"}
}