{
  "type": "Feature",
  "properties": {
    "addr:full":"Kanonstr 36 Utrecht Utrecht 3531 BM",
    "addr:housenumber":"36",
    "addr:postcode":"3531 bm",
    "addr:street":"Kanonstr",
    "iso:country":"NL",
    "sg:address":"Kanonstr 36",
    "sg:city":"Utrecht",
    "sg:orig_category":"Elektrotechnische Artikelen",
    "sg:phone":"+31 30 299 9900",
    "sg:postcode":"3531 BM",
    "sg:province":"Utrecht",
    "sg:website":"http://www.littelfuse.com",
    "wof:name":"Littelfuse Bv",
    "wof:placetype":"venue"
},
  "geometry": {"coordinates":[5.104448,52.091911],"type":"Point"}
}