{
  "type": "Feature",
  "properties": {
    "iso:country":"NL",
    "sg:address":"Schiedamseweg 155A",
    "sg:city":"Rotterdam",
    "sg:classifiers":[
        {
            "category":"Bakery",
            "type":"Food & Drink"
        }
    ],
    "sg:phone":"+31 10 476 3590",
    "sg:postcode":"3026 AK",
    "sg:province":"Zuid-Holland",
    "sg:tags":[
        "brood",
        "banket"
    ],
    "wof:name":"Kees Vd Berg Beheer Bv",
    "wof:placetype":"venue"
},
  "geometry": {"coordinates":[4.441001,51.911098],"type":"Point"}
}