{
  "type": "Feature",
  "properties": {
    "addr:full":"Postbus 426 Heemstede Noord-Holland 2100 AK",
    "addr:housenumber":"426",
    "addr:postcode":"2100 ak",
    "addr:street":"Postbus",
    "iso:country":"NL",
    "sg:address":"Postbus 426",
    "sg:city":"Heemstede",
    "sg:orig_category":"Adviesbureaus Bedrijfsorganisatie",
    "sg:phone":"+31 23 547 1956",
    "sg:postcode":"2100 AK",
    "sg:province":"Noord-Holland",
    "sg:website":"http://www.maomtd.nl",
    "wof:name":"Mao/Mtd Groep",
    "wof:placetype":"venue"
},
  "geometry": {"coordinates":[4.621248,52.345287],"type":"Point"}
}