{
  "type": "Feature",
  "properties": {
    "addr:full":"Bontemorgen 1 Lienden Gelderland 4033 CV",
    "addr:housenumber":"1",
    "addr:postcode":"4033 cv",
    "addr:street":"Bontemorgen;Gelderland",
    "iso:country":"NL",
    "sg:address":"Bontemorgen 1",
    "sg:city":"Lienden",
    "sg:orig_category":"Bedrijfs- And Managementsconsultants",
    "sg:phone":"+31 344 604 047",
    "sg:postcode":"4033 CV",
    "sg:province":"Gelderland",
    "wof:name":"Buro Pragmatica",
    "wof:placetype":"venue"
},
  "geometry": {"coordinates":[5.521699,51.964706],"type":"Point"}
}