{
  "type": "Feature",
  "properties": {
    "addr:full":"Groenstr 114 Geleen Limburg 6162 ES",
    "addr:housenumber":"114",
    "addr:postcode":"6162 es",
    "addr:street":"Geleen Limburg",
    "iso:country":"NL",
    "sg:address":"Groenstr 114",
    "sg:city":"Geleen",
    "sg:orig_category":"Fietsen En Bromfietsen",
    "sg:phone":"+31 46 474 3290",
    "sg:postcode":"6162 ES",
    "sg:province":"Limburg",
    "wof:name":"Horsels, J",
    "wof:placetype":"venue"
},
  "geometry": {"coordinates":[5.828066,50.972763],"type":"Point"}
}