{
  "type": "Feature",
  "properties": {
    "iso:country":"NL",
    "sg:address":"Expansie 19A",
    "sg:city":"Marknesse",
    "sg:orig_category":"Natuurvoeding En Reformartikelen - Fabrieken En Groothandel",
    "sg:phone":"+31 527 651 994",
    "sg:postcode":"8316 GB",
    "sg:province":"Flevoland",
    "wof:name":"Fitline Ned",
    "wof:placetype":"venue"
},
  "geometry": {"coordinates":[5.871181,52.70969],"type":"Point"}
}