{
  "type": "Feature",
  "properties": {
    "addr:full":"Kleine N 47 Hoorn Nh Noord-Holland 1621 JE",
    "addr:housenumber":"47",
    "addr:postcode":"1621 je",
    "addr:street":"Kleine N",
    "iso:country":"NL",
    "sg:address":"Kleine N 47",
    "sg:city":"Hoorn Nh",
    "sg:classifiers":[
        {
            "category":"Utilities",
            "subcategory":"Cable",
            "type":"Services"
        }
    ],
    "sg:phone":"+31 229 212 812",
    "sg:postcode":"1621 JE",
    "sg:province":"Noord-Holland",
    "sg:tags":[
        "masseur",
        "en",
        "heilgymnasten"
    ],
    "wof:name":"Pondman, C",
    "wof:placetype":"venue"
},
  "geometry": {"coordinates":[5.052602,52.6436],"type":"Point"}
}