{
  "type": "Feature",
  "properties": {
    "iso:country":"NL",
    "sg:address":"Rabelingstraat 3",
    "sg:city":"Silvolde",
    "sg:orig_category":"Auto'S And Voertuigen",
    "sg:phone":"+31 315 324 087",
    "sg:postcode":"7064 KG",
    "sg:province":"Gelderland",
    "wof:name":"Autobedrijf Te Kaat Bv",
    "wof:placetype":"venue"
},
  "geometry": {"coordinates":[6.396434,51.912571],"type":"Point"}
}