{
  "type": "Feature",
  "properties": {
    "iso:country":"NL",
    "sg:address":"Dorpsstr 27",
    "sg:city":"Uffelte",
    "sg:classifiers":[
        {
            "category":"Travel",
            "subcategory":"Hotels & Motels",
            "type":"Entertainment"
        }
    ],
    "sg:phone":"+31 521 351 766",
    "sg:postcode":"7975 AN",
    "sg:province":"Provincie Drenthe",
    "wof:name":"Roskam, De",
    "wof:placetype":"venue"
},
  "geometry": {"coordinates":[6.276371,52.790417],"type":"Point"}
}