{
  "type": "Feature",
  "properties": {
    "addr:full":"Russenpln 8 Bergen Nh Noord-Holland 1861 JR",
    "addr:housenumber":"8",
    "addr:postcode":"1861 jr",
    "addr:street":"Russenpln",
    "iso:country":"NL",
    "sg:address":"Russenpln 8",
    "sg:city":"Bergen Nh",
    "sg:orig_category":"Adviesbureaus",
    "sg:phone":"+31 72 581 7774",
    "sg:postcode":"1861 JR",
    "sg:province":"Noord-Holland",
    "wof:name":"Thomsen, Prof Ing A F",
    "wof:placetype":"venue"
},
  "geometry": {"coordinates":[4.70126,52.67168],"type":"Point"}
}