{
  "type": "Feature",
  "properties": {
    "addr:full":"Weverstraat 3 Goirle North Brabant 5051 HZ",
    "addr:housenumber":"3",
    "addr:postcode":"5051 hz",
    "addr:street":"Weverstraat",
    "iso:country":"NL",
    "sg:address":"Weverstraat 3",
    "sg:city":"Goirle",
    "sg:orig_category":"Meubelzaken, Woning- And Keukeninrichting",
    "sg:phone":"+31 13 534 2524",
    "sg:postcode":"5051 HZ",
    "sg:province":"North Brabant",
    "wof:name":"Van Beurden Meubelen Cv",
    "wof:placetype":"venue"
},
  "geometry": {"coordinates":[5.0566139221,51.5135383606],"type":"Point"}
}