{
  "type": "Feature",
  "properties": {
    "addr:full":"Nw Hemwg 7E-7F Amsterdam Noord-Holland 1013 BG",
    "addr:postcode":"1013",
    "addr:street":"7E-7F",
    "iso:country":"NL",
    "sg:address":"Nw Hemwg 7E-7F",
    "sg:city":"Amsterdam",
    "sg:orig_category":"Boeken En Tijdschriften - Groothandel",
    "sg:phone":"+31 20 684 0566",
    "sg:postcode":"1013 BG",
    "sg:province":"Noord-Holland",
    "wof:name":"Raadsel, Het",
    "wof:placetype":"venue"
},
  "geometry": {"coordinates":[4.868172,52.394447],"type":"Point"}
}