{
  "type": "Feature",
  "properties": {
    "addr:full":"Taylorstr 1B Son Noord-Brabant 5691 CH",
    "addr:housenumber":"1b",
    "addr:postcode":"5691",
    "addr:street":"Taylorstr",
    "iso:country":"NL",
    "sg:address":"Taylorstr 1B",
    "sg:city":"Son",
    "sg:orig_category":"Fitnesscentra",
    "sg:phone":"+31 499 477 234",
    "sg:postcode":"5691 CH",
    "sg:province":"Noord-Brabant",
    "wof:name":"Fitnesscentr Son",
    "wof:placetype":"venue"
},
  "geometry": {"coordinates":[-101.937622,35.189621],"type":"Point"}
}