{
  "type": "Feature",
  "properties": {
    "addr:full":"Kelvinstraat 16 Didam Gelderland 6942 RD",
    "addr:housenumber":"16",
    "addr:postcode":"6942",
    "addr:street":"Kelvinstraat;Gelderland;Rd",
    "iso:country":"NL",
    "sg:address":"Kelvinstraat 16",
    "sg:city":"Didam",
    "sg:orig_category":"Metaalbekleding And -Behandeling",
    "sg:phone":"+31 316 581 440",
    "sg:postcode":"6942 RD",
    "sg:province":"Gelderland",
    "wof:name":"Vels Bv",
    "wof:placetype":"venue"
},
  "geometry": {"coordinates":[6.128348,51.936817],"type":"Point"}
}