{
  "type": "Feature",
  "properties": {
    "addr:full":"Grt Oord 15 Arnhem Gelderland 6811 GA",
    "addr:housenumber":"15",
    "addr:postcode":"6811 ga",
    "addr:street":"Oord",
    "iso:country":"NL",
    "sg:address":"Grt Oord 15",
    "sg:city":"Arnhem",
    "sg:orig_category":"Boeken En Tijdschriften",
    "sg:phone":"+31 26 442 4938",
    "sg:postcode":"6811 GA",
    "sg:province":"Gelderland",
    "wof:name":"Hijman",
    "wof:placetype":"venue"
},
  "geometry": {"coordinates":[5.906225,51.981827],"type":"Point"}
}