{
  "type": "Feature",
  "properties": {
    "addr:full":"Gen Cronjestr 152 Haarlem Noord-Holland 2021 JN",
    "addr:housenumber":"152",
    "addr:postcode":"2021 jn",
    "iso:country":"NL",
    "sg:address":"Gen Cronjestr 152",
    "sg:city":"Haarlem",
    "sg:orig_category":"Gelegenheidskleding",
    "sg:phone":"+31 23 526 6167",
    "sg:postcode":"2021 JN",
    "sg:province":"Noord-Holland",
    "wof:name":"Devotion",
    "wof:placetype":"venue"
},
  "geometry": {"coordinates":[4.642571,52.395634],"type":"Point"}
}