{
  "type": "Feature",
  "properties": {
    "iso:country":"NL",
    "sg:address":"O V Noortstr 5",
    "sg:city":"Hillegom",
    "sg:orig_category":"Bloembollen - Groothandel",
    "sg:phone":"+31 252 518 528",
    "sg:postcode":"2182 AE",
    "sg:province":"North Holland",
    "wof:name":"Hermans Bv, G H",
    "wof:placetype":"venue"
},
  "geometry": {"coordinates":[4.578603,52.290993],"type":"Point"}
}