{
  "type": "Feature",
  "properties": {
    "addr:full":"Noordeinde 144 Oostzaan Noord-Holland 1511 AH",
    "addr:housenumber":"144",
    "addr:postcode":"1511 ah",
    "addr:street":"Noordeinde",
    "iso:country":"NL",
    "sg:address":"Noordeinde 144",
    "sg:city":"Oostzaan",
    "sg:orig_category":"Bloemen En Planten - Decoratie",
    "sg:phone":"+31 75 684 8485",
    "sg:postcode":"1511 AH",
    "sg:province":"Noord-Holland",
    "wof:name":"Season Flowers",
    "wof:placetype":"venue"
},
  "geometry": {"coordinates":[4.868821,52.453705],"type":"Point"}
}