{
  "type": "Feature",
  "properties": {
    "iso:country":"NL",
    "sg:address":"Markt 28",
    "sg:city":"Kerkrade",
    "sg:orig_category":"Opticiens",
    "sg:phone":"+31 45 545 2618",
    "sg:postcode":"6461 EC",
    "sg:province":"Limburg",
    "sg:website":"http://www.goudengids.nl",
    "wof:name":"Bemelmans, Optiek",
    "wof:placetype":"venue"
},
  "geometry": {"coordinates":[6.0628399849,50.8654136658],"type":"Point"}
}