{
  "type": "Feature",
  "properties": {
    "iso:country":"NL",
    "sg:address":"Eikvaren 28",
    "sg:city":"Bilthoven",
    "sg:orig_category":"Ongediertebestrijding En Ontsmetting",
    "sg:phone":"+31 30 228 4222",
    "sg:postcode":"3723 TJ",
    "sg:province":"Utrecht",
    "wof:name":"Bos Wespenbestrijding, J",
    "wof:placetype":"venue"
},
  "geometry": {"coordinates":[5.187172,52.131405],"type":"Point"}
}