{
  "type": "Feature",
  "properties": {
    "addr:full":"E Strouvenln 55 Maastricht Limburg 6214 AX",
    "addr:housenumber":"55",
    "addr:postcode":"6214 ax",
    "iso:country":"NL",
    "sg:address":"E Strouvenln 55",
    "sg:city":"Maastricht",
    "sg:orig_category":"Horloges En Klokken Fournituren - Fabr. En Grooth",
    "sg:phone":"+31 43 321 5000",
    "sg:postcode":"6214 AX",
    "sg:province":"Limburg",
    "wof:name":"Christal",
    "wof:placetype":"venue"
},
  "geometry": {"coordinates":[5.67913,50.845001],"type":"Point"}
}