{
  "type": "Feature",
  "properties": {
    "addr:full":"Beekstr 32 Nuenen Noord-Brabant 5673 NA",
    "addr:housenumber":"32",
    "addr:postcode":"5673 na",
    "addr:street":"Beekstr",
    "iso:country":"NL",
    "sg:address":"Beekstr 32",
    "sg:city":"Nuenen",
    "sg:orig_category":"Webdesign Bureaus",
    "sg:phone":"+31 40 206 5696",
    "sg:postcode":"5673 NA",
    "sg:province":"Noord-Brabant",
    "sg:website":"http://www.at-cetera.nl",
    "wof:name":"At Cetera",
    "wof:placetype":"venue"
},
  "geometry": {"coordinates":[5.5590639114,51.4754447937],"type":"Point"}
}