{
  "type": "Feature",
  "properties": {
    "addr:full":"Barneveldsewg 2 Otterlo Gelderland 6731 EK",
    "addr:housenumber":"2",
    "addr:postcode":"6731 ek",
    "addr:street":"Barneveldsewg;Gelderland",
    "iso:country":"NL",
    "sg:address":"Barneveldsewg 2",
    "sg:city":"Otterlo",
    "sg:classifiers":[
        {
            "category":"Retail",
            "subcategory":"Auto Repair",
            "type":"Services"
        }
    ],
    "sg:phone":"+31 318 591 057",
    "sg:postcode":"6731 EK",
    "sg:province":"Gelderland",
    "sg:tags":[
        "garage"
    ],
    "wof:name":"Groeneveld, Evert",
    "wof:placetype":"venue"
},
  "geometry": {"coordinates":[5.759205,52.102962],"type":"Point"}
}