{
  "type": "Feature",
  "properties": {
    "iso:country":"NL",
    "sg:address":"Weimarstraat 180",
    "sg:city":"'S Gravenhage",
    "sg:orig_category":"Meubelzaken, Woning- And Keukeninrichting",
    "sg:phone":"+31 70 346 9495",
    "sg:postcode":"2562 HP",
    "sg:province":"South Holland",
    "wof:name":"Epskamp Slaapwarenhuis Bv",
    "wof:placetype":"venue"
},
  "geometry": {"coordinates":[4.280181,52.07513],"type":"Point"}
}