{
  "type": "Feature",
  "properties": {
    "iso:country":"NL",
    "sg:address":"Volkerakstr 32",
    "sg:city":"S Gravenhage",
    "sg:orig_category":"Behangers",
    "sg:phone":"+31 70 389 3409",
    "sg:postcode":"2595 VE",
    "sg:province":"Zuid-Holland",
    "wof:name":"Nieuwkoop & Van Leeuwen",
    "wof:placetype":"venue"
},
  "geometry": {"coordinates":[4.33507,52.081421],"type":"Point"}
}