{
  "type": "Feature",
  "properties": {
    "addr:full":"Zuiderdk 16 Venhuizen Minas Gerais 1606 MG",
    "addr:housenumber":"16",
    "addr:postcode":"1606 mg",
    "addr:street":"Zuiderdk",
    "iso:country":"NL",
    "sg:address":"Zuiderdk 16",
    "sg:city":"Venhuizen",
    "sg:orig_category":"Lasbedrijven",
    "sg:phone":"+31 6 20600411",
    "sg:postcode":"1606 MG",
    "sg:province":"Minas Gerais",
    "wof:name":"Breedijk, J",
    "wof:placetype":"venue"
},
  "geometry": {"coordinates":[-45.451351,-18.57752],"type":"Point"}
}