{
  "type": "Feature",
  "properties": {
    "addr:full":"Gasthuisdijk 8 Zwolle Overijssel 8041 AG",
    "addr:housenumber":"8",
    "addr:postcode":"8041",
    "addr:street":"Gasthuisdijk",
    "iso:country":"NL",
    "sg:address":"Gasthuisdijk 8",
    "sg:city":"Zwolle",
    "sg:classifiers":[
        {
            "category":"Bakery",
            "type":"Food & Drink"
        }
    ],
    "sg:phone":"+31 38 421 6665",
    "sg:postcode":"8041 AG",
    "sg:province":"Overijssel",
    "sg:tags":[
        "brood",
        "banket"
    ],
    "wof:name":"Vof Lindeboom",
    "wof:placetype":"venue"
},
  "geometry": {"coordinates":[6.074756,52.517601],"type":"Point"}
}