{
  "type": "Feature",
  "properties": {
    "addr:full":"De Rijf 9 Malden Gelderland 6581 VA",
    "addr:housenumber":"9",
    "addr:postcode":"6581",
    "addr:street":"De Rijf;Gelderland",
    "iso:country":"NL",
    "sg:address":"De Rijf 9",
    "sg:city":"Malden",
    "sg:orig_category":"Kinderopvang Behalve Thuis",
    "sg:phone":"+31 24 358 7155",
    "sg:postcode":"6581 VA",
    "sg:province":"Gelderland",
    "wof:name":"Stichting Kinderopvang Regio Nijmegen",
    "wof:placetype":"venue"
},
  "geometry": {"coordinates":[5.85937,51.776886],"type":"Point"}
}