{
  "type": "Feature",
  "properties": {
    "addr:full":"Beneden Dwarsdiep 17A Veendam Groningen 9645 LA",
    "addr:housenumber":"17a",
    "addr:postcode":"9645 la",
    "addr:street":"Beneden Dwarsdiep",
    "iso:country":"NL",
    "sg:address":"Beneden Dwarsdiep 17A",
    "sg:city":"Veendam",
    "sg:orig_category":"Onderhoudswerken",
    "sg:phone":"+31 598 622 094",
    "sg:postcode":"9645 LA",
    "sg:province":"Groningen",
    "wof:name":"Martena Klus- En Timmerbedrijf",
    "wof:placetype":"venue"
},
  "geometry": {"coordinates":[6.88814,53.119419],"type":"Point"}
}