{
  "type": "Feature",
  "properties": {
    "iso:country":"NL",
    "sg:address":"Eibersburen 3",
    "sg:city":"Lutjegast",
    "sg:orig_category":"Product-Promotie",
    "sg:phone":"+31 594 249 037",
    "sg:postcode":"9866 TH",
    "sg:province":"Groningen",
    "wof:name":"Terpstra",
    "wof:placetype":"venue"
},
  "geometry": {"coordinates":[6.270579,53.244892],"type":"Point"}
}