{
  "type": "Feature",
  "properties": {
    "addr:full":"Beyerlandseln 119A Rotterdam Zuid-Holland 3074 ED",
    "addr:housenumber":"119a",
    "addr:postcode":"3074 ed",
    "iso:country":"NL",
    "sg:address":"Beyerlandseln 119A",
    "sg:city":"Rotterdam",
    "sg:classifiers":[
        {
            "category":"Food & Beverages",
            "subcategory":"Bakery",
            "type":"Retail Goods"
        }
    ],
    "sg:phone":"+31 10 486 1425",
    "sg:postcode":"3074 ED",
    "sg:province":"Zuid-Holland",
    "sg:tags":[
        "pizza"
    ],
    "wof:name":"Aris",
    "wof:placetype":"venue"
},
  "geometry": {"coordinates":[4.51149,51.89608],"type":"Point"}
}