{
  "type": "Feature",
  "properties": {
    "addr:full":"Ooststr 43 Oud Beyerland Zuid-Holland 3261 KM",
    "addr:housenumber":"43",
    "addr:postcode":"3261 km",
    "addr:street":"Ooststr;Oud Beyerland",
    "iso:country":"NL",
    "sg:address":"Ooststr 43",
    "sg:city":"Oud Beyerland",
    "sg:orig_category":"Juweliers",
    "sg:phone":"+31 186 620 609",
    "sg:postcode":"3261 KM",
    "sg:province":"Zuid-Holland",
    "wof:name":"Es, Frank Van",
    "wof:placetype":"venue"
},
  "geometry": {"coordinates":[4.413633,51.82653],"type":"Point"}
}