{
  "type": "Feature",
  "properties": {
    "addr:full":"Berliozstr 9 Maassluis South Holland 3144 KA",
    "addr:housenumber":"9",
    "addr:postcode":"3144 ka",
    "addr:street":"Berliozstr",
    "iso:country":"NL",
    "sg:address":"Berliozstr 9",
    "sg:city":"Maassluis",
    "sg:orig_category":"Kantoormachines",
    "sg:phone":"+31 10 591 5581",
    "sg:postcode":"3144 KA",
    "sg:province":"South Holland",
    "wof:name":"Javal",
    "wof:placetype":"venue"
},
  "geometry": {"coordinates":[4.2393808365,51.9251251221],"type":"Point"}
}