{
  "type": "Feature",
  "properties": {
    "addr:full":"Haagwg 190 Leiden Zuid-Holland 2324 NA",
    "addr:housenumber":"190",
    "addr:postcode":"2324 na",
    "iso:country":"NL",
    "sg:address":"Haagwg 190",
    "sg:city":"Leiden",
    "sg:classifiers":[
        {
            "category":"Utilities",
            "subcategory":"Cable",
            "type":"Services"
        }
    ],
    "sg:phone":"+31 71 576 3358",
    "sg:postcode":"2324 NA",
    "sg:province":"Zuid-Holland",
    "sg:tags":[
        "masseur",
        "en",
        "heilgymnasten"
    ],
    "wof:name":"Blue Heaven",
    "wof:placetype":"venue"
},
  "geometry": {"coordinates":[4.468998,52.153133],"type":"Point"}
}