{
  "type": "Feature",
  "properties": {
    "addr:full":"Meervlietstraat 73 Velsen-Zuid Noord-Holland 1981 BK",
    "addr:housenumber":"73",
    "addr:postcode":"1981 bk",
    "addr:street":"Meervlietstraat",
    "iso:country":"NL",
    "sg:address":"Meervlietstraat 73",
    "sg:city":"Velsen-Zuid",
    "sg:orig_category":"Bedrijfs- And Managementsconsultants",
    "sg:phone":"+31 255 510 732",
    "sg:postcode":"1981 BK",
    "sg:province":"Noord-Holland",
    "wof:name":"Adviesbureau Van Den Brink Bv",
    "wof:placetype":"venue"
},
  "geometry": {"coordinates":[4.648212,52.460629],"type":"Point"}
}