{
  "type": "Feature",
  "properties": {
    "addr:full":"Vlotgras 48 Spykenisse South Holland 3206 SN",
    "addr:housenumber":"48",
    "addr:postcode":"3206 sn",
    "addr:street":"Vlotgras",
    "iso:country":"NL",
    "sg:address":"Vlotgras 48",
    "sg:city":"Spykenisse",
    "sg:orig_category":"Begrafenisverzorging",
    "sg:phone":"+31 181 673 043",
    "sg:postcode":"3206 SN",
    "sg:province":"South Holland",
    "wof:name":"Pengel",
    "wof:placetype":"venue"
},
  "geometry": {"coordinates":[4.322524,51.827747],"type":"Point"}
}