{
  "type": "Feature",
  "properties": {
    "addr:full":"Rietdk 6A Rotterdam Zuid-Holland 3082 DS",
    "addr:housenumber":"6a",
    "addr:postcode":"3082 ds",
    "addr:street":"Rietdk",
    "iso:country":"NL",
    "sg:address":"Rietdk 6A",
    "sg:city":"Rotterdam",
    "sg:orig_category":"Kappers",
    "sg:phone":"+31 10 495 6737",
    "sg:postcode":"3082 DS",
    "sg:province":"Zuid-Holland",
    "sg:website":"http://www.fantasy.nl",
    "wof:name":"Fantasy",
    "wof:placetype":"venue"
},
  "geometry": {"coordinates":[4.4641418457,51.8925971985],"type":"Point"}
}