{
  "type": "Feature",
  "properties": {
    "addr:full":"Poortln 20 Wassenaar Zuid-Holland 2242 GN",
    "addr:housenumber":"20",
    "addr:postcode":"2242 gn",
    "addr:street":"Poortln",
    "iso:country":"NL",
    "sg:address":"Poortln 20",
    "sg:city":"Wassenaar",
    "sg:orig_category":"Bejaarden - Verzorgingstehuizen",
    "sg:phone":"+31 70 512 3200",
    "sg:postcode":"2242 GN",
    "sg:province":"Zuid-Holland",
    "wof:name":"Willibrord, Sticht Beheer Huize",
    "wof:placetype":"venue"
},
  "geometry": {"coordinates":[4.393863,52.14307],"type":"Point"}
}