{
  "type": "Feature",
  "properties": {
    "iso:country":"NL",
    "sg:address":"Strawinskylaan 1201",
    "sg:city":"Amsterdam",
    "sg:orig_category":"Voeding, Dranken And Tabak Gh",
    "sg:phone":"+31 20 664 8991",
    "sg:postcode":"1077 XX",
    "sg:province":"Noord-Holland",
    "wof:name":"F. Byvoet International Bv",
    "wof:placetype":"venue"
},
  "geometry": {"coordinates":[4.874113,52.340645],"type":"Point"}
}