{
  "type": "Feature",
  "properties": {
    "addr:full":"Westerstraat 115 Enkhuizen Noord-Holland 1601 AD",
    "addr:housenumber":"115",
    "addr:postcode":"1601 ad",
    "addr:street":"Westerstraat",
    "iso:country":"NL",
    "sg:address":"Westerstraat 115",
    "sg:city":"Enkhuizen",
    "sg:orig_category":"Kappers",
    "sg:phone":"+31 228 312 150",
    "sg:postcode":"1601 AD",
    "sg:province":"Noord-Holland",
    "wof:name":"Salon Charme",
    "wof:placetype":"venue"
},
  "geometry": {"coordinates":[5.287772,52.703373],"type":"Point"}
}