{
  "type": "Feature",
  "properties": {
    "addr:full":"Grt Visserystr 23B Rotterdam Zuid-Holland 3026 CB",
    "addr:housenumber":"23b",
    "addr:postcode":"3026 cb",
    "iso:country":"NL",
    "sg:address":"Grt Visserystr 23B",
    "sg:city":"Rotterdam",
    "sg:orig_category":"Juweliers",
    "sg:phone":"+31 10 262 2815",
    "sg:postcode":"3026 CB",
    "sg:province":"Zuid-Holland",
    "wof:name":"Goldshop, The",
    "wof:placetype":"venue"
},
  "geometry": {"coordinates":[4.442489,51.915371],"type":"Point"}
}