{
  "type": "Feature",
  "properties": {
    "iso:country":"NL",
    "sg:address":"Meyenhage 312- 314",
    "sg:city":"Rotterdam",
    "sg:orig_category":"Fietshandelaren",
    "sg:phone":"+31 900 7002917",
    "sg:postcode":"3085 CH",
    "sg:province":"South Holland",
    "wof:name":"Cyclecenter Slinge Bv",
    "wof:placetype":"venue"
},
  "geometry": {"coordinates":[4.484337,51.874519],"type":"Point"}
}