{
  "type": "Feature",
  "properties": {
    "addr:full":"De Trompet 2960 Heemskerk North Holland 1967 DD",
    "addr:housenumber":"2960",
    "addr:postcode":"1967 dd",
    "addr:street":"De Trompet",
    "iso:country":"NL",
    "sg:address":"De Trompet 2960",
    "sg:city":"Heemskerk",
    "sg:orig_category":"Accountants - Administratie- Consulenten En -Kantoren",
    "sg:phone":"+31 251 234 820",
    "sg:postcode":"1967 DD",
    "sg:province":"North Holland",
    "wof:name":"Acker, Van Den",
    "wof:placetype":"venue"
},
  "geometry": {"coordinates":[4.701124,52.50378],"type":"Point"}
}