{
  "type": "Feature",
  "properties": {
    "addr:full":"Zandoerle 2 Veldhoven North Brabant 5507 RK",
    "addr:housenumber":"2",
    "addr:postcode":"5507 rk",
    "addr:street":"Zandoerle",
    "iso:country":"NL",
    "sg:address":"Zandoerle 2",
    "sg:city":"Veldhoven",
    "sg:orig_category":"Fotojournalisten Freelance",
    "sg:phone":"+31 40 205 5025",
    "sg:postcode":"5507 RK",
    "sg:province":"North Brabant",
    "wof:name":"Keeris, Hennie",
    "wof:placetype":"venue"
},
  "geometry": {"coordinates":[5.358795,51.413609],"type":"Point"}
}