{
  "type": "Feature",
  "properties": {
    "addr:full":"C Beersmansstr 4D Rotterdam South Holland 3025 EE",
    "addr:housenumber":"4d",
    "addr:postcode":"3025 ee",
    "iso:country":"NL",
    "sg:address":"C Beersmansstr 4D",
    "sg:city":"Rotterdam",
    "sg:orig_category":"Webdesign Bureaus",
    "sg:phone":"+31 10 244 0163",
    "sg:postcode":"3025 EE",
    "sg:province":"South Holland",
    "sg:website":"http://www.smudge.nl",
    "wof:name":"Smudge",
    "wof:placetype":"venue"
},
  "geometry": {"coordinates":[4.4446277618,51.9092063904],"type":"Point"}
}