{
  "type": "Feature",
  "properties": {
    "iso:country":"NL",
    "sg:address":"Kr Weele 21-23",
    "sg:city":"Middelburg",
    "sg:orig_category":"Woninginrichting",
    "sg:phone":"+31 118 614 077",
    "sg:postcode":"4331 PA",
    "sg:province":"Zeeland",
    "sg:website":"http://www.mulderbinnenhuis.nl",
    "wof:name":"Mulder Binnenhuis",
    "wof:placetype":"venue"
},
  "geometry": {"coordinates":[3.6080269814,51.4990119934],"type":"Point"}
}