{
  "type": "Feature",
  "properties": {
    "addr:full":"Bisschopsmolenstraat 92 Etten-Leur North Brabant 4876 AP",
    "addr:housenumber":"92",
    "addr:postcode":"4876 ap",
    "addr:street":"Bisschopsmolenstraat",
    "iso:country":"NL",
    "sg:address":"Bisschopsmolenstraat 92",
    "sg:city":"Etten-Leur",
    "sg:orig_category":"Makelaars In Onroerend Goed",
    "sg:phone":"+31 76 503 3000",
    "sg:postcode":"4876 AP",
    "sg:province":"North Brabant",
    "wof:name":"Bax Makelaardij Bv",
    "wof:placetype":"venue"
},
  "geometry": {"coordinates":[4.635959,51.566025],"type":"Point"}
}