{
  "type": "Feature",
  "properties": {
    "addr:full":"V Scorelstr 65 Maassluis South Holland 3141 HT",
    "addr:housenumber":"65",
    "addr:postcode":"3141 ht",
    "iso:country":"NL",
    "sg:address":"V Scorelstr 65",
    "sg:city":"Maassluis",
    "sg:orig_category":"Montagebedrijven",
    "sg:phone":"+31 6 51509179",
    "sg:postcode":"3141 HT",
    "sg:province":"South Holland",
    "wof:name":"Baan, P De",
    "wof:placetype":"venue"
},
  "geometry": {"coordinates":[4.251202,51.924381],"type":"Point"}
}