{
  "type": "Feature",
  "properties": {
    "addr:full":"Landbouwstraat 63 Amsterdam Noord-Holland 1097 TM",
    "addr:housenumber":"63",
    "addr:postcode":"1097 tm",
    "addr:street":"Landbouwstraat",
    "iso:country":"NL",
    "sg:address":"Landbouwstraat 63",
    "sg:city":"Amsterdam",
    "sg:orig_category":"Overheidsdiensten",
    "sg:phone":"+31 20 692 2171",
    "sg:postcode":"1097 TM",
    "sg:province":"Noord-Holland",
    "wof:name":"Brinkhuis",
    "wof:placetype":"venue"
},
  "geometry": {"coordinates":[4.9431781769,52.3397369385],"type":"Point"}
}