{
  "type": "Feature",
  "properties": {
    "iso:country":"NL",
    "sg:address":"Landbouwstraat 63",
    "sg:city":"Amsterdam",
    "sg:orig_category":"Overheidsdiensten",
    "sg:phone":"+31 20 692 2171",
    "sg:postcode":"1097 TM",
    "sg:province":"Noord-Holland",
    "wof:name":"Brinkhuis",
    "wof:placetype":"venue"
},
  "geometry": {"coordinates":[4.9431781769,52.3397369385],"type":"Point"}
}