{
  "type": "Feature",
  "properties": {
    "addr:full":"Postbus 93 Rigel Maassluis South Holland 3140 AB",
    "addr:housenumber":"93",
    "addr:postcode":"3140 ab",
    "addr:street":"Postbus",
    "iso:country":"NL",
    "sg:address":"Postbus 93 Rigel",
    "sg:city":"Maassluis",
    "sg:orig_category":"Verenigingen En Stichtingen",
    "sg:phone":"+31 10 592 5391",
    "sg:postcode":"3140 AB",
    "sg:province":"South Holland",
    "wof:name":"Zeekadetkorps Maassluis, Sticht",
    "wof:placetype":"venue"
},
  "geometry": {"coordinates":[4.251202,51.924381],"type":"Point"}
}