{
  "type": "Feature",
  "properties": {
    "iso:country":"NL",
    "sg:address":"Kerkwg 33",
    "sg:city":"Pynacker",
    "sg:orig_category":"Loodgieters",
    "sg:phone":"+31 15 369 2561",
    "sg:postcode":"2641 GB",
    "sg:province":"Zuid-Holland",
    "wof:name":"Kemp",
    "wof:placetype":"venue"
},
  "geometry": {"coordinates":[4.431042,52.017269],"type":"Point"}
}