{
  "type": "Feature",
  "properties": {
    "addr:full":"J Israelsln 104 Arnhem Gelderland 6813 JH",
    "addr:housenumber":"104",
    "addr:postcode":"6813 jh",
    "iso:country":"NL",
    "sg:address":"J Israelsln 104",
    "sg:city":"Arnhem",
    "sg:orig_category":"Adviesbureaus Bedrijfsorganisatie",
    "sg:phone":"+31 26 445 4161",
    "sg:postcode":"6813 JH",
    "sg:province":"Gelderland",
    "sg:website":"http://www.moniquecornielje.nl",
    "wof:name":"Monique Cornielje",
    "wof:placetype":"venue"
},
  "geometry": {"coordinates":[5.877167,51.995708],"type":"Point"}
}