{
  "type": "Feature",
  "properties": {
    "addr:full":"Parlevinker 6 Nieuw Vennep Noord-Holland 2152 LC",
    "addr:housenumber":"6",
    "addr:postcode":"2152 lc",
    "addr:street":"Parlevinker;Nieuw Vennep",
    "iso:country":"NL",
    "sg:address":"Parlevinker 6",
    "sg:city":"Nieuw Vennep",
    "sg:orig_category":"Adviesbureaus Bedrijfsorganisatie",
    "sg:phone":"+31 252 689 609",
    "sg:postcode":"2152 LC",
    "sg:province":"Noord-Holland",
    "wof:name":"Keers Vof",
    "wof:placetype":"venue"
},
  "geometry": {"coordinates":[4.640854,52.270847],"type":"Point"}
}