{
  "type": "Feature",
  "properties": {
    "addr:full":"Buikslotermeerdk 27 Amsterdam Noord-Holland 1025 WH",
    "addr:housenumber":"27",
    "addr:postcode":"1025 wh",
    "addr:street":"Buikslotermeerdk",
    "iso:country":"NL",
    "sg:address":"Buikslotermeerdk 27",
    "sg:city":"Amsterdam",
    "sg:orig_category":"Schilders",
    "sg:phone":"+31 20 636 7175",
    "sg:postcode":"1025 WH",
    "sg:province":"Noord-Holland",
    "wof:name":"Compier, Gebr",
    "wof:placetype":"venue"
},
  "geometry": {"coordinates":[4.924025,52.396885],"type":"Point"}
}