{
  "type": "Feature",
  "properties": {
    "addr:full":"Printer 3 Coevorden Provincie Drenthe 7741 ME",
    "addr:housenumber":"3",
    "addr:postcode":"7741 me",
    "addr:street":"Printer;Provincie Drenthe",
    "iso:country":"NL",
    "sg:address":"Printer 3",
    "sg:city":"Coevorden",
    "sg:orig_category":"Verzekeringen - Verzekeringskantoren",
    "sg:phone":"+31 524 512 774",
    "sg:postcode":"7741 ME",
    "sg:province":"Provincie Drenthe",
    "wof:name":"Zz Adviesburo",
    "wof:placetype":"venue"
},
  "geometry": {"coordinates":[6.725392,52.66003],"type":"Point"}
}