{
  "type": "Feature",
  "properties": {
    "addr:full":"A De Drie Zwanen 13 S Hertogenbosch Noord-Brabant 5211 GR",
    "addr:housenumber":"13",
    "addr:postcode":"5211",
    "addr:street":"A De Drie Zwanen;S",
    "iso:country":"NL",
    "sg:address":"A De Drie Zwanen 13",
    "sg:city":"S Hertogenbosch",
    "sg:orig_category":"Adviesbureaus Bedrijfsorganisatie",
    "sg:phone":"+31 73 690 0695",
    "sg:postcode":"5211 GR",
    "sg:province":"Noord-Brabant",
    "wof:name":"Sensibel",
    "wof:placetype":"venue"
},
  "geometry": {"coordinates":[5.297879,51.68507],"type":"Point"}
}