{
  "type": "Feature",
  "properties": {
    "addr:full":"Torendreef 22 Bladel North Brabant 5531 ET",
    "addr:housenumber":"22",
    "addr:postcode":"5531 et",
    "addr:street":"Torendreef",
    "iso:country":"NL",
    "sg:address":"Torendreef 22",
    "sg:city":"Bladel",
    "sg:orig_category":"Hulpverlening Sociaal",
    "sg:phone":"+31 497 384 705",
    "sg:postcode":"5531 ET",
    "sg:province":"North Brabant",
    "wof:name":"Ned Rode Kruis, Het",
    "wof:placetype":"venue"
},
  "geometry": {"coordinates":[5.225115,51.370453],"type":"Point"}
}