{
  "type": "Feature",
  "properties": {
    "addr:full":"Statenlaan 16 'S Gravenhage Zuid-Holland 2582 GL",
    "addr:housenumber":"16",
    "addr:postcode":"2582 gl",
    "addr:street":"Statenlaan;' S",
    "iso:country":"NL",
    "sg:address":"Statenlaan 16",
    "sg:city":"'S Gravenhage",
    "sg:orig_category":"Binnenhuisarchitecten",
    "sg:phone":"+31 70 351 4657",
    "sg:postcode":"2582 GL",
    "sg:province":"Zuid-Holland",
    "wof:name":"Anna Home",
    "wof:placetype":"venue"
},
  "geometry": {"coordinates":[4.277141,52.091743],"type":"Point"}
}