{
  "type": "Feature",
  "properties": {
    "addr:full":"Koestr 24 Sloten Fr Friesland 8556 AB",
    "addr:housenumber":"24",
    "addr:postcode":"8556 ab",
    "addr:street":"Koestr",
    "iso:country":"NL",
    "sg:address":"Koestr 24",
    "sg:city":"Sloten Fr",
    "sg:orig_category":"Glasblazerijen",
    "sg:phone":"+31 514 531 580",
    "sg:postcode":"8556 AB",
    "sg:province":"Friesland",
    "sg:website":"http://www.castel.nl/jaapdeen",
    "wof:name":"Deen, Jaap",
    "wof:placetype":"venue"
},
  "geometry": {"coordinates":[5.646351,52.895123],"type":"Point"}
}