{
  "type": "Feature",
  "properties": {
    "addr:full":"T Stet 17 Akersloot North Holland 1921 BT",
    "addr:housenumber":"17",
    "addr:postcode":"1921 bt",
    "addr:street":"T Stet",
    "iso:country":"NL",
    "sg:address":"T Stet 17",
    "sg:city":"Akersloot",
    "sg:orig_category":"Grafisch Ontwerpers",
    "sg:phone":"+31 251 319 575",
    "sg:postcode":"1921 BT",
    "sg:province":"North Holland",
    "wof:name":"Sierra240",
    "wof:placetype":"venue"
},
  "geometry": {"coordinates":[4.740295,52.564423],"type":"Point"}
}