{
  "type": "Feature",
  "properties": {
    "addr:full":"Hoptunen 5 De Wilgen Provincie Friesland 9213 VK",
    "addr:housenumber":"5",
    "addr:postcode":"9213 vk",
    "addr:street":"Hoptunen;Friesland",
    "iso:country":"NL",
    "sg:address":"Hoptunen 5",
    "sg:city":"De Wilgen",
    "sg:orig_category":"Psychotherapeuten",
    "sg:phone":"+31 512 544 007",
    "sg:postcode":"9213 VK",
    "sg:province":"Provincie Friesland",
    "wof:name":"Vries, Drs H L De",
    "wof:placetype":"venue"
},
  "geometry": {"coordinates":[6.033569,53.099838],"type":"Point"}
}