{
  "type": "Feature",
  "properties": {
    "iso:country":"NL",
    "sg:address":"Almelosestr 88-90",
    "sg:city":"Raalte",
    "sg:orig_category":"Bloemen En Planten - Groothandel",
    "sg:phone":"+31 572 352 131",
    "sg:postcode":"8102 HE",
    "sg:province":"NL.08",
    "sg:website":"http://www.olaf-nijenkamp.nl",
    "wof:name":"Nijenkamp Vof, Olaf",
    "wof:placetype":"venue"
},
  "geometry": {"coordinates":[6.29591,52.383308],"type":"Point"}
}