{
  "type": "Feature",
  "properties": {
    "iso:country":"NL",
    "sg:address":"Favrestr 109",
    "sg:city":"Rotterdam",
    "sg:orig_category":"Administratie- En Boekhoudkantoren",
    "sg:phone":"+31 10 421 1301",
    "sg:postcode":"3066 EC",
    "sg:province":"Zuid-Holland",
    "wof:name":"Asp",
    "wof:placetype":"venue"
},
  "geometry": {"coordinates":[4.540299,51.935753],"type":"Point"}
}