{
  "type": "Feature",
  "properties": {
    "addr:full":"Voorstr 20 Wissenkerke Zeeland 4491 EW",
    "addr:housenumber":"20",
    "addr:postcode":"4491 ew",
    "addr:street":"Voorstr",
    "iso:country":"NL",
    "sg:address":"Voorstr 20",
    "sg:city":"Wissenkerke",
    "sg:orig_category":"Verenigingsgebouwen",
    "sg:phone":"+31 113 371 486",
    "sg:postcode":"4491 EW",
    "sg:province":"Zeeland",
    "wof:name":"Zaal Onder De Toren",
    "wof:placetype":"venue"
},
  "geometry": {"coordinates":[3.746574,51.585369],"type":"Point"}
}