{
  "type": "Feature",
  "properties": {
    "addr:full":"Transvaalkd 75 Amsterdam Noord-Holland 1092 JS",
    "addr:housenumber":"75",
    "addr:postcode":"1092 js",
    "addr:street":"Transvaalkd",
    "iso:country":"NL",
    "sg:address":"Transvaalkd 75",
    "sg:city":"Amsterdam",
    "sg:classifiers":[
        {
            "category":"Retail",
            "subcategory":"Auto Repair",
            "type":"Services"
        }
    ],
    "sg:phone":"+31 20 692 5169",
    "sg:postcode":"1092 JS",
    "sg:province":"Noord-Holland",
    "sg:tags":[
        "garage"
    ],
    "wof:name":"Transvaal",
    "wof:placetype":"venue"
},
  "geometry": {"coordinates":[4.922496,52.35305],"type":"Point"}
}