{
  "type": "Feature",
  "properties": {
    "iso:country":"NL",
    "sg:address":"Transvaalkd 75",
    "sg:city":"Amsterdam",
    "sg:classifiers":[
        {
            "category":"Retail",
            "subcategory":"Auto Repair",
            "type":"Services"
        }
    ],
    "sg:phone":"+31 20 692 5169",
    "sg:postcode":"1092 JS",
    "sg:province":"Noord-Holland",
    "sg:tags":[
        "garage"
    ],
    "wof:name":"Transvaal",
    "wof:placetype":"venue"
},
  "geometry": {"coordinates":[4.922496,52.35305],"type":"Point"}
}