{
  "type": "Feature",
  "properties": {
    "addr:full":"St. Annastraat 6 Nijmegen Gelderland 6524 GA",
    "addr:housenumber":"6",
    "addr:postcode":"6524 ga",
    "addr:street":"St. Annastraat;Gelderland",
    "iso:country":"NL",
    "sg:address":"St. Annastraat 6",
    "sg:city":"Nijmegen",
    "sg:orig_category":"Wegen And Sportterreinen",
    "sg:phone":"+31 24 322 1644",
    "sg:postcode":"6524 GA",
    "sg:province":"Gelderland",
    "wof:name":"P.B. Huberts Aanneming- En Wegenbouwonderneming Bv",
    "wof:placetype":"venue"
},
  "geometry": {"coordinates":[5.8596410751,51.8410987854],"type":"Point"}
}