{
  "type": "Feature",
  "properties": {
    "addr:full":"A Bloemaertstr 14 Utrecht Utrecht 3514 VP",
    "addr:housenumber":"14",
    "addr:postcode":"3514 vp",
    "iso:country":"NL",
    "sg:address":"A Bloemaertstr 14",
    "sg:city":"Utrecht",
    "sg:orig_category":"Bedrijfsopleidingen",
    "sg:phone":"+31 30 273 4199",
    "sg:postcode":"3514 VP",
    "sg:province":"Utrecht",
    "sg:website":"http://leidraad.coachingnet.nl",
    "wof:name":"Leidraad",
    "wof:placetype":"venue"
},
  "geometry": {"coordinates":[5.119507,52.099983],"type":"Point"}
}