{
  "type": "Feature",
  "properties": {
    "addr:full":"Sluiswg 16 Katwyk Zh South Holland 2225 XM",
    "addr:housenumber":"16;zh",
    "addr:postcode":"2225 xm",
    "addr:street":"Sluiswg",
    "iso:country":"NL",
    "sg:address":"Sluiswg 16",
    "sg:city":"Katwyk Zh",
    "sg:orig_category":"Peuterspeelzalen",
    "sg:phone":"+31 71 401 6411",
    "sg:postcode":"2225 XM",
    "sg:province":"South Holland",
    "wof:name":"Iene Miene Mutte",
    "wof:placetype":"venue"
},
  "geometry": {"coordinates":[4.396585,52.205109],"type":"Point"}
}