{
  "type": "Feature",
  "properties": {
    "addr:full":"Dykerpeelwg 22 Weert Limburg 6006 VE",
    "addr:housenumber":"22",
    "addr:postcode":"6006",
    "addr:street":"Dykerpeelwg;Ve",
    "iso:country":"NL",
    "sg:address":"Dykerpeelwg 22",
    "sg:city":"Weert",
    "sg:orig_category":"Adviesbureaus Beroeps- En Schoolkeuze",
    "sg:phone":"+31 6 53714169",
    "sg:postcode":"6006 VE",
    "sg:province":"Limburg",
    "wof:name":"Latent Talent",
    "wof:placetype":"venue"
},
  "geometry": {"coordinates":[5.697125,51.216309],"type":"Point"}
}