{
  "type": "Feature",
  "properties": {
    "addr:full":"Winterakker 2 Spijkenisse Zuid-Holland 3206 TG",
    "addr:housenumber":"2",
    "addr:postcode":"3206 tg",
    "addr:street":"Winterakker",
    "iso:country":"NL",
    "sg:address":"Winterakker 2",
    "sg:city":"Spijkenisse",
    "sg:classifiers":[
        {
            "category":"Bakery",
            "type":"Food & Drink"
        }
    ],
    "sg:phone":"+31 181 633 378",
    "sg:postcode":"3206 TG",
    "sg:province":"Zuid-Holland",
    "sg:tags":[
        "brood",
        "banket"
    ],
    "wof:name":"Jan Smeets Banketbakkerij Chocolaterie",
    "wof:placetype":"venue"
},
  "geometry": {"coordinates":[4.320806,51.833153],"type":"Point"}
}