{
  "type": "Feature",
  "properties": {
    "addr:full":"Katwoudehof 86 Arnhem Gelderland 6843 BZ",
    "addr:housenumber":"86",
    "addr:postcode":"6843 bz",
    "addr:street":"Katwoudehof",
    "iso:country":"NL",
    "sg:address":"Katwoudehof 86",
    "sg:city":"Arnhem",
    "sg:orig_category":"Autorijscholen",
    "sg:phone":"+31 26 381 3583",
    "sg:postcode":"6843 BZ",
    "sg:province":"Gelderland",
    "wof:name":"Winter, Bas",
    "wof:placetype":"venue"
},
  "geometry": {"coordinates":[5.867861,51.962292],"type":"Point"}
}