{
  "type": "Feature",
  "properties": {
    "addr:full":"Vondelsngl 55-59 Spykenisse South Holland 3202 XE",
    "addr:housenumber":"55-59",
    "addr:postcode":"3202 xe",
    "addr:street":"Spykenisse South",
    "iso:country":"NL",
    "sg:address":"Vondelsngl 55-59",
    "sg:city":"Spykenisse",
    "sg:classifiers":[
        {
            "category":"Restaurant",
            "type":"Food & Drink"
        }
    ],
    "sg:phone":"+31 181 617 460",
    "sg:postcode":"3202 XE",
    "sg:province":"South Holland",
    "wof:name":"Vincent",
    "wof:placetype":"venue"
},
  "geometry": {"coordinates":[4.31103,51.85767],"type":"Point"}
}