{
  "type": "Feature",
  "properties": {
    "iso:country":"NL",
    "sg:address":"Bredestg 31",
    "sg:city":"Tiel",
    "sg:orig_category":"Administratie- En Boekhoudkantoren",
    "sg:phone":"+31 344 695 940",
    "sg:postcode":"4004 LJ",
    "sg:province":"Gelderland",
    "wof:name":"First Finance Consultancy",
    "wof:placetype":"venue"
},
  "geometry": {"coordinates":[5.463118,51.920025],"type":"Point"}
}