{
  "type": "Feature",
  "properties": {
    "iso:country":"NL",
    "sg:address":"Venneperweg 545",
    "sg:city":"Nieuw Vennep",
    "sg:orig_category":"Loodgieterswerk, Verwarming And Sanitaire Installaties",
    "sg:phone":"+31 252 622 026",
    "sg:postcode":"2152 CB",
    "sg:province":"North Holland",
    "wof:name":"Gastechnisch Inst. Bureau C.B. Stroethof",
    "wof:placetype":"venue"
},
  "geometry": {"coordinates":[4.630601,52.266754],"type":"Point"}
}