{
  "type": "Feature",
  "properties": {
    "addr:full":"K Reke 11 Renesse Zeeland 4325 AM",
    "addr:housenumber":"11",
    "addr:postcode":"4325",
    "addr:street":"K Reke",
    "iso:country":"NL",
    "sg:address":"K Reke 11",
    "sg:city":"Renesse",
    "sg:orig_category":"Discotheken",
    "sg:phone":"+31 111 462 426",
    "sg:postcode":"4325 AM",
    "sg:province":"Zeeland",
    "wof:name":"Pigalle",
    "wof:placetype":"venue"
},
  "geometry": {"coordinates":[3.774561,51.731991],"type":"Point"}
}