{
  "type": "Feature",
  "properties": {
    "addr:full":"Leguaanstr 27 Almere Flevoland 1338 HB",
    "addr:housenumber":"27",
    "addr:postcode":"1338 hb",
    "addr:street":"Leguaanstr;Flevoland",
    "iso:country":"NL",
    "sg:address":"Leguaanstr 27",
    "sg:city":"Almere",
    "sg:orig_category":"Arbo- En Bedrijfsgezondheids- Diensten",
    "sg:phone":"+31 36 537 1610",
    "sg:postcode":"1338 HB",
    "sg:province":"Flevoland",
    "wof:name":"Pfi Consulting",
    "wof:placetype":"venue"
},
  "geometry": {"coordinates":[5.266462,52.382927],"type":"Point"}
}