{
  "type": "Feature",
  "properties": {
    "addr:full":"Rijnlanderweg 1405 Nieuw Vennep Noord-Holland 2153 KE",
    "addr:housenumber":"1405",
    "addr:postcode":"2153 ke",
    "addr:street":"Rijnlanderweg;Nieuw Vennep",
    "iso:country":"NL",
    "sg:address":"Rijnlanderweg 1405",
    "sg:city":"Nieuw Vennep",
    "sg:orig_category":"Loodgieterswerk, Verwarming And Sanitaire Installaties",
    "sg:phone":"+31 252 620 470",
    "sg:postcode":"2153 KE",
    "sg:province":"Noord-Holland",
    "wof:name":"Hkb Het Klussenbedrijf",
    "wof:placetype":"venue"
},
  "geometry": {"coordinates":[4.655736,52.25214],"type":"Point"}
}