{
  "type": "Feature",
  "properties": {
    "iso:country":"NL",
    "sg:address":"Hulshorststraat 81",
    "sg:city":"'S Gravenhage",
    "sg:orig_category":"Diverse Consumentenartikelen Gh",
    "sg:phone":"+31 70 363 0175",
    "sg:postcode":"2573 EB",
    "sg:province":"Zuid-Holland",
    "wof:name":"Koushk Imp & Exp Bv",
    "wof:placetype":"venue"
},
  "geometry": {"coordinates":[4.286927,52.065319],"type":"Point"}
}