{
  "type": "Feature",
  "properties": {
    "addr:full":"Heyendaalsewg 9 Nymegen South Carolina 6524 SC",
    "addr:housenumber":"9;6524",
    "addr:street":"Heyendaalsewg;South",
    "iso:country":"NL",
    "sg:address":"Heyendaalsewg 9",
    "sg:city":"Nymegen",
    "sg:orig_category":"Yoga-Instituten",
    "sg:phone":"+31 24 323 7315",
    "sg:postcode":"6524 SC",
    "sg:province":"South Carolina",
    "wof:name":"Houte, Lieske Van",
    "wof:placetype":"venue"
},
  "geometry": {"coordinates":[-80.947441,33.624981],"type":"Point"}
}