{
  "type": "Feature",
  "properties": {
    "addr:full":"Koemarkt 34 Purmerend Noord-Holland 1441 DD",
    "addr:housenumber":"34",
    "addr:postcode":"1441 dd",
    "addr:street":"Koemarkt",
    "iso:country":"NL",
    "sg:address":"Koemarkt 34",
    "sg:city":"Purmerend",
    "sg:orig_category":"New Age-Artikelen En -Diensten",
    "sg:phone":"+31 299 416 216",
    "sg:postcode":"1441 DD",
    "sg:province":"Noord-Holland",
    "wof:name":"Nieuwe Tijd",
    "wof:placetype":"venue"
},
  "geometry": {"coordinates":[4.949346,52.508129],"type":"Point"}
}