{
  "type": "Feature",
  "properties": {
    "addr:full":"Copernicusstraat 10 Weert Limburg 6003 DE",
    "addr:housenumber":"10",
    "addr:postcode":"6003 de",
    "addr:street":"Copernicusstraat",
    "iso:country":"NL",
    "sg:address":"Copernicusstraat 10",
    "sg:city":"Weert",
    "sg:classifiers":[
        {
            "category":"Retail",
            "subcategory":"Storage",
            "type":"Services"
        }
    ],
    "sg:phone":"+31 495 459 777",
    "sg:postcode":"6003 DE",
    "sg:province":"Limburg",
    "sg:tags":[
        "opslag",
        "bewaring"
    ],
    "wof:name":"Waterfront Bv",
    "wof:placetype":"venue"
},
  "geometry": {"coordinates":[5.7347369194,51.2738113403],"type":"Point"}
}