{
  "type": "Feature",
  "properties": {
    "addr:full":"S De Cockstr 15 Tilburg Noord-Brabant 5048 AW",
    "addr:housenumber":"15",
    "addr:postcode":"5048 aw",
    "addr:street":"S",
    "iso:country":"NL",
    "sg:address":"S De Cockstr 15",
    "sg:city":"Tilburg",
    "sg:orig_category":"Fietsen En Bromfietsen Onderdelen - Fabr. En Grooth",
    "sg:phone":"+31 13 594 2050",
    "sg:postcode":"5048 AW",
    "sg:province":"Noord-Brabant",
    "sg:website":"http://www.piaggio.nl",
    "wof:name":"Piaggio Benelux Bv",
    "wof:placetype":"venue"
},
  "geometry": {"coordinates":[5.051952,51.590282],"type":"Point"}
}