{
  "type": "Feature",
  "properties": {
    "iso:country":"NL",
    "sg:address":"Spaarndammerdk 13A",
    "sg:city":"Spaarndam",
    "sg:orig_category":"Loodgieters",
    "sg:phone":"+31 23 538 1269",
    "sg:postcode":"2064 KL",
    "sg:province":"Noord-Holland",
    "wof:name":"Drs",
    "wof:placetype":"venue"
},
  "geometry": {"coordinates":[4.71253,52.403042],"type":"Point"}
}