{
  "type": "Feature",
  "properties": {
    "addr:full":"Noorderkade 1027 Alkmaar Noord-Holland 1823 CJ",
    "addr:housenumber":"1027",
    "addr:postcode":"1823 cj",
    "addr:street":"Noorderkade",
    "iso:country":"NL",
    "sg:address":"Noorderkade 1027",
    "sg:city":"Alkmaar",
    "sg:orig_category":"Verlichting And Huishoudartikelen",
    "sg:phone":"+31 72 515 7987",
    "sg:postcode":"1823 CJ",
    "sg:province":"Noord-Holland",
    "wof:name":"Primalicht Verlichting Bv",
    "wof:placetype":"venue"
},
  "geometry": {"coordinates":[4.76043,52.638321],"type":"Point"}
}