{
  "type": "Feature",
  "properties": {
    "addr:full":"Kapitein Nemostraat 107 Tilburg North Brabant 5015 AS",
    "addr:housenumber":"107",
    "addr:postcode":"5015 as",
    "addr:street":"Kapitein Nemostraat",
    "iso:country":"NL",
    "sg:address":"Kapitein Nemostraat 107",
    "sg:city":"Tilburg",
    "sg:orig_category":"Metaalbekleding And -Behandeling",
    "sg:phone":"+31 13 542 4372",
    "sg:postcode":"5015 AS",
    "sg:province":"North Brabant",
    "wof:name":"Bv Etemf",
    "wof:placetype":"venue"
},
  "geometry": {"coordinates":[5.10535,51.568195],"type":"Point"}
}