{
  "type": "Feature",
  "properties": {
    "iso:country":"NL",
    "sg:address":"Meerln 52",
    "sg:city":"Medemblik",
    "sg:orig_category":"Sauna'S",
    "sg:phone":"+31 227 540 063",
    "sg:postcode":"1671 EG",
    "sg:province":"Noord-Holland",
    "wof:name":"Sauna Medemblik",
    "wof:placetype":"venue"
},
  "geometry": {"coordinates":[5.106715,52.771942],"type":"Point"}
}