{
  "type": "Feature",
  "properties": {
    "addr:full":"Overakkerstr 194 Breda Noord-Brabant 4834 XP",
    "addr:housenumber":"194",
    "addr:postcode":"4834 xp",
    "iso:country":"NL",
    "sg:address":"Overakkerstr 194",
    "sg:city":"Breda",
    "sg:orig_category":"Beeldende Kunstenaars",
    "sg:phone":"+31 76 520 7764",
    "sg:postcode":"4834 XP",
    "sg:province":"Noord-Brabant",
    "sg:website":"http://www.kunstkontakt/henrypennings.nl",
    "wof:name":"Pennings, Henry",
    "wof:placetype":"venue"
},
  "geometry": {"coordinates":[4.801208,51.568272],"type":"Point"}
}