{
  "type": "Feature",
  "properties": {
    "iso:country":"NL",
    "sg:address":"Burg Mentzstraat 23",
    "sg:city":"Terschelling West",
    "sg:orig_category":"Fitnesscentra",
    "sg:phone":"+31 562 443 306",
    "sg:postcode":"8881 AJ",
    "sg:province":"Provincie Friesland",
    "wof:name":"Sportschool Feel-Fit",
    "wof:placetype":"venue"
},
  "geometry": {"coordinates":[5.214094,53.360294],"type":"Point"}
}