{
  "type": "Feature",
  "properties": {
    "iso:country":"NL",
    "sg:address":"Marconistr 111",
    "sg:city":"Gouda",
    "sg:orig_category":"Fotoapparatuur En -Artikelen - Groothandel",
    "sg:phone":"+31 182 549 490",
    "sg:postcode":"2809 PG",
    "sg:province":"Zuid-Holland",
    "wof:name":"Molto Bello Bv",
    "wof:placetype":"venue"
},
  "geometry": {"coordinates":[4.691737,52.004417],"type":"Point"}
}