{
  "type": "Feature",
  "properties": {
    "addr:full":"Frankenslag 52 'S Gravenhage Zuid-Holland 2582 HS",
    "addr:housenumber":"52",
    "addr:postcode":"2582 hs",
    "addr:street":"Frankenslag;' S",
    "iso:country":"NL",
    "sg:address":"Frankenslag 52",
    "sg:city":"'S Gravenhage",
    "sg:orig_category":"Artsen And Specialisten",
    "sg:phone":"+31 70 354 9759",
    "sg:postcode":"2582 HS",
    "sg:province":"Zuid-Holland",
    "wof:name":"Drs. H. Verkade",
    "wof:placetype":"venue"
},
  "geometry": {"coordinates":[4.278936,52.09787],"type":"Point"}
}