{
  "type": "Feature",
  "properties": {
    "iso:country":"NL",
    "sg:address":"Beverwaardsewg 105",
    "sg:city":"Rotterdam",
    "sg:orig_category":"Autoreclame",
    "sg:phone":"+31 10 497 0789",
    "sg:postcode":"3077 GK",
    "sg:province":"South Holland",
    "wof:name":"Koro Reklame",
    "wof:placetype":"venue"
},
  "geometry": {"coordinates":[4.571066,51.898796],"type":"Point"}
}