{
  "type": "Feature",
  "properties": {
    "addr:full":"Grobbendonkstraat 1 Eindhoven North Brabant 5628 RE",
    "addr:housenumber":"1",
    "addr:postcode":"5628 re",
    "addr:street":"Grobbendonkstraat",
    "iso:country":"NL",
    "sg:address":"Grobbendonkstraat 1",
    "sg:city":"Eindhoven",
    "sg:orig_category":"Fitnesscentra",
    "sg:phone":"+31 40 248 4422",
    "sg:postcode":"5628 RE",
    "sg:province":"North Brabant",
    "wof:name":"Sport Inn",
    "wof:placetype":"venue"
},
  "geometry": {"coordinates":[5.483135,51.477348],"type":"Point"}
}