{
  "type": "Feature",
  "properties": {
    "addr:full":"Dr A Kuyperweg 12 Beesd Gelderland 4153 XB",
    "addr:housenumber":"12",
    "addr:postcode":"4153 xb",
    "addr:street":"Dr A Kuyperweg;Gelderland",
    "iso:country":"NL",
    "sg:address":"Dr A Kuyperweg 12",
    "sg:city":"Beesd",
    "sg:orig_category":"Loodgieterswerk, Verwarming And Sanitaire Installaties",
    "sg:phone":"+31 345 682 083",
    "sg:postcode":"4153 XB",
    "sg:province":"Gelderland",
    "wof:name":"De Tijd Gawalo Installatiebedrijf",
    "wof:placetype":"venue"
},
  "geometry": {"coordinates":[5.187334,51.884796],"type":"Point"}
}