{
  "type": "Feature",
  "properties": {
    "addr:full":"Kortenhoevenseweg 36A Lexmond Zuid-Holland 4128 CR",
    "addr:housenumber":"36a",
    "addr:postcode":"4128 cr",
    "addr:street":"Kortenhoevenseweg",
    "iso:country":"NL",
    "sg:address":"Kortenhoevenseweg 36A",
    "sg:city":"Lexmond",
    "sg:orig_category":"Werving And Selectie Van Tijdelijk Personeel And Uitzendkantoren",
    "sg:phone":"+31 347 342 737",
    "sg:postcode":"4128 CR",
    "sg:province":"Zuid-Holland",
    "wof:name":"Ips Ned-Planning",
    "wof:placetype":"venue"
},
  "geometry": {"coordinates":[5.0403580666,51.9636268616],"type":"Point"}
}