{
  "type": "Feature",
  "properties": {
    "addr:full":"Van De Kasteelestraat 11 'S Gravenzande Zuid-Holland 2691 ZL",
    "addr:housenumber":"11",
    "addr:postcode":"2691 zl",
    "addr:street":"Van De Kasteelestraat;' S",
    "iso:country":"NL",
    "sg:address":"Van De Kasteelestraat 11",
    "sg:city":"'S Gravenzande",
    "sg:orig_category":"Meubelzaken, Woning- And Keukeninrichting",
    "sg:phone":"+31 174 440 310",
    "sg:postcode":"2691 ZL",
    "sg:province":"Zuid-Holland",
    "wof:name":"L De Bruin & Zoon Bv",
    "wof:placetype":"venue"
},
  "geometry": {"coordinates":[4.162616,52.001263],"type":"Point"}
}