{
  "type": "Feature",
  "properties": {
    "addr:full":"Oud Loosd Dk 184 Loosdrecht Noord-Holland 1231 NG",
    "addr:housenumber":"184",
    "addr:postcode":"1231 ng",
    "addr:street":"Oud",
    "iso:country":"NL",
    "sg:address":"Oud Loosd Dk 184",
    "sg:city":"Loosdrecht",
    "sg:orig_category":"Kappers",
    "sg:phone":"+31 35 582 7968",
    "sg:postcode":"1231 NG",
    "sg:province":"Noord-Holland",
    "wof:name":"Annelies Haar Winkeltje",
    "wof:placetype":"venue"
},
  "geometry": {"coordinates":[5.0823459625,52.2070007324],"type":"Point"}
}