{
  "type": "Feature",
  "properties": {
    "iso:country":"NL",
    "sg:address":"Kanaalwg 25",
    "sg:city":"S Gravenhage",
    "sg:orig_category":"Open Haarden",
    "sg:phone":"+31 70 354 6235",
    "sg:postcode":"2584 CE",
    "sg:province":"Zuid-Holland",
    "wof:name":"Lange, Matthijs De",
    "wof:placetype":"venue"
},
  "geometry": {"coordinates":[4.28131,52.103199],"type":"Point"}
}