{
  "type": "Feature",
  "properties": {
    "addr:full":"Molenstr 67 Zundert North Brabant 4881 CR",
    "addr:housenumber":"67",
    "addr:postcode":"4881 cr",
    "addr:street":"Molenstr",
    "iso:country":"NL",
    "sg:address":"Molenstr 67",
    "sg:city":"Zundert",
    "sg:classifiers":[
        {
            "category":"Shopping",
            "subcategory":"Adult",
            "type":"Retail Goods"
        }
    ],
    "sg:phone":"+31 76 597 3164",
    "sg:postcode":"4881 CR",
    "sg:province":"North Brabant",
    "sg:tags":[
        "lingerie",
        "en",
        "tricotage"
    ],
    "wof:name":"Oda, Lingerie",
    "wof:placetype":"venue"
},
  "geometry": {"coordinates":[4.65998,51.469929],"type":"Point"}
}