{
  "type": "Feature",
  "properties": {
    "addr:full":"Van Woustraat 45 Amsterdam Noord-Holland 1074 AB",
    "addr:housenumber":"45",
    "addr:postcode":"1074 ab",
    "addr:street":"Van Woustraat",
    "iso:country":"NL",
    "sg:address":"Van Woustraat 45",
    "sg:city":"Amsterdam",
    "sg:orig_category":"Werving And Selectie Van Tijdelijk Personeel And Uitzendkantoren",
    "sg:phone":"+31 20 664 2838",
    "sg:postcode":"1074 AB",
    "sg:province":"Noord-Holland",
    "wof:name":"Short Track Uitzendburo",
    "wof:placetype":"venue"
},
  "geometry": {"coordinates":[4.9002509117,52.3561935425],"type":"Point"}
}