{
  "type": "Feature",
  "properties": {
    "addr:full":"A Staalmanpln 3 Amsterdam Noord-Holland 1066 AG",
    "addr:housenumber":"3",
    "addr:postcode":"1066",
    "iso:country":"NL",
    "sg:address":"A Staalmanpln 3",
    "sg:city":"Amsterdam",
    "sg:orig_category":"Kappers",
    "sg:phone":"+31 20 615 6000",
    "sg:postcode":"1066 AG",
    "sg:province":"Noord-Holland",
    "wof:name":"John",
    "wof:placetype":"venue"
},
  "geometry": {"coordinates":[4.8285470009,52.3496742249],"type":"Point"}
}