{
  "type": "Feature",
  "properties": {
    "addr:full":"Otterswyk 10 Dedemsvaart Overijssel 7701 PC",
    "addr:housenumber":"10",
    "addr:postcode":"7701 pc",
    "addr:street":"Otterswyk",
    "iso:country":"NL",
    "sg:address":"Otterswyk 10",
    "sg:city":"Dedemsvaart",
    "sg:orig_category":"Bloemen En Planten - Groothandel",
    "sg:phone":"+31 523 638 368",
    "sg:postcode":"7701 PC",
    "sg:province":"Overijssel",
    "wof:name":"Elst, Van Der",
    "wof:placetype":"venue"
},
  "geometry": {"coordinates":[6.457315,52.606258],"type":"Point"}
}