{
  "type": "Feature",
  "properties": {
    "addr:full":"Muntweg 344 Nijmegen Gelderland 6532 TM",
    "addr:housenumber":"344",
    "addr:postcode":"6532 tm",
    "addr:street":"Muntweg;Gelderland",
    "iso:country":"NL",
    "sg:address":"Muntweg 344",
    "sg:city":"Nijmegen",
    "sg:orig_category":"Metaalbekleding And -Behandeling",
    "sg:phone":"+31 24 355 1929",
    "sg:postcode":"6532 TM",
    "sg:province":"Gelderland",
    "wof:name":"Metaalwarenfabriek Forcero",
    "wof:placetype":"venue"
},
  "geometry": {"coordinates":[5.836613,51.831154],"type":"Point"}
}