{
  "type": "Feature",
  "properties": {
    "addr:full":"E Vd Beekstr 114 Luchth Schiphol Noord-Holland 1118 CN",
    "addr:housenumber":"114",
    "addr:postcode":"1118 cn",
    "addr:street":"E;Luchth",
    "iso:country":"NL",
    "sg:address":"E Vd Beekstr 114",
    "sg:city":"Luchth Schiphol",
    "sg:orig_category":"Luchtvaart- Maatschappijen",
    "sg:phone":"+31 20 405 8230",
    "sg:postcode":"1118 CN",
    "sg:province":"Noord-Holland",
    "sg:website":"http://www.swissworldcargo.com",
    "wof:name":"Swiss Air",
    "wof:placetype":"venue"
},
  "geometry": {"coordinates":[4.75221,52.305019],"type":"Point"}
}