{
  "type": "Feature",
  "properties": {
    "addr:full":"Wassenaarstr 21 Bergen Op Zoom Noord-Brabant 4611 BS",
    "addr:housenumber":"21",
    "addr:postcode":"4611 bs",
    "addr:street":"Wassenaarstr",
    "iso:country":"NL",
    "sg:address":"Wassenaarstr 21",
    "sg:city":"Bergen Op Zoom",
    "sg:orig_category":"Hoortoestellen",
    "sg:phone":"+31 164 238 947",
    "sg:postcode":"4611 BS",
    "sg:province":"Noord-Brabant",
    "wof:name":"Boxtel Hoorwinkels, Van",
    "wof:placetype":"venue"
},
  "geometry": {"coordinates":[4.293227,51.494511],"type":"Point"}
}