{
  "type": "Feature",
  "properties": {
    "addr:full":"Parallel Boulev 27 Noordwyk Zh South Holland 2202 HK",
    "addr:housenumber":"27",
    "addr:postcode":"2202 hk",
    "addr:street":"Noordwyk Zh",
    "iso:country":"NL",
    "sg:address":"Parallel Boulev 27",
    "sg:city":"Noordwyk Zh",
    "sg:orig_category":"Paardensport",
    "sg:phone":"+31 71 362 0044",
    "sg:postcode":"2202 HK",
    "sg:province":"South Holland",
    "wof:name":"Langeweg Live-Stock Services Bv",
    "wof:placetype":"venue"
},
  "geometry": {"coordinates":[4.435614,52.248837],"type":"Point"}
}