{
  "type": "Feature",
  "properties": {
    "addr:full":"Lamoraalwg 69 Egmond Ad Hoef North Holland 1934 CC",
    "addr:housenumber":"69",
    "addr:postcode":"1934 cc",
    "addr:street":"Lamoraalwg",
    "iso:country":"NL",
    "sg:address":"Lamoraalwg 69",
    "sg:city":"Egmond Ad Hoef",
    "sg:orig_category":"Open Haarden",
    "sg:phone":"+31 72 506 4133",
    "sg:postcode":"1934 CC",
    "sg:province":"North Holland",
    "wof:name":"Schouw, Meubelatelier De",
    "wof:placetype":"venue"
},
  "geometry": {"coordinates":[4.65601,52.620121],"type":"Point"}
}