{
  "type": "Feature",
  "properties": {
    "addr:full":"Ulenpas 86 Eindhoven Noord-Brabant 5655 JD",
    "addr:housenumber":"86",
    "addr:postcode":"5655 jd",
    "addr:street":"Ulenpas",
    "iso:country":"NL",
    "sg:address":"Ulenpas 86",
    "sg:city":"Eindhoven",
    "sg:orig_category":"Adviesbureaus Elektrotechniek",
    "sg:phone":"+31 40 252 6099",
    "sg:postcode":"5655 JD",
    "sg:province":"Noord-Brabant",
    "wof:name":"Maku",
    "wof:placetype":"venue"
},
  "geometry": {"coordinates":[5.434958,51.412346],"type":"Point"}
}