{
  "type": "Feature",
  "properties": {
    "addr:full":"Widooiestr 14 Maastricht Limburg 6215 KC",
    "addr:housenumber":"14",
    "addr:postcode":"6215 kc",
    "addr:street":"Widooiestr",
    "iso:country":"NL",
    "sg:address":"Widooiestr 14",
    "sg:city":"Maastricht",
    "sg:orig_category":"Kappers",
    "sg:phone":"+31 43 344 0237",
    "sg:postcode":"6215 KC",
    "sg:province":"Limburg",
    "wof:name":"Luan",
    "wof:placetype":"venue"
},
  "geometry": {"coordinates":[5.643738,50.84449],"type":"Point"}
}