{
  "type": "Feature",
  "properties": {
    "addr:full":"Atoomweg 66 Utrecht Utrecht 3542 AB",
    "addr:housenumber":"66",
    "addr:postcode":"3542 ab",
    "addr:street":"Atoomweg",
    "iso:country":"NL",
    "sg:address":"Atoomweg 66",
    "sg:city":"Utrecht",
    "sg:orig_category":"Geluidsopnamen",
    "sg:phone":"+31 30 221 1667",
    "sg:postcode":"3542 AB",
    "sg:province":"Utrecht",
    "wof:name":"Sandwijck Studio",
    "wof:placetype":"venue"
},
  "geometry": {"coordinates":[5.060486,52.11203],"type":"Point"}
}