{
  "type": "Feature",
  "properties": {
    "addr:full":"J Toetln 66 Yhorst Overijssel 7955 AZ",
    "addr:housenumber":"66",
    "addr:postcode":"7955",
    "addr:street":"Yhorst Overijssel",
    "iso:country":"NL",
    "sg:address":"J Toetln 66",
    "sg:city":"Yhorst",
    "sg:orig_category":"Voetbalverenigingen",
    "sg:phone":"+31 522 442 303",
    "sg:postcode":"7955 AZ",
    "sg:province":"Overijssel",
    "wof:name":"Ijhorst Vv",
    "wof:placetype":"venue"
},
  "geometry": {"coordinates":[6.289815,52.66082],"type":"Point"}
}