{
  "type": "Feature",
  "properties": {
    "iso:country":"NL",
    "sg:address":"Emmastraat 8",
    "sg:city":"Velp Gld",
    "sg:orig_category":"Goederenvervoer Over De Weg",
    "sg:phone":"+31 26 361 9584",
    "sg:postcode":"6881 ST",
    "sg:province":"Gelderland",
    "wof:name":"Jacobs Verhuizingen En Transporten Bv",
    "wof:placetype":"venue"
},
  "geometry": {"coordinates":[5.973073,51.995506],"type":"Point"}
}