{
  "type": "Feature",
  "properties": {
    "addr:full":"Boschdk 153 Eindhoven Noord-Brabant 5612 HB",
    "addr:housenumber":"153",
    "addr:postcode":"5612 hb",
    "iso:country":"NL",
    "sg:address":"Boschdk 153",
    "sg:city":"Eindhoven",
    "sg:orig_category":"Gehandicapten - Hulpmiddelen",
    "sg:phone":"+31 40 244 0088",
    "sg:postcode":"5612 HB",
    "sg:province":"Noord-Brabant",
    "wof:name":"Theofaan Centr V Blinden En Slechtzienden",
    "wof:placetype":"venue"
},
  "geometry": {"coordinates":[5.469454,51.446522],"type":"Point"}
}