{
  "type": "Feature",
  "properties": {
    "addr:full":"K Rietbergstr 1 Leiden Zuid-Holland 2321 BZ",
    "addr:housenumber":"1",
    "addr:postcode":"2321 bz",
    "addr:street":"Rietbergstr",
    "iso:country":"NL",
    "sg:address":"K Rietbergstr 1",
    "sg:city":"Leiden",
    "sg:orig_category":"Verpakkingen En Verpakkingsmaterialen",
    "sg:phone":"+31 71 576 3434",
    "sg:postcode":"2321 BZ",
    "sg:province":"Zuid-Holland",
    "sg:website":"http://www.cistron.nl/~schoutvp",
    "wof:name":"Schouten Bv",
    "wof:placetype":"venue"
},
  "geometry": {"coordinates":[4.480356,52.147018],"type":"Point"}
}