{
  "type": "Feature",
  "properties": {
    "addr:full":"V Eesterensngl 139 Alblasserdam Zuid-Holland 2951 VR",
    "addr:housenumber":"139",
    "addr:postcode":"2951 vr",
    "iso:country":"NL",
    "sg:address":"V Eesterensngl 139",
    "sg:city":"Alblasserdam",
    "sg:orig_category":"Administratie- En Boekhoudkantoren",
    "sg:phone":"+31 78 693 0747",
    "sg:postcode":"2951 VR",
    "sg:province":"Zuid-Holland",
    "wof:name":"Houwing, F N",
    "wof:placetype":"venue"
},
  "geometry": {"coordinates":[4.658851,51.861031],"type":"Point"}
}