{
  "type": "Feature",
  "properties": {
    "addr:full":"Bijdorp-Oost 18 Barendrecht South Holland 2992 LA",
    "addr:housenumber":"18",
    "addr:postcode":"2992 la",
    "addr:street":"Bijdorp-Oost",
    "iso:country":"NL",
    "sg:address":"Bijdorp-Oost 18",
    "sg:city":"Barendrecht",
    "sg:classifiers":[
        {
            "category":"Professional",
            "subcategory":"Accounting & Tax Preparation",
            "type":"Services"
        }
    ],
    "sg:phone":"+31 180 647 372",
    "sg:postcode":"2992 LA",
    "sg:province":"South Holland",
    "sg:tags":[
        "accountant"
    ],
    "wof:name":"Belaf Van Schoonhoven",
    "wof:placetype":"venue"
},
  "geometry": {"coordinates":[4.523899,51.863487],"type":"Point"}
}