{
  "type": "Feature",
  "properties": {
    "addr:full":"Hoofdstraat 20 Hoogezand Groningen 9601 EH",
    "addr:housenumber":"20",
    "addr:postcode":"9601 eh",
    "addr:street":"Hoofdstraat",
    "iso:country":"NL",
    "sg:address":"Hoofdstraat 20",
    "sg:city":"Hoogezand",
    "sg:orig_category":"Werving And Selectie Van Tijdelijk Personeel And Uitzendkantoren",
    "sg:phone":"+31 598 380 112",
    "sg:postcode":"9601 EH",
    "sg:province":"Groningen",
    "wof:name":"Uitzendbureau Start",
    "wof:placetype":"venue"
},
  "geometry": {"coordinates":[6.7578258514,53.163520813],"type":"Point"}
}