{
  "type": "Feature",
  "properties": {
    "addr:full":"Kerkstr 218 Amsterdam Noord-Holland 1017 GV",
    "addr:housenumber":"218",
    "addr:postcode":"1017 gv",
    "iso:country":"NL",
    "sg:address":"Kerkstr 218",
    "sg:city":"Amsterdam",
    "sg:orig_category":"Adviesbureaus Bedrijfsorganisatie",
    "sg:phone":"+31 20 422 0826",
    "sg:postcode":"1017 GV",
    "sg:province":"Noord-Holland",
    "wof:name":"Lintsen, Margareth",
    "wof:placetype":"venue"
},
  "geometry": {"coordinates":[4.891357,52.362888],"type":"Point"}
}