{
  "type": "Feature",
  "properties": {
    "iso:country":"NL",
    "sg:address":"Dorpsstraat 32",
    "sg:city":"Tuitjenhorn",
    "sg:orig_category":"Kappers",
    "sg:phone":"+31 226 393 736",
    "sg:postcode":"1747 HD",
    "sg:province":"Noord-Holland",
    "wof:name":"Studio Bibob",
    "wof:placetype":"venue"
},
  "geometry": {"coordinates":[4.749388,52.738003],"type":"Point"}
}