{
  "type": "Feature",
  "properties": {
    "addr:full":"De Maroc 35A Wateringen Zuid-Holland 2291 JX",
    "addr:housenumber":"35a",
    "addr:postcode":"2291 jx",
    "addr:street":"De Maroc",
    "iso:country":"NL",
    "sg:address":"De Maroc 35A",
    "sg:city":"Wateringen",
    "sg:orig_category":"Tandartsen",
    "sg:phone":"+31 174 295 635",
    "sg:postcode":"2291 JX",
    "sg:province":"Zuid-Holland",
    "wof:name":"J.C. Hutter",
    "wof:placetype":"venue"
},
  "geometry": {"coordinates":[4.285327,52.022488],"type":"Point"}
}