{
  "type": "Feature",
  "properties": {
    "addr:full":"Grt Breedstr 13 Dokkum Friesland 9101 KH",
    "addr:housenumber":"13",
    "addr:postcode":"9101 kh",
    "iso:country":"NL",
    "sg:address":"Grt Breedstr 13",
    "sg:city":"Dokkum",
    "sg:orig_category":"Broodjeszaken",
    "sg:phone":"+31 519 296 900",
    "sg:postcode":"9101 KH",
    "sg:province":"Friesland",
    "wof:name":"Keerpunt Van Dokkum, 'T",
    "wof:placetype":"venue"
},
  "geometry": {"coordinates":[5.9993,53.326698],"type":"Point"}
}