{
  "type": "Feature",
  "properties": {
    "addr:full":"St Urbanusstr 38 Amstelveen Noord-Holland 1187 BP",
    "addr:housenumber":"38",
    "addr:postcode":"1187 bp",
    "iso:country":"NL",
    "sg:address":"St Urbanusstr 38",
    "sg:city":"Amstelveen",
    "sg:orig_category":"Adviesbureaus Bedrijfsorganisatie",
    "sg:phone":"+31 20 345 5140",
    "sg:postcode":"1187 BP",
    "sg:province":"Noord-Holland",
    "wof:name":"Nooij, T A",
    "wof:placetype":"venue"
},
  "geometry": {"coordinates":[4.830542,52.291683],"type":"Point"}
}