{
  "type": "Feature",
  "properties": {
    "addr:full":"Het Gilde 11 Halsteren North Brabant 4661 MB",
    "addr:housenumber":"11",
    "addr:postcode":"4661 mb",
    "addr:street":"Het Gilde",
    "iso:country":"NL",
    "sg:address":"Het Gilde 11",
    "sg:city":"Halsteren",
    "sg:orig_category":"Makelaars In Onroerend Goed",
    "sg:phone":"+31 164 685 925",
    "sg:postcode":"4661 MB",
    "sg:province":"North Brabant",
    "wof:name":"Helmig Makelaardij En Taxatieburo O/G Bv",
    "wof:placetype":"venue"
},
  "geometry": {"coordinates":[4.282208,51.519325],"type":"Point"}
}