{
  "type": "Feature",
  "properties": {
    "addr:full":"Paterijstraat 17 Elburg Gelderland 8081 TA",
    "addr:housenumber":"17",
    "addr:postcode":"8081 ta",
    "addr:street":"Paterijstraat;Gelderland",
    "iso:country":"NL",
    "sg:address":"Paterijstraat 17",
    "sg:city":"Elburg",
    "sg:orig_category":"Volwassenenonderwijs",
    "sg:phone":"+31 525 682 205",
    "sg:postcode":"8081 TA",
    "sg:province":"Gelderland",
    "wof:name":"Capellen Scholengemeenschap Locatie Van",
    "wof:placetype":"venue"
},
  "geometry": {"coordinates":[5.845986,52.450584],"type":"Point"}
}