{
  "type": "Feature",
  "properties": {
    "addr:full":"Dreef 4 Didam Gelderland 6942 LJ",
    "addr:housenumber":"4;lj",
    "addr:postcode":"6942",
    "addr:street":"Dreef;Gelderland",
    "iso:country":"NL",
    "sg:address":"Dreef 4",
    "sg:city":"Didam",
    "sg:orig_category":"Verhuisdiensten",
    "sg:phone":"+31 316 248 845",
    "sg:postcode":"6942 LJ",
    "sg:province":"Gelderland",
    "wof:name":"R. Van Hunen",
    "wof:placetype":"venue"
},
  "geometry": {"coordinates":[6.140205,51.93972],"type":"Point"}
}