{
  "type": "Feature",
  "properties": {
    "addr:full":"Overschiesewg 68 Rotterdam South Holland 3044 EG",
    "addr:housenumber":"68",
    "addr:postcode":"3044 eg",
    "addr:street":"Overschiesewg",
    "iso:country":"NL",
    "sg:address":"Overschiesewg 68",
    "sg:city":"Rotterdam",
    "sg:orig_category":"Oud Metaal",
    "sg:phone":"+31 10 462 4232",
    "sg:postcode":"3044 EG",
    "sg:province":"South Holland",
    "wof:name":"Metalimex",
    "wof:placetype":"venue"
},
  "geometry": {"coordinates":[4.4091367722,51.9349060059],"type":"Point"}
}