{
  "type": "Feature",
  "properties": {
    "iso:country":"NL",
    "sg:address":"Kolenbranderstraat 24",
    "sg:city":"Breda",
    "sg:orig_category":"Parfum And Cosmetica Gh",
    "sg:phone":"+31 76 530 0608",
    "sg:postcode":"4813 CL",
    "sg:province":"Noord-Brabant",
    "wof:name":"Hans Van Maaren Import-Export Bv",
    "wof:placetype":"venue"
},
  "geometry": {"coordinates":[4.732079,51.574596],"type":"Point"}
}