{
  "type": "Feature",
  "properties": {
    "addr:full":"N Beetsln 136 Uithoorn Noord-Holland 1422 AW",
    "addr:housenumber":"136",
    "addr:postcode":"1422 aw",
    "addr:street":"N",
    "iso:country":"NL",
    "sg:address":"N Beetsln 136",
    "sg:city":"Uithoorn",
    "sg:orig_category":"Nagelstudio'S",
    "sg:phone":"+31 297 534 395",
    "sg:postcode":"1422 AW",
    "sg:province":"Noord-Holland",
    "sg:website":"http://www.something-nice.nl",
    "wof:name":"Something Nice",
    "wof:placetype":"venue"
},
  "geometry": {"coordinates":[4.828947,52.233421],"type":"Point"}
}