{
  "type": "Feature",
  "properties": {
    "addr:full":"Handelsstraat 18 Hoensbroek Limburg 6433 KB",
    "addr:housenumber":"18",
    "addr:postcode":"6433 kb",
    "addr:street":"Handelsstraat",
    "iso:country":"NL",
    "sg:address":"Handelsstraat 18",
    "sg:city":"Hoensbroek",
    "sg:orig_category":"Verhuur Catering-, Feest- En Evenementbenodigdheden",
    "sg:phone":"+31 45 575 5075",
    "sg:postcode":"6433 KB",
    "sg:province":"Limburg",
    "wof:name":"Van Traarbach Speelautomaten Bv",
    "wof:placetype":"venue"
},
  "geometry": {"coordinates":[5.934757,50.902496],"type":"Point"}
}