{
  "type": "Feature",
  "properties": {
    "addr:full":"Holthuizerdreef 55 Huissen Gelderland 6852 JJ",
    "addr:housenumber":"55",
    "addr:postcode":"6852 jj",
    "addr:street":"Holthuizerdreef;Gelderland",
    "iso:country":"NL",
    "sg:address":"Holthuizerdreef 55",
    "sg:city":"Huissen",
    "sg:orig_category":"Bedrijfsopleidingen",
    "sg:phone":"+31 26 388 6688",
    "sg:postcode":"6852 JJ",
    "sg:province":"Gelderland",
    "wof:name":"Innerspirit",
    "wof:placetype":"venue"
},
  "geometry": {"coordinates":[5.926636,51.947201],"type":"Point"}
}