{
  "type": "Feature",
  "properties": {
    "addr:full":"Molenstr 11 Dreumel Gelderland 6621 BE",
    "addr:housenumber":"11",
    "addr:postcode":"6621",
    "addr:street":"Molenstr;Gelderland",
    "iso:country":"NL",
    "sg:address":"Molenstr 11",
    "sg:city":"Dreumel",
    "sg:classifiers":[
        {
            "category":"Shopping",
            "subcategory":"News",
            "type":"Retail Goods"
        }
    ],
    "sg:phone":"+31 487 572 019",
    "sg:postcode":"6621 BE",
    "sg:province":"Gelderland",
    "sg:tags":[
        "maandbladen",
        "en",
        "week-"
    ],
    "wof:name":"Dreumel Weekblad",
    "wof:placetype":"venue"
},
  "geometry": {"coordinates":[5.4304709435,51.8513412476],"type":"Point"}
}