{
  "type": "Feature",
  "properties": {
    "iso:country":"NL",
    "sg:address":"Margarethastr 12A",
    "sg:city":"Ittervoort",
    "sg:orig_category":"Bloemen En Planten",
    "sg:phone":"+31 475 563 691",
    "sg:postcode":"6014 AE",
    "sg:province":"Limburg",
    "wof:name":"Zonnehoed, De",
    "wof:placetype":"venue"
},
  "geometry": {"coordinates":[5.82303,51.170422],"type":"Point"}
}