{
  "type": "Feature",
  "properties": {
    "addr:full":"Rijklof Van Goensplein 5 Haarlem North Holland 2024 AM",
    "addr:housenumber":"5",
    "addr:postcode":"2024",
    "addr:street":"Rijklof Van Goensplein",
    "iso:country":"NL",
    "sg:address":"Rijklof Van Goensplein 5",
    "sg:city":"Haarlem",
    "sg:orig_category":"Verzekeringen",
    "sg:phone":"+31 23 525 0093",
    "sg:postcode":"2024 AM",
    "sg:province":"North Holland",
    "wof:name":"Assurantiekantoor J. Tensen",
    "wof:placetype":"venue"
},
  "geometry": {"coordinates":[4.629111,52.404072],"type":"Point"}
}