{
  "type": "Feature",
  "properties": {
    "addr:full":"Kalverstr 177 Amsterdam Noord-Holland 1012 XB",
    "addr:housenumber":"177",
    "addr:postcode":"1012 xb",
    "iso:country":"NL",
    "sg:address":"Kalverstr 177",
    "sg:city":"Amsterdam",
    "sg:orig_category":"Schoenen",
    "sg:phone":"+31 20 623 3617",
    "sg:postcode":"1012 XB",
    "sg:province":"Noord-Holland",
    "sg:website":"http://www.cinderella.nl",
    "wof:name":"Cinderella",
    "wof:placetype":"venue"
},
  "geometry": {"coordinates":[4.891681,52.368259],"type":"Point"}
}