{
  "type": "Feature",
  "properties": {
    "addr:full":"Kapelwg 121 Amersfoort Utrecht 3818 BH",
    "addr:housenumber":"121",
    "addr:postcode":"3818 bh",
    "iso:country":"NL",
    "sg:address":"Kapelwg 121",
    "sg:city":"Amersfoort",
    "sg:orig_category":"Psychotherapeuten",
    "sg:phone":"+31 33 463 7570",
    "sg:postcode":"3818 BH",
    "sg:province":"Utrecht",
    "wof:name":"Berens Gesprekstherapie",
    "wof:placetype":"venue"
},
  "geometry": {"coordinates":[5.373274,52.138325],"type":"Point"}
}