{
  "type": "Feature",
  "properties": {
    "addr:full":"Orteliusstraat 316 Amsterdam Noord-Holland 1056 PR",
    "addr:housenumber":"316",
    "addr:postcode":"1056 pr",
    "addr:street":"Orteliusstraat",
    "iso:country":"NL",
    "sg:address":"Orteliusstraat 316",
    "sg:city":"Amsterdam",
    "sg:orig_category":"Diverse Grafische Activiteiten",
    "sg:phone":"+31 20 683 9862",
    "sg:postcode":"1056 PR",
    "sg:province":"Noord-Holland",
    "wof:name":"J J Rypkema",
    "wof:placetype":"venue"
},
  "geometry": {"coordinates":[4.847551,52.373592],"type":"Point"}
}