{
  "type": "Feature",
  "properties": {
    "addr:full":"Prinsengracht 130 Amsterdam Noord-Holland 1015 EB",
    "addr:housenumber":"130",
    "addr:postcode":"1015 eb",
    "addr:street":"Prinsengracht",
    "iso:country":"NL",
    "sg:address":"Prinsengracht 130",
    "sg:city":"Amsterdam",
    "sg:orig_category":"Herenmodezaken",
    "sg:phone":"+31 20 639 0320",
    "sg:postcode":"1015 EB",
    "sg:province":"Noord-Holland",
    "wof:name":"Arian Menswear",
    "wof:placetype":"venue"
},
  "geometry": {"coordinates":[4.883798,52.375938],"type":"Point"}
}