{
  "type": "Feature",
  "properties": {
    "addr:full":"Europaweg 188 Apeldoorn Gelderland 7336 AR",
    "addr:housenumber":"188",
    "addr:postcode":"7336",
    "addr:street":"Europaweg;Gelderland",
    "iso:country":"NL",
    "sg:address":"Europaweg 188",
    "sg:city":"Apeldoorn",
    "sg:orig_category":"Autokeuringen",
    "sg:phone":"+31 55 533 5522",
    "sg:postcode":"7336 AR",
    "sg:province":"Gelderland",
    "wof:name":"Uitlaat- En Remservice Europa",
    "wof:placetype":"venue"
},
  "geometry": {"coordinates":[5.937196,52.193939],"type":"Point"}
}