{
  "type": "Feature",
  "properties": {
    "addr:full":"Bleijerheiderstraat 102 Kerkrade Limburg 6462 AM",
    "addr:housenumber":"102",
    "addr:postcode":"6462",
    "addr:street":"Bleijerheiderstraat",
    "iso:country":"NL",
    "sg:address":"Bleijerheiderstraat 102",
    "sg:city":"Kerkrade",
    "sg:orig_category":"Bloemen And Planten",
    "sg:phone":"+31 45 545 2888",
    "sg:postcode":"6462 AM",
    "sg:province":"Limburg",
    "wof:name":"M L Dekonnink",
    "wof:placetype":"venue"
},
  "geometry": {"coordinates":[6.067486,50.854824],"type":"Point"}
}