{
  "type": "Feature",
  "properties": {
    "iso:country":"NL",
    "sg:address":"Scheendk 21-15",
    "sg:city":"Breukelen Ut",
    "sg:orig_category":"Accountants - Administratie- Consulenten En -Kantoren",
    "sg:phone":"+31 346 265 185",
    "sg:postcode":"3621 VC",
    "sg:province":"Utrecht",
    "wof:name":"Snijders, A J",
    "wof:placetype":"venue"
},
  "geometry": {"coordinates":[5.020621,52.178604],"type":"Point"}
}