{
  "type": "Feature",
  "properties": {
    "iso:country":"NL",
    "sg:address":"A Geesinkstr 9",
    "sg:city":"Utrecht",
    "sg:orig_category":"Sportverenigingen En Ontspannings- Verenigingen",
    "sg:phone":"+31 30 230 4967",
    "sg:postcode":"3552 BA",
    "sg:province":"Utrecht",
    "wof:name":"Aikikai Aikido Cult Sticht",
    "wof:placetype":"venue"
},
  "geometry": {"coordinates":[5.106248,52.105438],"type":"Point"}
}