{
  "type": "Feature",
  "properties": {
    "addr:full":"Hekselbrink 62 Enschede Overijssel 7544 BT",
    "addr:housenumber":"62",
    "addr:postcode":"7544 bt",
    "addr:street":"Hekselbrink",
    "iso:country":"NL",
    "sg:address":"Hekselbrink 62",
    "sg:city":"Enschede",
    "sg:orig_category":"Accountants - Administratie- Consulenten En -Kantoren",
    "sg:phone":"+31 53 477 7053",
    "sg:postcode":"7544 BT",
    "sg:province":"Overijssel",
    "wof:name":"Sanders",
    "wof:placetype":"venue"
},
  "geometry": {"coordinates":[6.870479,52.194916],"type":"Point"}
}