{
  "type": "Feature",
  "properties": {
    "addr:full":"Daltonstraat 13 Harderwijk Gelderland 3846 BX",
    "addr:housenumber":"13",
    "addr:postcode":"3846 bx",
    "addr:street":"Daltonstraat;Gelderland",
    "iso:country":"NL",
    "sg:address":"Daltonstraat 13",
    "sg:city":"Harderwijk",
    "sg:orig_category":"Kunststofverpakkingen Fab",
    "sg:phone":"+31 341 422 644",
    "sg:postcode":"3846 BX",
    "sg:province":"Gelderland",
    "wof:name":"Ringpack Bv",
    "wof:placetype":"venue"
},
  "geometry": {"coordinates":[5.647555,52.3615],"type":"Point"}
}