{
  "type": "Feature",
  "properties": {
    "addr:full":"Herenwg 19 Heemstede Noord-Holland 2105 MB",
    "addr:housenumber":"19",
    "addr:postcode":"2105 mb",
    "addr:street":"Herenwg",
    "iso:country":"NL",
    "sg:address":"Herenwg 19",
    "sg:city":"Heemstede",
    "sg:orig_category":"Binnenhuisarchitectuur",
    "sg:phone":"+31 23 524 3574",
    "sg:postcode":"2105 MB",
    "sg:province":"Noord-Holland",
    "wof:name":"Duo Disegno",
    "wof:placetype":"venue"
},
  "geometry": {"coordinates":[4.60335,52.336441],"type":"Point"}
}