{
  "type": "Feature",
  "properties": {
    "addr:full":"Alsacelaan 140 Eindhoven North Brabant 5627 CE",
    "addr:housenumber":"140",
    "addr:postcode":"5627 ce",
    "addr:street":"Alsacelaan",
    "iso:country":"NL",
    "sg:address":"Alsacelaan 140",
    "sg:city":"Eindhoven",
    "sg:orig_category":"Parfum And Cosmetica Gh",
    "sg:phone":"+31 40 242 9928",
    "sg:postcode":"5627 CE",
    "sg:province":"North Brabant",
    "wof:name":"Hado Cosmetics",
    "wof:placetype":"venue"
},
  "geometry": {"coordinates":[5.442436,51.485207],"type":"Point"}
}