{
  "type": "Feature",
  "properties": {
    "addr:full":"Weena 73 Rotterdam Zuid-Holland 3013 CH",
    "addr:housenumber":"73",
    "addr:postcode":"3013",
    "addr:street":"Weena",
    "iso:country":"NL",
    "sg:address":"Weena 73",
    "sg:city":"Rotterdam",
    "sg:orig_category":"Marktonderzoekbureaus",
    "sg:phone":"+31 10 282 4535",
    "sg:postcode":"3013 CH",
    "sg:province":"Zuid-Holland",
    "wof:name":"Skim Software Division Bv",
    "wof:placetype":"venue"
},
  "geometry": {"coordinates":[-73.944412,42.788071],"type":"Point"}
}