{
  "type": "Feature",
  "properties": {
    "addr:full":"Buorren 28 Terkaple Friesland 8542 AB",
    "addr:housenumber":"28",
    "addr:postcode":"8542 ab",
    "addr:street":"Buorren",
    "iso:country":"NL",
    "sg:address":"Buorren 28",
    "sg:city":"Terkaple",
    "sg:orig_category":"Horeca-Inrichtingen En -Uitrustingen",
    "sg:phone":"+31 566 689 897",
    "sg:postcode":"8542 AB",
    "sg:province":"Friesland",
    "wof:name":"Reserv 4",
    "wof:placetype":"venue"
},
  "geometry": {"coordinates":[5.787156,53.011879],"type":"Point"}
}