{
  "type": "Feature",
  "properties": {
    "addr:full":"Staphorster Kerkweg 40 Staphorst Overijssel 7951 JS",
    "addr:housenumber":"40",
    "addr:postcode":"7951 js",
    "addr:street":"Staphorster Kerkweg",
    "iso:country":"NL",
    "sg:address":"Staphorster Kerkweg 40",
    "sg:city":"Staphorst",
    "sg:classifiers":[
        {
            "category":"Education",
            "subcategory":"Preschool",
            "type":"Public Place"
        }
    ],
    "sg:phone":"+31 522 461 359",
    "sg:postcode":"7951 JS",
    "sg:province":"Overijssel",
    "sg:tags":[
        "kleuteronderwijs",
        "basis-"
    ],
    "wof:name":"Obs De Berkenhorst",
    "wof:placetype":"venue"
},
  "geometry": {"coordinates":[6.223439,52.632565],"type":"Point"}
}