{
  "type": "Feature",
  "properties": {
    "addr:full":"Waaigat 27 Amsterdam Noord-Holland 1018 AR",
    "addr:housenumber":"27",
    "addr:postcode":"1018",
    "addr:street":"Waaigat",
    "iso:country":"NL",
    "sg:address":"Waaigat 27",
    "sg:city":"Amsterdam",
    "sg:orig_category":"Verslagbureaus",
    "sg:phone":"+31 20 420 7183",
    "sg:postcode":"1018 AR",
    "sg:province":"Noord-Holland",
    "wof:name":"Greeuw, M",
    "wof:placetype":"venue"
},
  "geometry": {"coordinates":[-74.28478200000001,42.942238],"type":"Point"}
}