{
  "type": "Feature",
  "properties": {
    "addr:full":"Buitenerf 27A Breda Noord-Brabant 4824 HA",
    "addr:housenumber":"27a",
    "addr:postcode":"4824 ha",
    "addr:street":"Buitenerf",
    "iso:country":"NL",
    "sg:address":"Buitenerf 27A",
    "sg:city":"Breda",
    "sg:orig_category":"Psychotherapeuten",
    "sg:phone":"+31 76 542 5248",
    "sg:postcode":"4824 HA",
    "sg:province":"Noord-Brabant",
    "wof:name":"Labyrinthe",
    "wof:placetype":"venue"
},
  "geometry": {"coordinates":[4.749183,51.612061],"type":"Point"}
}