{
  "type": "Feature",
  "properties": {
    "addr:full":"Rijswijkseweg 648 'S Gravenhage Zuid-Holland 2516 HX",
    "addr:housenumber":"648 '",
    "addr:postcode":"2516 hx",
    "addr:street":"Rijswijkseweg",
    "iso:country":"NL",
    "sg:address":"Rijswijkseweg 648",
    "sg:city":"'S Gravenhage",
    "sg:orig_category":"Vertaal- And Tolkenbureaus",
    "sg:phone":"+31 70 319 3791",
    "sg:postcode":"2516 HX",
    "sg:province":"Zuid-Holland",
    "wof:name":"Jasa",
    "wof:placetype":"venue"
},
  "geometry": {"coordinates":[4.334737,52.060577],"type":"Point"}
}