{
  "type": "Feature",
  "properties": {
    "addr:full":"Kerkstraat 30 Boekel North Brabant 5427 BD",
    "addr:housenumber":"30",
    "addr:postcode":"5427 bd",
    "addr:street":"Kerkstraat",
    "iso:country":"NL",
    "sg:address":"Kerkstraat 30",
    "sg:city":"Boekel",
    "sg:orig_category":"Overheidsdiensten",
    "sg:phone":"+31 492 326 800",
    "sg:postcode":"5427 BD",
    "sg:province":"North Brabant",
    "wof:name":"Gemeente Boekel",
    "wof:placetype":"venue"
},
  "geometry": {"coordinates":[5.6734771729,51.6032752991],"type":"Point"}
}