{
  "type": "Feature",
  "properties": {
    "addr:full":"K Elisabethstr 13 Utrecht Utrecht 3511 JG",
    "addr:housenumber":"13",
    "addr:postcode":"3511 jg",
    "addr:street":"Elisabethstr",
    "iso:country":"NL",
    "sg:address":"K Elisabethstr 13",
    "sg:city":"Utrecht",
    "sg:orig_category":"Verenigingen En Stichtingen",
    "sg:phone":"+31 30 231 8222",
    "sg:postcode":"3511 JG",
    "sg:province":"Utrecht",
    "wof:name":"Landelijke Ver Groepswonen Van Ouderen",
    "wof:placetype":"venue"
},
  "geometry": {"coordinates":[5.115435,52.091331],"type":"Point"}
}