{
  "type": "Feature",
  "properties": {
    "iso:country":"NL",
    "sg:address":"Bos En Lommerwg 77",
    "sg:city":"Amsterdam",
    "sg:orig_category":"Makelaars En Adviseurs Onroerende Goederen",
    "sg:phone":"+31 20 684 8131",
    "sg:postcode":"1055 DP",
    "sg:province":"Noord-Holland",
    "wof:name":"Cbl Makelaars",
    "wof:placetype":"venue"
},
  "geometry": {"coordinates":[4.855769,52.38213],"type":"Point"}
}