{
  "type": "Feature",
  "properties": {
    "addr:full":"Heuvelbrink 86 Breda Noord-Brabant 4812 GT",
    "addr:housenumber":"86",
    "addr:postcode":"4812 gt",
    "addr:street":"Heuvelbrink",
    "iso:country":"NL",
    "sg:address":"Heuvelbrink 86",
    "sg:city":"Breda",
    "sg:orig_category":"Juridische Adviseurs",
    "sg:phone":"+31 76 515 6950",
    "sg:postcode":"4812 GT",
    "sg:province":"Noord-Brabant",
    "wof:name":"Lievaart, Krista",
    "wof:placetype":"venue"
},
  "geometry": {"coordinates":[4.750767,51.573822],"type":"Point"}
}