{
  "type": "Feature",
  "properties": {
    "iso:country":"NL",
    "sg:address":"Laageindse Stoep 1",
    "sg:city":"Waalwijk",
    "sg:orig_category":"Autokeuringen",
    "sg:phone":"+31 416 333 735",
    "sg:postcode":"5142 EK",
    "sg:province":"North Brabant",
    "wof:name":"Glasgarage Waalwijk",
    "wof:placetype":"venue"
},
  "geometry": {"coordinates":[5.080118,51.693111],"type":"Point"}
}