{
  "type": "Feature",
  "properties": {
    "addr:full":"Past V Kleefstr 21 Egmond Aan Zee Noord-Holland 1931 BL",
    "addr:housenumber":"21",
    "addr:postcode":"1931 bl",
    "addr:street":"Past;Kleefstr",
    "iso:country":"NL",
    "sg:address":"Past V Kleefstr 21",
    "sg:city":"Egmond Aan Zee",
    "sg:orig_category":"Artiesten/Gezelschappen",
    "sg:phone":"+31 72 507 0075",
    "sg:postcode":"1931 BL",
    "sg:province":"Noord-Holland",
    "wof:name":"Kaper, B",
    "wof:placetype":"venue"
},
  "geometry": {"coordinates":[4.630954,52.618732],"type":"Point"}
}