{
  "type": "Feature",
  "properties": {
    "addr:full":"Bunderstraat 19 Meerssen Limburg 6231 EH",
    "addr:housenumber":"19",
    "addr:postcode":"6231 eh",
    "addr:street":"Bunderstraat",
    "iso:country":"NL",
    "sg:address":"Bunderstraat 19",
    "sg:city":"Meerssen",
    "sg:orig_category":"Kappers",
    "sg:phone":"+31 43 364 2818",
    "sg:postcode":"6231 EH",
    "sg:province":"Limburg",
    "wof:name":"J A Ackermans Smeets",
    "wof:placetype":"venue"
},
  "geometry": {"coordinates":[5.751967907,50.8850250244],"type":"Point"}
}