{
  "type": "Feature",
  "properties": {
    "iso:country":"NL",
    "sg:address":"Vestdijk 133",
    "sg:city":"Eindhoven",
    "sg:orig_category":"Meubelzaken, Woning- And Keukeninrichting",
    "sg:phone":"+31 40 244 1344",
    "sg:postcode":"5611 CB",
    "sg:province":"Noord-Brabant",
    "wof:name":"Schellen Individueel Slaapcomport",
    "wof:placetype":"venue"
},
  "geometry": {"coordinates":[5.485687,51.435894],"type":"Point"}
}