{
  "type": "Feature",
  "properties": {
    "addr:full":"Toon Dupuisstraat 10 'S Gravenhage Zuid-Holland 2552 SB",
    "addr:housenumber":"10",
    "addr:postcode":"2552 sb",
    "addr:street":"Toon Dupuisstraat;' S",
    "iso:country":"NL",
    "sg:address":"Toon Dupuisstraat 10",
    "sg:city":"'S Gravenhage",
    "sg:orig_category":"Kinderopvang Behalve Thuis",
    "sg:phone":"+31 70 397 6327",
    "sg:postcode":"2552 SB",
    "sg:province":"Zuid-Holland",
    "wof:name":"Kinderdagverblijf Bolke Beer",
    "wof:placetype":"venue"
},
  "geometry": {"coordinates":[4.250901,52.055359],"type":"Point"}
}