{
  "type": "Feature",
  "properties": {
    "addr:full":"De Loper 4 Vlaardingen South Holland 3136 CN",
    "addr:housenumber":"4",
    "addr:postcode":"3136 cn",
    "addr:street":"De Loper",
    "iso:country":"NL",
    "sg:address":"De Loper 4",
    "sg:city":"Vlaardingen",
    "sg:orig_category":"Bloemen And Planten",
    "sg:phone":"+31 10 249 7050",
    "sg:postcode":"3136 CN",
    "sg:province":"South Holland",
    "wof:name":"Faunaland The Holy Bird",
    "wof:placetype":"venue"
},
  "geometry": {"coordinates":[4.347353,51.92989],"type":"Point"}
}