{
  "type": "Feature",
  "properties": {
    "addr:full":"Akkerwinde 1 Benschop Utrecht 3405 AT",
    "addr:housenumber":"1",
    "addr:postcode":"3405",
    "addr:street":"Akkerwinde",
    "iso:country":"NL",
    "sg:address":"Akkerwinde 1",
    "sg:city":"Benschop",
    "sg:orig_category":"Adviesbureaus Bedrijfsorganisatie",
    "sg:phone":"+31 348 451 540",
    "sg:postcode":"3405 AT",
    "sg:province":"Utrecht",
    "wof:name":"Polak",
    "wof:placetype":"venue"
},
  "geometry": {"coordinates":[4.984736,52.005367],"type":"Point"}
}