{
  "type": "Feature",
  "properties": {
    "iso:country":"NL",
    "sg:address":"Delfwg 37",
    "sg:city":"Noordwykerhout",
    "sg:orig_category":"Bloembollen - Groothandel",
    "sg:phone":"+31 252 532 313",
    "sg:postcode":"2211 VK",
    "sg:province":"Zuid-Holland",
    "sg:website":"http://www.bulbosa.nl",
    "wof:name":"Bulbosa Bv",
    "wof:placetype":"venue"
},
  "geometry": {"coordinates":[4.531562,52.285942],"type":"Point"}
}