{
  "type": "Feature",
  "properties": {
    "addr:full":"Grosthuizen 74 Avenhorn Noord-Holland 1633 EP",
    "addr:housenumber":"74",
    "addr:postcode":"1633 ep",
    "addr:street":"Grosthuizen",
    "iso:country":"NL",
    "sg:address":"Grosthuizen 74",
    "sg:city":"Avenhorn",
    "sg:orig_category":"Scholen Voor Basisonderwijs",
    "sg:phone":"+31 229 541 273",
    "sg:postcode":"1633 EP",
    "sg:province":"Noord-Holland",
    "wof:name":"Grosthuizersch Openb, De",
    "wof:placetype":"venue"
},
  "geometry": {"coordinates":[4.974436,52.617519],"type":"Point"}
}