{
  "type": "Feature",
  "properties": {
    "addr:full":"Beetzlaan 9 Soest Utrecht 3762 CA",
    "addr:housenumber":"9",
    "addr:postcode":"3762 ca",
    "addr:street":"Beetzlaan",
    "iso:country":"NL",
    "sg:address":"Beetzlaan 9",
    "sg:city":"Soest",
    "sg:orig_category":"Loodgieterswerk, Verwarming And Sanitaire Installaties",
    "sg:phone":"+31 35 601 3073",
    "sg:postcode":"3762 CA",
    "sg:province":"Utrecht",
    "wof:name":"W. Duijst",
    "wof:placetype":"venue"
},
  "geometry": {"coordinates":[5.28135,52.184586],"type":"Point"}
}