{
  "type": "Feature",
  "properties": {
    "iso:country":"NL",
    "sg:address":"Burg D Villeneuvesngl 24",
    "sg:city":"Rotterdam",
    "sg:orig_category":"Werving And Selectie Van Vast Personeel",
    "sg:phone":"+31 10 422 1251",
    "sg:postcode":"3055 AN",
    "sg:province":"South Holland",
    "wof:name":"Consultra Nederland",
    "wof:placetype":"venue"
},
  "geometry": {"coordinates":[4.5068898201,51.9613189697],"type":"Point"}
}