{
  "type": "Feature",
  "properties": {
    "addr:full":"Nassaukd 87/2Hg Amsterdam North Holland 1052 CV",
    "addr:housenumber":"87 / 2hg",
    "addr:postcode":"1052 cv",
    "addr:street":"Nassaukd",
    "iso:country":"NL",
    "sg:address":"Nassaukd 87/2Hg",
    "sg:city":"Amsterdam",
    "sg:orig_category":"Bloemen En Planten",
    "sg:phone":"+31 20 684 4914",
    "sg:postcode":"1052 CV",
    "sg:province":"North Holland",
    "wof:name":"Morning Glory",
    "wof:placetype":"venue"
},
  "geometry": {"coordinates":[4.87379,52.377899],"type":"Point"}
}