{
  "type": "Feature",
  "properties": {
    "addr:full":"Lavendel 17 Veenendaal Utrecht 3904 LM",
    "addr:housenumber":"17",
    "addr:postcode":"3904 lm",
    "addr:street":"Lavendel",
    "iso:country":"NL",
    "sg:address":"Lavendel 17",
    "sg:city":"Veenendaal",
    "sg:orig_category":"Webdesign Bureaus",
    "sg:phone":"+31 318 507 447",
    "sg:postcode":"3904 LM",
    "sg:province":"Utrecht",
    "sg:website":"http://www.inecom.nl",
    "wof:name":"Inecom",
    "wof:placetype":"venue"
},
  "geometry": {"coordinates":[5.551199913,52.0111808777],"type":"Point"}
}