{
  "type": "Feature",
  "properties": {
    "iso:country":"NL",
    "sg:address":"Demmerik 124",
    "sg:city":"Vinkeveen",
    "sg:orig_category":"Bloemen And Planten",
    "sg:phone":"+31 297 261 654",
    "sg:postcode":"3645 EG",
    "sg:province":"Utrecht",
    "wof:name":"F.A. Walter & Marijke Van Kouwen",
    "wof:placetype":"venue"
},
  "geometry": {"coordinates":[4.929787,52.200748],"type":"Point"}
}