{
  "type": "Feature",
  "properties": {
    "iso:country":"NL",
    "sg:address":"Herenstraat 88",
    "sg:city":"Voorhout",
    "sg:orig_category":"Bloemen And Planten",
    "sg:phone":"+31 252 211 641",
    "sg:postcode":"2215 KK",
    "sg:province":"Zuid-Holland",
    "wof:name":"Bouquetterie Tetteroo",
    "wof:placetype":"venue"
},
  "geometry": {"coordinates":[4.480927,52.221004],"type":"Point"}
}