{
  "type": "Feature",
  "properties": {
    "addr:full":"Twekkelerweg 70 Hengelo Ov Overijssel 7553 LN",
    "addr:housenumber":"70",
    "addr:postcode":"7553 ln",
    "addr:street":"Twekkelerweg;Ov",
    "iso:country":"NL",
    "sg:address":"Twekkelerweg 70",
    "sg:city":"Hengelo Ov",
    "sg:orig_category":"Voeding, Dranken And Tabak Gh",
    "sg:phone":"+31 74 250 0590",
    "sg:postcode":"7553 LN",
    "sg:province":"Overijssel",
    "wof:name":"Comert Bazaar International, Agentuur Co",
    "wof:placetype":"venue"
},
  "geometry": {"coordinates":[6.800507,52.258327],"type":"Point"}
}