{
  "type": "Feature",
  "properties": {
    "addr:full":"De Akkers 65 Schiedam South Holland 3124 AC",
    "addr:housenumber":"65",
    "addr:postcode":"3124 ac",
    "addr:street":"De Akkers",
    "iso:country":"NL",
    "sg:address":"De Akkers 65",
    "sg:city":"Schiedam",
    "sg:orig_category":"Metaalwerken",
    "sg:phone":"+31 10 247 0530",
    "sg:postcode":"3124 AC",
    "sg:province":"South Holland",
    "wof:name":"W.T.H. Dullaard Montage Bedrijf",
    "wof:placetype":"venue"
},
  "geometry": {"coordinates":[4.377146,51.941463],"type":"Point"}
}