{
  "type": "Feature",
  "properties": {
    "addr:full":"Graafschap Hornelaan 139 Weert Limburg 6001 AC",
    "addr:housenumber":"139",
    "addr:postcode":"6001 ac",
    "addr:street":"Graafschap Hornelaan",
    "iso:country":"NL",
    "sg:address":"Graafschap Hornelaan 139",
    "sg:city":"Weert",
    "sg:orig_category":"Goederenvervoer Over De Weg",
    "sg:phone":"+31 495 887 700",
    "sg:postcode":"6001 AC",
    "sg:province":"Limburg",
    "wof:name":"Wetron Internationale Transport Bv",
    "wof:placetype":"venue"
},
  "geometry": {"coordinates":[5.721964,51.261566],"type":"Point"}
}