{
  "type": "Feature",
  "properties": {
    "iso:country":"NL",
    "sg:address":"Burg Bickerstr 30",
    "sg:city":"Diemen",
    "sg:classifiers":[
        {
            "category":"Personal",
            "subcategory":"Nail Salon",
            "type":"Services"
        }
    ],
    "sg:phone":"+31 20 698 0523",
    "sg:postcode":"1111 CB",
    "sg:province":"Noord-Holland",
    "sg:tags":[
        "pedicure"
    ],
    "wof:name":"Moes-Kootstra, G",
    "wof:placetype":"venue"
},
  "geometry": {"coordinates":[4.96128,52.339382],"type":"Point"}
}