{
  "type": "Feature",
  "properties": {
    "addr:full":"Loostr 35 Loo Gld Gelderland 6924 AC",
    "addr:housenumber":"35",
    "addr:postcode":"6924 ac",
    "addr:street":"Loostr",
    "iso:country":"NL",
    "sg:address":"Loostr 35",
    "sg:city":"Loo Gld",
    "sg:orig_category":"Kinderopvang",
    "sg:phone":"+31 316 263 113",
    "sg:postcode":"6924 AC",
    "sg:province":"Gelderland",
    "sg:website":"http://www.de-kangoeroe.nl",
    "wof:name":"Bso Loo",
    "wof:placetype":"venue"
},
  "geometry": {"coordinates":[5.991276,51.930496],"type":"Point"}
}