{
  "type": "Feature",
  "properties": {
    "addr:full":"Prinses Beatrixweg 47 Geldermalsen Gelderland 4191 ZB",
    "addr:housenumber":"47",
    "addr:postcode":"4191 zb",
    "addr:street":"Prinses Beatrixweg;Gelderland",
    "iso:country":"NL",
    "sg:address":"Prinses Beatrixweg 47",
    "sg:city":"Geldermalsen",
    "sg:orig_category":"Metaalwerken",
    "sg:phone":"+31 345 576 221",
    "sg:postcode":"4191 ZB",
    "sg:province":"Gelderland",
    "wof:name":"Vab Vof",
    "wof:placetype":"venue"
},
  "geometry": {"coordinates":[5.30455,51.884537],"type":"Point"}
}