{
  "type": "Feature",
  "properties": {
    "addr:full":"Dorpsstr 64A Watergang Noord-Holland 1454 AM",
    "addr:housenumber":"64a",
    "addr:postcode":"1454",
    "addr:street":"Dorpsstr",
    "iso:country":"NL",
    "sg:address":"Dorpsstr 64A",
    "sg:city":"Watergang",
    "sg:orig_category":"Verenigingsgebouwen",
    "sg:phone":"+31 20 436 1253",
    "sg:postcode":"1454 AM",
    "sg:province":"Noord-Holland",
    "wof:name":"Nieuwe Boet, De",
    "wof:placetype":"venue"
},
  "geometry": {"coordinates":[4.952216,52.436733],"type":"Point"}
}