{
  "type": "Feature",
  "properties": {
    "addr:full":"Mauritskade 25 'S Gravenhage Zuid-Holland 2514 HD",
    "addr:housenumber":"25",
    "addr:postcode":"2514 hd",
    "addr:street":"Mauritskade;' S",
    "iso:country":"NL",
    "sg:address":"Mauritskade 25",
    "sg:city":"'S Gravenhage",
    "sg:orig_category":"Boekhouders",
    "sg:phone":"+31 70 346 3322",
    "sg:postcode":"2514 HD",
    "sg:province":"Zuid-Holland",
    "wof:name":"Advision Administr- En Belastingadv Kant",
    "wof:placetype":"venue"
},
  "geometry": {"coordinates":[4.307261,52.084644],"type":"Point"}
}