{
  "type": "Feature",
  "properties": {
    "addr:full":"Mandenmakerstr 190 Hoogvliet Rt Zuid-Holland 3194 DG",
    "addr:housenumber":"190",
    "addr:postcode":"rt;3194 dg",
    "iso:country":"NL",
    "sg:address":"Mandenmakerstr 190",
    "sg:city":"Hoogvliet Rt",
    "sg:orig_category":"Beveiliging",
    "sg:phone":"+31 10 416 6488",
    "sg:postcode":"3194 DG",
    "sg:province":"Zuid-Holland",
    "wof:name":"Waerd Bv, L B De",
    "wof:placetype":"venue"
},
  "geometry": {"coordinates":[4.37037,51.868671],"type":"Point"}
}