{
  "type": "Feature",
  "properties": {
    "addr:full":"Hoefkade 822 'S Gravenhage Zuid-Holland 2526 CV",
    "addr:housenumber":"822 '",
    "addr:postcode":"2526 cv",
    "addr:street":"Hoefkade",
    "iso:country":"NL",
    "sg:address":"Hoefkade 822",
    "sg:city":"'S Gravenhage",
    "sg:classifiers":[
        {
            "category":"Shopping",
            "subcategory":"Gifts & Souvenirs",
            "type":"Retail Goods"
        }
    ],
    "sg:phone":"+31 70 384 0462",
    "sg:postcode":"2526 CV",
    "sg:province":"Zuid-Holland",
    "sg:tags":[
        "geschenken"
    ],
    "wof:name":"Soliman",
    "wof:placetype":"venue"
},
  "geometry": {"coordinates":[4.310258,52.0667],"type":"Point"}
}