{
  "type": "Feature",
  "properties": {
    "addr:full":"Duinbeek 6 Eindhoven Noord-Brabant 5653 PM",
    "addr:housenumber":"6",
    "addr:postcode":"5653 pm",
    "addr:street":"Duinbeek",
    "iso:country":"NL",
    "sg:address":"Duinbeek 6",
    "sg:city":"Eindhoven",
    "sg:orig_category":"Public Relationbureaus",
    "sg:phone":"+31 40 252 8668",
    "sg:postcode":"5653 PM",
    "sg:province":"Noord-Brabant",
    "wof:name":"R. V.D. Werf",
    "wof:placetype":"venue"
},
  "geometry": {"coordinates":[5.441944,51.424927],"type":"Point"}
}