{
  "type": "Feature",
  "properties": {
    "addr:full":"Postbus 9022 Amstelveen Friesland 1180 MA",
    "addr:postcode":"9022;1180 ma",
    "addr:street":"Postbus",
    "iso:country":"NL",
    "sg:address":"Postbus 9022",
    "sg:city":"Amstelveen",
    "sg:orig_category":"Handwerkartikelen",
    "sg:phone":"+31 20 441 1625",
    "sg:postcode":"1180 MA",
    "sg:province":"Friesland",
    "sg:website":"http://www.handigzelf.nl",
    "wof:name":"Handig Zelf",
    "wof:placetype":"venue"
},
  "geometry": {"coordinates":[4.856945,52.303444],"type":"Point"}
}