{
  "type": "Feature",
  "properties": {
    "iso:country":"NL",
    "sg:address":"De Kiepe 54",
    "sg:city":"Enschede",
    "sg:orig_category":"Autoschade- Herstelbedrijven",
    "sg:phone":"+31 53 536 3656",
    "sg:postcode":"7544 HJ",
    "sg:province":"Overijssel",
    "wof:name":"Christenhuis, Autoschade",
    "wof:placetype":"venue"
},
  "geometry": {"coordinates":[6.884356,52.192333],"type":"Point"}
}