{
  "type": "Feature",
  "properties": {
    "iso:country":"NL",
    "sg:address":"Ackershof 9",
    "sg:city":"Pynacker",
    "sg:classifiers":[
        {
            "category":"Food & Beverages",
            "subcategory":"Bakery",
            "type":"Retail Goods"
        }
    ],
    "sg:phone":"+31 15 369 4977",
    "sg:postcode":"2641 DX",
    "sg:province":"Zuid-Holland",
    "sg:tags":[
        "brood",
        "en",
        "banket"
    ],
    "wof:name":"Rodenburg",
    "wof:placetype":"venue"
},
  "geometry": {"coordinates":[4.43285,52.018837],"type":"Point"}
}