{
  "type": "Feature",
  "properties": {
    "addr:full":"Kruisstraat 28 Haarlem North Holland 2011 PZ",
    "addr:housenumber":"28",
    "addr:postcode":"2011 pz",
    "addr:street":"Kruisstraat",
    "iso:country":"NL",
    "sg:address":"Kruisstraat 28",
    "sg:city":"Haarlem",
    "sg:orig_category":"Diverse Grafische Activiteiten",
    "sg:phone":"+31 23 531 5705",
    "sg:postcode":"2011 PZ",
    "sg:province":"North Holland",
    "wof:name":"Anne Rose Oosterbaan",
    "wof:placetype":"venue"
},
  "geometry": {"coordinates":[4.635631,52.383797],"type":"Point"}
}