{
  "type": "Feature",
  "properties": {
    "iso:country":"NL",
    "sg:address":"Lochemsewg 59",
    "sg:city":"Borculo",
    "sg:orig_category":"Vertaalbureaus",
    "sg:phone":"+31 545 275 751",
    "sg:postcode":"7271 WC",
    "sg:province":"Gelderland",
    "wof:name":"Tausk",
    "wof:placetype":"venue"
},
  "geometry": {"coordinates":[6.51966,52.123192],"type":"Point"}
}