{
  "type": "Feature",
  "properties": {
    "addr:full":"Mastbosstr 71 Breda North Brabant 4812 PA",
    "addr:housenumber":"71",
    "addr:postcode":"4812 pa",
    "addr:street":"Mastbosstr",
    "iso:country":"NL",
    "sg:address":"Mastbosstr 71",
    "sg:city":"Breda",
    "sg:orig_category":"Vertaalbureaus",
    "sg:phone":"+31 76 520 3332",
    "sg:postcode":"4812 PA",
    "sg:province":"North Brabant",
    "wof:name":"Martin J Koeman",
    "wof:placetype":"venue"
},
  "geometry": {"coordinates":[4.743372,51.57196],"type":"Point"}
}