{
  "type": "Feature",
  "properties": {
    "addr:full":"Hoogheuvelstr 112A Oss Noord-Brabant 5349 BA",
    "addr:housenumber":"112a",
    "addr:postcode":"5349 ba",
    "iso:country":"NL",
    "sg:address":"Hoogheuvelstr 112A",
    "sg:city":"Oss",
    "sg:orig_category":"Medische Installaties En Instrumenten",
    "sg:phone":"+31 412 653 335",
    "sg:postcode":"5349 BA",
    "sg:province":"Noord-Brabant",
    "wof:name":"Vectrys Bv",
    "wof:placetype":"venue"
},
  "geometry": {"coordinates":[-77.235214,38.312599],"type":"Point"}
}