{
  "type": "Feature",
  "properties": {
    "addr:full":"J Rekstr 1 Zaandam North Holland 1505 BA",
    "addr:housenumber":"1",
    "addr:postcode":"1505 ba",
    "iso:country":"NL",
    "sg:address":"J Rekstr 1",
    "sg:city":"Zaandam",
    "sg:orig_category":"Wasmachines En Wasdrogers - Onderhoud En Reparatie",
    "sg:phone":"+31 75 616 9517",
    "sg:postcode":"1505 BA",
    "sg:province":"North Holland",
    "wof:name":"Electroring Zanuservice",
    "wof:placetype":"venue"
},
  "geometry": {"coordinates":[4.8379979134,52.4355545044],"type":"Point"}
}