{
  "type": "Feature",
  "properties": {
    "addr:full":"Grietmansln 18 Oosterwolde Fr Friesland 8431 CS",
    "addr:housenumber":"18",
    "addr:postcode":"8431 cs",
    "addr:street":"Grietmansln",
    "iso:country":"NL",
    "sg:address":"Grietmansln 18",
    "sg:city":"Oosterwolde Fr",
    "sg:orig_category":"Fotoreportages",
    "sg:phone":"+31 516 514 162",
    "sg:postcode":"8431 CS",
    "sg:province":"Friesland",
    "wof:name":"Fred Platje Fotografie",
    "wof:placetype":"venue"
},
  "geometry": {"coordinates":[6.2899041176,52.9850997925],"type":"Point"}
}