{
  "type": "Feature",
  "properties": {
    "iso:country":"NL",
    "sg:address":"De Voorreep 118",
    "sg:city":"Erica",
    "sg:orig_category":"Kappers",
    "sg:phone":"+31 591 302 636",
    "sg:postcode":"7887 HC",
    "sg:province":"Drenthe",
    "wof:name":"Margriet",
    "wof:placetype":"venue"
},
  "geometry": {"coordinates":[6.927284,52.720863],"type":"Point"}
}