{
  "type": "Feature",
  "properties": {
    "iso:country":"NL",
    "sg:address":"Industriewg 20",
    "sg:city":"Sliedrecht",
    "sg:orig_category":"Lasapparaten En Benodigdheden",
    "sg:phone":"+31 184 419 333",
    "sg:postcode":"3361 HJ",
    "sg:province":"South Holland",
    "sg:website":"http://www.laspartners.nl",
    "wof:name":"Triton Bv",
    "wof:placetype":"venue"
},
  "geometry": {"coordinates":[4.764839,51.819283],"type":"Point"}
}