{
  "type": "Feature",
  "properties": {
    "addr:full":"Admiraal De Ruijterweg 139 Amsterdam Noord-Holland 1056 EZ",
    "addr:housenumber":"139",
    "addr:postcode":"1056 ez",
    "addr:street":"Admiraal De Ruijterweg",
    "iso:country":"NL",
    "sg:address":"Admiraal De Ruijterweg 139",
    "sg:city":"Amsterdam",
    "sg:orig_category":"Boekenuitgeverijen",
    "sg:phone":"+31 20 689 0494",
    "sg:postcode":"1056 EZ",
    "sg:province":"Noord-Holland",
    "wof:name":"Duizend En Een Uitgeverij",
    "wof:placetype":"venue"
},
  "geometry": {"coordinates":[4.858673,52.373474],"type":"Point"}
}