{
  "type": "Feature",
  "properties": {
    "addr:full":"Appelhof 5 Heukelum Gelderland 4161 BD",
    "addr:housenumber":"5",
    "addr:postcode":"4161 bd",
    "addr:street":"Appelhof;Gelderland",
    "iso:country":"NL",
    "sg:address":"Appelhof 5",
    "sg:city":"Heukelum",
    "sg:classifiers":[
        {
            "category":"Wholesale",
            "subcategory":"Meat",
            "type":"Manufacturing & Wholesale Goods"
        }
    ],
    "sg:phone":"+31 345 632 151",
    "sg:postcode":"4161 BD",
    "sg:province":"Gelderland",
    "sg:tags":[
        "abattoir"
    ],
    "wof:name":"Hoogenraad",
    "wof:placetype":"venue"
},
  "geometry": {"coordinates":[5.069928,51.872723],"type":"Point"}
}