{
  "type": "Feature",
  "properties": {
    "iso:country":"NL",
    "sg:address":"Strandweg 12",
    "sg:city":"'S Gravenhage",
    "sg:classifiers":[
        {
            "category":"Fast Food",
            "type":"Food & Drink"
        }
    ],
    "sg:phone":"+31 70 354 5545",
    "sg:postcode":"2586 JK",
    "sg:province":"Zuid-Holland",
    "sg:tags":[
        "afhaal",
        "restaurant"
    ],
    "wof:name":"Paviljoen La Playa",
    "wof:placetype":"venue"
},
  "geometry": {"coordinates":[4.28358,52.115429],"type":"Point"}
}