{
  "type": "Feature",
  "properties": {
    "addr:full":"Burg Hoogenboomln 52 Hoogwoud Noord-Holland 1718 BK",
    "addr:housenumber":"52",
    "addr:postcode":"1718 bk",
    "addr:street":"Burg",
    "iso:country":"NL",
    "sg:address":"Burg Hoogenboomln 52",
    "sg:city":"Hoogwoud",
    "sg:orig_category":"Kappers",
    "sg:phone":"+31 226 351 361",
    "sg:postcode":"1718 BK",
    "sg:province":"Noord-Holland",
    "wof:name":"Bosman, Yvonne",
    "wof:placetype":"venue"
},
  "geometry": {"coordinates":[4.9378561974,52.7181549072],"type":"Point"}
}