{
  "type": "Feature",
  "properties": {
    "addr:full":"Witte Paal 149 Schagen North Holland 1742 NX",
    "addr:housenumber":"149",
    "addr:postcode":"1742 nx",
    "addr:street":"Witte Paal",
    "iso:country":"NL",
    "sg:address":"Witte Paal 149",
    "sg:city":"Schagen",
    "sg:orig_category":"Binnenhuisarchitecten",
    "sg:phone":"+31 224 217 356",
    "sg:postcode":"1742 NX",
    "sg:province":"North Holland",
    "wof:name":"Vof Roly Design",
    "wof:placetype":"venue"
},
  "geometry": {"coordinates":[4.810962,52.775688],"type":"Point"}
}