{
  "type": "Feature",
  "properties": {
    "addr:full":"De Factory 24 Zwaag North Holland 1689 AL",
    "addr:housenumber":"24;1689",
    "addr:postcode":"al",
    "addr:street":"De;Holland",
    "iso:country":"NL",
    "sg:address":"De Factory 24",
    "sg:city":"Zwaag",
    "sg:orig_category":"Hijswerktuigen",
    "sg:phone":"+31 229 212 698",
    "sg:postcode":"1689 AL",
    "sg:province":"North Holland",
    "sg:website":"http://www.cranerepair.com",
    "wof:name":"Rusch Bv",
    "wof:placetype":"venue"
},
  "geometry": {"coordinates":[5.065114,52.669537],"type":"Point"}
}