{
  "type": "Feature",
  "properties": {
    "addr:full":"Herengracht 510 Amsterdam Noord-Holland 1017 CC",
    "addr:housenumber":"510",
    "addr:postcode":"1017 cc",
    "addr:street":"Herengracht",
    "iso:country":"NL",
    "sg:address":"Herengracht 510",
    "sg:city":"Amsterdam",
    "sg:orig_category":"Kunst And Kunstenaarsbenodigdheden",
    "sg:phone":"+31 20 627 7784",
    "sg:postcode":"1017 CC",
    "sg:province":"Noord-Holland",
    "wof:name":"Golden Bend",
    "wof:placetype":"venue"
},
  "geometry": {"coordinates":[4.893903,52.364719],"type":"Point"}
}