{
  "type": "Feature",
  "properties": {
    "addr:full":"Heikant 18 Kaatsheuvel North Brabant 5171 KM",
    "addr:housenumber":"18",
    "addr:postcode":"5171 km",
    "addr:street":"Heikant",
    "iso:country":"NL",
    "sg:address":"Heikant 18",
    "sg:city":"Kaatsheuvel",
    "sg:orig_category":"Verzekeringen",
    "sg:phone":"+31 416 272 759",
    "sg:postcode":"5171 KM",
    "sg:province":"North Brabant",
    "wof:name":"Assurantiekantoor J. Van Der Kaa",
    "wof:placetype":"venue"
},
  "geometry": {"coordinates":[5.042723,51.654778],"type":"Point"}
}