{
  "type": "Feature",
  "properties": {
    "addr:full":"Schoterweg 1 Haarlem North Holland 2021 HZ",
    "addr:housenumber":"1",
    "addr:postcode":"2021 hz",
    "addr:street":"Schoterweg",
    "iso:country":"NL",
    "sg:address":"Schoterweg 1",
    "sg:city":"Haarlem",
    "sg:orig_category":"Makelaars In Onroerend Goed",
    "sg:phone":"+31 23 525 6542",
    "sg:postcode":"2021 HZ",
    "sg:province":"North Holland",
    "wof:name":"Ag Makelaars Og",
    "wof:placetype":"venue"
},
  "geometry": {"coordinates":[4.640567,52.390957],"type":"Point"}
}