{
  "type": "Feature",
  "properties": {
    "iso:country":"NL",
    "sg:address":"Hogeweg 26",
    "sg:city":"Burgh Haamstede",
    "sg:orig_category":"Kampeerterreinen",
    "sg:phone":"+31 111 651 328",
    "sg:postcode":"4328 PD",
    "sg:province":"Zeeland",
    "wof:name":"Camping Rozenhof",
    "wof:placetype":"venue"
},
  "geometry": {"coordinates":[3.7279679775,51.6879005432],"type":"Point"}
}