{
  "type": "Feature",
  "properties": {
    "addr:full":"Boekenburglaan 151 Voorhout South Holland 2215 AC",
    "addr:housenumber":"151",
    "addr:postcode":"2215 ac",
    "addr:street":"Boekenburglaan",
    "iso:country":"NL",
    "sg:address":"Boekenburglaan 151",
    "sg:city":"Voorhout",
    "sg:orig_category":"Verzekeringen",
    "sg:phone":"+31 252 218 206",
    "sg:postcode":"2215 AC",
    "sg:province":"South Holland",
    "wof:name":"Max Berend Pensioenadvies",
    "wof:placetype":"venue"
},
  "geometry": {"coordinates":[4.480052,52.226357],"type":"Point"}
}