{
  "type": "Feature",
  "properties": {
    "addr:full":"Tuinbouwweg 41 Haarsteeg Noord-Brabant 5254  V",
    "addr:housenumber":"41",
    "addr:postcode":"5254 v",
    "addr:street":"Tuinbouwweg",
    "iso:country":"NL",
    "sg:address":"Tuinbouwweg 41",
    "sg:city":"Haarsteeg",
    "sg:classifiers":[
        {
            "category":"Retail",
            "subcategory":"Storage",
            "type":"Services"
        }
    ],
    "sg:phone":"+31 73 511 2509",
    "sg:postcode":"5254  V",
    "sg:province":"Noord-Brabant",
    "sg:tags":[
        "opslag",
        "bewaring"
    ],
    "wof:name":"Boom Vlijmen B.V.",
    "wof:placetype":"venue"
},
  "geometry": {"coordinates":[5.2016801834,51.709854126],"type":"Point"}
}