{
  "type": "Feature",
  "properties": {
    "addr:full":"Postweg 1 De Lutte Overijssel 7587 PB",
    "addr:housenumber":"1",
    "addr:postcode":"7587 pb",
    "addr:street":"Postweg",
    "iso:country":"NL",
    "sg:address":"Postweg 1",
    "sg:city":"De Lutte",
    "sg:orig_category":"Bloemen And Planten",
    "sg:phone":"+31 541 515 624",
    "sg:postcode":"7587 PB",
    "sg:province":"Overijssel",
    "wof:name":"Bloemsierkunst G. Uit Het Broek",
    "wof:placetype":"venue"
},
  "geometry": {"coordinates":[6.946859,52.293156],"type":"Point"}
}