{
  "type": "Feature",
  "properties": {
    "addr:full":"Rapenburg 1D Rynsburg Zuid-Holland 2231 GG",
    "addr:housenumber":"1d",
    "addr:postcode":"2231 gg",
    "addr:street":"Rapenburg",
    "iso:country":"NL",
    "sg:address":"Rapenburg 1D",
    "sg:city":"Rynsburg",
    "sg:orig_category":"Administratie- En Boekhoudkantoren",
    "sg:phone":"+31 71 408 5638",
    "sg:postcode":"2231 GG",
    "sg:province":"Zuid-Holland",
    "wof:name":"Egmond, G W Van",
    "wof:placetype":"venue"
},
  "geometry": {"coordinates":[4.439839,52.191402],"type":"Point"}
}