{
  "type": "Feature",
  "properties": {
    "iso:country":"NL",
    "sg:address":"Pastoor Verburghlaan 8",
    "sg:city":"Schipluiden",
    "sg:orig_category":"Boekhouders",
    "sg:phone":"+31 174 523 220",
    "sg:postcode":"2636 HA",
    "sg:province":"Zuid-Holland",
    "wof:name":"O M Stolze",
    "wof:placetype":"venue"
},
  "geometry": {"coordinates":[4.31591,51.97718],"type":"Point"}
}