{
  "type": "Feature",
  "properties": {
    "addr:full":"Oosterhoutsestr 18 Oosterhout Gld Gelderland 6678 PB",
    "addr:housenumber":"18",
    "addr:postcode":"6678 pb",
    "addr:street":"Oosterhoutsestr;Gld Gelderland",
    "iso:country":"NL",
    "sg:address":"Oosterhoutsestr 18",
    "sg:city":"Oosterhout Gld",
    "sg:orig_category":"Verenigingen En Stichtingen",
    "sg:phone":"+31 481 481 128",
    "sg:postcode":"6678 PB",
    "sg:province":"Gelderland",
    "wof:name":"Spilhuis, Sticht Het",
    "wof:placetype":"venue"
},
  "geometry": {"coordinates":[5.825978,51.882881],"type":"Point"}
}