{
  "type": "Feature",
  "properties": {
    "addr:full":"Marktkade 100 Musselkanaal Groningen 9581 AW",
    "addr:housenumber":"100",
    "addr:postcode":"9581 aw",
    "addr:street":"Marktkade",
    "iso:country":"NL",
    "sg:address":"Marktkade 100",
    "sg:city":"Musselkanaal",
    "sg:orig_category":"Begrafenisondernemers",
    "sg:phone":"+31 599 417 200",
    "sg:postcode":"9581 AW",
    "sg:province":"Groningen",
    "wof:name":"Eerste Neutrale Begrafenisver. Musselkanaal",
    "wof:placetype":"venue"
},
  "geometry": {"coordinates":[7.016811,52.926758],"type":"Point"}
}