{
  "type": "Feature",
  "properties": {
    "addr:full":"Haarlemmerstr 145 Leiden Zuid-Holland 2312 DN",
    "addr:housenumber":"145",
    "addr:postcode":"2312 dn",
    "iso:country":"NL",
    "sg:address":"Haarlemmerstr 145",
    "sg:city":"Leiden",
    "sg:orig_category":"Huishoudelijke Apparaten En Artikelen",
    "sg:phone":"+31 71 514 2814",
    "sg:postcode":"2312 DN",
    "sg:province":"Zuid-Holland",
    "wof:name":"Blokker Bv",
    "wof:placetype":"venue"
},
  "geometry": {"coordinates":[4.492307,52.160099],"type":"Point"}
}