{
  "type": "Feature",
  "properties": {
    "addr:full":"Kromhoutstraat 50 Ijmuiden North Holland 1976 BM",
    "addr:housenumber":"50",
    "addr:postcode":"1976 bm",
    "addr:street":"Kromhoutstraat",
    "iso:country":"NL",
    "sg:address":"Kromhoutstraat 50",
    "sg:city":"Ijmuiden",
    "sg:orig_category":"Goederenvervoer Over De Weg",
    "sg:phone":"+31 255 510 621",
    "sg:postcode":"1976 BM",
    "sg:province":"North Holland",
    "wof:name":"Zuidam Transport Bv",
    "wof:placetype":"venue"
},
  "geometry": {"coordinates":[4.586914,52.454536],"type":"Point"}
}