{
  "type": "Feature",
  "properties": {
    "iso:country":"NL",
    "sg:address":"Maliskampsestr 12",
    "sg:city":"Rosmalen",
    "sg:orig_category":"Adviesbureaus Bouwkunde",
    "sg:phone":"+31 73 523 0877",
    "sg:postcode":"5248 AD",
    "sg:province":"Noord-Brabant",
    "wof:name":"Wb",
    "wof:placetype":"venue"
},
  "geometry": {"coordinates":[5.379944,51.70694],"type":"Point"}
}