{
  "type": "Feature",
  "properties": {
    "addr:full":"P Potterwg 63 Groesbeek Gelderland 6562 XK",
    "addr:housenumber":"63",
    "addr:postcode":"6562 xk",
    "addr:street":"P;Gelderland",
    "iso:country":"NL",
    "sg:address":"P Potterwg 63",
    "sg:city":"Groesbeek",
    "sg:orig_category":"Artsen - Huisartsen",
    "sg:phone":"+31 24 397 4004",
    "sg:postcode":"6562 XK",
    "sg:province":"Gelderland",
    "wof:name":"Roessingh, B M",
    "wof:placetype":"venue"
},
  "geometry": {"coordinates":[5.934224,51.771751],"type":"Point"}
}