{
  "type": "Feature",
  "properties": {
    "addr:full":"Postbus 811 Arnhem Gelderland 6800 AV",
    "addr:housenumber":"811",
    "addr:postcode":"6800 av",
    "addr:street":"Postbus",
    "iso:country":"NL",
    "sg:address":"Postbus 811",
    "sg:city":"Arnhem",
    "sg:orig_category":"Verenigingen En Stichtingen",
    "sg:phone":"+31 26 351 6533",
    "sg:postcode":"6800 AV",
    "sg:province":"Gelderland",
    "sg:website":"http://www.doca.nl",
    "wof:name":"Doca Dokumentatiecentr Arnhem",
    "wof:placetype":"venue"
},
  "geometry": {"coordinates":[5.9124,51.979729],"type":"Point"}
}