{
  "type": "Feature",
  "properties": {
    "addr:full":"De Oude Veiling 49 Zwaag North Holland 1689 AB",
    "addr:housenumber":"49",
    "addr:postcode":"1689 ab",
    "addr:street":"De Oude Veiling;Holland",
    "iso:country":"NL",
    "sg:address":"De Oude Veiling 49",
    "sg:city":"Zwaag",
    "sg:orig_category":"Kasten - Fabrieken En Groothandel",
    "sg:phone":"+31 229 233 303",
    "sg:postcode":"1689 AB",
    "sg:province":"North Holland",
    "sg:website":"http://www.ronaldschouwink.nl",
    "wof:name":"Ronald Schouwink",
    "wof:placetype":"venue"
},
  "geometry": {"coordinates":[5.062005,52.662704],"type":"Point"}
}