{
  "type": "Feature",
  "properties": {
    "addr:full":"Aalsterwg 69-73 Eindhoven Noord-Brabant 5615 CB",
    "addr:housenumber":"69-73",
    "addr:postcode":"5615 cb",
    "iso:country":"NL",
    "sg:address":"Aalsterwg 69-73",
    "sg:city":"Eindhoven",
    "sg:orig_category":"Bruidskleding",
    "sg:phone":"+31 40 293 0905",
    "sg:postcode":"5615 CB",
    "sg:province":"Noord-Brabant",
    "sg:website":"http://www.bruidsmode.net",
    "wof:name":"Ann & John Bruidsmode",
    "wof:placetype":"venue"
},
  "geometry": {"coordinates":[5.486396,51.425926],"type":"Point"}
}