{
  "type": "Feature",
  "properties": {
    "iso:country":"NL",
    "sg:address":"Prins Bernhardplein 10",
    "sg:city":"Nuland",
    "sg:orig_category":"Overheidsdiensten",
    "sg:phone":"+31 73 532 1844",
    "sg:postcode":"5391 AR",
    "sg:province":"North Brabant",
    "wof:name":"Gemeenschapshuis",
    "wof:placetype":"venue"
},
  "geometry": {"coordinates":[5.4332671165,51.7282142639],"type":"Point"}
}