{
  "type": "Feature",
  "properties": {
    "addr:full":"Rosendaalsestr 414 Arnhem Gelderland 6824 CS",
    "addr:housenumber":"414",
    "addr:postcode":"6824 cs",
    "iso:country":"NL",
    "sg:address":"Rosendaalsestr 414",
    "sg:city":"Arnhem",
    "sg:orig_category":"Meubelmakerijen",
    "sg:phone":"+31 26 364 3030",
    "sg:postcode":"6824 CS",
    "sg:province":"Gelderland",
    "wof:name":"Meubelen Op Maat",
    "wof:placetype":"venue"
},
  "geometry": {"coordinates":[5.929125,51.990273],"type":"Point"}
}