{
  "type": "Feature",
  "properties": {
    "addr:full":"Egter Van Wissekerkeweg 5 Poederoijen Gelderland 5307 VA",
    "addr:housenumber":"5",
    "addr:postcode":"5307",
    "addr:street":"Egter Van Wissekerkeweg;Gelderland",
    "iso:country":"NL",
    "sg:address":"Egter Van Wissekerkeweg 5",
    "sg:city":"Poederoijen",
    "sg:orig_category":"Loodgieterswerk, Verwarming And Sanitaire Installaties",
    "sg:phone":"+31 418 671 647",
    "sg:postcode":"5307 VA",
    "sg:province":"Gelderland",
    "wof:name":"Technische Handels Onderneming Bakker",
    "wof:placetype":"venue"
},
  "geometry": {"coordinates":[-79.771446,38.003349],"type":"Point"}
}