{
  "type": "Feature",
  "properties": {
    "iso:country":"NL",
    "sg:address":"Egter Van Wissekerkeweg 5",
    "sg:city":"Poederoijen",
    "sg:orig_category":"Loodgieterswerk, Verwarming And Sanitaire Installaties",
    "sg:phone":"+31 418 671 647",
    "sg:postcode":"5307 VA",
    "sg:province":"Gelderland",
    "wof:name":"Technische Handels Onderneming Bakker",
    "wof:placetype":"venue"
},
  "geometry": {"coordinates":[-79.771446,38.003349],"type":"Point"}
}