{
  "type": "Feature",
  "properties": {
    "addr:full":"Pr J Frisoplaats 1 Tricht Gelderland 4196 AC",
    "addr:housenumber":"1",
    "addr:postcode":"4196 ac",
    "addr:street":"Frisoplaats;Gelderland",
    "iso:country":"NL",
    "sg:address":"Pr J Frisoplaats 1",
    "sg:city":"Tricht",
    "sg:orig_category":"Verenigingsgebouwen",
    "sg:phone":"+31 345 574 377",
    "sg:postcode":"4196 AC",
    "sg:province":"Gelderland",
    "wof:name":"Dorpshuis Tricht",
    "wof:placetype":"venue"
},
  "geometry": {"coordinates":[5.270542,51.890465],"type":"Point"}
}