{
  "type": "Feature",
  "properties": {
    "addr:full":"Provenierssngl 29 Rotterdam South Holland 3033 EE",
    "addr:housenumber":"29",
    "addr:postcode":"3033 ee",
    "addr:street":"Provenierssngl",
    "iso:country":"NL",
    "sg:address":"Provenierssngl 29",
    "sg:city":"Rotterdam",
    "sg:orig_category":"Organisatiebureaus",
    "sg:phone":"+31 10 467 6898",
    "sg:postcode":"3033 EE",
    "sg:province":"South Holland",
    "wof:name":"Turpin",
    "wof:placetype":"venue"
},
  "geometry": {"coordinates":[4.4719290733,51.9279136658],"type":"Point"}
}