{
  "type": "Feature",
  "properties": {
    "iso:country":"NL",
    "sg:address":"Bodendk 118",
    "sg:city":"Aalten",
    "sg:orig_category":"Adviesbureaus",
    "sg:phone":"+31 543 471 162",
    "sg:postcode":"7123 AA",
    "sg:province":"Gelderland",
    "wof:name":"Vaags, L E",
    "wof:placetype":"venue"
},
  "geometry": {"coordinates":[6.588274,51.913563],"type":"Point"}
}