{
  "type": "Feature",
  "properties": {
    "addr:full":"Kladde 19 Lepelstraat Noord-Brabant 4664 TB",
    "addr:housenumber":"19",
    "addr:postcode":"4664 tb",
    "addr:street":"Kladde",
    "iso:country":"NL",
    "sg:address":"Kladde 19",
    "sg:city":"Lepelstraat",
    "sg:orig_category":"Onderhoudswerken",
    "sg:phone":"+31 164 686 730",
    "sg:postcode":"4664 TB",
    "sg:province":"Noord-Brabant",
    "wof:name":"Bergh, Van Den",
    "wof:placetype":"venue"
},
  "geometry": {"coordinates":[4.26599,51.56435],"type":"Point"}
}