{
  "type": "Feature",
  "properties": {
    "addr:full":"Huygensstraat 27 Hilversum North Holland 1222 TJ",
    "addr:housenumber":"27",
    "addr:postcode":"1222 tj",
    "addr:street":"Huygensstraat",
    "iso:country":"NL",
    "sg:address":"Huygensstraat 27",
    "sg:city":"Hilversum",
    "sg:orig_category":"Boekhouders",
    "sg:phone":"+31 35 683 0881",
    "sg:postcode":"1222 TJ",
    "sg:province":"North Holland",
    "wof:name":"Adm Kantoor K Been",
    "wof:placetype":"venue"
},
  "geometry": {"coordinates":[5.180781,52.231625],"type":"Point"}
}