{
  "type": "Feature",
  "properties": {
    "addr:full":"Zuiderdiep 71 Valthermond Provincie Drenthe 7876 AD",
    "addr:housenumber":"71",
    "addr:postcode":"7876 ad",
    "addr:street":"Zuiderdiep;Provincie Drenthe",
    "iso:country":"NL",
    "sg:address":"Zuiderdiep 71",
    "sg:city":"Valthermond",
    "sg:orig_category":"Verenigingsgebouwen",
    "sg:phone":"+31 599 661 405",
    "sg:postcode":"7876 AD",
    "sg:province":"Provincie Drenthe",
    "wof:name":"Veurh\u00f4f, 'T",
    "wof:placetype":"venue"
},
  "geometry": {"coordinates":[6.923125,52.861607],"type":"Point"}
}