{
  "type": "Feature",
  "properties": {
    "addr:full":"L Hei 11 Sprundel North Brabant 4714 RE",
    "addr:housenumber":"11",
    "addr:postcode":"4714 re",
    "addr:street":"L Hei",
    "iso:country":"NL",
    "sg:address":"L Hei 11",
    "sg:city":"Sprundel",
    "sg:orig_category":"Plastic Verwerkende Industrie",
    "sg:phone":"+31 165 383 236",
    "sg:postcode":"4714 RE",
    "sg:province":"North Brabant",
    "wof:name":"Ckv",
    "wof:placetype":"venue"
},
  "geometry": {"coordinates":[4.601045,51.538265],"type":"Point"}
}