{
  "type": "Feature",
  "properties": {
    "addr:full":"Koldingwg 16 Groningen Groningen 9723 HK",
    "addr:housenumber":"16",
    "addr:postcode":"9723 hk",
    "addr:street":"Koldingwg",
    "iso:country":"NL",
    "sg:address":"Koldingwg 16",
    "sg:city":"Groningen",
    "sg:orig_category":"Automaterialen En Gereedschappen",
    "sg:phone":"+31 50 549 6111",
    "sg:postcode":"9723 HK",
    "sg:province":"Groningen",
    "sg:website":"http://www.brezan.nl",
    "wof:name":"Brezan",
    "wof:placetype":"venue"
},
  "geometry": {"coordinates":[6.607463,53.22049],"type":"Point"}
}