{
  "type": "Feature",
  "properties": {
    "iso:country":"NL",
    "sg:address":"H Seghersstr 43",
    "sg:city":"Amsterdam",
    "sg:orig_category":"Koeriersdiensten",
    "sg:phone":"+31 20 679 2752",
    "sg:postcode":"1072 LZ",
    "sg:province":"North Holland",
    "wof:name":"Ariston",
    "wof:placetype":"venue"
},
  "geometry": {"coordinates":[4.88868,52.353844],"type":"Point"}
}