{
  "type": "Feature",
  "properties": {
    "iso:country":"NL",
    "sg:address":"Hoofdstraat 34",
    "sg:city":"Meedhuizen",
    "sg:orig_category":"Huishoudapparatuur, Televisies And Radio'S",
    "sg:phone":"+31 596 533 537",
    "sg:postcode":"9937 PE",
    "sg:province":"Groningen",
    "wof:name":"Technisch Bedrijf Wich",
    "wof:placetype":"venue"
},
  "geometry": {"coordinates":[6.911031,53.285515],"type":"Point"}
}