{
  "type": "Feature",
  "properties": {
    "iso:country":"NL",
    "sg:address":"Hoofdwg 716",
    "sg:city":"Hoofddorp",
    "sg:orig_category":"Hypotheken",
    "sg:phone":"+31 23 569 8530",
    "sg:postcode":"2132 BV",
    "sg:province":"Noord-Holland",
    "sg:website":"http://www.alphahypotheken.nl",
    "wof:name":"Alpha",
    "wof:placetype":"venue"
},
  "geometry": {"coordinates":[4.691686,52.304432],"type":"Point"}
}