{
  "type": "Feature",
  "properties": {
    "addr:full":"Rijksweg Zuid 18 Elst Gld Gelderland 6662 KD",
    "addr:housenumber":"18",
    "addr:postcode":"6662 kd",
    "addr:street":"Rijksweg Zuid;Gld Gelderland",
    "iso:country":"NL",
    "sg:address":"Rijksweg Zuid 18",
    "sg:city":"Elst Gld",
    "sg:orig_category":"Verzekeringen",
    "sg:phone":"+31 481 371 986",
    "sg:postcode":"6662 KD",
    "sg:province":"Gelderland",
    "wof:name":"Assurantiekantoor Koobs De Hartog",
    "wof:placetype":"venue"
},
  "geometry": {"coordinates":[5.848416,51.917793],"type":"Point"}
}