{
  "type": "Feature",
  "properties": {
    "addr:full":"Torenln 14 Hengelo Ov Overijssel 7559 PJ",
    "addr:housenumber":"14",
    "addr:postcode":"7559 pj",
    "addr:street":"Torenln;Ov",
    "iso:country":"NL",
    "sg:address":"Torenln 14",
    "sg:city":"Hengelo Ov",
    "sg:orig_category":"Parketvloeren",
    "sg:phone":"+31 74 277 7879",
    "sg:postcode":"7559 PJ",
    "sg:province":"Overijssel",
    "sg:website":"http://www.dejongparkethengelo.nl",
    "wof:name":"Jong Parket Hengelo, De",
    "wof:placetype":"venue"
},
  "geometry": {"coordinates":[6.81299,52.283512],"type":"Point"}
}