{
  "type": "Feature",
  "properties": {
    "addr:full":"Geleenstraat 26 Heerlen Limburg 6411 HS",
    "addr:housenumber":"26",
    "addr:postcode":"6411 hs",
    "addr:street":"Geleenstraat",
    "iso:country":"NL",
    "sg:address":"Geleenstraat 26",
    "sg:city":"Heerlen",
    "sg:orig_category":"Baby- And Kinderkleding",
    "sg:phone":"+31 45 571 2341",
    "sg:postcode":"6411 HS",
    "sg:province":"Limburg",
    "wof:name":"Peek & Cloppenburg ( P&C)",
    "wof:placetype":"venue"
},
  "geometry": {"coordinates":[5.977814,50.887238],"type":"Point"}
}