{
  "type": "Feature",
  "properties": {
    "iso:country":"NL",
    "sg:address":"Ruysdaelkade 177/179",
    "sg:city":"Amsterdam",
    "sg:orig_category":"Autokeuringen",
    "sg:phone":"+31 20 675 6580",
    "sg:postcode":"1072 AT",
    "sg:province":"Noord-Holland",
    "wof:name":"Selling Motorschade Service",
    "wof:placetype":"venue"
},
  "geometry": {"coordinates":[4.887021,52.352749],"type":"Point"}
}