{
  "type": "Feature",
  "properties": {
    "addr:full":"Boswg 19 Opende Groningen 9865 XB",
    "addr:housenumber":"19",
    "addr:postcode":"9865 xb",
    "addr:street":"Boswg",
    "iso:country":"NL",
    "sg:address":"Boswg 19",
    "sg:city":"Opende",
    "sg:orig_category":"Adviesbureaus",
    "sg:phone":"+31 594 659 072",
    "sg:postcode":"9865 XB",
    "sg:province":"Groningen",
    "wof:name":"Opa",
    "wof:placetype":"venue"
},
  "geometry": {"coordinates":[6.211425,53.160049],"type":"Point"}
}