{
  "type": "Feature",
  "properties": {
    "addr:full":"Rijnstraat 29 Woerden Utrecht 3441 BP",
    "addr:housenumber":"29",
    "addr:postcode":"3441 bp",
    "addr:street":"Rijnstraat",
    "iso:country":"NL",
    "sg:address":"Rijnstraat 29",
    "sg:city":"Woerden",
    "sg:orig_category":"Kantoorartikelen",
    "sg:phone":"+31 348 412 076",
    "sg:postcode":"3441 BP",
    "sg:province":"Utrecht",
    "wof:name":"Boekhandel Karssen",
    "wof:placetype":"venue"
},
  "geometry": {"coordinates":[4.8847541809,52.086769104],"type":"Point"}
}