{
  "type": "Feature",
  "properties": {
    "addr:full":"A. Hofmanweg 43 Haarlem Noord-Holland 2031 BH",
    "addr:housenumber":"43",
    "addr:postcode":"2031 bh",
    "addr:street":"A. Hofmanweg",
    "iso:country":"NL",
    "sg:address":"A. Hofmanweg 43",
    "sg:city":"Haarlem",
    "sg:orig_category":"Bedrijfsinventaris Gh",
    "sg:phone":"+31 23 532 9755",
    "sg:postcode":"2031 BH",
    "sg:province":"Noord-Holland",
    "wof:name":"Sanelli Bv",
    "wof:placetype":"venue"
},
  "geometry": {"coordinates":[4.66521,52.396297],"type":"Point"}
}