{
  "type": "Feature",
  "properties": {
    "iso:country":"NL",
    "sg:address":"Zandstr 42",
    "sg:city":"Culemborg",
    "sg:orig_category":"Houtbewerking",
    "sg:phone":"+31 345 512 752",
    "sg:postcode":"4101 EH",
    "sg:province":"Gelderland",
    "wof:name":"Kroon, De",
    "wof:placetype":"venue"
},
  "geometry": {"coordinates":[5.227917,51.954548],"type":"Point"}
}