{
  "type": "Feature",
  "properties": {
    "iso:country":"NL",
    "sg:address":"Tottenhamstraat 17",
    "sg:city":"Dedemsvaart",
    "sg:orig_category":"Kampeerterreinen",
    "sg:phone":"+31 523 613 535",
    "sg:postcode":"7701 BL",
    "sg:province":"Overijssel",
    "wof:name":"De Colenbrander",
    "wof:placetype":"venue"
},
  "geometry": {"coordinates":[6.5243449211,52.6074371338],"type":"Point"}
}