{
  "type": "Feature",
  "properties": {
    "addr:full":"Gorenweg 6 Buinen Provincie Drenthe 9528 PJ",
    "addr:housenumber":"6",
    "addr:postcode":"9528 pj",
    "addr:street":"Gorenweg;Provincie Drenthe",
    "iso:country":"NL",
    "sg:address":"Gorenweg 6",
    "sg:city":"Buinen",
    "sg:orig_category":"Boekhouders",
    "sg:phone":"+31 599 212 482",
    "sg:postcode":"9528 PJ",
    "sg:province":"Provincie Drenthe",
    "wof:name":"Administratiekantoor Van Eijk",
    "wof:placetype":"venue"
},
  "geometry": {"coordinates":[6.833695,52.93462],"type":"Point"}
}