{
  "type": "Feature",
  "properties": {
    "addr:full":"Broekslagen 14 Steenwijk Overijssel 8331 TJ",
    "addr:housenumber":"14",
    "addr:postcode":"8331 tj",
    "addr:street":"Broekslagen",
    "iso:country":"NL",
    "sg:address":"Broekslagen 14",
    "sg:city":"Steenwijk",
    "sg:orig_category":"Meubelzaken, Woning- And Keukeninrichting",
    "sg:phone":"+31 521 514 623",
    "sg:postcode":"8331 TJ",
    "sg:province":"Overijssel",
    "wof:name":"H. Kruider Meubelen Bv",
    "wof:placetype":"venue"
},
  "geometry": {"coordinates":[6.09459,52.778332],"type":"Point"}
}