{
  "type": "Feature",
  "properties": {
    "iso:country":"NL",
    "sg:address":"Schimmelpenninckkade 11",
    "sg:city":"Amersfoort",
    "sg:orig_category":"Diverse Grafische Activiteiten",
    "sg:phone":"+31 33 470 1285",
    "sg:postcode":"3813 AC",
    "sg:province":"Utrecht",
    "wof:name":"Else Where",
    "wof:placetype":"venue"
},
  "geometry": {"coordinates":[5.386066,52.15979],"type":"Point"}
}