{
  "type": "Feature",
  "properties": {
    "addr:full":"Keizersgr 784 Amsterdam North Holland 1017 EC",
    "addr:housenumber":"784",
    "addr:postcode":"1017 ec",
    "iso:country":"NL",
    "sg:address":"Keizersgr 784",
    "sg:city":"Amsterdam",
    "sg:orig_category":"Video - Faciliteiten En Producties",
    "sg:phone":"+31 20 421 0606",
    "sg:postcode":"1017 EC",
    "sg:province":"North Holland",
    "sg:website":"http://www.bigpete.com",
    "wof:name":"Ponti & Ponti",
    "wof:placetype":"venue"
},
  "geometry": {"coordinates":[4.899433,52.363682],"type":"Point"}
}