{
  "type": "Feature",
  "properties": {
    "iso:country":"NL",
    "sg:address":"Keizerstraat 26",
    "sg:city":"Den Helder",
    "sg:orig_category":"Juweliers",
    "sg:phone":"+31 223 613 793",
    "sg:postcode":"1781 GG",
    "sg:province":"Noord-Holland",
    "wof:name":"Mantje Juweliers",
    "wof:placetype":"venue"
},
  "geometry": {"coordinates":[4.7627,52.958561],"type":"Point"}
}