{
  "type": "Feature",
  "properties": {
    "iso:country":"NL",
    "sg:address":"Prinsendam 62",
    "sg:city":"Oosterhout Nb",
    "sg:orig_category":"Webdesign Bureaus",
    "sg:phone":"+31 162 471 522",
    "sg:postcode":"4908 AB",
    "sg:province":"North Brabant",
    "wof:name":"Comm Site",
    "wof:placetype":"venue"
},
  "geometry": {"coordinates":[4.8584661484,51.6634902954],"type":"Point"}
}