{
  "type": "Feature",
  "properties": {
    "addr:full":"Bettowg 34 Schiedam Zuid-Holland 3125 AB",
    "addr:housenumber":"34",
    "addr:postcode":"3125 ab",
    "addr:street":"Bettowg",
    "iso:country":"NL",
    "sg:address":"Bettowg 34",
    "sg:city":"Schiedam",
    "sg:orig_category":"Metaalbewerking",
    "sg:phone":"+31 10 462 5422",
    "sg:postcode":"3125 AB",
    "sg:province":"Zuid-Holland",
    "wof:name":"Largo Bv",
    "wof:placetype":"venue"
},
  "geometry": {"coordinates":[4.40997,51.925182],"type":"Point"}
}