{
  "type": "Feature",
  "properties": {
    "addr:full":"Overstraat 26 Amerongen Utrecht 3958 BV",
    "addr:housenumber":"26",
    "addr:postcode":"3958 bv",
    "addr:street":"Overstraat",
    "iso:country":"NL",
    "sg:address":"Overstraat 26",
    "sg:city":"Amerongen",
    "sg:orig_category":"Kappers",
    "sg:phone":"+31 343 451 446",
    "sg:postcode":"3958 BV",
    "sg:province":"Utrecht",
    "wof:name":"Barneveld, H L Van",
    "wof:placetype":"venue"
},
  "geometry": {"coordinates":[5.4572191238,51.9987220764],"type":"Point"}
}