{
  "type": "Feature",
  "properties": {
    "addr:full":"Visserswg 38B Elst Ut Utrecht 3922 GH",
    "addr:housenumber":"38b",
    "addr:postcode":"ut;3922 gh",
    "addr:street":"Visserswg",
    "iso:country":"NL",
    "sg:address":"Visserswg 38B",
    "sg:city":"Elst Ut",
    "sg:orig_category":"Verhuur",
    "sg:phone":"+31 318 472 507",
    "sg:postcode":"3922 GH",
    "sg:province":"Utrecht",
    "wof:name":"Troost",
    "wof:placetype":"venue"
},
  "geometry": {"coordinates":[5.48069,51.990444],"type":"Point"}
}