{
  "type": "Feature",
  "properties": {
    "addr:full":"Rivierapln 5 Haarlem Noord-Holland 2037 AS",
    "addr:housenumber":"5",
    "addr:postcode":"2037 as",
    "addr:street":"Rivierapln",
    "iso:country":"NL",
    "sg:address":"Rivierapln 5",
    "sg:city":"Haarlem",
    "sg:orig_category":"Kappers",
    "sg:phone":"+31 23 540 6054",
    "sg:postcode":"2037 AS",
    "sg:province":"Noord-Holland",
    "wof:name":"Cosmo",
    "wof:placetype":"venue"
},
  "geometry": {"coordinates":[4.653195858,52.3573455811],"type":"Point"}
}