{
  "type": "Feature",
  "properties": {
    "addr:full":"Tinnegieter 7 Hoorn Nh Noord-Holland 1625 AN",
    "addr:housenumber":"7",
    "addr:postcode":"1625 an",
    "addr:street":"Tinnegieter",
    "iso:country":"NL",
    "sg:address":"Tinnegieter 7",
    "sg:city":"Hoorn Nh",
    "sg:orig_category":"Adviesbureaus Automatisering",
    "sg:phone":"+31 229 211 385",
    "sg:postcode":"1625 AN",
    "sg:province":"Noord-Holland",
    "wof:name":"Inforesult",
    "wof:placetype":"venue"
},
  "geometry": {"coordinates":[5.044655,52.657085],"type":"Point"}
}