{
  "type": "Feature",
  "properties": {
    "addr:full":"Diessenseweg 16 Hilvarenbeek Noord-Brabant 5081 AJ",
    "addr:housenumber":"16",
    "addr:postcode":"5081 aj",
    "addr:street":"Diessenseweg",
    "iso:country":"NL",
    "sg:address":"Diessenseweg 16",
    "sg:city":"Hilvarenbeek",
    "sg:orig_category":"Makelaars In Onroerend Goed",
    "sg:phone":"+31 13 505 1363",
    "sg:postcode":"5081 AJ",
    "sg:province":"Noord-Brabant",
    "wof:name":"Era Makelaardij Damen Hilvarenbeek",
    "wof:placetype":"venue"
},
  "geometry": {"coordinates":[5.139065,51.484272],"type":"Point"}
}