{
  "type": "Feature",
  "properties": {
    "iso:country":"NL",
    "sg:address":"Nyverheidswg 40",
    "sg:city":"Oosterhout Nb",
    "sg:orig_category":"Autoreclame",
    "sg:phone":"+31 162 470 688",
    "sg:postcode":"4906 CL",
    "sg:province":"Noord-Brabant",
    "sg:website":"http://www.art-design.nl",
    "wof:name":"Art Design",
    "wof:placetype":"venue"
},
  "geometry": {"coordinates":[4.84785,51.656799],"type":"Point"}
}