{
  "type": "Feature",
  "properties": {
    "addr:full":"Berkhaag 11 Sprang Capelle Noord-Brabant 5161 CC",
    "addr:housenumber":"11",
    "addr:postcode":"5161 cc",
    "addr:street":"Berkhaag",
    "iso:country":"NL",
    "sg:address":"Berkhaag 11",
    "sg:city":"Sprang Capelle",
    "sg:orig_category":"Adviesbureaus",
    "sg:phone":"+31 416 540 581",
    "sg:postcode":"5161 CC",
    "sg:province":"Noord-Brabant",
    "wof:name":"Gravemaker-Tuinder, C W A M",
    "wof:placetype":"venue"
},
  "geometry": {"coordinates":[5.028401,51.668098],"type":"Point"}
}