{
  "type": "Feature",
  "properties": {
    "iso:country":"NL",
    "sg:address":"Sint Wilfriedstraat 6",
    "sg:city":"Eindhoven",
    "sg:orig_category":"Vertaal- And Tolkenbureaus",
    "sg:phone":"+31 40 211 1001",
    "sg:postcode":"5643 SC",
    "sg:province":"Noord-Brabant",
    "wof:name":"J.O. Dieleman",
    "wof:placetype":"venue"
},
  "geometry": {"coordinates":[5.506825,51.42625],"type":"Point"}
}