{
  "type": "Feature",
  "properties": {
    "addr:full":"Herepln 4 Groningen Groningen 9711 GA",
    "addr:housenumber":"4",
    "addr:postcode":"9711 ga",
    "addr:street":"Herepln",
    "iso:country":"NL",
    "sg:address":"Herepln 4",
    "sg:city":"Groningen",
    "sg:orig_category":"Grafisch Ontwerpers",
    "sg:phone":"+31 50 589 1444",
    "sg:postcode":"9711 GA",
    "sg:province":"Groningen",
    "sg:website":"http://www.g2k.nl",
    "wof:name":"G2K",
    "wof:placetype":"venue"
},
  "geometry": {"coordinates":[6.56882,53.213531],"type":"Point"}
}