{
  "type": "Feature",
  "properties": {
    "iso:country":"NL",
    "sg:address":"Kanaalwg Oz 4",
    "sg:city":"Hellevoetsluis",
    "sg:orig_category":"Machinehandel",
    "sg:phone":"+31 181 314 288",
    "sg:postcode":"3224 AA",
    "sg:province":"South Holland",
    "wof:name":"Haringvliet",
    "wof:placetype":"venue"
},
  "geometry": {"coordinates":[4.13464,51.823521],"type":"Point"}
}