{
  "type": "Feature",
  "properties": {
    "iso:country":"NL",
    "sg:address":"Floraliastraat 93",
    "sg:city":"Oss",
    "sg:orig_category":"Overheidsdiensten",
    "sg:phone":"+31 412 636 310",
    "sg:postcode":"5342 BH",
    "sg:province":"Virginia",
    "wof:name":"Stichting Kortfoort Buurthuis",
    "wof:placetype":"venue"
},
  "geometry": {"coordinates":[-77.2352142334,38.3125991821],"type":"Point"}
}