{
  "type": "Feature",
  "properties": {
    "iso:country":"NL",
    "sg:address":"Dr Holtroplaan 1",
    "sg:city":"7900",
    "sg:classifiers":[
        {
            "category":"Banks & Credit Unions",
            "subcategory":"Bank",
            "type":"Services"
        }
    ],
    "sg:phone":"+31 3152860855",
    "sg:postcode":"HOOG EV",
    "wof:name":"De Nederlandsche Bank Nv",
    "wof:placetype":"venue"
},
  "geometry": {"coordinates":[6.60624,52.908051],"type":"Point"}
}