{
  "type": "Feature",
  "properties": {
    "addr:full":"P C Hooftstr 17 Zwolle Overijssel 8023 AJ",
    "addr:housenumber":"17",
    "addr:postcode":"8023 aj",
    "addr:street":"P C Hooftstr",
    "iso:country":"NL",
    "sg:address":"P C Hooftstr 17",
    "sg:city":"Zwolle",
    "sg:orig_category":"Adviesbureaus Bouwkunde",
    "sg:phone":"+31 38 454 6897",
    "sg:postcode":"8023 AJ",
    "sg:province":"Overijssel",
    "wof:name":"Bp&A Bureau Voor Bouwkunde",
    "wof:placetype":"venue"
},
  "geometry": {"coordinates":[6.112934,52.516068],"type":"Point"}
}