{
  "type": "Feature",
  "properties": {
    "addr:full":"Bildtdk 3 Berlikum Fr Friesland 9041 CC",
    "addr:housenumber":"3",
    "addr:postcode":"9041 cc",
    "addr:street":"Bildtdk",
    "iso:country":"NL",
    "sg:address":"Bildtdk 3",
    "sg:city":"Berlikum Fr",
    "sg:orig_category":"Begrafenisverzorging",
    "sg:phone":"+31 518 461 526",
    "sg:postcode":"9041 CC",
    "sg:province":"Friesland",
    "wof:name":"Laatste Eer Berlikum, De",
    "wof:placetype":"venue"
},
  "geometry": {"coordinates":[5.655688,53.24548],"type":"Point"}
}