{
  "type": "Feature",
  "properties": {
    "iso:country":"NL",
    "sg:address":"Wierdensewg 30",
    "sg:city":"Vriezenveen",
    "sg:orig_category":"Bestratingen",
    "sg:phone":"+31 546 562 521",
    "sg:postcode":"7671 JK",
    "sg:province":"Overijssel",
    "wof:name":"Meer'S, Van Der",
    "wof:placetype":"venue"
},
  "geometry": {"coordinates":[6.602073,52.400589],"type":"Point"}
}