{
  "type": "Feature",
  "properties": {
    "addr:full":"Huygensstr 38 Ymuiden Noord-Holland 1973 AD",
    "addr:housenumber":"38",
    "addr:postcode":"1973 ad",
    "addr:street":"Huygensstr",
    "iso:country":"NL",
    "sg:address":"Huygensstr 38",
    "sg:city":"Ymuiden",
    "sg:orig_category":"Loodgieters",
    "sg:phone":"+31 255 536 737",
    "sg:postcode":"1973 AD",
    "sg:province":"Noord-Holland",
    "wof:name":"Combitotaal",
    "wof:placetype":"venue"
},
  "geometry": {"coordinates":[4.603785,52.460094],"type":"Point"}
}