{
  "type": "Feature",
  "properties": {
    "addr:full":"Oosterwg 15 Valkenburg Lb Limburg 6301 PX",
    "addr:housenumber":"15",
    "addr:postcode":"lb;6301 px",
    "addr:street":"Oosterwg",
    "iso:country":"NL",
    "sg:address":"Oosterwg 15",
    "sg:city":"Valkenburg Lb",
    "sg:orig_category":"Artsen - Huisartsen",
    "sg:phone":"+31 43 601 4499",
    "sg:postcode":"6301 PX",
    "sg:province":"Limburg",
    "wof:name":"Sint Pieter Praktijk",
    "wof:placetype":"venue"
},
  "geometry": {"coordinates":[5.839718,50.864079],"type":"Point"}
}