{
  "type": "Feature",
  "properties": {
    "addr:full":"Amazone 75 Dordrecht Zuid-Holland 3315 WH",
    "addr:housenumber":"75",
    "addr:postcode":"3315 wh",
    "addr:street":"Amazone",
    "iso:country":"NL",
    "sg:address":"Amazone 75",
    "sg:city":"Dordrecht",
    "sg:orig_category":"Autorijscholen",
    "sg:phone":"+31 78 616 8411",
    "sg:postcode":"3315 WH",
    "sg:province":"Zuid-Holland",
    "sg:website":"http://www.allesindordrecht.nl",
    "wof:name":"Op Weg",
    "wof:placetype":"venue"
},
  "geometry": {"coordinates":[4.705716,51.808125],"type":"Point"}
}