{
  "type": "Feature",
  "properties": {
    "addr:full":"Wilhelminastraat 4 Asten North Brabant 5721 KJ",
    "addr:housenumber":"4",
    "addr:postcode":"5721 kj",
    "addr:street":"Wilhelminastraat",
    "iso:country":"NL",
    "sg:address":"Wilhelminastraat 4",
    "sg:city":"Asten",
    "sg:orig_category":"Verzekeringen",
    "sg:phone":"+31 493 695 221",
    "sg:postcode":"5721 KJ",
    "sg:province":"North Brabant",
    "wof:name":"Louwers Verzekeringen",
    "wof:placetype":"venue"
},
  "geometry": {"coordinates":[5.743696,51.403053],"type":"Point"}
}