{
  "type": "Feature",
  "properties": {
    "addr:full":"Wilhelminastraat 31 Haarlem North Holland 2011 VJ",
    "addr:housenumber":"31",
    "addr:postcode":"2011 vj",
    "addr:street":"Wilhelminastraat",
    "iso:country":"NL",
    "sg:address":"Wilhelminastraat 31",
    "sg:city":"Haarlem",
    "sg:orig_category":"Verzekeringen",
    "sg:phone":"+31 23 531 7150",
    "sg:postcode":"2011 VJ",
    "sg:province":"North Holland",
    "sg:website":"http://www.endema.nl",
    "wof:name":"Endema Assurantie Adviseurs Bv",
    "wof:placetype":"venue"
},
  "geometry": {"coordinates":[4.627747,52.379711],"type":"Point"}
}