{
  "type": "Feature",
  "properties": {
    "iso:country":"NL",
    "sg:address":"Kuifeendhof 26",
    "sg:city":"Delft",
    "sg:orig_category":"Kappers",
    "sg:phone":"+31 15 257 1156",
    "sg:postcode":"2623 NS",
    "sg:province":"South Holland",
    "wof:name":"B.H.W. Voeten",
    "wof:placetype":"venue"
},
  "geometry": {"coordinates":[4.3594241142,51.9820289612],"type":"Point"}
}