{
  "type": "Feature",
  "properties": {
    "addr:full":"Oosteinde 75 St Jacobiparochie Friesland 9079 LB",
    "addr:housenumber":"75",
    "addr:postcode":"9079 lb",
    "addr:street":"Oosteinde;St Jacobiparochie Friesland",
    "iso:country":"NL",
    "sg:address":"Oosteinde 75",
    "sg:city":"St Jacobiparochie",
    "sg:orig_category":"Administratie- En Boekhoudkantoren",
    "sg:phone":"+31 518 491 297",
    "sg:postcode":"9079 LB",
    "sg:province":"Friesland",
    "wof:name":"Koopmans",
    "wof:placetype":"venue"
},
  "geometry": {"coordinates":[5.61227,53.273342],"type":"Point"}
}