{
  "type": "Feature",
  "properties": {
    "addr:full":"De Ruyterstraat 37 Koog A/D Zaan Noord-Holland 1541 CV",
    "addr:housenumber":"37;a / d",
    "addr:postcode":"1541 cv",
    "addr:street":"De Ruyterstraat",
    "iso:country":"NL",
    "sg:address":"De Ruyterstraat 37",
    "sg:city":"Koog A/D Zaan",
    "sg:orig_category":"Goederenvervoer Over De Weg",
    "sg:phone":"+31 75 616 6005",
    "sg:postcode":"1541 CV",
    "sg:province":"Noord-Holland",
    "wof:name":"Deijle Trans",
    "wof:placetype":"venue"
},
  "geometry": {"coordinates":[4.809398,52.460388],"type":"Point"}
}