{
  "type": "Feature",
  "properties": {
    "addr:full":"Heusdenln 26 Tilburg Noord-Brabant 5045 BN",
    "addr:housenumber":"26",
    "addr:postcode":"5045 bn",
    "addr:street":"Heusdenln",
    "iso:country":"NL",
    "sg:address":"Heusdenln 26",
    "sg:city":"Tilburg",
    "sg:classifiers":[
        {
            "category":"Personal",
            "subcategory":"Nail Salon",
            "type":"Services"
        }
    ],
    "sg:phone":"+31 13 570 4978",
    "sg:postcode":"5045 BN",
    "sg:province":"Noord-Brabant",
    "sg:tags":[
        "pedicure"
    ],
    "wof:name":"Neumann-Ijpelaar, J",
    "wof:placetype":"venue"
},
  "geometry": {"coordinates":[5.003508,51.581619],"type":"Point"}
}