{
  "type": "Feature",
  "properties": {
    "iso:country":"NL",
    "sg:address":"Vlinderkleuven 60",
    "sg:city":"Assen",
    "sg:orig_category":"Video - Faciliteiten En Producties",
    "sg:phone":"+31 592 407 032",
    "sg:postcode":"9403 ZJ",
    "sg:province":"Provincie Drenthe",
    "sg:website":"http://www.videosportvision.com",
    "wof:name":"Sportvision",
    "wof:placetype":"venue"
},
  "geometry": {"coordinates":[6.59006,53.022404],"type":"Point"}
}