{
  "type": "Feature",
  "properties": {
    "iso:country":"NL",
    "sg:address":"Oscar Romerolaan 16",
    "sg:city":"Hilversum",
    "sg:orig_category":"Waterbeheer",
    "sg:phone":"+31 35 672 1500",
    "sg:postcode":"1216 TK",
    "sg:province":"Noord-Holland",
    "wof:name":"Nv Waterleidingbedrijf Midden-Nederland",
    "wof:placetype":"venue"
},
  "geometry": {"coordinates":[5.1406798363,52.2122612],"type":"Point"}
}