{
  "type": "Feature",
  "properties": {
    "addr:full":"Rijndijk 11 Westervoort Gelderland 6931 SC",
    "addr:housenumber":"11",
    "addr:postcode":"6931",
    "addr:street":"Rijndijk;Gelderland",
    "iso:country":"NL",
    "sg:address":"Rijndijk 11",
    "sg:city":"Westervoort",
    "sg:orig_category":"Kantoormachines Geen Computers Fab",
    "sg:phone":"+31 26 312 0553",
    "sg:postcode":"6931 SC",
    "sg:province":"Gelderland",
    "wof:name":"Solicom",
    "wof:placetype":"venue"
},
  "geometry": {"coordinates":[5.9603362083,51.9610481262],"type":"Point"}
}