{
  "type": "Feature",
  "properties": {
    "addr:full":"Arnhemsewg 370 Apeldoorn Gelderland 7334 AC",
    "addr:housenumber":"370",
    "addr:postcode":"7334 ac",
    "addr:street":"Gelderland",
    "iso:country":"NL",
    "sg:address":"Arnhemsewg 370",
    "sg:city":"Apeldoorn",
    "sg:orig_category":"Adviesbureaus Bedrijfsorganisatie",
    "sg:phone":"+31 6 23229665",
    "sg:postcode":"7334 AC",
    "sg:province":"Gelderland",
    "wof:name":"Haagen",
    "wof:placetype":"venue"
},
  "geometry": {"coordinates":[5.961985,52.181992],"type":"Point"}
}