{
  "type": "Feature",
  "properties": {
    "iso:country":"NL",
    "sg:address":"Hofwg 8",
    "sg:city":"Nykerkerveen",
    "sg:orig_category":"Hek- En Rasterwerken",
    "sg:phone":"+31 33 257 2812",
    "sg:postcode":"3864 EH",
    "sg:province":"Gelderland",
    "sg:website":"http://www.landmansiermetaal.nl",
    "wof:name":"Landman Siermetaal",
    "wof:placetype":"venue"
},
  "geometry": {"coordinates":[5.467385,52.193272],"type":"Point"}
}