{
  "type": "Feature",
  "properties": {
    "addr:full":"Bonifaciusstr 16 Doetinchem Gelderland 7009 MP",
    "addr:housenumber":"16",
    "addr:postcode":"7009 mp",
    "addr:street":"Bonifaciusstr;Gelderland",
    "iso:country":"NL",
    "sg:address":"Bonifaciusstr 16",
    "sg:city":"Doetinchem",
    "sg:orig_category":"Adviesbureaus",
    "sg:phone":"+31 314 380 132",
    "sg:postcode":"7009 MP",
    "sg:province":"Gelderland",
    "wof:name":"Harding",
    "wof:placetype":"venue"
},
  "geometry": {"coordinates":[6.292736,51.982899],"type":"Point"}
}