{
  "type": "Feature",
  "properties": {
    "addr:full":"Boddens Hosangweg 56 Woubrugge Zuid-Holland 2481 LA",
    "addr:housenumber":"56",
    "addr:postcode":"2481 la",
    "addr:street":"Boddens Hosangweg",
    "iso:country":"NL",
    "sg:address":"Boddens Hosangweg 56",
    "sg:city":"Woubrugge",
    "sg:orig_category":"Public Relationbureaus",
    "sg:phone":"+31 172 519 819",
    "sg:postcode":"2481 LA",
    "sg:province":"Zuid-Holland",
    "wof:name":"Com-Pri Communicatie In De Gezondheidszorg",
    "wof:placetype":"venue"
},
  "geometry": {"coordinates":[4.637437,52.173347],"type":"Point"}
}