{
  "type": "Feature",
  "properties": {
    "addr:full":"Emmastraat 39 Rozenburg Zh Zuid-Holland 3181 GC",
    "addr:housenumber":"39",
    "addr:postcode":"zh;3181 gc",
    "addr:street":"Emmastraat",
    "iso:country":"NL",
    "sg:address":"Emmastraat 39",
    "sg:city":"Rozenburg Zh",
    "sg:classifiers":[
        {
            "category":"Communications",
            "subcategory":"Television Station",
            "type":"Services"
        }
    ],
    "sg:phone":"+31 181 219 159",
    "sg:postcode":"3181 GC",
    "sg:province":"Zuid-Holland",
    "sg:tags":[
        "video",
        "audio",
        "verhuur"
    ],
    "wof:name":"Videotheek Rozenburg",
    "wof:placetype":"venue"
},
  "geometry": {"coordinates":[4.243849,51.905891],"type":"Point"}
}