{
  "type": "Feature",
  "properties": {
    "addr:full":"Houtsestraat 22 Sint Oedenrode Noord-Brabant 5492 TM",
    "addr:housenumber":"22;oedenrode",
    "addr:postcode":"5492 tm",
    "addr:street":"Houtsestraat",
    "iso:country":"NL",
    "sg:address":"Houtsestraat 22",
    "sg:city":"Sint Oedenrode",
    "sg:orig_category":"Levende Dieren Gh",
    "sg:phone":"+31 413 477 195",
    "sg:postcode":"5492 TM",
    "sg:province":"Noord-Brabant",
    "wof:name":"Varkenshandel M. Van Den Berkmortel",
    "wof:placetype":"venue"
},
  "geometry": {"coordinates":[5.472659,51.544376],"type":"Point"}
}