{
  "type": "Feature",
  "properties": {
    "iso:country":"NL",
    "sg:address":"Hoofdweg 622",
    "sg:city":"Hoofddorp",
    "sg:orig_category":"Public Relationbureaus",
    "sg:phone":"+31 23 562 6112",
    "sg:postcode":"2132 MJ",
    "sg:province":"North Holland",
    "wof:name":"Igaf Europe Ltd.",
    "wof:placetype":"venue"
},
  "geometry": {"coordinates":[4.698441,52.309128],"type":"Point"}
}