{
  "type": "Feature",
  "properties": {
    "addr:full":"Dorpsstraat 68 Geesteren Ov Overijssel 7678 AX",
    "addr:housenumber":"68",
    "addr:postcode":"7678 ax",
    "addr:street":"Dorpsstraat;Ov",
    "iso:country":"NL",
    "sg:address":"Dorpsstraat 68",
    "sg:city":"Geesteren Ov",
    "sg:orig_category":"Verlichting And Huishoudartikelen",
    "sg:phone":"+31 546 631 202",
    "sg:postcode":"7678 AX",
    "sg:province":"Overijssel",
    "wof:name":"A.B. Veldhuis",
    "wof:placetype":"venue"
},
  "geometry": {"coordinates":[6.73434,52.420143],"type":"Point"}
}