{
  "type": "Feature",
  "properties": {
    "addr:full":"Radeweg 19 Vaassen Gelderland 8171 MD",
    "addr:housenumber":"19",
    "addr:postcode":"8171",
    "addr:street":"Radeweg;Gelderland",
    "iso:country":"NL",
    "sg:address":"Radeweg 19",
    "sg:city":"Vaassen",
    "sg:orig_category":"Schilderwerk",
    "sg:phone":"+31 578 571 473",
    "sg:postcode":"8171 MD",
    "sg:province":"Gelderland",
    "wof:name":"Joop Mossink Schildersbedrijf Bv",
    "wof:placetype":"venue"
},
  "geometry": {"coordinates":[5.985964,52.30114],"type":"Point"}
}