{
  "type": "Feature",
  "properties": {
    "iso:country":"NL",
    "sg:address":"Postbus 4172",
    "sg:city":"Ridderkerk",
    "sg:orig_category":"Adviesbureaus Bouwkosten",
    "sg:phone":"+31 180 426 830",
    "sg:postcode":"2980 GD",
    "sg:province":"Zuid-Holland",
    "wof:name":"Callforce",
    "wof:placetype":"venue"
},
  "geometry": {"coordinates":[4.598051,51.871727],"type":"Point"}
}