{
  "type": "Feature",
  "properties": {
    "iso:country":"NL",
    "sg:address":"Oosterparallelwg 31+41",
    "sg:city":"Staphorst",
    "sg:classifiers":[
        {
            "category":"Home & Garden",
            "subcategory":"Hardware",
            "type":"Retail Goods"
        }
    ],
    "sg:phone":"+31 522 461 402",
    "sg:postcode":"7951 DD",
    "sg:province":"Overijssel",
    "sg:tags":[
        "machine",
        "houtbewerking",
        "-"
    ],
    "wof:name":"Talen Houtbewerkingsmachines",
    "wof:placetype":"venue"
},
  "geometry": {"coordinates":[6.220158,52.646011],"type":"Point"}
}