{
  "type": "Feature",
  "properties": {
    "addr:full":"Rottermontstr 2 S Gravenhage Zuid-Holland 2562 NG",
    "addr:housenumber":"2;gravenhage",
    "addr:postcode":"2562 ng",
    "addr:street":"Rottermontstr;S",
    "iso:country":"NL",
    "sg:address":"Rottermontstr 2",
    "sg:city":"S Gravenhage",
    "sg:orig_category":"Woningbouw- Verenigingen En -Stichtingen",
    "sg:phone":"+31 70 345 2494",
    "sg:postcode":"2562 NG",
    "sg:province":"Zuid-Holland",
    "wof:name":"Vooruit Ii, Co\u00f7P Ver",
    "wof:placetype":"venue"
},
  "geometry": {"coordinates":[4.2832598686,52.0750007629],"type":"Point"}
}