{
  "type": "Feature",
  "properties": {
    "addr:full":"Looiersgracht 12 Amsterdam Noord-Holland 1016 VS",
    "addr:housenumber":"12",
    "addr:postcode":"1016 vs",
    "addr:street":"Looiersgracht",
    "iso:country":"NL",
    "sg:address":"Looiersgracht 12",
    "sg:city":"Amsterdam",
    "sg:orig_category":"Verlichting And Huishoudartikelen",
    "sg:phone":"+31 20 625 3721",
    "sg:postcode":"1016 VS",
    "sg:province":"Noord-Holland",
    "wof:name":"Lor De God Van Het Overschot",
    "wof:placetype":"venue"
},
  "geometry": {"coordinates":[-74.11232800000001,42.977543],"type":"Point"}
}