{
  "type": "Feature",
  "properties": {
    "addr:full":"Sleutelbloemstraat 6 Klaaswaal South Holland 3286 VN",
    "addr:housenumber":"6",
    "addr:postcode":"3286 vn",
    "addr:street":"Sleutelbloemstraat",
    "iso:country":"NL",
    "sg:address":"Sleutelbloemstraat 6",
    "sg:city":"Klaaswaal",
    "sg:orig_category":"Boekhouders",
    "sg:phone":"+31 186 572 588",
    "sg:postcode":"3286 VN",
    "sg:province":"South Holland",
    "wof:name":"Adm.-Bel.- En Adviesburo L.H. Ridderhof",
    "wof:placetype":"venue"
},
  "geometry": {"coordinates":[4.448029,51.774284],"type":"Point"}
}