{
  "type": "Feature",
  "properties": {
    "addr:full":"Kosterijland 46 Bunnik Utrecht 3981 AJ",
    "addr:housenumber":"46",
    "addr:postcode":"3981 aj",
    "addr:street":"Kosterijland",
    "iso:country":"NL",
    "sg:address":"Kosterijland 46",
    "sg:city":"Bunnik",
    "sg:orig_category":"Vertaal- And Tolkenbureaus",
    "sg:phone":"+31 30 692 2844",
    "sg:postcode":"3981 AJ",
    "sg:province":"Utrecht",
    "wof:name":"Wts Vertalingen Bv",
    "wof:placetype":"venue"
},
  "geometry": {"coordinates":[5.20812,52.061741],"type":"Point"}
}