{
  "type": "Feature",
  "properties": {
    "addr:full":"Grote Brink 3 Borger Provincie Drenthe 9531  A",
    "addr:housenumber":"3;9531 a",
    "addr:street":"Grote Brink;Provincie",
    "iso:country":"NL",
    "sg:address":"Grote Brink 3",
    "sg:city":"Borger",
    "sg:orig_category":"Banken And Kredietinstellingen",
    "sg:phone":"+31 599 234 340",
    "sg:postcode":"9531  A",
    "sg:province":"Provincie Drenthe",
    "wof:name":"Bruna",
    "wof:placetype":"venue"
},
  "geometry": {"coordinates":[6.789282,52.922997],"type":"Point"}
}