{
  "type": "Feature",
  "properties": {
    "iso:country":"NL",
    "sg:address":"Stuurboord 59",
    "sg:city":"Huizen",
    "sg:orig_category":"Verhuisdiensten",
    "sg:phone":"+31 35 525 3635",
    "sg:postcode":"1276 CP",
    "sg:province":"North Holland",
    "wof:name":"Fokke Van Alphen Bv",
    "wof:placetype":"venue"
},
  "geometry": {"coordinates":[5.256104,52.292538],"type":"Point"}
}