{
  "type": "Feature",
  "properties": {
    "iso:country":"NL",
    "sg:address":"Boekelosestraat 257",
    "sg:city":"Enschede",
    "sg:orig_category":"Alternatieve Geneeskunde",
    "sg:phone":"+31 53 428 3943",
    "sg:postcode":"7548 AS",
    "sg:province":"Overijssel",
    "wof:name":"Klassiek Homeopaat Tineke Schaper",
    "wof:placetype":"venue"
},
  "geometry": {"coordinates":[6.812634,52.204556],"type":"Point"}
}