{
  "type": "Feature",
  "properties": {
    "addr:full":"C Eyckstr 33 Meerssen Limburg 6231 GX",
    "addr:housenumber":"33",
    "addr:postcode":"6231 gx",
    "iso:country":"NL",
    "sg:address":"C Eyckstr 33",
    "sg:city":"Meerssen",
    "sg:orig_category":"Adviesbureaus Bouwkunde",
    "sg:phone":"+31 43 364 3240",
    "sg:postcode":"6231 GX",
    "sg:province":"Limburg",
    "sg:website":"http://www.bvgg.nl",
    "wof:name":"Bvgg",
    "wof:placetype":"venue"
},
  "geometry": {"coordinates":[5.753205,50.885006],"type":"Point"}
}