{
  "type": "Feature",
  "properties": {
    "addr:full":"Mekkelenbergwg 30A M Elstgeest Harbrinkhoek Overijssel 7615 PP",
    "addr:housenumber":"30a m",
    "addr:postcode":"7615 pp",
    "addr:street":"Mekkelenbergwg;Elstgeest",
    "iso:country":"NL",
    "sg:address":"Mekkelenbergwg 30A M Elstgeest",
    "sg:city":"Harbrinkhoek",
    "sg:orig_category":"Grafisch Ontwerpers",
    "sg:phone":"+31 546 866 739",
    "sg:postcode":"7615 PP",
    "sg:province":"Overijssel",
    "wof:name":"Elstgeest, Maureen",
    "wof:placetype":"venue"
},
  "geometry": {"coordinates":[6.723061,52.385136],"type":"Point"}
}