{
  "type": "Feature",
  "properties": {
    "addr:full":"Hofdijksweg 20 Ouddorp Zh Zuid-Holland 3253 KB",
    "addr:housenumber":"20",
    "addr:postcode":"3253 kb",
    "addr:street":"Hofdijksweg",
    "iso:country":"NL",
    "sg:address":"Hofdijksweg 20",
    "sg:city":"Ouddorp Zh",
    "sg:orig_category":"Banken And Kredietinstellingen",
    "sg:phone":"+31 187 498 888",
    "sg:postcode":"3253 KB",
    "sg:province":"Zuid-Holland",
    "wof:name":"Rabobank",
    "wof:placetype":"venue"
},
  "geometry": {"coordinates":[3.936554,51.810917],"type":"Point"}
}