{
  "type": "Feature",
  "properties": {
    "addr:full":"Pres Rooseveltln 772 Vlissingen Zeeland 4382 NB",
    "addr:housenumber":"772",
    "addr:postcode":"4382 nb",
    "iso:country":"NL",
    "sg:address":"Pres Rooseveltln 772",
    "sg:city":"Vlissingen",
    "sg:orig_category":"Keukens",
    "sg:phone":"+31 118 431 278",
    "sg:postcode":"4382 NB",
    "sg:province":"Zeeland",
    "wof:name":"Belle Keukens, Van",
    "wof:placetype":"venue"
},
  "geometry": {"coordinates":[3.585935,51.453945],"type":"Point"}
}