{
  "type": "Feature",
  "properties": {
    "addr:full":"Veldweg 47 Hattem Gelderland 8051 NN",
    "addr:housenumber":"47",
    "addr:postcode":"8051 nn",
    "addr:street":"Veldweg;Gelderland",
    "iso:country":"NL",
    "sg:address":"Veldweg 47",
    "sg:city":"Hattem",
    "sg:orig_category":"Artsen And Specialisten",
    "sg:phone":"+31 38 444 3781",
    "sg:postcode":"8051 NN",
    "sg:province":"Gelderland",
    "wof:name":"B. Dane",
    "wof:placetype":"venue"
},
  "geometry": {"coordinates":[6.059967,52.460735],"type":"Point"}
}