{
  "type": "Feature",
  "properties": {
    "addr:full":"Struisgrasstr 27 Amsterdam North Holland 1032 LE",
    "addr:housenumber":"27",
    "addr:postcode":"1032 le",
    "addr:street":"Struisgrasstr",
    "iso:country":"NL",
    "sg:address":"Struisgrasstr 27",
    "sg:city":"Amsterdam",
    "sg:orig_category":"Woninginrichting",
    "sg:phone":"+31 20 637 3752",
    "sg:postcode":"1032 LE",
    "sg:province":"North Holland",
    "wof:name":"Derchique",
    "wof:placetype":"venue"
},
  "geometry": {"coordinates":[4.9075832367,52.3945541382],"type":"Point"}
}