{
  "type": "Feature",
  "properties": {
    "addr:full":"Oranjestraat 2 Vlaardingen Zuid-Holland 3134 EV",
    "addr:housenumber":"2",
    "addr:postcode":"3134 ev",
    "addr:street":"Oranjestraat",
    "iso:country":"NL",
    "sg:address":"Oranjestraat 2",
    "sg:city":"Vlaardingen",
    "sg:orig_category":"Geluidsopnamen",
    "sg:phone":"+31 10 434 0432",
    "sg:postcode":"3134 EV",
    "sg:province":"Zuid-Holland",
    "wof:name":"Geluidsstudio Het Pand",
    "wof:placetype":"venue"
},
  "geometry": {"coordinates":[4.34686,51.907902],"type":"Point"}
}