{
  "type": "Feature",
  "properties": {
    "addr:full":"Dorpsstraat 75 Zoetermeer South Holland 2712 AD",
    "addr:housenumber":"75",
    "addr:postcode":"2712 ad",
    "addr:street":"Dorpsstraat",
    "iso:country":"NL",
    "sg:address":"Dorpsstraat 75",
    "sg:city":"Zoetermeer",
    "sg:orig_category":"Huishoudapparatuur, Televisies And Radio'S",
    "sg:phone":"+31 79 316 3904",
    "sg:postcode":"2712 AD",
    "sg:province":"South Holland",
    "wof:name":"Van Bemmel & Kroon Bv",
    "wof:placetype":"venue"
},
  "geometry": {"coordinates":[4.496833,52.056229],"type":"Point"}
}