{
  "type": "Feature",
  "properties": {
    "addr:full":"Dorpsstr 35A Wagenberg Noord-Brabant 4845 CC",
    "addr:housenumber":"35a",
    "addr:postcode":"4845 cc",
    "addr:street":"Dorpsstr",
    "iso:country":"NL",
    "sg:address":"Dorpsstr 35A",
    "sg:city":"Wagenberg",
    "sg:classifiers":[
        {
            "category":"Wholesale",
            "subcategory":"Motor Vehicles",
            "type":"Manufacturing & Wholesale Goods"
        }
    ],
    "sg:phone":"+31 76 593 1035",
    "sg:postcode":"4845 CC",
    "sg:province":"Noord-Brabant",
    "sg:tags":[
        "scooter",
        "en"
    ],
    "wof:name":"Bm Service",
    "wof:placetype":"venue"
},
  "geometry": {"coordinates":[4.743965,51.663776],"type":"Point"}
}