{
  "type": "Feature",
  "properties": {
    "iso:country":"NL",
    "sg:address":"Molenkom 9",
    "sg:city":"Arnhem",
    "sg:orig_category":"Autorijscholen",
    "sg:phone":"+31 6 53173344",
    "sg:postcode":"6811 JP",
    "sg:province":"Gelderland",
    "sg:website":"http://www.verkeersschoolvdbergh.nl",
    "wof:name":"Bergh, Van Den",
    "wof:placetype":"venue"
},
  "geometry": {"coordinates":[5.903217,51.979668],"type":"Point"}
}