{
  "type": "Feature",
  "properties": {
    "addr:full":"Spijkerstraat 215 Arnhem Gelderland 6828 DD",
    "addr:housenumber":"215",
    "addr:postcode":"6828 dd",
    "addr:street":"Spijkerstraat",
    "iso:country":"NL",
    "sg:address":"Spijkerstraat 215",
    "sg:city":"Arnhem",
    "sg:orig_category":"Film-, Tv- And Videoproductie",
    "sg:phone":"+31 26 442 0524",
    "sg:postcode":"6828 DD",
    "sg:province":"Gelderland",
    "wof:name":"Viva Vox",
    "wof:placetype":"venue"
},
  "geometry": {"coordinates":[5.919401,51.982861],"type":"Point"}
}