{
  "type": "Feature",
  "properties": {
    "addr:full":"Stationsstr 28B Epe Gelderland 8161 CR",
    "addr:housenumber":"28b;8161",
    "addr:postcode":"cr",
    "addr:street":"Stationsstr;Gelderland",
    "iso:country":"NL",
    "sg:address":"Stationsstr 28B",
    "sg:city":"Epe",
    "sg:orig_category":"Verenigingen En Stichtingen",
    "sg:phone":"+31 578 629 484",
    "sg:postcode":"8161 CR",
    "sg:province":"Gelderland",
    "wof:name":"Lets Ruilkring",
    "wof:placetype":"venue"
},
  "geometry": {"coordinates":[5.988526,52.347538],"type":"Point"}
}