{
  "type": "Feature",
  "properties": {
    "addr:full":"Koningstraat 79 Arnhem Gelderland 6811 DK",
    "addr:housenumber":"79",
    "addr:postcode":"6811 dk",
    "addr:street":"Koningstraat",
    "iso:country":"NL",
    "sg:address":"Koningstraat 79",
    "sg:city":"Arnhem",
    "sg:orig_category":"Damesmodezaken",
    "sg:phone":"+31 26 351 4298",
    "sg:postcode":"6811 DK",
    "sg:province":"Gelderland",
    "wof:name":"Naturals",
    "wof:placetype":"venue"
},
  "geometry": {"coordinates":[5.909832,51.981621],"type":"Point"}
}