{
  "type": "Feature",
  "properties": {
    "addr:full":"Hoofdstr 59 Bovenkarspel Noord-Holland 1611 AB",
    "addr:housenumber":"59",
    "addr:postcode":"1611 ab",
    "addr:street":"Hoofdstr",
    "iso:country":"NL",
    "sg:address":"Hoofdstr 59",
    "sg:city":"Bovenkarspel",
    "sg:classifiers":[
        {
            "category":"Retail",
            "subcategory":"Auto Repair",
            "type":"Services"
        }
    ],
    "sg:phone":"+31 228 312 632",
    "sg:postcode":"1611 AB",
    "sg:province":"Noord-Holland",
    "sg:tags":[
        "garage"
    ],
    "wof:name":"Kornalijnslijper, Ed",
    "wof:placetype":"venue"
},
  "geometry": {"coordinates":[5.239166,52.697929],"type":"Point"}
}