{
  "type": "Feature",
  "properties": {
    "addr:full":"Oudegr 97 Utrecht Utrecht 3511 AD",
    "addr:housenumber":"97",
    "addr:postcode":"3511 ad",
    "addr:street":"Oudegr",
    "iso:country":"NL",
    "sg:address":"Oudegr 97",
    "sg:city":"Utrecht",
    "sg:orig_category":"Kinderkleding",
    "sg:phone":"+31 30 223 1195",
    "sg:postcode":"3511 AD",
    "sg:province":"Utrecht",
    "wof:name":"Mexx Kids Store Utrecht",
    "wof:placetype":"venue"
},
  "geometry": {"coordinates":[5.115405,52.088932],"type":"Point"}
}