{
  "type": "Feature",
  "properties": {
    "addr:full":"Zandsestraat 15 Bemmel Gelderland 6681 KB",
    "addr:housenumber":"15",
    "addr:postcode":"6681 kb",
    "addr:street":"Zandsestraat;Gelderland",
    "iso:country":"NL",
    "sg:address":"Zandsestraat 15",
    "sg:city":"Bemmel",
    "sg:orig_category":"Bloemen And Planten",
    "sg:phone":"+31 481 462 193",
    "sg:postcode":"6681 KB",
    "sg:province":"Gelderland",
    "wof:name":"Handelskwekerij Pigmans Bv",
    "wof:placetype":"venue"
},
  "geometry": {"coordinates":[5.878357,51.877899],"type":"Point"}
}