{
  "type": "Feature",
  "properties": {
    "addr:full":"Mandrill 37 Wognum North Holland 1687 VM",
    "addr:housenumber":"37",
    "addr:postcode":"1687 vm",
    "addr:street":"Mandrill",
    "iso:country":"NL",
    "sg:address":"Mandrill 37",
    "sg:city":"Wognum",
    "sg:orig_category":"Postzegels",
    "sg:phone":"+31 229 572 549",
    "sg:postcode":"1687 VM",
    "sg:province":"North Holland",
    "wof:name":"Avv",
    "wof:placetype":"venue"
},
  "geometry": {"coordinates":[5.017512,52.68478],"type":"Point"}
}