{
  "type": "Feature",
  "properties": {
    "iso:country":"NL",
    "sg:address":"Planckstr 15",
    "sg:city":"Dordrecht",
    "sg:orig_category":"Verf En Lak - Fabrieken En Groothandel",
    "sg:phone":"+31 78 618 0988",
    "sg:postcode":"3316 GS",
    "sg:province":"Zuid-Holland",
    "wof:name":"Eurochemie Bv",
    "wof:placetype":"venue"
},
  "geometry": {"coordinates":[4.634916,51.777962],"type":"Point"}
}