{
  "type": "Feature",
  "properties": {
    "addr:full":"Noord 9 Schagen Noord-Holland 1741 BA",
    "addr:housenumber":"9",
    "addr:postcode":"1741 ba",
    "addr:street":"Noord",
    "iso:country":"NL",
    "sg:address":"Noord 9",
    "sg:city":"Schagen",
    "sg:orig_category":"Metselwerken",
    "sg:phone":"+31 224 215 645",
    "sg:postcode":"1741 BA",
    "sg:province":"Noord-Holland",
    "wof:name":"Kerst Zwart",
    "wof:placetype":"venue"
},
  "geometry": {"coordinates":[4.795426,52.787209],"type":"Point"}
}