{
  "type": "Feature",
  "properties": {
    "addr:full":"Wegterswg 37 Hengelo Overijssel 7556 BP",
    "addr:housenumber":"37",
    "addr:postcode":"7556 bp",
    "addr:street":"Wegterswg",
    "iso:country":"NL",
    "sg:address":"Wegterswg 37",
    "sg:city":"Hengelo",
    "sg:orig_category":"Architecten En Architectenbureaus",
    "sg:phone":"+31 74 291 2617",
    "sg:postcode":"7556 BP",
    "sg:province":"Overijssel",
    "wof:name":"Dragt, G",
    "wof:placetype":"venue"
},
  "geometry": {"coordinates":[6.770224,52.28376],"type":"Point"}
}