{
  "type": "Feature",
  "properties": {
    "addr:full":"Nieuwewg 22A Eemnes Utrecht 3755 AD",
    "addr:housenumber":"22a",
    "addr:postcode":"3755 ad",
    "addr:street":"Nieuwewg",
    "iso:country":"NL",
    "sg:address":"Nieuwewg 22A",
    "sg:city":"Eemnes",
    "sg:orig_category":"Geluidsopnamestudio'S",
    "sg:phone":"+31 35 531 7161",
    "sg:postcode":"3755 AD",
    "sg:province":"Utrecht",
    "wof:name":"Brunet De Rochebrune",
    "wof:placetype":"venue"
},
  "geometry": {"coordinates":[5.248043,52.254951],"type":"Point"}
}