{
  "type": "Feature",
  "properties": {
    "addr:full":"Winkelcentrum 25 Etten-Leur North Brabant 4873 AB",
    "addr:housenumber":"25",
    "addr:postcode":"4873 ab",
    "addr:street":"Winkelcentrum",
    "iso:country":"NL",
    "sg:address":"Winkelcentrum 25",
    "sg:city":"Etten-Leur",
    "sg:orig_category":"Huishoudapparatuur, Televisies And Radio'S",
    "sg:phone":"+31 76 502 0672",
    "sg:postcode":"4873 AB",
    "sg:province":"North Brabant",
    "wof:name":"Horn Electro",
    "wof:placetype":"venue"
},
  "geometry": {"coordinates":[4.635814,51.568314],"type":"Point"}
}