{
  "type": "Feature",
  "properties": {
    "addr:full":"Torenstraat 33B Drachten Friesland 9203 BD",
    "addr:housenumber":"33b",
    "addr:postcode":"9203 bd",
    "addr:street":"Torenstraat",
    "iso:country":"NL",
    "sg:address":"Torenstraat 33B",
    "sg:city":"Drachten",
    "sg:orig_category":"Artsen And Specialisten",
    "sg:phone":"+31 512 518 855",
    "sg:postcode":"9203 BD",
    "sg:province":"Friesland",
    "wof:name":"J.J.B. Oudenaarden",
    "wof:placetype":"venue"
},
  "geometry": {"coordinates":[6.100347,53.109379],"type":"Point"}
}