{
  "type": "Feature",
  "properties": {
    "addr:full":"Colijnhof 52 Goes Zeeland 4463 TL",
    "addr:housenumber":"52",
    "addr:postcode":"4463 tl",
    "addr:street":"Colijnhof",
    "iso:country":"NL",
    "sg:address":"Colijnhof 52",
    "sg:city":"Goes",
    "sg:orig_category":"Boekhouders",
    "sg:phone":"+31 113 222 250",
    "sg:postcode":"4463 TL",
    "sg:province":"Zeeland",
    "wof:name":"Admar",
    "wof:placetype":"venue"
},
  "geometry": {"coordinates":[3.881874,51.509781],"type":"Point"}
}