{
  "type": "Feature",
  "properties": {
    "addr:full":"Koperwiek 40 Etten Leur Noord-Brabant 4872 WL",
    "addr:housenumber":"40",
    "addr:postcode":"4872 wl",
    "addr:street":"Koperwiek",
    "iso:country":"NL",
    "sg:address":"Koperwiek 40",
    "sg:city":"Etten Leur",
    "sg:orig_category":"Zonnebank- En Solariumcentra",
    "sg:phone":"+31 76 501 5880",
    "sg:postcode":"4872 WL",
    "sg:province":"Noord-Brabant",
    "wof:name":"Broeren Zonnehemel Verhuur",
    "wof:placetype":"venue"
},
  "geometry": {"coordinates":[4.659528,51.573269],"type":"Point"}
}