{
  "type": "Feature",
  "properties": {
    "addr:full":"Treubstraat 40 Katwijk Zh South Holland 2221 AM",
    "addr:housenumber":"40",
    "addr:postcode":"zh;2221",
    "addr:street":"Treubstraat",
    "iso:country":"NL",
    "sg:address":"Treubstraat 40",
    "sg:city":"Katwijk Zh",
    "sg:orig_category":"Boekhouders",
    "sg:phone":"+31 71 402 8573",
    "sg:postcode":"2221 AM",
    "sg:province":"South Holland",
    "wof:name":"Administratiekantoor Comptesse",
    "wof:placetype":"venue"
},
  "geometry": {"coordinates":[4.417606,52.205124],"type":"Point"}
}