{
  "type": "Feature",
  "properties": {
    "addr:full":"Haefland 6 Brunssum Limburg 6441 PA",
    "addr:housenumber":"6",
    "addr:postcode":"6441 pa",
    "addr:street":"Haefland",
    "iso:country":"NL",
    "sg:address":"Haefland 6",
    "sg:city":"Brunssum",
    "sg:orig_category":"Autoschade- Herstelbedrijven",
    "sg:phone":"+31 45 564 2419",
    "sg:postcode":"6441 PA",
    "sg:province":"Limburg",
    "wof:name":"Crash Concept",
    "wof:placetype":"venue"
},
  "geometry": {"coordinates":[5.972325,50.958252],"type":"Point"}
}