{
  "type": "Feature",
  "properties": {
    "addr:full":"Christinalaan 14 Rijnsburg Zuid-Holland 2231 ZP",
    "addr:housenumber":"14",
    "addr:postcode":"2231 zp",
    "addr:street":"Christinalaan",
    "iso:country":"NL",
    "sg:address":"Christinalaan 14",
    "sg:city":"Rijnsburg",
    "sg:orig_category":"Bloemen And Planten",
    "sg:phone":"+31 71 403 5446",
    "sg:postcode":"2231 ZP",
    "sg:province":"Zuid-Holland",
    "wof:name":"Vijvers Bloemen",
    "wof:placetype":"venue"
},
  "geometry": {"coordinates":[4.440778,52.187206],"type":"Point"}
}