{
  "type": "Feature",
  "properties": {
    "addr:full":"Poolvoswg 93 Capelle Ad Yssel Zuid-Holland 2901 BM",
    "addr:housenumber":"93",
    "addr:postcode":"2901 bm",
    "addr:street":"Poolvoswg",
    "iso:country":"NL",
    "sg:address":"Poolvoswg 93",
    "sg:city":"Capelle Ad Yssel",
    "sg:orig_category":"Onderhoudswerken",
    "sg:phone":"+31 10 451 5222",
    "sg:postcode":"2901 BM",
    "sg:province":"Zuid-Holland",
    "wof:name":"Schipper Bv",
    "wof:placetype":"venue"
},
  "geometry": {"coordinates":[4.558392,51.911625],"type":"Point"}
}