{
  "type": "Feature",
  "properties": {
    "iso:country":"NL",
    "sg:address":"Constructiewg 6",
    "sg:city":"Nieuwegein",
    "sg:orig_category":"Verenigingen En Stichtingen",
    "sg:phone":"+31 30 601 8768",
    "sg:postcode":"3433 NN",
    "sg:province":"Utrecht",
    "sg:website":"http://www.redcross.nl",
    "wof:name":"Rode Kruis District Lekstroom",
    "wof:placetype":"venue"
},
  "geometry": {"coordinates":[5.101981,52.012852],"type":"Point"}
}