{
  "type": "Feature",
  "properties": {
    "iso:country":"NL",
    "sg:address":"Bonenburgerlaan 12",
    "sg:city":"Heerde",
    "sg:orig_category":"Werving And Selectie Van Tijdelijk Personeel And Uitzendkantoren",
    "sg:phone":"+31 578 695 800",
    "sg:postcode":"8181 HE",
    "sg:province":"Gelderland",
    "wof:name":"Randstad Uitzendbureau",
    "wof:placetype":"venue"
},
  "geometry": {"coordinates":[6.0414309502,52.3857688904],"type":"Point"}
}