{
  "type": "Feature",
  "properties": {
    "addr:full":"Florynstr 3 Delfgauw Zuid-Holland 2645 HH",
    "addr:housenumber":"3",
    "addr:postcode":"2645 hh",
    "addr:street":"Florynstr",
    "iso:country":"NL",
    "sg:address":"Florynstr 3",
    "sg:city":"Delfgauw",
    "sg:orig_category":"Scholen Voor Basisonderwijs",
    "sg:phone":"+31 15 256 4159",
    "sg:postcode":"2645 HH",
    "sg:province":"Zuid-Holland",
    "wof:name":"Tweemaster Openb, De",
    "wof:placetype":"venue"
},
  "geometry": {"coordinates":[4.396875,52.010315],"type":"Point"}
}