{
  "type": "Feature",
  "properties": {
    "addr:full":"Drie Decembersingel 46 Venlo Limburg 5921 AC",
    "addr:housenumber":"46",
    "addr:postcode":"5921 ac",
    "addr:street":"Drie Decembersingel",
    "iso:country":"NL",
    "sg:address":"Drie Decembersingel 46",
    "sg:city":"Venlo",
    "sg:orig_category":"Overheidsdiensten",
    "sg:phone":"+31 77 389 1111",
    "sg:postcode":"5921 AC",
    "sg:province":"Limburg",
    "wof:name":"Waterschap Peel En Maasvallei",
    "wof:placetype":"venue"
},
  "geometry": {"coordinates":[6.1375551224,51.3690757751],"type":"Point"}
}