{
  "type": "Feature",
  "properties": {
    "iso:country":"NL",
    "sg:address":"De Kragge 44",
    "sg:city":"Amersfoort",
    "sg:orig_category":"Projectontwikkeling",
    "sg:phone":"+31 33 451 9200",
    "sg:postcode":"3823 GS",
    "sg:province":"Utrecht",
    "sg:website":"http://www.agvastgoed.nl",
    "wof:name":"Ag Bv",
    "wof:placetype":"venue"
},
  "geometry": {"coordinates":[5.39961,52.189075],"type":"Point"}
}