{
  "type": "Feature",
  "properties": {
    "addr:full":"H K Onneswg 45-47 Bussum Noord-Holland 1404 CA",
    "addr:housenumber":"45-47",
    "addr:postcode":"1404 ca",
    "iso:country":"NL",
    "sg:address":"H K Onneswg 45-47",
    "sg:city":"Bussum",
    "sg:orig_category":"Huishoudapparatuur, Televisies And Radio'S",
    "sg:phone":"+31 35 691 4652",
    "sg:postcode":"1404 CA",
    "sg:province":"Noord-Holland",
    "wof:name":"Audio Video Center Van Zanten",
    "wof:placetype":"venue"
},
  "geometry": {"coordinates":[5.162605,52.276829],"type":"Point"}
}