{
  "type": "Feature",
  "properties": {
    "iso:country":"NL",
    "sg:address":"Grubbenweg 2",
    "sg:city":"Klimmen",
    "sg:orig_category":"Architecten",
    "sg:phone":"+31 45 405 1635",
    "sg:postcode":"6343 CB",
    "sg:province":"Limburg",
    "wof:name":"Ir H P Ritt Bv",
    "wof:placetype":"venue"
},
  "geometry": {"coordinates":[5.880585,50.875202],"type":"Point"}
}