{
  "type": "Feature",
  "properties": {
    "addr:full":"Zuiderkoggewg 2 Hem Noord-Holland 1607 MV",
    "addr:housenumber":"2",
    "addr:postcode":"1607 mv",
    "addr:street":"Zuiderkoggewg",
    "iso:country":"NL",
    "sg:address":"Zuiderkoggewg 2",
    "sg:city":"Hem",
    "sg:orig_category":"Machinefabrieken",
    "sg:phone":"+31 228 542 205",
    "sg:postcode":"1607 MV",
    "sg:province":"Noord-Holland",
    "wof:name":"Co Engineering Bv",
    "wof:placetype":"venue"
},
  "geometry": {"coordinates":[5.184842,52.656765],"type":"Point"}
}