{
  "type": "Feature",
  "properties": {
    "addr:full":"Schoolstraat 2 Beerta Groningen 9686 NC",
    "addr:housenumber":"2",
    "addr:postcode":"9686 nc",
    "addr:street":"Schoolstraat",
    "iso:country":"NL",
    "sg:address":"Schoolstraat 2",
    "sg:city":"Beerta",
    "sg:orig_category":"Kappers",
    "sg:phone":"+31 597 331 861",
    "sg:postcode":"9686 NC",
    "sg:province":"Groningen",
    "wof:name":"Kapsalon Agnes",
    "wof:placetype":"venue"
},
  "geometry": {"coordinates":[7.0947561264,53.1738739014],"type":"Point"}
}