{
  "type": "Feature",
  "properties": {
    "addr:full":"Sperwerstraat 33 Hilversum North Holland 1223 PN",
    "addr:housenumber":"33",
    "addr:postcode":"1223 pn",
    "addr:street":"Sperwerstraat",
    "iso:country":"NL",
    "sg:address":"Sperwerstraat 33",
    "sg:city":"Hilversum",
    "sg:orig_category":"Loodgieterswerk, Verwarming And Sanitaire Installaties",
    "sg:phone":"+31 35 685 5930",
    "sg:postcode":"1223 PN",
    "sg:province":"North Holland",
    "wof:name":"J.F. Bos",
    "wof:placetype":"venue"
},
  "geometry": {"coordinates":[5.199291,52.223049],"type":"Point"}
}