{
  "type": "Feature",
  "properties": {
    "addr:full":"Houtkolk 7 Dokkum Friesland 9101 BH",
    "addr:housenumber":"7",
    "addr:postcode":"9101 bh",
    "addr:street":"Houtkolk",
    "iso:country":"NL",
    "sg:address":"Houtkolk 7",
    "sg:city":"Dokkum",
    "sg:orig_category":"Drukkerijen And Copyshops",
    "sg:phone":"+31 519 297 942",
    "sg:postcode":"9101 BH",
    "sg:province":"Friesland",
    "wof:name":"Santexo",
    "wof:placetype":"venue"
},
  "geometry": {"coordinates":[5.989403,53.325085],"type":"Point"}
}