{
  "type": "Feature",
  "properties": {
    "addr:full":"Burg Leenstr 54 Lochem Gelderland 7242 AB",
    "addr:housenumber":"54",
    "addr:postcode":"7242 ab",
    "addr:street":"Burg;Gelderland",
    "iso:country":"NL",
    "sg:address":"Burg Leenstr 54",
    "sg:city":"Lochem",
    "sg:orig_category":"Drukkerijen",
    "sg:phone":"+31 573 254 630",
    "sg:postcode":"7242 AB",
    "sg:province":"Gelderland",
    "wof:name":"Lammerdink",
    "wof:placetype":"venue"
},
  "geometry": {"coordinates":[6.412586,52.158829],"type":"Point"}
}