{
  "type": "Feature",
  "properties": {
    "addr:full":"Oosterbroekwg 8 Gronsveld Limburg 6247 BN",
    "addr:housenumber":"8",
    "addr:postcode":"6247 bn",
    "addr:street":"Oosterbroekwg",
    "iso:country":"NL",
    "sg:address":"Oosterbroekwg 8",
    "sg:city":"Gronsveld",
    "sg:orig_category":"Betonijzervlechten",
    "sg:phone":"+31 43 408 1501",
    "sg:postcode":"6247 BN",
    "sg:province":"Limburg",
    "wof:name":"Pinxt, M",
    "wof:placetype":"venue"
},
  "geometry": {"coordinates":[5.731725,50.809811],"type":"Point"}
}