{
  "type": "Feature",
  "properties": {
    "addr:full":"Leidsestrwg 15 S Gravenhage Zuid-Holland 2594 BA",
    "addr:housenumber":"15;gravenhage",
    "addr:postcode":"2594 ba",
    "addr:street":"Leidsestrwg;S",
    "iso:country":"NL",
    "sg:address":"Leidsestrwg 15",
    "sg:city":"S Gravenhage",
    "sg:classifiers":[
        {
            "category":"Real Estate",
            "subcategory":"Real Estate Operator",
            "type":"Services"
        }
    ],
    "sg:phone":"+31 70 383 2860",
    "sg:postcode":"2594 BA",
    "sg:province":"Zuid-Holland",
    "sg:tags":[
        "appartementen",
        "en",
        "flat"
    ],
    "wof:name":"Ch\u00e2teau Bleu",
    "wof:placetype":"venue"
},
  "geometry": {"coordinates":[4.317415,52.083992],"type":"Point"}
}