{
  "type": "Feature",
  "properties": {
    "addr:full":"Broekstr 5 Brunssum Limburg 6443 XC",
    "addr:housenumber":"5",
    "addr:postcode":"6443 xc",
    "addr:street":"Broekstr",
    "iso:country":"NL",
    "sg:address":"Broekstr 5",
    "sg:city":"Brunssum",
    "sg:orig_category":"Kinderopvang",
    "sg:phone":"+31 45 527 4020",
    "sg:postcode":"6443 XC",
    "sg:province":"Limburg",
    "wof:name":"Rollebol",
    "wof:placetype":"venue"
},
  "geometry": {"coordinates":[5.982427,50.942909],"type":"Point"}
}