{
  "type": "Feature",
  "properties": {
    "addr:full":"Ubbo Emmiussingel 2 Groningen Groningen 9711 BH",
    "addr:housenumber":"2",
    "addr:postcode":"9711 bh",
    "addr:street":"Ubbo Emmiussingel",
    "iso:country":"NL",
    "sg:address":"Ubbo Emmiussingel 2",
    "sg:city":"Groningen",
    "sg:orig_category":"Makelaars In Onroerend Goed",
    "sg:phone":"+31 50 314 1232",
    "sg:postcode":"9711 BH",
    "sg:province":"Groningen",
    "wof:name":"Dtz Zadelhoff Vof",
    "wof:placetype":"venue"
},
  "geometry": {"coordinates":[6.568435,53.212769],"type":"Point"}
}