{
  "type": "Feature",
  "properties": {
    "iso:country":"NL",
    "sg:address":"Noordkd 64",
    "sg:city":"Waddinxveen",
    "sg:orig_category":"Projectinrichting",
    "sg:phone":"+31 182 516 223",
    "sg:postcode":"2741 EZ",
    "sg:province":"Zuid-Holland",
    "sg:website":"http://www.da-vinci.nl",
    "wof:name":"Da Vinci",
    "wof:placetype":"venue"
},
  "geometry": {"coordinates":[4.65507,52.044601],"type":"Point"}
}