{
  "type": "Feature",
  "properties": {
    "iso:country":"NL",
    "sg:address":"Dillenburgstr 9",
    "sg:city":"Eindhoven",
    "sg:orig_category":"Metaalbewerking",
    "sg:phone":"+31 40 259 7200",
    "sg:postcode":"5652 AM",
    "sg:province":"North Brabant",
    "sg:website":"HTTP://www.nebato.nl",
    "wof:name":"Nebato Bv",
    "wof:placetype":"venue"
},
  "geometry": {"coordinates":[5.439332,51.431591],"type":"Point"}
}