{
  "type": "Feature",
  "properties": {
    "iso:country":"NL",
    "sg:address":"Willem Schuylenburglaan 1",
    "sg:city":"Utrecht",
    "sg:orig_category":"Kinderopvang Behalve Thuis",
    "sg:phone":"+31 30 272 3037",
    "sg:postcode":"3571 SB",
    "sg:province":"Utrecht",
    "wof:name":"Kinderdagverblijf Mini Stek",
    "wof:placetype":"venue"
},
  "geometry": {"coordinates":[5.11792,52.10725],"type":"Point"}
}