{
  "type": "Feature",
  "properties": {
    "iso:country":"NL",
    "sg:address":"Houtmortelstr 37",
    "sg:city":"Thorn",
    "sg:orig_category":"Parketvloeren",
    "sg:phone":"+31 475 561 314",
    "sg:postcode":"6017 CM",
    "sg:province":"Limburg",
    "wof:name":"Heugten, P W M Van",
    "wof:placetype":"venue"
},
  "geometry": {"coordinates":[5.840663,51.167107],"type":"Point"}
}