{
  "type": "Feature",
  "properties": {
    "addr:full":"Hulst 122 Geldrop Noord-Brabant 5662 TK",
    "addr:housenumber":"122",
    "addr:postcode":"5662 tk",
    "addr:street":"Hulst",
    "iso:country":"NL",
    "sg:address":"Hulst 122",
    "sg:city":"Geldrop",
    "sg:classifiers":[
        {
            "category":"Retail",
            "subcategory":"Auto Repair",
            "type":"Services"
        }
    ],
    "sg:phone":"+31 40 286 3024",
    "sg:postcode":"5662 TK",
    "sg:province":"Noord-Brabant",
    "sg:tags":[
        "garage"
    ],
    "wof:name":"Geboers Autobedrijf, Mario",
    "wof:placetype":"venue"
},
  "geometry": {"coordinates":[5.544454,51.429989],"type":"Point"}
}