{
  "type": "Feature",
  "properties": {
    "addr:full":"Ahornstr 52 Utrecht Utrecht 3552 CH",
    "addr:housenumber":"52",
    "addr:postcode":"3552",
    "addr:street":"Ahornstr",
    "iso:country":"NL",
    "sg:address":"Ahornstr 52",
    "sg:city":"Utrecht",
    "sg:orig_category":"Grafisch Ontwerpers",
    "sg:phone":"+31 30 271 3237",
    "sg:postcode":"3552 CH",
    "sg:province":"Utrecht",
    "wof:name":"Spithoven, Maurice",
    "wof:placetype":"venue"
},
  "geometry": {"coordinates":[-73.996292,40.613091],"type":"Point"}
}