{
  "type": "Feature",
  "properties": {
    "addr:full":"Altingstr 223 S Gravenhage Zuid-Holland 2593 SW",
    "addr:housenumber":"223;gravenhage;2593",
    "addr:street":"S;Sw",
    "iso:country":"NL",
    "sg:address":"Altingstr 223",
    "sg:city":"S Gravenhage",
    "sg:orig_category":"Fietsen En Bromfietsen",
    "sg:phone":"+31 70 383 5697",
    "sg:postcode":"2593 SW",
    "sg:province":"Zuid-Holland",
    "wof:name":"Renzo",
    "wof:placetype":"venue"
},
  "geometry": {"coordinates":[4.34266,52.086121],"type":"Point"}
}