{
  "type": "Feature",
  "properties": {
    "addr:full":"Quadenoord 222 Rotterdam Zuid-Holland 3079 XJ",
    "addr:housenumber":"222",
    "addr:postcode":"3079 xj",
    "addr:street":"Quadenoord",
    "iso:country":"NL",
    "sg:address":"Quadenoord 222",
    "sg:city":"Rotterdam",
    "sg:classifiers":[
        {
            "category":"Utilities",
            "subcategory":"Cable",
            "type":"Services"
        }
    ],
    "sg:phone":"+31 10 484 6462",
    "sg:postcode":"3079 XJ",
    "sg:province":"Zuid-Holland",
    "sg:tags":[
        "masseur",
        "en",
        "heilgymnasten"
    ],
    "wof:name":"Bodytrend",
    "wof:placetype":"venue"
},
  "geometry": {"coordinates":[4.55818,51.878971],"type":"Point"}
}