{
  "type": "Feature",
  "properties": {
    "addr:full":"Struytse Hoeck 344 Hellevoetsluis South Holland 3223 DE",
    "addr:housenumber":"344",
    "addr:postcode":"3223 de",
    "addr:street":"Struytse Hoeck",
    "iso:country":"NL",
    "sg:address":"Struytse Hoeck 344",
    "sg:city":"Hellevoetsluis",
    "sg:orig_category":"Babyartikelen",
    "sg:phone":"+31 181 399 926",
    "sg:postcode":"3223 DE",
    "sg:province":"South Holland",
    "wof:name":"Pr?natal",
    "wof:placetype":"venue"
},
  "geometry": {"coordinates":[4.144677,51.82975],"type":"Point"}
}