{
  "type": "Feature",
  "properties": {
    "addr:full":"Koperwiekln 1 Bilthoven Utrecht 3722 CA",
    "addr:housenumber":"1",
    "addr:postcode":"3722 ca",
    "addr:street":"Koperwiekln",
    "iso:country":"NL",
    "sg:address":"Koperwiekln 1",
    "sg:city":"Bilthoven",
    "sg:orig_category":"Kaarsen - Fabrieken En Groothandel",
    "sg:phone":"+31 6 24645128",
    "sg:postcode":"3722 CA",
    "sg:province":"Utrecht",
    "wof:name":"Shamballa, Nederland",
    "wof:placetype":"venue"
},
  "geometry": {"coordinates":[5.2109298706,52.1214981079],"type":"Point"}
}