{
  "type": "Feature",
  "properties": {
    "addr:full":"Verrijn Stuartweg 71 Diemen Noord-Holland 1112 AW",
    "addr:housenumber":"71",
    "addr:postcode":"1112 aw",
    "addr:street":"Verrijn Stuartweg",
    "iso:country":"NL",
    "sg:address":"Verrijn Stuartweg 71",
    "sg:city":"Diemen",
    "sg:orig_category":"Zuivelproducten And Spijsoli?n Gh",
    "sg:phone":"+31 20 690 1853",
    "sg:postcode":"1112 AW",
    "sg:province":"Noord-Holland",
    "wof:name":"Eierencentrale West Nederland Bv",
    "wof:placetype":"venue"
},
  "geometry": {"coordinates":[4.96913,52.331261],"type":"Point"}
}