{
  "type": "Feature",
  "properties": {
    "addr:full":"Noordhollandstraat 61 Amsterdam North Holland 1081 AS",
    "addr:housenumber":"61",
    "addr:postcode":"1081 as",
    "addr:street":"Noordhollandstraat",
    "iso:country":"NL",
    "sg:address":"Noordhollandstraat 61",
    "sg:city":"Amsterdam",
    "sg:orig_category":"Diverse Grafische Activiteiten",
    "sg:phone":"+31 20 301 7211",
    "sg:postcode":"1081 AS",
    "sg:province":"North Holland",
    "wof:name":"Bagage Bureau",
    "wof:placetype":"venue"
},
  "geometry": {"coordinates":[4.865735,52.324684],"type":"Point"}
}