{
  "type": "Feature",
  "properties": {
    "addr:full":"Hamburgerstraat 59 Doetinchem Gelderland 7001 AJ",
    "addr:housenumber":"59",
    "addr:postcode":"7001 aj",
    "addr:street":"Hamburgerstraat;Gelderland",
    "iso:country":"NL",
    "sg:address":"Hamburgerstraat 59",
    "sg:city":"Doetinchem",
    "sg:classifiers":[
        {
            "category":"Retail",
            "subcategory":"Photofinishing",
            "type":"Services"
        }
    ],
    "sg:phone":"+31 314 378 651",
    "sg:postcode":"7001 AJ",
    "sg:province":"Gelderland",
    "sg:tags":[
        "foto",
        "film"
    ],
    "wof:name":"Drent Megastore Doetinchem Bv",
    "wof:placetype":"venue"
},
  "geometry": {"coordinates":[6.290523,51.964043],"type":"Point"}
}