{
  "type": "Feature",
  "properties": {
    "addr:full":"Onderlangs 35 Otterlo Gelderland 6731 BK",
    "addr:housenumber":"35",
    "addr:postcode":"6731 bk",
    "addr:street":"Onderlangs;Gelderland",
    "iso:country":"NL",
    "sg:address":"Onderlangs 35",
    "sg:city":"Otterlo",
    "sg:classifiers":[
        {
            "category":"Travel",
            "subcategory":"Hotels & Motels",
            "type":"Entertainment"
        }
    ],
    "sg:phone":"+31 318 591 220",
    "sg:postcode":"6731 BK",
    "sg:province":"Gelderland",
    "wof:name":"Carnegie'S Cottage",
    "wof:placetype":"venue"
},
  "geometry": {"coordinates":[5.778956,52.098713],"type":"Point"}
}