{
  "type": "Feature",
  "properties": {
    "iso:country":"NL",
    "sg:address":"Wingerdstr 51",
    "sg:city":"Beuningen Gld",
    "sg:orig_category":"Autorijscholen",
    "sg:phone":"+31 24 677 2557",
    "sg:postcode":"6641 BM",
    "sg:province":"Gelderland",
    "wof:name":"Theunissen Auto- & Bromfietsrijschool",
    "wof:placetype":"venue"
},
  "geometry": {"coordinates":[5.779983,51.858742],"type":"Point"}
}