{
  "type": "Feature",
  "properties": {
    "addr:full":"Euroweg 4 Leek Groningen 9351 EN",
    "addr:housenumber":"4",
    "addr:postcode":"9351 en",
    "addr:street":"Euroweg",
    "iso:country":"NL",
    "sg:address":"Euroweg 4",
    "sg:city":"Leek",
    "sg:orig_category":"Metaalwerken",
    "sg:phone":"+31 594 518 079",
    "sg:postcode":"9351 EN",
    "sg:province":"Groningen",
    "wof:name":"Vof Van Duinen Tapijt",
    "wof:placetype":"venue"
},
  "geometry": {"coordinates":[6.381019,53.165112],"type":"Point"}
}