{
  "type": "Feature",
  "properties": {
    "addr:full":"Stoombootwg 31 Amsterdam North Holland 1035 TT",
    "addr:housenumber":"31",
    "addr:postcode":"1035 tt",
    "addr:street":"Stoombootwg",
    "iso:country":"NL",
    "sg:address":"Stoombootwg 31",
    "sg:city":"Amsterdam",
    "sg:orig_category":"Wijnkoperijen En -Groothandel",
    "sg:phone":"+31 20 493 1444",
    "sg:postcode":"1035 TT",
    "sg:province":"North Holland",
    "wof:name":"Terres Des Vins",
    "wof:placetype":"venue"
},
  "geometry": {"coordinates":[4.9007759094,52.4175338745],"type":"Point"}
}