{
  "type": "Feature",
  "properties": {
    "addr:full":"Dompln 25 Utrecht Utrecht 3512 JE",
    "addr:housenumber":"25",
    "addr:postcode":"3512 je",
    "addr:street":"Dompln",
    "iso:country":"NL",
    "sg:address":"Dompln 25",
    "sg:city":"Utrecht",
    "sg:orig_category":"Kunsthandel",
    "sg:phone":"+31 30 223 1304",
    "sg:postcode":"3512 JE",
    "sg:province":"Utrecht",
    "wof:name":"Galeria Domplein",
    "wof:placetype":"venue"
},
  "geometry": {"coordinates":[5.121533,52.090321],"type":"Point"}
}