{
  "type": "Feature",
  "properties": {
    "addr:full":"Flamingowg 43 Luchth Schiphol Noord-Holland 1118 EE",
    "addr:housenumber":"43",
    "addr:postcode":"1118 ee",
    "addr:street":"Flamingowg",
    "iso:country":"NL",
    "sg:address":"Flamingowg 43",
    "sg:city":"Luchth Schiphol",
    "sg:orig_category":"Luchtvrachtexpediteurs",
    "sg:phone":"+31 20 316 0070",
    "sg:postcode":"1118 EE",
    "sg:province":"Noord-Holland",
    "wof:name":"Meijers Nv, J C",
    "wof:placetype":"venue"
},
  "geometry": {"coordinates":[4.735026,52.29171],"type":"Point"}
}