{
  "type": "Feature",
  "properties": {
    "addr:full":"Douwencamp 32 Nykerk Gld Gelderland 3861 LE",
    "addr:housenumber":"32",
    "addr:postcode":"3861 le",
    "addr:street":"Douwencamp;Gld Gelderland",
    "iso:country":"NL",
    "sg:address":"Douwencamp 32",
    "sg:city":"Nykerk Gld",
    "sg:orig_category":"Binnenhuisarchitectuur",
    "sg:phone":"+31 33 245 3558",
    "sg:postcode":"3861 LE",
    "sg:province":"Gelderland",
    "wof:name":"Tongeren, R Van",
    "wof:placetype":"venue"
},
  "geometry": {"coordinates":[5.489134,52.229774],"type":"Point"}
}