{
  "type": "Feature",
  "properties": {
    "addr:full":"Kronenburgsingel 19 Arnhem Gelderland 6831 GD",
    "addr:housenumber":"19",
    "addr:postcode":"6831 gd",
    "addr:street":"Kronenburgsingel",
    "iso:country":"NL",
    "sg:address":"Kronenburgsingel 19",
    "sg:city":"Arnhem",
    "sg:orig_category":"Banken And Kredietinstellingen",
    "sg:phone":"+31 26 320 1811",
    "sg:postcode":"6831 GD",
    "sg:province":"Gelderland",
    "wof:name":"Sns Bank",
    "wof:placetype":"venue"
},
  "geometry": {"coordinates":[5.898711,51.959671],"type":"Point"}
}