{
  "type": "Feature",
  "properties": {
    "addr:full":"Jhr De Jongestr 26 Klazienaveen Drenthe 7891 KN",
    "addr:housenumber":"26",
    "addr:postcode":"7891 kn",
    "addr:street":"Jhr De Jongestr",
    "iso:country":"NL",
    "sg:address":"Jhr De Jongestr 26",
    "sg:city":"Klazienaveen",
    "sg:orig_category":"Scholen Voor Basisonderwijs",
    "sg:phone":"+31 591 312 366",
    "sg:postcode":"7891 KN",
    "sg:province":"Drenthe",
    "wof:name":"Henricussch, Rk",
    "wof:placetype":"venue"
},
  "geometry": {"coordinates":[6.992676,52.723145],"type":"Point"}
}