{
  "type": "Feature",
  "properties": {
    "addr:full":"Rijsdijk 44 Rhoon South Holland 3161 HP",
    "addr:housenumber":"44",
    "addr:postcode":"3161 hp",
    "addr:street":"Rijsdijk",
    "iso:country":"NL",
    "sg:address":"Rijsdijk 44",
    "sg:city":"Rhoon",
    "sg:orig_category":"Verzekeringen",
    "sg:phone":"+31 10 501 5601",
    "sg:postcode":"3161 HP",
    "sg:province":"South Holland",
    "wof:name":"Mourik Marine Insurance Consultancy Bv",
    "wof:placetype":"venue"
},
  "geometry": {"coordinates":[4.429902,51.855629],"type":"Point"}
}