{
  "type": "Feature",
  "properties": {
    "iso:country":"NL",
    "sg:address":"Amsterdamsestraatweg 540",
    "sg:city":"Utrecht",
    "sg:orig_category":"Hypotheken And Hypotheekbanken",
    "sg:phone":"+31 30 246 8008",
    "sg:postcode":"3553 EN",
    "sg:province":"Utrecht",
    "wof:name":"Gruter En Partners Assurantien",
    "wof:placetype":"venue"
},
  "geometry": {"coordinates":[5.083884,52.109901],"type":"Point"}
}