{
  "type": "Feature",
  "properties": {
    "addr:full":"Eemlandweg 9 Huizen North Holland 1271 KR",
    "addr:housenumber":"9",
    "addr:postcode":"1271 kr",
    "addr:street":"Eemlandweg",
    "iso:country":"NL",
    "sg:address":"Eemlandweg 9",
    "sg:city":"Huizen",
    "sg:orig_category":"Autokeuringen",
    "sg:phone":"+31 35 525 3493",
    "sg:postcode":"1271 KR",
    "sg:province":"North Holland",
    "wof:name":"Autobedrijf Vos Bv",
    "wof:placetype":"venue"
},
  "geometry": {"coordinates":[5.239782,52.300442],"type":"Point"}
}