{
  "type": "Feature",
  "properties": {
    "addr:full":"Gouvernestraat 276 Rotterdam South Holland 3014 PX",
    "addr:housenumber":"276",
    "addr:postcode":"3014 px",
    "addr:street":"Gouvernestraat",
    "iso:country":"NL",
    "sg:address":"Gouvernestraat 276",
    "sg:city":"Rotterdam",
    "sg:orig_category":"Verhuur Catering-, Feest- En Evenementbenodigdheden",
    "sg:phone":"+31 10 225 0642",
    "sg:postcode":"3014 PX",
    "sg:province":"South Holland",
    "wof:name":"Horeca Onderhoud Werner",
    "wof:placetype":"venue"
},
  "geometry": {"coordinates":[4.469814,51.916656],"type":"Point"}
}