{
  "type": "Feature",
  "properties": {
    "addr:full":"Gildenstr 4A Nykerk Gld Gelderland 3861 RG",
    "addr:housenumber":"4a",
    "addr:postcode":"3861 rg",
    "addr:street":"Gildenstr;Gld Gelderland",
    "iso:country":"NL",
    "sg:address":"Gildenstr 4A",
    "sg:city":"Nykerk Gld",
    "sg:orig_category":"Levensmiddelen - Fabrieken En Groothandel",
    "sg:phone":"+31 33 245 5090",
    "sg:postcode":"3861 RG",
    "sg:province":"Gelderland",
    "sg:website":"http://www.wellerverhoef.nl",
    "wof:name":"Weller & Verhoef Bv",
    "wof:placetype":"venue"
},
  "geometry": {"coordinates":[5.485781,52.230118],"type":"Point"}
}