{
  "type": "Feature",
  "properties": {
    "iso:country":"NL",
    "sg:address":"Tilweg 34",
    "sg:city":"Gees",
    "sg:orig_category":"Wegen And Sportterreinen",
    "sg:phone":"+31 524 582 377",
    "sg:postcode":"7863 TK",
    "sg:province":"Kentucky",
    "wof:name":"A. Duinkerken",
    "wof:placetype":"venue"
},
  "geometry": {"coordinates":[-85.049949646,38.0581626892],"type":"Point"}
}