{
  "type": "Feature",
  "properties": {
    "addr:full":"Bentveldsduinweg 3 Aerdenhout Noord-Holland 2111 AK",
    "addr:housenumber":"3",
    "addr:postcode":"2111 ak",
    "addr:street":"Bentveldsduinweg",
    "iso:country":"NL",
    "sg:address":"Bentveldsduinweg 3",
    "sg:city":"Aerdenhout",
    "sg:orig_category":"Bedrijfs- And Managementsconsultants",
    "sg:phone":"+31 23 524 2753",
    "sg:postcode":"2111 AK",
    "sg:province":"Noord-Holland",
    "wof:name":"M & M Group Bv",
    "wof:placetype":"venue"
},
  "geometry": {"coordinates":[4.588451,52.364258],"type":"Point"}
}