{
  "type": "Feature",
  "properties": {
    "addr:full":"Driemanssteewg 50 Rotterdam Zuid-Holland 3084 CB",
    "addr:housenumber":"50",
    "addr:postcode":"3084 cb",
    "addr:street":"Driemanssteewg",
    "iso:country":"NL",
    "sg:address":"Driemanssteewg 50",
    "sg:city":"Rotterdam",
    "sg:orig_category":"Hydraulische Apparaten En Installaties",
    "sg:phone":"+31 10 293 8080",
    "sg:postcode":"3084 CB",
    "sg:province":"Zuid-Holland",
    "wof:name":"Hydrosteel Supplies Bv",
    "wof:placetype":"venue"
},
  "geometry": {"coordinates":[4.455532,51.86536],"type":"Point"}
}