{
  "type": "Feature",
  "properties": {
    "iso:country":"NL",
    "sg:address":"Laat 128",
    "sg:city":"Alkmaar",
    "sg:orig_category":"Schoenen",
    "sg:phone":"+31 72 512 1107",
    "sg:postcode":"1811 EL",
    "sg:province":"Noord-Holland",
    "wof:name":"Schoenenreus",
    "wof:placetype":"venue"
},
  "geometry": {"coordinates":[4.746857,52.630634],"type":"Point"}
}