{
  "type": "Feature",
  "properties": {
    "addr:full":"Bruilweering 411 Eelderwolde Drenthe 9766 ",
    "addr:housenumber":"411",
    "addr:postcode":"9766",
    "addr:street":"Bruilweering",
    "iso:country":"NL",
    "sg:address":"Bruilweering 411",
    "sg:city":"Eelderwolde",
    "sg:orig_category":"Schilders",
    "sg:phone":"+31 50 527 9918",
    "sg:postcode":"9766 ",
    "sg:province":"Drenthe",
    "wof:name":"Veen, W H Van",
    "wof:placetype":"venue"
},
  "geometry": {"coordinates":[6.53033,53.193199],"type":"Point"}
}