{
  "type": "Feature",
  "properties": {
    "iso:country":"NL",
    "sg:address":"Bruilweering 411",
    "sg:city":"Eelderwolde",
    "sg:orig_category":"Schilders",
    "sg:phone":"+31 50 527 9918",
    "sg:postcode":"9766 ",
    "sg:province":"Drenthe",
    "wof:name":"Veen, W H Van",
    "wof:placetype":"venue"
},
  "geometry": {"coordinates":[6.53033,53.193199],"type":"Point"}
}