{
  "type": "Feature",
  "properties": {
    "addr:full":"Keppelstr 36 Dokkum Friesland 9101 MV",
    "addr:housenumber":"36",
    "addr:postcode":"9101 mv",
    "addr:street":"Keppelstr",
    "iso:country":"NL",
    "sg:address":"Keppelstr 36",
    "sg:city":"Dokkum",
    "sg:orig_category":"Cafetaria'S",
    "sg:phone":"+31 519 297 061",
    "sg:postcode":"9101 MV",
    "sg:province":"Friesland",
    "wof:name":"Woudpoort, De",
    "wof:placetype":"venue"
},
  "geometry": {"coordinates":[5.999551,53.323948],"type":"Point"}
}