{
  "type": "Feature",
  "properties": {
    "addr:full":"Burg Rothestr 53A Wyk Aan Zee North Holland 1949 CC",
    "addr:housenumber":"53a",
    "addr:postcode":"1949 cc",
    "addr:street":"Burg Rothestr",
    "iso:country":"NL",
    "sg:address":"Burg Rothestr 53A",
    "sg:city":"Wyk Aan Zee",
    "sg:orig_category":"Vakantieverblijven",
    "sg:phone":"+31 251 374 250",
    "sg:postcode":"1949 CC",
    "sg:province":"North Holland",
    "wof:name":"Banjaert",
    "wof:placetype":"venue"
},
  "geometry": {"coordinates":[4.594696,52.491993],"type":"Point"}
}