{
  "type": "Feature",
  "properties": {
    "addr:full":"Veldensteinlaan 15 Jaarsveld Utrecht 3413 MK",
    "addr:housenumber":"15",
    "addr:postcode":"3413",
    "addr:street":"Veldensteinlaan",
    "iso:country":"NL",
    "sg:address":"Veldensteinlaan 15",
    "sg:city":"Jaarsveld",
    "sg:orig_category":"Schoonheidssalons",
    "sg:phone":"+31 348 551 521",
    "sg:postcode":"3413 MK",
    "sg:province":"Utrecht",
    "wof:name":"Schoonheidssalon Aphrodite",
    "wof:placetype":"venue"
},
  "geometry": {"coordinates":[4.974614,51.969624],"type":"Point"}
}