{
  "type": "Feature",
  "properties": {
    "addr:full":"Emmalaan 2 Etten-Leur North Brabant 4872 CA",
    "addr:housenumber":"2",
    "addr:postcode":"4872 ca",
    "addr:street":"Emmalaan",
    "iso:country":"NL",
    "sg:address":"Emmalaan 2",
    "sg:city":"Etten-Leur",
    "sg:orig_category":"Bejaardeninstellingen And Serviceflats",
    "sg:phone":"+31 76 503 4888",
    "sg:postcode":"4872 CA",
    "sg:province":"North Brabant",
    "wof:name":"Vitalis Emmaflat",
    "wof:placetype":"venue"
},
  "geometry": {"coordinates":[4.649096,51.577057],"type":"Point"}
}