{
  "type": "Feature",
  "properties": {
    "addr:full":"Middenweg 591 Heerhugowaard Noord-Holland 1704 BH",
    "addr:housenumber":"591",
    "addr:postcode":"1704 bh",
    "addr:street":"Middenweg",
    "iso:country":"NL",
    "sg:address":"Middenweg 591",
    "sg:city":"Heerhugowaard",
    "sg:orig_category":"Fruitteelt",
    "sg:phone":"+31 72 574 3630",
    "sg:postcode":"1704 BH",
    "sg:province":"Noord-Holland",
    "wof:name":"Vof G.I.M. De Wit-G.A.J. Veldman",
    "wof:placetype":"venue"
},
  "geometry": {"coordinates":[4.852463,52.716179],"type":"Point"}
}