{
  "type": "Feature",
  "properties": {
    "iso:country":"NL",
    "sg:address":"Hoofdstraat 63",
    "sg:city":"Apeldoorn",
    "sg:orig_category":"Schoenen",
    "sg:phone":"+31 55 579 1888",
    "sg:postcode":"7311 JV",
    "sg:province":"Gelderland",
    "wof:name":"Dolcis",
    "wof:placetype":"venue"
},
  "geometry": {"coordinates":[5.964063,52.212788],"type":"Point"}
}