{
  "type": "Feature",
  "properties": {
    "addr:full":"Aalsmeerderdijk 212 Aalsmeerderbrug North Holland 1436 BB",
    "addr:housenumber":"212",
    "addr:postcode":"1436 bb",
    "addr:street":"Aalsmeerderdijk",
    "iso:country":"NL",
    "sg:address":"Aalsmeerderdijk 212",
    "sg:city":"Aalsmeerderbrug",
    "sg:orig_category":"Bloemen- And Plantenteelt",
    "sg:phone":"+31 20 653 4272",
    "sg:postcode":"1436 BB",
    "sg:province":"North Holland",
    "wof:name":"Orchideeen Maarssen Handelskwekerij Bv",
    "wof:placetype":"venue"
},
  "geometry": {"coordinates":[4.765229,52.277454],"type":"Point"}
}