{
  "type": "Feature",
  "properties": {
    "addr:full":"Duinzoom 8 Rockanje Zuid-Holland 3235 CD",
    "addr:housenumber":"8",
    "addr:postcode":"3235 cd",
    "addr:street":"Duinzoom",
    "iso:country":"NL",
    "sg:address":"Duinzoom 8",
    "sg:city":"Rockanje",
    "sg:orig_category":"Beeldende Kunstenaars",
    "sg:phone":"+31 181 402 465",
    "sg:postcode":"3235 CD",
    "sg:province":"Zuid-Holland",
    "wof:name":"Hazelbag, B L F",
    "wof:placetype":"venue"
},
  "geometry": {"coordinates":[4.060215,51.871384],"type":"Point"}
}