{
  "type": "Feature",
  "properties": {
    "iso:country":"NL",
    "sg:address":"Haagweg 11",
    "sg:city":"Rijswijk Zh",
    "sg:orig_category":"Kappers",
    "sg:phone":"+31 70 399 4777",
    "sg:postcode":"2281 AA",
    "sg:province":"Zuid-Holland",
    "wof:name":"Good Looking Haarmode",
    "wof:placetype":"venue"
},
  "geometry": {"coordinates":[4.3361568451,52.0590324402],"type":"Point"}
}