{
  "type": "Feature",
  "properties": {
    "addr:full":"Steynln 19F Zeist Utrecht 3701 EA",
    "addr:housenumber":"19f",
    "addr:postcode":"3701 ea",
    "iso:country":"NL",
    "sg:address":"Steynln 19F",
    "sg:city":"Zeist",
    "sg:orig_category":"Land- En Tuinbouw - Loonbedrijven",
    "sg:phone":"+31 30 692 1566",
    "sg:postcode":"3701 EA",
    "sg:province":"Utrecht",
    "wof:name":"Rdp Agro Vision International",
    "wof:placetype":"venue"
},
  "geometry": {"coordinates":[5.24387,52.08548],"type":"Point"}
}