{
  "type": "Feature",
  "properties": {
    "addr:full":"Gein Z 47 Abcoude North Holland 1391 JH",
    "addr:housenumber":"47",
    "addr:postcode":"1391 jh",
    "addr:street":"Gein Z",
    "iso:country":"NL",
    "sg:address":"Gein Z 47",
    "sg:city":"Abcoude",
    "sg:orig_category":"Lasbedrijven",
    "sg:phone":"+31 6 53936583",
    "sg:postcode":"1391 JH",
    "sg:province":"North Holland",
    "wof:name":"Bch",
    "wof:placetype":"venue"
},
  "geometry": {"coordinates":[4.992898,52.277439],"type":"Point"}
}