{
  "type": "Feature",
  "properties": {
    "iso:country":"NL",
    "sg:address":"Lankerensewg 45",
    "sg:city":"Voorthuizen",
    "sg:orig_category":"Keukens",
    "sg:phone":"+31 342 478 200",
    "sg:postcode":"3781 NB",
    "sg:province":"Gelderland",
    "sg:website":"HTTP://www.terrabv.nl",
    "wof:name":"Terra Bv",
    "wof:placetype":"venue"
},
  "geometry": {"coordinates":[5.5735,52.184608],"type":"Point"}
}