{
  "type": "Feature",
  "properties": {
    "addr:full":"Meeden 35 Winsum Gn Groningen 9951 HX",
    "addr:housenumber":"35",
    "addr:postcode":"gn;9951 hx",
    "addr:street":"Meeden",
    "iso:country":"NL",
    "sg:address":"Meeden 35",
    "sg:city":"Winsum Gn",
    "sg:orig_category":"Volwassenenonderwijs",
    "sg:phone":"+31 595 441 701",
    "sg:postcode":"9951 HX",
    "sg:province":"Groningen",
    "wof:name":"De Klockslach",
    "wof:placetype":"venue"
},
  "geometry": {"coordinates":[6.529642,53.325802],"type":"Point"}
}