{
  "type": "Feature",
  "properties": {
    "addr:full":"Oudkerkhof 37 Utrecht Utrecht 3512 GJ",
    "addr:housenumber":"37",
    "addr:postcode":"3512 gj",
    "addr:street":"Oudkerkhof",
    "iso:country":"NL",
    "sg:address":"Oudkerkhof 37",
    "sg:city":"Utrecht",
    "sg:orig_category":"Kampeerartikelen",
    "sg:phone":"+31 30 231 6334",
    "sg:postcode":"3512 GJ",
    "sg:province":"Utrecht",
    "sg:website":"http://www.sportcampingshop.nl",
    "wof:name":"Sport Camping Shop",
    "wof:placetype":"venue"
},
  "geometry": {"coordinates":[5.1215901375,52.0917205811],"type":"Point"}
}