{
  "type": "Feature",
  "properties": {
    "addr:full":"P C Hooftstr 102 Amsterdam North Holland 1071 CC",
    "addr:housenumber":"102",
    "addr:postcode":"1071 cc",
    "addr:street":"P C Hooftstr",
    "iso:country":"NL",
    "sg:address":"P C Hooftstr 102",
    "sg:city":"Amsterdam",
    "sg:orig_category":"Modeontwerpen",
    "sg:phone":"+31 20 662 6336",
    "sg:postcode":"1071 CC",
    "sg:province":"North Holland",
    "wof:name":"Paul Schulten",
    "wof:placetype":"venue"
},
  "geometry": {"coordinates":[4.879759,52.360149],"type":"Point"}
}