{
  "type": "Feature",
  "properties": {
    "addr:full":"Koekoekln 68 Bussum Noord-Holland 1403 EH",
    "addr:housenumber":"68",
    "addr:postcode":"1403 eh",
    "addr:street":"Koekoekln",
    "iso:country":"NL",
    "sg:address":"Koekoekln 68",
    "sg:city":"Bussum",
    "sg:classifiers":[
        {
            "category":"Food & Beverages",
            "subcategory":"Bakery",
            "type":"Retail Goods"
        }
    ],
    "sg:phone":"+31 35 691 2085",
    "sg:postcode":"1403 EH",
    "sg:province":"Noord-Holland",
    "sg:tags":[
        "brood",
        "en",
        "banket"
    ],
    "wof:name":"Egmond, Van",
    "wof:placetype":"venue"
},
  "geometry": {"coordinates":[5.162605,52.276829],"type":"Point"}
}