{
  "type": "Feature",
  "properties": {
    "addr:full":"Andreasstr 10 Utrecht Utrecht 3511 VD",
    "addr:housenumber":"10",
    "addr:postcode":"3511 vd",
    "addr:street":"Andreasstr",
    "iso:country":"NL",
    "sg:address":"Andreasstr 10",
    "sg:city":"Utrecht",
    "sg:orig_category":"Bedrijfsopleidingen",
    "sg:phone":"+31 30 241 6614",
    "sg:postcode":"3511 VD",
    "sg:province":"Utrecht",
    "sg:website":"http://www.mientjefluyt.nl",
    "wof:name":"Fluyt, Mientje",
    "wof:placetype":"venue"
},
  "geometry": {"coordinates":[5.119764,52.085976],"type":"Point"}
}