{
  "type": "Feature",
  "properties": {
    "addr:full":"Lichtenhorststr 1 Didam Gelderland 6942 GS",
    "addr:housenumber":"1",
    "addr:postcode":"6942 gs",
    "addr:street":"Lichtenhorststr;Gelderland",
    "iso:country":"NL",
    "sg:address":"Lichtenhorststr 1",
    "sg:city":"Didam",
    "sg:orig_category":"Zonweringen",
    "sg:phone":"+31 316 224 132",
    "sg:postcode":"6942 GS",
    "sg:province":"Gelderland",
    "sg:website":"http://www.diemzon.nl",
    "wof:name":"Diemzon",
    "wof:placetype":"venue"
},
  "geometry": {"coordinates":[6.142492,51.932919],"type":"Point"}
}