{
  "type": "Feature",
  "properties": {
    "iso:country":"NL",
    "sg:address":"Lichtenhorststr 1",
    "sg:city":"Didam",
    "sg:orig_category":"Zonweringen",
    "sg:phone":"+31 316 224 132",
    "sg:postcode":"6942 GS",
    "sg:province":"Gelderland",
    "sg:website":"http://www.diemzon.nl",
    "wof:name":"Diemzon",
    "wof:placetype":"venue"
},
  "geometry": {"coordinates":[6.142492,51.932919],"type":"Point"}
}