{
  "type": "Feature",
  "properties": {
    "addr:full":"Lysterhaag 1 Houten Utrecht 3993 AS",
    "addr:housenumber":"1",
    "addr:postcode":"3993 as",
    "addr:street":"Lysterhaag",
    "iso:country":"NL",
    "sg:address":"Lysterhaag 1",
    "sg:city":"Houten",
    "sg:orig_category":"Kinderhuizen",
    "sg:phone":"+31 30 637 9435",
    "sg:postcode":"3993 AS",
    "sg:province":"Utrecht",
    "sg:website":"http://www.kipkeino.org",
    "wof:name":"Kip Keino Children'S Home",
    "wof:placetype":"venue"
},
  "geometry": {"coordinates":[5.167443,52.039734],"type":"Point"}
}