{
  "type": "Feature",
  "properties": {
    "addr:full":"C Anthoniszstr 32Hs Amsterdam North Holland 1071 VV",
    "addr:postcode":"1071 vv",
    "iso:country":"NL",
    "sg:address":"C Anthoniszstr 32Hs",
    "sg:city":"Amsterdam",
    "sg:classifiers":[
        {
            "category":"Shopping",
            "subcategory":"Gifts & Souvenirs",
            "type":"Retail Goods"
        }
    ],
    "sg:phone":"+31 20 671 7993",
    "sg:postcode":"1071 VV",
    "sg:province":"North Holland",
    "sg:tags":[
        "wens-",
        "en",
        "prentbriefkaarten"
    ],
    "wof:name":"Witcard",
    "wof:placetype":"venue"
},
  "geometry": {"coordinates":[4.8841509819,52.3534049988],"type":"Point"}
}