{
  "type": "Feature",
  "properties": {
    "addr:full":"Moreelsestraat 7 Amsterdam Noord-Holland 1071 BJ",
    "addr:housenumber":"7",
    "addr:postcode":"1071 bj",
    "addr:street":"Moreelsestraat",
    "iso:country":"NL",
    "sg:address":"Moreelsestraat 7",
    "sg:city":"Amsterdam",
    "sg:orig_category":"Binnenhuisarchitecten",
    "sg:phone":"+31 20 664 3203",
    "sg:postcode":"1071 BJ",
    "sg:province":"Noord-Holland",
    "wof:name":"Stadt En Zand",
    "wof:placetype":"venue"
},
  "geometry": {"coordinates":[4.881124,52.355507],"type":"Point"}
}