{
  "type": "Feature",
  "properties": {
    "addr:full":"Bethlehemkerkplein 28 Zwolle (Ov) Overijssel 8011 PH",
    "addr:housenumber":"28",
    "addr:postcode":"8011",
    "addr:street":"Bethlehemkerkplein",
    "iso:country":"NL",
    "sg:address":"Bethlehemkerkplein 28",
    "sg:city":"Zwolle (Ov)",
    "sg:classifiers":[
        {
            "category":"Bars & Pubs",
            "type":"Food & Drink"
        }
    ],
    "sg:phone":"+31 38 423 0685",
    "sg:postcode":"8011 PH",
    "sg:province":"Overijssel",
    "wof:name":"Deli Rest B.V.",
    "wof:placetype":"venue"
},
  "geometry": {"coordinates":[6.093987,52.511021],"type":"Point"}
}