{
  "type": "Feature",
  "properties": {
    "addr:full":"Bergse Dorpsstraat 33 Rotterdam Zuid-Holland 3054 GA",
    "addr:housenumber":"33",
    "addr:postcode":"3054 ga",
    "addr:street":"Bergse Dorpsstraat",
    "iso:country":"NL",
    "sg:address":"Bergse Dorpsstraat 33",
    "sg:city":"Rotterdam",
    "sg:orig_category":"Wasserettes And Stomerijen",
    "sg:phone":"+31 10 422 3228",
    "sg:postcode":"3054 GA",
    "sg:province":"Zuid-Holland",
    "wof:name":"Cleanette Renova Bv",
    "wof:placetype":"venue"
},
  "geometry": {"coordinates":[4.4945597649,51.9561538696],"type":"Point"}
}