{
  "type": "Feature",
  "properties": {
    "iso:country":"NL",
    "sg:address":"Junusstr 2",
    "sg:city":"Wageningen",
    "sg:orig_category":"Bloemen En Planten - Decoratie",
    "sg:phone":"+31 317 412 880",
    "sg:postcode":"6701 AX",
    "sg:province":"Gelderland",
    "wof:name":"Wilde Wingerd, De",
    "wof:placetype":"venue"
},
  "geometry": {"coordinates":[5.662647,51.965714],"type":"Point"}
}