{
  "type": "Feature",
  "properties": {
    "addr:full":"Siriusstraat 41 Tilburg Noord-Brabant 5015 BT",
    "addr:housenumber":"41",
    "addr:postcode":"5015 bt",
    "addr:street":"Siriusstraat",
    "iso:country":"NL",
    "sg:address":"Siriusstraat 41",
    "sg:city":"Tilburg",
    "sg:orig_category":"Airconditioning And Ventilatie",
    "sg:phone":"+31 13 583 8100",
    "sg:postcode":"5015 BT",
    "sg:province":"Noord-Brabant",
    "wof:name":"Sulzer Infra Nederland Bv",
    "wof:placetype":"venue"
},
  "geometry": {"coordinates":[5.111555,51.575829],"type":"Point"}
}