{
  "type": "Feature",
  "properties": {
    "addr:full":"Achterweg 21 Nieuwe Wetering South Holland 2376 AX",
    "addr:housenumber":"21",
    "addr:postcode":"2376 ax",
    "addr:street":"Achterweg",
    "iso:country":"NL",
    "sg:address":"Achterweg 21",
    "sg:city":"Nieuwe Wetering",
    "sg:orig_category":"Boomverzorging",
    "sg:phone":"+31 71 331 3136",
    "sg:postcode":"2376 AX",
    "sg:province":"South Holland",
    "wof:name":"Uit Den Boogaard, C W",
    "wof:placetype":"venue"
},
  "geometry": {"coordinates":[4.61756,52.208679],"type":"Point"}
}