{
  "type": "Feature",
  "properties": {
    "addr:full":"Koestr 6 Centr Org Zwolle NL.08 8011 NK",
    "addr:housenumber":"6;org",
    "addr:postcode":"8011 nk",
    "addr:street":"Koestr",
    "iso:country":"NL",
    "sg:address":"Koestr 6 Centr Org",
    "sg:city":"Zwolle",
    "sg:orig_category":"Verenigingen En Stichtingen",
    "sg:phone":"+31 38 421 6050",
    "sg:postcode":"8011 NK",
    "sg:province":"NL.08",
    "wof:name":"Stad En Welzijn, Sticht",
    "wof:placetype":"venue"
},
  "geometry": {"coordinates":[6.088738,52.512566],"type":"Point"}
}