{
  "type": "Feature",
  "properties": {
    "iso:country":"NL",
    "sg:address":"Binnenweg 170",
    "sg:city":"Heemstede",
    "sg:orig_category":"Woningbouwverenigingen",
    "sg:phone":"+31 23 528 8555",
    "sg:postcode":"2101 JR",
    "sg:province":"Noord-Holland",
    "wof:name":"Woningstichting Binnenhof",
    "wof:placetype":"venue"
},
  "geometry": {"coordinates":[4.6209487915,52.3550758362],"type":"Point"}
}