{
  "type": "Feature",
  "properties": {
    "addr:full":"Directeur Vd Muhlenln 59 Kerkrade Limburg 6463 VZ",
    "addr:housenumber":"59",
    "addr:postcode":"6463 vz",
    "addr:street":"Directeur",
    "iso:country":"NL",
    "sg:address":"Directeur Vd Muhlenln 59",
    "sg:city":"Kerkrade",
    "sg:orig_category":"Boekhouders",
    "sg:phone":"+31 45 545 5823",
    "sg:postcode":"6463 VZ",
    "sg:province":"Limburg",
    "wof:name":"Adviesburo Lenssen",
    "wof:placetype":"venue"
},
  "geometry": {"coordinates":[6.071546,50.873692],"type":"Point"}
}