{
  "type": "Feature",
  "properties": {
    "addr:full":"Stationstraat 43 Simpelveld Limburg 6369 VH",
    "addr:housenumber":"43",
    "addr:postcode":"6369 vh",
    "addr:street":"Stationstraat",
    "iso:country":"NL",
    "sg:address":"Stationstraat 43",
    "sg:city":"Simpelveld",
    "sg:orig_category":"Granen, Zaden And Diervoeders Gh",
    "sg:phone":"+31 45 544 1391",
    "sg:postcode":"6369 VH",
    "sg:province":"Limburg",
    "wof:name":"H. Corten Bv",
    "wof:placetype":"venue"
},
  "geometry": {"coordinates":[5.982154,50.83474],"type":"Point"}
}