{
  "type": "Feature",
  "properties": {
    "addr:full":"Leonard Springerlaan 23 Groningen Groningen 9727 KB",
    "addr:housenumber":"23",
    "addr:postcode":"9727 kb",
    "addr:street":"Leonard Springerlaan",
    "iso:country":"NL",
    "sg:address":"Leonard Springerlaan 23",
    "sg:city":"Groningen",
    "sg:orig_category":"Vakorganisaties",
    "sg:phone":"+31 50 363 1800",
    "sg:postcode":"9727 KB",
    "sg:province":"Groningen",
    "sg:website":"http://www.abvakabo.nl",
    "wof:name":"Abvakabo",
    "wof:placetype":"venue"
},
  "geometry": {"coordinates":[6.553387,53.202785],"type":"Point"}
}