{
  "type": "Feature",
  "properties": {
    "addr:full":"Kwinkenplein 12 Groningen Groningen 9712 GZ",
    "addr:housenumber":"12",
    "addr:postcode":"9712 gz",
    "addr:street":"Kwinkenplein",
    "iso:country":"NL",
    "sg:address":"Kwinkenplein 12",
    "sg:city":"Groningen",
    "sg:orig_category":"Architecten",
    "sg:phone":"+31 50 312 4445",
    "sg:postcode":"9712 GZ",
    "sg:province":"Groningen",
    "wof:name":"Olga Architecten Bv",
    "wof:placetype":"venue"
},
  "geometry": {"coordinates":[6.567225,53.219456],"type":"Point"}
}