{
  "type": "Feature",
  "properties": {
    "addr:full":"De Hazelaars 9 Boekel Noord-Brabant 5427 TZ",
    "addr:housenumber":"9",
    "addr:postcode":"5427 tz",
    "addr:street":"De Hazelaars",
    "iso:country":"NL",
    "sg:address":"De Hazelaars 9",
    "sg:city":"Boekel",
    "sg:orig_category":"Houtgroothandel",
    "sg:phone":"+31 6 55370693",
    "sg:postcode":"5427 TZ",
    "sg:province":"Noord-Brabant",
    "wof:name":"Hol-Rush Bv",
    "wof:placetype":"venue"
},
  "geometry": {"coordinates":[5.668692,51.599854],"type":"Point"}
}