{
  "type": "Feature",
  "properties": {
    "iso:country":"NL",
    "sg:address":"Loefzyde 17",
    "sg:city":"Amersfoort",
    "sg:orig_category":"Koeriersdiensten",
    "sg:phone":"+31 33 257 0214",
    "sg:postcode":"3823 TD",
    "sg:province":"Utrecht",
    "wof:name":"Snelle Vogel, De",
    "wof:placetype":"venue"
},
  "geometry": {"coordinates":[5.3968200684,52.1891593933],"type":"Point"}
}