{
  "type": "Feature",
  "properties": {
    "iso:country":"NL",
    "sg:address":"Boedapestln 79",
    "sg:city":"Ysselstein Ut",
    "sg:orig_category":"Verzekeringen - Verzekeringskantoren",
    "sg:phone":"+31 30 688 0463",
    "sg:postcode":"3404 CC",
    "sg:province":"Utrecht",
    "wof:name":"Grasso",
    "wof:placetype":"venue"
},
  "geometry": {"coordinates":[5.040538,52.010986],"type":"Point"}
}