{
  "type": "Feature",
  "properties": {
    "iso:country":"NL",
    "sg:address":"Hezelaar 23",
    "sg:city":"Gemert",
    "sg:orig_category":"Fotoreportages",
    "sg:phone":"+31 6 26880221",
    "sg:postcode":"5422 BX",
    "sg:province":"Noord-Brabant",
    "wof:name":"Verbruggen, Arjan",
    "wof:placetype":"venue"
},
  "geometry": {"coordinates":[5.700701,51.555805],"type":"Point"}
}