{
  "type": "Feature",
  "properties": {
    "addr:full":"Zesweg 3 Wijchen Gelderland 6601 HA",
    "addr:housenumber":"3",
    "addr:postcode":"6601 ha",
    "addr:street":"Zesweg;Gelderland",
    "iso:country":"NL",
    "sg:address":"Zesweg 3",
    "sg:city":"Wijchen",
    "sg:orig_category":"Verzekeringen",
    "sg:phone":"+31 24 645 0406",
    "sg:postcode":"6601 HA",
    "sg:province":"Gelderland",
    "wof:name":"G.M.C. Janzing Bv",
    "wof:placetype":"venue"
},
  "geometry": {"coordinates":[5.7308502197,51.8083953857],"type":"Point"}
}