{
  "type": "Feature",
  "properties": {
    "addr:full":"Toermalijn 3 Oss Virginia 5345 TJ",
    "addr:housenumber":"3",
    "addr:postcode":"5345 tj",
    "addr:street":"Toermalijn",
    "iso:country":"NL",
    "sg:address":"Toermalijn 3",
    "sg:city":"Oss",
    "sg:orig_category":"Kappers",
    "sg:phone":"+31 412 624 877",
    "sg:postcode":"5345 TJ",
    "sg:province":"Virginia",
    "wof:name":"Dameskapsalon Riet",
    "wof:placetype":"venue"
},
  "geometry": {"coordinates":[-77.2352142334,38.3125991821],"type":"Point"}
}