{
  "type": "Feature",
  "properties": {
    "addr:full":"Noordereinde 233 'S Graveland Noord-Holland 1243 JT",
    "addr:housenumber":"233 ' s",
    "addr:postcode":"1243 jt",
    "addr:street":"Noordereinde",
    "iso:country":"NL",
    "sg:address":"Noordereinde 233",
    "sg:city":"'S Graveland",
    "sg:orig_category":"Public Relationbureaus",
    "sg:phone":"+31 35 582 6969",
    "sg:postcode":"1243 JT",
    "sg:province":"Noord-Holland",
    "wof:name":"Mvsp Publiciteit Promotie Public Relation",
    "wof:placetype":"venue"
},
  "geometry": {"coordinates":[5.121021,52.247902],"type":"Point"}
}