{
  "type": "Feature",
  "properties": {
    "iso:country":"NL",
    "sg:address":"Hofhooistr 39",
    "sg:city":"Dreumel",
    "sg:orig_category":"Woninginrichting",
    "sg:phone":"+31 487 573 267",
    "sg:postcode":"6621 ZM",
    "sg:province":"Gelderland",
    "wof:name":"Sommeren, Van",
    "wof:placetype":"venue"
},
  "geometry": {"coordinates":[5.4379639626,51.8510017395],"type":"Point"}
}