{
  "type": "Feature",
  "properties": {
    "iso:country":"NL",
    "sg:address":"Rustenbergherstraat 11",
    "sg:city":"Hardenberg",
    "sg:orig_category":"Kappers",
    "sg:phone":"+31 523 261 962",
    "sg:postcode":"7771 CM",
    "sg:province":"Overijssel",
    "wof:name":"E Zwart",
    "wof:placetype":"venue"
},
  "geometry": {"coordinates":[6.6043839455,52.5736618042],"type":"Point"}
}