{
  "type": "Feature",
  "properties": {
    "addr:full":"Houtweg 113 Emmen Provincie Drenthe 7823 PE",
    "addr:housenumber":"113",
    "addr:postcode":"7823 pe",
    "addr:street":"Houtweg;Provincie Drenthe",
    "iso:country":"NL",
    "sg:address":"Houtweg 113",
    "sg:city":"Emmen",
    "sg:orig_category":"Babyartikelen Detailhandel",
    "sg:phone":"+31 591 626 072",
    "sg:postcode":"7823 PE",
    "sg:province":"Provincie Drenthe",
    "wof:name":"Benjamini",
    "wof:placetype":"venue"
},
  "geometry": {"coordinates":[6.939262,52.792534],"type":"Point"}
}