{
  "type": "Feature",
  "properties": {
    "addr:full":"Warmondpln 2 Hank North Dakota 4273 EC",
    "addr:housenumber":"2",
    "addr:postcode":"4273 ec",
    "addr:street":"Warmondpln",
    "iso:country":"NL",
    "sg:address":"Warmondpln 2",
    "sg:city":"Hank",
    "sg:orig_category":"Woninginrichting",
    "sg:phone":"+31 162 402 336",
    "sg:postcode":"4273 EC",
    "sg:province":"North Dakota",
    "wof:name":"Andr? Heijmans",
    "wof:placetype":"venue"
},
  "geometry": {"coordinates":[-103.8032608032,48.6026802063],"type":"Point"}
}