{
  "type": "Feature",
  "properties": {
    "addr:full":"V Schaffelaarstr 3 Barneveld Gelderland 3771 BP",
    "addr:housenumber":"3",
    "addr:postcode":"3771 bp",
    "addr:street":"Schaffelaarstr;Gelderland",
    "iso:country":"NL",
    "sg:address":"V Schaffelaarstr 3",
    "sg:city":"Barneveld",
    "sg:orig_category":"Bijouterie?n",
    "sg:phone":"+31 342 493 580",
    "sg:postcode":"3771 BP",
    "sg:province":"Gelderland",
    "wof:name":"Stras",
    "wof:placetype":"venue"
},
  "geometry": {"coordinates":[5.588843,52.141216],"type":"Point"}
}