{
  "type": "Feature",
  "properties": {
    "addr:full":"Loevestein 68 Dordrecht Zuid-Holland 3328 JL",
    "addr:housenumber":"68",
    "addr:postcode":"3328 jl",
    "addr:street":"Loevestein",
    "iso:country":"NL",
    "sg:address":"Loevestein 68",
    "sg:city":"Dordrecht",
    "sg:orig_category":"Koeriersdiensten",
    "sg:phone":"+31 78 651 2029",
    "sg:postcode":"3328 JL",
    "sg:province":"Zuid-Holland",
    "wof:name":"Mks Koeriersdiensten",
    "wof:placetype":"venue"
},
  "geometry": {"coordinates":[4.664997,51.774975],"type":"Point"}
}