{
  "type": "Feature",
  "properties": {
    "iso:country":"NL",
    "sg:address":"Diederikstraat 61",
    "sg:city":"Gemert",
    "sg:orig_category":"Overheidsdiensten",
    "sg:phone":"+31 492 365 022",
    "sg:postcode":"5421 EV",
    "sg:province":"Noord-Brabant",
    "wof:name":"Wijkcentrum 'T Bergje",
    "wof:placetype":"venue"
},
  "geometry": {"coordinates":[5.6816749573,51.5561256409],"type":"Point"}
}