{
  "type": "Feature",
  "properties": {
    "iso:country":"NL",
    "sg:address":"Molenstraat 37",
    "sg:city":"Winssen",
    "sg:orig_category":"Bloemen And Planten",
    "sg:phone":"+31 487 521 711",
    "sg:postcode":"6645 BS",
    "sg:province":"Gelderland",
    "wof:name":"T Bakhuysje",
    "wof:placetype":"venue"
},
  "geometry": {"coordinates":[5.698955,51.882214],"type":"Point"}
}