{
  "type": "Feature",
  "properties": {
    "iso:country":"NL",
    "sg:address":"Westeinde 211",
    "sg:city":"Vriezenveen",
    "sg:orig_category":"Zuivelproducten And Spijsoli?n Gh",
    "sg:phone":"+31 546 566 388",
    "sg:postcode":"7671 EP",
    "sg:province":"Overijssel",
    "wof:name":"J. Wassink",
    "wof:placetype":"venue"
},
  "geometry": {"coordinates":[6.616656,52.409039],"type":"Point"}
}