{
  "type": "Feature",
  "properties": {
    "addr:full":"Lieve Vrouwegracht 14 Montfoort Utrecht 3417 HN",
    "addr:housenumber":"14",
    "addr:postcode":"3417 hn",
    "addr:street":"Lieve Vrouwegracht",
    "iso:country":"NL",
    "sg:address":"Lieve Vrouwegracht 14",
    "sg:city":"Montfoort",
    "sg:orig_category":"Fotostudio'S And Fotografen",
    "sg:phone":"+31 348 474 158",
    "sg:postcode":"3417 HN",
    "sg:province":"Utrecht",
    "wof:name":"Marcel Kraan Fotografie",
    "wof:placetype":"venue"
},
  "geometry": {"coordinates":[4.947092,52.043842],"type":"Point"}
}