{
  "type": "Feature",
  "properties": {
    "addr:full":"Kerkln 11 Egmond Binnen Noord-Holland 1935 EV",
    "addr:housenumber":"11",
    "addr:street":"Kerkln;Egmond",
    "iso:country":"NL",
    "sg:address":"Kerkln 11",
    "sg:city":"Egmond Binnen",
    "sg:orig_category":"Schilders",
    "sg:phone":"+31 72 506 4695",
    "sg:postcode":"1935 EV",
    "sg:province":"Noord-Holland",
    "wof:name":"Beukers & Zn",
    "wof:placetype":"venue"
},
  "geometry": {"coordinates":[4.655705,52.596455],"type":"Point"}
}