{
  "type": "Feature",
  "properties": {
    "iso:country":"NL",
    "sg:address":"Distelstraat 25",
    "sg:city":"Hellevoetsluis",
    "sg:orig_category":"Diverse Grafische Activiteiten",
    "sg:phone":"+31 181 321 283",
    "sg:postcode":"3222 XB",
    "sg:province":"Zuid-Holland",
    "wof:name":"G.H. En L. Grafische Vormgeving",
    "wof:placetype":"venue"
},
  "geometry": {"coordinates":[4.132032,51.838787],"type":"Point"}
}