{
  "type": "Feature",
  "properties": {
    "addr:full":"De Jagerwg 202 Dordrecht South Holland 3328 HG",
    "addr:housenumber":"202",
    "addr:postcode":"3328 hg",
    "iso:country":"NL",
    "sg:address":"De Jagerwg 202",
    "sg:city":"Dordrecht",
    "sg:orig_category":"Kunstgebitten",
    "sg:phone":"+31 78 651 1546",
    "sg:postcode":"3328 HG",
    "sg:province":"South Holland",
    "wof:name":"Hemmes Tandtechniek",
    "wof:placetype":"venue"
},
  "geometry": {"coordinates":[4.683347,51.778873],"type":"Point"}
}