{
  "type": "Feature",
  "properties": {
    "addr:full":"P Florisstr 3 Hoorn Nh Noord-Holland 1623 RS",
    "addr:housenumber":"3",
    "addr:postcode":"1623 rs",
    "addr:street":"P Florisstr",
    "iso:country":"NL",
    "sg:address":"P Florisstr 3",
    "sg:city":"Hoorn Nh",
    "sg:orig_category":"Meubelmakerijen",
    "sg:phone":"+31 229 275 321",
    "sg:postcode":"1623 RS",
    "sg:province":"Noord-Holland",
    "wof:name":"Mc Meubel",
    "wof:placetype":"venue"
},
  "geometry": {"coordinates":[5.069271,52.643124],"type":"Point"}
}