{
  "type": "Feature",
  "properties": {
    "addr:full":"Walenkampstr 34 Amsterdam Noord-Holland 1019 EB",
    "addr:housenumber":"34",
    "addr:postcode":"1019 eb",
    "addr:street":"Walenkampstr",
    "iso:country":"NL",
    "sg:address":"Walenkampstr 34",
    "sg:city":"Amsterdam",
    "sg:orig_category":"Schilders",
    "sg:phone":"+31 6 55305935",
    "sg:postcode":"1019 EB",
    "sg:province":"Noord-Holland",
    "wof:name":"Kruis & Sabajo",
    "wof:placetype":"venue"
},
  "geometry": {"coordinates":[4.941468,52.36784],"type":"Point"}
}