{
  "type": "Feature",
  "properties": {
    "addr:full":"Marconistr 6A Goes Ohio 4461 HH",
    "addr:housenumber":"6a",
    "addr:postcode":"4461 hh",
    "addr:street":"Marconistr",
    "iso:country":"NL",
    "sg:address":"Marconistr 6A",
    "sg:city":"Goes",
    "sg:orig_category":"Woninginrichting",
    "sg:phone":"+31 113 271 550",
    "sg:postcode":"4461 HH",
    "sg:province":"Ohio",
    "wof:name":"Leen Bakker",
    "wof:placetype":"venue"
},
  "geometry": {"coordinates":[-83.9141693115,39.7688331604],"type":"Point"}
}