{
  "type": "Feature",
  "properties": {
    "addr:full":"Dijklaan 31 Breda North Brabant 4814 CA",
    "addr:housenumber":"31",
    "addr:postcode":"4814 ca",
    "addr:street":"Dijklaan",
    "iso:country":"NL",
    "sg:address":"Dijklaan 31",
    "sg:city":"Breda",
    "sg:orig_category":"Kappers",
    "sg:phone":"+31 76 521 5096",
    "sg:postcode":"4814 CA",
    "sg:province":"North Brabant",
    "wof:name":"Frans Coiffures",
    "wof:placetype":"venue"
},
  "geometry": {"coordinates":[4.7601308823,51.5854415894],"type":"Point"}
}