{
  "type": "Feature",
  "properties": {
    "addr:full":"Gageldk 1 Maarssen Utrecht 3602 AG",
    "addr:housenumber":"1",
    "addr:postcode":"3602",
    "addr:street":"Gageldk",
    "iso:country":"NL",
    "sg:address":"Gageldk 1",
    "sg:city":"Maarssen",
    "sg:orig_category":"Verhuizingen",
    "sg:phone":"+31 30 262 4654",
    "sg:postcode":"3602 AG",
    "sg:province":"Utrecht",
    "wof:name":"Niekerk & Zonen, Fa Joh",
    "wof:placetype":"venue"
},
  "geometry": {"coordinates":[5.075138,52.140896],"type":"Point"}
}