{
  "type": "Feature",
  "properties": {
    "iso:country":"NL",
    "sg:address":"Rechtestraat 27",
    "sg:city":"Eindhoven",
    "sg:orig_category":"Herenmodezaken",
    "sg:phone":"+31 40 293 9230",
    "sg:postcode":"5611 GM",
    "sg:province":"Noord-Brabant",
    "wof:name":"Setpoint Bv",
    "wof:placetype":"venue"
},
  "geometry": {"coordinates":[5.478267,51.438545],"type":"Point"}
}