{
  "type": "Feature",
  "properties": {
    "addr:full":"Hoefbladstraat 22 Alphen A/D Rijn South Holland 2403 VB",
    "addr:housenumber":"22",
    "addr:postcode":"2403 vb",
    "addr:street":"Hoefbladstraat",
    "iso:country":"NL",
    "sg:address":"Hoefbladstraat 22",
    "sg:city":"Alphen A/D Rijn",
    "sg:orig_category":"Kantoorartikelen",
    "sg:phone":"+31 172 438 589",
    "sg:postcode":"2403 VB",
    "sg:province":"South Holland",
    "wof:name":"Voskuilen Telecom",
    "wof:placetype":"venue"
},
  "geometry": {"coordinates":[4.6866550446,52.1466217041],"type":"Point"}
}