{
  "type": "Feature",
  "properties": {
    "addr:full":"Wagenmaker 7 Stadskanaal Groningen 9502 ES",
    "addr:housenumber":"7",
    "addr:postcode":"9502 es",
    "addr:street":"Wagenmaker",
    "iso:country":"NL",
    "sg:address":"Wagenmaker 7",
    "sg:city":"Stadskanaal",
    "sg:orig_category":"Bouwmaterialen Gh",
    "sg:phone":"+31 599 614 040",
    "sg:postcode":"9502 ES",
    "sg:province":"Groningen",
    "wof:name":"Sanilux Bv",
    "wof:placetype":"venue"
},
  "geometry": {"coordinates":[6.982829,52.976456],"type":"Point"}
}