{
  "type": "Feature",
  "properties": {
    "addr:full":"Drie Pistolengang 4 Zwolle Overijssel 8011 XH",
    "addr:housenumber":"4",
    "addr:postcode":"8011 xh",
    "addr:street":"Drie Pistolengang",
    "iso:country":"NL",
    "sg:address":"Drie Pistolengang 4",
    "sg:city":"Zwolle",
    "sg:orig_category":"Discountwinkels",
    "sg:phone":"+31 38 421 9941",
    "sg:postcode":"8011 XH",
    "sg:province":"Overijssel",
    "wof:name":"Jan Sikkes Lappenland Bv",
    "wof:placetype":"venue"
},
  "geometry": {"coordinates":[6.088738,52.512566],"type":"Point"}
}