{
  "type": "Feature",
  "properties": {
    "iso:country":"NL",
    "sg:address":"Mandenmakerstr 130",
    "sg:city":"Hoogvliet Rt",
    "sg:orig_category":"Onderhoudswerken",
    "sg:phone":"+31 10 465 0520",
    "sg:postcode":"3194 DG",
    "sg:province":"Zuid-Holland",
    "wof:name":"Technocare Bv",
    "wof:placetype":"venue"
},
  "geometry": {"coordinates":[4.374293,51.867733],"type":"Point"}
}