{
  "type": "Feature",
  "properties": {
    "addr:full":"Dinxperloln 12 Tilburg Noord-Brabant 5043 GW",
    "addr:housenumber":"12",
    "addr:postcode":"5043 gw",
    "addr:street":"Dinxperloln",
    "iso:country":"NL",
    "sg:address":"Dinxperloln 12",
    "sg:city":"Tilburg",
    "sg:orig_category":"Adviesbureaus Bedrijfsorganisatie",
    "sg:phone":"+31 13 571 2527",
    "sg:postcode":"5043 GW",
    "sg:province":"Noord-Brabant",
    "wof:name":"Vromans",
    "wof:placetype":"venue"
},
  "geometry": {"coordinates":[5.013577,51.5788],"type":"Point"}
}