{
  "type": "Feature",
  "properties": {
    "addr:full":"Bergvink 2 Veenendaal Utrecht 3906 AS",
    "addr:housenumber":"2",
    "addr:postcode":"3906 as",
    "addr:street":"Bergvink",
    "iso:country":"NL",
    "sg:address":"Bergvink 2",
    "sg:city":"Veenendaal",
    "sg:orig_category":"Administratie- En Boekhoudkantoren",
    "sg:phone":"+31 6 48400128",
    "sg:postcode":"3906 AS",
    "sg:province":"Utrecht",
    "wof:name":"Cva",
    "wof:placetype":"venue"
},
  "geometry": {"coordinates":[5.531509,52.031612],"type":"Point"}
}