{
  "type": "Feature",
  "properties": {
    "addr:full":"Doortocht 3-B Bodegraven Zuid-Holland 2411 DS",
    "addr:housenumber":"3-b",
    "addr:postcode":"2411 ds",
    "addr:street":"Doortocht",
    "iso:country":"NL",
    "sg:address":"Doortocht 3-B",
    "sg:city":"Bodegraven",
    "sg:orig_category":"Visspeciaalzaken",
    "sg:phone":"+31 172 616 767",
    "sg:postcode":"2411 DS",
    "sg:province":"Zuid-Holland",
    "wof:name":"Vishandel Vd Toorn'S",
    "wof:placetype":"venue"
},
  "geometry": {"coordinates":[4.741041,52.084282],"type":"Point"}
}