{
  "type": "Feature",
  "properties": {
    "iso:country":"NL",
    "sg:address":"Nude 36-38",
    "sg:city":"Rhenen",
    "sg:orig_category":"Meubelzaken, Woning- And Keukeninrichting",
    "sg:phone":"+31 317 418 182",
    "sg:postcode":"3911 VK",
    "sg:province":"Utrecht",
    "wof:name":"Perfect Waterbedden",
    "wof:placetype":"venue"
},
  "geometry": {"coordinates":[5.6182961464,51.9560623169],"type":"Point"}
}