{
  "type": "Feature",
  "properties": {
    "addr:full":"Laurens Reaalstraat 23 Utrecht Utrecht 3531 GM",
    "addr:housenumber":"23",
    "addr:postcode":"3531 gm",
    "addr:street":"Laurens Reaalstraat",
    "iso:country":"NL",
    "sg:address":"Laurens Reaalstraat 23",
    "sg:city":"Utrecht",
    "sg:orig_category":"Fitnesscentra",
    "sg:phone":"+31 30 293 5407",
    "sg:postcode":"3531 GM",
    "sg:province":"Utrecht",
    "wof:name":"Fitness-Studio New Style",
    "wof:placetype":"venue"
},
  "geometry": {"coordinates":[5.095953,52.089684],"type":"Point"}
}