{
  "type": "Feature",
  "properties": {
    "addr:full":"Rendementswg 20C Mydrecht Utrecht 3641 SL",
    "addr:housenumber":"20c mydrecht",
    "addr:postcode":"3641 sl",
    "addr:street":"Rendementswg",
    "iso:country":"NL",
    "sg:address":"Rendementswg 20C",
    "sg:city":"Mydrecht",
    "sg:orig_category":"Sanitaire Artikelen",
    "sg:phone":"+31 297 250 525",
    "sg:postcode":"3641 SL",
    "sg:province":"Utrecht",
    "sg:website":"http://www.josvanzijl.nl",
    "wof:name":"Jos Van Zijl",
    "wof:placetype":"venue"
},
  "geometry": {"coordinates":[4.885355,52.208897],"type":"Point"}
}