{
  "type": "Feature",
  "properties": {
    "addr:full":"Handelskade 16 Noord-Scharwoude North Holland 1723 MZ",
    "addr:housenumber":"16",
    "addr:postcode":"1723 mz",
    "addr:street":"Handelskade",
    "iso:country":"NL",
    "sg:address":"Handelskade 16",
    "sg:city":"Noord-Scharwoude",
    "sg:orig_category":"Fruit And Groenten Gh",
    "sg:phone":"+31 226 312 413",
    "sg:postcode":"1723 MZ",
    "sg:province":"North Holland",
    "wof:name":"G. Kooy Export Bv",
    "wof:placetype":"venue"
},
  "geometry": {"coordinates":[4.814439,52.707466],"type":"Point"}
}