{
  "type": "Feature",
  "properties": {
    "addr:full":"Runstraat 5 Amsterdam Noord-Holland 1016 GJ",
    "addr:housenumber":"5",
    "addr:postcode":"1016 gj",
    "addr:street":"Runstraat",
    "iso:country":"NL",
    "sg:address":"Runstraat 5",
    "sg:city":"Amsterdam",
    "sg:orig_category":"Drogisterijen",
    "sg:phone":"+31 20 623 3443",
    "sg:postcode":"1016 GJ",
    "sg:province":"Noord-Holland",
    "wof:name":"Firma De Witte Tandenwinkel Amsterdam",
    "wof:placetype":"venue"
},
  "geometry": {"coordinates":[4.883957,52.368755],"type":"Point"}
}