{
  "type": "Feature",
  "properties": {
    "addr:full":"Stationsstr 16 Zutphen Gelderland 7201 MD",
    "addr:housenumber":"16",
    "addr:postcode":"7201",
    "addr:street":"Stationsstr;Gelderland",
    "iso:country":"NL",
    "sg:address":"Stationsstr 16",
    "sg:city":"Zutphen",
    "sg:orig_category":"Verzekeringen - Verzekeringskantoren",
    "sg:phone":"+31 575 582 424",
    "sg:postcode":"7201 MD",
    "sg:province":"Gelderland",
    "wof:name":"Univ\u00e9",
    "wof:placetype":"venue"
},
  "geometry": {"coordinates":[6.1915249825,52.1402015686],"type":"Point"}
}