{
  "type": "Feature",
  "properties": {
    "addr:full":"Kl Garnwerd 4 Winsum Gn Groningen 9951 TR",
    "addr:housenumber":"4",
    "addr:postcode":"gn;9951 tr",
    "addr:street":"Kl",
    "iso:country":"NL",
    "sg:address":"Kl Garnwerd 4",
    "sg:city":"Winsum Gn",
    "sg:classifiers":[
        {
            "category":"Sports & Exercise",
            "subcategory":"Stables",
            "type":"Entertainment"
        }
    ],
    "sg:phone":"+31 595 441 299",
    "sg:postcode":"9951 TR",
    "sg:province":"Groningen",
    "sg:tags":[
        "maneges"
    ],
    "wof:name":"Homan Manege, K J",
    "wof:placetype":"venue"
},
  "geometry": {"coordinates":[6.508998,53.32077],"type":"Point"}
}