{
  "type": "Feature",
  "properties": {
    "addr:full":"G Trestorffstr 20 Amsterdam North Holland 1063 VM",
    "addr:housenumber":"20",
    "addr:postcode":"1063 vm",
    "iso:country":"NL",
    "sg:address":"G Trestorffstr 20",
    "sg:city":"Amsterdam",
    "sg:orig_category":"Glazenwasserijen",
    "sg:phone":"+31 6 13153611",
    "sg:postcode":"1063 VM",
    "sg:province":"North Holland",
    "wof:name":"Holtbeck",
    "wof:placetype":"venue"
},
  "geometry": {"coordinates":[4.829455,52.381401],"type":"Point"}
}