{
  "type": "Feature",
  "properties": {
    "addr:full":"Egelantiersstraat 143 Amsterdam Noord-Holland 1015 RA",
    "addr:housenumber":"143",
    "addr:postcode":"1015 ra",
    "addr:street":"Egelantiersstraat",
    "iso:country":"NL",
    "sg:address":"Egelantiersstraat 143",
    "sg:city":"Amsterdam",
    "sg:orig_category":"Fotografie Reclame En Mode",
    "sg:phone":"+31 20 530 6000",
    "sg:postcode":"1015 RA",
    "sg:province":"Noord-Holland",
    "sg:website":"http://www.unit.nl",
    "wof:name":"Unit Cma",
    "wof:placetype":"venue"
},
  "geometry": {"coordinates":[4.879253,52.375862],"type":"Point"}
}