{
  "type": "Feature",
  "properties": {
    "addr:full":"Zuideinde 9 Oostzaan North Holland 1511 GA",
    "addr:housenumber":"9",
    "addr:postcode":"1511 ga",
    "addr:street":"Zuideinde",
    "iso:country":"NL",
    "sg:address":"Zuideinde 9",
    "sg:city":"Oostzaan",
    "sg:orig_category":"Loodgieterswerk, Verwarming And Sanitaire Installaties",
    "sg:phone":"+31 75 684 5643",
    "sg:postcode":"1511 GA",
    "sg:province":"North Holland",
    "wof:name":"Klompmaker Vof",
    "wof:placetype":"venue"
},
  "geometry": {"coordinates":[4.875853,52.440037],"type":"Point"}
}