{
  "type": "Feature",
  "properties": {
    "addr:full":"Noordwg 3 Staphorst NL.08 7951 RB",
    "addr:housenumber":"3;nl.08",
    "addr:postcode":"7951 rb",
    "addr:street":"Noordwg",
    "iso:country":"NL",
    "sg:address":"Noordwg 3",
    "sg:city":"Staphorst",
    "sg:orig_category":"Puien",
    "sg:phone":"+31 522 238 888",
    "sg:postcode":"7951 RB",
    "sg:province":"NL.08",
    "wof:name":"Gevelbeheer Nederland Bv",
    "wof:placetype":"venue"
},
  "geometry": {"coordinates":[6.19648,52.675644],"type":"Point"}
}