{
  "type": "Feature",
  "properties": {
    "iso:country":"NL",
    "sg:address":"Driegaardsestr 21",
    "sg:city":"Huissen",
    "sg:orig_category":"Verzekeringen - Verzekeringskantoren",
    "sg:phone":"+31 26 325 9147",
    "sg:postcode":"6851 GN",
    "sg:province":"Gelderland",
    "wof:name":"Charbon & Partners",
    "wof:placetype":"venue"
},
  "geometry": {"coordinates":[5.925249,51.931129],"type":"Point"}
}