{
  "type": "Feature",
  "properties": {
    "addr:full":"Westerstraat 60 Enkhuizen Noord-Holland 1601 AL",
    "addr:housenumber":"60;1601",
    "addr:postcode":"al",
    "addr:street":"Westerstraat",
    "iso:country":"NL",
    "sg:address":"Westerstraat 60",
    "sg:city":"Enkhuizen",
    "sg:orig_category":"Metaalwerken",
    "sg:phone":"+31 228 312 831",
    "sg:postcode":"1601 AL",
    "sg:province":"Noord-Holland",
    "wof:name":"D. Van Kalsbeek",
    "wof:placetype":"venue"
},
  "geometry": {"coordinates":[5.291519,52.704258],"type":"Point"}
}