{
  "type": "Feature",
  "properties": {
    "addr:full":"Heipoldersstr 2A Heeze Noord-Brabant 5591 KB",
    "addr:housenumber":"2a",
    "addr:postcode":"5591 kb",
    "addr:street":"Heipoldersstr",
    "iso:country":"NL",
    "sg:address":"Heipoldersstr 2A",
    "sg:city":"Heeze",
    "sg:classifiers":[
        {
            "category":"Government",
            "subcategory":"Department Of Motor Vehicles",
            "type":"Public Place"
        }
    ],
    "sg:phone":"+31 40 226 2331",
    "sg:postcode":"5591 KB",
    "sg:province":"Noord-Brabant",
    "sg:tags":[
        "rijscholen",
        "scooter",
        "en",
        "-"
    ],
    "sg:website":"http://www.rijschoolsmulders.nl",
    "wof:name":"Smulders Auto- En Motorrijschool",
    "wof:placetype":"venue"
},
  "geometry": {"coordinates":[5.588013,51.371761],"type":"Point"}
}