{
  "type": "Feature",
  "properties": {
    "iso:country":"NL",
    "sg:address":"Dorpsstraat 106",
    "sg:city":"Warmond",
    "sg:orig_category":"Loodgieterswerk, Verwarming And Sanitaire Installaties",
    "sg:phone":"+31 71 301 0214",
    "sg:postcode":"2361 BN",
    "sg:province":"Zuid-Holland",
    "wof:name":"Mark De Nie Installatietechniek",
    "wof:placetype":"venue"
},
  "geometry": {"coordinates":[4.506471,52.198448],"type":"Point"}
}