{
  "type": "Feature",
  "properties": {
    "addr:full":"Parallelwg 2 Heerlen Limburg 6411 ND",
    "addr:housenumber":"2",
    "addr:postcode":"6411 nd",
    "addr:street":"Parallelwg",
    "iso:country":"NL",
    "sg:address":"Parallelwg 2",
    "sg:city":"Heerlen",
    "sg:orig_category":"Adviesbureaus Bouwkunde",
    "sg:phone":"+31 45 574 2255",
    "sg:postcode":"6411 ND",
    "sg:province":"Limburg",
    "wof:name":"L & D Project Management",
    "wof:placetype":"venue"
},
  "geometry": {"coordinates":[5.973667,50.890656],"type":"Point"}
}