{
  "type": "Feature",
  "properties": {
    "addr:full":"Oldenzaalsestr 762 Enschede Overijssel 7524 AH",
    "addr:housenumber":"762",
    "addr:postcode":"7524 ah",
    "iso:country":"NL",
    "sg:address":"Oldenzaalsestr 762",
    "sg:city":"Enschede",
    "sg:orig_category":"Adviesbureaus Bedrijfsorganisatie",
    "sg:phone":"+31 53 433 0087",
    "sg:postcode":"7524 AH",
    "sg:province":"Overijssel",
    "wof:name":"Gimec Bv",
    "wof:placetype":"venue"
},
  "geometry": {"coordinates":[6.91675,52.245319],"type":"Point"}
}