{
  "type": "Feature",
  "properties": {
    "iso:country":"NL",
    "sg:address":"Duinzicht 2",
    "sg:city":"Valkenburg Zh",
    "sg:orig_category":"Adviesbureaus Bedrijfsorganisatie",
    "sg:phone":"+31 71 401 8324",
    "sg:postcode":"2235 BV",
    "sg:province":"Zuid-Holland",
    "wof:name":"Fifty - Fifty",
    "wof:placetype":"venue"
},
  "geometry": {"coordinates":[4.426368,52.180836],"type":"Point"}
}