{
  "type": "Feature",
  "properties": {
    "addr:full":"Wethouder Kreftlaan 16 Zevenhuizen Zh Zuid-Holland 2761 TZ",
    "addr:housenumber":"16",
    "addr:postcode":"2761 tz",
    "addr:street":"Wethouder Kreftlaan",
    "iso:country":"NL",
    "sg:address":"Wethouder Kreftlaan 16",
    "sg:city":"Zevenhuizen Zh",
    "sg:orig_category":"Verhuur Kantoorapparatuur",
    "sg:phone":"+31 180 632 462",
    "sg:postcode":"2761 TZ",
    "sg:province":"Zuid-Holland",
    "wof:name":"Bijsterbosch",
    "wof:placetype":"venue"
},
  "geometry": {"coordinates":[4.582125,52.008865],"type":"Point"}
}