{
  "type": "Feature",
  "properties": {
    "addr:full":"Blommendaal 62 Meerkerk Zuid-Holland 4231 DD",
    "addr:housenumber":"62",
    "addr:postcode":"4231 dd",
    "addr:street":"Blommendaal",
    "iso:country":"NL",
    "sg:address":"Blommendaal 62",
    "sg:city":"Meerkerk",
    "sg:orig_category":"Goederenvervoer Over De Weg",
    "sg:phone":"+31 183 353 095",
    "sg:postcode":"4231 DD",
    "sg:province":"Zuid-Holland",
    "wof:name":"G.W. Tuyl",
    "wof:placetype":"venue"
},
  "geometry": {"coordinates":[4.993543,51.917404],"type":"Point"}
}