{
  "type": "Feature",
  "properties": {
    "addr:full":"Rijsdk 51 Krimpen Aan Den Ijssel Zuid-Holland 2931 AW",
    "addr:housenumber":"51",
    "addr:postcode":"2931 aw",
    "addr:street":"Rijsdk",
    "iso:country":"NL",
    "sg:address":"Rijsdk 51",
    "sg:city":"Krimpen Aan Den Ijssel",
    "sg:orig_category":"Huisdierenfokkers",
    "sg:phone":"+31 180 551 310",
    "sg:postcode":"2931 AW",
    "sg:province":"Zuid-Holland",
    "wof:name":"Nederlandse Cairn Terrier Club",
    "wof:placetype":"venue"
},
  "geometry": {"coordinates":[4.630337,51.892891],"type":"Point"}
}