{
  "type": "Feature",
  "properties": {
    "iso:country":"NL",
    "sg:address":"Serpeling 6",
    "sg:city":"Avenhorn",
    "sg:orig_category":"Jachten - Schilderwerken En Onderhoud",
    "sg:phone":"+31 229 542 591",
    "sg:postcode":"1633 DM",
    "sg:province":"North Holland",
    "wof:name":"Nautic Hoorn",
    "wof:placetype":"venue"
},
  "geometry": {"coordinates":[4.950452,52.621243],"type":"Point"}
}