{
  "type": "Feature",
  "properties": {
    "addr:full":"Kruyderlaan 35 Nieuwegein Utrecht 3431 BM",
    "addr:housenumber":"35",
    "addr:postcode":"3431 bm",
    "addr:street":"Kruyderlaan",
    "iso:country":"NL",
    "sg:address":"Kruyderlaan 35",
    "sg:city":"Nieuwegein",
    "sg:orig_category":"Film-, Tv- And Videoproductie",
    "sg:phone":"+31 30 604 4422",
    "sg:postcode":"3431 BM",
    "sg:province":"Utrecht",
    "wof:name":"Fofic Bv",
    "wof:placetype":"venue"
},
  "geometry": {"coordinates":[5.086486,52.029652],"type":"Point"}
}