{
  "type": "Feature",
  "properties": {
    "addr:full":"Dichterhof 34 Almere Flevoland 1315 LN",
    "addr:housenumber":"34",
    "addr:postcode":"1315 ln",
    "addr:street":"Dichterhof;Flevoland",
    "iso:country":"NL",
    "sg:address":"Dichterhof 34",
    "sg:city":"Almere",
    "sg:orig_category":"Opticiens",
    "sg:phone":"+31 6 52310447",
    "sg:postcode":"1315 LN",
    "sg:province":"Flevoland",
    "sg:website":"http://www.schotenboog.nl",
    "wof:name":"Schotenboog Lv",
    "wof:placetype":"venue"
},
  "geometry": {"coordinates":[5.2197198868,52.3728370667],"type":"Point"}
}