{
  "type": "Feature",
  "properties": {
    "iso:country":"NL",
    "sg:address":"Kerkweg 26",
    "sg:city":"Vaassen",
    "sg:orig_category":"Boekhandels",
    "sg:phone":"+31 578 560 010",
    "sg:postcode":"8171 VR",
    "sg:province":"Gelderland",
    "wof:name":"Fonteyn & Andersen",
    "wof:placetype":"venue"
},
  "geometry": {"coordinates":[5.963826,52.28833],"type":"Point"}
}