{
  "type": "Feature",
  "properties": {
    "iso:country":"NL",
    "sg:address":"Mina Kruseman-Erf 272",
    "sg:city":"Dordrecht",
    "sg:orig_category":"Houten Verpakkingen Fab",
    "sg:phone":"+31 78 621 1052",
    "sg:postcode":"3315 GK",
    "sg:province":"Zuid-Holland",
    "wof:name":"S.A. Bolger Trading",
    "wof:placetype":"venue"
},
  "geometry": {"coordinates":[4.733482,51.799408],"type":"Point"}
}