{
  "type": "Feature",
  "properties": {
    "addr:full":"Middenvliet 16 Den Helder Noord-Holland 1786 PM",
    "addr:housenumber":"16",
    "addr:postcode":"1786 pm",
    "addr:street":"Middenvliet",
    "iso:country":"NL",
    "sg:address":"Middenvliet 16",
    "sg:city":"Den Helder",
    "sg:orig_category":"Bloembollen - Groothandel",
    "sg:phone":"+31 223 637 357",
    "sg:postcode":"1786 PM",
    "sg:province":"Noord-Holland",
    "wof:name":"Honders-Duineveld, Fa",
    "wof:placetype":"venue"
},
  "geometry": {"coordinates":[4.768332,52.913338],"type":"Point"}
}