{
  "type": "Feature",
  "properties": {
    "addr:full":"Kerkstr 2 Oldenzaal Overijssel 7571 EE",
    "addr:housenumber":"2",
    "addr:postcode":"7571 ee",
    "addr:street":"Kerkstr",
    "iso:country":"NL",
    "sg:address":"Kerkstr 2",
    "sg:city":"Oldenzaal",
    "sg:orig_category":"Hypotheken",
    "sg:phone":"+31 541 570 710",
    "sg:postcode":"7571 EE",
    "sg:province":"Overijssel",
    "wof:name":"Hakenberg, De",
    "wof:placetype":"venue"
},
  "geometry": {"coordinates":[6.92904,52.313271],"type":"Point"}
}