{
  "type": "Feature",
  "properties": {
    "addr:full":"Dorpsstraat 117 Rosmalen Noord-Brabant 5241 EB",
    "addr:housenumber":"117",
    "addr:postcode":"5241 eb",
    "addr:street":"Dorpsstraat",
    "iso:country":"NL",
    "sg:address":"Dorpsstraat 117",
    "sg:city":"Rosmalen",
    "sg:orig_category":"Meubelzaken, Woning- And Keukeninrichting",
    "sg:phone":"+31 73 521 2317",
    "sg:postcode":"5241 EB",
    "sg:province":"Noord-Brabant",
    "wof:name":"De Veer Woon- En Slaapcomfort",
    "wof:placetype":"venue"
},
  "geometry": {"coordinates":[5.359461,51.71386],"type":"Point"}
}