{
  "type": "Feature",
  "properties": {
    "addr:full":"Paleiskd 100 Den Helder North Holland 1781 AR",
    "addr:housenumber":"100",
    "addr:postcode":"1781",
    "iso:country":"NL",
    "sg:address":"Paleiskd 100",
    "sg:city":"Den Helder",
    "sg:orig_category":"On- Offshore",
    "sg:phone":"+31 223 625 307",
    "sg:postcode":"1781 AR",
    "sg:province":"North Holland",
    "wof:name":"Geocal Sarl",
    "wof:placetype":"venue"
},
  "geometry": {"coordinates":[4.758825,52.958191],"type":"Point"}
}