{
  "type": "Feature",
  "properties": {
    "iso:country":"NL",
    "sg:address":"Croy 5B",
    "sg:city":"Eindhoven",
    "sg:orig_category":"Adviesbureaus Bedrijfsorganisatie",
    "sg:phone":"+31 40 257 3626",
    "sg:postcode":"5653 LC",
    "sg:province":"Noord-Brabant",
    "wof:name":"Reputatie Management Groep, De",
    "wof:placetype":"venue"
},
  "geometry": {"coordinates":[5.432691,51.418274],"type":"Point"}
}