{
  "type": "Feature",
  "properties": {
    "addr:full":"Noordwolderweg 7 Bedum Groningen 9781 AD",
    "addr:housenumber":"7",
    "addr:postcode":"9781 ad",
    "addr:street":"Noordwolderweg",
    "iso:country":"NL",
    "sg:address":"Noordwolderweg 7",
    "sg:city":"Bedum",
    "sg:classifiers":[
        {
            "category":"Retail",
            "subcategory":"Photofinishing",
            "type":"Services"
        }
    ],
    "sg:phone":"+31 50 301 3091",
    "sg:postcode":"9781 AD",
    "sg:province":"Groningen",
    "sg:tags":[
        "foto",
        "film"
    ],
    "wof:name":"Objektief",
    "wof:placetype":"venue"
},
  "geometry": {"coordinates":[6.595658,53.300121],"type":"Point"}
}