{
  "type": "Feature",
  "properties": {
    "iso:country":"NL",
    "sg:address":"Bremwg 209",
    "sg:city":"Venlo",
    "sg:classifiers":[
        {
            "category":"Personal",
            "subcategory":"Nail Salon",
            "type":"Services"
        }
    ],
    "sg:phone":"+31 77 354 2397",
    "sg:postcode":"5915 GK",
    "sg:province":"Limburg",
    "sg:tags":[
        "pedicure"
    ],
    "wof:name":"Vriezen-Balmeo, L H",
    "wof:placetype":"venue"
},
  "geometry": {"coordinates":[6.189666,51.360329],"type":"Point"}
}