{
  "type": "Feature",
  "properties": {
    "addr:full":"De Meent 32 Odijk Utrecht 3984 JK",
    "addr:housenumber":"32",
    "addr:postcode":"3984 jk",
    "addr:street":"De Meent",
    "iso:country":"NL",
    "sg:address":"De Meent 32",
    "sg:city":"Odijk",
    "sg:orig_category":"Fotostudio'S And Fotografen",
    "sg:phone":"+31 30 656 2122",
    "sg:postcode":"3984 JK",
    "sg:province":"Utrecht",
    "wof:name":"Combi Foto Blom",
    "wof:placetype":"venue"
},
  "geometry": {"coordinates":[5.232995,52.050365],"type":"Point"}
}