{
  "type": "Feature",
  "properties": {
    "iso:country":"NL",
    "sg:address":"Leeuwerikstr 30",
    "sg:city":"Fynaart",
    "sg:orig_category":"Honden- En Kattentrimsalons",
    "sg:phone":"+31 168 465 717",
    "sg:postcode":"4793 HE",
    "sg:province":"Noord-Brabant",
    "sg:website":"http://www.hondentrimstudiopluk.nl",
    "wof:name":"Pluk",
    "wof:placetype":"venue"
},
  "geometry": {"coordinates":[4.475169,51.636791],"type":"Point"}
}