{
  "type": "Feature",
  "properties": {
    "iso:country":"NL",
    "sg:address":"A Vd Leeuwstr 35",
    "sg:city":"Rotterdam",
    "sg:orig_category":"Webdesign Bureaus",
    "sg:phone":"+31 10 220 6000",
    "sg:postcode":"3069 WH",
    "sg:province":"Zuid-Holland",
    "sg:website":"http://www.linawebdesigns.nl",
    "wof:name":"Lina",
    "wof:placetype":"venue"
},
  "geometry": {"coordinates":[4.5659852028,51.9663467407],"type":"Point"}
}