{
  "type": "Feature",
  "properties": {
    "iso:country":"NL",
    "sg:address":"Kleverparkwg 40",
    "sg:city":"Haarlem",
    "sg:orig_category":"Wijnkoperijen En -Groothandel",
    "sg:phone":"+31 23 527 5858",
    "sg:postcode":"2023 CG",
    "sg:province":"North Holland",
    "sg:website":"http://www.wijnvriend.nl",
    "wof:name":"Wijnvriend, De",
    "wof:placetype":"venue"
},
  "geometry": {"coordinates":[4.6301760674,52.3917503357],"type":"Point"}
}