{
  "type": "Feature",
  "properties": {
    "iso:country":"NL",
    "sg:address":"De Kibbel 1",
    "sg:city":"Wervershoof",
    "sg:orig_category":"Waterbouwkundige Werken",
    "sg:phone":"+31 228 582 798",
    "sg:postcode":"1693 NW",
    "sg:province":"Noord-Holland",
    "sg:website":"http://www.koperbv.nl",
    "wof:name":"Koper & Zn Bv, J",
    "wof:placetype":"venue"
},
  "geometry": {"coordinates":[5.1642951965,52.7255401611],"type":"Point"}
}