{
  "type": "Feature",
  "properties": {
    "addr:full":"Lactariawg 12 Stevensbeek North Brabant 5844 AJ",
    "addr:housenumber":"12",
    "addr:postcode":"5844 aj",
    "addr:street":"Lactariawg",
    "iso:country":"NL",
    "sg:address":"Lactariawg 12",
    "sg:city":"Stevensbeek",
    "sg:orig_category":"Voetbalverenigingen",
    "sg:phone":"+31 485 382 480",
    "sg:postcode":"5844 AJ",
    "sg:province":"North Brabant",
    "wof:name":"Eindse Boys",
    "wof:placetype":"venue"
},
  "geometry": {"coordinates":[5.917364,51.604069],"type":"Point"}
}