{
  "type": "Feature",
  "properties": {
    "addr:full":"Iepenstr 6 Krommenie Noord-Holland 1561 KA",
    "addr:housenumber":"6",
    "addr:postcode":"1561 ka",
    "addr:street":"Iepenstr",
    "iso:country":"NL",
    "sg:address":"Iepenstr 6",
    "sg:city":"Krommenie",
    "sg:orig_category":"Fietsen En Bromfietsen",
    "sg:phone":"+31 75 628 1590",
    "sg:postcode":"1561 KA",
    "sg:province":"Noord-Holland",
    "wof:name":"Bruyns, Evert",
    "wof:placetype":"venue"
},
  "geometry": {"coordinates":[4.761842,52.495518],"type":"Point"}
}