{
  "type": "Feature",
  "properties": {
    "iso:country":"NL",
    "sg:address":"Badstr 4",
    "sg:city":"Domburg",
    "sg:classifiers":[
        {
            "category":"Travel",
            "subcategory":"Hotels & Motels",
            "type":"Entertainment"
        }
    ],
    "sg:phone":"+31 118 582 943",
    "sg:postcode":"4357 AT",
    "sg:province":"Zeeland",
    "wof:name":"Noordzee",
    "wof:placetype":"venue"
},
  "geometry": {"coordinates":[3.498193,51.565876],"type":"Point"}
}