{
  "type": "Feature",
  "properties": {
    "addr:full":"Neerstraat 6 Roermond Limburg 6041 KC",
    "addr:housenumber":"6",
    "addr:postcode":"6041 kc",
    "addr:street":"Neerstraat",
    "iso:country":"NL",
    "sg:address":"Neerstraat 6",
    "sg:city":"Roermond",
    "sg:orig_category":"Werving And Selectie Van Tijdelijk Personeel And Uitzendkantoren",
    "sg:phone":"+31 475 335 300",
    "sg:postcode":"6041 KC",
    "sg:province":"Limburg",
    "wof:name":"Manpower Uitzendorganisatie",
    "wof:placetype":"venue"
},
  "geometry": {"coordinates":[5.9851517677,51.1943588257],"type":"Point"}
}