{
  "type": "Feature",
  "properties": {
    "addr:full":"Waarderweg 7 Haarlem North Holland 2031 BN",
    "addr:housenumber":"7",
    "addr:postcode":"2031 bn",
    "addr:street":"Waarderweg",
    "iso:country":"NL",
    "sg:address":"Waarderweg 7",
    "sg:city":"Haarlem",
    "sg:orig_category":"Hout Gh",
    "sg:phone":"+31 23 532 0008",
    "sg:postcode":"2031 BN",
    "sg:province":"North Holland",
    "wof:name":"Wolff Hardhout Import Bv",
    "wof:placetype":"venue"
},
  "geometry": {"coordinates":[4.663631,52.388039],"type":"Point"}
}