{
  "type": "Feature",
  "properties": {
    "addr:full":"Nijverheidstraat 13 Kruiningen Zeeland 4416 BV",
    "addr:housenumber":"13",
    "addr:postcode":"4416 bv",
    "addr:street":"Nijverheidstraat",
    "iso:country":"NL",
    "sg:address":"Nijverheidstraat 13",
    "sg:city":"Kruiningen",
    "sg:orig_category":"Fietshandelaren",
    "sg:phone":"+31 113 320 008",
    "sg:postcode":"4416 BV",
    "sg:province":"Zeeland",
    "wof:name":"A P Van Noorden",
    "wof:placetype":"venue"
},
  "geometry": {"coordinates":[4.036767,51.446678],"type":"Point"}
}