{
  "type": "Feature",
  "properties": {
    "iso:country":"NL",
    "sg:address":"Rijksstraatweg 17",
    "sg:city":"Ridderkerk",
    "sg:orig_category":"Personenvervoer Zonder Dienstregeling",
    "sg:phone":"+31 180 422 800",
    "sg:postcode":"2988 BA",
    "sg:province":"Zuid-Holland",
    "wof:name":"De Jong'S Autobedrijf Bv",
    "wof:placetype":"venue"
},
  "geometry": {"coordinates":[4.602249,51.845604],"type":"Point"}
}