{
  "type": "Feature",
  "properties": {
    "iso:country":"NL",
    "sg:address":"Sprangseweg 13",
    "sg:city":"Waalwijk",
    "sg:orig_category":"Bloemen And Planten",
    "sg:phone":"+31 416 333 078",
    "sg:postcode":"5144 NV",
    "sg:province":"Noord-Brabant",
    "wof:name":"Jan Pullens",
    "wof:placetype":"venue"
},
  "geometry": {"coordinates":[5.050586,51.680401],"type":"Point"}
}