{
  "type": "Feature",
  "properties": {
    "addr:full":"Binnendamsewg 53 Giessenburg Zuid-Holland 3381 GB",
    "addr:housenumber":"53",
    "addr:postcode":"3381 gb",
    "addr:street":"Binnendamsewg",
    "iso:country":"NL",
    "sg:address":"Binnendamsewg 53",
    "sg:city":"Giessenburg",
    "sg:orig_category":"Juridische Adviseurs",
    "sg:phone":"+31 184 422 553",
    "sg:postcode":"3381 GB",
    "sg:province":"Zuid-Holland",
    "wof:name":"Toxopeus Bv",
    "wof:placetype":"venue"
},
  "geometry": {"coordinates":[4.856174,51.832745],"type":"Point"}
}