{
  "type": "Feature",
  "properties": {
    "addr:full":"Kerkring 32 Oude-Tonge Zuid-Holland 3255 AH",
    "addr:housenumber":"32",
    "addr:postcode":"3255 ah",
    "addr:street":"Kerkring",
    "iso:country":"NL",
    "sg:address":"Kerkring 32",
    "sg:city":"Oude-Tonge",
    "sg:orig_category":"Kappers",
    "sg:phone":"+31 187 642 100",
    "sg:postcode":"3255 AH",
    "sg:province":"Zuid-Holland",
    "wof:name":"Valentino Haarmode",
    "wof:placetype":"venue"
},
  "geometry": {"coordinates":[4.213107,51.6912],"type":"Point"}
}