{
  "type": "Feature",
  "properties": {
    "addr:full":"Kamperfoeliestraat 2B 'S Gravenhage Zuid-Holland 2563 KJ",
    "addr:housenumber":"2b",
    "addr:postcode":"2563 kj",
    "addr:street":"Kamperfoeliestraat;' S",
    "iso:country":"NL",
    "sg:address":"Kamperfoeliestraat 2B",
    "sg:city":"'S Gravenhage",
    "sg:orig_category":"Bloemen And Planten",
    "sg:phone":"+31 70 325 8704",
    "sg:postcode":"2563 KJ",
    "sg:province":"Zuid-Holland",
    "wof:name":"C.A. Pronk",
    "wof:placetype":"venue"
},
  "geometry": {"coordinates":[4.269217,52.06757],"type":"Point"}
}