{
  "type": "Feature",
  "properties": {
    "iso:country":"NL",
    "sg:address":"Hammerstraat 7",
    "sg:city":"Vroomshoop",
    "sg:orig_category":"Opticiens",
    "sg:phone":"+31 546 642 890",
    "sg:postcode":"7681 DA",
    "sg:province":"Overijssel",
    "wof:name":"Mijn Opticien Diekman Bv",
    "wof:placetype":"venue"
},
  "geometry": {"coordinates":[6.5722379684,52.461139679],"type":"Point"}
}