{
  "type": "Feature",
  "properties": {
    "addr:full":"Assendorperstraat 62 Zwolle Overijssel 8012 CA",
    "addr:housenumber":"62",
    "addr:postcode":"8012 ca",
    "addr:street":"Assendorperstraat",
    "iso:country":"NL",
    "sg:address":"Assendorperstraat 62",
    "sg:city":"Zwolle",
    "sg:orig_category":"Kappers",
    "sg:phone":"+31 38 423 2188",
    "sg:postcode":"8012 CA",
    "sg:province":"Overijssel",
    "wof:name":"Yvon'S",
    "wof:placetype":"venue"
},
  "geometry": {"coordinates":[6.099827,52.507412],"type":"Point"}
}