{
  "type": "Feature",
  "properties": {
    "addr:full":"Pleinwg 148A Rotterdam South Holland 3083 ER",
    "addr:housenumber":"148a",
    "addr:postcode":"3083 er",
    "iso:country":"NL",
    "sg:address":"Pleinwg 148A",
    "sg:city":"Rotterdam",
    "sg:orig_category":"Kappers",
    "sg:phone":"+31 10 480 7656",
    "sg:postcode":"3083 ER",
    "sg:province":"South Holland",
    "wof:name":"Hair Square",
    "wof:placetype":"venue"
},
  "geometry": {"coordinates":[4.4811468124,51.8908348083],"type":"Point"}
}