{
  "type": "Feature",
  "properties": {
    "addr:full":"Boomdk 30 Wolphaartsdyk Zeeland 4471 AZ",
    "addr:housenumber":"30",
    "addr:postcode":"4471",
    "addr:street":"Boomdk;Zeeland",
    "iso:country":"NL",
    "sg:address":"Boomdk 30",
    "sg:city":"Wolphaartsdyk",
    "sg:orig_category":"Onroerende Goederen",
    "sg:phone":"+31 113 586 024",
    "sg:postcode":"4471 AZ",
    "sg:province":"Zeeland",
    "wof:name":"Tonnko",
    "wof:placetype":"venue"
},
  "geometry": {"coordinates":[3.818706,51.52636],"type":"Point"}
}