{
  "type": "Feature",
  "properties": {
    "addr:full":"Gebroeders Potstraat 30 Nieuw Lekkerland South Holland 2957 KC",
    "addr:housenumber":"30",
    "addr:postcode":"2957 kc",
    "addr:street":"Gebroeders Potstraat",
    "iso:country":"NL",
    "sg:address":"Gebroeders Potstraat 30",
    "sg:city":"Nieuw Lekkerland",
    "sg:orig_category":"Boekhouders",
    "sg:phone":"+31 184 683 256",
    "sg:postcode":"2957 KC",
    "sg:province":"South Holland",
    "wof:name":"Gg Administratie Controlling Consultancy",
    "wof:placetype":"venue"
},
  "geometry": {"coordinates":[4.684081,51.889908],"type":"Point"}
}