{
  "type": "Feature",
  "properties": {
    "iso:country":"NL",
    "sg:address":"Theseusstr 1",
    "sg:city":"Amsterdam",
    "sg:orig_category":"Goudsmeden En Zilversmeden",
    "sg:phone":"+31 20 673 5014",
    "sg:postcode":"1076 XK",
    "sg:province":"Noord-Holland",
    "wof:name":"Anke Amo Akerboom",
    "wof:placetype":"venue"
},
  "geometry": {"coordinates":[4.861279,52.34906],"type":"Point"}
}