{
  "type": "Feature",
  "properties": {
    "addr:full":"Froonackerdk 2 Winsum Fr Friesland 8831 ZH",
    "addr:housenumber":"2",
    "addr:postcode":"8831 zh",
    "addr:street":"Froonackerdk",
    "iso:country":"NL",
    "sg:address":"Froonackerdk 2",
    "sg:city":"Winsum Fr",
    "sg:orig_category":"Loonbedrijven",
    "sg:phone":"+31 517 341 231",
    "sg:postcode":"8831 ZH",
    "sg:province":"Friesland",
    "wof:name":"Miedema, A S",
    "wof:placetype":"venue"
},
  "geometry": {"coordinates":[5.64622,53.148548],"type":"Point"}
}