{
  "type": "Feature",
  "properties": {
    "addr:full":"Burgwal 17 Haarlem Noord-Holland 2011 BA",
    "addr:housenumber":"17",
    "addr:postcode":"2011 ba",
    "addr:street":"Burgwal",
    "iso:country":"NL",
    "sg:address":"Burgwal 17",
    "sg:city":"Haarlem",
    "sg:orig_category":"Bedrijfsopleidingen",
    "sg:phone":"+31 23 533 7196",
    "sg:postcode":"2011 BA",
    "sg:province":"Noord-Holland",
    "sg:website":"http://www.burnoutturnin.nl",
    "wof:name":"Sanders",
    "wof:placetype":"venue"
},
  "geometry": {"coordinates":[4.642798,52.379372],"type":"Point"}
}