{
  "type": "Feature",
  "properties": {
    "iso:country":"NL",
    "sg:address":"L Couperusstr 3",
    "sg:city":"Gemert",
    "sg:orig_category":"Adviesbureaus Werktuigbouwkunde",
    "sg:phone":"+31 492 390 000",
    "sg:postcode":"5421 RH",
    "sg:province":"Noord-Brabant",
    "wof:name":"Frans Scheepens",
    "wof:placetype":"venue"
},
  "geometry": {"coordinates":[5.681305,51.563885],"type":"Point"}
}