{
  "type": "Feature",
  "properties": {
    "iso:country":"NL",
    "sg:address":"J V Bynendreef 3",
    "sg:city":"Oosterhout Nb",
    "sg:orig_category":"Adviesbureaus Bedrijfsorganisatie",
    "sg:phone":"+31 162 421 502",
    "sg:postcode":"4904 WD",
    "sg:province":"Noord-Brabant",
    "wof:name":"Plasman & Simjouw Partn Vof",
    "wof:placetype":"venue"
},
  "geometry": {"coordinates":[4.84311,51.62178],"type":"Point"}
}