{
  "type": "Feature",
  "properties": {
    "addr:full":"Gildestr 107 Naaldwyk Zuid-Holland 2671 BV",
    "addr:housenumber":"107",
    "addr:postcode":"2671 bv",
    "addr:street":"Naaldwyk",
    "iso:country":"NL",
    "sg:address":"Gildestr 107",
    "sg:city":"Naaldwyk",
    "sg:classifiers":[
        {
            "category":"Retail",
            "subcategory":"Auto Repair",
            "type":"Services"
        }
    ],
    "sg:phone":"+31 174 610 956",
    "sg:postcode":"2671 BV",
    "sg:province":"Zuid-Holland",
    "sg:tags":[
        "garage"
    ],
    "sg:website":"http://www.drive.to/rien",
    "wof:name":"Gulik Autobedrijf M C Van",
    "wof:placetype":"venue"
},
  "geometry": {"coordinates":[4.210344,52.002022],"type":"Point"}
}