{
  "type": "Feature",
  "properties": {
    "addr:full":"Kievitstraat 25 Helmond Noord-Brabant 5702 LC",
    "addr:housenumber":"25",
    "addr:postcode":"5702 lc",
    "addr:street":"Kievitstraat",
    "iso:country":"NL",
    "sg:address":"Kievitstraat 25",
    "sg:city":"Helmond",
    "sg:orig_category":"Makelaars In Onroerend Goed",
    "sg:phone":"+31 492 529 852",
    "sg:postcode":"5702 LC",
    "sg:province":"Noord-Brabant",
    "wof:name":"A. Annouwari",
    "wof:placetype":"venue"
},
  "geometry": {"coordinates":[5.660346,51.492546],"type":"Point"}
}