{
  "type": "Feature",
  "properties": {
    "addr:full":"Hyacinthenstr 23 Maastricht Limburg 6214 TC",
    "addr:housenumber":"23",
    "addr:postcode":"6214 tc",
    "addr:street":"Hyacinthenstr",
    "iso:country":"NL",
    "sg:address":"Hyacinthenstr 23",
    "sg:city":"Maastricht",
    "sg:orig_category":"Adviesbureaus Bedrijfsorganisatie",
    "sg:phone":"+31 43 343 1497",
    "sg:postcode":"6214 TC",
    "sg:province":"Limburg",
    "sg:website":"http://www.cuci.nl/~e-amac",
    "wof:name":"Euro-African",
    "wof:placetype":"venue"
},
  "geometry": {"coordinates":[5.673257,50.846252],"type":"Point"}
}