{
  "type": "Feature",
  "properties": {
    "addr:full":"A Verweyln 2A Uithoorn North Holland 1422 TR",
    "addr:housenumber":"2a",
    "addr:postcode":"1422 tr",
    "iso:country":"NL",
    "sg:address":"A Verweyln 2A",
    "sg:city":"Uithoorn",
    "sg:orig_category":"Kappers",
    "sg:phone":"+31 297 566 644",
    "sg:postcode":"1422 TR",
    "sg:province":"North Holland",
    "wof:name":"Warrels",
    "wof:placetype":"venue"
},
  "geometry": {"coordinates":[4.828947,52.233421],"type":"Point"}
}