{
  "type": "Feature",
  "properties": {
    "iso:country":"NL",
    "sg:address":"Akkerwinde 9",
    "sg:city":"Hoogvliet Rt",
    "sg:orig_category":"Kaas",
    "sg:phone":"+31 10 438 0247",
    "sg:postcode":"3191 RA",
    "sg:province":"Zuid-Holland",
    "wof:name":"Kaasland",
    "wof:placetype":"venue"
},
  "geometry": {"coordinates":[4.3654999733,51.8610115051],"type":"Point"}
}