{
  "type": "Feature",
  "properties": {
    "iso:country":"NL",
    "sg:address":"Kennedeyboulev",
    "sg:city":"Egmond Aan Zee",
    "sg:classifiers":[
        {
            "category":"Fast Food",
            "type":"Food & Drink"
        }
    ],
    "sg:phone":"+31 72 506 5009",
    "sg:postcode":"1931 XM",
    "sg:province":"North Holland",
    "sg:tags":[
        "afhaal",
        "restaurant"
    ],
    "wof:name":"De Zilvermeeuw",
    "wof:placetype":"venue"
},
  "geometry": {"coordinates":[4.621995,52.615269],"type":"Point"}
}