{
  "type": "Feature",
  "properties": {
    "addr:full":"Bargerbosch 13 Winterswijk Gelderland 7103 DG",
    "addr:housenumber":"13",
    "addr:postcode":"7103 dg",
    "addr:street":"Bargerbosch;Gelderland",
    "iso:country":"NL",
    "sg:address":"Bargerbosch 13",
    "sg:city":"Winterswijk",
    "sg:orig_category":"Sportterreinen And Installaties Behalve Sportcentra",
    "sg:phone":"+31 543 518 017",
    "sg:postcode":"7103 DG",
    "sg:province":"Gelderland",
    "wof:name":"Zwemschool I. Beyers",
    "wof:placetype":"venue"
},
  "geometry": {"coordinates":[6.72287,51.983223],"type":"Point"}
}