{
  "type": "Feature",
  "properties": {
    "iso:country":"NL",
    "sg:address":"Reitschewg 3F",
    "sg:city":"S Hertogenbosch",
    "sg:classifiers":[
        {
            "category":"Manufacturing",
            "subcategory":"Textiles",
            "type":"Manufacturing & Wholesale Goods"
        }
    ],
    "sg:phone":"+31 73 644 4854",
    "sg:postcode":"5232 BX",
    "sg:province":"North Brabant",
    "sg:tags":[
        "polyester"
    ],
    "sg:website":"http://www.fibertec.nl",
    "wof:name":"Fibertec Europe Bv",
    "wof:placetype":"venue"
},
  "geometry": {"coordinates":[5.339335,51.708698],"type":"Point"}
}