{
  "type": "Feature",
  "properties": {
    "addr:full":"Nieuwstraat 20 Baarle Nassau Noord-Brabant 5111 CW",
    "addr:housenumber":"20",
    "addr:postcode":"5111 cw",
    "addr:street":"Nieuwstraat",
    "iso:country":"NL",
    "sg:address":"Nieuwstraat 20",
    "sg:city":"Baarle Nassau",
    "sg:orig_category":"Banken And Kredietinstellingen",
    "sg:phone":"+31 13 507 6565",
    "sg:postcode":"5111 CW",
    "sg:province":"Noord-Brabant",
    "wof:name":"Abn Amro",
    "wof:placetype":"venue"
},
  "geometry": {"coordinates":[4.92629,51.449741],"type":"Point"}
}