{
  "type": "Feature",
  "properties": {
    "addr:full":"Herenstr 46 Breukelen Ut Utrecht 3621 AR",
    "addr:housenumber":"46",
    "addr:postcode":"3621",
    "addr:street":"Herenstr",
    "iso:country":"NL",
    "sg:address":"Herenstr 46",
    "sg:city":"Breukelen Ut",
    "sg:orig_category":"Antiquiteiten",
    "sg:phone":"+31 346 264 233",
    "sg:postcode":"3621 AR",
    "sg:province":"Utrecht",
    "wof:name":"Prins, Ellen",
    "wof:placetype":"venue"
},
  "geometry": {"coordinates":[5.003277,52.172874],"type":"Point"}
}