{
  "type": "Feature",
  "properties": {
    "iso:country":"NL",
    "sg:address":"Nieuwstad 62",
    "sg:city":"Zutphen",
    "sg:orig_category":"Onderhoudswerken",
    "sg:phone":"+31 575 512 994",
    "sg:postcode":"7201 NS",
    "sg:province":"Gelderland",
    "wof:name":"Muflex",
    "wof:placetype":"venue"
},
  "geometry": {"coordinates":[6.197669,52.144707],"type":"Point"}
}