{
  "type": "Feature",
  "properties": {
    "addr:full":"Edisonstraat 29 Doetinchem Gelderland 7006 RA",
    "addr:housenumber":"29",
    "addr:postcode":"7006 ra",
    "addr:street":"Edisonstraat;Gelderland",
    "iso:country":"NL",
    "sg:address":"Edisonstraat 29",
    "sg:city":"Doetinchem",
    "sg:orig_category":"Metaalbekleding And -Behandeling",
    "sg:phone":"+31 314 342 670",
    "sg:postcode":"7006 RA",
    "sg:province":"Gelderland",
    "wof:name":"Firma Slijpservice Doetinchem Vof",
    "wof:placetype":"venue"
},
  "geometry": {"coordinates":[6.262526,51.970276],"type":"Point"}
}