{
  "type": "Feature",
  "properties": {
    "addr:full":"Reutsedijk 7 Vught Noord-Brabant 5264 PC",
    "addr:housenumber":"7",
    "addr:postcode":"5264 pc",
    "addr:street":"Reutsedijk",
    "iso:country":"NL",
    "sg:address":"Reutsedijk 7",
    "sg:city":"Vught",
    "sg:orig_category":"Opvangtehuizen",
    "sg:phone":"+31 73 692 1731",
    "sg:postcode":"5264 PC",
    "sg:province":"Noord-Brabant",
    "wof:name":"Asielzoekerscentrum Vught",
    "wof:placetype":"venue"
},
  "geometry": {"coordinates":[5.2868652344,51.6741638184],"type":"Point"}
}