{
  "type": "Feature",
  "properties": {
    "addr:full":"Broekhem 11 Valkenburg Lb Limburg 6301 HD",
    "addr:housenumber":"11",
    "addr:postcode":"lb;6301 hd",
    "addr:street":"Broekhem",
    "iso:country":"NL",
    "sg:address":"Broekhem 11",
    "sg:city":"Valkenburg Lb",
    "sg:classifiers":[
        {
            "category":"Travel",
            "subcategory":"Hotels & Motels",
            "type":"Entertainment"
        }
    ],
    "sg:phone":"+31 43 601 2244",
    "sg:postcode":"6301 HD",
    "sg:province":"Limburg",
    "wof:name":"Hotel Restaurant Prinses Juliana Bv",
    "wof:placetype":"venue"
},
  "geometry": {"coordinates":[5.827642,50.868961],"type":"Point"}
}