{
  "type": "Feature",
  "properties": {
    "addr:full":"Florynwg 7 Velp Gld Gelderland 6883 JN",
    "addr:housenumber":"7",
    "addr:postcode":"6883 jn",
    "addr:street":"Florynwg;Gld Gelderland",
    "iso:country":"NL",
    "sg:address":"Florynwg 7",
    "sg:city":"Velp Gld",
    "sg:orig_category":"Schilders",
    "sg:phone":"+31 26 361 9145",
    "sg:postcode":"6883 JN",
    "sg:province":"Gelderland",
    "wof:name":"Bosveld, Gebr",
    "wof:placetype":"venue"
},
  "geometry": {"coordinates":[5.989296,51.983055],"type":"Point"}
}