{
  "type": "Feature",
  "properties": {
    "addr:full":"Berkelkd 10 Zutphen Gelderland 7201 JE",
    "addr:housenumber":"10",
    "addr:postcode":"7201 je",
    "addr:street":"Berkelkd;Gelderland",
    "iso:country":"NL",
    "sg:address":"Berkelkd 10",
    "sg:city":"Zutphen",
    "sg:orig_category":"Adviesbureaus Bedrijfsorganisatie",
    "sg:phone":"+31 575 545 439",
    "sg:postcode":"7201 JE",
    "sg:province":"Gelderland",
    "wof:name":"Mhm",
    "wof:placetype":"venue"
},
  "geometry": {"coordinates":[6.191525,52.140202],"type":"Point"}
}