{
  "type": "Feature",
  "properties": {
    "addr:full":"Hoefweg 194A Bleiswijk South Holland 2665 LE",
    "addr:housenumber":"194a",
    "addr:postcode":"2665 le",
    "addr:street":"Hoefweg",
    "iso:country":"NL",
    "sg:address":"Hoefweg 194A",
    "sg:city":"Bleiswijk",
    "sg:orig_category":"Houten Verpakkingen Fab",
    "sg:phone":"+31 10 521 5300",
    "sg:postcode":"2665 LE",
    "sg:province":"South Holland",
    "wof:name":"Harry De Hoog Bv",
    "wof:placetype":"venue"
},
  "geometry": {"coordinates":[4.537716,52.028671],"type":"Point"}
}