{
  "type": "Feature",
  "properties": {
    "addr:full":"Boerskottenhoek 32 Enschede NL.08 7546 DA",
    "addr:housenumber":"32;7546",
    "addr:postcode":"da",
    "addr:street":"Boerskottenhoek",
    "iso:country":"NL",
    "sg:address":"Boerskottenhoek 32",
    "sg:city":"Enschede",
    "sg:orig_category":"Verloskundigen",
    "sg:phone":"+31 53 478 0535",
    "sg:postcode":"7546 DA",
    "sg:province":"NL.08",
    "wof:name":"De Bie-Post",
    "wof:placetype":"venue"
},
  "geometry": {"coordinates":[6.857317,52.187302],"type":"Point"}
}