{
  "type": "Feature",
  "properties": {
    "addr:full":"Passeerdersgr 18 Amsterdam Noord-Holland 1016 XH",
    "addr:housenumber":"18",
    "addr:postcode":"1016 xh",
    "addr:street":"Passeerdersgr",
    "iso:country":"NL",
    "sg:address":"Passeerdersgr 18",
    "sg:city":"Amsterdam",
    "sg:orig_category":"Wijnkoperijen En -Groothandel",
    "sg:phone":"+31 20 627 1538",
    "sg:postcode":"1016 XH",
    "sg:province":"Noord-Holland",
    "wof:name":"Hoekstra & Verhagen Bv",
    "wof:placetype":"venue"
},
  "geometry": {"coordinates":[4.8812680244,52.3672866821],"type":"Point"}
}