{
  "type": "Feature",
  "properties": {
    "addr:full":"Dorpsstraat 99 Bemmel Gelderland 6681 BM",
    "addr:housenumber":"99",
    "addr:postcode":"6681 bm",
    "addr:street":"Dorpsstraat;Gelderland",
    "iso:country":"NL",
    "sg:address":"Dorpsstraat 99",
    "sg:city":"Bemmel",
    "sg:orig_category":"Boekhouders",
    "sg:phone":"+31 481 466 253",
    "sg:postcode":"6681 BM",
    "sg:province":"Gelderland",
    "wof:name":"Admin- En Bedrijfsadviesbureau Folio Bv",
    "wof:placetype":"venue"
},
  "geometry": {"coordinates":[5.895744,51.88792],"type":"Point"}
}