{
  "type": "Feature",
  "properties": {
    "addr:full":"Dorpsstr 154 Zuid Beyerland Zuid-Holland 3284 AK",
    "addr:housenumber":"154;beyerland",
    "addr:postcode":"3284 ak",
    "iso:country":"NL",
    "sg:address":"Dorpsstr 154",
    "sg:city":"Zuid Beyerland",
    "sg:orig_category":"Homeopathie",
    "sg:phone":"+31 186 662 713",
    "sg:postcode":"3284 AK",
    "sg:province":"Zuid-Holland",
    "wof:name":"Hoorne-Fokkema, G Van",
    "wof:placetype":"venue"
},
  "geometry": {"coordinates":[4.368185,51.749817],"type":"Point"}
}