{
  "type": "Feature",
  "properties": {
    "addr:full":"De Genestetlaan 1 Hilversum Noord-Holland 1215 EB",
    "addr:housenumber":"1",
    "addr:postcode":"1215 eb",
    "addr:street":"De Genestetlaan",
    "iso:country":"NL",
    "sg:address":"De Genestetlaan 1",
    "sg:city":"Hilversum",
    "sg:orig_category":"Geluidsopnamen",
    "sg:phone":"+31 35 621 5929",
    "sg:postcode":"1215 EB",
    "sg:province":"Noord-Holland",
    "wof:name":"Ad Wolthers Music Service",
    "wof:placetype":"venue"
},
  "geometry": {"coordinates":[5.162078,52.218155],"type":"Point"}
}