{
  "type": "Feature",
  "properties": {
    "addr:full":"Waalsewg 90 Tull En T Waal Utrecht 3999 NV",
    "addr:housenumber":"90",
    "addr:postcode":"3999 nv",
    "addr:street":"Waalsewg;Tull En T Waal",
    "iso:country":"NL",
    "sg:address":"Waalsewg 90",
    "sg:city":"Tull En T Waal",
    "sg:classifiers":[
        {
            "category":"Sports & Exercise",
            "subcategory":"Stables",
            "type":"Entertainment"
        }
    ],
    "sg:phone":"+31 30 608 1933",
    "sg:postcode":"3999 NV",
    "sg:province":"Utrecht",
    "sg:tags":[
        "maneges"
    ],
    "wof:name":"Coxdijcke",
    "wof:placetype":"venue"
},
  "geometry": {"coordinates":[5.122898,52.006962],"type":"Point"}
}