{
  "type": "Feature",
  "properties": {
    "iso:country":"NL",
    "sg:address":"Straalsteen 87",
    "sg:city":"Heerhugowaard",
    "sg:orig_category":"Grafische Bedrijven",
    "sg:phone":"+31 72 572 1954",
    "sg:postcode":"1703 ES",
    "sg:province":"North Holland",
    "wof:name":"Astro Design",
    "wof:placetype":"venue"
},
  "geometry": {"coordinates":[4.822026,52.661701],"type":"Point"}
}