{
  "type": "Feature",
  "properties": {
    "iso:country":"NL",
    "sg:address":"Deventerwg 7",
    "sg:city":"Laren Gld",
    "sg:orig_category":"Kappers",
    "sg:phone":"+31 573 401 575",
    "sg:postcode":"7245 AW",
    "sg:province":"Gelderland",
    "wof:name":"Lamar Salon",
    "wof:placetype":"venue"
},
  "geometry": {"coordinates":[6.363355,52.194031],"type":"Point"}
}