{
  "type": "Feature",
  "properties": {
    "addr:full":"Lenculenstraat 1 Maastricht Limburg 6211 KP",
    "addr:housenumber":"1",
    "addr:postcode":"6211 kp",
    "addr:street":"Lenculenstraat",
    "iso:country":"NL",
    "sg:address":"Lenculenstraat 1",
    "sg:city":"Maastricht",
    "sg:orig_category":"Kappers",
    "sg:phone":"+31 43 325 3425",
    "sg:postcode":"6211 KP",
    "sg:province":"Limburg",
    "wof:name":"Contrast Kappers",
    "wof:placetype":"venue"
},
  "geometry": {"coordinates":[5.6899271011,50.8468513489],"type":"Point"}
}