{
  "type": "Feature",
  "properties": {
    "iso:country":"NL",
    "sg:address":"Karekiet 16",
    "sg:city":"Bunschoten Spakenburg",
    "sg:classifiers":[
        {
            "category":"Education",
            "subcategory":"Preschool",
            "type":"Public Place"
        }
    ],
    "sg:phone":"+31 33 298 2204",
    "sg:postcode":"3752 NB",
    "sg:province":"Utrecht",
    "sg:tags":[
        "kleuteronderwijs",
        "basis-"
    ],
    "wof:name":"Prot Chr Basisschool De Vlucht",
    "wof:placetype":"venue"
},
  "geometry": {"coordinates":[5.36464,52.240459],"type":"Point"}
}