{
  "type": "Feature",
  "properties": {
    "iso:country":"NL",
    "sg:address":"Henri Polaklaan 12",
    "sg:city":"Amsterdam",
    "sg:orig_category":"Diverse Grafische Activiteiten",
    "sg:phone":"+31 20 638 6892",
    "sg:postcode":"1018 CS",
    "sg:province":"Noord-Holland",
    "wof:name":"Bureau Voor Leuke Dingen",
    "wof:placetype":"venue"
},
  "geometry": {"coordinates":[4.910719,52.367668],"type":"Point"}
}