{
  "type": "Feature",
  "properties": {
    "iso:country":"NL",
    "sg:address":"Odradastr 23",
    "sg:city":"Eersel",
    "sg:orig_category":"Machineonderhoud En -Reparatie",
    "sg:phone":"+31 6 55700183",
    "sg:postcode":"5521 CP",
    "sg:province":"North Brabant",
    "wof:name":"Maas",
    "wof:placetype":"venue"
},
  "geometry": {"coordinates":[5.3208589554,51.359500885],"type":"Point"}
}