{
  "type": "Feature",
  "properties": {
    "addr:full":"Kreupeleweg 2 Klaaswaal Zuid-Holland 3286 BC",
    "addr:housenumber":"2",
    "addr:postcode":"3286 bc",
    "addr:street":"Kreupeleweg",
    "iso:country":"NL",
    "sg:address":"Kreupeleweg 2",
    "sg:city":"Klaaswaal",
    "sg:orig_category":"Kinderopvang Behalve Thuis",
    "sg:phone":"+31 186 574 519",
    "sg:postcode":"3286 BC",
    "sg:province":"Zuid-Holland",
    "wof:name":"Kinderopvang Cromstrijen",
    "wof:placetype":"venue"
},
  "geometry": {"coordinates":[4.441462,51.774475],"type":"Point"}
}