{
  "type": "Feature",
  "properties": {
    "addr:full":"Rivierstr 68 Rotterdam Zuid-Holland 3016 CH",
    "addr:housenumber":"68",
    "addr:postcode":"3016",
    "addr:street":"Rivierstr",
    "iso:country":"NL",
    "sg:address":"Rivierstr 68",
    "sg:city":"Rotterdam",
    "sg:orig_category":"Webdesign Bureaus",
    "sg:phone":"+31 10 440 5235",
    "sg:postcode":"3016 CH",
    "sg:province":"Zuid-Holland",
    "wof:name":"Ebz",
    "wof:placetype":"venue"
},
  "geometry": {"coordinates":[4.4761772156,51.9058456421],"type":"Point"}
}