{
  "type": "Feature",
  "properties": {
    "iso:country":"NL",
    "sg:address":"L Kerkstr 16",
    "sg:city":"Goes",
    "sg:orig_category":"Drogisterijen",
    "sg:phone":"+31 113 228 714",
    "sg:postcode":"4461 JH",
    "sg:province":"Zeeland",
    "sg:website":"http://www.drogisterij-fassaert.nl",
    "wof:name":"Da Drogisterij Parfumerie Fassaert",
    "wof:placetype":"venue"
},
  "geometry": {"coordinates":[-83.914169,39.768833],"type":"Point"}
}