{
  "type": "Feature",
  "properties": {
    "addr:full":"Hogenhof 2 Nijkerk Gld Gelderland 3861 CH",
    "addr:housenumber":"2",
    "addr:postcode":"3861",
    "addr:street":"Hogenhof;Gld Gelderland",
    "iso:country":"NL",
    "sg:address":"Hogenhof 2",
    "sg:city":"Nijkerk Gld",
    "sg:orig_category":"Meubelzaken, Woning- And Keukeninrichting",
    "sg:phone":"+31 33 245 7487",
    "sg:postcode":"3861 CH",
    "sg:province":"Gelderland",
    "wof:name":"A.C. Ham Meubelhal",
    "wof:placetype":"venue"
},
  "geometry": {"coordinates":[5.4788,52.222511],"type":"Point"}
}