{
  "type": "Feature",
  "properties": {
    "iso:country":"NL",
    "sg:address":"Herenwg 1B",
    "sg:city":"De Bilt",
    "sg:orig_category":"Makelaars En Adviseurs Hypotheken",
    "sg:phone":"+31 30 220 2940",
    "sg:postcode":"3732 CL",
    "sg:province":"Utrecht",
    "sg:website":"http://www.verzuumakelaardij.nl",
    "wof:name":"Verzuu",
    "wof:placetype":"venue"
},
  "geometry": {"coordinates":[5.182095,52.109966],"type":"Point"}
}