{
  "type": "Feature",
  "properties": {
    "addr:full":"Martinetstr 20 Deurne Noord-Brabant 5751 KR",
    "addr:housenumber":"20",
    "addr:postcode":"5751 kr",
    "addr:street":"Martinetstr",
    "iso:country":"NL",
    "sg:address":"Martinetstr 20",
    "sg:city":"Deurne",
    "sg:orig_category":"Opticiens",
    "sg:phone":"+31 493 313 913",
    "sg:postcode":"5751 KR",
    "sg:province":"Noord-Brabant",
    "wof:name":"Gool, Van",
    "wof:placetype":"venue"
},
  "geometry": {"coordinates":[5.794716835,51.4623260498],"type":"Point"}
}