{
  "type": "Feature",
  "properties": {
    "addr:full":"Pannerdenseweg 22 Doornenburg Khaskovo 6686 BG",
    "addr:housenumber":"22",
    "addr:postcode":"6686",
    "addr:street":"Pannerdenseweg",
    "iso:country":"NL",
    "sg:address":"Pannerdenseweg 22",
    "sg:city":"Doornenburg",
    "sg:orig_category":"Autokeuringen",
    "sg:phone":"+31 481 421 440",
    "sg:postcode":"6686 BG",
    "sg:province":"Khaskovo",
    "wof:name":"Gebrs Leenders",
    "wof:placetype":"venue"
},
  "geometry": {"coordinates":[25.485849,41.740528],"type":"Point"}
}