{
  "type": "Feature",
  "properties": {
    "iso:country":"NL",
    "sg:address":"Axelsestraat 74",
    "sg:city":"Terneuzen",
    "sg:orig_category":"Zuivelproducten",
    "sg:phone":"+31 115 612 615",
    "sg:postcode":"4537 AM",
    "sg:province":"Zeeland",
    "wof:name":"Firma J.B. Ruben",
    "wof:placetype":"venue"
},
  "geometry": {"coordinates":[3.833316,51.331081],"type":"Point"}
}