{
  "type": "Feature",
  "properties": {
    "addr:full":"Postelstr 11B Someren Noord-Brabant 5711 EM",
    "addr:housenumber":"11b",
    "addr:postcode":"5711 em",
    "addr:street":"Postelstr",
    "iso:country":"NL",
    "sg:address":"Postelstr 11B",
    "sg:city":"Someren",
    "sg:orig_category":"Kappers",
    "sg:phone":"+31 493 479 307",
    "sg:postcode":"5711 EM",
    "sg:province":"Noord-Brabant",
    "wof:name":"Just For You",
    "wof:placetype":"venue"
},
  "geometry": {"coordinates":[5.7114582062,51.3850860596],"type":"Point"}
}