{
  "type": "Feature",
  "properties": {
    "addr:full":"Dovenetel 98 Apeldoorn Gelderland 7322 DT",
    "addr:housenumber":"98",
    "addr:postcode":"7322 dt",
    "addr:street":"Dovenetel;Gelderland",
    "iso:country":"NL",
    "sg:address":"Dovenetel 98",
    "sg:city":"Apeldoorn",
    "sg:orig_category":"Technische Studies And Onderzoek",
    "sg:phone":"+31 55 366 3733",
    "sg:postcode":"7322 DT",
    "sg:province":"Gelderland",
    "wof:name":"N De Heus- Wiegersma & P J W Heinhuis",
    "wof:placetype":"venue"
},
  "geometry": {"coordinates":[5.980441,52.223011],"type":"Point"}
}