{
  "type": "Feature",
  "properties": {
    "addr:full":"Moerheimstr 52 Dedemsvaart NL.08 7701 CG",
    "addr:housenumber":"52;nl.08",
    "addr:postcode":"7701 cg",
    "addr:street":"Moerheimstr",
    "iso:country":"NL",
    "sg:address":"Moerheimstr 52",
    "sg:city":"Dedemsvaart",
    "sg:orig_category":"Fietsen En Bromfietsen",
    "sg:phone":"+31 523 612 525",
    "sg:postcode":"7701 CG",
    "sg:province":"NL.08",
    "wof:name":"Duinkerken Vof, J H",
    "wof:placetype":"venue"
},
  "geometry": {"coordinates":[6.462533,52.600407],"type":"Point"}
}