{
  "type": "Feature",
  "properties": {
    "addr:full":"Van Boetzelaerlaan 286 'S Gravenhage Zuid-Holland 2581 BC",
    "addr:housenumber":"286 '",
    "addr:postcode":"2581 bc",
    "addr:street":"Van Boetzelaerlaan",
    "iso:country":"NL",
    "sg:address":"Van Boetzelaerlaan 286",
    "sg:city":"'S Gravenhage",
    "sg:orig_category":"Overheidsdiensten",
    "sg:phone":"+31 70 355 2439",
    "sg:postcode":"2581 BC",
    "sg:province":"Zuid-Holland",
    "wof:name":"Thabor",
    "wof:placetype":"venue"
},
  "geometry": {"coordinates":[4.2701249123,52.0952453613],"type":"Point"}
}