{
  "type": "Feature",
  "properties": {
    "addr:full":"De Raat 28 Houten Utrecht 3995 EP",
    "addr:housenumber":"28",
    "addr:postcode":"3995 ep",
    "addr:street":"De Raat",
    "iso:country":"NL",
    "sg:address":"De Raat 28",
    "sg:city":"Houten",
    "sg:orig_category":"Woninginrichting",
    "sg:phone":"+31 30 637 1022",
    "sg:postcode":"3995 EP",
    "sg:province":"Utrecht",
    "wof:name":"Decorette",
    "wof:placetype":"venue"
},
  "geometry": {"coordinates":[5.1684088707,52.035823822],"type":"Point"}
}