{
  "type": "Feature",
  "properties": {
    "iso:country":"NL",
    "sg:address":"Glacisweg 26",
    "sg:city":"Maastricht",
    "sg:orig_category":"Fotostudio'S And Fotografen",
    "sg:phone":"+31 43 321 9676",
    "sg:postcode":"6212 BP",
    "sg:province":"Limburg",
    "wof:name":"Foto Harry Disch Jr",
    "wof:placetype":"venue"
},
  "geometry": {"coordinates":[5.691816,50.839855],"type":"Point"}
}