{
  "type": "Feature",
  "properties": {
    "addr:full":"Bautersemstr 38 S Gravenhage Zuid-Holland 2518 PC",
    "addr:housenumber":"38;gravenhage",
    "addr:postcode":"2518 pc",
    "addr:street":"Bautersemstr;S",
    "iso:country":"NL",
    "sg:address":"Bautersemstr 38",
    "sg:city":"S Gravenhage",
    "sg:classifiers":[
        {
            "category":"Professional",
            "subcategory":"Management & Consulting",
            "type":"Services"
        }
    ],
    "sg:phone":"+31 70 365 2123",
    "sg:postcode":"2518 PC",
    "sg:province":"Zuid-Holland",
    "sg:tags":[
        "relation",
        "adviesbureaus",
        "public"
    ],
    "sg:website":"http://www.baltuscom.nl",
    "wof:name":"Baltus",
    "wof:placetype":"venue"
},
  "geometry": {"coordinates":[4.29348,52.080318],"type":"Point"}
}