{
  "type": "Feature",
  "properties": {
    "addr:full":"Stationstraat 16 Heerlen Limburg 6411 NH",
    "addr:housenumber":"16",
    "addr:postcode":"6411 nh",
    "addr:street":"Stationstraat",
    "iso:country":"NL",
    "sg:address":"Stationstraat 16",
    "sg:city":"Heerlen",
    "sg:classifiers":[
        {
            "category":"Travel",
            "subcategory":"Hotels & Motels",
            "type":"Entertainment"
        }
    ],
    "sg:phone":"+31 45 571 9063",
    "sg:postcode":"6411 NH",
    "sg:province":"Limburg",
    "wof:name":"Hotel De La Station",
    "wof:placetype":"venue"
},
  "geometry": {"coordinates":[5.978422,50.889759],"type":"Point"}
}