{
  "type": "Feature",
  "properties": {
    "iso:country":"NL",
    "sg:address":"Maaseikerw 173",
    "sg:city":"Weert",
    "sg:orig_category":"Pluimveebedrijven En -Handelaren",
    "sg:phone":"+31 495 536 110",
    "sg:postcode":"6005 AD",
    "sg:province":"Limburg",
    "wof:name":"Saes, L H J",
    "wof:placetype":"venue"
},
  "geometry": {"coordinates":[5.721074,51.234329],"type":"Point"}
}