{
  "type": "Feature",
  "properties": {
    "addr:full":"Memlingstraat 5 Amersfoort Utrecht 3817 DK",
    "addr:housenumber":"5",
    "addr:postcode":"3817 dk",
    "addr:street":"Memlingstraat",
    "iso:country":"NL",
    "sg:address":"Memlingstraat 5",
    "sg:city":"Amersfoort",
    "sg:orig_category":"Autoverhuur",
    "sg:phone":"+31 33 461 5916",
    "sg:postcode":"3817 DK",
    "sg:province":"Utrecht",
    "wof:name":"Autoverhuur Van Dusschoten Bv",
    "wof:placetype":"venue"
},
  "geometry": {"coordinates":[5.39252,52.149334],"type":"Point"}
}