{
  "type": "Feature",
  "properties": {
    "addr:full":"Cor Van Der Bokstraat 1 Baarle Nassau Noord-Brabant 5111 VC",
    "addr:housenumber":"1",
    "addr:postcode":"5111 vc",
    "addr:street":"Cor Van Der Bokstraat",
    "iso:country":"NL",
    "sg:address":"Cor Van Der Bokstraat 1",
    "sg:city":"Baarle Nassau",
    "sg:classifiers":[
        {
            "category":"Education",
            "subcategory":"Preschool",
            "type":"Public Place"
        }
    ],
    "sg:phone":"+31 13 507 9453",
    "sg:postcode":"5111 VC",
    "sg:province":"Noord-Brabant",
    "sg:tags":[
        "kleuteronderwijs",
        "basis-"
    ],
    "wof:name":"Basisschool De Akkerwinde",
    "wof:placetype":"venue"
},
  "geometry": {"coordinates":[4.930059,51.444897],"type":"Point"}
}