{
  "type": "Feature",
  "properties": {
    "iso:country":"NL",
    "sg:address":"Philip Vingboonsstraat 187",
    "sg:city":"Rotterdam",
    "sg:orig_category":"Loodgieterswerk, Verwarming And Sanitaire Installaties",
    "sg:phone":"+31 10 220 0260",
    "sg:postcode":"3067 ZB",
    "sg:province":"Zuid-Holland",
    "wof:name":"Mbk",
    "wof:placetype":"venue"
},
  "geometry": {"coordinates":[4.538331,51.938988],"type":"Point"}
}