{
  "type": "Feature",
  "properties": {
    "addr:full":"Honingerdijk 70 Rotterdam Zuid-Holland 3062 NW",
    "addr:housenumber":"70",
    "addr:postcode":"3062 nw",
    "addr:street":"Honingerdijk",
    "iso:country":"NL",
    "sg:address":"Honingerdijk 70",
    "sg:city":"Rotterdam",
    "sg:orig_category":"Diverse Grafische Activiteiten",
    "sg:phone":"+31 10 890 9820",
    "sg:postcode":"3062 NW",
    "sg:province":"Zuid-Holland",
    "wof:name":"Krakatau Bv",
    "wof:placetype":"venue"
},
  "geometry": {"coordinates":[4.516901,51.918415],"type":"Point"}
}