{
  "type": "Feature",
  "properties": {
    "iso:country":"NL",
    "sg:address":"Wolfsenwaard 49",
    "sg:city":"Westervoort",
    "sg:classifiers":[
        {
            "category":"Retail",
            "subcategory":"Auto Repair",
            "type":"Services"
        }
    ],
    "sg:phone":"+31 26 311 6825",
    "sg:postcode":"6932 BK",
    "sg:province":"Gelderland",
    "sg:tags":[
        "garage"
    ],
    "wof:name":"Alexandria",
    "wof:placetype":"venue"
},
  "geometry": {"coordinates":[5.983013,51.953693],"type":"Point"}
}