{
  "type": "Feature",
  "properties": {
    "addr:full":"Mijnzetelln 6 Heerlen Limburg 6412 EN",
    "addr:housenumber":"6",
    "addr:postcode":"6412 en",
    "addr:street":"Mijnzetelln",
    "iso:country":"NL",
    "sg:address":"Mijnzetelln 6",
    "sg:city":"Heerlen",
    "sg:orig_category":"Verenigingsgebouwen",
    "sg:phone":"+31 45 572 2950",
    "sg:postcode":"6412 EN",
    "sg:province":"Limburg",
    "wof:name":"Gemeenschapshuis Zeswegen",
    "wof:placetype":"venue"
},
  "geometry": {"coordinates":[5.957889,50.898804],"type":"Point"}
}