{
  "type": "Feature",
  "properties": {
    "addr:full":"Cellostr 20 Amersfoort Utrecht 3822 CB",
    "addr:housenumber":"20",
    "addr:postcode":"3822 cb",
    "addr:street":"Cellostr",
    "iso:country":"NL",
    "sg:address":"Cellostr 20",
    "sg:city":"Amersfoort",
    "sg:orig_category":"Adviesbureaus Bedrijfsorganisatie",
    "sg:phone":"+31 6 51310808",
    "sg:postcode":"3822 CB",
    "sg:province":"Utrecht",
    "wof:name":"Zadelhoff",
    "wof:placetype":"venue"
},
  "geometry": {"coordinates":[5.403993,52.181644],"type":"Point"}
}