{
  "type": "Feature",
  "properties": {
    "addr:full":"Paradijspoort 58 Delft Zuid-Holland 2611 MB",
    "addr:housenumber":"58",
    "addr:postcode":"2611 mb",
    "addr:street":"Paradijspoort",
    "iso:country":"NL",
    "sg:address":"Paradijspoort 58",
    "sg:city":"Delft",
    "sg:classifiers":[
        {
            "category":"Shopping",
            "subcategory":"Clothing, Apparel, & Fashions",
            "type":"Retail Goods"
        }
    ],
    "sg:phone":"+31 15 214 4182",
    "sg:postcode":"2611 MB",
    "sg:province":"Zuid-Holland",
    "sg:tags":[
        "ondergoed",
        "lingerie"
    ],
    "wof:name":"Hunkemoller",
    "wof:placetype":"venue"
},
  "geometry": {"coordinates":[4.362924,52.009521],"type":"Point"}
}