{
  "type": "Feature",
  "properties": {
    "iso:country":"NL",
    "sg:address":"Arenbergln 271",
    "sg:city":"Breda",
    "sg:orig_category":"Meubelen",
    "sg:phone":"+31 76 549 7286",
    "sg:postcode":"4822 ZP",
    "sg:province":"Noord-Brabant",
    "wof:name":"Mierlo, Van",
    "wof:placetype":"venue"
},
  "geometry": {"coordinates":[4.726235,51.606468],"type":"Point"}
}