{
  "type": "Feature",
  "properties": {
    "addr:full":"S Vestdykstr 13 Hengelo Ov NL.08 7552 NR",
    "addr:housenumber":"13",
    "addr:postcode":"7552",
    "addr:street":"Ov;Nr",
    "iso:country":"NL",
    "sg:address":"S Vestdykstr 13",
    "sg:city":"Hengelo Ov",
    "sg:orig_category":"Oldtimers",
    "sg:phone":"+31 74 291 8772",
    "sg:postcode":"7552 NR",
    "sg:province":"NL.08",
    "sg:website":"HTTP://www.kevermobiel.nl",
    "wof:name":"Kever-Mobiel",
    "wof:placetype":"venue"
},
  "geometry": {"coordinates":[6.78971,52.266331],"type":"Point"}
}