{
  "type": "Feature",
  "properties": {
    "addr:full":"Industriestraat 2 Strijen Zuid-Holland 3291 CC",
    "addr:housenumber":"2",
    "addr:postcode":"3291 cc",
    "addr:street":"Industriestraat",
    "iso:country":"NL",
    "sg:address":"Industriestraat 2",
    "sg:city":"Strijen",
    "sg:orig_category":"Loodgieters- And Verwarmingsmateriaal Gh",
    "sg:phone":"+31 78 674 1444",
    "sg:postcode":"3291 CC",
    "sg:province":"Zuid-Holland",
    "wof:name":"Snikkers Handel Mij Bv",
    "wof:placetype":"venue"
},
  "geometry": {"coordinates":[4.55352,51.750496],"type":"Point"}
}