{
  "type": "Feature",
  "properties": {
    "iso:country":"NL",
    "sg:address":"Kleine Heitrak 7",
    "sg:city":"Asten",
    "sg:orig_category":"Landbouwmachines Gh",
    "sg:phone":"+31 493 341 722",
    "sg:postcode":"5721 SB",
    "sg:province":"North Brabant",
    "wof:name":"Van Den Eerenbeemt",
    "wof:placetype":"venue"
},
  "geometry": {"coordinates":[5.839849,51.389],"type":"Point"}
}