{
  "type": "Feature",
  "properties": {
    "iso:country":"NL",
    "sg:address":"Knaphof 1",
    "sg:city":"Lewedorp",
    "sg:orig_category":"Adviesbureaus Bouwkunde",
    "sg:phone":"+31 113 670 077",
    "sg:postcode":"4456 VX",
    "sg:province":"Zeeland",
    "wof:name":"Kok, Bouwkundig Adviesbureau J F De",
    "wof:placetype":"venue"
},
  "geometry": {"coordinates":[3.761398,51.470943],"type":"Point"}
}