{
  "type": "Feature",
  "properties": {
    "addr:full":"Kruisstraat 6 Diever Drenthe 7981 AR",
    "addr:housenumber":"6",
    "addr:postcode":"7981",
    "addr:street":"Kruisstraat",
    "iso:country":"NL",
    "sg:address":"Kruisstraat 6",
    "sg:city":"Diever",
    "sg:classifiers":[
        {
            "category":"Food & Beverages",
            "subcategory":"Fruits & Vegetables",
            "type":"Retail Goods"
        }
    ],
    "sg:phone":"+31 521 591 486",
    "sg:postcode":"7981 AR",
    "sg:province":"Drenthe",
    "sg:tags":[
        "groenten"
    ],
    "wof:name":"Fa Kamp En Co",
    "wof:placetype":"venue"
},
  "geometry": {"coordinates":[6.319934,52.855907],"type":"Point"}
}