{
  "type": "Feature",
  "properties": {
    "addr:full":"Franciscuswg 219 Hilversum North Holland 1216 SE",
    "addr:housenumber":"219",
    "addr:postcode":"1216 se",
    "iso:country":"NL",
    "sg:address":"Franciscuswg 219",
    "sg:city":"Hilversum",
    "sg:orig_category":"Omroep",
    "sg:phone":"+31 35 671 8718",
    "sg:postcode":"1216 SE",
    "sg:province":"North Holland",
    "sg:website":"http://www.hmg.net",
    "wof:name":"Rtl/Holland Media Groep Sa",
    "wof:placetype":"venue"
},
  "geometry": {"coordinates":[5.146357,52.214123],"type":"Point"}
}