{
  "type": "Feature",
  "properties": {
    "addr:full":"V M Kooystr 10D Amsterdam North Holland 1096 BR",
    "addr:housenumber":"10d",
    "addr:postcode":"1096 br",
    "iso:country":"NL",
    "sg:address":"V M Kooystr 10D",
    "sg:city":"Amsterdam",
    "sg:orig_category":"Verlichtingsartikelen - Fabrieken",
    "sg:phone":"+31 20 463 8861",
    "sg:postcode":"1096 BR",
    "sg:province":"North Holland",
    "sg:website":"http://www.danielsproducts.nl",
    "wof:name":"Daniels Products",
    "wof:placetype":"venue"
},
  "geometry": {"coordinates":[4.89319,52.373119],"type":"Point"}
}