{
  "type": "Feature",
  "properties": {
    "addr:full":"Elzenstraat 14 Drunen North Brabant 5151 AS",
    "addr:housenumber":"14",
    "addr:postcode":"5151 as",
    "addr:street":"Elzenstraat",
    "iso:country":"NL",
    "sg:address":"Elzenstraat 14",
    "sg:city":"Drunen",
    "sg:orig_category":"Fotostudio'S And Fotografen",
    "sg:phone":"+31 416 378 773",
    "sg:postcode":"5151 AS",
    "sg:province":"North Brabant",
    "wof:name":"Beter Photo",
    "wof:placetype":"venue"
},
  "geometry": {"coordinates":[5.124149,51.690166],"type":"Point"}
}