{
  "type": "Feature",
  "properties": {
    "iso:country":"NL",
    "sg:address":"Seinedreef 44",
    "sg:city":"Utrecht",
    "sg:orig_category":"Schoenen",
    "sg:phone":"+31 30 262 7877",
    "sg:postcode":"3562 KR",
    "sg:province":"Utrecht",
    "wof:name":"Bristol",
    "wof:placetype":"venue"
},
  "geometry": {"coordinates":[5.110452,52.113255],"type":"Point"}
}