{
  "type": "Feature",
  "properties": {
    "addr:full":"Seinedreef 44 Utrecht Utrecht 3562 KR",
    "addr:housenumber":"44",
    "addr:postcode":"3562 kr",
    "addr:street":"Seinedreef",
    "iso:country":"NL",
    "sg:address":"Seinedreef 44",
    "sg:city":"Utrecht",
    "sg:orig_category":"Schoenen",
    "sg:phone":"+31 30 262 7877",
    "sg:postcode":"3562 KR",
    "sg:province":"Utrecht",
    "wof:name":"Bristol",
    "wof:placetype":"venue"
},
  "geometry": {"coordinates":[5.110452,52.113255],"type":"Point"}
}