{
  "type": "Feature",
  "properties": {
    "addr:full":"Steenstr 152 Boxmeer Noord-Brabant 5831 JK",
    "addr:housenumber":"152",
    "addr:postcode":"5831 jk",
    "iso:country":"NL",
    "sg:address":"Steenstr 152",
    "sg:city":"Boxmeer",
    "sg:orig_category":"Notarissen En Notariskantoren",
    "sg:phone":"+31 485 573 472",
    "sg:postcode":"5831 JK",
    "sg:province":"Noord-Brabant",
    "wof:name":"Melis & Teeuwen",
    "wof:placetype":"venue"
},
  "geometry": {"coordinates":[5.946564,51.648617],"type":"Point"}
}