{
  "type": "Feature",
  "properties": {
    "addr:full":"Panamaln 144 Amsterdam North Holland 1019 AZ",
    "addr:housenumber":"144",
    "addr:postcode":"1019 az",
    "iso:country":"NL",
    "sg:address":"Panamaln 144",
    "sg:city":"Amsterdam",
    "sg:orig_category":"Luchtbehandelings- Apparaten",
    "sg:phone":"+31 20 675 0352",
    "sg:postcode":"1019 AZ",
    "sg:province":"North Holland",
    "wof:name":"Interpianotech Europe",
    "wof:placetype":"venue"
},
  "geometry": {"coordinates":[4.941788,52.372623],"type":"Point"}
}