{
  "type": "Feature",
  "properties": {
    "iso:country":"NL",
    "sg:address":"Legewg 22A",
    "sg:city":"Dokkum",
    "sg:orig_category":"Bruidskleding",
    "sg:phone":"+31 519 222 636",
    "sg:postcode":"9101 MC",
    "sg:province":"Friesland",
    "wof:name":"Bon Courage Bruidsboutique",
    "wof:placetype":"venue"
},
  "geometry": {"coordinates":[5.996184,53.324986],"type":"Point"}
}