{
  "type": "Feature",
  "properties": {
    "addr:full":"Walravenstraat 8 Ravenstein Noord-Brabant 5371 EK",
    "addr:housenumber":"8",
    "addr:postcode":"5371 ek",
    "addr:street":"Walravenstraat",
    "iso:country":"NL",
    "sg:address":"Walravenstraat 8",
    "sg:city":"Ravenstein",
    "sg:orig_category":"Meubelreparatie And -Restauratie",
    "sg:phone":"+31 486 412 508",
    "sg:postcode":"5371 EK",
    "sg:province":"Noord-Brabant",
    "wof:name":"Meubelstoffeerdersbedrijf E.H. Schuyling",
    "wof:placetype":"venue"
},
  "geometry": {"coordinates":[5.653193,51.792385],"type":"Point"}
}