{
  "type": "Feature",
  "properties": {
    "addr:full":"Oude Doetinchemseweg 40 Zeddam Gelderland 7038 BJ",
    "addr:housenumber":"40",
    "addr:postcode":"7038 bj",
    "addr:street":"Oude Doetinchemseweg;Gelderland",
    "iso:country":"NL",
    "sg:address":"Oude Doetinchemseweg 40",
    "sg:city":"Zeddam",
    "sg:orig_category":"Granen, Zaden And Diervoeders Gh",
    "sg:phone":"+31 314 651 549",
    "sg:postcode":"7038 BJ",
    "sg:province":"Gelderland",
    "wof:name":"Vof Klein Obbink",
    "wof:placetype":"venue"
},
  "geometry": {"coordinates":[6.26328,51.906124],"type":"Point"}
}