{
  "type": "Feature",
  "properties": {
    "iso:country":"NL",
    "sg:address":"Oude Doetinchemseweg 40",
    "sg:city":"Zeddam",
    "sg:orig_category":"Granen, Zaden And Diervoeders Gh",
    "sg:phone":"+31 314 651 549",
    "sg:postcode":"7038 BJ",
    "sg:province":"Gelderland",
    "wof:name":"Vof Klein Obbink",
    "wof:placetype":"venue"
},
  "geometry": {"coordinates":[6.26328,51.906124],"type":"Point"}
}