{
  "type": "Feature",
  "properties": {
    "addr:full":"Thornstr 3 Kerk Avezaath Gelderland 4012 EJ",
    "addr:housenumber":"3",
    "addr:postcode":"4012 ej",
    "addr:street":"Thornstr",
    "iso:country":"NL",
    "sg:address":"Thornstr 3",
    "sg:city":"Kerk Avezaath",
    "sg:orig_category":"Schilders",
    "sg:phone":"+31 344 682 818",
    "sg:postcode":"4012 EJ",
    "sg:province":"Gelderland",
    "wof:name":"Burens",
    "wof:placetype":"venue"
},
  "geometry": {"coordinates":[5.378908,51.898224],"type":"Point"}
}