{
  "type": "Feature",
  "properties": {
    "addr:full":"Haarstraat 21 Gorinchem Zuid-Holland 4201 JA",
    "addr:housenumber":"21",
    "addr:postcode":"4201 ja",
    "addr:street":"Haarstraat",
    "iso:country":"NL",
    "sg:address":"Haarstraat 21",
    "sg:city":"Gorinchem",
    "sg:orig_category":"Kappers",
    "sg:phone":"+31 183 636 811",
    "sg:postcode":"4201 JA",
    "sg:province":"Zuid-Holland",
    "wof:name":"Haarkoning",
    "wof:placetype":"venue"
},
  "geometry": {"coordinates":[4.9727511406,51.8309135437],"type":"Point"}
}