{
  "type": "Feature",
  "properties": {
    "addr:full":"Bernadotteln 195 Haarlem Noord-Holland 2037 GP",
    "addr:housenumber":"195",
    "addr:postcode":"2037 gp",
    "iso:country":"NL",
    "sg:address":"Bernadotteln 195",
    "sg:city":"Haarlem",
    "sg:classifiers":[
        {
            "category":"Food & Beverages",
            "subcategory":"Bakery",
            "type":"Retail Goods"
        }
    ],
    "sg:phone":"+31 23 535 4344",
    "sg:postcode":"2037 GP",
    "sg:province":"Noord-Holland",
    "sg:tags":[
        "pizza"
    ],
    "wof:name":"Orchidee",
    "wof:placetype":"venue"
},
  "geometry": {"coordinates":[4.66426,52.353531],"type":"Point"}
}