{
  "type": "Feature",
  "properties": {
    "addr:full":"Loosterweg Zuid 23 Lisse Zuid-Holland 2161 DT",
    "addr:housenumber":"23",
    "addr:postcode":"2161 dt",
    "addr:street":"Loosterweg Zuid",
    "iso:country":"NL",
    "sg:address":"Loosterweg Zuid 23",
    "sg:city":"Lisse",
    "sg:orig_category":"Bloemen And Planten Gh",
    "sg:phone":"+31 252 230 556",
    "sg:postcode":"2161 DT",
    "sg:province":"Zuid-Holland",
    "wof:name":"Fa W Van Der Salm En Zn",
    "wof:placetype":"venue"
},
  "geometry": {"coordinates":[4.521874,52.250751],"type":"Point"}
}