{
  "type": "Feature",
  "properties": {
    "addr:full":"Verwersdijk 4 Delft Zuid-Holland 2611 NH",
    "addr:housenumber":"4",
    "addr:postcode":"2611 nh",
    "addr:street":"Verwersdijk",
    "iso:country":"NL",
    "sg:address":"Verwersdijk 4",
    "sg:city":"Delft",
    "sg:orig_category":"Meubelzaken, Woning- And Keukeninrichting",
    "sg:phone":"+31 15 212 0132",
    "sg:postcode":"2611 NH",
    "sg:province":"Zuid-Holland",
    "wof:name":"Okido",
    "wof:placetype":"venue"
},
  "geometry": {"coordinates":[4.358292,52.014027],"type":"Point"}
}