{
  "type": "Feature",
  "properties": {
    "addr:full":"Haarstraat 187 Gorinchem Zuid-Holland 4201 JB",
    "addr:housenumber":"187",
    "addr:postcode":"4201 jb",
    "addr:street":"Haarstraat",
    "iso:country":"NL",
    "sg:address":"Haarstraat 187",
    "sg:city":"Gorinchem",
    "sg:orig_category":"Bejaardeninstellingen And Serviceflats",
    "sg:phone":"+31 183 636 677",
    "sg:postcode":"4201 JB",
    "sg:province":"Zuid-Holland",
    "wof:name":"De Lindeborg",
    "wof:placetype":"venue"
},
  "geometry": {"coordinates":[4.973273,51.831749],"type":"Point"}
}