{
  "type": "Feature",
  "properties": {
    "addr:full":"Plein 1969 7 Heeswyk Dinther Noord-Brabant 5473 CA",
    "addr:housenumber":"7;dinther",
    "addr:postcode":"5473 ca",
    "addr:street":"Plein 1969",
    "iso:country":"NL",
    "sg:address":"Plein 1969 7",
    "sg:city":"Heeswyk Dinther",
    "sg:orig_category":"Woninginrichting",
    "sg:phone":"+31 413 292 057",
    "sg:postcode":"5473 CA",
    "sg:province":"Noord-Brabant",
    "wof:name":"Zoggel, Van",
    "wof:placetype":"venue"
},
  "geometry": {"coordinates":[5.4739217758,51.6502456665],"type":"Point"}
}