{
  "type": "Feature",
  "properties": {
    "addr:full":"Maasdamstraat 2A Rotterdam Zuid-Holland 3081 EG",
    "addr:housenumber":"2a",
    "addr:postcode":"3081 eg",
    "addr:street":"Maasdamstraat",
    "iso:country":"NL",
    "sg:address":"Maasdamstraat 2A",
    "sg:city":"Rotterdam",
    "sg:orig_category":"Werving And Selectie Van Tijdelijk Personeel And Uitzendkantoren",
    "sg:phone":"+31 10 215 0904",
    "sg:postcode":"3081 EG",
    "sg:province":"Zuid-Holland",
    "wof:name":"Creyf'S",
    "wof:placetype":"venue"
},
  "geometry": {"coordinates":[4.4900159836,51.8927879333],"type":"Point"}
}