{
  "type": "Feature",
  "properties": {
    "iso:country":"NL",
    "sg:address":"M Ter Braakpln 24",
    "sg:city":"Gorinchem",
    "sg:orig_category":"Woningstoffeerders",
    "sg:phone":"+31 183 627 783",
    "sg:postcode":"4207 PP",
    "sg:province":"South Holland",
    "wof:name":"Goosens Woningstoffeerbedrijf",
    "wof:placetype":"venue"
},
  "geometry": {"coordinates":[4.9892339706,51.8386039734],"type":"Point"}
}