{
  "type": "Feature",
  "properties": {
    "addr:full":"M Ter Braakpln 24 Gorinchem South Holland 4207 PP",
    "addr:housenumber":"24",
    "addr:postcode":"4207 pp",
    "addr:street":"M",
    "iso:country":"NL",
    "sg:address":"M Ter Braakpln 24",
    "sg:city":"Gorinchem",
    "sg:orig_category":"Woningstoffeerders",
    "sg:phone":"+31 183 627 783",
    "sg:postcode":"4207 PP",
    "sg:province":"South Holland",
    "wof:name":"Goosens Woningstoffeerbedrijf",
    "wof:placetype":"venue"
},
  "geometry": {"coordinates":[4.9892339706,51.8386039734],"type":"Point"}
}