{
  "type": "Feature",
  "properties": {
    "addr:full":"Burg Falkenawg 35 Heerenveen Friesland 8442 KX",
    "addr:housenumber":"35",
    "addr:postcode":"8442 kx",
    "addr:street":"Burg",
    "iso:country":"NL",
    "sg:address":"Burg Falkenawg 35",
    "sg:city":"Heerenveen",
    "sg:orig_category":"Zonweringen",
    "sg:phone":"+31 6 13413585",
    "sg:postcode":"8442 KX",
    "sg:province":"Friesland",
    "wof:name":"Haitsma Zonweringen",
    "wof:placetype":"venue"
},
  "geometry": {"coordinates":[5.928439,52.955914],"type":"Point"}
}