{
  "type": "Feature",
  "properties": {
    "addr:full":"Akeleistr 13 Beuningen Gld Gelderland 6641 AS",
    "addr:housenumber":"13",
    "addr:postcode":"6641 as",
    "addr:street":"Akeleistr",
    "iso:country":"NL",
    "sg:address":"Akeleistr 13",
    "sg:city":"Beuningen Gld",
    "sg:orig_category":"Psychologen",
    "sg:phone":"+31 24 677 2228",
    "sg:postcode":"6641 AS",
    "sg:province":"Gelderland",
    "wof:name":"Oele, A A",
    "wof:placetype":"venue"
},
  "geometry": {"coordinates":[5.778419,51.861572],"type":"Point"}
}