{
  "type": "Feature",
  "properties": {
    "addr:full":"De Hofstede 12 Lienden Gelderland 4033 BT",
    "addr:housenumber":"12",
    "addr:postcode":"4033 bt",
    "addr:street":"De Hofstede;Gelderland",
    "iso:country":"NL",
    "sg:address":"De Hofstede 12",
    "sg:city":"Lienden",
    "sg:orig_category":"Meubelmakerijen",
    "sg:phone":"+31 344 603 791",
    "sg:postcode":"4033 BT",
    "sg:province":"Gelderland",
    "wof:name":"Ret, De",
    "wof:placetype":"venue"
},
  "geometry": {"coordinates":[5.517342,51.941284],"type":"Point"}
}