{
  "type": "Feature",
  "properties": {
    "iso:country":"NL",
    "sg:address":"Noorder Leidsevaart 32",
    "sg:city":"Hillegom",
    "sg:orig_category":"Bloemen And Planten Gh",
    "sg:phone":"+31 252 515 600",
    "sg:postcode":"2182 NB",
    "sg:province":"Zuid-Holland",
    "wof:name":"John De Groot Bv",
    "wof:placetype":"venue"
},
  "geometry": {"coordinates":[4.560969,52.305408],"type":"Point"}
}