{
  "type": "Feature",
  "properties": {
    "iso:country":"NL",
    "sg:address":"Pr Hendrikstr 59",
    "sg:city":"Gouda",
    "sg:orig_category":"Kappers",
    "sg:phone":"+31 182 519 488",
    "sg:postcode":"2802 JB",
    "sg:province":"South Holland",
    "wof:name":"Leeflang, C",
    "wof:placetype":"venue"
},
  "geometry": {"coordinates":[4.70422,52.007626],"type":"Point"}
}