{
  "type": "Feature",
  "properties": {
    "addr:full":"Vloeieind 21 Lage Mierde Noord-Brabant 5094 CL",
    "addr:housenumber":"21",
    "addr:postcode":"5094",
    "addr:street":"Vloeieind",
    "iso:country":"NL",
    "sg:address":"Vloeieind 21",
    "sg:city":"Lage Mierde",
    "sg:orig_category":"Goederenvervoer Over De Weg",
    "sg:phone":"+31 13 509 2465",
    "sg:postcode":"5094 CL",
    "sg:province":"Noord-Brabant",
    "wof:name":"Van Limpt Transport",
    "wof:placetype":"venue"
},
  "geometry": {"coordinates":[5.152129,51.39809],"type":"Point"}
}