{
  "type": "Feature",
  "properties": {
    "iso:country":"NL",
    "sg:address":"Rietlanden 1",
    "sg:city":"Beverwyk",
    "sg:orig_category":"Verhuur",
    "sg:phone":"+31 251 218 727",
    "sg:postcode":"1948 NE",
    "sg:province":"North Holland",
    "sg:website":"http://www.partysupport.nl",
    "wof:name":"Party Support",
    "wof:placetype":"venue"
},
  "geometry": {"coordinates":[4.658714,52.475555],"type":"Point"}
}