{
  "type": "Feature",
  "properties": {
    "iso:country":"NL",
    "sg:address":"Rokin 64",
    "sg:city":"Amsterdam",
    "sg:orig_category":"Vertaal- And Tolkenbureaus",
    "sg:phone":"+31 20 622 8551",
    "sg:postcode":"1012 KW",
    "sg:province":"North Holland",
    "wof:name":"Kaijhan Cs Tolken & Vertalers",
    "wof:placetype":"venue"
},
  "geometry": {"coordinates":[4.892373,52.370647],"type":"Point"}
}