{
  "type": "Feature",
  "properties": {
    "addr:full":"Boylestr 20 S Gravenhage South Holland 2563 EK",
    "addr:housenumber":"20",
    "addr:postcode":"2563 ek",
    "addr:street":"Boylestr;S Gravenhage",
    "iso:country":"NL",
    "sg:address":"Boylestr 20",
    "sg:city":"S Gravenhage",
    "sg:orig_category":"Verenigingen En Stichtingen",
    "sg:phone":"+31 70 365 3903",
    "sg:postcode":"2563 EK",
    "sg:province":"South Holland",
    "wof:name":"Fed Eekta, Sticht",
    "wof:placetype":"venue"
},
  "geometry": {"coordinates":[4.270956,52.072578],"type":"Point"}
}