{
  "type": "Feature",
  "properties": {
    "addr:full":"Garderenstr 14 Tilburg Noord-Brabant 5043 NG",
    "addr:housenumber":"14",
    "addr:postcode":"5043 ng",
    "addr:street":"Garderenstr",
    "iso:country":"NL",
    "sg:address":"Garderenstr 14",
    "sg:city":"Tilburg",
    "sg:orig_category":"Artsen - Specialisten Oogheelkunde",
    "sg:phone":"+31 13 570 2484",
    "sg:postcode":"5043 NG",
    "sg:province":"Noord-Brabant",
    "wof:name":"Tromp Bv, J F",
    "wof:placetype":"venue"
},
  "geometry": {"coordinates":[5.009794,51.583248],"type":"Point"}
}