{
  "type": "Feature",
  "properties": {
    "iso:country":"NL",
    "sg:address":"La Bonne Aventure 68",
    "sg:city":"Roermond",
    "sg:orig_category":"Adviesbureaus Bedrijfsorganisatie",
    "sg:phone":"+31 475 310 508",
    "sg:postcode":"6041 MC",
    "sg:province":"Limburg",
    "wof:name":"Pmm",
    "wof:placetype":"venue"
},
  "geometry": {"coordinates":[5.980685,51.194397],"type":"Point"}
}