{
  "type": "Feature",
  "properties": {
    "iso:country":"NL",
    "sg:address":"Kerkstraat 19",
    "sg:city":"Nunhem",
    "sg:orig_category":"Hoefdierhouderijen",
    "sg:phone":"+31 475 591 692",
    "sg:postcode":"6083 AD",
    "sg:province":"Limburg",
    "wof:name":"G. Vullers Hengstenhouderij Bv",
    "wof:placetype":"venue"
},
  "geometry": {"coordinates":[5.966999,51.24229],"type":"Point"}
}