{
  "type": "Feature",
  "properties": {
    "addr:full":"Wilhelminastr 42 Didam Gelderland 6942 BM",
    "addr:housenumber":"42",
    "addr:postcode":"6942 bm",
    "addr:street":"Wilhelminastr;Gelderland",
    "iso:country":"NL",
    "sg:address":"Wilhelminastr 42",
    "sg:city":"Didam",
    "sg:orig_category":"Hypotheken",
    "sg:phone":"+31 316 221 351",
    "sg:postcode":"6942 BM",
    "sg:province":"Gelderland",
    "wof:name":"Gerrits Lammers",
    "wof:placetype":"venue"
},
  "geometry": {"coordinates":[6.128752,51.936459],"type":"Point"}
}