{
  "type": "Feature",
  "properties": {
    "addr:full":"Staalwg 19 Culemborg Gelderland 4104 AS",
    "addr:housenumber":"19",
    "addr:postcode":"4104 as",
    "addr:street":"Staalwg;Gelderland",
    "iso:country":"NL",
    "sg:address":"Staalwg 19",
    "sg:city":"Culemborg",
    "sg:orig_category":"Kenteken- En Nummerplaten - Fabrieken",
    "sg:phone":"+31 345 521 326",
    "sg:postcode":"4104 AS",
    "sg:province":"Gelderland",
    "wof:name":"Kirpestein Bv",
    "wof:placetype":"venue"
},
  "geometry": {"coordinates":[5.217805,51.943375],"type":"Point"}
}