{
  "type": "Feature",
  "properties": {
    "iso:country":"NL",
    "sg:address":"Alsacelaan 85",
    "sg:city":"Eindhoven",
    "sg:orig_category":"Diverse Grafische Activiteiten",
    "sg:phone":"+31 40 256 8010",
    "sg:postcode":"5627 CB",
    "sg:province":"Noord-Brabant",
    "wof:name":"Progressive Impressions International",
    "wof:placetype":"venue"
},
  "geometry": {"coordinates":[5.442608,51.484318],"type":"Point"}
}