{
  "type": "Feature",
  "properties": {
    "addr:full":"Bolwerkswg 12 Zutphen Gelderland 7202 AH",
    "addr:housenumber":"12",
    "addr:postcode":"7202 ah",
    "addr:street":"Bolwerkswg;Gelderland",
    "iso:country":"NL",
    "sg:address":"Bolwerkswg 12",
    "sg:city":"Zutphen",
    "sg:classifiers":[
        {
            "category":"Retail",
            "subcategory":"Auto Repair",
            "type":"Services"
        }
    ],
    "sg:phone":"+31 575 513 372",
    "sg:postcode":"7202 AH",
    "sg:province":"Gelderland",
    "sg:tags":[
        "garage"
    ],
    "wof:name":"Poirri?",
    "wof:placetype":"venue"
},
  "geometry": {"coordinates":[6.190018,52.14666],"type":"Point"}
}