{
  "type": "Feature",
  "properties": {
    "addr:full":"Hoger Einde Zuid 26 Ouderkerk A/D Amstel North Holland 1191 AH",
    "addr:housenumber":"26;a / d",
    "addr:postcode":"1191 ah",
    "addr:street":"Hoger Einde Zuid;Amstel North",
    "iso:country":"NL",
    "sg:address":"Hoger Einde Zuid 26",
    "sg:city":"Ouderkerk A/D Amstel",
    "sg:orig_category":"Meubelzaken, Woning- And Keukeninrichting",
    "sg:phone":"+31 20 496 1988",
    "sg:postcode":"1191 AH",
    "sg:province":"North Holland",
    "wof:name":"Verwie Bv",
    "wof:placetype":"venue"
},
  "geometry": {"coordinates":[4.900785,52.298752],"type":"Point"}
}