{
  "type": "Feature",
  "properties": {
    "addr:full":"Lemsterpad 28 Lemmer Friesland 8531 AA",
    "addr:housenumber":"28",
    "addr:postcode":"8531 aa",
    "addr:street":"Lemsterpad",
    "iso:country":"NL",
    "sg:address":"Lemsterpad 28",
    "sg:city":"Lemmer",
    "sg:orig_category":"Meubelen - Fabrieken En Groothandel",
    "sg:phone":"+31 514 566 090",
    "sg:postcode":"8531 AA",
    "sg:province":"Friesland",
    "sg:website":"http://www.indexfurniture.nl",
    "wof:name":"Index Furniture",
    "wof:placetype":"venue"
},
  "geometry": {"coordinates":[5.719923,52.837833],"type":"Point"}
}