{
  "type": "Feature",
  "properties": {
    "addr:full":"Hillenaarplnts 96 Ryswyk Zh Zuid-Holland 2284 VV",
    "addr:housenumber":"96",
    "addr:postcode":"2284 vv",
    "addr:street":"Hillenaarplnts",
    "iso:country":"NL",
    "sg:address":"Hillenaarplnts 96",
    "sg:city":"Ryswyk Zh",
    "sg:orig_category":"Autorijscholen",
    "sg:phone":"+31 70 394 2209",
    "sg:postcode":"2284 VV",
    "sg:province":"Zuid-Holland",
    "wof:name":"Izendoorn, P A",
    "wof:placetype":"venue"
},
  "geometry": {"coordinates":[4.31319,52.041302],"type":"Point"}
}