{
  "type": "Feature",
  "properties": {
    "addr:full":"V Heemstraln 33 Arnhem Gelderland 6814 KB",
    "addr:housenumber":"33",
    "addr:postcode":"6814 kb",
    "iso:country":"NL",
    "sg:address":"V Heemstraln 33",
    "sg:city":"Arnhem",
    "sg:orig_category":"Vertalers",
    "sg:phone":"+31 26 445 4527",
    "sg:postcode":"6814 KB",
    "sg:province":"Gelderland",
    "wof:name":"Ella Lever",
    "wof:placetype":"venue"
},
  "geometry": {"coordinates":[5.904585,51.985519],"type":"Point"}
}