{
  "type": "Feature",
  "properties": {
    "addr:full":"Generaal Maczekstraat 63 Breda Noord-Brabant 4818 BV",
    "addr:housenumber":"63",
    "addr:postcode":"4818 bv",
    "addr:street":"Generaal Maczekstraat",
    "iso:country":"NL",
    "sg:address":"Generaal Maczekstraat 63",
    "sg:city":"Breda",
    "sg:orig_category":"Bloemen And Planten",
    "sg:phone":"+31 76 514 4490",
    "sg:postcode":"4818 BV",
    "sg:province":"Noord-Brabant",
    "wof:name":"Bloembinderij Cees Van Eijck Bv",
    "wof:placetype":"venue"
},
  "geometry": {"coordinates":[4.788794,51.57959],"type":"Point"}
}