{
  "type": "Feature",
  "properties": {
    "addr:full":"Landpoortstr 11 Woudrichem Noord-Brabant 4285 AR",
    "addr:housenumber":"11",
    "addr:postcode":"4285",
    "addr:street":"Landpoortstr",
    "iso:country":"NL",
    "sg:address":"Landpoortstr 11",
    "sg:city":"Woudrichem",
    "sg:orig_category":"Schilders",
    "sg:phone":"+31 183 301 860",
    "sg:postcode":"4285 AR",
    "sg:province":"Noord-Brabant",
    "wof:name":"Combee & Zn, P",
    "wof:placetype":"venue"
},
  "geometry": {"coordinates":[5.003812,51.816765],"type":"Point"}
}