{
  "type": "Feature",
  "properties": {
    "addr:full":"Nieuwstraat 63 Purmerend Noord-Holland 1441 CL",
    "addr:housenumber":"63",
    "addr:postcode":"1441",
    "addr:street":"Nieuwstraat",
    "iso:country":"NL",
    "sg:address":"Nieuwstraat 63",
    "sg:city":"Purmerend",
    "sg:classifiers":[
        {
            "category":"Fast Food",
            "type":"Food & Drink"
        }
    ],
    "sg:phone":"+31 299 436 114",
    "sg:postcode":"1441 CL",
    "sg:province":"Noord-Holland",
    "sg:tags":[
        "afhaal",
        "restaurant"
    ],
    "wof:name":"Italiaans Restaurant Italia",
    "wof:placetype":"venue"
},
  "geometry": {"coordinates":[4.946374,52.508163],"type":"Point"}
}