{
  "type": "Feature",
  "properties": {
    "addr:full":"Hazelaarlaan 19 Berkel-Enschot Noord-Brabant 5056 XM",
    "addr:housenumber":"19",
    "addr:postcode":"5056 xm",
    "addr:street":"Hazelaarlaan",
    "iso:country":"NL",
    "sg:address":"Hazelaarlaan 19",
    "sg:city":"Berkel-Enschot",
    "sg:orig_category":"Kappers",
    "sg:phone":"+31 13 533 3532",
    "sg:postcode":"5056 XM",
    "sg:province":"Noord-Brabant",
    "wof:name":"Coby",
    "wof:placetype":"venue"
},
  "geometry": {"coordinates":[5.1506748199,51.5870513916],"type":"Point"}
}