{
  "type": "Feature",
  "properties": {
    "addr:full":"Rijksweg 65 Naarden Noord-Holland 1411 GE",
    "addr:housenumber":"65",
    "addr:postcode":"1411",
    "addr:street":"Rijksweg",
    "iso:country":"NL",
    "sg:address":"Rijksweg 65",
    "sg:city":"Naarden",
    "sg:orig_category":"Makelaars In Onroerend Goed",
    "sg:phone":"+31 35 694 4500",
    "sg:postcode":"1411 GE",
    "sg:province":"Noord-Holland",
    "wof:name":"Koudijs Makelaardij In Onroerende Goederen Bv",
    "wof:placetype":"venue"
},
  "geometry": {"coordinates":[5.152024,52.289459],"type":"Point"}
}