{
  "type": "Feature",
  "properties": {
    "iso:country":"NL",
    "sg:address":"1E Middellandstr 79A",
    "sg:city":"Rotterdam",
    "sg:orig_category":"Goudsmeden En Zilversmeden",
    "sg:phone":"+31 10 425 7429",
    "sg:postcode":"3021 BB",
    "sg:province":"Zuid-Holland",
    "wof:name":"Paloeloe",
    "wof:placetype":"venue"
},
  "geometry": {"coordinates":[4.461625,51.918964],"type":"Point"}
}