{
  "type": "Feature",
  "properties": {
    "iso:country":"NL",
    "sg:address":"Oerlesestr 19",
    "sg:city":"Tilburg",
    "sg:orig_category":"Koffie-Automaten",
    "sg:phone":"+31 13 581 0102",
    "sg:postcode":"5021 TS",
    "sg:province":"Noord-Brabant",
    "sg:website":"http://www.vankriekenkoffie.nl",
    "wof:name":"Krieken, Van",
    "wof:placetype":"venue"
},
  "geometry": {"coordinates":[5.08259,51.546722],"type":"Point"}
}