{
  "type": "Feature",
  "properties": {
    "addr:full":"Koelerweg 10 Harfsen Gelderland 7217 SR",
    "addr:housenumber":"10",
    "addr:postcode":"7217 sr",
    "addr:street":"Koelerweg;Gelderland",
    "iso:country":"NL",
    "sg:address":"Koelerweg 10",
    "sg:city":"Harfsen",
    "sg:orig_category":"Kappers",
    "sg:phone":"+31 573 431 892",
    "sg:postcode":"7217 SR",
    "sg:province":"Gelderland",
    "wof:name":"A.H. Kolkman-Marsman",
    "wof:placetype":"venue"
},
  "geometry": {"coordinates":[6.3207249641,52.190322876],"type":"Point"}
}