{
  "type": "Feature",
  "properties": {
    "addr:full":"Bieremaln 129 S Gravenhage 2497 AX",
    "addr:housenumber":"129",
    "addr:postcode":"2497 ax",
    "addr:street":"S Gravenhage",
    "iso:country":"NL",
    "sg:address":"Bieremaln 129",
    "sg:city":"S Gravenhage",
    "sg:orig_category":"Administratie- En Boekhoudkantoren",
    "sg:phone":"+31 70 336 8073",
    "sg:postcode":"2497 AX",
    "wof:name":"Groeneveld",
    "wof:placetype":"venue"
},
  "geometry": {"coordinates":[4.36602,52.035912],"type":"Point"}
}