{
  "type": "Feature",
  "properties": {
    "addr:full":"Polakwg 15F Ryswyk Zh Zuid-Holland 2288 GG",
    "addr:housenumber":"15f",
    "addr:postcode":"2288 gg",
    "addr:street":"Ryswyk",
    "iso:country":"NL",
    "sg:address":"Polakwg 15F",
    "sg:city":"Ryswyk Zh",
    "sg:orig_category":"Verenigingen En Stichtingen",
    "sg:phone":"+31 70 390 7646",
    "sg:postcode":"2288 GG",
    "sg:province":"Zuid-Holland",
    "wof:name":"Bbs",
    "wof:placetype":"venue"
},
  "geometry": {"coordinates":[4.32436,52.037251],"type":"Point"}
}