{
  "type": "Feature",
  "properties": {
    "addr:full":"Passage 17 Waddinxveen South Holland 2741 HB",
    "addr:housenumber":"17",
    "addr:postcode":"2741 hb",
    "addr:street":"Passage",
    "iso:country":"NL",
    "sg:address":"Passage 17",
    "sg:city":"Waddinxveen",
    "sg:orig_category":"Poeliers",
    "sg:phone":"+31 182 610 818",
    "sg:postcode":"2741 HB",
    "sg:province":"South Holland",
    "wof:name":"Martens, Ton",
    "wof:placetype":"venue"
},
  "geometry": {"coordinates":[4.651111,52.045036],"type":"Point"}
}