{
  "type": "Feature",
  "properties": {
    "addr:full":"Ruiterpad 18 Rhenen Utrecht 3911 SL",
    "addr:housenumber":"18",
    "addr:postcode":"3911 sl",
    "addr:street":"Ruiterpad",
    "iso:country":"NL",
    "sg:address":"Ruiterpad 18",
    "sg:city":"Rhenen",
    "sg:orig_category":"Boekhouders",
    "sg:phone":"+31 317 618 528",
    "sg:postcode":"3911 SL",
    "sg:province":"Utrecht",
    "wof:name":"De Groot",
    "wof:placetype":"venue"
},
  "geometry": {"coordinates":[5.587151,51.973286],"type":"Point"}
}