{
  "type": "Feature",
  "properties": {
    "addr:full":"Punterwg 5 Maastricht Limburg 6222 NW",
    "addr:housenumber":"5",
    "addr:postcode":"6222 nw",
    "addr:street":"Punterwg",
    "iso:country":"NL",
    "sg:address":"Punterwg 5",
    "sg:city":"Maastricht",
    "sg:orig_category":"Bloemen En Planten - Groothandel",
    "sg:phone":"+31 43 362 0888",
    "sg:postcode":"6222 NW",
    "sg:province":"Limburg",
    "wof:name":"Zandbergen Bv, Gebr",
    "wof:placetype":"venue"
},
  "geometry": {"coordinates":[5.707883,50.878895],"type":"Point"}
}