{
  "type": "Feature",
  "properties": {
    "addr:full":"Kloosterstr 13 St Annaland Zeeland 4697 CR",
    "addr:housenumber":"13",
    "addr:postcode":"4697 cr",
    "addr:street":"Kloosterstr",
    "iso:country":"NL",
    "sg:address":"Kloosterstr 13",
    "sg:city":"St Annaland",
    "sg:orig_category":"Bibliotheken En Leeszalen Openbare",
    "sg:phone":"+31 166 652 836",
    "sg:postcode":"4697 CR",
    "sg:province":"Zeeland",
    "wof:name":"Openb Bibliotheek",
    "wof:placetype":"venue"
},
  "geometry": {"coordinates":[4.100135,51.598373],"type":"Point"}
}