{
  "type": "Feature",
  "properties": {
    "addr:full":"Edeseweg 93 Bennekom Gelderland 6721 JS",
    "addr:housenumber":"93",
    "addr:postcode":"6721 js",
    "addr:street":"Edeseweg;Gelderland",
    "iso:country":"NL",
    "sg:address":"Edeseweg 93",
    "sg:city":"Bennekom",
    "sg:orig_category":"Makelaars In Onroerend Goed",
    "sg:phone":"+31 318 419 511",
    "sg:postcode":"6721 JS",
    "sg:province":"Gelderland",
    "wof:name":"Makelaarskantoor P Houweling",
    "wof:placetype":"venue"
},
  "geometry": {"coordinates":[5.674302,52.005764],"type":"Point"}
}