{
  "type": "Feature",
  "properties": {
    "addr:full":"Merelln 579 Maassluis Zuid-Holland 3145 EV",
    "addr:housenumber":"579",
    "addr:postcode":"3145 ev",
    "iso:country":"NL",
    "sg:address":"Merelln 579",
    "sg:city":"Maassluis",
    "sg:orig_category":"Scheepvaartservice- Bureaus",
    "sg:phone":"+31 10 592 2720",
    "sg:postcode":"3145 EV",
    "sg:province":"Zuid-Holland",
    "wof:name":"Engelsman, H W",
    "wof:placetype":"venue"
},
  "geometry": {"coordinates":[4.251202,51.924381],"type":"Point"}
}