{
  "type": "Feature",
  "properties": {
    "addr:full":"Hofveld 132 Apeldoorn Gelderland 7333 BM",
    "addr:housenumber":"132",
    "addr:postcode":"7333 bm",
    "addr:street":"Hofveld;Gelderland",
    "iso:country":"NL",
    "sg:address":"Hofveld 132",
    "sg:city":"Apeldoorn",
    "sg:orig_category":"Cafetaria'S",
    "sg:phone":"+31 55 533 4973",
    "sg:postcode":"7333 BM",
    "sg:province":"Gelderland",
    "wof:name":"Meerpaal, De",
    "wof:placetype":"venue"
},
  "geometry": {"coordinates":[5.965855,52.191021],"type":"Point"}
}