{
  "type": "Feature",
  "properties": {
    "addr:full":"Vogelkersstr 36 S Gravenhage Zuid-Holland 2565 CL",
    "addr:housenumber":"36;gravenhage",
    "addr:postcode":"2565",
    "addr:street":"Vogelkersstr;S",
    "iso:country":"NL",
    "sg:address":"Vogelkersstr 36",
    "sg:city":"S Gravenhage",
    "sg:orig_category":"Dtp",
    "sg:phone":"+31 70 363 6653",
    "sg:postcode":"2565 CL",
    "sg:province":"Zuid-Holland",
    "wof:name":"Sijpesteyn, C & G V",
    "wof:placetype":"venue"
},
  "geometry": {"coordinates":[4.26129,52.076382],"type":"Point"}
}