{
  "type": "Feature",
  "properties": {
    "iso:country":"NL",
    "sg:address":"Boothstr 1C",
    "sg:city":"Utrecht",
    "sg:orig_category":"Vakorganisaties",
    "sg:phone":"+31 30 231 2591",
    "sg:postcode":"3512 BT",
    "sg:province":"Utrecht",
    "wof:name":"Hoger Spoorwegpersoneel, Ver Van",
    "wof:placetype":"venue"
},
  "geometry": {"coordinates":[5.12226,52.094048],"type":"Point"}
}