{
  "type": "Feature",
  "properties": {
    "addr:full":"Planker 3 Asten Noord-Brabant 5721 VG",
    "addr:housenumber":"3",
    "addr:postcode":"5721 vg",
    "addr:street":"Planker",
    "iso:country":"NL",
    "sg:address":"Planker 3",
    "sg:city":"Asten",
    "sg:orig_category":"Metaalbekleding And -Behandeling",
    "sg:phone":"+31 493 695 664",
    "sg:postcode":"5721 VG",
    "sg:province":"Noord-Brabant",
    "wof:name":"Twan Van Bussel Fijnmetaal",
    "wof:placetype":"venue"
},
  "geometry": {"coordinates":[5.756588,51.413967],"type":"Point"}
}