{
  "type": "Feature",
  "properties": {
    "iso:country":"NL",
    "sg:address":"Noorddammerwg 1C",
    "sg:city":"De Kwakel",
    "sg:orig_category":"Oldtimers",
    "sg:phone":"+31 297 540 257",
    "sg:postcode":"1424 NV",
    "sg:province":"Noord-Holland",
    "wof:name":"Amaryllis Bv",
    "wof:placetype":"venue"
},
  "geometry": {"coordinates":[4.801063,52.248783],"type":"Point"}
}