{
  "type": "Feature",
  "properties": {
    "iso:country":"NL",
    "sg:address":"Molenwerf 28",
    "sg:city":"Koog A/D Zaan",
    "sg:classifiers":[
        {
            "category":"Bakery",
            "type":"Food & Drink"
        }
    ],
    "sg:phone":"+31 75 631 5350",
    "sg:postcode":"1541 WR",
    "sg:province":"Noord-Holland",
    "sg:tags":[
        "brood",
        "banket"
    ],
    "wof:name":"Echte Bakker Nic De Lange Bv",
    "wof:placetype":"venue"
},
  "geometry": {"coordinates":[4.800327,52.462425],"type":"Point"}
}