{
  "type": "Feature",
  "properties": {
    "addr:full":"Fazant 22 Raalte NL.08 8103 EL",
    "addr:housenumber":"22;nl.08",
    "addr:postcode":"8103 el",
    "addr:street":"Fazant",
    "iso:country":"NL",
    "sg:address":"Fazant 22",
    "sg:city":"Raalte",
    "sg:orig_category":"Zonnebank- En Solariumcentra",
    "sg:phone":"+31 572 361 290",
    "sg:postcode":"8103 EL",
    "sg:province":"NL.08",
    "wof:name":"Slender You Zonnestudio Ans",
    "wof:placetype":"venue"
},
  "geometry": {"coordinates":[6.284472,52.392799],"type":"Point"}
}