{
  "type": "Feature",
  "properties": {
    "addr:full":"Venneperstr 19 Nieuw Vennep Noord-Holland 2151 AP",
    "addr:housenumber":"19",
    "addr:postcode":"2151 ap",
    "addr:street":"Venneperstr;Nieuw Vennep",
    "iso:country":"NL",
    "sg:address":"Venneperstr 19",
    "sg:city":"Nieuw Vennep",
    "sg:orig_category":"Postkantoren",
    "sg:phone":"+31 252 672 211",
    "sg:postcode":"2151 AP",
    "sg:province":"Noord-Holland",
    "sg:website":"http://www.postkantoor.nl",
    "wof:name":"Postkantoor",
    "wof:placetype":"venue"
},
  "geometry": {"coordinates":[4.630891,52.264835],"type":"Point"}
}