{
  "type": "Feature",
  "properties": {
    "addr:full":"Postbus 156 Hilversum Noord-Holland 1200 AD",
    "addr:housenumber":"156",
    "addr:postcode":"1200 ad",
    "addr:street":"Postbus",
    "iso:country":"NL",
    "sg:address":"Postbus 156",
    "sg:city":"Hilversum",
    "sg:orig_category":"Verenigingen En Stichtingen",
    "sg:phone":"+31 35 624 9651",
    "sg:postcode":"1200 AD",
    "sg:province":"Noord-Holland",
    "wof:name":"S Ka N Fonds",
    "wof:placetype":"venue"
},
  "geometry": {"coordinates":[5.171,52.223991],"type":"Point"}
}