{
  "type": "Feature",
  "properties": {
    "addr:full":"Achtmaalseweg 23 Zundert Noord-Brabant 4881 VH",
    "addr:housenumber":"23",
    "addr:postcode":"4881 vh",
    "addr:street":"Achtmaalseweg",
    "iso:country":"NL",
    "sg:address":"Achtmaalseweg 23",
    "sg:city":"Zundert",
    "sg:orig_category":"Autokeuringen",
    "sg:phone":"+31 76 597 3209",
    "sg:postcode":"4881 VH",
    "sg:province":"Noord-Brabant",
    "wof:name":"Garage Mouws",
    "wof:placetype":"venue"
},
  "geometry": {"coordinates":[4.654692,51.468021],"type":"Point"}
}