{
  "type": "Feature",
  "properties": {
    "addr:full":"Veelakker 7 Eindhoven North Brabant 5625 WJ",
    "addr:housenumber":"7",
    "addr:postcode":"5625 wj",
    "addr:street":"Veelakker",
    "iso:country":"NL",
    "sg:address":"Veelakker 7",
    "sg:city":"Eindhoven",
    "sg:orig_category":"Montagebedrijven",
    "sg:phone":"+31 6 22977907",
    "sg:postcode":"5625 WJ",
    "sg:province":"North Brabant",
    "wof:name":"Groeneveld",
    "wof:placetype":"venue"
},
  "geometry": {"coordinates":[5.484518,51.470207],"type":"Point"}
}