{
  "type": "Feature",
  "properties": {
    "addr:full":"Landeweel 44 Wouw North Brabant 4724 CW",
    "addr:housenumber":"44",
    "addr:postcode":"4724 cw",
    "addr:street":"Landeweel",
    "iso:country":"NL",
    "sg:address":"Landeweel 44",
    "sg:city":"Wouw",
    "sg:orig_category":"Begrafenisondernemers",
    "sg:phone":"+31 165 303 074",
    "sg:postcode":"4724 CW",
    "sg:province":"North Brabant",
    "wof:name":"Begrafenis En Crematieondern Coppens Bv",
    "wof:placetype":"venue"
},
  "geometry": {"coordinates":[4.395779,51.524128],"type":"Point"}
}