{
  "type": "Feature",
  "properties": {
    "iso:country":"NL",
    "sg:address":"Landeweel 44",
    "sg:city":"Wouw",
    "sg:orig_category":"Begrafenisondernemers",
    "sg:phone":"+31 165 303 074",
    "sg:postcode":"4724 CW",
    "sg:province":"North Brabant",
    "wof:name":"Begrafenis En Crematieondern Coppens Bv",
    "wof:placetype":"venue"
},
  "geometry": {"coordinates":[4.395779,51.524128],"type":"Point"}
}