{
  "type": "Feature",
  "properties": {
    "iso:country":"NL",
    "sg:address":"Drenthehof 31",
    "sg:city":"Helmond",
    "sg:orig_category":"Kalligrafische Ateliers",
    "sg:phone":"+31 492 513 585",
    "sg:postcode":"5709 CJ",
    "sg:province":"North Brabant",
    "wof:name":"Scrittura",
    "wof:placetype":"venue"
},
  "geometry": {"coordinates":[5.707485199,51.4765167236],"type":"Point"}
}