{
  "type": "Feature",
  "properties": {
    "addr:full":"V Boisotring 101 Zoetermeer Zuid-Holland 2722 AB",
    "addr:housenumber":"101",
    "addr:postcode":"2722 ab",
    "addr:street":"Boisotring",
    "iso:country":"NL",
    "sg:address":"V Boisotring 101",
    "sg:city":"Zoetermeer",
    "sg:classifiers":[
        {
            "category":"Personal",
            "subcategory":"Nail Salon",
            "type":"Services"
        }
    ],
    "sg:phone":"+31 79 331 4388",
    "sg:postcode":"2722 AB",
    "sg:province":"Zuid-Holland",
    "sg:tags":[
        "pedicure"
    ],
    "wof:name":"Vederlicht",
    "wof:placetype":"venue"
},
  "geometry": {"coordinates":[4.51464,52.053829],"type":"Point"}
}