{
  "type": "Feature",
  "properties": {
    "iso:country":"NL",
    "sg:address":"Zuid Voorstraat 16",
    "sg:city":"'S Gravendeel",
    "sg:classifiers":[
        {
            "category":"Fast Food",
            "type":"Food & Drink"
        }
    ],
    "sg:phone":"+31 78 673 4096",
    "sg:postcode":"3295 BW",
    "sg:province":"Zuid-Holland",
    "sg:tags":[
        "afhaal",
        "restaurant"
    ],
    "wof:name":"Quickly",
    "wof:placetype":"venue"
},
  "geometry": {"coordinates":[4.618917,51.780071],"type":"Point"}
}