{
  "type": "Feature",
  "properties": {
    "addr:full":"Molenweg 23 Andijk North Holland 1619 ET",
    "addr:housenumber":"23",
    "addr:postcode":"1619 et",
    "addr:street":"Molenweg",
    "iso:country":"NL",
    "sg:address":"Molenweg 23",
    "sg:city":"Andijk",
    "sg:orig_category":"Goederenvervoer Over De Weg",
    "sg:phone":"+31 228 591 576",
    "sg:postcode":"1619 ET",
    "sg:province":"North Holland",
    "wof:name":"Firma W. Vink En Zoon",
    "wof:placetype":"venue"
},
  "geometry": {"coordinates":[5.188662,52.744446],"type":"Point"}
}