{
  "type": "Feature",
  "properties": {
    "addr:full":"Stadhuispln 6 Almelo Overijssel 7607 EK",
    "addr:housenumber":"6",
    "addr:postcode":"7607 ek",
    "addr:street":"Stadhuispln",
    "iso:country":"NL",
    "sg:address":"Stadhuispln 6",
    "sg:city":"Almelo",
    "sg:orig_category":"Verenigingen En Stichtingen",
    "sg:phone":"+31 546 813 534",
    "sg:postcode":"7607 EK",
    "sg:province":"Overijssel",
    "wof:name":"Swo Almelo",
    "wof:placetype":"venue"
},
  "geometry": {"coordinates":[6.663458,52.357651],"type":"Point"}
}