{
  "type": "Feature",
  "properties": {
    "addr:full":"Andromeda 24 Loon Op Zand North Brabant 5175 VL",
    "addr:housenumber":"24",
    "addr:postcode":"5175 vl",
    "addr:street":"Andromeda",
    "iso:country":"NL",
    "sg:address":"Andromeda 24",
    "sg:city":"Loon Op Zand",
    "sg:orig_category":"Kunststof Ramen",
    "sg:phone":"+31 416 365 290",
    "sg:postcode":"5175 VL",
    "sg:province":"North Brabant",
    "wof:name":"Voogt",
    "wof:placetype":"venue"
},
  "geometry": {"coordinates":[5.077456,51.626522],"type":"Point"}
}