{
  "type": "Feature",
  "properties": {
    "addr:full":"Regentesseln 283 S Gravenhage Zuid-Holland 2562 EB",
    "addr:housenumber":"283;gravenhage",
    "addr:postcode":"2562 eb",
    "addr:street":"S",
    "iso:country":"NL",
    "sg:address":"Regentesseln 283",
    "sg:city":"S Gravenhage",
    "sg:orig_category":"Webdesign Bureaus",
    "sg:phone":"+31 70 310 6880",
    "sg:postcode":"2562 EB",
    "sg:province":"Zuid-Holland",
    "sg:website":"http://www.xmen.nl",
    "wof:name":"Xmen",
    "wof:placetype":"venue"
},
  "geometry": {"coordinates":[4.2832598686,52.0750007629],"type":"Point"}
}