{
  "type": "Feature",
  "properties": {
    "addr:full":"Dr. Moonsweg 12 Beers Nb North Brabant 5437 BG",
    "addr:housenumber":"12",
    "addr:postcode":"5437",
    "iso:country":"NL",
    "sg:address":"Dr. Moonsweg 12",
    "sg:city":"Beers Nb",
    "sg:orig_category":"Fotostudio'S And Fotografen",
    "sg:phone":"+31 485 316 215",
    "sg:postcode":"5437 BG",
    "sg:province":"North Brabant",
    "wof:name":"G. Van Oosterom",
    "wof:placetype":"venue"
},
  "geometry": {"coordinates":[5.818827,51.726791],"type":"Point"}
}