{
  "type": "Feature",
  "properties": {
    "addr:full":"Noordeinde 46 S Gravenhage South Holland 2514 GJ",
    "addr:housenumber":"46",
    "addr:postcode":"2514 gj",
    "addr:street":"Noordeinde;S Gravenhage",
    "iso:country":"NL",
    "sg:address":"Noordeinde 46",
    "sg:city":"S Gravenhage",
    "sg:orig_category":"Woninginrichting",
    "sg:phone":"+31 70 365 9102",
    "sg:postcode":"2514 GJ",
    "sg:province":"South Holland",
    "sg:website":"http://www.lifestyle.nl",
    "wof:name":"Lifestyle",
    "wof:placetype":"venue"
},
  "geometry": {"coordinates":[4.3093500137,52.084148407],"type":"Point"}
}