{
  "type": "Feature",
  "properties": {
    "addr:full":"Zr Hilkerstr 9 S Hertogenbosch Noord-Brabant 5221 JG",
    "addr:housenumber":"9",
    "addr:postcode":"5221 jg",
    "addr:street":"Hilkerstr",
    "iso:country":"NL",
    "sg:address":"Zr Hilkerstr 9",
    "sg:city":"S Hertogenbosch",
    "sg:orig_category":"Alarminstallaties",
    "sg:phone":"+31 73 633 0266",
    "sg:postcode":"5221 JG",
    "sg:province":"Noord-Brabant",
    "wof:name":"Aat",
    "wof:placetype":"venue"
},
  "geometry": {"coordinates":[5.266362,51.724773],"type":"Point"}
}