{
  "type": "Feature",
  "properties": {
    "iso:country":"NL",
    "sg:address":"Govert Van Wijnkade 43",
    "sg:city":"Maassluis",
    "sg:classifiers":[
        {
            "category":"Retail",
            "subcategory":"Storage",
            "type":"Services"
        }
    ],
    "sg:phone":"+31 10 592 7639",
    "sg:postcode":"3144 EG",
    "sg:province":"Zuid-Holland",
    "sg:tags":[
        "opslag",
        "bewaring"
    ],
    "wof:name":"Hamag Magazijninrichting Bv",
    "wof:placetype":"venue"
},
  "geometry": {"coordinates":[4.2469778061,51.9170761108],"type":"Point"}
}