{
  "type": "Feature",
  "properties": {
    "addr:full":"Castellumstraat 13 Alphen A/D Rijn South Holland 2405 CB",
    "addr:housenumber":"13",
    "addr:postcode":"2405 cb",
    "addr:street":"Castellumstraat",
    "iso:country":"NL",
    "sg:address":"Castellumstraat 13",
    "sg:city":"Alphen A/D Rijn",
    "sg:orig_category":"Werving And Selectie Van Tijdelijk Personeel And Uitzendkantoren",
    "sg:phone":"+31 172 470 240",
    "sg:postcode":"2405 CB",
    "sg:province":"South Holland",
    "wof:name":"Interim Personnel",
    "wof:placetype":"venue"
},
  "geometry": {"coordinates":[4.6599168777,52.128944397],"type":"Point"}
}