{
  "type": "Feature",
  "properties": {
    "addr:full":"Rheezerwg 73 Hardenberg Overijssel 7771 TD",
    "addr:housenumber":"73",
    "addr:postcode":"7771 td",
    "addr:street":"Rheezerwg",
    "iso:country":"NL",
    "sg:address":"Rheezerwg 73",
    "sg:city":"Hardenberg",
    "sg:orig_category":"Bejaarden - Verzorgingstehuizen",
    "sg:phone":"+31 523 265 577",
    "sg:postcode":"7771 TD",
    "sg:province":"Overijssel",
    "wof:name":"Clara Feyoena Heem",
    "wof:placetype":"venue"
},
  "geometry": {"coordinates":[6.598931,52.565102],"type":"Point"}
}