{
  "type": "Feature",
  "properties": {
    "addr:full":"Peperstraat 20 Elsloo Fr Friesland 8424 SJ",
    "addr:housenumber":"20",
    "addr:postcode":"8424",
    "addr:street":"Peperstraat",
    "iso:country":"NL",
    "sg:address":"Peperstraat 20",
    "sg:city":"Elsloo Fr",
    "sg:orig_category":"Architecten",
    "sg:phone":"+31 516 441 671",
    "sg:postcode":"8424 SJ",
    "sg:province":"Friesland",
    "wof:name":"Architectenburo Eckhardt & Leeuwenstein",
    "wof:placetype":"venue"
},
  "geometry": {"coordinates":[6.242507,52.957439],"type":"Point"}
}