{
  "type": "Feature",
  "properties": {
    "addr:full":"Puntkroos 5 Zwolle Overijssel 8043 NV",
    "addr:housenumber":"5",
    "addr:postcode":"8043 nv",
    "addr:street":"Puntkroos",
    "iso:country":"NL",
    "sg:address":"Puntkroos 5",
    "sg:city":"Zwolle",
    "sg:orig_category":"Schilders",
    "sg:phone":"+31 38 453 6301",
    "sg:postcode":"8043 NV",
    "sg:province":"Overijssel",
    "wof:name":"Beestman",
    "wof:placetype":"venue"
},
  "geometry": {"coordinates":[6.056809,52.541088],"type":"Point"}
}