{
  "type": "Feature",
  "properties": {
    "addr:full":"Arkendonk 5 Oosterhout Noord-Brabant 4907 XT",
    "addr:housenumber":"5",
    "addr:postcode":"4907 xt",
    "addr:street":"Arkendonk",
    "iso:country":"NL",
    "sg:address":"Arkendonk 5",
    "sg:city":"Oosterhout",
    "sg:orig_category":"Apotheken",
    "sg:phone":"+31 162 455 211",
    "sg:postcode":"4907 XT",
    "sg:province":"Noord-Brabant",
    "wof:name":"Dommelbergen",
    "wof:placetype":"venue"
},
  "geometry": {"coordinates":[4.864725,51.657768],"type":"Point"}
}