{
  "type": "Feature",
  "properties": {
    "addr:full":"Biezenbeemd 90 Oosterhout Nb Noord-Brabant 4907 EG",
    "addr:housenumber":"90",
    "addr:postcode":"4907 eg",
    "addr:street":"Biezenbeemd",
    "iso:country":"NL",
    "sg:address":"Biezenbeemd 90",
    "sg:city":"Oosterhout Nb",
    "sg:orig_category":"Administratie- En Boekhoudkantoren",
    "sg:phone":"+31 162 452 758",
    "sg:postcode":"4907 EG",
    "sg:province":"Noord-Brabant",
    "wof:name":"Marsman Administratiekantoor",
    "wof:placetype":"venue"
},
  "geometry": {"coordinates":[4.860261,51.658512],"type":"Point"}
}