{
  "type": "Feature",
  "properties": {
    "iso:country":"NL",
    "sg:address":"Koperslager 8C",
    "sg:city":"Eersel",
    "sg:orig_category":"Bedrijfskleding",
    "sg:phone":"+31 497 534 647",
    "sg:postcode":"5521 DE",
    "sg:province":"Noord-Brabant",
    "wof:name":"Denley Bv",
    "wof:placetype":"venue"
},
  "geometry": {"coordinates":[5.315883,51.364803],"type":"Point"}
}