{
  "type": "Feature",
  "properties": {
    "addr:full":"Steenwg 26 Utrecht Utrecht 3511 JR",
    "addr:housenumber":"26",
    "addr:postcode":"3511 jr",
    "addr:street":"Steenwg",
    "iso:country":"NL",
    "sg:address":"Steenwg 26",
    "sg:city":"Utrecht",
    "sg:orig_category":"Werving And Selectie Van Tijdelijk Personeel And Uitzendkantoren",
    "sg:phone":"+31 30 234 3888",
    "sg:postcode":"3511 JR",
    "sg:province":"Utrecht",
    "wof:name":"Ad Rem",
    "wof:placetype":"venue"
},
  "geometry": {"coordinates":[5.118519783,52.0907020569],"type":"Point"}
}