{
  "type": "Feature",
  "properties": {
    "addr:full":"St Ontcommerstr 24 Steenbergen Nb Noord-Brabant 4651 CR",
    "addr:housenumber":"24",
    "addr:postcode":"4651 cr",
    "iso:country":"NL",
    "sg:address":"St Ontcommerstr 24",
    "sg:city":"Steenbergen Nb",
    "sg:orig_category":"Begrafenisverzorging",
    "sg:phone":"+31 167 561 244",
    "sg:postcode":"4651 CR",
    "sg:province":"Noord-Brabant",
    "wof:name":"Hommel-De Maertelaere, A",
    "wof:placetype":"venue"
},
  "geometry": {"coordinates":[4.314555,51.585594],"type":"Point"}
}