{
  "type": "Feature",
  "properties": {
    "addr:full":"Noordzijde 2 Emmeloord NL. 8302 GL",
    "addr:housenumber":"2",
    "addr:postcode":"8302 gl",
    "addr:street":"Noordzijde;Nl.",
    "iso:country":"NL",
    "sg:address":"Noordzijde 2",
    "sg:city":"Emmeloord",
    "sg:orig_category":"Werving And Selectie Van Tijdelijk Personeel And Uitzendkantoren",
    "sg:phone":"+31 527 619 080",
    "sg:postcode":"8302 GL",
    "sg:province":"NL.",
    "wof:name":"Randstad Uitzendbureau",
    "wof:placetype":"venue"
},
  "geometry": {"coordinates":[5.7539582253,52.7118186951],"type":"Point"}
}