{
  "type": "Feature",
  "properties": {
    "addr:full":"Esschilderstr 31Rood Haarlem Noord-Holland 2012 BC",
    "addr:housenumber":"31rood",
    "addr:postcode":"2012 bc",
    "addr:street":"Esschilderstr",
    "iso:country":"NL",
    "sg:address":"Esschilderstr 31Rood",
    "sg:city":"Haarlem",
    "sg:orig_category":"Evenementenverzorging",
    "sg:phone":"+31 23 551 6860",
    "sg:postcode":"2012 BC",
    "sg:province":"Noord-Holland",
    "wof:name":"Crazy Cocktails",
    "wof:placetype":"venue"
},
  "geometry": {"coordinates":[4.636809,52.372185],"type":"Point"}
}