{
  "type": "Feature",
  "properties": {
    "addr:full":"Gevers Deynootweg 970 'S Gravenhage Zuid-Holland 2586 BW",
    "addr:housenumber":"970 '",
    "addr:postcode":"2586 bw",
    "addr:street":"Gevers Deynootweg",
    "iso:country":"NL",
    "sg:address":"Gevers Deynootweg 970",
    "sg:city":"'S Gravenhage",
    "sg:orig_category":"Boekhouders",
    "sg:phone":"+31 70 352 3634",
    "sg:postcode":"2586 BW",
    "sg:province":"Zuid-Holland",
    "wof:name":"Accountancy Kantoor A.G.E. Rietvelt",
    "wof:placetype":"venue"
},
  "geometry": {"coordinates":[4.284113,52.114285],"type":"Point"}
}