{
  "type": "Feature",
  "properties": {
    "iso:country":"NL",
    "sg:address":"De Haag 5",
    "sg:city":"Houten",
    "sg:orig_category":"Vakorganisaties",
    "sg:phone":"+31 30 639 4721",
    "sg:postcode":"3993 AV",
    "sg:province":"Utrecht",
    "sg:website":"http://www.vhpmetalektro.nl",
    "wof:name":"Vhp Metalektro",
    "wof:placetype":"venue"
},
  "geometry": {"coordinates":[5.168187,52.040134],"type":"Point"}
}