{
  "type": "Feature",
  "properties": {
    "addr:full":"Boddenkampsngl 140 Enschede Overijssel 7514 AS",
    "addr:housenumber":"140",
    "addr:postcode":"7514 as",
    "iso:country":"NL",
    "sg:address":"Boddenkampsngl 140",
    "sg:city":"Enschede",
    "sg:orig_category":"Verhuur",
    "sg:phone":"+31 53 435 4681",
    "sg:postcode":"7514 AS",
    "sg:province":"Overijssel",
    "wof:name":"Potkachel, De",
    "wof:placetype":"venue"
},
  "geometry": {"coordinates":[6.889823,52.228256],"type":"Point"}
}