{
  "type": "Feature",
  "properties": {
    "addr:full":"Spoorlaan 396 Tilburg North Brabant 5038 CG",
    "addr:housenumber":"396",
    "addr:postcode":"5038 cg",
    "addr:street":"Spoorlaan",
    "iso:country":"NL",
    "sg:address":"Spoorlaan 396",
    "sg:city":"Tilburg",
    "sg:orig_category":"Verplichte Sociale Verzekeringen",
    "sg:phone":"+31 13 537 6222",
    "sg:postcode":"5038 CG",
    "sg:province":"North Brabant",
    "wof:name":"Zorgverzekeraar Vgz",
    "wof:placetype":"venue"
},
  "geometry": {"coordinates":[5.085043,51.559891],"type":"Point"}
}