{
  "type": "Feature",
  "properties": {
    "iso:country":"NL",
    "sg:address":"Wenckebachwg 165",
    "sg:city":"Amsterdam",
    "sg:orig_category":"Parketvloeren",
    "sg:phone":"+31 20 668 1884",
    "sg:postcode":"1096 AM",
    "sg:province":"North Holland",
    "wof:name":"Albers Bv",
    "wof:placetype":"venue"
},
  "geometry": {"coordinates":[4.93378,52.335461],"type":"Point"}
}