{
  "type": "Feature",
  "properties": {
    "addr:full":"Kerkwg 30A Driebruggen Zuid-Holland 3465 JK",
    "addr:housenumber":"30a",
    "addr:postcode":"3465 jk",
    "addr:street":"Kerkwg",
    "iso:country":"NL",
    "sg:address":"Kerkwg 30A",
    "sg:city":"Driebruggen",
    "sg:orig_category":"Land- En Tuinbouw - Loonbedrijven",
    "sg:phone":"+31 6 54360533",
    "sg:postcode":"3465 JK",
    "sg:province":"Zuid-Holland",
    "wof:name":"Rodenburg, Hans",
    "wof:placetype":"venue"
},
  "geometry": {"coordinates":[4.797136,52.043915],"type":"Point"}
}