{
  "type": "Feature",
  "properties": {
    "addr:full":"Kaldenkerkerwg 100102 Venlo Limburg 5915 AE",
    "addr:housenumber":"100102",
    "addr:postcode":"5915 ae",
    "iso:country":"NL",
    "sg:address":"Kaldenkerkerwg 100102",
    "sg:city":"Venlo",
    "sg:orig_category":"Elektrotechnische Installatiebureaus",
    "sg:phone":"+31 77 351 4434",
    "sg:postcode":"5915 AE",
    "sg:province":"Limburg",
    "wof:name":"Nass, Gijs",
    "wof:placetype":"venue"
},
  "geometry": {"coordinates":[6.184358,51.34951],"type":"Point"}
}