{
  "type": "Feature",
  "properties": {
    "addr:full":"Groningerwg 62 Peize Drenthe 9321 TD",
    "addr:housenumber":"62",
    "addr:postcode":"9321 td",
    "addr:street":"Groningerwg",
    "iso:country":"NL",
    "sg:address":"Groningerwg 62",
    "sg:city":"Peize",
    "sg:orig_category":"Adviesbureaus Bouwkunde",
    "sg:phone":"+31 50 503 4952",
    "sg:postcode":"9321 TD",
    "sg:province":"Drenthe",
    "wof:name":"Laffrey",
    "wof:placetype":"venue"
},
  "geometry": {"coordinates":[6.503238,53.177227],"type":"Point"}
}