{
  "type": "Feature",
  "properties": {
    "addr:full":"Gronausestr 1078 Enschede NL.08 7534 AP",
    "addr:housenumber":"1078",
    "addr:postcode":"7534 ap",
    "iso:country":"NL",
    "sg:address":"Gronausestr 1078",
    "sg:city":"Enschede",
    "sg:classifiers":[
        {
            "category":"Food & Beverages",
            "subcategory":"Bakery",
            "type":"Retail Goods"
        }
    ],
    "sg:phone":"+31 53 461 7172",
    "sg:postcode":"7534 AP",
    "sg:province":"NL.08",
    "sg:tags":[
        "pizza"
    ],
    "wof:name":"Nuraghe, Il",
    "wof:placetype":"venue"
},
  "geometry": {"coordinates":[6.95486,52.2164],"type":"Point"}
}