{
  "type": "Feature",
  "properties": {
    "addr:full":"Gibraltarstr 61 Amsterdam Noord-Holland 1055 NK",
    "addr:housenumber":"61",
    "addr:postcode":"1055 nk",
    "addr:street":"Gibraltarstr",
    "iso:country":"NL",
    "sg:address":"Gibraltarstr 61",
    "sg:city":"Amsterdam",
    "sg:orig_category":"Scholen Voor Basisonderwijs",
    "sg:phone":"+31 20 682 2270",
    "sg:postcode":"1055 NK",
    "sg:province":"Noord-Holland",
    "wof:name":"Boomgaard Rk, De",
    "wof:placetype":"venue"
},
  "geometry": {"coordinates":[4.849985,52.38382],"type":"Point"}
}