{
  "type": "Feature",
  "properties": {
    "addr:full":"Kerkstraat 74 Zeeland Noord-Brabant 5411 BC",
    "addr:housenumber":"74",
    "addr:postcode":"5411 bc",
    "addr:street":"Kerkstraat",
    "iso:country":"NL",
    "sg:address":"Kerkstraat 74",
    "sg:city":"Zeeland",
    "sg:orig_category":"Kappers",
    "sg:phone":"+31 486 451 371",
    "sg:postcode":"5411 BC",
    "sg:province":"Noord-Brabant",
    "wof:name":"H.W.J.M. Derks",
    "wof:placetype":"venue"
},
  "geometry": {"coordinates":[5.675142765,51.698223114],"type":"Point"}
}