{
  "type": "Feature",
  "properties": {
    "iso:country":"NL",
    "sg:address":"Paul Gabrielstraat 131",
    "sg:city":"'S Gravenhage",
    "sg:orig_category":"Public Relationbureaus",
    "sg:phone":"+31 70 324 9502",
    "sg:postcode":"2596 VC",
    "sg:province":"South Holland",
    "wof:name":"Fa Chen Prod",
    "wof:placetype":"venue"
},
  "geometry": {"coordinates":[4.32653,52.094006],"type":"Point"}
}