{
  "type": "Feature",
  "properties": {
    "addr:full":"Leeuwerikstr 5 Berg En Terblyt Limburg 6325 BD",
    "addr:housenumber":"5",
    "addr:postcode":"6325 bd",
    "addr:street":"Leeuwerikstr;Limburg",
    "iso:country":"NL",
    "sg:address":"Leeuwerikstr 5",
    "sg:city":"Berg En Terblyt",
    "sg:orig_category":"Scholen Voor Basisonderwijs",
    "sg:phone":"+31 43 604 0729",
    "sg:postcode":"6325 BD",
    "sg:province":"Limburg",
    "wof:name":"Vilt",
    "wof:placetype":"venue"
},
  "geometry": {"coordinates":[5.805979,50.859604],"type":"Point"}
}