{
  "type": "Feature",
  "properties": {
    "addr:full":"Van Konijnenburgweg 17 Bergen Op Zoom Noord-Brabant 4611 HK",
    "addr:housenumber":"17",
    "addr:postcode":"4611 hk",
    "addr:street":"Van Konijnenburgweg",
    "iso:country":"NL",
    "sg:address":"Van Konijnenburgweg 17",
    "sg:city":"Bergen Op Zoom",
    "sg:orig_category":"Woninginrichting",
    "sg:phone":"+31 164 263 823",
    "sg:postcode":"4611 HK",
    "sg:province":"Noord-Brabant",
    "wof:name":"Kwantum",
    "wof:placetype":"venue"
},
  "geometry": {"coordinates":[4.278632164,51.4935150146],"type":"Point"}
}