{
  "type": "Feature",
  "properties": {
    "iso:country":"NL",
    "sg:address":"Julianastr 32",
    "sg:city":"Berkel En Rodenrys",
    "sg:orig_category":"Onderhoudswerken",
    "sg:phone":"+31 10 511 6480",
    "sg:postcode":"2651 DP",
    "sg:province":"Zuid-Holland",
    "wof:name":"Bloom",
    "wof:placetype":"venue"
},
  "geometry": {"coordinates":[4.480446,51.993698],"type":"Point"}
}