{
  "type": "Feature",
  "properties": {
    "addr:full":"Bisschopsmolenstr 120A Etten Leur Noord-Brabant 4876 AR",
    "addr:housenumber":"120a",
    "addr:postcode":"4876",
    "iso:country":"NL",
    "sg:address":"Bisschopsmolenstr 120A",
    "sg:city":"Etten Leur",
    "sg:orig_category":"Verloskundigen",
    "sg:phone":"+31 76 503 4167",
    "sg:postcode":"4876 AR",
    "sg:province":"Noord-Brabant",
    "wof:name":"Verloskundigenpraktijk Etten-Leur",
    "wof:placetype":"venue"
},
  "geometry": {"coordinates":[4.637494,51.565418],"type":"Point"}
}