{
  "type": "Feature",
  "properties": {
    "addr:full":"Postbus 407 Leeuwarden Friesland 8901 BE",
    "addr:housenumber":"407",
    "addr:postcode":"8901",
    "addr:street":"Postbus",
    "iso:country":"NL",
    "sg:address":"Postbus 407",
    "sg:city":"Leeuwarden",
    "sg:orig_category":"Levensmiddelen- Grondstoffen - Fabrieken En Groothandel",
    "sg:phone":"+31 58 294 8445",
    "sg:postcode":"8901 BE",
    "sg:province":"Friesland",
    "wof:name":"Laco",
    "wof:placetype":"venue"
},
  "geometry": {"coordinates":[5.79143,53.203049],"type":"Point"}
}