{
  "type": "Feature",
  "properties": {
    "iso:country":"NL",
    "sg:address":"Emmausstraat 3",
    "sg:city":"Sint Oedenrode",
    "sg:classifiers":[
        {
            "category":"Communications",
            "subcategory":"Television Station",
            "type":"Services"
        }
    ],
    "sg:phone":"+31 413 473 944",
    "sg:postcode":"5492 BK",
    "sg:province":"North Brabant",
    "sg:tags":[
        "video",
        "audio",
        "verhuur"
    ],
    "wof:name":"Videotheek Wagemaker",
    "wof:placetype":"venue"
},
  "geometry": {"coordinates":[5.458328,51.561428],"type":"Point"}
}