{
  "type": "Feature",
  "properties": {
    "iso:country":"NL",
    "sg:address":"Graafsebaan 40 B",
    "sg:city":"Rosmalen",
    "sg:orig_category":"Boekhouders",
    "sg:phone":"+31 73 522 1298",
    "sg:postcode":"5242 JM",
    "sg:province":"Noord-Brabant",
    "wof:name":"Haak Bv Administratiekantoor",
    "wof:placetype":"venue"
},
  "geometry": {"coordinates":[5.358016,51.703167],"type":"Point"}
}