{
  "type": "Feature",
  "properties": {
    "addr:full":"Hillegondastr 12 + 17 Rotterdam South Holland 3051 PB",
    "addr:housenumber":"12 + 17",
    "addr:postcode":"3051 pb",
    "addr:street":"Hillegondastr",
    "iso:country":"NL",
    "sg:address":"Hillegondastr 12 + 17",
    "sg:city":"Rotterdam",
    "sg:orig_category":"Open Haarden",
    "sg:phone":"+31 10 418 5047",
    "sg:postcode":"3051 PB",
    "sg:province":"South Holland",
    "wof:name":"Alphen, Van",
    "wof:placetype":"venue"
},
  "geometry": {"coordinates":[4.484442,51.945557],"type":"Point"}
}