{
  "type": "Feature",
  "properties": {
    "addr:full":"Nieuwendk 82-90 Amsterdam Noord-Holland 1012 MR",
    "addr:housenumber":"82-90",
    "addr:postcode":"1012 mr",
    "iso:country":"NL",
    "sg:address":"Nieuwendk 82-90",
    "sg:city":"Amsterdam",
    "sg:orig_category":"Gelegenheidskleding",
    "sg:phone":"+31 20 624 9402",
    "sg:postcode":"1012 MR",
    "sg:province":"Noord-Holland",
    "sg:website":"http://www.tipdebruin.nl",
    "wof:name":"Tip De Bruin",
    "wof:placetype":"venue"
},
  "geometry": {"coordinates":[4.896564,52.377037],"type":"Point"}
}