{
  "type": "Feature",
  "properties": {
    "addr:full":"Noorderhoofdstraat 32 Krommenie Noord-Holland 1561 AV",
    "addr:housenumber":"32",
    "addr:postcode":"1561 av",
    "addr:street":"Noorderhoofdstraat",
    "iso:country":"NL",
    "sg:address":"Noorderhoofdstraat 32",
    "sg:city":"Krommenie",
    "sg:classifiers":[
        {
            "category":"Fast Food",
            "type":"Food & Drink"
        }
    ],
    "sg:phone":"+31 75 628 1568",
    "sg:postcode":"1561 AV",
    "sg:province":"Noord-Holland",
    "sg:tags":[
        "afhaal",
        "restaurant"
    ],
    "wof:name":"Smikkelhof",
    "wof:placetype":"venue"
},
  "geometry": {"coordinates":[4.770016,52.500404],"type":"Point"}
}