{
  "type": "Feature",
  "properties": {
    "addr:full":"Land In Zicht 17 Almere Flevoland 1316 VJ",
    "addr:housenumber":"17",
    "addr:postcode":"1316 vj",
    "addr:street":"Land In Zicht;Flevoland",
    "iso:country":"NL",
    "sg:address":"Land In Zicht 17",
    "sg:city":"Almere",
    "sg:orig_category":"Psychotherapeuten",
    "sg:phone":"+31 36 534 5107",
    "sg:postcode":"1316 VJ",
    "sg:province":"Flevoland",
    "wof:name":"Hofstede-Slagter, J M H",
    "wof:placetype":"venue"
},
  "geometry": {"coordinates":[5.208593,52.393059],"type":"Point"}
}