{
  "type": "Feature",
  "properties": {
    "addr:full":"Nolderwg 1 Linde Dr Drenthe 7925 PE",
    "addr:housenumber":"1",
    "addr:postcode":"7925 pe",
    "addr:street":"Nolderwg;Linde Dr",
    "iso:country":"NL",
    "sg:address":"Nolderwg 1",
    "sg:city":"Linde Dr",
    "sg:classifiers":[
        {
            "category":"Sports & Exercise",
            "subcategory":"Stables",
            "type":"Entertainment"
        }
    ],
    "sg:phone":"+31 523 656 355",
    "sg:postcode":"7925 PE",
    "sg:province":"Drenthe",
    "sg:tags":[
        "maneges"
    ],
    "wof:name":"Nolder Hoefslag, De",
    "wof:placetype":"venue"
},
  "geometry": {"coordinates":[6.430908,52.631298],"type":"Point"}
}