{
  "type": "Feature",
  "properties": {
    "addr:full":"Praagsngl 133 Ysselstein Ut Utrecht 3404 VR",
    "addr:housenumber":"133",
    "addr:postcode":"3404 vr",
    "addr:street":"Ysselstein",
    "iso:country":"NL",
    "sg:address":"Praagsngl 133",
    "sg:city":"Ysselstein Ut",
    "sg:orig_category":"Schilders",
    "sg:phone":"+31 30 688 4768",
    "sg:postcode":"3404 VR",
    "sg:province":"Utrecht",
    "wof:name":"Elteren, J Van",
    "wof:placetype":"venue"
},
  "geometry": {"coordinates":[5.0281,52.02663],"type":"Point"}
}