{
  "type": "Feature",
  "properties": {
    "addr:full":"Hoornwg 66 Marum Groningen 9363 EH",
    "addr:housenumber":"66",
    "addr:postcode":"9363 eh",
    "addr:street":"Hoornwg",
    "iso:country":"NL",
    "sg:address":"Hoornwg 66",
    "sg:city":"Marum",
    "sg:orig_category":"Autorijscholen",
    "sg:phone":"+31 594 643 868",
    "sg:postcode":"9363 EH",
    "sg:province":"Groningen",
    "wof:name":"Wilpstra, H T",
    "wof:placetype":"venue"
},
  "geometry": {"coordinates":[6.255234,53.142845],"type":"Point"}
}