{
  "type": "Feature",
  "properties": {
    "iso:country":"NL",
    "sg:address":"Oordeelsestr 84",
    "sg:city":"Baarle Nassau",
    "sg:orig_category":"Loonbedrijven",
    "sg:phone":"+31 13 507 9249",
    "sg:postcode":"5111 PL",
    "sg:province":"Noord-Brabant",
    "wof:name":"Tilburg, Van",
    "wof:placetype":"venue"
},
  "geometry": {"coordinates":[4.9378,51.4459],"type":"Point"}
}