{
  "type": "Feature",
  "properties": {
    "iso:country":"NL",
    "sg:address":"Ekkersrijt 2052",
    "sg:city":"Son",
    "sg:classifiers":[
        {
            "category":"Retail",
            "subcategory":"Storage",
            "type":"Services"
        }
    ],
    "sg:phone":"+31 499 470 500",
    "sg:postcode":"5692 BA",
    "sg:province":"Noord-Brabant",
    "sg:tags":[
        "opslag",
        "bewaring"
    ],
    "wof:name":"M. Van Happen Container En Transport Bv",
    "wof:placetype":"venue"
},
  "geometry": {"coordinates":[-101.93762207029999,35.1896209717],"type":"Point"}
}