{
  "type": "Feature",
  "properties": {
    "addr:full":"Korvelsewg 174 Tilburg North Brabant 5025 JM",
    "addr:housenumber":"174",
    "addr:postcode":"5025 jm",
    "iso:country":"NL",
    "sg:address":"Korvelsewg 174",
    "sg:city":"Tilburg",
    "sg:orig_category":"Boeken En Tijdschriften",
    "sg:phone":"+31 13 545 7534",
    "sg:postcode":"5025 JM",
    "sg:province":"North Brabant",
    "sg:website":"http://www.boekelier.am.s.nl",
    "wof:name":"Boekelier, De",
    "wof:placetype":"venue"
},
  "geometry": {"coordinates":[5.070737,51.550205],"type":"Point"}
}