{
  "type": "Feature",
  "properties": {
    "addr:full":"Anthonie Van Leeuwenhoekstraat 1 Strijen Zuid-Holland 3291 CR",
    "addr:housenumber":"1;3291",
    "addr:postcode":"cr",
    "addr:street":"Anthonie Van Leeuwenhoekstraat",
    "iso:country":"NL",
    "sg:address":"Anthonie Van Leeuwenhoekstraat 1",
    "sg:city":"Strijen",
    "sg:orig_category":"Hout Gh",
    "sg:phone":"+31 78 674 8800",
    "sg:postcode":"3291 CR",
    "sg:province":"Zuid-Holland",
    "wof:name":"Van Der Sijde`S Houthandel",
    "wof:placetype":"venue"
},
  "geometry": {"coordinates":[4.553145,51.742794],"type":"Point"}
}