{
  "type": "Feature",
  "properties": {
    "iso:country":"NL",
    "sg:address":"Dorpsstraat 167",
    "sg:city":"Zevenhuizen Zh",
    "sg:orig_category":"Loodgieterswerk, Verwarming And Sanitaire Installaties",
    "sg:phone":"+31 180 631 206",
    "sg:postcode":"2761 AR",
    "sg:province":"Zuid-Holland",
    "wof:name":"P. Visser & Zonen",
    "wof:placetype":"venue"
},
  "geometry": {"coordinates":[4.579702,52.014542],"type":"Point"}
}