{
  "type": "Feature",
  "properties": {
    "addr:full":"Emmastr 70 Asten Noord-Brabant 5721 HD",
    "addr:housenumber":"70",
    "addr:postcode":"5721 hd",
    "addr:street":"Emmastr",
    "iso:country":"NL",
    "sg:address":"Emmastr 70",
    "sg:city":"Asten",
    "sg:orig_category":"Schilders",
    "sg:phone":"+31 493 691 736",
    "sg:postcode":"5721 HD",
    "sg:province":"Noord-Brabant",
    "wof:name":"Bekx Bv Glas- En Schildersbedrijf",
    "wof:placetype":"venue"
},
  "geometry": {"coordinates":[5.750776,51.401985],"type":"Point"}
}