{
  "type": "Feature",
  "properties": {
    "addr:full":"Dykwg 200 Andyk Noord-Holland 1619 JB",
    "addr:housenumber":"200",
    "addr:postcode":"1619 jb",
    "iso:country":"NL",
    "sg:address":"Dykwg 200",
    "sg:city":"Andyk",
    "sg:orig_category":"Handenarbeid",
    "sg:phone":"+31 228 592 311",
    "sg:postcode":"1619 JB",
    "sg:province":"Noord-Holland",
    "wof:name":"Winkeltje Van Greet, 'T",
    "wof:placetype":"venue"
},
  "geometry": {"coordinates":[5.222525,52.744362],"type":"Point"}
}