{
  "type": "Feature",
  "properties": {
    "addr:full":"Rietzanger 3 Veenendaal Utrecht 3906 NC",
    "addr:housenumber":"3",
    "addr:postcode":"3906 nc",
    "addr:street":"Rietzanger",
    "iso:country":"NL",
    "sg:address":"Rietzanger 3",
    "sg:city":"Veenendaal",
    "sg:orig_category":"Lasbedrijven",
    "sg:phone":"+31 318 550 515",
    "sg:postcode":"3906 NC",
    "sg:province":"Utrecht",
    "wof:name":"Geerink Welding",
    "wof:placetype":"venue"
},
  "geometry": {"coordinates":[5.527973,52.031193],"type":"Point"}
}