{
  "type": "Feature",
  "properties": {
    "iso:country":"NL",
    "sg:address":"Rietzanger 3",
    "sg:city":"Veenendaal",
    "sg:orig_category":"Lasbedrijven",
    "sg:phone":"+31 318 550 515",
    "sg:postcode":"3906 NC",
    "sg:province":"Utrecht",
    "wof:name":"Geerink Welding",
    "wof:placetype":"venue"
},
  "geometry": {"coordinates":[5.527973,52.031193],"type":"Point"}
}