{
  "type": "Feature",
  "properties": {
    "addr:full":"De Kloostertuin 48 Boxmeer Noord-Brabant 5831 JT",
    "addr:housenumber":"48",
    "addr:postcode":"5831 jt",
    "addr:street":"De Kloostertuin",
    "iso:country":"NL",
    "sg:address":"De Kloostertuin 48",
    "sg:city":"Boxmeer",
    "sg:orig_category":"Verlichting",
    "sg:phone":"+31 485 521 451",
    "sg:postcode":"5831 JT",
    "sg:province":"Noord-Brabant",
    "wof:name":"Berkvens, Jan",
    "wof:placetype":"venue"
},
  "geometry": {"coordinates":[5.950317,51.648895],"type":"Point"}
}