{
  "type": "Feature",
  "properties": {
    "iso:country":"NL",
    "sg:address":"A Cantastr 11",
    "sg:city":"Rotterdam",
    "sg:orig_category":"Adviesbureaus Bedrijfsorganisatie",
    "sg:phone":"+31 10 286 0625",
    "sg:postcode":"3066 HK",
    "sg:province":"Zuid-Holland",
    "wof:name":"Brons, Edu",
    "wof:placetype":"venue"
},
  "geometry": {"coordinates":[4.549594,51.930954],"type":"Point"}
}