{
  "type": "Feature",
  "properties": {
    "iso:country":"NL",
    "sg:address":"Nieuwe Erven 20",
    "sg:city":"Heesch",
    "sg:orig_category":"Autokeuringen",
    "sg:phone":"+31 412 452 265",
    "sg:postcode":"5384 TB",
    "sg:province":"North Brabant",
    "wof:name":"Jan Van Uden",
    "wof:placetype":"venue"
},
  "geometry": {"coordinates":[5.512091,51.725639],"type":"Point"}
}