{
  "type": "Feature",
  "properties": {
    "addr:full":"Slankweg 78 Enschede Overijssel 7532 PZ",
    "addr:housenumber":"78",
    "addr:postcode":"7532 pz",
    "addr:street":"Slankweg",
    "iso:country":"NL",
    "sg:address":"Slankweg 78",
    "sg:city":"Enschede",
    "sg:classifiers":[
        {
            "category":"Fast Food",
            "type":"Food & Drink"
        }
    ],
    "sg:phone":"+31 53 461 2904",
    "sg:postcode":"7532 PZ",
    "sg:province":"Overijssel",
    "sg:tags":[
        "afhaal",
        "restaurant"
    ],
    "wof:name":"Bestaria De Slank",
    "wof:placetype":"venue"
},
  "geometry": {"coordinates":[6.946235,52.219673],"type":"Point"}
}