{
  "type": "Feature",
  "properties": {
    "addr:full":"Groene Hilledijk 202 Rotterdam South Holland 3074 AB",
    "addr:housenumber":"202",
    "addr:postcode":"3074 ab",
    "addr:street":"Groene Hilledijk",
    "iso:country":"NL",
    "sg:address":"Groene Hilledijk 202",
    "sg:city":"Rotterdam",
    "sg:classifiers":[
        {
            "category":"Communications",
            "subcategory":"Television Station",
            "type":"Services"
        }
    ],
    "sg:phone":"+31 10 432 2212",
    "sg:postcode":"3074 AB",
    "sg:province":"South Holland",
    "sg:tags":[
        "video",
        "audio",
        "verhuur"
    ],
    "wof:name":"Videotheek Las Vegas",
    "wof:placetype":"venue"
},
  "geometry": {"coordinates":[4.509363,51.892609],"type":"Point"}
}