{
  "type": "Feature",
  "properties": {
    "iso:country":"NL",
    "sg:address":"Uitgang 2",
    "sg:city":"Drachten",
    "sg:orig_category":"Oud Papier",
    "sg:phone":"+31 512 515 834",
    "sg:postcode":"9202 NT",
    "sg:province":"Friesland",
    "wof:name":"Mast",
    "wof:placetype":"venue"
},
  "geometry": {"coordinates":[6.1119661331,53.101360321],"type":"Point"}
}