{
  "type": "Feature",
  "properties": {
    "addr:full":"Plaats 14 S Gravenhage Zuid-Holland 2513 AE",
    "addr:housenumber":"14;gravenhage",
    "addr:postcode":"2513 ae",
    "addr:street":"Plaats;S",
    "iso:country":"NL",
    "sg:address":"Plaats 14",
    "sg:city":"S Gravenhage",
    "sg:orig_category":"Herenkleding",
    "sg:phone":"+31 70 392 7951",
    "sg:postcode":"2513 AE",
    "sg:province":"Zuid-Holland",
    "sg:website":"http://www.vangils.tv",
    "wof:name":"Gils Store, Van",
    "wof:placetype":"venue"
},
  "geometry": {"coordinates":[4.30339,52.078442],"type":"Point"}
}