{
  "type": "Feature",
  "properties": {
    "addr:full":"Rivium Boulev 108 Capelle Ad Yssel Zuid-Holland 2909 LK",
    "addr:housenumber":"108;2909",
    "addr:postcode":"lk",
    "addr:street":"Rivium Boulev",
    "iso:country":"NL",
    "sg:address":"Rivium Boulev 108",
    "sg:city":"Capelle Ad Yssel",
    "sg:orig_category":"Arbo- En Bedrijfsgezondheids- Diensten",
    "sg:phone":"+31 10 429 6135",
    "sg:postcode":"2909 LK",
    "sg:province":"Zuid-Holland",
    "wof:name":"Intech Bv",
    "wof:placetype":"venue"
},
  "geometry": {"coordinates":[4.54677,51.913151],"type":"Point"}
}