{
  "type": "Feature",
  "properties": {
    "addr:full":"Nassaukd 1 Ryswyk Zh Zuid-Holland 2281 XA",
    "addr:housenumber":"1",
    "addr:postcode":"2281 xa",
    "addr:street":"Nassaukd",
    "iso:country":"NL",
    "sg:address":"Nassaukd 1",
    "sg:city":"Ryswyk Zh",
    "sg:orig_category":"Architecten En Architectenbureaus",
    "sg:phone":"+31 70 399 5777",
    "sg:postcode":"2281 XA",
    "sg:province":"Zuid-Holland",
    "wof:name":"Inbo Bv",
    "wof:placetype":"venue"
},
  "geometry": {"coordinates":[4.341704,52.056934],"type":"Point"}
}