{
  "type": "Feature",
  "properties": {
    "iso:country":"NL",
    "sg:address":"Erasmuswg 9",
    "sg:city":"Cadzand",
    "sg:orig_category":"Parkeergarages",
    "sg:phone":"+31 117 391 342",
    "sg:postcode":"4506 AA",
    "sg:province":"Zeeland",
    "wof:name":"Beach Deputy Service Bv",
    "wof:placetype":"venue"
},
  "geometry": {"coordinates":[3.410146,51.370655],"type":"Point"}
}