{
  "type": "Feature",
  "properties": {
    "addr:full":"Kroonenburg 76 Amersfoort Utrecht 3813 RN",
    "addr:housenumber":"76",
    "addr:postcode":"3813 rn",
    "addr:street":"Kroonenburg",
    "iso:country":"NL",
    "sg:address":"Kroonenburg 76",
    "sg:city":"Amersfoort",
    "sg:orig_category":"Grafische Bedrijven",
    "sg:phone":"+31 33 480 7369",
    "sg:postcode":"3813 RN",
    "sg:province":"Utrecht",
    "wof:name":"Timmerman",
    "wof:placetype":"venue"
},
  "geometry": {"coordinates":[5.387789,52.176327],"type":"Point"}
}