{
  "type": "Feature",
  "properties": {
    "addr:full":"Ondernemersstr 21 Ysselmuiden NL.08 8271 RS",
    "addr:housenumber":"21;8271",
    "addr:postcode":"rs",
    "addr:street":"Ondernemersstr",
    "iso:country":"NL",
    "sg:address":"Ondernemersstr 21",
    "sg:city":"Ysselmuiden",
    "sg:orig_category":"Loodgieters",
    "sg:phone":"+31 38 332 0012",
    "sg:postcode":"8271 RS",
    "sg:province":"NL.08",
    "wof:name":"Fien Bv, Installatiebedrijf",
    "wof:placetype":"venue"
},
  "geometry": {"coordinates":[5.939931,52.55434],"type":"Point"}
}