{
  "type": "Feature",
  "properties": {
    "addr:full":"Molenstraat 37 Budel North Brabant 6021 GT",
    "addr:housenumber":"37",
    "addr:postcode":"6021 gt",
    "addr:street":"Molenstraat",
    "iso:country":"NL",
    "sg:address":"Molenstraat 37",
    "sg:city":"Budel",
    "sg:orig_category":"Fietshandelaren",
    "sg:phone":"+31 495 491 385",
    "sg:postcode":"6021 GT",
    "sg:province":"North Brabant",
    "wof:name":"Jos Van Cranenbroek Jaspers",
    "wof:placetype":"venue"
},
  "geometry": {"coordinates":[5.569343,51.275475],"type":"Point"}
}