{
  "type": "Feature",
  "properties": {
    "addr:full":"Wilhelminastr 39A Breukelen Ut Utrecht 3621 VG",
    "addr:housenumber":"39a",
    "addr:postcode":"3621 vg",
    "addr:street":"Wilhelminastr",
    "iso:country":"NL",
    "sg:address":"Wilhelminastr 39A",
    "sg:city":"Breukelen Ut",
    "sg:orig_category":"Matrijzen",
    "sg:phone":"+31 346 265 050",
    "sg:postcode":"3621 VG",
    "sg:province":"Utrecht",
    "wof:name":"Smh Breukelen Bv",
    "wof:placetype":"venue"
},
  "geometry": {"coordinates":[5.001585,52.172958],"type":"Point"}
}