{
  "type": "Feature",
  "properties": {
    "addr:full":"H.J.E. Wenckebachweg 58 Amsterdam North Holland 1096 AN",
    "addr:housenumber":"58",
    "addr:postcode":"1096 an",
    "addr:street":"H.J.E. Wenckebachweg",
    "iso:country":"NL",
    "sg:address":"H.J.E. Wenckebachweg 58",
    "sg:city":"Amsterdam",
    "sg:orig_category":"Verlichting And Huishoudartikelen",
    "sg:phone":"+31 20 692 3924",
    "sg:postcode":"1096 AN",
    "sg:province":"North Holland",
    "wof:name":"Glasindustrie Kortijn Bv",
    "wof:placetype":"venue"
},
  "geometry": {"coordinates":[4.927346,52.33588],"type":"Point"}
}