{
  "type": "Feature",
  "properties": {
    "iso:country":"NL",
    "sg:address":"Beekln 343",
    "sg:city":"S Gravenhage",
    "sg:orig_category":"Koffie- En Theehuizen",
    "sg:phone":"+31 70 363 7677",
    "sg:postcode":"2562 AX",
    "sg:province":"South Holland",
    "wof:name":"Florence",
    "wof:placetype":"venue"
},
  "geometry": {"coordinates":[4.28326,52.075001],"type":"Point"}
}