{
  "type": "Feature",
  "properties": {
    "addr:full":"T Blok 175 Breda North Brabant 4823 JJ",
    "addr:housenumber":"175",
    "addr:postcode":"4823 jj",
    "addr:street":"T Blok",
    "iso:country":"NL",
    "sg:address":"T Blok 175",
    "sg:city":"Breda",
    "sg:classifiers":[
        {
            "category":"Education",
            "subcategory":"Preschool",
            "type":"Public Place"
        }
    ],
    "sg:phone":"+31 76 541 9404",
    "sg:postcode":"4823 JJ",
    "sg:province":"North Brabant",
    "sg:tags":[
        "kleuteronderwijs",
        "basis-"
    ],
    "wof:name":"Katholieke Basisschool Kievitsloop",
    "wof:placetype":"venue"
},
  "geometry": {"coordinates":[4.73705,51.625969],"type":"Point"}
}