{
  "type": "Feature",
  "properties": {
    "addr:full":"Buitenhaven 10B S Hertogenbosch Noord-Brabant 5211 TP",
    "addr:housenumber":"10b",
    "addr:postcode":"5211 tp",
    "addr:street":"Buitenhaven;S Hertogenbosch",
    "iso:country":"NL",
    "sg:address":"Buitenhaven 10B",
    "sg:city":"S Hertogenbosch",
    "sg:orig_category":"Homeopathie",
    "sg:phone":"+31 73 689 0239",
    "sg:postcode":"5211 TP",
    "sg:province":"Noord-Brabant",
    "wof:name":"Moll, H J P M",
    "wof:placetype":"venue"
},
  "geometry": {"coordinates":[5.299403,51.691296],"type":"Point"}
}