{
  "type": "Feature",
  "properties": {
    "addr:full":"Galvaniwg 10A Nunspeet Gelderland 8071 SC",
    "addr:housenumber":"10a",
    "addr:postcode":"8071",
    "addr:street":"Galvaniwg;Gelderland",
    "iso:country":"NL",
    "sg:address":"Galvaniwg 10A",
    "sg:city":"Nunspeet",
    "sg:classifiers":[
        {
            "category":"Food & Beverages",
            "subcategory":"Groceries & Convenience Stores",
            "type":"Retail Goods"
        }
    ],
    "sg:phone":"+31 341 264 426",
    "sg:postcode":"8071 SC",
    "sg:province":"Gelderland",
    "sg:tags":[
        "disposable"
    ],
    "sg:website":"http://www.altaircommerce.nl",
    "wof:name":"Altair Commerce Bv",
    "wof:placetype":"venue"
},
  "geometry": {"coordinates":[5.765987,52.375648],"type":"Point"}
}