{
  "type": "Feature",
  "properties": {
    "addr:full":"Limmerhoek 24C Alkmaar North Holland 1811 BA",
    "addr:housenumber":"24c",
    "addr:postcode":"1811 ba",
    "addr:street":"Limmerhoek",
    "iso:country":"NL",
    "sg:address":"Limmerhoek 24C",
    "sg:city":"Alkmaar",
    "sg:orig_category":"Verzekeringen - Verzekeringskantoren",
    "sg:phone":"+31 72 511 8870",
    "sg:postcode":"1811 BA",
    "sg:province":"North Holland",
    "wof:name":"Vlotman Bv",
    "wof:placetype":"venue"
},
  "geometry": {"coordinates":[4.753097,52.628277],"type":"Point"}
}