{
  "type": "Feature",
  "properties": {
    "iso:country":"NL",
    "sg:address":"Amstenraderwg 11",
    "sg:city":"Hoensbroek",
    "sg:orig_category":"Orthopedisch Schoeisel",
    "sg:phone":"+31 45 563 1533",
    "sg:postcode":"6431 EH",
    "sg:province":"Limburg",
    "wof:name":"Mertens",
    "wof:placetype":"venue"
},
  "geometry": {"coordinates":[5.927295208,50.9259910583],"type":"Point"}
}