{
  "type": "Feature",
  "properties": {
    "addr:full":"Swalm 22 Rotterdam South Holland 3068 LH",
    "addr:housenumber":"22",
    "addr:postcode":"3068 lh",
    "addr:street":"Swalm",
    "iso:country":"NL",
    "sg:address":"Swalm 22",
    "sg:city":"Rotterdam",
    "sg:orig_category":"Fotostudio'S And Fotografen",
    "sg:phone":"+31 10 456 6333",
    "sg:postcode":"3068 LH",
    "sg:province":"South Holland",
    "wof:name":"Fotogroothandel Kjp Netherlands Bv",
    "wof:placetype":"venue"
},
  "geometry": {"coordinates":[4.568545,51.958557],"type":"Point"}
}