{
  "type": "Feature",
  "properties": {
    "iso:country":"NL",
    "sg:address":"Kerkplein 5",
    "sg:city":"Sint Oedenrode",
    "sg:orig_category":"Opticiens",
    "sg:phone":"+31 413 474 860",
    "sg:postcode":"5492 AN",
    "sg:province":"Noord-Brabant",
    "wof:name":"Leo Leenders Optiek Bv",
    "wof:placetype":"venue"
},
  "geometry": {"coordinates":[5.4605631828,51.563205719],"type":"Point"}
}