{
  "type": "Feature",
  "properties": {
    "addr:full":"Kerkpln 1A Voorschoten Zuid-Holland 2251 BS",
    "addr:housenumber":"1a;2251",
    "addr:postcode":"bs",
    "addr:street":"Kerkpln",
    "iso:country":"NL",
    "sg:address":"Kerkpln 1A",
    "sg:city":"Voorschoten",
    "sg:orig_category":"Schoenen",
    "sg:phone":"+31 71 561 7825",
    "sg:postcode":"2251 BS",
    "sg:province":"Zuid-Holland",
    "wof:name":"Meer, Carel Van Der",
    "wof:placetype":"venue"
},
  "geometry": {"coordinates":[4.445836,52.124565],"type":"Point"}
}