{
  "type": "Feature",
  "properties": {
    "addr:full":"Johannes Vermeerplnts 4 Voorschoten Zuid-Holland 2251 GP",
    "addr:housenumber":"4",
    "addr:postcode":"2251 gp",
    "iso:country":"NL",
    "sg:address":"Johannes Vermeerplnts 4",
    "sg:city":"Voorschoten",
    "sg:orig_category":"Kappers",
    "sg:phone":"+31 71 561 4680",
    "sg:postcode":"2251 GP",
    "sg:province":"Zuid-Holland",
    "wof:name":"Dameskapsalon W.J. Wesseling",
    "wof:placetype":"venue"
},
  "geometry": {"coordinates":[4.4548249245,52.1236877441],"type":"Point"}
}