{
  "type": "Feature",
  "properties": {
    "addr:full":"Rijnseweg 16 Odijk Utrecht 3984 NG",
    "addr:housenumber":"16",
    "addr:postcode":"3984 ng",
    "addr:street":"Rijnseweg",
    "iso:country":"NL",
    "sg:address":"Rijnseweg 16",
    "sg:city":"Odijk",
    "sg:orig_category":"Fruit And Groenten Gh",
    "sg:phone":"+31 30 656 3300",
    "sg:postcode":"3984 NG",
    "sg:province":"Utrecht",
    "wof:name":"D. Vernooij",
    "wof:placetype":"venue"
},
  "geometry": {"coordinates":[5.245379,52.050091],"type":"Point"}
}