{
  "type": "Feature",
  "properties": {
    "addr:full":"Herendreef 28 Aardenburg Zeeland 4527 AJ",
    "addr:housenumber":"28",
    "addr:postcode":"4527 aj",
    "addr:street":"Herendreef",
    "iso:country":"NL",
    "sg:address":"Herendreef 28",
    "sg:city":"Aardenburg",
    "sg:orig_category":"Kantinebeheer",
    "sg:phone":"+31 117 491 264",
    "sg:postcode":"4527 AJ",
    "sg:province":"Zeeland",
    "wof:name":"Sebastiaan, St",
    "wof:placetype":"venue"
},
  "geometry": {"coordinates":[3.459266901,51.2802276611],"type":"Point"}
}