{
  "type": "Feature",
  "properties": {
    "addr:full":"C J V Houtenln 14 Weesp Noord-Holland 1381 CP",
    "addr:housenumber":"14",
    "addr:postcode":"1381 cp",
    "addr:street":"C;V Houtenln",
    "iso:country":"NL",
    "sg:address":"C J V Houtenln 14",
    "sg:city":"Weesp",
    "sg:orig_category":"Notarissen En Notariskantoren",
    "sg:phone":"+31 294 413 131",
    "sg:postcode":"1381 CP",
    "sg:province":"Noord-Holland",
    "wof:name":"Elten Van De Griend, Netwerk Notarissen",
    "wof:placetype":"venue"
},
  "geometry": {"coordinates":[5.03828,52.308315],"type":"Point"}
}