{
  "type": "Feature",
  "properties": {
    "addr:full":"Assendorperstr 174 Zwolle Overijssel 8012 CE",
    "addr:housenumber":"174",
    "addr:postcode":"8012 ce",
    "iso:country":"NL",
    "sg:address":"Assendorperstr 174",
    "sg:city":"Zwolle",
    "sg:orig_category":"Kappers",
    "sg:phone":"+31 38 423 1200",
    "sg:postcode":"8012 CE",
    "sg:province":"Overijssel",
    "wof:name":"M & R",
    "wof:placetype":"venue"
},
  "geometry": {"coordinates":[6.104678,52.503651],"type":"Point"}
}