{
  "type": "Feature",
  "properties": {
    "addr:full":"Zandstraat 54 Culemborg Gelderland 4101 EH",
    "addr:housenumber":"54",
    "addr:postcode":"4101 eh",
    "addr:street":"Zandstraat;Gelderland",
    "iso:country":"NL",
    "sg:address":"Zandstraat 54",
    "sg:city":"Culemborg",
    "sg:classifiers":[
        {
            "category":"Retail",
            "subcategory":"Photofinishing",
            "type":"Services"
        }
    ],
    "sg:phone":"+31 345 512 345",
    "sg:postcode":"4101 EH",
    "sg:province":"Gelderland",
    "sg:tags":[
        "foto",
        "film"
    ],
    "wof:name":"Studio Martin",
    "wof:placetype":"venue"
},
  "geometry": {"coordinates":[5.228136,51.954323],"type":"Point"}
}