{
  "type": "Feature",
  "properties": {
    "addr:full":"Grotestraat 11 Venray Limburg 5801 BD",
    "addr:housenumber":"11",
    "addr:postcode":"5801 bd",
    "addr:street":"Grotestraat",
    "iso:country":"NL",
    "sg:address":"Grotestraat 11",
    "sg:city":"Venray",
    "sg:orig_category":"Schoenen",
    "sg:phone":"+31 478 581 379",
    "sg:postcode":"5801 BD",
    "sg:province":"Limburg",
    "wof:name":"Hendricx Schoenen",
    "wof:placetype":"venue"
},
  "geometry": {"coordinates":[5.976028,51.52673],"type":"Point"}
}