{
  "type": "Feature",
  "properties": {
    "addr:full":"Mgr Hanssenln 83 Hoensbroek Limburg 6433 BK",
    "addr:housenumber":"83",
    "addr:postcode":"6433 bk",
    "addr:street":"Hanssenln",
    "iso:country":"NL",
    "sg:address":"Mgr Hanssenln 83",
    "sg:city":"Hoensbroek",
    "sg:orig_category":"Postkantoren",
    "sg:phone":"+31 45 521 5968",
    "sg:postcode":"6433 BK",
    "sg:province":"Limburg",
    "sg:website":"http://www.postkantoor.nl",
    "wof:name":"Postkantoor",
    "wof:placetype":"venue"
},
  "geometry": {"coordinates":[5.929783,50.914051],"type":"Point"}
}