{
  "type": "Feature",
  "properties": {
    "addr:full":"Gelijkheid 1 Zwolle NL.08 8014 XC",
    "addr:housenumber":"1",
    "addr:postcode":"8014 xc",
    "addr:street":"Gelijkheid",
    "iso:country":"NL",
    "sg:address":"Gelijkheid 1",
    "sg:city":"Zwolle",
    "sg:classifiers":[
        {
            "category":"Education",
            "subcategory":"Preschool",
            "type":"Public Place"
        }
    ],
    "sg:phone":"+31 38 465 2270",
    "sg:postcode":"8014 XC",
    "sg:province":"NL.08",
    "sg:tags":[
        "kleuteronderwijs",
        "basis-"
    ],
    "wof:name":"De Pol 1-2-4",
    "wof:placetype":"venue"
},
  "geometry": {"coordinates":[6.112437,52.483009],"type":"Point"}
}