{
  "type": "Feature",
  "properties": {
    "iso:country":"NL",
    "sg:address":"Badhuiswal 9",
    "sg:city":"Zwolle",
    "sg:classifiers":[
        {
            "category":"Utilities",
            "subcategory":"Cable",
            "type":"Services"
        }
    ],
    "sg:phone":"+31 38 421 5316",
    "sg:postcode":"8011 VZ",
    "sg:province":"Overijssel",
    "sg:tags":[
        "masseur",
        "en",
        "heilgymnasten"
    ],
    "wof:name":"Wit Bv, De",
    "wof:placetype":"venue"
},
  "geometry": {"coordinates":[6.100022,52.514763],"type":"Point"}
}