{
  "type": "Feature",
  "properties": {
    "addr:full":"Kosmonaut 22 Amersfoort Utrecht 3824 MK",
    "addr:housenumber":"22",
    "addr:postcode":"3824",
    "addr:street":"Kosmonaut",
    "iso:country":"NL",
    "sg:address":"Kosmonaut 22",
    "sg:city":"Amersfoort",
    "sg:orig_category":"Wegenbouw - Materialen",
    "sg:phone":"+31 33 456 5835",
    "sg:postcode":"3824 MK",
    "sg:province":"Utrecht",
    "sg:website":"http://www.ouwesteen.nl",
    "wof:name":"D'Ouwe Steen Bv",
    "wof:placetype":"venue"
},
  "geometry": {"coordinates":[5.3923239708,52.19871521],"type":"Point"}
}