{
  "type": "Feature",
  "properties": {
    "iso:country":"NL",
    "sg:address":"Commanderijstraat 28",
    "sg:city":"Schelluinen",
    "sg:orig_category":"Babyartikelen",
    "sg:phone":"+31 183 617 367",
    "sg:postcode":"4209 AR",
    "sg:province":"Zuid-Holland",
    "sg:website":"http://www.babyonboard.nl",
    "wof:name":"Baby On Board",
    "wof:placetype":"venue"
},
  "geometry": {"coordinates":[4.927174,51.843956],"type":"Point"}
}