{
  "type": "Feature",
  "properties": {
    "addr:full":"Baronielaan 134 Breda Noord-Brabant 4818 RD",
    "addr:housenumber":"134",
    "addr:postcode":"4818 rd",
    "addr:street":"Baronielaan",
    "iso:country":"NL",
    "sg:address":"Baronielaan 134",
    "sg:city":"Breda",
    "sg:orig_category":"Fotostudio'S And Fotografen",
    "sg:phone":"+31 76 522 8953",
    "sg:postcode":"4818 RD",
    "sg:province":"Noord-Brabant",
    "wof:name":"Factor",
    "wof:placetype":"venue"
},
  "geometry": {"coordinates":[4.777024,51.573982],"type":"Point"}
}