{
  "type": "Feature",
  "properties": {
    "addr:full":"Heidevenstraat 54 Nijmegen Gelderland 6533 TS",
    "addr:housenumber":"54",
    "addr:postcode":"6533 ts",
    "addr:street":"Heidevenstraat;Gelderland",
    "iso:country":"NL",
    "sg:address":"Heidevenstraat 54",
    "sg:city":"Nijmegen",
    "sg:orig_category":"Boekhouders",
    "sg:phone":"+31 24 356 0201",
    "sg:postcode":"6533 TS",
    "sg:province":"Gelderland",
    "wof:name":"Adminstratie Adviesbureau Lap",
    "wof:placetype":"venue"
},
  "geometry": {"coordinates":[5.850099,51.817181],"type":"Point"}
}