{
  "type": "Feature",
  "properties": {
    "addr:full":"Duin En Kruidbergerweg 2 Driehuis Nh North Holland 1985 HG",
    "addr:housenumber":"2",
    "addr:postcode":"1985 hg",
    "addr:street":"Duin En Kruidbergerweg;Nh North",
    "iso:country":"NL",
    "sg:address":"Duin En Kruidbergerweg 2",
    "sg:city":"Driehuis Nh",
    "sg:orig_category":"Begrafenisondernemers",
    "sg:phone":"+31 255 514 843",
    "sg:postcode":"1985 HG",
    "sg:province":"North Holland",
    "wof:name":"Crematorium Velsen Bv",
    "wof:placetype":"venue"
},
  "geometry": {"coordinates":[4.631842,52.445114],"type":"Point"}
}