{
  "type": "Feature",
  "properties": {
    "addr:full":"Piersonstr 10 Dieren Gelderland 6951 BD",
    "addr:housenumber":"10",
    "addr:postcode":"6951 bd",
    "addr:street":"Piersonstr;Gelderland",
    "iso:country":"NL",
    "sg:address":"Piersonstr 10",
    "sg:city":"Dieren",
    "sg:orig_category":"Opticiens",
    "sg:phone":"+31 313 414 556",
    "sg:postcode":"6951 BD",
    "sg:province":"Gelderland",
    "wof:name":"Verdonk Bv",
    "wof:placetype":"venue"
},
  "geometry": {"coordinates":[6.100564003,52.0496330261],"type":"Point"}
}