{
  "type": "Feature",
  "properties": {
    "addr:full":"Grand Combin 1 Eindhoven North Brabant 5624 NM",
    "addr:housenumber":"1",
    "addr:postcode":"5624",
    "addr:street":"Grand Combin",
    "iso:country":"NL",
    "sg:address":"Grand Combin 1",
    "sg:city":"Eindhoven",
    "sg:orig_category":"Milieu",
    "sg:phone":"+31 40 243 6485",
    "sg:postcode":"5624 NM",
    "sg:province":"North Brabant",
    "wof:name":"Bos",
    "wof:placetype":"venue"
},
  "geometry": {"coordinates":[5.453154,51.469646],"type":"Point"}
}