{
  "type": "Feature",
  "properties": {
    "addr:full":"Bikoln 121 Delft South Holland 2622 EE",
    "addr:housenumber":"121",
    "addr:postcode":"2622 ee",
    "iso:country":"NL",
    "sg:address":"Bikoln 121",
    "sg:city":"Delft",
    "sg:orig_category":"Kappers",
    "sg:phone":"+31 15 257 0721",
    "sg:postcode":"2622 EE",
    "sg:province":"South Holland",
    "wof:name":"Moli\u00e8r, Tom",
    "wof:placetype":"venue"
},
  "geometry": {"coordinates":[4.34454,51.982159],"type":"Point"}
}