{
  "type": "Feature",
  "properties": {
    "addr:full":"Looiersgracht 60 Amsterdam Noord-Holland 1016 VT",
    "addr:housenumber":"60",
    "addr:postcode":"1016",
    "addr:street":"Looiersgracht",
    "iso:country":"NL",
    "sg:address":"Looiersgracht 60",
    "sg:city":"Amsterdam",
    "sg:orig_category":"Meubelzaken, Woning- And Keukeninrichting",
    "sg:phone":"+31 20 626 3708",
    "sg:postcode":"1016 VT",
    "sg:province":"Noord-Holland",
    "wof:name":"Vanverre",
    "wof:placetype":"venue"
},
  "geometry": {"coordinates":[4.880635,52.368507],"type":"Point"}
}