{
  "type": "Feature",
  "properties": {
    "addr:full":"Gasthuisvest 13Rood Haarlem Noord-Holland 2011 ET",
    "addr:housenumber":"13rood",
    "addr:postcode":"2011 et",
    "addr:street":"Gasthuisvest",
    "iso:country":"NL",
    "sg:address":"Gasthuisvest 13Rood",
    "sg:city":"Haarlem",
    "sg:orig_category":"Fotojournalisten Freelance",
    "sg:phone":"+31 23 534 2246",
    "sg:postcode":"2011 ET",
    "sg:province":"Noord-Holland",
    "wof:name":"Steenwinkel",
    "wof:placetype":"venue"
},
  "geometry": {"coordinates":[4.631926,52.376293],"type":"Point"}
}