{
  "type": "Feature",
  "properties": {
    "addr:full":"Parallelwg 13 Wylre Limburg 6321 BA",
    "addr:housenumber":"13",
    "addr:postcode":"6321 ba",
    "addr:street":"Parallelwg;Limburg",
    "iso:country":"NL",
    "sg:address":"Parallelwg 13",
    "sg:city":"Wylre",
    "sg:orig_category":"Lpg-Installaties",
    "sg:phone":"+31 43 450 3099",
    "sg:postcode":"6321 BA",
    "sg:province":"Limburg",
    "wof:name":"M & M",
    "wof:placetype":"venue"
},
  "geometry": {"coordinates":[5.896679,50.833797],"type":"Point"}
}