{
  "type": "Feature",
  "properties": {
    "addr:full":"Hemdk 2 Sneek Friesland 8601 XH",
    "addr:housenumber":"2",
    "addr:postcode":"8601 xh",
    "addr:street":"Hemdk",
    "iso:country":"NL",
    "sg:address":"Hemdk 2",
    "sg:city":"Sneek",
    "sg:orig_category":"Scholen Voor Basisonderwijs",
    "sg:phone":"+31 515 482 482",
    "sg:postcode":"8601 XH",
    "sg:province":"Friesland",
    "wof:name":"Bogerman",
    "wof:placetype":"venue"
},
  "geometry": {"coordinates":[5.64892,53.035118],"type":"Point"}
}