{
  "type": "Feature",
  "properties": {
    "addr:full":"Diezerstr 36 Zwolle NL.08 8011 RG",
    "addr:housenumber":"36",
    "addr:postcode":"8011 rg",
    "addr:street":"Diezerstr",
    "iso:country":"NL",
    "sg:address":"Diezerstr 36",
    "sg:city":"Zwolle",
    "sg:orig_category":"Schoenen",
    "sg:phone":"+31 38 421 1570",
    "sg:postcode":"8011 RG",
    "sg:province":"NL.08",
    "sg:website":"http://www.dolcis.nl",
    "wof:name":"Dolcis",
    "wof:placetype":"venue"
},
  "geometry": {"coordinates":[6.094503,52.51239],"type":"Point"}
}