{
  "type": "Feature",
  "properties": {
    "iso:country":"NL",
    "sg:address":"Dorpsstr 109-111",
    "sg:city":"Zoetermeer",
    "sg:orig_category":"Fietsen En Bromfietsen",
    "sg:phone":"+31 79 316 0357",
    "sg:postcode":"2712 AE",
    "sg:province":"South Holland",
    "wof:name":"Xcitebikes",
    "wof:placetype":"venue"
},
  "geometry": {"coordinates":[4.498249,52.055534],"type":"Point"}
}