{
  "type": "Feature",
  "properties": {
    "addr:full":"Minstreel 54 Rhoon South Holland 3161 NE",
    "addr:housenumber":"54",
    "addr:postcode":"3161 ne",
    "addr:street":"Minstreel",
    "iso:country":"NL",
    "sg:address":"Minstreel 54",
    "sg:city":"Rhoon",
    "sg:classifiers":[
        {
            "category":"Personal",
            "subcategory":"Nail Salon",
            "type":"Services"
        }
    ],
    "sg:phone":"+31 10 501 3273",
    "sg:postcode":"3161 NE",
    "sg:province":"South Holland",
    "sg:tags":[
        "pedicure"
    ],
    "wof:name":"Wanum, I Van",
    "wof:placetype":"venue"
},
  "geometry": {"coordinates":[4.413528,51.861904],"type":"Point"}
}