{
  "type": "Feature",
  "properties": {
    "iso:country":"NL",
    "sg:address":"Triangelstraat 128",
    "sg:city":"Amersfoort",
    "sg:orig_category":"Loodgieterswerk, Verwarming And Sanitaire Installaties",
    "sg:phone":"+31 33 453 0699",
    "sg:postcode":"3822 DJ",
    "sg:province":"Utrecht",
    "wof:name":"Klussendienst Franken",
    "wof:placetype":"venue"
},
  "geometry": {"coordinates":[5.4055,52.183784],"type":"Point"}
}