{
  "type": "Feature",
  "properties": {
    "addr:full":"Postbus 538 Leeuwarden Friesland 8901 BH",
    "addr:housenumber":"538",
    "addr:postcode":"8901 bh",
    "addr:street":"Postbus",
    "iso:country":"NL",
    "sg:address":"Postbus 538",
    "sg:city":"Leeuwarden",
    "sg:orig_category":"Natuur- En Milieuorganisaties",
    "sg:phone":"+31 58 289 0463",
    "sg:postcode":"8901 BH",
    "sg:province":"Friesland",
    "sg:website":"http://www.ivn.nl",
    "wof:name":"Natuur- En Milieueduc Ivn",
    "wof:placetype":"venue"
},
  "geometry": {"coordinates":[5.79143,53.203049],"type":"Point"}
}