{
  "type": "Feature",
  "properties": {
    "addr:full":"G V Seystln 53 Zeist Utrecht 3703 BR",
    "addr:housenumber":"53",
    "addr:postcode":"3703 br",
    "addr:street":"V Seystln",
    "iso:country":"NL",
    "sg:address":"G V Seystln 53",
    "sg:city":"Zeist",
    "sg:orig_category":"Administratie- En Boekhoudkantoren",
    "sg:phone":"+31 30 693 2055",
    "sg:postcode":"3703 BR",
    "sg:province":"Utrecht",
    "sg:website":"http://www.mauros.nl",
    "wof:name":"Dinpar Bv",
    "wof:placetype":"venue"
},
  "geometry": {"coordinates":[5.24387,52.08548],"type":"Point"}
}