{
  "type": "Feature",
  "properties": {
    "addr:full":"Andromedastr 2 Tilburg Noord-Brabant 5015 AV",
    "addr:housenumber":"2",
    "addr:postcode":"5015 av",
    "addr:street":"Andromedastr",
    "iso:country":"NL",
    "sg:address":"Andromedastr 2",
    "sg:city":"Tilburg",
    "sg:orig_category":"Boekhandels",
    "sg:phone":"+31 13 582 0495",
    "sg:postcode":"5015 AV",
    "sg:province":"Noord-Brabant",
    "wof:name":"Media Expresse",
    "wof:placetype":"venue"
},
  "geometry": {"coordinates":[5.115709,51.569469],"type":"Point"}
}