{
  "type": "Feature",
  "properties": {
    "addr:full":"Oldewierde 263 Almere Flevoland 1353 JG",
    "addr:housenumber":"263",
    "addr:postcode":"1353 jg",
    "addr:street":"Oldewierde;Flevoland",
    "iso:country":"NL",
    "sg:address":"Oldewierde 263",
    "sg:city":"Almere",
    "sg:orig_category":"Loodgieterswerk, Verwarming And Sanitaire Installaties",
    "sg:phone":"+31 36 531 5929",
    "sg:postcode":"1353 JG",
    "sg:province":"Flevoland",
    "wof:name":"Preventief Onderhoudsbedrijf Hendriks",
    "wof:placetype":"venue"
},
  "geometry": {"coordinates":[5.208514,52.338291],"type":"Point"}
}