{
  "type": "Feature",
  "properties": {
    "addr:full":"Hg Nieuwstr 130 Dordrecht Zuid-Holland 3311 AK",
    "addr:housenumber":"130",
    "addr:postcode":"3311 ak",
    "iso:country":"NL",
    "sg:address":"Hg Nieuwstr 130",
    "sg:city":"Dordrecht",
    "sg:orig_category":"Antiquiteiten - Restauratie",
    "sg:phone":"+31 78 614 3199",
    "sg:postcode":"3311 AK",
    "sg:province":"Zuid-Holland",
    "wof:name":"Visser, M",
    "wof:placetype":"venue"
},
  "geometry": {"coordinates":[4.66249,51.815968],"type":"Point"}
}