{
  "type": "Feature",
  "properties": {
    "addr:full":"Bijlmerplein 94 Amsterdam Noord-Holland 1102 DA",
    "addr:housenumber":"94;1102",
    "addr:postcode":"da",
    "addr:street":"Bijlmerplein",
    "iso:country":"NL",
    "sg:address":"Bijlmerplein 94",
    "sg:city":"Amsterdam",
    "sg:orig_category":"Bloemen And Planten",
    "sg:phone":"+31 20 400 1893",
    "sg:postcode":"1102 DA",
    "sg:province":"Noord-Holland",
    "wof:name":"Lansuplant",
    "wof:placetype":"venue"
},
  "geometry": {"coordinates":[4.951719,52.314041],"type":"Point"}
}