{
  "type": "Feature",
  "properties": {
    "addr:full":"Burg V Engelenwg 112 Ysselmuiden Overijssel 8271 AV",
    "addr:housenumber":"112;8271",
    "addr:postcode":"av",
    "addr:street":"Burg V Engelenwg;Overijssel",
    "iso:country":"NL",
    "sg:address":"Burg V Engelenwg 112",
    "sg:city":"Ysselmuiden",
    "sg:orig_category":"Metselwerken",
    "sg:phone":"+31 38 332 0021",
    "sg:postcode":"8271 AV",
    "sg:province":"Overijssel",
    "wof:name":"Plender, Rick",
    "wof:placetype":"venue"
},
  "geometry": {"coordinates":[5.933985,52.564045],"type":"Point"}
}