{
  "type": "Feature",
  "properties": {
    "addr:full":"Zwolsewg 52 Deventer Overijssel 7412 AN",
    "addr:housenumber":"52",
    "addr:postcode":"7412 an",
    "addr:street":"Zwolsewg",
    "iso:country":"NL",
    "sg:address":"Zwolsewg 52",
    "sg:city":"Deventer",
    "sg:orig_category":"Kappers",
    "sg:phone":"+31 570 610 092",
    "sg:postcode":"7412 AN",
    "sg:province":"Overijssel",
    "wof:name":"Coupe Di Capelli",
    "wof:placetype":"venue"
},
  "geometry": {"coordinates":[6.1484899521,52.2595443726],"type":"Point"}
}