{
  "type": "Feature",
  "properties": {
    "addr:full":"Linnenwever 5 Wagenberg North Brabant 4845 PG",
    "addr:housenumber":"5",
    "addr:postcode":"4845 pg",
    "addr:street":"Linnenwever",
    "iso:country":"NL",
    "sg:address":"Linnenwever 5",
    "sg:city":"Wagenberg",
    "sg:orig_category":"Webdesign Bureaus",
    "sg:phone":"+31 76 593 5254",
    "sg:postcode":"4845 PG",
    "sg:province":"North Brabant",
    "sg:website":"http://www.quinexdesign.nl",
    "wof:name":"Quinex",
    "wof:placetype":"venue"
},
  "geometry": {"coordinates":[4.752093792,51.6662635803],"type":"Point"}
}