{
  "type": "Feature",
  "properties": {
    "addr:full":"Zegwaartsewg 166A Zoetermeer Zuid-Holland 2728 PC",
    "addr:housenumber":"166a",
    "addr:postcode":"2728 pc",
    "iso:country":"NL",
    "sg:address":"Zegwaartsewg 166A",
    "sg:city":"Zoetermeer",
    "sg:orig_category":"Autopoetsbedrijven",
    "sg:phone":"+31 79 342 4250",
    "sg:postcode":"2728 PC",
    "sg:province":"Zuid-Holland",
    "wof:name":"Car Cleaning Zoetermeer",
    "wof:placetype":"venue"
},
  "geometry": {"coordinates":[4.527738,52.068352],"type":"Point"}
}