{
  "type": "Feature",
  "properties": {
    "addr:full":"Weerdingerkanaal Zz 156A Nieuw Weerdinge Provincie Drenthe 7831 AK",
    "addr:housenumber":"156a",
    "addr:postcode":"7831 ak",
    "addr:street":"Weerdingerkanaal Zz;Nieuw Weerdinge Provincie Drenthe",
    "iso:country":"NL",
    "sg:address":"Weerdingerkanaal Zz 156A",
    "sg:city":"Nieuw Weerdinge",
    "sg:orig_category":"Makelaars In Onroerend Goed",
    "sg:phone":"+31 591 522 646",
    "sg:postcode":"7831 AK",
    "sg:province":"Provincie Drenthe",
    "wof:name":"Direkt Vastgoed En Verzekeringen",
    "wof:placetype":"venue"
},
  "geometry": {"coordinates":[6.987852,52.857391],"type":"Point"}
}