{
  "type": "Feature",
  "properties": {
    "addr:full":"Rhijnsburglaan 30 Heerde Gelderland 8181 XT",
    "addr:housenumber":"30",
    "addr:postcode":"8181 xt",
    "addr:street":"Rhijnsburglaan;Gelderland",
    "iso:country":"NL",
    "sg:address":"Rhijnsburglaan 30",
    "sg:city":"Heerde",
    "sg:orig_category":"Verzekeringen",
    "sg:phone":"+31 578 691 413",
    "sg:postcode":"8181 XT",
    "sg:province":"Gelderland",
    "wof:name":"Assurantie Kantoor J. V.D. Put",
    "wof:placetype":"venue"
},
  "geometry": {"coordinates":[6.031013,52.388645],"type":"Point"}
}