{
  "type": "Feature",
  "properties": {
    "addr:full":"Hooilandsewg 30 Roodeschool Groningen 9983 PE",
    "addr:housenumber":"30",
    "addr:postcode":"9983 pe",
    "addr:street":"Hooilandsewg",
    "iso:country":"NL",
    "sg:address":"Hooilandsewg 30",
    "sg:city":"Roodeschool",
    "sg:orig_category":"Banken",
    "sg:phone":"+31 595 437 930",
    "sg:postcode":"9983 PE",
    "sg:province":"Groningen",
    "sg:website":"http://www.rabobank.nl",
    "wof:name":"Rabobank",
    "wof:placetype":"venue"
},
  "geometry": {"coordinates":[6.764679,53.420017],"type":"Point"}
}