{
  "type": "Feature",
  "properties": {
    "iso:country":"NL",
    "sg:address":"Gildenveld 56",
    "sg:city":"Zeewolde",
    "sg:orig_category":"Binnenhuisarchitecten",
    "sg:phone":"+31 36 522 7220",
    "sg:postcode":"3892 DJ",
    "sg:province":"Flevoland",
    "wof:name":"E.A.T. Bos",
    "wof:placetype":"venue"
},
  "geometry": {"coordinates":[5.530544,52.323574],"type":"Point"}
}