{
  "type": "Feature",
  "properties": {
    "addr:full":"Wendelaarstraat 1 Alkmaar North Holland 1814 GR",
    "addr:housenumber":"1",
    "addr:postcode":"1814",
    "addr:street":"Wendelaarstraat",
    "iso:country":"NL",
    "sg:address":"Wendelaarstraat 1",
    "sg:city":"Alkmaar",
    "sg:orig_category":"Bloemen And Planten",
    "sg:phone":"+31 72 512 1186",
    "sg:postcode":"1814 GR",
    "sg:province":"North Holland",
    "wof:name":"Firma J.C. Jong",
    "wof:placetype":"venue"
},
  "geometry": {"coordinates":[4.7347350121,52.6186065674],"type":"Point"}
}