{
  "type": "Feature",
  "properties": {
    "iso:country":"NL",
    "sg:address":"Rimsky-Korssakovweg 45",
    "sg:city":"Almere",
    "sg:orig_category":"Kappers",
    "sg:phone":"+31 36 536 4482",
    "sg:postcode":"1323 LP",
    "sg:province":"Flevoland",
    "wof:name":"Korsten Coiffures",
    "wof:placetype":"venue"
},
  "geometry": {"coordinates":[5.191299,52.366833],"type":"Point"}
}