{
  "type": "Feature",
  "properties": {
    "addr:full":"Zinkerweg 11 Waalwijk North Brabant 5145 NL",
    "addr:housenumber":"11",
    "addr:postcode":"5145 nl",
    "addr:street":"Zinkerweg",
    "iso:country":"NL",
    "sg:address":"Zinkerweg 11",
    "sg:city":"Waalwijk",
    "sg:orig_category":"Verhuur Catering-, Feest- En Evenementbenodigdheden",
    "sg:phone":"+31 416 650 290",
    "sg:postcode":"5145 NL",
    "sg:province":"North Brabant",
    "wof:name":"Amutron Bv",
    "wof:placetype":"venue"
},
  "geometry": {"coordinates":[5.049081,51.693085],"type":"Point"}
}