{
  "type": "Feature",
  "properties": {
    "addr:full":"Beenekusstg 16 Marienvelde Gelderland 7263 SB",
    "addr:housenumber":"16",
    "addr:postcode":"7263 sb",
    "addr:street":"Beenekusstg;Gelderland",
    "iso:country":"NL",
    "sg:address":"Beenekusstg 16",
    "sg:city":"Marienvelde",
    "sg:orig_category":"Homeopathie",
    "sg:phone":"+31 544 482 881",
    "sg:postcode":"7263 SB",
    "sg:province":"Gelderland",
    "wof:name":"Sorcha Sickinghe-In 'T Veld",
    "wof:placetype":"venue"
},
  "geometry": {"coordinates":[6.489789,52.012482],"type":"Point"}
}