{
  "type": "Feature",
  "properties": {
    "addr:full":"Wilhelminaplantsoen 126 Diemen Noord-Holland 1111 CP",
    "addr:housenumber":"126",
    "addr:postcode":"1111 cp",
    "addr:street":"Wilhelminaplantsoen",
    "iso:country":"NL",
    "sg:address":"Wilhelminaplantsoen 126",
    "sg:city":"Diemen",
    "sg:orig_category":"Bibliotheken And Openbare Archieven",
    "sg:phone":"+31 20 690 2353",
    "sg:postcode":"1111 CP",
    "sg:province":"Noord-Holland",
    "wof:name":"Openbare Bibliotheek",
    "wof:placetype":"venue"
},
  "geometry": {"coordinates":[4.961011,52.341496],"type":"Point"}
}