{
  "type": "Feature",
  "properties": {
    "addr:full":"Kerkstr 25 Amsterdam Noord-Holland 1017 GA",
    "addr:housenumber":"25",
    "addr:postcode":"1017 ga",
    "addr:street":"Kerkstr",
    "iso:country":"NL",
    "sg:address":"Kerkstr 25",
    "sg:city":"Amsterdam",
    "sg:orig_category":"Kalenders En Agenda'S",
    "sg:phone":"+31 20 686 0974",
    "sg:postcode":"1017 GA",
    "sg:province":"Noord-Holland",
    "sg:website":"http://www.simpatico.org",
    "wof:name":"Simpatico",
    "wof:placetype":"venue"
},
  "geometry": {"coordinates":[-94.58502960209999,38.350479126],"type":"Point"}
}