{
  "type": "Feature",
  "properties": {
    "addr:full":"Arendhorsterwg 3 Ommen NL.08 7731 RC",
    "addr:housenumber":"3;nl.08",
    "addr:postcode":"7731 rc",
    "addr:street":"Arendhorsterwg",
    "iso:country":"NL",
    "sg:address":"Arendhorsterwg 3",
    "sg:city":"Ommen",
    "sg:orig_category":"Vakantieverblijven",
    "sg:phone":"+31 529 453 248",
    "sg:postcode":"7731 RC",
    "sg:province":"NL.08",
    "sg:website":"http://www.resort-de-arendshorst.nl",
    "wof:name":"Arendshorst Resort, De",
    "wof:placetype":"venue"
},
  "geometry": {"coordinates":[6.36421,52.52018],"type":"Point"}
}