{
  "type": "Feature",
  "properties": {
    "iso:country":"NL",
    "sg:address":"Veerkd 8",
    "sg:city":"Rotterdam",
    "sg:orig_category":"Werving En Selectie",
    "sg:phone":"+31 10 224 9944",
    "sg:postcode":"3016 DE",
    "sg:province":"South Holland",
    "sg:website":"http://www.espaz.nl",
    "wof:name":"Espaz Executive Secretaries",
    "wof:placetype":"venue"
},
  "geometry": {"coordinates":[4.4784550667,51.9228363037],"type":"Point"}
}