{
  "type": "Feature",
  "properties": {
    "addr:full":"Eelsmastate 50 Leeuwarden Friesland 8925 HM",
    "addr:housenumber":"50",
    "addr:postcode":"8925 hm",
    "addr:street":"Eelsmastate",
    "iso:country":"NL",
    "sg:address":"Eelsmastate 50",
    "sg:city":"Leeuwarden",
    "sg:orig_category":"Administratie- En Boekhoudkantoren",
    "sg:phone":"+31 58 266 3540",
    "sg:postcode":"8925 HM",
    "sg:province":"Friesland",
    "wof:name":"Dani\u00ebl Van Breeden",
    "wof:placetype":"venue"
},
  "geometry": {"coordinates":[5.856415,53.205898],"type":"Point"}
}