{
  "type": "Feature",
  "properties": {
    "addr:full":"Stenghof 102 Amsterdam Noord-Holland 1034 NP",
    "addr:housenumber":"102",
    "addr:postcode":"1034 np",
    "addr:street":"Stenghof",
    "iso:country":"NL",
    "sg:address":"Stenghof 102",
    "sg:city":"Amsterdam",
    "sg:orig_category":"Bedrijfs- And Managementsconsultants",
    "sg:phone":"+31 20 493 1661",
    "sg:postcode":"1034 NP",
    "sg:province":"Noord-Holland",
    "wof:name":"Repacom",
    "wof:placetype":"venue"
},
  "geometry": {"coordinates":[4.92387,52.411442],"type":"Point"}
}