{
  "type": "Feature",
  "properties": {
    "iso:country":"NL",
    "sg:address":"De Reede 71",
    "sg:city":"Veenendaal",
    "sg:orig_category":"Scholen Voor Basisonderwijs",
    "sg:phone":"+31 318 515 613",
    "sg:postcode":"3904 NT",
    "sg:province":"Utrecht",
    "wof:name":"Baken Ii Chr, Het",
    "wof:placetype":"venue"
},
  "geometry": {"coordinates":[5.531921,52.026348],"type":"Point"}
}