{
  "type": "Feature",
  "properties": {
    "addr:full":"Pluto 169 Den Helder North Holland 1785 AX",
    "addr:housenumber":"169",
    "addr:postcode":"1785 ax",
    "addr:street":"Pluto",
    "iso:country":"NL",
    "sg:address":"Pluto 169",
    "sg:city":"Den Helder",
    "sg:orig_category":"Webdesign Bureaus",
    "sg:phone":"+31 223 668 031",
    "sg:postcode":"1785 AX",
    "sg:province":"North Holland",
    "sg:website":"http://www.propage.nl",
    "wof:name":"Pro Page Prod",
    "wof:placetype":"venue"
},
  "geometry": {"coordinates":[4.7775979042,52.9465446472],"type":"Point"}
}