{
  "type": "Feature",
  "properties": {
    "addr:full":"Schaepmanstr 69 Wageningen Gelderland 6702 AR",
    "addr:housenumber":"69",
    "addr:postcode":"6702",
    "addr:street":"Schaepmanstr;Gelderland",
    "iso:country":"NL",
    "sg:address":"Schaepmanstr 69",
    "sg:city":"Wageningen",
    "sg:classifiers":[
        {
            "category":"Food & Beverages",
            "subcategory":"Bakery",
            "type":"Retail Goods"
        }
    ],
    "sg:phone":"+31 317 419 894",
    "sg:postcode":"6702 AR",
    "sg:province":"Gelderland",
    "sg:tags":[
        "pizza"
    ],
    "wof:name":"Exodus",
    "wof:placetype":"venue"
},
  "geometry": {"coordinates":[5.654246,51.964958],"type":"Point"}
}