{
  "type": "Feature",
  "properties": {
    "addr:full":"Plein 48 Tiel Gelderland 4001 LJ",
    "addr:housenumber":"48;lj",
    "addr:postcode":"4001",
    "addr:street":"Plein;Gelderland",
    "iso:country":"NL",
    "sg:address":"Plein 48",
    "sg:city":"Tiel",
    "sg:orig_category":"Musea",
    "sg:phone":"+31 344 614 416",
    "sg:postcode":"4001 LJ",
    "sg:province":"Gelderland",
    "wof:name":"Groote Soci\u00ebteit, De",
    "wof:placetype":"venue"
},
  "geometry": {"coordinates":[5.439598,51.886539],"type":"Point"}
}