{
  "type": "Feature",
  "properties": {
    "addr:full":"Noorderstat Str 57 Groningen Groningen 9716 AR",
    "addr:housenumber":"57",
    "addr:postcode":"9716",
    "addr:street":"Str",
    "iso:country":"NL",
    "sg:address":"Noorderstat Str 57",
    "sg:city":"Groningen",
    "sg:orig_category":"Psychotherapeuten",
    "sg:phone":"+31 50 577 3990",
    "sg:postcode":"9716 AR",
    "sg:province":"Groningen",
    "wof:name":"Tuinen-Heuker, Drs J Van",
    "wof:placetype":"venue"
},
  "geometry": {"coordinates":[6.5589,53.22905],"type":"Point"}
}