{
  "type": "Feature",
  "properties": {
    "iso:country":"NL",
    "sg:address":"Noorderstat Str 57",
    "sg:city":"Groningen",
    "sg:orig_category":"Psychotherapeuten",
    "sg:phone":"+31 50 577 3990",
    "sg:postcode":"9716 AR",
    "sg:province":"Groningen",
    "wof:name":"Tuinen-Heuker, Drs J Van",
    "wof:placetype":"venue"
},
  "geometry": {"coordinates":[6.5589,53.22905],"type":"Point"}
}