{
  "type": "Feature",
  "properties": {
    "addr:full":"Kloosterdk 24 Aalten Gelderland 7121 LL",
    "addr:housenumber":"24",
    "addr:postcode":"7121 ll",
    "addr:street":"Kloosterdk;Gelderland",
    "iso:country":"NL",
    "sg:address":"Kloosterdk 24",
    "sg:city":"Aalten",
    "sg:orig_category":"Land- En Tuinbouw - Loonbedrijven",
    "sg:phone":"+31 543 451 460",
    "sg:postcode":"7121 LL",
    "sg:province":"Gelderland",
    "wof:name":"Lensink & Jansen",
    "wof:placetype":"venue"
},
  "geometry": {"coordinates":[6.632062,51.965828],"type":"Point"}
}