{
  "type": "Feature",
  "properties": {
    "iso:country":"NL",
    "sg:address":"Hoofdstraat 197",
    "sg:city":"Sassenheim",
    "sg:orig_category":"Banken And Kredietinstellingen",
    "sg:phone":"+31 252 233 033",
    "sg:postcode":"2171 BC",
    "sg:province":"Zuid-Holland",
    "wof:name":"Postkantoor",
    "wof:placetype":"venue"
},
  "geometry": {"coordinates":[4.521841,52.226349],"type":"Point"}
}