{
  "type": "Feature",
  "properties": {
    "addr:full":"Kloosterdk 2 Monnickendam North Holland 1141 PJ",
    "addr:housenumber":"2",
    "addr:postcode":"1141 pj",
    "addr:street":"Kloosterdk",
    "iso:country":"NL",
    "sg:address":"Kloosterdk 2",
    "sg:city":"Monnickendam",
    "sg:orig_category":"Houtgroothandel",
    "sg:phone":"+31 299 651 515",
    "sg:postcode":"1141 PJ",
    "sg:province":"North Holland",
    "wof:name":"Dekker En Zn Houtgroothandel Bv",
    "wof:placetype":"venue"
},
  "geometry": {"coordinates":[5.028122,52.466026],"type":"Point"}
}