{
  "type": "Feature",
  "properties": {
    "addr:full":"L Nieuwstr 191 Schiedam South Holland 3111 AJ",
    "addr:housenumber":"191",
    "addr:postcode":"3111 aj",
    "iso:country":"NL",
    "sg:address":"L Nieuwstr 191",
    "sg:city":"Schiedam",
    "sg:orig_category":"Postkantoren",
    "sg:phone":"+31 10 426 4999",
    "sg:postcode":"3111 AJ",
    "sg:province":"South Holland",
    "sg:website":"http://www.postkantoor.nl",
    "wof:name":"Postkantoor",
    "wof:placetype":"venue"
},
  "geometry": {"coordinates":[4.40085,51.912815],"type":"Point"}
}