{
  "type": "Feature",
  "properties": {
    "addr:full":"Weseperwg 2/A Schalkhaar NL.08 7433 RM",
    "addr:housenumber":"2 / a;nl.08",
    "addr:postcode":"7433 rm",
    "addr:street":"Weseperwg",
    "iso:country":"NL",
    "sg:address":"Weseperwg 2/A",
    "sg:city":"Schalkhaar",
    "sg:orig_category":"Grondwerken",
    "sg:phone":"+31 570 531 200",
    "sg:postcode":"7433 RM",
    "sg:province":"NL.08",
    "wof:name":"Flierman, E J",
    "wof:placetype":"venue"
},
  "geometry": {"coordinates":[6.234917,52.312656],"type":"Point"}
}