{
  "type": "Feature",
  "properties": {
    "addr:full":"Opperduit 270 Lekkerkerk Zuid-Holland 2941 AN",
    "addr:housenumber":"270",
    "addr:postcode":"2941 an",
    "addr:street":"Opperduit",
    "iso:country":"NL",
    "sg:address":"Opperduit 270",
    "sg:city":"Lekkerkerk",
    "sg:orig_category":"Loonbedrijven",
    "sg:phone":"+31 180 664 344",
    "sg:postcode":"2941 AN",
    "sg:province":"Zuid-Holland",
    "wof:name":"Witvliet, C B",
    "wof:placetype":"venue"
},
  "geometry": {"coordinates":[4.720286,51.898853],"type":"Point"}
}