{
  "type": "Feature",
  "properties": {
    "addr:full":"Westerweg 53 Heiloo North Holland 1851 AB",
    "addr:housenumber":"53",
    "addr:postcode":"1851 ab",
    "addr:street":"Westerweg",
    "iso:country":"NL",
    "sg:address":"Westerweg 53",
    "sg:city":"Heiloo",
    "sg:orig_category":"Bloemen And Planten",
    "sg:phone":"+31 72 512 8936",
    "sg:postcode":"1851 AB",
    "sg:province":"North Holland",
    "wof:name":"Boomkwekerij G. Meijer",
    "wof:placetype":"venue"
},
  "geometry": {"coordinates":[4.718046,52.615406],"type":"Point"}
}