{
  "type": "Feature",
  "properties": {
    "addr:full":"1E Oosterparkstr 47 Amsterdam Noord-Holland 1091 GV",
    "addr:housenumber":"47",
    "addr:postcode":"1091 gv",
    "addr:street":"1E Oosterparkstr",
    "iso:country":"NL",
    "sg:address":"1E Oosterparkstr 47",
    "sg:city":"Amsterdam",
    "sg:orig_category":"Koffie- En Theehuizen",
    "sg:phone":"+31 20 463 9518",
    "sg:postcode":"1091 GV",
    "sg:province":"Noord-Holland",
    "wof:name":"Yamama, El",
    "wof:placetype":"venue"
},
  "geometry": {"coordinates":[4.908854,52.356026],"type":"Point"}
}