{
  "type": "Feature",
  "properties": {
    "iso:country":"NL",
    "sg:address":"Doorniksestr 59",
    "sg:city":"S Gravenhage",
    "sg:orig_category":"Adviesbureaus Bedrijfsorganisatie",
    "sg:phone":"+31 70 350 4170",
    "sg:postcode":"2587 XK",
    "sg:province":"Zuid-Holland",
    "wof:name":"Bromberg Bv, Ir J P",
    "wof:placetype":"venue"
},
  "geometry": {"coordinates":[4.29118,52.112942],"type":"Point"}
}