{
  "type": "Feature",
  "properties": {
    "iso:country":"NL",
    "sg:address":"Verrijn Stuartweg 6",
    "sg:city":"Diemen",
    "sg:orig_category":"Loodgieterswerk, Verwarming And Sanitaire Installaties",
    "sg:phone":"+31 20 314 1800",
    "sg:postcode":"1112 AX",
    "sg:province":"North Holland",
    "wof:name":"Bv Bureau Laagwater Voor Warmtetechniek En Sanitai",
    "wof:placetype":"venue"
},
  "geometry": {"coordinates":[4.962482,52.332214],"type":"Point"}
}