{
  "type": "Feature",
  "properties": {
    "iso:country":"NL",
    "sg:address":"Antony Moddermanstraat 38",
    "sg:city":"Tilburg",
    "sg:orig_category":"Paramedische Behandelingen",
    "sg:phone":"+31 13 467 3531",
    "sg:postcode":"5042 NE",
    "sg:province":"Noord-Brabant",
    "wof:name":"Logopedie M.A. Sparidans",
    "wof:placetype":"venue"
},
  "geometry": {"coordinates":[5.057317,51.568596],"type":"Point"}
}