{
  "type": "Feature",
  "properties": {
    "addr:full":"Tramwijk Zz 26 Nieuw Weerdinge Provincie Drenthe 7831 GH",
    "addr:housenumber":"26",
    "addr:postcode":"7831 gh",
    "addr:street":"Tramwijk Zz;Nieuw Weerdinge Provincie Drenthe",
    "iso:country":"NL",
    "sg:address":"Tramwijk Zz 26",
    "sg:city":"Nieuw Weerdinge",
    "sg:orig_category":"Goederenvervoer Over De Weg",
    "sg:phone":"+31 591 611 467",
    "sg:postcode":"7831 GH",
    "sg:province":"Provincie Drenthe",
    "wof:name":"Transportbedrijf K. Rademaker Bv",
    "wof:placetype":"venue"
},
  "geometry": {"coordinates":[6.950779,52.842464],"type":"Point"}
}