{
  "type": "Feature",
  "properties": {
    "iso:country":"NL",
    "sg:address":"Kerkwijk 67",
    "sg:city":"Berlicum Nb",
    "sg:orig_category":"Goederenvervoer Over De Weg",
    "sg:phone":"+31 73 503 4872",
    "sg:postcode":"5258 KB",
    "sg:province":"Noord-Brabant",
    "wof:name":"Harrie Kamp Internationaal Transport",
    "wof:placetype":"venue"
},
  "geometry": {"coordinates":[5.404671,51.676464],"type":"Point"}
}