{
  "type": "Feature",
  "properties": {
    "addr:full":"V Karnebeekstr 77A Zwolle NL.08 8011 JD",
    "addr:housenumber":"77a",
    "addr:postcode":"8011 jd",
    "iso:country":"NL",
    "sg:address":"V Karnebeekstr 77A",
    "sg:city":"Zwolle",
    "sg:orig_category":"Grafisch Ontwerpers",
    "sg:phone":"+31 38 421 5556",
    "sg:postcode":"8011 JD",
    "sg:province":"NL.08",
    "wof:name":"Kruse Beeldende Communicatie",
    "wof:placetype":"venue"
},
  "geometry": {"coordinates":[6.088738,52.512566],"type":"Point"}
}