{
  "type": "Feature",
  "properties": {
    "addr:full":"Burgemeester Suijsstraat 31 Tilburg North Brabant 5037 MB",
    "addr:housenumber":"31",
    "addr:postcode":"5037 mb",
    "addr:street":"Burgemeester Suijsstraat",
    "iso:country":"NL",
    "sg:address":"Burgemeester Suijsstraat 31",
    "sg:city":"Tilburg",
    "sg:orig_category":"Boekhouders",
    "sg:phone":"+31 13 468 4206",
    "sg:postcode":"5037 MB",
    "sg:province":"North Brabant",
    "wof:name":"Administratiekantoor A.H.C.M. Janssen",
    "wof:placetype":"venue"
},
  "geometry": {"coordinates":[5.060084,51.555683],"type":"Point"}
}