{
  "type": "Feature",
  "properties": {
    "addr:full":"Aaksterveld 146 Ameide South Holland 4233 GD",
    "addr:housenumber":"146",
    "addr:postcode":"4233 gd",
    "addr:street":"Aaksterveld",
    "iso:country":"NL",
    "sg:address":"Aaksterveld 146",
    "sg:city":"Ameide",
    "sg:orig_category":"Administratie- En Boekhoudkantoren",
    "sg:phone":"+31 183 600 375",
    "sg:postcode":"4233 GD",
    "sg:province":"South Holland",
    "wof:name":"Dekabos Administratiekantoor",
    "wof:placetype":"venue"
},
  "geometry": {"coordinates":[4.963468,51.951019],"type":"Point"}
}