{
  "type": "Feature",
  "properties": {
    "addr:full":"Coorningln 3 Druten Gelderland 6652 GE",
    "addr:housenumber":"3",
    "addr:postcode":"6652",
    "addr:street":"Coorningln",
    "iso:country":"NL",
    "sg:address":"Coorningln 3",
    "sg:city":"Druten",
    "sg:orig_category":"Administratie- En Boekhoudkantoren",
    "sg:phone":"+31 487 523 388",
    "sg:postcode":"6652 GE",
    "sg:province":"Gelderland",
    "wof:name":"Goeij, De",
    "wof:placetype":"venue"
},
  "geometry": {"coordinates":[5.604424,51.880421],"type":"Point"}
}