{
  "type": "Feature",
  "properties": {
    "addr:full":"Edisonstr 14 Zevenaar Gelderland 6902 PK",
    "addr:housenumber":"14",
    "addr:postcode":"6902 pk",
    "addr:street":"Edisonstr",
    "iso:country":"NL",
    "sg:address":"Edisonstr 14",
    "sg:city":"Zevenaar",
    "sg:orig_category":"Antiquiteiten",
    "sg:phone":"+31 316 524 461",
    "sg:postcode":"6902 PK",
    "sg:province":"Gelderland",
    "sg:website":"http://www.abc-antiques.com",
    "wof:name":"Abc Zevenaar",
    "wof:placetype":"venue"
},
  "geometry": {"coordinates":[6.082711,51.939819],"type":"Point"}
}