{
  "type": "Feature",
  "properties": {
    "addr:full":"Noordzandstraat 34 Yerseke Zeeland 4401 CG",
    "addr:housenumber":"34",
    "addr:postcode":"4401 cg",
    "addr:street":"Noordzandstraat",
    "iso:country":"NL",
    "sg:address":"Noordzandstraat 34",
    "sg:city":"Yerseke",
    "sg:orig_category":"Kantoorapparatuur Gh",
    "sg:phone":"+31 113 572 907",
    "sg:postcode":"4401 CG",
    "sg:province":"Zeeland",
    "wof:name":"P M Hoekman",
    "wof:placetype":"venue"
},
  "geometry": {"coordinates":[4.0503001213,51.4943656921],"type":"Point"}
}