{
  "type": "Feature",
  "properties": {
    "addr:full":"Heemraadssngl 122 Rotterdam Zuid-Holland 3021 DH",
    "addr:housenumber":"122",
    "addr:postcode":"3021 dh",
    "iso:country":"NL",
    "sg:address":"Heemraadssngl 122",
    "sg:city":"Rotterdam",
    "sg:orig_category":"Onroerende Goederen",
    "sg:phone":"+31 10 478 3335",
    "sg:postcode":"3021 DH",
    "sg:province":"Zuid-Holland",
    "wof:name":"Eljawa Bv",
    "wof:placetype":"venue"
},
  "geometry": {"coordinates":[4.455895,51.917698],"type":"Point"}
}