{
  "type": "Feature",
  "properties": {
    "addr:full":"Saffier 25 Venlo Limburg 5912 TN",
    "addr:housenumber":"25",
    "addr:postcode":"5912",
    "addr:street":"Saffier",
    "iso:country":"NL",
    "sg:address":"Saffier 25",
    "sg:city":"Venlo",
    "sg:orig_category":"Onroerende Goederen",
    "sg:phone":"+31 77 354 5632",
    "sg:postcode":"5912 TN",
    "sg:province":"Limburg",
    "wof:name":"Zuidveste",
    "wof:placetype":"venue"
},
  "geometry": {"coordinates":[6.175147,51.357819],"type":"Point"}
}