{
  "type": "Feature",
  "properties": {
    "addr:full":"Huidenstr 12 Amsterdam Noord-Holland 1016 ES",
    "addr:housenumber":"12",
    "addr:postcode":"1016 es",
    "addr:street":"Huidenstr",
    "iso:country":"NL",
    "sg:address":"Huidenstr 12",
    "sg:city":"Amsterdam",
    "sg:orig_category":"Banket",
    "sg:phone":"+31 20 623 9554",
    "sg:postcode":"1016 ES",
    "sg:province":"Noord-Holland",
    "wof:name":"Pompadour",
    "wof:placetype":"venue"
},
  "geometry": {"coordinates":[4.885893,52.368946],"type":"Point"}
}