{
  "type": "Feature",
  "properties": {
    "addr:full":"Pijnackerstraat 46 Amsterdam Noord-Holland 1072 JV",
    "addr:housenumber":"46",
    "addr:postcode":"1072 jv",
    "addr:street":"Pijnackerstraat",
    "iso:country":"NL",
    "sg:address":"Pijnackerstraat 46",
    "sg:city":"Amsterdam",
    "sg:orig_category":"Kansspelen",
    "sg:phone":"+31 20 675 7584",
    "sg:postcode":"1072 JV",
    "sg:province":"Noord-Holland",
    "wof:name":"Frans Bakker Automaten",
    "wof:placetype":"venue"
},
  "geometry": {"coordinates":[4.8889079094,52.3497657776],"type":"Point"}
}