{
  "type": "Feature",
  "properties": {
    "addr:full":"Vry Nederlandstr 51 Arnhem Gelderland 6826 AW",
    "addr:housenumber":"51",
    "addr:postcode":"6826 aw",
    "iso:country":"NL",
    "sg:address":"Vry Nederlandstr 51",
    "sg:city":"Arnhem",
    "sg:orig_category":"Bloemen En Planten",
    "sg:phone":"+31 26 362 1198",
    "sg:postcode":"6826 AW",
    "sg:province":"Gelderland",
    "wof:name":"Jan Fleur",
    "wof:placetype":"venue"
},
  "geometry": {"coordinates":[5.942256,51.983932],"type":"Point"}
}