{
  "type": "Feature",
  "properties": {
    "addr:full":"Poortersdreef 101 Amersfoort Utrecht 3824 DM",
    "addr:housenumber":"101",
    "addr:postcode":"3824 dm",
    "addr:street":"Poortersdreef",
    "iso:country":"NL",
    "sg:address":"Poortersdreef 101",
    "sg:city":"Amersfoort",
    "sg:orig_category":"Administratie- En Boekhoudkantoren",
    "sg:phone":"+31 33 455 2038",
    "sg:postcode":"3824 DM",
    "sg:province":"Utrecht",
    "wof:name":"Ceto",
    "wof:placetype":"venue"
},
  "geometry": {"coordinates":[5.382218,52.197929],"type":"Point"}
}