{
  "type": "Feature",
  "properties": {
    "iso:country":"NL",
    "sg:address":"Piet Heinstraat 20",
    "sg:city":"Zoetermeer",
    "sg:classifiers":[
        {
            "category":"Fast Food",
            "type":"Food & Drink"
        }
    ],
    "sg:phone":"+31 79 316 8684",
    "sg:postcode":"2712 KE",
    "sg:province":"South Holland",
    "sg:tags":[
        "afhaal",
        "restaurant"
    ],
    "wof:name":"Indonesisch Afhaalcentrum Toko Mahkota",
    "wof:placetype":"venue"
},
  "geometry": {"coordinates":[4.500527,52.050499],"type":"Point"}
}