{
  "type": "Feature",
  "properties": {
    "addr:full":"Poelkade 30 'S Gravenzande South Holland 2691 ME",
    "addr:housenumber":"30",
    "addr:postcode":"2691 me",
    "addr:street":"Poelkade;' S Gravenzande",
    "iso:country":"NL",
    "sg:address":"Poelkade 30",
    "sg:city":"'S Gravenzande",
    "sg:orig_category":"Bloemen And Planten",
    "sg:phone":"+31 174 628 122",
    "sg:postcode":"2691 ME",
    "sg:province":"South Holland",
    "wof:name":"Firma A. Vreugdenhil",
    "wof:placetype":"venue"
},
  "geometry": {"coordinates":[4.185795,51.996605],"type":"Point"}
}