{
  "type": "Feature",
  "properties": {
    "iso:country":"NL",
    "sg:address":"Exelsewg 6",
    "sg:city":"Laren Gld",
    "sg:orig_category":"Kaas",
    "sg:phone":"+31 573 421 319",
    "sg:postcode":"7245 VE",
    "sg:province":"Gelderland",
    "wof:name":"Kooihoek, De",
    "wof:placetype":"venue"
},
  "geometry": {"coordinates":[6.4129858017,52.1826896667],"type":"Point"}
}