{
  "type": "Feature",
  "properties": {
    "addr:full":"Snydersstr 6 Lelystad Flevoland 8224 AA",
    "addr:housenumber":"6",
    "addr:postcode":"8224 aa",
    "addr:street":"Snydersstr;Flevoland",
    "iso:country":"NL",
    "sg:address":"Snydersstr 6",
    "sg:city":"Lelystad",
    "sg:orig_category":"Bloemen En Planten",
    "sg:phone":"+31 320 243 730",
    "sg:postcode":"8224 AA",
    "sg:province":"Flevoland",
    "wof:name":"Korenschoof, De",
    "wof:placetype":"venue"
},
  "geometry": {"coordinates":[5.483492,52.519257],"type":"Point"}
}