{
  "type": "Feature",
  "properties": {
    "addr:full":"Barentszstraat 39 'S Gravenhage Zuid-Holland 2518 XD",
    "addr:housenumber":"39",
    "addr:postcode":"2518 xd",
    "addr:street":"Barentszstraat;' S",
    "iso:country":"NL",
    "sg:address":"Barentszstraat 39",
    "sg:city":"'S Gravenhage",
    "sg:orig_category":"Antiekzaken",
    "sg:phone":"+31 70 345 4814",
    "sg:postcode":"2518 XD",
    "sg:province":"Zuid-Holland",
    "wof:name":"M.F. Van Straaten",
    "wof:placetype":"venue"
},
  "geometry": {"coordinates":[4.297654,52.082985],"type":"Point"}
}