{
  "type": "Feature",
  "properties": {
    "addr:full":"Singel 99 Vlissingen Zeeland 4382 LN",
    "addr:housenumber":"99",
    "addr:postcode":"4382 ln",
    "addr:street":"Singel",
    "iso:country":"NL",
    "sg:address":"Singel 99",
    "sg:city":"Vlissingen",
    "sg:orig_category":"Paramedische Behandelingen",
    "sg:phone":"+31 118 418 918",
    "sg:postcode":"4382 LN",
    "sg:province":"Zeeland",
    "wof:name":"Podotherapeute W. Verduin",
    "wof:placetype":"venue"
},
  "geometry": {"coordinates":[3.573048,51.450294],"type":"Point"}
}