{
  "type": "Feature",
  "properties": {
    "iso:country":"NL",
    "sg:address":"Leeuwebek 14",
    "sg:city":"Huizen",
    "sg:orig_category":"Platenmaatschappijen",
    "sg:phone":"+31 35 526 2547",
    "sg:postcode":"1273 VE",
    "sg:province":"Noord-Holland",
    "wof:name":"Olivier Publishing",
    "wof:placetype":"venue"
},
  "geometry": {"coordinates":[5.25048,52.305588],"type":"Point"}
}