{
  "type": "Feature",
  "properties": {
    "addr:full":"Burgemeester Smitstraat 2A Zaandam North Holland 1501 RP",
    "addr:housenumber":"2a",
    "addr:postcode":"1501 rp",
    "addr:street":"Burgemeester Smitstraat",
    "iso:country":"NL",
    "sg:address":"Burgemeester Smitstraat 2A",
    "sg:city":"Zaandam",
    "sg:classifiers":[
        {
            "category":"Education",
            "subcategory":"Preschool",
            "type":"Public Place"
        }
    ],
    "sg:phone":"+31 75 616 2652",
    "sg:postcode":"1501 RP",
    "sg:province":"North Holland",
    "sg:tags":[
        "kleuteronderwijs",
        "basis-"
    ],
    "wof:name":"Herman Gorter",
    "wof:placetype":"venue"
},
  "geometry": {"coordinates":[4.835034,52.438683],"type":"Point"}
}