{
  "type": "Feature",
  "properties": {
    "iso:country":"NL",
    "sg:address":"Gooiergracht 15",
    "sg:city":"Laren Nh",
    "sg:orig_category":"Metaalbekleding And -Behandeling",
    "sg:phone":"+31 35 531 5253",
    "sg:postcode":"1251 VA",
    "sg:province":"Noord-Holland",
    "wof:name":"Lasservice Djp",
    "wof:placetype":"venue"
},
  "geometry": {"coordinates":[5.238638,52.246407],"type":"Point"}
}