{
  "type": "Feature",
  "properties": {
    "addr:full":"Wilgenstr 81 Haarlem Noord-Holland 2023 NN",
    "addr:housenumber":"81",
    "addr:postcode":"2023 nn",
    "addr:street":"Wilgenstr",
    "iso:country":"NL",
    "sg:address":"Wilgenstr 81",
    "sg:city":"Haarlem",
    "sg:orig_category":"Scholen Voor Basisonderwijs",
    "sg:phone":"+31 23 525 2369",
    "sg:postcode":"2023 NN",
    "sg:province":"Noord-Holland",
    "sg:website":"http://www.xs4all.nl/~wilghoek/",
    "wof:name":"Wilgenhoek Openb, De",
    "wof:placetype":"venue"
},
  "geometry": {"coordinates":[4.63239,52.403126],"type":"Point"}
}