{
  "type": "Feature",
  "properties": {
    "addr:full":"L Stammerdk 65 Amsterdam Zuidoost Noord-Holland 1109 BM",
    "addr:housenumber":"65",
    "addr:postcode":"zuidoost;1109 bm",
    "iso:country":"NL",
    "sg:address":"L Stammerdk 65",
    "sg:city":"Amsterdam Zuidoost",
    "sg:orig_category":"Jachthavens - Jachtwerven",
    "sg:phone":"+31 294 412 787",
    "sg:postcode":"1109 BM",
    "sg:province":"Noord-Holland",
    "wof:name":"Attema",
    "wof:placetype":"venue"
},
  "geometry": {"coordinates":[5.01655,52.305721],"type":"Point"}
}