{
  "type": "Feature",
  "properties": {
    "addr:full":"De Genestetstr 6 Enschede Overijssel 7514 CR",
    "addr:housenumber":"6",
    "addr:postcode":"7514 cr",
    "iso:country":"NL",
    "sg:address":"De Genestetstr 6",
    "sg:city":"Enschede",
    "sg:classifiers":[
        {
            "category":"Retail",
            "subcategory":"Auto Repair",
            "type":"Services"
        }
    ],
    "sg:phone":"+31 53 432 7411",
    "sg:postcode":"7514 CR",
    "sg:province":"Overijssel",
    "sg:tags":[
        "garage"
    ],
    "wof:name":"Dedo",
    "wof:placetype":"venue"
},
  "geometry": {"coordinates":[6.893669,52.226635],"type":"Point"}
}