{
  "type": "Feature",
  "properties": {
    "addr:full":"Van Der Hoopstraat 141 Beverwijk Noord-Holland 1945 TT",
    "addr:housenumber":"141",
    "addr:postcode":"1945 tt",
    "addr:street":"Van Der Hoopstraat",
    "iso:country":"NL",
    "sg:address":"Van Der Hoopstraat 141",
    "sg:city":"Beverwijk",
    "sg:orig_category":"Boekhouders",
    "sg:phone":"+31 6 51180016",
    "sg:postcode":"1945 TT",
    "sg:province":"Noord-Holland",
    "wof:name":"Goudje Van Outje",
    "wof:placetype":"venue"
},
  "geometry": {"coordinates":[4.67051,52.497871],"type":"Point"}
}