{
  "type": "Feature",
  "properties": {
    "iso:country":"NL",
    "sg:address":"Casterseweg 15",
    "sg:city":"Hoogeloon",
    "sg:orig_category":"Kantoorartikelen",
    "sg:phone":"+31 497 682 534",
    "sg:postcode":"5528 AS",
    "sg:province":"Noord-Brabant",
    "wof:name":"Berze Producten",
    "wof:placetype":"venue"
},
  "geometry": {"coordinates":[5.2629041672,51.3968009949],"type":"Point"}
}