{
  "type": "Feature",
  "properties": {
    "addr:full":"T Zand 28 Sleeuwijk North Brabant 4254 XP",
    "addr:housenumber":"28",
    "addr:postcode":"4254 xp",
    "addr:street":"T Zand",
    "iso:country":"NL",
    "sg:address":"T Zand 28",
    "sg:city":"Sleeuwijk",
    "sg:orig_category":"Hout Gh",
    "sg:phone":"+31 183 301 254",
    "sg:postcode":"4254 XP",
    "sg:province":"North Brabant",
    "wof:name":"Houtland Wejoma",
    "wof:placetype":"venue"
},
  "geometry": {"coordinates":[4.962159,51.813133],"type":"Point"}
}