{
  "type": "Feature",
  "properties": {
    "addr:full":"Kloosterweg 68 Laren Nh Noord-Holland 1251 WG",
    "addr:housenumber":"68",
    "addr:postcode":"1251 wg",
    "addr:street":"Kloosterweg",
    "iso:country":"NL",
    "sg:address":"Kloosterweg 68",
    "sg:city":"Laren Nh",
    "sg:orig_category":"Bloemen And Planten",
    "sg:phone":"+31 35 538 2568",
    "sg:postcode":"1251 WG",
    "sg:province":"Noord-Holland",
    "wof:name":"L. Bakker",
    "wof:placetype":"venue"
},
  "geometry": {"coordinates":[5.236094,52.248306],"type":"Point"}
}