{
  "type": "Feature",
  "properties": {
    "addr:full":"Loonberg 10 Bergen Op Zoom North Brabant 4617 NX",
    "addr:housenumber":"10",
    "addr:postcode":"4617 nx",
    "addr:street":"Loonberg",
    "iso:country":"NL",
    "sg:address":"Loonberg 10",
    "sg:city":"Bergen Op Zoom",
    "sg:orig_category":"Fotostudio'S And Fotografen",
    "sg:phone":"+31 164 251 023",
    "sg:postcode":"4617 NX",
    "sg:province":"North Brabant",
    "wof:name":"Fotografie John De Jong",
    "wof:placetype":"venue"
},
  "geometry": {"coordinates":[4.272768,51.474934],"type":"Point"}
}