{
  "type": "Feature",
  "properties": {
    "addr:full":"Zuidbargerstr 111 Emmen Drenthe 7812 AE",
    "addr:housenumber":"111",
    "addr:postcode":"7812 ae",
    "iso:country":"NL",
    "sg:address":"Zuidbargerstr 111",
    "sg:city":"Emmen",
    "sg:orig_category":"Verf En Lak - Fabrieken En Groothandel",
    "sg:phone":"+31 591 314 040",
    "sg:postcode":"7812 AE",
    "sg:province":"Drenthe",
    "wof:name":"Ch Bv",
    "wof:placetype":"venue"
},
  "geometry": {"coordinates":[6.907263,52.74897],"type":"Point"}
}