{
  "type": "Feature",
  "properties": {
    "iso:country":"NL",
    "sg:address":"Waterdrieblad 1A",
    "sg:city":"Huybergen",
    "sg:orig_category":"Sportverenigingen En Ontspannings- Verenigingen",
    "sg:phone":"+31 164 642 623",
    "sg:postcode":"4635 BP",
    "sg:province":"Noord-Brabant",
    "wof:name":"Huybergen Tennisver",
    "wof:placetype":"venue"
},
  "geometry": {"coordinates":[4.377671,51.435753],"type":"Point"}
}