{
  "type": "Feature",
  "properties": {
    "addr:full":"Egstraat 1 Dordrecht Zuid-Holland 3319 LA",
    "addr:housenumber":"1",
    "addr:postcode":"3319 la",
    "addr:street":"Egstraat",
    "iso:country":"NL",
    "sg:address":"Egstraat 1",
    "sg:city":"Dordrecht",
    "sg:orig_category":"Voeding, Dranken And Tabak Gh",
    "sg:phone":"+31 78 616 1555",
    "sg:postcode":"3319 LA",
    "sg:province":"Zuid-Holland",
    "wof:name":"Groma Bv",
    "wof:placetype":"venue"
},
  "geometry": {"coordinates":[4.715649,51.796791],"type":"Point"}
}