{
  "type": "Feature",
  "properties": {
    "addr:full":"Horsterweg 14 Zeewolde Flevoland 3891 EV",
    "addr:housenumber":"14",
    "addr:postcode":"3891 ev",
    "addr:street":"Horsterweg;Flevoland",
    "iso:country":"NL",
    "sg:address":"Horsterweg 14",
    "sg:city":"Zeewolde",
    "sg:orig_category":"Kappers",
    "sg:phone":"+31 36 522 6071",
    "sg:postcode":"3891 EV",
    "sg:province":"Flevoland",
    "wof:name":"Haarmode Alexandra",
    "wof:placetype":"venue"
},
  "geometry": {"coordinates":[5.5415101051,52.3298339844],"type":"Point"}
}