{
  "type": "Feature",
  "properties": {
    "addr:full":"Bosweg 10 Lochem Gelderland 7241 JH",
    "addr:housenumber":"10",
    "addr:postcode":"7241 jh",
    "addr:street":"Bosweg;Gelderland",
    "iso:country":"NL",
    "sg:address":"Bosweg 10",
    "sg:city":"Lochem",
    "sg:classifiers":[
        {
            "category":"Professional",
            "subcategory":"Accounting & Tax Preparation",
            "type":"Services"
        }
    ],
    "sg:phone":"+31 573 251 079",
    "sg:postcode":"7241 JH",
    "sg:province":"Gelderland",
    "sg:tags":[
        "accountant"
    ],
    "wof:name":"Handelsonderneming T. Regelink",
    "wof:placetype":"venue"
},
  "geometry": {"coordinates":[6.415501,52.155693],"type":"Point"}
}