{
  "type": "Feature",
  "properties": {
    "addr:full":"Dykstg 8 Meeuwen Noord-Brabant 4268 GK",
    "addr:housenumber":"8",
    "addr:postcode":"4268 gk",
    "addr:street":"Dykstg",
    "iso:country":"NL",
    "sg:address":"Dykstg 8",
    "sg:city":"Meeuwen",
    "sg:orig_category":"Bloemen En Planten - Groothandel",
    "sg:phone":"+31 416 351 252",
    "sg:postcode":"4268 GK",
    "sg:province":"Noord-Brabant",
    "wof:name":"Timmermans, W S G",
    "wof:placetype":"venue"
},
  "geometry": {"coordinates":[5.007525,51.729034],"type":"Point"}
}