{
  "type": "Feature",
  "properties": {
    "addr:full":"Postbus 289 Hoogeveen Drenthe 7900 AG",
    "addr:housenumber":"289",
    "addr:postcode":"7900",
    "addr:street":"Postbus",
    "iso:country":"NL",
    "sg:address":"Postbus 289",
    "sg:city":"Hoogeveen",
    "sg:orig_category":"Accountants - Administratie- Consulenten En -Kantoren",
    "sg:phone":"+31 528 262 323",
    "sg:postcode":"7900 AG",
    "sg:province":"Drenthe",
    "wof:name":"Krolstone",
    "wof:placetype":"venue"
},
  "geometry": {"coordinates":[6.47552,52.725975],"type":"Point"}
}