{
  "type": "Feature",
  "properties": {
    "addr:full":"Trasmolen 53 Maassluis Zuid-Holland 3146 TE",
    "addr:housenumber":"53",
    "addr:postcode":"3146 te",
    "addr:street":"Trasmolen",
    "iso:country":"NL",
    "sg:address":"Trasmolen 53",
    "sg:city":"Maassluis",
    "sg:orig_category":"Accountants - Administratie- Consulenten En -Kantoren",
    "sg:phone":"+31 10 591 9193",
    "sg:postcode":"3146 TE",
    "sg:province":"Zuid-Holland",
    "wof:name":"Zandstra",
    "wof:placetype":"venue"
},
  "geometry": {"coordinates":[4.225074,51.940399],"type":"Point"}
}