{
  "type": "Feature",
  "properties": {
    "addr:full":"Hogendk 34 Zaandam Noord-Holland 1506 AH",
    "addr:housenumber":"34",
    "addr:postcode":"1506 ah",
    "addr:street":"Hogendk",
    "iso:country":"NL",
    "sg:address":"Hogendk 34",
    "sg:city":"Zaandam",
    "sg:orig_category":"Grafisch Ontwerpers",
    "sg:phone":"+31 75 614 2970",
    "sg:postcode":"1506 AH",
    "sg:province":"Noord-Holland",
    "sg:website":"http://www.e-graphx.nl",
    "wof:name":"E-Graphx",
    "wof:placetype":"venue"
},
  "geometry": {"coordinates":[4.82383,52.438267],"type":"Point"}
}