{
  "type": "Feature",
  "properties": {
    "addr:full":"Tyvoortsebaan 5 Goirle Noord-Brabant 5051 HJ",
    "addr:housenumber":"5",
    "addr:postcode":"5051 hj",
    "addr:street":"Tyvoortsebaan",
    "iso:country":"NL",
    "sg:address":"Tyvoortsebaan 5",
    "sg:city":"Goirle",
    "sg:orig_category":"Schoenen",
    "sg:phone":"+31 13 530 8000",
    "sg:postcode":"5051 HJ",
    "sg:province":"Noord-Brabant",
    "sg:website":"http://www.brantano.nl",
    "wof:name":"Brantano",
    "wof:placetype":"venue"
},
  "geometry": {"coordinates":[5.05608,51.512222],"type":"Point"}
}