{
  "type": "Feature",
  "properties": {
    "addr:full":"V Stolbergwg 199 Veendam Groningen 9641 HK",
    "addr:housenumber":"199",
    "addr:postcode":"9641 hk",
    "addr:street":"Veendam",
    "iso:country":"NL",
    "sg:address":"V Stolbergwg 199",
    "sg:city":"Veendam",
    "sg:orig_category":"Advocaten En Advocatenkantoren",
    "sg:phone":"+31 598 635 396",
    "sg:postcode":"9641 HK",
    "sg:province":"Groningen",
    "wof:name":"Haan, De",
    "wof:placetype":"venue"
},
  "geometry": {"coordinates":[6.880442,53.106426],"type":"Point"}
}