{
  "type": "Feature",
  "properties": {
    "addr:full":"Hoofdstr 115A Grootegast Groningen 9861 AD",
    "addr:housenumber":"115a",
    "addr:postcode":"9861 ad",
    "iso:country":"NL",
    "sg:address":"Hoofdstr 115A",
    "sg:city":"Grootegast",
    "sg:orig_category":"Kappers",
    "sg:phone":"+31 594 613 016",
    "sg:postcode":"9861 AD",
    "sg:province":"Groningen",
    "wof:name":"Mystic",
    "wof:placetype":"venue"
},
  "geometry": {"coordinates":[6.276155,53.213268],"type":"Point"}
}