{
  "type": "Feature",
  "properties": {
    "addr:full":"Noordeindseweg 34 Delfgauw Zuid-Holland 2645 AL",
    "addr:housenumber":"34",
    "addr:postcode":"2645 al",
    "addr:street":"Noordeindseweg",
    "iso:country":"NL",
    "sg:address":"Noordeindseweg 34",
    "sg:city":"Delfgauw",
    "sg:orig_category":"Airconditioning And Ventilatie",
    "sg:phone":"+31 15 256 7150",
    "sg:postcode":"2645 AL",
    "sg:province":"Zuid-Holland",
    "wof:name":"Van Erven Bv",
    "wof:placetype":"venue"
},
  "geometry": {"coordinates":[4.394256,52.012051],"type":"Point"}
}