{
  "type": "Feature",
  "properties": {
    "addr:full":"Ypeloschoolweg 2 Enter Overijssel 7468 RE",
    "addr:housenumber":"2",
    "addr:postcode":"7468 re",
    "addr:street":"Ypeloschoolweg",
    "iso:country":"NL",
    "sg:address":"Ypeloschoolweg 2",
    "sg:city":"Enter",
    "sg:classifiers":[
        {
            "category":"Education",
            "subcategory":"Preschool",
            "type":"Public Place"
        }
    ],
    "sg:phone":"+31 547 383 661",
    "sg:postcode":"7468 RE",
    "sg:province":"Overijssel",
    "sg:tags":[
        "kleuteronderwijs",
        "basis-"
    ],
    "wof:name":"Christelijke Basisschool Rectum-Ypelo",
    "wof:placetype":"venue"
},
  "geometry": {"coordinates":[-76.841904,40.463078],"type":"Point"}
}