{
  "type": "Feature",
  "properties": {
    "addr:full":"Gierstr 6 Haarlem Noord-Holland 2011 GD",
    "addr:housenumber":"6",
    "addr:postcode":"2011 gd",
    "addr:street":"Gierstr",
    "iso:country":"NL",
    "sg:address":"Gierstr 6",
    "sg:city":"Haarlem",
    "sg:orig_category":"Boeken En Tijdschriften",
    "sg:phone":"+31 23 531 8163",
    "sg:postcode":"2011 GD",
    "sg:province":"Noord-Holland",
    "wof:name":"Kiekeboek Kinderboekwinkel",
    "wof:placetype":"venue"
},
  "geometry": {"coordinates":[4.632268,52.379383],"type":"Point"}
}