{
  "type": "Feature",
  "properties": {
    "iso:country":"NL",
    "sg:address":"F Hendrikstr 59",
    "sg:city":"Amsterdam",
    "sg:orig_category":"Grafisch Ontwerpers",
    "sg:phone":"+31 20 684 5547",
    "sg:postcode":"1052 HL",
    "sg:province":"North Holland",
    "wof:name":"Berkel, A Van",
    "wof:placetype":"venue"
},
  "geometry": {"coordinates":[4.873911,52.375954],"type":"Point"}
}