{
  "type": "Feature",
  "properties": {
    "addr:full":"T Frusselt 91 Vierhouten Gelderland 8076 RG",
    "addr:housenumber":"91",
    "addr:postcode":"8076 rg",
    "addr:street":"T Frusselt;Gelderland",
    "iso:country":"NL",
    "sg:address":"T Frusselt 91",
    "sg:city":"Vierhouten",
    "sg:orig_category":"Kampeerterreinen",
    "sg:phone":"+31 577 411 583",
    "sg:postcode":"8076 RG",
    "sg:province":"Gelderland",
    "wof:name":"Camping De Bunders",
    "wof:placetype":"venue"
},
  "geometry": {"coordinates":[5.8193092346,52.3241577148],"type":"Point"}
}