{
  "type": "Feature",
  "properties": {
    "iso:country":"NL",
    "sg:address":"Stokreefsweg 5",
    "sg:city":"Enter",
    "sg:orig_category":"Goederenvervoer Over De Weg",
    "sg:phone":"+31 547 381 501",
    "sg:postcode":"7468 SC",
    "sg:province":"Overijssel",
    "wof:name":"Fa. Hesselman",
    "wof:placetype":"venue"
},
  "geometry": {"coordinates":[-76.841904,40.463078],"type":"Point"}
}