{
  "type": "Feature",
  "properties": {
    "addr:full":"Hartenstraat 2 Den Helder North Holland 1781 TB",
    "addr:housenumber":"2",
    "addr:postcode":"1781 tb",
    "addr:street":"Hartenstraat",
    "iso:country":"NL",
    "sg:address":"Hartenstraat 2",
    "sg:city":"Den Helder",
    "sg:orig_category":"Kappers",
    "sg:phone":"+31 223 618 526",
    "sg:postcode":"1781 TB",
    "sg:province":"North Holland",
    "wof:name":"Michael Coiffures",
    "wof:placetype":"venue"
},
  "geometry": {"coordinates":[4.770064,52.955582],"type":"Point"}
}