{
  "type": "Feature",
  "properties": {
    "addr:full":"O Oenerwg 30-32 Oene Gelderland 8167 PD",
    "addr:housenumber":"30-32",
    "addr:postcode":"8167 pd",
    "addr:street":"Gelderland",
    "iso:country":"NL",
    "sg:address":"O Oenerwg 30-32",
    "sg:city":"Oene",
    "sg:orig_category":"Veiligheidsuitrusting En -Kleding",
    "sg:phone":"+31 578 641 226",
    "sg:postcode":"8167 PD",
    "sg:province":"Gelderland",
    "sg:website":"http://www.aro.nl",
    "wof:name":"Aro Schoeisel",
    "wof:placetype":"venue"
},
  "geometry": {"coordinates":[6.056493,52.352383],"type":"Point"}
}