{
  "type": "Feature",
  "properties": {
    "addr:full":"Dovenetelhof 39 Houten Utrecht 3991 GA",
    "addr:housenumber":"39",
    "addr:postcode":"3991 ga",
    "addr:street":"Dovenetelhof",
    "iso:country":"NL",
    "sg:address":"Dovenetelhof 39",
    "sg:city":"Houten",
    "sg:orig_category":"Adviesbureaus Bedrijfsorganisatie",
    "sg:phone":"+31 30 264 0390",
    "sg:postcode":"3991 GA",
    "sg:province":"Utrecht",
    "wof:name":"Linden, J Van Der",
    "wof:placetype":"venue"
},
  "geometry": {"coordinates":[5.164115,52.03017],"type":"Point"}
}