{
  "type": "Feature",
  "properties": {
    "iso:country":"NL",
    "sg:address":"Lysterbesln 76",
    "sg:city":"Lexmond",
    "sg:orig_category":"Adviesbureaus Waterbouwkunde",
    "sg:phone":"+31 347 341 441",
    "sg:postcode":"4128 SL",
    "sg:province":"Zuid-Holland",
    "wof:name":"Deva Advies Interim Management",
    "wof:placetype":"venue"
},
  "geometry": {"coordinates":[5.032561,51.963356],"type":"Point"}
}