{
  "type": "Feature",
  "properties": {
    "addr:full":"Raadhuislaan 13 Oss Noord-Brabant 5341 GL",
    "addr:housenumber":"13",
    "addr:postcode":"5341 gl",
    "addr:street":"Raadhuislaan",
    "iso:country":"NL",
    "sg:address":"Raadhuislaan 13",
    "sg:city":"Oss",
    "sg:orig_category":"Medische And Orthopedische Artikelen",
    "sg:phone":"+31 412 622 678",
    "sg:postcode":"5341 GL",
    "sg:province":"Noord-Brabant",
    "wof:name":"Stichting Thuiszorg Brabant Noord-Oost",
    "wof:placetype":"venue"
},
  "geometry": {"coordinates":[-93.52149199999999,45.170681],"type":"Point"}
}