{
  "type": "Feature",
  "properties": {
    "iso:country":"NL",
    "sg:address":"Zwaluwplein 16",
    "sg:city":"Boskoop",
    "sg:orig_category":"Verhuur Huishoudartikelen",
    "sg:phone":"+31 172 230 944",
    "sg:postcode":"2771 SC",
    "sg:province":"South Holland",
    "wof:name":"Entertainment Creation Result (Ecr)",
    "wof:placetype":"venue"
},
  "geometry": {"coordinates":[4.639026,52.066765],"type":"Point"}
}