{
  "type": "Feature",
  "properties": {
    "addr:full":"De Blauwe Zegge 73 Dedemsvaart Overijssel 7702 AJ",
    "addr:housenumber":"73",
    "addr:postcode":"7702 aj",
    "addr:street":"De Blauwe Zegge",
    "iso:country":"NL",
    "sg:address":"De Blauwe Zegge 73",
    "sg:city":"Dedemsvaart",
    "sg:orig_category":"Bestratingen",
    "sg:phone":"+31 523 615 548",
    "sg:postcode":"7702 AJ",
    "sg:province":"Overijssel",
    "wof:name":"Michel, H L",
    "wof:placetype":"venue"
},
  "geometry": {"coordinates":[6.454376,52.593151],"type":"Point"}
}