{
  "type": "Feature",
  "properties": {
    "iso:country":"NL",
    "sg:address":"Bruningsstraat 13",
    "sg:city":"Werkendam",
    "sg:orig_category":"Wegen And Sportterreinen",
    "sg:phone":"+31 183 501 959",
    "sg:postcode":"4251 LA",
    "sg:province":"Noord-Brabant",
    "wof:name":"A.H. Visser Bv",
    "wof:placetype":"venue"
},
  "geometry": {"coordinates":[4.8723978996,51.8045120239],"type":"Point"}
}