{
  "type": "Feature",
  "properties": {
    "addr:full":"Snuiverstr 111 Krommenie Noord-Holland 1561 HC",
    "addr:housenumber":"111",
    "addr:postcode":"1561 hc",
    "iso:country":"NL",
    "sg:address":"Snuiverstr 111",
    "sg:city":"Krommenie",
    "sg:orig_category":"Administratie- En Boekhoudkantoren",
    "sg:phone":"+31 75 622 7994",
    "sg:postcode":"1561 HC",
    "sg:province":"Noord-Holland",
    "wof:name":"Knobbe, J H",
    "wof:placetype":"venue"
},
  "geometry": {"coordinates":[4.757871,52.500019],"type":"Point"}
}