{
  "type": "Feature",
  "properties": {
    "addr:full":"Grotestr 34 Tubbergen NL.08 7651 CJ",
    "addr:housenumber":"34;nl.08",
    "addr:postcode":"7651 cj",
    "addr:street":"Grotestr",
    "iso:country":"NL",
    "sg:address":"Grotestr 34",
    "sg:city":"Tubbergen",
    "sg:classifiers":[
        {
            "category":"Travel",
            "subcategory":"Hotels & Motels",
            "type":"Entertainment"
        }
    ],
    "sg:phone":"+31 546 621 480",
    "sg:postcode":"7651 CJ",
    "sg:province":"NL.08",
    "sg:website":"http://www.hotel-tubbergen.nl",
    "wof:name":"Tubbergen, Hotel",
    "wof:placetype":"venue"
},
  "geometry": {"coordinates":[6.782071,52.40612],"type":"Point"}
}