{
  "type": "Feature",
  "properties": {
    "addr:full":"Bremerbergdk 39 Biddinghuizen Flevoland 8256 RD",
    "addr:housenumber":"39",
    "addr:postcode":"8256",
    "addr:street":"Bremerbergdk;Flevoland;Rd",
    "iso:country":"NL",
    "sg:address":"Bremerbergdk 39",
    "sg:city":"Biddinghuizen",
    "sg:orig_category":"Scheepsbouw En -Reparatie",
    "sg:phone":"+31 6 55396669",
    "sg:postcode":"8256 RD",
    "sg:province":"Flevoland",
    "sg:website":"http://www.verhoeve-yachtservice.nl",
    "wof:name":"Verhoeve",
    "wof:placetype":"venue"
},
  "geometry": {"coordinates":[5.749045,52.415894],"type":"Point"}
}