{
  "type": "Feature",
  "properties": {
    "iso:country":"NL",
    "sg:address":"Bernhardstr 3/A",
    "sg:city":"Waalwyk",
    "sg:classifiers":[
        {
            "category":"Retail",
            "subcategory":"Auto Repair",
            "type":"Services"
        }
    ],
    "sg:phone":"+31 416 332 689",
    "sg:postcode":"5141 GK",
    "sg:province":"Noord-Brabant",
    "sg:tags":[
        "garage"
    ],
    "wof:name":"Brok, A",
    "wof:placetype":"venue"
},
  "geometry": {"coordinates":[5.0677,51.687737],"type":"Point"}
}