{
  "type": "Feature",
  "properties": {
    "addr:full":"S Lewisplaats 49 Rotterdam Zuid-Holland 3068 EN",
    "addr:housenumber":"49",
    "addr:postcode":"3068 en",
    "addr:street":"S Lewisplaats",
    "iso:country":"NL",
    "sg:address":"S Lewisplaats 49",
    "sg:city":"Rotterdam",
    "sg:orig_category":"Homeopathie",
    "sg:phone":"+31 10 421 9513",
    "sg:postcode":"3068 EN",
    "sg:province":"Zuid-Holland",
    "wof:name":"Huttmann, M C",
    "wof:placetype":"venue"
},
  "geometry": {"coordinates":[4.554066,51.960747],"type":"Point"}
}