{
  "type": "Feature",
  "properties": {
    "addr:full":"V Ryckevorselstr 9 Gulpen Limburg 6271 GJ",
    "addr:housenumber":"9",
    "addr:postcode":"6271 gj",
    "addr:street":"Ryckevorselstr",
    "iso:country":"NL",
    "sg:address":"V Ryckevorselstr 9",
    "sg:city":"Gulpen",
    "sg:orig_category":"Kunststoffen - Fabrieken En Groothandel",
    "sg:phone":"+31 43 450 3898",
    "sg:postcode":"6271 GJ",
    "sg:province":"Limburg",
    "wof:name":"Hamar",
    "wof:placetype":"venue"
},
  "geometry": {"coordinates":[5.892,50.81488],"type":"Point"}
}