{
  "type": "Feature",
  "properties": {
    "addr:full":"Petuniatuin 42 Zoetermeer Zuid-Holland 2724 NB",
    "addr:housenumber":"42",
    "addr:postcode":"2724 nb",
    "addr:street":"Petuniatuin",
    "iso:country":"NL",
    "sg:address":"Petuniatuin 42",
    "sg:city":"Zoetermeer",
    "sg:orig_category":"Bloemen En Planten",
    "sg:phone":"+31 79 341 5307",
    "sg:postcode":"2724 NB",
    "sg:province":"Zuid-Holland",
    "wof:name":"Seghwaert",
    "wof:placetype":"venue"
},
  "geometry": {"coordinates":[4.51506,52.064323],"type":"Point"}
}