{
  "type": "Feature",
  "properties": {
    "addr:full":"Essenrys 12 St Willebrord Noord-Brabant 4711 PP",
    "addr:housenumber":"12",
    "addr:postcode":"4711 pp",
    "addr:street":"Essenrys",
    "iso:country":"NL",
    "sg:address":"Essenrys 12",
    "sg:city":"St Willebrord",
    "sg:orig_category":"Glazenwasserijen",
    "sg:phone":"+31 165 388 619",
    "sg:postcode":"4711 PP",
    "sg:province":"Noord-Brabant",
    "wof:name":"Vugt, Van",
    "wof:placetype":"venue"
},
  "geometry": {"coordinates":[4.593621,51.547909],"type":"Point"}
}