{
  "type": "Feature",
  "properties": {
    "addr:full":"De Paal 7/2 Almere Flevoland 1351 JB",
    "addr:housenumber":"7 / 2",
    "addr:postcode":"1351 jb",
    "addr:street":"De Paal;Flevoland",
    "iso:country":"NL",
    "sg:address":"De Paal 7/2",
    "sg:city":"Almere",
    "sg:orig_category":"Wasserettes, Stomerijen And Reiniging",
    "sg:phone":"+31 36 538 6404",
    "sg:postcode":"1351 JB",
    "sg:province":"Flevoland",
    "wof:name":"Vaks Bedrijfsdiensten",
    "wof:placetype":"venue"
},
  "geometry": {"coordinates":[5.2196278572,52.3466072083],"type":"Point"}
}