{
  "type": "Feature",
  "properties": {
    "addr:full":"Rodenbachstraat 70 'S Hertogenbosch Noord-Brabant 5216 VK",
    "addr:housenumber":"70",
    "addr:postcode":"5216 vk",
    "addr:street":"Rodenbachstraat;' S",
    "iso:country":"NL",
    "sg:address":"Rodenbachstraat 70",
    "sg:city":"'S Hertogenbosch",
    "sg:orig_category":"Architecten",
    "sg:phone":"+31 73 612 8673",
    "sg:postcode":"5216 VK",
    "sg:province":"Noord-Brabant",
    "wof:name":"Albers Milieu Onderzoek & Advies",
    "wof:placetype":"venue"
},
  "geometry": {"coordinates":[5.330975,51.680531],"type":"Point"}
}