{
  "type": "Feature",
  "properties": {
    "addr:full":"Molenaarserf 35 Eerbeek Gelderland 6961 NE",
    "addr:housenumber":"35;6961",
    "addr:street":"Molenaarserf;Gelderland;Ne",
    "iso:country":"NL",
    "sg:address":"Molenaarserf 35",
    "sg:city":"Eerbeek",
    "sg:orig_category":"Houtgroothandel Rondhout",
    "sg:phone":"+31 313 652 102",
    "sg:postcode":"6961 NE",
    "sg:province":"Gelderland",
    "wof:name":"Beld, H Van De",
    "wof:placetype":"venue"
},
  "geometry": {"coordinates":[6.057493,52.112103],"type":"Point"}
}