{
  "type": "Feature",
  "properties": {
    "addr:full":"Burg Krijgsmangeerde 43 Raamsdonksveer North Brabant 4942 AV",
    "addr:housenumber":"43",
    "addr:postcode":"4942 av",
    "addr:street":"Burg Krijgsmangeerde",
    "iso:country":"NL",
    "sg:address":"Burg Krijgsmangeerde 43",
    "sg:city":"Raamsdonksveer",
    "sg:classifiers":[
        {
            "category":"Education",
            "subcategory":"Preschool",
            "type":"Public Place"
        }
    ],
    "sg:phone":"+31 162 514 975",
    "sg:postcode":"4942 AV",
    "sg:province":"North Brabant",
    "sg:tags":[
        "kleuteronderwijs",
        "basis-"
    ],
    "wof:name":"Openbare Basisschool De Radonkel",
    "wof:placetype":"venue"
},
  "geometry": {"coordinates":[4.881337,51.701572],"type":"Point"}
}