{
  "type": "Feature",
  "properties": {
    "iso:country":"NL",
    "sg:address":"Hendrik Ter Brugghenstr 1",
    "sg:city":"Rijnsburg",
    "sg:orig_category":"Bloemen And Planten Gh",
    "sg:phone":"+31 71 402 8804",
    "sg:postcode":"2231 BW",
    "sg:province":"Zuid-Holland",
    "wof:name":"G. Van Egmond Bv",
    "wof:placetype":"venue"
},
  "geometry": {"coordinates":[4.431914,52.186714],"type":"Point"}
}