{
  "type": "Feature",
  "properties": {
    "iso:country":"NL",
    "sg:address":"J V Arkelstr 14",
    "sg:city":"Nieuw Lekkerland",
    "sg:orig_category":"Scheepssleep- En Duwvaart",
    "sg:phone":"+31 184 681 821",
    "sg:postcode":"2957 AP",
    "sg:province":"Zuid-Holland",
    "wof:name":"Edelweiss Vof",
    "wof:placetype":"venue"
},
  "geometry": {"coordinates":[4.68786,51.891094],"type":"Point"}
}