{
  "type": "Feature",
  "properties": {
    "addr:full":"Vlamingstr 55 Delft Zuid-Holland 2611 KS",
    "addr:housenumber":"55",
    "addr:postcode":"2611 ks",
    "addr:street":"Vlamingstr",
    "iso:country":"NL",
    "sg:address":"Vlamingstr 55",
    "sg:city":"Delft",
    "sg:orig_category":"Adviesbureaus Bedrijfsorganisatie",
    "sg:phone":"+31 15 215 8282",
    "sg:postcode":"2611 KS",
    "sg:province":"Zuid-Holland",
    "wof:name":"Inter Cultural Communication, Inst For",
    "wof:placetype":"venue"
},
  "geometry": {"coordinates":[4.362415,52.013416],"type":"Point"}
}