{
  "type": "Feature",
  "properties": {
    "addr:full":"Bloemgracht 72 Amsterdam Noord-Holland 1015 TL",
    "addr:housenumber":"72",
    "addr:postcode":"1015 tl",
    "addr:street":"Bloemgracht",
    "iso:country":"NL",
    "sg:address":"Bloemgracht 72",
    "sg:city":"Amsterdam",
    "sg:orig_category":"Diverse Grafische Activiteiten",
    "sg:phone":"+31 20 638 5963",
    "sg:postcode":"1015 TL",
    "sg:province":"Noord-Holland",
    "wof:name":"J.H. Hoogerhout",
    "wof:placetype":"venue"
},
  "geometry": {"coordinates":[4.881386,52.375084],"type":"Point"}
}