{
  "type": "Feature",
  "properties": {
    "addr:full":"Het Nardusboer 78 Oldenzaal Overijssel 7576 WJ",
    "addr:housenumber":"78",
    "addr:postcode":"7576 wj",
    "addr:street":"Het Nardusboer",
    "iso:country":"NL",
    "sg:address":"Het Nardusboer 78",
    "sg:city":"Oldenzaal",
    "sg:orig_category":"Boekhouders",
    "sg:phone":"+31 541 531 484",
    "sg:postcode":"7576 WJ",
    "sg:province":"Overijssel",
    "wof:name":"Advies- En Administratiekantoor H.B.C.",
    "wof:placetype":"venue"
},
  "geometry": {"coordinates":[6.89779,52.317028],"type":"Point"}
}