{
  "type": "Feature",
  "properties": {
    "addr:full":"Kerkweg Oost 161 2741 South Holland WADD IN",
    "addr:housenumber":"161",
    "addr:postcode":"2741",
    "addr:street":"Kerkweg Oost",
    "iso:country":"NL",
    "sg:address":"Kerkweg Oost 161",
    "sg:city":"2741",
    "sg:classifiers":[
        {
            "category":"Banks & Credit Unions",
            "subcategory":"Bank",
            "type":"Services"
        }
    ],
    "sg:phone":"+31 182 811 348",
    "sg:postcode":"WADD IN",
    "sg:province":"South Holland",
    "wof:name":"Rabobank, Waddinxveen",
    "wof:placetype":"venue"
},
  "geometry": {"coordinates":[4.655621,52.04443],"type":"Point"}
}