{
  "type": "Feature",
  "properties": {
    "addr:full":"Kalverdans 32 Boskoop Zuid-Holland 2771 RE",
    "addr:housenumber":"32",
    "addr:postcode":"2771 re",
    "addr:street":"Kalverdans",
    "iso:country":"NL",
    "sg:address":"Kalverdans 32",
    "sg:city":"Boskoop",
    "sg:classifiers":[
        {
            "category":"Professional",
            "subcategory":"Accounting & Tax Preparation",
            "type":"Services"
        }
    ],
    "sg:phone":"+31 172 235 730",
    "sg:postcode":"2771 RE",
    "sg:province":"Zuid-Holland",
    "sg:tags":[
        "accountant",
        "en",
        "-kantoren",
        "register-"
    ],
    "wof:name":"Arenthals Grant Thornton",
    "wof:placetype":"venue"
},
  "geometry": {"coordinates":[4.638774,52.074711],"type":"Point"}
}