{
  "type": "Feature",
  "properties": {
    "addr:full":"Riddersborch 14 Houten Utrecht 3992 BL",
    "addr:housenumber":"14",
    "addr:postcode":"3992 bl",
    "addr:street":"Riddersborch",
    "iso:country":"NL",
    "sg:address":"Riddersborch 14",
    "sg:city":"Houten",
    "sg:orig_category":"Adviesbureaus",
    "sg:phone":"+31 30 634 2855",
    "sg:postcode":"3992 BL",
    "sg:province":"Utrecht",
    "wof:name":"Dort, Van",
    "wof:placetype":"venue"
},
  "geometry": {"coordinates":[5.149467,52.036026],"type":"Point"}
}