{
  "type": "Feature",
  "properties": {
    "addr:full":"V Hamelstr 62 Soest Utrecht 3762 JE",
    "addr:housenumber":"62",
    "addr:postcode":"3762 je",
    "addr:street":"Soest",
    "iso:country":"NL",
    "sg:address":"V Hamelstr 62",
    "sg:city":"Soest",
    "sg:orig_category":"Verenigingen En Stichtingen",
    "sg:phone":"+31 35 603 3344",
    "sg:postcode":"3762 JE",
    "sg:province":"Utrecht",
    "wof:name":"Impuls, Sticht",
    "wof:placetype":"venue"
},
  "geometry": {"coordinates":[5.300385,52.184044],"type":"Point"}
}