{
  "type": "Feature",
  "properties": {
    "iso:country":"NL",
    "sg:address":"Mandenmakerstr 106C",
    "sg:city":"Hoogvliet Rt",
    "sg:orig_category":"Onderhoudswerken",
    "sg:phone":"+31 6 53788539",
    "sg:postcode":"3194 DG",
    "sg:province":"South Holland",
    "wof:name":"Kuipers, G",
    "wof:placetype":"venue"
},
  "geometry": {"coordinates":[4.375655,51.867455],"type":"Point"}
}