{
  "type": "Feature",
  "properties": {
    "iso:country":"NL",
    "sg:address":"Donkerstraat 43",
    "sg:city":"Harderwijk",
    "sg:orig_category":"Kantoorartikelen",
    "sg:phone":"+31 341 417 000",
    "sg:postcode":"3841 CB",
    "sg:province":"Gelderland",
    "wof:name":"Repro 7000 Bv",
    "wof:placetype":"venue"
},
  "geometry": {"coordinates":[5.6175670624,52.34923172],"type":"Point"}
}