{
  "type": "Feature",
  "properties": {
    "addr:full":"Vimmerik 6 Nieuwkuijk Noord-Brabant 5253 CB",
    "addr:housenumber":"6",
    "addr:postcode":"5253 cb",
    "addr:street":"Vimmerik",
    "iso:country":"NL",
    "sg:address":"Vimmerik 6",
    "sg:city":"Nieuwkuijk",
    "sg:orig_category":"Autokeuringen",
    "sg:phone":"+31 73 511 7179",
    "sg:postcode":"5253 CB",
    "sg:province":"Noord-Brabant",
    "wof:name":"Van Laarhoven Auto'S",
    "wof:placetype":"venue"
},
  "geometry": {"coordinates":[5.173774,51.694439],"type":"Point"}
}