{
  "type": "Feature",
  "properties": {
    "addr:full":"Kelvinstraat 36 'S Hertogenbosch Noord-Brabant 5223 GE",
    "addr:housenumber":"36",
    "addr:postcode":"5223",
    "addr:street":"Kelvinstraat;' S",
    "iso:country":"NL",
    "sg:address":"Kelvinstraat 36",
    "sg:city":"'S Hertogenbosch",
    "sg:classifiers":[
        {
            "category":"Retail",
            "subcategory":"Storage",
            "type":"Services"
        }
    ],
    "sg:phone":"+31 73 623 0049",
    "sg:postcode":"5223 GE",
    "sg:province":"Noord-Brabant",
    "sg:tags":[
        "opslag",
        "bewaring"
    ],
    "wof:name":"Evers Montage/Demontage Magazijn",
    "wof:placetype":"venue"
},
  "geometry": {"coordinates":[5.2858281136,51.6939086914],"type":"Point"}
}