{
  "type": "Feature",
  "properties": {
    "addr:full":"Hoofdstr 6A Herkenbosch Limburg 6075 AG",
    "addr:housenumber":"6a",
    "addr:postcode":"6075",
    "addr:street":"Hoofdstr",
    "iso:country":"NL",
    "sg:address":"Hoofdstr 6A",
    "sg:city":"Herkenbosch",
    "sg:orig_category":"Postkantoren",
    "sg:phone":"+31 475 531 320",
    "sg:postcode":"6075 AG",
    "sg:province":"Limburg",
    "sg:website":"http://www.postkantoor.nl",
    "wof:name":"Postkantoor",
    "wof:placetype":"venue"
},
  "geometry": {"coordinates":[6.061931,51.152771],"type":"Point"}
}