{
  "type": "Feature",
  "properties": {
    "addr:full":"Radswg 13 Roodeschool Groningen 9983 RB",
    "addr:housenumber":"13",
    "addr:postcode":"9983 rb",
    "addr:street":"Radswg",
    "iso:country":"NL",
    "sg:address":"Radswg 13",
    "sg:city":"Roodeschool",
    "sg:orig_category":"Loonbedrijven",
    "sg:phone":"+31 596 516 997",
    "sg:postcode":"9983 RB",
    "sg:province":"Groningen",
    "wof:name":"Stoppels, K J",
    "wof:placetype":"venue"
},
  "geometry": {"coordinates":[6.794303,53.4151],"type":"Point"}
}