{
  "type": "Feature",
  "properties": {
    "addr:full":"Postbus 591 Gorinchem Zuid-Holland 4200 AN",
    "addr:housenumber":"591",
    "addr:postcode":"4200 an",
    "addr:street":"Postbus",
    "iso:country":"NL",
    "sg:address":"Postbus 591",
    "sg:city":"Gorinchem",
    "sg:orig_category":"Verenigingen En Stichtingen",
    "sg:phone":"+31 183 637 740",
    "sg:postcode":"4200 AN",
    "sg:province":"Zuid-Holland",
    "sg:website":"http://www.caiw.nl/~macdanie/pvg/platform.htm",
    "wof:name":"Platform Voor Gehandicaptenbeleid, Sticht",
    "wof:placetype":"venue"
},
  "geometry": {"coordinates":[4.969185,51.830631],"type":"Point"}
}