{
  "type": "Feature",
  "properties": {
    "addr:full":"Spaarpot 121 Geldrop Noord-Brabant 5667 KW",
    "addr:housenumber":"121",
    "addr:postcode":"5667 kw",
    "addr:street":"Spaarpot",
    "iso:country":"NL",
    "sg:address":"Spaarpot 121",
    "sg:city":"Geldrop",
    "sg:orig_category":"Technische Studies And Onderzoek",
    "sg:phone":"+31 40 285 1685",
    "sg:postcode":"5667 KW",
    "sg:province":"Noord-Brabant",
    "wof:name":"Kers Engineering Service Bv",
    "wof:placetype":"venue"
},
  "geometry": {"coordinates":[5.555536,51.434044],"type":"Point"}
}