{
  "type": "Feature",
  "properties": {
    "iso:country":"NL",
    "sg:address":"De Donckstraat 24",
    "sg:city":"Sevenum",
    "sg:orig_category":"Overheidsdiensten",
    "sg:phone":"+31 77 467 2042",
    "sg:postcode":"5975 AC",
    "sg:province":"Limburg",
    "wof:name":"Jeugdcentrum Sevenum",
    "wof:placetype":"venue"
},
  "geometry": {"coordinates":[6.0338311195,51.4137992859],"type":"Point"}
}