{
  "type": "Feature",
  "properties": {
    "addr:full":"Fellenoord 100 Eindhoven North Brabant 5611 ZB",
    "addr:housenumber":"100",
    "addr:postcode":"5611 zb",
    "addr:street":"Fellenoord",
    "iso:country":"NL",
    "sg:address":"Fellenoord 100",
    "sg:city":"Eindhoven",
    "sg:orig_category":"Technische Studies And Onderzoek",
    "sg:phone":"+31 55 366 2583",
    "sg:postcode":"5611 ZB",
    "sg:province":"North Brabant",
    "wof:name":"Personeelscentrum Voor Werkgelegenheidsprojecten B",
    "wof:placetype":"venue"
},
  "geometry": {"coordinates":[5.473147,51.442387],"type":"Point"}
}