{
  "type": "Feature",
  "properties": {
    "addr:full":"Provincialeweg 9 Markenbinnen North Holland 1536 AC",
    "addr:housenumber":"9",
    "addr:postcode":"1536 ac",
    "addr:street":"Provincialeweg",
    "iso:country":"NL",
    "sg:address":"Provincialeweg 9",
    "sg:city":"Markenbinnen",
    "sg:orig_category":"Bedrijfsopleidingen",
    "sg:phone":"+31 75 641 1628",
    "sg:postcode":"1536 AC",
    "sg:province":"North Holland",
    "sg:website":"http://www.rboc-fmb.nl",
    "wof:name":"Fort Markenbinnen",
    "wof:placetype":"venue"
},
  "geometry": {"coordinates":[4.781045,52.533176],"type":"Point"}
}