{
  "type": "Feature",
  "properties": {
    "addr:full":"Dorpsstraat 103 Renswoude Utrecht 3927 BC",
    "addr:housenumber":"103",
    "addr:postcode":"3927 bc",
    "addr:street":"Dorpsstraat",
    "iso:country":"NL",
    "sg:address":"Dorpsstraat 103",
    "sg:city":"Renswoude",
    "sg:orig_category":"Babyartikelen Detailhandel",
    "sg:phone":"+31 318 574 676",
    "sg:postcode":"3927 BC",
    "sg:province":"Utrecht",
    "wof:name":"Wilma'S Baby- En Kinderhuis",
    "wof:placetype":"venue"
},
  "geometry": {"coordinates":[5.538561,52.074245],"type":"Point"}
}