{
  "type": "Feature",
  "properties": {
    "addr:full":"De Skieding 40 Drachtstercompagnie Friesland 9222 LB",
    "addr:housenumber":"40",
    "addr:postcode":"9222 lb",
    "addr:street":"De Skieding",
    "iso:country":"NL",
    "sg:address":"De Skieding 40",
    "sg:city":"Drachtstercompagnie",
    "sg:orig_category":"Fotografische And Optische Artikelen Gh",
    "sg:phone":"+31 512 342 753",
    "sg:postcode":"9222 LB",
    "sg:province":"Friesland",
    "wof:name":"Ammoniet",
    "wof:placetype":"venue"
},
  "geometry": {"coordinates":[6.173373,53.132961],"type":"Point"}
}