{
  "type": "Feature",
  "properties": {
    "addr:full":"Takkebysters 33 Breda Noord-Brabant 4817 BL",
    "addr:housenumber":"33",
    "addr:postcode":"4817 bl",
    "addr:street":"Takkebysters",
    "iso:country":"NL",
    "sg:address":"Takkebysters 33",
    "sg:city":"Breda",
    "sg:orig_category":"Gassen Industrieel En Medisch",
    "sg:phone":"+31 76 571 9417",
    "sg:postcode":"4817 BL",
    "sg:province":"Noord-Brabant",
    "wof:name":"Ypma Bv",
    "wof:placetype":"venue"
},
  "geometry": {"coordinates":[4.828612,51.597023],"type":"Point"}
}