{
  "type": "Feature",
  "properties": {
    "addr:full":"Uiterwg 123-127 Aalsmeer Noord-Holland 1431 AD",
    "addr:housenumber":"123-127",
    "addr:postcode":"1431 ad",
    "iso:country":"NL",
    "sg:address":"Uiterwg 123-127",
    "sg:city":"Aalsmeer",
    "sg:orig_category":"Beeldende Kunstenaars",
    "sg:phone":"+31 297 323 929",
    "sg:postcode":"1431 AD",
    "sg:province":"Noord-Holland",
    "wof:name":"Cleierij, De",
    "wof:placetype":"venue"
},
  "geometry": {"coordinates":[4.737752,52.263393],"type":"Point"}
}