{
  "type": "Feature",
  "properties": {
    "addr:full":"Elviraland 5 A 'S Gravenhage Zuid-Holland 2591 GE",
    "addr:housenumber":"5 a",
    "addr:postcode":"2591",
    "addr:street":"Elviraland;' S",
    "iso:country":"NL",
    "sg:address":"Elviraland 5 A",
    "sg:city":"'S Gravenhage",
    "sg:orig_category":"Kantoorapparatuur Gh",
    "sg:phone":"+31 70 383 8880",
    "sg:postcode":"2591 GE",
    "sg:province":"Zuid-Holland",
    "wof:name":"Uniepapier Randstad Bv",
    "wof:placetype":"venue"
},
  "geometry": {"coordinates":[4.3628530502,52.0952682495],"type":"Point"}
}