{
  "type": "Feature",
  "properties": {
    "addr:full":"Mgr Van De Weteringstr 73 Utrecht Utrecht 3581 ED",
    "addr:housenumber":"73",
    "addr:postcode":"3581 ed",
    "addr:street":"Mgr Van De Weteringstr",
    "iso:country":"NL",
    "sg:address":"Mgr Van De Weteringstr 73",
    "sg:city":"Utrecht",
    "sg:orig_category":"Fotostudio'S And Fotografen",
    "sg:phone":"+31 30 238 0050",
    "sg:postcode":"3581 ED",
    "sg:province":"Utrecht",
    "wof:name":"Evert Teijen Fotograaf",
    "wof:placetype":"venue"
},
  "geometry": {"coordinates":[5.13447,52.089989],"type":"Point"}
}