{
  "type": "Feature",
  "properties": {
    "addr:full":"Beekhuizenseweg 11 Velp Gld Gelderland 6881 AA",
    "addr:housenumber":"11",
    "addr:postcode":"6881 aa",
    "addr:street":"Beekhuizenseweg;Gld Gelderland",
    "iso:country":"NL",
    "sg:address":"Beekhuizenseweg 11",
    "sg:city":"Velp Gld",
    "sg:orig_category":"Architecten",
    "sg:phone":"+31 26 362 9301",
    "sg:postcode":"6881 AA",
    "sg:province":"Gelderland",
    "wof:name":"Architectenbureau Vos -Ten Broeke- Van Wely Bv",
    "wof:placetype":"venue"
},
  "geometry": {"coordinates":[5.984478,52.000851],"type":"Point"}
}