{
  "type": "Feature",
  "properties": {
    "addr:full":"Lynbaan 32 S Gravenhage Zuid-Holland 2512 VA",
    "addr:housenumber":"32;gravenhage",
    "addr:postcode":"2512",
    "addr:street":"Lynbaan;S",
    "iso:country":"NL",
    "sg:address":"Lynbaan 32",
    "sg:city":"S Gravenhage",
    "sg:orig_category":"Ziekenhuizen, Sanatoria, Verpleeghuizen",
    "sg:phone":"+31 70 330 2000",
    "sg:postcode":"2512 VA",
    "sg:province":"Zuid-Holland",
    "sg:website":"http://www.mchaaglanden.nl",
    "wof:name":"Mch-Westeinde",
    "wof:placetype":"venue"
},
  "geometry": {"coordinates":[4.30618,52.073212],"type":"Point"}
}