{
  "type": "Feature",
  "properties": {
    "iso:country":"NL",
    "sg:address":"Schurenbergweg 5",
    "sg:city":"Amsterdam Zuidoost",
    "sg:orig_category":"Film-, Tv- And Videoproductie",
    "sg:phone":"+31 20 517 4500",
    "sg:postcode":"1105 AP",
    "sg:province":"Noord-Holland",
    "wof:name":"Explainer Dc Bv",
    "wof:placetype":"venue"
},
  "geometry": {"coordinates":[4.948236,52.296085],"type":"Point"}
}