{
  "type": "Feature",
  "properties": {
    "iso:country":"NL",
    "sg:address":"Orlandopassage 18",
    "sg:city":"Kerkrade",
    "sg:orig_category":"Bijouterie?n",
    "sg:phone":"+31 45 546 1234",
    "sg:postcode":"6461 AM",
    "sg:province":"Limburg",
    "wof:name":"Lady Shop",
    "wof:placetype":"venue"
},
  "geometry": {"coordinates":[6.063885,50.865623],"type":"Point"}
}