{
  "type": "Feature",
  "properties": {
    "addr:full":"V Lieshoutstr 7 Helmond Noord-Brabant 5708 CD",
    "addr:housenumber":"7",
    "addr:postcode":"5708 cd",
    "addr:street":"Lieshoutstr",
    "iso:country":"NL",
    "sg:address":"V Lieshoutstr 7",
    "sg:city":"Helmond",
    "sg:orig_category":"Adviesbureaus Bedrijfsorganisatie",
    "sg:phone":"+31 6 54303634",
    "sg:postcode":"5708 CD",
    "sg:province":"Noord-Brabant",
    "sg:website":"http://www.ness-ct.com",
    "wof:name":"Ness",
    "wof:placetype":"venue"
},
  "geometry": {"coordinates":[5.618223,51.486515],"type":"Point"}
}