{
  "type": "Feature",
  "properties": {
    "addr:full":"G Vethln 13 Nunspeet Gelderland 8072 PS",
    "addr:housenumber":"13",
    "addr:postcode":"8072 ps",
    "addr:street":"Gelderland",
    "iso:country":"NL",
    "sg:address":"G Vethln 13",
    "sg:city":"Nunspeet",
    "sg:orig_category":"Bejaarden - Verzorgingstehuizen",
    "sg:phone":"+31 341 253 101",
    "sg:postcode":"8072 PS",
    "sg:province":"Gelderland",
    "wof:name":"Kodal, Het",
    "wof:placetype":"venue"
},
  "geometry": {"coordinates":[5.772205,52.374981],"type":"Point"}
}