{
  "type": "Feature",
  "properties": {
    "addr:full":"Regentesselaan 3 Breda North Brabant 4835 KK",
    "addr:housenumber":"3",
    "addr:postcode":"4835 kk",
    "addr:street":"Regentesselaan",
    "iso:country":"NL",
    "sg:address":"Regentesselaan 3",
    "sg:city":"Breda",
    "sg:orig_category":"Diverse Consumentenartikelen Gh",
    "sg:phone":"+31 76 520 8075",
    "sg:postcode":"4835 KK",
    "sg:province":"North Brabant",
    "wof:name":"Yazu",
    "wof:placetype":"venue"
},
  "geometry": {"coordinates":[4.7811,51.56921],"type":"Point"}
}