{
  "type": "Feature",
  "properties": {
    "addr:full":"Kamerikstr 17 Zuidzande Zeeland 4505 AL",
    "addr:housenumber":"17",
    "addr:postcode":"4505 al",
    "addr:street":"Kamerikstr",
    "iso:country":"NL",
    "sg:address":"Kamerikstr 17",
    "sg:city":"Zuidzande",
    "sg:orig_category":"Adviesbureaus Bedrijfsveiligheid",
    "sg:phone":"+31 117 450 065",
    "sg:postcode":"4505 AL",
    "sg:province":"Zeeland",
    "wof:name":"Tiscon Bv",
    "wof:placetype":"venue"
},
  "geometry": {"coordinates":[3.453358,51.341442],"type":"Point"}
}