{
  "type": "Feature",
  "properties": {
    "addr:full":"K Prinsengr 25 Amsterdam Noord-Holland 1013 GN",
    "addr:housenumber":"25",
    "addr:postcode":"1013 gn",
    "addr:street":"Prinsengr",
    "iso:country":"NL",
    "sg:address":"K Prinsengr 25",
    "sg:city":"Amsterdam",
    "sg:orig_category":"Adviesbureaus Bedrijfsorganisatie",
    "sg:phone":"+31 20 627 7078",
    "sg:postcode":"1013 GN",
    "sg:province":"Noord-Holland",
    "wof:name":"Bakker, Bert En Hannemieke",
    "wof:placetype":"venue"
},
  "geometry": {"coordinates":[4.887583,52.38633],"type":"Point"}
}