{
  "type": "Feature",
  "properties": {
    "iso:country":"NL",
    "sg:address":"Parnassusweg 23/3",
    "sg:city":"Amsterdam",
    "sg:orig_category":"Loodgieterswerk, Verwarming And Sanitaire Installaties",
    "sg:phone":"+31 20 673 7058",
    "sg:postcode":"1077 DC",
    "sg:province":"Noord-Holland",
    "wof:name":"F.O. Weserman",
    "wof:placetype":"venue"
},
  "geometry": {"coordinates":[4.867718,52.345184],"type":"Point"}
}