{
  "type": "Feature",
  "properties": {
    "addr:full":"Maartenbroersweg 55 A Hansweert Zeeland 4417 BK",
    "addr:housenumber":"55 a",
    "addr:postcode":"4417 bk",
    "addr:street":"Maartenbroersweg",
    "iso:country":"NL",
    "sg:address":"Maartenbroersweg 55 A",
    "sg:city":"Hansweert",
    "sg:orig_category":"Paramedische Behandelingen",
    "sg:phone":"+31 113 320 002",
    "sg:postcode":"4417 BK",
    "sg:province":"Zeeland",
    "wof:name":"Deltazorg",
    "wof:placetype":"venue"
},
  "geometry": {"coordinates":[4.000746,51.451225],"type":"Point"}
}