{
  "type": "Feature",
  "properties": {
    "addr:full":"Dr Tombrockln 1 Berkel Enschot Noord-Brabant 5056 NL",
    "addr:housenumber":"1",
    "addr:postcode":"5056 nl",
    "addr:street":"Berkel",
    "iso:country":"NL",
    "sg:address":"Dr Tombrockln 1",
    "sg:city":"Berkel Enschot",
    "sg:orig_category":"Artsen - Huisartsen",
    "sg:phone":"+31 13 533 1320",
    "sg:postcode":"5056 NL",
    "sg:province":"Noord-Brabant",
    "wof:name":"Geene, M J",
    "wof:placetype":"venue"
},
  "geometry": {"coordinates":[5.152251,51.58688],"type":"Point"}
}