{
  "type": "Feature",
  "properties": {
    "iso:country":"NL",
    "sg:address":"Dkn V Erpstr 10",
    "sg:city":"St Oedenrode",
    "sg:orig_category":"Verenigingsgebouwen",
    "sg:phone":"+31 413 475 544",
    "sg:postcode":"5492 CB",
    "sg:province":"North Brabant",
    "wof:name":"Ons Huis Ouderensoci\u00ebteit",
    "wof:placetype":"venue"
},
  "geometry": {"coordinates":[5.461095,51.564415],"type":"Point"}
}