{
  "type": "Feature",
  "properties": {
    "addr:full":"Kerkstr 7 Eindhoven Noord-Brabant 5611 GH",
    "addr:housenumber":"7",
    "addr:postcode":"5611 gh",
    "addr:street":"Kerkstr",
    "iso:country":"NL",
    "sg:address":"Kerkstr 7",
    "sg:city":"Eindhoven",
    "sg:orig_category":"Fotojournalisten Freelance",
    "sg:phone":"+31 40 244 4197",
    "sg:postcode":"5611 GH",
    "sg:province":"Noord-Brabant",
    "sg:website":"http://www.bvof.nl",
    "wof:name":"Overbeeke, Bart Van",
    "wof:placetype":"venue"
},
  "geometry": {"coordinates":[5.484105,51.434471],"type":"Point"}
}