{
  "type": "Feature",
  "properties": {
    "addr:full":"Paterstraat 22 Evertsoord Limburg 5977 NM",
    "addr:housenumber":"22",
    "addr:postcode":"5977",
    "addr:street":"Paterstraat",
    "iso:country":"NL",
    "sg:address":"Paterstraat 22",
    "sg:city":"Evertsoord",
    "sg:orig_category":"Overheidsdiensten",
    "sg:phone":"+31 77 464 1217",
    "sg:postcode":"5977 NM",
    "sg:province":"Limburg",
    "wof:name":"Evertsoord",
    "wof:placetype":"venue"
},
  "geometry": {"coordinates":[5.9590201378,51.4035606384],"type":"Point"}
}