{
  "type": "Feature",
  "properties": {
    "addr:full":"Beringstr 29 Geldrop Noord-Brabant 5665 GS",
    "addr:housenumber":"29",
    "addr:postcode":"5665 gs",
    "addr:street":"Beringstr",
    "iso:country":"NL",
    "sg:address":"Beringstr 29",
    "sg:city":"Geldrop",
    "sg:orig_category":"Geluidsinstallaties - Verhuur",
    "sg:phone":"+31 40 280 0680",
    "sg:postcode":"5665 GS",
    "sg:province":"Noord-Brabant",
    "sg:website":"http://www.hoevenaars.nl",
    "wof:name":"Hoevenaars Licht & Geluid",
    "wof:placetype":"venue"
},
  "geometry": {"coordinates":[5.580165,51.418949],"type":"Point"}
}