{
  "type": "Feature",
  "properties": {
    "addr:full":"Baardmeeswg 8 Zeewolde NL. 3899 XS",
    "addr:housenumber":"8",
    "addr:postcode":"3899 xs",
    "addr:street":"Baardmeeswg;Nl.",
    "iso:country":"NL",
    "sg:address":"Baardmeeswg 8",
    "sg:city":"Zeewolde",
    "sg:orig_category":"Betonindustrie",
    "sg:phone":"+31 36 521 8230",
    "sg:postcode":"3899 XS",
    "sg:province":"NL.",
    "wof:name":"Unibeton Bv",
    "wof:placetype":"venue"
},
  "geometry": {"coordinates":[5.500408,52.358715],"type":"Point"}
}