{
  "type": "Feature",
  "properties": {
    "addr:full":"L Blokwg 41A Zierikzee Zeeland 4301 NW",
    "addr:housenumber":"41a",
    "addr:postcode":"4301 nw",
    "iso:country":"NL",
    "sg:address":"L Blokwg 41A",
    "sg:city":"Zierikzee",
    "sg:orig_category":"Veenderijen",
    "sg:phone":"+31 111 450 280",
    "sg:postcode":"4301 NW",
    "sg:province":"Zeeland",
    "wof:name":"Agri Zeeland Bv",
    "wof:placetype":"venue"
},
  "geometry": {"coordinates":[3.921982,51.658524],"type":"Point"}
}