{
  "type": "Feature",
  "properties": {
    "addr:full":"P Potterplnts 32 Hillegom North Holland 2182 VG",
    "addr:housenumber":"32",
    "addr:postcode":"2182 vg",
    "addr:street":"P",
    "iso:country":"NL",
    "sg:address":"P Potterplnts 32",
    "sg:city":"Hillegom",
    "sg:orig_category":"Kappers",
    "sg:phone":"+31 252 523 219",
    "sg:postcode":"2182 VG",
    "sg:province":"North Holland",
    "wof:name":"Marjan",
    "wof:placetype":"venue"
},
  "geometry": {"coordinates":[4.578603,52.290993],"type":"Point"}
}