{
  "type": "Feature",
  "properties": {
    "addr:full":"Bolstoen 7A Amsterdam North Holland 1046 AS",
    "addr:housenumber":"7a",
    "addr:postcode":"1046 as",
    "addr:street":"Bolstoen",
    "iso:country":"NL",
    "sg:address":"Bolstoen 7A",
    "sg:city":"Amsterdam",
    "sg:orig_category":"Fotografie Reclame En Mode",
    "sg:phone":"+31 20 614 5259",
    "sg:postcode":"1046 AS",
    "sg:province":"North Holland",
    "sg:website":"http://www.tankstudios.nl",
    "wof:name":"Tank",
    "wof:placetype":"venue"
},
  "geometry": {"coordinates":[4.789585,52.390347],"type":"Point"}
}