{
  "type": "Feature",
  "properties": {
    "iso:country":"NL",
    "sg:address":"H Zwaardecroonstr 146",
    "sg:city":"S Gravenhage",
    "sg:orig_category":"Adviesbureaus Bedrijfsorganisatie",
    "sg:phone":"+31 70 335 2718",
    "sg:postcode":"2593 XW",
    "sg:province":"Zuid-Holland",
    "wof:name":"Mrse",
    "wof:placetype":"venue"
},
  "geometry": {"coordinates":[4.34266,52.086121],"type":"Point"}
}