{
  "type": "Feature",
  "properties": {
    "addr:full":"Westeinde 1 Berkenwoude Zuid-Holland 2825 AJ",
    "addr:housenumber":"1",
    "addr:postcode":"2825 aj",
    "addr:street":"Westeinde",
    "iso:country":"NL",
    "sg:address":"Westeinde 1",
    "sg:city":"Berkenwoude",
    "sg:classifiers":[
        {
            "category":"Sports & Exercise",
            "subcategory":"Stables",
            "type":"Entertainment"
        }
    ],
    "sg:phone":"+31 182 362 530",
    "sg:postcode":"2825 AJ",
    "sg:province":"Zuid-Holland",
    "sg:tags":[
        "maneges"
    ],
    "wof:name":"Bouwmeester",
    "wof:placetype":"venue"
},
  "geometry": {"coordinates":[4.708719,51.943836],"type":"Point"}
}