{
  "type": "Feature",
  "properties": {
    "iso:country":"NL",
    "sg:address":"Prof. Adolf Mayerlaan 19",
    "sg:city":"Utrecht",
    "sg:orig_category":"Bloemen And Planten",
    "sg:phone":"+31 30 273 3219",
    "sg:postcode":"3571 TH",
    "sg:province":"Utrecht",
    "wof:name":"Miranda'S Bloemen En Plantenshop",
    "wof:placetype":"venue"
},
  "geometry": {"coordinates":[5.126701,52.107212],"type":"Point"}
}