{
  "type": "Feature",
  "properties": {
    "iso:country":"NL",
    "sg:address":"Gr Adolfstr 36A",
    "sg:city":"Sneek",
    "sg:orig_category":"Kantoorbenodigdheden",
    "sg:phone":"+31 515 431 750",
    "sg:postcode":"8606 BT",
    "sg:province":"Friesland",
    "wof:name":"Nooitgedagt",
    "wof:placetype":"venue"
},
  "geometry": {"coordinates":[5.673910141,53.0255966187],"type":"Point"}
}