{
  "type": "Feature",
  "properties": {
    "addr:full":"Locht 77 Kerkrade Limburg 6466 GT",
    "addr:housenumber":"77",
    "addr:postcode":"6466 gt",
    "addr:street":"Locht",
    "iso:country":"NL",
    "sg:address":"Locht 77",
    "sg:city":"Kerkrade",
    "sg:orig_category":"Juridische Dienstverlening",
    "sg:phone":"+31 45 542 1795",
    "sg:postcode":"6466 GT",
    "sg:province":"Limburg",
    "wof:name":"C.A.S. Kerkrade",
    "wof:placetype":"venue"
},
  "geometry": {"coordinates":[6.012173,50.854778],"type":"Point"}
}