{
  "type": "Feature",
  "properties": {
    "addr:full":"Meeuwenlaan 102 A Amsterdam Noord-Holland 1021 JL",
    "addr:housenumber":"102 a",
    "addr:postcode":"1021 jl",
    "addr:street":"Meeuwenlaan",
    "iso:country":"NL",
    "sg:address":"Meeuwenlaan 102 A",
    "sg:city":"Amsterdam",
    "sg:orig_category":"Autoverhuur",
    "sg:phone":"+31 20 636 0513",
    "sg:postcode":"1021 JL",
    "sg:province":"Noord-Holland",
    "wof:name":"Autoverhuur Master Car Rent Bv",
    "wof:placetype":"venue"
},
  "geometry": {"coordinates":[4.922052,52.385769],"type":"Point"}
}