{
  "type": "Feature",
  "properties": {
    "addr:full":"Kemphaanstr 22 Wormer Noord-Holland 1531 VE",
    "addr:housenumber":"22",
    "addr:postcode":"1531",
    "addr:street":"Kemphaanstr;Ve",
    "iso:country":"NL",
    "sg:address":"Kemphaanstr 22",
    "sg:city":"Wormer",
    "sg:orig_category":"Schilders",
    "sg:phone":"+31 75 642 6431",
    "sg:postcode":"1531 VE",
    "sg:province":"Noord-Holland",
    "wof:name":"Daas",
    "wof:placetype":"venue"
},
  "geometry": {"coordinates":[4.810316,52.499702],"type":"Point"}
}