{
  "type": "Feature",
  "properties": {
    "iso:country":"NL",
    "sg:address":"Kemphaanstr 22",
    "sg:city":"Wormer",
    "sg:orig_category":"Schilders",
    "sg:phone":"+31 75 642 6431",
    "sg:postcode":"1531 VE",
    "sg:province":"Noord-Holland",
    "wof:name":"Daas",
    "wof:placetype":"venue"
},
  "geometry": {"coordinates":[4.810316,52.499702],"type":"Point"}
}