{
  "type": "Feature",
  "properties": {
    "addr:full":"Beekstr 33 Epe Gelderland 8162 HA",
    "addr:housenumber":"33",
    "addr:postcode":"8162 ha",
    "addr:street":"Beekstr;Gelderland",
    "iso:country":"NL",
    "sg:address":"Beekstr 33",
    "sg:city":"Epe",
    "sg:orig_category":"Verenigingsgebouwen",
    "sg:phone":"+31 578 613 710",
    "sg:postcode":"8162 HA",
    "sg:province":"Gelderland",
    "wof:name":"Verenigingsgebouw, Geref",
    "wof:placetype":"venue"
},
  "geometry": {"coordinates":[5.978502,52.347118],"type":"Point"}
}