{
  "type": "Feature",
  "properties": {
    "addr:full":"Achterom 67 S Gravenhage Zuid-Holland 2511 AH",
    "addr:housenumber":"67;gravenhage",
    "addr:postcode":"2511 ah",
    "addr:street":"Achterom;S",
    "iso:country":"NL",
    "sg:address":"Achterom 67",
    "sg:city":"S Gravenhage",
    "sg:orig_category":"Kappers",
    "sg:phone":"+31 70 346 3678",
    "sg:postcode":"2511 AH",
    "sg:province":"Zuid-Holland",
    "wof:name":"Chez Fred",
    "wof:placetype":"venue"
},
  "geometry": {"coordinates":[4.3162698746,52.0789604187],"type":"Point"}
}