{
  "type": "Feature",
  "properties": {
    "addr:full":"Dordtsestrwg 639-641 Rotterdam South Holland 3075 BC",
    "addr:housenumber":"639-641",
    "addr:postcode":"3075 bc",
    "iso:country":"NL",
    "sg:address":"Dordtsestrwg 639-641",
    "sg:city":"Rotterdam",
    "sg:orig_category":"Fietsen En Bromfietsen",
    "sg:phone":"+31 10 419 1945",
    "sg:postcode":"3075 BC",
    "sg:province":"South Holland",
    "sg:website":"http://www.berkenpeis.nl",
    "wof:name":"Berkenpeis Profile De Fietsspecialist",
    "wof:placetype":"venue"
},
  "geometry": {"coordinates":[4.504363,51.88192],"type":"Point"}
}