{
  "type": "Feature",
  "properties": {
    "iso:country":"NL",
    "sg:address":"Duit 3D",
    "sg:city":"Emmeloord",
    "sg:orig_category":"Onroerende Goederen",
    "sg:phone":"+31 527 611 694",
    "sg:postcode":"8305 BB",
    "sg:province":"Flevoland",
    "wof:name":"Vastion 4 Bv",
    "wof:placetype":"venue"
},
  "geometry": {"coordinates":[5.776746,52.711662],"type":"Point"}
}