{
  "type": "Feature",
  "properties": {
    "addr:full":"Travalje 22 Heerhugowaard North Holland 1701 HR",
    "addr:housenumber":"22",
    "addr:postcode":"1701 hr",
    "addr:street":"Travalje",
    "iso:country":"NL",
    "sg:address":"Travalje 22",
    "sg:city":"Heerhugowaard",
    "sg:orig_category":"Autorijscholen",
    "sg:phone":"+31 72 571 5871",
    "sg:postcode":"1701 HR",
    "sg:province":"North Holland",
    "sg:website":"http://www.adam-eva.nl",
    "wof:name":"Adam & Eva",
    "wof:placetype":"venue"
},
  "geometry": {"coordinates":[4.852442,52.668736],"type":"Point"}
}