{
  "type": "Feature",
  "properties": {
    "addr:full":"Kennedyplein 300 Eindhoven North Brabant 5611 ZV",
    "addr:housenumber":"300",
    "addr:postcode":"5611 zv",
    "addr:street":"Kennedyplein",
    "iso:country":"NL",
    "sg:address":"Kennedyplein 300",
    "sg:city":"Eindhoven",
    "sg:orig_category":"Verzekeringen",
    "sg:phone":"+31 40 246 2401",
    "sg:postcode":"5611 ZV",
    "sg:province":"North Brabant",
    "wof:name":"Vgz Zorgverzekeraar",
    "wof:placetype":"venue"
},
  "geometry": {"coordinates":[5.479888,51.444332],"type":"Point"}
}