{
  "type": "Feature",
  "properties": {
    "iso:country":"NL",
    "sg:address":"Veilingpassage 3",
    "sg:city":"Oud Beyerland",
    "sg:classifiers":[
        {
            "category":"Shopping",
            "subcategory":"Gifts & Souvenirs",
            "type":"Retail Goods"
        }
    ],
    "sg:phone":"+31 186 649 507",
    "sg:postcode":"3262 SX",
    "sg:province":"South Holland",
    "sg:tags":[
        "wens-",
        "en",
        "prentbriefkaarten"
    ],
    "wof:name":"Pokalot",
    "wof:placetype":"venue"
},
  "geometry": {"coordinates":[4.4129638672,51.8260536194],"type":"Point"}
}