{
  "type": "Feature",
  "properties": {
    "iso:country":"NL",
    "sg:address":"M Meeswg 5",
    "sg:city":"Rotterdam",
    "sg:orig_category":"Elektrotechnische Installatiebureaus",
    "sg:phone":"+31 10 407 8911",
    "sg:postcode":"3068 AV",
    "sg:province":"Zuid-Holland",
    "sg:website":"http://www.abb.nl",
    "wof:name":"Abb Bv",
    "wof:placetype":"venue"
},
  "geometry": {"coordinates":[4.55632,51.952709],"type":"Point"}
}