{
  "type": "Feature",
  "properties": {
    "addr:full":"Berkenstraat 45 Deurne Noord-Brabant 5753 GJ",
    "addr:housenumber":"45",
    "addr:postcode":"5753 gj",
    "addr:street":"Berkenstraat",
    "iso:country":"NL",
    "sg:address":"Berkenstraat 45",
    "sg:city":"Deurne",
    "sg:orig_category":"Metaalwerken",
    "sg:phone":"+31 493 316 001",
    "sg:postcode":"5753 GJ",
    "sg:province":"Noord-Brabant",
    "wof:name":"Vereyken Zonwering Deurne",
    "wof:placetype":"venue"
},
  "geometry": {"coordinates":[5.780267,51.449928],"type":"Point"}
}