{
  "type": "Feature",
  "properties": {
    "iso:country":"NL",
    "sg:address":"Middenwaard 39",
    "sg:city":"Heerhugowaard",
    "sg:orig_category":"Poeliers",
    "sg:phone":"+31 72 571 0950",
    "sg:postcode":"1703 SC",
    "sg:province":"North Holland",
    "wof:name":"Krijgsman",
    "wof:placetype":"venue"
},
  "geometry": {"coordinates":[4.83003,52.662788],"type":"Point"}
}