{
  "type": "Feature",
  "properties": {
    "addr:full":"Praamstraat 43 Den Helder North Holland 1784 NA",
    "addr:housenumber":"43",
    "addr:postcode":"1784 na",
    "addr:street":"Praamstraat",
    "iso:country":"NL",
    "sg:address":"Praamstraat 43",
    "sg:city":"Den Helder",
    "sg:orig_category":"Kappers",
    "sg:phone":"+31 223 668 398",
    "sg:postcode":"1784 NA",
    "sg:province":"North Holland",
    "wof:name":"Pour Elle(N)",
    "wof:placetype":"venue"
},
  "geometry": {"coordinates":[4.740863,52.932926],"type":"Point"}
}