{
  "type": "Feature",
  "properties": {
    "addr:full":"Huysbongerdwg 10 Montfort Limburg 6065 CJ",
    "addr:housenumber":"10",
    "addr:postcode":"6065 cj",
    "addr:street":"Huysbongerdwg",
    "iso:country":"NL",
    "sg:address":"Huysbongerdwg 10",
    "sg:city":"Montfort",
    "sg:orig_category":"Verzekeringen - Verzekeringskantoren",
    "sg:phone":"+31 475 542 244",
    "sg:postcode":"6065 CJ",
    "sg:province":"Limburg",
    "wof:name":"Storms En Geurts",
    "wof:placetype":"venue"
},
  "geometry": {"coordinates":[5.938734,51.128574],"type":"Point"}
}