{
  "type": "Feature",
  "properties": {
    "addr:full":"Dyk 16 Eersel North Brabant 5521 AX",
    "addr:housenumber":"16",
    "addr:postcode":"5521 ax",
    "addr:street":"Dyk",
    "iso:country":"NL",
    "sg:address":"Dyk 16",
    "sg:city":"Eersel",
    "sg:orig_category":"Woningbouw- Verenigingen En -Stichtingen",
    "sg:phone":"+31 497 517 835",
    "sg:postcode":"5521 AX",
    "sg:province":"North Brabant",
    "wof:name":"Zaligheden, Woningstichting De",
    "wof:placetype":"venue"
},
  "geometry": {"coordinates":[5.3090500832,51.3583106995],"type":"Point"}
}