{
  "type": "Feature",
  "properties": {
    "iso:country":"NL",
    "sg:address":"Ganzendiep 20",
    "sg:city":"Uithoorn",
    "sg:orig_category":"Artsen And Specialisten",
    "sg:phone":"+31 297 569 302",
    "sg:postcode":"1423 DB",
    "sg:province":"Utrecht",
    "wof:name":"J.J. Lugtmeijer",
    "wof:placetype":"venue"
},
  "geometry": {"coordinates":[4.819966,52.229691],"type":"Point"}
}