{
  "type": "Feature",
  "properties": {
    "iso:country":"NL",
    "sg:address":"Haven 15",
    "sg:city":"Breda",
    "sg:orig_category":"Verlichting And Huishoudartikelen",
    "sg:phone":"+31 76 521 1464",
    "sg:postcode":"4811 WL",
    "sg:province":"Noord-Brabant",
    "wof:name":"Van Poppel Verlichting Cv",
    "wof:placetype":"venue"
},
  "geometry": {"coordinates":[4.771685,51.591351],"type":"Point"}
}