{
  "type": "Feature",
  "properties": {
    "addr:full":"Het Sterrenbeeld 20 S Hertogenbosch Noord-Brabant 5215 ML",
    "addr:housenumber":"20",
    "addr:postcode":"5215 ml",
    "addr:street":"Het Sterrenbeeld;S",
    "iso:country":"NL",
    "sg:address":"Het Sterrenbeeld 20",
    "sg:city":"S Hertogenbosch",
    "sg:orig_category":"Elektrotechnische Artikelen",
    "sg:phone":"+31 73 687 3687",
    "sg:postcode":"5215 ML",
    "sg:province":"Noord-Brabant",
    "sg:website":"http://www.technischeunie.com",
    "wof:name":"Technische Unie",
    "wof:placetype":"venue"
},
  "geometry": {"coordinates":[5.357553,51.687],"type":"Point"}
}