{
  "type": "Feature",
  "properties": {
    "addr:full":"Symfoniestr 167 Nijmegen Gelderland 6544 TG",
    "addr:housenumber":"167",
    "addr:postcode":"6544 tg",
    "addr:street":"Gelderland",
    "iso:country":"NL",
    "sg:address":"Symfoniestr 167",
    "sg:city":"Nijmegen",
    "sg:orig_category":"Beeldende Kunstenaars",
    "sg:phone":"+31 24 377 4528",
    "sg:postcode":"6544 TG",
    "sg:province":"Gelderland",
    "wof:name":"Manche, A C M",
    "wof:placetype":"venue"
},
  "geometry": {"coordinates":[5.809501,51.833359],"type":"Point"}
}