{
  "type": "Feature",
  "properties": {
    "addr:full":"Wiegershof 10 Deurne Noord-Brabant 5751 XJ",
    "addr:housenumber":"10",
    "addr:postcode":"5751 xj",
    "addr:street":"Wiegershof",
    "iso:country":"NL",
    "sg:address":"Wiegershof 10",
    "sg:city":"Deurne",
    "sg:orig_category":"Technische Studies And Onderzoek",
    "sg:phone":"+31 493 315 147",
    "sg:postcode":"5751 XJ",
    "sg:province":"Noord-Brabant",
    "wof:name":"O.T.T. Oudelaar",
    "wof:placetype":"venue"
},
  "geometry": {"coordinates":[5.798081,51.459511],"type":"Point"}
}