{
  "type": "Feature",
  "properties": {
    "addr:full":"Gasthuisstraat 104 Helmond Noord-Brabant 5708 HP",
    "addr:housenumber":"104",
    "addr:postcode":"5708 hp",
    "addr:street":"Gasthuisstraat",
    "iso:country":"NL",
    "sg:address":"Gasthuisstraat 104",
    "sg:city":"Helmond",
    "sg:orig_category":"Metaalvrije Afvalrecycling",
    "sg:phone":"+31 492 536 762",
    "sg:postcode":"5708 HP",
    "sg:province":"Noord-Brabant",
    "wof:name":"Vripa Bv",
    "wof:placetype":"venue"
},
  "geometry": {"coordinates":[5.628666,51.47644],"type":"Point"}
}