{
  "type": "Feature",
  "properties": {
    "addr:full":"Bijlmerplein 686 Amsterdam Zuidoost Noord-Holland 1102 DZ",
    "addr:housenumber":"686",
    "addr:postcode":"zuidoost;1102 dz",
    "addr:street":"Bijlmerplein",
    "iso:country":"NL",
    "sg:address":"Bijlmerplein 686",
    "sg:city":"Amsterdam Zuidoost",
    "sg:orig_category":"Juweliers",
    "sg:phone":"+31 20 691 0568",
    "sg:postcode":"1102 DZ",
    "sg:province":"Noord-Holland",
    "wof:name":"Juwelierswinkel Gouden Suriname",
    "wof:placetype":"venue"
},
  "geometry": {"coordinates":[4.954204,52.314186],"type":"Point"}
}