{
  "type": "Feature",
  "properties": {
    "addr:full":"Paramariboweg 92 Apeldoorn Gelderland 7333 PB",
    "addr:housenumber":"92",
    "addr:postcode":"7333 pb",
    "addr:street":"Paramariboweg;Gelderland",
    "iso:country":"NL",
    "sg:address":"Paramariboweg 92",
    "sg:city":"Apeldoorn",
    "sg:orig_category":"Bouwnijverheidsmachines Gh",
    "sg:phone":"+31 55 534 0135",
    "sg:postcode":"7333 PB",
    "sg:province":"Gelderland",
    "wof:name":"Bo-Rent",
    "wof:placetype":"venue"
},
  "geometry": {"coordinates":[5.979094,52.179279],"type":"Point"}
}