{
  "type": "Feature",
  "properties": {
    "iso:country":"NL",
    "sg:address":"Waterborg 279",
    "sg:city":"Medemblik",
    "sg:orig_category":"Podotherapeuten",
    "sg:phone":"+31 227 543 682",
    "sg:postcode":"1671 NN",
    "sg:province":"Noord-Holland",
    "wof:name":"West Friesland, Praktijk",
    "wof:placetype":"venue"
},
  "geometry": {"coordinates":[5.098341,52.767807],"type":"Point"}
}