{
  "type": "Feature",
  "properties": {
    "iso:country":"NL",
    "sg:address":"Burg Hellenberg Hubarln 17",
    "sg:city":"Hilversum",
    "sg:orig_category":"Bedrijfs- And Managementsconsultants",
    "sg:phone":"+31 35 640 0922",
    "sg:postcode":"1217 LJ",
    "sg:province":"Noord-Holland",
    "wof:name":"Stephen Emmer Muziekproducties",
    "wof:placetype":"venue"
},
  "geometry": {"coordinates":[5.173077,52.229004],"type":"Point"}
}