{
  "type": "Feature",
  "properties": {
    "addr:full":"Vyfhuizenberg 42 Roosendaal Noord-Brabant 4708 AL",
    "addr:housenumber":"42",
    "addr:postcode":"4708 al",
    "addr:street":"Vyfhuizenberg",
    "iso:country":"NL",
    "sg:address":"Vyfhuizenberg 42",
    "sg:city":"Roosendaal",
    "sg:orig_category":"Begrafenisverzorging",
    "sg:phone":"+31 165 564 009",
    "sg:postcode":"4708 AL",
    "sg:province":"Noord-Brabant",
    "wof:name":"Coppens, C",
    "wof:placetype":"venue"
},
  "geometry": {"coordinates":[4.443258,51.522575],"type":"Point"}
}