{
  "type": "Feature",
  "properties": {
    "iso:country":"NL",
    "sg:address":"Kleiwg 45",
    "sg:city":"Rotterdam",
    "sg:orig_category":"Wasmachines En Wasdrogers",
    "sg:phone":"+31 10 422 5173",
    "sg:postcode":"3051 GJ",
    "sg:province":"Zuid-Holland",
    "wof:name":"Witgoedplaza",
    "wof:placetype":"venue"
},
  "geometry": {"coordinates":[4.4814319611,51.9451332092],"type":"Point"}
}