{
  "type": "Feature",
  "properties": {
    "addr:full":"2E Weteringdwstr 25-27 Amsterdam Noord-Holland 1017 SR",
    "addr:housenumber":"25-27",
    "addr:postcode":"1017 sr",
    "addr:street":"2E Weteringdwstr",
    "iso:country":"NL",
    "sg:address":"2E Weteringdwstr 25-27",
    "sg:city":"Amsterdam",
    "sg:orig_category":"Balletscholen",
    "sg:phone":"+31 20 626 6732",
    "sg:postcode":"1017 SR",
    "sg:province":"Noord-Holland",
    "wof:name":"Toverfluit Balletschool",
    "wof:placetype":"venue"
},
  "geometry": {"coordinates":[4.888306,52.361687],"type":"Point"}
}