{
  "type": "Feature",
  "properties": {
    "addr:full":"Vliegtuigstr 31 Amsterdam Noord-Holland 1059 CK",
    "addr:housenumber":"31",
    "addr:postcode":"1059 ck",
    "addr:street":"Vliegtuigstr",
    "iso:country":"NL",
    "sg:address":"Vliegtuigstr 31",
    "sg:city":"Amsterdam",
    "sg:orig_category":"Verhuizingen",
    "sg:phone":"+31 20 615 5463",
    "sg:postcode":"1059 CK",
    "sg:province":"Noord-Holland",
    "wof:name":"Boer & Zn, J F",
    "wof:placetype":"venue"
},
  "geometry": {"coordinates":[4.842795,52.339977],"type":"Point"}
}