{
  "type": "Feature",
  "properties": {
    "addr:full":"Middelweg 15D Leiden Zuid-Holland 2312 KE",
    "addr:housenumber":"15d",
    "addr:postcode":"2312 ke",
    "addr:street":"Middelweg",
    "iso:country":"NL",
    "sg:address":"Middelweg 15D",
    "sg:city":"Leiden",
    "sg:orig_category":"Wegen And Sportterreinen",
    "sg:phone":"+31 71 512 8709",
    "sg:postcode":"2312 KE",
    "sg:province":"Zuid-Holland",
    "wof:name":"D.F.L. Stouten",
    "wof:placetype":"venue"
},
  "geometry": {"coordinates":[4.4947919846,52.1577835083],"type":"Point"}
}