{
  "type": "Feature",
  "properties": {
    "addr:full":"J Valkeringln 1 Limmen Noord-Holland 1906 AS",
    "addr:housenumber":"1",
    "addr:postcode":"1906 as",
    "iso:country":"NL",
    "sg:address":"J Valkeringln 1",
    "sg:city":"Limmen",
    "sg:orig_category":"Feestartikelen",
    "sg:phone":"+31 72 505 1289",
    "sg:postcode":"1906 AS",
    "sg:province":"Noord-Holland",
    "wof:name":"Eba Bv",
    "wof:placetype":"venue"
},
  "geometry": {"coordinates":[4.698672,52.569626],"type":"Point"}
}