{
  "type": "Feature",
  "properties": {
    "addr:full":"Hazeldonk 12 Asten North Brabant 5721 TA",
    "addr:housenumber":"12",
    "addr:postcode":"5721 ta",
    "addr:street":"Hazeldonk",
    "iso:country":"NL",
    "sg:address":"Hazeldonk 12",
    "sg:city":"Asten",
    "sg:orig_category":"Bloemen En Planten",
    "sg:phone":"+31 493 692 163",
    "sg:postcode":"5721 TA",
    "sg:province":"North Brabant",
    "wof:name":"Wijnen Vof Tuincentrum",
    "wof:placetype":"venue"
},
  "geometry": {"coordinates":[5.740255,51.39571],"type":"Point"}
}