{
  "type": "Feature",
  "properties": {
    "addr:full":"Schrepelstr 23 Breda Noord-Brabant 4835 BC",
    "addr:housenumber":"23",
    "addr:postcode":"4835 bc",
    "addr:street":"Schrepelstr",
    "iso:country":"NL",
    "sg:address":"Schrepelstr 23",
    "sg:city":"Breda",
    "sg:orig_category":"Fotografie Reclame En Mode",
    "sg:phone":"+31 76 564 9155",
    "sg:postcode":"4835 BC",
    "sg:province":"Noord-Brabant",
    "wof:name":"Ren\u00e9 Van Dongen, Fotografie",
    "wof:placetype":"venue"
},
  "geometry": {"coordinates":[4.791592,51.573891],"type":"Point"}
}