{
  "type": "Feature",
  "properties": {
    "addr:full":"Kastelenstr 171 Amsterdam Noord-Holland 1082 ED",
    "addr:housenumber":"171",
    "addr:postcode":"1082 ed",
    "iso:country":"NL",
    "sg:address":"Kastelenstr 171",
    "sg:city":"Amsterdam",
    "sg:classifiers":[
        {
            "category":"Food & Beverages",
            "subcategory":"Bakery",
            "type":"Retail Goods"
        }
    ],
    "sg:phone":"+31 20 642 3501",
    "sg:postcode":"1082 ED",
    "sg:province":"Noord-Holland",
    "sg:tags":[
        "brood",
        "en",
        "banket"
    ],
    "wof:name":"B\u00f7Tcher",
    "wof:placetype":"venue"
},
  "geometry": {"coordinates":[4.874947,52.325718],"type":"Point"}
}