{
  "type": "Feature",
  "properties": {
    "addr:full":"Middelhoffstraat 5 Amsterdam Noord-Holland 1097 NJ",
    "addr:housenumber":"5",
    "addr:postcode":"1097 nj",
    "addr:street":"Middelhoffstraat",
    "iso:country":"NL",
    "sg:address":"Middelhoffstraat 5",
    "sg:city":"Amsterdam",
    "sg:orig_category":"Boekenuitgeverijen",
    "sg:phone":"+31 20 668 0824",
    "sg:postcode":"1097 NJ",
    "sg:province":"Noord-Holland",
    "wof:name":"Tutti-Frutti Produkties",
    "wof:placetype":"venue"
},
  "geometry": {"coordinates":[-74.2101821899,42.9482345581],"type":"Point"}
}