{
  "type": "Feature",
  "properties": {
    "addr:full":"Zandbergen 14 Rosmalen Noord-Brabant 5242 JC",
    "addr:housenumber":"14",
    "addr:postcode":"5242 jc",
    "addr:street":"Zandbergen",
    "iso:country":"NL",
    "sg:address":"Zandbergen 14",
    "sg:city":"Rosmalen",
    "sg:orig_category":"Artsen And Specialisten",
    "sg:phone":"+31 73 521 3788",
    "sg:postcode":"5242 JC",
    "sg:province":"Noord-Brabant",
    "wof:name":"J.F.M. Falke",
    "wof:placetype":"venue"
},
  "geometry": {"coordinates":[5.37374,51.708271],"type":"Point"}
}