{
  "type": "Feature",
  "properties": {
    "iso:country":"NL",
    "sg:address":"Clausstr 1",
    "sg:city":"Berghem",
    "sg:orig_category":"Horloges En Klokken",
    "sg:phone":"+31 412 401 684",
    "sg:postcode":"5351 CJ",
    "sg:province":"Noord-Brabant",
    "wof:name":"Orsouw Klokken, Van",
    "wof:placetype":"venue"
},
  "geometry": {"coordinates":[5.575205,51.772568],"type":"Point"}
}