{
  "type": "Feature",
  "properties": {
    "addr:full":"Roelvinkstraat 75 Winterswijk Gelderland 7101 GN",
    "addr:housenumber":"75",
    "addr:postcode":"7101 gn",
    "addr:street":"Roelvinkstraat;Gelderland",
    "iso:country":"NL",
    "sg:address":"Roelvinkstraat 75",
    "sg:city":"Winterswijk",
    "sg:orig_category":"Fotolaboratoria",
    "sg:phone":"+31 543 519 357",
    "sg:postcode":"7101 GN",
    "sg:province":"Gelderland",
    "wof:name":"Foto-Service",
    "wof:placetype":"venue"
},
  "geometry": {"coordinates":[6.717978,51.970924],"type":"Point"}
}