{
  "type": "Feature",
  "properties": {
    "iso:country":"NL",
    "sg:address":"Burgakker 6",
    "sg:city":"Boxtel",
    "sg:orig_category":"Loodgieterswerk, Verwarming And Sanitaire Installaties",
    "sg:phone":"+31 411 610 724",
    "sg:postcode":"5281 CH",
    "sg:province":"Noord-Brabant",
    "wof:name":"De Klussenier",
    "wof:placetype":"venue"
},
  "geometry": {"coordinates":[5.325603,51.587357],"type":"Point"}
}