{
  "type": "Feature",
  "properties": {
    "iso:country":"NL",
    "sg:address":"Brugstraat 50",
    "sg:city":"Mierlo",
    "sg:classifiers":[
        {
            "category":"Shopping",
            "subcategory":"Gifts & Souvenirs",
            "type":"Retail Goods"
        }
    ],
    "sg:phone":"+31 492 660 938",
    "sg:postcode":"5731 HJ",
    "sg:province":"Noord-Brabant",
    "sg:tags":[
        "geschenken"
    ],
    "wof:name":"Vof De Bruijn",
    "wof:placetype":"venue"
},
  "geometry": {"coordinates":[5.627936,51.450546],"type":"Point"}
}