{
  "type": "Feature",
  "properties": {
    "addr:full":"Hoffmeijerweg 2 Ambt Delden Overijssel 7495 RZ",
    "addr:housenumber":"2",
    "addr:postcode":"7495 rz",
    "addr:street":"Hoffmeijerweg",
    "iso:country":"NL",
    "sg:address":"Hoffmeijerweg 2",
    "sg:city":"Ambt Delden",
    "sg:orig_category":"Bloemen And Planten",
    "sg:phone":"+31 74 376 4206",
    "sg:postcode":"7495 RZ",
    "sg:province":"Overijssel",
    "wof:name":"L.B.M. Cattier",
    "wof:placetype":"venue"
},
  "geometry": {"coordinates":[6.651077,52.260422],"type":"Point"}
}