{
  "type": "Feature",
  "properties": {
    "addr:full":"Rykswg 46 Groningen Groningen 9731 AC",
    "addr:housenumber":"46",
    "addr:postcode":"9731 ac",
    "addr:street":"Rykswg",
    "iso:country":"NL",
    "sg:address":"Rykswg 46",
    "sg:city":"Groningen",
    "sg:orig_category":"Vertaalbureaus",
    "sg:phone":"+31 50 502 0969",
    "sg:postcode":"9731 AC",
    "sg:province":"Groningen",
    "sg:website":"http://www.voicesfromholland.nl/translations",
    "wof:name":"A & E Translations",
    "wof:placetype":"venue"
},
  "geometry": {"coordinates":[6.603957,53.227608],"type":"Point"}
}