{
  "type": "Feature",
  "properties": {
    "addr:full":"Molenstr 60 Westdorpe Zeeland 4554 LT",
    "addr:housenumber":"60",
    "addr:postcode":"4554 lt",
    "addr:street":"Molenstr",
    "iso:country":"NL",
    "sg:address":"Molenstr 60",
    "sg:city":"Westdorpe",
    "sg:classifiers":[
        {
            "category":"Food & Beverages",
            "subcategory":"Fruits & Vegetables",
            "type":"Retail Goods"
        }
    ],
    "sg:phone":"+31 115 451 767",
    "sg:postcode":"4554 LT",
    "sg:province":"Zeeland",
    "sg:tags":[
        "en",
        "groenten"
    ],
    "wof:name":"Vervaet-Thomaes Vof",
    "wof:placetype":"venue"
},
  "geometry": {"coordinates":[3.839239,51.225117],"type":"Point"}
}