{
  "type": "Feature",
  "properties": {
    "iso:country":"NL",
    "sg:address":"Geuzenweg 18",
    "sg:city":"Hilversum",
    "sg:classifiers":[
        {
            "category":"Fast Food",
            "type":"Food & Drink"
        }
    ],
    "sg:phone":"+31 35 685 1185",
    "sg:postcode":"1221 BT",
    "sg:province":"Noord-Holland",
    "sg:tags":[
        "afhaal",
        "restaurant"
    ],
    "wof:name":"Mitzi'S",
    "wof:placetype":"venue"
},
  "geometry": {"coordinates":[5.181816,52.228031],"type":"Point"}
}