{
  "type": "Feature",
  "properties": {
    "addr:full":"Florence Nightingalestraat 9 Ijsselstein (Ut) Utrecht 3404 XB",
    "addr:housenumber":"9",
    "addr:postcode":"3404 xb",
    "addr:street":"Florence Nightingalestraat",
    "iso:country":"NL",
    "sg:address":"Florence Nightingalestraat 9",
    "sg:city":"Ijsselstein (Ut)",
    "sg:orig_category":"Diverse Grafische Activiteiten",
    "sg:phone":"+31 30 687 5834",
    "sg:postcode":"3404 XB",
    "sg:province":"Utrecht",
    "wof:name":"Beet Vormgeving",
    "wof:placetype":"venue"
},
  "geometry": {"coordinates":[5.045482,52.013969],"type":"Point"}
}