{
  "type": "Feature",
  "properties": {
    "addr:full":"Oosterpk 53 Amsterdam Noord-Holland 1092 AP",
    "addr:housenumber":"53",
    "addr:postcode":"1092 ap",
    "addr:street":"Oosterpk",
    "iso:country":"NL",
    "sg:address":"Oosterpk 53",
    "sg:city":"Amsterdam",
    "sg:orig_category":"Video - Faciliteiten En Producties",
    "sg:phone":"+31 20 694 4483",
    "sg:postcode":"1092 AP",
    "sg:province":"Noord-Holland",
    "wof:name":"Nieuw Huis",
    "wof:placetype":"venue"
},
  "geometry": {"coordinates":[4.921475,52.358902],"type":"Point"}
}