{
  "type": "Feature",
  "properties": {
    "addr:full":"Orleanspln 18A Maastricht Limburg 6217 LB",
    "addr:housenumber":"18a",
    "addr:postcode":"6217 lb",
    "addr:street":"Orleanspln",
    "iso:country":"NL",
    "sg:address":"Orleanspln 18A",
    "sg:city":"Maastricht",
    "sg:orig_category":"Broodjeszaken",
    "sg:phone":"+31 43 354 0020",
    "sg:postcode":"6217 LB",
    "sg:province":"Limburg",
    "wof:name":"Jekerdal Vof",
    "wof:placetype":"venue"
},
  "geometry": {"coordinates":[5.673924,50.851212],"type":"Point"}
}