{
  "type": "Feature",
  "properties": {
    "addr:full":"Molenweg 27 Bergharen Gelderland 6617 BB",
    "addr:housenumber":"27",
    "addr:postcode":"6617 bb",
    "addr:street":"Molenweg;Gelderland",
    "iso:country":"NL",
    "sg:address":"Molenweg 27",
    "sg:city":"Bergharen",
    "sg:orig_category":"Banken And Kredietinstellingen",
    "sg:phone":"+31 487 532 141",
    "sg:postcode":"6617 BB",
    "sg:province":"Gelderland",
    "wof:name":"Arntz Assurantien",
    "wof:placetype":"venue"
},
  "geometry": {"coordinates":[5.6687,51.852928],"type":"Point"}
}