{
  "type": "Feature",
  "properties": {
    "addr:full":"Koninginnewg 31 Hilversum Noord-Holland 1217 KR",
    "addr:housenumber":"31",
    "addr:postcode":"1217 kr",
    "addr:street":"Koninginnewg",
    "iso:country":"NL",
    "sg:address":"Koninginnewg 31",
    "sg:city":"Hilversum",
    "sg:orig_category":"Omroep",
    "sg:phone":"+31 35 538 5538",
    "sg:postcode":"1217 KR",
    "sg:province":"Noord-Holland",
    "wof:name":"Radio 538",
    "wof:placetype":"venue"
},
  "geometry": {"coordinates":[5.171287,52.230179],"type":"Point"}
}