{
  "type": "Feature",
  "properties": {
    "iso:country":"NL",
    "sg:address":"Jodenstraat 28",
    "sg:city":"Venlo",
    "sg:orig_category":"Kappers",
    "sg:phone":"+31 77 351 5679",
    "sg:postcode":"5911 HK",
    "sg:province":"Limburg",
    "wof:name":"H.G.A.M. Buchholz",
    "wof:placetype":"venue"
},
  "geometry": {"coordinates":[6.1666588783,51.3691444397],"type":"Point"}
}