{
  "type": "Feature",
  "properties": {
    "addr:full":"Hoekse Aarkd 7 Ter Aar Zuid-Holland 2461 ET",
    "addr:housenumber":"7",
    "addr:postcode":"aar;2461 et",
    "addr:street":"Aarkd",
    "iso:country":"NL",
    "sg:address":"Hoekse Aarkd 7",
    "sg:city":"Ter Aar",
    "sg:orig_category":"Scheepswerven",
    "sg:phone":"+31 172 602 143",
    "sg:postcode":"2461 ET",
    "sg:province":"Zuid-Holland",
    "wof:name":"Ruig En Zn, De",
    "wof:placetype":"venue"
},
  "geometry": {"coordinates":[4.730787,52.181202],"type":"Point"}
}