{
  "type": "Feature",
  "properties": {
    "addr:full":"J S Bachln 167 Leidschendam Zuid-Holland 2264 WD",
    "addr:housenumber":"167",
    "addr:postcode":"2264 wd",
    "iso:country":"NL",
    "sg:address":"J S Bachln 167",
    "sg:city":"Leidschendam",
    "sg:orig_category":"Hypotheken",
    "sg:phone":"+31 70 444 2223",
    "sg:postcode":"2264 WD",
    "sg:province":"Zuid-Holland",
    "sg:website":"http://www.huis-hypotheek.nl",
    "wof:name":"Huis & Hypotheek",
    "wof:placetype":"venue"
},
  "geometry": {"coordinates":[4.393446,52.084591],"type":"Point"}
}