{
  "type": "Feature",
  "properties": {
    "addr:full":"Dr V Heeswg 1 Zwolle Overijssel 8025 AB",
    "addr:housenumber":"1",
    "addr:postcode":"8025 ab",
    "addr:street":"Dr;Heeswg",
    "iso:country":"NL",
    "sg:address":"Dr V Heeswg 1",
    "sg:city":"Zwolle",
    "sg:orig_category":"Scholen Voor Algemeen Voortgezet Onderwijs",
    "sg:phone":"+31 38 456 4560",
    "sg:postcode":"8025 AB",
    "sg:province":"Overijssel",
    "sg:website":"http://www.thorbecke-zwolle.nl",
    "wof:name":"Thorbecke Scholengemeenschap",
    "wof:placetype":"venue"
},
  "geometry": {"coordinates":[6.12659,52.51054],"type":"Point"}
}