{
  "type": "Feature",
  "properties": {
    "addr:full":"Huenderwg 18 Doldersum Drenthe 8386 XB",
    "addr:housenumber":"18",
    "addr:postcode":"8386 xb",
    "addr:street":"Huenderwg",
    "iso:country":"NL",
    "sg:address":"Huenderwg 18",
    "sg:city":"Doldersum",
    "sg:orig_category":"Pluimveebedrijven En -Handelaren",
    "sg:phone":"+31 521 387 209",
    "sg:postcode":"8386 XB",
    "sg:province":"Drenthe",
    "wof:name":"Schipper, Maatschap",
    "wof:placetype":"venue"
},
  "geometry": {"coordinates":[6.244348,52.884552],"type":"Point"}
}