{
  "type": "Feature",
  "properties": {
    "addr:full":"Julianastraat 34 Vlijmen Noord-Brabant 5251 ED",
    "addr:housenumber":"34",
    "addr:postcode":"5251 ed",
    "addr:street":"Julianastraat",
    "iso:country":"NL",
    "sg:address":"Julianastraat 34",
    "sg:city":"Vlijmen",
    "sg:orig_category":"Overheidsdiensten",
    "sg:phone":"+31 73 513 1789",
    "sg:postcode":"5251 ED",
    "sg:province":"Noord-Brabant",
    "wof:name":"Gemeente Vlijmen",
    "wof:placetype":"venue"
},
  "geometry": {"coordinates":[5.2217597961,51.6975631714],"type":"Point"}
}