{
  "type": "Feature",
  "properties": {
    "iso:country":"NL",
    "sg:address":"Weena 695",
    "sg:city":"Rotterdam",
    "sg:orig_category":"Hypotheken And Hypotheekbanken",
    "sg:phone":"+31 10 280 9910",
    "sg:postcode":"3013 AM",
    "sg:province":"Zuid-Holland",
    "wof:name":"Financiele Raadgevers Associatie Rotterdam Cv",
    "wof:placetype":"venue"
},
  "geometry": {"coordinates":[4.468776,51.92292],"type":"Point"}
}