{
  "type": "Feature",
  "properties": {
    "iso:country":"NL",
    "sg:address":"Brinkstraat 65",
    "sg:city":"Losser",
    "sg:orig_category":"Kappers",
    "sg:phone":"+31 53 538 1247",
    "sg:postcode":"7581 GB",
    "sg:province":"NL.08",
    "wof:name":"Kapsalon Koekenberg - Zurhorst",
    "wof:placetype":"venue"
},
  "geometry": {"coordinates":[7.0080690384,52.2636871338],"type":"Point"}
}