{
  "type": "Feature",
  "properties": {
    "addr:full":"Past Scholtenwg 9 Buren Fr Provincie Friesland 9164 KK",
    "addr:housenumber":"9",
    "addr:postcode":"9164 kk",
    "addr:street":"Friesland",
    "iso:country":"NL",
    "sg:address":"Past Scholtenwg 9",
    "sg:city":"Buren Fr",
    "sg:orig_category":"Groepsaccommodaties",
    "sg:phone":"+31 519 542 197",
    "sg:postcode":"9164 KK",
    "sg:province":"Provincie Friesland",
    "wof:name":"Westhoek, De",
    "wof:placetype":"venue"
},
  "geometry": {"coordinates":[5.796282,53.447182],"type":"Point"}
}