{
  "type": "Feature",
  "properties": {
    "addr:full":"Tapijtwg 2 Den Haag Zuid-Holland 2597 KH",
    "addr:housenumber":"2",
    "addr:postcode":"2597 kh",
    "addr:street":"Tapijtwg",
    "iso:country":"NL",
    "sg:address":"Tapijtwg 2",
    "sg:city":"Den Haag",
    "sg:orig_category":"Loopbaanbegeleiding",
    "sg:phone":"+31 70 351 4011",
    "sg:postcode":"2597 KH",
    "sg:province":"Zuid-Holland",
    "sg:website":"http://www.vanede.nl/indexgg.htm",
    "wof:name":"Ede & Partners Outplacement, Van",
    "wof:placetype":"venue"
},
  "geometry": {"coordinates":[4.304809,52.103668],"type":"Point"}
}