{
  "type": "Feature",
  "properties": {
    "iso:country":"NL",
    "sg:address":"Appelweg 11",
    "sg:city":"Moerdijk",
    "sg:orig_category":"Huisdierenvoer Fab",
    "sg:phone":"+31 168 415 350",
    "sg:postcode":"4782 PX",
    "sg:province":"Noord-Brabant",
    "wof:name":"Continentale Nutrition Ned Bv",
    "wof:placetype":"venue"
},
  "geometry": {"coordinates":[4.613371,51.69949],"type":"Point"}
}