{
  "type": "Feature",
  "properties": {
    "addr:full":"Groenhof 38 Amstelveen Noord-Holland 1186 ER",
    "addr:housenumber":"38",
    "addr:postcode":"1186 er",
    "addr:street":"Groenhof",
    "iso:country":"NL",
    "sg:address":"Groenhof 38",
    "sg:city":"Amstelveen",
    "sg:orig_category":"Verzekeringen - Verzekeringskantoren",
    "sg:phone":"+31 20 697 7799",
    "sg:postcode":"1186 ER",
    "sg:province":"Noord-Holland",
    "wof:name":"Boemerang, De",
    "wof:placetype":"venue"
},
  "geometry": {"coordinates":[4.869147,52.28973],"type":"Point"}
}