{
  "type": "Feature",
  "properties": {
    "iso:country":"NL",
    "sg:address":"Bemuurde Weerd Oz 1",
    "sg:city":"Utrecht",
    "sg:orig_category":"Loopbaanbegeleiding",
    "sg:phone":"+31 30 275 8460",
    "sg:postcode":"3514 AN",
    "sg:province":"Utrecht",
    "wof:name":"Octant",
    "wof:placetype":"venue"
},
  "geometry": {"coordinates":[5.116025,52.096657],"type":"Point"}
}