{
  "type": "Feature",
  "properties": {
    "addr:full":"Maasstraat 17 Schiedam Zuid-Holland 3114 NL",
    "addr:housenumber":"17",
    "addr:postcode":"3114 nl",
    "addr:street":"Maasstraat",
    "iso:country":"NL",
    "sg:address":"Maasstraat 17",
    "sg:city":"Schiedam",
    "sg:orig_category":"Metaalbekleding And -Behandeling",
    "sg:phone":"+31 10 473 2728",
    "sg:postcode":"3114 NL",
    "sg:province":"Zuid-Holland",
    "wof:name":"Contax",
    "wof:placetype":"venue"
},
  "geometry": {"coordinates":[4.403491,51.907444],"type":"Point"}
}