{
  "type": "Feature",
  "properties": {
    "iso:country":"NL",
    "sg:address":"Brinkhovenlaan 8",
    "sg:city":"Paterswolde",
    "sg:orig_category":"Fotostudio'S And Fotografen",
    "sg:phone":"+31 50 309 6871",
    "sg:postcode":"9765 BK",
    "sg:province":"Drenthe",
    "wof:name":"Rik Doorenbos",
    "wof:placetype":"venue"
},
  "geometry": {"coordinates":[6.569175,53.15033],"type":"Point"}
}