{
  "type": "Feature",
  "properties": {
    "addr:full":"Nyendal 13 Driebergen Rysenb Utrecht 3972 KC",
    "addr:housenumber":"13",
    "addr:postcode":"3972 kc",
    "addr:street":"Nyendal;Rysenb",
    "iso:country":"NL",
    "sg:address":"Nyendal 13",
    "sg:city":"Driebergen Rysenb",
    "sg:orig_category":"Psychotherapeuten",
    "sg:phone":"+31 343 520 355",
    "sg:postcode":"3972 KC",
    "sg:province":"Utrecht",
    "wof:name":"Buurmeijer, Dr F A",
    "wof:placetype":"venue"
},
  "geometry": {"coordinates":[5.283655,52.051552],"type":"Point"}
}