{
  "type": "Feature",
  "properties": {
    "addr:full":"Boulevard 37 Zeist Utrecht 3707 BL",
    "addr:housenumber":"37",
    "addr:postcode":"3707 bl",
    "addr:street":"Boulevard",
    "iso:country":"NL",
    "sg:address":"Boulevard 37",
    "sg:city":"Zeist",
    "sg:orig_category":"Kantoor- En Secretariaatsservice",
    "sg:phone":"+31 30 692 4231",
    "sg:postcode":"3707 BL",
    "sg:province":"Utrecht",
    "wof:name":"Document Center, The",
    "wof:placetype":"venue"
},
  "geometry": {"coordinates":[5.2553739548,52.101272583],"type":"Point"}
}