{
  "type": "Feature",
  "properties": {
    "iso:country":"NL",
    "sg:address":"Boterdorpse Verlaat 1",
    "sg:city":"Rotterdam",
    "sg:orig_category":"Werving And Selectie Van Vast Personeel",
    "sg:phone":"+31 10 418 8526",
    "sg:postcode":"3055 XA",
    "sg:province":"South Holland",
    "wof:name":"T.A.C.K. International",
    "wof:placetype":"venue"
},
  "geometry": {"coordinates":[4.5074520111,51.9522247314],"type":"Point"}
}