{
  "type": "Feature",
  "properties": {
    "addr:full":"Pr Hendrikln 21 Driebergen Rysenb Utrecht 3972 EV",
    "addr:housenumber":"21",
    "addr:street":"Driebergen Rysenb",
    "iso:country":"NL",
    "sg:address":"Pr Hendrikln 21",
    "sg:city":"Driebergen Rysenb",
    "sg:orig_category":"Woningstoffeerders",
    "sg:phone":"+31 6 22920538",
    "sg:postcode":"3972 EV",
    "sg:province":"Utrecht",
    "wof:name":"Roembeek",
    "wof:placetype":"venue"
},
  "geometry": {"coordinates":[5.2836551666,52.0515518188],"type":"Point"}
}