{
  "type": "Feature",
  "properties": {
    "addr:full":"Domselaerstr 18 Amsterdam North Holland 1093 MA",
    "addr:housenumber":"18",
    "addr:postcode":"1093 ma",
    "addr:street":"Domselaerstr",
    "iso:country":"NL",
    "sg:address":"Domselaerstr 18",
    "sg:city":"Amsterdam",
    "sg:orig_category":"Psychologen",
    "sg:phone":"+31 20 465 1297",
    "sg:postcode":"1093 MA",
    "sg:province":"North Holland",
    "wof:name":"Fopma",
    "wof:placetype":"venue"
},
  "geometry": {"coordinates":[4.926382,52.359474],"type":"Point"}
}