{
  "type": "Feature",
  "properties": {
    "addr:full":"De Kalkovens 10 Zwartsluis Overijssel 8064 PS",
    "addr:housenumber":"10",
    "addr:postcode":"8064 ps",
    "addr:street":"De Kalkovens",
    "iso:country":"NL",
    "sg:address":"De Kalkovens 10",
    "sg:city":"Zwartsluis",
    "sg:orig_category":"Verpakkingen En Verpakkingsmaterialen",
    "sg:phone":"+31 38 386 7111",
    "sg:postcode":"8064 PS",
    "sg:province":"Overijssel",
    "wof:name":"Besto Bv",
    "wof:placetype":"venue"
},
  "geometry": {"coordinates":[6.087893,52.647202],"type":"Point"}
}