{
  "type": "Feature",
  "properties": {
    "addr:full":"Koenraadlaan 100 Eindhoven Noord-Brabant 5651 EZ",
    "addr:housenumber":"100",
    "addr:postcode":"5651 ez",
    "addr:street":"Koenraadlaan",
    "iso:country":"NL",
    "sg:address":"Koenraadlaan 100",
    "sg:city":"Eindhoven",
    "sg:orig_category":"Overheidsdiensten",
    "sg:phone":"+31 40 252 5388",
    "sg:postcode":"5651 EZ",
    "sg:province":"Noord-Brabant",
    "wof:name":"Circulo Espanol Strijp",
    "wof:placetype":"venue"
},
  "geometry": {"coordinates":[5.4469280243,51.4460220337],"type":"Point"}
}