{
  "type": "Feature",
  "properties": {
    "addr:full":"Witherenstraat Venlo Limburg 5921 GC",
    "addr:postcode":"5921 gc",
    "addr:street":"Witherenstraat",
    "iso:country":"NL",
    "sg:address":"Witherenstraat",
    "sg:city":"Venlo",
    "sg:orig_category":"Winkelcentra",
    "sg:phone":"+31 336",
    "sg:postcode":"5921 GC",
    "sg:province":"Limburg",
    "wof:name":"Venlo Winkelcentrum De Wieen",
    "wof:placetype":"venue"
},
  "geometry": {"coordinates":[6.1489048004,51.3671112061],"type":"Point"}
}