{
  "type": "Feature",
  "properties": {
    "iso:country":"NL",
    "sg:address":"Schelpenhoek 29",
    "sg:city":"Diemen",
    "sg:orig_category":"Diverse Consumentenartikelen Gh",
    "sg:phone":"+31 20 461 6161",
    "sg:postcode":"1112 DG",
    "sg:province":"North Holland",
    "wof:name":"A. Maas",
    "wof:placetype":"venue"
},
  "geometry": {"coordinates":[4.960164,52.33511],"type":"Point"}
}