{
  "type": "Feature",
  "properties": {
    "addr:full":"Langstraat 36 Geldrop Noord-Brabant 5664 GH",
    "addr:housenumber":"36",
    "addr:postcode":"5664 gh",
    "addr:street":"Langstraat",
    "iso:country":"NL",
    "sg:address":"Langstraat 36",
    "sg:city":"Geldrop",
    "sg:orig_category":"Discountwinkels",
    "sg:phone":"+31 40 280 0110",
    "sg:postcode":"5664 GH",
    "sg:province":"Noord-Brabant",
    "wof:name":"Zeeman Textielsupers",
    "wof:placetype":"venue"
},
  "geometry": {"coordinates":[5.559153,51.421059],"type":"Point"}
}