{
  "type": "Feature",
  "properties": {
    "addr:full":"Hammerweg 3 Dalfsen Overijssel 7722 HW",
    "addr:housenumber":"3",
    "addr:postcode":"7722 hw",
    "addr:street":"Hammerweg",
    "iso:country":"NL",
    "sg:address":"Hammerweg 3",
    "sg:city":"Dalfsen",
    "sg:orig_category":"Hoefdierhouderijen",
    "sg:phone":"+31 529 458 300",
    "sg:postcode":"7722 HW",
    "sg:province":"Overijssel",
    "wof:name":"D.B. Nanning",
    "wof:placetype":"venue"
},
  "geometry": {"coordinates":[6.329929,52.500607],"type":"Point"}
}