{
  "type": "Feature",
  "properties": {
    "iso:country":"NL",
    "sg:address":"Parallelwg W 45A",
    "sg:city":"Culemborg",
    "sg:orig_category":"Kabels",
    "sg:phone":"+31 345 515 262",
    "sg:postcode":"4107 NA",
    "sg:province":"Gelderland",
    "wof:name":"Tasker Vof",
    "wof:placetype":"venue"
},
  "geometry": {"coordinates":[5.2344918251,51.9374313354],"type":"Point"}
}