{
  "type": "Feature",
  "properties": {
    "addr:full":"Dorpswg 3 Poederoyen CN. 5307 HK",
    "addr:housenumber":"3",
    "addr:postcode":"5307 hk",
    "addr:street":"Dorpswg;Cn.",
    "iso:country":"NL",
    "sg:address":"Dorpswg 3",
    "sg:city":"Poederoyen",
    "sg:orig_category":"Kappers",
    "sg:phone":"+31 418 671 403",
    "sg:postcode":"5307 HK",
    "sg:province":"CN.",
    "wof:name":"Elina",
    "wof:placetype":"venue"
},
  "geometry": {"coordinates":[114.1535415649,22.4112491608],"type":"Point"}
}