{
  "type": "Feature",
  "properties": {
    "iso:country":"NL",
    "sg:address":"Parkwg 196",
    "sg:city":"Voorburg",
    "sg:classifiers":[
        {
            "category":"Personal",
            "subcategory":"Nail Salon",
            "type":"Services"
        }
    ],
    "sg:phone":"+31 70 386 4134",
    "sg:postcode":"2271 BE",
    "sg:province":"Zuid-Holland",
    "sg:tags":[
        "pedicure"
    ],
    "wof:name":"Bruin, J De",
    "wof:placetype":"venue"
},
  "geometry": {"coordinates":[4.370486,52.073452],"type":"Point"}
}