{
  "type": "Feature",
  "properties": {
    "addr:full":"Jonkerslaan 2 Grijpskerk Groningen 9843 BS",
    "addr:housenumber":"2",
    "addr:postcode":"9843 bs",
    "addr:street":"Jonkerslaan",
    "iso:country":"NL",
    "sg:address":"Jonkerslaan 2",
    "sg:city":"Grijpskerk",
    "sg:orig_category":"Wasserettes And Stomerijen",
    "sg:phone":"+31 594 212 780",
    "sg:postcode":"9843 BS",
    "sg:province":"Groningen",
    "wof:name":"Gerner Stomen",
    "wof:placetype":"venue"
},
  "geometry": {"coordinates":[6.3074469566,53.2632141113],"type":"Point"}
}