{
  "type": "Feature",
  "properties": {
    "addr:full":"Hazelaarlaan 17 Berkel-Enschot Noord-Brabant 5056 XM",
    "addr:housenumber":"17",
    "addr:postcode":"5056 xm",
    "addr:street":"Hazelaarlaan",
    "iso:country":"NL",
    "sg:address":"Hazelaarlaan 17",
    "sg:city":"Berkel-Enschot",
    "sg:orig_category":"Vertaal- And Tolkenbureaus",
    "sg:phone":"+31 13 533 4693",
    "sg:postcode":"5056 XM",
    "sg:province":"Noord-Brabant",
    "wof:name":"Textservice Intfrans Bv",
    "wof:placetype":"venue"
},
  "geometry": {"coordinates":[5.15073,51.586956],"type":"Point"}
}