{
  "type": "Feature",
  "properties": {
    "addr:full":"Keizersgr 462 Amsterdam Noord-Holland 1016 GE",
    "addr:housenumber":"462",
    "addr:postcode":"1016",
    "iso:country":"NL",
    "sg:address":"Keizersgr 462",
    "sg:city":"Amsterdam",
    "sg:orig_category":"Verenigingen En Stichtingen",
    "sg:phone":"+31 20 420 7729",
    "sg:postcode":"1016 GE",
    "sg:province":"Noord-Holland",
    "sg:website":"http://www.wwvf.nl",
    "wof:name":"World Wide Video Festival",
    "wof:placetype":"venue"
},
  "geometry": {"coordinates":[4.884372,52.36694],"type":"Point"}
}