{
  "type": "Feature",
  "properties": {
    "iso:country":"NL",
    "sg:address":"Waterhuizerwg 34",
    "sg:city":"Haren Gn",
    "sg:orig_category":"Verzekeringen - Verzekeringskantoren",
    "sg:phone":"+31 50 534 4030",
    "sg:postcode":"9753 HS",
    "sg:province":"Groningen",
    "wof:name":"Grijs, De",
    "wof:placetype":"venue"
},
  "geometry": {"coordinates":[6.627138,53.169476],"type":"Point"}
}