{
  "type": "Feature",
  "properties": {
    "addr:full":"Kuperserf 1 Nijverdal Overijssel 7443 HC",
    "addr:housenumber":"1",
    "addr:postcode":"7443 hc",
    "addr:street":"Kuperserf",
    "iso:country":"NL",
    "sg:address":"Kuperserf 1",
    "sg:city":"Nijverdal",
    "sg:classifiers":[
        {
            "category":"Education",
            "subcategory":"Preschool",
            "type":"Public Place"
        }
    ],
    "sg:phone":"+31 548 617 329",
    "sg:postcode":"7443 HC",
    "sg:province":"Overijssel",
    "sg:tags":[
        "kleuteronderwijs",
        "basis-"
    ],
    "wof:name":"Kath Basisschool De Triangel",
    "wof:placetype":"venue"
},
  "geometry": {"coordinates":[6.482702,52.377045],"type":"Point"}
}