{
  "type": "Feature",
  "properties": {
    "addr:full":"T Haartje 16 Amersfoort Utrecht 3824 MS",
    "addr:housenumber":"16",
    "addr:postcode":"3824 ms",
    "addr:street":"T Haartje",
    "iso:country":"NL",
    "sg:address":"T Haartje 16",
    "sg:city":"Amersfoort",
    "sg:orig_category":"Architecten En Architectenbureaus",
    "sg:phone":"+31 33 456 3337",
    "sg:postcode":"3824 MS",
    "sg:province":"Utrecht",
    "wof:name":"Huisman, Derk-Jan",
    "wof:placetype":"venue"
},
  "geometry": {"coordinates":[5.390696,52.200439],"type":"Point"}
}