{
  "type": "Feature",
  "properties": {
    "addr:full":"Vlak 1 Dordrecht Zuid-Holland 3311 AT",
    "addr:housenumber":"1",
    "addr:postcode":"3311",
    "addr:street":"Vlak",
    "iso:country":"NL",
    "sg:address":"Vlak 1",
    "sg:city":"Dordrecht",
    "sg:orig_category":"Verenigingen En Stichtingen",
    "sg:phone":"+31 78 613 9676",
    "sg:postcode":"3311 AT",
    "sg:province":"Zuid-Holland",
    "wof:name":"Amicitia",
    "wof:placetype":"venue"
},
  "geometry": {"coordinates":[4.664629,51.817581],"type":"Point"}
}