{
  "type": "Feature",
  "properties": {
    "addr:full":"Meieryln 21 Kaatsheuvel Noord-Brabant 5171 ZN",
    "addr:housenumber":"21",
    "addr:postcode":"5171 zn",
    "addr:street":"Meieryln",
    "iso:country":"NL",
    "sg:address":"Meieryln 21",
    "sg:city":"Kaatsheuvel",
    "sg:orig_category":"Sportverenigingen En Ontspannings- Verenigingen",
    "sg:phone":"+31 416 282 279",
    "sg:postcode":"5171 ZN",
    "sg:province":"Noord-Brabant",
    "wof:name":"Desk, Handbalver",
    "wof:placetype":"venue"
},
  "geometry": {"coordinates":[5.033175,51.659588],"type":"Point"}
}