{
  "type": "Feature",
  "properties": {
    "addr:full":"Gyzenrooisewg 11 Geldrop Noord-Brabant 5661 MA",
    "addr:housenumber":"11",
    "addr:postcode":"5661 ma",
    "addr:street":"Gyzenrooisewg",
    "iso:country":"NL",
    "sg:address":"Gyzenrooisewg 11",
    "sg:city":"Geldrop",
    "sg:orig_category":"Kinderopvang",
    "sg:phone":"+31 40 286 1185",
    "sg:postcode":"5661 MA",
    "sg:province":"Noord-Brabant",
    "wof:name":"Potje Knor",
    "wof:placetype":"venue"
},
  "geometry": {"coordinates":[5.541649,51.414326],"type":"Point"}
}