{
  "type": "Feature",
  "properties": {
    "addr:full":"Nyverheidswg 2 Goor Overijssel 7471 EV",
    "addr:housenumber":"2",
    "addr:postcode":"7471 ev",
    "addr:street":"Nyverheidswg",
    "iso:country":"NL",
    "sg:address":"Nyverheidswg 2",
    "sg:city":"Goor",
    "sg:orig_category":"Meubelen - Fabrieken En Groothandel",
    "sg:phone":"+31 547 274 680",
    "sg:postcode":"7471 EV",
    "sg:province":"Overijssel",
    "wof:name":"Bendic Int Bv",
    "wof:placetype":"venue"
},
  "geometry": {"coordinates":[6.578333,52.243496],"type":"Point"}
}