{
  "type": "Feature",
  "properties": {
    "iso:country":"NL",
    "sg:address":"Industriestr 90",
    "sg:city":"Tegelen",
    "sg:orig_category":"Poeliers",
    "sg:phone":"+31 77 373 2316",
    "sg:postcode":"5931 PK",
    "sg:province":"Limburg",
    "wof:name":"Franssen",
    "wof:placetype":"venue"
},
  "geometry": {"coordinates":[6.141848,51.339142],"type":"Point"}
}