{
  "type": "Feature",
  "properties": {
    "iso:country":"NL",
    "sg:address":"Strandweg 37",
    "sg:city":"Buren Fr",
    "sg:orig_category":"Watersport-, Sport- And Kampeerbenodigdheden Verhuur",
    "sg:phone":"+31 519 542 417",
    "sg:postcode":"9164 KA",
    "sg:province":"Friesland",
    "wof:name":"H.J.Metz",
    "wof:placetype":"venue"
},
  "geometry": {"coordinates":[5.8006711006,53.4506912231],"type":"Point"}
}