{
  "type": "Feature",
  "properties": {
    "addr:full":"Berkenlaan 11 Barneveld Gelderland 3771 XV",
    "addr:housenumber":"11",
    "addr:postcode":"3771 xv",
    "addr:street":"Berkenlaan;Gelderland",
    "iso:country":"NL",
    "sg:address":"Berkenlaan 11",
    "sg:city":"Barneveld",
    "sg:orig_category":"Verzekeringen",
    "sg:phone":"+31 342 413 884",
    "sg:postcode":"3771 XV",
    "sg:province":"Gelderland",
    "wof:name":"Vons Barneveld Bv",
    "wof:placetype":"venue"
},
  "geometry": {"coordinates":[5.58929,52.149788],"type":"Point"}
}