{
  "type": "Feature",
  "properties": {
    "addr:full":"Fatimastr 60 Breda Noord-Brabant 4835 BD",
    "addr:housenumber":"60",
    "addr:postcode":"4835 bd",
    "addr:street":"Fatimastr",
    "iso:country":"NL",
    "sg:address":"Fatimastr 60",
    "sg:city":"Breda",
    "sg:orig_category":"Psychotherapeuten",
    "sg:phone":"+31 76 561 3421",
    "sg:postcode":"4835 BD",
    "sg:province":"Noord-Brabant",
    "wof:name":"Debats, Rose-Marie",
    "wof:placetype":"venue"
},
  "geometry": {"coordinates":[4.791702,51.574165],"type":"Point"}
}