{
  "type": "Feature",
  "properties": {
    "addr:full":"Archimedeswg 18 Leeuwarden Friesland 8912 AK",
    "addr:housenumber":"18",
    "addr:postcode":"8912 ak",
    "addr:street":"Archimedeswg",
    "iso:country":"NL",
    "sg:address":"Archimedeswg 18",
    "sg:city":"Leeuwarden",
    "sg:orig_category":"Betonwerken",
    "sg:phone":"+31 58 212 0014",
    "sg:postcode":"8912 AK",
    "sg:province":"Friesland",
    "wof:name":"Adema Betonrenovatie",
    "wof:placetype":"venue"
},
  "geometry": {"coordinates":[5.759575,53.195595],"type":"Point"}
}