{
  "type": "Feature",
  "properties": {
    "addr:full":"Parkwg 14 Zwolle Overijssel 8011 CK",
    "addr:housenumber":"14",
    "addr:postcode":"8011 ck",
    "addr:street":"Parkwg",
    "iso:country":"NL",
    "sg:address":"Parkwg 14",
    "sg:city":"Zwolle",
    "sg:orig_category":"Hulpverlening Sociaal",
    "sg:phone":"+31 38 426 8520",
    "sg:postcode":"8011 CK",
    "sg:province":"Overijssel",
    "wof:name":"Driehoek, De",
    "wof:placetype":"venue"
},
  "geometry": {"coordinates":[6.087962,52.508236],"type":"Point"}
}