{
  "type": "Feature",
  "properties": {
    "iso:country":"NL",
    "sg:address":"Koningin Julianaplein 10",
    "sg:city":"'S Gravenhage",
    "sg:orig_category":"Fietshandelaren",
    "sg:phone":"+31 70 385 3235",
    "sg:postcode":"2595 AA",
    "sg:province":"Zuid-Holland",
    "wof:name":"Rijwielshop Den Haag Cs",
    "wof:placetype":"venue"
},
  "geometry": {"coordinates":[4.32391,52.081871],"type":"Point"}
}