{
  "type": "Feature",
  "properties": {
    "addr:full":"Philipshoofjeswg 57 Dirksland South Holland 3247 XR",
    "addr:housenumber":"57",
    "addr:postcode":"3247 xr",
    "addr:street":"Philipshoofjeswg",
    "iso:country":"NL",
    "sg:address":"Philipshoofjeswg 57",
    "sg:city":"Dirksland",
    "sg:orig_category":"Verenigingsgebouwen",
    "sg:phone":"+31 187 601 696",
    "sg:postcode":"3247 XR",
    "sg:province":"South Holland",
    "wof:name":"West, Buurtver",
    "wof:placetype":"venue"
},
  "geometry": {"coordinates":[4.093066,51.745407],"type":"Point"}
}