{
  "type": "Feature",
  "properties": {
    "addr:full":"T Van De Lindenstraat 42 Noordwijk Zh South Holland 2202 VR",
    "addr:housenumber":"42",
    "addr:postcode":"zh;2202 vr",
    "addr:street":"De Lindenstraat",
    "iso:country":"NL",
    "sg:address":"T Van De Lindenstraat 42",
    "sg:city":"Noordwijk Zh",
    "sg:orig_category":"Bloemen And Planten Gh",
    "sg:phone":"+31 71 361 5482",
    "sg:postcode":"2202 VR",
    "sg:province":"South Holland",
    "wof:name":"M.C.M. Van Stein",
    "wof:placetype":"venue"
},
  "geometry": {"coordinates":[4.446002,52.247967],"type":"Point"}
}