{
  "type": "Feature",
  "properties": {
    "addr:full":"Apollolaan 15 Wildervank Groningen 9648 CK",
    "addr:housenumber":"15",
    "addr:postcode":"9648 ck",
    "addr:street":"Apollolaan",
    "iso:country":"NL",
    "sg:address":"Apollolaan 15",
    "sg:city":"Wildervank",
    "sg:classifiers":[
        {
            "category":"Fast Food",
            "type":"Food & Drink"
        }
    ],
    "sg:phone":"+31 598 630 113",
    "sg:postcode":"9648 CK",
    "sg:province":"Groningen",
    "sg:tags":[
        "afhaal",
        "restaurant"
    ],
    "wof:name":"Restaria Royaal Vof",
    "wof:placetype":"venue"
},
  "geometry": {"coordinates":[6.865055,53.085835],"type":"Point"}
}