{
  "type": "Feature",
  "properties": {
    "addr:full":"Stationsweg 149A Zuidlaren Drenthe 9471 GP",
    "addr:housenumber":"149a",
    "addr:postcode":"9471 gp",
    "addr:street":"Stationsweg",
    "iso:country":"NL",
    "sg:address":"Stationsweg 149A",
    "sg:city":"Zuidlaren",
    "sg:orig_category":"Boekhandels",
    "sg:phone":"+31 50 409 0900",
    "sg:postcode":"9471 GP",
    "sg:province":"Drenthe",
    "wof:name":"Stripsonline/Infaccom",
    "wof:placetype":"venue"
},
  "geometry": {"coordinates":[6.670373,53.091148],"type":"Point"}
}