{
  "type": "Feature",
  "properties": {
    "addr:full":"Plantsoengracht 1 Purmerend Noord-Holland 1441 DE",
    "addr:housenumber":"1",
    "addr:postcode":"1441 de",
    "addr:street":"Plantsoengracht",
    "iso:country":"NL",
    "sg:address":"Plantsoengracht 1",
    "sg:city":"Purmerend",
    "sg:orig_category":"Verzekeringen",
    "sg:phone":"+31 299 424 551",
    "sg:postcode":"1441 DE",
    "sg:province":"Noord-Holland",
    "wof:name":"Kocken Assurantien",
    "wof:placetype":"venue"
},
  "geometry": {"coordinates":[4.951308,52.50811],"type":"Point"}
}