{
  "type": "Feature",
  "properties": {
    "addr:full":"Haringbuiswg 35 Vlaardingen South Holland 3133 KP",
    "addr:housenumber":"35",
    "addr:postcode":"3133 kp",
    "addr:street":"Haringbuiswg",
    "iso:country":"NL",
    "sg:address":"Haringbuiswg 35",
    "sg:city":"Vlaardingen",
    "sg:orig_category":"Accountants - Administratie- Consulenten En -Kantoren",
    "sg:phone":"+31 10 445 2500",
    "sg:postcode":"3133 KP",
    "sg:province":"South Holland",
    "wof:name":"Houwelingen Vof, Van",
    "wof:placetype":"venue"
},
  "geometry": {"coordinates":[4.311672,51.898327],"type":"Point"}
}