{
  "type": "Feature",
  "properties": {
    "iso:country":"NL",
    "sg:address":"Bijlmerplein 556",
    "sg:city":"Amsterdam Zuidoost",
    "sg:orig_category":"Huishoudapparatuur, Televisies And Radio'S",
    "sg:phone":"+31 20 691 2614",
    "sg:postcode":"1102 DS",
    "sg:province":"Noord-Holland",
    "wof:name":"Modern Electronics",
    "wof:placetype":"venue"
},
  "geometry": {"coordinates":[4.955379,52.315342],"type":"Point"}
}