{
  "type": "Feature",
  "properties": {
    "addr:full":"Julianastr 8 Hulsberg Limburg 6336 TV",
    "addr:housenumber":"8",
    "addr:postcode":"6336 tv",
    "addr:street":"Julianastr",
    "iso:country":"NL",
    "sg:address":"Julianastr 8",
    "sg:city":"Hulsberg",
    "sg:orig_category":"Autorijscholen",
    "sg:phone":"+31 45 405 1618",
    "sg:postcode":"6336 TV",
    "sg:province":"Limburg",
    "wof:name":"Nelis, J L R",
    "wof:placetype":"venue"
},
  "geometry": {"coordinates":[5.857407,50.889378],"type":"Point"}
}