{
  "type": "Feature",
  "properties": {
    "addr:full":"A C De Graafwg 27 Wognum North Holland 1687 PS",
    "addr:housenumber":"27",
    "addr:postcode":"1687 ps",
    "addr:street":"C",
    "iso:country":"NL",
    "sg:address":"A C De Graafwg 27",
    "sg:city":"Wognum",
    "sg:orig_category":"Metaalbewerking",
    "sg:phone":"+31 229 578 542",
    "sg:postcode":"1687 PS",
    "sg:province":"North Holland",
    "wof:name":"Greeuw, Onderhoudsbedrijf De",
    "wof:placetype":"venue"
},
  "geometry": {"coordinates":[5.02865,52.693821],"type":"Point"}
}