{
  "type": "Feature",
  "properties": {
    "addr:full":"Veluwewg 99 Kootwykerbroek Gelderland 3774 BL",
    "addr:housenumber":"99",
    "addr:postcode":"3774 bl",
    "addr:street":"Veluwewg;Gelderland",
    "iso:country":"NL",
    "sg:address":"Veluwewg 99",
    "sg:city":"Kootwykerbroek",
    "sg:orig_category":"Huishoudelijke Apparaten En Artikelen",
    "sg:phone":"+31 342 441 228",
    "sg:postcode":"3774 BL",
    "sg:province":"Gelderland",
    "wof:name":"Butselaar, J Van",
    "wof:placetype":"venue"
},
  "geometry": {"coordinates":[5.676229,52.156391],"type":"Point"}
}