{
  "type": "Feature",
  "properties": {
    "iso:country":"NL",
    "sg:address":"Kielzog 13",
    "sg:city":"Huizen",
    "sg:classifiers":[
        {
            "category":"Personal",
            "subcategory":"Nail Salon",
            "type":"Services"
        }
    ],
    "sg:phone":"+31 35 525 8401",
    "sg:postcode":"1276 GW",
    "sg:province":"North Holland",
    "sg:tags":[
        "pedicure"
    ],
    "wof:name":"Bout, D",
    "wof:placetype":"venue"
},
  "geometry": {"coordinates":[5.249771,52.287621],"type":"Point"}
}