{
  "type": "Feature",
  "properties": {
    "addr:full":"H. Scheepstrahof 19 Almere NL. 1321 KH",
    "addr:housenumber":"19",
    "addr:postcode":"1321 kh",
    "addr:street":"H. Scheepstrahof;Nl.",
    "iso:country":"NL",
    "sg:address":"H. Scheepstrahof 19",
    "sg:city":"Almere",
    "sg:orig_category":"Autokeuringen",
    "sg:phone":"+31 36 535 0538",
    "sg:postcode":"1321 KH",
    "sg:province":"NL.",
    "wof:name":"S. Sardjoe",
    "wof:placetype":"venue"
},
  "geometry": {"coordinates":[5.189127,52.355419],"type":"Point"}
}