{
  "type": "Feature",
  "properties": {
    "iso:country":"NL",
    "sg:address":"Niekerkerweg 2",
    "sg:city":"Haaksbergen",
    "sg:orig_category":"Bloemen And Planten",
    "sg:phone":"+31 53 572 3256",
    "sg:postcode":"7481 TZ",
    "sg:province":"Overijssel",
    "wof:name":"Tuincentrum B.H. Nijhof",
    "wof:placetype":"venue"
},
  "geometry": {"coordinates":[6.761451,52.124249],"type":"Point"}
}