{
  "type": "Feature",
  "properties": {
    "iso:country":"NL",
    "sg:address":"Munnikenweg 38",
    "sg:city":"Veenendaal",
    "sg:orig_category":"Diverse Bedrijfsinstallaties Gh",
    "sg:phone":"+31 318 524 810",
    "sg:postcode":"3905 MJ",
    "sg:province":"Utrecht",
    "wof:name":"Handelsonderneming De Rijk Bv",
    "wof:placetype":"venue"
},
  "geometry": {"coordinates":[5.54205,52.035725],"type":"Point"}
}