{
  "type": "Feature",
  "properties": {
    "addr:full":"Hoofdstr 219 Hoogeveen Drenthe 7902 EJ",
    "addr:housenumber":"219",
    "addr:postcode":"7902 ej",
    "iso:country":"NL",
    "sg:address":"Hoofdstr 219",
    "sg:city":"Hoogeveen",
    "sg:orig_category":"Herenkleding",
    "sg:phone":"+31 528 264 195",
    "sg:postcode":"7902 EJ",
    "sg:province":"Drenthe",
    "wof:name":"Oever Bv, Ten",
    "wof:placetype":"venue"
},
  "geometry": {"coordinates":[6.478125,52.721363],"type":"Point"}
}