{
  "type": "Feature",
  "properties": {
    "addr:full":"Raadhuisplein 28 Hoogkarspel North Holland 1616 AV",
    "addr:housenumber":"28",
    "addr:postcode":"1616 av",
    "addr:street":"Raadhuisplein",
    "iso:country":"NL",
    "sg:address":"Raadhuisplein 28",
    "sg:city":"Hoogkarspel",
    "sg:orig_category":"Juweliers",
    "sg:phone":"+31 228 561 761",
    "sg:postcode":"1616 AV",
    "sg:province":"North Holland",
    "wof:name":"Juwelier Vd Mosselaar Hoogkarspel",
    "wof:placetype":"venue"
},
  "geometry": {"coordinates":[5.177003,52.695148],"type":"Point"}
}