{
  "type": "Feature",
  "properties": {
    "addr:full":"Rechte Tocht 7 Zaandam Noord-Holland 1507 BZ",
    "addr:housenumber":"7",
    "addr:postcode":"1507 bz",
    "addr:street":"Rechte Tocht",
    "iso:country":"NL",
    "sg:address":"Rechte Tocht 7",
    "sg:city":"Zaandam",
    "sg:orig_category":"Film-, Tv- And Videoproductie",
    "sg:phone":"+31 75 612 1385",
    "sg:postcode":"1507 BZ",
    "sg:province":"Noord-Holland",
    "wof:name":"Mts Audiovisueel",
    "wof:placetype":"venue"
},
  "geometry": {"coordinates":[4.803703,52.429825],"type":"Point"}
}