{
  "type": "Feature",
  "properties": {
    "addr:full":"Schoutenstraat 2A Hilversum North Holland 1211 BM",
    "addr:housenumber":"2a",
    "addr:postcode":"1211 bm",
    "addr:street":"Schoutenstraat",
    "iso:country":"NL",
    "sg:address":"Schoutenstraat 2A",
    "sg:city":"Hilversum",
    "sg:orig_category":"Damesmodezaken",
    "sg:phone":"+31 35 628 4393",
    "sg:postcode":"1211 BM",
    "sg:province":"North Holland",
    "wof:name":"Boetiek Maja",
    "wof:placetype":"venue"
},
  "geometry": {"coordinates":[5.173155,52.225349],"type":"Point"}
}