{
  "type": "Feature",
  "properties": {
    "addr:full":"Moerbalk 6 Wateringen Zuid-Holland 2291 MP",
    "addr:housenumber":"6",
    "addr:postcode":"2291 mp",
    "addr:street":"Moerbalk",
    "iso:country":"NL",
    "sg:address":"Moerbalk 6",
    "sg:city":"Wateringen",
    "sg:orig_category":"Adviesbureaus Bedrijfsorganisatie",
    "sg:phone":"+31 174 292 143",
    "sg:postcode":"2291 MP",
    "sg:province":"Zuid-Holland",
    "wof:name":"Liss",
    "wof:placetype":"venue"
},
  "geometry": {"coordinates":[4.272463,52.018982],"type":"Point"}
}