{
  "type": "Feature",
  "properties": {
    "iso:country":"NL",
    "sg:address":"Blauwehandstr 25",
    "sg:city":"Bergen Op Zoom",
    "sg:orig_category":"Adviesbureaus Bedrijfsorganisatie",
    "sg:phone":"+31 164 210 804",
    "sg:postcode":"4611 RK",
    "sg:province":"Noord-Brabant",
    "sg:website":"http://www.mensmentis.com",
    "wof:name":"Mens Mentis Consultancy",
    "wof:placetype":"venue"
},
  "geometry": {"coordinates":[4.28888,51.495953],"type":"Point"}
}