{
  "type": "Feature",
  "properties": {
    "addr:full":"Sweelinckdreef 21 Veenendaal Utrecht 3906 ZC",
    "addr:housenumber":"21",
    "addr:postcode":"3906 zc",
    "addr:street":"Sweelinckdreef",
    "iso:country":"NL",
    "sg:address":"Sweelinckdreef 21",
    "sg:city":"Veenendaal",
    "sg:orig_category":"Schoonheidsinstituten",
    "sg:phone":"+31 318 543 250",
    "sg:postcode":"3906 ZC",
    "sg:province":"Utrecht",
    "wof:name":"Berkenvelder-Vredegoor, A",
    "wof:placetype":"venue"
},
  "geometry": {"coordinates":[5.52867,52.035912],"type":"Point"}
}