{
  "type": "Feature",
  "properties": {
    "addr:full":"Westeinde 13 Arnhem Gelderland 6828 CS",
    "addr:housenumber":"13",
    "addr:postcode":"6828 cs",
    "addr:street":"Westeinde",
    "iso:country":"NL",
    "sg:address":"Westeinde 13",
    "sg:city":"Arnhem",
    "sg:orig_category":"Kappers",
    "sg:phone":"+31 26 370 4870",
    "sg:postcode":"6828 CS",
    "sg:province":"Gelderland",
    "wof:name":"Kapsalon Koksal",
    "wof:placetype":"venue"
},
  "geometry": {"coordinates":[5.9194140434,51.9846076965],"type":"Point"}
}