{
  "type": "Feature",
  "properties": {
    "iso:country":"NL",
    "sg:address":"Barnsteenstraat 40",
    "sg:city":"Alphen A/D Rijn",
    "sg:orig_category":"Marktonderzoekbureaus",
    "sg:phone":"+31 172 445 451",
    "sg:postcode":"2403 BZ",
    "sg:province":"Zuid-Holland",
    "wof:name":"Van Meenen/Lockefeer",
    "wof:placetype":"venue"
},
  "geometry": {"coordinates":[4.680053,52.140388],"type":"Point"}
}