{
  "type": "Feature",
  "properties": {
    "addr:full":"Veldweg 25 Herkenbosch Limburg 6075 NL",
    "addr:housenumber":"25",
    "addr:postcode":"6075 nl",
    "addr:street":"Veldweg",
    "iso:country":"NL",
    "sg:address":"Veldweg 25",
    "sg:city":"Herkenbosch",
    "sg:orig_category":"Koeriersdiensten",
    "sg:phone":"+31 475 332 084",
    "sg:postcode":"6075 NL",
    "sg:province":"Limburg",
    "wof:name":"Erdem Bv",
    "wof:placetype":"venue"
},
  "geometry": {"coordinates":[6.07042,51.167431],"type":"Point"}
}