{
  "type": "Feature",
  "properties": {
    "addr:full":"Graaf Van Solmsweg 54 'S Hertogenbosch Noord-Brabant 5222 BP",
    "addr:housenumber":"54",
    "addr:postcode":"5222 bp",
    "addr:street":"Graaf Van Solmsweg;' S",
    "iso:country":"NL",
    "sg:address":"Graaf Van Solmsweg 54",
    "sg:city":"'S Hertogenbosch",
    "sg:orig_category":"Verhuisdiensten",
    "sg:phone":"+31 73 622 0452",
    "sg:postcode":"5222 BP",
    "sg:province":"Noord-Brabant",
    "wof:name":"De Cirkel",
    "wof:placetype":"venue"
},
  "geometry": {"coordinates":[5.266465,51.708504],"type":"Point"}
}