{
  "type": "Feature",
  "properties": {
    "addr:full":"Voorstr 69B Egmond Aan Zee Noord-Holland 1931 AH",
    "addr:housenumber":"69b",
    "addr:postcode":"1931 ah",
    "addr:street":"Voorstr",
    "iso:country":"NL",
    "sg:address":"Voorstr 69B",
    "sg:city":"Egmond Aan Zee",
    "sg:orig_category":"Antiquiteiten",
    "sg:phone":"+31 72 506 6791",
    "sg:postcode":"1931 AH",
    "sg:province":"Noord-Holland",
    "wof:name":"Kleine Zoete Inval",
    "wof:placetype":"venue"
},
  "geometry": {"coordinates":[4.627435,52.61842],"type":"Point"}
}