{
  "type": "Feature",
  "properties": {
    "addr:full":"Meerhof 33 Leiden Zuid-Holland 2321 TH",
    "addr:housenumber":"33",
    "addr:postcode":"2321 th",
    "addr:street":"Meerhof",
    "iso:country":"NL",
    "sg:address":"Meerhof 33",
    "sg:city":"Leiden",
    "sg:orig_category":"Kinderopvang Behalve Thuis",
    "sg:phone":"+31 71 532 2942",
    "sg:postcode":"2321 TH",
    "sg:province":"Zuid-Holland",
    "wof:name":"Naschoolse Opvang Beer Grote",
    "wof:placetype":"venue"
},
  "geometry": {"coordinates":[4.477653,52.150417],"type":"Point"}
}