{
  "type": "Feature",
  "properties": {
    "addr:full":"Parkwg 52 Ede Gld Gelderland 6717 HV",
    "addr:housenumber":"52",
    "addr:postcode":"6717 hv",
    "addr:street":"Parkwg;Gld Gelderland",
    "iso:country":"NL",
    "sg:address":"Parkwg 52",
    "sg:city":"Ede Gld",
    "sg:orig_category":"Koffie- En Theehuizen",
    "sg:phone":"+31 318 635 253",
    "sg:postcode":"6717 HV",
    "sg:province":"Gelderland",
    "wof:name":"Zwarte Zee",
    "wof:placetype":"venue"
},
  "geometry": {"coordinates":[5.66701,52.027874],"type":"Point"}
}