{
  "type": "Feature",
  "properties": {
    "iso:country":"NL",
    "sg:address":"Pavanestr 32",
    "sg:city":"Venray",
    "sg:orig_category":"Scheepssleep- En Duwvaart",
    "sg:phone":"+31 478 513 055",
    "sg:postcode":"5802 LL",
    "sg:province":"Limburg",
    "wof:name":"Duo",
    "wof:placetype":"venue"
},
  "geometry": {"coordinates":[5.999838,51.523083],"type":"Point"}
}