{
  "type": "Feature",
  "properties": {
    "iso:country":"NL",
    "sg:address":"Prinsengr 783",
    "sg:city":"Amsterdam",
    "sg:orig_category":"Onroerende Goederen",
    "sg:phone":"+31 20 638 5750",
    "sg:postcode":"1017 JZ",
    "sg:province":"Noord-Holland",
    "wof:name":"Partituur Bv",
    "wof:placetype":"venue"
},
  "geometry": {"coordinates":[4.887328,52.363552],"type":"Point"}
}