{
  "type": "Feature",
  "properties": {
    "addr:full":"Spechtenkamp 233A Maarssen Utrecht 3607 KN",
    "addr:housenumber":"233a",
    "addr:postcode":"3607 kn",
    "addr:street":"Spechtenkamp",
    "iso:country":"NL",
    "sg:address":"Spechtenkamp 233A",
    "sg:city":"Maarssen",
    "sg:orig_category":"Verloskundigen",
    "sg:phone":"+31 346 599 590",
    "sg:postcode":"3607 KN",
    "sg:province":"Utrecht",
    "wof:name":"Gezondheidscentr Maarssenbroek, Sticht",
    "wof:placetype":"venue"
},
  "geometry": {"coordinates":[5.017768,52.137444],"type":"Point"}
}