{
  "type": "Feature",
  "properties": {
    "addr:full":"Bordewykln 8 Groningen Groningen 9721 TP",
    "addr:housenumber":"8",
    "addr:postcode":"9721 tp",
    "addr:street":"Bordewykln",
    "iso:country":"NL",
    "sg:address":"Bordewykln 8",
    "sg:city":"Groningen",
    "sg:orig_category":"Verzekeringen - Verzekeringskantoren",
    "sg:phone":"+31 50 525 2491",
    "sg:postcode":"9721 TP",
    "sg:province":"Groningen",
    "wof:name":"Takens, H",
    "wof:placetype":"venue"
},
  "geometry": {"coordinates":[6.57473,53.194111],"type":"Point"}
}