{
  "type": "Feature",
  "properties": {
    "addr:full":"Staalstraat 28 Amsterdam Noord-Holland 1011 JM",
    "addr:housenumber":"28",
    "addr:postcode":"1011 jm",
    "addr:street":"Staalstraat",
    "iso:country":"NL",
    "sg:address":"Staalstraat 28",
    "sg:city":"Amsterdam",
    "sg:orig_category":"Fotostudio'S And Fotografen",
    "sg:phone":"+31 20 625 9303",
    "sg:postcode":"1011 JM",
    "sg:province":"Noord-Holland",
    "wof:name":"Cultureel Organisatiebureau Arttra",
    "wof:placetype":"venue"
},
  "geometry": {"coordinates":[4.898284,52.368122],"type":"Point"}
}