{
  "type": "Feature",
  "properties": {
    "iso:country":"NL",
    "sg:address":"Biltstraat 79",
    "sg:city":"Utrecht-Centrum",
    "sg:classifiers":[
        {
            "category":"Retail",
            "subcategory":"Photofinishing",
            "type":"Services"
        }
    ],
    "sg:phone":"+31 30 231 5797",
    "sg:postcode":"3572 AJ",
    "sg:province":"Utrecht",
    "sg:tags":[
        "foto",
        "film"
    ],
    "wof:name":"Foto Film Office",
    "wof:placetype":"venue"
},
  "geometry": {"coordinates":[5.129852,52.095158],"type":"Point"}
}