{
  "type": "Feature",
  "properties": {
    "addr:full":"Sourethwg 11 Heerlen Limburg 6422 PC",
    "addr:housenumber":"11",
    "addr:postcode":"6422 pc",
    "addr:street":"Sourethwg",
    "iso:country":"NL",
    "sg:address":"Sourethwg 11",
    "sg:city":"Heerlen",
    "sg:orig_category":"Medische Installaties En Instrumenten",
    "sg:phone":"+31 45 547 1471",
    "sg:postcode":"6422 PC",
    "sg:province":"Limburg",
    "wof:name":"Minntech Bv",
    "wof:placetype":"venue"
},
  "geometry": {"coordinates":[5.994703,50.846493],"type":"Point"}
}