{
  "type": "Feature",
  "properties": {
    "addr:full":"Bukkumweg 5 Hilvarenbeek Noord-Brabant 5081 CT",
    "addr:housenumber":"5",
    "addr:postcode":"5081 ct",
    "addr:street":"Bukkumweg",
    "iso:country":"NL",
    "sg:address":"Bukkumweg 5",
    "sg:city":"Hilvarenbeek",
    "sg:orig_category":"Binnenhuisarchitecten",
    "sg:phone":"+31 13 505 8080",
    "sg:postcode":"5081 CT",
    "sg:province":"Noord-Brabant",
    "wof:name":"Unic Interieurprojekten En Projektmanagement",
    "wof:placetype":"venue"
},
  "geometry": {"coordinates":[5.14362,51.486214],"type":"Point"}
}