{
  "type": "Feature",
  "properties": {
    "iso:country":"NL",
    "sg:address":"Zilverschoon 102",
    "sg:city":"Sneek",
    "sg:orig_category":"Metaalbekleding And -Behandeling",
    "sg:phone":"+31 515 433 996",
    "sg:postcode":"8607 GC",
    "sg:province":"Friesland",
    "wof:name":"Lasservice Sneek",
    "wof:placetype":"venue"
},
  "geometry": {"coordinates":[5.6596369743,53.0197792053],"type":"Point"}
}