{
  "type": "Feature",
  "properties": {
    "addr:full":"Marconiwg 1 Zeewolde NL. 3899 BR",
    "addr:housenumber":"1",
    "addr:postcode":"3899 br",
    "addr:street":"Marconiwg;Nl.",
    "iso:country":"NL",
    "sg:address":"Marconiwg 1",
    "sg:city":"Zeewolde",
    "sg:orig_category":"Postorderbedrijven",
    "sg:phone":"+31 36 521 8251",
    "sg:postcode":"3899 BR",
    "sg:province":"NL.",
    "sg:website":"http://www.micro-mail.nl",
    "wof:name":"Micro-Mail Bv",
    "wof:placetype":"venue"
},
  "geometry": {"coordinates":[5.504703,52.352535],"type":"Point"}
}