{
  "type": "Feature",
  "properties": {
    "iso:country":"NL",
    "sg:address":"Zuidpln 10-14-18",
    "sg:city":"Rotterdam",
    "sg:orig_category":"Woningbouw- Verenigingen En -Stichtingen",
    "sg:phone":"+31 10 410 6700",
    "sg:postcode":"3083 CW",
    "sg:province":"Zuid-Holland",
    "wof:name":"Nieuwe Unie, De",
    "wof:placetype":"venue"
},
  "geometry": {"coordinates":[4.4860601425,51.8877906799],"type":"Point"}
}