{
  "type": "Feature",
  "properties": {
    "addr:full":"Goudlaan 69 'S Gravenhage Zuid-Holland 2544 EG",
    "addr:housenumber":"69",
    "addr:postcode":"2544 eg",
    "addr:street":"Goudlaan;' S",
    "iso:country":"NL",
    "sg:address":"Goudlaan 69",
    "sg:city":"'S Gravenhage",
    "sg:orig_category":"Verhuur Catering-, Feest- En Evenementbenodigdheden",
    "sg:phone":"+31 70 367 8914",
    "sg:postcode":"2544 EG",
    "sg:province":"Zuid-Holland",
    "wof:name":"Correct Speelautomaten",
    "wof:placetype":"venue"
},
  "geometry": {"coordinates":[4.255476,52.051868],"type":"Point"}
}