{
  "type": "Feature",
  "properties": {
    "iso:country":"NL",
    "sg:address":"Spoorln 39",
    "sg:city":"Valkenburg Lb",
    "sg:classifiers":[
        {
            "category":"Travel",
            "subcategory":"Hotels & Motels",
            "type":"Entertainment"
        }
    ],
    "sg:phone":"+31 43 601 3017",
    "sg:postcode":"6301 GB",
    "sg:province":"Limburg",
    "wof:name":"Spronck, J",
    "wof:placetype":"venue"
},
  "geometry": {"coordinates":[5.83344,50.861328],"type":"Point"}
}