{
  "type": "Feature",
  "properties": {
    "addr:full":"T M Kortenhorstln 1 Rosmalen North Brabant 5244 GD",
    "addr:housenumber":"1",
    "addr:postcode":"5244 gd",
    "iso:country":"NL",
    "sg:address":"T M Kortenhorstln 1",
    "sg:city":"Rosmalen",
    "sg:orig_category":"Verenigingen En Stichtingen",
    "sg:phone":"+31 73 521 9247",
    "sg:postcode":"5244 GD",
    "sg:province":"North Brabant",
    "wof:name":"Jongerenwerk Rosmalen",
    "wof:placetype":"venue"
},
  "geometry": {"coordinates":[5.39558,51.718182],"type":"Point"}
}