{
  "type": "Feature",
  "properties": {
    "iso:country":"NL",
    "sg:address":"Haringvliet 84",
    "sg:city":"Rotterdam",
    "sg:orig_category":"Makelaars En Adviseurs Onroerende Goederen",
    "sg:phone":"+31 10 213 2121",
    "sg:postcode":"3011 TG",
    "sg:province":"South Holland",
    "sg:website":"http://www.vdsvdv.nl",
    "wof:name":"Schee & Van Der Velde, Van Der",
    "wof:placetype":"venue"
},
  "geometry": {"coordinates":[4.494833,51.919415],"type":"Point"}
}