{
  "type": "Feature",
  "properties": {
    "iso:country":"NL",
    "sg:address":"Meent 83",
    "sg:city":"Veldhoven",
    "sg:orig_category":"Bloemen And Planten",
    "sg:phone":"+31 40 253 2482",
    "sg:postcode":"5501 JJ",
    "sg:province":"Noord-Brabant",
    "wof:name":"Oogenlust M. Van Dijk",
    "wof:placetype":"venue"
},
  "geometry": {"coordinates":[5.406578,51.41906],"type":"Point"}
}