{
  "type": "Feature",
  "properties": {
    "addr:full":"Rondweg 7 Leermens Groningen 9912 PA",
    "addr:housenumber":"7",
    "addr:postcode":"9912 pa",
    "addr:street":"Rondweg",
    "iso:country":"NL",
    "sg:address":"Rondweg 7",
    "sg:city":"Leermens",
    "sg:orig_category":"Boekhouders",
    "sg:phone":"+31 596 581 322",
    "sg:postcode":"9912 PA",
    "sg:province":"Groningen",
    "wof:name":"Administratiekantoor Kuizenga",
    "wof:placetype":"venue"
},
  "geometry": {"coordinates":[6.795344,53.346691],"type":"Point"}
}