{
  "type": "Feature",
  "properties": {
    "addr:full":"Keizersdijk 50 Rijssen Overijssel 7462 JB",
    "addr:housenumber":"50",
    "addr:postcode":"7462 jb",
    "addr:street":"Keizersdijk",
    "iso:country":"NL",
    "sg:address":"Keizersdijk 50",
    "sg:city":"Rijssen",
    "sg:orig_category":"Goederenvervoer Over De Weg",
    "sg:phone":"+31 548 515 056",
    "sg:postcode":"7462 JB",
    "sg:province":"Overijssel",
    "wof:name":"G.W. Groteboer Internationaal Transport",
    "wof:placetype":"venue"
},
  "geometry": {"coordinates":[6.482405,52.29768],"type":"Point"}
}