{
  "type": "Feature",
  "properties": {
    "addr:full":"Stadsbrink 519-521 Wageningen Gelderland 6707 AT",
    "addr:housenumber":"519-521",
    "addr:postcode":"6707",
    "addr:street":"Stadsbrink;Gelderland",
    "iso:country":"NL",
    "sg:address":"Stadsbrink 519-521",
    "sg:city":"Wageningen",
    "sg:orig_category":"Warenhuizen",
    "sg:phone":"+31 317 452 164",
    "sg:postcode":"6707 AT",
    "sg:province":"Gelderland",
    "sg:website":"HTTP://www.actionshop.nl",
    "wof:name":"Action",
    "wof:placetype":"venue"
},
  "geometry": {"coordinates":[5.6678638458,51.9695701599],"type":"Point"}
}