{
  "type": "Feature",
  "properties": {
    "iso:country":"NL",
    "sg:address":"Soestdijkseweg Zuid 123",
    "sg:city":"Bilthoven",
    "sg:orig_category":"Bedrijfs- And Managementsconsultants",
    "sg:phone":"+31 30 221 0315",
    "sg:postcode":"3721 AA",
    "sg:province":"Utrecht",
    "wof:name":"Brouwers Consultancy",
    "wof:placetype":"venue"
},
  "geometry": {"coordinates":[5.193006,52.115089],"type":"Point"}
}