{
  "type": "Feature",
  "properties": {
    "addr:full":"Geestbrugwg 99A Ryswyk Zh Zuid-Holland 2281 CJ",
    "addr:housenumber":"99a",
    "addr:postcode":"2281 cj",
    "addr:street":"Geestbrugwg",
    "iso:country":"NL",
    "sg:address":"Geestbrugwg 99A",
    "sg:city":"Ryswyk Zh",
    "sg:orig_category":"Galeries",
    "sg:phone":"+31 70 415 6220",
    "sg:postcode":"2281 CJ",
    "sg:province":"Zuid-Holland",
    "wof:name":"E Du Art",
    "wof:placetype":"venue"
},
  "geometry": {"coordinates":[4.341704,52.056934],"type":"Point"}
}