{
  "type": "Feature",
  "properties": {
    "addr:full":"Pr W Alexanderstr 16 Baambrugge Utrecht 1396 KC",
    "addr:housenumber":"16",
    "addr:postcode":"1396 kc",
    "addr:street":"W;Baambrugge",
    "iso:country":"NL",
    "sg:address":"Pr W Alexanderstr 16",
    "sg:city":"Baambrugge",
    "sg:orig_category":"Ongediertebestrijding En Ontsmetting",
    "sg:phone":"+31 294 291 251",
    "sg:postcode":"1396 KC",
    "sg:province":"Utrecht",
    "wof:name":"Meyer",
    "wof:placetype":"venue"
},
  "geometry": {"coordinates":[4.986148,52.245621],"type":"Point"}
}