{
  "type": "Feature",
  "properties": {
    "addr:full":"Drentestraat 20 Amsterdam Noord-Holland 1083 HK",
    "addr:housenumber":"20",
    "addr:postcode":"1083 hk",
    "addr:street":"Drentestraat",
    "iso:country":"NL",
    "sg:address":"Drentestraat 20",
    "sg:city":"Amsterdam",
    "sg:classifiers":[
        {
            "category":"Professional",
            "subcategory":"Accounting & Tax Preparation",
            "type":"Services"
        }
    ],
    "sg:phone":"+31 20 549 7222",
    "sg:postcode":"1083 HK",
    "sg:province":"Noord-Holland",
    "sg:tags":[
        "accountant"
    ],
    "wof:name":"Ernst & Young Accountants",
    "wof:placetype":"venue"
},
  "geometry": {"coordinates":[4.885956,52.336308],"type":"Point"}
}