{
  "type": "Feature",
  "properties": {
    "addr:full":"Breughelstr 6A Amsterdam North Holland 1077 LC",
    "addr:housenumber":"6a",
    "addr:postcode":"1077 lc",
    "addr:street":"Breughelstr",
    "iso:country":"NL",
    "sg:address":"Breughelstr 6A",
    "sg:city":"Amsterdam",
    "sg:orig_category":"Projectontwikkeling",
    "sg:phone":"+31 20 679 7878",
    "sg:postcode":"1077 LC",
    "sg:province":"North Holland",
    "wof:name":"Primerica Bv",
    "wof:placetype":"venue"
},
  "geometry": {"coordinates":[4.876991,52.35033],"type":"Point"}
}