{
  "type": "Feature",
  "properties": {
    "iso:country":"NL",
    "sg:address":"Appeldk 35",
    "sg:city":"Gorinchem",
    "sg:classifiers":[
        {
            "category":"Professional",
            "subcategory":"Accounting & Tax Preparation",
            "type":"Services"
        }
    ],
    "sg:phone":"+31 183 638 544",
    "sg:postcode":"4201 AE",
    "sg:province":"Zuid-Holland",
    "sg:tags":[
        "accountant",
        "en",
        "-kantoren",
        "register-"
    ],
    "wof:name":"Moret",
    "wof:placetype":"venue"
},
  "geometry": {"coordinates":[4.976833,51.828701],"type":"Point"}
}