{
  "type": "Feature",
  "properties": {
    "addr:full":"P Vd Veldenstr 10 Nieuw Lekkerland South Holland 2957 AX",
    "addr:housenumber":"10",
    "addr:postcode":"2957 ax",
    "addr:street":"P Vd Veldenstr",
    "iso:country":"NL",
    "sg:address":"P Vd Veldenstr 10",
    "sg:city":"Nieuw Lekkerland",
    "sg:orig_category":"Bloemen En Planten",
    "sg:phone":"+31 184 681 949",
    "sg:postcode":"2957 AX",
    "sg:province":"South Holland",
    "wof:name":"Hasman",
    "wof:placetype":"venue"
},
  "geometry": {"coordinates":[4.691083,51.888401],"type":"Point"}
}