{
  "type": "Feature",
  "properties": {
    "addr:full":"Westplein 12 Rotterdam Zuid-Holland 3016 BM",
    "addr:housenumber":"12",
    "addr:postcode":"3016 bm",
    "addr:street":"Westplein",
    "iso:country":"NL",
    "sg:address":"Westplein 12",
    "sg:city":"Rotterdam",
    "sg:orig_category":"Advocaten And Juridische Adviseurs",
    "sg:phone":"+31 10 277 2777",
    "sg:postcode":"3016 BM",
    "sg:province":"Zuid-Holland",
    "wof:name":"Akd Prinsen Van Wijmen",
    "wof:placetype":"venue"
},
  "geometry": {"coordinates":[4.477745,51.90871],"type":"Point"}
}