{
  "type": "Feature",
  "properties": {
    "addr:full":"Hg Nieuwstr 83 Dordrecht South Holland 3311 AJ",
    "addr:housenumber":"83",
    "addr:postcode":"3311 aj",
    "iso:country":"NL",
    "sg:address":"Hg Nieuwstr 83",
    "sg:city":"Dordrecht",
    "sg:classifiers":[
        {
            "category":"Education",
            "subcategory":"School",
            "type":"Public Place"
        }
    ],
    "sg:phone":"+31 78 614 1116",
    "sg:postcode":"3311 AJ",
    "sg:province":"South Holland",
    "sg:tags":[
        "studiebegeleiding",
        "en",
        "school-"
    ],
    "wof:name":"Kranenburg, Instituut",
    "wof:placetype":"venue"
},
  "geometry": {"coordinates":[4.662882,51.816422],"type":"Point"}
}