{
  "type": "Feature",
  "properties": {
    "addr:full":"Kooiplein 16 Castricum North Holland 1901 VW",
    "addr:housenumber":"16",
    "addr:postcode":"1901 vw",
    "addr:street":"Kooiplein",
    "iso:country":"NL",
    "sg:address":"Kooiplein 16",
    "sg:city":"Castricum",
    "sg:orig_category":"Boekhouders",
    "sg:phone":"+31 251 656 583",
    "sg:postcode":"1901 VW",
    "sg:province":"North Holland",
    "wof:name":"Administratie-En Assurantiekantoor H Lis",
    "wof:placetype":"venue"
},
  "geometry": {"coordinates":[4.670201,52.556091],"type":"Point"}
}