{
  "type": "Feature",
  "properties": {
    "addr:full":"Hofsleane 24 Berlikum Fr Provincie Friesland 9041 AR",
    "addr:housenumber":"24",
    "addr:postcode":"9041",
    "addr:street":"Hofsleane;Friesland",
    "iso:country":"NL",
    "sg:address":"Hofsleane 24",
    "sg:city":"Berlikum Fr",
    "sg:orig_category":"Boekhouders",
    "sg:phone":"+31 518 461 317",
    "sg:postcode":"9041 AR",
    "sg:province":"Provincie Friesland",
    "wof:name":"Administratiekantoor A.A. Groeneveld",
    "wof:placetype":"venue"
},
  "geometry": {"coordinates":[5.65046,53.243534],"type":"Point"}
}