{
  "type": "Feature",
  "properties": {
    "addr:full":"Morelgaard 21 Spijkenisse South Holland 3206 AP",
    "addr:housenumber":"21",
    "addr:postcode":"3206 ap",
    "addr:street":"Morelgaard",
    "iso:country":"NL",
    "sg:address":"Morelgaard 21",
    "sg:city":"Spijkenisse",
    "sg:orig_category":"Boekhouders",
    "sg:phone":"+31 181 633 334",
    "sg:postcode":"3206 AP",
    "sg:province":"South Holland",
    "wof:name":"Administratiekantoor Engelaan",
    "wof:placetype":"venue"
},
  "geometry": {"coordinates":[4.332751,51.833427],"type":"Point"}
}