{
  "type": "Feature",
  "properties": {
    "addr:full":"Molenweg 9 Hierden Gelderland 3849 RK",
    "addr:housenumber":"9",
    "addr:postcode":"3849 rk",
    "addr:street":"Molenweg;Gelderland",
    "iso:country":"NL",
    "sg:address":"Molenweg 9",
    "sg:city":"Hierden",
    "sg:classifiers":[
        {
            "category":"Professional",
            "subcategory":"Accounting & Tax Preparation",
            "type":"Services"
        }
    ],
    "sg:phone":"+31 341 451 589",
    "sg:postcode":"3849 RK",
    "sg:province":"Gelderland",
    "sg:tags":[
        "accountant"
    ],
    "wof:name":"E. Jacobs Management En Advies Bv",
    "wof:placetype":"venue"
},
  "geometry": {"coordinates":[5.678229,52.354866],"type":"Point"}
}