{
  "type": "Feature",
  "properties": {
    "addr:full":"Vt Hoffstr 6 Nykerk Gld Gelderland 3863 AX",
    "addr:housenumber":"6",
    "addr:postcode":"3863 ax",
    "addr:street":"Nykerk Gld Gelderland",
    "iso:country":"NL",
    "sg:address":"Vt Hoffstr 6",
    "sg:city":"Nykerk Gld",
    "sg:orig_category":"Artsen - Huisartsen",
    "sg:phone":"+31 33 245 9924",
    "sg:postcode":"3863 AX",
    "sg:province":"Gelderland",
    "wof:name":"Doornekamp, B J G",
    "wof:placetype":"venue"
},
  "geometry": {"coordinates":[5.464432,52.21619],"type":"Point"}
}