{
  "type": "Feature",
  "properties": {
    "addr:full":"Dierenriemstraat Groningen Groningen 9742 AN",
    "addr:postcode":"9742 an",
    "addr:street":"Dierenriemstraat",
    "iso:country":"NL",
    "sg:address":"Dierenriemstraat",
    "sg:city":"Groningen",
    "sg:orig_category":"Winkelcentra",
    "sg:phone":"+31 150",
    "sg:postcode":"9742 AN",
    "sg:province":"Groningen",
    "wof:name":"Groningen Winkelcentrum De Paddepoel",
    "wof:placetype":"venue"
},
  "geometry": {"coordinates":[6.546546936,53.2292671204],"type":"Point"}
}