{
  "type": "Feature",
  "properties": {
    "addr:full":"Werkhovensew 3 Odijk Utrecht 3984 LG",
    "addr:housenumber":"3",
    "addr:postcode":"3984 lg",
    "addr:street":"Werkhovensew",
    "iso:country":"NL",
    "sg:address":"Werkhovensew 3",
    "sg:city":"Odijk",
    "sg:classifiers":[
        {
            "category":"Sports & Exercise",
            "subcategory":"Stables",
            "type":"Entertainment"
        }
    ],
    "sg:phone":"+31 30 656 3028",
    "sg:postcode":"3984 LG",
    "sg:province":"Utrecht",
    "sg:tags":[
        "maneges"
    ],
    "wof:name":"Rijnstein",
    "wof:placetype":"venue"
},
  "geometry": {"coordinates":[5.230682,52.043713],"type":"Point"}
}