{
  "type": "Feature",
  "properties": {
    "addr:full":"A Flemingstr 3 Oud Beyerland Zuid-Holland 3261 MA",
    "addr:housenumber":"3",
    "addr:postcode":"3261 ma",
    "addr:street":"Oud Beyerland",
    "iso:country":"NL",
    "sg:address":"A Flemingstr 3",
    "sg:city":"Oud Beyerland",
    "sg:orig_category":"Banden - Fabrieken En Groothandel",
    "sg:phone":"+31 186 618 500",
    "sg:postcode":"3261 MA",
    "sg:province":"Zuid-Holland",
    "wof:name":"Klok Banden Bv, De",
    "wof:placetype":"venue"
},
  "geometry": {"coordinates":[4.434655,51.829967],"type":"Point"}
}