{
  "type": "Feature",
  "properties": {
    "addr:full":"Kaagstraat 12 Raalte Overijssel 8102 GZ",
    "addr:housenumber":"12",
    "addr:postcode":"8102 gz",
    "addr:street":"Kaagstraat",
    "iso:country":"NL",
    "sg:address":"Kaagstraat 12",
    "sg:city":"Raalte",
    "sg:orig_category":"Verhuur Catering-, Feest- En Evenementbenodigdheden",
    "sg:phone":"+31 572 354 427",
    "sg:postcode":"8102 GZ",
    "sg:province":"Overijssel",
    "wof:name":"Korbeld Verhuur",
    "wof:placetype":"venue"
},
  "geometry": {"coordinates":[6.285299,52.378815],"type":"Point"}
}