{
  "type": "Feature",
  "properties": {
    "addr:full":"V Stolbergln 29 Zoetermeer South Holland 2713 ES",
    "addr:housenumber":"29",
    "addr:postcode":"2713 es",
    "iso:country":"NL",
    "sg:address":"V Stolbergln 29",
    "sg:city":"Zoetermeer",
    "sg:orig_category":"Postkantoren",
    "sg:phone":"+31 79 316 3113",
    "sg:postcode":"2713 ES",
    "sg:province":"South Holland",
    "sg:website":"http://www.postkantoor.nl",
    "wof:name":"Postkantoor",
    "wof:placetype":"venue"
},
  "geometry": {"coordinates":[4.488925,52.06308],"type":"Point"}
}