{
  "type": "Feature",
  "properties": {
    "addr:full":"Hanzestraat 82 Arnhem Gelderland 6826 MN",
    "addr:housenumber":"82",
    "addr:postcode":"6826 mn",
    "addr:street":"Hanzestraat",
    "iso:country":"NL",
    "sg:address":"Hanzestraat 82",
    "sg:city":"Arnhem",
    "sg:orig_category":"Herenmodezaken",
    "sg:phone":"+31 26 361 0004",
    "sg:postcode":"6826 MN",
    "sg:province":"Gelderland",
    "wof:name":"Amici Mannenmode",
    "wof:placetype":"venue"
},
  "geometry": {"coordinates":[5.950821,51.982948],"type":"Point"}
}