{
  "type": "Feature",
  "properties": {
    "addr:full":"Herestraat 27 Grijpskerk Groningen 9843 AH",
    "addr:housenumber":"27",
    "addr:postcode":"9843 ah",
    "addr:street":"Herestraat",
    "iso:country":"NL",
    "sg:address":"Herestraat 27",
    "sg:city":"Grijpskerk",
    "sg:orig_category":"Bloemen And Planten",
    "sg:phone":"+31 594 212 386",
    "sg:postcode":"9843 AH",
    "sg:province":"Groningen",
    "wof:name":"Bloemenhuis Drint",
    "wof:placetype":"venue"
},
  "geometry": {"coordinates":[6.308063,53.26384],"type":"Point"}
}