{
  "type": "Feature",
  "properties": {
    "iso:country":"NL",
    "sg:address":"Edisonstraat 75",
    "sg:city":"Breda",
    "sg:orig_category":"Overheidsdiensten",
    "sg:phone":"+31 76 581 0679",
    "sg:postcode":"4816 AS",
    "sg:province":"Noord-Brabant",
    "wof:name":"De Freetimers",
    "wof:placetype":"venue"
},
  "geometry": {"coordinates":[4.7863650322,51.5997657776],"type":"Point"}
}