{
  "type": "Feature",
  "properties": {
    "addr:full":"Heerlerbaan 273 Heerlen Limburg 6418 CE",
    "addr:housenumber":"273",
    "addr:postcode":"6418 ce",
    "addr:street":"Heerlerbaan",
    "iso:country":"NL",
    "sg:address":"Heerlerbaan 273",
    "sg:city":"Heerlen",
    "sg:orig_category":"Keukens",
    "sg:phone":"+31 45 566 7090",
    "sg:postcode":"6418 CE",
    "sg:province":"Limburg",
    "wof:name":"Horn",
    "wof:placetype":"venue"
},
  "geometry": {"coordinates":[6.005099,50.863102],"type":"Point"}
}