{
  "type": "Feature",
  "properties": {
    "addr:full":"Bennebroekerlaan 77 Bennebroek Noord-Holland 2121 GS",
    "addr:housenumber":"77",
    "addr:postcode":"2121 gs",
    "addr:street":"Bennebroekerlaan",
    "iso:country":"NL",
    "sg:address":"Bennebroekerlaan 77",
    "sg:city":"Bennebroek",
    "sg:orig_category":"Bloemen And Planten",
    "sg:phone":"+31 23 584 5634",
    "sg:postcode":"2121 GS",
    "sg:province":"Noord-Holland",
    "wof:name":"Flower Fashion",
    "wof:placetype":"venue"
},
  "geometry": {"coordinates":[4.600485,52.321449],"type":"Point"}
}