{
  "type": "Feature",
  "properties": {
    "addr:full":"Berkenrodeln 32 Amstelveen Noord-Holland 1181 AJ",
    "addr:housenumber":"32",
    "addr:postcode":"1181 aj",
    "addr:street":"Berkenrodeln",
    "iso:country":"NL",
    "sg:address":"Berkenrodeln 32",
    "sg:city":"Amstelveen",
    "sg:orig_category":"Adviesbureaus Bedrijfsorganisatie",
    "sg:phone":"+31 20 345 8520",
    "sg:postcode":"1181 AJ",
    "sg:province":"Noord-Holland",
    "wof:name":"Ross, Drs F J",
    "wof:placetype":"venue"
},
  "geometry": {"coordinates":[4.866405,52.321133],"type":"Point"}
}