{
  "type": "Feature",
  "properties": {
    "addr:full":"Polluxstraat 38 Spijkenisse South Holland 3204 BV",
    "addr:housenumber":"38",
    "addr:postcode":"3204 bv",
    "addr:street":"Polluxstraat",
    "iso:country":"NL",
    "sg:address":"Polluxstraat 38",
    "sg:city":"Spijkenisse",
    "sg:orig_category":"Boekhouders",
    "sg:phone":"+31 181 617 364",
    "sg:postcode":"3204 BV",
    "sg:province":"South Holland",
    "wof:name":"A C Taselaar",
    "wof:placetype":"venue"
},
  "geometry": {"coordinates":[4.32803,51.839207],"type":"Point"}
}