{
  "type": "Feature",
  "properties": {
    "addr:full":"Zoutmanstr 34-36 S Gravenhage South Holland 2518 GR",
    "addr:housenumber":"34-36",
    "addr:postcode":"2518",
    "addr:street":"S Gravenhage",
    "iso:country":"NL",
    "sg:address":"Zoutmanstr 34-36",
    "sg:city":"S Gravenhage",
    "sg:orig_category":"Kantoorbenodigdheden",
    "sg:phone":"+31 70 346 7400",
    "sg:postcode":"2518 GR",
    "sg:province":"South Holland",
    "wof:name":"Heering & Van Leeuwen",
    "wof:placetype":"venue"
},
  "geometry": {"coordinates":[4.2934799194,52.0803184509],"type":"Point"}
}