{
  "type": "Feature",
  "properties": {
    "iso:country":"NL",
    "sg:address":"Exloerkyl Z 110",
    "sg:city":"Tweede Exloermond",
    "sg:orig_category":"Onroerende Goederen",
    "sg:phone":"+31 599 671 815",
    "sg:postcode":"9571 AE",
    "sg:province":"Provincie Drenthe",
    "wof:name":"Monden, De",
    "wof:placetype":"venue"
},
  "geometry": {"coordinates":[6.932583,52.887161],"type":"Point"}
}