{
  "type": "Feature",
  "properties": {
    "addr:full":"Oudedijk 34 Odiliapeel North Brabant 5409 AC",
    "addr:housenumber":"34",
    "addr:postcode":"5409 ac",
    "addr:street":"Oudedijk",
    "iso:country":"NL",
    "sg:address":"Oudedijk 34",
    "sg:city":"Odiliapeel",
    "sg:orig_category":"Meubelzaken, Woning- And Keukeninrichting",
    "sg:phone":"+31 413 273 963",
    "sg:postcode":"5409 AC",
    "sg:province":"North Brabant",
    "wof:name":"Vof Ad Van Gerwen Interieurverzorging",
    "wof:placetype":"venue"
},
  "geometry": {"coordinates":[5.702266,51.644543],"type":"Point"}
}