{
  "type": "Feature",
  "properties": {
    "addr:full":"Industrieweg 58 Staphorst NL.08 7951 TA",
    "addr:housenumber":"58;nl.08",
    "addr:postcode":"7951 ta",
    "addr:street":"Industrieweg",
    "iso:country":"NL",
    "sg:address":"Industrieweg 58",
    "sg:city":"Staphorst",
    "sg:orig_category":"Metaalbekleding And -Behandeling",
    "sg:phone":"+31 522 463 282",
    "sg:postcode":"7951 TA",
    "sg:province":"NL.08",
    "wof:name":"Dulasta Metaalbewerking Bv",
    "wof:placetype":"venue"
},
  "geometry": {"coordinates":[6.227504,52.634087],"type":"Point"}
}