{
  "type": "Feature",
  "properties": {
    "addr:full":"Tolakkerweg 34 Hollandsche Rading Utrecht 3739 JN",
    "addr:housenumber":"34",
    "addr:postcode":"rading;3739 jn",
    "addr:street":"Tolakkerweg",
    "iso:country":"NL",
    "sg:address":"Tolakkerweg 34",
    "sg:city":"Hollandsche Rading",
    "sg:orig_category":"Boekenuitgeverijen",
    "sg:phone":"+31 35 577 1640",
    "sg:postcode":"3739 JN",
    "sg:province":"Utrecht",
    "wof:name":"Abm Reclame & Uitgeverij",
    "wof:placetype":"venue"
},
  "geometry": {"coordinates":[5.174732,52.17569],"type":"Point"}
}