{
  "type": "Feature",
  "properties": {
    "addr:full":"Akkerstr 58 Vught North Brabant 5261 TX",
    "addr:housenumber":"58",
    "addr:postcode":"5261 tx",
    "addr:street":"Akkerstr",
    "iso:country":"NL",
    "sg:address":"Akkerstr 58",
    "sg:city":"Vught",
    "sg:orig_category":"Vertaalbureaus",
    "sg:phone":"+31 6 55733832",
    "sg:postcode":"5261 TX",
    "sg:province":"North Brabant",
    "sg:website":"http://www.rittertaalcontact.nl",
    "wof:name":"Ritter",
    "wof:placetype":"venue"
},
  "geometry": {"coordinates":[5.293479,51.651276],"type":"Point"}
}