{
  "type": "Feature",
  "properties": {
    "addr:full":"Dahliastr 1C St Oedenrode Noord-Brabant 5492 HL",
    "addr:housenumber":"1c",
    "addr:postcode":"5492 hl",
    "addr:street":"Dahliastr;St",
    "iso:country":"NL",
    "sg:address":"Dahliastr 1C",
    "sg:city":"St Oedenrode",
    "sg:orig_category":"Kappers",
    "sg:phone":"+31 413 476 105",
    "sg:postcode":"5492 HL",
    "sg:province":"Noord-Brabant",
    "wof:name":"Peter",
    "wof:placetype":"venue"
},
  "geometry": {"coordinates":[5.480632,51.551018],"type":"Point"}
}