{
  "type": "Feature",
  "properties": {
    "addr:full":"Lorentzstraat 52 Maastricht Limburg 6227 TM",
    "addr:housenumber":"52",
    "addr:postcode":"6227 tm",
    "addr:street":"Lorentzstraat",
    "iso:country":"NL",
    "sg:address":"Lorentzstraat 52",
    "sg:city":"Maastricht",
    "sg:orig_category":"Bedrijfs- And Managementsconsultants",
    "sg:phone":"+31 43 361 9922",
    "sg:postcode":"6227 TM",
    "sg:province":"Limburg",
    "wof:name":"Scil Development Bv",
    "wof:placetype":"venue"
},
  "geometry": {"coordinates":[5.7349,50.835938],"type":"Point"}
}