{
  "type": "Feature",
  "properties": {
    "addr:full":"Keizerstraat 76 Gouda South Holland 2801 NM",
    "addr:housenumber":"76",
    "addr:postcode":"2801",
    "addr:street":"Keizerstraat",
    "iso:country":"NL",
    "sg:address":"Keizerstraat 76",
    "sg:city":"Gouda",
    "sg:orig_category":"Huishoudapparatuur, Televisies And Radio'S",
    "sg:phone":"+31 182 515 248",
    "sg:postcode":"2801 NM",
    "sg:province":"South Holland",
    "wof:name":"Expert Willemsen Bv",
    "wof:placetype":"venue"
},
  "geometry": {"coordinates":[4.709448,52.008312],"type":"Point"}
}