{
  "type": "Feature",
  "properties": {
    "addr:full":"West-Peterstraat 48 Arnhem Gelderland 6822 AB",
    "addr:housenumber":"48",
    "addr:postcode":"6822 ab",
    "addr:street":"West-Peterstraat",
    "iso:country":"NL",
    "sg:address":"West-Peterstraat 48",
    "sg:city":"Arnhem",
    "sg:orig_category":"Artiestenbureaus",
    "sg:phone":"+31 26 351 1242",
    "sg:postcode":"6822 AB",
    "sg:province":"Gelderland",
    "wof:name":"Klankkleur",
    "wof:placetype":"venue"
},
  "geometry": {"coordinates":[5.915646,51.986809],"type":"Point"}
}