{
  "type": "Feature",
  "properties": {
    "addr:full":"Ina Boudier-Bakkerlaan 155 Utrecht Utrecht 3582 ZA",
    "addr:housenumber":"155",
    "addr:postcode":"3582",
    "addr:street":"Ina Boudier-Bakkerlaan",
    "iso:country":"NL",
    "sg:address":"Ina Boudier-Bakkerlaan 155",
    "sg:city":"Utrecht",
    "sg:orig_category":"Makelaars In Onroerend Goed",
    "sg:phone":"+31 30 252 5725",
    "sg:postcode":"3582 ZA",
    "sg:province":"Utrecht",
    "wof:name":"Stichting Sociale Huisvesting Utrecht",
    "wof:placetype":"venue"
},
  "geometry": {"coordinates":[5.132944,52.079521],"type":"Point"}
}