{
  "type": "Feature",
  "properties": {
    "iso:country":"NL",
    "sg:address":"Van De Meer De Walcherenstr 2",
    "sg:city":"Lichtenvoorde",
    "sg:orig_category":"Hypotheken",
    "sg:phone":"+31 544 377 113",
    "sg:postcode":"7131 EN",
    "sg:province":"Gelderland",
    "sg:website":"http://www.lichtenvoorde.hypotheekshop.nl/820",
    "wof:name":"Hypotheekshop, De",
    "wof:placetype":"venue"
},
  "geometry": {"coordinates":[6.570713,51.986816],"type":"Point"}
}