{
  "type": "Feature",
  "properties": {
    "iso:country":"NL",
    "sg:address":"Rijksstraatweg 437",
    "sg:city":"Haarlem",
    "sg:orig_category":"Boekhandels",
    "sg:phone":"+31 23 537 1580",
    "sg:postcode":"2025 DC",
    "sg:province":"North Holland",
    "wof:name":"Kantoorboekhandel Consten",
    "wof:placetype":"venue"
},
  "geometry": {"coordinates":[4.649929,52.41452],"type":"Point"}
}