{
  "type": "Feature",
  "properties": {
    "addr:full":"Emmaln 14 Geldermalsen Gelderland 4191 EK",
    "addr:housenumber":"14",
    "addr:postcode":"4191 ek",
    "addr:street":"Emmaln;Gelderland",
    "iso:country":"NL",
    "sg:address":"Emmaln 14",
    "sg:city":"Geldermalsen",
    "sg:orig_category":"Webdesign Bureaus",
    "sg:phone":"+31 345 581 974",
    "sg:postcode":"4191 EK",
    "sg:province":"Gelderland",
    "sg:website":"http://martijn@elserman.nl",
    "wof:name":"Elserman",
    "wof:placetype":"venue"
},
  "geometry": {"coordinates":[5.2909770012,51.8808746338],"type":"Point"}
}