{
  "type": "Feature",
  "properties": {
    "iso:country":"NL",
    "sg:address":"Willem Passtoorsstraat 74",
    "sg:city":"Zundert",
    "sg:orig_category":"Boomkwekerijen",
    "sg:phone":"+31 76 597 2263",
    "sg:postcode":"4881 BS",
    "sg:province":"North Brabant",
    "wof:name":"Boomkwekerij A.A.M. Vissenberg Vof",
    "wof:placetype":"venue"
},
  "geometry": {"coordinates":[4.660965,51.475826],"type":"Point"}
}