{
  "type": "Feature",
  "properties": {
    "addr:full":"Kreupelstr 14 Vierlingsbeek Noord-Brabant 5821 AX",
    "addr:housenumber":"14",
    "addr:postcode":"5821 ax",
    "addr:street":"Kreupelstr",
    "iso:country":"NL",
    "sg:address":"Kreupelstr 14",
    "sg:city":"Vierlingsbeek",
    "sg:orig_category":"Peuterspeelzalen",
    "sg:phone":"+31 478 632 474",
    "sg:postcode":"5821 AX",
    "sg:province":"Noord-Brabant",
    "wof:name":"Pompelientje",
    "wof:placetype":"venue"
},
  "geometry": {"coordinates":[6.012688,51.595264],"type":"Point"}
}