{
  "type": "Feature",
  "properties": {
    "addr:full":"Kneesweg 16 Anna Paulowna North Holland 1761 JC",
    "addr:housenumber":"16",
    "addr:postcode":"1761 jc",
    "addr:street":"Kneesweg",
    "iso:country":"NL",
    "sg:address":"Kneesweg 16",
    "sg:city":"Anna Paulowna",
    "sg:orig_category":"Granen, Zaden And Diervoeders Gh",
    "sg:phone":"+31 223 531 404",
    "sg:postcode":"1761 JC",
    "sg:province":"North Holland",
    "wof:name":"Bv Bloembollenkwekerij En -Handel Hartelust",
    "wof:placetype":"venue"
},
  "geometry": {"coordinates":[4.824425,52.842331],"type":"Point"}
}