{
  "type": "Feature",
  "properties": {
    "addr:full":"Ankerstr 10 Maassluis South Holland 3144 EA",
    "addr:housenumber":"10",
    "addr:postcode":"3144 ea",
    "addr:street":"Ankerstr",
    "iso:country":"NL",
    "sg:address":"Ankerstr 10",
    "sg:city":"Maassluis",
    "sg:classifiers":[
        {
            "category":"Banks & Credit Unions",
            "subcategory":"Investment Brokerage",
            "type":"Services"
        }
    ],
    "sg:phone":"+31 10 591 3314",
    "sg:postcode":"3144 EA",
    "sg:province":"South Holland",
    "sg:tags":[
        "pension"
    ],
    "wof:name":"Antonetta",
    "wof:placetype":"venue"
},
  "geometry": {"coordinates":[4.250972,51.921543],"type":"Point"}
}