{
  "type": "Feature",
  "properties": {
    "iso:country":"NL",
    "sg:address":"Molenstr 123",
    "sg:city":"Fynaart",
    "sg:orig_category":"Fietsen En Bromfietsen",
    "sg:phone":"+31 168 462 638",
    "sg:postcode":"4793 RB",
    "sg:province":"Noord-Brabant",
    "wof:name":"Sweere Rijwielen, P",
    "wof:placetype":"venue"
},
  "geometry": {"coordinates":[4.45616,51.638317],"type":"Point"}
}