{
  "type": "Feature",
  "properties": {
    "addr:full":"Bizonplnts 1 Almere Flevoland 1338 JE",
    "addr:housenumber":"1",
    "addr:postcode":"1338 je",
    "addr:street":"Bizonplnts;Flevoland",
    "iso:country":"NL",
    "sg:address":"Bizonplnts 1",
    "sg:city":"Almere",
    "sg:orig_category":"Nagelstudio'S",
    "sg:phone":"+31 36 549 0557",
    "sg:postcode":"1338 JE",
    "sg:province":"Flevoland",
    "wof:name":"Almere Goldfinger",
    "wof:placetype":"venue"
},
  "geometry": {"coordinates":[5.27846,52.386421],"type":"Point"}
}