{
  "type": "Feature",
  "properties": {
    "addr:full":"Zuidpln Hg 568 Rotterdam South Holland 3083 BM",
    "addr:housenumber":"568",
    "addr:postcode":"3083 bm",
    "addr:street":"Hg",
    "iso:country":"NL",
    "sg:address":"Zuidpln Hg 568",
    "sg:city":"Rotterdam",
    "sg:orig_category":"Boeken En Tijdschriften",
    "sg:phone":"+31 10 481 3928",
    "sg:postcode":"3083 BM",
    "sg:province":"South Holland",
    "wof:name":"Populair",
    "wof:placetype":"venue"
},
  "geometry": {"coordinates":[4.490137,51.887051],"type":"Point"}
}