{
  "type": "Feature",
  "properties": {
    "addr:full":"Gaffelhoek 67 Enschede Overijssel 7546 MT",
    "addr:housenumber":"67",
    "addr:postcode":"7546",
    "addr:street":"Gaffelhoek;Mt",
    "iso:country":"NL",
    "sg:address":"Gaffelhoek 67",
    "sg:city":"Enschede",
    "sg:orig_category":"Loodgieterswerk, Verwarming And Sanitaire Installaties",
    "sg:phone":"+31 53 477 7803",
    "sg:postcode":"7546 MT",
    "sg:province":"Overijssel",
    "wof:name":"R Beisser",
    "wof:placetype":"venue"
},
  "geometry": {"coordinates":[6.850535,52.199829],"type":"Point"}
}