{
  "type": "Feature",
  "properties": {
    "addr:full":"Postbus 75106 Schiphol North Holland 1117 ZR",
    "addr:postcode":"75106;1117 zr",
    "addr:street":"Postbus",
    "iso:country":"NL",
    "sg:address":"Postbus 75106",
    "sg:city":"Schiphol",
    "sg:orig_category":"Koeriersdiensten",
    "sg:phone":"+31 20 657 0040",
    "sg:postcode":"1117 ZR",
    "sg:province":"North Holland",
    "wof:name":"Courier Plus Bv",
    "wof:placetype":"venue"
},
  "geometry": {"coordinates":[4.81141,52.3088],"type":"Point"}
}