{
  "type": "Feature",
  "properties": {
    "iso:country":"NL",
    "sg:address":"Stationsstr 8",
    "sg:city":"Veghel",
    "sg:orig_category":"Autorijscholen",
    "sg:phone":"+31 413 376 272",
    "sg:postcode":"5461 JV",
    "sg:province":"Noord-Brabant",
    "wof:name":"Beste, De",
    "wof:placetype":"venue"
},
  "geometry": {"coordinates":[5.54535,51.618687],"type":"Point"}
}