{
  "type": "Feature",
  "properties": {
    "addr:full":"Hoofdwg 293 Hoofddorp North Holland 2131 LL",
    "addr:housenumber":"293",
    "addr:postcode":"2131 ll",
    "iso:country":"NL",
    "sg:address":"Hoofdwg 293",
    "sg:city":"Hoofddorp",
    "sg:orig_category":"Land- En Tuinbouw - Loonbedrijven",
    "sg:phone":"+31 23 555 1290",
    "sg:postcode":"2131 LL",
    "sg:province":"North Holland",
    "wof:name":"Kamper Agri Bv",
    "wof:placetype":"venue"
},
  "geometry": {"coordinates":[4.721608,52.326122],"type":"Point"}
}