{
  "type": "Feature",
  "properties": {
    "addr:full":"Erepryswg 7 Haren Gn Groningen 9753 AP",
    "addr:housenumber":"7",
    "addr:postcode":"9753 ap",
    "addr:street":"Erepryswg",
    "iso:country":"NL",
    "sg:address":"Erepryswg 7",
    "sg:city":"Haren Gn",
    "sg:orig_category":"Afslankinstituten",
    "sg:phone":"+31 50 534 3447",
    "sg:postcode":"9753 AP",
    "sg:province":"Groningen",
    "wof:name":"Jacqueline Beettjer",
    "wof:placetype":"venue"
},
  "geometry": {"coordinates":[6.60632,53.170658],"type":"Point"}
}