{
  "type": "Feature",
  "properties": {
    "addr:full":"Amstelpln 1 Amsterdam North Holland 1096 HA",
    "addr:housenumber":"1",
    "addr:postcode":"1096 ha",
    "addr:street":"Amstelpln",
    "iso:country":"NL",
    "sg:address":"Amstelpln 1",
    "sg:city":"Amsterdam",
    "sg:orig_category":"Werving En Selectie",
    "sg:phone":"+31 20 462 7777",
    "sg:postcode":"1096 HA",
    "sg:province":"North Holland",
    "wof:name":"Heidrick & Struggles",
    "wof:placetype":"venue"
},
  "geometry": {"coordinates":[4.9176487923,52.3443107605],"type":"Point"}
}