{
  "type": "Feature",
  "properties": {
    "addr:full":"Ln V Poot 355 S Gravenhage Zuid-Holland 2566 DA",
    "addr:housenumber":"355;gravenhage;2566",
    "addr:postcode":"da",
    "addr:street":"Ln;Poot;S",
    "iso:country":"NL",
    "sg:address":"Ln V Poot 355",
    "sg:city":"S Gravenhage",
    "sg:orig_category":"Scholen Voor Basisonderwijs",
    "sg:phone":"+31 70 325 7547",
    "sg:postcode":"2566 DA",
    "sg:province":"Zuid-Holland",
    "sg:website":"http://www.nutsschool.nl",
    "wof:name":"Nutsschool Laan Van Poot",
    "wof:placetype":"venue"
},
  "geometry": {"coordinates":[4.25553,52.079128],"type":"Point"}
}