{
  "type": "Feature",
  "properties": {
    "iso:country":"NL",
    "sg:address":"Rijksweg Noord 29",
    "sg:city":"Swalmen",
    "sg:orig_category":"Huishoudapparatuur, Televisies And Radio'S",
    "sg:phone":"+31 475 501 489",
    "sg:postcode":"6071 KS",
    "sg:province":"Limburg",
    "wof:name":"Radio Hautus A.P. Berkers",
    "wof:placetype":"venue"
},
  "geometry": {"coordinates":[6.040352,51.234329],"type":"Point"}
}