{
  "type": "Feature",
  "properties": {
    "addr:full":"Damrak 98 Amsterdam North Holland 1012 LP",
    "addr:housenumber":"98",
    "addr:postcode":"1012 lp",
    "addr:street":"Damrak",
    "iso:country":"NL",
    "sg:address":"Damrak 98",
    "sg:city":"Amsterdam",
    "sg:orig_category":"Werving And Selectie Van Tijdelijk Personeel And Uitzendkantoren",
    "sg:phone":"+31 20 421 3003",
    "sg:postcode":"1012 LP",
    "sg:province":"North Holland",
    "wof:name":"Ad Rem",
    "wof:placetype":"venue"
},
  "geometry": {"coordinates":[4.8932981491,52.3734779358],"type":"Point"}
}