{
  "type": "Feature",
  "properties": {
    "addr:full":"Deventerstr 62 Vaassen Gelderland 8171 AG",
    "addr:housenumber":"62",
    "addr:postcode":"8171",
    "addr:street":"Deventerstr;Gelderland",
    "iso:country":"NL",
    "sg:address":"Deventerstr 62",
    "sg:city":"Vaassen",
    "sg:orig_category":"Vertaalbureaus",
    "sg:phone":"+31 578 575 546",
    "sg:postcode":"8171 AG",
    "sg:province":"Gelderland",
    "wof:name":"Tijman",
    "wof:placetype":"venue"
},
  "geometry": {"coordinates":[5.976087,52.289917],"type":"Point"}
}