{
  "type": "Feature",
  "properties": {
    "addr:full":"Prins Hendrikweg 12 Noordwijk Zh South Holland 2202 EB",
    "addr:housenumber":"12",
    "addr:postcode":"zh;2202 eb",
    "addr:street":"Prins Hendrikweg",
    "iso:country":"NL",
    "sg:address":"Prins Hendrikweg 12",
    "sg:city":"Noordwijk Zh",
    "sg:orig_category":"Boekenuitgeverijen",
    "sg:phone":"+31 71 361 4892",
    "sg:postcode":"2202 EB",
    "sg:province":"South Holland",
    "wof:name":"Uitge. Jorrit, Promoties En Produkties B",
    "wof:placetype":"venue"
},
  "geometry": {"coordinates":[4.437316,52.241386],"type":"Point"}
}