{
  "type": "Feature",
  "properties": {
    "addr:full":"Wilhelminastr 2A Rhenen Utrecht 3911 MC",
    "addr:housenumber":"2a",
    "addr:postcode":"3911 mc",
    "addr:street":"Wilhelminastr",
    "iso:country":"NL",
    "sg:address":"Wilhelminastr 2A",
    "sg:city":"Rhenen",
    "sg:classifiers":[
        {
            "category":"Personal",
            "subcategory":"Nail Salon",
            "type":"Services"
        }
    ],
    "sg:phone":"+31 317 618 311",
    "sg:postcode":"3911 MC",
    "sg:province":"Utrecht",
    "sg:tags":[
        "pedicure"
    ],
    "wof:name":"Jacquelien Pedicure Praktijk",
    "wof:placetype":"venue"
},
  "geometry": {"coordinates":[5.569642,51.959015],"type":"Point"}
}