{
  "type": "Feature",
  "properties": {
    "addr:full":"Goenjeweg 2 Sevenum Limburg 5975 NZ",
    "addr:housenumber":"2",
    "addr:postcode":"5975 nz",
    "addr:street":"Goenjeweg",
    "iso:country":"NL",
    "sg:address":"Goenjeweg 2",
    "sg:city":"Sevenum",
    "sg:orig_category":"Diverse Dierenfokkers",
    "sg:phone":"+31 77 467 3221",
    "sg:postcode":"5975 NZ",
    "sg:province":"Limburg",
    "wof:name":"Smeetenhof Bv",
    "wof:placetype":"venue"
},
  "geometry": {"coordinates":[6.024643,51.387348],"type":"Point"}
}