{
  "type": "Feature",
  "properties": {
    "iso:country":"NL",
    "sg:address":"Sassenstr 76",
    "sg:city":"Zwolle",
    "sg:orig_category":"Open Haarden",
    "sg:phone":"+31 38 426 5502",
    "sg:postcode":"8011 PD",
    "sg:province":"Overijssel",
    "wof:name":"Dilay",
    "wof:placetype":"venue"
},
  "geometry": {"coordinates":[6.095308,52.510159],"type":"Point"}
}