{
  "type": "Feature",
  "properties": {
    "iso:country":"NL",
    "sg:address":"Bosschendk 1-3",
    "sg:city":"Oudenbosch",
    "sg:orig_category":"Cafetaria'S",
    "sg:phone":"+31 165 315 627",
    "sg:postcode":"4731 DA",
    "sg:province":"Noord-Brabant",
    "wof:name":"Schuiven, De",
    "wof:placetype":"venue"
},
  "geometry": {"coordinates":[4.534946,51.588737],"type":"Point"}
}