{
  "type": "Feature",
  "properties": {
    "addr:full":"Winterdijk 14 Waalwijk Noord-Brabant 5141 KE",
    "addr:housenumber":"14",
    "addr:postcode":"5141 ke",
    "addr:street":"Winterdijk",
    "iso:country":"NL",
    "sg:address":"Winterdijk 14",
    "sg:city":"Waalwijk",
    "sg:orig_category":"Fitnesscentra",
    "sg:phone":"+31 416 332 293",
    "sg:postcode":"5141 KE",
    "sg:province":"Noord-Brabant",
    "wof:name":"Ecker Sport & Fitness",
    "wof:placetype":"venue"
},
  "geometry": {"coordinates":[5.060778,51.690491],"type":"Point"}
}