{
  "type": "Feature",
  "properties": {
    "addr:full":"Katoenstr 24 Genemuiden NL.08 8281 JZ",
    "addr:housenumber":"24;nl.08",
    "addr:postcode":"8281 jz",
    "addr:street":"Katoenstr",
    "iso:country":"NL",
    "sg:address":"Katoenstr 24",
    "sg:city":"Genemuiden",
    "sg:orig_category":"Beveiliging",
    "sg:phone":"+31 38 385 2030",
    "sg:postcode":"8281 JZ",
    "sg:province":"NL.08",
    "wof:name":"Roetman",
    "wof:placetype":"venue"
},
  "geometry": {"coordinates":[6.063824,52.61499],"type":"Point"}
}