{
  "type": "Feature",
  "properties": {
    "addr:full":"Boodtlaan 6 De Koog Noord-Holland 1796 BE",
    "addr:housenumber":"6",
    "addr:postcode":"1796",
    "addr:street":"Boodtlaan",
    "iso:country":"NL",
    "sg:address":"Boodtlaan 6",
    "sg:city":"De Koog",
    "sg:classifiers":[
        {
            "category":"Travel",
            "subcategory":"Hotels & Motels",
            "type":"Entertainment"
        }
    ],
    "sg:phone":"+31 222 317 233",
    "sg:postcode":"1796 BE",
    "sg:province":"Noord-Holland",
    "wof:name":"Hotel Restaurant De Branding",
    "wof:placetype":"venue"
},
  "geometry": {"coordinates":[4.763169,53.100204],"type":"Point"}
}