{
  "type": "Feature",
  "properties": {
    "addr:full":"Zwaluwstr 104 Maassluis Zuid-Holland 3145 NH",
    "addr:housenumber":"104",
    "addr:postcode":"3145 nh",
    "iso:country":"NL",
    "sg:address":"Zwaluwstr 104",
    "sg:city":"Maassluis",
    "sg:orig_category":"Administratie- En Boekhoudkantoren",
    "sg:phone":"+31 10 592 8284",
    "sg:postcode":"3145 NH",
    "sg:province":"Zuid-Holland",
    "wof:name":"Anru",
    "wof:placetype":"venue"
},
  "geometry": {"coordinates":[4.238218,51.931713],"type":"Point"}
}