{
  "type": "Feature",
  "properties": {
    "addr:full":"Oosterstr 16 Leiden South Holland 2315 LH",
    "addr:housenumber":"16",
    "addr:postcode":"2315 lh",
    "addr:street":"Oosterstr",
    "iso:country":"NL",
    "sg:address":"Oosterstr 16",
    "sg:city":"Leiden",
    "sg:orig_category":"Verenigingsgebouwen",
    "sg:phone":"+31 71 521 9869",
    "sg:postcode":"2315 LH",
    "sg:province":"South Holland",
    "wof:name":"Schippertje, 'T",
    "wof:placetype":"venue"
},
  "geometry": {"coordinates":[4.506146,52.157158],"type":"Point"}
}