{
  "type": "Feature",
  "properties": {
    "addr:full":"Klapperdijk 22 Wapenveld Gelderland 8191 AD",
    "addr:housenumber":"22",
    "addr:postcode":"8191 ad",
    "addr:street":"Klapperdijk;Gelderland",
    "iso:country":"NL",
    "sg:address":"Klapperdijk 22",
    "sg:city":"Wapenveld",
    "sg:orig_category":"Verlichting And Huishoudartikelen",
    "sg:phone":"+31 38 447 8297",
    "sg:postcode":"8191 AD",
    "sg:province":"Gelderland",
    "wof:name":"J. Olthuis",
    "wof:placetype":"venue"
},
  "geometry": {"coordinates":[6.072447,52.431973],"type":"Point"}
}