{
  "type": "Feature",
  "properties": {
    "addr:full":"Horsterwg 38 Ermelo Gelderland 3851 PJ",
    "addr:housenumber":"38",
    "addr:postcode":"3851 pj",
    "addr:street":"Horsterwg;Gelderland",
    "iso:country":"NL",
    "sg:address":"Horsterwg 38",
    "sg:city":"Ermelo",
    "sg:orig_category":"Schilders",
    "sg:phone":"+31 341 558 264",
    "sg:postcode":"3851 PJ",
    "sg:province":"Gelderland",
    "wof:name":"Gielen Vof",
    "wof:placetype":"venue"
},
  "geometry": {"coordinates":[5.622619,52.30275],"type":"Point"}
}