{
  "type": "Feature",
  "properties": {
    "iso:country":"NL",
    "sg:address":"Weverwg 5",
    "sg:city":"Eerbeek",
    "sg:orig_category":"Houtgroothandel",
    "sg:phone":"+31 313 656 486",
    "sg:postcode":"6961 KM",
    "sg:province":"Gelderland",
    "wof:name":"Rogue Timber Bv",
    "wof:placetype":"venue"
},
  "geometry": {"coordinates":[6.047365,52.108215],"type":"Point"}
}