{
  "type": "Feature",
  "properties": {
    "addr:full":"Nykampenwg 181 Emmen Drenthe 7815 GJ",
    "addr:housenumber":"181",
    "addr:postcode":"7815 gj",
    "iso:country":"NL",
    "sg:address":"Nykampenwg 181",
    "sg:city":"Emmen",
    "sg:orig_category":"Artiesten/Gezelschappen",
    "sg:phone":"+31 591 619 515",
    "sg:postcode":"7815 GJ",
    "sg:province":"Drenthe",
    "wof:name":"Display",
    "wof:placetype":"venue"
},
  "geometry": {"coordinates":[6.893144,52.799126],"type":"Point"}
}