{
  "type": "Feature",
  "properties": {
    "iso:country":"NL",
    "sg:address":"Noordlierweg 57",
    "sg:city":"Schipluiden",
    "sg:orig_category":"Autokeuringen",
    "sg:phone":"+31 174 540 629",
    "sg:postcode":"2636 AB",
    "sg:province":"Zuid-Holland",
    "wof:name":"Van Winden",
    "wof:placetype":"venue"
},
  "geometry": {"coordinates":[4.28244,51.98645],"type":"Point"}
}