{
  "type": "Feature",
  "properties": {
    "iso:country":"NL",
    "sg:address":"Eikenlaan 1",
    "sg:city":"Vught",
    "sg:orig_category":"Beveiliging",
    "sg:phone":"+31 73 656 7975",
    "sg:postcode":"5263 GM",
    "sg:province":"Noord-Brabant",
    "wof:name":"Tracking & Tracing Innovation Bv",
    "wof:placetype":"venue"
},
  "geometry": {"coordinates":[5.27491,51.654137],"type":"Point"}
}