{
  "type": "Feature",
  "properties": {
    "addr:full":"Portengen 92A Kockengen Utrecht 3628 EH",
    "addr:housenumber":"92a",
    "addr:postcode":"3628 eh",
    "addr:street":"Portengen",
    "iso:country":"NL",
    "sg:address":"Portengen 92A",
    "sg:city":"Kockengen",
    "sg:orig_category":"Loonbedrijven",
    "sg:phone":"+31 346 241 585",
    "sg:postcode":"3628 EH",
    "sg:province":"Utrecht",
    "wof:name":"Versteegh",
    "wof:placetype":"venue"
},
  "geometry": {"coordinates":[4.950211,52.168007],"type":"Point"}
}