{
  "type": "Feature",
  "properties": {
    "addr:full":"Scheurrak 1 Urk Flevoland 8321 WB",
    "addr:housenumber":"1",
    "addr:postcode":"8321 wb",
    "addr:street":"Scheurrak;Flevoland",
    "iso:country":"NL",
    "sg:address":"Scheurrak 1",
    "sg:city":"Urk",
    "sg:orig_category":"Koel- En Vrieshuizen",
    "sg:phone":"+31 527 685 000",
    "sg:postcode":"8321 WB",
    "sg:province":"Flevoland",
    "wof:name":"Royal Bv",
    "wof:placetype":"venue"
},
  "geometry": {"coordinates":[5.617878,52.653801],"type":"Point"}
}