{
  "type": "Feature",
  "properties": {
    "addr:full":"Bergweg 72 Veenendaal Utrecht 3904 HR",
    "addr:housenumber":"72",
    "addr:postcode":"3904 hr",
    "addr:street":"Bergweg",
    "iso:country":"NL",
    "sg:address":"Bergweg 72",
    "sg:city":"Veenendaal",
    "sg:orig_category":"Schilderwerk",
    "sg:phone":"+31 318 550 375",
    "sg:postcode":"3904 HR",
    "sg:province":"Utrecht",
    "wof:name":"T.J.H. Henken",
    "wof:placetype":"venue"
},
  "geometry": {"coordinates":[5.538655,52.01376],"type":"Point"}
}