{
  "type": "Feature",
  "properties": {
    "iso:country":"NL",
    "sg:address":"De Enk 16",
    "sg:city":"Bemmel",
    "sg:orig_category":"Bloemen And Planten Gh",
    "sg:phone":"+31 481 465 478",
    "sg:postcode":"6681 HD",
    "sg:province":"Gelderland",
    "wof:name":"H.J.M. Scholten",
    "wof:placetype":"venue"
},
  "geometry": {"coordinates":[5.895321,51.898373],"type":"Point"}
}