{
  "type": "Feature",
  "properties": {
    "addr:full":"Bisschop Hamerstraat 14 Nijmegen Gelderland 6511 NB",
    "addr:housenumber":"14",
    "addr:postcode":"6511 nb",
    "addr:street":"Bisschop Hamerstraat;Gelderland",
    "iso:country":"NL",
    "sg:address":"Bisschop Hamerstraat 14",
    "sg:city":"Nijmegen",
    "sg:orig_category":"Verlichting And Huishoudartikelen",
    "sg:phone":"+31 24 360 3894",
    "sg:postcode":"6511 NB",
    "sg:province":"Gelderland",
    "wof:name":"Kijkshop",
    "wof:placetype":"venue"
},
  "geometry": {"coordinates":[5.859922,51.842869],"type":"Point"}
}