{
  "type": "Feature",
  "properties": {
    "iso:country":"NL",
    "sg:address":"Bedrijvenweg 1",
    "sg:city":"Andijk",
    "sg:orig_category":"Metaalbekleding And -Behandeling",
    "sg:phone":"+31 228 591 677",
    "sg:postcode":"1619 BK",
    "sg:province":"North Holland",
    "wof:name":"Fa Oppedijk Metaalwaren",
    "wof:placetype":"venue"
},
  "geometry": {"coordinates":[5.225193,52.738762],"type":"Point"}
}