{
  "type": "Feature",
  "properties": {
    "addr:full":"Ministerlaan 57 Zwolle NL.08 8014 PM",
    "addr:housenumber":"57",
    "addr:postcode":"8014 pm",
    "addr:street":"Ministerlaan",
    "iso:country":"NL",
    "sg:address":"Ministerlaan 57",
    "sg:city":"Zwolle",
    "sg:orig_category":"Film-, Tv- And Videoproductie",
    "sg:phone":"+31 38 465 3687",
    "sg:postcode":"8014 PM",
    "sg:province":"NL.08",
    "wof:name":"Lone Star",
    "wof:placetype":"venue"
},
  "geometry": {"coordinates":[6.111796,52.478207],"type":"Point"}
}