{
  "type": "Feature",
  "properties": {
    "iso:country":"NL",
    "sg:address":"Aalsmeerderwg 517",
    "sg:city":"Rozenburg Nh",
    "sg:orig_category":"Verpakkingen En Verpakkingsmaterialen",
    "sg:phone":"+31 20 653 4599",
    "sg:postcode":"1437 EE",
    "sg:province":"Noord-Holland",
    "wof:name":"Plasticon",
    "wof:placetype":"venue"
},
  "geometry": {"coordinates":[4.738468,52.282516],"type":"Point"}
}