{
  "type": "Feature",
  "properties": {
    "addr:full":"A Geertsstraat 19 Olst NL.08 8121 BK",
    "addr:housenumber":"19;nl.08",
    "addr:postcode":"8121 bk",
    "addr:street":"A Geertsstraat",
    "iso:country":"NL",
    "sg:address":"A Geertsstraat 19",
    "sg:city":"Olst",
    "sg:orig_category":"Kantoorartikelen",
    "sg:phone":"+31 570 561 298",
    "sg:postcode":"8121 BK",
    "sg:province":"NL.08",
    "wof:name":"Boek- En Kantoorvakhandel Korten",
    "wof:placetype":"venue"
},
  "geometry": {"coordinates":[6.1135411263,52.3374786377],"type":"Point"}
}