{
  "type": "Feature",
  "properties": {
    "addr:full":"Grt Kerkstr 42 Raamsdonksveer North Brabant 4941 DP",
    "addr:housenumber":"42",
    "addr:postcode":"4941 dp",
    "iso:country":"NL",
    "sg:address":"Grt Kerkstr 42",
    "sg:city":"Raamsdonksveer",
    "sg:orig_category":"Beeldende Kunstenaars",
    "sg:phone":"+31 162 523 090",
    "sg:postcode":"4941 DP",
    "sg:province":"North Brabant",
    "wof:name":"Gerritson",
    "wof:placetype":"venue"
},
  "geometry": {"coordinates":[4.869862,51.693905],"type":"Point"}
}