{
  "type": "Feature",
  "properties": {
    "addr:full":"Jupiterweg 55 Oss Noord-Brabant 5345 LR",
    "addr:housenumber":"55",
    "addr:postcode":"5345 lr",
    "addr:street":"Jupiterweg",
    "iso:country":"NL",
    "sg:address":"Jupiterweg 55",
    "sg:city":"Oss",
    "sg:orig_category":"Kappers",
    "sg:phone":"+31 412 652 516",
    "sg:postcode":"5345 LR",
    "sg:province":"Noord-Brabant",
    "wof:name":"S. V.D. Zanden",
    "wof:placetype":"venue"
},
  "geometry": {"coordinates":[-77.235214,38.312599],"type":"Point"}
}