{
  "type": "Feature",
  "properties": {
    "addr:full":"Petuniapln 2 Zwolle NL.08 8042 AV",
    "addr:housenumber":"2",
    "addr:postcode":"8042 av",
    "addr:street":"Petuniapln",
    "iso:country":"NL",
    "sg:address":"Petuniapln 2",
    "sg:city":"Zwolle",
    "sg:orig_category":"Kappers",
    "sg:phone":"+31 38 422 5069",
    "sg:postcode":"8042 AV",
    "sg:province":"NL.08",
    "wof:name":"Oostindie",
    "wof:placetype":"venue"
},
  "geometry": {"coordinates":[6.049886,52.521961],"type":"Point"}
}