{
  "type": "Feature",
  "properties": {
    "addr:full":"Belenbroeklaan 28 Heythuysen Limburg 6093 BT",
    "addr:housenumber":"28",
    "addr:postcode":"6093 bt",
    "addr:street":"Belenbroeklaan",
    "iso:country":"NL",
    "sg:address":"Belenbroeklaan 28",
    "sg:city":"Heythuysen",
    "sg:orig_category":"Bedrijfs- And Managementsconsultants",
    "sg:phone":"+31 475 492 673",
    "sg:postcode":"6093 BT",
    "sg:province":"Limburg",
    "wof:name":"D. Horree",
    "wof:placetype":"venue"
},
  "geometry": {"coordinates":[5.88586,51.248356],"type":"Point"}
}