{
  "type": "Feature",
  "properties": {
    "iso:country":"NL",
    "sg:address":"Leidsestrwg 153",
    "sg:city":"Woerden",
    "sg:orig_category":"Zoetwaren - Fabrieken En Groothandel",
    "sg:phone":"+31 348 430 324",
    "sg:postcode":"3443 BT",
    "sg:province":"Utrecht",
    "wof:name":"Lugano Bv",
    "wof:placetype":"venue"
},
  "geometry": {"coordinates":[4.887371,52.085117],"type":"Point"}
}