{
  "type": "Feature",
  "properties": {
    "addr:full":"Waalstr 46 Vlaardingen Zuid-Holland 3131 CS",
    "addr:housenumber":"46",
    "addr:postcode":"3131 cs",
    "addr:street":"Waalstr",
    "iso:country":"NL",
    "sg:address":"Waalstr 46",
    "sg:city":"Vlaardingen",
    "sg:orig_category":"Fietsen En Bromfietsen",
    "sg:phone":"+31 10 434 3913",
    "sg:postcode":"3131 CS",
    "sg:province":"Zuid-Holland",
    "sg:website":"http://www.leendejagertweewielers.nl",
    "wof:name":"Jager, Leen De",
    "wof:placetype":"venue"
},
  "geometry": {"coordinates":[4.340324,51.90868],"type":"Point"}
}