{
  "type": "Feature",
  "properties": {
    "addr:full":"Nordhornsestr 1 Denekamp Overijssel 7591 BC",
    "addr:housenumber":"1",
    "addr:postcode":"7591 bc",
    "addr:street":"Nordhornsestr",
    "iso:country":"NL",
    "sg:address":"Nordhornsestr 1",
    "sg:city":"Denekamp",
    "sg:orig_category":"Kinderkleding",
    "sg:phone":"+31 541 351 537",
    "sg:postcode":"7591 BC",
    "sg:province":"Overijssel",
    "wof:name":"Patrick Kinder & Jeugdmode",
    "wof:placetype":"venue"
},
  "geometry": {"coordinates":[7.00698,52.376495],"type":"Point"}
}