{
  "type": "Feature",
  "properties": {
    "addr:full":"Frieslandlaan 1 Veendam Groningen 9642 GL",
    "addr:housenumber":"1",
    "addr:postcode":"9642 gl",
    "addr:street":"Frieslandlaan",
    "iso:country":"NL",
    "sg:address":"Frieslandlaan 1",
    "sg:city":"Veendam",
    "sg:orig_category":"Krantenuitgeverijen",
    "sg:phone":"+31 598 632 729",
    "sg:postcode":"9642 GL",
    "sg:province":"Groningen",
    "wof:name":"Cobus Oosting Uitgever",
    "wof:placetype":"venue"
},
  "geometry": {"coordinates":[6.861208,53.093731],"type":"Point"}
}