{
  "type": "Feature",
  "properties": {
    "iso:country":"NL",
    "sg:address":"Kostverlorenhof 20-23",
    "sg:city":"Amstelveen",
    "sg:orig_category":"Banken And Kredietinstellingen",
    "sg:phone":"+31 20 643 2576",
    "sg:postcode":"1183  H",
    "sg:province":"North Holland",
    "wof:name":"Bruna",
    "wof:placetype":"venue"
},
  "geometry": {"coordinates":[4.874985,52.313042],"type":"Point"}
}