{
  "type": "Feature",
  "properties": {
    "iso:country":"NL",
    "sg:address":"Ceintuurbaan 292",
    "sg:city":"Amsterdam",
    "sg:classifiers":[
        {
            "category":"Shopping",
            "subcategory":"Adult",
            "type":"Retail Goods"
        }
    ],
    "sg:phone":"+31 20 662 9089",
    "sg:postcode":"1072 GK",
    "sg:province":"Noord-Holland",
    "sg:tags":[
        "lingerie",
        "en",
        "tricotage"
    ],
    "wof:name":"Veenendaalse Sinds 1929, De",
    "wof:placetype":"venue"
},
  "geometry": {"coordinates":[4.891707,52.352802],"type":"Point"}
}