{
  "type": "Feature",
  "properties": {
    "addr:full":"Keiwg 3A Oosterhout Nb Noord-Brabant 4901 JD",
    "addr:housenumber":"3a",
    "addr:postcode":"4901 jd",
    "addr:street":"Keiwg",
    "iso:country":"NL",
    "sg:address":"Keiwg 3A",
    "sg:city":"Oosterhout Nb",
    "sg:orig_category":"Herenkleding",
    "sg:phone":"+31 162 436 567",
    "sg:postcode":"4901 JD",
    "sg:province":"Noord-Brabant",
    "wof:name":"Gorgio",
    "wof:placetype":"venue"
},
  "geometry": {"coordinates":[4.860592,51.642948],"type":"Point"}
}