{
  "type": "Feature",
  "properties": {
    "addr:full":"P V Damstr 38 Almere NL. 1335 PG",
    "addr:housenumber":"38",
    "addr:postcode":"1335",
    "addr:street":"Damstr;Nl.;Pg",
    "iso:country":"NL",
    "sg:address":"P V Damstr 38",
    "sg:city":"Almere",
    "sg:orig_category":"Scholen Voor Basisonderwijs",
    "sg:phone":"+31 36 529 6818",
    "sg:postcode":"1335 PG",
    "sg:province":"NL.",
    "wof:name":"Egelantier, Basissch De",
    "wof:placetype":"venue"
},
  "geometry": {"coordinates":[5.29421,52.406631],"type":"Point"}
}