{
  "type": "Feature",
  "properties": {
    "addr:full":"Kraaijensteinweg 25 Burgh Haamstede Zeeland 4328 RZ",
    "addr:housenumber":"25",
    "addr:postcode":"4328 rz",
    "addr:street":"Kraaijensteinweg;Haamstede",
    "iso:country":"NL",
    "sg:address":"Kraaijensteinweg 25",
    "sg:city":"Burgh Haamstede",
    "sg:orig_category":"Kampeerterreinen",
    "sg:phone":"+31 111 651 852",
    "sg:postcode":"4328 RZ",
    "sg:province":"Zeeland",
    "wof:name":"C M De Broekert",
    "wof:placetype":"venue"
},
  "geometry": {"coordinates":[3.7371850014,51.6877288818],"type":"Point"}
}