{
  "type": "Feature",
  "properties": {
    "iso:country":"NL",
    "sg:address":"Lage Veenweg 6",
    "sg:city":"Emst",
    "sg:orig_category":"Bedrijfs- And Managementsconsultants",
    "sg:phone":"+31 578 662 222",
    "sg:postcode":"8166 HG",
    "sg:province":"Gelderland",
    "wof:name":"Bmmc Adviesbureau",
    "wof:placetype":"venue"
},
  "geometry": {"coordinates":[5.975392,52.315819],"type":"Point"}
}