{
  "type": "Feature",
  "properties": {
    "addr:full":"M Klompeln 76 Ryen Noord-Brabant 5122 BK",
    "addr:housenumber":"76",
    "addr:postcode":"5122 bk",
    "iso:country":"NL",
    "sg:address":"M Klompeln 76",
    "sg:city":"Ryen",
    "sg:orig_category":"Leesportefeuilles",
    "sg:phone":"+31 161 413 190",
    "sg:postcode":"5122 BK",
    "sg:province":"Noord-Brabant",
    "wof:name":"Dongen, M Van",
    "wof:placetype":"venue"
},
  "geometry": {"coordinates":[4.92752,51.59277],"type":"Point"}
}