{
  "type": "Feature",
  "properties": {
    "addr:full":"Soendastraat 180 Groningen Groningen 9715 SX",
    "addr:housenumber":"180",
    "addr:postcode":"9715 sx",
    "addr:street":"Soendastraat",
    "iso:country":"NL",
    "sg:address":"Soendastraat 180",
    "sg:city":"Groningen",
    "sg:orig_category":"Bejaardeninstellingen And Serviceflats",
    "sg:phone":"+31 50 577 5660",
    "sg:postcode":"9715 SX",
    "sg:province":"Groningen",
    "wof:name":"Verzorgingshuis Hamrikheem",
    "wof:placetype":"venue"
},
  "geometry": {"coordinates":[6.567372,53.236336],"type":"Point"}
}