{
  "type": "Feature",
  "properties": {
    "addr:full":"De Bolle 108 Hardegaryp Friesland 9254 JE",
    "addr:housenumber":"108",
    "addr:postcode":"9254 je",
    "addr:street":"De Bolle",
    "iso:country":"NL",
    "sg:address":"De Bolle 108",
    "sg:city":"Hardegaryp",
    "sg:orig_category":"Pianostemmen En -Reparatie",
    "sg:phone":"+31 511 472 788",
    "sg:postcode":"9254 JE",
    "sg:province":"Friesland",
    "wof:name":"Essen, J H Van",
    "wof:placetype":"venue"
},
  "geometry": {"coordinates":[5.929288,53.215206],"type":"Point"}
}