{
  "type": "Feature",
  "properties": {
    "iso:country":"NL",
    "sg:address":"De Zoeker Esch 6",
    "sg:city":"Losser",
    "sg:orig_category":"Modelmakerijen",
    "sg:phone":"+31 53 538 4448",
    "sg:postcode":"7582 CN",
    "sg:province":"Overijssel",
    "sg:website":"http://www.abboerrigter.nl",
    "wof:name":"Boerrigter, Modelmakerij A B",
    "wof:placetype":"venue"
},
  "geometry": {"coordinates":[7.007121,52.250832],"type":"Point"}
}