{
  "type": "Feature",
  "properties": {
    "addr:full":"Marinus Dammeweg 34 Venlo Limburg 5928 PW",
    "addr:housenumber":"34",
    "addr:postcode":"5928 pw",
    "addr:street":"Marinus Dammeweg",
    "iso:country":"NL",
    "sg:address":"Marinus Dammeweg 34",
    "sg:city":"Venlo",
    "sg:orig_category":"Metaalbekleding And -Behandeling",
    "sg:phone":"+31 77 387 5100",
    "sg:postcode":"5928 PW",
    "sg:province":"Limburg",
    "wof:name":"Schouren Metaal Bv",
    "wof:placetype":"venue"
},
  "geometry": {"coordinates":[6.160204,51.378448],"type":"Point"}
}