{
  "type": "Feature",
  "properties": {
    "addr:full":"Industriestr 84 Hengelo Ov NL.08 7553 CS",
    "addr:housenumber":"84",
    "addr:postcode":"7553 cs",
    "addr:street":"Industriestr;Ov",
    "iso:country":"NL",
    "sg:address":"Industriestr 84",
    "sg:city":"Hengelo Ov",
    "sg:classifiers":[
        {
            "category":"Wholesale",
            "subcategory":"Meat",
            "type":"Manufacturing & Wholesale Goods"
        }
    ],
    "sg:phone":"+31 74 242 5524",
    "sg:postcode":"7553 CS",
    "sg:province":"NL.08",
    "sg:tags":[
        "regeltechniek",
        "en",
        "meet-"
    ],
    "wof:name":"Zalm, H J Van Der",
    "wof:placetype":"venue"
},
  "geometry": {"coordinates":[6.785808,52.256214],"type":"Point"}
}