{
  "type": "Feature",
  "properties": {
    "addr:full":"Gerichtstr 22 Stein Lb Limburg 6171 TD",
    "addr:housenumber":"22",
    "addr:postcode":"lb;6171 td",
    "addr:street":"Gerichtstr",
    "iso:country":"NL",
    "sg:address":"Gerichtstr 22",
    "sg:city":"Stein Lb",
    "sg:classifiers":[
        {
            "category":"Government",
            "subcategory":"Department Of Motor Vehicles",
            "type":"Public Place"
        }
    ],
    "sg:phone":"+31 46 433 9828",
    "sg:postcode":"6171 TD",
    "sg:province":"Limburg",
    "sg:tags":[
        "rijscholen",
        "scooter",
        "en",
        "-"
    ],
    "wof:name":"Hermans, Auto- & Motorrijschool",
    "wof:placetype":"venue"
},
  "geometry": {"coordinates":[-93.129936,36.705662],"type":"Point"}
}