{
  "type": "Feature",
  "properties": {
    "iso:country":"NL",
    "sg:address":"Van 'T Hofflaan 19 Hs",
    "sg:city":"Amsterdam",
    "sg:orig_category":"Fitnesscentra",
    "sg:phone":"+31 20 693 9939",
    "sg:postcode":"1097 EL",
    "sg:province":"North Holland",
    "wof:name":"Fitness-Centrum Helisport",
    "wof:placetype":"venue"
},
  "geometry": {"coordinates":[4.936985,52.348328],"type":"Point"}
}