{
  "type": "Feature",
  "properties": {
    "iso:country":"NL",
    "sg:address":"Agaatstraat 28",
    "sg:city":"Groningen",
    "sg:orig_category":"Boekhouders",
    "sg:phone":"+31 50 577 5848",
    "sg:postcode":"9743 HW",
    "sg:province":"Groningen",
    "wof:name":"G. Douma Administraties",
    "wof:placetype":"venue"
},
  "geometry": {"coordinates":[6.523024,53.2285],"type":"Point"}
}