{
  "type": "Feature",
  "properties": {
    "addr:full":"Verversstr 4 Amsterdam Noord-Holland 1011 JA",
    "addr:housenumber":"4",
    "addr:postcode":"1011 ja",
    "addr:street":"Verversstr",
    "iso:country":"NL",
    "sg:address":"Verversstr 4",
    "sg:city":"Amsterdam",
    "sg:orig_category":"Antiquariaten",
    "sg:phone":"+31 20 620 0568",
    "sg:postcode":"1011 JA",
    "sg:province":"Noord-Holland",
    "wof:name":"Timbuctoo Ll",
    "wof:placetype":"venue"
},
  "geometry": {"coordinates":[4.899299,52.369427],"type":"Point"}
}