{
  "type": "Feature",
  "properties": {
    "addr:full":"Nieuwstr 48 Winsum Gn Groningen 9951 EJ",
    "addr:housenumber":"48",
    "addr:postcode":"gn;9951 ej",
    "addr:street":"Nieuwstr",
    "iso:country":"NL",
    "sg:address":"Nieuwstr 48",
    "sg:city":"Winsum Gn",
    "sg:orig_category":"Kappers",
    "sg:phone":"+31 595 441 562",
    "sg:postcode":"9951 EJ",
    "sg:province":"Groningen",
    "wof:name":"Time Out",
    "wof:placetype":"venue"
},
  "geometry": {"coordinates":[6.517395,53.334412],"type":"Point"}
}