{
  "type": "Feature",
  "properties": {
    "addr:full":"Postbus 141 Venlo Limburg 5900 AC",
    "addr:housenumber":"141",
    "addr:postcode":"5900 ac",
    "addr:street":"Postbus",
    "iso:country":"NL",
    "sg:address":"Postbus 141",
    "sg:city":"Venlo",
    "sg:orig_category":"Bedrijfsopleidingen",
    "sg:phone":"+31 877877688",
    "sg:postcode":"5900 AC",
    "sg:province":"Limburg",
    "sg:website":"http://www.ilec.nl",
    "wof:name":"Fontys Ilec",
    "wof:placetype":"venue"
},
  "geometry": {"coordinates":[6.17286,51.372421],"type":"Point"}
}