{
  "type": "Feature",
  "properties": {
    "iso:country":"NL",
    "sg:address":"Populierenlaan 59",
    "sg:city":"Krimpen A/D Ijssel",
    "sg:orig_category":"Paramedische Behandelingen",
    "sg:phone":"+31 180 520 798",
    "sg:postcode":"2925 CP",
    "sg:province":"Zuid-Holland",
    "wof:name":"Ing. M.R. Den Outer",
    "wof:placetype":"venue"
},
  "geometry": {"coordinates":[4.622794,51.916855],"type":"Point"}
}