{
  "type": "Feature",
  "properties": {
    "addr:full":"Tielerwg 10 Geldermalsen Gelderland 4191 NG",
    "addr:housenumber":"10",
    "addr:postcode":"4191 ng",
    "addr:street":"Tielerwg;Gelderland",
    "iso:country":"NL",
    "sg:address":"Tielerwg 10",
    "sg:city":"Geldermalsen",
    "sg:classifiers":[
        {
            "category":"Retail",
            "subcategory":"Auto Repair",
            "type":"Services"
        }
    ],
    "sg:phone":"+31 345 575 534",
    "sg:postcode":"4191 NG",
    "sg:province":"Gelderland",
    "sg:tags":[
        "garage"
    ],
    "wof:name":"Putten, Van",
    "wof:placetype":"venue"
},
  "geometry": {"coordinates":[5.302101,51.882038],"type":"Point"}
}