{
  "type": "Feature",
  "properties": {
    "addr:full":"Terborchlaan 301 Alkmaar North Holland 1816 MH",
    "addr:housenumber":"301",
    "addr:postcode":"1816 mh",
    "addr:street":"Terborchlaan",
    "iso:country":"NL",
    "sg:address":"Terborchlaan 301",
    "sg:city":"Alkmaar",
    "sg:orig_category":"Metaalbekleding And -Behandeling",
    "sg:phone":"+31 72 515 6098",
    "sg:postcode":"1816 MH",
    "sg:province":"North Holland",
    "wof:name":"Sportshop Slikker",
    "wof:placetype":"venue"
},
  "geometry": {"coordinates":[4.711854,52.633301],"type":"Point"}
}