{
  "type": "Feature",
  "properties": {
    "addr:full":"Schoolstraat 96 2250 Ae VOOR SC",
    "addr:housenumber":"96",
    "addr:postcode":"2250 ae",
    "addr:street":"Schoolstraat",
    "iso:country":"NL",
    "sg:address":"Schoolstraat 96",
    "sg:city":"2250 Ae",
    "sg:classifiers":[
        {
            "category":"Banks & Credit Unions",
            "subcategory":"Bank",
            "type":"Services"
        }
    ],
    "sg:phone":"+31 71 561 7343",
    "sg:postcode":"VOOR SC",
    "wof:name":"Ing Bank Nv",
    "wof:placetype":"venue"
},
  "geometry": {"coordinates":[-80.947441,33.624981],"type":"Point"}
}