{
  "type": "Feature",
  "properties": {
    "iso:country":"NL",
    "sg:address":"Reactorwg 49",
    "sg:city":"Utrecht",
    "sg:orig_category":"Verhuizingen",
    "sg:phone":"+31 800 0992223",
    "sg:postcode":"3542 AD",
    "sg:province":"Utrecht",
    "sg:website":"http://www.vanderlee.nl",
    "wof:name":"Lee Bv, Van Der",
    "wof:placetype":"venue"
},
  "geometry": {"coordinates":[5.061193,52.107147],"type":"Point"}
}