{
  "type": "Feature",
  "properties": {
    "addr:full":"Oude Heerweg 193 Velden Limburg 5941 EM",
    "addr:housenumber":"193",
    "addr:postcode":"5941 em",
    "addr:street":"Oude Heerweg",
    "iso:country":"NL",
    "sg:address":"Oude Heerweg 193",
    "sg:city":"Velden",
    "sg:orig_category":"Schilderwerk",
    "sg:phone":"+31 77 472 2241",
    "sg:postcode":"5941 EM",
    "sg:province":"Limburg",
    "wof:name":"Firma Gebr. Dirkx",
    "wof:placetype":"venue"
},
  "geometry": {"coordinates":[6.16585,51.421352],"type":"Point"}
}