{
  "type": "Feature",
  "properties": {
    "addr:full":"J Smit Erf 79 Dordrecht Zuid-Holland 3315 VC",
    "addr:housenumber":"79",
    "addr:postcode":"3315 vc",
    "addr:street":"Erf",
    "iso:country":"NL",
    "sg:address":"J Smit Erf 79",
    "sg:city":"Dordrecht",
    "sg:orig_category":"Onderhoudswerken",
    "sg:phone":"+31 78 630 0473",
    "sg:postcode":"3315 VC",
    "sg:province":"Zuid-Holland",
    "wof:name":"Asa Cinq, Fa",
    "wof:placetype":"venue"
},
  "geometry": {"coordinates":[4.721467,51.797729],"type":"Point"}
}