{
  "type": "Feature",
  "properties": {
    "addr:full":"Bergstraat 22 Valkenburg Lb Limburg 6301 AD",
    "addr:housenumber":"22",
    "addr:postcode":"lb;6301 ad",
    "addr:street":"Bergstraat",
    "iso:country":"NL",
    "sg:address":"Bergstraat 22",
    "sg:city":"Valkenburg Lb",
    "sg:orig_category":"Loodgieterswerk, Verwarming And Sanitaire Installaties",
    "sg:phone":"+31 43 601 4933",
    "sg:postcode":"6301 AD",
    "sg:province":"Limburg",
    "wof:name":"Loodgietersbedrijf J.J.H. Lemmens",
    "wof:placetype":"venue"
},
  "geometry": {"coordinates":[5.827953,50.845753],"type":"Point"}
}