{
  "type": "Feature",
  "properties": {
    "addr:full":"Domselaerstr 88 Amsterdam North Holland 1093 MA",
    "addr:housenumber":"88",
    "addr:postcode":"1093 ma",
    "addr:street":"Domselaerstr",
    "iso:country":"NL",
    "sg:address":"Domselaerstr 88",
    "sg:city":"Amsterdam",
    "sg:orig_category":"Psychotherapeuten",
    "sg:phone":"+31 20 463 3939",
    "sg:postcode":"1093 MA",
    "sg:province":"North Holland",
    "wof:name":"Integratieve Psychotherapie, Praktijk Voor",
    "wof:placetype":"venue"
},
  "geometry": {"coordinates":[4.927892,52.359848],"type":"Point"}
}