{
  "type": "Feature",
  "properties": {
    "iso:country":"NL",
    "sg:address":"Gebroeklaan 41",
    "sg:city":"Roermond",
    "sg:orig_category":"Kappers",
    "sg:phone":"+31 475 323 697",
    "sg:postcode":"6042 GN",
    "sg:province":"Limburg",
    "wof:name":"T.D.D. Dorenberg",
    "wof:placetype":"venue"
},
  "geometry": {"coordinates":[6.006559,51.193672],"type":"Point"}
}