{
  "type": "Feature",
  "properties": {
    "addr:full":"A V Scheltemastr 43 Voorburg Zuid-Holland 2274 VT",
    "addr:housenumber":"43",
    "addr:postcode":"2274",
    "addr:street":"A;Scheltemastr",
    "iso:country":"NL",
    "sg:address":"A V Scheltemastr 43",
    "sg:city":"Voorburg",
    "sg:orig_category":"Fotoreportages",
    "sg:phone":"+31 70 327 9588",
    "sg:postcode":"2274 VT",
    "sg:province":"Zuid-Holland",
    "wof:name":"Merlijn",
    "wof:placetype":"venue"
},
  "geometry": {"coordinates":[4.34952,52.073792],"type":"Point"}
}