{
  "type": "Feature",
  "properties": {
    "addr:full":"Rontgenwg 22 Alphen Aan Den Ryn Zuid-Holland 2408 AB",
    "addr:housenumber":"22",
    "addr:postcode":"2408 ab",
    "addr:street":"Rontgenwg;Aan Den Ryn",
    "iso:country":"NL",
    "sg:address":"Rontgenwg 22",
    "sg:city":"Alphen Aan Den Ryn",
    "sg:orig_category":"Ingenieursbureaus",
    "sg:phone":"+31 172 449 822",
    "sg:postcode":"2408 AB",
    "sg:province":"Zuid-Holland",
    "wof:name":"Geomet Bv",
    "wof:placetype":"venue"
},
  "geometry": {"coordinates":[4.633843,52.12254],"type":"Point"}
}