{
  "type": "Feature",
  "properties": {
    "addr:full":"Bindery 7R Amstelveen Noord-Holland 1185 ZH",
    "addr:housenumber":"7r",
    "addr:postcode":"1185 zh",
    "addr:street":"Bindery",
    "iso:country":"NL",
    "sg:address":"Bindery 7R",
    "sg:city":"Amstelveen",
    "sg:orig_category":"Administratie- En Boekhoudkantoren",
    "sg:phone":"+31 20 640 8513",
    "sg:postcode":"1185 ZH",
    "sg:province":"Noord-Holland",
    "wof:name":"Global Support Bv",
    "wof:placetype":"venue"
},
  "geometry": {"coordinates":[4.841634,52.288719],"type":"Point"}
}