{
  "type": "Feature",
  "properties": {
    "iso:country":"NL",
    "sg:address":"Uniastrjitte 34",
    "sg:city":"Ee",
    "sg:orig_category":"Autokeuringen",
    "sg:phone":"+31 519 518 227",
    "sg:postcode":"9131 KH",
    "sg:province":"Friesland",
    "wof:name":"Idsardi'S Autobedrijf",
    "wof:placetype":"venue"
},
  "geometry": {"coordinates":[6.101551,53.330944],"type":"Point"}
}