{
  "type": "Feature",
  "properties": {
    "addr:full":"Vlietln 55-85 Rotterdam Zuid-Holland 3061 DV",
    "addr:housenumber":"55-85",
    "addr:postcode":"rotterdam;3061 dv",
    "iso:country":"NL",
    "sg:address":"Vlietln 55-85",
    "sg:city":"Rotterdam",
    "sg:orig_category":"Verhuur",
    "sg:phone":"+31 10 288 8444",
    "sg:postcode":"3061 DV",
    "sg:province":"Zuid-Holland",
    "sg:website":"http://www.breur.nl",
    "wof:name":"Breur Verhuur Vlietlaan",
    "wof:placetype":"venue"
},
  "geometry": {"coordinates":[4.50434,51.927422],"type":"Point"}
}