{
  "type": "Feature",
  "properties": {
    "addr:full":"Oosterstr 79 Benningbroek Noord-Holland 1654 JN",
    "addr:housenumber":"79",
    "addr:postcode":"1654 jn",
    "addr:street":"Oosterstr",
    "iso:country":"NL",
    "sg:address":"Oosterstr 79",
    "sg:city":"Benningbroek",
    "sg:orig_category":"Vakantieverblijven",
    "sg:phone":"+31 229 591 297",
    "sg:postcode":"1654 JN",
    "sg:province":"Noord-Holland",
    "wof:name":"Hebu",
    "wof:placetype":"venue"
},
  "geometry": {"coordinates":[5.05427,52.70499],"type":"Point"}
}