{
  "type": "Feature",
  "properties": {
    "addr:full":"Brongouw 57 De Gouwen Almere NL. 1352 EG",
    "addr:housenumber":"57",
    "addr:postcode":"1352 eg",
    "addr:street":"Brongouw;Nl.",
    "iso:country":"NL",
    "sg:address":"Brongouw 57 De Gouwen",
    "sg:city":"Almere",
    "sg:orig_category":"Verenigingen En Stichtingen",
    "sg:phone":"+31 36 531 6147",
    "sg:postcode":"1352 EG",
    "sg:province":"NL.",
    "wof:name":"Gouwen, De",
    "wof:placetype":"venue"
},
  "geometry": {"coordinates":[5.2134,52.3442],"type":"Point"}
}