{
  "type": "Feature",
  "properties": {
    "addr:full":"Pr Bernhardwg 12A Oosterbeek Gelderland 6862 ZG",
    "addr:housenumber":"12a",
    "addr:postcode":"6862 zg",
    "addr:street":"Gelderland",
    "iso:country":"NL",
    "sg:address":"Pr Bernhardwg 12A",
    "sg:city":"Oosterbeek",
    "sg:orig_category":"Adviesbureaus Bedrijfsorganisatie",
    "sg:phone":"+31 26 339 0340",
    "sg:postcode":"6862 ZG",
    "sg:province":"Gelderland",
    "wof:name":"Ksmc",
    "wof:placetype":"venue"
},
  "geometry": {"coordinates":[5.857715,51.982143],"type":"Point"}
}