{
  "type": "Feature",
  "properties": {
    "addr:full":"C Geelln 43 Alphen Aan Den Ryn Zuid-Holland 2406 JE",
    "addr:housenumber":"43",
    "addr:postcode":"2406 je",
    "addr:street":"Aan Den Ryn",
    "iso:country":"NL",
    "sg:address":"C Geelln 43",
    "sg:city":"Alphen Aan Den Ryn",
    "sg:orig_category":"Adviesbureaus Bedrijfsorganisatie",
    "sg:phone":"+31 172 471 774",
    "sg:postcode":"2406 JE",
    "sg:province":"Zuid-Holland",
    "wof:name":"Quadri Dynamic",
    "wof:placetype":"venue"
},
  "geometry": {"coordinates":[4.67368,52.12981],"type":"Point"}
}