{
  "type": "Feature",
  "properties": {
    "addr:full":"Bovenstrwg 8 Oldebroek Gelderland 8096 PE",
    "addr:housenumber":"8",
    "addr:postcode":"8096 pe",
    "addr:street":"Bovenstrwg;Gelderland",
    "iso:country":"NL",
    "sg:address":"Bovenstrwg 8",
    "sg:city":"Oldebroek",
    "sg:orig_category":"Beeldende Kunstenaars",
    "sg:phone":"+31 525 631 212",
    "sg:postcode":"8096 PE",
    "sg:province":"Gelderland",
    "wof:name":"Irma Frijlink",
    "wof:placetype":"venue"
},
  "geometry": {"coordinates":[5.8934,52.445419],"type":"Point"}
}