{
  "type": "Feature",
  "properties": {
    "addr:full":"Wezerdreef 3 Utrecht Utrecht 3562 BC",
    "addr:housenumber":"3",
    "addr:postcode":"3562 bc",
    "addr:street":"Wezerdreef",
    "iso:country":"NL",
    "sg:address":"Wezerdreef 3",
    "sg:city":"Utrecht",
    "sg:classifiers":[
        {
            "category":"Education",
            "subcategory":"Preschool",
            "type":"Public Place"
        }
    ],
    "sg:phone":"+31 30 262 1586",
    "sg:postcode":"3562 BC",
    "sg:province":"Utrecht",
    "sg:tags":[
        "kleuteronderwijs",
        "basis-"
    ],
    "wof:name":"Openb Jenaplanschool Overvecht Locatie Wezerdreef",
    "wof:placetype":"venue"
},
  "geometry": {"coordinates":[5.124471,52.11692],"type":"Point"}
}