{
  "type": "Feature",
  "properties": {
    "addr:full":"Nijewei 25 Boornbergum Provincie Friesland 9212 PB",
    "addr:housenumber":"25",
    "addr:postcode":"9212 pb",
    "addr:street":"Nijewei;Provincie Friesland",
    "iso:country":"NL",
    "sg:address":"Nijewei 25",
    "sg:city":"Boornbergum",
    "sg:orig_category":"Kappers",
    "sg:phone":"+31 512 381 363",
    "sg:postcode":"9212 PB",
    "sg:province":"Provincie Friesland",
    "wof:name":"Haarstijl F",
    "wof:placetype":"venue"
},
  "geometry": {"coordinates":[6.0443840027,53.0851135254],"type":"Point"}
}