{
  "type": "Feature",
  "properties": {
    "iso:country":"NL",
    "sg:address":"Kromme Mijdrecht 30",
    "sg:city":"De Hoef",
    "sg:orig_category":"Pleziervaartuigen And Reparatie",
    "sg:phone":"+31 297 562 372",
    "sg:postcode":"1426 AB",
    "sg:province":"Utrecht",
    "wof:name":"Jachtwerf-En Onderhoudswerkplaats De Jon",
    "wof:placetype":"venue"
},
  "geometry": {"coordinates":[4.817724,52.226158],"type":"Point"}
}