{
  "type": "Feature",
  "properties": {
    "addr:full":"Benedenrywg 559 Rotterdam Zuid-Holland 3077 CJ",
    "addr:housenumber":"559",
    "addr:postcode":"3077 cj",
    "iso:country":"NL",
    "sg:address":"Benedenrywg 559",
    "sg:city":"Rotterdam",
    "sg:orig_category":"Adviesbureaus",
    "sg:phone":"+31 10 292 7864",
    "sg:postcode":"3077 CJ",
    "sg:province":"Zuid-Holland",
    "wof:name":"S'Jacob Bv",
    "wof:placetype":"venue"
},
  "geometry": {"coordinates":[4.555718,51.900978],"type":"Point"}
}