{
  "type": "Feature",
  "properties": {
    "iso:country":"NL",
    "sg:address":"Stationsstr 36",
    "sg:city":"Waddinxveen",
    "sg:classifiers":[
        {
            "category":"Education",
            "subcategory":"Special Training",
            "type":"Public Place"
        }
    ],
    "sg:phone":"+31 182 618 555",
    "sg:postcode":"2741 HS",
    "sg:province":"Zuid-Holland",
    "sg:tags":[
        "expertise"
    ],
    "wof:name":"Schuur & Zn Bv, A",
    "wof:placetype":"venue"
},
  "geometry": {"coordinates":[4.653556,52.04406],"type":"Point"}
}