{
  "type": "Feature",
  "properties": {
    "addr:full":"Amelinkhorst 44 Enschede Overijssel 7531 GP",
    "addr:housenumber":"44",
    "addr:postcode":"7531 gp",
    "addr:street":"Amelinkhorst",
    "iso:country":"NL",
    "sg:address":"Amelinkhorst 44",
    "sg:city":"Enschede",
    "sg:classifiers":[
        {
            "category":"Personal",
            "subcategory":"Nail Salon",
            "type":"Services"
        }
    ],
    "sg:phone":"+31 53 435 5304",
    "sg:postcode":"7531 GP",
    "sg:province":"Overijssel",
    "sg:tags":[
        "pedicure"
    ],
    "wof:name":"Wolff-De Koning, C M De",
    "wof:placetype":"venue"
},
  "geometry": {"coordinates":[6.92298,52.226921],"type":"Point"}
}