{
  "type": "Feature",
  "properties": {
    "addr:full":"Bergse Dorpsstraat 128 Rotterdam South Holland 3054 GG",
    "addr:housenumber":"128",
    "addr:postcode":"3054 gg",
    "addr:street":"Bergse Dorpsstraat",
    "iso:country":"NL",
    "sg:address":"Bergse Dorpsstraat 128",
    "sg:city":"Rotterdam",
    "sg:classifiers":[
        {
            "category":"Food & Beverages",
            "subcategory":"Fruits & Vegetables",
            "type":"Retail Goods"
        }
    ],
    "sg:phone":"+31 10 461 4408",
    "sg:postcode":"3054 GG",
    "sg:province":"South Holland",
    "sg:tags":[
        "groenten"
    ],
    "wof:name":"Fa De Winter & Zoon",
    "wof:placetype":"venue"
},
  "geometry": {"coordinates":[4.494343,51.958134],"type":"Point"}
}