{
  "type": "Feature",
  "properties": {
    "addr:full":"Molenberg 7 Broekhuizen Lb Limburg 5872 AJ",
    "addr:housenumber":"7",
    "addr:postcode":"lb;5872 aj",
    "addr:street":"Molenberg",
    "iso:country":"NL",
    "sg:address":"Molenberg 7",
    "sg:city":"Broekhuizen Lb",
    "sg:orig_category":"Binnenhuisarchitecten",
    "sg:phone":"+31 77 463 8203",
    "sg:postcode":"5872 AJ",
    "sg:province":"Limburg",
    "wof:name":"M Baijens",
    "wof:placetype":"venue"
},
  "geometry": {"coordinates":[-93.129936,36.705662],"type":"Point"}
}