{
  "type": "Feature",
  "properties": {
    "iso:country":"NL",
    "sg:address":"Bredestraat 9",
    "sg:city":"Meteren",
    "sg:orig_category":"Wegen And Sportterreinen",
    "sg:phone":"+31 345 569 363",
    "sg:postcode":"4194 TR",
    "sg:province":"Gelderland",
    "wof:name":"Gebr Van Doorn",
    "wof:placetype":"venue"
},
  "geometry": {"coordinates":[5.2743630409,51.8702583313],"type":"Point"}
}