{
  "type": "Feature",
  "properties": {
    "iso:country":"NL",
    "sg:address":"Prinsenln 11",
    "sg:city":"Woerden",
    "sg:orig_category":"Oldtimers",
    "sg:phone":"+31 348 411 215",
    "sg:postcode":"3442 CA",
    "sg:province":"Utrecht",
    "wof:name":"Norvoparts",
    "wof:placetype":"venue"
},
  "geometry": {"coordinates":[4.887371,52.085117],"type":"Point"}
}