{
  "type": "Feature",
  "properties": {
    "addr:full":"Apeldoornselaan 282 'S Gravenhage South Holland 2573 LX",
    "addr:housenumber":"282 '",
    "addr:postcode":"2573 lx",
    "addr:street":"Apeldoornselaan",
    "iso:country":"NL",
    "sg:address":"Apeldoornselaan 282",
    "sg:city":"'S Gravenhage",
    "sg:classifiers":[
        {
            "category":"Shopping",
            "subcategory":"Clothing, Apparel, & Fashions",
            "type":"Retail Goods"
        }
    ],
    "sg:phone":"+31 70 345 5937",
    "sg:postcode":"2573 LX",
    "sg:province":"South Holland",
    "sg:tags":[
        "ondergoed",
        "lingerie"
    ],
    "wof:name":"Livera Laarhoven",
    "wof:placetype":"venue"
},
  "geometry": {"coordinates":[4.281266,52.065941],"type":"Point"}
}