{
  "type": "Feature",
  "properties": {
    "addr:full":"Hyacinthenln 30 Geleen Limburg 6163 BK",
    "addr:housenumber":"30",
    "addr:postcode":"6163 bk",
    "addr:street":"Hyacinthenln",
    "iso:country":"NL",
    "sg:address":"Hyacinthenln 30",
    "sg:city":"Geleen",
    "sg:orig_category":"Lasbedrijven",
    "sg:phone":"+31 46 475 3239",
    "sg:postcode":"6163 BK",
    "sg:province":"Limburg",
    "wof:name":"Mitterbacher",
    "wof:placetype":"venue"
},
  "geometry": {"coordinates":[5.817662,50.98489],"type":"Point"}
}