{
  "type": "Feature",
  "properties": {
    "addr:full":"Bastendorfwg 1 Eindhoven Noord-Brabant 5625 LE",
    "addr:housenumber":"1",
    "addr:postcode":"5625 le",
    "addr:street":"Bastendorfwg",
    "iso:country":"NL",
    "sg:address":"Bastendorfwg 1",
    "sg:city":"Eindhoven",
    "sg:orig_category":"Adviesbureaus Bedrijfsorganisatie",
    "sg:phone":"+31 40 241 0348",
    "sg:postcode":"5625 LE",
    "sg:province":"Noord-Brabant",
    "wof:name":"Krooshof",
    "wof:placetype":"venue"
},
  "geometry": {"coordinates":[5.473054,51.471848],"type":"Point"}
}