{
  "type": "Feature",
  "properties": {
    "iso:country":"NL",
    "sg:address":"Nobelstr 56",
    "sg:city":"Brielle",
    "sg:orig_category":"Binnenhuisarchitectuur",
    "sg:phone":"+31 181 472 727",
    "sg:postcode":"3231 BD",
    "sg:province":"South Holland",
    "wof:name":"Ganzenveer, De",
    "wof:placetype":"venue"
},
  "geometry": {"coordinates":[4.163124,51.900681],"type":"Point"}
}