{
  "type": "Feature",
  "properties": {
    "addr:full":"Borgstee 27B Assen Provincie Drenthe 9403 TS",
    "addr:housenumber":"27b",
    "addr:postcode":"9403 ts",
    "addr:street":"Borgstee;Provincie Drenthe",
    "iso:country":"NL",
    "sg:address":"Borgstee 27B",
    "sg:city":"Assen",
    "sg:orig_category":"Verkoopautomaten",
    "sg:phone":"+31 592 347 170",
    "sg:postcode":"9403 TS",
    "sg:province":"Provincie Drenthe",
    "wof:name":"Beek, G Van De",
    "wof:placetype":"venue"
},
  "geometry": {"coordinates":[6.571526,53.013512],"type":"Point"}
}