{
  "type": "Feature",
  "properties": {
    "iso:country":"NL",
    "sg:address":"Roozenburgln 18",
    "sg:city":"Middelburg",
    "sg:orig_category":"Apotheken",
    "sg:phone":"+31 118 627 471",
    "sg:postcode":"4337 JH",
    "sg:province":"Zeeland",
    "wof:name":"Dauwendaele",
    "wof:placetype":"venue"
},
  "geometry": {"coordinates":[3.623496,51.492966],"type":"Point"}
}