{
  "type": "Feature",
  "properties": {
    "addr:full":"Spoorstr 8 Oldenzaal Overijssel 7572 CZ",
    "addr:housenumber":"8",
    "addr:postcode":"7572",
    "addr:street":"Spoorstr",
    "iso:country":"NL",
    "sg:address":"Spoorstr 8",
    "sg:city":"Oldenzaal",
    "sg:orig_category":"Zonnebank- En Solariumcentra",
    "sg:phone":"+31 541 520 222",
    "sg:postcode":"7572 CZ",
    "sg:province":"Overijssel",
    "wof:name":"Zonnestudio Parfum En Nagelstudio",
    "wof:placetype":"venue"
},
  "geometry": {"coordinates":[6.92815,52.30798],"type":"Point"}
}