{
  "type": "Feature",
  "properties": {
    "addr:full":"Zijlstraat 62 Haarlem North Holland 2011 TP",
    "addr:housenumber":"62",
    "addr:postcode":"2011 tp",
    "addr:street":"Zijlstraat",
    "iso:country":"NL",
    "sg:address":"Zijlstraat 62",
    "sg:city":"Haarlem",
    "sg:orig_category":"Meubelzaken, Woning- And Keukeninrichting",
    "sg:phone":"+31 23 531 0413",
    "sg:postcode":"2011 TP",
    "sg:province":"North Holland",
    "wof:name":"Imago Mundi",
    "wof:placetype":"venue"
},
  "geometry": {"coordinates":[4.632703,52.382198],"type":"Point"}
}