{
  "type": "Feature",
  "properties": {
    "addr:full":"Hoppenkuil 31 Eindhoven Noord-Brabant 5626 DD",
    "addr:housenumber":"31",
    "addr:postcode":"5626 dd",
    "addr:street":"Hoppenkuil",
    "iso:country":"NL",
    "sg:address":"Hoppenkuil 31",
    "sg:city":"Eindhoven",
    "sg:orig_category":"Schilders",
    "sg:phone":"+31 40 262 0660",
    "sg:postcode":"5626 DD",
    "sg:province":"Noord-Brabant",
    "wof:name":"Esdonk Bv, Rinus Van",
    "wof:placetype":"venue"
},
  "geometry": {"coordinates":[5.420871,51.479847],"type":"Point"}
}