{
  "type": "Feature",
  "properties": {
    "addr:full":"Kl Marktstr 2 Assen Provincie Drenthe 9401 JD",
    "addr:housenumber":"2",
    "addr:postcode":"9401 jd",
    "addr:street":"Provincie Drenthe",
    "iso:country":"NL",
    "sg:address":"Kl Marktstr 2",
    "sg:city":"Assen",
    "sg:orig_category":"Kinderkleding",
    "sg:phone":"+31 592 316 376",
    "sg:postcode":"9401 JD",
    "sg:province":"Provincie Drenthe",
    "sg:website":"http://www.hocus-pocus.nl",
    "wof:name":"Hokus Pokus",
    "wof:placetype":"venue"
},
  "geometry": {"coordinates":[6.562502,52.994167],"type":"Point"}
}