{
  "type": "Feature",
  "properties": {
    "addr:full":"Muntstraat 17 Maastricht Limburg 6211 EG",
    "addr:housenumber":"17",
    "addr:postcode":"6211 eg",
    "addr:street":"Muntstraat",
    "iso:country":"NL",
    "sg:address":"Muntstraat 17",
    "sg:city":"Maastricht",
    "sg:orig_category":"Boekhandels",
    "sg:phone":"+31 43 321 1410",
    "sg:postcode":"6211 EG",
    "sg:province":"Limburg",
    "wof:name":"Palero",
    "wof:placetype":"venue"
},
  "geometry": {"coordinates":[5.692434,50.850643],"type":"Point"}
}