{
  "type": "Feature",
  "properties": {
    "addr:full":"Lage Wipstraat 69 Zevenbergen Noord-Brabant 4761 EB",
    "addr:housenumber":"69",
    "addr:postcode":"4761 eb",
    "addr:street":"Lage Wipstraat",
    "iso:country":"NL",
    "sg:address":"Lage Wipstraat 69",
    "sg:city":"Zevenbergen",
    "sg:orig_category":"Geluidsopnamen",
    "sg:phone":"+31 168 327 522",
    "sg:postcode":"4761 EB",
    "sg:province":"Noord-Brabant",
    "wof:name":"Roel Jongenelen",
    "wof:placetype":"venue"
},
  "geometry": {"coordinates":[4.603833,51.645817],"type":"Point"}
}