{
  "type": "Feature",
  "properties": {
    "iso:country":"NL",
    "sg:address":"Ermontstr 12",
    "sg:city":"Wierden",
    "sg:orig_category":"Plasticverwerking - Apparaten En Benodigdheden",
    "sg:phone":"+31 546 577 713",
    "sg:postcode":"7641 DT",
    "sg:province":"Overijssel",
    "wof:name":"Mas Int Bv",
    "wof:placetype":"venue"
},
  "geometry": {"coordinates":[6.60411,52.365009],"type":"Point"}
}