{
  "type": "Feature",
  "properties": {
    "addr:full":"Klaas Keurisstraat 32 Anna Paulowna Noord-Holland 1761 CL",
    "addr:housenumber":"32",
    "addr:postcode":"1761",
    "addr:street":"Klaas Keurisstraat",
    "iso:country":"NL",
    "sg:address":"Klaas Keurisstraat 32",
    "sg:city":"Anna Paulowna",
    "sg:orig_category":"Bruidskleding",
    "sg:phone":"+31 223 533 935",
    "sg:postcode":"1761 CL",
    "sg:province":"Noord-Holland",
    "wof:name":"Ans Bruidsmode",
    "wof:placetype":"venue"
},
  "geometry": {"coordinates":[4.827244,52.861588],"type":"Point"}
}