{
  "type": "Feature",
  "properties": {
    "addr:full":"Htg Reinoudsngl 141 Venlo Limburg 5913 XC",
    "addr:housenumber":"141",
    "addr:postcode":"5913 xc",
    "iso:country":"NL",
    "sg:address":"Htg Reinoudsngl 141",
    "sg:city":"Venlo",
    "sg:orig_category":"Elektronica - Ontwikkeling En Groothandel",
    "sg:phone":"+31 77 306 0130",
    "sg:postcode":"5913 XC",
    "sg:province":"Limburg",
    "wof:name":"Cb Tronics",
    "wof:placetype":"venue"
},
  "geometry": {"coordinates":[6.17286,51.372421],"type":"Point"}
}