{
  "type": "Feature",
  "properties": {
    "addr:full":"Wundtln 1 Nymegen Gelderland 6525 XD",
    "addr:housenumber":"1",
    "addr:postcode":"6525 xd",
    "addr:street":"Wundtln;Gelderland",
    "iso:country":"NL",
    "sg:address":"Wundtln 1",
    "sg:city":"Nymegen",
    "sg:orig_category":"Onderzoekbureaus",
    "sg:phone":"+31 24 352 1911",
    "sg:postcode":"6525 XD",
    "sg:province":"Gelderland",
    "sg:website":"http://www.mpi.nl",
    "wof:name":"Max Planck Inst",
    "wof:placetype":"venue"
},
  "geometry": {"coordinates":[5.83296,51.842651],"type":"Point"}
}