{
  "type": "Feature",
  "properties": {
    "addr:full":"Laagstr 89 Ryen Noord-Brabant 5121 ZE",
    "addr:housenumber":"89",
    "addr:postcode":"5121 ze",
    "addr:street":"Laagstr",
    "iso:country":"NL",
    "sg:address":"Laagstr 89",
    "sg:city":"Ryen",
    "sg:orig_category":"Kappers",
    "sg:phone":"+31 6 21894255",
    "sg:postcode":"5121 ZE",
    "sg:province":"Noord-Brabant",
    "wof:name":"Ankies Haarmobiel",
    "wof:placetype":"venue"
},
  "geometry": {"coordinates":[4.9197001457,51.58801651],"type":"Point"}
}