{
  "type": "Feature",
  "properties": {
    "addr:full":"Ged Hamerkan 35 Amsterdam Noord-Holland 1021 KL",
    "addr:housenumber":"35",
    "addr:postcode":"1021 kl",
    "iso:country":"NL",
    "sg:address":"Ged Hamerkan 35",
    "sg:city":"Amsterdam",
    "sg:orig_category":"Mode Artikelen Dames En Heren - Fabrieken En Groothandel",
    "sg:phone":"+31 20 494 2515",
    "sg:postcode":"1021 KL",
    "sg:province":"Noord-Holland",
    "wof:name":"C Ferilli Bv",
    "wof:placetype":"venue"
},
  "geometry": {"coordinates":[4.925845,52.38501],"type":"Point"}
}