{
  "type": "Feature",
  "properties": {
    "addr:full":"Laarstr 5 Zutphen Gelderland 7201 CA",
    "addr:housenumber":"5",
    "addr:postcode":"7201 ca",
    "addr:street":"Laarstr;Gelderland",
    "iso:country":"NL",
    "sg:address":"Laarstr 5",
    "sg:city":"Zutphen",
    "sg:orig_category":"Kaarsen - Fabrieken En Groothandel",
    "sg:phone":"+31 575 543 849",
    "sg:postcode":"7201 CA",
    "sg:province":"Gelderland",
    "sg:website":"HTTP://www.honestproducts.nl",
    "wof:name":"Honest Products",
    "wof:placetype":"venue"
},
  "geometry": {"coordinates":[6.1996889114,52.1411132812],"type":"Point"}
}