{
  "type": "Feature",
  "properties": {
    "addr:full":"Oosterstraat 49 Groningen Groningen 9711 NR",
    "addr:housenumber":"49",
    "addr:postcode":"9711 nr",
    "addr:street":"Oosterstraat",
    "iso:country":"NL",
    "sg:address":"Oosterstraat 49",
    "sg:city":"Groningen",
    "sg:orig_category":"Juweliers",
    "sg:phone":"+31 50 312 3138",
    "sg:postcode":"9711 NR",
    "sg:province":"Groningen",
    "wof:name":"H W Scheich",
    "wof:placetype":"venue"
},
  "geometry": {"coordinates":[6.569908,53.216766],"type":"Point"}
}