{
  "type": "Feature",
  "properties": {
    "addr:full":"Beekstr 14 Nuenen Noord-Brabant 5671 CT",
    "addr:housenumber":"14",
    "addr:postcode":"5671 ct",
    "addr:street":"Beekstr",
    "iso:country":"NL",
    "sg:address":"Beekstr 14",
    "sg:city":"Nuenen",
    "sg:classifiers":[
        {
            "category":"Professional",
            "subcategory":"Management & Consulting",
            "type":"Services"
        }
    ],
    "sg:phone":"+31 40 283 9015",
    "sg:postcode":"5671 CT",
    "sg:province":"Noord-Brabant",
    "sg:tags":[
        "relation",
        "adviesbureaus",
        "public"
    ],
    "wof:name":"Bitter End, The",
    "wof:placetype":"venue"
},
  "geometry": {"coordinates":[5.553464,51.476894],"type":"Point"}
}