{
  "type": "Feature",
  "properties": {
    "iso:country":"NL",
    "sg:address":"Bulkensteinlaan 63",
    "sg:city":"Tiel",
    "sg:orig_category":"Public Relationbureaus",
    "sg:phone":"+31 344 631 790",
    "sg:postcode":"4003 TM",
    "sg:province":"Gelderland",
    "wof:name":"Aimable",
    "wof:placetype":"venue"
},
  "geometry": {"coordinates":[5.410385,51.893494],"type":"Point"}
}