{
  "type": "Feature",
  "properties": {
    "addr:full":"Aalsmeerderwg 312 Aalsmeer Noord-Holland 1432 CZ",
    "addr:housenumber":"312",
    "addr:postcode":"aalsmeer;1432",
    "iso:country":"NL",
    "sg:address":"Aalsmeerderwg 312",
    "sg:city":"Aalsmeer",
    "sg:orig_category":"Babyartikelen",
    "sg:phone":"+31 297 328 382",
    "sg:postcode":"1432 CZ",
    "sg:province":"Noord-Holland",
    "sg:website":"http://www.frutsel.nl",
    "wof:name":"Frutsel, Atelier",
    "wof:placetype":"venue"
},
  "geometry": {"coordinates":[4.802055,52.281952],"type":"Point"}
}