{
  "type": "Feature",
  "properties": {
    "addr:full":"Dorpshuisstr 2 Wanneperveen NL.08 7946 AP",
    "addr:housenumber":"2;nl.08",
    "addr:postcode":"7946 ap",
    "addr:street":"Dorpshuisstr",
    "iso:country":"NL",
    "sg:address":"Dorpshuisstr 2",
    "sg:city":"Wanneperveen",
    "sg:orig_category":"Zalenverhuur",
    "sg:phone":"+31 522 281 229",
    "sg:postcode":"7946 AP",
    "sg:province":"NL.08",
    "wof:name":"Wanne, De",
    "wof:placetype":"venue"
},
  "geometry": {"coordinates":[6.121038,52.703625],"type":"Point"}
}