{
  "type": "Feature",
  "properties": {
    "addr:full":"Bitgumerdk 30B Berlikum Fr Friesland 9041 CE",
    "addr:housenumber":"30b",
    "addr:postcode":"9041 ce",
    "addr:street":"Bitgumerdk",
    "iso:country":"NL",
    "sg:address":"Bitgumerdk 30B",
    "sg:city":"Berlikum Fr",
    "sg:orig_category":"Loodgieters",
    "sg:phone":"+31 518 461 206",
    "sg:postcode":"9041 CE",
    "sg:province":"Friesland",
    "sg:website":"http://www.bijlstra-installaties.nl",
    "wof:name":"Bijlstra Installaties",
    "wof:placetype":"venue"
},
  "geometry": {"coordinates":[5.66301,53.241581],"type":"Point"}
}