{
  "type": "Feature",
  "properties": {
    "addr:full":"J De Kruyfstr 13 Bunnik Utrecht 3981 DA",
    "addr:housenumber":"13",
    "addr:postcode":"3981 da",
    "addr:street":"J De Kruyfstr",
    "iso:country":"NL",
    "sg:address":"J De Kruyfstr 13",
    "sg:city":"Bunnik",
    "sg:orig_category":"Schilders",
    "sg:phone":"+31 30 656 4050",
    "sg:postcode":"3981 DA",
    "sg:province":"Utrecht",
    "wof:name":"Fokker",
    "wof:placetype":"venue"
},
  "geometry": {"coordinates":[5.19958,52.067097],"type":"Point"}
}