{
  "type": "Feature",
  "properties": {
    "addr:full":"Trompstraat 318 'S Gravenhage Zuid-Holland 2518 BS",
    "addr:housenumber":"318 ';2518",
    "addr:postcode":"bs",
    "addr:street":"Trompstraat",
    "iso:country":"NL",
    "sg:address":"Trompstraat 318",
    "sg:city":"'S Gravenhage",
    "sg:orig_category":"Werving And Selectie Van Vast Personeel",
    "sg:phone":"+31 70 311 0511",
    "sg:postcode":"2518 BS",
    "sg:province":"Zuid-Holland",
    "wof:name":"United Capacity Den Haag Bv",
    "wof:placetype":"venue"
},
  "geometry": {"coordinates":[4.2982559204,52.0846672058],"type":"Point"}
}