{
  "type": "Feature",
  "properties": {
    "addr:full":"Mosselseweg 3 Vorden Gelderland 7251 KT",
    "addr:housenumber":"3",
    "addr:postcode":"7251 kt",
    "addr:street":"Mosselseweg;Gelderland",
    "iso:country":"NL",
    "sg:address":"Mosselseweg 3",
    "sg:city":"Vorden",
    "sg:orig_category":"Kampeerterreinen",
    "sg:phone":"+31 575 556 743",
    "sg:postcode":"7251 KT",
    "sg:province":"Gelderland",
    "wof:name":"Prinsenhoeve Svr",
    "wof:placetype":"venue"
},
  "geometry": {"coordinates":[6.3616890907,52.1111946106],"type":"Point"}
}