{
  "type": "Feature",
  "properties": {
    "addr:full":"Bronsteewg 34 Heemstede North Holland 2101 AD",
    "addr:housenumber":"34",
    "addr:postcode":"2101 ad",
    "addr:street":"Bronsteewg",
    "iso:country":"NL",
    "sg:address":"Bronsteewg 34",
    "sg:city":"Heemstede",
    "sg:orig_category":"Artsen - Huisartsen",
    "sg:phone":"+31 23 528 0713",
    "sg:postcode":"2101 AD",
    "sg:province":"North Holland",
    "wof:name":"Doets, J F",
    "wof:placetype":"venue"
},
  "geometry": {"coordinates":[4.623375,52.358173],"type":"Point"}
}