{
  "type": "Feature",
  "properties": {
    "addr:full":"Elektronicaweg 40 Delft South Holland 2628 XG",
    "addr:housenumber":"40",
    "addr:postcode":"2628 xg",
    "addr:street":"Elektronicaweg",
    "iso:country":"NL",
    "sg:address":"Elektronicaweg 40",
    "sg:city":"Delft",
    "sg:orig_category":"Marktonderzoekbureaus",
    "sg:phone":"+31 15 275 4321",
    "sg:postcode":"2628 XG",
    "sg:province":"South Holland",
    "wof:name":"Essensor",
    "wof:placetype":"venue"
},
  "geometry": {"coordinates":[4.385608,51.99683],"type":"Point"}
}