{
  "type": "Feature",
  "properties": {
    "addr:full":"Looydijk 76 De Bilt Utrecht 3732 VG",
    "addr:housenumber":"76",
    "addr:postcode":"3732 vg",
    "addr:street":"Looydijk",
    "iso:country":"NL",
    "sg:address":"Looydijk 76",
    "sg:city":"De Bilt",
    "sg:classifiers":[
        {
            "category":"Fast Food",
            "type":"Food & Drink"
        }
    ],
    "sg:phone":"+31 30 220 5170",
    "sg:postcode":"3732 VG",
    "sg:province":"Utrecht",
    "sg:tags":[
        "afhaal",
        "restaurant"
    ],
    "wof:name":"Foodmaster",
    "wof:placetype":"venue"
},
  "geometry": {"coordinates":[5.183869,52.108593],"type":"Point"}
}