{
  "type": "Feature",
  "properties": {
    "addr:full":"Schoolstraat 17 Hellevoetsluis Zuid-Holland 3224 AM",
    "addr:housenumber":"17",
    "addr:postcode":"3224",
    "addr:street":"Schoolstraat",
    "iso:country":"NL",
    "sg:address":"Schoolstraat 17",
    "sg:city":"Hellevoetsluis",
    "sg:orig_category":"Metaalwerken",
    "sg:phone":"+31 181 327 537",
    "sg:postcode":"3224 AM",
    "sg:province":"Zuid-Holland",
    "wof:name":"Huco",
    "wof:placetype":"venue"
},
  "geometry": {"coordinates":[4.153503,51.834339],"type":"Point"}
}