{
  "type": "Feature",
  "properties": {
    "addr:full":"Slaak 120 Rotterdam Zuid-Holland 3061 CZ",
    "addr:housenumber":"120",
    "addr:postcode":"3061",
    "addr:street":"Slaak",
    "iso:country":"NL",
    "sg:address":"Slaak 120",
    "sg:city":"Rotterdam",
    "sg:orig_category":"Opticiens",
    "sg:phone":"+31 10 411 2344",
    "sg:postcode":"3061 CZ",
    "sg:province":"Zuid-Holland",
    "wof:name":"Groeneveld Brillen Bv",
    "wof:placetype":"venue"
},
  "geometry": {"coordinates":[4.4983510971,51.9239234924],"type":"Point"}
}