{
  "type": "Feature",
  "properties": {
    "addr:full":"Graafseweg 13 Mill Pennsylvania 5451 VT",
    "addr:housenumber":"13",
    "addr:postcode":"5451",
    "addr:street":"Graafseweg",
    "iso:country":"NL",
    "sg:address":"Graafseweg 13",
    "sg:city":"Mill",
    "sg:orig_category":"Hoger Onderwijs",
    "sg:phone":"+31 485 451 927",
    "sg:postcode":"5451 VT",
    "sg:province":"Pennsylvania",
    "wof:name":"Modevakschool Van Rossum",
    "wof:placetype":"venue"
},
  "geometry": {"coordinates":[-77.762939,41.90403],"type":"Point"}
}