{
  "type": "Feature",
  "properties": {
    "addr:full":"Neptunuslaan 62 Krommenie North Holland 1562 XM",
    "addr:housenumber":"62",
    "addr:postcode":"1562 xm",
    "addr:street":"Neptunuslaan",
    "iso:country":"NL",
    "sg:address":"Neptunuslaan 62",
    "sg:city":"Krommenie",
    "sg:orig_category":"Loodgieterswerk, Verwarming And Sanitaire Installaties",
    "sg:phone":"+31 75 771 3641",
    "sg:postcode":"1562 XM",
    "sg:province":"North Holland",
    "wof:name":"Totaaltechniek Marcel",
    "wof:placetype":"venue"
},
  "geometry": {"coordinates":[4.748762,52.499733],"type":"Point"}
}