{
  "type": "Feature",
  "properties": {
    "iso:country":"NL",
    "sg:address":"Zutphenseweg 192",
    "sg:city":"Eefde",
    "sg:orig_category":"Begrafenisondernemers",
    "sg:phone":"+31 575 540 990",
    "sg:postcode":"7211 EK",
    "sg:province":"Gelderland",
    "wof:name":"Coop. Uitvaartvereniging De Laatste Eer Ua",
    "wof:placetype":"venue"
},
  "geometry": {"coordinates":[6.22578,52.16814],"type":"Point"}
}