{
  "type": "Feature",
  "properties": {
    "addr:full":"Groenhof 106 Amstelveen Noord-Holland 1186 EW",
    "addr:housenumber":"106",
    "addr:postcode":"1186 ew",
    "addr:street":"Groenhof",
    "iso:country":"NL",
    "sg:address":"Groenhof 106",
    "sg:city":"Amstelveen",
    "sg:orig_category":"Grafisch Ontwerpers",
    "sg:phone":"+31 20 453 6686",
    "sg:postcode":"1186 EW",
    "sg:province":"Noord-Holland",
    "sg:website":"http://www.gabrielledevries.nl",
    "wof:name":"Vries, Gabri?lle De",
    "wof:placetype":"venue"
},
  "geometry": {"coordinates":[4.869981,52.289516],"type":"Point"}
}