{
  "type": "Feature",
  "properties": {
    "addr:full":"Echtenstein 100-U Amsterdam Zuidoost North Holland 1103 AB",
    "addr:housenumber":"100-u",
    "addr:postcode":"1103 ab",
    "addr:street":"Echtenstein",
    "iso:country":"NL",
    "sg:address":"Echtenstein 100-U",
    "sg:city":"Amsterdam Zuidoost",
    "sg:classifiers":[
        {
            "category":"Food & Beverages",
            "subcategory":"Candy",
            "type":"Retail Goods"
        }
    ],
    "sg:phone":"+31 20 600 9551",
    "sg:postcode":"1103 AB",
    "sg:province":"North Holland",
    "sg:tags":[
        "geld-",
        "en",
        "waardetransporten"
    ],
    "sg:website":"http://www.afristar.nl",
    "wof:name":"Afristar",
    "wof:placetype":"venue"
},
  "geometry": {"coordinates":[4.97467,52.32378],"type":"Point"}
}