{
  "type": "Feature",
  "properties": {
    "addr:full":"Rhonewg 30 Amsterdam Noord-Holland 1043 AH",
    "addr:housenumber":"30",
    "addr:postcode":"1043 ah",
    "addr:street":"Rhonewg",
    "iso:country":"NL",
    "sg:address":"Rhonewg 30",
    "sg:city":"Amsterdam",
    "sg:orig_category":"Verhuizingen",
    "sg:phone":"+31 20 411 3424",
    "sg:postcode":"1043 AH",
    "sg:province":"Noord-Holland",
    "sg:website":"http://www.apollo-verhuizingen.nl",
    "wof:name":"Apollo Verhuizingen",
    "wof:placetype":"venue"
},
  "geometry": {"coordinates":[4.826973,52.390278],"type":"Point"}
}