{
  "type": "Feature",
  "properties": {
    "addr:full":"Hoensbroeksingel 15 Rotterdam South Holland 3077 TA",
    "addr:housenumber":"15",
    "addr:postcode":"3077 ta",
    "addr:street":"Hoensbroeksingel",
    "iso:country":"NL",
    "sg:address":"Hoensbroeksingel 15",
    "sg:city":"Rotterdam",
    "sg:classifiers":[
        {
            "category":"Education",
            "subcategory":"Preschool",
            "type":"Public Place"
        }
    ],
    "sg:phone":"+31 10 292 7574",
    "sg:postcode":"3077 TA",
    "sg:province":"South Holland",
    "sg:tags":[
        "kleuteronderwijs",
        "basis-"
    ],
    "wof:name":"Openbare Basisschool De Rode Wiekel",
    "wof:placetype":"venue"
},
  "geometry": {"coordinates":[4.563338,51.895027],"type":"Point"}
}