{
  "type": "Feature",
  "properties": {
    "addr:full":"De Klauwier 5 Denekamp NL.08 7591 JP",
    "addr:housenumber":"5;nl.08",
    "addr:postcode":"7591 jp",
    "addr:street":"De Klauwier",
    "iso:country":"NL",
    "sg:address":"De Klauwier 5",
    "sg:city":"Denekamp",
    "sg:orig_category":"Administratie- En Boekhoudkantoren",
    "sg:phone":"+31 541 352 951",
    "sg:postcode":"7591 JP",
    "sg:province":"NL.08",
    "wof:name":"Groeneveld",
    "wof:placetype":"venue"
},
  "geometry": {"coordinates":[7.003711,52.386642],"type":"Point"}
}