{
  "type": "Feature",
  "properties": {
    "addr:full":"A Holzelsngl 6 Amsterdam Noord-Holland 1069 PN",
    "addr:housenumber":"6",
    "addr:postcode":"1069 pn",
    "iso:country":"NL",
    "sg:address":"A Holzelsngl 6",
    "sg:city":"Amsterdam",
    "sg:orig_category":"Beveiliging",
    "sg:phone":"+31 20 610 5014",
    "sg:postcode":"1069 PN",
    "sg:province":"Noord-Holland",
    "wof:name":"Bronlock, J",
    "wof:placetype":"venue"
},
  "geometry": {"coordinates":[4.78913,52.35305],"type":"Point"}
}