{
  "type": "Feature",
  "properties": {
    "addr:full":"Fauststr 1 Apeldoorn Gelderland 7323 BA",
    "addr:housenumber":"1",
    "addr:postcode":"7323 ba",
    "addr:street":"Fauststr;Gelderland",
    "iso:country":"NL",
    "sg:address":"Fauststr 1",
    "sg:city":"Apeldoorn",
    "sg:orig_category":"Elektronische Informatie- Systemen Off-Line",
    "sg:phone":"+31 55 577 8975",
    "sg:postcode":"7323 BA",
    "sg:province":"Gelderland",
    "wof:name":"Zorgnet Bv",
    "wof:placetype":"venue"
},
  "geometry": {"coordinates":[5.977115,52.231834],"type":"Point"}
}