{
  "type": "Feature",
  "properties": {
    "addr:full":"Buitenveldertseln 172 Amsterdam Noord-Holland 1081 AC",
    "addr:housenumber":"172",
    "addr:postcode":"1081 ac",
    "iso:country":"NL",
    "sg:address":"Buitenveldertseln 172",
    "sg:city":"Amsterdam",
    "sg:orig_category":"Bijouterie?n",
    "sg:phone":"+31 20 661 1384",
    "sg:postcode":"1081 AC",
    "sg:province":"Noord-Holland",
    "wof:name":"Lucia",
    "wof:placetype":"venue"
},
  "geometry": {"coordinates":[4.868465,52.324898],"type":"Point"}
}