{
  "type": "Feature",
  "properties": {
    "addr:full":"Oostermeent Z 11 Huizen North Holland 1274 ST",
    "addr:housenumber":"11",
    "addr:postcode":"1274 st",
    "iso:country":"NL",
    "sg:address":"Oostermeent Z 11",
    "sg:city":"Huizen",
    "sg:orig_category":"Kappersbenodigdheden",
    "sg:phone":"+31 35 642 0266",
    "sg:postcode":"1274 ST",
    "sg:province":"North Holland",
    "sg:website":"http://www.maksokappersshop.nl",
    "wof:name":"Makso",
    "wof:placetype":"venue"
},
  "geometry": {"coordinates":[5.264176,52.294964],"type":"Point"}
}