{
  "type": "Feature",
  "properties": {
    "addr:full":"Vierambachtsstraat 58 Rotterdam Zuid-Holland 3023 AP",
    "addr:housenumber":"58",
    "addr:postcode":"3023 ap",
    "addr:street":"Vierambachtsstraat",
    "iso:country":"NL",
    "sg:address":"Vierambachtsstraat 58",
    "sg:city":"Rotterdam",
    "sg:orig_category":"Juweliers",
    "sg:phone":"+31 10 425 9925",
    "sg:postcode":"3023 AP",
    "sg:province":"Zuid-Holland",
    "wof:name":"De Gouden Indiaan",
    "wof:placetype":"venue"
},
  "geometry": {"coordinates":[4.44929,51.916451],"type":"Point"}
}