{
  "type": "Feature",
  "properties": {
    "addr:full":"W De Withstr 141Hs Amsterdam Noord-Holland 1057 XS",
    "addr:housenumber":"141hs",
    "addr:postcode":"1057 xs",
    "addr:street":"W De Withstr",
    "iso:country":"NL",
    "sg:address":"W De Withstr 141Hs",
    "sg:city":"Amsterdam",
    "sg:orig_category":"Autorijscholen",
    "sg:phone":"+31 20 616 6677",
    "sg:postcode":"1057 XS",
    "sg:province":"Noord-Holland",
    "wof:name":"Rusch, J A",
    "wof:placetype":"venue"
},
  "geometry": {"coordinates":[4.858727,52.370918],"type":"Point"}
}