{
  "type": "Feature",
  "properties": {
    "iso:country":"NL",
    "sg:address":"Hoefsmedery 23",
    "sg:city":"Delfzyl",
    "sg:orig_category":"Orthopedagogen",
    "sg:phone":"+31 596 628 674",
    "sg:postcode":"9932 GN",
    "sg:province":"Groningen",
    "wof:name":"Benes- Gramsbergen, Drs A G J",
    "wof:placetype":"venue"
},
  "geometry": {"coordinates":[6.8893580437,53.3252334595],"type":"Point"}
}