{
  "type": "Feature",
  "properties": {
    "addr:full":"Brediusweg 14A Bussum Noord-Holland 1401 AG",
    "addr:housenumber":"14a",
    "addr:postcode":"1401",
    "addr:street":"Brediusweg",
    "iso:country":"NL",
    "sg:address":"Brediusweg 14A",
    "sg:city":"Bussum",
    "sg:orig_category":"Antiekzaken",
    "sg:phone":"+31 35 691 3630",
    "sg:postcode":"1401 AG",
    "sg:province":"Noord-Holland",
    "wof:name":"Antiquariaat Bredius",
    "wof:placetype":"venue"
},
  "geometry": {"coordinates":[5.165201,52.2803],"type":"Point"}
}