{
  "type": "Feature",
  "properties": {
    "addr:full":"M De Ruyterwg 84 Vught North Brabant 5262 VH",
    "addr:housenumber":"84",
    "addr:postcode":"5262 vh",
    "addr:street":"M",
    "iso:country":"NL",
    "sg:address":"M De Ruyterwg 84",
    "sg:city":"Vught",
    "sg:orig_category":"Autorijscholen",
    "sg:phone":"+31 73 656 8672",
    "sg:postcode":"5262 VH",
    "sg:province":"North Brabant",
    "wof:name":"Meijs, Hans",
    "wof:placetype":"venue"
},
  "geometry": {"coordinates":[5.286638,51.649178],"type":"Point"}
}