{
  "type": "Feature",
  "properties": {
    "addr:full":"Czaar Peterstraat 97 Amsterdam North Holland 1018 PE",
    "addr:housenumber":"97",
    "addr:postcode":"1018 pe",
    "addr:street":"Czaar Peterstraat",
    "iso:country":"NL",
    "sg:address":"Czaar Peterstraat 97",
    "sg:city":"Amsterdam",
    "sg:orig_category":"Metaalbekleding And -Behandeling",
    "sg:phone":"+31 20 625 9902",
    "sg:postcode":"1018 PE",
    "sg:province":"North Holland",
    "wof:name":"W.J.M. Werkhoven",
    "wof:placetype":"venue"
},
  "geometry": {"coordinates":[4.929426,52.370216],"type":"Point"}
}