{
  "type": "Feature",
  "properties": {
    "iso:country":"NL",
    "sg:address":"Nijverheidstraat 2",
    "sg:city":"Katwijk Zh",
    "sg:orig_category":"Kantoorartikelen",
    "sg:phone":"+31 71 402 5101",
    "sg:postcode":"2222 AV",
    "sg:province":"South Holland",
    "wof:name":"Nobels Machinefabriek Bv",
    "wof:placetype":"venue"
},
  "geometry": {"coordinates":[4.4338707924,52.2056465149],"type":"Point"}
}