{
  "type": "Feature",
  "properties": {
    "addr:full":"Geleenstraat 2 Heerlen Limburg 6411 HS",
    "addr:housenumber":"2",
    "addr:postcode":"6411 hs",
    "addr:street":"Geleenstraat",
    "iso:country":"NL",
    "sg:address":"Geleenstraat 2",
    "sg:city":"Heerlen",
    "sg:orig_category":"Opticiens",
    "sg:phone":"+31 45 574 0713",
    "sg:postcode":"6411 HS",
    "sg:province":"Limburg",
    "wof:name":"Roeks Opticiens Bv",
    "wof:placetype":"venue"
},
  "geometry": {"coordinates":[5.9784908295,50.8871192932],"type":"Point"}
}