{
  "type": "Feature",
  "properties": {
    "addr:full":"Middenweg 237 Amsterdam North Holland 1098 AP",
    "addr:housenumber":"237",
    "addr:postcode":"1098 ap",
    "addr:street":"Middenweg",
    "iso:country":"NL",
    "sg:address":"Middenweg 237",
    "sg:city":"Amsterdam",
    "sg:orig_category":"Kappers",
    "sg:phone":"+31 20 694 7217",
    "sg:postcode":"1098 AP",
    "sg:province":"North Holland",
    "wof:name":"Kapsalon Rento Cisou Bv",
    "wof:placetype":"venue"
},
  "geometry": {"coordinates":[4.9378361702,52.349395752],"type":"Point"}
}