{
  "type": "Feature",
  "properties": {
    "addr:full":"Verlaat 20 Leimuiden Zuid-Holland 2451 ZP",
    "addr:housenumber":"20",
    "addr:postcode":"2451 zp",
    "addr:street":"Verlaat",
    "iso:country":"NL",
    "sg:address":"Verlaat 20",
    "sg:city":"Leimuiden",
    "sg:orig_category":"Meubelmakerijen",
    "sg:phone":"+31 172 500 313",
    "sg:postcode":"2451 ZP",
    "sg:province":"Zuid-Holland",
    "wof:name":"Rijnsoever Jr, Willem Van",
    "wof:placetype":"venue"
},
  "geometry": {"coordinates":[4.670686,52.225983],"type":"Point"}
}