{
  "type": "Feature",
  "properties": {
    "addr:full":"Hellestr 24 Amersfoort Utrecht 3811 LL",
    "addr:housenumber":"24",
    "addr:postcode":"3811 ll",
    "addr:street":"Hellestr",
    "iso:country":"NL",
    "sg:address":"Hellestr 24",
    "sg:city":"Amersfoort",
    "sg:orig_category":"Ziekenhuizen, Sanatoria, Verpleeghuizen",
    "sg:phone":"+31 33 422 2345",
    "sg:postcode":"3811 LL",
    "sg:province":"Utrecht",
    "wof:name":"Eemland Zks",
    "wof:placetype":"venue"
},
  "geometry": {"coordinates":[5.384996,52.155834],"type":"Point"}
}