{
  "type": "Feature",
  "properties": {
    "addr:full":"Haagsemarkt 18 Breda Noord-Brabant 4813 BB",
    "addr:housenumber":"18",
    "addr:postcode":"4813 bb",
    "addr:street":"Haagsemarkt",
    "iso:country":"NL",
    "sg:address":"Haagsemarkt 18",
    "sg:city":"Breda",
    "sg:orig_category":"Fotoreportages",
    "sg:phone":"+31 76 514 3570",
    "sg:postcode":"4813 BB",
    "sg:province":"Noord-Brabant",
    "wof:name":"Unen, Van",
    "wof:placetype":"venue"
},
  "geometry": {"coordinates":[4.739317,51.577606],"type":"Point"}
}