{
  "type": "Feature",
  "properties": {
    "addr:full":"Hanesteensewg 2 Hattemerbroek Gelderland 8094 PM",
    "addr:housenumber":"2",
    "addr:postcode":"8094 pm",
    "addr:street":"Hanesteensewg;Gelderland",
    "iso:country":"NL",
    "sg:address":"Hanesteensewg 2",
    "sg:city":"Hattemerbroek",
    "sg:orig_category":"Hoefsmederijen",
    "sg:phone":"+31 38 376 2505",
    "sg:postcode":"8094 PM",
    "sg:province":"Gelderland",
    "wof:name":"Poppe, W S",
    "wof:placetype":"venue"
},
  "geometry": {"coordinates":[6.027129,52.476078],"type":"Point"}
}