{
  "type": "Feature",
  "properties": {
    "iso:country":"NL",
    "sg:address":"Burgemeester Jansenstr 32",
    "sg:city":"Tilburg",
    "sg:orig_category":"Technische Studies And Onderzoek",
    "sg:phone":"+31 13 463 5434",
    "sg:postcode":"5037 NC",
    "sg:province":"North Brabant",
    "wof:name":"Raadgevend Buro Voor De Gezondheidszorg",
    "wof:placetype":"venue"
},
  "geometry": {"coordinates":[5.058783,51.553181],"type":"Point"}
}