{
  "type": "Feature",
  "properties": {
    "addr:full":"De Brink 9 Losser Overijssel 7581 JC",
    "addr:housenumber":"9",
    "addr:postcode":"7581 jc",
    "addr:street":"De Brink",
    "iso:country":"NL",
    "sg:address":"De Brink 9",
    "sg:city":"Losser",
    "sg:orig_category":"Opticiens",
    "sg:phone":"+31 53 538 2513",
    "sg:postcode":"7581 JC",
    "sg:province":"Overijssel",
    "wof:name":"A.G. Blokhuis",
    "wof:placetype":"venue"
},
  "geometry": {"coordinates":[7.0058059692,52.2611732483],"type":"Point"}
}