{
  "type": "Feature",
  "properties": {
    "addr:full":"Parkstraat 11 Steijl Limburg 5935 BM",
    "addr:housenumber":"11",
    "addr:postcode":"5935 bm",
    "addr:street":"Parkstraat;Limburg",
    "iso:country":"NL",
    "sg:address":"Parkstraat 11",
    "sg:city":"Steijl",
    "sg:orig_category":"Keramische Producten Fab",
    "sg:phone":"+31 77 373 6775",
    "sg:postcode":"5935 BM",
    "sg:province":"Limburg",
    "wof:name":"N.A.M. Hoogland",
    "wof:placetype":"venue"
},
  "geometry": {"coordinates":[6.123025,51.333511],"type":"Point"}
}