{
  "type": "Feature",
  "properties": {
    "addr:full":"De Savornin Lohmanlaan 49 'S Gravenhage Zuid-Holland 2566 AH",
    "addr:housenumber":"49",
    "addr:postcode":"2566 ah",
    "addr:street":"De Savornin Lohmanlaan;' S",
    "iso:country":"NL",
    "sg:address":"De Savornin Lohmanlaan 49",
    "sg:city":"'S Gravenhage",
    "sg:orig_category":"Boekhouders",
    "sg:phone":"+31 70 325 3174",
    "sg:postcode":"2566 AH",
    "sg:province":"Zuid-Holland",
    "wof:name":"Admin & Ass Kant R Eversteyn",
    "wof:placetype":"venue"
},
  "geometry": {"coordinates":[4.244802,52.069046],"type":"Point"}
}