{
  "type": "Feature",
  "properties": {
    "addr:full":"Kerkstraat 39 Elshout North Brabant 5154 AN",
    "addr:housenumber":"39",
    "addr:postcode":"5154 an",
    "addr:street":"Kerkstraat",
    "iso:country":"NL",
    "sg:address":"Kerkstraat 39",
    "sg:city":"Elshout",
    "sg:orig_category":"Overheidsdiensten",
    "sg:phone":"+31 416 376 828",
    "sg:postcode":"5154 AN",
    "sg:province":"North Brabant",
    "wof:name":"T Rad",
    "wof:placetype":"venue"
},
  "geometry": {"coordinates":[5.1365070343,51.7011604309],"type":"Point"}
}