{
  "type": "Feature",
  "properties": {
    "addr:full":"Hereplein 5 Groningen Groningen 9711 GA",
    "addr:housenumber":"5",
    "addr:postcode":"9711 ga",
    "addr:street":"Hereplein",
    "iso:country":"NL",
    "sg:address":"Hereplein 5",
    "sg:city":"Groningen",
    "sg:orig_category":"Werving And Selectie Van Vast Personeel",
    "sg:phone":"+31 50 314 0104",
    "sg:postcode":"9711 GA",
    "sg:province":"Groningen",
    "wof:name":"Topstart Techniek",
    "wof:placetype":"venue"
},
  "geometry": {"coordinates":[6.5687971115,53.2133483887],"type":"Point"}
}