{
  "type": "Feature",
  "properties": {
    "addr:full":"Moerweide 75 Reeuwyk Zuid-Holland 2811 JC",
    "addr:housenumber":"75",
    "addr:postcode":"2811 jc",
    "addr:street":"Moerweide",
    "iso:country":"NL",
    "sg:address":"Moerweide 75",
    "sg:city":"Reeuwyk",
    "sg:orig_category":"Hijswerktuigen - Reparatie",
    "sg:phone":"+31 182 399 237",
    "sg:postcode":"2811 JC",
    "sg:province":"Zuid-Holland",
    "wof:name":"Rov? Reeuwijk",
    "wof:placetype":"venue"
},
  "geometry": {"coordinates":[4.729331,52.051979],"type":"Point"}
}