{
  "type": "Feature",
  "properties": {
    "addr:full":"Zwart Janstraat 96B Rotterdam South Holland 3035 AW",
    "addr:housenumber":"96b",
    "addr:postcode":"3035 aw",
    "addr:street":"Zwart Janstraat",
    "iso:country":"NL",
    "sg:address":"Zwart Janstraat 96B",
    "sg:city":"Rotterdam",
    "sg:orig_category":"Werving And Selectie Van Tijdelijk Personeel And Uitzendkantoren",
    "sg:phone":"+31 6 51096963",
    "sg:postcode":"3035 AW",
    "sg:province":"South Holland",
    "wof:name":"Didact",
    "wof:placetype":"venue"
},
  "geometry": {"coordinates":[4.477036953,51.9335479736],"type":"Point"}
}