{
  "type": "Feature",
  "properties": {
    "addr:full":"Alkmaarsestraat 16 'S Gravenhage South Holland 2587 RN",
    "addr:housenumber":"16",
    "addr:postcode":"2587 rn",
    "addr:street":"Alkmaarsestraat;' S Gravenhage",
    "iso:country":"NL",
    "sg:address":"Alkmaarsestraat 16",
    "sg:city":"'S Gravenhage",
    "sg:orig_category":"Vertaal- And Tolkenbureaus",
    "sg:phone":"+31 70 352 4578",
    "sg:postcode":"2587 RN",
    "sg:province":"South Holland",
    "wof:name":"Sandberg Translations And Real Estate Se",
    "wof:placetype":"venue"
},
  "geometry": {"coordinates":[4.288031,52.115189],"type":"Point"}
}