{
  "type": "Feature",
  "properties": {
    "addr:full":"Dorpsstr 48 Castricum Noord-Holland 1901 EM",
    "addr:housenumber":"48",
    "addr:postcode":"1901 em",
    "addr:street":"Dorpsstr",
    "iso:country":"NL",
    "sg:address":"Dorpsstr 48",
    "sg:city":"Castricum",
    "sg:orig_category":"Herenkleding",
    "sg:phone":"+31 251 652 271",
    "sg:postcode":"1901 EM",
    "sg:province":"Noord-Holland",
    "wof:name":"Mul Mannenmode",
    "wof:placetype":"venue"
},
  "geometry": {"coordinates":[4.662592,52.546745],"type":"Point"}
}