{
  "type": "Feature",
  "properties": {
    "addr:full":"Transitoweg 11 Moerdijk Noord-Brabant 4782 SM",
    "addr:housenumber":"11",
    "addr:postcode":"4782 sm",
    "addr:street":"Transitoweg",
    "iso:country":"NL",
    "sg:address":"Transitoweg 11",
    "sg:city":"Moerdijk",
    "sg:orig_category":"Metalen And Ertsen Gh",
    "sg:phone":"+31 168 382 200",
    "sg:postcode":"4782 SM",
    "sg:province":"Noord-Brabant",
    "wof:name":"Merwestaal Moerdijk Bv",
    "wof:placetype":"venue"
},
  "geometry": {"coordinates":[4.609939,51.678318],"type":"Point"}
}