{
  "type": "Feature",
  "properties": {
    "addr:full":"Ruurloseweg 81 Vorden Gelderland 7251 LC",
    "addr:housenumber":"81",
    "addr:postcode":"7251 lc",
    "addr:street":"Ruurloseweg;Gelderland",
    "iso:country":"NL",
    "sg:address":"Ruurloseweg 81",
    "sg:city":"Vorden",
    "sg:orig_category":"Kampeerterreinen",
    "sg:phone":"+31 575 551 492",
    "sg:postcode":"7251 LC",
    "sg:province":"Gelderland",
    "wof:name":"Camping Wientjesvoort Bv",
    "wof:placetype":"venue"
},
  "geometry": {"coordinates":[6.3495388031,52.1045227051],"type":"Point"}
}