{
  "type": "Feature",
  "properties": {
    "iso:country":"NL",
    "sg:address":"Heerbaan 136",
    "sg:city":"Millingen Ad Ryn",
    "sg:orig_category":"Koeltechniek",
    "sg:phone":"+31 481 450 055",
    "sg:postcode":"6566 EV",
    "sg:province":"Gelderland",
    "wof:name":"Frimakoeling",
    "wof:placetype":"venue"
},
  "geometry": {"coordinates":[6.047919,51.863026],"type":"Point"}
}