{
  "type": "Feature",
  "properties": {
    "addr:full":"Parkln 52 Eindhoven Noord-Brabant 5613 BH",
    "addr:housenumber":"52",
    "addr:postcode":"5613 bh",
    "addr:street":"Parkln",
    "iso:country":"NL",
    "sg:address":"Parkln 52",
    "sg:city":"Eindhoven",
    "sg:orig_category":"Banken",
    "sg:phone":"+31 40 265 7100",
    "sg:postcode":"5613 BH",
    "sg:province":"Noord-Brabant",
    "wof:name":"Lanschot Nv, F Van",
    "wof:placetype":"venue"
},
  "geometry": {"coordinates":[5.484105,51.434471],"type":"Point"}
}