{
  "type": "Feature",
  "properties": {
    "addr:full":"Narvikwg 5 Groningen Groningen 9723 TV",
    "addr:housenumber":"5",
    "addr:postcode":"9723 tv",
    "addr:street":"Narvikwg",
    "iso:country":"NL",
    "sg:address":"Narvikwg 5",
    "sg:city":"Groningen",
    "sg:orig_category":"Geluidsinstallaties",
    "sg:phone":"+31 50 549 9416",
    "sg:postcode":"9723 TV",
    "sg:province":"Groningen",
    "sg:website":"http://www.eltimaudio.com",
    "wof:name":"Eltim Bv",
    "wof:placetype":"venue"
},
  "geometry": {"coordinates":[6.608603,53.20549],"type":"Point"}
}