{
  "type": "Feature",
  "properties": {
    "addr:full":"Koningin Julianaweg 1 Heerenveen Friesland 8443 DP",
    "addr:housenumber":"1",
    "addr:postcode":"8443 dp",
    "addr:street":"Koningin Julianaweg",
    "iso:country":"NL",
    "sg:address":"Koningin Julianaweg 1",
    "sg:city":"Heerenveen",
    "sg:orig_category":"Bloemen And Planten",
    "sg:phone":"+31 513 636 250",
    "sg:postcode":"8443 DP",
    "sg:province":"Friesland",
    "wof:name":"Intratuin Heerenveen Bv",
    "wof:placetype":"venue"
},
  "geometry": {"coordinates":[5.941708,52.94537],"type":"Point"}
}