{
  "type": "Feature",
  "properties": {
    "addr:full":"Biltstr 443 Utrecht Utrecht 3572 AW",
    "addr:housenumber":"443",
    "addr:postcode":"3572 aw",
    "iso:country":"NL",
    "sg:address":"Biltstr 443",
    "sg:city":"Utrecht",
    "sg:orig_category":"Werving En Selectie",
    "sg:phone":"+31 30 231 0970",
    "sg:postcode":"3572 AW",
    "sg:province":"Utrecht",
    "wof:name":"Smit, Rik",
    "wof:placetype":"venue"
},
  "geometry": {"coordinates":[5.1359028816,52.0954208374],"type":"Point"}
}