{
  "type": "Feature",
  "properties": {
    "addr:full":"Horst 51 Gemert Noord-Brabant 5422 BJ",
    "addr:housenumber":"51",
    "addr:postcode":"5422 bj",
    "addr:street":"Horst",
    "iso:country":"NL",
    "sg:address":"Horst 51",
    "sg:city":"Gemert",
    "sg:orig_category":"Kantoor- En Interieurbeplanting",
    "sg:phone":"+31 492 366 954",
    "sg:postcode":"5422 BJ",
    "sg:province":"Noord-Brabant",
    "wof:name":"Aarts Interieurbeplantingen, Ger",
    "wof:placetype":"venue"
},
  "geometry": {"coordinates":[5.7049179077,51.5564804077],"type":"Point"}
}