{
  "type": "Feature",
  "properties": {
    "addr:full":"Mauvelaan 26 Maassluis South Holland 3141 KL",
    "addr:housenumber":"26",
    "addr:postcode":"3141 kl",
    "addr:street":"Mauvelaan",
    "iso:country":"NL",
    "sg:address":"Mauvelaan 26",
    "sg:city":"Maassluis",
    "sg:orig_category":"Film-, Tv- And Videoproductie",
    "sg:phone":"+31 10 592 4802",
    "sg:postcode":"3141 KL",
    "sg:province":"South Holland",
    "wof:name":"De Aanpak",
    "wof:placetype":"venue"
},
  "geometry": {"coordinates":[4.260308,51.916801],"type":"Point"}
}