{
  "type": "Feature",
  "properties": {
    "addr:full":"Kruisnetlaan 190 Rotterdam Zuid-Holland 3192 KC",
    "addr:housenumber":"190",
    "addr:postcode":"3192 kc",
    "addr:street":"Kruisnetlaan",
    "iso:country":"NL",
    "sg:address":"Kruisnetlaan 190",
    "sg:city":"Rotterdam",
    "sg:orig_category":"Overheidsdiensten",
    "sg:phone":"+31 10 438 5605",
    "sg:postcode":"3192 KC",
    "sg:province":"Zuid-Holland",
    "wof:name":"Het Swh Ankerklubhuis",
    "wof:placetype":"venue"
},
  "geometry": {"coordinates":[4.3684501648,51.8499717712],"type":"Point"}
}