{
  "type": "Feature",
  "properties": {
    "iso:country":"NL",
    "sg:address":"Gildewg 30",
    "sg:city":"Barneveld",
    "sg:orig_category":"Papier - Fabrieken En Groothandel",
    "sg:phone":"+31 342 492 690",
    "sg:postcode":"3771 NB",
    "sg:province":"Gelderland",
    "wof:name":"Rhine-Delta Recycled",
    "wof:placetype":"venue"
},
  "geometry": {"coordinates":[5.603653,52.166775],"type":"Point"}
}