{
  "type": "Feature",
  "properties": {
    "addr:full":"Bedryfswg 29 Vriezenveen NL.08 7671 EG",
    "addr:housenumber":"29;nl.08",
    "addr:postcode":"7671 eg",
    "addr:street":"Bedryfswg",
    "iso:country":"NL",
    "sg:address":"Bedryfswg 29",
    "sg:city":"Vriezenveen",
    "sg:orig_category":"Verlichtingsartikelen - Fabrieken",
    "sg:phone":"+31 546 565 757",
    "sg:postcode":"7671 EG",
    "sg:province":"NL.08",
    "wof:name":"Unired",
    "wof:placetype":"venue"
},
  "geometry": {"coordinates":[6.600179,52.411419],"type":"Point"}
}