{
  "type": "Feature",
  "properties": {
    "addr:full":"Dahliastr 14 Woerden Utrecht 3442 BN",
    "addr:housenumber":"14",
    "addr:postcode":"3442 bn",
    "addr:street":"Dahliastr",
    "iso:country":"NL",
    "sg:address":"Dahliastr 14",
    "sg:city":"Woerden",
    "sg:orig_category":"Acupunctuur",
    "sg:phone":"+31 348 416 118",
    "sg:postcode":"3442 BN",
    "sg:province":"Utrecht",
    "wof:name":"Hemert, Lies Van",
    "wof:placetype":"venue"
},
  "geometry": {"coordinates":[4.875498,52.084942],"type":"Point"}
}