{
  "type": "Feature",
  "properties": {
    "addr:full":"Hoofdstr 39B Gorssel Gelderland 7213 CP",
    "addr:housenumber":"39b",
    "addr:postcode":"7213 cp",
    "addr:street":"Hoofdstr;Gelderland",
    "iso:country":"NL",
    "sg:address":"Hoofdstr 39B",
    "sg:city":"Gorssel",
    "sg:orig_category":"Makelaars En Adviseurs Onroerende Goederen",
    "sg:phone":"+31 575 492 080",
    "sg:postcode":"7213 CP",
    "sg:province":"Gelderland",
    "sg:website":"http://www.vrie-link.nl",
    "wof:name":"Scarlett Ankersmit",
    "wof:placetype":"venue"
},
  "geometry": {"coordinates":[6.200194,52.198872],"type":"Point"}
}