{
  "type": "Feature",
  "properties": {
    "addr:full":"Kerkstr Z 18 Oeffelt Noord-Brabant 5441 AK",
    "addr:housenumber":"18",
    "addr:postcode":"5441 ak",
    "iso:country":"NL",
    "sg:address":"Kerkstr Z 18",
    "sg:city":"Oeffelt",
    "sg:classifiers":[
        {
            "category":"Food & Beverages",
            "subcategory":"Bakery",
            "type":"Retail Goods"
        }
    ],
    "sg:phone":"+31 485 361 238",
    "sg:postcode":"5441 AK",
    "sg:province":"Noord-Brabant",
    "sg:tags":[
        "brood",
        "en",
        "banket"
    ],
    "wof:name":"Buijssen, P",
    "wof:placetype":"venue"
},
  "geometry": {"coordinates":[5.938033,51.696774],"type":"Point"}
}