{
  "type": "Feature",
  "properties": {
    "addr:full":"Postbus 15 Purmerend Noord-Holland 1440 AA",
    "addr:housenumber":"15",
    "addr:postcode":"1440 aa",
    "addr:street":"Postbus",
    "iso:country":"NL",
    "sg:address":"Postbus 15",
    "sg:city":"Purmerend",
    "sg:orig_category":"Begraafplaatsen",
    "sg:phone":"+31 299 432 727",
    "sg:postcode":"1440 AA",
    "sg:province":"Noord-Holland",
    "wof:name":"Algemene Begraafplaats",
    "wof:placetype":"venue"
},
  "geometry": {"coordinates":[4.94793,52.507607],"type":"Point"}
}