{
  "type": "Feature",
  "properties": {
    "iso:country":"NL",
    "sg:address":"Echternachstraat 24",
    "sg:city":"'S Hertogenbosch",
    "sg:orig_category":"Onderhoud And Reparatie Kantoorapparatuur",
    "sg:phone":"+31 73 621 3757",
    "sg:postcode":"5224 TB",
    "sg:province":"Noord-Brabant",
    "wof:name":"Jfm",
    "wof:placetype":"venue"
},
  "geometry": {"coordinates":[5.264658,51.700035],"type":"Point"}
}