{
  "type": "Feature",
  "properties": {
    "addr:full":"Dorpsstr 137-139 Zuid Beyerland Zuid-Holland 3284 AE",
    "addr:housenumber":"137-139;beyerland",
    "addr:postcode":"3284 ae",
    "iso:country":"NL",
    "sg:address":"Dorpsstr 137-139",
    "sg:city":"Zuid Beyerland",
    "sg:orig_category":"Artsen - Huisartsen",
    "sg:phone":"+31 186 661 465",
    "sg:postcode":"3284 AE",
    "sg:province":"Zuid-Holland",
    "wof:name":"Plas, J L",
    "wof:placetype":"venue"
},
  "geometry": {"coordinates":[4.369756,51.749306],"type":"Point"}
}