{
  "type": "Feature",
  "properties": {
    "addr:full":"Noorder Leidsevaart 29 Hillegom Zuid-Holland 2182 NB",
    "addr:housenumber":"29",
    "addr:postcode":"2182 nb",
    "addr:street":"Noorder Leidsevaart",
    "iso:country":"NL",
    "sg:address":"Noorder Leidsevaart 29",
    "sg:city":"Hillegom",
    "sg:orig_category":"Bloemen And Planten",
    "sg:phone":"+31 252 515 725",
    "sg:postcode":"2182 NB",
    "sg:province":"Zuid-Holland",
    "wof:name":"J. Van Der Linden & Zoon Bv",
    "wof:placetype":"venue"
},
  "geometry": {"coordinates":[4.560494,52.304829],"type":"Point"}
}