{
  "type": "Feature",
  "properties": {
    "iso:country":"NL",
    "sg:address":"Nieuwe Spiegelstraat 36",
    "sg:city":"Amsterdam",
    "sg:orig_category":"Boekenuitgeverijen",
    "sg:phone":"+31 20 620 5171",
    "sg:postcode":"1017 DG",
    "sg:province":"North Holland",
    "wof:name":"Uitgeverij Bis Bv",
    "wof:placetype":"venue"
},
  "geometry": {"coordinates":[4.888841,52.363869],"type":"Point"}
}