{
  "type": "Feature",
  "properties": {
    "addr:full":"Hoofdstraat 143 Bovenkarspel Noord-Holland 1611 AD",
    "addr:housenumber":"143",
    "addr:postcode":"1611 ad",
    "addr:street":"Hoofdstraat",
    "iso:country":"NL",
    "sg:address":"Hoofdstraat 143",
    "sg:city":"Bovenkarspel",
    "sg:orig_category":"Huishoudapparatuur, Televisies And Radio'S",
    "sg:phone":"+31 228 511 280",
    "sg:postcode":"1611 AD",
    "sg:province":"Noord-Holland",
    "wof:name":"Nw Botman",
    "wof:placetype":"venue"
},
  "geometry": {"coordinates":[5.24424,52.698303],"type":"Point"}
}