{
  "type": "Feature",
  "properties": {
    "addr:full":"Doelenstraat 10 Almelo Overijssel 7607 AJ",
    "addr:housenumber":"10",
    "addr:postcode":"7607 aj",
    "addr:street":"Doelenstraat",
    "iso:country":"NL",
    "sg:address":"Doelenstraat 10",
    "sg:city":"Almelo",
    "sg:orig_category":"Huishoudapparatuur, Televisies And Radio'S",
    "sg:phone":"+31 546 814 237",
    "sg:postcode":"7607 AJ",
    "sg:province":"Overijssel",
    "wof:name":"Johs. Bennink-Almelo",
    "wof:placetype":"venue"
},
  "geometry": {"coordinates":[6.66562,52.359093],"type":"Point"}
}