{
  "type": "Feature",
  "properties": {
    "addr:full":"Orionweg 17 Haarlem Noord-Holland 2024 TA",
    "addr:housenumber":"17",
    "addr:postcode":"2024 ta",
    "addr:street":"Orionweg",
    "iso:country":"NL",
    "sg:address":"Orionweg 17",
    "sg:city":"Haarlem",
    "sg:orig_category":"Hypotheken And Hypotheekbanken",
    "sg:phone":"+31 23 525 9161",
    "sg:postcode":"2024 TA",
    "sg:province":"Noord-Holland",
    "wof:name":"Kohne Wester Assurantien",
    "wof:placetype":"venue"
},
  "geometry": {"coordinates":[4.639849,52.404194],"type":"Point"}
}