{
  "type": "Feature",
  "properties": {
    "addr:full":"Voltaweg 1 Middelburg Zeeland 4338 PS",
    "addr:housenumber":"1",
    "addr:postcode":"4338 ps",
    "addr:street":"Voltaweg",
    "iso:country":"NL",
    "sg:address":"Voltaweg 1",
    "sg:city":"Middelburg",
    "sg:orig_category":"Verhuur Landbouwmachines",
    "sg:phone":"+31 118 628 390",
    "sg:postcode":"4338 PS",
    "sg:province":"Zeeland",
    "wof:name":"Landbouwmachinebedrijf M. Gideonse",
    "wof:placetype":"venue"
},
  "geometry": {"coordinates":[3.647814,51.490742],"type":"Point"}
}