{
  "type": "Feature",
  "properties": {
    "addr:full":"Mesdagstraat 4 Reeuwijk Zuid-Holland 2811 VW",
    "addr:housenumber":"4",
    "addr:postcode":"2811 vw",
    "addr:street":"Mesdagstraat",
    "iso:country":"NL",
    "sg:address":"Mesdagstraat 4",
    "sg:city":"Reeuwijk",
    "sg:classifiers":[
        {
            "category":"Education",
            "subcategory":"Preschool",
            "type":"Public Place"
        }
    ],
    "sg:phone":"+31 182 393 235",
    "sg:postcode":"2811 VW",
    "sg:province":"Zuid-Holland",
    "sg:tags":[
        "kleuteronderwijs",
        "basis-"
    ],
    "wof:name":"Christelijke Nationale School De Regenboog",
    "wof:placetype":"venue"
},
  "geometry": {"coordinates":[4.719202,52.046951],"type":"Point"}
}