{
  "type": "Feature",
  "properties": {
    "addr:full":"Griffioen 20 Mijdrecht Utrecht 3641 LZ",
    "addr:housenumber":"20",
    "addr:postcode":"3641 lz",
    "addr:street":"Griffioen",
    "iso:country":"NL",
    "sg:address":"Griffioen 20",
    "sg:city":"Mijdrecht",
    "sg:orig_category":"Zuivelproducten",
    "sg:phone":"+31 297 284 095",
    "sg:postcode":"3641 LZ",
    "sg:province":"Utrecht",
    "wof:name":"Melk- En Zuivelhandel Arjan Van Schaik",
    "wof:placetype":"venue"
},
  "geometry": {"coordinates":[4.865717,52.212986],"type":"Point"}
}