{
  "type": "Feature",
  "properties": {
    "addr:full":"Teunisbloem 24 Moerdijk North Brabant 4761 WK",
    "addr:housenumber":"24",
    "addr:postcode":"4761 wk",
    "addr:street":"Teunisbloem",
    "iso:country":"NL",
    "sg:address":"Teunisbloem 24",
    "sg:city":"Moerdijk",
    "sg:orig_category":"Baby- And Kinderkleding",
    "sg:phone":"+31 168 370 815",
    "sg:postcode":"4761 WK",
    "sg:province":"North Brabant",
    "wof:name":"Shop4Kids",
    "wof:placetype":"venue"
},
  "geometry": {"coordinates":[4.590389,51.638187],"type":"Point"}
}