{
  "type": "Feature",
  "properties": {
    "iso:country":"NL",
    "sg:address":"Flora 46",
    "sg:city":"Deventer",
    "sg:orig_category":"Kappers",
    "sg:phone":"+31 570 510 559",
    "sg:postcode":"7422 LL",
    "sg:province":"NL.08",
    "wof:name":"Flair",
    "wof:placetype":"venue"
},
  "geometry": {"coordinates":[6.2157468796,52.2478752136],"type":"Point"}
}