{
  "type": "Feature",
  "properties": {
    "addr:full":"Herenstr 17 Bussum North Holland 1404 HB",
    "addr:housenumber":"17",
    "addr:postcode":"1404 hb",
    "addr:street":"Herenstr",
    "iso:country":"NL",
    "sg:address":"Herenstr 17",
    "sg:city":"Bussum",
    "sg:orig_category":"Boekenkasten",
    "sg:phone":"+31 35 693 8179",
    "sg:postcode":"1404 HB",
    "sg:province":"North Holland",
    "wof:name":"Hemert Interieur Design, Van",
    "wof:placetype":"venue"
},
  "geometry": {"coordinates":[5.16185,52.273151],"type":"Point"}
}