{
  "type": "Feature",
  "properties": {
    "iso:country":"NL",
    "sg:address":"Plattenburgerw 21",
    "sg:city":"Arnhem",
    "sg:orig_category":"Artsen - Huisartsen",
    "sg:phone":"+31 26 361 3771",
    "sg:postcode":"6824 ER",
    "sg:province":"Gelderland",
    "sg:website":"http://www.beerendonk.praktijkinfo.nl",
    "wof:name":"Beerendonk, A Van",
    "wof:placetype":"venue"
},
  "geometry": {"coordinates":[5.937334,51.987888],"type":"Point"}
}