{
  "type": "Feature",
  "properties": {
    "addr:full":"Deltastr 2 Kattendyke Zeeland 4474 AK",
    "addr:housenumber":"2",
    "addr:postcode":"4474 ak",
    "addr:street":"Deltastr;Zeeland",
    "iso:country":"NL",
    "sg:address":"Deltastr 2",
    "sg:city":"Kattendyke",
    "sg:orig_category":"Verenigingsgebouwen",
    "sg:phone":"+31 113 621 915",
    "sg:postcode":"4474 AK",
    "sg:province":"Zeeland",
    "wof:name":"Blokhuis, 'T",
    "wof:placetype":"venue"
},
  "geometry": {"coordinates":[3.943918,51.522644],"type":"Point"}
}