{
  "type": "Feature",
  "properties": {
    "addr:full":"Molenweg 53 Diepenveen Overijssel 7431 BH",
    "addr:housenumber":"53",
    "addr:postcode":"7431 bh",
    "addr:street":"Molenweg",
    "iso:country":"NL",
    "sg:address":"Molenweg 53",
    "sg:city":"Diepenveen",
    "sg:classifiers":[
        {
            "category":"Education",
            "subcategory":"Preschool",
            "type":"Public Place"
        }
    ],
    "sg:phone":"+31 570 591 588",
    "sg:postcode":"7431 BH",
    "sg:province":"Overijssel",
    "sg:tags":[
        "kleuteronderwijs",
        "basis-"
    ],
    "wof:name":"I.B. De Zonnewijzer",
    "wof:placetype":"venue"
},
  "geometry": {"coordinates":[6.148041,52.29348],"type":"Point"}
}