{
  "type": "Feature",
  "properties": {
    "addr:full":"Nieuwegracht 23 Soest Utrecht 3763 LP",
    "addr:housenumber":"23",
    "addr:postcode":"3763 lp",
    "addr:street":"Nieuwegracht",
    "iso:country":"NL",
    "sg:address":"Nieuwegracht 23",
    "sg:city":"Soest",
    "sg:orig_category":"Metaalbekleding And -Behandeling",
    "sg:phone":"+31 35 602 2050",
    "sg:postcode":"3763 LP",
    "sg:province":"Utrecht",
    "wof:name":"Straal Totaal Soest",
    "wof:placetype":"venue"
},
  "geometry": {"coordinates":[5.300385,52.184044],"type":"Point"}
}