{
  "type": "Feature",
  "properties": {
    "addr:full":"Holterwg 59B Colmschate NL.08 7429 AE",
    "addr:housenumber":"59b;nl.08",
    "addr:postcode":"7429 ae",
    "addr:street":"Holterwg",
    "iso:country":"NL",
    "sg:address":"Holterwg 59B",
    "sg:city":"Colmschate",
    "sg:orig_category":"Bloemen En Planten - Decoratie",
    "sg:phone":"+31 570 652 205",
    "sg:postcode":"7429 AE",
    "sg:province":"NL.08",
    "sg:website":"HTTP://www.paulhafkamp.nl",
    "wof:name":"Hafkamp, Paul",
    "wof:placetype":"venue"
},
  "geometry": {"coordinates":[6.216112,52.24876],"type":"Point"}
}