{
  "type": "Feature",
  "properties": {
    "addr:full":"Vuurse Dreef 12 Hollandsche Rading North Holland 3739 KT",
    "addr:housenumber":"12",
    "addr:postcode":"3739 kt",
    "addr:street":"Vuurse Dreef",
    "iso:country":"NL",
    "sg:address":"Vuurse Dreef 12",
    "sg:city":"Hollandsche Rading",
    "sg:orig_category":"Fietsen En Bromfietsen",
    "sg:phone":"+31 35 577 1303",
    "sg:postcode":"3739 KT",
    "sg:province":"North Holland",
    "sg:website":"http://www.vollenbroek.com",
    "wof:name":"Vollenbroek",
    "wof:placetype":"venue"
},
  "geometry": {"coordinates":[5.178853,52.178089],"type":"Point"}
}