{
  "type": "Feature",
  "properties": {
    "iso:country":"NL",
    "sg:address":"Panweg 118",
    "sg:city":"Zeist",
    "sg:classifiers":[
        {
            "category":"Fast Food",
            "type":"Food & Drink"
        }
    ],
    "sg:phone":"+31 30 693 1492",
    "sg:postcode":"3705 GG",
    "sg:province":"Utrecht",
    "sg:tags":[
        "afhaal",
        "restaurant"
    ],
    "wof:name":"Restaurant Tong Ah",
    "wof:placetype":"venue"
},
  "geometry": {"coordinates":[5.237125,52.107166],"type":"Point"}
}