{
  "type": "Feature",
  "properties": {
    "addr:full":"Schoutln 18 Weert Limburg 6002 EA",
    "addr:housenumber":"18",
    "addr:postcode":"6002 ea",
    "addr:street":"Schoutln",
    "iso:country":"NL",
    "sg:address":"Schoutln 18",
    "sg:city":"Weert",
    "sg:orig_category":"Verzekeringen - Verzekeringskantoren",
    "sg:phone":"+31 495 456 410",
    "sg:postcode":"6002 EA",
    "sg:province":"Limburg",
    "sg:website":"http://www.isidorus.nl",
    "wof:name":"Isidorus",
    "wof:placetype":"venue"
},
  "geometry": {"coordinates":[5.703781,51.255016],"type":"Point"}
}