{
  "type": "Feature",
  "properties": {
    "addr:full":"Schoolstr 24 Eefde Gelderland 7211 BC",
    "addr:housenumber":"24",
    "addr:postcode":"7211 bc",
    "addr:street":"Schoolstr;Gelderland",
    "iso:country":"NL",
    "sg:address":"Schoolstr 24",
    "sg:city":"Eefde",
    "sg:orig_category":"Autorijscholen",
    "sg:phone":"+31 575 512 204",
    "sg:postcode":"7211 BC",
    "sg:province":"Gelderland",
    "wof:name":"Pas, A J Ten",
    "wof:placetype":"venue"
},
  "geometry": {"coordinates":[6.227335,52.164143],"type":"Point"}
}