{
  "type": "Feature",
  "properties": {
    "addr:full":"Ryksstrwg 50B Ridderkerk Zuid-Holland 2988 BK",
    "addr:housenumber":"50b",
    "addr:postcode":"2988 bk",
    "addr:street":"Ryksstrwg",
    "iso:country":"NL",
    "sg:address":"Ryksstrwg 50B",
    "sg:city":"Ridderkerk",
    "sg:orig_category":"Kinderopvang",
    "sg:phone":"+31 180 422 615",
    "sg:postcode":"2988 BK",
    "sg:province":"Zuid-Holland",
    "wof:name":"Bron, De",
    "wof:placetype":"venue"
},
  "geometry": {"coordinates":[4.59669,51.849644],"type":"Point"}
}