{
  "type": "Feature",
  "properties": {
    "iso:country":"NL",
    "sg:address":"Stationsstr 130",
    "sg:city":"Beek Lb",
    "sg:orig_category":"Onderhoudswerken",
    "sg:phone":"+31 46 437 0945",
    "sg:postcode":"6191 BG",
    "sg:province":"Limburg",
    "wof:name":"Swelsen, Wil",
    "wof:placetype":"venue"
},
  "geometry": {"coordinates":[25.773649,42.610851],"type":"Point"}
}