{
  "type": "Feature",
  "properties": {
    "addr:full":"Damstr 105 Yerseke Zeeland 4401 AS",
    "addr:housenumber":"105",
    "addr:postcode":"4401 as",
    "iso:country":"NL",
    "sg:address":"Damstr 105",
    "sg:city":"Yerseke",
    "sg:orig_category":"Babyartikelen",
    "sg:phone":"+31 113 576 321",
    "sg:postcode":"4401 AS",
    "sg:province":"Zeeland",
    "wof:name":"Little Ones",
    "wof:placetype":"venue"
},
  "geometry": {"coordinates":[4.045713,51.499187],"type":"Point"}
}