{
  "type": "Feature",
  "properties": {
    "addr:full":"V Wesenbekestr 63 S Gravenhage South Holland 2581 TS",
    "addr:housenumber":"63",
    "addr:postcode":"2581 ts",
    "addr:street":"S Gravenhage",
    "iso:country":"NL",
    "sg:address":"V Wesenbekestr 63",
    "sg:city":"S Gravenhage",
    "sg:orig_category":"Kappers",
    "sg:phone":"+31 70 354 7601",
    "sg:postcode":"2581 TS",
    "sg:province":"South Holland",
    "wof:name":"Alfon, Haaratelier",
    "wof:placetype":"venue"
},
  "geometry": {"coordinates":[4.2703590393,52.0913467407],"type":"Point"}
}