{
  "type": "Feature",
  "properties": {
    "iso:country":"NL",
    "sg:address":"Ln V Eikenrode 10",
    "sg:city":"Loosdrecht",
    "sg:orig_category":"Kantoor- En Secretariaatsservice",
    "sg:phone":"+31 35 582 5994",
    "sg:postcode":"1231 BP",
    "sg:province":"North Holland",
    "wof:name":"Jongebloet, Bur Karin",
    "wof:placetype":"venue"
},
  "geometry": {"coordinates":[5.0816349983,52.2068748474],"type":"Point"}
}