{
  "type": "Feature",
  "properties": {
    "addr:full":"Borndiep 66 Capelle Ad Yssel Zuid-Holland 2904 RB",
    "addr:housenumber":"66;2904",
    "addr:postcode":"rb",
    "addr:street":"Borndiep",
    "iso:country":"NL",
    "sg:address":"Borndiep 66",
    "sg:city":"Capelle Ad Yssel",
    "sg:orig_category":"Sportverenigingen En Ontspannings- Verenigingen",
    "sg:phone":"+31 10 450 0634",
    "sg:postcode":"2904 RB",
    "sg:province":"Zuid-Holland",
    "wof:name":"Budo",
    "wof:placetype":"venue"
},
  "geometry": {"coordinates":[4.603625,51.936905],"type":"Point"}
}