{
  "type": "Feature",
  "properties": {
    "addr:full":"Pagodedreef 4 Utrecht Utrecht 3564 XS",
    "addr:housenumber":"4",
    "addr:postcode":"3564 xs",
    "addr:street":"Pagodedreef",
    "iso:country":"NL",
    "sg:address":"Pagodedreef 4",
    "sg:city":"Utrecht",
    "sg:orig_category":"Scholen Voor Basisonderwijs",
    "sg:phone":"+31 30 261 0616",
    "sg:postcode":"3564 XS",
    "sg:province":"Utrecht",
    "wof:name":"Johannes Rk",
    "wof:placetype":"venue"
},
  "geometry": {"coordinates":[5.10463,52.12719],"type":"Point"}
}