{
  "type": "Feature",
  "properties": {
    "addr:full":"Avestein 9 Oss Noord-Brabant 5346 TV",
    "addr:housenumber":"9",
    "addr:postcode":"5346 tv",
    "addr:street":"Avestein",
    "iso:country":"NL",
    "sg:address":"Avestein 9",
    "sg:city":"Oss",
    "sg:orig_category":"Pianostemmen En -Reparatie",
    "sg:phone":"+31 412 625 382",
    "sg:postcode":"5346 TV",
    "sg:province":"Noord-Brabant",
    "wof:name":"Ham-Ernst, Ingeborg V/D",
    "wof:placetype":"venue"
},
  "geometry": {"coordinates":[-91.21502700000001,44.578613],"type":"Point"}
}