{
  "type": "Feature",
  "properties": {
    "addr:full":"Kloosterstraat 6 Haarlem Noord-Holland 2021 VN",
    "addr:housenumber":"6",
    "addr:postcode":"2021 vn",
    "addr:street":"Kloosterstraat",
    "iso:country":"NL",
    "sg:address":"Kloosterstraat 6",
    "sg:city":"Haarlem",
    "sg:orig_category":"Wasserettes And Stomerijen",
    "sg:phone":"+31 23 525 7547",
    "sg:postcode":"2021 VN",
    "sg:province":"Noord-Holland",
    "wof:name":"Perfect",
    "wof:placetype":"venue"
},
  "geometry": {"coordinates":[4.6412391663,52.3942909241],"type":"Point"}
}