{
  "type": "Feature",
  "properties": {
    "addr:full":"Koningsstraat 10 Opheusden Gelderland 4043 JB",
    "addr:housenumber":"10",
    "addr:postcode":"4043 jb",
    "addr:street":"Koningsstraat;Gelderland",
    "iso:country":"NL",
    "sg:address":"Koningsstraat 10",
    "sg:city":"Opheusden",
    "sg:orig_category":"Goederenvervoer Over De Weg",
    "sg:phone":"+31 488 441 428",
    "sg:postcode":"4043 JB",
    "sg:province":"Gelderland",
    "wof:name":"Internat Transportbedrijf Gebroeders Jan",
    "wof:placetype":"venue"
},
  "geometry": {"coordinates":[5.635335,51.93568],"type":"Point"}
}