{
  "type": "Feature",
  "properties": {
    "iso:country":"NL",
    "sg:address":"Stadhouderskd 94",
    "sg:city":"Amsterdam",
    "sg:orig_category":"Kinderkleding",
    "sg:phone":"+31 20 662 3998",
    "sg:postcode":"1073 AV",
    "sg:province":"North Holland",
    "wof:name":"Bloomies",
    "wof:placetype":"venue"
},
  "geometry": {"coordinates":[4.8984,52.353001],"type":"Point"}
}