{
  "type": "Feature",
  "properties": {
    "addr:full":"Aar 375 Rotterdam South Holland 3068 HA",
    "addr:housenumber":"375",
    "addr:postcode":"3068 ha",
    "addr:street":"Aar",
    "iso:country":"NL",
    "sg:address":"Aar 375",
    "sg:city":"Rotterdam",
    "sg:classifiers":[
        {
            "category":"Education",
            "subcategory":"Preschool",
            "type":"Public Place"
        }
    ],
    "sg:phone":"+31 10 456 4984",
    "sg:postcode":"3068 HA",
    "sg:province":"South Holland",
    "sg:tags":[
        "kleuteronderwijs",
        "basis-"
    ],
    "wof:name":"De Vliedberg Rk",
    "wof:placetype":"venue"
},
  "geometry": {"coordinates":[4.568047,51.962997],"type":"Point"}
}