{
  "type": "Feature",
  "properties": {
    "addr:full":"Kykduinln 103 Tilburg Noord-Brabant 5045 PH",
    "addr:housenumber":"103",
    "addr:postcode":"5045",
    "addr:street":"Tilburg",
    "iso:country":"NL",
    "sg:address":"Kykduinln 103",
    "sg:city":"Tilburg",
    "sg:orig_category":"Administratie- En Boekhoudkantoren",
    "sg:phone":"+31 13 572 0459",
    "sg:postcode":"5045 PH",
    "sg:province":"Noord-Brabant",
    "wof:name":"Heuer",
    "wof:placetype":"venue"
},
  "geometry": {"coordinates":[4.98149,51.59214],"type":"Point"}
}