{
  "type": "Feature",
  "properties": {
    "addr:full":"Adm De Ruyterstr 1C Aalten Gelderland 7122 WD",
    "addr:housenumber":"1c",
    "addr:postcode":"7122",
    "addr:street":"Gelderland",
    "iso:country":"NL",
    "sg:address":"Adm De Ruyterstr 1C",
    "sg:city":"Aalten",
    "sg:orig_category":"Homeopathie",
    "sg:phone":"+31 6 23939555",
    "sg:postcode":"7122 WD",
    "sg:province":"Gelderland",
    "sg:website":"http://www.vitaalinbalans.com",
    "wof:name":"Vitaal In Balans",
    "wof:placetype":"venue"
},
  "geometry": {"coordinates":[6.57916,51.92429],"type":"Point"}
}