{
  "type": "Feature",
  "properties": {
    "addr:full":"Janskerkhof 15 Utrecht Utrecht 3512 BL",
    "addr:housenumber":"15",
    "addr:postcode":"3512 bl",
    "addr:street":"Janskerkhof",
    "iso:country":"NL",
    "sg:address":"Janskerkhof 15",
    "sg:city":"Utrecht",
    "sg:orig_category":"Makelaars En Adviseurs Onroerende Goederen",
    "sg:phone":"+31 30 231 4730",
    "sg:postcode":"3512 BL",
    "sg:province":"Utrecht",
    "wof:name":"Kestro Bv",
    "wof:placetype":"venue"
},
  "geometry": {"coordinates":[5.122262,52.093933],"type":"Point"}
}