{
  "type": "Feature",
  "properties": {
    "iso:country":"NL",
    "sg:address":"Mettenbrincklaan 9",
    "sg:city":"Barneveld",
    "sg:orig_category":"Bloemen And Planten Gh",
    "sg:phone":"+31 342 490 563",
    "sg:postcode":"3771 HX",
    "sg:province":"Gelderland",
    "wof:name":"G. Vlasman Groothandel In Potplanten",
    "wof:placetype":"venue"
},
  "geometry": {"coordinates":[5.586678,52.146927],"type":"Point"}
}