{
  "type": "Feature",
  "properties": {
    "iso:country":"NL",
    "sg:address":"Leeuwerik 30",
    "sg:city":"Venhuizen",
    "sg:orig_category":"Schilders",
    "sg:phone":"+31 6 53539746",
    "sg:postcode":"1606 CC",
    "sg:province":"Noord-Holland",
    "wof:name":"Laan, Gerard",
    "wof:placetype":"venue"
},
  "geometry": {"coordinates":[5.20586,52.664722],"type":"Point"}
}