{
  "type": "Feature",
  "properties": {
    "addr:full":"Eikbosserwg 240 Hilversum Noord-Holland 1213 SC",
    "addr:housenumber":"240",
    "addr:postcode":"hilversum;1213 sc",
    "iso:country":"NL",
    "sg:address":"Eikbosserwg 240",
    "sg:city":"Hilversum",
    "sg:classifiers":[
        {
            "category":"Retail",
            "subcategory":"Auto Repair",
            "type":"Services"
        }
    ],
    "sg:phone":"+31 35 623 2683",
    "sg:postcode":"1213 SC",
    "sg:province":"Noord-Holland",
    "sg:tags":[
        "garage"
    ],
    "wof:name":"Militant Autobedrijf",
    "wof:placetype":"venue"
},
  "geometry": {"coordinates":[5.173231,52.210289],"type":"Point"}
}