{
  "type": "Feature",
  "properties": {
    "iso:country":"NL",
    "sg:address":"Voorstraat 31",
    "sg:city":"Beesd",
    "sg:orig_category":"Kappers",
    "sg:phone":"+31 345 681 723",
    "sg:postcode":"4153 AH",
    "sg:province":"Gelderland",
    "wof:name":"Kapsalon Figaro",
    "wof:placetype":"venue"
},
  "geometry": {"coordinates":[5.1959052086,51.8846092224],"type":"Point"}
}