{
  "type": "Feature",
  "properties": {
    "addr:full":"Biltstr 83 Utrecht Utrecht 3572 AK",
    "addr:housenumber":"83",
    "addr:postcode":"3572 ak",
    "addr:street":"Biltstr",
    "iso:country":"NL",
    "sg:address":"Biltstr 83",
    "sg:city":"Utrecht",
    "sg:orig_category":"Broodjeszaken",
    "sg:phone":"+31 30 232 8211",
    "sg:postcode":"3572 AK",
    "sg:province":"Utrecht",
    "wof:name":"Broodje Van Koot",
    "wof:placetype":"venue"
},
  "geometry": {"coordinates":[5.130161,52.095184],"type":"Point"}
}