{
  "type": "Feature",
  "properties": {
    "addr:full":"Cereslaan 18 Heesch Noord-Brabant 5384 VT",
    "addr:housenumber":"18",
    "addr:postcode":"5384",
    "addr:street":"Cereslaan",
    "iso:country":"NL",
    "sg:address":"Cereslaan 18",
    "sg:city":"Heesch",
    "sg:classifiers":[
        {
            "category":"Fast Food",
            "type":"Food & Drink"
        }
    ],
    "sg:phone":"+31 412 456 232",
    "sg:postcode":"5384 VT",
    "sg:province":"Noord-Brabant",
    "sg:tags":[
        "afhaal",
        "restaurant"
    ],
    "wof:name":"Mcdonald'S Restaurant Mcdrive",
    "wof:placetype":"venue"
},
  "geometry": {"coordinates":[5.510195,51.734898],"type":"Point"}
}