{
  "type": "Feature",
  "properties": {
    "iso:country":"NL",
    "sg:address":"Lindegracht 1",
    "sg:city":"Heerenveen",
    "sg:classifiers":[
        {
            "category":"Retail",
            "subcategory":"Photofinishing",
            "type":"Services"
        }
    ],
    "sg:phone":"+31 513 628 360",
    "sg:postcode":"8441 GJ",
    "sg:province":"Friesland",
    "sg:tags":[
        "foto",
        "film"
    ],
    "wof:name":"Foto Haasdijk Heerenveen",
    "wof:placetype":"venue"
},
  "geometry": {"coordinates":[5.968742,52.950188],"type":"Point"}
}