{
  "type": "Feature",
  "properties": {
    "addr:full":"Topaasstr 14 Hengelo Ov Overijssel 7554 TH",
    "addr:housenumber":"14",
    "addr:postcode":"7554 th",
    "addr:street":"Topaasstr;Ov",
    "iso:country":"NL",
    "sg:address":"Topaasstr 14",
    "sg:city":"Hengelo Ov",
    "sg:orig_category":"Materiaalonderzoek",
    "sg:phone":"+31 74 291 0052",
    "sg:postcode":"7554 TH",
    "sg:province":"Overijssel",
    "wof:name":"R\u00f6ntgen Technische Dienst Bv",
    "wof:placetype":"venue"
},
  "geometry": {"coordinates":[6.777409,52.238911],"type":"Point"}
}