{
  "type": "Feature",
  "properties": {
    "addr:full":"Tweevoren 52 Nuenen Noord-Brabant 5672 SE",
    "addr:housenumber":"52",
    "addr:postcode":"5672 se",
    "addr:street":"Tweevoren",
    "iso:country":"NL",
    "sg:address":"Tweevoren 52",
    "sg:city":"Nuenen",
    "sg:orig_category":"Onderhoud And Reparatie Kantoorapparatuur",
    "sg:phone":"+31 40 290 6487",
    "sg:postcode":"5672 SE",
    "sg:province":"Noord-Brabant",
    "wof:name":"Maas Phd",
    "wof:placetype":"venue"
},
  "geometry": {"coordinates":[5.554975,51.462704],"type":"Point"}
}