{
  "type": "Feature",
  "properties": {
    "iso:country":"NL",
    "sg:address":"Sportln 6",
    "sg:city":"Tzum",
    "sg:orig_category":"Begraafplaatsen",
    "sg:phone":"+31 517 452 379",
    "sg:postcode":"8804 NP",
    "sg:province":"Provincie Friesland",
    "wof:name":"Begraafplaats",
    "wof:placetype":"venue"
},
  "geometry": {"coordinates":[5.562655,53.158768],"type":"Point"}
}