{
  "type": "Feature",
  "properties": {
    "addr:full":"Beatrixstr 46 Wolvega Provincie Friesland 8471 RL",
    "addr:housenumber":"46",
    "addr:postcode":"8471 rl",
    "addr:street":"Beatrixstr;Provincie Friesland",
    "iso:country":"NL",
    "sg:address":"Beatrixstr 46",
    "sg:city":"Wolvega",
    "sg:orig_category":"Autopoetsbedrijven",
    "sg:phone":"+31 561 616 693",
    "sg:postcode":"8471 RL",
    "sg:province":"Provincie Friesland",
    "wof:name":"Jong Autopoetsbedrijf, De",
    "wof:placetype":"venue"
},
  "geometry": {"coordinates":[5.994409,52.872837],"type":"Point"}
}