{
  "type": "Feature",
  "properties": {
    "iso:country":"NL",
    "sg:address":"Sassenstraat 45",
    "sg:city":"Zwolle",
    "sg:orig_category":"Kantoorartikelen",
    "sg:phone":"+31 38 421 6605",
    "sg:postcode":"8011 PB",
    "sg:province":"Overijssel",
    "wof:name":"Van Munster Kantoorboekhandel",
    "wof:placetype":"venue"
},
  "geometry": {"coordinates":[6.0955119133,52.5103416443],"type":"Point"}
}