{
  "type": "Feature",
  "properties": {
    "addr:full":"V L Stirumln 75 Naarden Noord-Holland 1411 BN",
    "addr:housenumber":"75",
    "addr:postcode":"1411 bn",
    "addr:street":"V",
    "iso:country":"NL",
    "sg:address":"V L Stirumln 75",
    "sg:city":"Naarden",
    "sg:orig_category":"Houtgroothandel",
    "sg:phone":"+31 35 694 4375",
    "sg:postcode":"1411 BN",
    "sg:province":"Noord-Holland",
    "wof:name":"Befeo",
    "wof:placetype":"venue"
},
  "geometry": {"coordinates":[5.161848,52.296371],"type":"Point"}
}