{
  "type": "Feature",
  "properties": {
    "addr:full":"Witte Paal 5 Schagen Noord-Holland 1742 NL",
    "addr:housenumber":"5",
    "addr:postcode":"1742 nl",
    "addr:street":"Witte Paal",
    "iso:country":"NL",
    "sg:address":"Witte Paal 5",
    "sg:city":"Schagen",
    "sg:orig_category":"Metaalwerken",
    "sg:phone":"+31 224 272 100",
    "sg:postcode":"1742 NL",
    "sg:province":"Noord-Holland",
    "wof:name":"Myresjo Nederland Bv",
    "wof:placetype":"venue"
},
  "geometry": {"coordinates":[4.807483,52.77985],"type":"Point"}
}