{
  "type": "Feature",
  "properties": {
    "addr:full":"Veldpoort 15A Swalmen Limburg 6071 JK",
    "addr:housenumber":"15a",
    "addr:postcode":"6071 jk",
    "addr:street":"Veldpoort",
    "iso:country":"NL",
    "sg:address":"Veldpoort 15A",
    "sg:city":"Swalmen",
    "sg:orig_category":"Verenigingen En Stichtingen",
    "sg:phone":"+31 475 503 054",
    "sg:postcode":"6071 JK",
    "sg:province":"Limburg",
    "wof:name":"Huurders Belangen Ver",
    "wof:placetype":"venue"
},
  "geometry": {"coordinates":[6.038059,51.233372],"type":"Point"}
}