{
  "type": "Feature",
  "properties": {
    "iso:country":"NL",
    "sg:address":"R Visscherln 4",
    "sg:city":"Zeist",
    "sg:orig_category":"Geluidsinstallaties - Verhuur",
    "sg:phone":"+31 6 15541399",
    "sg:postcode":"3705 SG",
    "sg:province":"Utrecht",
    "sg:website":"http://www.klompstra.nl/extreme",
    "wof:name":"Extreme Rental",
    "wof:placetype":"venue"
},
  "geometry": {"coordinates":[5.24387,52.08548],"type":"Point"}
}