{
  "type": "Feature",
  "properties": {
    "addr:full":"Gateweiden 1 Landgraaf Limburg 6373 JL",
    "addr:housenumber":"1",
    "addr:postcode":"6373 jl",
    "addr:street":"Gateweiden",
    "iso:country":"NL",
    "sg:address":"Gateweiden 1",
    "sg:city":"Landgraaf",
    "sg:orig_category":"Meubelzaken, Woning- And Keukeninrichting",
    "sg:phone":"+31 45 531 1932",
    "sg:postcode":"6373 JL",
    "sg:province":"Limburg",
    "wof:name":"A. Hanssen",
    "wof:placetype":"venue"
},
  "geometry": {"coordinates":[6.029047,50.905415],"type":"Point"}
}