{
  "type": "Feature",
  "properties": {
    "addr:full":"Koningsln 17 Utrecht Utrecht 3583 GD",
    "addr:housenumber":"17",
    "addr:postcode":"3583 gd",
    "addr:street":"Koningsln",
    "iso:country":"NL",
    "sg:address":"Koningsln 17",
    "sg:city":"Utrecht",
    "sg:orig_category":"Architecten En Architectenbureaus",
    "sg:phone":"+31 30 251 4588",
    "sg:postcode":"3583 GD",
    "sg:province":"Utrecht",
    "wof:name":"Berger, P",
    "wof:placetype":"venue"
},
  "geometry": {"coordinates":[5.14208,52.089878],"type":"Point"}
}