{
  "type": "Feature",
  "properties": {
    "iso:country":"NL",
    "sg:address":"Achter Oventje 5",
    "sg:city":"Zeeland",
    "sg:classifiers":[
        {
            "category":"Travel",
            "subcategory":"Hotels & Motels",
            "type":"Entertainment"
        }
    ],
    "sg:phone":"+31 486 451 753",
    "sg:postcode":"5411 NM",
    "sg:province":"North Brabant",
    "wof:name":"Boerderij",
    "wof:placetype":"venue"
},
  "geometry": {"coordinates":[5.680031,51.678719],"type":"Point"}
}