{
  "type": "Feature",
  "properties": {
    "iso:country":"NL",
    "sg:address":"Voorerf 41",
    "sg:city":"Breda",
    "sg:orig_category":"Verpakkingsmachines",
    "sg:phone":"+31 76 541 4068",
    "sg:postcode":"4824 GM",
    "sg:province":"Noord-Brabant",
    "wof:name":"Globetech Bv",
    "wof:placetype":"venue"
},
  "geometry": {"coordinates":[4.752648,51.613472],"type":"Point"}
}