{
  "type": "Feature",
  "properties": {
    "addr:full":"Kruiseind 45 Gemert North Brabant 5421 NB",
    "addr:housenumber":"45",
    "addr:postcode":"5421 nb",
    "addr:street":"Kruiseind",
    "iso:country":"NL",
    "sg:address":"Kruiseind 45",
    "sg:city":"Gemert",
    "sg:orig_category":"Meubelzaken, Woning- And Keukeninrichting",
    "sg:phone":"+31 492 361 423",
    "sg:postcode":"5421 NB",
    "sg:province":"North Brabant",
    "wof:name":"Rijkers Slaaprijk Meubelen Bv",
    "wof:placetype":"venue"
},
  "geometry": {"coordinates":[5.680858,51.559952],"type":"Point"}
}