{
  "type": "Feature",
  "properties": {
    "addr:full":"Ln V Luxemburg 4 Roosendaal Noord-Brabant 4701 CB",
    "addr:housenumber":"4",
    "addr:postcode":"4701 cb",
    "addr:street":"Ln;Luxemburg",
    "iso:country":"NL",
    "sg:address":"Ln V Luxemburg 4",
    "sg:city":"Roosendaal",
    "sg:orig_category":"Scholen Voor Basisonderwijs",
    "sg:phone":"+31 165 570 950",
    "sg:postcode":"4701 CB",
    "sg:province":"Noord-Brabant",
    "wof:name":"St Jan Rk School",
    "wof:placetype":"venue"
},
  "geometry": {"coordinates":[4.45767,51.531403],"type":"Point"}
}