{
  "type": "Feature",
  "properties": {
    "addr:full":"V Musschenb Str 1A Amsterdam North Holland 1091 GD",
    "addr:housenumber":"1a",
    "addr:postcode":"1091 gd",
    "addr:street":"Str",
    "iso:country":"NL",
    "sg:address":"V Musschenb Str 1A",
    "sg:city":"Amsterdam",
    "sg:orig_category":"Vertaalbureaus",
    "sg:phone":"+31 20 463 6828",
    "sg:postcode":"1091 GD",
    "sg:province":"North Holland",
    "wof:name":"Arabesk Net",
    "wof:placetype":"venue"
},
  "geometry": {"coordinates":[4.9130601883,52.3548698425],"type":"Point"}
}