{
  "type": "Feature",
  "properties": {
    "addr:full":"Meropestraat 16 Hoek Van Holland South Holland 3151 JL",
    "addr:housenumber":"16",
    "addr:postcode":"3151 jl",
    "addr:street":"Meropestraat",
    "iso:country":"NL",
    "sg:address":"Meropestraat 16",
    "sg:city":"Hoek Van Holland",
    "sg:orig_category":"Alternatieve Geneeskunde",
    "sg:phone":"+31 174 382 101",
    "sg:postcode":"3151 JL",
    "sg:province":"South Holland",
    "wof:name":"G.M. Seijdel-Vlietstra",
    "wof:placetype":"venue"
},
  "geometry": {"coordinates":[4.138145,51.980881],"type":"Point"}
}