{
  "type": "Feature",
  "properties": {
    "addr:full":"Stationspln 9 Groningen Groningen 9726 AE",
    "addr:housenumber":"9",
    "addr:postcode":"9726 ae",
    "addr:street":"Stationspln",
    "iso:country":"NL",
    "sg:address":"Stationspln 9",
    "sg:city":"Groningen",
    "sg:orig_category":"Pensioenen",
    "sg:phone":"+31 50 582 1821",
    "sg:postcode":"9726 AE",
    "sg:province":"Groningen",
    "wof:name":"Tpg Kpn",
    "wof:placetype":"venue"
},
  "geometry": {"coordinates":[6.563556,53.211681],"type":"Point"}
}