{
  "type": "Feature",
  "properties": {
    "addr:full":"Postbus 22147 Rotterdam 3003 DC",
    "addr:housenumber":"22147",
    "addr:postcode":"3003",
    "addr:street":"Postbus",
    "iso:country":"NL",
    "sg:address":"Postbus 22147",
    "sg:city":"Rotterdam",
    "sg:orig_category":"Scholen Voor Basisonderwijs",
    "sg:phone":"+31 10 412 6573",
    "sg:postcode":"3003 DC",
    "wof:name":"Vier Leeuwen Openb, De",
    "wof:placetype":"venue"
},
  "geometry": {"coordinates":[4.47842,51.92289],"type":"Point"}
}