{
  "type": "Feature",
  "properties": {
    "addr:full":"Akerstraat Noord 224 Hoensbroek Limburg 6431 HT",
    "addr:housenumber":"224",
    "addr:postcode":"6431 ht",
    "addr:street":"Akerstraat Noord",
    "iso:country":"NL",
    "sg:address":"Akerstraat Noord 224",
    "sg:city":"Hoensbroek",
    "sg:orig_category":"Meubelzaken, Woning- And Keukeninrichting",
    "sg:phone":"+31 45 522 8232",
    "sg:postcode":"6431 HT",
    "sg:province":"Limburg",
    "wof:name":"Desta",
    "wof:placetype":"venue"
},
  "geometry": {"coordinates":[5.939953,50.927662],"type":"Point"}
}