{
  "type": "Feature",
  "properties": {
    "addr:full":"Stobbeln 18 Vroomshoop Overijssel 7681 ZN",
    "addr:housenumber":"18",
    "addr:postcode":"7681 zn",
    "addr:street":"Stobbeln",
    "iso:country":"NL",
    "sg:address":"Stobbeln 18",
    "sg:city":"Vroomshoop",
    "sg:orig_category":"Verenigingen En Stichtingen",
    "sg:phone":"+31 546 641 028",
    "sg:postcode":"7681 ZN",
    "sg:province":"Overijssel",
    "wof:name":"Luchtsport, Postduivenver De",
    "wof:placetype":"venue"
},
  "geometry": {"coordinates":[6.57085,52.476582],"type":"Point"}
}