{
  "type": "Feature",
  "properties": {
    "addr:full":"Copernicusstraat 49 Amsterdam North Holland 1098 JE",
    "addr:housenumber":"49",
    "addr:postcode":"1098 je",
    "addr:street":"Copernicusstraat",
    "iso:country":"NL",
    "sg:address":"Copernicusstraat 49",
    "sg:city":"Amsterdam",
    "sg:classifiers":[
        {
            "category":"Fast Food",
            "type":"Food & Drink"
        }
    ],
    "sg:phone":"+31 20 665 7845",
    "sg:postcode":"1098 JE",
    "sg:province":"North Holland",
    "sg:tags":[
        "afhaal",
        "restaurant"
    ],
    "wof:name":"Theo",
    "wof:placetype":"venue"
},
  "geometry": {"coordinates":[4.937764,52.355286],"type":"Point"}
}