{
  "type": "Feature",
  "properties": {
    "addr:full":"Jagerspad 28 Landgraaf Limburg 6374 CZ",
    "addr:housenumber":"28",
    "addr:postcode":"6374",
    "addr:street":"Jagerspad",
    "iso:country":"NL",
    "sg:address":"Jagerspad 28",
    "sg:city":"Landgraaf",
    "sg:orig_category":"Juridische Adviseurs",
    "sg:phone":"+31 45 531 2949",
    "sg:postcode":"6374 CZ",
    "sg:province":"Limburg",
    "wof:name":"Gillissen, Mr J F M",
    "wof:placetype":"venue"
},
  "geometry": {"coordinates":[6.034395,50.921749],"type":"Point"}
}