{
  "type": "Feature",
  "properties": {
    "iso:country":"NL",
    "sg:address":"Bosln 81",
    "sg:city":"Dronten",
    "sg:orig_category":"Schippers",
    "sg:phone":"+31 321 313 920",
    "sg:postcode":"8253 AH",
    "sg:province":"Flevoland",
    "wof:name":"C",
    "wof:placetype":"venue"
},
  "geometry": {"coordinates":[5.70501,52.53508],"type":"Point"}
}