{
  "type": "Feature",
  "properties": {
    "addr:full":"Stadhoudersln 1 Oostburg Zeeland 4501 KE",
    "addr:housenumber":"1",
    "addr:postcode":"4501 ke",
    "addr:street":"Stadhoudersln",
    "iso:country":"NL",
    "sg:address":"Stadhoudersln 1",
    "sg:city":"Oostburg",
    "sg:orig_category":"Scholen Voor Algemeen Voortgezet Onderwijs",
    "sg:phone":"+31 117 455 151",
    "sg:postcode":"4501 KE",
    "sg:province":"Zeeland",
    "wof:name":"Roc Westerschelde",
    "wof:placetype":"venue"
},
  "geometry": {"coordinates":[3.489277,51.325771],"type":"Point"}
}