{
  "type": "Feature",
  "properties": {
    "addr:full":"Mahlerlaan 10 Naarden Noord-Holland 1411 HW",
    "addr:housenumber":"10",
    "addr:postcode":"1411 hw",
    "addr:street":"Mahlerlaan",
    "iso:country":"NL",
    "sg:address":"Mahlerlaan 10",
    "sg:city":"Naarden",
    "sg:orig_category":"Vertaal- And Tolkenbureaus",
    "sg:phone":"+31 35 695 3559",
    "sg:postcode":"1411 HW",
    "sg:province":"Noord-Holland",
    "wof:name":"Allure Translation",
    "wof:placetype":"venue"
},
  "geometry": {"coordinates":[5.174098,52.289692],"type":"Point"}
}