{
  "type": "Feature",
  "properties": {
    "addr:full":"Mauritsweg 20 Rotterdam South Holland 3012 JR",
    "addr:housenumber":"20",
    "addr:postcode":"3012 jr",
    "addr:street":"Mauritsweg",
    "iso:country":"NL",
    "sg:address":"Mauritsweg 20",
    "sg:city":"Rotterdam",
    "sg:orig_category":"Hulpverlening Sociaal",
    "sg:phone":"+31 10 412 8734",
    "sg:postcode":"3012 JR",
    "sg:province":"South Holland",
    "wof:name":"Adriaans Sticht, Nico",
    "wof:placetype":"venue"
},
  "geometry": {"coordinates":[4.472337,51.919991],"type":"Point"}
}