{
  "type": "Feature",
  "properties": {
    "addr:full":"Orion 3 Lisse North Holland 2163 AJ",
    "addr:housenumber":"3",
    "addr:postcode":"2163 aj",
    "addr:street":"Orion",
    "iso:country":"NL",
    "sg:address":"Orion 3",
    "sg:city":"Lisse",
    "sg:orig_category":"Plafonds",
    "sg:phone":"+31 252 411 209",
    "sg:postcode":"2163 AJ",
    "sg:province":"North Holland",
    "wof:name":"Scheurwater, R",
    "wof:placetype":"venue"
},
  "geometry": {"coordinates":[4.56377,52.265388],"type":"Point"}
}