{
  "type": "Feature",
  "properties": {
    "addr:full":"Schoolstraat 41 Twello Gelderland 7391 DA",
    "addr:housenumber":"41",
    "addr:postcode":"7391 da",
    "addr:street":"Schoolstraat;Gelderland",
    "iso:country":"NL",
    "sg:address":"Schoolstraat 41",
    "sg:city":"Twello",
    "sg:orig_category":"Apothekers",
    "sg:phone":"+31 571 271 771",
    "sg:postcode":"7391 DA",
    "sg:province":"Gelderland",
    "wof:name":"Apotheek Twello",
    "wof:placetype":"venue"
},
  "geometry": {"coordinates":[6.105045,52.237],"type":"Point"}
}