{
  "type": "Feature",
  "properties": {
    "addr:full":"Osdorperwg 187 Amsterdam North Holland 1069 LL",
    "addr:housenumber":"187",
    "addr:postcode":"1069 ll",
    "iso:country":"NL",
    "sg:address":"Osdorperwg 187",
    "sg:city":"Amsterdam",
    "sg:orig_category":"Autoschade- Herstelbedrijven",
    "sg:phone":"+31 6 26026167",
    "sg:postcode":"1069 LL",
    "sg:province":"North Holland",
    "wof:name":"Groot, R De",
    "wof:placetype":"venue"
},
  "geometry": {"coordinates":[4.794539,52.347633],"type":"Point"}
}