{
  "type": "Feature",
  "properties": {
    "iso:country":"NL",
    "sg:address":"H De Grootln 30",
    "sg:city":"Weesp",
    "sg:orig_category":"Bejaarden - Verzorgingstehuizen",
    "sg:phone":"+31 294 239 670",
    "sg:postcode":"1381 DE",
    "sg:province":"Noord-Holland",
    "wof:name":"Oversingel",
    "wof:placetype":"venue"
},
  "geometry": {"coordinates":[5.03828,52.308315],"type":"Point"}
}