{
  "type": "Feature",
  "properties": {
    "addr:full":"Keulschevaart 10 Breukelen Ut Utrecht 3621 MX",
    "addr:housenumber":"10",
    "addr:postcode":"3621 mx",
    "addr:street":"Keulschevaart",
    "iso:country":"NL",
    "sg:address":"Keulschevaart 10",
    "sg:city":"Breukelen Ut",
    "sg:orig_category":"Goederenvervoer Over De Weg",
    "sg:phone":"+31 346 259 200",
    "sg:postcode":"3621 MX",
    "sg:province":"Utrecht",
    "wof:name":"Paper Logistics Bv",
    "wof:placetype":"venue"
},
  "geometry": {"coordinates":[4.992924,52.162582],"type":"Point"}
}