{
  "type": "Feature",
  "properties": {
    "addr:full":"N Beetsstr 140 Amsterdam Noord-Holland 1054 XV",
    "addr:housenumber":"140",
    "addr:postcode":"1054 xv",
    "addr:street":"N",
    "iso:country":"NL",
    "sg:address":"N Beetsstr 140",
    "sg:city":"Amsterdam",
    "sg:orig_category":"Verhuizingen",
    "sg:phone":"+31 20 618 2901",
    "sg:postcode":"1054 XV",
    "sg:province":"Noord-Holland",
    "wof:name":"Soelen En Zn'S, J C Van",
    "wof:placetype":"venue"
},
  "geometry": {"coordinates":[4.867577,52.362221],"type":"Point"}
}