{
  "type": "Feature",
  "properties": {
    "addr:full":"Stationswg 73C Ede Gld Gelderland 6711 PL",
    "addr:housenumber":"73c;6711",
    "addr:postcode":"pl",
    "addr:street":"Stationswg;Gld Gelderland",
    "iso:country":"NL",
    "sg:address":"Stationswg 73C",
    "sg:city":"Ede Gld",
    "sg:orig_category":"Adviesbureaus Bedrijfsorganisatie",
    "sg:phone":"+31 318 613 623",
    "sg:postcode":"6711 PL",
    "sg:province":"Gelderland",
    "wof:name":"Circle Bv",
    "wof:placetype":"venue"
},
  "geometry": {"coordinates":[5.669747,52.035305],"type":"Point"}
}