{
  "type": "Feature",
  "properties": {
    "addr:full":"Winkelhof 60-62 Leiderdorp Zuid-Holland 2353 TV",
    "addr:postcode":"60-62 leiderdorp;2353 tv",
    "addr:street":"Winkelhof",
    "iso:country":"NL",
    "sg:address":"Winkelhof 60-62",
    "sg:city":"Leiderdorp",
    "sg:orig_category":"Schoonheidsinstituten",
    "sg:phone":"+31 71 542 1260",
    "sg:postcode":"2353 TV",
    "sg:province":"Zuid-Holland",
    "wof:name":"Shiseido, Schoonheidssalon",
    "wof:placetype":"venue"
},
  "geometry": {"coordinates":[4.531841,52.16267],"type":"Point"}
}