{
  "type": "Feature",
  "properties": {
    "addr:full":"Voorstr 142 Roosendaal Noord-Brabant 4702 EV",
    "addr:housenumber":"142",
    "iso:country":"NL",
    "sg:address":"Voorstr 142",
    "sg:city":"Roosendaal",
    "sg:orig_category":"Geluidsinstallaties - Verhuur",
    "sg:phone":"+31 165 545 727",
    "sg:postcode":"4702 EV",
    "sg:province":"Noord-Brabant",
    "wof:name":"Amw Geluid & Licht Verhuur",
    "wof:placetype":"venue"
},
  "geometry": {"coordinates":[4.473689,51.531338],"type":"Point"}
}