{
  "type": "Feature",
  "properties": {
    "iso:country":"NL",
    "sg:address":"Kofschipstraat 11",
    "sg:city":"Alkmaar",
    "sg:classifiers":[
        {
            "category":"Education",
            "subcategory":"Preschool",
            "type":"Public Place"
        }
    ],
    "sg:phone":"+31 72 561 4660",
    "sg:postcode":"1826 CG",
    "sg:province":"North Holland",
    "sg:tags":[
        "kleuteronderwijs",
        "basis-"
    ],
    "wof:name":"Het Kompas",
    "wof:placetype":"venue"
},
  "geometry": {"coordinates":[4.763646,52.653019],"type":"Point"}
}