{
  "type": "Feature",
  "properties": {
    "addr:full":"Bloemstraat 9 Ijmuiden North Holland 1975 EM",
    "addr:housenumber":"9",
    "addr:postcode":"1975 em",
    "addr:street":"Bloemstraat",
    "iso:country":"NL",
    "sg:address":"Bloemstraat 9",
    "sg:city":"Ijmuiden",
    "sg:orig_category":"Boekhouders",
    "sg:phone":"+31 255 536 596",
    "sg:postcode":"1975 EM",
    "sg:province":"North Holland",
    "wof:name":"El Ro Administraties",
    "wof:placetype":"venue"
},
  "geometry": {"coordinates":[4.594842,52.461224],"type":"Point"}
}