{
  "type": "Feature",
  "properties": {
    "addr:full":"Paramaribowg 77 Apeldoorn Gelderland 7333 PA",
    "addr:housenumber":"77",
    "addr:postcode":"7333",
    "addr:street":"Paramaribowg;Gelderland",
    "iso:country":"NL",
    "sg:address":"Paramaribowg 77",
    "sg:city":"Apeldoorn",
    "sg:orig_category":"Bedrijfsmechanisatie En -Automatisering",
    "sg:phone":"+31 55 599 8844",
    "sg:postcode":"7333 PA",
    "sg:province":"Gelderland",
    "wof:name":"Tomra Systems Bv",
    "wof:placetype":"venue"
},
  "geometry": {"coordinates":[5.979706,52.177601],"type":"Point"}
}