{
  "type": "Feature",
  "properties": {
    "iso:country":"NL",
    "sg:address":"S Bikostr 304",
    "sg:city":"Utrecht",
    "sg:orig_category":"Modevakscholen",
    "sg:phone":"+31 30 272 0268",
    "sg:postcode":"3573 BH",
    "sg:province":"Utrecht",
    "wof:name":"Ploeg, B Van Der",
    "wof:placetype":"venue"
},
  "geometry": {"coordinates":[5.146313,52.110783],"type":"Point"}
}