{
  "type": "Feature",
  "properties": {
    "addr:full":"Rietveldenwg 16 S Hertogenbosch Noord-Brabant 5222 AR",
    "addr:housenumber":"16",
    "addr:postcode":"5222",
    "addr:street":"Rietveldenwg;S",
    "iso:country":"NL",
    "sg:address":"Rietveldenwg 16",
    "sg:city":"S Hertogenbosch",
    "sg:orig_category":"Loopbaanbegeleiding",
    "sg:phone":"+31 73 645 0408",
    "sg:postcode":"5222 AR",
    "sg:province":"Noord-Brabant",
    "wof:name":"Aob-Compaz",
    "wof:placetype":"venue"
},
  "geometry": {"coordinates":[5.283304,51.69677],"type":"Point"}
}