{
  "type": "Feature",
  "properties": {
    "addr:full":"Kerkstr 38 Doesburg Gelderland 6981 CN",
    "addr:housenumber":"38",
    "addr:postcode":"6981 cn",
    "addr:street":"Kerkstr;Gelderland",
    "iso:country":"NL",
    "sg:address":"Kerkstr 38",
    "sg:city":"Doesburg",
    "sg:orig_category":"Opticiens",
    "sg:phone":"+31 313 472 282",
    "sg:postcode":"6981 CN",
    "sg:province":"Gelderland",
    "wof:name":"Teunissen",
    "wof:placetype":"venue"
},
  "geometry": {"coordinates":[6.1350989342,52.0137901306],"type":"Point"}
}