{
  "type": "Feature",
  "properties": {
    "addr:full":"Grotestraat 246 Waalwijk Noord-Brabant 5141 HE",
    "addr:housenumber":"246",
    "addr:postcode":"5141 he",
    "addr:street":"Grotestraat",
    "iso:country":"NL",
    "sg:address":"Grotestraat 246",
    "sg:city":"Waalwijk",
    "sg:orig_category":"Biljart- And Snookerzalen",
    "sg:phone":"+31 416 344 019",
    "sg:postcode":"5141 HE",
    "sg:province":"Noord-Brabant",
    "wof:name":"Grand Cafe Marquis Bv",
    "wof:placetype":"venue"
},
  "geometry": {"coordinates":[5.069185,51.690578],"type":"Point"}
}