{
  "type": "Feature",
  "properties": {
    "addr:full":"Terra Cottapln 22 Maastricht Limburg 6216 BJ",
    "addr:housenumber":"22",
    "addr:postcode":"6216 bj",
    "iso:country":"NL",
    "sg:address":"Terra Cottapln 22",
    "sg:city":"Maastricht",
    "sg:orig_category":"Behangselpapier En Wandbekleding",
    "sg:phone":"+31 43 347 8851",
    "sg:postcode":"6216 BJ",
    "sg:province":"Limburg",
    "wof:name":"Bartels",
    "wof:placetype":"venue"
},
  "geometry": {"coordinates":[5.659089,50.851643],"type":"Point"}
}