{
  "type": "Feature",
  "properties": {
    "addr:full":"Dorpsstr 1 Oisterwyk Noord-Brabant 5061 HH",
    "addr:housenumber":"1",
    "addr:postcode":"5061 hh",
    "addr:street":"Dorpsstr",
    "iso:country":"NL",
    "sg:address":"Dorpsstr 1",
    "sg:city":"Oisterwyk",
    "sg:orig_category":"Cafetaria'S",
    "sg:phone":"+31 13 528 2540",
    "sg:postcode":"5061 HH",
    "sg:province":"Noord-Brabant",
    "wof:name":"Graft Bv",
    "wof:placetype":"venue"
},
  "geometry": {"coordinates":[5.192108,51.580433],"type":"Point"}
}