{
  "type": "Feature",
  "properties": {
    "addr:full":"Stationswg 107 Ede Gld Gelderland 6711 PN",
    "addr:housenumber":"107",
    "addr:postcode":"6711 pn",
    "addr:street":"Gld Gelderland",
    "iso:country":"NL",
    "sg:address":"Stationswg 107",
    "sg:city":"Ede Gld",
    "sg:orig_category":"Kappers",
    "sg:phone":"+31 318 614 494",
    "sg:postcode":"6711 PN",
    "sg:province":"Gelderland",
    "wof:name":"Paats, D",
    "wof:placetype":"venue"
},
  "geometry": {"coordinates":[5.671087,52.030869],"type":"Point"}
}