{
  "type": "Feature",
  "properties": {
    "addr:full":"Eenhoornplnts 5 Oostburg Zeeland 4501 CL",
    "addr:housenumber":"5",
    "addr:postcode":"4501",
    "addr:street":"Eenhoornplnts",
    "iso:country":"NL",
    "sg:address":"Eenhoornplnts 5",
    "sg:city":"Oostburg",
    "sg:orig_category":"Handenarbeid",
    "sg:phone":"+31 117 455 363",
    "sg:postcode":"4501 CL",
    "sg:province":"Zeeland",
    "wof:name":"Stulpje Van Liselotte, Het",
    "wof:placetype":"venue"
},
  "geometry": {"coordinates":[3.489277,51.325771],"type":"Point"}
}