{
  "type": "Feature",
  "properties": {
    "addr:full":"Dorpsw 97 Schellinkhout Noord-Holland 1697 KG",
    "addr:housenumber":"97",
    "addr:postcode":"1697 kg",
    "addr:street":"Dorpsw",
    "iso:country":"NL",
    "sg:address":"Dorpsw 97",
    "sg:city":"Schellinkhout",
    "sg:orig_category":"Verzekeringen - Verzekeringskantoren",
    "sg:phone":"+31 229 501 251",
    "sg:postcode":"1697 KG",
    "sg:province":"Noord-Holland",
    "wof:name":"Mol, J W",
    "wof:placetype":"venue"
},
  "geometry": {"coordinates":[5.12144,52.635487],"type":"Point"}
}