{
  "type": "Feature",
  "properties": {
    "iso:country":"NL",
    "sg:address":"Huibevendreef 20",
    "sg:city":"Tilburg",
    "sg:orig_category":"Sportverenigingen En Ontspannings- Verenigingen",
    "sg:phone":"+31 13 571 2747",
    "sg:postcode":"5043 EW",
    "sg:province":"Noord-Brabant",
    "wof:name":"Heyhoef Tennisver, Tc",
    "wof:placetype":"venue"
},
  "geometry": {"coordinates":[5.008561,51.577332],"type":"Point"}
}