{
  "type": "Feature",
  "properties": {
    "addr:full":"Huibevendreef 20 Tilburg Noord-Brabant 5043 EW",
    "addr:housenumber":"20",
    "addr:postcode":"5043 ew",
    "addr:street":"Huibevendreef",
    "iso:country":"NL",
    "sg:address":"Huibevendreef 20",
    "sg:city":"Tilburg",
    "sg:orig_category":"Sportverenigingen En Ontspannings- Verenigingen",
    "sg:phone":"+31 13 571 2747",
    "sg:postcode":"5043 EW",
    "sg:province":"Noord-Brabant",
    "wof:name":"Heyhoef Tennisver, Tc",
    "wof:placetype":"venue"
},
  "geometry": {"coordinates":[5.008561,51.577332],"type":"Point"}
}