{
  "type": "Feature",
  "properties": {
    "iso:country":"NL",
    "sg:address":"Burg Klauckelaan 4",
    "sg:city":"Appingedam",
    "sg:orig_category":"Kinderopvang Behalve Thuis",
    "sg:phone":"+31 596 626 805",
    "sg:postcode":"9902 KZ",
    "sg:province":"Groningen",
    "wof:name":"Mkd De Dompeldiek",
    "wof:placetype":"venue"
},
  "geometry": {"coordinates":[6.859981,53.3162],"type":"Point"}
}