{
  "type": "Feature",
  "properties": {
    "addr:full":"Markt 4 Prinsenbeek North Brabant 4841 AC",
    "addr:housenumber":"4",
    "addr:postcode":"4841 ac",
    "addr:street":"Markt",
    "iso:country":"NL",
    "sg:address":"Markt 4",
    "sg:city":"Prinsenbeek",
    "sg:orig_category":"Cafetaria'S",
    "sg:phone":"+31 76 541 2262",
    "sg:postcode":"4841 AC",
    "sg:province":"North Brabant",
    "wof:name":"Kavelaars",
    "wof:placetype":"venue"
},
  "geometry": {"coordinates":[4.718187,51.599689],"type":"Point"}
}