{
  "type": "Feature",
  "properties": {
    "addr:full":"Arena 121 S Hertogenbosch Noord-Brabant 5211 XT",
    "addr:housenumber":"121",
    "addr:postcode":"5211 xt",
    "addr:street":"Arena;S Hertogenbosch",
    "iso:country":"NL",
    "sg:address":"Arena 121",
    "sg:city":"S Hertogenbosch",
    "sg:orig_category":"Bloemen En Planten",
    "sg:phone":"+31 73 614 6297",
    "sg:postcode":"5211 XT",
    "sg:province":"Noord-Brabant",
    "wof:name":"Sleutjes, Ger",
    "wof:placetype":"venue"
},
  "geometry": {"coordinates":[5.3038,51.690269],"type":"Point"}
}