{
  "type": "Feature",
  "properties": {
    "iso:country":"NL",
    "sg:address":"Van Linschotenstraat 3",
    "sg:city":"Valkenswaard",
    "sg:orig_category":"Verzekeringen",
    "sg:phone":"+31 40 201 4887",
    "sg:postcode":"5554 PM",
    "sg:province":"North Brabant",
    "wof:name":"Assurantien Sallaerts",
    "wof:placetype":"venue"
},
  "geometry": {"coordinates":[5.445383,51.34964],"type":"Point"}
}