{
  "type": "Feature",
  "properties": {
    "addr:full":"Van Linschotenstraat 3 Valkenswaard North Brabant 5554 PM",
    "addr:housenumber":"3",
    "addr:postcode":"5554 pm",
    "addr:street":"Van Linschotenstraat",
    "iso:country":"NL",
    "sg:address":"Van Linschotenstraat 3",
    "sg:city":"Valkenswaard",
    "sg:orig_category":"Verzekeringen",
    "sg:phone":"+31 40 201 4887",
    "sg:postcode":"5554 PM",
    "sg:province":"North Brabant",
    "wof:name":"Assurantien Sallaerts",
    "wof:placetype":"venue"
},
  "geometry": {"coordinates":[5.445383,51.34964],"type":"Point"}
}