{
  "type": "Feature",
  "properties": {
    "addr:full":"Middel Broekweg 68 Honselersdijk Zuid-Holland 2675 KD",
    "addr:housenumber":"68",
    "addr:postcode":"2675 kd",
    "addr:street":"Middel Broekweg",
    "iso:country":"NL",
    "sg:address":"Middel Broekweg 68",
    "sg:city":"Honselersdijk",
    "sg:orig_category":"Bloemen And Planten",
    "sg:phone":"+31 174 624 063",
    "sg:postcode":"2675 KD",
    "sg:province":"Zuid-Holland",
    "wof:name":"Gebroeders Valstar",
    "wof:placetype":"venue"
},
  "geometry": {"coordinates":[4.233228,51.999538],"type":"Point"}
}