{
  "type": "Feature",
  "properties": {
    "addr:full":"De Dam 15 Leek Groningen 9351 AL",
    "addr:housenumber":"15",
    "addr:postcode":"9351 al",
    "addr:street":"De Dam",
    "iso:country":"NL",
    "sg:address":"De Dam 15",
    "sg:city":"Leek",
    "sg:classifiers":[
        {
            "category":"Food & Beverages",
            "subcategory":"Fruits & Vegetables",
            "type":"Retail Goods"
        }
    ],
    "sg:phone":"+31 594 512 180",
    "sg:postcode":"9351 AL",
    "sg:province":"Groningen",
    "sg:tags":[
        "en",
        "groenten"
    ],
    "wof:name":"Velde, Fa Van De",
    "wof:placetype":"venue"
},
  "geometry": {"coordinates":[6.391503,53.162121],"type":"Point"}
}