{
  "type": "Feature",
  "properties": {
    "addr:full":"Kerkwg 8 Wognum North Holland 1687 PJ",
    "addr:housenumber":"8",
    "addr:postcode":"1687 pj",
    "addr:street":"Kerkwg",
    "iso:country":"NL",
    "sg:address":"Kerkwg 8",
    "sg:city":"Wognum",
    "sg:orig_category":"Fietsen En Bromfietsen",
    "sg:phone":"+31 229 572 341",
    "sg:postcode":"1687 PJ",
    "sg:province":"North Holland",
    "sg:website":"http://www.bankras.nl",
    "wof:name":"Bankras",
    "wof:placetype":"venue"
},
  "geometry": {"coordinates":[5.017414,52.685799],"type":"Point"}
}