{
  "type": "Feature",
  "properties": {
    "addr:full":"Lange Blokweg 52 Zierikzee Zeeland 4301 NZ",
    "addr:housenumber":"52",
    "addr:postcode":"4301 nz",
    "addr:street":"Lange Blokweg",
    "iso:country":"NL",
    "sg:address":"Lange Blokweg 52",
    "sg:city":"Zierikzee",
    "sg:orig_category":"Levende Dieren Gh",
    "sg:phone":"+31 111 481 246",
    "sg:postcode":"4301 NZ",
    "sg:province":"Zeeland",
    "wof:name":"J. Van Zuidland",
    "wof:placetype":"venue"
},
  "geometry": {"coordinates":[3.922364,51.658463],"type":"Point"}
}