{
  "type": "Feature",
  "properties": {
    "addr:full":"Wittevrouwensngl 34 Utrecht Utrecht 3581 GC",
    "addr:housenumber":"34",
    "addr:postcode":"3581 gc",
    "addr:street":"Wittevrouwensngl",
    "iso:country":"NL",
    "sg:address":"Wittevrouwensngl 34",
    "sg:city":"Utrecht",
    "sg:orig_category":"Psychotherapeuten",
    "sg:phone":"+31 30 230 0547",
    "sg:postcode":"3581 GC",
    "sg:province":"Utrecht",
    "wof:name":"Prakt V Gestalt En Psychosynthese",
    "wof:placetype":"venue"
},
  "geometry": {"coordinates":[5.127314,52.094414],"type":"Point"}
}