{
  "type": "Feature",
  "properties": {
    "iso:country":"NL",
    "sg:address":"G J Van Heekstraat 99",
    "sg:city":"Enschede",
    "sg:orig_category":"Wasserettes And Stomerijen",
    "sg:phone":"+31 53 433 3480",
    "sg:postcode":"7521 EB",
    "sg:province":"NL.08",
    "wof:name":"Roeloffzen En Co. Textielverzorging Bv",
    "wof:placetype":"venue"
},
  "geometry": {"coordinates":[6.8662481308,52.2277336121],"type":"Point"}
}