{
  "type": "Feature",
  "properties": {
    "iso:country":"NL",
    "sg:address":"Dorpsstr 20",
    "sg:city":"Aarle Rixtel",
    "sg:orig_category":"Opticiens",
    "sg:phone":"+31 492 386 078",
    "sg:postcode":"5735 ED",
    "sg:province":"Noord-Brabant",
    "wof:name":"Vorst, P Van Der",
    "wof:placetype":"venue"
},
  "geometry": {"coordinates":[5.639149189,51.5099372864],"type":"Point"}
}