{
  "type": "Feature",
  "properties": {
    "addr:full":"Julialaantje 38 Rijswijk Zh Zuid-Holland 2283 TB",
    "addr:housenumber":"38",
    "addr:postcode":"zh;2283 tb",
    "addr:street":"Julialaantje",
    "iso:country":"NL",
    "sg:address":"Julialaantje 38",
    "sg:city":"Rijswijk Zh",
    "sg:orig_category":"Bejaardeninstellingen And Serviceflats",
    "sg:phone":"+31 70 307 1444",
    "sg:postcode":"2283 TB",
    "sg:province":"Zuid-Holland",
    "wof:name":"Stichting Zorginstellingen Rijswijk Huize Westhoff",
    "wof:placetype":"venue"
},
  "geometry": {"coordinates":[4.319091,52.050976],"type":"Point"}
}