{
  "type": "Feature",
  "properties": {
    "addr:full":"Roskamstr 5 Almelo Overijssel 7602 JX",
    "addr:housenumber":"5",
    "addr:postcode":"7602 jx",
    "addr:street":"Roskamstr",
    "iso:country":"NL",
    "sg:address":"Roskamstr 5",
    "sg:city":"Almelo",
    "sg:orig_category":"Kappers",
    "sg:phone":"+31 546 499 055",
    "sg:postcode":"7602 JX",
    "sg:province":"Overijssel",
    "wof:name":"Buurstede",
    "wof:placetype":"venue"
},
  "geometry": {"coordinates":[6.6699280739,52.3667945862],"type":"Point"}
}