{
  "type": "Feature",
  "properties": {
    "addr:full":"Leeuwerikstr 23 Drachten Provincie Friesland 9203 BR",
    "addr:housenumber":"23",
    "addr:postcode":"9203 br",
    "addr:street":"Leeuwerikstr;Provincie Friesland",
    "iso:country":"NL",
    "sg:address":"Leeuwerikstr 23",
    "sg:city":"Drachten",
    "sg:orig_category":"Oldtimers",
    "sg:phone":"+31 512 532 298",
    "sg:postcode":"9203 BR",
    "sg:province":"Provincie Friesland",
    "wof:name":"Meter, Gerrit",
    "wof:placetype":"venue"
},
  "geometry": {"coordinates":[6.105108,53.109135],"type":"Point"}
}