{
  "type": "Feature",
  "properties": {
    "addr:full":"Wydaustr 31 Middelburg Zeeland 4337 VD",
    "addr:housenumber":"31",
    "addr:postcode":"4337 vd",
    "addr:street":"Wydaustr",
    "iso:country":"NL",
    "sg:address":"Wydaustr 31",
    "sg:city":"Middelburg",
    "sg:orig_category":"Vertaalbureaus",
    "sg:phone":"+31 118 641 919",
    "sg:postcode":"4337 VD",
    "sg:province":"Zeeland",
    "sg:website":"http://www.kalliope.nl",
    "wof:name":"Kalliope Uw Tekstbureau",
    "wof:placetype":"venue"
},
  "geometry": {"coordinates":[3.632309,51.490677],"type":"Point"}
}