{
  "type": "Feature",
  "properties": {
    "addr:full":"Mesdagpln 34 Baarn Utrecht 3741 SM",
    "addr:housenumber":"34",
    "addr:postcode":"3741 sm",
    "addr:street":"Mesdagpln",
    "iso:country":"NL",
    "sg:address":"Mesdagpln 34",
    "sg:city":"Baarn",
    "sg:orig_category":"Meubelen",
    "sg:phone":"+31 35 541 3030",
    "sg:postcode":"3741 SM",
    "sg:province":"Utrecht",
    "wof:name":"Gerritse, A",
    "wof:placetype":"venue"
},
  "geometry": {"coordinates":[5.292226,52.217136],"type":"Point"}
}