{
  "type": "Feature",
  "properties": {
    "addr:full":"Statendaalder 1 Leiderdorp Zuid-Holland 2353 TH",
    "addr:housenumber":"1",
    "addr:postcode":"2353 th",
    "addr:street":"Statendaalder",
    "iso:country":"NL",
    "sg:address":"Statendaalder 1",
    "sg:city":"Leiderdorp",
    "sg:orig_category":"Overheidsdiensten",
    "sg:phone":"+31 71 545 8500",
    "sg:postcode":"2353 TH",
    "sg:province":"Zuid-Holland",
    "wof:name":"Gemeente Leiderdorp",
    "wof:placetype":"venue"
},
  "geometry": {"coordinates":[4.5328841209,52.162109375],"type":"Point"}
}