{
  "type": "Feature",
  "properties": {
    "addr:full":"Pypersdk 4 De Koog North Holland 1796 MJ",
    "addr:housenumber":"4",
    "addr:postcode":"1796 mj",
    "addr:street":"Pypersdk",
    "iso:country":"NL",
    "sg:address":"Pypersdk 4",
    "sg:city":"De Koog",
    "sg:orig_category":"Vakantieverblijven",
    "sg:phone":"+31 222 327 202",
    "sg:postcode":"1796 MJ",
    "sg:province":"North Holland",
    "sg:website":"http://www.frissebries.nl",
    "wof:name":"Frisse Bries",
    "wof:placetype":"venue"
},
  "geometry": {"coordinates":[4.776518,53.08886],"type":"Point"}
}