{
  "type": "Feature",
  "properties": {
    "addr:full":"Lithsedijk 13 Lith Florida 5397 EA",
    "addr:housenumber":"13",
    "addr:postcode":"5397 ea",
    "addr:street":"Lithsedijk",
    "iso:country":"NL",
    "sg:address":"Lithsedijk 13",
    "sg:city":"Lith",
    "sg:classifiers":[
        {
            "category":"Retail",
            "subcategory":"Photofinishing",
            "type":"Services"
        }
    ],
    "sg:phone":"+31 412 481 532",
    "sg:postcode":"5397 EA",
    "sg:province":"Florida",
    "sg:tags":[
        "foto",
        "film"
    ],
    "wof:name":"Videotheek Frens",
    "wof:placetype":"venue"
},
  "geometry": {"coordinates":[-82.170288,27.862659],"type":"Point"}
}