{
  "type": "Feature",
  "properties": {
    "addr:full":"Goudsbloemln 50 S Gravenhage Zuid-Holland 2565 CT",
    "addr:housenumber":"50;gravenhage",
    "addr:postcode":"2565 ct",
    "addr:street":"Goudsbloemln;S",
    "iso:country":"NL",
    "sg:address":"Goudsbloemln 50",
    "sg:city":"S Gravenhage",
    "sg:orig_category":"Fotoreportages",
    "sg:phone":"+31 6 50524290",
    "sg:postcode":"2565 CT",
    "sg:province":"Zuid-Holland",
    "wof:name":"Leeuwen, Brenda Van",
    "wof:placetype":"venue"
},
  "geometry": {"coordinates":[4.26129,52.076382],"type":"Point"}
}