{
  "type": "Feature",
  "properties": {
    "addr:full":"Prins Hendrikstraat 21 Raamsdonksveer Noord-Brabant 4941 JT",
    "addr:housenumber":"21",
    "addr:postcode":"4941 jt",
    "addr:street":"Prins Hendrikstraat",
    "iso:country":"NL",
    "sg:address":"Prins Hendrikstraat 21",
    "sg:city":"Raamsdonksveer",
    "sg:orig_category":"Autokeuringen",
    "sg:phone":"+31 162 516 206",
    "sg:postcode":"4941 JT",
    "sg:province":"Noord-Brabant",
    "wof:name":"C. Boezer",
    "wof:placetype":"venue"
},
  "geometry": {"coordinates":[4.875874,51.697109],"type":"Point"}
}