{
  "type": "Feature",
  "properties": {
    "addr:full":"K Onneswg 62 Hilversum Noord-Holland 1223 JL",
    "addr:housenumber":"62",
    "addr:postcode":"1223 jl",
    "addr:street":"Onneswg",
    "iso:country":"NL",
    "sg:address":"K Onneswg 62",
    "sg:city":"Hilversum",
    "sg:orig_category":"Onderhoudswerken",
    "sg:phone":"+31 6 15058208",
    "sg:postcode":"1223 JL",
    "sg:province":"Noord-Holland",
    "wof:name":"Nederend, Lennard Van Het",
    "wof:placetype":"venue"
},
  "geometry": {"coordinates":[5.20301,52.22831],"type":"Point"}
}