{
  "type": "Feature",
  "properties": {
    "addr:full":"Hanzestr 68 Arnhem Gelderland 6826 MN",
    "addr:housenumber":"68",
    "addr:postcode":"6826 mn",
    "addr:street":"Hanzestr",
    "iso:country":"NL",
    "sg:address":"Hanzestr 68",
    "sg:city":"Arnhem",
    "sg:classifiers":[
        {
            "category":"Food & Beverages",
            "subcategory":"Bakery",
            "type":"Retail Goods"
        }
    ],
    "sg:phone":"+31 26 361 3912",
    "sg:postcode":"6826 MN",
    "sg:province":"Gelderland",
    "sg:tags":[
        "brood",
        "en",
        "banket"
    ],
    "sg:website":"http://www.bakkerbart.nl",
    "wof:name":"Bart",
    "wof:placetype":"venue"
},
  "geometry": {"coordinates":[5.950495,51.982857],"type":"Point"}
}