{
  "type": "Feature",
  "properties": {
    "addr:full":"Nieuwstraat 26 Maassluis Zuid-Holland 3141 AA",
    "addr:housenumber":"26",
    "addr:postcode":"3141 aa",
    "addr:street":"Nieuwstraat",
    "iso:country":"NL",
    "sg:address":"Nieuwstraat 26",
    "sg:city":"Maassluis",
    "sg:orig_category":"Boekhandels",
    "sg:phone":"+31 10 591 3521",
    "sg:postcode":"3141 AA",
    "sg:province":"Zuid-Holland",
    "wof:name":"Joco",
    "wof:placetype":"venue"
},
  "geometry": {"coordinates":[4.254497,51.921001],"type":"Point"}
}