{
  "type": "Feature",
  "properties": {
    "addr:full":"Noorderstr 116 Sappemeer Groningen 9611 AN",
    "addr:housenumber":"116",
    "addr:postcode":"9611 an",
    "iso:country":"NL",
    "sg:address":"Noorderstr 116",
    "sg:city":"Sappemeer",
    "sg:orig_category":"Autoschade- Herstelbedrijven",
    "sg:phone":"+31 598 393 242",
    "sg:postcode":"9611 AN",
    "sg:province":"Groningen",
    "wof:name":"Heide, Van Der",
    "wof:placetype":"venue"
},
  "geometry": {"coordinates":[6.780988,53.163818],"type":"Point"}
}