{
  "type": "Feature",
  "properties": {
    "addr:full":"Dalemstraat 56 Gorinchem Zuid-Holland 4201 BR",
    "addr:housenumber":"56",
    "addr:postcode":"4201 br",
    "addr:street":"Dalemstraat",
    "iso:country":"NL",
    "sg:address":"Dalemstraat 56",
    "sg:city":"Gorinchem",
    "sg:orig_category":"Fotostudio'S And Fotografen",
    "sg:phone":"+31 183 635 627",
    "sg:postcode":"4201 BR",
    "sg:province":"Zuid-Holland",
    "wof:name":"Van Goethem",
    "wof:placetype":"venue"
},
  "geometry": {"coordinates":[4.97956,51.828625],"type":"Point"}
}