{
  "type": "Feature",
  "properties": {
    "addr:full":"Faberstraat 9 Dieren Gelderland 6951 BJ",
    "addr:housenumber":"9",
    "addr:postcode":"6951 bj",
    "addr:street":"Faberstraat;Gelderland",
    "iso:country":"NL",
    "sg:address":"Faberstraat 9",
    "sg:city":"Dieren",
    "sg:orig_category":"Verhuur Audiovisuele Apparatuur",
    "sg:phone":"+31 313 450 445",
    "sg:postcode":"6951 BJ",
    "sg:province":"Gelderland",
    "wof:name":"Backwood Music",
    "wof:placetype":"venue"
},
  "geometry": {"coordinates":[6.099092,52.049862],"type":"Point"}
}