{
  "type": "Feature",
  "properties": {
    "addr:full":"Gaardendreef 23 Amersfoort Utrecht 3824 AT",
    "addr:housenumber":"23",
    "addr:postcode":"3824",
    "addr:street":"Gaardendreef",
    "iso:country":"NL",
    "sg:address":"Gaardendreef 23",
    "sg:city":"Amersfoort",
    "sg:orig_category":"Boekhouders",
    "sg:phone":"+31 33 455 2646",
    "sg:postcode":"3824 AT",
    "sg:province":"Utrecht",
    "wof:name":"Administratie En Adviesbureau Context",
    "wof:placetype":"venue"
},
  "geometry": {"coordinates":[5.370015,52.197422],"type":"Point"}
}