{
  "type": "Feature",
  "properties": {
    "addr:full":"Maritzstraat 20 Vaassen Gelderland 8172 CB",
    "addr:housenumber":"20",
    "addr:postcode":"8172 cb",
    "addr:street":"Maritzstraat;Gelderland",
    "iso:country":"NL",
    "sg:address":"Maritzstraat 20",
    "sg:city":"Vaassen",
    "sg:orig_category":"Verhuur Huishoudartikelen",
    "sg:phone":"+31 578 571 768",
    "sg:postcode":"8172 CB",
    "sg:province":"Gelderland",
    "wof:name":"H. De Weerd",
    "wof:placetype":"venue"
},
  "geometry": {"coordinates":[5.952979,52.282288],"type":"Point"}
}