{
  "type": "Feature",
  "properties": {
    "iso:country":"NL",
    "sg:address":"Kloppersakker 2",
    "sg:city":"Zaltbommel",
    "sg:orig_category":"Adviesbureaus",
    "sg:phone":"+31 418 684 758",
    "sg:postcode":"5301 ZV",
    "sg:province":"Gelderland",
    "wof:name":"Toja",
    "wof:placetype":"venue"
},
  "geometry": {"coordinates":[5.234648,51.80085],"type":"Point"}
}