{
  "type": "Feature",
  "properties": {
    "addr:full":"Kloppersakker 2 Zaltbommel Gelderland 5301 ZV",
    "addr:housenumber":"2",
    "addr:postcode":"5301 zv",
    "addr:street":"Kloppersakker;Gelderland",
    "iso:country":"NL",
    "sg:address":"Kloppersakker 2",
    "sg:city":"Zaltbommel",
    "sg:orig_category":"Adviesbureaus",
    "sg:phone":"+31 418 684 758",
    "sg:postcode":"5301 ZV",
    "sg:province":"Gelderland",
    "wof:name":"Toja",
    "wof:placetype":"venue"
},
  "geometry": {"coordinates":[5.234648,51.80085],"type":"Point"}
}