{
  "type": "Feature",
  "properties": {
    "addr:full":"Kerkstr 44 Loon Op Zand North Brabant 5175 BB",
    "addr:housenumber":"44",
    "addr:postcode":"5175 bb",
    "addr:street":"Kerkstr",
    "iso:country":"NL",
    "sg:address":"Kerkstr 44",
    "sg:city":"Loon Op Zand",
    "sg:orig_category":"Fietsen En Bromfietsen",
    "sg:phone":"+31 416 361 322",
    "sg:postcode":"5175 BB",
    "sg:province":"North Brabant",
    "wof:name":"Rekreatief",
    "wof:placetype":"venue"
},
  "geometry": {"coordinates":[5.076348,51.627399],"type":"Point"}
}