{
  "type": "Feature",
  "properties": {
    "addr:full":"Loosduinsewg 637 S Gravenhage Zuid-Holland 2571 AK",
    "addr:housenumber":"637;gravenhage",
    "addr:postcode":"2571 ak",
    "addr:street":"S",
    "iso:country":"NL",
    "sg:address":"Loosduinsewg 637",
    "sg:city":"S Gravenhage",
    "sg:orig_category":"Centrale Verwarming - Groothandel",
    "sg:phone":"+31 70 360 2924",
    "sg:postcode":"2571 AK",
    "sg:province":"Zuid-Holland",
    "wof:name":"Verploegen",
    "wof:placetype":"venue"
},
  "geometry": {"coordinates":[4.29037,52.06884],"type":"Point"}
}