{
  "type": "Feature",
  "properties": {
    "addr:full":"Buurtweg 16 Den Haag Zuid-Holland 2585 AK",
    "addr:housenumber":"16",
    "addr:postcode":"2585 ak",
    "addr:street":"Buurtweg",
    "iso:country":"NL",
    "sg:address":"Buurtweg 16",
    "sg:city":"Den Haag",
    "sg:orig_category":"Werving And Selectie Van Tijdelijk Personeel And Uitzendkantoren",
    "sg:phone":"+31 70 361 4188",
    "sg:postcode":"2585 AK",
    "sg:province":"Zuid-Holland",
    "wof:name":"Direkt Uitzendburo Bv",
    "wof:placetype":"venue"
},
  "geometry": {"coordinates":[4.2977700233,52.0947990417],"type":"Point"}
}