{
  "type": "Feature",
  "properties": {
    "addr:full":"Rembrandtpln 17-3 Amsterdam Noord-Holland 1017 CT",
    "addr:housenumber":"17-3",
    "addr:postcode":"1017 ct",
    "iso:country":"NL",
    "sg:address":"Rembrandtpln 17-3",
    "sg:city":"Amsterdam",
    "sg:orig_category":"Omroep",
    "sg:phone":"+31 20 555 0555",
    "sg:postcode":"1017 CT",
    "sg:province":"Noord-Holland",
    "wof:name":"Mtnl-Multiculturele Televisie Nederland",
    "wof:placetype":"venue"
},
  "geometry": {"coordinates":[4.897004,52.366394],"type":"Point"}
}