{
  "type": "Feature",
  "properties": {
    "iso:country":"NL",
    "sg:address":"Damrak 93",
    "sg:city":"Amsterdam",
    "sg:classifiers":[
        {
            "category":"Travel",
            "subcategory":"Hotels & Motels",
            "type":"Entertainment"
        }
    ],
    "sg:phone":"+31 20 555 0666",
    "sg:postcode":"1012 LP",
    "sg:province":"Noord-Holland",
    "sg:website":"http://www.hotelamsterdam.nl",
    "wof:name":"Amsterdam",
    "wof:placetype":"venue"
},
  "geometry": {"coordinates":[4.893598,52.373783],"type":"Point"}
}