{
  "type": "Feature",
  "properties": {
    "addr:full":"Deylerwg 177 Wassenaar South Holland 2241 AE",
    "addr:housenumber":"177",
    "addr:postcode":"2241 ae",
    "iso:country":"NL",
    "sg:address":"Deylerwg 177",
    "sg:city":"Wassenaar",
    "sg:orig_category":"Onroerende Goederen",
    "sg:phone":"+31 70 514 0855",
    "sg:postcode":"2241 AE",
    "sg:province":"South Holland",
    "wof:name":"Rademakers Bv, B",
    "wof:placetype":"venue"
},
  "geometry": {"coordinates":[4.423265,52.14761],"type":"Point"}
}