{
  "type": "Feature",
  "properties": {
    "addr:full":"Rykswg 179 Malden Gelderland 6581 EK",
    "addr:housenumber":"179",
    "addr:postcode":"6581 ek",
    "addr:street":"Gelderland",
    "iso:country":"NL",
    "sg:address":"Rykswg 179",
    "sg:city":"Malden",
    "sg:orig_category":"Kinderopvang",
    "sg:phone":"+31 24 358 0815",
    "sg:postcode":"6581 EK",
    "sg:province":"Gelderland",
    "wof:name":"Infantes Fortunae",
    "wof:placetype":"venue"
},
  "geometry": {"coordinates":[5.854767,51.779118],"type":"Point"}
}