{
  "type": "Feature",
  "properties": {
    "iso:country":"NL",
    "sg:address":"Binnenbaan 38",
    "sg:city":"Rhoon",
    "sg:orig_category":"Partycatering And -Organisatie",
    "sg:phone":"+31 10 501 0999",
    "sg:postcode":"3161 VB",
    "sg:province":"South Holland",
    "wof:name":"Fresh Partners Bv",
    "wof:placetype":"venue"
},
  "geometry": {"coordinates":[4.432732,51.859329],"type":"Point"}
}