{
  "type": "Feature",
  "properties": {
    "addr:full":"Blokmoeren 18 Breda North Brabant 4824 JN",
    "addr:housenumber":"18",
    "addr:postcode":"4824 jn",
    "addr:street":"Blokmoeren",
    "iso:country":"NL",
    "sg:address":"Blokmoeren 18",
    "sg:city":"Breda",
    "sg:classifiers":[
        {
            "category":"Education",
            "subcategory":"Preschool",
            "type":"Public Place"
        }
    ],
    "sg:phone":"+31 76 542 3846",
    "sg:postcode":"4824 JN",
    "sg:province":"North Brabant",
    "sg:tags":[
        "kleuteronderwijs",
        "basis-"
    ],
    "wof:name":"Kbs De Werft",
    "wof:placetype":"venue"
},
  "geometry": {"coordinates":[4.743616,51.613762],"type":"Point"}
}