{
  "type": "Feature",
  "properties": {
    "addr:full":"Abraham Kuyperpark 171 Nieuwegein Utrecht 3437 JD",
    "addr:housenumber":"171",
    "addr:postcode":"3437 jd",
    "addr:street":"Abraham Kuyperpark",
    "iso:country":"NL",
    "sg:address":"Abraham Kuyperpark 171",
    "sg:city":"Nieuwegein",
    "sg:orig_category":"Kinderopvang Behalve Thuis",
    "sg:phone":"+31 30 605 5333",
    "sg:postcode":"3437 JD",
    "sg:province":"Utrecht",
    "wof:name":"Kinderdagverblijf Brummi",
    "wof:placetype":"venue"
},
  "geometry": {"coordinates":[5.080047,52.054012],"type":"Point"}
}