{
  "type": "Feature",
  "properties": {
    "addr:full":"Liguster 20 Leidschendam Zuid-Holland 2262 AC",
    "addr:housenumber":"20",
    "addr:postcode":"2262 ac",
    "addr:street":"Liguster",
    "iso:country":"NL",
    "sg:address":"Liguster 20",
    "sg:city":"Leidschendam",
    "sg:orig_category":"Banken",
    "sg:phone":"+31 70 317 4174",
    "sg:postcode":"2262 AC",
    "sg:province":"Zuid-Holland",
    "sg:website":"http://www.rabobank.nl",
    "wof:name":"Rabobank",
    "wof:placetype":"venue"
},
  "geometry": {"coordinates":[4.385227,52.088413],"type":"Point"}
}