{
  "type": "Feature",
  "properties": {
    "addr:full":"Wilhelminapk 24 Breda Noord-Brabant 4818 SM",
    "addr:housenumber":"24",
    "addr:postcode":"4818 sm",
    "addr:street":"Wilhelminapk",
    "iso:country":"NL",
    "sg:address":"Wilhelminapk 24",
    "sg:city":"Breda",
    "sg:orig_category":"Accountants - Administratie- Consulenten En -Kantoren",
    "sg:phone":"+31 76 522 1905",
    "sg:postcode":"4818 SM",
    "sg:province":"Noord-Brabant",
    "sg:website":"http://www.vaa.nl",
    "wof:name":"Vos Zomer & Partners",
    "wof:placetype":"venue"
},
  "geometry": {"coordinates":[4.782657,51.58028],"type":"Point"}
}