{
  "type": "Feature",
  "properties": {
    "addr:full":"Kl Berg 79 Eindhoven Noord-Brabant 5611 JT",
    "addr:housenumber":"79",
    "addr:postcode":"5611 jt",
    "addr:street":"Kl Berg",
    "iso:country":"NL",
    "sg:address":"Kl Berg 79",
    "sg:city":"Eindhoven",
    "sg:orig_category":"Kappers",
    "sg:phone":"+31 40 246 7530",
    "sg:postcode":"5611 JT",
    "sg:province":"Noord-Brabant",
    "wof:name":"Nessiv",
    "wof:placetype":"venue"
},
  "geometry": {"coordinates":[5.484105,51.434471],"type":"Point"}
}