{
  "type": "Feature",
  "properties": {
    "addr:full":"Dorpsstraat 26 Renswoude Utrecht 3927 BD",
    "addr:housenumber":"26",
    "addr:postcode":"3927 bd",
    "addr:street":"Dorpsstraat",
    "iso:country":"NL",
    "sg:address":"Dorpsstraat 26",
    "sg:city":"Renswoude",
    "sg:orig_category":"Schilderwerk",
    "sg:phone":"+31 318 571 329",
    "sg:postcode":"3927 BD",
    "sg:province":"Utrecht",
    "wof:name":"W J Brunt",
    "wof:placetype":"venue"
},
  "geometry": {"coordinates":[5.545181,52.07254],"type":"Point"}
}