{
  "type": "Feature",
  "properties": {
    "addr:full":"Jonge Voolwg 16 Wormerveer Noord-Holland 1521 RJ",
    "addr:housenumber":"16",
    "addr:postcode":"1521 rj",
    "iso:country":"NL",
    "sg:address":"Jonge Voolwg 16",
    "sg:city":"Wormerveer",
    "sg:orig_category":"Loodgieters",
    "sg:phone":"+31 75 628 6525",
    "sg:postcode":"1521 RJ",
    "sg:province":"Noord-Holland",
    "wof:name":"Boer, De",
    "wof:placetype":"venue"
},
  "geometry": {"coordinates":[4.782314,52.507256],"type":"Point"}
}