{
  "type": "Feature",
  "properties": {
    "addr:full":"Dierenseln 114 S Gravenhage Zuid-Holland 2573 KK",
    "addr:housenumber":"114;gravenhage",
    "addr:postcode":"2573 kk",
    "addr:street":"S",
    "iso:country":"NL",
    "sg:address":"Dierenseln 114",
    "sg:city":"S Gravenhage",
    "sg:orig_category":"Fotozaken",
    "sg:phone":"+31 70 356 3017",
    "sg:postcode":"2573 KK",
    "sg:province":"Zuid-Holland",
    "wof:name":"Quick & Sharp",
    "wof:placetype":"venue"
},
  "geometry": {"coordinates":[4.2844,52.064911],"type":"Point"}
}