{
  "type": "Feature",
  "properties": {
    "iso:country":"NL",
    "sg:address":"Welplaatwg 30",
    "sg:city":"Botlek Rt",
    "sg:orig_category":"Petrochemische Producten",
    "sg:phone":"+31 10 490 1800",
    "sg:postcode":"3197 KS",
    "sg:province":"Zuid-Holland",
    "wof:name":"Carbon Black Ned Bv",
    "wof:placetype":"venue"
},
  "geometry": {"coordinates":[4.285139,51.881321],"type":"Point"}
}