{
  "type": "Feature",
  "properties": {
    "addr:full":"Zwart Janstr 8 Rotterdam Zuid-Holland 3035 AS",
    "addr:housenumber":"8",
    "addr:postcode":"3035 as",
    "addr:street":"Janstr",
    "iso:country":"NL",
    "sg:address":"Zwart Janstr 8",
    "sg:city":"Rotterdam",
    "sg:orig_category":"Opticiens",
    "sg:phone":"+31 10 467 5397",
    "sg:postcode":"3035 AS",
    "sg:province":"Zuid-Holland",
    "wof:name":"Pearle",
    "wof:placetype":"venue"
},
  "geometry": {"coordinates":[4.4804258347,51.9323501587],"type":"Point"}
}