{
  "type": "Feature",
  "properties": {
    "addr:full":"Tikspad 2 Den Ham Ov Overijssel 7683 BT",
    "addr:housenumber":"2",
    "addr:postcode":"ov;7683 bt",
    "addr:street":"Tikspad",
    "iso:country":"NL",
    "sg:address":"Tikspad 2",
    "sg:city":"Den Ham Ov",
    "sg:orig_category":"Zuivelproducten",
    "sg:phone":"+31 546 671 368",
    "sg:postcode":"7683 BT",
    "sg:province":"Overijssel",
    "wof:name":"R Abma",
    "wof:placetype":"venue"
},
  "geometry": {"coordinates":[6.496274,52.462387],"type":"Point"}
}