{
  "type": "Feature",
  "properties": {
    "addr:full":"Beemdstr 5 Eindhoven Noord-Brabant 5653 MA",
    "addr:housenumber":"5",
    "addr:postcode":"5653 ma",
    "addr:street":"Beemdstr",
    "iso:country":"NL",
    "sg:address":"Beemdstr 5",
    "sg:city":"Eindhoven",
    "sg:orig_category":"Accountants - Administratie- Consulenten En -Kantoren",
    "sg:phone":"+31 40 212 5300",
    "sg:postcode":"5653 MA",
    "sg:province":"Noord-Brabant",
    "sg:website":"http://www.plasa.nl",
    "wof:name":"Plasa Groep",
    "wof:placetype":"venue"
},
  "geometry": {"coordinates":[5.451413,51.43037],"type":"Point"}
}