{
  "type": "Feature",
  "properties": {
    "iso:country":"NL",
    "sg:address":"Citroenvlinderstr 16",
    "sg:city":"Veenendaal",
    "sg:orig_category":"Kunststoffen- Verwerkende Industrie",
    "sg:phone":"+31 318 551 616",
    "sg:postcode":"3905 KK",
    "sg:province":"Utrecht",
    "wof:name":"Bma",
    "wof:placetype":"venue"
},
  "geometry": {"coordinates":[5.561416,52.0368],"type":"Point"}
}