{
  "type": "Feature",
  "properties": {
    "addr:full":"Steenstraat 9 Arnhem Gelderland 6828 CA",
    "addr:housenumber":"9",
    "addr:postcode":"6828 ca",
    "addr:street":"Steenstraat",
    "iso:country":"NL",
    "sg:address":"Steenstraat 9",
    "sg:city":"Arnhem",
    "sg:orig_category":"Verlichting And Huishoudartikelen",
    "sg:phone":"+31 26 442 2885",
    "sg:postcode":"6828 CA",
    "sg:province":"Gelderland",
    "wof:name":"T Binnenhuis Arnhem Bv",
    "wof:placetype":"venue"
},
  "geometry": {"coordinates":[5.914847,51.983601],"type":"Point"}
}