{
  "type": "Feature",
  "properties": {
    "iso:country":"NL",
    "sg:address":"Kr Nering 12",
    "sg:city":"Heerjansdam",
    "sg:orig_category":"Babyartikelen",
    "sg:phone":"+31 78 677 1588",
    "sg:postcode":"2995 BH",
    "sg:province":"Zuid-Holland",
    "wof:name":"Nicoline",
    "wof:placetype":"venue"
},
  "geometry": {"coordinates":[4.564294,51.83588],"type":"Point"}
}