{
  "type": "Feature",
  "properties": {
    "addr:full":"Gravin Sabinastraat 36 Zuid-Beijerland Zuid-Holland 3284 AP",
    "addr:housenumber":"36",
    "addr:postcode":"3284 ap",
    "addr:street":"Gravin Sabinastraat",
    "iso:country":"NL",
    "sg:address":"Gravin Sabinastraat 36",
    "sg:city":"Zuid-Beijerland",
    "sg:orig_category":"Verlichting And Huishoudartikelen",
    "sg:phone":"+31 186 661 320",
    "sg:postcode":"3284 AP",
    "sg:province":"Zuid-Holland",
    "wof:name":"A. Sint-Nieklaas",
    "wof:placetype":"venue"
},
  "geometry": {"coordinates":[4.366197,51.750488],"type":"Point"}
}