{
  "type": "Feature",
  "properties": {
    "addr:full":"Postbus 8817 Eindhoven Noord-Brabant 5605 LV",
    "addr:housenumber":"8817",
    "addr:postcode":"5605",
    "addr:street":"Postbus",
    "iso:country":"NL",
    "sg:address":"Postbus 8817",
    "sg:city":"Eindhoven",
    "sg:orig_category":"Koeriersdiensten",
    "sg:phone":"+31 40 291 0525",
    "sg:postcode":"5605 LV",
    "sg:province":"Noord-Brabant",
    "wof:name":"Efficient Logistics",
    "wof:placetype":"venue"
},
  "geometry": {"coordinates":[5.48016,51.437061],"type":"Point"}
}