{
  "type": "Feature",
  "properties": {
    "addr:full":"Heerenwg 212A Heiloo Noord-Holland 1851 KZ",
    "addr:housenumber":"212a",
    "addr:postcode":"1851 kz",
    "iso:country":"NL",
    "sg:address":"Heerenwg 212A",
    "sg:city":"Heiloo",
    "sg:orig_category":"Administratie- En Boekhoudkantoren",
    "sg:phone":"+31 72 533 9419",
    "sg:postcode":"1851 KZ",
    "sg:province":"Noord-Holland",
    "wof:name":"Bosma, B",
    "wof:placetype":"venue"
},
  "geometry": {"coordinates":[4.6989150047,52.5970993042],"type":"Point"}
}