{
  "type": "Feature",
  "properties": {
    "addr:full":"Kemphaanstr 15 Wormer North Holland 1531 VA",
    "addr:housenumber":"15",
    "addr:postcode":"1531",
    "addr:street":"Kemphaanstr",
    "iso:country":"NL",
    "sg:address":"Kemphaanstr 15",
    "sg:city":"Wormer",
    "sg:orig_category":"Verpakkingsmachines",
    "sg:phone":"+31 75 621 9596",
    "sg:postcode":"1531 VA",
    "sg:province":"North Holland",
    "wof:name":"Synchro-Pak",
    "wof:placetype":"venue"
},
  "geometry": {"coordinates":[4.80974,52.499413],"type":"Point"}
}