{
  "type": "Feature",
  "properties": {
    "addr:full":"Nw Crooswyksewg 27A Rotterdam Zuid-Holland 3034 PL",
    "addr:housenumber":"27a",
    "addr:postcode":"3034 pl",
    "iso:country":"NL",
    "sg:address":"Nw Crooswyksewg 27A",
    "sg:city":"Rotterdam",
    "sg:orig_category":"Oud Metaal",
    "sg:phone":"+31 6 41668658",
    "sg:postcode":"3034 PL",
    "sg:province":"Zuid-Holland",
    "wof:name":"Terlouw",
    "wof:placetype":"venue"
},
  "geometry": {"coordinates":[4.4977741241,51.9358253479],"type":"Point"}
}