{
  "type": "Feature",
  "properties": {
    "addr:full":"Prinsesselaan 51 Sommelsdijk Zuid-Holland 3245 XN",
    "addr:housenumber":"51",
    "addr:postcode":"3245 xn",
    "addr:street":"Prinsesselaan",
    "iso:country":"NL",
    "sg:address":"Prinsesselaan 51",
    "sg:city":"Sommelsdijk",
    "sg:orig_category":"Bejaardeninstellingen And Serviceflats",
    "sg:phone":"+31 187 488 300",
    "sg:postcode":"3245 XN",
    "sg:province":"Zuid-Holland",
    "wof:name":"Verzorgingshuis De Goede Ree",
    "wof:placetype":"venue"
},
  "geometry": {"coordinates":[4.155461,51.755234],"type":"Point"}
}