{
  "type": "Feature",
  "properties": {
    "addr:full":"Grachtstraat 26 Voerendaal Limburg 6367 CB",
    "addr:housenumber":"26",
    "addr:postcode":"6367 cb",
    "addr:street":"Grachtstraat",
    "iso:country":"NL",
    "sg:address":"Grachtstraat 26",
    "sg:city":"Voerendaal",
    "sg:orig_category":"Binnenhuisarchitecten",
    "sg:phone":"+31 45 575 3065",
    "sg:postcode":"6367 CB",
    "sg:province":"Limburg",
    "wof:name":"J. Hoefsloot",
    "wof:placetype":"venue"
},
  "geometry": {"coordinates":[5.940269,50.879444],"type":"Point"}
}