{
  "type": "Feature",
  "properties": {
    "iso:country":"NL",
    "sg:address":"Vyverln 20",
    "sg:city":"Brunssum",
    "sg:orig_category":"Adviesbureaus Marketing",
    "sg:phone":"+31 45 400 9425",
    "sg:postcode":"6443 BB",
    "sg:province":"Limburg",
    "sg:website":"http://www.mqi.nl",
    "wof:name":"Market Quest International",
    "wof:placetype":"venue"
},
  "geometry": {"coordinates":[5.970233,50.943302],"type":"Point"}
}