{
  "type": "Feature",
  "properties": {
    "addr:full":"Valkenkamp 767 Maarssen Utrecht 3607 MX",
    "addr:housenumber":"767",
    "addr:postcode":"3607 mx",
    "addr:street":"Valkenkamp",
    "iso:country":"NL",
    "sg:address":"Valkenkamp 767",
    "sg:city":"Maarssen",
    "sg:orig_category":"Webdesign Bureaus",
    "sg:phone":"+31 346 570 420",
    "sg:postcode":"3607 MX",
    "sg:province":"Utrecht",
    "sg:website":"http://www.tritonyte.com",
    "wof:name":"Tritonyte",
    "wof:placetype":"venue"
},
  "geometry": {"coordinates":[5.0099301338,52.14012146],"type":"Point"}
}