{
  "type": "Feature",
  "properties": {
    "addr:full":"Bakkerstr 1517 Bennekom Gelderland 6721 WG",
    "addr:housenumber":"1517",
    "addr:postcode":"6721 wg",
    "addr:street":"Gelderland",
    "iso:country":"NL",
    "sg:address":"Bakkerstr 1517",
    "sg:city":"Bennekom",
    "sg:orig_category":"Administratie- En Boekhoudkantoren",
    "sg:phone":"+31 318 430 032",
    "sg:postcode":"6721 WG",
    "sg:province":"Gelderland",
    "wof:name":"Carpe Diem",
    "wof:placetype":"venue"
},
  "geometry": {"coordinates":[5.67427,51.99987],"type":"Point"}
}