{
  "type": "Feature",
  "properties": {
    "addr:full":"Archimedesbaan 10 Nieuwegein Utrecht 3439 ME",
    "addr:housenumber":"10",
    "addr:postcode":"3439",
    "addr:street":"Archimedesbaan",
    "iso:country":"NL",
    "sg:address":"Archimedesbaan 10",
    "sg:city":"Nieuwegein",
    "sg:classifiers":[
        {
            "category":"Shopping",
            "subcategory":"Gifts & Souvenirs",
            "type":"Retail Goods"
        }
    ],
    "sg:phone":"+31 30 605 0833",
    "sg:postcode":"3439 ME",
    "sg:province":"Utrecht",
    "sg:tags":[
        "wens-",
        "en",
        "prentbriefkaarten"
    ],
    "wof:name":"Aco Bv",
    "wof:placetype":"venue"
},
  "geometry": {"coordinates":[5.1043071747,52.0353775024],"type":"Point"}
}