{
  "type": "Feature",
  "properties": {
    "addr:full":"Slabbecoornweg 38 Tholen Zeeland 4691 RZ",
    "addr:housenumber":"38",
    "addr:postcode":"4691 rz",
    "addr:street":"Slabbecoornweg",
    "iso:country":"NL",
    "sg:address":"Slabbecoornweg 38",
    "sg:city":"Tholen",
    "sg:orig_category":"Pompen And Compressoren Fab",
    "sg:phone":"+31 166 603 497",
    "sg:postcode":"4691 RZ",
    "sg:province":"Zeeland",
    "wof:name":"Handelsonderneming Van Beers Techniek Bv",
    "wof:placetype":"venue"
},
  "geometry": {"coordinates":[4.232194,51.548447],"type":"Point"}
}