{
  "type": "Feature",
  "properties": {
    "addr:full":"D Curtiusstr 7-110 Amsterdam North Holland 1051 JL",
    "addr:housenumber":"7-110",
    "addr:postcode":"1051 jl",
    "iso:country":"NL",
    "sg:address":"D Curtiusstr 7-110",
    "sg:city":"Amsterdam",
    "sg:orig_category":"Vertaalbureaus",
    "sg:phone":"+31 20 681 6701",
    "sg:postcode":"1051 JL",
    "sg:province":"North Holland",
    "sg:website":"http://www.sumatra.demon.nl",
    "wof:name":"Ploegsma, Technische Vertalingen",
    "wof:placetype":"venue"
},
  "geometry": {"coordinates":[4.871745,52.379089],"type":"Point"}
}