{
  "type": "Feature",
  "properties": {
    "addr:full":"Zylbaan 12 Leiderdorp South Holland 2352 BN",
    "addr:housenumber":"12",
    "addr:postcode":"2352 bn",
    "addr:street":"Zylbaan",
    "iso:country":"NL",
    "sg:address":"Zylbaan 12",
    "sg:city":"Leiderdorp",
    "sg:orig_category":"Fotografie Reclame En Mode",
    "sg:phone":"+31 71 589 0877",
    "sg:postcode":"2352 BN",
    "sg:province":"South Holland",
    "wof:name":"Stefan Mizee",
    "wof:placetype":"venue"
},
  "geometry": {"coordinates":[4.534218,52.156174],"type":"Point"}
}