{
  "type": "Feature",
  "properties": {
    "addr:full":"Valkenburgerwg 125 Wylre Limburg 6321 GC",
    "addr:housenumber":"125",
    "addr:postcode":"6321 gc",
    "addr:street":"Wylre Limburg",
    "iso:country":"NL",
    "sg:address":"Valkenburgerwg 125",
    "sg:city":"Wylre",
    "sg:orig_category":"Orthopedische Artikelen",
    "sg:phone":"+31 43 459 2051",
    "sg:postcode":"6321 GC",
    "sg:province":"Limburg",
    "wof:name":"Heussen-De Bie, I I",
    "wof:placetype":"venue"
},
  "geometry": {"coordinates":[5.8834819794,50.8461532593],"type":"Point"}
}