{
  "type": "Feature",
  "properties": {
    "addr:full":"Binnenwg 210 Heemstede Noord-Holland 2101 JT",
    "addr:housenumber":"210",
    "addr:postcode":"2101 jt",
    "iso:country":"NL",
    "sg:address":"Binnenwg 210",
    "sg:city":"Heemstede",
    "sg:orig_category":"Mobiele- En Autotelefoons",
    "sg:phone":"+31 23 528 6964",
    "sg:postcode":"2101 JT",
    "sg:province":"Noord-Holland",
    "sg:website":"http://www.phones.telecomtoday.nl",
    "wof:name":"Telecom Today Phones",
    "wof:placetype":"venue"
},
  "geometry": {"coordinates":[4.621935,52.356564],"type":"Point"}
}