{
  "type": "Feature",
  "properties": {
    "iso:country":"NL",
    "sg:address":"Het Meer 193",
    "sg:city":"Heerenveen",
    "sg:orig_category":"Verhuur Catering-, Feest- En Evenementbenodigdheden",
    "sg:phone":"+31 513 620 883",
    "sg:postcode":"8448 GE",
    "sg:province":"Friesland",
    "wof:name":"Kuip Automaten",
    "wof:placetype":"venue"
},
  "geometry": {"coordinates":[5.946942,52.966133],"type":"Point"}
}