{
  "type": "Feature",
  "properties": {
    "addr:full":"Kroesmeestersdreef 1 Maastricht Limburg 6216 PK",
    "addr:housenumber":"1",
    "addr:postcode":"6216 pk",
    "addr:street":"Kroesmeestersdreef",
    "iso:country":"NL",
    "sg:address":"Kroesmeestersdreef 1",
    "sg:city":"Maastricht",
    "sg:orig_category":"Boekhouders",
    "sg:phone":"+31 43 343 2464",
    "sg:postcode":"6216 PK",
    "sg:province":"Limburg",
    "wof:name":"Administratiekantoor Van Toledo",
    "wof:placetype":"venue"
},
  "geometry": {"coordinates":[5.66113,50.843163],"type":"Point"}
}