{
  "type": "Feature",
  "properties": {
    "addr:full":"T Hofflandt 43 Ulvenhout Noord-Brabant 4851 TB",
    "addr:housenumber":"43",
    "addr:postcode":"4851 tb",
    "addr:street":"T Hofflandt",
    "iso:country":"NL",
    "sg:address":"T Hofflandt 43",
    "sg:city":"Ulvenhout",
    "sg:orig_category":"Administratie- En Boekhoudkantoren",
    "sg:phone":"+31 76 561 3319",
    "sg:postcode":"4851 TB",
    "sg:province":"Noord-Brabant",
    "wof:name":"Aa Bv, Van Der",
    "wof:placetype":"venue"
},
  "geometry": {"coordinates":[4.802859,51.547611],"type":"Point"}
}