{
  "type": "Feature",
  "properties": {
    "addr:full":"Rijnsburgerweg 130 Rijnsburg South Holland 2231 AG",
    "addr:housenumber":"130",
    "addr:postcode":"2231",
    "addr:street":"Rijnsburgerweg",
    "iso:country":"NL",
    "sg:address":"Rijnsburgerweg 130",
    "sg:city":"Rijnsburg",
    "sg:orig_category":"Bloemen And Planten",
    "sg:phone":"+31 71 402 9822",
    "sg:postcode":"2231 AG",
    "sg:province":"South Holland",
    "wof:name":"Decotrend",
    "wof:placetype":"venue"
},
  "geometry": {"coordinates":[4.447092,52.187084],"type":"Point"}
}