{
  "type": "Feature",
  "properties": {
    "iso:country":"NL",
    "sg:address":"Parkweg 1",
    "sg:city":"6121",
    "sg:classifiers":[
        {
            "category":"Banks & Credit Unions",
            "subcategory":"Bank",
            "type":"Services"
        }
    ],
    "sg:phone":"+31 449858824",
    "sg:postcode":"BORN ",
    "sg:province":"Limburg",
    "wof:name":"Rabobank Born",
    "wof:placetype":"venue"
},
  "geometry": {"coordinates":[5.808912,51.031826],"type":"Point"}
}