{
  "type": "Feature",
  "properties": {
    "addr:full":"Beesdestraat 89 Rotterdam South Holland 3077 HB",
    "addr:housenumber":"89",
    "addr:postcode":"3077 hb",
    "addr:street":"Beesdestraat",
    "iso:country":"NL",
    "sg:address":"Beesdestraat 89",
    "sg:city":"Rotterdam",
    "sg:orig_category":"Keramische Producten Fab",
    "sg:phone":"+31 10 479 7859",
    "sg:postcode":"3077 HB",
    "sg:province":"South Holland",
    "wof:name":"G. Simons-Bor",
    "wof:placetype":"venue"
},
  "geometry": {"coordinates":[4.566651,51.887772],"type":"Point"}
}