{
  "type": "Feature",
  "properties": {
    "iso:country":"NL",
    "sg:address":"Holwierderweg 16",
    "sg:city":"Appingedam",
    "sg:orig_category":"Postkantoren",
    "sg:phone":"+31 596 620 959",
    "sg:postcode":"9901 TN",
    "sg:province":"Groningen",
    "wof:name":"Jeanet Davids",
    "wof:placetype":"venue"
},
  "geometry": {"coordinates":[6.866004,53.333206],"type":"Point"}
}