{
  "type": "Feature",
  "properties": {
    "addr:full":"Parkweg 67 Beesd Gelderland 4153 XL",
    "addr:housenumber":"67",
    "addr:postcode":"4153 xl",
    "addr:street":"Parkweg;Gelderland",
    "iso:country":"NL",
    "sg:address":"Parkweg 67",
    "sg:city":"Beesd",
    "sg:orig_category":"Diverse Consumentenartikelen Gh",
    "sg:phone":"+31 345 683 804",
    "sg:postcode":"4153 XL",
    "sg:province":"Gelderland",
    "wof:name":"Altranet Cv",
    "wof:placetype":"venue"
},
  "geometry": {"coordinates":[5.188767,51.896717],"type":"Point"}
}