{
  "type": "Feature",
  "properties": {
    "addr:full":"Zieuwentsewg 32A Beltrum Gelderland 7156 RC",
    "addr:housenumber":"32a",
    "addr:postcode":"7156 rc",
    "addr:street":"Zieuwentsewg;Gelderland",
    "iso:country":"NL",
    "sg:address":"Zieuwentsewg 32A",
    "sg:city":"Beltrum",
    "sg:orig_category":"Adviesbureaus Bedrijfsorganisatie",
    "sg:phone":"+31 544 481 234",
    "sg:postcode":"7156 RC",
    "sg:province":"Gelderland",
    "wof:name":"Hoks Bv",
    "wof:placetype":"venue"
},
  "geometry": {"coordinates":[6.543733,52.041363],"type":"Point"}
}