{
  "type": "Feature",
  "properties": {
    "addr:full":"Duivelsbrugln 78 Breda Noord-Brabant 4835 JJ",
    "addr:housenumber":"78",
    "addr:postcode":"4835 jj",
    "addr:street":"Duivelsbrugln",
    "iso:country":"NL",
    "sg:address":"Duivelsbrugln 78",
    "sg:city":"Breda",
    "sg:orig_category":"Fotoreportages",
    "sg:phone":"+31 76 560 0352",
    "sg:postcode":"4835 JJ",
    "sg:province":"Noord-Brabant",
    "wof:name":"Schouten, M P",
    "wof:placetype":"venue"
},
  "geometry": {"coordinates":[4.778852,51.566738],"type":"Point"}
}