{
  "type": "Feature",
  "properties": {
    "iso:country":"NL",
    "sg:address":"Wilhelminastraat 47",
    "sg:city":"Steenwijk",
    "sg:classifiers":[
        {
            "category":"Education",
            "subcategory":"Preschool",
            "type":"Public Place"
        }
    ],
    "sg:phone":"+31 521 514 686",
    "sg:postcode":"8331 ME",
    "sg:province":"NL.08",
    "sg:tags":[
        "kleuteronderwijs",
        "basis-"
    ],
    "wof:name":"Bernhardschool",
    "wof:placetype":"venue"
},
  "geometry": {"coordinates":[6.118601,52.782841],"type":"Point"}
}