{
  "type": "Feature",
  "properties": {
    "addr:full":"Orion 45 Bleiswyk South Holland 2665 WB",
    "addr:housenumber":"45",
    "addr:postcode":"2665 wb",
    "addr:street":"Orion",
    "iso:country":"NL",
    "sg:address":"Orion 45",
    "sg:city":"Bleiswyk",
    "sg:orig_category":"Acupunctuur",
    "sg:phone":"+31 10 521 7520",
    "sg:postcode":"2665 WB",
    "sg:province":"South Holland",
    "sg:website":"http://www.vermin.nl",
    "wof:name":"Vermin J R M",
    "wof:placetype":"venue"
},
  "geometry": {"coordinates":[4.545766,52.012451],"type":"Point"}
}