{
  "type": "Feature",
  "properties": {
    "addr:full":"Winkelc Coevering 33 Geldrop Noord-Brabant 5665 GA",
    "addr:housenumber":"33",
    "addr:postcode":"5665 ga",
    "addr:street":"Winkelc Coevering",
    "iso:country":"NL",
    "sg:address":"Winkelc Coevering 33",
    "sg:city":"Geldrop",
    "sg:orig_category":"Verenigingsgebouwen",
    "sg:phone":"+31 40 285 6844",
    "sg:postcode":"5665 GA",
    "sg:province":"Noord-Brabant",
    "wof:name":"Dreef, De",
    "wof:placetype":"venue"
},
  "geometry": {"coordinates":[5.573121,51.417786],"type":"Point"}
}