{
  "type": "Feature",
  "properties": {
    "iso:country":"NL",
    "sg:address":"Ruytersstr 37",
    "sg:city":"Ursem",
    "sg:orig_category":"Elektrotechnische Installatiebureaus",
    "sg:phone":"+31 72 502 1344",
    "sg:postcode":"1645 SB",
    "sg:province":"Noord-Holland",
    "sg:website":"http://www.konijn-elektro.nl",
    "wof:name":"Adam Konijn Vof",
    "wof:placetype":"venue"
},
  "geometry": {"coordinates":[4.891467,52.627033],"type":"Point"}
}