{
  "type": "Feature",
  "properties": {
    "iso:country":"NL",
    "sg:address":"Hofkampstraat 69",
    "sg:city":"Almelo",
    "sg:classifiers":[
        {
            "category":"Fast Food",
            "type":"Food & Drink"
        }
    ],
    "sg:phone":"+31 546 815 211",
    "sg:postcode":"7607 NC",
    "sg:province":"Overijssel",
    "sg:tags":[
        "afhaal",
        "restaurant"
    ],
    "wof:name":"Jojo'S Hamburgers",
    "wof:placetype":"venue"
},
  "geometry": {"coordinates":[6.675893,52.35313],"type":"Point"}
}