{
  "type": "Feature",
  "properties": {
    "addr:full":"Paterstraat 128 Kerkdriel Gelderland 5331 EL",
    "addr:housenumber":"128;5331",
    "addr:postcode":"el",
    "addr:street":"Paterstraat;Gelderland",
    "iso:country":"NL",
    "sg:address":"Paterstraat 128",
    "sg:city":"Kerkdriel",
    "sg:classifiers":[
        {
            "category":"Food & Beverages",
            "subcategory":"Fruits & Vegetables",
            "type":"Retail Goods"
        }
    ],
    "sg:phone":"+31 418 632 424",
    "sg:postcode":"5331 EL",
    "sg:province":"Gelderland",
    "sg:tags":[
        "groenten"
    ],
    "wof:name":"F. Richt-V.D. Bogaard",
    "wof:placetype":"venue"
},
  "geometry": {"coordinates":[5.330566,51.765804],"type":"Point"}
}