{
  "type": "Feature",
  "properties": {
    "iso:country":"NL",
    "sg:address":"Rooseveltlaan 185",
    "sg:city":"Amsterdam",
    "sg:orig_category":"Parfum And Cosmetica Gh",
    "sg:phone":"+31 20 642 0180",
    "sg:postcode":"1079 AN",
    "sg:province":"North Holland",
    "wof:name":"Christiane Aimee Bv",
    "wof:placetype":"venue"
},
  "geometry": {"coordinates":[4.897422,52.342869],"type":"Point"}
}