{
  "type": "Feature",
  "properties": {
    "iso:country":"NL",
    "sg:address":"Columbusstraat 177",
    "sg:city":"'S Gravenhage",
    "sg:orig_category":"Schilderwerk",
    "sg:phone":"+31 70 364 8828",
    "sg:postcode":"2561 AG",
    "sg:province":"Zuid-Holland",
    "wof:name":"Hartman Schilder- En Totaalonderhoud",
    "wof:placetype":"venue"
},
  "geometry": {"coordinates":[4.277297,52.077503],"type":"Point"}
}