{
  "type": "Feature",
  "properties": {
    "addr:full":"Waterlandsngl 145 S Gravenhage South Holland 2548 SP",
    "addr:housenumber":"145",
    "addr:postcode":"2548 sp",
    "addr:street":"S Gravenhage",
    "iso:country":"NL",
    "sg:address":"Waterlandsngl 145",
    "sg:city":"S Gravenhage",
    "sg:orig_category":"Kantoor- En Secretariaatsservice",
    "sg:phone":"+31 6 22063918",
    "sg:postcode":"2548 SP",
    "sg:province":"South Holland",
    "wof:name":"Op En Top",
    "wof:placetype":"venue"
},
  "geometry": {"coordinates":[4.2901000977,52.0298881531],"type":"Point"}
}