{
  "type": "Feature",
  "properties": {
    "addr:full":"Robijnstraat 20 Groningen Groningen 9743 KR",
    "addr:housenumber":"20",
    "addr:postcode":"9743 kr",
    "addr:street":"Robijnstraat",
    "iso:country":"NL",
    "sg:address":"Robijnstraat 20",
    "sg:city":"Groningen",
    "sg:orig_category":"Verzekeringen",
    "sg:phone":"+31 50 577 3617",
    "sg:postcode":"9743 KR",
    "sg:province":"Groningen",
    "wof:name":"A Barneveld Assurantien",
    "wof:placetype":"venue"
},
  "geometry": {"coordinates":[6.527597,53.23056],"type":"Point"}
}