{
  "type": "Feature",
  "properties": {
    "iso:country":"NL",
    "sg:address":"Hoofdweg 14",
    "sg:city":"Terschelling West",
    "sg:orig_category":"Kampeerterreinen",
    "sg:phone":"+31 562 442 056",
    "sg:postcode":"8881 HA",
    "sg:province":"Provincie Friesland",
    "wof:name":"S D Wulp",
    "wof:placetype":"venue"
},
  "geometry": {"coordinates":[5.2416391373,53.3734054565],"type":"Point"}
}