{
  "type": "Feature",
  "properties": {
    "addr:full":"Grotestr 136 Almelo Overijssel 7607 CW",
    "addr:housenumber":"136",
    "addr:postcode":"7607 cw",
    "iso:country":"NL",
    "sg:address":"Grotestr 136",
    "sg:city":"Almelo",
    "sg:orig_category":"Modelbouw",
    "sg:phone":"+31 546 812 981",
    "sg:postcode":"7607 CW",
    "sg:province":"Overijssel",
    "wof:name":"Somberg",
    "wof:placetype":"venue"
},
  "geometry": {"coordinates":[6.666426,52.35368],"type":"Point"}
}