{
  "type": "Feature",
  "properties": {
    "iso:country":"NL",
    "sg:address":"Kevelhamhoek 95",
    "sg:city":"Enschede",
    "sg:orig_category":"Boeken En Tijdschriften",
    "sg:phone":"+31 53 477 3797",
    "sg:postcode":"7546 EN",
    "sg:province":"Overijssel",
    "wof:name":"Hko Bv",
    "wof:placetype":"venue"
},
  "geometry": {"coordinates":[6.855568,52.193642],"type":"Point"}
}