{
  "type": "Feature",
  "properties": {
    "addr:full":"Roesterd 28 Ravenstein Noord-Brabant 5371 MR",
    "addr:housenumber":"28",
    "addr:postcode":"5371 mr",
    "addr:street":"Roesterd",
    "iso:country":"NL",
    "sg:address":"Roesterd 28",
    "sg:city":"Ravenstein",
    "sg:orig_category":"Tekstschrijversters",
    "sg:phone":"+31 486 416 149",
    "sg:postcode":"5371 MR",
    "sg:province":"Noord-Brabant",
    "wof:name":"Tekst En Word-Art",
    "wof:placetype":"venue"
},
  "geometry": {"coordinates":[5.64182,51.791416],"type":"Point"}
}