{
  "type": "Feature",
  "properties": {
    "addr:full":"A Loosjesstr 36 Haarlem Noord-Holland 2032 MC",
    "addr:housenumber":"36",
    "addr:postcode":"2032 mc",
    "iso:country":"NL",
    "sg:address":"A Loosjesstr 36",
    "sg:city":"Haarlem",
    "sg:orig_category":"Onderhoudswerken",
    "sg:phone":"+31 23 535 2416",
    "sg:postcode":"2032 MC",
    "sg:province":"Noord-Holland",
    "wof:name":"Weele En Partner, Van Der",
    "wof:placetype":"venue"
},
  "geometry": {"coordinates":[4.651883,52.378792],"type":"Point"}
}