{
  "type": "Feature",
  "properties": {
    "addr:full":"Amundsenweg 41 Goes Zeeland 4462 GP",
    "addr:housenumber":"41",
    "addr:postcode":"4462 gp",
    "addr:street":"Amundsenweg",
    "iso:country":"NL",
    "sg:address":"Amundsenweg 41",
    "sg:city":"Goes",
    "sg:orig_category":"Automaterialen En Gereedschappen",
    "sg:phone":"+31 113 215 555",
    "sg:postcode":"4462 GP",
    "sg:province":"Zeeland",
    "wof:name":"Aoc Bv",
    "wof:placetype":"venue"
},
  "geometry": {"coordinates":[-83.914169,39.768833],"type":"Point"}
}