{
  "type": "Feature",
  "properties": {
    "addr:full":"Havenweg 42 Uithuizermeeden Groningen 9982 ED",
    "addr:housenumber":"42",
    "addr:postcode":"9982 ed",
    "addr:street":"Havenweg",
    "iso:country":"NL",
    "sg:address":"Havenweg 42",
    "sg:city":"Uithuizermeeden",
    "sg:orig_category":"Loodgieterswerk, Verwarming And Sanitaire Installaties",
    "sg:phone":"+31 595 412 725",
    "sg:postcode":"9982 ED",
    "sg:province":"Groningen",
    "wof:name":"Pieterman Klussenbedrijf",
    "wof:placetype":"venue"
},
  "geometry": {"coordinates":[6.730361,53.410492],"type":"Point"}
}