{
  "type": "Feature",
  "properties": {
    "iso:country":"NL",
    "sg:address":"Vleugelnootsngl 48",
    "sg:city":"Almere",
    "sg:orig_category":"Autorijscholen",
    "sg:phone":"+31 36 545 1913",
    "sg:postcode":"1326 ER",
    "sg:province":"Flevoland",
    "wof:name":"Autorijschool Almere",
    "wof:placetype":"venue"
},
  "geometry": {"coordinates":[5.247384,52.372585],"type":"Point"}
}