{
  "type": "Feature",
  "properties": {
    "iso:country":"NL",
    "sg:address":"Oude Engelenseweg 7",
    "sg:city":"'S Hertogenbosch",
    "sg:orig_category":"Pleziervaartuigen And Reparatie",
    "sg:phone":"+31 73 621 2798",
    "sg:postcode":"5222 AA",
    "sg:province":"Noord-Brabant",
    "wof:name":"Beekwilder Yachting",
    "wof:placetype":"venue"
},
  "geometry": {"coordinates":[5.281129,51.701748],"type":"Point"}
}