{
  "type": "Feature",
  "properties": {
    "addr:full":"Oranjestr 14 Velp Gld Gelderland 6881 SE",
    "addr:housenumber":"14;6881",
    "addr:street":"Oranjestr;Gld Gelderland;Se",
    "iso:country":"NL",
    "sg:address":"Oranjestr 14",
    "sg:city":"Velp Gld",
    "sg:orig_category":"Kinderkleding",
    "sg:phone":"+31 26 361 5118",
    "sg:postcode":"6881 SE",
    "sg:province":"Gelderland",
    "wof:name":"Ollie",
    "wof:placetype":"venue"
},
  "geometry": {"coordinates":[5.969625,51.995441],"type":"Point"}
}