{
  "type": "Feature",
  "properties": {
    "addr:full":"Borodinlaan 60 Schiedam South Holland 3122 HB",
    "addr:housenumber":"60",
    "addr:postcode":"3122 hb",
    "addr:street":"Borodinlaan",
    "iso:country":"NL",
    "sg:address":"Borodinlaan 60",
    "sg:city":"Schiedam",
    "sg:orig_category":"Fietshandelaren",
    "sg:phone":"+31 10 470 4122",
    "sg:postcode":"3122 HB",
    "sg:province":"South Holland",
    "wof:name":"Hans Damme",
    "wof:placetype":"venue"
},
  "geometry": {"coordinates":[4.367803,51.933434],"type":"Point"}
}