{
  "type": "Feature",
  "properties": {
    "addr:full":"Hollandsch Diep 1A Capelle Ad Yssel Zuid-Holland 2904 EP",
    "addr:housenumber":"1a;2904",
    "addr:postcode":"ep",
    "addr:street":"Hollandsch Diep",
    "iso:country":"NL",
    "sg:address":"Hollandsch Diep 1A",
    "sg:city":"Capelle Ad Yssel",
    "sg:orig_category":"Administratie- En Boekhoudkantoren",
    "sg:phone":"+31 10 264 3232",
    "sg:postcode":"2904 EP",
    "sg:province":"Zuid-Holland",
    "wof:name":"Holland Balans",
    "wof:placetype":"venue"
},
  "geometry": {"coordinates":[4.600882,51.935814],"type":"Point"}
}