{
  "type": "Feature",
  "properties": {
    "addr:full":"Kwakelsteeg 1 Rijnsburg South Holland 2231 BH",
    "addr:housenumber":"1",
    "addr:postcode":"2231 bh",
    "addr:street":"Kwakelsteeg",
    "iso:country":"NL",
    "sg:address":"Kwakelsteeg 1",
    "sg:city":"Rijnsburg",
    "sg:orig_category":"Verhuur Gereedschapsmachines And Gereedschappen",
    "sg:phone":"+31 71 402 0812",
    "sg:postcode":"2231 BH",
    "sg:province":"South Holland",
    "wof:name":"Firma J.C. Zandbergen",
    "wof:placetype":"venue"
},
  "geometry": {"coordinates":[4.449701,52.19099],"type":"Point"}
}