{
  "type": "Feature",
  "properties": {
    "iso:country":"NL",
    "sg:address":"Warmoesstr 96",
    "sg:city":"Amsterdam",
    "sg:orig_category":"Discotheken",
    "sg:phone":"+31 20 623 9604",
    "sg:postcode":"1012 JH",
    "sg:province":"Noord-Holland",
    "wof:name":"Cockring",
    "wof:placetype":"venue"
},
  "geometry": {"coordinates":[4.896814,52.374565],"type":"Point"}
}