{
  "type": "Feature",
  "properties": {
    "addr:full":"Wassenaarstr 15 St Annaparochie Provincie Friesland 9076 DH",
    "addr:housenumber":"15",
    "addr:postcode":"9076 dh",
    "addr:street":"Wassenaarstr;Friesland",
    "iso:country":"NL",
    "sg:address":"Wassenaarstr 15",
    "sg:city":"St Annaparochie",
    "sg:orig_category":"Bejaarden - Verzorgingstehuizen",
    "sg:phone":"+31 518 401 532",
    "sg:postcode":"9076 DH",
    "sg:province":"Provincie Friesland",
    "wof:name":"Bildt, Het",
    "wof:placetype":"venue"
},
  "geometry": {"coordinates":[5.658873,53.275364],"type":"Point"}
}