{
  "type": "Feature",
  "properties": {
    "iso:country":"NL",
    "sg:address":"Oude Rijksweg 28",
    "sg:city":"Garmerwolde",
    "sg:orig_category":"Pleziervaartuigen And Reparatie",
    "sg:phone":"+31 50 541 3207",
    "sg:postcode":"9798 PB",
    "sg:province":"Groningen",
    "wof:name":"Jachtbouw Groeneveld",
    "wof:placetype":"venue"
},
  "geometry": {"coordinates":[6.65926,53.24654],"type":"Point"}
}