{
  "type": "Feature",
  "properties": {
    "addr:full":"Zes Landenstraat 1 Heerlen Limburg 6414 GG",
    "addr:housenumber":"1",
    "addr:postcode":"6414 gg",
    "addr:street":"Zes Landenstraat",
    "iso:country":"NL",
    "sg:address":"Zes Landenstraat 1",
    "sg:city":"Heerlen",
    "sg:classifiers":[
        {
            "category":"Education",
            "subcategory":"Preschool",
            "type":"Public Place"
        }
    ],
    "sg:phone":"+31 45 521 2250",
    "sg:postcode":"6414 GG",
    "sg:province":"Limburg",
    "sg:tags":[
        "kleuteronderwijs",
        "basis-"
    ],
    "wof:name":"Basisschool De Schakel",
    "wof:placetype":"venue"
},
  "geometry": {"coordinates":[5.965715,50.923168],"type":"Point"}
}