{
  "type": "Feature",
  "properties": {
    "addr:full":"Stationswg 109 Ede Gld Gelderland 6711 PN",
    "addr:housenumber":"109",
    "addr:postcode":"6711 pn",
    "addr:street":"Gld Gelderland",
    "iso:country":"NL",
    "sg:address":"Stationswg 109",
    "sg:city":"Ede Gld",
    "sg:orig_category":"Adviesbureaus Beroeps-, School- And Studiekeuze",
    "sg:phone":"+31 318 619 049",
    "sg:postcode":"6711 PN",
    "sg:province":"Gelderland",
    "wof:name":"Zuid-Vallei, De",
    "wof:placetype":"venue"
},
  "geometry": {"coordinates":[5.671134,52.030712],"type":"Point"}
}