{
  "type": "Feature",
  "properties": {
    "addr:full":"Theresiastr 125 S Gravenhage Zuid-Holland 2593 AE",
    "addr:housenumber":"125;gravenhage",
    "addr:postcode":"2593 ae",
    "addr:street":"S",
    "iso:country":"NL",
    "sg:address":"Theresiastr 125",
    "sg:city":"S Gravenhage",
    "sg:orig_category":"Apotheken",
    "sg:phone":"+31 70 383 6566",
    "sg:postcode":"2593 AE",
    "sg:province":"Zuid-Holland",
    "wof:name":"Theresia",
    "wof:placetype":"venue"
},
  "geometry": {"coordinates":[4.34266,52.086121],"type":"Point"}
}