{
  "type": "Feature",
  "properties": {
    "addr:full":"Wenckebachstr 8 Noordwykerhout Zuid-Holland 2211 RV",
    "addr:housenumber":"8",
    "addr:postcode":"2211 rv",
    "addr:street":"Wenckebachstr",
    "iso:country":"NL",
    "sg:address":"Wenckebachstr 8",
    "sg:city":"Noordwykerhout",
    "sg:orig_category":"Administratie- En Boekhoudkantoren",
    "sg:phone":"+31 252 373 110",
    "sg:postcode":"2211 RV",
    "sg:province":"Zuid-Holland",
    "wof:name":"Janssen, H W Th",
    "wof:placetype":"venue"
},
  "geometry": {"coordinates":[4.491189,52.26347],"type":"Point"}
}