{
  "type": "Feature",
  "properties": {
    "addr:full":"Terpeborch 74 Rosmalen North Brabant 5241 KB",
    "addr:housenumber":"74",
    "addr:postcode":"5241 kb",
    "addr:street":"Terpeborch",
    "iso:country":"NL",
    "sg:address":"Terpeborch 74",
    "sg:city":"Rosmalen",
    "sg:orig_category":"Scholen Voor Basisonderwijs",
    "sg:phone":"+31 73 521 3995",
    "sg:postcode":"5241 KB",
    "sg:province":"North Brabant",
    "wof:name":"Borch Rk, De",
    "wof:placetype":"venue"
},
  "geometry": {"coordinates":[5.360361,51.722466],"type":"Point"}
}