{
  "type": "Feature",
  "properties": {
    "addr:full":"Grenswg 21-23 Surhuisterveen Friesland 9231 HT",
    "addr:housenumber":"21-23",
    "addr:postcode":"9231 ht",
    "iso:country":"NL",
    "sg:address":"Grenswg 21-23",
    "sg:city":"Surhuisterveen",
    "sg:classifiers":[
        {
            "category":"Retail",
            "subcategory":"Auto Repair",
            "type":"Services"
        }
    ],
    "sg:phone":"+31 512 362 429",
    "sg:postcode":"9231 HT",
    "sg:province":"Friesland",
    "sg:tags":[
        "garage"
    ],
    "sg:website":"http://www.poelmanautos.nl",
    "wof:name":"Poelman Auto'S",
    "wof:placetype":"venue"
},
  "geometry": {"coordinates":[6.183192,53.182316],"type":"Point"}
}