{
  "type": "Feature",
  "properties": {
    "addr:full":"Molenstr 37 Beers Nb Noord-Brabant 5437 AA",
    "addr:housenumber":"37",
    "addr:postcode":"5437 aa",
    "addr:street":"Molenstr",
    "iso:country":"NL",
    "sg:address":"Molenstr 37",
    "sg:city":"Beers Nb",
    "sg:classifiers":[
        {
            "category":"Sports & Exercise",
            "subcategory":"Stables",
            "type":"Entertainment"
        }
    ],
    "sg:phone":"+31 485 312 062",
    "sg:postcode":"5437 AA",
    "sg:province":"Noord-Brabant",
    "sg:tags":[
        "maneges"
    ],
    "wof:name":"Witte Hoeve, De",
    "wof:placetype":"venue"
},
  "geometry": {"coordinates":[5.837642,51.726742],"type":"Point"}
}