{
  "type": "Feature",
  "properties": {
    "iso:country":"NL",
    "sg:address":"Beukstr 13",
    "sg:city":"Drunen",
    "sg:orig_category":"Scholen Voor Basisonderwijs",
    "sg:phone":"+31 416 373 594",
    "sg:postcode":"5151 ZK",
    "sg:province":"Noord-Brabant",
    "wof:name":"Bolster Rk, De",
    "wof:placetype":"venue"
},
  "geometry": {"coordinates":[5.122898,51.691002],"type":"Point"}
}