{
  "type": "Feature",
  "properties": {
    "addr:full":"De Voorreep 102 Erica Drenthe 7887 HC",
    "addr:housenumber":"102",
    "addr:postcode":"erica;7887 hc",
    "addr:street":"De Voorreep",
    "iso:country":"NL",
    "sg:address":"De Voorreep 102",
    "sg:city":"Erica",
    "sg:orig_category":"Verbouwingen",
    "sg:phone":"+31 591 302 240",
    "sg:postcode":"7887 HC",
    "sg:province":"Drenthe",
    "wof:name":"Wijnands & Vinke, Bouwgroep",
    "wof:placetype":"venue"
},
  "geometry": {"coordinates":[6.925081,52.719864],"type":"Point"}
}