{
  "type": "Feature",
  "properties": {
    "addr:full":"Emmaln 17 Apeldoorn Gelderland 7316 ED",
    "addr:housenumber":"17",
    "addr:postcode":"7316 ed",
    "addr:street":"Emmaln;Gelderland",
    "iso:country":"NL",
    "sg:address":"Emmaln 17",
    "sg:city":"Apeldoorn",
    "sg:orig_category":"Journalisten Freelance",
    "sg:phone":"+31 55 521 2704",
    "sg:postcode":"7316 ED",
    "sg:province":"Gelderland",
    "wof:name":"Bladwerk, Buro",
    "wof:placetype":"venue"
},
  "geometry": {"coordinates":[5.959134,52.223557],"type":"Point"}
}