{
  "type": "Feature",
  "properties": {
    "addr:full":"Vechtstr 13 Bergen Op Zoom North Brabant 4615 CD",
    "addr:housenumber":"13",
    "addr:postcode":"4615 cd",
    "addr:street":"Vechtstr",
    "iso:country":"NL",
    "sg:address":"Vechtstr 13",
    "sg:city":"Bergen Op Zoom",
    "sg:orig_category":"Autorijscholen",
    "sg:phone":"+31 6 53525202",
    "sg:postcode":"4615 CD",
    "sg:province":"North Brabant",
    "wof:name":"Yilmaz, Habib",
    "wof:placetype":"venue"
},
  "geometry": {"coordinates":[4.284195,51.484657],"type":"Point"}
}