{
  "type": "Feature",
  "properties": {
    "addr:full":"Hofmeestery 4 Huissen Gelderland 6852 ND",
    "addr:housenumber":"4",
    "addr:postcode":"6852 nd",
    "addr:street":"Hofmeestery;Gelderland",
    "iso:country":"NL",
    "sg:address":"Hofmeestery 4",
    "sg:city":"Huissen",
    "sg:orig_category":"Muziekinstrumenten En Bladmuziek",
    "sg:phone":"+31 6 26486048",
    "sg:postcode":"6852 ND",
    "sg:province":"Gelderland",
    "sg:website":"http://www.accoorden.com",
    "wof:name":"Boltjes",
    "wof:placetype":"venue"
},
  "geometry": {"coordinates":[5.928752,51.935616],"type":"Point"}
}