{
  "type": "Feature",
  "properties": {
    "addr:full":"Krommezantweg 2 Dordrecht South Holland 3319 GH",
    "addr:housenumber":"2",
    "addr:postcode":"3319 gh",
    "addr:street":"Krommezantweg",
    "iso:country":"NL",
    "sg:address":"Krommezantweg 2",
    "sg:city":"Dordrecht",
    "sg:orig_category":"Bloemen And Planten",
    "sg:phone":"+31 78 616 0320",
    "sg:postcode":"3319 GH",
    "sg:province":"South Holland",
    "wof:name":"Bloemsierkunst Bussem",
    "wof:placetype":"venue"
},
  "geometry": {"coordinates":[4.705279,51.795025],"type":"Point"}
}