{
  "type": "Feature",
  "properties": {
    "addr:full":"Weikamperwg 35 Hoenderloo Gelderland 7351 TE",
    "addr:housenumber":"35;7351",
    "addr:postcode":"te",
    "addr:street":"Weikamperwg;Gelderland",
    "iso:country":"NL",
    "sg:address":"Weikamperwg 35",
    "sg:city":"Hoenderloo",
    "sg:orig_category":"Achtergrondmuziek",
    "sg:phone":"+31 55 378 1839",
    "sg:postcode":"7351 TE",
    "sg:province":"Gelderland",
    "wof:name":"Muziek Design",
    "wof:placetype":"venue"
},
  "geometry": {"coordinates":[5.878869,52.1269],"type":"Point"}
}