{
  "type": "Feature",
  "properties": {
    "addr:full":"Beukwg 73 Hengelo Ov Overijssel 7556 DD",
    "addr:housenumber":"73",
    "addr:postcode":"7556 dd",
    "addr:street":"Beukwg;Ov",
    "iso:country":"NL",
    "sg:address":"Beukwg 73",
    "sg:city":"Hengelo Ov",
    "sg:orig_category":"Architecten En Architectenbureaus",
    "sg:phone":"+31 74 250 5453",
    "sg:postcode":"7556 DD",
    "sg:province":"Overijssel",
    "wof:name":"Tuns + Horsting Architecten Bv",
    "wof:placetype":"venue"
},
  "geometry": {"coordinates":[6.792252,52.272511],"type":"Point"}
}