{
  "type": "Feature",
  "properties": {
    "addr:full":"A G Wyerswg 9 Wekerom Gelderland 6733 AR",
    "addr:housenumber":"9",
    "addr:postcode":"6733",
    "addr:street":"A;Wyerswg;Gelderland",
    "iso:country":"NL",
    "sg:address":"A G Wyerswg 9",
    "sg:city":"Wekerom",
    "sg:orig_category":"Begrafenisverzorging",
    "sg:phone":"+31 318 461 640",
    "sg:postcode":"6733 AR",
    "sg:province":"Gelderland",
    "wof:name":"Hardeman, W",
    "wof:placetype":"venue"
},
  "geometry": {"coordinates":[5.71421,52.111546],"type":"Point"}
}