{
  "type": "Feature",
  "properties": {
    "addr:full":"Perengaard 13 Doorn Utrecht 3941 LX",
    "addr:housenumber":"13",
    "addr:postcode":"3941 lx",
    "addr:street":"Perengaard",
    "iso:country":"NL",
    "sg:address":"Perengaard 13",
    "sg:city":"Doorn",
    "sg:orig_category":"Administratie- En Boekhoudkantoren",
    "sg:phone":"+31 343 415 907",
    "sg:postcode":"3941 LX",
    "sg:province":"Utrecht",
    "wof:name":"Elverding Bv",
    "wof:placetype":"venue"
},
  "geometry": {"coordinates":[5.348367,52.029549],"type":"Point"}
}