{
  "type": "Feature",
  "properties": {
    "addr:full":"Biesdelselaan 32 Velp Gld Gelderland 6881 CH",
    "addr:housenumber":"32",
    "addr:postcode":"6881",
    "addr:street":"Biesdelselaan;Gld Gelderland",
    "iso:country":"NL",
    "sg:address":"Biesdelselaan 32",
    "sg:city":"Velp Gld",
    "sg:orig_category":"Autokeuringen",
    "sg:phone":"+31 26 361 5578",
    "sg:postcode":"6881 CH",
    "sg:province":"Gelderland",
    "wof:name":"Trudon",
    "wof:placetype":"venue"
},
  "geometry": {"coordinates":[5.979158,52.002007],"type":"Point"}
}