{
  "type": "Feature",
  "properties": {
    "iso:country":"NL",
    "sg:address":"Voorstraat 2E",
    "sg:city":"Almkerk",
    "sg:classifiers":[
        {
            "category":"Food & Beverages",
            "subcategory":"Fruits & Vegetables",
            "type":"Retail Goods"
        }
    ],
    "sg:phone":"+31 183 405 119",
    "sg:postcode":"4286 AL",
    "sg:province":"Noord-Brabant",
    "sg:tags":[
        "groenten"
    ],
    "wof:name":"Ottevanger Groentespecialist",
    "wof:placetype":"venue"
},
  "geometry": {"coordinates":[4.960301,51.770714],"type":"Point"}
}