{
  "type": "Feature",
  "properties": {
    "addr:full":"Telefoonweg 9 Ede Gld Gelderland 6712 GA",
    "addr:housenumber":"9",
    "addr:postcode":"6712 ga",
    "addr:street":"Telefoonweg;Gld Gelderland",
    "iso:country":"NL",
    "sg:address":"Telefoonweg 9",
    "sg:city":"Ede Gld",
    "sg:classifiers":[
        {
            "category":"Food & Beverages",
            "subcategory":"Fruits & Vegetables",
            "type":"Retail Goods"
        }
    ],
    "sg:phone":"+31 318 611 149",
    "sg:postcode":"6712 GA",
    "sg:province":"Gelderland",
    "sg:tags":[
        "groenten"
    ],
    "wof:name":"L. Van Ginkel",
    "wof:placetype":"venue"
},
  "geometry": {"coordinates":[5.666642,52.047935],"type":"Point"}
}