{
  "type": "Feature",
  "properties": {
    "addr:full":"Midstraat 26 Joure Friesland 8501 AP",
    "addr:housenumber":"26",
    "addr:postcode":"8501 ap",
    "addr:street":"Midstraat",
    "iso:country":"NL",
    "sg:address":"Midstraat 26",
    "sg:city":"Joure",
    "sg:orig_category":"Werving And Selectie Van Tijdelijk Personeel And Uitzendkantoren",
    "sg:phone":"+31 513 418 567",
    "sg:postcode":"8501 AP",
    "sg:province":"Friesland",
    "wof:name":"Start",
    "wof:placetype":"venue"
},
  "geometry": {"coordinates":[5.7933979034,52.968536377],"type":"Point"}
}