{
  "type": "Feature",
  "properties": {
    "addr:full":"Kalkbranderstraat 31 Zwolle Overijssel 8043 BG",
    "addr:housenumber":"31",
    "addr:postcode":"8043",
    "addr:street":"Kalkbranderstraat",
    "iso:country":"NL",
    "sg:address":"Kalkbranderstraat 31",
    "sg:city":"Zwolle",
    "sg:orig_category":"Vertaal- And Tolkenbureaus",
    "sg:phone":"+31 38 444 8507",
    "sg:postcode":"8043 BG",
    "sg:province":"Overijssel",
    "wof:name":"Vertaalbureau Bemar",
    "wof:placetype":"venue"
},
  "geometry": {"coordinates":[6.064084,52.53484],"type":"Point"}
}