{
  "type": "Feature",
  "properties": {
    "iso:country":"NL",
    "sg:address":"Valeriaan 23",
    "sg:city":"Ysselstein Ut",
    "sg:orig_category":"Grafisch Ontwerpers",
    "sg:phone":"+31 30 688 5661",
    "sg:postcode":"3401 LB",
    "sg:province":"Utrecht",
    "wof:name":"Noorderlicht, Het",
    "wof:placetype":"venue"
},
  "geometry": {"coordinates":[5.032484,52.021915],"type":"Point"}
}