{
  "type": "Feature",
  "properties": {
    "addr:full":"Baanstraat 4 Vlaardingen Zuid-Holland 3131 CA",
    "addr:housenumber":"4",
    "addr:postcode":"3131 ca",
    "addr:street":"Baanstraat",
    "iso:country":"NL",
    "sg:address":"Baanstraat 4",
    "sg:city":"Vlaardingen",
    "sg:orig_category":"Fitnesscentra",
    "sg:phone":"+31 10 474 8079",
    "sg:postcode":"3131 CA",
    "sg:province":"Zuid-Holland",
    "wof:name":"Sportschool Egberth Thomas",
    "wof:placetype":"venue"
},
  "geometry": {"coordinates":[4.343367,51.907051],"type":"Point"}
}