{
  "type": "Feature",
  "properties": {
    "iso:country":"NL",
    "sg:address":"Mierdseweg 49",
    "sg:city":"Reusel",
    "sg:orig_category":"Autokeuringen",
    "sg:phone":"+31 497 620 088",
    "sg:postcode":"5541 EP",
    "sg:province":"Noord-Brabant",
    "wof:name":"Van Poppel Autoschade",
    "wof:placetype":"venue"
},
  "geometry": {"coordinates":[5.160129,51.368439],"type":"Point"}
}