{
  "type": "Feature",
  "properties": {
    "iso:country":"NL",
    "sg:address":"Dorpsstr 63",
    "sg:city":"Eexterveen",
    "sg:orig_category":"Farmaceutische Industrie En Groothandel",
    "sg:phone":"+31 598 468 455",
    "sg:postcode":"9658 PJ",
    "sg:province":"Drenthe",
    "wof:name":"Adriani",
    "wof:placetype":"venue"
},
  "geometry": {"coordinates":[6.805545,53.051731],"type":"Point"}
}