{
  "type": "Feature",
  "properties": {
    "addr:full":"Julianalaan 6 Wognum Noord-Holland 1687 BD",
    "addr:housenumber":"6",
    "addr:postcode":"1687 bd",
    "addr:street":"Julianalaan",
    "iso:country":"NL",
    "sg:address":"Julianalaan 6",
    "sg:city":"Wognum",
    "sg:orig_category":"Farmaceutische Producten Gh",
    "sg:phone":"+31 229 571 977",
    "sg:postcode":"1687 BD",
    "sg:province":"Noord-Holland",
    "wof:name":"Verbandtrommelservice Gre Makkes",
    "wof:placetype":"venue"
},
  "geometry": {"coordinates":[5.02825,52.683563],"type":"Point"}
}