{
  "type": "Feature",
  "properties": {
    "addr:full":"Venkel 6 Klazienaveen Provincie Drenthe 7891 DZ",
    "addr:housenumber":"6",
    "addr:postcode":"7891 dz",
    "addr:street":"Venkel;Provincie Drenthe",
    "iso:country":"NL",
    "sg:address":"Venkel 6",
    "sg:city":"Klazienaveen",
    "sg:orig_category":"Ziekenhuizen, Sanatoria, Verpleeghuizen",
    "sg:phone":"+31 591 311 429",
    "sg:postcode":"7891 DZ",
    "sg:province":"Provincie Drenthe",
    "wof:name":"Weegbree, De",
    "wof:placetype":"venue"
},
  "geometry": {"coordinates":[6.988507,52.724991],"type":"Point"}
}