{
  "type": "Feature",
  "properties": {
    "addr:full":"Kerklaan 21 Moordrecht South Holland 2841 XH",
    "addr:housenumber":"21",
    "addr:postcode":"2841 xh",
    "addr:street":"Kerklaan",
    "iso:country":"NL",
    "sg:address":"Kerklaan 21",
    "sg:city":"Moordrecht",
    "sg:orig_category":"Bloemen And Planten",
    "sg:phone":"+31 182 373 541",
    "sg:postcode":"2841 XH",
    "sg:province":"South Holland",
    "wof:name":"Groene Vingers",
    "wof:placetype":"venue"
},
  "geometry": {"coordinates":[4.669969,51.986694],"type":"Point"}
}