{
  "type": "Feature",
  "properties": {
    "iso:country":"NL",
    "sg:address":"Not Oostingstr 18",
    "sg:city":"Emmen",
    "sg:orig_category":"Biljartzalen",
    "sg:phone":"+31 591 613 999",
    "sg:postcode":"7811 CT",
    "sg:province":"Drenthe",
    "wof:name":"Big Balls",
    "wof:placetype":"venue"
},
  "geometry": {"coordinates":[6.894578,52.7841],"type":"Point"}
}