{
  "type": "Feature",
  "properties": {
    "addr:full":"Singel 3 Vierpolders South Holland 3237 AS",
    "addr:housenumber":"3",
    "addr:postcode":"3237 as",
    "addr:street":"Singel",
    "iso:country":"NL",
    "sg:address":"Singel 3",
    "sg:city":"Vierpolders",
    "sg:orig_category":"Heiwerken En Funderingstechniek",
    "sg:phone":"+31 181 412 831",
    "sg:postcode":"3237 AS",
    "sg:province":"South Holland",
    "wof:name":"Funtec",
    "wof:placetype":"venue"
},
  "geometry": {"coordinates":[4.18114,51.878914],"type":"Point"}
}