{
  "type": "Feature",
  "properties": {
    "iso:country":"NL",
    "sg:address":"Maerelaan 3",
    "sg:city":"Heemskerk",
    "sg:orig_category":"Advocaten And Juridische Adviseurs",
    "sg:phone":"+31 251 246 644",
    "sg:postcode":"1961 KA",
    "sg:province":"Noord-Holland",
    "wof:name":"Advocatenkantoor Mellema",
    "wof:placetype":"venue"
},
  "geometry": {"coordinates":[4.672787,52.510761],"type":"Point"}
}