{
  "type": "Feature",
  "properties": {
    "addr:full":"Piksenbrink 5 Enschede Overijssel 7544 BE",
    "addr:housenumber":"5",
    "addr:postcode":"7544",
    "addr:street":"Piksenbrink",
    "iso:country":"NL",
    "sg:address":"Piksenbrink 5",
    "sg:city":"Enschede",
    "sg:orig_category":"Metaalwerken",
    "sg:phone":"+31 53 476 6776",
    "sg:postcode":"7544 BE",
    "sg:province":"Overijssel",
    "wof:name":"Sundecor",
    "wof:placetype":"venue"
},
  "geometry": {"coordinates":[6.872387,52.196041],"type":"Point"}
}