{
  "type": "Feature",
  "properties": {
    "iso:country":"NL",
    "sg:address":"Piksenbrink 5",
    "sg:city":"Enschede",
    "sg:orig_category":"Metaalwerken",
    "sg:phone":"+31 53 476 6776",
    "sg:postcode":"7544 BE",
    "sg:province":"Overijssel",
    "wof:name":"Sundecor",
    "wof:placetype":"venue"
},
  "geometry": {"coordinates":[6.872387,52.196041],"type":"Point"}
}