{
  "type": "Feature",
  "properties": {
    "addr:full":"Pres Kennedyln 98 Amsterdam Noord-Holland 1079 NH",
    "addr:housenumber":"98",
    "addr:postcode":"1079 nh",
    "iso:country":"NL",
    "sg:address":"Pres Kennedyln 98",
    "sg:city":"Amsterdam",
    "sg:orig_category":"Administratie- En Boekhoudkantoren",
    "sg:phone":"+31 20 644 9808",
    "sg:postcode":"1079 NH",
    "sg:province":"Noord-Holland",
    "wof:name":"Hgdo",
    "wof:placetype":"venue"
},
  "geometry": {"coordinates":[4.90256,52.339931],"type":"Point"}
}