{
  "type": "Feature",
  "properties": {
    "addr:full":"Kapellestr 30 Sluis Zeeland 4524 CZ",
    "addr:housenumber":"30",
    "addr:postcode":"4524",
    "addr:street":"Kapellestr",
    "iso:country":"NL",
    "sg:address":"Kapellestr 30",
    "sg:city":"Sluis",
    "sg:orig_category":"Schoenen",
    "sg:phone":"+31 117 462 313",
    "sg:postcode":"4524 CZ",
    "sg:province":"Zeeland",
    "wof:name":"Maxim",
    "wof:placetype":"venue"
},
  "geometry": {"coordinates":[15.47527,49.803791],"type":"Point"}
}