{
  "type": "Feature",
  "properties": {
    "addr:full":"Hoofdstraat 10 Ried Friesland 8811 HD",
    "addr:housenumber":"10",
    "addr:postcode":"8811 hd",
    "addr:street":"Hoofdstraat",
    "iso:country":"NL",
    "sg:address":"Hoofdstraat 10",
    "sg:city":"Ried",
    "sg:orig_category":"Koeriersdiensten",
    "sg:phone":"+31 517 269 575",
    "sg:postcode":"8811 HD",
    "sg:province":"Friesland",
    "wof:name":"Meren Post",
    "wof:placetype":"venue"
},
  "geometry": {"coordinates":[5.591151,53.222977],"type":"Point"}
}