{
  "type": "Feature",
  "properties": {
    "addr:full":"Middag 91 Babberich Gelderland 6909 CC",
    "addr:housenumber":"91",
    "addr:postcode":"6909 cc",
    "addr:street":"Middag;Gelderland",
    "iso:country":"NL",
    "sg:address":"Middag 91",
    "sg:city":"Babberich",
    "sg:orig_category":"Fotoreportages",
    "sg:phone":"+31 316 248 835",
    "sg:postcode":"6909 CC",
    "sg:province":"Gelderland",
    "wof:name":"Artistique Bv",
    "wof:placetype":"venue"
},
  "geometry": {"coordinates":[6.113691,51.906746],"type":"Point"}
}