{
  "type": "Feature",
  "properties": {
    "iso:country":"NL",
    "sg:address":"Dr Jan Van Breemenstraat 4",
    "sg:city":"Amsterdam",
    "sg:orig_category":"Organisaties And Verenigingen",
    "sg:phone":"+31 20 589 6464",
    "sg:postcode":"1056 AB",
    "sg:province":"Noord-Holland",
    "wof:name":"Nederlandse Vereniging V Reumabestrijding",
    "wof:placetype":"venue"
},
  "geometry": {"coordinates":[4.844481945,52.3710746765],"type":"Point"}
}