{
  "type": "Feature",
  "properties": {
    "addr:full":"W Buytewechstr 107C Rotterdam Zuid-Holland 3024 XB",
    "addr:housenumber":"107c",
    "addr:postcode":"3024 xb",
    "addr:street":"W",
    "iso:country":"NL",
    "sg:address":"W Buytewechstr 107C",
    "sg:city":"Rotterdam",
    "sg:orig_category":"Modellenbureaus En Modellen Freelance",
    "sg:phone":"+31 10 244 7070",
    "sg:postcode":"3024 XB",
    "sg:province":"Zuid-Holland",
    "wof:name":"D-Face",
    "wof:placetype":"venue"
},
  "geometry": {"coordinates":[4.457305,51.906807],"type":"Point"}
}