{
  "type": "Feature",
  "properties": {
    "addr:full":"Jan Valsterweg 103 Dordrecht Zuid-Holland 3315 LG",
    "addr:housenumber":"103",
    "addr:postcode":"3315 lg",
    "addr:street":"Jan Valsterweg",
    "iso:country":"NL",
    "sg:address":"Jan Valsterweg 103",
    "sg:city":"Dordrecht",
    "sg:orig_category":"Public Relationbureaus",
    "sg:phone":"+31 78 616 5588",
    "sg:postcode":"3315 LG",
    "sg:province":"Zuid-Holland",
    "wof:name":"Reclame Adviesbureau Mz + Partners Bv",
    "wof:placetype":"venue"
},
  "geometry": {"coordinates":[4.703024,51.804066],"type":"Point"}
}