{
  "type": "Feature",
  "properties": {
    "iso:country":"NL",
    "sg:address":"Steenstraat 4",
    "sg:city":"Wijk Bij Duurstede",
    "sg:orig_category":"Apothekers",
    "sg:phone":"+31 343 573 603",
    "sg:postcode":"3961 VP",
    "sg:province":"Utrecht",
    "wof:name":"Apotheek Dorestede",
    "wof:placetype":"venue"
},
  "geometry": {"coordinates":[5.344042,51.974789],"type":"Point"}
}