{
  "type": "Feature",
  "properties": {
    "addr:full":"De La Reylaan 34/25 Zeist Utrecht 3707 TM",
    "addr:housenumber":"34 / 25",
    "addr:postcode":"3707 tm",
    "addr:street":"De La Reylaan",
    "iso:country":"NL",
    "sg:address":"De La Reylaan 34/25",
    "sg:city":"Zeist",
    "sg:orig_category":"Meubelreparatie And -Restauratie",
    "sg:phone":"+31 30 692 4120",
    "sg:postcode":"3707 TM",
    "sg:province":"Utrecht",
    "wof:name":"Theo Schenk Meubelrestauratie",
    "wof:placetype":"venue"
},
  "geometry": {"coordinates":[5.248047,52.092083],"type":"Point"}
}