{
  "type": "Feature",
  "properties": {
    "iso:country":"NL",
    "sg:address":"Nikkelstr 18",
    "sg:city":"Naarden",
    "sg:orig_category":"Kunststoffen- Verwerkende Industrie",
    "sg:phone":"+31 35 694 5545",
    "sg:postcode":"1411 AK",
    "sg:province":"Noord-Holland",
    "wof:name":"Akf/ Agf Bv",
    "wof:placetype":"venue"
},
  "geometry": {"coordinates":[5.146982,52.304325],"type":"Point"}
}