{
  "type": "Feature",
  "properties": {
    "iso:country":"NL",
    "sg:address":"Parallelwg 11",
    "sg:city":"Veenendaal",
    "sg:orig_category":"Cafetaria'S",
    "sg:phone":"+31 318 512 700",
    "sg:postcode":"3903 BA",
    "sg:province":"Utrecht",
    "wof:name":"Engelenburg, Van",
    "wof:placetype":"venue"
},
  "geometry": {"coordinates":[5.551156,52.017803],"type":"Point"}
}