{
  "type": "Feature",
  "properties": {
    "addr:full":"Planetenbaan 46 De Hummeltjes Ysselstein Ut Utrecht 3402 HP",
    "addr:housenumber":"46",
    "addr:postcode":"3402 hp",
    "addr:street":"Planetenbaan",
    "iso:country":"NL",
    "sg:address":"Planetenbaan 46 De Hummeltjes",
    "sg:city":"Ysselstein Ut",
    "sg:orig_category":"Peuterspeelzalen",
    "sg:phone":"+31 30 688 9260",
    "sg:postcode":"3402 HP",
    "sg:province":"Utrecht",
    "wof:name":"Welzijnswerk Ysselsteinse, Sticht",
    "wof:placetype":"venue"
},
  "geometry": {"coordinates":[5.0281,52.02663],"type":"Point"}
}