{
  "type": "Feature",
  "properties": {
    "addr:full":"Hoenderstr 10 Ledeacker Noord-Brabant 5846 AE",
    "addr:housenumber":"10",
    "addr:postcode":"5846 ae",
    "addr:street":"Hoenderstr",
    "iso:country":"NL",
    "sg:address":"Hoenderstr 10",
    "sg:city":"Ledeacker",
    "sg:orig_category":"Dierenvoeder - Fabrieken",
    "sg:phone":"+31 485 382 324",
    "sg:postcode":"5846 AE",
    "sg:province":"Noord-Brabant",
    "wof:name":"Jarco",
    "wof:placetype":"venue"
},
  "geometry": {"coordinates":[5.862988,51.635342],"type":"Point"}
}