{
  "type": "Feature",
  "properties": {
    "addr:full":"Postbus 3978 Breda Noord-Brabant 4800 DZ",
    "addr:housenumber":"3978",
    "addr:postcode":"breda;4800 dz",
    "addr:street":"Postbus",
    "iso:country":"NL",
    "sg:address":"Postbus 3978",
    "sg:city":"Breda",
    "sg:orig_category":"Koeriersdiensten",
    "sg:phone":"+31 6 18822263",
    "sg:postcode":"4800 DZ",
    "sg:province":"Noord-Brabant",
    "sg:website":"http://www.postbusexpress.nl",
    "wof:name":"Postbusexpress.Nl",
    "wof:placetype":"venue"
},
  "geometry": {"coordinates":[4.77492,51.588699],"type":"Point"}
}