{
  "type": "Feature",
  "properties": {
    "iso:country":"NL",
    "sg:address":"Klaproos 15",
    "sg:city":"Bergambacht",
    "sg:classifiers":[
        {
            "category":"Personal",
            "subcategory":"Nail Salon",
            "type":"Services"
        }
    ],
    "sg:phone":"+31 182 352 483",
    "sg:postcode":"2861 WK",
    "sg:province":"Zuid-Holland",
    "sg:tags":[
        "pedicure"
    ],
    "wof:name":"Koldenhof-Burggraaf, W G",
    "wof:placetype":"venue"
},
  "geometry": {"coordinates":[4.792838,51.936573],"type":"Point"}
}