{
  "type": "Feature",
  "properties": {
    "addr:full":"Plompertstraat 114 Rotterdam South Holland 3087 BD",
    "addr:housenumber":"114",
    "addr:postcode":"3087 bd",
    "addr:street":"Plompertstraat",
    "iso:country":"NL",
    "sg:address":"Plompertstraat 114",
    "sg:city":"Rotterdam",
    "sg:orig_category":"Partycatering And -Organisatie",
    "sg:phone":"+31 10 429 7030",
    "sg:postcode":"3087 BD",
    "sg:province":"South Holland",
    "wof:name":"Marinus Van Donk Party- En Cateringservice",
    "wof:placetype":"venue"
},
  "geometry": {"coordinates":[4.459604,51.887066],"type":"Point"}
}