{
  "type": "Feature",
  "properties": {
    "addr:full":"Bremhorstln 8 Wassenaar Zuid-Holland 2244 ES",
    "addr:housenumber":"8",
    "addr:postcode":"2244 es",
    "addr:street":"Bremhorstln",
    "iso:country":"NL",
    "sg:address":"Bremhorstln 8",
    "sg:city":"Wassenaar",
    "sg:orig_category":"Adviesbureaus Bedrijfsorganisatie",
    "sg:phone":"+31 70 326 2234",
    "sg:postcode":"2244 ES",
    "sg:province":"Zuid-Holland",
    "wof:name":"Dialogix",
    "wof:placetype":"venue"
},
  "geometry": {"coordinates":[4.3652191162,52.1133728027],"type":"Point"}
}