{
  "type": "Feature",
  "properties": {
    "addr:full":"Dorpsstr 174C Halsteren Noord-Brabant 4661 HV",
    "addr:housenumber":"174c",
    "addr:postcode":"4661 hv",
    "addr:street":"Dorpsstr",
    "iso:country":"NL",
    "sg:address":"Dorpsstr 174C",
    "sg:city":"Halsteren",
    "sg:orig_category":"Bloemen En Planten",
    "sg:phone":"+31 164 684 404",
    "sg:postcode":"4661 HV",
    "sg:province":"Noord-Brabant",
    "sg:website":"http://www.bloemenstal.nl/halsteren.net",
    "wof:name":"Bloemenstal Vof, De",
    "wof:placetype":"venue"
},
  "geometry": {"coordinates":[4.272297,51.522339],"type":"Point"}
}