{
  "type": "Feature",
  "properties": {
    "addr:full":"Morelstr 69B Utrecht Utrecht 3552 GM",
    "addr:housenumber":"69b",
    "addr:postcode":"3552 gm",
    "addr:street":"Morelstr",
    "iso:country":"NL",
    "sg:address":"Morelstr 69B",
    "sg:city":"Utrecht",
    "sg:orig_category":"Cafetaria'S",
    "sg:phone":"+31 30 244 4933",
    "sg:postcode":"3552 GM",
    "sg:province":"Utrecht",
    "wof:name":"Pascal",
    "wof:placetype":"venue"
},
  "geometry": {"coordinates":[5.10372,52.108692],"type":"Point"}
}