{
  "type": "Feature",
  "properties": {
    "addr:full":"Industriewg 13 Woerden Utrecht 3442 AE",
    "addr:housenumber":"13",
    "addr:postcode":"3442 ae",
    "addr:street":"Industriewg",
    "iso:country":"NL",
    "sg:address":"Industriewg 13",
    "sg:city":"Woerden",
    "sg:orig_category":"Organisatiebureaus",
    "sg:phone":"+31 348 437 060",
    "sg:postcode":"3442 AE",
    "sg:province":"Utrecht",
    "wof:name":"Image 3000 Bv",
    "wof:placetype":"venue"
},
  "geometry": {"coordinates":[4.8790440559,52.0806503296],"type":"Point"}
}