{
  "type": "Feature",
  "properties": {
    "addr:full":"Beyerlandseln 11A Rotterdam Zuid-Holland 3074 EA",
    "addr:housenumber":"11a",
    "addr:postcode":"3074 ea",
    "addr:street":"Beyerlandseln",
    "iso:country":"NL",
    "sg:address":"Beyerlandseln 11A",
    "sg:city":"Rotterdam",
    "sg:orig_category":"Kinderopvang",
    "sg:phone":"+31 10 290 9960",
    "sg:postcode":"3074 EA",
    "sg:province":"Zuid-Holland",
    "wof:name":"Stip, Stichting",
    "wof:placetype":"venue"
},
  "geometry": {"coordinates":[4.51149,51.89608],"type":"Point"}
}