{
  "type": "Feature",
  "properties": {
    "iso:country":"NL",
    "sg:address":"Parkweg 2",
    "sg:city":"'S Gravenhage",
    "sg:orig_category":"Schoenen",
    "sg:phone":"+31 70 355 0233",
    "sg:postcode":"2585 JJ",
    "sg:province":"Zuid-Holland",
    "wof:name":"Carrington & Reeves",
    "wof:placetype":"venue"
},
  "geometry": {"coordinates":[4.286016,52.098289],"type":"Point"}
}