{
  "type": "Feature",
  "properties": {
    "addr:full":"Postbus 82112 'S-Gravenhage Flevoland 2508 EC",
    "addr:housenumber":"82112",
    "addr:postcode":"2508 ec",
    "addr:street":"Postbus;Flevoland",
    "iso:country":"NL",
    "sg:address":"Postbus 82112",
    "sg:city":"'S-Gravenhage",
    "sg:orig_category":"Verzekeringen - Verzekeringskantoren",
    "sg:phone":"+31 70 306 0742",
    "sg:postcode":"2508 EC",
    "sg:province":"Flevoland",
    "wof:name":"Spaarbelegger, De",
    "wof:placetype":"venue"
},
  "geometry": {"coordinates":[4.31361,52.07832],"type":"Point"}
}