{
  "type": "Feature",
  "properties": {
    "addr:full":"T Hoog 1 Vleuten Utrecht 3451 RC",
    "addr:housenumber":"1",
    "addr:postcode":"3451 rc",
    "addr:street":"T Hoog",
    "iso:country":"NL",
    "sg:address":"T Hoog 1",
    "sg:city":"Vleuten",
    "sg:orig_category":"Betonboringen",
    "sg:phone":"+31 30 677 3829",
    "sg:postcode":"3451 RC",
    "sg:province":"Utrecht",
    "wof:name":"Kroon",
    "wof:placetype":"venue"
},
  "geometry": {"coordinates":[4.991945,52.102577],"type":"Point"}
}