{
  "type": "Feature",
  "properties": {
    "addr:full":"Lemsterhoek 13 Rotterdam Zuid-Holland 3085 EG",
    "addr:housenumber":"13",
    "addr:postcode":"3085 eg",
    "addr:street":"Lemsterhoek",
    "iso:country":"NL",
    "sg:address":"Lemsterhoek 13",
    "sg:city":"Rotterdam",
    "sg:orig_category":"Montagebedrijven",
    "sg:phone":"+31 6 51122704",
    "sg:postcode":"3085 EG",
    "sg:province":"Zuid-Holland",
    "wof:name":"Kerdel",
    "wof:placetype":"venue"
},
  "geometry": {"coordinates":[4.487381,51.872543],"type":"Point"}
}