{
  "type": "Feature",
  "properties": {
    "addr:full":"Ambachtstr 7 Utrecht Utrecht 3512 ER",
    "addr:housenumber":"7",
    "addr:postcode":"3512 er",
    "addr:street":"Ambachtstr",
    "iso:country":"NL",
    "sg:address":"Ambachtstr 7",
    "sg:city":"Utrecht",
    "sg:orig_category":"Verzekeringen - Verzekeringskantoren",
    "sg:phone":"+31 30 231 7572",
    "sg:postcode":"3512 ER",
    "sg:province":"Utrecht",
    "wof:name":"Opstelten",
    "wof:placetype":"venue"
},
  "geometry": {"coordinates":[5.124434,52.092648],"type":"Point"}
}