{
  "type": "Feature",
  "properties": {
    "addr:full":"Spaarnestraat 4 Rotterdam Zuid-Holland 3044 CM",
    "addr:housenumber":"4",
    "addr:postcode":"3044 cm",
    "addr:street":"Spaarnestraat",
    "iso:country":"NL",
    "sg:address":"Spaarnestraat 4",
    "sg:city":"Rotterdam",
    "sg:orig_category":"Vers Brood And Banket Fab",
    "sg:phone":"+31 10 437 8877",
    "sg:postcode":"3044 CM",
    "sg:province":"Zuid-Holland",
    "wof:name":"Bakkerij A.A. Den Boer Bv",
    "wof:placetype":"venue"
},
  "geometry": {"coordinates":[4.416039,51.936764],"type":"Point"}
}