{
  "type": "Feature",
  "properties": {
    "addr:full":"V Meelstr 16 Zwyndrecht South Holland 3331 KR",
    "addr:housenumber":"16",
    "addr:postcode":"3331 kr",
    "addr:street":"Zwyndrecht South",
    "iso:country":"NL",
    "sg:address":"V Meelstr 16",
    "sg:city":"Zwyndrecht",
    "sg:orig_category":"Kappers",
    "sg:phone":"+31 78 612 7351",
    "sg:postcode":"3331 KR",
    "sg:province":"South Holland",
    "wof:name":"Hilko",
    "wof:placetype":"venue"
},
  "geometry": {"coordinates":[4.6407299042,51.8207015991],"type":"Point"}
}