{
  "type": "Feature",
  "properties": {
    "addr:full":"Willem I I I-Straat 4 Sint Willebrord North Brabant 4711 BW",
    "addr:housenumber":"4",
    "addr:postcode":"4711 bw",
    "addr:street":"Willem I I I-Straat",
    "iso:country":"NL",
    "sg:address":"Willem I I I-Straat 4",
    "sg:city":"Sint Willebrord",
    "sg:orig_category":"Fitnesscentra",
    "sg:phone":"+31 165 383 371",
    "sg:postcode":"4711 BW",
    "sg:province":"North Brabant",
    "wof:name":"Sport + Fitness A. Van De Broek",
    "wof:placetype":"venue"
},
  "geometry": {"coordinates":[4.591566,51.547859],"type":"Point"}
}