{
  "type": "Feature",
  "properties": {
    "addr:full":"Asterwg 7A Amsterdam Noord-Holland 1031 HL",
    "addr:housenumber":"7a",
    "addr:postcode":"1031 hl",
    "addr:street":"Asterwg",
    "iso:country":"NL",
    "sg:address":"Asterwg 7A",
    "sg:city":"Amsterdam",
    "sg:orig_category":"Koeltechniek",
    "sg:phone":"+31 20 631 5326",
    "sg:postcode":"1031 HL",
    "sg:province":"Noord-Holland",
    "wof:name":"Zeeman Koeltechniek",
    "wof:placetype":"venue"
},
  "geometry": {"coordinates":[4.904553,52.389194],"type":"Point"}
}