{
  "type": "Feature",
  "properties": {
    "addr:full":"Volmolengracht 4 Leiden Zuid-Holland 2312 PH",
    "addr:housenumber":"4",
    "addr:postcode":"2312",
    "addr:street":"Volmolengracht",
    "iso:country":"NL",
    "sg:address":"Volmolengracht 4",
    "sg:city":"Leiden",
    "sg:orig_category":"Glaszetten",
    "sg:phone":"+31 71 521 8055",
    "sg:postcode":"2312 PH",
    "sg:province":"Zuid-Holland",
    "wof:name":"Vidre",
    "wof:placetype":"venue"
},
  "geometry": {"coordinates":[4.493022,52.162739],"type":"Point"}
}