{
  "type": "Feature",
  "properties": {
    "iso:country":"NL",
    "sg:address":"Dordsedk 512",
    "sg:city":"Klazienaveen",
    "sg:orig_category":"Haarden En Kachels",
    "sg:phone":"+31 591 311 800",
    "sg:postcode":"7891 NS",
    "sg:province":"Drenthe",
    "wof:name":"Hemel",
    "wof:placetype":"venue"
},
  "geometry": {"coordinates":[6.984777,52.721085],"type":"Point"}
}