{
  "type": "Feature",
  "properties": {
    "addr:full":"Herengracht 48 Leiden Zuid-Holland 2312 LE",
    "addr:housenumber":"48",
    "addr:postcode":"2312 le",
    "addr:street":"Herengracht",
    "iso:country":"NL",
    "sg:address":"Herengracht 48",
    "sg:city":"Leiden",
    "sg:orig_category":"Boekhouders",
    "sg:phone":"+31 71 516 6600",
    "sg:postcode":"2312 LE",
    "sg:province":"Zuid-Holland",
    "wof:name":"Stichting Katholiek Onderwijs Voorschoten",
    "wof:placetype":"venue"
},
  "geometry": {"coordinates":[4.499221,52.15802],"type":"Point"}
}