{
  "type": "Feature",
  "properties": {
    "addr:full":"Peelschol 14 Deurne Noord-Brabant 5754 GP",
    "addr:housenumber":"14",
    "addr:postcode":"5754 gp",
    "addr:street":"Peelschol",
    "iso:country":"NL",
    "sg:address":"Peelschol 14",
    "sg:city":"Deurne",
    "sg:orig_category":"Diverse Grafische Activiteiten",
    "sg:phone":"+31 493 318 764",
    "sg:postcode":"5754 GP",
    "sg:province":"Noord-Brabant",
    "wof:name":"Aja",
    "wof:placetype":"venue"
},
  "geometry": {"coordinates":[5.812673,51.462486],"type":"Point"}
}