{
  "type": "Feature",
  "properties": {
    "addr:full":"Concertweg 3 Alphen A/D Rijn Zuid-Holland 2402 JG",
    "addr:housenumber":"3",
    "addr:postcode":"2402 jg",
    "addr:street":"Concertweg",
    "iso:country":"NL",
    "sg:address":"Concertweg 3",
    "sg:city":"Alphen A/D Rijn",
    "sg:orig_category":"Overheidsdiensten",
    "sg:phone":"+31 172 436 123",
    "sg:postcode":"2402 JG",
    "sg:province":"Zuid-Holland",
    "wof:name":"De Ridder",
    "wof:placetype":"venue"
},
  "geometry": {"coordinates":[4.6591901779,52.1487312317],"type":"Point"}
}