{
  "type": "Feature",
  "properties": {
    "iso:country":"NL",
    "sg:address":"Prof Minckelerswg 4C",
    "sg:city":"Waalwyk",
    "sg:orig_category":"Autoruiten",
    "sg:phone":"+31 416 650 021",
    "sg:postcode":"5144 NZ",
    "sg:province":"North Brabant",
    "wof:name":"Autofix Waalwijk",
    "wof:placetype":"venue"
},
  "geometry": {"coordinates":[5.055504,51.680927],"type":"Point"}
}