{
  "type": "Feature",
  "properties": {
    "addr:full":"Kruisakkers 14 Bergen Op Zoom Noord-Brabant 4613 BV",
    "addr:housenumber":"14",
    "addr:postcode":"4613 bv",
    "addr:street":"Kruisakkers",
    "iso:country":"NL",
    "sg:address":"Kruisakkers 14",
    "sg:city":"Bergen Op Zoom",
    "sg:orig_category":"Parketvloeren - Onderhoud En Reparatie",
    "sg:phone":"+31 164 211 911",
    "sg:postcode":"4613 BV",
    "sg:province":"Noord-Brabant",
    "sg:website":"http://www.bevotechniek.nl",
    "wof:name":"Bevo Parketservice",
    "wof:placetype":"venue"
},
  "geometry": {"coordinates":[4.277876,51.504551],"type":"Point"}
}