{
  "type": "Feature",
  "properties": {
    "addr:full":"Meerkoetstraat 16 Uitgeest North Holland 1911 XG",
    "addr:housenumber":"16",
    "addr:postcode":"1911 xg",
    "addr:street":"Meerkoetstraat",
    "iso:country":"NL",
    "sg:address":"Meerkoetstraat 16",
    "sg:city":"Uitgeest",
    "sg:orig_category":"Fotostudio'S And Fotografen",
    "sg:phone":"+31 251 654 565",
    "sg:postcode":"1911 XG",
    "sg:province":"North Holland",
    "wof:name":"Bram De Hollander Fotografie",
    "wof:placetype":"venue"
},
  "geometry": {"coordinates":[4.708828,52.534424],"type":"Point"}
}