{
  "type": "Feature",
  "properties": {
    "addr:full":"Grt Kerkhof 6 Deventer Overijssel 7411 KT",
    "addr:housenumber":"6",
    "addr:postcode":"7411 kt",
    "addr:street":"Kerkhof",
    "iso:country":"NL",
    "sg:address":"Grt Kerkhof 6",
    "sg:city":"Deventer",
    "sg:orig_category":"Hulpverlening Sociaal",
    "sg:phone":"+31 570 617 842",
    "sg:postcode":"7411 KT",
    "sg:province":"Overijssel",
    "wof:name":"Latijnse School, Sticht",
    "wof:placetype":"venue"
},
  "geometry": {"coordinates":[6.155341,52.251415],"type":"Point"}
}