{
  "type": "Feature",
  "properties": {
    "addr:full":"Wilhelminaln 25 Ruurlo Gelderland 7261 BP",
    "addr:housenumber":"25",
    "addr:postcode":"7261 bp",
    "addr:street":"Wilhelminaln;Gelderland",
    "iso:country":"NL",
    "sg:address":"Wilhelminaln 25",
    "sg:city":"Ruurlo",
    "sg:orig_category":"Kappers",
    "sg:phone":"+31 573 442 490",
    "sg:postcode":"7261 BP",
    "sg:province":"Gelderland",
    "wof:name":"Marga",
    "wof:placetype":"venue"
},
  "geometry": {"coordinates":[6.451753,52.089409],"type":"Point"}
}