{
  "type": "Feature",
  "properties": {
    "iso:country":"NL",
    "sg:address":"Wilhelminaln 25",
    "sg:city":"Ruurlo",
    "sg:orig_category":"Kappers",
    "sg:phone":"+31 573 442 490",
    "sg:postcode":"7261 BP",
    "sg:province":"Gelderland",
    "wof:name":"Marga",
    "wof:placetype":"venue"
},
  "geometry": {"coordinates":[6.451753,52.089409],"type":"Point"}
}