{
  "type": "Feature",
  "properties": {
    "iso:country":"NL",
    "sg:address":"Brinkstr 29",
    "sg:city":"Denekamp",
    "sg:orig_category":"Kappers",
    "sg:phone":"+31 541 351 298",
    "sg:postcode":"7591 DM",
    "sg:province":"NL.08",
    "wof:name":"Tres Jolie",
    "wof:placetype":"venue"
},
  "geometry": {"coordinates":[7.004165,52.376804],"type":"Point"}
}