{
  "type": "Feature",
  "properties": {
    "addr:full":"Oranjestr 123 Gilze North Brabant 5126 BN",
    "addr:housenumber":"123",
    "addr:postcode":"5126 bn",
    "iso:country":"NL",
    "sg:address":"Oranjestr 123",
    "sg:city":"Gilze",
    "sg:orig_category":"Verhuur",
    "sg:phone":"+31 161 453 287",
    "sg:postcode":"5126 BN",
    "sg:province":"North Brabant",
    "wof:name":"Klaassen Junior",
    "wof:placetype":"venue"
},
  "geometry": {"coordinates":[4.927307,51.542442],"type":"Point"}
}