{
  "type": "Feature",
  "properties": {
    "addr:full":"Zoutkeetspln 76 Amsterdam North Holland 1013 LD",
    "addr:housenumber":"76",
    "addr:postcode":"1013 ld",
    "addr:street":"Zoutkeetspln",
    "iso:country":"NL",
    "sg:address":"Zoutkeetspln 76",
    "sg:city":"Amsterdam",
    "sg:orig_category":"Watersportartikelen",
    "sg:phone":"+31 20 622 1955",
    "sg:postcode":"1013 LD",
    "sg:province":"North Holland",
    "wof:name":"Leeuw Anno 1888, J De",
    "wof:placetype":"venue"
},
  "geometry": {"coordinates":[4.8852038383,52.3886642456],"type":"Point"}
}