{
  "type": "Feature",
  "properties": {
    "iso:country":"NL",
    "sg:address":"Grevelingen 20",
    "sg:city":"Alphen A/D Rijn",
    "sg:orig_category":"Meubels And Huishoudapparatuur Gh",
    "sg:phone":"+31 172 416 231",
    "sg:postcode":"2401 DN",
    "sg:province":"Zuid-Holland",
    "wof:name":"P.W.J.A. Griffioen",
    "wof:placetype":"venue"
},
  "geometry": {"coordinates":[4.653135,52.149693],"type":"Point"}
}