{
  "type": "Feature",
  "properties": {
    "addr:full":"Gedep Laanwg 43 Andijk Noord-Holland 1619 PB",
    "addr:housenumber":"43",
    "addr:postcode":"1619 pb",
    "iso:country":"NL",
    "sg:address":"Gedep Laanwg 43",
    "sg:city":"Andijk",
    "sg:orig_category":"Zonweringen",
    "sg:phone":"+31 228 591 326",
    "sg:postcode":"1619 PB",
    "sg:province":"Noord-Holland",
    "wof:name":"Zeehoek, De",
    "wof:placetype":"venue"
},
  "geometry": {"coordinates":[5.196393,52.732418],"type":"Point"}
}