{
  "type": "Feature",
  "properties": {
    "addr:full":"Tolnegenwg 47 Stroe Gelderland 3776 PT",
    "addr:housenumber":"47",
    "addr:postcode":"3776",
    "addr:street":"Tolnegenwg;Gelderland;Pt",
    "iso:country":"NL",
    "sg:address":"Tolnegenwg 47",
    "sg:city":"Stroe",
    "sg:orig_category":"Accountants - Administratie- Consulenten En -Kantoren",
    "sg:phone":"+31 342 443 188",
    "sg:postcode":"3776 PT",
    "sg:province":"Gelderland",
    "wof:name":"Miltenburg & Jansen, Van",
    "wof:placetype":"venue"
},
  "geometry": {"coordinates":[5.681159,52.192596],"type":"Point"}
}