{
  "type": "Feature",
  "properties": {
    "iso:country":"NL",
    "sg:address":"Raadhuisstr 20",
    "sg:city":"Doetinchem",
    "sg:orig_category":"Nagelstudio'S",
    "sg:phone":"+31 314 394 484",
    "sg:postcode":"7001 EW",
    "sg:province":"Gelderland",
    "wof:name":"B?casse, La",
    "wof:placetype":"venue"
},
  "geometry": {"coordinates":[6.292747,51.964413],"type":"Point"}
}