{
  "type": "Feature",
  "properties": {
    "addr:full":"Lieve Vrouwestraat 28 Amersfoort Utrecht 3811 BR",
    "addr:housenumber":"28",
    "addr:postcode":"3811 br",
    "addr:street":"Lieve Vrouwestraat",
    "iso:country":"NL",
    "sg:address":"Lieve Vrouwestraat 28",
    "sg:city":"Amersfoort",
    "sg:orig_category":"Voeding, Dranken And Tabak Gh",
    "sg:phone":"+31 33 465 3146",
    "sg:postcode":"3811 BR",
    "sg:province":"Utrecht",
    "wof:name":"Teheran Import/Export",
    "wof:placetype":"venue"
},
  "geometry": {"coordinates":[5.387628,52.155876],"type":"Point"}
}