{
  "type": "Feature",
  "properties": {
    "addr:full":"Haven 26 Lauwersoog Groningen 9976 VN",
    "addr:housenumber":"26",
    "addr:postcode":"9976 vn",
    "addr:street":"Haven",
    "iso:country":"NL",
    "sg:address":"Haven 26",
    "sg:city":"Lauwersoog",
    "sg:orig_category":"Garnalen - Groothandel",
    "sg:phone":"+31 519 349 426",
    "sg:postcode":"9976 VN",
    "sg:province":"Groningen",
    "wof:name":"Kant Bv",
    "wof:placetype":"venue"
},
  "geometry": {"coordinates":[6.21264,53.409481],"type":"Point"}
}