{
  "type": "Feature",
  "properties": {
    "iso:country":"NL",
    "sg:address":"Bergsebaan 6A",
    "sg:city":"Wouw",
    "sg:classifiers":[
        {
            "category":"Retail",
            "subcategory":"Auto Repair",
            "type":"Services"
        }
    ],
    "sg:phone":"+31 165 301 579",
    "sg:postcode":"4724 SW",
    "sg:province":"Noord-Brabant",
    "sg:tags":[
        "garage"
    ],
    "sg:website":"http://www.autostrada.nl/vdwege",
    "wof:name":"Wegen, Van Der",
    "wof:placetype":"venue"
},
  "geometry": {"coordinates":[4.379461,51.516479],"type":"Point"}
}