{
  "type": "Feature",
  "properties": {
    "addr:full":"Oudegracht 316 Utrecht Utrecht 3511 PK",
    "addr:housenumber":"316",
    "addr:postcode":"3511 pk",
    "addr:street":"Oudegracht",
    "iso:country":"NL",
    "sg:address":"Oudegracht 316",
    "sg:city":"Utrecht",
    "sg:orig_category":"Binnenhuisarchitecten",
    "sg:phone":"+31 30 231 8608",
    "sg:postcode":"3511 PK",
    "sg:province":"Utrecht",
    "wof:name":"Odette Ex",
    "wof:placetype":"venue"
},
  "geometry": {"coordinates":[5.115405,52.088932],"type":"Point"}
}