{
  "type": "Feature",
  "properties": {
    "iso:country":"NL",
    "sg:address":"G Bomansstr 2",
    "sg:city":"Culemborg",
    "sg:orig_category":"Administratie- En Boekhoudkantoren",
    "sg:phone":"+31 345 611 663",
    "sg:postcode":"4103 WR",
    "sg:province":"Gelderland",
    "sg:website":"http://www.ciad.nl",
    "wof:name":"Ciad Bv",
    "wof:placetype":"venue"
},
  "geometry": {"coordinates":[5.228344,51.948811],"type":"Point"}
}