{
  "type": "Feature",
  "properties": {
    "addr:full":"Postbus 2002 Enschede NL.08 7500 CA",
    "addr:housenumber":"2002",
    "addr:postcode":"7500 ca",
    "addr:street":"Postbus",
    "iso:country":"NL",
    "sg:address":"Postbus 2002",
    "sg:city":"Enschede",
    "sg:orig_category":"Belastingconsulenten/ Belastingadviseurs",
    "sg:phone":"+31 53 430 8585",
    "sg:postcode":"7500 CA",
    "sg:province":"NL.08",
    "sg:website":"http://www.lovotax.nl/",
    "wof:name":"Loyens & Loeff",
    "wof:placetype":"venue"
},
  "geometry": {"coordinates":[6.89112,52.220821],"type":"Point"}
}