{
  "type": "Feature",
  "properties": {
    "addr:full":"Gildehof 4 Tiel Gelderland 4002 HG",
    "addr:housenumber":"4",
    "addr:postcode":"4002 hg",
    "addr:street":"Gildehof;Gelderland",
    "iso:country":"NL",
    "sg:address":"Gildehof 4",
    "sg:city":"Tiel",
    "sg:orig_category":"Projectontwikkeling",
    "sg:phone":"+31 183 625 452",
    "sg:postcode":"4002 HG",
    "sg:province":"Gelderland",
    "wof:name":"Jong Bv, De",
    "wof:placetype":"venue"
},
  "geometry": {"coordinates":[5.42033,51.896103],"type":"Point"}
}