{
  "type": "Feature",
  "properties": {
    "addr:full":"Havikstr 2 Oldenzaal Overijssel 7574 BD",
    "addr:housenumber":"2",
    "addr:postcode":"7574 bd",
    "addr:street":"Havikstr",
    "iso:country":"NL",
    "sg:address":"Havikstr 2",
    "sg:city":"Oldenzaal",
    "sg:orig_category":"Verenigingen En Stichtingen",
    "sg:phone":"+31 541 571 421",
    "sg:postcode":"7574 BD",
    "sg:province":"Overijssel",
    "wof:name":"Impuls 'T Barghoes, Sticht",
    "wof:placetype":"venue"
},
  "geometry": {"coordinates":[6.935573,52.300278],"type":"Point"}
}