{
  "type": "Feature",
  "properties": {
    "addr:full":"Tentstr 86 Vaals Limburg 6291 BJ",
    "addr:housenumber":"86",
    "addr:postcode":"6291 bj",
    "addr:street":"Tentstr",
    "iso:country":"NL",
    "sg:address":"Tentstr 86",
    "sg:city":"Vaals",
    "sg:orig_category":"Kantoor- En Secretariaatsservice",
    "sg:phone":"+31 43 308 0022",
    "sg:postcode":"6291 BJ",
    "sg:province":"Limburg",
    "sg:website":"http://www.comservice.nl",
    "wof:name":"Comservice",
    "wof:placetype":"venue"
},
  "geometry": {"coordinates":[6.0162000656,50.7677574158],"type":"Point"}
}