{
  "type": "Feature",
  "properties": {
    "addr:full":"Thuyaln 1 Gorssel Gelderland 7213 VW",
    "addr:housenumber":"1",
    "addr:postcode":"7213",
    "addr:street":"Thuyaln;Gelderland;Vw",
    "iso:country":"NL",
    "sg:address":"Thuyaln 1",
    "sg:city":"Gorssel",
    "sg:orig_category":"Psychotherapeuten",
    "sg:phone":"+31 575 492 246",
    "sg:postcode":"7213 VW",
    "sg:province":"Gelderland",
    "wof:name":"Duvekot De Jager, Erica",
    "wof:placetype":"venue"
},
  "geometry": {"coordinates":[6.20043,52.198807],"type":"Point"}
}