{
  "type": "Feature",
  "properties": {
    "iso:country":"NL",
    "sg:address":"Geerdinkswg 69",
    "sg:city":"Hengelo Ov",
    "sg:orig_category":"Bloemen En Planten",
    "sg:phone":"+31 74 243 7331",
    "sg:postcode":"7555 DJ",
    "sg:province":"NL.08",
    "wof:name":"Rosa, La",
    "wof:placetype":"venue"
},
  "geometry": {"coordinates":[6.775111,52.260777],"type":"Point"}
}