{
  "type": "Feature",
  "properties": {
    "iso:country":"NL",
    "sg:address":"Pr Margrietstr 10",
    "sg:city":"Baambrugge",
    "sg:orig_category":"Verenigingsgebouwen",
    "sg:phone":"+31 294 291 955",
    "sg:postcode":"1396 JX",
    "sg:province":"Utrecht",
    "wof:name":"Vijf Bogen Dorpshuis, De",
    "wof:placetype":"venue"
},
  "geometry": {"coordinates":[4.987918,52.246033],"type":"Point"}
}