{
  "type": "Feature",
  "properties": {
    "iso:country":"NL",
    "sg:address":"Condorwg 10",
    "sg:city":"Apeldoorn",
    "sg:orig_category":"Winkelinrichting",
    "sg:phone":"+31 55 542 5756",
    "sg:postcode":"7332 AC",
    "sg:province":"Gelderland",
    "sg:website":"http://www.ssap.nl",
    "wof:name":"Shop Supplies Apeldoorn",
    "wof:placetype":"venue"
},
  "geometry": {"coordinates":[5.976266861,52.2075195312],"type":"Point"}
}