{
  "type": "Feature",
  "properties": {
    "addr:full":"Verryn Stuartlaan 44 Rijswijk Zh Zuid-Holland 2288 EN",
    "addr:housenumber":"44",
    "addr:postcode":"zh;2288 en",
    "addr:street":"Verryn Stuartlaan",
    "iso:country":"NL",
    "sg:address":"Verryn Stuartlaan 44",
    "sg:city":"Rijswijk Zh",
    "sg:orig_category":"Diverse Consumentenartikelen Gh",
    "sg:phone":"+31 70 395 0165",
    "sg:postcode":"2288 EN",
    "sg:province":"Zuid-Holland",
    "wof:name":"Euromonde International Bv",
    "wof:placetype":"venue"
},
  "geometry": {"coordinates":[4.330992,52.039139],"type":"Point"}
}