{
  "type": "Feature",
  "properties": {
    "addr:full":"Pekingsngl 47 Ysselstein Ut Utrecht 3404 EC",
    "addr:housenumber":"47",
    "addr:postcode":"3404 ec",
    "addr:street":"Pekingsngl",
    "iso:country":"NL",
    "sg:address":"Pekingsngl 47",
    "sg:city":"Ysselstein Ut",
    "sg:orig_category":"Autorijscholen",
    "sg:phone":"+31 30 262 3530",
    "sg:postcode":"3404 EC",
    "sg:province":"Utrecht",
    "sg:website":"http://www.rijschoolstart.nl",
    "wof:name":"Start, Rijschool",
    "wof:placetype":"venue"
},
  "geometry": {"coordinates":[5.04104,52.009521],"type":"Point"}
}