{
  "type": "Feature",
  "properties": {
    "addr:full":"Esdoornstraat 8 Bentelo Overijssel 7497 ME",
    "addr:housenumber":"8",
    "addr:postcode":"7497 me",
    "addr:street":"Esdoornstraat",
    "iso:country":"NL",
    "sg:address":"Esdoornstraat 8",
    "sg:city":"Bentelo",
    "sg:orig_category":"Diverse Bedrijfsinstallaties Gh",
    "sg:phone":"+31 547 292 644",
    "sg:postcode":"7497 ME",
    "sg:province":"Overijssel",
    "wof:name":"C.H.M. Joersen",
    "wof:placetype":"venue"
},
  "geometry": {"coordinates":[6.683041,52.225368],"type":"Point"}
}