{
  "type": "Feature",
  "properties": {
    "iso:country":"NL",
    "sg:address":"Bredasewg 108/Sectie 6",
    "sg:city":"Oosterhout Nb",
    "sg:orig_category":"Fotografie Reclame En Mode",
    "sg:phone":"+31 162 421 489",
    "sg:postcode":"4902 NS",
    "sg:province":"North Brabant",
    "sg:website":"http://www.ronhuizer.nl",
    "wof:name":"Huizer, Ron",
    "wof:placetype":"venue"
},
  "geometry": {"coordinates":[4.85625,51.643051],"type":"Point"}
}