{
  "type": "Feature",
  "properties": {
    "addr:full":"Tempeliersstraat 14 Haarlem Noord-Holland 2012 ED",
    "addr:housenumber":"14",
    "addr:postcode":"2012 ed",
    "addr:street":"Tempeliersstraat",
    "iso:country":"NL",
    "sg:address":"Tempeliersstraat 14",
    "sg:city":"Haarlem",
    "sg:orig_category":"Bedrijfs- And Managementsconsultants",
    "sg:phone":"+31 23 532 2007",
    "sg:postcode":"2012 ED",
    "sg:province":"Noord-Holland",
    "wof:name":"Bos",
    "wof:placetype":"venue"
},
  "geometry": {"coordinates":[4.62623,52.375778],"type":"Point"}
}