{
  "type": "Feature",
  "properties": {
    "iso:country":"NL",
    "sg:address":"Tempeliersstraat 14",
    "sg:city":"Haarlem",
    "sg:orig_category":"Bedrijfs- And Managementsconsultants",
    "sg:phone":"+31 23 532 2007",
    "sg:postcode":"2012 ED",
    "sg:province":"Noord-Holland",
    "wof:name":"Bos",
    "wof:placetype":"venue"
},
  "geometry": {"coordinates":[4.62623,52.375778],"type":"Point"}
}