{
  "type": "Feature",
  "properties": {
    "addr:full":"Schoolstr 1D Volendam Noord-Holland 1131 CK",
    "addr:housenumber":"1d",
    "addr:postcode":"1131 ck",
    "iso:country":"NL",
    "sg:address":"Schoolstr 1D",
    "sg:city":"Volendam",
    "sg:orig_category":"Artsen - Huisartsen",
    "sg:phone":"+31 299 368 606",
    "sg:postcode":"1131 CK",
    "sg:province":"Noord-Holland",
    "wof:name":"Schilder, A G M",
    "wof:placetype":"venue"
},
  "geometry": {"coordinates":[5.068712,52.494286],"type":"Point"}
}