{
  "type": "Feature",
  "properties": {
    "addr:full":"Lindeplein 4 Brunssum Limburg 6444 AT",
    "addr:housenumber":"4",
    "addr:postcode":"6444",
    "addr:street":"Lindeplein",
    "iso:country":"NL",
    "sg:address":"Lindeplein 4",
    "sg:city":"Brunssum",
    "sg:orig_category":"Werving And Selectie Van Tijdelijk Personeel And Uitzendkantoren",
    "sg:phone":"+31 45 525 6161",
    "sg:postcode":"6444 AT",
    "sg:province":"Limburg",
    "wof:name":"Uitzendbureau Start",
    "wof:placetype":"venue"
},
  "geometry": {"coordinates":[5.9701161385,50.9437408447],"type":"Point"}
}