{
  "type": "Feature",
  "properties": {
    "addr:full":"Zuiderstg 16 Purmerend Noord-Holland 1441 BD",
    "addr:housenumber":"16",
    "addr:postcode":"1441 bd",
    "addr:street":"Zuiderstg",
    "iso:country":"NL",
    "sg:address":"Zuiderstg 16",
    "sg:city":"Purmerend",
    "sg:orig_category":"Fietsen En Bromfietsen",
    "sg:phone":"+31 299 429 962",
    "sg:postcode":"1441 BD",
    "sg:province":"Noord-Holland",
    "wof:name":"Pcs",
    "wof:placetype":"venue"
},
  "geometry": {"coordinates":[4.945908,52.508778],"type":"Point"}
}