{
  "type": "Feature",
  "properties": {
    "addr:full":"Noordbuurtsewg 3 Zoeterwoude Zuid-Holland 2381 ER",
    "addr:housenumber":"3",
    "addr:postcode":"2381 er",
    "addr:street":"Noordbuurtsewg",
    "iso:country":"NL",
    "sg:address":"Noordbuurtsewg 3",
    "sg:city":"Zoeterwoude",
    "sg:orig_category":"Administratie- En Boekhoudkantoren",
    "sg:phone":"+31 71 580 3338",
    "sg:postcode":"2381 ER",
    "sg:province":"Zuid-Holland",
    "wof:name":"Kroon",
    "wof:placetype":"venue"
},
  "geometry": {"coordinates":[4.497444,52.122608],"type":"Point"}
}