{
  "type": "Feature",
  "properties": {
    "addr:full":"K Onnesstr 21 Zandvoort North Holland 2041 CB",
    "addr:housenumber":"21",
    "addr:postcode":"2041 cb",
    "addr:street":"Onnesstr",
    "iso:country":"NL",
    "sg:address":"K Onnesstr 21",
    "sg:city":"Zandvoort",
    "sg:orig_category":"Autopoetsbedrijven",
    "sg:phone":"+31 23 571 9828",
    "sg:postcode":"2041 CB",
    "sg:province":"North Holland",
    "wof:name":"Visser",
    "wof:placetype":"venue"
},
  "geometry": {"coordinates":[4.52729,52.370747],"type":"Point"}
}