{
  "type": "Feature",
  "properties": {
    "addr:full":"Ijsbaanpad 78 Amsterdam North Holland 1076 CW",
    "addr:housenumber":"78",
    "addr:postcode":"1076 cw",
    "addr:street":"Ijsbaanpad",
    "iso:country":"NL",
    "sg:address":"Ijsbaanpad 78",
    "sg:city":"Amsterdam",
    "sg:orig_category":"Film-, Tv- And Videoproductie",
    "sg:phone":"+31 20 676 4925",
    "sg:postcode":"1076 CW",
    "sg:province":"North Holland",
    "wof:name":"Balou Otter",
    "wof:placetype":"venue"
},
  "geometry": {"coordinates":[4.849215,52.341476],"type":"Point"}
}