{
  "type": "Feature",
  "properties": {
    "iso:country":"NL",
    "sg:address":"Leeghwaterstr 103",
    "sg:city":"Sliedrecht",
    "sg:orig_category":"Meubelen",
    "sg:phone":"+31 184 412 549",
    "sg:postcode":"3364 AE",
    "sg:province":"South Holland",
    "sg:website":"http://www.lundia.nl",
    "wof:name":"Lundia Bv",
    "wof:placetype":"venue"
},
  "geometry": {"coordinates":[4.753887,51.830685],"type":"Point"}
}