{
  "type": "Feature",
  "properties": {
    "addr:full":"Smeerling 16 Onstwedde Groningen 9591 TX",
    "addr:housenumber":"16",
    "addr:postcode":"9591 tx",
    "addr:street":"Smeerling",
    "iso:country":"NL",
    "sg:address":"Smeerling 16",
    "sg:city":"Onstwedde",
    "sg:orig_category":"Antiquiteiten - Restauratie",
    "sg:phone":"+31 599 313 558",
    "sg:postcode":"9591 TX",
    "sg:province":"Groningen",
    "wof:name":"Bert Bakker",
    "wof:placetype":"venue"
},
  "geometry": {"coordinates":[7.081263,53.024788],"type":"Point"}
}