{
  "type": "Feature",
  "properties": {
    "iso:country":"NL",
    "sg:address":"Misterstraat 59",
    "sg:city":"Winterswijk",
    "sg:orig_category":"Kappers",
    "sg:phone":"+31 543 520 599",
    "sg:postcode":"7101 ET",
    "sg:province":"Gelderland",
    "wof:name":"Ami Kappers",
    "wof:placetype":"venue"
},
  "geometry": {"coordinates":[6.715760231,51.9702835083],"type":"Point"}
}