{
  "type": "Feature",
  "properties": {
    "addr:full":"Spaarnwouderweg 1075 Vijfhuizen Noord-Holland 2141 BN",
    "addr:housenumber":"1075",
    "addr:postcode":"vijfhuizen;2141 bn",
    "addr:street":"Spaarnwouderweg",
    "iso:country":"NL",
    "sg:address":"Spaarnwouderweg 1075",
    "sg:city":"Vijfhuizen",
    "sg:orig_category":"Metaalafval, Schrootrecycling And Sloperijen",
    "sg:phone":"+31 23 535 4652",
    "sg:postcode":"2141 BN",
    "sg:province":"Noord-Holland",
    "wof:name":"Autosloperij Dogan",
    "wof:placetype":"venue"
},
  "geometry": {"coordinates":[4.703618,52.37191],"type":"Point"}
}