{
  "type": "Feature",
  "properties": {
    "addr:full":"Molenakkerpln 2 Weert Limburg 6003 BM",
    "addr:housenumber":"2",
    "addr:postcode":"6003 bm",
    "addr:street":"Molenakkerpln",
    "iso:country":"NL",
    "sg:address":"Molenakkerpln 2",
    "sg:city":"Weert",
    "sg:orig_category":"Begrafenisverzorging",
    "sg:phone":"+31 495 550 312",
    "sg:postcode":"6003 BM",
    "sg:province":"Limburg",
    "wof:name":"Ritueel",
    "wof:placetype":"venue"
},
  "geometry": {"coordinates":[5.711414,51.264061],"type":"Point"}
}