{
  "type": "Feature",
  "properties": {
    "addr:full":"Simonspln 9B Doetinchem Gelderland 7001 BM",
    "addr:housenumber":"9b",
    "addr:postcode":"7001 bm",
    "addr:street":"Simonspln;Gelderland",
    "iso:country":"NL",
    "sg:address":"Simonspln 9B",
    "sg:city":"Doetinchem",
    "sg:orig_category":"Herenkleding",
    "sg:phone":"+31 314 392 298",
    "sg:postcode":"7001 BM",
    "sg:province":"Gelderland",
    "sg:website":"http://www.newportblue.nl",
    "wof:name":"Newport Blue",
    "wof:placetype":"venue"
},
  "geometry": {"coordinates":[6.288631,51.965195],"type":"Point"}
}