{
  "type": "Feature",
  "properties": {
    "addr:full":"Spaarneweg 47 Cruquius Noord-Holland 2142 EN",
    "addr:housenumber":"47",
    "addr:postcode":"2142 en",
    "addr:street":"Spaarneweg",
    "iso:country":"NL",
    "sg:address":"Spaarneweg 47",
    "sg:city":"Cruquius",
    "sg:orig_category":"Diverse Bedrijfsinstallaties Gh",
    "sg:phone":"+31 23 529 4648",
    "sg:postcode":"2142 EN",
    "sg:province":"Noord-Holland",
    "wof:name":"Romonta Bv",
    "wof:placetype":"venue"
},
  "geometry": {"coordinates":[4.629405,52.333073],"type":"Point"}
}