{
  "type": "Feature",
  "properties": {
    "iso:country":"NL",
    "sg:address":"De Berken 8",
    "sg:city":"Bergschenhoek",
    "sg:orig_category":"Montagebedrijven",
    "sg:phone":"+31 10 521 8675",
    "sg:postcode":"2661 AW",
    "sg:province":"South Holland",
    "wof:name":"Bloom",
    "wof:placetype":"venue"
},
  "geometry": {"coordinates":[4.494713,51.989712],"type":"Point"}
}