{
  "type": "Feature",
  "properties": {
    "addr:full":"Kloosterdk 85 Sibculo Overijssel 7693 PP",
    "addr:housenumber":"85",
    "addr:postcode":"7693 pp",
    "addr:street":"Kloosterdk",
    "iso:country":"NL",
    "sg:address":"Kloosterdk 85",
    "sg:city":"Sibculo",
    "sg:orig_category":"Bloemen En Planten",
    "sg:phone":"+31 6 53789994",
    "sg:postcode":"7693 PP",
    "sg:province":"Overijssel",
    "wof:name":"Maat Vof, Van De",
    "wof:placetype":"venue"
},
  "geometry": {"coordinates":[6.636887,52.481041],"type":"Point"}
}