{
  "type": "Feature",
  "properties": {
    "iso:country":"NL",
    "sg:address":"De Zoeker Esch 5",
    "sg:city":"Losser",
    "sg:orig_category":"Kunststoffen- Verwerkende Industrie",
    "sg:phone":"+31 53 538 7239",
    "sg:postcode":"7582 CN",
    "sg:province":"NL.08",
    "wof:name":"Final Plastics Ned Bv",
    "wof:placetype":"venue"
},
  "geometry": {"coordinates":[7.00721,52.250561],"type":"Point"}
}