{
  "type": "Feature",
  "properties": {
    "addr:full":"De Zoeker Esch 5 Losser NL.08 7582 CN",
    "addr:housenumber":"5;nl.08",
    "addr:postcode":"7582 cn",
    "addr:street":"De Zoeker Esch",
    "iso:country":"NL",
    "sg:address":"De Zoeker Esch 5",
    "sg:city":"Losser",
    "sg:orig_category":"Kunststoffen- Verwerkende Industrie",
    "sg:phone":"+31 53 538 7239",
    "sg:postcode":"7582 CN",
    "sg:province":"NL.08",
    "wof:name":"Final Plastics Ned Bv",
    "wof:placetype":"venue"
},
  "geometry": {"coordinates":[7.00721,52.250561],"type":"Point"}
}