{
  "type": "Feature",
  "properties": {
    "addr:full":"Crooswyksewg 118 Rotterdam South Holland 3034 HP",
    "addr:housenumber":"118",
    "addr:postcode":"3034 hp",
    "iso:country":"NL",
    "sg:address":"Crooswyksewg 118",
    "sg:city":"Rotterdam",
    "sg:orig_category":"Kaas",
    "sg:phone":"+31 10 411 3047",
    "sg:postcode":"3034 HP",
    "sg:province":"South Holland",
    "wof:name":"Crooswijks Kaashuis",
    "wof:placetype":"venue"
},
  "geometry": {"coordinates":[4.4924030304,51.9304847717],"type":"Point"}
}