{
  "type": "Feature",
  "properties": {
    "addr:full":"Marktstraat 10 Raalte Overijssel 8102 CK",
    "addr:housenumber":"10",
    "addr:postcode":"8102 ck",
    "addr:street":"Marktstraat",
    "iso:country":"NL",
    "sg:address":"Marktstraat 10",
    "sg:city":"Raalte",
    "sg:orig_category":"Kantoorartikelen",
    "sg:phone":"+31 572 360 555",
    "sg:postcode":"8102 CK",
    "sg:province":"Overijssel",
    "wof:name":"Klein Beernink Kantoorvakhandel Bv",
    "wof:placetype":"venue"
},
  "geometry": {"coordinates":[6.2761340141,52.3856163025],"type":"Point"}
}