{
  "type": "Feature",
  "properties": {
    "iso:country":"NL",
    "sg:address":"Marshallweg 7",
    "sg:city":"Rotterdam",
    "sg:orig_category":"Paramedische Behandelingen",
    "sg:phone":"+31 10 456 4252",
    "sg:postcode":"3068 JN",
    "sg:province":"Zuid-Holland",
    "wof:name":"Logopedie Ommoord-Zevenkamp",
    "wof:placetype":"venue"
},
  "geometry": {"coordinates":[4.544768,51.959156],"type":"Point"}
}