{
  "type": "Feature",
  "properties": {
    "iso:country":"NL",
    "sg:address":"Duinkerkenstr 21",
    "sg:city":"Groningen",
    "sg:classifiers":[
        {
            "category":"Wholesale",
            "subcategory":"Meat",
            "type":"Manufacturing & Wholesale Goods"
        }
    ],
    "sg:phone":"+31 50 587 7877",
    "sg:postcode":"9723 BN",
    "sg:province":"Groningen",
    "sg:tags":[
        "regeltechniek",
        "en",
        "meet-"
    ],
    "wof:name":"Schut Bv",
    "wof:placetype":"venue"
},
  "geometry": {"coordinates":[6.60056,53.200474],"type":"Point"}
}