{
  "type": "Feature",
  "properties": {
    "addr:full":"Eikenln 25 Hazerswoude Dorp Zuid-Holland 2391 DV",
    "addr:housenumber":"25",
    "addr:postcode":"2391 dv",
    "addr:street":"Eikenln",
    "iso:country":"NL",
    "sg:address":"Eikenln 25",
    "sg:city":"Hazerswoude Dorp",
    "sg:orig_category":"Keukens",
    "sg:phone":"+31 172 587 358",
    "sg:postcode":"2391 DV",
    "sg:province":"Zuid-Holland",
    "wof:name":"Rdb Design",
    "wof:placetype":"venue"
},
  "geometry": {"coordinates":[4.598354,52.097652],"type":"Point"}
}