{
  "type": "Feature",
  "properties": {
    "addr:full":"Korte Engelenburgerkade 26 Dordrecht Zuid-Holland 3311 CG",
    "addr:housenumber":"26",
    "addr:postcode":"3311 cg",
    "addr:street":"Korte Engelenburgerkade",
    "iso:country":"NL",
    "sg:address":"Korte Engelenburgerkade 26",
    "sg:city":"Dordrecht",
    "sg:orig_category":"Architecten",
    "sg:phone":"+31 78 614 5048",
    "sg:postcode":"3311 CG",
    "sg:province":"Zuid-Holland",
    "wof:name":"Architectenburo Ir. J.C. Stoutjesdijk",
    "wof:placetype":"venue"
},
  "geometry": {"coordinates":[4.66089,51.815132],"type":"Point"}
}