{
  "type": "Feature",
  "properties": {
    "iso:country":"NL",
    "sg:address":"Noordeinde 44",
    "sg:city":"Landsmeer",
    "sg:orig_category":"Makelaars En Adviseurs Onroerende Goederen",
    "sg:phone":"+31 20 482 0525",
    "sg:postcode":"1121 AE",
    "sg:province":"North Holland",
    "wof:name":"Hallie, Geraldine",
    "wof:placetype":"venue"
},
  "geometry": {"coordinates":[4.91402,52.440907],"type":"Point"}
}