{
  "type": "Feature",
  "properties": {
    "addr:full":"Biest 112A Weert Limburg 6001 AT",
    "addr:housenumber":"112a",
    "addr:postcode":"6001",
    "addr:street":"Biest",
    "iso:country":"NL",
    "sg:address":"Biest 112A",
    "sg:city":"Weert",
    "sg:orig_category":"Zalenverhuur",
    "sg:phone":"+31 495 538 221",
    "sg:postcode":"6001 AT",
    "sg:province":"Limburg",
    "wof:name":"Hook, De",
    "wof:placetype":"venue"
},
  "geometry": {"coordinates":[5.713719,51.260056],"type":"Point"}
}