{
  "type": "Feature",
  "properties": {
    "addr:full":"V Hattumstr 8 Ellewoutsdyk Zeeland 4437 AG",
    "addr:housenumber":"8",
    "addr:postcode":"4437",
    "addr:street":"Hattumstr;Zeeland",
    "iso:country":"NL",
    "sg:address":"V Hattumstr 8",
    "sg:city":"Ellewoutsdyk",
    "sg:orig_category":"Hengelsportartikelen",
    "sg:phone":"+31 113 548 554",
    "sg:postcode":"4437 AG",
    "sg:province":"Zeeland",
    "wof:name":"Scaldis",
    "wof:placetype":"venue"
},
  "geometry": {"coordinates":[3.816252,51.388504],"type":"Point"}
}