{
  "type": "Feature",
  "properties": {
    "addr:full":"Beneluxln 305 Hengelo Ov Overijssel 7559 JV",
    "addr:housenumber":"305",
    "addr:postcode":"7559 jv",
    "addr:street":"Ov",
    "iso:country":"NL",
    "sg:address":"Beneluxln 305",
    "sg:city":"Hengelo Ov",
    "sg:orig_category":"Bloemen En Planten - Groothandel",
    "sg:phone":"+31 74 276 6666",
    "sg:postcode":"7559 JV",
    "sg:province":"Overijssel",
    "wof:name":"Twenthe Plant Bv",
    "wof:placetype":"venue"
},
  "geometry": {"coordinates":[6.78971,52.266331],"type":"Point"}
}