{
  "type": "Feature",
  "properties": {
    "addr:full":"Oosterwyk Wz 56A Nieuw Dordrecht Provincie Drenthe 7885 TN",
    "addr:housenumber":"56a",
    "addr:postcode":"7885",
    "addr:street":"Oosterwyk Wz;Nieuw Dordrecht Provincie Drenthe",
    "iso:country":"NL",
    "sg:address":"Oosterwyk Wz 56A",
    "sg:city":"Nieuw Dordrecht",
    "sg:orig_category":"Verenigingsgebouwen",
    "sg:phone":"+31 591 317 373",
    "sg:postcode":"7885 TN",
    "sg:province":"Provincie Drenthe",
    "wof:name":"Soc Kultureel Werk",
    "wof:placetype":"venue"
},
  "geometry": {"coordinates":[6.96808,52.749065],"type":"Point"}
}