{
  "type": "Feature",
  "properties": {
    "addr:full":"Blaricumsngl 20 Tilburg North Brabant 5043 XS",
    "addr:housenumber":"20",
    "addr:postcode":"5043 xs",
    "addr:street":"Blaricumsngl",
    "iso:country":"NL",
    "sg:address":"Blaricumsngl 20",
    "sg:city":"Tilburg",
    "sg:orig_category":"Meubelen - Fabrieken En Groothandel",
    "sg:phone":"+31 13 570 3630",
    "sg:postcode":"5043 XS",
    "sg:province":"North Brabant",
    "wof:name":"Benkske, 'T",
    "wof:placetype":"venue"
},
  "geometry": {"coordinates":[5.019229,51.583206],"type":"Point"}
}