{
  "type": "Feature",
  "properties": {
    "addr:full":"K Doormanstr 30 Rotterdam South Holland 3012 GJ",
    "addr:housenumber":"30",
    "addr:postcode":"3012 gj",
    "addr:street":"Doormanstr",
    "iso:country":"NL",
    "sg:address":"K Doormanstr 30",
    "sg:city":"Rotterdam",
    "sg:orig_category":"Adviesbureaus Bouwkunde",
    "sg:phone":"+31 10 412 4300",
    "sg:postcode":"3012 GJ",
    "sg:province":"South Holland",
    "sg:website":"http://www.corderoy.com",
    "wof:name":"Corderoy Int Neth Bv",
    "wof:placetype":"venue"
},
  "geometry": {"coordinates":[4.473749,51.9226],"type":"Point"}
}