{
  "type": "Feature",
  "properties": {
    "addr:full":"Passage / Corridor 79 Veenendaal Utrecht 3901 AZ",
    "addr:housenumber":"79",
    "addr:postcode":"3901",
    "addr:street":"Passage / Corridor",
    "iso:country":"NL",
    "sg:address":"Passage / Corridor 79",
    "sg:city":"Veenendaal",
    "sg:orig_category":"Kinderkleding",
    "sg:phone":"+31 318 507 670",
    "sg:postcode":"3901 AZ",
    "sg:province":"Utrecht",
    "sg:website":"http://www.toetjuniorstore.nl",
    "wof:name":"Toet Junior Store",
    "wof:placetype":"venue"
},
  "geometry": {"coordinates":[5.55418,52.024902],"type":"Point"}
}