{
  "type": "Feature",
  "properties": {
    "addr:full":"Wilhelminasingel 68 Maastricht Limburg 6221 BK",
    "addr:housenumber":"68",
    "addr:postcode":"6221 bk",
    "addr:street":"Wilhelminasingel",
    "iso:country":"NL",
    "sg:address":"Wilhelminasingel 68",
    "sg:city":"Maastricht",
    "sg:orig_category":"Kappers",
    "sg:phone":"+31 43 321 5425",
    "sg:postcode":"6221 BK",
    "sg:province":"Limburg",
    "wof:name":"Creations Robert Smids",
    "wof:placetype":"venue"
},
  "geometry": {"coordinates":[5.7013998032,50.8497695923],"type":"Point"}
}