{
  "type": "Feature",
  "properties": {
    "addr:full":"Gouwzeestr 234 Purmerend North Holland 1443 KG",
    "addr:housenumber":"234",
    "addr:postcode":"1443 kg",
    "iso:country":"NL",
    "sg:address":"Gouwzeestr 234",
    "sg:city":"Purmerend",
    "sg:orig_category":"Grafisch Ontwerpers",
    "sg:phone":"+31 299 770 789",
    "sg:postcode":"1443 KG",
    "sg:province":"North Holland",
    "wof:name":"Nitin",
    "wof:placetype":"venue"
},
  "geometry": {"coordinates":[4.979236,52.509697],"type":"Point"}
}