{
  "type": "Feature",
  "properties": {
    "addr:full":"Kerkstraat 8 Asten North Brabant 5721 GV",
    "addr:housenumber":"8",
    "addr:postcode":"5721 gv",
    "addr:street":"Kerkstraat",
    "iso:country":"NL",
    "sg:address":"Kerkstraat 8",
    "sg:city":"Asten",
    "sg:orig_category":"Overheidsdiensten",
    "sg:phone":"+31 493 691 349",
    "sg:postcode":"5721 GV",
    "sg:province":"North Brabant",
    "wof:name":"De Klepel",
    "wof:placetype":"venue"
},
  "geometry": {"coordinates":[5.7447981834,51.4025192261],"type":"Point"}
}