{
  "type": "Feature",
  "properties": {
    "iso:country":"NL",
    "sg:address":"Maaldery 5",
    "sg:city":"Nieuwerkerk Yssel",
    "sg:orig_category":"Autotransmissies Automatisch",
    "sg:phone":"+31 180 321 323",
    "sg:postcode":"2913 LZ",
    "sg:province":"Zuid-Holland",
    "wof:name":"A & R Bv",
    "wof:placetype":"venue"
},
  "geometry": {"coordinates":[4.60879,51.980492],"type":"Point"}
}