{
  "type": "Feature",
  "properties": {
    "addr:full":"Schelmseweg 1 Arnhem Gelderland 6816 PA",
    "addr:housenumber":"1",
    "addr:postcode":"6816 pa",
    "addr:street":"Schelmseweg",
    "iso:country":"NL",
    "sg:address":"Schelmseweg 1",
    "sg:city":"Arnhem",
    "sg:classifiers":[
        {
            "category":"Travel",
            "subcategory":"Hotels & Motels",
            "type":"Entertainment"
        }
    ],
    "sg:phone":"+31 26 442 5994",
    "sg:postcode":"6816 PA",
    "sg:province":"Gelderland",
    "wof:name":"Pension Warnsborn",
    "wof:placetype":"venue"
},
  "geometry": {"coordinates":[5.876332,51.99828],"type":"Point"}
}