{
  "type": "Feature",
  "properties": {
    "addr:full":"Marykestr 10 Mill West Virginia 5451 ZK",
    "addr:housenumber":"10",
    "addr:postcode":"5451",
    "addr:street":"Marykestr;Zk",
    "iso:country":"NL",
    "sg:address":"Marykestr 10",
    "sg:city":"Mill",
    "sg:orig_category":"Banden",
    "sg:phone":"+31 485 455 566",
    "sg:postcode":"5451 ZK",
    "sg:province":"West Virginia",
    "wof:name":"Gemert, Hans Van",
    "wof:placetype":"venue"
},
  "geometry": {"coordinates":[-80.143074,38.165218],"type":"Point"}
}