{
  "type": "Feature",
  "properties": {
    "addr:full":"Noordhoevelaan 39 Dordrecht Zuid-Holland 3319 CH",
    "addr:housenumber":"39",
    "addr:postcode":"3319",
    "addr:street":"Noordhoevelaan",
    "iso:country":"NL",
    "sg:address":"Noordhoevelaan 39",
    "sg:city":"Dordrecht",
    "sg:orig_category":"Autokeuringen",
    "sg:phone":"+31 78 621 1210",
    "sg:postcode":"3319 CH",
    "sg:province":"Zuid-Holland",
    "wof:name":"Verkerk Autobedrijf",
    "wof:placetype":"venue"
},
  "geometry": {"coordinates":[4.699313,51.800224],"type":"Point"}
}