{
  "type": "Feature",
  "properties": {
    "addr:full":"Meinweg 228 Herkenbosch Limburg 6075 NA",
    "addr:housenumber":"228",
    "addr:postcode":"6075 na",
    "addr:street":"Meinweg",
    "iso:country":"NL",
    "sg:address":"Meinweg 228",
    "sg:city":"Herkenbosch",
    "sg:classifiers":[
        {
            "category":"Food & Beverages",
            "subcategory":"Fruits & Vegetables",
            "type":"Retail Goods"
        }
    ],
    "sg:phone":"+31 475 533 019",
    "sg:postcode":"6075 NA",
    "sg:province":"Limburg",
    "sg:tags":[
        "groenten"
    ],
    "wof:name":"A. Willemsen",
    "wof:placetype":"venue"
},
  "geometry": {"coordinates":[6.066254,51.154297],"type":"Point"}
}