{
  "type": "Feature",
  "properties": {
    "addr:full":"De Factory 10B Zwaag Noord-Holland 1689 AL",
    "addr:housenumber":"10b",
    "addr:postcode":"1689 al",
    "addr:street":"De Factory",
    "iso:country":"NL",
    "sg:address":"De Factory 10B",
    "sg:city":"Zwaag",
    "sg:orig_category":"Biljarts - Fabrieken",
    "sg:phone":"+31 229 214 738",
    "sg:postcode":"1689 AL",
    "sg:province":"Noord-Holland",
    "wof:name":"Feller Biljart Vof",
    "wof:placetype":"venue"
},
  "geometry": {"coordinates":[5.065337,52.667259],"type":"Point"}
}