{
  "type": "Feature",
  "properties": {
    "addr:full":"Dalweg 4A Eexterzandvoort Provincie Drenthe 9464 TE",
    "addr:housenumber":"4a;9464",
    "addr:postcode":"te",
    "addr:street":"Dalweg;Provincie Drenthe",
    "iso:country":"NL",
    "sg:address":"Dalweg 4A",
    "sg:city":"Eexterzandvoort",
    "sg:orig_category":"Kampeerterreinen",
    "sg:phone":"+31 598 468 333",
    "sg:postcode":"9464 TE",
    "sg:province":"Provincie Drenthe",
    "wof:name":"Oostermoer",
    "wof:placetype":"venue"
},
  "geometry": {"coordinates":[6.7871489525,53.0323753357],"type":"Point"}
}