{
  "type": "Feature",
  "properties": {
    "iso:country":"NL",
    "sg:address":"Erfvoort 28",
    "sg:city":"Noordwykerhout",
    "sg:orig_category":"Autorijscholen",
    "sg:phone":"+31 252 375 694",
    "sg:postcode":"2211 DE",
    "sg:province":"Zuid-Holland",
    "wof:name":"Margreth, Autorijschool",
    "wof:placetype":"venue"
},
  "geometry": {"coordinates":[4.488725,52.262447],"type":"Point"}
}