{
  "type": "Feature",
  "properties": {
    "addr:full":"Minervum 7040 Breda Noord-Brabant 4817 ZL",
    "addr:housenumber":"7040",
    "addr:postcode":"breda;4817 zl",
    "addr:street":"Minervum",
    "iso:country":"NL",
    "sg:address":"Minervum 7040",
    "sg:city":"Breda",
    "sg:orig_category":"Diverse Bedrijfsinstallaties Gh",
    "sg:phone":"+31 76 572 0820",
    "sg:postcode":"4817 ZL",
    "sg:province":"Noord-Brabant",
    "wof:name":"Sandvik Process Systems Bv",
    "wof:placetype":"venue"
},
  "geometry": {"coordinates":[4.829872,51.587402],"type":"Point"}
}