{
  "type": "Feature",
  "properties": {
    "addr:full":"In De Cramer 24 Heerlen Limburg 6411 RS",
    "addr:housenumber":"24",
    "addr:postcode":"6411 rs",
    "addr:street":"In De Cramer",
    "iso:country":"NL",
    "sg:address":"In De Cramer 24",
    "sg:city":"Heerlen",
    "sg:orig_category":"Bloemen And Planten",
    "sg:phone":"+31 45 574 1342",
    "sg:postcode":"6411 RS",
    "sg:province":"Limburg",
    "wof:name":"De Boekettenspecialist Overtoom Vof",
    "wof:placetype":"venue"
},
  "geometry": {"coordinates":[5.957212,50.895241],"type":"Point"}
}