{
  "type": "Feature",
  "properties": {
    "addr:full":"Berlagelaan 39 Bilthoven Utrecht 3723 AA",
    "addr:housenumber":"39",
    "addr:postcode":"3723 aa",
    "addr:street":"Berlagelaan",
    "iso:country":"NL",
    "sg:address":"Berlagelaan 39",
    "sg:city":"Bilthoven",
    "sg:orig_category":"Diverse Grafische Activiteiten",
    "sg:phone":"+31 30 228 1097",
    "sg:postcode":"3723 AA",
    "sg:province":"Utrecht",
    "wof:name":"W. Burleson - Patist",
    "wof:placetype":"venue"
},
  "geometry": {"coordinates":[5.188734,52.127632],"type":"Point"}
}