{
  "type": "Feature",
  "properties": {
    "iso:country":"NL",
    "sg:address":"Broekestraat 18",
    "sg:city":"Venlo",
    "sg:orig_category":"Bloemen And Planten Gh",
    "sg:phone":"+31 77 320 0613",
    "sg:postcode":"5912 PD",
    "sg:province":"Limburg",
    "wof:name":"J.W.M. Christis",
    "wof:placetype":"venue"
},
  "geometry": {"coordinates":[6.173726,51.356754],"type":"Point"}
}