{
  "type": "Feature",
  "properties": {
    "addr:full":"G V Prinstererwg 29 Katwyk Zh South Holland 2221 AB",
    "addr:housenumber":"29;zh",
    "addr:postcode":"2221 ab",
    "addr:street":"V Prinstererwg",
    "iso:country":"NL",
    "sg:address":"G V Prinstererwg 29",
    "sg:city":"Katwyk Zh",
    "sg:orig_category":"Kappers",
    "sg:phone":"+31 71 408 0166",
    "sg:postcode":"2221 AB",
    "sg:province":"South Holland",
    "wof:name":"Karin",
    "wof:placetype":"venue"
},
  "geometry": {"coordinates":[4.4205698967,52.1875991821],"type":"Point"}
}