{
  "type": "Feature",
  "properties": {
    "addr:full":"Kampersweg 10 Ospel Limburg 6035 PM",
    "addr:housenumber":"10",
    "addr:postcode":"6035 pm",
    "addr:street":"Kampersweg",
    "iso:country":"NL",
    "sg:address":"Kampersweg 10",
    "sg:city":"Ospel",
    "sg:orig_category":"Pluimveehouderijen",
    "sg:phone":"+31 495 663 334",
    "sg:postcode":"6035 PM",
    "sg:province":"Limburg",
    "wof:name":"J.H.A. Beerens",
    "wof:placetype":"venue"
},
  "geometry": {"coordinates":[-86.165451,34.620892],"type":"Point"}
}