{
  "type": "Feature",
  "properties": {
    "addr:full":"Coolsngl 93 Rotterdam South Holland 3012 AE",
    "addr:housenumber":"93",
    "addr:postcode":"3012 ae",
    "addr:street":"Coolsngl",
    "iso:country":"NL",
    "sg:address":"Coolsngl 93",
    "sg:city":"Rotterdam",
    "sg:orig_category":"Banken",
    "sg:phone":"+31 10 401 9001",
    "sg:postcode":"3012 AE",
    "sg:province":"South Holland",
    "sg:website":"http://www.meespierson.com",
    "wof:name":"Meespierson",
    "wof:placetype":"venue"
},
  "geometry": {"coordinates":[4.478455,51.922836],"type":"Point"}
}