{
  "type": "Feature",
  "properties": {
    "addr:full":"Piekstr 63-65 Rotterdam Zuid-Holland 3071 EL",
    "addr:housenumber":"63-65",
    "addr:postcode":"rotterdam;3071 el",
    "iso:country":"NL",
    "sg:address":"Piekstr 63-65",
    "sg:city":"Rotterdam",
    "sg:orig_category":"Meel - Fabrieken En Groothandel",
    "sg:phone":"+31 10 486 6332",
    "sg:postcode":"3071 EL",
    "sg:province":"Zuid-Holland",
    "sg:website":"http://www.trouw-buckwheat.nl",
    "wof:name":"Trouw Bv, J",
    "wof:placetype":"venue"
},
  "geometry": {"coordinates":[4.512552,51.907467],"type":"Point"}
}