{
  "type": "Feature",
  "properties": {
    "addr:full":"O Industriewg 22 Franeker Friesland 8801 JW",
    "addr:housenumber":"22",
    "addr:postcode":"8801 jw",
    "iso:country":"NL",
    "sg:address":"O Industriewg 22",
    "sg:city":"Franeker",
    "sg:orig_category":"Houtindustrie",
    "sg:phone":"+31 517 398 186",
    "sg:postcode":"8801 JW",
    "sg:province":"Friesland",
    "sg:website":"http://www.woods-franeker.nl",
    "wof:name":"Woods Houtbouw",
    "wof:placetype":"venue"
},
  "geometry": {"coordinates":[5.564585,53.181568],"type":"Point"}
}