{
  "type": "Feature",
  "properties": {
    "addr:full":"Smaragdln 5-15 Hoofddorp Noord-Holland 2132 VX",
    "addr:housenumber":"5-15",
    "addr:postcode":"2132 vx",
    "iso:country":"NL",
    "sg:address":"Smaragdln 5-15",
    "sg:city":"Hoofddorp",
    "sg:orig_category":"Autoschade- Herstelbedrijven",
    "sg:phone":"+31 23 568 3200",
    "sg:postcode":"2132 VX",
    "sg:province":"Noord-Holland",
    "sg:website":"http://www.vankalmthout.nl",
    "wof:name":"Kalmthout & Van Niel Bv, Van",
    "wof:placetype":"venue"
},
  "geometry": {"coordinates":[4.687791,52.291389],"type":"Point"}
}