{
  "type": "Feature",
  "properties": {
    "addr:full":"Ten Veldestr 96 De Meern Utrecht 3454 EN",
    "addr:housenumber":"96",
    "addr:postcode":"3454 en",
    "addr:street":"Ten",
    "iso:country":"NL",
    "sg:address":"Ten Veldestr 96",
    "sg:city":"De Meern",
    "sg:orig_category":"Scholen Voor Basisonderwijs",
    "sg:phone":"+31 30 666 2680",
    "sg:postcode":"3454 EN",
    "sg:province":"Utrecht",
    "wof:name":"Drie Koningen Rk",
    "wof:placetype":"venue"
},
  "geometry": {"coordinates":[5.032401,52.077694],"type":"Point"}
}