{
  "type": "Feature",
  "properties": {
    "iso:country":"NL",
    "sg:address":"Sint Willibrordstraat 3",
    "sg:city":"Millingen A/D Rijn",
    "sg:classifiers":[
        {
            "category":"Food & Beverages",
            "subcategory":"Fruits & Vegetables",
            "type":"Retail Goods"
        }
    ],
    "sg:phone":"+31 481 431 202",
    "sg:postcode":"6566 DD",
    "sg:province":"Gelderland",
    "sg:tags":[
        "groenten"
    ],
    "wof:name":"Groente- En Delicatessenzaak Van Der Sta",
    "wof:placetype":"venue"
},
  "geometry": {"coordinates":[6.045505,51.864132],"type":"Point"}
}