{
  "type": "Feature",
  "properties": {
    "iso:country":"NL",
    "sg:address":"Gemeentewg 372",
    "sg:city":"Staphorst",
    "sg:orig_category":"Dierenvoeder - Fabrieken",
    "sg:phone":"+31 522 441 262",
    "sg:postcode":"7951 PH",
    "sg:province":"NL.08",
    "wof:name":"Agtersmid, Fa",
    "wof:placetype":"venue"
},
  "geometry": {"coordinates":[6.253437,52.662987],"type":"Point"}
}