{
  "type": "Feature",
  "properties": {
    "addr:full":"Kerkhoekstraat 13 Yerseke Zeeland 4401 GB",
    "addr:housenumber":"13",
    "addr:postcode":"4401 gb",
    "addr:street":"Kerkhoekstraat",
    "iso:country":"NL",
    "sg:address":"Kerkhoekstraat 13",
    "sg:city":"Yerseke",
    "sg:orig_category":"Kappers",
    "sg:phone":"+31 113 572 254",
    "sg:postcode":"4401 GB",
    "sg:province":"Zeeland",
    "wof:name":"Kapsalon Therese",
    "wof:placetype":"venue"
},
  "geometry": {"coordinates":[4.0487971306,51.4908218384],"type":"Point"}
}