{
  "type": "Feature",
  "properties": {
    "addr:full":"Dorpstr 27 Westerhoven Noord-Brabant 5563 BC",
    "addr:housenumber":"27",
    "addr:postcode":"5563 bc",
    "addr:street":"Dorpstr",
    "iso:country":"NL",
    "sg:address":"Dorpstr 27",
    "sg:city":"Westerhoven",
    "sg:orig_category":"Schoonheidsinstituten",
    "sg:phone":"+31 40 201 9421",
    "sg:postcode":"5563 BC",
    "sg:province":"Noord-Brabant",
    "sg:website":"http://www.wellness-centre-intermezzo.nl",
    "wof:name":"Wellness Centre Intermezzo",
    "wof:placetype":"venue"
},
  "geometry": {"coordinates":[5.394531,51.330345],"type":"Point"}
}