{
  "type": "Feature",
  "properties": {
    "iso:country":"NL",
    "sg:address":"Pascalstr 1A",
    "sg:city":"Hoogeveen",
    "sg:orig_category":"Lederwaren - Fabrieken En Groothandel",
    "sg:phone":"+31 528 233 787",
    "sg:postcode":"7903 BJ",
    "sg:province":"Drenthe",
    "sg:website":"http://home.worldonline.nl/~lederwar",
    "wof:name":"Dani\u00eblle",
    "wof:placetype":"venue"
},
  "geometry": {"coordinates":[6.511445,52.728546],"type":"Point"}
}