{
  "type": "Feature",
  "properties": {
    "iso:country":"NL",
    "sg:address":"M Lutherwg 181",
    "sg:city":"Amstelveen",
    "sg:orig_category":"Medische Installaties En Instrumenten",
    "sg:phone":"+31 20 345 3337",
    "sg:postcode":"1185 AL",
    "sg:province":"Noord-Holland",
    "wof:name":"Medicles",
    "wof:placetype":"venue"
},
  "geometry": {"coordinates":[4.862468,52.29224],"type":"Point"}
}