{
  "type": "Feature",
  "properties": {
    "addr:full":"Wellseindsedk 34 Well Gld Gelderland 5325 KD",
    "addr:housenumber":"34",
    "addr:postcode":"5325 kd",
    "addr:street":"Wellseindsedk;Gld Gelderland",
    "iso:country":"NL",
    "sg:address":"Wellseindsedk 34",
    "sg:city":"Well Gld",
    "sg:classifiers":[
        {
            "category":"Sports & Exercise",
            "subcategory":"Stables",
            "type":"Entertainment"
        }
    ],
    "sg:phone":"+31 418 551 552",
    "sg:postcode":"5325 KD",
    "sg:province":"Gelderland",
    "sg:tags":[
        "maneges"
    ],
    "sg:website":"http://www.easyhorse.nl",
    "wof:name":"Easy Horse Ranch",
    "wof:placetype":"venue"
},
  "geometry": {"coordinates":[5.175284,51.762772],"type":"Point"}
}