{
  "type": "Feature",
  "properties": {
    "addr:full":"J De Walestr 1 Leeuwarden Friesland 8921 XB",
    "addr:housenumber":"1",
    "addr:postcode":"8921 xb",
    "addr:street":"J De Walestr",
    "iso:country":"NL",
    "sg:address":"J De Walestr 1",
    "sg:city":"Leeuwarden",
    "sg:orig_category":"Scholen Voor Basisonderwijs",
    "sg:phone":"+31 58 266 5909",
    "sg:postcode":"8921 XB",
    "sg:province":"Friesland",
    "wof:name":"Sprong, Rk Bassisch De",
    "wof:placetype":"venue"
},
  "geometry": {"coordinates":[5.814997,53.210857],"type":"Point"}
}