{
  "type": "Feature",
  "properties": {
    "addr:full":"Burg Jansenln 49 Zwyndrecht Zuid-Holland 3331 HD",
    "addr:housenumber":"49",
    "addr:postcode":"3331 hd",
    "addr:street":"Burg",
    "iso:country":"NL",
    "sg:address":"Burg Jansenln 49",
    "sg:city":"Zwyndrecht",
    "sg:classifiers":[
        {
            "category":"Food & Beverages",
            "subcategory":"Bakery",
            "type":"Retail Goods"
        }
    ],
    "sg:phone":"+31 78 625 8751",
    "sg:postcode":"3331 HD",
    "sg:province":"Zuid-Holland",
    "sg:tags":[
        "pizza"
    ],
    "sg:website":"http://www.dominos.nl",
    "wof:name":"Domino",
    "wof:placetype":"venue"
},
  "geometry": {"coordinates":[4.64073,51.820702],"type":"Point"}
}