{
  "type": "Feature",
  "properties": {
    "iso:country":"NL",
    "sg:address":"Hoeven 14",
    "sg:city":"Nederweert Eind",
    "sg:orig_category":"Verhuur Catering-, Feest- En Evenementbenodigdheden",
    "sg:phone":"+31 495 632 617",
    "sg:postcode":"6034 RB",
    "sg:province":"Limburg",
    "wof:name":"Sander Koppen Party Tenten Verh. P.H. Koppen",
    "wof:placetype":"venue"
},
  "geometry": {"coordinates":[5.801623,51.290779],"type":"Point"}
}