{
  "type": "Feature",
  "properties": {
    "addr:full":"Vlettevaart 41 Rucphen Noord-Brabant 4715 EZ",
    "addr:housenumber":"41",
    "addr:postcode":"4715 ez",
    "addr:street":"Vlettevaart",
    "iso:country":"NL",
    "sg:address":"Vlettevaart 41",
    "sg:city":"Rucphen",
    "sg:orig_category":"Administratie- En Boekhoudkantoren",
    "sg:phone":"+31 165 344 861",
    "sg:postcode":"4715 EZ",
    "sg:province":"Noord-Brabant",
    "wof:name":"Administratief Service Kantoor",
    "wof:placetype":"venue"
},
  "geometry": {"coordinates":[4.558708,51.531223],"type":"Point"}
}