{
  "type": "Feature",
  "properties": {
    "addr:full":"Nassauln 17 S Gravenhage Zuid-Holland 2514 JT",
    "addr:housenumber":"17;gravenhage",
    "addr:postcode":"2514 jt",
    "addr:street":"Nassauln;S",
    "iso:country":"NL",
    "sg:address":"Nassauln 17",
    "sg:city":"S Gravenhage",
    "sg:orig_category":"Adviesbureaus",
    "sg:phone":"+31 70 302 9000",
    "sg:postcode":"2514 JT",
    "sg:province":"Zuid-Holland",
    "wof:name":"Pace",
    "wof:placetype":"venue"
},
  "geometry": {"coordinates":[4.30935,52.084148],"type":"Point"}
}