{
  "type": "Feature",
  "properties": {
    "iso:country":"NL",
    "sg:address":"Weebosserwg 12",
    "sg:city":"Bergeyk",
    "sg:orig_category":"Nagelstudio'S",
    "sg:phone":"+31 497 573 051",
    "sg:postcode":"5571 LM",
    "sg:province":"Noord-Brabant",
    "wof:name":"Liesbeth",
    "wof:placetype":"venue"
},
  "geometry": {"coordinates":[5.340195,51.312145],"type":"Point"}
}