{
  "type": "Feature",
  "properties": {
    "addr:full":"Voorsterwg 85 Loenen Gld Gelderland 7371 EK",
    "addr:housenumber":"85",
    "addr:postcode":"7371 ek",
    "addr:street":"Voorsterwg;Gld Gelderland",
    "iso:country":"NL",
    "sg:address":"Voorsterwg 85",
    "sg:city":"Loenen Gld",
    "sg:orig_category":"Grafisch Ontwerpers",
    "sg:phone":"+31 55 576 0765",
    "sg:postcode":"7371 EK",
    "sg:province":"Gelderland",
    "wof:name":"Mooijekind Ontwerpers Bv",
    "wof:placetype":"venue"
},
  "geometry": {"coordinates":[6.047707,52.135876],"type":"Point"}
}