{
  "type": "Feature",
  "properties": {
    "iso:country":"NL",
    "sg:address":"Stationsstr 29",
    "sg:city":"Epe",
    "sg:orig_category":"Begrafenisverzorging",
    "sg:phone":"+31 578 612 403",
    "sg:postcode":"8161 CP",
    "sg:province":"Gelderland",
    "wof:name":"Nuva",
    "wof:placetype":"venue"
},
  "geometry": {"coordinates":[5.989175,52.347805],"type":"Point"}
}