{
  "type": "Feature",
  "properties": {
    "iso:country":"NL",
    "sg:address":"Hoogstraat 6",
    "sg:city":"Veldhoven",
    "sg:orig_category":"Verzekeringen",
    "sg:phone":"+31 40 254 6502",
    "sg:postcode":"5502 AW",
    "sg:province":"Noord-Brabant",
    "wof:name":"J J Van Beers",
    "wof:placetype":"venue"
},
  "geometry": {"coordinates":[5.412625,51.421211],"type":"Point"}
}