{
  "type": "Feature",
  "properties": {
    "addr:full":"M Stokestr 34 Zeist Utrecht 3702 BM",
    "addr:housenumber":"34",
    "addr:postcode":"3702 bm",
    "iso:country":"NL",
    "sg:address":"M Stokestr 34",
    "sg:city":"Zeist",
    "sg:orig_category":"Timmerwerken",
    "sg:phone":"+31 6 21263077",
    "sg:postcode":"3702 BM",
    "sg:province":"Utrecht",
    "wof:name":"Spies",
    "wof:placetype":"venue"
},
  "geometry": {"coordinates":[5.234652,52.090683],"type":"Point"}
}