{
  "type": "Feature",
  "properties": {
    "addr:full":"Engelbertswg 4 Hengelo Ov Overijssel 7554 SN",
    "addr:housenumber":"4",
    "addr:postcode":"7554 sn",
    "addr:street":"Engelbertswg;Ov",
    "iso:country":"NL",
    "sg:address":"Engelbertswg 4",
    "sg:city":"Hengelo Ov",
    "sg:orig_category":"Administratie- En Boekhoudkantoren",
    "sg:phone":"+31 74 367 6418",
    "sg:postcode":"7554 SN",
    "sg:province":"Overijssel",
    "wof:name":"Ekl",
    "wof:placetype":"venue"
},
  "geometry": {"coordinates":[6.750179,52.214352],"type":"Point"}
}