{
  "type": "Feature",
  "properties": {
    "iso:country":"NL",
    "sg:address":"Thorbeckelaan 72",
    "sg:city":"Barneveld",
    "sg:orig_category":"Metaalbekleding And -Behandeling",
    "sg:phone":"+31 342 415 169",
    "sg:postcode":"3771 EK",
    "sg:province":"Gelderland",
    "wof:name":"Straalbedrijf Noorlander Barneveld Bv",
    "wof:placetype":"venue"
},
  "geometry": {"coordinates":[5.575566,52.146145],"type":"Point"}
}