{
  "type": "Feature",
  "properties": {
    "iso:country":"NL",
    "sg:address":"Hofsngl 227",
    "sg:city":"Arnhem",
    "sg:orig_category":"Onderhoudswerken",
    "sg:phone":"+31 26 321 1398",
    "sg:postcode":"6834 GG",
    "sg:province":"Gelderland",
    "wof:name":"Hueting",
    "wof:placetype":"venue"
},
  "geometry": {"coordinates":[5.92518,51.953201],"type":"Point"}
}