{
  "type": "Feature",
  "properties": {
    "addr:full":"Flevowg 18 Leiden South Holland 2318 BZ",
    "addr:housenumber":"18",
    "addr:postcode":"2318 bz",
    "addr:street":"Flevowg",
    "iso:country":"NL",
    "sg:address":"Flevowg 18",
    "sg:city":"Leiden",
    "sg:orig_category":"Ventilatoren",
    "sg:phone":"+31 71 521 8604",
    "sg:postcode":"2318 BZ",
    "sg:province":"South Holland",
    "wof:name":"Jn",
    "wof:placetype":"venue"
},
  "geometry": {"coordinates":[4.49633,52.174507],"type":"Point"}
}