{
  "type": "Feature",
  "properties": {
    "iso:country":"NL",
    "sg:address":"Geuzenwg 158",
    "sg:city":"Hilversum",
    "sg:orig_category":"Onderhoudswerken",
    "sg:phone":"+31 6 21598415",
    "sg:postcode":"1221 BX",
    "sg:province":"North Holland",
    "wof:name":"Rob",
    "wof:placetype":"venue"
},
  "geometry": {"coordinates":[5.185927,52.230915],"type":"Point"}
}