{
  "type": "Feature",
  "properties": {
    "iso:country":"NL",
    "sg:address":"Yzerenkuilenwg 25",
    "sg:city":"Meerssen",
    "sg:orig_category":"Waterleidingbedrijven",
    "sg:phone":"+31 43 365 6104",
    "sg:postcode":"6231 AA",
    "sg:province":"Limburg",
    "wof:name":"Wml",
    "wof:placetype":"venue"
},
  "geometry": {"coordinates":[5.7425851822,50.8720855713],"type":"Point"}
}