{
  "type": "Feature",
  "properties": {
    "addr:full":"Troelstrahoeve 62 Waddinxveen Zuid-Holland 2743 JE",
    "addr:housenumber":"62",
    "addr:postcode":"2743 je",
    "addr:street":"Troelstrahoeve",
    "iso:country":"NL",
    "sg:address":"Troelstrahoeve 62",
    "sg:city":"Waddinxveen",
    "sg:orig_category":"Zuivelproducten",
    "sg:phone":"+31 182 619 843",
    "sg:postcode":"2743 JE",
    "sg:province":"Zuid-Holland",
    "wof:name":"Notenhandel D. Monster",
    "wof:placetype":"venue"
},
  "geometry": {"coordinates":[4.635738,52.033604],"type":"Point"}
}