{
  "type": "Feature",
  "properties": {
    "iso:country":"NL",
    "sg:address":"Muntstr 2",
    "sg:city":"Medemblik",
    "sg:orig_category":"Sportverenigingen En Ontspannings- Verenigingen",
    "sg:phone":"+31 229 582 677",
    "sg:postcode":"1671 CW",
    "sg:province":"Noord-Holland",
    "sg:website":"http://members.xoom.com/doksoeri",
    "wof:name":"Dok-Soe-Ri Taekwondo Centr",
    "wof:placetype":"venue"
},
  "geometry": {"coordinates":[5.102875,52.772652],"type":"Point"}
}