{
  "type": "Feature",
  "properties": {
    "addr:full":"Bloemenschans 157 Voorhout South Holland 2215 MV",
    "addr:housenumber":"157",
    "addr:postcode":"2215 mv",
    "addr:street":"Bloemenschans",
    "iso:country":"NL",
    "sg:address":"Bloemenschans 157",
    "sg:city":"Voorhout",
    "sg:orig_category":"Peuterspeelzalen",
    "sg:phone":"+31 252 218 276",
    "sg:postcode":"2215 MV",
    "sg:province":"South Holland",
    "wof:name":"Dribbel",
    "wof:placetype":"venue"
},
  "geometry": {"coordinates":[4.489619,52.219364],"type":"Point"}
}