{
  "type": "Feature",
  "properties": {
    "addr:full":"Cannenburg 164 Dordrecht South Holland 3328 AX",
    "addr:housenumber":"164",
    "addr:postcode":"3328 ax",
    "addr:street":"Cannenburg",
    "iso:country":"NL",
    "sg:address":"Cannenburg 164",
    "sg:city":"Dordrecht",
    "sg:orig_category":"Kantoorartikelen",
    "sg:phone":"+31 78 651 2353",
    "sg:postcode":"3328 AX",
    "sg:province":"South Holland",
    "wof:name":"Msn",
    "wof:placetype":"venue"
},
  "geometry": {"coordinates":[4.6854171753,51.7782325745],"type":"Point"}
}