{
  "type": "Feature",
  "properties": {
    "addr:full":"Laakwg 30 Nykerkerveen Gelderland 3864 LC",
    "addr:housenumber":"30",
    "addr:postcode":"3864 lc",
    "addr:street":"Laakwg;Gelderland",
    "iso:country":"NL",
    "sg:address":"Laakwg 30",
    "sg:city":"Nykerkerveen",
    "sg:orig_category":"Wormenkwekerijen",
    "sg:phone":"+31 33 257 2407",
    "sg:postcode":"3864 LC",
    "sg:province":"Gelderland",
    "wof:name":"Hendriksen",
    "wof:placetype":"venue"
},
  "geometry": {"coordinates":[5.4578809738,52.1922035217],"type":"Point"}
}