{
  "type": "Feature",
  "properties": {
    "addr:full":"Onderlangs 4-8 Barendrecht Zuid-Holland 2991 EM",
    "addr:housenumber":"4-8",
    "addr:postcode":"2991 em",
    "addr:street":"Onderlangs",
    "iso:country":"NL",
    "sg:address":"Onderlangs 4-8",
    "sg:city":"Barendrecht",
    "sg:orig_category":"Baby- And Kinderkleding",
    "sg:phone":"+31 180 616 365",
    "sg:postcode":"2991 EM",
    "sg:province":"Zuid-Holland",
    "wof:name":"Koonings Babykleding & Kinderkleding",
    "wof:placetype":"venue"
},
  "geometry": {"coordinates":[4.538182,51.855701],"type":"Point"}
}