{
  "type": "Feature",
  "properties": {
    "addr:full":"Essenburg 20 Alphen Aan Den Ryn Zuid-Holland 2402 KP",
    "addr:housenumber":"20",
    "addr:postcode":"2402 kp",
    "addr:street":"Essenburg;Aan Den Ryn",
    "iso:country":"NL",
    "sg:address":"Essenburg 20",
    "sg:city":"Alphen Aan Den Ryn",
    "sg:orig_category":"Beeldende Kunstenaars",
    "sg:phone":"+31 172 419 793",
    "sg:postcode":"2402 KP",
    "sg:province":"Zuid-Holland",
    "sg:website":"http://www.nimi.nl",
    "wof:name":"Luister Art & Smile Company",
    "wof:placetype":"venue"
},
  "geometry": {"coordinates":[4.673751,52.148537],"type":"Point"}
}