{
  "type": "Feature",
  "properties": {
    "addr:full":"Werkendelsln 7 Heiloo North Holland 1851 VA",
    "addr:housenumber":"7",
    "addr:postcode":"1851",
    "addr:street":"Werkendelsln",
    "iso:country":"NL",
    "sg:address":"Werkendelsln 7",
    "sg:city":"Heiloo",
    "sg:orig_category":"Verenigingen En Stichtingen",
    "sg:phone":"+31 72 532 1664",
    "sg:postcode":"1851 VA",
    "sg:province":"North Holland",
    "wof:name":"Lichtbaken, Sticht Het",
    "wof:placetype":"venue"
},
  "geometry": {"coordinates":[4.713702,52.604191],"type":"Point"}
}