{
  "type": "Feature",
  "properties": {
    "addr:full":"Oosterwg 1 Groningen Groningen 9724 CA",
    "addr:housenumber":"1",
    "addr:postcode":"9724 ca",
    "addr:street":"Oosterwg",
    "iso:country":"NL",
    "sg:address":"Oosterwg 1",
    "sg:city":"Groningen",
    "sg:orig_category":"Webdesign Bureaus",
    "sg:phone":"+31 50 311 7252",
    "sg:postcode":"9724 CA",
    "sg:province":"Groningen",
    "sg:website":"http://www.okergroep.nl",
    "wof:name":"Okergroep, De",
    "wof:placetype":"venue"
},
  "geometry": {"coordinates":[6.5744462013,53.2127304077],"type":"Point"}
}