{
  "type": "Feature",
  "properties": {
    "addr:full":"Branderwg 1D Zwolle Overijssel 8042 PD",
    "addr:housenumber":"1d",
    "addr:postcode":"8042 pd",
    "iso:country":"NL",
    "sg:address":"Branderwg 1D",
    "sg:city":"Zwolle",
    "sg:orig_category":"Elektronica - Ontwikkeling En Groothandel",
    "sg:phone":"+31 38 422 5173",
    "sg:postcode":"8042 PD",
    "sg:province":"Overijssel",
    "wof:name":"Ijssel Components Bv",
    "wof:placetype":"venue"
},
  "geometry": {"coordinates":[6.058434,52.518063],"type":"Point"}
}