{
  "type": "Feature",
  "properties": {
    "addr:full":"Floresstraat 47 Haarlem North Holland 2022 BC",
    "addr:housenumber":"47",
    "addr:postcode":"2022 bc",
    "addr:street":"Floresstraat",
    "iso:country":"NL",
    "sg:address":"Floresstraat 47",
    "sg:city":"Haarlem",
    "sg:orig_category":"Fitnesscentra",
    "sg:phone":"+31 23 527 4080",
    "sg:postcode":"2022 BC",
    "sg:province":"North Holland",
    "wof:name":"Pauel Sport",
    "wof:placetype":"venue"
},
  "geometry": {"coordinates":[4.647236,52.39859],"type":"Point"}
}