{
  "type": "Feature",
  "properties": {
    "addr:full":"Mathenesserln 214 Rotterdam Zuid-Holland 3021 HM",
    "addr:housenumber":"214",
    "addr:postcode":"3021 hm",
    "iso:country":"NL",
    "sg:address":"Mathenesserln 214",
    "sg:city":"Rotterdam",
    "sg:orig_category":"Advocaten En Advocatenkantoren",
    "sg:phone":"+31 10 478 2000",
    "sg:postcode":"3021 HM",
    "sg:province":"Zuid-Holland",
    "wof:name":"Griend Mr W F, Van Der",
    "wof:placetype":"venue"
},
  "geometry": {"coordinates":[4.462736,51.914528],"type":"Point"}
}