{
  "type": "Feature",
  "properties": {
    "addr:full":"Kon Julianapln 30 S Gravenhage Zuid-Holland 2595 AA",
    "addr:housenumber":"30;gravenhage",
    "addr:postcode":"2595 aa",
    "addr:street":"Kon;S",
    "iso:country":"NL",
    "sg:address":"Kon Julianapln 30",
    "sg:city":"S Gravenhage",
    "sg:orig_category":"Verenigingen En Stichtingen",
    "sg:phone":"+31 70 324 3857",
    "sg:postcode":"2595 AA",
    "sg:province":"Zuid-Holland",
    "wof:name":"Binnenstad Den Haag",
    "wof:placetype":"venue"
},
  "geometry": {"coordinates":[4.33507,52.081421],"type":"Point"}
}