{
  "type": "Feature",
  "properties": {
    "iso:country":"NL",
    "sg:address":"Vosselmanstraat 201",
    "sg:city":"Apeldoorn",
    "sg:orig_category":"Politie",
    "sg:phone":"+31 900 8844",
    "sg:postcode":"7311 CL",
    "sg:province":"Gelderland",
    "wof:name":"Politie Apeldoorn",
    "wof:placetype":"venue"
},
  "geometry": {"coordinates":[5.954693,52.215374],"type":"Point"}
}