{
  "type": "Feature",
  "properties": {
    "iso:country":"NL",
    "sg:address":"Goeman Borgesiusstraat 2",
    "sg:city":"Amsterdam",
    "sg:orig_category":"Bibliotheken And Openbare Archieven",
    "sg:phone":"+31 20 613 0804",
    "sg:postcode":"1067 LN",
    "sg:province":"North Holland",
    "wof:name":"Openbare Bibliotheek En Leeszaal",
    "wof:placetype":"venue"
},
  "geometry": {"coordinates":[4.800164,52.377064],"type":"Point"}
}