{
  "type": "Feature",
  "properties": {
    "addr:full":"Kievitswg 10 Grypskerk Groningen 9843 HA",
    "addr:housenumber":"10",
    "addr:postcode":"9843 ha",
    "addr:street":"Kievitswg",
    "iso:country":"NL",
    "sg:address":"Kievitswg 10",
    "sg:city":"Grypskerk",
    "sg:orig_category":"Meubelen",
    "sg:phone":"+31 594 211 664",
    "sg:postcode":"9843 HA",
    "sg:province":"Groningen",
    "wof:name":"Young Living",
    "wof:placetype":"venue"
},
  "geometry": {"coordinates":[6.306361,53.265652],"type":"Point"}
}