{
  "type": "Feature",
  "properties": {
    "addr:full":"Bucht 9 Bergeyk North Brabant 5571 CT",
    "addr:housenumber":"9",
    "addr:postcode":"5571 ct",
    "addr:street":"Bucht",
    "iso:country":"NL",
    "sg:address":"Bucht 9",
    "sg:city":"Bergeyk",
    "sg:orig_category":"Kappers",
    "sg:phone":"+31 497 573 604",
    "sg:postcode":"5571 CT",
    "sg:province":"North Brabant",
    "wof:name":"Fien",
    "wof:placetype":"venue"
},
  "geometry": {"coordinates":[5.3646788597,51.3241653442],"type":"Point"}
}