{
  "type": "Feature",
  "properties": {
    "addr:full":"Oldenzijlsterweg 6 Oldenzijl Groningen 9986 XM",
    "addr:housenumber":"6",
    "addr:postcode":"9986 xm",
    "addr:street":"Oldenzijlsterweg",
    "iso:country":"NL",
    "sg:address":"Oldenzijlsterweg 6",
    "sg:city":"Oldenzijl",
    "sg:classifiers":[
        {
            "category":"Education",
            "subcategory":"Preschool",
            "type":"Public Place"
        }
    ],
    "sg:phone":"+31 595 464 313",
    "sg:postcode":"9986 XM",
    "sg:province":"Groningen",
    "sg:tags":[
        "kleuteronderwijs",
        "basis-"
    ],
    "wof:name":"Dalton Openbare Basisschool Schutsluis",
    "wof:placetype":"venue"
},
  "geometry": {"coordinates":[6.712782,53.393017],"type":"Point"}
}