{
  "type": "Feature",
  "properties": {
    "addr:full":"Gilzerijenstraat 32 Rotterdam Zuid-Holland 3045 PJ",
    "addr:housenumber":"32",
    "addr:postcode":"3045 pj",
    "addr:street":"Gilzerijenstraat",
    "iso:country":"NL",
    "sg:address":"Gilzerijenstraat 32",
    "sg:city":"Rotterdam",
    "sg:orig_category":"Metaalafval, Schrootrecycling And Sloperijen",
    "sg:phone":"+31 10 461 1422",
    "sg:postcode":"3045 PJ",
    "sg:province":"Zuid-Holland",
    "sg:website":"http://www.a-team.autosloperij.nl",
    "wof:name":"A-Team Autosloperij",
    "wof:placetype":"venue"
},
  "geometry": {"coordinates":[4.451378,51.953758],"type":"Point"}
}