{
  "type": "Feature",
  "properties": {
    "addr:full":"Royaards Van Den Hamkade 3 Utrecht Utrecht 3552 CJ",
    "addr:housenumber":"3",
    "addr:postcode":"3552 cj",
    "addr:street":"Royaards Van Den Hamkade",
    "iso:country":"NL",
    "sg:address":"Royaards Van Den Hamkade 3",
    "sg:city":"Utrecht",
    "sg:orig_category":"Vertalers",
    "sg:phone":"+31 30 243 9119",
    "sg:postcode":"3552 CJ",
    "sg:province":"Utrecht",
    "wof:name":"Best-Bet",
    "wof:placetype":"venue"
},
  "geometry": {"coordinates":[5.1021,52.102375],"type":"Point"}
}