{
  "type": "Feature",
  "properties": {
    "addr:full":"Oudaenstr 9 Haarlem Noord-Holland 2026 SB",
    "addr:housenumber":"9",
    "addr:postcode":"2026 sb",
    "addr:street":"Oudaenstr",
    "iso:country":"NL",
    "sg:address":"Oudaenstr 9",
    "sg:city":"Haarlem",
    "sg:orig_category":"Adviesbureaus Bedrijfsorganisatie",
    "sg:phone":"+31 6 21500159",
    "sg:postcode":"2026 SB",
    "sg:province":"Noord-Holland",
    "wof:name":"Breed, M",
    "wof:placetype":"venue"
},
  "geometry": {"coordinates":[4.651916,52.419556],"type":"Point"}
}