{
  "type": "Feature",
  "properties": {
    "addr:full":"W Fleertmanstr 12 Oldenzaal NL.08 7575 EC",
    "addr:housenumber":"12;nl.08",
    "addr:postcode":"7575 ec",
    "addr:street":"W",
    "iso:country":"NL",
    "sg:address":"W Fleertmanstr 12",
    "sg:city":"Oldenzaal",
    "sg:orig_category":"Veren - Fabrieken En Groothandel",
    "sg:phone":"+31 541 585 252",
    "sg:postcode":"7575 EC",
    "sg:province":"NL.08",
    "sg:website":"http://www.tvt.nl",
    "wof:name":"Technische Veren Twente Bv",
    "wof:placetype":"venue"
},
  "geometry": {"coordinates":[6.922376,52.295532],"type":"Point"}
}