{
  "type": "Feature",
  "properties": {
    "iso:country":"NL",
    "sg:address":"Havezatenlaan 20",
    "sg:city":"Hengelo Ov",
    "sg:orig_category":"Kinderopvang Behalve Thuis",
    "sg:phone":"+31 74 255 3100",
    "sg:postcode":"7557 VZ",
    "sg:province":"Overijssel",
    "wof:name":"Stichting Kindercentrum Esrein",
    "wof:placetype":"venue"
},
  "geometry": {"coordinates":[6.81813,52.272442],"type":"Point"}
}