{
  "type": "Feature",
  "properties": {
    "iso:country":"NL",
    "sg:address":"Mauritskd 81",
    "sg:city":"S Gravenhage",
    "sg:orig_category":"Kantoorbenodigdheden",
    "sg:phone":"+31 70 346 7524",
    "sg:postcode":"2514 HH",
    "sg:province":"South Holland",
    "wof:name":"Winter, Gebr",
    "wof:placetype":"venue"
},
  "geometry": {"coordinates":[4.3093500137,52.084148407],"type":"Point"}
}