{
  "type": "Feature",
  "properties": {
    "addr:full":"Hoekerwg 9 Zwolle NL.08 8042 PH",
    "addr:housenumber":"9",
    "addr:postcode":"8042",
    "addr:street":"Hoekerwg",
    "iso:country":"NL",
    "sg:address":"Hoekerwg 9",
    "sg:city":"Zwolle",
    "sg:orig_category":"Openbaar Vervoer",
    "sg:phone":"+31 38 425 4700",
    "sg:postcode":"8042 PH",
    "sg:province":"NL.08",
    "sg:website":"http://www.midnet-tours.nl",
    "wof:name":"Midnet",
    "wof:placetype":"venue"
},
  "geometry": {"coordinates":[6.0521450043,52.5134925842],"type":"Point"}
}