{
  "type": "Feature",
  "properties": {
    "iso:country":"NL",
    "sg:address":"Rooseveltstraat 38",
    "sg:city":"Schimmert",
    "sg:orig_category":"Fitnesscentra",
    "sg:phone":"+31 45 404 2224",
    "sg:postcode":"6333 EE",
    "sg:province":"Limburg",
    "wof:name":"Ki Jo Mi - Fitness",
    "wof:placetype":"venue"
},
  "geometry": {"coordinates":[5.820175,50.904896],"type":"Point"}
}