{
  "type": "Feature",
  "properties": {
    "addr:full":"Wethouder Venteweg 50 Gouda Zuid-Holland 2805 JP",
    "addr:housenumber":"50",
    "addr:postcode":"2805 jp",
    "addr:street":"Wethouder Venteweg",
    "iso:country":"NL",
    "sg:address":"Wethouder Venteweg 50",
    "sg:city":"Gouda",
    "sg:orig_category":"Loodgieterswerk, Verwarming And Sanitaire Installaties",
    "sg:phone":"+31 182 583 229",
    "sg:postcode":"2805 JP",
    "sg:province":"Zuid-Holland",
    "wof:name":"Installatiebedrijf Roes",
    "wof:placetype":"venue"
},
  "geometry": {"coordinates":[4.722268,52.019989],"type":"Point"}
}