{
  "type": "Feature",
  "properties": {
    "addr:full":"Horndk 18 Loosdrecht Noord-Holland 1231 NW",
    "addr:housenumber":"18",
    "addr:postcode":"1231 nw",
    "addr:street":"Horndk",
    "iso:country":"NL",
    "sg:address":"Horndk 18",
    "sg:city":"Loosdrecht",
    "sg:orig_category":"Watersportartikelen",
    "sg:phone":"+31 35 582 0838",
    "sg:postcode":"1231 NW",
    "sg:province":"Noord-Holland",
    "wof:name":"Boatnet",
    "wof:placetype":"venue"
},
  "geometry": {"coordinates":[5.0679998398,52.2120933533],"type":"Point"}
}