{
  "type": "Feature",
  "properties": {
    "iso:country":"NL",
    "sg:address":"Krommewg 2",
    "sg:city":"Lunteren",
    "sg:orig_category":"Accountants - Administratie- Consulenten En -Kantoren",
    "sg:phone":"+31 318 574 154",
    "sg:postcode":"6741 NK",
    "sg:province":"Gelderland",
    "wof:name":"Glind Accountancy, Van De",
    "wof:placetype":"venue"
},
  "geometry": {"coordinates":[5.575095,52.072304],"type":"Point"}
}