{
  "type": "Feature",
  "properties": {
    "addr:full":"Schuytstraat 101 Pernis Rt South Holland 3195 SM",
    "addr:housenumber":"101",
    "addr:postcode":"rt;3195 sm",
    "addr:street":"Schuytstraat",
    "iso:country":"NL",
    "sg:address":"Schuytstraat 101",
    "sg:city":"Pernis Rt",
    "sg:classifiers":[
        {
            "category":"Fast Food",
            "type":"Food & Drink"
        }
    ],
    "sg:phone":"+31 10 416 7598",
    "sg:postcode":"3195 SM",
    "sg:province":"South Holland",
    "sg:tags":[
        "afhaal",
        "restaurant"
    ],
    "wof:name":"Snackbar Pernis",
    "wof:placetype":"venue"
},
  "geometry": {"coordinates":[4.38855,51.888851],"type":"Point"}
}