{
  "type": "Feature",
  "properties": {
    "addr:full":"Galvanistraat 50 Ede Gld Gelderland 6716 AE",
    "addr:housenumber":"50",
    "addr:postcode":"6716 ae",
    "addr:street":"Galvanistraat;Gld Gelderland",
    "iso:country":"NL",
    "sg:address":"Galvanistraat 50",
    "sg:city":"Ede Gld",
    "sg:orig_category":"Airconditioning And Ventilatie",
    "sg:phone":"+31 318 633 346",
    "sg:postcode":"6716 AE",
    "sg:province":"Gelderland",
    "wof:name":"Camfil Bv",
    "wof:placetype":"venue"
},
  "geometry": {"coordinates":[5.623337,52.028309],"type":"Point"}
}