{
  "type": "Feature",
  "properties": {
    "addr:full":"Raaltepad 34 Almere NL. 1324 EV",
    "addr:housenumber":"34",
    "addr:street":"Raaltepad;Nl.",
    "iso:country":"NL",
    "sg:address":"Raaltepad 34",
    "sg:city":"Almere",
    "sg:orig_category":"Kappers",
    "sg:phone":"+31 36 534 0946",
    "sg:postcode":"1324 EV",
    "sg:province":"NL.",
    "wof:name":"Kapsalon Nico Van Der Stadt",
    "wof:placetype":"venue"
},
  "geometry": {"coordinates":[5.2113251686,52.3656578064],"type":"Point"}
}