{
  "type": "Feature",
  "properties": {
    "addr:full":"Postelstr 48 S Hertogenbosch Noord-Brabant 5211 EB",
    "addr:housenumber":"48",
    "addr:postcode":"5211 eb",
    "addr:street":"Postelstr;S",
    "iso:country":"NL",
    "sg:address":"Postelstr 48",
    "sg:city":"S Hertogenbosch",
    "sg:orig_category":"Displays, Showcards En Toonmaterialen",
    "sg:phone":"+31 73 612 0533",
    "sg:postcode":"5211 EB",
    "sg:province":"Noord-Brabant",
    "sg:website":"http://www.rietdijk.nl",
    "wof:name":"Rietdijk Creatieve Communicatie Bv",
    "wof:placetype":"venue"
},
  "geometry": {"coordinates":[5.300625,51.688389],"type":"Point"}
}