{
  "type": "Feature",
  "properties": {
    "iso:country":"NL",
    "sg:address":"Statenlaan 29",
    "sg:city":"'S Hertogenbosch",
    "sg:orig_category":"Werving And Selectie Van Tijdelijk Personeel And Uitzendkantoren",
    "sg:phone":"+31 73 646 1640",
    "sg:postcode":"5223 LA",
    "sg:province":"Noord-Brabant",
    "wof:name":"Bouwmeesters Personeelsdiensten",
    "wof:placetype":"venue"
},
  "geometry": {"coordinates":[5.2897849083,51.6897850037],"type":"Point"}
}