{
  "type": "Feature",
  "properties": {
    "addr:full":"Penningkruid 39 Purmerend North Holland 1441 XW",
    "addr:housenumber":"39",
    "addr:postcode":"1441 xw",
    "addr:street":"Penningkruid",
    "iso:country":"NL",
    "sg:address":"Penningkruid 39",
    "sg:city":"Purmerend",
    "sg:orig_category":"Onderhoudswerken",
    "sg:phone":"+31 299 472 862",
    "sg:postcode":"1441 XW",
    "sg:province":"North Holland",
    "wof:name":"Kwant",
    "wof:placetype":"venue"
},
  "geometry": {"coordinates":[4.953632,52.49192],"type":"Point"}
}