{
  "type": "Feature",
  "properties": {
    "addr:full":"Tuinderswg 12 De Lier Zuid-Holland 2678 LM",
    "addr:housenumber":"12",
    "addr:postcode":"2678 lm",
    "addr:street":"Tuinderswg",
    "iso:country":"NL",
    "sg:address":"Tuinderswg 12",
    "sg:city":"De Lier",
    "sg:orig_category":"Projectinrichting",
    "sg:phone":"+31 174 511 358",
    "sg:postcode":"2678 LM",
    "sg:province":"Zuid-Holland",
    "wof:name":"Cfi",
    "wof:placetype":"venue"
},
  "geometry": {"coordinates":[4.264144,51.983292],"type":"Point"}
}