{
  "type": "Feature",
  "properties": {
    "addr:full":"Schoolstraat 2 Moergestel Noord-Brabant 5066 EE",
    "addr:housenumber":"2",
    "addr:postcode":"5066 ee",
    "addr:street":"Schoolstraat",
    "iso:country":"NL",
    "sg:address":"Schoolstraat 2",
    "sg:city":"Moergestel",
    "sg:orig_category":"Kappers",
    "sg:phone":"+31 13 513 3162",
    "sg:postcode":"5066 EE",
    "sg:province":"Noord-Brabant",
    "wof:name":"T Kapperke",
    "wof:placetype":"venue"
},
  "geometry": {"coordinates":[5.183134079,51.5440216064],"type":"Point"}
}