{
  "type": "Feature",
  "properties": {
    "addr:full":"Laan Vd Mensenrechten 137 'S Gravenhage Zuid-Holland 2552 NR",
    "addr:housenumber":"137 '",
    "addr:postcode":"2552 nr",
    "addr:street":"Laan Vd Mensenrechten",
    "iso:country":"NL",
    "sg:address":"Laan Vd Mensenrechten 137",
    "sg:city":"'S Gravenhage",
    "sg:classifiers":[
        {
            "category":"Professional",
            "subcategory":"Accounting & Tax Preparation",
            "type":"Services"
        }
    ],
    "sg:phone":"+31 70 397 2997",
    "sg:postcode":"2552 NR",
    "sg:province":"Zuid-Holland",
    "sg:tags":[
        "accountant"
    ],
    "wof:name":"Accountant- En Administratie- Consulent L. Van Zon",
    "wof:placetype":"venue"
},
  "geometry": {"coordinates":[4.258173,52.058952],"type":"Point"}
}