{
  "type": "Feature",
  "properties": {
    "addr:full":"V V Goghstr 12 Hazerswoude Dorp Zuid-Holland 2391 VB",
    "addr:housenumber":"12",
    "addr:postcode":"2391 vb",
    "addr:street":"Goghstr",
    "iso:country":"NL",
    "sg:address":"V V Goghstr 12",
    "sg:city":"Hazerswoude Dorp",
    "sg:orig_category":"Onderhoudswerken",
    "sg:phone":"+31 172 586 030",
    "sg:postcode":"2391 VB",
    "sg:province":"Zuid-Holland",
    "sg:website":"http://www.reinald-demoed.nl",
    "wof:name":"Reinald D?moed",
    "wof:placetype":"venue"
},
  "geometry": {"coordinates":[4.59104,52.097099],"type":"Point"}
}