{
  "type": "Feature",
  "properties": {
    "addr:full":"Leeksterwg 23 Haulerwyk Provincie Friesland 8433 KV",
    "addr:housenumber":"23",
    "addr:postcode":"8433 kv",
    "addr:street":"Leeksterwg;Provincie Friesland",
    "iso:country":"NL",
    "sg:address":"Leeksterwg 23",
    "sg:city":"Haulerwyk",
    "sg:orig_category":"Verenigingsgebouwen",
    "sg:phone":"+31 516 421 677",
    "sg:postcode":"8433 KV",
    "sg:province":"Provincie Friesland",
    "wof:name":"Dorpshuis Haulerwijk",
    "wof:placetype":"venue"
},
  "geometry": {"coordinates":[6.331489,53.067219],"type":"Point"}
}