{
  "type": "Feature",
  "properties": {
    "addr:full":"Hof Van Spaland 70 Schiedam Zuid-Holland 3121 CC",
    "addr:housenumber":"70",
    "addr:postcode":"3121 cc",
    "addr:street":"Hof Van Spaland",
    "iso:country":"NL",
    "sg:address":"Hof Van Spaland 70",
    "sg:city":"Schiedam",
    "sg:classifiers":[
        {
            "category":"Shopping",
            "subcategory":"Clothing, Apparel, & Fashions",
            "type":"Retail Goods"
        }
    ],
    "sg:phone":"+31 10 471 8433",
    "sg:postcode":"3121 CC",
    "sg:province":"Zuid-Holland",
    "sg:tags":[
        "ondergoed",
        "lingerie"
    ],
    "wof:name":"Passepartout Middelbosch",
    "wof:placetype":"venue"
},
  "geometry": {"coordinates":[4.374907,51.934769],"type":"Point"}
}