{
  "type": "Feature",
  "properties": {
    "addr:full":"Willemsparkweg 74 Amsterdam North Holland 1071 HK",
    "addr:housenumber":"74",
    "addr:postcode":"1071 hk",
    "addr:street":"Willemsparkweg",
    "iso:country":"NL",
    "sg:address":"Willemsparkweg 74",
    "sg:city":"Amsterdam",
    "sg:classifiers":[
        {
            "category":"Communications",
            "subcategory":"Television Station",
            "type":"Services"
        }
    ],
    "sg:phone":"+31 20 673 9674",
    "sg:postcode":"1071 HK",
    "sg:province":"North Holland",
    "sg:tags":[
        "video",
        "audio",
        "verhuur"
    ],
    "wof:name":"Videotheek Filmplan",
    "wof:placetype":"venue"
},
  "geometry": {"coordinates":[4.874585,52.357304],"type":"Point"}
}