{
  "type": "Feature",
  "properties": {
    "addr:full":"Rijssensestraat 1 Wierden Overijssel 7642 CV",
    "addr:housenumber":"1",
    "addr:postcode":"7642 cv",
    "addr:street":"Rijssensestraat",
    "iso:country":"NL",
    "sg:address":"Rijssensestraat 1",
    "sg:city":"Wierden",
    "sg:orig_category":"Banken And Kredietinstellingen",
    "sg:phone":"+31 546 571 940",
    "sg:postcode":"7642 CV",
    "sg:province":"Overijssel",
    "wof:name":"Abn Amro",
    "wof:placetype":"venue"
},
  "geometry": {"coordinates":[6.590382,52.355583],"type":"Point"}
}