{
  "type": "Feature",
  "properties": {
    "addr:full":"Colijnstraat 30 Nunspeet Gelderland 8072 AW",
    "addr:housenumber":"30",
    "addr:postcode":"8072 aw",
    "addr:street":"Colijnstraat;Gelderland",
    "iso:country":"NL",
    "sg:address":"Colijnstraat 30",
    "sg:city":"Nunspeet",
    "sg:orig_category":"Film-, Tv- And Videoproductie",
    "sg:phone":"+31 341 250 607",
    "sg:postcode":"8072 AW",
    "sg:province":"Gelderland",
    "wof:name":"New Horizon",
    "wof:placetype":"venue"
},
  "geometry": {"coordinates":[5.80345,52.382729],"type":"Point"}
}