{
  "type": "Feature",
  "properties": {
    "addr:full":"Klarinetsingel 3 Zwijndrecht Zuid-Holland 3335 DE",
    "addr:housenumber":"3",
    "addr:postcode":"3335 de",
    "addr:street":"Klarinetsingel",
    "iso:country":"NL",
    "sg:address":"Klarinetsingel 3",
    "sg:city":"Zwijndrecht",
    "sg:orig_category":"Overheidsdiensten",
    "sg:phone":"+31 78 610 2547",
    "sg:postcode":"3335 DE",
    "sg:province":"Zuid-Holland",
    "wof:name":"T Klankbord",
    "wof:placetype":"venue"
},
  "geometry": {"coordinates":[4.6096458435,51.8206291199],"type":"Point"}
}