{
  "type": "Feature",
  "properties": {
    "iso:country":"NL",
    "sg:address":"Topshoofd 43",
    "sg:city":"Urk",
    "sg:orig_category":"Schilders",
    "sg:phone":"+31 6 20078271",
    "sg:postcode":"8321 CV",
    "sg:province":"Flevoland",
    "wof:name":"Cor Mazereeuw Schilderwerken",
    "wof:placetype":"venue"
},
  "geometry": {"coordinates":[5.609639,52.661339],"type":"Point"}
}