{
  "type": "Feature",
  "properties": {
    "addr:full":"Merwedekanaal 6 Gorinchem South Holland 4206 BC",
    "addr:housenumber":"6",
    "addr:postcode":"4206 bc",
    "addr:street":"Merwedekanaal",
    "iso:country":"NL",
    "sg:address":"Merwedekanaal 6",
    "sg:city":"Gorinchem",
    "sg:orig_category":"Kunstgebitten",
    "sg:phone":"+31 183 620 960",
    "sg:postcode":"4206 BC",
    "sg:province":"South Holland",
    "wof:name":"Karssies Tandprothetiek",
    "wof:placetype":"venue"
},
  "geometry": {"coordinates":[4.980291,51.847885],"type":"Point"}
}