{
  "type": "Feature",
  "properties": {
    "addr:full":"Rijksweg 60 Maastricht Limburg 6228 XZ",
    "addr:housenumber":"60",
    "addr:postcode":"6228 xz",
    "addr:street":"Rijksweg",
    "iso:country":"NL",
    "sg:address":"Rijksweg 60",
    "sg:city":"Maastricht",
    "sg:orig_category":"Bloemen And Planten",
    "sg:phone":"+31 43 361 6265",
    "sg:postcode":"6228 XZ",
    "sg:province":"Limburg",
    "wof:name":"Leliveld De Heeg Bloemen",
    "wof:placetype":"venue"
},
  "geometry": {"coordinates":[5.729081,50.82803],"type":"Point"}
}