{
  "type": "Feature",
  "properties": {
    "addr:full":"Dommelstr 70 Oss Noord-Brabant 5347 JL",
    "addr:housenumber":"70",
    "addr:postcode":"5347 jl",
    "addr:street":"Dommelstr",
    "iso:country":"NL",
    "sg:address":"Dommelstr 70",
    "sg:city":"Oss",
    "sg:orig_category":"Kantoor- En Bedrijfsmeubelen",
    "sg:phone":"+31 412 627 111",
    "sg:postcode":"5347 JL",
    "sg:province":"Noord-Brabant",
    "wof:name":"Bukan Office Bv",
    "wof:placetype":"venue"
},
  "geometry": {"coordinates":[-77.2352142334,38.3125991821],"type":"Point"}
}