{
  "type": "Feature",
  "properties": {
    "addr:full":"Entersewg 9 Goor NL.08 7471 SB",
    "addr:housenumber":"9;nl.08",
    "addr:postcode":"7471 sb",
    "addr:street":"Entersewg",
    "iso:country":"NL",
    "sg:address":"Entersewg 9",
    "sg:city":"Goor",
    "sg:orig_category":"Elektronica - Ontwikkeling En Groothandel",
    "sg:phone":"+31 547 263 311",
    "sg:postcode":"7471 SB",
    "sg:province":"NL.08",
    "sg:website":"http://www.login-bv.com",
    "wof:name":"Login Bv",
    "wof:placetype":"venue"
},
  "geometry": {"coordinates":[6.591546,52.243622],"type":"Point"}
}