{
  "type": "Feature",
  "properties": {
    "addr:full":"Hyacinthwg 5 S Gravenhage Zuid-Holland 2565 RE",
    "addr:housenumber":"5;gravenhage",
    "addr:postcode":"2565 re",
    "addr:street":"Hyacinthwg;S",
    "iso:country":"NL",
    "sg:address":"Hyacinthwg 5",
    "sg:city":"S Gravenhage",
    "sg:orig_category":"Kinderopvang",
    "sg:phone":"+31 70 368 7580",
    "sg:postcode":"2565 RE",
    "sg:province":"Zuid-Holland",
    "wof:name":"Hyacinthe",
    "wof:placetype":"venue"
},
  "geometry": {"coordinates":[4.26129,52.076382],"type":"Point"}
}