{
  "type": "Feature",
  "properties": {
    "addr:full":"Natriumweg 8 Amersfoort Utrecht 3812 PV",
    "addr:housenumber":"8",
    "addr:postcode":"3812 pv",
    "addr:street":"Natriumweg",
    "iso:country":"NL",
    "sg:address":"Natriumweg 8",
    "sg:city":"Amersfoort",
    "sg:orig_category":"Metaalbekleding And -Behandeling",
    "sg:phone":"+31 33 461 3241",
    "sg:postcode":"3812 PV",
    "sg:province":"Utrecht",
    "wof:name":"Huisman Metaalindustrie Bv",
    "wof:placetype":"venue"
},
  "geometry": {"coordinates":[5.363417,52.166393],"type":"Point"}
}