{
  "type": "Feature",
  "properties": {
    "iso:country":"NL",
    "sg:address":"V Haersolteln 2",
    "sg:city":"Hasselt",
    "sg:classifiers":[
        {
            "category":"Personal",
            "subcategory":"Nail Salon",
            "type":"Services"
        }
    ],
    "sg:phone":"+31 38 477 1581",
    "sg:postcode":"8061 EG",
    "sg:province":"NL.08",
    "sg:tags":[
        "pedicure"
    ],
    "wof:name":"Brinkman-Linthorst, J A A M",
    "wof:placetype":"venue"
},
  "geometry": {"coordinates":[6.088755,52.592861],"type":"Point"}
}