{
  "type": "Feature",
  "properties": {
    "addr:full":"Tussen De Graften 12 Beek Lb Limburg 6191 LB",
    "addr:housenumber":"12",
    "addr:postcode":"lb;6191 lb",
    "addr:street":"Tussen De Graften",
    "iso:country":"NL",
    "sg:address":"Tussen De Graften 12",
    "sg:city":"Beek Lb",
    "sg:orig_category":"Wegenbouw - Materialen",
    "sg:phone":"+31 46 428 0189",
    "sg:postcode":"6191 LB",
    "sg:province":"Limburg",
    "wof:name":"Jorissen Beek Bv, P T J M",
    "wof:placetype":"venue"
},
  "geometry": {"coordinates":[-93.1299362183,36.7056617737],"type":"Point"}
}