{
  "type": "Feature",
  "properties": {
    "addr:full":"Graanweg 13 Moerdijk Noord-Brabant 4782 PP",
    "addr:housenumber":"13",
    "addr:postcode":"4782 pp",
    "addr:street":"Graanweg",
    "iso:country":"NL",
    "sg:address":"Graanweg 13",
    "sg:city":"Moerdijk",
    "sg:classifiers":[
        {
            "category":"Retail",
            "subcategory":"Storage",
            "type":"Services"
        }
    ],
    "sg:phone":"+31 168 381 111",
    "sg:postcode":"4782 PP",
    "sg:province":"Noord-Brabant",
    "sg:tags":[
        "opslag",
        "bewaring"
    ],
    "wof:name":"Sinco & Sluyter Bv",
    "wof:placetype":"venue"
},
  "geometry": {"coordinates":[4.6038761139,51.6840705872],"type":"Point"}
}