{
  "type": "Feature",
  "properties": {
    "addr:full":"Geulstr 41 Bunde Limburg 6241 NA",
    "addr:housenumber":"41",
    "addr:postcode":"6241 na",
    "addr:street":"Geulstr",
    "iso:country":"NL",
    "sg:address":"Geulstr 41",
    "sg:city":"Bunde",
    "sg:orig_category":"Verenigingen En Stichtingen",
    "sg:phone":"+31 43 364 3136",
    "sg:postcode":"6241 NA",
    "sg:province":"Limburg",
    "wof:name":"Bundense Jeugd- En Jongerenver",
    "wof:placetype":"venue"
},
  "geometry": {"coordinates":[5.725116,50.897438],"type":"Point"}
}