{
  "type": "Feature",
  "properties": {
    "addr:full":"St Hubertuspln 24 Venlo Limburg 5921 BD",
    "addr:housenumber":"24",
    "addr:postcode":"5921 bd",
    "iso:country":"NL",
    "sg:address":"St Hubertuspln 24",
    "sg:city":"Venlo",
    "sg:orig_category":"Kaas",
    "sg:phone":"+31 77 387 1255",
    "sg:postcode":"5921 BD",
    "sg:province":"Limburg",
    "wof:name":"Kaashoek, De",
    "wof:placetype":"venue"
},
  "geometry": {"coordinates":[6.1419267654,51.3672370911],"type":"Point"}
}