{
  "type": "Feature",
  "properties": {
    "addr:full":"Rembrandtln 78 Huizen Noord-Holland 1272 GP",
    "addr:housenumber":"78",
    "addr:postcode":"1272 gp",
    "addr:street":"Rembrandtln",
    "iso:country":"NL",
    "sg:address":"Rembrandtln 78",
    "sg:city":"Huizen",
    "sg:orig_category":"Kaas",
    "sg:phone":"+31 35 525 2156",
    "sg:postcode":"1272 GP",
    "sg:province":"Noord-Holland",
    "wof:name":"Vos, J",
    "wof:placetype":"venue"
},
  "geometry": {"coordinates":[5.2334480286,52.2907524109],"type":"Point"}
}