{
  "type": "Feature",
  "properties": {
    "addr:full":"Ramsbrugwg 28 Wenum Wiesel Gelderland 7345 DW",
    "addr:housenumber":"28",
    "addr:postcode":"7345 dw",
    "addr:street":"Ramsbrugwg",
    "iso:country":"NL",
    "sg:address":"Ramsbrugwg 28",
    "sg:city":"Wenum Wiesel",
    "sg:orig_category":"Beeldende Kunstenaars",
    "sg:phone":"+31 55 312 1321",
    "sg:postcode":"7345 DW",
    "sg:province":"Gelderland",
    "wof:name":"Greet Grottendieck",
    "wof:placetype":"venue"
},
  "geometry": {"coordinates":[5.965031,52.264992],"type":"Point"}
}