{
  "type": "Feature",
  "properties": {
    "addr:full":"Willemsvaart 18 Zwolle Overijssel 8019 AB",
    "addr:housenumber":"18",
    "addr:postcode":"8019 ab",
    "addr:street":"Willemsvaart",
    "iso:country":"NL",
    "sg:address":"Willemsvaart 18",
    "sg:city":"Zwolle",
    "sg:orig_category":"Veilingen",
    "sg:phone":"+31 38 423 2429",
    "sg:postcode":"8019 AB",
    "sg:province":"Overijssel",
    "wof:name":"Venduehuis Zwolle",
    "wof:placetype":"venue"
},
  "geometry": {"coordinates":[6.078693,52.505951],"type":"Point"}
}