{
  "type": "Feature",
  "properties": {
    "iso:country":"NL",
    "sg:address":"Engelandln 25",
    "sg:city":"Zoetermeer",
    "sg:orig_category":"Onderhoudswerken",
    "sg:phone":"+31 79 342 6792",
    "sg:postcode":"2711 DN",
    "sg:province":"Zuid-Holland",
    "wof:name":"Sabrina",
    "wof:placetype":"venue"
},
  "geometry": {"coordinates":[4.490698,52.059757],"type":"Point"}
}