{
  "type": "Feature",
  "properties": {
    "addr:full":"Bordewijklaan 15 'S Gravenhage South Holland 2591 XR",
    "addr:housenumber":"15",
    "addr:postcode":"2591 xr",
    "addr:street":"Bordewijklaan;' S Gravenhage",
    "iso:country":"NL",
    "sg:address":"Bordewijklaan 15",
    "sg:city":"'S Gravenhage",
    "sg:orig_category":"Juridische Dienstverlening",
    "sg:phone":"+31 70 349 1111",
    "sg:postcode":"2591 XR",
    "sg:province":"South Holland",
    "wof:name":"Benelux Merkenbureau Voor Tekeningen En Modellen",
    "wof:placetype":"venue"
},
  "geometry": {"coordinates":[4.364857,52.089558],"type":"Point"}
}