{
  "type": "Feature",
  "properties": {
    "iso:country":"NL",
    "sg:address":"Grotestraat 64",
    "sg:city":"Goor",
    "sg:classifiers":[
        {
            "category":"Food & Beverages",
            "subcategory":"Fruits & Vegetables",
            "type":"Retail Goods"
        }
    ],
    "sg:phone":"+31 547 272 887",
    "sg:postcode":"7471 BR",
    "sg:province":"NL.08",
    "sg:tags":[
        "groenten"
    ],
    "wof:name":"Groentehal G.J. Wiemerink",
    "wof:placetype":"venue"
},
  "geometry": {"coordinates":[6.586886,52.233208],"type":"Point"}
}