{
  "type": "Feature",
  "properties": {
    "addr:full":"Grotestraat 64 Goor NL.08 7471 BR",
    "addr:housenumber":"64;nl.08",
    "addr:postcode":"7471 br",
    "addr:street":"Grotestraat",
    "iso:country":"NL",
    "sg:address":"Grotestraat 64",
    "sg:city":"Goor",
    "sg:classifiers":[
        {
            "category":"Food & Beverages",
            "subcategory":"Fruits & Vegetables",
            "type":"Retail Goods"
        }
    ],
    "sg:phone":"+31 547 272 887",
    "sg:postcode":"7471 BR",
    "sg:province":"NL.08",
    "sg:tags":[
        "groenten"
    ],
    "wof:name":"Groentehal G.J. Wiemerink",
    "wof:placetype":"venue"
},
  "geometry": {"coordinates":[6.586886,52.233208],"type":"Point"}
}