{
  "type": "Feature",
  "properties": {
    "iso:country":"NL",
    "sg:address":"Hamert 9",
    "sg:city":"Wellerlooi",
    "sg:orig_category":"Golfbanen",
    "sg:phone":"+31 77 473 2727",
    "sg:postcode":"5856 CL",
    "sg:province":"Limburg",
    "sg:website":"http://www.roobeek.nl/golfcentrum_roobeek",
    "wof:name":"Roobeek",
    "wof:placetype":"venue"
},
  "geometry": {"coordinates":[6.176441,51.50021],"type":"Point"}
}