{
  "type": "Feature",
  "properties": {
    "addr:full":"Kunderberg 10 Voerendaal Limburg 6367 AL",
    "addr:housenumber":"10",
    "addr:postcode":"6367 al",
    "addr:street":"Kunderberg",
    "iso:country":"NL",
    "sg:address":"Kunderberg 10",
    "sg:city":"Voerendaal",
    "sg:classifiers":[
        {
            "category":"Retail",
            "subcategory":"Auto Repair",
            "type":"Services"
        }
    ],
    "sg:phone":"+31 45 575 2865",
    "sg:postcode":"6367 AL",
    "sg:province":"Limburg",
    "sg:tags":[
        "garage"
    ],
    "wof:name":"Smeets Autobedrijf, Jo",
    "wof:placetype":"venue"
},
  "geometry": {"coordinates":[5.94592,50.873409],"type":"Point"}
}