{
  "type": "Feature",
  "properties": {
    "addr:full":"Velserb Dreef 9 Velserbroek Noord-Holland 1991 AN",
    "addr:housenumber":"9",
    "addr:postcode":"1991 an",
    "addr:street":"Dreef",
    "iso:country":"NL",
    "sg:address":"Velserb Dreef 9",
    "sg:city":"Velserbroek",
    "sg:orig_category":"Banken",
    "sg:phone":"+31 23 513 0440",
    "sg:postcode":"1991 AN",
    "sg:province":"Noord-Holland",
    "sg:website":"http://www.rabobank.nl",
    "wof:name":"Rabobank",
    "wof:placetype":"venue"
},
  "geometry": {"coordinates":[4.663725,52.432453],"type":"Point"}
}