{
  "type": "Feature",
  "properties": {
    "addr:full":"Hogeweg 96 Amersfoort Utrecht 3814 CG",
    "addr:housenumber":"96",
    "addr:postcode":"3814 cg",
    "addr:street":"Hogeweg",
    "iso:country":"NL",
    "sg:address":"Hogeweg 96",
    "sg:city":"Amersfoort",
    "sg:orig_category":"Verzekeringen",
    "sg:phone":"+31 33 479 9194",
    "sg:postcode":"3814 CG",
    "sg:province":"Utrecht",
    "wof:name":"Eggenkamp Assurantien",
    "wof:placetype":"venue"
},
  "geometry": {"coordinates":[5.386085,52.152325],"type":"Point"}
}