{
  "type": "Feature",
  "properties": {
    "iso:country":"NL",
    "sg:address":"Vogelpan 43",
    "sg:city":"Hilversum",
    "sg:orig_category":"Koeriersdiensten",
    "sg:phone":"+31 35 685 7339",
    "sg:postcode":"1223 KS",
    "sg:province":"Noord-Holland",
    "wof:name":"Koerierservice Eype",
    "wof:placetype":"venue"
},
  "geometry": {"coordinates":[5.202055,52.23],"type":"Point"}
}