{
  "type": "Feature",
  "properties": {
    "addr:full":"L Smeestr 16 Utrecht Utrecht 3511 PW",
    "addr:housenumber":"16",
    "addr:postcode":"3511 pw",
    "iso:country":"NL",
    "sg:address":"L Smeestr 16",
    "sg:city":"Utrecht",
    "sg:orig_category":"Grafisch Ontwerpers",
    "sg:phone":"+31 30 234 0181",
    "sg:postcode":"3511 PW",
    "sg:province":"Utrecht",
    "sg:website":"http://www.audioimago.nl",
    "wof:name":"Audio Imago",
    "wof:placetype":"venue"
},
  "geometry": {"coordinates":[5.121342,52.085964],"type":"Point"}
}