{
  "type": "Feature",
  "properties": {
    "addr:full":"Brede Haven T.O. 47 S Hertogenbosch Noord-Brabant 5211 TM",
    "addr:housenumber":"t.o. 47",
    "addr:postcode":"5211 tm",
    "addr:street":"Brede Haven;S Hertogenbosch",
    "iso:country":"NL",
    "sg:address":"Brede Haven T.O. 47",
    "sg:city":"S Hertogenbosch",
    "sg:orig_category":"Webdesign Bureaus",
    "sg:phone":"+31 73 613 3345",
    "sg:postcode":"5211 TM",
    "sg:province":"Noord-Brabant",
    "sg:website":"http://www.no-more-heroes.nl",
    "wof:name":"No-More-Heroes",
    "wof:placetype":"venue"
},
  "geometry": {"coordinates":[5.2996740341,51.6930198669],"type":"Point"}
}