{
  "type": "Feature",
  "properties": {
    "iso:country":"NL",
    "sg:address":"Stationswg 6",
    "sg:city":"Heenvliet",
    "sg:orig_category":"Bloemen En Planten - Decoratie",
    "sg:phone":"+31 181 662 118",
    "sg:postcode":"3218 AV",
    "sg:province":"Zuid-Holland",
    "wof:name":"Helianthus",
    "wof:placetype":"venue"
},
  "geometry": {"coordinates":[4.244278,51.862907],"type":"Point"}
}