{
  "type": "Feature",
  "properties": {
    "addr:full":"Nokweg 1 Leimuiden Zuid-Holland 2451 AL",
    "addr:housenumber":"1",
    "addr:postcode":"2451 al",
    "addr:street":"Nokweg",
    "iso:country":"NL",
    "sg:address":"Nokweg 1",
    "sg:city":"Leimuiden",
    "sg:orig_category":"Schilderwerk",
    "sg:phone":"+31 172 508 119",
    "sg:postcode":"2451 AL",
    "sg:province":"Zuid-Holland",
    "wof:name":"Firma D. Zemel & Zonen",
    "wof:placetype":"venue"
},
  "geometry": {"coordinates":[4.672474,52.224838],"type":"Point"}
}