{
  "type": "Feature",
  "properties": {
    "addr:full":"Markt 27 Zevenaar Gelderland 6901 AH",
    "addr:housenumber":"27",
    "addr:postcode":"6901 ah",
    "addr:street":"Markt",
    "iso:country":"NL",
    "sg:address":"Markt 27",
    "sg:city":"Zevenaar",
    "sg:orig_category":"Meubelreparatie And -Restauratie",
    "sg:phone":"+31 316 524 415",
    "sg:postcode":"6901 AH",
    "sg:province":"Gelderland",
    "wof:name":"Kusters-Knol Bv",
    "wof:placetype":"venue"
},
  "geometry": {"coordinates":[6.076246,51.92635],"type":"Point"}
}