{
  "type": "Feature",
  "properties": {
    "addr:full":"Bredestr 12 Oostburg Zeeland 4501 EC",
    "addr:housenumber":"12",
    "addr:postcode":"4501 ec",
    "addr:street":"Bredestr",
    "iso:country":"NL",
    "sg:address":"Bredestr 12",
    "sg:city":"Oostburg",
    "sg:orig_category":"Fietsen En Bromfietsen Verhuur",
    "sg:phone":"+31 117 452 338",
    "sg:postcode":"4501 EC",
    "sg:province":"Zeeland",
    "sg:website":"http://www.cornelisfietsen.nl",
    "wof:name":"Cornelis Tweewielers",
    "wof:placetype":"venue"
},
  "geometry": {"coordinates":[3.494866,51.328655],"type":"Point"}
}