{
  "type": "Feature",
  "properties": {
    "addr:full":"Ijssel 1 Leidschendam South Holland 2267 DZ",
    "addr:housenumber":"1",
    "addr:postcode":"2267 dz",
    "addr:street":"Ijssel",
    "iso:country":"NL",
    "sg:address":"Ijssel 1",
    "sg:city":"Leidschendam",
    "sg:orig_category":"Wasserettes And Stomerijen",
    "sg:phone":"+31 70 320 6114",
    "sg:postcode":"2267 DZ",
    "sg:province":"South Holland",
    "wof:name":"Pasgeld Bv",
    "wof:placetype":"venue"
},
  "geometry": {"coordinates":[4.4003200531,52.0788803101],"type":"Point"}
}