{
  "type": "Feature",
  "properties": {
    "addr:full":"Industriewg 40 Rotterdam Zuid-Holland 3044 CB",
    "addr:housenumber":"40",
    "addr:postcode":"3044 cb",
    "addr:street":"Industriewg",
    "iso:country":"NL",
    "sg:address":"Industriewg 40",
    "sg:city":"Rotterdam",
    "sg:orig_category":"Levensmiddelen - Fabrieken En Groothandel",
    "sg:phone":"+31 10 437 8812",
    "sg:postcode":"3044 CB",
    "sg:province":"Zuid-Holland",
    "wof:name":"Tur-Ned Int Trading Bv",
    "wof:placetype":"venue"
},
  "geometry": {"coordinates":[4.413924,51.934212],"type":"Point"}
}