{
  "type": "Feature",
  "properties": {
    "addr:full":"Baander 15 Emmen Drenthe 7811 HH",
    "addr:housenumber":"15",
    "addr:postcode":"7811 hh",
    "addr:street":"Baander",
    "iso:country":"NL",
    "sg:address":"Baander 15",
    "sg:city":"Emmen",
    "sg:orig_category":"Makelaars In Onroerend Goed",
    "sg:phone":"+31 591 612 120",
    "sg:postcode":"7811 HH",
    "sg:province":"Drenthe",
    "wof:name":"Makelaardij Kuper Bv",
    "wof:placetype":"venue"
},
  "geometry": {"coordinates":[6.896151,52.781498],"type":"Point"}
}