{
  "type": "Feature",
  "properties": {
    "addr:full":"Rustenburgerwg 103 Heerhugowaard Noord-Holland 1703 RV",
    "addr:housenumber":"103",
    "addr:postcode":"1703 rv",
    "iso:country":"NL",
    "sg:address":"Rustenburgerwg 103",
    "sg:city":"Heerhugowaard",
    "sg:orig_category":"Zonnebank- En Solariumcentra",
    "sg:phone":"+31 72 572 4206",
    "sg:postcode":"1703 RV",
    "sg:province":"Noord-Holland",
    "wof:name":"Della Vita",
    "wof:placetype":"venue"
},
  "geometry": {"coordinates":[4.836543,52.657261],"type":"Point"}
}