{
  "type": "Feature",
  "properties": {
    "addr:full":"Herenstr 42 Rhenen Utrecht 3911 JG",
    "addr:housenumber":"42",
    "addr:postcode":"3911 jg",
    "addr:street":"Herenstr",
    "iso:country":"NL",
    "sg:address":"Herenstr 42",
    "sg:city":"Rhenen",
    "sg:orig_category":"Woninginrichting",
    "sg:phone":"+31 317 621 493",
    "sg:postcode":"3911 JG",
    "sg:province":"Utrecht",
    "wof:name":"Berch Poort, Huyze",
    "wof:placetype":"venue"
},
  "geometry": {"coordinates":[5.5689997673,51.9570579529],"type":"Point"}
}