{
  "type": "Feature",
  "properties": {
    "iso:country":"NL",
    "sg:address":"Noorderkroon 99",
    "sg:city":"Veenendaal",
    "sg:orig_category":"Koeltechniek",
    "sg:phone":"+31 318 524 719",
    "sg:postcode":"3902 VC",
    "sg:province":"Utrecht",
    "wof:name":"Blom",
    "wof:placetype":"venue"
},
  "geometry": {"coordinates":[5.570596,52.026123],"type":"Point"}
}