{
  "type": "Feature",
  "properties": {
    "iso:country":"NL",
    "sg:address":"Lugtenbergwg 9",
    "sg:city":"Nunspeet",
    "sg:orig_category":"Makelaars En Adviseurs Onroerende Goederen",
    "sg:phone":"+31 341 264 040",
    "sg:postcode":"8071 XG",
    "sg:province":"Gelderland",
    "sg:website":"http://www.westerink.org",
    "wof:name":"Westerink",
    "wof:placetype":"venue"
},
  "geometry": {"coordinates":[5.770907,52.372597],"type":"Point"}
}