{
  "type": "Feature",
  "properties": {
    "iso:country":"NL",
    "sg:address":"Bakkerskamp 24",
    "sg:city":"Losser",
    "sg:orig_category":"Artiestenbureaus",
    "sg:phone":"+31 53 538 3142",
    "sg:postcode":"7582 HA",
    "sg:province":"Overijssel",
    "wof:name":"W A Loff",
    "wof:placetype":"venue"
},
  "geometry": {"coordinates":[6.993407,52.267345],"type":"Point"}
}