{
  "type": "Feature",
  "properties": {
    "addr:full":"Zandstr 127B Beneden Leeuwen Gelderland 6658 CR",
    "addr:housenumber":"127b",
    "addr:postcode":"6658 cr",
    "iso:country":"NL",
    "sg:address":"Zandstr 127B",
    "sg:city":"Beneden Leeuwen",
    "sg:orig_category":"Postkantoren",
    "sg:phone":"+31 487 594 997",
    "sg:postcode":"6658 CR",
    "sg:province":"Gelderland",
    "sg:website":"http://www.postkantoor.nl",
    "wof:name":"Postkantoor",
    "wof:placetype":"venue"
},
  "geometry": {"coordinates":[5.509708,51.880894],"type":"Point"}
}