{
  "type": "Feature",
  "properties": {
    "iso:country":"NL",
    "sg:address":"Kerkstr 13",
    "sg:city":"Mook",
    "sg:orig_category":"Natuurvoeding En Reformartikelen",
    "sg:phone":"+31 24 696 2159",
    "sg:postcode":"6585 AT",
    "sg:province":"Limburg",
    "wof:name":"Alo? Vera",
    "wof:placetype":"venue"
},
  "geometry": {"coordinates":[5.882133,51.749863],"type":"Point"}
}