{
  "type": "Feature",
  "properties": {
    "addr:full":"Beukenlaan 10 Nuenen Noord-Brabant 5671 AJ",
    "addr:housenumber":"10",
    "addr:postcode":"5671 aj",
    "addr:street":"Beukenlaan",
    "iso:country":"NL",
    "sg:address":"Beukenlaan 10",
    "sg:city":"Nuenen",
    "sg:orig_category":"Juridische Dienstverlening",
    "sg:phone":"+31 40 283 1186",
    "sg:postcode":"5671 AJ",
    "sg:province":"Noord-Brabant",
    "wof:name":"Seneca Bv",
    "wof:placetype":"venue"
},
  "geometry": {"coordinates":[5.537184,51.473927],"type":"Point"}
}