{
  "type": "Feature",
  "properties": {
    "addr:full":"Kerssemakersstr 32B Raalte NL.08 8101 AN",
    "addr:housenumber":"32b;nl.08",
    "addr:postcode":"8101 an",
    "addr:street":"Kerssemakersstr",
    "iso:country":"NL",
    "sg:address":"Kerssemakersstr 32B",
    "sg:city":"Raalte",
    "sg:orig_category":"Accountants - Administratie- Consulenten En -Kantoren",
    "sg:phone":"+31 572 330 930",
    "sg:postcode":"8101 AN",
    "sg:province":"NL.08",
    "wof:name":"Werff Krabbe Timmerhuis, Van Der",
    "wof:placetype":"venue"
},
  "geometry": {"coordinates":[6.268157,52.387451],"type":"Point"}
}