{
  "type": "Feature",
  "properties": {
    "addr:full":"Gommelsestr 4 Biezenmortel Noord-Brabant 5074 NG",
    "addr:housenumber":"4",
    "addr:postcode":"5074 ng",
    "addr:street":"Gommelsestr",
    "iso:country":"NL",
    "sg:address":"Gommelsestr 4",
    "sg:city":"Biezenmortel",
    "sg:orig_category":"Heftrucks",
    "sg:phone":"+31 13 511 9132",
    "sg:postcode":"5074 NG",
    "sg:province":"Noord-Brabant",
    "wof:name":"Bertens, J",
    "wof:placetype":"venue"
},
  "geometry": {"coordinates":[5.174141,51.613895],"type":"Point"}
}