{
  "type": "Feature",
  "properties": {
    "addr:full":"Lage Zijde 5 Eindhoven North Brabant 5626 DL",
    "addr:housenumber":"5",
    "addr:postcode":"5626 dl",
    "addr:street":"Lage Zijde",
    "iso:country":"NL",
    "sg:address":"Lage Zijde 5",
    "sg:city":"Eindhoven",
    "sg:orig_category":"Metaalwerken",
    "sg:phone":"+31 40 262 3400",
    "sg:postcode":"5626 DL",
    "sg:province":"North Brabant",
    "wof:name":"Prozon Nederland Bv",
    "wof:placetype":"venue"
},
  "geometry": {"coordinates":[5.418978,51.481567],"type":"Point"}
}