{
  "type": "Feature",
  "properties": {
    "iso:country":"NL",
    "sg:address":"Arnhemseweg 266",
    "sg:city":"Apeldoorn",
    "sg:orig_category":"Artsen And Specialisten",
    "sg:phone":"+31 55 533 2369",
    "sg:postcode":"7334 AA",
    "sg:province":"Gelderland",
    "wof:name":"J.A. Boksteijn",
    "wof:placetype":"venue"
},
  "geometry": {"coordinates":[5.961974,52.193352],"type":"Point"}
}