{
  "type": "Feature",
  "properties": {
    "addr:full":"Eisenhowerln 87 Delft Zuid-Holland 2625 GH",
    "addr:housenumber":"87",
    "addr:postcode":"2625 gh",
    "addr:street":"Eisenhowerln",
    "iso:country":"NL",
    "sg:address":"Eisenhowerln 87",
    "sg:city":"Delft",
    "sg:orig_category":"Adviesbureaus Bedrijfsorganisatie",
    "sg:phone":"+31 15 256 5243",
    "sg:postcode":"2625 GH",
    "sg:province":"Zuid-Holland",
    "wof:name":"Barendregt, Ir G",
    "wof:placetype":"venue"
},
  "geometry": {"coordinates":[4.348855,51.990498],"type":"Point"}
}