{
  "type": "Feature",
  "properties": {
    "addr:full":"Venakkerstr 20 Valkenswaard Noord-Brabant 5552 LK",
    "addr:housenumber":"20",
    "addr:postcode":"5552 lk",
    "addr:street":"Venakkerstr",
    "iso:country":"NL",
    "sg:address":"Venakkerstr 20",
    "sg:city":"Valkenswaard",
    "sg:orig_category":"Verenigingen En Stichtingen",
    "sg:phone":"+31 40 204 9070",
    "sg:postcode":"5552 LK",
    "sg:province":"Noord-Brabant",
    "wof:name":"Jozef Buurtver, St",
    "wof:placetype":"venue"
},
  "geometry": {"coordinates":[5.453875,51.358215],"type":"Point"}
}