{
  "type": "Feature",
  "properties": {
    "addr:full":"Tollenaersngl 15 Leiderdorp Zuid-Holland 2352 JL",
    "addr:housenumber":"15",
    "addr:postcode":"2352 jl",
    "addr:street":"Tollenaersngl",
    "iso:country":"NL",
    "sg:address":"Tollenaersngl 15",
    "sg:city":"Leiderdorp",
    "sg:orig_category":"Adviesbureaus Bedrijfsorganisatie",
    "sg:phone":"+31 71 589 6850",
    "sg:postcode":"2352 JL",
    "sg:province":"Zuid-Holland",
    "wof:name":"Gala",
    "wof:placetype":"venue"
},
  "geometry": {"coordinates":[4.534218,52.156174],"type":"Point"}
}