{
  "type": "Feature",
  "properties": {
    "addr:full":"Bunschotenweg 200 Rotterdam Zuid-Holland 3089 KC",
    "addr:housenumber":"200",
    "addr:postcode":"3089 kc",
    "addr:street":"Bunschotenweg",
    "iso:country":"NL",
    "sg:address":"Bunschotenweg 200",
    "sg:city":"Rotterdam",
    "sg:classifiers":[
        {
            "category":"Retail",
            "subcategory":"Storage",
            "type":"Services"
        }
    ],
    "sg:phone":"+31 10 494 0511",
    "sg:postcode":"3089 KC",
    "sg:province":"Zuid-Holland",
    "sg:tags":[
        "opslag",
        "bewaring"
    ],
    "wof:name":"Ecr Gordijn Containers Bv",
    "wof:placetype":"venue"
},
  "geometry": {"coordinates":[4.4038572311,51.8904342651],"type":"Point"}
}