{
  "type": "Feature",
  "properties": {
    "addr:full":"Bennebroekerln 17C Bennebroek Noord-Holland 2121 GP",
    "addr:housenumber":"17c",
    "addr:postcode":"2121 gp",
    "addr:street":"Bennebroekerln",
    "iso:country":"NL",
    "sg:address":"Bennebroekerln 17C",
    "sg:city":"Bennebroek",
    "sg:orig_category":"Hypotheken",
    "sg:phone":"+31 23 584 0808",
    "sg:postcode":"2121 GP",
    "sg:province":"Noord-Holland",
    "wof:name":"For Finance",
    "wof:placetype":"venue"
},
  "geometry": {"coordinates":[4.594271,52.318798],"type":"Point"}
}