{
  "type": "Feature",
  "properties": {
    "iso:country":"NL",
    "sg:address":"C Binghamwg 98",
    "sg:city":"Rotterdam",
    "sg:orig_category":"Verenigingen En Stichtingen",
    "sg:phone":"+31 10 479 2696",
    "sg:postcode":"3077 PZ",
    "sg:province":"South Holland",
    "wof:name":"Rottweiler Werkgroep, Eerste Ned",
    "wof:placetype":"venue"
},
  "geometry": {"coordinates":[4.57035,51.883656],"type":"Point"}
}