{
  "type": "Feature",
  "properties": {
    "addr:full":"Derkingehof 11 Assen Drenthe 9403 PD",
    "addr:housenumber":"11",
    "addr:postcode":"9403 pd",
    "addr:street":"Derkingehof",
    "iso:country":"NL",
    "sg:address":"Derkingehof 11",
    "sg:city":"Assen",
    "sg:orig_category":"Adviesbureaus Financieel",
    "sg:phone":"+31 592 340 548",
    "sg:postcode":"9403 PD",
    "sg:province":"Drenthe",
    "wof:name":"B & M",
    "wof:placetype":"venue"
},
  "geometry": {"coordinates":[6.574086,53.016521],"type":"Point"}
}