{
  "type": "Feature",
  "properties": {
    "addr:full":"Norgstr 209 S Gravenhage South Holland 2545 TZ",
    "addr:housenumber":"209",
    "addr:postcode":"2545 tz",
    "addr:street":"S Gravenhage",
    "iso:country":"NL",
    "sg:address":"Norgstr 209",
    "sg:city":"S Gravenhage",
    "sg:orig_category":"Zonnebank- En Solariumcentra",
    "sg:phone":"+31 70 329 2963",
    "sg:postcode":"2545 TZ",
    "sg:province":"South Holland",
    "wof:name":"Sun Colour",
    "wof:placetype":"venue"
},
  "geometry": {"coordinates":[4.27049,52.05093],"type":"Point"}
}