{
  "type": "Feature",
  "properties": {
    "iso:country":"NL",
    "sg:address":"Romerkerkwg 39",
    "sg:city":"Beverwyk",
    "sg:orig_category":"Kamerverhuur En -Bemiddeling",
    "sg:phone":"+31 251 251 535",
    "sg:postcode":"1943 EV",
    "sg:province":"Noord-Holland",
    "wof:name":"Vos",
    "wof:placetype":"venue"
},
  "geometry": {"coordinates":[4.6540970802,52.4853858948],"type":"Point"}
}