{
  "type": "Feature",
  "properties": {
    "addr:full":"Penninglaan 2 Rijswijk Zh South Holland 2281 BX",
    "addr:housenumber":"2",
    "addr:postcode":"2281 bx",
    "addr:street":"Penninglaan",
    "iso:country":"NL",
    "sg:address":"Penninglaan 2",
    "sg:city":"Rijswijk Zh",
    "sg:orig_category":"Kappers",
    "sg:phone":"+31 70 398 9596",
    "sg:postcode":"2281 BX",
    "sg:province":"South Holland",
    "wof:name":"Hairclip",
    "wof:placetype":"venue"
},
  "geometry": {"coordinates":[4.3429389,52.0589256287],"type":"Point"}
}