{
  "type": "Feature",
  "properties": {
    "iso:country":"NL",
    "sg:address":"Didamseweg 142",
    "sg:city":"Zevenaar",
    "sg:orig_category":"Verf And Drukinkt Fab",
    "sg:phone":"+31 316 594 444",
    "sg:postcode":"6902 PE",
    "sg:province":"Gelderland",
    "wof:name":"Sicpa Sinclair Bv",
    "wof:placetype":"venue"
},
  "geometry": {"coordinates":[6.088472,51.937035],"type":"Point"}
}