{
  "type": "Feature",
  "properties": {
    "iso:country":"NL",
    "sg:address":"Zuiderlingedk 23",
    "sg:city":"Heukelum",
    "sg:orig_category":"Koffie- En Theehuizen",
    "sg:phone":"+31 183 562 656",
    "sg:postcode":"4161 BM",
    "sg:province":"Gelderland",
    "wof:name":"Uitspanning, De",
    "wof:placetype":"venue"
},
  "geometry": {"coordinates":[5.053868,51.856831],"type":"Point"}
}