{
  "type": "Feature",
  "properties": {
    "addr:full":"Ketelaarskampwg 1-7 S Hertogenbosch North Brabant 5222 AL",
    "addr:housenumber":"1-7",
    "addr:postcode":"5222 al",
    "addr:street":"Ketelaarskampwg;S Hertogenbosch",
    "iso:country":"NL",
    "sg:address":"Ketelaarskampwg 1-7",
    "sg:city":"S Hertogenbosch",
    "sg:orig_category":"Verf En Lak - Fabrieken En Groothandel",
    "sg:phone":"+31 73 627 1700",
    "sg:postcode":"5222 AL",
    "sg:province":"North Brabant",
    "wof:name":"Sigma Bv",
    "wof:placetype":"venue"
},
  "geometry": {"coordinates":[5.274783,51.703182],"type":"Point"}
}