{
  "type": "Feature",
  "properties": {
    "addr:full":"Lohengrinstr 20 S Gravenhage Zuid-Holland 2555 WP",
    "addr:housenumber":"20;gravenhage",
    "addr:postcode":"2555 wp",
    "addr:street":"Lohengrinstr;S",
    "iso:country":"NL",
    "sg:address":"Lohengrinstr 20",
    "sg:city":"S Gravenhage",
    "sg:orig_category":"Adviesbureaus Bedrijfsorganisatie",
    "sg:phone":"+31 70 325 2911",
    "sg:postcode":"2555 WP",
    "sg:province":"Zuid-Holland",
    "wof:name":"Sjerp",
    "wof:placetype":"venue"
},
  "geometry": {"coordinates":[4.2417,52.06638],"type":"Point"}
}