{
  "type": "Feature",
  "properties": {
    "addr:full":"Schoolstraat 9 Wageningen Gelderland 6701 AZ",
    "addr:housenumber":"9",
    "addr:postcode":"6701",
    "addr:street":"Schoolstraat;Gelderland",
    "iso:country":"NL",
    "sg:address":"Schoolstraat 9",
    "sg:city":"Wageningen",
    "sg:orig_category":"Discountwinkels",
    "sg:phone":"+31 317 421 909",
    "sg:postcode":"6701 AZ",
    "sg:province":"Gelderland",
    "wof:name":"Wibra Bv",
    "wof:placetype":"venue"
},
  "geometry": {"coordinates":[5.664367,51.967529],"type":"Point"}
}