{
  "type": "Feature",
  "properties": {
    "addr:full":"I Enschedewg 28 Haarlem Noord-Holland 2031 CR",
    "addr:housenumber":"28;2031",
    "addr:postcode":"cr",
    "iso:country":"NL",
    "sg:address":"I Enschedewg 28",
    "sg:city":"Haarlem",
    "sg:orig_category":"Grafische Materialen",
    "sg:phone":"+31 23 534 6095",
    "sg:postcode":"2031 CR",
    "sg:province":"Noord-Holland",
    "wof:name":"Visprox Bv",
    "wof:placetype":"venue"
},
  "geometry": {"coordinates":[4.66449,52.395248],"type":"Point"}
}