{
  "type": "Feature",
  "properties": {
    "addr:full":"Beethovenstr 300 Amsterdam Noord-Holland 1077 WZ",
    "addr:housenumber":"300",
    "addr:postcode":"1077 wz",
    "iso:country":"NL",
    "sg:address":"Beethovenstr 300",
    "sg:city":"Amsterdam",
    "sg:orig_category":"Banken",
    "sg:phone":"+31 20 348 5000",
    "sg:postcode":"1077 WZ",
    "sg:province":"Noord-Holland",
    "wof:name":"Dexia Bank Nederland Nv",
    "wof:placetype":"venue"
},
  "geometry": {"coordinates":[4.8765,52.34182],"type":"Point"}
}