{
  "type": "Feature",
  "properties": {
    "addr:full":"Herengr 141 Amsterdam Noord-Holland 1015 BH",
    "addr:housenumber":"141",
    "addr:postcode":"1015 bh",
    "iso:country":"NL",
    "sg:address":"Herengr 141",
    "sg:city":"Amsterdam",
    "sg:orig_category":"Adviesbureaus Bedrijfsorganisatie",
    "sg:phone":"+31 20 520 6250",
    "sg:postcode":"1015 BH",
    "sg:province":"Noord-Holland",
    "sg:website":"http://www.essernet.nl",
    "wof:name":"Esser",
    "wof:placetype":"venue"
},
  "geometry": {"coordinates":[4.888974,52.375343],"type":"Point"}
}