{
  "type": "Feature",
  "properties": {
    "iso:country":"NL",
    "sg:address":"Postbus 149",
    "sg:city":"Heerenveen",
    "sg:orig_category":"Koelkasten",
    "sg:phone":"+31 513 681 303",
    "sg:postcode":"8440 AC",
    "sg:province":"Friesland",
    "sg:website":"http://www.polar-koelkasten.nl",
    "wof:name":"Polar",
    "wof:placetype":"venue"
},
  "geometry": {"coordinates":[5.929095,52.95845],"type":"Point"}
}