{
  "type": "Feature",
  "properties": {
    "addr:full":"Gasthuisstraat 108 Helmond North Brabant 5708 HP",
    "addr:housenumber":"108",
    "addr:postcode":"5708 hp",
    "addr:street":"Gasthuisstraat",
    "iso:country":"NL",
    "sg:address":"Gasthuisstraat 108",
    "sg:city":"Helmond",
    "sg:orig_category":"Elektronische Bedrijfsinstallaties",
    "sg:phone":"+31 492 528 975",
    "sg:postcode":"5708 HP",
    "sg:province":"North Brabant",
    "wof:name":"Vahlkamp Handelsonderneming Bv",
    "wof:placetype":"venue"
},
  "geometry": {"coordinates":[5.629029,51.476433],"type":"Point"}
}