{
  "type": "Feature",
  "properties": {
    "iso:country":"NL",
    "sg:address":"Leeuwerikstr 41B",
    "sg:city":"Amsterdam",
    "sg:orig_category":"Administratie- En Boekhoudkantoren",
    "sg:phone":"+31 20 632 2175",
    "sg:postcode":"1021 GJ",
    "sg:province":"Noord-Holland",
    "wof:name":"Bela",
    "wof:placetype":"venue"
},
  "geometry": {"coordinates":[4.916391,52.385124],"type":"Point"}
}