{
  "type": "Feature",
  "properties": {
    "addr:full":"Walstraat 14 Arnhem Gelderland 6811 BC",
    "addr:housenumber":"14",
    "addr:postcode":"6811 bc",
    "addr:street":"Walstraat",
    "iso:country":"NL",
    "sg:address":"Walstraat 14",
    "sg:city":"Arnhem",
    "sg:orig_category":"Kappers",
    "sg:phone":"+31 26 443 8880",
    "sg:postcode":"6811 BC",
    "sg:province":"Gelderland",
    "wof:name":"Chrystel Coiffure",
    "wof:placetype":"venue"
},
  "geometry": {"coordinates":[5.9124698639,51.9822998047],"type":"Point"}
}