{
  "type": "Feature",
  "properties": {
    "addr:full":"Achterstraat 74 Asperen Gelderland 4147 AD",
    "addr:housenumber":"74",
    "addr:postcode":"4147 ad",
    "addr:street":"Achterstraat;Gelderland",
    "iso:country":"NL",
    "sg:address":"Achterstraat 74",
    "sg:city":"Asperen",
    "sg:orig_category":"Boekhouders",
    "sg:phone":"+31 345 619 555",
    "sg:postcode":"4147 AD",
    "sg:province":"Gelderland",
    "wof:name":"Administratiekantoor Ridderbos",
    "wof:placetype":"venue"
},
  "geometry": {"coordinates":[5.11664,51.880699],"type":"Point"}
}