{
  "type": "Feature",
  "properties": {
    "addr:full":"Raadhuislaan 2 Werkendam Noord-Brabant 4251 VS",
    "addr:housenumber":"2",
    "addr:postcode":"4251 vs",
    "addr:street":"Raadhuislaan",
    "iso:country":"NL",
    "sg:address":"Raadhuislaan 2",
    "sg:city":"Werkendam",
    "sg:orig_category":"Overheidsdiensten",
    "sg:phone":"+31 183 507 200",
    "sg:postcode":"4251 VS",
    "sg:province":"Noord-Brabant",
    "wof:name":"Gemeente Werkendam",
    "wof:placetype":"venue"
},
  "geometry": {"coordinates":[4.8980298042,51.8068008423],"type":"Point"}
}