{
  "type": "Feature",
  "properties": {
    "addr:full":"Ryksstrwg 42 Hellevoetsluis Zuid-Holland 3223 KA",
    "addr:housenumber":"42",
    "addr:postcode":"3223 ka",
    "addr:street":"Ryksstrwg",
    "iso:country":"NL",
    "sg:address":"Ryksstrwg 42",
    "sg:city":"Hellevoetsluis",
    "sg:orig_category":"Bioscopen",
    "sg:phone":"+31 181 327 500",
    "sg:postcode":"3223 KA",
    "sg:province":"Zuid-Holland",
    "wof:name":"Tivoli",
    "wof:placetype":"venue"
},
  "geometry": {"coordinates":[4.14703,51.830406],"type":"Point"}
}