{
  "type": "Feature",
  "properties": {
    "addr:full":"Suze Robertsonstraat 89 'S Gravenhage South Holland 2526 WS",
    "addr:housenumber":"89",
    "addr:postcode":"2526 ws",
    "addr:street":"Suze Robertsonstraat;' S Gravenhage",
    "iso:country":"NL",
    "sg:address":"Suze Robertsonstraat 89",
    "sg:city":"'S Gravenhage",
    "sg:orig_category":"Overheidsdiensten",
    "sg:phone":"+31 70 380 8216",
    "sg:postcode":"2526 WS",
    "sg:province":"South Holland",
    "wof:name":"De Tuimelaar",
    "wof:placetype":"venue"
},
  "geometry": {"coordinates":[4.312417984,52.0648002625],"type":"Point"}
}