{
  "type": "Feature",
  "properties": {
    "addr:full":"Wilhelminastraat 21 Roden Drenthe 9301 AJ",
    "addr:housenumber":"21",
    "addr:postcode":"9301 aj",
    "addr:street":"Wilhelminastraat",
    "iso:country":"NL",
    "sg:address":"Wilhelminastraat 21",
    "sg:city":"Roden",
    "sg:classifiers":[
        {
            "category":"Shopping",
            "subcategory":"Clothing, Apparel, & Fashions",
            "type":"Retail Goods"
        }
    ],
    "sg:phone":"+31 50 501 6376",
    "sg:postcode":"9301 AJ",
    "sg:province":"Drenthe",
    "sg:tags":[
        "ondergoed",
        "lingerie"
    ],
    "wof:name":"Rijpma Lingerie En Badmode",
    "wof:placetype":"venue"
},
  "geometry": {"coordinates":[6.430877,53.138573],"type":"Point"}
}