{
  "type": "Feature",
  "properties": {
    "addr:full":"Pr Bernhardln 25 Amersfoort Utrecht 3818 ZE",
    "addr:housenumber":"25",
    "addr:postcode":"3818 ze",
    "iso:country":"NL",
    "sg:address":"Pr Bernhardln 25",
    "sg:city":"Amersfoort",
    "sg:classifiers":[
        {
            "category":"Professional",
            "subcategory":"Management & Consulting",
            "type":"Services"
        }
    ],
    "sg:phone":"+31 33 465 7673",
    "sg:postcode":"3818 ZE",
    "sg:province":"Utrecht",
    "sg:tags":[
        "relation",
        "adviesbureaus",
        "public"
    ],
    "sg:website":"http://www.bij-de-hand.nl",
    "wof:name":"Bij-De -Hand",
    "wof:placetype":"venue"
},
  "geometry": {"coordinates":[5.386085,52.152325],"type":"Point"}
}