{
  "type": "Feature",
  "properties": {
    "addr:full":"Voordijk 269 Barendrecht Zuid-Holland 2992 AL",
    "addr:housenumber":"269",
    "addr:postcode":"2992 al",
    "addr:street":"Voordijk",
    "iso:country":"NL",
    "sg:address":"Voordijk 269",
    "sg:city":"Barendrecht",
    "sg:orig_category":"Metaalbekleding And -Behandeling",
    "sg:phone":"+31 180 618 002",
    "sg:postcode":"2992 AL",
    "sg:province":"Zuid-Holland",
    "wof:name":"A Huijgen",
    "wof:placetype":"venue"
},
  "geometry": {"coordinates":[4.54064,51.853176],"type":"Point"}
}