{
  "type": "Feature",
  "properties": {
    "addr:full":"Maasstr 175 Amsterdam North Holland 1079 BG",
    "addr:housenumber":"175",
    "addr:postcode":"1079",
    "iso:country":"NL",
    "sg:address":"Maasstr 175",
    "sg:city":"Amsterdam",
    "sg:orig_category":"Kappers",
    "sg:phone":"+31 20 644 4502",
    "sg:postcode":"1079 BG",
    "sg:province":"North Holland",
    "wof:name":"Klok, Rien",
    "wof:placetype":"venue"
},
  "geometry": {"coordinates":[4.897769,52.341732],"type":"Point"}
}