{
  "type": "Feature",
  "properties": {
    "addr:full":"Grosthuizen 131 Avenhorn Noord-Holland 1633 ES",
    "addr:housenumber":"131",
    "addr:postcode":"1633 es",
    "addr:street":"Grosthuizen",
    "iso:country":"NL",
    "sg:address":"Grosthuizen 131",
    "sg:city":"Avenhorn",
    "sg:orig_category":"Begrafenisverzorging",
    "sg:phone":"+31 229 233 130",
    "sg:postcode":"1633 ES",
    "sg:province":"Noord-Holland",
    "wof:name":"Jonge, De",
    "wof:placetype":"venue"
},
  "geometry": {"coordinates":[4.966063,52.616123],"type":"Point"}
}