{
  "type": "Feature",
  "properties": {
    "addr:full":"Schutstraat 3 Hoogeveen Drenthe 7907 CA",
    "addr:housenumber":"3",
    "addr:postcode":"7907 ca",
    "addr:street":"Schutstraat",
    "iso:country":"NL",
    "sg:address":"Schutstraat 3",
    "sg:city":"Hoogeveen",
    "sg:orig_category":"Herenmodezaken",
    "sg:phone":"+31 528 250 918",
    "sg:postcode":"7907 CA",
    "sg:province":"Drenthe",
    "wof:name":"De Gentleman",
    "wof:placetype":"venue"
},
  "geometry": {"coordinates":[6.477458,52.720287],"type":"Point"}
}