{
  "type": "Feature",
  "properties": {
    "addr:full":"Stadspolder 11 Drieborg Groningen 9688 TL",
    "addr:housenumber":"11",
    "addr:postcode":"9688 tl",
    "addr:street":"Stadspolder",
    "iso:country":"NL",
    "sg:address":"Stadspolder 11",
    "sg:city":"Drieborg",
    "sg:orig_category":"Verhuur Landbouwmachines",
    "sg:phone":"+31 597 591 071",
    "sg:postcode":"9688 TL",
    "sg:province":"Groningen",
    "wof:name":"Van Wieringen Verreiker Verhuur",
    "wof:placetype":"venue"
},
  "geometry": {"coordinates":[7.191594,53.217213],"type":"Point"}
}