{
  "type": "Feature",
  "properties": {
    "addr:full":"Wilhelminastraat 39 Hoensbroek Limburg 6431 XS",
    "addr:housenumber":"39",
    "addr:postcode":"6431 xs",
    "addr:street":"Wilhelminastraat",
    "iso:country":"NL",
    "sg:address":"Wilhelminastraat 39",
    "sg:city":"Hoensbroek",
    "sg:classifiers":[
        {
            "category":"Fast Food",
            "type":"Food & Drink"
        }
    ],
    "sg:phone":"+31 45 522 2728",
    "sg:postcode":"6431 XS",
    "sg:province":"Limburg",
    "sg:tags":[
        "afhaal",
        "restaurant"
    ],
    "wof:name":"Frietje Nico",
    "wof:placetype":"venue"
},
  "geometry": {"coordinates":[5.931757,50.922817],"type":"Point"}
}