{
  "type": "Feature",
  "properties": {
    "iso:country":"NL",
    "sg:address":"Bruine Hoopswg 2A",
    "sg:city":"Hoge Hexel",
    "sg:orig_category":"Gehandicapteninformatie",
    "sg:phone":"+31 546 574 944",
    "sg:postcode":"7645 BJ",
    "sg:province":"Overijssel",
    "wof:name":"M\u00f7Lnbelt Manege",
    "wof:placetype":"venue"
},
  "geometry": {"coordinates":[6.563553,52.397137],"type":"Point"}
}