{
  "type": "Feature",
  "properties": {
    "addr:full":"Baartmanstraat 11 Sassenheim Zuid-Holland 2171 DA",
    "addr:housenumber":"11",
    "addr:postcode":"2171 da",
    "addr:street":"Baartmanstraat",
    "iso:country":"NL",
    "sg:address":"Baartmanstraat 11",
    "sg:city":"Sassenheim",
    "sg:orig_category":"Vaste And Vloeibare Brandstoffen",
    "sg:phone":"+31 252 214 956",
    "sg:postcode":"2171 DA",
    "sg:province":"Zuid-Holland",
    "wof:name":"J.H. Hoogeveen",
    "wof:placetype":"venue"
},
  "geometry": {"coordinates":[4.516125,52.220776],"type":"Point"}
}