{
  "type": "Feature",
  "properties": {
    "addr:full":"Kommerveldlaan 2 Eygelshoven Limburg 6471 HL",
    "addr:housenumber":"2",
    "addr:postcode":"6471 hl",
    "addr:street":"Kommerveldlaan",
    "iso:country":"NL",
    "sg:address":"Kommerveldlaan 2",
    "sg:city":"Eygelshoven",
    "sg:orig_category":"Bloemen And Planten",
    "sg:phone":"+31 45 535 1313",
    "sg:postcode":"6471 HL",
    "sg:province":"Limburg",
    "wof:name":"Rega Bv",
    "wof:placetype":"venue"
},
  "geometry": {"coordinates":[6.051939,50.890121],"type":"Point"}
}