{
  "type": "Feature",
  "properties": {
    "addr:full":"1E Weerdsweg 132 Deventer Overijssel 7412 WX",
    "addr:housenumber":"132",
    "addr:postcode":"7412 wx",
    "addr:street":"1E Weerdsweg",
    "iso:country":"NL",
    "sg:address":"1E Weerdsweg 132",
    "sg:city":"Deventer",
    "sg:orig_category":"Woningbouwverenigingen",
    "sg:phone":"+31 570 614 540",
    "sg:postcode":"7412 WX",
    "sg:province":"Overijssel",
    "wof:name":"Woningvereniging Eigen Bouw",
    "wof:placetype":"venue"
},
  "geometry": {"coordinates":[6.1416988373,52.2628707886],"type":"Point"}
}