{
  "type": "Feature",
  "properties": {
    "addr:full":"Rynstr 58A Amsterdam North Holland 1078 RD",
    "addr:housenumber":"58a",
    "addr:postcode":"1078 rd",
    "addr:street":"Rynstr",
    "iso:country":"NL",
    "sg:address":"Rynstr 58A",
    "sg:city":"Amsterdam",
    "sg:orig_category":"Fotozaken",
    "sg:phone":"+31 20 673 0357",
    "sg:postcode":"1078 RD",
    "sg:province":"North Holland",
    "wof:name":"Quick Print",
    "wof:placetype":"venue"
},
  "geometry": {"coordinates":[4.89178,52.34341],"type":"Point"}
}