{
  "type": "Feature",
  "properties": {
    "addr:full":"Schermeerstr 13A Stompetoren Noord-Holland 1841 GE",
    "addr:housenumber":"13a",
    "addr:postcode":"1841",
    "addr:street":"Schermeerstr",
    "iso:country":"NL",
    "sg:address":"Schermeerstr 13A",
    "sg:city":"Stompetoren",
    "sg:orig_category":"Lijstenmakerijen",
    "sg:phone":"+31 72 503 9566",
    "sg:postcode":"1841 GE",
    "sg:province":"Noord-Holland",
    "sg:website":"http://www.inlijstservice.nl",
    "wof:name":"Duin Inlijstservice, C",
    "wof:placetype":"venue"
},
  "geometry": {"coordinates":[4.818768,52.612991],"type":"Point"}
}