{
  "type": "Feature",
  "properties": {
    "iso:country":"NL",
    "sg:address":"Rivierenlaan 113",
    "sg:city":"Rozenburg Zh",
    "sg:orig_category":"Boekhouders",
    "sg:phone":"+31 181 212 515",
    "sg:postcode":"3181 DN",
    "sg:province":"Zuid-Holland",
    "wof:name":"H. Van Kruining Adviezen & Administratie",
    "wof:placetype":"venue"
},
  "geometry": {"coordinates":[4.250698,51.900093],"type":"Point"}
}