{
  "type": "Feature",
  "properties": {
    "iso:country":"NL",
    "sg:address":"S Burgerstr 455",
    "sg:city":"S Gravenhage",
    "sg:orig_category":"Grafisch Ontwerpers",
    "sg:phone":"+31 70 389 9633",
    "sg:postcode":"2572 TD",
    "sg:province":"South Holland",
    "wof:name":"Cirque De Pepin",
    "wof:placetype":"venue"
},
  "geometry": {"coordinates":[4.29421,52.06422],"type":"Point"}
}