{
  "type": "Feature",
  "properties": {
    "addr:full":"Korte Moermondsweg 25 Renesse Zeeland 4325 LB",
    "addr:housenumber":"25",
    "addr:postcode":"4325 lb",
    "addr:street":"Korte Moermondsweg",
    "iso:country":"NL",
    "sg:address":"Korte Moermondsweg 25",
    "sg:city":"Renesse",
    "sg:orig_category":"Kampeerterreinen",
    "sg:phone":"+31 111 462 960",
    "sg:postcode":"4325 LB",
    "sg:province":"Zeeland",
    "wof:name":"Camping Chanremo",
    "wof:placetype":"venue"
},
  "geometry": {"coordinates":[3.7971289158,51.7361564636],"type":"Point"}
}