{
  "type": "Feature",
  "properties": {
    "addr:full":"Davidsplein 11 Veenendaal Utrecht 3905 AZ",
    "addr:housenumber":"11",
    "addr:postcode":"3905",
    "addr:street":"Davidsplein",
    "iso:country":"NL",
    "sg:address":"Davidsplein 11",
    "sg:city":"Veenendaal",
    "sg:orig_category":"Bloemen And Planten",
    "sg:phone":"+31 318 510 106",
    "sg:postcode":"3905 AZ",
    "sg:province":"Utrecht",
    "wof:name":"Bloemsierkunst Cees Korver",
    "wof:placetype":"venue"
},
  "geometry": {"coordinates":[5.54751,52.029739],"type":"Point"}
}