{
  "type": "Feature",
  "properties": {
    "addr:full":"Nieuwstraat 379 Apeldoorn Gelderland 7311 BR",
    "addr:housenumber":"379",
    "addr:postcode":"7311 br",
    "addr:street":"Nieuwstraat;Gelderland",
    "iso:country":"NL",
    "sg:address":"Nieuwstraat 379",
    "sg:city":"Apeldoorn",
    "sg:orig_category":"Organisaties And Verenigingen",
    "sg:phone":"+31 55 521 8924",
    "sg:postcode":"7311 BR",
    "sg:province":"Gelderland",
    "wof:name":"Kunstuitleen Sbk",
    "wof:placetype":"venue"
},
  "geometry": {"coordinates":[5.9584498405,52.2158317566],"type":"Point"}
}