{
  "type": "Feature",
  "properties": {
    "addr:full":"Estrikwurk 2 Workum Friesland 8711 KD",
    "addr:housenumber":"2",
    "addr:postcode":"8711 kd",
    "addr:street":"Estrikwurk",
    "iso:country":"NL",
    "sg:address":"Estrikwurk 2",
    "sg:city":"Workum",
    "sg:orig_category":"Gespecialiseerde Bouw",
    "sg:phone":"+31 515 542 454",
    "sg:postcode":"8711 KD",
    "sg:province":"Friesland",
    "wof:name":"Faber Engineering & Konstruktiewerken Lemmer",
    "wof:placetype":"venue"
},
  "geometry": {"coordinates":[5.453252,52.981567],"type":"Point"}
}