{
  "type": "Feature",
  "properties": {
    "addr:full":"V Metmanstr 3 Ryswyk Zh South Holland 2282 GL",
    "addr:housenumber":"3;zh",
    "addr:postcode":"2282 gl",
    "addr:street":"Metmanstr",
    "iso:country":"NL",
    "sg:address":"V Metmanstr 3",
    "sg:city":"Ryswyk Zh",
    "sg:classifiers":[
        {
            "category":"Manufacturing",
            "subcategory":"Electronics",
            "type":"Manufacturing & Wholesale Goods"
        }
    ],
    "sg:phone":"+31 70 390 0769",
    "sg:postcode":"2282 GL",
    "sg:province":"South Holland",
    "sg:tags":[
        "en",
        "laser",
        "lasertechniek"
    ],
    "wof:name":"Laser Internationaal Holland",
    "wof:placetype":"venue"
},
  "geometry": {"coordinates":[4.33694,52.056503],"type":"Point"}
}