{
  "type": "Feature",
  "properties": {
    "addr:full":"Haverterstr 14 Koningsbosch Limburg 6104 AR",
    "addr:housenumber":"14",
    "addr:postcode":"6104",
    "addr:street":"Haverterstr",
    "iso:country":"NL",
    "sg:address":"Haverterstr 14",
    "sg:city":"Koningsbosch",
    "sg:orig_category":"Voetbalverenigingen",
    "sg:phone":"+31 475 302 364",
    "sg:postcode":"6104 AR",
    "sg:province":"Limburg",
    "wof:name":"Juliana K",
    "wof:placetype":"venue"
},
  "geometry": {"coordinates":[5.953882,51.053143],"type":"Point"}
}