{
  "type": "Feature",
  "properties": {
    "addr:full":"Hofveld 40 Apeldoorn Gelderland 7331 KD",
    "addr:housenumber":"40",
    "addr:postcode":"7331 kd",
    "addr:street":"Hofveld;Gelderland",
    "iso:country":"NL",
    "sg:address":"Hofveld 40",
    "sg:city":"Apeldoorn",
    "sg:orig_category":"Glazenwasserijen",
    "sg:phone":"+31 55 540 2777",
    "sg:postcode":"7331 KD",
    "sg:province":"Gelderland",
    "wof:name":"Vga",
    "wof:placetype":"venue"
},
  "geometry": {"coordinates":[5.9654,52.196327],"type":"Point"}
}