{
  "type": "Feature",
  "properties": {
    "addr:full":"Tintelberg 4 Roermond Limburg 6041 PS",
    "addr:housenumber":"4",
    "addr:postcode":"6041 ps",
    "addr:street":"Tintelberg",
    "iso:country":"NL",
    "sg:address":"Tintelberg 4",
    "sg:city":"Roermond",
    "sg:orig_category":"Adviesbureaus Bedrijfsorganisatie",
    "sg:phone":"+31 475 315 360",
    "sg:postcode":"6041 PS",
    "sg:province":"Limburg",
    "wof:name":"Brinkerhof, J D",
    "wof:placetype":"venue"
},
  "geometry": {"coordinates":[5.975197,51.17931],"type":"Point"}
}