{
  "type": "Feature",
  "properties": {
    "addr:full":"Talud 20 Gorinchem Zuid-Holland 4207 EH",
    "addr:housenumber":"20",
    "addr:postcode":"4207 eh",
    "addr:street":"Talud",
    "iso:country":"NL",
    "sg:address":"Talud 20",
    "sg:city":"Gorinchem",
    "sg:orig_category":"Verhuur",
    "sg:phone":"+31 183 664 601",
    "sg:postcode":"4207 EH",
    "sg:province":"Zuid-Holland",
    "wof:name":"Bellissimo",
    "wof:placetype":"venue"
},
  "geometry": {"coordinates":[4.987683,51.831978],"type":"Point"}
}