{
  "type": "Feature",
  "properties": {
    "addr:full":"Oudestraat 64 Neede California 7161 DX",
    "addr:housenumber":"64",
    "addr:postcode":"7161 dx",
    "addr:street":"Oudestraat",
    "iso:country":"NL",
    "sg:address":"Oudestraat 64",
    "sg:city":"Neede",
    "sg:orig_category":"Werving And Selectie Van Vast Personeel",
    "sg:phone":"+31 545 296 158",
    "sg:postcode":"7161 DX",
    "sg:province":"California",
    "wof:name":"Arbeidsbureau Neede",
    "wof:placetype":"venue"
},
  "geometry": {"coordinates":[-121.3170623779,38.2996330261],"type":"Point"}
}