{
  "type": "Feature",
  "properties": {
    "addr:full":"Deltapln 8 Deventer NL.08 7417 BG",
    "addr:housenumber":"8;nl.08",
    "addr:postcode":"7417",
    "addr:street":"Deltapln",
    "iso:country":"NL",
    "sg:address":"Deltapln 8",
    "sg:city":"Deventer",
    "sg:orig_category":"Kappers",
    "sg:phone":"+31 570 620 877",
    "sg:postcode":"7417 BG",
    "sg:province":"NL.08",
    "wof:name":"Cox, Hannelore",
    "wof:placetype":"venue"
},
  "geometry": {"coordinates":[6.185336113,52.2551345825],"type":"Point"}
}