{
  "type": "Feature",
  "properties": {
    "addr:full":"Crosestein 1624 Zeist Noord-Holland 3704 PA",
    "addr:housenumber":"1624",
    "addr:postcode":"3704 pa",
    "addr:street":"Crosestein",
    "iso:country":"NL",
    "sg:address":"Crosestein 1624",
    "sg:city":"Zeist",
    "sg:orig_category":"Onderhoudswerken",
    "sg:phone":"+31 30 695 5250",
    "sg:postcode":"3704 PA",
    "sg:province":"Noord-Holland",
    "wof:name":"Aalten, J",
    "wof:placetype":"venue"
},
  "geometry": {"coordinates":[5.21876,52.090332],"type":"Point"}
}