{
  "type": "Feature",
  "properties": {
    "iso:country":"NL",
    "sg:address":"Bingerweg 14",
    "sg:city":"Haarlem",
    "sg:orig_category":"Metaalbekleding And -Behandeling",
    "sg:phone":"+31 23 542 6446",
    "sg:postcode":"2031 AZ",
    "sg:province":"Noord-Holland",
    "wof:name":"Breedveld",
    "wof:placetype":"venue"
},
  "geometry": {"coordinates":[4.662778,52.396877],"type":"Point"}
}