{
  "type": "Feature",
  "properties": {
    "iso:country":"NL",
    "sg:address":"Malbergstraat 27",
    "sg:city":"Voerendaal",
    "sg:orig_category":"Vertaal- And Tolkenbureaus",
    "sg:phone":"+31 45 575 4436",
    "sg:postcode":"6367 BT",
    "sg:province":"Limburg",
    "wof:name":"Beate Schmitz Vertalingen",
    "wof:placetype":"venue"
},
  "geometry": {"coordinates":[5.938477,50.878876],"type":"Point"}
}