{
  "type": "Feature",
  "properties": {
    "iso:country":"NL",
    "sg:address":"Hoefstraat 75",
    "sg:city":"Tilburg",
    "sg:orig_category":"Fotostudio'S And Fotografen",
    "sg:phone":"+31 13 535 9447",
    "sg:postcode":"5014 NH",
    "sg:province":"Noord-Brabant",
    "wof:name":"M Van Den Broek",
    "wof:placetype":"venue"
},
  "geometry": {"coordinates":[5.087731,51.573883],"type":"Point"}
}