{
  "type": "Feature",
  "properties": {
    "addr:full":"Delftweg 188 Rotterdam Zuid-Holland 3046 NC",
    "addr:housenumber":"188",
    "addr:postcode":"3046 nc",
    "addr:street":"Delftweg",
    "iso:country":"NL",
    "sg:address":"Delftweg 188",
    "sg:city":"Rotterdam",
    "sg:orig_category":"Loodgieterswerk, Verwarming And Sanitaire Installaties",
    "sg:phone":"+31 10 462 0411",
    "sg:postcode":"3046 NC",
    "sg:province":"Zuid-Holland",
    "wof:name":"Technisch Buro Tom Bv",
    "wof:placetype":"venue"
},
  "geometry": {"coordinates":[4.403862,51.954384],"type":"Point"}
}