{
  "type": "Feature",
  "properties": {
    "iso:country":"NL",
    "sg:address":"Torenmolen 125",
    "sg:city":"Barendrecht",
    "sg:orig_category":"Handelsbemiddeling Textiel And Lederwaren",
    "sg:phone":"+31 180 610 124",
    "sg:postcode":"2992 DH",
    "sg:province":"Zuid-Holland",
    "wof:name":"Textielerij",
    "wof:placetype":"venue"
},
  "geometry": {"coordinates":[4.529382,51.849487],"type":"Point"}
}