{
  "type": "Feature",
  "properties": {
    "addr:full":"Kornwierde 56 Almere Flevoland 1353 KE",
    "addr:housenumber":"56",
    "addr:postcode":"1353 ke",
    "addr:street":"Kornwierde;Flevoland",
    "iso:country":"NL",
    "sg:address":"Kornwierde 56",
    "sg:city":"Almere",
    "sg:orig_category":"Architecten",
    "sg:phone":"+31 36 531 4768",
    "sg:postcode":"1353 KE",
    "sg:province":"Flevoland",
    "wof:name":"Van Brenk Tuintechnieken",
    "wof:placetype":"venue"
},
  "geometry": {"coordinates":[5.203589,52.338497],"type":"Point"}
}