{
  "type": "Feature",
  "properties": {
    "addr:full":"Apollo 135 Soesterberg Utrecht 3769 TC",
    "addr:housenumber":"135",
    "addr:postcode":"3769 tc",
    "addr:street":"Apollo",
    "iso:country":"NL",
    "sg:address":"Apollo 135",
    "sg:city":"Soesterberg",
    "sg:orig_category":"Bedrijfs- And Managementsconsultants",
    "sg:phone":"+31 346 352 305",
    "sg:postcode":"3769 TC",
    "sg:province":"Utrecht",
    "wof:name":"Pierre Storimans Bv",
    "wof:placetype":"venue"
},
  "geometry": {"coordinates":[5.301231,52.118446],"type":"Point"}
}