{
  "type": "Feature",
  "properties": {
    "iso:country":"NL",
    "sg:address":"Grotewaard 40",
    "sg:city":"Noordeloos",
    "sg:orig_category":"Melkmachines",
    "sg:phone":"+31 183 588 444",
    "sg:postcode":"4225 SL",
    "sg:province":"Zuid-Holland",
    "wof:name":"Melticom Bv",
    "wof:placetype":"venue"
},
  "geometry": {"coordinates":[4.934495,51.886585],"type":"Point"}
}