{
  "type": "Feature",
  "properties": {
    "iso:country":"NL",
    "sg:address":"Jozef Israelslaan 30",
    "sg:city":"Vlissingen",
    "sg:orig_category":"Kappers",
    "sg:phone":"+31 118 410 637",
    "sg:postcode":"4382 VM",
    "sg:province":"Zeeland",
    "wof:name":"Karin'S Haarmode",
    "wof:placetype":"venue"
},
  "geometry": {"coordinates":[3.5746040344,51.4535102844],"type":"Point"}
}