{
  "type": "Feature",
  "properties": {
    "addr:full":"W Barendszstr 6A Arnhem Gelderland 6828 ZK",
    "addr:housenumber":"6a",
    "addr:postcode":"6828",
    "addr:street":"W;Zk",
    "iso:country":"NL",
    "sg:address":"W Barendszstr 6A",
    "sg:city":"Arnhem",
    "sg:orig_category":"Winkelinrichting",
    "sg:phone":"+31 26 442 2571",
    "sg:postcode":"6828 ZK",
    "sg:province":"Gelderland",
    "wof:name":"Quint",
    "wof:placetype":"venue"
},
  "geometry": {"coordinates":[5.9218158722,51.9777603149],"type":"Point"}
}