{
  "type": "Feature",
  "properties": {
    "addr:full":"Hoofdstraat 43 Kortgene Zeeland 4484 CB",
    "addr:housenumber":"43",
    "addr:postcode":"4484 cb",
    "addr:street":"Hoofdstraat",
    "iso:country":"NL",
    "sg:address":"Hoofdstraat 43",
    "sg:city":"Kortgene",
    "sg:orig_category":"Medische Apparatuur And Prothesen Fab",
    "sg:phone":"+31 113 301 200",
    "sg:postcode":"4484 CB",
    "sg:province":"Zeeland",
    "wof:name":"Tandprothetisch Laboratorium Johan Van E",
    "wof:placetype":"venue"
},
  "geometry": {"coordinates":[3.8016951084,51.5571975708],"type":"Point"}
}