{
  "type": "Feature",
  "properties": {
    "addr:full":"Pastoor Smitsstraat 40 Sint Oedenrode North Brabant 5491 XP",
    "addr:housenumber":"40",
    "addr:postcode":"5491 xp",
    "addr:street":"Pastoor Smitsstraat;Oedenrode",
    "iso:country":"NL",
    "sg:address":"Pastoor Smitsstraat 40",
    "sg:city":"Sint Oedenrode",
    "sg:orig_category":"Overheidsdiensten",
    "sg:phone":"+31 413 473 363",
    "sg:postcode":"5491 XP",
    "sg:province":"North Brabant",
    "wof:name":"De Holm",
    "wof:placetype":"venue"
},
  "geometry": {"coordinates":[5.4008998871,51.5828781128],"type":"Point"}
}