{
  "type": "Feature",
  "properties": {
    "addr:full":"Onderwijsboulevard 215 'S Hertogenbosch Noord-Brabant 5223 DE",
    "addr:housenumber":"215 ' s",
    "addr:postcode":"5223 de",
    "addr:street":"Onderwijsboulevard",
    "iso:country":"NL",
    "sg:address":"Onderwijsboulevard 215",
    "sg:city":"'S Hertogenbosch",
    "sg:classifiers":[
        {
            "category":"Professional",
            "subcategory":"Accounting & Tax Preparation",
            "type":"Services"
        }
    ],
    "sg:phone":"+31 73 629 5295",
    "sg:postcode":"5223 DE",
    "sg:province":"Noord-Brabant",
    "sg:tags":[
        "accountant"
    ],
    "wof:name":"Hogeschool 'S-Hertogenbosch",
    "wof:placetype":"venue"
},
  "geometry": {"coordinates":[5.287169,51.688335],"type":"Point"}
}