{
  "type": "Feature",
  "properties": {
    "addr:full":"Slochterenln 5 Bussum Noord-Holland 1405 AL",
    "addr:housenumber":"5",
    "addr:postcode":"1405 al",
    "addr:street":"Slochterenln",
    "iso:country":"NL",
    "sg:address":"Slochterenln 5",
    "sg:city":"Bussum",
    "sg:orig_category":"Meubelen",
    "sg:phone":"+31 35 694 1213",
    "sg:postcode":"1405 AL",
    "sg:province":"Noord-Holland",
    "sg:website":"http://www.tresor.nl",
    "wof:name":"Tresor, Le",
    "wof:placetype":"venue"
},
  "geometry": {"coordinates":[5.156512,52.279541],"type":"Point"}
}