{
  "type": "Feature",
  "properties": {
    "addr:full":"Heiligharn 240 Den Helder Noord-Holland 1785 ST",
    "addr:housenumber":"240",
    "addr:postcode":"1785 st",
    "addr:street":"Heiligharn",
    "iso:country":"NL",
    "sg:address":"Heiligharn 240",
    "sg:city":"Den Helder",
    "sg:orig_category":"Woningbouwverenigingen",
    "sg:phone":"+31 223 634 595",
    "sg:postcode":"1785 ST",
    "sg:province":"Noord-Holland",
    "wof:name":"Woningsticht Den Helder",
    "wof:placetype":"venue"
},
  "geometry": {"coordinates":[4.7733840942,52.9359169006],"type":"Point"}
}