{
  "type": "Feature",
  "properties": {
    "addr:full":"Marnixstraat 382 Amsterdam Noord-Holland 1016 XX",
    "addr:housenumber":"382",
    "addr:postcode":"1016 xx",
    "addr:street":"Marnixstraat",
    "iso:country":"NL",
    "sg:address":"Marnixstraat 382",
    "sg:city":"Amsterdam",
    "sg:classifiers":[
        {
            "category":"Travel",
            "subcategory":"Hotels & Motels",
            "type":"Entertainment"
        }
    ],
    "sg:phone":"+31 20 625 0777",
    "sg:postcode":"1016 XX",
    "sg:province":"Noord-Holland",
    "wof:name":"Hotel Het Witte Huis",
    "wof:placetype":"venue"
},
  "geometry": {"coordinates":[4.880004,52.365406],"type":"Point"}
}