{
  "type": "Feature",
  "properties": {
    "addr:full":"Hoogstr 48 Montfoort Utrecht 3417 HD",
    "addr:housenumber":"48",
    "addr:postcode":"3417 hd",
    "addr:street":"Hoogstr",
    "iso:country":"NL",
    "sg:address":"Hoogstr 48",
    "sg:city":"Montfoort",
    "sg:orig_category":"Mode-Artikelen Dames En Heren",
    "sg:phone":"+31 348 421 612",
    "sg:postcode":"3417 HD",
    "sg:province":"Utrecht",
    "wof:name":"Brouwer Bv",
    "wof:placetype":"venue"
},
  "geometry": {"coordinates":[4.946729,52.044067],"type":"Point"}
}