{
  "type": "Feature",
  "properties": {
    "addr:full":"Mentieswg 1 Elburg Gelderland 8081 RZ",
    "addr:housenumber":"1",
    "addr:postcode":"8081 rz",
    "addr:street":"Mentieswg;Gelderland",
    "iso:country":"NL",
    "sg:address":"Mentieswg 1",
    "sg:city":"Elburg",
    "sg:orig_category":"Paardenhandelaren",
    "sg:phone":"+31 525 681 060",
    "sg:postcode":"8081 RZ",
    "sg:province":"Gelderland",
    "wof:name":"Rommelpot, De",
    "wof:placetype":"venue"
},
  "geometry": {"coordinates":[5.870086,52.455818],"type":"Point"}
}