{
  "type": "Feature",
  "properties": {
    "addr:full":"Pr Marykestr 4 Twello Gelderland 7391 DP",
    "addr:housenumber":"4",
    "addr:postcode":"7391 dp",
    "addr:street":"Gelderland",
    "iso:country":"NL",
    "sg:address":"Pr Marykestr 4",
    "sg:city":"Twello",
    "sg:orig_category":"Autorijscholen",
    "sg:phone":"+31 571 270 344",
    "sg:postcode":"7391 DP",
    "sg:province":"Gelderland",
    "wof:name":"Rayman",
    "wof:placetype":"venue"
},
  "geometry": {"coordinates":[6.095215,52.237442],"type":"Point"}
}