{
  "type": "Feature",
  "properties": {
    "addr:full":"Paardenhoeve 54 Houten Utrecht 3992 PK",
    "addr:housenumber":"54",
    "addr:postcode":"3992 pk",
    "addr:street":"Paardenhoeve",
    "iso:country":"NL",
    "sg:address":"Paardenhoeve 54",
    "sg:city":"Houten",
    "sg:orig_category":"Fotostudio'S And Fotografen",
    "sg:phone":"+31 30 637 8555",
    "sg:postcode":"3992 PK",
    "sg:province":"Utrecht",
    "wof:name":"Ben De Vries Fotografie",
    "wof:placetype":"venue"
},
  "geometry": {"coordinates":[5.159313,52.039135],"type":"Point"}
}