{
  "type": "Feature",
  "properties": {
    "addr:full":"Eendrachtsstraat 150 Rotterdam South Holland 3012 XR",
    "addr:housenumber":"150",
    "addr:postcode":"3012 xr",
    "addr:street":"Eendrachtsstraat",
    "iso:country":"NL",
    "sg:address":"Eendrachtsstraat 150",
    "sg:city":"Rotterdam",
    "sg:orig_category":"Diverse Grafische Activiteiten",
    "sg:phone":"+31 10 240 0788",
    "sg:postcode":"3012 XR",
    "sg:province":"South Holland",
    "wof:name":"Studio Stad Jim Van Der Put Martin Jung",
    "wof:placetype":"venue"
},
  "geometry": {"coordinates":[4.477331,51.913925],"type":"Point"}
}