{
  "type": "Feature",
  "properties": {
    "iso:country":"NL",
    "sg:address":"Lindenstr 93",
    "sg:city":"Spykenisse",
    "sg:orig_category":"Verzekeringen - Verzekeringskantoren",
    "sg:phone":"+31 181 697 231",
    "sg:postcode":"3203 VH",
    "sg:province":"Zuid-Holland",
    "wof:name":"Dijkxhoorn Assuranti\u00ebn Spijkenisse",
    "wof:placetype":"venue"
},
  "geometry": {"coordinates":[4.34116,51.840771],"type":"Point"}
}