{
  "type": "Feature",
  "properties": {
    "iso:country":"NL",
    "sg:address":"Ds Kingwg 9",
    "sg:city":"Heerenveen",
    "sg:orig_category":"Fitnesscentra",
    "sg:phone":"+31 513 624 928",
    "sg:postcode":"8446 KZ",
    "sg:province":"Friesland",
    "sg:website":"http://www.balans4u.nl",
    "wof:name":"Balans Vof",
    "wof:placetype":"venue"
},
  "geometry": {"coordinates":[5.924529,52.950272],"type":"Point"}
}