{
  "type": "Feature",
  "properties": {
    "iso:country":"NL",
    "sg:address":"Gaffelaar 15",
    "sg:city":"Brielle",
    "sg:orig_category":"Beeldende Kunstenaars",
    "sg:phone":"+31 181 417 070",
    "sg:postcode":"3232 TA",
    "sg:province":"Zuid-Holland",
    "wof:name":"Groenewegen, M",
    "wof:placetype":"venue"
},
  "geometry": {"coordinates":[4.159041,51.894733],"type":"Point"}
}