{
  "type": "Feature",
  "properties": {
    "addr:full":"Goudkade 12 Gouda South Holland 2802 AA",
    "addr:housenumber":"12",
    "addr:postcode":"2802 aa",
    "addr:street":"Goudkade",
    "iso:country":"NL",
    "sg:address":"Goudkade 12",
    "sg:city":"Gouda",
    "sg:orig_category":"Autokeuringen",
    "sg:phone":"+31 182 521 228",
    "sg:postcode":"2802 AA",
    "sg:province":"South Holland",
    "wof:name":"W Bogaard",
    "wof:placetype":"venue"
},
  "geometry": {"coordinates":[4.690346,52.013424],"type":"Point"}
}