{
  "type": "Feature",
  "properties": {
    "addr:full":"Frisiastate 1 Oenkerk Friesland 9062 GX",
    "addr:housenumber":"1",
    "addr:postcode":"9062 gx",
    "addr:street":"Frisiastate",
    "iso:country":"NL",
    "sg:address":"Frisiastate 1",
    "sg:city":"Oenkerk",
    "sg:orig_category":"Artsen - Huisartsen",
    "sg:phone":"+31 58 256 1337",
    "sg:postcode":"9062 GX",
    "sg:province":"Friesland",
    "wof:name":"Boer, P B De",
    "wof:placetype":"venue"
},
  "geometry": {"coordinates":[5.898886,53.251617],"type":"Point"}
}