{
  "type": "Feature",
  "properties": {
    "addr:full":"Provincialeweg 11 Mijdrecht Utrecht 3641 RS",
    "addr:housenumber":"11",
    "addr:postcode":"3641 rs",
    "addr:street":"Provincialeweg",
    "iso:country":"NL",
    "sg:address":"Provincialeweg 11",
    "sg:city":"Mijdrecht",
    "sg:orig_category":"Autokeuringen",
    "sg:phone":"+31 297 281 363",
    "sg:postcode":"3641 RS",
    "sg:province":"Utrecht",
    "wof:name":"Hogendoorn Autobanden Bv",
    "wof:placetype":"venue"
},
  "geometry": {"coordinates":[4.883454,52.215939],"type":"Point"}
}