{
  "type": "Feature",
  "properties": {
    "iso:country":"NL",
    "sg:address":"Buyskade 43",
    "sg:city":"Amsterdam",
    "sg:orig_category":"Bedrijfs- And Managementsconsultants",
    "sg:phone":"+31 20 686 4600",
    "sg:postcode":"1051 HT",
    "sg:province":"Noord-Holland",
    "wof:name":"Alfabeeld",
    "wof:placetype":"venue"
},
  "geometry": {"coordinates":[4.870847,52.377281],"type":"Point"}
}