{
  "type": "Feature",
  "properties": {
    "addr:full":"Herlaerstraat 55 Hilvarenbeek Noord-Brabant 5081 BJ",
    "addr:housenumber":"55",
    "addr:postcode":"5081 bj",
    "addr:street":"Herlaerstraat",
    "iso:country":"NL",
    "sg:address":"Herlaerstraat 55",
    "sg:city":"Hilvarenbeek",
    "sg:orig_category":"Beroepsorganisaties",
    "sg:phone":"+31 13 505 3184",
    "sg:postcode":"5081 BJ",
    "sg:province":"Noord-Brabant",
    "wof:name":"Fnv",
    "wof:placetype":"venue"
},
  "geometry": {"coordinates":[5.129319,51.488308],"type":"Point"}
}