{
  "type": "Feature",
  "properties": {
    "iso:country":"NL",
    "sg:address":"Ambachtswg 4A",
    "sg:city":"Rhoon",
    "sg:orig_category":"Bewakingsdiensten",
    "sg:phone":"+31 10 506 7074",
    "sg:postcode":"3161 GL",
    "sg:province":"Zuid-Holland",
    "wof:name":"Albrandswaard",
    "wof:placetype":"venue"
},
  "geometry": {"coordinates":[4.43428,51.861107],"type":"Point"}
}