{
  "type": "Feature",
  "properties": {
    "addr:full":"Postbus 2603 Amersfoort Utrecht 3800 GD",
    "addr:housenumber":"2603",
    "addr:postcode":"3800 gd",
    "addr:street":"Postbus",
    "iso:country":"NL",
    "sg:address":"Postbus 2603",
    "sg:city":"Amersfoort",
    "sg:orig_category":"Fotojournalisten Freelance",
    "sg:phone":"+31 341 431 225",
    "sg:postcode":"3800 GD",
    "sg:province":"Utrecht",
    "wof:name":"Schipper, Ruben",
    "wof:placetype":"venue"
},
  "geometry": {"coordinates":[5.38959,52.156101],"type":"Point"}
}