{
  "type": "Feature",
  "properties": {
    "addr:full":"Floralaan 146 Wervershoof Noord-Holland 1693 GR",
    "addr:housenumber":"146",
    "addr:postcode":"1693",
    "addr:street":"Floralaan",
    "iso:country":"NL",
    "sg:address":"Floralaan 146",
    "sg:city":"Wervershoof",
    "sg:orig_category":"Architecten",
    "sg:phone":"+31 228 582 353",
    "sg:postcode":"1693 GR",
    "sg:province":"Noord-Holland",
    "wof:name":"P.J.M. Vertelman",
    "wof:placetype":"venue"
},
  "geometry": {"coordinates":[5.154426,52.732906],"type":"Point"}
}