{
  "type": "Feature",
  "properties": {
    "addr:full":"Tjalk 2 Loosdrecht Noord-Holland 1231 TW",
    "addr:housenumber":"2",
    "addr:postcode":"1231 tw",
    "addr:street":"Tjalk",
    "iso:country":"NL",
    "sg:address":"Tjalk 2",
    "sg:city":"Loosdrecht",
    "sg:orig_category":"Goederenvervoer Over De Weg",
    "sg:phone":"+31 35 582 5550",
    "sg:postcode":"1231 TW",
    "sg:province":"Noord-Holland",
    "wof:name":"Transportbedrijf Van De Wetering Loosdrecht Bv",
    "wof:placetype":"venue"
},
  "geometry": {"coordinates":[5.13078,52.195255],"type":"Point"}
}