{
  "type": "Feature",
  "properties": {
    "addr:full":"Schutstr 70 Hoogeveen Drenthe 7901 EG",
    "addr:housenumber":"70",
    "addr:postcode":"7901 eg",
    "addr:street":"Schutstr",
    "iso:country":"NL",
    "sg:address":"Schutstr 70",
    "sg:city":"Hoogeveen",
    "sg:orig_category":"Huishoudelijke Apparaten En Artikelen",
    "sg:phone":"+31 528 265 656",
    "sg:postcode":"7901 EG",
    "sg:province":"Drenthe",
    "wof:name":"Zoer",
    "wof:placetype":"venue"
},
  "geometry": {"coordinates":[6.474576,52.720242],"type":"Point"}
}