{
  "type": "Feature",
  "properties": {
    "addr:full":"Kastanjeboom 22 Culemborg Gelderland 4101 VT",
    "addr:housenumber":"22",
    "addr:postcode":"4101",
    "addr:street":"Kastanjeboom;Gelderland",
    "iso:country":"NL",
    "sg:address":"Kastanjeboom 22",
    "sg:city":"Culemborg",
    "sg:orig_category":"Boekhouders",
    "sg:phone":"+31 345 519 205",
    "sg:postcode":"4101 VT",
    "sg:province":"Gelderland",
    "wof:name":"Adm- & Belastingadviesbureau Leerentveld",
    "wof:placetype":"venue"
},
  "geometry": {"coordinates":[5.242019,51.959404],"type":"Point"}
}