{
  "type": "Feature",
  "properties": {
    "addr:full":"A Derkinderenstr 7 Eindhoven North Brabant 5613 JL",
    "addr:housenumber":"7",
    "addr:postcode":"5613 jl",
    "iso:country":"NL",
    "sg:address":"A Derkinderenstr 7",
    "sg:city":"Eindhoven",
    "sg:orig_category":"Onderhoudswerken",
    "sg:phone":"+31 40 246 2567",
    "sg:postcode":"5613 JL",
    "sg:province":"North Brabant",
    "wof:name":"Heerwaarden, Van",
    "wof:placetype":"venue"
},
  "geometry": {"coordinates":[5.499383,51.438091],"type":"Point"}
}