{
  "type": "Feature",
  "properties": {
    "iso:country":"NL",
    "sg:address":"Tolweg 13",
    "sg:city":"Oud Annerveen",
    "sg:orig_category":"Diverse Bedrijfsinstallaties Gh",
    "sg:phone":"+31 598 491 971",
    "sg:postcode":"9655 PD",
    "sg:province":"Drenthe",
    "wof:name":"Scapa Scandia Limited",
    "wof:placetype":"venue"
},
  "geometry": {"coordinates":[6.762412,53.087746],"type":"Point"}
}