{
  "type": "Feature",
  "properties": {
    "addr:full":"Oudorperplein 2 Alkmaar Noord-Holland 1823 HA",
    "addr:housenumber":"2",
    "addr:postcode":"1823 ha",
    "addr:street":"Oudorperplein",
    "iso:country":"NL",
    "sg:address":"Oudorperplein 2",
    "sg:city":"Alkmaar",
    "sg:orig_category":"Kappers",
    "sg:phone":"+31 72 512 0831",
    "sg:postcode":"1823 HA",
    "sg:province":"Noord-Holland",
    "wof:name":"De Witte Kapsalon",
    "wof:placetype":"venue"
},
  "geometry": {"coordinates":[4.7654891014,52.6340866089],"type":"Point"}
}