{
  "type": "Feature",
  "properties": {
    "addr:full":"Lynbaansgr 162 Amsterdam Noord-Holland 1016 VX",
    "addr:housenumber":"162",
    "addr:postcode":"1016 vx",
    "iso:country":"NL",
    "sg:address":"Lynbaansgr 162",
    "sg:city":"Amsterdam",
    "sg:orig_category":"Schietbanen",
    "sg:phone":"+31 20 616 9023",
    "sg:postcode":"1016 VX",
    "sg:province":"Noord-Holland",
    "wof:name":"Superschot Vereniging",
    "wof:placetype":"venue"
},
  "geometry": {"coordinates":[4.877796,52.370125],"type":"Point"}
}