{
  "type": "Feature",
  "properties": {
    "addr:full":"Chroomsteden 18-20 Enschede Overijssel 7547 TL",
    "addr:housenumber":"18-20",
    "addr:postcode":"7547 tl",
    "addr:street":"Chroomsteden",
    "iso:country":"NL",
    "sg:address":"Chroomsteden 18-20",
    "sg:city":"Enschede",
    "sg:orig_category":"Verhuur",
    "sg:phone":"+31 53 434 1208",
    "sg:postcode":"7547 TL",
    "sg:province":"Overijssel",
    "sg:website":"http://www.nijland-verhuur.nl",
    "wof:name":"Nijland Mise & Place",
    "wof:placetype":"venue"
},
  "geometry": {"coordinates":[6.830811,52.215809],"type":"Point"}
}