{
  "type": "Feature",
  "properties": {
    "addr:full":"Broekergouw 5 B Amsterdam Noord-Holland 1027 AH",
    "addr:housenumber":"5 b",
    "addr:postcode":"1027 ah",
    "addr:street":"Broekergouw",
    "iso:country":"NL",
    "sg:address":"Broekergouw 5 B",
    "sg:city":"Amsterdam",
    "sg:orig_category":"Hoefdierhouderijen",
    "sg:phone":"+31 20 632 6228",
    "sg:postcode":"1027 AH",
    "sg:province":"Noord-Holland",
    "wof:name":"Zenith Arabians",
    "wof:placetype":"venue"
},
  "geometry": {"coordinates":[4.972343,52.413319],"type":"Point"}
}