{
  "type": "Feature",
  "properties": {
    "addr:full":"Kievitstraat 10 Maassluis Zuid-Holland 3145 CD",
    "addr:housenumber":"10",
    "addr:postcode":"3145 cd",
    "addr:street":"Kievitstraat",
    "iso:country":"NL",
    "sg:address":"Kievitstraat 10",
    "sg:city":"Maassluis",
    "sg:orig_category":"Goederenvervoer Over De Weg",
    "sg:phone":"+31 10 592 5769",
    "sg:postcode":"3145 CD",
    "sg:province":"Zuid-Holland",
    "wof:name":"Transportbedrijf P.C.M. Van Heijningen Vof",
    "wof:placetype":"venue"
},
  "geometry": {"coordinates":[4.232076,51.931774],"type":"Point"}
}