{
  "type": "Feature",
  "properties": {
    "addr:full":"Gr Karelln 5 Nieuwegein Utrecht 3434 DT",
    "addr:housenumber":"5",
    "addr:postcode":"3434 dt",
    "iso:country":"NL",
    "sg:address":"Gr Karelln 5",
    "sg:city":"Nieuwegein",
    "sg:orig_category":"Landmeetkundige Bureaus",
    "sg:phone":"+31 30 606 7817",
    "sg:postcode":"3434 DT",
    "sg:province":"Utrecht",
    "wof:name":"Intergeo Vof",
    "wof:placetype":"venue"
},
  "geometry": {"coordinates":[5.082197,52.027325],"type":"Point"}
}