{
  "type": "Feature",
  "properties": {
    "addr:full":"Voltastraat 84 Doetinchem Gelderland 7006 RW",
    "addr:housenumber":"84;7006",
    "addr:street":"Voltastraat;Gelderland;Rw",
    "iso:country":"NL",
    "sg:address":"Voltastraat 84",
    "sg:city":"Doetinchem",
    "sg:orig_category":"Hang- And Sluitwerk Fab",
    "sg:phone":"+31 314 369 988",
    "sg:postcode":"7006 RW",
    "sg:province":"Gelderland",
    "wof:name":"Bosch Ehs Bv",
    "wof:placetype":"venue"
},
  "geometry": {"coordinates":[6.256036,51.971451],"type":"Point"}
}