{
  "type": "Feature",
  "properties": {
    "addr:full":"Groene Kykerwg 12 Apeldoorn Gelderland 7313 GB",
    "addr:housenumber":"12",
    "addr:postcode":"7313 gb",
    "addr:street":"Groene Kykerwg;Gelderland",
    "iso:country":"NL",
    "sg:address":"Groene Kykerwg 12",
    "sg:city":"Apeldoorn",
    "sg:orig_category":"Vertaalbureaus",
    "sg:phone":"+31 55 355 0933",
    "sg:postcode":"7313 GB",
    "sg:province":"Gelderland",
    "sg:website":"http://www.technischvertaalburea.nl",
    "wof:name":"Tilleman Technisch Vertaalbureau",
    "wof:placetype":"venue"
},
  "geometry": {"coordinates":[5.931518,52.219025],"type":"Point"}
}