{
  "type": "Feature",
  "properties": {
    "addr:full":"Wilgstraat 67 'S Gravenhage Zuid-Holland 2565 MC",
    "addr:housenumber":"67;2565",
    "addr:postcode":"mc",
    "addr:street":"Wilgstraat;' S",
    "iso:country":"NL",
    "sg:address":"Wilgstraat 67",
    "sg:city":"'S Gravenhage",
    "sg:orig_category":"Verzekeringen",
    "sg:phone":"+31 70 363 1588",
    "sg:postcode":"2565 MC",
    "sg:province":"Zuid-Holland",
    "wof:name":"Ass Kant K.P.Tjin",
    "wof:placetype":"venue"
},
  "geometry": {"coordinates":[4.271786,52.080341],"type":"Point"}
}