{
  "type": "Feature",
  "properties": {
    "addr:full":"Leeuwerikstr 134 Leeuwarden Friesland 8916 CJ",
    "addr:housenumber":"134",
    "addr:postcode":"8916 cj",
    "iso:country":"NL",
    "sg:address":"Leeuwerikstr 134",
    "sg:city":"Leeuwarden",
    "sg:orig_category":"Verloskundigen",
    "sg:phone":"+31 58 212 1772",
    "sg:postcode":"8916 CJ",
    "sg:province":"Friesland",
    "wof:name":"Donker & Minni Porte, Wilma",
    "wof:placetype":"venue"
},
  "geometry": {"coordinates":[5.780097,53.206593],"type":"Point"}
}