{
  "type": "Feature",
  "properties": {
    "addr:full":"De Kalkovens 2 Zwartsluis NL.08 8064 PS",
    "addr:housenumber":"2;nl.08",
    "addr:postcode":"8064 ps",
    "addr:street":"De Kalkovens",
    "iso:country":"NL",
    "sg:address":"De Kalkovens 2",
    "sg:city":"Zwartsluis",
    "sg:orig_category":"Zuivelproducten",
    "sg:phone":"+31 38 386 7675",
    "sg:postcode":"8064 PS",
    "sg:province":"NL.08",
    "wof:name":"Melkhandel Corporaal",
    "wof:placetype":"venue"
},
  "geometry": {"coordinates":[6.090889,52.646393],"type":"Point"}
}