{
  "type": "Feature",
  "properties": {
    "addr:full":"Emmikhovenstraat 2 Amsterdam Noord-Holland 1069 DH",
    "addr:housenumber":"2",
    "addr:postcode":"1069 dh",
    "addr:street":"Emmikhovenstraat",
    "iso:country":"NL",
    "sg:address":"Emmikhovenstraat 2",
    "sg:city":"Amsterdam",
    "sg:orig_category":"Autokeuringen",
    "sg:phone":"+31 20 619 9242",
    "sg:postcode":"1069 DH",
    "sg:province":"Noord-Holland",
    "wof:name":"Garage Tussenmeer",
    "wof:placetype":"venue"
},
  "geometry": {"coordinates":[4.796565,52.35799],"type":"Point"}
}