{
  "type": "Feature",
  "properties": {
    "addr:full":"Wilhelminapk 108 Tilburg North Brabant 5041 EE",
    "addr:housenumber":"108",
    "addr:postcode":"5041 ee",
    "iso:country":"NL",
    "sg:address":"Wilhelminapk 108",
    "sg:city":"Tilburg",
    "sg:orig_category":"Verenigingen En Stichtingen",
    "sg:phone":"+31 13 543 1276",
    "sg:postcode":"5041 EE",
    "sg:province":"North Brabant",
    "wof:name":"Black And White",
    "wof:placetype":"venue"
},
  "geometry": {"coordinates":[5.0786,51.56432],"type":"Point"}
}