{
  "type": "Feature",
  "properties": {
    "iso:country":"NL",
    "sg:address":"Ringdam 3",
    "sg:city":"Herwen",
    "sg:orig_category":"Verzekeringen",
    "sg:phone":"+31 316 541 914",
    "sg:postcode":"6914 AA",
    "sg:province":"Gelderland",
    "wof:name":"Matthijsse Assurantien Bv",
    "wof:placetype":"venue"
},
  "geometry": {"coordinates":[6.103774,51.875523],"type":"Point"}
}