{
  "type": "Feature",
  "properties": {
    "iso:country":"NL",
    "sg:address":"Kapelsepad 13",
    "sg:city":"Lopikerkapel",
    "sg:orig_category":"Metselwerken",
    "sg:phone":"+31 6 51385029",
    "sg:postcode":"3412 KL",
    "sg:province":"Utrecht",
    "wof:name":"Bruin, De",
    "wof:placetype":"venue"
},
  "geometry": {"coordinates":[5.043509,51.990482],"type":"Point"}
}