{
  "type": "Feature",
  "properties": {
    "iso:country":"NL",
    "sg:address":"Naberln 22",
    "sg:city":"Utrecht",
    "sg:orig_category":"Belastingconsulenten/ Belastingadviseurs",
    "sg:phone":"+31 30 271 2150",
    "sg:postcode":"3571 ZJ",
    "sg:province":"Utrecht",
    "wof:name":"Crouwel, H A",
    "wof:placetype":"venue"
},
  "geometry": {"coordinates":[5.12917,52.108181],"type":"Point"}
}