{
  "type": "Feature",
  "properties": {
    "addr:full":"W Voorstr 68 Oud Beyerland South Holland 3262 JP",
    "addr:housenumber":"68",
    "addr:postcode":"3262 jp",
    "addr:street":"W;Oud Beyerland",
    "iso:country":"NL",
    "sg:address":"W Voorstr 68",
    "sg:city":"Oud Beyerland",
    "sg:orig_category":"Belastingconsulenten/ Belastingadviseurs",
    "sg:phone":"+31 186 617 600",
    "sg:postcode":"3262 JP",
    "sg:province":"South Holland",
    "wof:name":"Vrij",
    "wof:placetype":"venue"
},
  "geometry": {"coordinates":[4.41701,51.823044],"type":"Point"}
}