{
  "type": "Feature",
  "properties": {
    "addr:full":"Kleine Molenstraat 6 Elst Gld Gelderland 6661 ED",
    "addr:housenumber":"6",
    "addr:postcode":"6661 ed",
    "addr:street":"Kleine Molenstraat;Gld Gelderland",
    "iso:country":"NL",
    "sg:address":"Kleine Molenstraat 6",
    "sg:city":"Elst Gld",
    "sg:orig_category":"Discountwinkels",
    "sg:phone":"+31 481 378 284",
    "sg:postcode":"6661 ED",
    "sg:province":"Gelderland",
    "wof:name":"Ter Stal Textiel Bv",
    "wof:placetype":"venue"
},
  "geometry": {"coordinates":[5.844134,51.919346],"type":"Point"}
}