{
  "type": "Feature",
  "properties": {
    "addr:full":"Hoogeveenenweg 83 Nieuwerkerk Ad Ijssel South Holland 2913 LV",
    "addr:housenumber":"83",
    "addr:postcode":"2913",
    "addr:street":"Hoogeveenenweg;Ijssel",
    "iso:country":"NL",
    "sg:address":"Hoogeveenenweg 83",
    "sg:city":"Nieuwerkerk Ad Ijssel",
    "sg:orig_category":"Chemische Producten Gh",
    "sg:phone":"+31 180 314 777",
    "sg:postcode":"2913 LV",
    "sg:province":"South Holland",
    "wof:name":"Poly Service Bv",
    "wof:placetype":"venue"
},
  "geometry": {"coordinates":[4.611469,51.980244],"type":"Point"}
}