{
  "type": "Feature",
  "properties": {
    "addr:full":"Dingspelstraat 36 Gieten Drenthe 9461 JG",
    "addr:housenumber":"36",
    "addr:postcode":"9461 jg",
    "addr:street":"Dingspelstraat",
    "iso:country":"NL",
    "sg:address":"Dingspelstraat 36",
    "sg:city":"Gieten",
    "sg:orig_category":"Boekhouders",
    "sg:phone":"+31 592 261 031",
    "sg:postcode":"9461 JG",
    "sg:province":"Drenthe",
    "wof:name":"Administratiekantoor H. Zwiers",
    "wof:placetype":"venue"
},
  "geometry": {"coordinates":[6.767016,53.001991],"type":"Point"}
}