{
  "type": "Feature",
  "properties": {
    "addr:full":"Van Almondelaan 28 Hilversum Noord-Holland 1215 PD",
    "addr:housenumber":"28",
    "addr:postcode":"1215 pd",
    "addr:street":"Van Almondelaan",
    "iso:country":"NL",
    "sg:address":"Van Almondelaan 28",
    "sg:city":"Hilversum",
    "sg:orig_category":"Boekenuitgeverijen",
    "sg:phone":"+31 35 621 5901",
    "sg:postcode":"1215 PD",
    "sg:province":"Noord-Holland",
    "wof:name":"Schuijt Opleidingen",
    "wof:placetype":"venue"
},
  "geometry": {"coordinates":[5.152777,52.211658],"type":"Point"}
}