{
  "type": "Feature",
  "properties": {
    "addr:full":"Vullinghspk 4 Heeze North Brabant 5591 DB",
    "addr:housenumber":"4",
    "addr:postcode":"5591 db",
    "addr:street":"Vullinghspk",
    "iso:country":"NL",
    "sg:address":"Vullinghspk 4",
    "sg:city":"Heeze",
    "sg:orig_category":"Kappers",
    "sg:phone":"+31 40 226 3737",
    "sg:postcode":"5591 DB",
    "sg:province":"North Brabant",
    "wof:name":"Kreatief, Salon",
    "wof:placetype":"venue"
},
  "geometry": {"coordinates":[5.579227,51.380131],"type":"Point"}
}