{
  "type": "Feature",
  "properties": {
    "addr:full":"Wilhelminastraat 16 Barneveld Gelderland 3771 AR",
    "addr:housenumber":"16",
    "addr:postcode":"3771",
    "addr:street":"Wilhelminastraat;Gelderland",
    "iso:country":"NL",
    "sg:address":"Wilhelminastraat 16",
    "sg:city":"Barneveld",
    "sg:orig_category":"Werving And Selectie Van Tijdelijk Personeel And Uitzendkantoren",
    "sg:phone":"+31 342 423 399",
    "sg:postcode":"3771 AR",
    "sg:province":"Gelderland",
    "wof:name":"Randstad Uitzendbureau",
    "wof:placetype":"venue"
},
  "geometry": {"coordinates":[5.5898990631,52.1370544434],"type":"Point"}
}