{
  "type": "Feature",
  "properties": {
    "addr:full":"Televisiewg 157 Almere Flevoland 1322 BH",
    "addr:housenumber":"157",
    "addr:postcode":"1322 bh",
    "addr:street":"Flevoland",
    "iso:country":"NL",
    "sg:address":"Televisiewg 157",
    "sg:city":"Almere",
    "sg:orig_category":"Pompinstallaties En -Onderhoud",
    "sg:phone":"+31 36 546 1999",
    "sg:postcode":"1322 BH",
    "sg:province":"Flevoland",
    "sg:website":"http://www.quavac.com",
    "wof:name":"Qua-Vac",
    "wof:placetype":"venue"
},
  "geometry": {"coordinates":[5.180881,52.349762],"type":"Point"}
}