{
  "type": "Feature",
  "properties": {
    "addr:full":"Erasmusln 2 Heemstede Noord-Holland 2105 RD",
    "addr:housenumber":"2",
    "addr:postcode":"2105 rd",
    "addr:street":"Erasmusln",
    "iso:country":"NL",
    "sg:address":"Erasmusln 2",
    "sg:city":"Heemstede",
    "sg:orig_category":"Onroerende Goederen",
    "sg:phone":"+31 23 529 3214",
    "sg:postcode":"2105 RD",
    "sg:province":"Noord-Holland",
    "wof:name":"Welle Donker",
    "wof:placetype":"venue"
},
  "geometry": {"coordinates":[4.609098,52.352772],"type":"Point"}
}