{
  "type": "Feature",
  "properties": {
    "addr:full":"Calechelaan 17 Leek Groningen 9351 PJ",
    "addr:housenumber":"17",
    "addr:postcode":"9351 pj",
    "addr:street":"Calechelaan",
    "iso:country":"NL",
    "sg:address":"Calechelaan 17",
    "sg:city":"Leek",
    "sg:orig_category":"Vertaal- And Tolkenbureaus",
    "sg:phone":"+31 594 515 257",
    "sg:postcode":"9351 PJ",
    "sg:province":"Groningen",
    "wof:name":"Drs A M Bruins-Willig",
    "wof:placetype":"venue"
},
  "geometry": {"coordinates":[6.376948,53.174538],"type":"Point"}
}