{
  "type": "Feature",
  "properties": {
    "addr:full":"Markollenweg 2 Holten NL.08 7451 HH",
    "addr:housenumber":"2;nl.08",
    "addr:postcode":"7451 hh",
    "addr:street":"Markollenweg",
    "iso:country":"NL",
    "sg:address":"Markollenweg 2",
    "sg:city":"Holten",
    "sg:orig_category":"Technische Studies And Onderzoek",
    "sg:phone":"+31 548 362 611",
    "sg:postcode":"7451 HH",
    "sg:province":"NL.08",
    "wof:name":"Raadgevend Ingenieursbureau Abrahamsen",
    "wof:placetype":"venue"
},
  "geometry": {"coordinates":[6.437213,52.292107],"type":"Point"}
}