{
  "type": "Feature",
  "properties": {
    "addr:full":"Bramerduinenpad 11 Nes Ameland Friesland 9163 KG",
    "addr:housenumber":"11",
    "addr:postcode":"9163 kg",
    "addr:street":"Bramerduinenpad",
    "iso:country":"NL",
    "sg:address":"Bramerduinenpad 11",
    "sg:city":"Nes Ameland",
    "sg:orig_category":"Vakantieverblijven",
    "sg:phone":"+31 517 392 935",
    "sg:postcode":"9163 KG",
    "sg:province":"Friesland",
    "wof:name":"Blierherne",
    "wof:placetype":"venue"
},
  "geometry": {"coordinates":[5.781205,53.447796],"type":"Point"}
}