{
  "type": "Feature",
  "properties": {
    "addr:full":"Vroegeling 45 Heemskerk North Holland 1964 KR",
    "addr:housenumber":"45",
    "addr:postcode":"1964 kr",
    "addr:street":"Vroegeling",
    "iso:country":"NL",
    "sg:address":"Vroegeling 45",
    "sg:city":"Heemskerk",
    "sg:orig_category":"Behangers",
    "sg:phone":"+31 251 244 397",
    "sg:postcode":"1964 KR",
    "sg:province":"North Holland",
    "sg:website":"http://www.bronder.com",
    "wof:name":"Bronder Behangersbedrijf",
    "wof:placetype":"venue"
},
  "geometry": {"coordinates":[4.655098,52.512688],"type":"Point"}
}