{
  "type": "Feature",
  "properties": {
    "addr:full":"Ferdinand Bolstraat 99 Amsterdam North Holland 1072 LD",
    "addr:housenumber":"99",
    "addr:postcode":"1072 ld",
    "addr:street":"Ferdinand Bolstraat",
    "iso:country":"NL",
    "sg:address":"Ferdinand Bolstraat 99",
    "sg:city":"Amsterdam",
    "sg:orig_category":"Fotolaboratoria",
    "sg:phone":"+31 20 671 5583",
    "sg:postcode":"1072 LD",
    "sg:province":"North Holland",
    "wof:name":"Super Photo Snelservice",
    "wof:placetype":"venue"
},
  "geometry": {"coordinates":[4.891166,52.353287],"type":"Point"}
}