{
  "type": "Feature",
  "properties": {
    "addr:full":"De Lairessestraat 33E Amsterdam Noord-Holland 1071 NS",
    "addr:housenumber":"33e",
    "addr:postcode":"1071 ns",
    "addr:street":"De Lairessestraat",
    "iso:country":"NL",
    "sg:address":"De Lairessestraat 33E",
    "sg:city":"Amsterdam",
    "sg:orig_category":"Beautyfarms And Sauna'S",
    "sg:phone":"+31 20 664 1793",
    "sg:postcode":"1071 NS",
    "sg:province":"Noord-Holland",
    "wof:name":"Peter Hin Yoga & Massagepraktijk",
    "wof:placetype":"venue"
},
  "geometry": {"coordinates":[4.876142,52.35463],"type":"Point"}
}