{
  "type": "Feature",
  "properties": {
    "addr:full":"Goirkestraat 2 Tilburg Noord-Brabant 5046 GK",
    "addr:housenumber":"2",
    "addr:postcode":"5046 gk",
    "addr:street":"Goirkestraat",
    "iso:country":"NL",
    "sg:address":"Goirkestraat 2",
    "sg:city":"Tilburg",
    "sg:orig_category":"Diverse Consumentenartikelen Gh",
    "sg:phone":"+31 13 542 0246",
    "sg:postcode":"5046 GK",
    "sg:province":"Noord-Brabant",
    "wof:name":"T & T Bolivia Import En Distributie",
    "wof:placetype":"venue"
},
  "geometry": {"coordinates":[5.083421,51.575176],"type":"Point"}
}