{
  "type": "Feature",
  "properties": {
    "addr:full":"Ambachtsweg 14 Pijnacker Zuid-Holland 2641 KS",
    "addr:housenumber":"14",
    "addr:postcode":"2641 ks",
    "addr:street":"Ambachtsweg",
    "iso:country":"NL",
    "sg:address":"Ambachtsweg 14",
    "sg:city":"Pijnacker",
    "sg:orig_category":"Metaalwerken",
    "sg:phone":"+31 15 369 9643",
    "sg:postcode":"2641 KS",
    "sg:province":"Zuid-Holland",
    "wof:name":"Vadeko Interieurprojecten",
    "wof:placetype":"venue"
},
  "geometry": {"coordinates":[4.44036,52.028881],"type":"Point"}
}