{
  "type": "Feature",
  "properties": {
    "iso:country":"NL",
    "sg:address":"Kyckerwg 95",
    "sg:city":"De Lier",
    "sg:orig_category":"Kassenbouw",
    "sg:phone":"+31 174 518 811",
    "sg:postcode":"2678 AC",
    "sg:province":"Zuid-Holland",
    "wof:name":"Hct",
    "wof:placetype":"venue"
},
  "geometry": {"coordinates":[4.236771,51.974808],"type":"Point"}
}