{
  "type": "Feature",
  "properties": {
    "addr:full":"Groenlandsekd 41 Vinkeveen Utrecht 3645 BB",
    "addr:housenumber":"41",
    "addr:postcode":"3645 bb",
    "addr:street":"Groenlandsekd",
    "iso:country":"NL",
    "sg:address":"Groenlandsekd 41",
    "sg:city":"Vinkeveen",
    "sg:orig_category":"Agenturen En Commissiehandel",
    "sg:phone":"+31 294 291 578",
    "sg:postcode":"3645 BB",
    "sg:province":"Utrecht",
    "wof:name":"Vreugdenhil",
    "wof:placetype":"venue"
},
  "geometry": {"coordinates":[4.979016,52.228642],"type":"Point"}
}