{
  "type": "Feature",
  "properties": {
    "addr:full":"Roerdompstraat 2 Beek Ubbergen Gelderland 6573 BH",
    "addr:housenumber":"2",
    "addr:postcode":"6573 bh",
    "addr:street":"Roerdompstraat",
    "iso:country":"NL",
    "sg:address":"Roerdompstraat 2",
    "sg:city":"Beek Ubbergen",
    "sg:classifiers":[
        {
            "category":"Education",
            "subcategory":"Preschool",
            "type":"Public Place"
        }
    ],
    "sg:phone":"+31 24 684 1712",
    "sg:postcode":"6573 BH",
    "sg:province":"Gelderland",
    "sg:tags":[
        "kleuteronderwijs",
        "basis-"
    ],
    "wof:name":"Basisschool De Biezenkamp",
    "wof:placetype":"venue"
},
  "geometry": {"coordinates":[5.928527,51.830948],"type":"Point"}
}