{
  "type": "Feature",
  "properties": {
    "addr:full":"Industriestraat 21 Ijmuiden Noord-Holland 1976 CS",
    "addr:housenumber":"21",
    "addr:postcode":"1976 cs",
    "addr:street":"Industriestraat",
    "iso:country":"NL",
    "sg:address":"Industriestraat 21",
    "sg:city":"Ijmuiden",
    "sg:orig_category":"Meubelzaken, Woning- And Keukeninrichting",
    "sg:phone":"+31 251 227 004",
    "sg:postcode":"1976 CS",
    "sg:province":"Noord-Holland",
    "wof:name":"Vof Geels Meubelen",
    "wof:placetype":"venue"
},
  "geometry": {"coordinates":[4.5865,52.458763],"type":"Point"}
}