{
  "type": "Feature",
  "properties": {
    "addr:full":"Kl Gracht 28 Maastricht Limburg 6211 CB",
    "addr:housenumber":"28",
    "addr:postcode":"6211 cb",
    "addr:street":"Kl Gracht",
    "iso:country":"NL",
    "sg:address":"Kl Gracht 28",
    "sg:city":"Maastricht",
    "sg:orig_category":"Autorijscholen",
    "sg:phone":"+31 43 321 0199",
    "sg:postcode":"6211 CB",
    "sg:province":"Limburg",
    "wof:name":"Vogels Bv, Rob",
    "wof:placetype":"venue"
},
  "geometry": {"coordinates":[5.691857,50.852558],"type":"Point"}
}