{
  "type": "Feature",
  "properties": {
    "addr:full":"Reijerweg 249 Ridderkerk Zuid-Holland 2983 AS",
    "addr:housenumber":"249",
    "addr:postcode":"2983 as",
    "addr:street":"Reijerweg",
    "iso:country":"NL",
    "sg:address":"Reijerweg 249",
    "sg:city":"Ridderkerk",
    "sg:orig_category":"Volwassenenonderwijs",
    "sg:phone":"+31 180 486 999",
    "sg:postcode":"2983 AS",
    "sg:province":"Zuid-Holland",
    "wof:name":"Gemini College",
    "wof:placetype":"venue"
},
  "geometry": {"coordinates":[4.598596,51.880875],"type":"Point"}
}