{
  "type": "Feature",
  "properties": {
    "addr:full":"Gender 9 Oisterwyk Noord-Brabant 5061 RR",
    "addr:housenumber":"9",
    "addr:postcode":"5061 rr",
    "addr:street":"Gender",
    "iso:country":"NL",
    "sg:address":"Gender 9",
    "sg:city":"Oisterwyk",
    "sg:orig_category":"Nagelstudio'S",
    "sg:phone":"+31 13 528 8126",
    "sg:postcode":"5061 RR",
    "sg:province":"Noord-Brabant",
    "wof:name":"Karin'S Nagelstudio",
    "wof:placetype":"venue"
},
  "geometry": {"coordinates":[5.177495,51.580605],"type":"Point"}
}