{
  "type": "Feature",
  "properties": {
    "iso:country":"NL",
    "sg:address":"Molenstr 80",
    "sg:city":"Zundert",
    "sg:orig_category":"Postkantoren",
    "sg:phone":"+31 76 597 2350",
    "sg:postcode":"4881 CT",
    "sg:province":"Noord-Brabant",
    "sg:website":"http://www.postkantoor.nl",
    "wof:name":"Postkantoor",
    "wof:placetype":"venue"
},
  "geometry": {"coordinates":[4.660498,51.470413],"type":"Point"}
}