{
  "type": "Feature",
  "properties": {
    "addr:full":"Oranjestr 29-33 Almelo NL.08 7607 BH",
    "addr:housenumber":"29-33;nl.08",
    "addr:postcode":"7607 bh",
    "iso:country":"NL",
    "sg:address":"Oranjestr 29-33",
    "sg:city":"Almelo",
    "sg:orig_category":"Banken",
    "sg:phone":"+31 546 533 022",
    "sg:postcode":"7607 BH",
    "sg:province":"NL.08",
    "wof:name":"Regio Bank",
    "wof:placetype":"venue"
},
  "geometry": {"coordinates":[6.666805,52.359608],"type":"Point"}
}