{
  "type": "Feature",
  "properties": {
    "addr:full":"Steve Bikostraat 18 Hengelo Ov Overijssel 7557 LZ",
    "addr:housenumber":"18",
    "addr:postcode":"7557 lz",
    "addr:street":"Steve Bikostraat;Ov",
    "iso:country":"NL",
    "sg:address":"Steve Bikostraat 18",
    "sg:city":"Hengelo Ov",
    "sg:orig_category":"Hout Gh",
    "sg:phone":"+31 74 250 2054",
    "sg:postcode":"7557 LZ",
    "sg:province":"Overijssel",
    "wof:name":"B.Oostendorp",
    "wof:placetype":"venue"
},
  "geometry": {"coordinates":[6.819874,52.275417],"type":"Point"}
}