{
  "type": "Feature",
  "properties": {
    "addr:full":"Baanhoekwg 1A Dordrecht Zuid-Holland 3313 LA",
    "addr:housenumber":"1a",
    "addr:postcode":"3313 la",
    "addr:street":"Baanhoekwg",
    "iso:country":"NL",
    "sg:address":"Baanhoekwg 1A",
    "sg:city":"Dordrecht",
    "sg:classifiers":[
        {
            "category":"Arena",
            "subcategory":"Auto Racetrack",
            "type":"Entertainment"
        }
    ],
    "sg:phone":"+31 78 616 6164",
    "sg:postcode":"3313 LA",
    "sg:province":"Zuid-Holland",
    "sg:tags":[
        "en",
        "racebanen",
        "kart-"
    ],
    "sg:website":"http://www.kart.nl",
    "wof:name":"Go-Kart-Indoor Karting",
    "wof:placetype":"venue"
},
  "geometry": {"coordinates":[4.72531,51.81496],"type":"Point"}
}