{
  "type": "Feature",
  "properties": {
    "addr:full":"Sumatrakd 615 Amsterdam Noord-Holland 1019 PS",
    "addr:housenumber":"615",
    "addr:postcode":"1019 ps",
    "iso:country":"NL",
    "sg:address":"Sumatrakd 615",
    "sg:city":"Amsterdam",
    "sg:orig_category":"Homeopathie",
    "sg:phone":"+31 20 623 6220",
    "sg:postcode":"1019 PS",
    "sg:province":"Noord-Holland",
    "wof:name":"Klassieke Homeopathie",
    "wof:placetype":"venue"
},
  "geometry": {"coordinates":[4.930756,52.378654],"type":"Point"}
}