{
  "type": "Feature",
  "properties": {
    "addr:full":"Kerkpln 12 Malden Gelderland 6581 AC",
    "addr:housenumber":"12",
    "addr:postcode":"6581 ac",
    "addr:street":"Kerkpln;Gelderland",
    "iso:country":"NL",
    "sg:address":"Kerkpln 12",
    "sg:city":"Malden",
    "sg:orig_category":"Muziekinstrumenten En Bladmuziek",
    "sg:phone":"+31 24 358 4196",
    "sg:postcode":"6581 AC",
    "sg:province":"Gelderland",
    "sg:website":"http://www.accordeonmuseum.nl",
    "wof:name":"Accordeonstemmer, De",
    "wof:placetype":"venue"
},
  "geometry": {"coordinates":[5.851802,51.780952],"type":"Point"}
}