{
  "type": "Feature",
  "properties": {
    "addr:full":"Harselaarseweg 109 Barneveld Gelderland 3771 MA",
    "addr:housenumber":"109",
    "addr:postcode":"3771 ma",
    "addr:street":"Harselaarseweg;Gelderland",
    "iso:country":"NL",
    "sg:address":"Harselaarseweg 109",
    "sg:city":"Barneveld",
    "sg:classifiers":[
        {
            "category":"Retail",
            "subcategory":"Storage",
            "type":"Services"
        }
    ],
    "sg:phone":"+31 342 421 123",
    "sg:postcode":"3771 MA",
    "sg:province":"Gelderland",
    "sg:tags":[
        "opslag",
        "bewaring"
    ],
    "wof:name":"Milagro Bv",
    "wof:placetype":"venue"
},
  "geometry": {"coordinates":[5.5805888176,52.1643676758],"type":"Point"}
}