{
  "type": "Feature",
  "properties": {
    "addr:full":"Ridderhofln 26 Koudekerk Ad Ryn Zuid-Holland 2396 CM",
    "addr:housenumber":"26",
    "addr:postcode":"2396 cm",
    "addr:street":"Ridderhofln",
    "iso:country":"NL",
    "sg:address":"Ridderhofln 26",
    "sg:city":"Koudekerk Ad Ryn",
    "sg:orig_category":"Beeldende Kunstenaars",
    "sg:phone":"+31 71 341 2605",
    "sg:postcode":"2396 CM",
    "sg:province":"Zuid-Holland",
    "wof:name":"Asperen, Martin Van",
    "wof:placetype":"venue"
},
  "geometry": {"coordinates":[4.603195,52.133533],"type":"Point"}
}