{
  "type": "Feature",
  "properties": {
    "addr:full":"Oostdijk 42 Oud Beijerland South Holland 3261 KH",
    "addr:housenumber":"42",
    "addr:postcode":"3261 kh",
    "addr:street":"Oostdijk;Oud Beijerland",
    "iso:country":"NL",
    "sg:address":"Oostdijk 42",
    "sg:city":"Oud Beijerland",
    "sg:classifiers":[
        {
            "category":"Fast Food",
            "type":"Food & Drink"
        }
    ],
    "sg:phone":"+31 186 622 770",
    "sg:postcode":"3261 KH",
    "sg:province":"South Holland",
    "sg:tags":[
        "afhaal",
        "restaurant"
    ],
    "wof:name":"Cafetaria De Dijk",
    "wof:placetype":"venue"
},
  "geometry": {"coordinates":[4.414101,51.826145],"type":"Point"}
}