{
  "type": "Feature",
  "properties": {
    "addr:full":"Wolvenln 30 Hilversum North Holland 1216 DA",
    "addr:housenumber":"30",
    "addr:postcode":"1216 da",
    "addr:street":"Wolvenln",
    "iso:country":"NL",
    "sg:address":"Wolvenln 30",
    "sg:city":"Hilversum",
    "sg:orig_category":"Acupunctuur",
    "sg:phone":"+31 35 623 7753",
    "sg:postcode":"1216 DA",
    "sg:province":"North Holland",
    "wof:name":"Yang, Z G",
    "wof:placetype":"venue"
},
  "geometry": {"coordinates":[5.150261,52.21627],"type":"Point"}
}