{
  "type": "Feature",
  "properties": {
    "addr:full":"Textielweg 8 Amersfoort Utrecht 3812 RV",
    "addr:housenumber":"8",
    "addr:postcode":"3812 rv",
    "addr:street":"Textielweg",
    "iso:country":"NL",
    "sg:address":"Textielweg 8",
    "sg:city":"Amersfoort",
    "sg:orig_category":"Chemische Producten Gh",
    "sg:phone":"+31 33 461 9512",
    "sg:postcode":"3812 RV",
    "sg:province":"Utrecht",
    "wof:name":"Kleurin Bv",
    "wof:placetype":"venue"
},
  "geometry": {"coordinates":[5.369771,52.164402],"type":"Point"}
}