{
  "type": "Feature",
  "properties": {
    "iso:country":"NL",
    "sg:address":"Zevenenderdrift 2",
    "sg:city":"Laren Nh",
    "sg:orig_category":"Woninginrichting",
    "sg:phone":"+31 35 538 0835",
    "sg:postcode":"1251 RC",
    "sg:province":"North Holland",
    "wof:name":"Room For Living",
    "wof:placetype":"venue"
},
  "geometry": {"coordinates":[5.2277150154,52.2530632019],"type":"Point"}
}