{
  "type": "Feature",
  "properties": {
    "addr:full":"Grt Hertoginneln 145 S Gravenhage South Holland 2517 EP",
    "addr:housenumber":"145",
    "addr:postcode":"2517 ep",
    "addr:street":"S Gravenhage",
    "iso:country":"NL",
    "sg:address":"Grt Hertoginneln 145",
    "sg:city":"S Gravenhage",
    "sg:orig_category":"Fotoreportages",
    "sg:phone":"+31 6 24711338",
    "sg:postcode":"2517 EP",
    "sg:province":"South Holland",
    "wof:name":"Triep Art",
    "wof:placetype":"venue"
},
  "geometry": {"coordinates":[4.28708,52.08667],"type":"Point"}
}