{
  "type": "Feature",
  "properties": {
    "addr:full":"Bovenwg 77 St Pancras North Holland 1834 CC",
    "addr:housenumber":"77",
    "addr:postcode":"1834 cc",
    "addr:street":"Bovenwg",
    "iso:country":"NL",
    "sg:address":"Bovenwg 77",
    "sg:city":"St Pancras",
    "sg:orig_category":"Fietsen En Bromfietsen",
    "sg:phone":"+31 72 562 5602",
    "sg:postcode":"1834 CC",
    "sg:province":"North Holland",
    "wof:name":"J & H Cv",
    "wof:placetype":"venue"
},
  "geometry": {"coordinates":[4.783557,52.661404],"type":"Point"}
}