{
  "type": "Feature",
  "properties": {
    "addr:full":"Groene Zoom 20 Roden Drenthe 9301 SJ",
    "addr:housenumber":"20",
    "addr:postcode":"9301",
    "addr:street":"Groene Zoom",
    "iso:country":"NL",
    "sg:address":"Groene Zoom 20",
    "sg:city":"Roden",
    "sg:orig_category":"Kinderopvang",
    "sg:phone":"+31 50 502 0188",
    "sg:postcode":"9301 SJ",
    "sg:province":"Drenthe",
    "wof:name":"Dinges",
    "wof:placetype":"venue"
},
  "geometry": {"coordinates":[6.41516,53.137131],"type":"Point"}
}