{
  "type": "Feature",
  "properties": {
    "addr:full":"Haarlemmerwg 135 Amsterdam Noord-Holland 1051 KX",
    "addr:housenumber":"135",
    "addr:postcode":"1051 kx",
    "iso:country":"NL",
    "sg:address":"Haarlemmerwg 135",
    "sg:city":"Amsterdam",
    "sg:orig_category":"Haarden En Kachels",
    "sg:phone":"+31 20 686 1500",
    "sg:postcode":"1051 KX",
    "sg:province":"Noord-Holland",
    "wof:name":"Jaspers",
    "wof:placetype":"venue"
},
  "geometry": {"coordinates":[4.872803,52.385296],"type":"Point"}
}