{
  "type": "Feature",
  "properties": {
    "addr:full":"Populierenlaan 8 Hattem Gelderland 8051 DA",
    "addr:housenumber":"8",
    "addr:postcode":"8051 da",
    "addr:street":"Populierenlaan;Gelderland",
    "iso:country":"NL",
    "sg:address":"Populierenlaan 8",
    "sg:city":"Hattem",
    "sg:orig_category":"Autokeuringen",
    "sg:phone":"+31 38 444 0000",
    "sg:postcode":"8051 DA",
    "sg:province":"Gelderland",
    "wof:name":"Handelsonderneming De Jong En Ploeg",
    "wof:placetype":"venue"
},
  "geometry": {"coordinates":[6.072074,52.466496],"type":"Point"}
}