{
  "type": "Feature",
  "properties": {
    "iso:country":"NL",
    "sg:address":"Zuiderzeestrwg 493A",
    "sg:city":"Wezep",
    "sg:orig_category":"Kappers",
    "sg:phone":"+31 38 376 4147",
    "sg:postcode":"8091 CM",
    "sg:province":"Gelderland",
    "wof:name":"Alma",
    "wof:placetype":"venue"
},
  "geometry": {"coordinates":[5.9988799095,52.4582672119],"type":"Point"}
}