{
  "type": "Feature",
  "properties": {
    "addr:full":"Gooiland 4B Beverwyk Noord-Holland 1948 RC",
    "addr:housenumber":"4b",
    "addr:postcode":"1948 rc",
    "addr:street":"Gooiland",
    "iso:country":"NL",
    "sg:address":"Gooiland 4B",
    "sg:city":"Beverwyk",
    "sg:classifiers":[
        {
            "category":"Government",
            "subcategory":"Department Of Motor Vehicles",
            "type":"Public Place"
        }
    ],
    "sg:phone":"+31 251 213 822",
    "sg:postcode":"1948 RC",
    "sg:province":"Noord-Holland",
    "sg:tags":[
        "rijscholen",
        "scooter",
        "en",
        "-"
    ],
    "sg:website":"http://www.klingeler.nl",
    "wof:name":"Klingeler, Verkeersschool",
    "wof:placetype":"venue"
},
  "geometry": {"coordinates":[4.671763,52.468224],"type":"Point"}
}