{
  "type": "Feature",
  "properties": {
    "addr:full":"Postbus 170 Roelofarendsveen Zuid-Holland 2370 AD",
    "addr:housenumber":"170",
    "addr:postcode":"2370 ad",
    "addr:street":"Postbus",
    "iso:country":"NL",
    "sg:address":"Postbus 170",
    "sg:city":"Roelofarendsveen",
    "sg:orig_category":"Bloemen En Planten - Groothandel",
    "sg:phone":"+31 71 331 4100",
    "sg:postcode":"2370 AD",
    "sg:province":"Zuid-Holland",
    "wof:name":"Straathof Bv",
    "wof:placetype":"venue"
},
  "geometry": {"coordinates":[4.6314,52.203491],"type":"Point"}
}