{
  "type": "Feature",
  "properties": {
    "addr:full":"V Riebeeckstr 1 Barneveld Gelderland 3772 KE",
    "addr:housenumber":"1",
    "addr:postcode":"3772 ke",
    "addr:street":"Riebeeckstr;Gelderland",
    "iso:country":"NL",
    "sg:address":"V Riebeeckstr 1",
    "sg:city":"Barneveld",
    "sg:orig_category":"Boekhandels",
    "sg:phone":"+31 342 414 892",
    "sg:postcode":"3772 KE",
    "sg:province":"Gelderland",
    "wof:name":"Media Expresse",
    "wof:placetype":"venue"
},
  "geometry": {"coordinates":[5.588843,52.141216],"type":"Point"}
}