{
  "type": "Feature",
  "properties": {
    "addr:full":"Demer 17 Eindhoven Noord-Brabant 5611 AN",
    "addr:housenumber":"17",
    "addr:postcode":"5611 an",
    "addr:street":"Demer",
    "iso:country":"NL",
    "sg:address":"Demer 17",
    "sg:city":"Eindhoven",
    "sg:orig_category":"Dameskleding",
    "sg:phone":"+31 40 296 1900",
    "sg:postcode":"5611 AN",
    "sg:province":"Noord-Brabant",
    "wof:name":"Esprit",
    "wof:placetype":"venue"
},
  "geometry": {"coordinates":[5.47718,51.440594],"type":"Point"}
}