{
  "type": "Feature",
  "properties": {
    "addr:full":"Statenwg 50A Rotterdam Zuid-Holland 3039 JD",
    "addr:housenumber":"50a",
    "addr:postcode":"3039 jd",
    "addr:street":"Statenwg",
    "iso:country":"NL",
    "sg:address":"Statenwg 50A",
    "sg:city":"Rotterdam",
    "sg:orig_category":"Goudsmeden En Zilversmeden",
    "sg:phone":"+31 10 465 6585",
    "sg:postcode":"3039 JD",
    "sg:province":"Zuid-Holland",
    "wof:name":"Nijman, Werner",
    "wof:placetype":"venue"
},
  "geometry": {"coordinates":[4.456709,51.933174],"type":"Point"}
}