{
  "type": "Feature",
  "properties": {
    "addr:full":"Vlotbrugwg 26 Almere Flevoland 1332 AJ",
    "addr:housenumber":"26",
    "addr:postcode":"1332 aj",
    "addr:street":"Vlotbrugwg;Flevoland",
    "iso:country":"NL",
    "sg:address":"Vlotbrugwg 26",
    "sg:city":"Almere",
    "sg:orig_category":"Koeriersdiensten",
    "sg:phone":"+31 36 529 0405",
    "sg:postcode":"1332 AJ",
    "sg:province":"Flevoland",
    "wof:name":"Vst R66",
    "wof:placetype":"venue"
},
  "geometry": {"coordinates":[5.246481,52.402325],"type":"Point"}
}