{
  "type": "Feature",
  "properties": {
    "iso:country":"NL",
    "sg:address":"Dokter Van Stratenweg 15",
    "sg:city":"Gorinchem",
    "sg:classifiers":[
        {
            "category":"Professional",
            "subcategory":"Accounting & Tax Preparation",
            "type":"Services"
        }
    ],
    "sg:phone":"+31 183 629 589",
    "sg:postcode":"4205 LA",
    "sg:province":"Zuid-Holland",
    "sg:tags":[
        "accountant"
    ],
    "wof:name":"Ottevanger Accountancy",
    "wof:placetype":"venue"
},
  "geometry": {"coordinates":[4.952731,51.84296],"type":"Point"}
}