{
  "type": "Feature",
  "properties": {
    "iso:country":"NL",
    "sg:address":"Weena 723",
    "sg:city":"Rotterdam",
    "sg:orig_category":"Grafisch Ontwerpers",
    "sg:phone":"+31 10 411 9010",
    "sg:postcode":"3013 AM",
    "sg:province":"Zuid-Holland",
    "wof:name":"Dumbar, Studio",
    "wof:placetype":"venue"
},
  "geometry": {"coordinates":[4.46803,51.9226],"type":"Point"}
}