{
  "type": "Feature",
  "properties": {
    "iso:country":"NL",
    "sg:address":"Drogery 179",
    "sg:city":"Den Hoorn Zh",
    "sg:orig_category":"Administratie- En Boekhoudkantoren",
    "sg:phone":"+31 15 256 8894",
    "sg:postcode":"2635 GR",
    "sg:province":"South Holland",
    "sg:website":"http://www.admin-plus.nl",
    "wof:name":"Admin Plus Bv",
    "wof:placetype":"venue"
},
  "geometry": {"coordinates":[4.337013,51.99873],"type":"Point"}
}