{
  "type": "Feature",
  "properties": {
    "iso:country":"NL",
    "sg:address":"Hanzeweg 11",
    "sg:city":"Gouda",
    "sg:orig_category":"Kantoorartikelen",
    "sg:phone":"+31 182 572 388",
    "sg:postcode":"2803 MC",
    "sg:province":"South Holland",
    "wof:name":"Multi Office Gouda Bv",
    "wof:placetype":"venue"
},
  "geometry": {"coordinates":[4.6753129959,52.0235557556],"type":"Point"}
}