{
  "type": "Feature",
  "properties": {
    "addr:full":"Goudse Rijweg 13 Rotterdam South Holland 3061 DA",
    "addr:housenumber":"13",
    "addr:postcode":"3061 da",
    "addr:street":"Goudse Rijweg",
    "iso:country":"NL",
    "sg:address":"Goudse Rijweg 13",
    "sg:city":"Rotterdam",
    "sg:orig_category":"Verlichting And Huishoudartikelen",
    "sg:phone":"+31 10 452 2381",
    "sg:postcode":"3061 DA",
    "sg:province":"South Holland",
    "wof:name":"De Groene Lantaarn",
    "wof:placetype":"venue"
},
  "geometry": {"coordinates":[4.500797,51.928944],"type":"Point"}
}