{
  "type": "Feature",
  "properties": {
    "addr:full":"Polluxstr 6 Bergen Op Zoom Noord-Brabant 4625 CD",
    "addr:housenumber":"6",
    "addr:postcode":"4625 cd",
    "addr:street":"Polluxstr",
    "iso:country":"NL",
    "sg:address":"Polluxstr 6",
    "sg:city":"Bergen Op Zoom",
    "sg:orig_category":"Onderhoudswerken",
    "sg:phone":"+31 164 244 835",
    "sg:postcode":"4625 CD",
    "sg:province":"Noord-Brabant",
    "wof:name":"Pebo",
    "wof:placetype":"venue"
},
  "geometry": {"coordinates":[4.302963,51.478306],"type":"Point"}
}