{
  "type": "Feature",
  "properties": {
    "addr:full":"Deken Vaasstraat 11 Wolvega Friesland 8472 AA",
    "addr:housenumber":"11",
    "addr:postcode":"8472 aa",
    "addr:street":"Deken Vaasstraat",
    "iso:country":"NL",
    "sg:address":"Deken Vaasstraat 11",
    "sg:city":"Wolvega",
    "sg:orig_category":"Accountants - Administratie- Consulenten En -Kantoren",
    "sg:phone":"+31 561 616 694",
    "sg:postcode":"8472 AA",
    "sg:province":"Friesland",
    "wof:name":"Dol",
    "wof:placetype":"venue"
},
  "geometry": {"coordinates":[6.006957,52.87944],"type":"Point"}
}