{
  "type": "Feature",
  "properties": {
    "addr:full":"Lonnekerbrugstr 104 Enschede NL.08 7547 AL",
    "addr:housenumber":"104",
    "addr:postcode":"7547",
    "addr:street":"Al",
    "iso:country":"NL",
    "sg:address":"Lonnekerbrugstr 104",
    "sg:city":"Enschede",
    "sg:orig_category":"Machinefabrieken",
    "sg:phone":"+31 53 431 3269",
    "sg:postcode":"7547 AL",
    "sg:province":"NL.08",
    "wof:name":"Rondhuis Bv",
    "wof:placetype":"venue"
},
  "geometry": {"coordinates":[6.85211,52.228516],"type":"Point"}
}