{
  "type": "Feature",
  "properties": {
    "addr:full":"Baanhoekweg 38 Dordrecht Zuid-Holland 3313 LA",
    "addr:housenumber":"38",
    "addr:postcode":"3313 la",
    "addr:street":"Baanhoekweg",
    "iso:country":"NL",
    "sg:address":"Baanhoekweg 38",
    "sg:city":"Dordrecht",
    "sg:orig_category":"Openbaar Vervoer",
    "sg:phone":"+31 6 22246235",
    "sg:postcode":"3313 LA",
    "sg:province":"Zuid-Holland",
    "wof:name":"Waterbus Bv",
    "wof:placetype":"venue"
},
  "geometry": {"coordinates":[4.7338218689,51.8143501282],"type":"Point"}
}