{
  "type": "Feature",
  "properties": {
    "addr:full":"Lage Baan 12 Schaijk Noord-Brabant 5374 NN",
    "addr:housenumber":"12",
    "addr:postcode":"5374 nn",
    "addr:street":"Lage Baan",
    "iso:country":"NL",
    "sg:address":"Lage Baan 12",
    "sg:city":"Schaijk",
    "sg:orig_category":"Boekhouders",
    "sg:phone":"+31 486 464 181",
    "sg:postcode":"5374 NN",
    "sg:province":"Noord-Brabant",
    "wof:name":"Com Lac",
    "wof:placetype":"venue"
},
  "geometry": {"coordinates":[5.597573,51.742817],"type":"Point"}
}