{
  "type": "Feature",
  "properties": {
    "iso:country":"NL",
    "sg:address":"Lage Baan 12",
    "sg:city":"Schaijk",
    "sg:orig_category":"Boekhouders",
    "sg:phone":"+31 486 464 181",
    "sg:postcode":"5374 NN",
    "sg:province":"Noord-Brabant",
    "wof:name":"Com Lac",
    "wof:placetype":"venue"
},
  "geometry": {"coordinates":[5.597573,51.742817],"type":"Point"}
}