{
  "type": "Feature",
  "properties": {
    "addr:full":"P Zeemanstr 14 Wychen Gelderland 6603 AW",
    "addr:housenumber":"14",
    "addr:postcode":"6603 aw",
    "addr:street":"P;Wychen Gelderland",
    "iso:country":"NL",
    "sg:address":"P Zeemanstr 14",
    "sg:city":"Wychen",
    "sg:classifiers":[
        {
            "category":"Wholesale",
            "subcategory":"Meat",
            "type":"Manufacturing & Wholesale Goods"
        }
    ],
    "sg:phone":"+31 24 642 2439",
    "sg:postcode":"6603 AW",
    "sg:province":"Gelderland",
    "sg:tags":[
        "regeltechniek",
        "en",
        "meet-"
    ],
    "wof:name":"Tecflow Int Bv",
    "wof:placetype":"venue"
},
  "geometry": {"coordinates":[5.748455,51.811211],"type":"Point"}
}