{
  "type": "Feature",
  "properties": {
    "addr:full":"Stadionpln 43 Maastricht Limburg 6225 XW",
    "addr:housenumber":"43",
    "addr:postcode":"6225 xw",
    "addr:street":"Stadionpln",
    "iso:country":"NL",
    "sg:address":"Stadionpln 43",
    "sg:city":"Maastricht",
    "sg:orig_category":"Makelaars En Adviseurs Overzeese Producten",
    "sg:phone":"+31 43 601 1575",
    "sg:postcode":"6225 XW",
    "sg:province":"Limburg",
    "wof:name":"Multi Concepts Bv",
    "wof:placetype":"venue"
},
  "geometry": {"coordinates":[5.716654,50.857197],"type":"Point"}
}