{
  "type": "Feature",
  "properties": {
    "addr:full":"Grotestr 25 Ede Gld Gelderland 6711 AH",
    "addr:housenumber":"25",
    "addr:postcode":"6711 ah",
    "addr:street":"Grotestr;Gld Gelderland",
    "iso:country":"NL",
    "sg:address":"Grotestr 25",
    "sg:city":"Ede Gld",
    "sg:orig_category":"Schoenen",
    "sg:phone":"+31 318 650 660",
    "sg:postcode":"6711 AH",
    "sg:province":"Gelderland",
    "wof:name":"Manfield",
    "wof:placetype":"venue"
},
  "geometry": {"coordinates":[5.669896,52.044495],"type":"Point"}
}