{
  "type": "Feature",
  "properties": {
    "iso:country":"NL",
    "sg:address":"Stationsstr 20",
    "sg:city":"Alphen Aan Den Ryn",
    "sg:orig_category":"Adviesbureaus Bedrijfsorganisatie",
    "sg:phone":"+31 172 471 202",
    "sg:postcode":"2405 BN",
    "sg:province":"Zuid-Holland",
    "wof:name":"Introvision",
    "wof:placetype":"venue"
},
  "geometry": {"coordinates":[4.660773,52.125572],"type":"Point"}
}