{
  "type": "Feature",
  "properties": {
    "addr:full":"Eksterstr 2 Rotterdam Zuid-Holland 3083 XB",
    "addr:housenumber":"2",
    "addr:postcode":"3083 xb",
    "addr:street":"Eksterstr",
    "iso:country":"NL",
    "sg:address":"Eksterstr 2",
    "sg:city":"Rotterdam",
    "sg:orig_category":"Kappers",
    "sg:phone":"+31 10 481 6270",
    "sg:postcode":"3083 XB",
    "sg:province":"Zuid-Holland",
    "wof:name":"Tsang, H S",
    "wof:placetype":"venue"
},
  "geometry": {"coordinates":[4.474269,51.889809],"type":"Point"}
}