{
  "type": "Feature",
  "properties": {
    "addr:full":"Pauwtjesmolen 34 Hardinxveld Giessend Zuid-Holland 3371 RM",
    "addr:housenumber":"34;giessend",
    "addr:postcode":"3371 rm",
    "addr:street":"Pauwtjesmolen",
    "iso:country":"NL",
    "sg:address":"Pauwtjesmolen 34",
    "sg:city":"Hardinxveld Giessend",
    "sg:orig_category":"Loodgieterswerk, Verwarming And Sanitaire Installaties",
    "sg:phone":"+31 184 612 136",
    "sg:postcode":"3371 RM",
    "sg:province":"Zuid-Holland",
    "wof:name":"S. Timmermans",
    "wof:placetype":"venue"
},
  "geometry": {"coordinates":[4.842125,51.829224],"type":"Point"}
}