{
  "type": "Feature",
  "properties": {
    "iso:country":"NL",
    "sg:address":"Asterstraat 1",
    "sg:city":"Oss",
    "sg:orig_category":"Verlichting And Huishoudartikelen",
    "sg:phone":"+31 412 637 191",
    "sg:postcode":"5342 BL",
    "sg:province":"Virginia",
    "wof:name":"Van Happen Design",
    "wof:placetype":"venue"
},
  "geometry": {"coordinates":[-77.235214,38.312599],"type":"Point"}
}