{
  "type": "Feature",
  "properties": {
    "iso:country":"NL",
    "sg:address":"Korianderhof 251",
    "sg:city":"Wierden",
    "sg:orig_category":"Verzekeringen - Verzekeringskantoren",
    "sg:phone":"+31 546 574 346",
    "sg:postcode":"7641 XN",
    "sg:province":"Overijssel",
    "wof:name":"Hollegien",
    "wof:placetype":"venue"
},
  "geometry": {"coordinates":[6.608609,52.361565],"type":"Point"}
}