{
  "type": "Feature",
  "properties": {
    "addr:full":"Conradhof 12 Tilburg Noord-Brabant 5025 DV",
    "addr:housenumber":"12",
    "addr:postcode":"5025 dv",
    "addr:street":"Conradhof",
    "iso:country":"NL",
    "sg:address":"Conradhof 12",
    "sg:city":"Tilburg",
    "sg:orig_category":"Licentiebemiddeling",
    "sg:phone":"+31 13 544 4975",
    "sg:postcode":"5025 DV",
    "sg:province":"Noord-Brabant",
    "wof:name":"Hcc",
    "wof:placetype":"venue"
},
  "geometry": {"coordinates":[5.074472,51.549667],"type":"Point"}
}