{
  "type": "Feature",
  "properties": {
    "iso:country":"NL",
    "sg:address":"Molentocht 1",
    "sg:city":"Linschoten",
    "sg:orig_category":"Adviesbureaus Bedrijfsorganisatie",
    "sg:phone":"+31 348 425 679",
    "sg:postcode":"3461 JD",
    "sg:province":"Utrecht",
    "wof:name":"Echtelt, Van",
    "wof:placetype":"venue"
},
  "geometry": {"coordinates":[4.919374,52.066597],"type":"Point"}
}