{
  "type": "Feature",
  "properties": {
    "addr:full":"Oude Vlissingseweg 40 Middelburg Zeeland 4336 AE",
    "addr:housenumber":"40",
    "addr:postcode":"4336 ae",
    "addr:street":"Oude Vlissingseweg",
    "iso:country":"NL",
    "sg:address":"Oude Vlissingseweg 40",
    "sg:city":"Middelburg",
    "sg:classifiers":[
        {
            "category":"Education",
            "subcategory":"Preschool",
            "type":"Public Place"
        }
    ],
    "sg:phone":"+31 118 611 633",
    "sg:postcode":"4336 AE",
    "sg:province":"Zeeland",
    "sg:tags":[
        "kleuteronderwijs",
        "basis-"
    ],
    "wof:name":"Openbare Basisschool De Leeuwenburch",
    "wof:placetype":"venue"
},
  "geometry": {"coordinates":[3.610943,51.486973],"type":"Point"}
}