{
  "type": "Feature",
  "properties": {
    "addr:full":"Zuiddijk 9 Maassluis South Holland 3143 AS",
    "addr:housenumber":"9",
    "addr:postcode":"3143 as",
    "addr:street":"Zuiddijk",
    "iso:country":"NL",
    "sg:address":"Zuiddijk 9",
    "sg:city":"Maassluis",
    "sg:orig_category":"Kappers",
    "sg:phone":"+31 10 591 0259",
    "sg:postcode":"3143 AS",
    "sg:province":"South Holland",
    "wof:name":"Kapper Don Sauna Zonnebank",
    "wof:placetype":"venue"
},
  "geometry": {"coordinates":[4.2543301582,51.9210548401],"type":"Point"}
}