{
  "type": "Feature",
  "properties": {
    "iso:country":"NL",
    "sg:address":"Ravehorst 14",
    "sg:city":"Honselersdyk",
    "sg:orig_category":"Adviesbureaus Elektrotechniek",
    "sg:phone":"+31 174 620 706",
    "sg:postcode":"2675 WH",
    "sg:province":"Zuid-Holland",
    "wof:name":"Bontek Bv",
    "wof:placetype":"venue"
},
  "geometry": {"coordinates":[4.229989,52.003601],"type":"Point"}
}