{
  "type": "Feature",
  "properties": {
    "addr:full":"Kennedylaan 4 Veghel North Brabant 5466 AA",
    "addr:housenumber":"4",
    "addr:postcode":"5466 aa",
    "addr:street":"Kennedylaan",
    "iso:country":"NL",
    "sg:address":"Kennedylaan 4",
    "sg:city":"Veghel",
    "sg:classifiers":[
        {
            "category":"Fast Food",
            "type":"Food & Drink"
        }
    ],
    "sg:phone":"+31 413 352 858",
    "sg:postcode":"5466 AA",
    "sg:province":"North Brabant",
    "sg:tags":[
        "afhaal",
        "restaurant"
    ],
    "wof:name":"Mcdonald'S Restaurant",
    "wof:placetype":"venue"
},
  "geometry": {"coordinates":[5.524768,51.605171],"type":"Point"}
}