{
  "type": "Feature",
  "properties": {
    "iso:country":"NL",
    "sg:address":"C.Storkstraat 2",
    "sg:city":"Zwolle (Ov)",
    "sg:orig_category":"Bloemen And Planten",
    "sg:phone":"+31 38 467 0050",
    "sg:postcode":"8013 NT",
    "sg:province":"NL.08",
    "wof:name":"Tuincentrum Intratuin",
    "wof:placetype":"venue"
},
  "geometry": {"coordinates":[6.117236,52.49675],"type":"Point"}
}