{
  "type": "Feature",
  "properties": {
    "iso:country":"NL",
    "sg:address":"Veerstr 5",
    "sg:city":"Wageningen",
    "sg:orig_category":"Cafetaria'S",
    "sg:phone":"+31 317 424 101",
    "sg:postcode":"6703 CA",
    "sg:province":"Gelderland",
    "wof:name":"Jeruzalem",
    "wof:placetype":"venue"
},
  "geometry": {"coordinates":[5.668235,51.967052],"type":"Point"}
}