{
  "type": "Feature",
  "properties": {
    "addr:full":"Kuikhornsterweg 72 Zwaagwesteinde Provincie Friesland 9271 HD",
    "addr:housenumber":"72",
    "addr:postcode":"9271 hd",
    "addr:street":"Kuikhornsterweg;Provincie Friesland",
    "iso:country":"NL",
    "sg:address":"Kuikhornsterweg 72",
    "sg:city":"Zwaagwesteinde",
    "sg:orig_category":"Huisdierenfokkers",
    "sg:phone":"+31 511 442 500",
    "sg:postcode":"9271 HD",
    "sg:province":"Provincie Friesland",
    "wof:name":"Kennel Van Kuikhorne",
    "wof:placetype":"venue"
},
  "geometry": {"coordinates":[6.024928,53.242844],"type":"Point"}
}