{
  "type": "Feature",
  "properties": {
    "iso:country":"NL",
    "sg:address":"Dorpstr 38",
    "sg:city":"Ulestraten",
    "sg:orig_category":"Beeldende Kunstenaars",
    "sg:phone":"+31 43 362 0236",
    "sg:postcode":"6235 AD",
    "sg:province":"Limburg",
    "wof:name":"Rijs, P W",
    "wof:placetype":"venue"
},
  "geometry": {"coordinates":[5.787293,50.904522],"type":"Point"}
}