{
  "type": "Feature",
  "properties": {
    "addr:full":"Gen Bothastraat 7K Eindhoven Noord-Brabant 5642 NJ",
    "addr:housenumber":"7k",
    "addr:postcode":"5642 nj",
    "addr:street":"Gen Bothastraat",
    "iso:country":"NL",
    "sg:address":"Gen Bothastraat 7K",
    "sg:city":"Eindhoven",
    "sg:orig_category":"Binnenhuisarchitecten",
    "sg:phone":"+31 40 290 8588",
    "sg:postcode":"5642 NJ",
    "sg:province":"Noord-Brabant",
    "wof:name":"Buro Bas Vormgevers",
    "wof:placetype":"venue"
},
  "geometry": {"coordinates":[5.515867,51.442661],"type":"Point"}
}