{
  "type": "Feature",
  "properties": {
    "addr:full":"Meidoornlaan 1 Vlissingen Zeeland 4382 TJ",
    "addr:housenumber":"1",
    "addr:postcode":"4382 tj",
    "addr:street":"Meidoornlaan",
    "iso:country":"NL",
    "sg:address":"Meidoornlaan 1",
    "sg:city":"Vlissingen",
    "sg:orig_category":"Fotostudio'S And Fotografen",
    "sg:phone":"+31 118 418 239",
    "sg:postcode":"4382 TJ",
    "sg:province":"Zeeland",
    "wof:name":"Foto Hofman",
    "wof:placetype":"venue"
},
  "geometry": {"coordinates":[3.577181,51.451984],"type":"Point"}
}