{
  "type": "Feature",
  "properties": {
    "addr:full":"Kampsedk 1 Enspyk Gelderland 4157 GK",
    "addr:housenumber":"1",
    "addr:postcode":"4157 gk",
    "addr:street":"Kampsedk;Gelderland",
    "iso:country":"NL",
    "sg:address":"Kampsedk 1",
    "sg:city":"Enspyk",
    "sg:orig_category":"Meubelen - Fabrieken En Groothandel",
    "sg:phone":"+31 345 652 430",
    "sg:postcode":"4157 GK",
    "sg:province":"Gelderland",
    "wof:name":"Opus",
    "wof:placetype":"venue"
},
  "geometry": {"coordinates":[5.218968,51.885536],"type":"Point"}
}