{
  "type": "Feature",
  "properties": {
    "addr:full":"Dorpsstr 30 Bergschenhoek South Holland 2661 CG",
    "addr:housenumber":"30",
    "addr:postcode":"2661 cg",
    "addr:street":"Dorpsstr",
    "iso:country":"NL",
    "sg:address":"Dorpsstr 30",
    "sg:city":"Bergschenhoek",
    "sg:orig_category":"Cafetaria'S",
    "sg:phone":"+31 10 521 2461",
    "sg:postcode":"2661 CG",
    "sg:province":"South Holland",
    "wof:name":"Smulhoek, De",
    "wof:placetype":"venue"
},
  "geometry": {"coordinates":[4.500271,51.989071],"type":"Point"}
}