{
  "type": "Feature",
  "properties": {
    "iso:country":"NL",
    "sg:address":"Blekerstr 30",
    "sg:city":"Groningen",
    "sg:orig_category":"Onderhoudswerken",
    "sg:phone":"+31 6 20619333",
    "sg:postcode":"9718 EC",
    "sg:province":"Groningen",
    "wof:name":"Hilboesen & Hovenkamp",
    "wof:placetype":"venue"
},
  "geometry": {"coordinates":[6.555943,53.21611],"type":"Point"}
}