{
  "type": "Feature",
  "properties": {
    "addr:full":"Langstraat 54 Schimmert Limburg 6333 CG",
    "addr:housenumber":"54",
    "addr:postcode":"6333 cg",
    "addr:street":"Langstraat",
    "iso:country":"NL",
    "sg:address":"Langstraat 54",
    "sg:city":"Schimmert",
    "sg:orig_category":"Bloemen And Planten",
    "sg:phone":"+31 45 404 1418",
    "sg:postcode":"6333 CG",
    "sg:province":"Limburg",
    "wof:name":"Bloemenhandel Ed Houtvast",
    "wof:placetype":"venue"
},
  "geometry": {"coordinates":[5.818959,50.908138],"type":"Point"}
}