{
  "type": "Feature",
  "properties": {
    "iso:country":"NL",
    "sg:address":"Ringlaan 8",
    "sg:city":"Nieuw Amsterdam",
    "sg:classifiers":[
        {
            "category":"Education",
            "subcategory":"Preschool",
            "type":"Public Place"
        }
    ],
    "sg:phone":"+31 591 552 042",
    "sg:postcode":"7833 CD",
    "sg:province":"New York",
    "sg:tags":[
        "kleuteronderwijs",
        "basis-"
    ],
    "wof:name":"Openbare Basisschool De Wenke",
    "wof:placetype":"venue"
},
  "geometry": {"coordinates":[-74.163521,42.945232],"type":"Point"}
}