{
  "type": "Feature",
  "properties": {
    "iso:country":"NL",
    "sg:address":"Molenstraat 12",
    "sg:city":"Goor",
    "sg:orig_category":"Verlichting And Huishoudartikelen",
    "sg:phone":"+31 547 272 173",
    "sg:postcode":"7471 CL",
    "sg:province":"NL.08",
    "wof:name":"Firma Lamers",
    "wof:placetype":"venue"
},
  "geometry": {"coordinates":[6.587932,52.2369],"type":"Point"}
}