{
  "type": "Feature",
  "properties": {
    "iso:country":"NL",
    "sg:address":"Vd Kunstr 21B",
    "sg:city":"S Gravenhage",
    "sg:orig_category":"Keukens",
    "sg:phone":"+31 70 388 9858",
    "sg:postcode":"2521 BA",
    "sg:province":"Zuid-Holland",
    "wof:name":"Top",
    "wof:placetype":"venue"
},
  "geometry": {"coordinates":[4.32071,52.062988],"type":"Point"}
}