{
  "type": "Feature",
  "properties": {
    "iso:country":"NL",
    "sg:address":"Grt Beer 5-17",
    "sg:city":"Hoorn Nh",
    "sg:orig_category":"Bloemen En Planten",
    "sg:phone":"+31 229 238 649",
    "sg:postcode":"1622 ES",
    "sg:province":"Noord-Holland",
    "wof:name":"Groene Paradijs, Het",
    "wof:placetype":"venue"
},
  "geometry": {"coordinates":[5.03707,52.63929],"type":"Point"}
}