{
  "type": "Feature",
  "properties": {
    "addr:full":"De Molen 17 Houten Utrecht 3994 DA",
    "addr:housenumber":"17",
    "addr:postcode":"3994 da",
    "addr:street":"De Molen",
    "iso:country":"NL",
    "sg:address":"De Molen 17",
    "sg:city":"Houten",
    "sg:orig_category":"Arbo- En Bedrijfsgezondheids- Diensten",
    "sg:phone":"+31 30 634 0099",
    "sg:postcode":"3994 DA",
    "sg:province":"Utrecht",
    "sg:website":"http://www.asbl.nu",
    "wof:name":"Peters & Du Boeuff Bv",
    "wof:placetype":"venue"
},
  "geometry": {"coordinates":[5.176697,52.029087],"type":"Point"}
}