{
  "type": "Feature",
  "properties": {
    "iso:country":"NL",
    "sg:address":"Fanfarestraat 17",
    "sg:city":"'S Gravenhage",
    "sg:orig_category":"Loodgieterswerk, Verwarming And Sanitaire Installaties",
    "sg:phone":"+31 70 397 9885",
    "sg:postcode":"2553 VT",
    "sg:province":"South Holland",
    "wof:name":"Timmer- En Onderhoudsbedrijf E.R. Koolho",
    "wof:placetype":"venue"
},
  "geometry": {"coordinates":[4.230721,52.054207],"type":"Point"}
}