{
  "type": "Feature",
  "properties": {
    "iso:country":"NL",
    "sg:address":"Brink 18",
    "sg:city":"Scheerwolde",
    "sg:orig_category":"Kappers",
    "sg:phone":"+31 521 370 234",
    "sg:postcode":"8371 WH",
    "sg:province":"NL.08",
    "wof:name":"Rieneke",
    "wof:placetype":"venue"
},
  "geometry": {"coordinates":[6.014299,52.757313],"type":"Point"}
}