{
  "type": "Feature",
  "properties": {
    "addr:full":"Slachthuiskade 18 Poeldijk South Holland 2685 LN",
    "addr:housenumber":"18",
    "addr:postcode":"2685 ln",
    "addr:street":"Slachthuiskade",
    "iso:country":"NL",
    "sg:address":"Slachthuiskade 18",
    "sg:city":"Poeldijk",
    "sg:orig_category":"Autokeuringen",
    "sg:phone":"+31 174 244 723",
    "sg:postcode":"2685 LN",
    "sg:province":"South Holland",
    "wof:name":"Garage Bijlsma",
    "wof:placetype":"venue"
},
  "geometry": {"coordinates":[4.210285,52.020981],"type":"Point"}
}