{
  "type": "Feature",
  "properties": {
    "iso:country":"NL",
    "sg:address":"Kerkstraat 105",
    "sg:city":"Noordwijkerhout",
    "sg:orig_category":"Kappers",
    "sg:phone":"+31 252 372 775",
    "sg:postcode":"2211 RG",
    "sg:province":"Zuid-Holland",
    "wof:name":"Kapsalon Flair",
    "wof:placetype":"venue"
},
  "geometry": {"coordinates":[4.4869418144,52.2513160706],"type":"Point"}
}