{
  "type": "Feature",
  "properties": {
    "addr:full":"Sterappelstraat 50 Bunde Limburg 6241 JL",
    "addr:housenumber":"50",
    "addr:postcode":"6241 jl",
    "addr:street":"Sterappelstraat",
    "iso:country":"NL",
    "sg:address":"Sterappelstraat 50",
    "sg:city":"Bunde",
    "sg:orig_category":"Paramedische Behandelingen",
    "sg:phone":"+31 43 364 1291",
    "sg:postcode":"6241 JL",
    "sg:province":"Limburg",
    "wof:name":"Logopedie C.M. Meuris & G.A.M. Sondeijker",
    "wof:placetype":"venue"
},
  "geometry": {"coordinates":[5.724396,50.896187],"type":"Point"}
}