{
  "type": "Feature",
  "properties": {
    "addr:full":"Oude Engelenseweg 31 'S Hertogenbosch Noord-Brabant 5222 AB",
    "addr:housenumber":"31",
    "addr:postcode":"5222 ab",
    "addr:street":"Oude Engelenseweg;' S",
    "iso:country":"NL",
    "sg:address":"Oude Engelenseweg 31",
    "sg:city":"'S Hertogenbosch",
    "sg:orig_category":"Verhuur Audiovisuele Apparatuur",
    "sg:phone":"+31 73 621 0781",
    "sg:postcode":"5222 AB",
    "sg:province":"Noord-Brabant",
    "wof:name":"Luid En Duidelijk",
    "wof:placetype":"venue"
},
  "geometry": {"coordinates":[5.281129,51.701748],"type":"Point"}
}