{
  "type": "Feature",
  "properties": {
    "iso:country":"NL",
    "sg:address":"L Geere 26",
    "sg:city":"Middelburg",
    "sg:orig_category":"Schoenen",
    "sg:phone":"+31 118 650 686",
    "sg:postcode":"4331 LX",
    "sg:province":"Zeeland",
    "wof:name":"Schoenenreus",
    "wof:placetype":"venue"
},
  "geometry": {"coordinates":[3.608489,51.496914],"type":"Point"}
}