{
  "type": "Feature",
  "properties": {
    "iso:country":"NL",
    "sg:address":"Costerusstraat 11",
    "sg:city":"Woerden",
    "sg:orig_category":"Goederenvervoer Over De Weg",
    "sg:phone":"+31 348 416 670",
    "sg:postcode":"3441 AK",
    "sg:province":"Utrecht",
    "wof:name":"Transportbedrijf N.H. De Jonge",
    "wof:placetype":"venue"
},
  "geometry": {"coordinates":[4.880971,52.085644],"type":"Point"}
}