{
  "type": "Feature",
  "properties": {
    "addr:full":"Noorderstraat 283 Sappemeer Groningen 9611 AH",
    "addr:housenumber":"283",
    "addr:postcode":"9611 ah",
    "addr:street":"Noorderstraat",
    "iso:country":"NL",
    "sg:address":"Noorderstraat 283",
    "sg:city":"Sappemeer",
    "sg:orig_category":"Huizensloop And Bouwrijp Maken",
    "sg:phone":"+31 598 392 061",
    "sg:postcode":"9611 AH",
    "sg:province":"Groningen",
    "wof:name":"Aannemersbedrijf R Brondijk Bv",
    "wof:placetype":"venue"
},
  "geometry": {"coordinates":[6.803532,53.164612],"type":"Point"}
}