{
  "type": "Feature",
  "properties": {
    "addr:full":"Bysselsewg 11 Biddinghuizen NL. 8256 RE",
    "addr:housenumber":"11",
    "addr:postcode":"8256",
    "addr:street":"Bysselsewg;Nl.",
    "iso:country":"NL",
    "sg:address":"Bysselsewg 11",
    "sg:city":"Biddinghuizen",
    "sg:orig_category":"Onderhoudswerken",
    "sg:phone":"+31 321 334 041",
    "sg:postcode":"8256 RE",
    "sg:province":"NL.",
    "wof:name":"Boonen, G",
    "wof:placetype":"venue"
},
  "geometry": {"coordinates":[5.753554,52.421154],"type":"Point"}
}