{
  "type": "Feature",
  "properties": {
    "iso:country":"NL",
    "sg:address":"Schoenerweg 32",
    "sg:city":"Maastricht",
    "sg:orig_category":"Papier And Karton Fab",
    "sg:phone":"+31 43 363 3910",
    "sg:postcode":"6222 NX",
    "sg:province":"Limburg",
    "wof:name":"Bv Filtropa",
    "wof:placetype":"venue"
},
  "geometry": {"coordinates":[5.719846,50.878544],"type":"Point"}
}