{
  "type": "Feature",
  "properties": {
    "addr:full":"Nyverheidswg 9 T Harde Gelderland 8084 GV",
    "addr:housenumber":"9 t",
    "addr:postcode":"8084 gv",
    "addr:street":"Nyverheidswg;Harde Gelderland",
    "iso:country":"NL",
    "sg:address":"Nyverheidswg 9",
    "sg:city":"T Harde",
    "sg:orig_category":"Sportverenigingen En Ontspannings- Verenigingen",
    "sg:phone":"+31 525 652 329",
    "sg:postcode":"8084 GV",
    "sg:province":"Gelderland",
    "wof:name":"Harde Tennisclub, 'T",
    "wof:placetype":"venue"
},
  "geometry": {"coordinates":[5.873204,52.419792],"type":"Point"}
}