{
  "type": "Feature",
  "properties": {
    "addr:full":"Sint Josephstraat 23 Tegelen Limburg 5931 CB",
    "addr:housenumber":"23",
    "addr:postcode":"5931 cb",
    "addr:street":"Sint Josephstraat",
    "iso:country":"NL",
    "sg:address":"Sint Josephstraat 23",
    "sg:city":"Tegelen",
    "sg:orig_category":"Goederenvervoer Over De Weg",
    "sg:phone":"+31 77 373 2381",
    "sg:postcode":"5931 CB",
    "sg:province":"Limburg",
    "wof:name":"J.H.H. Brauer",
    "wof:placetype":"venue"
},
  "geometry": {"coordinates":[6.13215,51.341621],"type":"Point"}
}