{
  "type": "Feature",
  "properties": {
    "addr:full":"Dr A F Philipswg 25 Assen Provincie Drenthe 9403 AC",
    "addr:housenumber":"25",
    "addr:postcode":"9403 ac",
    "addr:street":"Dr A F Philipswg;Provincie Drenthe",
    "iso:country":"NL",
    "sg:address":"Dr A F Philipswg 25",
    "sg:city":"Assen",
    "sg:orig_category":"Autoschade- Herstelbedrijven",
    "sg:phone":"+31 592 314 111",
    "sg:postcode":"9403 AC",
    "sg:province":"Provincie Drenthe",
    "wof:name":"Aa",
    "wof:placetype":"venue"
},
  "geometry": {"coordinates":[6.574919,52.998718],"type":"Point"}
}