{
  "type": "Feature",
  "properties": {
    "iso:country":"NL",
    "sg:address":"Spoorstraat 16",
    "sg:city":"Varsseveld",
    "sg:orig_category":"Bruidskleding",
    "sg:phone":"+31 315 241 307",
    "sg:postcode":"7051 CJ",
    "sg:province":"Gelderland",
    "wof:name":"Heezen Mannenmode",
    "wof:placetype":"venue"
},
  "geometry": {"coordinates":[6.461424,51.942734],"type":"Point"}
}