{
  "type": "Feature",
  "properties": {
    "addr:full":"Meerweg 11 Haren Gn Groningen 9752 JA",
    "addr:housenumber":"11",
    "addr:postcode":"9752 ja",
    "addr:street":"Meerweg",
    "iso:country":"NL",
    "sg:address":"Meerweg 11",
    "sg:city":"Haren Gn",
    "sg:orig_category":"Opticiens",
    "sg:phone":"+31 50 534 4082",
    "sg:postcode":"9752 JA",
    "sg:province":"Groningen",
    "wof:name":"Ouwerkerk Optiek",
    "wof:placetype":"venue"
},
  "geometry": {"coordinates":[6.6020112038,53.1727905273],"type":"Point"}
}