{
  "type": "Feature",
  "properties": {
    "addr:full":"Techniekweg 28 Utrecht Utrecht 3542 DT",
    "addr:housenumber":"28",
    "addr:postcode":"3542 dt",
    "addr:street":"Techniekweg",
    "iso:country":"NL",
    "sg:address":"Techniekweg 28",
    "sg:city":"Utrecht",
    "sg:orig_category":"Schilderwerk",
    "sg:phone":"+31 30 280 2828",
    "sg:postcode":"3542 DT",
    "sg:province":"Utrecht",
    "wof:name":"Recon Schilderwerken Bv",
    "wof:placetype":"venue"
},
  "geometry": {"coordinates":[5.045781,52.126503],"type":"Point"}
}