{
  "type": "Feature",
  "properties": {
    "addr:full":"Stationspln 11 Arnhem Gelderland 6811 KG",
    "addr:housenumber":"11",
    "addr:postcode":"6811 kg",
    "addr:street":"Stationspln",
    "iso:country":"NL",
    "sg:address":"Stationspln 11",
    "sg:city":"Arnhem",
    "sg:orig_category":"Verenigingen En Stichtingen",
    "sg:phone":"+31 26 442 6740",
    "sg:postcode":"6811 KG",
    "sg:province":"Gelderland",
    "wof:name":"Plattelandsjongeren Gelderland",
    "wof:placetype":"venue"
},
  "geometry": {"coordinates":[5.901485,51.983303],"type":"Point"}
}