{
  "type": "Feature",
  "properties": {
    "iso:country":"NL",
    "sg:address":"Berglaan 64",
    "sg:city":"Drachten",
    "sg:orig_category":"Verzekeringen",
    "sg:phone":"+31 512 524 014",
    "sg:postcode":"9203 EJ",
    "sg:province":"Provincie Friesland",
    "wof:name":"Ctb Assurantien Bv",
    "wof:placetype":"venue"
},
  "geometry": {"coordinates":[6.10876,53.10397],"type":"Point"}
}