{
  "type": "Feature",
  "properties": {
    "addr:full":"Hoogeinde 3 Tiel Gelderland 4001 BH",
    "addr:housenumber":"3",
    "addr:postcode":"4001 bh",
    "addr:street":"Hoogeinde;Gelderland",
    "iso:country":"NL",
    "sg:address":"Hoogeinde 3",
    "sg:city":"Tiel",
    "sg:orig_category":"Kappers",
    "sg:phone":"+31 344 613 524",
    "sg:postcode":"4001 BH",
    "sg:province":"Gelderland",
    "wof:name":"Kapsalon Van Zwam",
    "wof:placetype":"venue"
},
  "geometry": {"coordinates":[5.4306960106,51.8880958557],"type":"Point"}
}