{
  "type": "Feature",
  "properties": {
    "addr:full":"Rubensplein 21 C Schiedam Zuid-Holland 3116 BP",
    "addr:housenumber":"21 c",
    "addr:postcode":"3116 bp",
    "addr:street":"Rubensplein",
    "iso:country":"NL",
    "sg:address":"Rubensplein 21 C",
    "sg:city":"Schiedam",
    "sg:classifiers":[
        {
            "category":"Fast Food",
            "type":"Food & Drink"
        }
    ],
    "sg:phone":"+31 10 473 6183",
    "sg:postcode":"3116 BP",
    "sg:province":"Zuid-Holland",
    "sg:tags":[
        "afhaal",
        "restaurant"
    ],
    "wof:name":"Taria De Leede",
    "wof:placetype":"venue"
},
  "geometry": {"coordinates":[4.382944,51.911278],"type":"Point"}
}