{
  "type": "Feature",
  "properties": {
    "addr:full":"Daslook 2 Venray Limburg 5803 CH",
    "addr:housenumber":"2",
    "addr:postcode":"5803",
    "addr:street":"Daslook",
    "iso:country":"NL",
    "sg:address":"Daslook 2",
    "sg:city":"Venray",
    "sg:classifiers":[
        {
            "category":"Arena",
            "subcategory":"Auto Racetrack",
            "type":"Entertainment"
        }
    ],
    "sg:phone":"+31 478 586 155",
    "sg:postcode":"5803 CH",
    "sg:province":"Limburg",
    "sg:tags":[
        "en",
        "racebanen",
        "kart-"
    ],
    "wof:name":"Kart Express",
    "wof:placetype":"venue"
},
  "geometry": {"coordinates":[5.987087,51.532139],"type":"Point"}
}