{
  "type": "Feature",
  "properties": {
    "addr:full":"Hoornbloem 1 Apeldoorn Gelderland 7322 AN",
    "addr:housenumber":"1",
    "addr:postcode":"7322 an",
    "addr:street":"Hoornbloem;Gelderland",
    "iso:country":"NL",
    "sg:address":"Hoornbloem 1",
    "sg:city":"Apeldoorn",
    "sg:orig_category":"Bedrijfs- And Managementsconsultants",
    "sg:phone":"+31 55 366 4877",
    "sg:postcode":"7322 AN",
    "sg:province":"Gelderland",
    "wof:name":"A.J. Grefhorst Management Ondersteuning",
    "wof:placetype":"venue"
},
  "geometry": {"coordinates":[5.976078,52.222996],"type":"Point"}
}