{
  "type": "Feature",
  "properties": {
    "addr:full":"Enterstraat 212 Rijssen Overijssel 7461 PE",
    "addr:housenumber":"212",
    "addr:postcode":"7461 pe",
    "addr:street":"Enterstraat",
    "iso:country":"NL",
    "sg:address":"Enterstraat 212",
    "sg:city":"Rijssen",
    "sg:orig_category":"Goederenvervoer Over De Weg",
    "sg:phone":"+31 548 518 787",
    "sg:postcode":"7461 PE",
    "sg:province":"Overijssel",
    "wof:name":"Dekker Transport Vof",
    "wof:placetype":"venue"
},
  "geometry": {"coordinates":[6.54931,52.296066],"type":"Point"}
}