{
  "type": "Feature",
  "properties": {
    "iso:country":"NL",
    "sg:address":"Columbusstraat 282",
    "sg:city":"'S Gravenhage",
    "sg:orig_category":"Fitnesscentra",
    "sg:phone":"+31 70 310 6826",
    "sg:postcode":"2561 AX",
    "sg:province":"Zuid-Holland",
    "wof:name":"Arts Keumgang Martial",
    "wof:placetype":"venue"
},
  "geometry": {"coordinates":[4.274582,52.076431],"type":"Point"}
}