{
  "type": "Feature",
  "properties": {
    "iso:country":"NL",
    "sg:address":"Boomgaardwg 4",
    "sg:city":"Middelharnis",
    "sg:orig_category":"Loonbedrijven",
    "sg:phone":"+31 187 483 886",
    "sg:postcode":"3241 LA",
    "sg:province":"South Holland",
    "wof:name":"Peeman & Znn, Firma L",
    "wof:placetype":"venue"
},
  "geometry": {"coordinates":[4.173875,51.749683],"type":"Point"}
}