{
  "type": "Feature",
  "properties": {
    "addr:full":"Het Klooster 12 Deventer NL.08 7411 NH",
    "addr:housenumber":"12;nl.08",
    "addr:postcode":"7411 nh",
    "addr:street":"Het Klooster",
    "iso:country":"NL",
    "sg:address":"Het Klooster 12",
    "sg:city":"Deventer",
    "sg:orig_category":"Bibliotheken And Openbare Archieven",
    "sg:phone":"+31 570 693 887",
    "sg:postcode":"7411 NH",
    "sg:province":"NL.08",
    "wof:name":"Stads- Of Athenaeumbibliotheek",
    "wof:placetype":"venue"
},
  "geometry": {"coordinates":[6.152542,52.253365],"type":"Point"}
}