{
  "type": "Feature",
  "properties": {
    "addr:full":"Jan Evertsenstraat 102 Amsterdam Noord-Holland 1056 EH",
    "addr:housenumber":"102",
    "addr:postcode":"1056 eh",
    "addr:street":"Jan Evertsenstraat",
    "iso:country":"NL",
    "sg:address":"Jan Evertsenstraat 102",
    "sg:city":"Amsterdam",
    "sg:orig_category":"Herenmodezaken",
    "sg:phone":"+31 20 612 9592",
    "sg:postcode":"1056 EH",
    "sg:province":"Noord-Holland",
    "wof:name":"Hans Herenconfectie Bv",
    "wof:placetype":"venue"
},
  "geometry": {"coordinates":[4.853045,52.370735],"type":"Point"}
}