{
  "type": "Feature",
  "properties": {
    "addr:full":"Venraysewg 208H Venlo Limburg 5928 RJ",
    "addr:housenumber":"208h",
    "addr:postcode":"5928 rj",
    "addr:street":"Venraysewg",
    "iso:country":"NL",
    "sg:address":"Venraysewg 208H",
    "sg:city":"Venlo",
    "sg:orig_category":"Bloemen En Planten - Groothandel",
    "sg:phone":"+31 77 396 9590",
    "sg:postcode":"5928 RJ",
    "sg:province":"Limburg",
    "wof:name":"Nicky Fleur",
    "wof:placetype":"venue"
},
  "geometry": {"coordinates":[6.152722,51.376091],"type":"Point"}
}