{
  "type": "Feature",
  "properties": {
    "addr:full":"S Gravelandsewg 248 Schiedam Zuid-Holland 3125 BK",
    "addr:housenumber":"248",
    "addr:postcode":"3125 bk",
    "iso:country":"NL",
    "sg:address":"S Gravelandsewg 248",
    "sg:city":"Schiedam",
    "sg:orig_category":"Kantoor- En Bedrijfsmeubelen",
    "sg:phone":"+31 10 470 2611",
    "sg:postcode":"3125 BK",
    "sg:province":"Zuid-Holland",
    "sg:website":"http://www.backshop.nl",
    "wof:name":"Backshop C & G",
    "wof:placetype":"venue"
},
  "geometry": {"coordinates":[4.3981528282,51.9354858398],"type":"Point"}
}