{
  "type": "Feature",
  "properties": {
    "addr:full":"Dopperstraat 22 Bunschoten Spakenburg Utrecht 3752 JG",
    "addr:housenumber":"22",
    "addr:postcode":"3752 jg",
    "addr:street":"Dopperstraat",
    "iso:country":"NL",
    "sg:address":"Dopperstraat 22",
    "sg:city":"Bunschoten Spakenburg",
    "sg:orig_category":"Goederenvervoer Over De Weg",
    "sg:phone":"+31 33 298 2709",
    "sg:postcode":"3752 JG",
    "sg:province":"Utrecht",
    "wof:name":"J. Malestein",
    "wof:placetype":"venue"
},
  "geometry": {"coordinates":[5.370602,52.244522],"type":"Point"}
}