{
  "type": "Feature",
  "properties": {
    "addr:full":"Schietbaan 9 Delden NL.08 7491 HC",
    "addr:housenumber":"9;nl.08",
    "addr:postcode":"7491 hc",
    "addr:street":"Schietbaan",
    "iso:country":"NL",
    "sg:address":"Schietbaan 9",
    "sg:city":"Delden",
    "sg:orig_category":"Administratie- En Boekhoudkantoren",
    "sg:phone":"+31 74 376 2890",
    "sg:postcode":"7491 HC",
    "sg:province":"NL.08",
    "wof:name":"Blekkenhorst",
    "wof:placetype":"venue"
},
  "geometry": {"coordinates":[6.698787,52.258488],"type":"Point"}
}