{
  "type": "Feature",
  "properties": {
    "iso:country":"NL",
    "sg:address":"Amsteldk 32",
    "sg:city":"Amsterdam",
    "sg:orig_category":"Psychotherapeuten",
    "sg:phone":"+31 20 673 9976",
    "sg:postcode":"1074 HT",
    "sg:province":"Noord-Holland",
    "wof:name":"Rientsma, Drs M C",
    "wof:placetype":"venue"
},
  "geometry": {"coordinates":[4.904652,52.356213],"type":"Point"}
}