{
  "type": "Feature",
  "properties": {
    "addr:full":"Rijksstraatweg 243 Hellevoetsluis Zuid-Holland 3222 KD",
    "addr:housenumber":"243",
    "addr:postcode":"3222 kd",
    "addr:street":"Rijksstraatweg",
    "iso:country":"NL",
    "sg:address":"Rijksstraatweg 243",
    "sg:city":"Hellevoetsluis",
    "sg:orig_category":"Technische Studies And Onderzoek",
    "sg:phone":"+31 181 322 877",
    "sg:postcode":"3222 KD",
    "sg:province":"Zuid-Holland",
    "wof:name":"Jahn Ingenieursbureau Bv",
    "wof:placetype":"venue"
},
  "geometry": {"coordinates":[4.14027,51.853889],"type":"Point"}
}