{
  "type": "Feature",
  "properties": {
    "addr:full":"Muiderstraatweg 58B Diemen Noord-Holland 1111 PT",
    "addr:housenumber":"58b",
    "addr:postcode":"1111 pt",
    "addr:street":"Muiderstraatweg",
    "iso:country":"NL",
    "sg:address":"Muiderstraatweg 58B",
    "sg:city":"Diemen",
    "sg:orig_category":"Makelaars In Onroerend Goed",
    "sg:phone":"+31 20 695 8485",
    "sg:postcode":"1111 PT",
    "sg:province":"Noord-Holland",
    "wof:name":"J. De Jager",
    "wof:placetype":"venue"
},
  "geometry": {"coordinates":[4.967607,52.337181],"type":"Point"}
}