{
  "type": "Feature",
  "properties": {
    "addr:full":"Domela Nieuwenhuisweg 6 Dordrecht Zuid-Holland 3317 SE",
    "addr:housenumber":"6",
    "addr:postcode":"3317 se",
    "addr:street":"Domela Nieuwenhuisweg",
    "iso:country":"NL",
    "sg:address":"Domela Nieuwenhuisweg 6",
    "sg:city":"Dordrecht",
    "sg:orig_category":"Fitnesscentra",
    "sg:phone":"+31 78 610 5354",
    "sg:postcode":"3317 SE",
    "sg:province":"Zuid-Holland",
    "wof:name":"Budo Instituut Weeland",
    "wof:placetype":"venue"
},
  "geometry": {"coordinates":[4.665488,51.786591],"type":"Point"}
}