{
  "type": "Feature",
  "properties": {
    "addr:full":"Arnhemsewg 7 Zevenaar Gelderland 6901 DS",
    "addr:housenumber":"7",
    "addr:postcode":"6901 ds",
    "addr:street":"Arnhemsewg",
    "iso:country":"NL",
    "sg:address":"Arnhemsewg 7",
    "sg:city":"Zevenaar",
    "sg:orig_category":"Verzekeringen - Verzekeringskantoren",
    "sg:phone":"+31 316 528 965",
    "sg:postcode":"6901 DS",
    "sg:province":"Gelderland",
    "wof:name":"Mee\u00f9s",
    "wof:placetype":"venue"
},
  "geometry": {"coordinates":[6.073769,51.928516],"type":"Point"}
}