{
  "type": "Feature",
  "properties": {
    "addr:full":"Ceramstr 6 Groningen Groningen 9715 JN",
    "addr:housenumber":"6",
    "addr:postcode":"9715 jn",
    "addr:street":"Ceramstr",
    "iso:country":"NL",
    "sg:address":"Ceramstr 6",
    "sg:city":"Groningen",
    "sg:orig_category":"Schilders",
    "sg:phone":"+31 50 577 6444",
    "sg:postcode":"9715 JN",
    "sg:province":"Groningen",
    "wof:name":"Alfa",
    "wof:placetype":"venue"
},
  "geometry": {"coordinates":[6.572914,53.232555],"type":"Point"}
}