{
  "type": "Feature",
  "properties": {
    "addr:full":"Lage Markt 5 Nijmegen Gelderland 6511 VK",
    "addr:housenumber":"5",
    "addr:postcode":"6511 vk",
    "addr:street":"Lage Markt;Gelderland",
    "iso:country":"NL",
    "sg:address":"Lage Markt 5",
    "sg:city":"Nijmegen",
    "sg:orig_category":"Fotostudio'S And Fotografen",
    "sg:phone":"+31 24 360 2312",
    "sg:postcode":"6511 VK",
    "sg:province":"Gelderland",
    "wof:name":"Pennings Photodesign",
    "wof:placetype":"venue"
},
  "geometry": {"coordinates":[5.862066,51.849613],"type":"Point"}
}