{
  "type": "Feature",
  "properties": {
    "addr:full":"J Ryksenstr 148 Almere Flevoland 1335 NX",
    "addr:housenumber":"148",
    "addr:postcode":"1335 nx",
    "addr:street":"Flevoland",
    "iso:country":"NL",
    "sg:address":"J Ryksenstr 148",
    "sg:city":"Almere",
    "sg:orig_category":"Wintersportkleding En -Artikelen",
    "sg:phone":"+31 6 54677293",
    "sg:postcode":"1335 NX",
    "sg:province":"Flevoland",
    "sg:website":"http://www.d-spot.nl",
    "wof:name":"D-Spot",
    "wof:placetype":"venue"
},
  "geometry": {"coordinates":[5.2922468185,52.406337738],"type":"Point"}
}