{
  "type": "Feature",
  "properties": {
    "iso:country":"NL",
    "sg:address":"Brouwersstr 102",
    "sg:city":"Haarlem",
    "sg:orig_category":"Bloemen En Planten - Decoratie",
    "sg:phone":"+31 23 532 6591",
    "sg:postcode":"2013 WP",
    "sg:province":"Noord-Holland",
    "wof:name":"Fleur 2000",
    "wof:placetype":"venue"
},
  "geometry": {"coordinates":[4.620275,52.379765],"type":"Point"}
}