{
  "type": "Feature",
  "properties": {
    "addr:full":"Bosstraat 91 Swalmen Limburg 6071 XT",
    "addr:housenumber":"91",
    "addr:postcode":"6071 xt",
    "addr:street":"Bosstraat",
    "iso:country":"NL",
    "sg:address":"Bosstraat 91",
    "sg:city":"Swalmen",
    "sg:orig_category":"Verlichting And Huishoudartikelen",
    "sg:phone":"+31 475 504 417",
    "sg:postcode":"6071 XT",
    "sg:province":"Limburg",
    "wof:name":"Hodselmans Verlichting S.H.P. Hodselmans",
    "wof:placetype":"venue"
},
  "geometry": {"coordinates":[6.053987,51.236603],"type":"Point"}
}