{
  "type": "Feature",
  "properties": {
    "addr:full":"De Nw Aanleg 22 Diepenveen Overijssel 7431 BR",
    "addr:housenumber":"22",
    "addr:postcode":"7431 br",
    "addr:street":"De Nw Aanleg",
    "iso:country":"NL",
    "sg:address":"De Nw Aanleg 22",
    "sg:city":"Diepenveen",
    "sg:orig_category":"Meubelen - Fabrieken En Groothandel",
    "sg:phone":"+31 570 591 912",
    "sg:postcode":"7431 BR",
    "sg:province":"Overijssel",
    "wof:name":"Sbm",
    "wof:placetype":"venue"
},
  "geometry": {"coordinates":[6.153874,52.290218],"type":"Point"}
}