{
  "type": "Feature",
  "properties": {
    "iso:country":"NL",
    "sg:address":"Roserije 47",
    "sg:city":"Maastricht",
    "sg:classifiers":[
        {
            "category":"Communications",
            "subcategory":"Television Station",
            "type":"Services"
        }
    ],
    "sg:phone":"+31 43 367 1140",
    "sg:postcode":"6228 DH",
    "sg:province":"Limburg",
    "sg:tags":[
        "video",
        "audio",
        "verhuur"
    ],
    "wof:name":"Filmclub Videotheek Videoworld",
    "wof:placetype":"venue"
},
  "geometry": {"coordinates":[5.726001,50.827778],"type":"Point"}
}