{
  "type": "Feature",
  "properties": {
    "addr:full":"Michelsln 17 Someren North Brabant 5712 PL",
    "addr:housenumber":"17",
    "addr:postcode":"5712 pl",
    "addr:street":"Michelsln",
    "iso:country":"NL",
    "sg:address":"Michelsln 17",
    "sg:city":"Someren",
    "sg:orig_category":"Pluimveebedrijven En -Handelaren",
    "sg:phone":"+31 493 493 921",
    "sg:postcode":"5712 PL",
    "sg:province":"North Brabant",
    "wof:name":"Boomen, F C H G Van Den",
    "wof:placetype":"venue"
},
  "geometry": {"coordinates":[5.733936,51.356915],"type":"Point"}
}