{
  "type": "Feature",
  "properties": {
    "addr:full":"Toscaninipad 5 Delft Zuid-Holland 2625 ZG",
    "addr:housenumber":"5",
    "addr:postcode":"2625 zg",
    "addr:street":"Toscaninipad",
    "iso:country":"NL",
    "sg:address":"Toscaninipad 5",
    "sg:city":"Delft",
    "sg:orig_category":"Vertaal- And Tolkenbureaus",
    "sg:phone":"+31 15 251 0827",
    "sg:postcode":"2625 ZG",
    "sg:province":"Zuid-Holland",
    "wof:name":"Cls-Chinese Language Services",
    "wof:placetype":"venue"
},
  "geometry": {"coordinates":[4.338109,51.993675],"type":"Point"}
}