{
  "type": "Feature",
  "properties": {
    "iso:country":"NL",
    "sg:address":"Fransestr 19",
    "sg:city":"Ameide",
    "sg:orig_category":"Bloemen En Planten",
    "sg:phone":"+31 183 600 743",
    "sg:postcode":"4233 EC",
    "sg:province":"Zuid-Holland",
    "wof:name":"Bloem",
    "wof:placetype":"venue"
},
  "geometry": {"coordinates":[4.962639,51.957691],"type":"Point"}
}