{
  "type": "Feature",
  "properties": {
    "addr:full":"Melkbon 59 Enkhuizen Noord-Holland 1602 JD",
    "addr:housenumber":"59",
    "addr:postcode":"1602 jd",
    "addr:street":"Melkbon",
    "iso:country":"NL",
    "sg:address":"Melkbon 59",
    "sg:city":"Enkhuizen",
    "sg:orig_category":"Kantoor- En Secretariaatsservice",
    "sg:phone":"+31 228 325 030",
    "sg:postcode":"1602 JD",
    "sg:province":"Noord-Holland",
    "wof:name":"Molenaar",
    "wof:placetype":"venue"
},
  "geometry": {"coordinates":[5.2631320953,52.710269928],"type":"Point"}
}