{
  "type": "Feature",
  "properties": {
    "addr:full":"Lauwers 2-4 Veendam Groningen 9642 KX",
    "addr:housenumber":"2-4",
    "addr:postcode":"9642 kx",
    "addr:street":"Lauwers",
    "iso:country":"NL",
    "sg:address":"Lauwers 2-4",
    "sg:city":"Veendam",
    "sg:orig_category":"Scholen Voor Basisonderwijs",
    "sg:phone":"+31 598 619 787",
    "sg:postcode":"9642 KX",
    "sg:province":"Groningen",
    "wof:name":"Viermaster, De",
    "wof:placetype":"venue"
},
  "geometry": {"coordinates":[6.85265,53.09293],"type":"Point"}
}