{
  "type": "Feature",
  "properties": {
    "addr:full":"Grunder 299 Amsterdam Zuidoost Noord-Holland 1103 HN",
    "addr:housenumber":"299",
    "addr:postcode":"zuidoost;1103 hn",
    "addr:street":"Grunder",
    "iso:country":"NL",
    "sg:address":"Grunder 299",
    "sg:city":"Amsterdam Zuidoost",
    "sg:orig_category":"Verenigingen En Stichtingen",
    "sg:phone":"+31 20 600 3346",
    "sg:postcode":"1103 HN",
    "sg:province":"Noord-Holland",
    "wof:name":"Sida, Sticht",
    "wof:placetype":"venue"
},
  "geometry": {"coordinates":[4.97467,52.32378],"type":"Point"}
}