{
  "type": "Feature",
  "properties": {
    "iso:country":"NL",
    "sg:address":"De Biezen 21",
    "sg:city":"Ijsselstein Ut",
    "sg:classifiers":[
        {
            "category":"Fast Food",
            "type":"Food & Drink"
        }
    ],
    "sg:phone":"+31 30 687 0263",
    "sg:postcode":"3401 GD",
    "sg:province":"Utrecht",
    "sg:tags":[
        "afhaal",
        "restaurant"
    ],
    "wof:name":"New Ocean City Afhaalcentrum",
    "wof:placetype":"venue"
},
  "geometry": {"coordinates":[5.04266,52.017044],"type":"Point"}
}