{
  "type": "Feature",
  "properties": {
    "addr:full":"Nieuwewg 61E Hoofddorp Noord-Holland 2132 CM",
    "addr:housenumber":"61e",
    "addr:postcode":"2132 cm",
    "addr:street":"Nieuwewg",
    "iso:country":"NL",
    "sg:address":"Nieuwewg 61E",
    "sg:city":"Hoofddorp",
    "sg:orig_category":"Adviesbureaus Bedrijfsorganisatie",
    "sg:phone":"+31 23 562 1534",
    "sg:postcode":"2132 CM",
    "sg:province":"Noord-Holland",
    "wof:name":"Transformatica Bv",
    "wof:placetype":"venue"
},
  "geometry": {"coordinates":[4.696725,52.303028],"type":"Point"}
}