{
  "type": "Feature",
  "properties": {
    "addr:full":"Scheepmakerskade 44 Rotterdam Zuid-Holland 3011 VX",
    "addr:housenumber":"44",
    "addr:postcode":"3011 vx",
    "addr:street":"Scheepmakerskade",
    "iso:country":"NL",
    "sg:address":"Scheepmakerskade 44",
    "sg:city":"Rotterdam",
    "sg:orig_category":"Beautyfarms And Sauna'S",
    "sg:phone":"+31 10 233 1667",
    "sg:postcode":"3011 VX",
    "sg:province":"Zuid-Holland",
    "wof:name":"Les Beautes Du Soleil Zonnebank",
    "wof:placetype":"venue"
},
  "geometry": {"coordinates":[4.484714,51.914616],"type":"Point"}
}