{
  "type": "Feature",
  "properties": {
    "addr:full":"Remmet Van Milplaats 15 Rotterdam Zuid-Holland 3067 AN",
    "addr:housenumber":"15",
    "addr:postcode":"3067 an",
    "addr:street":"Remmet Van Milplaats",
    "iso:country":"NL",
    "sg:address":"Remmet Van Milplaats 15",
    "sg:city":"Rotterdam",
    "sg:orig_category":"Overheidsdiensten",
    "sg:phone":"+31 10 420 5055",
    "sg:postcode":"3067 AN",
    "sg:province":"Zuid-Holland",
    "wof:name":"Buurthuis Alexanderpol",
    "wof:placetype":"venue"
},
  "geometry": {"coordinates":[4.5479078293,51.9404602051],"type":"Point"}
}