{
  "type": "Feature",
  "properties": {
    "addr:full":"M Havelaarln 389 Amstelveen Noord-Holland 1183 LX",
    "addr:housenumber":"389",
    "addr:postcode":"1183 lx",
    "iso:country":"NL",
    "sg:address":"M Havelaarln 389",
    "sg:city":"Amstelveen",
    "sg:classifiers":[
        {
            "category":"Personal",
            "subcategory":"Nail Salon",
            "type":"Services"
        }
    ],
    "sg:phone":"+31 20 641 8890",
    "sg:postcode":"1183 LX",
    "sg:province":"Noord-Holland",
    "sg:tags":[
        "pedicure"
    ],
    "wof:name":"Siem, Debby",
    "wof:placetype":"venue"
},
  "geometry": {"coordinates":[4.856945,52.303444],"type":"Point"}
}