{
  "type": "Feature",
  "properties": {
    "addr:full":"Prinsengr 909 Amsterdam North Holland 1017 KD",
    "addr:housenumber":"909",
    "addr:postcode":"1017 kd",
    "iso:country":"NL",
    "sg:address":"Prinsengr 909",
    "sg:city":"Amsterdam",
    "sg:orig_category":"Vertaalbureaus",
    "sg:phone":"+31 20 624 7635",
    "sg:postcode":"1017 KD",
    "sg:province":"North Holland",
    "wof:name":"Jenny Spits",
    "wof:placetype":"venue"
},
  "geometry": {"coordinates":[4.890986,52.362568],"type":"Point"}
}