{
  "type": "Feature",
  "properties": {
    "addr:full":"Drielandendreef 32 Harderwyk Gelderland 3845 CA",
    "addr:housenumber":"32",
    "addr:postcode":"3845 ca",
    "addr:street":"Drielandendreef;Gelderland",
    "iso:country":"NL",
    "sg:address":"Drielandendreef 32",
    "sg:city":"Harderwyk",
    "sg:orig_category":"Verhuizingen",
    "sg:phone":"+31 341 417 158",
    "sg:postcode":"3845 CA",
    "sg:province":"Gelderland",
    "wof:name":"Groot & Zonen, Firma J De",
    "wof:placetype":"venue"
},
  "geometry": {"coordinates":[-119.270203,37.271832],"type":"Point"}
}