{
  "type": "Feature",
  "properties": {
    "iso:country":"NL",
    "sg:address":"Lange Heul 167",
    "sg:city":"Bussum",
    "sg:orig_category":"Verzekeringen",
    "sg:phone":"+31 35 693 2847",
    "sg:postcode":"1403 NH",
    "sg:province":"Noord-Holland",
    "wof:name":"Assurantie En Adviesbureau Mauritz",
    "wof:placetype":"venue"
},
  "geometry": {"coordinates":[5.169126,52.262295],"type":"Point"}
}