{
  "type": "Feature",
  "properties": {
    "addr:full":"Deijmanstraat 14 Amsterdam Noord-Holland 1091 SE",
    "addr:housenumber":"14;1091",
    "addr:street":"Deijmanstraat;Se",
    "iso:country":"NL",
    "sg:address":"Deijmanstraat 14",
    "sg:city":"Amsterdam",
    "sg:orig_category":"Diverse Consumentenartikelen Gh",
    "sg:phone":"+31 20 668 6622",
    "sg:postcode":"1091 SE",
    "sg:province":"Noord-Holland",
    "wof:name":"Office-Power",
    "wof:placetype":"venue"
},
  "geometry": {"coordinates":[4.91306,52.35487],"type":"Point"}
}