{
  "type": "Feature",
  "properties": {
    "addr:full":"Adelaartlaan 206 Geldrop North Brabant 5665 CS",
    "addr:housenumber":"206",
    "addr:postcode":"5665 cs",
    "addr:street":"Adelaartlaan",
    "iso:country":"NL",
    "sg:address":"Adelaartlaan 206",
    "sg:city":"Geldrop",
    "sg:orig_category":"Paramedische Behandelingen",
    "sg:phone":"+31 40 285 9618",
    "sg:postcode":"5665 CS",
    "sg:province":"North Brabant",
    "wof:name":"W.E. Verschuren-Zomers",
    "wof:placetype":"venue"
},
  "geometry": {"coordinates":[5.571721,51.41655],"type":"Point"}
}