{
  "type": "Feature",
  "properties": {
    "iso:country":"NL",
    "sg:address":"D Collinstr 17",
    "sg:city":"Almere",
    "sg:orig_category":"Adviesbureaus Bouwkunde",
    "sg:phone":"+31 36 545 2820",
    "sg:postcode":"1326 TN",
    "sg:province":"Flevoland",
    "wof:name":"Advies & Tekenburo Bouwtechniek",
    "wof:placetype":"venue"
},
  "geometry": {"coordinates":[5.258183,52.362598],"type":"Point"}
}