{
  "type": "Feature",
  "properties": {
    "addr:full":"Galileiplnts 56 Amsterdam Noord-Holland 1098 NB",
    "addr:housenumber":"56;1098",
    "addr:postcode":"nb",
    "addr:street":"Galileiplnts",
    "iso:country":"NL",
    "sg:address":"Galileiplnts 56",
    "sg:city":"Amsterdam",
    "sg:orig_category":"Adviesbureaus Financieringen",
    "sg:phone":"+31 20 694 0245",
    "sg:postcode":"1098 NB",
    "sg:province":"Noord-Holland",
    "wof:name":"Hansen, J K",
    "wof:placetype":"venue"
},
  "geometry": {"coordinates":[4.94688,52.349209],"type":"Point"}
}