{
  "type": "Feature",
  "properties": {
    "addr:full":"Rosmarynstg 9 Amsterdam North Holland 1012 RP",
    "addr:housenumber":"9",
    "addr:postcode":"1012 rp",
    "addr:street":"Rosmarynstg",
    "iso:country":"NL",
    "sg:address":"Rosmarynstg 9",
    "sg:city":"Amsterdam",
    "sg:orig_category":"Koffie- En Theehuizen",
    "sg:phone":"+31 20 624 7023",
    "sg:postcode":"1012 RP",
    "sg:province":"North Holland",
    "wof:name":"Kadinsky",
    "wof:placetype":"venue"
},
  "geometry": {"coordinates":[4.889805,52.370308],"type":"Point"}
}