{
  "type": "Feature",
  "properties": {
    "addr:full":"Gouwestraat 13 'S Gravenhage South Holland 2515 SM",
    "addr:housenumber":"13",
    "addr:postcode":"2515 sm",
    "addr:street":"Gouwestraat;' S Gravenhage",
    "iso:country":"NL",
    "sg:address":"Gouwestraat 13",
    "sg:city":"'S Gravenhage",
    "sg:classifiers":[
        {
            "category":"Education",
            "subcategory":"Preschool",
            "type":"Public Place"
        }
    ],
    "sg:phone":"+31 70 383 4801",
    "sg:postcode":"2515 SM",
    "sg:province":"South Holland",
    "sg:tags":[
        "kleuteronderwijs",
        "basis-"
    ],
    "wof:name":"Jan Van Nassauschool",
    "wof:placetype":"venue"
},
  "geometry": {"coordinates":[4.322634,52.074921],"type":"Point"}
}