{
  "type": "Feature",
  "properties": {
    "addr:full":"Wilhelminastr 13 Vlagtwedde Groningen 9541 AM",
    "addr:housenumber":"13",
    "addr:postcode":"9541",
    "addr:street":"Wilhelminastr",
    "iso:country":"NL",
    "sg:address":"Wilhelminastr 13",
    "sg:city":"Vlagtwedde",
    "sg:orig_category":"Postkantoren",
    "sg:phone":"+31 599 312 334",
    "sg:postcode":"9541 AM",
    "sg:province":"Groningen",
    "sg:website":"http://www.postkantoor.nl",
    "wof:name":"Postkantoor",
    "wof:placetype":"venue"
},
  "geometry": {"coordinates":[7.112657,53.02602],"type":"Point"}
}