{
  "type": "Feature",
  "properties": {
    "iso:country":"NL",
    "sg:address":"Achterwillensewg 22C",
    "sg:city":"Gouda",
    "sg:orig_category":"Vakorganisaties",
    "sg:phone":"+31 182 546 687",
    "sg:postcode":"2805 JX",
    "sg:province":"Zuid-Holland",
    "wof:name":"Fnv Bouw",
    "wof:placetype":"venue"
},
  "geometry": {"coordinates":[4.724336,52.01825],"type":"Point"}
}