{
  "type": "Feature",
  "properties": {
    "addr:full":"H Dunantwg 5 Bodegraven Zuid-Holland 2411 NJ",
    "addr:housenumber":"5",
    "addr:postcode":"2411 nj",
    "iso:country":"NL",
    "sg:address":"H Dunantwg 5",
    "sg:city":"Bodegraven",
    "sg:orig_category":"Zuivel - Groothandel",
    "sg:phone":"+31 172 650 007",
    "sg:postcode":"2411 NJ",
    "sg:province":"Zuid-Holland",
    "wof:name":"Keijzer Bv, De",
    "wof:placetype":"venue"
},
  "geometry": {"coordinates":[4.750164,52.071167],"type":"Point"}
}