{
  "type": "Feature",
  "properties": {
    "iso:country":"NL",
    "sg:address":"Gardeniersln 21",
    "sg:city":"Apeldoorn",
    "sg:orig_category":"Vertaalbureaus",
    "sg:phone":"+31 55 579 1164",
    "sg:postcode":"7314 CS",
    "sg:province":"Gelderland",
    "wof:name":"Crockett-Steures, M M T",
    "wof:placetype":"venue"
},
  "geometry": {"coordinates":[5.950765,52.218239],"type":"Point"}
}