{
  "type": "Feature",
  "properties": {
    "addr:full":"Dorpsstr 10 Noord Sleen Drenthe 7846 AT",
    "addr:housenumber":"10",
    "addr:postcode":"7846",
    "addr:street":"Dorpsstr",
    "iso:country":"NL",
    "sg:address":"Dorpsstr 10",
    "sg:city":"Noord Sleen",
    "sg:orig_category":"Wijnkoperijen En -Groothandel",
    "sg:phone":"+31 591 361 737",
    "sg:postcode":"7846 AT",
    "sg:province":"Drenthe",
    "wof:name":"Oude Smederij, De",
    "wof:placetype":"venue"
},
  "geometry": {"coordinates":[6.7977380753,52.7930793762],"type":"Point"}
}