{
  "type": "Feature",
  "properties": {
    "addr:full":"Kon Julianawg 17 Heerenveen Friesland 8443 DP",
    "addr:housenumber":"17",
    "addr:postcode":"8443 dp",
    "addr:street":"Kon",
    "iso:country":"NL",
    "sg:address":"Kon Julianawg 17",
    "sg:city":"Heerenveen",
    "sg:orig_category":"Schilders",
    "sg:phone":"+31 513 636 154",
    "sg:postcode":"8443 DP",
    "sg:province":"Friesland",
    "wof:name":"Boersma, Piet",
    "wof:placetype":"venue"
},
  "geometry": {"coordinates":[5.929095,52.95845],"type":"Point"}
}