{
  "type": "Feature",
  "properties": {
    "addr:full":"Kerklaan 45 Wateringen South Holland 2291 CD",
    "addr:housenumber":"45",
    "addr:postcode":"2291 cd",
    "addr:street":"Kerklaan",
    "iso:country":"NL",
    "sg:address":"Kerklaan 45",
    "sg:city":"Wateringen",
    "sg:orig_category":"Fotostudio'S And Fotografen",
    "sg:phone":"+31 174 297 187",
    "sg:postcode":"2291 CD",
    "sg:province":"South Holland",
    "wof:name":"Foto Peter V Raamsdonk Exclusieve Fotogr",
    "wof:placetype":"venue"
},
  "geometry": {"coordinates":[4.272093,52.027287],"type":"Point"}
}