{
  "type": "Feature",
  "properties": {
    "iso:country":"NL",
    "sg:address":"Dominee Boersstrjitte 16",
    "sg:city":"Reduzum",
    "sg:orig_category":"Kappers",
    "sg:phone":"+31 566 602 196",
    "sg:postcode":"9008 SC",
    "sg:province":"Friesland",
    "wof:name":"Kapsalon Papillot",
    "wof:placetype":"venue"
},
  "geometry": {"coordinates":[-80.9474411011,33.6249809265],"type":"Point"}
}