{
  "type": "Feature",
  "properties": {
    "addr:full":"V Wyngaerdenstr 6 S Gravenhage Zuid-Holland 2596 TX",
    "addr:housenumber":"6;gravenhage;2596",
    "addr:street":"Wyngaerdenstr;S",
    "iso:country":"NL",
    "sg:address":"V Wyngaerdenstr 6",
    "sg:city":"S Gravenhage",
    "sg:orig_category":"Journalisten Freelance",
    "sg:phone":"+31 70 326 8171",
    "sg:postcode":"2596 TX",
    "sg:province":"Zuid-Holland",
    "wof:name":"Kerkvliet",
    "wof:placetype":"venue"
},
  "geometry": {"coordinates":[4.31846,52.093311],"type":"Point"}
}