{
  "type": "Feature",
  "properties": {
    "iso:country":"NL",
    "sg:address":"Markt 17",
    "sg:city":"Delft",
    "sg:orig_category":"Meubelzaken, Woning- And Keukeninrichting",
    "sg:phone":"+31 15 212 6109",
    "sg:postcode":"2611 GP",
    "sg:province":"Zuid-Holland",
    "wof:name":"Van Waay En Soetekouw Bv",
    "wof:placetype":"venue"
},
  "geometry": {"coordinates":[4.3582,52.01096],"type":"Point"}
}