{
  "type": "Feature",
  "properties": {
    "addr:full":"Galjoenstr 1 Tilburg Noord-Brabant 5017 CL",
    "addr:housenumber":"1",
    "addr:postcode":"5017",
    "addr:street":"Galjoenstr",
    "iso:country":"NL",
    "sg:address":"Galjoenstr 1",
    "sg:city":"Tilburg",
    "sg:orig_category":"Machinehandel",
    "sg:phone":"+31 13 532 1136",
    "sg:postcode":"5017 CL",
    "sg:province":"Noord-Brabant",
    "wof:name":"Intermedia Holl Bv",
    "wof:placetype":"venue"
},
  "geometry": {"coordinates":[5.100198,51.554268],"type":"Point"}
}