{
  "type": "Feature",
  "properties": {
    "addr:full":"Lokhorst 145 Leiderdorp Zuid-Holland 2352 KE",
    "addr:housenumber":"145",
    "addr:postcode":"2352 ke",
    "addr:street":"Lokhorst",
    "iso:country":"NL",
    "sg:address":"Lokhorst 145",
    "sg:city":"Leiderdorp",
    "sg:orig_category":"Bewakingsdiensten",
    "sg:phone":"+31 71 542 4314",
    "sg:postcode":"2352 KE",
    "sg:province":"Zuid-Holland",
    "sg:website":"http://www.housewatchers.nl",
    "wof:name":"House Watchers",
    "wof:placetype":"venue"
},
  "geometry": {"coordinates":[4.528556,52.157543],"type":"Point"}
}