{
  "type": "Feature",
  "properties": {
    "iso:country":"NL",
    "sg:address":"Cort Van Der Lindenkade 32",
    "sg:city":"Amsterdam",
    "sg:orig_category":"Goederenvervoer Over De Weg",
    "sg:phone":"+31 20 613 4355",
    "sg:postcode":"1067 LJ",
    "sg:province":"Noord-Holland",
    "wof:name":"Europe International Distribution",
    "wof:placetype":"venue"
},
  "geometry": {"coordinates":[4.794049,52.376247],"type":"Point"}
}