{
  "type": "Feature",
  "properties": {
    "addr:full":"Meekeshof 69 Wijtgaard Friesland 9089 BD",
    "addr:housenumber":"69",
    "addr:postcode":"9089 bd",
    "addr:street":"Meekeshof",
    "iso:country":"NL",
    "sg:address":"Meekeshof 69",
    "sg:city":"Wijtgaard",
    "sg:orig_category":"Architecten",
    "sg:phone":"+31 58 255 3010",
    "sg:postcode":"9089 BD",
    "sg:province":"Friesland",
    "wof:name":"Ir. A. Bergsma Grietzen Architect Bi",
    "wof:placetype":"venue"
},
  "geometry": {"coordinates":[5.781672,53.140594],"type":"Point"}
}