{
  "type": "Feature",
  "properties": {
    "addr:full":"Dillingecamp 9 Emmen Drenthe 7824 EC",
    "addr:housenumber":"9",
    "addr:postcode":"7824 ec",
    "addr:street":"Dillingecamp",
    "iso:country":"NL",
    "sg:address":"Dillingecamp 9",
    "sg:city":"Emmen",
    "sg:orig_category":"Boekhouders",
    "sg:phone":"+31 591 620 605",
    "sg:postcode":"7824 EC",
    "sg:province":"Drenthe",
    "wof:name":"J.P. Heijne",
    "wof:placetype":"venue"
},
  "geometry": {"coordinates":[6.92549,52.782608],"type":"Point"}
}