{
  "type": "Feature",
  "properties": {
    "addr:full":"Oudegracht 63 Utrecht Utrecht 3511 AD",
    "addr:housenumber":"63",
    "addr:postcode":"3511 ad",
    "addr:street":"Oudegracht",
    "iso:country":"NL",
    "sg:address":"Oudegracht 63",
    "sg:city":"Utrecht",
    "sg:orig_category":"Zalenexploitatie",
    "sg:phone":"+31 30 232 2026",
    "sg:postcode":"3511 AD",
    "sg:province":"Utrecht",
    "wof:name":"Art Lease Bv",
    "wof:placetype":"venue"
},
  "geometry": {"coordinates":[5.115405,52.088932],"type":"Point"}
}