{
  "type": "Feature",
  "properties": {
    "addr:full":"Oliemulderswg 53 Groningen Groningen 9713 VA",
    "addr:housenumber":"53",
    "addr:postcode":"9713",
    "addr:street":"Oliemulderswg",
    "iso:country":"NL",
    "sg:address":"Oliemulderswg 53",
    "sg:city":"Groningen",
    "sg:orig_category":"Accumulatoren",
    "sg:phone":"+31 50 318 5140",
    "sg:postcode":"9713 VA",
    "sg:province":"Groningen",
    "wof:name":"Deta",
    "wof:placetype":"venue"
},
  "geometry": {"coordinates":[6.582446,53.231331],"type":"Point"}
}