{
  "type": "Feature",
  "properties": {
    "addr:full":"Elandsgracht 105 Amsterdam Noord-Holland 1016 TT",
    "addr:housenumber":"105",
    "addr:postcode":"1016 tt",
    "addr:street":"Elandsgracht",
    "iso:country":"NL",
    "sg:address":"Elandsgracht 105",
    "sg:city":"Amsterdam",
    "sg:orig_category":"Diverse Grafische Activiteiten",
    "sg:phone":"+31 20 623 2434",
    "sg:postcode":"1016 TT",
    "sg:province":"Noord-Holland",
    "wof:name":"Boekbindery Keve Bv",
    "wof:placetype":"venue"
},
  "geometry": {"coordinates":[4.878966,52.3689],"type":"Point"}
}