{
  "type": "Feature",
  "properties": {
    "addr:full":"Steenpad 21F Willemstad Nb Noord-Brabant 4797 SG",
    "addr:housenumber":"21f",
    "addr:postcode":"4797 sg",
    "addr:street":"Steenpad",
    "iso:country":"NL",
    "sg:address":"Steenpad 21F",
    "sg:city":"Willemstad Nb",
    "sg:orig_category":"Parfumerie - Groothandel",
    "sg:phone":"+31 168 473 746",
    "sg:postcode":"4797 SG",
    "sg:province":"Noord-Brabant",
    "wof:name":"Cosmetic Supply Bv",
    "wof:placetype":"venue"
},
  "geometry": {"coordinates":[4.43319,51.675362],"type":"Point"}
}