{
  "type": "Feature",
  "properties": {
    "addr:full":"Ninnesweg 121 Panningen Limburg 5981 PB",
    "addr:housenumber":"121",
    "addr:postcode":"5981 pb",
    "addr:street":"Ninnesweg",
    "iso:country":"NL",
    "sg:address":"Ninnesweg 121",
    "sg:city":"Panningen",
    "sg:orig_category":"Houtverwerking",
    "sg:phone":"+31 77 307 2268",
    "sg:postcode":"5981 PB",
    "sg:province":"Limburg",
    "wof:name":"Houthandel Lianmie",
    "wof:placetype":"venue"
},
  "geometry": {"coordinates":[5.972405,51.348045],"type":"Point"}
}