{
  "type": "Feature",
  "properties": {
    "iso:country":"NL",
    "sg:address":"Anna Van Burenplein 7",
    "sg:city":"Bathmen",
    "sg:orig_category":"Kappers",
    "sg:phone":"+31 570 542 697",
    "sg:postcode":"7437 XP",
    "sg:province":"Overijssel",
    "wof:name":"Dameskapsalon Ingrid",
    "wof:placetype":"venue"
},
  "geometry": {"coordinates":[6.2977190018,52.2481765747],"type":"Point"}
}