{
  "type": "Feature",
  "properties": {
    "addr:full":"De Loet 84 Castricum North Holland 1902 BL",
    "addr:housenumber":"84",
    "addr:postcode":"1902 bl",
    "addr:street":"De Loet",
    "iso:country":"NL",
    "sg:address":"De Loet 84",
    "sg:city":"Castricum",
    "sg:orig_category":"Verzekeringen",
    "sg:phone":"+31 251 657 211",
    "sg:postcode":"1902 BL",
    "sg:province":"North Holland",
    "wof:name":"Gerard Cobelens Assurantien",
    "wof:placetype":"venue"
},
  "geometry": {"coordinates":[4.673269,52.547058],"type":"Point"}
}