{
  "type": "Feature",
  "properties": {
    "addr:full":"Flierderwg 1 Gorssel Gelderland 7213 LT",
    "addr:housenumber":"1",
    "addr:postcode":"7213 lt",
    "addr:street":"Flierderwg;Gelderland",
    "iso:country":"NL",
    "sg:address":"Flierderwg 1",
    "sg:city":"Gorssel",
    "sg:orig_category":"Touringcars",
    "sg:phone":"+31 575 494 123",
    "sg:postcode":"7213 LT",
    "sg:province":"Gelderland",
    "sg:website":"http://www.samberg.nl",
    "wof:name":"Samberg Bv Taxi",
    "wof:placetype":"venue"
},
  "geometry": {"coordinates":[6.215145,52.187828],"type":"Point"}
}