{
  "type": "Feature",
  "properties": {
    "addr:full":"Dorpsstr 22 Vorden Gelderland 7251 BB",
    "addr:housenumber":"22",
    "addr:postcode":"7251 bb",
    "addr:street":"Dorpsstr;Gelderland",
    "iso:country":"NL",
    "sg:address":"Dorpsstr 22",
    "sg:city":"Vorden",
    "sg:orig_category":"Binnenhuisarchitectuur",
    "sg:phone":"+31 575 551 314",
    "sg:postcode":"7251 BB",
    "sg:province":"Gelderland",
    "sg:website":"http://www.wimpolman.nl",
    "wof:name":"Polman, Wim",
    "wof:placetype":"venue"
},
  "geometry": {"coordinates":[6.314576,52.103554],"type":"Point"}
}