{
  "type": "Feature",
  "properties": {
    "iso:country":"NL",
    "sg:address":"Herenwg 94",
    "sg:city":"Hoogwoud",
    "sg:orig_category":"Bloembollen - Groothandel",
    "sg:phone":"+31 226 351 475",
    "sg:postcode":"1718 AH",
    "sg:province":"Noord-Holland",
    "wof:name":"Hoogland Vof, M S",
    "wof:placetype":"venue"
},
  "geometry": {"coordinates":[4.942702,52.728783],"type":"Point"}
}