{
  "type": "Feature",
  "properties": {
    "addr:full":"Stationstr 149E Nuth Limburg 6361 BH",
    "addr:housenumber":"149e",
    "addr:postcode":"6361 bh",
    "addr:street":"Stationstr",
    "iso:country":"NL",
    "sg:address":"Stationstr 149E",
    "sg:city":"Nuth",
    "sg:orig_category":"Keukens",
    "sg:phone":"+31 45 524 4610",
    "sg:postcode":"6361 BH",
    "sg:province":"Limburg",
    "sg:website":"http://www.keukenstudio-nuth.nl",
    "wof:name":"Keukenstudio Nuth Bv",
    "wof:placetype":"venue"
},
  "geometry": {"coordinates":[5.885999,50.918785],"type":"Point"}
}