{
  "type": "Feature",
  "properties": {
    "iso:country":"NL",
    "sg:address":"Hoofdstr 130",
    "sg:city":"Hillegom",
    "sg:orig_category":"Boeken En Tijdschriften",
    "sg:phone":"+31 252 525 973",
    "sg:postcode":"2181 EH",
    "sg:province":"North Holland",
    "sg:website":"http://www.bruna.nl/",
    "wof:name":"Bruna",
    "wof:placetype":"venue"
},
  "geometry": {"coordinates":[4.578373,52.292065],"type":"Point"}
}