{
  "type": "Feature",
  "properties": {
    "addr:full":"Gr Hendrik 3 Pln 33 Breda Noord-Brabant 4819 CJ",
    "addr:housenumber":"3;33",
    "addr:postcode":"4819 cj",
    "addr:street":"Hendrik;Pln",
    "iso:country":"NL",
    "sg:address":"Gr Hendrik 3 Pln 33",
    "sg:city":"Breda",
    "sg:orig_category":"Schoonheidsinstituten",
    "sg:phone":"+31 76 515 4835",
    "sg:postcode":"4819 CJ",
    "sg:province":"Noord-Brabant",
    "wof:name":"Wilma",
    "wof:placetype":"venue"
},
  "geometry": {"coordinates":[4.771241,51.577282],"type":"Point"}
}