{
  "type": "Feature",
  "properties": {
    "addr:full":"Rengerslaan 2 Leeuwarden Friesland 8917 DD",
    "addr:housenumber":"2",
    "addr:postcode":"8917 dd",
    "addr:street":"Rengerslaan",
    "iso:country":"NL",
    "sg:address":"Rengerslaan 2",
    "sg:city":"Leeuwarden",
    "sg:orig_category":"Begrafenisondernemers",
    "sg:phone":"+31 58 212 3990",
    "sg:postcode":"8917 DD",
    "sg:province":"Friesland",
    "wof:name":"Nuva Friese Uitvaartverzorging",
    "wof:placetype":"venue"
},
  "geometry": {"coordinates":[5.794818,53.207272],"type":"Point"}
}