{
  "type": "Feature",
  "properties": {
    "addr:full":"Leimuidenstr 25 Tilburg North Brabant 5045 ZA",
    "addr:housenumber":"25",
    "addr:postcode":"5045",
    "addr:street":"Leimuidenstr",
    "iso:country":"NL",
    "sg:address":"Leimuidenstr 25",
    "sg:city":"Tilburg",
    "sg:orig_category":"Parketvloeren",
    "sg:phone":"+31 13 571 8000",
    "sg:postcode":"5045 ZA",
    "sg:province":"North Brabant",
    "wof:name":"Mierlo, Van",
    "wof:placetype":"venue"
},
  "geometry": {"coordinates":[5.002616,51.590202],"type":"Point"}
}