{
  "type": "Feature",
  "properties": {
    "addr:full":"Kokermolen 3 Houten Utrecht 3994 DG",
    "addr:housenumber":"3",
    "addr:postcode":"3994 dg",
    "addr:street":"Kokermolen",
    "iso:country":"NL",
    "sg:address":"Kokermolen 3",
    "sg:city":"Houten",
    "sg:orig_category":"Makelaars En Adviseurs Verzekeringen",
    "sg:phone":"+31 30 691 2218",
    "sg:postcode":"3994 DG",
    "sg:province":"Utrecht",
    "wof:name":"Finagri Bv",
    "wof:placetype":"venue"
},
  "geometry": {"coordinates":[5.17682,52.02927],"type":"Point"}
}