{
  "type": "Feature",
  "properties": {
    "addr:full":"Parkstr 26 Nuenen Noord-Brabant 5671 GG",
    "addr:housenumber":"26",
    "addr:postcode":"5671 gg",
    "addr:street":"Parkstr",
    "iso:country":"NL",
    "sg:address":"Parkstr 26",
    "sg:city":"Nuenen",
    "sg:orig_category":"Kappers",
    "sg:phone":"+31 40 283 6284",
    "sg:postcode":"5671 GG",
    "sg:province":"Noord-Brabant",
    "wof:name":"Raymond Deckers Haarmode",
    "wof:placetype":"venue"
},
  "geometry": {"coordinates":[5.545633,51.472054],"type":"Point"}
}