{
  "type": "Feature",
  "properties": {
    "iso:country":"NL",
    "sg:address":"Glacisweg 48",
    "sg:city":"Hulst",
    "sg:orig_category":"Verzekeringen",
    "sg:phone":"+31 114 312 220",
    "sg:postcode":"4561 HG",
    "sg:province":"Zeeland",
    "wof:name":"Assurantiekantoor Boidin Hulst Bv",
    "wof:placetype":"venue"
},
  "geometry": {"coordinates":[4.050413,51.285267],"type":"Point"}
}