{
  "type": "Feature",
  "properties": {
    "iso:country":"NL",
    "sg:address":"Coolsestraat 37D",
    "sg:city":"Rotterdam",
    "sg:orig_category":"Visserij",
    "sg:phone":"+31 10 414 7292",
    "sg:postcode":"3014 LB",
    "sg:province":"Zuid-Holland",
    "wof:name":"W.J. Den Boer",
    "wof:placetype":"venue"
},
  "geometry": {"coordinates":[4.465461,51.92181],"type":"Point"}
}