{
  "type": "Feature",
  "properties": {
    "iso:country":"NL",
    "sg:address":"Antillenstr 37-2",
    "sg:city":"Amsterdam",
    "sg:orig_category":"Vertalers",
    "sg:phone":"+31 20 412 2138",
    "sg:postcode":"1058 GZ",
    "sg:province":"North Holland",
    "wof:name":"W\u00f3jcicka, Elzbieta",
    "wof:placetype":"venue"
},
  "geometry": {"coordinates":[4.850283,52.359501],"type":"Point"}
}