{
  "type": "Feature",
  "properties": {
    "addr:full":"Touwbaan 10 Leiderdorp South Holland 2352 CZ",
    "addr:housenumber":"10",
    "addr:postcode":"2352",
    "addr:street":"Touwbaan",
    "iso:country":"NL",
    "sg:address":"Touwbaan 10",
    "sg:city":"Leiderdorp",
    "sg:orig_category":"Wegen And Sportterreinen",
    "sg:phone":"+31 71 589 9319",
    "sg:postcode":"2352 CZ",
    "sg:province":"South Holland",
    "wof:name":"Aannemersbedrijf Gebroeders Kooijman Bv",
    "wof:placetype":"venue"
},
  "geometry": {"coordinates":[4.5210151672,52.161907196],"type":"Point"}
}