{
  "type": "Feature",
  "properties": {
    "addr:full":"Van Leeuwenhoekstraat 22-24 Harderwijk Gelderland 3846 CB",
    "addr:housenumber":"22-24",
    "addr:postcode":"3846 cb",
    "addr:street":"Van Leeuwenhoekstraat;Gelderland",
    "iso:country":"NL",
    "sg:address":"Van Leeuwenhoekstraat 22-24",
    "sg:city":"Harderwijk",
    "sg:classifiers":[
        {
            "category":"Retail",
            "subcategory":"Storage",
            "type":"Services"
        }
    ],
    "sg:phone":"+31 341 413 601",
    "sg:postcode":"3846 CB",
    "sg:province":"Gelderland",
    "sg:tags":[
        "opslag",
        "bewaring"
    ],
    "wof:name":"Jansen Op- En Overslag Bv",
    "wof:placetype":"venue"
},
  "geometry": {"coordinates":[5.6480817795,52.3641014099],"type":"Point"}
}