{
  "type": "Feature",
  "properties": {
    "addr:full":"Havenkade-West 1 Winschoten Groningen 9672 BB",
    "addr:housenumber":"1",
    "addr:postcode":"9672 bb",
    "addr:street":"Havenkade-West",
    "iso:country":"NL",
    "sg:address":"Havenkade-West 1",
    "sg:city":"Winschoten",
    "sg:orig_category":"Goederenvervoer Over De Weg",
    "sg:phone":"+31 597 422 916",
    "sg:postcode":"9672 BB",
    "sg:province":"Groningen",
    "wof:name":"Stegra Transport Bv",
    "wof:placetype":"venue"
},
  "geometry": {"coordinates":[7.045327,53.141617],"type":"Point"}
}