{
  "type": "Feature",
  "properties": {
    "addr:full":"Keizersveld 32 Venray Limburg 5803 AN",
    "addr:housenumber":"32",
    "addr:postcode":"5803 an",
    "addr:street":"Keizersveld",
    "iso:country":"NL",
    "sg:address":"Keizersveld 32",
    "sg:city":"Venray",
    "sg:orig_category":"Keuken- Groot-Installaties",
    "sg:phone":"+31 478 513 985",
    "sg:postcode":"5803 AN",
    "sg:province":"Limburg",
    "wof:name":"Janssen Ysselsteyn",
    "wof:placetype":"venue"
},
  "geometry": {"coordinates":[5.988841,51.539642],"type":"Point"}
}