{
  "type": "Feature",
  "properties": {
    "addr:full":"Nieuwsteeg 31 Hoorn Nh North Holland 1621 EC",
    "addr:housenumber":"31",
    "addr:postcode":"1621 ec",
    "addr:street":"Nieuwsteeg;Nh North",
    "iso:country":"NL",
    "sg:address":"Nieuwsteeg 31",
    "sg:city":"Hoorn Nh",
    "sg:orig_category":"Opticiens",
    "sg:phone":"+31 229 213 657",
    "sg:postcode":"1621 EC",
    "sg:province":"North Holland",
    "wof:name":"Hans Anders Opticiens",
    "wof:placetype":"venue"
},
  "geometry": {"coordinates":[5.0585122108,52.6414031982],"type":"Point"}
}