{
  "type": "Feature",
  "properties": {
    "addr:full":"Platinastr 41 Hengelo Ov Overijssel 7554 NC",
    "addr:housenumber":"41",
    "addr:postcode":"7554 nc",
    "addr:street":"Platinastr;Ov",
    "iso:country":"NL",
    "sg:address":"Platinastr 41",
    "sg:city":"Hengelo Ov",
    "sg:orig_category":"Lasbedrijven",
    "sg:phone":"+31 74 259 4143",
    "sg:postcode":"7554 NC",
    "sg:province":"Overijssel",
    "wof:name":"Oost Lastechniek Vof",
    "wof:placetype":"venue"
},
  "geometry": {"coordinates":[6.761817,52.243191],"type":"Point"}
}