{
  "type": "Feature",
  "properties": {
    "addr:full":"Onderweg 91 Waddinxveen Zuid-Holland 2742 LB",
    "addr:housenumber":"91",
    "addr:postcode":"2742 lb",
    "addr:street":"Onderweg",
    "iso:country":"NL",
    "sg:address":"Onderweg 91",
    "sg:city":"Waddinxveen",
    "sg:orig_category":"Wegen And Sportterreinen",
    "sg:phone":"+31 182 613 234",
    "sg:postcode":"2742 LB",
    "sg:province":"Zuid-Holland",
    "wof:name":"Gebroeders Van Vliet",
    "wof:placetype":"venue"
},
  "geometry": {"coordinates":[4.6356091499,52.0456886292],"type":"Point"}
}