{
  "type": "Feature",
  "properties": {
    "addr:full":"M Naeffln 40 Lochem Gelderland 7241 GE",
    "addr:housenumber":"40",
    "addr:postcode":"7241",
    "addr:street":"Gelderland",
    "iso:country":"NL",
    "sg:address":"M Naeffln 40",
    "sg:city":"Lochem",
    "sg:orig_category":"Adviesbureaus Bedrijfsorganisatie",
    "sg:phone":"+31 573 251 042",
    "sg:postcode":"7241 GE",
    "sg:province":"Gelderland",
    "wof:name":"Blom, Bur",
    "wof:placetype":"venue"
},
  "geometry": {"coordinates":[6.409836,52.162872],"type":"Point"}
}