{
  "type": "Feature",
  "properties": {
    "addr:full":"Stanleystr 23 Heerlen Limburg 6413 HR",
    "addr:housenumber":"23",
    "addr:postcode":"6413 hr",
    "addr:street":"Stanleystr",
    "iso:country":"NL",
    "sg:address":"Stanleystr 23",
    "sg:city":"Heerlen",
    "sg:orig_category":"Apotheken",
    "sg:phone":"+31 45 521 0772",
    "sg:postcode":"6413 HR",
    "sg:province":"Limburg",
    "wof:name":"Ganzeweide",
    "wof:placetype":"venue"
},
  "geometry": {"coordinates":[5.949646,50.919151],"type":"Point"}
}