{
  "type": "Feature",
  "properties": {
    "addr:full":"Dom Huybenlaan 17 Egmond-Binnen Noord-Holland 1935 BA",
    "addr:housenumber":"17",
    "addr:postcode":"egmond-binnen;1935 ba",
    "addr:street":"Dom Huybenlaan",
    "iso:country":"NL",
    "sg:address":"Dom Huybenlaan 17",
    "sg:city":"Egmond-Binnen",
    "sg:orig_category":"Schilderwerk",
    "sg:phone":"+31 72 506 5487",
    "sg:postcode":"1935 BA",
    "sg:province":"Noord-Holland",
    "wof:name":"C.A. Zentveld",
    "wof:placetype":"venue"
},
  "geometry": {"coordinates":[4.658081,52.594666],"type":"Point"}
}