{
  "type": "Feature",
  "properties": {
    "addr:full":"Leeuwenburg 10 Gouda Zuid-Holland 2804 WN",
    "addr:housenumber":"10",
    "addr:postcode":"2804 wn",
    "addr:street":"Leeuwenburg",
    "iso:country":"NL",
    "sg:address":"Leeuwenburg 10",
    "sg:city":"Gouda",
    "sg:orig_category":"Hypotheken And Hypotheekbanken",
    "sg:phone":"+31 182 534 377",
    "sg:postcode":"2804 WN",
    "sg:province":"Zuid-Holland",
    "wof:name":"Leeuwenborch Verzekeringen En Pensioenen",
    "wof:placetype":"venue"
},
  "geometry": {"coordinates":[4.706504,52.032207],"type":"Point"}
}