{
  "type": "Feature",
  "properties": {
    "iso:country":"NL",
    "sg:address":"Elderveldpln 19",
    "sg:city":"Arnhem",
    "sg:orig_category":"Zoetwaren - Winkels",
    "sg:phone":"+31 26 381 1447",
    "sg:postcode":"6843 JA",
    "sg:province":"Gelderland",
    "wof:name":"Jamin Bv",
    "wof:placetype":"venue"
},
  "geometry": {"coordinates":[5.859659,51.960537],"type":"Point"}
}