{
  "type": "Feature",
  "properties": {
    "addr:full":"Pluim Es 82 Krimpen Ad Yssel Zuid-Holland 2925 CN",
    "addr:housenumber":"82",
    "addr:postcode":"2925 cn",
    "addr:street":"Es",
    "iso:country":"NL",
    "sg:address":"Pluim Es 82",
    "sg:city":"Krimpen Ad Yssel",
    "sg:orig_category":"Administratie- En Boekhoudkantoren",
    "sg:phone":"+31 180 551 010",
    "sg:postcode":"2925 CN",
    "sg:province":"Zuid-Holland",
    "wof:name":"Emvo",
    "wof:placetype":"venue"
},
  "geometry": {"coordinates":[4.620464,51.915142],"type":"Point"}
}