{
  "type": "Feature",
  "properties": {
    "addr:full":"A Ariensstr 170 Schiedam Zuid-Holland 3119 VC",
    "addr:housenumber":"170",
    "addr:postcode":"3119 vc",
    "iso:country":"NL",
    "sg:address":"A Ariensstr 170",
    "sg:city":"Schiedam",
    "sg:orig_category":"Adviesbureaus Bedrijfsorganisatie",
    "sg:phone":"+31 10 246 0231",
    "sg:postcode":"3119 VC",
    "sg:province":"Zuid-Holland",
    "wof:name":"Oryn",
    "wof:placetype":"venue"
},
  "geometry": {"coordinates":[4.401062,51.921501],"type":"Point"}
}