{
  "type": "Feature",
  "properties": {
    "iso:country":"NL",
    "sg:address":"Hordk 98",
    "sg:city":"Rotterdam",
    "sg:orig_category":"Acupunctuur",
    "sg:phone":"+31 10 497 7893",
    "sg:postcode":"3079 DK",
    "sg:province":"South Holland",
    "wof:name":"Human Care",
    "wof:placetype":"venue"
},
  "geometry": {"coordinates":[4.540309,51.879173],"type":"Point"}
}