{
  "type": "Feature",
  "properties": {
    "addr:full":"Numansgors 38 Numansdorp South Holland 3281 HA",
    "addr:housenumber":"38",
    "addr:postcode":"3281 ha",
    "addr:street":"Numansgors",
    "iso:country":"NL",
    "sg:address":"Numansgors 38",
    "sg:city":"Numansdorp",
    "sg:orig_category":"Fotografie Reclame En Mode",
    "sg:phone":"+31 186 655 280",
    "sg:postcode":"3281 HA",
    "sg:province":"South Holland",
    "wof:name":"Volder En De Meij Vof",
    "wof:placetype":"venue"
},
  "geometry": {"coordinates":[4.447924,51.71703],"type":"Point"}
}