{
  "type": "Feature",
  "properties": {
    "addr:full":"Binnen Bantammerstraat 17 Amsterdam Noord-Holland 1011 CJ",
    "addr:housenumber":"17",
    "addr:postcode":"1011 cj",
    "addr:street":"Binnen Bantammerstraat",
    "iso:country":"NL",
    "sg:address":"Binnen Bantammerstraat 17",
    "sg:city":"Amsterdam",
    "sg:classifiers":[
        {
            "category":"Food & Beverages",
            "subcategory":"Fruits & Vegetables",
            "type":"Retail Goods"
        }
    ],
    "sg:phone":"+31 20 624 5513",
    "sg:postcode":"1011 CJ",
    "sg:province":"Noord-Holland",
    "sg:tags":[
        "groenten"
    ],
    "wof:name":"Joop En Trudi Petersen",
    "wof:placetype":"venue"
},
  "geometry": {"coordinates":[4.902405,52.373886],"type":"Point"}
}