{
  "type": "Feature",
  "properties": {
    "addr:full":"Ptr Vd Elsenstr 3 Gemert Noord-Brabant 5421 HZ",
    "addr:housenumber":"3",
    "addr:postcode":"ptr;5421 hz",
    "addr:street":"Elsenstr",
    "iso:country":"NL",
    "sg:address":"Ptr Vd Elsenstr 3",
    "sg:city":"Gemert",
    "sg:orig_category":"Advocaten En Advocatenkantoren",
    "sg:phone":"+31 492 366 176",
    "sg:postcode":"5421 HZ",
    "sg:province":"Noord-Brabant",
    "wof:name":"Kersemakers, Mr J G J",
    "wof:placetype":"venue"
},
  "geometry": {"coordinates":[5.688309,51.553539],"type":"Point"}
}