{
  "type": "Feature",
  "properties": {
    "addr:full":"Zuideropgaande 71A Hollandscheveld Drenthe 7913 TJ",
    "addr:housenumber":"71a",
    "addr:postcode":"7913 tj",
    "addr:street":"Zuideropgaande",
    "iso:country":"NL",
    "sg:address":"Zuideropgaande 71A",
    "sg:city":"Hollandscheveld",
    "sg:orig_category":"Graszoden",
    "sg:phone":"+31 528 361 300",
    "sg:postcode":"7913 TJ",
    "sg:province":"Drenthe",
    "wof:name":"Bremer, R",
    "wof:placetype":"venue"
},
  "geometry": {"coordinates":[6.538419,52.68792],"type":"Point"}
}