{
  "type": "Feature",
  "properties": {
    "addr:full":"De Vlotkampweg 6 Nijmegen Gelderland 6545 AG",
    "addr:housenumber":"6",
    "addr:postcode":"6545",
    "addr:street":"De Vlotkampweg;Gelderland",
    "iso:country":"NL",
    "sg:address":"De Vlotkampweg 6",
    "sg:city":"Nijmegen",
    "sg:orig_category":"Goederenvervoer Over De Weg",
    "sg:phone":"+31 24 378 2970",
    "sg:postcode":"6545 AG",
    "sg:province":"Gelderland",
    "wof:name":"Transpose",
    "wof:placetype":"venue"
},
  "geometry": {"coordinates":[5.812938,51.8461],"type":"Point"}
}