{
  "type": "Feature",
  "properties": {
    "iso:country":"NL",
    "sg:address":"Withuisstraat 6",
    "sg:city":"Terheijden",
    "sg:orig_category":"Bloemen And Planten",
    "sg:phone":"+31 76 593 1260",
    "sg:postcode":"4844 GA",
    "sg:province":"Noord-Brabant",
    "wof:name":"Firma Gebr. Van Vugt Bloemisterij",
    "wof:placetype":"venue"
},
  "geometry": {"coordinates":[4.737656,51.655998],"type":"Point"}
}