{
  "type": "Feature",
  "properties": {
    "addr:full":"V Baerlestr 36 Amsterdam North Holland 1071 AX",
    "addr:housenumber":"36",
    "addr:postcode":"1071 ax",
    "iso:country":"NL",
    "sg:address":"V Baerlestr 36",
    "sg:city":"Amsterdam",
    "sg:orig_category":"Opticiens",
    "sg:phone":"+31 20 676 7305",
    "sg:postcode":"1071 AX",
    "sg:province":"North Holland",
    "wof:name":"Pearle",
    "wof:placetype":"venue"
},
  "geometry": {"coordinates":[4.8770098686,52.3555488586],"type":"Point"}
}