{
  "type": "Feature",
  "properties": {
    "addr:full":"N Bohrwg 157 Utrecht Utrecht 3542 CA",
    "addr:housenumber":"157",
    "addr:postcode":"3542 ca",
    "addr:street":"N",
    "iso:country":"NL",
    "sg:address":"N Bohrwg 157",
    "sg:city":"Utrecht",
    "sg:orig_category":"Mode-Artikelen Dames En Heren",
    "sg:phone":"+31 30 241 3633",
    "sg:postcode":"3542 CA",
    "sg:province":"Utrecht",
    "wof:name":"Double Moon Bv",
    "wof:placetype":"venue"
},
  "geometry": {"coordinates":[5.04973,52.122677],"type":"Point"}
}