{
  "type": "Feature",
  "properties": {
    "iso:country":"NL",
    "sg:address":"Herengracht 455/2",
    "sg:city":"Amsterdam",
    "sg:orig_category":"Werving And Selectie Van Vast Personeel",
    "sg:phone":"+31 20 552 3162",
    "sg:postcode":"1017 BS",
    "sg:province":"Noord-Holland",
    "wof:name":"Mobiliteitsbureau",
    "wof:placetype":"venue"
},
  "geometry": {"coordinates":[4.8896298409,52.3663825989],"type":"Point"}
}