{
  "type": "Feature",
  "properties": {
    "addr:full":"De Plas 3 Raalte NL.08 8102 CS",
    "addr:housenumber":"3;nl.08",
    "addr:postcode":"8102 cs",
    "addr:street":"De Plas",
    "iso:country":"NL",
    "sg:address":"De Plas 3",
    "sg:city":"Raalte",
    "sg:orig_category":"Meubelzaken, Woning- And Keukeninrichting",
    "sg:phone":"+31 572 351 004",
    "sg:postcode":"8102 CS",
    "sg:province":"NL.08",
    "wof:name":"H & R Slaapcomfort",
    "wof:placetype":"venue"
},
  "geometry": {"coordinates":[6.274854,52.385651],"type":"Point"}
}