{
  "type": "Feature",
  "properties": {
    "iso:country":"NL",
    "sg:address":"Makado Center 84-85",
    "sg:city":"Schagen",
    "sg:orig_category":"Verlichting",
    "sg:phone":"+31 224 212 116",
    "sg:postcode":"1741 JA",
    "sg:province":"Noord-Holland",
    "wof:name":"Gift Light",
    "wof:placetype":"venue"
},
  "geometry": {"coordinates":[4.796864,52.787453],"type":"Point"}
}