{
  "type": "Feature",
  "properties": {
    "addr:full":"Cosmeastraat 4 Spijkenisse Zuid-Holland 3202 SE",
    "addr:housenumber":"4",
    "addr:postcode":"3202 se",
    "addr:street":"Cosmeastraat",
    "iso:country":"NL",
    "sg:address":"Cosmeastraat 4",
    "sg:city":"Spijkenisse",
    "sg:orig_category":"Autokeuringen",
    "sg:phone":"+31 181 617 809",
    "sg:postcode":"3202 SE",
    "sg:province":"Zuid-Holland",
    "wof:name":"Shamin Auto Clean",
    "wof:placetype":"venue"
},
  "geometry": {"coordinates":[4.319843,51.854038],"type":"Point"}
}