{
  "type": "Feature",
  "properties": {
    "iso:country":"NL",
    "sg:address":"Dukdalfwg 42",
    "sg:city":"Amsterdam",
    "sg:orig_category":"Kantoor- En Bedrijfsmeubelen",
    "sg:phone":"+31 20 506 0011",
    "sg:postcode":"1041 BE",
    "sg:province":"New York",
    "sg:website":"http://www.workware.nl",
    "wof:name":"Doorn Workware Bv, Van",
    "wof:placetype":"venue"
},
  "geometry": {"coordinates":[-74.0635604858,42.9433288574],"type":"Point"}
}