{
  "type": "Feature",
  "properties": {
    "addr:full":"Goudhaver 4 Zeewolde NL. 3892 BK",
    "addr:housenumber":"4",
    "addr:postcode":"3892 bk",
    "addr:street":"Goudhaver;Nl.",
    "iso:country":"NL",
    "sg:address":"Goudhaver 4",
    "sg:city":"Zeewolde",
    "sg:orig_category":"Product-Promotie",
    "sg:phone":"+31 36 522 3656",
    "sg:postcode":"3892 BK",
    "sg:province":"NL.",
    "wof:name":"Ripas",
    "wof:placetype":"venue"
},
  "geometry": {"coordinates":[5.544755,52.32655],"type":"Point"}
}