{
  "type": "Feature",
  "properties": {
    "addr:full":"A Perkstr 30 Hilversum Noord-Holland 1217 NT",
    "addr:housenumber":"30",
    "addr:postcode":"1217 nt",
    "iso:country":"NL",
    "sg:address":"A Perkstr 30",
    "sg:city":"Hilversum",
    "sg:orig_category":"Verzekeringen - Verzekeringskantoren",
    "sg:phone":"+31 35 621 4622",
    "sg:postcode":"1217 NT",
    "sg:province":"Noord-Holland",
    "wof:name":"Nieuwenhuis-Hermsen",
    "wof:placetype":"venue"
},
  "geometry": {"coordinates":[5.164653,52.226307],"type":"Point"}
}