{
  "type": "Feature",
  "properties": {
    "addr:full":"Willemserf 82 Eemnes Utrecht 3755 XM",
    "addr:housenumber":"82",
    "addr:postcode":"3755 xm",
    "addr:street":"Willemserf",
    "iso:country":"NL",
    "sg:address":"Willemserf 82",
    "sg:city":"Eemnes",
    "sg:orig_category":"Kantoor- En Secretariaatsservice",
    "sg:phone":"+31 35 533 4579",
    "sg:postcode":"3755 XM",
    "sg:province":"Utrecht",
    "sg:website":"http://www.officeforyou.nl",
    "wof:name":"Office For You",
    "wof:placetype":"venue"
},
  "geometry": {"coordinates":[5.2553329468,52.2576370239],"type":"Point"}
}