{
  "type": "Feature",
  "properties": {
    "addr:full":"Zandzegge 6 Leiden Zuid-Holland 2318 ZL",
    "addr:housenumber":"6",
    "addr:postcode":"2318 zl",
    "addr:street":"Zandzegge",
    "iso:country":"NL",
    "sg:address":"Zandzegge 6",
    "sg:city":"Leiden",
    "sg:orig_category":"Bedrijfsopleidingen",
    "sg:phone":"+31 71 528 2068",
    "sg:postcode":"2318 ZL",
    "sg:province":"Zuid-Holland",
    "wof:name":"Kerndialoog",
    "wof:placetype":"venue"
},
  "geometry": {"coordinates":[4.502075,52.181259],"type":"Point"}
}