{
  "type": "Feature",
  "properties": {
    "addr:full":"Dorpsstraat 389 Assendelft Noord-Holland 1566 BE",
    "addr:housenumber":"389",
    "addr:postcode":"1566",
    "addr:street":"Dorpsstraat",
    "iso:country":"NL",
    "sg:address":"Dorpsstraat 389",
    "sg:city":"Assendelft",
    "sg:orig_category":"Bloemen And Planten",
    "sg:phone":"+31 75 687 1296",
    "sg:postcode":"1566 BE",
    "sg:province":"Noord-Holland",
    "wof:name":"Bloemenhuis Rosanna",
    "wof:placetype":"venue"
},
  "geometry": {"coordinates":[4.74079,52.466515],"type":"Point"}
}