{
  "type": "Feature",
  "properties": {
    "iso:country":"NL",
    "sg:address":"Reigersbek 16",
    "sg:city":"Nieuwegein",
    "sg:orig_category":"Honden- En Kattentrimsalons",
    "sg:phone":"+31 30 601 1511",
    "sg:postcode":"3434 XJ",
    "sg:province":"Utrecht",
    "wof:name":"Hondenkapper, De",
    "wof:placetype":"venue"
},
  "geometry": {"coordinates":[5.08134,52.010075],"type":"Point"}
}