{
  "type": "Feature",
  "properties": {
    "addr:full":"Vd Horststr 33 Tilburg North Brabant 5012 GW",
    "addr:housenumber":"33",
    "addr:postcode":"5012 gw",
    "iso:country":"NL",
    "sg:address":"Vd Horststr 33",
    "sg:city":"Tilburg",
    "sg:orig_category":"Evenementenverzorging",
    "sg:phone":"+31 13 456 3944",
    "sg:postcode":"5012 GW",
    "sg:province":"North Brabant",
    "sg:website":"http://www.allez-hop.myweb.nl",
    "wof:name":"Allez-Hop! Circusworkshops",
    "wof:placetype":"venue"
},
  "geometry": {"coordinates":[5.098483,51.582245],"type":"Point"}
}