{
  "type": "Feature",
  "properties": {
    "iso:country":"NL",
    "sg:address":"Vosseleane 16",
    "sg:city":"Woudsend",
    "sg:orig_category":"Bedrijfsinventaris Gh",
    "sg:phone":"+31 514 591 333",
    "sg:postcode":"8551 RA",
    "sg:province":"Provincie Friesland",
    "wof:name":"Reekers Installatiebedrijf Bv",
    "wof:placetype":"venue"
},
  "geometry": {"coordinates":[5.62872,52.943733],"type":"Point"}
}