{
  "type": "Feature",
  "properties": {
    "addr:full":"Arendhorst 29 Roermond Limburg 6043 RR",
    "addr:housenumber":"29",
    "addr:postcode":"6043 rr",
    "addr:street":"Arendhorst",
    "iso:country":"NL",
    "sg:address":"Arendhorst 29",
    "sg:city":"Roermond",
    "sg:orig_category":"Sportclubs",
    "sg:phone":"+31 475 323 506",
    "sg:postcode":"6043 RR",
    "sg:province":"Limburg",
    "wof:name":"Suzuki Savage Club",
    "wof:placetype":"venue"
},
  "geometry": {"coordinates":[6.023467,51.187481],"type":"Point"}
}