{
  "type": "Feature",
  "properties": {
    "iso:country":"NL",
    "sg:address":"Diedenwg 20",
    "sg:city":"Wageningen",
    "sg:orig_category":"Onderzoekbureaus",
    "sg:phone":"+31 317 485 383",
    "sg:postcode":"6703 GW",
    "sg:province":"Gelderland",
    "wof:name":"Centre For Food Sciences",
    "wof:placetype":"venue"
},
  "geometry": {"coordinates":[5.684176,51.969048],"type":"Point"}
}