{
  "type": "Feature",
  "properties": {
    "addr:full":"Nyverheidstr 5 Leerdam Zuid-Holland 4143 HN",
    "addr:housenumber":"5",
    "addr:postcode":"4143 hn",
    "addr:street":"Nyverheidstr",
    "iso:country":"NL",
    "sg:address":"Nyverheidstr 5",
    "sg:city":"Leerdam",
    "sg:orig_category":"Geluidsisolatie",
    "sg:phone":"+31 345 638 020",
    "sg:postcode":"4143 HN",
    "sg:province":"Zuid-Holland",
    "wof:name":"Mitac Bv",
    "wof:placetype":"venue"
},
  "geometry": {"coordinates":[5.102475,51.89814],"type":"Point"}
}