{
  "type": "Feature",
  "properties": {
    "addr:full":"Hortensiastr 25 Nederweert Limburg 6031 VB",
    "addr:housenumber":"25",
    "addr:postcode":"6031 vb",
    "addr:street":"Hortensiastr",
    "iso:country":"NL",
    "sg:address":"Hortensiastr 25",
    "sg:city":"Nederweert",
    "sg:orig_category":"Administratie- En Boekhoudkantoren",
    "sg:phone":"+31 495 632 297",
    "sg:postcode":"6031 VB",
    "sg:province":"Limburg",
    "wof:name":"Kruijs, J H A Van De",
    "wof:placetype":"venue"
},
  "geometry": {"coordinates":[5.74202,51.283321],"type":"Point"}
}