{
  "type": "Feature",
  "properties": {
    "addr:full":"T Dorseypad 6 Rotterdam Zuid-Holland 3069 XX",
    "addr:housenumber":"6",
    "addr:postcode":"3069 xx",
    "addr:street":"T Dorseypad",
    "iso:country":"NL",
    "sg:address":"T Dorseypad 6",
    "sg:city":"Rotterdam",
    "sg:orig_category":"Metselwerken",
    "sg:phone":"+31 10 455 9684",
    "sg:postcode":"3069 XX",
    "sg:province":"Zuid-Holland",
    "wof:name":"Doesburg Rotterdam Bv",
    "wof:placetype":"venue"
},
  "geometry": {"coordinates":[4.57412,51.971165],"type":"Point"}
}