{
  "type": "Feature",
  "properties": {
    "iso:country":"NL",
    "sg:address":"De Arabier 12",
    "sg:city":"Dronten",
    "sg:orig_category":"Schoonheidssalons",
    "sg:phone":"+31 321 318 925",
    "sg:postcode":"8252 GR",
    "sg:province":"NL.",
    "wof:name":"Schoonheidssalon Anja",
    "wof:placetype":"venue"
},
  "geometry": {"coordinates":[5.710616,52.513142],"type":"Point"}
}