{
  "type": "Feature",
  "properties": {
    "addr:full":"Industriewg 46K Grootebroek Noord-Holland 1613 KV",
    "addr:housenumber":"46k",
    "addr:postcode":"1613 kv",
    "addr:street":"Industriewg",
    "iso:country":"NL",
    "sg:address":"Industriewg 46K",
    "sg:city":"Grootebroek",
    "sg:orig_category":"Administratie- En Boekhoudkantoren",
    "sg:phone":"+31 228 511 573",
    "sg:postcode":"1613 KV",
    "sg:province":"Noord-Holland",
    "wof:name":"Keeman",
    "wof:placetype":"venue"
},
  "geometry": {"coordinates":[5.229345,52.694061],"type":"Point"}
}