{
  "type": "Feature",
  "properties": {
    "addr:full":"Nw Blekerstr 126 Groningen Groningen 9718 EM",
    "addr:housenumber":"126",
    "addr:postcode":"9718 em",
    "iso:country":"NL",
    "sg:address":"Nw Blekerstr 126",
    "sg:city":"Groningen",
    "sg:orig_category":"Adviesbureaus Bedrijfsorganisatie",
    "sg:phone":"+31 6 53748608",
    "sg:postcode":"9718 EM",
    "sg:province":"Groningen",
    "wof:name":"Toxopeus",
    "wof:placetype":"venue"
},
  "geometry": {"coordinates":[6.550394,53.214855],"type":"Point"}
}