{
  "type": "Feature",
  "properties": {
    "addr:full":"Kapelstraat 4 Baarle Nassau Noord-Brabant 5111 HK",
    "addr:housenumber":"4",
    "addr:postcode":"5111 hk",
    "addr:street":"Kapelstraat",
    "iso:country":"NL",
    "sg:address":"Kapelstraat 4",
    "sg:city":"Baarle Nassau",
    "sg:orig_category":"Kappers",
    "sg:phone":"+31 13 507 7188",
    "sg:postcode":"5111 HK",
    "sg:province":"Noord-Brabant",
    "wof:name":"Kapsalon Petit",
    "wof:placetype":"venue"
},
  "geometry": {"coordinates":[4.9397611618,51.4417495728],"type":"Point"}
}