{
  "type": "Feature",
  "properties": {
    "addr:full":"J J Costerstr 3 St Annaparochie Provincie Friesland 9076 EA",
    "addr:housenumber":"3",
    "addr:postcode":"9076 ea",
    "addr:street":"St;Provincie Friesland",
    "iso:country":"NL",
    "sg:address":"J J Costerstr 3",
    "sg:city":"St Annaparochie",
    "sg:orig_category":"Psychologen",
    "sg:phone":"+31 518 403 908",
    "sg:postcode":"9076 EA",
    "sg:province":"Provincie Friesland",
    "wof:name":"Psychologenpraktijk Regio Noard",
    "wof:placetype":"venue"
},
  "geometry": {"coordinates":[5.654757,53.27483],"type":"Point"}
}