{
  "type": "Feature",
  "properties": {
    "addr:full":"Foarwei 10 Oudwoude Provincie Friesland 9294 KD",
    "addr:housenumber":"10",
    "addr:postcode":"9294 kd",
    "addr:street":"Foarwei;Provincie Friesland",
    "iso:country":"NL",
    "sg:address":"Foarwei 10",
    "sg:city":"Oudwoude",
    "sg:orig_category":"Houtgroothandel",
    "sg:phone":"+31 511 451 868",
    "sg:postcode":"9294 KD",
    "sg:province":"Provincie Friesland",
    "wof:name":"Timersma",
    "wof:placetype":"venue"
},
  "geometry": {"coordinates":[6.119513,53.279446],"type":"Point"}
}