{
  "type": "Feature",
  "properties": {
    "addr:full":"Zutphensewg 126 Eefde Gelderland 7211 EG",
    "addr:housenumber":"126",
    "addr:postcode":"7211 eg",
    "addr:street":"Gelderland",
    "iso:country":"NL",
    "sg:address":"Zutphensewg 126",
    "sg:city":"Eefde",
    "sg:orig_category":"Fietsen En Bromfietsen",
    "sg:phone":"+31 575 544 944",
    "sg:postcode":"7211 EG",
    "sg:province":"Gelderland",
    "wof:name":"Onstenk, Gertie",
    "wof:placetype":"venue"
},
  "geometry": {"coordinates":[6.223536,52.173729],"type":"Point"}
}