{
  "type": "Feature",
  "properties": {
    "iso:country":"NL",
    "sg:address":"Markendaalsewg 163",
    "sg:city":"Breda",
    "sg:orig_category":"Fotoreportages",
    "sg:phone":"+31 76 515 4911",
    "sg:postcode":"4811 KW",
    "sg:province":"Noord-Brabant",
    "wof:name":"Liempd, Bert Van",
    "wof:placetype":"venue"
},
  "geometry": {"coordinates":[4.774313,51.582996],"type":"Point"}
}