{
  "type": "Feature",
  "properties": {
    "addr:full":"Cremerstr 245 Utrecht Utrecht 3532 BJ",
    "addr:housenumber":"245",
    "addr:postcode":"3532 bj",
    "iso:country":"NL",
    "sg:address":"Cremerstr 245",
    "sg:city":"Utrecht",
    "sg:orig_category":"Verenigingen En Stichtingen",
    "sg:phone":"+31 30 293 8717",
    "sg:postcode":"3532 BJ",
    "sg:province":"Utrecht",
    "wof:name":"Emma Centrum, Sticht",
    "wof:placetype":"venue"
},
  "geometry": {"coordinates":[5.098754,52.096104],"type":"Point"}
}