{
  "type": "Feature",
  "properties": {
    "addr:full":"Hinthamerstr 86A S Hertogenbosch North Brabant 5211 MS",
    "addr:housenumber":"86a",
    "addr:postcode":"5211 ms",
    "addr:street":"Hinthamerstr;S Hertogenbosch",
    "iso:country":"NL",
    "sg:address":"Hinthamerstr 86A",
    "sg:city":"S Hertogenbosch",
    "sg:orig_category":"Zonnebank- En Solariumcentra",
    "sg:phone":"+31 73 612 3404",
    "sg:postcode":"5211 MS",
    "sg:province":"North Brabant",
    "sg:website":"http://www.sundays.nl",
    "wof:name":"Sunday'S",
    "wof:placetype":"venue"
},
  "geometry": {"coordinates":[5.309012,51.688728],"type":"Point"}
}