{
  "type": "Feature",
  "properties": {
    "addr:full":"Burg Keyzerwg 16B Papendrecht Zuid-Holland 3352 AR",
    "addr:housenumber":"16b",
    "addr:postcode":"3352",
    "addr:street":"Burg Keyzerwg",
    "iso:country":"NL",
    "sg:address":"Burg Keyzerwg 16B",
    "sg:city":"Papendrecht",
    "sg:orig_category":"Verhuur",
    "sg:phone":"+31 78 641 5646",
    "sg:postcode":"3352 AR",
    "sg:province":"Zuid-Holland",
    "sg:website":"http://www.momeproductions.com",
    "wof:name":"Mo Me Productions",
    "wof:placetype":"venue"
},
  "geometry": {"coordinates":[4.683685,51.826294],"type":"Point"}
}