{
  "type": "Feature",
  "properties": {
    "addr:full":"Boomvalk 6 Veenendaal Utrecht 3905 RJ",
    "addr:housenumber":"6",
    "addr:postcode":"3905 rj",
    "addr:street":"Boomvalk",
    "iso:country":"NL",
    "sg:address":"Boomvalk 6",
    "sg:city":"Veenendaal",
    "sg:orig_category":"Juridische Dienstverlening",
    "sg:phone":"+31 318 561 609",
    "sg:postcode":"3905 RJ",
    "sg:province":"Utrecht",
    "wof:name":"Adviesbureau In Overheidsgeschillen V'Da",
    "wof:placetype":"venue"
},
  "geometry": {"coordinates":[5.536723,52.028744],"type":"Point"}
}