{
  "type": "Feature",
  "properties": {
    "iso:country":"NL",
    "sg:address":"Vresselse Akkers 7",
    "sg:city":"Sint Oedenrode",
    "sg:orig_category":"Kampeerterreinen",
    "sg:phone":"+31 499 476 733",
    "sg:postcode":"5491 PG",
    "sg:province":"Noord-Brabant",
    "wof:name":"T Vressels Bos",
    "wof:placetype":"venue"
},
  "geometry": {"coordinates":[5.5117821693,51.5380172729],"type":"Point"}
}