{
  "type": "Feature",
  "properties": {
    "addr:full":"Johan Braakensiekhof 27 Amsterdam Noord-Holland 1068 KK",
    "addr:housenumber":"27",
    "addr:postcode":"1068 kk",
    "addr:street":"Johan Braakensiekhof",
    "iso:country":"NL",
    "sg:address":"Johan Braakensiekhof 27",
    "sg:city":"Amsterdam",
    "sg:orig_category":"Makelaars In Onroerend Goed",
    "sg:phone":"+31 20 610 9413",
    "sg:postcode":"1068 KK",
    "sg:province":"Noord-Holland",
    "wof:name":"E.A.J. Van Deene",
    "wof:placetype":"venue"
},
  "geometry": {"coordinates":[4.815578,52.351952],"type":"Point"}
}