{
  "type": "Feature",
  "properties": {
    "addr:full":"Steenbokstr 9 Haarlem North Holland 2024 RH",
    "addr:housenumber":"9",
    "addr:postcode":"2024 rh",
    "addr:street":"Steenbokstr",
    "iso:country":"NL",
    "sg:address":"Steenbokstr 9",
    "sg:city":"Haarlem",
    "sg:orig_category":"Onderhoudswerken",
    "sg:phone":"+31 23 526 5769",
    "sg:postcode":"2024 RH",
    "sg:province":"North Holland",
    "wof:name":"Mitch",
    "wof:placetype":"venue"
},
  "geometry": {"coordinates":[4.635898,52.404709],"type":"Point"}
}