{
  "type": "Feature",
  "properties": {
    "addr:full":"Weth V Haperenstr 36 Breda North Brabant 4813 AM",
    "addr:housenumber":"36",
    "addr:postcode":"4813",
    "addr:street":"Weth V Haperenstr",
    "iso:country":"NL",
    "sg:address":"Weth V Haperenstr 36",
    "sg:city":"Breda",
    "sg:orig_category":"Koeriersdiensten",
    "sg:phone":"+31 76 522 6360",
    "sg:postcode":"4813 AM",
    "sg:province":"North Brabant",
    "wof:name":"Vite Transport Bv",
    "wof:placetype":"venue"
},
  "geometry": {"coordinates":[4.771685,51.591351],"type":"Point"}
}