{
  "type": "Feature",
  "properties": {
    "addr:full":"Hortensiastr 11 S Gravenpolder Zeeland 4431 EA",
    "addr:housenumber":"11",
    "addr:postcode":"4431 ea",
    "addr:street":"Hortensiastr;S Gravenpolder Zeeland",
    "iso:country":"NL",
    "sg:address":"Hortensiastr 11",
    "sg:city":"S Gravenpolder",
    "sg:classifiers":[
        {
            "category":"Personal",
            "subcategory":"Nail Salon",
            "type":"Services"
        }
    ],
    "sg:phone":"+31 113 312 918",
    "sg:postcode":"4431 EA",
    "sg:province":"Zeeland",
    "sg:tags":[
        "pedicure"
    ],
    "wof:name":"Stokx, J A",
    "wof:placetype":"venue"
},
  "geometry": {"coordinates":[3.909943,51.458374],"type":"Point"}
}