{
  "type": "Feature",
  "properties": {
    "addr:full":"Friesestraat 10 Coevorden Drenthe 7741 GV",
    "addr:housenumber":"10",
    "addr:postcode":"7741 gv",
    "addr:street":"Friesestraat",
    "iso:country":"NL",
    "sg:address":"Friesestraat 10",
    "sg:city":"Coevorden",
    "sg:orig_category":"Bloemen And Planten",
    "sg:phone":"+31 524 518 110",
    "sg:postcode":"7741 GV",
    "sg:province":"Drenthe",
    "wof:name":"T Klavertje Vier",
    "wof:placetype":"venue"
},
  "geometry": {"coordinates":[6.740067,52.661461],"type":"Point"}
}