{
  "type": "Feature",
  "properties": {
    "iso:country":"NL",
    "sg:address":"Bos En Lommerwg 232 Zaak",
    "sg:city":"Amsterdam",
    "sg:classifiers":[
        {
            "category":"Farming",
            "subcategory":"Fish & Marine Products",
            "type":"Manufacturing & Wholesale Goods"
        }
    ],
    "sg:phone":"+31 20 684 3897",
    "sg:postcode":"1055 EJ",
    "sg:province":"Noord-Holland",
    "sg:tags":[
        "vi"
    ],
    "wof:name":"Molenaar, Fa Gebr",
    "wof:placetype":"venue"
},
  "geometry": {"coordinates":[4.85337,52.380409],"type":"Point"}
}