{
  "type": "Feature",
  "properties": {
    "addr:full":"Postbus 204 Leek Groningen 9350 AE",
    "addr:housenumber":"204",
    "addr:postcode":"9350 ae",
    "addr:street":"Postbus",
    "iso:country":"NL",
    "sg:address":"Postbus 204",
    "sg:city":"Leek",
    "sg:orig_category":"Verenigingen En Stichtingen",
    "sg:phone":"+31 594 513 319",
    "sg:postcode":"9350 AE",
    "sg:province":"Groningen",
    "wof:name":"Samuel Levie, Sticht",
    "wof:placetype":"venue"
},
  "geometry": {"coordinates":[6.392695,53.162521],"type":"Point"}
}