{
  "type": "Feature",
  "properties": {
    "addr:full":"Schepel 6 Wierden Overijssel 7641 JG",
    "addr:housenumber":"6",
    "addr:postcode":"7641 jg",
    "addr:street":"Schepel",
    "iso:country":"NL",
    "sg:address":"Schepel 6",
    "sg:city":"Wierden",
    "sg:orig_category":"Adviesbureaus Bedrijfsorganisatie",
    "sg:phone":"+31 546 575 042",
    "sg:postcode":"7641 JG",
    "sg:province":"Overijssel",
    "sg:website":"http://www.bcoin.nl",
    "wof:name":"Bcoin",
    "wof:placetype":"venue"
},
  "geometry": {"coordinates":[6.602892,52.365623],"type":"Point"}
}