{
  "type": "Feature",
  "properties": {
    "addr:full":"Riksingenstr 19 Maastricht Limburg 6215 KJ",
    "addr:housenumber":"19",
    "addr:postcode":"6215 kj",
    "addr:street":"Riksingenstr",
    "iso:country":"NL",
    "sg:address":"Riksingenstr 19",
    "sg:city":"Maastricht",
    "sg:orig_category":"Onderhoudswerken",
    "sg:phone":"+31 43 347 8233",
    "sg:postcode":"6215 KJ",
    "sg:province":"Limburg",
    "wof:name":"Bank, P & P",
    "wof:placetype":"venue"
},
  "geometry": {"coordinates":[5.648638,50.84499],"type":"Point"}
}