{
  "type": "Feature",
  "properties": {
    "addr:full":"Eemstraat 42 Den Helder North Holland 1784 CE",
    "addr:housenumber":"42",
    "addr:postcode":"1784 ce",
    "addr:street":"Eemstraat",
    "iso:country":"NL",
    "sg:address":"Eemstraat 42",
    "sg:city":"Den Helder",
    "sg:orig_category":"Kinderopvang Behalve Thuis",
    "sg:phone":"+31 223 636 997",
    "sg:postcode":"1784 CE",
    "sg:province":"North Holland",
    "wof:name":"De Troubadour Dagverblijf Voor Verst. Gehandicapte",
    "wof:placetype":"venue"
},
  "geometry": {"coordinates":[4.74464,52.941238],"type":"Point"}
}