{
  "type": "Feature",
  "properties": {
    "addr:full":"Kortenhoevensewg 38 Lexmond Zuid-Holland 4128 CR",
    "addr:housenumber":"38",
    "addr:postcode":"4128 cr",
    "addr:street":"Kortenhoevensewg",
    "iso:country":"NL",
    "sg:address":"Kortenhoevensewg 38",
    "sg:city":"Lexmond",
    "sg:orig_category":"Autoschade- Herstelbedrijven",
    "sg:phone":"+31 347 342 190",
    "sg:postcode":"4128 CR",
    "sg:province":"Zuid-Holland",
    "wof:name":"Autoschade Lexmond",
    "wof:placetype":"venue"
},
  "geometry": {"coordinates":[5.040546,51.963703],"type":"Point"}
}