{
  "type": "Feature",
  "properties": {
    "addr:full":"Beekstraat 77 Arnhem Gelderland 6811 DX",
    "addr:housenumber":"77",
    "addr:postcode":"6811 dx",
    "addr:street":"Beekstraat",
    "iso:country":"NL",
    "sg:address":"Beekstraat 77",
    "sg:city":"Arnhem",
    "sg:orig_category":"Meubelzaken, Woning- And Keukeninrichting",
    "sg:phone":"+31 26 442 5108",
    "sg:postcode":"6811 DX",
    "sg:province":"Gelderland",
    "sg:website":"http://www.damminga.nl",
    "wof:name":"Slaapkenner Damminga",
    "wof:placetype":"venue"
},
  "geometry": {"coordinates":[5.911461,51.980904],"type":"Point"}
}