{
  "type": "Feature",
  "properties": {
    "iso:country":"NL",
    "sg:address":"Leewg 31",
    "sg:city":"Berkel En Rodenrys",
    "sg:orig_category":"Grondwerken",
    "sg:phone":"+31 10 511 3777",
    "sg:postcode":"2651 CL",
    "sg:province":"Zuid-Holland",
    "wof:name":"Etten Bv, J Van",
    "wof:placetype":"venue"
},
  "geometry": {"coordinates":[4.457098,51.995071],"type":"Point"}
}