{
  "type": "Feature",
  "properties": {
    "addr:full":"Koekoekweg 69 Hengelo Ov Overijssel 7557 PG",
    "addr:housenumber":"69",
    "addr:postcode":"7557 pg",
    "addr:street":"Koekoekweg;Ov",
    "iso:country":"NL",
    "sg:address":"Koekoekweg 69",
    "sg:city":"Hengelo Ov",
    "sg:orig_category":"Fotostudio'S And Fotografen",
    "sg:phone":"+31 74 242 1101",
    "sg:postcode":"7557 PG",
    "sg:province":"Overijssel",
    "wof:name":"Studio Kapar",
    "wof:placetype":"venue"
},
  "geometry": {"coordinates":[6.805837,52.269043],"type":"Point"}
}