{
  "type": "Feature",
  "properties": {
    "addr:full":"Cruquiuswg 178 Heemstede North Holland 2103 LW",
    "addr:housenumber":"178",
    "addr:postcode":"2103 lw",
    "iso:country":"NL",
    "sg:address":"Cruquiuswg 178",
    "sg:city":"Heemstede",
    "sg:orig_category":"Wasmachines En Wasdrogers - Onderhoud En Reparatie",
    "sg:phone":"+31 23 547 6975",
    "sg:postcode":"2103 LW",
    "sg:province":"North Holland",
    "wof:name":"Dennis Vollenga Technische Dienst",
    "wof:placetype":"venue"
},
  "geometry": {"coordinates":[4.6330938339,52.341468811],"type":"Point"}
}