{
  "type": "Feature",
  "properties": {
    "addr:full":"Florawg 119 Roelofarendsveen South Holland 2371 AR",
    "addr:housenumber":"119",
    "addr:postcode":"2371",
    "iso:country":"NL",
    "sg:address":"Florawg 119",
    "sg:city":"Roelofarendsveen",
    "sg:orig_category":"Bloemen En Planten - Groothandel",
    "sg:phone":"+31 71 331 7090",
    "sg:postcode":"2371 AR",
    "sg:province":"South Holland",
    "wof:name":"Bakker Bv, Jac",
    "wof:placetype":"venue"
},
  "geometry": {"coordinates":[4.619356,52.184566],"type":"Point"}
}