{
  "type": "Feature",
  "properties": {
    "addr:full":"Irenelaan 8 Haren Gn Groningen 9752 LS",
    "addr:housenumber":"8",
    "addr:postcode":"9752 ls",
    "addr:street":"Irenelaan",
    "iso:country":"NL",
    "sg:address":"Irenelaan 8",
    "sg:city":"Haren Gn",
    "sg:orig_category":"Farmaceutische Producten Gh",
    "sg:phone":"+31 50 534 9508",
    "sg:postcode":"9752 LS",
    "sg:province":"Groningen",
    "wof:name":"Inter-Act",
    "wof:placetype":"venue"
},
  "geometry": {"coordinates":[6.604503,53.167442],"type":"Point"}
}