{
  "type": "Feature",
  "properties": {
    "addr:full":"J De Raadtkd 47 Hoogvliet Rt South Holland 3191 VJ",
    "addr:housenumber":"47",
    "addr:postcode":"3191 vj",
    "addr:street":"J De Raadtkd;Rt South",
    "iso:country":"NL",
    "sg:address":"J De Raadtkd 47",
    "sg:city":"Hoogvliet Rt",
    "sg:orig_category":"Kunsthandel",
    "sg:phone":"+31 10 295 7557",
    "sg:postcode":"3191 VJ",
    "sg:province":"South Holland",
    "wof:name":"Kunst Op Maat",
    "wof:placetype":"venue"
},
  "geometry": {"coordinates":[4.3655,51.861012],"type":"Point"}
}