{
  "type": "Feature",
  "properties": {
    "iso:country":"NL",
    "sg:address":"Rynlanderwg 799",
    "sg:city":"Hoofddorp",
    "sg:orig_category":"Bloemen En Planten - Groothandel",
    "sg:phone":"+31 20 653 3893",
    "sg:postcode":"2132 NK",
    "sg:province":"Noord-Holland",
    "wof:name":"Koeckhoven Bv",
    "wof:placetype":"venue"
},
  "geometry": {"coordinates":[4.723214,52.299217],"type":"Point"}
}