{
  "type": "Feature",
  "properties": {
    "addr:full":"Op De Grensberg 5 Venlo Limburg 5916 KA",
    "addr:housenumber":"5",
    "addr:postcode":"5916 ka",
    "addr:street":"Op De Grensberg",
    "iso:country":"NL",
    "sg:address":"Op De Grensberg 5",
    "sg:city":"Venlo",
    "sg:orig_category":"Kappers",
    "sg:phone":"+31 77 352 1820",
    "sg:postcode":"5916 KA",
    "sg:province":"Limburg",
    "wof:name":"Jacqueline Hermsen",
    "wof:placetype":"venue"
},
  "geometry": {"coordinates":[6.2030482292,51.3764228821],"type":"Point"}
}