{
  "type": "Feature",
  "properties": {
    "addr:full":"Marktpln 2 Uithoorn Noord-Holland 1421 AC",
    "addr:housenumber":"2",
    "addr:postcode":"1421 ac",
    "addr:street":"Marktpln",
    "iso:country":"NL",
    "sg:address":"Marktpln 2",
    "sg:city":"Uithoorn",
    "sg:orig_category":"Architecten En Architectenbureaus",
    "sg:phone":"+31 297 564 151",
    "sg:postcode":"1421 AC",
    "sg:province":"Noord-Holland",
    "wof:name":"Zanger + Dane, Architekten Bna De",
    "wof:placetype":"venue"
},
  "geometry": {"coordinates":[4.832309,52.233021],"type":"Point"}
}