{
  "type": "Feature",
  "properties": {
    "addr:full":"Haarstraat 4 Rijssen NL.08 7462 AP",
    "addr:housenumber":"4;nl.08",
    "addr:postcode":"7462 ap",
    "addr:street":"Haarstraat",
    "iso:country":"NL",
    "sg:address":"Haarstraat 4",
    "sg:city":"Rijssen",
    "sg:orig_category":"Juweliers",
    "sg:phone":"+31 548 512 679",
    "sg:postcode":"7462 AP",
    "sg:province":"NL.08",
    "wof:name":"Muller'S Horlogerie",
    "wof:placetype":"venue"
},
  "geometry": {"coordinates":[6.520178,52.307941],"type":"Point"}
}