{
  "type": "Feature",
  "properties": {
    "iso:country":"NL",
    "sg:address":"Noordlangewg 6",
    "sg:city":"Dinteloord",
    "sg:orig_category":"Tuinaanleg En -Onderhoud",
    "sg:phone":"+31 167 521 039",
    "sg:postcode":"4671 PK",
    "sg:province":"Noord-Brabant",
    "wof:name":"Amber",
    "wof:placetype":"venue"
},
  "geometry": {"coordinates":[4.36698,51.627323],"type":"Point"}
}