{
  "type": "Feature",
  "properties": {
    "iso:country":"NL",
    "sg:address":"Oranjesingel 21",
    "sg:city":"Nijmegen",
    "sg:orig_category":"Makelaars In Onroerend Goed",
    "sg:phone":"+31 24 360 6900",
    "sg:postcode":"6511 NM",
    "sg:province":"Gelderland",
    "wof:name":"Beaufort Payens Makelaardij Bv",
    "wof:placetype":"venue"
},
  "geometry": {"coordinates":[5.863997,51.841812],"type":"Point"}
}