{
  "type": "Feature",
  "properties": {
    "addr:full":"Roerdompstr 35 Wormer Noord-Holland 1531 XE",
    "addr:housenumber":"35",
    "addr:postcode":"1531 xe",
    "addr:street":"Roerdompstr",
    "iso:country":"NL",
    "sg:address":"Roerdompstr 35",
    "sg:city":"Wormer",
    "sg:orig_category":"Mensendieck - Oefentherapeuten",
    "sg:phone":"+31 75 642 6265",
    "sg:postcode":"1531 XE",
    "sg:province":"Noord-Holland",
    "wof:name":"Annette Booiman En Loekie Stevens",
    "wof:placetype":"venue"
},
  "geometry": {"coordinates":[4.815506,52.500893],"type":"Point"}
}