{
  "type": "Feature",
  "properties": {
    "iso:country":"NL",
    "sg:address":"Goudsesngl 97",
    "sg:city":"Rotterdam",
    "sg:orig_category":"Postkantoren",
    "sg:phone":"+31 10 413 6328",
    "sg:postcode":"3031 EE",
    "sg:province":"South Holland",
    "sg:website":"http://www.postkantoor.nl",
    "wof:name":"Postkantoor",
    "wof:placetype":"venue"
},
  "geometry": {"coordinates":[4.49056,51.926991],"type":"Point"}
}