{
  "type": "Feature",
  "properties": {
    "addr:full":"Zorgvlietstr 209 Breda North Brabant 4834 NB",
    "addr:housenumber":"209",
    "addr:postcode":"4834 nb",
    "iso:country":"NL",
    "sg:address":"Zorgvlietstr 209",
    "sg:city":"Breda",
    "sg:orig_category":"Grafisch Ontwerpers",
    "sg:phone":"+31 76 565 6236",
    "sg:postcode":"4834 NB",
    "sg:province":"North Brabant",
    "wof:name":"Graphic Jam",
    "wof:placetype":"venue"
},
  "geometry": {"coordinates":[4.811641,51.57357],"type":"Point"}
}