{
  "type": "Feature",
  "properties": {
    "addr:full":"St Jorisstr 17 S Hertogenbosch Noord-Brabant 5211 HA",
    "addr:housenumber":"17",
    "addr:postcode":"5211 ha",
    "addr:street":"S",
    "iso:country":"NL",
    "sg:address":"St Jorisstr 17",
    "sg:city":"S Hertogenbosch",
    "sg:orig_category":"Journalisten Freelance",
    "sg:phone":"+31 73 614 4989",
    "sg:postcode":"5211 HA",
    "sg:province":"Noord-Brabant",
    "wof:name":"Kersten, Scarlett",
    "wof:placetype":"venue"
},
  "geometry": {"coordinates":[5.30144,51.686131],"type":"Point"}
}