{
  "type": "Feature",
  "properties": {
    "addr:full":"Lommelsedijk 42 Luyksgestel North Brabant 5575 XD",
    "addr:housenumber":"42",
    "addr:postcode":"5575 xd",
    "addr:street":"Lommelsedijk",
    "iso:country":"NL",
    "sg:address":"Lommelsedijk 42",
    "sg:city":"Luyksgestel",
    "sg:orig_category":"Houtverwerking",
    "sg:phone":"+31 497 542 370",
    "sg:postcode":"5575 XD",
    "sg:province":"North Brabant",
    "wof:name":"Rondhouthandel Van Diepenbeek",
    "wof:placetype":"venue"
},
  "geometry": {"coordinates":[5.315654,51.267765],"type":"Point"}
}