{
  "type": "Feature",
  "properties": {
    "iso:country":"NL",
    "sg:address":"Postbus 149",
    "sg:city":"Lochem",
    "sg:orig_category":"Binnenhuisarchitectuur",
    "sg:phone":"+31 573 257 185",
    "sg:postcode":"7240 AC",
    "sg:province":"Gelderland",
    "wof:name":"Rietbergen, Karin",
    "wof:placetype":"venue"
},
  "geometry": {"coordinates":[6.4098358154,52.1628723145],"type":"Point"}
}