{
  "type": "Feature",
  "properties": {
    "addr:full":"Karel Doormanlaan 116 Hilversum Noord-Holland 1215 NR",
    "addr:housenumber":"116",
    "addr:postcode":"1215 nr",
    "addr:street":"Karel Doormanlaan",
    "iso:country":"NL",
    "sg:address":"Karel Doormanlaan 116",
    "sg:city":"Hilversum",
    "sg:orig_category":"Elektronische Bedrijfsinstallaties",
    "sg:phone":"+31 35 621 6901",
    "sg:postcode":"1215 NR",
    "sg:province":"Noord-Holland",
    "wof:name":"Bon Services",
    "wof:placetype":"venue"
},
  "geometry": {"coordinates":[5.156476,52.211823],"type":"Point"}
}