{
  "type": "Feature",
  "properties": {
    "addr:full":"Markt 61 Maastricht Limburg 6211 CL",
    "addr:housenumber":"61",
    "addr:postcode":"6211",
    "addr:street":"Markt",
    "iso:country":"NL",
    "sg:address":"Markt 61",
    "sg:city":"Maastricht",
    "sg:orig_category":"Vertaalbureaus",
    "sg:phone":"+31 43 321 8570",
    "sg:postcode":"6211 CL",
    "sg:province":"Limburg",
    "wof:name":"Bollen, M",
    "wof:placetype":"venue"
},
  "geometry": {"coordinates":[5.69188,50.850891],"type":"Point"}
}