{
  "type": "Feature",
  "properties": {
    "addr:full":"Brongouw 145 Almere Flevoland 1352 EN",
    "addr:housenumber":"145",
    "addr:postcode":"1352 en",
    "addr:street":"Brongouw;Flevoland",
    "iso:country":"NL",
    "sg:address":"Brongouw 145",
    "sg:city":"Almere",
    "sg:orig_category":"Film-, Tv- And Videoproductie",
    "sg:phone":"+31 36 535 5202",
    "sg:postcode":"1352 EN",
    "sg:province":"Flevoland",
    "wof:name":"Lemon",
    "wof:placetype":"venue"
},
  "geometry": {"coordinates":[5.214496,52.344669],"type":"Point"}
}