{
  "type": "Feature",
  "properties": {
    "addr:full":"Grote Tiende 4 Kruisland Noord-Brabant 4756 CC",
    "addr:housenumber":"4",
    "addr:postcode":"4756 cc",
    "addr:street":"Grote Tiende",
    "iso:country":"NL",
    "sg:address":"Grote Tiende 4",
    "sg:city":"Kruisland",
    "sg:orig_category":"Alternatieve Geneeskunde",
    "sg:phone":"+31 167 532 878",
    "sg:postcode":"4756 CC",
    "sg:province":"Noord-Brabant",
    "wof:name":"Schoonheidsstudio Hanneke Gommeren",
    "wof:placetype":"venue"
},
  "geometry": {"coordinates":[4.410204,51.56863],"type":"Point"}
}