{
  "type": "Feature",
  "properties": {
    "addr:full":"Rijksweg 4 Gulpen Limburg 6271 AE",
    "addr:housenumber":"4",
    "addr:postcode":"6271 ae",
    "addr:street":"Rijksweg",
    "iso:country":"NL",
    "sg:address":"Rijksweg 4",
    "sg:city":"Gulpen",
    "sg:orig_category":"Banken And Kredietinstellingen",
    "sg:phone":"+31 43 450 5600",
    "sg:postcode":"6271 AE",
    "sg:province":"Limburg",
    "wof:name":"Rabobank",
    "wof:placetype":"venue"
},
  "geometry": {"coordinates":[5.889172,50.813931],"type":"Point"}
}