{
  "type": "Feature",
  "properties": {
    "iso:country":"NL",
    "sg:address":"Orlyplein 119",
    "sg:city":"Amsterdam",
    "sg:orig_category":"Boekenuitgeverijen",
    "sg:phone":"+31 20 686 6039",
    "sg:postcode":"1043 DT",
    "sg:province":"North Holland",
    "wof:name":"Ako Bv",
    "wof:placetype":"venue"
},
  "geometry": {"coordinates":[4.836964,52.38876],"type":"Point"}
}