{
  "type": "Feature",
  "properties": {
    "addr:full":"Lindeln 27 Delft South Holland 2612 VH",
    "addr:housenumber":"27",
    "addr:postcode":"2612 vh",
    "addr:street":"Lindeln",
    "iso:country":"NL",
    "sg:address":"Lindeln 27",
    "sg:city":"Delft",
    "sg:orig_category":"Kinderkleding",
    "sg:phone":"+31 15 212 8484",
    "sg:postcode":"2612 VH",
    "sg:province":"South Holland",
    "wof:name":"Swing, De",
    "wof:placetype":"venue"
},
  "geometry": {"coordinates":[4.364836,52.018326],"type":"Point"}
}