{
  "type": "Feature",
  "properties": {
    "addr:full":"Haarlemmerstr 172 Leiden Zuid-Holland 2312 GG",
    "addr:housenumber":"172",
    "addr:postcode":"2312 gg",
    "iso:country":"NL",
    "sg:address":"Haarlemmerstr 172",
    "sg:city":"Leiden",
    "sg:orig_category":"Kinderkleding",
    "sg:phone":"+31 71 566 3304",
    "sg:postcode":"2312 GG",
    "sg:province":"Zuid-Holland",
    "wof:name":"Hennes & Mauritz",
    "wof:placetype":"venue"
},
  "geometry": {"coordinates":[4.494025,52.160332],"type":"Point"}
}