{
  "type": "Feature",
  "properties": {
    "addr:full":"Paulus Potterstraat 5 Zelhem Gelderland 7021 DZ",
    "addr:housenumber":"5",
    "addr:postcode":"7021 dz",
    "addr:street":"Paulus Potterstraat;Gelderland",
    "iso:country":"NL",
    "sg:address":"Paulus Potterstraat 5",
    "sg:city":"Zelhem",
    "sg:orig_category":"Boekhouders",
    "sg:phone":"+31 314 621 920",
    "sg:postcode":"7021 DZ",
    "sg:province":"Gelderland",
    "wof:name":"G.J. Maalderink",
    "wof:placetype":"venue"
},
  "geometry": {"coordinates":[6.359098,52.009232],"type":"Point"}
}