{
  "type": "Feature",
  "properties": {
    "addr:full":"Jan Ligthartstraat 39 Rotterdam Zuid-Holland 3083 AL",
    "addr:housenumber":"39",
    "addr:postcode":"3083 al",
    "addr:street":"Jan Ligthartstraat",
    "iso:country":"NL",
    "sg:address":"Jan Ligthartstraat 39",
    "sg:city":"Rotterdam",
    "sg:orig_category":"Drukkerijen And Copyshops",
    "sg:phone":"+31 10 290 7722",
    "sg:postcode":"3083 AL",
    "sg:province":"Zuid-Holland",
    "wof:name":"Vof Drukkerij Groenewegen",
    "wof:placetype":"venue"
},
  "geometry": {"coordinates":[4.497236,51.88599],"type":"Point"}
}