{
  "type": "Feature",
  "properties": {
    "addr:full":"Kemperstr 2 Hoogeveen Drenthe 7901 CB",
    "addr:housenumber":"2",
    "addr:postcode":"7901 cb",
    "addr:street":"Kemperstr",
    "iso:country":"NL",
    "sg:address":"Kemperstr 2",
    "sg:city":"Hoogeveen",
    "sg:orig_category":"Bejaarden - Verzorgingstehuizen",
    "sg:phone":"+31 528 263 288",
    "sg:postcode":"7901 CB",
    "sg:province":"Drenthe",
    "wof:name":"Olden Kinholt",
    "wof:placetype":"venue"
},
  "geometry": {"coordinates":[6.473083,52.727745],"type":"Point"}
}