{
  "type": "Feature",
  "properties": {
    "addr:full":"Havikskruid 13 Diemen North Holland 1112 NG",
    "addr:housenumber":"13",
    "addr:postcode":"1112 ng",
    "addr:street":"Havikskruid",
    "iso:country":"NL",
    "sg:address":"Havikskruid 13",
    "sg:city":"Diemen",
    "sg:orig_category":"Fotografie Reclame En Mode",
    "sg:phone":"+31 20 699 3507",
    "sg:postcode":"1112 NG",
    "sg:province":"North Holland",
    "wof:name":"Schaftenaar, J",
    "wof:placetype":"venue"
},
  "geometry": {"coordinates":[4.955452,52.333633],"type":"Point"}
}