{
  "type": "Feature",
  "properties": {
    "addr:full":"Nw Markt 11 Roosendaal Noord-Brabant 4701 AA",
    "addr:housenumber":"11",
    "addr:postcode":"4701 aa",
    "addr:street":"Markt",
    "iso:country":"NL",
    "sg:address":"Nw Markt 11",
    "sg:city":"Roosendaal",
    "sg:orig_category":"Schoenen",
    "sg:phone":"+31 165 571 875",
    "sg:postcode":"4701 AA",
    "sg:province":"Noord-Brabant",
    "wof:name":"Haren Bv, Van",
    "wof:placetype":"venue"
},
  "geometry": {"coordinates":[4.456019,51.531822],"type":"Point"}
}