{
  "type": "Feature",
  "properties": {
    "iso:country":"NL",
    "sg:address":"H Bulthuiswg 11-13",
    "sg:city":"Sneek",
    "sg:orig_category":"Scheepsstofferingen",
    "sg:phone":"+31 515 420 007",
    "sg:postcode":"8606 KB",
    "sg:province":"Friesland",
    "sg:website":"http://www.jaarsmasilvius.nl",
    "wof:name":"Jaarsma & Silvius Scheepsstoff",
    "wof:placetype":"venue"
},
  "geometry": {"coordinates":[5.698177,53.020767],"type":"Point"}
}