{
  "type": "Feature",
  "properties": {
    "iso:country":"NL",
    "sg:address":"Hg Molenstr 13",
    "sg:city":"Zierikzee",
    "sg:orig_category":"Bejaarden - Verzorgingstehuizen",
    "sg:phone":"+31 111 416 455",
    "sg:postcode":"4301 KB",
    "sg:province":"Zeeland",
    "wof:name":"Wieken, De",
    "wof:placetype":"venue"
},
  "geometry": {"coordinates":[3.921381,51.6506],"type":"Point"}
}