{
  "type": "Feature",
  "properties": {
    "addr:full":"Venenwg 19 Zwanenburg Noord-Holland 1161 AK",
    "addr:housenumber":"19",
    "addr:postcode":"1161 ak",
    "addr:street":"Venenwg",
    "iso:country":"NL",
    "sg:address":"Venenwg 19",
    "sg:city":"Zwanenburg",
    "sg:orig_category":"Medische Installaties En Instrumenten",
    "sg:phone":"+31 20 497 6252",
    "sg:postcode":"1161 AK",
    "sg:province":"Noord-Holland",
    "wof:name":"Mainit",
    "wof:placetype":"venue"
},
  "geometry": {"coordinates":[4.737902,52.381874],"type":"Point"}
}