{
  "type": "Feature",
  "properties": {
    "addr:full":"Grondmolen 19 Vianen Zh South Holland 4133 EB",
    "addr:housenumber":"19",
    "addr:postcode":"zh;4133 eb",
    "addr:street":"Grondmolen",
    "iso:country":"NL",
    "sg:address":"Grondmolen 19",
    "sg:city":"Vianen Zh",
    "sg:orig_category":"Autorijscholen",
    "sg:phone":"+31 347 373 445",
    "sg:postcode":"4133 EB",
    "sg:province":"South Holland",
    "wof:name":"Woudenberg, F H Van",
    "wof:placetype":"venue"
},
  "geometry": {"coordinates":[5.077695,51.985683],"type":"Point"}
}