{
  "type": "Feature",
  "properties": {
    "addr:full":"Wilhelminalaan 12 'S Gravenmoer Noord-Brabant 5109 AG",
    "addr:housenumber":"12",
    "addr:postcode":"gravenmoer;5109",
    "addr:street":"Wilhelminalaan;S",
    "iso:country":"NL",
    "sg:address":"Wilhelminalaan 12",
    "sg:city":"'S Gravenmoer",
    "sg:orig_category":"Sportclubs",
    "sg:phone":"+31 162 322 117",
    "sg:postcode":"5109 AG",
    "sg:province":"Noord-Brabant",
    "wof:name":"Sv Capelle",
    "wof:placetype":"venue"
},
  "geometry": {"coordinates":[4.933341,51.650932],"type":"Point"}
}