{
  "type": "Feature",
  "properties": {
    "addr:full":"Leuvenlaan 59 Maastricht Limburg 6229 GX",
    "addr:housenumber":"59",
    "addr:postcode":"6229 gx",
    "addr:street":"Leuvenlaan",
    "iso:country":"NL",
    "sg:address":"Leuvenlaan 59",
    "sg:city":"Maastricht",
    "sg:orig_category":"Verzekeringen",
    "sg:phone":"+31 43 361 8888",
    "sg:postcode":"6229 GX",
    "sg:province":"Limburg",
    "wof:name":"Reinders Assurantiegroep",
    "wof:placetype":"venue"
},
  "geometry": {"coordinates":[5.706929,50.83614],"type":"Point"}
}