{
  "type": "Feature",
  "properties": {
    "iso:country":"NL",
    "sg:address":"Purmerweg 19",
    "sg:city":"Purmerend",
    "sg:orig_category":"Boekhouders",
    "sg:phone":"+31 299 420 870",
    "sg:postcode":"1441 RA",
    "sg:province":"Noord-Holland",
    "wof:name":"Administratiekantoor Avanti Advisering",
    "wof:placetype":"venue"
},
  "geometry": {"coordinates":[4.964548,52.504028],"type":"Point"}
}