{
  "type": "Feature",
  "properties": {
    "iso:country":"NL",
    "sg:address":"Lemmeraak 9",
    "sg:city":"Bergen Op Zoom",
    "sg:orig_category":"Psychotherapeuten",
    "sg:phone":"+31 164 249 300",
    "sg:postcode":"4617 GK",
    "sg:province":"Noord-Brabant",
    "sg:website":"http://www.ptpc.nl",
    "wof:name":"Corten, Psychotherapiepraktijk",
    "wof:placetype":"venue"
},
  "geometry": {"coordinates":[4.268633,51.480831],"type":"Point"}
}