{
  "type": "Feature",
  "properties": {
    "iso:country":"NL",
    "sg:address":"Burg Hoogenboomln 50",
    "sg:city":"Hoogwoud",
    "sg:orig_category":"Juweliers",
    "sg:phone":"+31 226 351 606",
    "sg:postcode":"1718 BK",
    "sg:province":"Noord-Holland",
    "wof:name":"C. Bakker",
    "wof:placetype":"venue"
},
  "geometry": {"coordinates":[4.937709,52.718155],"type":"Point"}
}