{
  "type": "Feature",
  "properties": {
    "addr:full":"Burg Hoogenboomln 50 Hoogwoud Noord-Holland 1718 BK",
    "addr:housenumber":"50",
    "addr:postcode":"1718 bk",
    "addr:street":"Burg",
    "iso:country":"NL",
    "sg:address":"Burg Hoogenboomln 50",
    "sg:city":"Hoogwoud",
    "sg:orig_category":"Juweliers",
    "sg:phone":"+31 226 351 606",
    "sg:postcode":"1718 BK",
    "sg:province":"Noord-Holland",
    "wof:name":"C. Bakker",
    "wof:placetype":"venue"
},
  "geometry": {"coordinates":[4.937709,52.718155],"type":"Point"}
}