{
  "type": "Feature",
  "properties": {
    "addr:full":"Oude Graaf 6 Weert Limburg 6002 NL",
    "addr:housenumber":"6",
    "addr:postcode":"6002 nl",
    "addr:street":"Oude Graaf",
    "iso:country":"NL",
    "sg:address":"Oude Graaf 6",
    "sg:city":"Weert",
    "sg:orig_category":"Meubelen - Fabrieken En Groothandel",
    "sg:phone":"+31 495 625 888",
    "sg:postcode":"6002 NL",
    "sg:province":"Limburg",
    "wof:name":"Klooster, Van 'T",
    "wof:placetype":"venue"
},
  "geometry": {"coordinates":[5.659202,51.244717],"type":"Point"}
}