{
  "type": "Feature",
  "properties": {
    "addr:full":"Kerkstr 6 Hattem Gelderland 8051 GL",
    "addr:housenumber":"6",
    "addr:postcode":"8051 gl",
    "addr:street":"Kerkstr;Gelderland",
    "iso:country":"NL",
    "sg:address":"Kerkstr 6",
    "sg:city":"Hattem",
    "sg:orig_category":"Herenkleding",
    "sg:phone":"+31 38 444 2754",
    "sg:postcode":"8051 GL",
    "sg:province":"Gelderland",
    "wof:name":"Manhattem",
    "wof:placetype":"venue"
},
  "geometry": {"coordinates":[6.069248,52.474632],"type":"Point"}
}