{
  "type": "Feature",
  "properties": {
    "addr:full":"Terneuzensestr 62A Zaamslag Zeeland 4543 BP",
    "addr:housenumber":"62a",
    "addr:postcode":"4543 bp",
    "addr:street":"Terneuzensestr",
    "iso:country":"NL",
    "sg:address":"Terneuzensestr 62A",
    "sg:city":"Zaamslag",
    "sg:orig_category":"Bloemen En Planten",
    "sg:phone":"+31 115 432 091",
    "sg:postcode":"4543 BP",
    "sg:province":"Zeeland",
    "wof:name":"Bloemenwinkeltje",
    "wof:placetype":"venue"
},
  "geometry": {"coordinates":[3.907471,51.312962],"type":"Point"}
}