{
  "type": "Feature",
  "properties": {
    "addr:full":"Sadatwg 41 Delft Zuid-Holland 2622 PA",
    "addr:housenumber":"41",
    "addr:postcode":"2622 pa",
    "addr:street":"Sadatwg",
    "iso:country":"NL",
    "sg:address":"Sadatwg 41",
    "sg:city":"Delft",
    "sg:orig_category":"Adviesbureaus Bouwkunde",
    "sg:phone":"+31 15 256 0696",
    "sg:postcode":"2622 PA",
    "sg:province":"Zuid-Holland",
    "sg:website":"http://www.bouwinspecties.nl",
    "wof:name":"Ham, Cor",
    "wof:placetype":"venue"
},
  "geometry": {"coordinates":[4.339902,51.983837],"type":"Point"}
}