{
  "type": "Feature",
  "properties": {
    "addr:full":"P De Hooghstr 11 Heemstede North Holland 2102 BX",
    "addr:housenumber":"11",
    "addr:postcode":"2102 bx",
    "addr:street":"P",
    "iso:country":"NL",
    "sg:address":"P De Hooghstr 11",
    "sg:city":"Heemstede",
    "sg:orig_category":"Fotografie Reclame En Mode",
    "sg:phone":"+31 23 528 8249",
    "sg:postcode":"2102 BX",
    "sg:province":"North Holland",
    "wof:name":"Booij, Lieselot",
    "wof:placetype":"venue"
},
  "geometry": {"coordinates":[4.629867,52.359009],"type":"Point"}
}