{
  "type": "Feature",
  "properties": {
    "addr:full":"Plantage Kerkln 38 Amsterdam North Holland 1018 CZ",
    "addr:housenumber":"38",
    "addr:postcode":"1018",
    "addr:street":"Plantage Kerkln",
    "iso:country":"NL",
    "sg:address":"Plantage Kerkln 38",
    "sg:city":"Amsterdam",
    "sg:orig_category":"Fotoreportages",
    "sg:phone":"+31 20 627 8729",
    "sg:postcode":"1018 CZ",
    "sg:province":"North Holland",
    "sg:website":"http://www.artis.nl",
    "wof:name":"Zoo Artis",
    "wof:placetype":"venue"
},
  "geometry": {"coordinates":[4.912332,52.366783],"type":"Point"}
}