{
  "type": "Feature",
  "properties": {
    "addr:full":"Muldersweg 5 Staphorst Overijssel 7951 DG",
    "addr:housenumber":"5",
    "addr:postcode":"7951 dg",
    "addr:street":"Muldersweg",
    "iso:country":"NL",
    "sg:address":"Muldersweg 5",
    "sg:city":"Staphorst",
    "sg:orig_category":"Fotostudio'S And Fotografen",
    "sg:phone":"+31 522 461 882",
    "sg:postcode":"7951 DG",
    "sg:province":"Overijssel",
    "wof:name":"Foto Boessenkool",
    "wof:placetype":"venue"
},
  "geometry": {"coordinates":[6.204976,52.642292],"type":"Point"}
}