{
  "type": "Feature",
  "properties": {
    "addr:full":"Mr. Jaap Burgerlaan 8 Willemstad Nb Noord-Brabant 4797 CX",
    "addr:housenumber":"8",
    "addr:postcode":"4797 cx",
    "addr:street":"Mr. Jaap Burgerlaan",
    "iso:country":"NL",
    "sg:address":"Mr. Jaap Burgerlaan 8",
    "sg:city":"Willemstad Nb",
    "sg:orig_category":"Bedrijfs- And Managementsconsultants",
    "sg:phone":"+31 168 473 802",
    "sg:postcode":"4797 CX",
    "sg:province":"Noord-Brabant",
    "wof:name":"Perspectief",
    "wof:placetype":"venue"
},
  "geometry": {"coordinates":[4.432364,51.674484],"type":"Point"}
}