{
  "type": "Feature",
  "properties": {
    "iso:country":"NL",
    "sg:address":"Nieuwewg 7",
    "sg:city":"Valkenburg Lb",
    "sg:classifiers":[
        {
            "category":"Travel",
            "subcategory":"Hotels & Motels",
            "type":"Entertainment"
        }
    ],
    "sg:phone":"+31 43 601 5341",
    "sg:postcode":"6301 ES",
    "sg:province":"Limburg",
    "wof:name":"Atlas",
    "wof:placetype":"venue"
},
  "geometry": {"coordinates":[5.832839,50.867256],"type":"Point"}
}