{
  "type": "Feature",
  "properties": {
    "addr:full":"Abstederdk 64 Utrecht Utrecht 3582 BR",
    "addr:housenumber":"64",
    "addr:postcode":"3582 br",
    "addr:street":"Abstederdk",
    "iso:country":"NL",
    "sg:address":"Abstederdk 64",
    "sg:city":"Utrecht",
    "sg:orig_category":"Administratie- En Boekhoudkantoren",
    "sg:phone":"+31 30 254 3207",
    "sg:postcode":"3582 BR",
    "sg:province":"Utrecht",
    "wof:name":"Noyo",
    "wof:placetype":"venue"
},
  "geometry": {"coordinates":[5.129875,52.083801],"type":"Point"}
}