{
  "type": "Feature",
  "properties": {
    "iso:country":"NL",
    "sg:address":"Vlielandsewg 58B",
    "sg:city":"Pynacker",
    "sg:orig_category":"Machineonderhoud En -Reparatie",
    "sg:phone":"+31 15 369 6670",
    "sg:postcode":"2641 PP",
    "sg:province":"Zuid-Holland",
    "wof:name":"Tas, N J",
    "wof:placetype":"venue"
},
  "geometry": {"coordinates":[4.434869,52.026852],"type":"Point"}
}