{
  "type": "Feature",
  "properties": {
    "addr:full":"Wilhelminakade 3 Uithoorn Utrecht 1421 AB",
    "addr:housenumber":"3",
    "addr:postcode":"1421 ab",
    "addr:street":"Wilhelminakade",
    "iso:country":"NL",
    "sg:address":"Wilhelminakade 3",
    "sg:city":"Uithoorn",
    "sg:orig_category":"Verhuur Catering-, Feest- En Evenementbenodigdheden",
    "sg:phone":"+31 297 561 119",
    "sg:postcode":"1421 AB",
    "sg:province":"Utrecht",
    "wof:name":"Karsto Amusement Bv",
    "wof:placetype":"venue"
},
  "geometry": {"coordinates":[4.834256,52.233414],"type":"Point"}
}