{
  "type": "Feature",
  "properties": {
    "addr:full":"Keurmeestersdreef 200 Maastricht Limburg 6216 EB",
    "addr:housenumber":"200",
    "addr:postcode":"6216 eb",
    "addr:street":"Keurmeestersdreef",
    "iso:country":"NL",
    "sg:address":"Keurmeestersdreef 200",
    "sg:city":"Maastricht",
    "sg:orig_category":"Autokeuringen",
    "sg:phone":"+31 43 347 9937",
    "sg:postcode":"6216 EB",
    "sg:province":"Limburg",
    "wof:name":"Total Self Service Station Belfort",
    "wof:placetype":"venue"
},
  "geometry": {"coordinates":[5.654229,50.844566],"type":"Point"}
}