{
  "type": "Feature",
  "properties": {
    "addr:full":"Hargewaard 1 Alkmaar Noord-Holland 1824 TA",
    "addr:housenumber":"1",
    "addr:postcode":"1824 ta",
    "addr:street":"Hargewaard",
    "iso:country":"NL",
    "sg:address":"Hargewaard 1",
    "sg:city":"Alkmaar",
    "sg:orig_category":"Autorijscholen",
    "sg:phone":"+31 72 561 0021",
    "sg:postcode":"1824 TA",
    "sg:province":"Noord-Holland",
    "wof:name":"Hove, Van",
    "wof:placetype":"venue"
},
  "geometry": {"coordinates":[4.746054,52.644272],"type":"Point"}
}