{
  "type": "Feature",
  "properties": {
    "addr:full":"Hogeschoorweg 290 Venlo Limburg 5914 CZ",
    "addr:housenumber":"290",
    "addr:postcode":"5914",
    "addr:street":"Hogeschoorweg",
    "iso:country":"NL",
    "sg:address":"Hogeschoorweg 290",
    "sg:city":"Venlo",
    "sg:orig_category":"Woningbouwverenigingen",
    "sg:phone":"+31 77 351 8525",
    "sg:postcode":"5914 CZ",
    "sg:province":"Limburg",
    "wof:name":"Beschut Wonen",
    "wof:placetype":"venue"
},
  "geometry": {"coordinates":[6.1686310768,51.3832321167],"type":"Point"}
}