{
  "type": "Feature",
  "properties": {
    "addr:full":"De Houtduif 19 Surhuisterveen Friesland 9231 KB",
    "addr:housenumber":"19",
    "addr:postcode":"9231 kb",
    "addr:street":"De Houtduif",
    "iso:country":"NL",
    "sg:address":"De Houtduif 19",
    "sg:city":"Surhuisterveen",
    "sg:orig_category":"Goederenvervoer Over De Weg",
    "sg:phone":"+31 512 361 358",
    "sg:postcode":"9231 KB",
    "sg:province":"Friesland",
    "wof:name":"Van Kooy Transport",
    "wof:placetype":"venue"
},
  "geometry": {"coordinates":[6.167435,53.186001],"type":"Point"}
}