{
  "type": "Feature",
  "properties": {
    "addr:full":"Panweg 65 Zeist Utrecht 3705 GC",
    "addr:housenumber":"65",
    "addr:postcode":"3705 gc",
    "addr:street":"Panweg",
    "iso:country":"NL",
    "sg:address":"Panweg 65",
    "sg:city":"Zeist",
    "sg:orig_category":"Kinderopvang Behalve Thuis",
    "sg:phone":"+31 30 695 8469",
    "sg:postcode":"3705 GC",
    "sg:province":"Utrecht",
    "wof:name":"Kinderopvang Zeist Stichting",
    "wof:placetype":"venue"
},
  "geometry": {"coordinates":[5.241588,52.100071],"type":"Point"}
}