{
  "type": "Feature",
  "properties": {
    "addr:full":"Markt 9B Panningen Limburg 5981 AM",
    "addr:housenumber":"9b",
    "addr:postcode":"5981",
    "addr:street":"Markt",
    "iso:country":"NL",
    "sg:address":"Markt 9B",
    "sg:city":"Panningen",
    "sg:orig_category":"Bloemen En Planten - Decoratie",
    "sg:phone":"+31 77 307 1805",
    "sg:postcode":"5981 AM",
    "sg:province":"Limburg",
    "wof:name":"Greuske Vof, 'T",
    "wof:placetype":"venue"
},
  "geometry": {"coordinates":[5.980443,51.328873],"type":"Point"}
}