{
  "type": "Feature",
  "properties": {
    "iso:country":"NL",
    "sg:address":"Markt 4",
    "sg:city":"Geertruidenberg",
    "sg:orig_category":"Adviesbureaus Bedrijfsorganisatie",
    "sg:phone":"+31 6 53131860",
    "sg:postcode":"4931 BS",
    "sg:province":"Noord-Brabant",
    "wof:name":"Calcar, Van",
    "wof:placetype":"venue"
},
  "geometry": {"coordinates":[4.861424,51.700554],"type":"Point"}
}