{
  "type": "Feature",
  "properties": {
    "addr:full":"Kruisakkers 38 Bergen Op Zoom North Brabant 4613 BV",
    "addr:housenumber":"38",
    "addr:postcode":"4613 bv",
    "addr:street":"Kruisakkers",
    "iso:country":"NL",
    "sg:address":"Kruisakkers 38",
    "sg:city":"Bergen Op Zoom",
    "sg:orig_category":"Veiligheidsuitrusting En -Kleding",
    "sg:phone":"+31 164 250 656",
    "sg:postcode":"4613 BV",
    "sg:province":"North Brabant",
    "sg:website":"http://www.avertmichel.nl",
    "wof:name":"Avert, Michel Van Der",
    "wof:placetype":"venue"
},
  "geometry": {"coordinates":[4.27841,51.50502],"type":"Point"}
}