{
  "type": "Feature",
  "properties": {
    "addr:full":"Titaniumstr 41 Rotterdam South Holland 3067 GD",
    "addr:housenumber":"41",
    "addr:postcode":"3067 gd",
    "addr:street":"Titaniumstr",
    "iso:country":"NL",
    "sg:address":"Titaniumstr 41",
    "sg:city":"Rotterdam",
    "sg:orig_category":"Bedrijfsmechanisatie En -Automatisering",
    "sg:phone":"+31 10 299 0881",
    "sg:postcode":"3067 GD",
    "sg:province":"South Holland",
    "sg:website":"http://www.velobyte.nl",
    "wof:name":"Velobyte Bv",
    "wof:placetype":"venue"
},
  "geometry": {"coordinates":[4.538306,51.948124],"type":"Point"}
}