{
  "type": "Feature",
  "properties": {
    "iso:country":"NL",
    "sg:address":"Pr Margrietln 37",
    "sg:city":"Wezep",
    "sg:orig_category":"Elektrotechnische Apparatuur - Fabrieken En Groothandel",
    "sg:phone":"+31 38 376 0315",
    "sg:postcode":"8091 AV",
    "sg:province":"Gelderland",
    "wof:name":"Indesign",
    "wof:placetype":"venue"
},
  "geometry": {"coordinates":[5.996861,52.449566],"type":"Point"}
}