{
  "type": "Feature",
  "properties": {
    "addr:full":"Karveel 4506 Lelystad Flevoland 8242 VA",
    "addr:postcode":"4506;8242",
    "addr:street":"Karveel;Flevoland",
    "iso:country":"NL",
    "sg:address":"Karveel 4506",
    "sg:city":"Lelystad",
    "sg:orig_category":"Marketingbureaus",
    "sg:phone":"+31 320 242 887",
    "sg:postcode":"8242 VA",
    "sg:province":"Flevoland",
    "wof:name":"Ab Grafisch Advies",
    "wof:placetype":"venue"
},
  "geometry": {"coordinates":[5.457027,52.521507],"type":"Point"}
}