{
  "type": "Feature",
  "properties": {
    "addr:full":"Janvossenstg 23 Leiden Zuid-Holland 2312 WB",
    "addr:housenumber":"23",
    "addr:postcode":"2312 wb",
    "addr:street":"Janvossenstg",
    "iso:country":"NL",
    "sg:address":"Janvossenstg 23",
    "sg:city":"Leiden",
    "sg:orig_category":"Beeldende Kunstenaars",
    "sg:phone":"+31 71 514 6759",
    "sg:postcode":"2312 WB",
    "sg:province":"Zuid-Holland",
    "wof:name":"Hoogstraten, Wim",
    "wof:placetype":"venue"
},
  "geometry": {"coordinates":[4.492188,52.161598],"type":"Point"}
}