{
  "type": "Feature",
  "properties": {
    "addr:full":"Markt 7 Velden Limburg 5941 GA",
    "addr:housenumber":"7",
    "addr:postcode":"5941 ga",
    "addr:street":"Markt",
    "iso:country":"NL",
    "sg:address":"Markt 7",
    "sg:city":"Velden",
    "sg:classifiers":[
        {
            "category":"Travel",
            "subcategory":"Hotels & Motels",
            "type":"Entertainment"
        }
    ],
    "sg:phone":"+31 77 472 1235",
    "sg:postcode":"5941 GA",
    "sg:province":"Limburg",
    "wof:name":"Bascule, De",
    "wof:placetype":"venue"
},
  "geometry": {"coordinates":[6.164417,51.414734],"type":"Point"}
}