{
  "type": "Feature",
  "properties": {
    "iso:country":"NL",
    "sg:address":"Tiber 88-90",
    "sg:city":"Leidschendam",
    "sg:orig_category":"Parfum And Cosmetica Gh",
    "sg:phone":"+31 70 419 0404",
    "sg:postcode":"2267 CD",
    "sg:province":"South Holland",
    "wof:name":"Mades Cosmetics Bv",
    "wof:placetype":"venue"
},
  "geometry": {"coordinates":[4.40032,52.07888],"type":"Point"}
}