{
  "type": "Feature",
  "properties": {
    "addr:full":"Kon Wilhelminastr 20 Uitgeest North Holland 1911 EV",
    "addr:housenumber":"20",
    "addr:postcode":"1911 ev",
    "addr:street":"Kon Wilhelminastr",
    "iso:country":"NL",
    "sg:address":"Kon Wilhelminastr 20",
    "sg:city":"Uitgeest",
    "sg:orig_category":"Verf En Lak",
    "sg:phone":"+31 251 313 703",
    "sg:postcode":"1911 EV",
    "sg:province":"North Holland",
    "wof:name":"Tiebie, W",
    "wof:placetype":"venue"
},
  "geometry": {"coordinates":[4.710915,52.527382],"type":"Point"}
}