{
  "type": "Feature",
  "properties": {
    "iso:country":"NL",
    "sg:address":"Klokkendk 4",
    "sg:city":"Lochem",
    "sg:orig_category":"Kappers",
    "sg:phone":"+31 573 255 662",
    "sg:postcode":"7241 SP",
    "sg:province":"Gelderland",
    "wof:name":"Maurien",
    "wof:placetype":"venue"
},
  "geometry": {"coordinates":[6.377525,52.154202],"type":"Point"}
}