{
  "type": "Feature",
  "properties": {
    "addr:full":"Bosseestr 43 Beneden Leeuwen Gelderland 6658 AT",
    "addr:housenumber":"43",
    "addr:postcode":"6658",
    "addr:street":"Bosseestr",
    "iso:country":"NL",
    "sg:address":"Bosseestr 43",
    "sg:city":"Beneden Leeuwen",
    "sg:orig_category":"Schippers",
    "sg:phone":"+31 487 593 135",
    "sg:postcode":"6658 AT",
    "sg:province":"Gelderland",
    "wof:name":"Derksen Vof, H P C",
    "wof:placetype":"venue"
},
  "geometry": {"coordinates":[5.514282,51.885284],"type":"Point"}
}