{
  "type": "Feature",
  "properties": {
    "addr:full":"K Doormanstr 125 Activiteitencentrum Amsterdam Noord-Holland 1055 VE",
    "addr:housenumber":"125",
    "addr:postcode":"1055",
    "addr:street":"Activiteitencentrum;Ve",
    "iso:country":"NL",
    "sg:address":"K Doormanstr 125 Activiteitencentrum",
    "sg:city":"Amsterdam",
    "sg:orig_category":"Verenigingsgebouwen",
    "sg:phone":"+31 20 686 1400",
    "sg:postcode":"1055 VE",
    "sg:province":"Noord-Holland",
    "wof:name":"Swwt-Impuls",
    "wof:placetype":"venue"
},
  "geometry": {"coordinates":[4.85337,52.380409],"type":"Point"}
}