{
  "type": "Feature",
  "properties": {
    "iso:country":"NL",
    "sg:address":"Scherpenheuvelln 17",
    "sg:city":"Eindhoven",
    "sg:orig_category":"Zonweringen",
    "sg:phone":"+31 40 242 7763",
    "sg:postcode":"5628 TT",
    "sg:province":"Noord-Brabant",
    "wof:name":"Zonnelux Bv",
    "wof:placetype":"venue"
},
  "geometry": {"coordinates":[5.47191,51.48011],"type":"Point"}
}