{
  "type": "Feature",
  "properties": {
    "iso:country":"NL",
    "sg:address":"De Run 4473",
    "sg:city":"Veldhoven",
    "sg:orig_category":"Autokeuringen",
    "sg:phone":"+31 40 230 8308",
    "sg:postcode":"5503 LS",
    "sg:province":"North Brabant",
    "wof:name":"Regionaal Vers Centrum Eindhoven",
    "wof:placetype":"venue"
},
  "geometry": {"coordinates":[5.424666,51.409138],"type":"Point"}
}