{
  "type": "Feature",
  "properties": {
    "addr:full":"Rapperswg 18 Almelo Overijssel 7603 VN",
    "addr:housenumber":"18",
    "addr:postcode":"7603 vn",
    "addr:street":"Rapperswg",
    "iso:country":"NL",
    "sg:address":"Rapperswg 18",
    "sg:city":"Almelo",
    "sg:orig_category":"Voegwerken",
    "sg:phone":"+31 546 866 307",
    "sg:postcode":"7603 VN",
    "sg:province":"Overijssel",
    "wof:name":"Meijer, R",
    "wof:placetype":"venue"
},
  "geometry": {"coordinates":[6.685121,52.368435],"type":"Point"}
}