{
  "type": "Feature",
  "properties": {
    "addr:full":"Molenstr 45B Zundert Noord-Brabant 4881 CP",
    "addr:housenumber":"45b",
    "addr:postcode":"4881 cp",
    "addr:street":"Molenstr",
    "iso:country":"NL",
    "sg:address":"Molenstr 45B",
    "sg:city":"Zundert",
    "sg:orig_category":"Projectontwikkeling",
    "sg:phone":"+31 76 597 1078",
    "sg:postcode":"4881 CP",
    "sg:province":"Noord-Brabant",
    "wof:name":"Proteam",
    "wof:placetype":"venue"
},
  "geometry": {"coordinates":[4.661202,51.470394],"type":"Point"}
}