{
  "type": "Feature",
  "properties": {
    "addr:full":"Domineeshofweg 1 Westkapelle Zeeland 4361 JD",
    "addr:housenumber":"1",
    "addr:postcode":"4361 jd",
    "addr:street":"Domineeshofweg",
    "iso:country":"NL",
    "sg:address":"Domineeshofweg 1",
    "sg:city":"Westkapelle",
    "sg:orig_category":"Kampeerterreinen",
    "sg:phone":"+31 118 571 388",
    "sg:postcode":"4361 JD",
    "sg:province":"Zeeland",
    "wof:name":"Camping De Boomgaard Bv",
    "wof:placetype":"venue"
},
  "geometry": {"coordinates":[3.4537870884,51.5341262817],"type":"Point"}
}