{
  "type": "Feature",
  "properties": {
    "iso:country":"NL",
    "sg:address":"Kervelhof 30",
    "sg:city":"Hoogvliet Rt",
    "sg:orig_category":"Diverse Consumentenartikelen Gh",
    "sg:phone":"+31 10 416 0406",
    "sg:postcode":"3193 JH",
    "sg:province":"Zuid-Holland",
    "wof:name":"Sparkle Trading",
    "wof:placetype":"venue"
},
  "geometry": {"coordinates":[4.348584,51.862762],"type":"Point"}
}