{
  "type": "Feature",
  "properties": {
    "addr:full":"Wesselseweg 110 Kootwijkerbroek Gelderland 3774 RL",
    "addr:housenumber":"110",
    "addr:postcode":"3774 rl",
    "addr:street":"Wesselseweg;Gelderland",
    "iso:country":"NL",
    "sg:address":"Wesselseweg 110",
    "sg:city":"Kootwijkerbroek",
    "sg:orig_category":"Meubelreparatie And -Restauratie",
    "sg:phone":"+31 342 421 519",
    "sg:postcode":"3774 RL",
    "sg:province":"Gelderland",
    "wof:name":"G.J. Van Beek",
    "wof:placetype":"venue"
},
  "geometry": {"coordinates":[5.639913,52.14941],"type":"Point"}
}