{
  "type": "Feature",
  "properties": {
    "addr:full":"Puttenstr 34A Genemuiden Overijssel 8281 BP",
    "addr:housenumber":"34a",
    "addr:postcode":"8281 bp",
    "addr:street":"Puttenstr",
    "iso:country":"NL",
    "sg:address":"Puttenstr 34A",
    "sg:city":"Genemuiden",
    "sg:classifiers":[
        {
            "category":"Professional",
            "subcategory":"Accounting & Tax Preparation",
            "type":"Services"
        }
    ],
    "sg:phone":"+31 38 851 5200",
    "sg:postcode":"8281 BP",
    "sg:province":"Overijssel",
    "sg:tags":[
        "accountant",
        "en",
        "-kantoren",
        "register-"
    ],
    "sg:website":"http://www.brouwers.nl",
    "wof:name":"Brouwers",
    "wof:placetype":"venue"
},
  "geometry": {"coordinates":[6.047648,52.624062],"type":"Point"}
}