{
  "type": "Feature",
  "properties": {
    "addr:full":"Binnendk 29 Lelystad Flevoland 8244 AA",
    "addr:housenumber":"29",
    "addr:postcode":"8244 aa",
    "addr:street":"Binnendk;Flevoland",
    "iso:country":"NL",
    "sg:address":"Binnendk 29",
    "sg:city":"Lelystad",
    "sg:orig_category":"Koffie- En Theehuizen",
    "sg:phone":"+31 320 226 148",
    "sg:postcode":"8244 AA",
    "sg:province":"Flevoland",
    "wof:name":"Cisca",
    "wof:placetype":"venue"
},
  "geometry": {"coordinates":[5.42007,52.499989],"type":"Point"}
}