{
  "type": "Feature",
  "properties": {
    "addr:full":"Groeneweg 109 'S Gravenzande Zuid-Holland 2691 ML",
    "addr:housenumber":"109 '",
    "addr:postcode":"2691 ml",
    "addr:street":"Groeneweg",
    "iso:country":"NL",
    "sg:address":"Groeneweg 109",
    "sg:city":"'S Gravenzande",
    "sg:orig_category":"Huizensloop And Bouwrijp Maken",
    "sg:phone":"+31 174 625 406",
    "sg:postcode":"2691 ML",
    "sg:province":"Zuid-Holland",
    "wof:name":"H. V.D. Hout",
    "wof:placetype":"venue"
},
  "geometry": {"coordinates":[4.199777,51.977943],"type":"Point"}
}