{
  "type": "Feature",
  "properties": {
    "addr:full":"Nieuwez Voorburgw 144 Amsterdam Noord-Holland 1012 SJ",
    "addr:housenumber":"144",
    "addr:postcode":"1012",
    "iso:country":"NL",
    "sg:address":"Nieuwez Voorburgw 144",
    "sg:city":"Amsterdam",
    "sg:classifiers":[
        {
            "category":"Travel",
            "subcategory":"Hotels & Motels",
            "type":"Entertainment"
        }
    ],
    "sg:phone":"+31 20 624 2484",
    "sg:postcode":"1012 SJ",
    "sg:province":"Noord-Holland",
    "wof:name":"Tamara",
    "wof:placetype":"venue"
},
  "geometry": {"coordinates":[4.891525,52.374809],"type":"Point"}
}