{
  "type": "Feature",
  "properties": {
    "addr:full":"Langeweg 17 'S Gravenpolder Zeeland 4431 CE",
    "addr:housenumber":"17",
    "addr:postcode":"4431 ce",
    "addr:street":"Langeweg;' S Gravenpolder Zeeland",
    "iso:country":"NL",
    "sg:address":"Langeweg 17",
    "sg:city":"'S Gravenpolder",
    "sg:orig_category":"Bouwnijverheidsmachines Gh",
    "sg:phone":"+31 113 312 186",
    "sg:postcode":"4431 CE",
    "sg:province":"Zeeland",
    "wof:name":"Techno West Services",
    "wof:placetype":"venue"
},
  "geometry": {"coordinates":[3.904123,51.459702],"type":"Point"}
}