{
  "type": "Feature",
  "properties": {
    "iso:country":"NL",
    "sg:address":"Koepoortstraat 44",
    "sg:city":"Doesburg",
    "sg:orig_category":"Diverse Grafische Activiteiten",
    "sg:phone":"+31 313 484 485",
    "sg:postcode":"6981 AT",
    "sg:province":"Gelderland",
    "wof:name":"A. Bikker",
    "wof:placetype":"venue"
},
  "geometry": {"coordinates":[6.132933,52.016499],"type":"Point"}
}