{
  "type": "Feature",
  "properties": {
    "iso:country":"NL",
    "sg:address":"Beneluxln 909",
    "sg:city":"Utrecht",
    "sg:orig_category":"Verenigingen En Stichtingen",
    "sg:phone":"+31 30 284 4521",
    "sg:postcode":"3526 KK",
    "sg:province":"Utrecht",
    "wof:name":"Tvd",
    "wof:placetype":"venue"
},
  "geometry": {"coordinates":[5.102438,52.068104],"type":"Point"}
}