{
  "type": "Feature",
  "properties": {
    "iso:country":"NL",
    "sg:address":"Appelgaard 62",
    "sg:city":"Lienden",
    "sg:orig_category":"Administratie- En Boekhoudkantoren",
    "sg:phone":"+31 344 603 695",
    "sg:postcode":"4033 JD",
    "sg:province":"Gelderland",
    "wof:name":"Ics",
    "wof:placetype":"venue"
},
  "geometry": {"coordinates":[5.511593,51.947823],"type":"Point"}
}