{
  "type": "Feature",
  "properties": {
    "addr:full":"Appelgaard 62 Lienden Gelderland 4033 JD",
    "addr:housenumber":"62",
    "addr:postcode":"4033 jd",
    "addr:street":"Appelgaard;Gelderland",
    "iso:country":"NL",
    "sg:address":"Appelgaard 62",
    "sg:city":"Lienden",
    "sg:orig_category":"Administratie- En Boekhoudkantoren",
    "sg:phone":"+31 344 603 695",
    "sg:postcode":"4033 JD",
    "sg:province":"Gelderland",
    "wof:name":"Ics",
    "wof:placetype":"venue"
},
  "geometry": {"coordinates":[5.511593,51.947823],"type":"Point"}
}