{
  "type": "Feature",
  "properties": {
    "iso:country":"NL",
    "sg:address":"Cannenburgln 6",
    "sg:city":"Arnhem",
    "sg:orig_category":"Beeldende Kunstenaars",
    "sg:phone":"+31 26 442 0185",
    "sg:postcode":"6825 KK",
    "sg:province":"Gelderland",
    "wof:name":"Krynen & Lotus Goedhart Vof, Peter",
    "wof:placetype":"venue"
},
  "geometry": {"coordinates":[5.962798,51.978481],"type":"Point"}
}