{
  "type": "Feature",
  "properties": {
    "addr:full":"Raadhuisplein 2 Mijdrecht Utrecht 3641 EE",
    "addr:housenumber":"2",
    "addr:postcode":"3641 ee",
    "addr:street":"Raadhuisplein",
    "iso:country":"NL",
    "sg:address":"Raadhuisplein 2",
    "sg:city":"Mijdrecht",
    "sg:orig_category":"Opticiens",
    "sg:phone":"+31 297 285 953",
    "sg:postcode":"3641 EE",
    "sg:province":"Utrecht",
    "wof:name":"Oogmerk Opticien Van Der Zwaard",
    "wof:placetype":"venue"
},
  "geometry": {"coordinates":[4.8664708138,52.2073822021],"type":"Point"}
}