{
  "type": "Feature",
  "properties": {
    "iso:country":"NL",
    "sg:address":"Zandstr 41",
    "sg:city":"Opynen",
    "sg:orig_category":"Elektrotechnische Artikelen",
    "sg:phone":"+31 418 651 589",
    "sg:postcode":"4184 EG",
    "sg:province":"Gelderland",
    "wof:name":"Varelma",
    "wof:placetype":"venue"
},
  "geometry": {"coordinates":[5.313264,51.830254],"type":"Point"}
}