{
  "type": "Feature",
  "properties": {
    "addr:full":"Zandstr 41 Opynen Gelderland 4184 EG",
    "addr:housenumber":"41",
    "addr:postcode":"4184 eg",
    "addr:street":"Zandstr;Gelderland",
    "iso:country":"NL",
    "sg:address":"Zandstr 41",
    "sg:city":"Opynen",
    "sg:orig_category":"Elektrotechnische Artikelen",
    "sg:phone":"+31 418 651 589",
    "sg:postcode":"4184 EG",
    "sg:province":"Gelderland",
    "wof:name":"Varelma",
    "wof:placetype":"venue"
},
  "geometry": {"coordinates":[5.313264,51.830254],"type":"Point"}
}