{
  "type": "Feature",
  "properties": {
    "iso:country":"NL",
    "sg:address":"Herestraat 26",
    "sg:city":"Grijpskerk",
    "sg:classifiers":[
        {
            "category":"Fast Food",
            "type":"Food & Drink"
        }
    ],
    "sg:phone":"+31 594 212 718",
    "sg:postcode":"9843 AK",
    "sg:province":"Groningen",
    "sg:tags":[
        "afhaal",
        "restaurant"
    ],
    "wof:name":"Snackbar Honky Tonk",
    "wof:placetype":"venue"
},
  "geometry": {"coordinates":[6.308193,53.263569],"type":"Point"}
}