{
  "type": "Feature",
  "properties": {
    "iso:country":"NL",
    "sg:address":"Goudkd 16",
    "sg:city":"Gouda",
    "sg:orig_category":"Ovenbouw",
    "sg:phone":"+31 182 591 400",
    "sg:postcode":"2802 AA",
    "sg:province":"Zuid-Holland",
    "wof:name":"Gouda Vuurvast Nv",
    "wof:placetype":"venue"
},
  "geometry": {"coordinates":[4.710714817,52.0100059509],"type":"Point"}
}