{
  "type": "Feature",
  "properties": {
    "addr:full":"Het Veer 78 Avenhorn Noord-Holland 1633 HE",
    "addr:housenumber":"78",
    "addr:postcode":"1633 he",
    "addr:street":"Het Veer",
    "iso:country":"NL",
    "sg:address":"Het Veer 78",
    "sg:city":"Avenhorn",
    "sg:orig_category":"Werk- And Beschermkleding Fab",
    "sg:phone":"+31 229 542 636",
    "sg:postcode":"1633 HE",
    "sg:province":"Noord-Holland",
    "wof:name":"Backstreet Bv",
    "wof:placetype":"venue"
},
  "geometry": {"coordinates":[4.9569759369,52.618396759],"type":"Point"}
}