{
  "type": "Feature",
  "properties": {
    "addr:full":"Ardennenln 70 Tilburg Noord-Brabant 5022 NM",
    "addr:housenumber":"70",
    "addr:postcode":"5022",
    "addr:street":"Ardennenln",
    "iso:country":"NL",
    "sg:address":"Ardennenln 70",
    "sg:city":"Tilburg",
    "sg:orig_category":"Metselwerken",
    "sg:phone":"+31 13 536 1530",
    "sg:postcode":"5022 NM",
    "sg:province":"Noord-Brabant",
    "wof:name":"Zebregs",
    "wof:placetype":"venue"
},
  "geometry": {"coordinates":[5.09431,51.541271],"type":"Point"}
}