{
  "type": "Feature",
  "properties": {
    "addr:full":"Dorpstraat 1 Maastricht Limburg 6227 BK",
    "addr:housenumber":"1",
    "addr:postcode":"6227 bk",
    "addr:street":"Dorpstraat",
    "iso:country":"NL",
    "sg:address":"Dorpstraat 1",
    "sg:city":"Maastricht",
    "sg:orig_category":"Huishoudapparatuur, Televisies And Radio'S",
    "sg:phone":"+31 43 367 1188",
    "sg:postcode":"6227 BK",
    "sg:province":"Limburg",
    "wof:name":"Elektro Weerts Bv",
    "wof:placetype":"venue"
},
  "geometry": {"coordinates":[5.727809,50.843334],"type":"Point"}
}