{
  "type": "Feature",
  "properties": {
    "addr:full":"Stationsstr 104 Deurne Noord-Brabant 5751 HH",
    "addr:housenumber":"104",
    "addr:postcode":"5751 hh",
    "iso:country":"NL",
    "sg:address":"Stationsstr 104",
    "sg:city":"Deurne",
    "sg:orig_category":"Autorijscholen",
    "sg:phone":"+31 493 317 510",
    "sg:postcode":"5751 HH",
    "sg:province":"Noord-Brabant",
    "wof:name":"Fransen, Eric",
    "wof:placetype":"venue"
},
  "geometry": {"coordinates":[5.7875,51.459381],"type":"Point"}
}