{
  "type": "Feature",
  "properties": {
    "iso:country":"NL",
    "sg:address":"Wilhelminastraat 32",
    "sg:city":"Noordwijk Zh",
    "sg:orig_category":"Keuken- Groot-Installaties",
    "sg:phone":"+31 71 364 6768",
    "sg:postcode":"2201 KC",
    "sg:province":"South Holland",
    "wof:name":"Atik Bv",
    "wof:placetype":"venue"
},
  "geometry": {"coordinates":[4.448783,52.235798],"type":"Point"}
}