{
  "type": "Feature",
  "properties": {
    "addr:full":"Leeuwenbergweg 6 Loenen Gld Gelderland 7371 AL",
    "addr:housenumber":"6",
    "addr:postcode":"7371",
    "addr:street":"Leeuwenbergweg;Gld Gelderland",
    "iso:country":"NL",
    "sg:address":"Leeuwenbergweg 6",
    "sg:city":"Loenen Gld",
    "sg:orig_category":"Bedrijfs- And Managementsconsultants",
    "sg:phone":"+31 55 505 2528",
    "sg:postcode":"7371 AL",
    "sg:province":"Gelderland",
    "wof:name":"Eban",
    "wof:placetype":"venue"
},
  "geometry": {"coordinates":[6.01798,52.11705],"type":"Point"}
}