{
  "type": "Feature",
  "properties": {
    "addr:full":"St Walburgkerkpad 43B Tiel Gelderland 4001 MG",
    "addr:housenumber":"43b",
    "addr:postcode":"4001 mg",
    "addr:street":"St Walburgkerkpad;Gelderland",
    "iso:country":"NL",
    "sg:address":"St Walburgkerkpad 43B",
    "sg:city":"Tiel",
    "sg:orig_category":"Kunstnijverheid",
    "sg:phone":"+31 344 620 729",
    "sg:postcode":"4001 MG",
    "sg:province":"Gelderland",
    "wof:name":"Bennani",
    "wof:placetype":"venue"
},
  "geometry": {"coordinates":[5.430147,51.886803],"type":"Point"}
}