{
  "type": "Feature",
  "properties": {
    "addr:full":"C V Brienenstr 54 Maastricht Limburg 6225 BE",
    "addr:housenumber":"54",
    "addr:postcode":"6225",
    "addr:street":"V Brienenstr",
    "iso:country":"NL",
    "sg:address":"C V Brienenstr 54",
    "sg:city":"Maastricht",
    "sg:orig_category":"Schoonheidsinstituten",
    "sg:phone":"+31 43 363 7142",
    "sg:postcode":"6225 BE",
    "sg:province":"Limburg",
    "wof:name":"Excellent",
    "wof:placetype":"venue"
},
  "geometry": {"coordinates":[5.73794,50.863708],"type":"Point"}
}