{
  "type": "Feature",
  "properties": {
    "addr:full":"Geuzenstr 15 Amsterdam Noord-Holland 1056 JX",
    "addr:housenumber":"15",
    "addr:postcode":"1056 jx",
    "addr:street":"Geuzenstr",
    "iso:country":"NL",
    "sg:address":"Geuzenstr 15",
    "sg:city":"Amsterdam",
    "sg:orig_category":"Adviesbureaus Bouwkunde",
    "sg:phone":"+31 20 618 2758",
    "sg:postcode":"1056 JX",
    "sg:province":"Noord-Holland",
    "wof:name":"Feekes",
    "wof:placetype":"venue"
},
  "geometry": {"coordinates":[4.864837,52.371323],"type":"Point"}
}