{
  "type": "Feature",
  "properties": {
    "addr:full":"Bakkersstraat 11 Westknollendam Noord-Holland 1525 PV",
    "addr:housenumber":"11",
    "addr:postcode":"1525 pv",
    "addr:street":"Bakkersstraat",
    "iso:country":"NL",
    "sg:address":"Bakkersstraat 11",
    "sg:city":"Westknollendam",
    "sg:orig_category":"Wegen And Sportterreinen",
    "sg:phone":"+31 75 628 3858",
    "sg:postcode":"1525 PV",
    "sg:province":"Noord-Holland",
    "wof:name":"J. Dik",
    "wof:placetype":"venue"
},
  "geometry": {"coordinates":[4.7852869034,52.5183677673],"type":"Point"}
}