{
  "type": "Feature",
  "properties": {
    "addr:full":"Lumeystr 26 Amsterdam Noord-Holland 1056 VX",
    "addr:housenumber":"26",
    "addr:postcode":"1056 vx",
    "addr:street":"Lumeystr",
    "iso:country":"NL",
    "sg:address":"Lumeystr 26",
    "sg:city":"Amsterdam",
    "sg:orig_category":"Filmstudio'S En -Productie",
    "sg:phone":"+31 20 616 6339",
    "sg:postcode":"1056 VX",
    "sg:province":"Noord-Holland",
    "wof:name":"Lunar Sea",
    "wof:placetype":"venue"
},
  "geometry": {"coordinates":[4.86136,52.372948],"type":"Point"}
}