{
  "type": "Feature",
  "properties": {
    "iso:country":"NL",
    "sg:address":"Markt 10",
    "sg:city":"Weert",
    "sg:orig_category":"Verlichting",
    "sg:phone":"+31 495 532 071",
    "sg:postcode":"6001 EK",
    "sg:province":"Limburg",
    "wof:name":"Rechmann",
    "wof:placetype":"venue"
},
  "geometry": {"coordinates":[5.706399,51.253914],"type":"Point"}
}