{
  "type": "Feature",
  "properties": {
    "addr:full":"Bilderdykstr 5 Amsterdam North Holland 1052 NA",
    "addr:housenumber":"5",
    "addr:postcode":"1052 na",
    "addr:street":"Bilderdykstr",
    "iso:country":"NL",
    "sg:address":"Bilderdykstr 5",
    "sg:city":"Amsterdam",
    "sg:orig_category":"Vertalers",
    "sg:phone":"+31 20 616 2224",
    "sg:postcode":"1052 NA",
    "sg:province":"North Holland",
    "wof:name":"Cleaver, M",
    "wof:placetype":"venue"
},
  "geometry": {"coordinates":[4.871291,52.372196],"type":"Point"}
}