{
  "type": "Feature",
  "properties": {
    "iso:country":"NL",
    "sg:address":"C De Wittstr 28",
    "sg:city":"Delft",
    "sg:orig_category":"Administratie- En Boekhoudkantoren",
    "sg:phone":"+31 15 256 8053",
    "sg:postcode":"2613 GH",
    "sg:province":"Zuid-Holland",
    "sg:website":"http://www.duve.nl",
    "wof:name":"Duv\u00e9 Belastingadviesbureau, A J H",
    "wof:placetype":"venue"
},
  "geometry": {"coordinates":[4.350803,52.009216],"type":"Point"}
}