{
  "type": "Feature",
  "properties": {
    "addr:full":"Dorpsstr 29 Nunspeet Gelderland 8071 BX",
    "addr:housenumber":"29",
    "addr:postcode":"8071 bx",
    "addr:street":"Dorpsstr;Gelderland",
    "iso:country":"NL",
    "sg:address":"Dorpsstr 29",
    "sg:city":"Nunspeet",
    "sg:orig_category":"Juweliers",
    "sg:phone":"+31 341 252 806",
    "sg:postcode":"8071 BX",
    "sg:province":"Gelderland",
    "wof:name":"Hordijk, Jaap",
    "wof:placetype":"venue"
},
  "geometry": {"coordinates":[5.784304,52.375973],"type":"Point"}
}