{
  "type": "Feature",
  "properties": {
    "iso:country":"NL",
    "sg:address":"Hamburgerstraat 33",
    "sg:city":"Doetinchem",
    "sg:classifiers":[
        {
            "category":"Shopping",
            "subcategory":"Clothing, Apparel, & Fashions",
            "type":"Retail Goods"
        }
    ],
    "sg:phone":"+31 314 364 244",
    "sg:postcode":"7001 AH",
    "sg:province":"Gelderland",
    "sg:tags":[
        "ondergoed",
        "lingerie"
    ],
    "wof:name":"Hunkemoller",
    "wof:placetype":"venue"
},
  "geometry": {"coordinates":[6.290012,51.964577],"type":"Point"}
}