{
  "type": "Feature",
  "properties": {
    "addr:full":"Veilingwg 17-19 Huissen Gelderland 6851 EG",
    "addr:housenumber":"17-19",
    "addr:postcode":"6851 eg",
    "addr:street":"Gelderland",
    "iso:country":"NL",
    "sg:address":"Veilingwg 17-19",
    "sg:city":"Huissen",
    "sg:orig_category":"Zaden",
    "sg:phone":"+31 26 325 9109",
    "sg:postcode":"6851 EG",
    "sg:province":"Gelderland",
    "wof:name":"Bestebreurtje Bv, P",
    "wof:placetype":"venue"
},
  "geometry": {"coordinates":[5.926244,51.911381],"type":"Point"}
}