{
  "type": "Feature",
  "properties": {
    "addr:full":"Haarlemmerstraat 107 Leiden Zuid-Holland 2312 DM",
    "addr:housenumber":"107",
    "addr:postcode":"2312 dm",
    "addr:street":"Haarlemmerstraat",
    "iso:country":"NL",
    "sg:address":"Haarlemmerstraat 107",
    "sg:city":"Leiden",
    "sg:orig_category":"Opticiens",
    "sg:phone":"+31 71 513 4495",
    "sg:postcode":"2312 DM",
    "sg:province":"Zuid-Holland",
    "wof:name":"Pearle Opticiens",
    "wof:placetype":"venue"
},
  "geometry": {"coordinates":[4.4900331497,52.1603736877],"type":"Point"}
}