{
  "type": "Feature",
  "properties": {
    "addr:full":"Nyverheidswg 12 Utrecht Utrecht 3534 AM",
    "addr:housenumber":"12",
    "addr:postcode":"3534",
    "addr:street":"Nyverheidswg",
    "iso:country":"NL",
    "sg:address":"Nyverheidswg 12",
    "sg:city":"Utrecht",
    "sg:orig_category":"Fitnesscentra",
    "sg:phone":"+31 346 556 801",
    "sg:postcode":"3534 AM",
    "sg:province":"Utrecht",
    "wof:name":"Scorpio",
    "wof:placetype":"venue"
},
  "geometry": {"coordinates":[5.08359,52.101311],"type":"Point"}
}