{
  "type": "Feature",
  "properties": {
    "addr:full":"Hoofdstr 9 Didam Gelderland 6942 AP",
    "addr:housenumber":"9",
    "addr:postcode":"6942 ap",
    "addr:street":"Hoofdstr;Gelderland",
    "iso:country":"NL",
    "sg:address":"Hoofdstr 9",
    "sg:city":"Didam",
    "sg:orig_category":"Fotoreportages",
    "sg:phone":"+31 316 221 530",
    "sg:postcode":"6942 AP",
    "sg:province":"Gelderland",
    "sg:website":"http://www.combivreeman.nl",
    "wof:name":"Vreeman",
    "wof:placetype":"venue"
},
  "geometry": {"coordinates":[6.129066,51.938122],"type":"Point"}
}