{
  "type": "Feature",
  "properties": {
    "iso:country":"NL",
    "sg:address":"Nw Noord 24",
    "sg:city":"Hoorn Nh",
    "sg:orig_category":"Kinderkleding",
    "sg:phone":"+31 229 210 402",
    "sg:postcode":"1621 EN",
    "sg:province":"North Holland",
    "wof:name":"Mixi For Boys And Girls",
    "wof:placetype":"venue"
},
  "geometry": {"coordinates":[5.05207,52.642399],"type":"Point"}
}