{
  "type": "Feature",
  "properties": {
    "addr:full":"Parallelwg 1A Hardenberg NL.08 7772 SB",
    "addr:housenumber":"1a;nl.08",
    "addr:postcode":"7772 sb",
    "addr:street":"Parallelwg",
    "iso:country":"NL",
    "sg:address":"Parallelwg 1A",
    "sg:city":"Hardenberg",
    "sg:orig_category":"Autorijscholen",
    "sg:phone":"+31 523 260 789",
    "sg:postcode":"7772 SB",
    "sg:province":"NL.08",
    "wof:name":"Hiemstra",
    "wof:placetype":"venue"
},
  "geometry": {"coordinates":[6.628521,52.572681],"type":"Point"}
}