{
  "type": "Feature",
  "properties": {
    "iso:country":"NL",
    "sg:address":"Boterdiepstr 46",
    "sg:city":"Amsterdam",
    "sg:orig_category":"Wijnkoperijen En -Groothandel",
    "sg:phone":"+31 20 685 4385",
    "sg:postcode":"1079 SZ",
    "sg:province":"North Holland",
    "wof:name":"Huiskes Van Den Berg En Huiskes Vof",
    "wof:placetype":"venue"
},
  "geometry": {"coordinates":[4.909594059,52.3418540955],"type":"Point"}
}