{
  "type": "Feature",
  "properties": {
    "iso:country":"NL",
    "sg:address":"Middenweg 2",
    "sg:city":"Collendoorn",
    "sg:orig_category":"Boekhouders",
    "sg:phone":"+31 523 683 697",
    "sg:postcode":"7798 CP",
    "sg:province":"NL.08",
    "wof:name":"Belastingadvies- En Boekhoudkantoor W.L.Stegeman",
    "wof:placetype":"venue"
},
  "geometry": {"coordinates":[6.575647,52.600124],"type":"Point"}
}