{
  "type": "Feature",
  "properties": {
    "addr:full":"V Nyenrodewg 662 Amsterdam North Holland 1082 JA",
    "addr:housenumber":"662",
    "addr:postcode":"1082 ja",
    "iso:country":"NL",
    "sg:address":"V Nyenrodewg 662",
    "sg:city":"Amsterdam",
    "sg:classifiers":[
        {
            "category":"Professional",
            "subcategory":"Accounting & Tax Preparation",
            "type":"Services"
        }
    ],
    "sg:phone":"+31 20 642 5891",
    "sg:postcode":"1082 JA",
    "sg:province":"North Holland",
    "sg:tags":[
        "accountant",
        "en",
        "-kantoren",
        "register-"
    ],
    "wof:name":"Cohen, D",
    "wof:placetype":"venue"
},
  "geometry": {"coordinates":[4.87756,52.330521],"type":"Point"}
}