{
  "type": "Feature",
  "properties": {
    "addr:full":"Schoolstr 23 Bakel North Brabant 5761 BV",
    "addr:housenumber":"23",
    "addr:postcode":"5761 bv",
    "addr:street":"Schoolstr",
    "iso:country":"NL",
    "sg:address":"Schoolstr 23",
    "sg:city":"Bakel",
    "sg:orig_category":"Bloemen En Planten",
    "sg:phone":"+31 492 340 748",
    "sg:postcode":"5761 BV",
    "sg:province":"North Brabant",
    "wof:name":"Versilia",
    "wof:placetype":"venue"
},
  "geometry": {"coordinates":[5.74074,51.502453],"type":"Point"}
}