{
  "type": "Feature",
  "properties": {
    "iso:country":"NL",
    "sg:address":"Besanconlaan 13",
    "sg:city":"Eindhoven",
    "sg:orig_category":"Vertaal- And Tolkenbureaus",
    "sg:phone":"+31 40 242 0747",
    "sg:postcode":"5627 LR",
    "sg:province":"Noord-Brabant",
    "wof:name":"Kragt Creative Translations & Assistance",
    "wof:placetype":"venue"
},
  "geometry": {"coordinates":[5.447739,51.485641],"type":"Point"}
}