{
  "type": "Feature",
  "properties": {
    "addr:full":"Duinkerkenstraat 33 Groningen Groningen 9723 BP",
    "addr:housenumber":"33",
    "addr:postcode":"9723 bp",
    "addr:street":"Duinkerkenstraat",
    "iso:country":"NL",
    "sg:address":"Duinkerkenstraat 33",
    "sg:city":"Groningen",
    "sg:orig_category":"Meubeltextiel Fab",
    "sg:phone":"+31 50 318 3031",
    "sg:postcode":"9723 BP",
    "sg:province":"Groningen",
    "wof:name":"Mennens Groningen Bv",
    "wof:placetype":"venue"
},
  "geometry": {"coordinates":[6.60736,53.19878],"type":"Point"}
}