{
  "type": "Feature",
  "properties": {
    "iso:country":"NL",
    "sg:address":"Van Kinschotstraat 114/4Hg",
    "sg:city":"Delft",
    "sg:orig_category":"Loodgieterswerk, Verwarming And Sanitaire Installaties",
    "sg:phone":"+31 15 214 4612",
    "sg:postcode":"2614 XP",
    "sg:province":"South Holland",
    "wof:name":"B. Bentem Onderhoudsbedrijf",
    "wof:placetype":"venue"
},
  "geometry": {"coordinates":[4.338244,52.011578],"type":"Point"}
}