{
  "type": "Feature",
  "properties": {
    "addr:full":"De Steven 26 Drachten Friesland 9206 AX",
    "addr:housenumber":"26",
    "addr:postcode":"9206 ax",
    "addr:street":"De Steven",
    "iso:country":"NL",
    "sg:address":"De Steven 26",
    "sg:city":"Drachten",
    "sg:orig_category":"Jachthavens - Jachtwerven",
    "sg:phone":"+31 512 512 669",
    "sg:postcode":"9206 AX",
    "sg:province":"Friesland",
    "wof:name":"Steven, De",
    "wof:placetype":"venue"
},
  "geometry": {"coordinates":[6.054589,53.114273],"type":"Point"}
}