{
  "type": "Feature",
  "properties": {
    "addr:full":"G Wilhelmln 6 Leek Groningen 9351 GL",
    "addr:housenumber":"6",
    "addr:postcode":"9351 gl",
    "addr:street":"Leek",
    "iso:country":"NL",
    "sg:address":"G Wilhelmln 6",
    "sg:city":"Leek",
    "sg:orig_category":"Elektronica - Ontwikkeling En Groothandel",
    "sg:phone":"+31 594 519 348",
    "sg:postcode":"9351 GL",
    "sg:province":"Groningen",
    "wof:name":"Feeltronics",
    "wof:placetype":"venue"
},
  "geometry": {"coordinates":[6.379235,53.162449],"type":"Point"}
}