{
  "type": "Feature",
  "properties": {
    "addr:full":"Goeverneurplein 8 'S Gravenhage Zuid-Holland 2523 EB",
    "addr:housenumber":"8 '",
    "addr:postcode":"2523 eb",
    "addr:street":"Goeverneurplein",
    "iso:country":"NL",
    "sg:address":"Goeverneurplein 8",
    "sg:city":"'S Gravenhage",
    "sg:orig_category":"Overheidsdiensten",
    "sg:phone":"+31 70 394 0194",
    "sg:postcode":"2523 EB",
    "sg:province":"Zuid-Holland",
    "wof:name":"De Wijkplaats",
    "wof:placetype":"venue"
},
  "geometry": {"coordinates":[4.3139481544,52.0561141968],"type":"Point"}
}