{
  "type": "Feature",
  "properties": {
    "iso:country":"NL",
    "sg:address":"Schoenerweg 40",
    "sg:city":"Maastricht",
    "sg:orig_category":"Goederenvervoer Over De Weg",
    "sg:phone":"+31 43 363 0330",
    "sg:postcode":"6222 NX",
    "sg:province":"Limburg",
    "wof:name":"Janssenauto'S Internationaal Bv",
    "wof:placetype":"venue"
},
  "geometry": {"coordinates":[5.71995,50.875874],"type":"Point"}
}