{
  "type": "Feature",
  "properties": {
    "addr:full":"Haagbeukenpad 4 Woerden South Holland 3442 JN",
    "addr:housenumber":"4",
    "addr:postcode":"3442 jn",
    "addr:street":"Haagbeukenpad",
    "iso:country":"NL",
    "sg:address":"Haagbeukenpad 4",
    "sg:city":"Woerden",
    "sg:orig_category":"Autopoetsbedrijven",
    "sg:phone":"+31 348 411 335",
    "sg:postcode":"3442 JN",
    "sg:province":"South Holland",
    "wof:name":"Mvg",
    "wof:placetype":"venue"
},
  "geometry": {"coordinates":[4.873656,52.079151],"type":"Point"}
}