{
  "type": "Feature",
  "properties": {
    "addr:full":"Reestein 6 Nieuw Vennep Noord-Holland 2151 KB",
    "addr:housenumber":"6",
    "addr:postcode":"2151 kb",
    "addr:street":"Reestein;Nieuw Vennep",
    "iso:country":"NL",
    "sg:address":"Reestein 6",
    "sg:city":"Nieuw Vennep",
    "sg:orig_category":"Webdesign Bureaus",
    "sg:phone":"+31 6 52014389",
    "sg:postcode":"2151 KB",
    "sg:province":"Noord-Holland",
    "wof:name":"Trisign",
    "wof:placetype":"venue"
},
  "geometry": {"coordinates":[4.6172981262,52.2726402283],"type":"Point"}
}