{
  "type": "Feature",
  "properties": {
    "iso:country":"NL",
    "sg:address":"Paletplein 89",
    "sg:city":"'S Gravenhage",
    "sg:orig_category":"Opticiens",
    "sg:phone":"+31 70 380 7292",
    "sg:postcode":"2526 GZ",
    "sg:province":"South Holland",
    "wof:name":"Optiek V/H Dykman",
    "wof:placetype":"venue"
},
  "geometry": {"coordinates":[4.3030557632,52.0690574646],"type":"Point"}
}