{
  "type": "Feature",
  "properties": {
    "addr:full":"Stationsplein 9 Hellevoetsluis Zuid-Holland 3224 AT",
    "addr:housenumber":"9",
    "addr:postcode":"3224",
    "addr:street":"Stationsplein",
    "iso:country":"NL",
    "sg:address":"Stationsplein 9",
    "sg:city":"Hellevoetsluis",
    "sg:orig_category":"Sauna'S",
    "sg:phone":"+31 6 53372267",
    "sg:postcode":"3224 AT",
    "sg:province":"Zuid-Holland",
    "wof:name":"Voorham Bv",
    "wof:placetype":"venue"
},
  "geometry": {"coordinates":[4.13546,51.823025],"type":"Point"}
}