{
  "type": "Feature",
  "properties": {
    "addr:full":"2E Tochtwg 56 Nieuwerkerk Yssel Zuid-Holland 2913 LS",
    "addr:housenumber":"56",
    "addr:postcode":"2913 ls",
    "addr:street":"2E Tochtwg",
    "iso:country":"NL",
    "sg:address":"2E Tochtwg 56",
    "sg:city":"Nieuwerkerk Yssel",
    "sg:orig_category":"Bloemen En Planten",
    "sg:phone":"+31 180 314 078",
    "sg:postcode":"2913 LS",
    "sg:province":"Zuid-Holland",
    "wof:name":"Bloemenvariatie, De",
    "wof:placetype":"venue"
},
  "geometry": {"coordinates":[4.62029,51.986916],"type":"Point"}
}