{
  "type": "Feature",
  "properties": {
    "addr:full":"Gaffel 24 Zeewolde Flevoland 3891 KD",
    "addr:housenumber":"24",
    "addr:postcode":"3891 kd",
    "addr:street":"Gaffel;Flevoland",
    "iso:country":"NL",
    "sg:address":"Gaffel 24",
    "sg:city":"Zeewolde",
    "sg:orig_category":"Ventilatoren",
    "sg:phone":"+31 36 522 2223",
    "sg:postcode":"3891 KD",
    "sg:province":"Flevoland",
    "wof:name":"Bosa",
    "wof:placetype":"venue"
},
  "geometry": {"coordinates":[5.526325,52.338753],"type":"Point"}
}