{
  "type": "Feature",
  "properties": {
    "addr:full":"Postbus 908 Spykenisse South Holland 3200 AW",
    "addr:housenumber":"908",
    "addr:postcode":"3200 aw",
    "addr:street":"Postbus",
    "iso:country":"NL",
    "sg:address":"Postbus 908",
    "sg:city":"Spykenisse",
    "sg:orig_category":"Verenigingen En Stichtingen",
    "sg:phone":"+31 181 678 712",
    "sg:postcode":"3200 AW",
    "sg:province":"South Holland",
    "wof:name":"Clusterkantoor Pameijerkeerkring",
    "wof:placetype":"venue"
},
  "geometry": {"coordinates":[4.35844,51.837879],"type":"Point"}
}