{
  "type": "Feature",
  "properties": {
    "addr:full":"Agricolastr 161 Apeldoorn Gelderland 7323 JH",
    "addr:housenumber":"161",
    "addr:postcode":"7323 jh",
    "addr:street":"Gelderland",
    "iso:country":"NL",
    "sg:address":"Agricolastr 161",
    "sg:city":"Apeldoorn",
    "sg:orig_category":"Verenigingsgebouwen",
    "sg:phone":"+31 55 366 7348",
    "sg:postcode":"7323 JH",
    "sg:province":"Gelderland",
    "wof:name":"Boerderij, De",
    "wof:placetype":"venue"
},
  "geometry": {"coordinates":[5.991649,52.225277],"type":"Point"}
}