{
  "type": "Feature",
  "properties": {
    "addr:full":"Singel 140 Dordrecht Zuid-Holland 3311 PE",
    "addr:housenumber":"140",
    "addr:postcode":"3311 pe",
    "addr:street":"Singel",
    "iso:country":"NL",
    "sg:address":"Singel 140",
    "sg:city":"Dordrecht",
    "sg:classifiers":[
        {
            "category":"Education",
            "subcategory":"Preschool",
            "type":"Public Place"
        }
    ],
    "sg:phone":"+31 78 613 7194",
    "sg:postcode":"3311 PE",
    "sg:province":"Zuid-Holland",
    "sg:tags":[
        "kleuteronderwijs",
        "basis-"
    ],
    "wof:name":"Bavinckschool",
    "wof:placetype":"venue"
},
  "geometry": {"coordinates":[4.67366,51.809917],"type":"Point"}
}