{
  "type": "Feature",
  "properties": {
    "addr:full":"Uraniumwg 2 Heerenveen Friesland 8445 PH",
    "addr:housenumber":"2",
    "addr:postcode":"8445",
    "addr:street":"Uraniumwg",
    "iso:country":"NL",
    "sg:address":"Uraniumwg 2",
    "sg:city":"Heerenveen",
    "sg:classifiers":[
        {
            "category":"Retail",
            "subcategory":"Auto Repair",
            "type":"Services"
        }
    ],
    "sg:phone":"+31 513 633 290",
    "sg:postcode":"8445 PH",
    "sg:province":"Friesland",
    "sg:tags":[
        "garage"
    ],
    "wof:name":"Hoeve Vof, A En H Ten",
    "wof:placetype":"venue"
},
  "geometry": {"coordinates":[5.943495,52.934978],"type":"Point"}
}