{
  "type": "Feature",
  "properties": {
    "iso:country":"NL",
    "sg:address":"Grindwg 220",
    "sg:city":"Rotterdam",
    "sg:orig_category":"Fotoreportages",
    "sg:phone":"+31 10 461 1675",
    "sg:postcode":"3055 VD",
    "sg:province":"South Holland",
    "wof:name":"Nelisse Peter",
    "wof:placetype":"venue"
},
  "geometry": {"coordinates":[4.495741,51.964294],"type":"Point"}
}