{
  "type": "Feature",
  "properties": {
    "addr:full":"Noordwg 68 S Gravenhage South Holland 2548 AC",
    "addr:housenumber":"68",
    "addr:postcode":"2548 ac",
    "addr:street":"Noordwg;S Gravenhage",
    "iso:country":"NL",
    "sg:address":"Noordwg 68",
    "sg:city":"S Gravenhage",
    "sg:orig_category":"Sportverenigingen En Ontspannings- Verenigingen",
    "sg:phone":"+31 174 298 140",
    "sg:postcode":"2548 AC",
    "sg:province":"South Holland",
    "wof:name":"Devona Gymnastiek- En Jazzver",
    "wof:placetype":"venue"
},
  "geometry": {"coordinates":[4.2901,52.029888],"type":"Point"}
}