{
  "type": "Feature",
  "properties": {
    "addr:full":"Turfstr 13 Arnhem Gelderland 6811 HL",
    "addr:housenumber":"13",
    "addr:postcode":"6811 hl",
    "addr:street":"Turfstr",
    "iso:country":"NL",
    "sg:address":"Turfstr 13",
    "sg:city":"Arnhem",
    "sg:orig_category":"Fietsen En Bromfietsen",
    "sg:phone":"+31 26 351 2062",
    "sg:postcode":"6811 HL",
    "sg:province":"Gelderland",
    "wof:name":"Reerink",
    "wof:placetype":"venue"
},
  "geometry": {"coordinates":[5.909034,51.978722],"type":"Point"}
}