{
  "type": "Feature",
  "properties": {
    "addr:full":"Voorstr 6 Holwerd Provincie Friesland 9151 HE",
    "addr:housenumber":"6",
    "addr:postcode":"9151 he",
    "addr:street":"Voorstr;Provincie Friesland",
    "iso:country":"NL",
    "sg:address":"Voorstr 6",
    "sg:city":"Holwerd",
    "sg:classifiers":[
        {
            "category":"Travel",
            "subcategory":"Hotels & Motels",
            "type":"Entertainment"
        }
    ],
    "sg:phone":"+31 519 561 552",
    "sg:postcode":"9151 HE",
    "sg:province":"Provincie Friesland",
    "wof:name":"Gouden Klok, De",
    "wof:placetype":"venue"
},
  "geometry": {"coordinates":[5.898681,53.369198],"type":"Point"}
}