{
  "type": "Feature",
  "properties": {
    "addr:full":"Postelstraat 9 Someren North Brabant 5711 EM",
    "addr:housenumber":"9",
    "addr:postcode":"5711 em",
    "addr:street":"Postelstraat",
    "iso:country":"NL",
    "sg:address":"Postelstraat 9",
    "sg:city":"Someren",
    "sg:orig_category":"Opticiens",
    "sg:phone":"+31 493 491 769",
    "sg:postcode":"5711 EM",
    "sg:province":"North Brabant",
    "wof:name":"Stokvis Optiek Brillen & Contactlenzen",
    "wof:placetype":"venue"
},
  "geometry": {"coordinates":[5.7115011215,51.3851089478],"type":"Point"}
}