{
  "type": "Feature",
  "properties": {
    "addr:full":"Markt 68 Hapert Noord-Brabant 5527 EN",
    "addr:housenumber":"68",
    "addr:postcode":"5527 en",
    "addr:street":"Markt",
    "iso:country":"NL",
    "sg:address":"Markt 68",
    "sg:city":"Hapert",
    "sg:classifiers":[
        {
            "category":"Food & Beverages",
            "subcategory":"Fruits & Vegetables",
            "type":"Retail Goods"
        }
    ],
    "sg:phone":"+31 497 385 584",
    "sg:postcode":"5527 EN",
    "sg:province":"Noord-Brabant",
    "sg:tags":[
        "groenten"
    ],
    "wof:name":"Groente- En Fruit G W Dekker",
    "wof:placetype":"venue"
},
  "geometry": {"coordinates":[5.25194,51.36969],"type":"Point"}
}