{
  "type": "Feature",
  "properties": {
    "addr:full":"Herbergierserf 30 Houten Utrecht 3991 KJ",
    "addr:housenumber":"30",
    "addr:postcode":"3991 kj",
    "addr:street":"Herbergierserf",
    "iso:country":"NL",
    "sg:address":"Herbergierserf 30",
    "sg:city":"Houten",
    "sg:classifiers":[
        {
            "category":"Professional",
            "subcategory":"Accounting & Tax Preparation",
            "type":"Services"
        }
    ],
    "sg:phone":"+31 30 635 1658",
    "sg:postcode":"3991 KJ",
    "sg:province":"Utrecht",
    "sg:tags":[
        "accountant"
    ],
    "wof:name":"Accountantskantoor Kok",
    "wof:placetype":"venue"
},
  "geometry": {"coordinates":[5.168767,52.027817],"type":"Point"}
}