{
  "type": "Feature",
  "properties": {
    "addr:full":"Sumatrastr 27 S Gravenhage Zuid-Holland 2585 CL",
    "addr:housenumber":"27;gravenhage",
    "addr:postcode":"2585",
    "addr:street":"Sumatrastr;S",
    "iso:country":"NL",
    "sg:address":"Sumatrastr 27",
    "sg:city":"S Gravenhage",
    "sg:orig_category":"Kappers",
    "sg:phone":"+31 70 350 4734",
    "sg:postcode":"2585 CL",
    "sg:province":"Zuid-Holland",
    "wof:name":"Raymond Renirie",
    "wof:placetype":"venue"
},
  "geometry": {"coordinates":[4.29777,52.094799],"type":"Point"}
}