{
  "type": "Feature",
  "properties": {
    "addr:full":"Langeweide 89 Zaandam Noord-Holland 1507 NC",
    "addr:housenumber":"89;1507",
    "addr:postcode":"nc",
    "addr:street":"Langeweide",
    "iso:country":"NL",
    "sg:address":"Langeweide 89",
    "sg:city":"Zaandam",
    "sg:classifiers":[
        {
            "category":"Fast Food",
            "type":"Food & Drink"
        }
    ],
    "sg:phone":"+31 75 617 1325",
    "sg:postcode":"1507 NC",
    "sg:province":"Noord-Holland",
    "sg:tags":[
        "afhaal",
        "restaurant"
    ],
    "wof:name":"Bamboetuin",
    "wof:placetype":"venue"
},
  "geometry": {"coordinates":[4.802858,52.448437],"type":"Point"}
}