{
  "type": "Feature",
  "properties": {
    "addr:full":"Hazenstraat 33 Hilversum Noord-Holland 1216 AV",
    "addr:housenumber":"33",
    "addr:postcode":"1216 av",
    "addr:street":"Hazenstraat",
    "iso:country":"NL",
    "sg:address":"Hazenstraat 33",
    "sg:city":"Hilversum",
    "sg:orig_category":"Artiestenbureaus",
    "sg:phone":"+31 35 624 8352",
    "sg:postcode":"1216 AV",
    "sg:province":"Noord-Holland",
    "wof:name":"Lady Salon Trio Dame Blanche",
    "wof:placetype":"venue"
},
  "geometry": {"coordinates":[5.152105,52.22171],"type":"Point"}
}