{
  "type": "Feature",
  "properties": {
    "addr:full":"Saroleastraat 66 Heerlen Limburg 6411 LW",
    "addr:housenumber":"66",
    "addr:postcode":"6411 lw",
    "addr:street":"Saroleastraat",
    "iso:country":"NL",
    "sg:address":"Saroleastraat 66",
    "sg:city":"Heerlen",
    "sg:classifiers":[
        {
            "category":"Restaurant",
            "type":"Food & Drink"
        }
    ],
    "sg:phone":"+31 45 574 1128",
    "sg:postcode":"6411 LW",
    "sg:province":"Limburg",
    "wof:name":"Le Croissanterie Chez Antoine",
    "wof:placetype":"venue"
},
  "geometry": {"coordinates":[5.976756,50.889668],"type":"Point"}
}