{
  "type": "Feature",
  "properties": {
    "iso:country":"NL",
    "sg:address":"Spanker 3",
    "sg:city":"Loosdrecht",
    "sg:orig_category":"Adviesbureaus Bedrijfsorganisatie",
    "sg:phone":"+31 35 577 9560",
    "sg:postcode":"1231 TB",
    "sg:province":"North Holland",
    "wof:name":"Wardekker",
    "wof:placetype":"venue"
},
  "geometry": {"coordinates":[5.136916,52.197708],"type":"Point"}
}