{
  "type": "Feature",
  "properties": {
    "addr:full":"Spanker 3 Loosdrecht North Holland 1231 TB",
    "addr:housenumber":"3",
    "addr:postcode":"1231 tb",
    "addr:street":"Spanker",
    "iso:country":"NL",
    "sg:address":"Spanker 3",
    "sg:city":"Loosdrecht",
    "sg:orig_category":"Adviesbureaus Bedrijfsorganisatie",
    "sg:phone":"+31 35 577 9560",
    "sg:postcode":"1231 TB",
    "sg:province":"North Holland",
    "wof:name":"Wardekker",
    "wof:placetype":"venue"
},
  "geometry": {"coordinates":[5.136916,52.197708],"type":"Point"}
}