{
  "type": "Feature",
  "properties": {
    "iso:country":"NL",
    "sg:address":"Vondellaan 39",
    "sg:city":"Gemert",
    "sg:orig_category":"Begrafenisondernemers",
    "sg:phone":"+31 492 367 609",
    "sg:postcode":"5421 PN",
    "sg:province":"North Brabant",
    "wof:name":"Uitvaartverzorging Rene Van Hoof/Graco Gemert",
    "wof:placetype":"venue"
},
  "geometry": {"coordinates":[5.683474,51.559856],"type":"Point"}
}