{
  "type": "Feature",
  "properties": {
    "addr:full":"De Ravenberg 50 Beek Ubbergen Gelderland 6573 DZ",
    "addr:housenumber":"50",
    "addr:postcode":"6573 dz",
    "addr:street":"De Ravenberg",
    "iso:country":"NL",
    "sg:address":"De Ravenberg 50",
    "sg:city":"Beek Ubbergen",
    "sg:orig_category":"Keuken- Groot-Installaties",
    "sg:phone":"+31 24 366 2662",
    "sg:postcode":"6573 DZ",
    "sg:province":"Gelderland",
    "wof:name":"Kropman & Co Vof",
    "wof:placetype":"venue"
},
  "geometry": {"coordinates":[5.919494,51.829189],"type":"Point"}
}