{
  "type": "Feature",
  "properties": {
    "addr:full":"In De Cramer 17A Heerlen Limburg 6411 RS",
    "addr:housenumber":"17a",
    "addr:postcode":"6411 rs",
    "addr:street":"In De Cramer",
    "iso:country":"NL",
    "sg:address":"In De Cramer 17A",
    "sg:city":"Heerlen",
    "sg:orig_category":"Lasapparaten En Benodigdheden",
    "sg:phone":"+31 45 532 5040",
    "sg:postcode":"6411 RS",
    "sg:province":"Limburg",
    "wof:name":"Welding Wire Bv",
    "wof:placetype":"venue"
},
  "geometry": {"coordinates":[5.956326,50.895432],"type":"Point"}
}