{
  "type": "Feature",
  "properties": {
    "iso:country":"NL",
    "sg:address":"Van Dedemlaan 23",
    "sg:city":"Hoevelaken",
    "sg:orig_category":"Boekenuitgeverijen",
    "sg:phone":"+31 33 253 4575",
    "sg:postcode":"3871 TD",
    "sg:province":"Gelderland",
    "wof:name":"Prosveta",
    "wof:placetype":"venue"
},
  "geometry": {"coordinates":[5.453091,52.170929],"type":"Point"}
}