{
  "type": "Feature",
  "properties": {
    "iso:country":"NL",
    "sg:address":"Van Roijstraat 9",
    "sg:city":"Aarle Rixtel",
    "sg:orig_category":"Autokeuringen",
    "sg:phone":"+31 492 382 559",
    "sg:postcode":"5735 GC",
    "sg:province":"Noord-Brabant",
    "wof:name":"Van Dommelen Car Reconditioning",
    "wof:placetype":"venue"
},
  "geometry": {"coordinates":[5.640398,51.508572],"type":"Point"}
}