{
  "type": "Feature",
  "properties": {
    "iso:country":"NL",
    "sg:address":"Burg Feitsmapk 1",
    "sg:city":"Sliedrecht",
    "sg:orig_category":"Kinderactiviteiten",
    "sg:phone":"+31 184 417 993",
    "sg:postcode":"3362 BZ",
    "sg:province":"Zuid-Holland",
    "wof:name":"Kinderboerderij",
    "wof:placetype":"venue"
},
  "geometry": {"coordinates":[4.782451,51.822536],"type":"Point"}
}