{
  "type": "Feature",
  "properties": {
    "iso:country":"NL",
    "sg:address":"Vd Horststr 42",
    "sg:city":"Maassluis",
    "sg:orig_category":"Kappers",
    "sg:phone":"+31 10 592 7576",
    "sg:postcode":"3141 TH",
    "sg:province":"Zuid-Holland",
    "wof:name":"Salon, De",
    "wof:placetype":"venue"
},
  "geometry": {"coordinates":[4.257221,51.919067],"type":"Point"}
}