{
  "type": "Feature",
  "properties": {
    "addr:full":"C Ouwejanstr 23 Zaandam North Holland 1506 SX",
    "addr:housenumber":"23",
    "addr:postcode":"1506 sx",
    "iso:country":"NL",
    "sg:address":"C Ouwejanstr 23",
    "sg:city":"Zaandam",
    "sg:orig_category":"Meubelen",
    "sg:phone":"+31 75 614 6484",
    "sg:postcode":"1506 SX",
    "sg:province":"North Holland",
    "wof:name":"Geels Vof",
    "wof:placetype":"venue"
},
  "geometry": {"coordinates":[4.826718,52.423439],"type":"Point"}
}