{
  "type": "Feature",
  "properties": {
    "addr:full":"Braakhekkewg 9 Harfsen Gelderland 7217 SK",
    "addr:housenumber":"9",
    "addr:street":"Braakhekkewg;Gelderland 7217",
    "iso:country":"NL",
    "sg:address":"Braakhekkewg 9",
    "sg:city":"Harfsen",
    "sg:orig_category":"Bloemen En Planten",
    "sg:phone":"+31 573 431 963",
    "sg:postcode":"7217 SK",
    "sg:province":"Gelderland",
    "wof:name":"Winde, De",
    "wof:placetype":"venue"
},
  "geometry": {"coordinates":[6.298084,52.190544],"type":"Point"}
}