{
  "type": "Feature",
  "properties": {
    "iso:country":"NL",
    "sg:address":"Palmstraat 17",
    "sg:city":"Nederweert",
    "sg:orig_category":"Boekhouders",
    "sg:phone":"+31 495 633 013",
    "sg:postcode":"6031 XK",
    "sg:province":"Limburg",
    "wof:name":"Administratiekantoor Leo Roos",
    "wof:placetype":"venue"
},
  "geometry": {"coordinates":[5.738222,51.283669],"type":"Point"}
}