{
  "type": "Feature",
  "properties": {
    "addr:full":"Kerklaan 69 Nieuwerkerk Ad Ijssel South Holland 2912 CJ",
    "addr:housenumber":"69",
    "addr:postcode":"2912 cj",
    "addr:street":"Kerklaan;Ijssel",
    "iso:country":"NL",
    "sg:address":"Kerklaan 69",
    "sg:city":"Nieuwerkerk Ad Ijssel",
    "sg:orig_category":"Verlichting And Huishoudartikelen",
    "sg:phone":"+31 180 318 023",
    "sg:postcode":"2912 CJ",
    "sg:province":"South Holland",
    "wof:name":"Rene Doof Selekt Wonen",
    "wof:placetype":"venue"
},
  "geometry": {"coordinates":[4.606189,51.970325],"type":"Point"}
}