{
  "type": "Feature",
  "properties": {
    "addr:full":"Klaproosln 23 Terneuzen Zeeland 4537 CW",
    "addr:housenumber":"23",
    "addr:postcode":"4537 cw",
    "addr:street":"Klaproosln",
    "iso:country":"NL",
    "sg:address":"Klaproosln 23",
    "sg:city":"Terneuzen",
    "sg:orig_category":"Scheepvaartservice- Bureaus",
    "sg:phone":"+31 115 631 555",
    "sg:postcode":"4537 CW",
    "sg:province":"Zeeland",
    "wof:name":"Vries, De",
    "wof:placetype":"venue"
},
  "geometry": {"coordinates":[3.836728,51.320854],"type":"Point"}
}