{
  "type": "Feature",
  "properties": {
    "iso:country":"NL",
    "sg:address":"Rembrandtlaan 36",
    "sg:city":"Meppel",
    "sg:classifiers":[
        {
            "category":"Fast Food",
            "type":"Food & Drink"
        }
    ],
    "sg:phone":"+31 522 254 724",
    "sg:postcode":"7944 GH",
    "sg:province":"Provincie Drenthe",
    "sg:tags":[
        "afhaal",
        "restaurant"
    ],
    "wof:name":"Bestaria Koedijkslanden",
    "wof:placetype":"venue"
},
  "geometry": {"coordinates":[6.184624,52.686798],"type":"Point"}
}