{
  "type": "Feature",
  "properties": {
    "addr:full":"Oostpolderwg 2 Krabbendyke Zeeland 4413 NN",
    "addr:housenumber":"2",
    "addr:postcode":"4413 nn",
    "addr:street":"Oostpolderwg;Zeeland",
    "iso:country":"NL",
    "sg:address":"Oostpolderwg 2",
    "sg:city":"Krabbendyke",
    "sg:orig_category":"Verpakkingen En Verpakkingsmaterialen",
    "sg:phone":"+31 113 503 310",
    "sg:postcode":"4413 NN",
    "sg:province":"Zeeland",
    "wof:name":"Nnz Bv",
    "wof:placetype":"venue"
},
  "geometry": {"coordinates":[4.12731,51.427509],"type":"Point"}
}