{
  "type": "Feature",
  "properties": {
    "addr:full":"Burg Neetstr 37 Ouderkerk Ad Yssel South Holland 2935 BA",
    "addr:housenumber":"37",
    "addr:postcode":"2935 ba",
    "addr:street":"Burg;Yssel",
    "iso:country":"NL",
    "sg:address":"Burg Neetstr 37",
    "sg:city":"Ouderkerk Ad Yssel",
    "sg:orig_category":"Woningbouw- Verenigingen En -Stichtingen",
    "sg:phone":"+31 180 683 017",
    "sg:postcode":"2935 BA",
    "sg:province":"South Holland",
    "wof:name":"Samenwerking",
    "wof:placetype":"venue"
},
  "geometry": {"coordinates":[4.6375851631,51.932926178],"type":"Point"}
}