{
  "type": "Feature",
  "properties": {
    "addr:full":"Ds Kingwg 7 Heerenveen Friesland 8446 KZ",
    "addr:housenumber":"7",
    "addr:postcode":"8446 kz",
    "addr:street":"Ds Kingwg",
    "iso:country":"NL",
    "sg:address":"Ds Kingwg 7",
    "sg:city":"Heerenveen",
    "sg:orig_category":"Fitnesscentra",
    "sg:phone":"+31 513 628 745",
    "sg:postcode":"8446 KZ",
    "sg:province":"Friesland",
    "wof:name":"Tigra",
    "wof:placetype":"venue"
},
  "geometry": {"coordinates":[5.926671,52.947525],"type":"Point"}
}