{
  "type": "Feature",
  "properties": {
    "iso:country":"NL",
    "sg:address":"Frankenstraat 12",
    "sg:city":"'S Gravenhage",
    "sg:orig_category":"Vertaal- And Tolkenbureaus",
    "sg:phone":"+31 70 351 4501",
    "sg:postcode":"2582 SK",
    "sg:province":"South Holland",
    "wof:name":"Joanna Serraris Business Services",
    "wof:placetype":"venue"
},
  "geometry": {"coordinates":[4.276834,52.098305],"type":"Point"}
}