{
  "type": "Feature",
  "properties": {
    "addr:full":"Industrieweg 120 Berkel En Rodenrijs Zuid-Holland 2651 BD",
    "addr:housenumber":"120",
    "addr:postcode":"2651 bd",
    "addr:street":"Industrieweg",
    "iso:country":"NL",
    "sg:address":"Industrieweg 120",
    "sg:city":"Berkel En Rodenrijs",
    "sg:orig_category":"Algemene Werktuigbouw",
    "sg:phone":"+31 10 511 4030",
    "sg:postcode":"2651 BD",
    "sg:province":"Zuid-Holland",
    "wof:name":"Metaalbedrijf Bv",
    "wof:placetype":"venue"
},
  "geometry": {"coordinates":[4.456966,51.979687],"type":"Point"}
}