{
  "type": "Feature",
  "properties": {
    "addr:full":"Dongenseweg 8 Kaatsheuvel Noord-Brabant 5171 NA",
    "addr:housenumber":"8",
    "addr:postcode":"5171 na",
    "addr:street":"Dongenseweg",
    "iso:country":"NL",
    "sg:address":"Dongenseweg 8",
    "sg:city":"Kaatsheuvel",
    "sg:orig_category":"Pluimveehouderijen",
    "sg:phone":"+31 416 276 764",
    "sg:postcode":"5171 NA",
    "sg:province":"Noord-Brabant",
    "wof:name":"A.A.O. In 'T Groen",
    "wof:placetype":"venue"
},
  "geometry": {"coordinates":[4.991824,51.648705],"type":"Point"}
}