{
  "type": "Feature",
  "properties": {
    "iso:country":"NL",
    "sg:address":"H V Viandenstr 33",
    "sg:city":"Amersfoort",
    "sg:orig_category":"Drukkerijen",
    "sg:phone":"+31 33 463 5757",
    "sg:postcode":"3817 AA",
    "sg:province":"Utrecht",
    "sg:website":"http://www.printa-perfecta.nl",
    "wof:name":"Printa Perfecta",
    "wof:placetype":"venue"
},
  "geometry": {"coordinates":[5.386085,52.152325],"type":"Point"}
}