{
  "type": "Feature",
  "properties": {
    "addr:full":"Kruiswg 855 Hoofddorp North Holland 2132 NG",
    "addr:housenumber":"855",
    "addr:postcode":"2132 ng",
    "iso:country":"NL",
    "sg:address":"Kruiswg 855",
    "sg:city":"Hoofddorp",
    "sg:orig_category":"Zoetwaren - Fabrieken En Groothandel",
    "sg:phone":"+31 23 566 0700",
    "sg:postcode":"2132 NG",
    "sg:province":"North Holland",
    "wof:name":"Kraft Foods Nl Bv",
    "wof:placetype":"venue"
},
  "geometry": {"coordinates":[4.704574,52.299278],"type":"Point"}
}