{
  "type": "Feature",
  "properties": {
    "addr:full":"Kerkpln 22 Dalfsen Overijssel 7721 AD",
    "addr:housenumber":"22",
    "addr:postcode":"7721 ad",
    "addr:street":"Kerkpln",
    "iso:country":"NL",
    "sg:address":"Kerkpln 22",
    "sg:city":"Dalfsen",
    "sg:orig_category":"Bedrijfsopleidingen",
    "sg:phone":"+31 529 434 226",
    "sg:postcode":"7721 AD",
    "sg:province":"Overijssel",
    "wof:name":"Tact",
    "wof:placetype":"venue"
},
  "geometry": {"coordinates":[6.261061,52.505207],"type":"Point"}
}