{
  "type": "Feature",
  "properties": {
    "addr:full":"Bud Abbottstraat 10 Almere NL. 1325 CP",
    "addr:housenumber":"10",
    "addr:postcode":"1325 cp",
    "addr:street":"Bud Abbottstraat;Nl.",
    "iso:country":"NL",
    "sg:address":"Bud Abbottstraat 10",
    "sg:city":"Almere",
    "sg:orig_category":"Kantoorartikelen",
    "sg:phone":"+31 36 537 5140",
    "sg:postcode":"1325 CP",
    "sg:province":"NL.",
    "wof:name":"Hms",
    "wof:placetype":"venue"
},
  "geometry": {"coordinates":[5.2317609787,52.3750114441],"type":"Point"}
}