{
  "type": "Feature",
  "properties": {
    "addr:full":"Hoogstraat 26 Woudrichem North Brabant 4285 AH",
    "addr:housenumber":"26",
    "addr:postcode":"4285 ah",
    "addr:street":"Hoogstraat",
    "iso:country":"NL",
    "sg:address":"Hoogstraat 26",
    "sg:city":"Woudrichem",
    "sg:orig_category":"Fruit And Groenten Gh",
    "sg:phone":"+31 183 302 711",
    "sg:postcode":"4285 AH",
    "sg:province":"North Brabant",
    "wof:name":"J. Berm",
    "wof:placetype":"venue"
},
  "geometry": {"coordinates":[5.004733,51.817715],"type":"Point"}
}