{
  "type": "Feature",
  "properties": {
    "addr:full":"Ruitersstraat 24 Landgraaf Limburg 6371 GP",
    "addr:housenumber":"24",
    "addr:postcode":"6371 gp",
    "addr:street":"Ruitersstraat",
    "iso:country":"NL",
    "sg:address":"Ruitersstraat 24",
    "sg:city":"Landgraaf",
    "sg:orig_category":"Banken And Kredietinstellingen",
    "sg:phone":"+31 45 531 5441",
    "sg:postcode":"6371 GP",
    "sg:province":"Limburg",
    "wof:name":"Ing Bank",
    "wof:placetype":"venue"
},
  "geometry": {"coordinates":[6.014582,50.898624],"type":"Point"}
}