{
  "type": "Feature",
  "properties": {
    "iso:country":"NL",
    "sg:address":"Raadhuispln 12",
    "sg:city":"Veendam",
    "sg:orig_category":"Opticiens",
    "sg:phone":"+31 598 619 490",
    "sg:postcode":"9641 AW",
    "sg:province":"Groningen",
    "wof:name":"Greving & Greving",
    "wof:placetype":"venue"
},
  "geometry": {"coordinates":[6.8779401779,53.1044082642],"type":"Point"}
}