{
  "type": "Feature",
  "properties": {
    "iso:country":"NL",
    "sg:address":"Huizerweg 17-19",
    "sg:city":"Bussum",
    "sg:orig_category":"Gespecialiseerde Voeding",
    "sg:phone":"+31 35 698 1515",
    "sg:postcode":"1401 GD",
    "sg:province":"Noord-Holland",
    "wof:name":"Natuurwinkel Bussum",
    "wof:placetype":"venue"
},
  "geometry": {"coordinates":[5.169783,52.274342],"type":"Point"}
}