{
  "type": "Feature",
  "properties": {
    "addr:full":"De Strodekker 1 Boxtel North Brabant 5283 NN",
    "addr:housenumber":"1",
    "addr:postcode":"5283 nn",
    "addr:street":"De Strodekker",
    "iso:country":"NL",
    "sg:address":"De Strodekker 1",
    "sg:city":"Boxtel",
    "sg:orig_category":"Administratie- En Boekhoudkantoren",
    "sg:phone":"+31 411 674 739",
    "sg:postcode":"5283 NN",
    "sg:province":"North Brabant",
    "wof:name":"Ask-It",
    "wof:placetype":"venue"
},
  "geometry": {"coordinates":[5.347207,51.582272],"type":"Point"}
}