{
  "type": "Feature",
  "properties": {
    "iso:country":"NL",
    "sg:address":"Kuiper 1 , (Ind Terr Haagdoorn)",
    "sg:city":"Eersel",
    "sg:orig_category":"Tekstverwerking - Servicebureaus",
    "sg:phone":"+31 497 516 222",
    "sg:postcode":"5521 DG",
    "sg:province":"Noord-Brabant",
    "wof:name":"Agee",
    "wof:placetype":"venue"
},
  "geometry": {"coordinates":[5.319393,51.365993],"type":"Point"}
}