{
  "type": "Feature",
  "properties": {
    "addr:full":"Marktstraat 56 Musselkanaal Groningen 9581 AC",
    "addr:housenumber":"56",
    "addr:postcode":"9581 ac",
    "addr:street":"Marktstraat",
    "iso:country":"NL",
    "sg:address":"Marktstraat 56",
    "sg:city":"Musselkanaal",
    "sg:orig_category":"Kappers",
    "sg:phone":"+31 599 417 835",
    "sg:postcode":"9581 AC",
    "sg:province":"Groningen",
    "wof:name":"Kapsalon Mireille",
    "wof:placetype":"venue"
},
  "geometry": {"coordinates":[7.0141448975,52.9294891357],"type":"Point"}
}