{
  "type": "Feature",
  "properties": {
    "addr:full":"Moerbeiln 56 Hilversum Noord-Holland 1214 LX",
    "addr:housenumber":"56",
    "addr:postcode":"1214 lx",
    "addr:street":"Moerbeiln",
    "iso:country":"NL",
    "sg:address":"Moerbeiln 56",
    "sg:city":"Hilversum",
    "sg:orig_category":"Dtp",
    "sg:phone":"+31 35 622 1741",
    "sg:postcode":"1214 LX",
    "sg:province":"Noord-Holland",
    "wof:name":"Vergouwe Graphics",
    "wof:placetype":"venue"
},
  "geometry": {"coordinates":[5.1695,52.228565],"type":"Point"}
}