{
  "type": "Feature",
  "properties": {
    "addr:full":"Dorpsstraat 563 Noord-Scharwoude North Holland 1723 HA",
    "addr:housenumber":"563",
    "addr:postcode":"1723 ha",
    "addr:street":"Dorpsstraat",
    "iso:country":"NL",
    "sg:address":"Dorpsstraat 563",
    "sg:city":"Noord-Scharwoude",
    "sg:classifiers":[
        {
            "category":"Food & Beverages",
            "subcategory":"Fruits & Vegetables",
            "type":"Retail Goods"
        }
    ],
    "sg:phone":"+31 226 315 065",
    "sg:postcode":"1723 HA",
    "sg:province":"North Holland",
    "sg:tags":[
        "groenten"
    ],
    "wof:name":"P.N. Duijs",
    "wof:placetype":"venue"
},
  "geometry": {"coordinates":[4.810541,52.700287],"type":"Point"}
}