{
  "type": "Feature",
  "properties": {
    "iso:country":"NL",
    "sg:address":"Dorpspln 1",
    "sg:city":"Terheyden",
    "sg:orig_category":"Bejaarden - Verzorgingstehuizen",
    "sg:phone":"+31 76 593 2910",
    "sg:postcode":"4844 CM",
    "sg:province":"Noord-Brabant",
    "wof:name":"Antonius Abt, St Cierconflex",
    "wof:placetype":"venue"
},
  "geometry": {"coordinates":[4.753285,51.642422],"type":"Point"}
}