{
  "type": "Feature",
  "properties": {
    "addr:full":"Cereslaan 50 Bussum Noord-Holland 1402 LL",
    "addr:housenumber":"50;1402",
    "addr:postcode":"ll",
    "addr:street":"Cereslaan",
    "iso:country":"NL",
    "sg:address":"Cereslaan 50",
    "sg:city":"Bussum",
    "sg:orig_category":"Diverse Grafische Activiteiten",
    "sg:phone":"+31 35 692 2035",
    "sg:postcode":"1402 LL",
    "sg:province":"Noord-Holland",
    "wof:name":"All Grafix Grafisch Ontwerp",
    "wof:placetype":"venue"
},
  "geometry": {"coordinates":[5.166581,52.27211],"type":"Point"}
}