{
  "type": "Feature",
  "properties": {
    "addr:full":"Middenwg 16 Breezand Noord-Holland 1764 KL",
    "addr:housenumber":"16",
    "addr:postcode":"1764 kl",
    "addr:street":"Middenwg",
    "iso:country":"NL",
    "sg:address":"Middenwg 16",
    "sg:city":"Breezand",
    "sg:orig_category":"Bloemen En Planten",
    "sg:phone":"+31 6 51824600",
    "sg:postcode":"1764 KL",
    "sg:province":"Noord-Holland",
    "wof:name":"Dijk, J C Van",
    "wof:placetype":"venue"
},
  "geometry": {"coordinates":[4.807318,52.874992],"type":"Point"}
}