{
  "type": "Feature",
  "properties": {
    "iso:country":"NL",
    "sg:address":"Wittebollestraat 45",
    "sg:city":"Tilburg",
    "sg:orig_category":"Verhuur Audiovisuele Apparatuur",
    "sg:phone":"+31 13 535 0634",
    "sg:postcode":"5046 CE",
    "sg:province":"North Brabant",
    "wof:name":"Vof Leylox",
    "wof:placetype":"venue"
},
  "geometry": {"coordinates":[5.07958,51.575424],"type":"Point"}
}