{
  "type": "Feature",
  "properties": {
    "addr:full":"Brinkmannpassage 32 Haarlem North Holland 2011 NZ",
    "addr:housenumber":"32",
    "addr:postcode":"2011 nz",
    "addr:street":"Brinkmannpassage",
    "iso:country":"NL",
    "sg:address":"Brinkmannpassage 32",
    "sg:city":"Haarlem",
    "sg:orig_category":"Boeken En Tijdschriften",
    "sg:phone":"+31 23 531 6781",
    "sg:postcode":"2011 NZ",
    "sg:province":"North Holland",
    "wof:name":"Ako",
    "wof:placetype":"venue"
},
  "geometry": {"coordinates":[4.63594,52.381596],"type":"Point"}
}