{
  "type": "Feature",
  "properties": {
    "addr:full":"St Janstr 97 Sprundel North Brabant 4714 EC",
    "addr:housenumber":"97",
    "addr:postcode":"4714 ec",
    "iso:country":"NL",
    "sg:address":"St Janstr 97",
    "sg:city":"Sprundel",
    "sg:orig_category":"Woninginrichting",
    "sg:phone":"+31 165 388 008",
    "sg:postcode":"4714 EC",
    "sg:province":"North Brabant",
    "wof:name":"Meubeltrend",
    "wof:placetype":"venue"
},
  "geometry": {"coordinates":[4.6043119431,51.538684845],"type":"Point"}
}