{
  "type": "Feature",
  "properties": {
    "addr:full":"Kruizemuntstr 245 Apeldoorn Gelderland 7322 LL",
    "addr:housenumber":"245",
    "addr:postcode":"7322 ll",
    "addr:street":"Gelderland",
    "iso:country":"NL",
    "sg:address":"Kruizemuntstr 245",
    "sg:city":"Apeldoorn",
    "sg:orig_category":"Video - Faciliteiten En Producties",
    "sg:phone":"+31 55 360 1621",
    "sg:postcode":"7322 LL",
    "sg:province":"Gelderland",
    "sg:website":"http://www.bedrijfstelevisie.nl",
    "wof:name":"Eelco Gelling, Bedrijfstelevisie",
    "wof:placetype":"venue"
},
  "geometry": {"coordinates":[5.989221,52.218037],"type":"Point"}
}