{
  "type": "Feature",
  "properties": {
    "iso:country":"NL",
    "sg:address":"Lindenln 24",
    "sg:city":"Heerhugowaard",
    "sg:orig_category":"Administratie- En Boekhoudkantoren",
    "sg:phone":"+31 72 571 6706",
    "sg:postcode":"1701 GV",
    "sg:province":"Noord-Holland",
    "wof:name":"Heiligers Bv, A H",
    "wof:placetype":"venue"
},
  "geometry": {"coordinates":[4.827522,52.665195],"type":"Point"}
}