{
  "type": "Feature",
  "properties": {
    "iso:country":"NL",
    "sg:address":"Albrandswaardsedk 64",
    "sg:city":"Poortugaal",
    "sg:orig_category":"Verenigingen En Stichtingen",
    "sg:phone":"+31 10 501 7339",
    "sg:postcode":"3172 TJ",
    "sg:province":"South Holland",
    "wof:name":"Foekepot, De",
    "wof:placetype":"venue"
},
  "geometry": {"coordinates":[4.39803,51.84885],"type":"Point"}
}