{
  "type": "Feature",
  "properties": {
    "addr:full":"Spiegelstr 32 Bussum Noord-Holland 1405 HX",
    "addr:housenumber":"32",
    "addr:postcode":"1405 hx",
    "addr:street":"Spiegelstr",
    "iso:country":"NL",
    "sg:address":"Spiegelstr 32",
    "sg:city":"Bussum",
    "sg:orig_category":"Woninginrichting",
    "sg:phone":"+31 35 691 3668",
    "sg:postcode":"1405 HX",
    "sg:province":"Noord-Holland",
    "wof:name":"Rijswijk, Fa C",
    "wof:placetype":"venue"
},
  "geometry": {"coordinates":[5.1591610909,52.2742080688],"type":"Point"}
}