{
  "type": "Feature",
  "properties": {
    "addr:full":"Westln 27 Pynacker South Holland 2641 DS",
    "addr:housenumber":"27",
    "addr:postcode":"2641 ds",
    "addr:street":"Westln;Pynacker South",
    "iso:country":"NL",
    "sg:address":"Westln 27",
    "sg:city":"Pynacker",
    "sg:orig_category":"Makelaars En Adviseurs Onroerende Goederen",
    "sg:phone":"+31 15 369 4744",
    "sg:postcode":"2641 DS",
    "sg:province":"South Holland",
    "wof:name":"Parkplan Makelaardij Pijnacker",
    "wof:placetype":"venue"
},
  "geometry": {"coordinates":[4.425071,51.987968],"type":"Point"}
}