{
  "type": "Feature",
  "properties": {
    "addr:full":"Willemskade 19 Zwolle Overijssel 8011 AD",
    "addr:housenumber":"19",
    "addr:postcode":"8011 ad",
    "addr:street":"Willemskade",
    "iso:country":"NL",
    "sg:address":"Willemskade 19",
    "sg:city":"Zwolle",
    "sg:classifiers":[
        {
            "category":"Professional",
            "subcategory":"Accounting & Tax Preparation",
            "type":"Services"
        }
    ],
    "sg:phone":"+31 38 421 5315",
    "sg:postcode":"8011 AD",
    "sg:province":"Overijssel",
    "sg:tags":[
        "accountant"
    ],
    "wof:name":"De Vries En Vd Berg Bv",
    "wof:placetype":"venue"
},
  "geometry": {"coordinates":[6.084899,52.509129],"type":"Point"}
}