{
  "type": "Feature",
  "properties": {
    "iso:country":"NL",
    "sg:address":"Vondellaan 38",
    "sg:city":"Bergen Op Zoom",
    "sg:orig_category":"Bedrijfs- And Managementsconsultants",
    "sg:phone":"+31 164 250 752",
    "sg:postcode":"4624 HM",
    "sg:province":"North Brabant",
    "wof:name":"Van Rompaey Consulting",
    "wof:placetype":"venue"
},
  "geometry": {"coordinates":[4.29789,51.485493],"type":"Point"}
}