{
  "type": "Feature",
  "properties": {
    "iso:country":"NL",
    "sg:address":"Van Merodestraat 14",
    "sg:city":"Leidschendam",
    "sg:orig_category":"Bloemen And Planten Gh",
    "sg:phone":"+31 71 580 3152",
    "sg:postcode":"2266 JX",
    "sg:province":"Zuid-Holland",
    "wof:name":"J W A Borst Hand In Grond",
    "wof:placetype":"venue"
},
  "geometry": {"coordinates":[4.472552,52.095364],"type":"Point"}
}