{
  "type": "Feature",
  "properties": {
    "addr:full":"Middenstr 35 Lobith Gelderland 6915 AM",
    "addr:housenumber":"35",
    "addr:postcode":"6915",
    "addr:street":"Middenstr;Gelderland",
    "iso:country":"NL",
    "sg:address":"Middenstr 35",
    "sg:city":"Lobith",
    "sg:orig_category":"Kappers",
    "sg:phone":"+31 316 541 335",
    "sg:postcode":"6915 AM",
    "sg:province":"Gelderland",
    "wof:name":"Moustache Haarmode",
    "wof:placetype":"venue"
},
  "geometry": {"coordinates":[6.11936,51.861904],"type":"Point"}
}