{
  "type": "Feature",
  "properties": {
    "addr:full":"Grootmeesterpln 48 Utrecht Utrecht 3554 EE",
    "addr:housenumber":"48",
    "addr:postcode":"3554 ee",
    "addr:street":"Grootmeesterpln",
    "iso:country":"NL",
    "sg:address":"Grootmeesterpln 48",
    "sg:city":"Utrecht",
    "sg:orig_category":"Autorijscholen",
    "sg:phone":"+31 30 234 1941",
    "sg:postcode":"3554 EE",
    "sg:province":"Utrecht",
    "wof:name":"Fred Auto- En Motorrijschool",
    "wof:placetype":"venue"
},
  "geometry": {"coordinates":[5.090429,52.112713],"type":"Point"}
}