{
  "type": "Feature",
  "properties": {
    "addr:full":"Koningshof 14 Obdam Noord-Holland 1713 BJ",
    "addr:housenumber":"14",
    "addr:postcode":"1713 bj",
    "addr:street":"Koningshof",
    "iso:country":"NL",
    "sg:address":"Koningshof 14",
    "sg:city":"Obdam",
    "sg:orig_category":"Schilders",
    "sg:phone":"+31 226 451 287",
    "sg:postcode":"1713 BJ",
    "sg:province":"Noord-Holland",
    "wof:name":"John Rood",
    "wof:placetype":"venue"
},
  "geometry": {"coordinates":[4.910987,52.673267],"type":"Point"}
}