{
  "type": "Feature",
  "properties": {
    "addr:full":"Hollandscheveld Opgaande 34 Hollandscheveld Drenthe 7913 VD",
    "addr:housenumber":"34",
    "addr:postcode":"7913 vd",
    "addr:street":"Opgaande",
    "iso:country":"NL",
    "sg:address":"Hollandscheveld Opgaande 34",
    "sg:city":"Hollandscheveld",
    "sg:orig_category":"Geluidsopnamen",
    "sg:phone":"+31 528 342 286",
    "sg:postcode":"7913 VD",
    "sg:province":"Drenthe",
    "wof:name":"Opnamestudio No Name",
    "wof:placetype":"venue"
},
  "geometry": {"coordinates":[6.522227,52.706612],"type":"Point"}
}