{
  "type": "Feature",
  "properties": {
    "iso:country":"NL",
    "sg:address":"Blekersdk 30",
    "sg:city":"Dordrecht",
    "sg:orig_category":"Administratie- En Boekhoudkantoren",
    "sg:phone":"+31 78 613 9106",
    "sg:postcode":"3311 LE",
    "sg:province":"Zuid-Holland",
    "wof:name":"Drielen, B Van",
    "wof:placetype":"venue"
},
  "geometry": {"coordinates":[4.670897,51.811104],"type":"Point"}
}