{
  "type": "Feature",
  "properties": {
    "addr:full":"Het Haagje 156 Hoogeveen Drenthe 7906 AE",
    "addr:housenumber":"156",
    "addr:postcode":"7906 ae",
    "addr:street":"Het Haagje",
    "iso:country":"NL",
    "sg:address":"Het Haagje 156",
    "sg:city":"Hoogeveen",
    "sg:orig_category":"Woninginrichting",
    "sg:phone":"+31 528 263 108",
    "sg:postcode":"7906 AE",
    "sg:province":"Drenthe",
    "wof:name":"Woonwinkel, De",
    "wof:placetype":"venue"
},
  "geometry": {"coordinates":[6.4866528511,52.7208824158],"type":"Point"}
}