{
  "type": "Feature",
  "properties": {
    "addr:full":"Norbertynenstr 3 Arnhem Gelderland 6823 PJ",
    "addr:housenumber":"3",
    "addr:postcode":"6823 pj",
    "addr:street":"Norbertynenstr",
    "iso:country":"NL",
    "sg:address":"Norbertynenstr 3",
    "sg:city":"Arnhem",
    "sg:orig_category":"Belastingconsulenten/ Belastingadviseurs",
    "sg:phone":"+31 26 339 2449",
    "sg:postcode":"6823 PJ",
    "sg:province":"Gelderland",
    "wof:name":"Jagt, Van Der",
    "wof:placetype":"venue"
},
  "geometry": {"coordinates":[5.93804,52.002609],"type":"Point"}
}