{
  "type": "Feature",
  "properties": {
    "addr:full":"Mariastraat 57 Rijen North Brabant 5121 JV",
    "addr:housenumber":"57",
    "addr:postcode":"5121 jv",
    "addr:street":"Mariastraat",
    "iso:country":"NL",
    "sg:address":"Mariastraat 57",
    "sg:city":"Rijen",
    "sg:orig_category":"Technische Studies And Onderzoek",
    "sg:phone":"+31 161 227 176",
    "sg:postcode":"5121 JV",
    "sg:province":"North Brabant",
    "wof:name":"Van Straten Van Der Haven Contructieadviseurs Bv",
    "wof:placetype":"venue"
},
  "geometry": {"coordinates":[4.914258,51.590279],"type":"Point"}
}