{
  "type": "Feature",
  "properties": {
    "addr:full":"Sixlaan 31 Hillegom Zuid-Holland 2182 AA",
    "addr:housenumber":"31",
    "addr:postcode":"2182 aa",
    "addr:street":"Sixlaan",
    "iso:country":"NL",
    "sg:address":"Sixlaan 31",
    "sg:city":"Hillegom",
    "sg:orig_category":"Politie",
    "sg:phone":"+31 71 364 4486",
    "sg:postcode":"2182 AA",
    "sg:province":"Zuid-Holland",
    "wof:name":"Politie Hollands Midden Bureau Hillegom",
    "wof:placetype":"venue"
},
  "geometry": {"coordinates":[4.577773,52.29842],"type":"Point"}
}