{
  "type": "Feature",
  "properties": {
    "addr:full":"Dennenln 122 Zwanenburg Noord-Holland 1161 CT",
    "addr:housenumber":"122",
    "addr:postcode":"1161 ct",
    "addr:street":"Zwanenburg",
    "iso:country":"NL",
    "sg:address":"Dennenln 122",
    "sg:city":"Zwanenburg",
    "sg:orig_category":"Fietshandelaren",
    "sg:phone":"+31 20 497 8874",
    "sg:postcode":"1161 CT",
    "sg:province":"Noord-Holland",
    "wof:name":"Reus Wielersport",
    "wof:placetype":"venue"
},
  "geometry": {"coordinates":[4.747476,52.376595],"type":"Point"}
}