{
  "type": "Feature",
  "properties": {
    "iso:country":"NL",
    "sg:address":"Van Goghlaan 30",
    "sg:city":"Bleiswijk",
    "sg:orig_category":"Vertaal- And Tolkenbureaus",
    "sg:phone":"+31 10 521 9397",
    "sg:postcode":"2665 XC",
    "sg:province":"Zuid-Holland",
    "wof:name":"La Loupe",
    "wof:placetype":"venue"
},
  "geometry": {"coordinates":[4.527104,52.009842],"type":"Point"}
}