{
  "type": "Feature",
  "properties": {
    "addr:full":"Postbus 571 Hoofddorp Noord-Holland 2130 AN",
    "addr:housenumber":"571",
    "addr:postcode":"2130 an",
    "addr:street":"Postbus",
    "iso:country":"NL",
    "sg:address":"Postbus 571",
    "sg:city":"Hoofddorp",
    "sg:orig_category":"Verenigingen En Stichtingen",
    "sg:phone":"+31 23 564 1313",
    "sg:postcode":"2130 AN",
    "sg:province":"Noord-Holland",
    "wof:name":"Vluchtelingenwerk Haarlemmermeer, Sticht",
    "wof:placetype":"venue"
},
  "geometry": {"coordinates":[4.68729,52.308708],"type":"Point"}
}