{
  "type": "Feature",
  "properties": {
    "addr:full":"Oranjestr 22 Velp Gld Gelderland 6881 SE",
    "addr:housenumber":"22;6881",
    "addr:street":"Oranjestr;Gld Gelderland;Se",
    "iso:country":"NL",
    "sg:address":"Oranjestr 22",
    "sg:city":"Velp Gld",
    "sg:orig_category":"Kappers",
    "sg:phone":"+31 26 364 8320",
    "sg:postcode":"6881 SE",
    "sg:province":"Gelderland",
    "wof:name":"Mystic Haarmode Velp",
    "wof:placetype":"venue"
},
  "geometry": {"coordinates":[5.969662,51.995266],"type":"Point"}
}