{
  "type": "Feature",
  "properties": {
    "addr:full":"Stationsplein 33 Almere Flevoland 1315 KT",
    "addr:housenumber":"33",
    "addr:postcode":"1315 kt",
    "addr:street":"Stationsplein;Flevoland",
    "iso:country":"NL",
    "sg:address":"Stationsplein 33",
    "sg:city":"Almere",
    "sg:orig_category":"Wasserettes And Stomerijen",
    "sg:phone":"+31 36 534 1355",
    "sg:postcode":"1315 KT",
    "sg:province":"Flevoland",
    "wof:name":"Palthe Stomerijen Bv",
    "wof:placetype":"venue"
},
  "geometry": {"coordinates":[5.2191457748,52.3747940063],"type":"Point"}
}