{
  "type": "Feature",
  "properties": {
    "iso:country":"NL",
    "sg:address":"Oude Postwg 129",
    "sg:city":"Austerlitz",
    "sg:orig_category":"Zuivel - Groothandel",
    "sg:phone":"+31 343 491 652",
    "sg:postcode":"3711 AE",
    "sg:province":"Utrecht",
    "wof:name":"Kroon, N J",
    "wof:placetype":"venue"
},
  "geometry": {"coordinates":[5.313458,52.079159],"type":"Point"}
}