{
  "type": "Feature",
  "properties": {
    "addr:full":"Postbus 94728 Amsterdam Drenthe 1090 GS",
    "addr:housenumber":"94728",
    "addr:postcode":"1090 gs",
    "addr:street":"Postbus",
    "iso:country":"NL",
    "sg:address":"Postbus 94728",
    "sg:city":"Amsterdam",
    "sg:orig_category":"Verenigingen En Stichtingen",
    "sg:phone":"+31 20 779 6702",
    "sg:postcode":"1090 GS",
    "sg:province":"Drenthe",
    "wof:name":"Last-Post, Sticht De",
    "wof:placetype":"venue"
},
  "geometry": {"coordinates":[4.89205,52.37355],"type":"Point"}
}