{
  "type": "Feature",
  "properties": {
    "addr:full":"J Oudegeeststr 11 Schiedam Zuid-Holland 3119 HB",
    "addr:housenumber":"11",
    "addr:postcode":"3119 hb",
    "iso:country":"NL",
    "sg:address":"J Oudegeeststr 11",
    "sg:city":"Schiedam",
    "sg:classifiers":[
        {
            "category":"Retail",
            "subcategory":"Storage",
            "type":"Services"
        }
    ],
    "sg:phone":"+31 10 273 6077",
    "sg:postcode":"3119 HB",
    "sg:province":"Zuid-Holland",
    "sg:tags":[
        "op-",
        "en",
        "overslagbedrijven"
    ],
    "wof:name":"Rojo",
    "wof:placetype":"venue"
},
  "geometry": {"coordinates":[4.39816,51.918472],"type":"Point"}
}