{
  "type": "Feature",
  "properties": {
    "addr:full":"Noorderdiep 330A Nieuw Buinen Provincie Drenthe 9521 BM",
    "addr:housenumber":"330a",
    "addr:postcode":"9521 bm",
    "addr:street":"Noorderdiep;Drenthe",
    "iso:country":"NL",
    "sg:address":"Noorderdiep 330A",
    "sg:city":"Nieuw Buinen",
    "sg:classifiers":[
        {
            "category":"Personal",
            "subcategory":"Nail Salon",
            "type":"Services"
        }
    ],
    "sg:phone":"+31 599 620 910",
    "sg:postcode":"9521 BM",
    "sg:province":"Provincie Drenthe",
    "sg:tags":[
        "pedicure"
    ],
    "wof:name":"Gineke Rasters",
    "wof:placetype":"venue"
},
  "geometry": {"coordinates":[6.941666,52.960991],"type":"Point"}
}