{
  "type": "Feature",
  "properties": {
    "addr:full":"Oude Dijk 10 Rosmalen North Brabant 5241 CV",
    "addr:housenumber":"10",
    "addr:postcode":"5241 cv",
    "addr:street":"Oude Dijk",
    "iso:country":"NL",
    "sg:address":"Oude Dijk 10",
    "sg:city":"Rosmalen",
    "sg:orig_category":"Kappers",
    "sg:phone":"+31 73 521 5501",
    "sg:postcode":"5241 CV",
    "sg:province":"North Brabant",
    "wof:name":"Ron'S Haarmode",
    "wof:placetype":"venue"
},
  "geometry": {"coordinates":[5.360221,51.718529],"type":"Point"}
}