{
  "type": "Feature",
  "properties": {
    "addr:full":"Schuttersveld 1 Enschede NL.08 7514 AC",
    "addr:housenumber":"1",
    "addr:postcode":"7514 ac",
    "addr:street":"Schuttersveld",
    "iso:country":"NL",
    "sg:address":"Schuttersveld 1",
    "sg:city":"Enschede",
    "sg:orig_category":"Meubelzaken, Woning- And Keukeninrichting",
    "sg:phone":"+31 53 433 4434",
    "sg:postcode":"7514 AC",
    "sg:province":"NL.08",
    "wof:name":"Johan Nijenhuis Interieurs",
    "wof:placetype":"venue"
},
  "geometry": {"coordinates":[6.881211,52.2253],"type":"Point"}
}