{
  "type": "Feature",
  "properties": {
    "iso:country":"NL",
    "sg:address":"Schoolstraat 2",
    "sg:city":"Oostkapelle",
    "sg:orig_category":"Kinderopvang Behalve Thuis",
    "sg:phone":"+31 118 583 835",
    "sg:postcode":"4356 BX",
    "sg:province":"Zeeland",
    "wof:name":"Kleine Beer",
    "wof:placetype":"venue"
},
  "geometry": {"coordinates":[3.550562,51.56525],"type":"Point"}
}