{
  "type": "Feature",
  "properties": {
    "iso:country":"NL",
    "sg:address":"A V Ostadeln 21",
    "sg:city":"Utrecht",
    "sg:orig_category":"Psychologen",
    "sg:phone":"+31 30 252 1128",
    "sg:postcode":"3583 AA",
    "sg:province":"Utrecht",
    "wof:name":"Jong, Tieneke De",
    "wof:placetype":"venue"
},
  "geometry": {"coordinates":[5.14371,52.086601],"type":"Point"}
}