{
  "type": "Feature",
  "properties": {
    "addr:full":"Roeselarestr 210 Breda North Brabant 4826 JL",
    "addr:housenumber":"210",
    "addr:postcode":"4826 jl",
    "iso:country":"NL",
    "sg:address":"Roeselarestr 210",
    "sg:city":"Breda",
    "sg:orig_category":"Glazenwasserijen",
    "sg:phone":"+31 76 522 5642",
    "sg:postcode":"4826 JL",
    "sg:province":"North Brabant",
    "wof:name":"Verhelpen, F M",
    "wof:placetype":"venue"
},
  "geometry": {"coordinates":[4.787718,51.607449],"type":"Point"}
}