{
  "type": "Feature",
  "properties": {
    "addr:full":"Suderstrand 2 Stavoren Friesland 8715 HP",
    "addr:housenumber":"2",
    "addr:postcode":"8715 hp",
    "addr:street":"Suderstrand",
    "iso:country":"NL",
    "sg:address":"Suderstrand 2",
    "sg:city":"Stavoren",
    "sg:orig_category":"Jachthavens - Jachtwerven",
    "sg:phone":"+31 514 684 674",
    "sg:postcode":"8715 HP",
    "sg:province":"Friesland",
    "sg:website":"HTTP://www.skipsmaritiem.nl",
    "wof:name":"Marina Stavoren Buitenhaven Bv",
    "wof:placetype":"venue"
},
  "geometry": {"coordinates":[5.364776,52.876492],"type":"Point"}
}