{
  "type": "Feature",
  "properties": {
    "iso:country":"NL",
    "sg:address":"Hekerbeekwg 86",
    "sg:city":"Valkenburg Lb",
    "sg:classifiers":[
        {
            "category":"Banks & Credit Unions",
            "subcategory":"Investment Brokerage",
            "type":"Services"
        }
    ],
    "sg:phone":"+31 43 601 3175",
    "sg:postcode":"6301 EN",
    "sg:province":"Limburg",
    "sg:tags":[
        "pension"
    ],
    "wof:name":"Scheepers",
    "wof:placetype":"venue"
},
  "geometry": {"coordinates":[5.844469,50.871548],"type":"Point"}
}