{
  "type": "Feature",
  "properties": {
    "addr:full":"Marconistraat 2 Dedemsvaart Overijssel 7701 SJ",
    "addr:housenumber":"2",
    "addr:postcode":"7701",
    "addr:street":"Marconistraat",
    "iso:country":"NL",
    "sg:address":"Marconistraat 2",
    "sg:city":"Dedemsvaart",
    "sg:orig_category":"Meubelzaken, Woning- And Keukeninrichting",
    "sg:phone":"+31 523 615 731",
    "sg:postcode":"7701 SJ",
    "sg:province":"Overijssel",
    "wof:name":"Apple International Bv",
    "wof:placetype":"venue"
},
  "geometry": {"coordinates":[6.4866700172,52.601764679],"type":"Point"}
}