{
  "type": "Feature",
  "properties": {
    "addr:full":"Woudseweg 40 Den Hoorn Zh South Holland 2635 CD",
    "addr:housenumber":"40",
    "addr:postcode":"2635 cd",
    "addr:street":"Woudseweg",
    "iso:country":"NL",
    "sg:address":"Woudseweg 40",
    "sg:city":"Den Hoorn Zh",
    "sg:orig_category":"Juridische Dienstverlening",
    "sg:phone":"+31 15 261 4098",
    "sg:postcode":"2635 CD",
    "sg:province":"South Holland",
    "wof:name":"Juridisch En Bedrijfskundig Advieskantoor",
    "wof:placetype":"venue"
},
  "geometry": {"coordinates":[4.326837,51.998974],"type":"Point"}
}