{
  "type": "Feature",
  "properties": {
    "iso:country":"NL",
    "sg:address":"V Ghentstr 13",
    "sg:city":"Twello",
    "sg:orig_category":"Juweliers",
    "sg:phone":"+31 571 272 417",
    "sg:postcode":"7391 CR",
    "sg:province":"Gelderland",
    "wof:name":"Hartgers",
    "wof:placetype":"venue"
},
  "geometry": {"coordinates":[6.106505,52.238346],"type":"Point"}
}