{
  "type": "Feature",
  "properties": {
    "addr:full":"Heusdenhoutsewg 155 Breda Noord-Brabant 4817 NB",
    "addr:housenumber":"155",
    "addr:postcode":"4817 nb",
    "iso:country":"NL",
    "sg:address":"Heusdenhoutsewg 155",
    "sg:city":"Breda",
    "sg:classifiers":[
        {
            "category":"Personal",
            "subcategory":"Nail Salon",
            "type":"Services"
        }
    ],
    "sg:phone":"+31 6 22193341",
    "sg:postcode":"4817 NB",
    "sg:province":"Noord-Brabant",
    "sg:tags":[
        "pedicure"
    ],
    "wof:name":"Hout-Luijks, H Van Den",
    "wof:placetype":"venue"
},
  "geometry": {"coordinates":[4.818288,51.593483],"type":"Point"}
}