{
  "type": "Feature",
  "properties": {
    "addr:full":"Stevensweg 39 Dordrecht South Holland 3319 AH",
    "addr:housenumber":"39",
    "addr:postcode":"3319 ah",
    "addr:street":"Stevensweg",
    "iso:country":"NL",
    "sg:address":"Stevensweg 39",
    "sg:city":"Dordrecht",
    "sg:orig_category":"Bloemen And Planten",
    "sg:phone":"+31 78 616 5167",
    "sg:postcode":"3319 AH",
    "sg:province":"South Holland",
    "wof:name":"Groenrijk De Staartploeg",
    "wof:placetype":"venue"
},
  "geometry": {"coordinates":[4.692628,51.787552],"type":"Point"}
}