{
  "type": "Feature",
  "properties": {
    "addr:full":"De Beverspyken 11 S Hertogenbosch North Brabant 5221 EE",
    "addr:housenumber":"11",
    "addr:postcode":"5221 ee",
    "addr:street":"S Hertogenbosch",
    "iso:country":"NL",
    "sg:address":"De Beverspyken 11",
    "sg:city":"S Hertogenbosch",
    "sg:orig_category":"Horecabenodigdheden",
    "sg:phone":"+31 73 621 7776",
    "sg:postcode":"5221 EE",
    "sg:province":"North Brabant",
    "wof:name":"Robben Bv, Willie",
    "wof:placetype":"venue"
},
  "geometry": {"coordinates":[5.2651,51.712406],"type":"Point"}
}