{
  "type": "Feature",
  "properties": {
    "addr:full":"Herengr 226 Amsterdam Noord-Holland 1016 BT",
    "addr:housenumber":"226",
    "addr:postcode":"1016 bt",
    "iso:country":"NL",
    "sg:address":"Herengr 226",
    "sg:city":"Amsterdam",
    "sg:orig_category":"Advocaten En Advocatenkantoren",
    "sg:phone":"+31 20 625 2410",
    "sg:postcode":"1016 BT",
    "sg:province":"Noord-Holland",
    "wof:name":"Braakman, Mr R L",
    "wof:placetype":"venue"
},
  "geometry": {"coordinates":[4.886632,52.372559],"type":"Point"}
}