{
  "type": "Feature",
  "properties": {
    "addr:full":"Gloriantdreef 4 Utrecht Utrecht 3562 KX",
    "addr:housenumber":"4",
    "addr:postcode":"3562 kx",
    "addr:street":"Gloriantdreef",
    "iso:country":"NL",
    "sg:address":"Gloriantdreef 4",
    "sg:city":"Utrecht",
    "sg:orig_category":"Advocaten And Juridische Adviseurs",
    "sg:phone":"+31 30 265 1010",
    "sg:postcode":"3562 KX",
    "sg:province":"Utrecht",
    "wof:name":"Advocatenkantoor Kragten & Van Marwijk",
    "wof:placetype":"venue"
},
  "geometry": {"coordinates":[5.111596,52.114735],"type":"Point"}
}