{
  "type": "Feature",
  "properties": {
    "addr:full":"Markerkant 10118 Almere Flevoland 1316 AL",
    "addr:housenumber":"1316",
    "addr:postcode":"10118;al",
    "addr:street":"Markerkant;Flevoland",
    "iso:country":"NL",
    "sg:address":"Markerkant 10118",
    "sg:city":"Almere",
    "sg:orig_category":"Levensmiddelen - Fabrieken En Groothandel",
    "sg:phone":"+31 36 534 6081",
    "sg:postcode":"1316 AL",
    "sg:province":"Flevoland",
    "wof:name":"Al-Sheikh",
    "wof:placetype":"venue"
},
  "geometry": {"coordinates":[5.220163,52.387119],"type":"Point"}
}