{
  "type": "Feature",
  "properties": {
    "addr:full":"De Paal 7 Unit 6 Almere NL. 1351 JB",
    "addr:housenumber":"7 unit 6",
    "addr:postcode":"1351 jb",
    "addr:street":"De Paal;Nl.",
    "iso:country":"NL",
    "sg:address":"De Paal 7 Unit 6",
    "sg:city":"Almere",
    "sg:orig_category":"Wijnkoperijen En -Groothandel",
    "sg:phone":"+31 36 538 6740",
    "sg:postcode":"1351 JB",
    "sg:province":"NL.",
    "sg:website":"http://www.vinifins.nl",
    "wof:name":"Vinifins Bv, Wijnimporteur",
    "wof:placetype":"venue"
},
  "geometry": {"coordinates":[5.2202382088,52.349521637],"type":"Point"}
}