{
  "type": "Feature",
  "properties": {
    "addr:full":"V Riebeeckstr 14 Utrecht Utrecht 3531 EJ",
    "addr:housenumber":"14",
    "addr:postcode":"3531 ej",
    "iso:country":"NL",
    "sg:address":"V Riebeeckstr 14",
    "sg:city":"Utrecht",
    "sg:orig_category":"Hondenscholen",
    "sg:phone":"+31 30 290 0388",
    "sg:postcode":"3531 EJ",
    "sg:province":"Utrecht",
    "wof:name":"Nubis - Gedragstherapie",
    "wof:placetype":"venue"
},
  "geometry": {"coordinates":[5.09574,52.090012],"type":"Point"}
}