{
  "type": "Feature",
  "properties": {
    "iso:country":"NL",
    "sg:address":"Walstraat 40",
    "sg:city":"Rijssen",
    "sg:classifiers":[
        {
            "category":"Fast Food",
            "type":"Food & Drink"
        }
    ],
    "sg:phone":"+31 548 515 016",
    "sg:postcode":"7462 BB",
    "sg:province":"Overijssel",
    "sg:tags":[
        "afhaal",
        "restaurant"
    ],
    "wof:name":"Eethuisje Walgaarde",
    "wof:placetype":"venue"
},
  "geometry": {"coordinates":[6.518732,52.307007],"type":"Point"}
}