{
  "type": "Feature",
  "properties": {
    "addr:full":"Schipluidensewg 6 Wateringen Zuid-Holland 2291 PC",
    "addr:housenumber":"6",
    "addr:postcode":"2291 pc",
    "addr:street":"Schipluidensewg",
    "iso:country":"NL",
    "sg:address":"Schipluidensewg 6",
    "sg:city":"Wateringen",
    "sg:classifiers":[
        {
            "category":"Retail",
            "subcategory":"Auto Repair",
            "type":"Services"
        }
    ],
    "sg:phone":"+31 174 221 122",
    "sg:postcode":"2291 PC",
    "sg:province":"Zuid-Holland",
    "sg:tags":[
        "garage"
    ],
    "wof:name":"Tinga",
    "wof:placetype":"venue"
},
  "geometry": {"coordinates":[4.290755,52.013779],"type":"Point"}
}