{
  "type": "Feature",
  "properties": {
    "addr:full":"Ign. Bispincklaan 1 Bloemendaal North Holland 2061 EM",
    "addr:housenumber":"1",
    "addr:postcode":"2061 em",
    "addr:street":"Ign. Bispincklaan",
    "iso:country":"NL",
    "sg:address":"Ign. Bispincklaan 1",
    "sg:city":"Bloemendaal",
    "sg:orig_category":"Kinderopvang Behalve Thuis",
    "sg:phone":"+31 23 533 8344",
    "sg:postcode":"2061 EM",
    "sg:province":"North Holland",
    "wof:name":"Buitenschoolsepvang De Toverhoed",
    "wof:placetype":"venue"
},
  "geometry": {"coordinates":[4.620803,52.40247],"type":"Point"}
}