{
  "type": "Feature",
  "properties": {
    "iso:country":"NL",
    "sg:address":"Brede Steeg 35",
    "sg:city":"Oisterwijk",
    "sg:orig_category":"Advocaten And Juridische Adviseurs",
    "sg:phone":"+31 13 528 7522",
    "sg:postcode":"5062 KG",
    "sg:province":"Noord-Brabant",
    "wof:name":"Assurantie Adv En Woningbur De Bruin Bv",
    "wof:placetype":"venue"
},
  "geometry": {"coordinates":[5.189673,51.572376],"type":"Point"}
}