{
  "type": "Feature",
  "properties": {
    "addr:full":"Predikherenln 351 Tilburg Noord-Brabant 5042 CG",
    "addr:housenumber":"351",
    "addr:postcode":"5042 cg",
    "addr:street":"Tilburg",
    "iso:country":"NL",
    "sg:address":"Predikherenln 351",
    "sg:city":"Tilburg",
    "sg:orig_category":"Autorijscholen",
    "sg:phone":"+31 13 468 3040",
    "sg:postcode":"5042 CG",
    "sg:province":"Noord-Brabant",
    "wof:name":"Onzenoord, M Van",
    "wof:placetype":"venue"
},
  "geometry": {"coordinates":[5.055182,51.575962],"type":"Point"}
}