{
  "type": "Feature",
  "properties": {
    "iso:country":"NL",
    "sg:address":"Beethovenstr 118",
    "sg:city":"Amsterdam",
    "sg:orig_category":"Verzekeringen - Verzekeringskantoren",
    "sg:phone":"+31 20 646 3125",
    "sg:postcode":"1077 JR",
    "sg:province":"North Holland",
    "wof:name":"Link, Gebr",
    "wof:placetype":"venue"
},
  "geometry": {"coordinates":[4.876493,52.346252],"type":"Point"}
}