{
  "type": "Feature",
  "properties": {
    "addr:full":"Henxelseweg 13 Winterswijk Henxel Gelderland 7113 AD",
    "addr:housenumber":"13",
    "addr:postcode":"7113 ad",
    "addr:street":"Henxelseweg",
    "iso:country":"NL",
    "sg:address":"Henxelseweg 13",
    "sg:city":"Winterswijk Henxel",
    "sg:orig_category":"Autokeuringen",
    "sg:phone":"+31 543 562 440",
    "sg:postcode":"7113 AD",
    "sg:province":"Gelderland",
    "wof:name":"G. En N. Smid Vof",
    "wof:placetype":"venue"
},
  "geometry": {"coordinates":[6.753085,51.986446],"type":"Point"}
}