{
  "type": "Feature",
  "properties": {
    "iso:country":"NL",
    "sg:address":"Schimminck 25",
    "sg:city":"Zaltbommel",
    "sg:orig_category":"Pompen And Compressoren Fab",
    "sg:phone":"+31 418 514 587",
    "sg:postcode":"5301 KR",
    "sg:province":"Gelderland",
    "wof:name":"Handelsonderneming Timmer Hydrauliek Zaltbommel Bv",
    "wof:placetype":"venue"
},
  "geometry": {"coordinates":[5.266989,51.811817],"type":"Point"}
}