{
  "type": "Feature",
  "properties": {
    "iso:country":"NL",
    "sg:address":"Gravenstraat 8",
    "sg:city":"'S Gravenzande",
    "sg:orig_category":"Bedrijfsinventaris Gh",
    "sg:phone":"+31 174 414 540",
    "sg:postcode":"2691 AL",
    "sg:province":"South Holland",
    "wof:name":"Westland Hair Cosmetics",
    "wof:placetype":"venue"
},
  "geometry": {"coordinates":[4.162572,52.003448],"type":"Point"}
}