{
  "type": "Feature",
  "properties": {
    "addr:full":"Veldsalie 16 Klazienaveen Drenthe 7891 WX",
    "addr:housenumber":"16",
    "addr:postcode":"7891 wx",
    "addr:street":"Veldsalie",
    "iso:country":"NL",
    "sg:address":"Veldsalie 16",
    "sg:city":"Klazienaveen",
    "sg:orig_category":"Fruit And Groenten Gh",
    "sg:phone":"+31 591 301 785",
    "sg:postcode":"7891 WX",
    "sg:province":"Drenthe",
    "wof:name":"De Jong En Zn.",
    "wof:placetype":"venue"
},
  "geometry": {"coordinates":[6.975908,52.733006],"type":"Point"}
}