{
  "type": "Feature",
  "properties": {
    "addr:full":"Groenestraat 38 Nijkerk Gld Gelderland 3861 CN",
    "addr:housenumber":"38",
    "addr:postcode":"3861 cn",
    "addr:street":"Groenestraat;Gld Gelderland",
    "iso:country":"NL",
    "sg:address":"Groenestraat 38",
    "sg:city":"Nijkerk Gld",
    "sg:classifiers":[
        {
            "category":"Shopping",
            "subcategory":"Gifts & Souvenirs",
            "type":"Retail Goods"
        }
    ],
    "sg:phone":"+31 33 246 0843",
    "sg:postcode":"3861 CN",
    "sg:province":"Gelderland",
    "sg:tags":[
        "geschenken"
    ],
    "wof:name":"H. Appeldoorn",
    "wof:placetype":"venue"
},
  "geometry": {"coordinates":[5.480059,52.221493],"type":"Point"}
}