{
  "type": "Feature",
  "properties": {
    "addr:full":"Geleenstraat 9 Heerlen Limburg 6411 HP",
    "addr:housenumber":"9",
    "addr:postcode":"6411 hp",
    "addr:street":"Geleenstraat",
    "iso:country":"NL",
    "sg:address":"Geleenstraat 9",
    "sg:city":"Heerlen",
    "sg:orig_category":"Bioscopen",
    "sg:phone":"+31 45 571 3030",
    "sg:postcode":"6411 HP",
    "sg:province":"Limburg",
    "wof:name":"H 5 Theaters",
    "wof:placetype":"venue"
},
  "geometry": {"coordinates":[5.978183,50.887032],"type":"Point"}
}