{
  "type": "Feature",
  "properties": {
    "iso:country":"NL",
    "sg:address":"Beeklaan 151",
    "sg:city":"'S Gravenhage",
    "sg:orig_category":"Gespecialiseerde Voeding",
    "sg:phone":"+31 70 345 3244",
    "sg:postcode":"2562 AD",
    "sg:province":"Zuid-Holland",
    "wof:name":"Indian Bazar Ned Bv",
    "wof:placetype":"venue"
},
  "geometry": {"coordinates":[4.281983,52.073509],"type":"Point"}
}