{
  "type": "Feature",
  "properties": {
    "addr:full":"Koningin Emmakade 118 A 'S Gravenhage Zuid-Holland 2518 JJ",
    "addr:housenumber":"118 a",
    "addr:postcode":"2518 jj",
    "addr:street":"Koningin Emmakade;' S",
    "iso:country":"NL",
    "sg:address":"Koningin Emmakade 118 A",
    "sg:city":"'S Gravenhage",
    "sg:classifiers":[
        {
            "category":"Bars & Pubs",
            "type":"Food & Drink"
        }
    ],
    "sg:phone":"+31 70 345 4060",
    "sg:postcode":"2518 JJ",
    "sg:province":"Zuid-Holland",
    "wof:name":"Eetcafe De Klap",
    "wof:placetype":"venue"
},
  "geometry": {"coordinates":[4.289299,52.080273],"type":"Point"}
}