{
  "type": "Feature",
  "properties": {
    "addr:full":"Kostverloren 28 Streefkerk South Holland 2959 BW",
    "addr:housenumber":"28",
    "addr:postcode":"2959 bw",
    "addr:street":"Kostverloren",
    "iso:country":"NL",
    "sg:address":"Kostverloren 28",
    "sg:city":"Streefkerk",
    "sg:classifiers":[
        {
            "category":"Personal",
            "subcategory":"Nail Salon",
            "type":"Services"
        }
    ],
    "sg:phone":"+31 184 683 598",
    "sg:postcode":"2959 BW",
    "sg:province":"South Holland",
    "sg:tags":[
        "pedicure"
    ],
    "wof:name":"Streef-Groenendijk, P T",
    "wof:placetype":"venue"
},
  "geometry": {"coordinates":[4.742725,51.899002],"type":"Point"}
}