{
  "type": "Feature",
  "properties": {
    "addr:full":"W De Withstr 180 Amsterdam Noord-Holland 1057 ZL",
    "addr:housenumber":"180",
    "addr:postcode":"1057 zl",
    "addr:street":"W De Withstr",
    "iso:country":"NL",
    "sg:address":"W De Withstr 180",
    "sg:city":"Amsterdam",
    "sg:orig_category":"Meubelen",
    "sg:phone":"+31 20 683 7763",
    "sg:postcode":"1057 ZL",
    "sg:province":"Noord-Holland",
    "wof:name":"Knolletje, Het",
    "wof:placetype":"venue"
},
  "geometry": {"coordinates":[4.859112,52.371204],"type":"Point"}
}