{
  "type": "Feature",
  "properties": {
    "addr:full":"Horsterwg 420 Venlo Limburg 5928 NJ",
    "addr:housenumber":"420",
    "addr:postcode":"5928 nj",
    "iso:country":"NL",
    "sg:address":"Horsterwg 420",
    "sg:city":"Venlo",
    "sg:orig_category":"Autopoetsbedrijven",
    "sg:phone":"+31 77 387 3790",
    "sg:postcode":"5928 NJ",
    "sg:province":"Limburg",
    "wof:name":"Aquina Bv",
    "wof:placetype":"venue"
},
  "geometry": {"coordinates":[6.11955,51.395309],"type":"Point"}
}