{
  "type": "Feature",
  "properties": {
    "addr:full":"Bydorpln 8B Zoetermeer South Holland 2713 RR",
    "addr:housenumber":"8b",
    "addr:postcode":"2713 rr",
    "addr:street":"Bydorpln",
    "iso:country":"NL",
    "sg:address":"Bydorpln 8B",
    "sg:city":"Zoetermeer",
    "sg:orig_category":"Verenigingen En Stichtingen",
    "sg:phone":"+31 79 331 3969",
    "sg:postcode":"2713 RR",
    "sg:province":"South Holland",
    "wof:name":"Mevrouw Latenstaan",
    "wof:placetype":"venue"
},
  "geometry": {"coordinates":[4.488925,52.06308],"type":"Point"}
}