{
  "type": "Feature",
  "properties": {
    "iso:country":"NL",
    "sg:address":"Willy Sluiterstraat 7",
    "sg:city":"Katwijk Zh",
    "sg:orig_category":"Geluidsopnamen",
    "sg:phone":"+31 71 407 8066",
    "sg:postcode":"2225 KC",
    "sg:province":"Zuid-Holland",
    "wof:name":"Mem",
    "wof:placetype":"venue"
},
  "geometry": {"coordinates":[4.395008,52.201031],"type":"Point"}
}