{
  "type": "Feature",
  "properties": {
    "iso:country":"NL",
    "sg:address":"Kottenseweg 132A",
    "sg:city":"Winterswijk Brinkh",
    "sg:orig_category":"Medische Apparatuur And Prothesen Fab",
    "sg:phone":"+31 543 563 334",
    "sg:postcode":"7115 AE",
    "sg:province":"Gelderland",
    "wof:name":"Brinkheurnse Tandtechniek Vof",
    "wof:placetype":"venue"
},
  "geometry": {"coordinates":[6.749419,51.953365],"type":"Point"}
}