{
  "type": "Feature",
  "properties": {
    "addr:full":"Cobrastr 18 Almere Flevoland 1338 HL",
    "addr:housenumber":"18",
    "addr:postcode":"1338 hl",
    "addr:street":"Cobrastr;Flevoland",
    "iso:country":"NL",
    "sg:address":"Cobrastr 18",
    "sg:city":"Almere",
    "sg:orig_category":"Adviesbureaus",
    "sg:phone":"+31 36 532 6498",
    "sg:postcode":"1338 HL",
    "sg:province":"Flevoland",
    "wof:name":"Alst, Van",
    "wof:placetype":"venue"
},
  "geometry": {"coordinates":[5.271137,52.382351],"type":"Point"}
}