{
  "type": "Feature",
  "properties": {
    "iso:country":"NL",
    "sg:address":"Wilde Wingerd 26",
    "sg:city":"Helmond",
    "sg:orig_category":"Binnenhuisarchitecten",
    "sg:phone":"+31 492 532 632",
    "sg:postcode":"5708 DC",
    "sg:province":"North Brabant",
    "wof:name":"Van Kasteren Arch. Buro",
    "wof:placetype":"venue"
},
  "geometry": {"coordinates":[5.61468,51.483311],"type":"Point"}
}