{
  "type": "Feature",
  "properties": {
    "addr:full":"Bilderdijkstraat 19 Heerhugowaard North Holland 1702 AM",
    "addr:housenumber":"19",
    "addr:postcode":"1702",
    "addr:street":"Bilderdijkstraat",
    "iso:country":"NL",
    "sg:address":"Bilderdijkstraat 19",
    "sg:city":"Heerhugowaard",
    "sg:orig_category":"Boekhouders",
    "sg:phone":"+31 72 571 2288",
    "sg:postcode":"1702 AM",
    "sg:province":"North Holland",
    "wof:name":"Administratiekantoor J.P. Ory",
    "wof:placetype":"venue"
},
  "geometry": {"coordinates":[4.833463,52.665363],"type":"Point"}
}