{
  "type": "Feature",
  "properties": {
    "addr:full":"Trompenbergerwg 8A Hilversum Noord-Holland 1217 BE",
    "addr:housenumber":"8a",
    "addr:postcode":"1217",
    "addr:street":"Trompenbergerwg",
    "iso:country":"NL",
    "sg:address":"Trompenbergerwg 8A",
    "sg:city":"Hilversum",
    "sg:orig_category":"Organisatiebureaus",
    "sg:phone":"+31 35 621 9131",
    "sg:postcode":"1217 BE",
    "sg:province":"Noord-Holland",
    "wof:name":"Inter P & O Bv",
    "wof:placetype":"venue"
},
  "geometry": {"coordinates":[5.1616001129,52.2349052429],"type":"Point"}
}