{
  "type": "Feature",
  "properties": {
    "addr:full":"Vyzelgr 2 Amsterdam Noord-Holland 1017 HR",
    "addr:housenumber":"2",
    "addr:postcode":"1017 hr",
    "addr:street":"Vyzelgr",
    "iso:country":"NL",
    "sg:address":"Vyzelgr 2",
    "sg:city":"Amsterdam",
    "sg:orig_category":"Ambassades/Consulaten",
    "sg:phone":"+31 20 530 6969",
    "sg:postcode":"1017 HR",
    "sg:province":"Noord-Holland",
    "wof:name":"Frankrijk Consulaat",
    "wof:placetype":"venue"
},
  "geometry": {"coordinates":[4.891104,52.361835],"type":"Point"}
}