{
  "type": "Feature",
  "properties": {
    "addr:full":"Kamphuizenlaan 29 Arnhem Gelderland 6825 EA",
    "addr:housenumber":"29",
    "addr:postcode":"6825 ea",
    "addr:street":"Kamphuizenlaan",
    "iso:country":"NL",
    "sg:address":"Kamphuizenlaan 29",
    "sg:city":"Arnhem",
    "sg:orig_category":"Schilderwerk",
    "sg:phone":"+31 26 361 7784",
    "sg:postcode":"6825 EA",
    "sg:province":"Gelderland",
    "wof:name":"Schildersbedrijf Bailly",
    "wof:placetype":"venue"
},
  "geometry": {"coordinates":[5.965469,51.982082],"type":"Point"}
}