{
  "type": "Feature",
  "properties": {
    "addr:full":"Schuwacht 242 Lekkerkerk Zuid-Holland 2941 EK",
    "addr:housenumber":"242",
    "addr:postcode":"2941 ek",
    "addr:street":"Schuwacht",
    "iso:country":"NL",
    "sg:address":"Schuwacht 242",
    "sg:city":"Lekkerkerk",
    "sg:orig_category":"Boekhouders",
    "sg:phone":"+31 180 524 596",
    "sg:postcode":"2941 EK",
    "sg:province":"Zuid-Holland",
    "wof:name":"Select Loonadministratie",
    "wof:placetype":"venue"
},
  "geometry": {"coordinates":[4.65272,51.891602],"type":"Point"}
}