{
  "type": "Feature",
  "properties": {
    "addr:full":"Nw Gouwe Wz 18A Gouda Zuid-Holland 2802 AN",
    "addr:housenumber":"18a",
    "addr:postcode":"2802 an",
    "addr:street":"Nw Gouwe Wz",
    "iso:country":"NL",
    "sg:address":"Nw Gouwe Wz 18A",
    "sg:city":"Gouda",
    "sg:orig_category":"Vaarscholen",
    "sg:phone":"+31 182 517 525",
    "sg:postcode":"2802 AN",
    "sg:province":"Zuid-Holland",
    "wof:name":"Iduna",
    "wof:placetype":"venue"
},
  "geometry": {"coordinates":[4.69882,52.013142],"type":"Point"}
}