{
  "type": "Feature",
  "properties": {
    "iso:country":"NL",
    "sg:address":"Flamingohoek 36",
    "sg:city":"Spijkenisse",
    "sg:orig_category":"Diverse Grafische Activiteiten",
    "sg:phone":"+31 181 697 288",
    "sg:postcode":"3201 HC",
    "sg:province":"Zuid-Holland",
    "wof:name":"Tilia Cordata",
    "wof:placetype":"venue"
},
  "geometry": {"coordinates":[4.319743,51.846733],"type":"Point"}
}