{
  "type": "Feature",
  "properties": {
    "iso:country":"NL",
    "sg:address":"Herestraat 2",
    "sg:city":"Grijpskerk",
    "sg:orig_category":"Makelaars In Onroerend Goed",
    "sg:phone":"+31 594 212 556",
    "sg:postcode":"9843 AK",
    "sg:province":"Groningen",
    "wof:name":"Steller & Henstra",
    "wof:placetype":"venue"
},
  "geometry": {"coordinates":[6.310302,53.263493],"type":"Point"}
}