{
  "type": "Feature",
  "properties": {
    "addr:full":"Doelstraat 52 Haarlem North Holland 2011 XD",
    "addr:housenumber":"52",
    "addr:postcode":"2011 xd",
    "addr:street":"Doelstraat",
    "iso:country":"NL",
    "sg:address":"Doelstraat 52",
    "sg:city":"Haarlem",
    "sg:orig_category":"Overheidsdiensten",
    "sg:phone":"+31 23 531 7211",
    "sg:postcode":"2011 XD",
    "sg:province":"North Holland",
    "wof:name":"Koinonia",
    "wof:placetype":"venue"
},
  "geometry": {"coordinates":[4.6312041283,52.3775138855],"type":"Point"}
}