{
  "type": "Feature",
  "properties": {
    "addr:full":"Corellistraat 5 Hazerswoude Rijndijk South Holland 2394 GZ",
    "addr:housenumber":"5",
    "addr:postcode":"2394 gz",
    "addr:street":"Corellistraat;Hazerswoude Rijndijk",
    "iso:country":"NL",
    "sg:address":"Corellistraat 5",
    "sg:city":"Hazerswoude Rijndijk",
    "sg:orig_category":"Fotostudio'S And Fotografen",
    "sg:phone":"+31 71 341 2723",
    "sg:postcode":"2394 GZ",
    "sg:province":"South Holland",
    "wof:name":"John Hakkaart Fotografie",
    "wof:placetype":"venue"
},
  "geometry": {"coordinates":[4.593625,52.12569],"type":"Point"}
}