{
  "type": "Feature",
  "properties": {
    "iso:country":"NL",
    "sg:address":"Fahrenheitweg 2",
    "sg:city":"Leeuwarden",
    "sg:orig_category":"Diverse Grafische Activiteiten",
    "sg:phone":"+31 58 212 5307",
    "sg:postcode":"8912 AJ",
    "sg:province":"Friesland",
    "wof:name":"Boekbinderij Friesland Bv",
    "wof:placetype":"venue"
},
  "geometry": {"coordinates":[5.768809,53.19381],"type":"Point"}
}