{
  "type": "Feature",
  "properties": {
    "addr:full":"Spadeln 26 Apeldoorn Gelderland 7331 AL",
    "addr:housenumber":"26",
    "addr:postcode":"7331",
    "addr:street":"Spadeln;Gelderland",
    "iso:country":"NL",
    "sg:address":"Spadeln 26",
    "sg:city":"Apeldoorn",
    "sg:orig_category":"Verpakkingsbedrijven",
    "sg:phone":"+31 55 533 1265",
    "sg:postcode":"7331 AL",
    "sg:province":"Gelderland",
    "wof:name":"Pharma Pack",
    "wof:placetype":"venue"
},
  "geometry": {"coordinates":[5.96886,52.201382],"type":"Point"}
}