{
  "type": "Feature",
  "properties": {
    "addr:full":"Brucknerstr 32 Zwyndrecht Zuid-Holland 3335 CN",
    "addr:housenumber":"32",
    "addr:postcode":"3335 cn",
    "addr:street":"Brucknerstr",
    "iso:country":"NL",
    "sg:address":"Brucknerstr 32",
    "sg:city":"Zwyndrecht",
    "sg:orig_category":"Administratie- En Boekhoudkantoren",
    "sg:phone":"+31 78 629 9866",
    "sg:postcode":"3335 CN",
    "sg:province":"Zuid-Holland",
    "sg:website":"http://www.bolendevos.nl",
    "wof:name":"Bol & De Vos Bv",
    "wof:placetype":"venue"
},
  "geometry": {"coordinates":[4.60712,51.827839],"type":"Point"}
}