{
  "type": "Feature",
  "properties": {
    "addr:full":"Nieuwstr 6 Terneuzen Zeeland 4531 CW",
    "addr:housenumber":"6",
    "addr:postcode":"4531 cw",
    "addr:street":"Nieuwstr",
    "iso:country":"NL",
    "sg:address":"Nieuwstr 6",
    "sg:city":"Terneuzen",
    "sg:orig_category":"Hypotheken",
    "sg:phone":"+31 115 614 700",
    "sg:postcode":"4531 CW",
    "sg:province":"Zeeland",
    "wof:name":"H&G",
    "wof:placetype":"venue"
},
  "geometry": {"coordinates":[3.777881,51.307133],"type":"Point"}
}