{
  "type": "Feature",
  "properties": {
    "iso:country":"NL",
    "sg:address":"Keulsekd 181",
    "sg:city":"Utrecht",
    "sg:orig_category":"Energiebedrijven",
    "sg:phone":"+31 30 247 2211",
    "sg:postcode":"3534 AC",
    "sg:province":"Utrecht",
    "wof:name":"Reliant Energy Power Generation Benelux Nv",
    "wof:placetype":"venue"
},
  "geometry": {"coordinates":[5.08914,52.103111],"type":"Point"}
}