{
  "type": "Feature",
  "properties": {
    "iso:country":"NL",
    "sg:address":"Graan Voor Visch 15245",
    "sg:city":"Hoofddorp",
    "sg:orig_category":"Administratie- En Boekhoudkantoren",
    "sg:phone":"+31 23 561 5386",
    "sg:postcode":"2132 EC",
    "sg:province":"Noord-Brabant",
    "wof:name":"Lambregts",
    "wof:placetype":"venue"
},
  "geometry": {"coordinates":[4.69083,52.294361],"type":"Point"}
}