{
  "type": "Feature",
  "properties": {
    "iso:country":"NL",
    "sg:address":"Binnenvaert 46",
    "sg:city":"Kaatsheuvel",
    "sg:orig_category":"Schoenen",
    "sg:phone":"+31 416 278 119",
    "sg:postcode":"5171 MR",
    "sg:province":"Noord-Brabant",
    "wof:name":"Kuik, Van",
    "wof:placetype":"venue"
},
  "geometry": {"coordinates":[5.041668,51.661541],"type":"Point"}
}