{
  "type": "Feature",
  "properties": {
    "addr:full":"Parallelweg West 83 Culemborg Gelderland 4107 NA",
    "addr:housenumber":"83",
    "addr:postcode":"4107 na",
    "addr:street":"Parallelweg West;Gelderland",
    "iso:country":"NL",
    "sg:address":"Parallelweg West 83",
    "sg:city":"Culemborg",
    "sg:orig_category":"Metaalafval, Schrootrecycling And Sloperijen",
    "sg:phone":"+31 345 513 441",
    "sg:postcode":"4107 NA",
    "sg:province":"Gelderland",
    "wof:name":"Handelsmaatschappij J.M. Driessen & Zonen Bv",
    "wof:placetype":"venue"
},
  "geometry": {"coordinates":[5.241063,51.928703],"type":"Point"}
}