{
  "type": "Feature",
  "properties": {
    "addr:full":"Kleine Badstraat 2 Groningen Groningen 9726 CH",
    "addr:housenumber":"2",
    "addr:postcode":"9726",
    "addr:street":"Kleine Badstraat",
    "iso:country":"NL",
    "sg:address":"Kleine Badstraat 2",
    "sg:city":"Groningen",
    "sg:orig_category":"Meubelzaken, Woning- And Keukeninrichting",
    "sg:phone":"+31 50 318 0418",
    "sg:postcode":"9726 CH",
    "sg:province":"Groningen",
    "wof:name":"H. Hagenouw",
    "wof:placetype":"venue"
},
  "geometry": {"coordinates":[6.557390213,53.2114982605],"type":"Point"}
}