{
  "type": "Feature",
  "properties": {
    "iso:country":"NL",
    "sg:address":"Saenredamstraat 4",
    "sg:city":"'S Gravenhage",
    "sg:classifiers":[
        {
            "category":"Education",
            "subcategory":"Preschool",
            "type":"Public Place"
        }
    ],
    "sg:phone":"+31 70 380 8494",
    "sg:postcode":"2525 TN",
    "sg:province":"South Holland",
    "sg:tags":[
        "kleuteronderwijs",
        "basis-"
    ],
    "wof:name":"Koningin Beatrixschool",
    "wof:placetype":"venue"
},
  "geometry": {"coordinates":[4.305471,52.064404],"type":"Point"}
}