{
  "type": "Feature",
  "properties": {
    "iso:country":"NL",
    "sg:address":"Marie Heinekenplein 716",
    "sg:city":"Amsterdam",
    "sg:orig_category":"Boekenuitgeverijen",
    "sg:phone":"+31 20 662 1663",
    "sg:postcode":"1072 MN",
    "sg:province":"North Holland",
    "wof:name":"Frank Fehmers Productions Bv",
    "wof:placetype":"venue"
},
  "geometry": {"coordinates":[4.891128,52.35688],"type":"Point"}
}