{
  "type": "Feature",
  "properties": {
    "addr:full":"Grote Kromme Elleboog 3 Groningen Groningen 9712 BJ",
    "addr:housenumber":"3",
    "addr:postcode":"9712 bj",
    "addr:street":"Grote Kromme Elleboog",
    "iso:country":"NL",
    "sg:address":"Grote Kromme Elleboog 3",
    "sg:city":"Groningen",
    "sg:orig_category":"Boekhandels",
    "sg:phone":"+31 50 318 6314",
    "sg:postcode":"9712 BJ",
    "sg:province":"Groningen",
    "wof:name":"Stripwinkel Ambrosius",
    "wof:placetype":"venue"
},
  "geometry": {"coordinates":[6.56252,53.218102],"type":"Point"}
}