{
  "type": "Feature",
  "properties": {
    "addr:full":"Postbus 10034 Assen Drenthe 9400 CA",
    "addr:housenumber":"10034",
    "addr:postcode":"9400 ca",
    "addr:street":"Postbus",
    "iso:country":"NL",
    "sg:address":"Postbus 10034",
    "sg:city":"Assen",
    "sg:orig_category":"Natuur- En Milieuorganisaties",
    "sg:phone":"+31 592 313 389",
    "sg:postcode":"9400 CA",
    "sg:province":"Drenthe",
    "sg:website":"http://www.burobakker.nl",
    "wof:name":"Bakker, Buro",
    "wof:placetype":"venue"
},
  "geometry": {"coordinates":[6.559506,52.994041],"type":"Point"}
}