{
  "type": "Feature",
  "properties": {
    "addr:full":"Sluispolderwg 44A Zaandam North Holland 1505 HK",
    "addr:housenumber":"44a",
    "addr:postcode":"1505 hk",
    "addr:street":"Sluispolderwg",
    "iso:country":"NL",
    "sg:address":"Sluispolderwg 44A",
    "sg:city":"Zaandam",
    "sg:orig_category":"Elektrotechnische Installatiebureaus",
    "sg:phone":"+31 75 650 4600",
    "sg:postcode":"1505 HK",
    "sg:province":"North Holland",
    "wof:name":"Bree - De Keizer Bv, De",
    "wof:placetype":"venue"
},
  "geometry": {"coordinates":[4.850599,52.419106],"type":"Point"}
}