{
  "type": "Feature",
  "properties": {
    "addr:full":"Heerewg 198 Schoorl Noord-Holland 1871 EN",
    "addr:housenumber":"198",
    "addr:postcode":"1871 en",
    "iso:country":"NL",
    "sg:address":"Heerewg 198",
    "sg:city":"Schoorl",
    "sg:orig_category":"Beeldende Kunstenaars",
    "sg:phone":"+31 72 509 1128",
    "sg:postcode":"1871 EN",
    "sg:province":"Noord-Holland",
    "wof:name":"Viegers, G M V M",
    "wof:placetype":"venue"
},
  "geometry": {"coordinates":[4.676947,52.716412],"type":"Point"}
}