{
  "type": "Feature",
  "properties": {
    "addr:full":"Middelwg 1 Leersum Utrecht 3956 TJ",
    "addr:housenumber":"1",
    "addr:postcode":"3956 tj",
    "addr:street":"Middelwg",
    "iso:country":"NL",
    "sg:address":"Middelwg 1",
    "sg:city":"Leersum",
    "sg:orig_category":"Administratie- En Boekhoudkantoren",
    "sg:phone":"+31 343 455 690",
    "sg:postcode":"3956 TJ",
    "sg:province":"Utrecht",
    "sg:website":"http://www.adpharm.nl",
    "wof:name":"Adpharm",
    "wof:placetype":"venue"
},
  "geometry": {"coordinates":[5.424489,52.012306],"type":"Point"}
}