{
  "type": "Feature",
  "properties": {
    "iso:country":"NL",
    "sg:address":"Hoogmadesewg 72",
    "sg:city":"Leiderdorp",
    "sg:orig_category":"Politie",
    "sg:phone":"+31 900 8844",
    "sg:postcode":"2351 CV",
    "sg:province":"Zuid-Holland",
    "wof:name":"Politie",
    "wof:placetype":"venue"
},
  "geometry": {"coordinates":[4.536926,52.155468],"type":"Point"}
}