{
  "type": "Feature",
  "properties": {
    "addr:full":"Breitnerstr 52C Leeuwarden Friesland 8932 CD",
    "addr:housenumber":"52c",
    "addr:postcode":"8932 cd",
    "addr:street":"Breitnerstr",
    "iso:country":"NL",
    "sg:address":"Breitnerstr 52C",
    "sg:city":"Leeuwarden",
    "sg:orig_category":"Fotografie Reclame En Mode",
    "sg:phone":"+31 58 212 9026",
    "sg:postcode":"8932 CD",
    "sg:province":"Friesland",
    "sg:website":"http://www.denmark.nl",
    "wof:name":"Markic, Denis",
    "wof:placetype":"venue"
},
  "geometry": {"coordinates":[5.785648,53.190178],"type":"Point"}
}