{
  "type": "Feature",
  "properties": {
    "iso:country":"NL",
    "sg:address":"Atalanta 134",
    "sg:city":"Zeewolde",
    "sg:orig_category":"Modetekenaars Freelance",
    "sg:phone":"+31 36 522 5971",
    "sg:postcode":"3892 EJ",
    "sg:province":"NL.",
    "wof:name":"Keers, Maaike",
    "wof:placetype":"venue"
},
  "geometry": {"coordinates":[5.548572,52.321213],"type":"Point"}
}