{
  "type": "Feature",
  "properties": {
    "iso:country":"NL",
    "sg:address":"Hoogewaard 4",
    "sg:city":"Winssen",
    "sg:orig_category":"Vakantieverblijven",
    "sg:phone":"+31 487 521 227",
    "sg:postcode":"6645 AA",
    "sg:province":"Gelderland",
    "sg:website":"http://www.dehoogewaard.nl",
    "wof:name":"Hoogewaard, Vakantieboerderij De",
    "wof:placetype":"venue"
},
  "geometry": {"coordinates":[5.719766,51.876072],"type":"Point"}
}