{
  "type": "Feature",
  "properties": {
    "addr:full":"Heyenratherwg 4 Heyenrath Limburg 6276 PC",
    "addr:housenumber":"4",
    "addr:postcode":"6276 pc",
    "addr:street":"Heyenratherwg",
    "iso:country":"NL",
    "sg:address":"Heyenratherwg 4",
    "sg:city":"Heyenrath",
    "sg:classifiers":[
        {
            "category":"Travel",
            "subcategory":"Hotels & Motels",
            "type":"Entertainment"
        }
    ],
    "sg:phone":"+31 43 457 3546",
    "sg:postcode":"6276 PC",
    "sg:province":"Limburg",
    "sg:website":"http://www.goldentuliphotels.nl//tislenaken",
    "wof:name":"Golden Tulip Slenaken",
    "wof:placetype":"venue"
},
  "geometry": {"coordinates":[5.874822,50.775337],"type":"Point"}
}