{
  "type": "Feature",
  "properties": {
    "iso:country":"NL",
    "sg:address":"Monseigneur Hanssenstr 17",
    "sg:city":"Heerlen",
    "sg:orig_category":"Drogisterijen",
    "sg:phone":"+31 45 521 1760",
    "sg:postcode":"6414 CC",
    "sg:province":"Limburg",
    "wof:name":"Drogisterij De Heksenberg",
    "wof:placetype":"venue"
},
  "geometry": {"coordinates":[5.973036,50.914089],"type":"Point"}
}