{
  "type": "Feature",
  "properties": {
    "addr:full":"Poolsterstraat 51 Rotterdam Zuid-Holland 3067 LX",
    "addr:housenumber":"51",
    "addr:postcode":"3067 lx",
    "addr:street":"Poolsterstraat",
    "iso:country":"NL",
    "sg:address":"Poolsterstraat 51",
    "sg:city":"Rotterdam",
    "sg:orig_category":"Juweliers",
    "sg:phone":"+31 10 420 1804",
    "sg:postcode":"3067 LX",
    "sg:province":"Zuid-Holland",
    "wof:name":"Berkman Juwelier-Diamantair",
    "wof:placetype":"venue"
},
  "geometry": {"coordinates":[4.553962,51.949924],"type":"Point"}
}