{
  "type": "Feature",
  "properties": {
    "addr:full":"Zonnebaan 2 Maarssen Utrecht 3606 AC",
    "addr:housenumber":"2",
    "addr:postcode":"3606 ac",
    "addr:street":"Zonnebaan",
    "iso:country":"NL",
    "sg:address":"Zonnebaan 2",
    "sg:city":"Maarssen",
    "sg:orig_category":"Kantoor- And Schoolbenodigdheden Gh",
    "sg:phone":"+31 30 242 4777",
    "sg:postcode":"3606 AC",
    "sg:province":"Utrecht",
    "wof:name":"Antalis Bv",
    "wof:placetype":"venue"
},
  "geometry": {"coordinates":[5.0404458046,52.14295578],"type":"Point"}
}