{
  "type": "Feature",
  "properties": {
    "iso:country":"NL",
    "sg:address":"Haagse Schouwwg 8",
    "sg:city":"Leiden",
    "sg:orig_category":"Verzekerings- Maatschappijen",
    "sg:phone":"+31 71 576 9254",
    "sg:postcode":"2332 KG",
    "sg:province":"Zuid-Holland",
    "sg:website":"http://www.nn.nl",
    "wof:name":"Nationale-Nederlanden",
    "wof:placetype":"venue"
},
  "geometry": {"coordinates":[4.456505,52.164814],"type":"Point"}
}