{
  "type": "Feature",
  "properties": {
    "addr:full":"Veerstr 10 Maassluis Zuid-Holland 3142 CP",
    "addr:housenumber":"10",
    "addr:postcode":"3142 cp",
    "addr:street":"Veerstr",
    "iso:country":"NL",
    "sg:address":"Veerstr 10",
    "sg:city":"Maassluis",
    "sg:orig_category":"Woninginrichting",
    "sg:phone":"+31 10 591 2729",
    "sg:postcode":"3142 CP",
    "sg:province":"Zuid-Holland",
    "wof:name":"Boudesteijn",
    "wof:placetype":"venue"
},
  "geometry": {"coordinates":[4.2536220551,51.9221153259],"type":"Point"}
}