{
  "type": "Feature",
  "properties": {
    "iso:country":"NL",
    "sg:address":"Dr G H Amshoffwg 7",
    "sg:city":"Hoogeveen",
    "sg:orig_category":"Artsen - Overigen",
    "sg:phone":"+31 528 233 343",
    "sg:postcode":"7909 AK",
    "sg:province":"Drenthe",
    "wof:name":"Hyperbare Geneeskunde, Inst Voor",
    "wof:placetype":"venue"
},
  "geometry": {"coordinates":[6.461744,52.726875],"type":"Point"}
}