{
  "type": "Feature",
  "properties": {
    "addr:full":"Heibloemseweg 14 Panningen Limburg 5981 PH",
    "addr:housenumber":"14",
    "addr:postcode":"5981",
    "addr:street":"Heibloemseweg",
    "iso:country":"NL",
    "sg:address":"Heibloemseweg 14",
    "sg:city":"Panningen",
    "sg:orig_category":"Hoefdierhouderijen",
    "sg:phone":"+31 77 307 4946",
    "sg:postcode":"5981 PH",
    "sg:province":"Limburg",
    "wof:name":"Heesen Paardenmelk",
    "wof:placetype":"venue"
},
  "geometry": {"coordinates":[5.960587,51.331081],"type":"Point"}
}