{
  "type": "Feature",
  "properties": {
    "addr:full":"Kastanjelaan 16A Sauwerd Groningen 9771 AZ",
    "addr:housenumber":"16a",
    "addr:postcode":"9771 az",
    "addr:street":"Kastanjelaan",
    "iso:country":"NL",
    "sg:address":"Kastanjelaan 16A",
    "sg:city":"Sauwerd",
    "sg:classifiers":[
        {
            "category":"Education",
            "subcategory":"Preschool",
            "type":"Public Place"
        }
    ],
    "sg:phone":"+31 50 306 1760",
    "sg:postcode":"9771 AZ",
    "sg:province":"Groningen",
    "sg:tags":[
        "kleuteronderwijs",
        "basis-"
    ],
    "wof:name":"Peuterspeelzaal 'T Molentje",
    "wof:placetype":"venue"
},
  "geometry": {"coordinates":[6.53717,53.294331],"type":"Point"}
}