{
  "type": "Feature",
  "properties": {
    "addr:full":"Ceintuurbaan 398 Amsterdam Noord-Holland 1073 EN",
    "addr:housenumber":"398",
    "addr:postcode":"1073 en",
    "addr:street":"Ceintuurbaan",
    "iso:country":"NL",
    "sg:address":"Ceintuurbaan 398",
    "sg:city":"Amsterdam",
    "sg:orig_category":"Apothekers",
    "sg:phone":"+31 20 662 3610",
    "sg:postcode":"1073 EN",
    "sg:province":"Noord-Holland",
    "wof:name":"Apotheek De Vijzel",
    "wof:placetype":"venue"
},
  "geometry": {"coordinates":[4.90099,52.354595],"type":"Point"}
}