{
  "type": "Feature",
  "properties": {
    "addr:full":"Zeebodemstr 8 Ens Flevoland 8307 DD",
    "addr:housenumber":"8",
    "addr:postcode":"8307 dd",
    "addr:street":"Zeebodemstr;Flevoland",
    "iso:country":"NL",
    "sg:address":"Zeebodemstr 8",
    "sg:city":"Ens",
    "sg:orig_category":"Mensendieck - Oefentherapeuten",
    "sg:phone":"+31 527 253 998",
    "sg:postcode":"8307 DD",
    "sg:province":"Flevoland",
    "wof:name":"Nibbering-Heilbron, D A",
    "wof:placetype":"venue"
},
  "geometry": {"coordinates":[5.823675,52.639538],"type":"Point"}
}