{
  "type": "Feature",
  "properties": {
    "iso:country":"NL",
    "sg:address":"Mozartstraat 15",
    "sg:city":"Barendrecht",
    "sg:orig_category":"Schilderwerk",
    "sg:phone":"+31 180 620 105",
    "sg:postcode":"2992 RD",
    "sg:province":"South Holland",
    "wof:name":"Schildersbedrijf J.P.Schefferlie",
    "wof:placetype":"venue"
},
  "geometry": {"coordinates":[4.523809,51.848801],"type":"Point"}
}