{
  "type": "Feature",
  "properties": {
    "addr:full":"Rynsburgerwg 10 Leiden South Holland 2333 AA",
    "addr:housenumber":"10",
    "addr:postcode":"2333 aa",
    "addr:street":"Rynsburgerwg",
    "iso:country":"NL",
    "sg:address":"Rynsburgerwg 10",
    "sg:city":"Leiden",
    "sg:orig_category":"Orthopedische Artikelen",
    "sg:phone":"+31 71 521 9598",
    "sg:postcode":"2333 AA",
    "sg:province":"South Holland",
    "wof:name":"Welzorg",
    "wof:placetype":"venue"
},
  "geometry": {"coordinates":[4.4814271927,52.1684036255],"type":"Point"}
}