{
  "type": "Feature",
  "properties": {
    "addr:full":"Vennestr 4E Lisse Zuid-Holland 2161 LE",
    "addr:housenumber":"4e",
    "addr:postcode":"2161 le",
    "addr:street":"Vennestr",
    "iso:country":"NL",
    "sg:address":"Vennestr 4E",
    "sg:city":"Lisse",
    "sg:orig_category":"Pensioenen",
    "sg:phone":"+31 252 428 510",
    "sg:postcode":"2161 LE",
    "sg:province":"Zuid-Holland",
    "sg:website":"http://www.4pac.nl",
    "wof:name":"4Pac Bv",
    "wof:placetype":"venue"
},
  "geometry": {"coordinates":[4.553053,52.252033],"type":"Point"}
}