{
  "type": "Feature",
  "properties": {
    "addr:full":"De Oude Schut 10 Weert Limburg 6001 JL",
    "addr:housenumber":"10",
    "addr:postcode":"6001 jl",
    "addr:street":"De Oude Schut",
    "iso:country":"NL",
    "sg:address":"De Oude Schut 10",
    "sg:city":"Weert",
    "sg:orig_category":"Kappers",
    "sg:phone":"+31 495 542 519",
    "sg:postcode":"6001 JL",
    "sg:province":"Limburg",
    "wof:name":"Forbici",
    "wof:placetype":"venue"
},
  "geometry": {"coordinates":[5.7072892189,51.2531700134],"type":"Point"}
}