{
  "type": "Feature",
  "properties": {
    "addr:full":"Schipholwg 181 Badhoevedorp North Holland 1171 PK",
    "addr:housenumber":"181",
    "addr:postcode":"1171 pk",
    "iso:country":"NL",
    "sg:address":"Schipholwg 181",
    "sg:city":"Badhoevedorp",
    "sg:classifiers":[
        {
            "category":"Travel",
            "subcategory":"Hotels & Motels",
            "type":"Entertainment"
        }
    ],
    "sg:phone":"+31 20 502 5100",
    "sg:postcode":"1171 PK",
    "sg:province":"North Holland",
    "sg:website":"http://www.accorhotels.com",
    "wof:name":"Ibis Hotel Amsterdam Airport",
    "wof:placetype":"venue"
},
  "geometry": {"coordinates":[4.784972,52.329388],"type":"Point"}
}