{
  "type": "Feature",
  "properties": {
    "iso:country":"NL",
    "sg:address":"Luttik Oudorp 114",
    "sg:city":"Alkmaar",
    "sg:orig_category":"Antiekzaken",
    "sg:phone":"+31 72 511 6311",
    "sg:postcode":"1811 MZ",
    "sg:province":"Noord-Holland",
    "wof:name":"Kunsthandel Drie Kronen Bv",
    "wof:placetype":"venue"
},
  "geometry": {"coordinates":[4.751818,52.631001],"type":"Point"}
}