{
  "type": "Feature",
  "properties": {
    "addr:full":"Ds Kremerstr 25 Heeze Noord-Brabant 5591 GH",
    "addr:housenumber":"25",
    "addr:postcode":"5591 gh",
    "addr:street":"Ds Kremerstr",
    "iso:country":"NL",
    "sg:address":"Ds Kremerstr 25",
    "sg:city":"Heeze",
    "sg:orig_category":"Sportverenigingen En Ontspannings- Verenigingen",
    "sg:phone":"+31 40 226 5232",
    "sg:postcode":"5591 GH",
    "sg:province":"Noord-Brabant",
    "wof:name":"Eymerick, Korfbalver",
    "wof:placetype":"venue"
},
  "geometry": {"coordinates":[5.573301,51.382042],"type":"Point"}
}