{
  "type": "Feature",
  "properties": {
    "addr:full":"Oudkerkhof 42 Utrecht Utrecht 3512 GL",
    "addr:housenumber":"42",
    "addr:postcode":"3512 gl",
    "addr:street":"Oudkerkhof",
    "iso:country":"NL",
    "sg:address":"Oudkerkhof 42",
    "sg:city":"Utrecht",
    "sg:orig_category":"Opticiens",
    "sg:phone":"+31 30 231 2983",
    "sg:postcode":"3512 GL",
    "sg:province":"Utrecht",
    "wof:name":"Stopler-Optiek Bv",
    "wof:placetype":"venue"
},
  "geometry": {"coordinates":[5.1217679977,52.0920372009],"type":"Point"}
}