{
  "type": "Feature",
  "properties": {
    "addr:full":"Klimopstraat 1 Zwolle Overijssel 8012 DD",
    "addr:housenumber":"1",
    "addr:postcode":"8012 dd",
    "addr:street":"Klimopstraat",
    "iso:country":"NL",
    "sg:address":"Klimopstraat 1",
    "sg:city":"Zwolle",
    "sg:orig_category":"Meubelreparatie And -Restauratie",
    "sg:phone":"+31 38 421 5930",
    "sg:postcode":"8012 DD",
    "sg:province":"Overijssel",
    "wof:name":"Meubelstoffeerspecialist Moddejonge",
    "wof:placetype":"venue"
},
  "geometry": {"coordinates":[6.107587,52.501095],"type":"Point"}
}