{
  "type": "Feature",
  "properties": {
    "addr:full":"Rhederweg 10 Bellingwolde Groningen 9695 CC",
    "addr:housenumber":"10",
    "addr:postcode":"9695 cc",
    "addr:street":"Rhederweg",
    "iso:country":"NL",
    "sg:address":"Rhederweg 10",
    "sg:city":"Bellingwolde",
    "sg:orig_category":"Bloemen And Planten",
    "sg:phone":"+31 597 532 250",
    "sg:postcode":"9695 CC",
    "sg:province":"Groningen",
    "wof:name":"Interfleur",
    "wof:placetype":"venue"
},
  "geometry": {"coordinates":[7.147579,53.100498],"type":"Point"}
}