{
  "type": "Feature",
  "properties": {
    "iso:country":"NL",
    "sg:address":"Rhederweg 10",
    "sg:city":"Bellingwolde",
    "sg:orig_category":"Bloemen And Planten",
    "sg:phone":"+31 597 532 250",
    "sg:postcode":"9695 CC",
    "sg:province":"Groningen",
    "wof:name":"Interfleur",
    "wof:placetype":"venue"
},
  "geometry": {"coordinates":[7.147579,53.100498],"type":"Point"}
}