{
  "type": "Feature",
  "properties": {
    "addr:full":"Schepersbos 10 Wezep Gelderland 8091 HB",
    "addr:housenumber":"10",
    "addr:postcode":"8091 hb",
    "addr:street":"Schepersbos",
    "iso:country":"NL",
    "sg:address":"Schepersbos 10",
    "sg:city":"Wezep",
    "sg:orig_category":"Goederenvervoer Over De Weg",
    "sg:phone":"+31 38 376 4240",
    "sg:postcode":"8091 HB",
    "sg:province":"Gelderland",
    "wof:name":"W. Van Ommen",
    "wof:placetype":"venue"
},
  "geometry": {"coordinates":[6.005857,52.465553],"type":"Point"}
}