{
  "type": "Feature",
  "properties": {
    "addr:full":"Fregatln 19 Delfzyl Groningen 9934 ET",
    "addr:housenumber":"19",
    "addr:postcode":"9934 et",
    "addr:street":"Fregatln",
    "iso:country":"NL",
    "sg:address":"Fregatln 19",
    "sg:city":"Delfzyl",
    "sg:orig_category":"Voetbalverenigingen",
    "sg:phone":"+31 596 630 005",
    "sg:postcode":"9934 ET",
    "sg:province":"Groningen",
    "wof:name":"Eems Boys",
    "wof:placetype":"venue"
},
  "geometry": {"coordinates":[6.909404,53.330002],"type":"Point"}
}