{
  "type": "Feature",
  "properties": {
    "addr:full":"Faurestraat 37 Eindhoven Noord-Brabant 5654 PZ",
    "addr:housenumber":"37",
    "addr:postcode":"5654 pz",
    "addr:street":"Faurestraat",
    "iso:country":"NL",
    "sg:address":"Faurestraat 37",
    "sg:city":"Eindhoven",
    "sg:orig_category":"Binnenvaart",
    "sg:phone":"+31 40 257 0681",
    "sg:postcode":"5654 PZ",
    "sg:province":"Noord-Brabant",
    "wof:name":"Snijder Aqua Star",
    "wof:placetype":"venue"
},
  "geometry": {"coordinates":[5.450322,51.421055],"type":"Point"}
}