{
  "type": "Feature",
  "properties": {
    "addr:full":"Koppelstokstr 65 S Gravenhage South Holland 2583 CB",
    "addr:housenumber":"65",
    "addr:postcode":"2583 cb",
    "addr:street":"Koppelstokstr;S Gravenhage",
    "iso:country":"NL",
    "sg:address":"Koppelstokstr 65",
    "sg:city":"S Gravenhage",
    "sg:orig_category":"Autoschade- Herstelbedrijven",
    "sg:phone":"+31 70 358 8150",
    "sg:postcode":"2583 CB",
    "sg:province":"South Holland",
    "wof:name":"All In",
    "wof:placetype":"venue"
},
  "geometry": {"coordinates":[4.25526,52.09124],"type":"Point"}
}