{
  "type": "Feature",
  "properties": {
    "addr:full":"Semeinszstraat 14 Enkhuizen North Holland 1601 NR",
    "addr:housenumber":"14",
    "addr:postcode":"1601 nr",
    "addr:street":"Semeinszstraat",
    "iso:country":"NL",
    "sg:address":"Semeinszstraat 14",
    "sg:city":"Enkhuizen",
    "sg:orig_category":"Kappers",
    "sg:phone":"+31 228 313 582",
    "sg:postcode":"1601 NR",
    "sg:province":"North Holland",
    "wof:name":"W.M. Van Dinteren-Imming",
    "wof:placetype":"venue"
},
  "geometry": {"coordinates":[5.28768,52.703922],"type":"Point"}
}