{
  "type": "Feature",
  "properties": {
    "addr:full":"Scheepmakerij 16 Delft Zuid-Holland 2628 AA",
    "addr:housenumber":"16",
    "addr:postcode":"2628 aa",
    "addr:street":"Scheepmakerij",
    "iso:country":"NL",
    "sg:address":"Scheepmakerij 16",
    "sg:city":"Delft",
    "sg:orig_category":"Binnenhuisarchitecten",
    "sg:phone":"+31 15 257 4900",
    "sg:postcode":"2628 AA",
    "sg:province":"Zuid-Holland",
    "wof:name":"Machette",
    "wof:placetype":"venue"
},
  "geometry": {"coordinates":[4.36199,52.004875],"type":"Point"}
}