{
  "type": "Feature",
  "properties": {
    "addr:full":"Raadhuisln 50 Mynsheerenland Zuid-Holland 3271 BT",
    "addr:housenumber":"50",
    "addr:postcode":"3271 bt",
    "addr:street":"Raadhuisln",
    "iso:country":"NL",
    "sg:address":"Raadhuisln 50",
    "sg:city":"Mynsheerenland",
    "sg:classifiers":[
        {
            "category":"Retail",
            "subcategory":"Auto Repair",
            "type":"Services"
        }
    ],
    "sg:phone":"+31 186 601 477",
    "sg:postcode":"3271 BT",
    "sg:province":"Zuid-Holland",
    "sg:tags":[
        "garage"
    ],
    "wof:name":"Reedijk Bv",
    "wof:placetype":"venue"
},
  "geometry": {"coordinates":[4.492185,51.797523],"type":"Point"}
}