{
  "type": "Feature",
  "properties": {
    "addr:full":"Albert Cuijpstraat 13 Hengelo Ov Overijssel 7556 GD",
    "addr:housenumber":"13",
    "addr:postcode":"7556 gd",
    "addr:street":"Albert Cuijpstraat;Ov",
    "iso:country":"NL",
    "sg:address":"Albert Cuijpstraat 13",
    "sg:city":"Hengelo Ov",
    "sg:orig_category":"Verlichting And Huishoudartikelen",
    "sg:phone":"+31 74 242 6217",
    "sg:postcode":"7556 GD",
    "sg:province":"Overijssel",
    "wof:name":"J.J. Paauwe",
    "wof:placetype":"venue"
},
  "geometry": {"coordinates":[6.786307,52.273708],"type":"Point"}
}