{
  "type": "Feature",
  "properties": {
    "iso:country":"NL",
    "sg:address":"Mansholtstraat 61",
    "sg:city":"Hoogezand",
    "sg:orig_category":"Pijpleidingen",
    "sg:phone":"+31 598 323 296",
    "sg:postcode":"9602 SC",
    "sg:province":"Groningen",
    "wof:name":"Oving Industrie Service",
    "wof:placetype":"venue"
},
  "geometry": {"coordinates":[6.743163,53.156689],"type":"Point"}
}