{
  "type": "Feature",
  "properties": {
    "addr:full":"G V Amstelln 31 Zeist Utrecht 3703 BC",
    "addr:housenumber":"31",
    "addr:postcode":"3703 bc",
    "addr:street":"V Amstelln",
    "iso:country":"NL",
    "sg:address":"G V Amstelln 31",
    "sg:city":"Zeist",
    "sg:orig_category":"Woninginrichting",
    "sg:phone":"+31 30 691 7764",
    "sg:postcode":"3703 BC",
    "sg:province":"Utrecht",
    "wof:name":"Liefde, D De",
    "wof:placetype":"venue"
},
  "geometry": {"coordinates":[5.2438697815,52.0854797363],"type":"Point"}
}