{
  "type": "Feature",
  "properties": {
    "addr:full":"Wilhelminasingel 104 Maastricht Limburg 6221 BL",
    "addr:housenumber":"104",
    "addr:postcode":"6221 bl",
    "addr:street":"Wilhelminasingel",
    "iso:country":"NL",
    "sg:address":"Wilhelminasingel 104",
    "sg:city":"Maastricht",
    "sg:orig_category":"Vertaal- And Tolkenbureaus",
    "sg:phone":"+31 43 321 8985",
    "sg:postcode":"6221 BL",
    "sg:province":"Limburg",
    "wof:name":"Balance",
    "wof:placetype":"venue"
},
  "geometry": {"coordinates":[5.702264,50.848083],"type":"Point"}
}