{
  "type": "Feature",
  "properties": {
    "addr:full":"Koevoetstraat 49 Bergen Op Zoom Noord-Brabant 4611 PB",
    "addr:housenumber":"49",
    "addr:postcode":"4611 pb",
    "addr:street":"Koevoetstraat",
    "iso:country":"NL",
    "sg:address":"Koevoetstraat 49",
    "sg:city":"Bergen Op Zoom",
    "sg:orig_category":"Werving And Selectie Van Tijdelijk Personeel And Uitzendkantoren",
    "sg:phone":"+31 164 252 650",
    "sg:postcode":"4611 PB",
    "sg:province":"Noord-Brabant",
    "wof:name":"Uitzendbureau Start",
    "wof:placetype":"venue"
},
  "geometry": {"coordinates":[4.2900362015,51.4939498901],"type":"Point"}
}