{
  "type": "Feature",
  "properties": {
    "addr:full":"Torenln 37 Laren Nh North Holland 1251 HG",
    "addr:housenumber":"37",
    "addr:postcode":"1251 hg",
    "addr:street":"Torenln;Nh North",
    "iso:country":"NL",
    "sg:address":"Torenln 37",
    "sg:city":"Laren Nh",
    "sg:classifiers":[
        {
            "category":"Personal",
            "subcategory":"Nail Salon",
            "type":"Services"
        }
    ],
    "sg:phone":"+31 35 538 1061",
    "sg:postcode":"1251 HG",
    "sg:province":"North Holland",
    "sg:tags":[
        "pedicure"
    ],
    "wof:name":"Verver",
    "wof:placetype":"venue"
},
  "geometry": {"coordinates":[5.22387,52.256741],"type":"Point"}
}