{
  "type": "Feature",
  "properties": {
    "addr:full":"Baarsjesstraat 45 Middelburg Zeeland 4335 HJ",
    "addr:housenumber":"45",
    "addr:postcode":"4335 hj",
    "addr:street":"Baarsjesstraat",
    "iso:country":"NL",
    "sg:address":"Baarsjesstraat 45",
    "sg:city":"Middelburg",
    "sg:classifiers":[
        {
            "category":"Education",
            "subcategory":"Preschool",
            "type":"Public Place"
        }
    ],
    "sg:phone":"+31 118 614 517",
    "sg:postcode":"4335 HJ",
    "sg:province":"Zeeland",
    "sg:tags":[
        "kleuteronderwijs",
        "basis-"
    ],
    "wof:name":"Openbare Basisschool De Beverburch",
    "wof:placetype":"venue"
},
  "geometry": {"coordinates":[3.603486,51.492161],"type":"Point"}
}