{
  "type": "Feature",
  "properties": {
    "iso:country":"NL",
    "sg:address":"St. Willibrordstraat 45",
    "sg:city":"Berkel-Enschot",
    "sg:orig_category":"Loodgieterswerk, Verwarming And Sanitaire Installaties",
    "sg:phone":"+31 13 533 3321",
    "sg:postcode":"5056 HT",
    "sg:province":"Noord-Brabant",
    "wof:name":"Loodgietersbedrijf M. Van Iersel",
    "wof:placetype":"venue"
},
  "geometry": {"coordinates":[5.138836,51.588566],"type":"Point"}
}