{
  "type": "Feature",
  "properties": {
    "addr:full":"Ultramarijnhof 15 Ijsselstein Ut Utrecht 3402 JR",
    "addr:housenumber":"15",
    "addr:postcode":"3402 jr",
    "addr:street":"Ultramarijnhof",
    "iso:country":"NL",
    "sg:address":"Ultramarijnhof 15",
    "sg:city":"Ijsselstein Ut",
    "sg:orig_category":"Beursorganisaties And Standbouw",
    "sg:phone":"+31 30 687 0546",
    "sg:postcode":"3402 JR",
    "sg:province":"Utrecht",
    "wof:name":"Ontwerpbureau Van Boheemen",
    "wof:placetype":"venue"
},
  "geometry": {"coordinates":[5.042846,52.033104],"type":"Point"}
}