{
  "type": "Feature",
  "properties": {
    "iso:country":"NL",
    "sg:address":"Kromhoutstr 10",
    "sg:city":"Ymuiden",
    "sg:orig_category":"Bedrijfsopleidingen",
    "sg:phone":"+31 255 523 131",
    "sg:postcode":"1976 BM",
    "sg:province":"North Holland",
    "sg:website":"http://www.ucadeny.nl",
    "wof:name":"Ucademy",
    "wof:placetype":"venue"
},
  "geometry": {"coordinates":[4.57443,52.454971],"type":"Point"}
}