{
  "type": "Feature",
  "properties": {
    "addr:full":"Binnenwg 85A Heemstede Noord-Holland 2101 JD",
    "addr:housenumber":"85a",
    "addr:postcode":"2101 jd",
    "addr:street":"Binnenwg",
    "iso:country":"NL",
    "sg:address":"Binnenwg 85A",
    "sg:city":"Heemstede",
    "sg:orig_category":"Kinderkleding",
    "sg:phone":"+31 23 528 2840",
    "sg:postcode":"2101 JD",
    "sg:province":"Noord-Holland",
    "wof:name":"Toddler'S",
    "wof:placetype":"venue"
},
  "geometry": {"coordinates":[4.621096,52.353222],"type":"Point"}
}