{
  "type": "Feature",
  "properties": {
    "iso:country":"NL",
    "sg:address":"Brinklaan 84",
    "sg:city":"Bussum",
    "sg:orig_category":"Meubelzaken, Woning- And Keukeninrichting",
    "sg:phone":"+31 35 691 2220",
    "sg:postcode":"1404 GM",
    "sg:province":"Noord-Holland",
    "wof:name":"Richter Slaapcomfort",
    "wof:placetype":"venue"
},
  "geometry": {"coordinates":[5.1626,52.273655],"type":"Point"}
}