{
  "type": "Feature",
  "properties": {
    "addr:full":"Brinklaan 84 Bussum Noord-Holland 1404 GM",
    "addr:housenumber":"84",
    "addr:postcode":"1404 gm",
    "addr:street":"Brinklaan",
    "iso:country":"NL",
    "sg:address":"Brinklaan 84",
    "sg:city":"Bussum",
    "sg:orig_category":"Meubelzaken, Woning- And Keukeninrichting",
    "sg:phone":"+31 35 691 2220",
    "sg:postcode":"1404 GM",
    "sg:province":"Noord-Holland",
    "wof:name":"Richter Slaapcomfort",
    "wof:placetype":"venue"
},
  "geometry": {"coordinates":[5.1626,52.273655],"type":"Point"}
}