{
  "type": "Feature",
  "properties": {
    "addr:full":"Hunzedal 65 Borger Drenthe 9531 GC",
    "addr:housenumber":"65",
    "addr:postcode":"9531 gc",
    "addr:street":"Hunzedal",
    "iso:country":"NL",
    "sg:address":"Hunzedal 65",
    "sg:city":"Borger",
    "sg:classifiers":[
        {
            "category":"Travel",
            "subcategory":"Hotels & Motels",
            "type":"Entertainment"
        }
    ],
    "sg:phone":"+31 599 235 071",
    "sg:postcode":"9531 GC",
    "sg:province":"Drenthe",
    "wof:name":"G.T. Jager",
    "wof:placetype":"venue"
},
  "geometry": {"coordinates":[6.80178,52.918655],"type":"Point"}
}