{
  "type": "Feature",
  "properties": {
    "addr:full":"Waddenland 68 Duivendrecht Noord-Holland 1115 XG",
    "addr:housenumber":"68",
    "addr:postcode":"1115 xg",
    "addr:street":"Waddenland",
    "iso:country":"NL",
    "sg:address":"Waddenland 68",
    "sg:city":"Duivendrecht",
    "sg:orig_category":"Bloemen En Planten",
    "sg:phone":"+31 20 368 0640",
    "sg:postcode":"1115 XG",
    "sg:province":"Noord-Holland",
    "wof:name":"Sovitro International Bv",
    "wof:placetype":"venue"
},
  "geometry": {"coordinates":[4.938139,52.331589],"type":"Point"}
}