{
  "type": "Feature",
  "properties": {
    "iso:country":"NL",
    "sg:address":"Schoolstr 24",
    "sg:city":"Oldehove",
    "sg:orig_category":"Keukens",
    "sg:phone":"+31 594 591 897",
    "sg:postcode":"9883 PH",
    "sg:province":"Groningen",
    "wof:name":"Exclusief Keukencentrum",
    "wof:placetype":"venue"
},
  "geometry": {"coordinates":[6.393728,53.304672],"type":"Point"}
}