{
  "type": "Feature",
  "properties": {
    "addr:full":"Schoolstr 24 Oldehove Groningen 9883 PH",
    "addr:housenumber":"24",
    "addr:postcode":"9883",
    "addr:street":"Schoolstr",
    "iso:country":"NL",
    "sg:address":"Schoolstr 24",
    "sg:city":"Oldehove",
    "sg:orig_category":"Keukens",
    "sg:phone":"+31 594 591 897",
    "sg:postcode":"9883 PH",
    "sg:province":"Groningen",
    "wof:name":"Exclusief Keukencentrum",
    "wof:placetype":"venue"
},
  "geometry": {"coordinates":[6.393728,53.304672],"type":"Point"}
}