{
  "type": "Feature",
  "properties": {
    "iso:country":"NL",
    "sg:address":"Bredasewg 1",
    "sg:city":"Etten Leur",
    "sg:orig_category":"Woningbouw- Verenigingen En -Stichtingen",
    "sg:phone":"+31 76 502 4600",
    "sg:postcode":"4872 LA",
    "sg:province":"Noord-Brabant",
    "sg:website":"http://www.woonwel.nl",
    "wof:name":"Woonstichting Etten-Leur",
    "wof:placetype":"venue"
},
  "geometry": {"coordinates":[4.6492371559,51.5707855225],"type":"Point"}
}