{
  "type": "Feature",
  "properties": {
    "addr:full":"Parmentierlaan 7 Amstelveen Noord-Holland 1185 CT",
    "addr:housenumber":"7",
    "addr:postcode":"1185 ct",
    "addr:street":"Parmentierlaan",
    "iso:country":"NL",
    "sg:address":"Parmentierlaan 7",
    "sg:city":"Amstelveen",
    "sg:orig_category":"Makelaars In Onroerend Goed",
    "sg:phone":"+31 20 641 0808",
    "sg:postcode":"1185 CT",
    "sg:province":"Noord-Holland",
    "wof:name":"J C Verhoef",
    "wof:placetype":"venue"
},
  "geometry": {"coordinates":[4.859347,52.297955],"type":"Point"}
}