{
  "type": "Feature",
  "properties": {
    "addr:full":"Allemanswg 68 Losser NL.08 7582 HL",
    "addr:housenumber":"68;nl.08",
    "addr:postcode":"7582 hl",
    "addr:street":"Allemanswg",
    "iso:country":"NL",
    "sg:address":"Allemanswg 68",
    "sg:city":"Losser",
    "sg:orig_category":"Pensioenen",
    "sg:phone":"+31 53 538 7294",
    "sg:postcode":"7582 HL",
    "sg:province":"NL.08",
    "wof:name":"Beter Leven",
    "wof:placetype":"venue"
},
  "geometry": {"coordinates":[6.997204,52.265282],"type":"Point"}
}