{
  "type": "Feature",
  "properties": {
    "iso:country":"NL",
    "sg:address":"Brugstr 4",
    "sg:city":"Orvelte",
    "sg:orig_category":"Artiesten",
    "sg:phone":"+31 593 562 861",
    "sg:postcode":"9441 PG",
    "sg:province":"Drenthe",
    "wof:name":"Henk Renting",
    "wof:placetype":"venue"
},
  "geometry": {"coordinates":[6.661054,52.844204],"type":"Point"}
}