{
  "type": "Feature",
  "properties": {
    "addr:full":"Loefzij 57 Huizen Noord-Holland 1276 HJ",
    "addr:housenumber":"57",
    "addr:postcode":"1276 hj",
    "addr:street":"Loefzij",
    "iso:country":"NL",
    "sg:address":"Loefzij 57",
    "sg:city":"Huizen",
    "sg:orig_category":"Autoverhuur",
    "sg:phone":"+31 35 623 1617",
    "sg:postcode":"1276 HJ",
    "sg:province":"Noord-Holland",
    "wof:name":"Bi Bi Rent",
    "wof:placetype":"venue"
},
  "geometry": {"coordinates":[5.253272,52.288578],"type":"Point"}
}