{
  "type": "Feature",
  "properties": {
    "addr:full":"Noorderstr 1 Uithuizen Groningen 9981 CL",
    "addr:housenumber":"1",
    "addr:postcode":"9981",
    "addr:street":"Noorderstr",
    "iso:country":"NL",
    "sg:address":"Noorderstr 1",
    "sg:city":"Uithuizen",
    "sg:orig_category":"Kappers",
    "sg:phone":"+31 595 431 720",
    "sg:postcode":"9981 CL",
    "sg:province":"Groningen",
    "wof:name":"Dries",
    "wof:placetype":"venue"
},
  "geometry": {"coordinates":[6.6763701439,53.4078598022],"type":"Point"}
}