{
  "type": "Feature",
  "properties": {
    "iso:country":"NL",
    "sg:address":"Veilingstr 10",
    "sg:city":"Arnhem",
    "sg:orig_category":"Meubelmakerijen",
    "sg:phone":"+31 26 351 5252",
    "sg:postcode":"6827 AK",
    "sg:province":"Gelderland",
    "sg:website":"http://www.dewig.nl",
    "wof:name":"Wig Meubelmakerij, De",
    "wof:placetype":"venue"
},
  "geometry": {"coordinates":[5.91968,51.97337],"type":"Point"}
}