{
  "type": "Feature",
  "properties": {
    "iso:country":"NL",
    "sg:address":"Unastr 58",
    "sg:city":"Valkenswaard",
    "sg:orig_category":"Voetbalverenigingen",
    "sg:phone":"+31 40 204 9498",
    "sg:postcode":"5552 BN",
    "sg:province":"Noord-Brabant",
    "wof:name":"Fc Zwarthoed",
    "wof:placetype":"venue"
},
  "geometry": {"coordinates":[5.459239,51.357002],"type":"Point"}
}