{
  "type": "Feature",
  "properties": {
    "addr:full":"Molenstr 4 Delden Overijssel 7491 BG",
    "addr:housenumber":"4",
    "addr:postcode":"7491",
    "addr:street":"Molenstr",
    "iso:country":"NL",
    "sg:address":"Molenstr 4",
    "sg:city":"Delden",
    "sg:orig_category":"Biljarts - Fabrieken",
    "sg:phone":"+31 74 376 3901",
    "sg:postcode":"7491 BG",
    "sg:province":"Overijssel",
    "wof:name":"Oude Nijhuis, Biljarthandel",
    "wof:placetype":"venue"
},
  "geometry": {"coordinates":[6.709676,52.262093],"type":"Point"}
}