{
  "type": "Feature",
  "properties": {
    "addr:full":"Kruislaan 182 Amsterdam Noord-Holland 1098 SK",
    "addr:housenumber":"182",
    "addr:street":"Kruislaan;1098",
    "iso:country":"NL",
    "sg:address":"Kruislaan 182",
    "sg:city":"Amsterdam",
    "sg:orig_category":"Artiesten",
    "sg:phone":"+31 20 668 1551",
    "sg:postcode":"1098 SK",
    "sg:province":"Noord-Holland",
    "wof:name":"The Artbox Bv",
    "wof:placetype":"venue"
},
  "geometry": {"coordinates":[4.941721,52.348412],"type":"Point"}
}