{
  "type": "Feature",
  "properties": {
    "iso:country":"NL",
    "sg:address":"Hooipolderwg 3",
    "sg:city":"Den Hoorn Zh",
    "sg:orig_category":"Kunststoffen - Fabrieken En Groothandel",
    "sg:phone":"+31 15 262 4545",
    "sg:postcode":"2635 CZ",
    "sg:province":"Zuid-Holland",
    "sg:website":"http://www.kascoplex.nl",
    "wof:name":"Kascoplex+ Bv",
    "wof:placetype":"venue"
},
  "geometry": {"coordinates":[4.322587,51.997536],"type":"Point"}
}