{
  "type": "Feature",
  "properties": {
    "iso:country":"NL",
    "sg:address":"Knuitershoek 6",
    "sg:city":"Ossenisse",
    "sg:orig_category":"Kampeerterreinen",
    "sg:phone":"+31 114 681 489",
    "sg:postcode":"4589 RL",
    "sg:province":"Zeeland",
    "wof:name":"Camping 'T Mussenist",
    "wof:placetype":"venue"
},
  "geometry": {"coordinates":[3.966547966,51.3917388916],"type":"Point"}
}