{
  "type": "Feature",
  "properties": {
    "addr:full":"Valkstraat 15 Reusel Noord-Brabant 5541 TP",
    "addr:housenumber":"15",
    "addr:postcode":"5541 tp",
    "addr:street":"Valkstraat",
    "iso:country":"NL",
    "sg:address":"Valkstraat 15",
    "sg:city":"Reusel",
    "sg:orig_category":"Metaalwerken",
    "sg:phone":"+31 497 641 436",
    "sg:postcode":"5541 TP",
    "sg:province":"Noord-Brabant",
    "wof:name":"Peeters Zonwering",
    "wof:placetype":"venue"
},
  "geometry": {"coordinates":[5.163557,51.357662],"type":"Point"}
}