{
  "type": "Feature",
  "properties": {
    "addr:full":"Dracht 29 Heerenveen Provincie Friesland 8442 BK",
    "addr:housenumber":"29",
    "addr:postcode":"8442 bk",
    "addr:street":"Dracht;Provincie Friesland",
    "iso:country":"NL",
    "sg:address":"Dracht 29",
    "sg:city":"Heerenveen",
    "sg:orig_category":"Boekhandels",
    "sg:phone":"+31 513 622 932",
    "sg:postcode":"8442 BK",
    "sg:province":"Provincie Friesland",
    "wof:name":"Witte Boekenmarkt, De",
    "wof:placetype":"venue"
},
  "geometry": {"coordinates":[5.924558,52.958778],"type":"Point"}
}