{
  "type": "Feature",
  "properties": {
    "addr:full":"Fransestraat 58 Nijmegen Gelderland 6524 JE",
    "addr:housenumber":"58",
    "addr:postcode":"6524 je",
    "addr:street":"Fransestraat;Gelderland",
    "iso:country":"NL",
    "sg:address":"Fransestraat 58",
    "sg:city":"Nijmegen",
    "sg:orig_category":"Herenmodezaken",
    "sg:phone":"+31 24 323 3612",
    "sg:postcode":"6524 JE",
    "sg:province":"Gelderland",
    "wof:name":"Confectiebedrijf Van Dal Bv",
    "wof:placetype":"venue"
},
  "geometry": {"coordinates":[5.860802,51.838314],"type":"Point"}
}