{
  "type": "Feature",
  "properties": {
    "iso:country":"NL",
    "sg:address":"Preludestr 7",
    "sg:city":"S Gravenhage",
    "sg:orig_category":"Onroerende Goederen",
    "sg:phone":"+31 70 391 4692",
    "sg:postcode":"2553 SV",
    "sg:province":"Zuid-Holland",
    "wof:name":"Leeuwen, R W M Van",
    "wof:placetype":"venue"
},
  "geometry": {"coordinates":[4.21987,52.046589],"type":"Point"}
}