{
  "type": "Feature",
  "properties": {
    "addr:full":"Roerdompstr 11 Wormer Noord-Holland 1531 XE",
    "addr:housenumber":"11",
    "addr:postcode":"1531 xe",
    "addr:street":"Roerdompstr",
    "iso:country":"NL",
    "sg:address":"Roerdompstr 11",
    "sg:city":"Wormer",
    "sg:orig_category":"Honden- En Kattentrimsalons",
    "sg:phone":"+31 75 642 0656",
    "sg:postcode":"1531 XE",
    "sg:province":"Noord-Holland",
    "wof:name":"Astrid'S Trimsalon",
    "wof:placetype":"venue"
},
  "geometry": {"coordinates":[4.81547,52.500252],"type":"Point"}
}