{
  "type": "Feature",
  "properties": {
    "iso:country":"NL",
    "sg:address":"Oude Veer 6",
    "sg:city":"Papendrecht",
    "sg:orig_category":"Fietsen En Bromfietsen",
    "sg:phone":"+31 78 615 3959",
    "sg:postcode":"3353 GS",
    "sg:province":"Zuid-Holland",
    "wof:name":"Ijzerman, Johan",
    "wof:placetype":"venue"
},
  "geometry": {"coordinates":[4.68442,51.825119],"type":"Point"}
}