{
  "type": "Feature",
  "properties": {
    "addr:full":"Marrewijklaan 41 Spijkenisse Zuid-Holland 3201 BH",
    "addr:housenumber":"41",
    "addr:postcode":"3201 bh",
    "addr:street":"Marrewijklaan",
    "iso:country":"NL",
    "sg:address":"Marrewijklaan 41",
    "sg:city":"Spijkenisse",
    "sg:orig_category":"Opticiens",
    "sg:phone":"+31 181 620 671",
    "sg:postcode":"3201 BH",
    "sg:province":"Zuid-Holland",
    "wof:name":"Langstraat Select Center",
    "wof:placetype":"venue"
},
  "geometry": {"coordinates":[4.3278479576,51.8482704163],"type":"Point"}
}