{
  "type": "Feature",
  "properties": {
    "iso:country":"NL",
    "sg:address":"Dorpsstraat 24",
    "sg:city":"Dussen",
    "sg:orig_category":"Glaszetten",
    "sg:phone":"+31 416 391 187",
    "sg:postcode":"4271 AC",
    "sg:province":"Noord-Brabant",
    "wof:name":"Vof Glashandel Dussen",
    "wof:placetype":"venue"
},
  "geometry": {"coordinates":[4.960099,51.730366],"type":"Point"}
}