{
  "type": "Feature",
  "properties": {
    "iso:country":"NL",
    "sg:address":"Steenovenweg 3",
    "sg:city":"Helmond",
    "sg:orig_category":"Kantoorapparatuur Gh",
    "sg:phone":"+31 492 506 022",
    "sg:postcode":"5708 HN",
    "sg:province":"Noord-Brabant",
    "wof:name":"Easy 4 All",
    "wof:placetype":"venue"
},
  "geometry": {"coordinates":[5.6271719933,51.4740066528],"type":"Point"}
}