{
  "type": "Feature",
  "properties": {
    "iso:country":"NL",
    "sg:address":"Sporenstr 8",
    "sg:city":"Maastricht",
    "sg:orig_category":"Schoenen - Reparaties",
    "sg:phone":"+31 43 321 9098",
    "sg:postcode":"6211 EB",
    "sg:province":"Limburg",
    "wof:name":"Hoenjet",
    "wof:placetype":"venue"
},
  "geometry": {"coordinates":[5.690084,50.849594],"type":"Point"}
}