{
  "type": "Feature",
  "properties": {
    "addr:full":"Dorpsstraat 78 Lunteren Gelderland 6741 AM",
    "addr:housenumber":"78",
    "addr:postcode":"6741",
    "addr:street":"Dorpsstraat;Gelderland",
    "iso:country":"NL",
    "sg:address":"Dorpsstraat 78",
    "sg:city":"Lunteren",
    "sg:classifiers":[
        {
            "category":"Fast Food",
            "type":"Food & Drink"
        }
    ],
    "sg:phone":"+31 318 485 224",
    "sg:postcode":"6741 AM",
    "sg:province":"Gelderland",
    "sg:tags":[
        "afhaal",
        "restaurant"
    ],
    "wof:name":"Restaurant Pizzeria Grillroom Bella Italia",
    "wof:placetype":"venue"
},
  "geometry": {"coordinates":[5.620403,52.085258],"type":"Point"}
}