{
  "type": "Feature",
  "properties": {
    "addr:full":"Parallelweg 1 Bergambacht Zuid-Holland 2861 EC",
    "addr:housenumber":"1",
    "addr:postcode":"2861 ec",
    "addr:street":"Parallelweg",
    "iso:country":"NL",
    "sg:address":"Parallelweg 1",
    "sg:city":"Bergambacht",
    "sg:orig_category":"Bloemen And Planten",
    "sg:phone":"+31 182 351 329",
    "sg:postcode":"2861 EC",
    "sg:province":"Zuid-Holland",
    "wof:name":"Tuindecoratie Kleijn Bv",
    "wof:placetype":"venue"
},
  "geometry": {"coordinates":[4.780558,51.930569],"type":"Point"}
}