{
  "type": "Feature",
  "properties": {
    "addr:full":"Bredewg 11 Waddinxveen Zuid-Holland 2742 KT",
    "addr:housenumber":"11",
    "addr:postcode":"2742 kt",
    "addr:street":"Bredewg",
    "iso:country":"NL",
    "sg:address":"Bredewg 11",
    "sg:city":"Waddinxveen",
    "sg:orig_category":"Loonbedrijven",
    "sg:phone":"+31 6 21242807",
    "sg:postcode":"2742 KT",
    "sg:province":"Zuid-Holland",
    "wof:name":"Baas, O F",
    "wof:placetype":"venue"
},
  "geometry": {"coordinates":[4.602965,52.027954],"type":"Point"}
}