{
  "type": "Feature",
  "properties": {
    "addr:full":"Houtlaan 21 Drachten Provincie Friesland 9203 AN",
    "addr:housenumber":"21",
    "addr:postcode":"9203 an",
    "addr:street":"Houtlaan;Provincie Friesland",
    "iso:country":"NL",
    "sg:address":"Houtlaan 21",
    "sg:city":"Drachten",
    "sg:orig_category":"Bouwmaterialen Gh",
    "sg:phone":"+31 512 512 353",
    "sg:postcode":"9203 AN",
    "sg:province":"Provincie Friesland",
    "wof:name":"Schildersbedrijf G.Th. Rebbers",
    "wof:placetype":"venue"
},
  "geometry": {"coordinates":[6.099255,53.108643],"type":"Point"}
}