{
  "type": "Feature",
  "properties": {
    "iso:country":"NL",
    "sg:address":"Binnenpolderwg 1",
    "sg:city":"Gouda",
    "sg:orig_category":"Kantoormachines",
    "sg:phone":"+31 182 511 663",
    "sg:postcode":"2807 LC",
    "sg:province":"Zuid-Holland",
    "wof:name":"Jupiter",
    "wof:placetype":"venue"
},
  "geometry": {"coordinates":[4.7498707771,52.0054702759],"type":"Point"}
}