{
  "type": "Feature",
  "properties": {
    "addr:full":"Korvelsewg 150 Tilburg Noord-Brabant 5025 JL",
    "addr:housenumber":"150",
    "addr:postcode":"5025 jl",
    "addr:street":"Tilburg",
    "iso:country":"NL",
    "sg:address":"Korvelsewg 150",
    "sg:city":"Tilburg",
    "sg:orig_category":"Boeken En Tijdschriften",
    "sg:phone":"+31 13 542 2012",
    "sg:postcode":"5025 JL",
    "sg:province":"Noord-Brabant",
    "wof:name":"Lotje",
    "wof:placetype":"venue"
},
  "geometry": {"coordinates":[5.07222,51.550514],"type":"Point"}
}