{
  "type": "Feature",
  "properties": {
    "addr:full":"Hammarskjoldhof 45 Utrecht Utrecht 3527 HD",
    "addr:housenumber":"45",
    "addr:postcode":"3527 hd",
    "addr:street":"Hammarskjoldhof",
    "iso:country":"NL",
    "sg:address":"Hammarskjoldhof 45",
    "sg:city":"Utrecht",
    "sg:orig_category":"Schoenen",
    "sg:phone":"+31 30 293 6673",
    "sg:postcode":"3527 HD",
    "sg:province":"Utrecht",
    "wof:name":"Schoenenreus",
    "wof:placetype":"venue"
},
  "geometry": {"coordinates":[5.094222,52.074421],"type":"Point"}
}