{
  "type": "Feature",
  "properties": {
    "addr:full":"Industrieweg 44 Grootebroek Noord-Holland 1613  K",
    "addr:housenumber":"44;1613",
    "addr:postcode":"k",
    "addr:street":"Industrieweg",
    "iso:country":"NL",
    "sg:address":"Industrieweg 44",
    "sg:city":"Grootebroek",
    "sg:orig_category":"Autoreparatie And Auto-Onderhoud",
    "sg:phone":"+31 228 511 888",
    "sg:postcode":"1613  K",
    "sg:province":"Noord-Holland",
    "wof:name":"Gerard Struik Autobanden Bv",
    "wof:placetype":"venue"
},
  "geometry": {"coordinates":[5.228966,52.694077],"type":"Point"}
}