{
  "type": "Feature",
  "properties": {
    "addr:full":"Drieendijk 1 Heenvliet South Holland 3218 LB",
    "addr:housenumber":"1",
    "addr:postcode":"3218 lb",
    "addr:street":"Drieendijk",
    "iso:country":"NL",
    "sg:address":"Drieendijk 1",
    "sg:city":"Heenvliet",
    "sg:orig_category":"Landbouwmachines Gh",
    "sg:phone":"+31 181 663 124",
    "sg:postcode":"3218 LB",
    "sg:province":"South Holland",
    "wof:name":"Lien Nederland Bv",
    "wof:placetype":"venue"
},
  "geometry": {"coordinates":[4.235315,51.856007],"type":"Point"}
}