{
  "type": "Feature",
  "properties": {
    "addr:full":"De Singel 5 Grypskerk Groningen 9843 ES",
    "addr:housenumber":"5",
    "addr:postcode":"9843 es",
    "addr:street":"De Singel",
    "iso:country":"NL",
    "sg:address":"De Singel 5",
    "sg:city":"Grypskerk",
    "sg:orig_category":"Voetbalverenigingen",
    "sg:phone":"+31 594 213 289",
    "sg:postcode":"9843 ES",
    "sg:province":"Groningen",
    "wof:name":"Grijpskerk Vv",
    "wof:placetype":"venue"
},
  "geometry": {"coordinates":[6.31298,53.250111],"type":"Point"}
}