{
  "type": "Feature",
  "properties": {
    "addr:full":"Haagwg 168 , (Bij De Hoornbrug) Ryswyk Zh Zuid-Holland 2282 AJ",
    "addr:housenumber":"168",
    "addr:postcode":"2282 aj",
    "addr:street":"Bij De Hoornbrug Ryswyk",
    "iso:country":"NL",
    "sg:address":"Haagwg 168 , (Bij De Hoornbrug)",
    "sg:city":"Ryswyk Zh",
    "sg:orig_category":"Kappers",
    "sg:phone":"+31 70 390 5095",
    "sg:postcode":"2282 AJ",
    "sg:province":"Zuid-Holland",
    "wof:name":"Uiterste Haarverzorging",
    "wof:placetype":"venue"
},
  "geometry": {"coordinates":[4.33694,52.056503],"type":"Point"}
}