{
  "type": "Feature",
  "properties": {
    "addr:full":"Stokkumsewg 18 S Heerenberg Gelderland 7041 BW",
    "addr:housenumber":"18",
    "addr:postcode":"7041 bw",
    "addr:street":"Stokkumsewg;S Heerenberg Gelderland",
    "iso:country":"NL",
    "sg:address":"Stokkumsewg 18",
    "sg:city":"S Heerenberg",
    "sg:orig_category":"Goudsmeden En Zilversmeden",
    "sg:phone":"+31 314 665 175",
    "sg:postcode":"7041 BW",
    "sg:province":"Gelderland",
    "wof:name":"Jong, H J De",
    "wof:placetype":"venue"
},
  "geometry": {"coordinates":[6.244288,51.877579],"type":"Point"}
}