{
  "type": "Feature",
  "properties": {
    "iso:country":"NL",
    "sg:address":"Tinelstr 5A",
    "sg:city":"Eindhoven",
    "sg:orig_category":"Kappers",
    "sg:phone":"+31 40 255 1675",
    "sg:postcode":"5654 LS",
    "sg:province":"North Brabant",
    "wof:name":"Mar",
    "wof:placetype":"venue"
},
  "geometry": {"coordinates":[5.455822,51.419746],"type":"Point"}
}