{
  "type": "Feature",
  "properties": {
    "addr:full":"Raadhuisplein 36 Nieuwerkerk Ad Ijssel South Holland 2914 KM",
    "addr:housenumber":"36",
    "addr:postcode":"2914 km",
    "addr:street":"Raadhuisplein;Ijssel",
    "iso:country":"NL",
    "sg:address":"Raadhuisplein 36",
    "sg:city":"Nieuwerkerk Ad Ijssel",
    "sg:orig_category":"Verzekeringen",
    "sg:phone":"+31 180 313 884",
    "sg:postcode":"2914 KM",
    "sg:province":"South Holland",
    "wof:name":"Krens Assuranties",
    "wof:placetype":"venue"
},
  "geometry": {"coordinates":[4.616295,51.967377],"type":"Point"}
}