{
  "type": "Feature",
  "properties": {
    "addr:full":"J De Wittstr 40 Hilversum North Holland 1215 GX",
    "addr:housenumber":"40",
    "addr:postcode":"1215 gx",
    "addr:street":"J De Wittstr",
    "iso:country":"NL",
    "sg:address":"J De Wittstr 40",
    "sg:city":"Hilversum",
    "sg:orig_category":"Zonnebank- En Solariumcentra",
    "sg:phone":"+31 35 621 7359",
    "sg:postcode":"1215 GX",
    "sg:province":"North Holland",
    "sg:website":"http://www.hellemond.nl",
    "wof:name":"Hellemond Sport, Van",
    "wof:placetype":"venue"
},
  "geometry": {"coordinates":[5.158715,52.212444],"type":"Point"}
}