{
  "type": "Feature",
  "properties": {
    "addr:full":"Buskesdries 13C Andelst Gelderland 6673 DP",
    "addr:housenumber":"13c",
    "addr:postcode":"6673 dp",
    "addr:street":"Buskesdries;Gelderland",
    "iso:country":"NL",
    "sg:address":"Buskesdries 13C",
    "sg:city":"Andelst",
    "sg:orig_category":"Adviesbureaus Automatisering",
    "sg:phone":"+31 488 421 618",
    "sg:postcode":"6673 DP",
    "sg:province":"Gelderland",
    "sg:website":"http://www.infound.nl",
    "wof:name":"Infound Bv",
    "wof:placetype":"venue"
},
  "geometry": {"coordinates":[5.714092,51.915295],"type":"Point"}
}