{
  "type": "Feature",
  "properties": {
    "addr:full":"Onyxdk 5 Roosendaal Noord-Brabant 4706 LN",
    "addr:housenumber":"5",
    "addr:postcode":"4706 ln",
    "addr:street":"Onyxdk",
    "iso:country":"NL",
    "sg:address":"Onyxdk 5",
    "sg:city":"Roosendaal",
    "sg:orig_category":"Biljartzalen",
    "sg:phone":"+31 165 533 676",
    "sg:postcode":"4706 LN",
    "sg:province":"Noord-Brabant",
    "sg:website":"http://www.delantaarn.com",
    "wof:name":"Carambole, La",
    "wof:placetype":"venue"
},
  "geometry": {"coordinates":[4.494799,51.523621],"type":"Point"}
}