{
  "type": "Feature",
  "properties": {
    "addr:full":"Havenstr 1A Colynsplaat Zeeland 4486 AA",
    "addr:housenumber":"1a",
    "addr:postcode":"4486 aa",
    "addr:street":"Havenstr;Zeeland",
    "iso:country":"NL",
    "sg:address":"Havenstr 1A",
    "sg:city":"Colynsplaat",
    "sg:orig_category":"Watersportartikelen",
    "sg:phone":"+31 113 695 159",
    "sg:postcode":"4486 AA",
    "sg:province":"Zeeland",
    "wof:name":"Neron Vof",
    "wof:placetype":"venue"
},
  "geometry": {"coordinates":[3.8495619297,51.59973526],"type":"Point"}
}