{
  "type": "Feature",
  "properties": {
    "addr:full":"Hoofdwg 132 Schildwolde Groningen 9626 AJ",
    "addr:housenumber":"132",
    "addr:postcode":"9626 aj",
    "iso:country":"NL",
    "sg:address":"Hoofdwg 132",
    "sg:city":"Schildwolde",
    "sg:orig_category":"Warenhuizen",
    "sg:phone":"+31 598 421 374",
    "sg:postcode":"9626 AJ",
    "sg:province":"Groningen",
    "wof:name":"Warenhuis 1001",
    "wof:placetype":"venue"
},
  "geometry": {"coordinates":[6.8151741028,53.2323646545],"type":"Point"}
}