{
  "type": "Feature",
  "properties": {
    "addr:full":"W De Zwygerln 52 Zevenaar Gelderland 6904 CM",
    "addr:housenumber":"52",
    "addr:postcode":"6904 cm",
    "addr:street":"W De Zwygerln",
    "iso:country":"NL",
    "sg:address":"W De Zwygerln 52",
    "sg:city":"Zevenaar",
    "sg:orig_category":"Kinderopvang",
    "sg:phone":"+31 316 526 445",
    "sg:postcode":"6904 CM",
    "sg:province":"Gelderland",
    "wof:name":"Maatjes, De",
    "wof:placetype":"venue"
},
  "geometry": {"coordinates":[6.076878,51.931618],"type":"Point"}
}