{
  "type": "Feature",
  "properties": {
    "addr:full":"Lipperkerkstraat 63 Enschede NL.08 7511 CV",
    "addr:housenumber":"63",
    "addr:postcode":"7511",
    "addr:street":"Lipperkerkstraat;Cv",
    "iso:country":"NL",
    "sg:address":"Lipperkerkstraat 63",
    "sg:city":"Enschede",
    "sg:orig_category":"Onderhoud And Reparatie Kantoorapparatuur",
    "sg:phone":"+31 53 432 8796",
    "sg:postcode":"7511 CV",
    "sg:province":"NL.08",
    "wof:name":"Focom Computers & Peripherals",
    "wof:placetype":"venue"
},
  "geometry": {"coordinates":[6.905995,52.220909],"type":"Point"}
}