{
  "type": "Feature",
  "properties": {
    "addr:full":"Lovensestr 178B Tilburg Noord-Brabant 5014 DV",
    "addr:housenumber":"178b",
    "addr:postcode":"5014 dv",
    "iso:country":"NL",
    "sg:address":"Lovensestr 178B",
    "sg:city":"Tilburg",
    "sg:orig_category":"Vertalers",
    "sg:phone":"+31 13 535 8246",
    "sg:postcode":"5014 DV",
    "sg:province":"Noord-Brabant",
    "wof:name":"Rutten, K M",
    "wof:placetype":"venue"
},
  "geometry": {"coordinates":[5.099376,51.561787],"type":"Point"}
}