{
  "type": "Feature",
  "properties": {
    "iso:country":"NL",
    "sg:address":"P H Buismanln 27",
    "sg:city":"Tiel",
    "sg:orig_category":"Webdesign Bureaus",
    "sg:phone":"+31 344 683 221",
    "sg:postcode":"4007 WB",
    "sg:province":"Gelderland",
    "sg:website":"http://www.4-site.nl",
    "wof:name":"4-Site",
    "wof:placetype":"venue"
},
  "geometry": {"coordinates":[5.4306960106,51.8880958557],"type":"Point"}
}