{
  "type": "Feature",
  "properties": {
    "iso:country":"NL",
    "sg:address":"Lokhorst 2",
    "sg:city":"Leiderdorp",
    "sg:orig_category":"Kantoorartikelen",
    "sg:phone":"+31 71 541 1967",
    "sg:postcode":"2352 KG",
    "sg:province":"Zuid-Holland",
    "wof:name":"Kantor Trading",
    "wof:placetype":"venue"
},
  "geometry": {"coordinates":[4.5286478996,52.1579055786],"type":"Point"}
}