{
  "type": "Feature",
  "properties": {
    "addr:full":"De Vecht 8 Dronten Flevoland 8253 PH",
    "addr:housenumber":"8",
    "addr:postcode":"8253",
    "addr:street":"De Vecht;Flevoland",
    "iso:country":"NL",
    "sg:address":"De Vecht 8",
    "sg:city":"Dronten",
    "sg:orig_category":"Diverse Grafische Activiteiten",
    "sg:phone":"+31 321 318 277",
    "sg:postcode":"8253 PH",
    "sg:province":"Flevoland",
    "wof:name":"Vankan Vof",
    "wof:placetype":"venue"
},
  "geometry": {"coordinates":[5.703253,52.54269],"type":"Point"}
}