{
  "type": "Feature",
  "properties": {
    "addr:full":"Schiewg 113C Rotterdam Zuid-Holland 3038 AL",
    "addr:housenumber":"113c",
    "addr:postcode":"3038 al",
    "addr:street":"Schiewg",
    "iso:country":"NL",
    "sg:address":"Schiewg 113C",
    "sg:city":"Rotterdam",
    "sg:orig_category":"Verzekeringen - Verzekeringskantoren",
    "sg:phone":"+31 10 466 6252",
    "sg:postcode":"3038 AL",
    "sg:province":"Zuid-Holland",
    "wof:name":"Pieters-De Galan Bv, I B",
    "wof:placetype":"venue"
},
  "geometry": {"coordinates":[4.466088,51.933289],"type":"Point"}
}