{
  "type": "Feature",
  "properties": {
    "iso:country":"NL",
    "sg:address":"Limburgln 12",
    "sg:city":"Someren",
    "sg:orig_category":"Loonbedrijven",
    "sg:phone":"+31 6 29006347",
    "sg:postcode":"5712 PM",
    "sg:province":"Noord-Brabant",
    "wof:name":"Mierlo, Thijs Van",
    "wof:placetype":"venue"
},
  "geometry": {"coordinates":[5.666935,51.351524],"type":"Point"}
}