{
  "type": "Feature",
  "properties": {
    "addr:full":"Arsenaalplein 3 Vlissingen Zeeland 4381 BL",
    "addr:housenumber":"3",
    "addr:postcode":"4381 bl",
    "addr:street":"Arsenaalplein",
    "iso:country":"NL",
    "sg:address":"Arsenaalplein 3",
    "sg:city":"Vlissingen",
    "sg:orig_category":"Kansspelen",
    "sg:phone":"+31 118 430 152",
    "sg:postcode":"4381 BL",
    "sg:province":"Zeeland",
    "wof:name":"Carrousel",
    "wof:placetype":"venue"
},
  "geometry": {"coordinates":[3.5773770809,51.4413719177],"type":"Point"}
}