{
  "type": "Feature",
  "properties": {
    "iso:country":"NL",
    "sg:address":"Voorstr 29",
    "sg:city":"Katwyk Zh",
    "sg:orig_category":"Hypotheken",
    "sg:phone":"+31 71 401 0135",
    "sg:postcode":"2225 EK",
    "sg:province":"Zuid-Holland",
    "wof:name":"Hypotheekplanner, De",
    "wof:placetype":"venue"
},
  "geometry": {"coordinates":[4.396585,52.205109],"type":"Point"}
}