{
  "type": "Feature",
  "properties": {
    "addr:full":"Koppelln 13 Bilthoven Utrecht 3721 PD",
    "addr:housenumber":"13",
    "addr:postcode":"3721 pd",
    "addr:street":"Koppelln",
    "iso:country":"NL",
    "sg:address":"Koppelln 13",
    "sg:city":"Bilthoven",
    "sg:orig_category":"Adviesbureaus Bedrijfsorganisatie",
    "sg:phone":"+31 30 229 2758",
    "sg:postcode":"3721 PD",
    "sg:province":"Utrecht",
    "wof:name":"Iew",
    "wof:placetype":"venue"
},
  "geometry": {"coordinates":[5.18986,52.12133],"type":"Point"}
}