{
  "type": "Feature",
  "properties": {
    "addr:full":"D Blesstr 6 Amsterdam North Holland 1073 LA",
    "addr:housenumber":"6",
    "addr:postcode":"1073 la",
    "iso:country":"NL",
    "sg:address":"D Blesstr 6",
    "sg:city":"Amsterdam",
    "sg:orig_category":"Grafisch Ontwerpers",
    "sg:phone":"+31 20 673 1434",
    "sg:postcode":"1073 LA",
    "sg:province":"North Holland",
    "wof:name":"Sijl, Wim Van",
    "wof:placetype":"venue"
},
  "geometry": {"coordinates":[4.901685,52.349319],"type":"Point"}
}