{
  "type": "Feature",
  "properties": {
    "addr:full":"Valkenburgerwg 49 Nuth Limburg 6361 EB",
    "addr:housenumber":"49",
    "addr:postcode":"6361 eb",
    "addr:street":"Valkenburgerwg",
    "iso:country":"NL",
    "sg:address":"Valkenburgerwg 49",
    "sg:city":"Nuth",
    "sg:orig_category":"Wapens En Munitie",
    "sg:phone":"+31 45 565 0040",
    "sg:postcode":"6361 EB",
    "sg:province":"Limburg",
    "sg:website":"http://www.mauricedrummen.nl",
    "wof:name":"Drummen En Zn, Fa M",
    "wof:placetype":"venue"
},
  "geometry": {"coordinates":[5.8769369125,50.9144477844],"type":"Point"}
}