{
  "type": "Feature",
  "properties": {
    "addr:full":"Marspoortstr 8A Zutphen Gelderland 7201 JB",
    "addr:housenumber":"8a",
    "addr:postcode":"7201 jb",
    "addr:street":"Marspoortstr;Gelderland",
    "iso:country":"NL",
    "sg:address":"Marspoortstr 8A",
    "sg:city":"Zutphen",
    "sg:orig_category":"Antiquiteiten",
    "sg:phone":"+31 575 512 775",
    "sg:postcode":"7201 JB",
    "sg:province":"Gelderland",
    "wof:name":"Marschpoort Kunst & Antiek",
    "wof:placetype":"venue"
},
  "geometry": {"coordinates":[6.1917700768,52.141368866],"type":"Point"}
}