{
  "type": "Feature",
  "properties": {
    "addr:full":"Mauritsplantsoen 17 Rijnsburg Zuid-Holland 2231 VP",
    "addr:housenumber":"17",
    "addr:postcode":"2231 vp",
    "addr:street":"Mauritsplantsoen",
    "iso:country":"NL",
    "sg:address":"Mauritsplantsoen 17",
    "sg:city":"Rijnsburg",
    "sg:orig_category":"Bloemen And Planten Gh",
    "sg:phone":"+31 71 408 0110",
    "sg:postcode":"2231 VP",
    "sg:province":"Zuid-Holland",
    "wof:name":"Fa. Goudriaan & De Mooij",
    "wof:placetype":"venue"
},
  "geometry": {"coordinates":[4.439168,52.185349],"type":"Point"}
}