{
  "type": "Feature",
  "properties": {
    "iso:country":"NL",
    "sg:address":"Alkmaargracht 81",
    "sg:city":"Almere",
    "sg:orig_category":"Fotostudio'S And Fotografen",
    "sg:phone":"+31 36 533 5100",
    "sg:postcode":"1324 PM",
    "sg:province":"NL.",
    "wof:name":"Eric Polman Fotografie",
    "wof:placetype":"venue"
},
  "geometry": {"coordinates":[5.207466,52.366554],"type":"Point"}
}