{
  "type": "Feature",
  "properties": {
    "iso:country":"NL",
    "sg:address":"Wittevrouwensngl 6",
    "sg:city":"Utrecht",
    "sg:orig_category":"Psychotherapeuten",
    "sg:phone":"+31 30 231 4408",
    "sg:postcode":"3581 GA",
    "sg:province":"Utrecht",
    "wof:name":"Vermeulen-Landaal, Drs",
    "wof:placetype":"venue"
},
  "geometry": {"coordinates":[5.128466,52.092987],"type":"Point"}
}