{
  "type": "Feature",
  "properties": {
    "addr:full":"Gorsselse Enkwg 2 Gorssel Gelderland 7213 LM",
    "addr:housenumber":"2",
    "addr:postcode":"7213 lm",
    "addr:street":"Enkwg;Gelderland",
    "iso:country":"NL",
    "sg:address":"Gorsselse Enkwg 2",
    "sg:city":"Gorssel",
    "sg:orig_category":"Malerijen",
    "sg:phone":"+31 575 492 566",
    "sg:postcode":"7213 LM",
    "sg:province":"Gelderland",
    "wof:name":"Eesterhoek",
    "wof:placetype":"venue"
},
  "geometry": {"coordinates":[6.198355,52.19191],"type":"Point"}
}