{
  "type": "Feature",
  "properties": {
    "iso:country":"NL",
    "sg:address":"Schoonloerstraat 12",
    "sg:city":"Grolloo",
    "sg:orig_category":"Autokeuringen",
    "sg:phone":"+31 592 501 368",
    "sg:postcode":"9444 PP",
    "sg:province":"Provincie Drenthe",
    "wof:name":"Autobedrijf S. Dijkstra Vof",
    "wof:placetype":"venue"
},
  "geometry": {"coordinates":[6.674762,52.932159],"type":"Point"}
}