{
  "type": "Feature",
  "properties": {
    "iso:country":"NL",
    "sg:address":"Vinkenstr 185",
    "sg:city":"Amsterdam",
    "sg:orig_category":"Bejaarden - Verzorgingstehuizen",
    "sg:phone":"+31 20 623 1052",
    "sg:postcode":"1013 JR",
    "sg:province":"Noord-Holland",
    "wof:name":"Rietvinck, De",
    "wof:placetype":"venue"
},
  "geometry": {"coordinates":[4.884371,52.383553],"type":"Point"}
}