{
  "type": "Feature",
  "properties": {
    "addr:full":"Postbus 299 Rotterdam 3000 AG",
    "addr:housenumber":"299",
    "addr:postcode":"3000",
    "addr:street":"Postbus",
    "iso:country":"NL",
    "sg:address":"Postbus 299",
    "sg:city":"Rotterdam",
    "sg:orig_category":"Adviesbureaus",
    "sg:phone":"+31 10 243 0921",
    "sg:postcode":"3000 AG",
    "wof:name":"Senioren Adviseur, De",
    "wof:placetype":"venue"
},
  "geometry": {"coordinates":[4.47075,51.922619],"type":"Point"}
}