{
  "type": "Feature",
  "properties": {
    "addr:full":"Utrechtsewg 75 Zeist Utrecht 3702 AA",
    "addr:housenumber":"75",
    "addr:postcode":"3702 aa",
    "addr:street":"Utrechtsewg",
    "iso:country":"NL",
    "sg:address":"Utrechtsewg 75",
    "sg:city":"Zeist",
    "sg:orig_category":"Verzekerings- Maatschappijen",
    "sg:phone":"+31 30 693 3166",
    "sg:postcode":"3702 AA",
    "sg:province":"Utrecht",
    "wof:name":"Dbv Verzekeringen",
    "wof:placetype":"venue"
},
  "geometry": {"coordinates":[5.229412,52.088463],"type":"Point"}
}