{
  "type": "Feature",
  "properties": {
    "addr:full":"Plantsoensngl Z 1-3 S Heerenberg Gelderland 7041 ZC",
    "addr:housenumber":"1-3",
    "addr:postcode":"7041 zc",
    "addr:street":"S Heerenberg Gelderland",
    "iso:country":"NL",
    "sg:address":"Plantsoensngl Z 1-3",
    "sg:city":"S Heerenberg",
    "sg:orig_category":"Babyartikelen",
    "sg:phone":"+31 314 661 551",
    "sg:postcode":"7041 ZC",
    "sg:province":"Gelderland",
    "sg:website":"http://www.babyspeciaalzaak.nl",
    "wof:name":"Otto Hageman Babyspeciaalzaak",
    "wof:placetype":"venue"
},
  "geometry": {"coordinates":[6.248145,51.873497],"type":"Point"}
}