{
  "type": "Feature",
  "properties": {
    "addr:full":"Bredaseweg 221 Roosendaal North Brabant 4705 RN",
    "addr:housenumber":"221",
    "addr:postcode":"4705 rn",
    "addr:street":"Bredaseweg",
    "iso:country":"NL",
    "sg:address":"Bredaseweg 221",
    "sg:city":"Roosendaal",
    "sg:orig_category":"Public Relationbureaus",
    "sg:phone":"+31 165 548 000",
    "sg:postcode":"4705 RN",
    "sg:province":"North Brabant",
    "wof:name":"Scribart Bv",
    "wof:placetype":"venue"
},
  "geometry": {"coordinates":[4.492904,51.541317],"type":"Point"}
}