{
  "type": "Feature",
  "properties": {
    "iso:country":"NL",
    "sg:address":"Trans 21",
    "sg:city":"Arnhem",
    "sg:orig_category":"Onroerende Goederen",
    "sg:phone":"+31 26 443 0246",
    "sg:postcode":"6811 HS",
    "sg:province":"Gelderland",
    "wof:name":"Erku Bv",
    "wof:placetype":"venue"
},
  "geometry": {"coordinates":[5.90649,51.978168],"type":"Point"}
}