{
  "type": "Feature",
  "properties": {
    "addr:full":"Smidsstraat 2 Hellendoorn Overijssel 7447 CJ",
    "addr:housenumber":"2",
    "addr:postcode":"7447 cj",
    "addr:street":"Smidsstraat",
    "iso:country":"NL",
    "sg:address":"Smidsstraat 2",
    "sg:city":"Hellendoorn",
    "sg:orig_category":"Juweliers",
    "sg:phone":"+31 548 654 185",
    "sg:postcode":"7447 CJ",
    "sg:province":"Overijssel",
    "wof:name":"Edelsmederij J.H. Dubbink",
    "wof:placetype":"venue"
},
  "geometry": {"coordinates":[6.44922,52.390911],"type":"Point"}
}