{
  "type": "Feature",
  "properties": {
    "addr:full":"Rijksstraatweg 176 Haren Gn Groningen 9752 BP",
    "addr:housenumber":"176",
    "addr:postcode":"9752 bp",
    "addr:street":"Rijksstraatweg",
    "iso:country":"NL",
    "sg:address":"Rijksstraatweg 176",
    "sg:city":"Haren Gn",
    "sg:orig_category":"Wasserettes And Stomerijen",
    "sg:phone":"+31 50 534 5375",
    "sg:postcode":"9752 BP",
    "sg:province":"Groningen",
    "wof:name":"Gerner Stomen Bv",
    "wof:placetype":"venue"
},
  "geometry": {"coordinates":[6.6040549278,53.1727752686],"type":"Point"}
}