{
  "type": "Feature",
  "properties": {
    "iso:country":"NL",
    "sg:address":"Assendorperstraat 173",
    "sg:city":"Zwolle",
    "sg:orig_category":"Kappers",
    "sg:phone":"+31 38 421 3525",
    "sg:postcode":"8012 DL",
    "sg:province":"NL.08",
    "wof:name":"Salon Kamphorst",
    "wof:placetype":"venue"
},
  "geometry": {"coordinates":[6.105729,52.503048],"type":"Point"}
}