{
  "type": "Feature",
  "properties": {
    "iso:country":"NL",
    "sg:address":"Maximiliaanstr 17",
    "sg:city":"Ysselstein Ut",
    "sg:orig_category":"Onderhoudswerken",
    "sg:phone":"+31 30 688 5276",
    "sg:postcode":"3401 ZJ",
    "sg:province":"Utrecht",
    "wof:name":"My Happiness",
    "wof:placetype":"venue"
},
  "geometry": {"coordinates":[5.044663,52.016918],"type":"Point"}
}