{
  "type": "Feature",
  "properties": {
    "iso:country":"NL",
    "sg:address":"Stationsstr 12",
    "sg:city":"Gramsbergen",
    "sg:orig_category":"Schilders",
    "sg:phone":"+31 524 561 429",
    "sg:postcode":"7783 AS",
    "sg:province":"Overijssel",
    "wof:name":"Bakker",
    "wof:placetype":"venue"
},
  "geometry": {"coordinates":[6.675495,52.611164],"type":"Point"}
}