{
  "type": "Feature",
  "properties": {
    "addr:full":"Baambruggestr 77 S Gravenhage South Holland 2546 SG",
    "addr:housenumber":"77",
    "addr:postcode":"2546 sg",
    "addr:street":"Baambruggestr;S Gravenhage",
    "iso:country":"NL",
    "sg:address":"Baambruggestr 77",
    "sg:city":"S Gravenhage",
    "sg:orig_category":"Keukens",
    "sg:phone":"+31 70 329 6595",
    "sg:postcode":"2546 SG",
    "sg:province":"South Holland",
    "wof:name":"Oosten, Van",
    "wof:placetype":"venue"
},
  "geometry": {"coordinates":[4.274271,52.058716],"type":"Point"}
}