{
  "type": "Feature",
  "properties": {
    "iso:country":"NL",
    "sg:address":"Hoogstraat 62",
    "sg:city":"Leerdam",
    "sg:orig_category":"Verhuur Diversen",
    "sg:phone":"+31 345 610 128",
    "sg:postcode":"4141 BD",
    "sg:province":"Zuid-Holland",
    "wof:name":"Schreuders Ski Sport",
    "wof:placetype":"venue"
},
  "geometry": {"coordinates":[5.093784,51.890575],"type":"Point"}
}