{
  "type": "Feature",
  "properties": {
    "addr:full":"Veldspaatstraat 9 Maastricht Limburg 6216 BM",
    "addr:housenumber":"9",
    "addr:postcode":"6216 bm",
    "addr:street":"Veldspaatstraat",
    "iso:country":"NL",
    "sg:address":"Veldspaatstraat 9",
    "sg:city":"Maastricht",
    "sg:orig_category":"Partycatering And -Organisatie",
    "sg:phone":"+31 43 343 2801",
    "sg:postcode":"6216 BM",
    "sg:province":"Limburg",
    "wof:name":"J M P Hermans",
    "wof:placetype":"venue"
},
  "geometry": {"coordinates":[5.661123,50.851269],"type":"Point"}
}