{
  "type": "Feature",
  "properties": {
    "iso:country":"NL",
    "sg:address":"Groenstraat 6",
    "sg:city":"Valkenburg Lb",
    "sg:orig_category":"Verhuur Bouwmachines",
    "sg:phone":"+31 43 601 3926",
    "sg:postcode":"6301 PH",
    "sg:province":"Limburg",
    "wof:name":"M. Lousberg & Zn.",
    "wof:placetype":"venue"
},
  "geometry": {"coordinates":[5.832223,50.83952],"type":"Point"}
}