{
  "type": "Feature",
  "properties": {
    "addr:full":"Bar Vd Heydenln 19 Wichmond Gelderland 7234 SB",
    "addr:housenumber":"19",
    "addr:postcode":"7234 sb",
    "addr:street":"Gelderland",
    "iso:country":"NL",
    "sg:address":"Bar Vd Heydenln 19",
    "sg:city":"Wichmond",
    "sg:orig_category":"Afslankinstituten",
    "sg:phone":"+31 575 441 801",
    "sg:postcode":"7234 SB",
    "sg:province":"Gelderland",
    "sg:website":"http://www.eganederland.nl",
    "wof:name":"Eekloh, 'T",
    "wof:placetype":"venue"
},
  "geometry": {"coordinates":[6.25944,52.08799],"type":"Point"}
}