{
  "type": "Feature",
  "properties": {
    "iso:country":"NL",
    "sg:address":"Ceintuurbaan N 108",
    "sg:city":"Roden",
    "sg:orig_category":"Accountants - Administratie- Consulenten En -Kantoren",
    "sg:phone":"+31 50 501 1155",
    "sg:postcode":"9301 NZ",
    "sg:province":"Provincie Drenthe",
    "sg:website":"http://www.hoeksema.nl",
    "wof:name":"Hoeksema",
    "wof:placetype":"venue"
},
  "geometry": {"coordinates":[6.430315,53.14563],"type":"Point"}
}