{
  "type": "Feature",
  "properties": {
    "addr:full":"Jonkerlaan 4 Vriezenveen Overijssel 7671 GM",
    "addr:housenumber":"4",
    "addr:postcode":"7671 gm",
    "addr:street":"Jonkerlaan",
    "iso:country":"NL",
    "sg:address":"Jonkerlaan 4",
    "sg:city":"Vriezenveen",
    "sg:orig_category":"Bibliotheken And Openbare Archieven",
    "sg:phone":"+31 546 562 385",
    "sg:postcode":"7671 GM",
    "sg:province":"Overijssel",
    "wof:name":"Openbare Bibliotheek",
    "wof:placetype":"venue"
},
  "geometry": {"coordinates":[6.624469,52.411098],"type":"Point"}
}