{
  "type": "Feature",
  "properties": {
    "addr:full":"Schoollaan 16 Paterswolde Provincie Drenthe 9765 AC",
    "addr:housenumber":"16",
    "addr:postcode":"9765 ac",
    "addr:street":"Schoollaan;Provincie Drenthe",
    "iso:country":"NL",
    "sg:address":"Schoollaan 16",
    "sg:city":"Paterswolde",
    "sg:orig_category":"Verhuur Kleding And Schoenen",
    "sg:phone":"+31 50 309 6032",
    "sg:postcode":"9765 AC",
    "sg:province":"Provincie Drenthe",
    "wof:name":"Ado'S Centrum",
    "wof:placetype":"venue"
},
  "geometry": {"coordinates":[6.567328,53.142719],"type":"Point"}
}