{
  "type": "Feature",
  "properties": {
    "iso:country":"NL",
    "sg:address":"Solingenstr 21",
    "sg:city":"Deventer",
    "sg:orig_category":"Bloemen En Planten - Groothandel",
    "sg:phone":"+31 570 658 537",
    "sg:postcode":"7421 ZP",
    "sg:province":"NL.08",
    "sg:website":"http://www.henkkraltbloemen.nl",
    "wof:name":"Henk Kralt Vof",
    "wof:placetype":"venue"
},
  "geometry": {"coordinates":[6.214647,52.241066],"type":"Point"}
}