{
  "type": "Feature",
  "properties": {
    "addr:full":"Hoogstr 24 Veghel North Brabant 5462 CX",
    "addr:housenumber":"24",
    "addr:postcode":"5462 cx",
    "addr:street":"Hoogstr",
    "iso:country":"NL",
    "sg:address":"Hoogstr 24",
    "sg:city":"Veghel",
    "sg:orig_category":"Verlichting",
    "sg:phone":"+31 413 321 315",
    "sg:postcode":"5462 CX",
    "sg:province":"North Brabant",
    "sg:website":"http://www.lichtstudio.nl",
    "wof:name":"Lichtstudio Veghel",
    "wof:placetype":"venue"
},
  "geometry": {"coordinates":[5.614073,51.594501],"type":"Point"}
}