{
  "type": "Feature",
  "properties": {
    "addr:full":"Bergweg 19 Arnhem Gelderland 6881 CC",
    "addr:housenumber":"19",
    "addr:postcode":"6881 cc",
    "addr:street":"Bergweg",
    "iso:country":"NL",
    "sg:address":"Bergweg 19",
    "sg:city":"Arnhem",
    "sg:orig_category":"Film-, Tv- And Videoproductie",
    "sg:phone":"+31 26 443 1818",
    "sg:postcode":"6881 CC",
    "sg:province":"Gelderland",
    "wof:name":"Avu Audiovisuele Uitvoeringen",
    "wof:placetype":"venue"
},
  "geometry": {"coordinates":[5.900939,51.982727],"type":"Point"}
}