{
  "type": "Feature",
  "properties": {
    "addr:full":"Vianenweg 7 Holten Overijssel 7451 TD",
    "addr:housenumber":"7",
    "addr:postcode":"7451 td",
    "addr:street":"Vianenweg",
    "iso:country":"NL",
    "sg:address":"Vianenweg 7",
    "sg:city":"Holten",
    "sg:orig_category":"Muziekinstrumenten",
    "sg:phone":"+31 548 362 123",
    "sg:postcode":"7451 TD",
    "sg:province":"Overijssel",
    "wof:name":"R.H.B. Bos",
    "wof:placetype":"venue"
},
  "geometry": {"coordinates":[6.446768,52.272533],"type":"Point"}
}