{
  "type": "Feature",
  "properties": {
    "iso:country":"NL",
    "sg:address":"Dovenetelln 24A",
    "sg:city":"Arnhem",
    "sg:orig_category":"Verenigingsgebouwen",
    "sg:phone":"+31 26 321 7606",
    "sg:postcode":"6841 EH",
    "sg:province":"Gelderland",
    "wof:name":"Zuid Wester, De",
    "wof:placetype":"venue"
},
  "geometry": {"coordinates":[5.90049,51.968643],"type":"Point"}
}