{
  "type": "Feature",
  "properties": {
    "iso:country":"NL",
    "sg:address":"Rokkeveenseweg 49",
    "sg:city":"2712",
    "sg:classifiers":[
        {
            "category":"Industrial Area",
            "type":"Public Place"
        }
    ],
    "sg:phone":"+31 79 353 9000",
    "sg:postcode":"PJ Z OE",
    "sg:province":"South Holland",
    "sg:tags":[
        "large",
        "private"
    ],
    "sg:website":"www.numico.com",
    "wof:name":"Royal Numico N.V.",
    "wof:placetype":"venue"
},
  "geometry": {"coordinates":[4.505318,52.046005],"type":"Point"}
}