{
  "type": "Feature",
  "properties": {
    "addr:full":"Princenhoff 6 Den Helder North Holland 1785 RV",
    "addr:housenumber":"6",
    "addr:postcode":"1785 rv",
    "addr:street":"Princenhoff",
    "iso:country":"NL",
    "sg:address":"Princenhoff 6",
    "sg:city":"Den Helder",
    "sg:orig_category":"Verzekeringen - Verzekeringskantoren",
    "sg:phone":"+31 223 633 436",
    "sg:postcode":"1785 RV",
    "sg:province":"North Holland",
    "wof:name":"Troost, J",
    "wof:placetype":"venue"
},
  "geometry": {"coordinates":[4.775643,52.933998],"type":"Point"}
}