{
  "type": "Feature",
  "properties": {
    "addr:full":"Aalberseln 26 Woerden Utrecht 3445 TB",
    "addr:housenumber":"26",
    "addr:postcode":"3445 tb",
    "addr:street":"Aalberseln",
    "iso:country":"NL",
    "sg:address":"Aalberseln 26",
    "sg:city":"Woerden",
    "sg:orig_category":"Fotografie Reclame En Mode",
    "sg:phone":"+31 348 421 857",
    "sg:postcode":"3445 TB",
    "sg:province":"Utrecht",
    "wof:name":"Graaf, Trudelies De",
    "wof:placetype":"venue"
},
  "geometry": {"coordinates":[4.887371,52.085117],"type":"Point"}
}