{
  "type": "Feature",
  "properties": {
    "addr:full":"A Schelfhoutstr 39A Amsterdam North Holland 1058 HS",
    "addr:housenumber":"39a",
    "addr:postcode":"1058 hs",
    "iso:country":"NL",
    "sg:address":"A Schelfhoutstr 39A",
    "sg:city":"Amsterdam",
    "sg:orig_category":"Kinderkleding",
    "sg:phone":"+31 20 408 1300",
    "sg:postcode":"1058 HS",
    "sg:province":"North Holland",
    "wof:name":"Imps & Elfs Bv",
    "wof:placetype":"venue"
},
  "geometry": {"coordinates":[4.851061,52.35704],"type":"Point"}
}