{
  "type": "Feature",
  "properties": {
    "addr:full":"Pyramideweg 13 Urk Flevoland 8321 CG",
    "addr:housenumber":"13",
    "addr:postcode":"8321 cg",
    "addr:street":"Pyramideweg;Flevoland",
    "iso:country":"NL",
    "sg:address":"Pyramideweg 13",
    "sg:city":"Urk",
    "sg:orig_category":"Werving And Selectie Van Tijdelijk Personeel And Uitzendkantoren",
    "sg:phone":"+31 527 686 405",
    "sg:postcode":"8321 CG",
    "sg:province":"Flevoland",
    "wof:name":"Randstad Uitzendbureau Bv",
    "wof:placetype":"venue"
},
  "geometry": {"coordinates":[5.6078691483,52.6624717712],"type":"Point"}
}