{
  "type": "Feature",
  "properties": {
    "iso:country":"NL",
    "sg:address":"Op De Driessen 67",
    "sg:city":"Koningsbosch",
    "sg:orig_category":"Video - Faciliteiten En Producties",
    "sg:phone":"+31 475 302 517",
    "sg:postcode":"6104 AV",
    "sg:province":"Limburg",
    "wof:name":"M & E",
    "wof:placetype":"venue"
},
  "geometry": {"coordinates":[5.952481,51.051949],"type":"Point"}
}