{
  "type": "Feature",
  "properties": {
    "addr:full":"Straussln 124 S Gravenhage South Holland 2551 NR",
    "addr:housenumber":"124",
    "addr:postcode":"2551 nr",
    "addr:street":"S Gravenhage",
    "iso:country":"NL",
    "sg:address":"Straussln 124",
    "sg:city":"S Gravenhage",
    "sg:orig_category":"Verzekeringen - Verzekeringskantoren",
    "sg:phone":"+31 70 325 4176",
    "sg:postcode":"2551 NR",
    "sg:province":"South Holland",
    "sg:website":"http://www.fin-advies.nl",
    "wof:name":"Fin-Advies",
    "wof:placetype":"venue"
},
  "geometry": {"coordinates":[4.23775,52.058601],"type":"Point"}
}