{
  "type": "Feature",
  "properties": {
    "addr:full":"Maasdijk 219 Wijk En Aalburg Gelderland 4261 AJ",
    "addr:housenumber":"219",
    "addr:postcode":"4261 aj",
    "addr:street":"Maasdijk",
    "iso:country":"NL",
    "sg:address":"Maasdijk 219",
    "sg:city":"Wijk En Aalburg",
    "sg:orig_category":"Fruit And Groenten Gh",
    "sg:phone":"+31 416 691 197",
    "sg:postcode":"4261 AJ",
    "sg:province":"Gelderland",
    "wof:name":"A. Vos",
    "wof:placetype":"venue"
},
  "geometry": {"coordinates":[5.119928,51.772141],"type":"Point"}
}