{
  "type": "Feature",
  "properties": {
    "iso:country":"NL",
    "sg:address":"Den Engelsenstr 8",
    "sg:city":"Zevenbergen",
    "sg:orig_category":"Timmerwerken",
    "sg:phone":"+31 168 326 855",
    "sg:postcode":"4761 GP",
    "sg:province":"Noord-Brabant",
    "wof:name":"Snelders Timmerwerken",
    "wof:placetype":"venue"
},
  "geometry": {"coordinates":[4.602394,51.651375],"type":"Point"}
}