{
  "type": "Feature",
  "properties": {
    "addr:full":"Ossewg 21 Berghem Noord-Brabant 5351 AA",
    "addr:housenumber":"21",
    "addr:postcode":"5351 aa",
    "addr:street":"Ossewg",
    "iso:country":"NL",
    "sg:address":"Ossewg 21",
    "sg:city":"Berghem",
    "sg:orig_category":"Verzekeringen - Verzekeringskantoren",
    "sg:phone":"+31 412 403 614",
    "sg:postcode":"5351 AA",
    "sg:province":"Noord-Brabant",
    "wof:name":"Ballegooij Bv, Van",
    "wof:placetype":"venue"
},
  "geometry": {"coordinates":[5.562348,51.768993],"type":"Point"}
}