{
  "type": "Feature",
  "properties": {
    "addr:full":"Heerlerbaan 173 Heerlen Limburg 6418 CC",
    "addr:housenumber":"173",
    "addr:postcode":"6418 cc",
    "addr:street":"Heerlerbaan",
    "iso:country":"NL",
    "sg:address":"Heerlerbaan 173",
    "sg:city":"Heerlen",
    "sg:orig_category":"Kappers",
    "sg:phone":"+31 45 541 7183",
    "sg:postcode":"6418 CC",
    "sg:province":"Limburg",
    "wof:name":"Mg Hairstyling",
    "wof:placetype":"venue"
},
  "geometry": {"coordinates":[6.000049,50.867413],"type":"Point"}
}