{
  "type": "Feature",
  "properties": {
    "addr:full":"Javastr 69 Amsterdam Noord-Holland 1094 HB",
    "addr:housenumber":"69",
    "addr:postcode":"1094 hb",
    "addr:street":"Javastr",
    "iso:country":"NL",
    "sg:address":"Javastr 69",
    "sg:city":"Amsterdam",
    "sg:orig_category":"Kappers",
    "sg:phone":"+31 20 692 0818",
    "sg:postcode":"1094 HB",
    "sg:province":"Noord-Holland",
    "wof:name":"Sa\u00efdi",
    "wof:placetype":"venue"
},
  "geometry": {"coordinates":[4.934279,52.363831],"type":"Point"}
}