{
  "type": "Feature",
  "properties": {
    "addr:full":"Meerten Verhoffstraat 30 Breda Noord-Brabant 4811 AS",
    "addr:housenumber":"30",
    "addr:postcode":"4811 as",
    "addr:street":"Meerten Verhoffstraat",
    "iso:country":"NL",
    "sg:address":"Meerten Verhoffstraat 30",
    "sg:city":"Breda",
    "sg:orig_category":"Overheidsdiensten",
    "sg:phone":"+31 76 525 2800",
    "sg:postcode":"4811 AS",
    "sg:province":"Noord-Brabant",
    "wof:name":"Mf Belastingdienst / Sigo",
    "wof:placetype":"venue"
},
  "geometry": {"coordinates":[4.7812891006,51.5944099426],"type":"Point"}
}