{
  "type": "Feature",
  "properties": {
    "iso:country":"NL",
    "sg:address":"Wijkerstraatweg 251",
    "sg:city":"Velsen-Noord",
    "sg:orig_category":"Kantoorartikelen",
    "sg:phone":"+31 251 216 290",
    "sg:postcode":"1951 EG",
    "sg:province":"Noord-Holland",
    "wof:name":"Polycon Nederland Bv",
    "wof:placetype":"venue"
},
  "geometry": {"coordinates":[4.6471152306,52.4747390747],"type":"Point"}
}