{
  "type": "Feature",
  "properties": {
    "addr:full":"Molenlaan 19 Honselersdijk Zuid-Holland 2675 CA",
    "addr:housenumber":"19",
    "addr:postcode":"2675 ca",
    "addr:street":"Molenlaan",
    "iso:country":"NL",
    "sg:address":"Molenlaan 19",
    "sg:city":"Honselersdijk",
    "sg:orig_category":"Schilderwerk",
    "sg:phone":"+31 174 625 585",
    "sg:postcode":"2675 CA",
    "sg:province":"Zuid-Holland",
    "wof:name":"T. De Vette",
    "wof:placetype":"venue"
},
  "geometry": {"coordinates":[4.231046,52.007679],"type":"Point"}
}