{
  "type": "Feature",
  "properties": {
    "addr:full":"Slenkstr 1 Ysselmuiden Overijssel 8271 TA",
    "addr:housenumber":"1",
    "addr:postcode":"8271 ta",
    "addr:street":"Slenkstr;Overijssel",
    "iso:country":"NL",
    "sg:address":"Slenkstr 1",
    "sg:city":"Ysselmuiden",
    "sg:orig_category":"Tuinaanleg En -Onderhoud",
    "sg:phone":"+31 38 332 1354",
    "sg:postcode":"8271 TA",
    "sg:province":"Overijssel",
    "wof:name":"Alja Tuinaanleg En Onderhoud",
    "wof:placetype":"venue"
},
  "geometry": {"coordinates":[5.93093,52.563976],"type":"Point"}
}