{
  "type": "Feature",
  "properties": {
    "addr:full":"Dijk 43 Broek Op Langedijk Noord-Holland 1721 AA",
    "addr:housenumber":"43",
    "addr:postcode":"1721 aa",
    "addr:street":"Dijk",
    "iso:country":"NL",
    "sg:address":"Dijk 43",
    "sg:city":"Broek Op Langedijk",
    "sg:orig_category":"Wegenbouw",
    "sg:phone":"+31 226 316 388",
    "sg:postcode":"1721 AA",
    "sg:province":"Noord-Holland",
    "wof:name":"Sandam",
    "wof:placetype":"venue"
},
  "geometry": {"coordinates":[4.8021531105,52.6705513],"type":"Point"}
}