{
  "type": "Feature",
  "properties": {
    "addr:full":"Lekdk 7A Everdingen Utrecht 4121 KG",
    "addr:housenumber":"7a",
    "addr:postcode":"4121 kg",
    "addr:street":"Lekdk",
    "iso:country":"NL",
    "sg:address":"Lekdk 7A",
    "sg:city":"Everdingen",
    "sg:orig_category":"Meubelen - Fabrieken En Groothandel",
    "sg:phone":"+31 347 351 272",
    "sg:postcode":"4121 KG",
    "sg:province":"Utrecht",
    "wof:name":"Speravi",
    "wof:placetype":"venue"
},
  "geometry": {"coordinates":[5.169846,51.96381],"type":"Point"}
}