{
  "type": "Feature",
  "properties": {
    "addr:full":"Postbus 16 Zevenaar Gelderland 6900 AA",
    "addr:housenumber":"16",
    "addr:postcode":"6900 aa",
    "addr:street":"Postbus",
    "iso:country":"NL",
    "sg:address":"Postbus 16",
    "sg:city":"Zevenaar",
    "sg:orig_category":"Fotoreportages",
    "sg:phone":"+31 316 333 034",
    "sg:postcode":"6900 AA",
    "sg:province":"Gelderland",
    "wof:name":"Emje",
    "wof:placetype":"venue"
},
  "geometry": {"coordinates":[6.076878,51.931618],"type":"Point"}
}