{
  "type": "Feature",
  "properties": {
    "iso:country":"NL",
    "sg:address":"Arkelstein 23",
    "sg:city":"Dordrecht",
    "sg:orig_category":"Goederenvervoer Over De Weg",
    "sg:phone":"+31 78 618 7422",
    "sg:postcode":"3328 BA",
    "sg:province":"South Holland",
    "wof:name":"Beacon Freightline Limited",
    "wof:placetype":"venue"
},
  "geometry": {"coordinates":[4.666283,51.773537],"type":"Point"}
}