{
  "type": "Feature",
  "properties": {
    "addr:full":"Bernstraat 56 Haarlem Noord-Holland 2034 CW",
    "addr:housenumber":"56",
    "addr:postcode":"2034 cw",
    "addr:street":"Bernstraat",
    "iso:country":"NL",
    "sg:address":"Bernstraat 56",
    "sg:city":"Haarlem",
    "sg:orig_category":"Verhuur Bouwmachines",
    "sg:phone":"+31 23 535 3086",
    "sg:postcode":"2034 CW",
    "sg:province":"Noord-Holland",
    "wof:name":"Huijnen Steigers",
    "wof:placetype":"venue"
},
  "geometry": {"coordinates":[4.649984,52.357555],"type":"Point"}
}