{
  "type": "Feature",
  "properties": {
    "addr:full":"Zeegat 55 Hellevoetsluis Zuid-Holland 3224 SH",
    "addr:housenumber":"55",
    "addr:postcode":"3224 sh",
    "addr:street":"Zeegat",
    "iso:country":"NL",
    "sg:address":"Zeegat 55",
    "sg:city":"Hellevoetsluis",
    "sg:orig_category":"Koeltechniek",
    "sg:phone":"+31 187 317 207",
    "sg:postcode":"3224 SH",
    "sg:province":"Zuid-Holland",
    "wof:name":"Reijenga",
    "wof:placetype":"venue"
},
  "geometry": {"coordinates":[4.145941,51.823898],"type":"Point"}
}