{
  "type": "Feature",
  "properties": {
    "iso:country":"NL",
    "sg:address":"Zeegat 55",
    "sg:city":"Hellevoetsluis",
    "sg:orig_category":"Koeltechniek",
    "sg:phone":"+31 187 317 207",
    "sg:postcode":"3224 SH",
    "sg:province":"Zuid-Holland",
    "wof:name":"Reijenga",
    "wof:placetype":"venue"
},
  "geometry": {"coordinates":[4.145941,51.823898],"type":"Point"}
}