{
  "type": "Feature",
  "properties": {
    "iso:country":"NL",
    "sg:address":"Hoofdwg N 7",
    "sg:city":"Spyk Gn",
    "sg:classifiers":[
        {
            "category":"Retail",
            "subcategory":"Auto Repair",
            "type":"Services"
        }
    ],
    "sg:phone":"+31 596 591 241",
    "sg:postcode":"9909 AC",
    "sg:province":"Groningen",
    "sg:tags":[
        "garage"
    ],
    "wof:name":"West",
    "wof:placetype":"venue"
},
  "geometry": {"coordinates":[6.83624,53.388969],"type":"Point"}
}