{
  "type": "Feature",
  "properties": {
    "addr:full":"Ysbaanwg 11 Laren Nh Noord-Holland 1251 VT",
    "addr:housenumber":"11",
    "addr:postcode":"1251",
    "addr:street":"Ysbaanwg",
    "iso:country":"NL",
    "sg:address":"Ysbaanwg 11",
    "sg:city":"Laren Nh",
    "sg:orig_category":"Onderhoudswerken",
    "sg:phone":"+31 35 531 9137",
    "sg:postcode":"1251 VT",
    "sg:province":"Noord-Holland",
    "wof:name":"Bolweg Onderhoudsprojecten",
    "wof:placetype":"venue"
},
  "geometry": {"coordinates":[5.22387,52.256741],"type":"Point"}
}