{
  "type": "Feature",
  "properties": {
    "iso:country":"NL",
    "sg:address":"De Rietlanden 3",
    "sg:city":"Giethoorn",
    "sg:orig_category":"Jachthavens - Jachtwerven",
    "sg:phone":"+31 521 361 173",
    "sg:postcode":"8355 CP",
    "sg:province":"Overijssel",
    "sg:website":"http://www.marinefacts.nl",
    "wof:name":"Marinefacts",
    "wof:placetype":"venue"
},
  "geometry": {"coordinates":[6.047649,52.721142],"type":"Point"}
}