{
  "type": "Feature",
  "properties": {
    "iso:country":"NL",
    "sg:address":"Wilhelminastraat 13",
    "sg:city":"Mijnsheerenland",
    "sg:orig_category":"Verzekeringen",
    "sg:phone":"+31 186 606 160",
    "sg:postcode":"3271 BX",
    "sg:province":"Zuid-Holland",
    "wof:name":"Pensioendesk",
    "wof:placetype":"venue"
},
  "geometry": {"coordinates":[4.492333,51.797634],"type":"Point"}
}