{
  "type": "Feature",
  "properties": {
    "addr:full":"F Hendrikpln 14 S Gravenhage Zuid-Holland 2582 AT",
    "addr:housenumber":"14;gravenhage",
    "addr:postcode":"2582",
    "addr:street":"S",
    "iso:country":"NL",
    "sg:address":"F Hendrikpln 14",
    "sg:city":"S Gravenhage",
    "sg:orig_category":"Notarissen En Notariskantoren",
    "sg:phone":"+31 70 350 0994",
    "sg:postcode":"2582 AT",
    "sg:province":"Zuid-Holland",
    "wof:name":"Zweeden, Mr C F Van",
    "wof:placetype":"venue"
},
  "geometry": {"coordinates":[4.27852,52.092411],"type":"Point"}
}