{
  "type": "Feature",
  "properties": {
    "addr:full":"Watertorenwg 180 Rotterdam South Holland 3063 HA",
    "addr:housenumber":"180",
    "addr:postcode":"3063 ha",
    "iso:country":"NL",
    "sg:address":"Watertorenwg 180",
    "sg:city":"Rotterdam",
    "sg:orig_category":"Grafisch Ontwerpers",
    "sg:phone":"+31 10 452 1669",
    "sg:postcode":"3063 HA",
    "sg:province":"South Holland",
    "wof:name":"Stoopman, J",
    "wof:placetype":"venue"
},
  "geometry": {"coordinates":[4.519781,51.912193],"type":"Point"}
}