{
  "type": "Feature",
  "properties": {
    "addr:full":"Groenling 1 Etten Leur North Brabant 4872 CR",
    "addr:housenumber":"1",
    "addr:postcode":"4872 cr",
    "addr:street":"Groenling",
    "iso:country":"NL",
    "sg:address":"Groenling 1",
    "sg:city":"Etten Leur",
    "sg:orig_category":"Adviesbureaus Bouwkunde",
    "sg:phone":"+31 76 504 0432",
    "sg:postcode":"4872 CR",
    "sg:province":"North Brabant",
    "sg:website":"http://www.bov.nl",
    "wof:name":"Bov, Bouwkundig Advies",
    "wof:placetype":"venue"
},
  "geometry": {"coordinates":[4.650538,51.572254],"type":"Point"}
}