{
  "type": "Feature",
  "properties": {
    "iso:country":"NL",
    "sg:address":"Staalstr 1",
    "sg:city":"Ridderkerk",
    "sg:orig_category":"Kampeerauto'S",
    "sg:phone":"+31 180 427 292",
    "sg:postcode":"2984 AJ",
    "sg:province":"South Holland",
    "sg:website":"http://www.jmrtrading.nl",
    "wof:name":"Jmr Bv",
    "wof:placetype":"venue"
},
  "geometry": {"coordinates":[4.607448101,51.873046875],"type":"Point"}
}