{
  "type": "Feature",
  "properties": {
    "addr:full":"Waldhoornpln 9 Ryswyk Zh South Holland 2287 EH",
    "addr:housenumber":"9;zh",
    "addr:postcode":"2287 eh",
    "addr:street":"Waldhoornpln",
    "iso:country":"NL",
    "sg:address":"Waldhoornpln 9",
    "sg:city":"Ryswyk Zh",
    "sg:orig_category":"Zonnebank- En Solariumcentra",
    "sg:phone":"+31 70 394 7616",
    "sg:postcode":"2287 EH",
    "sg:province":"South Holland",
    "sg:website":"http://www.total-sun.nl",
    "wof:name":"Total Sun",
    "wof:placetype":"venue"
},
  "geometry": {"coordinates":[4.32436,52.037251],"type":"Point"}
}