{
  "type": "Feature",
  "properties": {
    "iso:country":"NL",
    "sg:address":"Engelsbergenstr 2A",
    "sg:city":"Eindhoven",
    "sg:orig_category":"Biljartzalen",
    "sg:phone":"+31 40 252 5268",
    "sg:postcode":"5616 JC",
    "sg:province":"Noord-Brabant",
    "wof:name":"Snooker",
    "wof:placetype":"venue"
},
  "geometry": {"coordinates":[5.461235,51.438511],"type":"Point"}
}