{
  "type": "Feature",
  "properties": {
    "iso:country":"NL",
    "sg:address":"Wetering 3",
    "sg:city":"Vleuten",
    "sg:orig_category":"Diverse Bedrijfsinstallaties Gh",
    "sg:phone":"+31 30 677 4151",
    "sg:postcode":"3451 BN",
    "sg:province":"Utrecht",
    "wof:name":"M. Kolkman Bv",
    "wof:placetype":"venue"
},
  "geometry": {"coordinates":[5.010789,52.105865],"type":"Point"}
}