{
  "type": "Feature",
  "properties": {
    "addr:full":"K De Groteln 353A Eindhoven North Brabant 5654 NN",
    "addr:housenumber":"353a",
    "addr:postcode":"5654 nn",
    "addr:street":"K De Groteln",
    "iso:country":"NL",
    "sg:address":"K De Groteln 353A",
    "sg:city":"Eindhoven",
    "sg:orig_category":"Binnenhuisarchitectuur",
    "sg:phone":"+31 40 212 2154",
    "sg:postcode":"5654 NN",
    "sg:province":"North Brabant",
    "sg:website":"http://www.b-covered.com",
    "wof:name":"B-Covered",
    "wof:placetype":"venue"
},
  "geometry": {"coordinates":[5.45901,51.420891],"type":"Point"}
}