{
  "type": "Feature",
  "properties": {
    "addr:full":"Hongkongstraat 10 Rotterdam South Holland 3047 BS",
    "addr:housenumber":"10",
    "addr:postcode":"3047 bs",
    "addr:street":"Hongkongstraat",
    "iso:country":"NL",
    "sg:address":"Hongkongstraat 10",
    "sg:city":"Rotterdam",
    "sg:orig_category":"Airconditioning And Ventilatie",
    "sg:phone":"+31 10 437 6255",
    "sg:postcode":"3047 BS",
    "sg:province":"South Holland",
    "wof:name":"Multi Import Bv",
    "wof:placetype":"venue"
},
  "geometry": {"coordinates":[4.407675,51.943226],"type":"Point"}
}