{
  "type": "Feature",
  "properties": {
    "iso:country":"NL",
    "sg:address":"Noordeinde 128C",
    "sg:city":"Landsmeer",
    "sg:orig_category":"Bedrijfs- And Managementsconsultants",
    "sg:phone":"+31 20 482 0401",
    "sg:postcode":"1121 AL",
    "sg:province":"Noord-Holland",
    "wof:name":"Integral Knowledge Utilization Bv",
    "wof:placetype":"venue"
},
  "geometry": {"coordinates":[4.913653,52.436401],"type":"Point"}
}