{
  "type": "Feature",
  "properties": {
    "iso:country":"NL",
    "sg:address":"Espakker 18",
    "sg:city":"Teteringen",
    "sg:orig_category":"Onderhoud And Reparatie Kantoorapparatuur",
    "sg:phone":"+31 162 439 677",
    "sg:postcode":"4847 HA",
    "sg:province":"North Brabant",
    "wof:name":"Solution Oplossingen In Multimedia",
    "wof:placetype":"venue"
},
  "geometry": {"coordinates":[4.816101,51.606426],"type":"Point"}
}