{
  "type": "Feature",
  "properties": {
    "iso:country":"NL",
    "sg:address":"Dorpsstr 39",
    "sg:city":"Zuidlaarderveen",
    "sg:orig_category":"Verbouwingen",
    "sg:phone":"+31 598 491 887",
    "sg:postcode":"9474 PB",
    "sg:province":"Provincie Drenthe",
    "wof:name":"Brugge, D",
    "wof:placetype":"venue"
},
  "geometry": {"coordinates":[6.748872,53.103146],"type":"Point"}
}