{
  "type": "Feature",
  "properties": {
    "addr:full":"Nieuwkoopseweg 11 Pijnacker Zuid-Holland 2641 PA",
    "addr:housenumber":"11",
    "addr:postcode":"2641 pa",
    "addr:street":"Nieuwkoopseweg",
    "iso:country":"NL",
    "sg:address":"Nieuwkoopseweg 11",
    "sg:city":"Pijnacker",
    "sg:orig_category":"Overheidsdiensten",
    "sg:phone":"+31 15 369 2630",
    "sg:postcode":"2641 PA",
    "sg:province":"Zuid-Holland",
    "wof:name":"De Notelaer",
    "wof:placetype":"venue"
},
  "geometry": {"coordinates":[4.4310531616,52.0307006836],"type":"Point"}
}