{
  "type": "Feature",
  "properties": {
    "addr:full":"Columbusplein 11 Amsterdam North Holland 1057 TS",
    "addr:housenumber":"11",
    "addr:postcode":"1057 ts",
    "addr:street":"Columbusplein",
    "iso:country":"NL",
    "sg:address":"Columbusplein 11",
    "sg:city":"Amsterdam",
    "sg:orig_category":"Meubelmakerijen",
    "sg:phone":"+31 20 683 5969",
    "sg:postcode":"1057 TS",
    "sg:province":"North Holland",
    "wof:name":"Jos Belle",
    "wof:placetype":"venue"
},
  "geometry": {"coordinates":[4.855908,52.365494],"type":"Point"}
}