{
  "type": "Feature",
  "properties": {
    "addr:full":"Lange Delft 39 Middelburg Zeeland 4331  A",
    "addr:housenumber":"39;4331 a",
    "addr:street":"Lange Delft",
    "iso:country":"NL",
    "sg:address":"Lange Delft 39",
    "sg:city":"Middelburg",
    "sg:orig_category":"Boekenuitgeverijen",
    "sg:phone":"+31 118 650 211",
    "sg:postcode":"4331  A",
    "sg:province":"Zeeland",
    "wof:name":"Bruna",
    "wof:placetype":"venue"
},
  "geometry": {"coordinates":[3.614633,51.498444],"type":"Point"}
}