{
  "type": "Feature",
  "properties": {
    "addr:full":"Goorbergseweg 31 Molenschot North Brabant 5124 NE",
    "addr:housenumber":"31",
    "addr:postcode":"5124 ne",
    "addr:street":"Goorbergseweg",
    "iso:country":"NL",
    "sg:address":"Goorbergseweg 31",
    "sg:city":"Molenschot",
    "sg:orig_category":"Bedrijfs- And Managementsconsultants",
    "sg:phone":"+31 161 412 601",
    "sg:postcode":"5124 NE",
    "sg:province":"North Brabant",
    "wof:name":"Syndicus",
    "wof:placetype":"venue"
},
  "geometry": {"coordinates":[4.881146,51.581139],"type":"Point"}
}