{
  "type": "Feature",
  "properties": {
    "addr:full":"Bloemendaalseweg 325 Overveen North Holland 2051 GH",
    "addr:housenumber":"325",
    "addr:postcode":"2051 gh",
    "addr:street":"Bloemendaalseweg",
    "iso:country":"NL",
    "sg:address":"Bloemendaalseweg 325",
    "sg:city":"Overveen",
    "sg:orig_category":"Huishoudapparatuur, Televisies And Radio'S",
    "sg:phone":"+31 23 525 8424",
    "sg:postcode":"2051 GH",
    "sg:province":"North Holland",
    "wof:name":"Dvd Plus",
    "wof:placetype":"venue"
},
  "geometry": {"coordinates":[4.60798,52.388729],"type":"Point"}
}