{
  "type": "Feature",
  "properties": {
    "iso:country":"NL",
    "sg:address":"Raadhuisstr 22",
    "sg:city":"Roosendaal",
    "sg:orig_category":"Schoenen",
    "sg:phone":"+31 165 556 771",
    "sg:postcode":"4701 PS",
    "sg:province":"Noord-Brabant",
    "wof:name":"Fiore",
    "wof:placetype":"venue"
},
  "geometry": {"coordinates":[4.457725,51.532333],"type":"Point"}
}