{
  "type": "Feature",
  "properties": {
    "addr:full":"Kanaalstraat 128 Utrecht Utrecht 3531 CP",
    "addr:housenumber":"128",
    "addr:postcode":"3531 cp",
    "addr:street":"Kanaalstraat",
    "iso:country":"NL",
    "sg:address":"Kanaalstraat 128",
    "sg:city":"Utrecht",
    "sg:orig_category":"Gespecialiseerde Voeding",
    "sg:phone":"+31 30 293 8231",
    "sg:postcode":"3531 CP",
    "sg:province":"Utrecht",
    "wof:name":"Paryba",
    "wof:placetype":"venue"
},
  "geometry": {"coordinates":[5.098621,52.091011],"type":"Point"}
}