{
  "type": "Feature",
  "properties": {
    "addr:full":"Dykwg 305 Andyk North Holland 1619 JH",
    "addr:housenumber":"305",
    "addr:postcode":"1619 jh",
    "addr:street":"Andyk North",
    "iso:country":"NL",
    "sg:address":"Dykwg 305",
    "sg:city":"Andyk",
    "sg:classifiers":[
        {
            "category":"Wholesale",
            "subcategory":"Motor Vehicles",
            "type":"Manufacturing & Wholesale Goods"
        }
    ],
    "sg:phone":"+31 228 593 376",
    "sg:postcode":"1619 JH",
    "sg:province":"North Holland",
    "sg:tags":[
        "scooter",
        "en"
    ],
    "wof:name":"Twin Power",
    "wof:placetype":"venue"
},
  "geometry": {"coordinates":[5.222525,52.744362],"type":"Point"}
}