{
  "type": "Feature",
  "properties": {
    "iso:country":"NL",
    "sg:address":"Binckhorstlaan 340",
    "sg:city":"'S Gravenhage",
    "sg:orig_category":"Fotografische And Optische Artikelen Gh",
    "sg:phone":"+31 70 381 4101",
    "sg:postcode":"2516 BL",
    "sg:province":"Zuid-Holland",
    "wof:name":"East West Agencies Bv",
    "wof:placetype":"venue"
},
  "geometry": {"coordinates":[4.34188,52.065208],"type":"Point"}
}