{
  "type": "Feature",
  "properties": {
    "addr:full":"Industriewg 24A Grootebroek Noord-Holland 1613 KV",
    "addr:housenumber":"24a",
    "addr:postcode":"1613 kv",
    "addr:street":"Industriewg",
    "iso:country":"NL",
    "sg:address":"Industriewg 24A",
    "sg:city":"Grootebroek",
    "sg:classifiers":[
        {
            "category":"Wholesale",
            "subcategory":"Motor Vehicles",
            "type":"Manufacturing & Wholesale Goods"
        }
    ],
    "sg:phone":"+31 228 520 339",
    "sg:postcode":"1613 KV",
    "sg:province":"Noord-Holland",
    "sg:tags":[
        "scooter",
        "en"
    ],
    "wof:name":"Ditmar",
    "wof:placetype":"venue"
},
  "geometry": {"coordinates":[5.223419,52.694447],"type":"Point"}
}