{
  "type": "Feature",
  "properties": {
    "addr:full":"Botpln 5 Almere Flevoland 1317 SK",
    "addr:housenumber":"5",
    "addr:street":"Botpln;Flevoland 1317",
    "iso:country":"NL",
    "sg:address":"Botpln 5",
    "sg:city":"Almere",
    "sg:classifiers":[
        {
            "category":"Food & Beverages",
            "subcategory":"Bakery",
            "type":"Retail Goods"
        }
    ],
    "sg:phone":"+31 36 534 1866",
    "sg:postcode":"1317 SK",
    "sg:province":"Flevoland",
    "sg:tags":[
        "brood",
        "en",
        "banket"
    ],
    "wof:name":"Rebel, G J",
    "wof:placetype":"venue"
},
  "geometry": {"coordinates":[5.23159,52.389122],"type":"Point"}
}