{
  "type": "Feature",
  "properties": {
    "addr:full":"Brugstr 22 Groningen Groningen 9711 HZ",
    "addr:housenumber":"22",
    "addr:postcode":"9711 hz",
    "addr:street":"Brugstr",
    "iso:country":"NL",
    "sg:address":"Brugstr 22",
    "sg:city":"Groningen",
    "sg:orig_category":"Gelegenheidskleding",
    "sg:phone":"+31 50 312 1675",
    "sg:postcode":"9711 HZ",
    "sg:province":"Groningen",
    "sg:website":"www.ggspecialsizes.com",
    "wof:name":"Vinke",
    "wof:placetype":"venue"
},
  "geometry": {"coordinates":[6.560261,53.216183],"type":"Point"}
}