{
  "type": "Feature",
  "properties": {
    "iso:country":"NL",
    "sg:address":"Prunuslaan 1",
    "sg:city":"Appingedam",
    "sg:orig_category":"Boekhouders",
    "sg:phone":"+31 596 620 485",
    "sg:postcode":"9902 PT",
    "sg:province":"Groningen",
    "wof:name":"Administratiekantoor Droogsma",
    "wof:placetype":"venue"
},
  "geometry": {"coordinates":[6.8688230515,53.3129844666],"type":"Point"}
}