{
  "type": "Feature",
  "properties": {
    "iso:country":"NL",
    "sg:address":"A V Ostadeln 67",
    "sg:city":"Utrecht",
    "sg:orig_category":"Webdesign Bureaus",
    "sg:phone":"+31 30 254 1027",
    "sg:postcode":"3583 AC",
    "sg:province":"Utrecht",
    "wof:name":"Groenenboom, Niels",
    "wof:placetype":"venue"
},
  "geometry": {"coordinates":[5.1437101364,52.0866012573],"type":"Point"}
}