{
  "type": "Feature",
  "properties": {
    "addr:full":"Hogenendsewg 76 Didam Gelderland 6942 DW",
    "addr:housenumber":"76",
    "addr:postcode":"6942 dw",
    "addr:street":"Hogenendsewg;Gelderland",
    "iso:country":"NL",
    "sg:address":"Hogenendsewg 76",
    "sg:city":"Didam",
    "sg:orig_category":"Plafonds",
    "sg:phone":"+31 316 226 624",
    "sg:postcode":"6942 DW",
    "sg:province":"Gelderland",
    "wof:name":"Waplamon",
    "wof:placetype":"venue"
},
  "geometry": {"coordinates":[6.124124,51.933697],"type":"Point"}
}