{
  "type": "Feature",
  "properties": {
    "addr:full":"Laakweg 2 Nootdorp South Holland 2631 PJ",
    "addr:housenumber":"2",
    "addr:postcode":"2631 pj",
    "addr:street":"Laakweg",
    "iso:country":"NL",
    "sg:address":"Laakweg 2",
    "sg:city":"Nootdorp",
    "sg:orig_category":"Personenvervoer Zonder Dienstregeling",
    "sg:phone":"+31 15 310 7141",
    "sg:postcode":"2631 PJ",
    "sg:province":"South Holland",
    "wof:name":"Hofstad Tours Bv",
    "wof:placetype":"venue"
},
  "geometry": {"coordinates":[4.411936,52.039413],"type":"Point"}
}