{
  "type": "Feature",
  "properties": {
    "addr:full":"Nieuwewg 2 Poeldyk Zuid-Holland 2685 AP",
    "addr:housenumber":"2",
    "addr:postcode":"2685 ap",
    "addr:street":"Nieuwewg",
    "iso:country":"NL",
    "sg:address":"Nieuwewg 2",
    "sg:city":"Poeldyk",
    "sg:orig_category":"Verzekeringen - Verzekeringskantoren",
    "sg:phone":"+31 174 643 244",
    "sg:postcode":"2685 AP",
    "sg:province":"Zuid-Holland",
    "sg:website":"http://www.wubbenbauer.nl",
    "wof:name":"Wubben-Bauer",
    "wof:placetype":"venue"
},
  "geometry": {"coordinates":[4.226438,52.032814],"type":"Point"}
}