{
  "type": "Feature",
  "properties": {
    "addr:full":"Avondsterwg 10 Leeuwarden Provincie Friesland 8938 AK",
    "addr:housenumber":"10",
    "addr:postcode":"8938 ak",
    "addr:street":"Avondsterwg;Provincie Friesland",
    "iso:country":"NL",
    "sg:address":"Avondsterwg 10",
    "sg:city":"Leeuwarden",
    "sg:orig_category":"Verenigingen En Stichtingen",
    "sg:phone":"+31 58 280 0175",
    "sg:postcode":"8938 AK",
    "sg:province":"Provincie Friesland",
    "wof:name":"Scantri Hal",
    "wof:placetype":"venue"
},
  "geometry": {"coordinates":[5.842486,53.191177],"type":"Point"}
}