{
  "type": "Feature",
  "properties": {
    "addr:full":"De Hofstede 32 Lienden Gelderland 4033 BV",
    "addr:housenumber":"32",
    "addr:postcode":"4033 bv",
    "addr:street":"De Hofstede;Gelderland",
    "iso:country":"NL",
    "sg:address":"De Hofstede 32",
    "sg:city":"Lienden",
    "sg:orig_category":"Goederenvervoer Over De Weg",
    "sg:phone":"+31 344 600 717",
    "sg:postcode":"4033 BV",
    "sg:province":"Gelderland",
    "wof:name":"D. Gijsberts",
    "wof:placetype":"venue"
},
  "geometry": {"coordinates":[5.52054,51.938335],"type":"Point"}
}