{
  "type": "Feature",
  "properties": {
    "addr:full":"Lemelerberg 117 Capelle A/D Ijssel Zuid-Holland 2905 NK",
    "addr:housenumber":"117;a / d",
    "addr:postcode":"2905 nk",
    "addr:street":"Lemelerberg",
    "iso:country":"NL",
    "sg:address":"Lemelerberg 117",
    "sg:city":"Capelle A/D Ijssel",
    "sg:orig_category":"Boekhouders",
    "sg:phone":"+31 10 451 1592",
    "sg:postcode":"2905 NK",
    "sg:province":"Zuid-Holland",
    "wof:name":"Administratiekantoor Schiltman & Partners",
    "wof:placetype":"venue"
},
  "geometry": {"coordinates":[4.5846,51.923401],"type":"Point"}
}