{
  "type": "Feature",
  "properties": {
    "addr:full":"Middenveer 2 Sliedrecht Zuid-Holland 3361 TK",
    "addr:housenumber":"2",
    "addr:postcode":"3361 tk",
    "addr:street":"Middenveer",
    "iso:country":"NL",
    "sg:address":"Middenveer 2",
    "sg:city":"Sliedrecht",
    "sg:orig_category":"Boekhouders",
    "sg:phone":"+31 184 416 979",
    "sg:postcode":"3361 TK",
    "sg:province":"Zuid-Holland",
    "wof:name":"A.K.B. Administratie & Advies",
    "wof:placetype":"venue"
},
  "geometry": {"coordinates":[4.783568,51.818241],"type":"Point"}
}