{
  "type": "Feature",
  "properties": {
    "iso:country":"NL",
    "sg:address":"Heulwg 128B",
    "sg:city":"Kwintsheul",
    "sg:orig_category":"Administratie- En Boekhoudkantoren",
    "sg:phone":"+31 174 290 731",
    "sg:postcode":"2295 KK",
    "sg:province":"Zuid-Holland",
    "wof:name":"Hc-Partners",
    "wof:placetype":"venue"
},
  "geometry": {"coordinates":[4.256872,52.016438],"type":"Point"}
}