{
  "type": "Feature",
  "properties": {
    "addr:full":"Fonteynenburghlaan 19 Voorburg Zuid-Holland 2275 CZ",
    "addr:housenumber":"19",
    "addr:postcode":"2275",
    "addr:street":"Fonteynenburghlaan",
    "iso:country":"NL",
    "sg:address":"Fonteynenburghlaan 19",
    "sg:city":"Voorburg",
    "sg:orig_category":"Architecten",
    "sg:phone":"+31 70 319 1404",
    "sg:postcode":"2275 CZ",
    "sg:province":"Zuid-Holland",
    "wof:name":"Architectenbureau Ir Martien Vogelezang Bi",
    "wof:placetype":"venue"
},
  "geometry": {"coordinates":[4.349547,52.062298],"type":"Point"}
}