{
  "type": "Feature",
  "properties": {
    "addr:full":"Markt 20 Venlo Limburg 5911 HD",
    "addr:housenumber":"20",
    "addr:postcode":"5911 hd",
    "addr:street":"Markt",
    "iso:country":"NL",
    "sg:address":"Markt 20",
    "sg:city":"Venlo",
    "sg:orig_category":"Juweliers",
    "sg:phone":"+31 77 352 4798",
    "sg:postcode":"5911 HD",
    "sg:province":"Limburg",
    "wof:name":"D & D Juweliers",
    "wof:placetype":"venue"
},
  "geometry": {"coordinates":[6.168542,51.370461],"type":"Point"}
}