{
  "type": "Feature",
  "properties": {
    "addr:full":"Bobinestr 7-15 Veenendaal Utrecht 3903 KE",
    "addr:housenumber":"7-15",
    "addr:postcode":"3903 ke",
    "iso:country":"NL",
    "sg:address":"Bobinestr 7-15",
    "sg:city":"Veenendaal",
    "sg:orig_category":"Fotografie Reclame En Mode",
    "sg:phone":"+31 318 438 880",
    "sg:postcode":"3903 KE",
    "sg:province":"Utrecht",
    "sg:website":"http://www.virro.nl",
    "wof:name":"Virro",
    "wof:placetype":"venue"
},
  "geometry": {"coordinates":[5.576474,52.003845],"type":"Point"}
}