{
  "type": "Feature",
  "properties": {
    "addr:full":"Nijverheidsstraat 91 Wildervank Groningen 9648 JE",
    "addr:housenumber":"91",
    "addr:postcode":"9648 je",
    "addr:street":"Nijverheidsstraat",
    "iso:country":"NL",
    "sg:address":"Nijverheidsstraat 91",
    "sg:city":"Wildervank",
    "sg:orig_category":"Organisaties And Verenigingen",
    "sg:phone":"+31 598 618 023",
    "sg:postcode":"9648 JE",
    "sg:province":"Groningen",
    "wof:name":"Dierenbescherming",
    "wof:placetype":"venue"
},
  "geometry": {"coordinates":[6.8670191765,53.086391449],"type":"Point"}
}