{
  "type": "Feature",
  "properties": {
    "iso:country":"NL",
    "sg:address":"Spiegelstraat 13",
    "sg:city":"Zutphen",
    "sg:orig_category":"Bibliotheken And Openbare Archieven",
    "sg:phone":"+31 575 512 157",
    "sg:postcode":"7201 KA",
    "sg:province":"Gelderland",
    "wof:name":"Stadsarchief",
    "wof:placetype":"venue"
},
  "geometry": {"coordinates":[6.193958,52.142246],"type":"Point"}
}