{
  "type": "Feature",
  "properties": {
    "addr:full":"J Evertsenstr 22 Landgraaf Limburg 6372 XB",
    "addr:housenumber":"22",
    "addr:postcode":"6372 xb",
    "iso:country":"NL",
    "sg:address":"J Evertsenstr 22",
    "sg:city":"Landgraaf",
    "sg:classifiers":[
        {
            "category":"Personal",
            "subcategory":"Nail Salon",
            "type":"Services"
        }
    ],
    "sg:phone":"+31 45 541 8001",
    "sg:postcode":"6372 XB",
    "sg:province":"Limburg",
    "sg:tags":[
        "pedicure"
    ],
    "wof:name":"Baurmann-Odekerken, M J",
    "wof:placetype":"venue"
},
  "geometry": {"coordinates":[6.014977,50.876492],"type":"Point"}
}