{
  "type": "Feature",
  "properties": {
    "addr:full":"Hollestelleweg 9 Ovezande Zeeland 4441 TS",
    "addr:housenumber":"9",
    "addr:postcode":"4441 ts",
    "addr:street":"Hollestelleweg",
    "iso:country":"NL",
    "sg:address":"Hollestelleweg 9",
    "sg:city":"Ovezande",
    "sg:orig_category":"Metaalwerken",
    "sg:phone":"+31 113 352 407",
    "sg:postcode":"4441 TS",
    "sg:province":"Zeeland",
    "wof:name":"Besto-Sol Zonweringen En Afsluitingen Bv",
    "wof:placetype":"venue"
},
  "geometry": {"coordinates":[3.773758,51.436466],"type":"Point"}
}