{
  "type": "Feature",
  "properties": {
    "iso:country":"NL",
    "sg:address":"Marktstr 25",
    "sg:city":"Zevenaar",
    "sg:orig_category":"Huishoudelijke Apparaten En Artikelen",
    "sg:phone":"+31 316 343 052",
    "sg:postcode":"6901 AK",
    "sg:province":"Gelderland",
    "wof:name":"Blokker Bv",
    "wof:placetype":"venue"
},
  "geometry": {"coordinates":[6.076346,51.927361],"type":"Point"}
}