{
  "type": "Feature",
  "properties": {
    "iso:country":"NL",
    "sg:address":"Rochussenstraat 15",
    "sg:city":"Rotterdam",
    "sg:orig_category":"Architecten",
    "sg:phone":"+31 10 436 1600",
    "sg:postcode":"3015 EA",
    "sg:province":"Zuid-Holland",
    "wof:name":"Stimuleringsfonds Voor Architectuur",
    "wof:placetype":"venue"
},
  "geometry": {"coordinates":[4.471964,51.915985],"type":"Point"}
}