{
  "type": "Feature",
  "properties": {
    "addr:full":"Postbus 4010 Arnhem Gelderland 6803 EA",
    "addr:housenumber":"4010",
    "addr:postcode":"6803 ea",
    "addr:street":"Postbus",
    "iso:country":"NL",
    "sg:address":"Postbus 4010",
    "sg:city":"Arnhem",
    "sg:orig_category":"Glazenwasserijen",
    "sg:phone":"+31 6 54675777",
    "sg:postcode":"6803 EA",
    "sg:province":"Gelderland",
    "wof:name":"M & M",
    "wof:placetype":"venue"
},
  "geometry": {"coordinates":[5.9124,51.979729],"type":"Point"}
}