{
  "type": "Feature",
  "properties": {
    "addr:full":"Strikkd 23 Pynacker Zuid-Holland 2641 PV",
    "addr:housenumber":"23",
    "addr:postcode":"2641 pv",
    "addr:street":"Strikkd",
    "iso:country":"NL",
    "sg:address":"Strikkd 23",
    "sg:city":"Pynacker",
    "sg:orig_category":"Loonbedrijven",
    "sg:phone":"+31 6 15634803",
    "sg:postcode":"2641 PV",
    "sg:province":"Zuid-Holland",
    "wof:name":"Burg, L G Van Der",
    "wof:placetype":"venue"
},
  "geometry": {"coordinates":[4.425071,51.987968],"type":"Point"}
}