{
  "type": "Feature",
  "properties": {
    "addr:full":"Vrolikstr 60H Amsterdam North Holland 1091 VH",
    "addr:postcode":"1091 vh",
    "iso:country":"NL",
    "sg:address":"Vrolikstr 60H",
    "sg:city":"Amsterdam",
    "sg:orig_category":"Kaartverkoop En Reserveringen",
    "sg:phone":"+31 6 47166122",
    "sg:postcode":"1091 VH",
    "sg:province":"North Holland",
    "wof:name":"Lamonsa",
    "wof:placetype":"venue"
},
  "geometry": {"coordinates":[4.9165081978,52.3556060791],"type":"Point"}
}