{
  "type": "Feature",
  "properties": {
    "iso:country":"NL",
    "sg:address":"Heliumwg 13",
    "sg:city":"Amersfoort",
    "sg:orig_category":"Automaterialen En Gereedschappen",
    "sg:phone":"+31 33 461 0044",
    "sg:postcode":"3812 RD",
    "sg:province":"Utrecht",
    "wof:name":"Lasaulec Amersfoort",
    "wof:placetype":"venue"
},
  "geometry": {"coordinates":[5.354629,52.170807],"type":"Point"}
}