{
  "type": "Feature",
  "properties": {
    "addr:full":"Hoofdstr 212 Uithuizermeeden Groningen 9982 AL",
    "addr:housenumber":"212",
    "addr:postcode":"9982 al",
    "iso:country":"NL",
    "sg:address":"Hoofdstr 212",
    "sg:city":"Uithuizermeeden",
    "sg:orig_category":"Kappers",
    "sg:phone":"+31 595 413 809",
    "sg:postcode":"9982 AL",
    "sg:province":"Groningen",
    "wof:name":"Haarboetiek",
    "wof:placetype":"venue"
},
  "geometry": {"coordinates":[6.7278270721,53.4156303406],"type":"Point"}
}