{
  "type": "Feature",
  "properties": {
    "addr:full":"Sloetsweg 374 Hengelo Ov NL.08 7556 HX",
    "addr:housenumber":"374",
    "addr:postcode":"7556 hx",
    "addr:street":"Sloetsweg;Ov",
    "iso:country":"NL",
    "sg:address":"Sloetsweg 374",
    "sg:city":"Hengelo Ov",
    "sg:orig_category":"Autokeuringen",
    "sg:phone":"+31 74 291 0567",
    "sg:postcode":"7556 HX",
    "sg:province":"NL.08",
    "wof:name":"Roelvink'S Autobedrijf",
    "wof:placetype":"venue"
},
  "geometry": {"coordinates":[6.788624,52.277332],"type":"Point"}
}