{
  "type": "Feature",
  "properties": {
    "addr:full":"Kaiserstraat 19 Leiden South Holland 2311 GN",
    "addr:housenumber":"19",
    "addr:postcode":"2311 gn",
    "addr:street":"Kaiserstraat",
    "iso:country":"NL",
    "sg:address":"Kaiserstraat 19",
    "sg:city":"Leiden",
    "sg:classifiers":[
        {
            "category":"Fast Food",
            "type":"Food & Drink"
        }
    ],
    "sg:phone":"+31 71 566 1642",
    "sg:postcode":"2311 GN",
    "sg:province":"South Holland",
    "sg:tags":[
        "afhaal",
        "restaurant"
    ],
    "wof:name":"De Nijl",
    "wof:placetype":"venue"
},
  "geometry": {"coordinates":[4.485936,52.155792],"type":"Point"}
}