{
  "type": "Feature",
  "properties": {
    "addr:full":"Molendk 78 Goudswaard South Holland 3267 AM",
    "addr:housenumber":"78",
    "addr:postcode":"3267",
    "addr:street":"Molendk",
    "iso:country":"NL",
    "sg:address":"Molendk 78",
    "sg:city":"Goudswaard",
    "sg:orig_category":"Kunsthandel",
    "sg:phone":"+31 186 691 392",
    "sg:postcode":"3267 AM",
    "sg:province":"South Holland",
    "wof:name":"Oude Gemeentehuis, Het",
    "wof:placetype":"venue"
},
  "geometry": {"coordinates":[4.277755,51.795441],"type":"Point"}
}