{
  "type": "Feature",
  "properties": {
    "addr:full":"Burg V Royenstr 139 Hoogezand Groningen 9602 CD",
    "addr:housenumber":"139",
    "addr:postcode":"9602 cd",
    "addr:street":"Burg V Royenstr",
    "iso:country":"NL",
    "sg:address":"Burg V Royenstr 139",
    "sg:city":"Hoogezand",
    "sg:orig_category":"Elektrotechnische Installatiebureaus",
    "sg:phone":"+31 598 351 201",
    "sg:postcode":"9602 CD",
    "sg:province":"Groningen",
    "wof:name":"Mulder Bv",
    "wof:placetype":"venue"
},
  "geometry": {"coordinates":[6.754265,53.15551],"type":"Point"}
}