{
  "type": "Feature",
  "properties": {
    "addr:full":"Kalverstraat 1 Goirle North Brabant 5051 NK",
    "addr:housenumber":"1",
    "addr:postcode":"5051 nk",
    "addr:street":"Kalverstraat",
    "iso:country":"NL",
    "sg:address":"Kalverstraat 1",
    "sg:city":"Goirle",
    "sg:orig_category":"Verzekeringen",
    "sg:phone":"+31 13 534 9114",
    "sg:postcode":"5051 NK",
    "sg:province":"North Brabant",
    "wof:name":"Van Huijgevoort En Vaes Verzekeringen",
    "wof:placetype":"venue"
},
  "geometry": {"coordinates":[5.067362,51.521114],"type":"Point"}
}