{
  "type": "Feature",
  "properties": {
    "addr:full":"Zevenkampse Ring 205 Rotterdam South Holland 3068 PZ",
    "addr:housenumber":"205",
    "addr:postcode":"3068 pz",
    "addr:street":"Zevenkampse Ring",
    "iso:country":"NL",
    "sg:address":"Zevenkampse Ring 205",
    "sg:city":"Rotterdam",
    "sg:orig_category":"Kantoor- En Secretariaatsservice",
    "sg:phone":"+31 10 421 5479",
    "sg:postcode":"3068 PZ",
    "sg:province":"South Holland",
    "sg:website":"http://www.evas-specials.nl",
    "wof:name":"Eva'S Specials",
    "wof:placetype":"venue"
},
  "geometry": {"coordinates":[4.5763978958,51.9662361145],"type":"Point"}
}