{
  "type": "Feature",
  "properties": {
    "addr:full":"Waterweg 54 Nunspeet Gelderland 8071 RT",
    "addr:housenumber":"54",
    "addr:postcode":"8071 rt",
    "addr:street":"Waterweg;Gelderland",
    "iso:country":"NL",
    "sg:address":"Waterweg 54",
    "sg:city":"Nunspeet",
    "sg:orig_category":"Bloemen And Planten",
    "sg:phone":"+31 341 254 988",
    "sg:postcode":"8071 RT",
    "sg:province":"Gelderland",
    "wof:name":"Groenrijk Nunspeet",
    "wof:placetype":"venue"
},
  "geometry": {"coordinates":[5.772205,52.374981],"type":"Point"}
}