{
  "type": "Feature",
  "properties": {
    "addr:full":"Buijs Ballotstraat 40 'S Gravenhage Zuid-Holland 2563 ZL",
    "addr:housenumber":"40",
    "addr:postcode":"2563 zl",
    "addr:street":"Buijs Ballotstraat;' S",
    "iso:country":"NL",
    "sg:address":"Buijs Ballotstraat 40",
    "sg:city":"'S Gravenhage",
    "sg:orig_category":"Technische Studies And Onderzoek",
    "sg:phone":"+31 70 310 6316",
    "sg:postcode":"2563 ZL",
    "sg:province":"Zuid-Holland",
    "wof:name":"Love Your Lijf On Site",
    "wof:placetype":"venue"
},
  "geometry": {"coordinates":[4.274902,52.077091],"type":"Point"}
}