{
  "type": "Feature",
  "properties": {
    "addr:full":"Borodinln 58B Schiedam Zuid-Holland 3122 HB",
    "addr:housenumber":"58b",
    "addr:postcode":"3122 hb",
    "addr:street":"Borodinln",
    "iso:country":"NL",
    "sg:address":"Borodinln 58B",
    "sg:city":"Schiedam",
    "sg:orig_category":"Bloemen En Planten",
    "sg:phone":"+31 6 18556355",
    "sg:postcode":"3122 HB",
    "sg:province":"Zuid-Holland",
    "wof:name":"Fleurrens",
    "wof:placetype":"venue"
},
  "geometry": {"coordinates":[4.367869,51.933411],"type":"Point"}
}