{
  "type": "Feature",
  "properties": {
    "addr:full":"S Gravelandseweg 6 Hilversum Noord-Holland 1211 BR",
    "addr:housenumber":"6",
    "addr:postcode":"1211 br",
    "iso:country":"NL",
    "sg:address":"S Gravelandseweg 6",
    "sg:city":"Hilversum",
    "sg:orig_category":"Chemische Producten Gh",
    "sg:phone":"+31 35 624 7625",
    "sg:postcode":"1211 BR",
    "sg:province":"Noord-Holland",
    "wof:name":"Griya Busana Nederland",
    "wof:placetype":"venue"
},
  "geometry": {"coordinates":[5.17193,52.22496],"type":"Point"}
}