{
  "type": "Feature",
  "properties": {
    "addr:full":"W Heukelsln 38 Utrecht Utrecht 3581 ST",
    "addr:housenumber":"38",
    "addr:postcode":"3581 st",
    "addr:street":"W",
    "iso:country":"NL",
    "sg:address":"W Heukelsln 38",
    "sg:city":"Utrecht",
    "sg:orig_category":"Werving En Selectie",
    "sg:phone":"+31 30 251 4831",
    "sg:postcode":"3581 ST",
    "sg:province":"Utrecht",
    "sg:website":"http://www.totalcompanysupport.nl",
    "wof:name":"Total Company Support Bv",
    "wof:placetype":"venue"
},
  "geometry": {"coordinates":[5.134469986,52.0899887085],"type":"Point"}
}