{
  "type": "Feature",
  "properties": {
    "addr:full":"Maaspoort 13 Weert Limburg 6001 BN",
    "addr:housenumber":"13",
    "addr:postcode":"6001 bn",
    "addr:street":"Maaspoort",
    "iso:country":"NL",
    "sg:address":"Maaspoort 13",
    "sg:city":"Weert",
    "sg:orig_category":"Meubelzaken, Woning- And Keukeninrichting",
    "sg:phone":"+31 495 524 985",
    "sg:postcode":"6001 BN",
    "sg:province":"Limburg",
    "wof:name":"Busch Meubelen",
    "wof:placetype":"venue"
},
  "geometry": {"coordinates":[5.710869,51.25198],"type":"Point"}
}