{
  "type": "Feature",
  "properties": {
    "addr:full":"Mauvestr 42 Arnhem Gelderland 6813 JM",
    "addr:housenumber":"42",
    "addr:postcode":"6813 jm",
    "addr:street":"Mauvestr",
    "iso:country":"NL",
    "sg:address":"Mauvestr 42",
    "sg:city":"Arnhem",
    "sg:orig_category":"Binnenhuisarchitectuur",
    "sg:phone":"+31 26 445 1182",
    "sg:postcode":"6813 JM",
    "sg:province":"Gelderland",
    "wof:name":"Ingen, Loek Van",
    "wof:placetype":"venue"
},
  "geometry": {"coordinates":[5.882073,51.997688],"type":"Point"}
}