{
  "type": "Feature",
  "properties": {
    "addr:full":"Oldenzaalsestr 7 Denekamp NL.08 7591 GK",
    "addr:housenumber":"7;nl.08",
    "addr:postcode":"7591 gk",
    "addr:street":"Oldenzaalsestr",
    "iso:country":"NL",
    "sg:address":"Oldenzaalsestr 7",
    "sg:city":"Denekamp",
    "sg:orig_category":"Boeken En Tijdschriften",
    "sg:phone":"+31 541 351 273",
    "sg:postcode":"7591 GK",
    "sg:province":"NL.08",
    "wof:name":"Brummelhuis, L J",
    "wof:placetype":"venue"
},
  "geometry": {"coordinates":[7.00432,52.37392],"type":"Point"}
}