{
  "type": "Feature",
  "properties": {
    "addr:full":"Kastanjestr 4 Veghel Noord-Brabant 5461 CJ",
    "addr:housenumber":"4",
    "addr:postcode":"5461 cj",
    "addr:street":"Kastanjestr",
    "iso:country":"NL",
    "sg:address":"Kastanjestr 4",
    "sg:city":"Veghel",
    "sg:orig_category":"Elektrotechnische Installatiebureaus",
    "sg:phone":"+31 413 367 367",
    "sg:postcode":"5461 CJ",
    "sg:province":"Noord-Brabant",
    "wof:name":"Brand, Jan V/D",
    "wof:placetype":"venue"
},
  "geometry": {"coordinates":[5.546452,51.624664],"type":"Point"}
}