{
  "type": "Feature",
  "properties": {
    "iso:country":"NL",
    "sg:address":"Standerdmolen 75",
    "sg:city":"Amsterdam",
    "sg:orig_category":"Etaleurs And Showroominrichters",
    "sg:phone":"+31 20 631 1851",
    "sg:postcode":"1035 ED",
    "sg:province":"North Holland",
    "wof:name":"J. De Winter",
    "wof:placetype":"venue"
},
  "geometry": {"coordinates":[4.890215,52.416759],"type":"Point"}
}