{
  "type": "Feature",
  "properties": {
    "addr:full":"St Barbarawg 62 Budel Dorplein Noord-Brabant 6024 AT",
    "addr:housenumber":"62",
    "addr:postcode":"6024",
    "iso:country":"NL",
    "sg:address":"St Barbarawg 62",
    "sg:city":"Budel Dorplein",
    "sg:orig_category":"Motoren - Onderdelen",
    "sg:phone":"+31 6 22443638",
    "sg:postcode":"6024 AT",
    "sg:province":"Noord-Brabant",
    "wof:name":"Motorcross Service Budel",
    "wof:placetype":"venue"
},
  "geometry": {"coordinates":[5.571554,51.237476],"type":"Point"}
}