{
  "type": "Feature",
  "properties": {
    "iso:country":"NL",
    "sg:address":"Orleansstr 45A",
    "sg:city":"Maastricht",
    "sg:orig_category":"Kamerverhuur En -Bemiddeling",
    "sg:phone":"+31 43 347 1759",
    "sg:postcode":"6217 LD",
    "sg:province":"Limburg",
    "wof:name":"Blom",
    "wof:placetype":"venue"
},
  "geometry": {"coordinates":[5.6729598045,50.8513221741],"type":"Point"}
}