{
  "type": "Feature",
  "properties": {
    "addr:full":"Ameidepark 8 Helmond North Brabant 5701 ZZ",
    "addr:housenumber":"8",
    "addr:postcode":"5701 zz",
    "addr:street":"Ameidepark",
    "iso:country":"NL",
    "sg:address":"Ameidepark 8",
    "sg:city":"Helmond",
    "sg:orig_category":"Bejaarden - Verzorgingstehuizen",
    "sg:phone":"+31 492 589 500",
    "sg:postcode":"5701 ZZ",
    "sg:province":"North Brabant",
    "wof:name":"Ameide, De",
    "wof:placetype":"venue"
},
  "geometry": {"coordinates":[5.659157,51.48103],"type":"Point"}
}