{
  "type": "Feature",
  "properties": {
    "addr:full":"Westerdreef 3A Nieuw Vennep North Holland 2152 CS",
    "addr:housenumber":"3a",
    "addr:postcode":"2152 cs",
    "addr:street":"Westerdreef;Nieuw Vennep North",
    "iso:country":"NL",
    "sg:address":"Westerdreef 3A",
    "sg:city":"Nieuw Vennep",
    "sg:orig_category":"Huishoudapparatuur, Televisies And Radio'S",
    "sg:phone":"+31 252 674 584",
    "sg:postcode":"2152 CS",
    "sg:province":"North Holland",
    "wof:name":"Bruiningscentrum Nieuw-Vennep",
    "wof:placetype":"venue"
},
  "geometry": {"coordinates":[4.629751,52.271259],"type":"Point"}
}