{
  "type": "Feature",
  "properties": {
    "addr:full":"J Verhulstln 40 Heemstede Noord-Holland 2102 XT",
    "addr:housenumber":"40",
    "addr:postcode":"2102 xt",
    "iso:country":"NL",
    "sg:address":"J Verhulstln 40",
    "sg:city":"Heemstede",
    "sg:orig_category":"Kinderactiviteiten",
    "sg:phone":"+31 23 547 5885",
    "sg:postcode":"2102 XT",
    "sg:province":"Noord-Holland",
    "sg:website":"http://www.lilaluna.nl",
    "wof:name":"Lilaluna",
    "wof:placetype":"venue"
},
  "geometry": {"coordinates":[4.621248,52.345287],"type":"Point"}
}