{
  "type": "Feature",
  "properties": {
    "addr:full":"Wilgendreef 10 Heeswyk Dinther North Brabant 5473 SM",
    "addr:housenumber":"10",
    "addr:postcode":"5473 sm",
    "addr:street":"Wilgendreef",
    "iso:country":"NL",
    "sg:address":"Wilgendreef 10",
    "sg:city":"Heeswyk Dinther",
    "sg:orig_category":"Webdesign Bureaus",
    "sg:phone":"+31 413 296 321",
    "sg:postcode":"5473 SM",
    "sg:province":"North Brabant",
    "wof:name":"Jece",
    "wof:placetype":"venue"
},
  "geometry": {"coordinates":[5.4823389053,51.652923584],"type":"Point"}
}