{
  "type": "Feature",
  "properties": {
    "addr:full":"Industriewg 32 Noordhorn Groningen 9804 TG",
    "addr:housenumber":"32",
    "addr:postcode":"9804 tg",
    "addr:street":"Industriewg",
    "iso:country":"NL",
    "sg:address":"Industriewg 32",
    "sg:city":"Noordhorn",
    "sg:orig_category":"Onderhoudswerken",
    "sg:phone":"+31 594 503 010",
    "sg:postcode":"9804 TG",
    "sg:province":"Groningen",
    "wof:name":"Kooi Bv, B J",
    "wof:placetype":"venue"
},
  "geometry": {"coordinates":[6.395717,53.256977],"type":"Point"}
}