{
  "type": "Feature",
  "properties": {
    "addr:full":"Passewaays Hogewg 6 Tiel Gelderland 4007 PJ",
    "addr:housenumber":"6",
    "addr:postcode":"4007 pj",
    "addr:street":"Hogewg;Gelderland",
    "iso:country":"NL",
    "sg:address":"Passewaays Hogewg 6",
    "sg:city":"Tiel",
    "sg:classifiers":[
        {
            "category":"Food & Beverages",
            "subcategory":"Fruits & Vegetables",
            "type":"Retail Goods"
        }
    ],
    "sg:phone":"+31 344 612 238",
    "sg:postcode":"4007 PJ",
    "sg:province":"Gelderland",
    "sg:tags":[
        "en",
        "groenten"
    ],
    "wof:name":"Koopmans, J",
    "wof:placetype":"venue"
},
  "geometry": {"coordinates":[5.430696,51.888096],"type":"Point"}
}