{
  "type": "Feature",
  "properties": {
    "addr:full":"Binnenweg 155 Heemstede Noord-Holland 2101 JH",
    "addr:housenumber":"155",
    "addr:postcode":"2101 jh",
    "addr:street":"Binnenweg",
    "iso:country":"NL",
    "sg:address":"Binnenweg 155",
    "sg:city":"Heemstede",
    "sg:orig_category":"Discountwinkels",
    "sg:phone":"+31 23 547 0620",
    "sg:postcode":"2101 JH",
    "sg:province":"Noord-Holland",
    "wof:name":"Zeeman Textielsupers",
    "wof:placetype":"venue"
},
  "geometry": {"coordinates":[4.620769,52.355431],"type":"Point"}
}