{
  "type": "Feature",
  "properties": {
    "addr:full":"Weg De Verenigde Naties 1 Utrecht Utrecht 3527 KT",
    "addr:housenumber":"1",
    "addr:postcode":"3527 kt",
    "addr:street":"Weg De Verenigde Naties",
    "iso:country":"NL",
    "sg:address":"Weg De Verenigde Naties 1",
    "sg:city":"Utrecht",
    "sg:orig_category":"Diverse Opleidingen And Onderwijs",
    "sg:phone":"+31 30 297 1520",
    "sg:postcode":"3527 KT",
    "sg:province":"Utrecht",
    "wof:name":"Appoint Opleidingen",
    "wof:placetype":"venue"
},
  "geometry": {"coordinates":[5.097268,52.084846],"type":"Point"}
}