{
  "type": "Feature",
  "properties": {
    "addr:full":"Badorfstr 53 Wyk By Duurstede Utrecht 3962 CC",
    "addr:housenumber":"53",
    "addr:postcode":"duurstede;3962 cc",
    "addr:street":"Badorfstr",
    "iso:country":"NL",
    "sg:address":"Badorfstr 53",
    "sg:city":"Wyk By Duurstede",
    "sg:orig_category":"Verzekeringen - Verzekeringskantoren",
    "sg:phone":"+31 343 571 359",
    "sg:postcode":"3962 CC",
    "sg:province":"Utrecht",
    "wof:name":"Schram-Van Der Velden, W J A",
    "wof:placetype":"venue"
},
  "geometry": {"coordinates":[5.34077,51.977455],"type":"Point"}
}