{
  "type": "Feature",
  "properties": {
    "addr:full":"Johan Willem Frisolaan 15 Breda Noord-Brabant 4835 AA",
    "addr:housenumber":"15",
    "addr:postcode":"4835 aa",
    "addr:street":"Johan Willem Frisolaan",
    "iso:country":"NL",
    "sg:address":"Johan Willem Frisolaan 15",
    "sg:city":"Breda",
    "sg:orig_category":"Advocaten And Juridische Adviseurs",
    "sg:phone":"+31 76 565 7562",
    "sg:postcode":"4835 AA",
    "sg:province":"Noord-Brabant",
    "wof:name":"Advocatenkantoor Gerritsen & Schuurink",
    "wof:placetype":"venue"
},
  "geometry": {"coordinates":[4.77925,51.572079],"type":"Point"}
}