{
  "type": "Feature",
  "properties": {
    "addr:full":"Kethelwg 89 Vlaardingen Zuid-Holland 3135 GD",
    "addr:housenumber":"89",
    "addr:postcode":"3135 gd",
    "addr:street":"Kethelwg",
    "iso:country":"NL",
    "sg:address":"Kethelwg 89",
    "sg:city":"Vlaardingen",
    "sg:orig_category":"Artiesten/Gezelschappen",
    "sg:phone":"+31 10 435 9629",
    "sg:postcode":"3135 GD",
    "sg:province":"Zuid-Holland",
    "sg:website":"http://www.amazingstroopwafels.nl",
    "wof:name":"The Amazing Stroopwafels",
    "wof:placetype":"venue"
},
  "geometry": {"coordinates":[4.354822,51.919476],"type":"Point"}
}