{
  "type": "Feature",
  "properties": {
    "iso:country":"NL",
    "sg:address":"Noordstraat 29",
    "sg:city":"Axel",
    "sg:orig_category":"Kappers",
    "sg:phone":"+31 115 561 586",
    "sg:postcode":"4571 GB",
    "sg:province":"Zeeland",
    "wof:name":"Kapsalons Jaap Van Den Hout",
    "wof:placetype":"venue"
},
  "geometry": {"coordinates":[-2.2321801186,54.3139190674],"type":"Point"}
}