{
  "type": "Feature",
  "properties": {
    "addr:full":"Limaweg 25 Waddinxveen Zuid-Holland 2743 CB",
    "addr:housenumber":"25",
    "addr:postcode":"2743 cb",
    "addr:street":"Limaweg",
    "iso:country":"NL",
    "sg:address":"Limaweg 25",
    "sg:city":"Waddinxveen",
    "sg:orig_category":"Boekenuitgeverijen",
    "sg:phone":"+31 182 641 111",
    "sg:postcode":"2743 CB",
    "sg:province":"Zuid-Holland",
    "wof:name":"Opleidingscentrum Svs",
    "wof:placetype":"venue"
},
  "geometry": {"coordinates":[4.645904,52.038975],"type":"Point"}
}