{
  "type": "Feature",
  "properties": {
    "iso:country":"NL",
    "sg:address":"Zeewindeln 71",
    "sg:city":"S Gravenhage",
    "sg:orig_category":"Vertaalbureaus",
    "sg:phone":"+31 70 323 1878",
    "sg:postcode":"2554 HB",
    "sg:province":"South Holland",
    "wof:name":"Bailey, Jackie",
    "wof:placetype":"venue"
},
  "geometry": {"coordinates":[4.22476,52.067989],"type":"Point"}
}