{
  "type": "Feature",
  "properties": {
    "addr:full":"Vlierenbroek 26 Breda Noord-Brabant 4822 XM",
    "addr:housenumber":"26",
    "addr:postcode":"4822 xm",
    "addr:street":"Vlierenbroek",
    "iso:country":"NL",
    "sg:address":"Vlierenbroek 26",
    "sg:city":"Breda",
    "sg:orig_category":"Hulpverlening Sociaal",
    "sg:phone":"+31 76 544 0285",
    "sg:postcode":"4822 XM",
    "sg:province":"Noord-Brabant",
    "wof:name":"Vertizontaal",
    "wof:placetype":"venue"
},
  "geometry": {"coordinates":[4.727718,51.606316],"type":"Point"}
}