{
  "type": "Feature",
  "properties": {
    "iso:country":"NL",
    "sg:address":"Nieuwstr 4",
    "sg:city":"Roosendaal",
    "sg:orig_category":"Verenigingen En Stichtingen",
    "sg:phone":"+31 165 555 520",
    "sg:postcode":"4701 HS",
    "sg:province":"North Brabant",
    "wof:name":"Slachtofferhulp Midden- En West-Brabant",
    "wof:placetype":"venue"
},
  "geometry": {"coordinates":[4.458844,51.532925],"type":"Point"}
}