{
  "type": "Feature",
  "properties": {
    "iso:country":"NL",
    "sg:address":"Cereskade 39",
    "sg:city":"Stadskanaal",
    "sg:orig_category":"Geluidsopnamen",
    "sg:phone":"+31 599 653 211",
    "sg:postcode":"9503 GC",
    "sg:province":"Groningen",
    "wof:name":"Eurodisc",
    "wof:placetype":"venue"
},
  "geometry": {"coordinates":[6.971186,52.96814],"type":"Point"}
}