{
  "type": "Feature",
  "properties": {
    "addr:full":"V Ruisdaelstr 3 Ommen Overijssel 7731 SW",
    "addr:housenumber":"3;7731",
    "addr:street":"Ruisdaelstr;Sw",
    "iso:country":"NL",
    "sg:address":"V Ruisdaelstr 3",
    "sg:city":"Ommen",
    "sg:orig_category":"Wasmiddelen - Fabrieken En Groothandel",
    "sg:phone":"+31 529 451 435",
    "sg:postcode":"7731 SW",
    "sg:province":"Overijssel",
    "wof:name":"Dutch Detergents International Bv",
    "wof:placetype":"venue"
},
  "geometry": {"coordinates":[6.4229698181,52.5177536011],"type":"Point"}
}