{
  "type": "Feature",
  "properties": {
    "addr:full":"Voornesewg 8 Heerewaarden Gelderland 6624 KR",
    "addr:housenumber":"8",
    "addr:postcode":"6624 kr",
    "addr:street":"Voornesewg;Gelderland",
    "iso:country":"NL",
    "sg:address":"Voornesewg 8",
    "sg:city":"Heerewaarden",
    "sg:orig_category":"Grondwerken",
    "sg:phone":"+31 487 572 127",
    "sg:postcode":"6624 KR",
    "sg:province":"Gelderland",
    "wof:name":"Groot Bv, De",
    "wof:placetype":"venue"
},
  "geometry": {"coordinates":[5.4072,51.830349],"type":"Point"}
}