{
  "type": "Feature",
  "properties": {
    "addr:full":"J. Geesinkweg 801 Amsterdam Noord-Holland 1096 AZ",
    "addr:housenumber":"801",
    "addr:postcode":"1096 az",
    "addr:street":"J. Geesinkweg",
    "iso:country":"NL",
    "sg:address":"J. Geesinkweg 801",
    "sg:city":"Amsterdam",
    "sg:orig_category":"Verzekeringen",
    "sg:phone":"+31 20 600 5440",
    "sg:postcode":"1096 AZ",
    "sg:province":"Noord-Holland",
    "wof:name":"Cooperatie Omnicare Reishulp Ua",
    "wof:placetype":"venue"
},
  "geometry": {"coordinates":[4.933273,52.335217],"type":"Point"}
}