{
  "type": "Feature",
  "properties": {
    "addr:full":"Floris Voslaan 2 Naarden North Holland 1411 KB",
    "addr:housenumber":"2",
    "addr:postcode":"1411 kb",
    "addr:street":"Floris Voslaan",
    "iso:country":"NL",
    "sg:address":"Floris Voslaan 2",
    "sg:city":"Naarden",
    "sg:orig_category":"Verzekeringen",
    "sg:phone":"+31 35 694 3329",
    "sg:postcode":"1411 KB",
    "sg:province":"North Holland",
    "wof:name":"B.H. Van Beem Assurantien",
    "wof:placetype":"venue"
},
  "geometry": {"coordinates":[5.19327,52.285984],"type":"Point"}
}