{
  "type": "Feature",
  "properties": {
    "addr:full":"Weimarstraat 147 'S Gravenhage Zuid-Holland 2562 GV",
    "addr:housenumber":"147 '",
    "addr:postcode":"2562 gv",
    "addr:street":"Weimarstraat",
    "iso:country":"NL",
    "sg:address":"Weimarstraat 147",
    "sg:city":"'S Gravenhage",
    "sg:classifiers":[
        {
            "category":"Bakery",
            "type":"Food & Drink"
        }
    ],
    "sg:phone":"+31 70 346 0241",
    "sg:postcode":"2562 GV",
    "sg:province":"Zuid-Holland",
    "sg:tags":[
        "brood",
        "banket"
    ],
    "wof:name":"Van Der Pluim Roodenrijs Bakker",
    "wof:placetype":"venue"
},
  "geometry": {"coordinates":[4.280606,52.075706],"type":"Point"}
}