{
  "type": "Feature",
  "properties": {
    "addr:full":"Kattenburgergr 11A Amsterdam Noord-Holland 1018 KN",
    "addr:housenumber":"11a",
    "addr:postcode":"1018 kn",
    "addr:street":"Kattenburgergr",
    "iso:country":"NL",
    "sg:address":"Kattenburgergr 11A",
    "sg:city":"Amsterdam",
    "sg:orig_category":"Vertalers",
    "sg:phone":"+31 20 639 2841",
    "sg:postcode":"1018 KN",
    "sg:province":"Noord-Holland",
    "wof:name":"Schaap, Drs T",
    "wof:placetype":"venue"
},
  "geometry": {"coordinates":[4.917069,52.370628],"type":"Point"}
}