{
  "type": "Feature",
  "properties": {
    "addr:full":"Drift 4 Dwingeloo Drenthe 7991 AA",
    "addr:housenumber":"4",
    "addr:postcode":"7991 aa",
    "addr:street":"Drift",
    "iso:country":"NL",
    "sg:address":"Drift 4",
    "sg:city":"Dwingeloo",
    "sg:classifiers":[
        {
            "category":"Travel",
            "subcategory":"Hotels & Motels",
            "type":"Entertainment"
        }
    ],
    "sg:phone":"+31 521 591 538",
    "sg:postcode":"7991 AA",
    "sg:province":"Drenthe",
    "wof:name":"Drift, De",
    "wof:placetype":"venue"
},
  "geometry": {"coordinates":[6.368068,52.830925],"type":"Point"}
}