{
  "type": "Feature",
  "properties": {
    "addr:full":"Kadoelenweg 221 Amsterdam North Holland 1035 NH",
    "addr:housenumber":"221",
    "addr:postcode":"1035 nh",
    "addr:street":"Kadoelenweg",
    "iso:country":"NL",
    "sg:address":"Kadoelenweg 221",
    "sg:city":"Amsterdam",
    "sg:orig_category":"Wegen And Sportterreinen",
    "sg:phone":"+31 20 631 2758",
    "sg:postcode":"1035 NH",
    "sg:province":"North Holland",
    "wof:name":"Aannemingsbedrijf De Kock Bv",
    "wof:placetype":"venue"
},
  "geometry": {"coordinates":[4.9084181786,52.4116821289],"type":"Point"}
}