{
  "type": "Feature",
  "properties": {
    "iso:country":"NL",
    "sg:address":"Heemstedestr 10",
    "sg:city":"Amsterdam",
    "sg:orig_category":"Hotels: Reservation",
    "sg:phone":"+31 20 408 1600",
    "sg:postcode":"1058 NM",
    "sg:province":"North Holland",
    "sg:website":"http://www.amsterdambusinesshotels.nl",
    "wof:name":"Amsterdam Business Hotel Reservations Bv",
    "wof:placetype":"venue"
},
  "geometry": {"coordinates":[4.848926,52.351727],"type":"Point"}
}