{
  "type": "Feature",
  "properties": {
    "addr:full":"Havenwg 35 Oosterhout Nb Noord-Brabant 4905 AA",
    "addr:housenumber":"35",
    "addr:postcode":"4905 aa",
    "addr:street":"Havenwg",
    "iso:country":"NL",
    "sg:address":"Havenwg 35",
    "sg:city":"Oosterhout Nb",
    "sg:orig_category":"Zoetwaren - Fabrieken En Groothandel",
    "sg:phone":"+31 162 453 361",
    "sg:postcode":"4905 AA",
    "sg:province":"Noord-Brabant",
    "wof:name":"Joosen Bv, Rens",
    "wof:placetype":"venue"
},
  "geometry": {"coordinates":[4.850019,51.65065],"type":"Point"}
}