{
  "type": "Feature",
  "properties": {
    "iso:country":"NL",
    "sg:address":"Uitslagsweg 1",
    "sg:city":"Hengelo Ov",
    "sg:orig_category":"Kantoorartikelen",
    "sg:phone":"+31 74 242 1679",
    "sg:postcode":"7556 LN",
    "sg:province":"NL.08",
    "wof:name":"Kws",
    "wof:placetype":"venue"
},
  "geometry": {"coordinates":[6.7922668457,52.2741928101],"type":"Point"}
}