{
  "type": "Feature",
  "properties": {
    "addr:full":"Malledk 3Lds15 25 Spykenisse Zuid-Holland 3208 LA",
    "addr:housenumber":"25",
    "addr:postcode":"3208 la",
    "iso:country":"NL",
    "sg:address":"Malledk 3Lds15 25",
    "sg:city":"Spykenisse",
    "sg:classifiers":[
        {
            "category":"Retail",
            "subcategory":"Storage",
            "type":"Services"
        }
    ],
    "sg:phone":"+31 181 603 333",
    "sg:postcode":"3208 LA",
    "sg:province":"Zuid-Holland",
    "sg:tags":[
        "op-",
        "en",
        "overslagbedrijven"
    ],
    "sg:website":"http://www.karlrapp.nl",
    "wof:name":"Rapp Bv, Karl",
    "wof:placetype":"venue"
},
  "geometry": {"coordinates":[4.3029,51.84264],"type":"Point"}
}