{
  "type": "Feature",
  "properties": {
    "iso:country":"NL",
    "sg:address":"Schildmos 21",
    "sg:city":"Nieuwerkerk Yssel",
    "sg:orig_category":"Binnenhuisarchitectuur",
    "sg:phone":"+31 180 319 203",
    "sg:postcode":"2914 XD",
    "sg:province":"South Holland",
    "wof:name":"Waterman",
    "wof:placetype":"venue"
},
  "geometry": {"coordinates":[4.612757,51.970577],"type":"Point"}
}