{
  "type": "Feature",
  "properties": {
    "iso:country":"NL",
    "sg:address":"Bakkeveensterweg 11",
    "sg:city":"Waskemeer",
    "sg:classifiers":[
        {
            "category":"Education",
            "subcategory":"Preschool",
            "type":"Public Place"
        }
    ],
    "sg:phone":"+31 516 421 002",
    "sg:postcode":"8434 NP",
    "sg:province":"Friesland",
    "sg:tags":[
        "kleuteronderwijs",
        "basis-"
    ],
    "wof:name":"Openbare Basisschool Meester Van Hasselt",
    "wof:placetype":"venue"
},
  "geometry": {"coordinates":[6.281497,53.058826],"type":"Point"}
}