{
  "type": "Feature",
  "properties": {
    "iso:country":"NL",
    "sg:address":"Toldk 1",
    "sg:city":"Laren Gld",
    "sg:orig_category":"Grondwerken",
    "sg:phone":"+31 573 401 518",
    "sg:postcode":"7245 RG",
    "sg:province":"Gelderland",
    "wof:name":"Klein Velderman Vof",
    "wof:placetype":"venue"
},
  "geometry": {"coordinates":[6.364344,52.219326],"type":"Point"}
}