{
  "type": "Feature",
  "properties": {
    "addr:full":"Toermalyndreef 66 Emmen Drenthe 7828 AS",
    "addr:housenumber":"66",
    "addr:postcode":"7828 as",
    "addr:street":"Toermalyndreef",
    "iso:country":"NL",
    "sg:address":"Toermalyndreef 66",
    "sg:city":"Emmen",
    "sg:orig_category":"Adviesbureaus Werktuigbouwkunde",
    "sg:phone":"+31 591 621 461",
    "sg:postcode":"7828 AS",
    "sg:province":"Drenthe",
    "wof:name":"Gemar Techn Adv & Bem",
    "wof:placetype":"venue"
},
  "geometry": {"coordinates":[6.91047,52.736309],"type":"Point"}
}