{
  "type": "Feature",
  "properties": {
    "iso:country":"NL",
    "sg:address":"Witte Singel 10",
    "sg:city":"Roelofarendsveen",
    "sg:classifiers":[
        {
            "category":"Fast Food",
            "type":"Food & Drink"
        }
    ],
    "sg:phone":"+31 71 331 6673",
    "sg:postcode":"2371 CB",
    "sg:province":"Zuid-Holland",
    "sg:tags":[
        "afhaal",
        "restaurant"
    ],
    "wof:name":"P. Heemskerk",
    "wof:placetype":"venue"
},
  "geometry": {"coordinates":[4.628754,52.192387],"type":"Point"}
}