{
  "type": "Feature",
  "properties": {
    "addr:full":"Postbus 9600 Arnhem Gelderland 6800 TC",
    "addr:housenumber":"9600",
    "addr:postcode":"6800 tc",
    "addr:street":"Postbus",
    "iso:country":"NL",
    "sg:address":"Postbus 9600",
    "sg:city":"Arnhem",
    "sg:orig_category":"Bedrijfsopleidingen",
    "sg:phone":"+31 26 366 5240",
    "sg:postcode":"6800 TC",
    "sg:province":"Gelderland",
    "wof:name":"Okw",
    "wof:placetype":"venue"
},
  "geometry": {"coordinates":[5.9124,51.979729],"type":"Point"}
}