{
  "type": "Feature",
  "properties": {
    "addr:full":"Industriestr 10 A Naaldwyk Zuid-Holland 2671 CT",
    "addr:housenumber":"10 a",
    "addr:postcode":"2671 ct",
    "addr:street":"Industriestr",
    "iso:country":"NL",
    "sg:address":"Industriestr 10 A",
    "sg:city":"Naaldwyk",
    "sg:orig_category":"Loodgieters",
    "sg:phone":"+31 174 648 435",
    "sg:postcode":"2671 CT",
    "sg:province":"Zuid-Holland",
    "sg:website":"http://www.huppelschoten.com",
    "wof:name":"Huppelschoten Bv",
    "wof:placetype":"venue"
},
  "geometry": {"coordinates":[4.212662,51.99984],"type":"Point"}
}