{
  "type": "Feature",
  "properties": {
    "addr:full":"Brugfortstraat 2 Heijen Limburg 6598 ME",
    "addr:housenumber":"2",
    "addr:postcode":"6598 me",
    "addr:street":"Brugfortstraat",
    "iso:country":"NL",
    "sg:address":"Brugfortstraat 2",
    "sg:city":"Heijen",
    "sg:orig_category":"Huishoudapparatuur, Televisies And Radio'S",
    "sg:phone":"+31 485 531 356",
    "sg:postcode":"6598 ME",
    "sg:province":"Limburg",
    "wof:name":"Radio Goossens",
    "wof:placetype":"venue"
},
  "geometry": {"coordinates":[6.022578,51.671356],"type":"Point"}
}