{
  "type": "Feature",
  "properties": {
    "addr:full":"Voorstreek 52 Leeuwarden Provincie Friesland 8911 JR",
    "addr:housenumber":"52",
    "addr:postcode":"8911 jr",
    "addr:street":"Voorstreek;Provincie Friesland",
    "iso:country":"NL",
    "sg:address":"Voorstreek 52",
    "sg:city":"Leeuwarden",
    "sg:orig_category":"Elektrotechnische Artikelen",
    "sg:phone":"+31 58 213 8466",
    "sg:postcode":"8911 JR",
    "sg:province":"Provincie Friesland",
    "wof:name":"Tdc",
    "wof:placetype":"venue"
},
  "geometry": {"coordinates":[5.800833,53.2033],"type":"Point"}
}