{
  "type": "Feature",
  "properties": {
    "iso:country":"NL",
    "sg:address":"Sonsbeeksingel 25",
    "sg:city":"Arnhem",
    "sg:orig_category":"Bedrijfs- And Managementsconsultants",
    "sg:phone":"+31 26 445 4636",
    "sg:postcode":"6814 AB",
    "sg:province":"Gelderland",
    "wof:name":"Peelen Consultancy Bv",
    "wof:placetype":"venue"
},
  "geometry": {"coordinates":[5.909458,51.985725],"type":"Point"}
}