{
  "type": "Feature",
  "properties": {
    "addr:full":"Stoeldraaierstraat 70 Groningen Groningen 9712 BX",
    "addr:housenumber":"70",
    "addr:postcode":"9712 bx",
    "addr:street":"Stoeldraaierstraat",
    "iso:country":"NL",
    "sg:address":"Stoeldraaierstraat 70",
    "sg:city":"Groningen",
    "sg:orig_category":"Verlichting And Huishoudartikelen",
    "sg:phone":"+31 50 313 2282",
    "sg:postcode":"9712 BX",
    "sg:province":"Groningen",
    "wof:name":"Gerdez",
    "wof:placetype":"venue"
},
  "geometry": {"coordinates":[6.562992,53.218063],"type":"Point"}
}