{
  "type": "Feature",
  "properties": {
    "addr:full":"Vaartwg 89 Hilversum North Holland 1217 SM",
    "addr:housenumber":"89",
    "addr:postcode":"1217 sm",
    "addr:street":"Vaartwg",
    "iso:country":"NL",
    "sg:address":"Vaartwg 89",
    "sg:city":"Hilversum",
    "sg:orig_category":"Organisatiebureaus",
    "sg:phone":"+31 35 625 6000",
    "sg:postcode":"1217 SM",
    "sg:province":"North Holland",
    "sg:website":"http://www.the-group.nl",
    "wof:name":"Entertainment Group Bv, The",
    "wof:placetype":"venue"
},
  "geometry": {"coordinates":[5.162197113,52.2226638794],"type":"Point"}
}