{
  "type": "Feature",
  "properties": {
    "addr:full":"Penningkruid 80A Venray Limburg 5803 KK",
    "addr:housenumber":"80a",
    "addr:postcode":"5803 kk",
    "addr:street":"Penningkruid",
    "iso:country":"NL",
    "sg:address":"Penningkruid 80A",
    "sg:city":"Venray",
    "sg:orig_category":"Kappers",
    "sg:phone":"+31 478 515 073",
    "sg:postcode":"5803 KK",
    "sg:province":"Limburg",
    "wof:name":"Patzio",
    "wof:placetype":"venue"
},
  "geometry": {"coordinates":[5.994771,51.536034],"type":"Point"}
}