{
  "type": "Feature",
  "properties": {
    "iso:country":"NL",
    "sg:address":"Kokmeeuw 12",
    "sg:city":"Weert",
    "sg:orig_category":"Loodgieterswerk, Verwarming And Sanitaire Installaties",
    "sg:phone":"+31 495 543 460",
    "sg:postcode":"6005 KD",
    "sg:province":"Limburg",
    "wof:name":"H. Huyerjans",
    "wof:placetype":"venue"
},
  "geometry": {"coordinates":[5.721482,51.245159],"type":"Point"}
}