{
  "type": "Feature",
  "properties": {
    "addr:full":"Boschstraat 50 Breda Noord-Brabant 4811 GJ",
    "addr:housenumber":"50",
    "addr:postcode":"4811 gj",
    "addr:street":"Boschstraat",
    "iso:country":"NL",
    "sg:address":"Boschstraat 50",
    "sg:city":"Breda",
    "sg:orig_category":"Kledingzaken",
    "sg:phone":"+31 76 521 3384",
    "sg:postcode":"4811 GJ",
    "sg:province":"Noord-Brabant",
    "wof:name":"Revalon Confectie/Lederwaren Industrie",
    "wof:placetype":"venue"
},
  "geometry": {"coordinates":[4.782278,51.590328],"type":"Point"}
}