{
  "type": "Feature",
  "properties": {
    "addr:full":"Palenbergerwg 5 Landgraaf Limburg 6374 LS",
    "addr:housenumber":"5",
    "addr:postcode":"6374 ls",
    "addr:street":"Palenbergerwg",
    "iso:country":"NL",
    "sg:address":"Palenbergerwg 5",
    "sg:city":"Landgraaf",
    "sg:orig_category":"Peuterspeelzalen",
    "sg:phone":"+31 45 532 1835",
    "sg:postcode":"6374 LS",
    "sg:province":"Limburg",
    "wof:name":"Broamelke",
    "wof:placetype":"venue"
},
  "geometry": {"coordinates":[6.088125,50.91713],"type":"Point"}
}