{
  "type": "Feature",
  "properties": {
    "addr:full":"Beekstr 19 Asten Noord-Brabant 5721 PC",
    "addr:housenumber":"19",
    "addr:postcode":"5721 pc",
    "addr:street":"Beekstr",
    "iso:country":"NL",
    "sg:address":"Beekstr 19",
    "sg:city":"Asten",
    "sg:orig_category":"Verhuur",
    "sg:phone":"+31 493 670 518",
    "sg:postcode":"5721 PC",
    "sg:province":"Noord-Brabant",
    "wof:name":"Hoff, Van Der",
    "wof:placetype":"venue"
},
  "geometry": {"coordinates":[5.725514,51.418556],"type":"Point"}
}