{
  "type": "Feature",
  "properties": {
    "addr:full":"Basstr 102 Helmond Noord-Brabant 5702 SK",
    "addr:housenumber":"102",
    "addr:street":"5702",
    "iso:country":"NL",
    "sg:address":"Basstr 102",
    "sg:city":"Helmond",
    "sg:orig_category":"Administratie- En Boekhoudkantoren",
    "sg:phone":"+31 492 541 593",
    "sg:postcode":"5702 SK",
    "sg:province":"Noord-Brabant",
    "wof:name":"Christiaens",
    "wof:placetype":"venue"
},
  "geometry": {"coordinates":[5.659562,51.49662],"type":"Point"}
}