{
  "type": "Feature",
  "properties": {
    "addr:full":"Nieuwe Binnenweg 222 Rotterdam Zuid-Holland 3021 GM",
    "addr:housenumber":"222",
    "addr:postcode":"3021 gm",
    "addr:street":"Nieuwe Binnenweg",
    "iso:country":"NL",
    "sg:address":"Nieuwe Binnenweg 222",
    "sg:city":"Rotterdam",
    "sg:orig_category":"Boekenuitgeverijen",
    "sg:phone":"+31 10 476 1253",
    "sg:postcode":"3021 GM",
    "sg:province":"Zuid-Holland",
    "wof:name":"Europa Boekhandel V/H Van Alphen",
    "wof:placetype":"venue"
},
  "geometry": {"coordinates":[4.461774,51.913338],"type":"Point"}
}