{
  "type": "Feature",
  "properties": {
    "addr:full":"Akoleienstr 8 Amsterdam Noord-Holland 1016 LN",
    "addr:housenumber":"8",
    "addr:postcode":"1016 ln",
    "addr:street":"Akoleienstr",
    "iso:country":"NL",
    "sg:address":"Akoleienstr 8",
    "sg:city":"Amsterdam",
    "sg:orig_category":"Beeldende Kunstenaars",
    "sg:phone":"+31 20 627 5952",
    "sg:postcode":"1016 LN",
    "sg:province":"Noord-Holland",
    "wof:name":"Mandelbaum, G W",
    "wof:placetype":"venue"
},
  "geometry": {"coordinates":[4.878084,52.372971],"type":"Point"}
}