{
  "type": "Feature",
  "properties": {
    "addr:full":"Achterstr 28A Woerden Utrecht 3441 EH",
    "addr:housenumber":"28a",
    "addr:postcode":"3441 eh",
    "addr:street":"Achterstr",
    "iso:country":"NL",
    "sg:address":"Achterstr 28A",
    "sg:city":"Woerden",
    "sg:orig_category":"Product-Promotie",
    "sg:phone":"+31 348 480 597",
    "sg:postcode":"3441 EH",
    "sg:province":"Utrecht",
    "wof:name":"Stateline Productions 89",
    "wof:placetype":"venue"
},
  "geometry": {"coordinates":[4.886967,52.086277],"type":"Point"}
}