{
  "type": "Feature",
  "properties": {
    "addr:full":"Delftechpark 26 Delft Zuid-Holland 2628 XH",
    "addr:housenumber":"26",
    "addr:postcode":"2628 xh",
    "addr:street":"Delftechpark",
    "iso:country":"NL",
    "sg:address":"Delftechpark 26",
    "sg:city":"Delft",
    "sg:orig_category":"Technische Studies And Onderzoek",
    "sg:phone":"+31 10 529 0509",
    "sg:postcode":"2628 XH",
    "sg:province":"Zuid-Holland",
    "wof:name":"Kristech",
    "wof:placetype":"venue"
},
  "geometry": {"coordinates":[4.383871,51.997326],"type":"Point"}
}