{
  "type": "Feature",
  "properties": {
    "addr:full":"Landvoogd 2 Rhoon South Holland 3161 NC",
    "addr:housenumber":"2",
    "addr:postcode":"3161 nc",
    "addr:street":"Landvoogd",
    "iso:country":"NL",
    "sg:address":"Landvoogd 2",
    "sg:city":"Rhoon",
    "sg:orig_category":"Boekhouders",
    "sg:phone":"+31 10 501 5737",
    "sg:postcode":"3161 NC",
    "sg:province":"South Holland",
    "wof:name":"Administratiekantoor Albrandswaard",
    "wof:placetype":"venue"
},
  "geometry": {"coordinates":[4.415492,51.861263],"type":"Point"}
}