{
  "type": "Feature",
  "properties": {
    "iso:country":"NL",
    "sg:address":"Westervalge 18",
    "sg:city":"Warffum",
    "sg:orig_category":"Peuterspeelzalen",
    "sg:phone":"+31 595 425 344",
    "sg:postcode":"9989 EB",
    "sg:province":"Groningen",
    "wof:name":"Hummelh\u00f6rn",
    "wof:placetype":"venue"
},
  "geometry": {"coordinates":[6.553587,53.392193],"type":"Point"}
}