{
  "type": "Feature",
  "properties": {
    "addr:full":"Pylhovestr 33 Enschede NL.08 7521 VS",
    "addr:housenumber":"33",
    "addr:postcode":"7521",
    "addr:street":"Pylhovestr",
    "iso:country":"NL",
    "sg:address":"Pylhovestr 33",
    "sg:city":"Enschede",
    "sg:orig_category":"Machineonderhoud En -Reparatie",
    "sg:phone":"+31 53 432 8905",
    "sg:postcode":"7521 VS",
    "sg:province":"NL.08",
    "wof:name":"Harmen De Jong",
    "wof:placetype":"venue"
},
  "geometry": {"coordinates":[6.86892,52.228996],"type":"Point"}
}