{
  "type": "Feature",
  "properties": {
    "iso:country":"NL",
    "sg:address":"Kloosring 93",
    "sg:city":"Oud Beyerland",
    "sg:orig_category":"Adviesbureaus Bouwkunde",
    "sg:phone":"+31 186 615 853",
    "sg:postcode":"3261 SG",
    "sg:province":"Zuid-Holland",
    "wof:name":"Quaak",
    "wof:placetype":"venue"
},
  "geometry": {"coordinates":[4.430816,51.819073],"type":"Point"}
}