{
  "type": "Feature",
  "properties": {
    "addr:full":"Vyverln 5 Groenekan Utrecht 3737 RE",
    "addr:housenumber":"5",
    "addr:postcode":"3737",
    "addr:street":"Vyverln",
    "iso:country":"NL",
    "sg:address":"Vyverln 5",
    "sg:city":"Groenekan",
    "sg:orig_category":"Adviesbureaus Bouwkunde",
    "sg:phone":"+31 346 212 966",
    "sg:postcode":"3737 RE",
    "sg:province":"Utrecht",
    "wof:name":"Bouwat",
    "wof:placetype":"venue"
},
  "geometry": {"coordinates":[5.15268,52.123119],"type":"Point"}
}