{
  "type": "Feature",
  "properties": {
    "addr:full":"Industrieweg 2 Andijk North Holland 1619 BZ",
    "addr:housenumber":"2",
    "addr:postcode":"1619 bz",
    "addr:street":"Industrieweg",
    "iso:country":"NL",
    "sg:address":"Industrieweg 2",
    "sg:city":"Andijk",
    "sg:orig_category":"Metaalbekleding And -Behandeling",
    "sg:phone":"+31 228 592 309",
    "sg:postcode":"1619 BZ",
    "sg:province":"North Holland",
    "wof:name":"Metaalbewerkingsbedrijf Scherpenzeel Bv",
    "wof:placetype":"venue"
},
  "geometry": {"coordinates":[5.224109,52.741341],"type":"Point"}
}