{
  "type": "Feature",
  "properties": {
    "addr:full":"Glazenierstr 1 Alkmaar Noord-Holland 1825 BR",
    "addr:housenumber":"1",
    "addr:postcode":"1825 br",
    "addr:street":"Glazenierstr",
    "iso:country":"NL",
    "sg:address":"Glazenierstr 1",
    "sg:city":"Alkmaar",
    "sg:orig_category":"Verenigingsgebouwen",
    "sg:phone":"+31 72 562 0970",
    "sg:postcode":"1825 BR",
    "sg:province":"Noord-Holland",
    "wof:name":"Ambacht, 'T",
    "wof:placetype":"venue"
},
  "geometry": {"coordinates":[4.745752,52.651733],"type":"Point"}
}