{
  "type": "Feature",
  "properties": {
    "addr:full":"Oude Oppenhuizerweg 93 Sneek Friesland 8606 JD",
    "addr:housenumber":"93",
    "addr:postcode":"8606 jd",
    "addr:street":"Oude Oppenhuizerweg",
    "iso:country":"NL",
    "sg:address":"Oude Oppenhuizerweg 93",
    "sg:city":"Sneek",
    "sg:orig_category":"Watersport-, Sport- And Kampeerbenodigdheden Verhuur",
    "sg:phone":"+31 515 411 771",
    "sg:postcode":"8606 JD",
    "sg:province":"Friesland",
    "wof:name":"Botenverhuur L. Van Der Pol",
    "wof:placetype":"venue"
},
  "geometry": {"coordinates":[5.6851639748,53.0248413086],"type":"Point"}
}