{
  "type": "Feature",
  "properties": {
    "addr:full":"Schoolstr 2 Bakel Noord-Brabant 5761 BV",
    "addr:housenumber":"2",
    "addr:postcode":"5761 bv",
    "addr:street":"Schoolstr",
    "iso:country":"NL",
    "sg:address":"Schoolstr 2",
    "sg:city":"Bakel",
    "sg:orig_category":"Saunabaden - Import En Groothandel",
    "sg:phone":"+31 492 341 257",
    "sg:postcode":"5761 BV",
    "sg:province":"Noord-Brabant",
    "wof:name":"Bakel Zonnecentrum",
    "wof:placetype":"venue"
},
  "geometry": {"coordinates":[5.739673,51.503326],"type":"Point"}
}