{
  "type": "Feature",
  "properties": {
    "addr:full":"Madepolderwg 49 C S Gravenhage Zuid-Holland 2553 EG",
    "addr:housenumber":"49 c",
    "addr:postcode":"2553 eg",
    "addr:street":"Madepolderwg",
    "iso:country":"NL",
    "sg:address":"Madepolderwg 49 C",
    "sg:city":"S Gravenhage",
    "sg:orig_category":"Oldtimers",
    "sg:phone":"+31 174 212 277",
    "sg:postcode":"2553 EG",
    "sg:province":"Zuid-Holland",
    "sg:website":"http://www.winfredvandijk.nl",
    "wof:name":"Dijk, Winfred Van",
    "wof:placetype":"venue"
},
  "geometry": {"coordinates":[4.21987,52.046589],"type":"Point"}
}