{
  "type": "Feature",
  "properties": {
    "addr:full":"Schaafdries 58 Ravenstein Noord-Brabant 5371 NJ",
    "addr:housenumber":"58",
    "addr:postcode":"5371 nj",
    "addr:street":"Schaafdries",
    "iso:country":"NL",
    "sg:address":"Schaafdries 58",
    "sg:city":"Ravenstein",
    "sg:orig_category":"Adviesbureaus Bedrijfsorganisatie",
    "sg:phone":"+31 486 416 750",
    "sg:postcode":"5371 NJ",
    "sg:province":"Noord-Brabant",
    "wof:name":"Venturi",
    "wof:placetype":"venue"
},
  "geometry": {"coordinates":[5.637877,51.794147],"type":"Point"}
}