{
  "type": "Feature",
  "properties": {
    "addr:full":"Raadhuisstr 49 Koog Aan De Zaan Noord-Holland 1541 JB",
    "addr:housenumber":"49",
    "addr:postcode":"1541 jb",
    "addr:street":"Raadhuisstr",
    "iso:country":"NL",
    "sg:address":"Raadhuisstr 49",
    "sg:city":"Koog Aan De Zaan",
    "sg:orig_category":"Woningstoffeerders",
    "sg:phone":"+31 75 616 3632",
    "sg:postcode":"1541 JB",
    "sg:province":"Noord-Holland",
    "wof:name":"Hoveling, Fa J",
    "wof:placetype":"venue"
},
  "geometry": {"coordinates":[4.8109068871,52.4627304077],"type":"Point"}
}