{
  "type": "Feature",
  "properties": {
    "addr:full":"Da Costakd 97 Amsterdam Noord-Holland 1053 WR",
    "addr:housenumber":"97",
    "addr:postcode":"1053 wr",
    "iso:country":"NL",
    "sg:address":"Da Costakd 97",
    "sg:city":"Amsterdam",
    "sg:orig_category":"Omroep",
    "sg:phone":"+31 20 683 1212",
    "sg:postcode":"1053 WR",
    "sg:province":"Noord-Holland",
    "wof:name":"Parousia",
    "wof:placetype":"venue"
},
  "geometry": {"coordinates":[4.86733,52.366638],"type":"Point"}
}