{
  "type": "Feature",
  "properties": {
    "addr:full":"Oranjelaan 12 Hilversum North Holland 1217 LW",
    "addr:housenumber":"12",
    "addr:postcode":"1217 lw",
    "addr:street":"Oranjelaan",
    "iso:country":"NL",
    "sg:address":"Oranjelaan 12",
    "sg:city":"Hilversum",
    "sg:orig_category":"Marktonderzoekbureaus",
    "sg:phone":"+31 35 623 1947",
    "sg:postcode":"1217 LW",
    "sg:province":"North Holland",
    "wof:name":"Van Eunen Marketing",
    "wof:placetype":"venue"
},
  "geometry": {"coordinates":[5.160984,52.228027],"type":"Point"}
}