{
  "type": "Feature",
  "properties": {
    "iso:country":"NL",
    "sg:address":"Schoondijkseweg 1",
    "sg:city":"Groede",
    "sg:classifiers":[
        {
            "category":"Travel",
            "subcategory":"Hotels & Motels",
            "type":"Entertainment"
        }
    ],
    "sg:phone":"+31 117 371 371",
    "sg:postcode":"4503 GK",
    "sg:province":"Zeeland",
    "wof:name":"Eierkurf D' Bed & Breakfast",
    "wof:placetype":"venue"
},
  "geometry": {"coordinates":[3.510615,51.372688],"type":"Point"}
}