{
  "type": "Feature",
  "properties": {
    "addr:full":"Oud Loosdrechtsedijk 170 Loosdrecht Noord-Holland 1231 NE",
    "addr:housenumber":"170;1231",
    "addr:postcode":"ne",
    "addr:street":"Oud Loosdrechtsedijk",
    "iso:country":"NL",
    "sg:address":"Oud Loosdrechtsedijk 170",
    "sg:city":"Loosdrecht",
    "sg:orig_category":"Boekenuitgeverijen",
    "sg:phone":"+31 35 582 7595",
    "sg:postcode":"1231 NE",
    "sg:province":"Noord-Holland",
    "wof:name":"Harmonia Bv",
    "wof:placetype":"venue"
},
  "geometry": {"coordinates":[5.083813,52.206947],"type":"Point"}
}