{
  "type": "Feature",
  "properties": {
    "addr:full":"Emmerhoutstr 1 Emmen Provincie Drenthe 7814 XV",
    "addr:housenumber":"1;7814",
    "addr:postcode":"xv",
    "addr:street":"Emmerhoutstr;Provincie Drenthe",
    "iso:country":"NL",
    "sg:address":"Emmerhoutstr 1",
    "sg:city":"Emmen",
    "sg:orig_category":"Verenigingsgebouwen",
    "sg:phone":"+31 591 617 450",
    "sg:postcode":"7814 XV",
    "sg:province":"Provincie Drenthe",
    "wof:name":"Weerdinger Dorpshuis",
    "wof:placetype":"venue"
},
  "geometry": {"coordinates":[6.918231,52.817451],"type":"Point"}
}