{
  "type": "Feature",
  "properties": {
    "addr:full":"Vleutensewg 160 Utrecht Utrecht 3532 HN",
    "addr:housenumber":"160",
    "addr:postcode":"3532 hn",
    "iso:country":"NL",
    "sg:address":"Vleutensewg 160",
    "sg:city":"Utrecht",
    "sg:orig_category":"Projectinrichting",
    "sg:phone":"+31 30 296 4689",
    "sg:postcode":"3532 HN",
    "sg:province":"Utrecht",
    "wof:name":"Emek",
    "wof:placetype":"venue"
},
  "geometry": {"coordinates":[5.099307,52.092934],"type":"Point"}
}