{
  "type": "Feature",
  "properties": {
    "addr:full":"Dr Erensstr 46A Valkenburg Lb Limburg 6301 DX",
    "addr:housenumber":"46a",
    "addr:postcode":"lb;6301 dx",
    "iso:country":"NL",
    "sg:address":"Dr Erensstr 46A",
    "sg:city":"Valkenburg Lb",
    "sg:orig_category":"Zonnebank- En Solariumcentra",
    "sg:phone":"+31 43 601 1572",
    "sg:postcode":"6301 DX",
    "sg:province":"Limburg",
    "wof:name":"Playa Sun & Beauty",
    "wof:placetype":"venue"
},
  "geometry": {"coordinates":[5.83344,50.861328],"type":"Point"}
}