{
  "type": "Feature",
  "properties": {
    "iso:country":"NL",
    "sg:address":"M A De Ruijterstraat 30",
    "sg:city":"Haaksbergen",
    "sg:orig_category":"Schilderwerk",
    "sg:phone":"+31 53 572 2223",
    "sg:postcode":"7482 BZ",
    "sg:province":"Overijssel",
    "wof:name":"Schildersbedrijf Jan Te Lintelo",
    "wof:placetype":"venue"
},
  "geometry": {"coordinates":[6.738196,52.160065],"type":"Point"}
}