{
  "type": "Feature",
  "properties": {
    "iso:country":"NL",
    "sg:address":"Westerstr 11",
    "sg:city":"Zandvoort",
    "sg:classifiers":[
        {
            "category":"Banks & Credit Unions",
            "subcategory":"Investment Brokerage",
            "type":"Services"
        }
    ],
    "sg:phone":"+31 23 571 2447",
    "sg:postcode":"2042 HE",
    "sg:province":"North Holland",
    "sg:tags":[
        "pension"
    ],
    "wof:name":"Golfslag",
    "wof:placetype":"venue"
},
  "geometry": {"coordinates":[4.526483,52.371284],"type":"Point"}
}