{
  "type": "Feature",
  "properties": {
    "addr:full":"Saenredamstr 15 Amsterdam Noord-Holland 1072 CA",
    "addr:housenumber":"15",
    "addr:postcode":"1072 ca",
    "addr:street":"Saenredamstr",
    "iso:country":"NL",
    "sg:address":"Saenredamstr 15",
    "sg:city":"Amsterdam",
    "sg:orig_category":"Filmstudio'S En -Productie",
    "sg:phone":"+31 20 470 2277",
    "sg:postcode":"1072 CA",
    "sg:province":"Noord-Holland",
    "wof:name":"Kock, P A De",
    "wof:placetype":"venue"
},
  "geometry": {"coordinates":[-74.18394499999999,42.971195],"type":"Point"}
}