{
  "type": "Feature",
  "properties": {
    "iso:country":"NL",
    "sg:address":"Forum 35",
    "sg:city":"Assen",
    "sg:orig_category":"Damesmodezaken",
    "sg:phone":"+31 591 315 141",
    "sg:postcode":"9401 EE",
    "sg:province":"Drenthe",
    "wof:name":"Boetiek Shape",
    "wof:placetype":"venue"
},
  "geometry": {"coordinates":[6.56114,52.995487],"type":"Point"}
}