{
  "type": "Feature",
  "properties": {
    "iso:country":"NL",
    "sg:address":"Wildemanstg 1",
    "sg:city":"Wyk By Duurstede",
    "sg:orig_category":"Huidtherapeuten",
    "sg:phone":"+31 343 575 056",
    "sg:postcode":"3961 AP",
    "sg:province":"Utrecht",
    "wof:name":"Fentener Van Vlissingen, J M",
    "wof:placetype":"venue"
},
  "geometry": {"coordinates":[5.34814,51.972122],"type":"Point"}
}