{
  "type": "Feature",
  "properties": {
    "iso:country":"NL",
    "sg:address":"Treebord 19",
    "sg:city":"Enkhuizen",
    "sg:orig_category":"Administratie- En Boekhoudkantoren",
    "sg:phone":"+31 228 321 166",
    "sg:postcode":"1602 GT",
    "sg:province":"Noord-Holland",
    "wof:name":"Brielee Int",
    "wof:placetype":"venue"
},
  "geometry": {"coordinates":[5.26488,52.715412],"type":"Point"}
}