{
  "type": "Feature",
  "properties": {
    "addr:full":"Pr Bernhardstr 45 Vianen Zh Utrecht 4132 XE",
    "addr:housenumber":"45",
    "addr:postcode":"zh;4132 xe",
    "iso:country":"NL",
    "sg:address":"Pr Bernhardstr 45",
    "sg:city":"Vianen Zh",
    "sg:orig_category":"Scheepssleep- En Duwvaart",
    "sg:phone":"+31 347 375 712",
    "sg:postcode":"4132 XE",
    "sg:province":"Utrecht",
    "wof:name":"Anco",
    "wof:placetype":"venue"
},
  "geometry": {"coordinates":[5.089005,51.989281],"type":"Point"}
}