{
  "type": "Feature",
  "properties": {
    "iso:country":"NL",
    "sg:address":"Gorterstr 4",
    "sg:city":"Zevenhuizen Zh",
    "sg:orig_category":"Mode-Artikelen Dames En Heren",
    "sg:phone":"+31 180 634 403",
    "sg:postcode":"2761 LL",
    "sg:province":"South Holland",
    "wof:name":"Madden",
    "wof:placetype":"venue"
},
  "geometry": {"coordinates":[4.58329,52.014378],"type":"Point"}
}