{
  "type": "Feature",
  "properties": {
    "addr:full":"Zandhoek 12 Amsterdam North Holland 1013 KT",
    "addr:housenumber":"12",
    "addr:postcode":"1013 kt",
    "addr:street":"Zandhoek",
    "iso:country":"NL",
    "sg:address":"Zandhoek 12",
    "sg:city":"Amsterdam",
    "sg:orig_category":"Architecten",
    "sg:phone":"+31 20 626 1023",
    "sg:postcode":"1013 KT",
    "sg:province":"North Holland",
    "wof:name":"Ir T C Ruimschotel Bv",
    "wof:placetype":"venue"
},
  "geometry": {"coordinates":[4.889845,52.388062],"type":"Point"}
}