{
  "type": "Feature",
  "properties": {
    "addr:full":"A P Fokkerstr 47 Groningen Groningen 9713 JK",
    "addr:housenumber":"47",
    "addr:postcode":"9713 jk",
    "addr:street":"A;Fokkerstr",
    "iso:country":"NL",
    "sg:address":"A P Fokkerstr 47",
    "sg:city":"Groningen",
    "sg:orig_category":"Fotoreportages",
    "sg:phone":"+31 50 311 2540",
    "sg:postcode":"9713 JK",
    "sg:province":"Groningen",
    "sg:website":"http://www.moorlach.nl",
    "wof:name":"Absolut Fotografie",
    "wof:placetype":"venue"
},
  "geometry": {"coordinates":[6.57398,53.227165],"type":"Point"}
}