{
  "type": "Feature",
  "properties": {
    "addr:full":"Groesbeekseweg 134 Nijmegen Gelderland 6524 DM",
    "addr:housenumber":"134",
    "addr:postcode":"6524 dm",
    "addr:street":"Groesbeekseweg;Gelderland",
    "iso:country":"NL",
    "sg:address":"Groesbeekseweg 134",
    "sg:city":"Nijmegen",
    "sg:orig_category":"Artsen And Specialisten",
    "sg:phone":"+31 24 322 0922",
    "sg:postcode":"6524 DM",
    "sg:province":"Gelderland",
    "wof:name":"W. H. Beukelman",
    "wof:placetype":"venue"
},
  "geometry": {"coordinates":[5.867306,51.836872],"type":"Point"}
}