{
  "type": "Feature",
  "properties": {
    "addr:full":"Heistr 123 Helmond Noord-Brabant 5701 HK",
    "addr:housenumber":"123",
    "addr:postcode":"5701 hk",
    "iso:country":"NL",
    "sg:address":"Heistr 123",
    "sg:city":"Helmond",
    "sg:orig_category":"Gordijnenateliers",
    "sg:phone":"+31 492 475 051",
    "sg:postcode":"5701 HK",
    "sg:province":"Noord-Brabant",
    "wof:name":"Zilvernaald Gordijnen",
    "wof:placetype":"venue"
},
  "geometry": {"coordinates":[5.661467,51.483269],"type":"Point"}
}