{
  "type": "Feature",
  "properties": {
    "addr:full":"H De Grootstr 41 Gorinchem Zuid-Holland 4206 ZD",
    "addr:housenumber":"41",
    "addr:postcode":"4206 zd",
    "iso:country":"NL",
    "sg:address":"H De Grootstr 41",
    "sg:city":"Gorinchem",
    "sg:orig_category":"Beveiliging",
    "sg:phone":"+31 183 626 860",
    "sg:postcode":"4206 ZD",
    "sg:province":"Zuid-Holland",
    "wof:name":"Vkbg",
    "wof:placetype":"venue"
},
  "geometry": {"coordinates":[4.978671,51.84016],"type":"Point"}
}