{
  "type": "Feature",
  "properties": {
    "iso:country":"NL",
    "sg:address":"Wederikweg 90",
    "sg:city":"Haren Gn",
    "sg:orig_category":"Binnenhuisarchitecten",
    "sg:phone":"+31 50 535 0555",
    "sg:postcode":"9753 AE",
    "sg:province":"Groningen",
    "wof:name":"Ruurd Voorneveld Architectonische Vormge",
    "wof:placetype":"venue"
},
  "geometry": {"coordinates":[6.619639,53.176212],"type":"Point"}
}