{
  "type": "Feature",
  "properties": {
    "addr:full":"Hoofdstraat 98 Rijen North Brabant 5121 JH",
    "addr:housenumber":"98",
    "addr:postcode":"5121 jh",
    "addr:street":"Hoofdstraat",
    "iso:country":"NL",
    "sg:address":"Hoofdstraat 98",
    "sg:city":"Rijen",
    "sg:orig_category":"Opticiens",
    "sg:phone":"+31 161 222 501",
    "sg:postcode":"5121 JH",
    "sg:province":"North Brabant",
    "wof:name":"Hans Van Rooij Brilmode",
    "wof:placetype":"venue"
},
  "geometry": {"coordinates":[4.9174489975,51.5930480957],"type":"Point"}
}