{
  "type": "Feature",
  "properties": {
    "addr:full":"Rijnstr 66 Enschede NL.08 7523 GH",
    "addr:housenumber":"66",
    "addr:postcode":"7523 gh",
    "addr:street":"Rijnstr",
    "iso:country":"NL",
    "sg:address":"Rijnstr 66",
    "sg:city":"Enschede",
    "sg:orig_category":"Poeliers",
    "sg:phone":"+31 53 433 8099",
    "sg:postcode":"7523 GH",
    "sg:province":"NL.08",
    "wof:name":"Kooi, Edwin Van Der",
    "wof:placetype":"venue"
},
  "geometry": {"coordinates":[6.893797,52.239056],"type":"Point"}
}