{
  "type": "Feature",
  "properties": {
    "iso:country":"NL",
    "sg:address":"V Blankenburgstr 91 En 83",
    "sg:city":"S Gravenhage",
    "sg:classifiers":[
        {
            "category":"Banks & Credit Unions",
            "subcategory":"Investment Brokerage",
            "type":"Services"
        }
    ],
    "sg:phone":"+31 70 363 2033",
    "sg:postcode":"2517 XN",
    "sg:province":"Zuid-Holland",
    "sg:tags":[
        "pension"
    ],
    "wof:name":"Nines",
    "wof:placetype":"venue"
},
  "geometry": {"coordinates":[4.28708,52.08667],"type":"Point"}
}