{
  "type": "Feature",
  "properties": {
    "addr:full":"De Gors 25 Almelo NL.08 7609 DZ",
    "addr:housenumber":"25;nl.08",
    "addr:postcode":"7609 dz",
    "addr:street":"De Gors",
    "iso:country":"NL",
    "sg:address":"De Gors 25",
    "sg:city":"Almelo",
    "sg:orig_category":"Kappers",
    "sg:phone":"+31 546 810 462",
    "sg:postcode":"7609 DZ",
    "sg:province":"NL.08",
    "wof:name":"Eyes On Hairfashion",
    "wof:placetype":"venue"
},
  "geometry": {"coordinates":[6.630452,52.336006],"type":"Point"}
}