{
  "type": "Feature",
  "properties": {
    "iso:country":"NL",
    "sg:address":"Amsterdamsewg 24",
    "sg:city":"Amstelveen",
    "sg:orig_category":"Meubelstoffering",
    "sg:phone":"+31 20 643 9895",
    "sg:postcode":"1182 HD",
    "sg:province":"Noord-Holland",
    "wof:name":"Bouw Meubelstoffeerderij",
    "wof:placetype":"venue"
},
  "geometry": {"coordinates":[4.84681,52.304962],"type":"Point"}
}