{
  "type": "Feature",
  "properties": {
    "iso:country":"NL",
    "sg:address":"Dorpsstr 43",
    "sg:city":"Melick",
    "sg:orig_category":"Sportverenigingen En Ontspannings- Verenigingen",
    "sg:phone":"+31 475 533 955",
    "sg:postcode":"6074 GA",
    "sg:province":"Limburg",
    "wof:name":"Harmonie Condordia",
    "wof:placetype":"venue"
},
  "geometry": {"coordinates":[-83.222931,32.678131],"type":"Point"}
}