{
  "type": "Feature",
  "properties": {
    "addr:full":"Goudsmidshoeve 403 Apeldoorn Gelderland 7326 RD",
    "addr:housenumber":"403",
    "addr:postcode":"7326",
    "addr:street":"Goudsmidshoeve;Gelderland;Rd",
    "iso:country":"NL",
    "sg:address":"Goudsmidshoeve 403",
    "sg:city":"Apeldoorn",
    "sg:orig_category":"Hoger Onderwijs",
    "sg:phone":"+31 55 541 4992",
    "sg:postcode":"7326 RD",
    "sg:province":"Gelderland",
    "wof:name":"Modevakschool 'T Hoevehoekje",
    "wof:placetype":"venue"
},
  "geometry": {"coordinates":[6.015219,52.192722],"type":"Point"}
}