{
  "type": "Feature",
  "properties": {
    "iso:country":"NL",
    "sg:address":"Stationspln 1",
    "sg:city":"Rotterdam",
    "sg:orig_category":"Kousen En Sokken",
    "sg:phone":"+31 10 411 4686",
    "sg:postcode":"3013 AJ",
    "sg:province":"Zuid-Holland",
    "wof:name":"Jambelle",
    "wof:placetype":"venue"
},
  "geometry": {"coordinates":[4.468986,51.924057],"type":"Point"}
}