{
  "type": "Feature",
  "properties": {
    "addr:full":"Dominee Van Meursstraat 33 Wapenveld Gelderland 8191 AM",
    "addr:housenumber":"33",
    "addr:postcode":"8191",
    "addr:street":"Dominee Van Meursstraat;Gelderland",
    "iso:country":"NL",
    "sg:address":"Dominee Van Meursstraat 33",
    "sg:city":"Wapenveld",
    "sg:orig_category":"Autokeuringen",
    "sg:phone":"+31 38 447 0183",
    "sg:postcode":"8191 AM",
    "sg:province":"Gelderland",
    "wof:name":"A. Nikkels En Zn. Vof",
    "wof:placetype":"venue"
},
  "geometry": {"coordinates":[6.075169,52.428543],"type":"Point"}
}