{
  "type": "Feature",
  "properties": {
    "iso:country":"NL",
    "sg:address":"Dominee Van Meursstraat 33",
    "sg:city":"Wapenveld",
    "sg:orig_category":"Autokeuringen",
    "sg:phone":"+31 38 447 0183",
    "sg:postcode":"8191 AM",
    "sg:province":"Gelderland",
    "wof:name":"A. Nikkels En Zn. Vof",
    "wof:placetype":"venue"
},
  "geometry": {"coordinates":[6.075169,52.428543],"type":"Point"}
}