{
  "type": "Feature",
  "properties": {
    "addr:full":"Grafelykheidswg 50 Dordrecht Zuid-Holland 3328 EM",
    "addr:housenumber":"50",
    "addr:postcode":"3328 em",
    "addr:street":"Grafelykheidswg",
    "iso:country":"NL",
    "sg:address":"Grafelykheidswg 50",
    "sg:city":"Dordrecht",
    "sg:orig_category":"Kappers",
    "sg:phone":"+31 78 617 9600",
    "sg:postcode":"3328 EM",
    "sg:province":"Zuid-Holland",
    "wof:name":"Koning, Jos\u00e9 De",
    "wof:placetype":"venue"
},
  "geometry": {"coordinates":[4.67695,51.778332],"type":"Point"}
}