{
  "type": "Feature",
  "properties": {
    "addr:full":"Nikkelstr 1 Naarden Noord-Holland 1411 AB",
    "addr:housenumber":"1",
    "addr:postcode":"1411 ab",
    "addr:street":"Nikkelstr",
    "iso:country":"NL",
    "sg:address":"Nikkelstr 1",
    "sg:city":"Naarden",
    "sg:orig_category":"Drukkerijen",
    "sg:phone":"+31 35 694 5613",
    "sg:postcode":"1411 AB",
    "sg:province":"Noord-Holland",
    "sg:website":"http://www.losprint.nl",
    "wof:name":"Los Druk & Design",
    "wof:placetype":"venue"
},
  "geometry": {"coordinates":[5.150702,52.303432],"type":"Point"}
}