{
  "type": "Feature",
  "properties": {
    "addr:full":"Dotterbloem 57 Leidschendam South Holland 2266 MA",
    "addr:housenumber":"57",
    "addr:postcode":"2266 ma",
    "addr:street":"Dotterbloem",
    "iso:country":"NL",
    "sg:address":"Dotterbloem 57",
    "sg:city":"Leidschendam",
    "sg:orig_category":"Schilderwerk",
    "sg:phone":"+31 71 580 4502",
    "sg:postcode":"2266 MA",
    "sg:province":"South Holland",
    "wof:name":"Optima Onderhoudsbedrijf",
    "wof:placetype":"venue"
},
  "geometry": {"coordinates":[4.467659,52.094753],"type":"Point"}
}