{
  "type": "Feature",
  "properties": {
    "addr:full":"Witte De Withstraat 11A Rotterdam Zuid-Holland 3012 BK",
    "addr:housenumber":"11a",
    "addr:postcode":"3012 bk",
    "addr:street":"Witte De Withstraat",
    "iso:country":"NL",
    "sg:address":"Witte De Withstraat 11A",
    "sg:city":"Rotterdam",
    "sg:orig_category":"Balletscholen",
    "sg:phone":"+31 10 411 5666",
    "sg:postcode":"3012 BK",
    "sg:province":"Zuid-Holland",
    "sg:website":"http://www.paraddy.nl",
    "wof:name":"Paraddy Quality Dancewear",
    "wof:placetype":"venue"
},
  "geometry": {"coordinates":[4.479256,51.916214],"type":"Point"}
}