{
  "type": "Feature",
  "properties": {
    "addr:full":"Ceresln 1 Veendam Groningen 9641 MJ",
    "addr:housenumber":"1",
    "addr:postcode":"9641 mj",
    "addr:street":"Ceresln",
    "iso:country":"NL",
    "sg:address":"Ceresln 1",
    "sg:city":"Veendam",
    "sg:orig_category":"Autopoetsbedrijven",
    "sg:phone":"+31 598 634 265",
    "sg:postcode":"9641 MJ",
    "sg:province":"Groningen",
    "wof:name":"Crc Veendam/Delfzijl",
    "wof:placetype":"venue"
},
  "geometry": {"coordinates":[6.880442,53.106426],"type":"Point"}
}