{
  "type": "Feature",
  "properties": {
    "addr:full":"Prunuslaan 2 Nieuwe Pekela Groningen 9663 CW",
    "addr:housenumber":"2",
    "addr:postcode":"9663 cw",
    "addr:street":"Prunuslaan",
    "iso:country":"NL",
    "sg:address":"Prunuslaan 2",
    "sg:city":"Nieuwe Pekela",
    "sg:orig_category":"Bejaardeninstellingen And Serviceflats",
    "sg:phone":"+31 597 645 250",
    "sg:postcode":"9663 CW",
    "sg:province":"Groningen",
    "wof:name":"Clockstede Verzorgingshuis",
    "wof:placetype":"venue"
},
  "geometry": {"coordinates":[6.963807,53.077011],"type":"Point"}
}