{
  "type": "Feature",
  "properties": {
    "addr:full":"De Streekwg 25 Den Andel Groningen 9956 PN",
    "addr:housenumber":"25",
    "addr:postcode":"andel;9956 pn",
    "addr:street":"Den",
    "iso:country":"NL",
    "sg:address":"De Streekwg 25",
    "sg:city":"Den Andel",
    "sg:orig_category":"Grafmonumenten",
    "sg:phone":"+31 595 422 207",
    "sg:postcode":"9956 PN",
    "sg:province":"Groningen",
    "wof:name":"Jac Poel Bv",
    "wof:placetype":"venue"
},
  "geometry": {"coordinates":[6.508067,53.391659],"type":"Point"}
}