{
  "type": "Feature",
  "properties": {
    "iso:country":"NL",
    "sg:address":"Zeilenmakerspad 7",
    "sg:city":"Zaandam",
    "sg:orig_category":"Keramische Producten Fab",
    "sg:phone":"+31 75 635 4622",
    "sg:postcode":"1509 BZ",
    "sg:province":"North Holland",
    "wof:name":"De Saense Lelie",
    "wof:placetype":"venue"
},
  "geometry": {"coordinates":[4.821909,52.473011],"type":"Point"}
}