{
  "type": "Feature",
  "properties": {
    "iso:country":"NL",
    "sg:address":"Klaashofwg 21",
    "sg:city":"Eibergen",
    "sg:orig_category":"Glasdecoratie",
    "sg:phone":"+31 545 479 606",
    "sg:postcode":"7151 DR",
    "sg:province":"Gelderland",
    "sg:website":"http://www.glasatelier.net",
    "wof:name":"Glasatelier, Het",
    "wof:placetype":"venue"
},
  "geometry": {"coordinates":[6.648763,52.097145],"type":"Point"}
}