{
  "type": "Feature",
  "properties": {
    "addr:full":"Burg V Oersln 18 Oosterhout Nb Noord-Brabant 4904 LL",
    "addr:housenumber":"18",
    "addr:postcode":"4904 ll",
    "addr:street":"Burg V Oersln",
    "iso:country":"NL",
    "sg:address":"Burg V Oersln 18",
    "sg:city":"Oosterhout Nb",
    "sg:orig_category":"Adviesbureaus Bedrijfsorganisatie",
    "sg:phone":"+31 162 455 401",
    "sg:postcode":"4904 LL",
    "sg:province":"Noord-Brabant",
    "wof:name":"Weide Bv, Van Der",
    "wof:placetype":"venue"
},
  "geometry": {"coordinates":[4.85625,51.643051],"type":"Point"}
}