{
  "type": "Feature",
  "properties": {
    "addr:full":"Lanciersstr 104 Tilburg North Brabant 5017 CT",
    "addr:housenumber":"104",
    "addr:postcode":"5017 ct",
    "iso:country":"NL",
    "sg:address":"Lanciersstr 104",
    "sg:city":"Tilburg",
    "sg:orig_category":"Kappers",
    "sg:phone":"+31 13 544 3158",
    "sg:postcode":"5017 CT",
    "sg:province":"North Brabant",
    "wof:name":"Hair",
    "wof:placetype":"venue"
},
  "geometry": {"coordinates":[5.097422123,51.5540847778],"type":"Point"}
}