{
  "type": "Feature",
  "properties": {
    "iso:country":"NL",
    "sg:address":"Oranjestr 2A",
    "sg:city":"S Gravenhage",
    "sg:orig_category":"Adviesbureaus",
    "sg:phone":"+31 70 427 5433",
    "sg:postcode":"2514 JB",
    "sg:province":"Zuid-Holland",
    "wof:name":"Fundus Bv",
    "wof:placetype":"venue"
},
  "geometry": {"coordinates":[4.30935,52.084148],"type":"Point"}
}