{
  "type": "Feature",
  "properties": {
    "addr:full":"Albastdijk 95 Roosendaal Noord-Brabant 4706 AM",
    "addr:housenumber":"95",
    "addr:postcode":"4706",
    "addr:street":"Albastdijk",
    "iso:country":"NL",
    "sg:address":"Albastdijk 95",
    "sg:city":"Roosendaal",
    "sg:orig_category":"Architecten",
    "sg:phone":"+31 165 536 484",
    "sg:postcode":"4706 AM",
    "sg:province":"Noord-Brabant",
    "wof:name":"Architectenbureau Van Poucke Bna",
    "wof:placetype":"venue"
},
  "geometry": {"coordinates":[4.481764,51.523148],"type":"Point"}
}