{
  "type": "Feature",
  "properties": {
    "addr:full":"Kloetenseweg 68 Winterswijk Gelderland 7101 VB",
    "addr:housenumber":"68",
    "addr:postcode":"7101 vb",
    "addr:street":"Kloetenseweg;Gelderland",
    "iso:country":"NL",
    "sg:address":"Kloetenseweg 68",
    "sg:city":"Winterswijk",
    "sg:orig_category":"Boekhouders",
    "sg:phone":"+31 543 531 111",
    "sg:postcode":"7101 VB",
    "sg:province":"Gelderland",
    "wof:name":"Administratiekantoor Braak & Van Gaalen",
    "wof:placetype":"venue"
},
  "geometry": {"coordinates":[6.735767,51.970924],"type":"Point"}
}