{
  "type": "Feature",
  "properties": {
    "iso:country":"NL",
    "sg:address":"Donge 6",
    "sg:city":"Barendrecht",
    "sg:orig_category":"Verenigingen En Stichtingen",
    "sg:phone":"+31 180 622 920",
    "sg:postcode":"2991 RG",
    "sg:province":"Zuid-Holland",
    "wof:name":"Ver Verstr Onderwijs Geref Gr Slag",
    "wof:placetype":"venue"
},
  "geometry": {"coordinates":[4.549722,51.854073],"type":"Point"}
}