{
  "type": "Feature",
  "properties": {
    "addr:full":"Langveldstr 17 Alken BE.05 B-35 70",
    "addr:housenumber":"17;b-35 70",
    "addr:street":"Langveldstr;Be.05",
    "iso:country":"NL",
    "sg:address":"Langveldstr 17",
    "sg:city":"Alken",
    "sg:orig_category":"Luchtvaart- Maatschappijen",
    "sg:phone":"+31 11314419",
    "sg:postcode":"B-35 70",
    "sg:province":"BE.05",
    "wof:name":"Air Limo",
    "wof:placetype":"venue"
},
  "geometry": {"coordinates":[5.30736,50.876362],"type":"Point"}
}