{
  "type": "Feature",
  "properties": {
    "addr:full":"Kruitmolenln 162 Middelburg Zeeland 4337 KW",
    "addr:housenumber":"162",
    "addr:postcode":"4337 kw",
    "iso:country":"NL",
    "sg:address":"Kruitmolenln 162",
    "sg:city":"Middelburg",
    "sg:orig_category":"Verzekeringen - Verzekeringskantoren",
    "sg:phone":"+31 118 633 885",
    "sg:postcode":"4337 KW",
    "sg:province":"Zeeland",
    "wof:name":"Pellikaan, Paul",
    "wof:placetype":"venue"
},
  "geometry": {"coordinates":[3.631489,51.492538],"type":"Point"}
}