{
  "type": "Feature",
  "properties": {
    "addr:full":"Neptunushof 13 Krimpen Aan De Lek South Holland 2931 XR",
    "addr:housenumber":"13",
    "addr:postcode":"2931 xr",
    "addr:street":"Neptunushof",
    "iso:country":"NL",
    "sg:address":"Neptunushof 13",
    "sg:city":"Krimpen Aan De Lek",
    "sg:orig_category":"Webdesign Bureaus",
    "sg:phone":"+31 180 521 332",
    "sg:postcode":"2931 XR",
    "sg:province":"South Holland",
    "sg:website":"http://www.robtix.nl",
    "wof:name":"Robtix",
    "wof:placetype":"venue"
},
  "geometry": {"coordinates":[4.6352968216,51.8964920044],"type":"Point"}
}