{
  "type": "Feature",
  "properties": {
    "addr:full":"Jeekelstr 33 Leerdam Zuid-Holland 4142 AB",
    "addr:housenumber":"33",
    "addr:postcode":"4142 ab",
    "addr:street":"Jeekelstr",
    "iso:country":"NL",
    "sg:address":"Jeekelstr 33",
    "sg:city":"Leerdam",
    "sg:orig_category":"Onderhoudswerken",
    "sg:phone":"+31 345 630 398",
    "sg:postcode":"4142 AB",
    "sg:province":"Zuid-Holland",
    "wof:name":"Wielders, Ben",
    "wof:placetype":"venue"
},
  "geometry": {"coordinates":[5.086002,51.892727],"type":"Point"}
}