{
  "type": "Feature",
  "properties": {
    "iso:country":"NL",
    "sg:address":"Krommenieerwg 44",
    "sg:city":"Wormerveer",
    "sg:orig_category":"Cafetaria'S",
    "sg:phone":"+31 75 640 8904",
    "sg:postcode":"1521 HK",
    "sg:province":"Noord-Holland",
    "wof:name":"Marktzicht Cafetaria/Lunchroom",
    "wof:placetype":"venue"
},
  "geometry": {"coordinates":[4.78631,52.494926],"type":"Point"}
}