{
  "type": "Feature",
  "properties": {
    "addr:full":"Stuyvesantln 3 Alphen Aan Den Ryn Zuid-Holland 2404 XN",
    "addr:housenumber":"3",
    "addr:postcode":"2404 xn",
    "addr:street":"Stuyvesantln;Aan Den Ryn",
    "iso:country":"NL",
    "sg:address":"Stuyvesantln 3",
    "sg:city":"Alphen Aan Den Ryn",
    "sg:orig_category":"Grafische Bedrijven",
    "sg:phone":"+31 172 466 111",
    "sg:postcode":"2404 XN",
    "sg:province":"Zuid-Holland",
    "sg:website":"http://www.alfabase.nl",
    "wof:name":"Alfa Base Publicatie Processors Bv",
    "wof:placetype":"venue"
},
  "geometry": {"coordinates":[4.651111,52.136532],"type":"Point"}
}