{
  "type": "Feature",
  "properties": {
    "iso:country":"NL",
    "sg:address":"Marktveldpassage 1B",
    "sg:city":"Vught",
    "sg:orig_category":"Zoetwaren - Winkels",
    "sg:phone":"+31 73 656 8951",
    "sg:postcode":"5261 EC",
    "sg:province":"North Brabant",
    "wof:name":"Snoepkont, De",
    "wof:placetype":"venue"
},
  "geometry": {"coordinates":[5.301104,51.658623],"type":"Point"}
}