{
  "type": "Feature",
  "properties": {
    "addr:full":"Blauwedk 33 Middelburg Zeeland 4331 JD",
    "addr:housenumber":"33",
    "addr:postcode":"4331 jd",
    "addr:street":"Blauwedk",
    "iso:country":"NL",
    "sg:address":"Blauwedk 33",
    "sg:city":"Middelburg",
    "sg:orig_category":"Acupunctuur",
    "sg:phone":"+31 118 626 895",
    "sg:postcode":"4331 JD",
    "sg:province":"Zeeland",
    "wof:name":"Wintein, M J C",
    "wof:placetype":"venue"
},
  "geometry": {"coordinates":[3.614426,51.495163],"type":"Point"}
}