{
  "type": "Feature",
  "properties": {
    "addr:full":"F V Beststr 1 Valkenswaard Noord-Brabant 5554 EA",
    "addr:housenumber":"1",
    "addr:postcode":"5554 ea",
    "addr:street":"Beststr",
    "iso:country":"NL",
    "sg:address":"F V Beststr 1",
    "sg:city":"Valkenswaard",
    "sg:classifiers":[
        {
            "category":"Travel",
            "subcategory":"Hotels & Motels",
            "type":"Entertainment"
        }
    ],
    "sg:phone":"+31 40 201 2369",
    "sg:postcode":"5554 EA",
    "sg:province":"Noord-Brabant",
    "sg:website":"http://www.valkenswaard-plaza.nl",
    "wof:name":"Valk Bv, Hotel De",
    "wof:placetype":"venue"
},
  "geometry": {"coordinates":[5.45897,51.35051],"type":"Point"}
}