{
  "type": "Feature",
  "properties": {
    "addr:full":"Sniep 20 Diemen Noord-Holland 1112 AG",
    "addr:housenumber":"20",
    "addr:postcode":"1112",
    "addr:street":"Sniep",
    "iso:country":"NL",
    "sg:address":"Sniep 20",
    "sg:city":"Diemen",
    "sg:orig_category":"Betonmortel",
    "sg:phone":"+31 20 690 1850",
    "sg:postcode":"1112 AG",
    "sg:province":"Noord-Holland",
    "wof:name":"Transportbeton Diemen Bv",
    "wof:placetype":"venue"
},
  "geometry": {"coordinates":[4.974689,52.333576],"type":"Point"}
}