{
  "type": "Feature",
  "properties": {
    "iso:country":"NL",
    "sg:address":"Heide 2",
    "sg:city":"Roermond",
    "sg:classifiers":[
        {
            "category":"Sports & Exercise",
            "subcategory":"Stables",
            "type":"Entertainment"
        }
    ],
    "sg:phone":"+31 6 51255364",
    "sg:postcode":"6042 LN",
    "sg:province":"Limburg",
    "sg:tags":[
        "maneges"
    ],
    "sg:website":"http://www.centro-lusitano.nl",
    "wof:name":"Centro Lusitano",
    "wof:placetype":"venue"
},
  "geometry": {"coordinates":[6.048408,51.19352],"type":"Point"}
}