{
  "type": "Feature",
  "properties": {
    "addr:full":"Middel Broekweg 120 Honselersdijk South Holland 2675 KJ",
    "addr:housenumber":"120",
    "addr:postcode":"2675 kj",
    "addr:street":"Middel Broekweg",
    "iso:country":"NL",
    "sg:address":"Middel Broekweg 120",
    "sg:city":"Honselersdijk",
    "sg:orig_category":"Juridische Dienstverlening",
    "sg:phone":"+31 174 631 864",
    "sg:postcode":"2675 KJ",
    "sg:province":"South Holland",
    "wof:name":"Zwinkels Juridisch Advies",
    "wof:placetype":"venue"
},
  "geometry": {"coordinates":[4.239,52.005554],"type":"Point"}
}