{
  "type": "Feature",
  "properties": {
    "addr:full":"Voorstr 14 Ysselstein Ut Utrecht 3401 DC",
    "addr:housenumber":"14",
    "addr:postcode":"3401",
    "addr:street":"Voorstr",
    "iso:country":"NL",
    "sg:address":"Voorstr 14",
    "sg:city":"Ysselstein Ut",
    "sg:orig_category":"Discotheken",
    "sg:phone":"+31 30 688 4600",
    "sg:postcode":"3401 DC",
    "sg:province":"Utrecht",
    "wof:name":"Kangaroo",
    "wof:placetype":"venue"
},
  "geometry": {"coordinates":[5.045206,52.019695],"type":"Point"}
}