{
  "type": "Feature",
  "properties": {
    "addr:full":"Colynln 6 Groningen Groningen 9722 PL",
    "addr:housenumber":"6",
    "addr:postcode":"9722 pl",
    "addr:street":"Colynln",
    "iso:country":"NL",
    "sg:address":"Colynln 6",
    "sg:city":"Groningen",
    "sg:orig_category":"Balletscholen",
    "sg:phone":"+31 50 527 5191",
    "sg:postcode":"9722 PL",
    "sg:province":"Groningen",
    "wof:name":"Haren, Balletschool",
    "wof:placetype":"venue"
},
  "geometry": {"coordinates":[6.58877,53.197392],"type":"Point"}
}