{
  "type": "Feature",
  "properties": {
    "addr:full":"Kleverparkwg 59Zw Haarlem Noord-Holland 2023 CB",
    "addr:housenumber":"59zw",
    "addr:postcode":"2023 cb",
    "addr:street":"Kleverparkwg",
    "iso:country":"NL",
    "sg:address":"Kleverparkwg 59Zw",
    "sg:city":"Haarlem",
    "sg:orig_category":"Binnenhuisarchitectuur",
    "sg:phone":"+31 23 525 3828",
    "sg:postcode":"2023 CB",
    "sg:province":"Noord-Holland",
    "wof:name":"Janssen, C",
    "wof:placetype":"venue"
},
  "geometry": {"coordinates":[4.629759,52.392872],"type":"Point"}
}