{
  "type": "Feature",
  "properties": {
    "addr:full":"Molenstraat 67 Ede Gld Gelderland 6712 CS",
    "addr:housenumber":"67",
    "addr:postcode":"6712 cs",
    "addr:street":"Molenstraat;Gld Gelderland",
    "iso:country":"NL",
    "sg:address":"Molenstraat 67",
    "sg:city":"Ede Gld",
    "sg:orig_category":"Meubelzaken, Woning- And Keukeninrichting",
    "sg:phone":"+31 318 615 732",
    "sg:postcode":"6712 CS",
    "sg:province":"Gelderland",
    "wof:name":"Klassiek Wonen",
    "wof:placetype":"venue"
},
  "geometry": {"coordinates":[5.664915,52.046288],"type":"Point"}
}