{
  "type": "Feature",
  "properties": {
    "addr:full":"Vliestroom 2 Urk Flevoland 8321 EG",
    "addr:housenumber":"2",
    "addr:postcode":"8321 eg",
    "addr:street":"Vliestroom;Flevoland",
    "iso:country":"NL",
    "sg:address":"Vliestroom 2",
    "sg:city":"Urk",
    "sg:orig_category":"Autokeuringen",
    "sg:phone":"+31 527 686 860",
    "sg:postcode":"8321 EG",
    "sg:province":"Flevoland",
    "wof:name":"Gebr Hoekstra",
    "wof:placetype":"venue"
},
  "geometry": {"coordinates":[5.608658,52.655571],"type":"Point"}
}