{
  "type": "Feature",
  "properties": {
    "addr:full":"Hillinenwg 79A Hillegom Zuid-Holland 2182 VB",
    "addr:housenumber":"79a",
    "addr:postcode":"2182 vb",
    "addr:street":"Hillinenwg",
    "iso:country":"NL",
    "sg:address":"Hillinenwg 79A",
    "sg:city":"Hillegom",
    "sg:orig_category":"Kinderopvang",
    "sg:phone":"+31 252 517 201",
    "sg:postcode":"2182 VB",
    "sg:province":"Zuid-Holland",
    "wof:name":"Boefje, Peuterspeelzaal 'T",
    "wof:placetype":"venue"
},
  "geometry": {"coordinates":[4.583533,52.283314],"type":"Point"}
}