{
  "type": "Feature",
  "properties": {
    "iso:country":"NL",
    "sg:address":"R Hartpln 2A",
    "sg:city":"Amsterdam",
    "sg:orig_category":"Oppascentrales",
    "sg:phone":"+31 20 679 6793",
    "sg:postcode":"1071 TT",
    "sg:province":"Noord-Holland",
    "wof:name":"Peuterette, De",
    "wof:placetype":"venue"
},
  "geometry": {"coordinates":[4.8824338913,52.3531150818],"type":"Point"}
}