{
  "type": "Feature",
  "properties": {
    "iso:country":"NL",
    "sg:address":"Min Ruysstr 4",
    "sg:city":"Geleen",
    "sg:orig_category":"Administratie- En Boekhoudkantoren",
    "sg:phone":"+31 46 478 9389",
    "sg:postcode":"6162 XK",
    "sg:province":"Limburg",
    "sg:website":"http://www.abdata.nl",
    "wof:name":"Abdata Vof",
    "wof:placetype":"venue"
},
  "geometry": {"coordinates":[5.825043,50.975037],"type":"Point"}
}