{
  "type": "Feature",
  "properties": {
    "addr:full":"Hessenweg 102 De Bilt Utrecht 3731 JM",
    "addr:housenumber":"102",
    "addr:postcode":"3731 jm",
    "addr:street":"Hessenweg",
    "iso:country":"NL",
    "sg:address":"Hessenweg 102",
    "sg:city":"De Bilt",
    "sg:orig_category":"Discountwinkels",
    "sg:phone":"+31 30 220 1211",
    "sg:postcode":"3731 JM",
    "sg:province":"Utrecht",
    "wof:name":"Zeeman Textielsupers",
    "wof:placetype":"venue"
},
  "geometry": {"coordinates":[5.180784,52.108986],"type":"Point"}
}