{
  "type": "Feature",
  "properties": {
    "iso:country":"NL",
    "sg:address":"Bavelseln 68",
    "sg:city":"Breda",
    "sg:classifiers":[
        {
            "category":"Retail",
            "subcategory":"Auto Repair",
            "type":"Services"
        }
    ],
    "sg:phone":"+31 76 565 3721",
    "sg:postcode":"4835 GN",
    "sg:province":"Noord-Brabant",
    "sg:tags":[
        "garage"
    ],
    "wof:name":"Jespers, J J",
    "wof:placetype":"venue"
},
  "geometry": {"coordinates":[4.78509,51.569248],"type":"Point"}
}