{
  "type": "Feature",
  "properties": {
    "addr:full":"Bergseln 279C Rotterdam Zuid-Holland 3038 CD",
    "addr:housenumber":"279c",
    "addr:postcode":"3038 cd",
    "addr:street":"Bergseln",
    "iso:country":"NL",
    "sg:address":"Bergseln 279C",
    "sg:city":"Rotterdam",
    "sg:orig_category":"Loodgieters",
    "sg:phone":"+31 10 425 5177",
    "sg:postcode":"3038 CD",
    "sg:province":"Zuid-Holland",
    "wof:name":"Verburg, Nico",
    "wof:placetype":"venue"
},
  "geometry": {"coordinates":[4.46465,51.935558],"type":"Point"}
}