{
  "type": "Feature",
  "properties": {
    "addr:full":"Postbus 81139 Rotterdam 3009 GC",
    "addr:housenumber":"81139",
    "addr:postcode":"3009 gc",
    "addr:street":"Postbus",
    "iso:country":"NL",
    "sg:address":"Postbus 81139",
    "sg:city":"Rotterdam",
    "sg:orig_category":"Verzekeringen - Verzekeringskantoren",
    "sg:phone":"+31 10 421 0938",
    "sg:postcode":"3009 GC",
    "wof:name":"Freelink, L J",
    "wof:placetype":"venue"
},
  "geometry": {"coordinates":[4.47075,51.922619],"type":"Point"}
}