{
  "type": "Feature",
  "properties": {
    "addr:full":"Ansinghlaan 38 Nieuwegein Utrecht 3431 GV",
    "addr:housenumber":"38",
    "addr:postcode":"3431 gv",
    "addr:street":"Ansinghlaan",
    "iso:country":"NL",
    "sg:address":"Ansinghlaan 38",
    "sg:city":"Nieuwegein",
    "sg:orig_category":"Boekhouders",
    "sg:phone":"+31 30 605 2638",
    "sg:postcode":"3431 GV",
    "sg:province":"Utrecht",
    "wof:name":"Hr V O F",
    "wof:placetype":"venue"
},
  "geometry": {"coordinates":[5.079824,52.03632],"type":"Point"}
}