{
  "type": "Feature",
  "properties": {
    "addr:full":"Spielehorst 20 Enschede NL.08 7531 ES",
    "addr:housenumber":"20",
    "addr:postcode":"7531 es",
    "addr:street":"Spielehorst",
    "iso:country":"NL",
    "sg:address":"Spielehorst 20",
    "sg:city":"Enschede",
    "sg:orig_category":"Kunststofverpakkingen Fab",
    "sg:phone":"+31 53 433 7161",
    "sg:postcode":"7531 ES",
    "sg:province":"NL.08",
    "wof:name":"Ps Product Support",
    "wof:placetype":"venue"
},
  "geometry": {"coordinates":[6.927657,52.224529],"type":"Point"}
}