{
  "type": "Feature",
  "properties": {
    "addr:full":"De Kolk 17 Surhuisterveen Friesland 9231 CT",
    "addr:housenumber":"17",
    "addr:postcode":"9231 ct",
    "addr:street":"De Kolk",
    "iso:country":"NL",
    "sg:address":"De Kolk 17",
    "sg:city":"Surhuisterveen",
    "sg:orig_category":"Opticiens",
    "sg:phone":"+31 512 361 486",
    "sg:postcode":"9231 CT",
    "sg:province":"Friesland",
    "wof:name":"Werkman",
    "wof:placetype":"venue"
},
  "geometry": {"coordinates":[6.1651368141,53.1822853088],"type":"Point"}
}