{
  "type": "Feature",
  "properties": {
    "addr:full":"Postbus 3416 S Hertogenbosch 5203 DK",
    "addr:housenumber":"3416",
    "addr:postcode":"5203 dk",
    "addr:street":"Postbus;S Hertogenbosch",
    "iso:country":"NL",
    "sg:address":"Postbus 3416",
    "sg:city":"S Hertogenbosch",
    "sg:orig_category":"Administratie- En Boekhoudkantoren",
    "sg:phone":"+31 6 55811576",
    "sg:postcode":"5203 DK",
    "wof:name":"Buraad",
    "wof:placetype":"venue"
},
  "geometry": {"coordinates":[5.30421,51.68922],"type":"Point"}
}