{
  "type": "Feature",
  "properties": {
    "addr:full":"Koetsdrift 7 Nieuwegein Utrecht 3436 XK",
    "addr:housenumber":"7",
    "addr:postcode":"3436 xk",
    "addr:street":"Koetsdrift",
    "iso:country":"NL",
    "sg:address":"Koetsdrift 7",
    "sg:city":"Nieuwegein",
    "sg:orig_category":"Binnenhuisarchitecten",
    "sg:phone":"+31 30 603 5898",
    "sg:postcode":"3436 XK",
    "sg:province":"Utrecht",
    "wof:name":"J.A. Repi Interieurverzorging",
    "wof:placetype":"venue"
},
  "geometry": {"coordinates":[5.073755,52.030846],"type":"Point"}
}