{
  "type": "Feature",
  "properties": {
    "addr:full":"H Vd Boschstr 18B Amerongen Utrecht 3958 CD",
    "addr:housenumber":"18b",
    "addr:postcode":"3958 cd",
    "iso:country":"NL",
    "sg:address":"H Vd Boschstr 18B",
    "sg:city":"Amerongen",
    "sg:orig_category":"Autorijscholen",
    "sg:phone":"+31 343 451 688",
    "sg:postcode":"3958 CD",
    "sg:province":"Utrecht",
    "wof:name":"Huisman, John",
    "wof:placetype":"venue"
},
  "geometry": {"coordinates":[5.46023,52.000702],"type":"Point"}
}