{
  "type": "Feature",
  "properties": {
    "addr:full":"Deltawg 1 Tholen Zeeland 4691 RX",
    "addr:housenumber":"1",
    "addr:postcode":"4691 rx",
    "addr:street":"Deltawg",
    "iso:country":"NL",
    "sg:address":"Deltawg 1",
    "sg:city":"Tholen",
    "sg:orig_category":"Kunststoffen - Fabrieken En Groothandel",
    "sg:phone":"+31 166 609 590",
    "sg:postcode":"4691 RX",
    "sg:province":"Zeeland",
    "wof:name":"Uniflange Bv",
    "wof:placetype":"venue"
},
  "geometry": {"coordinates":[4.23094,51.539661],"type":"Point"}
}