{
  "type": "Feature",
  "properties": {
    "addr:full":"De Kwinkelier 48 Bilthoven Utrecht 3722 AS",
    "addr:housenumber":"48",
    "addr:postcode":"3722 as",
    "addr:street":"De Kwinkelier",
    "iso:country":"NL",
    "sg:address":"De Kwinkelier 48",
    "sg:city":"Bilthoven",
    "sg:orig_category":"Fotografische And Optische Artikelen Gh",
    "sg:phone":"+31 30 229 1783",
    "sg:postcode":"3722 AS",
    "sg:province":"Utrecht",
    "wof:name":"Hartmann Optiek",
    "wof:placetype":"venue"
},
  "geometry": {"coordinates":[5.20972,52.12883],"type":"Point"}
}