{
  "type": "Feature",
  "properties": {
    "addr:full":"Blaricumseplein 19 'S Gravenhage Zuid-Holland 2574 SN",
    "addr:housenumber":"19",
    "addr:postcode":"2574 sn",
    "addr:street":"Blaricumseplein;' S",
    "iso:country":"NL",
    "sg:address":"Blaricumseplein 19",
    "sg:city":"'S Gravenhage",
    "sg:orig_category":"Sportclubs",
    "sg:phone":"+31 70 364 6341",
    "sg:postcode":"2574 SN",
    "sg:province":"Zuid-Holland",
    "wof:name":"Tafeltennisbond Nederland Afdeling Holland West",
    "wof:placetype":"venue"
},
  "geometry": {"coordinates":[4.277442,52.063301],"type":"Point"}
}