{
  "type": "Feature",
  "properties": {
    "iso:country":"NL",
    "sg:address":"A Frankln 88",
    "sg:city":"Bussum",
    "sg:orig_category":"Adviesbureaus Bedrijfsorganisatie",
    "sg:phone":"+31 35 691 9530",
    "sg:postcode":"1403 HS",
    "sg:province":"Noord-Holland",
    "wof:name":"Curiel Cons",
    "wof:placetype":"venue"
},
  "geometry": {"coordinates":[5.1918,52.268147],"type":"Point"}
}