{
  "type": "Feature",
  "properties": {
    "addr:full":"Dr Holtroplaan 35 Eindhoven North Brabant 5652 XR",
    "addr:housenumber":"35",
    "addr:postcode":"5652 xr",
    "addr:street":"Dr Holtroplaan",
    "iso:country":"NL",
    "sg:address":"Dr Holtroplaan 35",
    "sg:city":"Eindhoven",
    "sg:orig_category":"Werving And Selectie Van Tijdelijk Personeel And Uitzendkantoren",
    "sg:phone":"+31 40 257 8000",
    "sg:postcode":"5652 XR",
    "sg:province":"North Brabant",
    "wof:name":"Euro Match",
    "wof:placetype":"venue"
},
  "geometry": {"coordinates":[5.4277439117,51.4399108887],"type":"Point"}
}