{
  "type": "Feature",
  "properties": {
    "addr:full":"Beursplein 37 Rotterdam Zuid-Holland 3011 AA",
    "addr:housenumber":"37",
    "addr:postcode":"3011 aa",
    "addr:street":"Beursplein",
    "iso:country":"NL",
    "sg:address":"Beursplein 37",
    "sg:city":"Rotterdam",
    "sg:orig_category":"Levende Dieren Gh",
    "sg:phone":"+31 10 405 6000",
    "sg:postcode":"3011 AA",
    "sg:province":"Zuid-Holland",
    "wof:name":"Bv Weil V/H Hagenbeek & Van Der Schalk",
    "wof:placetype":"venue"
},
  "geometry": {"coordinates":[4.480417,51.920151],"type":"Point"}
}