{
  "type": "Feature",
  "properties": {
    "iso:country":"NL",
    "sg:address":"Radboud 42",
    "sg:city":"Almelo",
    "sg:orig_category":"Vertalers",
    "sg:phone":"+31 546 490 152",
    "sg:postcode":"7608 JK",
    "sg:province":"NL.08",
    "wof:name":"Hernandez Spaans Vertaalburo",
    "wof:placetype":"venue"
},
  "geometry": {"coordinates":[6.67092,52.378273],"type":"Point"}
}