{
  "type": "Feature",
  "properties": {
    "iso:country":"NL",
    "sg:address":"Verlengde Nieuwstraat 38",
    "sg:city":"Groningen",
    "sg:orig_category":"Meubelmakerijen",
    "sg:phone":"+31 50 318 4281",
    "sg:postcode":"9724 HD",
    "sg:province":"Groningen",
    "wof:name":"Vorm In Hout Vof",
    "wof:placetype":"venue"
},
  "geometry": {"coordinates":[6.582478,53.20982],"type":"Point"}
}