{
  "type": "Feature",
  "properties": {
    "addr:full":"Kijkakkers 1 Maarheeze Noord-Brabant 6026 ER",
    "addr:housenumber":"1",
    "addr:postcode":"6026 er",
    "addr:street":"Kijkakkers",
    "iso:country":"NL",
    "sg:address":"Kijkakkers 1",
    "sg:city":"Maarheeze",
    "sg:orig_category":"Bibliotheken En Leeszalen Openbare",
    "sg:phone":"+31 495 592 009",
    "sg:postcode":"6026 ER",
    "sg:province":"Noord-Brabant",
    "wof:name":"Openb Bibliotheek",
    "wof:placetype":"venue"
},
  "geometry": {"coordinates":[5.611521,51.313362],"type":"Point"}
}