{
  "type": "Feature",
  "properties": {
    "addr:full":"Stationsstr 13 Boxtel North Brabant 5281 GA",
    "addr:housenumber":"13",
    "addr:postcode":"5281 ga",
    "addr:street":"Stationsstr",
    "iso:country":"NL",
    "sg:address":"Stationsstr 13",
    "sg:city":"Boxtel",
    "sg:orig_category":"Juweliers",
    "sg:phone":"+31 411 678 234",
    "sg:postcode":"5281 GA",
    "sg:province":"North Brabant",
    "wof:name":"Lammers, Juwelier-Goudsmid",
    "wof:placetype":"venue"
},
  "geometry": {"coordinates":[5.323376,51.588184],"type":"Point"}
}