{
  "type": "Feature",
  "properties": {
    "iso:country":"NL",
    "sg:address":"Dieselstr 16",
    "sg:city":"Hoogeveen",
    "sg:orig_category":"Kaasgroothandel",
    "sg:phone":"+31 528 279 078",
    "sg:postcode":"7903 AR",
    "sg:province":"Drenthe",
    "wof:name":"Koekoek",
    "wof:placetype":"venue"
},
  "geometry": {"coordinates":[6.4995350838,52.7347717285],"type":"Point"}
}