{
  "type": "Feature",
  "properties": {
    "addr:full":"Harpdreef 47 Etten Leur Noord-Brabant 4876 ZW",
    "addr:housenumber":"47",
    "addr:postcode":"4876 zw",
    "addr:street":"Harpdreef",
    "iso:country":"NL",
    "sg:address":"Harpdreef 47",
    "sg:city":"Etten Leur",
    "sg:orig_category":"Facilitaire Dienstverlening",
    "sg:phone":"+31 76 501 8750",
    "sg:postcode":"4876 ZW",
    "sg:province":"Noord-Brabant",
    "wof:name":"Energy Procurement",
    "wof:placetype":"venue"
},
  "geometry": {"coordinates":[4.638462,51.559162],"type":"Point"}
}