{
  "type": "Feature",
  "properties": {
    "addr:full":"Pigmenthof 52 Almere NL. 1339 HD",
    "addr:housenumber":"52",
    "addr:postcode":"1339 hd",
    "addr:street":"Pigmenthof;Nl.",
    "iso:country":"NL",
    "sg:address":"Pigmenthof 52",
    "sg:city":"Almere",
    "sg:orig_category":"Jachten - Schilderwerken En Onderhoud",
    "sg:phone":"+31 6 54606506",
    "sg:postcode":"1339 HD",
    "sg:province":"NL.",
    "sg:website":"http://www.bakkersjachtservice.nl",
    "wof:name":"Bakker'S Jachtservice",
    "wof:placetype":"venue"
},
  "geometry": {"coordinates":[5.296369,52.391621],"type":"Point"}
}