{
  "type": "Feature",
  "properties": {
    "addr:full":"Zijderveldselaan 58 Zijderveld South Holland 4122 GR",
    "addr:housenumber":"58",
    "addr:postcode":"4122",
    "addr:street":"Zijderveldselaan",
    "iso:country":"NL",
    "sg:address":"Zijderveldselaan 58",
    "sg:city":"Zijderveld",
    "sg:orig_category":"Musea And Historische Gebouwen",
    "sg:phone":"+31 345 642 601",
    "sg:postcode":"4122 GR",
    "sg:province":"South Holland",
    "wof:name":"Herder Museum",
    "wof:placetype":"venue"
},
  "geometry": {"coordinates":[5.117985,51.946884],"type":"Point"}
}