{
  "type": "Feature",
  "properties": {
    "addr:full":"Tamboerpassage 130 Hoogeveen Provincie Drenthe 7902 GT",
    "addr:housenumber":"130;7902",
    "addr:postcode":"gt",
    "addr:street":"Tamboerpassage;Provincie",
    "iso:country":"NL",
    "sg:address":"Tamboerpassage 130",
    "sg:city":"Hoogeveen",
    "sg:orig_category":"Kappers",
    "sg:phone":"+31 528 262 395",
    "sg:postcode":"7902 GT",
    "sg:province":"Provincie Drenthe",
    "wof:name":"Kapsalon De Barbery",
    "wof:placetype":"venue"
},
  "geometry": {"coordinates":[6.4799799919,52.7262573242],"type":"Point"}
}