{
  "type": "Feature",
  "properties": {
    "addr:full":"Stationspln 8 Breda Noord-Brabant 4811 BB",
    "addr:housenumber":"8",
    "addr:postcode":"4811 bb",
    "addr:street":"Stationspln",
    "iso:country":"NL",
    "sg:address":"Stationspln 8",
    "sg:city":"Breda",
    "sg:orig_category":"Broodjeszaken",
    "sg:phone":"+31 76 521 9793",
    "sg:postcode":"4811 BB",
    "sg:province":"Noord-Brabant",
    "sg:website":"http://www.holle-bolle-gijs.nl",
    "wof:name":"Holle Bolle Gijs/Rest 'T Valken",
    "wof:placetype":"venue"
},
  "geometry": {"coordinates":[4.779238,51.594517],"type":"Point"}
}