{
  "type": "Feature",
  "properties": {
    "addr:full":"Plataanstraat 34 Breda Noord-Brabant 4814 LD",
    "addr:housenumber":"34",
    "addr:postcode":"4814 ld",
    "addr:street":"Plataanstraat",
    "iso:country":"NL",
    "sg:address":"Plataanstraat 34",
    "sg:city":"Breda",
    "sg:orig_category":"Wegen And Sportterreinen",
    "sg:phone":"+31 76 520 1325",
    "sg:postcode":"4814 LD",
    "sg:province":"Noord-Brabant",
    "wof:name":"A. Boumeester",
    "wof:placetype":"venue"
},
  "geometry": {"coordinates":[4.7585778236,51.5883674622],"type":"Point"}
}