{
  "type": "Feature",
  "properties": {
    "addr:full":"De Els 35 Haaksbergen NL.08 7482 BA",
    "addr:housenumber":"35;nl.08",
    "addr:postcode":"7482 ba",
    "addr:street":"De Els",
    "iso:country":"NL",
    "sg:address":"De Els 35",
    "sg:city":"Haaksbergen",
    "sg:orig_category":"Farmaceutische Producten Gh",
    "sg:phone":"+31 53 572 2565",
    "sg:postcode":"7482 BA",
    "sg:province":"NL.08",
    "wof:name":"Laimex Bv",
    "wof:placetype":"venue"
},
  "geometry": {"coordinates":[6.745468,52.161907],"type":"Point"}
}