{
  "type": "Feature",
  "properties": {
    "iso:country":"NL",
    "sg:address":"Chopinstr 18",
    "sg:city":"Zevenaar",
    "sg:orig_category":"Postorderbedrijven",
    "sg:phone":"+31 316 840 246",
    "sg:postcode":"6904 JD",
    "sg:province":"Gelderland",
    "sg:website":"http://www.countrymen.myweb.nl",
    "wof:name":"Cowboy Maik'S",
    "wof:placetype":"venue"
},
  "geometry": {"coordinates":[6.062651,51.931011],"type":"Point"}
}