{
  "type": "Feature",
  "properties": {
    "addr:full":"Handelswg 10A Hasselt Overijssel 8061 RL",
    "addr:housenumber":"10a",
    "addr:postcode":"8061 rl",
    "addr:street":"Handelswg",
    "iso:country":"NL",
    "sg:address":"Handelswg 10A",
    "sg:city":"Hasselt",
    "sg:orig_category":"Adviesbureaus Elektrotechniek",
    "sg:phone":"+31 38 477 3514",
    "sg:postcode":"8061 RL",
    "sg:province":"Overijssel",
    "sg:website":"http://www.kie-engineering.nl",
    "wof:name":"Kie Engineering",
    "wof:placetype":"venue"
},
  "geometry": {"coordinates":[6.087259,52.580158],"type":"Point"}
}