{
  "type": "Feature",
  "properties": {
    "iso:country":"NL",
    "sg:address":"Dorpsstraat 23",
    "sg:city":"Heinenoord",
    "sg:classifiers":[
        {
            "category":"Travel",
            "subcategory":"Hotels & Motels",
            "type":"Entertainment"
        }
    ],
    "sg:phone":"+31 186 601 896",
    "sg:postcode":"3274 BB",
    "sg:province":"Zuid-Holland",
    "wof:name":"Kosthuis De Noord",
    "wof:placetype":"venue"
},
  "geometry": {"coordinates":[4.476485,51.825535],"type":"Point"}
}