{
  "type": "Feature",
  "properties": {
    "addr:full":"Weidekruidveld 21 Almere NL. 1313 JR",
    "addr:housenumber":"21;1313",
    "addr:street":"Weidekruidveld;Nl.",
    "iso:country":"NL",
    "sg:address":"Weidekruidveld 21",
    "sg:city":"Almere",
    "sg:orig_category":"Babyartikelen",
    "sg:phone":"+31 36 534 4071",
    "sg:postcode":"1313 JR",
    "sg:province":"NL.",
    "wof:name":"Harlekijn, De",
    "wof:placetype":"venue"
},
  "geometry": {"coordinates":[5.193992,52.383614],"type":"Point"}
}