{
  "type": "Feature",
  "properties": {
    "iso:country":"NL",
    "sg:address":"Fruitweg 28",
    "sg:city":"Leiden",
    "sg:orig_category":"Bouwmaterialen Gh",
    "sg:phone":"+31 71 531 5488",
    "sg:postcode":"2321 GK",
    "sg:province":"Zuid-Holland",
    "wof:name":"Sikkens Center",
    "wof:placetype":"venue"
},
  "geometry": {"coordinates":[4.488267,52.147686],"type":"Point"}
}