{
  "type": "Feature",
  "properties": {
    "addr:full":"Rendementswg 24E Mydrecht Utrecht 3641 SL",
    "addr:housenumber":"24e mydrecht",
    "addr:postcode":"3641 sl",
    "addr:street":"Rendementswg",
    "iso:country":"NL",
    "sg:address":"Rendementswg 24E",
    "sg:city":"Mydrecht",
    "sg:orig_category":"Kantoor- En Secretariaatsservice",
    "sg:phone":"+31 297 285 144",
    "sg:postcode":"3641 SL",
    "sg:province":"Utrecht",
    "sg:website":"http://www.3xs.org",
    "wof:name":"Special Secretary Service",
    "wof:placetype":"venue"
},
  "geometry": {"coordinates":[4.884663105,52.2098846436],"type":"Point"}
}