{
  "type": "Feature",
  "properties": {
    "addr:full":"Nobelstraat 98 Oud Beijerland South Holland 3262 PM",
    "addr:housenumber":"98",
    "addr:postcode":"3262 pm",
    "addr:street":"Nobelstraat;Oud Beijerland",
    "iso:country":"NL",
    "sg:address":"Nobelstraat 98",
    "sg:city":"Oud Beijerland",
    "sg:orig_category":"Verzekeringen",
    "sg:phone":"+31 186 613 602",
    "sg:postcode":"3262 PM",
    "sg:province":"South Holland",
    "wof:name":"Dick Groeneweg Verzekeringen",
    "wof:placetype":"venue"
},
  "geometry": {"coordinates":[4.409495,51.825787],"type":"Point"}
}