{
  "type": "Feature",
  "properties": {
    "iso:country":"NL",
    "sg:address":"Slachthuisstr 63",
    "sg:city":"Zaandam",
    "sg:orig_category":"Scholen Voor Basisonderwijs",
    "sg:phone":"+31 75 616 5977",
    "sg:postcode":"1508 EC",
    "sg:province":"North Holland",
    "wof:name":"Voorthuysen Mlk, Dr A Van",
    "wof:placetype":"venue"
},
  "geometry": {"coordinates":[4.816766,52.461689],"type":"Point"}
}