{
  "type": "Feature",
  "properties": {
    "addr:full":"Zinkstr 53 Breda Noord-Brabant 4823 AC",
    "addr:housenumber":"53",
    "addr:postcode":"4823 ac",
    "addr:street":"Zinkstr",
    "iso:country":"NL",
    "sg:address":"Zinkstr 53",
    "sg:city":"Breda",
    "sg:orig_category":"Etiketten",
    "sg:phone":"+31 76 542 5040",
    "sg:postcode":"4823 AC",
    "sg:province":"Noord-Brabant",
    "sg:website":"http://www.bergetiketten.nl",
    "wof:name":"Berg Bv",
    "wof:placetype":"venue"
},
  "geometry": {"coordinates":[4.717921,51.612976],"type":"Point"}
}