{
  "type": "Feature",
  "properties": {
    "iso:country":"NL",
    "sg:address":"Sweelinckpln 1",
    "sg:city":"S Gravenhage",
    "sg:orig_category":"Octrooigemachtigden- Bureaus",
    "sg:phone":"+31 70 365 4833",
    "sg:postcode":"2517 GK",
    "sg:province":"Zuid-Holland",
    "sg:website":"http://www.arnold-siedsma.nl",
    "wof:name":"Arnold & Siedsma",
    "wof:placetype":"venue"
},
  "geometry": {"coordinates":[4.28708,52.08667],"type":"Point"}
}