{
  "type": "Feature",
  "properties": {
    "addr:full":"T Harkeswei 14 Lippenhuizen Friesland 8408 CE",
    "addr:housenumber":"14",
    "addr:postcode":"8408 ce",
    "addr:street":"T Harkeswei",
    "iso:country":"NL",
    "sg:address":"T Harkeswei 14",
    "sg:city":"Lippenhuizen",
    "sg:classifiers":[
        {
            "category":"Sports & Exercise",
            "subcategory":"Stables",
            "type":"Entertainment"
        }
    ],
    "sg:phone":"+31 513 461 718",
    "sg:postcode":"8408 CE",
    "sg:province":"Friesland",
    "sg:tags":[
        "maneges"
    ],
    "wof:name":"Passage, De",
    "wof:placetype":"venue"
},
  "geometry": {"coordinates":[-39.34277,-5.32226],"type":"Point"}
}