{
  "type": "Feature",
  "properties": {
    "addr:full":"J Vermeerln 161B Roosendaal Noord-Brabant 4703 KN",
    "addr:housenumber":"161b",
    "addr:postcode":"4703 kn",
    "iso:country":"NL",
    "sg:address":"J Vermeerln 161B",
    "sg:city":"Roosendaal",
    "sg:orig_category":"Administratie- En Boekhoudkantoren",
    "sg:phone":"+31 165 554 617",
    "sg:postcode":"4703 KN",
    "sg:province":"Noord-Brabant",
    "wof:name":"Oosterhout, Administratiekantoor",
    "wof:placetype":"venue"
},
  "geometry": {"coordinates":[4.442486,51.541161],"type":"Point"}
}