{
  "type": "Feature",
  "properties": {
    "addr:full":"Sikkelveld 20 Houten Utrecht 3993 RJ",
    "addr:housenumber":"20",
    "addr:postcode":"3993 rj",
    "addr:street":"Sikkelveld",
    "iso:country":"NL",
    "sg:address":"Sikkelveld 20",
    "sg:city":"Houten",
    "sg:orig_category":"Adviesbureaus Beveiliging",
    "sg:phone":"+31 30 634 0189",
    "sg:postcode":"3993 RJ",
    "sg:province":"Utrecht",
    "wof:name":"Regent Holding Bv",
    "wof:placetype":"venue"
},
  "geometry": {"coordinates":[5.17487,52.042477],"type":"Point"}
}