{
  "type": "Feature",
  "properties": {
    "addr:full":"Stratumsedijk 3 Eindhoven North Brabant 5611 NA",
    "addr:housenumber":"3",
    "addr:postcode":"5611 na",
    "addr:street":"Stratumsedijk",
    "iso:country":"NL",
    "sg:address":"Stratumsedijk 3",
    "sg:city":"Eindhoven",
    "sg:classifiers":[
        {
            "category":"Retail",
            "subcategory":"Photofinishing",
            "type":"Services"
        }
    ],
    "sg:phone":"+31 40 212 1202",
    "sg:postcode":"5611 NA",
    "sg:province":"North Brabant",
    "sg:tags":[
        "foto",
        "film"
    ],
    "wof:name":"City Foto",
    "wof:placetype":"venue"
},
  "geometry": {"coordinates":[5.483754,51.434849],"type":"Point"}
}