{
  "type": "Feature",
  "properties": {
    "addr:full":"Singel 1B Wyk By Duurstede Utrecht 3961 CE",
    "addr:housenumber":"1b",
    "addr:postcode":"3961 ce",
    "addr:street":"Singel",
    "iso:country":"NL",
    "sg:address":"Singel 1B",
    "sg:city":"Wyk By Duurstede",
    "sg:classifiers":[
        {
            "category":"Sports & Exercise",
            "subcategory":"Stables",
            "type":"Entertainment"
        }
    ],
    "sg:phone":"+31 343 578 449",
    "sg:postcode":"3961 CE",
    "sg:province":"Utrecht",
    "sg:tags":[
        "maneges"
    ],
    "wof:name":"Wildkamp, De",
    "wof:placetype":"venue"
},
  "geometry": {"coordinates":[5.341867,51.968807],"type":"Point"}
}