{
  "type": "Feature",
  "properties": {
    "addr:full":"Dommelstr 6 Eindhoven Noord-Brabant 5611 CK",
    "addr:housenumber":"6",
    "addr:postcode":"5611 ck",
    "addr:street":"Dommelstr",
    "iso:country":"NL",
    "sg:address":"Dommelstr 6",
    "sg:city":"Eindhoven",
    "sg:orig_category":"Verenigingen En Stichtingen",
    "sg:phone":"+31 40 243 4264",
    "sg:postcode":"5611 CK",
    "sg:province":"Noord-Brabant",
    "wof:name":"Boei, Dac De",
    "wof:placetype":"venue"
},
  "geometry": {"coordinates":[5.482969,51.441708],"type":"Point"}
}