{
  "type": "Feature",
  "properties": {
    "addr:full":"Grt Beer 37 Bleiswyk Zuid-Holland 2665 WK",
    "addr:housenumber":"37",
    "addr:postcode":"2665 wk",
    "iso:country":"NL",
    "sg:address":"Grt Beer 37",
    "sg:city":"Bleiswyk",
    "sg:orig_category":"Adviesbureaus Bouwkunde",
    "sg:phone":"+31 10 521 6919",
    "sg:postcode":"2665 WK",
    "sg:province":"Zuid-Holland",
    "wof:name":"Heer, C De",
    "wof:placetype":"venue"
},
  "geometry": {"coordinates":[4.531235,52.012997],"type":"Point"}
}