{
  "type": "Feature",
  "properties": {
    "addr:full":"Dracht 132 Heerenveen Provincie Friesland 8442 BZ",
    "addr:housenumber":"132",
    "addr:postcode":"8442 bz",
    "addr:street":"Dracht;Provincie Friesland",
    "iso:country":"NL",
    "sg:address":"Dracht 132",
    "sg:city":"Heerenveen",
    "sg:orig_category":"Kappers",
    "sg:phone":"+31 513 653 141",
    "sg:postcode":"8442 BZ",
    "sg:province":"Provincie Friesland",
    "wof:name":"Neris",
    "wof:placetype":"venue"
},
  "geometry": {"coordinates":[5.925899,52.957344],"type":"Point"}
}