{
  "type": "Feature",
  "properties": {
    "addr:full":"Lt Gen V Heutszln 8 Baarn Utrecht 3743 JN",
    "addr:housenumber":"8",
    "addr:postcode":"3743 jn",
    "addr:street":"Heutszln",
    "iso:country":"NL",
    "sg:address":"Lt Gen V Heutszln 8",
    "sg:city":"Baarn",
    "sg:orig_category":"Adviesbureaus Economie",
    "sg:phone":"+31 35 548 9020",
    "sg:postcode":"3743 JN",
    "sg:province":"Utrecht",
    "sg:website":"http://www.horwath.nl",
    "wof:name":"Horwath",
    "wof:placetype":"venue"
},
  "geometry": {"coordinates":[5.292121,52.21101],"type":"Point"}
}