{
  "type": "Feature",
  "properties": {
    "addr:full":"Oosterstreek 82 Oosterstreek Friesland 8388 NG",
    "addr:housenumber":"82",
    "addr:postcode":"8388 ng",
    "addr:street":"Oosterstreek",
    "iso:country":"NL",
    "sg:address":"Oosterstreek 82",
    "sg:city":"Oosterstreek",
    "sg:orig_category":"Geluidsinstallaties - Verhuur",
    "sg:phone":"+31 561 432 192",
    "sg:postcode":"8388 NG",
    "sg:province":"Friesland",
    "sg:website":"http://www.gsn-meurs.com",
    "wof:name":"Gsn",
    "wof:placetype":"venue"
},
  "geometry": {"coordinates":[6.169245,52.899948],"type":"Point"}
}