{
  "type": "Feature",
  "properties": {
    "addr:full":"Van Kinsbergenlaan 65 Terneuzen Zeeland 4535 BH",
    "addr:housenumber":"65",
    "addr:postcode":"4535 bh",
    "addr:street":"Van Kinsbergenlaan",
    "iso:country":"NL",
    "sg:address":"Van Kinsbergenlaan 65",
    "sg:city":"Terneuzen",
    "sg:orig_category":"Diverse Grafische Activiteiten",
    "sg:phone":"+31 115 618 431",
    "sg:postcode":"4535 BH",
    "sg:province":"Zeeland",
    "wof:name":"Arno Boer",
    "wof:placetype":"venue"
},
  "geometry": {"coordinates":[3.85513,51.318554],"type":"Point"}
}