{
  "type": "Feature",
  "properties": {
    "iso:country":"NL",
    "sg:address":"Veerstr 22",
    "sg:city":"Standdaarbuiten",
    "sg:orig_category":"Dieselmotoren",
    "sg:phone":"+31 165 317 757",
    "sg:postcode":"4758 BS",
    "sg:province":"Noord-Brabant",
    "wof:name":"Leeman",
    "wof:placetype":"venue"
},
  "geometry": {"coordinates":[4.517871,51.608494],"type":"Point"}
}