{
  "type": "Feature",
  "properties": {
    "addr:full":"Fideliostr 76 Alkmaar Noord-Holland 1827 RH",
    "addr:housenumber":"76",
    "addr:postcode":"1827 rh",
    "addr:street":"Fideliostr",
    "iso:country":"NL",
    "sg:address":"Fideliostr 76",
    "sg:city":"Alkmaar",
    "sg:orig_category":"Kantoormachines - Fabrieken En Groothandel",
    "sg:phone":"+31 72 561 2015",
    "sg:postcode":"1827 RH",
    "sg:province":"Noord-Holland",
    "wof:name":"Loerakker Bv",
    "wof:placetype":"venue"
},
  "geometry": {"coordinates":[4.7746748924,52.6691322327],"type":"Point"}
}