{
  "type": "Feature",
  "properties": {
    "addr:full":"G Doustr 1B Amsterdam Noord-Holland 1072 VG",
    "addr:housenumber":"1b",
    "addr:postcode":"1072 vg",
    "iso:country":"NL",
    "sg:address":"G Doustr 1B",
    "sg:city":"Amsterdam",
    "sg:orig_category":"Adviesbureaus Bedrijfsorganisatie",
    "sg:phone":"+31 20 675 2362",
    "sg:postcode":"1072 VG",
    "sg:province":"Noord-Holland",
    "wof:name":"Roy Van Zuydewijn, De",
    "wof:placetype":"venue"
},
  "geometry": {"coordinates":[4.887313,52.355385],"type":"Point"}
}