{
  "type": "Feature",
  "properties": {
    "addr:full":"H De Grootstr 55 Delft Zuid-Holland 2613 VN",
    "addr:housenumber":"55",
    "addr:postcode":"2613 vn",
    "addr:street":"Delft",
    "iso:country":"NL",
    "sg:address":"H De Grootstr 55",
    "sg:city":"Delft",
    "sg:orig_category":"Kinderopvang",
    "sg:phone":"+31 15 213 3203",
    "sg:postcode":"2613 VN",
    "sg:province":"Zuid-Holland",
    "wof:name":"Teddybeer, Kinderdagverblijf De",
    "wof:placetype":"venue"
},
  "geometry": {"coordinates":[4.352048,52.008873],"type":"Point"}
}