{
  "type": "Feature",
  "properties": {
    "addr:full":"Wilhelminaln 40 Delft Zuid-Holland 2625 KH",
    "addr:housenumber":"40",
    "addr:postcode":"2625 kh",
    "addr:street":"Wilhelminaln",
    "iso:country":"NL",
    "sg:address":"Wilhelminaln 40",
    "sg:city":"Delft",
    "sg:orig_category":"Adviesbureaus Bedrijfsveiligheid",
    "sg:phone":"+31 15 262 2974",
    "sg:postcode":"2625 KH",
    "sg:province":"Zuid-Holland",
    "wof:name":"Adr",
    "wof:placetype":"venue"
},
  "geometry": {"coordinates":[4.340279,51.987488],"type":"Point"}
}