{
  "type": "Feature",
  "properties": {
    "addr:full":"Pippelingstraat 4 Eindhoven North Brabant 5632 NS",
    "addr:housenumber":"4",
    "addr:postcode":"5632 ns",
    "addr:street":"Pippelingstraat",
    "iso:country":"NL",
    "sg:address":"Pippelingstraat 4",
    "sg:city":"Eindhoven",
    "sg:orig_category":"Boekenuitgeverijen",
    "sg:phone":"+31 40 241 2229",
    "sg:postcode":"5632 NS",
    "sg:province":"North Brabant",
    "wof:name":"F.C. Kruger",
    "wof:placetype":"venue"
},
  "geometry": {"coordinates":[5.493546,51.479774],"type":"Point"}
}