{
  "type": "Feature",
  "properties": {
    "addr:full":"Pampusln 190 Weesp Noord-Holland 1382 JS",
    "addr:housenumber":"190",
    "addr:postcode":"1382 js",
    "iso:country":"NL",
    "sg:address":"Pampusln 190",
    "sg:city":"Weesp",
    "sg:orig_category":"Pompen - Fabrieken",
    "sg:phone":"+31 294 492 222",
    "sg:postcode":"1382 JS",
    "sg:province":"Noord-Holland",
    "sg:website":"http://www.grundfos.com",
    "wof:name":"Grundfos Nederland Bv",
    "wof:placetype":"venue"
},
  "geometry": {"coordinates":[5.03828,52.308315],"type":"Point"}
}