{
  "type": "Feature",
  "properties": {
    "iso:country":"NL",
    "sg:address":"Kennemerstrwg 470",
    "sg:city":"Heiloo",
    "sg:orig_category":"Cafetaria'S",
    "sg:phone":"+31 72 533 0067",
    "sg:postcode":"1851 NG",
    "sg:province":"North Holland",
    "sg:website":"http://www.cosycorner.nl",
    "wof:name":"Cosy Corner",
    "wof:placetype":"venue"
},
  "geometry": {"coordinates":[4.713702,52.604191],"type":"Point"}
}