{
  "type": "Feature",
  "properties": {
    "iso:country":"NL",
    "sg:address":"Celsiusstraat 210",
    "sg:city":"Zandvoort",
    "sg:orig_category":"Pleziervaartuigen And Reparatie",
    "sg:phone":"+31 23 571 8695",
    "sg:postcode":"2041 TR",
    "sg:province":"Noord-Holland",
    "wof:name":"Technisch Bureau Pesa",
    "wof:placetype":"venue"
},
  "geometry": {"coordinates":[4.553722,52.380074],"type":"Point"}
}