{
  "type": "Feature",
  "properties": {
    "addr:full":"Boonsweg 8A Heinenoord South Holland 3274 LH",
    "addr:housenumber":"8a",
    "addr:postcode":"3274 lh",
    "addr:street":"Boonsweg",
    "iso:country":"NL",
    "sg:address":"Boonsweg 8A",
    "sg:city":"Heinenoord",
    "sg:orig_category":"Machinefabrieken",
    "sg:phone":"+31 186 609 299",
    "sg:postcode":"3274 LH",
    "sg:province":"South Holland",
    "wof:name":"Osterholt Bv",
    "wof:placetype":"venue"
},
  "geometry": {"coordinates":[4.521974,51.814999],"type":"Point"}
}