{
  "type": "Feature",
  "properties": {
    "addr:full":"Den Dries 17 Gilze Noord-Brabant 5126 EC",
    "addr:housenumber":"17",
    "addr:postcode":"5126 ec",
    "addr:street":"Den Dries",
    "iso:country":"NL",
    "sg:address":"Den Dries 17",
    "sg:city":"Gilze",
    "sg:orig_category":"Administratie- En Boekhoudkantoren",
    "sg:phone":"+31 161 452 191",
    "sg:postcode":"5126 EC",
    "sg:province":"Noord-Brabant",
    "wof:name":"Paradox",
    "wof:placetype":"venue"
},
  "geometry": {"coordinates":[4.946111,51.537975],"type":"Point"}
}