{
  "type": "Feature",
  "properties": {
    "iso:country":"NL",
    "sg:address":"Batelaar 29",
    "sg:city":"Oosterhout Nb",
    "sg:orig_category":"Voegwerken",
    "sg:phone":"+31 162 454 034",
    "sg:postcode":"4907 KH",
    "sg:province":"North Brabant",
    "wof:name":"Ernst",
    "wof:placetype":"venue"
},
  "geometry": {"coordinates":[4.864761,51.661282],"type":"Point"}
}