{
  "type": "Feature",
  "properties": {
    "addr:full":"Oudegr 106-108 Utrecht Utrecht 3511 AV",
    "addr:housenumber":"106-108",
    "addr:postcode":"3511 av",
    "iso:country":"NL",
    "sg:address":"Oudegr 106-108",
    "sg:city":"Utrecht",
    "sg:orig_category":"Onroerende Goederen",
    "sg:phone":"+31 30 231 6114",
    "sg:postcode":"3511 AV",
    "sg:province":"Utrecht",
    "wof:name":"Lisman Bv",
    "wof:placetype":"venue"
},
  "geometry": {"coordinates":[5.115405,52.088932],"type":"Point"}
}