{
  "type": "Feature",
  "properties": {
    "iso:country":"NL",
    "sg:address":"Diamantln 15",
    "sg:city":"Hoofddorp",
    "sg:orig_category":"Kabelwerken",
    "sg:phone":"+31 72 518 6900",
    "sg:postcode":"2132 WV",
    "sg:province":"Noord-Holland",
    "sg:website":"http://www.multikabel.nl",
    "wof:name":"Communikabel Nv",
    "wof:placetype":"venue"
},
  "geometry": {"coordinates":[4.6854801178,52.2921333313],"type":"Point"}
}