{
  "type": "Feature",
  "properties": {
    "addr:full":"Verzetstr 29 Holten Overijssel 7451 DL",
    "addr:housenumber":"29",
    "addr:postcode":"7451 dl",
    "addr:street":"Verzetstr",
    "iso:country":"NL",
    "sg:address":"Verzetstr 29",
    "sg:city":"Holten",
    "sg:orig_category":"Plafonds",
    "sg:phone":"+31 6 27082485",
    "sg:postcode":"7451 DL",
    "sg:province":"Overijssel",
    "wof:name":"Sterling",
    "wof:placetype":"venue"
},
  "geometry": {"coordinates":[6.408637,52.278027],"type":"Point"}
}