{
  "type": "Feature",
  "properties": {
    "addr:full":"Tjerk Hiddesstraat 163 Zandvoort Noord-Holland 2041 JK",
    "addr:housenumber":"163",
    "addr:postcode":"zandvoort;2041 jk",
    "addr:street":"Tjerk Hiddesstraat",
    "iso:country":"NL",
    "sg:address":"Tjerk Hiddesstraat 163",
    "sg:city":"Zandvoort",
    "sg:classifiers":[
        {
            "category":"Fast Food",
            "type":"Food & Drink"
        }
    ],
    "sg:phone":"+31 6 28458303",
    "sg:postcode":"2041 JK",
    "sg:province":"Noord-Holland",
    "sg:tags":[
        "afhaal",
        "restaurant"
    ],
    "wof:name":"Marco",
    "wof:placetype":"venue"
},
  "geometry": {"coordinates":[4.533427,52.382431],"type":"Point"}
}