{
  "type": "Feature",
  "properties": {
    "addr:full":"J C Van Wijkstraat 62 Anna Paulowna North Holland 1761 CR",
    "addr:housenumber":"62",
    "addr:postcode":"1761 cr",
    "addr:street":"J;Van Wijkstraat",
    "iso:country":"NL",
    "sg:address":"J C Van Wijkstraat 62",
    "sg:city":"Anna Paulowna",
    "sg:orig_category":"Kappers",
    "sg:phone":"+31 223 533 526",
    "sg:postcode":"1761 CR",
    "sg:province":"North Holland",
    "wof:name":"Op En Top",
    "wof:placetype":"venue"
},
  "geometry": {"coordinates":[4.82521,52.861042],"type":"Point"}
}