{
  "type": "Feature",
  "properties": {
    "addr:full":"Pluggematen 6 Steenwijk Overijssel 8331 TV",
    "addr:housenumber":"6",
    "addr:postcode":"8331 tv",
    "addr:street":"Pluggematen",
    "iso:country":"NL",
    "sg:address":"Pluggematen 6",
    "sg:city":"Steenwijk",
    "sg:orig_category":"Verhuur Bouwmachines",
    "sg:phone":"+31 521 514 135",
    "sg:postcode":"8331 TV",
    "sg:province":"Overijssel",
    "wof:name":"Gereedschapnet",
    "wof:placetype":"venue"
},
  "geometry": {"coordinates":[6.092462,52.780449],"type":"Point"}
}