{
  "type": "Feature",
  "properties": {
    "iso:country":"NL",
    "sg:address":"Sumatrastr 47",
    "sg:city":"Amsterdam",
    "sg:orig_category":"Koffie- En Theehuizen",
    "sg:phone":"+31 20 692 2968",
    "sg:postcode":"1094 LN",
    "sg:province":"Noord-Holland",
    "wof:name":"Trefpunt, Het",
    "wof:placetype":"venue"
},
  "geometry": {"coordinates":[4.935802,52.363243],"type":"Point"}
}