{
  "type": "Feature",
  "properties": {
    "addr:full":"Sumatrastr 47 Amsterdam Noord-Holland 1094 LN",
    "addr:housenumber":"47",
    "addr:postcode":"1094 ln",
    "addr:street":"Sumatrastr",
    "iso:country":"NL",
    "sg:address":"Sumatrastr 47",
    "sg:city":"Amsterdam",
    "sg:orig_category":"Koffie- En Theehuizen",
    "sg:phone":"+31 20 692 2968",
    "sg:postcode":"1094 LN",
    "sg:province":"Noord-Holland",
    "wof:name":"Trefpunt, Het",
    "wof:placetype":"venue"
},
  "geometry": {"coordinates":[4.935802,52.363243],"type":"Point"}
}