{
  "type": "Feature",
  "properties": {
    "addr:full":"Rodenrijseweg 7 Berkel En Rodenrijs Zuid-Holland 2651 BM",
    "addr:housenumber":"7",
    "addr:postcode":"2651 bm",
    "addr:street":"Rodenrijseweg",
    "iso:country":"NL",
    "sg:address":"Rodenrijseweg 7",
    "sg:city":"Berkel En Rodenrijs",
    "sg:orig_category":"Huisdierenvoer Fab",
    "sg:phone":"+31 10 511 2144",
    "sg:postcode":"2651 BM",
    "sg:province":"Zuid-Holland",
    "wof:name":"Treurniet Mengvoeders Bv",
    "wof:placetype":"venue"
},
  "geometry": {"coordinates":[4.475164,51.992744],"type":"Point"}
}