{
  "type": "Feature",
  "properties": {
    "addr:full":"K Tiendewg 1 Gouda South Holland 2801 JS",
    "addr:housenumber":"1",
    "addr:postcode":"2801 js",
    "addr:street":"Tiendewg",
    "iso:country":"NL",
    "sg:address":"K Tiendewg 1",
    "sg:city":"Gouda",
    "sg:orig_category":"Kantoorbenodigdheden",
    "sg:phone":"+31 182 515 155",
    "sg:postcode":"2801 JS",
    "sg:province":"South Holland",
    "sg:website":"http://www.mado.nl",
    "wof:name":"Mado Gouda Bv",
    "wof:placetype":"venue"
},
  "geometry": {"coordinates":[4.7117519379,52.0117378235],"type":"Point"}
}