{
  "type": "Feature",
  "properties": {
    "addr:full":"K Doormanln 52 Bussum Noord-Holland 1403 TN",
    "addr:housenumber":"52",
    "addr:postcode":"1403",
    "addr:street":"Doormanln",
    "iso:country":"NL",
    "sg:address":"K Doormanln 52",
    "sg:city":"Bussum",
    "sg:orig_category":"Apotheken",
    "sg:phone":"+31 35 693 1618",
    "sg:postcode":"1403 TN",
    "sg:province":"Noord-Holland",
    "wof:name":"Bussum-Zuid",
    "wof:placetype":"venue"
},
  "geometry": {"coordinates":[5.177812,52.265961],"type":"Point"}
}