{
  "type": "Feature",
  "properties": {
    "iso:country":"NL",
    "sg:address":"Schapenweide 6",
    "sg:city":"Breda",
    "sg:orig_category":"Ongediertebestrijding En Ontsmetting",
    "sg:phone":"+31 76 548 6660",
    "sg:postcode":"4824 AN",
    "sg:province":"North Brabant",
    "sg:website":"http://www.anticimex.nl",
    "wof:name":"Anticimex Benelux Bv",
    "wof:placetype":"venue"
},
  "geometry": {"coordinates":[4.758748,51.612152],"type":"Point"}
}