{
  "type": "Feature",
  "properties": {
    "addr:full":"Vleugelnootln 30 Zoeterwoude Zuid-Holland 2382 EN",
    "addr:housenumber":"30",
    "addr:postcode":"2382 en",
    "addr:street":"Vleugelnootln",
    "iso:country":"NL",
    "sg:address":"Vleugelnootln 30",
    "sg:city":"Zoeterwoude",
    "sg:orig_category":"Adviesbureaus Elektrotechniek",
    "sg:phone":"+31 71 589 7597",
    "sg:postcode":"2382 EN",
    "sg:province":"Zuid-Holland",
    "wof:name":"Oish Bv",
    "wof:placetype":"venue"
},
  "geometry": {"coordinates":[4.520232,52.143734],"type":"Point"}
}