{
  "type": "Feature",
  "properties": {
    "addr:full":"St Antoniusstr 6A Bergen Lb Limburg 5854 CM",
    "addr:housenumber":"6a",
    "addr:postcode":"lb;5854 cm",
    "iso:country":"NL",
    "sg:address":"St Antoniusstr 6A",
    "sg:city":"Bergen Lb",
    "sg:orig_category":"Bloemen En Planten",
    "sg:phone":"+31 485 341 421",
    "sg:postcode":"5854 CM",
    "sg:province":"Limburg",
    "wof:name":"Lucassen",
    "wof:placetype":"venue"
},
  "geometry": {"coordinates":[-93.129936,36.705662],"type":"Point"}
}