{
  "type": "Feature",
  "properties": {
    "addr:full":"Raadhuisstr 2 Druten Gelderland 6651 BZ",
    "addr:housenumber":"2",
    "addr:postcode":"6651 bz",
    "addr:street":"Raadhuisstr",
    "iso:country":"NL",
    "sg:address":"Raadhuisstr 2",
    "sg:city":"Druten",
    "sg:orig_category":"Scholen Voor Basisonderwijs",
    "sg:phone":"+31 487 512 694",
    "sg:postcode":"6651 BZ",
    "sg:province":"Gelderland",
    "wof:name":"De Dijk",
    "wof:placetype":"venue"
},
  "geometry": {"coordinates":[5.604633,51.886333],"type":"Point"}
}