{
  "type": "Feature",
  "properties": {
    "addr:full":"Postbus 130 Zeewolde Flevoland 3890 AC",
    "addr:housenumber":"130",
    "addr:postcode":"3890 ac",
    "addr:street":"Postbus;Flevoland",
    "iso:country":"NL",
    "sg:address":"Postbus 130",
    "sg:city":"Zeewolde",
    "sg:orig_category":"Adviesbureaus Bedrijfsorganisatie",
    "sg:phone":"+31 36 522 2123",
    "sg:postcode":"3890 AC",
    "sg:province":"Flevoland",
    "wof:name":"Perceptie",
    "wof:placetype":"venue"
},
  "geometry": {"coordinates":[5.54213,52.332512],"type":"Point"}
}