{
  "type": "Feature",
  "properties": {
    "addr:full":"Venepad 5-1 Rutten Flevoland 8313 PD",
    "addr:housenumber":"5-1",
    "addr:postcode":"8313 pd",
    "addr:street":"Venepad;Flevoland",
    "iso:country":"NL",
    "sg:address":"Venepad 5-1",
    "sg:city":"Rutten",
    "sg:orig_category":"Ongediertebestrijding En Ontsmetting",
    "sg:phone":"+31 527 262 889",
    "sg:postcode":"8313 PD",
    "sg:province":"Flevoland",
    "wof:name":"Holtland, W A",
    "wof:placetype":"venue"
},
  "geometry": {"coordinates":[5.699579,52.788471],"type":"Point"}
}