{
  "type": "Feature",
  "properties": {
    "addr:full":"Laan Van Vollenhove 2793 Zeist Utrecht 3706 AJ",
    "addr:housenumber":"2793",
    "addr:postcode":"3706 aj",
    "addr:street":"Laan Van Vollenhove",
    "iso:country":"NL",
    "sg:address":"Laan Van Vollenhove 2793",
    "sg:city":"Zeist",
    "sg:orig_category":"Wasserettes And Stomerijen",
    "sg:phone":"+31 30 695 8005",
    "sg:postcode":"3706 AJ",
    "sg:province":"Utrecht",
    "wof:name":"Het Kleding Vakhuis",
    "wof:placetype":"venue"
},
  "geometry": {"coordinates":[5.2232952118,52.1008720398],"type":"Point"}
}