{
  "type": "Feature",
  "properties": {
    "iso:country":"NL",
    "sg:address":"Nicehof 8",
    "sg:city":"Eindhoven",
    "sg:orig_category":"Arbo- En Bedrijfsgezondheids- Diensten",
    "sg:phone":"+31 40 295 2293",
    "sg:postcode":"5627 GC",
    "sg:province":"Noord-Brabant",
    "wof:name":"Qm En T",
    "wof:placetype":"venue"
},
  "geometry": {"coordinates":[5.445492,51.478859],"type":"Point"}
}