{
  "type": "Feature",
  "properties": {
    "addr:full":"Kortemeestraat 27 Bergen Op Zoom Noord-Brabant 4611 TL",
    "addr:housenumber":"27",
    "addr:postcode":"4611 tl",
    "addr:street":"Kortemeestraat",
    "iso:country":"NL",
    "sg:address":"Kortemeestraat 27",
    "sg:city":"Bergen Op Zoom",
    "sg:orig_category":"Bloemen And Planten",
    "sg:phone":"+31 164 255 563",
    "sg:postcode":"4611 TL",
    "sg:province":"Noord-Brabant",
    "wof:name":"Bloemenshop 'T Vierkantje",
    "wof:placetype":"venue"
},
  "geometry": {"coordinates":[4.28634,51.495644],"type":"Point"}
}