{
  "type": "Feature",
  "properties": {
    "iso:country":"NL",
    "sg:address":"Geldelozewg 33",
    "sg:city":"Hoorn Nh",
    "sg:orig_category":"Medische Installaties En Instrumenten",
    "sg:phone":"+31 229 211 728",
    "sg:postcode":"1625 NW",
    "sg:province":"Noord-Holland",
    "wof:name":"Trango Bv",
    "wof:placetype":"venue"
},
  "geometry": {"coordinates":[5.048878,52.650879],"type":"Point"}
}