{
  "type": "Feature",
  "properties": {
    "addr:full":"Mr J C Buhrmannln 103 Weesp Noord-Holland 1381 GK",
    "addr:housenumber":"103",
    "addr:postcode":"1381 gk",
    "addr:street":"Mr J C Buhrmannln",
    "iso:country":"NL",
    "sg:address":"Mr J C Buhrmannln 103",
    "sg:city":"Weesp",
    "sg:orig_category":"Schilders",
    "sg:phone":"+31 294 418 513",
    "sg:postcode":"1381 GK",
    "sg:province":"Noord-Holland",
    "wof:name":"Bouman, Schilders",
    "wof:placetype":"venue"
},
  "geometry": {"coordinates":[5.03828,52.308315],"type":"Point"}
}