{
  "type": "Feature",
  "properties": {
    "addr:full":"Commandeursweg 85 Bennekom Gelderland 6721 ZL",
    "addr:housenumber":"85",
    "addr:postcode":"6721 zl",
    "addr:street":"Commandeursweg;Gelderland",
    "iso:country":"NL",
    "sg:address":"Commandeursweg 85",
    "sg:city":"Bennekom",
    "sg:classifiers":[
        {
            "category":"Education",
            "subcategory":"Preschool",
            "type":"Public Place"
        }
    ],
    "sg:phone":"+31 318 415 851",
    "sg:postcode":"6721 ZL",
    "sg:province":"Gelderland",
    "sg:tags":[
        "kleuteronderwijs",
        "basis-"
    ],
    "wof:name":"Openbare Basisschool De Prinssenakker",
    "wof:placetype":"venue"
},
  "geometry": {"coordinates":[5.675792,52.000942],"type":"Point"}
}