{
  "type": "Feature",
  "properties": {
    "addr:full":"Prinsengr 444 Amsterdam Noord-Holland 1017 KE",
    "addr:housenumber":"444",
    "addr:postcode":"1017 ke",
    "iso:country":"NL",
    "sg:address":"Prinsengr 444",
    "sg:city":"Amsterdam",
    "sg:classifiers":[
        {
            "category":"Travel",
            "subcategory":"Hotels & Motels",
            "type":"Entertainment"
        }
    ],
    "sg:phone":"+31 20 620 1212",
    "sg:postcode":"1017 KE",
    "sg:province":"Noord-Holland",
    "sg:website":"http://www.dtfh.nl",
    "wof:name":"Dikker & Thijs, Fenice Hotel",
    "wof:placetype":"venue"
},
  "geometry": {"coordinates":[4.883733,52.365059],"type":"Point"}
}