{
  "type": "Feature",
  "properties": {
    "iso:country":"NL",
    "sg:address":"Wetterkant 8",
    "sg:city":"Gorredyk",
    "sg:orig_category":"Machineonderhoud En -Reparatie",
    "sg:phone":"+31 6 54936610",
    "sg:postcode":"8401 GC",
    "sg:province":"Friesland",
    "wof:name":"Zeinstra",
    "wof:placetype":"venue"
},
  "geometry": {"coordinates":[6.06447,53.00478],"type":"Point"}
}