{
  "type": "Feature",
  "properties": {
    "addr:full":"Ceintuurbaan 396I Amsterdam Noord-Holland 1073 EN",
    "addr:housenumber":"396i",
    "addr:postcode":"1073 en",
    "addr:street":"Ceintuurbaan",
    "iso:country":"NL",
    "sg:address":"Ceintuurbaan 396I",
    "sg:city":"Amsterdam",
    "sg:orig_category":"Adviesbureaus Bedrijfsorganisatie",
    "sg:phone":"+31 20 676 1125",
    "sg:postcode":"1073 EN",
    "sg:province":"Noord-Holland",
    "wof:name":"Belt, Jan Van Den",
    "wof:placetype":"venue"
},
  "geometry": {"coordinates":[4.900919,52.354572],"type":"Point"}
}