{
  "type": "Feature",
  "properties": {
    "addr:full":"Skuniadyk 10 Bakhuizen Provincie Friesland 8574 TR",
    "addr:housenumber":"10",
    "addr:postcode":"8574 tr",
    "addr:street":"Skuniadyk;Provincie Friesland",
    "iso:country":"NL",
    "sg:address":"Skuniadyk 10",
    "sg:city":"Bakhuizen",
    "sg:orig_category":"Boekhouders",
    "sg:phone":"+31 514 581 465",
    "sg:postcode":"8574 TR",
    "sg:province":"Provincie Friesland",
    "wof:name":"Administratie- En Adviesbureau De Boer",
    "wof:placetype":"venue"
},
  "geometry": {"coordinates":[5.458756,52.864941],"type":"Point"}
}