{
  "type": "Feature",
  "properties": {
    "iso:country":"NL",
    "sg:address":"Meeuwerderwg 109",
    "sg:city":"Groningen",
    "sg:classifiers":[
        {
            "category":"Food & Beverages",
            "subcategory":"Bakery",
            "type":"Retail Goods"
        }
    ],
    "sg:phone":"+31 50 312 4690",
    "sg:postcode":"9724 ER",
    "sg:province":"Groningen",
    "sg:tags":[
        "brood",
        "en",
        "banket"
    ],
    "wof:name":"Stoethuus",
    "wof:placetype":"venue"
},
  "geometry": {"coordinates":[6.578806,53.211021],"type":"Point"}
}