{
  "type": "Feature",
  "properties": {
    "iso:country":"NL",
    "sg:address":"Bosweg 23",
    "sg:city":"Hoogersmilde",
    "sg:orig_category":"Kampeerterreinen",
    "sg:phone":"+31 592 459 356",
    "sg:postcode":"9423 TA",
    "sg:province":"Provincie Drenthe",
    "wof:name":"De Reeenwissel",
    "wof:placetype":"venue"
},
  "geometry": {"coordinates":[6.3812308311,52.9059486389],"type":"Point"}
}