{
  "type": "Feature",
  "properties": {
    "iso:country":"NL",
    "sg:address":"Kl Hof 29",
    "sg:city":"Vleuten",
    "sg:orig_category":"Administratie- En Boekhoudkantoren",
    "sg:phone":"+31 30 677 5364",
    "sg:postcode":"3451 LN",
    "sg:province":"Utrecht",
    "wof:name":"Break Even Point",
    "wof:placetype":"venue"
},
  "geometry": {"coordinates":[5.017655,52.107643],"type":"Point"}
}