{
  "type": "Feature",
  "properties": {
    "addr:full":"Kasteelln 5 Schipluiden Zuid-Holland 2636 HW",
    "addr:housenumber":"5",
    "addr:postcode":"2636 hw",
    "addr:street":"Kasteelln",
    "iso:country":"NL",
    "sg:address":"Kasteelln 5",
    "sg:city":"Schipluiden",
    "sg:orig_category":"Woningbouw- Verenigingen En -Stichtingen",
    "sg:phone":"+31 15 380 9363",
    "sg:postcode":"2636 HW",
    "sg:province":"Zuid-Holland",
    "wof:name":"St Willibrordus",
    "wof:placetype":"venue"
},
  "geometry": {"coordinates":[4.3159098625,51.977180481],"type":"Point"}
}