{
  "type": "Feature",
  "properties": {
    "iso:country":"NL",
    "sg:address":"Pannekoekstraat 35A-37A",
    "sg:city":"Rotterdam",
    "sg:orig_category":"Werving And Selectie Van Tijdelijk Personeel And Uitzendkantoren",
    "sg:phone":"+31 10 240 9060",
    "sg:postcode":"3011 LC",
    "sg:province":"Zuid-Holland",
    "wof:name":"Ubn Uizendburo",
    "wof:placetype":"venue"
},
  "geometry": {"coordinates":[4.4876270294,51.9233322144],"type":"Point"}
}