{
  "type": "Feature",
  "properties": {
    "iso:country":"NL",
    "sg:address":"Europawg 1",
    "sg:city":"Vleuten",
    "sg:orig_category":"Sportverenigingen En Ontspannings- Verenigingen",
    "sg:phone":"+31 30 666 3235",
    "sg:postcode":"3451 HG",
    "sg:province":"Utrecht",
    "wof:name":"Fletiomare Hockeycl",
    "wof:placetype":"venue"
},
  "geometry": {"coordinates":[5.01342,52.105862],"type":"Point"}
}