{
  "type": "Feature",
  "properties": {
    "iso:country":"NL",
    "sg:address":"Economiestr 39",
    "sg:city":"Hoensbroek",
    "sg:orig_category":"Administratie- En Boekhoudkantoren",
    "sg:phone":"+31 45 533 1548",
    "sg:postcode":"6433 KC",
    "sg:province":"Limburg",
    "wof:name":"Pulacon",
    "wof:placetype":"venue"
},
  "geometry": {"coordinates":[5.933451,50.90498],"type":"Point"}
}