{
  "type": "Feature",
  "properties": {
    "addr:full":"Baroniehof 214 Helmond Noord-Brabant 5709 HD",
    "addr:housenumber":"214",
    "addr:postcode":"5709 hd",
    "addr:street":"Baroniehof",
    "iso:country":"NL",
    "sg:address":"Baroniehof 214",
    "sg:city":"Helmond",
    "sg:orig_category":"Peuterspeelzalen",
    "sg:phone":"+31 492 511 263",
    "sg:postcode":"5709 HD",
    "sg:province":"Noord-Brabant",
    "wof:name":"Ukkepuk",
    "wof:placetype":"venue"
},
  "geometry": {"coordinates":[5.700856,51.473007],"type":"Point"}
}