{
  "type": "Feature",
  "properties": {
    "addr:full":"Doelenpln 10 Delft South Holland 2611 BP",
    "addr:housenumber":"10",
    "addr:postcode":"2611 bp",
    "addr:street":"Doelenpln",
    "iso:country":"NL",
    "sg:address":"Doelenpln 10",
    "sg:city":"Delft",
    "sg:classifiers":[
        {
            "category":"Travel",
            "subcategory":"Hotels & Motels",
            "type":"Entertainment"
        }
    ],
    "sg:phone":"+31 15 212 6046",
    "sg:postcode":"2611 BP",
    "sg:province":"South Holland",
    "sg:website":"http://www.hoteldeplataan.nl",
    "wof:name":"Plataan, De",
    "wof:placetype":"venue"
},
  "geometry": {"coordinates":[4.358304,52.014385],"type":"Point"}
}