{
  "type": "Feature",
  "properties": {
    "addr:full":"A Jacobsstr 81 Heemskerk Noord-Holland 1963 CB",
    "addr:housenumber":"81",
    "addr:postcode":"1963 cb",
    "iso:country":"NL",
    "sg:address":"A Jacobsstr 81",
    "sg:city":"Heemskerk",
    "sg:orig_category":"Artsen - Huisartsen",
    "sg:phone":"+31 251 245 390",
    "sg:postcode":"1963 CB",
    "sg:province":"Noord-Holland",
    "wof:name":"Schutte, C Y",
    "wof:placetype":"venue"
},
  "geometry": {"coordinates":[4.685673,52.518982],"type":"Point"}
}