{
  "type": "Feature",
  "properties": {
    "addr:full":"Grote Marktstraat 20 'S Gravenhage Zuid-Holland 2511 BJ",
    "addr:housenumber":"20",
    "addr:postcode":"2511 bj",
    "addr:street":"Grote Marktstraat;' S",
    "iso:country":"NL",
    "sg:address":"Grote Marktstraat 20",
    "sg:city":"'S Gravenhage",
    "sg:orig_category":"Binnenhuisarchitecten",
    "sg:phone":"+31 70 360 3078",
    "sg:postcode":"2511 BJ",
    "sg:province":"Zuid-Holland",
    "wof:name":"W Stallinga",
    "wof:placetype":"venue"
},
  "geometry": {"coordinates":[4.31627,52.07896],"type":"Point"}
}