{
  "type": "Feature",
  "properties": {
    "addr:full":"Loseweg 59 Apeldoorn Gelderland 7315 BC",
    "addr:housenumber":"59",
    "addr:postcode":"7315 bc",
    "addr:street":"Loseweg;Gelderland",
    "iso:country":"NL",
    "sg:address":"Loseweg 59",
    "sg:city":"Apeldoorn",
    "sg:orig_category":"Kledingzaken",
    "sg:phone":"+31 55 521 3709",
    "sg:postcode":"7315 BC",
    "sg:province":"Gelderland",
    "wof:name":"Oxener Schoenen Bv",
    "wof:placetype":"venue"
},
  "geometry": {"coordinates":[5.951255,52.225876],"type":"Point"}
}