{
  "type": "Feature",
  "properties": {
    "addr:full":"Westwal 11 Urk Flevoland 8321 WG",
    "addr:housenumber":"11",
    "addr:postcode":"8321 wg",
    "addr:street":"Westwal;Flevoland",
    "iso:country":"NL",
    "sg:address":"Westwal 11",
    "sg:city":"Urk",
    "sg:orig_category":"Aggregaten",
    "sg:phone":"+31 527 685 358",
    "sg:postcode":"8321 WG",
    "sg:province":"Flevoland",
    "wof:name":"Alpha Shipping Vof",
    "wof:placetype":"venue"
},
  "geometry": {"coordinates":[5.619126,52.653732],"type":"Point"}
}