{
  "type": "Feature",
  "properties": {
    "addr:full":"Onrust 26 Zwijndrecht South Holland 3331 GN",
    "addr:housenumber":"26",
    "addr:postcode":"3331 gn",
    "addr:street":"Onrust",
    "iso:country":"NL",
    "sg:address":"Onrust 26",
    "sg:city":"Zwijndrecht",
    "sg:orig_category":"Autokeuringen",
    "sg:phone":"+31 78 612 8881",
    "sg:postcode":"3331 GN",
    "sg:province":"South Holland",
    "wof:name":"Garage Attent",
    "wof:placetype":"venue"
},
  "geometry": {"coordinates":[4.63841,51.823116],"type":"Point"}
}