{
  "type": "Feature",
  "properties": {
    "iso:country":"NL",
    "sg:address":"Passage Zuidpoort 1-3",
    "sg:city":"Breda",
    "sg:orig_category":"Wereldwinkels",
    "sg:phone":"+31 76 522 8585",
    "sg:postcode":"4811 NT",
    "sg:province":"Noord-Brabant",
    "wof:name":"Wereldwinkel",
    "wof:placetype":"venue"
},
  "geometry": {"coordinates":[4.7779831886,51.582359314],"type":"Point"}
}