{
  "type": "Feature",
  "properties": {
    "iso:country":"NL",
    "sg:address":"Oude Oeverstr 120",
    "sg:city":"Arnhem",
    "sg:orig_category":"Kinderopvang",
    "sg:phone":"+31 26 353 7410",
    "sg:postcode":"6811 JZ",
    "sg:province":"Gelderland",
    "sg:website":"http://www.kintent.nl",
    "wof:name":"Kintent",
    "wof:placetype":"venue"
},
  "geometry": {"coordinates":[5.903438,51.981216],"type":"Point"}
}