{
  "type": "Feature",
  "properties": {
    "iso:country":"NL",
    "sg:address":"Weerdingerkanaal Nz 150",
    "sg:city":"Nieuw Weerdinge",
    "sg:orig_category":"Verlichting And Huishoudartikelen",
    "sg:phone":"+31 591 521 363",
    "sg:postcode":"7831 HK",
    "sg:province":"Drenthe",
    "wof:name":"Wachtmeester Woninginrichting",
    "wof:placetype":"venue"
},
  "geometry": {"coordinates":[6.985349,52.857094],"type":"Point"}
}