{
  "type": "Feature",
  "properties": {
    "addr:full":"Weerdingerkanaal Nz 150 Nieuw Weerdinge Drenthe 7831 HK",
    "addr:housenumber":"150",
    "addr:postcode":"7831 hk",
    "addr:street":"Weerdingerkanaal Nz;Nieuw Weerdinge",
    "iso:country":"NL",
    "sg:address":"Weerdingerkanaal Nz 150",
    "sg:city":"Nieuw Weerdinge",
    "sg:orig_category":"Verlichting And Huishoudartikelen",
    "sg:phone":"+31 591 521 363",
    "sg:postcode":"7831 HK",
    "sg:province":"Drenthe",
    "wof:name":"Wachtmeester Woninginrichting",
    "wof:placetype":"venue"
},
  "geometry": {"coordinates":[6.985349,52.857094],"type":"Point"}
}