{
  "type": "Feature",
  "properties": {
    "addr:full":"Schoutenstraat 14 Utrecht Utrecht 3512 GB",
    "addr:housenumber":"14",
    "addr:postcode":"3512 gb",
    "addr:street":"Schoutenstraat",
    "iso:country":"NL",
    "sg:address":"Schoutenstraat 14",
    "sg:city":"Utrecht",
    "sg:orig_category":"Werving And Selectie Van Tijdelijk Personeel And Uitzendkantoren",
    "sg:phone":"+31 30 236 8823",
    "sg:postcode":"3512 GB",
    "sg:province":"Utrecht",
    "wof:name":"Merit",
    "wof:placetype":"venue"
},
  "geometry": {"coordinates":[5.1190271378,52.0927734375],"type":"Point"}
}