{
  "type": "Feature",
  "properties": {
    "addr:full":"L B Pearsonstraat 17 Groningen Groningen 9728 WR",
    "addr:housenumber":"17",
    "addr:postcode":"9728 wr",
    "addr:street":"L B Pearsonstraat",
    "iso:country":"NL",
    "sg:address":"L B Pearsonstraat 17",
    "sg:city":"Groningen",
    "sg:orig_category":"Verhuur Audiovisuele Apparatuur",
    "sg:phone":"+31 50 525 5721",
    "sg:postcode":"9728 WR",
    "sg:province":"Groningen",
    "wof:name":"Pag",
    "wof:placetype":"venue"
},
  "geometry": {"coordinates":[6.553382,53.184483],"type":"Point"}
}