{
  "type": "Feature",
  "properties": {
    "addr:full":"Kromstraat 23 Veldhoven Noord-Brabant 5504 BA",
    "addr:housenumber":"23",
    "addr:postcode":"5504 ba",
    "addr:street":"Kromstraat",
    "iso:country":"NL",
    "sg:address":"Kromstraat 23",
    "sg:city":"Veldhoven",
    "sg:classifiers":[
        {
            "category":"Food & Beverages",
            "subcategory":"Fruits & Vegetables",
            "type":"Retail Goods"
        }
    ],
    "sg:phone":"+31 40 253 7536",
    "sg:postcode":"5504 BA",
    "sg:province":"Noord-Brabant",
    "sg:tags":[
        "groenten"
    ],
    "wof:name":"Vershof Kooiman",
    "wof:placetype":"venue"
},
  "geometry": {"coordinates":[5.393842,51.403397],"type":"Point"}
}