{
  "type": "Feature",
  "properties": {
    "addr:full":"A Vd Heuvelstr 29 Bunnik Utrecht 3981 CT",
    "addr:housenumber":"29",
    "addr:postcode":"3981 ct",
    "addr:street":"A",
    "iso:country":"NL",
    "sg:address":"A Vd Heuvelstr 29",
    "sg:city":"Bunnik",
    "sg:orig_category":"Administratie- En Boekhoudkantoren",
    "sg:phone":"+31 30 656 2992",
    "sg:postcode":"3981 CT",
    "sg:province":"Utrecht",
    "wof:name":"Baken Bunnik",
    "wof:placetype":"venue"
},
  "geometry": {"coordinates":[5.20049,52.065277],"type":"Point"}
}