{
  "type": "Feature",
  "properties": {
    "iso:country":"NL",
    "sg:address":"Lyceumln 12",
    "sg:city":"Stadskanaal",
    "sg:orig_category":"Onderhoudswerken",
    "sg:phone":"+31 599 653 034",
    "sg:postcode":"9503 BH",
    "sg:province":"Groningen",
    "wof:name":"Vries, De",
    "wof:placetype":"venue"
},
  "geometry": {"coordinates":[6.951802,52.985916],"type":"Point"}
}