{
  "type": "Feature",
  "properties": {
    "addr:full":"Lyceumln 12 Stadskanaal Groningen 9503 BH",
    "addr:housenumber":"12",
    "addr:postcode":"9503 bh",
    "addr:street":"Lyceumln",
    "iso:country":"NL",
    "sg:address":"Lyceumln 12",
    "sg:city":"Stadskanaal",
    "sg:orig_category":"Onderhoudswerken",
    "sg:phone":"+31 599 653 034",
    "sg:postcode":"9503 BH",
    "sg:province":"Groningen",
    "wof:name":"Vries, De",
    "wof:placetype":"venue"
},
  "geometry": {"coordinates":[6.951802,52.985916],"type":"Point"}
}