{
  "type": "Feature",
  "properties": {
    "addr:full":"Molenhoekpassage 4 Rosmalen North Brabant 5242 CZ",
    "addr:housenumber":"4",
    "addr:postcode":"5242",
    "addr:street":"Molenhoekpassage",
    "iso:country":"NL",
    "sg:address":"Molenhoekpassage 4",
    "sg:city":"Rosmalen",
    "sg:orig_category":"Fotozaken",
    "sg:phone":"+31 73 521 4691",
    "sg:postcode":"5242 CZ",
    "sg:province":"North Brabant",
    "wof:name":"Stijntjes",
    "wof:placetype":"venue"
},
  "geometry": {"coordinates":[5.366423,51.710289],"type":"Point"}
}