{
  "type": "Feature",
  "properties": {
    "addr:full":"Oisterwyksebaan 87 Tilburg North Brabant 5018 CA",
    "addr:housenumber":"87",
    "addr:postcode":"5018 ca",
    "addr:street":"Oisterwyksebaan",
    "iso:country":"NL",
    "sg:address":"Oisterwyksebaan 87",
    "sg:city":"Tilburg",
    "sg:orig_category":"Biljarts - Fabrieken",
    "sg:phone":"+31 13 535 7744",
    "sg:postcode":"5018 CA",
    "sg:province":"North Brabant",
    "wof:name":"Erp, Biljartmaker Frans Van",
    "wof:placetype":"venue"
},
  "geometry": {"coordinates":[5.106271,51.554928],"type":"Point"}
}