{
  "type": "Feature",
  "properties": {
    "addr:full":"Molenstr 109 Apeldoorn Gelderland 7321 BD",
    "addr:housenumber":"109",
    "addr:postcode":"7321 bd",
    "addr:street":"Molenstr;Gelderland",
    "iso:country":"NL",
    "sg:address":"Molenstr 109",
    "sg:city":"Apeldoorn",
    "sg:classifiers":[
        {
            "category":"Personal",
            "subcategory":"Nail Salon",
            "type":"Services"
        }
    ],
    "sg:phone":"+31 55 366 9940",
    "sg:postcode":"7321 BD",
    "sg:province":"Gelderland",
    "sg:tags":[
        "pedicure"
    ],
    "wof:name":"Brand, L H",
    "wof:placetype":"venue"
},
  "geometry": {"coordinates":[5.97822,52.21228],"type":"Point"}
}