{
  "type": "Feature",
  "properties": {
    "addr:full":"Onderlangs 16 Dirksland Zuid-Holland 3247 BL",
    "addr:housenumber":"16",
    "addr:postcode":"3247 bl",
    "addr:street":"Onderlangs",
    "iso:country":"NL",
    "sg:address":"Onderlangs 16",
    "sg:city":"Dirksland",
    "sg:classifiers":[
        {
            "category":"Shopping",
            "subcategory":"Gifts & Souvenirs",
            "type":"Retail Goods"
        }
    ],
    "sg:phone":"+31 187 605 354",
    "sg:postcode":"3247 BL",
    "sg:province":"Zuid-Holland",
    "sg:tags":[
        "geschenken"
    ],
    "wof:name":"Zero'S",
    "wof:placetype":"venue"
},
  "geometry": {"coordinates":[4.104471,51.748528],"type":"Point"}
}