{
  "type": "Feature",
  "properties": {
    "addr:full":"Lupineweg 70 Apeldoorn Gelderland 7325 AH",
    "addr:housenumber":"70",
    "addr:postcode":"7325 ah",
    "addr:street":"Lupineweg;Gelderland",
    "iso:country":"NL",
    "sg:address":"Lupineweg 70",
    "sg:city":"Apeldoorn",
    "sg:orig_category":"Binnenhuisarchitecten",
    "sg:phone":"+31 55 360 2615",
    "sg:postcode":"7325 AH",
    "sg:province":"Gelderland",
    "wof:name":"Interieurs Bjs",
    "wof:placetype":"venue"
},
  "geometry": {"coordinates":[6.016395,52.210911],"type":"Point"}
}