{
  "type": "Feature",
  "properties": {
    "iso:country":"NL",
    "sg:address":"P Krugerstr 1",
    "sg:city":"Katwyk Zh",
    "sg:orig_category":"Behangers",
    "sg:phone":"+31 71 407 2097",
    "sg:postcode":"2225 ZJ",
    "sg:province":"South Holland",
    "wof:name":"Leen Dijkhuizen",
    "wof:placetype":"venue"
},
  "geometry": {"coordinates":[4.39656,52.205101],"type":"Point"}
}