{
  "type": "Feature",
  "properties": {
    "addr:full":"Reinaldstraat 42 Valkenburg Lb Limburg 6301 EC",
    "addr:housenumber":"42",
    "addr:postcode":"lb;6301 ec",
    "addr:street":"Reinaldstraat",
    "iso:country":"NL",
    "sg:address":"Reinaldstraat 42",
    "sg:city":"Valkenburg Lb",
    "sg:orig_category":"Werving And Selectie Van Tijdelijk Personeel And Uitzendkantoren",
    "sg:phone":"+31 43 601 0318",
    "sg:postcode":"6301 EC",
    "sg:province":"Limburg",
    "wof:name":"Adecco",
    "wof:placetype":"venue"
},
  "geometry": {"coordinates":[5.8348522186,50.8658828735],"type":"Point"}
}