{
  "type": "Feature",
  "properties": {
    "addr:full":"Schoolpad 6 Den Oever Noord-Holland 1779 GH",
    "addr:housenumber":"6",
    "addr:postcode":"1779 gh",
    "addr:street":"Schoolpad",
    "iso:country":"NL",
    "sg:address":"Schoolpad 6",
    "sg:city":"Den Oever",
    "sg:orig_category":"Grondwerken",
    "sg:phone":"+31 227 511 363",
    "sg:postcode":"1779 GH",
    "sg:province":"Noord-Holland",
    "wof:name":"Heijblok & Znn, M S",
    "wof:placetype":"venue"
},
  "geometry": {"coordinates":[5.010367,52.930264],"type":"Point"}
}