{
  "type": "Feature",
  "properties": {
    "addr:full":"Bregwaard 77 Alkmaar Noord-Holland 1824 EJ",
    "addr:housenumber":"77",
    "addr:postcode":"1824 ej",
    "addr:street":"Bregwaard",
    "iso:country":"NL",
    "sg:address":"Bregwaard 77",
    "sg:city":"Alkmaar",
    "sg:orig_category":"Fotostudio'S And Fotografen",
    "sg:phone":"+31 72 562 4303",
    "sg:postcode":"1824 EJ",
    "sg:province":"Noord-Holland",
    "wof:name":"Rene",
    "wof:placetype":"venue"
},
  "geometry": {"coordinates":[4.749966,52.640423],"type":"Point"}
}