{
  "type": "Feature",
  "properties": {
    "addr:full":"Deurningerstraat 328 Enschede NL.08 7522 CN",
    "addr:housenumber":"328",
    "addr:postcode":"7522 cn",
    "addr:street":"Deurningerstraat",
    "iso:country":"NL",
    "sg:address":"Deurningerstraat 328",
    "sg:city":"Enschede",
    "sg:orig_category":"Public Relationbureaus",
    "sg:phone":"+31 53 430 2307",
    "sg:postcode":"7522 CN",
    "sg:province":"NL.08",
    "wof:name":"Engelen Marketing",
    "wof:placetype":"venue"
},
  "geometry": {"coordinates":[6.885573,52.235458],"type":"Point"}
}