{
  "type": "Feature",
  "properties": {
    "iso:country":"NL",
    "sg:address":"Starnheim 9",
    "sg:city":"Abcoude",
    "sg:orig_category":"Woonarken Bouw En Handel",
    "sg:phone":"+31 294 286 497",
    "sg:postcode":"1391 RV",
    "sg:province":"North Holland",
    "wof:name":"Bonstra, P W",
    "wof:placetype":"venue"
},
  "geometry": {"coordinates":[4.9646830559,52.2739906311],"type":"Point"}
}