{
  "type": "Feature",
  "properties": {
    "addr:full":"Hoogstraat 9 Toldijk Gelderland 7227 ND",
    "addr:housenumber":"9",
    "addr:postcode":"7227 nd",
    "addr:street":"Hoogstraat",
    "iso:country":"NL",
    "sg:address":"Hoogstraat 9",
    "sg:city":"Toldijk",
    "sg:orig_category":"Levende Dieren Gh",
    "sg:phone":"+31 575 451 328",
    "sg:postcode":"7227 ND",
    "sg:province":"Gelderland",
    "wof:name":"Veehandel G.J. Bulten",
    "wof:placetype":"venue"
},
  "geometry": {"coordinates":[6.224549,52.052608],"type":"Point"}
}