{
  "type": "Feature",
  "properties": {
    "addr:full":"Jan Mankeslaan 104 Heerenveen Friesland 8442 HS",
    "addr:housenumber":"104",
    "addr:postcode":"8442 hs",
    "addr:street":"Jan Mankeslaan",
    "iso:country":"NL",
    "sg:address":"Jan Mankeslaan 104",
    "sg:city":"Heerenveen",
    "sg:orig_category":"Vertaalbureaus",
    "sg:phone":"+31 513 622 641",
    "sg:postcode":"8442 HS",
    "sg:province":"Friesland",
    "wof:name":"Warmelink",
    "wof:placetype":"venue"
},
  "geometry": {"coordinates":[5.935452,52.954979],"type":"Point"}
}