{
  "type": "Feature",
  "properties": {
    "addr:full":"Noordvliet 49 Maassluis Zuid-Holland 3142 CJ",
    "addr:housenumber":"49",
    "addr:postcode":"3142 cj",
    "addr:street":"Noordvliet",
    "iso:country":"NL",
    "sg:address":"Noordvliet 49",
    "sg:city":"Maassluis",
    "sg:orig_category":"Herenkleding",
    "sg:phone":"+31 10 591 2061",
    "sg:postcode":"3142 CJ",
    "sg:province":"Zuid-Holland",
    "wof:name":"Hemert, Van",
    "wof:placetype":"venue"
},
  "geometry": {"coordinates":[4.249698,51.924328],"type":"Point"}
}