{
  "type": "Feature",
  "properties": {
    "addr:full":"Lagedk 31-33 Zaandyk North Holland 1544 BB",
    "addr:housenumber":"31-33",
    "addr:postcode":"1544 bb",
    "addr:street":"Zaandyk North",
    "iso:country":"NL",
    "sg:address":"Lagedk 31-33",
    "sg:city":"Zaandyk",
    "sg:orig_category":"Notarissen En Notariskantoren",
    "sg:phone":"+31 75 647 0570",
    "sg:postcode":"1544 BB",
    "sg:province":"North Holland",
    "wof:name":"Moesker, Mr A",
    "wof:placetype":"venue"
},
  "geometry": {"coordinates":[4.813439,52.473759],"type":"Point"}
}