{
  "type": "Feature",
  "properties": {
    "iso:country":"NL",
    "sg:address":"Overtoom 445",
    "sg:city":"Amsterdam",
    "sg:orig_category":"Diverse Grafische Activiteiten",
    "sg:phone":"+31 20 616 3104",
    "sg:postcode":"1054 KG",
    "sg:province":"Noord-Holland",
    "wof:name":"Studio Rm",
    "wof:placetype":"venue"
},
  "geometry": {"coordinates":[4.859715,52.358685],"type":"Point"}
}