{
  "type": "Feature",
  "properties": {
    "iso:country":"NL",
    "sg:address":"Velserduinpln 1",
    "sg:city":"Ymuiden",
    "sg:orig_category":"Banket",
    "sg:phone":"+31 255 511 340",
    "sg:postcode":"1971 BR",
    "sg:province":"Noord-Holland",
    "sg:website":"http://www.beeksmabanket.nl",
    "wof:name":"Beeksma Banket",
    "wof:placetype":"venue"
},
  "geometry": {"coordinates":[4.620306,52.460266],"type":"Point"}
}