{
  "type": "Feature",
  "properties": {
    "addr:full":"Forintdreef 75 Woerden Utrecht 3446 XS",
    "addr:housenumber":"75",
    "addr:postcode":"3446 xs",
    "addr:street":"Forintdreef",
    "iso:country":"NL",
    "sg:address":"Forintdreef 75",
    "sg:city":"Woerden",
    "sg:orig_category":"Adviesbureaus Bedrijfsorganisatie",
    "sg:phone":"+31 348 502 801",
    "sg:postcode":"3446 XS",
    "sg:province":"Utrecht",
    "sg:website":"http://www.denkar.nl",
    "wof:name":"Denkar Bv",
    "wof:placetype":"venue"
},
  "geometry": {"coordinates":[4.901868,52.080357],"type":"Point"}
}