{
  "type": "Feature",
  "properties": {
    "addr:full":"Vd Duyn V Maasdamstr 1 Culemborg Gelderland 4102 GB",
    "addr:housenumber":"1",
    "addr:postcode":"4102 gb",
    "addr:street":"Maasdamstr;Gelderland",
    "iso:country":"NL",
    "sg:address":"Vd Duyn V Maasdamstr 1",
    "sg:city":"Culemborg",
    "sg:classifiers":[
        {
            "category":"Bakery",
            "type":"Food & Drink"
        }
    ],
    "sg:phone":"+31 345 514 327",
    "sg:postcode":"4102 GB",
    "sg:province":"Gelderland",
    "sg:tags":[
        "brood",
        "banket"
    ],
    "wof:name":"J. Van Leeuwen",
    "wof:placetype":"venue"
},
  "geometry": {"coordinates":[5.22148,51.952175],"type":"Point"}
}