{
  "type": "Feature",
  "properties": {
    "addr:full":"Veeneggeweg 16 Geesteren Ov Overijssel 7678 RC",
    "addr:housenumber":"16",
    "addr:postcode":"7678 rc",
    "addr:street":"Veeneggeweg;Ov",
    "iso:country":"NL",
    "sg:address":"Veeneggeweg 16",
    "sg:city":"Geesteren Ov",
    "sg:orig_category":"Levende Dieren Gh",
    "sg:phone":"+31 546 631 738",
    "sg:postcode":"7678 RC",
    "sg:province":"Overijssel",
    "wof:name":"R.B.A. Kreuwel",
    "wof:placetype":"venue"
},
  "geometry": {"coordinates":[6.712163,52.398247],"type":"Point"}
}