{
  "type": "Feature",
  "properties": {
    "iso:country":"NL",
    "sg:address":"Mercuriuswg 19",
    "sg:city":"Zutphen",
    "sg:orig_category":"Machinehandel",
    "sg:phone":"+31 575 515 077",
    "sg:postcode":"7202 BS",
    "sg:province":"Gelderland",
    "wof:name":"Velde Bv, Ten",
    "wof:placetype":"venue"
},
  "geometry": {"coordinates":[6.197641,52.154068],"type":"Point"}
}