{
  "type": "Feature",
  "properties": {
    "addr:full":"Van Aelstlaan 93 Veldhoven Noord-Brabant 5503 BC",
    "addr:housenumber":"93",
    "addr:postcode":"5503 bc",
    "addr:street":"Van Aelstlaan",
    "iso:country":"NL",
    "sg:address":"Van Aelstlaan 93",
    "sg:city":"Veldhoven",
    "sg:orig_category":"Paramedische Behandelingen",
    "sg:phone":"+31 40 254 5054",
    "sg:postcode":"5503 BC",
    "sg:province":"Noord-Brabant",
    "wof:name":"Mevr E M Coppens",
    "wof:placetype":"venue"
},
  "geometry": {"coordinates":[5.401925,51.410416],"type":"Point"}
}