{
  "type": "Feature",
  "properties": {
    "addr:full":"Wilhelminastraat 22 Weesp Noord-Holland 1381 CL",
    "addr:housenumber":"22",
    "addr:postcode":"1381",
    "addr:street":"Wilhelminastraat",
    "iso:country":"NL",
    "sg:address":"Wilhelminastraat 22",
    "sg:city":"Weesp",
    "sg:orig_category":"Beursorganisaties And Standbouw",
    "sg:phone":"+31 294 480 634",
    "sg:postcode":"1381 CL",
    "sg:province":"Noord-Holland",
    "wof:name":"Liefting Services",
    "wof:placetype":"venue"
},
  "geometry": {"coordinates":[5.041517,52.305069],"type":"Point"}
}