{
  "type": "Feature",
  "properties": {
    "iso:country":"NL",
    "sg:address":"Nassaukd 359 Ii",
    "sg:city":"Amsterdam",
    "sg:orig_category":"Beeldende Kunstenaars",
    "sg:phone":"+31 6 22243690",
    "sg:postcode":"1054 AA",
    "sg:province":"North Holland",
    "wof:name":"Dings Vof, Nicolas",
    "wof:placetype":"venue"
},
  "geometry": {"coordinates":[4.86857,52.361408],"type":"Point"}
}