{
  "type": "Feature",
  "properties": {
    "addr:full":"Gasthuisgraaf 16 Sittard Limburg 6136 KS",
    "addr:housenumber":"16",
    "addr:postcode":"6136 ks",
    "addr:street":"Gasthuisgraaf",
    "iso:country":"NL",
    "sg:address":"Gasthuisgraaf 16",
    "sg:city":"Sittard",
    "sg:orig_category":"Wegen And Sportterreinen",
    "sg:phone":"+31 46 452 0517",
    "sg:postcode":"6136 KS",
    "sg:province":"Limburg",
    "wof:name":"Aannemingsbedrijf En Handelsonderneming Moermans B",
    "wof:placetype":"venue"
},
  "geometry": {"coordinates":[5.8717970848,51.0158233643],"type":"Point"}
}