{
  "type": "Feature",
  "properties": {
    "addr:full":"Kon Wilhelminahvn Zz 19 Vlaardingen Zuid-Holland 3134 KG",
    "addr:housenumber":"19",
    "addr:postcode":"3134 kg",
    "addr:street":"Kon;Zz",
    "iso:country":"NL",
    "sg:address":"Kon Wilhelminahvn Zz 19",
    "sg:city":"Vlaardingen",
    "sg:orig_category":"Diverse Grafische Activiteiten",
    "sg:phone":"+31 10 435 6496",
    "sg:postcode":"3134 KG",
    "sg:province":"Zuid-Holland",
    "wof:name":"Cornel Graphics",
    "wof:placetype":"venue"
},
  "geometry": {"coordinates":[4.340359,51.910442],"type":"Point"}
}