{
  "type": "Feature",
  "properties": {
    "addr:full":"Eemslandweg 58 Zwartemeer Provincie Drenthe 7894 AC",
    "addr:housenumber":"58",
    "addr:postcode":"7894 ac",
    "addr:street":"Eemslandweg;Provincie Drenthe",
    "iso:country":"NL",
    "sg:address":"Eemslandweg 58",
    "sg:city":"Zwartemeer",
    "sg:orig_category":"Kappers",
    "sg:phone":"+31 591 312 662",
    "sg:postcode":"7894 AC",
    "sg:province":"Provincie Drenthe",
    "wof:name":"Mascha'S Kapsalon",
    "wof:placetype":"venue"
},
  "geometry": {"coordinates":[7.04068,52.722393],"type":"Point"}
}