{
  "type": "Feature",
  "properties": {
    "addr:full":"Giek 7 Huizen Noord-Holland 1276 JC",
    "addr:housenumber":"7",
    "addr:postcode":"1276 jc",
    "addr:street":"Giek",
    "iso:country":"NL",
    "sg:address":"Giek 7",
    "sg:city":"Huizen",
    "sg:orig_category":"Marketingbureaus",
    "sg:phone":"+31 35 523 0753",
    "sg:postcode":"1276 JC",
    "sg:province":"Noord-Holland",
    "wof:name":"Vons Services",
    "wof:placetype":"venue"
},
  "geometry": {"coordinates":[5.254287,52.288975],"type":"Point"}
}