{
  "type": "Feature",
  "properties": {
    "iso:country":"NL",
    "sg:address":"Zandvoorterwg 40",
    "sg:city":"Aerdenhout",
    "sg:orig_category":"Makelaars En Adviseurs Onroerende Goederen",
    "sg:phone":"+31 23 524 5660",
    "sg:postcode":"2111 GW",
    "sg:province":"Noord-Holland",
    "wof:name":"Borghwijck Bv",
    "wof:placetype":"venue"
},
  "geometry": {"coordinates":[4.584945,52.363129],"type":"Point"}
}