{
  "type": "Feature",
  "properties": {
    "iso:country":"NL",
    "sg:address":"Sterrenkamp 1",
    "sg:city":"Emmen",
    "sg:orig_category":"Werving And Selectie Van Tijdelijk Personeel And Uitzendkantoren",
    "sg:phone":"+31 591 656 810",
    "sg:postcode":"7811 HA",
    "sg:province":"Provincie Drenthe",
    "wof:name":"Start",
    "wof:placetype":"venue"
},
  "geometry": {"coordinates":[6.8970470428,52.7836952209],"type":"Point"}
}