{
  "type": "Feature",
  "properties": {
    "addr:full":"J P Heyestr 96 Amsterdam Noord-Holland 1053 GT",
    "addr:housenumber":"96",
    "addr:postcode":"1053 gt",
    "addr:street":"J P Heyestr",
    "iso:country":"NL",
    "sg:address":"J P Heyestr 96",
    "sg:city":"Amsterdam",
    "sg:orig_category":"Koffie- En Theehuizen",
    "sg:phone":"+31 20 618 6084",
    "sg:postcode":"1053 GT",
    "sg:province":"Noord-Holland",
    "wof:name":"Heyestraat 96, J P",
    "wof:placetype":"venue"
},
  "geometry": {"coordinates":[4.86733,52.366638],"type":"Point"}
}