{
  "type": "Feature",
  "properties": {
    "addr:full":"Gasthuisln 54 Delft South Holland 2611 RB",
    "addr:housenumber":"54",
    "addr:postcode":"2611 rb",
    "addr:street":"Gasthuisln",
    "iso:country":"NL",
    "sg:address":"Gasthuisln 54",
    "sg:city":"Delft",
    "sg:orig_category":"Kinderkleding",
    "sg:phone":"+31 15 212 8028",
    "sg:postcode":"2611 RB",
    "sg:province":"South Holland",
    "wof:name":"Happy Kids",
    "wof:placetype":"venue"
},
  "geometry": {"coordinates":[4.35869,52.011505],"type":"Point"}
}