{
  "type": "Feature",
  "properties": {
    "addr:full":"Henk Curierekade 12 Amsterdam Noord-Holland 1013 CH",
    "addr:housenumber":"12",
    "addr:postcode":"1013",
    "iso:country":"NL",
    "sg:address":"Henk Curierekade 12",
    "sg:city":"Amsterdam",
    "sg:orig_category":"Fotostudio'S And Fotografen",
    "sg:phone":"+31 20 686 4233",
    "sg:postcode":"1013 CH",
    "sg:province":"Noord-Holland",
    "wof:name":"John Muller Fotostudio",
    "wof:placetype":"venue"
},
  "geometry": {"coordinates":[4.881045,52.389675],"type":"Point"}
}