{
  "type": "Feature",
  "properties": {
    "iso:country":"NL",
    "sg:address":"Everwijnstraat 21",
    "sg:city":"Culemborg",
    "sg:orig_category":"Opticiens",
    "sg:phone":"+31 345 532 500",
    "sg:postcode":"4101 CE",
    "sg:province":"Gelderland",
    "wof:name":"Hans Anders Opticiens",
    "wof:placetype":"venue"
},
  "geometry": {"coordinates":[5.2254109383,51.9563598633],"type":"Point"}
}