{
  "type": "Feature",
  "properties": {
    "iso:country":"NL",
    "sg:address":"Kernreactorstr 24",
    "sg:city":"Veenendaal",
    "sg:orig_category":"Autowasserettes",
    "sg:phone":"+31 318 612 294",
    "sg:postcode":"3903 LG",
    "sg:province":"Utrecht",
    "wof:name":"Erik'S Truck & Carwash",
    "wof:placetype":"venue"
},
  "geometry": {"coordinates":[5.566558,52.010746],"type":"Point"}
}