{
  "type": "Feature",
  "properties": {
    "addr:full":"Galle Promenade 49 Velserbroek Noord-Holland 1991 PP",
    "addr:housenumber":"49",
    "addr:postcode":"1991 pp",
    "addr:street":"Galle Promenade",
    "iso:country":"NL",
    "sg:address":"Galle Promenade 49",
    "sg:city":"Velserbroek",
    "sg:orig_category":"Balletartikelen",
    "sg:phone":"+31 23 537 3082",
    "sg:postcode":"1991 PP",
    "sg:province":"Noord-Holland",
    "sg:website":"http://www.danseres.nl",
    "wof:name":"Fou Sportif, Le",
    "wof:placetype":"venue"
},
  "geometry": {"coordinates":[-97.911247,29.74032],"type":"Point"}
}