{
  "type": "Feature",
  "properties": {
    "addr:full":"Koemarkt 8 Purmerend Noord-Holland 1441 DC",
    "addr:housenumber":"8",
    "addr:postcode":"1441",
    "addr:street":"Koemarkt",
    "iso:country":"NL",
    "sg:address":"Koemarkt 8",
    "sg:city":"Purmerend",
    "sg:orig_category":"Kappers",
    "sg:phone":"+31 229 432 318",
    "sg:postcode":"1441 DC",
    "sg:province":"Noord-Holland",
    "wof:name":"Partners",
    "wof:placetype":"venue"
},
  "geometry": {"coordinates":[4.948573,52.508827],"type":"Point"}
}