{
  "type": "Feature",
  "properties": {
    "addr:full":"Roosendaalseweg 11 Sint Willebrord Noord-Brabant 4711 RR",
    "addr:housenumber":"11",
    "addr:postcode":"4711 rr",
    "addr:street":"Roosendaalseweg",
    "iso:country":"NL",
    "sg:address":"Roosendaalseweg 11",
    "sg:city":"Sint Willebrord",
    "sg:orig_category":"Personenvervoer Zonder Dienstregeling",
    "sg:phone":"+31 165 382 851",
    "sg:postcode":"4711 RR",
    "sg:province":"Noord-Brabant",
    "wof:name":"Muijs Touringcarbedrijf En Reisbureau",
    "wof:placetype":"venue"
},
  "geometry": {"coordinates":[4.587499,51.559536],"type":"Point"}
}