{
  "type": "Feature",
  "properties": {
    "addr:full":"Potteriestraat 131 Maastricht Limburg 6216 VD",
    "addr:housenumber":"131",
    "addr:postcode":"6216 vd",
    "addr:street":"Potteriestraat",
    "iso:country":"NL",
    "sg:address":"Potteriestraat 131",
    "sg:city":"Maastricht",
    "sg:orig_category":"Artsen And Specialisten",
    "sg:phone":"+31 43 343 3809",
    "sg:postcode":"6216 VD",
    "sg:province":"Limburg",
    "wof:name":"J.J.M. Theunissen Huisarts",
    "wof:placetype":"venue"
},
  "geometry": {"coordinates":[5.658204,50.850189],"type":"Point"}
}