{
  "type": "Feature",
  "properties": {
    "addr:full":"Nijeveense Bovenboer 1 Nijeveen Provincie Drenthe 7948 LD",
    "addr:housenumber":"1",
    "addr:postcode":"7948 ld",
    "addr:street":"Nijeveense Bovenboer;Provincie Drenthe",
    "iso:country":"NL",
    "sg:address":"Nijeveense Bovenboer 1",
    "sg:city":"Nijeveen",
    "sg:orig_category":"Wegen And Sportterreinen",
    "sg:phone":"+31 522 491 776",
    "sg:postcode":"7948 LD",
    "sg:province":"Provincie Drenthe",
    "wof:name":"Aannemingsbedrijf Hopman",
    "wof:placetype":"venue"
},
  "geometry": {"coordinates":[6.1725459099,52.7504653931],"type":"Point"}
}