{
  "type": "Feature",
  "properties": {
    "addr:full":"Theresiastr 72 S Gravenhage South Holland 2593 AR",
    "addr:housenumber":"72",
    "addr:postcode":"2593",
    "addr:street":"Theresiastr;S Gravenhage",
    "iso:country":"NL",
    "sg:address":"Theresiastr 72",
    "sg:city":"S Gravenhage",
    "sg:orig_category":"Boeken En Tijdschriften",
    "sg:phone":"+31 70 335 0894",
    "sg:postcode":"2593 AR",
    "sg:province":"South Holland",
    "wof:name":"Taurus",
    "wof:placetype":"venue"
},
  "geometry": {"coordinates":[4.34266,52.086121],"type":"Point"}
}