{
  "type": "Feature",
  "properties": {
    "addr:full":"Nw Ebbingestr 85 Groningen Groningen 9712 NG",
    "addr:housenumber":"85",
    "addr:postcode":"9712 ng",
    "iso:country":"NL",
    "sg:address":"Nw Ebbingestr 85",
    "sg:city":"Groningen",
    "sg:orig_category":"Kappers",
    "sg:phone":"+31 50 527 4980",
    "sg:postcode":"9712 NG",
    "sg:province":"Groningen",
    "wof:name":"5Th Avenue Hairstylists",
    "wof:placetype":"venue"
},
  "geometry": {"coordinates":[6.5623922348,53.2249488831],"type":"Point"}
}