{
  "type": "Feature",
  "properties": {
    "iso:country":"NL",
    "sg:address":"Brewersstraat 26",
    "sg:city":"Simpelveld",
    "sg:classifiers":[
        {
            "category":"Professional",
            "subcategory":"Accounting & Tax Preparation",
            "type":"Services"
        }
    ],
    "sg:phone":"+31 45 568 0062",
    "sg:postcode":"6369 EN",
    "sg:province":"Limburg",
    "sg:tags":[
        "accountant"
    ],
    "wof:name":"Drs W Terstappen Bv",
    "wof:placetype":"venue"
},
  "geometry": {"coordinates":[5.972904,50.840954],"type":"Point"}
}