{
  "type": "Feature",
  "properties": {
    "addr:full":"Emmastraat 67 Goirle Noord-Brabant 5051 LM",
    "addr:housenumber":"67",
    "addr:postcode":"5051 lm",
    "addr:street":"Emmastraat",
    "iso:country":"NL",
    "sg:address":"Emmastraat 67",
    "sg:city":"Goirle",
    "sg:orig_category":"Kappers",
    "sg:phone":"+31 13 534 1517",
    "sg:postcode":"5051 LM",
    "sg:province":"Noord-Brabant",
    "wof:name":"Verschuren Coiffure",
    "wof:placetype":"venue"
},
  "geometry": {"coordinates":[5.071923,51.522453],"type":"Point"}
}