{
  "type": "Feature",
  "properties": {
    "addr:full":"Welbergswg 8 Ambt Delden NL.08 7495 SZ",
    "addr:housenumber":"8",
    "addr:postcode":"nl.08 7495 sz",
    "addr:street":"Welbergswg",
    "iso:country":"NL",
    "sg:address":"Welbergswg 8",
    "sg:city":"Ambt Delden",
    "sg:orig_category":"Adviesbureaus Bedrijfsorganisatie",
    "sg:phone":"+31 74 384 1396",
    "sg:postcode":"7495 SZ",
    "sg:province":"NL.08",
    "wof:name":"Combin Bv",
    "wof:placetype":"venue"
},
  "geometry": {"coordinates":[6.669126,52.283928],"type":"Point"}
}