{
  "type": "Feature",
  "properties": {
    "addr:full":"Wilhelminaw 47 Dieren BN. 6951 BN",
    "addr:housenumber":"47;bn.",
    "addr:postcode":"6951 bn",
    "addr:street":"Wilhelminaw",
    "iso:country":"NL",
    "sg:address":"Wilhelminaw 47",
    "sg:city":"Dieren",
    "sg:orig_category":"Verzekeringen - Verzekeringskantoren",
    "sg:phone":"+31 313 419 030",
    "sg:postcode":"6951 BN",
    "sg:province":"BN.",
    "wof:name":"Best Living",
    "wof:placetype":"venue"
},
  "geometry": {"coordinates":[114.598969,4.52513],"type":"Point"}
}