{
  "type": "Feature",
  "properties": {
    "addr:full":"Tureluurweg 47 Diemen Noord-Holland 1111 WL",
    "addr:housenumber":"47",
    "addr:postcode":"1111 wl",
    "addr:street":"Tureluurweg",
    "iso:country":"NL",
    "sg:address":"Tureluurweg 47",
    "sg:city":"Diemen",
    "sg:orig_category":"Public Relationbureaus",
    "sg:phone":"+31 20 600 8292",
    "sg:postcode":"1111 WL",
    "sg:province":"Noord-Holland",
    "wof:name":"Marcel Schilders Public Relations",
    "wof:placetype":"venue"
},
  "geometry": {"coordinates":[4.97558,52.349575],"type":"Point"}
}