{
  "type": "Feature",
  "properties": {
    "addr:full":"Straatweg 19 Maarssen Utrecht 3603 CV",
    "addr:housenumber":"19",
    "addr:postcode":"3603 cv",
    "addr:street":"Straatweg",
    "iso:country":"NL",
    "sg:address":"Straatweg 19",
    "sg:city":"Maarssen",
    "sg:orig_category":"Juridische Dienstverlening",
    "sg:phone":"+31 346 563 321",
    "sg:postcode":"3603 CV",
    "sg:province":"Utrecht",
    "wof:name":"Ajb Pensioenadviseurs En Actuarissen Bv",
    "wof:placetype":"venue"
},
  "geometry": {"coordinates":[5.032324,52.141621],"type":"Point"}
}