{
  "type": "Feature",
  "properties": {
    "addr:full":"Greveling 139 Annerveensche Kanaal Drenthe 9654 PP",
    "addr:housenumber":"139",
    "addr:postcode":"9654 pp",
    "addr:street":"Greveling",
    "iso:country":"NL",
    "sg:address":"Greveling 139",
    "sg:city":"Annerveensche Kanaal",
    "sg:orig_category":"Banken And Kredietinstellingen",
    "sg:phone":"+31 598 491 512",
    "sg:postcode":"9654 PP",
    "sg:province":"Drenthe",
    "wof:name":"Postkantoor",
    "wof:placetype":"venue"
},
  "geometry": {"coordinates":[6.806479,53.074974],"type":"Point"}
}