{
  "type": "Feature",
  "properties": {
    "iso:country":"NL",
    "sg:address":"Winkelcentrum Woensel 42",
    "sg:city":"Eindhoven",
    "sg:orig_category":"Banken And Kredietinstellingen",
    "sg:phone":"+31 40 241 5494",
    "sg:postcode":"5625 AC",
    "sg:province":"Noord-Brabant",
    "wof:name":"Ing Bank",
    "wof:placetype":"venue"
},
  "geometry": {"coordinates":[5.476175,51.469093],"type":"Point"}
}