{
  "type": "Feature",
  "properties": {
    "addr:full":"Winkelcentrum Woensel 42 Eindhoven Noord-Brabant 5625 AC",
    "addr:housenumber":"42",
    "addr:postcode":"5625 ac",
    "addr:street":"Winkelcentrum Woensel",
    "iso:country":"NL",
    "sg:address":"Winkelcentrum Woensel 42",
    "sg:city":"Eindhoven",
    "sg:orig_category":"Banken And Kredietinstellingen",
    "sg:phone":"+31 40 241 5494",
    "sg:postcode":"5625 AC",
    "sg:province":"Noord-Brabant",
    "wof:name":"Ing Bank",
    "wof:placetype":"venue"
},
  "geometry": {"coordinates":[5.476175,51.469093],"type":"Point"}
}