{
  "type": "Feature",
  "properties": {
    "addr:full":"De Steenbok 8A S Hertogenbosch Noord-Brabant 5215 ME",
    "addr:housenumber":"8a",
    "addr:postcode":"5215 me",
    "addr:street":"De Steenbok;S Hertogenbosch",
    "iso:country":"NL",
    "sg:address":"De Steenbok 8A",
    "sg:city":"S Hertogenbosch",
    "sg:orig_category":"Koeriersdiensten",
    "sg:phone":"+31 73 691 0957",
    "sg:postcode":"5215 ME",
    "sg:province":"Noord-Brabant",
    "wof:name":"Broko",
    "wof:placetype":"venue"
},
  "geometry": {"coordinates":[5.359569,51.686729],"type":"Point"}
}