{
  "type": "Feature",
  "properties": {
    "addr:full":"Wynkoperstr 2D Gorinchem Zuid-Holland 4204 HK",
    "addr:housenumber":"2d",
    "addr:postcode":"gorinchem;4204 hk",
    "iso:country":"NL",
    "sg:address":"Wynkoperstr 2D",
    "sg:city":"Gorinchem",
    "sg:orig_category":"Boeken En Tijdschriften",
    "sg:phone":"+31 183 638 029",
    "sg:postcode":"4204 HK",
    "sg:province":"Zuid-Holland",
    "sg:website":"http://www.bruna.nl",
    "wof:name":"Bruna",
    "wof:placetype":"venue"
},
  "geometry": {"coordinates":[4.959294,51.837677],"type":"Point"}
}