{
  "type": "Feature",
  "properties": {
    "addr:full":"Kotter 10 Lemmer Friesland 8531 CS",
    "addr:housenumber":"10",
    "addr:postcode":"8531 cs",
    "addr:street":"Kotter",
    "iso:country":"NL",
    "sg:address":"Kotter 10",
    "sg:city":"Lemmer",
    "sg:orig_category":"Fruit And Groenten Gh",
    "sg:phone":"+31 514 565 660",
    "sg:postcode":"8531 CS",
    "sg:province":"Friesland",
    "wof:name":"Uienhandel B. Moed",
    "wof:placetype":"venue"
},
  "geometry": {"coordinates":[5.720677,52.842304],"type":"Point"}
}