{
  "type": "Feature",
  "properties": {
    "addr:full":"Sluis 3 Marknesse Flevoland 8316 AM",
    "addr:housenumber":"3",
    "addr:postcode":"8316",
    "addr:street":"Sluis;Flevoland",
    "iso:country":"NL",
    "sg:address":"Sluis 3",
    "sg:city":"Marknesse",
    "sg:orig_category":"Overheidsdiensten",
    "sg:phone":"+31 527 203 301",
    "sg:postcode":"8316 AM",
    "sg:province":"Flevoland",
    "wof:name":"Herv Kerk Geb",
    "wof:placetype":"venue"
},
  "geometry": {"coordinates":[5.8625020981,52.7074127197],"type":"Point"}
}