{
  "type": "Feature",
  "properties": {
    "addr:full":"Verwoldsewg 1 Laren Gld Gelderland 7245 AG",
    "addr:housenumber":"1",
    "addr:postcode":"7245",
    "addr:street":"Verwoldsewg;Gld Gelderland",
    "iso:country":"NL",
    "sg:address":"Verwoldsewg 1",
    "sg:city":"Laren Gld",
    "sg:orig_category":"Verenigingsgebouwen",
    "sg:phone":"+31 573 401 636",
    "sg:postcode":"7245 AG",
    "sg:province":"Gelderland",
    "wof:name":"Kruispunt, 'T",
    "wof:placetype":"venue"
},
  "geometry": {"coordinates":[6.366481,52.192535],"type":"Point"}
}