{
  "type": "Feature",
  "properties": {
    "iso:country":"NL",
    "sg:address":"J Jongkindstr 177 Iv",
    "sg:city":"Amsterdam",
    "sg:orig_category":"Autorijscholen",
    "sg:phone":"+31 20 659 6551",
    "sg:postcode":"1062 CZ",
    "sg:province":"Noord-Holland",
    "wof:name":"Griese, Frans",
    "wof:placetype":"venue"
},
  "geometry": {"coordinates":[4.83975,52.351082],"type":"Point"}
}