{
  "type": "Feature",
  "properties": {
    "addr:full":"De Pol 1 Losser NL.08 7581 CZ",
    "addr:housenumber":"7581",
    "addr:street":"De",
    "iso:country":"NL",
    "sg:address":"De Pol 1",
    "sg:city":"Losser",
    "sg:orig_category":"Zonweringen",
    "sg:phone":"+31 53 538 4453",
    "sg:postcode":"7581 CZ",
    "sg:province":"NL.08",
    "sg:website":"http://www.o-s-d.nl",
    "wof:name":"Osd Zonweringen",
    "wof:placetype":"venue"
},
  "geometry": {"coordinates":[7.009226,52.245754],"type":"Point"}
}