{
  "type": "Feature",
  "properties": {
    "addr:full":"Julianastraat 13 Drunen North Brabant 5151 VT",
    "addr:housenumber":"13",
    "addr:postcode":"5151",
    "addr:street":"Julianastraat",
    "iso:country":"NL",
    "sg:address":"Julianastraat 13",
    "sg:city":"Drunen",
    "sg:orig_category":"Hoger Onderwijs",
    "sg:phone":"+31 416 372 753",
    "sg:postcode":"5151 VT",
    "sg:province":"North Brabant",
    "wof:name":"W.Th.C.M. Van Laarhoven",
    "wof:placetype":"venue"
},
  "geometry": {"coordinates":[5.132859,51.689117],"type":"Point"}
}