{
  "type": "Feature",
  "properties": {
    "addr:full":"Haarlemmerstraat 25-29 Leiden Zuid-Holland 2312 DJ",
    "addr:housenumber":"25-29",
    "addr:postcode":"2312 dj",
    "addr:street":"Haarlemmerstraat",
    "iso:country":"NL",
    "sg:address":"Haarlemmerstraat 25-29",
    "sg:city":"Leiden",
    "sg:orig_category":"Discountwinkels",
    "sg:phone":"+31 71 512 0983",
    "sg:postcode":"2312 DJ",
    "sg:province":"Zuid-Holland",
    "wof:name":"P B Labrujere",
    "wof:placetype":"venue"
},
  "geometry": {"coordinates":[4.486582,52.161285],"type":"Point"}
}