{
  "type": "Feature",
  "properties": {
    "addr:full":"Hengelstr 37 Gilze Noord-Brabant 5126 EA",
    "addr:housenumber":"37",
    "addr:postcode":"5126 ea",
    "addr:street":"Hengelstr",
    "iso:country":"NL",
    "sg:address":"Hengelstr 37",
    "sg:city":"Gilze",
    "sg:orig_category":"Bedrijfsopleidingen",
    "sg:phone":"+31 161 451 707",
    "sg:postcode":"5126 EA",
    "sg:province":"Noord-Brabant",
    "wof:name":"Join Connection",
    "wof:placetype":"venue"
},
  "geometry": {"coordinates":[4.947206,51.537479],"type":"Point"}
}