{
  "type": "Feature",
  "properties": {
    "addr:full":"Johan Huizingalaan 322 Amsterdam North Holland 1065 JP",
    "addr:housenumber":"322",
    "addr:postcode":"1065 jp",
    "addr:street":"Johan Huizingalaan",
    "iso:country":"NL",
    "sg:address":"Johan Huizingalaan 322",
    "sg:city":"Amsterdam",
    "sg:orig_category":"Kappers",
    "sg:phone":"+31 20 619 9813",
    "sg:postcode":"1065 JP",
    "sg:province":"North Holland",
    "wof:name":"Vip'S Hair",
    "wof:placetype":"venue"
},
  "geometry": {"coordinates":[4.827111,52.353172],"type":"Point"}
}