{
  "type": "Feature",
  "properties": {
    "iso:country":"NL",
    "sg:address":"Gyroscoopwg 86",
    "sg:city":"Amsterdam",
    "sg:orig_category":"Displays, Showcards En Toonmaterialen",
    "sg:phone":"+31 20 614 6716",
    "sg:postcode":"1042 AX",
    "sg:province":"Noord-Holland",
    "wof:name":"Impact Bv",
    "wof:placetype":"venue"
},
  "geometry": {"coordinates":[4.844427,52.399635],"type":"Point"}
}