{
  "type": "Feature",
  "properties": {
    "iso:country":"NL",
    "sg:address":"Hemeltjenskampwg 8",
    "sg:city":"Diepenveen",
    "sg:orig_category":"Artiesten/Gezelschappen",
    "sg:phone":"+31 570 592 098",
    "sg:postcode":"7431 CC",
    "sg:province":"Overijssel",
    "wof:name":"Diepenveens Gemengd Koor",
    "wof:placetype":"venue"
},
  "geometry": {"coordinates":[6.145631,52.295357],"type":"Point"}
}