{
  "type": "Feature",
  "properties": {
    "addr:full":"Stationswg 59 Drachten Friesland 9201 GH",
    "addr:housenumber":"59",
    "addr:postcode":"9201 gh",
    "addr:street":"Stationswg",
    "iso:country":"NL",
    "sg:address":"Stationswg 59",
    "sg:city":"Drachten",
    "sg:orig_category":"Schilders",
    "sg:phone":"+31 6 10949441",
    "sg:postcode":"9201 GH",
    "sg:province":"Friesland",
    "wof:name":"Brouwer, J",
    "wof:placetype":"venue"
},
  "geometry": {"coordinates":[6.096803,53.111469],"type":"Point"}
}