{
  "type": "Feature",
  "properties": {
    "addr:full":"Zr Meyboomstr 155 Leiden South Holland 2331 PG",
    "addr:housenumber":"155",
    "addr:postcode":"2331 pg",
    "iso:country":"NL",
    "sg:address":"Zr Meyboomstr 155",
    "sg:city":"Leiden",
    "sg:orig_category":"Autorijscholen",
    "sg:phone":"+31 71 572 2709",
    "sg:postcode":"2331 PG",
    "sg:province":"South Holland",
    "wof:name":"Take-4",
    "wof:placetype":"venue"
},
  "geometry": {"coordinates":[4.449704,52.14967],"type":"Point"}
}