{
  "type": "Feature",
  "properties": {
    "addr:full":"Wagenstr 32 S Gravenhage Zuid-Holland 2512 AX",
    "addr:housenumber":"32;gravenhage",
    "addr:postcode":"2512 ax",
    "addr:street":"Wagenstr;S",
    "iso:country":"NL",
    "sg:address":"Wagenstr 32",
    "sg:city":"S Gravenhage",
    "sg:orig_category":"Kappers",
    "sg:phone":"+31 70 346 6743",
    "sg:postcode":"2512 AX",
    "sg:province":"Zuid-Holland",
    "sg:website":"http://www.cosmo.nl/",
    "wof:name":"Cosmo",
    "wof:placetype":"venue"
},
  "geometry": {"coordinates":[4.3061800003,52.0732116699],"type":"Point"}
}