{
  "type": "Feature",
  "properties": {
    "iso:country":"NL",
    "sg:address":"Putsmolentje 3",
    "sg:city":"Ossendrecht",
    "sg:orig_category":"Goederenvervoer Over De Weg",
    "sg:phone":"+31 164 672 753",
    "sg:postcode":"4641 SK",
    "sg:province":"Noord-Brabant",
    "wof:name":"C. De Wit Intertransport Bv",
    "wof:placetype":"venue"
},
  "geometry": {"coordinates":[4.352615,51.391853],"type":"Point"}
}