{
  "type": "Feature",
  "properties": {
    "addr:full":"Loostr 69B Loo Gld Gelderland 6924 AD",
    "addr:housenumber":"69b",
    "addr:postcode":"6924 ad",
    "addr:street":"Loostr",
    "iso:country":"NL",
    "sg:address":"Loostr 69B",
    "sg:city":"Loo Gld",
    "sg:orig_category":"Verenigingen En Stichtingen",
    "sg:phone":"+31 316 267 754",
    "sg:postcode":"6924 AD",
    "sg:province":"Gelderland",
    "wof:name":"Excelsior",
    "wof:placetype":"venue"
},
  "geometry": {"coordinates":[5.982496,51.929581],"type":"Point"}
}