{
  "type": "Feature",
  "properties": {
    "addr:full":"Nieuwstr 107 Werkplaats Purmerend Noord-Holland 1441 CL",
    "addr:housenumber":"107",
    "addr:postcode":"1441",
    "addr:street":"Werkplaats",
    "iso:country":"NL",
    "sg:address":"Nieuwstr 107 Werkplaats",
    "sg:city":"Purmerend",
    "sg:orig_category":"Marktkramen",
    "sg:phone":"+31 299 420 765",
    "sg:postcode":"1441 CL",
    "sg:province":"Noord-Holland",
    "wof:name":"Modder & Zn, Fa H A",
    "wof:placetype":"venue"
},
  "geometry": {"coordinates":[4.94793,52.507607],"type":"Point"}
}