{
  "type": "Feature",
  "properties": {
    "addr:full":"Nieuweweg 10 Anna Paulowna Noord-Holland 1761 EH",
    "addr:housenumber":"10",
    "addr:postcode":"1761 eh",
    "addr:street":"Nieuweweg",
    "iso:country":"NL",
    "sg:address":"Nieuweweg 10",
    "sg:city":"Anna Paulowna",
    "sg:orig_category":"Meubelzaken, Woning- And Keukeninrichting",
    "sg:phone":"+31 223 531 208",
    "sg:postcode":"1761 EH",
    "sg:province":"Noord-Holland",
    "wof:name":"Nuland Woonstijl",
    "wof:placetype":"venue"
},
  "geometry": {"coordinates":[4.83282,52.86256],"type":"Point"}
}