{
  "type": "Feature",
  "properties": {
    "iso:country":"NL",
    "sg:address":"Edisonstr 11",
    "sg:city":"Almelo",
    "sg:orig_category":"Kunststoffen - Fabrieken En Groothandel",
    "sg:phone":"+31 546 486 486",
    "sg:postcode":"7601 PS",
    "sg:province":"NL.08",
    "sg:website":"http://www.herikon.nl",
    "wof:name":"Herikon Bv",
    "wof:placetype":"venue"
},
  "geometry": {"coordinates":[6.683672,52.338612],"type":"Point"}
}