{
  "type": "Feature",
  "properties": {
    "iso:country":"NL",
    "sg:address":"Htg Aalbrechtwg 5",
    "sg:city":"Alkmaar",
    "sg:orig_category":"Verenigingen En Stichtingen",
    "sg:phone":"+31 72 564 0393",
    "sg:postcode":"1823 DL",
    "sg:province":"North Holland",
    "wof:name":"Confess Samenwerkingsverband Zorgverbreding Alkmaar Eo",
    "wof:placetype":"venue"
},
  "geometry": {"coordinates":[4.764915,52.642918],"type":"Point"}
}