{
  "type": "Feature",
  "properties": {
    "iso:country":"NL",
    "sg:address":"Asingaborg 5",
    "sg:city":"Amsterdam",
    "sg:orig_category":"Montagebedrijven",
    "sg:phone":"+31 20 642 1747",
    "sg:postcode":"1082 SC",
    "sg:province":"North Holland",
    "wof:name":"Buiten, M",
    "wof:placetype":"venue"
},
  "geometry": {"coordinates":[4.870842,52.334301],"type":"Point"}
}