{
  "type": "Feature",
  "properties": {
    "addr:full":"Het Spoor 84 Houten Utrecht 3994 AL",
    "addr:housenumber":"84",
    "addr:postcode":"3994 al",
    "addr:street":"Het Spoor",
    "iso:country":"NL",
    "sg:address":"Het Spoor 84",
    "sg:city":"Houten",
    "sg:orig_category":"Organisatiebureaus",
    "sg:phone":"+31 30 608 1846",
    "sg:postcode":"3994 AL",
    "sg:province":"Utrecht",
    "wof:name":"Vmpo",
    "wof:placetype":"venue"
},
  "geometry": {"coordinates":[5.179142952,52.0232582092],"type":"Point"}
}