{
  "type": "Feature",
  "properties": {
    "addr:full":"Verl Hoofdwg 55 Nieuw Beerta Groningen 9687 PE",
    "addr:housenumber":"55",
    "addr:postcode":"beerta;9687 pe",
    "addr:street":"Nieuw",
    "iso:country":"NL",
    "sg:address":"Verl Hoofdwg 55",
    "sg:city":"Nieuw Beerta",
    "sg:orig_category":"Land- En Tuinbouw - Loonbedrijven",
    "sg:phone":"+31 597 521 469",
    "sg:postcode":"9687 PE",
    "sg:province":"Groningen",
    "wof:name":"Leeuwma, D E",
    "wof:placetype":"venue"
},
  "geometry": {"coordinates":[7.177676,53.202187],"type":"Point"}
}