{
  "type": "Feature",
  "properties": {
    "iso:country":"NL",
    "sg:address":"Elbawg 2",
    "sg:city":"Amsterdam",
    "sg:orig_category":"Levensmiddelen- Grondstoffen - Fabrieken En Groothandel",
    "sg:phone":"+31 20 480 3711",
    "sg:postcode":"1044 AD",
    "sg:province":"North Holland",
    "wof:name":"Cargill Bv",
    "wof:placetype":"venue"
},
  "geometry": {"coordinates":[4.80868,52.416492],"type":"Point"}
}