{
  "type": "Feature",
  "properties": {
    "iso:country":"NL",
    "sg:address":"P Poststr 48",
    "sg:city":"Almelo",
    "sg:orig_category":"Kappers",
    "sg:phone":"+31 6 53315215",
    "sg:postcode":"7606 TG",
    "sg:province":"Overijssel",
    "wof:name":"Modo",
    "wof:placetype":"venue"
},
  "geometry": {"coordinates":[6.646851,52.34803],"type":"Point"}
}