{
  "type": "Feature",
  "properties": {
    "addr:full":"Verlorenkost 10 Oosterend Nh Noord-Holland 1794 BA",
    "addr:housenumber":"10",
    "addr:postcode":"1794 ba",
    "addr:street":"Verlorenkost",
    "iso:country":"NL",
    "sg:address":"Verlorenkost 10",
    "sg:city":"Oosterend Nh",
    "sg:orig_category":"Metselwerken",
    "sg:phone":"+31 222 318 878",
    "sg:postcode":"1794 BA",
    "sg:province":"Noord-Holland",
    "wof:name":"Legierse, Hans",
    "wof:placetype":"venue"
},
  "geometry": {"coordinates":[4.874737,53.084431],"type":"Point"}
}