{
  "type": "Feature",
  "properties": {
    "iso:country":"NL",
    "sg:address":"Rykswg 28A",
    "sg:city":"Uffelte",
    "sg:orig_category":"Farmaceutische Industrie En Groothandel",
    "sg:phone":"+31 521 351 638",
    "sg:postcode":"7975 RT",
    "sg:province":"Drenthe",
    "wof:name":"Dac",
    "wof:placetype":"venue"
},
  "geometry": {"coordinates":[6.280793,52.785122],"type":"Point"}
}