{
  "type": "Feature",
  "properties": {
    "addr:full":"Eufraatstr 10 Spykenisse Zuid-Holland 3207 AA",
    "addr:housenumber":"10",
    "addr:postcode":"3207 aa",
    "addr:street":"Eufraatstr",
    "iso:country":"NL",
    "sg:address":"Eufraatstr 10",
    "sg:city":"Spykenisse",
    "sg:orig_category":"Administratie- En Boekhoudkantoren",
    "sg:phone":"+31 181 617 948",
    "sg:postcode":"3207 AA",
    "sg:province":"Zuid-Holland",
    "wof:name":"Balans",
    "wof:placetype":"venue"
},
  "geometry": {"coordinates":[4.351626,51.842865],"type":"Point"}
}