{
  "type": "Feature",
  "properties": {
    "addr:full":"G V Ledenberchstr 135 Amsterdam North Holland 1052 VE",
    "addr:housenumber":"135",
    "addr:postcode":"1052",
    "addr:street":"V Ledenberchstr;Ve",
    "iso:country":"NL",
    "sg:address":"G V Ledenberchstr 135",
    "sg:city":"Amsterdam",
    "sg:orig_category":"Koffie- En Theehuizen",
    "sg:phone":"+31 20 686 5144",
    "sg:postcode":"1052 VE",
    "sg:province":"North Holland",
    "wof:name":"Top, De",
    "wof:placetype":"venue"
},
  "geometry": {"coordinates":[4.87379,52.377899],"type":"Point"}
}