{
  "type": "Feature",
  "properties": {
    "addr:full":"R Castelynstr 13A Diemen Noord-Holland 1111 AW",
    "addr:housenumber":"13a",
    "addr:postcode":"1111 aw",
    "iso:country":"NL",
    "sg:address":"R Castelynstr 13A",
    "sg:city":"Diemen",
    "sg:orig_category":"Wassalons",
    "sg:phone":"+31 20 600 1077",
    "sg:postcode":"1111 AW",
    "sg:province":"Noord-Holland",
    "wof:name":"Dubbelblank",
    "wof:placetype":"venue"
},
  "geometry": {"coordinates":[4.9559059143,52.3404159546],"type":"Point"}
}