{
  "type": "Feature",
  "properties": {
    "addr:full":"A V Schendelstr 698 Utrecht Utrecht 3511 MJ",
    "addr:housenumber":"698",
    "addr:postcode":"3511 mj",
    "addr:street":"A;Schendelstr",
    "iso:country":"NL",
    "sg:address":"A V Schendelstr 698",
    "sg:city":"Utrecht",
    "sg:orig_category":"Adviesbureaus",
    "sg:phone":"+31 30 296 6485",
    "sg:postcode":"3511 MJ",
    "sg:province":"Utrecht",
    "wof:name":"Grondbank Nederland Bv",
    "wof:placetype":"venue"
},
  "geometry": {"coordinates":[5.115405,52.088932],"type":"Point"}
}