{
  "type": "Feature",
  "properties": {
    "addr:full":"Strawinskylaan 3101 Amsterdam North Holland 1077 ZX",
    "addr:housenumber":"3101",
    "addr:postcode":"1077 zx",
    "addr:street":"Strawinskylaan",
    "iso:country":"NL",
    "sg:address":"Strawinskylaan 3101",
    "sg:city":"Amsterdam",
    "sg:orig_category":"Zalenexploitatie",
    "sg:phone":"+31 20 642 7295",
    "sg:postcode":"1077 ZX",
    "sg:province":"North Holland",
    "wof:name":"Galerie Vromans",
    "wof:placetype":"venue"
},
  "geometry": {"coordinates":[4.869389,52.340435],"type":"Point"}
}