{
  "type": "Feature",
  "properties": {
    "addr:full":"Vossenhol 16 Bemmel Gelderland 6681 DL",
    "addr:housenumber":"16",
    "addr:postcode":"6681 dl",
    "addr:street":"Vossenhol;Gelderland",
    "iso:country":"NL",
    "sg:address":"Vossenhol 16",
    "sg:city":"Bemmel",
    "sg:orig_category":"Adviesbureaus Financieel",
    "sg:phone":"+31 481 450 534",
    "sg:postcode":"6681 DL",
    "sg:province":"Gelderland",
    "sg:website":"http://www.uveco.nl",
    "wof:name":"Uveco De Betuwe",
    "wof:placetype":"venue"
},
  "geometry": {"coordinates":[5.891026,51.89241],"type":"Point"}
}