{
  "type": "Feature",
  "properties": {
    "addr:full":"Daalseweg 358 Nijmegen Gelderland 6523 CG",
    "addr:housenumber":"358",
    "addr:postcode":"6523 cg",
    "addr:street":"Daalseweg;Gelderland",
    "iso:country":"NL",
    "sg:address":"Daalseweg 358",
    "sg:city":"Nijmegen",
    "sg:orig_category":"Diverse Opleidingen And Onderwijs",
    "sg:phone":"+31 24 328 0074",
    "sg:postcode":"6523 CG",
    "sg:province":"Gelderland",
    "wof:name":"Drs R K M Marttin",
    "wof:placetype":"venue"
},
  "geometry": {"coordinates":[5.87898,51.83503],"type":"Point"}
}