{
  "type": "Feature",
  "properties": {
    "addr:full":"Beeklaan 16 Doorwerth Gelderland 6865 VH",
    "addr:housenumber":"16",
    "addr:postcode":"6865 vh",
    "addr:street":"Beeklaan;Gelderland",
    "iso:country":"NL",
    "sg:address":"Beeklaan 16",
    "sg:city":"Doorwerth",
    "sg:orig_category":"Public Relationbureaus",
    "sg:phone":"+31 26 333 4297",
    "sg:postcode":"6865 VH",
    "sg:province":"Gelderland",
    "wof:name":"Vd Bergh & Vegelin Bv",
    "wof:placetype":"venue"
},
  "geometry": {"coordinates":[5.813828,51.974564],"type":"Point"}
}