{
  "type": "Feature",
  "properties": {
    "addr:full":"Sint Cathrijnestraat 6 Zaandam Noord-Holland 1501 NN",
    "addr:housenumber":"6",
    "addr:postcode":"1501 nn",
    "addr:street":"Sint Cathrijnestraat",
    "iso:country":"NL",
    "sg:address":"Sint Cathrijnestraat 6",
    "sg:city":"Zaandam",
    "sg:orig_category":"Autokeuringen",
    "sg:phone":"+31 75 616 3908",
    "sg:postcode":"1501 NN",
    "sg:province":"Noord-Holland",
    "wof:name":"Zweeds Ml Station En Gar. C.A. & E Timme",
    "wof:placetype":"venue"
},
  "geometry": {"coordinates":[4.830629,52.43856],"type":"Point"}
}