{
  "type": "Feature",
  "properties": {
    "iso:country":"NL",
    "sg:address":"Vliertstr 6",
    "sg:city":"Vught",
    "sg:orig_category":"Verenigingen En Stichtingen",
    "sg:phone":"+31 73 656 0539",
    "sg:postcode":"5261 EL",
    "sg:province":"Noord-Brabant",
    "wof:name":"Sob",
    "wof:placetype":"venue"
},
  "geometry": {"coordinates":[5.297558,51.656357],"type":"Point"}
}