{
  "type": "Feature",
  "properties": {
    "addr:full":"Markt 55 Maastricht Limburg 6211 CK",
    "addr:housenumber":"55",
    "addr:postcode":"6211 ck",
    "addr:street":"Markt",
    "iso:country":"NL",
    "sg:address":"Markt 55",
    "sg:city":"Maastricht",
    "sg:orig_category":"Meubelzaken, Woning- And Keukeninrichting",
    "sg:phone":"+31 43 321 5331",
    "sg:postcode":"6211 CK",
    "sg:province":"Limburg",
    "wof:name":"Van Lijf'S Meubileerinrichting",
    "wof:placetype":"venue"
},
  "geometry": {"coordinates":[5.692154,50.851109],"type":"Point"}
}