{
  "type": "Feature",
  "properties": {
    "addr:full":"Laarwoud 29 Almelo Overijssel 7608 AG",
    "addr:housenumber":"29",
    "addr:postcode":"7608",
    "addr:street":"Laarwoud",
    "iso:country":"NL",
    "sg:address":"Laarwoud 29",
    "sg:city":"Almelo",
    "sg:orig_category":"Psychotherapeuten",
    "sg:phone":"+31 546 860 556",
    "sg:postcode":"7608 AG",
    "sg:province":"Overijssel",
    "wof:name":"Kunstzinnig Therapeut",
    "wof:placetype":"venue"
},
  "geometry": {"coordinates":[6.689946,52.379398],"type":"Point"}
}