{
  "type": "Feature",
  "properties": {
    "addr:full":"Ommelsewg 17D Asten Noord-Brabant 5721 WT",
    "addr:housenumber":"17d",
    "addr:postcode":"5721 wt",
    "addr:street":"Ommelsewg",
    "iso:country":"NL",
    "sg:address":"Ommelsewg 17D",
    "sg:city":"Asten",
    "sg:orig_category":"Kappers",
    "sg:phone":"+31 493 697 427",
    "sg:postcode":"5721 WT",
    "sg:province":"Noord-Brabant",
    "wof:name":"Marielle",
    "wof:placetype":"venue"
},
  "geometry": {"coordinates":[5.747083,51.409992],"type":"Point"}
}