{
  "type": "Feature",
  "properties": {
    "addr:full":"Piusstr 72 Tilburg Noord-Brabant 5038 WT",
    "addr:housenumber":"72",
    "addr:postcode":"5038 wt",
    "addr:street":"Piusstr",
    "iso:country":"NL",
    "sg:address":"Piusstr 72",
    "sg:city":"Tilburg",
    "sg:orig_category":"Muziekinstrumenten En Bladmuziek",
    "sg:phone":"+31 13 544 2625",
    "sg:postcode":"5038 WT",
    "sg:province":"Noord-Brabant",
    "wof:name":"Music All In",
    "wof:placetype":"venue"
},
  "geometry": {"coordinates":[5.089345,51.551792],"type":"Point"}
}