{
  "type": "Feature",
  "properties": {
    "addr:full":"St Antoniusstr 30 De Mortel Noord-Brabant 5425 VE",
    "addr:housenumber":"30",
    "addr:postcode":"5425",
    "addr:street":"De;Ve",
    "iso:country":"NL",
    "sg:address":"St Antoniusstr 30",
    "sg:city":"De Mortel",
    "sg:orig_category":"Verenigingsgebouwen",
    "sg:phone":"+31 492 363 630",
    "sg:postcode":"5425 VE",
    "sg:province":"Noord-Brabant",
    "wof:name":"Wilg, De",
    "wof:placetype":"venue"
},
  "geometry": {"coordinates":[5.708233,51.541363],"type":"Point"}
}