{
  "type": "Feature",
  "properties": {
    "iso:country":"NL",
    "sg:address":"Hoofdstr 126",
    "sg:city":"Driebergen Rysenb",
    "sg:orig_category":"Kunsthandel",
    "sg:phone":"+31 343 511 235",
    "sg:postcode":"3972 LD",
    "sg:province":"Utrecht",
    "sg:website":"http://www.ercanvas.com",
    "wof:name":"Er Canvas",
    "wof:placetype":"venue"
},
  "geometry": {"coordinates":[5.275964,52.055794],"type":"Point"}
}