{
  "type": "Feature",
  "properties": {
    "iso:country":"NL",
    "sg:address":"Vledderkamp 6",
    "sg:city":"Vlagtwedde",
    "sg:orig_category":"Kappers",
    "sg:phone":"+31 599 312 503",
    "sg:postcode":"9541 BC",
    "sg:province":"Groningen",
    "wof:name":"Andre",
    "wof:placetype":"venue"
},
  "geometry": {"coordinates":[7.1188311577,53.0246963501],"type":"Point"}
}