{
  "type": "Feature",
  "properties": {
    "addr:full":"Tiberdreef 30 Utrecht Utrecht 3561 GG",
    "addr:housenumber":"30",
    "addr:postcode":"3561 gg",
    "addr:street":"Tiberdreef",
    "iso:country":"NL",
    "sg:address":"Tiberdreef 30",
    "sg:city":"Utrecht",
    "sg:orig_category":"Broodjeszaken",
    "sg:phone":"+31 30 261 4747",
    "sg:postcode":"3561 GG",
    "sg:province":"Utrecht",
    "wof:name":"Picollo",
    "wof:placetype":"venue"
},
  "geometry": {"coordinates":[5.125079,52.110348],"type":"Point"}
}