{
  "type": "Feature",
  "properties": {
    "iso:country":"NL",
    "sg:address":"Pluim Es 32",
    "sg:city":"Krimpen Ad Yssel",
    "sg:orig_category":"Tekstverwerking - Servicebureaus",
    "sg:phone":"+31 180 520 522",
    "sg:postcode":"2925 CM",
    "sg:province":"Zuid-Holland",
    "wof:name":"Beware",
    "wof:placetype":"venue"
},
  "geometry": {"coordinates":[4.620946,51.916321],"type":"Point"}
}