{
  "type": "Feature",
  "properties": {
    "iso:country":"NL",
    "sg:address":"Driebergsestrwg 9",
    "sg:city":"Doorn",
    "sg:orig_category":"Verenigingen En Stichtingen",
    "sg:phone":"+31 343 473 250",
    "sg:postcode":"3941 ZS",
    "sg:province":"Utrecht",
    "sg:website":"http://www.mitex.nl",
    "wof:name":"Mitex",
    "wof:placetype":"venue"
},
  "geometry": {"coordinates":[5.323852,52.035809],"type":"Point"}
}