{
  "type": "Feature",
  "properties": {
    "addr:full":"Copynln 35 Groenekan Utrecht 3737 AV",
    "addr:housenumber":"35",
    "addr:postcode":"3737 av",
    "addr:street":"Copynln",
    "iso:country":"NL",
    "sg:address":"Copynln 35",
    "sg:city":"Groenekan",
    "sg:orig_category":"Kantoor- En Secretariaatsservice",
    "sg:phone":"+31 346 214 337",
    "sg:postcode":"3737 AV",
    "sg:province":"Utrecht",
    "wof:name":"Bob",
    "wof:placetype":"venue"
},
  "geometry": {"coordinates":[5.1526799202,52.1231193542],"type":"Point"}
}