{
  "type": "Feature",
  "properties": {
    "addr:full":"Maagdenbergweg 5 Venlo Limburg 5915 CN",
    "addr:housenumber":"5",
    "addr:postcode":"5915 cn",
    "addr:street":"Maagdenbergweg",
    "iso:country":"NL",
    "sg:address":"Maagdenbergweg 5",
    "sg:city":"Venlo",
    "sg:orig_category":"Medische And Orthopedische Artikelen",
    "sg:phone":"+31 77 351 7909",
    "sg:postcode":"5915 CN",
    "sg:province":"Limburg",
    "wof:name":"Elisabeth Smits-Rinner",
    "wof:placetype":"venue"
},
  "geometry": {"coordinates":[6.177607,51.360825],"type":"Point"}
}