{
  "type": "Feature",
  "properties": {
    "addr:full":"Tolhusln 10 Gorredyk Friesland 8401 GA",
    "addr:housenumber":"10",
    "addr:postcode":"8401 ga",
    "addr:street":"Tolhusln",
    "iso:country":"NL",
    "sg:address":"Tolhusln 10",
    "sg:city":"Gorredyk",
    "sg:orig_category":"Dumpgoederen",
    "sg:phone":"+31 513 466 791",
    "sg:postcode":"8401 GA",
    "sg:province":"Friesland",
    "wof:name":"Hennekes, E",
    "wof:placetype":"venue"
},
  "geometry": {"coordinates":[6.06447,53.00478],"type":"Point"}
}