{
  "type": "Feature",
  "properties": {
    "addr:full":"Rokin 89 Amsterdam Noord-Holland 1012 KL",
    "addr:housenumber":"89",
    "addr:postcode":"1012 kl",
    "addr:street":"Rokin",
    "iso:country":"NL",
    "sg:address":"Rokin 89",
    "sg:city":"Amsterdam",
    "sg:classifiers":[
        {
            "category":"Bars & Pubs",
            "type":"Food & Drink"
        }
    ],
    "sg:phone":"+31 20 421 2654",
    "sg:postcode":"1012 KL",
    "sg:province":"Noord-Holland",
    "wof:name":"The Tara Irish Pub",
    "wof:placetype":"venue"
},
  "geometry": {"coordinates":[4.892932,52.370228],"type":"Point"}
}