{
  "type": "Feature",
  "properties": {
    "addr:full":"Amsterdamsestrwg 542 Utrecht Utrecht 3553 EN",
    "addr:housenumber":"542",
    "addr:postcode":"3553 en",
    "iso:country":"NL",
    "sg:address":"Amsterdamsestrwg 542",
    "sg:city":"Utrecht",
    "sg:orig_category":"Psychologen",
    "sg:phone":"+31 6 17618549",
    "sg:postcode":"3553 EN",
    "sg:province":"Utrecht",
    "sg:website":"http://www.intimiteit.nl",
    "wof:name":"Reijmers, Mw Drs M C",
    "wof:placetype":"venue"
},
  "geometry": {"coordinates":[5.083754,52.109932],"type":"Point"}
}