{
  "type": "Feature",
  "properties": {
    "addr:full":"De Lairessestraat 96 Amsterdam Noord-Holland 1071 PJ",
    "addr:housenumber":"96",
    "addr:postcode":"1071 pj",
    "addr:street":"De Lairessestraat",
    "iso:country":"NL",
    "sg:address":"De Lairessestraat 96",
    "sg:city":"Amsterdam",
    "sg:orig_category":"Juridische Dienstverlening",
    "sg:phone":"+31 20 675 8535",
    "sg:postcode":"1071 PJ",
    "sg:province":"Noord-Holland",
    "wof:name":"Mr. F. Kaan Notaris En Juridisch Adviseur",
    "wof:placetype":"venue"
},
  "geometry": {"coordinates":[4.871879,52.353779],"type":"Point"}
}