{
  "type": "Feature",
  "properties": {
    "addr:full":"Benedictushof 48 Vianen Zh South Holland 4133 AK",
    "addr:housenumber":"48",
    "addr:postcode":"zh;4133 ak",
    "addr:street":"Benedictushof",
    "iso:country":"NL",
    "sg:address":"Benedictushof 48",
    "sg:city":"Vianen Zh",
    "sg:orig_category":"Veiligheidsuitrusting En -Kleding",
    "sg:phone":"+31 347 377 191",
    "sg:postcode":"4133 AK",
    "sg:province":"South Holland",
    "sg:website":"http://www.gehoor-bescherming.nl",
    "wof:name":"Protect",
    "wof:placetype":"venue"
},
  "geometry": {"coordinates":[5.084133,51.984211],"type":"Point"}
}