{
  "type": "Feature",
  "properties": {
    "addr:full":"Aalsterwg 24 Eindhoven Noord-Brabant 5615 CG",
    "addr:housenumber":"24",
    "addr:postcode":"5615 cg",
    "addr:street":"Aalsterwg",
    "iso:country":"NL",
    "sg:address":"Aalsterwg 24",
    "sg:city":"Eindhoven",
    "sg:orig_category":"Makelaars En Adviseurs Onroerende Goederen",
    "sg:phone":"+31 40 212 0164",
    "sg:postcode":"5615 CG",
    "sg:province":"Noord-Brabant",
    "sg:website":"http://www.edwillems.nl",
    "wof:name":"Ed Willems",
    "wof:placetype":"venue"
},
  "geometry": {"coordinates":[5.486462,51.427872],"type":"Point"}
}