{
  "type": "Feature",
  "properties": {
    "iso:country":"NL",
    "sg:address":"Italiaanse Zeedk 120",
    "sg:city":"Hoorn Nh",
    "sg:orig_category":"Psychologen",
    "sg:phone":"+31 229 275 245",
    "sg:postcode":"1621 AK",
    "sg:province":"Noord-Holland",
    "wof:name":"Brink-Krol, E Van Den",
    "wof:placetype":"venue"
},
  "geometry": {"coordinates":[5.062375,52.63699],"type":"Point"}
}