{
  "type": "Feature",
  "properties": {
    "addr:full":"Plesmanweg 2 Beverwijk North Holland 1945 WK",
    "addr:housenumber":"2",
    "addr:postcode":"1945 wk",
    "addr:street":"Plesmanweg",
    "iso:country":"NL",
    "sg:address":"Plesmanweg 2",
    "sg:city":"Beverwijk",
    "sg:orig_category":"Begrafenisverzorging",
    "sg:phone":"+31 251 254 135",
    "sg:postcode":"1945 WK",
    "sg:province":"North Holland",
    "wof:name":"Eerden, Jan Van",
    "wof:placetype":"venue"
},
  "geometry": {"coordinates":[4.659884,52.496586],"type":"Point"}
}