{
  "type": "Feature",
  "properties": {
    "iso:country":"NL",
    "sg:address":"Maldenhof 419",
    "sg:city":"Amsterdam Zuidoost",
    "sg:orig_category":"Vertaal- And Tolkenbureaus",
    "sg:phone":"+31 20 400 1880",
    "sg:postcode":"1106 EM",
    "sg:province":"Noord-Holland",
    "wof:name":"T Barwari",
    "wof:placetype":"venue"
},
  "geometry": {"coordinates":[4.969117,52.303719],"type":"Point"}
}