{
  "type": "Feature",
  "properties": {
    "addr:full":"Eendrachtsstr 28B Velsen Noord Noord-Holland 1951 AZ",
    "addr:housenumber":"28b",
    "addr:postcode":"1951 az",
    "addr:street":"Eendrachtsstr",
    "iso:country":"NL",
    "sg:address":"Eendrachtsstr 28B",
    "sg:city":"Velsen Noord",
    "sg:orig_category":"Kinderkleding",
    "sg:phone":"+31 251 217 297",
    "sg:postcode":"1951 AZ",
    "sg:province":"Noord-Holland",
    "wof:name":"Dandy & Duties",
    "wof:placetype":"venue"
},
  "geometry": {"coordinates":[4.638059,52.46703],"type":"Point"}
}