{
  "type": "Feature",
  "properties": {
    "addr:full":"Klapperdk 1 Geesteren Gld Gelderland 7274 DD",
    "addr:housenumber":"1",
    "addr:postcode":"7274 dd",
    "addr:street":"Klapperdk;Gld Gelderland",
    "iso:country":"NL",
    "sg:address":"Klapperdk 1",
    "sg:city":"Geesteren Gld",
    "sg:orig_category":"Vakantieverblijven",
    "sg:phone":"+31 545 271 692",
    "sg:postcode":"7274 DD",
    "sg:province":"Gelderland",
    "sg:website":"http://www.vakantieboerderijen.com",
    "wof:name":"Klappe, De",
    "wof:placetype":"venue"
},
  "geometry": {"coordinates":[6.527421,52.125061],"type":"Point"}
}