{
  "type": "Feature",
  "properties": {
    "iso:country":"NL",
    "sg:address":"Kraaierstraat 3",
    "sg:city":"Leiden",
    "sg:orig_category":"Verhuur Kantoorapparatuur",
    "sg:phone":"+31 71 512 5007",
    "sg:postcode":"2311 NR",
    "sg:province":"Zuid-Holland",
    "wof:name":"Cross",
    "wof:placetype":"venue"
},
  "geometry": {"coordinates":[4.497923,52.155876],"type":"Point"}
}