{
  "type": "Feature",
  "properties": {
    "addr:full":"Nieuwe Waalreseweg 199 Valkenswaard Noord-Brabant 5552 EJ",
    "addr:housenumber":"199",
    "addr:postcode":"5552 ej",
    "addr:street":"Nieuwe Waalreseweg",
    "iso:country":"NL",
    "sg:address":"Nieuwe Waalreseweg 199",
    "sg:city":"Valkenswaard",
    "sg:orig_category":"Bloemen And Planten",
    "sg:phone":"+31 40 204 4222",
    "sg:postcode":"5552 EJ",
    "sg:province":"Noord-Brabant",
    "wof:name":"Tuincentrum Coppelmans Bv",
    "wof:placetype":"venue"
},
  "geometry": {"coordinates":[5.445053,51.367535],"type":"Point"}
}