{
  "type": "Feature",
  "properties": {
    "addr:full":"Parelstraat 19 Hengelo Ov NL.08 7554 TL",
    "addr:housenumber":"19",
    "addr:postcode":"7554 tl",
    "addr:street":"Parelstraat;Ov",
    "iso:country":"NL",
    "sg:address":"Parelstraat 19",
    "sg:city":"Hengelo Ov",
    "sg:classifiers":[
        {
            "category":"Retail",
            "subcategory":"Storage",
            "type":"Services"
        }
    ],
    "sg:phone":"+31 74 291 4024",
    "sg:postcode":"7554 TL",
    "sg:province":"NL.08",
    "sg:tags":[
        "opslag",
        "bewaring"
    ],
    "wof:name":"Boldershoek Bv",
    "wof:placetype":"venue"
},
  "geometry": {"coordinates":[6.7897100449,52.266330719],"type":"Point"}
}