{
  "type": "Feature",
  "properties": {
    "addr:full":"Dorpsstr 98 Haule Friesland 8432 PE",
    "addr:housenumber":"98",
    "addr:postcode":"8432 pe",
    "addr:street":"Dorpsstr",
    "iso:country":"NL",
    "sg:address":"Dorpsstr 98",
    "sg:city":"Haule",
    "sg:orig_category":"Adviesbureaus Bedrijfsorganisatie",
    "sg:phone":"+31 516 577 523",
    "sg:postcode":"8432 PE",
    "sg:province":"Friesland",
    "wof:name":"Baltink Bv",
    "wof:placetype":"venue"
},
  "geometry": {"coordinates":[-38.083542,-8.37738],"type":"Point"}
}