{
  "type": "Feature",
  "properties": {
    "addr:full":"Leyparkwg 27 Tilburg North Brabant 5022 AA",
    "addr:housenumber":"27",
    "addr:postcode":"5022 aa",
    "addr:street":"Leyparkwg",
    "iso:country":"NL",
    "sg:address":"Leyparkwg 27",
    "sg:city":"Tilburg",
    "sg:orig_category":"Vertaalbureaus",
    "sg:phone":"+31 13 535 1213",
    "sg:postcode":"5022 AA",
    "sg:province":"North Brabant",
    "wof:name":"Traduit-Forma",
    "wof:placetype":"venue"
},
  "geometry": {"coordinates":[5.100638,51.545025],"type":"Point"}
}