{
  "type": "Feature",
  "properties": {
    "addr:full":"Zandstr 56 Gennep Limburg 6591 DD",
    "addr:housenumber":"56",
    "addr:postcode":"6591 dd",
    "addr:street":"Zandstr",
    "iso:country":"NL",
    "sg:address":"Zandstr 56",
    "sg:city":"Gennep",
    "sg:orig_category":"Banken",
    "sg:phone":"+31 485 550 550",
    "sg:postcode":"6591 DD",
    "sg:province":"Limburg",
    "sg:website":"http://www.rabobank.nl",
    "wof:name":"Rabobank",
    "wof:placetype":"venue"
},
  "geometry": {"coordinates":[5.97119,51.699299],"type":"Point"}
}