{
  "type": "Feature",
  "properties": {
    "addr:full":"Middelhorsterweg 72/1 Haren Gn Groningen 9751 TH",
    "addr:housenumber":"72 / 1",
    "addr:postcode":"9751 th",
    "addr:street":"Middelhorsterweg",
    "iso:country":"NL",
    "sg:address":"Middelhorsterweg 72/1",
    "sg:city":"Haren Gn",
    "sg:orig_category":"Autokeuringen",
    "sg:phone":"+31 50 534 8500",
    "sg:postcode":"9751 TH",
    "sg:province":"Groningen",
    "wof:name":"Caaham Tuning",
    "wof:placetype":"venue"
},
  "geometry": {"coordinates":[6.620338,53.170033],"type":"Point"}
}