{
  "type": "Feature",
  "properties": {
    "addr:full":"Javastraat 58 Amsterdam Noord-Holland 1094 HK",
    "addr:housenumber":"58",
    "addr:postcode":"1094 hk",
    "addr:street":"Javastraat",
    "iso:country":"NL",
    "sg:address":"Javastraat 58",
    "sg:city":"Amsterdam",
    "sg:classifiers":[
        {
            "category":"Food & Beverages",
            "subcategory":"Fruits & Vegetables",
            "type":"Retail Goods"
        }
    ],
    "sg:phone":"+31 20 668 4308",
    "sg:postcode":"1094 HK",
    "sg:province":"Noord-Holland",
    "sg:tags":[
        "groenten"
    ],
    "wof:name":"Superstar Market",
    "wof:placetype":"venue"
},
  "geometry": {"coordinates":[4.933982,52.363556],"type":"Point"}
}