{
  "type": "Feature",
  "properties": {
    "addr:full":"Dammersboog 114 Velserbroek North Holland 1991 XT",
    "addr:housenumber":"114",
    "addr:postcode":"1991 xt",
    "addr:street":"Dammersboog",
    "iso:country":"NL",
    "sg:address":"Dammersboog 114",
    "sg:city":"Velserbroek",
    "sg:orig_category":"Onroerende Goederen",
    "sg:phone":"+31 23 539 6050",
    "sg:postcode":"1991 XT",
    "sg:province":"North Holland",
    "wof:name":"Verdonk Bv",
    "wof:placetype":"venue"
},
  "geometry": {"coordinates":[4.66456,52.429199],"type":"Point"}
}