{
  "type": "Feature",
  "properties": {
    "addr:full":"Tacitus 5 Wyk By Duurstede Utrecht 3962 LE",
    "addr:housenumber":"5",
    "addr:postcode":"duurstede;3962 le",
    "addr:street":"Tacitus",
    "iso:country":"NL",
    "sg:address":"Tacitus 5",
    "sg:city":"Wyk By Duurstede",
    "sg:orig_category":"Onroerende Goederen",
    "sg:phone":"+31 343 591 629",
    "sg:postcode":"3962 LE",
    "sg:province":"Utrecht",
    "sg:website":"http://www.bernadagolf.nl",
    "wof:name":"Bernadagolf",
    "wof:placetype":"venue"
},
  "geometry": {"coordinates":[5.326976,51.983246],"type":"Point"}
}