{
  "type": "Feature",
  "properties": {
    "iso:country":"NL",
    "sg:address":"Tacitus 5",
    "sg:city":"Wyk By Duurstede",
    "sg:orig_category":"Onroerende Goederen",
    "sg:phone":"+31 343 591 629",
    "sg:postcode":"3962 LE",
    "sg:province":"Utrecht",
    "sg:website":"http://www.bernadagolf.nl",
    "wof:name":"Bernadagolf",
    "wof:placetype":"venue"
},
  "geometry": {"coordinates":[5.326976,51.983246],"type":"Point"}
}