{
  "type": "Feature",
  "properties": {
    "addr:full":"Inslagstraat 8 Neede Gelderland 7161 ZE",
    "addr:housenumber":"8",
    "addr:postcode":"7161",
    "addr:street":"Inslagstraat;Gelderland",
    "iso:country":"NL",
    "sg:address":"Inslagstraat 8",
    "sg:city":"Neede",
    "sg:orig_category":"Paramedische Behandelingen",
    "sg:phone":"+31 545 294 871",
    "sg:postcode":"7161 ZE",
    "sg:province":"Gelderland",
    "wof:name":"Y. De Graaf",
    "wof:placetype":"venue"
},
  "geometry": {"coordinates":[-121.31706200000001,38.299633],"type":"Point"}
}