{
  "type": "Feature",
  "properties": {
    "iso:country":"NL",
    "sg:address":"Dorpsstraat 37",
    "sg:city":"Warmond",
    "sg:orig_category":"Woningbouwverenigingen",
    "sg:phone":"+31 71 301 2191",
    "sg:postcode":"2361 AP",
    "sg:province":"Zuid-Holland",
    "wof:name":"Woningstichting Warmunda",
    "wof:placetype":"venue"
},
  "geometry": {"coordinates":[4.5041589737,52.1968803406],"type":"Point"}
}