{
  "type": "Feature",
  "properties": {
    "addr:full":"Touwslagery 2 Amstelveen Noord-Holland 1185 ZP",
    "addr:housenumber":"2",
    "addr:postcode":"1185 zp",
    "addr:street":"Touwslagery",
    "iso:country":"NL",
    "sg:address":"Touwslagery 2",
    "sg:city":"Amstelveen",
    "sg:orig_category":"Verhuizingen",
    "sg:phone":"+31 20 641 2234",
    "sg:postcode":"1185 ZP",
    "sg:province":"Noord-Holland",
    "sg:website":"http://www.gorter-logistiek.nl",
    "wof:name":"Gorter Bv, Gebroeders",
    "wof:placetype":"venue"
},
  "geometry": {"coordinates":[4.836504,52.283451],"type":"Point"}
}