{
  "type": "Feature",
  "properties": {
    "addr:full":"Kleine Houtstraat 66 Haarlem Noord-Holland 2011 DP",
    "addr:housenumber":"66",
    "addr:postcode":"2011 dp",
    "addr:street":"Kleine Houtstraat",
    "iso:country":"NL",
    "sg:address":"Kleine Houtstraat 66",
    "sg:city":"Haarlem",
    "sg:classifiers":[
        {
            "category":"Bakery",
            "type":"Food & Drink"
        }
    ],
    "sg:phone":"+31 23 532 3461",
    "sg:postcode":"2011 DP",
    "sg:province":"Noord-Holland",
    "sg:tags":[
        "brood",
        "banket"
    ],
    "wof:name":"In De Gevulde Broodmand",
    "wof:placetype":"venue"
},
  "geometry": {"coordinates":[4.635907,52.378078],"type":"Point"}
}