{
  "type": "Feature",
  "properties": {
    "iso:country":"NL",
    "sg:address":"Handelsstr 23",
    "sg:city":"Sittard",
    "sg:orig_category":"Kantoor- En Bedrijfsmeubelen",
    "sg:phone":"+31 46 451 4867",
    "sg:postcode":"6135 KK",
    "sg:province":"Limburg",
    "sg:website":"http://www.kantoormeubelen-zuid.nl",
    "wof:name":"Kantoormeubelen Zuid",
    "wof:placetype":"venue"
},
  "geometry": {"coordinates":[5.8476238251,51.0008811951],"type":"Point"}
}