{
  "type": "Feature",
  "properties": {
    "addr:full":"Kerkstraat 51 Harlingen Friesland 8701 HR",
    "addr:housenumber":"51",
    "addr:postcode":"8701 hr",
    "addr:street":"Kerkstraat",
    "iso:country":"NL",
    "sg:address":"Kerkstraat 51",
    "sg:city":"Harlingen",
    "sg:classifiers":[
        {
            "category":"Travel",
            "subcategory":"Hotels & Motels",
            "type":"Entertainment"
        }
    ],
    "sg:phone":"+31 515 575 299",
    "sg:postcode":"8701 HR",
    "sg:province":"Friesland",
    "wof:name":"Hotel Stadslogement Hid Hero Hiem",
    "wof:placetype":"venue"
},
  "geometry": {"coordinates":[-97.695549,26.189859],"type":"Point"}
}