{
  "type": "Feature",
  "properties": {
    "addr:full":"Speelhuisln 151 Breda Noord-Brabant 4815 CD",
    "addr:housenumber":"151",
    "addr:postcode":"4815 cd",
    "iso:country":"NL",
    "sg:address":"Speelhuisln 151",
    "sg:city":"Breda",
    "sg:orig_category":"Kunsthandel",
    "sg:phone":"+31 76 571 6371",
    "sg:postcode":"4815 CD",
    "sg:province":"Noord-Brabant",
    "wof:name":"Graphics Home Gallery",
    "wof:placetype":"venue"
},
  "geometry": {"coordinates":[4.771685,51.591351],"type":"Point"}
}