{
  "type": "Feature",
  "properties": {
    "addr:full":"Wilhelminapk 76 Valkenswaard Noord-Brabant 5554 JG",
    "addr:housenumber":"76",
    "addr:postcode":"5554 jg",
    "addr:street":"Wilhelminapk",
    "iso:country":"NL",
    "sg:address":"Wilhelminapk 76",
    "sg:city":"Valkenswaard",
    "sg:orig_category":"Hypotheken",
    "sg:phone":"+31 40 204 8000",
    "sg:postcode":"5554 JG",
    "sg:province":"Noord-Brabant",
    "wof:name":"Gorp, Van",
    "wof:placetype":"venue"
},
  "geometry": {"coordinates":[5.462418,51.345764],"type":"Point"}
}