{
  "type": "Feature",
  "properties": {
    "addr:full":"Straatwg 10 Maarssen Utrecht 3604 BB",
    "addr:housenumber":"10",
    "addr:postcode":"3604 bb",
    "addr:street":"Straatwg",
    "iso:country":"NL",
    "sg:address":"Straatwg 10",
    "sg:city":"Maarssen",
    "sg:orig_category":"Kinderkleding",
    "sg:phone":"+31 30 236 9602",
    "sg:postcode":"3604 BB",
    "sg:province":"Utrecht",
    "wof:name":"Deugniet",
    "wof:placetype":"venue"
},
  "geometry": {"coordinates":[5.048366,52.131191],"type":"Point"}
}