{
  "type": "Feature",
  "properties": {
    "addr:full":"Deventerwg 29A Bathmen Overijssel 7437 BH",
    "addr:housenumber":"29a",
    "addr:postcode":"7437 bh",
    "addr:street":"Deventerwg",
    "iso:country":"NL",
    "sg:address":"Deventerwg 29A",
    "sg:city":"Bathmen",
    "sg:orig_category":"Schilders",
    "sg:phone":"+31 570 542 660",
    "sg:postcode":"7437 BH",
    "sg:province":"Overijssel",
    "sg:website":"http://www.benniebieleman.nl",
    "wof:name":"Bieleman, Bennie",
    "wof:placetype":"venue"
},
  "geometry": {"coordinates":[6.277959,52.249725],"type":"Point"}
}