{
  "type": "Feature",
  "properties": {
    "addr:full":"Postbus 52 Balk Friesland 8560 AB",
    "addr:housenumber":"52",
    "addr:postcode":"8560 ab",
    "addr:street":"Postbus",
    "iso:country":"NL",
    "sg:address":"Postbus 52",
    "sg:city":"Balk",
    "sg:orig_category":"Waterbehandeling En Waterzuiverings- Systemen",
    "sg:phone":"+31 514 608 500",
    "sg:postcode":"8560 AB",
    "sg:province":"Friesland",
    "wof:name":"Paques Bv",
    "wof:placetype":"venue"
},
  "geometry": {"coordinates":[-100.8285827637,36.6088294983],"type":"Point"}
}