{
  "type": "Feature",
  "properties": {
    "addr:full":"Lusthofln 2 Leiden Zuid-Holland 2316 JA",
    "addr:housenumber":"2",
    "addr:postcode":"2316 ja",
    "addr:street":"Lusthofln",
    "iso:country":"NL",
    "sg:address":"Lusthofln 2",
    "sg:city":"Leiden",
    "sg:orig_category":"Scholen Voor Basisonderwijs",
    "sg:phone":"+31 71 521 8471",
    "sg:postcode":"2316 JA",
    "sg:province":"Zuid-Holland",
    "wof:name":"Singel Rk, De",
    "wof:placetype":"venue"
},
  "geometry": {"coordinates":[4.504181,52.163586],"type":"Point"}
}