{
  "type": "Feature",
  "properties": {
    "addr:full":"Stationsstraat 13 Volendam Noord-Holland 1131 ZN",
    "addr:housenumber":"13",
    "addr:postcode":"1131 zn",
    "addr:street":"Stationsstraat",
    "iso:country":"NL",
    "sg:address":"Stationsstraat 13",
    "sg:city":"Volendam",
    "sg:orig_category":"Zuivelproducten",
    "sg:phone":"+31 299 363 927",
    "sg:postcode":"1131 ZN",
    "sg:province":"Noord-Holland",
    "wof:name":"Vof Maas",
    "wof:placetype":"venue"
},
  "geometry": {"coordinates":[5.073801,52.493954],"type":"Point"}
}