{
  "type": "Feature",
  "properties": {
    "addr:full":"Randstad 22 125 Almere NL. 1316 BW",
    "addr:housenumber":"125",
    "addr:postcode":"1316 bw",
    "addr:street":"Randstad 22;Nl.",
    "iso:country":"NL",
    "sg:address":"Randstad 22 125",
    "sg:city":"Almere",
    "sg:orig_category":"Verzekeringen - Verzekeringskantoren",
    "sg:phone":"+31 36 530 6295",
    "sg:postcode":"1316 BW",
    "sg:province":"NL.",
    "wof:name":"Diagnose Groep Vof",
    "wof:placetype":"venue"
},
  "geometry": {"coordinates":[5.227952,52.378349],"type":"Point"}
}