{
  "type": "Feature",
  "properties": {
    "addr:full":"Pop Dijkemaweg 45 Groningen Groningen 9731 BD",
    "addr:housenumber":"45",
    "addr:postcode":"9731 bd",
    "addr:street":"Pop Dijkemaweg",
    "iso:country":"NL",
    "sg:address":"Pop Dijkemaweg 45",
    "sg:city":"Groningen",
    "sg:orig_category":"Zuivelproducten And Spijsoli?n Gh",
    "sg:phone":"+31 50 549 2633",
    "sg:postcode":"9731 BD",
    "sg:province":"Groningen",
    "wof:name":"Vof Gebroeders Van Dijken",
    "wof:placetype":"venue"
},
  "geometry": {"coordinates":[6.591366,53.230797],"type":"Point"}
}