{
  "type": "Feature",
  "properties": {
    "addr:full":"Schoolstraat 1 Bedum Groningen 9781 JL",
    "addr:housenumber":"1",
    "addr:postcode":"9781 jl",
    "addr:street":"Schoolstraat",
    "iso:country":"NL",
    "sg:address":"Schoolstraat 1",
    "sg:city":"Bedum",
    "sg:orig_category":"Overheidsdiensten",
    "sg:phone":"+31 50 301 8911",
    "sg:postcode":"9781 JL",
    "sg:province":"Groningen",
    "wof:name":"Gemeente Bedum",
    "wof:placetype":"venue"
},
  "geometry": {"coordinates":[6.600897789,53.3007049561],"type":"Point"}
}