{
  "type": "Feature",
  "properties": {
    "iso:country":"NL",
    "sg:address":"Grote Beukelaer 18",
    "sg:city":"Heino",
    "sg:orig_category":"Verzekeringen",
    "sg:phone":"+31 572 390 699",
    "sg:postcode":"8141 BP",
    "sg:province":"Overijssel",
    "wof:name":"Evon Advies",
    "wof:placetype":"venue"
},
  "geometry": {"coordinates":[-95.398735,46.498905],"type":"Point"}
}