{
  "type": "Feature",
  "properties": {
    "addr:full":"Derde Stationsstraat 345 Zoetermeer South Holland 2718 AJ",
    "addr:housenumber":"345",
    "addr:postcode":"2718 aj",
    "addr:street":"Derde Stationsstraat",
    "iso:country":"NL",
    "sg:address":"Derde Stationsstraat 345",
    "sg:city":"Zoetermeer",
    "sg:orig_category":"Bloemen And Planten",
    "sg:phone":"+31 79 361 1090",
    "sg:postcode":"2718 AJ",
    "sg:province":"South Holland",
    "wof:name":"Hutuin Bv",
    "wof:placetype":"venue"
},
  "geometry": {"coordinates":[4.483366,52.042],"type":"Point"}
}