{
  "type": "Feature",
  "properties": {
    "iso:country":"NL",
    "sg:address":"Zutphenseweg 176",
    "sg:city":"Eefde",
    "sg:classifiers":[
        {
            "category":"Retail",
            "subcategory":"Storage",
            "type":"Services"
        }
    ],
    "sg:phone":"+31 575 543 777",
    "sg:postcode":"7211 EJ",
    "sg:province":"Gelderland",
    "sg:tags":[
        "opslag",
        "bewaring"
    ],
    "wof:name":"Topslag Magazijninrichting Bv",
    "wof:placetype":"venue"
},
  "geometry": {"coordinates":[6.2259612083,52.1701660156],"type":"Point"}
}