{
  "type": "Feature",
  "properties": {
    "iso:country":"NL",
    "sg:address":"Herckenrathstr 1",
    "sg:city":"Monster",
    "sg:orig_category":"Accountants - Administratie- Consulenten En -Kantoren",
    "sg:phone":"+31 174 212 331",
    "sg:postcode":"2681 DG",
    "sg:province":"Zuid-Holland",
    "wof:name":"Janszen Bv",
    "wof:placetype":"venue"
},
  "geometry": {"coordinates":[-84.369049,40.363762],"type":"Point"}
}