{
  "type": "Feature",
  "properties": {
    "addr:full":"Heerderweg 37 Maastricht Limburg 6224 LA",
    "addr:housenumber":"37",
    "addr:postcode":"6224 la",
    "addr:street":"Heerderweg",
    "iso:country":"NL",
    "sg:address":"Heerderweg 37",
    "sg:city":"Maastricht",
    "sg:orig_category":"Autokeuringen",
    "sg:phone":"+31 43 362 0046",
    "sg:postcode":"6224 LA",
    "sg:province":"Limburg",
    "wof:name":"M & D Autobanden",
    "wof:placetype":"venue"
},
  "geometry": {"coordinates":[5.708402,50.84621],"type":"Point"}
}