{
  "type": "Feature",
  "properties": {
    "iso:country":"NL",
    "sg:address":"Marconistraat 31",
    "sg:city":"Rotterdam",
    "sg:orig_category":"Fruit And Groenten Gh",
    "sg:phone":"+31 10 425 5700",
    "sg:postcode":"3029 AG",
    "sg:province":"Zuid-Holland",
    "wof:name":"Hint Fruit Import Bv",
    "wof:placetype":"venue"
},
  "geometry": {"coordinates":[4.425376,51.912479],"type":"Point"}
}