{
  "type": "Feature",
  "properties": {
    "addr:full":"Marconistraat 31 Rotterdam Zuid-Holland 3029 AG",
    "addr:housenumber":"31",
    "addr:postcode":"3029",
    "addr:street":"Marconistraat",
    "iso:country":"NL",
    "sg:address":"Marconistraat 31",
    "sg:city":"Rotterdam",
    "sg:orig_category":"Fruit And Groenten Gh",
    "sg:phone":"+31 10 425 5700",
    "sg:postcode":"3029 AG",
    "sg:province":"Zuid-Holland",
    "wof:name":"Hint Fruit Import Bv",
    "wof:placetype":"venue"
},
  "geometry": {"coordinates":[4.425376,51.912479],"type":"Point"}
}