{
  "type": "Feature",
  "properties": {
    "addr:full":"Europalaan 4 Nuth Limburg 6361 CV",
    "addr:housenumber":"4",
    "addr:postcode":"6361 cv",
    "addr:street":"Europalaan",
    "iso:country":"NL",
    "sg:address":"Europalaan 4",
    "sg:city":"Nuth",
    "sg:orig_category":"Juridische Dienstverlening",
    "sg:phone":"+31 45 524 6002",
    "sg:postcode":"6361 CV",
    "sg:province":"Limburg",
    "wof:name":"M. Scholten",
    "wof:placetype":"venue"
},
  "geometry": {"coordinates":[5.879228,50.91188],"type":"Point"}
}