{
  "type": "Feature",
  "properties": {
    "addr:full":"Damakkerwg 16 Otterlo Gelderland 6731 DA",
    "addr:housenumber":"16",
    "addr:postcode":"6731 da",
    "addr:street":"Damakkerwg;Gelderland",
    "iso:country":"NL",
    "sg:address":"Damakkerwg 16",
    "sg:city":"Otterlo",
    "sg:orig_category":"Paardensport",
    "sg:phone":"+31 318 595 052",
    "sg:postcode":"6731 DA",
    "sg:province":"Gelderland",
    "sg:website":"http://www.elysahof.nl",
    "wof:name":"Elysahof Paardenhouderij Vof",
    "wof:placetype":"venue"
},
  "geometry": {"coordinates":[5.740046,52.102798],"type":"Point"}
}