{
  "type": "Feature",
  "properties": {
    "addr:full":"Brouwerijstraat 13 Kloosterzande Zeeland 4587 BZ",
    "addr:housenumber":"13",
    "addr:postcode":"4587 bz",
    "addr:street":"Brouwerijstraat",
    "iso:country":"NL",
    "sg:address":"Brouwerijstraat 13",
    "sg:city":"Kloosterzande",
    "sg:orig_category":"Kinderopvang Behalve Thuis",
    "sg:phone":"+31 114 683 130",
    "sg:postcode":"4587 BZ",
    "sg:province":"Zeeland",
    "wof:name":"Kinderopvang Kiekeboe",
    "wof:placetype":"venue"
},
  "geometry": {"coordinates":[4.009087,51.368713],"type":"Point"}
}