{
  "type": "Feature",
  "properties": {
    "addr:full":"Frambozengaard 39 Wijk Bij Duurstede Utrecht 3962 JT",
    "addr:housenumber":"39",
    "addr:postcode":"3962 jt",
    "addr:street":"Frambozengaard",
    "iso:country":"NL",
    "sg:address":"Frambozengaard 39",
    "sg:city":"Wijk Bij Duurstede",
    "sg:orig_category":"Onderhoud And Reparatie Kantoorapparatuur",
    "sg:phone":"+31 343 571 086",
    "sg:postcode":"3962 JT",
    "sg:province":"Utrecht",
    "wof:name":"S.P.C. Spliet Personal Computers",
    "wof:placetype":"venue"
},
  "geometry": {"coordinates":[5.344972,51.983467],"type":"Point"}
}