{
  "type": "Feature",
  "properties": {
    "addr:full":"De Olmen 17 Bergschenhoek Zuid-Holland 2661 AT",
    "addr:housenumber":"17",
    "addr:postcode":"2661",
    "addr:street":"De Olmen",
    "iso:country":"NL",
    "sg:address":"De Olmen 17",
    "sg:city":"Bergschenhoek",
    "sg:orig_category":"Webdesign Bureaus",
    "sg:phone":"+31 10 522 3040",
    "sg:postcode":"2661 AT",
    "sg:province":"Zuid-Holland",
    "sg:website":"http://www.mixtrix.nl",
    "wof:name":"Mixtrix",
    "wof:placetype":"venue"
},
  "geometry": {"coordinates":[4.4965047836,51.990852356],"type":"Point"}
}