{
  "type": "Feature",
  "properties": {
    "addr:full":"Aalsdk 4A Buren Gld Gelderland 4116 LN",
    "addr:housenumber":"4a",
    "addr:postcode":"4116 ln",
    "addr:street":"Aalsdk;Gld Gelderland",
    "iso:country":"NL",
    "sg:address":"Aalsdk 4A",
    "sg:city":"Buren Gld",
    "sg:orig_category":"Adviesbureaus Bedrijfsorganisatie",
    "sg:phone":"+31 345 502 725",
    "sg:postcode":"4116 LN",
    "sg:province":"Gelderland",
    "wof:name":"Grosman Bv",
    "wof:placetype":"venue"
},
  "geometry": {"coordinates":[5.343409,51.925564],"type":"Point"}
}