{
  "type": "Feature",
  "properties": {
    "addr:full":"Papenbroeksstg 2 Amsterdam Noord-Holland 1012 NW",
    "addr:housenumber":"2",
    "addr:postcode":"1012 nw",
    "addr:street":"Papenbroeksstg",
    "iso:country":"NL",
    "sg:address":"Papenbroeksstg 2",
    "sg:city":"Amsterdam",
    "sg:orig_category":"Luchtvaart- Maatschappijen",
    "sg:phone":"+31 20 624 8109",
    "sg:postcode":"1012 NW",
    "sg:province":"Noord-Holland",
    "wof:name":"Air India Ltd",
    "wof:placetype":"venue"
},
  "geometry": {"coordinates":[4.892454,52.372299],"type":"Point"}
}