{
  "type": "Feature",
  "properties": {
    "addr:full":"Klapstraat 76 Arnhem Gelderland 6842 AG",
    "addr:housenumber":"76",
    "addr:postcode":"6842",
    "addr:street":"Klapstraat",
    "iso:country":"NL",
    "sg:address":"Klapstraat 76",
    "sg:city":"Arnhem",
    "sg:orig_category":"Huishoudapparatuur, Televisies And Radio'S",
    "sg:phone":"+31 26 381 4898",
    "sg:postcode":"6842 AG",
    "sg:province":"Gelderland",
    "wof:name":"Debo Tv Audio Video",
    "wof:placetype":"venue"
},
  "geometry": {"coordinates":[5.878547,51.964882],"type":"Point"}
}