{
  "type": "Feature",
  "properties": {
    "addr:full":"Finsestr 1 Zutphen Gelderland 7202 CE",
    "addr:housenumber":"1",
    "addr:postcode":"7202 ce",
    "addr:street":"Finsestr;Gelderland",
    "iso:country":"NL",
    "sg:address":"Finsestr 1",
    "sg:city":"Zutphen",
    "sg:orig_category":"Verpakkingsbedrijven",
    "sg:phone":"+31 575 599 500",
    "sg:postcode":"7202 CE",
    "sg:province":"Gelderland",
    "sg:website":"http://www.alcanpackaging.com",
    "wof:name":"Lawson Mardon Picopac Bv",
    "wof:placetype":"venue"
},
  "geometry": {"coordinates":[6.204001,52.154964],"type":"Point"}
}