{
  "type": "Feature",
  "properties": {
    "iso:country":"NL",
    "sg:address":"Churchillstraat 71",
    "sg:city":"Barneveld",
    "sg:orig_category":"Werving And Selectie Van Vast Personeel",
    "sg:phone":"+31 342 422 090",
    "sg:postcode":"3772 KV",
    "sg:province":"Gelderland",
    "wof:name":"Master Data Systems Bv",
    "wof:placetype":"venue"
},
  "geometry": {"coordinates":[5.5841789246,52.1347503662],"type":"Point"}
}