{
  "type": "Feature",
  "properties": {
    "iso:country":"NL",
    "sg:address":"Kerklaan 450",
    "sg:city":"Capelle A/D Ijssel",
    "sg:orig_category":"Banken And Kredietinstellingen",
    "sg:phone":"+31 10 459 3500",
    "sg:postcode":"2903 HJ",
    "sg:province":"Zuid-Holland",
    "wof:name":"Ing Bank",
    "wof:placetype":"venue"
},
  "geometry": {"coordinates":[4.59039,51.932411],"type":"Point"}
}