{
  "type": "Feature",
  "properties": {
    "addr:full":"Goirkestr 65 Tilburg Noord-Brabant 5046 GD",
    "addr:housenumber":"65",
    "addr:postcode":"5046 gd",
    "addr:street":"Goirkestr",
    "iso:country":"NL",
    "sg:address":"Goirkestr 65",
    "sg:city":"Tilburg",
    "sg:orig_category":"Zoetwaren - Winkels",
    "sg:phone":"+31 13 542 0198",
    "sg:postcode":"5046 GD",
    "sg:province":"Noord-Brabant",
    "wof:name":"Snoepwinkeltje, 'T",
    "wof:placetype":"venue"
},
  "geometry": {"coordinates":[5.080455,51.572918],"type":"Point"}
}