{
  "type": "Feature",
  "properties": {
    "addr:full":"Nieuwe Waterwegstraat 5 Schiedam South Holland 3115 HE",
    "addr:housenumber":"5",
    "addr:postcode":"3115 he",
    "addr:street":"Nieuwe Waterwegstraat",
    "iso:country":"NL",
    "sg:address":"Nieuwe Waterwegstraat 5",
    "sg:city":"Schiedam",
    "sg:orig_category":"Metalen And Ertsen Gh",
    "sg:phone":"+31 10 426 8155",
    "sg:postcode":"3115 HE",
    "sg:province":"South Holland",
    "wof:name":"Technische Handelsonderneming J. Hersbach Bv",
    "wof:placetype":"venue"
},
  "geometry": {"coordinates":[4.384866,51.903599],"type":"Point"}
}