{
  "type": "Feature",
  "properties": {
    "addr:full":"Postbus 70 Overveen Noord-Holland 2050 AB",
    "addr:housenumber":"70",
    "addr:postcode":"2050 ab",
    "addr:street":"Postbus",
    "iso:country":"NL",
    "sg:address":"Postbus 70",
    "sg:city":"Overveen",
    "sg:orig_category":"Vertalers",
    "sg:phone":"+31 23 527 4074",
    "sg:postcode":"2050 AB",
    "sg:province":"Noord-Holland",
    "wof:name":"Os, T Van",
    "wof:placetype":"venue"
},
  "geometry": {"coordinates":[4.61159,52.391682],"type":"Point"}
}