{
  "type": "Feature",
  "properties": {
    "addr:full":"Pelikaanstr 59 Assen Provincie Drenthe 9404 CJ",
    "addr:housenumber":"59",
    "addr:postcode":"9404 cj",
    "addr:street":"Pelikaanstr;Provincie Drenthe",
    "iso:country":"NL",
    "sg:address":"Pelikaanstr 59",
    "sg:city":"Assen",
    "sg:orig_category":"Webdesign Bureaus",
    "sg:phone":"+31 592 311 027",
    "sg:postcode":"9404 CJ",
    "sg:province":"Provincie Drenthe",
    "wof:name":"Porretje",
    "wof:placetype":"venue"
},
  "geometry": {"coordinates":[6.5766048431,52.9900093079],"type":"Point"}
}