{
  "type": "Feature",
  "properties": {
    "iso:country":"NL",
    "sg:address":"Cromhoutstraat 27",
    "sg:city":"Enkhuizen",
    "sg:orig_category":"Technische Studies And Onderzoek",
    "sg:phone":"+31 228 317 530",
    "sg:postcode":"1601 EA",
    "sg:province":"North Holland",
    "wof:name":"Kleijweg Design",
    "wof:placetype":"venue"
},
  "geometry": {"coordinates":[5.283832,52.699959],"type":"Point"}
}