{
  "type": "Feature",
  "properties": {
    "iso:country":"NL",
    "sg:address":"Houthemerweg 90",
    "sg:city":"Meerssen",
    "sg:orig_category":"Kampeerterreinen",
    "sg:phone":"+31 43 364 2085",
    "sg:postcode":"6231 KW",
    "sg:province":"Limburg",
    "wof:name":"A.N.W.B. Kampeercentrum Aan Geul En Bos",
    "wof:placetype":"venue"
},
  "geometry": {"coordinates":[5.772110939,50.8778572083],"type":"Point"}
}