{
  "type": "Feature",
  "properties": {
    "addr:full":"Bevrijdingsweg 7 Kaatsheuvel Noord-Brabant 5171 PS",
    "addr:housenumber":"7",
    "addr:postcode":"5171 ps",
    "addr:street":"Bevrijdingsweg",
    "iso:country":"NL",
    "sg:address":"Bevrijdingsweg 7",
    "sg:city":"Kaatsheuvel",
    "sg:orig_category":"Diverse Bedrijfsinstallaties Gh",
    "sg:phone":"+31 416 541 280",
    "sg:postcode":"5171 PS",
    "sg:province":"Noord-Brabant",
    "wof:name":"Isco Fournituren",
    "wof:placetype":"venue"
},
  "geometry": {"coordinates":[5.036206,51.664818],"type":"Point"}
}