{
  "type": "Feature",
  "properties": {
    "addr:full":"Wooldstraat 41 Winterswijk Gelderland 7101 NN",
    "addr:housenumber":"41",
    "addr:postcode":"7101 nn",
    "addr:street":"Wooldstraat;Gelderland",
    "iso:country":"NL",
    "sg:address":"Wooldstraat 41",
    "sg:city":"Winterswijk",
    "sg:orig_category":"Huishoudelijk Textiel Fab",
    "sg:phone":"+31 543 531 550",
    "sg:postcode":"7101 NN",
    "sg:province":"Gelderland",
    "wof:name":"Costello Clothing",
    "wof:placetype":"venue"
},
  "geometry": {"coordinates":[6.721167,51.970432],"type":"Point"}
}