{
  "type": "Feature",
  "properties": {
    "addr:full":"Molenplein 5 Ter Apel Groningen 9561 KS",
    "addr:housenumber":"5",
    "addr:postcode":"9561 ks",
    "addr:street":"Molenplein",
    "iso:country":"NL",
    "sg:address":"Molenplein 5",
    "sg:city":"Ter Apel",
    "sg:orig_category":"Kappers",
    "sg:phone":"+31 599 587 277",
    "sg:postcode":"9561 KS",
    "sg:province":"Groningen",
    "wof:name":"Salon Van Oost",
    "wof:placetype":"venue"
},
  "geometry": {"coordinates":[7.062042,52.874905],"type":"Point"}
}