{
  "type": "Feature",
  "properties": {
    "addr:full":"Grootzand 9 Sneek Friesland 8601 AR",
    "addr:housenumber":"9",
    "addr:postcode":"8601",
    "addr:street":"Grootzand",
    "iso:country":"NL",
    "sg:address":"Grootzand 9",
    "sg:city":"Sneek",
    "sg:orig_category":"Fotolaboratoria",
    "sg:phone":"+31 515 413 144",
    "sg:postcode":"8601 AR",
    "sg:province":"Friesland",
    "wof:name":"Foto Flashlight",
    "wof:placetype":"venue"
},
  "geometry": {"coordinates":[5.661015,53.03178],"type":"Point"}
}