{
  "type": "Feature",
  "properties": {
    "addr:full":"Zandwg 205 De Meern Utrecht 3454 HE",
    "addr:housenumber":"205",
    "addr:postcode":"3454 he",
    "iso:country":"NL",
    "sg:address":"Zandwg 205",
    "sg:city":"De Meern",
    "sg:classifiers":[
        {
            "category":"Sports & Exercise",
            "subcategory":"Stables",
            "type":"Entertainment"
        }
    ],
    "sg:phone":"+31 30 666 4871",
    "sg:postcode":"3454 HE",
    "sg:province":"Utrecht",
    "sg:tags":[
        "maneges"
    ],
    "wof:name":"Voornruiters, De",
    "wof:placetype":"venue"
},
  "geometry": {"coordinates":[5.017688,52.086452],"type":"Point"}
}