{
  "type": "Feature",
  "properties": {
    "addr:full":"Wylerbaan 23 Groesbeek Gelderland 6561 KN",
    "addr:housenumber":"23",
    "addr:postcode":"6561 kn",
    "addr:street":"Wylerbaan;Gelderland",
    "iso:country":"NL",
    "sg:address":"Wylerbaan 23",
    "sg:city":"Groesbeek",
    "sg:orig_category":"Bloemen En Planten",
    "sg:phone":"+31 24 397 5108",
    "sg:postcode":"6561 KN",
    "sg:province":"Gelderland",
    "wof:name":"Pujari Plattel",
    "wof:placetype":"venue"
},
  "geometry": {"coordinates":[5.943496,51.790009],"type":"Point"}
}