{
  "type": "Feature",
  "properties": {
    "addr:full":"Haverstr Passage 12 Enschede Overijssel 7511 EW",
    "addr:housenumber":"12",
    "addr:postcode":"7511 ew",
    "addr:street":"Passage",
    "iso:country":"NL",
    "sg:address":"Haverstr Passage 12",
    "sg:city":"Enschede",
    "sg:orig_category":"Drogisterijen",
    "sg:phone":"+31 53 430 1470",
    "sg:postcode":"7511 EW",
    "sg:province":"Overijssel",
    "wof:name":"Kruidvat",
    "wof:placetype":"venue"
},
  "geometry": {"coordinates":[6.898073,52.219879],"type":"Point"}
}