{
  "type": "Feature",
  "properties": {
    "addr:full":"V Polanenpk 296 Wassenaar Zuid-Holland 2241 SB",
    "addr:housenumber":"296",
    "addr:postcode":"2241 sb",
    "iso:country":"NL",
    "sg:address":"V Polanenpk 296",
    "sg:city":"Wassenaar",
    "sg:orig_category":"Onderhoudswerken",
    "sg:phone":"+31 70 517 7013",
    "sg:postcode":"2241 SB",
    "sg:province":"Zuid-Holland",
    "wof:name":"Keijzer, Paul",
    "wof:placetype":"venue"
},
  "geometry": {"coordinates":[4.393863,52.14307],"type":"Point"}
}