{
  "type": "Feature",
  "properties": {
    "addr:full":"Huygensstraat 45 Hilversum Noord-Holland 1222 TJ",
    "addr:housenumber":"45",
    "addr:postcode":"1222 tj",
    "addr:street":"Huygensstraat",
    "iso:country":"NL",
    "sg:address":"Huygensstraat 45",
    "sg:city":"Hilversum",
    "sg:orig_category":"Geluidsopnamen",
    "sg:phone":"+31 35 683 2291",
    "sg:postcode":"1222 TJ",
    "sg:province":"Noord-Holland",
    "wof:name":"Dingo Holland",
    "wof:placetype":"venue"
},
  "geometry": {"coordinates":[5.182079,52.230934],"type":"Point"}
}