{
  "type": "Feature",
  "properties": {
    "addr:full":"Valkseweg 47 Barneveld Gelderland 3771 RC",
    "addr:housenumber":"47",
    "addr:postcode":"3771 rc",
    "addr:street":"Valkseweg;Gelderland",
    "iso:country":"NL",
    "sg:address":"Valkseweg 47",
    "sg:city":"Barneveld",
    "sg:orig_category":"Mobiele Service Aan Motorvoertuigen",
    "sg:phone":"+31 342 413 590",
    "sg:postcode":"3771 RC",
    "sg:province":"Gelderland",
    "wof:name":"Vof Rosendal",
    "wof:placetype":"venue"
},
  "geometry": {"coordinates":[5.597206,52.135048],"type":"Point"}
}