{
  "type": "Feature",
  "properties": {
    "iso:country":"NL",
    "sg:address":"De Hoefkens 25",
    "sg:city":"Moergestel",
    "sg:orig_category":"Keukens",
    "sg:phone":"+31 13 513 6195",
    "sg:postcode":"5066 BX",
    "sg:province":"North Brabant",
    "wof:name":"Meijdenberg, R Van Den",
    "wof:placetype":"venue"
},
  "geometry": {"coordinates":[5.171843,51.547508],"type":"Point"}
}