{
  "type": "Feature",
  "properties": {
    "iso:country":"NL",
    "sg:address":"Paulus Potterstraat 1",
    "sg:city":"Rijnsburg",
    "sg:orig_category":"Bloemen And Planten Gh",
    "sg:phone":"+31 71 402 5107",
    "sg:postcode":"2231 BX",
    "sg:province":"Zuid-Holland",
    "wof:name":"K. Notenboom Bloemenexport",
    "wof:placetype":"venue"
},
  "geometry": {"coordinates":[4.431215,52.186703],"type":"Point"}
}