{
  "type": "Feature",
  "properties": {
    "addr:full":"Robinsonstraat 136 Leeuwarden Friesland 8923 AX",
    "addr:housenumber":"136",
    "addr:postcode":"8923 ax",
    "addr:street":"Robinsonstraat",
    "iso:country":"NL",
    "sg:address":"Robinsonstraat 136",
    "sg:city":"Leeuwarden",
    "sg:classifiers":[
        {
            "category":"Fast Food",
            "type":"Food & Drink"
        }
    ],
    "sg:phone":"+31 58 266 5956",
    "sg:postcode":"8923 AX",
    "sg:province":"Friesland",
    "sg:tags":[
        "afhaal",
        "restaurant"
    ],
    "wof:name":"S Sinnema",
    "wof:placetype":"venue"
},
  "geometry": {"coordinates":[5.816415,53.216187],"type":"Point"}
}