{
  "type": "Feature",
  "properties": {
    "addr:full":"V Duivenvoordestr 13 Hensbroek Noord-Holland 1711 KD",
    "addr:housenumber":"13",
    "addr:postcode":"1711 kd",
    "addr:street":"V Duivenvoordestr",
    "iso:country":"NL",
    "sg:address":"V Duivenvoordestr 13",
    "sg:city":"Hensbroek",
    "sg:orig_category":"Bedrijfsmechanisatie En -Automatisering",
    "sg:phone":"+31 226 450 126",
    "sg:postcode":"1711 KD",
    "sg:province":"Noord-Holland",
    "wof:name":"Te Winkel",
    "wof:placetype":"venue"
},
  "geometry": {"coordinates":[4.885502,52.657707],"type":"Point"}
}