{
  "type": "Feature",
  "properties": {
    "addr:full":"Goudhaver 63 Zeewolde Flevoland 3892 BJ",
    "addr:housenumber":"63",
    "addr:postcode":"3892 bj",
    "addr:street":"Goudhaver;Flevoland",
    "iso:country":"NL",
    "sg:address":"Goudhaver 63",
    "sg:city":"Zeewolde",
    "sg:orig_category":"Adviesbureaus Bedrijfsorganisatie",
    "sg:phone":"+31 36 522 1322",
    "sg:postcode":"3892 BJ",
    "sg:province":"Flevoland",
    "wof:name":"Libra",
    "wof:placetype":"venue"
},
  "geometry": {"coordinates":[5.547491,52.324879],"type":"Point"}
}