{
  "type": "Feature",
  "properties": {
    "addr:full":"E Wolffstr 80Hs Amsterdam Noord-Holland 1053 TW",
    "addr:postcode":"1053 tw",
    "iso:country":"NL",
    "sg:address":"E Wolffstr 80Hs",
    "sg:city":"Amsterdam",
    "sg:orig_category":"Webdesign Bureaus",
    "sg:phone":"+31 20 689 3795",
    "sg:postcode":"1053 TW",
    "sg:province":"Noord-Holland",
    "wof:name":"Mulder",
    "wof:placetype":"venue"
},
  "geometry": {"coordinates":[4.8676781654,52.3687286377],"type":"Point"}
}