{
  "type": "Feature",
  "properties": {
    "addr:full":"Minervum 7076 Breda North Brabant 4817 ZK",
    "addr:housenumber":"7076",
    "addr:postcode":"4817",
    "addr:street":"Minervum;Zk",
    "iso:country":"NL",
    "sg:address":"Minervum 7076",
    "sg:city":"Breda",
    "sg:orig_category":"Fotostudio'S And Fotografen",
    "sg:phone":"+31 76 571 5148",
    "sg:postcode":"4817 ZK",
    "sg:province":"North Brabant",
    "wof:name":"Foto Studio Evs",
    "wof:placetype":"venue"
},
  "geometry": {"coordinates":[4.83315,51.588089],"type":"Point"}
}