{
  "type": "Feature",
  "properties": {
    "iso:country":"NL",
    "sg:address":"Westerwijzend 65",
    "sg:city":"Hoogkarspel",
    "sg:orig_category":"Metaalwerken",
    "sg:phone":"+31 228 562 445",
    "sg:postcode":"1616 LB",
    "sg:province":"Noord-Holland",
    "wof:name":"L.W.E. Van Amerongen",
    "wof:placetype":"venue"
},
  "geometry": {"coordinates":[5.169262,52.687458],"type":"Point"}
}