{
  "type": "Feature",
  "properties": {
    "iso:country":"NL",
    "sg:address":"Korte Nieuwstraat 139",
    "sg:city":"Utrecht",
    "sg:orig_category":"Begrafenisondernemers",
    "sg:phone":"+31 30 233 2676",
    "sg:postcode":"3512 NM",
    "sg:province":"Utrecht",
    "wof:name":"Drs. T.C. Bakker",
    "wof:placetype":"venue"
},
  "geometry": {"coordinates":[5.122293,52.088913],"type":"Point"}
}