{
  "type": "Feature",
  "properties": {
    "addr:full":"Bereklauw 6 Huizen North Holland 1273 TM",
    "addr:housenumber":"6",
    "addr:postcode":"1273 tm",
    "addr:street":"Bereklauw",
    "iso:country":"NL",
    "sg:address":"Bereklauw 6",
    "sg:city":"Huizen",
    "sg:orig_category":"Hoger Onderwijs",
    "sg:phone":"+31 35 525 0651",
    "sg:postcode":"1273 TM",
    "sg:province":"North Holland",
    "wof:name":"Oosterse Film-, Tv-, Theater- En Kunstac",
    "wof:placetype":"venue"
},
  "geometry": {"coordinates":[5.253375,52.304565],"type":"Point"}
}