{
  "type": "Feature",
  "properties": {
    "addr:full":"Nieuwendammerdk 297 Amsterdam Noord-Holland 1025 LM",
    "addr:housenumber":"297",
    "addr:postcode":"1025 lm",
    "iso:country":"NL",
    "sg:address":"Nieuwendammerdk 297",
    "sg:city":"Amsterdam",
    "sg:orig_category":"Administratie- En Boekhoudkantoren",
    "sg:phone":"+31 20 632 7466",
    "sg:postcode":"1025 LM",
    "sg:province":"Noord-Holland",
    "sg:website":"http://www.dejong-deruyter.nl",
    "wof:name":"Jong + De Ruyter Bv, De",
    "wof:placetype":"venue"
},
  "geometry": {"coordinates":[4.9331,52.391609],"type":"Point"}
}