{
  "type": "Feature",
  "properties": {
    "addr:full":"Postbus 86 Wageningen Gelderland 6700 AB",
    "addr:housenumber":"86",
    "addr:postcode":"6700 ab",
    "addr:street":"Postbus;Gelderland",
    "iso:country":"NL",
    "sg:address":"Postbus 86",
    "sg:city":"Wageningen",
    "sg:orig_category":"Adviesbureaus Financieel",
    "sg:phone":"+31 317 426 132",
    "sg:postcode":"6700 AB",
    "sg:province":"Gelderland",
    "sg:website":"http://www.optiewinst.nl",
    "wof:name":"Option Advisors",
    "wof:placetype":"venue"
},
  "geometry": {"coordinates":[5.660976,51.964355],"type":"Point"}
}