{
  "type": "Feature",
  "properties": {
    "addr:full":"Sint Josephpark 1 Blokker Noord-Holland 1695 AM",
    "addr:housenumber":"1",
    "addr:postcode":"1695",
    "addr:street":"Sint Josephpark",
    "iso:country":"NL",
    "sg:address":"Sint Josephpark 1",
    "sg:city":"Blokker",
    "sg:orig_category":"Bejaardeninstellingen And Serviceflats",
    "sg:phone":"+31 229 240 604",
    "sg:postcode":"1695 AM",
    "sg:province":"Noord-Holland",
    "wof:name":"Stichting Ouderenzorg Blokkerzwaag",
    "wof:placetype":"venue"
},
  "geometry": {"coordinates":[5.091602,52.66312],"type":"Point"}
}