{
  "type": "Feature",
  "properties": {
    "iso:country":"NL",
    "sg:address":"G Gezellestr 7",
    "sg:city":"Oldenzaal",
    "sg:orig_category":"Fotoreportages",
    "sg:phone":"+31 541 520 896",
    "sg:postcode":"7576 AG",
    "sg:province":"NL.08",
    "sg:website":"http://www.pwfoto.nl",
    "wof:name":"Peter Willemsen, Fotografie",
    "wof:placetype":"venue"
},
  "geometry": {"coordinates":[6.909902,52.311817],"type":"Point"}
}