{
  "type": "Feature",
  "properties": {
    "addr:full":"Valkenkamp 649 Maarssen Utrecht 3607 MP",
    "addr:housenumber":"649",
    "addr:postcode":"3607 mp",
    "addr:street":"Valkenkamp",
    "iso:country":"NL",
    "sg:address":"Valkenkamp 649",
    "sg:city":"Maarssen",
    "sg:orig_category":"Makelaars En Adviseurs Onroerende Goederen",
    "sg:phone":"+31 346 569 396",
    "sg:postcode":"3607 MP",
    "sg:province":"Utrecht",
    "wof:name":"Slooten, Van",
    "wof:placetype":"venue"
},
  "geometry": {"coordinates":[5.010806,52.13739],"type":"Point"}
}