{
  "type": "Feature",
  "properties": {
    "addr:full":"Heistr 6A Helmond Noord-Brabant 5701 HN",
    "addr:housenumber":"6a",
    "addr:postcode":"5701 hn",
    "addr:street":"Heistr",
    "iso:country":"NL",
    "sg:address":"Heistr 6A",
    "sg:city":"Helmond",
    "sg:orig_category":"Verenigingen En Stichtingen",
    "sg:phone":"+31 492 537 071",
    "sg:postcode":"5701 HN",
    "sg:province":"Noord-Brabant",
    "wof:name":"Kleerkast, Stichting De",
    "wof:placetype":"venue"
},
  "geometry": {"coordinates":[5.666551,51.483097],"type":"Point"}
}