{
  "type": "Feature",
  "properties": {
    "addr:full":"Azelmastr 5 Zevenbergen North Brabant 4761 AB",
    "addr:housenumber":"5",
    "addr:postcode":"4761 ab",
    "addr:street":"Azelmastr",
    "iso:country":"NL",
    "sg:address":"Azelmastr 5",
    "sg:city":"Zevenbergen",
    "sg:orig_category":"Pottenbakkerijen",
    "sg:phone":"+31 168 325 340",
    "sg:postcode":"4761 AB",
    "sg:province":"North Brabant",
    "wof:name":"Donkisjot",
    "wof:placetype":"venue"
},
  "geometry": {"coordinates":[4.610567,51.643253],"type":"Point"}
}