{
  "type": "Feature",
  "properties": {
    "addr:full":"Scheurkamp 37 Warnsveld Gelderland 7231 EB",
    "addr:housenumber":"37",
    "addr:postcode":"7231 eb",
    "addr:street":"Scheurkamp;Gelderland",
    "iso:country":"NL",
    "sg:address":"Scheurkamp 37",
    "sg:city":"Warnsveld",
    "sg:orig_category":"Autokeuringen",
    "sg:phone":"+31 575 521 555",
    "sg:postcode":"7231 EB",
    "sg:province":"Gelderland",
    "wof:name":"Hms Hydraulische Machinebouw Schieven",
    "wof:placetype":"venue"
},
  "geometry": {"coordinates":[6.225585,52.140984],"type":"Point"}
}