{
  "type": "Feature",
  "properties": {
    "addr:full":"Isebrandtsheerd 46 Groningen Groningen 9737 LH",
    "addr:housenumber":"46",
    "addr:postcode":"9737 lh",
    "addr:street":"Isebrandtsheerd",
    "iso:country":"NL",
    "sg:address":"Isebrandtsheerd 46",
    "sg:city":"Groningen",
    "sg:orig_category":"Adviesbureaus Gezondheidszorg",
    "sg:phone":"+31 50 526 9608",
    "sg:postcode":"9737 LH",
    "sg:province":"Groningen",
    "wof:name":"Bio-Elektra",
    "wof:placetype":"venue"
},
  "geometry": {"coordinates":[6.593055,53.245689],"type":"Point"}
}