{
  "type": "Feature",
  "properties": {
    "addr:full":"Savannahweg 49 Utrecht Utrecht 3542 AW",
    "addr:housenumber":"49",
    "addr:postcode":"3542 aw",
    "addr:street":"Savannahweg",
    "iso:country":"NL",
    "sg:address":"Savannahweg 49",
    "sg:city":"Utrecht",
    "sg:orig_category":"Loodgieterswerk, Verwarming And Sanitaire Installaties",
    "sg:phone":"+31 30 241 3111",
    "sg:postcode":"3542 AW",
    "sg:province":"Utrecht",
    "wof:name":"Feenstra Warmte Totaal Zorg Bv",
    "wof:placetype":"venue"
},
  "geometry": {"coordinates":[5.04409,52.115181],"type":"Point"}
}