{
  "type": "Feature",
  "properties": {
    "addr:full":"J Winklerwei 269 Leeuwarden Friesland 8915 ES",
    "addr:housenumber":"269",
    "addr:postcode":"8915 es",
    "addr:street":"Winklerwei",
    "iso:country":"NL",
    "sg:address":"J Winklerwei 269",
    "sg:city":"Leeuwarden",
    "sg:orig_category":"Lasbedrijven",
    "sg:phone":"+31 6 55868759",
    "sg:postcode":"8915 ES",
    "sg:province":"Friesland",
    "wof:name":"Ez-Mar",
    "wof:placetype":"venue"
},
  "geometry": {"coordinates":[5.76452,53.207081],"type":"Point"}
}