{
  "type": "Feature",
  "properties": {
    "addr:full":"Brink 4 Laren Nh North Holland 1251 KV",
    "addr:housenumber":"4",
    "addr:postcode":"1251 kv",
    "addr:street":"Brink;Nh North",
    "iso:country":"NL",
    "sg:address":"Brink 4",
    "sg:city":"Laren Nh",
    "sg:orig_category":"Bedrijfs- And Managementsconsultants",
    "sg:phone":"+31 35 531 1935",
    "sg:postcode":"1251 KV",
    "sg:province":"North Holland",
    "wof:name":"Bv Zoek Tho A4 Administratie",
    "wof:placetype":"venue"
},
  "geometry": {"coordinates":[5.224232,52.256447],"type":"Point"}
}