{
  "type": "Feature",
  "properties": {
    "addr:full":"Beatrixln 34 Westmaas Zuid-Holland 3273 AB",
    "addr:housenumber":"34",
    "addr:postcode":"3273 ab",
    "addr:street":"Beatrixln",
    "iso:country":"NL",
    "sg:address":"Beatrixln 34",
    "sg:city":"Westmaas",
    "sg:orig_category":"Glazenwasserijen",
    "sg:phone":"+31 186 573 472",
    "sg:postcode":"3273 AB",
    "sg:province":"Zuid-Holland",
    "wof:name":"Montijn",
    "wof:placetype":"venue"
},
  "geometry": {"coordinates":[4.471378,51.786438],"type":"Point"}
}