{
  "type": "Feature",
  "properties": {
    "iso:country":"NL",
    "sg:address":"Dam 9",
    "sg:city":"Amsterdam",
    "sg:orig_category":"Kappers",
    "sg:phone":"+31 20 627 3037",
    "sg:postcode":"1012 JS",
    "sg:province":"Noord-Holland",
    "wof:name":"Douglas, Hans",
    "wof:placetype":"venue"
},
  "geometry": {"coordinates":[4.8943161964,52.3726921082],"type":"Point"}
}