{
  "type": "Feature",
  "properties": {
    "addr:full":"Wyngaardswg 48 B Heerlen Limburg 6412 PJ",
    "addr:housenumber":"48 b",
    "addr:postcode":"6412 pj",
    "addr:street":"Wyngaardswg",
    "iso:country":"NL",
    "sg:address":"Wyngaardswg 48 B",
    "sg:city":"Heerlen",
    "sg:classifiers":[
        {
            "category":"Shopping",
            "subcategory":"Gifts & Souvenirs",
            "type":"Retail Goods"
        }
    ],
    "sg:phone":"+31 45 522 8082",
    "sg:postcode":"6412 PJ",
    "sg:province":"Limburg",
    "sg:tags":[
        "wens-",
        "en",
        "prentbriefkaarten"
    ],
    "wof:name":"Gubbels, B",
    "wof:placetype":"venue"
},
  "geometry": {"coordinates":[5.9450559616,50.9076080322],"type":"Point"}
}