{
  "type": "Feature",
  "properties": {
    "iso:country":"NL",
    "sg:address":"St Pieterstr 19",
    "sg:city":"Kerkrade",
    "sg:orig_category":"Schoenen",
    "sg:phone":"+31 45 545 3844",
    "sg:postcode":"6463 CP",
    "sg:province":"Limburg",
    "wof:name":"Leki",
    "wof:placetype":"venue"
},
  "geometry": {"coordinates":[6.066584,50.874424],"type":"Point"}
}