{
  "type": "Feature",
  "properties": {
    "addr:full":"Kallestraat 3 Hunsel Limburg 6013 RM",
    "addr:housenumber":"3",
    "addr:postcode":"6013 rm",
    "addr:street":"Kallestraat",
    "iso:country":"NL",
    "sg:address":"Kallestraat 3",
    "sg:city":"Hunsel",
    "sg:classifiers":[
        {
            "category":"Retail",
            "subcategory":"Photofinishing",
            "type":"Services"
        }
    ],
    "sg:phone":"+31 475 565 744",
    "sg:postcode":"6013 RM",
    "sg:province":"Limburg",
    "sg:tags":[
        "foto",
        "film"
    ],
    "wof:name":"Foto/Video Giesbertz",
    "wof:placetype":"venue"
},
  "geometry": {"coordinates":[5.812909,51.189693],"type":"Point"}
}