{
  "type": "Feature",
  "properties": {
    "addr:full":"V Wassenaerln 6 Baarn Utrecht 3742 AH",
    "addr:housenumber":"6",
    "addr:postcode":"3742 ah",
    "addr:street":"Wassenaerln",
    "iso:country":"NL",
    "sg:address":"V Wassenaerln 6",
    "sg:city":"Baarn",
    "sg:orig_category":"Hoeden",
    "sg:phone":"+31 35 541 1826",
    "sg:postcode":"3742 AH",
    "sg:province":"Utrecht",
    "wof:name":"Herma De Jong, Hoedenontwerpster",
    "wof:placetype":"venue"
},
  "geometry": {"coordinates":[5.292121,52.21101],"type":"Point"}
}