{
  "type": "Feature",
  "properties": {
    "addr:full":"Dkn Reuvekampln 1 Didam Gelderland 6941 AN",
    "addr:housenumber":"1",
    "addr:postcode":"6941 an",
    "addr:street":"Reuvekampln;Gelderland",
    "iso:country":"NL",
    "sg:address":"Dkn Reuvekampln 1",
    "sg:city":"Didam",
    "sg:classifiers":[
        {
            "category":"Travel",
            "subcategory":"Hotels & Motels",
            "type":"Entertainment"
        }
    ],
    "sg:phone":"+31 316 221 841",
    "sg:postcode":"6941 AN",
    "sg:province":"Gelderland",
    "sg:website":"http://www.liemershof.nl",
    "wof:name":"Liemershof",
    "wof:placetype":"venue"
},
  "geometry": {"coordinates":[6.128371,51.940891],"type":"Point"}
}