{
  "type": "Feature",
  "properties": {
    "addr:full":"De Oeverloper 227 Dronten Flevoland 8251 HL",
    "addr:housenumber":"227",
    "addr:postcode":"8251 hl",
    "addr:street":"De Oeverloper;Flevoland",
    "iso:country":"NL",
    "sg:address":"De Oeverloper 227",
    "sg:city":"Dronten",
    "sg:orig_category":"Administratie- En Boekhoudkantoren",
    "sg:phone":"+31 321 315 382",
    "sg:postcode":"8251 HL",
    "sg:province":"Flevoland",
    "wof:name":"Ferwerda",
    "wof:placetype":"venue"
},
  "geometry": {"coordinates":[5.727503,52.529179],"type":"Point"}
}