{
  "type": "Feature",
  "properties": {
    "addr:full":"De Hosterd 55 Heumen Gelderland 6582 CD",
    "addr:housenumber":"55",
    "addr:postcode":"6582 cd",
    "addr:street":"De Hosterd;Gelderland",
    "iso:country":"NL",
    "sg:address":"De Hosterd 55",
    "sg:city":"Heumen",
    "sg:orig_category":"Milieu",
    "sg:phone":"+31 24 357 3892",
    "sg:postcode":"6582 CD",
    "sg:province":"Gelderland",
    "sg:website":"http://www.idmilieu.com",
    "wof:name":"Id",
    "wof:placetype":"venue"
},
  "geometry": {"coordinates":[5.846608,51.766441],"type":"Point"}
}