{
  "type": "Feature",
  "properties": {
    "addr:full":"Limbrichterstr 48 Sittard Limburg 6131 ED",
    "addr:housenumber":"48",
    "addr:postcode":"6131 ed",
    "addr:street":"Limbrichterstr",
    "iso:country":"NL",
    "sg:address":"Limbrichterstr 48",
    "sg:city":"Sittard",
    "sg:orig_category":"Juweliers",
    "sg:phone":"+31 46 452 4495",
    "sg:postcode":"6131 ED",
    "sg:province":"Limburg",
    "wof:name":"Caprice",
    "wof:placetype":"venue"
},
  "geometry": {"coordinates":[5.868927,50.998089],"type":"Point"}
}