{
  "type": "Feature",
  "properties": {
    "iso:country":"NL",
    "sg:address":"Maaspoort 17",
    "sg:city":"Weert",
    "sg:orig_category":"Bloemen And Planten",
    "sg:phone":"+31 495 524 485",
    "sg:postcode":"6001 BN",
    "sg:province":"Limburg",
    "wof:name":"Vof Bloematelier Mart Huijgen",
    "wof:placetype":"venue"
},
  "geometry": {"coordinates":[5.711062,51.251923],"type":"Point"}
}