{
  "type": "Feature",
  "properties": {
    "addr:full":"Kloosterstr 17 Weert Limburg 6001 XS",
    "addr:housenumber":"17",
    "addr:postcode":"6001 xs",
    "addr:street":"Kloosterstr",
    "iso:country":"NL",
    "sg:address":"Kloosterstr 17",
    "sg:city":"Weert",
    "sg:orig_category":"Verenigingen En Stichtingen",
    "sg:phone":"+31 495 543 858",
    "sg:postcode":"6001 XS",
    "sg:province":"Limburg",
    "wof:name":"Servicebureau Woonconsumenten Limburg",
    "wof:placetype":"venue"
},
  "geometry": {"coordinates":[5.715828,51.258263],"type":"Point"}
}