{
  "type": "Feature",
  "properties": {
    "addr:full":"Ds. Kalshovenweg 11 Elspeet Gelderland 8075 AE",
    "addr:housenumber":"11",
    "addr:postcode":"8075 ae",
    "addr:street":"Ds. Kalshovenweg;Gelderland",
    "iso:country":"NL",
    "sg:address":"Ds. Kalshovenweg 11",
    "sg:city":"Elspeet",
    "sg:orig_category":"Verhuur Voertuigen Behalve Auto'S",
    "sg:phone":"+31 577 491 089",
    "sg:postcode":"8075 AE",
    "sg:province":"Gelderland",
    "wof:name":"Van Der Horst Aanhangwagens",
    "wof:placetype":"venue"
},
  "geometry": {"coordinates":[5.784866,52.292454],"type":"Point"}
}