{
  "type": "Feature",
  "properties": {
    "addr:full":"Suze Groenewegplein 12 Franeker Friesland 8802 MH",
    "addr:housenumber":"12",
    "addr:postcode":"8802 mh",
    "addr:street":"Suze Groenewegplein",
    "iso:country":"NL",
    "sg:address":"Suze Groenewegplein 12",
    "sg:city":"Franeker",
    "sg:orig_category":"Vers Brood And Banket Fab",
    "sg:phone":"+31 517 394 137",
    "sg:postcode":"8802 MH",
    "sg:province":"Friesland",
    "wof:name":"Bakkerij Molter",
    "wof:placetype":"venue"
},
  "geometry": {"coordinates":[5.532337,53.196182],"type":"Point"}
}