{
  "type": "Feature",
  "properties": {
    "addr:full":"Belder 49 Roosendaal Noord-Brabant 4704 RK",
    "addr:housenumber":"49",
    "addr:postcode":"4704 rk",
    "addr:street":"Belder",
    "iso:country":"NL",
    "sg:address":"Belder 49",
    "sg:city":"Roosendaal",
    "sg:orig_category":"Keukens",
    "sg:phone":"+31 165 556 763",
    "sg:postcode":"4704 RK",
    "sg:province":"Noord-Brabant",
    "wof:name":"Bulthaup, Presentatie",
    "wof:placetype":"venue"
},
  "geometry": {"coordinates":[4.461224,51.556244],"type":"Point"}
}