{
  "type": "Feature",
  "properties": {
    "addr:full":"Weidehek 58B Breda Noord-Brabant 4824 AS",
    "addr:housenumber":"58b",
    "addr:postcode":"4824 as",
    "addr:street":"Weidehek",
    "iso:country":"NL",
    "sg:address":"Weidehek 58B",
    "sg:city":"Breda",
    "sg:orig_category":"Schilders",
    "sg:phone":"+31 76 541 0631",
    "sg:postcode":"4824 AS",
    "sg:province":"Noord-Brabant",
    "sg:website":"http://www.schilderalpha.nl",
    "wof:name":"Alpha Bv",
    "wof:placetype":"venue"
},
  "geometry": {"coordinates":[4.75365,51.615002],"type":"Point"}
}