{
  "type": "Feature",
  "properties": {
    "addr:full":"Drooghe Bol 1008 Den Helder Noord-Holland 1788 VA",
    "addr:housenumber":"1008",
    "addr:postcode":"1788",
    "addr:street":"Drooghe Bol",
    "iso:country":"NL",
    "sg:address":"Drooghe Bol 1008",
    "sg:city":"Den Helder",
    "sg:orig_category":"Zuivelproducten",
    "sg:phone":"+31 223 647 015",
    "sg:postcode":"1788 VA",
    "sg:province":"Noord-Holland",
    "wof:name":"Vomar Kaasboer/Poelier",
    "wof:placetype":"venue"
},
  "geometry": {"coordinates":[4.74153,52.884998],"type":"Point"}
}