{
  "type": "Feature",
  "properties": {
    "addr:full":"Zeeburgerdk 537 Amsterdam Noord-Holland 1095 AE",
    "addr:housenumber":"537",
    "addr:postcode":"1095 ae",
    "iso:country":"NL",
    "sg:address":"Zeeburgerdk 537",
    "sg:city":"Amsterdam",
    "sg:orig_category":"Fotojournalisten Freelance",
    "sg:phone":"+31 20 694 7463",
    "sg:postcode":"1095 AE",
    "sg:province":"Noord-Holland",
    "wof:name":"Bennekom, Joris Van",
    "wof:placetype":"venue"
},
  "geometry": {"coordinates":[4.969215,52.361691],"type":"Point"}
}