{
  "type": "Feature",
  "properties": {
    "iso:country":"NL",
    "sg:address":"Verryn Stuartlaan 17",
    "sg:city":"Rijswijk Zh",
    "sg:orig_category":"Zuivelproducten And Spijsoli?n Gh",
    "sg:phone":"+31 70 390 8307",
    "sg:postcode":"2288 EK",
    "sg:province":"Zuid-Holland",
    "wof:name":"Amtrol Ned",
    "wof:placetype":"venue"
},
  "geometry": {"coordinates":[4.334237,52.040272],"type":"Point"}
}