{
  "type": "Feature",
  "properties": {
    "addr:full":"Tremolietdk 13 Roosendaal North Brabant 4706 TW",
    "addr:housenumber":"13",
    "addr:postcode":"4706 tw",
    "addr:street":"Tremolietdk",
    "iso:country":"NL",
    "sg:address":"Tremolietdk 13",
    "sg:city":"Roosendaal",
    "sg:orig_category":"Maquettes",
    "sg:phone":"+31 165 570 842",
    "sg:postcode":"4706 TW",
    "sg:province":"North Brabant",
    "sg:website":"http://www.scaleart.nl",
    "wof:name":"Scale Art Bv",
    "wof:placetype":"venue"
},
  "geometry": {"coordinates":[4.498742,51.519287],"type":"Point"}
}