{
  "type": "Feature",
  "properties": {
    "addr:full":"Bremhorst 4 Teteringen Noord-Brabant 4847 CK",
    "addr:housenumber":"4",
    "addr:postcode":"4847 ck",
    "addr:street":"Bremhorst",
    "iso:country":"NL",
    "sg:address":"Bremhorst 4",
    "sg:city":"Teteringen",
    "sg:orig_category":"Marktonderzoekbureaus",
    "sg:phone":"+31 76 571 3883",
    "sg:postcode":"4847 CK",
    "sg:province":"Noord-Brabant",
    "wof:name":"Hollander Textielmarketing & Premiums",
    "wof:placetype":"venue"
},
  "geometry": {"coordinates":[4.819591,51.603901],"type":"Point"}
}