{
  "type": "Feature",
  "properties": {
    "iso:country":"NL",
    "sg:address":"Bremhorst 4",
    "sg:city":"Teteringen",
    "sg:orig_category":"Marktonderzoekbureaus",
    "sg:phone":"+31 76 571 3883",
    "sg:postcode":"4847 CK",
    "sg:province":"Noord-Brabant",
    "wof:name":"Hollander Textielmarketing & Premiums",
    "wof:placetype":"venue"
},
  "geometry": {"coordinates":[4.819591,51.603901],"type":"Point"}
}