{
  "type": "Feature",
  "properties": {
    "iso:country":"NL",
    "sg:address":"Westeinde 74",
    "sg:city":"Berkenwoude",
    "sg:orig_category":"Adviesbureaus Bedrijfsorganisatie",
    "sg:phone":"+31 182 362 697",
    "sg:postcode":"2825 AL",
    "sg:province":"Zuid-Holland",
    "wof:name":"Munnik",
    "wof:placetype":"venue"
},
  "geometry": {"coordinates":[4.6906,51.936989],"type":"Point"}
}