{
  "type": "Feature",
  "properties": {
    "addr:full":"Paltrokmolen 17 Purmerend North Holland 1444 GM",
    "addr:housenumber":"17",
    "addr:postcode":"1444 gm",
    "addr:street":"Paltrokmolen",
    "iso:country":"NL",
    "sg:address":"Paltrokmolen 17",
    "sg:city":"Purmerend",
    "sg:orig_category":"Administratie- En Boekhoudkantoren",
    "sg:phone":"+31 299 425 009",
    "sg:postcode":"1444 GM",
    "sg:province":"North Holland",
    "wof:name":"Admikro",
    "wof:placetype":"venue"
},
  "geometry": {"coordinates":[4.970701,52.519691],"type":"Point"}
}