{
  "type": "Feature",
  "properties": {
    "addr:full":"Lomanstr 94 Amsterdam Noord-Holland 1075 RH",
    "addr:housenumber":"94",
    "addr:postcode":"1075 rh",
    "addr:street":"Lomanstr",
    "iso:country":"NL",
    "sg:address":"Lomanstr 94",
    "sg:city":"Amsterdam",
    "sg:orig_category":"Adviesbureaus Bedrijfsorganisatie",
    "sg:phone":"+31 6 25030253",
    "sg:postcode":"1075 RH",
    "sg:province":"Noord-Holland",
    "wof:name":"Procipio",
    "wof:placetype":"venue"
},
  "geometry": {"coordinates":[4.858034,52.350941],"type":"Point"}
}