{
  "type": "Feature",
  "properties": {
    "addr:full":"Achtsewg N 5 Eindhoven Noord-Brabant 5651 GG",
    "addr:housenumber":"5",
    "addr:postcode":"5651 gg",
    "addr:street":"N",
    "iso:country":"NL",
    "sg:address":"Achtsewg N 5",
    "sg:city":"Eindhoven",
    "sg:orig_category":"Medische Installaties En Instrumenten",
    "sg:phone":"+31 40 276 6849",
    "sg:postcode":"5651 GG",
    "sg:province":"Noord-Brabant",
    "wof:name":"Panalytical Eindhoven Bv",
    "wof:placetype":"venue"
},
  "geometry": {"coordinates":[5.42676,51.463428],"type":"Point"}
}