{
  "type": "Feature",
  "properties": {
    "addr:full":"Hoofdstr 17 Kesteren Gelderland 4041 AA",
    "addr:housenumber":"17",
    "addr:postcode":"4041 aa",
    "addr:street":"Hoofdstr;Gelderland",
    "iso:country":"NL",
    "sg:address":"Hoofdstr 17",
    "sg:city":"Kesteren",
    "sg:orig_category":"Bloemen En Planten",
    "sg:phone":"+31 488 482 749",
    "sg:postcode":"4041 AA",
    "sg:province":"Gelderland",
    "wof:name":"Berkje, Het",
    "wof:placetype":"venue"
},
  "geometry": {"coordinates":[5.574345,51.933842],"type":"Point"}
}