{
  "type": "Feature",
  "properties": {
    "addr:full":"Boulevard Paulus Loot 29 Zandvoort Noord-Holland 2042 AD",
    "addr:housenumber":"29",
    "addr:postcode":"2042 ad",
    "addr:street":"Boulevard Paulus Loot",
    "iso:country":"NL",
    "sg:address":"Boulevard Paulus Loot 29",
    "sg:city":"Zandvoort",
    "sg:classifiers":[
        {
            "category":"Fast Food",
            "type":"Food & Drink"
        }
    ],
    "sg:phone":"+31 23 571 3031",
    "sg:postcode":"2042 AD",
    "sg:province":"Noord-Holland",
    "sg:tags":[
        "afhaal",
        "restaurant"
    ],
    "wof:name":"Strandpaviljoen Amirika",
    "wof:placetype":"venue"
},
  "geometry": {"coordinates":[4.522811,52.369137],"type":"Point"}
}