{
  "type": "Feature",
  "properties": {
    "iso:country":"NL",
    "sg:address":"Hessenwg 181",
    "sg:city":"De Bilt",
    "sg:orig_category":"Kappers",
    "sg:phone":"+31 30 221 1489",
    "sg:postcode":"3731 JH",
    "sg:province":"Utrecht",
    "wof:name":"Dilia Herenkapsalon",
    "wof:placetype":"venue"
},
  "geometry": {"coordinates":[5.1823449135,52.1118545532],"type":"Point"}
}