{
  "type": "Feature",
  "properties": {
    "addr:full":"Poseidon 15 Hellevoetsluis South Holland 3225 TH",
    "addr:housenumber":"15",
    "addr:postcode":"3225 th",
    "addr:street":"Poseidon",
    "iso:country":"NL",
    "sg:address":"Poseidon 15",
    "sg:city":"Hellevoetsluis",
    "sg:orig_category":"Begrafenisondernemers",
    "sg:phone":"+31 181 319 694",
    "sg:postcode":"3225 TH",
    "sg:province":"South Holland",
    "wof:name":"Alg Begrafenis & Crematie Ond Silentium",
    "wof:placetype":"venue"
},
  "geometry": {"coordinates":[4.155756,51.835918],"type":"Point"}
}