{
  "type": "Feature",
  "properties": {
    "addr:full":"Fluitekruid 62 Den Hoorn Zh Zuid-Holland 2635 KT",
    "addr:housenumber":"62",
    "addr:postcode":"2635 kt",
    "addr:street":"Fluitekruid",
    "iso:country":"NL",
    "sg:address":"Fluitekruid 62",
    "sg:city":"Den Hoorn Zh",
    "sg:orig_category":"Bibliotheken And Openbare Archieven",
    "sg:phone":"+31 15 261 1838",
    "sg:postcode":"2635 KT",
    "sg:province":"Zuid-Holland",
    "wof:name":"Bibliotheek Den Hoorn",
    "wof:placetype":"venue"
},
  "geometry": {"coordinates":[4.332473,52.004189],"type":"Point"}
}