{
  "type": "Feature",
  "properties": {
    "addr:full":"Berkelstraat 43 Groningen Groningen 9725 GV",
    "addr:housenumber":"43",
    "addr:postcode":"9725 gv",
    "addr:street":"Berkelstraat",
    "iso:country":"NL",
    "sg:address":"Berkelstraat 43",
    "sg:city":"Groningen",
    "sg:orig_category":"Loodgieterswerk, Verwarming And Sanitaire Installaties",
    "sg:phone":"+31 50 526 3784",
    "sg:postcode":"9725 GV",
    "sg:province":"Groningen",
    "wof:name":"Klussenburo Heuckeroth",
    "wof:placetype":"venue"
},
  "geometry": {"coordinates":[6.565722,53.206741],"type":"Point"}
}