{
  "type": "Feature",
  "properties": {
    "addr:full":"Schoolstraat 6A Echt Limburg 6102 AE",
    "addr:housenumber":"6a",
    "addr:postcode":"6102 ae",
    "addr:street":"Schoolstraat",
    "iso:country":"NL",
    "sg:address":"Schoolstraat 6A",
    "sg:city":"Echt",
    "sg:orig_category":"Hoger Onderwijs",
    "sg:phone":"+31 475 482 451",
    "sg:postcode":"6102 AE",
    "sg:province":"Limburg",
    "wof:name":"A. Meijers-Jans",
    "wof:placetype":"venue"
},
  "geometry": {"coordinates":[55.115898,24.287849],"type":"Point"}
}