{
  "type": "Feature",
  "properties": {
    "addr:full":"Postbus 39 Gulpen Limburg 6270 AA",
    "addr:housenumber":"39",
    "addr:postcode":"6270 aa",
    "addr:street":"Postbus",
    "iso:country":"NL",
    "sg:address":"Postbus 39",
    "sg:city":"Gulpen",
    "sg:orig_category":"Scholen Voor Basisonderwijs",
    "sg:phone":"+31 43 450 6150",
    "sg:postcode":"6270 AA",
    "sg:province":"Limburg",
    "wof:name":"Triangel Rk, De",
    "wof:placetype":"venue"
},
  "geometry": {"coordinates":[5.88998,50.817322],"type":"Point"}
}