{
  "type": "Feature",
  "properties": {
    "addr:full":"Heezenpoort 15A Doetinchem Gelderland 7001 BK",
    "addr:housenumber":"15a",
    "addr:postcode":"7001 bk",
    "addr:street":"Heezenpoort;Gelderland",
    "iso:country":"NL",
    "sg:address":"Heezenpoort 15A",
    "sg:city":"Doetinchem",
    "sg:orig_category":"Hypotheken",
    "sg:phone":"+31 314 363 114",
    "sg:postcode":"7001 BK",
    "sg:province":"Gelderland",
    "wof:name":"Huis & Leven",
    "wof:placetype":"venue"
},
  "geometry": {"coordinates":[6.28918,51.965668],"type":"Point"}
}