{
  "type": "Feature",
  "properties": {
    "addr:full":"Ceintuurbaan 296 Amsterdam Noord-Holland 1072 GK",
    "addr:housenumber":"296",
    "addr:postcode":"1072 gk",
    "addr:street":"Ceintuurbaan",
    "iso:country":"NL",
    "sg:address":"Ceintuurbaan 296",
    "sg:city":"Amsterdam",
    "sg:orig_category":"Zonweringen",
    "sg:phone":"+31 20 676 0205",
    "sg:postcode":"1072 GK",
    "sg:province":"Noord-Holland",
    "wof:name":"Binnekade, Ton",
    "wof:placetype":"venue"
},
  "geometry": {"coordinates":[4.892177,52.352791],"type":"Point"}
}