{
  "type": "Feature",
  "properties": {
    "iso:country":"NL",
    "sg:address":"Noordijkstraat 62",
    "sg:city":"Brouwershaven",
    "sg:classifiers":[
        {
            "category":"Travel",
            "subcategory":"Hotels & Motels",
            "type":"Entertainment"
        }
    ],
    "sg:phone":"+31 35 603 0401",
    "sg:postcode":"4318 BK",
    "sg:province":"Zeeland",
    "wof:name":"Ans'Bungalow Bos-En-Veld",
    "wof:placetype":"venue"
},
  "geometry": {"coordinates":[3.907166,51.727097],"type":"Point"}
}