{
  "type": "Feature",
  "properties": {
    "iso:country":"NL",
    "sg:address":"Pr Hendrikstr 187",
    "sg:city":"Hoek Van Holland",
    "sg:orig_category":"Onroerende Goederen",
    "sg:phone":"+31 174 286 991",
    "sg:postcode":"3151 AG",
    "sg:province":"Zuid-Holland",
    "sg:website":"http://www.leegstandsbeheer.nl",
    "wof:name":"Interim Leegstandsbeheer Bv",
    "wof:placetype":"venue"
},
  "geometry": {"coordinates":[4.133046,51.976128],"type":"Point"}
}