{
  "type": "Feature",
  "properties": {
    "addr:full":"Bleekerweg 4 Heusden Gem Asten Noord-Brabant 5725 BE",
    "addr:housenumber":"4",
    "addr:postcode":"5725",
    "addr:street":"Bleekerweg",
    "iso:country":"NL",
    "sg:address":"Bleekerweg 4",
    "sg:city":"Heusden Gem Asten",
    "sg:orig_category":"Pluimveehouderijen",
    "sg:phone":"+31 493 560 212",
    "sg:postcode":"5725 BE",
    "sg:province":"Noord-Brabant",
    "wof:name":"P. Driessen",
    "wof:placetype":"venue"
},
  "geometry": {"coordinates":[5.774043,51.37912],"type":"Point"}
}