{
  "type": "Feature",
  "properties": {
    "addr:full":"De Strengen 14 Malden Gelderland 6581 JZ",
    "addr:housenumber":"14",
    "addr:postcode":"6581 jz",
    "addr:street":"De Strengen;Gelderland",
    "iso:country":"NL",
    "sg:address":"De Strengen 14",
    "sg:city":"Malden",
    "sg:orig_category":"Adviesbureaus Bedrijfsorganisatie",
    "sg:phone":"+31 24 397 0200",
    "sg:postcode":"6581 JZ",
    "sg:province":"Gelderland",
    "wof:name":"Oov Partners",
    "wof:placetype":"venue"
},
  "geometry": {"coordinates":[5.856643,51.772457],"type":"Point"}
}