{
  "type": "Feature",
  "properties": {
    "addr:full":"Wassenaarstraat 76 Bergen Op Zoom Noord-Brabant 4611 BW",
    "addr:housenumber":"76",
    "addr:postcode":"4611 bw",
    "addr:street":"Wassenaarstraat",
    "iso:country":"NL",
    "sg:address":"Wassenaarstraat 76",
    "sg:city":"Bergen Op Zoom",
    "sg:orig_category":"Paramedische Behandelingen",
    "sg:phone":"+31 164 253 479",
    "sg:postcode":"4611 BW",
    "sg:province":"Noord-Brabant",
    "wof:name":"De Kleine Winst",
    "wof:placetype":"venue"
},
  "geometry": {"coordinates":[4.291452,51.493141],"type":"Point"}
}