{
  "type": "Feature",
  "properties": {
    "iso:country":"NL",
    "sg:address":"Rolklaver 3",
    "sg:city":"Nootdorp",
    "sg:orig_category":"Waterbehandeling En Waterzuiverings- Systemen",
    "sg:phone":"+31 15 361 8506",
    "sg:postcode":"2631 SN",
    "sg:province":"Zuid-Holland",
    "sg:website":"http://www.ocean-waterbehandeling.nl",
    "wof:name":"Ocean",
    "wof:placetype":"venue"
},
  "geometry": {"coordinates":[4.4005022049,52.0426101685],"type":"Point"}
}