{
  "type": "Feature",
  "properties": {
    "addr:full":"Goedendorplaan 3 Rijswijk Zh Zuid-Holland 2286 MV",
    "addr:housenumber":"3",
    "addr:postcode":"zh;2286 mv",
    "addr:street":"Goedendorplaan",
    "iso:country":"NL",
    "sg:address":"Goedendorplaan 3",
    "sg:city":"Rijswijk Zh",
    "sg:classifiers":[
        {
            "category":"Education",
            "subcategory":"Preschool",
            "type":"Public Place"
        }
    ],
    "sg:phone":"+31 70 393 3993",
    "sg:postcode":"2286 MV",
    "sg:province":"Zuid-Holland",
    "sg:tags":[
        "kleuteronderwijs",
        "basis-"
    ],
    "wof:name":"Peuterspeelzaal Nijntje",
    "wof:placetype":"venue"
},
  "geometry": {"coordinates":[4.316823,52.024616],"type":"Point"}
}