{
  "type": "Feature",
  "properties": {
    "iso:country":"NL",
    "sg:address":"Herbert H Dowweg .",
    "sg:city":"Hoek",
    "sg:classifiers":[
        {
            "category":"Retail",
            "subcategory":"Storage",
            "type":"Services"
        }
    ],
    "sg:phone":"+31 115 621 135",
    "sg:postcode":"4542 NN",
    "sg:province":"Zeeland",
    "sg:tags":[
        "op-",
        "en",
        "overslagbedrijven"
    ],
    "wof:name":"Zeeland Terminal",
    "wof:placetype":"venue"
},
  "geometry": {"coordinates":[3.775919,51.331623],"type":"Point"}
}