{
  "type": "Feature",
  "properties": {
    "addr:full":"Heschepad 49 Oss Noord-Brabant 5341 GS",
    "addr:housenumber":"49",
    "addr:postcode":"5341 gs",
    "addr:street":"Heschepad",
    "iso:country":"NL",
    "sg:address":"Heschepad 49",
    "sg:city":"Oss",
    "sg:orig_category":"Kaas",
    "sg:phone":"+31 412 628 242",
    "sg:postcode":"5341 GS",
    "sg:province":"Noord-Brabant",
    "wof:name":"Groenwoudt",
    "wof:placetype":"venue"
},
  "geometry": {"coordinates":[-77.2352142334,38.3125991821],"type":"Point"}
}