{
  "type": "Feature",
  "properties": {
    "addr:full":"Panamakd 44 Amsterdam Noord-Holland 1019 AX",
    "addr:housenumber":"44",
    "addr:postcode":"1019 ax",
    "addr:street":"Panamakd",
    "iso:country":"NL",
    "sg:address":"Panamakd 44",
    "sg:city":"Amsterdam",
    "sg:orig_category":"Psychotherapeuten",
    "sg:phone":"+31 20 419 7567",
    "sg:postcode":"1019 AX",
    "sg:province":"Noord-Holland",
    "wof:name":"Stades, Drs Pien",
    "wof:placetype":"venue"
},
  "geometry": {"coordinates":[4.893195,52.373119],"type":"Point"}
}