{
  "type": "Feature",
  "properties": {
    "addr:full":"Den Sliem 85A Groenlo Gelderland 7141 JG",
    "addr:housenumber":"85a",
    "addr:postcode":"7141 jg",
    "addr:street":"Den Sliem;Gelderland",
    "iso:country":"NL",
    "sg:address":"Den Sliem 85A",
    "sg:city":"Groenlo",
    "sg:orig_category":"Kunststof Ramen",
    "sg:phone":"+31 544 372 534",
    "sg:postcode":"7141 JG",
    "sg:province":"Gelderland",
    "sg:website":"http://www.proge.nl",
    "wof:name":"Proge",
    "wof:placetype":"venue"
},
  "geometry": {"coordinates":[6.623,52.053532],"type":"Point"}
}