{
  "type": "Feature",
  "properties": {
    "addr:full":"De Dam 6 Leek Groningen 9351 AM",
    "addr:housenumber":"6",
    "addr:postcode":"9351",
    "addr:street":"De Dam",
    "iso:country":"NL",
    "sg:address":"De Dam 6",
    "sg:city":"Leek",
    "sg:classifiers":[
        {
            "category":"Food & Beverages",
            "subcategory":"Fruits & Vegetables",
            "type":"Retail Goods"
        }
    ],
    "sg:phone":"+31 594 513 183",
    "sg:postcode":"9351 AM",
    "sg:province":"Groningen",
    "sg:tags":[
        "groenten"
    ],
    "wof:name":"Lubbers Groente- En Fruithal",
    "wof:placetype":"venue"
},
  "geometry": {"coordinates":[6.392343,53.162128],"type":"Point"}
}