{
  "type": "Feature",
  "properties": {
    "addr:full":"Houtrib 23 Monnickendam Noord-Holland 1141 DB",
    "addr:housenumber":"23",
    "addr:postcode":"1141 db",
    "addr:street":"Houtrib",
    "iso:country":"NL",
    "sg:address":"Houtrib 23",
    "sg:city":"Monnickendam",
    "sg:orig_category":"Maquettes",
    "sg:phone":"+31 299 653 565",
    "sg:postcode":"1141 DB",
    "sg:province":"Noord-Holland",
    "wof:name":"Rienderhoff",
    "wof:placetype":"venue"
},
  "geometry": {"coordinates":[5.042368,52.449669],"type":"Point"}
}