{
  "type": "Feature",
  "properties": {
    "addr:full":"Noordzandstr 34 Yerseke Zeeland 4401 CG",
    "addr:housenumber":"34",
    "addr:postcode":"4401 cg",
    "addr:street":"Noordzandstr",
    "iso:country":"NL",
    "sg:address":"Noordzandstr 34",
    "sg:city":"Yerseke",
    "sg:orig_category":"Postkantoren",
    "sg:phone":"+31 113 571 322",
    "sg:postcode":"4401 CG",
    "sg:province":"Zeeland",
    "sg:website":"http://www.postkantoor.nl",
    "wof:name":"Postkantoor",
    "wof:placetype":"venue"
},
  "geometry": {"coordinates":[4.0503,51.494366],"type":"Point"}
}