{
  "type": "Feature",
  "properties": {
    "iso:country":"NL",
    "sg:address":"Verspyckln 1",
    "sg:city":"Naaldwyk",
    "sg:orig_category":"Verenigingen En Stichtingen",
    "sg:phone":"+31 174 629 992",
    "sg:postcode":"2671 CR",
    "sg:province":"Zuid-Holland",
    "wof:name":"Buitenlandse Landgenoten Stichting",
    "wof:placetype":"venue"
},
  "geometry": {"coordinates":[4.209316,51.997429],"type":"Point"}
}