{
  "type": "Feature",
  "properties": {
    "addr:full":"Kattedoorn 21 Tiel Gelderland 4007 SM",
    "addr:housenumber":"21",
    "addr:postcode":"4007 sm",
    "addr:street":"Kattedoorn;Gelderland",
    "iso:country":"NL",
    "sg:address":"Kattedoorn 21",
    "sg:city":"Tiel",
    "sg:orig_category":"Plafonds",
    "sg:phone":"+31 6 51795531",
    "sg:postcode":"4007 SM",
    "sg:province":"Gelderland",
    "wof:name":"Bza",
    "wof:placetype":"venue"
},
  "geometry": {"coordinates":[5.392297,51.869114],"type":"Point"}
}