{
  "type": "Feature",
  "properties": {
    "addr:full":"Grevelingen 5 Tilburg Noord-Brabant 5032 TC",
    "addr:housenumber":"5",
    "addr:postcode":"5032 tc",
    "addr:street":"Grevelingen",
    "iso:country":"NL",
    "sg:address":"Grevelingen 5",
    "sg:city":"Tilburg",
    "sg:orig_category":"Adviesbureaus Bouwkosten",
    "sg:phone":"+31 13 590 1773",
    "sg:postcode":"5032 TC",
    "sg:province":"Noord-Brabant",
    "wof:name":"Dbm",
    "wof:placetype":"venue"
},
  "geometry": {"coordinates":[5.044281,51.551273],"type":"Point"}
}