{
  "type": "Feature",
  "properties": {
    "addr:full":"Boveneind 28 Leek Groningen 9351 AR",
    "addr:housenumber":"28",
    "addr:postcode":"9351",
    "addr:street":"Boveneind",
    "iso:country":"NL",
    "sg:address":"Boveneind 28",
    "sg:city":"Leek",
    "sg:orig_category":"Hengelsportartikelen",
    "sg:phone":"+31 594 514 166",
    "sg:postcode":"9351 AR",
    "sg:province":"Groningen",
    "wof:name":"Kuperus Hengelsportartikelen",
    "wof:placetype":"venue"
},
  "geometry": {"coordinates":[6.388671,53.160652],"type":"Point"}
}