{
  "type": "Feature",
  "properties": {
    "addr:full":"W Kloosstr 7 Etten Leur Noord-Brabant 4873 EE",
    "addr:housenumber":"7",
    "addr:postcode":"4873 ee",
    "addr:street":"W",
    "iso:country":"NL",
    "sg:address":"W Kloosstr 7",
    "sg:city":"Etten Leur",
    "sg:orig_category":"Administratie- En Boekhoudkantoren",
    "sg:phone":"+31 76 503 4132",
    "sg:postcode":"4873 EE",
    "sg:province":"Noord-Brabant",
    "wof:name":"Hoon, M De",
    "wof:placetype":"venue"
},
  "geometry": {"coordinates":[4.644719,51.5676],"type":"Point"}
}