{
  "type": "Feature",
  "properties": {
    "addr:full":"Nobelweg 10 Amsterdam Noord-Holland 1097 AR",
    "addr:housenumber":"10",
    "addr:postcode":"1097",
    "addr:street":"Nobelweg",
    "iso:country":"NL",
    "sg:address":"Nobelweg 10",
    "sg:city":"Amsterdam",
    "sg:orig_category":"Bloemen And Planten",
    "sg:phone":"+31 20 462 2922",
    "sg:postcode":"1097 AR",
    "sg:province":"Noord-Holland",
    "wof:name":"Intratuin",
    "wof:placetype":"venue"
},
  "geometry": {"coordinates":[-58.372601,-34.587639],"type":"Point"}
}