{
  "type": "Feature",
  "properties": {
    "addr:full":"Brederodestraat 16 Assendelft Noord-Holland 1566 TK",
    "addr:housenumber":"16",
    "addr:postcode":"1566 tk",
    "addr:street":"Brederodestraat",
    "iso:country":"NL",
    "sg:address":"Brederodestraat 16",
    "sg:city":"Assendelft",
    "sg:orig_category":"Boekhouders",
    "sg:phone":"+31 75 687 1737",
    "sg:postcode":"1566 TK",
    "sg:province":"Noord-Holland",
    "wof:name":"C.P.W. Van Den Berg Administratie Bv",
    "wof:placetype":"venue"
},
  "geometry": {"coordinates":[4.742221,52.464504],"type":"Point"}
}