{
  "type": "Feature",
  "properties": {
    "addr:full":"Troelstraln 37 Groningen Groningen 9722 JC",
    "addr:housenumber":"37",
    "addr:postcode":"9722 jc",
    "addr:street":"Troelstraln",
    "iso:country":"NL",
    "sg:address":"Troelstraln 37",
    "sg:city":"Groningen",
    "sg:orig_category":"Loodgieters",
    "sg:phone":"+31 50 526 2408",
    "sg:postcode":"9722 JC",
    "sg:province":"Groningen",
    "wof:name":"Sienot",
    "wof:placetype":"venue"
},
  "geometry": {"coordinates":[6.58561,53.196854],"type":"Point"}
}