{
  "type": "Feature",
  "properties": {
    "addr:full":"Torkruidstraat 11 Lisserbroek Noord-Holland 2165 XL",
    "addr:housenumber":"11",
    "addr:postcode":"2165 xl",
    "addr:street":"Torkruidstraat",
    "iso:country":"NL",
    "sg:address":"Torkruidstraat 11",
    "sg:city":"Lisserbroek",
    "sg:orig_category":"Bloemen And Planten Gh",
    "sg:phone":"+31 252 414 506",
    "sg:postcode":"2165 XL",
    "sg:province":"Noord-Holland",
    "wof:name":"Fa Imthorn-Botanica",
    "wof:placetype":"venue"
},
  "geometry": {"coordinates":[4.574872,52.259212],"type":"Point"}
}