{
  "type": "Feature",
  "properties": {
    "addr:full":"Marconistr 4 Zwolle Overijssel 8013 PK",
    "addr:housenumber":"4",
    "addr:postcode":"8013 pk",
    "addr:street":"Marconistr",
    "iso:country":"NL",
    "sg:address":"Marconistr 4",
    "sg:city":"Zwolle",
    "sg:classifiers":[
        {
            "category":"Retail",
            "subcategory":"Auto Repair",
            "type":"Services"
        }
    ],
    "sg:phone":"+31 38 465 5565",
    "sg:postcode":"8013 PK",
    "sg:province":"Overijssel",
    "sg:tags":[
        "garage"
    ],
    "wof:name":"Brakke Bv, J",
    "wof:placetype":"venue"
},
  "geometry": {"coordinates":[6.124783,52.497772],"type":"Point"}
}