{
  "type": "Feature",
  "properties": {
    "addr:full":"Kennedystraat 18 A Boekel Noord-Brabant 5427 CJ",
    "addr:housenumber":"18 a",
    "addr:postcode":"5427 cj",
    "addr:street":"Kennedystraat",
    "iso:country":"NL",
    "sg:address":"Kennedystraat 18 A",
    "sg:city":"Boekel",
    "sg:classifiers":[
        {
            "category":"Communications",
            "subcategory":"Television Station",
            "type":"Services"
        }
    ],
    "sg:phone":"+31 492 322 229",
    "sg:postcode":"5427 CJ",
    "sg:province":"Noord-Brabant",
    "sg:tags":[
        "video",
        "audio",
        "verhuur"
    ],
    "wof:name":"Videohouse",
    "wof:placetype":"venue"
},
  "geometry": {"coordinates":[5.668544,51.602745],"type":"Point"}
}