{
  "type": "Feature",
  "properties": {
    "addr:full":"Tempeliersstr 71-1 Haarlem North Holland 2012 EC",
    "addr:housenumber":"71-1",
    "addr:postcode":"2012 ec",
    "iso:country":"NL",
    "sg:address":"Tempeliersstr 71-1",
    "sg:city":"Haarlem",
    "sg:orig_category":"Verenigingen En Stichtingen",
    "sg:phone":"+31 23 531 4606",
    "sg:postcode":"2012 EC",
    "sg:province":"North Holland",
    "wof:name":"Klank-Beeld",
    "wof:placetype":"venue"
},
  "geometry": {"coordinates":[4.630351,52.375397],"type":"Point"}
}