{
  "type": "Feature",
  "properties": {
    "addr:full":"Aarlesewg 30 Best Texas 5684 LN",
    "addr:housenumber":"30",
    "addr:postcode":"5684 ln",
    "addr:street":"Aarlesewg",
    "iso:country":"NL",
    "sg:address":"Aarlesewg 30",
    "sg:city":"Best",
    "sg:orig_category":"Onderhoudswerken",
    "sg:phone":"+31 499 371 604",
    "sg:postcode":"5684 LN",
    "sg:province":"Texas",
    "wof:name":"Kaathoven, Van",
    "wof:placetype":"venue"
},
  "geometry": {"coordinates":[-101.618134,31.224251],"type":"Point"}
}