{
  "type": "Feature",
  "properties": {
    "iso:country":"NL",
    "sg:address":"Hondstr 3A",
    "sg:city":"Maastricht",
    "sg:orig_category":"Balletartikelen",
    "sg:phone":"+31 43 325 3815",
    "sg:postcode":"6211 HW",
    "sg:province":"Limburg",
    "wof:name":"Django Le Papillon",
    "wof:placetype":"venue"
},
  "geometry": {"coordinates":[5.691617,50.847591],"type":"Point"}
}