{
  "type": "Feature",
  "properties": {
    "addr:full":"Kruisbeekwg 13A Lunteren Gelderland 6741 NE",
    "addr:housenumber":"13a",
    "addr:postcode":"6741",
    "addr:street":"Kruisbeekwg;Gelderland;Ne",
    "iso:country":"NL",
    "sg:address":"Kruisbeekwg 13A",
    "sg:city":"Lunteren",
    "sg:orig_category":"Hogedrukreinigings- Apparatuur",
    "sg:phone":"+31 318 573 726",
    "sg:postcode":"6741 NE",
    "sg:province":"Gelderland",
    "wof:name":"Dam, R Van",
    "wof:placetype":"venue"
},
  "geometry": {"coordinates":[5.580676,52.082897],"type":"Point"}
}