{
  "type": "Feature",
  "properties": {
    "iso:country":"NL",
    "sg:address":"Schuilenburgerweg 4",
    "sg:city":"Hellendoorn",
    "sg:orig_category":"Kinderopvang Behalve Thuis",
    "sg:phone":"+31 548 632 340",
    "sg:postcode":"7447 RP",
    "sg:province":"Overijssel",
    "wof:name":"Kinderopvang De Knuist",
    "wof:placetype":"venue"
},
  "geometry": {"coordinates":[6.45474,52.393738],"type":"Point"}
}