{
  "type": "Feature",
  "properties": {
    "addr:full":"L Hillewg 189B Rotterdam South Holland 3073 BN",
    "addr:housenumber":"189b",
    "addr:postcode":"3073 bn",
    "iso:country":"NL",
    "sg:address":"L Hillewg 189B",
    "sg:city":"Rotterdam",
    "sg:orig_category":"Artsen - Huisartsen",
    "sg:phone":"+31 10 485 9545",
    "sg:postcode":"3073 BN",
    "sg:province":"South Holland",
    "wof:name":"Schipper, W J De",
    "wof:placetype":"venue"
},
  "geometry": {"coordinates":[4.497261,51.890911],"type":"Point"}
}