{
  "type": "Feature",
  "properties": {
    "iso:country":"NL",
    "sg:address":"Laat 58",
    "sg:city":"Alkmaar",
    "sg:orig_category":"Hypotheken And Hypotheekbanken",
    "sg:phone":"+31 72 515 3020",
    "sg:postcode":"1811 EK",
    "sg:province":"Noord-Holland",
    "wof:name":"Hypotheek Visie Alkmaar",
    "wof:placetype":"venue"
},
  "geometry": {"coordinates":[4.751169,52.629047],"type":"Point"}
}