{
  "type": "Feature",
  "properties": {
    "iso:country":"NL",
    "sg:address":"Goudsesingel 244-252",
    "sg:city":"Rotterdam",
    "sg:orig_category":"Meubelzaken, Woning- And Keukeninrichting",
    "sg:phone":"+31 10 414 3773",
    "sg:postcode":"3011 KE",
    "sg:province":"South Holland",
    "wof:name":"Slaapbankencentrum",
    "wof:placetype":"venue"
},
  "geometry": {"coordinates":[4.49175,51.924091],"type":"Point"}
}