{
  "type": "Feature",
  "properties": {
    "addr:full":"Oostzyde 242 Zaandam North Holland 1508 ES",
    "addr:housenumber":"242",
    "addr:postcode":"1508 es",
    "addr:street":"Oostzyde",
    "iso:country":"NL",
    "sg:address":"Oostzyde 242",
    "sg:city":"Zaandam",
    "sg:orig_category":"Psychologen",
    "sg:phone":"+31 75 614 6418",
    "sg:postcode":"1508 ES",
    "sg:province":"North Holland",
    "wof:name":"Focus 4 Soul Bv",
    "wof:placetype":"venue"
},
  "geometry": {"coordinates":[4.81295,52.44162],"type":"Point"}
}