{
  "type": "Feature",
  "properties": {
    "addr:full":"Solwerderwg 9 Appingedam Groningen 9901 BR",
    "addr:housenumber":"9",
    "addr:postcode":"9901 br",
    "addr:street":"Solwerderwg",
    "iso:country":"NL",
    "sg:address":"Solwerderwg 9",
    "sg:city":"Appingedam",
    "sg:orig_category":"Ziekenhuizen, Sanatoria, Verpleeghuizen",
    "sg:phone":"+31 596 686 600",
    "sg:postcode":"9901 BR",
    "sg:province":"Groningen",
    "wof:name":"Fivelland",
    "wof:placetype":"venue"
},
  "geometry": {"coordinates":[6.870579,53.323025],"type":"Point"}
}