{
  "type": "Feature",
  "properties": {
    "addr:full":"Steenbergseweg 46 Dinteloord North Brabant 4671 BH",
    "addr:housenumber":"46",
    "addr:postcode":"4671 bh",
    "addr:street":"Steenbergseweg",
    "iso:country":"NL",
    "sg:address":"Steenbergseweg 46",
    "sg:city":"Dinteloord",
    "sg:orig_category":"Autokeuringen",
    "sg:phone":"+31 167 522 793",
    "sg:postcode":"4671 BH",
    "sg:province":"North Brabant",
    "wof:name":"Shell",
    "wof:placetype":"venue"
},
  "geometry": {"coordinates":[4.36615,51.633251],"type":"Point"}
}