{
  "type": "Feature",
  "properties": {
    "iso:country":"NL",
    "sg:address":"Sportlaan 72",
    "sg:city":"'S Hertogenbosch",
    "sg:orig_category":"Kantoorapparatuur Gh",
    "sg:phone":"+31 73 621 7575",
    "sg:postcode":"5223 AZ",
    "sg:province":"Noord-Brabant",
    "wof:name":"Dsp Berends Kantoorsystemen",
    "wof:placetype":"venue"
},
  "geometry": {"coordinates":[5.2856531143,51.6854515076],"type":"Point"}
}