{
  "type": "Feature",
  "properties": {
    "iso:country":"NL",
    "sg:address":"Henri Dunantplein 6",
    "sg:city":"De Bilt",
    "sg:orig_category":"Farmaceutische Producten Gh",
    "sg:phone":"+31 30 220 4040",
    "sg:postcode":"3731 CL",
    "sg:province":"Utrecht",
    "wof:name":"Intermark Technology Bv",
    "wof:placetype":"venue"
},
  "geometry": {"coordinates":[5.17298,52.109791],"type":"Point"}
}