{
  "type": "Feature",
  "properties": {
    "addr:full":"Nieuwstraat 59 Koewacht Zeeland 4576 AJ",
    "addr:housenumber":"59",
    "addr:postcode":"4576 aj",
    "addr:street":"Nieuwstraat",
    "iso:country":"NL",
    "sg:address":"Nieuwstraat 59",
    "sg:city":"Koewacht",
    "sg:orig_category":"Verlichting And Huishoudartikelen",
    "sg:phone":"+31 114 361 612",
    "sg:postcode":"4576 AJ",
    "sg:province":"Zeeland",
    "wof:name":"G.M. De Caluwe",
    "wof:placetype":"venue"
},
  "geometry": {"coordinates":[3.972782,51.227718],"type":"Point"}
}