{
  "type": "Feature",
  "properties": {
    "addr:full":"Tweede Westerparklaan 127 Utrecht Utrecht 3544 VP",
    "addr:housenumber":"127",
    "addr:postcode":"3544 vp",
    "addr:street":"Tweede Westerparklaan",
    "iso:country":"NL",
    "sg:address":"Tweede Westerparklaan 127",
    "sg:city":"Utrecht",
    "sg:orig_category":"Autorijscholen",
    "sg:phone":"+31 30 288 5296",
    "sg:postcode":"3544 VP",
    "sg:province":"Utrecht",
    "wof:name":"Fokker Autorijschool",
    "wof:placetype":"venue"
},
  "geometry": {"coordinates":[5.049608,52.091099],"type":"Point"}
}