{
  "type": "Feature",
  "properties": {
    "iso:country":"NL",
    "sg:address":"Ranonkelstraat 7",
    "sg:city":"Enschede",
    "sg:orig_category":"Technische Studies And Onderzoek",
    "sg:phone":"+31 53 432 8449",
    "sg:postcode":"7531 WV",
    "sg:province":"NL.08",
    "wof:name":"Van Steenoven Design Bv",
    "wof:placetype":"venue"
},
  "geometry": {"coordinates":[6.91873,52.22644],"type":"Point"}
}