{
  "type": "Feature",
  "properties": {
    "addr:full":"Stokkersweg 8 Eibergen Gelderland 7151 MK",
    "addr:housenumber":"8",
    "addr:postcode":"7151",
    "addr:street":"Stokkersweg;Gelderland",
    "iso:country":"NL",
    "sg:address":"Stokkersweg 8",
    "sg:city":"Eibergen",
    "sg:orig_category":"Kantoorartikelen",
    "sg:phone":"+31 545 472 023",
    "sg:postcode":"7151 MK",
    "sg:province":"Gelderland",
    "wof:name":"Timmerman Kantoormachines",
    "wof:placetype":"venue"
},
  "geometry": {"coordinates":[6.6238827705,52.1088180542],"type":"Point"}
}