{
  "type": "Feature",
  "properties": {
    "addr:full":"Rechtstraat 77 Maastricht Limburg 6221 EH",
    "addr:housenumber":"77",
    "addr:postcode":"6221 eh",
    "addr:street":"Rechtstraat",
    "iso:country":"NL",
    "sg:address":"Rechtstraat 77",
    "sg:city":"Maastricht",
    "sg:orig_category":"Kunst And Kunstenaarsbenodigdheden",
    "sg:phone":"+31 43 325 3690",
    "sg:postcode":"6221 EH",
    "sg:province":"Limburg",
    "wof:name":"Rive Gauche",
    "wof:placetype":"venue"
},
  "geometry": {"coordinates":[5.698457,50.848068],"type":"Point"}
}