{
  "type": "Feature",
  "properties": {
    "addr:full":"Emmersewg 10 Diessen Noord-Brabant 5087 TV",
    "addr:housenumber":"10",
    "addr:postcode":"5087 tv",
    "addr:street":"Emmersewg",
    "iso:country":"NL",
    "sg:address":"Emmersewg 10",
    "sg:city":"Diessen",
    "sg:classifiers":[
        {
            "category":"Sports & Exercise",
            "subcategory":"Stables",
            "type":"Entertainment"
        }
    ],
    "sg:phone":"+31 13 504 2766",
    "sg:postcode":"5087 TV",
    "sg:province":"Noord-Brabant",
    "sg:tags":[
        "maneges"
    ],
    "wof:name":"Hoef, De",
    "wof:placetype":"venue"
},
  "geometry": {"coordinates":[5.195569,51.483448],"type":"Point"}
}