{
  "type": "Feature",
  "properties": {
    "iso:country":"NL",
    "sg:address":"Voorstraat 429",
    "sg:city":"Dordrecht",
    "sg:orig_category":"Kappers",
    "sg:phone":"+31 78 613 7346",
    "sg:postcode":"3311 CT",
    "sg:province":"South Holland",
    "wof:name":"F.M. Van Leeuwen",
    "wof:placetype":"venue"
},
  "geometry": {"coordinates":[4.6618151665,51.8135871887],"type":"Point"}
}