{
  "type": "Feature",
  "properties": {
    "addr:full":"Veldmaterstr 2 Haaksbergen Overijssel 7482 TB",
    "addr:housenumber":"2",
    "addr:postcode":"7482 tb",
    "addr:street":"Veldmaterstr",
    "iso:country":"NL",
    "sg:address":"Veldmaterstr 2",
    "sg:city":"Haaksbergen",
    "sg:orig_category":"Orthopedagogen",
    "sg:phone":"+31 53 572 3160",
    "sg:postcode":"7482 TB",
    "sg:province":"Overijssel",
    "wof:name":"Broeke, Drs A B H M Ten",
    "wof:placetype":"venue"
},
  "geometry": {"coordinates":[6.7438368797,52.1674385071],"type":"Point"}
}