{
  "type": "Feature",
  "properties": {
    "addr:full":"Slootdreef 66 Zoetermeer Zuid-Holland 2724 AN",
    "addr:housenumber":"66",
    "addr:postcode":"2724 an",
    "addr:street":"Slootdreef",
    "iso:country":"NL",
    "sg:address":"Slootdreef 66",
    "sg:city":"Zoetermeer",
    "sg:orig_category":"Adviesbureaus Bedrijfsorganisatie",
    "sg:phone":"+31 79 331 9464",
    "sg:postcode":"2724 AN",
    "sg:province":"Zuid-Holland",
    "wof:name":"Bos Bv, R C",
    "wof:placetype":"venue"
},
  "geometry": {"coordinates":[4.513855,52.063488],"type":"Point"}
}