{
  "type": "Feature",
  "properties": {
    "addr:full":"Goudsteen 2 Maassluis Zuid-Holland 3142 CA",
    "addr:housenumber":"2",
    "addr:postcode":"3142 ca",
    "addr:street":"Goudsteen",
    "iso:country":"NL",
    "sg:address":"Goudsteen 2",
    "sg:city":"Maassluis",
    "sg:classifiers":[
        {
            "category":"Retail",
            "subcategory":"Photofinishing",
            "type":"Services"
        }
    ],
    "sg:phone":"+31 10 591 2532",
    "sg:postcode":"3142 CA",
    "sg:province":"Zuid-Holland",
    "sg:tags":[
        "foto",
        "film"
    ],
    "wof:name":"P.J.J. Teunissen",
    "wof:placetype":"venue"
},
  "geometry": {"coordinates":[4.253829,51.922569],"type":"Point"}
}