{
  "type": "Feature",
  "properties": {
    "addr:full":"Eleonorastr 111 Vlaardingen South Holland 3135 PA",
    "addr:housenumber":"111",
    "addr:postcode":"3135 pa",
    "iso:country":"NL",
    "sg:address":"Eleonorastr 111",
    "sg:city":"Vlaardingen",
    "sg:orig_category":"Acupunctuur",
    "sg:phone":"+31 10 434 0485",
    "sg:postcode":"3135 PA",
    "sg:province":"South Holland",
    "wof:name":"Bruggeman, H",
    "wof:placetype":"venue"
},
  "geometry": {"coordinates":[4.357423,51.914516],"type":"Point"}
}