{
  "type": "Feature",
  "properties": {
    "addr:full":"Achterwg 28 Herwynen Gelderland 4171 BC",
    "addr:housenumber":"28",
    "addr:postcode":"4171 bc",
    "addr:street":"Achterwg;Gelderland",
    "iso:country":"NL",
    "sg:address":"Achterwg 28",
    "sg:city":"Herwynen",
    "sg:orig_category":"Banken",
    "sg:phone":"+31 345 589 700",
    "sg:postcode":"4171 BC",
    "sg:province":"Gelderland",
    "sg:website":"http://www.rabobank.nl",
    "wof:name":"Rabobank",
    "wof:placetype":"venue"
},
  "geometry": {"coordinates":[5.130299,51.824982],"type":"Point"}
}