{
  "type": "Feature",
  "properties": {
    "addr:full":"Olmstraat 1 Breda Noord-Brabant 4814 LL",
    "addr:housenumber":"1",
    "addr:postcode":"4814 ll",
    "addr:street":"Olmstraat",
    "iso:country":"NL",
    "sg:address":"Olmstraat 1",
    "sg:city":"Breda",
    "sg:orig_category":"Marktonderzoekbureaus",
    "sg:phone":"+31 76 520 4574",
    "sg:postcode":"4814 LL",
    "sg:province":"Noord-Brabant",
    "wof:name":"Adviesbureau Micom Arabische Markt",
    "wof:placetype":"venue"
},
  "geometry": {"coordinates":[4.757178,51.587376],"type":"Point"}
}