{
  "type": "Feature",
  "properties": {
    "addr:full":"Van Den Berghlaan 78 Hoofddorp North Holland 2132 AT",
    "addr:housenumber":"78",
    "addr:postcode":"2132",
    "addr:street":"Van Den Berghlaan",
    "iso:country":"NL",
    "sg:address":"Van Den Berghlaan 78",
    "sg:city":"Hoofddorp",
    "sg:classifiers":[
        {
            "category":"Education",
            "subcategory":"Preschool",
            "type":"Public Place"
        }
    ],
    "sg:phone":"+31 23 561 6216",
    "sg:postcode":"2132 AT",
    "sg:province":"North Holland",
    "sg:tags":[
        "kleuteronderwijs",
        "basis-"
    ],
    "wof:name":"Freinet Basisschool",
    "wof:placetype":"venue"
},
  "geometry": {"coordinates":[4.703498,52.303406],"type":"Point"}
}