{
  "type": "Feature",
  "properties": {
    "iso:country":"NL",
    "sg:address":"Ceresstr 6",
    "sg:city":"Vlissingen",
    "sg:orig_category":"Webdesign Bureaus",
    "sg:phone":"+31 118 475 070",
    "sg:postcode":"4386 AX",
    "sg:province":"Zeeland",
    "sg:website":"http://www.wepdiezijn.nl",
    "wof:name":"Siahaya Wepdiezijn.Nl",
    "wof:placetype":"venue"
},
  "geometry": {"coordinates":[3.5923891068,51.4673995972],"type":"Point"}
}