{
  "type": "Feature",
  "properties": {
    "addr:full":"Vd Bergstr 6 Oud Beyerland Zuid-Holland 3263 EB",
    "addr:housenumber":"6",
    "addr:postcode":"3263 eb",
    "addr:street":"Oud Beyerland",
    "iso:country":"NL",
    "sg:address":"Vd Bergstr 6",
    "sg:city":"Oud Beyerland",
    "sg:orig_category":"Adviesbureaus Bedrijfsorganisatie",
    "sg:phone":"+31 186 640 913",
    "sg:postcode":"3263 EB",
    "sg:province":"Zuid-Holland",
    "wof:name":"Multibrains Bv",
    "wof:placetype":"venue"
},
  "geometry": {"coordinates":[4.404189,51.827976],"type":"Point"}
}