{
  "type": "Feature",
  "properties": {
    "iso:country":"NL",
    "sg:address":"Helmondseweg 20",
    "sg:city":"Aarle Rixtel",
    "sg:orig_category":"Metaalwerken",
    "sg:phone":"+31 492 524 914",
    "sg:postcode":"5735 RB",
    "sg:province":"Noord-Brabant",
    "wof:name":"Stucadoorsbedrijf Jac Janssen Bv",
    "wof:placetype":"venue"
},
  "geometry": {"coordinates":[5.65054,51.506783],"type":"Point"}
}