{
  "type": "Feature",
  "properties": {
    "addr:full":"Tienkamp 2 Krimpen Ad Yssel South Holland 2924 VC",
    "addr:housenumber":"2",
    "addr:postcode":"2924 vc",
    "addr:street":"Tienkamp;Yssel",
    "iso:country":"NL",
    "sg:address":"Tienkamp 2",
    "sg:city":"Krimpen Ad Yssel",
    "sg:orig_category":"Bloemen En Planten - Decoratie",
    "sg:phone":"+31 180 550 067",
    "sg:postcode":"2924 VC",
    "sg:province":"South Holland",
    "wof:name":"Indigo",
    "wof:placetype":"venue"
},
  "geometry": {"coordinates":[4.604232,51.923344],"type":"Point"}
}