{
  "type": "Feature",
  "properties": {
    "addr:full":"Stevenzandsestr 59 Tilburg Noord-Brabant 5021 HB",
    "addr:housenumber":"59",
    "addr:postcode":"5021 hb",
    "addr:street":"Stevenzandsestr",
    "iso:country":"NL",
    "sg:address":"Stevenzandsestr 59",
    "sg:city":"Tilburg",
    "sg:orig_category":"Webdesign Bureaus",
    "sg:phone":"+31 13 543 0072",
    "sg:postcode":"5021 HB",
    "sg:province":"Noord-Brabant",
    "wof:name":"Weps",
    "wof:placetype":"venue"
},
  "geometry": {"coordinates":[5.0896229744,51.5513038635],"type":"Point"}
}