{
  "type": "Feature",
  "properties": {
    "addr:full":"Karveelweg 14 Maastricht Limburg 6222 NH",
    "addr:housenumber":"14",
    "addr:postcode":"6222 nh",
    "addr:street":"Karveelweg",
    "iso:country":"NL",
    "sg:address":"Karveelweg 14",
    "sg:city":"Maastricht",
    "sg:orig_category":"Zuivelproducten And Spijsoli?n Gh",
    "sg:phone":"+31 43 362 0699",
    "sg:postcode":"6222 NH",
    "sg:province":"Limburg",
    "wof:name":"Van Der Wee Kaas Bv",
    "wof:placetype":"venue"
},
  "geometry": {"coordinates":[5.706552,50.87431],"type":"Point"}
}