{
  "type": "Feature",
  "properties": {
    "addr:full":"Fuchsiastr 42 S Gravenhage Zuid-Holland 2565 PS",
    "addr:housenumber":"42;gravenhage",
    "addr:postcode":"2565 ps",
    "addr:street":"Fuchsiastr;S",
    "iso:country":"NL",
    "sg:address":"Fuchsiastr 42",
    "sg:city":"S Gravenhage",
    "sg:orig_category":"Adviesbureaus",
    "sg:phone":"+31 70 323 8216",
    "sg:postcode":"2565 PS",
    "sg:province":"Zuid-Holland",
    "wof:name":"Marral",
    "wof:placetype":"venue"
},
  "geometry": {"coordinates":[4.26129,52.076382],"type":"Point"}
}