{
  "type": "Feature",
  "properties": {
    "iso:country":"NL",
    "sg:address":"Aegidiusstr 98A",
    "sg:city":"Rotterdam",
    "sg:orig_category":"Modellenbureaus En Modellen Freelance",
    "sg:phone":"+31 10 412 1232",
    "sg:postcode":"3061 XP",
    "sg:province":"South Holland",
    "wof:name":"Botte Hond, Huize De",
    "wof:placetype":"venue"
},
  "geometry": {"coordinates":[4.510584,51.923466],"type":"Point"}
}