{
  "type": "Feature",
  "properties": {
    "iso:country":"NL",
    "sg:address":"Westenengerdk 14",
    "sg:city":"Harskamp",
    "sg:orig_category":"Makelaars En Adviseurs Onroerende Goederen",
    "sg:phone":"+31 318 457 241",
    "sg:postcode":"6732 GR",
    "sg:province":"Gelderland",
    "wof:name":"Fliert, G Van De",
    "wof:placetype":"venue"
},
  "geometry": {"coordinates":[5.732635,52.122196],"type":"Point"}
}