{
  "type": "Feature",
  "properties": {
    "iso:country":"NL",
    "sg:address":"De Ploeg 12",
    "sg:city":"Wezep",
    "sg:orig_category":"Adviesbureaus Bouwkunde",
    "sg:phone":"+31 38 375 8778",
    "sg:postcode":"8091 NA",
    "sg:province":"Gelderland",
    "wof:name":"Artes5 Calculatiebureau",
    "wof:placetype":"venue"
},
  "geometry": {"coordinates":[5.990594,52.454071],"type":"Point"}
}