{
  "type": "Feature",
  "properties": {
    "addr:full":"Maliebaan 95 Utrecht Utrecht 3581 CH",
    "addr:housenumber":"95",
    "addr:postcode":"3581",
    "addr:street":"Maliebaan",
    "iso:country":"NL",
    "sg:address":"Maliebaan 95",
    "sg:city":"Utrecht",
    "sg:orig_category":"Technische Studies And Onderzoek",
    "sg:phone":"+31 30 231 1377",
    "sg:postcode":"3581 CH",
    "sg:province":"Utrecht",
    "wof:name":"Lichtveld Buis & Partners Bv",
    "wof:placetype":"venue"
},
  "geometry": {"coordinates":[5.135642,52.092258],"type":"Point"}
}