{
  "type": "Feature",
  "properties": {
    "iso:country":"NL",
    "sg:address":"Nieuwemeerdijk 294",
    "sg:city":"Badhoevedorp",
    "sg:orig_category":"Overheidsdiensten",
    "sg:phone":"+31 20 601 0616",
    "sg:postcode":"1171 NS",
    "sg:province":"North Holland",
    "wof:name":"Rehoboth",
    "wof:placetype":"venue"
},
  "geometry": {"coordinates":[4.8139638901,52.3279914856],"type":"Point"}
}