{
  "type": "Feature",
  "properties": {
    "addr:full":"Burg. D. Kooimanweg 885 Purmerend North Holland 1444 CE",
    "addr:housenumber":"885",
    "addr:postcode":"1444 ce",
    "addr:street":"Burg. D. Kooimanweg",
    "iso:country":"NL",
    "sg:address":"Burg. D. Kooimanweg 885",
    "sg:city":"Purmerend",
    "sg:orig_category":"Kappers",
    "sg:phone":"+31 299 460 364",
    "sg:postcode":"1444 CE",
    "sg:province":"North Holland",
    "wof:name":"Marja Bouwmeester",
    "wof:placetype":"venue"
},
  "geometry": {"coordinates":[4.957149,52.525726],"type":"Point"}
}