{
  "type": "Feature",
  "properties": {
    "addr:full":"Hogewg 69 Zaltbommel Gelderland 5301 LK",
    "addr:housenumber":"69",
    "addr:postcode":"5301 lk",
    "addr:street":"Hogewg;Gelderland",
    "iso:country":"NL",
    "sg:address":"Hogewg 69",
    "sg:city":"Zaltbommel",
    "sg:orig_category":"Projectontwikkeling",
    "sg:phone":"+31 418 681 133",
    "sg:postcode":"5301 LK",
    "sg:province":"Gelderland",
    "wof:name":"Burgfonds Bv",
    "wof:placetype":"venue"
},
  "geometry": {"coordinates":[5.2563,51.80101],"type":"Point"}
}