{
  "type": "Feature",
  "properties": {
    "iso:country":"NL",
    "sg:address":"Hooft Graaflandstraat 73",
    "sg:city":"Utrecht",
    "sg:orig_category":"Onderhoud And Reparatie Kantoorapparatuur",
    "sg:phone":"+31 30 280 5948",
    "sg:postcode":"3525 VN",
    "sg:province":"Utrecht",
    "wof:name":"Lyrae Automatisering",
    "wof:placetype":"venue"
},
  "geometry": {"coordinates":[5.117582,52.06218],"type":"Point"}
}