{
  "type": "Feature",
  "properties": {
    "addr:full":"Botterstr 5 Huizen Noord-Holland 1271 XL",
    "addr:housenumber":"5",
    "addr:postcode":"1271 xl",
    "addr:street":"Botterstr",
    "iso:country":"NL",
    "sg:address":"Botterstr 5",
    "sg:city":"Huizen",
    "sg:orig_category":"Vakorganisaties",
    "sg:phone":"+31 35 525 4820",
    "sg:postcode":"1271 XL",
    "sg:province":"Noord-Holland",
    "wof:name":"Cnv",
    "wof:placetype":"venue"
},
  "geometry": {"coordinates":[5.23076,52.302971],"type":"Point"}
}