{
  "type": "Feature",
  "properties": {
    "addr:full":"Oude Kruisweg 94 Cruquius North Holland 2142 EH",
    "addr:housenumber":"94",
    "addr:postcode":"2142 eh",
    "addr:street":"Oude Kruisweg",
    "iso:country":"NL",
    "sg:address":"Oude Kruisweg 94",
    "sg:city":"Cruquius",
    "sg:orig_category":"Goederenvervoer Over De Weg",
    "sg:phone":"+31 23 528 8981",
    "sg:postcode":"2142 EH",
    "sg:province":"North Holland",
    "wof:name":"Hoogenboom En Zoon",
    "wof:placetype":"venue"
},
  "geometry": {"coordinates":[4.642466,52.332191],"type":"Point"}
}