{
  "type": "Feature",
  "properties": {
    "addr:full":"Molenln 88A Honselersdyk South Holland 2675 CG",
    "addr:housenumber":"88a",
    "addr:postcode":"2675 cg",
    "addr:street":"Molenln",
    "iso:country":"NL",
    "sg:address":"Molenln 88A",
    "sg:city":"Honselersdyk",
    "sg:orig_category":"Onderhoudswerken",
    "sg:phone":"+31 174 620 352",
    "sg:postcode":"2675 CG",
    "sg:province":"South Holland",
    "wof:name":"Berendse, P J M",
    "wof:placetype":"venue"
},
  "geometry": {"coordinates":[4.234445,52.004486],"type":"Point"}
}