{
  "type": "Feature",
  "properties": {
    "addr:full":"De Lind 2 Prinsenbeek Noord-Brabant 4841 KC",
    "addr:housenumber":"2",
    "addr:postcode":"4841 kc",
    "addr:street":"De Lind",
    "iso:country":"NL",
    "sg:address":"De Lind 2",
    "sg:city":"Prinsenbeek",
    "sg:orig_category":"Drukkerijen",
    "sg:phone":"+31 76 541 3745",
    "sg:postcode":"4841 KC",
    "sg:province":"Noord-Brabant",
    "wof:name":"Perfekt Drukkerij Bv",
    "wof:placetype":"venue"
},
  "geometry": {"coordinates":[4.702324,51.604774],"type":"Point"}
}