{
  "type": "Feature",
  "properties": {
    "addr:full":"Hoofdstr 8 Valkenburg Zh Zuid-Holland 2235 CG",
    "addr:housenumber":"8",
    "addr:postcode":"2235 cg",
    "addr:street":"Hoofdstr",
    "iso:country":"NL",
    "sg:address":"Hoofdstr 8",
    "sg:city":"Valkenburg Zh",
    "sg:orig_category":"Bloemen En Planten",
    "sg:phone":"+31 71 407 5931",
    "sg:postcode":"2235 CG",
    "sg:province":"Zuid-Holland",
    "wof:name":"Bol, A",
    "wof:placetype":"venue"
},
  "geometry": {"coordinates":[4.434025,52.180401],"type":"Point"}
}