{
  "type": "Feature",
  "properties": {
    "iso:country":"NL",
    "sg:address":"Europaweg 4",
    "sg:city":"Zoetermeer",
    "sg:orig_category":"Overheidsdiensten",
    "sg:phone":"+31 79 323 2323",
    "sg:postcode":"2711 AH",
    "sg:province":"Zuid-Holland",
    "wof:name":"Ministerie Van Onderwijs Cultuur En Wetenschappen",
    "wof:placetype":"venue"
},
  "geometry": {"coordinates":[4.4896640778,52.063419342],"type":"Point"}
}