{
  "type": "Feature",
  "properties": {
    "iso:country":"NL",
    "sg:address":"Wegastr 40",
    "sg:city":"S Gravenhage",
    "sg:orig_category":"Plotservice",
    "sg:phone":"+31 70 347 6464",
    "sg:postcode":"2516 AP",
    "sg:province":"South Holland",
    "sg:website":"http://www.reprovandekamp.nl",
    "wof:name":"Repro-Van De Kamp Bv",
    "wof:placetype":"venue"
},
  "geometry": {"coordinates":[4.33931,52.06786],"type":"Point"}
}