{
  "type": "Feature",
  "properties": {
    "addr:full":"Randenburgsewg 11 Reeuwyk Zuid-Holland 2811 PR",
    "addr:housenumber":"11",
    "addr:postcode":"2811 pr",
    "addr:street":"Randenburgsewg",
    "iso:country":"NL",
    "sg:address":"Randenburgsewg 11",
    "sg:city":"Reeuwyk",
    "sg:orig_category":"Grondwerken",
    "sg:phone":"+31 182 393 071",
    "sg:postcode":"2811 PR",
    "sg:province":"Zuid-Holland",
    "wof:name":"Verkleij, Wim",
    "wof:placetype":"venue"
},
  "geometry": {"coordinates":[4.666631,52.061165],"type":"Point"}
}