{
  "type": "Feature",
  "properties": {
    "addr:full":"Paulingstraat 12 Castricum North Holland 1902 CX",
    "addr:housenumber":"12",
    "addr:postcode":"1902 cx",
    "addr:street":"Paulingstraat",
    "iso:country":"NL",
    "sg:address":"Paulingstraat 12",
    "sg:city":"Castricum",
    "sg:orig_category":"Bedrijfs- And Managementsconsultants",
    "sg:phone":"+31 251 670 820",
    "sg:postcode":"1902 CX",
    "sg:province":"North Holland",
    "wof:name":"Bouwhuis Training & Advies Bv",
    "wof:placetype":"venue"
},
  "geometry": {"coordinates":[4.679072,52.546806],"type":"Point"}
}