{
  "type": "Feature",
  "properties": {
    "iso:country":"NL",
    "sg:address":"Emmapark 100",
    "sg:city":"Pijnacker",
    "sg:classifiers":[
        {
            "category":"Retail",
            "subcategory":"Photofinishing",
            "type":"Services"
        }
    ],
    "sg:phone":"+31 15 369 2855",
    "sg:postcode":"2641 EN",
    "sg:province":"Zuid-Holland",
    "sg:tags":[
        "foto",
        "film"
    ],
    "wof:name":"Foto-Video Dubbel D Bv",
    "wof:placetype":"venue"
},
  "geometry": {"coordinates":[4.431131,52.01815],"type":"Point"}
}