{
  "type": "Feature",
  "properties": {
    "iso:country":"NL",
    "sg:address":"Cramerstr 9",
    "sg:city":"Tilburg",
    "sg:orig_category":"Autorijscholen",
    "sg:phone":"+31 13 455 5202",
    "sg:postcode":"5011 VM",
    "sg:province":"Noord-Brabant",
    "wof:name":"Sammy",
    "wof:placetype":"venue"
},
  "geometry": {"coordinates":[5.075818,51.578819],"type":"Point"}
}