{
  "type": "Feature",
  "properties": {
    "iso:country":"NL",
    "sg:address":"Noordermiddenweg 10",
    "sg:city":"Creil",
    "sg:orig_category":"Bloemen- And Plantenteelt",
    "sg:phone":"+31 527 274 557",
    "sg:postcode":"8312 PE",
    "sg:province":"Flevoland",
    "wof:name":"Firma Van Meer Wuestenenk",
    "wof:placetype":"venue"
},
  "geometry": {"coordinates":[5.660859108,52.7586250305],"type":"Point"}
}