{
  "type": "Feature",
  "properties": {
    "addr:full":"Planckstraat 48 Dordrecht Zuid-Holland 3316 GS",
    "addr:housenumber":"48",
    "addr:postcode":"3316 gs",
    "addr:street":"Planckstraat",
    "iso:country":"NL",
    "sg:address":"Planckstraat 48",
    "sg:city":"Dordrecht",
    "sg:orig_category":"Elektronische Bedrijfsinstallaties",
    "sg:phone":"+31 78 651 5150",
    "sg:postcode":"3316 GS",
    "sg:province":"Zuid-Holland",
    "wof:name":"Technisch Bureau Mous Bv",
    "wof:placetype":"venue"
},
  "geometry": {"coordinates":[4.635269,51.776752],"type":"Point"}
}