{
  "type": "Feature",
  "properties": {
    "addr:full":"Sloep 3 De Rijp Noord-Holland 1483 HA",
    "addr:housenumber":"3",
    "addr:postcode":"1483 ha",
    "addr:street":"Sloep",
    "iso:country":"NL",
    "sg:address":"Sloep 3",
    "sg:city":"De Rijp",
    "sg:orig_category":"Artsen - Huisartsen",
    "sg:phone":"+31 299 671 455",
    "sg:postcode":"1483 HA",
    "sg:province":"Noord-Holland",
    "wof:name":"Vijver, F J M Van De",
    "wof:placetype":"venue"
},
  "geometry": {"coordinates":[4.844032,52.558357],"type":"Point"}
}