{
  "type": "Feature",
  "properties": {
    "addr:full":"Vogelenzangseweg 21 Vogelenzang North Holland 2114 BA",
    "addr:housenumber":"21",
    "addr:postcode":"2114 ba",
    "addr:street":"Vogelenzangseweg",
    "iso:country":"NL",
    "sg:address":"Vogelenzangseweg 21",
    "sg:city":"Vogelenzang",
    "sg:orig_category":"Waterbeheer",
    "sg:phone":"+31 23 523 3636",
    "sg:postcode":"2114 BA",
    "sg:province":"North Holland",
    "wof:name":"Gemeentewaterleidingen Amsterdam Leiduin",
    "wof:placetype":"venue"
},
  "geometry": {"coordinates":[4.5818939209,52.3354873657],"type":"Point"}
}