{
  "type": "Feature",
  "properties": {
    "addr:full":"Schoener 3630 Lelystad Flevoland 8243 WN",
    "addr:postcode":"3630;8243 wn",
    "addr:street":"Schoener;Flevoland",
    "iso:country":"NL",
    "sg:address":"Schoener 3630",
    "sg:city":"Lelystad",
    "sg:orig_category":"Kunst And Kunstenaarsbenodigdheden",
    "sg:phone":"+31 320 254 391",
    "sg:postcode":"8243 WN",
    "sg:province":"Flevoland",
    "wof:name":"Lijstenmakerij Bohle",
    "wof:placetype":"venue"
},
  "geometry": {"coordinates":[5.460839,52.501781],"type":"Point"}
}