{
  "type": "Feature",
  "properties": {
    "addr:full":"Kooienswater 75 Zoetermeer South Holland 2715 AG",
    "addr:housenumber":"75",
    "addr:postcode":"2715",
    "addr:street":"Kooienswater",
    "iso:country":"NL",
    "sg:address":"Kooienswater 75",
    "sg:city":"Zoetermeer",
    "sg:classifiers":[
        {
            "category":"Personal",
            "subcategory":"Nail Salon",
            "type":"Services"
        }
    ],
    "sg:phone":"+31 79 321 4426",
    "sg:postcode":"2715 AG",
    "sg:province":"South Holland",
    "sg:tags":[
        "pedicure"
    ],
    "wof:name":"Tol-Van Egmond, J A",
    "wof:placetype":"venue"
},
  "geometry": {"coordinates":[4.473891,52.050953],"type":"Point"}
}