{
  "type": "Feature",
  "properties": {
    "addr:full":"Langstraat 11 Barneveld Gelderland 3771 BA",
    "addr:housenumber":"11",
    "addr:postcode":"3771 ba",
    "addr:street":"Langstraat;Gelderland",
    "iso:country":"NL",
    "sg:address":"Langstraat 11",
    "sg:city":"Barneveld",
    "sg:orig_category":"Kappers",
    "sg:phone":"+31 342 412 997",
    "sg:postcode":"3771 BA",
    "sg:province":"Gelderland",
    "wof:name":"E. Leeuwis",
    "wof:placetype":"venue"
},
  "geometry": {"coordinates":[5.5840849876,52.1404418945],"type":"Point"}
}