{
  "type": "Feature",
  "properties": {
    "addr:full":"Sierbloem 3 Rotterdam Zuid-Holland 3068 AP",
    "addr:housenumber":"3",
    "addr:postcode":"3068 ap",
    "addr:street":"Sierbloem",
    "iso:country":"NL",
    "sg:address":"Sierbloem 3",
    "sg:city":"Rotterdam",
    "sg:orig_category":"Beveiliging",
    "sg:phone":"+31 10 286 0541",
    "sg:postcode":"3068 AP",
    "sg:province":"Zuid-Holland",
    "sg:website":"http://www.deskvof.nl",
    "wof:name":"Desk",
    "wof:placetype":"venue"
},
  "geometry": {"coordinates":[4.535047,51.955463],"type":"Point"}
}