{
  "type": "Feature",
  "properties": {
    "iso:country":"NL",
    "sg:address":"Beatrixstraat 2",
    "sg:city":"Rossum Gld",
    "sg:orig_category":"Glaszetten",
    "sg:phone":"+31 418 662 147",
    "sg:postcode":"5328 AX",
    "sg:province":"Gelderland",
    "wof:name":"Glasservice Glorius",
    "wof:placetype":"venue"
},
  "geometry": {"coordinates":[5.329657,51.798813],"type":"Point"}
}