{
  "type": "Feature",
  "properties": {
    "addr:full":"Beatrixstraat 2 Rossum Gld Gelderland 5328 AX",
    "addr:housenumber":"2",
    "addr:postcode":"5328 ax",
    "addr:street":"Beatrixstraat;Gld Gelderland",
    "iso:country":"NL",
    "sg:address":"Beatrixstraat 2",
    "sg:city":"Rossum Gld",
    "sg:orig_category":"Glaszetten",
    "sg:phone":"+31 418 662 147",
    "sg:postcode":"5328 AX",
    "sg:province":"Gelderland",
    "wof:name":"Glasservice Glorius",
    "wof:placetype":"venue"
},
  "geometry": {"coordinates":[5.329657,51.798813],"type":"Point"}
}