{
  "type": "Feature",
  "properties": {
    "addr:full":"Grt Hazelaar 13 Bergen Op Zoom Noord-Brabant 4623 AJ",
    "addr:housenumber":"13",
    "addr:postcode":"4623 aj",
    "addr:street":"Hazelaar",
    "iso:country":"NL",
    "sg:address":"Grt Hazelaar 13",
    "sg:city":"Bergen Op Zoom",
    "sg:orig_category":"Administratie- En Boekhoudkantoren",
    "sg:phone":"+31 164 244 372",
    "sg:postcode":"4623 AJ",
    "sg:province":"Noord-Brabant",
    "wof:name":"Dietvorst",
    "wof:placetype":"venue"
},
  "geometry": {"coordinates":[4.30881,51.491013],"type":"Point"}
}