{
  "type": "Feature",
  "properties": {
    "addr:full":"Willem Iii Straat 21 Wateringen South Holland 2291 TL",
    "addr:housenumber":"21",
    "addr:postcode":"2291 tl",
    "addr:street":"Willem Iii Straat",
    "iso:country":"NL",
    "sg:address":"Willem Iii Straat 21",
    "sg:city":"Wateringen",
    "sg:orig_category":"Boekhouders",
    "sg:phone":"+31 174 292 572",
    "sg:postcode":"2291 TL",
    "sg:province":"South Holland",
    "wof:name":"Administratiekantoor P. Sterk",
    "wof:placetype":"venue"
},
  "geometry": {"coordinates":[4.268939,52.027985],"type":"Point"}
}