{
  "type": "Feature",
  "properties": {
    "addr:full":"Dorpsstr 105 Renswoude Utrecht 3927 BC",
    "addr:housenumber":"105",
    "addr:postcode":"3927 bc",
    "iso:country":"NL",
    "sg:address":"Dorpsstr 105",
    "sg:city":"Renswoude",
    "sg:orig_category":"Kinderkleding",
    "sg:phone":"+31 318 574 676",
    "sg:postcode":"3927 BC",
    "sg:province":"Utrecht",
    "wof:name":"Harlekijn",
    "wof:placetype":"venue"
},
  "geometry": {"coordinates":[5.538464,52.074284],"type":"Point"}
}