{
  "type": "Feature",
  "properties": {
    "addr:full":"Kraanvogelstr 18 Velp Gld Gelderland 6883 CL",
    "addr:housenumber":"18",
    "addr:postcode":"6883",
    "addr:street":"Kraanvogelstr;Gld Gelderland",
    "iso:country":"NL",
    "sg:address":"Kraanvogelstr 18",
    "sg:city":"Velp Gld",
    "sg:orig_category":"Gordijnenateliers",
    "sg:phone":"+31 26 364 6107",
    "sg:postcode":"6883 CL",
    "sg:province":"Gelderland",
    "wof:name":"Matser",
    "wof:placetype":"venue"
},
  "geometry": {"coordinates":[5.984801,51.986008],"type":"Point"}
}