{
  "type": "Feature",
  "properties": {
    "iso:country":"NL",
    "sg:address":"Tupolevln 32",
    "sg:city":"Schiphol Ryk",
    "sg:orig_category":"Medische Installaties En Instrumenten - Fabrieken",
    "sg:phone":"+31 20 653 0553",
    "sg:postcode":"1119 NZ",
    "sg:province":"North Holland",
    "sg:website":"http://www.scanlangroup.com",
    "wof:name":"Scanlan Group Bv",
    "wof:placetype":"venue"
},
  "geometry": {"coordinates":[4.75638,52.281315],"type":"Point"}
}