{
  "type": "Feature",
  "properties": {
    "iso:country":"NL",
    "sg:address":"Geerdinkswg 205",
    "sg:city":"Hengelo Ov",
    "sg:orig_category":"Accountants - Administratie- Consulenten En -Kantoren",
    "sg:phone":"+31 74 291 4569",
    "sg:postcode":"7555 DZ",
    "sg:province":"Overijssel",
    "wof:name":"Eshuisbl\u00f7Mer",
    "wof:placetype":"venue"
},
  "geometry": {"coordinates":[6.775103,52.266941],"type":"Point"}
}