{
  "type": "Feature",
  "properties": {
    "addr:full":"De Streekweg 5 Den Andel Groningen 9956 PN",
    "addr:housenumber":"5",
    "addr:postcode":"andel;9956 pn",
    "addr:street":"De Streekweg",
    "iso:country":"NL",
    "sg:address":"De Streekweg 5",
    "sg:city":"Den Andel",
    "sg:orig_category":"Metaalbekleding And -Behandeling",
    "sg:phone":"+31 595 424 734",
    "sg:postcode":"9956 PN",
    "sg:province":"Groningen",
    "wof:name":"Uptide Metal Parts",
    "wof:placetype":"venue"
},
  "geometry": {"coordinates":[6.507646,53.393024],"type":"Point"}
}