{
  "type": "Feature",
  "properties": {
    "iso:country":"NL",
    "sg:address":"Delfweg 40",
    "sg:city":"Noordwijkerhout",
    "sg:orig_category":"Bouwmaterialen Gh",
    "sg:phone":"+31 252 419 033",
    "sg:postcode":"2211 VM",
    "sg:province":"Zuid-Holland",
    "wof:name":"Atlas Acomfa Bv",
    "wof:placetype":"venue"
},
  "geometry": {"coordinates":[4.530893,52.286278],"type":"Point"}
}