{
  "type": "Feature",
  "properties": {
    "addr:full":"Kloosterstraat 1 Heythuysen Limburg 6093 CT",
    "addr:housenumber":"1",
    "addr:postcode":"6093 ct",
    "addr:street":"Kloosterstraat",
    "iso:country":"NL",
    "sg:address":"Kloosterstraat 1",
    "sg:city":"Heythuysen",
    "sg:classifiers":[
        {
            "category":"Fast Food",
            "type":"Food & Drink"
        }
    ],
    "sg:phone":"+31 475 496 207",
    "sg:postcode":"6093 CT",
    "sg:province":"Limburg",
    "sg:tags":[
        "afhaal",
        "restaurant"
    ],
    "wof:name":"Sphinx Heythuysen",
    "wof:placetype":"venue"
},
  "geometry": {"coordinates":[5.893891,51.24979],"type":"Point"}
}