{
  "type": "Feature",
  "properties": {
    "iso:country":"NL",
    "sg:address":"Eikhofweg 5",
    "sg:city":"Holthees",
    "sg:classifiers":[
        {
            "category":"Shopping",
            "subcategory":"Gifts & Souvenirs",
            "type":"Retail Goods"
        }
    ],
    "sg:phone":"+31 478 639 040",
    "sg:postcode":"5824 AR",
    "sg:province":"Noord-Brabant",
    "sg:tags":[
        "geschenken"
    ],
    "wof:name":"Mg Trading Bv",
    "wof:placetype":"venue"
},
  "geometry": {"coordinates":[6.007479,51.574135],"type":"Point"}
}