{
  "type": "Feature",
  "properties": {
    "addr:full":"Kanaal A Nz 100 Emmer Compascuum Drenthe 7881 KL",
    "addr:housenumber":"100;compascuum",
    "addr:postcode":"7881 kl",
    "addr:street":"Kanaal A Nz",
    "iso:country":"NL",
    "sg:address":"Kanaal A Nz 100",
    "sg:city":"Emmer Compascuum",
    "sg:classifiers":[
        {
            "category":"Food & Beverages",
            "subcategory":"Bakery",
            "type":"Retail Goods"
        }
    ],
    "sg:phone":"+31 591 351 308",
    "sg:postcode":"7881 KL",
    "sg:province":"Drenthe",
    "sg:tags":[
        "brood",
        "en",
        "banket"
    ],
    "wof:name":"Kort, J",
    "wof:placetype":"venue"
},
  "geometry": {"coordinates":[170.36663799999999,-43.587711],"type":"Point"}
}