{
  "type": "Feature",
  "properties": {
    "addr:full":"Iepenln 51 Bussum North Holland 1406 PT",
    "addr:housenumber":"51",
    "addr:postcode":"1406 pt",
    "addr:street":"Iepenln",
    "iso:country":"NL",
    "sg:address":"Iepenln 51",
    "sg:city":"Bussum",
    "sg:orig_category":"Psychosociale Therapeuten",
    "sg:phone":"+31 35 691 9202",
    "sg:postcode":"1406 PT",
    "sg:province":"North Holland",
    "wof:name":"Suzette Timmers Verhoeven",
    "wof:placetype":"venue"
},
  "geometry": {"coordinates":[5.158838,52.26952],"type":"Point"}
}