{
  "type": "Feature",
  "properties": {
    "addr:full":"Jonkheer Mockkade 33 Hillegom Zuid-Holland 2181 AL",
    "addr:housenumber":"33",
    "addr:postcode":"2181 al",
    "addr:street":"Jonkheer Mockkade",
    "iso:country":"NL",
    "sg:address":"Jonkheer Mockkade 33",
    "sg:city":"Hillegom",
    "sg:orig_category":"Autokeuringen",
    "sg:phone":"+31 252 531 199",
    "sg:postcode":"2181 AL",
    "sg:province":"Zuid-Holland",
    "wof:name":"Garagebedrijf Van Der Raat",
    "wof:placetype":"venue"
},
  "geometry": {"coordinates":[4.582985,52.290062],"type":"Point"}
}