{
  "type": "Feature",
  "properties": {
    "iso:country":"NL",
    "sg:address":"Kometenstr 101",
    "sg:city":"Hilversum",
    "sg:orig_category":"Journalisten Freelance",
    "sg:phone":"+31 35 685 2238",
    "sg:postcode":"1223 CJ",
    "sg:province":"Noord-Holland",
    "wof:name":"Ethi-Script",
    "wof:placetype":"venue"
},
  "geometry": {"coordinates":[5.195498,52.232632],"type":"Point"}
}