{
  "type": "Feature",
  "properties": {
    "addr:full":"Overwinningspln 111 Groningen Groningen 9728 GS",
    "addr:housenumber":"111",
    "addr:postcode":"9728 gs",
    "iso:country":"NL",
    "sg:address":"Overwinningspln 111",
    "sg:city":"Groningen",
    "sg:orig_category":"Kappers",
    "sg:phone":"+31 50 525 0328",
    "sg:postcode":"9728 GS",
    "sg:province":"Groningen",
    "wof:name":"Onnes",
    "wof:placetype":"venue"
},
  "geometry": {"coordinates":[6.558543,53.198483],"type":"Point"}
}