{
  "type": "Feature",
  "properties": {
    "addr:full":"Gasstraat Oost 40 Oss Noord-Brabant 5349 AV",
    "addr:housenumber":"40",
    "addr:postcode":"5349 av",
    "addr:street":"Gasstraat Oost",
    "iso:country":"NL",
    "sg:address":"Gasstraat Oost 40",
    "sg:city":"Oss",
    "sg:orig_category":"Verhuur Gereedschapsmachines And Gereedschappen",
    "sg:phone":"+31 412 647 972",
    "sg:postcode":"5349 AV",
    "sg:province":"Noord-Brabant",
    "wof:name":"Kramen Exploitatie W.L.L. Van Haaren",
    "wof:placetype":"venue"
},
  "geometry": {"coordinates":[-77.235214,38.312599],"type":"Point"}
}