{
  "type": "Feature",
  "properties": {
    "iso:country":"NL",
    "sg:address":"Bautscherwg 56",
    "sg:city":"Heerlen",
    "sg:orig_category":"Banken",
    "sg:phone":"+31 45 566 0067",
    "sg:postcode":"6418 EM",
    "sg:province":"Limburg",
    "sg:website":"http://www.sns.nl",
    "wof:name":"Sns",
    "wof:placetype":"venue"
},
  "geometry": {"coordinates":[6.004803,50.867023],"type":"Point"}
}