{
  "type": "Feature",
  "properties": {
    "addr:full":"Raadhuisln 4 Werkendam Noord-Brabant 4251 VS",
    "addr:housenumber":"4",
    "addr:postcode":"4251 vs",
    "addr:street":"Raadhuisln",
    "iso:country":"NL",
    "sg:address":"Raadhuisln 4",
    "sg:city":"Werkendam",
    "sg:orig_category":"Bejaarden - Verzorgingstehuizen",
    "sg:phone":"+31 183 662 400",
    "sg:postcode":"4251 VS",
    "sg:province":"Noord-Brabant",
    "wof:name":"Goezate",
    "wof:placetype":"venue"
},
  "geometry": {"coordinates":[4.895317,51.808372],"type":"Point"}
}