{
  "type": "Feature",
  "properties": {
    "iso:country":"NL",
    "sg:address":"Scheldestr 252Hg",
    "sg:city":"Amsterdam",
    "sg:orig_category":"Beurzen",
    "sg:phone":"+31 20 673 2614",
    "sg:postcode":"1078 GE",
    "sg:province":"Noord-Holland",
    "wof:name":"A & C",
    "wof:placetype":"venue"
},
  "geometry": {"coordinates":[4.8908,52.344711],"type":"Point"}
}