{
  "type": "Feature",
  "properties": {
    "addr:full":"Kastanjeln 44 Doetinchem Gelderland 7004 AK",
    "addr:housenumber":"44",
    "addr:postcode":"7004 ak",
    "addr:street":"Kastanjeln;Gelderland",
    "iso:country":"NL",
    "sg:address":"Kastanjeln 44",
    "sg:city":"Doetinchem",
    "sg:orig_category":"Organisatiebureaus",
    "sg:phone":"+31 314 362 722",
    "sg:postcode":"7004 AK",
    "sg:province":"Gelderland",
    "wof:name":"Tradecare",
    "wof:placetype":"venue"
},
  "geometry": {"coordinates":[6.3052210808,51.9559860229],"type":"Point"}
}