{
  "type": "Feature",
  "properties": {
    "iso:country":"NL",
    "sg:address":"Treubstr 1C",
    "sg:city":"Ryswyk Zh",
    "sg:orig_category":"Adviesbureaus Personeel",
    "sg:phone":"+31 70 360 2585",
    "sg:postcode":"2288 EG",
    "sg:province":"Zuid-Holland",
    "sg:website":"http://www.geldergroep.nl",
    "wof:name":"Geldergroep",
    "wof:placetype":"venue"
},
  "geometry": {"coordinates":[4.32436,52.037251],"type":"Point"}
}