{
  "type": "Feature",
  "properties": {
    "addr:full":"Antwerpsestr 16 S Gravenhage South Holland 2587 AG",
    "addr:housenumber":"16",
    "addr:postcode":"2587",
    "addr:street":"Antwerpsestr;S Gravenhage",
    "iso:country":"NL",
    "sg:address":"Antwerpsestr 16",
    "sg:city":"S Gravenhage",
    "sg:orig_category":"Adviesbureaus Planologie",
    "sg:phone":"+31 70 354 3025",
    "sg:postcode":"2587 AG",
    "sg:province":"South Holland",
    "wof:name":"Dauvellier",
    "wof:placetype":"venue"
},
  "geometry": {"coordinates":[4.29118,52.112942],"type":"Point"}
}