{
  "type": "Feature",
  "properties": {
    "addr:full":"Stationsplein 10 Lelystad NL. 8232 DL",
    "addr:housenumber":"10",
    "addr:postcode":"8232 dl",
    "addr:street":"Stationsplein;Nl.",
    "iso:country":"NL",
    "sg:address":"Stationsplein 10",
    "sg:city":"Lelystad",
    "sg:orig_category":"Watersport-, Sport- And Kampeerbenodigdheden Verhuur",
    "sg:phone":"+31 320 282 790",
    "sg:postcode":"8232 DL",
    "sg:province":"NL.",
    "wof:name":"Fietsenverhuur",
    "wof:placetype":"venue"
},
  "geometry": {"coordinates":[5.4729008675,52.5133209229],"type":"Point"}
}