{
  "type": "Feature",
  "properties": {
    "addr:full":"Kl Heiligland 20/Zw Haarlem North Holland 2011 EG",
    "addr:housenumber":"20 / zw",
    "addr:postcode":"2011 eg",
    "addr:street":"Kl Heiligland",
    "iso:country":"NL",
    "sg:address":"Kl Heiligland 20/Zw",
    "sg:city":"Haarlem",
    "sg:orig_category":"Fitnesscentra",
    "sg:phone":"+31 23 531 6914",
    "sg:postcode":"2011 EG",
    "sg:province":"North Holland",
    "wof:name":"Beautyline, Damessportschool",
    "wof:placetype":"venue"
},
  "geometry": {"coordinates":[4.642253,52.380562],"type":"Point"}
}