{
  "type": "Feature",
  "properties": {
    "addr:full":"Oostvest 56 Haarlem Noord-Holland 2011 AK",
    "addr:housenumber":"56",
    "addr:postcode":"2011 ak",
    "addr:street":"Oostvest",
    "iso:country":"NL",
    "sg:address":"Oostvest 56",
    "sg:city":"Haarlem",
    "sg:orig_category":"Cd'S, Grammofoonpl. En Muziekcass.-Maatschapp. En Grooth",
    "sg:phone":"+31 23 551 0854",
    "sg:postcode":"2011 AK",
    "sg:province":"Noord-Holland",
    "sg:website":"http://www.worldconnection.nl",
    "wof:name":"World Connection Bv",
    "wof:placetype":"venue"
},
  "geometry": {"coordinates":[4.646307,52.381062],"type":"Point"}
}