{
  "type": "Feature",
  "properties": {
    "iso:country":"NL",
    "sg:address":"Zonnedauw 10",
    "sg:city":"Oirschot",
    "sg:orig_category":"Vakantieverblijven",
    "sg:phone":"+31 40 262 1292",
    "sg:postcode":"5688 HM",
    "sg:province":"North Brabant",
    "wof:name":"Sprinkhaan, De",
    "wof:placetype":"venue"
},
  "geometry": {"coordinates":[5.388746,51.480499],"type":"Point"}
}