{
  "type": "Feature",
  "properties": {
    "addr:full":"Kapelln 16 Den Hoorn Zh Zuid-Holland 2635 DC",
    "addr:housenumber":"16",
    "addr:postcode":"2635",
    "addr:street":"Kapelln",
    "iso:country":"NL",
    "sg:address":"Kapelln 16",
    "sg:city":"Den Hoorn Zh",
    "sg:orig_category":"Voetbalverenigingen",
    "sg:phone":"+31 15 261 6792",
    "sg:postcode":"2635 DC",
    "sg:province":"Zuid-Holland",
    "wof:name":"Hoorn Vv, Den",
    "wof:placetype":"venue"
},
  "geometry": {"coordinates":[4.331055,51.99958],"type":"Point"}
}