{
  "type": "Feature",
  "properties": {
    "addr:full":"Westerstr 145 Amsterdam North Holland 1015 MA",
    "addr:housenumber":"145",
    "addr:postcode":"1015 ma",
    "iso:country":"NL",
    "sg:address":"Westerstr 145",
    "sg:city":"Amsterdam",
    "sg:orig_category":"Fietsen En Bromfietsen",
    "sg:phone":"+31 20 624 6195",
    "sg:postcode":"1015 MA",
    "sg:province":"North Holland",
    "wof:name":"Grimminck, Th M",
    "wof:placetype":"venue"
},
  "geometry": {"coordinates":[4.882504,52.378014],"type":"Point"}
}