{
  "type": "Feature",
  "properties": {
    "addr:full":"Hamelandroute 89 Aalten Gelderland 7121 JC",
    "addr:housenumber":"89",
    "addr:postcode":"7121 jc",
    "addr:street":"Hamelandroute;Gelderland",
    "iso:country":"NL",
    "sg:address":"Hamelandroute 89",
    "sg:city":"Aalten",
    "sg:orig_category":"Projectontwikkeling",
    "sg:phone":"+31 543 478 943",
    "sg:postcode":"7121 JC",
    "sg:province":"Gelderland",
    "wof:name":"Els",
    "wof:placetype":"venue"
},
  "geometry": {"coordinates":[6.58551,51.894989],"type":"Point"}
}