{
  "type": "Feature",
  "properties": {
    "iso:country":"NL",
    "sg:address":"Walstr 106",
    "sg:city":"Doetinchem",
    "sg:orig_category":"Koffiebranderijen",
    "sg:phone":"+31 314 333 770",
    "sg:postcode":"7001 BV",
    "sg:province":"Gelderland",
    "wof:name":"Veneti\u00eb",
    "wof:placetype":"venue"
},
  "geometry": {"coordinates":[6.288535,51.96677],"type":"Point"}
}