{
  "type": "Feature",
  "properties": {
    "iso:country":"NL",
    "sg:address":"Hurksestr 41",
    "sg:city":"Eindhoven",
    "sg:orig_category":"Werving En Selectie",
    "sg:phone":"+31 40 250 3100",
    "sg:postcode":"5652 AH",
    "sg:province":"North Brabant",
    "wof:name":"Topstart Select",
    "wof:placetype":"venue"
},
  "geometry": {"coordinates":[5.4335398674,51.4339408875],"type":"Point"}
}