{
  "type": "Feature",
  "properties": {
    "addr:full":"Leusveld 5 Ede Gld Gelderland 6715 GJ",
    "addr:housenumber":"5",
    "addr:postcode":"6715 gj",
    "addr:street":"Leusveld;Gld Gelderland",
    "iso:country":"NL",
    "sg:address":"Leusveld 5",
    "sg:city":"Ede Gld",
    "sg:orig_category":"Loodgieterswerk, Verwarming And Sanitaire Installaties",
    "sg:phone":"+31 318 636 494",
    "sg:postcode":"6715 GJ",
    "sg:province":"Gelderland",
    "wof:name":"G. Mulder Klussenbedrijf",
    "wof:placetype":"venue"
},
  "geometry": {"coordinates":[5.629911,52.04575],"type":"Point"}
}