{
  "type": "Feature",
  "properties": {
    "addr:full":"P De Hooghstr 71 Maarssen Utrecht 3601 EH",
    "addr:housenumber":"71",
    "addr:postcode":"3601 eh",
    "addr:street":"P",
    "iso:country":"NL",
    "sg:address":"P De Hooghstr 71",
    "sg:city":"Maarssen",
    "sg:orig_category":"Kinderopvang",
    "sg:phone":"+31 346 283 471",
    "sg:postcode":"3601 EH",
    "sg:province":"Utrecht",
    "sg:website":"http://www.abc-tje.nl",
    "wof:name":"Abc-Tje",
    "wof:placetype":"venue"
},
  "geometry": {"coordinates":[5.041285,52.143734],"type":"Point"}
}