{
  "type": "Feature",
  "properties": {
    "addr:full":"Nw Waterwegstr 53-55 Schiedam South Holland 3115 HE",
    "addr:housenumber":"53-55",
    "addr:postcode":"3115 he",
    "iso:country":"NL",
    "sg:address":"Nw Waterwegstr 53-55",
    "sg:city":"Schiedam",
    "sg:classifiers":[
        {
            "category":"Retail",
            "subcategory":"Storage",
            "type":"Services"
        }
    ],
    "sg:phone":"+31 10 427 1230",
    "sg:postcode":"3115 HE",
    "sg:province":"South Holland",
    "sg:tags":[
        "op-",
        "en",
        "overslagbedrijven"
    ],
    "sg:website":"http://www.nwssilo.nl",
    "wof:name":"Nieuwe Waterweg Silo Bv",
    "wof:placetype":"venue"
},
  "geometry": {"coordinates":[4.39076,51.90073],"type":"Point"}
}