{
  "type": "Feature",
  "properties": {
    "iso:country":"NL",
    "sg:address":"Laathof 24",
    "sg:city":"Ulvenhout",
    "sg:orig_category":"Administratie- En Boekhoudkantoren",
    "sg:phone":"+31 76 587 8793",
    "sg:postcode":"4851 ET",
    "sg:province":"Noord-Brabant",
    "sg:website":"http://www.bacchus-advies.nl",
    "wof:name":"Bacchus Organisatie Advies Bv",
    "wof:placetype":"venue"
},
  "geometry": {"coordinates":[4.794401,51.54805],"type":"Point"}
}