{
  "type": "Feature",
  "properties": {
    "iso:country":"NL",
    "sg:address":"Postbus 62",
    "sg:city":"Beuningen Gld",
    "sg:orig_category":"Scholen Voor Basisonderwijs",
    "sg:phone":"+31 24 677 2086",
    "sg:postcode":"6640 AB",
    "sg:province":"Gelderland",
    "wof:name":"Achtsprong Openb, De",
    "wof:placetype":"venue"
},
  "geometry": {"coordinates":[5.77018,51.861549],"type":"Point"}
}