{
  "type": "Feature",
  "properties": {
    "addr:full":"Barndegat 18 Zaandam North Holland 1505 HN",
    "addr:housenumber":"18",
    "addr:postcode":"1505 hn",
    "addr:street":"Barndegat",
    "iso:country":"NL",
    "sg:address":"Barndegat 18",
    "sg:city":"Zaandam",
    "sg:orig_category":"Goederenvervoer Over De Weg",
    "sg:phone":"+31 75 616 3329",
    "sg:postcode":"1505 HN",
    "sg:province":"North Holland",
    "wof:name":"B. De Hart",
    "wof:placetype":"venue"
},
  "geometry": {"coordinates":[4.859691,52.427738],"type":"Point"}
}