{
  "type": "Feature",
  "properties": {
    "iso:country":"NL",
    "sg:address":"Laan Van Cattenbroeck 13",
    "sg:city":"Zeist",
    "sg:orig_category":"Kappers",
    "sg:phone":"+31 30 692 5023",
    "sg:postcode":"3703 BH",
    "sg:province":"Utrecht",
    "wof:name":"Haarmode Harry Schildkamp",
    "wof:placetype":"venue"
},
  "geometry": {"coordinates":[5.2282671928,52.0788345337],"type":"Point"}
}