{
  "type": "Feature",
  "properties": {
    "addr:full":"Roelenengweg 1 Voorthuizen Gelderland 3781 BA",
    "addr:housenumber":"1",
    "addr:postcode":"3781 ba",
    "addr:street":"Roelenengweg;Gelderland",
    "iso:country":"NL",
    "sg:address":"Roelenengweg 1",
    "sg:city":"Voorthuizen",
    "sg:orig_category":"Sportclubs",
    "sg:phone":"+31 342 472 380",
    "sg:postcode":"3781 BA",
    "sg:province":"Gelderland",
    "wof:name":"Voetbalvereniging Vvop",
    "wof:placetype":"venue"
},
  "geometry": {"coordinates":[5.607845,52.188103],"type":"Point"}
}