{
  "type": "Feature",
  "properties": {
    "iso:country":"NL",
    "sg:address":"Roelenengweg 1",
    "sg:city":"Voorthuizen",
    "sg:orig_category":"Sportclubs",
    "sg:phone":"+31 342 472 380",
    "sg:postcode":"3781 BA",
    "sg:province":"Gelderland",
    "wof:name":"Voetbalvereniging Vvop",
    "wof:placetype":"venue"
},
  "geometry": {"coordinates":[5.607845,52.188103],"type":"Point"}
}