{
  "type": "Feature",
  "properties": {
    "addr:full":"Herenwg 54 Zwolle Overijssel 8023 DB",
    "addr:housenumber":"54",
    "addr:postcode":"8023 db",
    "addr:street":"Herenwg",
    "iso:country":"NL",
    "sg:address":"Herenwg 54",
    "sg:city":"Zwolle",
    "sg:orig_category":"Kappers",
    "sg:phone":"+31 38 455 0022",
    "sg:postcode":"8023 DB",
    "sg:province":"Overijssel",
    "wof:name":"Carla",
    "wof:placetype":"venue"
},
  "geometry": {"coordinates":[6.1169228554,52.5115470886],"type":"Point"}
}