{
  "type": "Feature",
  "properties": {
    "addr:full":"Leenderweg 39 Valkenswaard Noord-Brabant 5554 CK",
    "addr:housenumber":"39",
    "addr:postcode":"5554 ck",
    "addr:street":"Leenderweg",
    "iso:country":"NL",
    "sg:address":"Leenderweg 39",
    "sg:city":"Valkenswaard",
    "sg:orig_category":"Schoenen",
    "sg:phone":"+31 40 201 2756",
    "sg:postcode":"5554 CK",
    "sg:province":"Noord-Brabant",
    "wof:name":"J. Roosen",
    "wof:placetype":"venue"
},
  "geometry": {"coordinates":[5.464051,51.351879],"type":"Point"}
}