{
  "type": "Feature",
  "properties": {
    "addr:full":"Franekereind 1 Harlingen Friesland 8861 AA",
    "addr:housenumber":"1",
    "addr:postcode":"8861 aa",
    "addr:street":"Franekereind",
    "iso:country":"NL",
    "sg:address":"Franekereind 1",
    "sg:city":"Harlingen",
    "sg:orig_category":"Artsen - Huisartsen",
    "sg:phone":"+31 517 416 565",
    "sg:postcode":"8861 AA",
    "sg:province":"Friesland",
    "wof:name":"Blok, C G H",
    "wof:placetype":"venue"
},
  "geometry": {"coordinates":[5.421907,53.174732],"type":"Point"}
}