{
  "type": "Feature",
  "properties": {
    "addr:full":"Bloemerstraat 88 Nijmegen Gelderland 6511 EM",
    "addr:housenumber":"88",
    "addr:postcode":"6511 em",
    "addr:street":"Bloemerstraat;Gelderland",
    "iso:country":"NL",
    "sg:address":"Bloemerstraat 88",
    "sg:city":"Nijmegen",
    "sg:orig_category":"Glaszetten",
    "sg:phone":"+31 24 322 5563",
    "sg:postcode":"6511 EM",
    "sg:province":"Gelderland",
    "wof:name":"Glashandel A. Van Haagen",
    "wof:placetype":"venue"
},
  "geometry": {"coordinates":[5.861296,51.845444],"type":"Point"}
}