{
  "type": "Feature",
  "properties": {
    "addr:full":"Evenaar 8 Rotterdam Zuid-Holland 3067 DA",
    "addr:housenumber":"8",
    "addr:postcode":"3067 da",
    "addr:street":"Evenaar",
    "iso:country":"NL",
    "sg:address":"Evenaar 8",
    "sg:city":"Rotterdam",
    "sg:orig_category":"Overheidsdiensten",
    "sg:phone":"+31 10 450 2245",
    "sg:postcode":"3067 DA",
    "sg:province":"Zuid-Holland",
    "wof:name":"Eindpunt",
    "wof:placetype":"venue"
},
  "geometry": {"coordinates":[4.5675210953,51.9469070435],"type":"Point"}
}