{
  "type": "Feature",
  "properties": {
    "iso:country":"NL",
    "sg:address":"V Oldenbarnev Ln 10",
    "sg:city":"Amersfoort",
    "sg:orig_category":"Verenigingen En Stichtingen",
    "sg:phone":"+31 33 461 1949",
    "sg:postcode":"3818 HB",
    "sg:province":"Utrecht",
    "wof:name":"Herv Bond Voor Inwendige Zending",
    "wof:placetype":"venue"
},
  "geometry": {"coordinates":[5.386085,52.152325],"type":"Point"}
}