{
  "type": "Feature",
  "properties": {
    "iso:country":"NL",
    "sg:address":"Vlettevaart 8",
    "sg:city":"Tilburg",
    "sg:orig_category":"Marktonderzoekbureaus",
    "sg:phone":"+31 13 468 2070",
    "sg:postcode":"5032 BM",
    "sg:province":"Noord-Brabant",
    "wof:name":"Amm Adviesburo Marketing Management Drs.",
    "wof:placetype":"venue"
},
  "geometry": {"coordinates":[5.035393,51.545406],"type":"Point"}
}