{
  "type": "Feature",
  "properties": {
    "iso:country":"NL",
    "sg:address":"Amsteldk 137",
    "sg:city":"Amsterdam",
    "sg:classifiers":[
        {
            "category":"Fast Food",
            "type":"Food & Drink"
        }
    ],
    "sg:phone":"+31 20 644 8623",
    "sg:postcode":"1079 LE",
    "sg:province":"Noord-Holland",
    "sg:tags":[
        "afhaal",
        "restaurant"
    ],
    "wof:name":"Victoria",
    "wof:placetype":"venue"
},
  "geometry": {"coordinates":[4.911112,52.346718],"type":"Point"}
}