{
  "type": "Feature",
  "properties": {
    "iso:country":"NL",
    "sg:address":"Wayesteinsngl 23",
    "sg:city":"Nieuw Vennep",
    "sg:orig_category":"Verzekeringen - Verzekeringskantoren",
    "sg:phone":"+31 252 681 720",
    "sg:postcode":"2151 KR",
    "sg:province":"North Holland",
    "sg:website":"http://www.kelkerk.nl",
    "wof:name":"Kellendonk & Kerkhoven",
    "wof:placetype":"venue"
},
  "geometry": {"coordinates":[4.611451,52.274563],"type":"Point"}
}