{
  "type": "Feature",
  "properties": {
    "addr:full":"Past De Katerstr 7 Baarle Nassau Noord-Brabant 5111 CM",
    "addr:housenumber":"7",
    "addr:postcode":"5111 cm",
    "addr:street":"Past;Katerstr",
    "iso:country":"NL",
    "sg:address":"Past De Katerstr 7",
    "sg:city":"Baarle Nassau",
    "sg:orig_category":"Bibliotheken En Leeszalen Openbare",
    "sg:phone":"+31 13 507 8351",
    "sg:postcode":"5111 CM",
    "sg:province":"Noord-Brabant",
    "wof:name":"Openb Bibliotheek",
    "wof:placetype":"venue"
},
  "geometry": {"coordinates":[4.9270348549,51.4416809082],"type":"Point"}
}