{
  "type": "Feature",
  "properties": {
    "addr:full":"Rembrandt Van Rijnstraat 34 Oisterwijk Noord-Brabant 5062 LM",
    "addr:housenumber":"34",
    "addr:postcode":"5062 lm",
    "addr:street":"Rembrandt Van Rijnstraat",
    "iso:country":"NL",
    "sg:address":"Rembrandt Van Rijnstraat 34",
    "sg:city":"Oisterwijk",
    "sg:orig_category":"Juridische Dienstverlening",
    "sg:phone":"+31 13 528 2004",
    "sg:postcode":"5062 LM",
    "sg:province":"Noord-Brabant",
    "wof:name":"Adviesbureau Mr. S.L.M. Van Haaren",
    "wof:placetype":"venue"
},
  "geometry": {"coordinates":[5.185602,51.57283],"type":"Point"}
}