{
  "type": "Feature",
  "properties": {
    "addr:full":"Harkulo 28 Rotterdam Zuid-Holland 3085 MJ",
    "addr:housenumber":"28",
    "addr:postcode":"3085 mj",
    "addr:street":"Harkulo",
    "iso:country":"NL",
    "sg:address":"Harkulo 28",
    "sg:city":"Rotterdam",
    "sg:orig_category":"Haarwerken",
    "sg:phone":"+31 10 480 2778",
    "sg:postcode":"3085 MJ",
    "sg:province":"Zuid-Holland",
    "wof:name":"Haarboetiek Zuid",
    "wof:placetype":"venue"
},
  "geometry": {"coordinates":[4.482679,51.874504],"type":"Point"}
}