{
  "type": "Feature",
  "properties": {
    "addr:full":"Singellaan 65 Heiligerlee Groningen 9677 RP",
    "addr:housenumber":"65",
    "addr:postcode":"9677 rp",
    "addr:street":"Singellaan",
    "iso:country":"NL",
    "sg:address":"Singellaan 65",
    "sg:city":"Heiligerlee",
    "sg:orig_category":"Boekhouders",
    "sg:phone":"+31 597 416 234",
    "sg:postcode":"9677 RP",
    "sg:province":"Groningen",
    "wof:name":"Administratiekantoor En Inkassoburo P. Kuiper",
    "wof:placetype":"venue"
},
  "geometry": {"coordinates":[7.005246,53.157799],"type":"Point"}
}