{
  "type": "Feature",
  "properties": {
    "addr:full":"Norritstraat 1A Noordhorn Groningen 9804 RG",
    "addr:housenumber":"1a",
    "addr:postcode":"9804 rg",
    "addr:street":"Norritstraat",
    "iso:country":"NL",
    "sg:address":"Norritstraat 1A",
    "sg:city":"Noordhorn",
    "sg:classifiers":[
        {
            "category":"Travel",
            "subcategory":"Hotels & Motels",
            "type":"Entertainment"
        }
    ],
    "sg:phone":"+31 594 502 698",
    "sg:postcode":"9804 RG",
    "sg:province":"Groningen",
    "wof:name":"Familie Van Leijsen",
    "wof:placetype":"venue"
},
  "geometry": {"coordinates":[6.394953,53.26408],"type":"Point"}
}