{
  "type": "Feature",
  "properties": {
    "addr:full":"Provincialewg O 18 Haastrecht Zuid-Holland 2851 AE",
    "addr:housenumber":"18",
    "addr:postcode":"2851 ae",
    "iso:country":"NL",
    "sg:address":"Provincialewg O 18",
    "sg:city":"Haastrecht",
    "sg:orig_category":"Poeliers",
    "sg:phone":"+31 348 562 105",
    "sg:postcode":"2851 AE",
    "sg:province":"Zuid-Holland",
    "wof:name":"Vermeulen, J",
    "wof:placetype":"venue"
},
  "geometry": {"coordinates":[4.832872,52.015236],"type":"Point"}
}