{
  "type": "Feature",
  "properties": {
    "addr:full":"Wilhelminastr 17 Panningen Limburg 5981 XW",
    "addr:housenumber":"17",
    "addr:postcode":"5981 xw",
    "addr:street":"Wilhelminastr",
    "iso:country":"NL",
    "sg:address":"Wilhelminastr 17",
    "sg:city":"Panningen",
    "sg:orig_category":"Drukkerijen",
    "sg:phone":"+31 77 306 6888",
    "sg:postcode":"5981 XW",
    "sg:province":"Limburg",
    "wof:name":"Holbox Offset Bv",
    "wof:placetype":"venue"
},
  "geometry": {"coordinates":[5.979851,51.333714],"type":"Point"}
}