{
  "type": "Feature",
  "properties": {
    "addr:full":"Kompas 13 Veenendaal Utrecht 3904 PN",
    "addr:housenumber":"13",
    "addr:postcode":"3904 pn",
    "addr:street":"Kompas",
    "iso:country":"NL",
    "sg:address":"Kompas 13",
    "sg:city":"Veenendaal",
    "sg:orig_category":"Organisatiebureaus",
    "sg:phone":"+31 318 540 694",
    "sg:postcode":"3904 PN",
    "sg:province":"Utrecht",
    "wof:name":"Bouwmeester, Hans",
    "wof:placetype":"venue"
},
  "geometry": {"coordinates":[5.5286011696,52.0217781067],"type":"Point"}
}