{
  "type": "Feature",
  "properties": {
    "addr:full":"Haarwg 22 Tiendeveen Drenthe 7936 TP",
    "addr:housenumber":"22",
    "addr:postcode":"7936 tp",
    "addr:street":"Haarwg",
    "iso:country":"NL",
    "sg:address":"Haarwg 22",
    "sg:city":"Tiendeveen",
    "sg:classifiers":[
        {
            "category":"Travel",
            "subcategory":"Hotels & Motels",
            "type":"Entertainment"
        }
    ],
    "sg:phone":"+31 528 331 380",
    "sg:postcode":"7936 TP",
    "sg:province":"Drenthe",
    "wof:name":"Martensplek",
    "wof:placetype":"venue"
},
  "geometry": {"coordinates":[6.564269,52.761333],"type":"Point"}
}