{
  "type": "Feature",
  "properties": {
    "addr:full":"Berkenstr 7 Winkel Noord-Holland 1731 SW",
    "addr:housenumber":"7",
    "addr:postcode":"1731 sw",
    "addr:street":"Berkenstr",
    "iso:country":"NL",
    "sg:address":"Berkenstr 7",
    "sg:city":"Winkel",
    "sg:orig_category":"Verenigingen En Stichtingen",
    "sg:phone":"+31 224 542 776",
    "sg:postcode":"1731 SW",
    "sg:province":"Noord-Holland",
    "wof:name":"Dorstige Biet, De",
    "wof:placetype":"venue"
},
  "geometry": {"coordinates":[-110.788887,33.006603],"type":"Point"}
}