{
  "type": "Feature",
  "properties": {
    "addr:full":"Locht 42 Kerkrade Limburg 6466 GW",
    "addr:housenumber":"42",
    "addr:postcode":"6466 gw",
    "addr:street":"Locht",
    "iso:country":"NL",
    "sg:address":"Locht 42",
    "sg:city":"Kerkrade",
    "sg:orig_category":"Goederenvervoer Over De Weg",
    "sg:phone":"+31 45 541 1063",
    "sg:postcode":"6466 GW",
    "sg:province":"Limburg",
    "wof:name":"Frits Nollgen Transportbedrijf Bv",
    "wof:placetype":"venue"
},
  "geometry": {"coordinates":[6.010216,50.856476],"type":"Point"}
}