{
  "type": "Feature",
  "properties": {
    "addr:full":"J Thyssenstr 32 Nederasselt Gelderland 6612 BA",
    "addr:housenumber":"32",
    "addr:postcode":"6612 ba",
    "addr:street":"Gelderland",
    "iso:country":"NL",
    "sg:address":"J Thyssenstr 32",
    "sg:city":"Nederasselt",
    "sg:orig_category":"Gordijnenateliers",
    "sg:phone":"+31 24 622 1596",
    "sg:postcode":"6612 BA",
    "sg:province":"Gelderland",
    "wof:name":"Lima",
    "wof:placetype":"venue"
},
  "geometry": {"coordinates":[5.747158,51.771778],"type":"Point"}
}