{
  "type": "Feature",
  "properties": {
    "addr:full":"Van Hoornestraat 15 Gorinchem Zuid-Holland 4206 XC",
    "addr:housenumber":"15",
    "addr:postcode":"4206 xc",
    "addr:street":"Van Hoornestraat",
    "iso:country":"NL",
    "sg:address":"Van Hoornestraat 15",
    "sg:city":"Gorinchem",
    "sg:orig_category":"Verlichting And Huishoudartikelen",
    "sg:phone":"+31 183 632 654",
    "sg:postcode":"4206 XC",
    "sg:province":"Zuid-Holland",
    "wof:name":"Van Der Ree",
    "wof:placetype":"venue"
},
  "geometry": {"coordinates":[4.983196,51.841061],"type":"Point"}
}