{
  "type": "Feature",
  "properties": {
    "addr:full":"Waterloweg 58 Ede Gld Gelderland 6713 AT",
    "addr:housenumber":"58",
    "addr:postcode":"6713",
    "addr:street":"Waterloweg;Gld Gelderland",
    "iso:country":"NL",
    "sg:address":"Waterloweg 58",
    "sg:city":"Ede Gld",
    "sg:orig_category":"Goederenvervoer Over De Weg",
    "sg:phone":"+31 318 615 575",
    "sg:postcode":"6713 AT",
    "sg:province":"Gelderland",
    "wof:name":"Sneldienst Ede",
    "wof:placetype":"venue"
},
  "geometry": {"coordinates":[5.662774,52.04266],"type":"Point"}
}