{
  "type": "Feature",
  "properties": {
    "addr:full":"Einsteinstr 95 Kudelstaart Noord-Holland 1433 KJ",
    "addr:housenumber":"95",
    "addr:postcode":"1433 kj",
    "addr:street":"Einsteinstr",
    "iso:country":"NL",
    "sg:address":"Einsteinstr 95",
    "sg:city":"Kudelstaart",
    "sg:orig_category":"Apotheken",
    "sg:phone":"+31 297 327 036",
    "sg:postcode":"1433 KJ",
    "sg:province":"Noord-Holland",
    "wof:name":"Groen",
    "wof:placetype":"venue"
},
  "geometry": {"coordinates":[4.749566,52.234783],"type":"Point"}
}