{
  "type": "Feature",
  "properties": {
    "iso:country":"NL",
    "sg:address":"De Coubertinln 29",
    "sg:city":"Waalwyk",
    "sg:orig_category":"Loodgieters",
    "sg:phone":"+31 416 343 651",
    "sg:postcode":"5143 AB",
    "sg:province":"Noord-Brabant",
    "wof:name":"Klusbus",
    "wof:placetype":"venue"
},
  "geometry": {"coordinates":[5.079889,51.68401],"type":"Point"}
}