{
  "type": "Feature",
  "properties": {
    "addr:full":"Gerard Douplantsoen 24 Voorschoten Zuid-Holland 2251 GN",
    "addr:housenumber":"24",
    "addr:postcode":"2251 gn",
    "addr:street":"Gerard Douplantsoen",
    "iso:country":"NL",
    "sg:address":"Gerard Douplantsoen 24",
    "sg:city":"Voorschoten",
    "sg:orig_category":"Verzekeringen",
    "sg:phone":"+31 71 561 5987",
    "sg:postcode":"2251 GN",
    "sg:province":"Zuid-Holland",
    "wof:name":"Koopmans Assurantien",
    "wof:placetype":"venue"
},
  "geometry": {"coordinates":[4.454439,52.123653],"type":"Point"}
}