{
  "type": "Feature",
  "properties": {
    "addr:full":"Stationsstr 39 Deurne Noord-Brabant 5751 HB",
    "addr:housenumber":"39",
    "addr:postcode":"5751 hb",
    "addr:street":"Stationsstr",
    "iso:country":"NL",
    "sg:address":"Stationsstr 39",
    "sg:city":"Deurne",
    "sg:orig_category":"Warenhuizen",
    "sg:phone":"+31 493 314 146",
    "sg:postcode":"5751 HB",
    "sg:province":"Noord-Brabant",
    "wof:name":"Hema",
    "wof:placetype":"venue"
},
  "geometry": {"coordinates":[5.7923288345,51.461681366],"type":"Point"}
}