{
  "type": "Feature",
  "properties": {
    "addr:full":"De Limiet 15 Vianen Zh South Holland 4131 NR",
    "addr:housenumber":"15",
    "addr:postcode":"zh;4131 nr",
    "addr:street":"De Limiet",
    "iso:country":"NL",
    "sg:address":"De Limiet 15",
    "sg:city":"Vianen Zh",
    "sg:orig_category":"Verenigingen En Stichtingen",
    "sg:phone":"+31 347 329 804",
    "sg:postcode":"4131 NR",
    "sg:province":"South Holland",
    "wof:name":"Dak En Milieu, Sticht",
    "wof:placetype":"venue"
},
  "geometry": {"coordinates":[5.091063,51.977867],"type":"Point"}
}