{
  "type": "Feature",
  "properties": {
    "addr:full":"Zonnebaars 3 Krommenie North Holland 1562 KC",
    "addr:housenumber":"3",
    "addr:postcode":"1562 kc",
    "addr:street":"Zonnebaars",
    "iso:country":"NL",
    "sg:address":"Zonnebaars 3",
    "sg:city":"Krommenie",
    "sg:orig_category":"Pensioenen",
    "sg:phone":"+31 75 622 6935",
    "sg:postcode":"1562 KC",
    "sg:province":"North Holland",
    "wof:name":"Ico",
    "wof:placetype":"venue"
},
  "geometry": {"coordinates":[4.771065,52.508385],"type":"Point"}
}