{
  "type": "Feature",
  "properties": {
    "iso:country":"NL",
    "sg:address":"Provincialewg 96",
    "sg:city":"Oosteind",
    "sg:orig_category":"Verenigingsgebouwen",
    "sg:phone":"+31 162 456 037",
    "sg:postcode":"4909 AL",
    "sg:province":"North Brabant",
    "wof:name":"Oostquartier",
    "wof:placetype":"venue"
},
  "geometry": {"coordinates":[4.902924,51.646259],"type":"Point"}
}