{
  "type": "Feature",
  "properties": {
    "iso:country":"NL",
    "sg:address":"Minervum 1614",
    "sg:city":"Breda",
    "sg:orig_category":"Kantoorartikelen",
    "sg:phone":"+31 76 560 1034",
    "sg:postcode":"4817 ZL",
    "sg:province":"Noord-Brabant",
    "wof:name":"Rsl Europe Audio & Light Bv",
    "wof:placetype":"venue"
},
  "geometry": {"coordinates":[4.82791996,51.583820343],"type":"Point"}
}