{
  "type": "Feature",
  "properties": {
    "addr:full":"Arnhemsewg 146 Apeldoorn Gelderland 7335 DN",
    "addr:housenumber":"146",
    "addr:postcode":"7335 dn",
    "addr:street":"Gelderland",
    "iso:country":"NL",
    "sg:address":"Arnhemsewg 146",
    "sg:city":"Apeldoorn",
    "sg:orig_category":"Kappers",
    "sg:phone":"+31 55 533 5023",
    "sg:postcode":"7335 DN",
    "sg:province":"Gelderland",
    "wof:name":"Kapperij, De",
    "wof:placetype":"venue"
},
  "geometry": {"coordinates":[5.9591999054,52.2003707886],"type":"Point"}
}