{
  "type": "Feature",
  "properties": {
    "addr:full":"T Hoefje 23 Bruinisse Zeeland 4311 EX",
    "addr:housenumber":"23",
    "addr:postcode":"4311 ex",
    "addr:street":"T Hoefje",
    "iso:country":"NL",
    "sg:address":"T Hoefje 23",
    "sg:city":"Bruinisse",
    "sg:orig_category":"Binnenhuisarchitecten",
    "sg:phone":"+31 111 482 569",
    "sg:postcode":"4311 EX",
    "sg:province":"Zeeland",
    "wof:name":"Ton Heeg Studio Voor Binnenhuisarchitect",
    "wof:placetype":"venue"
},
  "geometry": {"coordinates":[4.087216,51.66058],"type":"Point"}
}