{
  "type": "Feature",
  "properties": {
    "addr:full":"Amer 1 Brielle Zuid-Holland 3232 HA",
    "addr:housenumber":"1",
    "addr:postcode":"3232 ha",
    "addr:street":"Amer",
    "iso:country":"NL",
    "sg:address":"Amer 1",
    "sg:city":"Brielle",
    "sg:classifiers":[
        {
            "category":"Travel",
            "subcategory":"Hotels & Motels",
            "type":"Entertainment"
        }
    ],
    "sg:phone":"+31 181 416 588",
    "sg:postcode":"3232 HA",
    "sg:province":"Zuid-Holland",
    "wof:name":"Bastion Hotel",
    "wof:placetype":"venue"
},
  "geometry": {"coordinates":[4.1713957787,51.8985595703],"type":"Point"}
}