{
  "type": "Feature",
  "properties": {
    "iso:country":"NL",
    "sg:address":"Postbus 294",
    "sg:city":"Maarssen",
    "sg:orig_category":"Postzegels",
    "sg:phone":"+31 346 550 618",
    "sg:postcode":"3600 AG",
    "sg:province":"Utrecht",
    "wof:name":"Lodewijk",
    "wof:placetype":"venue"
},
  "geometry": {"coordinates":[5.040446,52.142956],"type":"Point"}
}