{
  "type": "Feature",
  "properties": {
    "iso:country":"NL",
    "sg:address":"Grotestraat 32",
    "sg:city":"Venray",
    "sg:orig_category":"Herenmodezaken",
    "sg:phone":"+31 478 586 387",
    "sg:postcode":"5801 BH",
    "sg:province":"Limburg",
    "wof:name":"Corridor Herenmode",
    "wof:placetype":"venue"
},
  "geometry": {"coordinates":[5.975482,51.526005],"type":"Point"}
}