{
  "type": "Feature",
  "properties": {
    "iso:country":"NL",
    "sg:address":"Melkweg 42",
    "sg:city":"Laren Nh",
    "sg:classifiers":[
        {
            "category":"Education",
            "subcategory":"Preschool",
            "type":"Public Place"
        }
    ],
    "sg:phone":"+31 35 533 4355",
    "sg:postcode":"1251 PT",
    "sg:province":"Noord-Holland",
    "sg:tags":[
        "kleuteronderwijs",
        "basis-"
    ],
    "wof:name":"Openbare Basisschool De Ploeg",
    "wof:placetype":"venue"
},
  "geometry": {"coordinates":[5.235588,52.252426],"type":"Point"}
}