{
  "type": "Feature",
  "properties": {
    "addr:full":"Terp 23 Wommels Friesland 8731 AX",
    "addr:housenumber":"23",
    "addr:postcode":"8731 ax",
    "addr:street":"Terp",
    "iso:country":"NL",
    "sg:address":"Terp 23",
    "sg:city":"Wommels",
    "sg:orig_category":"Kappers",
    "sg:phone":"+31 515 331 303",
    "sg:postcode":"8731 AX",
    "sg:province":"Friesland",
    "wof:name":"Boschma",
    "wof:placetype":"venue"
},
  "geometry": {"coordinates":[5.587430954,53.1082115173],"type":"Point"}
}