{
  "type": "Feature",
  "properties": {
    "iso:country":"NL",
    "sg:address":"Terp 23",
    "sg:city":"Wommels",
    "sg:orig_category":"Kappers",
    "sg:phone":"+31 515 331 303",
    "sg:postcode":"8731 AX",
    "sg:province":"Friesland",
    "wof:name":"Boschma",
    "wof:placetype":"venue"
},
  "geometry": {"coordinates":[5.587430954,53.1082115173],"type":"Point"}
}