{
  "type": "Feature",
  "properties": {
    "iso:country":"NL",
    "sg:address":"Breestr 2",
    "sg:city":"Hoorn",
    "sg:orig_category":"Fietsen En Bromfietsen",
    "sg:phone":"+31 229 216 666",
    "sg:postcode":"1621 CG",
    "sg:province":"Noord-Holland",
    "wof:name":"Trukee",
    "wof:placetype":"venue"
},
  "geometry": {"coordinates":[5.061324,52.640175],"type":"Point"}
}