{
  "type": "Feature",
  "properties": {
    "addr:full":"V Cittersstr 22A Rotterdam Zuid-Holland 3022 LK",
    "addr:housenumber":"22a",
    "addr:postcode":"3022 lk",
    "iso:country":"NL",
    "sg:address":"V Cittersstr 22A",
    "sg:city":"Rotterdam",
    "sg:orig_category":"Verenigingen En Stichtingen",
    "sg:phone":"+31 10 476 0148",
    "sg:postcode":"3022 LK",
    "sg:province":"Zuid-Holland",
    "wof:name":"Adam En Eva, Sticht 40-60+ Van",
    "wof:placetype":"venue"
},
  "geometry": {"coordinates":[4.4463,51.919788],"type":"Point"}
}