{
  "type": "Feature",
  "properties": {
    "addr:full":"Hoge Gouwe 89 Gouda Zuid-Holland 2801 LD",
    "addr:housenumber":"89",
    "addr:postcode":"2801 ld",
    "addr:street":"Hoge Gouwe",
    "iso:country":"NL",
    "sg:address":"Hoge Gouwe 89",
    "sg:city":"Gouda",
    "sg:orig_category":"Fietshandelaren",
    "sg:phone":"+31 182 513 630",
    "sg:postcode":"2801 LD",
    "sg:province":"Zuid-Holland",
    "wof:name":"L. Van Oel En Zoon",
    "wof:placetype":"venue"
},
  "geometry": {"coordinates":[4.70688,52.009724],"type":"Point"}
}