{
  "type": "Feature",
  "properties": {
    "addr:full":"Polderln 19-21 Rotterdam Zuid-Holland 3074 MA",
    "addr:housenumber":"19-21",
    "addr:postcode":"rotterdam;3074 ma",
    "iso:country":"NL",
    "sg:address":"Polderln 19-21",
    "sg:city":"Rotterdam",
    "sg:orig_category":"Fietsen En Bromfietsen",
    "sg:phone":"+31 10 484 7887",
    "sg:postcode":"3074 MA",
    "sg:province":"Zuid-Holland",
    "wof:name":"Horst Rijwielhandel Zuid, A Van Der",
    "wof:placetype":"venue"
},
  "geometry": {"coordinates":[4.51149,51.89608],"type":"Point"}
}