{
  "type": "Feature",
  "properties": {
    "iso:country":"NL",
    "sg:address":"Zijdstraat 70",
    "sg:city":"Aalsmeer",
    "sg:classifiers":[
        {
            "category":"Food & Beverages",
            "subcategory":"Fruits & Vegetables",
            "type":"Retail Goods"
        }
    ],
    "sg:phone":"+31 297 324 488",
    "sg:postcode":"1431 EE",
    "sg:province":"Noord-Holland",
    "sg:tags":[
        "groenten"
    ],
    "wof:name":"Firma Gebr. Kreike",
    "wof:placetype":"venue"
},
  "geometry": {"coordinates":[4.747922,52.267487],"type":"Point"}
}