{
  "type": "Feature",
  "properties": {
    "iso:country":"NL",
    "sg:address":"Bylwerffstr 1",
    "sg:city":"Rotterdam",
    "sg:orig_category":"Kappers",
    "sg:phone":"+31 10 265 2306",
    "sg:postcode":"3039 VD",
    "sg:province":"Zuid-Holland",
    "wof:name":"Kappertje, 'T",
    "wof:placetype":"venue"
},
  "geometry": {"coordinates":[4.4581990242,51.9329109192],"type":"Point"}
}