{
  "type": "Feature",
  "properties": {
    "iso:country":"NL",
    "sg:address":"Oude Binnenwg 103",
    "sg:city":"Rotterdam",
    "sg:orig_category":"Broodjeszaken",
    "sg:phone":"+31 10 433 4933",
    "sg:postcode":"3012 JB",
    "sg:province":"Zuid-Holland",
    "wof:name":"Dicle",
    "wof:placetype":"venue"
},
  "geometry": {"coordinates":[4.47491,51.917652],"type":"Point"}
}