{
  "type": "Feature",
  "properties": {
    "addr:full":"De Vredenburg 20 Strijen Zuid-Holland 3291 GC",
    "addr:housenumber":"20",
    "addr:postcode":"3291 gc",
    "addr:street":"De Vredenburg",
    "iso:country":"NL",
    "sg:address":"De Vredenburg 20",
    "sg:city":"Strijen",
    "sg:orig_category":"Fotostudio'S And Fotografen",
    "sg:phone":"+31 78 674 4201",
    "sg:postcode":"3291 GC",
    "sg:province":"Zuid-Holland",
    "wof:name":"Fotografie Martin Kwakernaat",
    "wof:placetype":"venue"
},
  "geometry": {"coordinates":[4.555446,51.738129],"type":"Point"}
}