{
  "type": "Feature",
  "properties": {
    "addr:full":"Nieuwstr 7C Eindhoven Noord-Brabant 5611 DA",
    "addr:housenumber":"7c",
    "addr:postcode":"5611 da",
    "addr:street":"Nieuwstr",
    "iso:country":"NL",
    "sg:address":"Nieuwstr 7C",
    "sg:city":"Eindhoven",
    "sg:orig_category":"Boeken En Tijdschriften",
    "sg:phone":"+31 40 296 3299",
    "sg:postcode":"5611 DA",
    "sg:province":"Noord-Brabant",
    "sg:website":"http://www.stripwinkelatomik.nl",
    "wof:name":"Atomik",
    "wof:placetype":"venue"
},
  "geometry": {"coordinates":[5.484105,51.434471],"type":"Point"}
}