{
  "type": "Feature",
  "properties": {
    "addr:full":"Paulus Buijsstraat 52 'S-Gravenhage Zuid-Holland 2582 CK",
    "addr:housenumber":"52",
    "addr:postcode":"s-gravenhage;2582 ck",
    "addr:street":"Paulus Buijsstraat",
    "iso:country":"NL",
    "sg:address":"Paulus Buijsstraat 52",
    "sg:city":"'S-Gravenhage",
    "sg:orig_category":"Adviesbureaus",
    "sg:phone":"+31 70 352 2632",
    "sg:postcode":"2582 CK",
    "sg:province":"Zuid-Holland",
    "wof:name":"Ivm",
    "wof:placetype":"venue"
},
  "geometry": {"coordinates":[4.27747,52.096085],"type":"Point"}
}