{
  "type": "Feature",
  "properties": {
    "addr:full":"V Wischstr 38 Terborg Gelderland 7061 ZZ",
    "addr:housenumber":"38",
    "addr:postcode":"7061 zz",
    "addr:street":"Gelderland",
    "iso:country":"NL",
    "sg:address":"V Wischstr 38",
    "sg:city":"Terborg",
    "sg:orig_category":"Fotoreportages",
    "sg:phone":"+31 315 329 838",
    "sg:postcode":"7061 ZZ",
    "sg:province":"Gelderland",
    "wof:name":"Colour Art",
    "wof:placetype":"venue"
},
  "geometry": {"coordinates":[6.364855,51.919666],"type":"Point"}
}