{
  "type": "Feature",
  "properties": {
    "addr:full":"Haaswykwg O 69A Dordrecht Zuid-Holland 3319 GB",
    "addr:housenumber":"69a",
    "addr:postcode":"3319 gb",
    "addr:street":"O",
    "iso:country":"NL",
    "sg:address":"Haaswykwg O 69A",
    "sg:city":"Dordrecht",
    "sg:orig_category":"Ziekenhuizen, Sanatoria, Verpleeghuizen",
    "sg:phone":"+31 78 622 0000",
    "sg:postcode":"3319 GB",
    "sg:province":"Zuid-Holland",
    "sg:website":"http://www.hetparkhuis.nl",
    "wof:name":"Parkhuis, Verpleeghuis Het",
    "wof:placetype":"venue"
},
  "geometry": {"coordinates":[4.712283,51.796104],"type":"Point"}
}