{
  "type": "Feature",
  "properties": {
    "addr:full":"Spaarnestr 4 S Gravenhage Zuid-Holland 2515 VN",
    "addr:housenumber":"4;gravenhage",
    "addr:postcode":"2515 vn",
    "addr:street":"Spaarnestr;S",
    "iso:country":"NL",
    "sg:address":"Spaarnestr 4",
    "sg:city":"S Gravenhage",
    "sg:orig_category":"Kopieerservice",
    "sg:phone":"+31 70 381 7702",
    "sg:postcode":"2515 VN",
    "sg:province":"Zuid-Holland",
    "sg:website":"http://www.colorworks.nl",
    "wof:name":"Color Works",
    "wof:placetype":"venue"
},
  "geometry": {"coordinates":[4.31741,52.083988],"type":"Point"}
}