{
  "type": "Feature",
  "properties": {
    "iso:country":"NL",
    "sg:address":"Beatrixstr 64",
    "sg:city":"Oldenzaal",
    "sg:orig_category":"Bejaarden - Verzorgingstehuizen",
    "sg:phone":"+31 541 513 274",
    "sg:postcode":"7573 AB",
    "sg:province":"NL.08",
    "wof:name":"Zorgfederatie Oldenzaal",
    "wof:placetype":"venue"
},
  "geometry": {"coordinates":[6.928936,52.308754],"type":"Point"}
}