{
  "type": "Feature",
  "properties": {
    "iso:country":"NL",
    "sg:address":"K P Vd Mandeleln 84",
    "sg:city":"Rotterdam",
    "sg:classifiers":[
        {
            "category":"Professional",
            "subcategory":"Accounting & Tax Preparation",
            "type":"Services"
        }
    ],
    "sg:phone":"+31 10 242 5777",
    "sg:postcode":"3062 MB",
    "sg:province":"South Holland",
    "sg:tags":[
        "accountant",
        "en",
        "-kantoren",
        "register-"
    ],
    "wof:name":"Jonker Jo?ll Bv",
    "wof:placetype":"venue"
},
  "geometry": {"coordinates":[4.51759,51.931339],"type":"Point"}
}