{
  "type": "Feature",
  "properties": {
    "addr:full":"Hg Zyde 48 Bavel North Brabant 4854 AJ",
    "addr:housenumber":"48",
    "addr:postcode":"4854 aj",
    "iso:country":"NL",
    "sg:address":"Hg Zyde 48",
    "sg:city":"Bavel",
    "sg:orig_category":"Onroerende Goederen",
    "sg:phone":"+31 161 432 677",
    "sg:postcode":"4854 AJ",
    "sg:province":"North Brabant",
    "wof:name":"Putten, Van",
    "wof:placetype":"venue"
},
  "geometry": {"coordinates":[4.829695,51.565334],"type":"Point"}
}