{
  "type": "Feature",
  "properties": {
    "addr:full":"Aalsmeerderweg 45 Aalsmeer Noord-Holland 1432 CG",
    "addr:housenumber":"45",
    "addr:postcode":"1432 cg",
    "addr:street":"Aalsmeerderweg",
    "iso:country":"NL",
    "sg:address":"Aalsmeerderweg 45",
    "sg:city":"Aalsmeer",
    "sg:orig_category":"Bloemen And Planten",
    "sg:phone":"+31 20 345 6306",
    "sg:postcode":"1432 CG",
    "sg:province":"Noord-Holland",
    "wof:name":"H.J. En C. Van Leeuwen Bv",
    "wof:placetype":"venue"
},
  "geometry": {"coordinates":[4.774457,52.272614],"type":"Point"}
}