{
  "type": "Feature",
  "properties": {
    "addr:full":"Overblaak 108 Rotterdam Zuid-Holland 3011 MH",
    "addr:housenumber":"108",
    "addr:postcode":"3011 mh",
    "addr:street":"Overblaak",
    "iso:country":"NL",
    "sg:address":"Overblaak 108",
    "sg:city":"Rotterdam",
    "sg:orig_category":"Bedrijfsopleidingen",
    "sg:phone":"+31 10 412 4009",
    "sg:postcode":"3011 MH",
    "sg:province":"Zuid-Holland",
    "wof:name":"Verhoeven & Bocklandt",
    "wof:placetype":"venue"
},
  "geometry": {"coordinates":[4.489177,51.920544],"type":"Point"}
}