{
  "type": "Feature",
  "properties": {
    "iso:country":"NL",
    "sg:address":"Beurtschipper 20",
    "sg:city":"Oudkarspel",
    "sg:orig_category":"Verhuur Diversen",
    "sg:phone":"+31 226 315 631",
    "sg:postcode":"1724 VH",
    "sg:province":"Noord-Holland",
    "wof:name":"Langedijk",
    "wof:placetype":"venue"
},
  "geometry": {"coordinates":[4.806251,52.707932],"type":"Point"}
}