{
  "type": "Feature",
  "properties": {
    "addr:full":"Stationsstr 21 Etten Leur Noord-Brabant 4872 TA",
    "addr:housenumber":"21",
    "addr:postcode":"4872 ta",
    "addr:street":"Stationsstr",
    "iso:country":"NL",
    "sg:address":"Stationsstr 21",
    "sg:city":"Etten Leur",
    "sg:orig_category":"Psychotherapeuten",
    "sg:phone":"+31 76 503 8899",
    "sg:postcode":"4872 TA",
    "sg:province":"Noord-Brabant",
    "wof:name":"Erp, Drs J H M Van",
    "wof:placetype":"venue"
},
  "geometry": {"coordinates":[4.636928,51.571888],"type":"Point"}
}