{
  "type": "Feature",
  "properties": {
    "addr:full":"Kalslagerring 442 Nieuw Vennep Noord-Holland 2151 TK",
    "addr:housenumber":"442",
    "addr:postcode":"2151 tk",
    "addr:street":"Kalslagerring;Nieuw Vennep",
    "iso:country":"NL",
    "sg:address":"Kalslagerring 442",
    "sg:city":"Nieuw Vennep",
    "sg:orig_category":"Koeriersdiensten",
    "sg:phone":"+31 6 55777532",
    "sg:postcode":"2151 TK",
    "sg:province":"Noord-Holland",
    "wof:name":"Golpeek",
    "wof:placetype":"venue"
},
  "geometry": {"coordinates":[4.619006,52.263134],"type":"Point"}
}