{
  "type": "Feature",
  "properties": {
    "addr:full":"Postbus 92 Reusel Noord-Brabant 5540 AB",
    "addr:housenumber":"92",
    "addr:postcode":"5540 ab",
    "addr:street":"Postbus",
    "iso:country":"NL",
    "sg:address":"Postbus 92",
    "sg:city":"Reusel",
    "sg:orig_category":"Adviesbureaus",
    "sg:phone":"+31 6 53225214",
    "sg:postcode":"5540 AB",
    "sg:province":"Noord-Brabant",
    "wof:name":"Tema Diensten Bv",
    "wof:placetype":"venue"
},
  "geometry": {"coordinates":[5.16184,51.361759],"type":"Point"}
}