{
  "type": "Feature",
  "properties": {
    "addr:full":"Surinamewg 8 Haarlem Noord-Holland 2035 VA",
    "addr:housenumber":"8",
    "addr:postcode":"2035",
    "addr:street":"Surinamewg",
    "iso:country":"NL",
    "sg:address":"Surinamewg 8",
    "sg:city":"Haarlem",
    "sg:orig_category":"Gehandicapteninformatie",
    "sg:phone":"+31 23 535 8877",
    "sg:postcode":"2035 VA",
    "sg:province":"Noord-Holland",
    "wof:name":"Mdgg/Spd",
    "wof:placetype":"venue"
},
  "geometry": {"coordinates":[4.652379,52.362041],"type":"Point"}
}