{
  "type": "Feature",
  "properties": {
    "addr:full":"Chassestr 75 Amsterdam Noord-Holland 1057 JA",
    "addr:housenumber":"75",
    "addr:postcode":"1057 ja",
    "addr:street":"Chassestr",
    "iso:country":"NL",
    "sg:address":"Chassestr 75",
    "sg:city":"Amsterdam",
    "sg:orig_category":"Beeldende Kunstenaars",
    "sg:phone":"+31 20 618 2736",
    "sg:postcode":"1057 JA",
    "sg:province":"Noord-Holland",
    "wof:name":"Leeuwen, Frans Van",
    "wof:placetype":"venue"
},
  "geometry": {"coordinates":[4.861092,52.369827],"type":"Point"}
}