{
  "type": "Feature",
  "properties": {
    "addr:full":"Gr Houtstr 111 Haarlem North Holland 2011 SJ",
    "addr:housenumber":"111",
    "addr:postcode":"2011",
    "iso:country":"NL",
    "sg:address":"Gr Houtstr 111",
    "sg:city":"Haarlem",
    "sg:orig_category":"Bioscopen",
    "sg:phone":"+31 23 531 1004",
    "sg:postcode":"2011 SJ",
    "sg:province":"North Holland",
    "wof:name":"Cinema Palace",
    "wof:placetype":"venue"
},
  "geometry": {"coordinates":[4.632428,52.378155],"type":"Point"}
}