{
  "type": "Feature",
  "properties": {
    "addr:full":"Winterakoniet 21 Leeuwarden Provincie Friesland 8935 JM",
    "addr:housenumber":"21",
    "addr:postcode":"8935 jm",
    "addr:street":"Winterakoniet;Provincie Friesland",
    "iso:country":"NL",
    "sg:address":"Winterakoniet 21",
    "sg:city":"Leeuwarden",
    "sg:orig_category":"Fitnesscentra",
    "sg:phone":"+31 58 288 3626",
    "sg:postcode":"8935 JM",
    "sg:province":"Provincie Friesland",
    "wof:name":"Fysiofitness",
    "wof:placetype":"venue"
},
  "geometry": {"coordinates":[5.822345,53.187717],"type":"Point"}
}