{
  "type": "Feature",
  "properties": {
    "addr:full":"Westdijk 31 Mijnsheerenland South Holland 3271 LL",
    "addr:housenumber":"31",
    "addr:postcode":"3271 ll",
    "addr:street":"Westdijk",
    "iso:country":"NL",
    "sg:address":"Westdijk 31",
    "sg:city":"Mijnsheerenland",
    "sg:orig_category":"Fotostudio'S And Fotografen",
    "sg:phone":"+31 186 603 263",
    "sg:postcode":"3271 LL",
    "sg:province":"South Holland",
    "wof:name":"Bianchi Vakfotografie",
    "wof:placetype":"venue"
},
  "geometry": {"coordinates":[4.466604,51.798714],"type":"Point"}
}