{
  "type": "Feature",
  "properties": {
    "addr:full":"Koningstraat 23 Haarlem North Holland 2011 TB",
    "addr:housenumber":"23",
    "addr:postcode":"2011 tb",
    "addr:street":"Koningstraat",
    "iso:country":"NL",
    "sg:address":"Koningstraat 23",
    "sg:city":"Haarlem",
    "sg:orig_category":"Boekhouders",
    "sg:phone":"+31 23 534 3975",
    "sg:postcode":"2011 TB",
    "sg:province":"North Holland",
    "wof:name":"Heres Accounting & Consulting",
    "wof:placetype":"venue"
},
  "geometry": {"coordinates":[4.634499,52.380566],"type":"Point"}
}