{
  "type": "Feature",
  "properties": {
    "addr:full":"Hoevestein 8 Oosterhout Nb Noord-Brabant 4903 SC",
    "addr:housenumber":"8",
    "addr:postcode":"4903 sc",
    "addr:street":"Hoevestein",
    "iso:country":"NL",
    "sg:address":"Hoevestein 8",
    "sg:city":"Oosterhout Nb",
    "sg:orig_category":"Meubels And Huishoudapparatuur Gh",
    "sg:phone":"+31 162 428 640",
    "sg:postcode":"4903 SC",
    "sg:province":"Noord-Brabant",
    "wof:name":"Metaltex Nederland Bv",
    "wof:placetype":"venue"
},
  "geometry": {"coordinates":[4.870342,51.629433],"type":"Point"}
}