{
  "type": "Feature",
  "properties": {
    "addr:full":"Zomereik 48 Best Texas 5682 HH",
    "addr:housenumber":"48",
    "addr:postcode":"5682 hh",
    "addr:street":"Zomereik",
    "iso:country":"NL",
    "sg:address":"Zomereik 48",
    "sg:city":"Best",
    "sg:orig_category":"Zonne-Energie",
    "sg:phone":"+31 499 392 261",
    "sg:postcode":"5682 HH",
    "sg:province":"Texas",
    "sg:website":"http://www.dbcom.nl",
    "wof:name":"Dbcom",
    "wof:placetype":"venue"
},
  "geometry": {"coordinates":[-101.618134,31.224251],"type":"Point"}
}