{
  "type": "Feature",
  "properties": {
    "addr:full":"Goudsesngl 130377 Rotterdam Zuid-Holland 3011 KD",
    "addr:housenumber":"130377",
    "addr:postcode":"3011 kd",
    "iso:country":"NL",
    "sg:address":"Goudsesngl 130377",
    "sg:city":"Rotterdam",
    "sg:orig_category":"Adviesbureaus Bouwkunde",
    "sg:phone":"+31 10 280 0621",
    "sg:postcode":"3011 KD",
    "sg:province":"Zuid-Holland",
    "wof:name":"Vlb Bv",
    "wof:placetype":"venue"
},
  "geometry": {"coordinates":[4.49347,51.92334],"type":"Point"}
}