{
  "type": "Feature",
  "properties": {
    "addr:full":"De Factorij 28M Zwaag Noord-Holland 1689 AL",
    "addr:housenumber":"28m",
    "addr:postcode":"1689 al",
    "addr:street":"De Factorij",
    "iso:country":"NL",
    "sg:address":"De Factorij 28M",
    "sg:city":"Zwaag",
    "sg:orig_category":"Chemische Producten Gh",
    "sg:phone":"+31 229 272 282",
    "sg:postcode":"1689 AL",
    "sg:province":"Noord-Holland",
    "wof:name":"Hifi Industrial Film",
    "wof:placetype":"venue"
},
  "geometry": {"coordinates":[5.064945,52.670143],"type":"Point"}
}