{
  "type": "Feature",
  "properties": {
    "iso:country":"NL",
    "sg:address":"Tafelbaai 25",
    "sg:city":"Capelle Ad Yssel",
    "sg:orig_category":"Fotoapparatuur En Filmapparatuur - Reparatie",
    "sg:phone":"+31 10 450 6810",
    "sg:postcode":"2904 BJ",
    "sg:province":"Zuid-Holland",
    "wof:name":"Yacon",
    "wof:placetype":"venue"
},
  "geometry": {"coordinates":[4.614877,51.933487],"type":"Point"}
}