{
  "type": "Feature",
  "properties": {
    "iso:country":"NL",
    "sg:address":"Wilhelminastraat 2",
    "sg:city":"Koog A/D Zaan",
    "sg:orig_category":"Kappers",
    "sg:phone":"+31 75 616 2978",
    "sg:postcode":"1541 GN",
    "sg:province":"Noord-Holland",
    "wof:name":"Kapsalon Wilma",
    "wof:placetype":"venue"
},
  "geometry": {"coordinates":[4.8088102341,52.461971283],"type":"Point"}
}