{
  "type": "Feature",
  "properties": {
    "iso:country":"NL",
    "sg:address":"Vlytwg 4",
    "sg:city":"Wapenveld",
    "sg:orig_category":"Machinefabrieken",
    "sg:phone":"+31 38 447 2525",
    "sg:postcode":"8191 JP",
    "sg:province":"Gelderland",
    "wof:name":"Audion Machinery Bv",
    "wof:placetype":"venue"
},
  "geometry": {"coordinates":[6.072336,52.436893],"type":"Point"}
}