{
  "type": "Feature",
  "properties": {
    "addr:full":"Haven 74 Schoonhoven South Holland 2871 CR",
    "addr:housenumber":"74",
    "addr:postcode":"2871 cr",
    "addr:street":"Haven",
    "iso:country":"NL",
    "sg:address":"Haven 74",
    "sg:city":"Schoonhoven",
    "sg:orig_category":"Herenmodezaken",
    "sg:phone":"+31 182 382 469",
    "sg:postcode":"2871 CR",
    "sg:province":"South Holland",
    "wof:name":"Bulle'S Mannenmode Vof",
    "wof:placetype":"venue"
},
  "geometry": {"coordinates":[4.85134,51.945763],"type":"Point"}
}