{
  "type": "Feature",
  "properties": {
    "addr:full":"Schoolpad 9 Laren Nh Noord-Holland 1251 ZN",
    "addr:housenumber":"9",
    "addr:postcode":"1251 zn",
    "addr:street":"Schoolpad",
    "iso:country":"NL",
    "sg:address":"Schoolpad 9",
    "sg:city":"Laren Nh",
    "sg:orig_category":"Fotoreportages",
    "sg:phone":"+31 35 538 7081",
    "sg:postcode":"1251 ZN",
    "sg:province":"Noord-Holland",
    "wof:name":"Hest, Marja Van",
    "wof:placetype":"venue"
},
  "geometry": {"coordinates":[5.23131,52.256508],"type":"Point"}
}