{
  "type": "Feature",
  "properties": {
    "addr:full":"Lavendelpln 47 Eindhoven North Brabant 5643 DG",
    "addr:housenumber":"47",
    "addr:postcode":"5643 dg",
    "addr:street":"Lavendelpln",
    "iso:country":"NL",
    "sg:address":"Lavendelpln 47",
    "sg:city":"Eindhoven",
    "sg:orig_category":"Verenigingen En Stichtingen",
    "sg:phone":"+31 40 212 5119",
    "sg:postcode":"5643 DG",
    "sg:province":"North Brabant",
    "sg:website":"http://www.kruidenbuurt.nl",
    "wof:name":"Buurtbeheer Kruidenbuurt, Sticht",
    "wof:placetype":"venue"
},
  "geometry": {"coordinates":[5.502573,51.420559],"type":"Point"}
}