{
  "type": "Feature",
  "properties": {
    "iso:country":"NL",
    "sg:address":"Industriewg 107",
    "sg:city":"Heeze",
    "sg:orig_category":"Kunststoffen- Verwerkende Industrie",
    "sg:phone":"+31 40 224 1160",
    "sg:postcode":"5591 JL",
    "sg:province":"North Brabant",
    "wof:name":"Vdl Bv",
    "wof:placetype":"venue"
},
  "geometry": {"coordinates":[5.582438,51.369156],"type":"Point"}
}