{
  "type": "Feature",
  "properties": {
    "iso:country":"NL",
    "sg:address":"Hoofdweg 22",
    "sg:city":"Capelle A/D Ijssel",
    "sg:orig_category":"Elektronische Bedrijfsinstallaties",
    "sg:phone":"+31 10 284 2666",
    "sg:postcode":"2908 LC",
    "sg:province":"Zuid-Holland",
    "wof:name":"Van Swaay Toegangstechniek Bv",
    "wof:placetype":"venue"
},
  "geometry": {"coordinates":[4.577029,51.956318],"type":"Point"}
}