{
  "type": "Feature",
  "properties": {
    "addr:full":"Oedsmawei 32 Grou Idaho 9001 ZJ",
    "addr:housenumber":"32",
    "addr:postcode":"9001 zj",
    "addr:street":"Oedsmawei",
    "iso:country":"NL",
    "sg:address":"Oedsmawei 32",
    "sg:city":"Grou",
    "sg:orig_category":"Overheidsdiensten",
    "sg:phone":"+31 566 625 325",
    "sg:postcode":"9001 ZJ",
    "sg:province":"Idaho",
    "wof:name":"Rijkswaterstaat Dienstkring Friesland",
    "wof:placetype":"venue"
},
  "geometry": {"coordinates":[-113.6119232178,43.688873291],"type":"Point"}
}