{
  "type": "Feature",
  "properties": {
    "addr:full":"Vlieterweg 14 Scherpenzeel Gld Gelderland 3925 GB",
    "addr:housenumber":"14",
    "addr:postcode":"3925 gb",
    "addr:street":"Vlieterweg;Gld Gelderland",
    "iso:country":"NL",
    "sg:address":"Vlieterweg 14",
    "sg:city":"Scherpenzeel Gld",
    "sg:orig_category":"Diverse Bedrijfsinstallaties Gh",
    "sg:phone":"+31 33 277 3938",
    "sg:postcode":"3925 GB",
    "sg:province":"Gelderland",
    "wof:name":"Intramac Bv",
    "wof:placetype":"venue"
},
  "geometry": {"coordinates":[5.48323,52.077679],"type":"Point"}
}