{
  "type": "Feature",
  "properties": {
    "addr:full":"Mariastr 78 S Gravenhage Zuid-Holland 2595 GP",
    "addr:housenumber":"78;gravenhage",
    "addr:postcode":"2595 gp",
    "addr:street":"Mariastr;S",
    "iso:country":"NL",
    "sg:address":"Mariastr 78",
    "sg:city":"S Gravenhage",
    "sg:orig_category":"Vertaalbureaus",
    "sg:phone":"+31 70 385 8910",
    "sg:postcode":"2595 GP",
    "sg:province":"Zuid-Holland",
    "wof:name":"Plain English",
    "wof:placetype":"venue"
},
  "geometry": {"coordinates":[4.33507,52.081421],"type":"Point"}
}