{
  "type": "Feature",
  "properties": {
    "addr:full":"A Fokkerstr 79 Goes Ohio 4462 ES",
    "addr:housenumber":"79",
    "addr:postcode":"4462 es",
    "iso:country":"NL",
    "sg:address":"A Fokkerstr 79",
    "sg:city":"Goes",
    "sg:orig_category":"Verlichtingsartikelen - Fabrieken",
    "sg:phone":"+31 113 272 020",
    "sg:postcode":"4462 ES",
    "sg:province":"Ohio",
    "sg:website":"http://www.lightingpartner.nl",
    "wof:name":"Lighting Partner",
    "wof:placetype":"venue"
},
  "geometry": {"coordinates":[-83.914169,39.768833],"type":"Point"}
}