{
  "type": "Feature",
  "properties": {
    "iso:country":"NL",
    "sg:address":"Oranjelaan 1 A",
    "sg:city":"Warnsveld",
    "sg:orig_category":"Binnenhuisarchitecten",
    "sg:phone":"+31 575 527 225",
    "sg:postcode":"7231 EW",
    "sg:province":"Gelderland",
    "wof:name":"Kippers Interieurarchitectuur",
    "wof:placetype":"venue"
},
  "geometry": {"coordinates":[6.230902,52.140247],"type":"Point"}
}