{
  "type": "Feature",
  "properties": {
    "addr:full":"Kerkstr 38 Enschede NL.08 7532 AV",
    "addr:housenumber":"38",
    "addr:postcode":"7532 av",
    "addr:street":"Kerkstr",
    "iso:country":"NL",
    "sg:address":"Kerkstr 38",
    "sg:city":"Enschede",
    "sg:orig_category":"Fietsen En Bromfietsen",
    "sg:phone":"+31 53 461 1297",
    "sg:postcode":"7532 AV",
    "sg:province":"NL.08",
    "wof:name":"Kroeze",
    "wof:placetype":"venue"
},
  "geometry": {"coordinates":[6.973698,52.217781],"type":"Point"}
}