{
  "type": "Feature",
  "properties": {
    "addr:full":"Korenmolen 75 Alphen Aan Den Rijn Zuid-Holland 2406 KB",
    "addr:housenumber":"75",
    "addr:postcode":"2406 kb",
    "addr:street":"Korenmolen",
    "iso:country":"NL",
    "sg:address":"Korenmolen 75",
    "sg:city":"Alphen Aan Den Rijn",
    "sg:orig_category":"Wasserettes, Stomerijen And Reiniging",
    "sg:phone":"+31 172 490 750",
    "sg:postcode":"2406 KB",
    "sg:province":"Zuid-Holland",
    "wof:name":"Chemdry",
    "wof:placetype":"venue"
},
  "geometry": {"coordinates":[4.6714520454,52.1227264404],"type":"Point"}
}