{
  "type": "Feature",
  "properties": {
    "iso:country":"NL",
    "sg:address":"Kogerpolder 17",
    "sg:city":"Starnmeer",
    "sg:orig_category":"Honden- En Kattentrimsalons",
    "sg:phone":"+31 75 641 1611",
    "sg:postcode":"1488 AB",
    "sg:province":"Noord-Holland",
    "wof:name":"Doniels",
    "wof:placetype":"venue"
},
  "geometry": {"coordinates":[4.821554,52.532173],"type":"Point"}
}