{
  "type": "Feature",
  "properties": {
    "iso:country":"NL",
    "sg:address":"Witte Paal 219",
    "sg:city":"Schagen",
    "sg:orig_category":"Sanitaire Artikelen",
    "sg:phone":"+31 224 215 566",
    "sg:postcode":"1742 LA",
    "sg:province":"Noord-Holland",
    "wof:name":"Verblauw Sanilux",
    "wof:placetype":"venue"
},
  "geometry": {"coordinates":[4.812249,52.781551],"type":"Point"}
}