{
  "type": "Feature",
  "properties": {
    "addr:full":"Koperslagersstraat 10 Sneek Friesland 8601 WL",
    "addr:housenumber":"10",
    "addr:postcode":"8601 wl",
    "addr:street":"Koperslagersstraat",
    "iso:country":"NL",
    "sg:address":"Koperslagersstraat 10",
    "sg:city":"Sneek",
    "sg:orig_category":"Verhuur Audiovisuele Apparatuur",
    "sg:phone":"+31 515 430 107",
    "sg:postcode":"8601 WL",
    "sg:province":"Friesland",
    "wof:name":"I. Eckhardt Professioneel",
    "wof:placetype":"venue"
},
  "geometry": {"coordinates":[5.634028,53.028355],"type":"Point"}
}