{
  "type": "Feature",
  "properties": {
    "addr:full":"Breestr 39 Beverwyk North Holland 1941 EE",
    "addr:housenumber":"39",
    "addr:postcode":"1941 ee",
    "addr:street":"Breestr;North",
    "iso:country":"NL",
    "sg:address":"Breestr 39",
    "sg:city":"Beverwyk",
    "sg:orig_category":"Opticiens",
    "sg:phone":"+31 251 216 203",
    "sg:postcode":"1941 EE",
    "sg:province":"North Holland",
    "wof:name":"Huis Van Maaren, Het",
    "wof:placetype":"venue"
},
  "geometry": {"coordinates":[4.6565170288,52.4805641174],"type":"Point"}
}