{
  "type": "Feature",
  "properties": {
    "addr:full":"Biesterwg 2 Eindhoven Noord-Brabant 5615 AH",
    "addr:housenumber":"2",
    "addr:postcode":"5615 ah",
    "addr:street":"Biesterwg",
    "iso:country":"NL",
    "sg:address":"Biesterwg 2",
    "sg:city":"Eindhoven",
    "sg:orig_category":"Onderhoudswerken",
    "sg:phone":"+31 40 212 1833",
    "sg:postcode":"5615 AH",
    "sg:province":"Noord-Brabant",
    "wof:name":"Borgers, A",
    "wof:placetype":"venue"
},
  "geometry": {"coordinates":[5.488437,51.42688],"type":"Point"}
}