{
  "type": "Feature",
  "properties": {
    "addr:full":"Waage Naak 1 Wessem Limburg 6019 AA",
    "addr:housenumber":"1",
    "addr:postcode":"6019 aa",
    "addr:street":"Waage Naak",
    "iso:country":"NL",
    "sg:address":"Waage Naak 1",
    "sg:city":"Wessem",
    "sg:orig_category":"Farmaceutische Producten Gh",
    "sg:phone":"+31 475 561 405",
    "sg:postcode":"6019 AA",
    "sg:province":"Limburg",
    "wof:name":"Allegiance",
    "wof:placetype":"venue"
},
  "geometry": {"coordinates":[5.877902,51.157429],"type":"Point"}
}