{
  "type": "Feature",
  "properties": {
    "addr:full":"Traasterdk 1A Bathmen Overijssel 7437 RZ",
    "addr:housenumber":"1a",
    "addr:postcode":"7437 rz",
    "addr:street":"Traasterdk",
    "iso:country":"NL",
    "sg:address":"Traasterdk 1A",
    "sg:city":"Bathmen",
    "sg:orig_category":"Wegenbouw",
    "sg:phone":"+31 570 638 168",
    "sg:postcode":"7437 RZ",
    "sg:province":"Overijssel",
    "wof:name":"Flierman Bv, Gerrit",
    "wof:placetype":"venue"
},
  "geometry": {"coordinates":[6.2882218361,52.2532844543],"type":"Point"}
}