{
  "type": "Feature",
  "properties": {
    "addr:full":"Gebr Vd Boogaardstr 1 Steenbergen Nb North Brabant 4651 ZV",
    "addr:housenumber":"1;nb",
    "addr:postcode":"gebr;4651 zv",
    "addr:street":"Boogaardstr",
    "iso:country":"NL",
    "sg:address":"Gebr Vd Boogaardstr 1",
    "sg:city":"Steenbergen Nb",
    "sg:orig_category":"Kappers",
    "sg:phone":"+31 167 565 437",
    "sg:postcode":"4651 ZV",
    "sg:province":"North Brabant",
    "wof:name":"C. Oerlemans Kapsalon",
    "wof:placetype":"venue"
},
  "geometry": {"coordinates":[4.3145551682,51.5855941772],"type":"Point"}
}