{
  "type": "Feature",
  "properties": {
    "addr:full":"Roemerstr 35 Nykerk Gld Gelderland 3861 JX",
    "addr:housenumber":"35",
    "addr:postcode":"3861 jx",
    "addr:street":"Roemerstr;Gld Gelderland",
    "iso:country":"NL",
    "sg:address":"Roemerstr 35",
    "sg:city":"Nykerk Gld",
    "sg:orig_category":"Verenigingen En Stichtingen",
    "sg:phone":"+31 33 246 3208",
    "sg:postcode":"3861 JX",
    "sg:province":"Gelderland",
    "wof:name":"Kom Over En Help, Sticht",
    "wof:placetype":"venue"
},
  "geometry": {"coordinates":[5.489808,52.225693],"type":"Point"}
}