{
  "type": "Feature",
  "properties": {
    "iso:country":"NL",
    "sg:address":"Warmoesstr 55",
    "sg:city":"Amsterdam",
    "sg:classifiers":[
        {
            "category":"Travel",
            "subcategory":"Hotels & Motels",
            "type":"Entertainment"
        }
    ],
    "sg:phone":"+31 20 623 7462",
    "sg:postcode":"1012 HW",
    "sg:province":"North Holland",
    "sg:website":"http://www.the-greenhouse-effect.com",
    "wof:name":"Greenhouse Effect, The",
    "wof:placetype":"venue"
},
  "geometry": {"coordinates":[4.898279,52.375275],"type":"Point"}
}