{
  "type": "Feature",
  "properties": {
    "iso:country":"NL",
    "sg:address":"Zwanendreef 4",
    "sg:city":"Stolwijk",
    "sg:orig_category":"Schilderwerk",
    "sg:phone":"+31 182 341 882",
    "sg:postcode":"2821 VZ",
    "sg:province":"Zuid-Holland",
    "wof:name":"Schildersbedrijf J.H. Verdoold",
    "wof:placetype":"venue"
},
  "geometry": {"coordinates":[4.775216,51.974487],"type":"Point"}
}