{
  "type": "Feature",
  "properties": {
    "addr:full":"Spaarnestr 162 Leiden Zuid-Holland 2314 TS",
    "addr:housenumber":"162",
    "addr:postcode":"2314 ts",
    "iso:country":"NL",
    "sg:address":"Spaarnestr 162",
    "sg:city":"Leiden",
    "sg:orig_category":"Journalisten Freelance",
    "sg:phone":"+31 71 542 0595",
    "sg:postcode":"2314 TS",
    "sg:province":"Zuid-Holland",
    "sg:website":"http://www.minus10media.nl",
    "wof:name":"-10",
    "wof:placetype":"venue"
},
  "geometry": {"coordinates":[4.515564,52.150845],"type":"Point"}
}