{
  "type": "Feature",
  "properties": {
    "iso:country":"NL",
    "sg:address":"Lange Breestraat 7",
    "sg:city":"Dordrecht",
    "sg:classifiers":[
        {
            "category":"Fast Food",
            "type":"Food & Drink"
        }
    ],
    "sg:phone":"+31 78 613 9389",
    "sg:postcode":"3311 VK",
    "sg:province":"Zuid-Holland",
    "sg:tags":[
        "afhaal",
        "restaurant"
    ],
    "wof:name":"Mama",
    "wof:placetype":"venue"
},
  "geometry": {"coordinates":[4.665947,51.81329],"type":"Point"}
}