{
  "type": "Feature",
  "properties": {
    "addr:full":"Kanaalstr 153 Lisse North Holland 2161 JE",
    "addr:housenumber":"153",
    "addr:postcode":"2161 je",
    "iso:country":"NL",
    "sg:address":"Kanaalstr 153",
    "sg:city":"Lisse",
    "sg:orig_category":"Kappers",
    "sg:phone":"+31 252 420 312",
    "sg:postcode":"2161 JE",
    "sg:province":"North Holland",
    "wof:name":"Jooks",
    "wof:placetype":"venue"
},
  "geometry": {"coordinates":[4.5627121925,52.2586669922],"type":"Point"}
}