{
  "type": "Feature",
  "properties": {
    "addr:full":"Park Sparrendaal 80 Driebergen-Rijsenburg Utrecht 3971 SP",
    "addr:housenumber":"80",
    "addr:postcode":"3971 sp",
    "addr:street":"Park Sparrendaal",
    "iso:country":"NL",
    "sg:address":"Park Sparrendaal 80",
    "sg:city":"Driebergen-Rijsenburg",
    "sg:orig_category":"Verzekeringen",
    "sg:phone":"+31 343 521 275",
    "sg:postcode":"3971 SP",
    "sg:province":"Utrecht",
    "wof:name":"Postova",
    "wof:placetype":"venue"
},
  "geometry": {"coordinates":[5.282649,52.056679],"type":"Point"}
}