{
  "type": "Feature",
  "properties": {
    "addr:full":"Pasweg 11 Bunde Limburg 6241 CT",
    "addr:housenumber":"11",
    "addr:postcode":"6241 ct",
    "addr:street":"Pasweg",
    "iso:country":"NL",
    "sg:address":"Pasweg 11",
    "sg:city":"Bunde",
    "sg:orig_category":"Elektronische Bedrijfsinstallaties",
    "sg:phone":"+31 43 364 5938",
    "sg:postcode":"6241 CT",
    "sg:province":"Limburg",
    "wof:name":"Diefstalpreventiebureau Conemans",
    "wof:placetype":"venue"
},
  "geometry": {"coordinates":[5.731149,50.899181],"type":"Point"}
}