{
  "type": "Feature",
  "properties": {
    "addr:full":"Passage 10 Spijkenisse South Holland 3201 EP",
    "addr:housenumber":"10",
    "addr:postcode":"3201 ep",
    "addr:street":"Passage",
    "iso:country":"NL",
    "sg:address":"Passage 10",
    "sg:city":"Spijkenisse",
    "sg:orig_category":"Verlichting And Huishoudartikelen",
    "sg:phone":"+31 181 690 308",
    "sg:postcode":"3201 EP",
    "sg:province":"South Holland",
    "wof:name":"Xenos Bv",
    "wof:placetype":"venue"
},
  "geometry": {"coordinates":[4.32697,51.849567],"type":"Point"}
}