{
  "type": "Feature",
  "properties": {
    "addr:full":"Korte Leidsedwarsstraat 79 Amsterdam Noord-Holland 1017 PW",
    "addr:housenumber":"79",
    "addr:postcode":"1017 pw",
    "addr:street":"Korte Leidsedwarsstraat",
    "iso:country":"NL",
    "sg:address":"Korte Leidsedwarsstraat 79",
    "sg:city":"Amsterdam",
    "sg:classifiers":[
        {
            "category":"Travel",
            "subcategory":"Hotels & Motels",
            "type":"Entertainment"
        }
    ],
    "sg:phone":"+31 20 627 2505",
    "sg:postcode":"1017 PW",
    "sg:province":"Noord-Holland",
    "wof:name":"Het Leidseplein Hotel",
    "wof:placetype":"venue"
},
  "geometry": {"coordinates":[4.883966,52.363983],"type":"Point"}
}