{
  "type": "Feature",
  "properties": {
    "iso:country":"NL",
    "sg:address":"Steltsestr 37",
    "sg:city":"Lent",
    "sg:orig_category":"Bloemen En Planten - Groothandel",
    "sg:phone":"+31 24 360 4425",
    "sg:postcode":"6663 BN",
    "sg:province":"Virginia",
    "wof:name":"Disveld Handels- En Cactuskwekerij Bv, Jos",
    "wof:placetype":"venue"
},
  "geometry": {"coordinates":[-77.241432,38.151344],"type":"Point"}
}