{
  "type": "Feature",
  "properties": {
    "iso:country":"NL",
    "sg:address":"Mozartdreef 8",
    "sg:city":"Veenendaal",
    "sg:orig_category":"Psychologen",
    "sg:phone":"+31 318 554 166",
    "sg:postcode":"3906 BP",
    "sg:province":"Utrecht",
    "wof:name":"Enteract",
    "wof:placetype":"venue"
},
  "geometry": {"coordinates":[5.531982,52.034595],"type":"Point"}
}