{
  "type": "Feature",
  "properties": {
    "iso:country":"NL",
    "sg:address":"Loevesteinsngl 33",
    "sg:city":"Rotterdam",
    "sg:orig_category":"Glazenwasserijen",
    "sg:phone":"+31 10 479 0493",
    "sg:postcode":"3077 HL",
    "sg:province":"Zuid-Holland",
    "wof:name":"Wijk, W A De",
    "wof:placetype":"venue"
},
  "geometry": {"coordinates":[4.566893,51.890907],"type":"Point"}
}