{
  "type": "Feature",
  "properties": {
    "addr:full":"Plevierweide 22 Baarn Utrecht 3742 XV",
    "addr:housenumber":"22",
    "addr:postcode":"3742 xv",
    "addr:street":"Plevierweide",
    "iso:country":"NL",
    "sg:address":"Plevierweide 22",
    "sg:city":"Baarn",
    "sg:classifiers":[
        {
            "category":"Utilities",
            "subcategory":"Cable",
            "type":"Services"
        }
    ],
    "sg:phone":"+31 35 541 6358",
    "sg:postcode":"3742 XV",
    "sg:province":"Utrecht",
    "sg:tags":[
        "masseur",
        "en",
        "heilgymnasten"
    ],
    "wof:name":"Ada Lakenman",
    "wof:placetype":"venue"
},
  "geometry": {"coordinates":[5.295982,52.199402],"type":"Point"}
}