{
  "type": "Feature",
  "properties": {
    "addr:full":"Kon Julianapln 19A Voorburg Zuid-Holland 2273 BR",
    "addr:housenumber":"19a",
    "addr:postcode":"2273 br",
    "addr:street":"Kon",
    "iso:country":"NL",
    "sg:address":"Kon Julianapln 19A",
    "sg:city":"Voorburg",
    "sg:orig_category":"Woninginrichting",
    "sg:phone":"+31 70 387 9667",
    "sg:postcode":"2273 BR",
    "sg:province":"Zuid-Holland",
    "wof:name":"Franse, Woninginrichting",
    "wof:placetype":"venue"
},
  "geometry": {"coordinates":[4.3575029373,52.0763320923],"type":"Point"}
}