{
  "type": "Feature",
  "properties": {
    "addr:full":"Industriewg 26 Mierlo Noord-Brabant 5731 HR",
    "addr:housenumber":"26",
    "addr:postcode":"5731 hr",
    "addr:street":"Industriewg",
    "iso:country":"NL",
    "sg:address":"Industriewg 26",
    "sg:city":"Mierlo",
    "sg:orig_category":"Levensmiddelen - Fabrieken En Groothandel",
    "sg:phone":"+31 492 663 952",
    "sg:postcode":"5731 HR",
    "sg:province":"Noord-Brabant",
    "wof:name":"Gnt Ned Bv",
    "wof:placetype":"venue"
},
  "geometry": {"coordinates":[5.622498,51.447918],"type":"Point"}
}