{
  "type": "Feature",
  "properties": {
    "addr:full":"Sint Gerlachusstraat 2 Banholt Limburg 6262 NJ",
    "addr:housenumber":"2",
    "addr:postcode":"6262 nj",
    "addr:street":"Sint Gerlachusstraat",
    "iso:country":"NL",
    "sg:address":"Sint Gerlachusstraat 2",
    "sg:city":"Banholt",
    "sg:classifiers":[
        {
            "category":"Professional",
            "subcategory":"Accounting & Tax Preparation",
            "type":"Services"
        }
    ],
    "sg:phone":"+31 43 457 2353",
    "sg:postcode":"6262 NJ",
    "sg:province":"Limburg",
    "sg:tags":[
        "accountant"
    ],
    "wof:name":"Administratie- En Assurantiekantoor Land",
    "wof:placetype":"venue"
},
  "geometry": {"coordinates":[5.806408,50.790546],"type":"Point"}
}