{
  "type": "Feature",
  "properties": {
    "addr:full":"Gaardedreef 167 Zoetermeer Zuid-Holland 2723 AZ",
    "addr:housenumber":"167",
    "addr:postcode":"2723 az",
    "addr:street":"Gaardedreef",
    "iso:country":"NL",
    "sg:address":"Gaardedreef 167",
    "sg:city":"Zoetermeer",
    "sg:orig_category":"Overheidsdiensten",
    "sg:phone":"+31 79 342 2131",
    "sg:postcode":"2723 AZ",
    "sg:province":"Zuid-Holland",
    "wof:name":"Patio",
    "wof:placetype":"venue"
},
  "geometry": {"coordinates":[4.5157017708,52.0617370605],"type":"Point"}
}