{
  "type": "Feature",
  "properties": {
    "addr:full":"Nikkelstraat 31 Lelystad Flevoland 8211 AJ",
    "addr:housenumber":"31",
    "addr:postcode":"8211 aj",
    "addr:street":"Nikkelstraat;Flevoland",
    "iso:country":"NL",
    "sg:address":"Nikkelstraat 31",
    "sg:city":"Lelystad",
    "sg:orig_category":"Metaalafval, Schrootrecycling And Sloperijen",
    "sg:phone":"+31 320 247 149",
    "sg:postcode":"8211 AJ",
    "sg:province":"Flevoland",
    "wof:name":"Autodemontagebedrijf Gebr. Van Der Feer",
    "wof:placetype":"venue"
},
  "geometry": {"coordinates":[5.52739,52.545631],"type":"Point"}
}