{
  "type": "Feature",
  "properties": {
    "iso:country":"NL",
    "sg:address":"Stiggoor 77",
    "sg:city":"Lochem",
    "sg:orig_category":"Verpakkingsmachines",
    "sg:phone":"+31 573 257 550",
    "sg:postcode":"7241 LD",
    "sg:province":"Gelderland",
    "sg:website":"HTTP://www.marantrading.nl",
    "wof:name":"Maran",
    "wof:placetype":"venue"
},
  "geometry": {"coordinates":[6.429599,52.158123],"type":"Point"}
}