{
  "type": "Feature",
  "properties": {
    "iso:country":"NL",
    "sg:address":"Rollandsln 84",
    "sg:city":"Haarlem",
    "sg:orig_category":"Verzekeringen - Verzekeringskantoren",
    "sg:phone":"+31 23 524 2181",
    "sg:postcode":"2015 GG",
    "sg:province":"Noord-Holland",
    "wof:name":"Wekru",
    "wof:placetype":"venue"
},
  "geometry": {"coordinates":[4.607004,52.382191],"type":"Point"}
}