{
  "type": "Feature",
  "properties": {
    "addr:full":"Bisschop De Vetplein 10 Gilze North Brabant 5126 CA",
    "addr:housenumber":"10",
    "addr:postcode":"5126 ca",
    "addr:street":"Bisschop De Vetplein",
    "iso:country":"NL",
    "sg:address":"Bisschop De Vetplein 10",
    "sg:city":"Gilze",
    "sg:orig_category":"Banken And Kredietinstellingen",
    "sg:phone":"+31 13 507 6600",
    "sg:postcode":"5126 CA",
    "sg:province":"North Brabant",
    "wof:name":"Rabobank",
    "wof:placetype":"venue"
},
  "geometry": {"coordinates":[4.939471,51.542095],"type":"Point"}
}