{
  "type": "Feature",
  "properties": {
    "addr:full":"A. Cuijplaan 101 Soest Utrecht 3764 TM",
    "addr:housenumber":"101",
    "addr:postcode":"3764 tm",
    "addr:street":"Cuijplaan",
    "iso:country":"NL",
    "sg:address":"A. Cuijplaan 101",
    "sg:city":"Soest",
    "sg:orig_category":"Opvangtehuizen",
    "sg:phone":"+31 35 603 2053",
    "sg:postcode":"3764 TM",
    "sg:province":"Utrecht",
    "wof:name":"Centraal Opvang Asielzoekers",
    "wof:placetype":"venue"
},
  "geometry": {"coordinates":[5.3003849983,52.1840438843],"type":"Point"}
}