{
  "type": "Feature",
  "properties": {
    "addr:full":"Fransestr 6 Ameide Zuid-Holland 4233 ED",
    "addr:housenumber":"6",
    "addr:postcode":"4233 ed",
    "addr:street":"Fransestr",
    "iso:country":"NL",
    "sg:address":"Fransestr 6",
    "sg:city":"Ameide",
    "sg:orig_category":"Metselwerken",
    "sg:phone":"+31 183 600 902",
    "sg:postcode":"4233 ED",
    "sg:province":"Zuid-Holland",
    "wof:name":"Wilco'S Lijmwerk",
    "wof:placetype":"venue"
},
  "geometry": {"coordinates":[4.962506,51.957771],"type":"Point"}
}