{
  "type": "Feature",
  "properties": {
    "iso:country":"NL",
    "sg:address":"De Ruyterlaan 2 A",
    "sg:city":"Enschede",
    "sg:classifiers":[
        {
            "category":"Professional",
            "subcategory":"Accounting & Tax Preparation",
            "type":"Services"
        }
    ],
    "sg:phone":"+31 53 432 7227",
    "sg:postcode":"7511 JH",
    "sg:province":"NL.08",
    "sg:tags":[
        "accountant"
    ],
    "wof:name":"Sieverink Accountancy",
    "wof:placetype":"venue"
},
  "geometry": {"coordinates":[6.887306,52.22197],"type":"Point"}
}