{
  "type": "Feature",
  "properties": {
    "iso:country":"NL",
    "sg:address":"Steynln 92",
    "sg:city":"Zeist",
    "sg:orig_category":"Kappers",
    "sg:phone":"+31 30 692 4115",
    "sg:postcode":"3701 EJ",
    "sg:province":"Utrecht",
    "sg:website":"http://www.schoonheidzeist.nl",
    "wof:name":"Schoonheid Kapsalon",
    "wof:placetype":"venue"
},
  "geometry": {"coordinates":[5.24387,52.08548],"type":"Point"}
}