{
  "type": "Feature",
  "properties": {
    "iso:country":"NL",
    "sg:address":"De Marke 62",
    "sg:city":"Hasselt",
    "sg:orig_category":"Boekhouders",
    "sg:phone":"+31 38 477 1684",
    "sg:postcode":"8061 BC",
    "sg:province":"NL.08",
    "wof:name":"Administratiekantoor A.J. Brink",
    "wof:placetype":"venue"
},
  "geometry": {"coordinates":[6.098436,52.593868],"type":"Point"}
}