{
  "type": "Feature",
  "properties": {
    "addr:full":"Keizerstr 169 S Gravenhage Zuid-Holland 2584 BE",
    "addr:housenumber":"169;gravenhage",
    "addr:postcode":"2584",
    "addr:street":"S",
    "iso:country":"NL",
    "sg:address":"Keizerstr 169",
    "sg:city":"S Gravenhage",
    "sg:orig_category":"Kappers",
    "sg:phone":"+31 70 355 3310",
    "sg:postcode":"2584 BE",
    "sg:province":"Zuid-Holland",
    "wof:name":"Martinhair",
    "wof:placetype":"venue"
},
  "geometry": {"coordinates":[4.28131,52.103199],"type":"Point"}
}