{
  "type": "Feature",
  "properties": {
    "addr:full":"Faunushof 12 Maastricht Limburg 6215 RL",
    "addr:housenumber":"12",
    "addr:postcode":"6215 rl",
    "addr:street":"Faunushof",
    "iso:country":"NL",
    "sg:address":"Faunushof 12",
    "sg:city":"Maastricht",
    "sg:orig_category":"Alternatieve Geneeskunde",
    "sg:phone":"+31 43 347 8443",
    "sg:postcode":"6215 RL",
    "sg:province":"Limburg",
    "wof:name":"Henriette Hovens",
    "wof:placetype":"venue"
},
  "geometry": {"coordinates":[5.647281,50.837486],"type":"Point"}
}