{
  "type": "Feature",
  "properties": {
    "addr:full":"Kelvinstraat 24 'S Hertogenbosch Noord-Brabant 5223 GE",
    "addr:housenumber":"24",
    "addr:postcode":"5223",
    "addr:street":"Kelvinstraat;' S",
    "iso:country":"NL",
    "sg:address":"Kelvinstraat 24",
    "sg:city":"'S Hertogenbosch",
    "sg:orig_category":"Fotografische And Optische Artikelen Gh",
    "sg:phone":"+31 73 622 1953",
    "sg:postcode":"5223 GE",
    "sg:province":"Noord-Brabant",
    "wof:name":"Coskun Optics",
    "wof:placetype":"venue"
},
  "geometry": {"coordinates":[5.285863,51.69416],"type":"Point"}
}