{
  "type": "Feature",
  "properties": {
    "iso:country":"NL",
    "sg:address":"Albert John Luthulistr 3",
    "sg:city":"Purmerend",
    "sg:orig_category":"Verzekeringen",
    "sg:phone":"+31 299 647 597",
    "sg:postcode":"1447 XD",
    "sg:province":"Noord-Holland",
    "wof:name":"Assurantiekantoor Groeneveld",
    "wof:placetype":"venue"
},
  "geometry": {"coordinates":[4.957021,52.487701],"type":"Point"}
}