{
  "type": "Feature",
  "properties": {
    "addr:full":"Maria Louisastraat 11 Vlaardingen Zuid-Holland 3136 BJ",
    "addr:housenumber":"11",
    "addr:postcode":"3136 bj",
    "addr:street":"Maria Louisastraat",
    "iso:country":"NL",
    "sg:address":"Maria Louisastraat 11",
    "sg:city":"Vlaardingen",
    "sg:orig_category":"Vertaal- And Tolkenbureaus",
    "sg:phone":"+31 10 474 3719",
    "sg:postcode":"3136 BJ",
    "sg:province":"Zuid-Holland",
    "wof:name":"Elly Hollemans Language Consultancy",
    "wof:placetype":"venue"
},
  "geometry": {"coordinates":[4.34703,51.926342],"type":"Point"}
}