{
  "type": "Feature",
  "properties": {
    "addr:full":"Oude Langendk 10 Delft Zuid-Holland 2611 GK",
    "addr:housenumber":"10",
    "addr:postcode":"2611 gk",
    "addr:street":"Oude Langendk",
    "iso:country":"NL",
    "sg:address":"Oude Langendk 10",
    "sg:city":"Delft",
    "sg:orig_category":"Opticiens",
    "sg:phone":"+31 15 214 2945",
    "sg:postcode":"2611 GK",
    "sg:province":"Zuid-Holland",
    "wof:name":"Graaf, T De",
    "wof:placetype":"venue"
},
  "geometry": {"coordinates":[4.3591170311,52.0109977722],"type":"Point"}
}