{
  "type": "Feature",
  "properties": {
    "addr:full":"Churchillln 3 Bergeyk Noord-Brabant 5571 AR",
    "addr:housenumber":"3",
    "addr:postcode":"5571",
    "addr:street":"Churchillln",
    "iso:country":"NL",
    "sg:address":"Churchillln 3",
    "sg:city":"Bergeyk",
    "sg:orig_category":"Gordijnenateliers",
    "sg:phone":"+31 497 572 844",
    "sg:postcode":"5571 AR",
    "sg:province":"Noord-Brabant",
    "wof:name":"Theuws, Marion",
    "wof:placetype":"venue"
},
  "geometry": {"coordinates":[-75.431854,40.311344],"type":"Point"}
}