{
  "type": "Feature",
  "properties": {
    "addr:full":"Levantstraat 2 Hengelo Ov Overijssel 7559 CC",
    "addr:housenumber":"2",
    "addr:postcode":"7559 cc",
    "addr:street":"Levantstraat;Ov",
    "iso:country":"NL",
    "sg:address":"Levantstraat 2",
    "sg:city":"Hengelo Ov",
    "sg:orig_category":"Binnenhuisarchitecten",
    "sg:phone":"+31 74 277 0250",
    "sg:postcode":"7559 CC",
    "sg:province":"Overijssel",
    "wof:name":"Insight Vormgevers Bv",
    "wof:placetype":"venue"
},
  "geometry": {"coordinates":[6.81758,52.29044],"type":"Point"}
}