{
  "type": "Feature",
  "properties": {
    "addr:full":"Brummelkant 5 Stadskanaal Groningen 9502 BB",
    "addr:housenumber":"5",
    "addr:postcode":"9502 bb",
    "addr:street":"Brummelkant",
    "iso:country":"NL",
    "sg:address":"Brummelkant 5",
    "sg:city":"Stadskanaal",
    "sg:orig_category":"Antiquiteiten",
    "sg:phone":"+31 599 614 344",
    "sg:postcode":"9502 BB",
    "sg:province":"Groningen",
    "wof:name":"Aan De Brummelkant",
    "wof:placetype":"venue"
},
  "geometry": {"coordinates":[6.959966,52.996227],"type":"Point"}
}