{
  "type": "Feature",
  "properties": {
    "addr:full":"Karel Lotsyweg 145 Dordrecht South Holland 3318 AL",
    "addr:housenumber":"145",
    "addr:postcode":"3318 al",
    "addr:street":"Karel Lotsyweg",
    "iso:country":"NL",
    "sg:address":"Karel Lotsyweg 145",
    "sg:city":"Dordrecht",
    "sg:orig_category":"Werving And Selectie Van Vast Personeel",
    "sg:phone":"+31 78 654 0540",
    "sg:postcode":"3318 AL",
    "sg:province":"South Holland",
    "wof:name":"Innoflex",
    "wof:placetype":"venue"
},
  "geometry": {"coordinates":[4.6788377762,51.7914085388],"type":"Point"}
}