{
  "type": "Feature",
  "properties": {
    "addr:full":"Wormerwg 24 Westbeemster Noord-Holland 1464 NB",
    "addr:housenumber":"24",
    "addr:postcode":"1464 nb",
    "addr:street":"Wormerwg",
    "iso:country":"NL",
    "sg:address":"Wormerwg 24",
    "sg:city":"Westbeemster",
    "sg:orig_category":"Psychologen",
    "sg:phone":"+31 75 641 1247",
    "sg:postcode":"1464 NB",
    "sg:province":"Noord-Holland",
    "wof:name":"Paz",
    "wof:placetype":"venue"
},
  "geometry": {"coordinates":[4.862651,52.546329],"type":"Point"}
}