{
  "type": "Feature",
  "properties": {
    "addr:full":"Borgweg 20 Schipborg Provincie Drenthe 9469 PH",
    "addr:housenumber":"20",
    "addr:postcode":"9469",
    "addr:street":"Borgweg;Provincie Drenthe",
    "iso:country":"NL",
    "sg:address":"Borgweg 20",
    "sg:city":"Schipborg",
    "sg:orig_category":"Loodgieterswerk, Verwarming And Sanitaire Installaties",
    "sg:phone":"+31 50 409 0000",
    "sg:postcode":"9469 PH",
    "sg:province":"Provincie Drenthe",
    "wof:name":"Bouwonderhoud Gout",
    "wof:placetype":"venue"
},
  "geometry": {"coordinates":[6.668319,53.071415],"type":"Point"}
}