{
  "type": "Feature",
  "properties": {
    "addr:full":"Fahrenheitstraat 5 Weert Limburg 6003 DC",
    "addr:housenumber":"5",
    "addr:postcode":"6003",
    "addr:street":"Fahrenheitstraat",
    "iso:country":"NL",
    "sg:address":"Fahrenheitstraat 5",
    "sg:city":"Weert",
    "sg:orig_category":"Elektronische Bedrijfsinstallaties",
    "sg:phone":"+31 495 521 380",
    "sg:postcode":"6003 DC",
    "sg:province":"Limburg",
    "wof:name":"Lipro Engineering Bv",
    "wof:placetype":"venue"
},
  "geometry": {"coordinates":[5.724389,51.266602],"type":"Point"}
}