{
  "type": "Feature",
  "properties": {
    "addr:full":"Hanzestr 86A Arnhem Gelderland 6826 MP",
    "addr:housenumber":"86a",
    "addr:postcode":"6826 mp",
    "addr:street":"Hanzestr",
    "iso:country":"NL",
    "sg:address":"Hanzestr 86A",
    "sg:city":"Arnhem",
    "sg:orig_category":"Lijstenmakerijen",
    "sg:phone":"+31 26 361 2203",
    "sg:postcode":"6826 MP",
    "sg:province":"Gelderland",
    "wof:name":"Stijl",
    "wof:placetype":"venue"
},
  "geometry": {"coordinates":[5.950915,51.982971],"type":"Point"}
}