{
  "type": "Feature",
  "properties": {
    "addr:full":"Visstraat 9 Dordrecht Zuid-Holland 3311 KX",
    "addr:housenumber":"9",
    "addr:postcode":"3311 kx",
    "addr:street":"Visstraat",
    "iso:country":"NL",
    "sg:address":"Visstraat 9",
    "sg:city":"Dordrecht",
    "sg:orig_category":"Wasserettes And Stomerijen",
    "sg:phone":"+31 78 639 0931",
    "sg:postcode":"3311 KX",
    "sg:province":"Zuid-Holland",
    "wof:name":"Palthe Stomerijen Bv",
    "wof:placetype":"venue"
},
  "geometry": {"coordinates":[4.6654520035,51.813785553],"type":"Point"}
}