{
  "type": "Feature",
  "properties": {
    "addr:full":"Spaarpot 23 Geldrop Noord-Brabant 5667 KV",
    "addr:housenumber":"23",
    "addr:postcode":"5667 kv",
    "addr:street":"Spaarpot",
    "iso:country":"NL",
    "sg:address":"Spaarpot 23",
    "sg:city":"Geldrop",
    "sg:orig_category":"Kunststoffen- Verwerkende Industrie",
    "sg:phone":"+31 40 280 9808",
    "sg:postcode":"5667 KV",
    "sg:province":"Noord-Brabant",
    "sg:website":"http://www.dpi-bv.nl",
    "wof:name":"Dpi",
    "wof:placetype":"venue"
},
  "geometry": {"coordinates":[5.560123,51.435551],"type":"Point"}
}