{
  "type": "Feature",
  "properties": {
    "addr:full":"Wilhelminawg 15 Appingedam Groningen 9901 CL",
    "addr:housenumber":"15",
    "addr:postcode":"9901",
    "addr:street":"Wilhelminawg",
    "iso:country":"NL",
    "sg:address":"Wilhelminawg 15",
    "sg:city":"Appingedam",
    "sg:orig_category":"Verloskundigen",
    "sg:phone":"+31 596 627 071",
    "sg:postcode":"9901 CL",
    "sg:province":"Groningen",
    "wof:name":"Pijpker-Kasten, L",
    "wof:placetype":"venue"
},
  "geometry": {"coordinates":[6.857888,53.322594],"type":"Point"}
}