{
  "type": "Feature",
  "properties": {
    "iso:country":"NL",
    "sg:address":"Koelandsdrift 1",
    "sg:city":"Onnen",
    "sg:orig_category":"Artiesten",
    "sg:phone":"+31 50 406 2502",
    "sg:postcode":"9755 PN",
    "sg:province":"Groningen",
    "wof:name":"P P Holterman",
    "wof:placetype":"venue"
},
  "geometry": {"coordinates":[6.642783,53.158524],"type":"Point"}
}