{
  "type": "Feature",
  "properties": {
    "addr:full":"Weteringsngl 2 Krimpen Ad Yssel South Holland 2921 BB",
    "addr:housenumber":"2",
    "addr:postcode":"2921 bb",
    "addr:street":"Weteringsngl;Yssel",
    "iso:country":"NL",
    "sg:address":"Weteringsngl 2",
    "sg:city":"Krimpen Ad Yssel",
    "sg:classifiers":[
        {
            "category":"Food & Beverages",
            "subcategory":"Bakery",
            "type":"Retail Goods"
        }
    ],
    "sg:phone":"+31 180 590 295",
    "sg:postcode":"2921 BB",
    "sg:province":"South Holland",
    "sg:tags":[
        "pizza"
    ],
    "wof:name":"Villa Nova",
    "wof:placetype":"venue"
},
  "geometry": {"coordinates":[4.5731,51.909908],"type":"Point"}
}