{
  "type": "Feature",
  "properties": {
    "addr:full":"Kalfjeslaan 52 Delft Zuid-Holland 2623 AJ",
    "addr:housenumber":"52",
    "addr:postcode":"2623 aj",
    "addr:street":"Kalfjeslaan",
    "iso:country":"NL",
    "sg:address":"Kalfjeslaan 52",
    "sg:city":"Delft",
    "sg:orig_category":"Parfum And Cosmetica Gh",
    "sg:phone":"+31 15 256 1999",
    "sg:postcode":"2623 AJ",
    "sg:province":"Zuid-Holland",
    "wof:name":"Bioclin-V.N. Benelux Vof",
    "wof:placetype":"venue"
},
  "geometry": {"coordinates":[4.358963,51.987549],"type":"Point"}
}