{
  "type": "Feature",
  "properties": {
    "addr:full":"Stationspln 131 S Hertogenbosch Noord-Brabant 5211 BP",
    "addr:housenumber":"131",
    "addr:postcode":"5211 bp",
    "addr:street":"S",
    "iso:country":"NL",
    "sg:address":"Stationspln 131",
    "sg:city":"S Hertogenbosch",
    "sg:orig_category":"Kappers",
    "sg:phone":"+31 73 613 3816",
    "sg:postcode":"5211 BP",
    "sg:province":"Noord-Brabant",
    "wof:name":"Hees, Van",
    "wof:placetype":"venue"
},
  "geometry": {"coordinates":[5.2951188087,51.6904602051],"type":"Point"}
}