{
  "type": "Feature",
  "properties": {
    "addr:full":"Korte Veerstraat 20 Haarlem Noord-Holland 2011 CL",
    "addr:housenumber":"20",
    "addr:postcode":"2011",
    "addr:street":"Korte Veerstraat",
    "iso:country":"NL",
    "sg:address":"Korte Veerstraat 20",
    "sg:city":"Haarlem",
    "sg:orig_category":"Film-, Tv- And Videoproductie",
    "sg:phone":"+31 23 542 7292",
    "sg:postcode":"2011 CL",
    "sg:province":"Noord-Holland",
    "wof:name":"Magic Green Productions",
    "wof:placetype":"venue"
},
  "geometry": {"coordinates":[4.637512,52.379478],"type":"Point"}
}