{
  "type": "Feature",
  "properties": {
    "iso:country":"NL",
    "sg:address":"Lumeystr 11A",
    "sg:city":"Rotterdam",
    "sg:orig_category":"Fotojournalisten Freelance",
    "sg:phone":"+31 10 466 9932",
    "sg:postcode":"3039 ZM",
    "sg:province":"Zuid-Holland",
    "wof:name":"Czerwinski, S",
    "wof:placetype":"venue"
},
  "geometry": {"coordinates":[4.461944,51.928661],"type":"Point"}
}