{
  "type": "Feature",
  "properties": {
    "addr:full":"Hoogstraat 11 Wageningen Gelderland 6701 BJ",
    "addr:housenumber":"11",
    "addr:postcode":"6701 bj",
    "addr:street":"Hoogstraat;Gelderland",
    "iso:country":"NL",
    "sg:address":"Hoogstraat 11",
    "sg:city":"Wageningen",
    "sg:orig_category":"Huishoudapparatuur, Televisies And Radio'S",
    "sg:phone":"+31 317 418 770",
    "sg:postcode":"6701 BJ",
    "sg:province":"Gelderland",
    "wof:name":"Onderdelencentrum Jan Weernekers",
    "wof:placetype":"venue"
},
  "geometry": {"coordinates":[5.660976,51.964355],"type":"Point"}
}