{
  "type": "Feature",
  "properties": {
    "addr:full":"Boskrekel 39 Deventer Overijssel 7423 HA",
    "addr:housenumber":"39",
    "addr:postcode":"7423 ha",
    "addr:street":"Boskrekel",
    "iso:country":"NL",
    "sg:address":"Boskrekel 39",
    "sg:city":"Deventer",
    "sg:orig_category":"Sanitaire Artikelen",
    "sg:phone":"+31 570 654 817",
    "sg:postcode":"7423 HA",
    "sg:province":"Overijssel",
    "wof:name":"Naaijer",
    "wof:placetype":"venue"
},
  "geometry": {"coordinates":[6.203555,52.25304],"type":"Point"}
}