{
  "type": "Feature",
  "properties": {
    "addr:full":"Tymanshof 1 Assen Drenthe 9403 PK",
    "addr:housenumber":"1",
    "addr:postcode":"9403 pk",
    "addr:street":"Tymanshof",
    "iso:country":"NL",
    "sg:address":"Tymanshof 1",
    "sg:city":"Assen",
    "sg:orig_category":"Adviesbureaus Elektronica",
    "sg:phone":"+31 592 344 698",
    "sg:postcode":"9403 PK",
    "sg:province":"Drenthe",
    "sg:website":"http://www.smartconsult.nl",
    "wof:name":"Smartconsult",
    "wof:placetype":"venue"
},
  "geometry": {"coordinates":[6.575758,53.015842],"type":"Point"}
}