{
  "type": "Feature",
  "properties": {
    "addr:full":"Mercuriusplein 59 Berlicum North Brabant 5258 AX",
    "addr:housenumber":"59",
    "addr:postcode":"5258 ax",
    "addr:street":"Mercuriusplein",
    "iso:country":"NL",
    "sg:address":"Mercuriusplein 59",
    "sg:city":"Berlicum",
    "sg:orig_category":"Juweliers",
    "sg:phone":"+31 73 503 8747",
    "sg:postcode":"5258 AX",
    "sg:province":"North Brabant",
    "wof:name":"Dickerscheid Juwelier",
    "wof:placetype":"venue"
},
  "geometry": {"coordinates":[5.399435,51.678524],"type":"Point"}
}