{
  "type": "Feature",
  "properties": {
    "addr:full":"H Reinderswg 28 Pesse Drenthe 7933 TW",
    "addr:housenumber":"28",
    "addr:postcode":"7933 tw",
    "iso:country":"NL",
    "sg:address":"H Reinderswg 28",
    "sg:city":"Pesse",
    "sg:orig_category":"Fotografie Reclame En Mode",
    "sg:phone":"+31 528 242 219",
    "sg:postcode":"7933 TW",
    "sg:province":"Drenthe",
    "wof:name":"Rikkers, Guido",
    "wof:placetype":"venue"
},
  "geometry": {"coordinates":[6.47833,52.794991],"type":"Point"}
}