{
  "type": "Feature",
  "properties": {
    "addr:full":"Laan 1954 6 De Meern Utrecht 3454 CR",
    "addr:housenumber":"6",
    "addr:postcode":"3454 cr",
    "addr:street":"Laan 1954",
    "iso:country":"NL",
    "sg:address":"Laan 1954 6",
    "sg:city":"De Meern",
    "sg:classifiers":[
        {
            "category":"Education",
            "subcategory":"Preschool",
            "type":"Public Place"
        }
    ],
    "sg:phone":"+31 30 666 1901",
    "sg:postcode":"3454 CR",
    "sg:province":"Utrecht",
    "sg:tags":[
        "kleuteronderwijs",
        "basis-"
    ],
    "wof:name":"Basisschool Koningin Beatrix",
    "wof:placetype":"venue"
},
  "geometry": {"coordinates":[5.03752,52.078983],"type":"Point"}
}