{
  "type": "Feature",
  "properties": {
    "addr:full":"Aan D Greune Paol 15A Grevenbicht Limburg 6127 BH",
    "addr:housenumber":"15a",
    "addr:postcode":"6127 bh",
    "addr:street":"Aan D Greune Paol",
    "iso:country":"NL",
    "sg:address":"Aan D Greune Paol 15A",
    "sg:city":"Grevenbicht",
    "sg:classifiers":[
        {
            "category":"Food & Beverages",
            "subcategory":"Bakery",
            "type":"Retail Goods"
        }
    ],
    "sg:phone":"+31 46 486 0200",
    "sg:postcode":"6127 BH",
    "sg:province":"Limburg",
    "sg:tags":[
        "brood",
        "en",
        "banket"
    ],
    "wof:name":"Jos Puts",
    "wof:placetype":"venue"
},
  "geometry": {"coordinates":[5.774904,51.041405],"type":"Point"}
}