{
  "type": "Feature",
  "properties": {
    "addr:full":"Groensngl 11 Middelstum Groningen 9991 EB",
    "addr:housenumber":"11",
    "addr:postcode":"9991 eb",
    "addr:street":"Groensngl",
    "iso:country":"NL",
    "sg:address":"Groensngl 11",
    "sg:city":"Middelstum",
    "sg:orig_category":"Modevakscholen",
    "sg:phone":"+31 595 552 763",
    "sg:postcode":"9991 EB",
    "sg:province":"Groningen",
    "wof:name":"Tunica",
    "wof:placetype":"venue"
},
  "geometry": {"coordinates":[6.64458,53.344803],"type":"Point"}
}