{
  "type": "Feature",
  "properties": {
    "addr:full":"Polyanderweg 9 Heenvliet South Holland 3218 XT",
    "addr:housenumber":"9",
    "addr:postcode":"3218 xt",
    "addr:street":"Polyanderweg",
    "iso:country":"NL",
    "sg:address":"Polyanderweg 9",
    "sg:city":"Heenvliet",
    "sg:orig_category":"Verhuur Catering-, Feest- En Evenementbenodigdheden",
    "sg:phone":"+31 181 664 488",
    "sg:postcode":"3218 XT",
    "sg:province":"South Holland",
    "wof:name":"Bv Handelsbureau Nbp",
    "wof:placetype":"venue"
},
  "geometry": {"coordinates":[4.234897,51.862499],"type":"Point"}
}