{
  "type": "Feature",
  "properties": {
    "iso:country":"NL",
    "sg:address":"R Feithstr 15",
    "sg:city":"Hengelo Ov",
    "sg:classifiers":[
        {
            "category":"Food & Beverages",
            "subcategory":"Fruits & Vegetables",
            "type":"Retail Goods"
        }
    ],
    "sg:phone":"+31 53 434 0160",
    "sg:postcode":"7552 HT",
    "sg:province":"Overijssel",
    "sg:tags":[
        "en",
        "groenten"
    ],
    "wof:name":"Top Fruit Int Cv",
    "wof:placetype":"venue"
},
  "geometry": {"coordinates":[6.78971,52.266331],"type":"Point"}
}