{
  "type": "Feature",
  "properties": {
    "iso:country":"NL",
    "sg:address":"Voorstraat 2",
    "sg:city":"Goor",
    "sg:orig_category":"Huishoudapparatuur, Televisies And Radio'S",
    "sg:phone":"+31 547 272 958",
    "sg:postcode":"7471 BZ",
    "sg:province":"Overijssel",
    "wof:name":"Firma H. Reiners",
    "wof:placetype":"venue"
},
  "geometry": {"coordinates":[6.587316,52.236034],"type":"Point"}
}