{
  "type": "Feature",
  "properties": {
    "addr:full":"Ketelhuispln 7 Amsterdam Noord-Holland 1054 RD",
    "addr:housenumber":"7",
    "addr:postcode":"1054 rd",
    "addr:street":"Ketelhuispln",
    "iso:country":"NL",
    "sg:address":"Ketelhuispln 7",
    "sg:city":"Amsterdam",
    "sg:orig_category":"Verenigingen En Stichtingen",
    "sg:phone":"+31 20 685 2232",
    "sg:postcode":"1054 RD",
    "sg:province":"Noord-Holland",
    "wof:name":"Verblijfsrecht Migrantenvrouw",
    "wof:placetype":"venue"
},
  "geometry": {"coordinates":[4.870781,52.363956],"type":"Point"}
}