{
  "type": "Feature",
  "properties": {
    "addr:full":"Kortfoortstraat 64 Oss Noord-Brabant 5342 AG",
    "addr:housenumber":"64",
    "addr:postcode":"5342",
    "addr:street":"Kortfoortstraat",
    "iso:country":"NL",
    "sg:address":"Kortfoortstraat 64",
    "sg:city":"Oss",
    "sg:orig_category":"Verzekeringen",
    "sg:phone":"+31 412 623 671",
    "sg:postcode":"5342 AG",
    "sg:province":"Noord-Brabant",
    "wof:name":"Van Peufflik Assurantien",
    "wof:placetype":"venue"
},
  "geometry": {"coordinates":[-77.235214,38.312599],"type":"Point"}
}