{
  "type": "Feature",
  "properties": {
    "addr:full":"Meestersweg 4 Staphorst Overijssel 7951 BS",
    "addr:housenumber":"4",
    "addr:postcode":"7951 bs",
    "addr:street":"Meestersweg",
    "iso:country":"NL",
    "sg:address":"Meestersweg 4",
    "sg:city":"Staphorst",
    "sg:orig_category":"Autokeuringen",
    "sg:phone":"+31 522 461 208",
    "sg:postcode":"7951 BS",
    "sg:province":"Overijssel",
    "wof:name":"Firma Vogelzang",
    "wof:placetype":"venue"
},
  "geometry": {"coordinates":[6.208062,52.648918],"type":"Point"}
}