{
  "type": "Feature",
  "properties": {
    "addr:full":"R Spierstr 175 Hoofddorp Noord-Holland 2135 TS",
    "addr:housenumber":"175",
    "addr:postcode":"2135 ts",
    "iso:country":"NL",
    "sg:address":"R Spierstr 175",
    "sg:city":"Hoofddorp",
    "sg:orig_category":"Hypotheken",
    "sg:phone":"+31 23 562 9415",
    "sg:postcode":"2135 TS",
    "sg:province":"Noord-Holland",
    "wof:name":"Hulsman",
    "wof:placetype":"venue"
},
  "geometry": {"coordinates":[4.661609,52.293652],"type":"Point"}
}