{
  "type": "Feature",
  "properties": {
    "addr:full":"Damstraat 32 Utrecht Utrecht 3531 BV",
    "addr:housenumber":"32",
    "addr:postcode":"3531 bv",
    "addr:street":"Damstraat",
    "iso:country":"NL",
    "sg:address":"Damstraat 32",
    "sg:city":"Utrecht",
    "sg:orig_category":"Visspeciaalzaken",
    "sg:phone":"+31 30 293 0337",
    "sg:postcode":"3531 BV",
    "sg:province":"Utrecht",
    "wof:name":"R.G. De Vos Vishandel",
    "wof:placetype":"venue"
},
  "geometry": {"coordinates":[5.103544,52.091408],"type":"Point"}
}