{
  "type": "Feature",
  "properties": {
    "addr:full":"Lagestr 15A Wapenveld Gelderland 8191 LN",
    "addr:housenumber":"15a",
    "addr:postcode":"8191 ln",
    "addr:street":"Lagestr;Gelderland",
    "iso:country":"NL",
    "sg:address":"Lagestr 15A",
    "sg:city":"Wapenveld",
    "sg:classifiers":[
        {
            "category":"Retail",
            "subcategory":"Auto Repair",
            "type":"Services"
        }
    ],
    "sg:phone":"+31 38 447 0034",
    "sg:postcode":"8191 LN",
    "sg:province":"Gelderland",
    "sg:tags":[
        "garage"
    ],
    "wof:name":"Bredewolt",
    "wof:placetype":"venue"
},
  "geometry": {"coordinates":[6.079053,52.429905],"type":"Point"}
}