{
  "type": "Feature",
  "properties": {
    "addr:full":"Reinwardtstr 262 Amsterdam Noord-Holland 1093 HP",
    "addr:housenumber":"262",
    "addr:postcode":"1093 hp",
    "iso:country":"NL",
    "sg:address":"Reinwardtstr 262",
    "sg:city":"Amsterdam",
    "sg:orig_category":"Juweliers",
    "sg:phone":"+31 20 663 9213",
    "sg:postcode":"1093 HP",
    "sg:province":"Noord-Holland",
    "wof:name":"Lachman Juwelier",
    "wof:placetype":"venue"
},
  "geometry": {"coordinates":[4.928173,52.361107],"type":"Point"}
}