{
  "type": "Feature",
  "properties": {
    "iso:country":"NL",
    "sg:address":"Van Konijnenburgweg 51",
    "sg:city":"Bergen Op Zoom",
    "sg:orig_category":"Huishoudapparatuur, Televisies And Radio'S",
    "sg:phone":"+31 164 235 256",
    "sg:postcode":"4612 PL",
    "sg:province":"Noord-Brabant",
    "wof:name":"Mikro Electro Bv",
    "wof:placetype":"venue"
},
  "geometry": {"coordinates":[4.274144,51.493748],"type":"Point"}
}