{
  "type": "Feature",
  "properties": {
    "addr:full":"Van Konijnenburgweg 51 Bergen Op Zoom Noord-Brabant 4612 PL",
    "addr:housenumber":"51",
    "addr:postcode":"4612 pl",
    "addr:street":"Van Konijnenburgweg",
    "iso:country":"NL",
    "sg:address":"Van Konijnenburgweg 51",
    "sg:city":"Bergen Op Zoom",
    "sg:orig_category":"Huishoudapparatuur, Televisies And Radio'S",
    "sg:phone":"+31 164 235 256",
    "sg:postcode":"4612 PL",
    "sg:province":"Noord-Brabant",
    "wof:name":"Mikro Electro Bv",
    "wof:placetype":"venue"
},
  "geometry": {"coordinates":[4.274144,51.493748],"type":"Point"}
}