{
  "type": "Feature",
  "properties": {
    "addr:full":"Garderbroekerwg 121 Kootwykerbroek Gelderland 3774 JC",
    "addr:housenumber":"121",
    "addr:postcode":"3774 jc",
    "addr:street":"Kootwykerbroek Gelderland",
    "iso:country":"NL",
    "sg:address":"Garderbroekerwg 121",
    "sg:city":"Kootwykerbroek",
    "sg:orig_category":"Onderhoudswerken",
    "sg:phone":"+31 342 478 410",
    "sg:postcode":"3774 JC",
    "sg:province":"Gelderland",
    "wof:name":"Stroet, Henk Van De",
    "wof:placetype":"venue"
},
  "geometry": {"coordinates":[5.668881,52.165058],"type":"Point"}
}