{
  "type": "Feature",
  "properties": {
    "addr:full":"Swanendrift 10 Zwijndrecht Zuid-Holland 3332 RN",
    "addr:housenumber":"10",
    "addr:postcode":"3332 rn",
    "addr:street":"Swanendrift",
    "iso:country":"NL",
    "sg:address":"Swanendrift 10",
    "sg:city":"Zwijndrecht",
    "sg:orig_category":"Boekhouders",
    "sg:phone":"+31 78 612 5719",
    "sg:postcode":"3332 RN",
    "sg:province":"Zuid-Holland",
    "wof:name":"Molenaar",
    "wof:placetype":"venue"
},
  "geometry": {"coordinates":[4.646111,51.823364],"type":"Point"}
}