{
  "type": "Feature",
  "properties": {
    "addr:full":"Kerkwg 13 Voorhout South Holland 2215 KM",
    "addr:housenumber":"13",
    "addr:postcode":"2215 km",
    "addr:street":"Kerkwg",
    "iso:country":"NL",
    "sg:address":"Kerkwg 13",
    "sg:city":"Voorhout",
    "sg:orig_category":"Logopedisten",
    "sg:phone":"+31 252 224 111",
    "sg:postcode":"2215 KM",
    "sg:province":"South Holland",
    "wof:name":"Nieuwenhuys, C",
    "wof:placetype":"venue"
},
  "geometry": {"coordinates":[4.483435,52.219879],"type":"Point"}
}