{
  "type": "Feature",
  "properties": {
    "iso:country":"NL",
    "sg:address":"Dorpsstr 49",
    "sg:city":"Holten",
    "sg:orig_category":"Verzekeringen - Verzekeringskantoren",
    "sg:phone":"+31 548 362 178",
    "sg:postcode":"7451 BS",
    "sg:province":"Overijssel",
    "wof:name":"Bannink, G H",
    "wof:placetype":"venue"
},
  "geometry": {"coordinates":[6.418776,52.282917],"type":"Point"}
}