{
  "type": "Feature",
  "properties": {
    "addr:full":"Bloemendalstraat 25 Vaals Limburg 6291 CL",
    "addr:housenumber":"25",
    "addr:postcode":"6291",
    "addr:street":"Bloemendalstraat",
    "iso:country":"NL",
    "sg:address":"Bloemendalstraat 25",
    "sg:city":"Vaals",
    "sg:orig_category":"Schilderwerk",
    "sg:phone":"+31 43 306 2130",
    "sg:postcode":"6291 CL",
    "sg:province":"Limburg",
    "wof:name":"Schildersbedrijf J. Cohlst",
    "wof:placetype":"venue"
},
  "geometry": {"coordinates":[6.0153,50.772324],"type":"Point"}
}