{
  "type": "Feature",
  "properties": {
    "addr:full":"Braakwg 23 Helmond North Brabant 5708 JJ",
    "addr:housenumber":"23",
    "addr:postcode":"5708 jj",
    "addr:street":"Braakwg",
    "iso:country":"NL",
    "sg:address":"Braakwg 23",
    "sg:city":"Helmond",
    "sg:orig_category":"Kinderopvang",
    "sg:phone":"+31 492 532 740",
    "sg:postcode":"5708 JJ",
    "sg:province":"North Brabant",
    "wof:name":"Debberke, Kinderdagverblijf 'T",
    "wof:placetype":"venue"
},
  "geometry": {"coordinates":[5.610996,51.48246],"type":"Point"}
}