{
  "type": "Feature",
  "properties": {
    "iso:country":"NL",
    "sg:address":"Jupiterstraat 143",
    "sg:city":"Krommenie",
    "sg:orig_category":"Kinderopvang",
    "sg:phone":"+31 75 670 6261",
    "sg:postcode":"1562 WP",
    "sg:province":"North Holland",
    "wof:name":"Opvanggroep",
    "wof:placetype":"venue"
},
  "geometry": {"coordinates":[4.75169,52.500629],"type":"Point"}
}