{
  "type": "Feature",
  "properties": {
    "addr:full":"Wenckebachstraat 1 Beverwijk Noord-Holland 1951 JZ",
    "addr:housenumber":"1",
    "addr:postcode":"1951 jz",
    "addr:street":"Wenckebachstraat",
    "iso:country":"NL",
    "sg:address":"Wenckebachstraat 1",
    "sg:city":"Beverwijk",
    "sg:orig_category":"Pompen And Compressoren Fab",
    "sg:phone":"+31 251 211 017",
    "sg:postcode":"1951 JZ",
    "sg:province":"Noord-Holland",
    "wof:name":"Bobach Service Gmbh",
    "wof:placetype":"venue"
},
  "geometry": {"coordinates":[4.645905,52.472397],"type":"Point"}
}