{
  "type": "Feature",
  "properties": {
    "iso:country":"NL",
    "sg:address":"Spoorwegstr 48",
    "sg:city":"Arnhem",
    "sg:orig_category":"Architecten En Architectenbureaus",
    "sg:phone":"+31 26 446 1368",
    "sg:postcode":"6828 AS",
    "sg:province":"Gelderland",
    "wof:name":"Nexit",
    "wof:placetype":"venue"
},
  "geometry": {"coordinates":[5.915572,51.984882],"type":"Point"}
}