{
  "type": "Feature",
  "properties": {
    "addr:full":"Landstr 90-100 Bussum Noord-Holland 1401 ES",
    "addr:postcode":"90-100;1401 es",
    "addr:street":"Landstr",
    "iso:country":"NL",
    "sg:address":"Landstr 90-100",
    "sg:city":"Bussum",
    "sg:orig_category":"Banden",
    "sg:phone":"+31 35 691 4441",
    "sg:postcode":"1401 ES",
    "sg:province":"Noord-Holland",
    "sg:website":"http://www.kwik-fit.nl",
    "wof:name":"Kwik-Fit",
    "wof:placetype":"venue"
},
  "geometry": {"coordinates":[5.164634,52.277603],"type":"Point"}
}