{
  "type": "Feature",
  "properties": {
    "addr:full":"Ondermaat 64 Hardenberg Overijssel 7772 JD",
    "addr:housenumber":"64",
    "addr:postcode":"7772 jd",
    "addr:street":"Ondermaat",
    "iso:country":"NL",
    "sg:address":"Ondermaat 64",
    "sg:city":"Hardenberg",
    "sg:orig_category":"Administratie- En Boekhoudkantoren",
    "sg:phone":"+31 523 270 460",
    "sg:postcode":"7772 JD",
    "sg:province":"Overijssel",
    "wof:name":"Mulder",
    "wof:placetype":"venue"
},
  "geometry": {"coordinates":[6.634698,52.58572],"type":"Point"}
}