{
  "type": "Feature",
  "properties": {
    "iso:country":"NL",
    "sg:address":"Provincialewg 11",
    "sg:city":"Zaandam",
    "sg:orig_category":"Levensmiddelen - Fabrieken En Groothandel",
    "sg:phone":"+31 75 659 9111",
    "sg:postcode":"1506 MA",
    "sg:province":"Noord-Holland",
    "sg:website":"http://www.albertheijn.nl",
    "wof:name":"Albert Heijn Bv",
    "wof:placetype":"venue"
},
  "geometry": {"coordinates":[4.827435,52.424019],"type":"Point"}
}