{
  "type": "Feature",
  "properties": {
    "addr:full":"Soerelsewg 1 Heerde Gelderland 8181 AK",
    "addr:housenumber":"1",
    "addr:postcode":"8181 ak",
    "addr:street":"Soerelsewg;Gelderland",
    "iso:country":"NL",
    "sg:address":"Soerelsewg 1",
    "sg:city":"Heerde",
    "sg:orig_category":"Adviesbureaus Bedrijfsorganisatie",
    "sg:phone":"+31 578 696 812",
    "sg:postcode":"8181 AK",
    "sg:province":"Gelderland",
    "wof:name":"Grinwis Bv, Dr",
    "wof:placetype":"venue"
},
  "geometry": {"coordinates":[6.041162,52.388714],"type":"Point"}
}