{
  "type": "Feature",
  "properties": {
    "iso:country":"NL",
    "sg:address":"Koningsveld 77",
    "sg:city":"Delft",
    "sg:orig_category":"Adviesbureaus Bedrijfsorganisatie",
    "sg:phone":"+31 15 213 7688",
    "sg:postcode":"2628 LK",
    "sg:province":"Zuid-Holland",
    "wof:name":"Konincxvelt Consultancy",
    "wof:placetype":"venue"
},
  "geometry": {"coordinates":[4.363549,52.002857],"type":"Point"}
}