{
  "type": "Feature",
  "properties": {
    "addr:full":"Westerduinweg 34 Bentveld Noord-Holland 2116 VH",
    "addr:housenumber":"34",
    "addr:postcode":"2116 vh",
    "addr:street":"Westerduinweg",
    "iso:country":"NL",
    "sg:address":"Westerduinweg 34",
    "sg:city":"Bentveld",
    "sg:orig_category":"Boekhouders",
    "sg:phone":"+31 23 524 3301",
    "sg:postcode":"2116 VH",
    "sg:province":"Noord-Holland",
    "wof:name":"Advies- En Administratiekant Mr. H.Th. Katz",
    "wof:placetype":"venue"
},
  "geometry": {"coordinates":[4.572838,52.368763],"type":"Point"}
}