{
  "type": "Feature",
  "properties": {
    "addr:full":"Ryksstrwg 78A Hardegaryp Friesland 9254 DK",
    "addr:housenumber":"78a hardegaryp",
    "addr:postcode":"9254 dk",
    "addr:street":"Ryksstrwg",
    "iso:country":"NL",
    "sg:address":"Ryksstrwg 78A",
    "sg:city":"Hardegaryp",
    "sg:orig_category":"Artiesten/Gezelschappen",
    "sg:phone":"+31 511 477 473",
    "sg:postcode":"9254 DK",
    "sg:province":"Friesland",
    "wof:name":"Zwaag, Peter Van Der",
    "wof:placetype":"venue"
},
  "geometry": {"coordinates":[5.94131,53.215366],"type":"Point"}
}