{
  "type": "Feature",
  "properties": {
    "addr:full":"Overschiestr 176 Amsterdam Noord-Holland 1062 XK",
    "addr:housenumber":"176",
    "addr:postcode":"1062 xk",
    "iso:country":"NL",
    "sg:address":"Overschiestr 176",
    "sg:city":"Amsterdam",
    "sg:orig_category":"Grafische Bedrijven",
    "sg:phone":"+31 20 588 2680",
    "sg:postcode":"1062 XK",
    "sg:province":"Noord-Holland",
    "wof:name":"Jong, Repro De",
    "wof:placetype":"venue"
},
  "geometry": {"coordinates":[4.839422,52.344387],"type":"Point"}
}