{
  "type": "Feature",
  "properties": {
    "addr:full":"Westblaak 2 Rotterdam Zuid-Holland 3012 KK",
    "addr:housenumber":"2",
    "addr:postcode":"3012 kk",
    "addr:street":"Westblaak",
    "iso:country":"NL",
    "sg:address":"Westblaak 2",
    "sg:city":"Rotterdam",
    "sg:orig_category":"Ambassades And Consulaten",
    "sg:phone":"+31 10 413 2270",
    "sg:postcode":"3012 KK",
    "sg:province":"Zuid-Holland",
    "wof:name":"Consulaat Generaal Van Turkije",
    "wof:placetype":"venue"
},
  "geometry": {"coordinates":[4.479745,51.917328],"type":"Point"}
}