{
  "type": "Feature",
  "properties": {
    "iso:country":"NL",
    "sg:address":"V Knobelsdorffpln 121",
    "sg:city":"Drachten",
    "sg:orig_category":"Verenigingen En Stichtingen",
    "sg:phone":"+31 512 518 540",
    "sg:postcode":"9203 DH",
    "sg:province":"Provincie Friesland",
    "sg:website":"http://www.anbo.nl",
    "wof:name":"Anbo",
    "wof:placetype":"venue"
},
  "geometry": {"coordinates":[6.099,53.104458],"type":"Point"}
}