{
  "type": "Feature",
  "properties": {
    "addr:full":"V Knobelsdorffpln 121 Drachten Provincie Friesland 9203 DH",
    "addr:housenumber":"121",
    "addr:postcode":"9203 dh",
    "addr:street":"Provincie Friesland",
    "iso:country":"NL",
    "sg:address":"V Knobelsdorffpln 121",
    "sg:city":"Drachten",
    "sg:orig_category":"Verenigingen En Stichtingen",
    "sg:phone":"+31 512 518 540",
    "sg:postcode":"9203 DH",
    "sg:province":"Provincie Friesland",
    "sg:website":"http://www.anbo.nl",
    "wof:name":"Anbo",
    "wof:placetype":"venue"
},
  "geometry": {"coordinates":[6.099,53.104458],"type":"Point"}
}