{
  "type": "Feature",
  "properties": {
    "addr:full":"Eratostr 1 Rotterdam Zuid-Holland 3054 SJ",
    "addr:housenumber":"1",
    "addr:postcode":"3054",
    "addr:street":"Eratostr",
    "iso:country":"NL",
    "sg:address":"Eratostr 1",
    "sg:city":"Rotterdam",
    "sg:orig_category":"Fietsen En Bromfietsen",
    "sg:phone":"+31 10 418 1599",
    "sg:postcode":"3054 SJ",
    "sg:province":"Zuid-Holland",
    "wof:name":"Welle, C Van Der",
    "wof:placetype":"venue"
},
  "geometry": {"coordinates":[4.489769,51.961082],"type":"Point"}
}