{
  "type": "Feature",
  "properties": {
    "addr:full":"Beverwijkstraat 63 Amsterdam North Holland 1024 VL",
    "addr:housenumber":"63",
    "addr:postcode":"1024 vl",
    "addr:street":"Beverwijkstraat",
    "iso:country":"NL",
    "sg:address":"Beverwijkstraat 63",
    "sg:city":"Amsterdam",
    "sg:orig_category":"Wegen And Sportterreinen",
    "sg:phone":"+31 20 636 6423",
    "sg:postcode":"1024 VL",
    "sg:province":"North Holland",
    "wof:name":"E Dobbelaer",
    "wof:placetype":"venue"
},
  "geometry": {"coordinates":[4.9550590515,52.3927345276],"type":"Point"}
}