{
  "type": "Feature",
  "properties": {
    "addr:full":"Amsteldijk Noord 34 Amstelveen Noord-Holland 1184 TD",
    "addr:housenumber":"34",
    "addr:postcode":"1184 td",
    "addr:street":"Amsteldijk Noord",
    "iso:country":"NL",
    "sg:address":"Amsteldijk Noord 34",
    "sg:city":"Amstelveen",
    "sg:orig_category":"Public Relationbureaus",
    "sg:phone":"+31 20 496 4441",
    "sg:postcode":"1184 TD",
    "sg:province":"Noord-Holland",
    "wof:name":"Interfootball Bv",
    "wof:placetype":"venue"
},
  "geometry": {"coordinates":[4.899792,52.301762],"type":"Point"}
}