{
  "type": "Feature",
  "properties": {
    "addr:full":"Hogewg 11 Wyk Aan Zee Noord-Holland 1949 AW",
    "addr:housenumber":"11",
    "addr:postcode":"zee;1949 aw",
    "addr:street":"Hogewg",
    "iso:country":"NL",
    "sg:address":"Hogewg 11",
    "sg:city":"Wyk Aan Zee",
    "sg:orig_category":"Adviesbureaus Bedrijfsorganisatie",
    "sg:phone":"+31 251 374 173",
    "sg:postcode":"1949 AW",
    "sg:province":"Noord-Holland",
    "sg:website":"HTTP://www.concorde.nu",
    "wof:name":"Concorde Bv",
    "wof:placetype":"venue"
},
  "geometry": {"coordinates":[4.594696,52.491993],"type":"Point"}
}