{
  "type": "Feature",
  "properties": {
    "addr:full":"Abraham Kuypersingel 57 Zwijndrecht South Holland 3332 HB",
    "addr:housenumber":"57",
    "addr:postcode":"3332 hb",
    "addr:street":"Abraham Kuypersingel",
    "iso:country":"NL",
    "sg:address":"Abraham Kuypersingel 57",
    "sg:city":"Zwijndrecht",
    "sg:orig_category":"Bedrijfs- And Managementsconsultants",
    "sg:phone":"+31 78 612 1153",
    "sg:postcode":"3332 HB",
    "sg:province":"South Holland",
    "wof:name":"Van Ooijen Management Support",
    "wof:placetype":"venue"
},
  "geometry": {"coordinates":[4.65944,51.826717],"type":"Point"}
}