{
  "type": "Feature",
  "properties": {
    "addr:full":"J Heinsstr 24 S Hertogenbosch North Brabant 5211 TD",
    "addr:housenumber":"24",
    "addr:postcode":"5211 td",
    "addr:street":"S Hertogenbosch",
    "iso:country":"NL",
    "sg:address":"J Heinsstr 24",
    "sg:city":"S Hertogenbosch",
    "sg:classifiers":[
        {
            "category":"Professional",
            "subcategory":"Management & Consulting",
            "type":"Services"
        }
    ],
    "sg:phone":"+31 73 612 3342",
    "sg:postcode":"5211 TD",
    "sg:province":"North Brabant",
    "sg:tags":[
        "relation",
        "adviesbureaus",
        "public"
    ],
    "wof:name":"Nieuwenhuizen",
    "wof:placetype":"venue"
},
  "geometry": {"coordinates":[5.302833,51.69305],"type":"Point"}
}