{
  "type": "Feature",
  "properties": {
    "addr:full":"Zyde 11 Boskoop Zuid-Holland 2771 EJ",
    "addr:housenumber":"11",
    "addr:postcode":"2771 ej",
    "addr:street":"Zyde",
    "iso:country":"NL",
    "sg:address":"Zyde 11",
    "sg:city":"Boskoop",
    "sg:orig_category":"Zalenverhuur",
    "sg:phone":"+31 172 214 075",
    "sg:postcode":"2771 EJ",
    "sg:province":"Zuid-Holland",
    "wof:name":"Loods, De",
    "wof:placetype":"venue"
},
  "geometry": {"coordinates":[4.657295,52.074478],"type":"Point"}
}