{
  "type": "Feature",
  "properties": {
    "iso:country":"NL",
    "sg:address":"Beatrixln 40",
    "sg:city":"Reeuwyk",
    "sg:classifiers":[
        {
            "category":"Food & Beverages",
            "subcategory":"Fruits & Vegetables",
            "type":"Retail Goods"
        }
    ],
    "sg:phone":"+31 182 395 974",
    "sg:postcode":"2811 LX",
    "sg:province":"Zuid-Holland",
    "sg:tags":[
        "en",
        "groenten"
    ],
    "wof:name":"Bron, L A",
    "wof:placetype":"venue"
},
  "geometry": {"coordinates":[4.688517,52.057495],"type":"Point"}
}