{
  "type": "Feature",
  "properties": {
    "iso:country":"NL",
    "sg:address":"Stokkumsewg 15",
    "sg:city":"S Heerenberg",
    "sg:orig_category":"Graveerbedrijven",
    "sg:phone":"+31 314 661 870",
    "sg:postcode":"7041 BT",
    "sg:province":"North Rhine-Westphalia",
    "wof:name":"Klaasing - Elkerbout",
    "wof:placetype":"venue"
},
  "geometry": {"coordinates":[6.24454,51.877308],"type":"Point"}
}