{
  "type": "Feature",
  "properties": {
    "addr:full":"Beethovenlaan 99 'S Gravenhage Zuid-Holland 2551 KB",
    "addr:housenumber":"99",
    "addr:postcode":"2551 kb",
    "addr:street":"Beethovenlaan;' S",
    "iso:country":"NL",
    "sg:address":"Beethovenlaan 99",
    "sg:city":"'S Gravenhage",
    "sg:orig_category":"Boekhouders",
    "sg:phone":"+31 70 368 4729",
    "sg:postcode":"2551 KB",
    "sg:province":"Zuid-Holland",
    "wof:name":"Administratie- En Belastingadv.Buro C. M",
    "wof:placetype":"venue"
},
  "geometry": {"coordinates":[4.228329,52.058205],"type":"Point"}
}