{
  "type": "Feature",
  "properties": {
    "iso:country":"NL",
    "sg:address":"Assumburg 8",
    "sg:city":"Vlissingen",
    "sg:orig_category":"Voetbalverenigingen",
    "sg:phone":"+31 118 471 945",
    "sg:postcode":"4385 EE",
    "sg:province":"Zeeland",
    "wof:name":"Jong Ambon",
    "wof:placetype":"venue"
},
  "geometry": {"coordinates":[3.569246,51.463791],"type":"Point"}
}