{
  "type": "Feature",
  "properties": {
    "addr:full":"Langstraat 71 Wassenaar Zuid-Holland 2242  K",
    "addr:housenumber":"71;2242",
    "addr:postcode":"k",
    "addr:street":"Langstraat",
    "iso:country":"NL",
    "sg:address":"Langstraat 71",
    "sg:city":"Wassenaar",
    "sg:orig_category":"Boekenuitgeverijen",
    "sg:phone":"+31 70 511 3978",
    "sg:postcode":"2242  K",
    "sg:province":"Zuid-Holland",
    "wof:name":"Bruna",
    "wof:placetype":"venue"
},
  "geometry": {"coordinates":[4.394354,52.143677],"type":"Point"}
}