{
  "type": "Feature",
  "properties": {
    "iso:country":"NL",
    "sg:address":"Ijsselstraat 36",
    "sg:city":"Velp Gld",
    "sg:orig_category":"Bloemen And Planten",
    "sg:phone":"+31 26 364 1236",
    "sg:postcode":"6882 LG",
    "sg:province":"Gelderland",
    "wof:name":"De Bloemenhal",
    "wof:placetype":"venue"
},
  "geometry": {"coordinates":[5.97301,51.99131],"type":"Point"}
}