{
  "type": "Feature",
  "properties": {
    "addr:full":"Kissel 52 Heerlen Limburg 6416 AC",
    "addr:housenumber":"52",
    "addr:postcode":"6416 ac",
    "addr:street":"Kissel",
    "iso:country":"NL",
    "sg:address":"Kissel 52",
    "sg:city":"Heerlen",
    "sg:orig_category":"Goederenvervoer Over De Weg",
    "sg:phone":"+31 45 570 8511",
    "sg:postcode":"6416 AC",
    "sg:province":"Limburg",
    "wof:name":"Van De Graaf Trans",
    "wof:placetype":"venue"
},
  "geometry": {"coordinates":[6.00174,50.889126],"type":"Point"}
}