{
  "type": "Feature",
  "properties": {
    "addr:full":"Geitenkamp 1-5 Arnhem Gelderland 6823 HC",
    "addr:housenumber":"1-5",
    "addr:postcode":"6823 hc",
    "addr:street":"Geitenkamp",
    "iso:country":"NL",
    "sg:address":"Geitenkamp 1-5",
    "sg:city":"Arnhem",
    "sg:orig_category":"Zonweringen",
    "sg:phone":"+31 26 442 4910",
    "sg:postcode":"6823 HC",
    "sg:province":"Gelderland",
    "sg:website":"http://www.boerma-arnhem.nl",
    "wof:name":"Boerma Woning- En Projectinricht",
    "wof:placetype":"venue"
},
  "geometry": {"coordinates":[5.941538,52.001133],"type":"Point"}
}