{
  "type": "Feature",
  "properties": {
    "iso:country":"NL",
    "sg:address":"Rondwg 10",
    "sg:city":"Wezep",
    "sg:orig_category":"Autopoetsbedrijven",
    "sg:phone":"+31 38 376 0260",
    "sg:postcode":"8091 XB",
    "sg:province":"Gelderland",
    "wof:name":"Schaftenaar",
    "wof:placetype":"venue"
},
  "geometry": {"coordinates":[6.00782,52.473801],"type":"Point"}
}