{
  "type": "Feature",
  "properties": {
    "addr:full":"Rapenburg 56Hs Amsterdam North Holland 1011 TZ",
    "addr:housenumber":"56hs",
    "addr:postcode":"1011 tz",
    "addr:street":"Rapenburg",
    "iso:country":"NL",
    "sg:address":"Rapenburg 56Hs",
    "sg:city":"Amsterdam",
    "sg:orig_category":"Kinderopvang Behalve Thuis",
    "sg:phone":"+31 20 624 6213",
    "sg:postcode":"1011 TZ",
    "sg:province":"North Holland",
    "wof:name":"Stichting De Stampertjes Halve Dagopvang",
    "wof:placetype":"venue"
},
  "geometry": {"coordinates":[4.908634,52.371094],"type":"Point"}
}