{
  "type": "Feature",
  "properties": {
    "addr:full":"Pr Irenestr 8 Oisterwyk Noord-Brabant 5061 TK",
    "addr:housenumber":"8",
    "addr:postcode":"5061 tk",
    "addr:street":"Oisterwyk",
    "iso:country":"NL",
    "sg:address":"Pr Irenestr 8",
    "sg:city":"Oisterwyk",
    "sg:orig_category":"Bloemen En Planten - Decoratie",
    "sg:phone":"+31 6 55331887",
    "sg:postcode":"5061 TK",
    "sg:province":"Noord-Brabant",
    "wof:name":"Massuger",
    "wof:placetype":"venue"
},
  "geometry": {"coordinates":[5.1821,51.57653],"type":"Point"}
}