{
  "type": "Feature",
  "properties": {
    "addr:full":"H Treubln 1 Laren Nh Noord-Holland 1251 CG",
    "addr:housenumber":"1",
    "addr:postcode":"1251 cg",
    "iso:country":"NL",
    "sg:address":"H Treubln 1",
    "sg:city":"Laren Nh",
    "sg:orig_category":"Elektronica - Ontwikkeling En Groothandel",
    "sg:phone":"+31 35 531 6800",
    "sg:postcode":"1251 CG",
    "sg:province":"Noord-Holland",
    "wof:name":"Tetru Bv",
    "wof:placetype":"venue"
},
  "geometry": {"coordinates":[5.22387,52.256741],"type":"Point"}
}