{
  "type": "Feature",
  "properties": {
    "iso:country":"NL",
    "sg:address":"Laat 153",
    "sg:city":"Alkmaar",
    "sg:orig_category":"Opticiens",
    "sg:phone":"+31 72 520 4755",
    "sg:postcode":"1811 EE",
    "sg:province":"Noord-Holland",
    "sg:website":"http://www.specsavers.nl",
    "wof:name":"Specsavers",
    "wof:placetype":"venue"
},
  "geometry": {"coordinates":[4.7473611832,52.6302642822],"type":"Point"}
}