{
  "type": "Feature",
  "properties": {
    "addr:full":"Bakkerstr 54 Arnhem Gelderland 6811 EJ",
    "addr:housenumber":"54",
    "addr:postcode":"6811 ej",
    "addr:street":"Bakkerstr",
    "iso:country":"NL",
    "sg:address":"Bakkerstr 54",
    "sg:city":"Arnhem",
    "sg:orig_category":"Zonnebank- En Solariumcentra",
    "sg:phone":"+31 26 445 8657",
    "sg:postcode":"6811 EJ",
    "sg:province":"Gelderland",
    "wof:name":"Ayk",
    "wof:placetype":"venue"
},
  "geometry": {"coordinates":[5.908111,51.979916],"type":"Point"}
}