{
  "type": "Feature",
  "properties": {
    "addr:full":"Industrieln 17 Asten Noord-Brabant 5721 BC",
    "addr:housenumber":"17",
    "addr:postcode":"5721 bc",
    "addr:street":"Industrieln",
    "iso:country":"NL",
    "sg:address":"Industrieln 17",
    "sg:city":"Asten",
    "sg:orig_category":"Pluimveeslachterijen",
    "sg:phone":"+31 493 697 815",
    "sg:postcode":"5721 BC",
    "sg:province":"Noord-Brabant",
    "wof:name":"Chi Pro Bv",
    "wof:placetype":"venue"
},
  "geometry": {"coordinates":[5.74422,51.408623],"type":"Point"}
}