{
  "type": "Feature",
  "properties": {
    "addr:full":"Hasker Utgongen 9 Oudehaske Friesland 8465 SJ",
    "addr:housenumber":"9",
    "addr:postcode":"8465",
    "addr:street":"Hasker Utgongen",
    "iso:country":"NL",
    "sg:address":"Hasker Utgongen 9",
    "sg:city":"Oudehaske",
    "sg:orig_category":"Goederenvervoer Over De Weg",
    "sg:phone":"+31 513 677 459",
    "sg:postcode":"8465 SJ",
    "sg:province":"Friesland",
    "wof:name":"Transportbedrijf A. Berger Vof",
    "wof:placetype":"venue"
},
  "geometry": {"coordinates":[5.872657,52.958748],"type":"Point"}
}