{
  "type": "Feature",
  "properties": {
    "iso:country":"NL",
    "sg:address":"Verloren Engh 7",
    "sg:city":"Blaricum",
    "sg:orig_category":"Bedrijfs- And Managementsconsultants",
    "sg:phone":"+31 35 531 7287",
    "sg:postcode":"1261 CP",
    "sg:province":"Noord-Holland",
    "wof:name":"D.C. Geest Management Consulting Service",
    "wof:placetype":"venue"
},
  "geometry": {"coordinates":[5.233505,52.270596],"type":"Point"}
}