{
  "type": "Feature",
  "properties": {
    "addr:full":"Koperwiek 7 Soest Utrecht 3766 AM",
    "addr:housenumber":"7",
    "addr:postcode":"3766",
    "addr:street":"Koperwiek",
    "iso:country":"NL",
    "sg:address":"Koperwiek 7",
    "sg:city":"Soest",
    "sg:orig_category":"Adviesbureaus Bedrijfsorganisatie",
    "sg:phone":"+31 35 601 9755",
    "sg:postcode":"3766 AM",
    "sg:province":"Utrecht",
    "wof:name":"Phelan Bv",
    "wof:placetype":"venue"
},
  "geometry": {"coordinates":[5.289738,52.163574],"type":"Point"}
}