{
  "type": "Feature",
  "properties": {
    "addr:full":"Marswg 15A Dalfsen NL.08 7722 MB",
    "addr:housenumber":"15a;nl.08",
    "addr:postcode":"7722 mb",
    "addr:street":"Marswg",
    "iso:country":"NL",
    "sg:address":"Marswg 15A",
    "sg:city":"Dalfsen",
    "sg:orig_category":"Bedrijfsopleidingen",
    "sg:phone":"+31 529 402 500",
    "sg:postcode":"7722 MB",
    "sg:province":"NL.08",
    "wof:name":"Bei Nederland",
    "wof:placetype":"venue"
},
  "geometry": {"coordinates":[6.213413,52.472336],"type":"Point"}
}