{
  "type": "Feature",
  "properties": {
    "addr:full":"Nieuwstr 94 Kerkrade Limburg 6462 GN",
    "addr:housenumber":"94",
    "addr:postcode":"6462 gn",
    "addr:street":"Nieuwstr",
    "iso:country":"NL",
    "sg:address":"Nieuwstr 94",
    "sg:city":"Kerkrade",
    "sg:orig_category":"Fotoreportages",
    "sg:phone":"+31 45 546 2789",
    "sg:postcode":"6462 GN",
    "sg:province":"Limburg",
    "wof:name":"Scala, La",
    "wof:placetype":"venue"
},
  "geometry": {"coordinates":[6.059685,50.863773],"type":"Point"}
}