{
  "type": "Feature",
  "properties": {
    "iso:country":"NL",
    "sg:address":"Meester Lokstraat 9",
    "sg:city":"Ravenswoud",
    "sg:orig_category":"Boekhouders",
    "sg:phone":"+31 516 433 785",
    "sg:postcode":"8427 RC",
    "sg:province":"Provincie Friesland",
    "wof:name":"I.M. Volk",
    "wof:placetype":"venue"
},
  "geometry": {"coordinates":[6.376202,52.960732],"type":"Point"}
}