{
  "type": "Feature",
  "properties": {
    "addr:full":"Sint Antoniusstraat 7 Baexem Limburg 6095 AK",
    "addr:housenumber":"7",
    "addr:postcode":"6095 ak",
    "addr:street":"Sint Antoniusstraat",
    "iso:country":"NL",
    "sg:address":"Sint Antoniusstraat 7",
    "sg:city":"Baexem",
    "sg:orig_category":"Metaalbekleding And -Behandeling",
    "sg:phone":"+31 475 451 495",
    "sg:postcode":"6095 AK",
    "sg:province":"Limburg",
    "wof:name":"Sematec Metaalbewerking Bv",
    "wof:placetype":"venue"
},
  "geometry": {"coordinates":[5.885061,51.22633],"type":"Point"}
}