{
  "type": "Feature",
  "properties": {
    "iso:country":"NL",
    "sg:address":"Vondelln 242",
    "sg:city":"Groningen",
    "sg:orig_category":"Autorijscholen",
    "sg:phone":"+31 50 526 0784",
    "sg:postcode":"9721 LL",
    "sg:province":"Groningen",
    "wof:name":"Langhout Autorijschool",
    "wof:placetype":"venue"
},
  "geometry": {"coordinates":[6.57067,53.195999],"type":"Point"}
}