{
  "type": "Feature",
  "properties": {
    "addr:full":"Groeneweg 27 Gouda South Holland 2801 ZA",
    "addr:housenumber":"27",
    "addr:postcode":"2801",
    "addr:street":"Groeneweg",
    "iso:country":"NL",
    "sg:address":"Groeneweg 27",
    "sg:city":"Gouda",
    "sg:classifiers":[
        {
            "category":"Education",
            "subcategory":"Preschool",
            "type":"Public Place"
        }
    ],
    "sg:phone":"+31 182 519 706",
    "sg:postcode":"2801 ZA",
    "sg:province":"South Holland",
    "sg:tags":[
        "kleuteronderwijs",
        "basis-"
    ],
    "wof:name":"Casimirschool",
    "wof:placetype":"venue"
},
  "geometry": {"coordinates":[4.7138857841,52.0107803345],"type":"Point"}
}