{
  "type": "Feature",
  "properties": {
    "addr:full":"Poeldk 13 Rypwetering Zuid-Holland 2375 NG",
    "addr:housenumber":"13",
    "addr:postcode":"2375 ng",
    "addr:street":"Poeldk",
    "iso:country":"NL",
    "sg:address":"Poeldk 13",
    "sg:city":"Rypwetering",
    "sg:orig_category":"Jachthavens - Jachtwerven",
    "sg:phone":"+31 71 501 8279",
    "sg:postcode":"2375 NG",
    "sg:province":"Zuid-Holland",
    "wof:name":"Ade, De",
    "wof:placetype":"venue"
},
  "geometry": {"coordinates":[4.587279,52.201023],"type":"Point"}
}