{
  "type": "Feature",
  "properties": {
    "addr:full":"A.M. De Jongstraat 26 Zegge North Brabant 4735 BW",
    "addr:housenumber":"26",
    "addr:postcode":"4735 bw",
    "addr:street":"A.M. De Jongstraat",
    "iso:country":"NL",
    "sg:address":"A.M. De Jongstraat 26",
    "sg:city":"Zegge",
    "sg:orig_category":"Bloemen And Planten",
    "sg:phone":"+31 165 539 258",
    "sg:postcode":"4735 BW",
    "sg:province":"North Brabant",
    "wof:name":"Roseanne",
    "wof:placetype":"venue"
},
  "geometry": {"coordinates":[4.519143,51.558887],"type":"Point"}
}