{
  "type": "Feature",
  "properties": {
    "addr:full":"Kapberg 4 Wognum Noord-Holland 1687 TD",
    "addr:housenumber":"4",
    "addr:postcode":"1687 td",
    "addr:street":"Kapberg",
    "iso:country":"NL",
    "sg:address":"Kapberg 4",
    "sg:city":"Wognum",
    "sg:orig_category":"Kunstnijverheidsartikelen - Fabrieken En Groothandel",
    "sg:phone":"+31 229 873 572",
    "sg:postcode":"1687 TD",
    "sg:province":"Noord-Holland",
    "wof:name":"African Beauty, The",
    "wof:placetype":"venue"
},
  "geometry": {"coordinates":[5.020307,52.681625],"type":"Point"}
}