{
  "type": "Feature",
  "properties": {
    "addr:full":"Lariksln 14 Leusden Utrecht 3833 AM",
    "addr:housenumber":"14",
    "addr:postcode":"3833",
    "addr:street":"Lariksln",
    "iso:country":"NL",
    "sg:address":"Lariksln 14",
    "sg:city":"Leusden",
    "sg:orig_category":"Fitnesscentra",
    "sg:phone":"+31 33 494 6409",
    "sg:postcode":"3833 AM",
    "sg:province":"Utrecht",
    "sg:website":"http://www.theomeijersport.nl",
    "wof:name":"Theo Meijer Sport",
    "wof:placetype":"venue"
},
  "geometry": {"coordinates":[5.42959,52.131248],"type":"Point"}
}