{
  "type": "Feature",
  "properties": {
    "iso:country":"NL",
    "sg:address":"Statendamweg 48",
    "sg:city":"Oosterhout Nb",
    "sg:orig_category":"Goederenvervoer Over De Weg",
    "sg:phone":"+31 162 454 037",
    "sg:postcode":"4905 AE",
    "sg:province":"North Brabant",
    "wof:name":"A. Taks-Hermans",
    "wof:placetype":"venue"
},
  "geometry": {"coordinates":[4.851151,51.649349],"type":"Point"}
}