{
  "type": "Feature",
  "properties": {
    "iso:country":"NL",
    "sg:address":"Larensewg 72",
    "sg:city":"Hilversum",
    "sg:orig_category":"Autorijscholen",
    "sg:phone":"+31 35 685 2637",
    "sg:postcode":"1222 HK",
    "sg:province":"Noord-Holland",
    "wof:name":"Bert Vuijst",
    "wof:placetype":"venue"
},
  "geometry": {"coordinates":[5.190849,52.233173],"type":"Point"}
}