{
  "type": "Feature",
  "properties": {
    "addr:full":"Schootsestraat 148 Eindhoven Noord-Brabant 5616 RH",
    "addr:housenumber":"148",
    "addr:postcode":"5616 rh",
    "addr:street":"Schootsestraat",
    "iso:country":"NL",
    "sg:address":"Schootsestraat 148",
    "sg:city":"Eindhoven",
    "sg:orig_category":"Metaalwerken",
    "sg:phone":"+31 40 251 1110",
    "sg:postcode":"5616 RH",
    "sg:province":"Noord-Brabant",
    "wof:name":"Zonwering En Rolluiken Tielemans Bv",
    "wof:placetype":"venue"
},
  "geometry": {"coordinates":[5.455217,51.442661],"type":"Point"}
}