{
  "type": "Feature",
  "properties": {
    "addr:full":"Hogeweg 99 Venlo Limburg 5914 BC",
    "addr:housenumber":"99",
    "addr:postcode":"5914 bc",
    "addr:street":"Hogeweg",
    "iso:country":"NL",
    "sg:address":"Hogeweg 99",
    "sg:city":"Venlo",
    "sg:orig_category":"Maatschappelijk Werk",
    "sg:phone":"+31 77 355 0222",
    "sg:postcode":"5914 BC",
    "sg:province":"Limburg",
    "wof:name":"Riagg Noord Limburg",
    "wof:placetype":"venue"
},
  "geometry": {"coordinates":[6.1742,51.377682],"type":"Point"}
}