{
  "type": "Feature",
  "properties": {
    "addr:full":"Hoogewg 54C Heiloo Noord-Holland 1851 PJ",
    "addr:housenumber":"54c",
    "addr:postcode":"1851 pj",
    "addr:street":"Hoogewg",
    "iso:country":"NL",
    "sg:address":"Hoogewg 54C",
    "sg:city":"Heiloo",
    "sg:orig_category":"Betonwerken",
    "sg:phone":"+31 72 515 6187",
    "sg:postcode":"1851 PJ",
    "sg:province":"Noord-Holland",
    "wof:name":"Berenbroek & Buur Bv",
    "wof:placetype":"venue"
},
  "geometry": {"coordinates":[4.694585,52.585567],"type":"Point"}
}