{
  "type": "Feature",
  "properties": {
    "iso:country":"NL",
    "sg:address":"Hoogewg 54C",
    "sg:city":"Heiloo",
    "sg:orig_category":"Betonwerken",
    "sg:phone":"+31 72 515 6187",
    "sg:postcode":"1851 PJ",
    "sg:province":"Noord-Holland",
    "wof:name":"Berenbroek & Buur Bv",
    "wof:placetype":"venue"
},
  "geometry": {"coordinates":[4.694585,52.585567],"type":"Point"}
}