{
  "type": "Feature",
  "properties": {
    "addr:full":"Oranjestr 6 Noord Scharwoude Noord-Holland 1723 MP",
    "addr:housenumber":"6",
    "addr:postcode":"1723 mp",
    "addr:street":"Oranjestr",
    "iso:country":"NL",
    "sg:address":"Oranjestr 6",
    "sg:city":"Noord Scharwoude",
    "sg:orig_category":"Koeltechniek",
    "sg:phone":"+31 226 318 044",
    "sg:postcode":"1723 MP",
    "sg:province":"Noord-Holland",
    "wof:name":"Witte Bv",
    "wof:placetype":"venue"
},
  "geometry": {"coordinates":[4.81024,52.698441],"type":"Point"}
}