{
  "type": "Feature",
  "properties": {
    "addr:full":"Oranjerie 103 Apeldoorn Gelderland 7311 WD",
    "addr:housenumber":"103",
    "addr:postcode":"7311",
    "addr:street":"Oranjerie;Gelderland",
    "iso:country":"NL",
    "sg:address":"Oranjerie 103",
    "sg:city":"Apeldoorn",
    "sg:orig_category":"Verlichting And Huishoudartikelen",
    "sg:phone":"+31 55 578 9558",
    "sg:postcode":"7311 WD",
    "sg:province":"Gelderland",
    "wof:name":"Lampenier Apeldoorn",
    "wof:placetype":"venue"
},
  "geometry": {"coordinates":[5.961812,52.212845],"type":"Point"}
}