{
  "type": "Feature",
  "properties": {
    "addr:full":"Vinkeslag 13 Boskoop Zuid-Holland 2771 KD",
    "addr:housenumber":"13",
    "addr:postcode":"2771 kd",
    "addr:street":"Vinkeslag",
    "iso:country":"NL",
    "sg:address":"Vinkeslag 13",
    "sg:city":"Boskoop",
    "sg:orig_category":"Honden- En Kattentrimsalons",
    "sg:phone":"+31 172 216 445",
    "sg:postcode":"2771 KD",
    "sg:province":"Zuid-Holland",
    "wof:name":"Hoogerdijk, Janneke",
    "wof:placetype":"venue"
},
  "geometry": {"coordinates":[4.642128,52.065033],"type":"Point"}
}