{
  "type": "Feature",
  "properties": {
    "addr:full":"Scheiding 35 Opende Groningen 9865 VB",
    "addr:housenumber":"35",
    "addr:postcode":"9865 vb",
    "addr:street":"Scheiding",
    "iso:country":"NL",
    "sg:address":"Scheiding 35",
    "sg:city":"Opende",
    "sg:orig_category":"Huizensloop And Bouwrijp Maken",
    "sg:phone":"+31 512 361 464",
    "sg:postcode":"9865 VB",
    "sg:province":"Groningen",
    "wof:name":"Handels- En Loonbedrijf P.H. Pama",
    "wof:placetype":"venue"
},
  "geometry": {"coordinates":[6.178444,53.168308],"type":"Point"}
}