{
  "type": "Feature",
  "properties": {
    "addr:full":"Kreiel 3 Wintelre North Brabant 5513 NW",
    "addr:housenumber":"3",
    "addr:postcode":"5513 nw",
    "addr:street":"Kreiel",
    "iso:country":"NL",
    "sg:address":"Kreiel 3",
    "sg:city":"Wintelre",
    "sg:orig_category":"Bungalowparken And Vakantiedorpen",
    "sg:phone":"+31 40 205 1567",
    "sg:postcode":"5513 NW",
    "sg:province":"North Brabant",
    "wof:name":"Kamphuis Den Hop",
    "wof:placetype":"venue"
},
  "geometry": {"coordinates":[5.318867,51.44453],"type":"Point"}
}