{
  "type": "Feature",
  "properties": {
    "iso:country":"NL",
    "sg:address":"Boven Oosterdiep 145",
    "sg:city":"Veendam",
    "sg:orig_category":"Juweliers",
    "sg:phone":"+31 598 612 697",
    "sg:postcode":"9641 JR",
    "sg:province":"Groningen",
    "wof:name":"H.B. Kerkhof",
    "wof:placetype":"venue"
},
  "geometry": {"coordinates":[6.876163,53.101292],"type":"Point"}
}