{
  "type": "Feature",
  "properties": {
    "addr:full":"Hinkert 2 Nederweert Limburg 6031 GS",
    "addr:housenumber":"2",
    "addr:postcode":"6031 gs",
    "addr:street":"Hinkert",
    "iso:country":"NL",
    "sg:address":"Hinkert 2",
    "sg:city":"Nederweert",
    "sg:orig_category":"Artsen And Specialisten",
    "sg:phone":"+31 495 633 345",
    "sg:postcode":"6031 GS",
    "sg:province":"Limburg",
    "wof:name":"E. Heemstra",
    "wof:placetype":"venue"
},
  "geometry": {"coordinates":[5.741461,51.286537],"type":"Point"}
}