{
  "type": "Feature",
  "properties": {
    "addr:full":"Leimuidenstr 32 Amsterdam North Holland 1059 EJ",
    "addr:housenumber":"32",
    "addr:postcode":"1059 ej",
    "addr:street":"Leimuidenstr",
    "iso:country":"NL",
    "sg:address":"Leimuidenstr 32",
    "sg:city":"Amsterdam",
    "sg:orig_category":"Verzekeringen - Verzekeringskantoren",
    "sg:phone":"+31 20 617 3224",
    "sg:postcode":"1059 EJ",
    "sg:province":"North Holland",
    "wof:name":"Duyvis Assuranti\u00ebn",
    "wof:placetype":"venue"
},
  "geometry": {"coordinates":[4.85023,52.349903],"type":"Point"}
}