{
  "type": "Feature",
  "properties": {
    "addr:full":"Jupiterstr 8A Zwolle NL.08 8022 RK",
    "addr:housenumber":"8a",
    "addr:postcode":"8022 rk",
    "addr:street":"Jupiterstr",
    "iso:country":"NL",
    "sg:address":"Jupiterstr 8A",
    "sg:city":"Zwolle",
    "sg:orig_category":"Verenigingsgebouwen",
    "sg:phone":"+31 38 454 8883",
    "sg:postcode":"8022 RK",
    "sg:province":"NL.08",
    "wof:name":"Bazuin, De",
    "wof:placetype":"venue"
},
  "geometry": {"coordinates":[6.109199,52.520027],"type":"Point"}
}