{
  "type": "Feature",
  "properties": {
    "addr:full":"Beulekamperweg 11 Nijkerk Gld Gelderland 3862 NV",
    "addr:housenumber":"11",
    "addr:postcode":"3862 nv",
    "addr:street":"Beulekamperweg;Gld Gelderland",
    "iso:country":"NL",
    "sg:address":"Beulekamperweg 11",
    "sg:city":"Nijkerk Gld",
    "sg:orig_category":"Levende Dieren Gh",
    "sg:phone":"+31 33 245 4822",
    "sg:postcode":"3862 NV",
    "sg:province":"Gelderland",
    "wof:name":"W.Schoeman",
    "wof:placetype":"venue"
},
  "geometry": {"coordinates":[5.523955,52.216473],"type":"Point"}
}