{
  "type": "Feature",
  "properties": {
    "addr:full":"Zandstraat 7 Culemborg Gelderland 4101 EC",
    "addr:housenumber":"7",
    "addr:postcode":"4101 ec",
    "addr:street":"Zandstraat;Gelderland",
    "iso:country":"NL",
    "sg:address":"Zandstraat 7",
    "sg:city":"Culemborg",
    "sg:orig_category":"Werving And Selectie Van Vast Personeel",
    "sg:phone":"+31 345 470 920",
    "sg:postcode":"4101 EC",
    "sg:province":"Gelderland",
    "wof:name":"Randstad Uitzendbureau",
    "wof:placetype":"venue"
},
  "geometry": {"coordinates":[5.2265071869,51.9549751282],"type":"Point"}
}