{
  "type": "Feature",
  "properties": {
    "addr:full":"Kleingouw 2 Andijk Noord-Holland 1619 CA",
    "addr:housenumber":"2",
    "addr:postcode":"1619 ca",
    "addr:street":"Kleingouw",
    "iso:country":"NL",
    "sg:address":"Kleingouw 2",
    "sg:city":"Andijk",
    "sg:orig_category":"Banken And Kredietinstellingen",
    "sg:phone":"+31 228 591 502",
    "sg:postcode":"1619 CA",
    "sg:province":"Noord-Holland",
    "wof:name":"Fortis Bank",
    "wof:placetype":"venue"
},
  "geometry": {"coordinates":[5.200143,52.741104],"type":"Point"}
}