{
  "type": "Feature",
  "properties": {
    "addr:full":"Laanstraat 2 Soest Utrecht 3762 KD",
    "addr:housenumber":"2",
    "addr:postcode":"3762 kd",
    "addr:street":"Laanstraat",
    "iso:country":"NL",
    "sg:address":"Laanstraat 2",
    "sg:city":"Soest",
    "sg:orig_category":"Verzekeringen",
    "sg:phone":"+31 35 602 7150",
    "sg:postcode":"3762 KD",
    "sg:province":"Utrecht",
    "wof:name":"Kraemer & Co",
    "wof:placetype":"venue"
},
  "geometry": {"coordinates":[5.275561,52.181496],"type":"Point"}
}