{
  "type": "Feature",
  "properties": {
    "addr:full":"Lagestraat 4 Loppersum Groningen 9919 AR",
    "addr:housenumber":"4",
    "addr:postcode":"9919",
    "addr:street":"Lagestraat",
    "iso:country":"NL",
    "sg:address":"Lagestraat 4",
    "sg:city":"Loppersum",
    "sg:orig_category":"Fietshandelaren",
    "sg:phone":"+31 596 572 897",
    "sg:postcode":"9919 AR",
    "sg:province":"Groningen",
    "wof:name":"Tweewielercentrum Bomekamp",
    "wof:placetype":"venue"
},
  "geometry": {"coordinates":[6.743985,53.33276],"type":"Point"}
}