{
  "type": "Feature",
  "properties": {
    "addr:full":"Wilhelminaln 18 Alphen Aan Den Ryn South Holland 2405 ED",
    "addr:housenumber":"18",
    "addr:postcode":"2405 ed",
    "addr:street":"Wilhelminaln;Aan Den Ryn",
    "iso:country":"NL",
    "sg:address":"Wilhelminaln 18",
    "sg:city":"Alphen Aan Den Ryn",
    "sg:orig_category":"Kantoor- En Secretariaatsservice",
    "sg:phone":"+31 172 488 888",
    "sg:postcode":"2405 ED",
    "sg:province":"South Holland",
    "sg:website":"http://www.easydesk.nl",
    "wof:name":"Easydesk Business Services",
    "wof:placetype":"venue"
},
  "geometry": {"coordinates":[4.662197113,52.1315460205],"type":"Point"}
}