{
  "type": "Feature",
  "properties": {
    "addr:full":"Zandwg 62 Ritthem Zeeland 4389 TH",
    "addr:housenumber":"62",
    "addr:postcode":"4389 th",
    "addr:street":"Zandwg",
    "iso:country":"NL",
    "sg:address":"Zandwg 62",
    "sg:city":"Ritthem",
    "sg:classifiers":[
        {
            "category":"Food & Beverages",
            "subcategory":"Fruits & Vegetables",
            "type":"Retail Goods"
        }
    ],
    "sg:phone":"+31 118 461 195",
    "sg:postcode":"4389 TH",
    "sg:province":"Zeeland",
    "sg:tags":[
        "en",
        "groenten"
    ],
    "wof:name":"Wielemaker, A J",
    "wof:placetype":"venue"
},
  "geometry": {"coordinates":[3.614582,51.457119],"type":"Point"}
}