{
  "type": "Feature",
  "properties": {
    "iso:country":"NL",
    "sg:address":"Bydorp W 82",
    "sg:city":"Barendrecht",
    "sg:orig_category":"Ventilatiesystemen",
    "sg:phone":"+31 180 691 450",
    "sg:postcode":"2992 LC",
    "sg:province":"South Holland",
    "wof:name":"Bergschenhoek Bv",
    "wof:placetype":"venue"
},
  "geometry": {"coordinates":[4.54064,51.853176],"type":"Point"}
}