{
  "type": "Feature",
  "properties": {
    "iso:country":"NL",
    "sg:address":"Oude Veer 3",
    "sg:city":"Papendrecht",
    "sg:orig_category":"Kinderkleding",
    "sg:phone":"+31 78 642 8060",
    "sg:postcode":"3351 AH",
    "sg:province":"South Holland",
    "wof:name":"Mgm Kids Store",
    "wof:placetype":"venue"
},
  "geometry": {"coordinates":[4.684131,51.824909],"type":"Point"}
}