{
  "type": "Feature",
  "properties": {
    "addr:full":"Hogewg 15A Zeeland North Brabant 5411 LP",
    "addr:housenumber":"15a",
    "addr:postcode":"5411 lp",
    "addr:street":"Hogewg",
    "iso:country":"NL",
    "sg:address":"Hogewg 15A",
    "sg:city":"Zeeland",
    "sg:orig_category":"Lasbedrijven",
    "sg:phone":"+31 486 453 078",
    "sg:postcode":"5411 LP",
    "sg:province":"North Brabant",
    "wof:name":"Freber Bv",
    "wof:placetype":"venue"
},
  "geometry": {"coordinates":[5.676312,51.709072],"type":"Point"}
}