{
  "type": "Feature",
  "properties": {
    "addr:full":"Spiekmanln 23 Arnhem Gelderland 6824 DL",
    "addr:housenumber":"23",
    "addr:postcode":"6824 dl",
    "addr:street":"Spiekmanln",
    "iso:country":"NL",
    "sg:address":"Spiekmanln 23",
    "sg:city":"Arnhem",
    "sg:orig_category":"Goudsmeden En Zilversmeden",
    "sg:phone":"+31 26 351 4396",
    "sg:postcode":"6824 DL",
    "sg:province":"Gelderland",
    "wof:name":"Diependaal",
    "wof:placetype":"venue"
},
  "geometry": {"coordinates":[5.931824,51.990078],"type":"Point"}
}