{
  "type": "Feature",
  "properties": {
    "addr:full":"Schapendrift 86 Blaricum Noord-Holland 1261 HS",
    "addr:housenumber":"86",
    "addr:postcode":"1261 hs",
    "addr:street":"Schapendrift",
    "iso:country":"NL",
    "sg:address":"Schapendrift 86",
    "sg:city":"Blaricum",
    "sg:orig_category":"Onroerende Goederen",
    "sg:phone":"+31 35 531 2342",
    "sg:postcode":"1261 HS",
    "sg:province":"Noord-Holland",
    "wof:name":"Prick En Partn Bv",
    "wof:placetype":"venue"
},
  "geometry": {"coordinates":[5.240686,52.264084],"type":"Point"}
}