{
  "type": "Feature",
  "properties": {
    "iso:country":"NL",
    "sg:address":"T Goyln 110/1",
    "sg:city":"Utrecht",
    "sg:orig_category":"Beeldende Kunstenaars",
    "sg:phone":"+31 30 288 7761",
    "sg:postcode":"3525 AK",
    "sg:province":"Utrecht",
    "wof:name":"Levenskunst",
    "wof:placetype":"venue"
},
  "geometry": {"coordinates":[5.11907,52.060612],"type":"Point"}
}