{
  "type": "Feature",
  "properties": {
    "addr:full":"Noorderbinnensngl 139 Groningen Groningen 9712 XM",
    "addr:housenumber":"139",
    "addr:postcode":"9712 xm",
    "iso:country":"NL",
    "sg:address":"Noorderbinnensngl 139",
    "sg:city":"Groningen",
    "sg:orig_category":"Psychologen",
    "sg:phone":"+31 50 311 1116",
    "sg:postcode":"9712 XM",
    "sg:province":"Groningen",
    "wof:name":"Leijenaar, Ds J C",
    "wof:placetype":"venue"
},
  "geometry": {"coordinates":[6.556269,53.220795],"type":"Point"}
}