{
  "type": "Feature",
  "properties": {
    "addr:full":"De Smelen 9 Valkenswaard North Brabant 5553 CT",
    "addr:housenumber":"9",
    "addr:postcode":"5553 ct",
    "addr:street":"De Smelen",
    "iso:country":"NL",
    "sg:address":"De Smelen 9",
    "sg:city":"Valkenswaard",
    "sg:orig_category":"Marktonderzoekbureaus",
    "sg:phone":"+31 40 201 2759",
    "sg:postcode":"5553 CT",
    "sg:province":"North Brabant",
    "wof:name":"Marie-Louise De Hoog",
    "wof:placetype":"venue"
},
  "geometry": {"coordinates":[5.47143,51.355759],"type":"Point"}
}