{
  "type": "Feature",
  "properties": {
    "addr:full":"Vijverlaan 17 Velp Gld Gelderland 6881 HK",
    "addr:housenumber":"17",
    "addr:postcode":"6881 hk",
    "addr:street":"Vijverlaan;Gld Gelderland",
    "iso:country":"NL",
    "sg:address":"Vijverlaan 17",
    "sg:city":"Velp Gld",
    "sg:orig_category":"Technische Studies And Onderzoek",
    "sg:phone":"+31 26 364 3050",
    "sg:postcode":"6881 HK",
    "sg:province":"Gelderland",
    "wof:name":"Totaal Hygiene Keur Thk",
    "wof:placetype":"venue"
},
  "geometry": {"coordinates":[5.974537,51.998032],"type":"Point"}
}