{
  "type": "Feature",
  "properties": {
    "addr:full":"Stompwijkseweg 70/A Leidschendam South Holland 2266 GH",
    "addr:housenumber":"70 / a",
    "addr:postcode":"2266 gh",
    "addr:street":"Stompwijkseweg",
    "iso:country":"NL",
    "sg:address":"Stompwijkseweg 70/A",
    "sg:city":"Leidschendam",
    "sg:orig_category":"Goederenvervoer Over De Weg",
    "sg:phone":"+31 70 327 4351",
    "sg:postcode":"2266 GH",
    "sg:province":"South Holland",
    "wof:name":"Transportbedrijf J.M.C. Verhagen",
    "wof:placetype":"venue"
},
  "geometry": {"coordinates":[4.439268,52.091419],"type":"Point"}
}