{
  "type": "Feature",
  "properties": {
    "addr:full":"Mr. Beelpark 1 Ede Gld Gelderland 6716 EV",
    "addr:housenumber":"1",
    "addr:postcode":"6716 ev",
    "addr:street":"Beelpark;Gld Gelderland",
    "iso:country":"NL",
    "sg:address":"Mr. Beelpark 1",
    "sg:city":"Ede Gld",
    "sg:orig_category":"Vertaal- And Tolkenbureaus",
    "sg:phone":"+31 318 643 990",
    "sg:postcode":"6716 EV",
    "sg:province":"Gelderland",
    "wof:name":"Jacqueline Stoffer-Heidrich",
    "wof:placetype":"venue"
},
  "geometry": {"coordinates":[5.66767,52.044979],"type":"Point"}
}