{
  "type": "Feature",
  "properties": {
    "addr:full":"Oude Rekemerstraat 57 Culemborg Gelderland 4105 AJ",
    "addr:housenumber":"57",
    "addr:postcode":"4105 aj",
    "addr:street":"Oude Rekemerstraat;Gelderland",
    "iso:country":"NL",
    "sg:address":"Oude Rekemerstraat 57",
    "sg:city":"Culemborg",
    "sg:orig_category":"Loonbedrijven",
    "sg:phone":"+31 345 512 402",
    "sg:postcode":"4105 AJ",
    "sg:province":"Gelderland",
    "wof:name":"Meijdam, G J",
    "wof:placetype":"venue"
},
  "geometry": {"coordinates":[5.219103,51.949619],"type":"Point"}
}