{
  "type": "Feature",
  "properties": {
    "addr:full":"Scannerstr 21 Amsterdam Noord-Holland 1033 RV",
    "addr:housenumber":"21",
    "addr:postcode":"1033 rv",
    "addr:street":"Scannerstr",
    "iso:country":"NL",
    "sg:address":"Scannerstr 21",
    "sg:city":"Amsterdam",
    "sg:orig_category":"Horeca-Inrichtingen En -Uitrustingen",
    "sg:phone":"+31 20 337 1576",
    "sg:postcode":"1033 RV",
    "sg:province":"Noord-Holland",
    "wof:name":"Klaasen Bv",
    "wof:placetype":"venue"
},
  "geometry": {"coordinates":[4.888084,52.407639],"type":"Point"}
}