{
  "type": "Feature",
  "properties": {
    "addr:full":"Waterrad 86 Grootebroek Noord-Holland 1613 CR",
    "addr:housenumber":"86",
    "addr:postcode":"1613 cr",
    "addr:street":"Waterrad",
    "iso:country":"NL",
    "sg:address":"Waterrad 86",
    "sg:city":"Grootebroek",
    "sg:classifiers":[
        {
            "category":"Retail",
            "subcategory":"Auto Repair",
            "type":"Services"
        }
    ],
    "sg:phone":"+31 228 516 957",
    "sg:postcode":"1613 CR",
    "sg:province":"Noord-Holland",
    "sg:tags":[
        "garage"
    ],
    "wof:name":"Viko",
    "wof:placetype":"venue"
},
  "geometry": {"coordinates":[5.230539,52.688747],"type":"Point"}
}