{
  "type": "Feature",
  "properties": {
    "addr:full":"Utrechtsewg 61-63 Amersfoort Utrecht 3818 EA",
    "addr:housenumber":"61-63",
    "addr:postcode":"3818 ea",
    "iso:country":"NL",
    "sg:address":"Utrechtsewg 61-63",
    "sg:city":"Amersfoort",
    "sg:orig_category":"Hypotheken",
    "sg:phone":"+31 33 461 6661",
    "sg:postcode":"3818 EA",
    "sg:province":"Utrecht",
    "wof:name":"I & I",
    "wof:placetype":"venue"
},
  "geometry": {"coordinates":[5.378919,52.150303],"type":"Point"}
}