{
  "type": "Feature",
  "properties": {
    "addr:full":"Zuiderl Dk Heukel 211 Spyk Gem Lingewaal South Holland 4211 BG",
    "addr:housenumber":"211",
    "addr:postcode":"4211",
    "addr:street":"Spyk Gem",
    "iso:country":"NL",
    "sg:address":"Zuiderl Dk Heukel 211",
    "sg:city":"Spyk Gem Lingewaal",
    "sg:orig_category":"Meubelmakerijen",
    "sg:phone":"+31 183 564 652",
    "sg:postcode":"4211 BG",
    "sg:province":"South Holland",
    "wof:name":"Project 4",
    "wof:placetype":"venue"
},
  "geometry": {"coordinates":[5.012339,51.856339],"type":"Point"}
}