{
  "type": "Feature",
  "properties": {
    "addr:full":"Patrysstr 1A Zwyndrecht Zuid-Holland 3334 AB",
    "addr:housenumber":"1a",
    "addr:postcode":"3334 ab",
    "addr:street":"Patrysstr",
    "iso:country":"NL",
    "sg:address":"Patrysstr 1A",
    "sg:city":"Zwyndrecht",
    "sg:orig_category":"Cafetaria'S",
    "sg:phone":"+31 78 619 2488",
    "sg:postcode":"3334 AB",
    "sg:province":"Zuid-Holland",
    "wof:name":"Patrijs, De",
    "wof:placetype":"venue"
},
  "geometry": {"coordinates":[4.61027,51.815418],"type":"Point"}
}