{
  "type": "Feature",
  "properties": {
    "addr:full":"Ahoywg 10 Rotterdam South Holland 3084 BA",
    "addr:housenumber":"10",
    "addr:postcode":"3084 ba",
    "addr:street":"Ahoywg",
    "iso:country":"NL",
    "sg:address":"Ahoywg 10",
    "sg:city":"Rotterdam",
    "sg:orig_category":"Organisatiebureaus",
    "sg:phone":"+31 10 293 3300",
    "sg:postcode":"3084 BA",
    "sg:province":"South Holland",
    "sg:website":"http://www.ahoy.nl",
    "wof:name":"Ahoy Rotterdam",
    "wof:placetype":"venue"
},
  "geometry": {"coordinates":[4.48954916,51.8824462891],"type":"Point"}
}