{
  "type": "Feature",
  "properties": {
    "addr:full":"Meidoornstr 7 Budel Noord-Brabant 6021 AX",
    "addr:housenumber":"7",
    "addr:postcode":"6021 ax",
    "addr:street":"Meidoornstr",
    "iso:country":"NL",
    "sg:address":"Meidoornstr 7",
    "sg:city":"Budel",
    "sg:orig_category":"Hek- En Rasterwerken",
    "sg:phone":"+31 495 494 176",
    "sg:postcode":"6021 AX",
    "sg:province":"Noord-Brabant",
    "wof:name":"Wh",
    "wof:placetype":"venue"
},
  "geometry": {"coordinates":[5.578737,51.275188],"type":"Point"}
}