{
  "type": "Feature",
  "properties": {
    "addr:full":"Lekdijk 187 Langerak Zh South Holland 2967 GJ",
    "addr:housenumber":"187;zh",
    "addr:postcode":"2967 gj",
    "addr:street":"Lekdijk",
    "iso:country":"NL",
    "sg:address":"Lekdijk 187",
    "sg:city":"Langerak Zh",
    "sg:orig_category":"Hout Gh",
    "sg:phone":"+31 184 601 341",
    "sg:postcode":"2967 GJ",
    "sg:province":"South Holland",
    "wof:name":"Labee Vezelpers Bv",
    "wof:placetype":"venue"
},
  "geometry": {"coordinates":[4.877221,51.93544],"type":"Point"}
}