{
  "type": "Feature",
  "properties": {
    "addr:full":"Lange Dam 27 Urk Flevoland 8321 XP",
    "addr:housenumber":"27",
    "addr:postcode":"8321 xp",
    "addr:street":"Lange Dam;Flevoland",
    "iso:country":"NL",
    "sg:address":"Lange Dam 27",
    "sg:city":"Urk",
    "sg:classifiers":[
        {
            "category":"Education",
            "subcategory":"Preschool",
            "type":"Public Place"
        }
    ],
    "sg:phone":"+31 527 682 751",
    "sg:postcode":"8321 XP",
    "sg:province":"Flevoland",
    "sg:tags":[
        "kleuteronderwijs",
        "basis-"
    ],
    "wof:name":"Dr. Maarten Lutherschool",
    "wof:placetype":"venue"
},
  "geometry": {"coordinates":[5.607033,52.666592],"type":"Point"}
}