{
  "type": "Feature",
  "properties": {
    "iso:country":"NL",
    "sg:address":"A Plesmanln 3",
    "sg:city":"Sassenheim",
    "sg:orig_category":"Adviesbureaus Bedrijfsorganisatie",
    "sg:phone":"+31 252 226 266",
    "sg:postcode":"2171 RE",
    "sg:province":"Zuid-Holland",
    "wof:name":"Dijk, M L C Van",
    "wof:placetype":"venue"
},
  "geometry": {"coordinates":[4.507703,52.219448],"type":"Point"}
}