{
  "type": "Feature",
  "properties": {
    "iso:country":"NL",
    "sg:address":"Prinsegracht 49-51",
    "sg:city":"'S Gravenhage",
    "sg:orig_category":"Makelaars In Onroerend Goed",
    "sg:phone":"+31 70 389 5141",
    "sg:postcode":"2512 EX",
    "sg:province":"Zuid-Holland",
    "wof:name":"Drie Kastelen Beleggingen Bv",
    "wof:placetype":"venue"
},
  "geometry": {"coordinates":[4.30444,52.074078],"type":"Point"}
}