{
  "type": "Feature",
  "properties": {
    "iso:country":"NL",
    "sg:address":"Oude Hoogstraat 3",
    "sg:city":"Amsterdam",
    "sg:orig_category":"Juweliers",
    "sg:phone":"+31 20 620 0508",
    "sg:postcode":"1012 CD",
    "sg:province":"Noord-Holland",
    "wof:name":"Yoeli Goud En Zilver",
    "wof:placetype":"venue"
},
  "geometry": {"coordinates":[4.897201,52.37149],"type":"Point"}
}