{
  "type": "Feature",
  "properties": {
    "addr:full":"Slangenburg 25 Almelo NL.08 7608 RS",
    "addr:housenumber":"25;nl.08",
    "addr:postcode":"7608 rs",
    "addr:street":"Slangenburg",
    "iso:country":"NL",
    "sg:address":"Slangenburg 25",
    "sg:city":"Almelo",
    "sg:orig_category":"Bedrijfs- And Managementsconsultants",
    "sg:phone":"+31 546 490 802",
    "sg:postcode":"7608 RS",
    "sg:province":"NL.08",
    "wof:name":"Sennen Consultancy",
    "wof:placetype":"venue"
},
  "geometry": {"coordinates":[6.691531,52.376591],"type":"Point"}
}