{
  "type": "Feature",
  "properties": {
    "addr:full":"Slechtvalk 2 Valkenswaard Noord-Brabant 5554 MB",
    "addr:housenumber":"2",
    "addr:postcode":"5554 mb",
    "addr:street":"Slechtvalk",
    "iso:country":"NL",
    "sg:address":"Slechtvalk 2",
    "sg:city":"Valkenswaard",
    "sg:orig_category":"Verbouwingen",
    "sg:phone":"+31 40 204 4311",
    "sg:postcode":"5554 MB",
    "sg:province":"Noord-Brabant",
    "sg:website":"http://www.utiliteitdiensten.nl",
    "wof:name":"Udb Bouwservice",
    "wof:placetype":"venue"
},
  "geometry": {"coordinates":[5.456621,51.3414],"type":"Point"}
}