{
  "type": "Feature",
  "properties": {
    "addr:full":"Koehorstmaat 8 Deurningen Overijssel 7561 BM",
    "addr:housenumber":"8",
    "addr:postcode":"7561 bm",
    "addr:street":"Koehorstmaat",
    "iso:country":"NL",
    "sg:address":"Koehorstmaat 8",
    "sg:city":"Deurningen",
    "sg:orig_category":"Huizensloop And Bouwrijp Maken",
    "sg:phone":"+31 74 277 3618",
    "sg:postcode":"7561 BM",
    "sg:province":"Overijssel",
    "wof:name":"Vof Wennink",
    "wof:placetype":"venue"
},
  "geometry": {"coordinates":[6.840173,52.303257],"type":"Point"}
}