{
  "type": "Feature",
  "properties": {
    "addr:full":"Stationsstr 59 Twello Gelderland 7391 EJ",
    "addr:housenumber":"59",
    "addr:postcode":"7391 ej",
    "addr:street":"Stationsstr;Gelderland",
    "iso:country":"NL",
    "sg:address":"Stationsstr 59",
    "sg:city":"Twello",
    "sg:orig_category":"Administratie- En Boekhoudkantoren",
    "sg:phone":"+31 571 280 601",
    "sg:postcode":"7391 EJ",
    "sg:province":"Gelderland",
    "wof:name":"Groot Koerkamp",
    "wof:placetype":"venue"
},
  "geometry": {"coordinates":[6.100046,52.239643],"type":"Point"}
}