{
  "type": "Feature",
  "properties": {
    "iso:country":"NL",
    "sg:address":"Zoeterwoudsesingel 41",
    "sg:city":"Leiden",
    "sg:orig_category":"Verzekeringen",
    "sg:phone":"+31 71 512 2917",
    "sg:postcode":"2313 EJ",
    "sg:province":"South Holland",
    "wof:name":"Assurantiekantoor Bakker",
    "wof:placetype":"venue"
},
  "geometry": {"coordinates":[4.49655,52.15266],"type":"Point"}
}