{
  "type": "Feature",
  "properties": {
    "iso:country":"NL",
    "sg:address":"Beatrixpln 22",
    "sg:city":"Bennebroek",
    "sg:orig_category":"Ontbijtservice",
    "sg:phone":"+31 6 21257535",
    "sg:postcode":"2121 XT",
    "sg:province":"Noord-Holland",
    "wof:name":"Liza'S Ontbijtservice",
    "wof:placetype":"venue"
},
  "geometry": {"coordinates":[4.602351,52.319096],"type":"Point"}
}