{
  "type": "Feature",
  "properties": {
    "addr:full":"Seinedreef 116 Utrecht Utrecht 3562 KT",
    "addr:housenumber":"116",
    "addr:postcode":"3562 kt",
    "addr:street":"Seinedreef",
    "iso:country":"NL",
    "sg:address":"Seinedreef 116",
    "sg:city":"Utrecht",
    "sg:orig_category":"Makelaars En Adviseurs Onroerende Goederen",
    "sg:phone":"+31 30 264 4555",
    "sg:postcode":"3562 KT",
    "sg:province":"Utrecht",
    "sg:website":"http://www.veenhuizen.net",
    "wof:name":"Veenhuizen",
    "wof:placetype":"venue"
},
  "geometry": {"coordinates":[5.111495,52.112709],"type":"Point"}
}