{
  "type": "Feature",
  "properties": {
    "addr:full":"Zwaanshals 309 Rotterdam Zuid-Holland 3035 KJ",
    "addr:housenumber":"309",
    "addr:postcode":"3035 kj",
    "addr:street":"Zwaanshals",
    "iso:country":"NL",
    "sg:address":"Zwaanshals 309",
    "sg:city":"Rotterdam",
    "sg:orig_category":"Hulpverlening Sociaal",
    "sg:phone":"+31 10 467 6322",
    "sg:postcode":"3035 KJ",
    "sg:province":"Zuid-Holland",
    "wof:name":"Jongeren Informatie Punt Oude Noorden",
    "wof:placetype":"venue"
},
  "geometry": {"coordinates":[4.48543,51.932438],"type":"Point"}
}