{
  "type": "Feature",
  "properties": {
    "addr:full":"Houtmolenstr 14 Doetinchem Gelderland 7008 AR",
    "addr:housenumber":"14",
    "addr:postcode":"7008",
    "addr:street":"Houtmolenstr;Gelderland",
    "iso:country":"NL",
    "sg:address":"Houtmolenstr 14",
    "sg:city":"Doetinchem",
    "sg:orig_category":"Verpakkingsbedrijven",
    "sg:phone":"+31 314 390 366",
    "sg:postcode":"7008 AR",
    "sg:province":"Gelderland",
    "wof:name":"Bieleveld-Gerritsen",
    "wof:placetype":"venue"
},
  "geometry": {"coordinates":[6.273972,51.970638],"type":"Point"}
}