{
  "type": "Feature",
  "properties": {
    "addr:full":"Techniekwg 6 Emmeloord Flevoland 8304 AW",
    "addr:housenumber":"6",
    "addr:postcode":"8304 aw",
    "addr:street":"Techniekwg;Flevoland",
    "iso:country":"NL",
    "sg:address":"Techniekwg 6",
    "sg:city":"Emmeloord",
    "sg:orig_category":"Automaterialen En Gereedschappen",
    "sg:phone":"+31 527 631 555",
    "sg:postcode":"8304 AW",
    "sg:province":"Flevoland",
    "wof:name":"Lasaulec Emmeloord",
    "wof:placetype":"venue"
},
  "geometry": {"coordinates":[5.755487,52.698063],"type":"Point"}
}