{
  "type": "Feature",
  "properties": {
    "addr:full":"Rooseveltweg 421 Wageningen Gelderland 6707 GR",
    "addr:housenumber":"421",
    "addr:postcode":"6707",
    "addr:street":"Rooseveltweg;Gelderland",
    "iso:country":"NL",
    "sg:address":"Rooseveltweg 421",
    "sg:city":"Wageningen",
    "sg:orig_category":"Boekhouders",
    "sg:phone":"+31 317 412 144",
    "sg:postcode":"6707 GR",
    "sg:province":"Gelderland",
    "wof:name":"Veluwse Administratieve Dienstverlening",
    "wof:placetype":"venue"
},
  "geometry": {"coordinates":[5.663467,51.973675],"type":"Point"}
}