{
  "type": "Feature",
  "properties": {
    "addr:full":"De Boelelaan 7 Amsterdam Noord-Holland 1083 HJ",
    "addr:housenumber":"7",
    "addr:postcode":"1083 hj",
    "addr:street":"De Boelelaan",
    "iso:country":"NL",
    "sg:address":"De Boelelaan 7",
    "sg:city":"Amsterdam",
    "sg:orig_category":"Luchtvaart",
    "sg:phone":"+31 20 646 1001",
    "sg:postcode":"1083 HJ",
    "sg:province":"Noord-Holland",
    "wof:name":"China Airlines",
    "wof:placetype":"venue"
},
  "geometry": {"coordinates":[4.885723,52.334583],"type":"Point"}
}