{
  "type": "Feature",
  "properties": {
    "iso:country":"NL",
    "sg:address":"Marketentster 54",
    "sg:city":"Alphen A/D Rijn",
    "sg:orig_category":"Diverse Grafische Activiteiten",
    "sg:phone":"+31 172 441 209",
    "sg:postcode":"2401 JH",
    "sg:province":"Zuid-Holland",
    "wof:name":"Hes / Vormgeving",
    "wof:placetype":"venue"
},
  "geometry": {"coordinates":[4.65227,52.153542],"type":"Point"}
}