{
  "type": "Feature",
  "properties": {
    "iso:country":"NL",
    "sg:address":"Bilderdijkstr 31",
    "sg:city":"Lichtenvoorde",
    "sg:orig_category":"Kappers",
    "sg:phone":"+31 544 371 658",
    "sg:postcode":"7131 NH",
    "sg:province":"Gelderland",
    "wof:name":"Ad?le",
    "wof:placetype":"venue"
},
  "geometry": {"coordinates":[-71.6328277588,44.0013008118],"type":"Point"}
}