{
  "type": "Feature",
  "properties": {
    "addr:full":"Stationsstraat 8 Heerenveen Provincie Friesland 8441 AX",
    "addr:housenumber":"8",
    "addr:postcode":"8441 ax",
    "addr:street":"Stationsstraat;Provincie Friesland",
    "iso:country":"NL",
    "sg:address":"Stationsstraat 8",
    "sg:city":"Heerenveen",
    "sg:orig_category":"Diverse Grafische Activiteiten",
    "sg:phone":"+31 513 651 119",
    "sg:postcode":"8441 AX",
    "sg:province":"Provincie Friesland",
    "wof:name":"B.S. Postmus",
    "wof:placetype":"venue"
},
  "geometry": {"coordinates":[5.915501,52.961937],"type":"Point"}
}