{
  "type": "Feature",
  "properties": {
    "addr:full":"Meerstr 19 Hillegom Zuid-Holland 2181 BH",
    "addr:housenumber":"19",
    "addr:postcode":"2181 bh",
    "addr:street":"Meerstr",
    "iso:country":"NL",
    "sg:address":"Meerstr 19",
    "sg:city":"Hillegom",
    "sg:orig_category":"Opticiens",
    "sg:phone":"+31 252 523 346",
    "sg:postcode":"2181 BH",
    "sg:province":"Zuid-Holland",
    "wof:name":"Bril 58",
    "wof:placetype":"venue"
},
  "geometry": {"coordinates":[4.580728054,52.2930374146],"type":"Point"}
}