{
  "type": "Feature",
  "properties": {
    "iso:country":"NL",
    "sg:address":"Burghoffweg 13",
    "sg:city":"Roermond",
    "sg:orig_category":"Huishoudapparatuur, Televisies And Radio'S",
    "sg:phone":"+31 475 425 262",
    "sg:postcode":"6042 EX",
    "sg:province":"Limburg",
    "wof:name":"Electro World Tummers",
    "wof:placetype":"venue"
},
  "geometry": {"coordinates":[6.016717,51.20842],"type":"Point"}
}