{
  "type": "Feature",
  "properties": {
    "addr:full":"Zoutmanstr 4 Rotterdam Zuid-Holland 3012 EV",
    "addr:housenumber":"4",
    "addr:postcode":"3012 ev",
    "addr:street":"Zoutmanstr",
    "iso:country":"NL",
    "sg:address":"Zoutmanstr 4",
    "sg:city":"Rotterdam",
    "sg:orig_category":"Logopedisten",
    "sg:phone":"+31 10 411 4224",
    "sg:postcode":"3012 EV",
    "sg:province":"Zuid-Holland",
    "wof:name":"Blokland, A C",
    "wof:placetype":"venue"
},
  "geometry": {"coordinates":[4.475699,51.9216],"type":"Point"}
}