{
  "type": "Feature",
  "properties": {
    "addr:full":"Postbus 64 Noordwijkerhout South Holland 2210 AB",
    "addr:housenumber":"64",
    "addr:postcode":"2210 ab",
    "addr:street":"Postbus",
    "iso:country":"NL",
    "sg:address":"Postbus 64",
    "sg:city":"Noordwijkerhout",
    "sg:orig_category":"Verlichting",
    "sg:phone":"+31 252 374 488",
    "sg:postcode":"2210 AB",
    "sg:province":"South Holland",
    "wof:name":"Burlight Design",
    "wof:placetype":"venue"
},
  "geometry": {"coordinates":[4.491189,52.26347],"type":"Point"}
}