{
  "type": "Feature",
  "properties": {
    "addr:full":"Slochterwg 35 Amsterdam Noord-Holland 1027 AA",
    "addr:housenumber":"35",
    "addr:postcode":"1027 aa",
    "addr:street":"Slochterwg",
    "iso:country":"NL",
    "sg:address":"Slochterwg 35",
    "sg:city":"Amsterdam",
    "sg:orig_category":"Verenigingen En Stichtingen",
    "sg:phone":"+31 20 403 3051",
    "sg:postcode":"1027 AA",
    "sg:province":"Noord-Holland",
    "wof:name":"Int Dispensary Assoc",
    "wof:placetype":"venue"
},
  "geometry": {"coordinates":[4.94874,52.421509],"type":"Point"}
}