{
  "type": "Feature",
  "properties": {
    "addr:full":"It Beaken 4 Joure Friesland 8502 BX",
    "addr:housenumber":"4",
    "addr:postcode":"8502 bx",
    "addr:street":"It Beaken",
    "iso:country":"NL",
    "sg:address":"It Beaken 4",
    "sg:city":"Joure",
    "sg:orig_category":"Apothekers",
    "sg:phone":"+31 513 414 252",
    "sg:postcode":"8502 BX",
    "sg:province":"Friesland",
    "wof:name":"Apotheek Skipsleat",
    "wof:placetype":"venue"
},
  "geometry": {"coordinates":[5.807745,52.972317],"type":"Point"}
}