{
  "type": "Feature",
  "properties": {
    "addr:full":"Aggerstraat 5 Rilland Zeeland 4411 CV",
    "addr:housenumber":"5",
    "addr:postcode":"4411 cv",
    "addr:street":"Aggerstraat",
    "iso:country":"NL",
    "sg:address":"Aggerstraat 5",
    "sg:city":"Rilland",
    "sg:orig_category":"Werving And Selectie Van Tijdelijk Personeel And Uitzendkantoren",
    "sg:phone":"+31 113 551 545",
    "sg:postcode":"4411 CV",
    "sg:province":"Zeeland",
    "wof:name":"De Bevelanden Bv",
    "wof:placetype":"venue"
},
  "geometry": {"coordinates":[4.1800789833,51.4195175171],"type":"Point"}
}