{
  "type": "Feature",
  "properties": {
    "addr:full":"Rauwenhoffwg 2 Epe Gelderland 8162 PK",
    "addr:housenumber":"2",
    "addr:postcode":"8162 pk",
    "addr:street":"Rauwenhoffwg;Gelderland",
    "iso:country":"NL",
    "sg:address":"Rauwenhoffwg 2",
    "sg:city":"Epe",
    "sg:orig_category":"Onroerende Goederen",
    "sg:phone":"+31 578 612 442",
    "sg:postcode":"8162 PK",
    "sg:province":"Gelderland",
    "wof:name":"Schouten Bv, J P",
    "wof:placetype":"venue"
},
  "geometry": {"coordinates":[5.949215,52.352688],"type":"Point"}
}