{
  "type": "Feature",
  "properties": {
    "addr:full":"Oude Trambaan 25 Heythuysen Limburg 6093 CD",
    "addr:housenumber":"25",
    "addr:postcode":"6093 cd",
    "addr:street":"Oude Trambaan",
    "iso:country":"NL",
    "sg:address":"Oude Trambaan 25",
    "sg:city":"Heythuysen",
    "sg:orig_category":"Orthopedisch Schoeisel",
    "sg:phone":"+31 475 493 900",
    "sg:postcode":"6093 CD",
    "sg:province":"Limburg",
    "wof:name":"Penders Bv",
    "wof:placetype":"venue"
},
  "geometry": {"coordinates":[5.8985619545,51.2481498718],"type":"Point"}
}