{
  "type": "Feature",
  "properties": {
    "iso:country":"NL",
    "sg:address":"Dorpsstr 35A",
    "sg:city":"Leimuiden",
    "sg:orig_category":"Bloemen En Planten",
    "sg:phone":"+31 172 506 910",
    "sg:postcode":"2451 AP",
    "sg:province":"Zuid-Holland",
    "wof:name":"Groene Hart, 'T",
    "wof:placetype":"venue"
},
  "geometry": {"coordinates":[4.672454,52.22295],"type":"Point"}
}