{
  "type": "Feature",
  "properties": {
    "iso:country":"NL",
    "sg:address":"Willebrordstraat 8",
    "sg:city":"Aalten",
    "sg:classifiers":[
        {
            "category":"Education",
            "subcategory":"Preschool",
            "type":"Public Place"
        }
    ],
    "sg:phone":"+31 543 473 242",
    "sg:postcode":"7121 DR",
    "sg:province":"Gelderland",
    "sg:tags":[
        "kleuteronderwijs",
        "basis-"
    ],
    "wof:name":"Groen Van Prinsterer Prot Chr",
    "wof:placetype":"venue"
},
  "geometry": {"coordinates":[6.584162,51.923489],"type":"Point"}
}