{
  "type": "Feature",
  "properties": {
    "addr:full":"Hans De Riesstraat 34 Alkmaar North Holland 1827 NR",
    "addr:housenumber":"34",
    "addr:postcode":"1827 nr",
    "addr:street":"Hans De Riesstraat",
    "iso:country":"NL",
    "sg:address":"Hans De Riesstraat 34",
    "sg:city":"Alkmaar",
    "sg:orig_category":"Marktonderzoekbureaus",
    "sg:phone":"+31 72 562 3937",
    "sg:postcode":"1827 NR",
    "sg:province":"North Holland",
    "wof:name":"Van Stralen",
    "wof:placetype":"venue"
},
  "geometry": {"coordinates":[4.770594,52.672997],"type":"Point"}
}