{
  "type": "Feature",
  "properties": {
    "addr:full":"Willem Barentszweg 30 Venlo Limburg 5928 LM",
    "addr:housenumber":"30",
    "addr:postcode":"5928 lm",
    "addr:street":"Willem Barentszweg",
    "iso:country":"NL",
    "sg:address":"Willem Barentszweg 30",
    "sg:city":"Venlo",
    "sg:orig_category":"Granen, Zaden And Diervoeders Gh",
    "sg:phone":"+31 77 396 9120",
    "sg:postcode":"5928 LM",
    "sg:province":"Limburg",
    "wof:name":"Schobbers Zaden Bv",
    "wof:placetype":"venue"
},
  "geometry": {"coordinates":[6.089699,51.391216],"type":"Point"}
}