{
  "type": "Feature",
  "properties": {
    "addr:full":"Schoterveld 42 Nieuwveen South Holland 2441 AX",
    "addr:housenumber":"42",
    "addr:postcode":"2441 ax",
    "addr:street":"Schoterveld",
    "iso:country":"NL",
    "sg:address":"Schoterveld 42",
    "sg:city":"Nieuwveen",
    "sg:orig_category":"Bedrijfsinventaris Gh",
    "sg:phone":"+31 172 538 415",
    "sg:postcode":"2441 AX",
    "sg:province":"South Holland",
    "wof:name":"Vof Heemskerk En Link",
    "wof:placetype":"venue"
},
  "geometry": {"coordinates":[4.75793,52.193256],"type":"Point"}
}