{
  "type": "Feature",
  "properties": {
    "addr:full":"Raadhuisstr 15 Koog Aan De Zaan North Holland 1541 JA",
    "addr:housenumber":"15",
    "addr:postcode":"1541 ja",
    "addr:street":"Raadhuisstr",
    "iso:country":"NL",
    "sg:address":"Raadhuisstr 15",
    "sg:city":"Koog Aan De Zaan",
    "sg:orig_category":"Homeopathie",
    "sg:phone":"+31 75 670 2160",
    "sg:postcode":"1541 JA",
    "sg:province":"North Holland",
    "wof:name":"Kruidentuin, De",
    "wof:placetype":"venue"
},
  "geometry": {"coordinates":[4.810784,52.461334],"type":"Point"}
}