{
  "type": "Feature",
  "properties": {
    "addr:full":"Leensterwg 32 Kloosterburen Groningen 9977 PC",
    "addr:housenumber":"32",
    "addr:postcode":"9977 pc",
    "addr:street":"Leensterwg",
    "iso:country":"NL",
    "sg:address":"Leensterwg 32",
    "sg:city":"Kloosterburen",
    "sg:orig_category":"Banken",
    "sg:phone":"+31 595 481 242",
    "sg:postcode":"9977 PC",
    "sg:province":"Groningen",
    "wof:name":"Regio Bank",
    "wof:placetype":"venue"
},
  "geometry": {"coordinates":[6.37395,53.386463],"type":"Point"}
}