{
  "type": "Feature",
  "properties": {
    "addr:full":"Industrieweg 2 Oudenbosch Noord-Brabant 4731 SC",
    "addr:housenumber":"2",
    "addr:postcode":"4731 sc",
    "addr:street":"Industrieweg",
    "iso:country":"NL",
    "sg:address":"Industrieweg 2",
    "sg:city":"Oudenbosch",
    "sg:orig_category":"Metaalbekleding And -Behandeling",
    "sg:phone":"+31 165 311 865",
    "sg:postcode":"4731 SC",
    "sg:province":"Noord-Brabant",
    "wof:name":"Verspaningstechniek Timmermans Oudenbosch Bv",
    "wof:placetype":"venue"
},
  "geometry": {"coordinates":[4.525886,51.584103],"type":"Point"}
}