{
  "type": "Feature",
  "properties": {
    "addr:full":"Schuttersbergweg 23 Arnhem Gelderland 6823 KE",
    "addr:housenumber":"23",
    "addr:postcode":"6823 ke",
    "addr:street":"Schuttersbergweg",
    "iso:country":"NL",
    "sg:address":"Schuttersbergweg 23",
    "sg:city":"Arnhem",
    "sg:orig_category":"Huishoudapparatuur, Televisies And Radio'S",
    "sg:phone":"+31 26 442 0851",
    "sg:postcode":"6823 KE",
    "sg:province":"Gelderland",
    "wof:name":"Th. J. Dibbets",
    "wof:placetype":"venue"
},
  "geometry": {"coordinates":[5.938268,52.002941],"type":"Point"}
}