{
  "type": "Feature",
  "properties": {
    "iso:country":"NL",
    "sg:address":"Mgr Zwysenstr 6",
    "sg:city":"Ravenstein",
    "sg:orig_category":"Manueel Therapeuten",
    "sg:phone":"+31 486 413 426",
    "sg:postcode":"5371 BS",
    "sg:province":"Noord-Brabant",
    "wof:name":"Saedt & P A E Daanen, E R",
    "wof:placetype":"venue"
},
  "geometry": {"coordinates":[5.671468,51.776047],"type":"Point"}
}