{
  "type": "Feature",
  "properties": {
    "addr:full":"Pastoor Ohllaan 39 Vleuten Utrecht 3451 CB",
    "addr:housenumber":"39",
    "addr:postcode":"3451 cb",
    "addr:street":"Pastoor Ohllaan",
    "iso:country":"NL",
    "sg:address":"Pastoor Ohllaan 39",
    "sg:city":"Vleuten",
    "sg:orig_category":"Woningbouwverenigingen",
    "sg:phone":"+31 30 677 9070",
    "sg:postcode":"3451 CB",
    "sg:province":"Utrecht",
    "wof:name":"Woningstichting Vleuten-De Meern",
    "wof:placetype":"venue"
},
  "geometry": {"coordinates":[5.0135259628,52.1037788391],"type":"Point"}
}