{
  "type": "Feature",
  "properties": {
    "addr:full":"Damloper 11 Oosterhout Nb Noord-Brabant 4902 CD",
    "addr:housenumber":"11",
    "addr:postcode":"4902 cd",
    "addr:street":"Damloper",
    "iso:country":"NL",
    "sg:address":"Damloper 11",
    "sg:city":"Oosterhout Nb",
    "sg:orig_category":"Koeriersdiensten",
    "sg:phone":"+31 6 20984197",
    "sg:postcode":"4902 CD",
    "sg:province":"Noord-Brabant",
    "wof:name":"Gouden Kroon",
    "wof:placetype":"venue"
},
  "geometry": {"coordinates":[4.840493,51.64373],"type":"Point"}
}