{
  "type": "Feature",
  "properties": {
    "addr:full":"Bakkerstraat 2A Haarlem Noord-Holland 2012 ZJ",
    "addr:housenumber":"2a",
    "addr:postcode":"2012 zj",
    "addr:street":"Bakkerstraat",
    "iso:country":"NL",
    "sg:address":"Bakkerstraat 2A",
    "sg:city":"Haarlem",
    "sg:orig_category":"Bloemen And Planten",
    "sg:phone":"+31 23 531 3433",
    "sg:postcode":"2012 ZJ",
    "sg:province":"Noord-Holland",
    "wof:name":"Van Deventer Bloemen-En Plantenhal",
    "wof:placetype":"venue"
},
  "geometry": {"coordinates":[4.636822,52.373287],"type":"Point"}
}