{
  "type": "Feature",
  "properties": {
    "addr:full":"Dr W Dreeslaan 2 Goes Zeeland 4463 XE",
    "addr:housenumber":"2",
    "addr:postcode":"4463 xe",
    "addr:street":"Dr W Dreeslaan",
    "iso:country":"NL",
    "sg:address":"Dr W Dreeslaan 2",
    "sg:city":"Goes",
    "sg:orig_category":"Drukkerijen And Copyshops",
    "sg:phone":"+31 113 228 350",
    "sg:postcode":"4463 XE",
    "sg:province":"Zeeland",
    "wof:name":"Vof Drukkerij Zeelandia",
    "wof:placetype":"venue"
},
  "geometry": {"coordinates":[-83.914169,39.768833],"type":"Point"}
}