{
  "type": "Feature",
  "properties": {
    "iso:country":"NL",
    "sg:address":"Hezelaarsestr 24",
    "sg:city":"Liempde",
    "sg:orig_category":"Administratie- En Boekhoudkantoren",
    "sg:phone":"+31 411 635 118",
    "sg:postcode":"5298 NJ",
    "sg:province":"Noord-Brabant",
    "wof:name":"Boons, W",
    "wof:placetype":"venue"
},
  "geometry": {"coordinates":[5.386954,51.564373],"type":"Point"}
}