{
  "type": "Feature",
  "properties": {
    "addr:full":"Eisenhowerln 108 S Gravenhage South Holland 2517 KL",
    "addr:housenumber":"108",
    "addr:postcode":"2517 kl",
    "addr:street":"S Gravenhage",
    "iso:country":"NL",
    "sg:address":"Eisenhowerln 108",
    "sg:city":"S Gravenhage",
    "sg:orig_category":"Verenigingen En Stichtingen",
    "sg:phone":"+31 70 306 8815",
    "sg:postcode":"2517 KL",
    "sg:province":"South Holland",
    "wof:name":"Goede Voeding",
    "wof:placetype":"venue"
},
  "geometry": {"coordinates":[4.28708,52.08667],"type":"Point"}
}