{
  "type": "Feature",
  "properties": {
    "addr:full":"Geldersekd 75 Amsterdam Noord-Holland 1011 EL",
    "addr:housenumber":"75;1011",
    "addr:postcode":"el",
    "addr:street":"Geldersekd",
    "iso:country":"NL",
    "sg:address":"Geldersekd 75",
    "sg:city":"Amsterdam",
    "sg:classifiers":[
        {
            "category":"Travel",
            "subcategory":"Hotels & Motels",
            "type":"Entertainment"
        }
    ],
    "sg:phone":"+31 20 422 3338",
    "sg:postcode":"1011 EL",
    "sg:province":"Noord-Holland",
    "wof:name":"Gelderse Neel",
    "wof:placetype":"venue"
},
  "geometry": {"coordinates":[4.893195,52.373119],"type":"Point"}
}