{
  "type": "Feature",
  "properties": {
    "addr:full":"Robijnstraat 5 Breda North Brabant 4817 JD",
    "addr:housenumber":"5",
    "addr:postcode":"4817 jd",
    "addr:street":"Robijnstraat",
    "iso:country":"NL",
    "sg:address":"Robijnstraat 5",
    "sg:city":"Breda",
    "sg:orig_category":"Boekhouders",
    "sg:phone":"+31 76 514 6400",
    "sg:postcode":"4817 JD",
    "sg:province":"North Brabant",
    "wof:name":"F. De Hoogh",
    "wof:placetype":"venue"
},
  "geometry": {"coordinates":[4.79881,51.590492],"type":"Point"}
}