{
  "type": "Feature",
  "properties": {
    "addr:full":"Wollefoppenwg 57C Rotterdam Zuid-Holland 3059 LG",
    "addr:housenumber":"57c",
    "addr:postcode":"3059 lg",
    "addr:street":"Wollefoppenwg",
    "iso:country":"NL",
    "sg:address":"Wollefoppenwg 57C",
    "sg:city":"Rotterdam",
    "sg:orig_category":"Zonweringen",
    "sg:phone":"+31 10 455 5380",
    "sg:postcode":"3059 LG",
    "sg:province":"Zuid-Holland",
    "sg:website":"http://www.ronmeijer.nl",
    "wof:name":"Ron Meijer",
    "wof:placetype":"venue"
},
  "geometry": {"coordinates":[4.59524,51.981709],"type":"Point"}
}