{
  "type": "Feature",
  "properties": {
    "addr:full":"Zwarte Bergend 1 Luyksgestel Noord-Brabant 5575 XP",
    "addr:housenumber":"1",
    "addr:postcode":"5575 xp",
    "addr:street":"Bergend",
    "iso:country":"NL",
    "sg:address":"Zwarte Bergend 1",
    "sg:city":"Luyksgestel",
    "sg:classifiers":[
        {
            "category":"Sports & Exercise",
            "subcategory":"Stables",
            "type":"Entertainment"
        }
    ],
    "sg:phone":"+31 6 50906448",
    "sg:postcode":"5575 XP",
    "sg:province":"Noord-Brabant",
    "sg:tags":[
        "maneges"
    ],
    "wof:name":"Es",
    "wof:placetype":"venue"
},
  "geometry": {"coordinates":[5.296994,51.293777],"type":"Point"}
}