{
  "type": "Feature",
  "properties": {
    "addr:full":"Bakboord 1 Stadskanaal Groningen 9501 JX",
    "addr:housenumber":"1",
    "addr:postcode":"9501 jx",
    "addr:street":"Bakboord",
    "iso:country":"NL",
    "sg:address":"Bakboord 1",
    "sg:city":"Stadskanaal",
    "sg:orig_category":"Adviesbureaus",
    "sg:phone":"+31 599 653 372",
    "sg:postcode":"9501 JX",
    "sg:province":"Groningen",
    "wof:name":"Pantachoe",
    "wof:placetype":"venue"
},
  "geometry": {"coordinates":[6.95583,52.997841],"type":"Point"}
}