{
  "type": "Feature",
  "properties": {
    "addr:full":"Hoge Biezen 4 Veghel Noord-Brabant 5465 PP",
    "addr:housenumber":"4",
    "addr:postcode":"5465 pp",
    "addr:street":"Hoge Biezen",
    "iso:country":"NL",
    "sg:address":"Hoge Biezen 4",
    "sg:city":"Veghel",
    "sg:orig_category":"Schilderwerk",
    "sg:phone":"+31 413 367 094",
    "sg:postcode":"5465 PP",
    "sg:province":"Noord-Brabant",
    "wof:name":"Schildersbedrijf J.P. Ketelaars",
    "wof:placetype":"venue"
},
  "geometry": {"coordinates":[5.534094,51.581287],"type":"Point"}
}