{
  "type": "Feature",
  "properties": {
    "addr:full":"Krokusstraat 47 Haarlem North Holland 2015 AE",
    "addr:housenumber":"47",
    "addr:postcode":"2015 ae",
    "addr:street":"Krokusstraat",
    "iso:country":"NL",
    "sg:address":"Krokusstraat 47",
    "sg:city":"Haarlem",
    "sg:orig_category":"Bedrijfs- And Managementsconsultants",
    "sg:phone":"+31 23 532 0028",
    "sg:postcode":"2015 AE",
    "sg:province":"North Holland",
    "wof:name":"Appel",
    "wof:placetype":"venue"
},
  "geometry": {"coordinates":[4.617975,52.384644],"type":"Point"}
}