{
  "type": "Feature",
  "properties": {
    "addr:full":"Wannerpln 5A Heerlen Limburg 6413 ET",
    "addr:housenumber":"5a",
    "addr:postcode":"6413 et",
    "addr:street":"Wannerpln",
    "iso:country":"NL",
    "sg:address":"Wannerpln 5A",
    "sg:city":"Heerlen",
    "sg:orig_category":"Geschenkartikelen",
    "sg:phone":"+31 45 521 7173",
    "sg:postcode":"6413 ET",
    "sg:province":"Limburg",
    "wof:name":"Kadoshop Danique",
    "wof:placetype":"venue"
},
  "geometry": {"coordinates":[5.955356,50.915283],"type":"Point"}
}