{
  "type": "Feature",
  "properties": {
    "addr:full":"Narcisstraat 31 Putte North Brabant 4645 CP",
    "addr:housenumber":"31",
    "addr:postcode":"4645 cp",
    "addr:street":"Narcisstraat",
    "iso:country":"NL",
    "sg:address":"Narcisstraat 31",
    "sg:city":"Putte",
    "sg:orig_category":"Boekhouders",
    "sg:phone":"+31 164 602 723",
    "sg:postcode":"4645 CP",
    "sg:province":"North Brabant",
    "wof:name":"Administratiekantoor M.P. Groffen",
    "wof:placetype":"venue"
},
  "geometry": {"coordinates":[4.39738,51.358967],"type":"Point"}
}