{
  "type": "Feature",
  "properties": {
    "addr:full":"Postbus 8 Westkapelle Zeeland 4360 AA",
    "addr:housenumber":"8",
    "addr:postcode":"4360 aa",
    "addr:street":"Postbus",
    "iso:country":"NL",
    "sg:address":"Postbus 8",
    "sg:city":"Westkapelle",
    "sg:orig_category":"Voetbalverenigingen",
    "sg:phone":"+31 118 571 929",
    "sg:postcode":"4360 AA",
    "sg:province":"Zeeland",
    "wof:name":"Noormannen, De",
    "wof:placetype":"venue"
},
  "geometry": {"coordinates":[3.43955,51.527538],"type":"Point"}
}