{
  "type": "Feature",
  "properties": {
    "addr:full":"K Kerkstr 11 Geldrop Noord-Brabant 5664 HE",
    "addr:housenumber":"11",
    "addr:postcode":"5664 he",
    "addr:street":"Kerkstr",
    "iso:country":"NL",
    "sg:address":"K Kerkstr 11",
    "sg:city":"Geldrop",
    "sg:orig_category":"Boeken En Tijdschriften",
    "sg:phone":"+31 40 286 2967",
    "sg:postcode":"5664 HE",
    "sg:province":"Noord-Brabant",
    "wof:name":"Grinsven, Fa Van",
    "wof:placetype":"venue"
},
  "geometry": {"coordinates":[5.558152,51.421303],"type":"Point"}
}