{
  "type": "Feature",
  "properties": {
    "iso:country":"NL",
    "sg:address":"Herenstraat 19",
    "sg:city":"Raalte",
    "sg:orig_category":"Boekenuitgeverijen",
    "sg:phone":"+31 572 351 300",
    "sg:postcode":"8102  C",
    "sg:province":"NL.08",
    "wof:name":"Bruna",
    "wof:placetype":"venue"
},
  "geometry": {"coordinates":[6.275134,52.386505],"type":"Point"}
}