{
  "type": "Feature",
  "properties": {
    "addr:full":"Nyverheidsstr 3-A Hoofddorp Noord-Holland 2132 AZ",
    "addr:housenumber":"3-a",
    "addr:postcode":"2132 az",
    "addr:street":"Nyverheidsstr",
    "iso:country":"NL",
    "sg:address":"Nyverheidsstr 3-A",
    "sg:city":"Hoofddorp",
    "sg:orig_category":"Drukkerijen",
    "sg:phone":"+31 23 564 0750",
    "sg:postcode":"2132 AZ",
    "sg:province":"Noord-Holland",
    "sg:website":"http://www.pre-press.nl",
    "wof:name":"Pre-Press & Copy Partners Bv",
    "wof:placetype":"venue"
},
  "geometry": {"coordinates":[4.697123,52.306038],"type":"Point"}
}