{
  "type": "Feature",
  "properties": {
    "addr:full":"Bikoln 55 Culemborg Gelderland 4105 HB",
    "addr:housenumber":"55",
    "addr:postcode":"4105 hb",
    "addr:street":"Bikoln;Gelderland",
    "iso:country":"NL",
    "sg:address":"Bikoln 55",
    "sg:city":"Culemborg",
    "sg:orig_category":"Projectontwikkeling",
    "sg:phone":"+31 345 530 246",
    "sg:postcode":"4105 HB",
    "sg:province":"Gelderland",
    "wof:name":"Heuvel, Henk Van Den",
    "wof:placetype":"venue"
},
  "geometry": {"coordinates":[5.22148,51.952175],"type":"Point"}
}