{
  "type": "Feature",
  "properties": {
    "iso:country":"NL",
    "sg:address":"Endegeest 2",
    "sg:city":"Bergen Nh",
    "sg:orig_category":"Binnenhuisarchitectuur",
    "sg:phone":"+31 6 29474943",
    "sg:postcode":"1861 VL",
    "sg:province":"North Holland",
    "wof:name":"Freelans",
    "wof:placetype":"venue"
},
  "geometry": {"coordinates":[4.696696,52.661228],"type":"Point"}
}