{
  "type": "Feature",
  "properties": {
    "iso:country":"NL",
    "sg:address":"Thurledewg 200",
    "sg:city":"Rotterdam",
    "sg:orig_category":"Verenigingen En Stichtingen",
    "sg:phone":"+31 10 415 2393",
    "sg:postcode":"3044 ES",
    "sg:province":"Zuid-Holland",
    "wof:name":"Rvv Eds",
    "wof:placetype":"venue"
},
  "geometry": {"coordinates":[4.414673,51.926579],"type":"Point"}
}