{
  "type": "Feature",
  "properties": {
    "addr:full":"Jansweg 15 Haarlem Noord-Holland 2011 KL",
    "addr:housenumber":"15",
    "addr:postcode":"2011 kl",
    "addr:street":"Jansweg",
    "iso:country":"NL",
    "sg:address":"Jansweg 15",
    "sg:city":"Haarlem",
    "sg:orig_category":"Werving And Selectie Van Vast Personeel",
    "sg:phone":"+31 23 553 2300",
    "sg:postcode":"2011 KL",
    "sg:province":"Noord-Holland",
    "wof:name":"Arbeidsbureau Haarlem",
    "wof:placetype":"venue"
},
  "geometry": {"coordinates":[4.6402459145,52.3872718811],"type":"Point"}
}