{
  "type": "Feature",
  "properties": {
    "addr:full":"De Grote Pol 11 Westervoort Gelderland 6932 DS",
    "addr:housenumber":"11",
    "addr:postcode":"6932 ds",
    "addr:street":"De Grote Pol;Gelderland",
    "iso:country":"NL",
    "sg:address":"De Grote Pol 11",
    "sg:city":"Westervoort",
    "sg:orig_category":"Goederenvervoer Over De Weg",
    "sg:phone":"+31 26 311 6236",
    "sg:postcode":"6932 DS",
    "sg:province":"Gelderland",
    "wof:name":"Gebroeders Wigman Cv",
    "wof:placetype":"venue"
},
  "geometry": {"coordinates":[5.98488,51.948151],"type":"Point"}
}