{
  "type": "Feature",
  "properties": {
    "addr:full":"H Kropln 101 S Gravenhage Zuid-Holland 2552 XP",
    "addr:housenumber":"101;gravenhage",
    "addr:postcode":"2552 xp",
    "addr:street":"S",
    "iso:country":"NL",
    "sg:address":"H Kropln 101",
    "sg:city":"S Gravenhage",
    "sg:orig_category":"Schoenen - Reparaties",
    "sg:phone":"+31 70 391 1934",
    "sg:postcode":"2552 XP",
    "sg:province":"Zuid-Holland",
    "wof:name":"Schoenmakerij Houtwijk",
    "wof:placetype":"venue"
},
  "geometry": {"coordinates":[4.24958,52.053631],"type":"Point"}
}