{
  "type": "Feature",
  "properties": {
    "addr:full":"Beatrixstr 12 Nieuwegein Utrecht 3433 CS",
    "addr:housenumber":"12",
    "addr:postcode":"3433 cs",
    "addr:street":"Beatrixstr",
    "iso:country":"NL",
    "sg:address":"Beatrixstr 12",
    "sg:city":"Nieuwegein",
    "sg:orig_category":"Glazenwasserijen",
    "sg:phone":"+31 6 51545861",
    "sg:postcode":"3433 CS",
    "sg:province":"Utrecht",
    "wof:name":"Kuik, Gilbert",
    "wof:placetype":"venue"
},
  "geometry": {"coordinates":[5.094341,52.007057],"type":"Point"}
}