{
  "type": "Feature",
  "properties": {
    "addr:full":"Oranjelaan 2 Baarle Nassau North Brabant 5111 XK",
    "addr:housenumber":"2",
    "addr:postcode":"5111 xk",
    "addr:street":"Oranjelaan",
    "iso:country":"NL",
    "sg:address":"Oranjelaan 2",
    "sg:city":"Baarle Nassau",
    "sg:orig_category":"Boekhouders",
    "sg:phone":"+31 13 507 8651",
    "sg:postcode":"5111 XK",
    "sg:province":"North Brabant",
    "wof:name":"Ad Meeuwesen",
    "wof:placetype":"venue"
},
  "geometry": {"coordinates":[4.927646,51.449669],"type":"Point"}
}