{
  "type": "Feature",
  "properties": {
    "addr:full":"Postbus 512 Arnhem Gelderland 6800 AM",
    "addr:housenumber":"512",
    "addr:postcode":"6800",
    "addr:street":"Postbus",
    "iso:country":"NL",
    "sg:address":"Postbus 512",
    "sg:city":"Arnhem",
    "sg:orig_category":"Onroerende Goederen",
    "sg:phone":"+31 26 351 0150",
    "sg:postcode":"6800 AM",
    "sg:province":"Gelderland",
    "wof:name":"Avb Bv",
    "wof:placetype":"venue"
},
  "geometry": {"coordinates":[5.9124,51.979729],"type":"Point"}
}