{
  "type": "Feature",
  "properties": {
    "addr:full":"Copernicuslaan 101 'S Hertogenbosch Noord-Brabant 5223 EC",
    "addr:housenumber":"101 ' s",
    "addr:postcode":"5223 ec",
    "addr:street":"Copernicuslaan",
    "iso:country":"NL",
    "sg:address":"Copernicuslaan 101",
    "sg:city":"'S Hertogenbosch",
    "sg:classifiers":[
        {
            "category":"Fast Food",
            "type":"Food & Drink"
        }
    ],
    "sg:phone":"+31 73 621 5194",
    "sg:postcode":"5223 EC",
    "sg:province":"Noord-Brabant",
    "sg:tags":[
        "afhaal",
        "restaurant"
    ],
    "wof:name":"Cafetaria 'T Bikkertje",
    "wof:placetype":"venue"
},
  "geometry": {"coordinates":[5.289064,51.695351],"type":"Point"}
}