{
  "type": "Feature",
  "properties": {
    "addr:full":"Orteliusstr 104 Amsterdam Noord-Holland 1057 BE",
    "addr:housenumber":"104",
    "addr:postcode":"1057",
    "iso:country":"NL",
    "sg:address":"Orteliusstr 104",
    "sg:city":"Amsterdam",
    "sg:orig_category":"Video - Faciliteiten En Producties",
    "sg:phone":"+31 20 771 0996",
    "sg:postcode":"1057 BE",
    "sg:province":"Noord-Holland",
    "wof:name":"Mary'S Inventions",
    "wof:placetype":"venue"
},
  "geometry": {"coordinates":[4.850622,52.367409],"type":"Point"}
}