{
  "type": "Feature",
  "properties": {
    "addr:full":"Nyverheidswg 33 Oudenbosch Noord-Brabant 4731 CZ",
    "addr:housenumber":"33",
    "addr:postcode":"4731",
    "addr:street":"Nyverheidswg",
    "iso:country":"NL",
    "sg:address":"Nyverheidswg 33",
    "sg:city":"Oudenbosch",
    "sg:classifiers":[
        {
            "category":"Retail",
            "subcategory":"Auto Repair",
            "type":"Services"
        }
    ],
    "sg:phone":"+31 165 311 811",
    "sg:postcode":"4731 CZ",
    "sg:province":"Noord-Brabant",
    "sg:tags":[
        "garage"
    ],
    "wof:name":"Cocar",
    "wof:placetype":"venue"
},
  "geometry": {"coordinates":[4.557647,51.58992],"type":"Point"}
}