{
  "type": "Feature",
  "properties": {
    "addr:full":"Wilgenln 35 Oud Alblas Zuid-Holland 2969 BT",
    "addr:housenumber":"35",
    "addr:postcode":"2969 bt",
    "addr:street":"Wilgenln;Oud Alblas",
    "iso:country":"NL",
    "sg:address":"Wilgenln 35",
    "sg:city":"Oud Alblas",
    "sg:orig_category":"Loodgieters",
    "sg:phone":"+31 184 693 303",
    "sg:postcode":"2969 BT",
    "sg:province":"Zuid-Holland",
    "wof:name":"Putten, R Van",
    "wof:placetype":"venue"
},
  "geometry": {"coordinates":[4.706906,51.856979],"type":"Point"}
}