{
  "type": "Feature",
  "properties": {
    "addr:full":"Oude Loswal 2B Hilversum Noord-Holland 1217 TG",
    "addr:housenumber":"2b",
    "addr:postcode":"1217 tg",
    "addr:street":"Oude Loswal",
    "iso:country":"NL",
    "sg:address":"Oude Loswal 2B",
    "sg:city":"Hilversum",
    "sg:orig_category":"Meubelreparatie And -Restauratie",
    "sg:phone":"+31 35 628 2906",
    "sg:postcode":"1217 TG",
    "sg:province":"Noord-Holland",
    "wof:name":"P.H.E.H. Murre",
    "wof:placetype":"venue"
},
  "geometry": {"coordinates":[5.15645,52.223133],"type":"Point"}
}