{
  "type": "Feature",
  "properties": {
    "iso:country":"NL",
    "sg:address":"Ryksstrwg 162",
    "sg:city":"Leersum",
    "sg:classifiers":[
        {
            "category":"Travel",
            "subcategory":"Hotels & Motels",
            "type":"Entertainment"
        }
    ],
    "sg:phone":"+31 343 451 381",
    "sg:postcode":"3956 CV",
    "sg:province":"Utrecht",
    "wof:name":"Vogelesang, C",
    "wof:placetype":"venue"
},
  "geometry": {"coordinates":[5.43237,52.010792],"type":"Point"}
}