{
  "type": "Feature",
  "properties": {
    "iso:country":"NL",
    "sg:address":"Franse Kampweg 5A",
    "sg:city":"Bussum",
    "sg:orig_category":"Kampeerterreinen",
    "sg:phone":"+31 35 691 1832",
    "sg:postcode":"1406 NV",
    "sg:province":"Noord-Holland",
    "wof:name":"Camping De Fransche Kamp",
    "wof:placetype":"venue"
},
  "geometry": {"coordinates":[5.1513361931,52.2597961426],"type":"Point"}
}