{
  "type": "Feature",
  "properties": {
    "addr:full":"Laan Der Continenten 182 Alphen Aan Den Rijn Zuid-Holland 2404 WE",
    "addr:housenumber":"182",
    "addr:postcode":"2404 we",
    "addr:street":"Laan Der Continenten",
    "iso:country":"NL",
    "sg:address":"Laan Der Continenten 182",
    "sg:city":"Alphen Aan Den Rijn",
    "sg:orig_category":"Administratie- En Boekhoudkantoren",
    "sg:phone":"+31 172 470 553",
    "sg:postcode":"2404 WE",
    "sg:province":"Zuid-Holland",
    "wof:name":"Alfa Service",
    "wof:placetype":"venue"
},
  "geometry": {"coordinates":[4.65436,52.128601],"type":"Point"}
}