{
  "type": "Feature",
  "properties": {
    "addr:full":"Spoordonksewg 44 Oirschot Noord-Brabant 5688 KD",
    "addr:housenumber":"44",
    "addr:postcode":"5688 kd",
    "addr:street":"Spoordonksewg",
    "iso:country":"NL",
    "sg:address":"Spoordonksewg 44",
    "sg:city":"Oirschot",
    "sg:orig_category":"Open Haarden",
    "sg:phone":"+31 499 574 808",
    "sg:postcode":"5688 KD",
    "sg:province":"Noord-Brabant",
    "wof:name":"Fire Design",
    "wof:placetype":"venue"
},
  "geometry": {"coordinates":[5.299426,51.509789],"type":"Point"}
}