{
  "type": "Feature",
  "properties": {
    "addr:full":"Zuiderkruis 416 Veenendaal Utrecht 3902 XM",
    "addr:housenumber":"416",
    "addr:postcode":"3902 xm",
    "addr:street":"Zuiderkruis",
    "iso:country":"NL",
    "sg:address":"Zuiderkruis 416",
    "sg:city":"Veenendaal",
    "sg:orig_category":"Bloemen And Planten",
    "sg:phone":"+31 318 551 749",
    "sg:postcode":"3902 XM",
    "sg:province":"Utrecht",
    "wof:name":"Kwekerij Spitsbergen",
    "wof:placetype":"venue"
},
  "geometry": {"coordinates":[5.570627,52.023972],"type":"Point"}
}