{
  "type": "Feature",
  "properties": {
    "addr:full":"Pleinwg 136 Rotterdam Zuid-Holland 3083 EP",
    "addr:housenumber":"136",
    "addr:postcode":"3083 ep",
    "iso:country":"NL",
    "sg:address":"Pleinwg 136",
    "sg:city":"Rotterdam",
    "sg:orig_category":"Huishoudapparatuur, Televisies And Radio'S",
    "sg:phone":"+31 10 481 6644",
    "sg:postcode":"3083 EP",
    "sg:province":"Zuid-Holland",
    "wof:name":"Dick Bakker Stereo Architectuur",
    "wof:placetype":"venue"
},
  "geometry": {"coordinates":[4.4816,51.890762],"type":"Point"}
}