{
  "type": "Feature",
  "properties": {
    "addr:full":"J W Frisoln 3C-3D S Gravenhage Zuid-Holland 2517 JS",
    "addr:postcode":"2517 js",
    "addr:street":"3C-3D",
    "iso:country":"NL",
    "sg:address":"J W Frisoln 3C-3D",
    "sg:city":"S Gravenhage",
    "sg:orig_category":"Verzekeringen - Verzekeringskantoren",
    "sg:phone":"+31 70 338 3000",
    "sg:postcode":"2517 JS",
    "sg:province":"Zuid-Holland",
    "sg:website":"http://www.ksagroep.nl",
    "wof:name":"Kervezee Schotte Bv",
    "wof:placetype":"venue"
},
  "geometry": {"coordinates":[4.28708,52.08667],"type":"Point"}
}