{
  "type": "Feature",
  "properties": {
    "addr:full":"Broekerhavenwg 168 Bovenkarspel Noord-Holland 1611 CJ",
    "addr:housenumber":"168",
    "addr:postcode":"1611 cj",
    "iso:country":"NL",
    "sg:address":"Broekerhavenwg 168",
    "sg:city":"Bovenkarspel",
    "sg:orig_category":"Schilders",
    "sg:phone":"+31 6 25087879",
    "sg:postcode":"1611 CJ",
    "sg:province":"Noord-Holland",
    "wof:name":"Bakker, Lowie",
    "wof:placetype":"venue"
},
  "geometry": {"coordinates":[5.252583,52.693047],"type":"Point"}
}