{
  "type": "Feature",
  "properties": {
    "addr:full":"Kwelkd 53 Tiel Gelderland 4001 RL",
    "addr:housenumber":"53",
    "addr:postcode":"4001 rl",
    "addr:street":"Kwelkd;Gelderland",
    "iso:country":"NL",
    "sg:address":"Kwelkd 53",
    "sg:city":"Tiel",
    "sg:classifiers":[
        {
            "category":"Food & Beverages",
            "subcategory":"Bakery",
            "type":"Retail Goods"
        }
    ],
    "sg:phone":"+31 344 615 256",
    "sg:postcode":"4001 RL",
    "sg:province":"Gelderland",
    "sg:tags":[
        "brood",
        "en",
        "banket"
    ],
    "wof:name":"Ehren",
    "wof:placetype":"venue"
},
  "geometry": {"coordinates":[5.430696,51.888096],"type":"Point"}
}