{
  "type": "Feature",
  "properties": {
    "iso:country":"NL",
    "sg:address":"Nieuwewg 185",
    "sg:city":"Doetinchem",
    "sg:orig_category":"Oud Metaal",
    "sg:phone":"+31 6 53922855",
    "sg:postcode":"7009 HB",
    "sg:province":"Gelderland",
    "wof:name":"Putten, Van",
    "wof:placetype":"venue"
},
  "geometry": {"coordinates":[6.2902541161,51.9690475464],"type":"Point"}
}