{
  "type": "Feature",
  "properties": {
    "addr:full":"K Elisabethstr 6 Utrecht Utrecht 3511 JG",
    "addr:housenumber":"6",
    "addr:postcode":"3511 jg",
    "addr:street":"Elisabethstr",
    "iso:country":"NL",
    "sg:address":"K Elisabethstr 6",
    "sg:city":"Utrecht",
    "sg:orig_category":"Verenigingen En Stichtingen",
    "sg:phone":"+31 30 232 8042",
    "sg:postcode":"3511 JG",
    "sg:province":"Utrecht",
    "wof:name":"Spolu Int Foundation",
    "wof:placetype":"venue"
},
  "geometry": {"coordinates":[5.115479,52.091087],"type":"Point"}
}