{
  "type": "Feature",
  "properties": {
    "iso:country":"NL",
    "sg:address":"Postbus 82",
    "sg:city":"Raalte",
    "sg:orig_category":"Waterleidingbedrijven",
    "sg:phone":"+31 572 854 000",
    "sg:postcode":"8100 AB",
    "sg:province":"Overijssel",
    "sg:website":"http://www.vitens.nl",
    "wof:name":"Vitens Overijssel",
    "wof:placetype":"venue"
},
  "geometry": {"coordinates":[6.2746281624,52.3872489929],"type":"Point"}
}