{
  "type": "Feature",
  "properties": {
    "addr:full":"Boomstede 206 Maarssen Utrecht 3608 AK",
    "addr:housenumber":"206",
    "addr:postcode":"3608 ak",
    "addr:street":"Boomstede",
    "iso:country":"NL",
    "sg:address":"Boomstede 206",
    "sg:city":"Maarssen",
    "sg:orig_category":"Zuivelproducten",
    "sg:phone":"+31 346 569 027",
    "sg:postcode":"3608 AK",
    "sg:province":"Utrecht",
    "wof:name":"Kaasspeciaalzaak Dammers Vof",
    "wof:placetype":"venue"
},
  "geometry": {"coordinates":[5.029095,52.1241],"type":"Point"}
}