{
  "type": "Feature",
  "properties": {
    "addr:full":"Mgr. Nolenslaan 7 Amstelveen Noord-Holland 1181 VL",
    "addr:housenumber":"7",
    "addr:postcode":"1181 vl",
    "addr:street":"Mgr. Nolenslaan",
    "iso:country":"NL",
    "sg:address":"Mgr. Nolenslaan 7",
    "sg:city":"Amstelveen",
    "sg:orig_category":"Bloemen And Planten Gh",
    "sg:phone":"+31 20 641 4575",
    "sg:postcode":"1181 VL",
    "sg:province":"Noord-Holland",
    "wof:name":"J.C. Fransen",
    "wof:placetype":"venue"
},
  "geometry": {"coordinates":[4.851672,52.30526],"type":"Point"}
}