{
  "type": "Feature",
  "properties": {
    "iso:country":"NL",
    "sg:address":"Reigerstr 61",
    "sg:city":"Badhoevedorp",
    "sg:orig_category":"Goudsmeden En Zilversmeden",
    "sg:phone":"+31 20 659 8762",
    "sg:postcode":"1171 TP",
    "sg:province":"Noord-Holland",
    "wof:name":"Yet Art",
    "wof:placetype":"venue"
},
  "geometry": {"coordinates":[4.780719,52.338074],"type":"Point"}
}