{
  "type": "Feature",
  "properties": {
    "iso:country":"NL",
    "sg:address":"Broeklanderweg 12",
    "sg:city":"Beemte Broekland",
    "sg:orig_category":"Vaste And Vloeibare Brandstoffen",
    "sg:phone":"+31 55 312 1544",
    "sg:postcode":"7341 PJ",
    "sg:province":"Gelderland",
    "wof:name":"B.H. Disbergen",
    "wof:placetype":"venue"
},
  "geometry": {"coordinates":[5.992558,52.265686],"type":"Point"}
}