{
  "type": "Feature",
  "properties": {
    "addr:full":"Weissenbruchstraat 29Bg Amsterdam Noord-Holland 1058 KL",
    "addr:housenumber":"29bg",
    "addr:postcode":"1058 kl",
    "addr:street":"Weissenbruchstraat",
    "iso:country":"NL",
    "sg:address":"Weissenbruchstraat 29Bg",
    "sg:city":"Amsterdam",
    "sg:orig_category":"Antiekzaken",
    "sg:phone":"+31 20 669 0247",
    "sg:postcode":"1058 KL",
    "sg:province":"Noord-Holland",
    "wof:name":"Antiquariaat Ls",
    "wof:placetype":"venue"
},
  "geometry": {"coordinates":[4.851009,52.35321],"type":"Point"}
}