{
  "type": "Feature",
  "properties": {
    "addr:full":"Mient 14B Capelle Ad Ijssel South Holland 2903 LC",
    "addr:housenumber":"14b",
    "addr:postcode":"2903 lc",
    "addr:street":"Mient;Ijssel",
    "iso:country":"NL",
    "sg:address":"Mient 14B",
    "sg:city":"Capelle Ad Ijssel",
    "sg:orig_category":"Koffers And Tassen Fab",
    "sg:phone":"+31 10 458 6564",
    "sg:postcode":"2903 LC",
    "sg:province":"South Holland",
    "wof:name":"Across International",
    "wof:placetype":"venue"
},
  "geometry": {"coordinates":[4.586955,51.924328],"type":"Point"}
}