{
  "type": "Feature",
  "properties": {
    "addr:full":"Looiersln 36 Leidschendam South Holland 2264 AB",
    "addr:housenumber":"36",
    "addr:postcode":"2264 ab",
    "addr:street":"Looiersln",
    "iso:country":"NL",
    "sg:address":"Looiersln 36",
    "sg:city":"Leidschendam",
    "sg:orig_category":"Administratie- En Boekhoudkantoren",
    "sg:phone":"+31 70 327 9295",
    "sg:postcode":"2264 AB",
    "sg:province":"South Holland",
    "wof:name":"Leijs",
    "wof:placetype":"venue"
},
  "geometry": {"coordinates":[4.393446,52.084591],"type":"Point"}
}