{
  "type": "Feature",
  "properties": {
    "addr:full":"Verwoldsewg 14 Laren Gld Gelderland 7245 AH",
    "addr:housenumber":"14",
    "addr:postcode":"7245 ah",
    "addr:street":"Verwoldsewg;Gld Gelderland",
    "iso:country":"NL",
    "sg:address":"Verwoldsewg 14",
    "sg:city":"Laren Gld",
    "sg:orig_category":"Peuterspeelzalen",
    "sg:phone":"+31 573 402 114",
    "sg:postcode":"7245 AH",
    "sg:province":"Gelderland",
    "wof:name":"Krummelhuske, 'T",
    "wof:placetype":"venue"
},
  "geometry": {"coordinates":[6.36788,52.19305],"type":"Point"}
}