{
  "type": "Feature",
  "properties": {
    "iso:country":"NL",
    "sg:address":"Bongerdplein 34",
    "sg:city":"Epe",
    "sg:orig_category":"Meubelzaken, Woning- And Keukeninrichting",
    "sg:phone":"+31 578 613 780",
    "sg:postcode":"8162 AZ",
    "sg:province":"Gelderland",
    "wof:name":"Woninginrichting Kasteel Bv",
    "wof:placetype":"venue"
},
  "geometry": {"coordinates":[5.980906,52.346413],"type":"Point"}
}