{
  "type": "Feature",
  "properties": {
    "iso:country":"NL",
    "sg:address":"Botreep 238",
    "sg:city":"Hoogvliet Rt",
    "sg:orig_category":"Koeriersdiensten",
    "sg:phone":"+31 10 416 3752",
    "sg:postcode":"3192 PE",
    "sg:province":"Zuid-Holland",
    "wof:name":"Kuyper",
    "wof:placetype":"venue"
},
  "geometry": {"coordinates":[4.370461,51.852627],"type":"Point"}
}