{
  "type": "Feature",
  "properties": {
    "addr:full":"Rijklof Van Goensstraat 10 'S Gravenhage Zuid-Holland 2593 EH",
    "addr:housenumber":"10",
    "addr:postcode":"2593 eh",
    "addr:street":"Rijklof Van Goensstraat;' S",
    "iso:country":"NL",
    "sg:address":"Rijklof Van Goensstraat 10",
    "sg:city":"'S Gravenhage",
    "sg:orig_category":"Autokeuringen",
    "sg:phone":"+31 70 381 5443",
    "sg:postcode":"2593 EH",
    "sg:province":"Zuid-Holland",
    "wof:name":"Ben Devilee Car Technics",
    "wof:placetype":"venue"
},
  "geometry": {"coordinates":[4.336795,52.087036],"type":"Point"}
}