{
  "type": "Feature",
  "properties": {
    "addr:full":"Javastraat 66 Amsterdam Noord-Holland 1094 HK",
    "addr:housenumber":"66",
    "addr:postcode":"1094 hk",
    "addr:street":"Javastraat",
    "iso:country":"NL",
    "sg:address":"Javastraat 66",
    "sg:city":"Amsterdam",
    "sg:classifiers":[
        {
            "category":"Retail",
            "subcategory":"Photofinishing",
            "type":"Services"
        }
    ],
    "sg:phone":"+31 20 693 6492",
    "sg:postcode":"1094 HK",
    "sg:province":"Noord-Holland",
    "sg:tags":[
        "foto",
        "film"
    ],
    "wof:name":"Vic'S Foto",
    "wof:placetype":"venue"
},
  "geometry": {"coordinates":[4.934293,52.363564],"type":"Point"}
}