{
  "type": "Feature",
  "properties": {
    "addr:full":"J F Kennedyln 99 Bunnik Utrecht 3981 GB",
    "addr:housenumber":"99",
    "addr:postcode":"3981 gb",
    "addr:street":"J F Kennedyln",
    "iso:country":"NL",
    "sg:address":"J F Kennedyln 99",
    "sg:city":"Bunnik",
    "sg:orig_category":"Verenigingen En Stichtingen",
    "sg:phone":"+31 30 656 5042",
    "sg:postcode":"3981 GB",
    "sg:province":"Utrecht",
    "wof:name":"Ando",
    "wof:placetype":"venue"
},
  "geometry": {"coordinates":[5.19958,52.067097],"type":"Point"}
}