{
  "type": "Feature",
  "properties": {
    "addr:full":"Bakkerswg 8 Voorthuizen Gelderland 3781 GP",
    "addr:housenumber":"8",
    "addr:postcode":"3781 gp",
    "addr:street":"Bakkerswg;Gelderland",
    "iso:country":"NL",
    "sg:address":"Bakkerswg 8",
    "sg:city":"Voorthuizen",
    "sg:orig_category":"Administratie- En Boekhoudkantoren",
    "sg:phone":"+31 342 471 270",
    "sg:postcode":"3781 GP",
    "sg:province":"Gelderland",
    "wof:name":"Hekkelman",
    "wof:placetype":"venue"
},
  "geometry": {"coordinates":[5.609774,52.18634],"type":"Point"}
}