{
  "type": "Feature",
  "properties": {
    "addr:full":"Hoofdstraat 193 Sassenheim Zuid-Holland 2171 BC",
    "addr:housenumber":"193",
    "addr:postcode":"2171 bc",
    "addr:street":"Hoofdstraat",
    "iso:country":"NL",
    "sg:address":"Hoofdstraat 193",
    "sg:city":"Sassenheim",
    "sg:classifiers":[
        {
            "category":"Fast Food",
            "type":"Food & Drink"
        }
    ],
    "sg:phone":"+31 252 211 423",
    "sg:postcode":"2171 BC",
    "sg:province":"Zuid-Holland",
    "sg:tags":[
        "afhaal",
        "restaurant"
    ],
    "wof:name":"Automathiek Postma",
    "wof:placetype":"venue"
},
  "geometry": {"coordinates":[4.521698,52.226223],"type":"Point"}
}