{
  "type": "Feature",
  "properties": {
    "iso:country":"NL",
    "sg:address":"Larix 28",
    "sg:city":"Hellevoetsluis",
    "sg:orig_category":"Adviesbureaus Gezondheidszorg",
    "sg:phone":"+31 181 320 746",
    "sg:postcode":"3224 ET",
    "sg:province":"Zuid-Holland",
    "wof:name":"Bonefaas Medical Bv",
    "wof:placetype":"venue"
},
  "geometry": {"coordinates":[4.154496,51.827423],"type":"Point"}
}