{
  "type": "Feature",
  "properties": {
    "addr:full":"Heerlenersteenwg 81 Kerkrade Limburg 6466 KS",
    "addr:housenumber":"81",
    "addr:postcode":"6466 ks",
    "addr:street":"Heerlenersteenwg",
    "iso:country":"NL",
    "sg:address":"Heerlenersteenwg 81",
    "sg:city":"Kerkrade",
    "sg:classifiers":[
        {
            "category":"Travel",
            "subcategory":"Hotels & Motels",
            "type":"Entertainment"
        }
    ],
    "sg:phone":"+31 45 542 0909",
    "sg:postcode":"6466 KS",
    "sg:province":"Limburg",
    "sg:website":"http://www.hotelformule1.com",
    "wof:name":"Formule 1 Hotel",
    "wof:placetype":"venue"
},
  "geometry": {"coordinates":[6.03203,50.86475],"type":"Point"}
}