{
  "type": "Feature",
  "properties": {
    "addr:full":"Postbus 92 Bergum Provincie Friesland 9250 AB",
    "addr:housenumber":"92",
    "addr:postcode":"9250 ab",
    "addr:street":"Postbus;Provincie Friesland",
    "iso:country":"NL",
    "sg:address":"Postbus 92",
    "sg:city":"Bergum",
    "sg:orig_category":"Verhuizingen",
    "sg:phone":"+31 512 471 650",
    "sg:postcode":"9250 AB",
    "sg:province":"Provincie Friesland",
    "wof:name":"Hoekema Verhuizingen",
    "wof:placetype":"venue"
},
  "geometry": {"coordinates":[5.9896,53.18951],"type":"Point"}
}