{
  "type": "Feature",
  "properties": {
    "addr:full":"Meent 17 Veldhoven North Brabant 5501 JJ",
    "addr:housenumber":"17",
    "addr:postcode":"5501 jj",
    "addr:street":"Meent",
    "iso:country":"NL",
    "sg:address":"Meent 17",
    "sg:city":"Veldhoven",
    "sg:classifiers":[
        {
            "category":"Food & Beverages",
            "subcategory":"Fruits & Vegetables",
            "type":"Retail Goods"
        }
    ],
    "sg:phone":"+31 40 254 9536",
    "sg:postcode":"5501 JJ",
    "sg:province":"North Brabant",
    "sg:tags":[
        "groenten"
    ],
    "wof:name":"Groente- En Fruitspec. Strijbosch",
    "wof:placetype":"venue"
},
  "geometry": {"coordinates":[5.405948,51.419064],"type":"Point"}
}