{
  "type": "Feature",
  "properties": {
    "addr:full":"Picassopassage 25 Capelle A/D Ijssel South Holland 2907 ME",
    "addr:housenumber":"25;a / d",
    "addr:postcode":"2907 me",
    "addr:street":"Picassopassage;Ijssel South",
    "iso:country":"NL",
    "sg:address":"Picassopassage 25",
    "sg:city":"Capelle A/D Ijssel",
    "sg:orig_category":"Kappers",
    "sg:phone":"+31 10 458 3505",
    "sg:postcode":"2907 ME",
    "sg:province":"South Holland",
    "wof:name":"Coiffure Wout Rombout Capelle A/D Ijssel",
    "wof:placetype":"venue"
},
  "geometry": {"coordinates":[4.5843338966,51.9533615112],"type":"Point"}
}