{
  "type": "Feature",
  "properties": {
    "addr:full":"Rossinilaan 14 Doetinchem Gelderland 7002 LT",
    "addr:housenumber":"14",
    "addr:postcode":"7002 lt",
    "addr:street":"Rossinilaan;Gelderland",
    "iso:country":"NL",
    "sg:address":"Rossinilaan 14",
    "sg:city":"Doetinchem",
    "sg:orig_category":"Fitnesscentra",
    "sg:phone":"+31 314 340 151",
    "sg:postcode":"7002 LT",
    "sg:province":"Gelderland",
    "wof:name":"Judoryu Doetinchem",
    "wof:placetype":"venue"
},
  "geometry": {"coordinates":[6.311027,51.96867],"type":"Point"}
}