{
  "type": "Feature",
  "properties": {
    "iso:country":"NL",
    "sg:address":"Deltapln 150-152",
    "sg:city":"S Gravenhage",
    "sg:orig_category":"Herenkleding",
    "sg:phone":"+31 70 325 4487",
    "sg:postcode":"2554 GR",
    "sg:province":"Zuid-Holland",
    "sg:website":"http://www.carlo.nl",
    "wof:name":"Carlo",
    "wof:placetype":"venue"
},
  "geometry": {"coordinates":[4.22476,52.067989],"type":"Point"}
}