{
  "type": "Feature",
  "properties": {
    "addr:full":"Postbus 24 Capelle Ad Yssel 2900 AA",
    "addr:housenumber":"24",
    "addr:postcode":"2900 aa",
    "addr:street":"Postbus;Yssel",
    "iso:country":"NL",
    "sg:address":"Postbus 24",
    "sg:city":"Capelle Ad Yssel",
    "sg:orig_category":"Bejaarden - Verzorgingstehuizen",
    "sg:phone":"+31 10 258 8155",
    "sg:postcode":"2900 AA",
    "wof:name":"Zorgbreed, Stichting",
    "wof:placetype":"venue"
},
  "geometry": {"coordinates":[4.5897,51.932758],"type":"Point"}
}