{
  "type": "Feature",
  "properties": {
    "iso:country":"NL",
    "sg:address":"Spinozawg 2",
    "sg:city":"Utrecht",
    "sg:orig_category":"Makelaars En Adviseurs Onroerende Goederen",
    "sg:phone":"+31 30 293 8108",
    "sg:postcode":"3532 SG",
    "sg:province":"Utrecht",
    "wof:name":"Willems, Bert",
    "wof:placetype":"venue"
},
  "geometry": {"coordinates":[5.085928,52.094765],"type":"Point"}
}