{
  "type": "Feature",
  "properties": {
    "addr:full":"Achterdijk 183 Zevenbergschen Hoek Noord-Brabant 4765 RE",
    "addr:housenumber":"183",
    "addr:postcode":"4765 re",
    "addr:street":"Achterdijk",
    "iso:country":"NL",
    "sg:address":"Achterdijk 183",
    "sg:city":"Zevenbergschen Hoek",
    "sg:orig_category":"Diverse Grafische Activiteiten",
    "sg:phone":"+31 168 452 889",
    "sg:postcode":"4765 RE",
    "sg:province":"Noord-Brabant",
    "wof:name":"Professional Text Design",
    "wof:placetype":"venue"
},
  "geometry": {"coordinates":[4.664118,51.676632],"type":"Point"}
}