{
  "type": "Feature",
  "properties": {
    "addr:full":"Driebergseweg 17 Zeist Utrecht 3708 JA",
    "addr:housenumber":"17",
    "addr:postcode":"3708 ja",
    "addr:street":"Driebergseweg",
    "iso:country":"NL",
    "sg:address":"Driebergseweg 17",
    "sg:city":"Zeist",
    "sg:orig_category":"Werving And Selectie Van Vast Personeel",
    "sg:phone":"+31 30 210 0400",
    "sg:postcode":"3708 JA",
    "sg:province":"Utrecht",
    "wof:name":"Panta Rhei",
    "wof:placetype":"venue"
},
  "geometry": {"coordinates":[5.2583651543,52.0678672791],"type":"Point"}
}