{
  "type": "Feature",
  "properties": {
    "addr:full":"Stommeerkade 21 A Aalsmeer North Holland 1431 EJ",
    "addr:housenumber":"21 a",
    "addr:postcode":"1431 ej",
    "addr:street":"Stommeerkade",
    "iso:country":"NL",
    "sg:address":"Stommeerkade 21 A",
    "sg:city":"Aalsmeer",
    "sg:orig_category":"Huishoudapparatuur, Televisies And Radio'S",
    "sg:phone":"+31 297 331 100",
    "sg:postcode":"1431 EJ",
    "sg:province":"North Holland",
    "wof:name":"Robesat",
    "wof:placetype":"venue"
},
  "geometry": {"coordinates":[4.753387,52.268097],"type":"Point"}
}