{
  "type": "Feature",
  "properties": {
    "addr:full":"V Hugostr 25 Venlo Limburg 5924 AK",
    "addr:housenumber":"25",
    "addr:postcode":"5924 ak",
    "iso:country":"NL",
    "sg:address":"V Hugostr 25",
    "sg:city":"Venlo",
    "sg:orig_category":"Administratie- En Boekhoudkantoren",
    "sg:phone":"+31 77 382 2410",
    "sg:postcode":"5924 AK",
    "sg:province":"Limburg",
    "wof:name":"Broekaart Bv, W H",
    "wof:placetype":"venue"
},
  "geometry": {"coordinates":[6.13,51.366501],"type":"Point"}
}