{
  "type": "Feature",
  "properties": {
    "addr:full":"Jupiterwg 30 Zeewolde Flevoland 3893 GD",
    "addr:housenumber":"30",
    "addr:postcode":"3893 gd",
    "addr:street":"Jupiterwg;Flevoland",
    "iso:country":"NL",
    "sg:address":"Jupiterwg 30",
    "sg:city":"Zeewolde",
    "sg:orig_category":"Satellietontvangst- En Antenne-Installaties",
    "sg:phone":"+31 36 540 2000",
    "sg:postcode":"3893 GD",
    "sg:province":"Flevoland",
    "sg:website":"http://www.satxs.nl",
    "wof:name":"Sat Xs",
    "wof:placetype":"venue"
},
  "geometry": {"coordinates":[5.52176,52.340393],"type":"Point"}
}