{
  "type": "Feature",
  "properties": {
    "iso:country":"NL",
    "sg:address":"Nieuw Baarswijk 12",
    "sg:city":"Breda",
    "sg:orig_category":"Boekhouders",
    "sg:phone":"+31 76 541 6851",
    "sg:postcode":"4823 GJ",
    "sg:province":"Noord-Brabant",
    "wof:name":"Administratiekantoor Nederhand",
    "wof:placetype":"venue"
},
  "geometry": {"coordinates":[4.753848,51.624584],"type":"Point"}
}