{
  "type": "Feature",
  "properties": {
    "addr:full":"Lijsterstraat 180 Drachten Provincie Friesland 9201 TM",
    "addr:housenumber":"180",
    "addr:postcode":"9201 tm",
    "addr:street":"Lijsterstraat;Provincie Friesland",
    "iso:country":"NL",
    "sg:address":"Lijsterstraat 180",
    "sg:city":"Drachten",
    "sg:orig_category":"Kappers",
    "sg:phone":"+31 512 526 120",
    "sg:postcode":"9201 TM",
    "sg:province":"Provincie Friesland",
    "wof:name":"Salon Haarsma Haarverzorging",
    "wof:placetype":"venue"
},
  "geometry": {"coordinates":[6.101847,53.114941],"type":"Point"}
}