{
  "type": "Feature",
  "properties": {
    "addr:full":"Karbeel 16 Gemert Noord-Brabant 5421 BR",
    "addr:housenumber":"16",
    "addr:postcode":"5421 br",
    "addr:street":"Karbeel",
    "iso:country":"NL",
    "sg:address":"Karbeel 16",
    "sg:city":"Gemert",
    "sg:orig_category":"Verenigingen En Stichtingen",
    "sg:phone":"+31 492 362 383",
    "sg:postcode":"5421 BR",
    "sg:province":"Noord-Brabant",
    "wof:name":"Diomage, Sticht",
    "wof:placetype":"venue"
},
  "geometry": {"coordinates":[5.68243,51.555828],"type":"Point"}
}