{
  "type": "Feature",
  "properties": {
    "addr:full":"Diezerstraat 53 Zwolle NL.08 8011 RC",
    "addr:housenumber":"53",
    "addr:postcode":"8011 rc",
    "addr:street":"Diezerstraat",
    "iso:country":"NL",
    "sg:address":"Diezerstraat 53",
    "sg:city":"Zwolle",
    "sg:orig_category":"Juweliers",
    "sg:phone":"+31 38 422 6566",
    "sg:postcode":"8011 RC",
    "sg:province":"NL.08",
    "wof:name":"Ville D'Or Zwolle Bv",
    "wof:placetype":"venue"
},
  "geometry": {"coordinates":[6.095478,52.512669],"type":"Point"}
}