{
  "type": "Feature",
  "properties": {
    "addr:full":"Kuyperswg 42 Renkum Gelderland 6871 ED",
    "addr:housenumber":"42",
    "addr:postcode":"6871 ed",
    "addr:street":"Kuyperswg;Gelderland",
    "iso:country":"NL",
    "sg:address":"Kuyperswg 42",
    "sg:city":"Renkum",
    "sg:orig_category":"Peuterspeelzalen",
    "sg:phone":"+31 317 315 592",
    "sg:postcode":"6871 ED",
    "sg:province":"Gelderland",
    "wof:name":"Krielhuis, Het",
    "wof:placetype":"venue"
},
  "geometry": {"coordinates":[5.741958,51.977161],"type":"Point"}
}