{
  "type": "Feature",
  "properties": {
    "addr:full":"Boveneind Nz 58 Benschop Utrecht 3405 AJ",
    "addr:housenumber":"58",
    "addr:postcode":"3405 aj",
    "addr:street":"Boveneind Nz",
    "iso:country":"NL",
    "sg:address":"Boveneind Nz 58",
    "sg:city":"Benschop",
    "sg:orig_category":"Adviesbureaus",
    "sg:phone":"+31 348 451 414",
    "sg:postcode":"3405 AJ",
    "sg:province":"Utrecht",
    "wof:name":"Tendency Int Ltd",
    "wof:placetype":"venue"
},
  "geometry": {"coordinates":[5.013279,52.012691],"type":"Point"}
}