{
  "type": "Feature",
  "properties": {
    "iso:country":"NL",
    "sg:address":"Narcisstr 8",
    "sg:city":"Voorschoten",
    "sg:orig_category":"Bloemen En Planten",
    "sg:phone":"+31 71 561 0999",
    "sg:postcode":"2252 XE",
    "sg:province":"Zuid-Holland",
    "wof:name":"Groene Kamer, De",
    "wof:placetype":"venue"
},
  "geometry": {"coordinates":[4.438731,52.126446],"type":"Point"}
}