{
  "type": "Feature",
  "properties": {
    "addr:full":"Zeuven Heuvels 15 Wezep Gelderland 8091 AG",
    "addr:housenumber":"15",
    "addr:postcode":"8091",
    "addr:street":"Zeuven Heuvels",
    "iso:country":"NL",
    "sg:address":"Zeuven Heuvels 15",
    "sg:city":"Wezep",
    "sg:orig_category":"Meubelen",
    "sg:phone":"+31 38 376 3800",
    "sg:postcode":"8091 AG",
    "sg:province":"Gelderland",
    "sg:website":"http://www.istilah.nl",
    "wof:name":"Istilah",
    "wof:placetype":"venue"
},
  "geometry": {"coordinates":[5.99888,52.458267],"type":"Point"}
}