{
  "type": "Feature",
  "properties": {
    "addr:full":"Raadhuisplein 40 Stein Lb Missouri 6171 JC",
    "addr:housenumber":"40",
    "addr:postcode":"6171 jc",
    "addr:street":"Raadhuisplein",
    "iso:country":"NL",
    "sg:address":"Raadhuisplein 40",
    "sg:city":"Stein Lb",
    "sg:orig_category":"Banken And Kredietinstellingen",
    "sg:phone":"+31 46 433 3133",
    "sg:postcode":"6171 JC",
    "sg:province":"Missouri",
    "wof:name":"Abn Amro",
    "wof:placetype":"venue"
},
  "geometry": {"coordinates":[-93.129936,36.705662],"type":"Point"}
}