{
  "type": "Feature",
  "properties": {
    "addr:full":"Surinamewg 23A Apeldoorn Gelderland 7333 PC",
    "addr:housenumber":"23a",
    "addr:postcode":"7333 pc",
    "addr:street":"Surinamewg;Gelderland",
    "iso:country":"NL",
    "sg:address":"Surinamewg 23A",
    "sg:city":"Apeldoorn",
    "sg:orig_category":"Koeriersdiensten",
    "sg:phone":"+31 55 538 6677",
    "sg:postcode":"7333 PC",
    "sg:province":"Gelderland",
    "sg:website":"http://www.nldistributie.nl",
    "wof:name":"Nl Distributie",
    "wof:placetype":"venue"
},
  "geometry": {"coordinates":[5.972949,52.175972],"type":"Point"}
}