{
  "type": "Feature",
  "properties": {
    "addr:full":"Europaweg 220 Apeldoorn Gelderland 7336 AR",
    "addr:housenumber":"220",
    "addr:postcode":"7336",
    "addr:street":"Europaweg;Gelderland",
    "iso:country":"NL",
    "sg:address":"Europaweg 220",
    "sg:city":"Apeldoorn",
    "sg:orig_category":"Bedrijfsinventaris Gh",
    "sg:phone":"+31 55 543 1111",
    "sg:postcode":"7336 AR",
    "sg:province":"Gelderland",
    "wof:name":"Kappers Groothandel Apeldoorn Bv",
    "wof:placetype":"venue"
},
  "geometry": {"coordinates":[5.933727,52.192966],"type":"Point"}
}