{
  "type": "Feature",
  "properties": {
    "addr:full":"Gassngl 18 Winschoten Groningen 9671 CX",
    "addr:housenumber":"18",
    "addr:postcode":"9671 cx",
    "addr:street":"Gassngl",
    "iso:country":"NL",
    "sg:address":"Gassngl 18",
    "sg:city":"Winschoten",
    "sg:orig_category":"Fitnesscentra",
    "sg:phone":"+31 597 422 777",
    "sg:postcode":"9671 CX",
    "sg:province":"Groningen",
    "wof:name":"Bewegingscentrum",
    "wof:placetype":"venue"
},
  "geometry": {"coordinates":[7.045145,53.14658],"type":"Point"}
}