{
  "type": "Feature",
  "properties": {
    "addr:full":"Vierambachtsstr 28B Rotterdam Zuid-Holland 3023 AN",
    "addr:housenumber":"28b",
    "addr:postcode":"3023 an",
    "addr:street":"Vierambachtsstr",
    "iso:country":"NL",
    "sg:address":"Vierambachtsstr 28B",
    "sg:city":"Rotterdam",
    "sg:classifiers":[
        {
            "category":"Restaurant",
            "type":"Food & Drink"
        }
    ],
    "sg:phone":"+31 10 425 9563",
    "sg:postcode":"3023 AN",
    "sg:province":"Zuid-Holland",
    "wof:name":"Pak On",
    "wof:placetype":"venue"
},
  "geometry": {"coordinates":[4.44929,51.916451],"type":"Point"}
}