{
  "type": "Feature",
  "properties": {
    "iso:country":"NL",
    "sg:address":"De Run 5436",
    "sg:city":"Veldhoven",
    "sg:orig_category":"Autokeuringen",
    "sg:phone":"+31 40 243 3685",
    "sg:postcode":"5504 DE",
    "sg:province":"Noord-Brabant",
    "wof:name":"Autolichtstad Bv",
    "wof:placetype":"venue"
},
  "geometry": {"coordinates":[5.413004,51.409302],"type":"Point"}
}