{
  "type": "Feature",
  "properties": {
    "iso:country":"NL",
    "sg:address":"Prandinga 2",
    "sg:city":"Oosterwolde Fr",
    "sg:orig_category":"Architecten",
    "sg:phone":"+31 516 513 715",
    "sg:postcode":"8431 VP",
    "sg:province":"Friesland",
    "wof:name":"Tuinontwerp En Adviesbureau Tineke Grin",
    "wof:placetype":"venue"
},
  "geometry": {"coordinates":[6.282072,52.996006],"type":"Point"}
}