{
  "type": "Feature",
  "properties": {
    "iso:country":"NL",
    "sg:address":"Slangevecht 6",
    "sg:city":"Amersfoort",
    "sg:orig_category":"Verzekeringen",
    "sg:phone":"+31 33 480 5020",
    "sg:postcode":"3813 LT",
    "sg:province":"Utrecht",
    "wof:name":"A.J.P. Braat Assurantien",
    "wof:placetype":"venue"
},
  "geometry": {"coordinates":[5.397958,52.176304],"type":"Point"}
}