{
  "type": "Feature",
  "properties": {
    "addr:full":"Bredeweg 239 Roermond Limburg 6043 GA",
    "addr:housenumber":"239",
    "addr:postcode":"6043 ga",
    "addr:street":"Bredeweg",
    "iso:country":"NL",
    "sg:address":"Bredeweg 239",
    "sg:city":"Roermond",
    "sg:orig_category":"Overheidsdiensten",
    "sg:phone":"+31 475 391 111",
    "sg:postcode":"6043 GA",
    "sg:province":"Limburg",
    "wof:name":"Kadaster Limburg",
    "wof:placetype":"venue"
},
  "geometry": {"coordinates":[6.0028471947,51.190776825],"type":"Point"}
}