{
  "type": "Feature",
  "properties": {
    "addr:full":"Noorddammerln 104 Amstelveen Noord-Holland 1187 AE",
    "addr:housenumber":"104",
    "addr:postcode":"1187 ae",
    "iso:country":"NL",
    "sg:address":"Noorddammerln 104",
    "sg:city":"Amstelveen",
    "sg:orig_category":"Verf En Lak",
    "sg:phone":"+31 20 641 3592",
    "sg:postcode":"1187 AE",
    "sg:province":"Noord-Holland",
    "wof:name":"Regelink & Zn, Fa H",
    "wof:placetype":"venue"
},
  "geometry": {"coordinates":[4.836121,52.293262],"type":"Point"}
}