{
  "type": "Feature",
  "properties": {
    "addr:full":"Bilderdykkd 13Hs Amsterdam Noord-Holland 1053 VA",
    "addr:postcode":"1053",
    "iso:country":"NL",
    "sg:address":"Bilderdykkd 13Hs",
    "sg:city":"Amsterdam",
    "sg:orig_category":"Grafisch Ontwerpers",
    "sg:phone":"+31 20 589 1944",
    "sg:postcode":"1053 VA",
    "sg:province":"Noord-Holland",
    "wof:name":"Dsgn Frm A'Dam",
    "wof:placetype":"venue"
},
  "geometry": {"coordinates":[-74.159927,42.962196],"type":"Point"}
}