{
  "type": "Feature",
  "properties": {
    "addr:full":"Ravelstr 2 Capelle Ad Yssel South Holland 2901 EH",
    "addr:housenumber":"2",
    "addr:postcode":"2901 eh",
    "addr:street":"Ravelstr;Yssel",
    "iso:country":"NL",
    "sg:address":"Ravelstr 2",
    "sg:city":"Capelle Ad Yssel",
    "sg:orig_category":"Facilitaire Dienstverlening",
    "sg:phone":"+31 10 288 7200",
    "sg:postcode":"2901 EH",
    "sg:province":"South Holland",
    "sg:website":"http://www.facilicorp.com",
    "wof:name":"Facilicorp Europe Bv",
    "wof:placetype":"venue"
},
  "geometry": {"coordinates":[4.56426,51.916981],"type":"Point"}
}