{
  "type": "Feature",
  "properties": {
    "addr:full":"Wadestein 32 Oosterhout Nb Noord-Brabant 4901 CP",
    "addr:housenumber":"32",
    "addr:postcode":"4901 cp",
    "addr:street":"Wadestein",
    "iso:country":"NL",
    "sg:address":"Wadestein 32",
    "sg:city":"Oosterhout Nb",
    "sg:orig_category":"Begrafenisondernemers",
    "sg:phone":"+31 162 471 357",
    "sg:postcode":"4901 CP",
    "sg:province":"Noord-Brabant",
    "wof:name":"Uitvaartverzorging Westen",
    "wof:placetype":"venue"
},
  "geometry": {"coordinates":[4.86187,51.649574],"type":"Point"}
}