{
  "type": "Feature",
  "properties": {
    "addr:full":"Volmolengr 18 Leiden South Holland 2312 PH",
    "addr:housenumber":"18",
    "addr:postcode":"2312",
    "addr:street":"Volmolengr",
    "iso:country":"NL",
    "sg:address":"Volmolengr 18",
    "sg:city":"Leiden",
    "sg:orig_category":"Beeldende Kunstenaars",
    "sg:phone":"+31 71 522 6249",
    "sg:postcode":"2312 PH",
    "sg:province":"South Holland",
    "wof:name":"Zelfde, R Van 'T",
    "wof:placetype":"venue"
},
  "geometry": {"coordinates":[4.493091,52.163002],"type":"Point"}
}