{
  "type": "Feature",
  "properties": {
    "addr:full":"Torendk 2 Ambt Delden Overijssel 7495 PX",
    "addr:housenumber":"2",
    "addr:postcode":"7495 px",
    "addr:street":"Torendk",
    "iso:country":"NL",
    "sg:address":"Torendk 2",
    "sg:city":"Ambt Delden",
    "sg:orig_category":"Evenementenverzorging",
    "sg:phone":"+31 74 256 9612",
    "sg:postcode":"7495 PX",
    "sg:province":"Overijssel",
    "sg:website":"http://www.croho.nl",
    "wof:name":"Croho Productions Vof",
    "wof:placetype":"venue"
},
  "geometry": {"coordinates":[6.709858,52.251041],"type":"Point"}
}