{
  "type": "Feature",
  "properties": {
    "addr:full":"Dennenstraat 4 Ijmuiden Noord-Holland 1971 ME",
    "addr:housenumber":"4",
    "addr:postcode":"1971 me",
    "addr:street":"Dennenstraat",
    "iso:country":"NL",
    "sg:address":"Dennenstraat 4",
    "sg:city":"Ijmuiden",
    "sg:orig_category":"Geluidsopnamen",
    "sg:phone":"+31 255 536 478",
    "sg:postcode":"1971 ME",
    "sg:province":"Noord-Holland",
    "wof:name":"Wesy Music",
    "wof:placetype":"venue"
},
  "geometry": {"coordinates":[4.628251,52.456512],"type":"Point"}
}