{
  "type": "Feature",
  "properties": {
    "iso:country":"NL",
    "sg:address":"Dennenstraat 4",
    "sg:city":"Ijmuiden",
    "sg:orig_category":"Geluidsopnamen",
    "sg:phone":"+31 255 536 478",
    "sg:postcode":"1971 ME",
    "sg:province":"Noord-Holland",
    "wof:name":"Wesy Music",
    "wof:placetype":"venue"
},
  "geometry": {"coordinates":[4.628251,52.456512],"type":"Point"}
}