{
  "type": "Feature",
  "properties": {
    "iso:country":"NL",
    "sg:address":"Robijnborch 13",
    "sg:city":"Rosmalen",
    "sg:orig_category":"Airconditioning And Ventilatie",
    "sg:phone":"+31 73 521 4269",
    "sg:postcode":"5241 LK",
    "sg:province":"Noord-Brabant",
    "wof:name":"L. Ender Technisch Bedrijf Bv",
    "wof:placetype":"venue"
},
  "geometry": {"coordinates":[5.351303,51.722046],"type":"Point"}
}