{
  "type": "Feature",
  "properties": {
    "iso:country":"NL",
    "sg:address":"F Bolhage 3",
    "sg:city":"Nieuwegein",
    "sg:orig_category":"Timmerwerken",
    "sg:phone":"+31 30 604 4470",
    "sg:postcode":"3437 NG",
    "sg:province":"Utrecht",
    "wof:name":"Smit, A M",
    "wof:placetype":"venue"
},
  "geometry": {"coordinates":[5.082197,52.027325],"type":"Point"}
}