{
  "type": "Feature",
  "properties": {
    "addr:full":"Vluchtheuvelstraat 1 Dreumel Gelderland 6621 BK",
    "addr:housenumber":"1",
    "addr:postcode":"6621 bk",
    "addr:street":"Vluchtheuvelstraat;Gelderland",
    "iso:country":"NL",
    "sg:address":"Vluchtheuvelstraat 1",
    "sg:city":"Dreumel",
    "sg:orig_category":"Houtverwerking",
    "sg:phone":"+31 487 571 736",
    "sg:postcode":"6621 BK",
    "sg:province":"Gelderland",
    "wof:name":"Lentse Machinale Houtbewerking",
    "wof:placetype":"venue"
},
  "geometry": {"coordinates":[5.428147,51.851891],"type":"Point"}
}