{
  "type": "Feature",
  "properties": {
    "addr:full":"Duivenvoorde 2-4 Zwyndrecht Zuid-Holland 3334 EH",
    "addr:housenumber":"2-4",
    "addr:postcode":"3334 eh",
    "addr:street":"Duivenvoorde",
    "iso:country":"NL",
    "sg:address":"Duivenvoorde 2-4",
    "sg:city":"Zwyndrecht",
    "sg:orig_category":"Scholen Voor Basisonderwijs",
    "sg:phone":"+31 78 612 3226",
    "sg:postcode":"3334 EH",
    "sg:province":"Zuid-Holland",
    "wof:name":"Twee Wieken, De",
    "wof:placetype":"venue"
},
  "geometry": {"coordinates":[4.603452,51.814266],"type":"Point"}
}