{
  "type": "Feature",
  "properties": {
    "iso:country":"NL",
    "sg:address":"Noordermeent 31",
    "sg:city":"Kraggenburg",
    "sg:orig_category":"Verzekeringen",
    "sg:phone":"+31 527 252 486",
    "sg:postcode":"8317 AA",
    "sg:province":"NL.",
    "wof:name":"L.G.M. Stokkel",
    "wof:placetype":"venue"
},
  "geometry": {"coordinates":[5.901859,52.663425],"type":"Point"}
}