{
  "type": "Feature",
  "properties": {
    "addr:full":"Wiekstraat 4 Rotterdam Zuid-Holland 3035 XP",
    "addr:housenumber":"4",
    "addr:postcode":"3035 xp",
    "addr:street":"Wiekstraat",
    "iso:country":"NL",
    "sg:address":"Wiekstraat 4",
    "sg:city":"Rotterdam",
    "sg:orig_category":"Bedrijfs- And Managementsconsultants",
    "sg:phone":"+31 10 465 7017",
    "sg:postcode":"3035 XP",
    "sg:province":"Zuid-Holland",
    "wof:name":"Photizo Management",
    "wof:placetype":"venue"
},
  "geometry": {"coordinates":[4.484636,51.933266],"type":"Point"}
}