{
  "type": "Feature",
  "properties": {
    "addr:full":"Zwartemees 46 Emmen Drenthe 7827 BH",
    "addr:housenumber":"46",
    "addr:postcode":"7827 bh",
    "addr:street":"Zwartemees",
    "iso:country":"NL",
    "sg:address":"Zwartemees 46",
    "sg:city":"Emmen",
    "sg:orig_category":"Verzekeringen",
    "sg:phone":"+31 591 631 262",
    "sg:postcode":"7827 BH",
    "sg:province":"Drenthe",
    "wof:name":"Assurantiebemiddeling G.J.H. Drenth",
    "wof:placetype":"venue"
},
  "geometry": {"coordinates":[6.901771,52.745884],"type":"Point"}
}