{
  "type": "Feature",
  "properties": {
    "addr:full":"Lorentzstraat 6 Harderwijk Gelderland 3846 AW",
    "addr:housenumber":"6",
    "addr:postcode":"3846 aw",
    "addr:street":"Lorentzstraat;Gelderland",
    "iso:country":"NL",
    "sg:address":"Lorentzstraat 6",
    "sg:city":"Harderwijk",
    "sg:orig_category":"Woningbouwverenigingen",
    "sg:phone":"+31 341 416 894",
    "sg:postcode":"3846 AW",
    "sg:province":"Gelderland",
    "wof:name":"Centrale Woningstichting",
    "wof:placetype":"venue"
},
  "geometry": {"coordinates":[5.6338949203,52.3565788269],"type":"Point"}
}