{
  "type": "Feature",
  "properties": {
    "iso:country":"NL",
    "sg:address":"Lorentzstraat 6",
    "sg:city":"Harderwijk",
    "sg:orig_category":"Woningbouwverenigingen",
    "sg:phone":"+31 341 416 894",
    "sg:postcode":"3846 AW",
    "sg:province":"Gelderland",
    "wof:name":"Centrale Woningstichting",
    "wof:placetype":"venue"
},
  "geometry": {"coordinates":[5.6338949203,52.3565788269],"type":"Point"}
}