{
  "type": "Feature",
  "properties": {
    "addr:full":"Brinklaan 79 Bussum Noord-Holland 1404 GA",
    "addr:housenumber":"79",
    "addr:postcode":"1404 ga",
    "addr:street":"Brinklaan",
    "iso:country":"NL",
    "sg:address":"Brinklaan 79",
    "sg:city":"Bussum",
    "sg:orig_category":"Meubelzaken, Woning- And Keukeninrichting",
    "sg:phone":"+31 35 691 5152",
    "sg:postcode":"1404 GA",
    "sg:province":"Noord-Holland",
    "wof:name":"Sleepwell Beddenspeciaalzaak",
    "wof:placetype":"venue"
},
  "geometry": {"coordinates":[5.16251,52.274799],"type":"Point"}
}