{
  "type": "Feature",
  "properties": {
    "addr:full":"Catsveld 75 Gouda Zuid-Holland 2804 BC",
    "addr:housenumber":"75",
    "addr:postcode":"2804 bc",
    "addr:street":"Catsveld",
    "iso:country":"NL",
    "sg:address":"Catsveld 75",
    "sg:city":"Gouda",
    "sg:orig_category":"Webdesign Bureaus",
    "sg:phone":"+31 182 535 532",
    "sg:postcode":"2804 BC",
    "sg:province":"Zuid-Holland",
    "sg:website":"http://www.waaromwebcompany.nl",
    "wof:name":"Webcom-Design",
    "wof:placetype":"venue"
},
  "geometry": {"coordinates":[4.7033538818,52.027885437],"type":"Point"}
}