{
  "type": "Feature",
  "properties": {
    "addr:full":"Singel 362 Amsterdam North Holland 1016 AH",
    "addr:housenumber":"362",
    "addr:postcode":"1016 ah",
    "addr:street":"Singel",
    "iso:country":"NL",
    "sg:address":"Singel 362",
    "sg:city":"Amsterdam",
    "sg:orig_category":"Fotostudio'S And Fotografen",
    "sg:phone":"+31 20 622 8643",
    "sg:postcode":"1016 AH",
    "sg:province":"North Holland",
    "wof:name":"Studio Wim Koen",
    "wof:placetype":"venue"
},
  "geometry": {"coordinates":[4.887499,52.369843],"type":"Point"}
}