{
  "type": "Feature",
  "properties": {
    "iso:country":"NL",
    "sg:address":"Energieweg 19",
    "sg:city":"Oosterhout Nb",
    "sg:orig_category":"Goederenvervoer Over De Weg",
    "sg:phone":"+31 162 436 888",
    "sg:postcode":"4906 CG",
    "sg:province":"North Brabant",
    "wof:name":"J. Van Den Berg & Zonen Cv",
    "wof:placetype":"venue"
},
  "geometry": {"coordinates":[4.840195,51.658276],"type":"Point"}
}