{
  "type": "Feature",
  "properties": {
    "addr:full":"Vingerling 15 Middelharnis Zuid-Holland 3241 EB",
    "addr:housenumber":"15",
    "addr:postcode":"3241 eb",
    "addr:street":"Vingerling",
    "iso:country":"NL",
    "sg:address":"Vingerling 15",
    "sg:city":"Middelharnis",
    "sg:orig_category":"Sportverenigingen En Ontspannings- Verenigingen",
    "sg:phone":"+31 187 485 158",
    "sg:postcode":"3241 EB",
    "sg:province":"Zuid-Holland",
    "wof:name":"Flacquee Watersportver",
    "wof:placetype":"venue"
},
  "geometry": {"coordinates":[4.166557,51.760593],"type":"Point"}
}