{
  "type": "Feature",
  "properties": {
    "iso:country":"NL",
    "sg:address":"Merwede 20",
    "sg:city":"Deurne",
    "sg:orig_category":"Loodgieterswerk, Verwarming And Sanitaire Installaties",
    "sg:phone":"+31 493 319 292",
    "sg:postcode":"5751 TB",
    "sg:province":"Noord-Brabant",
    "wof:name":"J.J.M. Vogels",
    "wof:placetype":"venue"
},
  "geometry": {"coordinates":[5.803432,51.45779],"type":"Point"}
}