{
  "type": "Feature",
  "properties": {
    "addr:full":"Postbus 99 Beuningen Gld 6640 AB",
    "addr:housenumber":"99",
    "addr:postcode":"6640 ab",
    "addr:street":"Postbus",
    "iso:country":"NL",
    "sg:address":"Postbus 99",
    "sg:city":"Beuningen Gld",
    "sg:orig_category":"Verzekeringen - Verzekeringskantoren",
    "sg:phone":"+31 24 675 0664",
    "sg:postcode":"6640 AB",
    "wof:name":"Smetsers, M W A",
    "wof:placetype":"venue"
},
  "geometry": {"coordinates":[5.77018,51.861549],"type":"Point"}
}