{
  "type": "Feature",
  "properties": {
    "addr:full":"Jansbuitensngl 7 Arnhem Gelderland 6811 AA",
    "addr:housenumber":"7",
    "addr:postcode":"6811 aa",
    "addr:street":"Jansbuitensngl",
    "iso:country":"NL",
    "sg:address":"Jansbuitensngl 7",
    "sg:city":"Arnhem",
    "sg:orig_category":"Fotografie Reclame En Mode",
    "sg:phone":"+31 26 445 1111",
    "sg:postcode":"6811 AA",
    "sg:province":"Gelderland",
    "wof:name":"Kuypers Bv, Frans",
    "wof:placetype":"venue"
},
  "geometry": {"coordinates":[5.907137,51.984756],"type":"Point"}
}