{
  "type": "Feature",
  "properties": {
    "addr:full":"Nijverheidsstraat 26 Oldenzaal Overijssel 7575 BJ",
    "addr:housenumber":"26",
    "addr:postcode":"7575 bj",
    "addr:street":"Nijverheidsstraat",
    "iso:country":"NL",
    "sg:address":"Nijverheidsstraat 26",
    "sg:city":"Oldenzaal",
    "sg:orig_category":"Meubelzaken, Woning- And Keukeninrichting",
    "sg:phone":"+31 541 520 911",
    "sg:postcode":"7575 BJ",
    "sg:province":"Overijssel",
    "wof:name":"Montel Zitmeubelen",
    "wof:placetype":"venue"
},
  "geometry": {"coordinates":[6.926049,52.296082],"type":"Point"}
}