{
  "type": "Feature",
  "properties": {
    "addr:full":"Hoofdstraat 9 Didam Gelderland 6942 AP",
    "addr:housenumber":"9",
    "addr:postcode":"6942 ap",
    "addr:street":"Hoofdstraat;Gelderland",
    "iso:country":"NL",
    "sg:address":"Hoofdstraat 9",
    "sg:city":"Didam",
    "sg:orig_category":"Fotostudio'S And Fotografen",
    "sg:phone":"+31 316 221 530",
    "sg:postcode":"6942 AP",
    "sg:province":"Gelderland",
    "wof:name":"Foto Vreeman",
    "wof:placetype":"venue"
},
  "geometry": {"coordinates":[6.129066,51.938122],"type":"Point"}
}