{
  "type": "Feature",
  "properties": {
    "iso:country":"NL",
    "sg:address":"Baarlosestr 18",
    "sg:city":"Venlo",
    "sg:classifiers":[
        {
            "category":"Food & Beverages",
            "subcategory":"Bakery",
            "type":"Retail Goods"
        }
    ],
    "sg:phone":"+31 77 382 6243",
    "sg:postcode":"5921 ED",
    "sg:province":"Limburg",
    "sg:tags":[
        "pizza"
    ],
    "wof:name":"Venezia",
    "wof:placetype":"venue"
},
  "geometry": {"coordinates":[6.151203,51.36425],"type":"Point"}
}