{
  "type": "Feature",
  "properties": {
    "addr:full":"Vlierberg 16 Eemnes Utrecht 3755 BS",
    "addr:housenumber":"16",
    "addr:postcode":"3755 bs",
    "addr:street":"Vlierberg",
    "iso:country":"NL",
    "sg:address":"Vlierberg 16",
    "sg:city":"Eemnes",
    "sg:orig_category":"Offsetdrukkerijen",
    "sg:phone":"+31 35 531 6464",
    "sg:postcode":"3755 BS",
    "sg:province":"Utrecht",
    "wof:name":"Grafistans",
    "wof:placetype":"venue"
},
  "geometry": {"coordinates":[5.249337,52.246891],"type":"Point"}
}