{
  "type": "Feature",
  "properties": {
    "addr:full":"Aldrinstr 9 Loon Op Zand Noord-Brabant 5175 XA",
    "addr:housenumber":"9",
    "addr:postcode":"5175 xa",
    "addr:street":"Aldrinstr",
    "iso:country":"NL",
    "sg:address":"Aldrinstr 9",
    "sg:city":"Loon Op Zand",
    "sg:orig_category":"Schoenen - Reparaties",
    "sg:phone":"+31 416 362 480",
    "sg:postcode":"5175 XA",
    "sg:province":"Noord-Brabant",
    "wof:name":"Jansen, H",
    "wof:placetype":"venue"
},
  "geometry": {"coordinates":[5.083421,51.626801],"type":"Point"}
}