{
  "type": "Feature",
  "properties": {
    "addr:full":"Brink 4 Hijken Provincie Drenthe 9415 PB",
    "addr:housenumber":"4",
    "addr:postcode":"9415 pb",
    "addr:street":"Brink;Provincie Drenthe",
    "iso:country":"NL",
    "sg:address":"Brink 4",
    "sg:city":"Hijken",
    "sg:orig_category":"Loodgieterswerk, Verwarming And Sanitaire Installaties",
    "sg:phone":"+31 593 526 715",
    "sg:postcode":"9415 PB",
    "sg:province":"Provincie Drenthe",
    "wof:name":"Nieuwelink Installatiebureau",
    "wof:placetype":"venue"
},
  "geometry": {"coordinates":[6.498958,52.895226],"type":"Point"}
}