{
  "type": "Feature",
  "properties": {
    "addr:full":"Scheepmakerij 260 Zwijndrecht Zuid-Holland 3331 MB",
    "addr:housenumber":"260",
    "addr:postcode":"3331 mb",
    "addr:street":"Scheepmakerij",
    "iso:country":"NL",
    "sg:address":"Scheepmakerij 260",
    "sg:city":"Zwijndrecht",
    "sg:orig_category":"Chemische Producten Gh",
    "sg:phone":"+31 78 625 5255",
    "sg:postcode":"3331 MB",
    "sg:province":"Zuid-Holland",
    "wof:name":"Ketting & De Haan Chemicals",
    "wof:placetype":"venue"
},
  "geometry": {"coordinates":[4.64771,51.81377],"type":"Point"}
}