{
  "type": "Feature",
  "properties": {
    "addr:full":"Borculosewg 99 Neede Gelderland 7161 GV",
    "addr:housenumber":"99",
    "addr:postcode":"7161 gv",
    "addr:street":"Borculosewg;Gelderland",
    "iso:country":"NL",
    "sg:address":"Borculosewg 99",
    "sg:city":"Neede",
    "sg:orig_category":"Metselwerken",
    "sg:phone":"+31 545 295 228",
    "sg:postcode":"7161 GV",
    "sg:province":"Gelderland",
    "wof:name":"Nijland",
    "wof:placetype":"venue"
},
  "geometry": {"coordinates":[-121.31706200000001,38.299633],"type":"Point"}
}