{
  "type": "Feature",
  "properties": {
    "iso:country":"NL",
    "sg:address":"Huis Te Landelaan 460",
    "sg:city":"Rijswijk Zh",
    "sg:orig_category":"Kappers",
    "sg:phone":"+31 70 393 4837",
    "sg:postcode":"2283 VJ",
    "sg:province":"South Holland",
    "wof:name":"Salon Hungaria",
    "wof:placetype":"venue"
},
  "geometry": {"coordinates":[4.322381,52.041054],"type":"Point"}
}