{
  "type": "Feature",
  "properties": {
    "addr:full":"C Netscherstr 54 Eindhoven Noord-Brabant 5643 VE",
    "addr:housenumber":"54",
    "addr:postcode":"5643",
    "addr:street":"C;Ve",
    "iso:country":"NL",
    "sg:address":"C Netscherstr 54",
    "sg:city":"Eindhoven",
    "sg:orig_category":"Beeldende Kunstenaars",
    "sg:phone":"+31 40 211 7747",
    "sg:postcode":"5643 VE",
    "sg:province":"Noord-Brabant",
    "wof:name":"Goor, T Van De",
    "wof:placetype":"venue"
},
  "geometry": {"coordinates":[5.505213,51.427464],"type":"Point"}
}