{
  "type": "Feature",
  "properties": {
    "addr:full":"Arnhemse Bovenweg 122 Zeist Utrecht 3708 AH",
    "addr:housenumber":"122",
    "addr:postcode":"3708 ah",
    "addr:street":"Arnhemse Bovenweg",
    "iso:country":"NL",
    "sg:address":"Arnhemse Bovenweg 122",
    "sg:city":"Zeist",
    "sg:orig_category":"Hout Gh",
    "sg:phone":"+31 30 698 1110",
    "sg:postcode":"3708 AH",
    "sg:province":"Utrecht",
    "wof:name":"Sca Timber Benelux",
    "wof:placetype":"venue"
},
  "geometry": {"coordinates":[5.261799,52.071835],"type":"Point"}
}