{
  "type": "Feature",
  "properties": {
    "addr:full":"Grasmeent 2 Hilversum Noord-Holland 1218 AA",
    "addr:housenumber":"2",
    "addr:postcode":"1218 aa",
    "addr:street":"Grasmeent",
    "iso:country":"NL",
    "sg:address":"Grasmeent 2",
    "sg:city":"Hilversum",
    "sg:orig_category":"Architecten",
    "sg:phone":"+31 35 693 9132",
    "sg:postcode":"1218 AA",
    "sg:province":"Noord-Holland",
    "wof:name":"Peter Kuyper-Architect Avb",
    "wof:placetype":"venue"
},
  "geometry": {"coordinates":[5.138283,52.2747],"type":"Point"}
}