{
  "type": "Feature",
  "properties": {
    "addr:full":"Hommelstraat 23 Arnhem Gelderland 6828 AJ",
    "addr:housenumber":"23",
    "addr:postcode":"6828 aj",
    "addr:street":"Hommelstraat",
    "iso:country":"NL",
    "sg:address":"Hommelstraat 23",
    "sg:city":"Arnhem",
    "sg:classifiers":[
        {
            "category":"Fast Food",
            "type":"Food & Drink"
        }
    ],
    "sg:phone":"+31 26 351 3275",
    "sg:postcode":"6828 AJ",
    "sg:province":"Gelderland",
    "sg:tags":[
        "afhaal",
        "restaurant"
    ],
    "wof:name":"Milano",
    "wof:placetype":"venue"
},
  "geometry": {"coordinates":[5.914201,51.984379],"type":"Point"}
}