{
  "type": "Feature",
  "properties": {
    "addr:full":"Timberwolfstr 5A Standdaarbuiten North Brabant 4758 AJ",
    "addr:housenumber":"5a",
    "addr:postcode":"4758 aj",
    "addr:street":"Timberwolfstr",
    "iso:country":"NL",
    "sg:address":"Timberwolfstr 5A",
    "sg:city":"Standdaarbuiten",
    "sg:orig_category":"Zalenverhuur",
    "sg:phone":"+31 165 312 182",
    "sg:postcode":"4758 AJ",
    "sg:province":"North Brabant",
    "wof:name":"Standaard, De",
    "wof:placetype":"venue"
},
  "geometry": {"coordinates":[4.514742,51.613007],"type":"Point"}
}