{
  "type": "Feature",
  "properties": {
    "addr:full":"Kerkstraat 4 Heerenveen Friesland 8441 EZ",
    "addr:housenumber":"4",
    "addr:postcode":"8441 ez",
    "addr:street":"Kerkstraat",
    "iso:country":"NL",
    "sg:address":"Kerkstraat 4",
    "sg:city":"Heerenveen",
    "sg:orig_category":"Boekhandels",
    "sg:phone":"+31 513 625 574",
    "sg:postcode":"8441 EZ",
    "sg:province":"Friesland",
    "wof:name":"De Brug Christelijke Boek, Muziek En Video",
    "wof:placetype":"venue"
},
  "geometry": {"coordinates":[6.012652,52.947124],"type":"Point"}
}