{
  "type": "Feature",
  "properties": {
    "addr:full":"Hoofdwg 110 Midwolda Groningen 9681 AK",
    "addr:housenumber":"110",
    "addr:postcode":"9681 ak",
    "addr:street":"Midwolda",
    "iso:country":"NL",
    "sg:address":"Hoofdwg 110",
    "sg:city":"Midwolda",
    "sg:orig_category":"Warenhuizen",
    "sg:phone":"+31 597 551 338",
    "sg:postcode":"9681 AK",
    "sg:province":"Groningen",
    "wof:name":"Edens Kok",
    "wof:placetype":"venue"
},
  "geometry": {"coordinates":[7.0024237633,53.19348526],"type":"Point"}
}