{
  "type": "Feature",
  "properties": {
    "iso:country":"NL",
    "sg:address":"Faradaystr 8A",
    "sg:city":"Tiel",
    "sg:orig_category":"Lasbedrijven",
    "sg:phone":"+31 344 620 820",
    "sg:postcode":"4004 JZ",
    "sg:province":"Gelderland",
    "wof:name":"Laar, Van",
    "wof:placetype":"venue"
},
  "geometry": {"coordinates":[5.434867,51.90731],"type":"Point"}
}