{
  "type": "Feature",
  "properties": {
    "addr:full":"Faradaystr 8A Tiel Gelderland 4004 JZ",
    "addr:housenumber":"8a",
    "addr:postcode":"4004 jz",
    "addr:street":"Faradaystr;Gelderland",
    "iso:country":"NL",
    "sg:address":"Faradaystr 8A",
    "sg:city":"Tiel",
    "sg:orig_category":"Lasbedrijven",
    "sg:phone":"+31 344 620 820",
    "sg:postcode":"4004 JZ",
    "sg:province":"Gelderland",
    "wof:name":"Laar, Van",
    "wof:placetype":"venue"
},
  "geometry": {"coordinates":[5.434867,51.90731],"type":"Point"}
}