{
  "type": "Feature",
  "properties": {
    "addr:full":"Postbus 788 'S-Hertogenbosch North Brabant 5201 AT",
    "addr:housenumber":"788",
    "addr:postcode":"5201",
    "addr:street":"Postbus",
    "iso:country":"NL",
    "sg:address":"Postbus 788",
    "sg:city":"'S-Hertogenbosch",
    "sg:orig_category":"Verenigingen En Stichtingen",
    "sg:phone":"+31 73 613 3811",
    "sg:postcode":"5201 AT",
    "sg:province":"North Brabant",
    "wof:name":"Fietsersbond Enfb",
    "wof:placetype":"venue"
},
  "geometry": {"coordinates":[5.30421,51.68922],"type":"Point"}
}