{
  "type": "Feature",
  "properties": {
    "addr:full":"Generaal Spoorlaan 8 Rijswijk Zh Zuid-Holland 2283 GM",
    "addr:housenumber":"8",
    "addr:postcode":"zh;2283 gm",
    "addr:street":"Generaal Spoorlaan",
    "iso:country":"NL",
    "sg:address":"Generaal Spoorlaan 8",
    "sg:city":"Rijswijk Zh",
    "sg:orig_category":"Partycatering And -Organisatie",
    "sg:phone":"+31 70 393 9555",
    "sg:postcode":"2283 GM",
    "sg:province":"Zuid-Holland",
    "wof:name":"De Lunchlijn",
    "wof:placetype":"venue"
},
  "geometry": {"coordinates":[4.32883,52.047092],"type":"Point"}
}