{
  "type": "Feature",
  "properties": {
    "iso:country":"NL",
    "sg:address":"De Naaldenmaker 12",
    "sg:city":"Veldhoven",
    "sg:orig_category":"Adviesbureaus",
    "sg:phone":"+31 40 253 6981",
    "sg:postcode":"5506 CD",
    "sg:province":"Noord-Brabant",
    "wof:name":"Techcom Cons",
    "wof:placetype":"venue"
},
  "geometry": {"coordinates":[5.385076,51.416821],"type":"Point"}
}