{
  "type": "Feature",
  "properties": {
    "iso:country":"NL",
    "sg:address":"Oirschotsewg 2",
    "sg:city":"Moergestel",
    "sg:orig_category":"Artsen - Huisartsen",
    "sg:phone":"+31 13 513 1204",
    "sg:postcode":"5066 CJ",
    "sg:province":"Noord-Brabant",
    "wof:name":"Terwindt & P R Blessing-Van Luijt, P N L H",
    "wof:placetype":"venue"
},
  "geometry": {"coordinates":[5.187846,51.545395],"type":"Point"}
}