{
  "type": "Feature",
  "properties": {
    "iso:country":"NL",
    "sg:address":"Oldemarktsewg 92",
    "sg:city":"Steenwykerwold",
    "sg:orig_category":"Verenigingsgebouwen",
    "sg:phone":"+31 521 588 760",
    "sg:postcode":"8341 SH",
    "sg:province":"NL.08",
    "wof:name":"Sportzaal En Clubgebouw",
    "wof:placetype":"venue"
},
  "geometry": {"coordinates":[6.067994,52.80389],"type":"Point"}
}