{
  "type": "Feature",
  "properties": {
    "addr:full":"Oldemarktsewg 92 Steenwykerwold NL.08 8341 SH",
    "addr:housenumber":"92;8341",
    "addr:street":"Oldemarktsewg;Sh",
    "iso:country":"NL",
    "sg:address":"Oldemarktsewg 92",
    "sg:city":"Steenwykerwold",
    "sg:orig_category":"Verenigingsgebouwen",
    "sg:phone":"+31 521 588 760",
    "sg:postcode":"8341 SH",
    "sg:province":"NL.08",
    "wof:name":"Sportzaal En Clubgebouw",
    "wof:placetype":"venue"
},
  "geometry": {"coordinates":[6.067994,52.80389],"type":"Point"}
}