{
  "type": "Feature",
  "properties": {
    "addr:full":"Kerkstr 6A Roggel Limburg 6088 EG",
    "addr:housenumber":"6a",
    "addr:postcode":"6088 eg",
    "addr:street":"Kerkstr",
    "iso:country":"NL",
    "sg:address":"Kerkstr 6A",
    "sg:city":"Roggel",
    "sg:orig_category":"Voetbalverenigingen",
    "sg:phone":"+31 475 495 890",
    "sg:postcode":"6088 EG",
    "sg:province":"Limburg",
    "wof:name":"Roggel",
    "wof:placetype":"venue"
},
  "geometry": {"coordinates":[5.920841,51.263489],"type":"Point"}
}