{
  "type": "Feature",
  "properties": {
    "addr:full":"G V Prinstererln 25 Enschede Overijssel 7521 AX",
    "addr:housenumber":"25",
    "addr:postcode":"7521 ax",
    "addr:street":"V Prinstererln",
    "iso:country":"NL",
    "sg:address":"G V Prinstererln 25",
    "sg:city":"Enschede",
    "sg:orig_category":"Grafisch Ontwerpers",
    "sg:phone":"+31 53 433 1639",
    "sg:postcode":"7521 AX",
    "sg:province":"Overijssel",
    "wof:name":"Wal, E P Van Der",
    "wof:placetype":"venue"
},
  "geometry": {"coordinates":[6.85233,52.234531],"type":"Point"}
}