{
  "type": "Feature",
  "properties": {
    "iso:country":"NL",
    "sg:address":"Meidoornstr 8B",
    "sg:city":"Tiel",
    "sg:orig_category":"Duiven En Duivensport - Artikelen",
    "sg:phone":"+31 344 612 587",
    "sg:postcode":"4001 ZE",
    "sg:province":"Gelderland",
    "wof:name":"Verwachting Postduivenver, De",
    "wof:placetype":"venue"
},
  "geometry": {"coordinates":[5.435756,51.894566],"type":"Point"}
}