{
  "type": "Feature",
  "properties": {
    "addr:full":"Stoofdk 95 Stavenisse Zeeland 4696 RR",
    "addr:housenumber":"95",
    "addr:postcode":"4696 rr",
    "addr:street":"Stoofdk",
    "iso:country":"NL",
    "sg:address":"Stoofdk 95",
    "sg:city":"Stavenisse",
    "sg:orig_category":"Werving En Selectie",
    "sg:phone":"+31 166 697 062",
    "sg:postcode":"4696 RR",
    "sg:province":"Zeeland",
    "sg:website":"http://www.zeelandrecruitment.nl",
    "wof:name":"Zeeland Recruitment",
    "wof:placetype":"venue"
},
  "geometry": {"coordinates":[4.0180039406,51.5895881653],"type":"Point"}
}