{
  "type": "Feature",
  "properties": {
    "addr:full":"Gouderakstr 26A Rotterdam South Holland 3079 DB",
    "addr:housenumber":"26a",
    "addr:postcode":"3079 db",
    "addr:street":"Gouderakstr",
    "iso:country":"NL",
    "sg:address":"Gouderakstr 26A",
    "sg:city":"Rotterdam",
    "sg:orig_category":"Elektrotechnische Apparatuur - Fabrieken En Groothandel",
    "sg:phone":"+31 10 262 4720",
    "sg:postcode":"3079 DB",
    "sg:province":"South Holland",
    "sg:website":"http://www.adeco.nl",
    "wof:name":"Adeco",
    "wof:placetype":"venue"
},
  "geometry": {"coordinates":[4.536294,51.876026],"type":"Point"}
}