{
  "type": "Feature",
  "properties": {
    "iso:country":"NL",
    "sg:address":"Hoofdstraat 50",
    "sg:city":"Beerta",
    "sg:orig_category":"Autokeuringen",
    "sg:phone":"+31 597 331 910",
    "sg:postcode":"9686 PE",
    "sg:province":"Groningen",
    "wof:name":"R. Mulder",
    "wof:placetype":"venue"
},
  "geometry": {"coordinates":[7.091278,53.169399],"type":"Point"}
}