{
  "type": "Feature",
  "properties": {
    "addr:full":"Walgtsestraat 5 Varik Gelderland 4064 CK",
    "addr:housenumber":"5",
    "addr:postcode":"4064 ck",
    "addr:street":"Walgtsestraat;Gelderland",
    "iso:country":"NL",
    "sg:address":"Walgtsestraat 5",
    "sg:city":"Varik",
    "sg:orig_category":"Overheidsdiensten",
    "sg:phone":"+31 344 651 467",
    "sg:postcode":"4064 CK",
    "sg:province":"Gelderland",
    "wof:name":"Varikdorpshuis",
    "wof:placetype":"venue"
},
  "geometry": {"coordinates":[5.3681139946,51.8227424622],"type":"Point"}
}