{
  "type": "Feature",
  "properties": {
    "addr:full":"Zonnedauwhof 23 Leusden Utrecht 3831 AH",
    "addr:housenumber":"23",
    "addr:postcode":"3831 ah",
    "addr:street":"Zonnedauwhof",
    "iso:country":"NL",
    "sg:address":"Zonnedauwhof 23",
    "sg:city":"Leusden",
    "sg:orig_category":"Honden- En Kattentrimsalons",
    "sg:phone":"+31 33 494 3150",
    "sg:postcode":"3831 AH",
    "sg:province":"Utrecht",
    "wof:name":"Otter Hondentrimsalon",
    "wof:placetype":"venue"
},
  "geometry": {"coordinates":[5.43941,52.138214],"type":"Point"}
}