{
  "type": "Feature",
  "properties": {
    "addr:full":"Kwartelstr 21A Leeuwarden Provincie Friesland 8916 BM",
    "addr:housenumber":"21a",
    "addr:postcode":"8916 bm",
    "addr:street":"Kwartelstr;Provincie Friesland",
    "iso:country":"NL",
    "sg:address":"Kwartelstr 21A",
    "sg:city":"Leeuwarden",
    "sg:orig_category":"Meubelstoffering",
    "sg:phone":"+31 58 213 7056",
    "sg:postcode":"8916 BM",
    "sg:province":"Provincie Friesland",
    "wof:name":"Veldhuis & Zn, Gerard",
    "wof:placetype":"venue"
},
  "geometry": {"coordinates":[5.780659,53.205696],"type":"Point"}
}