{
  "type": "Feature",
  "properties": {
    "addr:full":"Nijverheidsweg 3 Hellevoetsluis Zuid-Holland 3225 LL",
    "addr:housenumber":"3",
    "addr:postcode":"3225 ll",
    "addr:street":"Nijverheidsweg",
    "iso:country":"NL",
    "sg:address":"Nijverheidsweg 3",
    "sg:city":"Hellevoetsluis",
    "sg:orig_category":"Medische Apparatuur And Prothesen Fab",
    "sg:phone":"+31 181 391 000",
    "sg:postcode":"3225 LL",
    "sg:province":"Zuid-Holland",
    "wof:name":"Hoeve Tandtechniek Bv",
    "wof:placetype":"venue"
},
  "geometry": {"coordinates":[4.167019,51.835773],"type":"Point"}
}