{
  "type": "Feature",
  "properties": {
    "addr:full":"Vilstersestraat 3 Lemelerveld Overijssel 8152 AA",
    "addr:housenumber":"3",
    "addr:postcode":"8152 aa",
    "addr:street":"Vilstersestraat",
    "iso:country":"NL",
    "sg:address":"Vilstersestraat 3",
    "sg:city":"Lemelerveld",
    "sg:orig_category":"Autokeuringen",
    "sg:phone":"+31 572 372 400",
    "sg:postcode":"8152 AA",
    "sg:province":"Overijssel",
    "wof:name":"H L Duerink",
    "wof:placetype":"venue"
},
  "geometry": {"coordinates":[6.341674,52.446518],"type":"Point"}
}