{
  "type": "Feature",
  "properties": {
    "addr:full":"Herenwg 158 Alkmaar Noord-Holland 1822 AK",
    "addr:housenumber":"158",
    "addr:postcode":"1822 ak",
    "iso:country":"NL",
    "sg:address":"Herenwg 158",
    "sg:city":"Alkmaar",
    "sg:orig_category":"Verenigingsgebouwen",
    "sg:phone":"+31 72 561 5131",
    "sg:postcode":"1822 AK",
    "sg:province":"Noord-Holland",
    "wof:name":"Flash",
    "wof:placetype":"venue"
},
  "geometry": {"coordinates":[4.777161,52.640755],"type":"Point"}
}