{
  "type": "Feature",
  "properties": {
    "addr:full":"Lattropperstraat 130-132 Denekamp Overijssel 7591 PK",
    "addr:housenumber":"130-132",
    "addr:postcode":"7591 pk",
    "addr:street":"Lattropperstraat",
    "iso:country":"NL",
    "sg:address":"Lattropperstraat 130-132",
    "sg:city":"Denekamp",
    "sg:orig_category":"Schoenen",
    "sg:phone":"+31 541 221 261",
    "sg:postcode":"7591 PK",
    "sg:province":"Overijssel",
    "wof:name":"J.G. Oude Griep",
    "wof:placetype":"venue"
},
  "geometry": {"coordinates":[6.983631,52.399376],"type":"Point"}
}