{
  "type": "Feature",
  "properties": {
    "addr:full":"Bessenstr 16 Deventer Overijssel 7419 CP",
    "addr:housenumber":"16",
    "addr:postcode":"7419 cp",
    "addr:street":"Bessenstr",
    "iso:country":"NL",
    "sg:address":"Bessenstr 16",
    "sg:city":"Deventer",
    "sg:orig_category":"Nagelstudio'S",
    "sg:phone":"+31 6 23560498",
    "sg:postcode":"7419 CP",
    "sg:province":"Overijssel",
    "sg:website":"http://www.beautysaloon.nl",
    "wof:name":"Beauty Saloon",
    "wof:placetype":"venue"
},
  "geometry": {"coordinates":[6.141595,52.249474],"type":"Point"}
}