{
  "type": "Feature",
  "properties": {
    "addr:full":"Spaarweiden 85 Landgraaf Limburg 6374 ME",
    "addr:housenumber":"85",
    "addr:postcode":"6374 me",
    "addr:street":"Spaarweiden",
    "iso:country":"NL",
    "sg:address":"Spaarweiden 85",
    "sg:city":"Landgraaf",
    "sg:orig_category":"Kunststof Ramen",
    "sg:phone":"+31 45 532 2857",
    "sg:postcode":"6374 ME",
    "sg:province":"Limburg",
    "wof:name":"Wingelaar",
    "wof:placetype":"venue"
},
  "geometry": {"coordinates":[6.043612,50.918221],"type":"Point"}
}