{
  "type": "Feature",
  "properties": {
    "addr:full":"Vogelzankweg 153 Landgraaf Limburg 6374 AC",
    "addr:housenumber":"153",
    "addr:postcode":"6374 ac",
    "addr:street":"Vogelzankweg",
    "iso:country":"NL",
    "sg:address":"Vogelzankweg 153",
    "sg:city":"Landgraaf",
    "sg:orig_category":"Boekhouders",
    "sg:phone":"+31 45 531 5093",
    "sg:postcode":"6374 AC",
    "sg:province":"Limburg",
    "wof:name":"Administratiekantoor Mervo",
    "wof:placetype":"venue"
},
  "geometry": {"coordinates":[6.030857,50.916756],"type":"Point"}
}