{
  "type": "Feature",
  "properties": {
    "addr:full":"Zolastr 2 Venlo Limburg 5924 AW",
    "addr:housenumber":"2",
    "addr:postcode":"5924 aw",
    "addr:street":"Zolastr",
    "iso:country":"NL",
    "sg:address":"Zolastr 2",
    "sg:city":"Venlo",
    "sg:orig_category":"Geluidsinstallaties - Verhuur",
    "sg:phone":"+31 6 50292997",
    "sg:postcode":"5924 AW",
    "sg:province":"Limburg",
    "wof:name":"Venlona Licht & Geluidsystemen",
    "wof:placetype":"venue"
},
  "geometry": {"coordinates":[6.131491,51.365112],"type":"Point"}
}