{
  "type": "Feature",
  "properties": {
    "addr:full":"Stadhouderswg 153C Rotterdam South Holland 3039 EK",
    "addr:housenumber":"153c",
    "addr:postcode":"3039 ek",
    "addr:street":"Stadhouderswg",
    "iso:country":"NL",
    "sg:address":"Stadhouderswg 153C",
    "sg:city":"Rotterdam",
    "sg:orig_category":"Vertaalbureaus",
    "sg:phone":"+31 10 465 1751",
    "sg:postcode":"3039 EK",
    "sg:province":"South Holland",
    "wof:name":"Intercontinentaal",
    "wof:placetype":"venue"
},
  "geometry": {"coordinates":[4.457027,51.930012],"type":"Point"}
}