{
  "type": "Feature",
  "properties": {
    "addr:full":"Darwinstraat 4 Zoetermeer South Holland 2722 PX",
    "addr:housenumber":"4",
    "addr:postcode":"2722 px",
    "addr:street":"Darwinstraat",
    "iso:country":"NL",
    "sg:address":"Darwinstraat 4",
    "sg:city":"Zoetermeer",
    "sg:orig_category":"Diverse Grafische Activiteiten",
    "sg:phone":"+31 79 341 0746",
    "sg:postcode":"2722 PX",
    "sg:province":"South Holland",
    "wof:name":"Formzet Bv",
    "wof:placetype":"venue"
},
  "geometry": {"coordinates":[4.513804,52.053974],"type":"Point"}
}