{
  "type": "Feature",
  "properties": {
    "addr:full":"Spoorstraat 9 Borculo Gelderland 7271 CA",
    "addr:housenumber":"9",
    "addr:postcode":"7271 ca",
    "addr:street":"Spoorstraat;Gelderland",
    "iso:country":"NL",
    "sg:address":"Spoorstraat 9",
    "sg:city":"Borculo",
    "sg:orig_category":"Juweliers",
    "sg:phone":"+31 545 271 328",
    "sg:postcode":"7271 CA",
    "sg:province":"Gelderland",
    "wof:name":"F M J Muller En Zoon",
    "wof:placetype":"venue"
},
  "geometry": {"coordinates":[6.522929,52.117664],"type":"Point"}
}