{
  "type": "Feature",
  "properties": {
    "addr:full":"Waaldijk 22 Herwijnen Gelderland 4171 CE",
    "addr:housenumber":"22",
    "addr:postcode":"4171 ce",
    "addr:street":"Waaldijk;Gelderland",
    "iso:country":"NL",
    "sg:address":"Waaldijk 22",
    "sg:city":"Herwijnen",
    "sg:orig_category":"Juweliers",
    "sg:phone":"+31 418 581 309",
    "sg:postcode":"4171 CE",
    "sg:province":"Gelderland",
    "wof:name":"A Van Der Wal",
    "wof:placetype":"venue"
},
  "geometry": {"coordinates":[5.120004,51.825027],"type":"Point"}
}