{
  "type": "Feature",
  "properties": {
    "addr:full":"Kwartelwg 47 Wapenveld Gelderland 8191 AR",
    "addr:housenumber":"47",
    "addr:postcode":"8191",
    "addr:street":"Kwartelwg;Gelderland",
    "iso:country":"NL",
    "sg:address":"Kwartelwg 47",
    "sg:city":"Wapenveld",
    "sg:orig_category":"Kerkorgels - Bouw En Reparatie",
    "sg:phone":"+31 38 447 8869",
    "sg:postcode":"8191 AR",
    "sg:province":"Gelderland",
    "wof:name":"Patijn, J C",
    "wof:placetype":"venue"
},
  "geometry": {"coordinates":[6.076475,52.430012],"type":"Point"}
}