{
  "type": "Feature",
  "properties": {
    "addr:full":"Binnenhavenstr 8 Hengelo Ov Overijssel 7553 GJ",
    "addr:housenumber":"8",
    "addr:postcode":"7553 gj",
    "addr:street":"Binnenhavenstr;Ov",
    "iso:country":"NL",
    "sg:address":"Binnenhavenstr 8",
    "sg:city":"Hengelo Ov",
    "sg:orig_category":"Plastic Producten - Fabrieken En Groothandel",
    "sg:phone":"+31 74 243 9663",
    "sg:postcode":"7553 GJ",
    "sg:province":"Overijssel",
    "wof:name":"Hedam Bv",
    "wof:placetype":"venue"
},
  "geometry": {"coordinates":[6.784013,52.250591],"type":"Point"}
}