{
  "type": "Feature",
  "properties": {
    "iso:country":"NL",
    "sg:address":"Sterappelstr 50",
    "sg:city":"Bunde",
    "sg:orig_category":"Logopedisten",
    "sg:phone":"+31 6 55987373",
    "sg:postcode":"6241 JL",
    "sg:province":"Limburg",
    "wof:name":"Meuris",
    "wof:placetype":"venue"
},
  "geometry": {"coordinates":[5.724396,50.896187],"type":"Point"}
}