{
  "type": "Feature",
  "properties": {
    "addr:full":"Springersdiep 11 Capelle Ad Yssel South Holland 2904 ET",
    "addr:housenumber":"11;2904",
    "addr:postcode":"et",
    "addr:street":"Springersdiep;Yssel",
    "iso:country":"NL",
    "sg:address":"Springersdiep 11",
    "sg:city":"Capelle Ad Yssel",
    "sg:orig_category":"Kinderopvang",
    "sg:phone":"+31 10 450 5208",
    "sg:postcode":"2904 ET",
    "sg:province":"South Holland",
    "wof:name":"Huygen, Jan",
    "wof:placetype":"venue"
},
  "geometry": {"coordinates":[4.601702,51.93552],"type":"Point"}
}