{
  "type": "Feature",
  "properties": {
    "addr:full":"Duivenkamp 561 Maarssen Utrecht 3607 BL",
    "addr:housenumber":"561",
    "addr:postcode":"3607 bl",
    "addr:street":"Duivenkamp",
    "iso:country":"NL",
    "sg:address":"Duivenkamp 561",
    "sg:city":"Maarssen",
    "sg:orig_category":"Grafisch Ontwerpers",
    "sg:phone":"+31 346 282 703",
    "sg:postcode":"3607 BL",
    "sg:province":"Utrecht",
    "wof:name":"Pag?e",
    "wof:placetype":"venue"
},
  "geometry": {"coordinates":[5.026705,52.134666],"type":"Point"}
}