{
  "type": "Feature",
  "properties": {
    "addr:full":"Oranjeboomstr 3 Mill Noord-Brabant 5451 BK",
    "addr:housenumber":"3",
    "addr:postcode":"5451 bk",
    "addr:street":"Oranjeboomstr",
    "iso:country":"NL",
    "sg:address":"Oranjeboomstr 3",
    "sg:city":"Mill",
    "sg:orig_category":"Adviesbureaus Land- En Tuinbouw",
    "sg:phone":"+31 485 479 269",
    "sg:postcode":"5451 BK",
    "sg:province":"Noord-Brabant",
    "wof:name":"A&D Adviesbureau",
    "wof:placetype":"venue"
},
  "geometry": {"coordinates":[-88.40593699999999,31.767021],"type":"Point"}
}