{
  "type": "Feature",
  "properties": {
    "addr:full":"Kerkstraat 7 Nederhorst Den Berg Noord-Holland 1394 CW",
    "addr:housenumber":"7",
    "addr:postcode":"1394 cw",
    "addr:street":"Kerkstraat",
    "iso:country":"NL",
    "sg:address":"Kerkstraat 7",
    "sg:city":"Nederhorst Den Berg",
    "sg:orig_category":"Overheidsdiensten",
    "sg:phone":"+31 294 254 515",
    "sg:postcode":"1394 CW",
    "sg:province":"Noord-Holland",
    "wof:name":"De Bergplaats",
    "wof:placetype":"venue"
},
  "geometry": {"coordinates":[5.0437932014,52.2630805969],"type":"Point"}
}