{
  "type": "Feature",
  "properties": {
    "addr:full":"A Fokkerstr 8 Goes Zeeland 4462 ET",
    "addr:housenumber":"8",
    "addr:postcode":"4462 et",
    "iso:country":"NL",
    "sg:address":"A Fokkerstr 8",
    "sg:city":"Goes",
    "sg:orig_category":"Kabelexploitanten",
    "sg:phone":"+31 113 222 000",
    "sg:postcode":"4462 ET",
    "sg:province":"Zeeland",
    "wof:name":"Zekatel Bv",
    "wof:placetype":"venue"
},
  "geometry": {"coordinates":[-83.9141693115,39.7688331604],"type":"Point"}
}