{
  "type": "Feature",
  "properties": {
    "addr:full":"Cornelis Verolmestraat 23 Heusden Gem Heusden Noord-Brabant 5256 GR",
    "addr:housenumber":"23",
    "addr:postcode":"5256",
    "addr:street":"Cornelis Verolmestraat",
    "iso:country":"NL",
    "sg:address":"Cornelis Verolmestraat 23",
    "sg:city":"Heusden Gem Heusden",
    "sg:orig_category":"Loodgieterswerk, Verwarming And Sanitaire Installaties",
    "sg:phone":"+31 416 662 918",
    "sg:postcode":"5256 GR",
    "sg:province":"Noord-Brabant",
    "wof:name":"Van Der Meijden",
    "wof:placetype":"venue"
},
  "geometry": {"coordinates":[5.137256,51.724236],"type":"Point"}
}