{
  "type": "Feature",
  "properties": {
    "addr:full":"Pater Dr Loffeldstraat 18 Gemert Noord-Brabant 5421 TB",
    "addr:housenumber":"18",
    "addr:postcode":"5421 tb",
    "addr:street":"Pater Dr Loffeldstraat",
    "iso:country":"NL",
    "sg:address":"Pater Dr Loffeldstraat 18",
    "sg:city":"Gemert",
    "sg:orig_category":"Boekhouders",
    "sg:phone":"+31 492 364 001",
    "sg:postcode":"5421 TB",
    "sg:province":"Noord-Brabant",
    "wof:name":"Adm.- En Boekhoudkant. M. Crommentuijn",
    "wof:placetype":"venue"
},
  "geometry": {"coordinates":[5.692877,51.563396],"type":"Point"}
}