{
  "type": "Feature",
  "properties": {
    "addr:full":"Wheewg 33/A Goor Overijssel 7471 EV",
    "addr:housenumber":"33 / a",
    "addr:postcode":"7471 ev",
    "addr:street":"Wheewg",
    "iso:country":"NL",
    "sg:address":"Wheewg 33/A",
    "sg:city":"Goor",
    "sg:orig_category":"Metaalbewerking",
    "sg:phone":"+31 547 275 972",
    "sg:postcode":"7471 EV",
    "sg:province":"Overijssel",
    "wof:name":"Esge-Verspaning Bv",
    "wof:placetype":"venue"
},
  "geometry": {"coordinates":[6.580076,52.243149],"type":"Point"}
}