{
  "type": "Feature",
  "properties": {
    "addr:full":"Essenln 24 Ter Aar Zuid-Holland 2461 DH",
    "addr:housenumber":"24",
    "addr:postcode":"aar;2461 dh",
    "addr:street":"Essenln;Ter",
    "iso:country":"NL",
    "sg:address":"Essenln 24",
    "sg:city":"Ter Aar",
    "sg:orig_category":"Modelbouw",
    "sg:phone":"+31 172 603 963",
    "sg:postcode":"2461 DH",
    "sg:province":"Zuid-Holland",
    "wof:name":"Intermodel",
    "wof:placetype":"venue"
},
  "geometry": {"coordinates":[4.708873,52.167458],"type":"Point"}
}