{
  "type": "Feature",
  "properties": {
    "addr:full":"Vreeburg 5 Rosmalen Noord-Brabant 5241 EJ",
    "addr:housenumber":"5",
    "addr:postcode":"5241 ej",
    "addr:street":"Vreeburg",
    "iso:country":"NL",
    "sg:address":"Vreeburg 5",
    "sg:city":"Rosmalen",
    "sg:orig_category":"Opticiens",
    "sg:phone":"+31 73 521 9706",
    "sg:postcode":"5241 EJ",
    "sg:province":"Noord-Brabant",
    "wof:name":"Hans Anders Opticiens",
    "wof:placetype":"venue"
},
  "geometry": {"coordinates":[5.3626260757,51.7178497314],"type":"Point"}
}