{
  "type": "Feature",
  "properties": {
    "addr:full":"Nyverheidswg 26 Aalten Gelderland 7122 AB",
    "addr:housenumber":"26",
    "addr:postcode":"7122 ab",
    "addr:street":"Nyverheidswg;Gelderland",
    "iso:country":"NL",
    "sg:address":"Nyverheidswg 26",
    "sg:city":"Aalten",
    "sg:classifiers":[
        {
            "category":"Retail",
            "subcategory":"Auto Repair",
            "type":"Services"
        }
    ],
    "sg:phone":"+31 543 472 630",
    "sg:postcode":"7122 AB",
    "sg:province":"Gelderland",
    "sg:tags":[
        "garage"
    ],
    "wof:name":"Schaapveld",
    "wof:placetype":"venue"
},
  "geometry": {"coordinates":[6.578732,51.917274],"type":"Point"}
}