{
  "type": "Feature",
  "properties": {
    "iso:country":"NL",
    "sg:address":"Madelievenstr 25",
    "sg:city":"Amsterdam",
    "sg:orig_category":"Verenigingen En Stichtingen",
    "sg:phone":"+31 20 676 1064",
    "sg:postcode":"1015 NV",
    "sg:province":"North Holland",
    "wof:name":"Antroposofische Ver",
    "wof:placetype":"venue"
},
  "geometry": {"coordinates":[4.880134,52.376713],"type":"Point"}
}