{
  "type": "Feature",
  "properties": {
    "addr:full":"West Ringdijk 1 Moordrecht South Holland 2841 LV",
    "addr:housenumber":"1",
    "addr:postcode":"2841",
    "addr:street":"West Ringdijk",
    "iso:country":"NL",
    "sg:address":"West Ringdijk 1",
    "sg:city":"Moordrecht",
    "sg:classifiers":[
        {
            "category":"Fast Food",
            "type":"Food & Drink"
        }
    ],
    "sg:phone":"+31 182 373 993",
    "sg:postcode":"2841 LV",
    "sg:province":"South Holland",
    "sg:tags":[
        "afhaal",
        "restaurant"
    ],
    "wof:name":"Cafetaria 'T Hoekje",
    "wof:placetype":"venue"
},
  "geometry": {"coordinates":[4.66735,51.988018],"type":"Point"}
}