{
  "type": "Feature",
  "properties": {
    "addr:full":"Breestr 57 Koog Aan De Zaan Noord-Holland 1541 EC",
    "addr:housenumber":"57",
    "addr:postcode":"1541 ec",
    "addr:street":"Breestr",
    "iso:country":"NL",
    "sg:address":"Breestr 57",
    "sg:city":"Koog Aan De Zaan",
    "sg:orig_category":"Drukkerijen",
    "sg:phone":"+31 75 616 3766",
    "sg:postcode":"1541 EC",
    "sg:province":"Noord-Holland",
    "wof:name":"Top, De",
    "wof:placetype":"venue"
},
  "geometry": {"coordinates":[4.80897,52.459839],"type":"Point"}
}