{
  "type": "Feature",
  "properties": {
    "addr:full":"J V Galenstr 4 Amsterdam Noord-Holland 1051 KM",
    "addr:housenumber":"4",
    "addr:street":"J;Galenstr;1051 Km",
    "iso:country":"NL",
    "sg:address":"J V Galenstr 4",
    "sg:city":"Amsterdam",
    "sg:orig_category":"Fotolitho- En Reprografie - Inrichtingen",
    "sg:phone":"+31 20 682 2447",
    "sg:postcode":"1051 KM",
    "sg:province":"Noord-Holland",
    "wof:name":"Colortechniek Vof",
    "wof:placetype":"venue"
},
  "geometry": {"coordinates":[4.87107,52.37925],"type":"Point"}
}