{
  "type": "Feature",
  "properties": {
    "addr:full":"Guldenekker 10 Reusel Noord-Brabant 5541 DG",
    "addr:housenumber":"10",
    "addr:postcode":"5541 dg",
    "addr:street":"Guldenekker",
    "iso:country":"NL",
    "sg:address":"Guldenekker 10",
    "sg:city":"Reusel",
    "sg:orig_category":"Zuivelproducten",
    "sg:phone":"+31 497 643 390",
    "sg:postcode":"5541 DG",
    "sg:province":"Noord-Brabant",
    "wof:name":"Vof Van Gompel",
    "wof:placetype":"venue"
},
  "geometry": {"coordinates":[5.16996,51.358215],"type":"Point"}
}