{
  "type": "Feature",
  "properties": {
    "iso:country":"NL",
    "sg:address":"New Yorkweg 111",
    "sg:city":"Almere",
    "sg:orig_category":"Meubelzaken, Woning- And Keukeninrichting",
    "sg:phone":"+31 36 532 3701",
    "sg:postcode":"1334 NB",
    "sg:province":"Flevoland",
    "wof:name":"Royal Sleeptrend",
    "wof:placetype":"venue"
},
  "geometry": {"coordinates":[5.274761,52.394482],"type":"Point"}
}