{
  "type": "Feature",
  "properties": {
    "addr:full":"Nyverheidswg 17 Oosterhout Nb Noord-Brabant 4906 CM",
    "addr:housenumber":"17",
    "addr:postcode":"4906 cm",
    "addr:street":"Nyverheidswg",
    "iso:country":"NL",
    "sg:address":"Nyverheidswg 17",
    "sg:city":"Oosterhout Nb",
    "sg:orig_category":"Elektrotechnische Apparatuur - Fabrieken En Groothandel",
    "sg:phone":"+31 162 430 606",
    "sg:postcode":"4906 CM",
    "sg:province":"Noord-Brabant",
    "wof:name":"City Electrical Factors Bv",
    "wof:placetype":"venue"
},
  "geometry": {"coordinates":[4.846498,51.656906],"type":"Point"}
}