{
  "type": "Feature",
  "properties": {
    "addr:full":"Kerkln 1 Apeldoorn Gelderland 7311 AA",
    "addr:housenumber":"1",
    "addr:postcode":"7311 aa",
    "addr:street":"Kerkln;Gelderland",
    "iso:country":"NL",
    "sg:address":"Kerkln 1",
    "sg:city":"Apeldoorn",
    "sg:orig_category":"Kappers",
    "sg:phone":"+31 55 521 8283",
    "sg:postcode":"7311 AA",
    "sg:province":"Gelderland",
    "wof:name":"Heinze, P",
    "wof:placetype":"venue"
},
  "geometry": {"coordinates":[5.9656600952,52.2165184021],"type":"Point"}
}