{
  "type": "Feature",
  "properties": {
    "iso:country":"NL",
    "sg:address":"Diepstr 31",
    "sg:city":"Lomm",
    "sg:orig_category":"Huifkarren - Verhuur En Verkoop",
    "sg:phone":"+31 77 473 2169",
    "sg:postcode":"5943 BA",
    "sg:province":"Limburg",
    "wof:name":"Willemsen",
    "wof:placetype":"venue"
},
  "geometry": {"coordinates":[6.167563,51.444775],"type":"Point"}
}