{
  "type": "Feature",
  "properties": {
    "addr:full":"M A De Ruyterstr 76 Utrecht Utrecht 3572 XN",
    "addr:housenumber":"76",
    "addr:postcode":"3572 xn",
    "iso:country":"NL",
    "sg:address":"M A De Ruyterstr 76",
    "sg:city":"Utrecht",
    "sg:orig_category":"Organisatiebureaus",
    "sg:phone":"+31 30 271 4257",
    "sg:postcode":"3572 XN",
    "sg:province":"Utrecht",
    "sg:website":"http://www.ramonbeuk.nl",
    "wof:name":"Culinair Consultancy",
    "wof:placetype":"venue"
},
  "geometry": {"coordinates":[5.1359119415,52.1006965637],"type":"Point"}
}