{
  "type": "Feature",
  "properties": {
    "addr:full":"Appelvinklaan 15 Maarn Utrecht 3951 WR",
    "addr:housenumber":"15",
    "addr:postcode":"3951 wr",
    "addr:street":"Appelvinklaan",
    "iso:country":"NL",
    "sg:address":"Appelvinklaan 15",
    "sg:city":"Maarn",
    "sg:orig_category":"Technische Studies And Onderzoek",
    "sg:phone":"+31 343 442 494",
    "sg:postcode":"3951 WR",
    "sg:province":"Utrecht",
    "wof:name":"R.W.T. Derks Consulting",
    "wof:placetype":"venue"
},
  "geometry": {"coordinates":[5.376216,52.068634],"type":"Point"}
}