{
  "type": "Feature",
  "properties": {
    "addr:full":"Ln V Haagvliet 30 Voorburg Zuid-Holland 2271 XP",
    "addr:housenumber":"30",
    "addr:postcode":"2271 xp",
    "addr:street":"Ln;Haagvliet",
    "iso:country":"NL",
    "sg:address":"Ln V Haagvliet 30",
    "sg:city":"Voorburg",
    "sg:orig_category":"Boekbinderijen",
    "sg:phone":"+31 70 386 4591",
    "sg:postcode":"2271 XP",
    "sg:province":"Zuid-Holland",
    "sg:website":"http://www.verschoorvof.nl",
    "wof:name":"Verschoor Boekbinderij",
    "wof:placetype":"venue"
},
  "geometry": {"coordinates":[4.363825,52.068233],"type":"Point"}
}