{
  "type": "Feature",
  "properties": {
    "addr:full":"Molenstraat 64 Nijmegen Gelderland 6511 HG",
    "addr:housenumber":"64",
    "addr:postcode":"6511 hg",
    "addr:street":"Molenstraat;Gelderland",
    "iso:country":"NL",
    "sg:address":"Molenstraat 64",
    "sg:city":"Nijmegen",
    "sg:orig_category":"Damesmodezaken",
    "sg:phone":"+31 24 322 0604",
    "sg:postcode":"6511 HG",
    "sg:province":"Gelderland",
    "wof:name":"Boetiek 32",
    "wof:placetype":"venue"
},
  "geometry": {"coordinates":[5.8627,51.844601],"type":"Point"}
}