{
  "type": "Feature",
  "properties": {
    "addr:full":"Hogewg 133 Zaltbommel Gelderland 5301 LL",
    "addr:housenumber":"133",
    "addr:postcode":"5301 ll",
    "addr:street":"Gelderland",
    "iso:country":"NL",
    "sg:address":"Hogewg 133",
    "sg:city":"Zaltbommel",
    "sg:orig_category":"Adviesbureaus Bedrijfsorganisatie",
    "sg:phone":"+31 418 684 650",
    "sg:postcode":"5301 LL",
    "sg:province":"Gelderland",
    "sg:website":"http://www.meteq.nl",
    "wof:name":"Meteq Consult",
    "wof:placetype":"venue"
},
  "geometry": {"coordinates":[5.2563,51.80101],"type":"Point"}
}