{
  "type": "Feature",
  "properties": {
    "addr:full":"A F D Savornin Lohmanstr 2 Zaandam North Holland 1501 NH",
    "addr:housenumber":"2",
    "addr:postcode":"1501 nh",
    "addr:street":"A F D Savornin Lohmanstr",
    "iso:country":"NL",
    "sg:address":"A F D Savornin Lohmanstr 2",
    "sg:city":"Zaandam",
    "sg:orig_category":"Paramedische Behandelingen",
    "sg:phone":"+31 75 617 8233",
    "sg:postcode":"1501 NH",
    "sg:province":"North Holland",
    "wof:name":"Baars' Medical Supports",
    "wof:placetype":"venue"
},
  "geometry": {"coordinates":[4.827548,52.439514],"type":"Point"}
}