{
  "type": "Feature",
  "properties": {
    "addr:full":"Gildemeesterspln 100 Arnhem Gelderland 6826 LN",
    "addr:housenumber":"100",
    "addr:postcode":"6826 ln",
    "iso:country":"NL",
    "sg:address":"Gildemeesterspln 100",
    "sg:city":"Arnhem",
    "sg:orig_category":"Fotoreportages",
    "sg:phone":"+31 26 364 4319",
    "sg:postcode":"6826 LN",
    "sg:province":"Gelderland",
    "sg:website":"http://come.to/fotografe",
    "wof:name":"Bhomer",
    "wof:placetype":"venue"
},
  "geometry": {"coordinates":[5.952803,51.984791],"type":"Point"}
}