{
  "type": "Feature",
  "properties": {
    "iso:country":"NL",
    "sg:address":"Lomanlaan 37",
    "sg:city":"Hoogeveen",
    "sg:orig_category":"Loodgieterswerk, Verwarming And Sanitaire Installaties",
    "sg:phone":"+31 528 274 215",
    "sg:postcode":"7906 HB",
    "sg:province":"Drenthe",
    "wof:name":"G. Lunenborg",
    "wof:placetype":"venue"
},
  "geometry": {"coordinates":[6.478563,52.713726],"type":"Point"}
}