{
  "type": "Feature",
  "properties": {
    "iso:country":"NL",
    "sg:address":"Sibemaweg 97",
    "sg:city":"Maastricht",
    "sg:orig_category":"Elektronische Bedrijfsinstallaties",
    "sg:phone":"+31 43 363 0374",
    "sg:postcode":"6226 HX",
    "sg:province":"Limburg",
    "wof:name":"Hardy Security Systems",
    "wof:placetype":"venue"
},
  "geometry": {"coordinates":[5.718856,50.848621],"type":"Point"}
}