{
  "type": "Feature",
  "properties": {
    "addr:full":"Hoogend 9 Sneek Friesland 8601 AD",
    "addr:housenumber":"9",
    "addr:postcode":"8601 ad",
    "addr:street":"Hoogend",
    "iso:country":"NL",
    "sg:address":"Hoogend 9",
    "sg:city":"Sneek",
    "sg:orig_category":"Begrafenisondernemers",
    "sg:phone":"+31 515 411 000",
    "sg:postcode":"8601 AD",
    "sg:province":"Friesland",
    "wof:name":"J. Ae. De Boer'S Uitvaartverzorging Snee",
    "wof:placetype":"venue"
},
  "geometry": {"coordinates":[5.660365,53.029575],"type":"Point"}
}