{
  "type": "Feature",
  "properties": {
    "addr:full":"Kerkstr 7 Hengelo Gld Gelderland 7255 CB",
    "addr:housenumber":"7",
    "addr:postcode":"7255 cb",
    "addr:street":"Kerkstr",
    "iso:country":"NL",
    "sg:address":"Kerkstr 7",
    "sg:city":"Hengelo Gld",
    "sg:orig_category":"Kappers",
    "sg:phone":"+31 575 461 500",
    "sg:postcode":"7255 CB",
    "sg:province":"Gelderland",
    "wof:name":"Barbier, De",
    "wof:placetype":"venue"
},
  "geometry": {"coordinates":[6.3093018532,52.0526771545],"type":"Point"}
}