{
  "type": "Feature",
  "properties": {
    "iso:country":"NL",
    "sg:address":"L Dreef 13",
    "sg:city":"Culemborg",
    "sg:orig_category":"Adviesbureaus Bedrijfsorganisatie",
    "sg:phone":"+31 345 548 771",
    "sg:postcode":"4101 NR",
    "sg:province":"Gelderland",
    "wof:name":"Jobart Adviser",
    "wof:placetype":"venue"
},
  "geometry": {"coordinates":[5.237379,51.960926],"type":"Point"}
}