{
  "type": "Feature",
  "properties": {
    "addr:full":"Kaldebornwg 57 Heerlen Limburg 6416 HA",
    "addr:housenumber":"57",
    "addr:postcode":"6416 ha",
    "addr:street":"Kaldebornwg",
    "iso:country":"NL",
    "sg:address":"Kaldebornwg 57",
    "sg:city":"Heerlen",
    "sg:orig_category":"Organisatiebureaus",
    "sg:phone":"+31 45 542 4666",
    "sg:postcode":"6416 HA",
    "sg:province":"Limburg",
    "wof:name":"Beyer",
    "wof:placetype":"venue"
},
  "geometry": {"coordinates":[5.9917368889,50.8777389526],"type":"Point"}
}