{
  "type": "Feature",
  "properties": {
    "addr:full":"Kaatswg 6 Roderesch Drenthe 9305 TA",
    "addr:housenumber":"6",
    "addr:postcode":"9305 ta",
    "addr:street":"Kaatswg",
    "iso:country":"NL",
    "sg:address":"Kaatswg 6",
    "sg:city":"Roderesch",
    "sg:orig_category":"Geluidsinstallaties - Verhuur",
    "sg:phone":"+31 50 501 3146",
    "sg:postcode":"9305 TA",
    "sg:province":"Drenthe",
    "wof:name":"Wigo'S Audio Support",
    "wof:placetype":"venue"
},
  "geometry": {"coordinates":[6.419801,53.11409],"type":"Point"}
}