{
  "type": "Feature",
  "properties": {
    "addr:full":"Langeweg 1 Zuidland Zuid-Holland 3214 LJ",
    "addr:housenumber":"1",
    "addr:postcode":"3214 lj",
    "addr:street":"Langeweg",
    "iso:country":"NL",
    "sg:address":"Langeweg 1",
    "sg:city":"Zuidland",
    "sg:orig_category":"Diverse Bedrijfsinstallaties Gh",
    "sg:phone":"+31 181 458 555",
    "sg:postcode":"3214 LJ",
    "sg:province":"Zuid-Holland",
    "wof:name":"Marflex Bv",
    "wof:placetype":"venue"
},
  "geometry": {"coordinates":[4.245313,51.819984],"type":"Point"}
}