{
  "type": "Feature",
  "properties": {
    "iso:country":"NL",
    "sg:address":"Strevelsweg 700",
    "sg:city":"Rotterdam",
    "sg:orig_category":"Binnenhuisarchitecten",
    "sg:phone":"+31 10 202 1822",
    "sg:postcode":"3083 AS",
    "sg:province":"South Holland",
    "wof:name":"Ineen Ontwerp",
    "wof:placetype":"venue"
},
  "geometry": {"coordinates":[4.49325,51.887348],"type":"Point"}
}