{
  "type": "Feature",
  "properties": {
    "addr:full":"Beilervaart 79 Beilen Drenthe 9411 VC",
    "addr:housenumber":"79",
    "addr:postcode":"9411 vc",
    "addr:street":"Beilervaart",
    "iso:country":"NL",
    "sg:address":"Beilervaart 79",
    "sg:city":"Beilen",
    "sg:orig_category":"Adviesbureaus",
    "sg:phone":"+31 593 525 111",
    "sg:postcode":"9411 VC",
    "sg:province":"Drenthe",
    "wof:name":"Ag",
    "wof:placetype":"venue"
},
  "geometry": {"coordinates":[6.447993,52.868855],"type":"Point"}
}