{
  "type": "Feature",
  "properties": {
    "addr:full":"St Jozefstr 4 Stramproy Limburg 6039 BT",
    "addr:housenumber":"4",
    "addr:postcode":"6039 bt",
    "iso:country":"NL",
    "sg:address":"St Jozefstr 4",
    "sg:city":"Stramproy",
    "sg:orig_category":"Keukens",
    "sg:phone":"+31 495 564 018",
    "sg:postcode":"6039 BT",
    "sg:province":"Limburg",
    "wof:name":"Tonk, Wim",
    "wof:placetype":"venue"
},
  "geometry": {"coordinates":[5.718632,51.19651],"type":"Point"}
}