{
  "type": "Feature",
  "properties": {
    "addr:full":"Koningstraat 2 Steenwijk NL.08 8331 HV",
    "addr:housenumber":"2;nl.08",
    "addr:postcode":"8331 hv",
    "addr:street":"Koningstraat",
    "iso:country":"NL",
    "sg:address":"Koningstraat 2",
    "sg:city":"Steenwijk",
    "sg:orig_category":"Verlichting And Huishoudartikelen",
    "sg:phone":"+31 521 514 845",
    "sg:postcode":"8331 HV",
    "sg:province":"NL.08",
    "wof:name":"Kerkstra Verlichting",
    "wof:placetype":"venue"
},
  "geometry": {"coordinates":[6.11712,52.786598],"type":"Point"}
}