{
  "type": "Feature",
  "properties": {
    "iso:country":"NL",
    "sg:address":"A Poelmanstr 23",
    "sg:city":"Heemskerk",
    "sg:orig_category":"Bedrijfsopleidingen",
    "sg:phone":"+31 251 200 473",
    "sg:postcode":"1963 EP",
    "sg:province":"Noord-Holland",
    "wof:name":"Stb",
    "wof:placetype":"venue"
},
  "geometry": {"coordinates":[4.687041,52.521004],"type":"Point"}
}