{
  "type": "Feature",
  "properties": {
    "addr:full":"Sprendlingenstr 21 Oisterwyk North Brabant 5061 KM",
    "addr:housenumber":"21",
    "addr:postcode":"5061 km",
    "addr:street":"Sprendlingenstr",
    "iso:country":"NL",
    "sg:address":"Sprendlingenstr 21",
    "sg:city":"Oisterwyk",
    "sg:orig_category":"Grondwerken",
    "sg:phone":"+31 13 528 7281",
    "sg:postcode":"5061 KM",
    "sg:province":"North Brabant",
    "wof:name":"Save Bv",
    "wof:placetype":"venue"
},
  "geometry": {"coordinates":[5.186093,51.585102],"type":"Point"}
}