{
  "type": "Feature",
  "properties": {
    "addr:full":"Dordogneln 128 Eindhoven North Brabant 5627 HH",
    "addr:housenumber":"128",
    "addr:postcode":"5627 hh",
    "iso:country":"NL",
    "sg:address":"Dordogneln 128",
    "sg:city":"Eindhoven",
    "sg:orig_category":"Kunstgebitten",
    "sg:phone":"+31 40 241 7435",
    "sg:postcode":"5627 HH",
    "sg:province":"North Brabant",
    "wof:name":"Kruijff Tandprotheticus",
    "wof:placetype":"venue"
},
  "geometry": {"coordinates":[5.452158,51.479473],"type":"Point"}
}