{
  "type": "Feature",
  "properties": {
    "addr:full":"1E Hasselaerstr 3 Haarlem Noord-Holland 2013 GD",
    "addr:housenumber":"3",
    "addr:postcode":"2013 gd",
    "addr:street":"1E Hasselaerstr",
    "iso:country":"NL",
    "sg:address":"1E Hasselaerstr 3",
    "sg:city":"Haarlem",
    "sg:orig_category":"Adviesbureaus Automatisering",
    "sg:phone":"+31 23 526 6117",
    "sg:postcode":"2013 GD",
    "sg:province":"Noord-Holland",
    "sg:website":"http://www.wortell.nl",
    "wof:name":"Wortell Bv",
    "wof:placetype":"venue"
},
  "geometry": {"coordinates":[4.62771,52.38409],"type":"Point"}
}