{
  "type": "Feature",
  "properties": {
    "iso:country":"NL",
    "sg:address":"Nieuwevaart 10",
    "sg:city":"Amsterdam",
    "sg:orig_category":"Jachten - Schilderwerken En Onderhoud",
    "sg:phone":"+31 20 625 4356",
    "sg:postcode":"1018 AA",
    "sg:province":"Noord-Holland",
    "wof:name":"Past",
    "wof:placetype":"venue"
},
  "geometry": {"coordinates":[4.913347,52.370522],"type":"Point"}
}