{
  "type": "Feature",
  "properties": {
    "addr:full":"Keiwg 59 Oosterhout Nb Noord-Brabant 4901 JD",
    "addr:housenumber":"59",
    "addr:postcode":"4901 jd",
    "addr:street":"Keiwg",
    "iso:country":"NL",
    "sg:address":"Keiwg 59",
    "sg:city":"Oosterhout Nb",
    "sg:orig_category":"Geluidsinstallaties",
    "sg:phone":"+31 162 470 134",
    "sg:postcode":"4901 JD",
    "sg:province":"Noord-Brabant",
    "wof:name":"Rs, Audio En Light",
    "wof:placetype":"venue"
},
  "geometry": {"coordinates":[4.862197,51.641495],"type":"Point"}
}