{
  "type": "Feature",
  "properties": {
    "addr:full":"Havenstr 1 Schiedam Zuid-Holland 3115 HC",
    "addr:housenumber":"1",
    "addr:postcode":"3115 hc",
    "addr:street":"Havenstr",
    "iso:country":"NL",
    "sg:address":"Havenstr 1",
    "sg:city":"Schiedam",
    "sg:orig_category":"Gassen Industrieel En Medisch",
    "sg:phone":"+31 10 246 1616",
    "sg:postcode":"3115 HC",
    "sg:province":"Zuid-Holland",
    "sg:website":"http://www.hoekloos.nl",
    "wof:name":"Hoek Loos Bv",
    "wof:placetype":"venue"
},
  "geometry": {"coordinates":[4.39842,51.903881],"type":"Point"}
}