{
  "type": "Feature",
  "properties": {
    "addr:full":"Gentsestraat 46 'S Gravenhage South Holland 2587 HV",
    "addr:housenumber":"46",
    "addr:postcode":"2587 hv",
    "addr:street":"Gentsestraat;' S Gravenhage",
    "iso:country":"NL",
    "sg:address":"Gentsestraat 46",
    "sg:city":"'S Gravenhage",
    "sg:orig_category":"Binnenhuisarchitecten",
    "sg:phone":"+31 70 350 2648",
    "sg:postcode":"2587 HV",
    "sg:province":"South Holland",
    "wof:name":"Duo Deco Bv",
    "wof:placetype":"venue"
},
  "geometry": {"coordinates":[4.289983,52.110958],"type":"Point"}
}