{
  "type": "Feature",
  "properties": {
    "iso:country":"NL",
    "sg:address":"Boulevard 27",
    "sg:city":"Velp Gld",
    "sg:orig_category":"Public Relationbureaus",
    "sg:phone":"+31 26 361 4179",
    "sg:postcode":"6881 HP",
    "sg:province":"Gelderland",
    "wof:name":"Coiriet V Overbeek Comm.Man. Publ.Rel./Voorl.",
    "wof:placetype":"venue"
},
  "geometry": {"coordinates":[5.974032,51.999043],"type":"Point"}
}