{
  "type": "Feature",
  "properties": {
    "addr:full":"Kerkstraat 224 Brunssum Limburg 6441 BK",
    "addr:housenumber":"224",
    "addr:postcode":"6441 bk",
    "addr:street":"Kerkstraat",
    "iso:country":"NL",
    "sg:address":"Kerkstraat 224",
    "sg:city":"Brunssum",
    "sg:orig_category":"Fotolaboratoria",
    "sg:phone":"+31 45 564 6500",
    "sg:postcode":"6441 BK",
    "sg:province":"Limburg",
    "wof:name":"Warenhuis Vromen Brunssum Bv",
    "wof:placetype":"venue"
},
  "geometry": {"coordinates":[5.972092,50.94656],"type":"Point"}
}