{
  "type": "Feature",
  "properties": {
    "addr:full":"A Cuypstr 2 Arnhem Gelderland 6814 LD",
    "addr:housenumber":"2",
    "addr:postcode":"6814 ld",
    "iso:country":"NL",
    "sg:address":"A Cuypstr 2",
    "sg:city":"Arnhem",
    "sg:orig_category":"Verenigingen En Stichtingen",
    "sg:phone":"+31 26 443 5393",
    "sg:postcode":"6814 LD",
    "sg:province":"Gelderland",
    "sg:website":"http://www.kankerbestrijding.nl",
    "wof:name":"Kankerbestrijding Kwf",
    "wof:placetype":"venue"
},
  "geometry": {"coordinates":[5.889676,51.994461],"type":"Point"}
}