{
  "type": "Feature",
  "properties": {
    "addr:full":"Eigelhorst 19 Rotterdam Zuid-Holland 3085 VB",
    "addr:housenumber":"19",
    "addr:postcode":"3085 vb",
    "addr:street":"Eigelhorst",
    "iso:country":"NL",
    "sg:address":"Eigelhorst 19",
    "sg:city":"Rotterdam",
    "sg:orig_category":"Grondwerken",
    "sg:phone":"+31 10 423 0556",
    "sg:postcode":"3085 VB",
    "sg:province":"Zuid-Holland",
    "wof:name":"Kescom Bv",
    "wof:placetype":"venue"
},
  "geometry": {"coordinates":[4.496495,51.87709],"type":"Point"}
}