{
  "type": "Feature",
  "properties": {
    "addr:full":"Nieuwendammerdk 526G Amsterdam Noord-Holland 1023 BX",
    "addr:housenumber":"526g",
    "addr:postcode":"1023 bx",
    "addr:street":"Nieuwendammerdk",
    "iso:country":"NL",
    "sg:address":"Nieuwendammerdk 526G",
    "sg:city":"Amsterdam",
    "sg:orig_category":"Motorrevisie En -Inbouw",
    "sg:phone":"+31 20 632 0209",
    "sg:postcode":"1023 BX",
    "sg:province":"Noord-Holland",
    "sg:website":"http://www.oudejans.com",
    "wof:name":"Oudejans, Motorenrevisie",
    "wof:placetype":"venue"
},
  "geometry": {"coordinates":[4.945277,52.384846],"type":"Point"}
}