{
  "type": "Feature",
  "properties": {
    "addr:full":"Piet Heinstraat 79 Hengelo Ov NL.08 7556 XT",
    "addr:housenumber":"79",
    "addr:postcode":"7556 xt",
    "addr:street":"Piet Heinstraat;Ov",
    "iso:country":"NL",
    "sg:address":"Piet Heinstraat 79",
    "sg:city":"Hengelo Ov",
    "sg:orig_category":"Paramedische Behandelingen",
    "sg:phone":"+31 74 250 5800",
    "sg:postcode":"7556 XT",
    "sg:province":"NL.08",
    "wof:name":"Kraamzorg Ntn",
    "wof:placetype":"venue"
},
  "geometry": {"coordinates":[6.799956,52.271015],"type":"Point"}
}