{
  "type": "Feature",
  "properties": {
    "addr:full":"Zandenwg 3/A Maren Kessel Gelderland 5398 KD",
    "addr:housenumber":"3 / a",
    "addr:postcode":"5398 kd",
    "addr:street":"Zandenwg;Maren;Gelderland",
    "iso:country":"NL",
    "sg:address":"Zandenwg 3/A",
    "sg:city":"Maren Kessel",
    "sg:orig_category":"Modevakscholen",
    "sg:phone":"+31 412 479 470",
    "sg:postcode":"5398 KD",
    "sg:province":"Gelderland",
    "wof:name":"Ensaid",
    "wof:placetype":"venue"
},
  "geometry": {"coordinates":[5.365668,51.76255],"type":"Point"}
}