{
  "type": "Feature",
  "properties": {
    "addr:full":"Javakd 514 Amsterdam Noord-Holland 1019 SC",
    "addr:housenumber":"514;1019",
    "iso:country":"NL",
    "sg:address":"Javakd 514",
    "sg:city":"Amsterdam",
    "sg:orig_category":"Adviesbureaus Bedrijfsorganisatie",
    "sg:phone":"+31 20 419 6259",
    "sg:postcode":"1019 SC",
    "sg:province":"Noord-Holland",
    "wof:name":"Pno Bvba",
    "wof:placetype":"venue"
},
  "geometry": {"coordinates":[4.893195,52.373119],"type":"Point"}
}