{
  "type": "Feature",
  "properties": {
    "addr:full":"Noordschans 67 Klundert North Brabant 4791 RE",
    "addr:housenumber":"67",
    "addr:postcode":"4791 re",
    "addr:street":"Noordschans",
    "iso:country":"NL",
    "sg:address":"Noordschans 67",
    "sg:city":"Klundert",
    "sg:classifiers":[
        {
            "category":"Home & Garden",
            "subcategory":"Building Materials",
            "type":"Retail Goods"
        }
    ],
    "sg:phone":"+31 168 403 685",
    "sg:postcode":"4791 RE",
    "sg:province":"North Brabant",
    "sg:tags":[
        "hout",
        "en",
        "board",
        "triplex"
    ],
    "wof:name":"Vermeulen Houthandel",
    "wof:placetype":"venue"
},
  "geometry": {"coordinates":[4.52404,51.67804],"type":"Point"}
}