{
  "type": "Feature",
  "properties": {
    "addr:full":"Hurksestr 26B Eindhoven Noord-Brabant 5652 AL",
    "addr:housenumber":"26b",
    "addr:postcode":"5652 al",
    "addr:street":"Hurksestr",
    "iso:country":"NL",
    "sg:address":"Hurksestr 26B",
    "sg:city":"Eindhoven",
    "sg:orig_category":"Geluidsinstallaties",
    "sg:phone":"+31 40 291 0635",
    "sg:postcode":"5652 AL",
    "sg:province":"Noord-Brabant",
    "wof:name":"Teddo Peeren",
    "wof:placetype":"venue"
},
  "geometry": {"coordinates":[5.436544,51.433865],"type":"Point"}
}