{
  "type": "Feature",
  "properties": {
    "iso:country":"NL",
    "sg:address":"Zutphensestrwg 13",
    "sg:city":"Velp Gld",
    "sg:orig_category":"Video - Faciliteiten En Producties",
    "sg:phone":"+31 26 362 2992",
    "sg:postcode":"6881 WN",
    "sg:province":"Gelderland",
    "wof:name":"Ja Productions/Cumulus",
    "wof:placetype":"venue"
},
  "geometry": {"coordinates":[5.98364,51.997742],"type":"Point"}
}