{
  "type": "Feature",
  "properties": {
    "addr:full":"Soestdijkerstraatweg 110 Hilversum Noord-Holland 1213 XH",
    "addr:housenumber":"110",
    "addr:postcode":"1213 xh",
    "addr:street":"Soestdijkerstraatweg",
    "iso:country":"NL",
    "sg:address":"Soestdijkerstraatweg 110",
    "sg:city":"Hilversum",
    "sg:orig_category":"Diverse Bedrijfsinstallaties Gh",
    "sg:phone":"+31 35 646 0011",
    "sg:postcode":"1213 XH",
    "sg:province":"Noord-Holland",
    "wof:name":"Pipesystems & Components Bv",
    "wof:placetype":"venue"
},
  "geometry": {"coordinates":[5.204222,52.210617],"type":"Point"}
}