{
  "type": "Feature",
  "properties": {
    "addr:full":"Schoener 3109 Lelystad Flevoland 8243 WB",
    "addr:postcode":"3109;8243 wb",
    "addr:street":"Schoener;Flevoland",
    "iso:country":"NL",
    "sg:address":"Schoener 3109",
    "sg:city":"Lelystad",
    "sg:orig_category":"Kunststoffen - Fabrieken En Groothandel",
    "sg:phone":"+31 6 24229870",
    "sg:postcode":"8243 WB",
    "sg:province":"Flevoland",
    "wof:name":"Coretec",
    "wof:placetype":"venue"
},
  "geometry": {"coordinates":[5.458566,52.501019],"type":"Point"}
}