{
  "type": "Feature",
  "properties": {
    "addr:full":"Nyverheidswg 2 Schagerbrug Noord-Holland 1751 HG",
    "addr:housenumber":"2",
    "addr:postcode":"1751 hg",
    "addr:street":"Nyverheidswg",
    "iso:country":"NL",
    "sg:address":"Nyverheidswg 2",
    "sg:city":"Schagerbrug",
    "sg:orig_category":"Timmerwerken",
    "sg:phone":"+31 224 571 875",
    "sg:postcode":"1751 HG",
    "sg:province":"Noord-Holland",
    "wof:name":"Slagter Vof, H R",
    "wof:placetype":"venue"
},
  "geometry": {"coordinates":[4.754183,52.80349],"type":"Point"}
}