{
  "type": "Feature",
  "properties": {
    "iso:country":"NL",
    "sg:address":"Torendijk 10A",
    "sg:city":"Ambt Delden",
    "sg:orig_category":"Pluimveehouderijen",
    "sg:phone":"+31 74 376 3571",
    "sg:postcode":"7495 PX",
    "sg:province":"NL.08",
    "wof:name":"Pluimveebedrijf A W Jannink",
    "wof:placetype":"venue"
},
  "geometry": {"coordinates":[6.71091,52.248161],"type":"Point"}
}