{
  "type": "Feature",
  "properties": {
    "addr:full":"Heerbaan 9 Posterholt Limburg 6061 EB",
    "addr:housenumber":"9",
    "addr:postcode":"6061 eb",
    "addr:street":"Heerbaan",
    "iso:country":"NL",
    "sg:address":"Heerbaan 9",
    "sg:city":"Posterholt",
    "sg:orig_category":"Bedrijfskleding",
    "sg:phone":"+31 475 531 400",
    "sg:postcode":"6061 EB",
    "sg:province":"Limburg",
    "sg:website":"http://www.bedrijvenplanet.nl",
    "wof:name":"Botex",
    "wof:placetype":"venue"
},
  "geometry": {"coordinates":[6.036481,51.122585],"type":"Point"}
}