{
  "type": "Feature",
  "properties": {
    "addr:full":"Rechtstr 84 Maastricht Limburg 6221 EL",
    "addr:housenumber":"84",
    "addr:postcode":"6221 el",
    "addr:street":"Rechtstr",
    "iso:country":"NL",
    "sg:address":"Rechtstr 84",
    "sg:city":"Maastricht",
    "sg:classifiers":[
        {
            "category":"Professional",
            "subcategory":"Printing & Photocopies",
            "type":"Services"
        }
    ],
    "sg:phone":"+31 43 325 3232",
    "sg:postcode":"6221 EL",
    "sg:province":"Limburg",
    "sg:tags":[
        "printer"
    ],
    "sg:website":"http://www.riflessi.nl",
    "wof:name":"Riflessi",
    "wof:placetype":"venue"
},
  "geometry": {"coordinates":[5.698006,50.84808],"type":"Point"}
}