{
  "type": "Feature",
  "properties": {
    "iso:country":"NL",
    "sg:address":"Mezendaal 90",
    "sg:city":"Nieuwerkerk Yssel",
    "sg:orig_category":"Bejaarden - Verzorgingstehuizen",
    "sg:phone":"+31 180 333 899",
    "sg:postcode":"2914 EE",
    "sg:province":"Zuid-Holland",
    "wof:name":"Dianthus",
    "wof:placetype":"venue"
},
  "geometry": {"coordinates":[4.614766,51.968826],"type":"Point"}
}