{
  "type": "Feature",
  "properties": {
    "addr:full":"Industrieweg 12 Maarssen Utrecht 3606 AS",
    "addr:housenumber":"12",
    "addr:postcode":"3606 as",
    "addr:street":"Industrieweg",
    "iso:country":"NL",
    "sg:address":"Industrieweg 12",
    "sg:city":"Maarssen",
    "sg:orig_category":"Bouwmaterialen Gh",
    "sg:phone":"+31 346 573 232",
    "sg:postcode":"3606 AS",
    "sg:province":"Utrecht",
    "wof:name":"Glasurit",
    "wof:placetype":"venue"
},
  "geometry": {"coordinates":[5.040676,52.128193],"type":"Point"}
}