{
  "type": "Feature",
  "properties": {
    "addr:full":"Zamenhofsingel 27 Zwolle Overijssel 8021 DA",
    "addr:housenumber":"27",
    "addr:postcode":"8021 da",
    "addr:street":"Zamenhofsingel",
    "iso:country":"NL",
    "sg:address":"Zamenhofsingel 27",
    "sg:city":"Zwolle",
    "sg:orig_category":"Overheidsdiensten",
    "sg:phone":"+31 38 456 8899",
    "sg:postcode":"8021 DA",
    "sg:province":"Overijssel",
    "wof:name":"Belastingdienst Ondernemingen Zwolle",
    "wof:placetype":"venue"
},
  "geometry": {"coordinates":[6.0962901115,52.517490387],"type":"Point"}
}