{
  "type": "Feature",
  "properties": {
    "addr:full":"Poortland 41 Amsterdam North Holland 1046 BD",
    "addr:housenumber":"41",
    "addr:postcode":"1046 bd",
    "addr:street":"Poortland",
    "iso:country":"NL",
    "sg:address":"Poortland 41",
    "sg:city":"Amsterdam",
    "sg:orig_category":"Keuken- Groot-Installaties",
    "sg:phone":"+31 20 480 1050",
    "sg:postcode":"1046 BD",
    "sg:province":"North Holland",
    "wof:name":"F1Rst",
    "wof:placetype":"venue"
},
  "geometry": {"coordinates":[4.784803,52.392281],"type":"Point"}
}