{
  "type": "Feature",
  "properties": {
    "addr:full":"Muzenln 1 Heerlen Limburg 6411 AC",
    "addr:housenumber":"1",
    "addr:postcode":"6411 ac",
    "addr:street":"Muzenln",
    "iso:country":"NL",
    "sg:address":"Muzenln 1",
    "sg:city":"Heerlen",
    "sg:orig_category":"Parkeergarages",
    "sg:phone":"+31 900 4466880",
    "sg:postcode":"6411 AC",
    "sg:province":"Limburg",
    "wof:name":"Q-Park",
    "wof:placetype":"venue"
},
  "geometry": {"coordinates":[5.972232,50.886784],"type":"Point"}
}