{
  "type": "Feature",
  "properties": {
    "addr:full":"Admiraliteitstr 31 Amsterdam Noord-Holland 1018 KP",
    "addr:housenumber":"31",
    "addr:postcode":"1018 kp",
    "addr:street":"Admiraliteitstr",
    "iso:country":"NL",
    "sg:address":"Admiraliteitstr 31",
    "sg:city":"Amsterdam",
    "sg:orig_category":"Schilders",
    "sg:phone":"+31 20 774 8487",
    "sg:postcode":"1018 KP",
    "sg:province":"Noord-Holland",
    "sg:website":"http://www.firstclass-schilderwerken.nl",
    "wof:name":"First Class",
    "wof:placetype":"venue"
},
  "geometry": {"coordinates":[4.924103,52.368538],"type":"Point"}
}