{
  "type": "Feature",
  "properties": {
    "addr:full":"Oostendewg 24 Groningen Groningen 9723 HH",
    "addr:housenumber":"24",
    "addr:postcode":"9723 hh",
    "addr:street":"Oostendewg",
    "iso:country":"NL",
    "sg:address":"Oostendewg 24",
    "sg:city":"Groningen",
    "sg:orig_category":"Wasmachines En Wasdrogers - Onderhoud En Reparatie",
    "sg:phone":"+31 50 542 2636",
    "sg:postcode":"9723 HH",
    "sg:province":"Groningen",
    "wof:name":"Herman",
    "wof:placetype":"venue"
},
  "geometry": {"coordinates":[6.5974001884,53.2043571472],"type":"Point"}
}