{
  "type": "Feature",
  "properties": {
    "iso:country":"NL",
    "sg:address":"Bedryfswg 29",
    "sg:city":"Dronten",
    "sg:orig_category":"Land- En Tuinbouw - Loonbedrijven",
    "sg:phone":"+31 321 312 934",
    "sg:postcode":"8251 KK",
    "sg:province":"NL.",
    "sg:website":"http://www.maris-dronten.nl",
    "wof:name":"Maris Agro En Cultuurtechniek",
    "wof:placetype":"venue"
},
  "geometry": {"coordinates":[5.716603,52.532402],"type":"Point"}
}