{
  "type": "Feature",
  "properties": {
    "iso:country":"NL",
    "sg:address":"Aalsterweg 213",
    "sg:city":"Eindhoven",
    "sg:orig_category":"Architecten",
    "sg:phone":"+31 40 212 0745",
    "sg:postcode":"5644 RB",
    "sg:province":"Noord-Brabant",
    "wof:name":"Architectenburo C.M.T. Frerker",
    "wof:placetype":"venue"
},
  "geometry": {"coordinates":[5.484631,51.420002],"type":"Point"}
}