{
  "type": "Feature",
  "properties": {
    "addr:full":"Orlando Di Lassostraat 14 Oss Noord-Brabant 5344 AC",
    "addr:housenumber":"14",
    "addr:postcode":"5344 ac",
    "addr:street":"Orlando Di Lassostraat",
    "iso:country":"NL",
    "sg:address":"Orlando Di Lassostraat 14",
    "sg:city":"Oss",
    "sg:orig_category":"Bloemen And Planten Gh",
    "sg:phone":"+31 412 622 484",
    "sg:postcode":"5344 AC",
    "sg:province":"Noord-Brabant",
    "wof:name":"Ulehake Vof",
    "wof:placetype":"venue"
},
  "geometry": {"coordinates":[-77.235214,38.312599],"type":"Point"}
}