{
  "type": "Feature",
  "properties": {
    "addr:full":"Eendrachtswg 11 Tholen Zeeland 4691 EK",
    "addr:housenumber":"11",
    "addr:postcode":"4691 ek",
    "addr:street":"Eendrachtswg",
    "iso:country":"NL",
    "sg:address":"Eendrachtswg 11",
    "sg:city":"Tholen",
    "sg:orig_category":"Hypotheken",
    "sg:phone":"+31 166 605 360",
    "sg:postcode":"4691 EK",
    "sg:province":"Zeeland",
    "wof:name":"Hypotheekhuys Tholen",
    "wof:placetype":"venue"
},
  "geometry": {"coordinates":[4.223008,51.533115],"type":"Point"}
}