{
  "type": "Feature",
  "properties": {
    "iso:country":"NL",
    "sg:address":"Willemsparkwg 145",
    "sg:city":"Amsterdam",
    "sg:orig_category":"Adviesbureaus Marketing",
    "sg:phone":"+31 20 670 9892",
    "sg:postcode":"1071 GX",
    "sg:province":"Noord-Holland",
    "wof:name":"Doorn & Van Doorn Bv, Van",
    "wof:placetype":"venue"
},
  "geometry": {"coordinates":[4.871898,52.356201],"type":"Point"}
}