{
  "type": "Feature",
  "properties": {
    "addr:full":"Lichtenvoordseweg 58 Groenlo Gelderland 7141 DZ",
    "addr:housenumber":"58",
    "addr:postcode":"7141 dz",
    "addr:street":"Lichtenvoordseweg;Gelderland",
    "iso:country":"NL",
    "sg:address":"Lichtenvoordseweg 58",
    "sg:city":"Groenlo",
    "sg:orig_category":"Begrafenisondernemers",
    "sg:phone":"+31 544 461 515",
    "sg:postcode":"7141 DZ",
    "sg:province":"Gelderland",
    "wof:name":"Stichting Uitvaartverzorging Groenlo",
    "wof:placetype":"venue"
},
  "geometry": {"coordinates":[6.614417,52.035145],"type":"Point"}
}