{
  "type": "Feature",
  "properties": {
    "addr:full":"Aart Van Der Neerweg 1 Ouderkerk A/D Amstel North Holland 1191 EC",
    "addr:housenumber":"1;a / d",
    "addr:postcode":"1191 ec",
    "addr:street":"Aart Van Der Neerweg;Amstel North",
    "iso:country":"NL",
    "sg:address":"Aart Van Der Neerweg 1",
    "sg:city":"Ouderkerk A/D Amstel",
    "sg:orig_category":"Meubelzaken, Woning- And Keukeninrichting",
    "sg:phone":"+31 20 496 7310",
    "sg:postcode":"1191 EC",
    "sg:province":"North Holland",
    "wof:name":"Smeur Estetisch Wonen",
    "wof:placetype":"venue"
},
  "geometry": {"coordinates":[4.9124999046,52.299446106],"type":"Point"}
}