{
  "type": "Feature",
  "properties": {
    "addr:full":"Regulierenring 13B Bunnik Utrecht 3981 LA",
    "addr:housenumber":"13b",
    "addr:postcode":"3981 la",
    "addr:street":"Regulierenring",
    "iso:country":"NL",
    "sg:address":"Regulierenring 13B",
    "sg:city":"Bunnik",
    "sg:orig_category":"Adviesbureaus Bedrijfsorganisatie",
    "sg:phone":"+31 30 656 6080",
    "sg:postcode":"3981 LA",
    "sg:province":"Utrecht",
    "wof:name":"Quintens",
    "wof:placetype":"venue"
},
  "geometry": {"coordinates":[5.189418,52.063515],"type":"Point"}
}