{
  "type": "Feature",
  "properties": {
    "iso:country":"NL",
    "sg:address":"Postbus 150",
    "sg:city":"Ijsselstein Ut",
    "sg:orig_category":"Projectontwikkeling",
    "sg:phone":"+31 30 688 5560",
    "sg:postcode":"3400 AD",
    "wof:name":"Rijver Bv",
    "wof:placetype":"venue"
},
  "geometry": {"coordinates":[5.04266,52.01704],"type":"Point"}
}