{
  "type": "Feature",
  "properties": {
    "iso:country":"NL",
    "sg:address":"Nassaukd 16",
    "sg:city":"Amsterdam",
    "sg:orig_category":"Organisatiebureaus",
    "sg:phone":"+31 20 684 3947",
    "sg:postcode":"1052 CG",
    "sg:province":"Noord-Holland",
    "wof:name":"Pommeline Promotions",
    "wof:placetype":"venue"
},
  "geometry": {"coordinates":[4.8737897873,52.3778991699],"type":"Point"}
}