{
  "type": "Feature",
  "properties": {
    "addr:full":"Speulhofsbaan 10 Horst Limburg 5964 NV",
    "addr:housenumber":"10",
    "addr:postcode":"5964 nv",
    "addr:street":"Speulhofsbaan",
    "iso:country":"NL",
    "sg:address":"Speulhofsbaan 10",
    "sg:city":"Horst",
    "sg:orig_category":"Kappers",
    "sg:phone":"+31 77 398 1957",
    "sg:postcode":"5964 NV",
    "sg:province":"Limburg",
    "wof:name":"Kapsalon Janssen - Hermans",
    "wof:placetype":"venue"
},
  "geometry": {"coordinates":[-117.02272033689999,38.5024604797],"type":"Point"}
}