{
  "type": "Feature",
  "properties": {
    "iso:country":"NL",
    "sg:address":"Kwikstaart 10",
    "sg:city":"Nieuwegein",
    "sg:orig_category":"Fotoreportages",
    "sg:phone":"+31 30 604 3579",
    "sg:postcode":"3435 RM",
    "sg:province":"Utrecht",
    "wof:name":"Doorslag, De",
    "wof:placetype":"venue"
},
  "geometry": {"coordinates":[5.074133,52.027264],"type":"Point"}
}