{
  "type": "Feature",
  "properties": {
    "addr:full":"Kon Julianaln 1 Voorburg Zuid-Holland 2273 JA",
    "addr:housenumber":"1",
    "addr:postcode":"2273 ja",
    "addr:street":"Kon Julianaln",
    "iso:country":"NL",
    "sg:address":"Kon Julianaln 1",
    "sg:city":"Voorburg",
    "sg:orig_category":"Artsen - Manuele Geneeskunde",
    "sg:phone":"+31 70 386 8531",
    "sg:postcode":"2273 JA",
    "sg:province":"Zuid-Holland",
    "sg:website":"http://www.manuelegeneeskunde.nu",
    "wof:name":"Zweerts De Jong, W J",
    "wof:placetype":"venue"
},
  "geometry": {"coordinates":[4.346634,52.078804],"type":"Point"}
}