{
  "type": "Feature",
  "properties": {
    "addr:full":"Gantelstraat 3 Waalwijk North Brabant 5145 PH",
    "addr:housenumber":"3",
    "addr:postcode":"5145",
    "addr:street":"Gantelstraat",
    "iso:country":"NL",
    "sg:address":"Gantelstraat 3",
    "sg:city":"Waalwijk",
    "sg:orig_category":"Bouwmaterialen Gh",
    "sg:phone":"+31 416 335 922",
    "sg:postcode":"5145 PH",
    "sg:province":"North Brabant",
    "wof:name":"Rapetti Nederland Bv",
    "wof:placetype":"venue"
},
  "geometry": {"coordinates":[5.053622,51.70425],"type":"Point"}
}