{
  "type": "Feature",
  "properties": {
    "iso:country":"NL",
    "sg:address":"St Hubertusln 3",
    "sg:city":"Maastricht",
    "sg:orig_category":"Makelaars En Adviseurs Onroerende Goederen",
    "sg:phone":"+31 43 325 0230",
    "sg:postcode":"6211 KC",
    "sg:province":"Limburg",
    "wof:name":"Pustjens Bv",
    "wof:placetype":"venue"
},
  "geometry": {"coordinates":[5.69017,50.842621],"type":"Point"}
}