{
  "type": "Feature",
  "properties": {
    "addr:full":"Wittevrouwenstraat 42 Utrecht Utrecht 3512 CV",
    "addr:housenumber":"42",
    "addr:postcode":"3512 cv",
    "addr:street":"Wittevrouwenstraat",
    "iso:country":"NL",
    "sg:address":"Wittevrouwenstraat 42",
    "sg:city":"Utrecht",
    "sg:orig_category":"Verlichting And Huishoudartikelen",
    "sg:phone":"+31 30 230 2798",
    "sg:postcode":"3512 CV",
    "sg:province":"Utrecht",
    "wof:name":"Nisha",
    "wof:placetype":"venue"
},
  "geometry": {"coordinates":[5.125613,52.095043],"type":"Point"}
}