{
  "type": "Feature",
  "properties": {
    "iso:country":"NL",
    "sg:address":"Roeselarestr 195",
    "sg:city":"Breda",
    "sg:orig_category":"Kappers",
    "sg:phone":"+31 76 587 2683",
    "sg:postcode":"4826 JD",
    "sg:province":"Noord-Brabant",
    "wof:name":"Home Hair Styling",
    "wof:placetype":"venue"
},
  "geometry": {"coordinates":[4.7871780396,51.6089401245],"type":"Point"}
}