{
  "type": "Feature",
  "properties": {
    "addr:full":"Kruisstr 33 Haarlem Noord-Holland 2011 PW",
    "addr:housenumber":"33",
    "addr:postcode":"2011 pw",
    "addr:street":"Kruisstr",
    "iso:country":"NL",
    "sg:address":"Kruisstr 33",
    "sg:city":"Haarlem",
    "sg:orig_category":"Verlichting",
    "sg:phone":"+31 23 531 7232",
    "sg:postcode":"2011 PW",
    "sg:province":"Noord-Holland",
    "sg:website":"http://www.expotrading.nl",
    "wof:name":"Helios",
    "wof:placetype":"venue"
},
  "geometry": {"coordinates":[4.635748,52.383583],"type":"Point"}
}