{
  "type": "Feature",
  "properties": {
    "iso:country":"NL",
    "sg:address":"Bekkerstr 142",
    "sg:city":"Utrecht",
    "sg:orig_category":"Modellenbureaus En Modellen Freelance",
    "sg:phone":"+31 30 272 4087",
    "sg:postcode":"3572 SM",
    "sg:province":"Utrecht",
    "sg:website":"http://www.starsteps.nl",
    "wof:name":"Starsteps",
    "wof:placetype":"venue"
},
  "geometry": {"coordinates":[5.13335,52.099331],"type":"Point"}
}