{
  "type": "Feature",
  "properties": {
    "addr:full":"Heezerweg 213 Eindhoven Noord-Brabant 5643 KA",
    "addr:housenumber":"213",
    "addr:postcode":"5643 ka",
    "addr:street":"Heezerweg",
    "iso:country":"NL",
    "sg:address":"Heezerweg 213",
    "sg:city":"Eindhoven",
    "sg:orig_category":"Verhuur Audiovisuele Apparatuur",
    "sg:phone":"+31 40 211 9575",
    "sg:postcode":"5643 KA",
    "sg:province":"Noord-Brabant",
    "wof:name":"Konig Geluidstechniek",
    "wof:placetype":"venue"
},
  "geometry": {"coordinates":[5.496387,51.424999],"type":"Point"}
}