{
  "type": "Feature",
  "properties": {
    "addr:full":"Wierdensestraat 112 Almelo NL.08 7604 BK",
    "addr:housenumber":"112;nl.08",
    "addr:postcode":"7604 bk",
    "addr:street":"Wierdensestraat",
    "iso:country":"NL",
    "sg:address":"Wierdensestraat 112",
    "sg:city":"Almelo",
    "sg:orig_category":"Diverse Consumentenartikelen Gh",
    "sg:phone":"+31 546 827 333",
    "sg:postcode":"7604 BK",
    "sg:province":"NL.08",
    "wof:name":"Den Aalderink Bv",
    "wof:placetype":"venue"
},
  "geometry": {"coordinates":[6.651994,52.355198],"type":"Point"}
}