{
  "type": "Feature",
  "properties": {
    "iso:country":"NL",
    "sg:address":"Rensgars 3",
    "sg:city":"Schagen",
    "sg:classifiers":[
        {
            "category":"Shopping",
            "subcategory":"News",
            "type":"Retail Goods"
        }
    ],
    "sg:phone":"+31 224 296 565",
    "sg:postcode":"1741 BR",
    "sg:province":"Noord-Holland",
    "sg:tags":[
        "maandbladen",
        "en",
        "week-"
    ],
    "wof:name":"Noordhollands Weekblad",
    "wof:placetype":"venue"
},
  "geometry": {"coordinates":[4.7952570915,52.7862091064],"type":"Point"}
}