{
  "type": "Feature",
  "properties": {
    "addr:full":"Torenstraat 33 Sambeek Noord-Brabant 5836 AJ",
    "addr:housenumber":"33",
    "addr:postcode":"5836 aj",
    "addr:street":"Torenstraat",
    "iso:country":"NL",
    "sg:address":"Torenstraat 33",
    "sg:city":"Sambeek",
    "sg:orig_category":"Begrafenisondernemers",
    "sg:phone":"+31 485 573 941",
    "sg:postcode":"5836 AJ",
    "sg:province":"Noord-Brabant",
    "wof:name":"Begraafplaats Sambeek",
    "wof:placetype":"venue"
},
  "geometry": {"coordinates":[5.962479,51.638302],"type":"Point"}
}