{
  "type": "Feature",
  "properties": {
    "iso:country":"NL",
    "sg:address":"Torenstraat 33",
    "sg:city":"Sambeek",
    "sg:orig_category":"Begrafenisondernemers",
    "sg:phone":"+31 485 573 941",
    "sg:postcode":"5836 AJ",
    "sg:province":"Noord-Brabant",
    "wof:name":"Begraafplaats Sambeek",
    "wof:placetype":"venue"
},
  "geometry": {"coordinates":[5.962479,51.638302],"type":"Point"}
}