{
  "type": "Feature",
  "properties": {
    "iso:country":"NL",
    "sg:address":"Bakboard 38",
    "sg:city":"Joure",
    "sg:orig_category":"Administratie- En Boekhoudkantoren",
    "sg:phone":"+31 513 417 371",
    "sg:postcode":"8502 AM",
    "sg:province":"Friesland",
    "wof:name":"It Fryske Pompebl\u00ead",
    "wof:placetype":"venue"
},
  "geometry": {"coordinates":[5.804841,52.972595],"type":"Point"}
}