{
  "type": "Feature",
  "properties": {
    "addr:full":"Rottestr 6 Rotterdam Zuid-Holland 3032 XK",
    "addr:housenumber":"6",
    "addr:postcode":"3032 xk",
    "addr:street":"Rottestr",
    "iso:country":"NL",
    "sg:address":"Rottestr 6",
    "sg:city":"Rotterdam",
    "sg:orig_category":"Glazenwasserijen",
    "sg:phone":"+31 10 466 3419",
    "sg:postcode":"3032 XK",
    "sg:province":"Zuid-Holland",
    "wof:name":"Junior",
    "wof:placetype":"venue"
},
  "geometry": {"coordinates":[4.483815,51.928707],"type":"Point"}
}