{
  "type": "Feature",
  "properties": {
    "iso:country":"NL",
    "sg:address":"De Gorzen 21",
    "sg:city":"Oudenbosch",
    "sg:orig_category":"Waterkoelers En Drinkwaterinstallaties",
    "sg:phone":"+31 165 322 311",
    "sg:postcode":"4731 TV",
    "sg:province":"North Brabant",
    "wof:name":"Waterco Ned Bv",
    "wof:placetype":"venue"
},
  "geometry": {"coordinates":[4.535161972,51.6148986816],"type":"Point"}
}