{
  "type": "Feature",
  "properties": {
    "addr:full":"Broekhoekwg 38 Losser NL.08 7582 PT",
    "addr:housenumber":"38;nl.08",
    "addr:postcode":"7582 pt",
    "addr:street":"Broekhoekwg",
    "iso:country":"NL",
    "sg:address":"Broekhoekwg 38",
    "sg:city":"Losser",
    "sg:orig_category":"Autoschade- Herstelbedrijven",
    "sg:phone":"+31 53 538 7550",
    "sg:postcode":"7582 PT",
    "sg:province":"NL.08",
    "sg:website":"http://www.hassink-autoschade.nl",
    "wof:name":"Hassink, Autoschadebedrijf Bv",
    "wof:placetype":"venue"
},
  "geometry": {"coordinates":[7.006503,52.251537],"type":"Point"}
}