{
  "type": "Feature",
  "properties": {
    "addr:full":"Horndk 10 Loosdrecht Utrecht 1231 NW",
    "addr:housenumber":"10",
    "addr:postcode":"1231 nw",
    "addr:street":"Horndk",
    "iso:country":"NL",
    "sg:address":"Horndk 10",
    "sg:city":"Loosdrecht",
    "sg:orig_category":"Makelaars En Adviseurs Onroerende Goederen",
    "sg:phone":"+31 35 582 1661",
    "sg:postcode":"1231 NW",
    "sg:province":"Utrecht",
    "wof:name":"Vis Makelaar O Z",
    "wof:placetype":"venue"
},
  "geometry": {"coordinates":[5.068138,52.210529],"type":"Point"}
}