{
  "type": "Feature",
  "properties": {
    "iso:country":"NL",
    "sg:address":"J V Stolbergln 84A",
    "sg:city":"Rotterdam",
    "sg:orig_category":"Onderhoudswerken",
    "sg:phone":"+31 10 422 8471",
    "sg:postcode":"3051 CK",
    "sg:province":"Zuid-Holland",
    "wof:name":"Hillebrand, Onderhoudsbedr",
    "wof:placetype":"venue"
},
  "geometry": {"coordinates":[4.4782,51.945049],"type":"Point"}
}