{
  "type": "Feature",
  "properties": {
    "iso:country":"NL",
    "sg:address":"Hooiersweide 72",
    "sg:city":"Nieuwegein",
    "sg:orig_category":"Verhuur Audiovisuele Apparatuur",
    "sg:phone":"+31 30 604 7884",
    "sg:postcode":"3437 DT",
    "sg:province":"Utrecht",
    "wof:name":"A.J. Dimmendaal Geluidstechniek",
    "wof:placetype":"venue"
},
  "geometry": {"coordinates":[5.072521,52.049026],"type":"Point"}
}