{
  "type": "Feature",
  "properties": {
    "iso:country":"NL",
    "sg:address":"Zeefbaan 18",
    "sg:city":"Winschoten",
    "sg:orig_category":"Gordijnstoffen - Fabrieken En Groothandel",
    "sg:phone":"+31 597 471 200",
    "sg:postcode":"9672 BN",
    "sg:province":"Groningen",
    "wof:name":"Ado Bv",
    "wof:placetype":"venue"
},
  "geometry": {"coordinates":[7.056126,53.152195],"type":"Point"}
}