{
  "type": "Feature",
  "properties": {
    "iso:country":"NL",
    "sg:address":"Engstraat 16",
    "sg:city":"Heusden Gem Heusden",
    "sg:classifiers":[
        {
            "category":"Retail",
            "subcategory":"Photofinishing",
            "type":"Services"
        }
    ],
    "sg:phone":"+31 416 662 515",
    "sg:postcode":"5256 BD",
    "sg:province":"North Brabant",
    "sg:tags":[
        "foto",
        "film"
    ],
    "wof:name":"Grafiek Galerie Gille",
    "wof:placetype":"venue"
},
  "geometry": {"coordinates":[5.137598,51.734024],"type":"Point"}
}