{
  "type": "Feature",
  "properties": {
    "addr:full":"Linde 33 Naaldwyk Zuid-Holland 2671 PJ",
    "addr:housenumber":"33",
    "addr:postcode":"2671 pj",
    "addr:street":"Linde",
    "iso:country":"NL",
    "sg:address":"Linde 33",
    "sg:city":"Naaldwyk",
    "sg:orig_category":"Administratie- En Boekhoudkantoren",
    "sg:phone":"+31 174 624 713",
    "sg:postcode":"2671 PJ",
    "sg:province":"Zuid-Holland",
    "wof:name":"Glas, Ed",
    "wof:placetype":"venue"
},
  "geometry": {"coordinates":[4.198786,51.992176],"type":"Point"}
}