{
  "type": "Feature",
  "properties": {
    "addr:full":"Kerkstr 19 Someren North Brabant 5711 GT",
    "addr:housenumber":"19",
    "addr:postcode":"5711 gt",
    "addr:street":"Kerkstr",
    "iso:country":"NL",
    "sg:address":"Kerkstr 19",
    "sg:city":"Someren",
    "sg:orig_category":"Orthopedisch Schoeisel",
    "sg:phone":"+31 493 491 418",
    "sg:postcode":"5711 GT",
    "sg:province":"North Brabant",
    "wof:name":"Kanters-Vinken",
    "wof:placetype":"venue"
},
  "geometry": {"coordinates":[5.7112717628,51.3846511841],"type":"Point"}
}