{
  "type": "Feature",
  "properties": {
    "addr:full":"Kerkstr 14 Wolvega Friesland 8471 CD",
    "addr:housenumber":"14",
    "addr:postcode":"8471 cd",
    "addr:street":"Kerkstr",
    "iso:country":"NL",
    "sg:address":"Kerkstr 14",
    "sg:city":"Wolvega",
    "sg:orig_category":"Postkantoren",
    "sg:phone":"+31 561 613 470",
    "sg:postcode":"8471 CD",
    "sg:province":"Friesland",
    "sg:website":"http://www.postkantoor.nl",
    "wof:name":"Postkantoor",
    "wof:placetype":"venue"
},
  "geometry": {"coordinates":[5.997687,52.876209],"type":"Point"}
}