{
  "type": "Feature",
  "properties": {
    "addr:full":"Kleine Wittenburgerstr 2 Amsterdam Noord-Holland 1018 LV",
    "addr:housenumber":"2",
    "addr:postcode":"1018",
    "iso:country":"NL",
    "sg:address":"Kleine Wittenburgerstr 2",
    "sg:city":"Amsterdam",
    "sg:orig_category":"Fotostudio'S And Fotografen",
    "sg:phone":"+31 20 626 3949",
    "sg:postcode":"1018 LV",
    "sg:province":"Noord-Holland",
    "wof:name":"Henry",
    "wof:placetype":"venue"
},
  "geometry": {"coordinates":[4.919506,52.369728],"type":"Point"}
}