{
  "type": "Feature",
  "properties": {
    "addr:full":"Vriezerweg 14B Tynaarlo Drenthe 9482 TB",
    "addr:housenumber":"14b",
    "addr:postcode":"9482 tb",
    "addr:street":"Vriezerweg",
    "iso:country":"NL",
    "sg:address":"Vriezerweg 14B",
    "sg:city":"Tynaarlo",
    "sg:orig_category":"Verzekeringen - Verzekeringskantoren",
    "sg:phone":"+31 592 333 633",
    "sg:postcode":"9482 TB",
    "sg:province":"Drenthe",
    "sg:website":"http://www.numan-hof.nl",
    "wof:name":"Numan-Hof Assuranti\u00ebn",
    "wof:placetype":"venue"
},
  "geometry": {"coordinates":[6.597136,53.080116],"type":"Point"}
}