{
  "type": "Feature",
  "properties": {
    "addr:full":"Voorstr 43 Leiden Zuid-Holland 2315 JE",
    "addr:housenumber":"43",
    "addr:postcode":"2315 je",
    "addr:street":"Voorstr",
    "iso:country":"NL",
    "sg:address":"Voorstr 43",
    "sg:city":"Leiden",
    "sg:orig_category":"Bloemen En Planten - Groothandel",
    "sg:phone":"+31 71 522 2450",
    "sg:postcode":"2315 JE",
    "sg:province":"Zuid-Holland",
    "wof:name":"Noordermeer, N & R",
    "wof:placetype":"venue"
},
  "geometry": {"coordinates":[4.51286,52.162422],"type":"Point"}
}