{
  "type": "Feature",
  "properties": {
    "addr:full":"Kr Zandwg 80 Dordrecht South Holland 3319 LC",
    "addr:housenumber":"80",
    "addr:postcode":"3319 lc",
    "addr:street":"Zandwg",
    "iso:country":"NL",
    "sg:address":"Kr Zandwg 80",
    "sg:city":"Dordrecht",
    "sg:orig_category":"Hoogwerkers",
    "sg:phone":"+31 78 622 7710",
    "sg:postcode":"3319 LC",
    "sg:province":"South Holland",
    "wof:name":"Prisma Hoogwerksystemen",
    "wof:placetype":"venue"
},
  "geometry": {"coordinates":[4.7097,51.795559],"type":"Point"}
}