{
  "type": "Feature",
  "properties": {
    "addr:full":"Pr Beatrixwg 8 Grou Provincie Friesland 9001 JM",
    "addr:housenumber":"8",
    "addr:postcode":"9001 jm",
    "addr:street":"Grou Provincie Friesland",
    "iso:country":"NL",
    "sg:address":"Pr Beatrixwg 8",
    "sg:city":"Grou",
    "sg:orig_category":"Verenigingen En Stichtingen",
    "sg:phone":"+31 566 621 992",
    "sg:postcode":"9001 JM",
    "sg:province":"Provincie Friesland",
    "wof:name":"Friesland Vaart",
    "wof:placetype":"venue"
},
  "geometry": {"coordinates":[5.843953,53.091476],"type":"Point"}
}