{
  "type": "Feature",
  "properties": {
    "addr:full":"Vossenhof 5 Hooge Mierde North Brabant 5095 BS",
    "addr:housenumber":"5",
    "addr:postcode":"5095 bs",
    "addr:street":"Vossenhof",
    "iso:country":"NL",
    "sg:address":"Vossenhof 5",
    "sg:city":"Hooge Mierde",
    "sg:orig_category":"Loodgieterswerk, Verwarming And Sanitaire Installaties",
    "sg:phone":"+31 13 509 2682",
    "sg:postcode":"5095 BS",
    "sg:province":"North Brabant",
    "wof:name":"Allround",
    "wof:placetype":"venue"
},
  "geometry": {"coordinates":[5.133019,51.390804],"type":"Point"}
}