{
  "type": "Feature",
  "properties": {
    "addr:full":"De Jokse 414-416 Leeuwarden Friesland 8918 HJ",
    "addr:postcode":"414-416;8918 hj",
    "addr:street":"De Jokse",
    "iso:country":"NL",
    "sg:address":"De Jokse 414-416",
    "sg:city":"Leeuwarden",
    "sg:orig_category":"Verenigingen En Stichtingen",
    "sg:phone":"+31 58 267 1144",
    "sg:postcode":"8918 HJ",
    "sg:province":"Friesland",
    "wof:name":"Huurdersver Bilgaard",
    "wof:placetype":"venue"
},
  "geometry": {"coordinates":[5.795433,53.216923],"type":"Point"}
}