{
  "type": "Feature",
  "properties": {
    "addr:full":"Westsngl 54 Venray Limburg 5801 TX",
    "addr:housenumber":"54",
    "addr:postcode":"5801 tx",
    "addr:street":"Westsngl",
    "iso:country":"NL",
    "sg:address":"Westsngl 54",
    "sg:city":"Venray",
    "sg:orig_category":"Keukens",
    "sg:phone":"+31 478 582 851",
    "sg:postcode":"5801 TX",
    "sg:province":"Limburg",
    "wof:name":"Franssen",
    "wof:placetype":"venue"
},
  "geometry": {"coordinates":[5.977073,51.527157],"type":"Point"}
}