{
  "type": "Feature",
  "properties": {
    "addr:full":"Boelewerf 25 Ridderkerk Zuid-Holland 2987 VD",
    "addr:housenumber":"25",
    "addr:postcode":"2987 vd",
    "addr:street":"Boelewerf",
    "iso:country":"NL",
    "sg:address":"Boelewerf 25",
    "sg:city":"Ridderkerk",
    "sg:classifiers":[
        {
            "category":"Wholesale",
            "subcategory":"Meat",
            "type":"Manufacturing & Wholesale Goods"
        }
    ],
    "sg:phone":"+31 180 481 381",
    "sg:postcode":"2987 VD",
    "sg:province":"Zuid-Holland",
    "sg:tags":[
        "regeltechniek",
        "en",
        "meet-"
    ],
    "wof:name":"Ermaf",
    "wof:placetype":"venue"
},
  "geometry": {"coordinates":[4.580538,51.900497],"type":"Point"}
}