{
  "type": "Feature",
  "properties": {
    "addr:full":"Beatrixln 8 Doorn Utrecht 3941 EE",
    "addr:housenumber":"8",
    "addr:postcode":"3941 ee",
    "addr:street":"Beatrixln",
    "iso:country":"NL",
    "sg:address":"Beatrixln 8",
    "sg:city":"Doorn",
    "sg:orig_category":"Adviesbureaus Bedrijfsorganisatie",
    "sg:phone":"+31 343 420 924",
    "sg:postcode":"3941 EE",
    "sg:province":"Utrecht",
    "wof:name":"Karstens Bv",
    "wof:placetype":"venue"
},
  "geometry": {"coordinates":[5.345447,52.044834],"type":"Point"}
}