{
  "type": "Feature",
  "properties": {
    "addr:full":"Roelantstr 10 Amsterdam North Holland 1055 LP",
    "addr:housenumber":"10",
    "addr:postcode":"1055 lp",
    "addr:street":"Roelantstr",
    "iso:country":"NL",
    "sg:address":"Roelantstr 10",
    "sg:city":"Amsterdam",
    "sg:orig_category":"Wassalons",
    "sg:phone":"+31 20 684 9294",
    "sg:postcode":"1055 LP",
    "sg:province":"North Holland",
    "wof:name":"Erasmus",
    "wof:placetype":"venue"
},
  "geometry": {"coordinates":[4.8570542336,52.3771591187],"type":"Point"}
}