{
  "type": "Feature",
  "properties": {
    "iso:country":"NL",
    "sg:address":"Roelantstr 10",
    "sg:city":"Amsterdam",
    "sg:orig_category":"Wassalons",
    "sg:phone":"+31 20 684 9294",
    "sg:postcode":"1055 LP",
    "sg:province":"North Holland",
    "wof:name":"Erasmus",
    "wof:placetype":"venue"
},
  "geometry": {"coordinates":[4.8570542336,52.3771591187],"type":"Point"}
}