{
  "type": "Feature",
  "properties": {
    "iso:country":"NL",
    "sg:address":"Sperwerhof 31",
    "sg:city":"Schagen",
    "sg:orig_category":"Technische Studies And Onderzoek",
    "sg:phone":"+31 224 218 651",
    "sg:postcode":"1742 EB",
    "sg:province":"North Holland",
    "wof:name":"Koster Elektronika",
    "wof:placetype":"venue"
},
  "geometry": {"coordinates":[4.775876,52.785885],"type":"Point"}
}