{
  "type": "Feature",
  "properties": {
    "iso:country":"NL",
    "sg:address":"Scherpdeel 16",
    "sg:city":"Roosendaal",
    "sg:orig_category":"Autokeuringen",
    "sg:phone":"+31 165 557 274",
    "sg:postcode":"4703 HT",
    "sg:province":"Noord-Brabant",
    "wof:name":"P.A. Pruymboom",
    "wof:placetype":"venue"
},
  "geometry": {"coordinates":[4.447034,51.540508],"type":"Point"}
}