{
  "type": "Feature",
  "properties": {
    "addr:full":"Venrayseweg 35 Wanssum Limburg 5861 BC",
    "addr:housenumber":"35",
    "addr:postcode":"5861 bc",
    "addr:street":"Venrayseweg",
    "iso:country":"NL",
    "sg:address":"Venrayseweg 35",
    "sg:city":"Wanssum",
    "sg:orig_category":"Hoefdierhouderijen",
    "sg:phone":"+31 478 531 712",
    "sg:postcode":"5861 BC",
    "sg:province":"Limburg",
    "wof:name":"Paardenhouderij Janssen",
    "wof:placetype":"venue"
},
  "geometry": {"coordinates":[6.064089,51.529884],"type":"Point"}
}