{
  "type": "Feature",
  "properties": {
    "iso:country":"NL",
    "sg:address":"Emmastr 8D",
    "sg:city":"S Gravenhage",
    "sg:orig_category":"Adviesbureaus Financieringen",
    "sg:phone":"+31 70 335 1692",
    "sg:postcode":"2595 EJ",
    "sg:province":"Zuid-Holland",
    "wof:name":"Lavell",
    "wof:placetype":"venue"
},
  "geometry": {"coordinates":[4.33507,52.081421],"type":"Point"}
}