{
  "type": "Feature",
  "properties": {
    "addr:full":"Kl Haasdal 72 Schimmert Limburg 6333 AL",
    "addr:housenumber":"72",
    "addr:postcode":"6333 al",
    "iso:country":"NL",
    "sg:address":"Kl Haasdal 72",
    "sg:city":"Schimmert",
    "sg:orig_category":"Begrafenisverzorging",
    "sg:phone":"+31 6 51515080",
    "sg:postcode":"6333 AL",
    "sg:province":"Limburg",
    "wof:name":"Postema",
    "wof:placetype":"venue"
},
  "geometry": {"coordinates":[5.814405,50.896179],"type":"Point"}
}