{
  "type": "Feature",
  "properties": {
    "addr:full":"Kanaalkade 49 Alkmaar Noord-Holland 1811 LS",
    "addr:housenumber":"49",
    "addr:postcode":"1811 ls",
    "addr:street":"Kanaalkade",
    "iso:country":"NL",
    "sg:address":"Kanaalkade 49",
    "sg:city":"Alkmaar",
    "sg:orig_category":"Fietshandelaren",
    "sg:phone":"+31 900 7002874",
    "sg:postcode":"1811 LS",
    "sg:province":"Noord-Holland",
    "wof:name":"Scooter House",
    "wof:placetype":"venue"
},
  "geometry": {"coordinates":[4.746258,52.634361],"type":"Point"}
}