{
  "type": "Feature",
  "properties": {
    "addr:full":"Kranenpool 2 Brunssum Limburg 6443 VA",
    "addr:housenumber":"2",
    "addr:postcode":"6443",
    "addr:street":"Kranenpool",
    "iso:country":"NL",
    "sg:address":"Kranenpool 2",
    "sg:city":"Brunssum",
    "sg:orig_category":"Kunststoffen- Verwerkende Industrie",
    "sg:phone":"+31 45 525 0611",
    "sg:postcode":"6443 VA",
    "sg:province":"Limburg",
    "sg:website":"http://www.decostone.nl",
    "wof:name":"Decostone Eur Bv",
    "wof:placetype":"venue"
},
  "geometry": {"coordinates":[5.998972,50.944199],"type":"Point"}
}