{
  "type": "Feature",
  "properties": {
    "addr:full":"Zevenkampse Ring 285 Rotterdam South Holland 3068 PZ",
    "addr:housenumber":"285",
    "addr:postcode":"3068 pz",
    "addr:street":"Zevenkampse Ring",
    "iso:country":"NL",
    "sg:address":"Zevenkampse Ring 285",
    "sg:city":"Rotterdam",
    "sg:orig_category":"Webdesign Bureaus",
    "sg:phone":"+31 6 55725485",
    "sg:postcode":"3068 PZ",
    "sg:province":"South Holland",
    "sg:website":"http://www.netserv.nl",
    "wof:name":"Netserv",
    "wof:placetype":"venue"
},
  "geometry": {"coordinates":[4.5738921165,51.96509552],"type":"Point"}
}