{
  "type": "Feature",
  "properties": {
    "iso:country":"NL",
    "sg:address":"Lievershil 1",
    "sg:city":"Zwyndrecht",
    "sg:orig_category":"Autorijscholen",
    "sg:phone":"+31 78 619 6063",
    "sg:postcode":"3332 RH",
    "sg:province":"Zuid-Holland",
    "wof:name":"Munck Zwijndrecht Eo, De",
    "wof:placetype":"venue"
},
  "geometry": {"coordinates":[4.643554,51.825726],"type":"Point"}
}