{
  "type": "Feature",
  "properties": {
    "iso:country":"NL",
    "sg:address":"Past Nicolaus D Reimsstr 45",
    "sg:city":"Meerssen",
    "sg:orig_category":"Wegen And Sportterreinen",
    "sg:phone":"+31 43 358 5710",
    "sg:postcode":"6231 HJ",
    "sg:province":"Limburg",
    "wof:name":"Lieben Infra Bv",
    "wof:placetype":"venue"
},
  "geometry": {"coordinates":[5.7500839233,50.8884544373],"type":"Point"}
}