{
  "type": "Feature",
  "properties": {
    "addr:full":"Spuistr 21 S Gravenhage Zuid-Holland 2511 BC",
    "addr:housenumber":"21;gravenhage",
    "addr:postcode":"2511 bc",
    "addr:street":"Spuistr;S",
    "iso:country":"NL",
    "sg:address":"Spuistr 21",
    "sg:city":"S Gravenhage",
    "sg:orig_category":"Boeken Antiquarische En Gebruikte",
    "sg:phone":"+31 70 363 9712",
    "sg:postcode":"2511 BC",
    "sg:province":"Zuid-Holland",
    "sg:website":"http://www.deslegte.nl",
    "wof:name":"Slegte Bv, J De",
    "wof:placetype":"venue"
},
  "geometry": {"coordinates":[4.31627,52.07896],"type":"Point"}
}