{
  "type": "Feature",
  "properties": {
    "addr:full":"Koekoekstr 19 Vierakker Gelderland 7233 PB",
    "addr:housenumber":"19",
    "addr:postcode":"7233 pb",
    "addr:street":"Koekoekstr;Gelderland",
    "iso:country":"NL",
    "sg:address":"Koekoekstr 19",
    "sg:city":"Vierakker",
    "sg:orig_category":"Makelaars En Adviseurs Onroerende Goederen",
    "sg:phone":"+31 575 442 615",
    "sg:postcode":"7233 PB",
    "sg:province":"Gelderland",
    "wof:name":"Wagenvoort Advies Bv",
    "wof:placetype":"venue"
},
  "geometry": {"coordinates":[6.256527,52.106483],"type":"Point"}
}