{
  "type": "Feature",
  "properties": {
    "iso:country":"NL",
    "sg:address":"Ministerln 74",
    "sg:city":"Eindhoven",
    "sg:orig_category":"Adviesbureaus Bedrijfsorganisatie",
    "sg:phone":"+31 40 281 7624",
    "sg:postcode":"5631 ND",
    "sg:province":"Noord-Brabant",
    "wof:name":"Leeuw Bv, De",
    "wof:placetype":"venue"
},
  "geometry": {"coordinates":[5.51151,51.454987],"type":"Point"}
}