{
  "type": "Feature",
  "properties": {
    "addr:full":"Langelaan 46 Surhuisterveen Friesland 9231 EP",
    "addr:housenumber":"46",
    "addr:postcode":"9231 ep",
    "addr:street":"Langelaan",
    "iso:country":"NL",
    "sg:address":"Langelaan 46",
    "sg:city":"Surhuisterveen",
    "sg:orig_category":"Goederenvervoer Over De Weg",
    "sg:phone":"+31 512 362 178",
    "sg:postcode":"9231 EP",
    "sg:province":"Friesland",
    "wof:name":"Bv Transportbedrijf Kloezen De Boer",
    "wof:placetype":"venue"
},
  "geometry": {"coordinates":[6.175131,53.180386],"type":"Point"}
}