{
  "type": "Feature",
  "properties": {
    "addr:full":"Spuistraat 249 Amsterdam North Holland 1012 VP",
    "addr:housenumber":"249",
    "addr:postcode":"1012 vp",
    "addr:street":"Spuistraat",
    "iso:country":"NL",
    "sg:address":"Spuistraat 249",
    "sg:city":"Amsterdam",
    "sg:orig_category":"Vertaal- And Tolkenbureaus",
    "sg:phone":"+31 20 626 5399",
    "sg:postcode":"1012 VP",
    "sg:province":"North Holland",
    "wof:name":"Chinees Tolk & Vertaalbureau D.F.Y.",
    "wof:placetype":"venue"
},
  "geometry": {"coordinates":[4.889365,52.370712],"type":"Point"}
}