{
  "type": "Feature",
  "properties": {
    "addr:full":"Noorderbeekdwstr 125 S Gravenhage Zuid-Holland 2562 XP",
    "addr:housenumber":"125;gravenhage",
    "addr:postcode":"2562 xp",
    "addr:street":"S",
    "iso:country":"NL",
    "sg:address":"Noorderbeekdwstr 125",
    "sg:city":"S Gravenhage",
    "sg:orig_category":"Fotografie Reclame En Mode",
    "sg:phone":"+31 70 394 2483",
    "sg:postcode":"2562 XP",
    "sg:province":"Zuid-Holland",
    "wof:name":"Hamers, A F M",
    "wof:placetype":"venue"
},
  "geometry": {"coordinates":[4.28326,52.075001],"type":"Point"}
}