{
  "type": "Feature",
  "properties": {
    "addr:full":"Spuiweg 5 Waalwijk North Brabant 5145 NE",
    "addr:housenumber":"5",
    "addr:postcode":"5145 ne",
    "addr:street":"Spuiweg",
    "iso:country":"NL",
    "sg:address":"Spuiweg 5",
    "sg:city":"Waalwijk",
    "sg:orig_category":"Gespecialiseerde Bouw",
    "sg:phone":"+31 416 341 362",
    "sg:postcode":"5145 NE",
    "sg:province":"North Brabant",
    "wof:name":"Constructie- En Plaatwerk Eekels Waalwijk Bv",
    "wof:placetype":"venue"
},
  "geometry": {"coordinates":[5.050448,51.696793],"type":"Point"}
}