{
  "type": "Feature",
  "properties": {
    "addr:full":"Dykwg 127 Honselersdyk Zuid-Holland 2675 AC",
    "addr:housenumber":"127",
    "addr:postcode":"2675 ac",
    "addr:street":"Honselersdyk",
    "iso:country":"NL",
    "sg:address":"Dykwg 127",
    "sg:city":"Honselersdyk",
    "sg:orig_category":"Manueel Therapeuten",
    "sg:phone":"+31 174 640 024",
    "sg:postcode":"2675 AC",
    "sg:province":"Zuid-Holland",
    "wof:name":"Idsinga, C J Van",
    "wof:placetype":"venue"
},
  "geometry": {"coordinates":[4.22951,52.008755],"type":"Point"}
}