{
  "type": "Feature",
  "properties": {
    "addr:full":"Durgerdammerdk 3 Amsterdam Noord-Holland 1026 BX",
    "addr:housenumber":"3",
    "addr:postcode":"1026 bx",
    "addr:street":"Durgerdammerdk",
    "iso:country":"NL",
    "sg:address":"Durgerdammerdk 3",
    "sg:city":"Amsterdam",
    "sg:orig_category":"Watersportartikelen",
    "sg:phone":"+31 20 491 0225",
    "sg:postcode":"1026 BX",
    "sg:province":"Noord-Holland",
    "wof:name":"Hoek Van 'T Ij",
    "wof:placetype":"venue"
},
  "geometry": {"coordinates":[4.9770560265,52.3773880005],"type":"Point"}
}