{
  "type": "Feature",
  "properties": {
    "iso:country":"NL",
    "sg:address":"Zutphenseweg 33",
    "sg:city":"Deventer",
    "sg:orig_category":"Chemische Producten Gh",
    "sg:phone":"+31 570 635 060",
    "sg:postcode":"7418 AH",
    "sg:province":"NL.08",
    "wof:name":"Linear Products Inc",
    "wof:placetype":"venue"
},
  "geometry": {"coordinates":[6.1681,52.244541],"type":"Point"}
}