{
  "type": "Feature",
  "properties": {
    "addr:full":"Venewg 5 Rutten NL. 8313 PH",
    "addr:housenumber":"5",
    "addr:postcode":"8313",
    "addr:street":"Venewg;Nl.",
    "iso:country":"NL",
    "sg:address":"Venewg 5",
    "sg:city":"Rutten",
    "sg:orig_category":"Loonbedrijven",
    "sg:phone":"+31 527 262 493",
    "sg:postcode":"8313 PH",
    "sg:province":"NL.",
    "wof:name":"Veen, Ter",
    "wof:placetype":"venue"
},
  "geometry": {"coordinates":[5.726322,52.794765],"type":"Point"}
}