{
  "type": "Feature",
  "properties": {
    "addr:full":"Rustoordlaan 2 Eefde Gelderland 7211 AX",
    "addr:housenumber":"2",
    "addr:postcode":"7211 ax",
    "addr:street":"Rustoordlaan;Gelderland",
    "iso:country":"NL",
    "sg:address":"Rustoordlaan 2",
    "sg:city":"Eefde",
    "sg:orig_category":"Kappers",
    "sg:phone":"+31 575 519 513",
    "sg:postcode":"7211 AX",
    "sg:province":"Gelderland",
    "wof:name":"Flair Haarmode",
    "wof:placetype":"venue"
},
  "geometry": {"coordinates":[6.2284808159,52.1628379822],"type":"Point"}
}