{
  "type": "Feature",
  "properties": {
    "iso:country":"NL",
    "sg:address":"Oosterwerf 50",
    "sg:city":"Gouda",
    "sg:orig_category":"Journalisten Freelance",
    "sg:phone":"+31 182 539 939",
    "sg:postcode":"2804 LZ",
    "sg:province":"South Holland",
    "wof:name":"Parole",
    "wof:placetype":"venue"
},
  "geometry": {"coordinates":[4.715586,52.037331],"type":"Point"}
}