{
  "type": "Feature",
  "properties": {
    "addr:full":"Palacepln 68 S Gravenhage South Holland 2587 WG",
    "addr:housenumber":"68",
    "addr:postcode":"2587 wg",
    "addr:street":"Palacepln;S Gravenhage",
    "iso:country":"NL",
    "sg:address":"Palacepln 68",
    "sg:city":"S Gravenhage",
    "sg:orig_category":"Bedrijfsopleidingen",
    "sg:phone":"+31 70 325 6865",
    "sg:postcode":"2587 WG",
    "sg:province":"South Holland",
    "sg:website":"http://www.pre-act.nl",
    "wof:name":"Pre Act",
    "wof:placetype":"venue"
},
  "geometry": {"coordinates":[4.2911801338,52.1129417419],"type":"Point"}
}