{
  "type": "Feature",
  "properties": {
    "addr:full":"Edelhertwg 73 Almere Flevoland 1338 KB",
    "addr:housenumber":"73",
    "addr:postcode":"1338 kb",
    "addr:street":"Edelhertwg;Flevoland",
    "iso:country":"NL",
    "sg:address":"Edelhertwg 73",
    "sg:city":"Almere",
    "sg:orig_category":"Autorijscholen",
    "sg:phone":"+31 36 532 6125",
    "sg:postcode":"1338 KB",
    "sg:province":"Flevoland",
    "wof:name":"Kemme",
    "wof:placetype":"venue"
},
  "geometry": {"coordinates":[5.27463,52.384933],"type":"Point"}
}