{
  "type": "Feature",
  "properties": {
    "addr:full":"Gamersedijk 8 Zaltbommel Gelderland 5301 HT",
    "addr:housenumber":"8",
    "addr:postcode":"5301 ht",
    "addr:street":"Gamersedijk;Gelderland",
    "iso:country":"NL",
    "sg:address":"Gamersedijk 8",
    "sg:city":"Zaltbommel",
    "sg:orig_category":"Reclamebureaus",
    "sg:phone":"+31 418 680 404",
    "sg:postcode":"5301 HT",
    "sg:province":"Gelderland",
    "wof:name":"Van Oss Reclame",
    "wof:placetype":"venue"
},
  "geometry": {"coordinates":[5.240701,51.811451],"type":"Point"}
}