{
  "type": "Feature",
  "properties": {
    "iso:country":"NL",
    "sg:address":"Friezenwg 20",
    "sg:city":"Oss",
    "sg:orig_category":"Horecabenodigdheden",
    "sg:phone":"+31 412 628 082",
    "sg:postcode":"5349 AW",
    "sg:province":"Noord-Brabant",
    "wof:name":"Foodservice Oss",
    "wof:placetype":"venue"
},
  "geometry": {"coordinates":[5.561279,51.762806],"type":"Point"}
}