{
  "type": "Feature",
  "properties": {
    "iso:country":"NL",
    "sg:address":"Duyvesteynstr 9A",
    "sg:city":"Rotterdam",
    "sg:classifiers":[
        {
            "category":"Food & Beverages",
            "subcategory":"Bakery",
            "type":"Retail Goods"
        }
    ],
    "sg:phone":"+31 10 415 2434",
    "sg:postcode":"3042 BA",
    "sg:province":"South Holland",
    "sg:tags":[
        "brood",
        "en",
        "banket"
    ],
    "wof:name":"Breggen, Van Der",
    "wof:placetype":"venue"
},
  "geometry": {"coordinates":[4.428298,51.933243],"type":"Point"}
}