{
  "type": "Feature",
  "properties": {
    "addr:full":"Erepryshof 14 Houten Utrecht 3991 GV",
    "addr:housenumber":"14",
    "addr:postcode":"3991 gv",
    "addr:street":"Erepryshof",
    "iso:country":"NL",
    "sg:address":"Erepryshof 14",
    "sg:city":"Houten",
    "sg:orig_category":"Webdesign Bureaus",
    "sg:phone":"+31 30 638 1521",
    "sg:postcode":"3991 GV",
    "sg:province":"Utrecht",
    "sg:website":"http://www.wbwebdesign.com",
    "wof:name":"We(B)Design",
    "wof:placetype":"venue"
},
  "geometry": {"coordinates":[5.1652607918,52.0323562622],"type":"Point"}
}