{
  "type": "Feature",
  "properties": {
    "addr:full":"Singel 508 Amsterdam Noord-Holland 1017 AX",
    "addr:housenumber":"508",
    "addr:postcode":"1017 ax",
    "addr:street":"Singel",
    "iso:country":"NL",
    "sg:address":"Singel 508",
    "sg:city":"Amsterdam",
    "sg:orig_category":"Bloemen En Planten",
    "sg:phone":"+31 20 625 8282",
    "sg:postcode":"1017 AX",
    "sg:province":"Noord-Holland",
    "wof:name":"Bevaart, Kees",
    "wof:placetype":"venue"
},
  "geometry": {"coordinates":[4.89078,52.366932],"type":"Point"}
}