{
  "type": "Feature",
  "properties": {
    "addr:full":"Huijgenlaan 31 Bunschoten Spakenburg Utrecht 3752 CC",
    "addr:housenumber":"31",
    "addr:postcode":"3752 cc",
    "addr:street":"Huijgenlaan",
    "iso:country":"NL",
    "sg:address":"Huijgenlaan 31",
    "sg:city":"Bunschoten Spakenburg",
    "sg:orig_category":"Werving And Selectie Van Tijdelijk Personeel And Uitzendkantoren",
    "sg:phone":"+31 33 298 5181",
    "sg:postcode":"3752 CC",
    "sg:province":"Utrecht",
    "wof:name":"Adecco",
    "wof:placetype":"venue"
},
  "geometry": {"coordinates":[5.3739719391,52.2487373352],"type":"Point"}
}