{
  "type": "Feature",
  "properties": {
    "addr:full":"Paulus Buyslaan 23 Amersfoort Utrecht 3818 LC",
    "addr:housenumber":"23",
    "addr:postcode":"3818 lc",
    "addr:street":"Paulus Buyslaan",
    "iso:country":"NL",
    "sg:address":"Paulus Buyslaan 23",
    "sg:city":"Amersfoort",
    "sg:classifiers":[
        {
            "category":"Professional",
            "subcategory":"Accounting & Tax Preparation",
            "type":"Services"
        }
    ],
    "sg:phone":"+31 33 464 3030",
    "sg:postcode":"3818 LC",
    "sg:province":"Utrecht",
    "sg:tags":[
        "accountant"
    ],
    "wof:name":"Accountantskantoor Tummers Amersfoort Bv",
    "wof:placetype":"venue"
},
  "geometry": {"coordinates":[5.377381,52.151333],"type":"Point"}
}