{
  "type": "Feature",
  "properties": {
    "addr:full":"Hagedisberg 23 Roosendaal North Brabant 4708 HM",
    "addr:housenumber":"23",
    "addr:postcode":"4708 hm",
    "addr:street":"Hagedisberg",
    "iso:country":"NL",
    "sg:address":"Hagedisberg 23",
    "sg:city":"Roosendaal",
    "sg:orig_category":"Kappers",
    "sg:phone":"+31 165 564 472",
    "sg:postcode":"4708 HM",
    "sg:province":"North Brabant",
    "wof:name":"Ingrid",
    "wof:placetype":"venue"
},
  "geometry": {"coordinates":[4.4338507652,51.5150260925],"type":"Point"}
}