{
  "type": "Feature",
  "properties": {
    "iso:country":"NL",
    "sg:address":"Molenweg 34",
    "sg:city":"Scherpenzeel Gld",
    "sg:orig_category":"Organisaties And Verenigingen",
    "sg:phone":"+31 33 277 4413",
    "sg:postcode":"3925 CJ",
    "sg:province":"Gelderland",
    "wof:name":"Rijwielhulpmotorenclub Op Z'N Elf En Dertigst",
    "wof:placetype":"venue"
},
  "geometry": {"coordinates":[5.4860959053,52.0781211853],"type":"Point"}
}