{
  "type": "Feature",
  "properties": {
    "iso:country":"NL",
    "sg:address":"J C Mayln 6",
    "sg:city":"Utrecht",
    "sg:orig_category":"Mensendieck - Oefentherapeuten",
    "sg:phone":"+31 30 288 7806",
    "sg:postcode":"3526 GV",
    "sg:province":"Utrecht",
    "wof:name":"Swarte, J M",
    "wof:placetype":"venue"
},
  "geometry": {"coordinates":[5.09982,52.063389],"type":"Point"}
}