{
  "type": "Feature",
  "properties": {
    "iso:country":"NL",
    "sg:address":"V Hallstr 85",
    "sg:city":"Amsterdam",
    "sg:orig_category":"Kappers",
    "sg:phone":"+31 20 684 6871",
    "sg:postcode":"1051 HA",
    "sg:province":"Noord-Holland",
    "wof:name":"Florin",
    "wof:placetype":"venue"
},
  "geometry": {"coordinates":[4.8710699081,52.3792495728],"type":"Point"}
}