{
  "type": "Feature",
  "properties": {
    "addr:full":"Bedrijvenweg 48 Nijverdal Overijssel 7442 CW",
    "addr:housenumber":"48",
    "addr:postcode":"7442 cw",
    "addr:street":"Bedrijvenweg",
    "iso:country":"NL",
    "sg:address":"Bedrijvenweg 48",
    "sg:city":"Nijverdal",
    "sg:orig_category":"Autokeuringen",
    "sg:phone":"+31 548 610 075",
    "sg:postcode":"7442 CW",
    "sg:province":"Overijssel",
    "wof:name":"Wema Autoschade Bv",
    "wof:placetype":"venue"
},
  "geometry": {"coordinates":[6.494864,52.356037],"type":"Point"}
}