{
  "type": "Feature",
  "properties": {
    "iso:country":"NL",
    "sg:address":"Heuvelstraat 105",
    "sg:city":"Tilburg",
    "sg:orig_category":"Boekhandels",
    "sg:phone":"+31 13 535 4943",
    "sg:postcode":"5038 AD",
    "sg:province":"North Brabant",
    "wof:name":"Scholman Boekenhal",
    "wof:placetype":"venue"
},
  "geometry": {"coordinates":[5.084396,51.555485],"type":"Point"}
}