{
  "type": "Feature",
  "properties": {
    "addr:full":"Stadsmatenstr 1 Enschede NL.08 7513 AA",
    "addr:housenumber":"1",
    "addr:postcode":"7513 aa",
    "addr:street":"Stadsmatenstr",
    "iso:country":"NL",
    "sg:address":"Stadsmatenstr 1",
    "sg:city":"Enschede",
    "sg:orig_category":"Fotoreportages",
    "sg:phone":"+31 6 20684350",
    "sg:postcode":"7513 AA",
    "sg:province":"NL.08",
    "wof:name":"Noorderlicht, Fotografie",
    "wof:placetype":"venue"
},
  "geometry": {"coordinates":[6.881867,52.220322],"type":"Point"}
}