{
  "type": "Feature",
  "properties": {
    "addr:full":"Hofplein 32 Rotterdam Zuid-Holland 3011 AJ",
    "addr:housenumber":"32",
    "addr:postcode":"3011 aj",
    "addr:street":"Hofplein",
    "iso:country":"NL",
    "sg:address":"Hofplein 32",
    "sg:city":"Rotterdam",
    "sg:orig_category":"Werving And Selectie Van Tijdelijk Personeel And Uitzendkantoren",
    "sg:phone":"+31 10 411 0209",
    "sg:postcode":"3011 AJ",
    "sg:province":"Zuid-Holland",
    "wof:name":"Adecco",
    "wof:placetype":"venue"
},
  "geometry": {"coordinates":[4.4784412384,51.9242935181],"type":"Point"}
}