{
  "type": "Feature",
  "properties": {
    "iso:country":"NL",
    "sg:address":"Aardappelakker 26",
    "sg:city":"Zoetermeer",
    "sg:orig_category":"Huizensloop And Bouwrijp Maken",
    "sg:phone":"+31 79 331 2531",
    "sg:postcode":"2723 XG",
    "sg:province":"Zuid-Holland",
    "wof:name":"A.P. Bazuin",
    "wof:placetype":"venue"
},
  "geometry": {"coordinates":[4.516468,52.063274],"type":"Point"}
}