{
  "type": "Feature",
  "properties": {
    "addr:full":"Kennedyln 20 Goirle Noord-Brabant 5051 XG",
    "addr:housenumber":"20",
    "addr:postcode":"5051 xg",
    "addr:street":"Kennedyln",
    "iso:country":"NL",
    "sg:address":"Kennedyln 20",
    "sg:city":"Goirle",
    "sg:orig_category":"Adviesbureaus",
    "sg:phone":"+31 13 534 2531",
    "sg:postcode":"5051 XG",
    "sg:province":"Noord-Brabant",
    "wof:name":"E-Kwadraat",
    "wof:placetype":"venue"
},
  "geometry": {"coordinates":[5.067888,51.518623],"type":"Point"}
}