{
  "type": "Feature",
  "properties": {
    "iso:country":"NL",
    "sg:address":"Aarlesewg 8",
    "sg:city":"Lieshout",
    "sg:orig_category":"Machineonderhoud En -Reparatie",
    "sg:phone":"+31 492 383 458",
    "sg:postcode":"5737 RE",
    "sg:province":"Noord-Brabant",
    "wof:name":"Vesters",
    "wof:placetype":"venue"
},
  "geometry": {"coordinates":[5.610857,51.512665],"type":"Point"}
}