{
  "type": "Feature",
  "properties": {
    "iso:country":"NL",
    "sg:address":"D Goedkoopstr 13A",
    "sg:city":"Amsterdam",
    "sg:orig_category":"Banden",
    "sg:phone":"+31 20 462 0080",
    "sg:postcode":"1096 BD",
    "sg:province":"North Holland",
    "sg:website":"http://www.profile.nl",
    "wof:name":"Profile Tyrecenter 2000",
    "wof:placetype":"venue"
},
  "geometry": {"coordinates":[4.922426,52.335255],"type":"Point"}
}