{
  "type": "Feature",
  "properties": {
    "addr:full":"Wilhelminastr 8 Nuth Limburg 6361 CA",
    "addr:housenumber":"8",
    "addr:postcode":"6361 ca",
    "addr:street":"Wilhelminastr",
    "iso:country":"NL",
    "sg:address":"Wilhelminastr 8",
    "sg:city":"Nuth",
    "sg:orig_category":"Postkantoren",
    "sg:phone":"+31 45 524 1290",
    "sg:postcode":"6361 CA",
    "sg:province":"Limburg",
    "sg:website":"http://www.postkantoor.nl",
    "wof:name":"Postkantoor",
    "wof:placetype":"venue"
},
  "geometry": {"coordinates":[5.885999,50.918785],"type":"Point"}
}