{
  "type": "Feature",
  "properties": {
    "addr:full":"Molengat 1B Urk Flevoland 8321 MG",
    "addr:housenumber":"1b",
    "addr:postcode":"8321 mg",
    "addr:street":"Molengat;Flevoland",
    "iso:country":"NL",
    "sg:address":"Molengat 1B",
    "sg:city":"Urk",
    "sg:orig_category":"Diverse Bedrijfsinstallaties Gh",
    "sg:phone":"+31 527 684 007",
    "sg:postcode":"8321 MG",
    "sg:province":"Flevoland",
    "wof:name":"Nortec Engineering",
    "wof:placetype":"venue"
},
  "geometry": {"coordinates":[5.616922,52.655602],"type":"Point"}
}