{
  "type": "Feature",
  "properties": {
    "addr:full":"Zuidpln Hg 843 Rotterdam Zuid-Holland 3083 BK",
    "addr:housenumber":"843",
    "addr:postcode":"3083 bk",
    "addr:street":"Hg",
    "iso:country":"NL",
    "sg:address":"Zuidpln Hg 843",
    "sg:city":"Rotterdam",
    "sg:orig_category":"Herenkleding",
    "sg:phone":"+31 10 293 9941",
    "sg:postcode":"3083 BK",
    "sg:province":"Zuid-Holland",
    "sg:website":"http://www.wefashion.com",
    "wof:name":"We",
    "wof:placetype":"venue"
},
  "geometry": {"coordinates":[4.490526,51.886951],"type":"Point"}
}