{
  "type": "Feature",
  "properties": {
    "addr:full":"Weth Bankenstr 8 Batenburg Gelderland 6634 KC",
    "addr:housenumber":"8",
    "addr:postcode":"6634 kc",
    "addr:street":"Weth Bankenstr;Gelderland",
    "iso:country":"NL",
    "sg:address":"Weth Bankenstr 8",
    "sg:city":"Batenburg",
    "sg:orig_category":"Pluimveebedrijven En -Handelaren",
    "sg:phone":"+31 487 541 394",
    "sg:postcode":"6634 KC",
    "sg:province":"Gelderland",
    "wof:name":"Haren Vof, Van",
    "wof:placetype":"venue"
},
  "geometry": {"coordinates":[5.618404,51.832535],"type":"Point"}
}