{
  "type": "Feature",
  "properties": {
    "addr:full":"P Loosjesstr 15 Tilburg North Brabant 5013 BW",
    "addr:housenumber":"15",
    "addr:postcode":"5013 bw",
    "addr:street":"P",
    "iso:country":"NL",
    "sg:address":"P Loosjesstr 15",
    "sg:city":"Tilburg",
    "sg:orig_category":"Kappersbenodigdheden",
    "sg:phone":"+31 13 543 4028",
    "sg:postcode":"5013 BW",
    "sg:province":"North Brabant",
    "sg:website":"http://www.haarnet.nl",
    "wof:name":"Knegtel",
    "wof:placetype":"venue"
},
  "geometry": {"coordinates":[5.094015,51.573254],"type":"Point"}
}