{
  "type": "Feature",
  "properties": {
    "addr:full":"Badhuisstraat 17 Arnhem Gelderland 6827 AD",
    "addr:housenumber":"17",
    "addr:postcode":"6827 ad",
    "addr:street":"Badhuisstraat",
    "iso:country":"NL",
    "sg:address":"Badhuisstraat 17",
    "sg:city":"Arnhem",
    "sg:orig_category":"Autokeuringen",
    "sg:phone":"+31 26 443 3330",
    "sg:postcode":"6827 AD",
    "sg:province":"Gelderland",
    "wof:name":"Autolakcentrale All In",
    "wof:placetype":"venue"
},
  "geometry": {"coordinates":[5.915669,51.974216],"type":"Point"}
}