{
  "type": "Feature",
  "properties": {
    "iso:country":"NL",
    "sg:address":"Euterpedreef 16",
    "sg:city":"Utrecht",
    "sg:orig_category":"Kaas",
    "sg:phone":"+31 30 261 0460",
    "sg:postcode":"3561 CV",
    "sg:province":"Utrecht",
    "wof:name":"Kaasspecialist, De",
    "wof:placetype":"venue"
},
  "geometry": {"coordinates":[5.1281261444,52.1158981323],"type":"Point"}
}