{
  "type": "Feature",
  "properties": {
    "addr:full":"Voskuilenwg 59B Heerlen Limburg 6416 AH",
    "addr:housenumber":"59b",
    "addr:postcode":"6416 ah",
    "addr:street":"Voskuilenwg",
    "iso:country":"NL",
    "sg:address":"Voskuilenwg 59B",
    "sg:city":"Heerlen",
    "sg:orig_category":"Kantoor- En Bedrijfsmeubelen - Fabrieken En Groothandel",
    "sg:phone":"+31 45 574 2143",
    "sg:postcode":"6416 AH",
    "sg:province":"Limburg",
    "wof:name":"Profeq Bv",
    "wof:placetype":"venue"
},
  "geometry": {"coordinates":[5.9918441772,50.8889389038],"type":"Point"}
}