{
  "type": "Feature",
  "properties": {
    "addr:full":"Parkweg 2 'S Gravenhage South Holland 2585 JJ",
    "addr:housenumber":"2 '",
    "addr:postcode":"2585 jj",
    "addr:street":"Parkweg",
    "iso:country":"NL",
    "sg:address":"Parkweg 2",
    "sg:city":"'S Gravenhage",
    "sg:orig_category":"Bedrijfs- And Managementsconsultants",
    "sg:phone":"+31 70 358 7123",
    "sg:postcode":"2585 JJ",
    "sg:province":"South Holland",
    "wof:name":"Archipel Management & Trading Bv",
    "wof:placetype":"venue"
},
  "geometry": {"coordinates":[4.286016,52.098289],"type":"Point"}
}