{
  "type": "Feature",
  "properties": {
    "addr:full":"Langelermaatweg 11 Hengelo Ov Overijssel 7553 JD",
    "addr:housenumber":"11",
    "addr:postcode":"7553 jd",
    "addr:street":"Langelermaatweg;Ov",
    "iso:country":"NL",
    "sg:address":"Langelermaatweg 11",
    "sg:city":"Hengelo Ov",
    "sg:orig_category":"Diverse Consumentenartikelen Gh",
    "sg:phone":"+31 74 250 7609",
    "sg:postcode":"7553 JD",
    "sg:province":"Overijssel",
    "wof:name":"Arnic Import/Export",
    "wof:placetype":"venue"
},
  "geometry": {"coordinates":[6.79283,52.26004],"type":"Point"}
}