{
  "type": "Feature",
  "properties": {
    "addr:full":"Kolkwg 35 Lelystad Flevoland 8243 PN",
    "addr:housenumber":"35",
    "addr:postcode":"8243 pn",
    "addr:street":"Kolkwg;Flevoland",
    "iso:country":"NL",
    "sg:address":"Kolkwg 35",
    "sg:city":"Lelystad",
    "sg:orig_category":"Autoreclame",
    "sg:phone":"+31 320 262 727",
    "sg:postcode":"8243 PN",
    "sg:province":"Flevoland",
    "sg:website":"http://www.rofa.nl",
    "wof:name":"Rofe",
    "wof:placetype":"venue"
},
  "geometry": {"coordinates":[5.435064,52.504509],"type":"Point"}
}