{
  "type": "Feature",
  "properties": {
    "addr:full":"St Bavostr 25 Rysbergen Noord-Brabant 4891 CG",
    "addr:housenumber":"25",
    "addr:postcode":"4891 cg",
    "addr:street":"Rysbergen",
    "iso:country":"NL",
    "sg:address":"St Bavostr 25",
    "sg:city":"Rysbergen",
    "sg:classifiers":[
        {
            "category":"Food & Beverages",
            "subcategory":"Bakery",
            "type":"Retail Goods"
        }
    ],
    "sg:phone":"+31 76 596 4690",
    "sg:postcode":"4891 CG",
    "sg:province":"Noord-Brabant",
    "sg:tags":[
        "brood",
        "en",
        "banket"
    ],
    "wof:name":"Raats Gebackerij",
    "wof:placetype":"venue"
},
  "geometry": {"coordinates":[4.700606,51.515694],"type":"Point"}
}