{
  "type": "Feature",
  "properties": {
    "addr:full":"Rijnstraat 18 Amsterdam Noord-Holland 1078 RB",
    "addr:housenumber":"18",
    "addr:postcode":"1078 rb",
    "addr:street":"Rijnstraat",
    "iso:country":"NL",
    "sg:address":"Rijnstraat 18",
    "sg:city":"Amsterdam",
    "sg:orig_category":"Kappers",
    "sg:phone":"+31 20 662 2942",
    "sg:postcode":"1078 RB",
    "sg:province":"Noord-Holland",
    "sg:website":"http://www.dekapper.nl",
    "wof:name":"De Kapper",
    "wof:placetype":"venue"
},
  "geometry": {"coordinates":[4.9043011665,52.348110199],"type":"Point"}
}