{
  "type": "Feature",
  "properties": {
    "addr:full":"Zomerdijk 16 Meppel Drenthe 7942 JT",
    "addr:housenumber":"16",
    "addr:postcode":"7942 jt",
    "addr:street":"Zomerdijk",
    "iso:country":"NL",
    "sg:address":"Zomerdijk 16",
    "sg:city":"Meppel",
    "sg:orig_category":"Bouwmaterialen Gh",
    "sg:phone":"+31 522 240 300",
    "sg:postcode":"7942 JT",
    "sg:province":"Drenthe",
    "wof:name":"Balink Glas Meppel Bv",
    "wof:placetype":"venue"
},
  "geometry": {"coordinates":[6.173471,52.696545],"type":"Point"}
}