{
  "type": "Feature",
  "properties": {
    "addr:full":"V Bodelswingstr 16 Ootmarsum NL.08 7631 JJ",
    "addr:housenumber":"16;nl.08",
    "addr:postcode":"7631 jj",
    "iso:country":"NL",
    "sg:address":"V Bodelswingstr 16",
    "sg:city":"Ootmarsum",
    "sg:classifiers":[
        {
            "category":"Government",
            "subcategory":"Department Of Motor Vehicles",
            "type":"Public Place"
        }
    ],
    "sg:phone":"+31 541 295 200",
    "sg:postcode":"7631 JJ",
    "sg:province":"NL.08",
    "sg:tags":[
        "rijscholen",
        "scooter",
        "en",
        "-"
    ],
    "wof:name":"Martins",
    "wof:placetype":"venue"
},
  "geometry": {"coordinates":[6.89415,52.406929],"type":"Point"}
}