{
  "type": "Feature",
  "properties": {
    "addr:full":"Burgemeester Crezeelaan 42 De Lier Zuid-Holland 2678 KZ",
    "addr:housenumber":"42",
    "addr:postcode":"2678 kz",
    "addr:street":"Burgemeester Crezeelaan",
    "iso:country":"NL",
    "sg:address":"Burgemeester Crezeelaan 42",
    "sg:city":"De Lier",
    "sg:orig_category":"Bloemen And Planten Gh",
    "sg:phone":"+31 174 517 700",
    "sg:postcode":"2678 KZ",
    "sg:province":"Zuid-Holland",
    "wof:name":"Berg Produkt De Lier Bv",
    "wof:placetype":"venue"
},
  "geometry": {"coordinates":[4.259705,51.975201],"type":"Point"}
}