{
  "type": "Feature",
  "properties": {
    "iso:country":"NL",
    "sg:address":"Lakemondsestraat 1",
    "sg:city":"Opheusden",
    "sg:orig_category":"Wegen And Sportterreinen",
    "sg:phone":"+31 488 443 324",
    "sg:postcode":"4043 JC",
    "sg:province":"Gelderland",
    "wof:name":"De Key",
    "wof:placetype":"venue"
},
  "geometry": {"coordinates":[5.6466259956,51.9388084412],"type":"Point"}
}