{
  "type": "Feature",
  "properties": {
    "addr:full":"Helweg 80 Enschede NL.08 7546 PD",
    "addr:housenumber":"80",
    "addr:postcode":"7546 pd",
    "addr:street":"Helweg",
    "iso:country":"NL",
    "sg:address":"Helweg 80",
    "sg:city":"Enschede",
    "sg:orig_category":"Bloemen And Planten",
    "sg:phone":"+31 53 428 1361",
    "sg:postcode":"7546 PD",
    "sg:province":"NL.08",
    "wof:name":"Bloemenboerderij Nijhuis",
    "wof:placetype":"venue"
},
  "geometry": {"coordinates":[6.840429,52.196705],"type":"Point"}
}