{
  "type": "Feature",
  "properties": {
    "addr:full":"Ln V Meerdervoort 590 S Gravenhage Zuid-Holland 2563 BM",
    "addr:housenumber":"590;gravenhage",
    "addr:postcode":"2563 bm",
    "addr:street":"Ln;Meerdervoort;S",
    "iso:country":"NL",
    "sg:address":"Ln V Meerdervoort 590",
    "sg:city":"S Gravenhage",
    "sg:orig_category":"Kappers",
    "sg:phone":"+31 70 361 6215",
    "sg:postcode":"2563 BM",
    "sg:province":"Zuid-Holland",
    "wof:name":"Passion",
    "wof:placetype":"venue"
},
  "geometry": {"coordinates":[4.270956,52.072578],"type":"Point"}
}