{
  "type": "Feature",
  "properties": {
    "addr:full":"St Clemensstr 2 Hulsberg Limburg 6336 BC",
    "addr:housenumber":"2",
    "addr:postcode":"6336 bc",
    "addr:street":"Hulsberg Limburg",
    "iso:country":"NL",
    "sg:address":"St Clemensstr 2",
    "sg:city":"Hulsberg",
    "sg:orig_category":"Kappers",
    "sg:phone":"+31 45 405 2165",
    "sg:postcode":"6336 BC",
    "sg:province":"Limburg",
    "wof:name":"Lizy",
    "wof:placetype":"venue"
},
  "geometry": {"coordinates":[5.85947,50.890724],"type":"Point"}
}