{
  "type": "Feature",
  "properties": {
    "addr:full":"Weezenhof 8127 Nijmegen Gelderland 6536 CR",
    "addr:housenumber":"8127;6536",
    "addr:postcode":"cr",
    "addr:street":"Weezenhof;Gelderland",
    "iso:country":"NL",
    "sg:address":"Weezenhof 8127",
    "sg:city":"Nijmegen",
    "sg:orig_category":"Orthopedagogen",
    "sg:phone":"+31 24 345 0054",
    "sg:postcode":"6536 CR",
    "sg:province":"Gelderland",
    "wof:name":"Assman-Hulsmans, Drs C F C H",
    "wof:placetype":"venue"
},
  "geometry": {"coordinates":[5.8105158806,51.8016738892],"type":"Point"}
}