{
  "type": "Feature",
  "properties": {
    "iso:country":"NL",
    "sg:address":"Bloemstr 14",
    "sg:city":"Leiden",
    "sg:orig_category":"Schilders",
    "sg:phone":"+31 71 522 0814",
    "sg:postcode":"2315 HT",
    "sg:province":"Zuid-Holland",
    "wof:name":"Groeneveld, Schildersbedrijf",
    "wof:placetype":"venue"
},
  "geometry": {"coordinates":[4.509969,52.161999],"type":"Point"}
}