{
  "type": "Feature",
  "properties": {
    "addr:full":"Noorderhaven 8 Harlingen Provincie Friesland 8861 AN",
    "addr:housenumber":"8",
    "addr:postcode":"8861 an",
    "addr:street":"Noorderhaven;Provincie Friesland",
    "iso:country":"NL",
    "sg:address":"Noorderhaven 8",
    "sg:city":"Harlingen",
    "sg:orig_category":"Watersportartikelen",
    "sg:phone":"+31 517 417 190",
    "sg:postcode":"8861 AN",
    "sg:province":"Provincie Friesland",
    "wof:name":"Meer, Scheepswinkel Van",
    "wof:placetype":"venue"
},
  "geometry": {"coordinates":[5.4143228531,53.1753501892],"type":"Point"}
}