{
  "type": "Feature",
  "properties": {
    "addr:full":"Elzenln 27 Zegveld Utrecht 3474 KN",
    "addr:housenumber":"27",
    "addr:postcode":"3474 kn",
    "addr:street":"Elzenln",
    "iso:country":"NL",
    "sg:address":"Elzenln 27",
    "sg:city":"Zegveld",
    "sg:orig_category":"Adviesbureaus Bouwkunde",
    "sg:phone":"+31 348 691 845",
    "sg:postcode":"3474 KN",
    "sg:province":"Utrecht",
    "wof:name":"Nap",
    "wof:placetype":"venue"
},
  "geometry": {"coordinates":[4.831838,52.117168],"type":"Point"}
}