{
  "type": "Feature",
  "properties": {
    "addr:full":"Hoofdstr 91 S Gravenmoer Noord-Brabant 5109 AB",
    "addr:housenumber":"91",
    "addr:postcode":"5109 ab",
    "addr:street":"Hoofdstr;S Gravenmoer",
    "iso:country":"NL",
    "sg:address":"Hoofdstr 91",
    "sg:city":"S Gravenmoer",
    "sg:orig_category":"Koffie- En Theehuizen",
    "sg:phone":"+31 162 313 019",
    "sg:postcode":"5109 AB",
    "sg:province":"Noord-Brabant",
    "wof:name":"Trefpunt, 'T",
    "wof:placetype":"venue"
},
  "geometry": {"coordinates":[4.942179,51.649948],"type":"Point"}
}