{
  "type": "Feature",
  "properties": {
    "iso:country":"NL",
    "sg:address":"Kladde 48",
    "sg:city":"Lepelstraat",
    "sg:orig_category":"Boekhouders",
    "sg:phone":"+31 164 685 653",
    "sg:postcode":"4664 TC",
    "sg:province":"Noord-Brabant",
    "wof:name":"Administratiekantoor Vosmeer",
    "wof:placetype":"venue"
},
  "geometry": {"coordinates":[4.266059,51.563656],"type":"Point"}
}