{
  "type": "Feature",
  "properties": {
    "addr:full":"Hogenkampsweg 39 Zwolle NL.08 8022 DA",
    "addr:housenumber":"39",
    "addr:postcode":"8022 da",
    "addr:street":"Hogenkampsweg",
    "iso:country":"NL",
    "sg:address":"Hogenkampsweg 39",
    "sg:city":"Zwolle",
    "sg:orig_category":"Wasserettes And Stomerijen",
    "sg:phone":"+31 38 453 3435",
    "sg:postcode":"8022 DA",
    "sg:province":"NL.08",
    "wof:name":"Rentex Voorheen Dellen Wuyts",
    "wof:placetype":"venue"
},
  "geometry": {"coordinates":[6.1053037643,52.5213394165],"type":"Point"}
}