{
  "type": "Feature",
  "properties": {
    "addr:full":"Weteringschans 130 Amsterdam Noord-Holland 1017 XV",
    "addr:housenumber":"130",
    "addr:postcode":"1017 xv",
    "addr:street":"Weteringschans",
    "iso:country":"NL",
    "sg:address":"Weteringschans 130",
    "sg:city":"Amsterdam",
    "sg:orig_category":"Meubelzaken, Woning- And Keukeninrichting",
    "sg:phone":"+31 20 422 6127",
    "sg:postcode":"1017 XV",
    "sg:province":"Noord-Holland",
    "wof:name":"Lundia Amsterdam",
    "wof:placetype":"venue"
},
  "geometry": {"coordinates":[4.89678,52.359207],"type":"Point"}
}