{
  "type": "Feature",
  "properties": {
    "iso:country":"NL",
    "sg:address":"Rontgenweg 10",
    "sg:city":"Delft",
    "sg:orig_category":"Overheidsdiensten",
    "sg:phone":"+31 15 256 2216",
    "sg:postcode":"2624 BE",
    "sg:province":"Zuid-Holland",
    "wof:name":"Minervaplein",
    "wof:placetype":"venue"
},
  "geometry": {"coordinates":[4.357049942,51.9999198914],"type":"Point"}
}