{
  "type": "Feature",
  "properties": {
    "addr:full":"Van Den Boschstraat 219 'S Gravenhage Zuid-Holland 2595 AC",
    "addr:housenumber":"219 '",
    "addr:postcode":"2595 ac",
    "addr:street":"Van Den Boschstraat",
    "iso:country":"NL",
    "sg:address":"Van Den Boschstraat 219",
    "sg:city":"'S Gravenhage",
    "sg:orig_category":"Autokeuringen",
    "sg:phone":"+31 70 385 8484",
    "sg:postcode":"2595 AC",
    "sg:province":"Zuid-Holland",
    "wof:name":"Garage De Parel Vof",
    "wof:placetype":"venue"
},
  "geometry": {"coordinates":[4.332585,52.078793],"type":"Point"}
}