{
  "type": "Feature",
  "properties": {
    "addr:full":"Kinkerstraat 368Hs Amsterdam North Holland 1053 GH",
    "addr:housenumber":"368hs",
    "addr:postcode":"1053 gh",
    "addr:street":"Kinkerstraat",
    "iso:country":"NL",
    "sg:address":"Kinkerstraat 368Hs",
    "sg:city":"Amsterdam",
    "sg:orig_category":"Wasserettes And Stomerijen",
    "sg:phone":"+31 20 616 7925",
    "sg:postcode":"1053 GH",
    "sg:province":"North Holland",
    "wof:name":"Chemische Supernette",
    "wof:placetype":"venue"
},
  "geometry": {"coordinates":[4.8613247871,52.3646202087],"type":"Point"}
}