{
  "type": "Feature",
  "properties": {
    "addr:full":"Burgstraat 35 Gorinchem Zuid-Holland 4201 AB",
    "addr:housenumber":"35",
    "addr:postcode":"4201 ab",
    "addr:street":"Burgstraat",
    "iso:country":"NL",
    "sg:address":"Burgstraat 35",
    "sg:city":"Gorinchem",
    "sg:classifiers":[
        {
            "category":"Communications",
            "subcategory":"Television Station",
            "type":"Services"
        }
    ],
    "sg:phone":"+31 183 636 820",
    "sg:postcode":"4201 AB",
    "sg:province":"Zuid-Holland",
    "sg:tags":[
        "video",
        "audio",
        "verhuur"
    ],
    "wof:name":"Filmclub Videotheek",
    "wof:placetype":"venue"
},
  "geometry": {"coordinates":[4.978501,51.829899],"type":"Point"}
}