{
  "type": "Feature",
  "properties": {
    "addr:full":"Bredasewg 70 Chaam Noord-Brabant 4861 TD",
    "addr:housenumber":"70",
    "addr:postcode":"4861 td",
    "addr:street":"Bredasewg",
    "iso:country":"NL",
    "sg:address":"Bredasewg 70",
    "sg:city":"Chaam",
    "sg:orig_category":"Adviesbureaus Bedrijfsorganisatie",
    "sg:phone":"+31 161 493 096",
    "sg:postcode":"4861 TD",
    "sg:province":"Noord-Brabant",
    "wof:name":"Parr\u00e8sia Abc",
    "wof:placetype":"venue"
},
  "geometry": {"coordinates":[4.837693,51.518135],"type":"Point"}
}