{
  "type": "Feature",
  "properties": {
    "addr:full":"Schoolstr 45 Moergestel Noord-Brabant 5066 ED",
    "addr:housenumber":"45",
    "addr:postcode":"5066 ed",
    "addr:street":"Schoolstr",
    "iso:country":"NL",
    "sg:address":"Schoolstr 45",
    "sg:city":"Moergestel",
    "sg:orig_category":"Marktonderzoekbureaus",
    "sg:phone":"+31 13 513 3993",
    "sg:postcode":"5066 ED",
    "sg:province":"Noord-Brabant",
    "wof:name":"Mari\u00ebn Bv, P",
    "wof:placetype":"venue"
},
  "geometry": {"coordinates":[5.18074,51.539921],"type":"Point"}
}