{
  "type": "Feature",
  "properties": {
    "iso:country":"NL",
    "sg:address":"Splitting 36",
    "sg:city":"Emmen",
    "sg:orig_category":"Banken And Kredietinstellingen",
    "sg:phone":"+31 591 680 680",
    "sg:postcode":"7826 CN",
    "sg:province":"Provincie Drenthe",
    "wof:name":"Rabobank",
    "wof:placetype":"venue"
},
  "geometry": {"coordinates":[6.957233,52.772991],"type":"Point"}
}