{
  "type": "Feature",
  "properties": {
    "addr:full":"Terweewg 152 Oegstgeest Zuid-Holland 2341 CX",
    "addr:housenumber":"152",
    "addr:postcode":"2341 cx",
    "iso:country":"NL",
    "sg:address":"Terweewg 152",
    "sg:city":"Oegstgeest",
    "sg:orig_category":"Artsen - Huisartsen",
    "sg:phone":"+31 71 517 3994",
    "sg:postcode":"2341 CX",
    "sg:province":"Zuid-Holland",
    "wof:name":"Overvest, D L P Van",
    "wof:placetype":"venue"
},
  "geometry": {"coordinates":[4.470598,52.182869],"type":"Point"}
}