{
  "type": "Feature",
  "properties": {
    "addr:full":"Staalweg 7 Culemborg Gelderland 4104 AS",
    "addr:housenumber":"7",
    "addr:postcode":"4104 as",
    "addr:street":"Staalweg;Gelderland",
    "iso:country":"NL",
    "sg:address":"Staalweg 7",
    "sg:city":"Culemborg",
    "sg:orig_category":"Meubelreparatie And -Restauratie",
    "sg:phone":"+31 345 512 172",
    "sg:postcode":"4104 AS",
    "sg:province":"Gelderland",
    "wof:name":"Meubelbedrijf Cumery",
    "wof:placetype":"venue"
},
  "geometry": {"coordinates":[5.219403,51.944298],"type":"Point"}
}