{
  "type": "Feature",
  "properties": {
    "addr:full":"Ruurloseweg 14-16 Vorden Gelderland 7251 LK",
    "addr:housenumber":"14-16",
    "addr:postcode":"7251 lk",
    "addr:street":"Ruurloseweg;Gelderland",
    "iso:country":"NL",
    "sg:address":"Ruurloseweg 14-16",
    "sg:city":"Vorden",
    "sg:orig_category":"Binnenhuisarchitecten",
    "sg:phone":"+31 575 553 515",
    "sg:postcode":"7251 LK",
    "sg:province":"Gelderland",
    "wof:name":"G.J. Kip",
    "wof:placetype":"venue"
},
  "geometry": {"coordinates":[6.331858,52.104744],"type":"Point"}
}