{
  "type": "Feature",
  "properties": {
    "addr:full":"Den Hof 6 Bladel Noord-Brabant 5531 XH",
    "addr:housenumber":"6",
    "addr:postcode":"5531 xh",
    "addr:street":"Den Hof",
    "iso:country":"NL",
    "sg:address":"Den Hof 6",
    "sg:city":"Bladel",
    "sg:orig_category":"Plafonds",
    "sg:phone":"+31 497 385 616",
    "sg:postcode":"5531 XH",
    "sg:province":"Noord-Brabant",
    "wof:name":"Reflex Quality Systems",
    "wof:placetype":"venue"
},
  "geometry": {"coordinates":[5.216535,51.377941],"type":"Point"}
}