{
  "type": "Feature",
  "properties": {
    "iso:country":"NL",
    "sg:address":"Kerkln 4-6",
    "sg:city":"Hoogland",
    "sg:orig_category":"Banken",
    "sg:phone":"+31 33 421 8000",
    "sg:postcode":"3828 EB",
    "sg:province":"Utrecht",
    "sg:website":"http://www.rabobank.nl",
    "wof:name":"Rabobank",
    "wof:placetype":"venue"
},
  "geometry": {"coordinates":[5.375933,52.18663],"type":"Point"}
}