{
  "type": "Feature",
  "properties": {
    "iso:country":"NL",
    "sg:address":"Nyverheidswg 9",
    "sg:city":"Giessenburg",
    "sg:orig_category":"Kinderkleding",
    "sg:phone":"+31 184 659 080",
    "sg:postcode":"3381 LM",
    "sg:province":"South Holland",
    "wof:name":"Uma Bv",
    "wof:placetype":"venue"
},
  "geometry": {"coordinates":[4.896706,51.844204],"type":"Point"}
}