{
  "type": "Feature",
  "properties": {
    "addr:full":"Burgemeester Kuperuspln 138 Heerenveen Provincie Friesland 8442 CJ",
    "addr:housenumber":"138",
    "addr:postcode":"8442 cj",
    "addr:street":"Burgemeester Kuperuspln;Provincie Friesland",
    "iso:country":"NL",
    "sg:address":"Burgemeester Kuperuspln 138",
    "sg:city":"Heerenveen",
    "sg:orig_category":"Werving And Selectie Van Tijdelijk Personeel And Uitzendkantoren",
    "sg:phone":"+31 513 610 955",
    "sg:postcode":"8442 CJ",
    "sg:province":"Provincie Friesland",
    "wof:name":"Manpower",
    "wof:placetype":"venue"
},
  "geometry": {"coordinates":[5.92877388,52.9578781128],"type":"Point"}
}