{
  "type": "Feature",
  "properties": {
    "addr:full":"Oude Rijksweg 58 Rilland Zeeland 4411 SG",
    "addr:housenumber":"58",
    "addr:postcode":"4411 sg",
    "addr:street":"Oude Rijksweg",
    "iso:country":"NL",
    "sg:address":"Oude Rijksweg 58",
    "sg:city":"Rilland",
    "sg:orig_category":"Goederenvervoer Over De Weg",
    "sg:phone":"+31 113 552 171",
    "sg:postcode":"4411 SG",
    "sg:province":"Zeeland",
    "wof:name":"De Keijzer Vof",
    "wof:placetype":"venue"
},
  "geometry": {"coordinates":[4.154507,51.424011],"type":"Point"}
}