{
  "type": "Feature",
  "properties": {
    "addr:full":"Raadhuisstraat 7 Gilze Noord-Brabant 5126 CK",
    "addr:housenumber":"7",
    "addr:postcode":"5126 ck",
    "addr:street":"Raadhuisstraat",
    "iso:country":"NL",
    "sg:address":"Raadhuisstraat 7",
    "sg:city":"Gilze",
    "sg:orig_category":"Bedrijfs- And Managementsconsultants",
    "sg:phone":"+31 161 456 240",
    "sg:postcode":"5126 CK",
    "sg:province":"Noord-Brabant",
    "wof:name":"T.T. & B. Bur Transp Training En Bedrijfsadvies",
    "wof:placetype":"venue"
},
  "geometry": {"coordinates":[4.943621,51.541515],"type":"Point"}
}