{
  "type": "Feature",
  "properties": {
    "addr:full":"Predikherenstr 18 Utrecht Utrecht 3512 TN",
    "addr:housenumber":"18",
    "addr:postcode":"3512",
    "addr:street":"Predikherenstr",
    "iso:country":"NL",
    "sg:address":"Predikherenstr 18",
    "sg:city":"Utrecht",
    "sg:orig_category":"Galeries",
    "sg:phone":"+31 30 231 0399",
    "sg:postcode":"3512 TN",
    "sg:province":"Utrecht",
    "wof:name":"Pandje, 'T",
    "wof:placetype":"venue"
},
  "geometry": {"coordinates":[5.118392,52.094387],"type":"Point"}
}