{
  "type": "Feature",
  "properties": {
    "addr:full":"P Krugerstr 243 Vlissingen Zeeland 4382 MH",
    "addr:housenumber":"243",
    "addr:postcode":"4382 mh",
    "iso:country":"NL",
    "sg:address":"P Krugerstr 243",
    "sg:city":"Vlissingen",
    "sg:orig_category":"Kamerverhuur En -Bemiddeling",
    "sg:phone":"+31 118 419 010",
    "sg:postcode":"4382 MH",
    "sg:province":"Zeeland",
    "wof:name":"Muijnck, Fa De",
    "wof:placetype":"venue"
},
  "geometry": {"coordinates":[3.5797040462,51.4506225586],"type":"Point"}
}