{
  "type": "Feature",
  "properties": {
    "addr:full":"Dorpspln 11 Serooskerke Schouw Zeeland 4327 AG",
    "addr:housenumber":"11",
    "addr:postcode":"4327",
    "addr:street":"Dorpspln;Schouw Zeeland",
    "iso:country":"NL",
    "sg:address":"Dorpspln 11",
    "sg:city":"Serooskerke Schouw",
    "sg:orig_category":"Metselwerken",
    "sg:phone":"+31 111 671 753",
    "sg:postcode":"4327 AG",
    "sg:province":"Zeeland",
    "wof:name":"Smeding, G A",
    "wof:placetype":"venue"
},
  "geometry": {"coordinates":[3.814336,51.701752],"type":"Point"}
}