{
  "type": "Feature",
  "properties": {
    "addr:full":"St Jorisstr 12 S Hertogenbosch North Brabant 5211 HB",
    "addr:housenumber":"12",
    "addr:postcode":"5211 hb",
    "addr:street":"S Hertogenbosch",
    "iso:country":"NL",
    "sg:address":"St Jorisstr 12",
    "sg:city":"S Hertogenbosch",
    "sg:orig_category":"Octrooigemachtigden- Bureaus",
    "sg:phone":"+31 73 691 1350",
    "sg:postcode":"5211 HB",
    "sg:province":"North Brabant",
    "sg:website":"http://www.lioc.nl",
    "wof:name":"Lioc",
    "wof:placetype":"venue"
},
  "geometry": {"coordinates":[5.301279,51.686722],"type":"Point"}
}