{
  "type": "Feature",
  "properties": {
    "addr:full":"Postbus 283 Delft Zuid-Holland 2600 AG",
    "addr:housenumber":"283",
    "addr:postcode":"2600",
    "addr:street":"Postbus",
    "iso:country":"NL",
    "sg:address":"Postbus 283",
    "sg:city":"Delft",
    "sg:classifiers":[
        {
            "category":"Wholesale",
            "subcategory":"Meat",
            "type":"Manufacturing & Wholesale Goods"
        }
    ],
    "sg:phone":"+31 15 278 0111",
    "sg:postcode":"2600 AG",
    "sg:province":"Zuid-Holland",
    "sg:tags":[
        "regeltechniek",
        "en",
        "meet-"
    ],
    "wof:name":"Kalibra Ned Bv",
    "wof:placetype":"venue"
},
  "geometry": {"coordinates":[4.35869,52.011501],"type":"Point"}
}