{
  "type": "Feature",
  "properties": {
    "addr:full":"Clarissenhof 93 Duivendrecht Noord-Holland 1115 CC",
    "addr:housenumber":"93",
    "addr:postcode":"1115 cc",
    "addr:street":"Clarissenhof",
    "iso:country":"NL",
    "sg:address":"Clarissenhof 93",
    "sg:city":"Duivendrecht",
    "sg:orig_category":"Architecten En Architectenbureaus",
    "sg:phone":"+31 20 416 6467",
    "sg:postcode":"1115 CC",
    "sg:province":"Noord-Holland",
    "sg:website":"http://www.2design.nu",
    "wof:name":"2Design",
    "wof:placetype":"venue"
},
  "geometry": {"coordinates":[4.939506,52.333092],"type":"Point"}
}