{
  "type": "Feature",
  "properties": {
    "addr:full":"Van Calcarstraat 23 Deventer Overijssel 7415 CK",
    "addr:housenumber":"23",
    "addr:postcode":"7415 ck",
    "addr:street":"Van Calcarstraat",
    "iso:country":"NL",
    "sg:address":"Van Calcarstraat 23",
    "sg:city":"Deventer",
    "sg:orig_category":"Fotostudio'S And Fotografen",
    "sg:phone":"+31 570 623 311",
    "sg:postcode":"7415 CK",
    "sg:province":"Overijssel",
    "wof:name":"Martin Hagen Fotografie",
    "wof:placetype":"venue"
},
  "geometry": {"coordinates":[6.166889,52.263012],"type":"Point"}
}