{
  "type": "Feature",
  "properties": {
    "iso:country":"NL",
    "sg:address":"Ondernemerswg 6",
    "sg:city":"Tholen",
    "sg:orig_category":"Timmerwerken",
    "sg:phone":"+31 6 12886965",
    "sg:postcode":"4691 SL",
    "sg:province":"Zeeland",
    "wof:name":"Sitters",
    "wof:placetype":"venue"
},
  "geometry": {"coordinates":[4.228469,51.544586],"type":"Point"}
}