{
  "type": "Feature",
  "properties": {
    "addr:full":"Hoefbladhof 40 Houten Utrecht 3991 GH",
    "addr:housenumber":"40",
    "addr:postcode":"3991 gh",
    "addr:street":"Hoefbladhof",
    "iso:country":"NL",
    "sg:address":"Hoefbladhof 40",
    "sg:city":"Houten",
    "sg:orig_category":"Binnenhuisarchitecten",
    "sg:phone":"+31 30 638 0804",
    "sg:postcode":"3991 GH",
    "sg:province":"Utrecht",
    "wof:name":"Vof Ganseij Projektinrichting",
    "wof:placetype":"venue"
},
  "geometry": {"coordinates":[5.16346,52.032116],"type":"Point"}
}