{
  "type": "Feature",
  "properties": {
    "addr:full":"Hoofdstr 11D Velp Gld Gelderland 6881 TA",
    "addr:housenumber":"11d",
    "addr:postcode":"6881 ta",
    "addr:street":"Hoofdstr;Gld Gelderland",
    "iso:country":"NL",
    "sg:address":"Hoofdstr 11D",
    "sg:city":"Velp Gld",
    "sg:orig_category":"Banden",
    "sg:phone":"+31 26 364 1173",
    "sg:postcode":"6881 TA",
    "sg:province":"Gelderland",
    "sg:website":"http://www.kwik-fit.nl",
    "wof:name":"Kwik-Fit",
    "wof:placetype":"venue"
},
  "geometry": {"coordinates":[5.978641,51.996269],"type":"Point"}
}