{
  "type": "Feature",
  "properties": {
    "addr:full":"Zandstr 5 Made Noord-Brabant 4921 SK",
    "addr:housenumber":"5",
    "addr:street":"Zandstr;4921",
    "iso:country":"NL",
    "sg:address":"Zandstr 5",
    "sg:city":"Made",
    "sg:orig_category":"Lasapparaten En Benodigdheden",
    "sg:phone":"+31 162 686 000",
    "sg:postcode":"4921 SK",
    "sg:province":"Noord-Brabant",
    "wof:name":"Vanotools Bv",
    "wof:placetype":"venue"
},
  "geometry": {"coordinates":[-120.101364,36.829536],"type":"Point"}
}