{
  "type": "Feature",
  "properties": {
    "addr:full":"W Bontekoesngl 24 Gouda Zuid-Holland 2803 XN",
    "addr:housenumber":"24",
    "addr:postcode":"2803 xn",
    "addr:street":"W",
    "iso:country":"NL",
    "sg:address":"W Bontekoesngl 24",
    "sg:city":"Gouda",
    "sg:orig_category":"Voetbalverenigingen",
    "sg:phone":"+31 182 517 973",
    "sg:postcode":"2803 XN",
    "sg:province":"Zuid-Holland",
    "wof:name":"Controlec",
    "wof:placetype":"venue"
},
  "geometry": {"coordinates":[4.696954,52.021732],"type":"Point"}
}