{
  "type": "Feature",
  "properties": {
    "iso:country":"NL",
    "sg:address":"Kaaidk 14",
    "sg:city":"Kortgene",
    "sg:orig_category":"Administratie- En Boekhoudkantoren",
    "sg:phone":"+31 113 271 135",
    "sg:postcode":"4484 NP",
    "sg:province":"Zeeland",
    "wof:name":"Alda Tekstverwerking- En Administratiekantoor",
    "wof:placetype":"venue"
},
  "geometry": {"coordinates":[3.806572,51.554958],"type":"Point"}
}