{
  "type": "Feature",
  "properties": {
    "addr:full":"Amsterdamsewg 108 Amstelveen Noord-Holland 1182 HH",
    "addr:housenumber":"108",
    "addr:postcode":"1182 hh",
    "iso:country":"NL",
    "sg:address":"Amsterdamsewg 108",
    "sg:city":"Amstelveen",
    "sg:orig_category":"Woninginrichting",
    "sg:phone":"+31 20 643 9797",
    "sg:postcode":"1182 HH",
    "sg:province":"Noord-Holland",
    "wof:name":"Mario",
    "wof:placetype":"venue"
},
  "geometry": {"coordinates":[4.8468370438,52.3086242676],"type":"Point"}
}