{
  "type": "Feature",
  "properties": {
    "addr:full":"Het Wedde 47 Voorschoten Zuid-Holland 2253 RB",
    "addr:housenumber":"47",
    "addr:postcode":"2253 rb",
    "addr:street":"Het Wedde",
    "iso:country":"NL",
    "sg:address":"Het Wedde 47",
    "sg:city":"Voorschoten",
    "sg:orig_category":"Adviesbureaus Bedrijfsorganisatie",
    "sg:phone":"+31 71 576 0196",
    "sg:postcode":"2253 RB",
    "sg:province":"Zuid-Holland",
    "wof:name":"Lamet",
    "wof:placetype":"venue"
},
  "geometry": {"coordinates":[4.455167,52.141823],"type":"Point"}
}