{
  "type": "Feature",
  "properties": {
    "addr:full":"Fagot 16 S Hertogenbosch North Brabant 5231 DN",
    "addr:housenumber":"16",
    "addr:postcode":"5231 dn",
    "addr:street":"Fagot;S Hertogenbosch",
    "iso:country":"NL",
    "sg:address":"Fagot 16",
    "sg:city":"S Hertogenbosch",
    "sg:orig_category":"Verenigingen En Stichtingen",
    "sg:phone":"+31 73 641 8636",
    "sg:postcode":"5231 DN",
    "sg:province":"North Brabant",
    "wof:name":"Astmapati\u00ebntenver Vbba",
    "wof:placetype":"venue"
},
  "geometry": {"coordinates":[5.298599,51.714149],"type":"Point"}
}