{
  "type": "Feature",
  "properties": {
    "addr:full":"Archipel 1701 Lelystad NL. 8224 GJ",
    "addr:postcode":"1701;8224 gj",
    "addr:street":"Archipel;Nl.",
    "iso:country":"NL",
    "sg:address":"Archipel 1701",
    "sg:city":"Lelystad",
    "sg:orig_category":"Grafisch Ontwerpers",
    "sg:phone":"+31 6 14546245",
    "sg:postcode":"8224 GJ",
    "sg:province":"NL.",
    "wof:name":"Finerpix",
    "wof:placetype":"venue"
},
  "geometry": {"coordinates":[5.483132,52.509212],"type":"Point"}
}