{
  "type": "Feature",
  "properties": {
    "addr:full":"Julianastr 27 Berghem Noord-Brabant 5351 AL",
    "addr:housenumber":"27",
    "addr:postcode":"5351 al",
    "addr:street":"Julianastr",
    "iso:country":"NL",
    "sg:address":"Julianastr 27",
    "sg:city":"Berghem",
    "sg:orig_category":"Dierenvoeder - Fabrieken",
    "sg:phone":"+31 412 401 258",
    "sg:postcode":"5351 AL",
    "sg:province":"Noord-Brabant",
    "wof:name":"Oorschot, Van",
    "wof:placetype":"venue"
},
  "geometry": {"coordinates":[5.565091,51.771557],"type":"Point"}
}