{
  "type": "Feature",
  "properties": {
    "addr:full":"Seinstr 106-108 Hilversum Noord-Holland 1223 DC",
    "addr:housenumber":"106-108",
    "addr:postcode":"1223",
    "iso:country":"NL",
    "sg:address":"Seinstr 106-108",
    "sg:city":"Hilversum",
    "sg:orig_category":"Bloemen En Planten",
    "sg:phone":"+31 35 683 5891",
    "sg:postcode":"1223 DC",
    "sg:province":"Noord-Holland",
    "wof:name":"Bloemencorner'S Starflower Shop",
    "wof:placetype":"venue"
},
  "geometry": {"coordinates":[5.195186,52.233662],"type":"Point"}
}