{
  "type": "Feature",
  "properties": {
    "iso:country":"NL",
    "sg:address":"Skagenerf 58",
    "sg:city":"Rotterdam",
    "sg:orig_category":"Luchtfotografie",
    "sg:phone":"+31 10 456 6186",
    "sg:postcode":"3067 PX",
    "sg:province":"Zuid-Holland",
    "wof:name":"Uitdenbogerd, Hans",
    "wof:placetype":"venue"
},
  "geometry": {"coordinates":[4.557369,51.943306],"type":"Point"}
}