{
  "type": "Feature",
  "properties": {
    "addr:full":"Ripsestraat 2 De Rips Noord-Brabant 5764 PG",
    "addr:housenumber":"2",
    "addr:postcode":"5764 pg",
    "addr:street":"Ripsestraat",
    "iso:country":"NL",
    "sg:address":"Ripsestraat 2",
    "sg:city":"De Rips",
    "sg:orig_category":"Fietshandelaren",
    "sg:phone":"+31 493 599 221",
    "sg:postcode":"5764 PG",
    "sg:province":"Noord-Brabant",
    "wof:name":"Verschuren Van Kleef",
    "wof:placetype":"venue"
},
  "geometry": {"coordinates":[5.80726,51.549419],"type":"Point"}
}