{
  "type": "Feature",
  "properties": {
    "iso:country":"NL",
    "sg:address":"Gelderlandhaven 5A",
    "sg:city":"Nieuwegein",
    "sg:orig_category":"Autoradio'S",
    "sg:phone":"+31 30 606 7210",
    "sg:postcode":"3433 PG",
    "sg:province":"Utrecht",
    "wof:name":"Cartron",
    "wof:placetype":"venue"
},
  "geometry": {"coordinates":[5.106606,52.017014],"type":"Point"}
}