{
  "type": "Feature",
  "properties": {
    "addr:full":"Kastanjeln 1 Lochem Gelderland 7241 DX",
    "addr:housenumber":"1",
    "addr:postcode":"7241 dx",
    "addr:street":"Kastanjeln;Gelderland",
    "iso:country":"NL",
    "sg:address":"Kastanjeln 1",
    "sg:city":"Lochem",
    "sg:orig_category":"Adviesbureaus Bedrijfsorganisatie",
    "sg:phone":"+31 573 258 146",
    "sg:postcode":"7241 DX",
    "sg:province":"Gelderland",
    "sg:website":"HTTP://www.bigsmile.nl",
    "wof:name":"Big Smile",
    "wof:placetype":"venue"
},
  "geometry": {"coordinates":[6.418926,52.160721],"type":"Point"}
}