{
  "type": "Feature",
  "properties": {
    "addr:full":"Gerard Van Oostromstraat 49 Heusden Gem Heusden Noord-Brabant 5256 JK",
    "addr:housenumber":"49",
    "addr:postcode":"5256 jk",
    "addr:street":"Gerard Van Oostromstraat",
    "iso:country":"NL",
    "sg:address":"Gerard Van Oostromstraat 49",
    "sg:city":"Heusden Gem Heusden",
    "sg:orig_category":"Schilderwerk",
    "sg:phone":"+31 416 662 530",
    "sg:postcode":"5256 JK",
    "sg:province":"Noord-Brabant",
    "wof:name":"Van Mil Schilderwerken",
    "wof:placetype":"venue"
},
  "geometry": {"coordinates":[5.143004,51.721256],"type":"Point"}
}