{
  "type": "Feature",
  "properties": {
    "addr:full":"V Nahuyswg 8 Hasselt NL.08 8061 EZ",
    "addr:housenumber":"8",
    "addr:postcode":"8061 ez",
    "addr:street":"Nahuyswg",
    "iso:country":"NL",
    "sg:address":"V Nahuyswg 8",
    "sg:city":"Hasselt",
    "sg:orig_category":"Scheepswerven",
    "sg:phone":"+31 38 477 1215",
    "sg:postcode":"8061 EZ",
    "sg:province":"NL.08",
    "wof:name":"Bodewes",
    "wof:placetype":"venue"
},
  "geometry": {"coordinates":[6.088755,52.592861],"type":"Point"}
}