{
  "type": "Feature",
  "properties": {
    "iso:country":"NL",
    "sg:address":"Alexine Tinnepad 105",
    "sg:city":"'S Gravenhage",
    "sg:orig_category":"Boekhouders",
    "sg:phone":"+31 70 404 3735",
    "sg:postcode":"2553 TS",
    "sg:province":"South Holland",
    "wof:name":"Smit & Co., Administratieadviseurs",
    "wof:placetype":"venue"
},
  "geometry": {"coordinates":[4.22074,52.04887],"type":"Point"}
}