{
  "type": "Feature",
  "properties": {
    "iso:country":"NL",
    "sg:address":"Kaapstr 39",
    "sg:city":"De Koog",
    "sg:classifiers":[
        {
            "category":"Travel",
            "subcategory":"Hotels & Motels",
            "type":"Entertainment"
        }
    ],
    "sg:phone":"+31 222 317 370",
    "sg:postcode":"1796 AE",
    "sg:province":"Noord-Holland",
    "wof:name":"Tesselhof",
    "wof:placetype":"venue"
},
  "geometry": {"coordinates":[4.761654,53.098545],"type":"Point"}
}