{
  "type": "Feature",
  "properties": {
    "iso:country":"NL",
    "sg:address":"Remmerswaalstr 43",
    "sg:city":"De Zilk",
    "sg:orig_category":"Administratie- En Boekhoudkantoren",
    "sg:phone":"+31 252 531 855",
    "sg:postcode":"2191 BJ",
    "sg:province":"Zuid-Holland",
    "wof:name":"Horst, Ter",
    "wof:placetype":"venue"
},
  "geometry": {"coordinates":[4.545671,52.30196],"type":"Point"}
}