{
  "type": "Feature",
  "properties": {
    "addr:full":"Remmerswaalstr 43 De Zilk Zuid-Holland 2191 BJ",
    "addr:housenumber":"43",
    "addr:postcode":"2191 bj",
    "addr:street":"Remmerswaalstr",
    "iso:country":"NL",
    "sg:address":"Remmerswaalstr 43",
    "sg:city":"De Zilk",
    "sg:orig_category":"Administratie- En Boekhoudkantoren",
    "sg:phone":"+31 252 531 855",
    "sg:postcode":"2191 BJ",
    "sg:province":"Zuid-Holland",
    "wof:name":"Horst, Ter",
    "wof:placetype":"venue"
},
  "geometry": {"coordinates":[4.545671,52.30196],"type":"Point"}
}