{
  "type": "Feature",
  "properties": {
    "addr:full":"Veersedijk 293 Hendrik Ido Ambacht South Holland 3341 LM",
    "addr:housenumber":"293",
    "addr:postcode":"3341 lm",
    "addr:street":"Veersedijk",
    "iso:country":"NL",
    "sg:address":"Veersedijk 293",
    "sg:city":"Hendrik Ido Ambacht",
    "sg:orig_category":"Autokeuringen",
    "sg:phone":"+31 78 619 6195",
    "sg:postcode":"3341 LM",
    "sg:province":"South Holland",
    "wof:name":"P. Maaskant",
    "wof:placetype":"venue"
},
  "geometry": {"coordinates":[4.659311,51.833611],"type":"Point"}
}