{
  "type": "Feature",
  "properties": {
    "iso:country":"NL",
    "sg:address":"Winterakker 18",
    "sg:city":"Spijkenisse",
    "sg:orig_category":"Boekhandels",
    "sg:phone":"+31 181 636 273",
    "sg:postcode":"3206 TG",
    "sg:province":"South Holland",
    "wof:name":"Firma Edel",
    "wof:placetype":"venue"
},
  "geometry": {"coordinates":[4.320914,51.833206],"type":"Point"}
}