{
  "type": "Feature",
  "properties": {
    "addr:full":"Rijksweg 112 Velsen-Zuid North Holland 1981 LD",
    "addr:housenumber":"112",
    "addr:postcode":"1981 ld",
    "addr:street":"Rijksweg",
    "iso:country":"NL",
    "sg:address":"Rijksweg 112",
    "sg:city":"Velsen-Zuid",
    "sg:orig_category":"Farmaceutische Producten Gh",
    "sg:phone":"+31 255 566 800",
    "sg:postcode":"1981 LD",
    "sg:province":"North Holland",
    "wof:name":"Qrs Nederland Bv",
    "wof:placetype":"venue"
},
  "geometry": {"coordinates":[4.651578,52.45546],"type":"Point"}
}