{
  "type": "Feature",
  "properties": {
    "addr:full":"Papiermolen 13 Alphen Aan Den Ryn South Holland 2406 KL",
    "addr:housenumber":"13",
    "addr:postcode":"2406 kl",
    "addr:street":"Papiermolen;Aan Den Ryn",
    "iso:country":"NL",
    "sg:address":"Papiermolen 13",
    "sg:city":"Alphen Aan Den Ryn",
    "sg:orig_category":"Mobiele- En Autotelefoons",
    "sg:phone":"+31 172 495 661",
    "sg:postcode":"2406 KL",
    "sg:province":"South Holland",
    "wof:name":"Bellrental",
    "wof:placetype":"venue"
},
  "geometry": {"coordinates":[4.672131,52.123116],"type":"Point"}
}