{
  "type": "Feature",
  "properties": {
    "addr:full":"Torenstraat 66 Eygelshoven Limburg 6471 JX",
    "addr:housenumber":"66",
    "addr:postcode":"6471 jx",
    "addr:street":"Torenstraat",
    "iso:country":"NL",
    "sg:address":"Torenstraat 66",
    "sg:city":"Eygelshoven",
    "sg:orig_category":"Meubelreparatie And -Restauratie",
    "sg:phone":"+31 45 545 8542",
    "sg:postcode":"6471 JX",
    "sg:province":"Limburg",
    "wof:name":"H E J Kaesler",
    "wof:placetype":"venue"
},
  "geometry": {"coordinates":[6.053128,50.895538],"type":"Point"}
}