{
  "type": "Feature",
  "properties": {
    "addr:full":"Veenenburg 68 Gouda Zuid-Holland 2804 WZ",
    "addr:housenumber":"68",
    "addr:postcode":"2804 wz",
    "addr:street":"Veenenburg",
    "iso:country":"NL",
    "sg:address":"Veenenburg 68",
    "sg:city":"Gouda",
    "sg:orig_category":"Adviesbureaus Bedrijfsorganisatie",
    "sg:phone":"+31 6 20627118",
    "sg:postcode":"2804 WZ",
    "sg:province":"Zuid-Holland",
    "wof:name":"Outside-Insight",
    "wof:placetype":"venue"
},
  "geometry": {"coordinates":[4.70705,52.032616],"type":"Point"}
}