{
  "type": "Feature",
  "properties": {
    "iso:country":"NL",
    "sg:address":"Beverweg 102",
    "sg:city":"Breda",
    "sg:orig_category":"Hout Gh",
    "sg:phone":"+31 76 522 1540",
    "sg:postcode":"4817 LN",
    "sg:province":"Noord-Brabant",
    "wof:name":"Formido A. Muilwijk",
    "wof:placetype":"venue"
},
  "geometry": {"coordinates":[4.798284,51.59235],"type":"Point"}
}