{
  "type": "Feature",
  "properties": {
    "iso:country":"NL",
    "sg:address":"Wilhelminaln 5759",
    "sg:city":"Oosterhout Nb",
    "sg:orig_category":"Verenigingsgebouwen",
    "sg:phone":"+31 162 454 591",
    "sg:postcode":"4905 AT",
    "sg:province":"North Brabant",
    "wof:name":"Pannehoef, De",
    "wof:placetype":"venue"
},
  "geometry": {"coordinates":[4.84136,51.64431],"type":"Point"}
}