{
  "type": "Feature",
  "properties": {
    "iso:country":"NL",
    "sg:address":"L Jansstr 10",
    "sg:city":"Utrecht",
    "sg:orig_category":"Kunsthandel",
    "sg:phone":"+31 30 231 1463",
    "sg:postcode":"3512 BB",
    "sg:province":"Utrecht",
    "wof:name":"Juffermans",
    "wof:placetype":"venue"
},
  "geometry": {"coordinates":[5.119419,52.093655],"type":"Point"}
}