{
  "type": "Feature",
  "properties": {
    "iso:country":"NL",
    "sg:address":"Limburglaan 10",
    "sg:city":"Maastricht",
    "sg:orig_category":"Overheidsdiensten",
    "sg:phone":"+31 43 389 9999",
    "sg:postcode":"6229 GA",
    "sg:province":"Limburg",
    "wof:name":"Provincie Limburg",
    "wof:placetype":"venue"
},
  "geometry": {"coordinates":[5.7029490471,50.8382530212],"type":"Point"}
}