{
  "type": "Feature",
  "properties": {
    "addr:full":"Overtuinen 14 Zuidhorn Groningen 9801 BR",
    "addr:housenumber":"14",
    "addr:postcode":"9801 br",
    "addr:street":"Overtuinen",
    "iso:country":"NL",
    "sg:address":"Overtuinen 14",
    "sg:city":"Zuidhorn",
    "sg:classifiers":[
        {
            "category":"Shopping",
            "subcategory":"Clothing, Apparel, & Fashions",
            "type":"Retail Goods"
        }
    ],
    "sg:phone":"+31 594 506 251",
    "sg:postcode":"9801 BR",
    "sg:province":"Groningen",
    "sg:tags":[
        "ondergoed",
        "lingerie"
    ],
    "wof:name":"Oleander Import",
    "wof:placetype":"venue"
},
  "geometry": {"coordinates":[6.408851,53.243713],"type":"Point"}
}