{
  "type": "Feature",
  "properties": {
    "addr:full":"Lindegracht 2 Monnickendam Noord-Holland 1141 VW",
    "addr:housenumber":"2",
    "addr:postcode":"1141 vw",
    "addr:street":"Lindegracht",
    "iso:country":"NL",
    "sg:address":"Lindegracht 2",
    "sg:city":"Monnickendam",
    "sg:orig_category":"Fruit And Groenten Gh",
    "sg:phone":"+31 299 651 717",
    "sg:postcode":"1141 VW",
    "sg:province":"Noord-Holland",
    "wof:name":"Frumo Bv",
    "wof:placetype":"venue"
},
  "geometry": {"coordinates":[5.033422,52.457893],"type":"Point"}
}