{
  "type": "Feature",
  "properties": {
    "addr:full":"Hoofdstr 125 Uithuizermeeden Groningen 9982 AC",
    "addr:housenumber":"125",
    "addr:postcode":"9982 ac",
    "iso:country":"NL",
    "sg:address":"Hoofdstr 125",
    "sg:city":"Uithuizermeeden",
    "sg:classifiers":[
        {
            "category":"Food & Beverages",
            "subcategory":"Candy",
            "type":"Retail Goods"
        }
    ],
    "sg:phone":"+31 595 413 739",
    "sg:postcode":"9982 AC",
    "sg:province":"Groningen",
    "sg:tags":[
        "sport-",
        "en",
        "spelartikelen"
    ],
    "wof:name":"Zijlstra Sport",
    "wof:placetype":"venue"
},
  "geometry": {"coordinates":[6.726975,53.415577],"type":"Point"}
}