{
  "type": "Feature",
  "properties": {
    "iso:country":"NL",
    "sg:address":"Zandvoortweg 153",
    "sg:city":"Baarn",
    "sg:orig_category":"Fietshandelaren",
    "sg:phone":"+31 35 541 6833",
    "sg:postcode":"3741 BC",
    "sg:province":"Utrecht",
    "wof:name":"Elb Van Der Ent",
    "wof:placetype":"venue"
},
  "geometry": {"coordinates":[5.282464,52.218452],"type":"Point"}
}