{
  "type": "Feature",
  "properties": {
    "iso:country":"NL",
    "sg:address":"Oosterengweg 96",
    "sg:city":"Hilversum",
    "sg:orig_category":"Zuivelproducten",
    "sg:phone":"+31 35 685 2375",
    "sg:postcode":"1212 CP",
    "sg:province":"North Holland",
    "wof:name":"De Kaasspecialist Hilversum",
    "wof:placetype":"venue"
},
  "geometry": {"coordinates":[5.19506,52.218742],"type":"Point"}
}