{
  "type": "Feature",
  "properties": {
    "addr:full":"Oudeweg 107 Haarlem North Holland 2031 CC",
    "addr:housenumber":"107",
    "addr:postcode":"2031 cc",
    "addr:street":"Oudeweg",
    "iso:country":"NL",
    "sg:address":"Oudeweg 107",
    "sg:city":"Haarlem",
    "sg:orig_category":"Verhuur Voertuigen Behalve Auto'S",
    "sg:phone":"+31 23 531 1730",
    "sg:postcode":"2031 CC",
    "sg:province":"North Holland",
    "wof:name":"W. Hiemenz Aanhangwagens",
    "wof:placetype":"venue"
},
  "geometry": {"coordinates":[4.659614,52.385338],"type":"Point"}
}