{
  "type": "Feature",
  "properties": {
    "addr:full":"Drie Decembersingel 44B Venlo Limburg 5921 AC",
    "addr:housenumber":"44b",
    "addr:postcode":"5921 ac",
    "addr:street":"Drie Decembersingel",
    "iso:country":"NL",
    "sg:address":"Drie Decembersingel 44B",
    "sg:city":"Venlo",
    "sg:orig_category":"Fitnesscentra",
    "sg:phone":"+31 77 382 5264",
    "sg:postcode":"5921 AC",
    "sg:province":"Limburg",
    "wof:name":"La Vita Sana",
    "wof:placetype":"venue"
},
  "geometry": {"coordinates":[6.137595,51.369541],"type":"Point"}
}