{
  "type": "Feature",
  "properties": {
    "addr:full":"Lumeystr 18C Rotterdam Zuid-Holland 3039 ZP",
    "addr:housenumber":"18c",
    "addr:postcode":"3039 zp",
    "addr:street":"Lumeystr",
    "iso:country":"NL",
    "sg:address":"Lumeystr 18C",
    "sg:city":"Rotterdam",
    "sg:orig_category":"Webdesign Bureaus",
    "sg:phone":"+31 10 467 2092",
    "sg:postcode":"3039 ZP",
    "sg:province":"Zuid-Holland",
    "sg:website":"http://www.intris.nl",
    "wof:name":"Intris",
    "wof:placetype":"venue"
},
  "geometry": {"coordinates":[4.4626598358,51.9282684326],"type":"Point"}
}