{
  "type": "Feature",
  "properties": {
    "addr:full":"Scharnerwg 37A Maastricht Limburg 6224 JA",
    "addr:housenumber":"37a",
    "addr:postcode":"6224 ja",
    "addr:street":"Scharnerwg",
    "iso:country":"NL",
    "sg:address":"Scharnerwg 37A",
    "sg:city":"Maastricht",
    "sg:orig_category":"Makelaars En Adviseurs Onroerende Goederen",
    "sg:phone":"+31 43 362 5489",
    "sg:postcode":"6224 JA",
    "sg:province":"Limburg",
    "wof:name":"Smeets Bv, J",
    "wof:placetype":"venue"
},
  "geometry": {"coordinates":[5.717957,50.848728],"type":"Point"}
}