{
  "type": "Feature",
  "properties": {
    "addr:full":"Uilenburg 6 Hilvarenbeek North Brabant 5081 RH",
    "addr:housenumber":"6",
    "addr:postcode":"5081 rh",
    "addr:street":"Uilenburg",
    "iso:country":"NL",
    "sg:address":"Uilenburg 6",
    "sg:city":"Hilvarenbeek",
    "sg:orig_category":"Verenigingsgebouwen",
    "sg:phone":"+31 13 505 4328",
    "sg:postcode":"5081 RH",
    "sg:province":"North Brabant",
    "wof:name":"Wijkcentr Uilenburg",
    "wof:placetype":"venue"
},
  "geometry": {"coordinates":[5.140804,51.492287],"type":"Point"}
}