{
  "type": "Feature",
  "properties": {
    "addr:full":"Korhoenln 3 Ede Gld Gelderland 6713 BL",
    "addr:housenumber":"3;6713 bl",
    "addr:street":"Korhoenln;Gld Gelderland",
    "iso:country":"NL",
    "sg:address":"Korhoenln 3",
    "sg:city":"Ede Gld",
    "sg:orig_category":"Fotopersbureaus",
    "sg:phone":"+31 318 655 447",
    "sg:postcode":"6713 BL",
    "sg:province":"Gelderland",
    "wof:name":"Equestrian",
    "wof:placetype":"venue"
},
  "geometry": {"coordinates":[5.659148,52.040863],"type":"Point"}
}