{
  "type": "Feature",
  "properties": {
    "addr:full":"Zuiderparkln 251 S Gravenhage Zuid-Holland 2574 HJ",
    "addr:housenumber":"251;gravenhage",
    "addr:postcode":"2574 hj",
    "addr:street":"S",
    "iso:country":"NL",
    "sg:address":"Zuiderparkln 251",
    "sg:city":"S Gravenhage",
    "sg:orig_category":"Poeliers",
    "sg:phone":"+31 70 323 7356",
    "sg:postcode":"2574 HJ",
    "sg:province":"Zuid-Holland",
    "wof:name":"Meijer, Victor",
    "wof:placetype":"venue"
},
  "geometry": {"coordinates":[4.277523,52.064205],"type":"Point"}
}