{
  "type": "Feature",
  "properties": {
    "iso:country":"NL",
    "sg:address":"Newtonstraat 7",
    "sg:city":"Schiedam",
    "sg:orig_category":"Autokeuringen",
    "sg:phone":"+31 10 415 4247",
    "sg:postcode":"3112 WE",
    "sg:province":"South Holland",
    "wof:name":"Rr",
    "wof:placetype":"venue"
},
  "geometry": {"coordinates":[4.41566,51.91758],"type":"Point"}
}