{
  "type": "Feature",
  "properties": {
    "iso:country":"NL",
    "sg:address":"Postbus 51",
    "sg:city":"Gorssel",
    "sg:orig_category":"Adviesbureaus Bedrijfsorganisatie",
    "sg:phone":"+31 575 494 224",
    "sg:postcode":"7213 ZH",
    "sg:province":"Gelderland",
    "wof:name":"Claes, P F",
    "wof:placetype":"venue"
},
  "geometry": {"coordinates":[6.20043,52.198807],"type":"Point"}
}