{
  "type": "Feature",
  "properties": {
    "addr:full":"Aalsmeerderdk 98 Oude Meer Oklahoma 1438 AT",
    "addr:housenumber":"98",
    "addr:postcode":"1438",
    "addr:street":"Aalsmeerderdk",
    "iso:country":"NL",
    "sg:address":"Aalsmeerderdk 98",
    "sg:city":"Oude Meer",
    "sg:orig_category":"Bouwmachines",
    "sg:phone":"+31 20 653 3414",
    "sg:postcode":"1438 AT",
    "sg:province":"Oklahoma",
    "wof:name":"Peetoom, Ed",
    "wof:placetype":"venue"
},
  "geometry": {"coordinates":[-98.579796,34.781834],"type":"Point"}
}