{
  "type": "Feature",
  "properties": {
    "iso:country":"NL",
    "sg:address":"Voorstr 27",
    "sg:city":"Utrecht",
    "sg:orig_category":"Adviesbureaus",
    "sg:phone":"+31 30 231 6015",
    "sg:postcode":"3512 AJ",
    "sg:province":"Utrecht",
    "wof:name":"Banque Commerciale Du Maroc",
    "wof:placetype":"venue"
},
  "geometry": {"coordinates":[5.119813,52.094479],"type":"Point"}
}