{
  "type": "Feature",
  "properties": {
    "iso:country":"NL",
    "sg:address":"Liguster 25",
    "sg:city":"Leidschendam",
    "sg:orig_category":"Herenkleding",
    "sg:phone":"+31 70 320 7241",
    "sg:postcode":"2262 AC",
    "sg:province":"South Holland",
    "wof:name":"Moda Di Domani",
    "wof:placetype":"venue"
},
  "geometry": {"coordinates":[4.385063,52.088348],"type":"Point"}
}