{
  "type": "Feature",
  "properties": {
    "addr:full":"Willemstr 19 Alphen A/D Rijn Zuid-Holland 2405 EG",
    "addr:housenumber":"19",
    "addr:postcode":"2405 eg",
    "addr:street":"Willemstr",
    "iso:country":"NL",
    "sg:address":"Willemstr 19",
    "sg:city":"Alphen A/D Rijn",
    "sg:classifiers":[
        {
            "category":"Personal",
            "subcategory":"Nail Salon",
            "type":"Services"
        }
    ],
    "sg:phone":"+31 172 474 590",
    "sg:postcode":"2405 EG",
    "sg:province":"Zuid-Holland",
    "sg:tags":[
        "pedicure"
    ],
    "wof:name":"Kreuningen, C Van",
    "wof:placetype":"venue"
},
  "geometry": {"coordinates":[4.660441,52.133884],"type":"Point"}
}