{
  "type": "Feature",
  "properties": {
    "addr:full":"Waterstraat 28 Nijmegen Gelderland 6541 TK",
    "addr:housenumber":"28",
    "addr:postcode":"6541 tk",
    "addr:street":"Waterstraat;Gelderland",
    "iso:country":"NL",
    "sg:address":"Waterstraat 28",
    "sg:city":"Nijmegen",
    "sg:orig_category":"Verhuisdiensten",
    "sg:phone":"+31 24 377 0267",
    "sg:postcode":"6541 TK",
    "sg:province":"Gelderland",
    "wof:name":"Vrachttaxi Bakker",
    "wof:placetype":"venue"
},
  "geometry": {"coordinates":[5.840861,51.846733],"type":"Point"}
}