{
  "type": "Feature",
  "properties": {
    "addr:full":"Vlaardingweg 62 Rotterdam Zuid-Holland 3044 CK",
    "addr:housenumber":"62",
    "addr:postcode":"3044 ck",
    "addr:street":"Vlaardingweg",
    "iso:country":"NL",
    "sg:address":"Vlaardingweg 62",
    "sg:city":"Rotterdam",
    "sg:orig_category":"Werving And Selectie Van Tijdelijk Personeel And Uitzendkantoren",
    "sg:phone":"+31 10 437 4733",
    "sg:postcode":"3044 CK",
    "sg:province":"Zuid-Holland",
    "wof:name":"Willpower Personeelsvoorziening",
    "wof:placetype":"venue"
},
  "geometry": {"coordinates":[4.4148840904,51.9309463501],"type":"Point"}
}