{
  "type": "Feature",
  "properties": {
    "iso:country":"NL",
    "sg:address":"Parallelstraat 37",
    "sg:city":"Amstenrade",
    "sg:orig_category":"Discountwinkels",
    "sg:phone":"+31 46 442 4804",
    "sg:postcode":"6436 BN",
    "sg:province":"Limburg",
    "wof:name":"De Greef Textiel Bv",
    "wof:placetype":"venue"
},
  "geometry": {"coordinates":[5.921982,50.940678],"type":"Point"}
}