{
  "type": "Feature",
  "properties": {
    "addr:full":"Loosd Hoofdstr 100 S Gravenhage South Holland 2552 AK",
    "addr:housenumber":"100",
    "addr:postcode":"2552 ak",
    "addr:street":"S Gravenhage",
    "iso:country":"NL",
    "sg:address":"Loosd Hoofdstr 100",
    "sg:city":"S Gravenhage",
    "sg:orig_category":"Plastificeren",
    "sg:phone":"+31 70 404 0960",
    "sg:postcode":"2552 AK",
    "sg:province":"South Holland",
    "sg:website":"http://www.printstudio.nl",
    "wof:name":"Printstudio Loosduinen",
    "wof:placetype":"venue"
},
  "geometry": {"coordinates":[4.24958,52.053631],"type":"Point"}
}