{
  "type": "Feature",
  "properties": {
    "addr:full":"Papenhoefln 57 Oudewater Utrecht 3421 XN",
    "addr:housenumber":"57",
    "addr:postcode":"3421 xn",
    "addr:street":"Papenhoefln",
    "iso:country":"NL",
    "sg:address":"Papenhoefln 57",
    "sg:city":"Oudewater",
    "sg:orig_category":"Koeltechniek",
    "sg:phone":"+31 348 563 378",
    "sg:postcode":"3421 XN",
    "sg:province":"Utrecht",
    "wof:name":"Kok, Philip",
    "wof:placetype":"venue"
},
  "geometry": {"coordinates":[4.860275,52.026722],"type":"Point"}
}