{
  "type": "Feature",
  "properties": {
    "iso:country":"NL",
    "sg:address":"Prinsessenweg 121",
    "sg:city":"Nieuwegein",
    "sg:orig_category":"Modeontwerpen",
    "sg:phone":"+31 30 606 3101",
    "sg:postcode":"3433 AE",
    "sg:province":"Utrecht",
    "wof:name":"Freetex Fashion D-Sign",
    "wof:placetype":"venue"
},
  "geometry": {"coordinates":[5.102981,52.009529],"type":"Point"}
}