{
  "type": "Feature",
  "properties": {
    "addr:full":"Hadewychplaats 24 Spykenisse Zuid-Holland 3207 KG",
    "addr:housenumber":"24",
    "addr:postcode":"3207 kg",
    "addr:street":"Hadewychplaats",
    "iso:country":"NL",
    "sg:address":"Hadewychplaats 24",
    "sg:city":"Spykenisse",
    "sg:orig_category":"Huishoudelijke Apparaten En Artikelen",
    "sg:phone":"+31 181 687 116",
    "sg:postcode":"3207 KG",
    "sg:province":"Zuid-Holland",
    "wof:name":"Marskramer Bv",
    "wof:placetype":"venue"
},
  "geometry": {"coordinates":[4.35787,51.838669],"type":"Point"}
}