{
  "type": "Feature",
  "properties": {
    "addr:full":"Watertorenlaan 25 Leerdam Zuid-Holland 4141 HT",
    "addr:housenumber":"25",
    "addr:postcode":"4141 ht",
    "addr:street":"Watertorenlaan",
    "iso:country":"NL",
    "sg:address":"Watertorenlaan 25",
    "sg:city":"Leerdam",
    "sg:classifiers":[
        {
            "category":"Education",
            "subcategory":"Preschool",
            "type":"Public Place"
        }
    ],
    "sg:phone":"+31 345 614 317",
    "sg:postcode":"4141 HT",
    "sg:province":"Zuid-Holland",
    "sg:tags":[
        "kleuteronderwijs",
        "basis-"
    ],
    "wof:name":"Cbs Ichthus Locatie Juliana",
    "wof:placetype":"venue"
},
  "geometry": {"coordinates":[5.09763,51.894241],"type":"Point"}
}