{
  "type": "Feature",
  "properties": {
    "addr:full":"Churchillln 5 Helmond Noord-Brabant 5705 BK",
    "addr:housenumber":"5",
    "addr:postcode":"5705 bk",
    "addr:street":"Churchillln",
    "iso:country":"NL",
    "sg:address":"Churchillln 5",
    "sg:city":"Helmond",
    "sg:orig_category":"Banden",
    "sg:phone":"+31 492 534 750",
    "sg:postcode":"5705 BK",
    "sg:province":"Noord-Brabant",
    "sg:website":"http://www.euromaster.com",
    "wof:name":"Euromaster",
    "wof:placetype":"venue"
},
  "geometry": {"coordinates":[5.658284,51.482239],"type":"Point"}
}