{
  "type": "Feature",
  "properties": {
    "addr:full":"Kreitsberg 7 Zeeland Noord-Brabant 5411 RH",
    "addr:housenumber":"7",
    "addr:postcode":"5411 rh",
    "addr:street":"Kreitsberg",
    "iso:country":"NL",
    "sg:address":"Kreitsberg 7",
    "sg:city":"Zeeland",
    "sg:orig_category":"Sportclubs",
    "sg:phone":"+31 486 452 066",
    "sg:postcode":"5411 RH",
    "sg:province":"Noord-Brabant",
    "wof:name":"Stichting Centaur",
    "wof:placetype":"venue"
},
  "geometry": {"coordinates":[5.67807,51.709595],"type":"Point"}
}