{
  "type": "Feature",
  "properties": {
    "addr:full":"Pr Hendrikkd 53 Amsterdam Noord-Holland 1012 AC",
    "addr:housenumber":"53",
    "addr:postcode":"1012 ac",
    "iso:country":"NL",
    "sg:address":"Pr Hendrikkd 53",
    "sg:city":"Amsterdam",
    "sg:classifiers":[
        {
            "category":"Travel",
            "subcategory":"Hotels & Motels",
            "type":"Entertainment"
        }
    ],
    "sg:phone":"+31 20 623 7969",
    "sg:postcode":"1012 AC",
    "sg:province":"Noord-Holland",
    "sg:website":"http://www.hotel-prinshendrik.nl",
    "wof:name":"Prins Hendrik",
    "wof:placetype":"venue"
},
  "geometry": {"coordinates":[4.899502,52.376556],"type":"Point"}
}