{
  "type": "Feature",
  "properties": {
    "addr:full":"Herenstr 18A Ryswyk Zh South Holland 2282 BT",
    "addr:housenumber":"18a;zh",
    "addr:postcode":"2282 bt",
    "addr:street":"Herenstr",
    "iso:country":"NL",
    "sg:address":"Herenstr 18A",
    "sg:city":"Ryswyk Zh",
    "sg:orig_category":"Herenkleding",
    "sg:phone":"+31 70 399 5775",
    "sg:postcode":"2282 BT",
    "sg:province":"South Holland",
    "wof:name":"Intermezzo",
    "wof:placetype":"venue"
},
  "geometry": {"coordinates":[4.33694,52.056503],"type":"Point"}
}