{
  "type": "Feature",
  "properties": {
    "iso:country":"NL",
    "sg:address":"Bedumerweg 20",
    "sg:city":"Onderdendam",
    "sg:orig_category":"Verhuur Catering-, Feest- En Evenementbenodigdheden",
    "sg:phone":"+31 50 304 9500",
    "sg:postcode":"9959 PG",
    "sg:province":"Groningen",
    "wof:name":"Grootkeuken Installaties Polkerman",
    "wof:placetype":"venue"
},
  "geometry": {"coordinates":[6.58935,53.335209],"type":"Point"}
}