{
  "type": "Feature",
  "properties": {
    "addr:full":"Langendijk 54 Gorinchem South Holland 4201 CJ",
    "addr:housenumber":"54",
    "addr:postcode":"4201 cj",
    "addr:street":"Langendijk",
    "iso:country":"NL",
    "sg:address":"Langendijk 54",
    "sg:city":"Gorinchem",
    "sg:orig_category":"Kappers",
    "sg:phone":"+31 183 660 295",
    "sg:postcode":"4201 CJ",
    "sg:province":"South Holland",
    "wof:name":"Coiffure House Gorinchem",
    "wof:placetype":"venue"
},
  "geometry": {"coordinates":[4.975771904,51.8289527893],"type":"Point"}
}