{
  "type": "Feature",
  "properties": {
    "addr:full":"Jamaicadreef 39 Utrecht Utrecht 3563 SP",
    "addr:housenumber":"39",
    "addr:postcode":"3563 sp",
    "addr:street":"Jamaicadreef",
    "iso:country":"NL",
    "sg:address":"Jamaicadreef 39",
    "sg:city":"Utrecht",
    "sg:orig_category":"Boekhouders",
    "sg:phone":"+31 30 262 8785",
    "sg:postcode":"3563 SP",
    "sg:province":"Utrecht",
    "wof:name":"Administratiekantoor Jos Van Valkenburg",
    "wof:placetype":"venue"
},
  "geometry": {"coordinates":[5.09596,52.122021],"type":"Point"}
}