{
  "type": "Feature",
  "properties": {
    "iso:country":"NL",
    "sg:address":"Mercuriusweg 15",
    "sg:city":"Vlissingen",
    "sg:orig_category":"Elektriciens",
    "sg:phone":"+31 118 467 920",
    "sg:postcode":"4382 NC",
    "sg:province":"Zeeland",
    "wof:name":"Imtech Marine & Industry Bv",
    "wof:placetype":"venue"
},
  "geometry": {"coordinates":[3.583278,51.451241],"type":"Point"}
}