{
  "type": "Feature",
  "properties": {
    "addr:full":"Heikantstraat 18 Waalre Noord-Brabant 5581 VB",
    "addr:housenumber":"18",
    "addr:postcode":"5581 vb",
    "addr:street":"Heikantstraat",
    "iso:country":"NL",
    "sg:address":"Heikantstraat 18",
    "sg:city":"Waalre",
    "sg:orig_category":"Medische Apparatuur And Prothesen Fab",
    "sg:phone":"+31 40 221 6666",
    "sg:postcode":"5581 VB",
    "sg:province":"Noord-Brabant",
    "wof:name":"Tandtechn.Lab. K.Vink",
    "wof:placetype":"venue"
},
  "geometry": {"coordinates":[5.447205,51.376232],"type":"Point"}
}