{
  "type": "Feature",
  "properties": {
    "iso:country":"NL",
    "sg:address":"Zoetendk 12",
    "sg:city":"Reeuwyk",
    "sg:orig_category":"Onroerende Goederen",
    "sg:phone":"+31 182 399 189",
    "sg:postcode":"2811 HA",
    "sg:province":"Zuid-Holland",
    "wof:name":"Steengoed Bv",
    "wof:placetype":"venue"
},
  "geometry": {"coordinates":[4.722337,52.044903],"type":"Point"}
}