{
  "type": "Feature",
  "properties": {
    "iso:country":"NL",
    "sg:address":"G V Heemskerkstr 8",
    "sg:city":"Naaldwyk",
    "sg:orig_category":"Kantoor- En Secretariaatsservice",
    "sg:phone":"+31 174 624 911",
    "sg:postcode":"2671 AW",
    "sg:province":"Zuid-Holland",
    "wof:name":"Letter Express",
    "wof:placetype":"venue"
},
  "geometry": {"coordinates":[4.2052488327,51.9913978577],"type":"Point"}
}