{
  "type": "Feature",
  "properties": {
    "iso:country":"NL",
    "sg:address":"Wilgenoord 103",
    "sg:city":"Bodegraven",
    "sg:orig_category":"Haarwerken",
    "sg:phone":"+31 172 612 408",
    "sg:postcode":"2411 TD",
    "sg:province":"Zuid-Holland",
    "wof:name":"Boef, G",
    "wof:placetype":"venue"
},
  "geometry": {"coordinates":[4.740744,52.078556],"type":"Point"}
}