{
  "type": "Feature",
  "properties": {
    "iso:country":"NL",
    "sg:address":"Kerkweg 20",
    "sg:city":"Lekkerkerk",
    "sg:classifiers":[
        {
            "category":"Retail",
            "subcategory":"Photofinishing",
            "type":"Services"
        }
    ],
    "sg:phone":"+31 180 663 300",
    "sg:postcode":"2941 BM",
    "sg:province":"Zuid-Holland",
    "sg:tags":[
        "foto",
        "film"
    ],
    "wof:name":"Foto Klip",
    "wof:placetype":"venue"
},
  "geometry": {"coordinates":[4.68356,51.897175],"type":"Point"}
}