{
  "type": "Feature",
  "properties": {
    "iso:country":"NL",
    "sg:address":"Mathenesserwg 139A",
    "sg:city":"Rotterdam",
    "sg:classifiers":[
        {
            "category":"Food & Beverages",
            "subcategory":"Bakery",
            "type":"Retail Goods"
        }
    ],
    "sg:phone":"+31 10 462 7722",
    "sg:postcode":"3027 HN",
    "sg:province":"Zuid-Holland",
    "sg:tags":[
        "pizza"
    ],
    "sg:website":"http://www.pizzaamore.nl",
    "wof:name":"Amore",
    "wof:placetype":"venue"
},
  "geometry": {"coordinates":[4.43689,51.914253],"type":"Point"}
}