{
  "type": "Feature",
  "properties": {
    "iso:country":"NL",
    "sg:address":"Leeuweriklaan 12",
    "sg:city":"'S Gravenhage",
    "sg:orig_category":"Binnenhuisarchitecten",
    "sg:phone":"+31 70 365 7988",
    "sg:postcode":"2566 JE",
    "sg:province":"Zuid-Holland",
    "wof:name":"H.L.H. V.D. Bogerd",
    "wof:placetype":"venue"
},
  "geometry": {"coordinates":[4.26248,52.083809],"type":"Point"}
}