{
  "type": "Feature",
  "properties": {
    "iso:country":"NL",
    "sg:address":"Appelstr 242",
    "sg:city":"S Gravenhage",
    "sg:orig_category":"Boekhandels",
    "sg:phone":"+31 70 368 9780",
    "sg:postcode":"2564 EL",
    "sg:province":"Zuid-Holland",
    "wof:name":"Vos, J P De",
    "wof:placetype":"venue"
},
  "geometry": {"coordinates":[4.25946,52.06805],"type":"Point"}
}