{
  "type": "Feature",
  "properties": {
    "iso:country":"NL",
    "sg:address":"Karspeldreef 2",
    "sg:city":"Amsterdam Zuidoost",
    "sg:orig_category":"Woningbouw- Verenigingen En -Stichtingen",
    "sg:phone":"+31 20 342 9999",
    "sg:postcode":"1101 CJ",
    "sg:province":"Noord-Holland",
    "sg:website":"http://www.patrimonium.nl",
    "wof:name":"Patrimonium, Woningstichting",
    "wof:placetype":"venue"
},
  "geometry": {"coordinates":[4.9475002289,52.3048248291],"type":"Point"}
}