{
  "type": "Feature",
  "properties": {
    "addr:full":"Semmelweisstr 38 Haarlem Noord-Holland 2035 CV",
    "addr:housenumber":"38",
    "addr:postcode":"2035 cv",
    "addr:street":"Semmelweisstr",
    "iso:country":"NL",
    "sg:address":"Semmelweisstr 38",
    "sg:city":"Haarlem",
    "sg:orig_category":"Horecabenodigdheden",
    "sg:phone":"+31 23 533 5715",
    "sg:postcode":"2035 CV",
    "sg:province":"Noord-Holland",
    "wof:name":"Andrew",
    "wof:placetype":"venue"
},
  "geometry": {"coordinates":[4.661615,52.363621],"type":"Point"}
}