{
  "type": "Feature",
  "properties": {
    "addr:full":"Loowg 18A Bathmen Overijssel 7437 RR",
    "addr:housenumber":"18a",
    "addr:postcode":"7437 rr",
    "addr:street":"Loowg",
    "iso:country":"NL",
    "sg:address":"Loowg 18A",
    "sg:city":"Bathmen",
    "sg:orig_category":"Kappers",
    "sg:phone":"+31 570 540 618",
    "sg:postcode":"7437 RR",
    "sg:province":"Overijssel",
    "wof:name":"Louise Dameskapsalon",
    "wof:placetype":"venue"
},
  "geometry": {"coordinates":[6.290647,52.251205],"type":"Point"}
}