{
  "type": "Feature",
  "properties": {
    "addr:full":"Sandbergstr 2A Ommen Overijssel 7731 DG",
    "addr:housenumber":"2a",
    "addr:postcode":"7731 dg",
    "addr:street":"Sandbergstr",
    "iso:country":"NL",
    "sg:address":"Sandbergstr 2A",
    "sg:city":"Ommen",
    "sg:orig_category":"Scholen Voor Basisonderwijs",
    "sg:phone":"+31 529 452 988",
    "sg:postcode":"7731 DG",
    "sg:province":"Overijssel",
    "wof:name":"Juliana Chr, Kon",
    "wof:placetype":"venue"
},
  "geometry": {"coordinates":[6.421368,52.520588],"type":"Point"}
}