{
  "type": "Feature",
  "properties": {
    "addr:full":"Edisonstr 20 Lichtenvoorde Gelderland 7131 PB",
    "addr:housenumber":"20",
    "addr:postcode":"7131 pb",
    "addr:street":"Edisonstr;Gelderland",
    "iso:country":"NL",
    "sg:address":"Edisonstr 20",
    "sg:city":"Lichtenvoorde",
    "sg:orig_category":"Keuken- Groot-Installaties",
    "sg:phone":"+31 544 391 111",
    "sg:postcode":"7131 PB",
    "sg:province":"Gelderland",
    "sg:website":"http://www.atagkeukentechniek.com/",
    "wof:name":"Atag-Pelgrim Bv",
    "wof:placetype":"venue"
},
  "geometry": {"coordinates":[-36.777691,-7.16501],"type":"Point"}
}