{
  "type": "Feature",
  "properties": {
    "iso:country":"NL",
    "sg:address":"Broekweg 63",
    "sg:city":"Klazienaveen",
    "sg:orig_category":"Verhuur Bouwmachines",
    "sg:phone":"+31 591 314 716",
    "sg:postcode":"7891 RR",
    "sg:province":"Provincie Drenthe",
    "wof:name":"Frisjong Verhuur",
    "wof:placetype":"venue"
},
  "geometry": {"coordinates":[6.973018,52.720089],"type":"Point"}
}