{
  "type": "Feature",
  "properties": {
    "addr:full":"Grindweg 155 Scherpenzeel Fr Friesland 8483 JM",
    "addr:housenumber":"155",
    "addr:postcode":"8483 jm",
    "addr:street":"Grindweg",
    "iso:country":"NL",
    "sg:address":"Grindweg 155",
    "sg:city":"Scherpenzeel Fr",
    "sg:orig_category":"Kampeerterreinen",
    "sg:phone":"+31 561 481 269",
    "sg:postcode":"8483 JM",
    "sg:province":"Friesland",
    "wof:name":"Pannenkoekenboerderij Restaurant De Landerij",
    "wof:placetype":"venue"
},
  "geometry": {"coordinates":[5.8751478195,52.8296432495],"type":"Point"}
}