{
  "type": "Feature",
  "properties": {
    "addr:full":"Zwaanstraat 44 Cuijk North Brabant 5431 BP",
    "addr:housenumber":"44",
    "addr:postcode":"5431 bp",
    "addr:street":"Zwaanstraat",
    "iso:country":"NL",
    "sg:address":"Zwaanstraat 44",
    "sg:city":"Cuijk",
    "sg:orig_category":"Werving And Selectie Van Tijdelijk Personeel And Uitzendkantoren",
    "sg:phone":"+31 485 321 808",
    "sg:postcode":"5431 BP",
    "sg:province":"North Brabant",
    "wof:name":"Randstad",
    "wof:placetype":"venue"
},
  "geometry": {"coordinates":[5.8789830208,51.7299003601],"type":"Point"}
}