{
  "type": "Feature",
  "properties": {
    "addr:full":"Besterdpln 33 Tilburg Noord-Brabant 5014 HP",
    "addr:housenumber":"33",
    "addr:postcode":"5014 hp",
    "addr:street":"Besterdpln",
    "iso:country":"NL",
    "sg:address":"Besterdpln 33",
    "sg:city":"Tilburg",
    "sg:orig_category":"Woninginrichting",
    "sg:phone":"+31 13 543 7008",
    "sg:postcode":"5014 HP",
    "sg:province":"Noord-Brabant",
    "wof:name":"Strik En Strook",
    "wof:placetype":"venue"
},
  "geometry": {"coordinates":[5.0913228989,51.5645103455],"type":"Point"}
}