{
  "type": "Feature",
  "properties": {
    "iso:country":"NL",
    "sg:address":"Besterdpln 33",
    "sg:city":"Tilburg",
    "sg:orig_category":"Woninginrichting",
    "sg:phone":"+31 13 543 7008",
    "sg:postcode":"5014 HP",
    "sg:province":"Noord-Brabant",
    "wof:name":"Strik En Strook",
    "wof:placetype":"venue"
},
  "geometry": {"coordinates":[5.0913228989,51.5645103455],"type":"Point"}
}