{
  "type": "Feature",
  "properties": {
    "addr:full":"Duivekervel 13 Oldenzaal Overijssel 7577 CK",
    "addr:housenumber":"13",
    "addr:postcode":"7577 ck",
    "addr:street":"Duivekervel",
    "iso:country":"NL",
    "sg:address":"Duivekervel 13",
    "sg:city":"Oldenzaal",
    "sg:orig_category":"Gebouwenafwerking, Renovaties And Reiniging",
    "sg:phone":"+31 541 535 540",
    "sg:postcode":"7577 CK",
    "sg:province":"Overijssel",
    "wof:name":"M V R Oldenzaal",
    "wof:placetype":"venue"
},
  "geometry": {"coordinates":[6.927308,52.324875],"type":"Point"}
}