{
  "type": "Feature",
  "properties": {
    "iso:country":"NL",
    "sg:address":"Hogeweg 5",
    "sg:city":"Drunen",
    "sg:orig_category":"Boekhouders",
    "sg:phone":"+31 416 320 200",
    "sg:postcode":"5151 BJ",
    "sg:province":"North Brabant",
    "wof:name":"Administratiekantoor Nagtzaam",
    "wof:placetype":"venue"
},
  "geometry": {"coordinates":[5.140884,51.687229],"type":"Point"}
}