{
  "type": "Feature",
  "properties": {
    "addr:full":"Nyverheidswg 17 Best Texas 5683 CJ",
    "addr:housenumber":"17",
    "addr:postcode":"5683 cj",
    "addr:street":"Nyverheidswg",
    "iso:country":"NL",
    "sg:address":"Nyverheidswg 17",
    "sg:city":"Best",
    "sg:orig_category":"Mobiele- En Autotelefoons",
    "sg:phone":"+31 499 366 666",
    "sg:postcode":"5683 CJ",
    "sg:province":"Texas",
    "sg:website":"http://www.dtf.nl",
    "wof:name":"Teleforce Bv",
    "wof:placetype":"venue"
},
  "geometry": {"coordinates":[-101.618134,31.224251],"type":"Point"}
}