{
  "type": "Feature",
  "properties": {
    "addr:full":"Heycopstr 7 Utrecht Utrecht 3521 EN",
    "addr:housenumber":"7",
    "addr:postcode":"3521 en",
    "addr:street":"Heycopstr",
    "iso:country":"NL",
    "sg:address":"Heycopstr 7",
    "sg:city":"Utrecht",
    "sg:orig_category":"Webdesign Bureaus",
    "sg:phone":"+31 30 296 5571",
    "sg:postcode":"3521 EN",
    "sg:province":"Utrecht",
    "sg:website":"http://www.joyceblankestijn.nl",
    "wof:name":"Blankenstijn, Joyce",
    "wof:placetype":"venue"
},
  "geometry": {"coordinates":[5.1099181175,52.0788803101],"type":"Point"}
}