{
  "type": "Feature",
  "properties": {
    "addr:full":"Witmakersstr 1 Maastricht Limburg 6211 JA",
    "addr:housenumber":"1",
    "addr:postcode":"6211 ja",
    "addr:street":"Witmakersstr",
    "iso:country":"NL",
    "sg:address":"Witmakersstr 1",
    "sg:city":"Maastricht",
    "sg:orig_category":"Kunsthandel",
    "sg:phone":"+31 43 325 8589",
    "sg:postcode":"6211 JA",
    "sg:province":"Limburg",
    "wof:name":"Schiltaere",
    "wof:placetype":"venue"
},
  "geometry": {"coordinates":[5.691658,50.846718],"type":"Point"}
}