{
  "type": "Feature",
  "properties": {
    "addr:full":"Zuidplaspolderwg 15 Moordrecht Zuid-Holland 2841 DC",
    "addr:housenumber":"15",
    "addr:postcode":"2841",
    "addr:street":"Zuidplaspolderwg",
    "iso:country":"NL",
    "sg:address":"Zuidplaspolderwg 15",
    "sg:city":"Moordrecht",
    "sg:orig_category":"Ovenbouw",
    "sg:phone":"+31 182 374 620",
    "sg:postcode":"2841 DC",
    "sg:province":"Zuid-Holland",
    "sg:website":"http://www.wbtelectron.com",
    "wof:name":"Wbt Bv",
    "wof:placetype":"venue"
},
  "geometry": {"coordinates":[4.6713209152,51.9934692383],"type":"Point"}
}