{
  "type": "Feature",
  "properties": {
    "addr:full":"Brasserskade 1 Delft South Holland 2612 CA",
    "addr:housenumber":"1",
    "addr:postcode":"2612 ca",
    "addr:street":"Brasserskade",
    "iso:country":"NL",
    "sg:address":"Brasserskade 1",
    "sg:city":"Delft",
    "sg:orig_category":"Hoger Onderwijs",
    "sg:phone":"+31 15 215 0215",
    "sg:postcode":"2612 CA",
    "sg:province":"South Holland",
    "wof:name":"Hogeschool Delft",
    "wof:placetype":"venue"
},
  "geometry": {"coordinates":[4.352857,52.023407],"type":"Point"}
}