{
  "type": "Feature",
  "properties": {
    "addr:full":"Surinamepln 14 Amsterdam Noord-Holland 1058 GP",
    "addr:housenumber":"14",
    "addr:postcode":"1058 gp",
    "addr:street":"Surinamepln",
    "iso:country":"NL",
    "sg:address":"Surinamepln 14",
    "sg:city":"Amsterdam",
    "sg:orig_category":"Adviesbureaus Bedrijfsorganisatie",
    "sg:phone":"+31 20 689 8844",
    "sg:postcode":"1058 GP",
    "sg:province":"Noord-Holland",
    "wof:name":"Mulders Bv, H",
    "wof:placetype":"venue"
},
  "geometry": {"coordinates":[4.854074,52.358738],"type":"Point"}
}