{
  "type": "Feature",
  "properties": {
    "addr:full":"Van Slingelandtstraat 22 Amsterdam New York 1051 CH",
    "addr:housenumber":"22;1051",
    "addr:street":"Van Slingelandtstraat",
    "iso:country":"NL",
    "sg:address":"Van Slingelandtstraat 22",
    "sg:city":"Amsterdam",
    "sg:orig_category":"Kantoorartikelen",
    "sg:phone":"+31 20 681 3398",
    "sg:postcode":"1051 CH",
    "sg:province":"New York",
    "wof:name":"Parma Kantoorinrichting",
    "wof:placetype":"venue"
},
  "geometry": {"coordinates":[-74.24620819090001,42.9782867432],"type":"Point"}
}