{
  "type": "Feature",
  "properties": {
    "addr:full":"Voorstreek 5 Leeuwarden Friesland 8911 JH",
    "addr:housenumber":"5",
    "addr:postcode":"8911 jh",
    "addr:street":"Voorstreek",
    "iso:country":"NL",
    "sg:address":"Voorstreek 5",
    "sg:city":"Leeuwarden",
    "sg:orig_category":"Bloemen En Planten",
    "sg:phone":"+31 58 212 1330",
    "sg:postcode":"8911 JH",
    "sg:province":"Friesland",
    "wof:name":"Matahari",
    "wof:placetype":"venue"
},
  "geometry": {"coordinates":[5.798943,53.202412],"type":"Point"}
}