{
  "type": "Feature",
  "properties": {
    "iso:country":"NL",
    "sg:address":"Garde Jagerswei 4",
    "sg:city":"Grouw",
    "sg:orig_category":"Jachthavens - Jachtwerven",
    "sg:phone":"+31 566 621 335",
    "sg:postcode":"9001 ZP",
    "sg:province":"Friesland",
    "sg:website":"http://www.deblieken.nl",
    "wof:name":"Wester & Zn, Fa A E",
    "wof:placetype":"venue"
},
  "geometry": {"coordinates":[5.83863,53.099056],"type":"Point"}
}