{
  "type": "Feature",
  "properties": {
    "addr:full":"Rokin 118 Amsterdam North Holland 1012 LB",
    "addr:housenumber":"118",
    "addr:postcode":"1012 lb",
    "addr:street":"Rokin",
    "iso:country":"NL",
    "sg:address":"Rokin 118",
    "sg:city":"Amsterdam",
    "sg:orig_category":"Werving And Selectie Van Tijdelijk Personeel And Uitzendkantoren",
    "sg:phone":"+31 900 7002510",
    "sg:postcode":"1012 LB",
    "sg:province":"North Holland",
    "wof:name":"Tempo Team",
    "wof:placetype":"venue"
},
  "geometry": {"coordinates":[4.8918328285,52.3687286377],"type":"Point"}
}