{
  "type": "Feature",
  "properties": {
    "addr:full":"Bosstr 39 Driebergen Rysenb Utrecht 3971 XA",
    "addr:housenumber":"39",
    "addr:postcode":"3971 xa",
    "addr:street":"Bosstr;Rysenb",
    "iso:country":"NL",
    "sg:address":"Bosstr 39",
    "sg:city":"Driebergen Rysenb",
    "sg:orig_category":"Adviesbureaus Bedrijfsorganisatie",
    "sg:phone":"+31 343 516 902",
    "sg:postcode":"3971 XA",
    "sg:province":"Utrecht",
    "wof:name":"Bemmelen, Van",
    "wof:placetype":"venue"
},
  "geometry": {"coordinates":[5.283456,52.054398],"type":"Point"}
}