{
  "type": "Feature",
  "properties": {
    "addr:full":"Julianaplein 6 Vroomshoop Overijssel 7681 AW",
    "addr:housenumber":"6",
    "addr:postcode":"7681 aw",
    "addr:street":"Julianaplein",
    "iso:country":"NL",
    "sg:address":"Julianaplein 6",
    "sg:city":"Vroomshoop",
    "sg:orig_category":"Damesmodezaken",
    "sg:phone":"+31 546 641 310",
    "sg:postcode":"7681 AW",
    "sg:province":"Overijssel",
    "wof:name":"Nathalie Mode Bv",
    "wof:placetype":"venue"
},
  "geometry": {"coordinates":[6.571993,52.460403],"type":"Point"}
}