{
  "type": "Feature",
  "properties": {
    "iso:country":"NL",
    "sg:address":"Utrechtsedwstr 124",
    "sg:city":"Amsterdam",
    "sg:orig_category":"Horeca-Inrichtingen En -Uitrustingen",
    "sg:phone":"+31 20 528 9713",
    "sg:postcode":"1017 WJ",
    "sg:province":"Noord-Holland",
    "wof:name":"Vo-Raks Bv",
    "wof:placetype":"venue"
},
  "geometry": {"coordinates":[4.90082,52.361664],"type":"Point"}
}