{
  "type": "Feature",
  "properties": {
    "addr:full":"Beukelsdk 9 Deurne Noord-Brabant 5753 PA",
    "addr:housenumber":"9",
    "addr:postcode":"5753 pa",
    "addr:street":"Beukelsdk",
    "iso:country":"NL",
    "sg:address":"Beukelsdk 9",
    "sg:city":"Deurne",
    "sg:orig_category":"Waterbehandeling En Waterzuiverings- Systemen",
    "sg:phone":"+31 493 313 540",
    "sg:postcode":"5753 PA",
    "sg:province":"Noord-Brabant",
    "wof:name":"Kessel, Louis Van",
    "wof:placetype":"venue"
},
  "geometry": {"coordinates":[5.7667169571,51.4577331543],"type":"Point"}
}