{
  "type": "Feature",
  "properties": {
    "addr:full":"Kapt Nemostr 62 Tilburg North Brabant 5015 AM",
    "addr:housenumber":"62",
    "addr:postcode":"5015",
    "iso:country":"NL",
    "sg:address":"Kapt Nemostr 62",
    "sg:city":"Tilburg",
    "sg:orig_category":"Meubelen",
    "sg:phone":"+31 13 544 1177",
    "sg:postcode":"5015 AM",
    "sg:province":"North Brabant",
    "wof:name":"Maison Mondiale",
    "wof:placetype":"venue"
},
  "geometry": {"coordinates":[5.109818,51.567368],"type":"Point"}
}