{
  "type": "Feature",
  "properties": {
    "addr:full":"Hoofdstr 175 De Lier Zuid-Holland 2678 CJ",
    "addr:housenumber":"175",
    "addr:postcode":"2678 cj",
    "iso:country":"NL",
    "sg:address":"Hoofdstr 175",
    "sg:city":"De Lier",
    "sg:orig_category":"Woninginrichting",
    "sg:phone":"+31 174 513 589",
    "sg:postcode":"2678 CJ",
    "sg:province":"Zuid-Holland",
    "wof:name":"Lagerwerf & Zn, L",
    "wof:placetype":"venue"
},
  "geometry": {"coordinates":[4.2533531189,51.9756317139],"type":"Point"}
}