{
  "type": "Feature",
  "properties": {
    "addr:full":"Tussenlanen 20 Bergambacht Zuid-Holland 2861 CD",
    "addr:housenumber":"20",
    "addr:postcode":"2861 cd",
    "addr:street":"Tussenlanen",
    "iso:country":"NL",
    "sg:address":"Tussenlanen 20",
    "sg:city":"Bergambacht",
    "sg:orig_category":"Bloemen And Planten",
    "sg:phone":"+31 182 351 861",
    "sg:postcode":"2861 CD",
    "sg:province":"Zuid-Holland",
    "wof:name":"A. Molenaar",
    "wof:placetype":"venue"
},
  "geometry": {"coordinates":[4.796973,51.940014],"type":"Point"}
}