{
  "type": "Feature",
  "properties": {
    "addr:full":"Groenezoom 275 Rotterdam Zuid-Holland 3075 GE",
    "addr:housenumber":"275",
    "addr:postcode":"3075",
    "addr:street":"Groenezoom",
    "iso:country":"NL",
    "sg:address":"Groenezoom 275",
    "sg:city":"Rotterdam",
    "sg:classifiers":[
        {
            "category":"Food & Beverages",
            "subcategory":"Fruits & Vegetables",
            "type":"Retail Goods"
        }
    ],
    "sg:phone":"+31 10 419 1287",
    "sg:postcode":"3075 GE",
    "sg:province":"Zuid-Holland",
    "sg:tags":[
        "groenten"
    ],
    "wof:name":"Groenten- & Fruit M.A. Van Beusekom",
    "wof:placetype":"venue"
},
  "geometry": {"coordinates":[4.510308,51.884876],"type":"Point"}
}