{
  "type": "Feature",
  "properties": {
    "iso:country":"NL",
    "sg:address":"Merwedestraat 54",
    "sg:city":"Groningen",
    "sg:orig_category":"Bejaardeninstellingen And Serviceflats",
    "sg:phone":"+31 50 574 6100",
    "sg:postcode":"9725 KE",
    "sg:province":"Groningen",
    "wof:name":"Zorgcentrum Talmahuis",
    "wof:placetype":"venue"
},
  "geometry": {"coordinates":[6.567529,53.206352],"type":"Point"}
}