{
  "type": "Feature",
  "properties": {
    "addr:full":"Schoutenkampwg 4 Soest Utrecht 3768 AE",
    "addr:housenumber":"4",
    "addr:postcode":"3768 ae",
    "addr:street":"Schoutenkampwg",
    "iso:country":"NL",
    "sg:address":"Schoutenkampwg 4",
    "sg:city":"Soest",
    "sg:orig_category":"Artsen - Huisartsen",
    "sg:phone":"+31 35 601 2395",
    "sg:postcode":"3768 AE",
    "sg:province":"Utrecht",
    "wof:name":"Vrijmoet, K",
    "wof:placetype":"venue"
},
  "geometry": {"coordinates":[5.305786,52.164856],"type":"Point"}
}