{
  "type": "Feature",
  "properties": {
    "addr:full":"J Tooropstr 12 Deurne North Brabant 5753 DK",
    "addr:housenumber":"12",
    "addr:postcode":"5753 dk",
    "iso:country":"NL",
    "sg:address":"J Tooropstr 12",
    "sg:city":"Deurne",
    "sg:orig_category":"Bestratingen",
    "sg:phone":"+31 493 316 701",
    "sg:postcode":"5753 DK",
    "sg:province":"North Brabant",
    "wof:name":"Berg, Van Den",
    "wof:placetype":"venue"
},
  "geometry": {"coordinates":[5.795966,51.447918],"type":"Point"}
}