{
  "type": "Feature",
  "properties": {
    "addr:full":"Telefoonweg 79 Ede Gld Gelderland 6713 AK",
    "addr:housenumber":"79",
    "addr:postcode":"6713 ak",
    "addr:street":"Telefoonweg;Gld Gelderland",
    "iso:country":"NL",
    "sg:address":"Telefoonweg 79",
    "sg:city":"Ede Gld",
    "sg:orig_category":"Kappers",
    "sg:phone":"+31 318 616 430",
    "sg:postcode":"6713 AK",
    "sg:province":"Gelderland",
    "wof:name":"Eline Haarmode",
    "wof:placetype":"venue"
},
  "geometry": {"coordinates":[5.6685190201,52.0441627502],"type":"Point"}
}