{
  "type": "Feature",
  "properties": {
    "addr:full":"Hunsstr 43A Voerendaal Limburg 6367 JJ",
    "addr:housenumber":"43a",
    "addr:postcode":"6367 jj",
    "addr:street":"Hunsstr",
    "iso:country":"NL",
    "sg:address":"Hunsstr 43A",
    "sg:city":"Voerendaal",
    "sg:orig_category":"Adviesbureaus Bouwkunde",
    "sg:phone":"+31 45 567 1012",
    "sg:postcode":"6367 JJ",
    "sg:province":"Limburg",
    "wof:name":"S & U Projectpartners Bv",
    "wof:placetype":"venue"
},
  "geometry": {"coordinates":[5.950843,50.854897],"type":"Point"}
}