{
  "type": "Feature",
  "properties": {
    "addr:full":"Prinses Beatrixstraat 45 Harlingen Provincie Friesland 8862 TN",
    "addr:housenumber":"45",
    "addr:postcode":"8862",
    "addr:street":"Prinses Beatrixstraat;Provincie Friesland",
    "iso:country":"NL",
    "sg:address":"Prinses Beatrixstraat 45",
    "sg:city":"Harlingen",
    "sg:orig_category":"Fruit And Groenten Gh",
    "sg:phone":"+31 517 416 174",
    "sg:postcode":"8862 TN",
    "sg:province":"Provincie Friesland",
    "wof:name":"A. Nagel",
    "wof:placetype":"venue"
},
  "geometry": {"coordinates":[5.42676,53.167927],"type":"Point"}
}