{
  "type": "Feature",
  "properties": {
    "addr:full":"N Kraayertsedk 5 Lewedorp Zeeland 4456 NV",
    "addr:housenumber":"5",
    "addr:postcode":"4456 nv",
    "addr:street":"N Kraayertsedk",
    "iso:country":"NL",
    "sg:address":"N Kraayertsedk 5",
    "sg:city":"Lewedorp",
    "sg:orig_category":"Lasbedrijven",
    "sg:phone":"+31 113 612 888",
    "sg:postcode":"4456 NV",
    "sg:province":"Zeeland",
    "wof:name":"Baar, De",
    "wof:placetype":"venue"
},
  "geometry": {"coordinates":[3.74495,51.494785],"type":"Point"}
}