{
  "type": "Feature",
  "properties": {
    "addr:full":"J V Ghestelln 27 Rotterdam Zuid-Holland 3054 CE",
    "addr:housenumber":"27",
    "addr:postcode":"3054 ce",
    "addr:street":"J;Ghestelln",
    "iso:country":"NL",
    "sg:address":"J V Ghestelln 27",
    "sg:city":"Rotterdam",
    "sg:orig_category":"Adviesbureaus Bedrijfsorganisatie",
    "sg:phone":"+31 10 418 4137",
    "sg:postcode":"3054 CE",
    "sg:province":"Zuid-Holland",
    "wof:name":"Intvelt Bv",
    "wof:placetype":"venue"
},
  "geometry": {"coordinates":[4.49284,51.957539],"type":"Point"}
}