{
  "type": "Feature",
  "properties": {
    "iso:country":"NL",
    "sg:address":"Bosln 40",
    "sg:city":"Amerongen",
    "sg:orig_category":"Borduurwerken",
    "sg:phone":"+31 343 461 091",
    "sg:postcode":"3958 GZ",
    "sg:province":"Utrecht",
    "wof:name":"Aalbers",
    "wof:placetype":"venue"
},
  "geometry": {"coordinates":[5.46023,52.000702],"type":"Point"}
}