{
  "type": "Feature",
  "properties": {
    "addr:full":"Hoofdstraat 40 Drouwenerveen Drenthe 9525 TE",
    "addr:housenumber":"40",
    "addr:postcode":"9525 te",
    "addr:street":"Hoofdstraat",
    "iso:country":"NL",
    "sg:address":"Hoofdstraat 40",
    "sg:city":"Drouwenerveen",
    "sg:orig_category":"Fruit And Groenten Gh",
    "sg:phone":"+31 599 512 285",
    "sg:postcode":"9525 TE",
    "sg:province":"Drenthe",
    "wof:name":"G.E. Veldman",
    "wof:placetype":"venue"
},
  "geometry": {"coordinates":[6.849229,52.970367],"type":"Point"}
}