{
  "type": "Feature",
  "properties": {
    "addr:full":"Ywg 1003 Hoofddorp North Holland 2133 MG",
    "addr:housenumber":"1003",
    "addr:postcode":"2133 mg",
    "iso:country":"NL",
    "sg:address":"Ywg 1003",
    "sg:city":"Hoofddorp",
    "sg:orig_category":"Bedrijfshuisvesting",
    "sg:phone":"+31 23 561 5087",
    "sg:postcode":"2133 MG",
    "sg:province":"North Holland",
    "wof:name":"Mackenzie Bv",
    "wof:placetype":"venue"
},
  "geometry": {"coordinates":[4.66985,52.310452],"type":"Point"}
}