{
  "type": "Feature",
  "properties": {
    "iso:country":"NL",
    "sg:address":"Looierslaan 12",
    "sg:city":"Leidschendam",
    "sg:orig_category":"Wasserettes And Stomerijen",
    "sg:phone":"+31 70 327 3585",
    "sg:postcode":"2264 AA",
    "sg:province":"Zuid-Holland",
    "wof:name":"Wasserij De Haan",
    "wof:placetype":"venue"
},
  "geometry": {"coordinates":[4.3879861832,52.0820007324],"type":"Point"}
}