{
  "type": "Feature",
  "properties": {
    "addr:full":"H Dunantstr 4A Almelo Overijssel 7607 XK",
    "addr:housenumber":"4a",
    "addr:postcode":"7607 xk",
    "iso:country":"NL",
    "sg:address":"H Dunantstr 4A",
    "sg:city":"Almelo",
    "sg:orig_category":"Verhuur",
    "sg:phone":"+31 546 850 099",
    "sg:postcode":"7607 XK",
    "sg:province":"Overijssel",
    "sg:website":"http://www.lemerij.nl",
    "wof:name":"Lemerij, De",
    "wof:placetype":"venue"
},
  "geometry": {"coordinates":[6.657946,52.35965],"type":"Point"}
}