{
  "type": "Feature",
  "properties": {
    "iso:country":"NL",
    "sg:address":"De Zande 43",
    "sg:city":"Kamperveen",
    "sg:orig_category":"Meubelzaken, Woning- And Keukeninrichting",
    "sg:phone":"+31 38 363 6365",
    "sg:postcode":"8278 AH",
    "sg:province":"Overijssel",
    "wof:name":"Vof Capelle Antiques",
    "wof:placetype":"venue"
},
  "geometry": {"coordinates":[5.936121,52.506821],"type":"Point"}
}