{
  "type": "Feature",
  "properties": {
    "addr:full":"Wolfpad 30 Alkmaar North Holland 1813 AD",
    "addr:housenumber":"30",
    "addr:postcode":"1813 ad",
    "addr:street":"Wolfpad",
    "iso:country":"NL",
    "sg:address":"Wolfpad 30",
    "sg:city":"Alkmaar",
    "sg:orig_category":"Onroerende Goederen",
    "sg:phone":"+31 72 515 1446",
    "sg:postcode":"1813 AD",
    "sg:province":"North Holland",
    "wof:name":"Gedeka Bv",
    "wof:placetype":"venue"
},
  "geometry": {"coordinates":[4.753948,52.626705],"type":"Point"}
}