{
  "type": "Feature",
  "properties": {
    "addr:full":"Pk Vronesteyn 31 Voorburg South Holland 2271 HP",
    "addr:housenumber":"31",
    "addr:postcode":"2271 hp",
    "addr:street":"Pk Vronesteyn",
    "iso:country":"NL",
    "sg:address":"Pk Vronesteyn 31",
    "sg:city":"Voorburg",
    "sg:classifiers":[
        {
            "category":"Personal",
            "subcategory":"Nail Salon",
            "type":"Services"
        }
    ],
    "sg:phone":"+31 70 386 2270",
    "sg:postcode":"2271 HP",
    "sg:province":"South Holland",
    "sg:tags":[
        "pedicure"
    ],
    "wof:name":"Weijnen-De Lint, A C",
    "wof:placetype":"venue"
},
  "geometry": {"coordinates":[4.382118,52.076332],"type":"Point"}
}