{
  "type": "Feature",
  "properties": {
    "addr:full":"Ringhersmastr 31 Damwoude Georgia 9104 GA",
    "addr:housenumber":"31",
    "addr:postcode":"9104 ga",
    "addr:street":"Ringhersmastr;Georgia",
    "iso:country":"NL",
    "sg:address":"Ringhersmastr 31",
    "sg:city":"Damwoude",
    "sg:orig_category":"Metaalbewerking",
    "sg:phone":"+31 511 423 437",
    "sg:postcode":"9104 GA",
    "sg:province":"Georgia",
    "wof:name":"Jodocus",
    "wof:placetype":"venue"
},
  "geometry": {"coordinates":[-83.222931,32.678131],"type":"Point"}
}