{
  "type": "Feature",
  "properties": {
    "iso:country":"NL",
    "sg:address":"Biest 32",
    "sg:city":"Weert",
    "sg:orig_category":"Begrafenisverzorging",
    "sg:phone":"+31 495 631 363",
    "sg:postcode":"6001 AR",
    "sg:province":"Limburg",
    "sg:website":"http://www.vandeursen-uitvaart.nl",
    "wof:name":"Van Deursen",
    "wof:placetype":"venue"
},
  "geometry": {"coordinates":[-80.747246,38.354977],"type":"Point"}
}