{
  "type": "Feature",
  "properties": {
    "addr:full":"Bloemerd 2 Leiderdorp Zuid-Holland 2353 BZ",
    "addr:housenumber":"2",
    "addr:postcode":"2353 bz",
    "addr:street":"Bloemerd",
    "iso:country":"NL",
    "sg:address":"Bloemerd 2",
    "sg:city":"Leiderdorp",
    "sg:orig_category":"Verenigingen En Stichtingen",
    "sg:phone":"+31 71 589 3450",
    "sg:postcode":"2353 BZ",
    "sg:province":"Zuid-Holland",
    "wof:name":"Rcl Vv",
    "wof:placetype":"venue"
},
  "geometry": {"coordinates":[4.5446,52.164932],"type":"Point"}
}