{
  "type": "Feature",
  "properties": {
    "addr:full":"Nw Hoogstr 14 Amsterdam North Holland 1011 HE",
    "addr:housenumber":"14",
    "addr:postcode":"1011 he",
    "iso:country":"NL",
    "sg:address":"Nw Hoogstr 14",
    "sg:city":"Amsterdam",
    "sg:orig_category":"Geschenkartikelen",
    "sg:phone":"+31 20 427 5424",
    "sg:postcode":"1011 HE",
    "sg:province":"North Holland",
    "wof:name":"Cleijne Verschil, Het",
    "wof:placetype":"venue"
},
  "geometry": {"coordinates":[4.899488,52.370647],"type":"Point"}
}