{
  "type": "Feature",
  "properties": {
    "addr:full":"Eendrachtln 57 Breukelen Ut Utrecht 3621 DE",
    "addr:housenumber":"57",
    "addr:postcode":"3621 de",
    "addr:street":"Eendrachtln",
    "iso:country":"NL",
    "sg:address":"Eendrachtln 57",
    "sg:city":"Breukelen Ut",
    "sg:orig_category":"Loodgieters",
    "sg:phone":"+31 346 257 379",
    "sg:postcode":"3621 DE",
    "sg:province":"Utrecht",
    "sg:website":"http://www.rhijnenvechtstreek.nl",
    "wof:name":"Rhijn En Vechtstreek",
    "wof:placetype":"venue"
},
  "geometry": {"coordinates":[4.9980950356,52.1750221252],"type":"Point"}
}