{
  "type": "Feature",
  "properties": {
    "addr:full":"Deventerwg 83 Holten Overijssel 7451 MC",
    "addr:housenumber":"83",
    "addr:postcode":"7451 mc",
    "addr:street":"Deventerwg",
    "iso:country":"NL",
    "sg:address":"Deventerwg 83",
    "sg:city":"Holten",
    "sg:orig_category":"Voetbalverenigingen",
    "sg:phone":"+31 548 363 440",
    "sg:postcode":"7451 MC",
    "sg:province":"Overijssel",
    "wof:name":"Holten Vv",
    "wof:placetype":"venue"
},
  "geometry": {"coordinates":[6.354723,52.274986],"type":"Point"}
}