{
  "type": "Feature",
  "properties": {
    "addr:full":"Mr. Beelpark 25 Ede Gld Gelderland 6716 EV",
    "addr:housenumber":"25",
    "addr:postcode":"6716 ev",
    "addr:street":"Beelpark;Gld Gelderland",
    "iso:country":"NL",
    "sg:address":"Mr. Beelpark 25",
    "sg:city":"Ede Gld",
    "sg:orig_category":"Schoonheidssalons",
    "sg:phone":"+31 318 620 865",
    "sg:postcode":"6716 EV",
    "sg:province":"Gelderland",
    "wof:name":"Annie Timmer Pedicure",
    "wof:placetype":"venue"
},
  "geometry": {"coordinates":[5.66767,52.044979],"type":"Point"}
}