{
  "type": "Feature",
  "properties": {
    "addr:full":"Chopinstraat 9 Capelle A/D Ijssel South Holland 2901 EB",
    "addr:housenumber":"9;a / d",
    "addr:postcode":"2901 eb",
    "addr:street":"Chopinstraat;Ijssel South",
    "iso:country":"NL",
    "sg:address":"Chopinstraat 9",
    "sg:city":"Capelle A/D Ijssel",
    "sg:classifiers":[
        {
            "category":"Professional",
            "subcategory":"Accounting & Tax Preparation",
            "type":"Services"
        }
    ],
    "sg:phone":"+31 10 202 1385",
    "sg:postcode":"2901 EB",
    "sg:province":"South Holland",
    "sg:tags":[
        "accountant"
    ],
    "wof:name":"Van Keulen Bv",
    "wof:placetype":"venue"
},
  "geometry": {"coordinates":[4.556634,51.915028],"type":"Point"}
}