{
  "type": "Feature",
  "properties": {
    "iso:country":"NL",
    "sg:address":"Schoolwg 19",
    "sg:city":"Veeningen",
    "sg:orig_category":"Scholen Voor Basisonderwijs",
    "sg:phone":"+31 528 391 555",
    "sg:postcode":"7924 PL",
    "sg:province":"Drenthe",
    "wof:name":"Esdalsch Openb",
    "wof:placetype":"venue"
},
  "geometry": {"coordinates":[6.370695,52.668526],"type":"Point"}
}