{
  "type": "Feature",
  "properties": {
    "addr:full":"Molenwg 133 Nymegen Virginia 6543 VA",
    "addr:housenumber":"133;6543",
    "addr:street":"Nymegen Virginia",
    "iso:country":"NL",
    "sg:address":"Molenwg 133",
    "sg:city":"Nymegen",
    "sg:orig_category":"Autorijscholen",
    "sg:phone":"+31 24 377 0143",
    "sg:postcode":"6543 VA",
    "sg:province":"Virginia",
    "sg:website":"http://www.paullam.nl",
    "wof:name":"Paul Lam Bv",
    "wof:placetype":"venue"
},
  "geometry": {"coordinates":[-79.771446,38.003349],"type":"Point"}
}