{
  "type": "Feature",
  "properties": {
    "iso:country":"NL",
    "sg:address":"De Spade 3",
    "sg:city":"Heino",
    "sg:orig_category":"Administratie- En Boekhoudkantoren",
    "sg:phone":"+31 572 390 715",
    "sg:postcode":"8141 HJ",
    "sg:province":"Overijssel",
    "wof:name":"Jonker Evenboer, Hetty",
    "wof:placetype":"venue"
},
  "geometry": {"coordinates":[-95.398735,46.498905],"type":"Point"}
}