{
  "type": "Feature",
  "properties": {
    "addr:full":"Specht 10 Nieuwegein Utrecht 3435 CE",
    "addr:housenumber":"10",
    "addr:postcode":"3435 ce",
    "addr:street":"Specht",
    "iso:country":"NL",
    "sg:address":"Specht 10",
    "sg:city":"Nieuwegein",
    "sg:orig_category":"Hulpverlening Sociaal",
    "sg:phone":"+31 30 604 4202",
    "sg:postcode":"3435 CE",
    "sg:province":"Utrecht",
    "wof:name":"Doorslag, De",
    "wof:placetype":"venue"
},
  "geometry": {"coordinates":[5.078296,52.026001],"type":"Point"}
}