{
  "type": "Feature",
  "properties": {
    "addr:full":"Sourethwg 1 Heerlen Limburg 6422 PC",
    "addr:housenumber":"1",
    "addr:postcode":"6422 pc",
    "addr:street":"Sourethwg",
    "iso:country":"NL",
    "sg:address":"Sourethwg 1",
    "sg:city":"Heerlen",
    "sg:orig_category":"Arbo- En Bedrijfsgezondheids- Diensten",
    "sg:phone":"+31 45 541 0350",
    "sg:postcode":"6422 PC",
    "sg:province":"Limburg",
    "wof:name":"Ansil",
    "wof:placetype":"venue"
},
  "geometry": {"coordinates":[5.986758,50.850216],"type":"Point"}
}