{
  "type": "Feature",
  "properties": {
    "iso:country":"NL",
    "sg:address":"Kooikerspad 2",
    "sg:city":"Zoeterwoude",
    "sg:classifiers":[
        {
            "category":"Education",
            "subcategory":"Preschool",
            "type":"Public Place"
        }
    ],
    "sg:phone":"+31 71 542 1600",
    "sg:postcode":"2382 EA",
    "sg:province":"South Holland",
    "sg:tags":[
        "kleuteronderwijs",
        "basis-"
    ],
    "wof:name":"Bernardusschool",
    "wof:placetype":"venue"
},
  "geometry": {"coordinates":[4.522748,52.142521],"type":"Point"}
}