{
  "type": "Feature",
  "properties": {
    "addr:full":"J W Hagemanstraat 58 Eibergen Gelderland 7151 AH",
    "addr:housenumber":"58",
    "addr:postcode":"7151 ah",
    "addr:street":"W Hagemanstraat;Gelderland",
    "iso:country":"NL",
    "sg:address":"J W Hagemanstraat 58",
    "sg:city":"Eibergen",
    "sg:orig_category":"Artsen And Specialisten",
    "sg:phone":"+31 545 471 215",
    "sg:postcode":"7151 AH",
    "sg:province":"Gelderland",
    "wof:name":"H.L. Kwee",
    "wof:placetype":"venue"
},
  "geometry": {"coordinates":[6.651575,52.099358],"type":"Point"}
}