{
  "type": "Feature",
  "properties": {
    "addr:full":"Donker Curtiusstraat 2 Hoogezand Groningen 9602 PK",
    "addr:housenumber":"2",
    "addr:postcode":"9602 pk",
    "addr:street":"Donker Curtiusstraat",
    "iso:country":"NL",
    "sg:address":"Donker Curtiusstraat 2",
    "sg:city":"Hoogezand",
    "sg:classifiers":[
        {
            "category":"Education",
            "subcategory":"Preschool",
            "type":"Public Place"
        }
    ],
    "sg:phone":"+31 598 323 372",
    "sg:postcode":"9602 PK",
    "sg:province":"Groningen",
    "sg:tags":[
        "kleuteronderwijs",
        "basis-"
    ],
    "wof:name":"Gereformeerde Basisschool",
    "wof:placetype":"venue"
},
  "geometry": {"coordinates":[6.749386,53.155804],"type":"Point"}
}