{
  "type": "Feature",
  "properties": {
    "iso:country":"NL",
    "sg:address":"Hoofdweg 862",
    "sg:city":"Hoofddorp",
    "sg:orig_category":"Kinderopvang Behalve Thuis",
    "sg:phone":"+31 23 565 3860",
    "sg:postcode":"2132 MC",
    "sg:province":"Noord-Holland",
    "wof:name":"Kinderdagverblijf Twinkel",
    "wof:placetype":"venue"
},
  "geometry": {"coordinates":[4.675986,52.293526],"type":"Point"}
}