{
  "type": "Feature",
  "properties": {
    "addr:full":"Wiltonstraat 2 Zoetermeer South Holland 2722 NG",
    "addr:housenumber":"2",
    "addr:postcode":"2722 ng",
    "addr:street":"Wiltonstraat",
    "iso:country":"NL",
    "sg:address":"Wiltonstraat 2",
    "sg:city":"Zoetermeer",
    "sg:orig_category":"Diverse Grafische Activiteiten",
    "sg:phone":"+31 79 341 5171",
    "sg:postcode":"2722 NG",
    "sg:province":"South Holland",
    "wof:name":"Boekbinderij Van Der Kaay Coninck",
    "wof:placetype":"venue"
},
  "geometry": {"coordinates":[4.515489,52.051186],"type":"Point"}
}