{
  "type": "Feature",
  "properties": {
    "addr:full":"Rijksweg-West 50 Arnhem Gelderland 6842 BD",
    "addr:housenumber":"50",
    "addr:postcode":"6842 bd",
    "addr:street":"Rijksweg-West",
    "iso:country":"NL",
    "sg:address":"Rijksweg-West 50",
    "sg:city":"Arnhem",
    "sg:orig_category":"Overheidsdiensten",
    "sg:phone":"+31 26 381 4510",
    "sg:postcode":"6842 BD",
    "sg:province":"Gelderland",
    "wof:name":"Dorpshuis Elden",
    "wof:placetype":"venue"
},
  "geometry": {"coordinates":[5.8839101791,51.9597702026],"type":"Point"}
}