{
  "type": "Feature",
  "properties": {
    "addr:full":"Westerdreef 5V Nieuw Vennep Noord-Holland 2152 CS",
    "addr:housenumber":"5v",
    "addr:postcode":"2152 cs",
    "addr:street":"Westerdreef;Nieuw Vennep",
    "iso:country":"NL",
    "sg:address":"Westerdreef 5V",
    "sg:city":"Nieuw Vennep",
    "sg:orig_category":"Grafische Machines",
    "sg:phone":"+31 252 673 852",
    "sg:postcode":"2152 CS",
    "sg:province":"Noord-Holland",
    "sg:website":"http://www.grafiholland.nl",
    "wof:name":"Grafi-Holl Bv",
    "wof:placetype":"venue"
},
  "geometry": {"coordinates":[4.628588,52.270447],"type":"Point"}
}