{
  "type": "Feature",
  "properties": {
    "addr:full":"Ijsselstraat 1 Eindhoven Noord-Brabant 5626 BL",
    "addr:housenumber":"1",
    "addr:postcode":"5626 bl",
    "addr:street":"Ijsselstraat",
    "iso:country":"NL",
    "sg:address":"Ijsselstraat 1",
    "sg:city":"Eindhoven",
    "sg:orig_category":"Technische Studies And Onderzoek",
    "sg:phone":"+31 40 262 2175",
    "sg:postcode":"5626 BL",
    "sg:province":"Noord-Brabant",
    "wof:name":"Raadgevend Technische Buro J.T.M. Van De Poel Bv",
    "wof:placetype":"venue"
},
  "geometry": {"coordinates":[5.427286,51.479782],"type":"Point"}
}