{
  "type": "Feature",
  "properties": {
    "addr:full":"Kortendijk 2 Gorinchem Zuid-Holland 4201 KT",
    "addr:housenumber":"2",
    "addr:postcode":"4201 kt",
    "addr:street":"Kortendijk",
    "iso:country":"NL",
    "sg:address":"Kortendijk 2",
    "sg:city":"Gorinchem",
    "sg:orig_category":"Artiesten",
    "sg:phone":"+31 183 635 740",
    "sg:postcode":"4201 KT",
    "sg:province":"Zuid-Holland",
    "wof:name":"J Boom",
    "wof:placetype":"venue"
},
  "geometry": {"coordinates":[4.976554,51.830189],"type":"Point"}
}