{
  "type": "Feature",
  "properties": {
    "addr:full":"C.T. Storkweg 8 Assen Drenthe 9403 AG",
    "addr:housenumber":"8",
    "addr:postcode":"9403",
    "addr:street":"C.T. Storkweg",
    "iso:country":"NL",
    "sg:address":"C.T. Storkweg 8",
    "sg:city":"Assen",
    "sg:orig_category":"Autokeuringen",
    "sg:phone":"+31 592 318 701",
    "sg:postcode":"9403 AG",
    "sg:province":"Drenthe",
    "wof:name":"Garage Gellius Janssens",
    "wof:placetype":"venue"
},
  "geometry": {"coordinates":[6.573296,52.99868],"type":"Point"}
}