{
  "type": "Feature",
  "properties": {
    "addr:full":"Postwg 110 Lunteren Gelderland 6741 ML",
    "addr:housenumber":"110",
    "addr:postcode":"6741 ml",
    "addr:street":"Gelderland",
    "iso:country":"NL",
    "sg:address":"Postwg 110",
    "sg:city":"Lunteren",
    "sg:orig_category":"Kaas",
    "sg:phone":"+31 318 482 850",
    "sg:postcode":"6741 ML",
    "sg:province":"Gelderland",
    "wof:name":"Remeker",
    "wof:placetype":"venue"
},
  "geometry": {"coordinates":[5.5893850327,52.0895500183],"type":"Point"}
}