{
  "type": "Feature",
  "properties": {
    "iso:country":"NL",
    "sg:address":"Hoogstraat 6",
    "sg:city":"Harderwijk",
    "sg:orig_category":"Zalenexploitatie",
    "sg:phone":"+31 341 433 472",
    "sg:postcode":"3841 BS",
    "sg:province":"Gelderland",
    "wof:name":"Atelier Anna Rots",
    "wof:placetype":"venue"
},
  "geometry": {"coordinates":[5.617468,52.351116],"type":"Point"}
}