{
  "type": "Feature",
  "properties": {
    "addr:full":"Zeestr 71 S Gravenhage Zuid-Holland 2518 AA",
    "addr:housenumber":"71;gravenhage",
    "addr:postcode":"2518 aa",
    "addr:street":"Zeestr;S",
    "iso:country":"NL",
    "sg:address":"Zeestr 71",
    "sg:city":"S Gravenhage",
    "sg:orig_category":"Adviesbureaus",
    "sg:phone":"+31 70 365 3283",
    "sg:postcode":"2518 AA",
    "sg:province":"Zuid-Holland",
    "wof:name":"Hageman Van Hezik",
    "wof:placetype":"venue"
},
  "geometry": {"coordinates":[4.29348,52.080318],"type":"Point"}
}