{
  "type": "Feature",
  "properties": {
    "addr:full":"Den Ilp 33A Den Ilp North Holland 1127 PC",
    "addr:housenumber":"33a",
    "addr:postcode":"1127 pc",
    "addr:street":"Den Ilp",
    "iso:country":"NL",
    "sg:address":"Den Ilp 33A",
    "sg:city":"Den Ilp",
    "sg:orig_category":"Schilders",
    "sg:phone":"+31 20 482 2823",
    "sg:postcode":"1127 PC",
    "sg:province":"North Holland",
    "wof:name":"Boelhouwer",
    "wof:placetype":"venue"
},
  "geometry": {"coordinates":[4.909407,52.450638],"type":"Point"}
}