{
  "type": "Feature",
  "properties": {
    "addr:full":"Koningsvaren 51 Abcoude North Holland 1391 AE",
    "addr:housenumber":"51",
    "addr:postcode":"1391 ae",
    "addr:street":"Koningsvaren",
    "iso:country":"NL",
    "sg:address":"Koningsvaren 51",
    "sg:city":"Abcoude",
    "sg:orig_category":"Optiek - Fabrieken En Groothandel",
    "sg:phone":"+31 294 281 797",
    "sg:postcode":"1391 AE",
    "sg:province":"North Holland",
    "wof:name":"Amsterdam Eyewear Agency",
    "wof:placetype":"venue"
},
  "geometry": {"coordinates":[4.9692788124,52.2757301331],"type":"Point"}
}