{
  "type": "Feature",
  "properties": {
    "addr:full":"Meerwg 10 Kropswolde Groningen 9606 PN",
    "addr:housenumber":"10",
    "addr:postcode":"9606 pn",
    "addr:street":"Meerwg",
    "iso:country":"NL",
    "sg:address":"Meerwg 10",
    "sg:city":"Kropswolde",
    "sg:orig_category":"Adviesbureaus Bedrijfsorganisatie",
    "sg:phone":"+31 598 320 518",
    "sg:postcode":"9606 PN",
    "sg:province":"Groningen",
    "wof:name":"Kocon Bv",
    "wof:placetype":"venue"
},
  "geometry": {"coordinates":[6.705807,53.144047],"type":"Point"}
}