{
  "type": "Feature",
  "properties": {
    "addr:full":"Koekoekstr 66 Sprundel Noord-Brabant 4714 AL",
    "addr:housenumber":"66",
    "addr:postcode":"4714 al",
    "addr:street":"Koekoekstr",
    "iso:country":"NL",
    "sg:address":"Koekoekstr 66",
    "sg:city":"Sprundel",
    "sg:orig_category":"Kappers",
    "sg:phone":"+31 165 382 714",
    "sg:postcode":"4714 AL",
    "sg:province":"Noord-Brabant",
    "wof:name":"Bruijn, H De",
    "wof:placetype":"venue"
},
  "geometry": {"coordinates":[4.590113163,51.5402641296],"type":"Point"}
}