{
  "type": "Feature",
  "properties": {
    "addr:full":"Winkelcentrum Woensel 79 Eindhoven Noord-Brabant 5625 AD",
    "addr:housenumber":"79",
    "addr:postcode":"5625 ad",
    "addr:street":"Winkelcentrum Woensel",
    "iso:country":"NL",
    "sg:address":"Winkelcentrum Woensel 79",
    "sg:city":"Eindhoven",
    "sg:orig_category":"Wasserettes And Stomerijen",
    "sg:phone":"+31 40 248 1204",
    "sg:postcode":"5625 AD",
    "sg:province":"Noord-Brabant",
    "wof:name":"Stomerij Verhagen Bv",
    "wof:placetype":"venue"
},
  "geometry": {"coordinates":[5.4769082069,51.4706497192],"type":"Point"}
}