{
  "type": "Feature",
  "properties": {
    "addr:full":"Triangel 1 Rotterdam Zuid-Holland 3068 HT",
    "addr:housenumber":"1",
    "addr:postcode":"3068 ht",
    "addr:street":"Triangel",
    "iso:country":"NL",
    "sg:address":"Triangel 1",
    "sg:city":"Rotterdam",
    "sg:orig_category":"Verzekeringen - Verzekeringskantoren",
    "sg:phone":"+31 10 456 2887",
    "sg:postcode":"3068 HT",
    "sg:province":"Zuid-Holland",
    "wof:name":"Savert",
    "wof:placetype":"venue"
},
  "geometry": {"coordinates":[4.563746,51.962425],"type":"Point"}
}