{
  "type": "Feature",
  "properties": {
    "iso:country":"NL",
    "sg:address":"Bernardusplein 35",
    "sg:city":"Tilburg",
    "sg:orig_category":"Zuivelproducten",
    "sg:phone":"+31 13 468 1567",
    "sg:postcode":"5042 HR",
    "sg:province":"Noord-Brabant",
    "wof:name":"Kaasshop 'T Boerke",
    "wof:placetype":"venue"
},
  "geometry": {"coordinates":[5.059771,51.570683],"type":"Point"}
}