{
  "type": "Feature",
  "properties": {
    "addr:full":"J V Aalderenln 9 Hoogeveen Provincie Drenthe 7908 HC",
    "addr:housenumber":"9",
    "addr:postcode":"7908 hc",
    "addr:street":"J;Aalderenln;Provincie",
    "iso:country":"NL",
    "sg:address":"J V Aalderenln 9",
    "sg:city":"Hoogeveen",
    "sg:orig_category":"Fotoreportages",
    "sg:phone":"+31 528 235 833",
    "sg:postcode":"7908 HC",
    "sg:province":"Provincie Drenthe",
    "wof:name":"Gerrit Boer Fotostudio",
    "wof:placetype":"venue"
},
  "geometry": {"coordinates":[6.47552,52.725975],"type":"Point"}
}