{
  "type": "Feature",
  "properties": {
    "addr:full":"Huismanshof 30Hs Amsterdam Noord-Holland 1097 TH",
    "addr:housenumber":"30hs",
    "addr:postcode":"1097 th",
    "addr:street":"Huismanshof",
    "iso:country":"NL",
    "sg:address":"Huismanshof 30Hs",
    "sg:city":"Amsterdam",
    "sg:orig_category":"Voetbalverenigingen",
    "sg:phone":"+31 20 694 9521",
    "sg:postcode":"1097 TH",
    "sg:province":"Noord-Holland",
    "wof:name":"Amsterdam Zvv",
    "wof:placetype":"venue"
},
  "geometry": {"coordinates":[4.941937,52.341438],"type":"Point"}
}