{
  "type": "Feature",
  "properties": {
    "iso:country":"NL",
    "sg:address":"Sint Elisabethstraat 91",
    "sg:city":"Vught",
    "sg:orig_category":"Gespecialiseerde Bouw",
    "sg:phone":"+31 73 656 7699",
    "sg:postcode":"5261 VL",
    "sg:province":"Noord-Brabant",
    "wof:name":"Betonboor En Hakbedrijf H. Robben",
    "wof:placetype":"venue"
},
  "geometry": {"coordinates":[5.292737,51.652763],"type":"Point"}
}