{
  "type": "Feature",
  "properties": {
    "addr:full":"Meelstr 25 Zierikzee Zeeland 4301 EA",
    "addr:housenumber":"25",
    "addr:postcode":"4301 ea",
    "addr:street":"Meelstr",
    "iso:country":"NL",
    "sg:address":"Meelstr 25",
    "sg:city":"Zierikzee",
    "sg:orig_category":"Artsen - Huisartsen",
    "sg:phone":"+31 111 413 965",
    "sg:postcode":"4301 EA",
    "sg:province":"Zeeland",
    "wof:name":"Visser, J B",
    "wof:placetype":"venue"
},
  "geometry": {"coordinates":[3.918085,51.650337],"type":"Point"}
}