{
  "type": "Feature",
  "properties": {
    "addr:full":"Spitsenhagen 15 Rotterdam South Holland 3078 BM",
    "addr:housenumber":"15",
    "addr:postcode":"3078 bm",
    "addr:street":"Spitsenhagen",
    "iso:country":"NL",
    "sg:address":"Spitsenhagen 15",
    "sg:city":"Rotterdam",
    "sg:classifiers":[
        {
            "category":"Food & Beverages",
            "subcategory":"Bakery",
            "type":"Retail Goods"
        }
    ],
    "sg:phone":"+31 10 479 6970",
    "sg:postcode":"3078 BM",
    "sg:province":"South Holland",
    "sg:tags":[
        "pizza"
    ],
    "wof:name":"Shemshaak",
    "wof:placetype":"venue"
},
  "geometry": {"coordinates":[4.558806,51.887081],"type":"Point"}
}