{
  "type": "Feature",
  "properties": {
    "iso:country":"NL",
    "sg:address":"Ln V Schondeln 8",
    "sg:city":"Roermond",
    "sg:orig_category":"Product-Promotie",
    "sg:phone":"+31 475 343 309",
    "sg:postcode":"6045 CZ",
    "sg:province":"Limburg",
    "wof:name":"Promocon",
    "wof:placetype":"venue"
},
  "geometry": {"coordinates":[6.005031,51.167408],"type":"Point"}
}