{
  "type": "Feature",
  "properties": {
    "addr:full":"Ysseldk N 286 Ouderkerk Ad Yssel Zuid-Holland 2935 CP",
    "addr:housenumber":"286;2935",
    "addr:postcode":"cp",
    "addr:street":"N",
    "iso:country":"NL",
    "sg:address":"Ysseldk N 286",
    "sg:city":"Ouderkerk Ad Yssel",
    "sg:orig_category":"Scheepvaartmijen",
    "sg:phone":"+31 180 683 068",
    "sg:postcode":"2935 CP",
    "sg:province":"Zuid-Holland",
    "wof:name":"Jong, T De",
    "wof:placetype":"venue"
},
  "geometry": {"coordinates":[4.637585,51.932926],"type":"Point"}
}