{
  "type": "Feature",
  "properties": {
    "addr:full":"Postbus 43015 S Gravenhage Zeeland 2504 AA",
    "addr:housenumber":"43015",
    "addr:postcode":"2504 aa",
    "addr:street":"Postbus;S Gravenhage Zeeland",
    "iso:country":"NL",
    "sg:address":"Postbus 43015",
    "sg:city":"S Gravenhage",
    "sg:orig_category":"Woningbouw- Verenigingen En -Stichtingen",
    "sg:phone":"+31 70 321 5353",
    "sg:postcode":"2504 AA",
    "sg:province":"Zeeland",
    "wof:name":"Vestia Den Haag Zw",
    "wof:placetype":"venue"
},
  "geometry": {"coordinates":[4.3136100769,52.0783195496],"type":"Point"}
}