{
  "type": "Feature",
  "properties": {
    "addr:full":"A Thymstr 1 Venlo Limburg 5921 BA",
    "addr:housenumber":"1",
    "addr:postcode":"5921 ba",
    "iso:country":"NL",
    "sg:address":"A Thymstr 1",
    "sg:city":"Venlo",
    "sg:orig_category":"Artsen - Huisartsen",
    "sg:phone":"+31 77 387 1980",
    "sg:postcode":"5921 BA",
    "sg:province":"Limburg",
    "wof:name":"Hegeman, J B M",
    "wof:placetype":"venue"
},
  "geometry": {"coordinates":[6.14838,51.366421],"type":"Point"}
}