{
  "type": "Feature",
  "properties": {
    "addr:full":"Katwykerbroek 75 Katwyk Zh Zuid-Holland 2223 XN",
    "addr:housenumber":"75",
    "addr:postcode":"2223 xn",
    "addr:street":"Katwykerbroek",
    "iso:country":"NL",
    "sg:address":"Katwykerbroek 75",
    "sg:city":"Katwyk Zh",
    "sg:orig_category":"Keukens",
    "sg:phone":"+31 71 401 7121",
    "sg:postcode":"2223 XN",
    "sg:province":"Zuid-Holland",
    "sg:website":"http://www.portas.nl",
    "wof:name":"Portas Katwijk",
    "wof:placetype":"venue"
},
  "geometry": {"coordinates":[4.41584,52.18483],"type":"Point"}
}