{
  "type": "Feature",
  "properties": {
    "addr:full":"Helmln 23 Heemskerk Noord-Holland 1964 PH",
    "addr:housenumber":"23",
    "addr:postcode":"1964",
    "addr:street":"Helmln",
    "iso:country":"NL",
    "sg:address":"Helmln 23",
    "sg:city":"Heemskerk",
    "sg:classifiers":[
        {
            "category":"Food & Beverages",
            "subcategory":"Bakery",
            "type":"Retail Goods"
        }
    ],
    "sg:phone":"+31 251 247 875",
    "sg:postcode":"1964 PH",
    "sg:province":"Noord-Holland",
    "sg:tags":[
        "pizza"
    ],
    "wof:name":"Mamma Mia",
    "wof:placetype":"venue"
},
  "geometry": {"coordinates":[4.655393,52.507622],"type":"Point"}
}