{
  "type": "Feature",
  "properties": {
    "addr:full":"Isingstr 32 S Gravenhage Zuid-Holland 2522 JZ",
    "addr:housenumber":"32;gravenhage",
    "addr:postcode":"2522 jz",
    "addr:street":"Isingstr;S",
    "iso:country":"NL",
    "sg:address":"Isingstr 32",
    "sg:city":"S Gravenhage",
    "sg:orig_category":"Horecabenodigdheden",
    "sg:phone":"+31 70 390 6663",
    "sg:postcode":"2522 JZ",
    "sg:province":"Zuid-Holland",
    "wof:name":"Rimboe Vof",
    "wof:placetype":"venue"
},
  "geometry": {"coordinates":[4.32729,52.060848],"type":"Point"}
}