{
  "type": "Feature",
  "properties": {
    "iso:country":"NL",
    "sg:address":"Lattropperstraat 50",
    "sg:city":"Denekamp",
    "sg:orig_category":"Boekhouders",
    "sg:phone":"+31 541 354 470",
    "sg:postcode":"7591 PK",
    "sg:province":"NL.08",
    "wof:name":"Leus Administraties",
    "wof:placetype":"venue"
},
  "geometry": {"coordinates":[7.001406,52.384266],"type":"Point"}
}