{
  "type": "Feature",
  "properties": {
    "addr:full":"Horstln 10 Driebergen Rysenb Utrecht 3971 LC",
    "addr:housenumber":"10",
    "addr:postcode":"3971",
    "addr:street":"Horstln;Rysenb",
    "iso:country":"NL",
    "sg:address":"Horstln 10",
    "sg:city":"Driebergen Rysenb",
    "sg:orig_category":"Elektrotechnische Installatiebureaus",
    "sg:phone":"+31 343 515 123",
    "sg:postcode":"3971 LC",
    "sg:province":"Utrecht",
    "wof:name":"Buitendijk",
    "wof:placetype":"venue"
},
  "geometry": {"coordinates":[5.30052,52.065571],"type":"Point"}
}