{
  "type": "Feature",
  "properties": {
    "addr:full":"Stouwewg 33 Zwartsluis Overijssel 8064 PD",
    "addr:housenumber":"33",
    "addr:postcode":"8064 pd",
    "addr:street":"Stouwewg",
    "iso:country":"NL",
    "sg:address":"Stouwewg 33",
    "sg:city":"Zwartsluis",
    "sg:orig_category":"Jachthavens - Jachtwerven",
    "sg:phone":"+31 38 386 7145",
    "sg:postcode":"8064 PD",
    "sg:province":"Overijssel",
    "sg:website":"http://www.vitters.com",
    "wof:name":"Vitters Shipyard Bv",
    "wof:placetype":"venue"
},
  "geometry": {"coordinates":[6.09557,52.648472],"type":"Point"}
}