{
  "type": "Feature",
  "properties": {
    "addr:full":"Acacialn 2 Bennekom Gelderland 6721 CP",
    "addr:housenumber":"2",
    "addr:postcode":"6721 cp",
    "addr:street":"Acacialn;Gelderland",
    "iso:country":"NL",
    "sg:address":"Acacialn 2",
    "sg:city":"Bennekom",
    "sg:orig_category":"Accountants - Administratie- Consulenten En -Kantoren",
    "sg:phone":"+31 318 417 012",
    "sg:postcode":"6721 CP",
    "sg:province":"Gelderland",
    "wof:name":"Alfa Bv",
    "wof:placetype":"venue"
},
  "geometry": {"coordinates":[5.675792,52.000942],"type":"Point"}
}