{
  "type": "Feature",
  "properties": {
    "addr:full":"K Zevensterstr 6 Hoogvliet Rt Zuid-Holland 3193 TW",
    "addr:housenumber":"6",
    "addr:postcode":"rt;3193 tw",
    "addr:street":"Zevensterstr",
    "iso:country":"NL",
    "sg:address":"K Zevensterstr 6",
    "sg:city":"Hoogvliet Rt",
    "sg:orig_category":"Verenigingen En Stichtingen",
    "sg:phone":"+31 10 283 2900",
    "sg:postcode":"3193 TW",
    "sg:province":"Zuid-Holland",
    "wof:name":"Dsg/Aangepast Vervoer Hoogvliet",
    "wof:placetype":"venue"
},
  "geometry": {"coordinates":[4.352561,51.868172],"type":"Point"}
}