{
  "type": "Feature",
  "properties": {
    "iso:country":"NL",
    "sg:address":"Veerseweg 61",
    "sg:city":"Oosterhout Nb",
    "sg:orig_category":"Hypotheken And Hypotheekbanken",
    "sg:phone":"+31 162 435 941",
    "sg:postcode":"4901 ZD",
    "sg:province":"Noord-Brabant",
    "wof:name":"Drs P. Linders Consultancy Bv",
    "wof:placetype":"venue"
},
  "geometry": {"coordinates":[4.872771,51.646404],"type":"Point"}
}