{
  "type": "Feature",
  "properties": {
    "addr:full":"Flevoln 25/A Weesp Noord-Holland 1382 JX",
    "addr:housenumber":"25 / a",
    "addr:postcode":"1382 jx",
    "addr:street":"Flevoln",
    "iso:country":"NL",
    "sg:address":"Flevoln 25/A",
    "sg:city":"Weesp",
    "sg:orig_category":"Handwerkartikelen - Fabrieken En Groothandel",
    "sg:phone":"+31 294 415 070",
    "sg:postcode":"1382 JX",
    "sg:province":"Noord-Holland",
    "sg:website":"http://www.pako.nl",
    "wof:name":"Pako Bv",
    "wof:placetype":"venue"
},
  "geometry": {"coordinates":[5.03828,52.308315],"type":"Point"}
}