{
  "type": "Feature",
  "properties": {
    "addr:full":"J De Rooystr 14 Overloon Noord-Brabant 5825 BN",
    "addr:housenumber":"14",
    "addr:postcode":"5825 bn",
    "addr:street":"J De Rooystr",
    "iso:country":"NL",
    "sg:address":"J De Rooystr 14",
    "sg:city":"Overloon",
    "sg:orig_category":"Satellietontvangst- En Antenne-Installaties",
    "sg:phone":"+31 478 642 268",
    "sg:postcode":"5825 BN",
    "sg:province":"Noord-Brabant",
    "wof:name":"Spreeuwenberg-Jenniskens Vof",
    "wof:placetype":"venue"
},
  "geometry": {"coordinates":[5.94631,51.571255],"type":"Point"}
}