{
  "type": "Feature",
  "properties": {
    "addr:full":"Cabeljaustraat 5 Alkmaar North Holland 1815 GD",
    "addr:housenumber":"5",
    "addr:postcode":"1815 gd",
    "addr:street":"Cabeljaustraat",
    "iso:country":"NL",
    "sg:address":"Cabeljaustraat 5",
    "sg:city":"Alkmaar",
    "sg:orig_category":"Paramedische Behandelingen",
    "sg:phone":"+31 72 511 0407",
    "sg:postcode":"1815 GD",
    "sg:province":"North Holland",
    "wof:name":"R.M. Porck",
    "wof:placetype":"venue"
},
  "geometry": {"coordinates":[4.738514,52.632736],"type":"Point"}
}