{
  "type": "Feature",
  "properties": {
    "addr:full":"Binnenveer 2 Weesp Noord-Holland 1381 BT",
    "addr:housenumber":"2",
    "addr:postcode":"1381 bt",
    "addr:street":"Binnenveer",
    "iso:country":"NL",
    "sg:address":"Binnenveer 2",
    "sg:city":"Weesp",
    "sg:orig_category":"Juridische Dienstverlening",
    "sg:phone":"+31 294 483 355",
    "sg:postcode":"1381 BT",
    "sg:province":"Noord-Holland",
    "wof:name":"Swbc Amsterdam Bv",
    "wof:placetype":"venue"
},
  "geometry": {"coordinates":[5.039276,52.308327],"type":"Point"}
}