{
  "type": "Feature",
  "properties": {
    "addr:full":"St Nicolailn 1 Arnhem Gelderland 6821 HL",
    "addr:housenumber":"1",
    "addr:postcode":"6821 hl",
    "iso:country":"NL",
    "sg:address":"St Nicolailn 1",
    "sg:city":"Arnhem",
    "sg:orig_category":"Verenigingen En Stichtingen",
    "sg:phone":"+31 26 389 5022",
    "sg:postcode":"6821 HL",
    "sg:province":"Gelderland",
    "sg:website":"http://www.forasreizen.nl",
    "wof:name":"Foras, St",
    "wof:placetype":"venue"
},
  "geometry": {"coordinates":[5.911916,51.990288],"type":"Point"}
}