{
  "type": "Feature",
  "properties": {
    "addr:full":"Ommelanderwijk 8 Veendam Groningen 9644 TL",
    "addr:housenumber":"8",
    "addr:postcode":"9644 tl",
    "addr:street":"Ommelanderwijk",
    "iso:country":"NL",
    "sg:address":"Ommelanderwijk 8",
    "sg:city":"Veendam",
    "sg:classifiers":[
        {
            "category":"Parking",
            "subcategory":"Lot",
            "type":"Transportation"
        }
    ],
    "sg:phone":"+31 598 666 900",
    "sg:postcode":"9644 TL",
    "sg:province":"Groningen",
    "sg:tags":[
        "fab",
        "metalen",
        "tank"
    ],
    "wof:name":"Koop Materieel Bv",
    "wof:placetype":"venue"
},
  "geometry": {"coordinates":[6.895737,53.093704],"type":"Point"}
}