{
  "type": "Feature",
  "properties": {
    "addr:full":"Tongelresestr 445A Eindhoven North Brabant 5641 AW",
    "addr:housenumber":"445a",
    "addr:postcode":"5641 aw",
    "iso:country":"NL",
    "sg:address":"Tongelresestr 445A",
    "sg:city":"Eindhoven",
    "sg:orig_category":"Keukens",
    "sg:phone":"+31 40 281 9526",
    "sg:postcode":"5641 AW",
    "sg:province":"North Brabant",
    "sg:website":"http://www.maat-keuken.nl",
    "wof:name":"Maat Keuken",
    "wof:placetype":"venue"
},
  "geometry": {"coordinates":[5.513873,51.44553],"type":"Point"}
}