{
  "type": "Feature",
  "properties": {
    "addr:full":"Hoofdstraat Obergum 8 Winsum Gn Groningen 9951 AH",
    "addr:housenumber":"8",
    "addr:postcode":"gn;9951 ah",
    "addr:street":"Hoofdstraat Obergum",
    "iso:country":"NL",
    "sg:address":"Hoofdstraat Obergum 8",
    "sg:city":"Winsum Gn",
    "sg:orig_category":"Opticiens",
    "sg:phone":"+31 595 444 069",
    "sg:postcode":"9951 AH",
    "sg:province":"Groningen",
    "wof:name":"Engelsman Optiek",
    "wof:placetype":"venue"
},
  "geometry": {"coordinates":[6.5149769783,53.332862854],"type":"Point"}
}