{
  "type": "Feature",
  "properties": {
    "iso:country":"NL",
    "sg:address":"Willemstr 27A",
    "sg:city":"Hengelo Ov",
    "sg:orig_category":"Verzekeringen - Verzekeringskantoren",
    "sg:phone":"+31 74 255 8100",
    "sg:postcode":"7551 DL",
    "sg:province":"NL.08",
    "wof:name":"Spelt & Mastenbroek Bv",
    "wof:placetype":"venue"
},
  "geometry": {"coordinates":[6.789712,52.266361],"type":"Point"}
}