{
  "type": "Feature",
  "properties": {
    "iso:country":"NL",
    "sg:address":"Stationsstraat 37",
    "sg:city":"Gieten",
    "sg:orig_category":"Boekenuitgeverijen",
    "sg:phone":"+31 592 261 311",
    "sg:postcode":"9461  G",
    "sg:province":"Provincie Drenthe",
    "wof:name":"Bruna",
    "wof:placetype":"venue"
},
  "geometry": {"coordinates":[6.764623,53.001965],"type":"Point"}
}