{
  "type": "Feature",
  "properties": {
    "addr:full":"Zomerweg 145 Enschede Overijssel 7532 RB",
    "addr:housenumber":"145",
    "addr:postcode":"7532 rb",
    "addr:street":"Zomerweg",
    "iso:country":"NL",
    "sg:address":"Zomerweg 145",
    "sg:city":"Enschede",
    "sg:orig_category":"Metaalbekleding And -Behandeling",
    "sg:phone":"+31 53 461 5417",
    "sg:postcode":"7532 RB",
    "sg:province":"Overijssel",
    "wof:name":"Slijptechniek Nederland Vof",
    "wof:placetype":"venue"
},
  "geometry": {"coordinates":[6.944471,52.223118],"type":"Point"}
}