{
  "type": "Feature",
  "properties": {
    "addr:full":"Beertsterstr 33 Winschoten Groningen 9671 BK",
    "addr:housenumber":"33",
    "addr:postcode":"9671 bk",
    "addr:street":"Beertsterstr",
    "iso:country":"NL",
    "sg:address":"Beertsterstr 33",
    "sg:city":"Winschoten",
    "sg:orig_category":"Autorijscholen",
    "sg:phone":"+31 597 414 983",
    "sg:postcode":"9671 BK",
    "sg:province":"Groningen",
    "wof:name":"Rotgers, H",
    "wof:placetype":"venue"
},
  "geometry": {"coordinates":[7.043437,53.142799],"type":"Point"}
}