{
  "type": "Feature",
  "properties": {
    "addr:full":"Rijksstraatweg 232 Hellevoetsluis Zuid-Holland 3223 KD",
    "addr:housenumber":"232",
    "addr:postcode":"3223 kd",
    "addr:street":"Rijksstraatweg",
    "iso:country":"NL",
    "sg:address":"Rijksstraatweg 232",
    "sg:city":"Hellevoetsluis",
    "sg:orig_category":"Verlichting And Huishoudartikelen",
    "sg:phone":"+31 181 312 384",
    "sg:postcode":"3223 KD",
    "sg:province":"Zuid-Holland",
    "wof:name":"C Van Der Sijde Vof",
    "wof:placetype":"venue"
},
  "geometry": {"coordinates":[4.139181,51.845009],"type":"Point"}
}