{
  "type": "Feature",
  "properties": {
    "addr:full":"Benedenweg 280 Sint Pancras North Holland 1834 BC",
    "addr:housenumber":"280",
    "addr:postcode":"1834 bc",
    "addr:street":"Benedenweg",
    "iso:country":"NL",
    "sg:address":"Benedenweg 280",
    "sg:city":"Sint Pancras",
    "sg:orig_category":"Bloemen And Planten Gh",
    "sg:phone":"+31 72 562 3507",
    "sg:postcode":"1834 BC",
    "sg:province":"North Holland",
    "wof:name":"Hesca Handelsonderneming",
    "wof:placetype":"venue"
},
  "geometry": {"coordinates":[4.778422,52.653858],"type":"Point"}
}