{
  "type": "Feature",
  "properties": {
    "addr:full":"Amstelstraat 7 Bergen Op Zoom Noord-Brabant 4615 BX",
    "addr:housenumber":"7",
    "addr:postcode":"4615 bx",
    "addr:street":"Amstelstraat",
    "iso:country":"NL",
    "sg:address":"Amstelstraat 7",
    "sg:city":"Bergen Op Zoom",
    "sg:orig_category":"Verhuur Audiovisuele Apparatuur",
    "sg:phone":"+31 164 243 616",
    "sg:postcode":"4615 BX",
    "sg:province":"Noord-Brabant",
    "wof:name":"A.A.M. Van Egeraat",
    "wof:placetype":"venue"
},
  "geometry": {"coordinates":[4.2835907936,51.4852790833],"type":"Point"}
}