{
  "type": "Feature",
  "properties": {
    "iso:country":"NL",
    "sg:address":"Zenegroenkd 2",
    "sg:city":"Haarlem",
    "sg:orig_category":"Adviesbureaus Economie",
    "sg:phone":"+31 23 524 4500",
    "sg:postcode":"2015 KV",
    "sg:province":"Noord-Holland",
    "wof:name":"Kwaliteitskransen Ned, Sticht",
    "wof:placetype":"venue"
},
  "geometry": {"coordinates":[4.60896,52.371223],"type":"Point"}
}