{
  "type": "Feature",
  "properties": {
    "addr:full":"De Limiet 26B Vianen Ut South Holland 4131 NR",
    "addr:housenumber":"26b",
    "addr:postcode":"4131 nr",
    "addr:street":"De Limiet",
    "iso:country":"NL",
    "sg:address":"De Limiet 26B",
    "sg:city":"Vianen Ut",
    "sg:orig_category":"Verlichting",
    "sg:phone":"+31 347 343 700",
    "sg:postcode":"4131 NR",
    "sg:province":"South Holland",
    "wof:name":"Hellux Benelux",
    "wof:placetype":"venue"
},
  "geometry": {"coordinates":[5.087717,51.973885],"type":"Point"}
}