{
  "type": "Feature",
  "properties": {
    "iso:country":"NL",
    "sg:address":"De Limiet 26B",
    "sg:city":"Vianen Ut",
    "sg:orig_category":"Verlichting",
    "sg:phone":"+31 347 343 700",
    "sg:postcode":"4131 NR",
    "sg:province":"South Holland",
    "wof:name":"Hellux Benelux",
    "wof:placetype":"venue"
},
  "geometry": {"coordinates":[5.087717,51.973885],"type":"Point"}
}