{
  "type": "Feature",
  "properties": {
    "addr:full":"Industrieweg 13 Harderwijk Gelderland 3846 BB",
    "addr:housenumber":"13",
    "addr:postcode":"3846 bb",
    "addr:street":"Industrieweg;Gelderland",
    "iso:country":"NL",
    "sg:address":"Industrieweg 13",
    "sg:city":"Harderwijk",
    "sg:orig_category":"Drukkerijen And Copyshops",
    "sg:phone":"+31 341 412 501",
    "sg:postcode":"3846 BB",
    "sg:province":"Gelderland",
    "wof:name":"Drukkerij Wedding Bv",
    "wof:placetype":"venue"
},
  "geometry": {"coordinates":[5.636712,52.355625],"type":"Point"}
}