{
  "type": "Feature",
  "properties": {
    "addr:full":"Cornelisstr 78 Rood Haarlem Noord-Holland 2023 DK",
    "addr:housenumber":"78",
    "addr:postcode":"2023 dk",
    "addr:street":"Cornelisstr;Rood",
    "iso:country":"NL",
    "sg:address":"Cornelisstr 78 Rood",
    "sg:city":"Haarlem",
    "sg:orig_category":"Onderhoudswerken",
    "sg:phone":"+31 23 526 3870",
    "sg:postcode":"2023 DK",
    "sg:province":"Noord-Holland",
    "wof:name":"Roode, T J Van",
    "wof:placetype":"venue"
},
  "geometry": {"coordinates":[4.63421,52.39629],"type":"Point"}
}