{
  "type": "Feature",
  "properties": {
    "addr:full":"Wielstr 88 Beneden Leeuwen Gelderland 6658 BE",
    "addr:housenumber":"88",
    "addr:postcode":"6658",
    "addr:street":"Wielstr",
    "iso:country":"NL",
    "sg:address":"Wielstr 88",
    "sg:city":"Beneden Leeuwen",
    "sg:orig_category":"Acupunctuur",
    "sg:phone":"+31 487 591 016",
    "sg:postcode":"6658 BE",
    "sg:province":"Gelderland",
    "wof:name":"Snethorst Hans",
    "wof:placetype":"venue"
},
  "geometry": {"coordinates":[5.508735,51.88295],"type":"Point"}
}