{
  "type": "Feature",
  "properties": {
    "addr:full":"N Maesstr 94 Ede Gld Gelderland 6717 SW",
    "addr:housenumber":"94;6717",
    "addr:street":"N;Gld Gelderland;Sw",
    "iso:country":"NL",
    "sg:address":"N Maesstr 94",
    "sg:city":"Ede Gld",
    "sg:orig_category":"Verenigingen En Stichtingen",
    "sg:phone":"+31 318 645 209",
    "sg:postcode":"6717 SW",
    "sg:province":"Gelderland",
    "wof:name":"Alg Computer Club 85",
    "wof:placetype":"venue"
},
  "geometry": {"coordinates":[5.66767,52.044979],"type":"Point"}
}