{
  "type": "Feature",
  "properties": {
    "addr:full":"Asselsestraat 275/2 Apeldoorn Gelderland 7312 CV",
    "addr:housenumber":"275 / 2",
    "addr:postcode":"7312 cv",
    "addr:street":"Asselsestraat;Gelderland",
    "iso:country":"NL",
    "sg:address":"Asselsestraat 275/2",
    "sg:city":"Apeldoorn",
    "sg:orig_category":"Muziekinstrumenten",
    "sg:phone":"+31 53 355 7356",
    "sg:postcode":"7312 CV",
    "sg:province":"Gelderland",
    "wof:name":"Muziekhuis Gert Nijkamp",
    "wof:placetype":"venue"
},
  "geometry": {"coordinates":[5.939978,52.208271],"type":"Point"}
}