{
  "type": "Feature",
  "properties": {
    "addr:full":"Dorpsstraat 18 Nieuw Roden Drenthe 9311 PT",
    "addr:housenumber":"18",
    "addr:postcode":"9311 pt",
    "addr:street":"Dorpsstraat;Nieuw",
    "iso:country":"NL",
    "sg:address":"Dorpsstraat 18",
    "sg:city":"Nieuw Roden",
    "sg:orig_category":"Meubelreparatie And -Restauratie",
    "sg:phone":"+31 50 501 5086",
    "sg:postcode":"9311 PT",
    "sg:province":"Drenthe",
    "wof:name":"Meubelstoffeerderij Jeepee",
    "wof:placetype":"venue"
},
  "geometry": {"coordinates":[6.39768,53.130726],"type":"Point"}
}