{
  "type": "Feature",
  "properties": {
    "addr:full":"Una Corda 33 Krimpen Ad Yssel Zuid-Holland 2925 BW",
    "addr:housenumber":"33",
    "addr:postcode":"2925 bw",
    "addr:street":"Corda",
    "iso:country":"NL",
    "sg:address":"Una Corda 33",
    "sg:city":"Krimpen Ad Yssel",
    "sg:orig_category":"Beveiliging",
    "sg:phone":"+31 180 511 472",
    "sg:postcode":"2925 BW",
    "sg:province":"Zuid-Holland",
    "wof:name":"Sab",
    "wof:placetype":"venue"
},
  "geometry": {"coordinates":[4.610081,51.920525],"type":"Point"}
}