{
  "type": "Feature",
  "properties": {
    "iso:country":"NL",
    "sg:address":"Oude Raadhuispln 3",
    "sg:city":"Huizen",
    "sg:orig_category":"Juweliers",
    "sg:phone":"+31 35 525 1687",
    "sg:postcode":"1271 RH",
    "sg:province":"Noord-Holland",
    "wof:name":"Pampus, Van",
    "wof:placetype":"venue"
},
  "geometry": {"coordinates":[5.235417,52.29784],"type":"Point"}
}