{
  "type": "Feature",
  "properties": {
    "addr:full":"Schoterlandsewg 40 Nieuwehorne Friesland 8414 LX",
    "addr:housenumber":"40",
    "addr:postcode":"8414 lx",
    "addr:street":"Schoterlandsewg",
    "iso:country":"NL",
    "sg:address":"Schoterlandsewg 40",
    "sg:city":"Nieuwehorne",
    "sg:orig_category":"Wasmachines En Wasdrogers",
    "sg:phone":"+31 513 541 270",
    "sg:postcode":"8414 LX",
    "sg:province":"Friesland",
    "wof:name":"Pewe",
    "wof:placetype":"venue"
},
  "geometry": {"coordinates":[6.0574331284,52.950756073],"type":"Point"}
}