{
  "type": "Feature",
  "properties": {
    "addr:full":"De Wetering 21 Oosterhout Nb North Brabant 4906 CT",
    "addr:housenumber":"21;nb",
    "addr:postcode":"4906 ct",
    "addr:street":"De Wetering",
    "iso:country":"NL",
    "sg:address":"De Wetering 21",
    "sg:city":"Oosterhout Nb",
    "sg:orig_category":"Weegbruggen",
    "sg:phone":"+31 162 430 450",
    "sg:postcode":"4906 CT",
    "sg:province":"North Brabant",
    "sg:website":"http://www.pfister.nl",
    "wof:name":"Pfister Weegtechniek Bv",
    "wof:placetype":"venue"
},
  "geometry": {"coordinates":[4.845056057,51.6530380249],"type":"Point"}
}