{
  "type": "Feature",
  "properties": {
    "iso:country":"NL",
    "sg:address":"Struvestr 2",
    "sg:city":"Hilversum",
    "sg:orig_category":"Koeriersdiensten",
    "sg:phone":"+31 35 683 1238",
    "sg:postcode":"1223 EC",
    "sg:province":"Noord-Holland",
    "wof:name":"Private Drive",
    "wof:placetype":"venue"
},
  "geometry": {"coordinates":[5.195163,52.226513],"type":"Point"}
}