{
  "type": "Feature",
  "properties": {
    "addr:full":"Van Egmondstraat 82 'S Gravenhage South Holland 2581 XM",
    "addr:housenumber":"82",
    "addr:postcode":"2581 xm",
    "addr:street":"Van Egmondstraat;' S Gravenhage",
    "iso:country":"NL",
    "sg:address":"Van Egmondstraat 82",
    "sg:city":"'S Gravenhage",
    "sg:orig_category":"Public Relationbureaus",
    "sg:phone":"+31 70 358 8359",
    "sg:postcode":"2581 XM",
    "sg:province":"South Holland",
    "wof:name":"Spruijt",
    "wof:placetype":"venue"
},
  "geometry": {"coordinates":[4.268472,52.091152],"type":"Point"}
}