{
  "type": "Feature",
  "properties": {
    "addr:full":"Amalialn 23 Baarn Utrecht 3743 KE",
    "addr:housenumber":"23",
    "addr:postcode":"3743 ke",
    "addr:street":"Amalialn",
    "iso:country":"NL",
    "sg:address":"Amalialn 23",
    "sg:city":"Baarn",
    "sg:orig_category":"Adviesbureaus Bouwkunde",
    "sg:phone":"+31 35 541 7403",
    "sg:postcode":"3743 KE",
    "sg:province":"Utrecht",
    "wof:name":"Bouwkundig Adviesbureaus Baarn",
    "wof:placetype":"venue"
},
  "geometry": {"coordinates":[5.292121,52.21101],"type":"Point"}
}