{
  "type": "Feature",
  "properties": {
    "addr:full":"Nonnenmate 68 Doetinchem Gelderland 7006 CR",
    "addr:housenumber":"68;7006",
    "addr:postcode":"cr",
    "addr:street":"Nonnenmate;Gelderland",
    "iso:country":"NL",
    "sg:address":"Nonnenmate 68",
    "sg:city":"Doetinchem",
    "sg:orig_category":"Accountants - Administratie- Consulenten En -Kantoren",
    "sg:phone":"+31 314 342 421",
    "sg:postcode":"7006 CR",
    "sg:province":"Gelderland",
    "wof:name":"Accress",
    "wof:placetype":"venue"
},
  "geometry": {"coordinates":[6.269935,51.961365],"type":"Point"}
}