{
  "type": "Feature",
  "properties": {
    "addr:full":"Golfresidentie 39 Dronten Flevoland 8251 NK",
    "addr:housenumber":"39",
    "addr:postcode":"8251 nk",
    "addr:street":"Golfresidentie;Flevoland",
    "iso:country":"NL",
    "sg:address":"Golfresidentie 39",
    "sg:city":"Dronten",
    "sg:orig_category":"Beursorganisaties And Standbouw",
    "sg:phone":"+31 321 381 817",
    "sg:postcode":"8251 NK",
    "sg:province":"Flevoland",
    "wof:name":"Fillano Evenementen Decors",
    "wof:placetype":"venue"
},
  "geometry": {"coordinates":[5.715352,52.505638],"type":"Point"}
}