{
  "type": "Feature",
  "properties": {
    "iso:country":"NL",
    "sg:address":"Zeearend 10",
    "sg:city":"Almelo",
    "sg:orig_category":"Beveiliging",
    "sg:phone":"+31 546 819 772",
    "sg:postcode":"7609 PT",
    "sg:province":"Overijssel",
    "wof:name":"Schaafstra Bv",
    "wof:placetype":"venue"
},
  "geometry": {"coordinates":[6.639662,52.339409],"type":"Point"}
}