{
  "type": "Feature",
  "properties": {
    "iso:country":"NL",
    "sg:address":"C Muckstr 42",
    "sg:city":"Hengelo Ov",
    "sg:orig_category":"Goudsmeden En Zilversmeden",
    "sg:phone":"+31 74 277 6772",
    "sg:postcode":"7558 ER",
    "sg:province":"Overijssel",
    "wof:name":"Bilan, A",
    "wof:placetype":"venue"
},
  "geometry": {"coordinates":[6.830938,52.283737],"type":"Point"}
}