{
  "type": "Feature",
  "properties": {
    "addr:full":"C Muckstr 42 Hengelo Ov Overijssel 7558 ER",
    "addr:housenumber":"42",
    "addr:postcode":"7558 er",
    "addr:street":"Ov",
    "iso:country":"NL",
    "sg:address":"C Muckstr 42",
    "sg:city":"Hengelo Ov",
    "sg:orig_category":"Goudsmeden En Zilversmeden",
    "sg:phone":"+31 74 277 6772",
    "sg:postcode":"7558 ER",
    "sg:province":"Overijssel",
    "wof:name":"Bilan, A",
    "wof:placetype":"venue"
},
  "geometry": {"coordinates":[6.830938,52.283737],"type":"Point"}
}