{
  "type": "Feature",
  "properties": {
    "addr:full":"J V Wassenaerstr 25 Helmond Noord-Brabant 5703 CE",
    "addr:housenumber":"25",
    "addr:postcode":"5703 ce",
    "addr:street":"J;Wassenaerstr",
    "iso:country":"NL",
    "sg:address":"J V Wassenaerstr 25",
    "sg:city":"Helmond",
    "sg:orig_category":"Stukadoorsbedrijven",
    "sg:phone":"+31 492 555 188",
    "sg:postcode":"5703 CE",
    "sg:province":"Noord-Brabant",
    "wof:name":"Essers Stucadoorsbedrijf, M",
    "wof:placetype":"venue"
},
  "geometry": {"coordinates":[5.658284,51.482239],"type":"Point"}
}