{
  "type": "Feature",
  "properties": {
    "addr:full":"Bree 21 Rotterdam Zuid-Holland 3074 BA",
    "addr:housenumber":"21",
    "addr:postcode":"3074 ba",
    "addr:street":"Bree",
    "iso:country":"NL",
    "sg:address":"Bree 21",
    "sg:city":"Rotterdam",
    "sg:orig_category":"Drukkerijen And Copyshops",
    "sg:phone":"+31 10 419 5819",
    "sg:postcode":"3074 BA",
    "sg:province":"Zuid-Holland",
    "wof:name":"Vof Studio Quattro",
    "wof:placetype":"venue"
},
  "geometry": {"coordinates":[4.512334,51.890491],"type":"Point"}
}