{
  "type": "Feature",
  "properties": {
    "addr:full":"Pastoor Kerstenstraat 40 Boxmeer Noord-Brabant 5831 EW",
    "addr:housenumber":"40",
    "addr:postcode":"5831 ew",
    "addr:street":"Pastoor Kerstenstraat",
    "iso:country":"NL",
    "sg:address":"Pastoor Kerstenstraat 40",
    "sg:city":"Boxmeer",
    "sg:orig_category":"Medische Apparatuur And Prothesen Fab",
    "sg:phone":"+31 485 576 877",
    "sg:postcode":"5831 EW",
    "sg:province":"Noord-Brabant",
    "wof:name":"Tandprothetische Praktijk Giesbers",
    "wof:placetype":"venue"
},
  "geometry": {"coordinates":[5.945017,51.643356],"type":"Point"}
}