{
  "type": "Feature",
  "properties": {
    "addr:full":"Veenweidestraat 72 Purmerend Noord-Holland 1441 NH",
    "addr:housenumber":"72",
    "addr:postcode":"1441 nh",
    "addr:street":"Veenweidestraat",
    "iso:country":"NL",
    "sg:address":"Veenweidestraat 72",
    "sg:city":"Purmerend",
    "sg:orig_category":"Artiesten",
    "sg:phone":"+31 299 471 197",
    "sg:postcode":"1441 NH",
    "sg:province":"Noord-Holland",
    "wof:name":"Studio Theo Puntman",
    "wof:placetype":"venue"
},
  "geometry": {"coordinates":[4.963285,52.498226],"type":"Point"}
}