{
  "type": "Feature",
  "properties": {
    "addr:full":"Pelgrimstr 61 Gaanderen Gelderland 7011 BJ",
    "addr:housenumber":"61",
    "addr:postcode":"7011 bj",
    "addr:street":"Pelgrimstr;Gelderland",
    "iso:country":"NL",
    "sg:address":"Pelgrimstr 61",
    "sg:city":"Gaanderen",
    "sg:orig_category":"Bibliotheken En Leeszalen Openbare",
    "sg:phone":"+31 315 325 884",
    "sg:postcode":"7011 BJ",
    "sg:province":"Gelderland",
    "wof:name":"Openb Bibliotheek",
    "wof:placetype":"venue"
},
  "geometry": {"coordinates":[6.345124,51.934681],"type":"Point"}
}