{
  "type": "Feature",
  "properties": {
    "addr:full":"Ramspol 46 Haarlem North Holland 2036 BA",
    "addr:housenumber":"46",
    "addr:postcode":"2036 ba",
    "addr:street":"Ramspol",
    "iso:country":"NL",
    "sg:address":"Ramspol 46",
    "sg:city":"Haarlem",
    "sg:orig_category":"Schoonheidssalons",
    "sg:phone":"+31 23 540 0079",
    "sg:postcode":"2036 BA",
    "sg:province":"North Holland",
    "wof:name":"Agnes Vd Pligt'S Schoonheidssalon Ramspo",
    "wof:placetype":"venue"
},
  "geometry": {"coordinates":[4.655422,52.352287],"type":"Point"}
}