{
  "type": "Feature",
  "properties": {
    "addr:full":"Beukenweg 11 Amsterdam Noord-Holland 1092 AX",
    "addr:housenumber":"11",
    "addr:postcode":"1092 ax",
    "addr:street":"Beukenweg",
    "iso:country":"NL",
    "sg:address":"Beukenweg 11",
    "sg:city":"Amsterdam",
    "sg:orig_category":"Medische Apparatuur And Prothesen Fab",
    "sg:phone":"+31 20 693 9135",
    "sg:postcode":"1092 AX",
    "sg:province":"Noord-Holland",
    "wof:name":"Beter Horen Audire",
    "wof:placetype":"venue"
},
  "geometry": {"coordinates":[4.917903,52.357647],"type":"Point"}
}