{
  "type": "Feature",
  "properties": {
    "addr:full":"Factorij 115 Rotterdam Zuid-Holland 3071 AV",
    "addr:housenumber":"115",
    "addr:postcode":"3071 av",
    "addr:street":"Factorij",
    "iso:country":"NL",
    "sg:address":"Factorij 115",
    "sg:city":"Rotterdam",
    "sg:orig_category":"Film-, Tv- And Videoproductie",
    "sg:phone":"+31 10 215 1144",
    "sg:postcode":"3071 AV",
    "sg:province":"Zuid-Holland",
    "wof:name":"Verlaan In Video",
    "wof:placetype":"venue"
},
  "geometry": {"coordinates":[4.501134,51.910671],"type":"Point"}
}