{
  "type": "Feature",
  "properties": {
    "addr:full":"Koningin Wilhelminastr 39 Schoonrewoerd Zuid-Holland 4145 KH",
    "addr:housenumber":"39",
    "addr:postcode":"4145 kh",
    "addr:street":"Koningin Wilhelminastr",
    "iso:country":"NL",
    "sg:address":"Koningin Wilhelminastr 39",
    "sg:city":"Schoonrewoerd",
    "sg:orig_category":"Timmerwerk Van Hout And Kunststof",
    "sg:phone":"+31 345 641 475",
    "sg:postcode":"4145 KH",
    "sg:province":"Zuid-Holland",
    "wof:name":"Bouw- En Aannemersbedrijf J. Van Bruggen",
    "wof:placetype":"venue"
},
  "geometry": {"coordinates":[5.11574,51.921577],"type":"Point"}
}