{
  "type": "Feature",
  "properties": {
    "addr:full":"Kerkstr 49 Amsterdam Noord-Holland 1017 GB",
    "addr:housenumber":"49",
    "addr:postcode":"1017 gb",
    "addr:street":"Kerkstr",
    "iso:country":"NL",
    "sg:address":"Kerkstr 49",
    "sg:city":"Amsterdam",
    "sg:classifiers":[
        {
            "category":"Travel",
            "subcategory":"Hotels & Motels",
            "type":"Entertainment"
        }
    ],
    "sg:phone":"+31 20 622 7728",
    "sg:postcode":"1017 GB",
    "sg:province":"Noord-Holland",
    "sg:website":"http://www.aerohotel.nl",
    "wof:name":"Aero Hotel",
    "wof:placetype":"venue"
},
  "geometry": {"coordinates":[4.886055,52.365211],"type":"Point"}
}