{
  "type": "Feature",
  "properties": {
    "addr:full":"Havik 27 Amersfoort Utrecht 3811 EX",
    "addr:housenumber":"27",
    "addr:postcode":"3811 ex",
    "addr:street":"Havik",
    "iso:country":"NL",
    "sg:address":"Havik 27",
    "sg:city":"Amersfoort",
    "sg:orig_category":"Overheidsdiensten",
    "sg:phone":"+31 33 461 0302",
    "sg:postcode":"3811 EX",
    "sg:province":"Utrecht",
    "wof:name":"Filalethes",
    "wof:placetype":"venue"
},
  "geometry": {"coordinates":[5.3883681297,52.1572723389],"type":"Point"}
}