{
  "type": "Feature",
  "properties": {
    "addr:full":"Langestraat 66 Delden NL.08 7491 AH",
    "addr:housenumber":"66;nl.08",
    "addr:postcode":"7491 ah",
    "addr:street":"Langestraat",
    "iso:country":"NL",
    "sg:address":"Langestraat 66",
    "sg:city":"Delden",
    "sg:orig_category":"Schoenen",
    "sg:phone":"+31 74 376 2318",
    "sg:postcode":"7491 AH",
    "sg:province":"NL.08",
    "wof:name":"De Monnink Schoenen",
    "wof:placetype":"venue"
},
  "geometry": {"coordinates":[6.70986,52.2621],"type":"Point"}
}