{
  "type": "Feature",
  "properties": {
    "addr:full":"Kerkwg W 6 Waddinxveen Zuid-Holland 2742 BD",
    "addr:housenumber":"6",
    "addr:postcode":"2742 bd",
    "addr:street":"W",
    "iso:country":"NL",
    "sg:address":"Kerkwg W 6",
    "sg:city":"Waddinxveen",
    "sg:orig_category":"Fotoreportages",
    "sg:phone":"+31 182 615 439",
    "sg:postcode":"2742 BD",
    "sg:province":"Zuid-Holland",
    "wof:name":"Varsbayd",
    "wof:placetype":"venue"
},
  "geometry": {"coordinates":[4.641857,52.0467],"type":"Point"}
}