{
  "type": "Feature",
  "properties": {
    "iso:country":"NL",
    "sg:address":"Beitspad 2",
    "sg:city":"Zoetermeer",
    "sg:orig_category":"Kinderopvang Behalve Thuis",
    "sg:phone":"+31 79 361 2358",
    "sg:postcode":"2718 BJ",
    "sg:province":"South Holland",
    "wof:name":"Kinderopvang De Toverfluit",
    "wof:placetype":"venue"
},
  "geometry": {"coordinates":[4.491015,52.04277],"type":"Point"}
}