{
  "type": "Feature",
  "properties": {
    "addr:full":"Kroostwg N 159 Zeist Utrecht 3704 DW",
    "addr:housenumber":"159",
    "addr:postcode":"3704 dw",
    "addr:street":"N",
    "iso:country":"NL",
    "sg:address":"Kroostwg N 159",
    "sg:city":"Zeist",
    "sg:orig_category":"Verzekeringen - Verzekeringskantoren",
    "sg:phone":"+31 30 696 1969",
    "sg:postcode":"3704 DW",
    "sg:province":"Utrecht",
    "wof:name":"Hemert, F J J M Van",
    "wof:placetype":"venue"
},
  "geometry": {"coordinates":[5.212636,52.095905],"type":"Point"}
}