{
  "type": "Feature",
  "properties": {
    "addr:full":"Ammerdorfferstraat 10 Ursem North Holland 1645 SJ",
    "addr:housenumber":"10",
    "addr:postcode":"1645",
    "addr:street":"Ammerdorfferstraat",
    "iso:country":"NL",
    "sg:address":"Ammerdorfferstraat 10",
    "sg:city":"Ursem",
    "sg:orig_category":"Glaszetten",
    "sg:phone":"+31 72 502 1631",
    "sg:postcode":"1645 SJ",
    "sg:province":"North Holland",
    "wof:name":"Van Der Bijl Verf Behang Glas",
    "wof:placetype":"venue"
},
  "geometry": {"coordinates":[4.892882,52.627899],"type":"Point"}
}