{
  "type": "Feature",
  "properties": {
    "addr:full":"Hilsondisstr 1 Sprundel Noord-Brabant 4714 AM",
    "addr:housenumber":"1",
    "addr:postcode":"4714",
    "addr:street":"Hilsondisstr",
    "iso:country":"NL",
    "sg:address":"Hilsondisstr 1",
    "sg:city":"Sprundel",
    "sg:orig_category":"Verlichtingsartikelen - Groothandel",
    "sg:phone":"+31 165 350 436",
    "sg:postcode":"4714 AM",
    "sg:province":"Noord-Brabant",
    "sg:website":"http://www.mobilight.nl",
    "wof:name":"Mobilight Bv",
    "wof:placetype":"venue"
},
  "geometry": {"coordinates":[4.593658,51.53735],"type":"Point"}
}