{
  "type": "Feature",
  "properties": {
    "addr:full":"Burg Haspelsln 131A Amstelveen Noord-Holland 1181 NC",
    "addr:housenumber":"131a",
    "addr:postcode":"1181 nc",
    "addr:street":"Burg",
    "iso:country":"NL",
    "sg:address":"Burg Haspelsln 131A",
    "sg:city":"Amstelveen",
    "sg:orig_category":"Exploitatie- Maatschappijen",
    "sg:phone":"+31 20 641 3720",
    "sg:postcode":"1181 NC",
    "sg:province":"Noord-Holland",
    "wof:name":"Carintor Bv",
    "wof:placetype":"venue"
},
  "geometry": {"coordinates":[4.867448,52.305462],"type":"Point"}
}