{
  "type": "Feature",
  "properties": {
    "addr:full":"Van Leeuwenhoeklaan 82 Roosendaal North Brabant 4708 BD",
    "addr:housenumber":"82",
    "addr:postcode":"4708 bd",
    "addr:street":"Van Leeuwenhoeklaan",
    "iso:country":"NL",
    "sg:address":"Van Leeuwenhoeklaan 82",
    "sg:city":"Roosendaal",
    "sg:orig_category":"Felicitatiediensten",
    "sg:phone":"+31 165 544 420",
    "sg:postcode":"4708 BD",
    "sg:province":"North Brabant",
    "wof:name":"Koolen, J",
    "wof:placetype":"venue"
},
  "geometry": {"coordinates":[4.4422,51.528202],"type":"Point"}
}