{
  "type": "Feature",
  "properties": {
    "addr:full":"S Bikopln 17 Amsterdam Noord-Holland 1092 GM",
    "addr:housenumber":"17",
    "addr:postcode":"1092 gm",
    "iso:country":"NL",
    "sg:address":"S Bikopln 17",
    "sg:city":"Amsterdam",
    "sg:orig_category":"Bedrijfsopleidingen",
    "sg:phone":"+31 20 694 1190",
    "sg:postcode":"1092 GM",
    "sg:province":"Noord-Holland",
    "wof:name":"Lampe, V",
    "wof:placetype":"venue"
},
  "geometry": {"coordinates":[4.924003,52.355698],"type":"Point"}
}