{
  "type": "Feature",
  "properties": {
    "addr:full":"Cruquiusstr 10 Haarlem North Holland 2012 GC",
    "addr:housenumber":"10",
    "addr:postcode":"2012 gc",
    "addr:street":"Cruquiusstr",
    "iso:country":"NL",
    "sg:address":"Cruquiusstr 10",
    "sg:city":"Haarlem",
    "sg:orig_category":"Vertalers",
    "sg:phone":"+31 23 542 0934",
    "sg:postcode":"2012 GC",
    "sg:province":"North Holland",
    "wof:name":"Kooijman & Van Der Meulen",
    "wof:placetype":"venue"
},
  "geometry": {"coordinates":[4.624905,52.376801],"type":"Point"}
}