{
  "type": "Feature",
  "properties": {
    "addr:full":"Noordervoert 7 Hoogkarspel Noord-Holland 1616 PA",
    "addr:housenumber":"7",
    "addr:postcode":"1616 pa",
    "addr:street":"Noordervoert",
    "iso:country":"NL",
    "sg:address":"Noordervoert 7",
    "sg:city":"Hoogkarspel",
    "sg:orig_category":"Begrafenisondernemers",
    "sg:phone":"+31 228 561 592",
    "sg:postcode":"1616 PA",
    "sg:province":"Noord-Holland",
    "wof:name":"Begrafenis Vereniging De Laatste Eer",
    "wof:placetype":"venue"
},
  "geometry": {"coordinates":[5.177474,52.696598],"type":"Point"}
}