{
  "type": "Feature",
  "properties": {
    "iso:country":"NL",
    "sg:address":"Piet Heinstraat 44",
    "sg:city":"Nijmegen",
    "sg:orig_category":"Public Relationbureaus",
    "sg:phone":"+31 24 322 0466",
    "sg:postcode":"6512 GT",
    "sg:province":"Gelderland",
    "wof:name":"Lyon Romijnders",
    "wof:placetype":"venue"
},
  "geometry": {"coordinates":[5.853712,51.837303],"type":"Point"}
}