{
  "type": "Feature",
  "properties": {
    "addr:full":"Antoniushof 261 Utrecht Utrecht 3583 ZL",
    "addr:housenumber":"261",
    "addr:postcode":"3583 zl",
    "addr:street":"Antoniushof",
    "iso:country":"NL",
    "sg:address":"Antoniushof 261",
    "sg:city":"Utrecht",
    "sg:orig_category":"Artiesten/Gezelschappen",
    "sg:phone":"+31 30 254 1422",
    "sg:postcode":"3583 ZL",
    "sg:province":"Utrecht",
    "sg:website":"http://www.triomfo-infanti.nu",
    "wof:name":"Triomfo Infanti",
    "wof:placetype":"venue"
},
  "geometry": {"coordinates":[5.1449,52.086853],"type":"Point"}
}