{
  "type": "Feature",
  "properties": {
    "addr:full":"E Casimirln 42 Groningen Groningen 9717 AX",
    "addr:housenumber":"42",
    "addr:postcode":"9717 ax",
    "iso:country":"NL",
    "sg:address":"E Casimirln 42",
    "sg:city":"Groningen",
    "sg:orig_category":"Adviesbureaus Personeel",
    "sg:phone":"+31 50 313 6563",
    "sg:postcode":"9717 AX",
    "sg:province":"Groningen",
    "wof:name":"Hanssen",
    "wof:placetype":"venue"
},
  "geometry": {"coordinates":[6.549108,53.220451],"type":"Point"}
}