{
  "type": "Feature",
  "properties": {
    "addr:full":"Kievitlaan 41 Schagen Noord-Holland 1742 AB",
    "addr:housenumber":"41",
    "addr:postcode":"1742 ab",
    "addr:street":"Kievitlaan",
    "iso:country":"NL",
    "sg:address":"Kievitlaan 41",
    "sg:city":"Schagen",
    "sg:orig_category":"Fietshandelaren",
    "sg:phone":"+31 224 216 628",
    "sg:postcode":"1742 AB",
    "sg:province":"Noord-Holland",
    "wof:name":"Marco En Carla Windt",
    "wof:placetype":"venue"
},
  "geometry": {"coordinates":[4.787025,52.785046],"type":"Point"}
}