{
  "type": "Feature",
  "properties": {
    "addr:full":"Klinkertstraat 27 Hoensbroek Limburg 6433 PA",
    "addr:housenumber":"27",
    "addr:postcode":"6433 pa",
    "addr:street":"Klinkertstraat",
    "iso:country":"NL",
    "sg:address":"Klinkertstraat 27",
    "sg:city":"Hoensbroek",
    "sg:orig_category":"Bloemen And Planten",
    "sg:phone":"+31 45 521 5442",
    "sg:postcode":"6433 PA",
    "sg:province":"Limburg",
    "wof:name":"Turnerflower Vof",
    "wof:placetype":"venue"
},
  "geometry": {"coordinates":[5.919245,50.912796],"type":"Point"}
}