{
  "type": "Feature",
  "properties": {
    "addr:full":"De Bruyn Kopsstraat 12 Rijswijk Zh Zuid-Holland 2288 ED",
    "addr:housenumber":"12",
    "addr:postcode":"zh;2288 ed",
    "addr:street":"De Bruyn Kopsstraat",
    "iso:country":"NL",
    "sg:address":"De Bruyn Kopsstraat 12",
    "sg:city":"Rijswijk Zh",
    "sg:orig_category":"Verzekeringen",
    "sg:phone":"+31 70 307 4000",
    "sg:postcode":"2288 ED",
    "sg:province":"Zuid-Holland",
    "wof:name":"Lar Rechtsbijstand",
    "wof:placetype":"venue"
},
  "geometry": {"coordinates":[4.337464,52.041573],"type":"Point"}
}