{
  "type": "Feature",
  "properties": {
    "addr:full":"Quarlesstr 2 S Gravenhage Zuid-Holland 2552 VH",
    "addr:housenumber":"2;gravenhage",
    "addr:postcode":"2552 vh",
    "addr:street":"Quarlesstr;S",
    "iso:country":"NL",
    "sg:address":"Quarlesstr 2",
    "sg:city":"S Gravenhage",
    "sg:orig_category":"Voegwerken",
    "sg:phone":"+31 70 440 0983",
    "sg:postcode":"2552 VH",
    "sg:province":"Zuid-Holland",
    "wof:name":"Heppener",
    "wof:placetype":"venue"
},
  "geometry": {"coordinates":[4.24958,52.053631],"type":"Point"}
}