{
  "type": "Feature",
  "properties": {
    "addr:full":"Hoofdvaartsweg 73 Assen Drenthe 9405 AC",
    "addr:housenumber":"73",
    "addr:postcode":"9405 ac",
    "addr:street":"Hoofdvaartsweg",
    "iso:country":"NL",
    "sg:address":"Hoofdvaartsweg 73",
    "sg:city":"Assen",
    "sg:orig_category":"Wegen And Sportterreinen",
    "sg:phone":"+31 592 350 854",
    "sg:postcode":"9405 AC",
    "sg:province":"Drenthe",
    "wof:name":"Gebr. Hartenhof Bv",
    "wof:placetype":"venue"
},
  "geometry": {"coordinates":[6.5209197998,52.9965782166],"type":"Point"}
}