{
  "type": "Feature",
  "properties": {
    "addr:full":"Vijfsprongweg 30 Wekerom Gelderland 6733 JJ",
    "addr:housenumber":"30",
    "addr:postcode":"6733 jj",
    "addr:street":"Vijfsprongweg;Gelderland",
    "iso:country":"NL",
    "sg:address":"Vijfsprongweg 30",
    "sg:city":"Wekerom",
    "sg:orig_category":"Kampeerterreinen",
    "sg:phone":"+31 318 461 694",
    "sg:postcode":"6733 JJ",
    "sg:province":"Gelderland",
    "wof:name":"Camping Hent Uut 'T Zaant Bv",
    "wof:placetype":"venue"
},
  "geometry": {"coordinates":[5.6962947845,52.1102523804],"type":"Point"}
}