{
  "type": "Feature",
  "properties": {
    "iso:country":"NL",
    "sg:address":"Prins Bernhardlaan 18",
    "sg:city":"Ouderkerk A/D Amstel",
    "sg:orig_category":"Boekhouders",
    "sg:phone":"+31 20 496 4612",
    "sg:postcode":"1191 BP",
    "sg:province":"North Holland",
    "wof:name":"J.L. De Leeuw",
    "wof:placetype":"venue"
},
  "geometry": {"coordinates":[4.907422,52.298519],"type":"Point"}
}