{
  "type": "Feature",
  "properties": {
    "addr:full":"Haagwinde 1 Puttershoek Zuid-Holland 3297 WJ",
    "addr:housenumber":"1",
    "addr:postcode":"3297 wj",
    "addr:street":"Haagwinde",
    "iso:country":"NL",
    "sg:address":"Haagwinde 1",
    "sg:city":"Puttershoek",
    "sg:orig_category":"Sportverenigingen En Ontspannings- Verenigingen",
    "sg:phone":"+31 78 676 4150",
    "sg:postcode":"3297 WJ",
    "sg:province":"Zuid-Holland",
    "wof:name":"Ehs, Sjoelver",
    "wof:placetype":"venue"
},
  "geometry": {"coordinates":[4.559215,51.799831],"type":"Point"}
}