{
  "type": "Feature",
  "properties": {
    "addr:full":"Mathenesserln 386B Rotterdam South Holland 3023 HC",
    "addr:housenumber":"386b",
    "addr:postcode":"3023 hc",
    "iso:country":"NL",
    "sg:address":"Mathenesserln 386B",
    "sg:city":"Rotterdam",
    "sg:orig_category":"Grafisch Ontwerpers",
    "sg:phone":"+31 10 476 0203",
    "sg:postcode":"3023 HC",
    "sg:province":"South Holland",
    "wof:name":"Kuijpers, A T",
    "wof:placetype":"venue"
},
  "geometry": {"coordinates":[4.451117,51.913471],"type":"Point"}
}