{
  "type": "Feature",
  "properties": {
    "addr:full":"Lagewg 6A Raalte NL.08 8101 NM",
    "addr:housenumber":"6a;nl.08",
    "addr:postcode":"8101",
    "addr:street":"Lagewg",
    "iso:country":"NL",
    "sg:address":"Lagewg 6A",
    "sg:city":"Raalte",
    "sg:orig_category":"Kappers",
    "sg:phone":"+31 6 48335846",
    "sg:postcode":"8101 NM",
    "sg:province":"NL.08",
    "wof:name":"Patricia",
    "wof:placetype":"venue"
},
  "geometry": {"coordinates":[6.247667,52.388023],"type":"Point"}
}