{
  "type": "Feature",
  "properties": {
    "iso:country":"NL",
    "sg:address":"Karrestr 6",
    "sg:city":"Vlymen",
    "sg:orig_category":"Administratie- En Boekhoudkantoren",
    "sg:phone":"+31 73 511 4775",
    "sg:postcode":"5251 CR",
    "sg:province":"North Brabant",
    "wof:name":"Anl",
    "wof:placetype":"venue"
},
  "geometry": {"coordinates":[5.215498,51.696968],"type":"Point"}
}