{
  "type": "Feature",
  "properties": {
    "iso:country":"NL",
    "sg:address":"Vrykenstr 2",
    "sg:city":"Roggel",
    "sg:orig_category":"Zeilmakerijen",
    "sg:phone":"+31 475 492 445",
    "sg:postcode":"6088 PA",
    "sg:province":"Limburg",
    "sg:website":"http://www.budero.nl",
    "wof:name":"Budero Bv",
    "wof:placetype":"venue"
},
  "geometry": {"coordinates":[5.91955,51.263176],"type":"Point"}
}