{
  "type": "Feature",
  "properties": {
    "iso:country":"NL",
    "sg:address":"Thamerhorn 26",
    "sg:city":"Uithoorn",
    "sg:orig_category":"Horloges En Klokken - Reparatie En Onderhoud",
    "sg:phone":"+31 297 533 296",
    "sg:postcode":"1421 CE",
    "sg:province":"Noord-Holland",
    "wof:name":"Cooijmans Bv, A J",
    "wof:placetype":"venue"
},
  "geometry": {"coordinates":[4.817991,52.241062],"type":"Point"}
}