{
  "type": "Feature",
  "properties": {
    "addr:full":"Kon Wilhelminawg 349 Groenekan Utrecht 3737 BC",
    "addr:housenumber":"349",
    "addr:postcode":"3737 bc",
    "addr:street":"Kon",
    "iso:country":"NL",
    "sg:address":"Kon Wilhelminawg 349",
    "sg:city":"Groenekan",
    "sg:orig_category":"Horecabenodigdheden",
    "sg:phone":"+31 346 210 692",
    "sg:postcode":"3737 BC",
    "sg:province":"Utrecht",
    "wof:name":"Fabrie",
    "wof:placetype":"venue"
},
  "geometry": {"coordinates":[5.148828,52.130714],"type":"Point"}
}