{
  "type": "Feature",
  "properties": {
    "addr:full":"Tuinstr 125 Boskoop Zuid-Holland 2771 BZ",
    "addr:housenumber":"125",
    "addr:postcode":"2771 bz",
    "iso:country":"NL",
    "sg:address":"Tuinstr 125",
    "sg:city":"Boskoop",
    "sg:orig_category":"Verenigingen En Stichtingen",
    "sg:phone":"+31 172 216 795",
    "sg:postcode":"2771 BZ",
    "sg:province":"Zuid-Holland",
    "wof:name":"Ehbo",
    "wof:placetype":"venue"
},
  "geometry": {"coordinates":[4.672891,52.074268],"type":"Point"}
}