{
  "type": "Feature",
  "properties": {
    "addr:full":"Varkensmarkt 5 Lichtenvoorde Gelderland 7131 DH",
    "addr:housenumber":"5",
    "addr:postcode":"7131 dh",
    "addr:street":"Varkensmarkt;Gelderland",
    "iso:country":"NL",
    "sg:address":"Varkensmarkt 5",
    "sg:city":"Lichtenvoorde",
    "sg:orig_category":"Kappers",
    "sg:phone":"+31 544 373 299",
    "sg:postcode":"7131 DH",
    "sg:province":"Gelderland",
    "wof:name":"Kuijpers",
    "wof:placetype":"venue"
},
  "geometry": {"coordinates":[6.56792,51.988331],"type":"Point"}
}