{
  "type": "Feature",
  "properties": {
    "iso:country":"NL",
    "sg:address":"Varkensmarkt 5",
    "sg:city":"Lichtenvoorde",
    "sg:orig_category":"Kappers",
    "sg:phone":"+31 544 373 299",
    "sg:postcode":"7131 DH",
    "sg:province":"Gelderland",
    "wof:name":"Kuijpers",
    "wof:placetype":"venue"
},
  "geometry": {"coordinates":[6.56792,51.988331],"type":"Point"}
}