{
  "type": "Feature",
  "properties": {
    "addr:full":"Nieuwstraat 94 Almelo Overijssel 7605 AH",
    "addr:housenumber":"94",
    "addr:postcode":"7605 ah",
    "addr:street":"Nieuwstraat",
    "iso:country":"NL",
    "sg:address":"Nieuwstraat 94",
    "sg:city":"Almelo",
    "sg:orig_category":"Autokeuringen",
    "sg:phone":"+31 546 828 338",
    "sg:postcode":"7605 AH",
    "sg:province":"Overijssel",
    "wof:name":"G.A. Leus",
    "wof:placetype":"venue"
},
  "geometry": {"coordinates":[6.664543,52.354954],"type":"Point"}
}