{
  "type": "Feature",
  "properties": {
    "addr:full":"Postwg 15A De Glind Gelderland 3794 MJ",
    "addr:housenumber":"15a",
    "addr:postcode":"3794 mj",
    "addr:street":"Postwg",
    "iso:country":"NL",
    "sg:address":"Postwg 15A",
    "sg:city":"De Glind",
    "sg:orig_category":"Verenigingsgebouwen",
    "sg:phone":"+31 342 452 715",
    "sg:postcode":"3794 MJ",
    "sg:province":"Gelderland",
    "wof:name":"Akker, De",
    "wof:placetype":"venue"
},
  "geometry": {"coordinates":[5.534445,52.119755],"type":"Point"}
}