{
  "type": "Feature",
  "properties": {
    "addr:full":"Koperwiek 89 Capelle A/D Ijssel Zuid-Holland 2903 AD",
    "addr:housenumber":"89;a / d",
    "addr:postcode":"2903 ad",
    "addr:street":"Koperwiek",
    "iso:country":"NL",
    "sg:address":"Koperwiek 89",
    "sg:city":"Capelle A/D Ijssel",
    "sg:orig_category":"Wasserettes And Stomerijen",
    "sg:phone":"+31 10 450 3545",
    "sg:postcode":"2903 AD",
    "sg:province":"Zuid-Holland",
    "wof:name":"Kwaliteitsstomerij De Pauw",
    "wof:placetype":"venue"
},
  "geometry": {"coordinates":[4.5889830589,51.9304237366],"type":"Point"}
}