{
  "type": "Feature",
  "properties": {
    "addr:full":"Regisseurstr 16 Almere Flevoland 1315 LW",
    "addr:housenumber":"16",
    "addr:postcode":"1315 lw",
    "addr:street":"Regisseurstr;Flevoland",
    "iso:country":"NL",
    "sg:address":"Regisseurstr 16",
    "sg:city":"Almere",
    "sg:orig_category":"Warenhuizen",
    "sg:phone":"+31 900 9800",
    "sg:postcode":"1315 LW",
    "sg:province":"Flevoland",
    "wof:name":"Kijkshop",
    "wof:placetype":"venue"
},
  "geometry": {"coordinates":[5.2209877968,52.3728675842],"type":"Point"}
}