{
  "type": "Feature",
  "properties": {
    "iso:country":"NL",
    "sg:address":"Regisseurstr 16",
    "sg:city":"Almere",
    "sg:orig_category":"Warenhuizen",
    "sg:phone":"+31 900 9800",
    "sg:postcode":"1315 LW",
    "sg:province":"Flevoland",
    "wof:name":"Kijkshop",
    "wof:placetype":"venue"
},
  "geometry": {"coordinates":[5.2209877968,52.3728675842],"type":"Point"}
}