{
  "type": "Feature",
  "properties": {
    "addr:full":"Marnixlaan 302 Utrecht Utrecht 3552 HL",
    "addr:housenumber":"302",
    "addr:postcode":"3552 hl",
    "addr:street":"Marnixlaan",
    "iso:country":"NL",
    "sg:address":"Marnixlaan 302",
    "sg:city":"Utrecht",
    "sg:classifiers":[
        {
            "category":"Shopping",
            "subcategory":"Gifts & Souvenirs",
            "type":"Retail Goods"
        }
    ],
    "sg:phone":"+31 30 244 0144",
    "sg:postcode":"3552 HL",
    "sg:province":"Utrecht",
    "sg:tags":[
        "geschenken"
    ],
    "wof:name":"Kadoshop The Angel",
    "wof:placetype":"venue"
},
  "geometry": {"coordinates":[5.098994,52.109997],"type":"Point"}
}