{
  "type": "Feature",
  "properties": {
    "addr:full":"Soerabajaweg 6 Maastricht Limburg 6214 XS",
    "addr:housenumber":"6",
    "addr:postcode":"6214 xs",
    "addr:street":"Soerabajaweg",
    "iso:country":"NL",
    "sg:address":"Soerabajaweg 6",
    "sg:city":"Maastricht",
    "sg:orig_category":"Daken And Skeletbouw",
    "sg:phone":"+31 43 347 7645",
    "sg:postcode":"6214 XS",
    "sg:province":"Limburg",
    "wof:name":"Dakbedekkersbedrijf Severens",
    "wof:placetype":"venue"
},
  "geometry": {"coordinates":[5.667026,50.842052],"type":"Point"}
}