{
  "type": "Feature",
  "properties": {
    "iso:country":"NL",
    "sg:address":"Wachtpostdk 5",
    "sg:city":"Goor",
    "sg:orig_category":"Beeldende Kunstenaars",
    "sg:phone":"+31 547 274 530",
    "sg:postcode":"7471 LP",
    "sg:province":"NL.08",
    "sg:website":"http://www.home.zonnet.nl/flirtation",
    "wof:name":"Flirtation",
    "wof:placetype":"venue"
},
  "geometry": {"coordinates":[6.606223,52.231998],"type":"Point"}
}