{
  "type": "Feature",
  "properties": {
    "iso:country":"NL",
    "sg:address":"Lindenln 89",
    "sg:city":"Uffelte",
    "sg:orig_category":"Meubelstoffering",
    "sg:phone":"+31 521 351 791",
    "sg:postcode":"7975 AG",
    "sg:province":"Drenthe",
    "wof:name":"Hendriks Stoffeerhuis",
    "wof:placetype":"venue"
},
  "geometry": {"coordinates":[6.283506,52.791832],"type":"Point"}
}