{
  "type": "Feature",
  "properties": {
    "addr:full":"Kerkplein 5 Hoorn Nh Noord-Holland 1621 CX",
    "addr:housenumber":"5",
    "addr:postcode":"1621 cx",
    "addr:street":"Kerkplein",
    "iso:country":"NL",
    "sg:address":"Kerkplein 5",
    "sg:city":"Hoorn Nh",
    "sg:orig_category":"Kappers",
    "sg:phone":"+31 229 217 593",
    "sg:postcode":"1621 CX",
    "sg:province":"Noord-Holland",
    "wof:name":"Kapsalon Bibob",
    "wof:placetype":"venue"
},
  "geometry": {"coordinates":[5.0607748032,52.6401290894],"type":"Point"}
}