{
  "type": "Feature",
  "properties": {
    "addr:full":"Bruuk 126 Groesbeek Gelderland 6562 KN",
    "addr:housenumber":"126",
    "addr:postcode":"6562 kn",
    "addr:street":"Bruuk;Gelderland",
    "iso:country":"NL",
    "sg:address":"Bruuk 126",
    "sg:city":"Groesbeek",
    "sg:orig_category":"Diverse Grafische Activiteiten",
    "sg:phone":"+31 24 397 7973",
    "sg:postcode":"6562 KN",
    "sg:province":"Gelderland",
    "wof:name":"Tromp Grafische Vormgeving Bv",
    "wof:placetype":"venue"
},
  "geometry": {"coordinates":[5.96198,51.754333],"type":"Point"}
}