{
  "type": "Feature",
  "properties": {
    "addr:full":"Groeneln 52 Schiedam Zuid-Holland 3114 CJ",
    "addr:housenumber":"52",
    "addr:postcode":"3114 cj",
    "addr:street":"Groeneln",
    "iso:country":"NL",
    "sg:address":"Groeneln 52",
    "sg:city":"Schiedam",
    "sg:orig_category":"Juweliers",
    "sg:phone":"+31 10 473 4534",
    "sg:postcode":"3114 CJ",
    "sg:province":"Zuid-Holland",
    "wof:name":"Miriam",
    "wof:placetype":"venue"
},
  "geometry": {"coordinates":[4.403732,51.906536],"type":"Point"}
}