{
  "type": "Feature",
  "properties": {
    "addr:full":"Postbus 21115 Simpelveld Limburg 6369 ZJ",
    "addr:postcode":"21115;6369 zj",
    "addr:street":"Postbus",
    "iso:country":"NL",
    "sg:address":"Postbus 21115",
    "sg:city":"Simpelveld",
    "sg:orig_category":"Verenigingen En Stichtingen",
    "sg:phone":"+31 45 544 4516",
    "sg:postcode":"6369 ZJ",
    "sg:province":"Limburg",
    "wof:name":"Jeugdcentr Simpelveld",
    "wof:placetype":"venue"
},
  "geometry": {"coordinates":[5.982154,50.83474],"type":"Point"}
}