{
  "type": "Feature",
  "properties": {
    "iso:country":"NL",
    "sg:address":"Observantenwg 55",
    "sg:city":"Maastricht",
    "sg:orig_category":"Architecten En Architectenbureaus",
    "sg:phone":"+31 43 321 5646",
    "sg:postcode":"6212 EP",
    "sg:province":"Limburg",
    "wof:name":"Koene, Pieter",
    "wof:placetype":"venue"
},
  "geometry": {"coordinates":[5.690309,50.837406],"type":"Point"}
}