{
  "type": "Feature",
  "properties": {
    "iso:country":"NL",
    "sg:address":"J H Prengerln 23",
    "sg:city":"Hardenberg",
    "sg:orig_category":"Verenigingen En Stichtingen",
    "sg:phone":"+31 523 266 286",
    "sg:postcode":"7772 XB",
    "sg:province":"Overijssel",
    "wof:name":"Vrijwilligers Vakaturebank",
    "wof:placetype":"venue"
},
  "geometry": {"coordinates":[6.622884,52.57534],"type":"Point"}
}