{
  "type": "Feature",
  "properties": {
    "addr:full":"Arkendonk 73 Oosterhout Nb Noord-Brabant 4907 XP",
    "addr:housenumber":"73",
    "addr:postcode":"4907 xp",
    "addr:street":"Arkendonk",
    "iso:country":"NL",
    "sg:address":"Arkendonk 73",
    "sg:city":"Oosterhout Nb",
    "sg:orig_category":"Bloemen And Planten",
    "sg:phone":"+31 162 421 067",
    "sg:postcode":"4907 XP",
    "sg:province":"Noord-Brabant",
    "wof:name":"Bloemenhuis De Anjer",
    "wof:placetype":"venue"
},
  "geometry": {"coordinates":[4.85625,51.643051],"type":"Point"}
}