{
  "type": "Feature",
  "properties": {
    "iso:country":"NL",
    "sg:address":"Europaln 20",
    "sg:city":"Utrecht",
    "sg:orig_category":"Verzekeringen - Verzekeringskantoren",
    "sg:phone":"+31 30 284 8600",
    "sg:postcode":"3526 KS",
    "sg:province":"Utrecht",
    "wof:name":"Relan Zekerheid",
    "wof:placetype":"venue"
},
  "geometry": {"coordinates":[5.09982,52.063389],"type":"Point"}
}