{
  "type": "Feature",
  "properties": {
    "addr:full":"Boerendanserdk 41A Zwolle NL.08 8024 AE",
    "addr:housenumber":"41a",
    "addr:postcode":"8024 ae",
    "addr:street":"Boerendanserdk",
    "iso:country":"NL",
    "sg:address":"Boerendanserdk 41A",
    "sg:city":"Zwolle",
    "sg:orig_category":"Magazijninrichtingen",
    "sg:phone":"+31 38 453 0579",
    "sg:postcode":"8024 AE",
    "sg:province":"NL.08",
    "sg:website":"http://www.combirek.nl",
    "wof:name":"Combirek",
    "wof:placetype":"venue"
},
  "geometry": {"coordinates":[6.122467,52.519344],"type":"Point"}
}