{
  "type": "Feature",
  "properties": {
    "addr:full":"Tomberstraat 71 Papenhoven Limburg 6124 AK",
    "addr:housenumber":"71",
    "addr:postcode":"6124 ak",
    "addr:street":"Tomberstraat",
    "iso:country":"NL",
    "sg:address":"Tomberstraat 71",
    "sg:city":"Papenhoven",
    "sg:orig_category":"Huisdierenfokkers",
    "sg:phone":"+31 46 485 1473",
    "sg:postcode":"6124 AK",
    "sg:province":"Limburg",
    "wof:name":"De Caumerhof",
    "wof:placetype":"venue"
},
  "geometry": {"coordinates":[5.784659,51.036064],"type":"Point"}
}