{
  "type": "Feature",
  "properties": {
    "iso:country":"NL",
    "sg:address":"Papenvoort 73",
    "sg:city":"Geldrop",
    "sg:orig_category":"Metaalwerken",
    "sg:phone":"+31 40 286 7743",
    "sg:postcode":"5663 AE",
    "sg:province":"Noord-Brabant",
    "wof:name":"Montagebedrijf Sloots",
    "wof:placetype":"venue"
},
  "geometry": {"coordinates":[5.542545,51.42197],"type":"Point"}
}