{
  "type": "Feature",
  "properties": {
    "addr:full":"Heembadweg 17 Ter Apel Groningen 9561 CS",
    "addr:housenumber":"17",
    "addr:postcode":"9561 cs",
    "addr:street":"Heembadweg",
    "iso:country":"NL",
    "sg:address":"Heembadweg 17",
    "sg:city":"Ter Apel",
    "sg:orig_category":"Kampeerterreinen",
    "sg:phone":"+31 599 581 933",
    "sg:postcode":"9561 CS",
    "sg:province":"Groningen",
    "wof:name":"Camping Moeke'S Gat",
    "wof:placetype":"venue"
},
  "geometry": {"coordinates":[7.0583791733,52.8855743408],"type":"Point"}
}