{
  "type": "Feature",
  "properties": {
    "addr:full":"Gabbemastr 36 Sneek Provincie Friesland 8602 VD",
    "addr:housenumber":"36",
    "addr:postcode":"8602 vd",
    "addr:street":"Gabbemastr;Provincie Friesland",
    "iso:country":"NL",
    "sg:address":"Gabbemastr 36",
    "sg:city":"Sneek",
    "sg:orig_category":"Begrafenisverzorging",
    "sg:phone":"+31 515 431 875",
    "sg:postcode":"8602 VD",
    "sg:province":"Provincie Friesland",
    "wof:name":"Heslinga",
    "wof:placetype":"venue"
},
  "geometry": {"coordinates":[5.656701,53.043884],"type":"Point"}
}