{
  "type": "Feature",
  "properties": {
    "iso:country":"NL",
    "sg:address":"Ensahln 19",
    "sg:city":"Bilthoven",
    "sg:orig_category":"Psychotherapeuten",
    "sg:phone":"+31 30 225 1718",
    "sg:postcode":"3723 HT",
    "sg:province":"Utrecht",
    "wof:name":"Norden, A Van",
    "wof:placetype":"venue"
},
  "geometry": {"coordinates":[5.205415,52.13023],"type":"Point"}
}