{
  "type": "Feature",
  "properties": {
    "addr:full":"D Stalpertstr 61 Amsterdam Noord-Holland 1072 XB",
    "addr:housenumber":"61",
    "addr:postcode":"1072 xb",
    "iso:country":"NL",
    "sg:address":"D Stalpertstr 61",
    "sg:city":"Amsterdam",
    "sg:orig_category":"Koffie- En Theehuizen",
    "sg:phone":"+31 20 673 7089",
    "sg:postcode":"1072 XB",
    "sg:province":"Noord-Holland",
    "wof:name":"Turkiyem Genclik",
    "wof:placetype":"venue"
},
  "geometry": {"coordinates":[4.8901,52.356358],"type":"Point"}
}