{
  "type": "Feature",
  "properties": {
    "addr:full":"Industrieweg 19 Duivendrecht Noord-Holland 1115 AD",
    "addr:housenumber":"19",
    "addr:postcode":"1115 ad",
    "addr:street":"Industrieweg",
    "iso:country":"NL",
    "sg:address":"Industrieweg 19",
    "sg:city":"Duivendrecht",
    "sg:orig_category":"Personenvervoer Zonder Dienstregeling",
    "sg:phone":"+31 20 699 5544",
    "sg:postcode":"1115 AD",
    "sg:province":"Noord-Holland",
    "wof:name":"Kramer Autobedrijf Bv",
    "wof:placetype":"venue"
},
  "geometry": {"coordinates":[4.946734,52.336411],"type":"Point"}
}