{
  "type": "Feature",
  "properties": {
    "addr:full":"Kleasterwei 29 Goingaryp Provincie Friesland 8511 AA",
    "addr:housenumber":"29",
    "addr:postcode":"8511 aa",
    "addr:street":"Kleasterwei;Provincie Friesland",
    "iso:country":"NL",
    "sg:address":"Kleasterwei 29",
    "sg:city":"Goingaryp",
    "sg:orig_category":"Vaarscholen",
    "sg:phone":"+31 566 689 793",
    "sg:postcode":"8511 AA",
    "sg:province":"Provincie Friesland",
    "wof:name":"Nautische Diensten & Opleidingen",
    "wof:placetype":"venue"
},
  "geometry": {"coordinates":[5.774603,53.012722],"type":"Point"}
}