{
  "type": "Feature",
  "properties": {
    "iso:country":"NL",
    "sg:address":"Dubbelmonde 22",
    "sg:city":"Zevenbergen",
    "sg:orig_category":"Schilders",
    "sg:phone":"+31 168 326 243",
    "sg:postcode":"4761 NK",
    "sg:province":"Noord-Brabant",
    "wof:name":"Dijk, A C M Van",
    "wof:placetype":"venue"
},
  "geometry": {"coordinates":[4.59396,51.644974],"type":"Point"}
}