{
  "type": "Feature",
  "properties": {
    "addr:full":"Dubbelmonde 22 Zevenbergen Noord-Brabant 4761 NK",
    "addr:housenumber":"22",
    "addr:postcode":"4761 nk",
    "addr:street":"Dubbelmonde",
    "iso:country":"NL",
    "sg:address":"Dubbelmonde 22",
    "sg:city":"Zevenbergen",
    "sg:orig_category":"Schilders",
    "sg:phone":"+31 168 326 243",
    "sg:postcode":"4761 NK",
    "sg:province":"Noord-Brabant",
    "wof:name":"Dijk, A C M Van",
    "wof:placetype":"venue"
},
  "geometry": {"coordinates":[4.59396,51.644974],"type":"Point"}
}