{
  "type": "Feature",
  "properties": {
    "addr:full":"L P Boonstr 22 Almere Flevoland 1321 KC",
    "addr:housenumber":"22",
    "addr:postcode":"1321 kc",
    "addr:street":"Flevoland",
    "iso:country":"NL",
    "sg:address":"L P Boonstr 22",
    "sg:city":"Almere",
    "sg:orig_category":"Kinderactiviteiten",
    "sg:phone":"+31 36 844 7451",
    "sg:postcode":"1321 KC",
    "sg:province":"Flevoland",
    "sg:website":"http://www.kits-kist.nl",
    "wof:name":"Kits-Kist, De",
    "wof:placetype":"venue"
},
  "geometry": {"coordinates":[5.190558,52.357056],"type":"Point"}
}