{
  "type": "Feature",
  "properties": {
    "addr:full":"Spoorln 36 Groesbeek Gelderland 6562 AN",
    "addr:housenumber":"36",
    "addr:postcode":"6562 an",
    "addr:street":"Spoorln;Gelderland",
    "iso:country":"NL",
    "sg:address":"Spoorln 36",
    "sg:city":"Groesbeek",
    "sg:orig_category":"Glas",
    "sg:phone":"+31 24 397 1909",
    "sg:postcode":"6562 AN",
    "sg:province":"Gelderland",
    "wof:name":"Zee, Van Der",
    "wof:placetype":"venue"
},
  "geometry": {"coordinates":[5.93249,51.776745],"type":"Point"}
}