{
  "type": "Feature",
  "properties": {
    "addr:full":"Prinsesseweg 65 Groningen Groningen 9717 BD",
    "addr:housenumber":"65",
    "addr:postcode":"9717 bd",
    "addr:street":"Prinsesseweg",
    "iso:country":"NL",
    "sg:address":"Prinsesseweg 65",
    "sg:city":"Groningen",
    "sg:orig_category":"Artiestenbureaus",
    "sg:phone":"+31 50 318 9231",
    "sg:postcode":"9717 BD",
    "sg:province":"Groningen",
    "wof:name":"Marijke De Jong",
    "wof:placetype":"venue"
},
  "geometry": {"coordinates":[6.547999,53.222645],"type":"Point"}
}