{
  "type": "Feature",
  "properties": {
    "addr:full":"Kerkstr 2 Streefkerk South Holland 2959 BS",
    "addr:housenumber":"2",
    "addr:postcode":"2959 bs",
    "addr:street":"Kerkstr",
    "iso:country":"NL",
    "sg:address":"Kerkstr 2",
    "sg:city":"Streefkerk",
    "sg:orig_category":"Kabels",
    "sg:phone":"+31 184 686 789",
    "sg:postcode":"2959 BS",
    "sg:province":"South Holland",
    "wof:name":"Mgt",
    "wof:placetype":"venue"
},
  "geometry": {"coordinates":[4.7427220345,51.9018249512],"type":"Point"}
}