{
  "type": "Feature",
  "properties": {
    "addr:full":"Zuiderparkwg 113A S Hertogenbosch Noord-Brabant 5216 HB",
    "addr:housenumber":"113a",
    "addr:postcode":"5216 hb",
    "addr:street":"S Hertogenbosch",
    "iso:country":"NL",
    "sg:address":"Zuiderparkwg 113A",
    "sg:city":"S Hertogenbosch",
    "sg:orig_category":"Bedrijfsopleidingen",
    "sg:phone":"+31 73 614 6640",
    "sg:postcode":"5216 HB",
    "sg:province":"Noord-Brabant",
    "wof:name":"Itp Bv",
    "wof:placetype":"venue"
},
  "geometry": {"coordinates":[5.319072,51.682133],"type":"Point"}
}