{
  "type": "Feature",
  "properties": {
    "addr:full":"Pennendk 61 Ulvenhout Noord-Brabant 4851 VC",
    "addr:housenumber":"61",
    "addr:postcode":"4851 vc",
    "addr:street":"Pennendk",
    "iso:country":"NL",
    "sg:address":"Pennendk 61",
    "sg:city":"Ulvenhout",
    "sg:orig_category":"Administratie- En Boekhoudkantoren",
    "sg:phone":"+31 76 561 2993",
    "sg:postcode":"4851 VC",
    "sg:province":"Noord-Brabant",
    "wof:name":"Pijpers",
    "wof:placetype":"venue"
},
  "geometry": {"coordinates":[4.807359,51.546154],"type":"Point"}
}