{
  "type": "Feature",
  "properties": {
    "addr:full":"Industriewg 6 Bruinisse Zeeland 4311 RM",
    "addr:housenumber":"6",
    "addr:postcode":"4311 rm",
    "addr:street":"Industriewg",
    "iso:country":"NL",
    "sg:address":"Industriewg 6",
    "sg:city":"Bruinisse",
    "sg:classifiers":[
        {
            "category":"Farming",
            "subcategory":"Fish & Marine Products",
            "type":"Manufacturing & Wholesale Goods"
        }
    ],
    "sg:phone":"+31 111 484 149",
    "sg:postcode":"4311 RM",
    "sg:province":"Zeeland",
    "sg:tags":[
        "vi"
    ],
    "wof:name":"Waal, J De",
    "wof:placetype":"venue"
},
  "geometry": {"coordinates":[4.091303,51.6544],"type":"Point"}
}