{
  "type": "Feature",
  "properties": {
    "addr:full":"Industriewg 31 St Oedenrode Noord-Brabant 5492 NG",
    "addr:housenumber":"31",
    "addr:postcode":"5492 ng",
    "addr:street":"Industriewg",
    "iso:country":"NL",
    "sg:address":"Industriewg 31",
    "sg:city":"St Oedenrode",
    "sg:orig_category":"Keukens",
    "sg:phone":"+31 413 490 790",
    "sg:postcode":"5492 NG",
    "sg:province":"Noord-Brabant",
    "sg:website":"http://www.huyberts.nl",
    "wof:name":"Henry Huyberts Keukens En Interieurs Bv",
    "wof:placetype":"venue"
},
  "geometry": {"coordinates":[5.482797,51.55555],"type":"Point"}
}