{
  "type": "Feature",
  "properties": {
    "addr:full":"Ameidestraat 1 Helmond Noord-Brabant 5701 NN",
    "addr:housenumber":"1",
    "addr:postcode":"5701 nn",
    "addr:street":"Ameidestraat",
    "iso:country":"NL",
    "sg:address":"Ameidestraat 1",
    "sg:city":"Helmond",
    "sg:orig_category":"Meubelzaken, Woning- And Keukeninrichting",
    "sg:phone":"+31 492 540 855",
    "sg:postcode":"5701 NN",
    "sg:province":"Noord-Brabant",
    "wof:name":"Dirks Woninginrichting En Projekten Bv",
    "wof:placetype":"venue"
},
  "geometry": {"coordinates":[5.657405,51.478737],"type":"Point"}
}