{
  "type": "Feature",
  "properties": {
    "addr:full":"De Veken 36 Opmeer Noord-Holland 1716 KE",
    "addr:housenumber":"36",
    "addr:postcode":"1716 ke",
    "addr:street":"De Veken",
    "iso:country":"NL",
    "sg:address":"De Veken 36",
    "sg:city":"Opmeer",
    "sg:orig_category":"Dierenvoeder - Fabrieken",
    "sg:phone":"+31 226 368 111",
    "sg:postcode":"1716 KE",
    "sg:province":"Noord-Holland",
    "wof:name":"Rodi Bv",
    "wof:placetype":"venue"
},
  "geometry": {"coordinates":[4.962265,52.709534],"type":"Point"}
}