{
  "type": "Feature",
  "properties": {
    "iso:country":"NL",
    "sg:address":"Stadhuispln 264-265",
    "sg:city":"Tilburg",
    "sg:orig_category":"Wijnkoperijen En -Groothandel",
    "sg:phone":"+31 13 543 3259",
    "sg:postcode":"5038 TG",
    "sg:province":"North Brabant",
    "wof:name":"Bloems, Henri",
    "wof:placetype":"venue"
},
  "geometry": {"coordinates":[5.0875759125,51.5559082031],"type":"Point"}
}