{
  "type": "Feature",
  "properties": {
    "iso:country":"NL",
    "sg:address":"Industrieweg 6",
    "sg:city":"Culemborg",
    "sg:orig_category":"Diverse Grafische Activiteiten",
    "sg:phone":"+31 345 510 879",
    "sg:postcode":"4104 AR",
    "sg:province":"Gelderland",
    "wof:name":"Data Concept Documentation Services Europe Bv",
    "wof:placetype":"venue"
},
  "geometry": {"coordinates":[5.220463,51.942913],"type":"Point"}
}