{
  "type": "Feature",
  "properties": {
    "addr:full":"Beukelsdk 67A E Rotterdam South Holland 3021 AD",
    "addr:housenumber":"67a e",
    "addr:postcode":"3021 ad",
    "addr:street":"Beukelsdk",
    "iso:country":"NL",
    "sg:address":"Beukelsdk 67A E",
    "sg:city":"Rotterdam",
    "sg:orig_category":"Verenigingen En Stichtingen",
    "sg:phone":"+31 10 477 9612",
    "sg:postcode":"3021 AD",
    "sg:province":"South Holland",
    "wof:name":"Prabhakar Arya Samaadj",
    "wof:placetype":"venue"
},
  "geometry": {"coordinates":[4.45925,51.916531],"type":"Point"}
}