{
  "type": "Feature",
  "properties": {
    "addr:full":"Goudenregenstr 38 Bussum Noord-Holland 1402 EX",
    "addr:housenumber":"38",
    "addr:postcode":"1402 ex",
    "addr:street":"Goudenregenstr",
    "iso:country":"NL",
    "sg:address":"Goudenregenstr 38",
    "sg:city":"Bussum",
    "sg:orig_category":"Makelaars En Adviseurs Onroerende Goederen",
    "sg:phone":"+31 35 693 0078",
    "sg:postcode":"1402 EX",
    "sg:province":"Noord-Holland",
    "wof:name":"Smeink Bv, M J M",
    "wof:placetype":"venue"
},
  "geometry": {"coordinates":[5.186364,52.271851],"type":"Point"}
}