{
  "type": "Feature",
  "properties": {
    "addr:full":"Bassin 120 Maastricht Limburg 6211 AK",
    "addr:housenumber":"120",
    "addr:postcode":"6211 ak",
    "addr:street":"Bassin",
    "iso:country":"NL",
    "sg:address":"Bassin 120",
    "sg:city":"Maastricht",
    "sg:orig_category":"Architecten",
    "sg:phone":"+31 43 321 0047",
    "sg:postcode":"6211 AK",
    "sg:province":"Limburg",
    "wof:name":"Buro Hoen Vof",
    "wof:placetype":"venue"
},
  "geometry": {"coordinates":[5.690906,50.855194],"type":"Point"}
}