{
  "type": "Feature",
  "properties": {
    "iso:country":"NL",
    "sg:address":"Nyverheidswg N 60",
    "sg:city":"Amersfoort",
    "sg:orig_category":"Administratie- En Boekhoudkantoren",
    "sg:phone":"+31 33 469 9884",
    "sg:postcode":"3812 PM",
    "sg:province":"Utrecht",
    "wof:name":"Koch",
    "wof:placetype":"venue"
},
  "geometry": {"coordinates":[5.371126,52.165211],"type":"Point"}
}