{
  "type": "Feature",
  "properties": {
    "addr:full":"Noorderstr 1B Alkmaar Noord-Holland 1823 CS",
    "addr:housenumber":"1b",
    "addr:postcode":"1823 cs",
    "addr:street":"Noorderstr",
    "iso:country":"NL",
    "sg:address":"Noorderstr 1B",
    "sg:city":"Alkmaar",
    "sg:orig_category":"Optiek - Fabrieken En Groothandel",
    "sg:phone":"+31 72 564 6588",
    "sg:postcode":"1823 CS",
    "sg:province":"Noord-Holland",
    "wof:name":"Visineth Bv",
    "wof:placetype":"venue"
},
  "geometry": {"coordinates":[4.7604298592,52.6383209229],"type":"Point"}
}