{
  "type": "Feature",
  "properties": {
    "iso:country":"NL",
    "sg:address":"Schuilenburgerweg 8",
    "sg:city":"Hellendoorn",
    "sg:orig_category":"Overheidsdiensten",
    "sg:phone":"+31 548 655 022",
    "sg:postcode":"7447 RP",
    "sg:province":"Overijssel",
    "wof:name":"De Delle",
    "wof:placetype":"venue"
},
  "geometry": {"coordinates":[6.4546990395,52.3937950134],"type":"Point"}
}