{
  "type": "Feature",
  "properties": {
    "addr:full":"Valkenburgerstr 167 Amsterdam North Holland 1011 MJ",
    "addr:housenumber":"167",
    "addr:postcode":"1011 mj",
    "iso:country":"NL",
    "sg:address":"Valkenburgerstr 167",
    "sg:city":"Amsterdam",
    "sg:orig_category":"Keukens",
    "sg:phone":"+31 20 344 9400",
    "sg:postcode":"1011 MJ",
    "sg:province":"North Holland",
    "wof:name":"Arclinea",
    "wof:placetype":"venue"
},
  "geometry": {"coordinates":[4.906235,52.369217],"type":"Point"}
}