{
  "type": "Feature",
  "properties": {
    "addr:full":"Industriestr 48 Delft Zuid-Holland 2624 BB",
    "addr:housenumber":"48",
    "addr:postcode":"2624 bb",
    "addr:street":"Industriestr",
    "iso:country":"NL",
    "sg:address":"Industriestr 48",
    "sg:city":"Delft",
    "sg:orig_category":"Parketvloeren",
    "sg:phone":"+31 15 285 0214",
    "sg:postcode":"2624 BB",
    "sg:province":"Zuid-Holland",
    "wof:name":"Parkethuys Bv, 'T",
    "wof:placetype":"venue"
},
  "geometry": {"coordinates":[4.356516,52.000397],"type":"Point"}
}