{
  "type": "Feature",
  "properties": {
    "iso:country":"NL",
    "sg:address":"W Boumastr 23",
    "sg:city":"St Annaparochie",
    "sg:orig_category":"Verzekeringen - Verzekeringskantoren",
    "sg:phone":"+31 518 402 917",
    "sg:postcode":"9076 EM",
    "sg:province":"Friesland",
    "wof:name":"Riemersma Assurantiekantoor",
    "wof:placetype":"venue"
},
  "geometry": {"coordinates":[5.650862,53.271103],"type":"Point"}
}