{
  "type": "Feature",
  "properties": {
    "addr:full":"Buikslotermeerpln 166 Amsterdam Noord-Holland 1025 EZ",
    "addr:housenumber":"166",
    "addr:postcode":"1025 ez",
    "iso:country":"NL",
    "sg:address":"Buikslotermeerpln 166",
    "sg:city":"Amsterdam",
    "sg:orig_category":"Meubelen",
    "sg:phone":"+31 20 632 6635",
    "sg:postcode":"1025 EZ",
    "sg:province":"Noord-Holland",
    "wof:name":"Phoenix Bv, De",
    "wof:placetype":"venue"
},
  "geometry": {"coordinates":[4.937286,52.398167],"type":"Point"}
}