{
  "type": "Feature",
  "properties": {
    "addr:full":"Fahrenheitstraat 32 Kruiningen Zeeland 4416 DC",
    "addr:housenumber":"32",
    "addr:postcode":"4416",
    "addr:street":"Fahrenheitstraat",
    "iso:country":"NL",
    "sg:address":"Fahrenheitstraat 32",
    "sg:city":"Kruiningen",
    "sg:orig_category":"Marktonderzoekbureaus",
    "sg:phone":"+31 113 383 837",
    "sg:postcode":"4416 DC",
    "sg:province":"Zeeland",
    "wof:name":"A. Van Damme",
    "wof:placetype":"venue"
},
  "geometry": {"coordinates":[4.027477,51.452213],"type":"Point"}
}