{
  "type": "Feature",
  "properties": {
    "addr:full":"Cypressenlaan 26 Hoogezand Groningen 9603 DG",
    "addr:housenumber":"26",
    "addr:postcode":"9603 dg",
    "addr:street":"Cypressenlaan",
    "iso:country":"NL",
    "sg:address":"Cypressenlaan 26",
    "sg:city":"Hoogezand",
    "sg:classifiers":[
        {
            "category":"Professional",
            "subcategory":"Accounting & Tax Preparation",
            "type":"Services"
        }
    ],
    "sg:phone":"+31 598 351 707",
    "sg:postcode":"9603 DG",
    "sg:province":"Groningen",
    "sg:tags":[
        "accountant"
    ],
    "wof:name":"F Klatter",
    "wof:placetype":"venue"
},
  "geometry": {"coordinates":[6.758474,53.147243],"type":"Point"}
}