{
  "type": "Feature",
  "properties": {
    "addr:full":"Standerdmolen 8 Houten Utrecht 3995 AA",
    "addr:housenumber":"8",
    "addr:postcode":"3995 aa",
    "addr:street":"Standerdmolen",
    "iso:country":"NL",
    "sg:address":"Standerdmolen 8",
    "sg:city":"Houten",
    "sg:orig_category":"Technische Studies And Onderzoek",
    "sg:phone":"+31 30 635 0300",
    "sg:postcode":"3995 AA",
    "sg:province":"Utrecht",
    "wof:name":"Themiek Marketing Voor Techniek",
    "wof:placetype":"venue"
},
  "geometry": {"coordinates":[5.172159,52.029762],"type":"Point"}
}