{
  "type": "Feature",
  "properties": {
    "iso:country":"NL",
    "sg:address":"Mr Nennstiehlwg 85",
    "sg:city":"De Wilp Gn",
    "sg:orig_category":"Ventilatiesystemen",
    "sg:phone":"+31 594 643 050",
    "sg:postcode":"9367 PC",
    "sg:province":"Groningen",
    "wof:name":"Atn",
    "wof:placetype":"venue"
},
  "geometry": {"coordinates":[6.252655,53.11512],"type":"Point"}
}