{
  "type": "Feature",
  "properties": {
    "iso:country":"NL",
    "sg:address":"Wilhelminastraat 135",
    "sg:city":"Hoensbroek",
    "sg:orig_category":"Boekhouders",
    "sg:phone":"+31 45 523 4956",
    "sg:postcode":"6431 XV",
    "sg:province":"Limburg",
    "wof:name":"Teebee Administratieve Dienstverl",
    "wof:placetype":"venue"
},
  "geometry": {"coordinates":[5.935673,50.924267],"type":"Point"}
}