{
  "type": "Feature",
  "properties": {
    "addr:full":"Burg Kurversstr 7 Urmond Limburg 6129 KG",
    "addr:housenumber":"7",
    "addr:postcode":"6129 kg",
    "addr:street":"Burg Kurversstr",
    "iso:country":"NL",
    "sg:address":"Burg Kurversstr 7",
    "sg:city":"Urmond",
    "sg:orig_category":"Autoschade- Herstelbedrijven",
    "sg:phone":"+31 46 433 8264",
    "sg:postcode":"6129 KG",
    "sg:province":"Limburg",
    "wof:name":"Huub Roex",
    "wof:placetype":"venue"
},
  "geometry": {"coordinates":[5.771708,51.001644],"type":"Point"}
}