{
  "type": "Feature",
  "properties": {
    "iso:country":"NL",
    "sg:address":"Marconistr 25",
    "sg:city":"Barneveld",
    "sg:classifiers":[
        {
            "category":"Farming",
            "subcategory":"Fish & Marine Products",
            "type":"Manufacturing & Wholesale Goods"
        }
    ],
    "sg:phone":"+31 342 491 427",
    "sg:postcode":"3771 AM",
    "sg:province":"Gelderland",
    "sg:tags":[
        "vi"
    ],
    "wof:name":"Fieret, E",
    "wof:placetype":"venue"
},
  "geometry": {"coordinates":[5.596184,52.136261],"type":"Point"}
}