{
  "type": "Feature",
  "properties": {
    "addr:full":"Kennemerlaan 42 Ijmuiden Noord-Holland 1972 EP",
    "addr:housenumber":"42",
    "addr:postcode":"1972 ep",
    "addr:street":"Kennemerlaan",
    "iso:country":"NL",
    "sg:address":"Kennemerlaan 42",
    "sg:city":"Ijmuiden",
    "sg:orig_category":"Zuivelproducten",
    "sg:phone":"+31 255 530 890",
    "sg:postcode":"1972 EP",
    "sg:province":"Noord-Holland",
    "wof:name":"De Kaasmarkt",
    "wof:placetype":"venue"
},
  "geometry": {"coordinates":[4.604661,52.460621],"type":"Point"}
}