{
  "type": "Feature",
  "properties": {
    "addr:full":"Emrikweg 25 Haarlem Noord-Holland 2031 BT",
    "addr:housenumber":"25",
    "addr:postcode":"2031 bt",
    "addr:street":"Emrikweg",
    "iso:country":"NL",
    "sg:address":"Emrikweg 25",
    "sg:city":"Haarlem",
    "sg:orig_category":"Diverse Consumentenartikelen Gh",
    "sg:phone":"+31 23 532 1606",
    "sg:postcode":"2031 BT",
    "sg:province":"Noord-Holland",
    "wof:name":"Elzet Import/Export Vof",
    "wof:placetype":"venue"
},
  "geometry": {"coordinates":[4.663606,52.396118],"type":"Point"}
}