{
  "type": "Feature",
  "properties": {
    "iso:country":"NL",
    "sg:address":"Postbus 150",
    "sg:city":"Ryswyk Zh",
    "sg:orig_category":"Koeriersdiensten",
    "sg:phone":"+31 6 50882886",
    "sg:postcode":"2280 AD",
    "wof:name":"Pakkiestaksie, D\u00e9",
    "wof:placetype":"venue"
},
  "geometry": {"coordinates":[4.32436,52.037251],"type":"Point"}
}