{
  "type": "Feature",
  "properties": {
    "addr:full":"Groeneveldseweg 7 Schipluiden Zuid-Holland 2636 AN",
    "addr:housenumber":"7",
    "addr:postcode":"2636 an",
    "addr:street":"Groeneveldseweg",
    "iso:country":"NL",
    "sg:address":"Groeneveldseweg 7",
    "sg:city":"Schipluiden",
    "sg:orig_category":"Metaalwerken",
    "sg:phone":"+31 15 380 8241",
    "sg:postcode":"2636 AN",
    "sg:province":"Zuid-Holland",
    "wof:name":"M.J.M. Demmenie",
    "wof:placetype":"venue"
},
  "geometry": {"coordinates":[4.31591,51.97718],"type":"Point"}
}