{
  "type": "Feature",
  "properties": {
    "iso:country":"NL",
    "sg:address":"Kromstr 109",
    "sg:city":"Oss",
    "sg:orig_category":"Administratie- En Boekhoudkantoren",
    "sg:phone":"+31 412 625 010",
    "sg:postcode":"5345 AB",
    "sg:province":"Noord-Brabant",
    "sg:website":"http://www.home.hetnet.nl/~dekenaat-oss",
    "wof:name":"Dekenaal Centrum",
    "wof:placetype":"venue"
},
  "geometry": {"coordinates":[-93.460854,45.104435],"type":"Point"}
}