{
  "type": "Feature",
  "properties": {
    "iso:country":"NL",
    "sg:address":"Zuideinde 2A",
    "sg:city":"Volendam",
    "sg:orig_category":"Glas, Porselein En Aardewerk",
    "sg:phone":"+31 299 321 055",
    "sg:postcode":"1131 AH",
    "sg:province":"North Holland",
    "wof:name":"Excellence",
    "wof:placetype":"venue"
},
  "geometry": {"coordinates":[5.073695,52.49276],"type":"Point"}
}