{
  "type": "Feature",
  "properties": {
    "addr:full":"H Ter Kuilestr 133 Enschede Overijssel 7547 BC",
    "addr:housenumber":"133",
    "addr:postcode":"7547 bc",
    "addr:street":"H Ter Kuilestr",
    "iso:country":"NL",
    "sg:address":"H Ter Kuilestr 133",
    "sg:city":"Enschede",
    "sg:orig_category":"Drukkerijen",
    "sg:phone":"+31 53 432 3269",
    "sg:postcode":"7547 BC",
    "sg:province":"Overijssel",
    "wof:name":"Twenthe Drukkerij",
    "wof:placetype":"venue"
},
  "geometry": {"coordinates":[6.857841,52.220554],"type":"Point"}
}