{
  "type": "Feature",
  "properties": {
    "iso:country":"NL",
    "sg:address":"Europaln 7",
    "sg:city":"Eindhoven",
    "sg:orig_category":"Woningbouw- Verenigingen En -Stichtingen",
    "sg:phone":"+31 40 265 6300",
    "sg:postcode":"5622 NB",
    "sg:province":"Noord-Brabant",
    "sg:website":"http://www.swsehv.nl",
    "wof:name":"Sws, Woningstichting",
    "wof:placetype":"venue"
},
  "geometry": {"coordinates":[5.4629101753,51.4593811035],"type":"Point"}
}