{
  "type": "Feature",
  "properties": {
    "addr:full":"Marconistr 85 Rotterdam Zuid-Holland 3029 AJ",
    "addr:housenumber":"85",
    "addr:postcode":"3029 aj",
    "addr:street":"Marconistr",
    "iso:country":"NL",
    "sg:address":"Marconistr 85",
    "sg:city":"Rotterdam",
    "sg:orig_category":"Luchtvrachtexpediteurs",
    "sg:phone":"+31 10 437 5455",
    "sg:postcode":"3029 AJ",
    "sg:province":"Zuid-Holland",
    "wof:name":"Winterswijk Bv",
    "wof:placetype":"venue"
},
  "geometry": {"coordinates":[4.418875,51.913013],"type":"Point"}
}