{
  "type": "Feature",
  "properties": {
    "addr:full":"Hertenrade 161 S Gravenhage Zuid-Holland 2544 HE",
    "addr:housenumber":"161;gravenhage",
    "addr:postcode":"2544 he",
    "addr:street":"Hertenrade;S",
    "iso:country":"NL",
    "sg:address":"Hertenrade 161",
    "sg:city":"S Gravenhage",
    "sg:orig_category":"Betonijzervlechten",
    "sg:phone":"+31 70 366 0427",
    "sg:postcode":"2544 HE",
    "sg:province":"Zuid-Holland",
    "wof:name":"Torro",
    "wof:placetype":"venue"
},
  "geometry": {"coordinates":[4.25157,52.039551],"type":"Point"}
}