{
  "type": "Feature",
  "properties": {
    "addr:full":"Reiger 44 Sprang Capelle Noord-Brabant 5161 TZ",
    "addr:housenumber":"44",
    "addr:postcode":"5161 tz",
    "addr:street":"Reiger",
    "iso:country":"NL",
    "sg:address":"Reiger 44",
    "sg:city":"Sprang Capelle",
    "sg:orig_category":"Modevakscholen",
    "sg:phone":"+31 416 277 302",
    "sg:postcode":"5161 TZ",
    "sg:province":"Noord-Brabant",
    "wof:name":"Roomer, Bep",
    "wof:placetype":"venue"
},
  "geometry": {"coordinates":[5.019277,51.677979],"type":"Point"}
}