{
  "type": "Feature",
  "properties": {
    "addr:full":"Alferbos 166 Zoetermeer Zuid-Holland 2715 TJ",
    "addr:housenumber":"166",
    "addr:postcode":"2715 tj",
    "addr:street":"Alferbos",
    "iso:country":"NL",
    "sg:address":"Alferbos 166",
    "sg:city":"Zoetermeer",
    "sg:orig_category":"Woningstoffeerders",
    "sg:phone":"+31 79 321 4680",
    "sg:postcode":"2715 TJ",
    "sg:province":"Zuid-Holland",
    "wof:name":"Koning, M De",
    "wof:placetype":"venue"
},
  "geometry": {"coordinates":[4.4759378433,52.0564994812],"type":"Point"}
}