{
  "type": "Feature",
  "properties": {
    "addr:full":"Limbrichterstraat 61 Sittard Limburg 6131 EB",
    "addr:housenumber":"61",
    "addr:postcode":"6131 eb",
    "addr:street":"Limbrichterstraat",
    "iso:country":"NL",
    "sg:address":"Limbrichterstraat 61",
    "sg:city":"Sittard",
    "sg:classifiers":[
        {
            "category":"Retail",
            "subcategory":"Photofinishing",
            "type":"Services"
        }
    ],
    "sg:phone":"+31 46 420 0010",
    "sg:postcode":"6131 EB",
    "sg:province":"Limburg",
    "sg:tags":[
        "foto",
        "film"
    ],
    "wof:name":"Filmpost",
    "wof:placetype":"venue"
},
  "geometry": {"coordinates":[5.868898,50.998196],"type":"Point"}
}