{
  "type": "Feature",
  "properties": {
    "addr:full":"Kerkraderwg 19 Heerlen Limburg 6416 CC",
    "addr:housenumber":"19",
    "addr:postcode":"6416 cc",
    "addr:street":"Kerkraderwg",
    "iso:country":"NL",
    "sg:address":"Kerkraderwg 19",
    "sg:city":"Heerlen",
    "sg:orig_category":"Kappers",
    "sg:phone":"+31 45 541 3447",
    "sg:postcode":"6416 CC",
    "sg:province":"Limburg",
    "wof:name":"Raymond Coiffure",
    "wof:placetype":"venue"
},
  "geometry": {"coordinates":[5.995417,50.884418],"type":"Point"}
}