{
  "type": "Feature",
  "properties": {
    "iso:country":"NL",
    "sg:address":"Van Der Hooplaan 231A",
    "sg:city":"Amstelveen",
    "sg:classifiers":[
        {
            "category":"Restaurant",
            "type":"Food & Drink"
        }
    ],
    "sg:phone":"+31 20 640 3920",
    "sg:postcode":"1185 GC",
    "sg:province":"Noord-Holland",
    "wof:name":"Pain Bien",
    "wof:placetype":"venue"
},
  "geometry": {"coordinates":[4.854279,52.291935],"type":"Point"}
}