{
  "type": "Feature",
  "properties": {
    "addr:full":"Het Byvank 251B Enschede Overijssel 7544 DB",
    "addr:housenumber":"251b",
    "addr:postcode":"7544 db",
    "addr:street":"Het Byvank",
    "iso:country":"NL",
    "sg:address":"Het Byvank 251B",
    "sg:city":"Enschede",
    "sg:orig_category":"Verzekeringen - Verzekeringskantoren",
    "sg:phone":"+31 53 477 6819",
    "sg:postcode":"7544 DB",
    "sg:province":"Overijssel",
    "wof:name":"T\u00fcmah",
    "wof:placetype":"venue"
},
  "geometry": {"coordinates":[6.87453,52.193588],"type":"Point"}
}