{
  "type": "Feature",
  "properties": {
    "addr:full":"Ronde Bonk 28 Nieuwkoop CN. 2421 HK",
    "addr:housenumber":"28",
    "addr:postcode":"2421 hk",
    "addr:street":"Ronde Bonk;Cn.",
    "iso:country":"NL",
    "sg:address":"Ronde Bonk 28",
    "sg:city":"Nieuwkoop",
    "sg:classifiers":[
        {
            "category":"Personal",
            "subcategory":"Nail Salon",
            "type":"Services"
        }
    ],
    "sg:phone":"+31 172 575 267",
    "sg:postcode":"2421 HK",
    "sg:province":"CN.",
    "sg:tags":[
        "pedicure"
    ],
    "wof:name":"Eijk-Leliveld, Van",
    "wof:placetype":"venue"
},
  "geometry": {"coordinates":[114.153542,22.411249],"type":"Point"}
}