{
  "type": "Feature",
  "properties": {
    "addr:full":"Botterstr 33 Amsterdam Noord-Holland 1034 BR",
    "addr:housenumber":"33",
    "addr:postcode":"1034 br",
    "addr:street":"Botterstr",
    "iso:country":"NL",
    "sg:address":"Botterstr 33",
    "sg:city":"Amsterdam",
    "sg:orig_category":"Verzekeringen - Verzekeringskantoren",
    "sg:phone":"+31 20 492 1919",
    "sg:postcode":"1034 BR",
    "sg:province":"Noord-Holland",
    "wof:name":"B En Z",
    "wof:placetype":"venue"
},
  "geometry": {"coordinates":[4.909796,52.405437],"type":"Point"}
}