{
  "type": "Feature",
  "properties": {
    "addr:full":"Kerkstraat 29 Vianen Zh Utrecht 4132 BD",
    "addr:housenumber":"29",
    "addr:postcode":"zh;4132 bd",
    "addr:street":"Kerkstraat",
    "iso:country":"NL",
    "sg:address":"Kerkstraat 29",
    "sg:city":"Vianen Zh",
    "sg:orig_category":"Verlichting And Huishoudartikelen",
    "sg:phone":"+31 347 374 503",
    "sg:postcode":"4132 BD",
    "sg:province":"Utrecht",
    "wof:name":"Lijster Vloeren",
    "wof:placetype":"venue"
},
  "geometry": {"coordinates":[5.093182,51.994164],"type":"Point"}
}