{
  "type": "Feature",
  "properties": {
    "addr:full":"Hoogstraat 157 Eindhoven Noord-Brabant 5615 PC",
    "addr:housenumber":"157",
    "addr:postcode":"5615 pc",
    "addr:street":"Hoogstraat",
    "iso:country":"NL",
    "sg:address":"Hoogstraat 157",
    "sg:city":"Eindhoven",
    "sg:orig_category":"Meubels And Huishoudapparatuur Gh",
    "sg:phone":"+31 40 251 9088",
    "sg:postcode":"5615 PC",
    "sg:province":"Noord-Brabant",
    "wof:name":"Van De Moosdijk Antiek",
    "wof:placetype":"venue"
},
  "geometry": {"coordinates":[5.484105,51.434471],"type":"Point"}
}