{
  "type": "Feature",
  "properties": {
    "addr:full":"Burg Gilissenwg 57 Gennep Limburg 6591 ZN",
    "addr:housenumber":"57",
    "addr:postcode":"6591 zn",
    "addr:street":"Burg",
    "iso:country":"NL",
    "sg:address":"Burg Gilissenwg 57",
    "sg:city":"Gennep",
    "sg:orig_category":"Kunsthandel",
    "sg:phone":"+31 6 20555062",
    "sg:postcode":"6591 ZN",
    "sg:province":"Limburg",
    "sg:website":"http://www.kunsthandel-gennep.nl",
    "wof:name":"Kunsthandel Gennep",
    "wof:placetype":"venue"
},
  "geometry": {"coordinates":[5.978832,51.689278],"type":"Point"}
}