{
  "type": "Feature",
  "properties": {
    "addr:full":"Markt 31 Roermond Limburg 6041 EM",
    "addr:housenumber":"31",
    "addr:postcode":"6041 em",
    "addr:street":"Markt",
    "iso:country":"NL",
    "sg:address":"Markt 31",
    "sg:city":"Roermond",
    "sg:orig_category":"Overheidsdiensten",
    "sg:phone":"+31 475 359 999",
    "sg:postcode":"6041 EM",
    "sg:province":"Limburg",
    "wof:name":"Gemeente Roermond Sector Burgers En Samenleving",
    "wof:placetype":"venue"
},
  "geometry": {"coordinates":[5.9858698845,51.1958274841],"type":"Point"}
}