{
  "type": "Feature",
  "properties": {
    "addr:full":"Nw Weteringsewg 183 Groenekan Utrecht 3737 MH",
    "addr:housenumber":"183",
    "addr:postcode":"3737 mh",
    "iso:country":"NL",
    "sg:address":"Nw Weteringsewg 183",
    "sg:city":"Groenekan",
    "sg:orig_category":"Fotografie Reclame En Mode",
    "sg:phone":"+31 346 211 925",
    "sg:postcode":"3737 MH",
    "sg:province":"Utrecht",
    "wof:name":"Takkenberg, Kees",
    "wof:placetype":"venue"
},
  "geometry": {"coordinates":[5.180995,52.139935],"type":"Point"}
}