{
  "type": "Feature",
  "properties": {
    "addr:full":"Randwg 23 Hasselt Overijssel 8061 RW",
    "addr:housenumber":"23",
    "addr:postcode":"8061 rw",
    "addr:street":"Randwg",
    "iso:country":"NL",
    "sg:address":"Randwg 23",
    "sg:city":"Hasselt",
    "sg:classifiers":[
        {
            "category":"Retail",
            "subcategory":"Storage",
            "type":"Services"
        }
    ],
    "sg:phone":"+31 38 477 1727",
    "sg:postcode":"8061 RW",
    "sg:province":"Overijssel",
    "sg:tags":[
        "op-",
        "en",
        "overslagbedrijven"
    ],
    "wof:name":"Covatra Ned Bv",
    "wof:placetype":"venue"
},
  "geometry": {"coordinates":[6.09887,52.577271],"type":"Point"}
}