{
  "type": "Feature",
  "properties": {
    "iso:country":"NL",
    "sg:address":"Glanerbruggeweg 157",
    "sg:city":"Enschede",
    "sg:orig_category":"Houtverwerking",
    "sg:phone":"+31 53 461 1784",
    "sg:postcode":"7532 RG",
    "sg:province":"NL.08",
    "wof:name":"T Kerkenveld",
    "wof:placetype":"venue"
},
  "geometry": {"coordinates":[6.951623,52.240231],"type":"Point"}
}