{
  "type": "Feature",
  "properties": {
    "addr:full":"St. Anthonisweg 38 Boxmeer Noord-Brabant 5831 AE",
    "addr:housenumber":"38",
    "addr:postcode":"5831 ae",
    "addr:street":"St. Anthonisweg",
    "iso:country":"NL",
    "sg:address":"St. Anthonisweg 38",
    "sg:city":"Boxmeer",
    "sg:orig_category":"Drukkerijen And Copyshops",
    "sg:phone":"+31 485 576 413",
    "sg:postcode":"5831 AE",
    "sg:province":"Noord-Brabant",
    "wof:name":"Swanen Repro",
    "wof:placetype":"venue"
},
  "geometry": {"coordinates":[5.93451,51.645321],"type":"Point"}
}