{
  "type": "Feature",
  "properties": {
    "addr:full":"Middenweg 83 Breezand Noord-Holland 1764 KN",
    "addr:housenumber":"83",
    "addr:postcode":"1764 kn",
    "addr:street":"Middenweg",
    "iso:country":"NL",
    "sg:address":"Middenweg 83",
    "sg:city":"Breezand",
    "sg:orig_category":"Bloemen And Planten",
    "sg:phone":"+31 223 521 672",
    "sg:postcode":"1764 KN",
    "sg:province":"Noord-Holland",
    "wof:name":"Fa. Brands-Landman Kwekerij De Noordkop",
    "wof:placetype":"venue"
},
  "geometry": {"coordinates":[4.849513,52.890064],"type":"Point"}
}