{
  "type": "Feature",
  "properties": {
    "addr:full":"Langendijk 34 Breda Noord-Brabant 4819 EW",
    "addr:housenumber":"34",
    "addr:postcode":"4819 ew",
    "addr:street":"Langendijk",
    "iso:country":"NL",
    "sg:address":"Langendijk 34",
    "sg:city":"Breda",
    "sg:classifiers":[
        {
            "category":"Professional",
            "subcategory":"Accounting & Tax Preparation",
            "type":"Services"
        }
    ],
    "sg:phone":"+31 76 524 0500",
    "sg:postcode":"4819 EW",
    "sg:province":"Noord-Brabant",
    "sg:tags":[
        "accountant"
    ],
    "wof:name":"Pricewaterhousecoopers Nv",
    "wof:placetype":"venue"
},
  "geometry": {"coordinates":[4.765185,51.575348],"type":"Point"}
}