{
  "type": "Feature",
  "properties": {
    "addr:full":"Krommewoud 46 Zwaag Noord-Holland 1689 BP",
    "addr:housenumber":"46",
    "addr:postcode":"1689 bp",
    "addr:street":"Krommewoud",
    "iso:country":"NL",
    "sg:address":"Krommewoud 46",
    "sg:city":"Zwaag",
    "sg:orig_category":"Artsen - Huisartsen",
    "sg:phone":"+31 229 261 522",
    "sg:postcode":"1689 BP",
    "sg:province":"Noord-Holland",
    "wof:name":"Bangaerde",
    "wof:placetype":"venue"
},
  "geometry": {"coordinates":[5.082073,52.666565],"type":"Point"}
}