{
  "type": "Feature",
  "properties": {
    "addr:full":"Nieuwez Voorburgw 151 Amsterdam Noord-Holland 1012 RK",
    "addr:housenumber":"151",
    "addr:postcode":"1012 rk",
    "iso:country":"NL",
    "sg:address":"Nieuwez Voorburgw 151",
    "sg:city":"Amsterdam",
    "sg:orig_category":"Beeldende Kunstenaars",
    "sg:phone":"+31 20 420 4045",
    "sg:postcode":"1012 RK",
    "sg:province":"Noord-Holland",
    "wof:name":"Pander, Arnold",
    "wof:placetype":"venue"
},
  "geometry": {"coordinates":[4.89076,52.372536],"type":"Point"}
}