{
  "type": "Feature",
  "properties": {
    "addr:full":"Hoofdstraat 16 Kilder Gelderland 7035 AL",
    "addr:housenumber":"16",
    "addr:postcode":"7035",
    "addr:street":"Hoofdstraat;Gelderland",
    "iso:country":"NL",
    "sg:address":"Hoofdstraat 16",
    "sg:city":"Kilder",
    "sg:orig_category":"Paramedische Behandelingen",
    "sg:phone":"+31 314 684 789",
    "sg:postcode":"7035 AL",
    "sg:province":"Gelderland",
    "wof:name":"Mr. J.W. Jansen",
    "wof:placetype":"venue"
},
  "geometry": {"coordinates":[-88.06379699999999,42.174938],"type":"Point"}
}