{
  "type": "Feature",
  "properties": {
    "iso:country":"NL",
    "sg:address":"Oudedk 161",
    "sg:city":"Rotterdam",
    "sg:orig_category":"Nagelstudio'S",
    "sg:phone":"+31 6 23657618",
    "sg:postcode":"3061 AB",
    "sg:province":"Zuid-Holland",
    "wof:name":"Opoka",
    "wof:placetype":"venue"
},
  "geometry": {"coordinates":[4.509596,51.927589],"type":"Point"}
}