{
  "type": "Feature",
  "properties": {
    "addr:full":"Glasgowstr 8 Hengelo Ov NL.08 7559 KD",
    "addr:housenumber":"8",
    "addr:postcode":"7559 kd",
    "addr:street":"Glasgowstr;Ov",
    "iso:country":"NL",
    "sg:address":"Glasgowstr 8",
    "sg:city":"Hengelo Ov",
    "sg:orig_category":"Werving En Selectie",
    "sg:phone":"+31 74 267 4017",
    "sg:postcode":"7559 KD",
    "sg:province":"NL.08",
    "sg:website":"http://www.ict-carrieres.nl",
    "wof:name":"Ict Carri?res",
    "wof:placetype":"venue"
},
  "geometry": {"coordinates":[6.7977061272,52.2960014343],"type":"Point"}
}