{
  "type": "Feature",
  "properties": {
    "addr:full":"Fazantenkamp 958 Maarssen Utrecht 3607 EJ",
    "addr:housenumber":"958",
    "addr:postcode":"3607 ej",
    "addr:street":"Fazantenkamp",
    "iso:country":"NL",
    "sg:address":"Fazantenkamp 958",
    "sg:city":"Maarssen",
    "sg:classifiers":[
        {
            "category":"Professional",
            "subcategory":"Accounting & Tax Preparation",
            "type":"Services"
        }
    ],
    "sg:phone":"+31 346 564 909",
    "sg:postcode":"3607 EJ",
    "sg:province":"Utrecht",
    "sg:tags":[
        "accountant"
    ],
    "wof:name":"Stenton",
    "wof:placetype":"venue"
},
  "geometry": {"coordinates":[5.021424,52.130112],"type":"Point"}
}