{
  "type": "Feature",
  "properties": {
    "addr:full":"Zeeburgerpad 182 Amsterdam North Holland 1019 DZ",
    "addr:housenumber":"182",
    "addr:postcode":"1019 dz",
    "addr:street":"Zeeburgerpad",
    "iso:country":"NL",
    "sg:address":"Zeeburgerpad 182",
    "sg:city":"Amsterdam",
    "sg:orig_category":"Accountants - Administratie- Consulenten En -Kantoren",
    "sg:phone":"+31 20 520 5315",
    "sg:postcode":"1019 DZ",
    "sg:province":"North Holland",
    "sg:website":"http://www.zeta.nl",
    "wof:name":"Zeta",
    "wof:placetype":"venue"
},
  "geometry": {"coordinates":[4.941074,52.369144],"type":"Point"}
}