{
  "type": "Feature",
  "properties": {
    "addr:full":"Zuidlaarderweg 24 Annen Drenthe 9468 AE",
    "addr:housenumber":"24",
    "addr:postcode":"9468 ae",
    "addr:street":"Zuidlaarderweg",
    "iso:country":"NL",
    "sg:address":"Zuidlaarderweg 24",
    "sg:city":"Annen",
    "sg:orig_category":"Loodgieterswerk, Verwarming And Sanitaire Installaties",
    "sg:phone":"+31 592 271 502",
    "sg:postcode":"9468 AE",
    "sg:province":"Drenthe",
    "sg:website":"http://www.barthfidder.nl",
    "wof:name":"Barth Fidder",
    "wof:placetype":"venue"
},
  "geometry": {"coordinates":[-79.253815,33.471233],"type":"Point"}
}