{
  "type": "Feature",
  "properties": {
    "addr:full":"Renesselaan 16 De Meern Utrecht 3454 XX",
    "addr:housenumber":"16",
    "addr:postcode":"3454 xx",
    "addr:street":"Renesselaan",
    "iso:country":"NL",
    "sg:address":"Renesselaan 16",
    "sg:city":"De Meern",
    "sg:orig_category":"Loodgieterswerk, Verwarming And Sanitaire Installaties",
    "sg:phone":"+31 30 666 4501",
    "sg:postcode":"3454 XX",
    "sg:province":"Utrecht",
    "wof:name":"Voorsluys",
    "wof:placetype":"venue"
},
  "geometry": {"coordinates":[5.036613,52.07674],"type":"Point"}
}