{
  "type": "Feature",
  "properties": {
    "addr:full":"Postbus 5 Muiderberg Noord-Holland 1399 ZG",
    "addr:housenumber":"5;1399",
    "addr:postcode":"zg",
    "addr:street":"Postbus",
    "iso:country":"NL",
    "sg:address":"Postbus 5",
    "sg:city":"Muiderberg",
    "sg:orig_category":"Beveiliging",
    "sg:phone":"+31 294 461 044",
    "sg:postcode":"1399 ZG",
    "sg:province":"Noord-Holland",
    "wof:name":"Railsupport Bv",
    "wof:placetype":"venue"
},
  "geometry": {"coordinates":[5.116071,52.327091],"type":"Point"}
}