{
  "type": "Feature",
  "properties": {
    "addr:full":"Radiumstraat 87 Groningen Groningen 9743 SJ",
    "addr:housenumber":"87",
    "addr:postcode":"9743",
    "addr:street":"Radiumstraat",
    "iso:country":"NL",
    "sg:address":"Radiumstraat 87",
    "sg:city":"Groningen",
    "sg:orig_category":"Zuivelproducten And Spijsoli?n Gh",
    "sg:phone":"+31 50 571 1473",
    "sg:postcode":"9743 SJ",
    "sg:province":"Groningen",
    "wof:name":"T. Slotegraaf",
    "wof:placetype":"venue"
},
  "geometry": {"coordinates":[6.532494,53.223293],"type":"Point"}
}