{
  "type": "Feature",
  "properties": {
    "addr:full":"Rorowg 20 Roermond Limburg 6041 AS",
    "addr:housenumber":"20",
    "addr:postcode":"6041 as",
    "addr:street":"Rorowg",
    "iso:country":"NL",
    "sg:address":"Rorowg 20",
    "sg:city":"Roermond",
    "sg:orig_category":"Adviesbureaus Gezondheidszorg",
    "sg:phone":"+31 475 420 209",
    "sg:postcode":"6041 AS",
    "sg:province":"Limburg",
    "wof:name":"Lambregts",
    "wof:placetype":"venue"
},
  "geometry": {"coordinates":[5.993069,51.20982],"type":"Point"}
}