{
  "type": "Feature",
  "properties": {
    "addr:full":"Kl Nieuwland 2-4 Alkmaar North Holland 1811 DA",
    "addr:housenumber":"2-4",
    "addr:postcode":"1811 da",
    "addr:street":"Kl Nieuwland",
    "iso:country":"NL",
    "sg:address":"Kl Nieuwland 2-4",
    "sg:city":"Alkmaar",
    "sg:orig_category":"Honden- En Kattentrimsalons",
    "sg:phone":"+31 72 528 0775",
    "sg:postcode":"1811 DA",
    "sg:province":"North Holland",
    "wof:name":"Berb?e Hondentrimsalon",
    "wof:placetype":"venue"
},
  "geometry": {"coordinates":[4.749975,52.627846],"type":"Point"}
}