{
  "type": "Feature",
  "properties": {
    "addr:full":"Butzelaarstr 22 Luttenberg Buenos Aires 8105 AR",
    "addr:housenumber":"22;8105",
    "addr:street":"Butzelaarstr;Buenos Aires",
    "iso:country":"NL",
    "sg:address":"Butzelaarstr 22",
    "sg:city":"Luttenberg",
    "sg:orig_category":"Verenigingsgebouwen",
    "sg:phone":"+31 572 301 302",
    "sg:postcode":"8105 AR",
    "sg:province":"Buenos Aires",
    "wof:name":"Elckerlyc",
    "wof:placetype":"venue"
},
  "geometry": {"coordinates":[-62.364761,-38.751942],"type":"Point"}
}