{
  "type": "Feature",
  "properties": {
    "addr:full":"Wg-Plein 564 Amsterdam Noord-Holland 1054 SJ",
    "addr:housenumber":"564",
    "addr:postcode":"1054",
    "addr:street":"Wg-Plein",
    "iso:country":"NL",
    "sg:address":"Wg-Plein 564",
    "sg:city":"Amsterdam",
    "sg:orig_category":"Werving And Selectie Van Tijdelijk Personeel And Uitzendkantoren",
    "sg:phone":"+31 20 607 0107",
    "sg:postcode":"1054 SJ",
    "sg:province":"Noord-Holland",
    "wof:name":"Habitask Bv",
    "wof:placetype":"venue"
},
  "geometry": {"coordinates":[4.8718590736,52.3643989563],"type":"Point"}
}