{
  "type": "Feature",
  "properties": {
    "addr:full":"Rubensstr 3 Goor Overijssel 7471 HX",
    "addr:housenumber":"3",
    "addr:postcode":"7471 hx",
    "addr:street":"Rubensstr",
    "iso:country":"NL",
    "sg:address":"Rubensstr 3",
    "sg:city":"Goor",
    "sg:orig_category":"Sportverenigingen En Ontspannings- Verenigingen",
    "sg:phone":"+31 547 271 812",
    "sg:postcode":"7471 HX",
    "sg:province":"Overijssel",
    "wof:name":"Goorse Mixed",
    "wof:placetype":"venue"
},
  "geometry": {"coordinates":[6.573119,52.237503],"type":"Point"}
}