{
  "type": "Feature",
  "properties": {
    "addr:full":"Schweitzerstraat 86 Hoofddorp North Holland 2131 RH",
    "addr:housenumber":"86",
    "addr:postcode":"2131 rh",
    "addr:street":"Schweitzerstraat",
    "iso:country":"NL",
    "sg:address":"Schweitzerstraat 86",
    "sg:city":"Hoofddorp",
    "sg:orig_category":"Fotostudio'S And Fotografen",
    "sg:phone":"+31 23 564 1119",
    "sg:postcode":"2131 RH",
    "sg:province":"North Holland",
    "wof:name":"Jur Engelchor",
    "wof:placetype":"venue"
},
  "geometry": {"coordinates":[4.677365,52.307072],"type":"Point"}
}