{
  "type": "Feature",
  "properties": {
    "addr:full":"Reguliersbreestraat 49 Amsterdam North Holland 1017 CM",
    "addr:housenumber":"49",
    "addr:postcode":"1017 cm",
    "addr:street":"Reguliersbreestraat",
    "iso:country":"NL",
    "sg:address":"Reguliersbreestraat 49",
    "sg:city":"Amsterdam",
    "sg:classifiers":[
        {
            "category":"Retail",
            "subcategory":"Photofinishing",
            "type":"Services"
        }
    ],
    "sg:phone":"+31 20 623 8434",
    "sg:postcode":"1017 CM",
    "sg:province":"North Holland",
    "sg:tags":[
        "foto",
        "film"
    ],
    "wof:name":"Filmpost",
    "wof:placetype":"venue"
},
  "geometry": {"coordinates":[4.895664,52.366375],"type":"Point"}
}