{
  "type": "Feature",
  "properties": {
    "iso:country":"NL",
    "sg:address":"Heistraat 129",
    "sg:city":"Helmond",
    "sg:orig_category":"Kappers",
    "sg:phone":"+31 492 532 810",
    "sg:postcode":"5701 HK",
    "sg:province":"Noord-Brabant",
    "wof:name":"Salon Marie-Antoinette/ Bruidsm. Marie-A",
    "wof:placetype":"venue"
},
  "geometry": {"coordinates":[5.661278,51.483192],"type":"Point"}
}