{
  "type": "Feature",
  "properties": {
    "addr:full":"Jousterwg 32 Heerenveen Provincie Friesland 8447 RH",
    "addr:housenumber":"32",
    "addr:postcode":"8447 rh",
    "addr:street":"Jousterwg;Provincie Friesland",
    "iso:country":"NL",
    "sg:address":"Jousterwg 32",
    "sg:city":"Heerenveen",
    "sg:orig_category":"Automaterialen En Gereedschappen",
    "sg:phone":"+31 513 636 621",
    "sg:postcode":"8447 RH",
    "sg:province":"Provincie Friesland",
    "wof:name":"Ferwerda Bv, Gebr",
    "wof:placetype":"venue"
},
  "geometry": {"coordinates":[5.901284,52.96365],"type":"Point"}
}