{
  "type": "Feature",
  "properties": {
    "addr:full":"Marienburghpln 1 Deventer NL.08 7415 BR",
    "addr:housenumber":"1;nl.08",
    "addr:postcode":"7415 br",
    "addr:street":"Marienburghpln",
    "iso:country":"NL",
    "sg:address":"Marienburghpln 1",
    "sg:city":"Deventer",
    "sg:orig_category":"Kappers",
    "sg:phone":"+31 570 624 337",
    "sg:postcode":"7415 BR",
    "sg:province":"NL.08",
    "wof:name":"Pavette",
    "wof:placetype":"venue"
},
  "geometry": {"coordinates":[6.157754,52.266796],"type":"Point"}
}