{
  "type": "Feature",
  "properties": {
    "addr:full":"Peperstr 2 Amsterdam Noord-Holland 1011 TL",
    "addr:housenumber":"2",
    "addr:postcode":"1011 tl",
    "addr:street":"Peperstr",
    "iso:country":"NL",
    "sg:address":"Peperstr 2",
    "sg:city":"Amsterdam",
    "sg:orig_category":"Video - Faciliteiten En Producties",
    "sg:phone":"+31 20 627 1678",
    "sg:postcode":"1011 TL",
    "sg:province":"Noord-Holland",
    "wof:name":"Fran\u00e7ois Perrier",
    "wof:placetype":"venue"
},
  "geometry": {"coordinates":[4.90828,52.372242],"type":"Point"}
}