{
  "type": "Feature",
  "properties": {
    "addr:full":"Oude Liesselseweg 34 Deurne Noord-Brabant 5751 WP",
    "addr:housenumber":"34",
    "addr:postcode":"5751 wp",
    "addr:street":"Oude Liesselseweg",
    "iso:country":"NL",
    "sg:address":"Oude Liesselseweg 34",
    "sg:city":"Deurne",
    "sg:orig_category":"Artiestenbureaus",
    "sg:phone":"+31 493 320 001",
    "sg:postcode":"5751 WP",
    "sg:province":"Noord-Brabant",
    "wof:name":"Mangs",
    "wof:placetype":"venue"
},
  "geometry": {"coordinates":[5.795477,51.459003],"type":"Point"}
}