{
  "type": "Feature",
  "properties": {
    "addr:full":"Dorpsplein 91 Westervoort Gelderland 6931 CZ",
    "addr:housenumber":"91",
    "addr:postcode":"6931",
    "addr:street":"Dorpsplein;Gelderland",
    "iso:country":"NL",
    "sg:address":"Dorpsplein 91",
    "sg:city":"Westervoort",
    "sg:orig_category":"Bloemen And Planten",
    "sg:phone":"+31 26 312 0758",
    "sg:postcode":"6931 CZ",
    "sg:province":"Gelderland",
    "wof:name":"Leondia Vof",
    "wof:placetype":"venue"
},
  "geometry": {"coordinates":[5.966439,51.962727],"type":"Point"}
}