{
  "type": "Feature",
  "properties": {
    "addr:full":"Boeyesbosch 7 Burgh Haamstede Zeeland 4328 LN",
    "addr:housenumber":"7",
    "addr:postcode":"4328 ln",
    "addr:street":"Boeyesbosch;Haamstede",
    "iso:country":"NL",
    "sg:address":"Boeyesbosch 7",
    "sg:city":"Burgh Haamstede",
    "sg:orig_category":"Jachten - Schilderwerken En Onderhoud",
    "sg:phone":"+31 111 650 090",
    "sg:postcode":"4328 LN",
    "sg:province":"Zeeland",
    "sg:website":"http://www.grpro-clean.nl",
    "wof:name":"Gr Pro-Clean Zeeland Noord",
    "wof:placetype":"venue"
},
  "geometry": {"coordinates":[3.72991,51.691895],"type":"Point"}
}