{
  "type": "Feature",
  "properties": {
    "addr:full":"Marspoortstraat 15 Zutphen Gelderland 7201 JA",
    "addr:housenumber":"15",
    "addr:postcode":"7201 ja",
    "addr:street":"Marspoortstraat;Gelderland",
    "iso:country":"NL",
    "sg:address":"Marspoortstraat 15",
    "sg:city":"Zutphen",
    "sg:orig_category":"Artsen And Specialisten",
    "sg:phone":"+31 575 511 891",
    "sg:postcode":"7201 JA",
    "sg:province":"Gelderland",
    "wof:name":"Ivs Zutphen",
    "wof:placetype":"venue"
},
  "geometry": {"coordinates":[6.192001,52.141579],"type":"Point"}
}