{
  "type": "Feature",
  "properties": {
    "addr:full":"Flevostraat 182 Purmerend North Holland 1442 PZ",
    "addr:housenumber":"182",
    "addr:postcode":"1442 pz",
    "addr:street":"Flevostraat",
    "iso:country":"NL",
    "sg:address":"Flevostraat 182",
    "sg:city":"Purmerend",
    "sg:orig_category":"Autokeuringen",
    "sg:phone":"+31 299 435 877",
    "sg:postcode":"1442 PZ",
    "sg:province":"North Holland",
    "wof:name":"H.Q. Autoservice",
    "wof:placetype":"venue"
},
  "geometry": {"coordinates":[4.981544,52.518398],"type":"Point"}
}