{
  "type": "Feature",
  "properties": {
    "addr:full":"Steenstr 106 Boxmeer North Brabant 5831 JJ",
    "addr:housenumber":"106",
    "addr:postcode":"5831 jj",
    "iso:country":"NL",
    "sg:address":"Steenstr 106",
    "sg:city":"Boxmeer",
    "sg:orig_category":"Banken",
    "sg:phone":"+31 485 562 600",
    "sg:postcode":"5831 JJ",
    "sg:province":"North Brabant",
    "sg:website":"http://www.rabobank.nl",
    "wof:name":"Rabobank",
    "wof:placetype":"venue"
},
  "geometry": {"coordinates":[5.949323,51.647919],"type":"Point"}
}