{
  "type": "Feature",
  "properties": {
    "addr:full":"V Uvenwg 9 Wageningen Gelderland 6708 AD",
    "addr:housenumber":"9",
    "addr:postcode":"6708 ad",
    "addr:street":"Uvenwg;Gelderland",
    "iso:country":"NL",
    "sg:address":"V Uvenwg 9",
    "sg:city":"Wageningen",
    "sg:orig_category":"Scheepvaartservice- Bureaus",
    "sg:phone":"+31 317 479 911",
    "sg:postcode":"6708 AD",
    "sg:province":"Gelderland",
    "sg:website":"http://www.marin.nl",
    "wof:name":"Marin'S Nautical Centre Mscn",
    "wof:placetype":"venue"
},
  "geometry": {"coordinates":[5.660976,51.964355],"type":"Point"}
}