{
  "type": "Feature",
  "properties": {
    "addr:full":"Postbus 169 Vlaardingen South Holland 3130 AD",
    "addr:housenumber":"169",
    "addr:postcode":"3130 ad",
    "addr:street":"Postbus",
    "iso:country":"NL",
    "sg:address":"Postbus 169",
    "sg:city":"Vlaardingen",
    "sg:orig_category":"Verenigingen En Stichtingen",
    "sg:phone":"+31 10 435 4046",
    "sg:postcode":"3130 AD",
    "sg:province":"South Holland",
    "wof:name":"Haring & Bierfeest, Sticht",
    "wof:placetype":"venue"
},
  "geometry": {"coordinates":[4.340359,51.910442],"type":"Point"}
}