{
  "type": "Feature",
  "properties": {
    "iso:country":"NL",
    "sg:address":"Humberwg 12",
    "sg:city":"Amsterdam",
    "sg:orig_category":"Geluidsinstallaties",
    "sg:phone":"+31 20 613 1521",
    "sg:postcode":"1043 AC",
    "sg:province":"Noord-Holland",
    "wof:name":"Audio Pro Ned Bv",
    "wof:placetype":"venue"
},
  "geometry": {"coordinates":[4.830515,52.390564],"type":"Point"}
}