{
  "type": "Feature",
  "properties": {
    "iso:country":"NL",
    "sg:address":"Lindtsedk 76",
    "sg:city":"Zwyndrecht",
    "sg:orig_category":"Kantoor- En Bedrijfsmeubelen - Fabrieken En Groothandel",
    "sg:phone":"+31 78 623 1234",
    "sg:postcode":"3336 LE",
    "sg:province":"Zuid-Holland",
    "wof:name":"Schaffenburg Bv",
    "wof:placetype":"venue"
},
  "geometry": {"coordinates":[4.6080698967,51.8119316101],"type":"Point"}
}