{
  "type": "Feature",
  "properties": {
    "iso:country":"NL",
    "sg:address":"Achtmaalsebaan 40B",
    "sg:city":"Schyf",
    "sg:orig_category":"Vertaalbureaus",
    "sg:phone":"+31 165 342 792",
    "sg:postcode":"4721 SN",
    "sg:province":"Noord-Brabant",
    "wof:name":"Scandinavia",
    "wof:placetype":"venue"
},
  "geometry": {"coordinates":[4.545482,51.478153],"type":"Point"}
}