{
  "type": "Feature",
  "properties": {
    "addr:full":"Het Sluisje 25 Nieuwegein Utrecht 3438 AH",
    "addr:housenumber":"25",
    "addr:postcode":"3438 ah",
    "addr:street":"Het Sluisje",
    "iso:country":"NL",
    "sg:address":"Het Sluisje 25",
    "sg:city":"Nieuwegein",
    "sg:orig_category":"Partycatering And -Organisatie",
    "sg:phone":"+31 30 603 1551",
    "sg:postcode":"3438 AH",
    "sg:province":"Utrecht",
    "wof:name":"J. Vendrig Bedrijfscatering",
    "wof:placetype":"venue"
},
  "geometry": {"coordinates":[5.0941,52.037956],"type":"Point"}
}