{
  "type": "Feature",
  "properties": {
    "iso:country":"NL",
    "sg:address":"Langewg 8",
    "sg:city":"Blaricum",
    "sg:orig_category":"Adviesbureaus Financieel",
    "sg:phone":"+31 35 538 8033",
    "sg:postcode":"1261 EL",
    "sg:province":"Noord-Holland",
    "wof:name":"Viramon Bv",
    "wof:placetype":"venue"
},
  "geometry": {"coordinates":[5.243439,52.273277],"type":"Point"}
}