{
  "type": "Feature",
  "properties": {
    "addr:full":"Emmalaan 7 Soest Utrecht 3761 CS",
    "addr:housenumber":"7",
    "addr:postcode":"3761 cs",
    "addr:street":"Emmalaan",
    "iso:country":"NL",
    "sg:address":"Emmalaan 7",
    "sg:city":"Soest",
    "sg:orig_category":"Binnenhuisarchitecten",
    "sg:phone":"+31 35 601 0186",
    "sg:postcode":"3761 CS",
    "sg:province":"Utrecht",
    "wof:name":"Coops & Associates Vof",
    "wof:placetype":"venue"
},
  "geometry": {"coordinates":[5.289039,52.185883],"type":"Point"}
}