{
  "type": "Feature",
  "properties": {
    "addr:full":"Zandwg 3 Didam Gelderland 6942 JE",
    "addr:housenumber":"3",
    "addr:postcode":"6942 je",
    "addr:street":"Zandwg;Gelderland",
    "iso:country":"NL",
    "sg:address":"Zandwg 3",
    "sg:city":"Didam",
    "sg:orig_category":"Kappers",
    "sg:phone":"+31 316 228 153",
    "sg:postcode":"6942 JE",
    "sg:province":"Gelderland",
    "wof:name":"Miranda",
    "wof:placetype":"venue"
},
  "geometry": {"coordinates":[6.145001,51.938412],"type":"Point"}
}