{
  "type": "Feature",
  "properties": {
    "iso:country":"NL",
    "sg:address":"Gedempte Oude Gracht 3",
    "sg:city":"Haarlem",
    "sg:classifiers":[
        {
            "category":"Fast Food",
            "type":"Food & Drink"
        }
    ],
    "sg:phone":"+31 23 531 0671",
    "sg:postcode":"2011 GK",
    "sg:province":"Noord-Holland",
    "sg:tags":[
        "afhaal",
        "restaurant"
    ],
    "wof:name":"Snackbar De Smulhoek",
    "wof:placetype":"venue"
},
  "geometry": {"coordinates":[4.632259,52.382252],"type":"Point"}
}