{
  "type": "Feature",
  "properties": {
    "addr:full":"Kruisstr 45 Werkendam Noord-Brabant 4251 CV",
    "addr:housenumber":"45",
    "addr:postcode":"4251 cv",
    "addr:street":"Kruisstr",
    "iso:country":"NL",
    "sg:address":"Kruisstr 45",
    "sg:city":"Werkendam",
    "sg:orig_category":"Timmerwerken",
    "sg:phone":"+31 6 48427280",
    "sg:postcode":"4251 CV",
    "sg:province":"Noord-Brabant",
    "wof:name":"Smallman Betimmering",
    "wof:placetype":"venue"
},
  "geometry": {"coordinates":[4.895317,51.808372],"type":"Point"}
}