{
  "type": "Feature",
  "properties": {
    "iso:country":"NL",
    "sg:address":"Boudewynplnts 13",
    "sg:city":"Nunspeet",
    "sg:orig_category":"Administratie- En Boekhoudkantoren",
    "sg:phone":"+31 341 253 918",
    "sg:postcode":"8072 CR",
    "sg:province":"Gelderland",
    "wof:name":"Hazel-Druyff, J Van Den",
    "wof:placetype":"venue"
},
  "geometry": {"coordinates":[5.772205,52.374981],"type":"Point"}
}