{
  "type": "Feature",
  "properties": {
    "addr:full":"Omlooppad 2C Gouda Zuid-Holland 2805 RZ",
    "addr:housenumber":"2c",
    "addr:postcode":"2805 rz",
    "addr:street":"Omlooppad",
    "iso:country":"NL",
    "sg:address":"Omlooppad 2C",
    "sg:city":"Gouda",
    "sg:orig_category":"Handenarbeid",
    "sg:phone":"+31 6 50916493",
    "sg:postcode":"2805 RZ",
    "sg:province":"Zuid-Holland",
    "wof:name":"Tube, De",
    "wof:placetype":"venue"
},
  "geometry": {"coordinates":[4.715205,52.02589],"type":"Point"}
}