{
  "type": "Feature",
  "properties": {
    "addr:full":"Noordenwg 2 Ridderkerk Zuid-Holland 2984 AG",
    "addr:housenumber":"2",
    "addr:postcode":"2984",
    "addr:street":"Noordenwg",
    "iso:country":"NL",
    "sg:address":"Noordenwg 2",
    "sg:city":"Ridderkerk",
    "sg:orig_category":"Pijpleidingen - Installatie En Onderhoud",
    "sg:phone":"+31 10 416 5469",
    "sg:postcode":"2984 AG",
    "sg:province":"Zuid-Holland",
    "sg:website":"http://www.nimaridderkerk.nl",
    "wof:name":"Nima Mechanical Bv",
    "wof:placetype":"venue"
},
  "geometry": {"coordinates":[4.604343,51.872169],"type":"Point"}
}