{
  "type": "Feature",
  "properties": {
    "iso:country":"NL",
    "sg:address":"Rapenburg 47",
    "sg:city":"Amsterdam",
    "sg:orig_category":"Verenigingen En Stichtingen",
    "sg:phone":"+31 20 616 1377",
    "sg:postcode":"1011 TV",
    "sg:province":"North Holland",
    "sg:website":"http://www.vit-therapeuten.nl",
    "wof:name":"Integraal-Therapeuten, Ver Van",
    "wof:placetype":"venue"
},
  "geometry": {"coordinates":[4.908648,52.371441],"type":"Point"}
}