{
  "type": "Feature",
  "properties": {
    "addr:full":"Noordersluisweg 40 Lelystad Flevoland 8243 PR",
    "addr:housenumber":"40",
    "addr:postcode":"8243 pr",
    "addr:street":"Noordersluisweg;Flevoland",
    "iso:country":"NL",
    "sg:address":"Noordersluisweg 40",
    "sg:city":"Lelystad",
    "sg:orig_category":"Koeriersdiensten",
    "sg:phone":"+31 320 218 805",
    "sg:postcode":"8243 PR",
    "sg:province":"Flevoland",
    "sg:website":"http://www.flevobird.nl",
    "wof:name":"Selektvracht",
    "wof:placetype":"venue"
},
  "geometry": {"coordinates":[5.442676,52.502769],"type":"Point"}
}