{
  "type": "Feature",
  "properties": {
    "addr:full":"Dr V Noortstr 137 Leidschendam Zuid-Holland 2266 GV",
    "addr:housenumber":"137",
    "addr:postcode":"2266 gv",
    "addr:street":"Dr;Noortstr",
    "iso:country":"NL",
    "sg:address":"Dr V Noortstr 137",
    "sg:city":"Leidschendam",
    "sg:orig_category":"Woninginrichting",
    "sg:phone":"+31 71 580 2230",
    "sg:postcode":"2266 GV",
    "sg:province":"Zuid-Holland",
    "wof:name":"Schuijt, Leo",
    "wof:placetype":"venue"
},
  "geometry": {"coordinates":[4.4651350975,52.0956802368],"type":"Point"}
}