{
  "type": "Feature",
  "properties": {
    "iso:country":"NL",
    "sg:address":"Kerkendelweg 49",
    "sg:city":"Kootwijk",
    "sg:orig_category":"Kampeerterreinen",
    "sg:phone":"+31 577 456 224",
    "sg:postcode":"3775 KM",
    "sg:province":"Gelderland",
    "wof:name":"Camping Kerkendel",
    "wof:placetype":"venue"
},
  "geometry": {"coordinates":[5.7889351845,52.1856384277],"type":"Point"}
}