{
  "type": "Feature",
  "properties": {
    "addr:full":"Zonnenbergstr 25 Wilp Gld Gelderland 7384 DK",
    "addr:housenumber":"25",
    "addr:postcode":"7384 dk",
    "addr:street":"Zonnenbergstr;Gld Gelderland",
    "iso:country":"NL",
    "sg:address":"Zonnenbergstr 25",
    "sg:city":"Wilp Gld",
    "sg:orig_category":"Paardensport",
    "sg:phone":"+31 571 274 471",
    "sg:postcode":"7384 DK",
    "sg:province":"Gelderland",
    "wof:name":"B&S Vof",
    "wof:placetype":"venue"
},
  "geometry": {"coordinates":[6.092432,52.220406],"type":"Point"}
}