{
  "type": "Feature",
  "properties": {
    "addr:full":"Lauraplein 1 Heemskerk North Holland 1961 GP",
    "addr:housenumber":"1",
    "addr:postcode":"1961 gp",
    "addr:street":"Lauraplein",
    "iso:country":"NL",
    "sg:address":"Lauraplein 1",
    "sg:city":"Heemskerk",
    "sg:orig_category":"Kinderopvang Behalve Thuis",
    "sg:phone":"+31 251 207 721",
    "sg:postcode":"1961 GP",
    "sg:province":"North Holland",
    "wof:name":"Stichting Welzijnswerk Heemskerk",
    "wof:placetype":"venue"
},
  "geometry": {"coordinates":[4.674533,52.511501],"type":"Point"}
}