{
  "type": "Feature",
  "properties": {
    "iso:country":"NL",
    "sg:address":"Molenwerfsln 7-9",
    "sg:city":"Heemstede",
    "sg:orig_category":"Scholen Voor Basisonderwijs",
    "sg:phone":"+31 23 547 2575",
    "sg:postcode":"2103 TC",
    "sg:province":"Noord-Holland",
    "wof:name":"Valkenburg Rk",
    "wof:placetype":"venue"
},
  "geometry": {"coordinates":[4.621248,52.345287],"type":"Point"}
}