{
  "type": "Feature",
  "properties": {
    "addr:full":"Copernicusstraat 288 'S Gravenhage Zuid-Holland 2561 XH",
    "addr:housenumber":"288 '",
    "addr:postcode":"2561 xh",
    "addr:street":"Copernicusstraat",
    "iso:country":"NL",
    "sg:address":"Copernicusstraat 288",
    "sg:city":"'S Gravenhage",
    "sg:orig_category":"Verzekeringen",
    "sg:phone":"+31 70 360 8885",
    "sg:postcode":"2561 XH",
    "sg:province":"Zuid-Holland",
    "wof:name":"Van Binsbergen Ass",
    "wof:placetype":"venue"
},
  "geometry": {"coordinates":[4.273517,52.075191],"type":"Point"}
}