{
  "type": "Feature",
  "properties": {
    "addr:full":"Egeltjespad 3 Soest Utrecht 3766 AZ",
    "addr:housenumber":"3",
    "addr:postcode":"3766",
    "addr:street":"Egeltjespad",
    "iso:country":"NL",
    "sg:address":"Egeltjespad 3",
    "sg:city":"Soest",
    "sg:orig_category":"Boekhouders",
    "sg:phone":"+31 35 601 8886",
    "sg:postcode":"3766 AZ",
    "sg:province":"Utrecht",
    "wof:name":"Administratie En Belastingadviesburo Sch",
    "wof:placetype":"venue"
},
  "geometry": {"coordinates":[5.297137,52.164547],"type":"Point"}
}