{
  "type": "Feature",
  "properties": {
    "addr:full":"Hogebrugweg 4 Haarlo Gelderland 7273 PB",
    "addr:housenumber":"4",
    "addr:postcode":"7273 pb",
    "addr:street":"Hogebrugweg;Gelderland",
    "iso:country":"NL",
    "sg:address":"Hogebrugweg 4",
    "sg:city":"Haarlo",
    "sg:orig_category":"Kampeerterreinen",
    "sg:phone":"+31 545 261 342",
    "sg:postcode":"7273 PB",
    "sg:province":"Gelderland",
    "wof:name":"Camping En Kanoverhuur Groot Willink",
    "wof:placetype":"venue"
},
  "geometry": {"coordinates":[6.5503602028,52.1090621948],"type":"Point"}
}