{
  "type": "Feature",
  "properties": {
    "iso:country":"NL",
    "sg:address":"Schiedamsedk 6A",
    "sg:city":"Rotterdam",
    "sg:orig_category":"Meubelen",
    "sg:phone":"+31 10 213 3866",
    "sg:postcode":"3011 EB",
    "sg:province":"Zuid-Holland",
    "wof:name":"Sfeervol",
    "wof:placetype":"venue"
},
  "geometry": {"coordinates":[4.480994,51.917381],"type":"Point"}
}