{
  "type": "Feature",
  "properties": {
    "iso:country":"NL",
    "sg:address":"Frankeneng 102",
    "sg:city":"Ede Gld",
    "sg:orig_category":"Vers Brood And Banket Fab",
    "sg:phone":"+31 318 636 633",
    "sg:postcode":"6716 AA",
    "sg:province":"Gelderland",
    "wof:name":"Banket Gilde Secretariaat",
    "wof:placetype":"venue"
},
  "geometry": {"coordinates":[5.632077,52.03442],"type":"Point"}
}