{
  "type": "Feature",
  "properties": {
    "iso:country":"NL",
    "sg:address":"Griendstr 23",
    "sg:city":"Amsterdam",
    "sg:orig_category":"Wereldwinkels",
    "sg:phone":"+31 20 619 7534",
    "sg:postcode":"1069 TZ",
    "sg:province":"Noord-Holland",
    "wof:name":"Alverno, Sticht",
    "wof:placetype":"venue"
},
  "geometry": {"coordinates":[4.7799639702,52.3581809998],"type":"Point"}
}