{
  "type": "Feature",
  "properties": {
    "addr:full":"Griendstr 23 Amsterdam Noord-Holland 1069 TZ",
    "addr:housenumber":"23",
    "addr:postcode":"1069 tz",
    "addr:street":"Griendstr",
    "iso:country":"NL",
    "sg:address":"Griendstr 23",
    "sg:city":"Amsterdam",
    "sg:orig_category":"Wereldwinkels",
    "sg:phone":"+31 20 619 7534",
    "sg:postcode":"1069 TZ",
    "sg:province":"Noord-Holland",
    "wof:name":"Alverno, Sticht",
    "wof:placetype":"venue"
},
  "geometry": {"coordinates":[4.7799639702,52.3581809998],"type":"Point"}
}