{
  "type": "Feature",
  "properties": {
    "iso:country":"NL",
    "sg:address":"De Ambachten 7",
    "sg:city":"Zundert",
    "sg:orig_category":"Goederenvervoer Over De Weg",
    "sg:phone":"+31 76 597 4869",
    "sg:postcode":"4881 XZ",
    "sg:province":"Noord-Brabant",
    "wof:name":"Keijl-Transport",
    "wof:placetype":"venue"
},
  "geometry": {"coordinates":[4.649163,51.46402],"type":"Point"}
}