{
  "type": "Feature",
  "properties": {
    "iso:country":"NL",
    "sg:address":"Pastoor Van Herckstraat 49",
    "sg:city":"Gilze",
    "sg:orig_category":"Juridische Dienstverlening",
    "sg:phone":"+31 161 455 744",
    "sg:postcode":"5126 HV",
    "sg:province":"Noord-Brabant",
    "wof:name":"Juridisch Adviesburo Gilze",
    "wof:placetype":"venue"
},
  "geometry": {"coordinates":[4.93155,51.54343],"type":"Point"}
}