{
  "type": "Feature",
  "properties": {
    "iso:country":"NL",
    "sg:address":"Trouwln 55",
    "sg:city":"Tilburg",
    "sg:orig_category":"Herenkleding",
    "sg:phone":"+31 13 542 3103",
    "sg:postcode":"5021 WD",
    "sg:province":"Noord-Brabant",
    "wof:name":"Marijnen",
    "wof:placetype":"venue"
},
  "geometry": {"coordinates":[5.09061,51.548569],"type":"Point"}
}