{
  "type": "Feature",
  "properties": {
    "addr:full":"Trouwln 55 Tilburg Noord-Brabant 5021 WD",
    "addr:housenumber":"55",
    "addr:postcode":"5021 wd",
    "addr:street":"Trouwln",
    "iso:country":"NL",
    "sg:address":"Trouwln 55",
    "sg:city":"Tilburg",
    "sg:orig_category":"Herenkleding",
    "sg:phone":"+31 13 542 3103",
    "sg:postcode":"5021 WD",
    "sg:province":"Noord-Brabant",
    "wof:name":"Marijnen",
    "wof:placetype":"venue"
},
  "geometry": {"coordinates":[5.09061,51.548569],"type":"Point"}
}