{
  "type": "Feature",
  "properties": {
    "addr:full":"Jelle Van Damweg 17 Jubbega Friesland 8411 XA",
    "addr:housenumber":"17",
    "addr:postcode":"8411 xa",
    "addr:street":"Jelle Van Damweg",
    "iso:country":"NL",
    "sg:address":"Jelle Van Damweg 17",
    "sg:city":"Jubbega",
    "sg:orig_category":"Meubelzaken, Woning- And Keukeninrichting",
    "sg:phone":"+31 516 461 228",
    "sg:postcode":"8411 XA",
    "sg:province":"Friesland",
    "wof:name":"Blaauw Woonidee Bv",
    "wof:placetype":"venue"
},
  "geometry": {"coordinates":[6.12311,53.004692],"type":"Point"}
}