{
  "type": "Feature",
  "properties": {
    "addr:full":"M J Van Olmstraat 13 Winschoten Groningen 9672 AE",
    "addr:housenumber":"13",
    "addr:postcode":"9672 ae",
    "addr:street":"M J Van Olmstraat",
    "iso:country":"NL",
    "sg:address":"M J Van Olmstraat 13",
    "sg:city":"Winschoten",
    "sg:orig_category":"Kantoorartikelen",
    "sg:phone":"+31 597 423 712",
    "sg:postcode":"9672 AE",
    "sg:province":"Groningen",
    "wof:name":"Interoffice Kantoorinrichting Bv",
    "wof:placetype":"venue"
},
  "geometry": {"coordinates":[7.046889782,53.1338539124],"type":"Point"}
}