{
  "type": "Feature",
  "properties": {
    "iso:country":"NL",
    "sg:address":"Groenekanseweg 6 A",
    "sg:city":"Groenekan",
    "sg:orig_category":"Kantoorartikelen",
    "sg:phone":"+31 346 213 344",
    "sg:postcode":"3737 AG",
    "sg:province":"Utrecht",
    "wof:name":"Werkhoven'S Vloerenbedrijf En Interieurverzorging",
    "wof:placetype":"venue"
},
  "geometry": {"coordinates":[5.1478571892,52.1243515015],"type":"Point"}
}