{
  "type": "Feature",
  "properties": {
    "addr:full":"Jacob Van Den Eyndestr 73 Voorburg Zuid-Holland 2274 XA",
    "addr:housenumber":"73",
    "addr:postcode":"2274 xa",
    "addr:street":"Jacob Van Den Eyndestr",
    "iso:country":"NL",
    "sg:address":"Jacob Van Den Eyndestr 73",
    "sg:city":"Voorburg",
    "sg:orig_category":"Organisaties And Verenigingen",
    "sg:phone":"+31 70 333 9333",
    "sg:postcode":"2274 XA",
    "sg:province":"Zuid-Holland",
    "wof:name":"Stichting Nederlands Comite Unicef",
    "wof:placetype":"venue"
},
  "geometry": {"coordinates":[4.3566040993,52.0749969482],"type":"Point"}
}