{
  "type": "Feature",
  "properties": {
    "addr:full":"Stationsstraat 5 Oudenbosch Noord-Brabant 4731 GM",
    "addr:housenumber":"5",
    "addr:postcode":"4731 gm",
    "addr:street":"Stationsstraat",
    "iso:country":"NL",
    "sg:address":"Stationsstraat 5",
    "sg:city":"Oudenbosch",
    "sg:orig_category":"Advocaten And Juridische Adviseurs",
    "sg:phone":"+31 165 316 920",
    "sg:postcode":"4731 GM",
    "sg:province":"Noord-Brabant",
    "wof:name":"Advocatenkantoor Dictus",
    "wof:placetype":"venue"
},
  "geometry": {"coordinates":[4.533257,51.588287],"type":"Point"}
}