{
  "type": "Feature",
  "properties": {
    "addr:full":"Trawlerweg 8 Vlaardingen Zuid-Holland 3133 KS",
    "addr:housenumber":"8",
    "addr:postcode":"3133 ks",
    "addr:street":"Trawlerweg",
    "iso:country":"NL",
    "sg:address":"Trawlerweg 8",
    "sg:city":"Vlaardingen",
    "sg:classifiers":[
        {
            "category":"Retail",
            "subcategory":"Storage",
            "type":"Services"
        }
    ],
    "sg:phone":"+31 10 248 0522",
    "sg:postcode":"3133 KS",
    "sg:province":"Zuid-Holland",
    "sg:tags":[
        "opslag",
        "bewaring"
    ],
    "wof:name":"Dijkshoorn Verhuis En Meubeltransport",
    "wof:placetype":"venue"
},
  "geometry": {"coordinates":[4.3146619797,51.9003334045],"type":"Point"}
}