{
  "type": "Feature",
  "properties": {
    "addr:full":"Zuidersingel 58 Berkel En Rodenrijs South Holland 2651 AK",
    "addr:housenumber":"58",
    "addr:postcode":"2651 ak",
    "addr:street":"Zuidersingel",
    "iso:country":"NL",
    "sg:address":"Zuidersingel 58",
    "sg:city":"Berkel En Rodenrijs",
    "sg:orig_category":"Diverse Bedrijfsinstallaties Gh",
    "sg:phone":"+31 10 511 8197",
    "sg:postcode":"2651 AK",
    "sg:province":"South Holland",
    "wof:name":"Handelsonderneming J. Lievaart",
    "wof:placetype":"venue"
},
  "geometry": {"coordinates":[4.448746,51.973366],"type":"Point"}
}