{
  "type": "Feature",
  "properties": {
    "addr:full":"De Matenstr 47 Oldenzaal Overijssel 7572 BV",
    "addr:housenumber":"47",
    "addr:postcode":"7572 bv",
    "iso:country":"NL",
    "sg:address":"De Matenstr 47",
    "sg:city":"Oldenzaal",
    "sg:orig_category":"Petrochemische Industrie - Installaties En Onderhoud",
    "sg:phone":"+31 541 531 363",
    "sg:postcode":"7572 BV",
    "sg:province":"Overijssel",
    "wof:name":"Rosscor Int Bv",
    "wof:placetype":"venue"
},
  "geometry": {"coordinates":[6.913296,52.307915],"type":"Point"}
}