{
  "type": "Feature",
  "properties": {
    "addr:full":"Deppenbroekweg 1 Losser Overijssel 7582 RD",
    "addr:housenumber":"1",
    "addr:postcode":"7582 rd",
    "addr:street":"Deppenbroekweg",
    "iso:country":"NL",
    "sg:address":"Deppenbroekweg 1",
    "sg:city":"Losser",
    "sg:orig_category":"Granen, Zaden And Diervoeders Gh",
    "sg:phone":"+31 53 538 5846",
    "sg:postcode":"7582 RD",
    "sg:province":"Overijssel",
    "wof:name":"Fouragehandel J.H.G. Kienhuis",
    "wof:placetype":"venue"
},
  "geometry": {"coordinates":[6.996155,52.24855],"type":"Point"}
}