{
  "type": "Feature",
  "properties": {
    "iso:country":"NL",
    "sg:address":"Risseweg 3",
    "sg:city":"Weert",
    "sg:orig_category":"Verpakkingsbedrijven",
    "sg:phone":"+31 495 530 068",
    "sg:postcode":"6004 RM",
    "sg:province":"Limburg",
    "wof:name":"Looninpakbedrijf Alverpa Weert Bv",
    "wof:placetype":"venue"
},
  "geometry": {"coordinates":[5.731632,51.263187],"type":"Point"}
}