{
  "type": "Feature",
  "properties": {
    "iso:country":"NL",
    "sg:address":"Sont 1",
    "sg:city":"Delfzyl",
    "sg:orig_category":"Scholen Voor Basisonderwijs",
    "sg:phone":"+31 596 618 336",
    "sg:postcode":"9933 TA",
    "sg:province":"Groningen",
    "wof:name":"Viking Openb, De",
    "wof:placetype":"venue"
},
  "geometry": {"coordinates":[6.909611,53.340858],"type":"Point"}
}