{
  "type": "Feature",
  "properties": {
    "addr:full":"Bloemendaalsewg 48 Bloemendaal Noord-Holland 2061 CL",
    "addr:housenumber":"48",
    "addr:postcode":"2061",
    "addr:street":"Bloemendaalsewg",
    "iso:country":"NL",
    "sg:address":"Bloemendaalsewg 48",
    "sg:city":"Bloemendaal",
    "sg:orig_category":"Poeliers",
    "sg:phone":"+31 23 525 6821",
    "sg:postcode":"2061 CL",
    "sg:province":"Noord-Holland",
    "wof:name":"Wals Poeliers",
    "wof:placetype":"venue"
},
  "geometry": {"coordinates":[4.62031,52.404625],"type":"Point"}
}