{
  "type": "Feature",
  "properties": {
    "iso:country":"NL",
    "sg:address":"Hazelaarstr 2",
    "sg:city":"Vianen Zh",
    "sg:orig_category":"Verenigingsgebouwen",
    "sg:phone":"+31 347 371 905",
    "sg:postcode":"4131 AB",
    "sg:province":"South Holland",
    "wof:name":"Yovi",
    "wof:placetype":"venue"
},
  "geometry": {"coordinates":[5.10277,51.996548],"type":"Point"}
}