{
  "type": "Feature",
  "properties": {
    "addr:full":"Lindegracht 41 Heerenveen Provincie Friesland 8441 GK",
    "addr:housenumber":"41",
    "addr:postcode":"8441 gk",
    "addr:street":"Lindegracht;Provincie Friesland",
    "iso:country":"NL",
    "sg:address":"Lindegracht 41",
    "sg:city":"Heerenveen",
    "sg:orig_category":"Opticiens",
    "sg:phone":"+31 513 624 520",
    "sg:postcode":"8441 GK",
    "sg:province":"Provincie Friesland",
    "wof:name":"E. Groeneveld Heerenveen Optiek Bv",
    "wof:placetype":"venue"
},
  "geometry": {"coordinates":[5.9290947914,52.9584503174],"type":"Point"}
}