{
  "type": "Feature",
  "properties": {
    "addr:full":"Hogenendsewg 11 Didam Gelderland 6942 DS",
    "addr:housenumber":"11",
    "addr:postcode":"6942 ds",
    "addr:street":"Hogenendsewg;Gelderland",
    "iso:country":"NL",
    "sg:address":"Hogenendsewg 11",
    "sg:city":"Didam",
    "sg:orig_category":"Gehandicapteninformatie",
    "sg:phone":"+31 316 223 565",
    "sg:postcode":"6942 DS",
    "sg:province":"Gelderland",
    "wof:name":"Liemers Spel Sport Instuif Gehandicapten, De",
    "wof:placetype":"venue"
},
  "geometry": {"coordinates":[6.128838,51.933517],"type":"Point"}
}