{
  "type": "Feature",
  "properties": {
    "iso:country":"NL",
    "sg:address":"Bokelwg 18-22",
    "sg:city":"Schiedam",
    "sg:orig_category":"Metaaldraaierijen",
    "sg:phone":"+31 10 415 9201",
    "sg:postcode":"3125 AC",
    "sg:province":"South Holland",
    "wof:name":"Heijnen Bv",
    "wof:placetype":"venue"
},
  "geometry": {"coordinates":[4.414395,51.923157],"type":"Point"}
}