{
  "type": "Feature",
  "properties": {
    "addr:full":"Talmastr 20 Ryen North Brabant 5121 TH",
    "addr:housenumber":"20",
    "addr:postcode":"5121 th",
    "addr:street":"Talmastr",
    "iso:country":"NL",
    "sg:address":"Talmastr 20",
    "sg:city":"Ryen",
    "sg:orig_category":"Beeldende Kunstenaars",
    "sg:phone":"+31 161 224 764",
    "sg:postcode":"5121 TH",
    "sg:province":"North Brabant",
    "wof:name":"Hoogh-Franken, M De",
    "wof:placetype":"venue"
},
  "geometry": {"coordinates":[4.9197,51.588017],"type":"Point"}
}