{
  "type": "Feature",
  "properties": {
    "addr:full":"De Braken 14 Boxtel Noord-Brabant 5282 JJ",
    "addr:housenumber":"14",
    "addr:postcode":"5282 jj",
    "addr:street":"De Braken",
    "iso:country":"NL",
    "sg:address":"De Braken 14",
    "sg:city":"Boxtel",
    "sg:orig_category":"Autorijscholen",
    "sg:phone":"+31 411 674 608",
    "sg:postcode":"5282 JJ",
    "sg:province":"Noord-Brabant",
    "wof:name":"Theuns Autorijschool",
    "wof:placetype":"venue"
},
  "geometry": {"coordinates":[5.30443,51.591766],"type":"Point"}
}