{
  "type": "Feature",
  "properties": {
    "iso:country":"NL",
    "sg:address":"Postbus 232",
    "sg:city":"Goes",
    "sg:orig_category":"Voetbalverenigingen",
    "sg:phone":"+31 113 231 333",
    "sg:postcode":"4460 AE",
    "sg:province":"Ohio",
    "wof:name":"Goese",
    "wof:placetype":"venue"
},
  "geometry": {"coordinates":[-83.914169,39.768833],"type":"Point"}
}