{
  "type": "Feature",
  "properties": {
    "addr:full":"Kapeldk 15 Harfsen Gelderland 7217 SH",
    "addr:housenumber":"15;7217",
    "addr:postcode":"sh",
    "addr:street":"Kapeldk;Gelderland",
    "iso:country":"NL",
    "sg:address":"Kapeldk 15",
    "sg:city":"Harfsen",
    "sg:orig_category":"Kappersbenodigdheden",
    "sg:phone":"+31 573 430 514",
    "sg:postcode":"7217 SH",
    "sg:province":"Gelderland",
    "wof:name":"Pasadena Int.",
    "wof:placetype":"venue"
},
  "geometry": {"coordinates":[6.290311,52.18924],"type":"Point"}
}