{
  "type": "Feature",
  "properties": {
    "addr:full":"Spreeuwenstraat 239 Amersfoort Utrecht 3815 SW",
    "addr:housenumber":"239",
    "addr:postcode":"3815 sw",
    "addr:street":"Spreeuwenstraat",
    "iso:country":"NL",
    "sg:address":"Spreeuwenstraat 239",
    "sg:city":"Amersfoort",
    "sg:orig_category":"Verzekeringen",
    "sg:phone":"+31 33 475 8586",
    "sg:postcode":"3815 SW",
    "sg:province":"Utrecht",
    "wof:name":"Ass. Kantoor Alert Vof",
    "wof:placetype":"venue"
},
  "geometry": {"coordinates":[5.412772,52.161194],"type":"Point"}
}