{
  "type": "Feature",
  "properties": {
    "addr:full":"Van Leeuwenhoekweg 13 Dordrecht South Holland 3316 AV",
    "addr:housenumber":"13",
    "addr:postcode":"3316 av",
    "addr:street":"Van Leeuwenhoekweg",
    "iso:country":"NL",
    "sg:address":"Van Leeuwenhoekweg 13",
    "sg:city":"Dordrecht",
    "sg:orig_category":"Goederenvervoer Over De Weg",
    "sg:phone":"+31 78 614 0466",
    "sg:postcode":"3316 AV",
    "sg:province":"South Holland",
    "wof:name":"Transpass Bv",
    "wof:placetype":"venue"
},
  "geometry": {"coordinates":[4.641598,51.797829],"type":"Point"}
}