{
  "type": "Feature",
  "properties": {
    "addr:full":"Gracht 69 Scherpenzeel Fr Friesland 8483 KT",
    "addr:housenumber":"69",
    "addr:postcode":"8483 kt",
    "addr:street":"Gracht",
    "iso:country":"NL",
    "sg:address":"Gracht 69",
    "sg:city":"Scherpenzeel Fr",
    "sg:orig_category":"Modelbouw",
    "sg:phone":"+31 561 481 476",
    "sg:postcode":"8483 KT",
    "sg:province":"Friesland",
    "wof:name":"Wignand",
    "wof:placetype":"venue"
},
  "geometry": {"coordinates":[5.851664,52.82444],"type":"Point"}
}