{
  "type": "Feature",
  "properties": {
    "addr:full":"Springbeekwg 48 Venlo Limburg 5926 RJ",
    "addr:housenumber":"48",
    "addr:postcode":"5926 rj",
    "addr:street":"Springbeekwg",
    "iso:country":"NL",
    "sg:address":"Springbeekwg 48",
    "sg:city":"Venlo",
    "sg:orig_category":"Waterbehandeling En Waterzuiverings- Systemen",
    "sg:phone":"+31 77 382 8291",
    "sg:postcode":"5926 RJ",
    "sg:province":"Limburg",
    "sg:website":"http://www.erka-at.nl",
    "wof:name":"Erka Afvalwater & Techniek",
    "wof:placetype":"venue"
},
  "geometry": {"coordinates":[6.1267490387,51.3582267761],"type":"Point"}
}