{
  "type": "Feature",
  "properties": {
    "addr:full":"Julianastr 2 Veenendaal Utrecht 3905 EM",
    "addr:housenumber":"2",
    "addr:postcode":"3905 em",
    "addr:street":"Julianastr",
    "iso:country":"NL",
    "sg:address":"Julianastr 2",
    "sg:city":"Veenendaal",
    "sg:orig_category":"Modevakscholen",
    "sg:phone":"+31 318 523 888",
    "sg:postcode":"3905 EM",
    "sg:province":"Utrecht",
    "wof:name":"Eva",
    "wof:placetype":"venue"
},
  "geometry": {"coordinates":[5.550926,52.02969],"type":"Point"}
}