{
  "type": "Feature",
  "properties": {
    "addr:full":"Roodzwenk 36 Eemnes Utrecht 3755 WL",
    "addr:housenumber":"36",
    "addr:postcode":"3755 wl",
    "addr:street":"Roodzwenk",
    "iso:country":"NL",
    "sg:address":"Roodzwenk 36",
    "sg:city":"Eemnes",
    "sg:orig_category":"Schilders",
    "sg:phone":"+31 35 531 0514",
    "sg:postcode":"3755 WL",
    "sg:province":"Utrecht",
    "wof:name":"Fokken, Enrico",
    "wof:placetype":"venue"
},
  "geometry": {"coordinates":[5.251326,52.248734],"type":"Point"}
}