{
  "type": "Feature",
  "properties": {
    "addr:full":"Haagjeswg 50 Emmen Drenthe 7815 LM",
    "addr:housenumber":"50",
    "addr:postcode":"7815 lm",
    "addr:street":"Haagjeswg",
    "iso:country":"NL",
    "sg:address":"Haagjeswg 50",
    "sg:city":"Emmen",
    "sg:orig_category":"Psychologen",
    "sg:phone":"+31 591 641 663",
    "sg:postcode":"7815 LM",
    "sg:province":"Drenthe",
    "wof:name":"Psychologie Praktijk Emmen",
    "wof:placetype":"venue"
},
  "geometry": {"coordinates":[6.889023,52.796532],"type":"Point"}
}