{
  "type": "Feature",
  "properties": {
    "iso:country":"NL",
    "sg:address":"Zuring 7",
    "sg:city":"Cuijk",
    "sg:classifiers":[
        {
            "category":"Professional",
            "subcategory":"Accounting & Tax Preparation",
            "type":"Services"
        }
    ],
    "sg:phone":"+31 485 330 171",
    "sg:postcode":"5432 BW",
    "sg:province":"North Brabant",
    "sg:tags":[
        "accountant"
    ],
    "wof:name":"Company Account Bv",
    "wof:placetype":"venue"
},
  "geometry": {"coordinates":[5.861366,51.737545],"type":"Point"}
}