{
  "type": "Feature",
  "properties": {
    "addr:full":"Nipkowstr 17 Zwolle Overijssel 8013 RJ",
    "addr:housenumber":"17",
    "addr:postcode":"8013 rj",
    "addr:street":"Nipkowstr",
    "iso:country":"NL",
    "sg:address":"Nipkowstr 17",
    "sg:city":"Zwolle",
    "sg:orig_category":"Houtgroothandel Hardhout",
    "sg:phone":"+31 38 465 0500",
    "sg:postcode":"8013 RJ",
    "sg:province":"Overijssel",
    "sg:website":"http://www.huyskamps.nl",
    "wof:name":"Huyskamp'S Fijnhouthandel Zwolle Vof",
    "wof:placetype":"venue"
},
  "geometry": {"coordinates":[6.141169,52.491123],"type":"Point"}
}