{
  "type": "Feature",
  "properties": {
    "iso:country":"NL",
    "sg:address":"Kievithof 54",
    "sg:city":"Purmerend",
    "sg:orig_category":"Fotografie Reclame En Mode",
    "sg:phone":"+31 299 413 222",
    "sg:postcode":"1444 VZ",
    "sg:province":"North Holland",
    "wof:name":"Beijnhem, S Van",
    "wof:placetype":"venue"
},
  "geometry": {"coordinates":[4.958705,52.523464],"type":"Point"}
}