{
  "type": "Feature",
  "properties": {
    "addr:full":"Saffierln 16 Hoofddorp Noord-Holland 2132 VZ",
    "addr:housenumber":"16",
    "addr:postcode":"2132 vz",
    "addr:street":"Saffierln",
    "iso:country":"NL",
    "sg:address":"Saffierln 16",
    "sg:city":"Hoofddorp",
    "sg:orig_category":"Automaterialen En Gereedschappen",
    "sg:phone":"+31 23 554 2642",
    "sg:postcode":"2132 VZ",
    "sg:province":"Noord-Holland",
    "wof:name":"Lasaulec Hoofddorp",
    "wof:placetype":"venue"
},
  "geometry": {"coordinates":[4.69296,52.305393],"type":"Point"}
}