{
  "type": "Feature",
  "properties": {
    "iso:country":"NL",
    "sg:address":"Noordzeedk 123",
    "sg:city":"Dinteloord",
    "sg:orig_category":"Grondwerken",
    "sg:phone":"+31 167 522 326",
    "sg:postcode":"4671 TL",
    "sg:province":"Noord-Brabant",
    "wof:name":"Schijvenaars",
    "wof:placetype":"venue"
},
  "geometry": {"coordinates":[4.390896,51.63076],"type":"Point"}
}