{
  "type": "Feature",
  "properties": {
    "addr:full":"Castricummer Werf 3 Castricum Noord-Holland 1901 RW",
    "addr:housenumber":"3;1901",
    "addr:postcode":"rw",
    "addr:street":"Castricummer Werf",
    "iso:country":"NL",
    "sg:address":"Castricummer Werf 3",
    "sg:city":"Castricum",
    "sg:orig_category":"Onderhoudswerken",
    "sg:phone":"+31 251 659 550",
    "sg:postcode":"1901 RW",
    "sg:province":"Noord-Holland",
    "sg:website":"http://www.kobus.nl",
    "wof:name":"Kobus Kennemerland Bv",
    "wof:placetype":"venue"
},
  "geometry": {"coordinates":[4.66415,52.539642],"type":"Point"}
}