{
  "type": "Feature",
  "properties": {
    "addr:full":"Twenteroute 5A Heelweg Gelderland 7055 BD",
    "addr:housenumber":"5a",
    "addr:postcode":"7055 bd",
    "addr:street":"Twenteroute;Gelderland",
    "iso:country":"NL",
    "sg:address":"Twenteroute 5A",
    "sg:city":"Heelweg",
    "sg:orig_category":"Pluimveebedrijven En -Handelaren",
    "sg:phone":"+31 315 242 071",
    "sg:postcode":"7055 BD",
    "sg:province":"Gelderland",
    "wof:name":"Heusinkveld, W L",
    "wof:placetype":"venue"
},
  "geometry": {"coordinates":[6.49306,51.95953],"type":"Point"}
}