{
  "type": "Feature",
  "properties": {
    "iso:country":"NL",
    "sg:address":"Twenteroute 5A",
    "sg:city":"Heelweg",
    "sg:orig_category":"Pluimveebedrijven En -Handelaren",
    "sg:phone":"+31 315 242 071",
    "sg:postcode":"7055 BD",
    "sg:province":"Gelderland",
    "wof:name":"Heusinkveld, W L",
    "wof:placetype":"venue"
},
  "geometry": {"coordinates":[6.49306,51.95953],"type":"Point"}
}