{
  "type": "Feature",
  "properties": {
    "addr:full":"Oliemolenstraat 25 Heerlen Limburg 6411 GJ",
    "addr:housenumber":"25",
    "addr:postcode":"6411 gj",
    "addr:street":"Oliemolenstraat",
    "iso:country":"NL",
    "sg:address":"Oliemolenstraat 25",
    "sg:city":"Heerlen",
    "sg:orig_category":"Verzekeringen",
    "sg:phone":"+31 45 574 0235",
    "sg:postcode":"6411 GJ",
    "sg:province":"Limburg",
    "wof:name":"Marx Financial Planning En Pensioenen",
    "wof:placetype":"venue"
},
  "geometry": {"coordinates":[5.985324,50.884136],"type":"Point"}
}