{
  "type": "Feature",
  "properties": {
    "iso:country":"NL",
    "sg:address":"Jan Pieterszoon Coenstr 58",
    "sg:city":"Utrecht",
    "sg:classifiers":[
        {
            "category":"Food & Beverages",
            "subcategory":"Fruits & Vegetables",
            "type":"Retail Goods"
        }
    ],
    "sg:phone":"+31 30 294 1129",
    "sg:postcode":"3531 EW",
    "sg:province":"Utrecht",
    "sg:tags":[
        "groenten"
    ],
    "wof:name":"Bismillah",
    "wof:placetype":"venue"
},
  "geometry": {"coordinates":[5.097354,52.090874],"type":"Point"}
}