{
  "type": "Feature",
  "properties": {
    "iso:country":"NL",
    "sg:address":"Hoofdstraat 19",
    "sg:city":"Ter Apel",
    "sg:orig_category":"Verzekeringen",
    "sg:phone":"+31 599 581 759",
    "sg:postcode":"9561 JA",
    "sg:province":"Groningen",
    "wof:name":"Assurantie- En Bemiddelings Kantoor Kral",
    "wof:placetype":"venue"
},
  "geometry": {"coordinates":[7.067019,52.873959],"type":"Point"}
}