{
  "type": "Feature",
  "properties": {
    "addr:full":"Kerkbuurt 70 Oostzaan Noord-Holland 1511 BE",
    "addr:housenumber":"70",
    "addr:postcode":"1511",
    "addr:street":"Kerkbuurt",
    "iso:country":"NL",
    "sg:address":"Kerkbuurt 70",
    "sg:city":"Oostzaan",
    "sg:orig_category":"Verlichting And Huishoudartikelen",
    "sg:phone":"+31 75 684 1308",
    "sg:postcode":"1511 BE",
    "sg:province":"Noord-Holland",
    "wof:name":"Vof De Boer Geschenken",
    "wof:placetype":"venue"
},
  "geometry": {"coordinates":[4.874156,52.443256],"type":"Point"}
}