{
  "type": "Feature",
  "properties": {
    "addr:full":"Vierambachtenstraat 6 Hulst Zeeland 4561 WP",
    "addr:housenumber":"6",
    "addr:postcode":"4561 wp",
    "addr:street":"Vierambachtenstraat",
    "iso:country":"NL",
    "sg:address":"Vierambachtenstraat 6",
    "sg:city":"Hulst",
    "sg:orig_category":"Goederenvervoer Over De Weg",
    "sg:phone":"+31 114 315 158",
    "sg:postcode":"4561 WP",
    "sg:province":"Zeeland",
    "wof:name":"Verbraeken",
    "wof:placetype":"venue"
},
  "geometry": {"coordinates":[4.062308,51.285576],"type":"Point"}
}