{
  "type": "Feature",
  "properties": {
    "iso:country":"NL",
    "sg:address":"Baarsjeswg 160",
    "sg:city":"Amsterdam",
    "sg:orig_category":"Verenigingen En Stichtingen",
    "sg:phone":"+31 20 612 0497",
    "sg:postcode":"1057 HN",
    "sg:province":"Noord-Holland",
    "wof:name":"Jamaat-E-Ahl-E-Sunnat, Sticht",
    "wof:placetype":"venue"
},
  "geometry": {"coordinates":[4.862326,52.367844],"type":"Point"}
}