{
  "type": "Feature",
  "properties": {
    "iso:country":"NL",
    "sg:address":"Horsten 2",
    "sg:city":"Eindhoven",
    "sg:orig_category":"Ingenieursbureaus",
    "sg:phone":"+31 40 247 2672",
    "sg:postcode":"5612 AX",
    "sg:province":"Noord-Brabant",
    "sg:website":"http://www.mathmetrics.com",
    "wof:name":"Mathmetrics",
    "wof:placetype":"venue"
},
  "geometry": {"coordinates":[5.495501,51.449879],"type":"Point"}
}