{
  "type": "Feature",
  "properties": {
    "addr:full":"Prins Hendrikkade 33A Amsterdam Noord-Holland 1012 TM",
    "addr:housenumber":"33a",
    "addr:postcode":"1012 tm",
    "addr:street":"Prins Hendrikkade",
    "iso:country":"NL",
    "sg:address":"Prins Hendrikkade 33A",
    "sg:city":"Amsterdam",
    "sg:orig_category":"Binnenvaart",
    "sg:phone":"+31 20 622 7788",
    "sg:postcode":"1012 TM",
    "sg:province":"Noord-Holland",
    "wof:name":"Holland International Rondvaart Amsterdam",
    "wof:placetype":"venue"
},
  "geometry": {"coordinates":[4.897106,52.377823],"type":"Point"}
}