{
  "type": "Feature",
  "properties": {
    "addr:full":"Wilhelminaln 59 Valkenburg Lb Limburg 6301 GH",
    "addr:housenumber":"59",
    "addr:postcode":"lb;6301 gh",
    "addr:street":"Wilhelminaln",
    "iso:country":"NL",
    "sg:address":"Wilhelminaln 59",
    "sg:city":"Valkenburg Lb",
    "sg:orig_category":"Antiquiteiten",
    "sg:phone":"+31 43 601 3874",
    "sg:postcode":"6301 GH",
    "sg:province":"Limburg",
    "wof:name":"Alpha",
    "wof:placetype":"venue"
},
  "geometry": {"coordinates":[5.82998,50.864422],"type":"Point"}
}