{
  "type": "Feature",
  "properties": {
    "iso:country":"NL",
    "sg:address":"Uranusstraat 7",
    "sg:city":"Oudorp Nh",
    "sg:orig_category":"Projectontwikkeling",
    "sg:phone":"+31 72 520 5782",
    "sg:postcode":"1829 XD",
    "sg:province":"Noord-Holland",
    "wof:name":"Uranus Bv",
    "wof:placetype":"venue"
},
  "geometry": {"coordinates":[4.778609,52.630749],"type":"Point"}
}