{
  "type": "Feature",
  "properties": {
    "addr:full":"Zonnenburg 2 Utrecht Utrecht 3512 NL",
    "addr:housenumber":"2",
    "addr:postcode":"3512 nl",
    "addr:street":"Zonnenburg",
    "iso:country":"NL",
    "sg:address":"Zonnenburg 2",
    "sg:city":"Utrecht",
    "sg:orig_category":"Verenigingen En Stichtingen",
    "sg:phone":"+31 592 399 677",
    "sg:postcode":"3512 NL",
    "sg:province":"Utrecht",
    "sg:website":"http://www.sterrenkunde.nl/jwg",
    "wof:name":"Jwg Jongerenwerkgroep Voor Sterrenkunde",
    "wof:placetype":"venue"
},
  "geometry": {"coordinates":[5.128781,52.085056],"type":"Point"}
}