{
  "type": "Feature",
  "properties": {
    "addr:full":"Rustenburg 55 Zaandam Noord-Holland 1506 AX",
    "addr:housenumber":"55",
    "addr:postcode":"1506 ax",
    "addr:street":"Rustenburg",
    "iso:country":"NL",
    "sg:address":"Rustenburg 55",
    "sg:city":"Zaandam",
    "sg:orig_category":"Feestartikelen",
    "sg:phone":"+31 75 616 3641",
    "sg:postcode":"1506 AX",
    "sg:province":"Noord-Holland",
    "wof:name":"Koene, Feestartikelen",
    "wof:placetype":"venue"
},
  "geometry": {"coordinates":[4.817813,52.437588],"type":"Point"}
}