{
  "type": "Feature",
  "properties": {
    "addr:full":"Dragonder 7A Valkenswaard Noord-Brabant 5554 GM",
    "addr:housenumber":"7a",
    "addr:postcode":"5554 gm",
    "addr:street":"Dragonder",
    "iso:country":"NL",
    "sg:address":"Dragonder 7A",
    "sg:city":"Valkenswaard",
    "sg:orig_category":"Automaterialen En Gereedschappen",
    "sg:phone":"+31 40 208 2099",
    "sg:postcode":"5554 GM",
    "sg:province":"Noord-Brabant",
    "sg:website":"http://www.lasaulec.nl",
    "wof:name":"Lasaulec",
    "wof:placetype":"venue"
},
  "geometry": {"coordinates":[5.464324,51.339985],"type":"Point"}
}