{
  "type": "Feature",
  "properties": {
    "addr:full":"Watermolenstraat 3E Roosendaal North Brabant 4708 AN",
    "addr:housenumber":"3e",
    "addr:postcode":"4708 an",
    "addr:street":"Watermolenstraat",
    "iso:country":"NL",
    "sg:address":"Watermolenstraat 3E",
    "sg:city":"Roosendaal",
    "sg:orig_category":"Kantoorartikelen",
    "sg:phone":"+31 165 570 688",
    "sg:postcode":"4708 AN",
    "sg:province":"North Brabant",
    "wof:name":"A & B Kantoormeubelen",
    "wof:placetype":"venue"
},
  "geometry": {"coordinates":[4.4460711479,51.5203742981],"type":"Point"}
}