{
  "type": "Feature",
  "properties": {
    "addr:full":"Parklaan 10 Sittard Limburg 6131 KG",
    "addr:housenumber":"10",
    "addr:postcode":"6131 kg",
    "addr:street":"Parklaan",
    "iso:country":"NL",
    "sg:address":"Parklaan 10",
    "sg:city":"Sittard",
    "sg:orig_category":"Overheidsdiensten",
    "sg:phone":"+31 46 420 5700",
    "sg:postcode":"6131 KG",
    "sg:province":"Limburg",
    "wof:name":"Waterschap Roer En Overmaas",
    "wof:placetype":"venue"
},
  "geometry": {"coordinates":[5.8645892143,50.9967460632],"type":"Point"}
}