{
  "type": "Feature",
  "properties": {
    "addr:full":"Sint Jansstraat 13-15 Groningen Groningen 9712 JM",
    "addr:housenumber":"13-15",
    "addr:postcode":"9712 jm",
    "addr:street":"Sint Jansstraat",
    "iso:country":"NL",
    "sg:address":"Sint Jansstraat 13-15",
    "sg:city":"Groningen",
    "sg:orig_category":"Kantoorartikelen",
    "sg:phone":"+31 50 314 4788",
    "sg:postcode":"9712 JM",
    "sg:province":"Groningen",
    "wof:name":"Kantoorvakhandel Boot &Heijmans",
    "wof:placetype":"venue"
},
  "geometry": {"coordinates":[6.5708770752,53.2195701599],"type":"Point"}
}