{
  "type": "Feature",
  "properties": {
    "addr:full":"Trasmolen 11 Papendrecht Zuid-Holland 3352 AH",
    "addr:housenumber":"11",
    "addr:postcode":"3352 ah",
    "addr:street":"Trasmolen",
    "iso:country":"NL",
    "sg:address":"Trasmolen 11",
    "sg:city":"Papendrecht",
    "sg:orig_category":"Adviesbureaus Scheepsbouwkunde",
    "sg:phone":"+31 78 642 5111",
    "sg:postcode":"3352 AH",
    "sg:province":"Zuid-Holland",
    "wof:name":"Albcon Bv",
    "wof:placetype":"venue"
},
  "geometry": {"coordinates":[4.684917,51.839996],"type":"Point"}
}