{
  "type": "Feature",
  "properties": {
    "addr:full":"Lysterstr 16 Utrecht Utrecht 3514 TD",
    "addr:housenumber":"16",
    "addr:postcode":"3514 td",
    "addr:street":"Lysterstr",
    "iso:country":"NL",
    "sg:address":"Lysterstr 16",
    "sg:city":"Utrecht",
    "sg:orig_category":"Podotherapeuten",
    "sg:phone":"+31 30 271 8119",
    "sg:postcode":"3514 TD",
    "sg:province":"Utrecht",
    "wof:name":"Luxa Bv",
    "wof:placetype":"venue"
},
  "geometry": {"coordinates":[5.117712,52.097828],"type":"Point"}
}