{
  "type": "Feature",
  "properties": {
    "iso:country":"NL",
    "sg:address":"Waanderwg 50",
    "sg:city":"Emmen",
    "sg:orig_category":"Zuivel - Groothandel",
    "sg:phone":"+31 591 679 988",
    "sg:postcode":"7812 HZ",
    "sg:province":"Drenthe",
    "wof:name":"Dp Supply",
    "wof:placetype":"venue"
},
  "geometry": {"coordinates":[6.878359,52.752438],"type":"Point"}
}