{
  "type": "Feature",
  "properties": {
    "addr:full":"Markt 3 Hardenberg NL.08 7772 AE",
    "addr:housenumber":"3;nl.08",
    "addr:postcode":"7772 ae",
    "addr:street":"Markt",
    "iso:country":"NL",
    "sg:address":"Markt 3",
    "sg:city":"Hardenberg",
    "sg:orig_category":"Wasserettes And Stomerijen",
    "sg:phone":"+31 523 261 557",
    "sg:postcode":"7772 AE",
    "sg:province":"NL.08",
    "wof:name":"Stomerij/Wasserij Moderna Vof",
    "wof:placetype":"venue"
},
  "geometry": {"coordinates":[6.6183748245,52.5758857727],"type":"Point"}
}