{
  "type": "Feature",
  "properties": {
    "addr:full":"Baarnseveste 9 Nieuwegein Utrecht 3432 BA",
    "addr:housenumber":"9",
    "addr:postcode":"3432 ba",
    "addr:street":"Baarnseveste",
    "iso:country":"NL",
    "sg:address":"Baarnseveste 9",
    "sg:city":"Nieuwegein",
    "sg:orig_category":"Voetbalverenigingen",
    "sg:phone":"+31 30 604 3807",
    "sg:postcode":"3432 BA",
    "sg:province":"Utrecht",
    "wof:name":"Aan De Vecht",
    "wof:placetype":"venue"
},
  "geometry": {"coordinates":[5.093836,52.021873],"type":"Point"}
}