{
  "type": "Feature",
  "properties": {
    "iso:country":"NL",
    "sg:address":"Aurikelstr 44",
    "sg:city":"Amsterdam",
    "sg:orig_category":"Administratie- En Boekhoudkantoren",
    "sg:phone":"+31 20 494 1071",
    "sg:postcode":"1032 AW",
    "sg:province":"North Holland",
    "wof:name":"Emster, J Van Den",
    "wof:placetype":"venue"
},
  "geometry": {"coordinates":[4.917554,52.396233],"type":"Point"}
}