{
  "type": "Feature",
  "properties": {
    "iso:country":"NL",
    "sg:address":"Bankaplein 1",
    "sg:city":"'S Gravenhage",
    "sg:orig_category":"Bedrijfs- And Managementsconsultants",
    "sg:phone":"+31 70 355 9700",
    "sg:postcode":"2585 EV",
    "sg:province":"South Holland",
    "wof:name":"The Wissema Group Bv",
    "wof:placetype":"venue"
},
  "geometry": {"coordinates":[4.303329,52.092999],"type":"Point"}
}