{
  "type": "Feature",
  "properties": {
    "addr:full":"Lindtsedk 58 Zwyndrecht Zuid-Holland 3336 LE",
    "addr:housenumber":"58",
    "addr:postcode":"3336 le",
    "addr:street":"Lindtsedk",
    "iso:country":"NL",
    "sg:address":"Lindtsedk 58",
    "sg:city":"Zwyndrecht",
    "sg:orig_category":"Automaterialen En Gereedschappen",
    "sg:phone":"+31 78 619 5011",
    "sg:postcode":"3336 LE",
    "sg:province":"Zuid-Holland",
    "wof:name":"Becarparts Bv",
    "wof:placetype":"venue"
},
  "geometry": {"coordinates":[4.60844,51.809719],"type":"Point"}
}