{
  "type": "Feature",
  "properties": {
    "addr:full":"Baroniehof 189 Helmond North Brabant 5709 HL",
    "addr:housenumber":"189",
    "addr:postcode":"5709 hl",
    "addr:street":"Baroniehof",
    "iso:country":"NL",
    "sg:address":"Baroniehof 189",
    "sg:city":"Helmond",
    "sg:orig_category":"Organisatiebureaus",
    "sg:phone":"+31 492 556 067",
    "sg:postcode":"5709 HL",
    "sg:province":"North Brabant",
    "wof:name":"Oro Sticht De Meent",
    "wof:placetype":"venue"
},
  "geometry": {"coordinates":[5.7035479546,51.4727020264],"type":"Point"}
}