{
  "type": "Feature",
  "properties": {
    "iso:country":"NL",
    "sg:address":"Parkstraat 9",
    "sg:city":"Zaandam",
    "sg:orig_category":"Schoonheidssalons",
    "sg:phone":"+31 75 617 4365",
    "sg:postcode":"1506 WB",
    "sg:province":"Noord-Holland",
    "wof:name":"Agatha Staal-Aafjes",
    "wof:placetype":"venue"
},
  "geometry": {"coordinates":[4.817649,52.444298],"type":"Point"}
}