{
  "type": "Feature",
  "properties": {
    "addr:full":"Keiweg 24 Oosterhout Nb Noord-Brabant 4901 JA",
    "addr:housenumber":"24",
    "addr:postcode":"4901 ja",
    "addr:street":"Keiweg",
    "iso:country":"NL",
    "sg:address":"Keiweg 24",
    "sg:city":"Oosterhout Nb",
    "sg:orig_category":"Makelaars In Onroerend Goed",
    "sg:phone":"+31 162 447 447",
    "sg:postcode":"4901 JA",
    "sg:province":"Noord-Brabant",
    "wof:name":"Van De Water Bv Makelaardij Oz",
    "wof:placetype":"venue"
},
  "geometry": {"coordinates":[4.86066,51.64283],"type":"Point"}
}