{
  "type": "Feature",
  "properties": {
    "iso:country":"NL",
    "sg:address":"Keiweg 24",
    "sg:city":"Oosterhout Nb",
    "sg:orig_category":"Makelaars In Onroerend Goed",
    "sg:phone":"+31 162 447 447",
    "sg:postcode":"4901 JA",
    "sg:province":"Noord-Brabant",
    "wof:name":"Van De Water Bv Makelaardij Oz",
    "wof:placetype":"venue"
},
  "geometry": {"coordinates":[4.86066,51.64283],"type":"Point"}
}