{
  "type": "Feature",
  "properties": {
    "addr:full":"A Dekenln 49 S Gravenhage South Holland 2533 SG",
    "addr:housenumber":"49",
    "addr:postcode":"2533 sg",
    "addr:street":"S Gravenhage",
    "iso:country":"NL",
    "sg:address":"A Dekenln 49",
    "sg:city":"S Gravenhage",
    "sg:orig_category":"Begrafenisverzorging",
    "sg:phone":"+31 6 27108298",
    "sg:postcode":"2533 SG",
    "sg:province":"South Holland",
    "wof:name":"Forma Memoria",
    "wof:placetype":"venue"
},
  "geometry": {"coordinates":[4.28581,52.05286],"type":"Point"}
}