{
  "type": "Feature",
  "properties": {
    "addr:full":"Benschopperstraat 16 Ijsselstein Ut Utrecht 3401 DH",
    "addr:housenumber":"16",
    "addr:postcode":"3401 dh",
    "addr:street":"Benschopperstraat",
    "iso:country":"NL",
    "sg:address":"Benschopperstraat 16",
    "sg:city":"Ijsselstein Ut",
    "sg:orig_category":"Apothekers",
    "sg:phone":"+31 30 688 1370",
    "sg:postcode":"3401 DH",
    "sg:province":"Utrecht",
    "wof:name":"Apotheek Lamberts",
    "wof:placetype":"venue"
},
  "geometry": {"coordinates":[5.042187,52.018654],"type":"Point"}
}