{
  "type": "Feature",
  "properties": {
    "addr:full":"Witte Paal 12 Schagen North Holland 1742 NL",
    "addr:housenumber":"12",
    "addr:postcode":"1742 nl",
    "addr:street":"Witte Paal",
    "iso:country":"NL",
    "sg:address":"Witte Paal 12",
    "sg:city":"Schagen",
    "sg:orig_category":"Kermisexploitatie",
    "sg:phone":"+31 224 296 679",
    "sg:postcode":"1742 NL",
    "sg:province":"North Holland",
    "wof:name":"Corput, W P Van Den",
    "wof:placetype":"venue"
},
  "geometry": {"coordinates":[4.806415,52.781853],"type":"Point"}
}