{
  "type": "Feature",
  "properties": {
    "addr:full":"Spoorlaan 72 Oisterwijk Noord-Brabant 5061 HC",
    "addr:housenumber":"72",
    "addr:postcode":"5061 hc",
    "addr:street":"Spoorlaan",
    "iso:country":"NL",
    "sg:address":"Spoorlaan 72",
    "sg:city":"Oisterwijk",
    "sg:orig_category":"Huishoudapparatuur, Televisies And Radio'S",
    "sg:phone":"+31 13 521 9440",
    "sg:postcode":"5061 HC",
    "sg:province":"Noord-Brabant",
    "wof:name":"Vof Van Der Steen - Boeren",
    "wof:placetype":"venue"
},
  "geometry": {"coordinates":[5.196003,51.582115],"type":"Point"}
}