{
  "type": "Feature",
  "properties": {
    "addr:full":"Veenweg 9 Epe Gelderland 8162 RJ",
    "addr:housenumber":"9",
    "addr:postcode":"8162 rj",
    "addr:street":"Veenweg;Gelderland",
    "iso:country":"NL",
    "sg:address":"Veenweg 9",
    "sg:city":"Epe",
    "sg:orig_category":"Kampeerterreinen",
    "sg:phone":"+31 578 612 978",
    "sg:postcode":"8162 RJ",
    "sg:province":"Gelderland",
    "wof:name":"De Berghoeve",
    "wof:placetype":"venue"
},
  "geometry": {"coordinates":[5.9412899017,52.3357086182],"type":"Point"}
}