{
  "type": "Feature",
  "properties": {
    "addr:full":"Osdorper Ban 5 Amsterdam Noord-Holland 1068 LD",
    "addr:housenumber":"5",
    "addr:postcode":"1068 ld",
    "addr:street":"Osdorper Ban",
    "iso:country":"NL",
    "sg:address":"Osdorper Ban 5",
    "sg:city":"Amsterdam",
    "sg:orig_category":"Werving And Selectie Van Tijdelijk Personeel And Uitzendkantoren",
    "sg:phone":"+31 20 619 6450",
    "sg:postcode":"1068 LD",
    "sg:province":"Noord-Holland",
    "wof:name":"Acadeem Uitzendbureau",
    "wof:placetype":"venue"
},
  "geometry": {"coordinates":[4.8035402298,52.3625068665],"type":"Point"}
}