{
  "type": "Feature",
  "properties": {
    "iso:country":"NL",
    "sg:address":"Burg Rendorpstr 11",
    "sg:city":"Amsterdam",
    "sg:orig_category":"Videotheken",
    "sg:phone":"+31 20 613 6385",
    "sg:postcode":"1064 EL",
    "sg:province":"North Holland",
    "sg:website":"http://www.videoland.nl",
    "wof:name":"Sloterplas, De",
    "wof:placetype":"venue"
},
  "geometry": {"coordinates":[4.826763,52.373795],"type":"Point"}
}