{
  "type": "Feature",
  "properties": {
    "addr:full":"Oostmaasln 39 Rotterdam Zuid-Holland 3063 AN",
    "addr:housenumber":"39",
    "addr:postcode":"3063 an",
    "addr:street":"Oostmaasln",
    "iso:country":"NL",
    "sg:address":"Oostmaasln 39",
    "sg:city":"Rotterdam",
    "sg:orig_category":"Adviesbureaus Bedrijfsorganisatie",
    "sg:phone":"+31 10 212 2248",
    "sg:postcode":"3063 AN",
    "sg:province":"Zuid-Holland",
    "wof:name":"Kintraco",
    "wof:placetype":"venue"
},
  "geometry": {"coordinates":[4.51664,51.917206],"type":"Point"}
}