{
  "type": "Feature",
  "properties": {
    "iso:country":"NL",
    "sg:address":"Twentepoort W 5",
    "sg:city":"Almelo",
    "sg:orig_category":"Machineonderhoud En -Reparatie",
    "sg:phone":"+31 546 822 135",
    "sg:postcode":"7609 RD",
    "sg:province":"NL.08",
    "sg:website":"http://www.okegroep.nl",
    "wof:name":"Ok\u00e9 Bv",
    "wof:placetype":"venue"
},
  "geometry": {"coordinates":[6.648901,52.329124],"type":"Point"}
}