{
  "type": "Feature",
  "properties": {
    "addr:full":"Pannekoekstr 62A Rotterdam South Holland 3011 LJ",
    "addr:housenumber":"62a",
    "addr:postcode":"3011 lj",
    "addr:street":"Pannekoekstr",
    "iso:country":"NL",
    "sg:address":"Pannekoekstr 62A",
    "sg:city":"Rotterdam",
    "sg:orig_category":"Muziekinstrumenten En Bladmuziek",
    "sg:phone":"+31 10 413 7874",
    "sg:postcode":"3011 LJ",
    "sg:province":"South Holland",
    "wof:name":"Snoeks",
    "wof:placetype":"venue"
},
  "geometry": {"coordinates":[4.488343,51.923054],"type":"Point"}
}