{
  "type": "Feature",
  "properties": {
    "iso:country":"NL",
    "sg:address":"Oudestraat 35",
    "sg:city":"Neede",
    "sg:orig_category":"Opticiens",
    "sg:phone":"+31 545 291 391",
    "sg:postcode":"7161 DS",
    "sg:province":"Gelderland",
    "wof:name":"Van Rugge Optiek",
    "wof:placetype":"venue"
},
  "geometry": {"coordinates":[-121.3170623779,38.2996330261],"type":"Point"}
}