{
  "type": "Feature",
  "properties": {
    "addr:full":"Europaboulevard 183 Alkmaar North Holland 1825 RE",
    "addr:housenumber":"183",
    "addr:postcode":"1825 re",
    "addr:street":"Europaboulevard",
    "iso:country":"NL",
    "sg:address":"Europaboulevard 183",
    "sg:city":"Alkmaar",
    "sg:orig_category":"Opticiens",
    "sg:phone":"+31 72 562 7450",
    "sg:postcode":"1825 RE",
    "sg:province":"North Holland",
    "wof:name":"Hans Anders Opticiens",
    "wof:placetype":"venue"
},
  "geometry": {"coordinates":[4.7567400932,52.6546516418],"type":"Point"}
}