{
  "type": "Feature",
  "properties": {
    "addr:full":"Myrtegaarde 3 Nieuwegein Utrecht 3436 JP",
    "addr:housenumber":"3",
    "addr:postcode":"3436 jp",
    "addr:street":"Myrtegaarde",
    "iso:country":"NL",
    "sg:address":"Myrtegaarde 3",
    "sg:city":"Nieuwegein",
    "sg:orig_category":"Adviesbureaus Bouwkunde",
    "sg:phone":"+31 30 604 8707",
    "sg:postcode":"3436 JP",
    "sg:province":"Utrecht",
    "wof:name":"Zimmerman, Buro Ton",
    "wof:placetype":"venue"
},
  "geometry": {"coordinates":[5.0666489601,52.0346069336],"type":"Point"}
}