{
  "type": "Feature",
  "properties": {
    "addr:full":"Burg Van Sevenhovenstr 68 Stadskanaal Groningen 9503 CG",
    "addr:housenumber":"68",
    "addr:postcode":"9503 cg",
    "addr:street":"Burg;Sevenhovenstr",
    "iso:country":"NL",
    "sg:address":"Burg Van Sevenhovenstr 68",
    "sg:city":"Stadskanaal",
    "sg:orig_category":"Psychologen",
    "sg:phone":"+31 599 650 548",
    "sg:postcode":"9503 CG",
    "sg:province":"Groningen",
    "wof:name":"Holtjer & Jacobs",
    "wof:placetype":"venue"
},
  "geometry": {"coordinates":[6.959475,52.984375],"type":"Point"}
}