{
  "type": "Feature",
  "properties": {
    "iso:country":"NL",
    "sg:address":"Opperduit 398",
    "sg:city":"Lekkerkerk",
    "sg:orig_category":"Voegwerken",
    "sg:phone":"+31 180 661 141",
    "sg:postcode":"2941 AR",
    "sg:province":"South Holland",
    "wof:name":"Hoek & Hoogendijk Vof, Van Den",
    "wof:placetype":"venue"
},
  "geometry": {"coordinates":[4.703446,51.899166],"type":"Point"}
}