{
  "type": "Feature",
  "properties": {
    "addr:full":"Jacobus Pennweg 9 Hilversum Noord-Holland 1217 JG",
    "addr:housenumber":"9",
    "addr:postcode":"1217 jg",
    "addr:street":"Jacobus Pennweg",
    "iso:country":"NL",
    "sg:address":"Jacobus Pennweg 9",
    "sg:city":"Hilversum",
    "sg:orig_category":"Diverse Opleidingen And Onderwijs",
    "sg:phone":"+31 35 624 6355",
    "sg:postcode":"1217 JG",
    "sg:province":"Noord-Holland",
    "wof:name":"Fairfield College",
    "wof:placetype":"venue"
},
  "geometry": {"coordinates":[5.163197,52.233749],"type":"Point"}
}