{
  "type": "Feature",
  "properties": {
    "addr:full":"Postbus 2177 Gouda South Holland 2800 BH",
    "addr:housenumber":"2177",
    "addr:postcode":"2800 bh",
    "addr:street":"Postbus",
    "iso:country":"NL",
    "sg:address":"Postbus 2177",
    "sg:city":"Gouda",
    "sg:orig_category":"Glas, Porselein En Aardewerk",
    "sg:phone":"+31 182 585 934",
    "sg:postcode":"2800 BH",
    "sg:province":"South Holland",
    "wof:name":"Aero-Kim Bv",
    "wof:placetype":"venue"
},
  "geometry": {"coordinates":[4.710715,52.010006],"type":"Point"}
}