{
  "type": "Feature",
  "properties": {
    "addr:full":"Pauvrewg 29 Etten Leur North Brabant 4879 NJ",
    "addr:housenumber":"29",
    "addr:postcode":"4879 nj",
    "addr:street":"Pauvrewg",
    "iso:country":"NL",
    "sg:address":"Pauvrewg 29",
    "sg:city":"Etten Leur",
    "sg:orig_category":"Machineonderhoud En -Reparatie",
    "sg:phone":"+31 76 504 0695",
    "sg:postcode":"4879 NJ",
    "sg:province":"North Brabant",
    "wof:name":"Avv",
    "wof:placetype":"venue"
},
  "geometry": {"coordinates":[4.6255311966,51.5589256287],"type":"Point"}
}