{
  "type": "Feature",
  "properties": {
    "iso:country":"NL",
    "sg:address":"Waalstr 67",
    "sg:city":"Utrecht",
    "sg:orig_category":"Onderhoudswerken",
    "sg:phone":"+31 30 289 2853",
    "sg:postcode":"3522 SC",
    "sg:province":"Utrecht",
    "wof:name":"A & T",
    "wof:placetype":"venue"
},
  "geometry": {"coordinates":[5.116831,52.07394],"type":"Point"}
}