{
  "type": "Feature",
  "properties": {
    "addr:full":"Klaaskampen 1 Laren Nh North Holland 1251 KM",
    "addr:housenumber":"1",
    "addr:street":"Klaaskampen;Nh North;1251 Km",
    "iso:country":"NL",
    "sg:address":"Klaaskampen 1",
    "sg:city":"Laren Nh",
    "sg:orig_category":"Onroerende Goederen",
    "sg:phone":"+31 35 533 5592",
    "sg:postcode":"1251 KM",
    "sg:province":"North Holland",
    "wof:name":"Kappa Bv",
    "wof:placetype":"venue"
},
  "geometry": {"coordinates":[5.223998,52.256393],"type":"Point"}
}