{
  "type": "Feature",
  "properties": {
    "addr:full":"Werfpad 4 'S Hertogenbosch North Brabant 5212 VJ",
    "addr:housenumber":"4 ' s",
    "addr:postcode":"5212 vj",
    "addr:street":"Werfpad;Hertogenbosch",
    "iso:country":"NL",
    "sg:address":"Werfpad 4",
    "sg:city":"'S Hertogenbosch",
    "sg:orig_category":"Bouwnijverheidsmachines Gh",
    "sg:phone":"+31 73 613 6050",
    "sg:postcode":"5212 VJ",
    "sg:province":"North Brabant",
    "wof:name":"Bo-Rent",
    "wof:placetype":"venue"
},
  "geometry": {"coordinates":[5.302702,51.697079],"type":"Point"}
}