{
  "type": "Feature",
  "properties": {
    "addr:full":"J Obrechtstr 56 Amsterdam Noord-Holland 1071 KN",
    "addr:housenumber":"56",
    "addr:postcode":"1071 kn",
    "iso:country":"NL",
    "sg:address":"J Obrechtstr 56",
    "sg:city":"Amsterdam",
    "sg:orig_category":"Verenigingen En Stichtingen",
    "sg:phone":"+31 20 676 2032",
    "sg:postcode":"1071 KN",
    "sg:province":"Noord-Holland",
    "wof:name":"Mondriaan, Sticht",
    "wof:placetype":"venue"
},
  "geometry": {"coordinates":[4.876188,52.354622],"type":"Point"}
}