{
  "type": "Feature",
  "properties": {
    "addr:full":"Noordeind 18 Emmen Drenthe 7815 PA",
    "addr:housenumber":"18",
    "addr:postcode":"7815 pa",
    "addr:street":"Noordeind",
    "iso:country":"NL",
    "sg:address":"Noordeind 18",
    "sg:city":"Emmen",
    "sg:orig_category":"Binnenhuisarchitecten",
    "sg:phone":"+31 591 649 074",
    "sg:postcode":"7815 PA",
    "sg:province":"Drenthe",
    "wof:name":"Marja Otter, Meubelstoff. En Binnenhuisa",
    "wof:placetype":"venue"
},
  "geometry": {"coordinates":[6.890379,52.792774],"type":"Point"}
}