{
  "type": "Feature",
  "properties": {
    "addr:full":"Burgemeester Martenssingel 100 Gouda South Holland 2806 CX",
    "addr:housenumber":"100",
    "addr:postcode":"2806 cx",
    "addr:street":"Burgemeester Martenssingel",
    "iso:country":"NL",
    "sg:address":"Burgemeester Martenssingel 100",
    "sg:city":"Gouda",
    "sg:orig_category":"Fietshandelaren",
    "sg:phone":"+31 182 513 520",
    "sg:postcode":"2806 CX",
    "sg:province":"South Holland",
    "wof:name":"Van Leeuwen Tweewielers Bv.",
    "wof:placetype":"venue"
},
  "geometry": {"coordinates":[4.718111,52.010044],"type":"Point"}
}