{
  "type": "Feature",
  "properties": {
    "addr:full":"Poortstr 9 Serooskerke Walch Zeeland 4353 BH",
    "addr:housenumber":"9",
    "addr:postcode":"4353 bh",
    "addr:street":"Poortstr;Walch",
    "iso:country":"NL",
    "sg:address":"Poortstr 9",
    "sg:city":"Serooskerke Walch",
    "sg:orig_category":"Wereldwinkels",
    "sg:phone":"+31 118 592 665",
    "sg:postcode":"4353 BH",
    "sg:province":"Zeeland",
    "wof:name":"Wereldwinkel",
    "wof:placetype":"venue"
},
  "geometry": {"coordinates":[3.5974709988,51.5491981506],"type":"Point"}
}