{
  "type": "Feature",
  "properties": {
    "addr:full":"Castricummerw 6 Uitgeest Noord-Holland 1911 GA",
    "addr:housenumber":"6",
    "addr:postcode":"1911 ga",
    "addr:street":"Castricummerw",
    "iso:country":"NL",
    "sg:address":"Castricummerw 6",
    "sg:city":"Uitgeest",
    "sg:orig_category":"Verenigingsgebouwen",
    "sg:phone":"+31 251 313 430",
    "sg:postcode":"1911 GA",
    "sg:province":"Noord-Holland",
    "wof:name":"Jeugdhuis Herv Ger Fed",
    "wof:placetype":"venue"
},
  "geometry": {"coordinates":[-83.222931,32.678131],"type":"Point"}
}