{
  "type": "Feature",
  "properties": {
    "iso:country":"NL",
    "sg:address":"Sleutelbloemstraat 26",
    "sg:city":"Apeldoorn",
    "sg:orig_category":"Woningbouwverenigingen",
    "sg:phone":"+31 55 369 6969",
    "sg:postcode":"7322 AG",
    "sg:province":"Gelderland",
    "wof:name":"Woningstichting De Goede Woning",
    "wof:placetype":"venue"
},
  "geometry": {"coordinates":[5.9759459496,52.2255783081],"type":"Point"}
}