{
  "type": "Feature",
  "properties": {
    "iso:country":"NL",
    "sg:address":"A Paulownaln 179",
    "sg:city":"Zeist",
    "sg:orig_category":"Vertalers",
    "sg:phone":"+31 30 697 5344",
    "sg:postcode":"3708 HR",
    "sg:province":"Utrecht",
    "wof:name":"Leenders-Saddler, C M",
    "wof:placetype":"venue"
},
  "geometry": {"coordinates":[5.262415,52.072674],"type":"Point"}
}