{
  "type": "Feature",
  "properties": {
    "addr:full":"Oostgriend 89 Almere Flevoland 1356 HH",
    "addr:housenumber":"89",
    "addr:postcode":"1356 hh",
    "addr:street":"Oostgriend;Flevoland",
    "iso:country":"NL",
    "sg:address":"Oostgriend 89",
    "sg:city":"Almere",
    "sg:orig_category":"Webdesign Bureaus",
    "sg:phone":"+31 6 15058071",
    "sg:postcode":"1356 HH",
    "sg:province":"Flevoland",
    "sg:website":"http://www.webontwikkeling.nl",
    "wof:name":"Sirius",
    "wof:placetype":"venue"
},
  "geometry": {"coordinates":[5.2398900986,52.3373603821],"type":"Point"}
}