{
  "type": "Feature",
  "properties": {
    "addr:full":"Willemstraat 23 Utrecht Utrecht 3511 RG",
    "addr:housenumber":"23",
    "addr:postcode":"3511 rg",
    "addr:street":"Willemstraat",
    "iso:country":"NL",
    "sg:address":"Willemstraat 23",
    "sg:city":"Utrecht",
    "sg:orig_category":"Kappers",
    "sg:phone":"+31 30 234 0350",
    "sg:postcode":"3511 RG",
    "sg:province":"Utrecht",
    "wof:name":"Louise Hairfashion For Men",
    "wof:placetype":"venue"
},
  "geometry": {"coordinates":[5.11346,52.093857],"type":"Point"}
}