{
  "type": "Feature",
  "properties": {
    "addr:full":"Postbus 4016 Schiedam South Holland 3102 GA",
    "addr:postcode":"4016;3102 ga",
    "addr:street":"Postbus",
    "iso:country":"NL",
    "sg:address":"Postbus 4016",
    "sg:city":"Schiedam",
    "sg:orig_category":"Juwelen - Groothandel",
    "sg:phone":"+31 10 470 2109",
    "sg:postcode":"3102 GA",
    "sg:province":"South Holland",
    "wof:name":"Present Bv",
    "wof:placetype":"venue"
},
  "geometry": {"coordinates":[4.40013,51.918018],"type":"Point"}
}