{
  "type": "Feature",
  "properties": {
    "addr:full":"Europa Ring 220 Wierden Overijssel 7641 DG",
    "addr:housenumber":"220",
    "addr:postcode":"7641 dg",
    "addr:street":"Europa Ring",
    "iso:country":"NL",
    "sg:address":"Europa Ring 220",
    "sg:city":"Wierden",
    "sg:orig_category":"Verzekeringen - Verzekeringskantoren",
    "sg:phone":"+31 546 574 682",
    "sg:postcode":"7641 DG",
    "sg:province":"Overijssel",
    "wof:name":"Oude Hergelink, A J",
    "wof:placetype":"venue"
},
  "geometry": {"coordinates":[6.608185,52.364529],"type":"Point"}
}