{
  "type": "Feature",
  "properties": {
    "addr:full":"Goereesestraat 1 'S Gravenhage Zuid-Holland 2583 NL",
    "addr:housenumber":"1 '",
    "addr:postcode":"2583 nl",
    "addr:street":"Goereesestraat",
    "iso:country":"NL",
    "sg:address":"Goereesestraat 1",
    "sg:city":"'S Gravenhage",
    "sg:orig_category":"Boekenuitgeverijen",
    "sg:phone":"+31 70 352 3663",
    "sg:postcode":"2583 NL",
    "sg:province":"Zuid-Holland",
    "wof:name":"Klarenbeek'S Randstad Uitgeversmaatschappij",
    "wof:placetype":"venue"
},
  "geometry": {"coordinates":[4.25635,52.089188],"type":"Point"}
}