{
  "type": "Feature",
  "properties": {
    "iso:country":"NL",
    "sg:address":"Binnenwg 12",
    "sg:city":"Baambrugge",
    "sg:orig_category":"Accountants - Administratie- Consulenten En -Kantoren",
    "sg:phone":"+31 294 295 630",
    "sg:postcode":"1396 KM",
    "sg:province":"Utrecht",
    "wof:name":"Groot-Oskam, De",
    "wof:placetype":"venue"
},
  "geometry": {"coordinates":[4.993169,52.242756],"type":"Point"}
}