{
  "type": "Feature",
  "properties": {
    "addr:full":"Verhuizensestraat 5 Ingen Gelderland 4031 KS",
    "addr:housenumber":"5",
    "addr:postcode":"4031 ks",
    "addr:street":"Verhuizensestraat;Gelderland",
    "iso:country":"NL",
    "sg:address":"Verhuizensestraat 5",
    "sg:city":"Ingen",
    "sg:orig_category":"Kampeerterreinen",
    "sg:phone":"+31 344 603 383",
    "sg:postcode":"4031 KS",
    "sg:province":"Gelderland",
    "wof:name":"Bv Het Zwanemeer",
    "wof:placetype":"venue"
},
  "geometry": {"coordinates":[-98.3202133179,38.4980583191],"type":"Point"}
}