{
  "type": "Feature",
  "properties": {
    "iso:country":"NL",
    "sg:address":"Schootsveld 6",
    "sg:city":"Vierlingsbeek",
    "sg:orig_category":"Verlichting And Huishoudartikelen",
    "sg:phone":"+31 478 633 633",
    "sg:postcode":"5821 EH",
    "sg:province":"Noord-Brabant",
    "wof:name":"M & C Gordijnenatelier Bv",
    "wof:placetype":"venue"
},
  "geometry": {"coordinates":[5.999598,51.596424],"type":"Point"}
}