{
  "type": "Feature",
  "properties": {
    "addr:full":"Beatrixln 25 Soest Utrecht 3761 BC",
    "addr:housenumber":"25",
    "addr:postcode":"3761 bc",
    "addr:street":"Beatrixln",
    "iso:country":"NL",
    "sg:address":"Beatrixln 25",
    "sg:city":"Soest",
    "sg:orig_category":"Voetbalverenigingen",
    "sg:phone":"+31 35 602 8407",
    "sg:postcode":"3761 BC",
    "sg:province":"Utrecht",
    "wof:name":"Dvs Davo",
    "wof:placetype":"venue"
},
  "geometry": {"coordinates":[5.294202,52.185459],"type":"Point"}
}