{
  "type": "Feature",
  "properties": {
    "iso:country":"NL",
    "sg:address":"Troelstraln 1",
    "sg:city":"Baarn",
    "sg:orig_category":"Verloskundigen",
    "sg:phone":"+31 35 541 4559",
    "sg:postcode":"3741 VJ",
    "sg:province":"Utrecht",
    "wof:name":"Elferink-Jongeboer, P C",
    "wof:placetype":"venue"
},
  "geometry": {"coordinates":[5.286748,52.21843],"type":"Point"}
}