{
  "type": "Feature",
  "properties": {
    "addr:full":"Fannius Scholtenstraat 18 Amsterdam North Holland 1051 EX",
    "addr:housenumber":"18",
    "addr:postcode":"1051 ex",
    "addr:street":"Fannius Scholtenstraat",
    "iso:country":"NL",
    "sg:address":"Fannius Scholtenstraat 18",
    "sg:city":"Amsterdam",
    "sg:orig_category":"Verhuisdiensten",
    "sg:phone":"+31 20 686 1430",
    "sg:postcode":"1051 EX",
    "sg:province":"North Holland",
    "wof:name":"A Elhamdamoui",
    "wof:placetype":"venue"
},
  "geometry": {"coordinates":[4.873107,52.384727],"type":"Point"}
}