{
  "type": "Feature",
  "properties": {
    "addr:full":"Stationsstraat 105 Ermelo Gelderland 3851 NC",
    "addr:housenumber":"105",
    "addr:postcode":"3851 nc",
    "addr:street":"Stationsstraat;Gelderland",
    "iso:country":"NL",
    "sg:address":"Stationsstraat 105",
    "sg:city":"Ermelo",
    "sg:orig_category":"Opticiens",
    "sg:phone":"+31 341 558 893",
    "sg:postcode":"3851 NC",
    "sg:province":"Gelderland",
    "wof:name":"Pearle Opticiens",
    "wof:placetype":"venue"
},
  "geometry": {"coordinates":[5.6191267967,52.299571991],"type":"Point"}
}