{
  "type": "Feature",
  "properties": {
    "addr:full":"Voorburggr 69 Zuid Scharwoude Georgia 1722 GA",
    "addr:housenumber":"69",
    "addr:postcode":"1722 ga",
    "addr:street":"Voorburggr",
    "iso:country":"NL",
    "sg:address":"Voorburggr 69",
    "sg:city":"Zuid Scharwoude",
    "sg:orig_category":"Administratie- En Boekhoudkantoren",
    "sg:phone":"+31 226 312 781",
    "sg:postcode":"1722 GA",
    "sg:province":"Georgia",
    "wof:name":"Administratiekantoor W J Koster",
    "wof:placetype":"venue"
},
  "geometry": {"coordinates":[-83.222931,32.678131],"type":"Point"}
}