{
  "type": "Feature",
  "properties": {
    "addr:full":"Breewg 1A Koudekerke Zeeland 4371 SB",
    "addr:housenumber":"1a",
    "addr:postcode":"4371 sb",
    "addr:street":"Breewg",
    "iso:country":"NL",
    "sg:address":"Breewg 1A",
    "sg:city":"Koudekerke",
    "sg:orig_category":"Vakantieverblijven",
    "sg:phone":"+31 118 551 436",
    "sg:postcode":"4371 SB",
    "sg:province":"Zeeland",
    "wof:name":"Koets, B",
    "wof:placetype":"venue"
},
  "geometry": {"coordinates":[3.5438780785,51.4887619019],"type":"Point"}
}