{
  "type": "Feature",
  "properties": {
    "addr:full":"Dorpsplein 2 Heerjansdam Zuid-Holland 2995 BS",
    "addr:housenumber":"2",
    "addr:postcode":"2995 bs",
    "addr:street":"Dorpsplein",
    "iso:country":"NL",
    "sg:address":"Dorpsplein 2",
    "sg:city":"Heerjansdam",
    "sg:orig_category":"Verzekeringen",
    "sg:phone":"+31 78 677 1938",
    "sg:postcode":"2995 BS",
    "sg:province":"Zuid-Holland",
    "wof:name":"Intrada Adviesgroep Bv",
    "wof:placetype":"venue"
},
  "geometry": {"coordinates":[4.563322,51.835911],"type":"Point"}
}