{
  "type": "Feature",
  "properties": {
    "addr:full":"Hobbemastr 45 Middelharnis South Holland 3241 AC",
    "addr:housenumber":"45",
    "addr:postcode":"3241 ac",
    "addr:street":"Hobbemastr",
    "iso:country":"NL",
    "sg:address":"Hobbemastr 45",
    "sg:city":"Middelharnis",
    "sg:orig_category":"Vertalers",
    "sg:phone":"+31 187 485 288",
    "sg:postcode":"3241 AC",
    "sg:province":"South Holland",
    "wof:name":"Oomes-Glover, N",
    "wof:placetype":"venue"
},
  "geometry": {"coordinates":[4.163376,51.75655],"type":"Point"}
}