{
  "type": "Feature",
  "properties": {
    "addr:full":"Geelvinkbaai 106 Capelle A/D Ijssel Zuid-Holland 2904 BC",
    "addr:housenumber":"106;a / d",
    "addr:postcode":"2904 bc",
    "addr:street":"Geelvinkbaai",
    "iso:country":"NL",
    "sg:address":"Geelvinkbaai 106",
    "sg:city":"Capelle A/D Ijssel",
    "sg:orig_category":"Sportactiviteiten En -Evenementen",
    "sg:phone":"+31 10 442 4432",
    "sg:postcode":"2904 BC",
    "sg:province":"Zuid-Holland",
    "wof:name":"Balloon Adventures",
    "wof:placetype":"venue"
},
  "geometry": {"coordinates":[4.615143,51.932892],"type":"Point"}
}