{
  "type": "Feature",
  "properties": {
    "addr:full":"Hanzeplein 25 Zwolle NL.08 8017 JD",
    "addr:housenumber":"25",
    "addr:postcode":"8017 jd",
    "addr:street":"Hanzeplein",
    "iso:country":"NL",
    "sg:address":"Hanzeplein 25",
    "sg:city":"Zwolle",
    "sg:orig_category":"Zuivelproducten And Spijsoli?n Gh",
    "sg:phone":"+31 38 467 7444",
    "sg:postcode":"8017 JD",
    "sg:province":"NL.08",
    "wof:name":"Borculo Domo Ingredients",
    "wof:placetype":"venue"
},
  "geometry": {"coordinates":[6.085967,52.502666],"type":"Point"}
}