{
  "type": "Feature",
  "properties": {
    "addr:full":"Liesenbeemd 20 Breda Noord-Brabant 4824 NS",
    "addr:housenumber":"20",
    "addr:postcode":"4824 ns",
    "addr:street":"Liesenbeemd",
    "iso:country":"NL",
    "sg:address":"Liesenbeemd 20",
    "sg:city":"Breda",
    "sg:orig_category":"Voetbalverenigingen",
    "sg:phone":"+31 76 541 2121",
    "sg:postcode":"4824 NS",
    "sg:province":"Noord-Brabant",
    "wof:name":"Breda Vv",
    "wof:placetype":"venue"
},
  "geometry": {"coordinates":[4.74282,51.608479],"type":"Point"}
}