{
  "type": "Feature",
  "properties": {
    "addr:full":"Anna Paulownalaan 16 Soest Utrecht 3761 CW",
    "addr:housenumber":"16",
    "addr:postcode":"3761 cw",
    "addr:street":"Anna Paulownalaan",
    "iso:country":"NL",
    "sg:address":"Anna Paulownalaan 16",
    "sg:city":"Soest",
    "sg:orig_category":"Kappers",
    "sg:phone":"+31 35 601 9090",
    "sg:postcode":"3761 CW",
    "sg:province":"Utrecht",
    "wof:name":"Kapsalon Van Den Brakel",
    "wof:placetype":"venue"
},
  "geometry": {"coordinates":[5.291217804,52.1853942871],"type":"Point"}
}