{
  "type": "Feature",
  "properties": {
    "iso:country":"NL",
    "sg:address":"Industriewg 91",
    "sg:city":"Waalwyk",
    "sg:orig_category":"Jachten - Schilderwerken En Onderhoud",
    "sg:phone":"+31 416 337 848",
    "sg:postcode":"5145 PD",
    "sg:province":"Noord-Brabant",
    "sg:website":"http://www.moverbo.nl",
    "wof:name":"Moverbo Bv",
    "wof:placetype":"venue"
},
  "geometry": {"coordinates":[5.059115,51.705997],"type":"Point"}
}