{
  "type": "Feature",
  "properties": {
    "addr:full":"Herengracht 118 Zaandam North Holland 1506 DW",
    "addr:housenumber":"118",
    "addr:postcode":"1506 dw",
    "addr:street":"Herengracht",
    "iso:country":"NL",
    "sg:address":"Herengracht 118",
    "sg:city":"Zaandam",
    "sg:orig_category":"Verhuur Catering-, Feest- En Evenementbenodigdheden",
    "sg:phone":"+31 75 635 0020",
    "sg:postcode":"1506 DW",
    "sg:province":"North Holland",
    "wof:name":"Henk Van Dalen Speelautomatenexploitatie Bv",
    "wof:placetype":"venue"
},
  "geometry": {"coordinates":[4.816799,52.440762],"type":"Point"}
}