{
  "type": "Feature",
  "properties": {
    "addr:full":"C Kooymanln 3 Bergen Nh Noord-Holland 1862 GG",
    "addr:housenumber":"3",
    "addr:postcode":"1862 gg",
    "iso:country":"NL",
    "sg:address":"C Kooymanln 3",
    "sg:city":"Bergen Nh",
    "sg:orig_category":"Bloemen En Planten - Veilingen",
    "sg:phone":"+31 72 589 9758",
    "sg:postcode":"1862 GG",
    "sg:province":"Noord-Holland",
    "wof:name":"Giannakoudis, S",
    "wof:placetype":"venue"
},
  "geometry": {"coordinates":[4.70139,52.669979],"type":"Point"}
}