{
  "type": "Feature",
  "properties": {
    "addr:full":"Oude Deldenerweg 1 Enschede NL.08 7546 PP",
    "addr:housenumber":"1",
    "addr:postcode":"7546 pp",
    "addr:street":"Oude Deldenerweg",
    "iso:country":"NL",
    "sg:address":"Oude Deldenerweg 1",
    "sg:city":"Enschede",
    "sg:orig_category":"Kampeerterreinen",
    "sg:phone":"+31 53 428 1355",
    "sg:postcode":"7546 PP",
    "sg:province":"NL.08",
    "wof:name":"Vof Camping Twente",
    "wof:placetype":"venue"
},
  "geometry": {"coordinates":[6.7981548309,52.1783370972],"type":"Point"}
}