{
  "type": "Feature",
  "properties": {
    "addr:full":"Hoofdstr 6 Gorredyk Friesland 8401 BZ",
    "addr:housenumber":"6",
    "addr:postcode":"8401 bz",
    "addr:street":"Hoofdstr",
    "iso:country":"NL",
    "sg:address":"Hoofdstr 6",
    "sg:city":"Gorredyk",
    "sg:orig_category":"Verzekeringen - Verzekeringskantoren",
    "sg:phone":"+31 513 465 500",
    "sg:postcode":"8401 BZ",
    "sg:province":"Friesland",
    "wof:name":"Wal Bv, Van Der",
    "wof:placetype":"venue"
},
  "geometry": {"coordinates":[6.064449,53.004395],"type":"Point"}
}