{
  "type": "Feature",
  "properties": {
    "addr:full":"Rynwaterstr 33 Rotterdam Zuid-Holland 3063 HC",
    "addr:housenumber":"33",
    "addr:postcode":"3063 hc",
    "addr:street":"Rynwaterstr",
    "iso:country":"NL",
    "sg:address":"Rynwaterstr 33",
    "sg:city":"Rotterdam",
    "sg:orig_category":"Bloemen En Planten",
    "sg:phone":"+31 10 212 2080",
    "sg:postcode":"3063 HC",
    "sg:province":"Zuid-Holland",
    "wof:name":"Meiden, De",
    "wof:placetype":"venue"
},
  "geometry": {"coordinates":[4.521151,51.913601],"type":"Point"}
}