{
  "type": "Feature",
  "properties": {
    "iso:country":"NL",
    "sg:address":"Middelburgsewg 1A",
    "sg:city":"Waddinxveen",
    "sg:orig_category":"Architecten En Architectenbureaus",
    "sg:phone":"+31 182 394 344",
    "sg:postcode":"2741 LB",
    "sg:province":"Zuid-Holland",
    "sg:website":"http://www.toposarchitecten.nl",
    "wof:name":"Topos Bv",
    "wof:placetype":"venue"
},
  "geometry": {"coordinates":[4.677478,52.045155],"type":"Point"}
}