{
  "type": "Feature",
  "properties": {
    "addr:full":"Bereveld 2 Zwijndrecht Zuid-Holland 3334 GA",
    "addr:housenumber":"2",
    "addr:postcode":"3334 ga",
    "addr:street":"Bereveld",
    "iso:country":"NL",
    "sg:address":"Bereveld 2",
    "sg:city":"Zwijndrecht",
    "sg:orig_category":"Goederenvervoer Over De Weg",
    "sg:phone":"+31 78 610 3113",
    "sg:postcode":"3334 GA",
    "sg:province":"Zuid-Holland",
    "wof:name":"M. Sunderman Transport",
    "wof:placetype":"venue"
},
  "geometry": {"coordinates":[4.597762,51.813679],"type":"Point"}
}