{
  "type": "Feature",
  "properties": {
    "addr:full":"Kinkerstraat 284 Amsterdam North Holland 1053 GB",
    "addr:housenumber":"284",
    "addr:postcode":"1053 gb",
    "addr:street":"Kinkerstraat",
    "iso:country":"NL",
    "sg:address":"Kinkerstraat 284",
    "sg:city":"Amsterdam",
    "sg:orig_category":"Juweliers",
    "sg:phone":"+31 20 618 3070",
    "sg:postcode":"1053 GB",
    "sg:province":"North Holland",
    "wof:name":"Juwelier W. Nusselein",
    "wof:placetype":"venue"
},
  "geometry": {"coordinates":[4.864137,52.365299],"type":"Point"}
}