{
  "type": "Feature",
  "properties": {
    "iso:country":"NL",
    "sg:address":"Keienbergweg 57",
    "sg:city":"Amsterdam Zuidoost",
    "sg:orig_category":"Fotostudio'S And Fotografen",
    "sg:phone":"+31 20 697 2141",
    "sg:postcode":"1101 GA",
    "sg:province":"Noord-Holland",
    "wof:name":"Studio Dirk Karsten Bv",
    "wof:placetype":"venue"
},
  "geometry": {"coordinates":[4.936154,52.308155],"type":"Point"}
}