{
  "type": "Feature",
  "properties": {
    "iso:country":"NL",
    "sg:address":"Nieuwstr 42",
    "sg:city":"Hippolytushoef",
    "sg:orig_category":"Kappers",
    "sg:phone":"+31 227 591 265",
    "sg:postcode":"1777 CM",
    "sg:province":"Noord-Holland",
    "wof:name":"Verfaille",
    "wof:placetype":"venue"
},
  "geometry": {"coordinates":[4.961387,52.908043],"type":"Point"}
}