{
  "type": "Feature",
  "properties": {
    "addr:full":"Denekamperstr 18 Ootmarsum Overijssel 7631 AC",
    "addr:housenumber":"18",
    "addr:postcode":"7631 ac",
    "addr:street":"Denekamperstr",
    "iso:country":"NL",
    "sg:address":"Denekamperstr 18",
    "sg:city":"Ootmarsum",
    "sg:orig_category":"Houtgroothandel Rondhout",
    "sg:phone":"+31 541 291 403",
    "sg:postcode":"7631 AC",
    "sg:province":"Overijssel",
    "wof:name":"Oude Hengel, Fons",
    "wof:placetype":"venue"
},
  "geometry": {"coordinates":[6.899889,52.409637],"type":"Point"}
}