{
  "type": "Feature",
  "properties": {
    "addr:full":"Kampstraat 17 J Landgraaf Limburg 6371 AA",
    "addr:housenumber":"17 j",
    "addr:postcode":"6371 aa",
    "addr:street":"Kampstraat",
    "iso:country":"NL",
    "sg:address":"Kampstraat 17 J",
    "sg:city":"Landgraaf",
    "sg:orig_category":"Artiestenbureaus",
    "sg:phone":"+31 45 521 8920",
    "sg:postcode":"6371 AA",
    "sg:province":"Limburg",
    "wof:name":"Mv Music",
    "wof:placetype":"venue"
},
  "geometry": {"coordinates":[6.024073,50.906536],"type":"Point"}
}