{
  "type": "Feature",
  "properties": {
    "iso:country":"NL",
    "sg:address":"Heuvel Galerie 108",
    "sg:city":"Eindhoven",
    "sg:orig_category":"Herenmodezaken",
    "sg:phone":"+31 40 243 5091",
    "sg:postcode":"5611 DK",
    "sg:province":"Noord-Brabant",
    "wof:name":"Facet Mode Bv",
    "wof:placetype":"venue"
},
  "geometry": {"coordinates":[5.479552,51.439121],"type":"Point"}
}