{
  "type": "Feature",
  "properties": {
    "addr:full":"De Smelen 66 Valkenswaard Noord-Brabant 5553 CT",
    "addr:housenumber":"66",
    "addr:postcode":"5553 ct",
    "addr:street":"De Smelen",
    "iso:country":"NL",
    "sg:address":"De Smelen 66",
    "sg:city":"Valkenswaard",
    "sg:orig_category":"Verenigingen En Stichtingen",
    "sg:phone":"+31 40 201 5059",
    "sg:postcode":"5553 CT",
    "sg:province":"Noord-Brabant",
    "wof:name":"Jeame, Sticht",
    "wof:placetype":"venue"
},
  "geometry": {"coordinates":[5.471945,51.359024],"type":"Point"}
}