{
  "type": "Feature",
  "properties": {
    "addr:full":"Hoofdstr 77 Grootegast Groningen 9861 AC",
    "addr:housenumber":"77",
    "addr:postcode":"9861 ac",
    "addr:street":"Hoofdstr",
    "iso:country":"NL",
    "sg:address":"Hoofdstr 77",
    "sg:city":"Grootegast",
    "sg:orig_category":"Boekhandels",
    "sg:phone":"+31 594 612 118",
    "sg:postcode":"9861 AC",
    "sg:province":"Groningen",
    "wof:name":"Pietie'S",
    "wof:placetype":"venue"
},
  "geometry": {"coordinates":[6.279841,53.214207],"type":"Point"}
}