{
  "type": "Feature",
  "properties": {
    "addr:full":"Torenstraat 4 Heusden Gem Heusden Noord-Brabant 5256 NJ",
    "addr:housenumber":"4",
    "addr:postcode":"5256 nj",
    "addr:street":"Torenstraat",
    "iso:country":"NL",
    "sg:address":"Torenstraat 4",
    "sg:city":"Heusden Gem Heusden",
    "sg:orig_category":"Overheidsdiensten",
    "sg:phone":"+31 416 663 188",
    "sg:postcode":"5256 NJ",
    "sg:province":"Noord-Brabant",
    "wof:name":"Stichting Dorpshuis",
    "wof:placetype":"venue"
},
  "geometry": {"coordinates":[5.1566781998,51.7311973572],"type":"Point"}
}