{
  "type": "Feature",
  "properties": {
    "addr:full":"Textielweg 16 Culemborg Gelderland 4104 AM",
    "addr:housenumber":"16",
    "addr:postcode":"4104",
    "addr:street":"Textielweg;Gelderland",
    "iso:country":"NL",
    "sg:address":"Textielweg 16",
    "sg:city":"Culemborg",
    "sg:classifiers":[
        {
            "category":"Professional",
            "subcategory":"Accounting & Tax Preparation",
            "type":"Services"
        }
    ],
    "sg:phone":"+31 345 531 109",
    "sg:postcode":"4104 AM",
    "sg:province":"Gelderland",
    "sg:tags":[
        "accountant"
    ],
    "wof:name":"Accountantskantoor De Rek",
    "wof:placetype":"venue"
},
  "geometry": {"coordinates":[5.216359,51.941315],"type":"Point"}
}