{
  "type": "Feature",
  "properties": {
    "addr:full":"Wielewaallaan 39 Bussum North Holland 1403 BW",
    "addr:housenumber":"39",
    "addr:postcode":"1403 bw",
    "addr:street":"Wielewaallaan",
    "iso:country":"NL",
    "sg:address":"Wielewaallaan 39",
    "sg:city":"Bussum",
    "sg:orig_category":"Public Relationbureaus",
    "sg:phone":"+31 35 691 0023",
    "sg:postcode":"1403 BW",
    "sg:province":"North Holland",
    "wof:name":"E. Braat",
    "wof:placetype":"venue"
},
  "geometry": {"coordinates":[5.190435,52.270233],"type":"Point"}
}