{
  "type": "Feature",
  "properties": {
    "addr:full":"Postbus 1167 Rozenburg Zh 3180 AD",
    "addr:housenumber":"1167",
    "addr:postcode":"3180 ad",
    "addr:street":"Postbus",
    "iso:country":"NL",
    "sg:address":"Postbus 1167",
    "sg:city":"Rozenburg Zh",
    "sg:orig_category":"Wegenbouw",
    "sg:phone":"+31 181 254 472",
    "sg:postcode":"3180 AD",
    "sg:website":"http://www.kws.nl",
    "wof:name":"Kws Zuid-Holland Zuid",
    "wof:placetype":"venue"
},
  "geometry": {"coordinates":[4.2496099472,51.9044189453],"type":"Point"}
}