{
  "type": "Feature",
  "properties": {
    "addr:full":"Albert Van Meerveldstr 87 Zwartebroek Gelderland 3785 LP",
    "addr:housenumber":"87",
    "addr:postcode":"3785 lp",
    "addr:street":"Albert Van Meerveldstr;Gelderland",
    "iso:country":"NL",
    "sg:address":"Albert Van Meerveldstr 87",
    "sg:city":"Zwartebroek",
    "sg:orig_category":"Overheidsdiensten",
    "sg:phone":"+31 342 462 077",
    "sg:postcode":"3785 LP",
    "sg:province":"Gelderland",
    "wof:name":"De Belleman",
    "wof:placetype":"venue"
},
  "geometry": {"coordinates":[5.5080471039,52.1775360107],"type":"Point"}
}