{
  "type": "Feature",
  "properties": {
    "addr:full":"Vorkstr 1-3 Rotterdam Zuid-Holland 3075 NT",
    "addr:housenumber":"1-3",
    "addr:postcode":"3075 nt",
    "addr:street":"Vorkstr",
    "iso:country":"NL",
    "sg:address":"Vorkstr 1-3",
    "sg:city":"Rotterdam",
    "sg:orig_category":"Verenigingsgebouwen",
    "sg:phone":"+31 10 485 0237",
    "sg:postcode":"3075 NT",
    "sg:province":"Zuid-Holland",
    "wof:name":"Valkenier, De",
    "wof:placetype":"venue"
},
  "geometry": {"coordinates":[4.498839,51.888718],"type":"Point"}
}