{
  "type": "Feature",
  "properties": {
    "iso:country":"NL",
    "sg:address":"Vorkstr 1-3",
    "sg:city":"Rotterdam",
    "sg:orig_category":"Verenigingsgebouwen",
    "sg:phone":"+31 10 485 0237",
    "sg:postcode":"3075 NT",
    "sg:province":"Zuid-Holland",
    "wof:name":"Valkenier, De",
    "wof:placetype":"venue"
},
  "geometry": {"coordinates":[4.498839,51.888718],"type":"Point"}
}