{
  "type": "Feature",
  "properties": {
    "addr:full":"Boksdoornstr 57 Ridderkerk South Holland 2982 BA",
    "addr:housenumber":"57",
    "addr:postcode":"2982 ba",
    "addr:street":"Boksdoornstr",
    "iso:country":"NL",
    "sg:address":"Boksdoornstr 57",
    "sg:city":"Ridderkerk",
    "sg:orig_category":"Adviesbureaus Bouwkunde",
    "sg:phone":"+31 180 463 332",
    "sg:postcode":"2982 BA",
    "sg:province":"South Holland",
    "wof:name":"Gidouw",
    "wof:placetype":"venue"
},
  "geometry": {"coordinates":[4.587208,51.871391],"type":"Point"}
}