{
  "type": "Feature",
  "properties": {
    "addr:full":"Zorgvry 4 Haren Gn Groningen 9751 SM",
    "addr:housenumber":"4",
    "addr:postcode":"9751 sm",
    "addr:street":"Zorgvry",
    "iso:country":"NL",
    "sg:address":"Zorgvry 4",
    "sg:city":"Haren Gn",
    "sg:orig_category":"Psychotherapeuten",
    "sg:phone":"+31 50 525 6359",
    "sg:postcode":"9751 SM",
    "sg:province":"Groningen",
    "wof:name":"Hollander-Meersma, Drs M A Den",
    "wof:placetype":"venue"
},
  "geometry": {"coordinates":[6.615062,53.175648],"type":"Point"}
}