{
  "type": "Feature",
  "properties": {
    "iso:country":"NL",
    "sg:address":"Oude Ryn 114",
    "sg:city":"Leiden",
    "sg:orig_category":"Kunstbemiddeling",
    "sg:phone":"+31 6 54642412",
    "sg:postcode":"2312 HK",
    "sg:province":"Zuid-Holland",
    "wof:name":"Art Group Holland",
    "wof:placetype":"venue"
},
  "geometry": {"coordinates":[4.496125,52.160358],"type":"Point"}
}