{
  "type": "Feature",
  "properties": {
    "iso:country":"NL",
    "sg:address":"Oranjelust 67",
    "sg:city":"Voorburg",
    "sg:orig_category":"Zuivel - Groothandel",
    "sg:phone":"+31 70 387 5676",
    "sg:postcode":"2271 XG",
    "sg:province":"South Holland",
    "wof:name":"Prins Vof",
    "wof:placetype":"venue"
},
  "geometry": {"coordinates":[4.362312,52.070137],"type":"Point"}
}