{
  "type": "Feature",
  "properties": {
    "addr:full":"Sieverdingweg 5 Vragender Gelderland 7134 NH",
    "addr:housenumber":"5",
    "addr:postcode":"7134 nh",
    "addr:street":"Sieverdingweg;Gelderland",
    "iso:country":"NL",
    "sg:address":"Sieverdingweg 5",
    "sg:city":"Vragender",
    "sg:classifiers":[
        {
            "category":"Shopping",
            "subcategory":"Clothing, Apparel, & Fashions",
            "type":"Retail Goods"
        }
    ],
    "sg:phone":"+31 544 378 048",
    "sg:postcode":"7134 NH",
    "sg:province":"Gelderland",
    "sg:tags":[
        "ondergoed",
        "lingerie"
    ],
    "wof:name":"Tricot King",
    "wof:placetype":"venue"
},
  "geometry": {"coordinates":[6.612135,51.987198],"type":"Point"}
}