{
  "type": "Feature",
  "properties": {
    "addr:full":"Kloosterstr 1 Enschede Overijssel 7514 EZ",
    "addr:housenumber":"1",
    "addr:postcode":"7514 ez",
    "addr:street":"Kloosterstr",
    "iso:country":"NL",
    "sg:address":"Kloosterstr 1",
    "sg:city":"Enschede",
    "sg:orig_category":"Verenigingen En Stichtingen",
    "sg:phone":"+31 53 432 0122",
    "sg:postcode":"7514 EZ",
    "sg:province":"Overijssel",
    "wof:name":"Gilde, 'T",
    "wof:placetype":"venue"
},
  "geometry": {"coordinates":[6.89402,52.221962],"type":"Point"}
}