{
  "type": "Feature",
  "properties": {
    "addr:full":"Nieuwe Parklaan 89 'S Gravenhage South Holland 2587 BN",
    "addr:housenumber":"89",
    "addr:postcode":"2587 bn",
    "addr:street":"Nieuwe Parklaan;' S Gravenhage",
    "iso:country":"NL",
    "sg:address":"Nieuwe Parklaan 89",
    "sg:city":"'S Gravenhage",
    "sg:orig_category":"Verzekeringen",
    "sg:phone":"+31 70 352 2302",
    "sg:postcode":"2587 BN",
    "sg:province":"South Holland",
    "wof:name":"A K F Van Santen",
    "wof:placetype":"venue"
},
  "geometry": {"coordinates":[4.284297,52.111748],"type":"Point"}
}