{
  "type": "Feature",
  "properties": {
    "addr:full":"Jasmynln 16 Woerden Utrecht 3442 HZ",
    "addr:housenumber":"16",
    "addr:postcode":"3442 hz",
    "addr:street":"Jasmynln",
    "iso:country":"NL",
    "sg:address":"Jasmynln 16",
    "sg:city":"Woerden",
    "sg:orig_category":"Bedrijfsopleidingen",
    "sg:phone":"+31 6 54718146",
    "sg:postcode":"3442 HZ",
    "sg:province":"Utrecht",
    "wof:name":"Mlo",
    "wof:placetype":"venue"
},
  "geometry": {"coordinates":[4.887371,52.085117],"type":"Point"}
}