{
  "type": "Feature",
  "properties": {
    "addr:full":"Vaart Noordzijde 14 Appelscha Friesland 8426 AN",
    "addr:housenumber":"14",
    "addr:postcode":"8426 an",
    "addr:street":"Vaart Noordzijde",
    "iso:country":"NL",
    "sg:address":"Vaart Noordzijde 14",
    "sg:city":"Appelscha",
    "sg:orig_category":"Granen, Zaden And Diervoeders Gh",
    "sg:phone":"+31 516 431 208",
    "sg:postcode":"8426 AN",
    "sg:province":"Friesland",
    "wof:name":"P. Mulder",
    "wof:placetype":"venue"
},
  "geometry": {"coordinates":[6.345562,52.960201],"type":"Point"}
}