{
  "type": "Feature",
  "properties": {
    "addr:full":"Vaartwg 22 Hilversum Noord-Holland 1211 JH",
    "addr:housenumber":"22",
    "addr:postcode":"1211 jh",
    "addr:street":"Vaartwg",
    "iso:country":"NL",
    "sg:address":"Vaartwg 22",
    "sg:city":"Hilversum",
    "sg:orig_category":"Kappers",
    "sg:phone":"+31 35 624 4771",
    "sg:postcode":"1211 JH",
    "sg:province":"Noord-Holland",
    "wof:name":"Vos, Gerard",
    "wof:placetype":"venue"
},
  "geometry": {"coordinates":[5.169349,52.223114],"type":"Point"}
}