{
  "type": "Feature",
  "properties": {
    "addr:full":"Babborgapln 1 Babberich Gelderland 6909 DW",
    "addr:housenumber":"1",
    "addr:postcode":"6909 dw",
    "addr:street":"Babborgapln;Gelderland",
    "iso:country":"NL",
    "sg:address":"Babborgapln 1",
    "sg:city":"Babberich",
    "sg:orig_category":"Verenigingsgebouwen",
    "sg:phone":"+31 316 247 460",
    "sg:postcode":"6909 DW",
    "sg:province":"Gelderland",
    "wof:name":"Dorpshuis, St Jan",
    "wof:placetype":"venue"
},
  "geometry": {"coordinates":[6.118207,51.905231],"type":"Point"}
}