{
  "type": "Feature",
  "properties": {
    "addr:full":"Klokkemakersweg 19 Aalten Gelderland 7122 KB",
    "addr:housenumber":"19",
    "addr:postcode":"7122 kb",
    "addr:street":"Klokkemakersweg;Gelderland",
    "iso:country":"NL",
    "sg:address":"Klokkemakersweg 19",
    "sg:city":"Aalten",
    "sg:orig_category":"Huizensloop And Bouwrijp Maken",
    "sg:phone":"+31 543 466 361",
    "sg:postcode":"7122 KB",
    "sg:province":"Gelderland",
    "wof:name":"Hoftijzer Loonbedrijf Bv",
    "wof:placetype":"venue"
},
  "geometry": {"coordinates":[6.527106,51.896225],"type":"Point"}
}