{
  "type": "Feature",
  "properties": {
    "addr:full":"Rietstapstr 27 Rotterdam Zuid-Holland 3056 LS",
    "addr:housenumber":"27",
    "addr:postcode":"3056 ls",
    "addr:street":"Rietstapstr",
    "iso:country":"NL",
    "sg:address":"Rietstapstr 27",
    "sg:city":"Rotterdam",
    "sg:orig_category":"Grondwerken",
    "sg:phone":"+31 10 420 7290",
    "sg:postcode":"3056 LS",
    "sg:province":"Zuid-Holland",
    "wof:name":"Kloos, W A Van Der",
    "wof:placetype":"venue"
},
  "geometry": {"coordinates":[4.520313,51.956272],"type":"Point"}
}