{
  "type": "Feature",
  "properties": {
    "addr:full":"Raadhuisstraat 2 Waspik Noord-Brabant 5165 CH",
    "addr:housenumber":"2",
    "addr:postcode":"5165",
    "addr:street":"Raadhuisstraat",
    "iso:country":"NL",
    "sg:address":"Raadhuisstraat 2",
    "sg:city":"Waspik",
    "sg:orig_category":"Woningbouwverenigingen",
    "sg:phone":"+31 416 312 396",
    "sg:postcode":"5165 CH",
    "sg:province":"Noord-Brabant",
    "wof:name":"Woningstichting Volksbelang",
    "wof:placetype":"venue"
},
  "geometry": {"coordinates":[8.2241401672,46.8130912781],"type":"Point"}
}