{
  "type": "Feature",
  "properties": {
    "addr:full":"Kleine Tocht 19 Zaandam North Holland 1507 CB",
    "addr:housenumber":"19",
    "addr:postcode":"1507 cb",
    "addr:street":"Kleine Tocht",
    "iso:country":"NL",
    "sg:address":"Kleine Tocht 19",
    "sg:city":"Zaandam",
    "sg:orig_category":"Bloemen And Planten",
    "sg:phone":"+31 75 617 8244",
    "sg:postcode":"1507 CB",
    "sg:province":"North Holland",
    "wof:name":"Ranzijn Tuin & Dier Zaanstad Bv",
    "wof:placetype":"venue"
},
  "geometry": {"coordinates":[4.81158,52.431454],"type":"Point"}
}