{
  "type": "Feature",
  "properties": {
    "addr:full":"Peursumstraat 44 Amsterdam Zuidoost Noord-Holland 1106 BV",
    "addr:housenumber":"44",
    "addr:postcode":"zuidoost;1106 bv",
    "addr:street":"Peursumstraat",
    "iso:country":"NL",
    "sg:address":"Peursumstraat 44",
    "sg:city":"Amsterdam Zuidoost",
    "sg:orig_category":"Paramedische Behandelingen",
    "sg:phone":"+31 20 697 7244",
    "sg:postcode":"1106 BV",
    "sg:province":"Noord-Holland",
    "wof:name":"Logopedie Praktijk Reigersbos",
    "wof:placetype":"venue"
},
  "geometry": {"coordinates":[4.977278,52.29863],"type":"Point"}
}