{
  "type": "Feature",
  "properties": {
    "addr:full":"Laan Van Klarenbeek 127 Arnhem Gelderland 6824 JP",
    "addr:housenumber":"127",
    "addr:postcode":"6824 jp",
    "addr:street":"Laan Van Klarenbeek",
    "iso:country":"NL",
    "sg:address":"Laan Van Klarenbeek 127",
    "sg:city":"Arnhem",
    "sg:orig_category":"Boekhouders",
    "sg:phone":"+31 26 361 4824",
    "sg:postcode":"6824 JP",
    "sg:province":"Gelderland",
    "wof:name":"Administratiekantoor R.A. Boersbroek",
    "wof:placetype":"venue"
},
  "geometry": {"coordinates":[5.940305,51.991142],"type":"Point"}
}