{
  "type": "Feature",
  "properties": {
    "addr:full":"F V Eedenstr 22 Winschoten Groningen 9673 HV",
    "addr:housenumber":"22",
    "addr:postcode":"9673 hv",
    "addr:street":"Eedenstr",
    "iso:country":"NL",
    "sg:address":"F V Eedenstr 22",
    "sg:city":"Winschoten",
    "sg:orig_category":"Administratie- En Boekhoudkantoren",
    "sg:phone":"+31 597 431 312",
    "sg:postcode":"9673 HV",
    "sg:province":"Groningen",
    "wof:name":"Blaauw Vof, Piet De",
    "wof:placetype":"venue"
},
  "geometry": {"coordinates":[7.03573,53.137032],"type":"Point"}
}