{
  "type": "Feature",
  "properties": {
    "addr:full":"Veldmaterstr 1 Haaksbergen NL.08 7482 TA",
    "addr:housenumber":"1;nl.08",
    "addr:postcode":"7482 ta",
    "addr:street":"Veldmaterstr",
    "iso:country":"NL",
    "sg:address":"Veldmaterstr 1",
    "sg:city":"Haaksbergen",
    "sg:orig_category":"Fietsen En Bromfietsen",
    "sg:phone":"+31 53 572 6600",
    "sg:postcode":"7482 TA",
    "sg:province":"NL.08",
    "wof:name":"Hilderink Bv",
    "wof:placetype":"venue"
},
  "geometry": {"coordinates":[6.74302,52.167877],"type":"Point"}
}