{
  "type": "Feature",
  "properties": {
    "addr:full":"Houtbeekweg 10 Stroe Gelderland 3776 LZ",
    "addr:housenumber":"10",
    "addr:postcode":"3776 lz",
    "addr:street":"Houtbeekweg;Gelderland",
    "iso:country":"NL",
    "sg:address":"Houtbeekweg 10",
    "sg:city":"Stroe",
    "sg:orig_category":"Autokeuringen",
    "sg:phone":"+31 342 442 376",
    "sg:postcode":"3776 LZ",
    "sg:province":"Gelderland",
    "wof:name":"Vof Autopoetsbedrijf Schouten",
    "wof:placetype":"venue"
},
  "geometry": {"coordinates":[5.694842,52.187923],"type":"Point"}
}