{
  "type": "Feature",
  "properties": {
    "addr:full":"Noordeinde 37 Landsmeer North Holland 1121 AB",
    "addr:housenumber":"37",
    "addr:postcode":"1121 ab",
    "addr:street":"Noordeinde",
    "iso:country":"NL",
    "sg:address":"Noordeinde 37",
    "sg:city":"Landsmeer",
    "sg:orig_category":"Autokeuringen",
    "sg:phone":"+31 20 482 4942",
    "sg:postcode":"1121 AB",
    "sg:province":"North Holland",
    "wof:name":"P J Wals",
    "wof:placetype":"venue"
},
  "geometry": {"coordinates":[4.914382,52.441124],"type":"Point"}
}