{
  "type": "Feature",
  "properties": {
    "addr:full":"Hogelandsingel 188 Enschede Overijssel 7512 GK",
    "addr:housenumber":"188",
    "addr:postcode":"7512 gk",
    "addr:street":"Hogelandsingel",
    "iso:country":"NL",
    "sg:address":"Hogelandsingel 188",
    "sg:city":"Enschede",
    "sg:orig_category":"Autokeuringen",
    "sg:phone":"+31 53 431 3316",
    "sg:postcode":"7512 GK",
    "sg:province":"Overijssel",
    "wof:name":"Benzine De Jong Bv",
    "wof:placetype":"venue"
},
  "geometry": {"coordinates":[6.905199,52.212715],"type":"Point"}
}