{
  "type": "Feature",
  "properties": {
    "iso:country":"NL",
    "sg:address":"Neerstraat 1",
    "sg:city":"Roermond",
    "sg:orig_category":"Herenmodezaken",
    "sg:phone":"+31 475 319 000",
    "sg:postcode":"6041 KA",
    "sg:province":"Limburg",
    "wof:name":"Business Is Business",
    "wof:placetype":"venue"
},
  "geometry": {"coordinates":[5.985412,51.194592],"type":"Point"}
}