{
  "type": "Feature",
  "properties": {
    "addr:full":"Rapenburg 9 Leiden South Holland 2311 GD",
    "addr:housenumber":"9",
    "addr:postcode":"2311 gd",
    "addr:street":"Rapenburg",
    "iso:country":"NL",
    "sg:address":"Rapenburg 9",
    "sg:city":"Leiden",
    "sg:orig_category":"Vertaal- And Tolkenbureaus",
    "sg:phone":"+31 71 514 4505",
    "sg:postcode":"2311 GD",
    "sg:province":"South Holland",
    "wof:name":"Provertaal",
    "wof:placetype":"venue"
},
  "geometry": {"coordinates":[4.484511,52.159897],"type":"Point"}
}