{
  "type": "Feature",
  "properties": {
    "addr:full":"Ridderstr 4 Heusden Gem Heusd North Brabant 5256 EE",
    "addr:housenumber":"4",
    "addr:postcode":"5256 ee",
    "addr:street":"Ridderstr",
    "iso:country":"NL",
    "sg:address":"Ridderstr 4",
    "sg:city":"Heusden Gem Heusd",
    "sg:orig_category":"Lasbedrijven",
    "sg:phone":"+31 416 660 204",
    "sg:postcode":"5256 EE",
    "sg:province":"North Brabant",
    "wof:name":"Mc Welding",
    "wof:placetype":"venue"
},
  "geometry": {"coordinates":[5.136575,51.733521],"type":"Point"}
}