{
  "type": "Feature",
  "properties": {
    "iso:country":"NL",
    "sg:address":"Hoogeveensewg 27",
    "sg:city":"Benthuizen",
    "sg:orig_category":"Koel- En Vrieshuizen",
    "sg:phone":"+31 172 588 991",
    "sg:postcode":"2731 LA",
    "sg:province":"Zuid-Holland",
    "sg:website":"http://www.deltafresh.nl",
    "wof:name":"Delta Fresh",
    "wof:placetype":"venue"
},
  "geometry": {"coordinates":[4.573569,52.077946],"type":"Point"}
}