{
  "type": "Feature",
  "properties": {
    "addr:full":"Avelingen O 12 Gorinchem South Holland 4202 MN",
    "addr:housenumber":"12",
    "addr:postcode":"4202 mn",
    "addr:street":"Avelingen O",
    "iso:country":"NL",
    "sg:address":"Avelingen O 12",
    "sg:city":"Gorinchem",
    "sg:orig_category":"Verlichtingsartikelen - Groothandel",
    "sg:phone":"+31 183 669 200",
    "sg:postcode":"4202 MN",
    "sg:province":"South Holland",
    "sg:website":"http://www.massive.nl",
    "wof:name":"Massive Ned Bv",
    "wof:placetype":"venue"
},
  "geometry": {"coordinates":[4.947814,51.832191],"type":"Point"}
}