{
  "type": "Feature",
  "properties": {
    "addr:full":"Damsewg 91 Brandwyk South Holland 2974 VB",
    "addr:housenumber":"91",
    "addr:postcode":"2974 vb",
    "addr:street":"Damsewg",
    "iso:country":"NL",
    "sg:address":"Damsewg 91",
    "sg:city":"Brandwyk",
    "sg:orig_category":"Bloemen En Planten",
    "sg:phone":"+31 184 641 757",
    "sg:postcode":"2974 VB",
    "sg:province":"South Holland",
    "wof:name":"Op Den Dam",
    "wof:placetype":"venue"
},
  "geometry": {"coordinates":[4.848012,51.883732],"type":"Point"}
}