{
  "type": "Feature",
  "properties": {
    "addr:full":"Einsteinweg 82 Leiden Zuid-Holland 2333 CD",
    "addr:housenumber":"82",
    "addr:postcode":"2333 cd",
    "addr:street":"Einsteinweg",
    "iso:country":"NL",
    "sg:address":"Einsteinweg 82",
    "sg:city":"Leiden",
    "sg:orig_category":"Farmaceutische Producten Gh",
    "sg:phone":"+31 71 524 6700",
    "sg:postcode":"2333 CD",
    "sg:province":"Zuid-Holland",
    "wof:name":"Servier Nederland Bv",
    "wof:placetype":"venue"
},
  "geometry": {"coordinates":[4.459558,52.166813],"type":"Point"}
}