{
  "type": "Feature",
  "properties": {
    "iso:country":"NL",
    "sg:address":"Asterstraat 35",
    "sg:city":"Asten",
    "sg:classifiers":[
        {
            "category":"Education",
            "subcategory":"Preschool",
            "type":"Public Place"
        }
    ],
    "sg:phone":"+31 493 670 090",
    "sg:postcode":"5721 EE",
    "sg:province":"North Brabant",
    "sg:tags":[
        "kleuteronderwijs",
        "basis-"
    ],
    "wof:name":"Basisschool Deken Van Hout",
    "wof:placetype":"venue"
},
  "geometry": {"coordinates":[5.748537,51.408035],"type":"Point"}
}