{
  "type": "Feature",
  "properties": {
    "addr:full":"Heereweg 439 Lisse Zuid-Holland 2161 DB",
    "addr:housenumber":"439",
    "addr:postcode":"2161 db",
    "addr:street":"Heereweg",
    "iso:country":"NL",
    "sg:address":"Heereweg 439",
    "sg:city":"Lisse",
    "sg:orig_category":"Granen, Zaden And Diervoeders Gh",
    "sg:phone":"+31 252 240 050",
    "sg:postcode":"2161 DB",
    "sg:province":"Zuid-Holland",
    "wof:name":"Van Geest Nurseries Bv",
    "wof:placetype":"venue"
},
  "geometry": {"coordinates":[4.537197,52.239887],"type":"Point"}
}