{
  "type": "Feature",
  "properties": {
    "addr:full":"Prins Johan Frisopromenade 90 Rijswijk Gelderland 2294 DC",
    "addr:housenumber":"90",
    "addr:postcode":"2294",
    "addr:street":"Prins Johan Frisopromenade",
    "iso:country":"NL",
    "sg:address":"Prins Johan Frisopromenade 90",
    "sg:city":"Rijswijk",
    "sg:orig_category":"Huishoudapparatuur, Televisies And Radio'S",
    "sg:phone":"+31 70 396 6006",
    "sg:postcode":"2294 DC",
    "sg:province":"Gelderland",
    "wof:name":"It`S",
    "wof:placetype":"venue"
},
  "geometry": {"coordinates":[4.31399,52.038292],"type":"Point"}
}