{
  "type": "Feature",
  "properties": {
    "addr:full":"Friese Varkenm 14-16 Haarlem North Holland 2011 JA",
    "addr:housenumber":"14-16",
    "addr:postcode":"2011 ja",
    "addr:street":"Friese",
    "iso:country":"NL",
    "sg:address":"Friese Varkenm 14-16",
    "sg:city":"Haarlem",
    "sg:orig_category":"Parketvloeren",
    "sg:phone":"+31 23 532 3485",
    "sg:postcode":"2011 JA",
    "sg:province":"North Holland",
    "wof:name":"Bremer Bv",
    "wof:placetype":"venue"
},
  "geometry": {"coordinates":[4.642253,52.380562],"type":"Point"}
}