{
  "type": "Feature",
  "properties": {
    "addr:full":"Veilingstr 14B Elshout Noord-Brabant 5154 AA",
    "addr:housenumber":"14b",
    "addr:postcode":"5154 aa",
    "addr:street":"Veilingstr",
    "iso:country":"NL",
    "sg:address":"Veilingstr 14B",
    "sg:city":"Elshout",
    "sg:orig_category":"Geluidsinstallaties - Verhuur",
    "sg:phone":"+31 416 379 595",
    "sg:postcode":"5154 AA",
    "sg:province":"Noord-Brabant",
    "sg:website":"http://www.jan-mimpen.nl",
    "wof:name":"Jan Mimpen",
    "wof:placetype":"venue"
},
  "geometry": {"coordinates":[5.1416,51.695641],"type":"Point"}
}