{
  "type": "Feature",
  "properties": {
    "iso:country":"NL",
    "sg:address":"W De Merodestr 52",
    "sg:city":"Hengelo Ov",
    "sg:orig_category":"Kaas",
    "sg:phone":"+31 74 250 1739",
    "sg:postcode":"7552 WZ",
    "sg:province":"Overijssel",
    "wof:name":"Zuivelhoeve Bv, De",
    "wof:placetype":"venue"
},
  "geometry": {"coordinates":[6.8219809532,52.2626686096],"type":"Point"}
}