{
  "type": "Feature",
  "properties": {
    "addr:full":"Calandweg 36 Arnemuiden Zeeland 4341 RA",
    "addr:housenumber":"36",
    "addr:postcode":"4341 ra",
    "addr:street":"Calandweg",
    "iso:country":"NL",
    "sg:address":"Calandweg 36",
    "sg:city":"Arnemuiden",
    "sg:orig_category":"Luchtvaart- Maatschappijen",
    "sg:phone":"+31 113 612 406",
    "sg:postcode":"4341 RA",
    "sg:province":"Zeeland",
    "wof:name":"North Sea Airways",
    "wof:placetype":"venue"
},
  "geometry": {"coordinates":[3.74028,51.513302],"type":"Point"}
}