{
  "type": "Feature",
  "properties": {
    "addr:full":"De Reede 8A Urk NL. 8321 DA",
    "addr:housenumber":"8a",
    "addr:postcode":"8321 da",
    "addr:street":"De Reede;Nl.",
    "iso:country":"NL",
    "sg:address":"De Reede 8A",
    "sg:city":"Urk",
    "sg:orig_category":"Fietshandelaren",
    "sg:phone":"+31 527 683 006",
    "sg:postcode":"8321 DA",
    "sg:province":"NL.",
    "wof:name":"S. Bakker",
    "wof:placetype":"venue"
},
  "geometry": {"coordinates":[5.608509,52.661934],"type":"Point"}
}