{
  "type": "Feature",
  "properties": {
    "iso:country":"NL",
    "sg:address":"Scheldestr 17A",
    "sg:city":"Vlissingen",
    "sg:orig_category":"Bloemen En Planten",
    "sg:phone":"+31 118 412 686",
    "sg:postcode":"4381 RP",
    "sg:province":"Zeeland",
    "wof:name":"Mies, Bloemenhuis",
    "wof:placetype":"venue"
},
  "geometry": {"coordinates":[3.573894,51.44709],"type":"Point"}
}