{
  "type": "Feature",
  "properties": {
    "addr:full":"Rembrandtstraat 76 Nijmegen Gelderland 6521 MG",
    "addr:housenumber":"76",
    "addr:postcode":"6521 mg",
    "addr:street":"Rembrandtstraat;Gelderland",
    "iso:country":"NL",
    "sg:address":"Rembrandtstraat 76",
    "sg:city":"Nijmegen",
    "sg:orig_category":"Public Relationbureaus",
    "sg:phone":"+31 24 360 6295",
    "sg:postcode":"6521 MG",
    "sg:province":"Gelderland",
    "wof:name":"Petey Communicatie Support",
    "wof:placetype":"venue"
},
  "geometry": {"coordinates":[5.881894,51.83736],"type":"Point"}
}