{
  "type": "Feature",
  "properties": {
    "addr:full":"Stationsplein 62 Baarn Utrecht 3743 KM",
    "addr:housenumber":"62",
    "addr:postcode":"3743 km",
    "addr:street":"Stationsplein",
    "iso:country":"NL",
    "sg:address":"Stationsplein 62",
    "sg:city":"Baarn",
    "sg:classifiers":[
        {
            "category":"Professional",
            "subcategory":"Accounting & Tax Preparation",
            "type":"Services"
        }
    ],
    "sg:phone":"+31 35 541 6310",
    "sg:postcode":"3743 KM",
    "sg:province":"Utrecht",
    "sg:tags":[
        "accountant"
    ],
    "wof:name":"Inttax Bv",
    "wof:placetype":"venue"
},
  "geometry": {"coordinates":[5.292121,52.21101],"type":"Point"}
}