{
  "type": "Feature",
  "properties": {
    "addr:full":"J Vernewg 17 Tilburg North Brabant 5015 BE",
    "addr:housenumber":"17",
    "addr:postcode":"5015",
    "iso:country":"NL",
    "sg:address":"J Vernewg 17",
    "sg:city":"Tilburg",
    "sg:orig_category":"Autoschade- Herstelbedrijven",
    "sg:phone":"+31 13 542 1958",
    "sg:postcode":"5015 BE",
    "sg:province":"North Brabant",
    "sg:website":"http://www.haans.nl",
    "wof:name":"Haans Autoschades Bv",
    "wof:placetype":"venue"
},
  "geometry": {"coordinates":[5.111807,51.566467],"type":"Point"}
}