{
  "type": "Feature",
  "properties": {
    "addr:full":"De Beaufortlaan 24 Soest Utrecht 3768 MJ",
    "addr:housenumber":"24",
    "addr:postcode":"3768 mj",
    "addr:street":"De Beaufortlaan",
    "iso:country":"NL",
    "sg:address":"De Beaufortlaan 24",
    "sg:city":"Soest",
    "sg:orig_category":"Farmaceutische Producten Gh",
    "sg:phone":"+31 35 602 8384",
    "sg:postcode":"3768 MJ",
    "sg:province":"Utrecht",
    "wof:name":"Van De Hoef & Renes",
    "wof:placetype":"venue"
},
  "geometry": {"coordinates":[5.293294,52.145679],"type":"Point"}
}