{
  "type": "Feature",
  "properties": {
    "addr:full":"Ambachtstr 32 Werkhoven Utrecht 3985 SC",
    "addr:housenumber":"32",
    "addr:postcode":"3985",
    "addr:street":"Ambachtstr",
    "iso:country":"NL",
    "sg:address":"Ambachtstr 32",
    "sg:city":"Werkhoven",
    "sg:orig_category":"Fotoreportages",
    "sg:phone":"+31 343 552 148",
    "sg:postcode":"3985 SC",
    "sg:province":"Utrecht",
    "wof:name":"Harts, F",
    "wof:placetype":"venue"
},
  "geometry": {"coordinates":[5.246948,52.023949],"type":"Point"}
}