{
  "type": "Feature",
  "properties": {
    "addr:full":"Korte Delft 3 Middelburg Zeeland 4331 AT",
    "addr:housenumber":"3",
    "addr:postcode":"4331",
    "addr:street":"Korte Delft",
    "iso:country":"NL",
    "sg:address":"Korte Delft 3",
    "sg:city":"Middelburg",
    "sg:orig_category":"Opticiens",
    "sg:phone":"+31 118 641 117",
    "sg:postcode":"4331 AT",
    "sg:province":"Zeeland",
    "wof:name":"Ton'S Brillenmode En Contactlenzen",
    "wof:placetype":"venue"
},
  "geometry": {"coordinates":[3.6161220074,51.4996452332],"type":"Point"}
}