{
  "type": "Feature",
  "properties": {
    "addr:full":"Nylansdk 90 Leeuwarden Provincie Friesland 8931 GM",
    "addr:housenumber":"90",
    "addr:postcode":"8931 gm",
    "addr:street":"Nylansdk;Provincie Friesland",
    "iso:country":"NL",
    "sg:address":"Nylansdk 90",
    "sg:city":"Leeuwarden",
    "sg:orig_category":"Autorijscholen",
    "sg:phone":"+31 58 844 1127",
    "sg:postcode":"8931 GM",
    "sg:province":"Provincie Friesland",
    "wof:name":"Bouma & Zn, A J",
    "wof:placetype":"venue"
},
  "geometry": {"coordinates":[5.784962,53.185143],"type":"Point"}
}