{
  "type": "Feature",
  "properties": {
    "iso:country":"NL",
    "sg:address":"Visafslagwg 14",
    "sg:city":"S Gravenhage",
    "sg:orig_category":"Vis En Visproducten - Groothandel",
    "sg:phone":"+31 70 354 9842",
    "sg:postcode":"2583 DM",
    "sg:province":"South Holland",
    "wof:name":"Taal Bv, Wout",
    "wof:placetype":"venue"
},
  "geometry": {"coordinates":[4.25526,52.09124],"type":"Point"}
}