{
  "type": "Feature",
  "properties": {
    "addr:full":"Aristide Briandring 90 Vlaardingen South Holland 3137 DB",
    "addr:housenumber":"90",
    "addr:postcode":"3137 db",
    "addr:street":"Aristide Briandring",
    "iso:country":"NL",
    "sg:address":"Aristide Briandring 90",
    "sg:city":"Vlaardingen",
    "sg:orig_category":"Overheidsdiensten",
    "sg:phone":"+31 10 474 5066",
    "sg:postcode":"3137 DB",
    "sg:province":"South Holland",
    "wof:name":"Wijkcentrum Holy",
    "wof:placetype":"venue"
},
  "geometry": {"coordinates":[4.346075058,51.9331245422],"type":"Point"}
}