{
  "type": "Feature",
  "properties": {
    "addr:full":"Barrier 5 Bergeyk Noord-Brabant 5571 TV",
    "addr:housenumber":"5",
    "addr:postcode":"5571 tv",
    "addr:street":"Barrier",
    "iso:country":"NL",
    "sg:address":"Barrier 5",
    "sg:city":"Bergeyk",
    "sg:orig_category":"Loonbedrijven",
    "sg:phone":"+31 40 206 8337",
    "sg:postcode":"5571 TV",
    "sg:province":"Noord-Brabant",
    "wof:name":"Jamar",
    "wof:placetype":"venue"
},
  "geometry": {"coordinates":[5.399873,51.272152],"type":"Point"}
}