{
  "type": "Feature",
  "properties": {
    "addr:full":"Tarthorst 777 Wageningen Gelderland 6708 JB",
    "addr:housenumber":"777",
    "addr:postcode":"6708 jb",
    "addr:street":"Tarthorst;Gelderland",
    "iso:country":"NL",
    "sg:address":"Tarthorst 777",
    "sg:city":"Wageningen",
    "sg:orig_category":"Adviesbureaus Land- En Tuinbouw",
    "sg:phone":"+31 317 426 076",
    "sg:postcode":"6708 JB",
    "sg:province":"Gelderland",
    "wof:name":"Buys",
    "wof:placetype":"venue"
},
  "geometry": {"coordinates":[5.664768,51.978451],"type":"Point"}
}