{
  "type": "Feature",
  "properties": {
    "iso:country":"NL",
    "sg:address":"Kouterstr 20",
    "sg:city":"Someren",
    "sg:classifiers":[
        {
            "category":"Sports & Exercise",
            "subcategory":"Stables",
            "type":"Entertainment"
        }
    ],
    "sg:phone":"+31 493 491 644",
    "sg:postcode":"5711 PD",
    "sg:province":"Noord-Brabant",
    "sg:tags":[
        "maneges"
    ],
    "wof:name":"Vlerk, De",
    "wof:placetype":"venue"
},
  "geometry": {"coordinates":[5.706303,51.396439],"type":"Point"}
}