{
  "type": "Feature",
  "properties": {
    "addr:full":"Gravenstr 2 S Gravenhage Zuid-Holland 2513 AK",
    "addr:housenumber":"2;gravenhage",
    "addr:postcode":"2513 ak",
    "addr:street":"Gravenstr;S",
    "iso:country":"NL",
    "sg:address":"Gravenstr 2",
    "sg:city":"S Gravenhage",
    "sg:orig_category":"Warenhuizen",
    "sg:phone":"+31 70 330 5300",
    "sg:postcode":"2513 AK",
    "sg:province":"Zuid-Holland",
    "wof:name":"Bonneterie, Maison De",
    "wof:placetype":"venue"
},
  "geometry": {"coordinates":[4.3033900261,52.0784416199],"type":"Point"}
}