{
  "type": "Feature",
  "properties": {
    "iso:country":"NL",
    "sg:address":"Laanstr 37",
    "sg:city":"Baarn",
    "sg:orig_category":"Kaas",
    "sg:phone":"+31 35 541 2987",
    "sg:postcode":"3743 BA",
    "sg:province":"Utrecht",
    "wof:name":"Kaasspecialist Vof, De",
    "wof:placetype":"venue"
},
  "geometry": {"coordinates":[5.2899231911,52.2113838196],"type":"Point"}
}