{
  "type": "Feature",
  "properties": {
    "addr:full":"Ruysdaelstraat 49 Amsterdam Noord-Holland 1071 XA",
    "addr:housenumber":"49",
    "addr:postcode":"1071 xa",
    "addr:street":"Ruysdaelstraat",
    "iso:country":"NL",
    "sg:address":"Ruysdaelstraat 49",
    "sg:city":"Amsterdam",
    "sg:orig_category":"Paramedische Behandelingen",
    "sg:phone":"+31 20 573 2510",
    "sg:postcode":"1071 XA",
    "sg:province":"Noord-Holland",
    "wof:name":"Stichting Thuiszorg Amsterdam Zuid",
    "wof:placetype":"venue"
},
  "geometry": {"coordinates":[4.883041,52.353802],"type":"Point"}
}