{
  "type": "Feature",
  "properties": {
    "addr:full":"Vlierwg 7 Houten Utrecht 3991 BA",
    "addr:housenumber":"7",
    "addr:postcode":"3991 ba",
    "addr:street":"Vlierwg",
    "iso:country":"NL",
    "sg:address":"Vlierwg 7",
    "sg:city":"Houten",
    "sg:orig_category":"Begrafenisverzorging",
    "sg:phone":"+31 30 635 3820",
    "sg:postcode":"3991 BA",
    "sg:province":"Utrecht",
    "sg:website":"http://www.monuta.nl",
    "wof:name":"Monuta",
    "wof:placetype":"venue"
},
  "geometry": {"coordinates":[5.16409,52.027359],"type":"Point"}
}