{
  "type": "Feature",
  "properties": {
    "addr:full":"Weimarstr 229 S Gravenhage Zuid-Holland 2562 HG",
    "addr:housenumber":"229;gravenhage",
    "addr:postcode":"2562 hg",
    "addr:street":"S",
    "iso:country":"NL",
    "sg:address":"Weimarstr 229",
    "sg:city":"S Gravenhage",
    "sg:orig_category":"Horloges En Klokken - Reparatie En Onderhoud",
    "sg:phone":"+31 70 345 1485",
    "sg:postcode":"2562 HG",
    "sg:province":"Zuid-Holland",
    "wof:name":"Stevens, A",
    "wof:placetype":"venue"
},
  "geometry": {"coordinates":[4.2832598686,52.0750007629],"type":"Point"}
}