{
  "type": "Feature",
  "properties": {
    "addr:full":"Empelsewg 15A Rosmalen Noord-Brabant 5241 NA",
    "addr:housenumber":"15a",
    "addr:postcode":"5241 na",
    "addr:street":"Empelsewg",
    "iso:country":"NL",
    "sg:address":"Empelsewg 15A",
    "sg:city":"Rosmalen",
    "sg:classifiers":[
        {
            "category":"Retail",
            "subcategory":"Auto Repair",
            "type":"Services"
        }
    ],
    "sg:phone":"+31 73 642 5029",
    "sg:postcode":"5241 NA",
    "sg:province":"Noord-Brabant",
    "sg:tags":[
        "garage"
    ],
    "wof:name":"Grunsven, M Van",
    "wof:placetype":"venue"
},
  "geometry": {"coordinates":[5.33474,51.727028],"type":"Point"}
}