{
  "type": "Feature",
  "properties": {
    "addr:full":"Otweg 15 Boskoop Zuid-Holland 2771 VX",
    "addr:housenumber":"15",
    "addr:postcode":"2771 vx",
    "addr:street":"Otweg",
    "iso:country":"NL",
    "sg:address":"Otweg 15",
    "sg:city":"Boskoop",
    "sg:orig_category":"Autokeuringen",
    "sg:phone":"+31 172 213 789",
    "sg:postcode":"2771 VX",
    "sg:province":"Zuid-Holland",
    "wof:name":"Oxford Cars Bv",
    "wof:placetype":"venue"
},
  "geometry": {"coordinates":[4.651797,52.086601],"type":"Point"}
}