{
  "type": "Feature",
  "properties": {
    "iso:country":"NL",
    "sg:address":"Grindweg 127",
    "sg:city":"Rotterdam",
    "sg:orig_category":"Verzekeringen",
    "sg:phone":"+31 10 422 3388",
    "sg:postcode":"3054 VJ",
    "sg:province":"Zuid-Holland",
    "wof:name":"R.C. Quispel Assurantien Bv",
    "wof:placetype":"venue"
},
  "geometry": {"coordinates":[4.49602,51.96331],"type":"Point"}
}