{
  "type": "Feature",
  "properties": {
    "addr:full":"Eenerstraat 7 Norg Provincie Drenthe 9331 HA",
    "addr:housenumber":"7",
    "addr:postcode":"9331 ha",
    "addr:street":"Eenerstraat;Provincie Drenthe",
    "iso:country":"NL",
    "sg:address":"Eenerstraat 7",
    "sg:city":"Norg",
    "sg:orig_category":"Meubelzaken, Woning- And Keukeninrichting",
    "sg:phone":"+31 6 23086813",
    "sg:postcode":"9331 HA",
    "sg:province":"Provincie Drenthe",
    "wof:name":"Mundano",
    "wof:placetype":"venue"
},
  "geometry": {"coordinates":[6.455707,53.067562],"type":"Point"}
}