{
  "type": "Feature",
  "properties": {
    "addr:full":"Schoutstr 7 Bladel Noord-Brabant 5531 GR",
    "addr:housenumber":"7",
    "addr:postcode":"5531",
    "addr:street":"Schoutstr",
    "iso:country":"NL",
    "sg:address":"Schoutstr 7",
    "sg:city":"Bladel",
    "sg:orig_category":"Timmerwerken",
    "sg:phone":"+31 497 385 524",
    "sg:postcode":"5531 GR",
    "sg:province":"Noord-Brabant",
    "wof:name":"Smetsers, Henk",
    "wof:placetype":"venue"
},
  "geometry": {"coordinates":[5.227208,51.369858],"type":"Point"}
}