{
  "type": "Feature",
  "properties": {
    "addr:full":"Koningsln 48 Amsterdam Noord-Holland 1075 AE",
    "addr:housenumber":"48",
    "addr:postcode":"1075 ae",
    "addr:street":"Koningsln",
    "iso:country":"NL",
    "sg:address":"Koningsln 48",
    "sg:city":"Amsterdam",
    "sg:classifiers":[
        {
            "category":"Travel",
            "subcategory":"Hotels & Motels",
            "type":"Entertainment"
        }
    ],
    "sg:phone":"+31 20 673 5252",
    "sg:postcode":"1075 AE",
    "sg:province":"Noord-Holland",
    "wof:name":"Borgmann Villa Bv",
    "wof:placetype":"venue"
},
  "geometry": {"coordinates":[4.862613,52.355541],"type":"Point"}
}