{
  "type": "Feature",
  "properties": {
    "iso:country":"NL",
    "sg:address":"Kroostwg 49A",
    "sg:city":"Zeist",
    "sg:orig_category":"Pensioenen",
    "sg:phone":"+31 30 263 0442",
    "sg:postcode":"3704 EB",
    "sg:province":"Utrecht",
    "wof:name":"Lagerweij",
    "wof:placetype":"venue"
},
  "geometry": {"coordinates":[5.222477,52.08963],"type":"Point"}
}