{
  "type": "Feature",
  "properties": {
    "iso:country":"NL",
    "sg:address":"Westzijde 122",
    "sg:city":"Zaandam",
    "sg:orig_category":"Banken And Kredietinstellingen",
    "sg:phone":"+31 75 612 0855",
    "sg:postcode":"1506 EJ",
    "sg:province":"North Holland",
    "wof:name":"Ing Bank",
    "wof:placetype":"venue"
},
  "geometry": {"coordinates":[4.82058,52.44368],"type":"Point"}
}