{
  "type": "Feature",
  "properties": {
    "addr:full":"De Middend 98-100 Grootebroek Noord-Holland 1613 KZ",
    "addr:postcode":"98-100;1613 kz",
    "addr:street":"De Middend",
    "iso:country":"NL",
    "sg:address":"De Middend 98-100",
    "sg:city":"Grootebroek",
    "sg:orig_category":"Apotheken",
    "sg:phone":"+31 228 517 348",
    "sg:postcode":"1613 KZ",
    "sg:province":"Noord-Holland",
    "wof:name":"Stede Broec",
    "wof:placetype":"venue"
},
  "geometry": {"coordinates":[5.224966,52.697487],"type":"Point"}
}