{
  "type": "Feature",
  "properties": {
    "addr:full":"Kruiswg 1 Ridderkerk South Holland 2982 TN",
    "addr:housenumber":"1",
    "addr:postcode":"2982",
    "addr:street":"Kruiswg",
    "iso:country":"NL",
    "sg:address":"Kruiswg 1",
    "sg:city":"Ridderkerk",
    "sg:orig_category":"Fitnesscentra",
    "sg:phone":"+31 180 462 722",
    "sg:postcode":"2982 TN",
    "sg:province":"South Holland",
    "wof:name":"Reijerbos",
    "wof:placetype":"venue"
},
  "geometry": {"coordinates":[4.578535,51.87365],"type":"Point"}
}