{
  "type": "Feature",
  "properties": {
    "addr:full":"Leidsekd 82 Amsterdam North Holland 1017 PM",
    "addr:housenumber":"82",
    "addr:postcode":"1017 pm",
    "addr:street":"Leidsekd",
    "iso:country":"NL",
    "sg:address":"Leidsekd 82",
    "sg:city":"Amsterdam",
    "sg:classifiers":[
        {
            "category":"Travel",
            "subcategory":"Hotels & Motels",
            "type":"Entertainment"
        }
    ],
    "sg:phone":"+31 20 623 0295",
    "sg:postcode":"1017 PM",
    "sg:province":"North Holland",
    "wof:name":"Kooyk",
    "wof:placetype":"venue"
},
  "geometry": {"coordinates":[4.893195,52.373119],"type":"Point"}
}