{
  "type": "Feature",
  "properties": {
    "addr:full":"Bosjesw 29 Sluiskil Zeeland 4541 AM",
    "addr:housenumber":"29",
    "addr:postcode":"4541",
    "addr:street":"Bosjesw",
    "iso:country":"NL",
    "sg:address":"Bosjesw 29",
    "sg:city":"Sluiskil",
    "sg:orig_category":"Land- En Tuinbouw - Loonbedrijven",
    "sg:phone":"+31 115 471 384",
    "sg:postcode":"4541 AM",
    "sg:province":"Zeeland",
    "wof:name":"Walhout Jzn, J",
    "wof:placetype":"venue"
},
  "geometry": {"coordinates":[3.835255,51.279408],"type":"Point"}
}