{
  "type": "Feature",
  "properties": {
    "addr:full":"Dorpsstr 37 Wagenberg Noord-Brabant 4845 CC",
    "addr:housenumber":"37",
    "addr:postcode":"4845 cc",
    "addr:street":"Dorpsstr",
    "iso:country":"NL",
    "sg:address":"Dorpsstr 37",
    "sg:city":"Wagenberg",
    "sg:orig_category":"Kappers",
    "sg:phone":"+31 76 593 4446",
    "sg:postcode":"4845 CC",
    "sg:province":"Noord-Brabant",
    "wof:name":"Oo Nix",
    "wof:placetype":"venue"
},
  "geometry": {"coordinates":[4.744085,51.663872],"type":"Point"}
}