{
  "type": "Feature",
  "properties": {
    "addr:full":"Bloemendaalsewg 238 Overveen Noord-Holland 2051 GM",
    "addr:housenumber":"238",
    "addr:postcode":"2051 gm",
    "iso:country":"NL",
    "sg:address":"Bloemendaalsewg 238",
    "sg:city":"Overveen",
    "sg:orig_category":"Apotheken",
    "sg:phone":"+31 23 527 7447",
    "sg:postcode":"2051 GM",
    "sg:province":"Noord-Holland",
    "wof:name":"Elswout",
    "wof:placetype":"venue"
},
  "geometry": {"coordinates":[4.60922,52.390957],"type":"Point"}
}