{
  "type": "Feature",
  "properties": {
    "addr:full":"Van Der Baanstraat 26 Wolphaartsdijk Zeeland 4471 BR",
    "addr:housenumber":"26",
    "addr:postcode":"4471 br",
    "addr:street":"Van Der Baanstraat",
    "iso:country":"NL",
    "sg:address":"Van Der Baanstraat 26",
    "sg:city":"Wolphaartsdijk",
    "sg:classifiers":[
        {
            "category":"Education",
            "subcategory":"Preschool",
            "type":"Public Place"
        }
    ],
    "sg:phone":"+31 113 586 048",
    "sg:postcode":"4471 BR",
    "sg:province":"Zeeland",
    "sg:tags":[
        "kleuteronderwijs",
        "basis-"
    ],
    "wof:name":"Ichthusschool",
    "wof:placetype":"venue"
},
  "geometry": {"coordinates":[3.819837,51.530426],"type":"Point"}
}