{
  "type": "Feature",
  "properties": {
    "iso:country":"NL",
    "sg:address":"Hoofdstraat 97",
    "sg:city":"Kesteren",
    "sg:orig_category":"Pluimveehouderijen",
    "sg:phone":"+31 488 483 970",
    "sg:postcode":"4041 AC",
    "sg:province":"Gelderland",
    "wof:name":"H.C. Zaaijer",
    "wof:placetype":"venue"
},
  "geometry": {"coordinates":[5.573963,51.928089],"type":"Point"}
}