{
  "type": "Feature",
  "properties": {
    "iso:country":"NL",
    "sg:address":"Miep Giesstraat 20",
    "sg:city":"Montfoort",
    "sg:orig_category":"Parfum And Cosmetica Gh",
    "sg:phone":"+31 348 473 658",
    "sg:postcode":"3417 CZ",
    "sg:province":"Utrecht",
    "wof:name":"Schoonheidssalon Adrieene",
    "wof:placetype":"venue"
},
  "geometry": {"coordinates":[4.9585,52.044312],"type":"Point"}
}