{
  "type": "Feature",
  "properties": {
    "addr:full":"Forel 115 Ridderkerk Zuid-Holland 2986 RA",
    "addr:housenumber":"115",
    "addr:postcode":"2986 ra",
    "addr:street":"Forel",
    "iso:country":"NL",
    "sg:address":"Forel 115",
    "sg:city":"Ridderkerk",
    "sg:orig_category":"Administratie- En Boekhoudkantoren",
    "sg:phone":"+31 180 427 911",
    "sg:postcode":"2986 RA",
    "sg:province":"Zuid-Holland",
    "sg:website":"http://www.hcolijn.nl",
    "wof:name":"Colijn, H",
    "wof:placetype":"venue"
},
  "geometry": {"coordinates":[4.624025,51.865051],"type":"Point"}
}