{
  "type": "Feature",
  "properties": {
    "addr:full":"Stationsstraat 113 Ermelo Gelderland 3851 NC",
    "addr:housenumber":"113",
    "addr:postcode":"3851 nc",
    "addr:street":"Stationsstraat;Gelderland",
    "iso:country":"NL",
    "sg:address":"Stationsstraat 113",
    "sg:city":"Ermelo",
    "sg:orig_category":"Herenmodezaken",
    "sg:phone":"+31 341 551 453",
    "sg:postcode":"3851 NC",
    "sg:province":"Gelderland",
    "wof:name":"G.H. Schreurs Bv",
    "wof:placetype":"venue"
},
  "geometry": {"coordinates":[5.61842,52.299694],"type":"Point"}
}