{
  "type": "Feature",
  "properties": {
    "addr:full":"Ankelaarswg 432 Apeldoorn Gelderland 7323 AE",
    "addr:housenumber":"432",
    "addr:postcode":"7323 ae",
    "addr:street":"Gelderland",
    "iso:country":"NL",
    "sg:address":"Ankelaarswg 432",
    "sg:city":"Apeldoorn",
    "sg:orig_category":"Tegelwerken",
    "sg:phone":"+31 55 360 2197",
    "sg:postcode":"7323 AE",
    "sg:province":"Gelderland",
    "wof:name":"Vries En Schut, De",
    "wof:placetype":"venue"
},
  "geometry": {"coordinates":[5.990941,52.231331],"type":"Point"}
}