{
  "type": "Feature",
  "properties": {
    "addr:full":"J V Brakelplnts 6 Voorschoten Zuid-Holland 2253 TD",
    "addr:housenumber":"6",
    "addr:postcode":"2253 td",
    "addr:street":"J;Brakelplnts",
    "iso:country":"NL",
    "sg:address":"J V Brakelplnts 6",
    "sg:city":"Voorschoten",
    "sg:orig_category":"Administratie- En Boekhoudkantoren",
    "sg:phone":"+31 71 561 9401",
    "sg:postcode":"2253 TD",
    "sg:province":"Zuid-Holland",
    "wof:name":"Hakker, Hans",
    "wof:placetype":"venue"
},
  "geometry": {"coordinates":[4.44429,52.124825],"type":"Point"}
}