{
  "type": "Feature",
  "properties": {
    "addr:full":"H Hamerstr 99 S Gravendeel Zuid-Holland 3295 CG",
    "addr:housenumber":"99",
    "addr:postcode":"3295 cg",
    "addr:street":"S Gravendeel",
    "iso:country":"NL",
    "sg:address":"H Hamerstr 99",
    "sg:city":"S Gravendeel",
    "sg:orig_category":"Kappers",
    "sg:phone":"+31 78 673 1553",
    "sg:postcode":"3295 CG",
    "sg:province":"Zuid-Holland",
    "wof:name":"Haarzaak",
    "wof:placetype":"venue"
},
  "geometry": {"coordinates":[4.6132931709,51.7770423889],"type":"Point"}
}