{
  "type": "Feature",
  "properties": {
    "addr:full":"Vennipperhof 7 Hillegom Zuid-Holland 2181 RT",
    "addr:housenumber":"7",
    "addr:postcode":"2181 rt",
    "addr:street":"Vennipperhof",
    "iso:country":"NL",
    "sg:address":"Vennipperhof 7",
    "sg:city":"Hillegom",
    "sg:orig_category":"Bloemen And Planten Gh",
    "sg:phone":"+31 252 525 727",
    "sg:postcode":"2181 RT",
    "sg:province":"Zuid-Holland",
    "wof:name":"Wilco Willemse Bv",
    "wof:placetype":"venue"
},
  "geometry": {"coordinates":[4.583437,52.292786],"type":"Point"}
}