{
  "type": "Feature",
  "properties": {
    "iso:country":"NL",
    "sg:address":"W Barendrechtln 28",
    "sg:city":"Ryswyk Zh",
    "sg:orig_category":"Bedrijfsopleidingen",
    "sg:phone":"+31 70 415 0015",
    "sg:postcode":"2286 MG",
    "sg:province":"South Holland",
    "wof:name":"Solution",
    "wof:placetype":"venue"
},
  "geometry": {"coordinates":[4.32436,52.037251],"type":"Point"}
}