{
  "type": "Feature",
  "properties": {
    "addr:full":"Javastraat 98 Amsterdam North Holland 1094 HM",
    "addr:housenumber":"98",
    "addr:postcode":"1094 hm",
    "addr:street":"Javastraat",
    "iso:country":"NL",
    "sg:address":"Javastraat 98",
    "sg:city":"Amsterdam",
    "sg:orig_category":"Visspeciaalzaken",
    "sg:phone":"+31 20 694 1252",
    "sg:postcode":"1094 HM",
    "sg:province":"North Holland",
    "wof:name":"Vishandel Tol",
    "wof:placetype":"venue"
},
  "geometry": {"coordinates":[4.936321,52.363586],"type":"Point"}
}