{
  "type": "Feature",
  "properties": {
    "addr:full":"Lg Engwg 11 Putten Gelderland 3882 BC",
    "addr:housenumber":"11",
    "addr:postcode":"3882 bc",
    "addr:street":"Lg;Gelderland",
    "iso:country":"NL",
    "sg:address":"Lg Engwg 11",
    "sg:city":"Putten",
    "sg:orig_category":"Administratie- En Boekhoudkantoren",
    "sg:phone":"+31 341 362 535",
    "sg:postcode":"3882 BC",
    "sg:province":"Gelderland",
    "wof:name":"Meij, Van Der",
    "wof:placetype":"venue"
},
  "geometry": {"coordinates":[5.604902,52.25325],"type":"Point"}
}