{
  "type": "Feature",
  "properties": {
    "addr:full":"Langstraat 22 Weert Limburg 6001 CV",
    "addr:housenumber":"22",
    "addr:postcode":"6001 cv",
    "addr:street":"Langstraat",
    "iso:country":"NL",
    "sg:address":"Langstraat 22",
    "sg:city":"Weert",
    "sg:orig_category":"Fotolaboratoria",
    "sg:phone":"+31 495 533 121",
    "sg:postcode":"6001 CV",
    "sg:province":"Limburg",
    "wof:name":"Fotolaboratorium J.J. Knapen Bv",
    "wof:placetype":"venue"
},
  "geometry": {"coordinates":[5.703781,51.255016],"type":"Point"}
}