{
  "type": "Feature",
  "properties": {
    "addr:full":"Dorpsstr 57 Aalsmeer Noord-Holland 1431 CB",
    "addr:housenumber":"57",
    "addr:postcode":"1431 cb",
    "addr:street":"Dorpsstr",
    "iso:country":"NL",
    "sg:address":"Dorpsstr 57",
    "sg:city":"Aalsmeer",
    "sg:orig_category":"Touringcars",
    "sg:phone":"+31 297 346 302",
    "sg:postcode":"1431 CB",
    "sg:province":"Noord-Holland",
    "wof:name":"Met & Co Bv",
    "wof:placetype":"venue"
},
  "geometry": {"coordinates":[4.74885,52.270992],"type":"Point"}
}