{
  "type": "Feature",
  "properties": {
    "addr:full":"Davidstr 18 Enkhuizen Noord-Holland 1601 AV",
    "addr:housenumber":"18;1601",
    "addr:postcode":"av",
    "addr:street":"Davidstr",
    "iso:country":"NL",
    "sg:address":"Davidstr 18",
    "sg:city":"Enkhuizen",
    "sg:orig_category":"Schilders",
    "sg:phone":"+31 228 320 449",
    "sg:postcode":"1601 AV",
    "sg:province":"Noord-Holland",
    "sg:website":"http://www.schilderjeroen.nl",
    "wof:name":"Ekkelenkamp, Glas- & Schilderwerk J",
    "wof:placetype":"venue"
},
  "geometry": {"coordinates":[5.281253,52.703072],"type":"Point"}
}