{
  "type": "Feature",
  "properties": {
    "addr:full":"Dorpsstraat 22 Hellevoetsluis Zuid-Holland 3223 BG",
    "addr:housenumber":"22",
    "addr:postcode":"3223",
    "addr:street":"Dorpsstraat",
    "iso:country":"NL",
    "sg:address":"Dorpsstraat 22",
    "sg:city":"Hellevoetsluis",
    "sg:classifiers":[
        {
            "category":"Education",
            "subcategory":"Preschool",
            "type":"Public Place"
        }
    ],
    "sg:phone":"+31 181 313 165",
    "sg:postcode":"3223 BG",
    "sg:province":"Zuid-Holland",
    "sg:tags":[
        "kleuteronderwijs",
        "basis-"
    ],
    "wof:name":"Openbare Basisschool De Woelhoek",
    "wof:placetype":"venue"
},
  "geometry": {"coordinates":[4.143074,51.854248],"type":"Point"}
}