{
  "type": "Feature",
  "properties": {
    "addr:full":"Noorddonk 100 Steenbergen Nb North Brabant 4651 ZB",
    "addr:housenumber":"100;nb",
    "addr:postcode":"4651 zb",
    "addr:street":"Noorddonk",
    "iso:country":"NL",
    "sg:address":"Noorddonk 100",
    "sg:city":"Steenbergen Nb",
    "sg:orig_category":"Bedrijfsinventaris Gh",
    "sg:phone":"+31 167 540 575",
    "sg:postcode":"4651 ZB",
    "sg:province":"North Brabant",
    "wof:name":"Javeko Bv",
    "wof:placetype":"venue"
},
  "geometry": {"coordinates":[4.314555,51.585594],"type":"Point"}
}