{
  "type": "Feature",
  "properties": {
    "addr:full":"Overtoom 311 Amsterdam North Holland 1054 JL",
    "addr:housenumber":"311",
    "addr:postcode":"1054 jl",
    "addr:street":"Overtoom",
    "iso:country":"NL",
    "sg:address":"Overtoom 311",
    "sg:city":"Amsterdam",
    "sg:orig_category":"Adviesbureaus Marketing",
    "sg:phone":"+31 20 489 3929",
    "sg:postcode":"1054 JL",
    "sg:province":"North Holland",
    "wof:name":"Web At Work",
    "wof:placetype":"venue"
},
  "geometry": {"coordinates":[4.86436,52.359852],"type":"Point"}
}