{
  "type": "Feature",
  "properties": {
    "addr:full":"Jasmynstr 15 Puttershoek Zuid-Holland 3297 BA",
    "addr:housenumber":"15",
    "addr:postcode":"3297 ba",
    "addr:street":"Jasmynstr",
    "iso:country":"NL",
    "sg:address":"Jasmynstr 15",
    "sg:city":"Puttershoek",
    "sg:orig_category":"Adviesbureaus Bedrijfsorganisatie",
    "sg:phone":"+31 78 676 7099",
    "sg:postcode":"3297 BA",
    "sg:province":"Zuid-Holland",
    "wof:name":"Nion Bv",
    "wof:placetype":"venue"
},
  "geometry": {"coordinates":[4.563777,51.805138],"type":"Point"}
}