{
  "type": "Feature",
  "properties": {
    "iso:country":"NL",
    "sg:address":"Dr Poelsstraat 13",
    "sg:city":"Brunssum",
    "sg:orig_category":"Boekenuitgeverijen",
    "sg:phone":"+31 45 525 1086",
    "sg:postcode":"6444 AJ",
    "sg:province":"Limburg",
    "wof:name":"Drukkerij/Uitgeverij Gronau",
    "wof:placetype":"venue"
},
  "geometry": {"coordinates":[5.966191,50.944389],"type":"Point"}
}