{
  "type": "Feature",
  "properties": {
    "addr:full":"Postbus 630 Delft Zuid-Holland 2600 AP",
    "addr:housenumber":"630",
    "addr:postcode":"2600 ap",
    "addr:street":"Postbus",
    "iso:country":"NL",
    "sg:address":"Postbus 630",
    "sg:city":"Delft",
    "sg:orig_category":"Verenigingen En Stichtingen",
    "sg:phone":"+31 15 262 3011",
    "sg:postcode":"2600 AP",
    "sg:province":"Zuid-Holland",
    "wof:name":"Sranti",
    "wof:placetype":"venue"
},
  "geometry": {"coordinates":[4.35869,52.011501],"type":"Point"}
}