{
  "type": "Feature",
  "properties": {
    "addr:full":"O Voorstr 61 Oud Beyerland Zuid-Holland 3262 JG",
    "addr:housenumber":"61",
    "addr:postcode":"3262 jg",
    "addr:street":"Oud Beyerland",
    "iso:country":"NL",
    "sg:address":"O Voorstr 61",
    "sg:city":"Oud Beyerland",
    "sg:orig_category":"Herenkleding",
    "sg:phone":"+31 186 620 664",
    "sg:postcode":"3262 JG",
    "sg:province":"Zuid-Holland",
    "wof:name":"Divi Divi",
    "wof:placetype":"venue"
},
  "geometry": {"coordinates":[4.41701,51.823044],"type":"Point"}
}