{
  "type": "Feature",
  "properties": {
    "addr:full":"Swammerdamstr 26Bg Amsterdam North Holland 1091 RV",
    "addr:housenumber":"26bg",
    "addr:postcode":"1091 rv",
    "addr:street":"Swammerdamstr",
    "iso:country":"NL",
    "sg:address":"Swammerdamstr 26Bg",
    "sg:city":"Amsterdam",
    "sg:orig_category":"Grafisch Ontwerpers",
    "sg:phone":"+31 20 463 1616",
    "sg:postcode":"1091 RV",
    "sg:province":"North Holland",
    "sg:website":"http://www.maslow.nl",
    "wof:name":"Maslow",
    "wof:placetype":"venue"
},
  "geometry": {"coordinates":[4.907372,52.358051],"type":"Point"}
}