{
  "type": "Feature",
  "properties": {
    "addr:full":"Koningin Wilhelminalaan 20 Kedichem Zuid-Holland 4247 EN",
    "addr:housenumber":"20",
    "addr:postcode":"4247 en",
    "addr:street":"Koningin Wilhelminalaan",
    "iso:country":"NL",
    "sg:address":"Koningin Wilhelminalaan 20",
    "sg:city":"Kedichem",
    "sg:orig_category":"Overheidsdiensten",
    "sg:phone":"+31 183 562 353",
    "sg:postcode":"4247 EN",
    "sg:province":"Zuid-Holland",
    "wof:name":"H.C. Boets",
    "wof:placetype":"venue"
},
  "geometry": {"coordinates":[5.0514030457,51.860786438],"type":"Point"}
}