{
  "type": "Feature",
  "properties": {
    "iso:country":"NL",
    "sg:address":"Steegde 56",
    "sg:city":"Appelscha",
    "sg:orig_category":"Bloemen And Planten",
    "sg:phone":"+31 516 432 044",
    "sg:postcode":"8426 CC",
    "sg:province":"Friesland",
    "wof:name":"De Schans",
    "wof:placetype":"venue"
},
  "geometry": {"coordinates":[6.346544,52.956665],"type":"Point"}
}