{
  "type": "Feature",
  "properties": {
    "iso:country":"NL",
    "sg:address":"Admiraliteitsstraat 8",
    "sg:city":"Rotterdam",
    "sg:classifiers":[
        {
            "category":"Retail",
            "subcategory":"Photofinishing",
            "type":"Services"
        }
    ],
    "sg:phone":"+31 10 403 5300",
    "sg:postcode":"3063 EK",
    "sg:province":"South Holland",
    "sg:tags":[
        "foto",
        "film"
    ],
    "wof:name":"Foka Bv",
    "wof:placetype":"venue"
},
  "geometry": {"coordinates":[4.500636,51.922283],"type":"Point"}
}