{
  "type": "Feature",
  "properties": {
    "iso:country":"NL",
    "sg:address":"Hooiwg 15",
    "sg:city":"Lucaswolde",
    "sg:orig_category":"Keukens",
    "sg:phone":"+31 594 549 168",
    "sg:postcode":"9825 TE",
    "sg:province":"Groningen",
    "wof:name":"Brandsema",
    "wof:placetype":"venue"
},
  "geometry": {"coordinates":[6.301087,53.184635],"type":"Point"}
}