{
  "type": "Feature",
  "properties": {
    "addr:full":"Terworm 34 Haarlem Noord-Holland 2036 CP",
    "addr:housenumber":"34",
    "addr:postcode":"2036 cp",
    "addr:street":"Terworm",
    "iso:country":"NL",
    "sg:address":"Terworm 34",
    "sg:city":"Haarlem",
    "sg:classifiers":[
        {
            "category":"Wholesale",
            "subcategory":"Meat",
            "type":"Manufacturing & Wholesale Goods"
        }
    ],
    "sg:phone":"+31 23 543 1015",
    "sg:postcode":"2036 CP",
    "sg:province":"Noord-Holland",
    "sg:tags":[
        "regeltechniek",
        "en",
        "meet-"
    ],
    "sg:website":"http://www.topchoice.nl",
    "wof:name":"Topchoice Bv",
    "wof:placetype":"venue"
},
  "geometry": {"coordinates":[4.65805,52.348999],"type":"Point"}
}