{
  "type": "Feature",
  "properties": {
    "addr:full":"Maaseikerweg 257 Weert Limburg 6005 RA",
    "addr:housenumber":"257",
    "addr:postcode":"6005 ra",
    "addr:street":"Maaseikerweg",
    "iso:country":"NL",
    "sg:address":"Maaseikerweg 257",
    "sg:city":"Weert",
    "sg:orig_category":"Bloemen And Planten",
    "sg:phone":"+31 495 562 247",
    "sg:postcode":"6005 RA",
    "sg:province":"Limburg",
    "wof:name":"Flinsenhof",
    "wof:placetype":"venue"
},
  "geometry": {"coordinates":[5.722845,51.212376],"type":"Point"}
}