{
  "type": "Feature",
  "properties": {
    "addr:full":"Steekterweg 69 Alphen Aan Den Rijn Zuid-Holland 2407 BE",
    "addr:housenumber":"69",
    "addr:postcode":"2407",
    "addr:street":"Steekterweg",
    "iso:country":"NL",
    "sg:address":"Steekterweg 69",
    "sg:city":"Alphen Aan Den Rijn",
    "sg:orig_category":"Partycatering And -Organisatie",
    "sg:phone":"+31 172 434 260",
    "sg:postcode":"2407 BE",
    "sg:province":"Zuid-Holland",
    "wof:name":"Belle Lunch",
    "wof:placetype":"venue"
},
  "geometry": {"coordinates":[4.688267,52.116348],"type":"Point"}
}