{
  "type": "Feature",
  "properties": {
    "iso:country":"NL",
    "sg:address":"Voorduinstraat 49Zw",
    "sg:city":"Haarlem",
    "sg:orig_category":"Koeriersdiensten",
    "sg:phone":"+31 251 216 580",
    "sg:postcode":"2023 PC",
    "sg:province":"Noord-Holland",
    "wof:name":"Top Koeriers",
    "wof:placetype":"venue"
},
  "geometry": {"coordinates":[4.630891,52.40126],"type":"Point"}
}