{
  "type": "Feature",
  "properties": {
    "addr:full":"Stationswg 92C Heiloo Noord-Holland 1852 LN",
    "addr:housenumber":"92c",
    "addr:postcode":"1852 ln",
    "addr:street":"Stationswg",
    "iso:country":"NL",
    "sg:address":"Stationswg 92C",
    "sg:city":"Heiloo",
    "sg:orig_category":"Bejaarden - Verzorgingstehuizen",
    "sg:phone":"+31 72 533 0409",
    "sg:postcode":"1852 LN",
    "sg:province":"Noord-Holland",
    "wof:name":"Overkerck Woon- En Zorgcentr",
    "wof:placetype":"venue"
},
  "geometry": {"coordinates":[4.700853,52.600544],"type":"Point"}
}