{
  "type": "Feature",
  "properties": {
    "addr:full":"Grazendonkstr 8A Breda Noord-Brabant 4818 PJ",
    "addr:housenumber":"8a",
    "addr:postcode":"4818 pj",
    "addr:street":"Grazendonkstr",
    "iso:country":"NL",
    "sg:address":"Grazendonkstr 8A",
    "sg:city":"Breda",
    "sg:orig_category":"Artiesten/Gezelschappen",
    "sg:phone":"+31 76 520 6764",
    "sg:postcode":"4818 PJ",
    "sg:province":"Noord-Brabant",
    "wof:name":"Tropical Sound, The",
    "wof:placetype":"venue"
},
  "geometry": {"coordinates":[4.777995,51.573872],"type":"Point"}
}