{
  "type": "Feature",
  "properties": {
    "addr:full":"Bloemstr 10 A Sneek Friesland 8603 XW",
    "addr:housenumber":"10 a",
    "addr:postcode":"8603 xw",
    "addr:street":"Bloemstr",
    "iso:country":"NL",
    "sg:address":"Bloemstr 10 A",
    "sg:city":"Sneek",
    "sg:orig_category":"Verenigingen En Stichtingen",
    "sg:phone":"+31 515 424 560",
    "sg:postcode":"8603 XW",
    "sg:province":"Friesland",
    "wof:name":"Buro Jeugdzorg",
    "wof:placetype":"venue"
},
  "geometry": {"coordinates":[5.66045,53.034492],"type":"Point"}
}