{
  "type": "Feature",
  "properties": {
    "addr:full":"Joan Maetsuykerlaan 24 Haarlem North Holland 2024 AS",
    "addr:housenumber":"24",
    "addr:postcode":"2024 as",
    "addr:street":"Joan Maetsuykerlaan",
    "iso:country":"NL",
    "sg:address":"Joan Maetsuykerlaan 24",
    "sg:city":"Haarlem",
    "sg:orig_category":"Verzekeringen",
    "sg:phone":"+31 23 525 3332",
    "sg:postcode":"2024 AS",
    "sg:province":"North Holland",
    "wof:name":"Assurantiekantoor Meijeren",
    "wof:placetype":"venue"
},
  "geometry": {"coordinates":[4.629357,52.403366],"type":"Point"}
}