{
  "type": "Feature",
  "properties": {
    "addr:full":"Nieuwstr 75B Middelharnis Zuid-Holland 3241 CL",
    "addr:housenumber":"75b",
    "addr:postcode":"3241",
    "addr:street":"Nieuwstr",
    "iso:country":"NL",
    "sg:address":"Nieuwstr 75B",
    "sg:city":"Middelharnis",
    "sg:orig_category":"Kappers",
    "sg:phone":"+31 187 487 225",
    "sg:postcode":"3241 CL",
    "sg:province":"Zuid-Holland",
    "wof:name":"Chamonix",
    "wof:placetype":"venue"
},
  "geometry": {"coordinates":[4.1621928215,51.7598800659],"type":"Point"}
}