{
  "type": "Feature",
  "properties": {
    "addr:full":"Claudius Prinsenlaan 132 Breda North Brabant 4818 CP",
    "addr:housenumber":"132",
    "addr:postcode":"4818 cp",
    "addr:street":"Claudius Prinsenlaan",
    "iso:country":"NL",
    "sg:address":"Claudius Prinsenlaan 132",
    "sg:city":"Breda",
    "sg:orig_category":"Public Relationbureaus",
    "sg:phone":"+31 76 522 3333",
    "sg:postcode":"4818 CP",
    "sg:province":"North Brabant",
    "wof:name":"Efcom Newton 21",
    "wof:placetype":"venue"
},
  "geometry": {"coordinates":[4.798559,51.585705],"type":"Point"}
}