{
  "type": "Feature",
  "properties": {
    "addr:full":"Stadhuispln 65B Lelystad Flevoland 8232 VM",
    "addr:housenumber":"65b",
    "addr:postcode":"8232 vm",
    "addr:street":"Stadhuispln;Flevoland",
    "iso:country":"NL",
    "sg:address":"Stadhuispln 65B",
    "sg:city":"Lelystad",
    "sg:orig_category":"Projectontwikkeling",
    "sg:phone":"+31 320 215 210",
    "sg:postcode":"8232 VM",
    "sg:province":"Flevoland",
    "wof:name":"Develop Lelystad",
    "wof:placetype":"venue"
},
  "geometry": {"coordinates":[5.47694,52.50724],"type":"Point"}
}