{
  "type": "Feature",
  "properties": {
    "addr:full":"Huissensestraat 27 Arnhem Gelderland 6833 HL",
    "addr:housenumber":"27",
    "addr:postcode":"6833 hl",
    "addr:street":"Huissensestraat",
    "iso:country":"NL",
    "sg:address":"Huissensestraat 27",
    "sg:city":"Arnhem",
    "sg:orig_category":"Verzekeringen",
    "sg:phone":"+31 26 321 8931",
    "sg:postcode":"6833 HL",
    "sg:province":"Gelderland",
    "wof:name":"Takens Assurantien",
    "wof:placetype":"venue"
},
  "geometry": {"coordinates":[5.908436,51.968025],"type":"Point"}
}