{
  "type": "Feature",
  "properties": {
    "addr:full":"Limbrichterstraat 67 Sittard Limburg 6131 EB",
    "addr:housenumber":"67",
    "addr:postcode":"6131 eb",
    "addr:street":"Limbrichterstraat",
    "iso:country":"NL",
    "sg:address":"Limbrichterstraat 67",
    "sg:city":"Sittard",
    "sg:orig_category":"Kunst And Kunstenaarsbenodigdheden",
    "sg:phone":"+31 46 451 5003",
    "sg:postcode":"6131 EB",
    "sg:province":"Limburg",
    "wof:name":"F.E.M. Pfennings",
    "wof:placetype":"venue"
},
  "geometry": {"coordinates":[5.86725,50.998375],"type":"Point"}
}