{
  "type": "Feature",
  "properties": {
    "addr:full":"Lauwers 13 Zwyndrecht Zuid-Holland 3332 TA",
    "addr:housenumber":"13",
    "addr:postcode":"3332 ta",
    "addr:street":"Lauwers",
    "iso:country":"NL",
    "sg:address":"Lauwers 13",
    "sg:city":"Zwyndrecht",
    "sg:orig_category":"Scheepssleep- En Duwvaart",
    "sg:phone":"+31 78 619 2071",
    "sg:postcode":"3332 TA",
    "sg:province":"Zuid-Holland",
    "wof:name":"Bosklopper En Bosman Vof",
    "wof:placetype":"venue"
},
  "geometry": {"coordinates":[4.65647,51.822247],"type":"Point"}
}