{
  "type": "Feature",
  "properties": {
    "iso:country":"NL",
    "sg:address":"Parallelwg 10A",
    "sg:city":"Geldrop",
    "sg:orig_category":"Peuterspeelzalen",
    "sg:phone":"+31 40 286 2690",
    "sg:postcode":"5664 AC",
    "sg:province":"Noord-Brabant",
    "wof:name":"Hummelhof",
    "wof:placetype":"venue"
},
  "geometry": {"coordinates":[5.552993,51.418911],"type":"Point"}
}