{
  "type": "Feature",
  "properties": {
    "addr:full":"Draaibrug 11 Aardenburg Zeeland 4527 PB",
    "addr:housenumber":"11",
    "addr:postcode":"4527 pb",
    "addr:street":"Draaibrug",
    "iso:country":"NL",
    "sg:address":"Draaibrug 11",
    "sg:city":"Aardenburg",
    "sg:orig_category":"Diverse Grafische Activiteiten",
    "sg:phone":"+31 117 491 996",
    "sg:postcode":"4527 PB",
    "sg:province":"Zeeland",
    "wof:name":"Computerservice Cadzand",
    "wof:placetype":"venue"
},
  "geometry": {"coordinates":[3.428882,51.298691],"type":"Point"}
}