{
  "type": "Feature",
  "properties": {
    "addr:full":"Almelosestraat 1 Ootmarsum Overijssel 7631 CC",
    "addr:housenumber":"1",
    "addr:postcode":"7631 cc",
    "addr:street":"Almelosestraat",
    "iso:country":"NL",
    "sg:address":"Almelosestraat 1",
    "sg:city":"Ootmarsum",
    "sg:classifiers":[
        {
            "category":"Travel",
            "subcategory":"Hotels & Motels",
            "type":"Entertainment"
        }
    ],
    "sg:phone":"+31 541 292 775",
    "sg:postcode":"7631 CC",
    "sg:province":"Overijssel",
    "wof:name":"Hotel De Vos",
    "wof:placetype":"venue"
},
  "geometry": {"coordinates":[6.892848,52.4076],"type":"Point"}
}