{
  "type": "Feature",
  "properties": {
    "addr:full":"Vergtweg 57 Zaltbommel Gelderland 5301 TC",
    "addr:housenumber":"57",
    "addr:postcode":"5301 tc",
    "addr:street":"Vergtweg;Gelderland",
    "iso:country":"NL",
    "sg:address":"Vergtweg 57",
    "sg:city":"Zaltbommel",
    "sg:orig_category":"Fruit And Groenten Gh",
    "sg:phone":"+31 418 516 687",
    "sg:postcode":"5301 TC",
    "sg:province":"Gelderland",
    "wof:name":"D. Verhoeks",
    "wof:placetype":"venue"
},
  "geometry": {"coordinates":[5.248335,51.805706],"type":"Point"}
}