{
  "type": "Feature",
  "properties": {
    "iso:country":"NL",
    "sg:address":"Enschedesestr 99",
    "sg:city":"Hengelo Ov",
    "sg:orig_category":"Hoortoestellen",
    "sg:phone":"+31 74 242 4562",
    "sg:postcode":"7551 EK",
    "sg:province":"Overijssel",
    "wof:name":"Beter Horen",
    "wof:placetype":"venue"
},
  "geometry": {"coordinates":[6.800091,52.262959],"type":"Point"}
}