{
  "type": "Feature",
  "properties": {
    "addr:full":"Enschedesestr 99 Hengelo Ov Overijssel 7551 EK",
    "addr:housenumber":"99",
    "addr:postcode":"7551 ek",
    "addr:street":"Enschedesestr;Ov",
    "iso:country":"NL",
    "sg:address":"Enschedesestr 99",
    "sg:city":"Hengelo Ov",
    "sg:orig_category":"Hoortoestellen",
    "sg:phone":"+31 74 242 4562",
    "sg:postcode":"7551 EK",
    "sg:province":"Overijssel",
    "wof:name":"Beter Horen",
    "wof:placetype":"venue"
},
  "geometry": {"coordinates":[6.800091,52.262959],"type":"Point"}
}