{
  "type": "Feature",
  "properties": {
    "addr:full":"Opaalstraat 15 Hengelo Ov Overijssel 7554 TS",
    "addr:housenumber":"15",
    "addr:postcode":"7554 ts",
    "addr:street":"Opaalstraat;Ov",
    "iso:country":"NL",
    "sg:address":"Opaalstraat 15",
    "sg:city":"Hengelo Ov",
    "sg:classifiers":[
        {
            "category":"Retail",
            "subcategory":"Storage",
            "type":"Services"
        }
    ],
    "sg:phone":"+31 74 243 7218",
    "sg:postcode":"7554 TS",
    "sg:province":"Overijssel",
    "sg:tags":[
        "opslag",
        "bewaring"
    ],
    "wof:name":"Uniek Hengelo Bv",
    "wof:placetype":"venue"
},
  "geometry": {"coordinates":[6.7762269974,52.2434310913],"type":"Point"}
}