{
  "type": "Feature",
  "properties": {
    "addr:full":"Aalscholverlaan 4 Nijkerk Gld Gelderland 3862 KL",
    "addr:housenumber":"4;3862 kl",
    "addr:street":"Aalscholverlaan;Gld Gelderland",
    "iso:country":"NL",
    "sg:address":"Aalscholverlaan 4",
    "sg:city":"Nijkerk Gld",
    "sg:orig_category":"Zuivelproducten",
    "sg:phone":"+31 33 245 9059",
    "sg:postcode":"3862 KL",
    "sg:province":"Gelderland",
    "wof:name":"De Kaashap",
    "wof:placetype":"venue"
},
  "geometry": {"coordinates":[5.491093,52.213364],"type":"Point"}
}