{
  "type": "Feature",
  "properties": {
    "addr:full":"Lierstr 9 Almere Flevoland 1312 JZ",
    "addr:housenumber":"9",
    "addr:postcode":"1312 jz",
    "addr:street":"Lierstr;Flevoland",
    "iso:country":"NL",
    "sg:address":"Lierstr 9",
    "sg:city":"Almere",
    "sg:orig_category":"Verenigingen En Stichtingen",
    "sg:phone":"+31 36 536 7527",
    "sg:postcode":"1312 JZ",
    "sg:province":"Flevoland",
    "wof:name":"Turkse Arbeiders Sticht Almere",
    "wof:placetype":"venue"
},
  "geometry": {"coordinates":[5.194,52.3717],"type":"Point"}
}