{
  "type": "Feature",
  "properties": {
    "iso:country":"NL",
    "sg:address":"Clingendaal 17",
    "sg:city":"Zwijndrecht",
    "sg:orig_category":"Daken And Skeletbouw",
    "sg:phone":"+31 78 610 1219",
    "sg:postcode":"3334 GB",
    "sg:province":"Zuid-Holland",
    "wof:name":"Besto Dakbedekking",
    "wof:placetype":"venue"
},
  "geometry": {"coordinates":[4.597673,51.814365],"type":"Point"}
}