{
  "type": "Feature",
  "properties": {
    "addr:full":"Kostersbulte 2 Aalten Gelderland 7121 CN",
    "addr:housenumber":"2",
    "addr:postcode":"7121 cn",
    "addr:street":"Kostersbulte;Gelderland",
    "iso:country":"NL",
    "sg:address":"Kostersbulte 2",
    "sg:city":"Aalten",
    "sg:classifiers":[
        {
            "category":"Shopping",
            "subcategory":"Gifts & Souvenirs",
            "type":"Retail Goods"
        }
    ],
    "sg:phone":"+31 543 477 533",
    "sg:postcode":"7121 CN",
    "sg:province":"Gelderland",
    "sg:tags":[
        "geschenken"
    ],
    "wof:name":"Wereldwinkel",
    "wof:placetype":"venue"
},
  "geometry": {"coordinates":[6.582218,51.916264],"type":"Point"}
}