{
  "type": "Feature",
  "properties": {
    "addr:full":"Standerdmolen 71 Papendrecht Zuid-Holland 3352 CJ",
    "addr:housenumber":"71",
    "addr:postcode":"3352 cj",
    "addr:street":"Standerdmolen",
    "iso:country":"NL",
    "sg:address":"Standerdmolen 71",
    "sg:city":"Papendrecht",
    "sg:orig_category":"Psychologen",
    "sg:phone":"+31 78 641 2312",
    "sg:postcode":"3352 CJ",
    "sg:province":"Zuid-Holland",
    "wof:name":"Inzicht Pedagogisch Adviesbureau",
    "wof:placetype":"venue"
},
  "geometry": {"coordinates":[4.692847,51.841934],"type":"Point"}
}