{
  "type": "Feature",
  "properties": {
    "iso:country":"NL",
    "sg:address":"Rige 1",
    "sg:city":"Abbega",
    "sg:classifiers":[
        {
            "category":"Travel",
            "subcategory":"Hotels & Motels",
            "type":"Entertainment"
        }
    ],
    "sg:phone":"+31 515 569 683",
    "sg:postcode":"8617 LA",
    "sg:province":"Friesland",
    "wof:name":"Cnossen",
    "wof:placetype":"venue"
},
  "geometry": {"coordinates":[5.57456,53.027866],"type":"Point"}
}