{
  "type": "Feature",
  "properties": {
    "addr:full":"Kl Broekstr 55 Bergeyk North Brabant 5571 KE",
    "addr:housenumber":"55",
    "addr:postcode":"5571 ke",
    "addr:street":"Bergeyk North",
    "iso:country":"NL",
    "sg:address":"Kl Broekstr 55",
    "sg:city":"Bergeyk",
    "sg:orig_category":"Plafonds",
    "sg:phone":"+31 497 577 290",
    "sg:postcode":"5571 KE",
    "sg:province":"North Brabant",
    "wof:name":"Leeuwen, M Van",
    "wof:placetype":"venue"
},
  "geometry": {"coordinates":[5.360135,51.323326],"type":"Point"}
}