{
  "type": "Feature",
  "properties": {
    "addr:full":"Steynstr 12 Arnhem Gelderland 6814 AM",
    "addr:housenumber":"12",
    "addr:postcode":"6814",
    "addr:street":"Steynstr",
    "iso:country":"NL",
    "sg:address":"Steynstr 12",
    "sg:city":"Arnhem",
    "sg:orig_category":"Verenigingen En Stichtingen",
    "sg:phone":"+31 26 351 9029",
    "sg:postcode":"6814 AM",
    "sg:province":"Gelderland",
    "wof:name":"Kunst En Cult Gelderland, Sticht",
    "wof:placetype":"venue"
},
  "geometry": {"coordinates":[5.907636,51.986206],"type":"Point"}
}