{
  "type": "Feature",
  "properties": {
    "addr:full":"Westeinde 19 Waalwijk North Brabant 5141 AA",
    "addr:housenumber":"19",
    "addr:postcode":"5141 aa",
    "addr:street":"Westeinde",
    "iso:country":"NL",
    "sg:address":"Westeinde 19",
    "sg:city":"Waalwijk",
    "sg:orig_category":"Pleziervaartuigen And Reparatie",
    "sg:phone":"+31 416 335 635",
    "sg:postcode":"5141 AA",
    "sg:province":"North Brabant",
    "wof:name":"Verhoeven Jachtbouw Vof",
    "wof:placetype":"venue"
},
  "geometry": {"coordinates":[5.048161,51.688442],"type":"Point"}
}