{
  "type": "Feature",
  "properties": {
    "addr:full":"Leksmondhof 252 Amsterdam Zuidoost Noord-Holland 1108 EZ",
    "addr:housenumber":"252",
    "addr:postcode":"zuidoost;1108 ez",
    "addr:street":"Leksmondhof",
    "iso:country":"NL",
    "sg:address":"Leksmondhof 252",
    "sg:city":"Amsterdam Zuidoost",
    "sg:orig_category":"Public Relationbureaus",
    "sg:phone":"+31 20 697 6299",
    "sg:postcode":"1108 EZ",
    "sg:province":"Noord-Holland",
    "wof:name":"H.G. Andriese",
    "wof:placetype":"venue"
},
  "geometry": {"coordinates":[4.981162,52.309509],"type":"Point"}
}