{
  "type": "Feature",
  "properties": {
    "addr:full":"Postbus 8 Spanbroek Noord-Holland 1715 ZG",
    "addr:housenumber":"8",
    "addr:postcode":"1715 zg",
    "addr:street":"Postbus",
    "iso:country":"NL",
    "sg:address":"Postbus 8",
    "sg:city":"Spanbroek",
    "sg:orig_category":"Schilders",
    "sg:phone":"+31 226 359 667",
    "sg:postcode":"1715 ZG",
    "sg:province":"Noord-Holland",
    "wof:name":"Mechelen, Van",
    "wof:placetype":"venue"
},
  "geometry": {"coordinates":[4.945522,52.697983],"type":"Point"}
}