{
  "type": "Feature",
  "properties": {
    "addr:full":"Emmastr 35 Rozenburg Zh Zuid-Holland 3181 GC",
    "addr:housenumber":"35",
    "addr:postcode":"zh;3181 gc",
    "addr:street":"Emmastr",
    "iso:country":"NL",
    "sg:address":"Emmastr 35",
    "sg:city":"Rozenburg Zh",
    "sg:orig_category":"Kappers",
    "sg:phone":"+31 181 212 459",
    "sg:postcode":"3181 GC",
    "sg:province":"Zuid-Holland",
    "wof:name":"Wezemer",
    "wof:placetype":"venue"
},
  "geometry": {"coordinates":[4.244045,51.905842],"type":"Point"}
}