{
  "type": "Feature",
  "properties": {
    "addr:full":"Soestdijkerstraatw 54 Hilversum Noord-Holland 1213 XD",
    "addr:housenumber":"54",
    "addr:postcode":"1213 xd",
    "addr:street":"Soestdijkerstraatw",
    "iso:country":"NL",
    "sg:address":"Soestdijkerstraatw 54",
    "sg:city":"Hilversum",
    "sg:orig_category":"Zuivel - Groothandel",
    "sg:phone":"+31 35 685 9397",
    "sg:postcode":"1213 XD",
    "sg:province":"Noord-Holland",
    "wof:name":"Oosterom, W Van",
    "wof:placetype":"venue"
},
  "geometry": {"coordinates":[5.1695,52.228565],"type":"Point"}
}