{
  "type": "Feature",
  "properties": {
    "iso:country":"NL",
    "sg:address":"Nieuwehuizen 10",
    "sg:city":"Assen",
    "sg:orig_category":"Warenhuizen",
    "sg:phone":"+31 900 9800",
    "sg:postcode":"9401 JT",
    "sg:province":"Drenthe",
    "wof:name":"Kijkshop",
    "wof:placetype":"venue"
},
  "geometry": {"coordinates":[6.5638341904,52.9956474304],"type":"Point"}
}