{
  "type": "Feature",
  "properties": {
    "iso:country":"NL",
    "sg:address":"Haaksbergsewg 144A",
    "sg:city":"Neede",
    "sg:orig_category":"Wormenkwekerijen",
    "sg:phone":"+31 545 221 795",
    "sg:postcode":"7161 BN",
    "sg:province":"Gelderland",
    "sg:website":"http://www.dewormenhoek.tip.nl",
    "wof:name":"Wormenhoek, De",
    "wof:placetype":"venue"
},
  "geometry": {"coordinates":[-121.3170623779,38.2996330261],"type":"Point"}
}