{
  "type": "Feature",
  "properties": {
    "addr:full":"G Terborchstr 39 Almere NL. 1318 LE",
    "addr:housenumber":"39",
    "addr:postcode":"1318 le",
    "addr:street":"Nl.",
    "iso:country":"NL",
    "sg:address":"G Terborchstr 39",
    "sg:city":"Almere",
    "sg:orig_category":"Geschenkartikelen",
    "sg:phone":"+31 36 523 2645",
    "sg:postcode":"1318 LE",
    "sg:province":"NL.",
    "wof:name":"Irma",
    "wof:placetype":"venue"
},
  "geometry": {"coordinates":[5.253123,52.38084],"type":"Point"}
}