{
  "type": "Feature",
  "properties": {
    "addr:full":"Churchillweg 92 Wageningen Gelderland 6706 AD",
    "addr:housenumber":"92",
    "addr:postcode":"6706 ad",
    "addr:street":"Churchillweg;Gelderland",
    "iso:country":"NL",
    "sg:address":"Churchillweg 92",
    "sg:city":"Wageningen",
    "sg:orig_category":"Warenhuizen",
    "sg:phone":"+31 317 412 182",
    "sg:postcode":"6706 AD",
    "sg:province":"Gelderland",
    "wof:name":"De Gelderse Ijzerhandel",
    "wof:placetype":"venue"
},
  "geometry": {"coordinates":[5.6726379395,51.9738845825],"type":"Point"}
}