{
  "type": "Feature",
  "properties": {
    "addr:full":"Kapelstraat 10 Prinsenbeek Noord-Brabant 4841 GH",
    "addr:housenumber":"10",
    "addr:postcode":"4841 gh",
    "addr:street":"Kapelstraat",
    "iso:country":"NL",
    "sg:address":"Kapelstraat 10",
    "sg:city":"Prinsenbeek",
    "sg:orig_category":"Damesmodezaken",
    "sg:phone":"+31 76 541 2860",
    "sg:postcode":"4841 GH",
    "sg:province":"Noord-Brabant",
    "wof:name":"Nouwens",
    "wof:placetype":"venue"
},
  "geometry": {"coordinates":[4.717626,51.601303],"type":"Point"}
}