{
  "type": "Feature",
  "properties": {
    "addr:full":"Karperveen 163 Spykenisse Zuid-Holland 3205 HA",
    "addr:housenumber":"163",
    "addr:postcode":"3205 ha",
    "addr:street":"Karperveen",
    "iso:country":"NL",
    "sg:address":"Karperveen 163",
    "sg:city":"Spykenisse",
    "sg:orig_category":"Zeilmakerijen",
    "sg:phone":"+31 6 10720443",
    "sg:postcode":"3205 HA",
    "sg:province":"Zuid-Holland",
    "wof:name":"Bax Deco",
    "wof:placetype":"venue"
},
  "geometry": {"coordinates":[4.346045,51.832413],"type":"Point"}
}