{
  "type": "Feature",
  "properties": {
    "addr:full":"Meerzijde 23 Volendam Noord-Holland 1131 ZZ",
    "addr:housenumber":"23",
    "addr:postcode":"1131 zz",
    "addr:street":"Meerzijde",
    "iso:country":"NL",
    "sg:address":"Meerzijde 23",
    "sg:city":"Volendam",
    "sg:classifiers":[
        {
            "category":"Fast Food",
            "type":"Food & Drink"
        }
    ],
    "sg:phone":"+31 299 351 306",
    "sg:postcode":"1131 ZZ",
    "sg:province":"Noord-Holland",
    "sg:tags":[
        "afhaal",
        "restaurant"
    ],
    "wof:name":"Chinees Restaurant Golden Gong",
    "wof:placetype":"venue"
},
  "geometry": {"coordinates":[5.075773,52.494602],"type":"Point"}
}