{
  "type": "Feature",
  "properties": {
    "iso:country":"NL",
    "sg:address":"Weteringschans 26/3",
    "sg:city":"Amsterdam",
    "sg:orig_category":"Luchtvaart",
    "sg:phone":"+31 20 627 0561",
    "sg:postcode":"1017 SG",
    "sg:province":"Noord-Holland",
    "wof:name":"Russian International Airlines Aeroflot",
    "wof:placetype":"venue"
},
  "geometry": {"coordinates":[4.886951,52.360851],"type":"Point"}
}