{
  "type": "Feature",
  "properties": {
    "addr:full":"L Nering 33A Emmeloord NL. 8302 EA",
    "addr:housenumber":"33a",
    "addr:postcode":"8302 ea",
    "addr:street":"Nering;Nl.",
    "iso:country":"NL",
    "sg:address":"L Nering 33A",
    "sg:city":"Emmeloord",
    "sg:orig_category":"Wijnkoperijen En -Groothandel",
    "sg:phone":"+31 527 622 923",
    "sg:postcode":"8302 EA",
    "sg:province":"NL.",
    "wof:name":"Vetter, Paul",
    "wof:placetype":"venue"
},
  "geometry": {"coordinates":[5.7557559013,52.7114524841],"type":"Point"}
}