{
  "type": "Feature",
  "properties": {
    "iso:country":"NL",
    "sg:address":"Strevelswg 696",
    "sg:city":"Rotterdam",
    "sg:orig_category":"Verzekeringen - Verzekeringskantoren",
    "sg:phone":"+31 10 481 7766",
    "sg:postcode":"3083 AR",
    "sg:province":"Zuid-Holland",
    "sg:website":"http://www.theeuwkens.nl",
    "wof:name":"Theeuwkens & Znn Bv, H A C",
    "wof:placetype":"venue"
},
  "geometry": {"coordinates":[-73.97154999999999,42.786839],"type":"Point"}
}