{
  "type": "Feature",
  "properties": {
    "addr:full":"Groenmarkt 11 Meppel Provincie Drenthe 7941 KT",
    "addr:housenumber":"11",
    "addr:postcode":"7941 kt",
    "addr:street":"Groenmarkt;Provincie Drenthe",
    "iso:country":"NL",
    "sg:address":"Groenmarkt 11",
    "sg:city":"Meppel",
    "sg:orig_category":"Verlichting And Huishoudartikelen",
    "sg:phone":"+31 522 251 691",
    "sg:postcode":"7941 KT",
    "sg:province":"Provincie Drenthe",
    "wof:name":"Tapilux",
    "wof:placetype":"venue"
},
  "geometry": {"coordinates":[6.191025,52.696922],"type":"Point"}
}