{
  "type": "Feature",
  "properties": {
    "iso:country":"NL",
    "sg:address":"Groenmarkt 11",
    "sg:city":"Meppel",
    "sg:orig_category":"Verlichting And Huishoudartikelen",
    "sg:phone":"+31 522 251 691",
    "sg:postcode":"7941 KT",
    "sg:province":"Provincie Drenthe",
    "wof:name":"Tapilux",
    "wof:placetype":"venue"
},
  "geometry": {"coordinates":[6.191025,52.696922],"type":"Point"}
}