{
  "type": "Feature",
  "properties": {
    "addr:full":"De Tichelarij 21 Venlo Limburg 5913 GR",
    "addr:housenumber":"21",
    "addr:postcode":"5913",
    "addr:street":"De Tichelarij",
    "iso:country":"NL",
    "sg:address":"De Tichelarij 21",
    "sg:city":"Venlo",
    "sg:orig_category":"Verzekeringen",
    "sg:phone":"+31 77 351 3098",
    "sg:postcode":"5913 GR",
    "sg:province":"Limburg",
    "wof:name":"Vic Seuren Bv",
    "wof:placetype":"venue"
},
  "geometry": {"coordinates":[6.187081,51.374886],"type":"Point"}
}