{
  "type": "Feature",
  "properties": {
    "addr:full":"Raadhuisplein 1 Wognum Noord-Holland 1687 NG",
    "addr:housenumber":"1",
    "addr:postcode":"1687 ng",
    "addr:street":"Raadhuisplein",
    "iso:country":"NL",
    "sg:address":"Raadhuisplein 1",
    "sg:city":"Wognum",
    "sg:orig_category":"Overheidsdiensten",
    "sg:phone":"+31 229 571 020",
    "sg:postcode":"1687 NG",
    "sg:province":"Noord-Holland",
    "wof:name":"Gemeente Wognum",
    "wof:placetype":"venue"
},
  "geometry": {"coordinates":[5.0276141167,52.680431366],"type":"Point"}
}