{
  "type": "Feature",
  "properties": {
    "addr:full":"Kleverlaan 9 Haarlem Noord-Holland 2023 JC",
    "addr:housenumber":"9",
    "addr:postcode":"2023 jc",
    "addr:street":"Kleverlaan",
    "iso:country":"NL",
    "sg:address":"Kleverlaan 9",
    "sg:city":"Haarlem",
    "sg:orig_category":"Begrafenisondernemers",
    "sg:phone":"+31 23 511 4815",
    "sg:postcode":"2023 JC",
    "sg:province":"Noord-Holland",
    "wof:name":"Begraafplaatsen",
    "wof:placetype":"venue"
},
  "geometry": {"coordinates":[4.635158,52.395416],"type":"Point"}
}