{
  "type": "Feature",
  "properties": {
    "addr:full":"Breedelaan 1 Heiloo North Holland 1851 MA",
    "addr:housenumber":"1",
    "addr:postcode":"1851 ma",
    "addr:street":"Breedelaan",
    "iso:country":"NL",
    "sg:address":"Breedelaan 1",
    "sg:city":"Heiloo",
    "sg:orig_category":"Elektronische Bedrijfsinstallaties",
    "sg:phone":"+31 72 533 0553",
    "sg:postcode":"1851 MA",
    "sg:province":"North Holland",
    "wof:name":"R.J.W. Levie",
    "wof:placetype":"venue"
},
  "geometry": {"coordinates":[4.709465,52.601303],"type":"Point"}
}