{
  "type": "Feature",
  "properties": {
    "addr:full":"Postbus 1234 Papendrecht South Holland 3350 CE",
    "addr:housenumber":"1234",
    "addr:postcode":"3350 ce",
    "addr:street":"Postbus",
    "iso:country":"NL",
    "sg:address":"Postbus 1234",
    "sg:city":"Papendrecht",
    "sg:orig_category":"Kunststoffen - Fabrieken En Groothandel",
    "sg:phone":"+31 78 641 4200",
    "sg:postcode":"3350 CE",
    "sg:province":"South Holland",
    "wof:name":"J & G",
    "wof:placetype":"venue"
},
  "geometry": {"coordinates":[4.683685,51.826294],"type":"Point"}
}