{
  "type": "Feature",
  "properties": {
    "addr:full":"Gladiolenln 9 Beverwyk North Holland 1944 KT",
    "addr:housenumber":"9",
    "addr:postcode":"1944 kt",
    "addr:street":"Gladiolenln;North",
    "iso:country":"NL",
    "sg:address":"Gladiolenln 9",
    "sg:city":"Beverwyk",
    "sg:orig_category":"Keukenspeciaalzaken",
    "sg:phone":"+31 6 51102473",
    "sg:postcode":"1944 KT",
    "sg:province":"North Holland",
    "wof:name":"Trieling Bv",
    "wof:placetype":"venue"
},
  "geometry": {"coordinates":[4.649539,52.493141],"type":"Point"}
}