{
  "type": "Feature",
  "properties": {
    "addr:full":"Oude Zeewg 40 Noordwyk Zh Zuid-Holland 2202 CG",
    "addr:housenumber":"40",
    "addr:postcode":"2202 cg",
    "addr:street":"Oude Zeewg",
    "iso:country":"NL",
    "sg:address":"Oude Zeewg 40",
    "sg:city":"Noordwyk Zh",
    "sg:orig_category":"Beeldende Kunstenaars",
    "sg:phone":"+31 71 361 0417",
    "sg:postcode":"2202 CG",
    "sg:province":"Zuid-Holland",
    "wof:name":"Koopmans, Ine",
    "wof:placetype":"venue"
},
  "geometry": {"coordinates":[4.435614,52.248837],"type":"Point"}
}