{
  "type": "Feature",
  "properties": {
    "addr:full":"De Lairesseln 179 Rotterdam South Holland 3062 PH",
    "addr:housenumber":"179",
    "addr:postcode":"3062",
    "iso:country":"NL",
    "sg:address":"De Lairesseln 179",
    "sg:city":"Rotterdam",
    "sg:orig_category":"Homeopathie",
    "sg:phone":"+31 10 242 0579",
    "sg:postcode":"3062 PH",
    "sg:province":"South Holland",
    "wof:name":"Eisenberger",
    "wof:placetype":"venue"
},
  "geometry": {"coordinates":[4.526272,51.920586],"type":"Point"}
}