{
  "type": "Feature",
  "properties": {
    "iso:country":"NL",
    "sg:address":"Keizer Karelplein 8",
    "sg:city":"Maastricht",
    "sg:classifiers":[
        {
            "category":"Fast Food",
            "type":"Food & Drink"
        }
    ],
    "sg:phone":"+31 43 326 0477",
    "sg:postcode":"6211 TC",
    "sg:province":"Limburg",
    "sg:tags":[
        "afhaal",
        "restaurant"
    ],
    "wof:name":"Snackson'S I",
    "wof:placetype":"venue"
},
  "geometry": {"coordinates":[5.686232,50.849255],"type":"Point"}
}