{
  "type": "Feature",
  "properties": {
    "addr:full":"Willibrordusln 7-9 Waalre Noord-Brabant 5581 GA",
    "addr:housenumber":"7-9",
    "addr:postcode":"5581 ga",
    "addr:street":"Willibrordusln",
    "iso:country":"NL",
    "sg:address":"Willibrordusln 7-9",
    "sg:city":"Waalre",
    "sg:classifiers":[
        {
            "category":"Retail",
            "subcategory":"Auto Repair",
            "type":"Services"
        }
    ],
    "sg:phone":"+31 40 221 5811",
    "sg:postcode":"5581 GA",
    "sg:province":"Noord-Brabant",
    "sg:tags":[
        "garage"
    ],
    "sg:website":"http://www.dereumaux.nl",
    "wof:name":"Dereumaux Bv",
    "wof:placetype":"venue"
},
  "geometry": {"coordinates":[5.445226,51.386436],"type":"Point"}
}