{
  "type": "Feature",
  "properties": {
    "addr:full":"De Lairessestraat 90 Amsterdam Noord-Holland 1071 PJ",
    "addr:housenumber":"90",
    "addr:postcode":"1071 pj",
    "addr:street":"De Lairessestraat",
    "iso:country":"NL",
    "sg:address":"De Lairessestraat 90",
    "sg:city":"Amsterdam",
    "sg:classifiers":[
        {
            "category":"Professional",
            "subcategory":"Accounting & Tax Preparation",
            "type":"Services"
        }
    ],
    "sg:phone":"+31 20 673 5810",
    "sg:postcode":"1071 PJ",
    "sg:province":"Noord-Holland",
    "sg:tags":[
        "accountant"
    ],
    "wof:name":"Ritveld & Co Accountant",
    "wof:placetype":"venue"
},
  "geometry": {"coordinates":[4.872576,52.353958],"type":"Point"}
}