{
  "type": "Feature",
  "properties": {
    "iso:country":"NL",
    "sg:address":"Promenade 60C",
    "sg:city":"Heerlen",
    "sg:orig_category":"Fotozaken",
    "sg:phone":"+31 45 560 0021",
    "sg:postcode":"6411 JK",
    "sg:province":"Limburg",
    "wof:name":"Filmpost",
    "wof:placetype":"venue"
},
  "geometry": {"coordinates":[5.974467,50.886978],"type":"Point"}
}