{
  "type": "Feature",
  "properties": {
    "iso:country":"NL",
    "sg:address":"Maretakhof 7",
    "sg:city":"Roermond",
    "sg:orig_category":"Public Relationbureaus",
    "sg:phone":"+31 475 350 255",
    "sg:postcode":"6043 WX",
    "sg:province":"Limburg",
    "wof:name":"Ursem Communicatie",
    "wof:placetype":"venue"
},
  "geometry": {"coordinates":[6.017637,51.188271],"type":"Point"}
}