{
  "type": "Feature",
  "properties": {
    "addr:full":"Muyeveld 51 Vinkeveen Utrecht 3645 VJ",
    "addr:housenumber":"51",
    "addr:postcode":"3645 vj",
    "addr:street":"Muyeveld",
    "iso:country":"NL",
    "sg:address":"Muyeveld 51",
    "sg:city":"Vinkeveen",
    "sg:orig_category":"Fotoreportages",
    "sg:phone":"+31 297 562 022",
    "sg:postcode":"3645 VJ",
    "sg:province":"Utrecht",
    "wof:name":"Vision Quest",
    "wof:placetype":"venue"
},
  "geometry": {"coordinates":[4.923109,52.21085],"type":"Point"}
}