{
  "type": "Feature",
  "properties": {
    "addr:full":"Ooldseln 25 Laren Gld Gelderland 7245 PP",
    "addr:housenumber":"25",
    "addr:postcode":"7245 pp",
    "addr:street":"Ooldseln;Gld Gelderland",
    "iso:country":"NL",
    "sg:address":"Ooldseln 25",
    "sg:city":"Laren Gld",
    "sg:orig_category":"Voetverzorging",
    "sg:phone":"+31 573 400 595",
    "sg:postcode":"7245 PP",
    "sg:province":"Gelderland",
    "wof:name":"Mulder-Heuvelink, A J",
    "wof:placetype":"venue"
},
  "geometry": {"coordinates":[6.365639,52.19276],"type":"Point"}
}