{
  "type": "Feature",
  "properties": {
    "iso:country":"NL",
    "sg:address":"Javastraat 1",
    "sg:city":"'S Gravenhage",
    "sg:orig_category":"Banken And Kredietinstellingen",
    "sg:phone":"+31 70 356 6300",
    "sg:postcode":"2585 AA",
    "sg:province":"Zuid-Holland",
    "wof:name":"Abn Amro",
    "wof:placetype":"venue"
},
  "geometry": {"coordinates":[4.303662,52.087795],"type":"Point"}
}