{
  "type": "Feature",
  "properties": {
    "addr:full":"Zaarbelinkdijk 11 Keijenborg Gelderland 7256 KL",
    "addr:housenumber":"11",
    "addr:postcode":"7256 kl",
    "addr:street":"Zaarbelinkdijk;Gelderland",
    "iso:country":"NL",
    "sg:address":"Zaarbelinkdijk 11",
    "sg:city":"Keijenborg",
    "sg:orig_category":"Makelaars In Onroerend Goed",
    "sg:phone":"+31 575 461 779",
    "sg:postcode":"7256 KL",
    "sg:province":"Gelderland",
    "wof:name":"Makelaardij O.G. Wentink",
    "wof:placetype":"venue"
},
  "geometry": {"coordinates":[6.296932,52.038216],"type":"Point"}
}