{
  "type": "Feature",
  "properties": {
    "addr:full":"Burg Bletzstr 1D Amsterdam Zuidoost Noord-Holland 1109 AJ",
    "addr:housenumber":"1d",
    "addr:postcode":"1109 aj",
    "addr:street":"Burg",
    "iso:country":"NL",
    "sg:address":"Burg Bletzstr 1D",
    "sg:city":"Amsterdam Zuidoost",
    "sg:orig_category":"Artiesten/Gezelschappen",
    "sg:phone":"+31 294 252 921",
    "sg:postcode":"1109 AJ",
    "sg:province":"Noord-Holland",
    "sg:website":"http://www.rolenco.nl",
    "wof:name":"Rol & Co",
    "wof:placetype":"venue"
},
  "geometry": {"coordinates":[5.015949,52.304382],"type":"Point"}
}