{
  "type": "Feature",
  "properties": {
    "addr:full":"Honingstr 14B Hilversum Noord-Holland 1211 AW",
    "addr:housenumber":"14b",
    "addr:postcode":"1211 aw",
    "addr:street":"Honingstr",
    "iso:country":"NL",
    "sg:address":"Honingstr 14B",
    "sg:city":"Hilversum",
    "sg:orig_category":"Video - Faciliteiten En Producties",
    "sg:phone":"+31 35 628 5776",
    "sg:postcode":"1211 AW",
    "sg:province":"Noord-Holland",
    "sg:website":"http://www.beeldlijn.nl",
    "wof:name":"Beeldlijn Post-Production",
    "wof:placetype":"venue"
},
  "geometry": {"coordinates":[5.177289,52.228939],"type":"Point"}
}