{
  "type": "Feature",
  "properties": {
    "addr:full":"Gewandhuis 4 Boekel Noord-Brabant 5427 PW",
    "addr:housenumber":"4",
    "addr:postcode":"5427 pw",
    "addr:street":"Gewandhuis",
    "iso:country":"NL",
    "sg:address":"Gewandhuis 4",
    "sg:city":"Boekel",
    "sg:orig_category":"Drukkerijen",
    "sg:phone":"+31 492 326 026",
    "sg:postcode":"5427 PW",
    "sg:province":"Noord-Brabant",
    "wof:name":"Druk Service Boekel",
    "wof:placetype":"venue"
},
  "geometry": {"coordinates":[5.672121,51.615784],"type":"Point"}
}