{
  "type": "Feature",
  "properties": {
    "addr:full":"Dorpsstraat 559 Noord-Scharwoude North Holland 1723 HA",
    "addr:housenumber":"559",
    "addr:postcode":"1723 ha",
    "addr:street":"Dorpsstraat",
    "iso:country":"NL",
    "sg:address":"Dorpsstraat 559",
    "sg:city":"Noord-Scharwoude",
    "sg:orig_category":"Kansspelen",
    "sg:phone":"+31 226 318 725",
    "sg:postcode":"1723 HA",
    "sg:province":"North Holland",
    "wof:name":"Amusementshal Noord Scharwoude",
    "wof:placetype":"venue"
},
  "geometry": {"coordinates":[4.8105192184,52.7001419067],"type":"Point"}
}