{
  "type": "Feature",
  "properties": {
    "addr:full":"Vlinderveen 445 Spijkenisse Zuid-Holland 3205 EE",
    "addr:housenumber":"445",
    "addr:postcode":"3205 ee",
    "addr:street":"Vlinderveen",
    "iso:country":"NL",
    "sg:address":"Vlinderveen 445",
    "sg:city":"Spijkenisse",
    "sg:classifiers":[
        {
            "category":"Bakery",
            "type":"Food & Drink"
        }
    ],
    "sg:phone":"+31 181 640 409",
    "sg:postcode":"3205 EE",
    "sg:province":"Zuid-Holland",
    "sg:tags":[
        "brood",
        "banket"
    ],
    "wof:name":"Echte Bakker Voskamp",
    "wof:placetype":"venue"
},
  "geometry": {"coordinates":[4.343057,51.833141],"type":"Point"}
}