{
  "type": "Feature",
  "properties": {
    "addr:full":"Stationsstraat 17 Oisterwijk Noord-Brabant 5061 HE",
    "addr:housenumber":"17",
    "addr:postcode":"5061 he",
    "addr:street":"Stationsstraat",
    "iso:country":"NL",
    "sg:address":"Stationsstraat 17",
    "sg:city":"Oisterwijk",
    "sg:orig_category":"Herenmodezaken",
    "sg:phone":"+31 13 528 8807",
    "sg:postcode":"5061 HE",
    "sg:province":"Noord-Brabant",
    "wof:name":"Nicolai Van Hout Mannenmode Bv",
    "wof:placetype":"venue"
},
  "geometry": {"coordinates":[5.193631,51.581669],"type":"Point"}
}