{
  "type": "Feature",
  "properties": {
    "addr:full":"Patrijs 33 Deurne North Brabant 5754 DJ",
    "addr:housenumber":"33",
    "addr:postcode":"5754 dj",
    "addr:street":"Patrijs",
    "iso:country":"NL",
    "sg:address":"Patrijs 33",
    "sg:city":"Deurne",
    "sg:classifiers":[
        {
            "category":"Education",
            "subcategory":"Preschool",
            "type":"Public Place"
        }
    ],
    "sg:phone":"+31 493 311 018",
    "sg:postcode":"5754 DJ",
    "sg:province":"North Brabant",
    "sg:tags":[
        "kleuteronderwijs",
        "basis-"
    ],
    "wof:name":"Basisschool D'N Heiakker",
    "wof:placetype":"venue"
},
  "geometry": {"coordinates":[5.807878,51.465366],"type":"Point"}
}