{
  "type": "Feature",
  "properties": {
    "addr:full":"Tolstraat 94 Amsterdam North Holland 1073 SE",
    "addr:housenumber":"94",
    "addr:postcode":"1073 se",
    "addr:street":"Tolstraat",
    "iso:country":"NL",
    "sg:address":"Tolstraat 94",
    "sg:city":"Amsterdam",
    "sg:orig_category":"Fotostudio'S And Fotografen",
    "sg:phone":"+31 20 671 8510",
    "sg:postcode":"1073 SE",
    "sg:province":"North Holland",
    "wof:name":"Foto Studio M.S. Oort Bv",
    "wof:placetype":"venue"
},
  "geometry": {"coordinates":[4.90254,52.351955],"type":"Point"}
}