{
  "type": "Feature",
  "properties": {
    "addr:full":"Oosterblokker 172 Oosterblokker North Holland 1696 BM",
    "addr:housenumber":"172",
    "addr:postcode":"1696 bm",
    "addr:street":"Oosterblokker",
    "iso:country":"NL",
    "sg:address":"Oosterblokker 172",
    "sg:city":"Oosterblokker",
    "sg:orig_category":"Hefwerktuigen",
    "sg:phone":"+31 226 410 411",
    "sg:postcode":"1696 BM",
    "sg:province":"North Holland",
    "sg:website":"http://www.schaarheftafels.nl",
    "wof:name":"Hxs",
    "wof:placetype":"venue"
},
  "geometry": {"coordinates":[5.131266,52.674892],"type":"Point"}
}