{
  "type": "Feature",
  "properties": {
    "addr:full":"Venenweg 12 Zwanenburg Noord-Holland 1161 AK",
    "addr:housenumber":"12",
    "addr:postcode":"1161 ak",
    "addr:street":"Venenweg",
    "iso:country":"NL",
    "sg:address":"Venenweg 12",
    "sg:city":"Zwanenburg",
    "sg:orig_category":"Wasserettes And Stomerijen",
    "sg:phone":"+31 20 497 6987",
    "sg:postcode":"1161 AK",
    "sg:province":"Noord-Holland",
    "wof:name":"Ksw Reinette Bv",
    "wof:placetype":"venue"
},
  "geometry": {"coordinates":[4.7373290062,52.3810920715],"type":"Point"}
}