{
  "type": "Feature",
  "properties": {
    "addr:full":"Oostdk 28 Oud Beyerland South Holland 3261 KH",
    "addr:housenumber":"28",
    "addr:postcode":"3261 kh",
    "addr:street":"Oostdk;Oud Beyerland",
    "iso:country":"NL",
    "sg:address":"Oostdk 28",
    "sg:city":"Oud Beyerland",
    "sg:orig_category":"Schoenen - Reparaties",
    "sg:phone":"+31 186 617 516",
    "sg:postcode":"3261 KH",
    "sg:province":"South Holland",
    "sg:website":"http://www.franshermsen.nl",
    "wof:name":"Hermsen, Frans",
    "wof:placetype":"venue"
},
  "geometry": {"coordinates":[4.413818,51.826206],"type":"Point"}
}