{
  "type": "Feature",
  "properties": {
    "addr:full":"Gen De Wetstr 18 Haarlem Noord-Holland 2021 XH",
    "addr:housenumber":"18",
    "addr:postcode":"2021 xh",
    "addr:street":"Gen",
    "iso:country":"NL",
    "sg:address":"Gen De Wetstr 18",
    "sg:city":"Haarlem",
    "sg:orig_category":"Autorijscholen",
    "sg:phone":"+31 6 55152116",
    "sg:postcode":"2021 XH",
    "sg:province":"Noord-Holland",
    "wof:name":"Nurten",
    "wof:placetype":"venue"
},
  "geometry": {"coordinates":[4.641625,52.392239],"type":"Point"}
}