{
  "type": "Feature",
  "properties": {
    "addr:full":"Heyhoefpromenade 105 Tilburg North Brabant 5043 RB",
    "addr:housenumber":"105",
    "addr:postcode":"5043 rb",
    "addr:street":"Heyhoefpromenade",
    "iso:country":"NL",
    "sg:address":"Heyhoefpromenade 105",
    "sg:city":"Tilburg",
    "sg:orig_category":"Postkantoren",
    "sg:phone":"+31 13 571 3239",
    "sg:postcode":"5043 RB",
    "sg:province":"North Brabant",
    "sg:website":"http://www.postkantoor.nl",
    "wof:name":"Postkantoor",
    "wof:placetype":"venue"
},
  "geometry": {"coordinates":[5.005886,51.577938],"type":"Point"}
}