{
  "type": "Feature",
  "properties": {
    "addr:full":"Fuchsiastr 134 S Gravenhage Zuid-Holland 2565 PW",
    "addr:housenumber":"134;gravenhage",
    "addr:postcode":"2565 pw",
    "addr:street":"S",
    "iso:country":"NL",
    "sg:address":"Fuchsiastr 134",
    "sg:city":"S Gravenhage",
    "sg:orig_category":"Wasserijen",
    "sg:phone":"+31 70 368 7878",
    "sg:postcode":"2565 PW",
    "sg:province":"Zuid-Holland",
    "wof:name":"Tettero",
    "wof:placetype":"venue"
},
  "geometry": {"coordinates":[4.2612900734,52.0763816833],"type":"Point"}
}