{
  "type": "Feature",
  "properties": {
    "iso:country":"NL",
    "sg:address":"Zuideinde 80",
    "sg:city":"Oostzaan",
    "sg:orig_category":"Logopedisten",
    "sg:phone":"+31 75 684 1998",
    "sg:postcode":"1511 GH",
    "sg:province":"North Holland",
    "wof:name":"Logopediepraktijk Oostzaan",
    "wof:placetype":"venue"
},
  "geometry": {"coordinates":[4.878218,52.435184],"type":"Point"}
}