{
  "type": "Feature",
  "properties": {
    "addr:full":"Jislumerdk 15 Burdaard Friesland 9111 HC",
    "addr:housenumber":"15",
    "addr:postcode":"9111 hc",
    "addr:street":"Jislumerdk",
    "iso:country":"NL",
    "sg:address":"Jislumerdk 15",
    "sg:city":"Burdaard",
    "sg:orig_category":"Kunststof Ramen",
    "sg:phone":"+31 519 332 553",
    "sg:postcode":"9111 HC",
    "sg:province":"Friesland",
    "wof:name":"Reniko Ned Bv",
    "wof:placetype":"venue"
},
  "geometry": {"coordinates":[5.877561,53.29731],"type":"Point"}
}