{
  "type": "Feature",
  "properties": {
    "addr:full":"Kronenburgpassage 48 Arnhem Gelderland 6831 ER",
    "addr:housenumber":"48",
    "addr:postcode":"6831 er",
    "addr:street":"Kronenburgpassage",
    "iso:country":"NL",
    "sg:address":"Kronenburgpassage 48",
    "sg:city":"Arnhem",
    "sg:orig_category":"Herenmodezaken",
    "sg:phone":"+31 26 323 6242",
    "sg:postcode":"6831 ER",
    "sg:province":"Gelderland",
    "wof:name":"Amici Mannenmode",
    "wof:placetype":"venue"
},
  "geometry": {"coordinates":[5.897874,51.958431],"type":"Point"}
}