{
  "type": "Feature",
  "properties": {
    "addr:full":"Luitertwg 36A Zundert North Brabant 4882 TD",
    "addr:housenumber":"36a",
    "addr:postcode":"4882 td",
    "addr:street":"Luitertwg",
    "iso:country":"NL",
    "sg:address":"Luitertwg 36A",
    "sg:city":"Zundert",
    "sg:orig_category":"Optische Instrumenten",
    "sg:phone":"+31 76 597 4165",
    "sg:postcode":"4882 TD",
    "sg:province":"North Brabant",
    "wof:name":"Akster, De",
    "wof:placetype":"venue"
},
  "geometry": {"coordinates":[4.658449173,51.488483429],"type":"Point"}
}