{
  "type": "Feature",
  "properties": {
    "addr:full":"Grote Kromme Elleboog 15 Groningen Groningen 9712 BJ",
    "addr:housenumber":"15",
    "addr:postcode":"9712 bj",
    "addr:street":"Grote Kromme Elleboog",
    "iso:country":"NL",
    "sg:address":"Grote Kromme Elleboog 15",
    "sg:city":"Groningen",
    "sg:orig_category":"Diverse Grafische Activiteiten",
    "sg:phone":"+31 50 311 1391",
    "sg:postcode":"9712 BJ",
    "sg:province":"Groningen",
    "wof:name":"Annette V Kelckhoven, Grafische Vormgevin",
    "wof:placetype":"venue"
},
  "geometry": {"coordinates":[6.562114,53.218273],"type":"Point"}
}