{
  "type": "Feature",
  "properties": {
    "iso:country":"NL",
    "sg:address":"Kabof 115",
    "sg:city":"Hoogland",
    "sg:orig_category":"Verenigingen En Stichtingen",
    "sg:phone":"+31 33 480 3705",
    "sg:postcode":"3828 JD",
    "sg:province":"Utrecht",
    "wof:name":"Drentse Ver",
    "wof:placetype":"venue"
},
  "geometry": {"coordinates":[5.369384,52.187557],"type":"Point"}
}