{
  "type": "Feature",
  "properties": {
    "addr:full":"Hoogstr 29 Leerdam Zuid-Holland 4141 BA",
    "addr:housenumber":"29",
    "addr:postcode":"4141 ba",
    "addr:street":"Hoogstr",
    "iso:country":"NL",
    "sg:address":"Hoogstr 29",
    "sg:city":"Leerdam",
    "sg:orig_category":"Woninginrichting",
    "sg:phone":"+31 345 631 166",
    "sg:postcode":"4141 BA",
    "sg:province":"Zuid-Holland",
    "wof:name":"Jansen & Van Zanten",
    "wof:placetype":"venue"
},
  "geometry": {"coordinates":[5.0944700241,51.8904533386],"type":"Point"}
}