{
  "type": "Feature",
  "properties": {
    "addr:full":"Geerwg 32 Nootdorp Zuid-Holland 2631 PD",
    "addr:housenumber":"32",
    "addr:postcode":"2631 pd",
    "addr:street":"Geerwg",
    "iso:country":"NL",
    "sg:address":"Geerwg 32",
    "sg:city":"Nootdorp",
    "sg:orig_category":"Administratie- En Boekhoudkantoren",
    "sg:phone":"+31 15 310 0892",
    "sg:postcode":"2631 PD",
    "sg:province":"Zuid-Holland",
    "wof:name":"Jomino",
    "wof:placetype":"venue"
},
  "geometry": {"coordinates":[4.409335,52.039726],"type":"Point"}
}