{
  "type": "Feature",
  "properties": {
    "addr:full":"Utrechtseweg 351 De Bilt Utrecht 3731 GB",
    "addr:housenumber":"351",
    "addr:postcode":"3731 gb",
    "addr:street":"Utrechtseweg",
    "iso:country":"NL",
    "sg:address":"Utrechtseweg 351",
    "sg:city":"De Bilt",
    "sg:orig_category":"Metaalafval, Schrootrecycling And Sloperijen",
    "sg:phone":"+31 30 220 2308",
    "sg:postcode":"3731 GB",
    "sg:province":"Utrecht",
    "wof:name":"Autodemontagebedrijf Akkie Stomphorst Bv",
    "wof:placetype":"venue"
},
  "geometry": {"coordinates":[5.163073,52.099613],"type":"Point"}
}