{
  "type": "Feature",
  "properties": {
    "addr:full":"Mijdrechtstraat 14 Utrecht Utrecht 3522 HW",
    "addr:housenumber":"14",
    "addr:postcode":"3522 hw",
    "addr:street":"Mijdrechtstraat",
    "iso:country":"NL",
    "sg:address":"Mijdrechtstraat 14",
    "sg:city":"Utrecht",
    "sg:orig_category":"Fotostudio'S And Fotografen",
    "sg:phone":"+31 30 288 1496",
    "sg:postcode":"3522 HW",
    "sg:province":"Utrecht",
    "wof:name":"Carool Van Der Hagen",
    "wof:placetype":"venue"
},
  "geometry": {"coordinates":[5.118385,52.075062],"type":"Point"}
}