{
  "type": "Feature",
  "properties": {
    "addr:full":"Meerstr 8 Almere Flevoland 1353 AX",
    "addr:housenumber":"8",
    "addr:postcode":"1353 ax",
    "addr:street":"Meerstr;Flevoland",
    "iso:country":"NL",
    "sg:address":"Meerstr 8",
    "sg:city":"Almere",
    "sg:orig_category":"Cafetaria'S",
    "sg:phone":"+31 36 531 3355",
    "sg:postcode":"1353 AX",
    "sg:province":"Flevoland",
    "wof:name":"Happie Snack",
    "wof:placetype":"venue"
},
  "geometry": {"coordinates":[5.217929,52.334354],"type":"Point"}
}