{
  "type": "Feature",
  "properties": {
    "iso:country":"NL",
    "sg:address":"Antiloopstraat 45 A",
    "sg:city":"Breda",
    "sg:orig_category":"Glaszetten",
    "sg:phone":"+31 76 514 7970",
    "sg:postcode":"4817 LA",
    "sg:province":"North Brabant",
    "wof:name":"Mermans Glas Bv",
    "wof:placetype":"venue"
},
  "geometry": {"coordinates":[4.794103,51.592388],"type":"Point"}
}