{
  "type": "Feature",
  "properties": {
    "addr:full":"Antiloopstraat 45 A Breda North Brabant 4817 LA",
    "addr:housenumber":"45 a",
    "addr:postcode":"4817 la",
    "addr:street":"Antiloopstraat",
    "iso:country":"NL",
    "sg:address":"Antiloopstraat 45 A",
    "sg:city":"Breda",
    "sg:orig_category":"Glaszetten",
    "sg:phone":"+31 76 514 7970",
    "sg:postcode":"4817 LA",
    "sg:province":"North Brabant",
    "wof:name":"Mermans Glas Bv",
    "wof:placetype":"venue"
},
  "geometry": {"coordinates":[4.794103,51.592388],"type":"Point"}
}