{
  "type": "Feature",
  "properties": {
    "addr:full":"Hoofdweg 117 Lijnden Noord-Holland 1175 KM",
    "addr:housenumber":"117",
    "addr:street":"Hoofdweg;1175 Km",
    "iso:country":"NL",
    "sg:address":"Hoofdweg 117",
    "sg:city":"Lijnden",
    "sg:orig_category":"Loodgieterswerk, Verwarming And Sanitaire Installaties",
    "sg:phone":"+31 23 555 2097",
    "sg:postcode":"1175 KM",
    "sg:province":"Noord-Holland",
    "wof:name":"Tika Timmerbedrijf",
    "wof:placetype":"venue"
},
  "geometry": {"coordinates":[4.752138,52.347466],"type":"Point"}
}