{
  "type": "Feature",
  "properties": {
    "addr:full":"Industrieweg 4 Yerseke Zeeland 4401 LB",
    "addr:housenumber":"4",
    "addr:postcode":"4401 lb",
    "addr:street":"Industrieweg",
    "iso:country":"NL",
    "sg:address":"Industrieweg 4",
    "sg:city":"Yerseke",
    "sg:orig_category":"Technische Studies And Onderzoek",
    "sg:phone":"+31 113 572 106",
    "sg:postcode":"4401 LB",
    "sg:province":"Zeeland",
    "wof:name":"Skadoc Submersible Vehicles Bv",
    "wof:placetype":"venue"
},
  "geometry": {"coordinates":[4.049057,51.499432],"type":"Point"}
}