{
  "type": "Feature",
  "properties": {
    "iso:country":"NL",
    "sg:address":"Energiewg 3",
    "sg:city":"Gendringen",
    "sg:orig_category":"Grafkisten",
    "sg:phone":"+31 315 640 930",
    "sg:postcode":"7081 AD",
    "sg:province":"Gelderland",
    "wof:name":"Tomba",
    "wof:placetype":"venue"
},
  "geometry": {"coordinates":[6.384645,51.877636],"type":"Point"}
}