{
  "type": "Feature",
  "properties": {
    "addr:full":"Koppelweg 54 Amersfoort Utrecht 3813 SE",
    "addr:housenumber":"54",
    "addr:postcode":"3813 se",
    "addr:street":"Koppelweg",
    "iso:country":"NL",
    "sg:address":"Koppelweg 54",
    "sg:city":"Amersfoort",
    "sg:orig_category":"Metaalwerken",
    "sg:phone":"+31 33 479 0647",
    "sg:postcode":"3813 SE",
    "sg:province":"Utrecht",
    "wof:name":"Jbs Installatie & Systeembouw",
    "wof:placetype":"venue"
},
  "geometry": {"coordinates":[5.383331,52.162418],"type":"Point"}
}