{
  "type": "Feature",
  "properties": {
    "iso:country":"NL",
    "sg:address":"Liendenhof 17",
    "sg:city":"Amsterdam Zuidoost",
    "sg:orig_category":"Administratie- En Boekhoudkantoren",
    "sg:phone":"+31 20 697 1436",
    "sg:postcode":"1108 GX",
    "sg:province":"Noord-Holland",
    "wof:name":"Bohan Vof",
    "wof:placetype":"venue"
},
  "geometry": {"coordinates":[4.985677,52.308243],"type":"Point"}
}