{
  "type": "Feature",
  "properties": {
    "addr:full":"Liendenhof 17 Amsterdam Zuidoost Noord-Holland 1108 GX",
    "addr:housenumber":"17",
    "addr:postcode":"zuidoost;1108 gx",
    "addr:street":"Liendenhof",
    "iso:country":"NL",
    "sg:address":"Liendenhof 17",
    "sg:city":"Amsterdam Zuidoost",
    "sg:orig_category":"Administratie- En Boekhoudkantoren",
    "sg:phone":"+31 20 697 1436",
    "sg:postcode":"1108 GX",
    "sg:province":"Noord-Holland",
    "wof:name":"Bohan Vof",
    "wof:placetype":"venue"
},
  "geometry": {"coordinates":[4.985677,52.308243],"type":"Point"}
}