{
  "type": "Feature",
  "properties": {
    "iso:country":"NL",
    "sg:address":"Oude Oxerstg 3",
    "sg:city":"Deventer",
    "sg:classifiers":[
        {
            "category":"Retail",
            "subcategory":"Auto Repair",
            "type":"Services"
        }
    ],
    "sg:phone":"+31 570 651 332",
    "sg:postcode":"7421 KD",
    "sg:province":"Overijssel",
    "sg:tags":[
        "garage"
    ],
    "sg:website":"http://www.garagewolters.nl",
    "wof:name":"Wolters, Garage",
    "wof:placetype":"venue"
},
  "geometry": {"coordinates":[6.215789,52.243565],"type":"Point"}
}