{
  "type": "Feature",
  "properties": {
    "iso:country":"NL",
    "sg:address":"Wingerdstr 22",
    "sg:city":"S Gravenhage",
    "sg:orig_category":"Tuinaanleg En -Onderhoud",
    "sg:phone":"+31 70 352 2870",
    "sg:postcode":"2565 VC",
    "sg:province":"Zuid-Holland",
    "sg:website":"http://www.tjeerdalkema.nl",
    "wof:name":"Alkema, Tjeerd",
    "wof:placetype":"venue"
},
  "geometry": {"coordinates":[4.26129,52.076382],"type":"Point"}
}