{
  "type": "Feature",
  "properties": {
    "addr:full":"Loosdrechtseweg 117 Hilversum Noord-Holland 1215 JP",
    "addr:housenumber":"117",
    "addr:postcode":"1215 jp",
    "addr:street":"Loosdrechtseweg",
    "iso:country":"NL",
    "sg:address":"Loosdrechtseweg 117",
    "sg:city":"Hilversum",
    "sg:orig_category":"Boekhouders",
    "sg:phone":"+31 35 623 4091",
    "sg:postcode":"1215 JP",
    "sg:province":"Noord-Holland",
    "wof:name":"Van Den Hazel & Partner",
    "wof:placetype":"venue"
},
  "geometry": {"coordinates":[5.153768,52.216427],"type":"Point"}
}