{
  "type": "Feature",
  "properties": {
    "addr:full":"N.C.B.-Laan 68 Veghel North Brabant 5462 GE",
    "addr:housenumber":"68",
    "addr:postcode":"5462",
    "addr:street":"N.C.B.-Laan",
    "iso:country":"NL",
    "sg:address":"N.C.B.-Laan 68",
    "sg:city":"Veghel",
    "sg:orig_category":"Zuivelproducten And Spijsoli?n Gh",
    "sg:phone":"+31 413 341 155",
    "sg:postcode":"5462 GE",
    "sg:province":"North Brabant",
    "wof:name":"Jalutra Trading Company Bv",
    "wof:placetype":"venue"
},
  "geometry": {"coordinates":[5.523373,51.616173],"type":"Point"}
}