{
  "type": "Feature",
  "properties": {
    "addr:full":"Johannes J. Glasweg 85 Amsterdam North Holland 1035 ST",
    "addr:housenumber":"85",
    "addr:postcode":"1035 st",
    "addr:street":"Johannes J. Glasweg",
    "iso:country":"NL",
    "sg:address":"Johannes J. Glasweg 85",
    "sg:city":"Amsterdam",
    "sg:orig_category":"Architecten",
    "sg:phone":"+31 20 633 2933",
    "sg:postcode":"1035 ST",
    "sg:province":"North Holland",
    "wof:name":"N.J. Van Baarsen",
    "wof:placetype":"venue"
},
  "geometry": {"coordinates":[4.902945,52.421818],"type":"Point"}
}