{
  "type": "Feature",
  "properties": {
    "addr:full":"V Lennepstr 33 S Gravenzande Zuid-Holland 2691 ZS",
    "addr:housenumber":"33;gravenzande",
    "addr:postcode":"2691 zs",
    "addr:street":"S",
    "iso:country":"NL",
    "sg:address":"V Lennepstr 33",
    "sg:city":"S Gravenzande",
    "sg:orig_category":"Vertalers",
    "sg:phone":"+31 174 415 457",
    "sg:postcode":"2691 ZS",
    "sg:province":"Zuid-Holland",
    "wof:name":"Macdaniel",
    "wof:placetype":"venue"
},
  "geometry": {"coordinates":[4.16946,51.994629],"type":"Point"}
}