{
  "type": "Feature",
  "properties": {
    "addr:full":"Houtmarkt 57 Haarlem Noord-Holland 2011 AL",
    "addr:housenumber":"57",
    "addr:postcode":"2011 al",
    "addr:street":"Houtmarkt",
    "iso:country":"NL",
    "sg:address":"Houtmarkt 57",
    "sg:city":"Haarlem",
    "sg:orig_category":"Journalisten Freelance",
    "sg:phone":"+31 23 535 7434",
    "sg:postcode":"2011 AL",
    "sg:province":"Noord-Holland",
    "wof:name":"Meyer, Frank",
    "wof:placetype":"venue"
},
  "geometry": {"coordinates":[4.64435,52.380409],"type":"Point"}
}