{
  "type": "Feature",
  "properties": {
    "addr:full":"Zanderywg 13 Apeldoorn Gelderland 7312 EE",
    "addr:housenumber":"13",
    "addr:postcode":"7312 ee",
    "addr:street":"Zanderywg;Gelderland",
    "iso:country":"NL",
    "sg:address":"Zanderywg 13",
    "sg:city":"Apeldoorn",
    "sg:orig_category":"Antiquiteiten",
    "sg:phone":"+31 55 355 5786",
    "sg:postcode":"7312 EE",
    "sg:province":"Gelderland",
    "wof:name":"Kers, Antiekhandel",
    "wof:placetype":"venue"
},
  "geometry": {"coordinates":[5.941715,52.207375],"type":"Point"}
}