{
  "type": "Feature",
  "properties": {
    "addr:full":"L Wal 67-69 Arnhem Gelderland 6826 NA",
    "addr:housenumber":"67-69",
    "addr:postcode":"6826 na",
    "addr:street":"L Wal",
    "iso:country":"NL",
    "sg:address":"L Wal 67-69",
    "sg:city":"Arnhem",
    "sg:orig_category":"Fietsen En Bromfietsen",
    "sg:phone":"+31 26 361 3433",
    "sg:postcode":"6826 NA",
    "sg:province":"Gelderland",
    "wof:name":"Rooy, Tweewielers Van",
    "wof:placetype":"venue"
},
  "geometry": {"coordinates":[5.94264,51.983959],"type":"Point"}
}