{
  "type": "Feature",
  "properties": {
    "addr:full":"Stationsplein 10 Rotterdam South Holland 3013 AJ",
    "addr:housenumber":"10",
    "addr:postcode":"3013 aj",
    "addr:street":"Stationsplein",
    "iso:country":"NL",
    "sg:address":"Stationsplein 10",
    "sg:city":"Rotterdam",
    "sg:classifiers":[
        {
            "category":"Fast Food",
            "type":"Food & Drink"
        }
    ],
    "sg:phone":"+31 10 411 3758",
    "sg:postcode":"3013 AJ",
    "sg:province":"South Holland",
    "sg:tags":[
        "afhaal",
        "restaurant"
    ],
    "wof:name":"O.G.H. Janzon",
    "wof:placetype":"venue"
},
  "geometry": {"coordinates":[4.470507,51.924408],"type":"Point"}
}