{
  "type": "Feature",
  "properties": {
    "addr:full":"Lange Kerkstraat 86 Schiedam South Holland 3111 NR",
    "addr:housenumber":"86",
    "addr:postcode":"3111 nr",
    "addr:street":"Lange Kerkstraat",
    "iso:country":"NL",
    "sg:address":"Lange Kerkstraat 86",
    "sg:city":"Schiedam",
    "sg:orig_category":"Huishoudapparatuur, Televisies And Radio'S",
    "sg:phone":"+31 10 426 2996",
    "sg:postcode":"3111 NR",
    "sg:province":"South Holland",
    "wof:name":"Radio Henfli",
    "wof:placetype":"venue"
},
  "geometry": {"coordinates":[4.398838,51.918247],"type":"Point"}
}