{
  "type": "Feature",
  "properties": {
    "addr:full":"Middenstreek 5 Schiermonnikoog Friesland 9166 LL",
    "addr:housenumber":"5",
    "addr:postcode":"9166 ll",
    "addr:street":"Middenstreek",
    "iso:country":"NL",
    "sg:address":"Middenstreek 5",
    "sg:city":"Schiermonnikoog",
    "sg:orig_category":"Jeugdherbergen And Berghutten",
    "sg:phone":"+31 519 531 633",
    "sg:postcode":"9166 LL",
    "sg:province":"Friesland",
    "wof:name":"Manege Binnendijken",
    "wof:placetype":"venue"
},
  "geometry": {"coordinates":[6.160097,53.47818],"type":"Point"}
}