{
  "type": "Feature",
  "properties": {
    "addr:full":"Oude Oppenh Wg 20 Sneek Provincie Friesland 8606 JC",
    "addr:housenumber":"20",
    "addr:postcode":"8606 jc",
    "addr:street":"Oude;Wg;Provincie Friesland",
    "iso:country":"NL",
    "sg:address":"Oude Oppenh Wg 20",
    "sg:city":"Sneek",
    "sg:orig_category":"Jeugdherbergen",
    "sg:phone":"+31 515 412 132",
    "sg:postcode":"8606 JC",
    "sg:province":"Provincie Friesland",
    "sg:website":"http://www.wigledam.nl",
    "wof:name":"Wigledam Stayokay",
    "wof:placetype":"venue"
},
  "geometry": {"coordinates":[5.677133,53.027042],"type":"Point"}
}