{
  "type": "Feature",
  "properties": {
    "addr:full":"Rotsoord 24 Utrecht Utrecht 3523 CL",
    "addr:housenumber":"24",
    "addr:postcode":"3523",
    "addr:street":"Rotsoord",
    "iso:country":"NL",
    "sg:address":"Rotsoord 24",
    "sg:city":"Utrecht",
    "sg:orig_category":"Diensten Voor Huisdieren",
    "sg:phone":"+31 30 251 7255",
    "sg:postcode":"3523 CL",
    "sg:province":"Utrecht",
    "wof:name":"Vogelopvang",
    "wof:placetype":"venue"
},
  "geometry": {"coordinates":[5.121564,52.074528],"type":"Point"}
}