{
  "type": "Feature",
  "properties": {
    "addr:full":"Sluiswg 11A Lemmer Friesland 8531 DJ",
    "addr:housenumber":"11a",
    "addr:postcode":"8531 dj",
    "addr:street":"Sluiswg",
    "iso:country":"NL",
    "sg:address":"Sluiswg 11A",
    "sg:city":"Lemmer",
    "sg:orig_category":"Wegenbouw",
    "sg:phone":"+31 514 562 322",
    "sg:postcode":"8531 DJ",
    "sg:province":"Friesland",
    "wof:name":"Leijnse Bv, F B",
    "wof:placetype":"venue"
},
  "geometry": {"coordinates":[5.7151699066,52.8414878845],"type":"Point"}
}