{
  "type": "Feature",
  "properties": {
    "iso:country":"NL",
    "sg:address":"Tollenskd 3",
    "sg:city":"Voorburg",
    "sg:orig_category":"Administratie- En Boekhoudkantoren",
    "sg:phone":"+31 6 29521450",
    "sg:postcode":"2274 LT",
    "sg:province":"Zuid-Holland",
    "wof:name":"Echternach Advies Bv",
    "wof:placetype":"venue"
},
  "geometry": {"coordinates":[4.34952,52.073792],"type":"Point"}
}