{
  "type": "Feature",
  "properties": {
    "iso:country":"NL",
    "sg:address":"Dorpsstr 34",
    "sg:city":"Uffelte",
    "sg:orig_category":"Woninginrichting",
    "sg:phone":"+31 521 351 236",
    "sg:postcode":"7975 AP",
    "sg:province":"Drenthe",
    "wof:name":"Snoeken",
    "wof:placetype":"venue"
},
  "geometry": {"coordinates":[6.2803068161,52.7917022705],"type":"Point"}
}