{
  "type": "Feature",
  "properties": {
    "addr:full":"Claudius Prinsenlaan 142 Breda North Brabant 4818 CP",
    "addr:housenumber":"142",
    "addr:postcode":"4818 cp",
    "addr:street":"Claudius Prinsenlaan",
    "iso:country":"NL",
    "sg:address":"Claudius Prinsenlaan 142",
    "sg:city":"Breda",
    "sg:classifiers":[
        {
            "category":"Professional",
            "subcategory":"Accounting & Tax Preparation",
            "type":"Services"
        }
    ],
    "sg:phone":"+31 76 520 1892",
    "sg:postcode":"4818 CP",
    "sg:province":"North Brabant",
    "sg:tags":[
        "accountant"
    ],
    "wof:name":"Accountants En Belastingadviseurs Berk",
    "wof:placetype":"venue"
},
  "geometry": {"coordinates":[4.800303,51.585079],"type":"Point"}
}