{
  "type": "Feature",
  "properties": {
    "iso:country":"NL",
    "sg:address":"Astraat 10",
    "sg:city":"Groningen",
    "sg:classifiers":[
        {
            "category":"Bakery",
            "type":"Food & Drink"
        }
    ],
    "sg:phone":"+31 50 313 4000",
    "sg:postcode":"9718 CR",
    "sg:province":"Groningen",
    "sg:tags":[
        "brood",
        "banket"
    ],
    "wof:name":"De Vlaaienspecialist",
    "wof:placetype":"venue"
},
  "geometry": {"coordinates":[6.574715,53.217144],"type":"Point"}
}