{
  "type": "Feature",
  "properties": {
    "addr:full":"Dorpsstr 102 Oostknollendam Noord-Holland 1534 NN",
    "addr:housenumber":"102",
    "addr:postcode":"1534 nn",
    "iso:country":"NL",
    "sg:address":"Dorpsstr 102",
    "sg:city":"Oostknollendam",
    "sg:orig_category":"Belastingconsulenten/ Belastingadviseurs",
    "sg:phone":"+31 75 642 6175",
    "sg:postcode":"1534 NN",
    "sg:province":"Noord-Holland",
    "wof:name":"Dt Serviceburo",
    "wof:placetype":"venue"
},
  "geometry": {"coordinates":[4.801004,52.524395],"type":"Point"}
}