{
  "type": "Feature",
  "properties": {
    "addr:full":"Vinkenwg 35 Rynsburg Zuid-Holland 2231 NR",
    "addr:housenumber":"35",
    "addr:postcode":"2231 nr",
    "addr:street":"Vinkenwg",
    "iso:country":"NL",
    "sg:address":"Vinkenwg 35",
    "sg:city":"Rynsburg",
    "sg:orig_category":"Bloemen En Planten - Groothandel",
    "sg:phone":"+31 71 402 9363",
    "sg:postcode":"2231 NR",
    "sg:province":"Zuid-Holland",
    "wof:name":"Kwaak Vof, J Van Der",
    "wof:placetype":"venue"
},
  "geometry": {"coordinates":[4.455986,52.198982],"type":"Point"}
}