{
  "type": "Feature",
  "properties": {
    "addr:full":"Fagot 30 Ewijk Gelderland 6644 AZ",
    "addr:housenumber":"30",
    "addr:postcode":"6644",
    "addr:street":"Fagot;Gelderland",
    "iso:country":"NL",
    "sg:address":"Fagot 30",
    "sg:city":"Ewijk",
    "sg:orig_category":"Bedrijfs- And Managementsconsultants",
    "sg:phone":"+31 487 522 920",
    "sg:postcode":"6644 AZ",
    "sg:province":"Gelderland",
    "wof:name":"J.P. Stuurman",
    "wof:placetype":"venue"
},
  "geometry": {"coordinates":[5.736245,51.872105],"type":"Point"}
}