{
  "type": "Feature",
  "properties": {
    "addr:full":"Kernreactorstraat 24 Veenendaal Utrecht 3903 LG",
    "addr:housenumber":"24",
    "addr:postcode":"3903 lg",
    "addr:street":"Kernreactorstraat",
    "iso:country":"NL",
    "sg:address":"Kernreactorstraat 24",
    "sg:city":"Veenendaal",
    "sg:orig_category":"Vertaal- And Tolkenbureaus",
    "sg:phone":"+31 318 524 680",
    "sg:postcode":"3903 LG",
    "sg:province":"Utrecht",
    "wof:name":"Nieuw Europa Bureau Voor Oost Europa",
    "wof:placetype":"venue"
},
  "geometry": {"coordinates":[5.566558,52.010746],"type":"Point"}
}