{
  "type": "Feature",
  "properties": {
    "iso:country":"NL",
    "sg:address":"Keizershof 113",
    "sg:city":"Alphen Aan Den Rijn",
    "sg:orig_category":"Juweliers",
    "sg:phone":"+31 172 422 495",
    "sg:postcode":"2402  D",
    "sg:province":"South Holland",
    "wof:name":"Juwelier Gold",
    "wof:placetype":"venue"
},
  "geometry": {"coordinates":[4.658921,52.12719],"type":"Point"}
}