{
  "type": "Feature",
  "properties": {
    "addr:full":"Keizershof 113 Alphen Aan Den Rijn South Holland 2402  D",
    "addr:housenumber":"113;2402 d",
    "addr:street":"Keizershof",
    "iso:country":"NL",
    "sg:address":"Keizershof 113",
    "sg:city":"Alphen Aan Den Rijn",
    "sg:orig_category":"Juweliers",
    "sg:phone":"+31 172 422 495",
    "sg:postcode":"2402  D",
    "sg:province":"South Holland",
    "wof:name":"Juwelier Gold",
    "wof:placetype":"venue"
},
  "geometry": {"coordinates":[4.658921,52.12719],"type":"Point"}
}