{
  "type": "Feature",
  "properties": {
    "iso:country":"NL",
    "sg:address":"Nassaustr 22",
    "sg:city":"Haarlem",
    "sg:orig_category":"Drukkerijen",
    "sg:phone":"+31 23 532 0829",
    "sg:postcode":"2011 PJ",
    "sg:province":"Noord-Holland",
    "wof:name":"Teeuwen Haarlem Bv, Drukkerij",
    "wof:placetype":"venue"
},
  "geometry": {"coordinates":[4.634383,52.384586],"type":"Point"}
}