{
  "type": "Feature",
  "properties": {
    "iso:country":"NL",
    "sg:address":"Kruizemuntstr 108",
    "sg:city":"Apeldoorn",
    "sg:orig_category":"Artsen - Huisartsen",
    "sg:phone":"+31 55 366 5534",
    "sg:postcode":"7322 MA",
    "sg:province":"Gelderland",
    "wof:name":"Vermeulen, F P",
    "wof:placetype":"venue"
},
  "geometry": {"coordinates":[5.991763,52.217422],"type":"Point"}
}