{
  "type": "Feature",
  "properties": {
    "addr:full":"Kerkstr 45 Asten Noord-Brabant 5721 GS",
    "addr:housenumber":"45",
    "addr:postcode":"5721 gs",
    "addr:street":"Kerkstr",
    "iso:country":"NL",
    "sg:address":"Kerkstr 45",
    "sg:city":"Asten",
    "sg:orig_category":"Waterschappen",
    "sg:phone":"+31 493 696 432",
    "sg:postcode":"5721 GS",
    "sg:province":"Noord-Brabant",
    "wof:name":"Rofa",
    "wof:placetype":"venue"
},
  "geometry": {"coordinates":[5.7487940788,51.4004249573],"type":"Point"}
}