{
  "type": "Feature",
  "properties": {
    "addr:full":"Gouderakstr 10 Zoetermeer South Holland 2729 AB",
    "addr:housenumber":"10",
    "addr:postcode":"2729 ab",
    "addr:street":"Gouderakstr",
    "iso:country":"NL",
    "sg:address":"Gouderakstr 10",
    "sg:city":"Zoetermeer",
    "sg:orig_category":"Voegwerken",
    "sg:phone":"+31 79 361 5969",
    "sg:postcode":"2729 AB",
    "sg:province":"South Holland",
    "wof:name":"Spierings, Metsel- En Voegbedrijf",
    "wof:placetype":"venue"
},
  "geometry": {"coordinates":[4.529082,52.064217],"type":"Point"}
}