{
  "type": "Feature",
  "properties": {
    "addr:full":"Casteleynstr 3 Haarlem Noord-Holland 2012 AH",
    "addr:housenumber":"3",
    "addr:postcode":"2012 ah",
    "addr:street":"Casteleynstr",
    "iso:country":"NL",
    "sg:address":"Casteleynstr 3",
    "sg:city":"Haarlem",
    "sg:orig_category":"Artiesten/Gezelschappen",
    "sg:phone":"+31 23 534 5534",
    "sg:postcode":"2012 AH",
    "sg:province":"Noord-Holland",
    "wof:name":"Zwart, Jos",
    "wof:placetype":"venue"
},
  "geometry": {"coordinates":[4.639409,52.372711],"type":"Point"}
}