{
  "type": "Feature",
  "properties": {
    "addr:full":"Colijnlaan 16 Emmeloord Flevoland 8302 BM",
    "addr:housenumber":"16",
    "addr:postcode":"8302 bm",
    "addr:street":"Colijnlaan;Flevoland",
    "iso:country":"NL",
    "sg:address":"Colijnlaan 16",
    "sg:city":"Emmeloord",
    "sg:classifiers":[
        {
            "category":"Professional",
            "subcategory":"Accounting & Tax Preparation",
            "type":"Services"
        }
    ],
    "sg:phone":"+31 527 698 892",
    "sg:postcode":"8302 BM",
    "sg:province":"Flevoland",
    "sg:tags":[
        "accountant"
    ],
    "wof:name":"G. Ten Hoopen Bv",
    "wof:placetype":"venue"
},
  "geometry": {"coordinates":[5.765678,52.714806],"type":"Point"}
}