{
  "type": "Feature",
  "properties": {
    "iso:country":"NL",
    "sg:address":"Herenstr 49-51",
    "sg:city":"Slagharen",
    "sg:orig_category":"Parketvloeren",
    "sg:phone":"+31 523 682 373",
    "sg:postcode":"7776 AH",
    "sg:province":"Overijssel",
    "sg:website":"http://www.meijer-parket.nl",
    "wof:name":"Meijer Parket Vof Slagharen",
    "wof:placetype":"venue"
},
  "geometry": {"coordinates":[6.552079,52.629478],"type":"Point"}
}