{
  "type": "Feature",
  "properties": {
    "addr:full":"Stjelpdyk 1 Wjelsryp Friesland 8842 KM",
    "addr:housenumber":"1",
    "addr:postcode":"8842 km",
    "addr:street":"Stjelpdyk",
    "iso:country":"NL",
    "sg:address":"Stjelpdyk 1",
    "sg:city":"Wjelsryp",
    "sg:orig_category":"Film-, Tv- And Videoproductie",
    "sg:phone":"+31 517 342 410",
    "sg:postcode":"8842 KM",
    "sg:province":"Friesland",
    "wof:name":"Van Bussel Av Produkties",
    "wof:placetype":"venue"
},
  "geometry": {"coordinates":[5.619069,53.156006],"type":"Point"}
}