{
  "type": "Feature",
  "properties": {
    "iso:country":"NL",
    "sg:address":"Burg Wuitewg 82",
    "sg:city":"Drachten",
    "sg:orig_category":"Autorijscholen",
    "sg:phone":"+31 512 521 050",
    "sg:postcode":"9203 KM",
    "sg:province":"Friesland",
    "wof:name":"Spanje, Ton Van",
    "wof:placetype":"venue"
},
  "geometry": {"coordinates":[6.098526,53.100647],"type":"Point"}
}