{
  "type": "Feature",
  "properties": {
    "iso:country":"NL",
    "sg:address":"Twiskewg 80",
    "sg:city":"Zaandam",
    "sg:orig_category":"Bejaarden - Verzorgingstehuizen",
    "sg:phone":"+31 75 616 8751",
    "sg:postcode":"1504 AE",
    "sg:province":"North Holland",
    "wof:name":"Erasmushuis, Het",
    "wof:placetype":"venue"
},
  "geometry": {"coordinates":[4.84225,52.440891],"type":"Point"}
}