{
  "type": "Feature",
  "properties": {
    "addr:full":"Westzijde 220 Zaandam North Holland 1506 GG",
    "addr:housenumber":"220",
    "addr:postcode":"1506 gg",
    "addr:street":"Westzijde",
    "iso:country":"NL",
    "sg:address":"Westzijde 220",
    "sg:city":"Zaandam",
    "sg:orig_category":"Meubelzaken, Woning- And Keukeninrichting",
    "sg:phone":"+31 75 617 5256",
    "sg:postcode":"1506 GG",
    "sg:province":"North Holland",
    "wof:name":"De Steeg Grenen Meubelen",
    "wof:placetype":"venue"
},
  "geometry": {"coordinates":[4.819523,52.448147],"type":"Point"}
}