{
  "type": "Feature",
  "properties": {
    "addr:full":"Opdegraaf 33 Oirsbeek Limburg 6438 JA",
    "addr:housenumber":"33",
    "addr:postcode":"6438 ja",
    "addr:street":"Opdegraaf",
    "iso:country":"NL",
    "sg:address":"Opdegraaf 33",
    "sg:city":"Oirsbeek",
    "sg:orig_category":"Verhuur Bouwmachines",
    "sg:phone":"+31 46 442 2261",
    "sg:postcode":"6438 JA",
    "sg:province":"Limburg",
    "wof:name":"Expl Van Grondverzetmach Spruyt Bv",
    "wof:placetype":"venue"
},
  "geometry": {"coordinates":[5.905831,50.952583],"type":"Point"}
}