{
  "type": "Feature",
  "properties": {
    "addr:full":"Diepenbroek 8 Helmond North Brabant 5707 DA",
    "addr:housenumber":"8",
    "addr:postcode":"5707 da",
    "addr:street":"Diepenbroek",
    "iso:country":"NL",
    "sg:address":"Diepenbroek 8",
    "sg:city":"Helmond",
    "sg:orig_category":"Adviesbureaus Bouwkunde",
    "sg:phone":"+31 492 664 004",
    "sg:postcode":"5707 DA",
    "sg:province":"North Brabant",
    "wof:name":"Vogels Bv",
    "wof:placetype":"venue"
},
  "geometry": {"coordinates":[5.603601,51.463913],"type":"Point"}
}