{
  "type": "Feature",
  "properties": {
    "addr:full":"Bizetlaan 20 Vlijmen North Brabant 5251 HA",
    "addr:housenumber":"20",
    "addr:postcode":"5251 ha",
    "addr:street":"Bizetlaan",
    "iso:country":"NL",
    "sg:address":"Bizetlaan 20",
    "sg:city":"Vlijmen",
    "sg:orig_category":"Kantoorartikelen",
    "sg:phone":"+31 73 511 2720",
    "sg:postcode":"5251 HA",
    "sg:province":"North Brabant",
    "wof:name":"Noadd Systems Vof",
    "wof:placetype":"venue"
},
  "geometry": {"coordinates":[5.21960783,51.6996765137],"type":"Point"}
}