{
  "type": "Feature",
  "properties": {
    "addr:full":"Vd Palmstr 3 Papendrecht South Holland 3351 HA",
    "addr:housenumber":"3",
    "addr:postcode":"3351 ha",
    "iso:country":"NL",
    "sg:address":"Vd Palmstr 3",
    "sg:city":"Papendrecht",
    "sg:orig_category":"Zalenverhuur",
    "sg:phone":"+31 78 615 1837",
    "sg:postcode":"3351 HA",
    "sg:province":"South Holland",
    "wof:name":"Palm, De",
    "wof:placetype":"venue"
},
  "geometry": {"coordinates":[4.684271,51.832073],"type":"Point"}
}