{
  "type": "Feature",
  "properties": {
    "addr:full":"Kreitenmolenstr 107 Udenhout British Columbia 5071 BC",
    "addr:housenumber":"107",
    "addr:postcode":"5071 bc",
    "iso:country":"NL",
    "sg:address":"Kreitenmolenstr 107",
    "sg:city":"Udenhout",
    "sg:orig_category":"Meubelen",
    "sg:phone":"+31 13 511 3650",
    "sg:postcode":"5071 BC",
    "sg:province":"British Columbia",
    "sg:website":"http://www.molenaarmeubelen.nl",
    "wof:name":"Molenaar Bv",
    "wof:placetype":"venue"
},
  "geometry": {"coordinates":[-126.555511,54.485668],"type":"Point"}
}