{
  "type": "Feature",
  "properties": {
    "addr:full":"Dorpsstraat 6 A Vleuten Utrecht 3451 BK",
    "addr:housenumber":"6 a",
    "addr:postcode":"3451 bk",
    "addr:street":"Dorpsstraat",
    "iso:country":"NL",
    "sg:address":"Dorpsstraat 6 A",
    "sg:city":"Vleuten",
    "sg:orig_category":"Kappers",
    "sg:phone":"+31 30 677 1888",
    "sg:postcode":"3451 BK",
    "sg:province":"Utrecht",
    "wof:name":"Allround Haarmode",
    "wof:placetype":"venue"
},
  "geometry": {"coordinates":[5.0113749504,52.1062202454],"type":"Point"}
}