{
  "type": "Feature",
  "properties": {
    "addr:full":"Markt 46 Hapert North Brabant 5527 EN",
    "addr:housenumber":"46",
    "addr:postcode":"5527 en",
    "addr:street":"Markt",
    "iso:country":"NL",
    "sg:address":"Markt 46",
    "sg:city":"Hapert",
    "sg:orig_category":"Fitnesscentra",
    "sg:phone":"+31 497 385 456",
    "sg:postcode":"5527 EN",
    "sg:province":"North Brabant",
    "sg:website":"http://www.fitnesshapert.nl",
    "wof:name":"Fitness Hapert",
    "wof:placetype":"venue"
},
  "geometry": {"coordinates":[5.25194,51.36969],"type":"Point"}
}