{
  "type": "Feature",
  "properties": {
    "addr:full":"G. Van Nijenrodestraat 82 Breukelen Utrecht 3621 GM",
    "addr:housenumber":"82",
    "addr:postcode":"3621 gm",
    "addr:street":"G. Van Nijenrodestraat",
    "iso:country":"NL",
    "sg:address":"G. Van Nijenrodestraat 82",
    "sg:city":"Breukelen",
    "sg:orig_category":"Verpakkingsbedrijven",
    "sg:phone":"+31 346 262 804",
    "sg:postcode":"3621 GM",
    "sg:province":"Utrecht",
    "sg:website":"http://www.pauwbedrijven.nl",
    "wof:name":"Pauw Bedrijven",
    "wof:placetype":"venue"
},
  "geometry": {"coordinates":[5.001743,52.183502],"type":"Point"}
}