{
  "type": "Feature",
  "properties": {
    "iso:country":"NL",
    "sg:address":"Herbergiershorst 214",
    "sg:city":"Apeldoorn",
    "sg:orig_category":"Diverse Consumentenartikelen Gh",
    "sg:phone":"+31 55 533 4525",
    "sg:postcode":"7328 SH",
    "sg:province":"Gelderland",
    "wof:name":"Impala Fashion",
    "wof:placetype":"venue"
},
  "geometry": {"coordinates":[5.991853,52.204292],"type":"Point"}
}