{
  "type": "Feature",
  "properties": {
    "iso:country":"NL",
    "sg:address":"Ulgersmawg 23",
    "sg:city":"Groningen",
    "sg:orig_category":"Banden",
    "sg:phone":"+31 50 541 7532",
    "sg:postcode":"9731 BJ",
    "sg:province":"Groningen",
    "wof:name":"Bandentrend",
    "wof:placetype":"venue"
},
  "geometry": {"coordinates":[6.58824,53.232388],"type":"Point"}
}