{
  "type": "Feature",
  "properties": {
    "addr:full":"Stadhoudershof 8 Harmelen Utrecht 3481 HT",
    "addr:housenumber":"8",
    "addr:postcode":"3481 ht",
    "addr:street":"Stadhoudershof",
    "iso:country":"NL",
    "sg:address":"Stadhoudershof 8",
    "sg:city":"Harmelen",
    "sg:orig_category":"Adviesbureaus Bedrijfsorganisatie",
    "sg:phone":"+31 348 468 822",
    "sg:postcode":"3481 HT",
    "sg:province":"Utrecht",
    "wof:name":"Heremaelen, De",
    "wof:placetype":"venue"
},
  "geometry": {"coordinates":[4.958333,52.085663],"type":"Point"}
}