{
  "type": "Feature",
  "properties": {
    "addr:full":"Zuiderkruis 11 De Krim Overijssel 7782 SH",
    "addr:housenumber":"11",
    "addr:postcode":"7782 sh",
    "addr:street":"Zuiderkruis",
    "iso:country":"NL",
    "sg:address":"Zuiderkruis 11",
    "sg:city":"De Krim",
    "sg:orig_category":"Parketvloeren",
    "sg:phone":"+31 524 572 189",
    "sg:postcode":"7782 SH",
    "sg:province":"Overijssel",
    "wof:name":"Ro\u00eal Parket De Krim Vof",
    "wof:placetype":"venue"
},
  "geometry": {"coordinates":[6.619921,52.648262],"type":"Point"}
}