{
  "type": "Feature",
  "properties": {
    "addr:full":"Haven 14 Monnickendam Noord-Holland 1141 AZ",
    "addr:housenumber":"14",
    "addr:postcode":"1141 az",
    "addr:street":"Haven",
    "iso:country":"NL",
    "sg:address":"Haven 14",
    "sg:city":"Monnickendam",
    "sg:orig_category":"Verzekeringen - Verzekeringskantoren",
    "sg:phone":"+31 299 651 843",
    "sg:postcode":"1141 AZ",
    "sg:province":"Noord-Holland",
    "wof:name":"Elswijk Bv",
    "wof:placetype":"venue"
},
  "geometry": {"coordinates":[5.036618,52.460045],"type":"Point"}
}