{
  "type": "Feature",
  "properties": {
    "iso:country":"NL",
    "sg:address":"Citruswg 6",
    "sg:city":"Leiden",
    "sg:orig_category":"Meubelstoffering",
    "sg:phone":"+31 71 572 1700",
    "sg:postcode":"2321 KD",
    "sg:province":"Zuid-Holland",
    "wof:name":"Kleer",
    "wof:placetype":"venue"
},
  "geometry": {"coordinates":[4.48805,52.147243],"type":"Point"}
}