{
  "type": "Feature",
  "properties": {
    "iso:country":"NL",
    "sg:address":"Hoofdstr W 2123",
    "sg:city":"Winsum Gn",
    "sg:orig_category":"Fotozaken",
    "sg:phone":"+31 595 444 400",
    "sg:postcode":"9951 AA",
    "sg:province":"Groningen",
    "wof:name":"Vaszlovszky",
    "wof:placetype":"venue"
},
  "geometry": {"coordinates":[6.517395,53.334412],"type":"Point"}
}