{
  "type": "Feature",
  "properties": {
    "addr:full":"Kasteelhof 50 Druten Gelderland 6651 VB",
    "addr:housenumber":"50",
    "addr:postcode":"6651 vb",
    "addr:street":"Kasteelhof",
    "iso:country":"NL",
    "sg:address":"Kasteelhof 50",
    "sg:city":"Druten",
    "sg:orig_category":"Bejaarden - Verzorgingstehuizen",
    "sg:phone":"+31 487 516 894",
    "sg:postcode":"6651 VB",
    "sg:province":"Gelderland",
    "wof:name":"Swod",
    "wof:placetype":"venue"
},
  "geometry": {"coordinates":[5.607615,51.890991],"type":"Point"}
}