{
  "type": "Feature",
  "properties": {
    "addr:full":"Kinheim 4 Zwanenburg Noord-Holland 1161 AP",
    "addr:housenumber":"4",
    "addr:postcode":"1161 ap",
    "addr:street":"Kinheim",
    "iso:country":"NL",
    "sg:address":"Kinheim 4",
    "sg:city":"Zwanenburg",
    "sg:classifiers":[
        {
            "category":"Education",
            "subcategory":"Preschool",
            "type":"Public Place"
        }
    ],
    "sg:phone":"+31 20 497 4285",
    "sg:postcode":"1161 AP",
    "sg:province":"Noord-Holland",
    "sg:tags":[
        "kleuteronderwijs",
        "basis-"
    ],
    "wof:name":"Openbare Basisschool Aldoende",
    "wof:placetype":"venue"
},
  "geometry": {"coordinates":[4.734352,52.38102],"type":"Point"}
}