{
  "type": "Feature",
  "properties": {
    "addr:full":"Wirdumerweg 5 Loppersum Groningen 9919 HA",
    "addr:housenumber":"5",
    "addr:postcode":"9919 ha",
    "addr:street":"Wirdumerweg",
    "iso:country":"NL",
    "sg:address":"Wirdumerweg 5",
    "sg:city":"Loppersum",
    "sg:orig_category":"Overheidsdiensten",
    "sg:phone":"+31 596 571 674",
    "sg:postcode":"9919 HA",
    "sg:province":"Groningen",
    "wof:name":"Flits",
    "wof:placetype":"venue"
},
  "geometry": {"coordinates":[6.747440815,53.3324813843],"type":"Point"}
}