{
  "type": "Feature",
  "properties": {
    "iso:country":"NL",
    "sg:address":"R Visscherstr 23",
    "sg:city":"Almere",
    "sg:orig_category":"Administratie- En Boekhoudkantoren",
    "sg:phone":"+31 36 844 8779",
    "sg:postcode":"1321 CC",
    "sg:province":"Flevoland",
    "sg:website":"http://www.idofficesupport.nl",
    "wof:name":"Id Office Support",
    "wof:placetype":"venue"
},
  "geometry": {"coordinates":[5.185513,52.36237],"type":"Point"}
}