{
  "type": "Feature",
  "properties": {
    "addr:full":"Looveer 1C Huissen Gelderland 6851 AJ",
    "addr:housenumber":"1c",
    "addr:postcode":"6851 aj",
    "addr:street":"Looveer;Gelderland",
    "iso:country":"NL",
    "sg:address":"Looveer 1C",
    "sg:city":"Huissen",
    "sg:orig_category":"Betonmortel",
    "sg:phone":"+31 26 325 9128",
    "sg:postcode":"6851 AJ",
    "sg:province":"Gelderland",
    "wof:name":"Betonmortelbedrijven Cementbouw Bv",
    "wof:placetype":"venue"
},
  "geometry": {"coordinates":[5.96017,51.936085],"type":"Point"}
}