{
  "type": "Feature",
  "properties": {
    "addr:full":"Hoofdstr 39A Westerbork Drenthe 9431 AC",
    "addr:housenumber":"39a",
    "addr:postcode":"9431 ac",
    "addr:street":"Hoofdstr",
    "iso:country":"NL",
    "sg:address":"Hoofdstr 39A",
    "sg:city":"Westerbork",
    "sg:orig_category":"Boeken En Tijdschriften",
    "sg:phone":"+31 593 331 200",
    "sg:postcode":"9431 AC",
    "sg:province":"Drenthe",
    "wof:name":"Bruna",
    "wof:placetype":"venue"
},
  "geometry": {"coordinates":[6.613388,52.849567],"type":"Point"}
}