{
  "type": "Feature",
  "properties": {
    "addr:full":"Schiedamse Vest 103 Rotterdam Zuid-Holland 3012 BH",
    "addr:housenumber":"103",
    "addr:postcode":"3012 bh",
    "addr:street":"Schiedamse Vest",
    "iso:country":"NL",
    "sg:address":"Schiedamse Vest 103",
    "sg:city":"Rotterdam",
    "sg:orig_category":"Architecten",
    "sg:phone":"+31 10 444 3420",
    "sg:postcode":"3012 BH",
    "sg:province":"Zuid-Holland",
    "wof:name":"Squizzo Architecten",
    "wof:placetype":"venue"
},
  "geometry": {"coordinates":[4.479622,51.915298],"type":"Point"}
}