{
  "type": "Feature",
  "properties": {
    "addr:full":"Boedapestln 83-85 Ysselstein Ut Utrecht 3404 CC",
    "addr:housenumber":"83-85",
    "addr:postcode":"3404 cc",
    "addr:street":"Ysselstein",
    "iso:country":"NL",
    "sg:address":"Boedapestln 83-85",
    "sg:city":"Ysselstein Ut",
    "sg:orig_category":"Makelaars En Adviseurs Onroerende Goederen",
    "sg:phone":"+31 30 600 7080",
    "sg:postcode":"3404 CC",
    "sg:province":"Utrecht",
    "wof:name":"Vliet & Van Wiggen, Van",
    "wof:placetype":"venue"
},
  "geometry": {"coordinates":[5.0405,52.011032],"type":"Point"}
}