{
  "type": "Feature",
  "properties": {
    "addr:full":"J Vernewg 1 Emmen Drenthe 7821 AD",
    "addr:housenumber":"1",
    "addr:postcode":"7821 ad",
    "iso:country":"NL",
    "sg:address":"J Vernewg 1",
    "sg:city":"Emmen",
    "sg:orig_category":"Automaterialen En Gereedschappen",
    "sg:phone":"+31 591 654 654",
    "sg:postcode":"7821 AD",
    "sg:province":"Drenthe",
    "sg:website":"http://www.lasaulec.nl",
    "wof:name":"Lasaulec Emmen",
    "wof:placetype":"venue"
},
  "geometry": {"coordinates":[6.913794,52.773449],"type":"Point"}
}