{
  "type": "Feature",
  "properties": {
    "addr:full":"Het Anker 22 Raamsdonksveer North Brabant 4941 RG",
    "addr:housenumber":"22",
    "addr:postcode":"4941 rg",
    "addr:street":"Het Anker",
    "iso:country":"NL",
    "sg:address":"Het Anker 22",
    "sg:city":"Raamsdonksveer",
    "sg:orig_category":"Chemische Producten Gh",
    "sg:phone":"+31 162 522 852",
    "sg:postcode":"4941 RG",
    "sg:province":"North Brabant",
    "wof:name":"Marimpex Nederland Bv",
    "wof:placetype":"venue"
},
  "geometry": {"coordinates":[4.872585,51.696129],"type":"Point"}
}