{
  "type": "Feature",
  "properties": {
    "iso:country":"NL",
    "sg:address":"Amperestr 22",
    "sg:city":"Zwolle",
    "sg:orig_category":"Banden",
    "sg:phone":"+31 38 465 5830",
    "sg:postcode":"8013 PV",
    "sg:province":"NL.08",
    "sg:website":"http://www.euromaster.com",
    "wof:name":"Euromaster",
    "wof:placetype":"venue"
},
  "geometry": {"coordinates":[6.128539,52.492996],"type":"Point"}
}