{
  "type": "Feature",
  "properties": {
    "addr:full":"Ursulineweg 4 Leusden Utrecht 3833 AA",
    "addr:housenumber":"4",
    "addr:postcode":"3833 aa",
    "addr:street":"Ursulineweg",
    "iso:country":"NL",
    "sg:address":"Ursulineweg 4",
    "sg:city":"Leusden",
    "sg:orig_category":"Bloemen And Planten",
    "sg:phone":"+31 33 494 5161",
    "sg:postcode":"3833 AA",
    "sg:province":"Utrecht",
    "wof:name":"Oudshoorn Bloemen",
    "wof:placetype":"venue"
},
  "geometry": {"coordinates":[5.416489,52.138363],"type":"Point"}
}