{
  "type": "Feature",
  "properties": {
    "addr:full":"Westblaak 47 Rotterdam Zuid-Holland 3012 KD",
    "addr:housenumber":"47",
    "addr:postcode":"3012 kd",
    "addr:street":"Westblaak",
    "iso:country":"NL",
    "sg:address":"Westblaak 47",
    "sg:city":"Rotterdam",
    "sg:orig_category":"Woninginrichting",
    "sg:phone":"+31 10 213 3790",
    "sg:postcode":"3012 KD",
    "sg:province":"Zuid-Holland",
    "sg:website":"http://www.mellies.nl",
    "wof:name":"Mellies",
    "wof:placetype":"venue"
},
  "geometry": {"coordinates":[4.4779758453,51.9174308777],"type":"Point"}
}