{
  "type": "Feature",
  "properties": {
    "addr:full":"Onsteinseweg 20 Vorden Gelderland 7251 ML",
    "addr:housenumber":"20",
    "addr:postcode":"7251 ml",
    "addr:street":"Onsteinseweg;Gelderland",
    "iso:country":"NL",
    "sg:address":"Onsteinseweg 20",
    "sg:city":"Vorden",
    "sg:orig_category":"Huizensloop And Bouwrijp Maken",
    "sg:phone":"+31 575 556 691",
    "sg:postcode":"7251 ML",
    "sg:province":"Gelderland",
    "wof:name":"Dostal Aannemersbedrijf Bv",
    "wof:placetype":"venue"
},
  "geometry": {"coordinates":[6.385471,52.094543],"type":"Point"}
}