{
  "type": "Feature",
  "properties": {
    "addr:full":"Oude Sluis 19 Schiedam Zuid-Holland 3111 PK",
    "addr:housenumber":"19",
    "addr:postcode":"3111 pk",
    "addr:street":"Oude Sluis",
    "iso:country":"NL",
    "sg:address":"Oude Sluis 19",
    "sg:city":"Schiedam",
    "sg:orig_category":"Overheidsdiensten",
    "sg:phone":"+31 10 426 6623",
    "sg:postcode":"3111 PK",
    "sg:province":"Zuid-Holland",
    "wof:name":"Zakkendragershuis",
    "wof:placetype":"venue"
},
  "geometry": {"coordinates":[4.3981599808,51.91847229],"type":"Point"}
}