{
  "type": "Feature",
  "properties": {
    "iso:country":"NL",
    "sg:address":"Televisieweg 48",
    "sg:city":"Almere",
    "sg:orig_category":"Autokeuringen",
    "sg:phone":"+31 36 536 1420",
    "sg:postcode":"1322 AM",
    "sg:province":"NL.",
    "wof:name":"Algemeen Autobedrijf Raymond",
    "wof:placetype":"venue"
},
  "geometry": {"coordinates":[5.182786,52.350727],"type":"Point"}
}