{
  "type": "Feature",
  "properties": {
    "addr:full":"Schapenlaan 36 'S Gravenhage Zuid-Holland 2512 HV",
    "addr:housenumber":"36",
    "addr:postcode":"2512 hv",
    "addr:street":"Schapenlaan;' S",
    "iso:country":"NL",
    "sg:address":"Schapenlaan 36",
    "sg:city":"'S Gravenhage",
    "sg:orig_category":"Loodgieterswerk, Verwarming And Sanitaire Installaties",
    "sg:phone":"+31 70 366 9062",
    "sg:postcode":"2512 HV",
    "sg:province":"Zuid-Holland",
    "wof:name":"Van Den Heuvel Verbouw",
    "wof:placetype":"venue"
},
  "geometry": {"coordinates":[4.297374,52.072895],"type":"Point"}
}