{
  "type": "Feature",
  "properties": {
    "addr:full":"Traay 78 Driebergen Rysenb Utrecht 3971 GR",
    "addr:housenumber":"78",
    "addr:postcode":"3971",
    "addr:street":"Traay;Rysenb",
    "iso:country":"NL",
    "sg:address":"Traay 78",
    "sg:city":"Driebergen Rysenb",
    "sg:orig_category":"Psychotherapeuten",
    "sg:phone":"+31 343 554 394",
    "sg:postcode":"3971 GR",
    "sg:province":"Utrecht",
    "wof:name":"Psychosociale Praktijk",
    "wof:placetype":"venue"
},
  "geometry": {"coordinates":[5.287743,52.053806],"type":"Point"}
}