{
  "type": "Feature",
  "properties": {
    "addr:full":"Lekdk 140 Langerak Zh South Holland 2967 GG",
    "addr:housenumber":"140;zh",
    "addr:postcode":"2967 gg",
    "iso:country":"NL",
    "sg:address":"Lekdk 140",
    "sg:city":"Langerak Zh",
    "sg:orig_category":"Oud Metaal",
    "sg:phone":"+31 184 601 373",
    "sg:postcode":"2967 GG",
    "sg:province":"South Holland",
    "wof:name":"Hartog, C Den",
    "wof:placetype":"venue"
},
  "geometry": {"coordinates":[4.8821029663,51.9358291626],"type":"Point"}
}