{
  "type": "Feature",
  "properties": {
    "addr:full":"Stadhouderspln 37 Rotterdam Zuid-Holland 3039 ER",
    "addr:housenumber":"37",
    "addr:postcode":"3039 er",
    "addr:street":"Stadhouderspln",
    "iso:country":"NL",
    "sg:address":"Stadhouderspln 37",
    "sg:city":"Rotterdam",
    "sg:orig_category":"Bibliotheken En Leeszalen Openbare",
    "sg:phone":"+31 10 467 7736",
    "sg:postcode":"3039 ER",
    "sg:province":"Zuid-Holland",
    "sg:website":"http://www.bibliotheek.rotterdam.nl",
    "wof:name":"Bibliotheek Rotterdam",
    "wof:placetype":"venue"
},
  "geometry": {"coordinates":[4.464878,51.931637],"type":"Point"}
}