{
  "type": "Feature",
  "properties": {
    "iso:country":"NL",
    "sg:address":"Emmeriksewg 415",
    "sg:city":"Zutphen",
    "sg:orig_category":"Autorijscholen",
    "sg:phone":"+31 575 530 033",
    "sg:postcode":"7206 DC",
    "sg:province":"Gelderland",
    "wof:name":"Animo",
    "wof:placetype":"venue"
},
  "geometry": {"coordinates":[6.199593,52.125175],"type":"Point"}
}