{
  "type": "Feature",
  "properties": {
    "addr:full":"Emmeriksewg 415 Zutphen Gelderland 7206 DC",
    "addr:housenumber":"415",
    "addr:postcode":"7206",
    "addr:street":"Gelderland",
    "iso:country":"NL",
    "sg:address":"Emmeriksewg 415",
    "sg:city":"Zutphen",
    "sg:orig_category":"Autorijscholen",
    "sg:phone":"+31 575 530 033",
    "sg:postcode":"7206 DC",
    "sg:province":"Gelderland",
    "wof:name":"Animo",
    "wof:placetype":"venue"
},
  "geometry": {"coordinates":[6.199593,52.125175],"type":"Point"}
}