{
  "type": "Feature",
  "properties": {
    "addr:full":"Jarmuiden 33A Amsterdam Noord-Holland 1046 AC",
    "addr:housenumber":"33a",
    "addr:postcode":"1046 ac",
    "addr:street":"Jarmuiden",
    "iso:country":"NL",
    "sg:address":"Jarmuiden 33A",
    "sg:city":"Amsterdam",
    "sg:classifiers":[
        {
            "category":"Professional",
            "type":"Services"
        }
    ],
    "sg:phone":"+31 20 611 8434",
    "sg:postcode":"1046 AC",
    "sg:province":"Noord-Holland",
    "sg:tags":[
        "leasing"
    ],
    "wof:name":"Contractpartners Cv",
    "wof:placetype":"venue"
},
  "geometry": {"coordinates":[4.793235,52.39077],"type":"Point"}
}