{
  "type": "Feature",
  "properties": {
    "addr:full":"Elmerinkwg 17 Deventer Overijssel 7421 ES",
    "addr:housenumber":"17",
    "addr:postcode":"7421 es",
    "addr:street":"Elmerinkwg",
    "iso:country":"NL",
    "sg:address":"Elmerinkwg 17",
    "sg:city":"Deventer",
    "sg:orig_category":"Autorijscholen",
    "sg:phone":"+31 570 634 660",
    "sg:postcode":"7421 ES",
    "sg:province":"Overijssel",
    "wof:name":"Voorrang Rijschool",
    "wof:placetype":"venue"
},
  "geometry": {"coordinates":[6.228135,52.245781],"type":"Point"}
}