{
  "type": "Feature",
  "properties": {
    "addr:full":"Achterzeedk 1/A Barendrecht Zuid-Holland 2991 SB",
    "addr:housenumber":"1 / a",
    "addr:postcode":"2991 sb",
    "addr:street":"Achterzeedk",
    "iso:country":"NL",
    "sg:address":"Achterzeedk 1/A",
    "sg:city":"Barendrecht",
    "sg:orig_category":"Jachthavens - Jachtwerven",
    "sg:phone":"+31 78 677 2445",
    "sg:postcode":"2991 SB",
    "sg:province":"Zuid-Holland",
    "sg:website":"http://www.marinabarendrecht.nl",
    "wof:name":"Marina Barendrecht",
    "wof:placetype":"venue"
},
  "geometry": {"coordinates":[4.54911,51.83363],"type":"Point"}
}