{
  "type": "Feature",
  "properties": {
    "iso:country":"NL",
    "sg:address":"Kl Berg 28",
    "sg:city":"Eindhoven",
    "sg:orig_category":"Boeken En Tijdschriften",
    "sg:phone":"+31 40 244 7714",
    "sg:postcode":"5611 JV",
    "sg:province":"North Brabant",
    "sg:website":"http://www.heremiet.nl",
    "wof:name":"Heremiet, De",
    "wof:placetype":"venue"
},
  "geometry": {"coordinates":[5.476552,51.436584],"type":"Point"}
}