{
  "type": "Feature",
  "properties": {
    "addr:full":"Haarstr 15 Tuil Gelderland 4176 BK",
    "addr:housenumber":"15",
    "addr:postcode":"4176 bk",
    "addr:street":"Haarstr;Gelderland",
    "iso:country":"NL",
    "sg:address":"Haarstr 15",
    "sg:city":"Tuil",
    "sg:orig_category":"Wegmarkering",
    "sg:phone":"+31 418 594 190",
    "sg:postcode":"4176 BK",
    "sg:province":"Gelderland",
    "wof:name":"Pelle Bv",
    "wof:placetype":"venue"
},
  "geometry": {"coordinates":[5.2426071167,51.8247337341],"type":"Point"}
}