{
  "type": "Feature",
  "properties": {
    "addr:full":"Dijkgraafsewg 48C Wageningen Gelderland 6707 EM",
    "addr:housenumber":"48c",
    "addr:postcode":"6707 em",
    "addr:street":"Dijkgraafsewg;Gelderland",
    "iso:country":"NL",
    "sg:address":"Dijkgraafsewg 48C",
    "sg:city":"Wageningen",
    "sg:orig_category":"Kaas",
    "sg:phone":"+31 317 416 411",
    "sg:postcode":"6707 EM",
    "sg:province":"Gelderland",
    "wof:name":"Breunissen, H J",
    "wof:placetype":"venue"
},
  "geometry": {"coordinates":[5.6629390717,51.971408844],"type":"Point"}
}