{
  "type": "Feature",
  "properties": {
    "addr:full":"Abram V Rijckevorselweg 7 Capelle A/D Ijssel South Holland 2909 LB",
    "addr:housenumber":"7;a / d",
    "addr:postcode":"2909 lb",
    "addr:street":"Abram V Rijckevorselweg;Ijssel South",
    "iso:country":"NL",
    "sg:address":"Abram V Rijckevorselweg 7",
    "sg:city":"Capelle A/D Ijssel",
    "sg:orig_category":"Autokeuringen",
    "sg:phone":"+31 10 447 0055",
    "sg:postcode":"2909 LB",
    "sg:province":"South Holland",
    "wof:name":"Q8 Rivium Noord",
    "wof:placetype":"venue"
},
  "geometry": {"coordinates":[4.54499,51.917171],"type":"Point"}
}