{
  "type": "Feature",
  "properties": {
    "addr:full":"Deventerstraat 26 Vaassen Gelderland 8171 AE",
    "addr:housenumber":"26",
    "addr:postcode":"8171 ae",
    "addr:street":"Deventerstraat;Gelderland",
    "iso:country":"NL",
    "sg:address":"Deventerstraat 26",
    "sg:city":"Vaassen",
    "sg:orig_category":"Bloemen And Planten",
    "sg:phone":"+31 578 571 307",
    "sg:postcode":"8171 AE",
    "sg:province":"Gelderland",
    "wof:name":"Labberton Bloemenhuis",
    "wof:placetype":"venue"
},
  "geometry": {"coordinates":[5.972513,52.289864],"type":"Point"}
}