{
  "type": "Feature",
  "properties": {
    "addr:full":"Rijckevorsel V Kesselln 1 Sint Oedenrode Noord-Brabant 5491 GD",
    "addr:housenumber":"1;oedenrode",
    "addr:postcode":"5491 gd",
    "addr:street":"Rijckevorsel;Kesselln",
    "iso:country":"NL",
    "sg:address":"Rijckevorsel V Kesselln 1",
    "sg:city":"Sint Oedenrode",
    "sg:orig_category":"Woningbouwverenigingen",
    "sg:phone":"+31 413 476 910",
    "sg:postcode":"5491 GD",
    "sg:province":"Noord-Brabant",
    "wof:name":"Woningbouwvereniging Sint Oedenrode",
    "wof:placetype":"venue"
},
  "geometry": {"coordinates":[5.4071850777,51.5804748535],"type":"Point"}
}