{
  "type": "Feature",
  "properties": {
    "addr:full":"Oude Vismarkt 9 Culemborg Gelderland 4101 CA",
    "addr:housenumber":"9",
    "addr:postcode":"4101 ca",
    "addr:street":"Oude Vismarkt;Gelderland",
    "iso:country":"NL",
    "sg:address":"Oude Vismarkt 9",
    "sg:city":"Culemborg",
    "sg:orig_category":"Huishoudelijke Apparaten En Artikelen",
    "sg:phone":"+31 345 530 837",
    "sg:postcode":"4101 CA",
    "sg:province":"Gelderland",
    "wof:name":"Marskramer Bv",
    "wof:placetype":"venue"
},
  "geometry": {"coordinates":[5.22472,51.958473],"type":"Point"}
}