{
  "type": "Feature",
  "properties": {
    "addr:full":"Edisonstr 6 S Gravenhage South Holland 2561 BE",
    "addr:housenumber":"6",
    "addr:postcode":"2561",
    "addr:street":"Edisonstr;S Gravenhage",
    "iso:country":"NL",
    "sg:address":"Edisonstr 6",
    "sg:city":"S Gravenhage",
    "sg:orig_category":"Postzegels",
    "sg:phone":"+31 70 392 5409",
    "sg:postcode":"2561 BE",
    "sg:province":"South Holland",
    "wof:name":"Embe Stamps Bv",
    "wof:placetype":"venue"
},
  "geometry": {"coordinates":[4.27581,52.074532],"type":"Point"}
}