{
  "type": "Feature",
  "properties": {
    "iso:country":"NL",
    "sg:address":"Plantlustweg 5",
    "sg:city":"Serooskerke Walcheren",
    "sg:orig_category":"Fruit And Groenten Gh",
    "sg:phone":"+31 118 628 194",
    "sg:postcode":"4353 SC",
    "sg:province":"Zeeland",
    "wof:name":"Boomgaard De Zoete Kers",
    "wof:placetype":"venue"
},
  "geometry": {"coordinates":[3.608379,51.56266],"type":"Point"}
}