{
  "type": "Feature",
  "properties": {
    "addr:full":"Ruige Weide 41 Oudewater Utrecht 3421 TH",
    "addr:housenumber":"41",
    "addr:postcode":"3421 th",
    "addr:street":"Ruige Weide",
    "iso:country":"NL",
    "sg:address":"Ruige Weide 41",
    "sg:city":"Oudewater",
    "sg:orig_category":"Partycatering And -Organisatie",
    "sg:phone":"+31 348 562 801",
    "sg:postcode":"3421 TH",
    "sg:province":"Utrecht",
    "wof:name":"De Toverkol",
    "wof:placetype":"venue"
},
  "geometry": {"coordinates":[4.84891,52.033066],"type":"Point"}
}