{
  "type": "Feature",
  "properties": {
    "addr:full":"2E Lambertusstr 10/A Venlo Limburg 5921 HX",
    "addr:housenumber":"10 / a",
    "addr:postcode":"5921 hx",
    "addr:street":"2E Lambertusstr",
    "iso:country":"NL",
    "sg:address":"2E Lambertusstr 10/A",
    "sg:city":"Venlo",
    "sg:orig_category":"Fitnesscentra",
    "sg:phone":"+31 77 387 2916",
    "sg:postcode":"5921 HX",
    "sg:province":"Limburg",
    "wof:name":"Blariacum Fitness & Sportcentrum",
    "wof:placetype":"venue"
},
  "geometry": {"coordinates":[6.152612,51.370289],"type":"Point"}
}