{
  "type": "Feature",
  "properties": {
    "iso:country":"NL",
    "sg:address":"Dukaatstraat 13",
    "sg:city":"Oosterhout Nb",
    "sg:orig_category":"Metaalbekleding And -Behandeling",
    "sg:phone":"+31 162 457 744",
    "sg:postcode":"4903 RN",
    "sg:province":"North Brabant",
    "wof:name":"Staalbouw Brabant Bv",
    "wof:placetype":"venue"
},
  "geometry": {"coordinates":[4.870225,51.621567],"type":"Point"}
}