{
  "type": "Feature",
  "properties": {
    "addr:full":"Kan Pelsstr 10 Nymegen Gelderland 6525 VX",
    "addr:housenumber":"10",
    "addr:postcode":"6525 vx",
    "addr:street":"Nymegen Gelderland",
    "iso:country":"NL",
    "sg:address":"Kan Pelsstr 10",
    "sg:city":"Nymegen",
    "sg:orig_category":"Leesportefeuilles",
    "sg:phone":"+31 24 355 6731",
    "sg:postcode":"6525 VX",
    "sg:province":"Gelderland",
    "wof:name":"Schraven",
    "wof:placetype":"venue"
},
  "geometry": {"coordinates":[-98.320213,38.498058],"type":"Point"}
}