{
  "type": "Feature",
  "properties": {
    "addr:full":"Elspeterweg 43 Vaassen Gelderland 8171 ES",
    "addr:housenumber":"43",
    "addr:postcode":"8171 es",
    "addr:street":"Elspeterweg;Gelderland",
    "iso:country":"NL",
    "sg:address":"Elspeterweg 43",
    "sg:city":"Vaassen",
    "sg:orig_category":"Kampeerterreinen",
    "sg:phone":"+31 578 571 343",
    "sg:postcode":"8171 ES",
    "sg:province":"Gelderland",
    "wof:name":"Oordt Ballooning De Bosrand",
    "wof:placetype":"venue"
},
  "geometry": {"coordinates":[5.9438199997,52.284778595],"type":"Point"}
}