{
  "type": "Feature",
  "properties": {
    "addr:full":"Antillen 50 Apeldoorn Gelderland 7333 PG",
    "addr:housenumber":"50",
    "addr:postcode":"7333",
    "addr:street":"Antillen;Gelderland;Pg",
    "iso:country":"NL",
    "sg:address":"Antillen 50",
    "sg:city":"Apeldoorn",
    "sg:orig_category":"Verf En Lak - Fabrieken En Groothandel",
    "sg:phone":"+31 55 538 0480",
    "sg:postcode":"7333 PG",
    "sg:province":"Gelderland",
    "sg:website":"http://www.brouwervanveen.nl",
    "wof:name":"Brouwer & Van Veen Bv",
    "wof:placetype":"venue"
},
  "geometry": {"coordinates":[5.976136,52.181046],"type":"Point"}
}