{
  "type": "Feature",
  "properties": {
    "addr:full":"Bakenessergracht 30 Haarlem Noord-Holland 2011 JW",
    "addr:housenumber":"30",
    "addr:postcode":"2011 jw",
    "addr:street":"Bakenessergracht",
    "iso:country":"NL",
    "sg:address":"Bakenessergracht 30",
    "sg:city":"Haarlem",
    "sg:orig_category":"Krantenuitgeverijen",
    "sg:phone":"+31 23 534 0106",
    "sg:postcode":"2011 JW",
    "sg:province":"Noord-Holland",
    "wof:name":"Judo Magazine",
    "wof:placetype":"venue"
},
  "geometry": {"coordinates":[4.63963,52.382767],"type":"Point"}
}