{
  "type": "Feature",
  "properties": {
    "addr:full":"Lionstr 9B Arnemuiden Zeeland 4341 EL",
    "addr:housenumber":"9b",
    "addr:postcode":"4341 el",
    "addr:street":"Lionstr",
    "iso:country":"NL",
    "sg:address":"Lionstr 9B",
    "sg:city":"Arnemuiden",
    "sg:orig_category":"Duiven En Duivensport - Artikelen",
    "sg:phone":"+31 118 602 566",
    "sg:postcode":"4341 EL",
    "sg:province":"Zeeland",
    "wof:name":"Voorwaarts Postduivenver, De",
    "wof:placetype":"venue"
},
  "geometry": {"coordinates":[3.672465,51.500275],"type":"Point"}
}