{
  "type": "Feature",
  "properties": {
    "iso:country":"NL",
    "sg:address":"Hallsedk 12",
    "sg:city":"Tonden",
    "sg:orig_category":"Ongediertebestrijding En Ontsmetting",
    "sg:phone":"+31 575 476 412",
    "sg:postcode":"6975 AK",
    "sg:province":"Gelderland",
    "wof:name":"Stevens",
    "wof:placetype":"venue"
},
  "geometry": {"coordinates":[6.109681,52.127548],"type":"Point"}
}