{
  "type": "Feature",
  "properties": {
    "addr:full":"Kerkstraat 302 Brunssum Limburg 6441 BM",
    "addr:housenumber":"302",
    "addr:postcode":"6441 bm",
    "addr:street":"Kerkstraat",
    "iso:country":"NL",
    "sg:address":"Kerkstraat 302",
    "sg:city":"Brunssum",
    "sg:orig_category":"Paramedische Behandelingen",
    "sg:phone":"+31 45 527 4190",
    "sg:postcode":"6441 BM",
    "sg:province":"Limburg",
    "wof:name":"Logopedie Maatschap Mantelers En Nijssen",
    "wof:placetype":"venue"
},
  "geometry": {"coordinates":[5.972544,50.948284],"type":"Point"}
}