{
  "type": "Feature",
  "properties": {
    "iso:country":"NL",
    "sg:address":"Johannes Verhulststraat 182",
    "sg:city":"Amsterdam",
    "sg:orig_category":"Bedrijfs- And Managementsconsultants",
    "sg:phone":"+31 20 675 4920",
    "sg:postcode":"1075 HD",
    "sg:province":"North Holland",
    "wof:name":"Bokhorst Service Bv",
    "wof:placetype":"venue"
},
  "geometry": {"coordinates":[4.867313,52.353333],"type":"Point"}
}