{
  "type": "Feature",
  "properties": {
    "iso:country":"NL",
    "sg:address":"W Sluyterstr 30",
    "sg:city":"Eibergen",
    "sg:orig_category":"Vakantieverblijven",
    "sg:phone":"+31 545 473 042",
    "sg:postcode":"7151 VA",
    "sg:province":"Gelderland",
    "wof:name":"Woord, G J Ter",
    "wof:placetype":"venue"
},
  "geometry": {"coordinates":[6.650114,52.102818],"type":"Point"}
}