{
  "type": "Feature",
  "properties": {
    "addr:full":"Cederstr 32 Ymuiden North Holland 1971 KD",
    "addr:housenumber":"32",
    "addr:postcode":"1971 kd",
    "addr:street":"Cederstr",
    "iso:country":"NL",
    "sg:address":"Cederstr 32",
    "sg:city":"Ymuiden",
    "sg:orig_category":"Bloemen En Planten",
    "sg:phone":"+31 255 514 831",
    "sg:postcode":"1971 KD",
    "sg:province":"North Holland",
    "wof:name":"Mulder'S Bloemenhuis",
    "wof:placetype":"venue"
},
  "geometry": {"coordinates":[4.629922,52.455994],"type":"Point"}
}