{
  "type": "Feature",
  "properties": {
    "iso:country":"NL",
    "sg:address":"Korte Waarder 45",
    "sg:city":"Nieuwerbrug",
    "sg:orig_category":"Huizensloop And Bouwrijp Maken",
    "sg:phone":"+31 348 688 297",
    "sg:postcode":"2415 AT",
    "sg:province":"Zuid-Holland",
    "wof:name":"W Verburg",
    "wof:placetype":"venue"
},
  "geometry": {"coordinates":[4.822541,52.074905],"type":"Point"}
}