{
  "type": "Feature",
  "properties": {
    "iso:country":"NL",
    "sg:address":"Jan Van Renesseplein 1",
    "sg:city":"Gouda",
    "sg:orig_category":"Volwassenenonderwijs",
    "sg:phone":"+31 182 599 517",
    "sg:postcode":"2805 GT",
    "sg:province":"Zuid-Holland",
    "wof:name":"Coornhert Gymnasium",
    "wof:placetype":"venue"
},
  "geometry": {"coordinates":[4.719428,52.021896],"type":"Point"}
}