{
  "type": "Feature",
  "properties": {
    "addr:full":"Heuvel 4 Oosterhout Nb Noord-Brabant 4901 KC",
    "addr:housenumber":"4",
    "addr:postcode":"4901 kc",
    "addr:street":"Heuvel",
    "iso:country":"NL",
    "sg:address":"Heuvel 4",
    "sg:city":"Oosterhout Nb",
    "sg:orig_category":"Makelaars In Onroerend Goed",
    "sg:phone":"+31 162 472 950",
    "sg:postcode":"4901 KC",
    "sg:province":"Noord-Brabant",
    "wof:name":"Biemans Bv",
    "wof:placetype":"venue"
},
  "geometry": {"coordinates":[4.856665,51.643181],"type":"Point"}
}