{
  "type": "Feature",
  "properties": {
    "iso:country":"NL",
    "sg:address":"Heuvel 4",
    "sg:city":"Oosterhout Nb",
    "sg:orig_category":"Makelaars In Onroerend Goed",
    "sg:phone":"+31 162 472 950",
    "sg:postcode":"4901 KC",
    "sg:province":"Noord-Brabant",
    "wof:name":"Biemans Bv",
    "wof:placetype":"venue"
},
  "geometry": {"coordinates":[4.856665,51.643181],"type":"Point"}
}