{
  "type": "Feature",
  "properties": {
    "addr:full":"Zwollewg 1 Almere Flevoland 1324 EL",
    "addr:housenumber":"1;1324",
    "addr:postcode":"el",
    "addr:street":"Zwollewg;Flevoland",
    "iso:country":"NL",
    "sg:address":"Zwollewg 1",
    "sg:city":"Almere",
    "sg:orig_category":"Scholen Voor Algemeen Voortgezet Onderwijs",
    "sg:phone":"+31 36 533 1220",
    "sg:postcode":"1324 EL",
    "sg:province":"Flevoland",
    "wof:name":"Echnaton",
    "wof:placetype":"venue"
},
  "geometry": {"coordinates":[5.211798,52.367393],"type":"Point"}
}