{
  "type": "Feature",
  "properties": {
    "addr:full":"Schout Bigotln 4 S Hertogenbosch Noord-Brabant 5237 WE",
    "addr:housenumber":"4",
    "addr:postcode":"5237 we",
    "addr:street":"Schout Bigotln",
    "iso:country":"NL",
    "sg:address":"Schout Bigotln 4",
    "sg:city":"S Hertogenbosch",
    "sg:orig_category":"Kinderkleding",
    "sg:phone":"+31 73 642 9622",
    "sg:postcode":"5237 WE",
    "sg:province":"Noord-Brabant",
    "sg:website":"http://www.kinderbazar.nl",
    "wof:name":"Kinderbazar Nl",
    "wof:placetype":"venue"
},
  "geometry": {"coordinates":[5.277646,51.73679],"type":"Point"}
}