{
  "type": "Feature",
  "properties": {
    "iso:country":"NL",
    "sg:address":"De Grens 21",
    "sg:city":"Heijen",
    "sg:orig_category":"Goederenvervoer Over De Weg",
    "sg:phone":"+31 485 490 200",
    "sg:postcode":"6598 DK",
    "sg:province":"Limburg",
    "wof:name":"Noy Logistics Bv",
    "wof:placetype":"venue"
},
  "geometry": {"coordinates":[5.995591,51.662468],"type":"Point"}
}