{
  "type": "Feature",
  "properties": {
    "iso:country":"NL",
    "sg:address":"Ziedewydsedk 41/43",
    "sg:city":"Barendrecht",
    "sg:classifiers":[
        {
            "category":"Food & Beverages",
            "subcategory":"Fruits & Vegetables",
            "type":"Retail Goods"
        }
    ],
    "sg:phone":"+31 180 611 655",
    "sg:postcode":"2991 VP",
    "sg:province":"South Holland",
    "sg:tags":[
        "en",
        "groenten"
    ],
    "wof:name":"Vermaas, H",
    "wof:placetype":"venue"
},
  "geometry": {"coordinates":[4.54064,51.853176],"type":"Point"}
}