{
  "type": "Feature",
  "properties": {
    "addr:full":"Ramsbrugweg 14 Wenum Wiesel Gelderland 7345 DW",
    "addr:housenumber":"14",
    "addr:postcode":"7345 dw",
    "addr:street":"Ramsbrugweg",
    "iso:country":"NL",
    "sg:address":"Ramsbrugweg 14",
    "sg:city":"Wenum Wiesel",
    "sg:orig_category":"Begrafenisondernemers",
    "sg:phone":"+31 55 312 1380",
    "sg:postcode":"7345 DW",
    "sg:province":"Gelderland",
    "wof:name":"Wenum",
    "wof:placetype":"venue"
},
  "geometry": {"coordinates":[5.960265,52.265598],"type":"Point"}
}