{
  "type": "Feature",
  "properties": {
    "addr:full":"Leuvenstraat 89 Amsterdam Noord-Holland 1066 DZ",
    "addr:housenumber":"89",
    "addr:postcode":"1066 dz",
    "addr:street":"Leuvenstraat",
    "iso:country":"NL",
    "sg:address":"Leuvenstraat 89",
    "sg:city":"Amsterdam",
    "sg:orig_category":"Marktonderzoekbureaus",
    "sg:phone":"+31 20 615 1855",
    "sg:postcode":"1066 DZ",
    "sg:province":"Noord-Holland",
    "wof:name":"Care 4 More",
    "wof:placetype":"venue"
},
  "geometry": {"coordinates":[4.819988,52.346104],"type":"Point"}
}