{
  "type": "Feature",
  "properties": {
    "addr:full":"Hoofdwg 1 Burdaard Provincie Friesland 9112 HG",
    "addr:housenumber":"1",
    "addr:postcode":"9112 hg",
    "addr:street":"Hoofdwg;Provincie Friesland",
    "iso:country":"NL",
    "sg:address":"Hoofdwg 1",
    "sg:city":"Burdaard",
    "sg:orig_category":"Verenigingsgebouwen",
    "sg:phone":"+31 519 332 705",
    "sg:postcode":"9112 HG",
    "sg:province":"Provincie Friesland",
    "wof:name":"Pitch, The",
    "wof:placetype":"venue"
},
  "geometry": {"coordinates":[5.879771,53.293659],"type":"Point"}
}