{
  "type": "Feature",
  "properties": {
    "addr:full":"Postbus 1318 Aalsmeer Flevoland 1430 BH",
    "addr:housenumber":"1318",
    "addr:postcode":"1430 bh",
    "addr:street":"Postbus;Flevoland",
    "iso:country":"NL",
    "sg:address":"Postbus 1318",
    "sg:city":"Aalsmeer",
    "sg:orig_category":"Bloemen En Planten - Groothandel",
    "sg:phone":"+31 297 342 749",
    "sg:postcode":"1430 BH",
    "sg:province":"Flevoland",
    "wof:name":"Dai Ichi Holl",
    "wof:placetype":"venue"
},
  "geometry": {"coordinates":[4.749068,52.266991],"type":"Point"}
}