{
  "type": "Feature",
  "properties": {
    "addr:full":"Van Hardenbroeklaan 17 Bunnik Utrecht 3981 EN",
    "addr:housenumber":"17",
    "addr:postcode":"3981 en",
    "addr:street":"Van Hardenbroeklaan",
    "iso:country":"NL",
    "sg:address":"Van Hardenbroeklaan 17",
    "sg:city":"Bunnik",
    "sg:orig_category":"Partycatering And -Organisatie",
    "sg:phone":"+31 30 656 2550",
    "sg:postcode":"3981 EN",
    "sg:province":"Utrecht",
    "wof:name":"Henk Lotgering",
    "wof:placetype":"venue"
},
  "geometry": {"coordinates":[5.199053,52.06823],"type":"Point"}
}