{
  "type": "Feature",
  "properties": {
    "addr:full":"V Stolkwg 31 S Gravenhage Zuid-Holland 2585 JN",
    "addr:housenumber":"31;gravenhage",
    "addr:postcode":"2585 jn",
    "addr:street":"S",
    "iso:country":"NL",
    "sg:address":"V Stolkwg 31",
    "sg:city":"S Gravenhage",
    "sg:orig_category":"Verenigingen En Stichtingen",
    "sg:phone":"+31 70 358 9331",
    "sg:postcode":"2585 JN",
    "sg:province":"Zuid-Holland",
    "sg:website":"http://www.nao.nl",
    "wof:name":"Ned Aardappel Org",
    "wof:placetype":"venue"
},
  "geometry": {"coordinates":[4.29777,52.094799],"type":"Point"}
}