{
  "type": "Feature",
  "properties": {
    "iso:country":"NL",
    "sg:address":"Simon Bolivarstraat 67",
    "sg:city":"Utrecht",
    "sg:orig_category":"Bedrijfs- And Managementsconsultants",
    "sg:phone":"+31 30 273 2857",
    "sg:postcode":"3573 ZK",
    "sg:province":"Utrecht",
    "wof:name":"Auryn",
    "wof:placetype":"venue"
},
  "geometry": {"coordinates":[5.148943,52.109035],"type":"Point"}
}