{
  "type": "Feature",
  "properties": {
    "addr:full":"Sint Barbaraplein 23 Oss Noord-Brabant 5341 LK",
    "addr:housenumber":"23",
    "addr:postcode":"5341 lk",
    "addr:street":"Sint Barbaraplein",
    "iso:country":"NL",
    "sg:address":"Sint Barbaraplein 23",
    "sg:city":"Oss",
    "sg:orig_category":"Boekhouders",
    "sg:phone":"+31 412 630 450",
    "sg:postcode":"5341 LK",
    "sg:province":"Noord-Brabant",
    "wof:name":"Administratiekantoor Ariaans Bv",
    "wof:placetype":"venue"
},
  "geometry": {"coordinates":[-77.235214,38.312599],"type":"Point"}
}