{
  "type": "Feature",
  "properties": {
    "addr:full":"Walderstraat 28 Lochem Gelderland 7241 BJ",
    "addr:housenumber":"28",
    "addr:postcode":"7241 bj",
    "addr:street":"Walderstraat;Gelderland",
    "iso:country":"NL",
    "sg:address":"Walderstraat 28",
    "sg:city":"Lochem",
    "sg:orig_category":"Artiesten",
    "sg:phone":"+31 573 253 830",
    "sg:postcode":"7241 BJ",
    "sg:province":"Gelderland",
    "wof:name":"J De La Rie",
    "wof:placetype":"venue"
},
  "geometry": {"coordinates":[6.412852,52.162407],"type":"Point"}
}