{
  "type": "Feature",
  "properties": {
    "addr:full":"Bosstraat 3 Bergen Op Zoom Noord-Brabant 4611 NA",
    "addr:housenumber":"3",
    "addr:postcode":"4611 na",
    "addr:street":"Bosstraat",
    "iso:country":"NL",
    "sg:address":"Bosstraat 3",
    "sg:city":"Bergen Op Zoom",
    "sg:orig_category":"Huishoudapparatuur, Televisies And Radio'S",
    "sg:phone":"+31 164 244 916",
    "sg:postcode":"4611 NA",
    "sg:province":"Noord-Brabant",
    "wof:name":"Expert Van Vliet",
    "wof:placetype":"venue"
},
  "geometry": {"coordinates":[4.281987,51.495953],"type":"Point"}
}