{
  "type": "Feature",
  "properties": {
    "iso:country":"NL",
    "sg:address":"J Douwamastr 1",
    "sg:city":"Sneek",
    "sg:orig_category":"Huishoudelijke Apparaten En Artikelen",
    "sg:phone":"+31 515 413 535",
    "sg:postcode":"8602 BJ",
    "sg:province":"Friesland",
    "wof:name":"Sneuphoek, De",
    "wof:placetype":"venue"
},
  "geometry": {"coordinates":[5.659516,53.040665],"type":"Point"}
}