{
  "type": "Feature",
  "properties": {
    "addr:full":"Osdorperweg 547 Amsterdam Noord-Holland 1067 ST",
    "addr:housenumber":"547",
    "addr:postcode":"1067 st",
    "addr:street":"Osdorperweg",
    "iso:country":"NL",
    "sg:address":"Osdorperweg 547",
    "sg:city":"Amsterdam",
    "sg:orig_category":"Autokeuringen",
    "sg:phone":"+31 20 619 0087",
    "sg:postcode":"1067 ST",
    "sg:province":"Noord-Holland",
    "wof:name":"E.M. Van Der Laan En Zoon",
    "wof:placetype":"venue"
},
  "geometry": {"coordinates":[4.783351,52.367226],"type":"Point"}
}