{
  "type": "Feature",
  "properties": {
    "addr:full":"Frambozenweg 43 Leiden Zuid-Holland 2321 KA",
    "addr:housenumber":"43",
    "addr:postcode":"2321 ka",
    "addr:street":"Frambozenweg",
    "iso:country":"NL",
    "sg:address":"Frambozenweg 43",
    "sg:city":"Leiden",
    "sg:classifiers":[
        {
            "category":"Retail",
            "subcategory":"Storage",
            "type":"Services"
        }
    ],
    "sg:phone":"+31 71 576 9256",
    "sg:postcode":"2321 KA",
    "sg:province":"Zuid-Holland",
    "sg:tags":[
        "opslag",
        "bewaring"
    ],
    "wof:name":"Storematch",
    "wof:placetype":"venue"
},
  "geometry": {"coordinates":[4.488699913,52.1473617554],"type":"Point"}
}