{
  "type": "Feature",
  "properties": {
    "addr:full":"Wateringseweg 5 Poeldijk Zuid-Holland 2685 SP",
    "addr:housenumber":"5",
    "addr:postcode":"2685 sp",
    "addr:street":"Wateringseweg",
    "iso:country":"NL",
    "sg:address":"Wateringseweg 5",
    "sg:city":"Poeldijk",
    "sg:orig_category":"Bloemen And Planten",
    "sg:phone":"+31 174 245 572",
    "sg:postcode":"2685 SP",
    "sg:province":"Zuid-Holland",
    "wof:name":"Handelskwekerijen M.C.M. Enthoven",
    "wof:placetype":"venue"
},
  "geometry": {"coordinates":[4.228783,52.022163],"type":"Point"}
}