{
  "type": "Feature",
  "properties": {
    "addr:full":"Vosberg 13 Panningen Limburg 5981 NL",
    "addr:housenumber":"13",
    "addr:postcode":"5981 nl",
    "addr:street":"Vosberg",
    "iso:country":"NL",
    "sg:address":"Vosberg 13",
    "sg:city":"Panningen",
    "sg:orig_category":"Land- En Tuinbouw - Loonbedrijven",
    "sg:phone":"+31 77 307 1447",
    "sg:postcode":"5981 NL",
    "sg:province":"Limburg",
    "wof:name":"Peeters, Gebr",
    "wof:placetype":"venue"
},
  "geometry": {"coordinates":[5.979119,51.340305],"type":"Point"}
}