{
  "type": "Feature",
  "properties": {
    "addr:full":"Meentsestraat 63 Giesbeek Gelderland 6987 CK",
    "addr:housenumber":"63",
    "addr:postcode":"6987 ck",
    "addr:street":"Meentsestraat;Gelderland",
    "iso:country":"NL",
    "sg:address":"Meentsestraat 63",
    "sg:city":"Giesbeek",
    "sg:orig_category":"Drukkerijen And Copyshops",
    "sg:phone":"+31 313 631 498",
    "sg:postcode":"6987 CK",
    "sg:province":"Gelderland",
    "wof:name":"Sima-Druk",
    "wof:placetype":"venue"
},
  "geometry": {"coordinates":[6.064447,51.992512],"type":"Point"}
}