{
  "type": "Feature",
  "properties": {
    "iso:country":"NL",
    "sg:address":"W. M. Dudokweg 36",
    "sg:city":"Heerhugowaard",
    "sg:orig_category":"Onderhoud And Reparatie Kantoorapparatuur",
    "sg:phone":"+31 72 574 5407",
    "sg:postcode":"1703 DB",
    "sg:province":"Noord-Holland",
    "wof:name":"Votronics",
    "wof:placetype":"venue"
},
  "geometry": {"coordinates":[4.81755,52.666378],"type":"Point"}
}