{
  "type": "Feature",
  "properties": {
    "addr:full":"Havenwg 13 Waalwyk North Brabant 5145 NJ",
    "addr:housenumber":"13",
    "addr:postcode":"5145 nj",
    "addr:street":"Havenwg",
    "iso:country":"NL",
    "sg:address":"Havenwg 13",
    "sg:city":"Waalwyk",
    "sg:orig_category":"Banden",
    "sg:phone":"+31 416 335 029",
    "sg:postcode":"5145 NJ",
    "sg:province":"North Brabant",
    "sg:website":"http://www.profile.nl",
    "wof:name":"Profile Tyrecenter De Hoeve",
    "wof:placetype":"venue"
},
  "geometry": {"coordinates":[5.048317,51.693687],"type":"Point"}
}