{
  "type": "Feature",
  "properties": {
    "addr:full":"2E Jachthaven Ab 4 Ab Dordrecht Zuid-Holland 3312 AZ",
    "addr:housenumber":"4 ab",
    "addr:postcode":"3312 az",
    "addr:street":"2E Jachthaven Ab",
    "iso:country":"NL",
    "sg:address":"2E Jachthaven Ab 4 Ab",
    "sg:city":"Dordrecht",
    "sg:orig_category":"Verenigingen En Stichtingen",
    "sg:phone":"+31 78 613 8777",
    "sg:postcode":"3312 AZ",
    "sg:province":"Zuid-Holland",
    "wof:name":"Waterlust",
    "wof:placetype":"venue"
},
  "geometry": {"coordinates":[4.656506,51.811916],"type":"Point"}
}