{
  "type": "Feature",
  "properties": {
    "iso:country":"NL",
    "sg:address":"St. Martinusstraat 33",
    "sg:city":"Rucphen",
    "sg:orig_category":"Fietshandelaren",
    "sg:phone":"+31 165 343 335",
    "sg:postcode":"4715 AG",
    "sg:province":"Noord-Brabant",
    "wof:name":"Martens Tweewielers",
    "wof:placetype":"venue"
},
  "geometry": {"coordinates":[4.555501,51.535431],"type":"Point"}
}