{
  "type": "Feature",
  "properties": {
    "iso:country":"NL",
    "sg:address":"Willem Knaapenstraat 16",
    "sg:city":"Geldrop",
    "sg:orig_category":"Boekhouders",
    "sg:phone":"+31 40 286 8039",
    "sg:postcode":"5666 TN",
    "sg:province":"Noord-Brabant",
    "wof:name":"Administratie- En Advieskantoor Redt",
    "wof:placetype":"venue"
},
  "geometry": {"coordinates":[5.570756,51.426586],"type":"Point"}
}