{
  "type": "Feature",
  "properties": {
    "addr:full":"Rondostraat 88 Enschede Overijssel 7534 GK",
    "addr:housenumber":"88",
    "addr:postcode":"7534 gk",
    "addr:street":"Rondostraat",
    "iso:country":"NL",
    "sg:address":"Rondostraat 88",
    "sg:city":"Enschede",
    "sg:orig_category":"Binnenhuisarchitecten",
    "sg:phone":"+31 53 461 4284",
    "sg:postcode":"7534 GK",
    "sg:province":"Overijssel",
    "wof:name":"Venn. Ond. Fa. Ruud Waltmann Interieurar",
    "wof:placetype":"venue"
},
  "geometry": {"coordinates":[6.965918,52.208736],"type":"Point"}
}