{
  "type": "Feature",
  "properties": {
    "iso:country":"NL",
    "sg:address":"Rondostraat 88",
    "sg:city":"Enschede",
    "sg:orig_category":"Binnenhuisarchitecten",
    "sg:phone":"+31 53 461 4284",
    "sg:postcode":"7534 GK",
    "sg:province":"Overijssel",
    "wof:name":"Venn. Ond. Fa. Ruud Waltmann Interieurar",
    "wof:placetype":"venue"
},
  "geometry": {"coordinates":[6.965918,52.208736],"type":"Point"}
}