{
  "type": "Feature",
  "properties": {
    "addr:full":"St Josephstr 3 Meerssen Limburg 6231 EC",
    "addr:housenumber":"3",
    "addr:postcode":"6231 ec",
    "iso:country":"NL",
    "sg:address":"St Josephstr 3",
    "sg:city":"Meerssen",
    "sg:orig_category":"Makelaars En Adviseurs Onroerende Goederen",
    "sg:phone":"+31 43 364 7272",
    "sg:postcode":"6231 EC",
    "sg:province":"Limburg",
    "wof:name":"Pinxt Bv",
    "wof:placetype":"venue"
},
  "geometry": {"coordinates":[5.744903,50.886543],"type":"Point"}
}