{
  "type": "Feature",
  "properties": {
    "addr:full":"Springw 162 Utrecht Utrecht 3511 VZ",
    "addr:housenumber":"162",
    "addr:postcode":"3511 vz",
    "iso:country":"NL",
    "sg:address":"Springw 162",
    "sg:city":"Utrecht",
    "sg:orig_category":"Verenigingen En Stichtingen",
    "sg:phone":"+31 30 231 4117",
    "sg:postcode":"3511 VZ",
    "sg:province":"Utrecht",
    "wof:name":"Zending En Opwekking, Sticht",
    "wof:placetype":"venue"
},
  "geometry": {"coordinates":[5.120868,52.085438],"type":"Point"}
}