{
  "type": "Feature",
  "properties": {
    "addr:full":"Middelsluissedijk Oz 74 Numansdorp Zuid-Holland 3281 LE",
    "addr:housenumber":"74",
    "addr:postcode":"3281 le",
    "addr:street":"Middelsluissedijk Oz",
    "iso:country":"NL",
    "sg:address":"Middelsluissedijk Oz 74",
    "sg:city":"Numansdorp",
    "sg:orig_category":"Loodgieterswerk, Verwarming And Sanitaire Installaties",
    "sg:phone":"+31 186 654 110",
    "sg:postcode":"3281 LE",
    "sg:province":"Zuid-Holland",
    "wof:name":"Aannemers- En Loodgietersbedr G.C. V Bek",
    "wof:placetype":"venue"
},
  "geometry": {"coordinates":[4.473364,51.741928],"type":"Point"}
}