{
  "type": "Feature",
  "properties": {
    "addr:full":"Westzyde 262/B Zaandam Noord-Holland 1506 GJ",
    "addr:housenumber":"262 / b",
    "addr:postcode":"1506 gj",
    "iso:country":"NL",
    "sg:address":"Westzyde 262/B",
    "sg:city":"Zaandam",
    "sg:orig_category":"Notarissen En Notariskantoren",
    "sg:phone":"+31 75 670 1911",
    "sg:postcode":"1506 GJ",
    "sg:province":"Noord-Holland",
    "wof:name":"Lamers, Mr J T",
    "wof:placetype":"venue"
},
  "geometry": {"coordinates":[4.808925,52.44944],"type":"Point"}
}