{
  "type": "Feature",
  "properties": {
    "addr:full":"Cor Van Der Bokstraat 3 Baarle Nassau Noord-Brabant 5111 VC",
    "addr:housenumber":"3",
    "addr:postcode":"5111 vc",
    "addr:street":"Cor Van Der Bokstraat",
    "iso:country":"NL",
    "sg:address":"Cor Van Der Bokstraat 3",
    "sg:city":"Baarle Nassau",
    "sg:classifiers":[
        {
            "category":"Food & Beverages",
            "subcategory":"Fruits & Vegetables",
            "type":"Retail Goods"
        }
    ],
    "sg:phone":"+31 13 507 7102",
    "sg:postcode":"5111 VC",
    "sg:province":"Noord-Brabant",
    "sg:tags":[
        "groenten"
    ],
    "wof:name":"Groente- En Fruitspeciaalzaak Tini Pulle",
    "wof:placetype":"venue"
},
  "geometry": {"coordinates":[4.930725,51.445179],"type":"Point"}
}