{
  "type": "Feature",
  "properties": {
    "addr:full":"Waleweg 4 Strijen Zuid-Holland 3291 AX",
    "addr:housenumber":"4",
    "addr:postcode":"3291 ax",
    "addr:street":"Waleweg",
    "iso:country":"NL",
    "sg:address":"Waleweg 4",
    "sg:city":"Strijen",
    "sg:orig_category":"Veilingen",
    "sg:phone":"+31 78 674 2162",
    "sg:postcode":"3291 AX",
    "sg:province":"Zuid-Holland",
    "wof:name":"Kwekerij Van Nes Bv",
    "wof:placetype":"venue"
},
  "geometry": {"coordinates":[4.546089,51.750256],"type":"Point"}
}