{
  "type": "Feature",
  "properties": {
    "addr:full":"De Genestetstraat 120 Sliedrecht South Holland 3362 TH",
    "addr:housenumber":"120",
    "addr:postcode":"3362 th",
    "addr:street":"De Genestetstraat",
    "iso:country":"NL",
    "sg:address":"De Genestetstraat 120",
    "sg:city":"Sliedrecht",
    "sg:orig_category":"Paramedische Behandelingen",
    "sg:phone":"+31 184 422 868",
    "sg:postcode":"3362 TH",
    "sg:province":"South Holland",
    "wof:name":"Terminale Thuiszorg",
    "wof:placetype":"venue"
},
  "geometry": {"coordinates":[4.782343,51.818825],"type":"Point"}
}