{
  "type": "Feature",
  "properties": {
    "iso:country":"NL",
    "sg:address":"Dorpsstraat 68",
    "sg:city":"Zevenhuizen Zh",
    "sg:orig_category":"Kinderopvang Behalve Thuis",
    "sg:phone":"+31 180 632 693",
    "sg:postcode":"2761 AG",
    "sg:province":"South Holland",
    "wof:name":"Peuterspeelzaal De Zeven Dwergen",
    "wof:placetype":"venue"
},
  "geometry": {"coordinates":[4.583307,52.009781],"type":"Point"}
}