{
  "type": "Feature",
  "properties": {
    "addr:full":"Schubertlaan 1 Apeldoorn Gelderland 7333 CR",
    "addr:housenumber":"1",
    "addr:postcode":"7333 cr",
    "addr:street":"Schubertlaan;Gelderland",
    "iso:country":"NL",
    "sg:address":"Schubertlaan 1",
    "sg:city":"Apeldoorn",
    "sg:orig_category":"Kappers",
    "sg:phone":"+31 55 533 2318",
    "sg:postcode":"7333 CR",
    "sg:province":"Gelderland",
    "wof:name":"Fa Pleging Kapsalon En Parf",
    "wof:placetype":"venue"
},
  "geometry": {"coordinates":[5.9654359818,52.1897544861],"type":"Point"}
}