{
  "type": "Feature",
  "properties": {
    "iso:country":"NL",
    "sg:address":"Walstr 90",
    "sg:city":"Vlissingen",
    "sg:orig_category":"Juweliers",
    "sg:phone":"+31 118 413 116",
    "sg:postcode":"4381 GE",
    "sg:province":"Zeeland",
    "wof:name":"Boven, Van",
    "wof:placetype":"venue"
},
  "geometry": {"coordinates":[3.573702,51.44442],"type":"Point"}
}