{
  "type": "Feature",
  "properties": {
    "iso:country":"NL",
    "sg:address":"Oranje Nassaustraat 1",
    "sg:city":"Heerlen",
    "sg:orig_category":"Juweliers",
    "sg:phone":"+31 45 571 2440",
    "sg:postcode":"6411 LD",
    "sg:province":"Limburg",
    "wof:name":"Vaessen Bv",
    "wof:placetype":"venue"
},
  "geometry": {"coordinates":[5.979199,50.888294],"type":"Point"}
}