{
  "type": "Feature",
  "properties": {
    "addr:full":"Zuidpln Hg 715 Rotterdam Zuid-Holland 3083 BJ",
    "addr:housenumber":"715",
    "addr:postcode":"3083 bj",
    "addr:street":"Hg",
    "iso:country":"NL",
    "sg:address":"Zuidpln Hg 715",
    "sg:city":"Rotterdam",
    "sg:orig_category":"Drogisterijen",
    "sg:phone":"+31 10 481 6619",
    "sg:postcode":"3083 BJ",
    "sg:province":"Zuid-Holland",
    "wof:name":"Kruidvat",
    "wof:placetype":"venue"
},
  "geometry": {"coordinates":[4.490345,51.886997],"type":"Point"}
}