{
  "type": "Feature",
  "properties": {
    "iso:country":"NL",
    "sg:address":"Rolafwg N 50",
    "sg:city":"Lopik",
    "sg:orig_category":"Discotheken",
    "sg:phone":"+31 30 686 8302",
    "sg:postcode":"3411 BK",
    "sg:province":"Utrecht",
    "sg:website":"http://www.manebrug.nl",
    "wof:name":"Manebrug, De",
    "wof:placetype":"venue"
},
  "geometry": {"coordinates":[4.949352,51.97517],"type":"Point"}
}