{
  "type": "Feature",
  "properties": {
    "addr:full":"Het Jebbink 45 Vorden Gelderland 7251 BJ",
    "addr:housenumber":"45",
    "addr:postcode":"7251 bj",
    "addr:street":"Het Jebbink;Gelderland",
    "iso:country":"NL",
    "sg:address":"Het Jebbink 45",
    "sg:city":"Vorden",
    "sg:orig_category":"Kappers",
    "sg:phone":"+31 575 463 066",
    "sg:postcode":"7251 BJ",
    "sg:province":"Gelderland",
    "wof:name":"Sylvia",
    "wof:placetype":"venue"
},
  "geometry": {"coordinates":[6.305321,52.108604],"type":"Point"}
}