{
  "type": "Feature",
  "properties": {
    "addr:full":"Prinsengracht 487 Amsterdam North Holland 1016 HP",
    "addr:housenumber":"487",
    "addr:postcode":"1016 hp",
    "addr:street":"Prinsengracht",
    "iso:country":"NL",
    "sg:address":"Prinsengracht 487",
    "sg:city":"Amsterdam",
    "sg:orig_category":"Diverse Grafische Activiteiten",
    "sg:phone":"+31 20 627 9513",
    "sg:postcode":"1016 HP",
    "sg:province":"North Holland",
    "wof:name":"Anne Lammers",
    "wof:placetype":"venue"
},
  "geometry": {"coordinates":[4.883152,52.3694],"type":"Point"}
}