{
  "type": "Feature",
  "properties": {
    "addr:full":"Bennebroekerln 91 Bennebroek Noord-Holland 2121 GS",
    "addr:housenumber":"91",
    "addr:postcode":"2121 gs",
    "addr:street":"Bennebroekerln",
    "iso:country":"NL",
    "sg:address":"Bennebroekerln 91",
    "sg:city":"Bennebroek",
    "sg:orig_category":"Cafetaria'S",
    "sg:phone":"+31 23 584 6774",
    "sg:postcode":"2121 GS",
    "sg:province":"Noord-Holland",
    "wof:name":"Meerburcht",
    "wof:placetype":"venue"
},
  "geometry": {"coordinates":[4.6008739471,52.3212509155],"type":"Point"}
}