{
  "type": "Feature",
  "properties": {
    "addr:full":"Druivenstr 37 S Gravenhage South Holland 2564 VE",
    "addr:housenumber":"37",
    "addr:postcode":"2564",
    "addr:street":"Druivenstr;S Gravenhage;Ve",
    "iso:country":"NL",
    "sg:address":"Druivenstr 37",
    "sg:city":"S Gravenhage",
    "sg:orig_category":"Logopedisten",
    "sg:phone":"+31 70 368 2282",
    "sg:postcode":"2564 VE",
    "sg:province":"South Holland",
    "wof:name":"Zegwaard-Vos, H B",
    "wof:placetype":"venue"
},
  "geometry": {"coordinates":[4.25946,52.06805],"type":"Point"}
}