{
  "type": "Feature",
  "properties": {
    "addr:full":"De Uilenburg 74 Veldhoven Noord-Brabant 5502 RL",
    "addr:housenumber":"74",
    "addr:postcode":"5502 rl",
    "addr:street":"De Uilenburg",
    "iso:country":"NL",
    "sg:address":"De Uilenburg 74",
    "sg:city":"Veldhoven",
    "sg:orig_category":"Gelegenheidskleding",
    "sg:phone":"+31 40 212 6206",
    "sg:postcode":"5502 RL",
    "sg:province":"Noord-Brabant",
    "wof:name":"Luijt Gelegenheidskleding, Van",
    "wof:placetype":"venue"
},
  "geometry": {"coordinates":[5.409292,51.425297],"type":"Point"}
}