{
  "type": "Feature",
  "properties": {
    "iso:country":"NL",
    "sg:address":"Wilhelminastraat 10",
    "sg:city":"Roden",
    "sg:orig_category":"Kappers",
    "sg:phone":"+31 50 501 6180",
    "sg:postcode":"9301 AK",
    "sg:province":"Drenthe",
    "wof:name":"De Barbier",
    "wof:placetype":"venue"
},
  "geometry": {"coordinates":[6.4317851067,53.1383399963],"type":"Point"}
}