{
  "type": "Feature",
  "properties": {
    "iso:country":"NL",
    "sg:address":"Steenstraat 39",
    "sg:city":"Leiden",
    "sg:orig_category":"Bioscopen",
    "sg:phone":"+31 71 513 3210",
    "sg:postcode":"2312 BV",
    "sg:province":"South Holland",
    "wof:name":"Studio Theater",
    "wof:placetype":"venue"
},
  "geometry": {"coordinates":[4.4844908714,52.162563324],"type":"Point"}
}