{
  "type": "Feature",
  "properties": {
    "addr:full":"Sportsngl 17 Krimpen Ad Yssel Zuid-Holland 2924 XN",
    "addr:housenumber":"17",
    "addr:postcode":"2924 xn",
    "addr:street":"Sportsngl",
    "iso:country":"NL",
    "sg:address":"Sportsngl 17",
    "sg:city":"Krimpen Ad Yssel",
    "sg:orig_category":"Peuterspeelzalen",
    "sg:phone":"+31 180 519 213",
    "sg:postcode":"2924 XN",
    "sg:province":"Zuid-Holland",
    "wof:name":"Dikkertje Dap",
    "wof:placetype":"venue"
},
  "geometry": {"coordinates":[4.61758,51.925629],"type":"Point"}
}