{
  "type": "Feature",
  "properties": {
    "iso:country":"NL",
    "sg:address":"Prof Jordanln 2",
    "sg:city":"Utrecht",
    "sg:orig_category":"Artsen - Huisartsen",
    "sg:phone":"+31 30 271 5121",
    "sg:postcode":"3571 KA",
    "sg:province":"Utrecht",
    "wof:name":"Dijke, Van",
    "wof:placetype":"venue"
},
  "geometry": {"coordinates":[5.131287,52.103889],"type":"Point"}
}