{
  "type": "Feature",
  "properties": {
    "addr:full":"Kromvenweg 16 Lierop North Brabant 5715 RG",
    "addr:housenumber":"16",
    "addr:postcode":"5715 rg",
    "addr:street":"Kromvenweg",
    "iso:country":"NL",
    "sg:address":"Kromvenweg 16",
    "sg:city":"Lierop",
    "sg:orig_category":"Metaalbekleding And -Behandeling",
    "sg:phone":"+31 492 332 075",
    "sg:postcode":"5715 RG",
    "sg:province":"North Brabant",
    "wof:name":"Van Doorn Verspaningstechniek",
    "wof:placetype":"venue"
},
  "geometry": {"coordinates":[5.69047,51.409569],"type":"Point"}
}