{
  "type": "Feature",
  "properties": {
    "addr:full":"Ceresstr 11 Stadskanaal Groningen 9502 EA",
    "addr:housenumber":"11",
    "addr:postcode":"9502 ea",
    "addr:street":"Ceresstr",
    "iso:country":"NL",
    "sg:address":"Ceresstr 11",
    "sg:city":"Stadskanaal",
    "sg:classifiers":[
        {
            "category":"Professional",
            "type":"Services"
        }
    ],
    "sg:phone":"+31 599 659 596",
    "sg:postcode":"9502 EA",
    "sg:province":"Groningen",
    "sg:tags":[
        "leasing"
    ],
    "sg:website":"http://www.4-lease.nl",
    "wof:name":"4-Lease Bv",
    "wof:placetype":"venue"
},
  "geometry": {"coordinates":[6.973376,52.970573],"type":"Point"}
}