{
  "type": "Feature",
  "properties": {
    "addr:full":"V Vollenhovenstr 36-40 Rotterdam South Holland 3016 BJ",
    "addr:housenumber":"36-40",
    "addr:postcode":"3016 bj",
    "iso:country":"NL",
    "sg:address":"V Vollenhovenstr 36-40",
    "sg:city":"Rotterdam",
    "sg:orig_category":"Kantoor- En Bedrijfsmeubelen",
    "sg:phone":"+31 10 412 2230",
    "sg:postcode":"3016 BJ",
    "sg:province":"South Holland",
    "sg:website":"http://www.pfs-rotterdam.nl",
    "wof:name":"Pfs Rotterdam Bv",
    "wof:placetype":"venue"
},
  "geometry": {"coordinates":[4.4784550667,51.9228363037],"type":"Point"}
}