{
  "type": "Feature",
  "properties": {
    "iso:country":"NL",
    "sg:address":"Rynauwenstr 105",
    "sg:city":"S Gravenhage",
    "sg:classifiers":[
        {
            "category":"Retail",
            "subcategory":"Auto Repair",
            "type":"Services"
        }
    ],
    "sg:phone":"+31 70 367 6795",
    "sg:postcode":"2532 VC",
    "sg:province":"Zuid-Holland",
    "sg:tags":[
        "garage"
    ],
    "wof:name":"Moerwijk",
    "wof:placetype":"venue"
},
  "geometry": {"coordinates":[4.29807,52.048569],"type":"Point"}
}