{
  "type": "Feature",
  "properties": {
    "addr:full":"Geversstraat 48 Oegstgeest South Holland 2342 AB",
    "addr:housenumber":"48",
    "addr:postcode":"2342 ab",
    "addr:street":"Geversstraat",
    "iso:country":"NL",
    "sg:address":"Geversstraat 48",
    "sg:city":"Oegstgeest",
    "sg:orig_category":"Kinderopvang Behalve Thuis",
    "sg:phone":"+31 71 517 3801",
    "sg:postcode":"2342 AB",
    "sg:province":"South Holland",
    "wof:name":"Kinderdagverblijf Kiekeboe",
    "wof:placetype":"venue"
},
  "geometry": {"coordinates":[4.466711,52.177441],"type":"Point"}
}