{
  "type": "Feature",
  "properties": {
    "addr:full":"Passaat 34 De Meern Utrecht 3454 KE",
    "addr:housenumber":"34",
    "addr:postcode":"3454 ke",
    "addr:street":"Passaat",
    "iso:country":"NL",
    "sg:address":"Passaat 34",
    "sg:city":"De Meern",
    "sg:orig_category":"Beeldende Kunstenaars",
    "sg:phone":"+31 30 666 7222",
    "sg:postcode":"3454 KE",
    "sg:province":"Utrecht",
    "sg:website":"http://www.blikopkunst.nl/vanseeters",
    "wof:name":"Erica Van Seeters",
    "wof:placetype":"venue"
},
  "geometry": {"coordinates":[5.030605,52.087917],"type":"Point"}
}