{
  "type": "Feature",
  "properties": {
    "addr:full":"Amersfoortseweg 14 Bunschoten Spakenburg Utrecht 3751 LK",
    "addr:housenumber":"14",
    "addr:postcode":"3751 lk",
    "addr:street":"Amersfoortseweg",
    "iso:country":"NL",
    "sg:address":"Amersfoortseweg 14",
    "sg:city":"Bunschoten Spakenburg",
    "sg:orig_category":"Vaste And Vloeibare Brandstoffen",
    "sg:phone":"+31 33 299 8282",
    "sg:postcode":"3751 LK",
    "sg:province":"Utrecht",
    "wof:name":"Lp Gas Bv",
    "wof:placetype":"venue"
},
  "geometry": {"coordinates":[5.369549,52.226486],"type":"Point"}
}