{
  "type": "Feature",
  "properties": {
    "addr:full":"Damln 11 Leidschendam South Holland 2265 AL",
    "addr:housenumber":"11",
    "addr:postcode":"2265 al",
    "addr:street":"Damln",
    "iso:country":"NL",
    "sg:address":"Damln 11",
    "sg:city":"Leidschendam",
    "sg:orig_category":"Kaas",
    "sg:phone":"+31 70 327 1398",
    "sg:postcode":"2265 AL",
    "sg:province":"South Holland",
    "sg:website":"http://www.verskado-verbeek.nl",
    "wof:name":"Kaaswinkeltje, 'T",
    "wof:placetype":"venue"
},
  "geometry": {"coordinates":[4.3964138031,52.0815658569],"type":"Point"}
}