{
  "type": "Feature",
  "properties": {
    "addr:full":"Oude Kerkstraat 2 Etten-Leur Noord-Brabant 4878 AA",
    "addr:housenumber":"2",
    "addr:postcode":"4878 aa",
    "addr:street":"Oude Kerkstraat",
    "iso:country":"NL",
    "sg:address":"Oude Kerkstraat 2",
    "sg:city":"Etten-Leur",
    "sg:orig_category":"Bedrijfsinventaris Gh",
    "sg:phone":"+31 76 508 5200",
    "sg:postcode":"4878 AA",
    "sg:province":"Noord-Brabant",
    "wof:name":"Fri Jado Bv",
    "wof:placetype":"venue"
},
  "geometry": {"coordinates":[4.624465,51.568504],"type":"Point"}
}