{
  "type": "Feature",
  "properties": {
    "addr:full":"Weg En Land 6 Bergschenhoek South Holland 2661 DB",
    "addr:housenumber":"6",
    "addr:postcode":"2661 db",
    "addr:street":"Weg En Land",
    "iso:country":"NL",
    "sg:address":"Weg En Land 6",
    "sg:city":"Bergschenhoek",
    "sg:orig_category":"Verbouwingen",
    "sg:phone":"+31 10 521 6491",
    "sg:postcode":"2661 DB",
    "sg:province":"South Holland",
    "wof:name":"Ruigrok En Van Der Pad",
    "wof:placetype":"venue"
},
  "geometry": {"coordinates":[4.499165,51.978588],"type":"Point"}
}