{
  "type": "Feature",
  "properties": {
    "addr:full":"Steenstr 66 Arnhem Gelderland 6828 CN",
    "addr:housenumber":"66",
    "addr:postcode":"6828 cn",
    "addr:street":"Steenstr",
    "iso:country":"NL",
    "sg:address":"Steenstr 66",
    "sg:city":"Arnhem",
    "sg:orig_category":"Woningtextiel",
    "sg:phone":"+31 26 351 0896",
    "sg:postcode":"6828 CN",
    "sg:province":"Gelderland",
    "wof:name":"Diek Bv",
    "wof:placetype":"venue"
},
  "geometry": {"coordinates":[5.9186558723,51.9840812683],"type":"Point"}
}