{
  "type": "Feature",
  "properties": {
    "addr:full":"Weteringkd 46 S Gravenhage South Holland 2515 AP",
    "addr:housenumber":"46",
    "addr:postcode":"2515 ap",
    "addr:street":"Weteringkd;S Gravenhage",
    "iso:country":"NL",
    "sg:address":"Weteringkd 46",
    "sg:city":"S Gravenhage",
    "sg:orig_category":"Kappers",
    "sg:phone":"+31 70 385 9888",
    "sg:postcode":"2515 AP",
    "sg:province":"South Holland",
    "wof:name":"Chez Bob",
    "wof:placetype":"venue"
},
  "geometry": {"coordinates":[4.3174099922,52.0839881897],"type":"Point"}
}