{
  "type": "Feature",
  "properties": {
    "addr:full":"J Leentvaarln 17 Rotterdam South Holland 3065 DC",
    "addr:housenumber":"17",
    "addr:postcode":"3065",
    "iso:country":"NL",
    "sg:address":"J Leentvaarln 17",
    "sg:city":"Rotterdam",
    "sg:orig_category":"Werving En Selectie",
    "sg:phone":"+31 10 242 4444",
    "sg:postcode":"3065 DC",
    "sg:province":"South Holland",
    "sg:website":"http://www.verhagenenpartners.nl",
    "wof:name":"Verhagen + Partners",
    "wof:placetype":"venue"
},
  "geometry": {"coordinates":[4.5381541252,51.9221191406],"type":"Point"}
}