{
  "type": "Feature",
  "properties": {
    "addr:full":"Hobbemaplnts 44 Heerhugowaard Noord-Holland 1701 KG",
    "addr:housenumber":"44",
    "addr:postcode":"1701 kg",
    "addr:street":"Hobbemaplnts",
    "iso:country":"NL",
    "sg:address":"Hobbemaplnts 44",
    "sg:city":"Heerhugowaard",
    "sg:orig_category":"Antiquiteiten",
    "sg:phone":"+31 6 54290968",
    "sg:postcode":"1701 KG",
    "sg:province":"Noord-Holland",
    "wof:name":"Milatz",
    "wof:placetype":"venue"
},
  "geometry": {"coordinates":[4.827522,52.665195],"type":"Point"}
}