{
  "type": "Feature",
  "properties": {
    "addr:full":"Kleine Tocht 21 Zaandam Noord-Holland 1507 CB",
    "addr:housenumber":"21;1507",
    "addr:postcode":"cb",
    "addr:street":"Kleine Tocht",
    "iso:country":"NL",
    "sg:address":"Kleine Tocht 21",
    "sg:city":"Zaandam",
    "sg:orig_category":"Adviesbureaus Bouwkunde",
    "sg:phone":"+31 75 614 6232",
    "sg:postcode":"1507 CB",
    "sg:province":"Noord-Holland",
    "sg:website":"http://www.bbth.nl",
    "wof:name":"Bbth Bouwkundig Adviesbureau",
    "wof:placetype":"venue"
},
  "geometry": {"coordinates":[4.810382,52.430805],"type":"Point"}
}