{
  "type": "Feature",
  "properties": {
    "addr:full":"Tuinstraat 65 Tilburg Noord-Brabant 5038 DB",
    "addr:housenumber":"65",
    "addr:postcode":"5038 db",
    "addr:street":"Tuinstraat",
    "iso:country":"NL",
    "sg:address":"Tuinstraat 65",
    "sg:city":"Tilburg",
    "sg:orig_category":"Binnenhuisarchitecten",
    "sg:phone":"+31 13 536 0628",
    "sg:postcode":"5038 DB",
    "sg:province":"Noord-Brabant",
    "wof:name":"Ja Vormgevers M/V",
    "wof:placetype":"venue"
},
  "geometry": {"coordinates":[5.083339,51.557549],"type":"Point"}
}