{
  "type": "Feature",
  "properties": {
    "addr:full":"Torenstr 3 Heusden Gem Heusd Noord-Brabant 5256 NJ",
    "addr:housenumber":"3",
    "addr:postcode":"heusd;5256 nj",
    "addr:street":"Torenstr",
    "iso:country":"NL",
    "sg:address":"Torenstr 3",
    "sg:city":"Heusden Gem Heusd",
    "sg:orig_category":"Autorijscholen",
    "sg:phone":"+31 416 663 539",
    "sg:postcode":"5256 NJ",
    "sg:province":"Noord-Brabant",
    "wof:name":"Bakker, Eric",
    "wof:placetype":"venue"
},
  "geometry": {"coordinates":[5.156835,51.731525],"type":"Point"}
}