{
  "type": "Feature",
  "properties": {
    "addr:full":"Gasthuisstraat 51 Kaatsheuvel Noord-Brabant 5171 GD",
    "addr:housenumber":"51",
    "addr:postcode":"5171 gd",
    "addr:street":"Gasthuisstraat",
    "iso:country":"NL",
    "sg:address":"Gasthuisstraat 51",
    "sg:city":"Kaatsheuvel",
    "sg:orig_category":"Fietshandelaren",
    "sg:phone":"+31 416 273 068",
    "sg:postcode":"5171 GD",
    "sg:province":"Noord-Brabant",
    "wof:name":"J.Chr.M. Van Rooij",
    "wof:placetype":"venue"
},
  "geometry": {"coordinates":[5.037148,51.658482],"type":"Point"}
}