{
  "type": "Feature",
  "properties": {
    "addr:full":"Heemradenln 30-32 Ysselstein Ut Utrecht 3401 GX",
    "addr:housenumber":"30-32",
    "addr:postcode":"3401 gx",
    "addr:street":"Ysselstein",
    "iso:country":"NL",
    "sg:address":"Heemradenln 30-32",
    "sg:city":"Ysselstein Ut",
    "sg:orig_category":"Scholen Voor Basisonderwijs",
    "sg:phone":"+31 30 688 3423",
    "sg:postcode":"3401 GX",
    "sg:province":"Utrecht",
    "wof:name":"Opstap Rk, De",
    "wof:placetype":"venue"
},
  "geometry": {"coordinates":[5.04266,52.017044],"type":"Point"}
}