{
  "type": "Feature",
  "properties": {
    "iso:country":"NL",
    "sg:address":"Pastoor Ruttenweg 6",
    "sg:city":"Venlo",
    "sg:orig_category":"Goederenvervoer Over De Weg",
    "sg:phone":"+31 77 382 0625",
    "sg:postcode":"5926 RX",
    "sg:province":"Limburg",
    "wof:name":"Fa. J. Kesselmans En Zonen",
    "wof:placetype":"venue"
},
  "geometry": {"coordinates":[6.12885,51.359383],"type":"Point"}
}