{
  "type": "Feature",
  "properties": {
    "addr:full":"R Meeuwiszwg 35 Brielle Zuid-Holland 3231 CM",
    "addr:housenumber":"35",
    "addr:postcode":"3231 cm",
    "iso:country":"NL",
    "sg:address":"R Meeuwiszwg 35",
    "sg:city":"Brielle",
    "sg:orig_category":"Jachthavens - Jachtwerven",
    "sg:phone":"+31 181 413 759",
    "sg:postcode":"3231 CM",
    "sg:province":"Zuid-Holland",
    "wof:name":"Troost, De",
    "wof:placetype":"venue"
},
  "geometry": {"coordinates":[4.1678748131,51.9040603638],"type":"Point"}
}