{
  "type": "Feature",
  "properties": {
    "addr:full":"Holthuizerstraat 12 Haaksbergen NL.08 7482 ET",
    "addr:housenumber":"12;nl.08",
    "addr:postcode":"7482 et",
    "addr:street":"Holthuizerstraat",
    "iso:country":"NL",
    "sg:address":"Holthuizerstraat 12",
    "sg:city":"Haaksbergen",
    "sg:classifiers":[
        {
            "category":"Education",
            "subcategory":"Preschool",
            "type":"Public Place"
        }
    ],
    "sg:phone":"+31 53 572 3993",
    "sg:postcode":"7482 ET",
    "sg:province":"NL.08",
    "sg:tags":[
        "kleuteronderwijs",
        "basis-"
    ],
    "wof:name":"Basisschool De Holthuizen",
    "wof:placetype":"venue"
},
  "geometry": {"coordinates":[6.720564,52.160721],"type":"Point"}
}