{
  "type": "Feature",
  "properties": {
    "addr:full":"Hobbemastr 23/B S Gravenhage South Holland 2526 JE",
    "addr:housenumber":"23 / b",
    "addr:postcode":"2526 je",
    "addr:street":"Hobbemastr",
    "iso:country":"NL",
    "sg:address":"Hobbemastr 23/B",
    "sg:city":"S Gravenhage",
    "sg:orig_category":"Kappers",
    "sg:phone":"+31 70 380 8381",
    "sg:postcode":"2526 JE",
    "sg:province":"South Holland",
    "wof:name":"G\u00f7Zde Kapsalon",
    "wof:placetype":"venue"
},
  "geometry": {"coordinates":[4.3055500984,52.0680999756],"type":"Point"}
}