{
  "type": "Feature",
  "properties": {
    "addr:full":"Geraniumveld 33 Nieuwerkerk Yssel Zuid-Holland 2914 CJ",
    "addr:housenumber":"33",
    "addr:postcode":"2914 cj",
    "addr:street":"Geraniumveld",
    "iso:country":"NL",
    "sg:address":"Geraniumveld 33",
    "sg:city":"Nieuwerkerk Yssel",
    "sg:orig_category":"Grafisch Ontwerpers",
    "sg:phone":"+31 180 318 479",
    "sg:postcode":"2914 CJ",
    "sg:province":"Zuid-Holland",
    "sg:website":"http://www.bearson.nl",
    "wof:name":"Bearson",
    "wof:placetype":"venue"
},
  "geometry": {"coordinates":[4.622945,51.971233],"type":"Point"}
}