{
  "type": "Feature",
  "properties": {
    "addr:full":"Lijsterbesstraat 15 Sint Willebrord Noord-Brabant 4711 RJ",
    "addr:housenumber":"15",
    "addr:postcode":"4711 rj",
    "addr:street":"Lijsterbesstraat",
    "iso:country":"NL",
    "sg:address":"Lijsterbesstraat 15",
    "sg:city":"Sint Willebrord",
    "sg:orig_category":"Goederenvervoer Over De Weg",
    "sg:phone":"+31 165 383 143",
    "sg:postcode":"4711 RJ",
    "sg:province":"Noord-Brabant",
    "wof:name":"R. Glerum Int. Transport",
    "wof:placetype":"venue"
},
  "geometry": {"coordinates":[4.578936,51.548325],"type":"Point"}
}