{
  "type": "Feature",
  "properties": {
    "iso:country":"NL",
    "sg:address":"Tweede Goudsbloemdwstr 20",
    "sg:city":"Amsterdam",
    "sg:orig_category":"Boekhandels",
    "sg:phone":"+31 20 626 9773",
    "sg:postcode":"1015 JZ",
    "sg:province":"Noord-Holland",
    "wof:name":"Sigarenmagazijn Steenbergen",
    "wof:placetype":"venue"
},
  "geometry": {"coordinates":[4.88393,52.380516],"type":"Point"}
}