{
  "type": "Feature",
  "properties": {
    "addr:full":"Kleine Markt 5 Vlissingen Zeeland 4381 EJ",
    "addr:housenumber":"5",
    "addr:postcode":"4381 ej",
    "addr:street":"Kleine Markt",
    "iso:country":"NL",
    "sg:address":"Kleine Markt 5",
    "sg:city":"Vlissingen",
    "sg:orig_category":"Baby- And Kinderkleding",
    "sg:phone":"+31 118 415 665",
    "sg:postcode":"4381 EJ",
    "sg:province":"Zeeland",
    "wof:name":"Just 4 Teens",
    "wof:placetype":"venue"
},
  "geometry": {"coordinates":[3.575065,51.444031],"type":"Point"}
}