{
  "type": "Feature",
  "properties": {
    "addr:full":"Nieuwstraat 18 Deventer NL.08 7411 LL",
    "addr:housenumber":"18;nl.08",
    "addr:postcode":"7411 ll",
    "addr:street":"Nieuwstraat",
    "iso:country":"NL",
    "sg:address":"Nieuwstraat 18",
    "sg:city":"Deventer",
    "sg:orig_category":"Kappers",
    "sg:phone":"+31 570 613 427",
    "sg:postcode":"7411 LL",
    "sg:province":"NL.08",
    "wof:name":"Knip In",
    "wof:placetype":"venue"
},
  "geometry": {"coordinates":[6.159899,52.251034],"type":"Point"}
}