{
  "type": "Feature",
  "properties": {
    "addr:full":"Lokhorstwg 11 Ermelo Gelderland 3851 SE",
    "addr:housenumber":"11",
    "addr:postcode":"3851",
    "addr:street":"Lokhorstwg;Gelderland;Se",
    "iso:country":"NL",
    "sg:address":"Lokhorstwg 11",
    "sg:city":"Ermelo",
    "sg:orig_category":"Bloemen En Planten - Decoratie",
    "sg:phone":"+31 341 561 256",
    "sg:postcode":"3851 SE",
    "sg:province":"Gelderland",
    "wof:name":"Binderij, De",
    "wof:placetype":"venue"
},
  "geometry": {"coordinates":[5.619879,52.318768],"type":"Point"}
}