{
  "type": "Feature",
  "properties": {
    "addr:full":"Hg Ryndijk 3 A Woerden Utrecht 3449 HA",
    "addr:housenumber":"3 a",
    "addr:postcode":"3449 ha",
    "iso:country":"NL",
    "sg:address":"Hg Ryndijk 3 A",
    "sg:city":"Woerden",
    "sg:orig_category":"Overheidsdiensten",
    "sg:phone":"+31 348 430 897",
    "sg:postcode":"3449 HA",
    "sg:province":"Utrecht",
    "wof:name":"K 77",
    "wof:placetype":"venue"
},
  "geometry": {"coordinates":[4.8873710632,52.0851173401],"type":"Point"}
}