{
  "type": "Feature",
  "properties": {
    "addr:full":"Ln V Meerdervoort 302A S Gravenhage Zuid-Holland 2563 AL",
    "addr:housenumber":"302a s",
    "addr:postcode":"2563 al",
    "addr:street":"Ln;Meerdervoort",
    "iso:country":"NL",
    "sg:address":"Ln V Meerdervoort 302A",
    "sg:city":"S Gravenhage",
    "sg:orig_category":"Haarwerken",
    "sg:phone":"+31 70 427 7408",
    "sg:postcode":"2563 AL",
    "sg:province":"Zuid-Holland",
    "sg:website":"http://www.brooks-haar.nl",
    "wof:name":"Brooks Haarinstituut",
    "wof:placetype":"venue"
},
  "geometry": {"coordinates":[4.270956,52.072578],"type":"Point"}
}