{
  "type": "Feature",
  "properties": {
    "addr:full":"Het Hoge 36 Vorden Gelderland 7251 XX",
    "addr:housenumber":"36",
    "addr:postcode":"7251 xx",
    "addr:street":"Het Hoge;Gelderland",
    "iso:country":"NL",
    "sg:address":"Het Hoge 36",
    "sg:city":"Vorden",
    "sg:classifiers":[
        {
            "category":"Education",
            "subcategory":"Preschool",
            "type":"Public Place"
        }
    ],
    "sg:phone":"+31 575 552 036",
    "sg:postcode":"7251 XX",
    "sg:province":"Gelderland",
    "sg:tags":[
        "kleuteronderwijs",
        "basis-"
    ],
    "wof:name":"Basisschool Het Hoge",
    "wof:placetype":"venue"
},
  "geometry": {"coordinates":[6.30913,52.10321],"type":"Point"}
}