{
  "type": "Feature",
  "properties": {
    "addr:full":"De Amert 134 Veghel Noord-Brabant 5462 GH",
    "addr:housenumber":"134",
    "addr:postcode":"veghel;5462 gh",
    "addr:street":"De Amert",
    "iso:country":"NL",
    "sg:address":"De Amert 134",
    "sg:city":"Veghel",
    "sg:orig_category":"Onderhoudswerken",
    "sg:phone":"+31 413 354 988",
    "sg:postcode":"5462 GH",
    "sg:province":"Noord-Brabant",
    "sg:website":"http://www.i-es.nl",
    "wof:name":"I & Es Bv",
    "wof:placetype":"venue"
},
  "geometry": {"coordinates":[5.518737,51.622936],"type":"Point"}
}