{
  "type": "Feature",
  "properties": {
    "addr:full":"Gandhistr 7 Middelburg Zeeland 4336 LC",
    "addr:housenumber":"7",
    "addr:postcode":"4336 lc",
    "addr:street":"Gandhistr",
    "iso:country":"NL",
    "sg:address":"Gandhistr 7",
    "sg:city":"Middelburg",
    "sg:orig_category":"Schoonheidsinstituten",
    "sg:phone":"+31 118 616 274",
    "sg:postcode":"4336 LC",
    "sg:province":"Zeeland",
    "wof:name":"Jafra",
    "wof:placetype":"venue"
},
  "geometry": {"coordinates":[3.60767,51.483208],"type":"Point"}
}