{
  "type": "Feature",
  "properties": {
    "iso:country":"NL",
    "sg:address":"Jagersdreef 30",
    "sg:city":"Driebergen Rysenb",
    "sg:orig_category":"Adviesbureaus Bedrijfsorganisatie",
    "sg:phone":"+31 343 521 389",
    "sg:postcode":"3972 XE",
    "sg:province":"Utrecht",
    "wof:name":"Broekgaarden",
    "wof:placetype":"venue"
},
  "geometry": {"coordinates":[5.272445,52.050503],"type":"Point"}
}