{
  "type": "Feature",
  "properties": {
    "addr:full":"Heuvelstraat 61 Tilburg Noord-Brabant 5038 AC",
    "addr:housenumber":"61",
    "addr:postcode":"5038 ac",
    "addr:street":"Heuvelstraat",
    "iso:country":"NL",
    "sg:address":"Heuvelstraat 61",
    "sg:city":"Tilburg",
    "sg:orig_category":"Juweliers",
    "sg:phone":"+31 13 543 4868",
    "sg:postcode":"5038 AC",
    "sg:province":"Noord-Brabant",
    "wof:name":"August Pijnenburg Bv",
    "wof:placetype":"venue"
},
  "geometry": {"coordinates":[5.087087,51.556221],"type":"Point"}
}