{
  "type": "Feature",
  "properties": {
    "addr:full":"Albertln 16 Nunspeet Gelderland 8072 CJ",
    "addr:housenumber":"16",
    "addr:postcode":"8072 cj",
    "addr:street":"Albertln;Gelderland",
    "iso:country":"NL",
    "sg:address":"Albertln 16",
    "sg:city":"Nunspeet",
    "sg:orig_category":"Manueel Therapeuten",
    "sg:phone":"+31 341 257 406",
    "sg:postcode":"8072 CJ",
    "sg:province":"Gelderland",
    "wof:name":"Boterenbrood, H",
    "wof:placetype":"venue"
},
  "geometry": {"coordinates":[5.800883,52.387745],"type":"Point"}
}