{
  "type": "Feature",
  "properties": {
    "addr:full":"Nyverheidsstr 3 Tweede Exloermond Drenthe 9571 CA",
    "addr:housenumber":"3",
    "addr:postcode":"9571 ca",
    "addr:street":"Nyverheidsstr;Tweede Exloermond",
    "iso:country":"NL",
    "sg:address":"Nyverheidsstr 3",
    "sg:city":"Tweede Exloermond",
    "sg:orig_category":"Adviesbureaus Bedrijfsveiligheid",
    "sg:phone":"+31 599 672 109",
    "sg:postcode":"9571 CA",
    "sg:province":"Drenthe",
    "wof:name":"Opleiding Veiligheid & Milieu Bv",
    "wof:placetype":"venue"
},
  "geometry": {"coordinates":[-119.270203,37.271832],"type":"Point"}
}