{
  "type": "Feature",
  "properties": {
    "addr:full":"Van Rosenburgweg 21 Nijmegen Gelderland 6537 TM",
    "addr:housenumber":"21",
    "addr:postcode":"6537 tm",
    "addr:street":"Van Rosenburgweg;Gelderland",
    "iso:country":"NL",
    "sg:address":"Van Rosenburgweg 21",
    "sg:city":"Nijmegen",
    "sg:orig_category":"Zuivelproducten And Spijsoli?n Gh",
    "sg:phone":"+31 24 344 3939",
    "sg:postcode":"6537 TM",
    "sg:province":"Gelderland",
    "wof:name":"De Hippe Kip",
    "wof:placetype":"venue"
},
  "geometry": {"coordinates":[5.780024,51.819626],"type":"Point"}
}