{
  "type": "Feature",
  "properties": {
    "addr:full":"Lekstraat 153 'S Gravenhage Zuid-Holland 2515 XD",
    "addr:housenumber":"153 '",
    "addr:postcode":"2515 xd",
    "addr:street":"Lekstraat",
    "iso:country":"NL",
    "sg:address":"Lekstraat 153",
    "sg:city":"'S Gravenhage",
    "sg:orig_category":"Fietshandelaren",
    "sg:phone":"+31 70 385 5395",
    "sg:postcode":"2515 XD",
    "sg:province":"Zuid-Holland",
    "wof:name":"Fa Dekker & Pronk",
    "wof:placetype":"venue"
},
  "geometry": {"coordinates":[4.327765,52.077049],"type":"Point"}
}