{
  "type": "Feature",
  "properties": {
    "iso:country":"NL",
    "sg:address":"Borkeldwg 2",
    "sg:city":"Markelo",
    "sg:orig_category":"Honden- En Kattentrimsalons",
    "sg:phone":"+31 547 363 149",
    "sg:postcode":"7475 RV",
    "sg:province":"Overijssel",
    "wof:name":"Boxo",
    "wof:placetype":"venue"
},
  "geometry": {"coordinates":[6.461576,52.260761],"type":"Point"}
}