{
  "type": "Feature",
  "properties": {
    "addr:full":"Drieherenln 33 Heemstede Noord-Holland 2103 SB",
    "addr:housenumber":"33",
    "addr:postcode":"2103 sb",
    "addr:street":"Drieherenln",
    "iso:country":"NL",
    "sg:address":"Drieherenln 33",
    "sg:city":"Heemstede",
    "sg:orig_category":"Onderhoudswerken",
    "sg:phone":"+31 23 529 1850",
    "sg:postcode":"2103 SB",
    "sg:province":"Noord-Holland",
    "wof:name":"April Bv",
    "wof:placetype":"venue"
},
  "geometry": {"coordinates":[4.624387,52.344917],"type":"Point"}
}