{
  "type": "Feature",
  "properties": {
    "addr:full":"Sleedoornstraat 41 'S Gravenhage Zuid-Holland 2565 WL",
    "addr:housenumber":"41",
    "addr:postcode":"2565 wl",
    "addr:street":"Sleedoornstraat;' S",
    "iso:country":"NL",
    "sg:address":"Sleedoornstraat 41",
    "sg:city":"'S Gravenhage",
    "sg:orig_category":"Artsen And Specialisten",
    "sg:phone":"+31 70 345 3247",
    "sg:postcode":"2565 WL",
    "sg:province":"Zuid-Holland",
    "wof:name":"Huisartspraktijk Bos Vastar Vos",
    "wof:placetype":"venue"
},
  "geometry": {"coordinates":[4.263323,52.07811],"type":"Point"}
}