{
  "type": "Feature",
  "properties": {
    "addr:full":"Heemraadssngl 196 Rotterdam South Holland 3021 DM",
    "addr:housenumber":"196",
    "addr:postcode":"3021 dm",
    "iso:country":"NL",
    "sg:address":"Heemraadssngl 196",
    "sg:city":"Rotterdam",
    "sg:orig_category":"Verenigingen En Stichtingen",
    "sg:phone":"+31 10 425 9033",
    "sg:postcode":"3021 DM",
    "sg:province":"South Holland",
    "wof:name":"Abri, Sticht",
    "wof:placetype":"venue"
},
  "geometry": {"coordinates":[4.455971,51.915001],"type":"Point"}
}