{
  "type": "Feature",
  "properties": {
    "addr:full":"Zeilmakerstraat 18 Assen Drenthe 9403 VA",
    "addr:housenumber":"18",
    "addr:postcode":"9403",
    "addr:street":"Zeilmakerstraat",
    "iso:country":"NL",
    "sg:address":"Zeilmakerstraat 18",
    "sg:city":"Assen",
    "sg:orig_category":"Meubelzaken, Woning- And Keukeninrichting",
    "sg:phone":"+31 592 342 446",
    "sg:postcode":"9403 VA",
    "sg:province":"Drenthe",
    "wof:name":"Blomsma Woninginrichting Bv",
    "wof:placetype":"venue"
},
  "geometry": {"coordinates":[6.578787,53.010681],"type":"Point"}
}