{
  "type": "Feature",
  "properties": {
    "addr:full":"Meerwg 227 Haren Gn Groningen 9752 XD",
    "addr:housenumber":"227",
    "addr:postcode":"9752 xd",
    "iso:country":"NL",
    "sg:address":"Meerwg 227",
    "sg:city":"Haren Gn",
    "sg:orig_category":"Verenigingen En Stichtingen",
    "sg:phone":"+31 50 309 1366",
    "sg:postcode":"9752 XD",
    "sg:province":"Groningen",
    "sg:website":"http://home.wxs.nl/~joost.noot/",
    "wof:name":"Vwdtp, Watersp Ver",
    "wof:placetype":"venue"
},
  "geometry": {"coordinates":[6.576185,53.162102],"type":"Point"}
}