{
  "type": "Feature",
  "properties": {
    "addr:full":"Broekhin Zuid 20 Roermond Limburg 6042 EC",
    "addr:housenumber":"20",
    "addr:postcode":"6042 ec",
    "addr:street":"Broekhin Zuid",
    "iso:country":"NL",
    "sg:address":"Broekhin Zuid 20",
    "sg:city":"Roermond",
    "sg:orig_category":"Meubelzaken, Woning- And Keukeninrichting",
    "sg:phone":"+31 475 310 930",
    "sg:postcode":"6042 EC",
    "sg:province":"Limburg",
    "wof:name":"Matrassenhal Roermond",
    "wof:placetype":"venue"
},
  "geometry": {"coordinates":[6.003796,51.202454],"type":"Point"}
}