{
  "type": "Feature",
  "properties": {
    "addr:full":"Kerkstraat 25 Amsterdam Noord-Holland 1017 GA",
    "addr:housenumber":"25",
    "addr:postcode":"1017 ga",
    "addr:street":"Kerkstraat",
    "iso:country":"NL",
    "sg:address":"Kerkstraat 25",
    "sg:city":"Amsterdam",
    "sg:classifiers":[
        {
            "category":"Travel",
            "subcategory":"Hotels & Motels",
            "type":"Entertainment"
        }
    ],
    "sg:phone":"+31 20 626 9746",
    "sg:postcode":"1017 GA",
    "sg:province":"Noord-Holland",
    "wof:name":"Greenwich Village",
    "wof:placetype":"venue"
},
  "geometry": {"coordinates":[-94.58503,38.350479],"type":"Point"}
}