{
  "type": "Feature",
  "properties": {
    "addr:full":"Industrieweg 31 Zwolle Overijssel 8031 EB",
    "addr:housenumber":"31",
    "addr:postcode":"8031 eb",
    "addr:street":"Industrieweg",
    "iso:country":"NL",
    "sg:address":"Industrieweg 31",
    "sg:city":"Zwolle",
    "sg:orig_category":"Metaalbekleding And -Behandeling",
    "sg:phone":"+31 38 421 5254",
    "sg:postcode":"8031 EB",
    "sg:province":"Overijssel",
    "wof:name":"Scheepswerf En Machinefabriek Leenman Bv",
    "wof:placetype":"venue"
},
  "geometry": {"coordinates":[6.082165,52.519161],"type":"Point"}
}