{
  "type": "Feature",
  "properties": {
    "addr:full":"Postbus 43 Alphen Aan Den Ryn 2400 AA",
    "addr:housenumber":"43",
    "addr:postcode":"2400 aa",
    "addr:street":"Postbus;Aan Den Ryn",
    "iso:country":"NL",
    "sg:address":"Postbus 43",
    "sg:city":"Alphen Aan Den Ryn",
    "sg:orig_category":"Wijnkoperijen En -Groothandel",
    "sg:phone":"+31 172 416 752",
    "sg:postcode":"2400 AA",
    "wof:name":"Kraay En Co Bv",
    "wof:placetype":"venue"
},
  "geometry": {"coordinates":[4.6889500618,52.1310882568],"type":"Point"}
}