{
  "type": "Feature",
  "properties": {
    "addr:full":"Wedderwg 7 Oude Pekela Groningen 9665 JL",
    "addr:housenumber":"7",
    "addr:postcode":"pekela;9665 jl",
    "addr:street":"Wedderwg",
    "iso:country":"NL",
    "sg:address":"Wedderwg 7",
    "sg:city":"Oude Pekela",
    "sg:orig_category":"Begrafenisverzorging",
    "sg:phone":"+31 597 612 353",
    "sg:postcode":"9665 JL",
    "sg:province":"Groningen",
    "wof:name":"Uitvaart Org Groningen Ua, Coop",
    "wof:placetype":"venue"
},
  "geometry": {"coordinates":[7.011652,53.1017],"type":"Point"}
}