{
  "type": "Feature",
  "properties": {
    "addr:full":"Vennewg 49 Goirle Noord-Brabant 5051 BN",
    "addr:housenumber":"49",
    "addr:postcode":"5051 bn",
    "addr:street":"Vennewg",
    "iso:country":"NL",
    "sg:address":"Vennewg 49",
    "sg:city":"Goirle",
    "sg:orig_category":"Verzekeringen - Verzekeringskantoren",
    "sg:phone":"+31 13 580 0603",
    "sg:postcode":"5051 BN",
    "sg:province":"Noord-Brabant",
    "wof:name":"Hoskens, Assuranti\u00ebn",
    "wof:placetype":"venue"
},
  "geometry": {"coordinates":[5.05893,51.528629],"type":"Point"}
}