{
  "type": "Feature",
  "properties": {
    "addr:full":"Zesstedenwg 69 Grootebroek Noord-Holland 1613 JB",
    "addr:housenumber":"69",
    "addr:postcode":"1613 jb",
    "addr:street":"Zesstedenwg",
    "iso:country":"NL",
    "sg:address":"Zesstedenwg 69",
    "sg:city":"Grootebroek",
    "sg:classifiers":[
        {
            "category":"Personal",
            "subcategory":"Nail Salon",
            "type":"Services"
        }
    ],
    "sg:phone":"+31 228 514 609",
    "sg:postcode":"1613 JB",
    "sg:province":"Noord-Holland",
    "sg:tags":[
        "pedicure"
    ],
    "wof:name":"Marjan",
    "wof:placetype":"venue"
},
  "geometry": {"coordinates":[5.228889,52.697079],"type":"Point"}
}