{
  "type": "Feature",
  "properties": {
    "addr:full":"Bredewg 4 Amsterdam Noord-Holland 1098 BP",
    "addr:housenumber":"4",
    "addr:postcode":"1098 bp",
    "addr:street":"Bredewg",
    "iso:country":"NL",
    "sg:address":"Bredewg 4",
    "sg:city":"Amsterdam",
    "sg:orig_category":"Filmstudio'S En -Productie",
    "sg:phone":"+31 20 468 4732",
    "sg:postcode":"1098 BP",
    "sg:province":"Noord-Holland",
    "wof:name":"Richter, Hans",
    "wof:placetype":"venue"
},
  "geometry": {"coordinates":[4.92981,52.355484],"type":"Point"}
}