{
  "type": "Feature",
  "properties": {
    "addr:full":"Stationsstraat 200 Apeldoorn Gelderland 7311 MJ",
    "addr:housenumber":"200",
    "addr:postcode":"7311 mj",
    "addr:street":"Stationsstraat;Gelderland",
    "iso:country":"NL",
    "sg:address":"Stationsstraat 200",
    "sg:city":"Apeldoorn",
    "sg:orig_category":"Makelaars In Onroerend Goed",
    "sg:phone":"+31 55 521 2100",
    "sg:postcode":"7311 MJ",
    "sg:province":"Gelderland",
    "wof:name":"Rmtk",
    "wof:placetype":"venue"
},
  "geometry": {"coordinates":[5.965161,52.215855],"type":"Point"}
}