{
  "type": "Feature",
  "properties": {
    "addr:full":"Amstelveensewg 253 Amsterdam North Holland 1076 CR",
    "addr:housenumber":"253",
    "addr:postcode":"1076 cr",
    "iso:country":"NL",
    "sg:address":"Amstelveensewg 253",
    "sg:city":"Amsterdam",
    "sg:orig_category":"Meubelstoffering",
    "sg:phone":"+31 20 679 4737",
    "sg:postcode":"1076 CR",
    "sg:province":"North Holland",
    "wof:name":"Nanninga, J",
    "wof:placetype":"venue"
},
  "geometry": {"coordinates":[4.858082,52.345428],"type":"Point"}
}