{
  "type": "Feature",
  "properties": {
    "addr:full":"Spekstr 17 Den Dungen Noord-Brabant 5275 JG",
    "addr:housenumber":"17",
    "addr:postcode":"5275 jg",
    "addr:street":"Spekstr",
    "iso:country":"NL",
    "sg:address":"Spekstr 17",
    "sg:city":"Den Dungen",
    "sg:orig_category":"Koeltechniek",
    "sg:phone":"+31 73 594 2708",
    "sg:postcode":"5275 JG",
    "sg:province":"Noord-Brabant",
    "wof:name":"Food Systems Benelux Bv",
    "wof:placetype":"venue"
},
  "geometry": {"coordinates":[5.382589,51.660465],"type":"Point"}
}