{
  "type": "Feature",
  "properties": {
    "addr:full":"Doetsewg 43 Giessenburg Zuid-Holland 3381 KE",
    "addr:housenumber":"43",
    "addr:postcode":"3381 ke",
    "addr:street":"Doetsewg",
    "iso:country":"NL",
    "sg:address":"Doetsewg 43",
    "sg:city":"Giessenburg",
    "sg:orig_category":"Parketvloeren",
    "sg:phone":"+31 184 654 393",
    "sg:postcode":"3381 KE",
    "sg:province":"Zuid-Holland",
    "sg:website":"http://www.vloerenhuis.com",
    "wof:name":"Muis",
    "wof:placetype":"venue"
},
  "geometry": {"coordinates":[4.898166,51.857956],"type":"Point"}
}