{
  "type": "Feature",
  "properties": {
    "iso:country":"NL",
    "sg:address":"Westeind 85",
    "sg:city":"Papendrecht",
    "sg:orig_category":"Bloemen And Planten",
    "sg:phone":"+31 78 641 0474",
    "sg:postcode":"3351 AM",
    "sg:province":"Zuid-Holland",
    "wof:name":"Ron",
    "wof:placetype":"venue"
},
  "geometry": {"coordinates":[4.678209,51.82679],"type":"Point"}
}