{
  "type": "Feature",
  "properties": {
    "addr:full":"Postbus 27 De Wyk Provincie Drenthe 7957 ZG",
    "addr:housenumber":"27",
    "addr:postcode":"7957 zg",
    "addr:street":"Postbus;De Wyk Provincie Drenthe",
    "iso:country":"NL",
    "sg:address":"Postbus 27",
    "sg:city":"De Wyk",
    "sg:orig_category":"Projectinrichting",
    "sg:phone":"+31 522 442 385",
    "sg:postcode":"7957 ZG",
    "sg:province":"Provincie Drenthe",
    "wof:name":"Ahorta Vof",
    "wof:placetype":"venue"
},
  "geometry": {"coordinates":[6.28726,52.672199],"type":"Point"}
}