{
  "type": "Feature",
  "properties": {
    "iso:country":"NL",
    "sg:address":"Gewandhuis 7",
    "sg:city":"Boekel",
    "sg:orig_category":"Diverse Consumentenartikelen Gh",
    "sg:phone":"+31 492 325 088",
    "sg:postcode":"5427 PW",
    "sg:province":"North Brabant",
    "wof:name":"Verhagen Vof",
    "wof:placetype":"venue"
},
  "geometry": {"coordinates":[5.67417,51.616238],"type":"Point"}
}