{
  "type": "Feature",
  "properties": {
    "iso:country":"NL",
    "sg:address":"Hoofdstr 68",
    "sg:city":"Schimmert",
    "sg:orig_category":"Bodemonderzoek",
    "sg:phone":"+31 45 404 1359",
    "sg:postcode":"6333 BK",
    "sg:province":"Limburg",
    "wof:name":"Envicon Milieuadviesbureau Bv",
    "wof:placetype":"venue"
},
  "geometry": {"coordinates":[5.825835,50.906666],"type":"Point"}
}