{
  "type": "Feature",
  "properties": {
    "addr:full":"Westlaan 12 Pijnacker South Holland 2641 DM",
    "addr:housenumber":"12",
    "addr:postcode":"2641 dm",
    "addr:street":"Westlaan",
    "iso:country":"NL",
    "sg:address":"Westlaan 12",
    "sg:city":"Pijnacker",
    "sg:classifiers":[
        {
            "category":"Communications",
            "subcategory":"Television Station",
            "type":"Services"
        }
    ],
    "sg:phone":"+31 15 369 4380",
    "sg:postcode":"2641 DM",
    "sg:province":"South Holland",
    "sg:tags":[
        "video",
        "audio",
        "verhuur"
    ],
    "wof:name":"Cinerent Pijnacker",
    "wof:placetype":"venue"
},
  "geometry": {"coordinates":[4.429126,52.018883],"type":"Point"}
}