{
  "type": "Feature",
  "properties": {
    "addr:full":"Ameidestr 2 Helmond Noord-Brabant 5701 NP",
    "addr:housenumber":"2",
    "addr:postcode":"5701 np",
    "addr:street":"Ameidestr",
    "iso:country":"NL",
    "sg:address":"Ameidestr 2",
    "sg:city":"Helmond",
    "sg:orig_category":"Herenkleding",
    "sg:phone":"+31 492 599 320",
    "sg:postcode":"5701 NP",
    "sg:province":"Noord-Brabant",
    "wof:name":"Haver, Rob",
    "wof:placetype":"venue"
},
  "geometry": {"coordinates":[5.657442,51.47897],"type":"Point"}
}