{
  "type": "Feature",
  "properties": {
    "addr:full":"Flierstraat 81B Lage Zwaluwe Noord-Brabant 4926 AB",
    "addr:housenumber":"81b",
    "addr:postcode":"zwaluwe;4926 ab",
    "addr:street":"Flierstraat",
    "iso:country":"NL",
    "sg:address":"Flierstraat 81B",
    "sg:city":"Lage Zwaluwe",
    "sg:orig_category":"Technische Studies And Onderzoek",
    "sg:phone":"+31 168 482 119",
    "sg:postcode":"4926 AB",
    "sg:province":"Noord-Brabant",
    "wof:name":"V & S Survey",
    "wof:placetype":"venue"
},
  "geometry": {"coordinates":[4.685379,51.713585],"type":"Point"}
}