{
  "type": "Feature",
  "properties": {
    "iso:country":"NL",
    "sg:address":"Beurtschipper 20",
    "sg:city":"Nykerk Gld",
    "sg:orig_category":"Elektronica - Ontwikkeling En Groothandel",
    "sg:phone":"+31 33 246 5314",
    "sg:postcode":"3861 SC",
    "sg:province":"Gelderland",
    "sg:website":"http://www.windmill-innovations.com",
    "wof:name":"Windmill Innovations Bv",
    "wof:placetype":"venue"
},
  "geometry": {"coordinates":[5.46531,52.229191],"type":"Point"}
}