{
  "type": "Feature",
  "properties": {
    "iso:country":"NL",
    "sg:address":"Abbringstraat 68",
    "sg:city":"Purmerend",
    "sg:orig_category":"Goederenvervoer Over De Weg",
    "sg:phone":"+31 6 53736548",
    "sg:postcode":"1447 PB",
    "sg:province":"Noord-Holland",
    "wof:name":"Haije Bv",
    "wof:placetype":"venue"
},
  "geometry": {"coordinates":[4.973544,52.489864],"type":"Point"}
}