{
  "type": "Feature",
  "properties": {
    "addr:full":"Het Boerrigter 82 Losser NL.08 7582 DC",
    "addr:housenumber":"82;nl.08",
    "addr:postcode":"7582",
    "addr:street":"Het Boerrigter",
    "iso:country":"NL",
    "sg:address":"Het Boerrigter 82",
    "sg:city":"Losser",
    "sg:orig_category":"Honden- En Kattentrimsalons",
    "sg:phone":"+31 53 538 6061",
    "sg:postcode":"7582 DC",
    "sg:province":"NL.08",
    "wof:name":"Kassenaar, Jet",
    "wof:placetype":"venue"
},
  "geometry": {"coordinates":[7.00072,52.257156],"type":"Point"}
}