{
  "type": "Feature",
  "properties": {
    "iso:country":"NL",
    "sg:address":"De Deimt 3",
    "sg:city":"Dronten",
    "sg:orig_category":"Landbouwmachines Gh",
    "sg:phone":"+31 321 310 227",
    "sg:postcode":"8252 JG",
    "sg:province":"Flevoland",
    "wof:name":"Handelsonderneming Bert Van 'T Oever",
    "wof:placetype":"venue"
},
  "geometry": {"coordinates":[5.701562,52.514801],"type":"Point"}
}