{
  "type": "Feature",
  "properties": {
    "addr:full":"Dubbeldamseweg Noord 23 Dordrecht South Holland 3311 LW",
    "addr:housenumber":"23",
    "addr:postcode":"3311 lw",
    "addr:street":"Dubbeldamseweg Noord",
    "iso:country":"NL",
    "sg:address":"Dubbeldamseweg Noord 23",
    "sg:city":"Dordrecht",
    "sg:orig_category":"Boekenuitgeverijen",
    "sg:phone":"+31 78 613 8613",
    "sg:postcode":"3311 LW",
    "sg:province":"South Holland",
    "wof:name":"Dekkers Boek-En Kantoorboekh.- Drukkerij",
    "wof:placetype":"venue"
},
  "geometry": {"coordinates":[4.672458,51.807777],"type":"Point"}
}