{
  "type": "Feature",
  "properties": {
    "addr:full":"Zeedk 22 Utrecht Utrecht 3513 GZ",
    "addr:housenumber":"22",
    "addr:postcode":"3513 gz",
    "addr:street":"Zeedk",
    "iso:country":"NL",
    "sg:address":"Zeedk 22",
    "sg:city":"Utrecht",
    "sg:orig_category":"Houtgroothandel",
    "sg:phone":"+31 30 233 0930",
    "sg:postcode":"3513 GZ",
    "sg:province":"Utrecht",
    "wof:name":"Houten Hart, Het",
    "wof:placetype":"venue"
},
  "geometry": {"coordinates":[5.112263,52.099651],"type":"Point"}
}