{
  "type": "Feature",
  "properties": {
    "iso:country":"NL",
    "sg:address":"Exterpad 11",
    "sg:city":"Enkhuizen",
    "sg:orig_category":"Sportverenigingen En Ontspannings- Verenigingen",
    "sg:phone":"+31 228 319 017",
    "sg:postcode":"1601 RB",
    "sg:province":"North Holland",
    "wof:name":"Enkhuizer Harddraverij Ver",
    "wof:placetype":"venue"
},
  "geometry": {"coordinates":[5.285338,52.705536],"type":"Point"}
}