{
  "type": "Feature",
  "properties": {
    "addr:full":"Klaphekweg 30 Ede Gelderland 6713 HN",
    "addr:housenumber":"30",
    "addr:postcode":"6713 hn",
    "addr:street":"Klaphekweg;Gelderland",
    "iso:country":"NL",
    "sg:address":"Klaphekweg 30",
    "sg:city":"Ede",
    "sg:orig_category":"Autoverhuur",
    "sg:phone":"+31 318 640 230",
    "sg:postcode":"6713 HN",
    "sg:province":"Gelderland",
    "sg:website":"http://www.budget.nl",
    "wof:name":"Budget Rent A Car",
    "wof:placetype":"venue"
},
  "geometry": {"coordinates":[5.653813,52.034428],"type":"Point"}
}