{
  "type": "Feature",
  "properties": {
    "iso:country":"NL",
    "sg:address":"Stephensonwg 12",
    "sg:city":"Gorinchem",
    "sg:orig_category":"Bedrijfswagenaccessoires",
    "sg:phone":"+31 183 641 400",
    "sg:postcode":"4207 HB",
    "sg:province":"South Holland",
    "sg:website":"http://www.groeneveld.nl",
    "wof:name":"Groeneveld Transport Effici?ncy Bv",
    "wof:placetype":"venue"
},
  "geometry": {"coordinates":[5.000027,51.842819],"type":"Point"}
}