{
  "type": "Feature",
  "properties": {
    "addr:full":"Spui 246 S Gravenhage South Holland 2511 BZ",
    "addr:housenumber":"246",
    "addr:postcode":"2511 bz",
    "addr:street":"Spui;S Gravenhage",
    "iso:country":"NL",
    "sg:address":"Spui 246",
    "sg:city":"S Gravenhage",
    "sg:orig_category":"Bloemen En Planten",
    "sg:phone":"+31 70 361 6007",
    "sg:postcode":"2511 BZ",
    "sg:province":"South Holland",
    "wof:name":"Oxalis",
    "wof:placetype":"venue"
},
  "geometry": {"coordinates":[4.31627,52.07896],"type":"Point"}
}