{
  "type": "Feature",
  "properties": {
    "addr:full":"Paterswoldseweg 125 Groningen Groningen 9727 BE",
    "addr:housenumber":"125",
    "addr:postcode":"9727",
    "addr:street":"Paterswoldseweg",
    "iso:country":"NL",
    "sg:address":"Paterswoldseweg 125",
    "sg:city":"Groningen",
    "sg:orig_category":"Overheidsdiensten",
    "sg:phone":"+31 50 525 7134",
    "sg:postcode":"9727 BE",
    "sg:province":"Groningen",
    "wof:name":"Parkzucht",
    "wof:placetype":"venue"
},
  "geometry": {"coordinates":[6.5578718185,53.2055892944],"type":"Point"}
}