{
  "type": "Feature",
  "properties": {
    "iso:country":"NL",
    "sg:address":"Drienerstr 4",
    "sg:city":"Hengelo Ov",
    "sg:orig_category":"Wereldwinkels",
    "sg:phone":"+31 74 291 6169",
    "sg:postcode":"7551 HG",
    "sg:province":"Overijssel",
    "wof:name":"Wereldwinkel",
    "wof:placetype":"venue"
},
  "geometry": {"coordinates":[6.7961559296,52.2646942139],"type":"Point"}
}