{
  "type": "Feature",
  "properties": {
    "addr:full":"Oude Provincia Wg 28 Hapert North Brabant 5527 BP",
    "addr:housenumber":"28",
    "addr:postcode":"5527 bp",
    "addr:street":"Oude;Wg",
    "iso:country":"NL",
    "sg:address":"Oude Provincia Wg 28",
    "sg:city":"Hapert",
    "sg:orig_category":"Metselwerken",
    "sg:phone":"+31 497 387 266",
    "sg:postcode":"5527 BP",
    "sg:province":"North Brabant",
    "wof:name":"Gils, Van",
    "wof:placetype":"venue"
},
  "geometry": {"coordinates":[5.255498,51.370995],"type":"Point"}
}