{
  "type": "Feature",
  "properties": {
    "addr:full":"Lupinestraat 1 Capelle A/D Ijssel South Holland 2906 CV",
    "addr:housenumber":"1;a / d",
    "addr:postcode":"2906 cv",
    "addr:street":"Lupinestraat;Ijssel South",
    "iso:country":"NL",
    "sg:address":"Lupinestraat 1",
    "sg:city":"Capelle A/D Ijssel",
    "sg:orig_category":"Bejaardeninstellingen And Serviceflats",
    "sg:phone":"+31 10 284 5555",
    "sg:postcode":"2906 CV",
    "sg:province":"South Holland",
    "wof:name":"De Rustenburg",
    "wof:placetype":"venue"
},
  "geometry": {"coordinates":[4.57061,51.936211],"type":"Point"}
}