{
  "type": "Feature",
  "properties": {
    "addr:full":"Schoolstr 13 Meyel Limburg 5768 AN",
    "addr:housenumber":"13",
    "addr:postcode":"5768 an",
    "addr:street":"Schoolstr",
    "iso:country":"NL",
    "sg:address":"Schoolstr 13",
    "sg:city":"Meyel",
    "sg:orig_category":"Meubelstoffering",
    "sg:phone":"+31 77 466 2772",
    "sg:postcode":"5768 AN",
    "sg:province":"Limburg",
    "wof:name":"Mennen, A",
    "wof:placetype":"venue"
},
  "geometry": {"coordinates":[5.88575,51.34428],"type":"Point"}
}