{
  "type": "Feature",
  "properties": {
    "addr:full":"Tuindersstraat 72 Ijmuiden Noord-Holland 1971 ZR",
    "addr:housenumber":"72",
    "addr:postcode":"1971 zr",
    "addr:street":"Tuindersstraat",
    "iso:country":"NL",
    "sg:address":"Tuindersstraat 72",
    "sg:city":"Ijmuiden",
    "sg:orig_category":"Metselwerken",
    "sg:phone":"+31 6 53271310",
    "sg:postcode":"1971 ZR",
    "sg:province":"Noord-Holland",
    "wof:name":"Bastiaansen, F",
    "wof:placetype":"venue"
},
  "geometry": {"coordinates":[4.623923,52.456676],"type":"Point"}
}