{
  "type": "Feature",
  "properties": {
    "addr:full":"Domineesln 81A Zwanenburg Noord-Holland 1161 BW",
    "addr:housenumber":"81a",
    "addr:postcode":"1161 bw",
    "addr:street":"Domineesln",
    "iso:country":"NL",
    "sg:address":"Domineesln 81A",
    "sg:city":"Zwanenburg",
    "sg:orig_category":"Verpakkingen En Verpakkingsmaterialen",
    "sg:phone":"+31 6 53332223",
    "sg:postcode":"1161 BW",
    "sg:province":"Noord-Holland",
    "wof:name":"Ruh\u00fa Vof",
    "wof:placetype":"venue"
},
  "geometry": {"coordinates":[4.74723,52.376625],"type":"Point"}
}