{
  "type": "Feature",
  "properties": {
    "addr:full":"Gentsevaart 14 Kapellebrug Zeeland 4565 EV",
    "addr:housenumber":"14",
    "addr:postcode":"4565 ev",
    "addr:street":"Gentsevaart",
    "iso:country":"NL",
    "sg:address":"Gentsevaart 14",
    "sg:city":"Kapellebrug",
    "sg:orig_category":"Film-, Tv- And Videoproductie",
    "sg:phone":"+31 114 370 208",
    "sg:postcode":"4565 EV",
    "sg:province":"Zeeland",
    "wof:name":"Kintech",
    "wof:placetype":"venue"
},
  "geometry": {"coordinates":[4.064269,51.258961],"type":"Point"}
}