{
  "type": "Feature",
  "properties": {
    "iso:country":"NL",
    "sg:address":"Gentsevaart 14",
    "sg:city":"Kapellebrug",
    "sg:orig_category":"Film-, Tv- And Videoproductie",
    "sg:phone":"+31 114 370 208",
    "sg:postcode":"4565 EV",
    "sg:province":"Zeeland",
    "wof:name":"Kintech",
    "wof:placetype":"venue"
},
  "geometry": {"coordinates":[4.064269,51.258961],"type":"Point"}
}