{
  "type": "Feature",
  "properties": {
    "addr:full":"Brugstraat 69 Roosendaal Noord-Brabant 4701 LD",
    "addr:housenumber":"69",
    "addr:postcode":"4701 ld",
    "addr:street":"Brugstraat",
    "iso:country":"NL",
    "sg:address":"Brugstraat 69",
    "sg:city":"Roosendaal",
    "sg:orig_category":"Juridische Dienstverlening",
    "sg:phone":"+31 165 544 927",
    "sg:postcode":"4701 LD",
    "sg:province":"Noord-Brabant",
    "wof:name":"Buro Voor Rechtshulp",
    "wof:placetype":"venue"
},
  "geometry": {"coordinates":[4.460117,51.538754],"type":"Point"}
}