{
  "type": "Feature",
  "properties": {
    "iso:country":"NL",
    "sg:address":"Schiekd 4",
    "sg:city":"Rotterdam",
    "sg:orig_category":"Juweliers",
    "sg:phone":"+31 10 466 8616",
    "sg:postcode":"3032 AJ",
    "sg:province":"South Holland",
    "sg:website":"http://www.juwelier.nu",
    "wof:name":"Arnold P Van Willegen Juwelier",
    "wof:placetype":"venue"
},
  "geometry": {"coordinates":[4.470867,51.931068],"type":"Point"}
}