{
  "type": "Feature",
  "properties": {
    "iso:country":"NL",
    "sg:address":"Verlengde Dorpsstraat 6",
    "sg:city":"Putten",
    "sg:orig_category":"Discountwinkels",
    "sg:phone":"+31 341 360 861",
    "sg:postcode":"3881 BG",
    "sg:province":"Gelderland",
    "wof:name":"Hans Textiel",
    "wof:placetype":"venue"
},
  "geometry": {"coordinates":[5.608591,52.260536],"type":"Point"}
}