{
  "type": "Feature",
  "properties": {
    "addr:full":"Van Bronckhorstlaan 2 Wassenaar Zuid-Holland 2242 PX",
    "addr:housenumber":"2",
    "addr:postcode":"2242 px",
    "addr:street":"Van Bronckhorstlaan",
    "iso:country":"NL",
    "sg:address":"Van Bronckhorstlaan 2",
    "sg:city":"Wassenaar",
    "sg:orig_category":"Vertaal- And Tolkenbureaus",
    "sg:phone":"+31 70 511 4800",
    "sg:postcode":"2242 PX",
    "sg:province":"Zuid-Holland",
    "wof:name":"English Writers Wassenaar",
    "wof:placetype":"venue"
},
  "geometry": {"coordinates":[4.387944,52.157616],"type":"Point"}
}