{
  "type": "Feature",
  "properties": {
    "iso:country":"NL",
    "sg:address":"Lepelaarsingel 74",
    "sg:city":"Vlaardingen",
    "sg:orig_category":"Meubelzaken, Woning- And Keukeninrichting",
    "sg:phone":"+31 10 475 1344",
    "sg:postcode":"3136 PB",
    "sg:province":"South Holland",
    "wof:name":"Robemi Bv",
    "wof:placetype":"venue"
},
  "geometry": {"coordinates":[4.353778,51.926483],"type":"Point"}
}