{
  "type": "Feature",
  "properties": {
    "addr:full":"Lanciersstr 102 Tilburg North Brabant 5017 CT",
    "addr:housenumber":"102",
    "addr:postcode":"5017 ct",
    "iso:country":"NL",
    "sg:address":"Lanciersstr 102",
    "sg:city":"Tilburg",
    "sg:orig_category":"Verenigingen En Stichtingen",
    "sg:phone":"+31 13 542 4099",
    "sg:postcode":"5017 CT",
    "sg:province":"North Brabant",
    "sg:website":"http://www.marivin.nl",
    "wof:name":"Thuishaven Tilburg, Sticht",
    "wof:placetype":"venue"
},
  "geometry": {"coordinates":[5.097393,51.554127],"type":"Point"}
}