{
  "type": "Feature",
  "properties": {
    "addr:full":"Prof Junkersln 12 Amstelveen Noord-Holland 1185 JL",
    "addr:housenumber":"12",
    "addr:postcode":"1185 jl",
    "iso:country":"NL",
    "sg:address":"Prof Junkersln 12",
    "sg:city":"Amstelveen",
    "sg:orig_category":"Bedrijfsopleidingen",
    "sg:phone":"+31 20 641 0817",
    "sg:postcode":"1185 JL",
    "sg:province":"Noord-Holland",
    "wof:name":"Som Seminars Op Maat",
    "wof:placetype":"venue"
},
  "geometry": {"coordinates":[4.851183,52.298622],"type":"Point"}
}