{
  "type": "Feature",
  "properties": {
    "iso:country":"NL",
    "sg:address":"Instr 9A",
    "sg:city":"Budel",
    "sg:orig_category":"Fitnesscentra",
    "sg:phone":"+31 495 496 810",
    "sg:postcode":"6021 AC",
    "sg:province":"Noord-Brabant",
    "wof:name":"Anna",
    "wof:placetype":"venue"
},
  "geometry": {"coordinates":[5.58209,51.265312],"type":"Point"}
}