{
  "type": "Feature",
  "properties": {
    "iso:country":"NL",
    "sg:address":"Het Hoekstuk 11",
    "sg:city":"Heiloo",
    "sg:classifiers":[
        {
            "category":"Food & Beverages",
            "subcategory":"Fruits & Vegetables",
            "type":"Retail Goods"
        }
    ],
    "sg:phone":"+31 72 533 6171",
    "sg:postcode":"1852 KX",
    "sg:province":"North Holland",
    "sg:tags":[
        "groenten"
    ],
    "wof:name":"Groentespecialist Freek Baanders",
    "wof:placetype":"venue"
},
  "geometry": {"coordinates":[4.687535,52.603832],"type":"Point"}
}