{
  "type": "Feature",
  "properties": {
    "iso:country":"NL",
    "sg:address":"Raadhuisplein 1",
    "sg:city":"Hoofddorp",
    "sg:orig_category":"Overheidsdiensten",
    "sg:phone":"+31 23 567 6543",
    "sg:postcode":"2132 TZ",
    "sg:province":"North Holland",
    "wof:name":"Gemeente Haarlemmermeer",
    "wof:placetype":"venue"
},
  "geometry": {"coordinates":[4.6963357925,52.3014640808],"type":"Point"}
}