{
  "type": "Feature",
  "properties": {
    "iso:country":"NL",
    "sg:address":"Merwedekd 119",
    "sg:city":"Utrecht",
    "sg:orig_category":"Belastingconsulenten/ Belastingadviseurs",
    "sg:phone":"+31 30 294 0498",
    "sg:postcode":"3521 EP",
    "sg:province":"Utrecht",
    "wof:name":"Vos, Mr H",
    "wof:placetype":"venue"
},
  "geometry": {"coordinates":[5.11037,52.084572],"type":"Point"}
}