{
  "type": "Feature",
  "properties": {
    "addr:full":"Reubenberg 27 Swalmen Limburg 6071 PS",
    "addr:housenumber":"27",
    "addr:postcode":"6071 ps",
    "addr:street":"Reubenberg",
    "iso:country":"NL",
    "sg:address":"Reubenberg 27",
    "sg:city":"Swalmen",
    "sg:orig_category":"Loodgieters",
    "sg:phone":"+31 475 501 972",
    "sg:postcode":"6071 PS",
    "sg:province":"Limburg",
    "wof:name":"Bisschops",
    "wof:placetype":"venue"
},
  "geometry": {"coordinates":[6.05593,51.240665],"type":"Point"}
}