{
  "type": "Feature",
  "properties": {
    "addr:full":"Monseigneur Ariensstraat 1 Rijen Noord-Brabant 5121 CA",
    "addr:housenumber":"1",
    "addr:postcode":"5121 ca",
    "addr:street":"Monseigneur Ariensstraat",
    "iso:country":"NL",
    "sg:address":"Monseigneur Ariensstraat 1",
    "sg:city":"Rijen",
    "sg:classifiers":[
        {
            "category":"Education",
            "subcategory":"Preschool",
            "type":"Public Place"
        }
    ],
    "sg:phone":"+31 161 223 987",
    "sg:postcode":"5121 CA",
    "sg:province":"Noord-Brabant",
    "sg:tags":[
        "kleuteronderwijs",
        "basis-"
    ],
    "wof:name":"Jenaplan Basisschool De Kring",
    "wof:placetype":"venue"
},
  "geometry": {"coordinates":[4.906745,51.58773],"type":"Point"}
}