{
  "type": "Feature",
  "properties": {
    "addr:full":"A V Stolkwg 46 Rotterdam South Holland 3041 JA",
    "addr:housenumber":"46",
    "addr:postcode":"3041 ja",
    "addr:street":"A;Stolkwg",
    "iso:country":"NL",
    "sg:address":"A V Stolkwg 46",
    "sg:city":"Rotterdam",
    "sg:orig_category":"Woninginrichting",
    "sg:phone":"+31 10 262 2242",
    "sg:postcode":"3041 JA",
    "sg:province":"South Holland",
    "wof:name":"Kwantum",
    "wof:placetype":"venue"
},
  "geometry": {"coordinates":[4.4418401718,51.9281311035],"type":"Point"}
}