{
  "type": "Feature",
  "properties": {
    "addr:full":"Hg Slagen 359 S Hertogenbosch Noord-Brabant 5233 SP",
    "addr:housenumber":"359",
    "addr:postcode":"5233 sp",
    "addr:street":"Hg Slagen;S Hertogenbosch",
    "iso:country":"NL",
    "sg:address":"Hg Slagen 359",
    "sg:city":"S Hertogenbosch",
    "sg:orig_category":"Montagebedrijven",
    "sg:phone":"+31 73 644 7311",
    "sg:postcode":"5233 SP",
    "sg:province":"Noord-Brabant",
    "wof:name":"Hart, De",
    "wof:placetype":"venue"
},
  "geometry": {"coordinates":[5.320069,51.709862],"type":"Point"}
}