{
  "type": "Feature",
  "properties": {
    "addr:full":"Tamboerijn 9 Soest Utrecht 3766 HA",
    "addr:housenumber":"9",
    "addr:postcode":"3766 ha",
    "addr:street":"Tamboerijn",
    "iso:country":"NL",
    "sg:address":"Tamboerijn 9",
    "sg:city":"Soest",
    "sg:orig_category":"Kaas",
    "sg:phone":"+31 35 601 8491",
    "sg:postcode":"3766 HA",
    "sg:province":"Utrecht",
    "wof:name":"Kaasspecialist, De",
    "wof:placetype":"venue"
},
  "geometry": {"coordinates":[5.2815279961,52.1691665649],"type":"Point"}
}