{
  "type": "Feature",
  "properties": {
    "iso:country":"NL",
    "sg:address":"Lombardstg 7",
    "sg:city":"Zutphen",
    "sg:orig_category":"Bedrijfsopleidingen",
    "sg:phone":"+31 575 542 459",
    "sg:postcode":"7201 LH",
    "sg:province":"Gelderland",
    "wof:name":"Liever Leren",
    "wof:placetype":"venue"
},
  "geometry": {"coordinates":[6.196974,52.141872],"type":"Point"}
}