{
  "type": "Feature",
  "properties": {
    "addr:full":"Oranjestr 1 Stryen South Holland 3291 BS",
    "addr:housenumber":"1",
    "addr:postcode":"3291 bs",
    "addr:street":"Oranjestr",
    "iso:country":"NL",
    "sg:address":"Oranjestr 1",
    "sg:city":"Stryen",
    "sg:orig_category":"Projectontwikkeling",
    "sg:phone":"+31 78 674 2117",
    "sg:postcode":"3291 BS",
    "sg:province":"South Holland",
    "wof:name":"Bomas Bv",
    "wof:placetype":"venue"
},
  "geometry": {"coordinates":[4.54727,51.750832],"type":"Point"}
}