{
  "type": "Feature",
  "properties": {
    "addr:full":"Cunerastraat 35A Nibbixwoud Noord-Holland 1688 WC",
    "addr:housenumber":"35a",
    "addr:postcode":"1688 wc",
    "addr:street":"Cunerastraat",
    "iso:country":"NL",
    "sg:address":"Cunerastraat 35A",
    "sg:city":"Nibbixwoud",
    "sg:orig_category":"Tandartsen",
    "sg:phone":"+31 229 573 535",
    "sg:postcode":"1688 WC",
    "sg:province":"Noord-Holland",
    "wof:name":"J.G. Loa",
    "wof:placetype":"venue"
},
  "geometry": {"coordinates":[5.058854,52.691776],"type":"Point"}
}