{
  "type": "Feature",
  "properties": {
    "iso:country":"NL",
    "sg:address":"1E Exloermond 111",
    "sg:city":"Eerste Exloermond",
    "sg:orig_category":"Hoefsmederijen",
    "sg:phone":"+31 599 671 933",
    "sg:postcode":"9573 PG",
    "sg:province":"Provincie Drenthe",
    "wof:name":"Dollen, J",
    "wof:placetype":"venue"
},
  "geometry": {"coordinates":[6.962185,52.939659],"type":"Point"}
}