{
  "type": "Feature",
  "properties": {
    "iso:country":"NL",
    "sg:address":"Aphroditestr 43",
    "sg:city":"Tilburg",
    "sg:orig_category":"Zonweringen",
    "sg:phone":"+31 13 572 1130",
    "sg:postcode":"5047 TW",
    "sg:province":"Noord-Brabant",
    "wof:name":"Brabant-Service",
    "wof:placetype":"venue"
},
  "geometry": {"coordinates":[5.027871,51.586575],"type":"Point"}
}