{
  "type": "Feature",
  "properties": {
    "addr:full":"Plompetorengr 19 Utrecht Utrecht 3512 CB",
    "addr:housenumber":"19",
    "addr:postcode":"3512 cb",
    "addr:street":"Plompetorengr",
    "iso:country":"NL",
    "sg:address":"Plompetorengr 19",
    "sg:city":"Utrecht",
    "sg:orig_category":"Adviesbureaus",
    "sg:phone":"+31 30 233 3937",
    "sg:postcode":"3512 CB",
    "sg:province":"Utrecht",
    "sg:website":"http://www.svmgroep.nl",
    "wof:name":"Svm St Vrijwilligers Management",
    "wof:placetype":"venue"
},
  "geometry": {"coordinates":[5.124058,52.096401],"type":"Point"}
}