{
  "type": "Feature",
  "properties": {
    "addr:full":"Pr Julianastr 92 Zaltbommel Gelderland 5301 PK",
    "addr:housenumber":"92",
    "addr:postcode":"5301 pk",
    "addr:street":"Gelderland",
    "iso:country":"NL",
    "sg:address":"Pr Julianastr 92",
    "sg:city":"Zaltbommel",
    "sg:orig_category":"Montagebedrijven",
    "sg:phone":"+31 418 512 689",
    "sg:postcode":"5301 PK",
    "sg:province":"Gelderland",
    "wof:name":"Lb 2000 Vof",
    "wof:placetype":"venue"
},
  "geometry": {"coordinates":[5.253285,51.80397],"type":"Point"}
}