{
  "type": "Feature",
  "properties": {
    "addr:full":"Veenslag 74B Veenendaal Utrecht 3905 SL",
    "addr:housenumber":"74b",
    "addr:postcode":"3905 sl",
    "addr:street":"Veenslag",
    "iso:country":"NL",
    "sg:address":"Veenslag 74B",
    "sg:city":"Veenendaal",
    "sg:orig_category":"Kaas",
    "sg:phone":"+31 318 526 444",
    "sg:postcode":"3905 SL",
    "sg:province":"Utrecht",
    "wof:name":"Zetten, M Van",
    "wof:placetype":"venue"
},
  "geometry": {"coordinates":[5.5328650475,52.0281410217],"type":"Point"}
}