{
  "type": "Feature",
  "properties": {
    "addr:full":"Monsterseweg 68 'S Gravenzande South Holland 2691 JJ",
    "addr:housenumber":"68",
    "addr:postcode":"2691 jj",
    "addr:street":"Monsterseweg;' S Gravenzande",
    "iso:country":"NL",
    "sg:address":"Monsterseweg 68",
    "sg:city":"'S Gravenzande",
    "sg:orig_category":"Bloemen And Planten",
    "sg:phone":"+31 174 413 811",
    "sg:postcode":"2691 JJ",
    "sg:province":"South Holland",
    "wof:name":"Firma L.G. Vreugdenhil & Zn",
    "wof:placetype":"venue"
},
  "geometry": {"coordinates":[4.153183,52.012299],"type":"Point"}
}