{
  "type": "Feature",
  "properties": {
    "addr:full":"V Pallandtwg 15A Neerynen Gelderland 4182 CB",
    "addr:housenumber":"15a;4182",
    "addr:postcode":"cb",
    "addr:street":"Neerynen Gelderland",
    "iso:country":"NL",
    "sg:address":"V Pallandtwg 15A",
    "sg:city":"Neerynen",
    "sg:orig_category":"Scholen Voor Basisonderwijs",
    "sg:phone":"+31 418 652 156",
    "sg:postcode":"4182 CB",
    "sg:province":"Gelderland",
    "wof:name":"Basisschool, Chr",
    "wof:placetype":"venue"
},
  "geometry": {"coordinates":[5.27931,51.8316],"type":"Point"}
}