{
  "type": "Feature",
  "properties": {
    "addr:full":"Vlaskamp 16 Leiderdorp Zuid-Holland 2353 HT",
    "addr:housenumber":"16",
    "addr:postcode":"2353 ht",
    "addr:street":"Vlaskamp",
    "iso:country":"NL",
    "sg:address":"Vlaskamp 16",
    "sg:city":"Leiderdorp",
    "sg:orig_category":"Artsen - Huisartsen",
    "sg:phone":"+31 71 589 1100",
    "sg:postcode":"2353 HT",
    "sg:province":"Zuid-Holland",
    "wof:name":"Du Ry Van Beest Holle, O",
    "wof:placetype":"venue"
},
  "geometry": {"coordinates":[4.536167,52.157806],"type":"Point"}
}