{
  "type": "Feature",
  "properties": {
    "addr:full":"Spoorhavenstr 28 Coevorden Provincie Drenthe 7741 JE",
    "addr:housenumber":"28",
    "addr:postcode":"7741 je",
    "addr:street":"Spoorhavenstr;Provincie Drenthe",
    "iso:country":"NL",
    "sg:address":"Spoorhavenstr 28",
    "sg:city":"Coevorden",
    "sg:orig_category":"Logopedisten",
    "sg:phone":"+31 524 512 151",
    "sg:postcode":"7741 JE",
    "sg:province":"Provincie Drenthe",
    "wof:name":"Valks-Bartels, W",
    "wof:placetype":"venue"
},
  "geometry": {"coordinates":[6.739582,52.659447],"type":"Point"}
}