{
  "type": "Feature",
  "properties": {
    "iso:country":"NL",
    "sg:address":"Prof Dr Zernikewg 52",
    "sg:city":"De Bilt",
    "sg:orig_category":"Orthopedagogen",
    "sg:phone":"+31 30 221 3021",
    "sg:postcode":"3731 KE",
    "sg:province":"Utrecht",
    "wof:name":"Hogenelst, Drs G G",
    "wof:placetype":"venue"
},
  "geometry": {"coordinates":[5.1788258553,52.1145973206],"type":"Point"}
}