{
  "type": "Feature",
  "properties": {
    "addr:full":"Kastanjeplein 4 Amsterdam Noord-Holland 1092 CJ",
    "addr:housenumber":"4",
    "addr:postcode":"1092 cj",
    "addr:street":"Kastanjeplein",
    "iso:country":"NL",
    "sg:address":"Kastanjeplein 4",
    "sg:city":"Amsterdam",
    "sg:orig_category":"Wasserettes And Stomerijen",
    "sg:phone":"+31 20 665 5891",
    "sg:postcode":"1092 CJ",
    "sg:province":"Noord-Holland",
    "wof:name":"Wassalon Dorst En Koelma",
    "wof:placetype":"venue"
},
  "geometry": {"coordinates":[4.9231891632,52.3588485718],"type":"Point"}
}