{
  "type": "Feature",
  "properties": {
    "iso:country":"NL",
    "sg:address":"Oranjestr 34",
    "sg:city":"Almelo",
    "sg:orig_category":"Kinderkleding",
    "sg:phone":"+31 546 452 999",
    "sg:postcode":"7607 BK",
    "sg:province":"NL.08",
    "wof:name":"Kids Avenue",
    "wof:placetype":"venue"
},
  "geometry": {"coordinates":[6.666522,52.359856],"type":"Point"}
}