{
  "type": "Feature",
  "properties": {
    "addr:full":"Zevenhuizerstr 154 Bunschoten Spakenb Utrecht 3751 LD",
    "addr:housenumber":"154",
    "addr:postcode":"3751 ld",
    "addr:street":"Bunschoten Spakenb",
    "iso:country":"NL",
    "sg:address":"Zevenhuizerstr 154",
    "sg:city":"Bunschoten Spakenb",
    "sg:classifiers":[
        {
            "category":"Sports & Exercise",
            "subcategory":"Stables",
            "type":"Entertainment"
        }
    ],
    "sg:phone":"+31 33 456 4429",
    "sg:postcode":"3751 LD",
    "sg:province":"Utrecht",
    "sg:tags":[
        "maneges"
    ],
    "wof:name":"Groenendaal",
    "wof:placetype":"venue"
},
  "geometry": {"coordinates":[5.38841,52.208462],"type":"Point"}
}