{
  "type": "Feature",
  "properties": {
    "addr:full":"Speelweide 1 Leiderdorp South Holland 2353 MP",
    "addr:housenumber":"1",
    "addr:postcode":"2353 mp",
    "addr:street":"Speelweide",
    "iso:country":"NL",
    "sg:address":"Speelweide 1",
    "sg:city":"Leiderdorp",
    "sg:orig_category":"Juridische Dienstverlening",
    "sg:phone":"+31 71 589 5538",
    "sg:postcode":"2353 MP",
    "sg:province":"South Holland",
    "wof:name":"Kanters Jura Visie",
    "wof:placetype":"venue"
},
  "geometry": {"coordinates":[4.532968,52.16814],"type":"Point"}
}