{
  "type": "Feature",
  "properties": {
    "addr:full":"Deventerpad 16 Almere Flevoland 1324 EE",
    "addr:housenumber":"16",
    "addr:postcode":"1324 ee",
    "addr:street":"Deventerpad;Flevoland",
    "iso:country":"NL",
    "sg:address":"Deventerpad 16",
    "sg:city":"Almere",
    "sg:classifiers":[
        {
            "category":"Fast Food",
            "type":"Food & Drink"
        }
    ],
    "sg:phone":"+31 36 534 0257",
    "sg:postcode":"1324 EE",
    "sg:province":"Flevoland",
    "sg:tags":[
        "afhaal",
        "restaurant"
    ],
    "wof:name":"Grill Bar Jerusalem",
    "wof:placetype":"venue"
},
  "geometry": {"coordinates":[5.214288,52.367897],"type":"Point"}
}