{
  "type": "Feature",
  "properties": {
    "addr:full":"Borgeind 47 Roermond Limburg 6041 AP",
    "addr:housenumber":"47",
    "addr:postcode":"6041 ap",
    "addr:street":"Borgeind",
    "iso:country":"NL",
    "sg:address":"Borgeind 47",
    "sg:city":"Roermond",
    "sg:orig_category":"Vertaalbureaus",
    "sg:phone":"+31 475 337 343",
    "sg:postcode":"6041 AP",
    "sg:province":"Limburg",
    "wof:name":"Rosa",
    "wof:placetype":"venue"
},
  "geometry": {"coordinates":[5.994704,51.211678],"type":"Point"}
}