{
  "type": "Feature",
  "properties": {
    "addr:full":"Wysmuller Meyerp 3 Spykenisse South Holland 3207 GL",
    "addr:housenumber":"3",
    "addr:postcode":"3207 gl",
    "addr:street":"Meyerp",
    "iso:country":"NL",
    "sg:address":"Wysmuller Meyerp 3",
    "sg:city":"Spykenisse",
    "sg:orig_category":"Pianostemmen En -Reparatie",
    "sg:phone":"+31 181 680 681",
    "sg:postcode":"3207 GL",
    "sg:province":"South Holland",
    "wof:name":"Lang, R M De",
    "wof:placetype":"venue"
},
  "geometry": {"coordinates":[4.35787,51.838669],"type":"Point"}
}