{
  "type": "Feature",
  "properties": {
    "iso:country":"NL",
    "sg:address":"J H B Koekkoekstr 43",
    "sg:city":"Hilversum",
    "sg:orig_category":"Beeldende Kunstenaars",
    "sg:phone":"+31 6 24589141",
    "sg:postcode":"1214 AC",
    "sg:province":"Noord-Holland",
    "wof:name":"Marjon Katerberg",
    "wof:placetype":"venue"
},
  "geometry": {"coordinates":[5.17437,52.219234],"type":"Point"}
}