{
  "type": "Feature",
  "properties": {
    "addr:full":"Dorpsstr 123 Zwaag Noord-Holland 1689 ET",
    "addr:housenumber":"123",
    "addr:postcode":"1689 et",
    "iso:country":"NL",
    "sg:address":"Dorpsstr 123",
    "sg:city":"Zwaag",
    "sg:orig_category":"Kinderopvang",
    "sg:phone":"+31 229 248 745",
    "sg:postcode":"1689 ET",
    "sg:province":"Noord-Holland",
    "wof:name":"Accommodatie Kindercentr Hoorn, Sticht",
    "wof:placetype":"venue"
},
  "geometry": {"coordinates":[5.068001,52.666481],"type":"Point"}
}