{
  "type": "Feature",
  "properties": {
    "addr:full":"Houtzaagmolen 103 Ridderkerk South Holland 2986 GE",
    "addr:housenumber":"103",
    "addr:postcode":"2986",
    "addr:street":"Houtzaagmolen",
    "iso:country":"NL",
    "sg:address":"Houtzaagmolen 103",
    "sg:city":"Ridderkerk",
    "sg:orig_category":"Webdesign Bureaus",
    "sg:phone":"+31 180 464 677",
    "sg:postcode":"2986 GE",
    "sg:province":"South Holland",
    "sg:website":"http://www.comwave.nl",
    "wof:name":"Comwave Bv",
    "wof:placetype":"venue"
},
  "geometry": {"coordinates":[4.6180319786,51.8661384583],"type":"Point"}
}