{
  "type": "Feature",
  "properties": {
    "iso:country":"NL",
    "sg:address":"Dr Kuyperln 26",
    "sg:city":"Velsen Zuid",
    "sg:orig_category":"Fotojournalisten Freelance",
    "sg:phone":"+31 255 540 011",
    "sg:postcode":"1981 CD",
    "sg:province":"Noord-Holland",
    "wof:name":"Kovacs, Eva",
    "wof:placetype":"venue"
},
  "geometry": {"coordinates":[4.636649,52.461674],"type":"Point"}
}