{
  "type": "Feature",
  "properties": {
    "addr:full":"Oosterstr 8 Nykerk Gld Gelderland 3861 BJ",
    "addr:housenumber":"8",
    "addr:postcode":"3861 bj",
    "addr:street":"Oosterstr;Gld Gelderland",
    "iso:country":"NL",
    "sg:address":"Oosterstr 8",
    "sg:city":"Nykerk Gld",
    "sg:orig_category":"Juweliers",
    "sg:phone":"+31 33 245 7513",
    "sg:postcode":"3861 BJ",
    "sg:province":"Gelderland",
    "wof:name":"Graaff Juwelier, De",
    "wof:placetype":"venue"
},
  "geometry": {"coordinates":[5.4831,52.221569],"type":"Point"}
}