{
  "type": "Feature",
  "properties": {
    "addr:full":"Urkerwg 62 Urk NL. 8322 NB",
    "addr:housenumber":"62",
    "addr:postcode":"8322 nb",
    "addr:street":"Urkerwg;Nl.",
    "iso:country":"NL",
    "sg:address":"Urkerwg 62",
    "sg:city":"Urk",
    "sg:orig_category":"Kinderactiviteiten",
    "sg:phone":"+31 527 687 344",
    "sg:postcode":"8322 NB",
    "sg:province":"NL.",
    "wof:name":"Stekplek, De",
    "wof:placetype":"venue"
},
  "geometry": {"coordinates":[5.63686,52.658699],"type":"Point"}
}