{
  "type": "Feature",
  "properties": {
    "addr:full":"Burg De Meesterstr 5 Harderwijk Gelderland 3846 AA",
    "addr:housenumber":"5",
    "addr:postcode":"3846 aa",
    "addr:street":"Gelderland",
    "iso:country":"NL",
    "sg:address":"Burg De Meesterstr 5",
    "sg:city":"Harderwijk",
    "sg:orig_category":"Artsen And Specialisten",
    "sg:phone":"+31 341 439 666",
    "sg:postcode":"3846 AA",
    "sg:province":"Gelderland",
    "wof:name":"Ggd Noordwest-Veluwe",
    "wof:placetype":"venue"
},
  "geometry": {"coordinates":[5.626553,52.35265],"type":"Point"}
}