{
  "type": "Feature",
  "properties": {
    "addr:full":"Palacepln 76 S Gravenhage Zuid-Holland 2587 WG",
    "addr:housenumber":"76;gravenhage",
    "addr:postcode":"2587 wg",
    "addr:street":"Palacepln;S",
    "iso:country":"NL",
    "sg:address":"Palacepln 76",
    "sg:city":"S Gravenhage",
    "sg:orig_category":"Webdesign Bureaus",
    "sg:phone":"+31 6 52340069",
    "sg:postcode":"2587 WG",
    "sg:province":"Zuid-Holland",
    "sg:website":"http://www.siteresult.com",
    "wof:name":"Site Result",
    "wof:placetype":"venue"
},
  "geometry": {"coordinates":[4.2911801338,52.1129417419],"type":"Point"}
}