{
  "type": "Feature",
  "properties": {
    "addr:full":"A Jacobsln 49 Hengelo Ov Overijssel 7555 PJ",
    "addr:housenumber":"49",
    "addr:postcode":"7555 pj",
    "addr:street":"Ov",
    "iso:country":"NL",
    "sg:address":"A Jacobsln 49",
    "sg:city":"Hengelo Ov",
    "sg:orig_category":"Ziekenhuizen, Sanatoria, Verpleeghuizen",
    "sg:phone":"+31 74 242 4491",
    "sg:postcode":"7555 PJ",
    "sg:province":"Overijssel",
    "wof:name":"Rode Kruis Ned Bloedbank",
    "wof:placetype":"venue"
},
  "geometry": {"coordinates":[6.78971,52.266331],"type":"Point"}
}