{
  "type": "Feature",
  "properties": {
    "addr:full":"Forellenwg 20 Raamsdonksveer North Brabant 4941 SJ",
    "addr:housenumber":"20",
    "addr:postcode":"4941",
    "addr:street":"Forellenwg",
    "iso:country":"NL",
    "sg:address":"Forellenwg 20",
    "sg:city":"Raamsdonksveer",
    "sg:classifiers":[
        {
            "category":"Wholesale",
            "subcategory":"Meat",
            "type":"Manufacturing & Wholesale Goods"
        }
    ],
    "sg:phone":"+31 162 523 448",
    "sg:postcode":"4941 SJ",
    "sg:province":"North Brabant",
    "sg:tags":[
        "abattoir"
    ],
    "wof:name":"Dombosch Bv",
    "wof:placetype":"venue"
},
  "geometry": {"coordinates":[4.87447,51.715897],"type":"Point"}
}