{
  "type": "Feature",
  "properties": {
    "addr:full":"Rhododendronstraat 20 Venlo Limburg 5925 EH",
    "addr:housenumber":"20",
    "addr:postcode":"5925 eh",
    "addr:street":"Rhododendronstraat",
    "iso:country":"NL",
    "sg:address":"Rhododendronstraat 20",
    "sg:city":"Venlo",
    "sg:orig_category":"Krantenuitgeverijen",
    "sg:phone":"+31 77 382 2393",
    "sg:postcode":"5925 EH",
    "sg:province":"Limburg",
    "wof:name":"Uitgeverij Mondeo",
    "wof:placetype":"venue"
},
  "geometry": {"coordinates":[6.127499,51.371807],"type":"Point"}
}