{
  "type": "Feature",
  "properties": {
    "addr:full":"Tongerseweg 57 Maastricht Limburg 6213 GA",
    "addr:housenumber":"57",
    "addr:postcode":"6213 ga",
    "addr:street":"Tongerseweg",
    "iso:country":"NL",
    "sg:address":"Tongerseweg 57",
    "sg:city":"Maastricht",
    "sg:orig_category":"Huishoudapparatuur, Televisies And Radio'S",
    "sg:phone":"+31 43 325 2661",
    "sg:postcode":"6213 GA",
    "sg:province":"Limburg",
    "wof:name":"Megapool Bv",
    "wof:placetype":"venue"
},
  "geometry": {"coordinates":[5.678409,50.843739],"type":"Point"}
}