{
  "type": "Feature",
  "properties": {
    "addr:full":"Van Kinsbergenstraat 3 Weert Limburg 6004 ET",
    "addr:housenumber":"3",
    "addr:postcode":"6004 et",
    "addr:street":"Van Kinsbergenstraat",
    "iso:country":"NL",
    "sg:address":"Van Kinsbergenstraat 3",
    "sg:city":"Weert",
    "sg:orig_category":"Kappers",
    "sg:phone":"+31 495 520 220",
    "sg:postcode":"6004 ET",
    "sg:province":"Limburg",
    "wof:name":"Kapsalon Marja M.P.A. Smeets",
    "wof:placetype":"venue"
},
  "geometry": {"coordinates":[5.7289981842,51.2531356812],"type":"Point"}
}