{
  "type": "Feature",
  "properties": {
    "iso:country":"NL",
    "sg:address":"Venbroekstraat 5",
    "sg:city":"Nieuwkuijk",
    "sg:orig_category":"Meubelzaken, Woning- And Keukeninrichting",
    "sg:phone":"+31 73 511 4985",
    "sg:postcode":"5253 AS",
    "sg:province":"Noord-Brabant",
    "wof:name":"Cantu Meubelen Bv",
    "wof:placetype":"venue"
},
  "geometry": {"coordinates":[5.185661,51.693993],"type":"Point"}
}