{
  "type": "Feature",
  "properties": {
    "addr:full":"J Heynsstr 10 Tilburg Noord-Brabant 5041 GB",
    "addr:housenumber":"10",
    "addr:postcode":"5041 gb",
    "iso:country":"NL",
    "sg:address":"J Heynsstr 10",
    "sg:city":"Tilburg",
    "sg:orig_category":"Postkantoren",
    "sg:phone":"+31 13 535 2934",
    "sg:postcode":"5041 GB",
    "sg:province":"Noord-Brabant",
    "sg:website":"http://www postkantoor.nl",
    "wof:name":"Postkantoor",
    "wof:placetype":"venue"
},
  "geometry": {"coordinates":[5.0786,51.56432],"type":"Point"}
}