{
  "type": "Feature",
  "properties": {
    "addr:full":"Bochtje 7 Riel Noord-Brabant 5133 TL",
    "addr:housenumber":"7",
    "addr:postcode":"5133 tl",
    "addr:street":"Bochtje",
    "iso:country":"NL",
    "sg:address":"Bochtje 7",
    "sg:city":"Riel",
    "sg:orig_category":"Adviesbureaus Bouwkunde",
    "sg:phone":"+31 13 518 6020",
    "sg:postcode":"5133 TL",
    "sg:province":"Noord-Brabant",
    "wof:name":"B En O Bv",
    "wof:placetype":"venue"
},
  "geometry": {"coordinates":[5.026886,51.529797],"type":"Point"}
}