{
  "type": "Feature",
  "properties": {
    "addr:full":"Burgemeester Baumannlaan 101 Rotterdam Zuid-Holland 3043 AH",
    "addr:housenumber":"101",
    "addr:postcode":"3043 ah",
    "addr:street":"Burgemeester Baumannlaan",
    "iso:country":"NL",
    "sg:address":"Burgemeester Baumannlaan 101",
    "sg:city":"Rotterdam",
    "sg:orig_category":"Verlichting And Huishoudartikelen",
    "sg:phone":"+31 10 437 1661",
    "sg:postcode":"3043 AH",
    "sg:province":"Zuid-Holland",
    "wof:name":"Hans Groen, Elektro Vof",
    "wof:placetype":"venue"
},
  "geometry": {"coordinates":[4.426651,51.937653],"type":"Point"}
}