{
  "type": "Feature",
  "properties": {
    "addr:full":"Bloemenoordplein 3 Waalwijk North Brabant 5143 TB",
    "addr:housenumber":"3",
    "addr:postcode":"5143 tb",
    "addr:street":"Bloemenoordplein",
    "iso:country":"NL",
    "sg:address":"Bloemenoordplein 3",
    "sg:city":"Waalwijk",
    "sg:orig_category":"Overheidsdiensten",
    "sg:phone":"+31 416 337 982",
    "sg:postcode":"5143 TB",
    "sg:province":"North Brabant",
    "wof:name":"Buurthuis Bloemenoord",
    "wof:placetype":"venue"
},
  "geometry": {"coordinates":[5.0795068741,51.6815261841],"type":"Point"}
}