{
  "type": "Feature",
  "properties": {
    "iso:country":"NL",
    "sg:address":"Sint Janstraat 45",
    "sg:city":"Middelburg",
    "sg:classifiers":[
        {
            "category":"Fast Food",
            "type":"Food & Drink"
        }
    ],
    "sg:phone":"+31 118 627 474",
    "sg:postcode":"4331 KB",
    "sg:province":"Zeeland",
    "sg:tags":[
        "afhaal",
        "restaurant"
    ],
    "wof:name":"De Nijl",
    "wof:placetype":"venue"
},
  "geometry": {"coordinates":[3.614375,51.49678],"type":"Point"}
}