{
  "type": "Feature",
  "properties": {
    "iso:country":"NL",
    "sg:address":"P Zeemanwg 218",
    "sg:city":"Dordrecht",
    "sg:orig_category":"Metaalgroothandel",
    "sg:phone":"+31 78 651 0765",
    "sg:postcode":"3316 GZ",
    "sg:province":"Zuid-Holland",
    "sg:website":"http://www.PFF.nl",
    "wof:name":"Pff Europa Bv",
    "wof:placetype":"venue"
},
  "geometry": {"coordinates":[4.632575,51.774281],"type":"Point"}
}