{
  "type": "Feature",
  "properties": {
    "addr:full":"V Duvenvoordestr 19 Waalwyk Noord-Brabant 5141 BP",
    "addr:housenumber":"19",
    "addr:postcode":"5141 bp",
    "addr:street":"V Duvenvoordestr",
    "iso:country":"NL",
    "sg:address":"V Duvenvoordestr 19",
    "sg:city":"Waalwyk",
    "sg:orig_category":"Homeopathie",
    "sg:phone":"+31 416 564 142",
    "sg:postcode":"5141 BP",
    "sg:province":"Noord-Brabant",
    "wof:name":"Kluijtmans, H A M",
    "wof:placetype":"venue"
},
  "geometry": {"coordinates":[5.062876,51.689789],"type":"Point"}
}