{
  "type": "Feature",
  "properties": {
    "addr:full":"Cannenburgln 257 S Gravenhage South Holland 2532 AL",
    "addr:housenumber":"257",
    "addr:postcode":"2532 al",
    "addr:street":"S Gravenhage",
    "iso:country":"NL",
    "sg:address":"Cannenburgln 257",
    "sg:city":"S Gravenhage",
    "sg:orig_category":"Onderhoudswerken",
    "sg:phone":"+31 6 22114634",
    "sg:postcode":"2532 AL",
    "sg:province":"South Holland",
    "wof:name":"Koppes",
    "wof:placetype":"venue"
},
  "geometry": {"coordinates":[4.29807,52.048569],"type":"Point"}
}