{
  "type": "Feature",
  "properties": {
    "addr:full":"Schepen Bierwischstraat 5/14 Arnhem Gelderland 6831 HZ",
    "addr:housenumber":"5 / 14",
    "addr:postcode":"6831 hz",
    "addr:street":"Schepen Bierwischstraat",
    "iso:country":"NL",
    "sg:address":"Schepen Bierwischstraat 5/14",
    "sg:city":"Arnhem",
    "sg:orig_category":"Boekhouders",
    "sg:phone":"+31 26 323 3353",
    "sg:postcode":"6831 HZ",
    "sg:province":"Gelderland",
    "wof:name":"Administratiekantoor Wien",
    "wof:placetype":"venue"
},
  "geometry": {"coordinates":[5.897418,51.959881],"type":"Point"}
}