{
  "type": "Feature",
  "properties": {
    "addr:full":"Sportln 5 Hellevoetsluis Zuid-Holland 3223 EV",
    "addr:housenumber":"5",
    "addr:postcode":"3223 ev",
    "addr:street":"Sportln",
    "iso:country":"NL",
    "sg:address":"Sportln 5",
    "sg:city":"Hellevoetsluis",
    "sg:orig_category":"Accountants - Administratie- Consulenten En -Kantoren",
    "sg:phone":"+31 181 316 400",
    "sg:postcode":"3223 EV",
    "sg:province":"Zuid-Holland",
    "wof:name":"Wea Bv",
    "wof:placetype":"venue"
},
  "geometry": {"coordinates":[4.14703,51.830406],"type":"Point"}
}