{
  "type": "Feature",
  "properties": {
    "addr:full":"Industrieweg 1 Woerden Utrecht 3442 AE",
    "addr:housenumber":"1",
    "addr:postcode":"3442 ae",
    "addr:street":"Industrieweg",
    "iso:country":"NL",
    "sg:address":"Industrieweg 1",
    "sg:city":"Woerden",
    "sg:orig_category":"Fitnesscentra",
    "sg:phone":"+31 348 420 588",
    "sg:postcode":"3442 AE",
    "sg:province":"Utrecht",
    "wof:name":"Physical Fitness",
    "wof:placetype":"venue"
},
  "geometry": {"coordinates":[4.881661,52.080826],"type":"Point"}
}