{
  "type": "Feature",
  "properties": {
    "addr:full":"In De Cramer 200 Heerlen Limburg 6412 PM",
    "addr:housenumber":"200",
    "addr:postcode":"6412 pm",
    "addr:street":"In De Cramer",
    "iso:country":"NL",
    "sg:address":"In De Cramer 200",
    "sg:city":"Heerlen",
    "sg:orig_category":"Fruit And Groenten Gh",
    "sg:phone":"+31 45 575 9200",
    "sg:postcode":"6412 PM",
    "sg:province":"Limburg",
    "wof:name":"Eussi Meyers Bv",
    "wof:placetype":"venue"
},
  "geometry": {"coordinates":[5.937676,50.901627],"type":"Point"}
}