{
  "type": "Feature",
  "properties": {
    "iso:country":"NL",
    "sg:address":"Bieselaar 30",
    "sg:city":"S Gravenmoer",
    "sg:orig_category":"Grondwerken",
    "sg:phone":"+31 162 312 820",
    "sg:postcode":"5109 BB",
    "sg:province":"Noord-Brabant",
    "wof:name":"Ernst Hulst Grondwerken",
    "wof:placetype":"venue"
},
  "geometry": {"coordinates":[4.9426,51.660007],"type":"Point"}
}