{
  "type": "Feature",
  "properties": {
    "addr:full":"Randenburgseweg 14 Reeuwijk Zuid-Holland 2811 PS",
    "addr:housenumber":"14",
    "addr:postcode":"2811 ps",
    "addr:street":"Randenburgseweg",
    "iso:country":"NL",
    "sg:address":"Randenburgseweg 14",
    "sg:city":"Reeuwijk",
    "sg:classifiers":[
        {
            "category":"Food & Beverages",
            "subcategory":"Fruits & Vegetables",
            "type":"Retail Goods"
        }
    ],
    "sg:phone":"+31 182 392 330",
    "sg:postcode":"2811 PS",
    "sg:province":"Zuid-Holland",
    "sg:tags":[
        "groenten"
    ],
    "wof:name":"J Th Vermeulen",
    "wof:placetype":"venue"
},
  "geometry": {"coordinates":[4.671227,52.061207],"type":"Point"}
}