{
  "type": "Feature",
  "properties": {
    "addr:full":"Noorderkroonstraat 164 Dordrecht South Holland 3318 VT",
    "addr:housenumber":"164",
    "addr:postcode":"3318",
    "addr:street":"Noorderkroonstraat",
    "iso:country":"NL",
    "sg:address":"Noorderkroonstraat 164",
    "sg:city":"Dordrecht",
    "sg:orig_category":"Kinderopvang Behalve Thuis",
    "sg:phone":"+31 78 652 3580",
    "sg:postcode":"3318 VT",
    "sg:province":"South Holland",
    "wof:name":"Kinderdagverblijf De Ballon",
    "wof:placetype":"venue"
},
  "geometry": {"coordinates":[4.683198,51.787586],"type":"Point"}
}