{
  "type": "Feature",
  "properties": {
    "addr:full":"Hoofdweg 99 Schildwolde Groningen 9626 AC",
    "addr:housenumber":"99",
    "addr:postcode":"9626 ac",
    "addr:street":"Hoofdweg",
    "iso:country":"NL",
    "sg:address":"Hoofdweg 99",
    "sg:city":"Schildwolde",
    "sg:orig_category":"Landbouwmachines Gh",
    "sg:phone":"+31 598 421 517",
    "sg:postcode":"9626 AC",
    "sg:province":"Groningen",
    "wof:name":"Landbouwwerktuigenhandel Broekema Bv",
    "wof:placetype":"venue"
},
  "geometry": {"coordinates":[6.814407,53.229992],"type":"Point"}
}