{
  "type": "Feature",
  "properties": {
    "iso:country":"NL",
    "sg:address":"Touwslagery 7",
    "sg:city":"Zevenbergen",
    "sg:orig_category":"Non-Classified Establishments",
    "sg:phone":"+31 168 482 220",
    "sg:postcode":"4762 AT",
    "sg:province":"Noord-Brabant",
    "wof:name":"Polucon Voegafdichtingen Bv",
    "wof:placetype":"venue"
},
  "geometry": {"coordinates":[4.622639,51.643429],"type":"Point"}
}