{
  "type": "Feature",
  "properties": {
    "addr:full":"Hermitageln 25 Amsterdam Noord-Holland 1064 WE",
    "addr:housenumber":"25",
    "addr:postcode":"1064 we",
    "addr:street":"Hermitageln",
    "iso:country":"NL",
    "sg:address":"Hermitageln 25",
    "sg:city":"Amsterdam",
    "sg:orig_category":"Fotojournalisten Freelance",
    "sg:phone":"+31 20 614 5073",
    "sg:postcode":"1064 WE",
    "sg:province":"Noord-Holland",
    "wof:name":"Brink, T Van Den",
    "wof:placetype":"venue"
},
  "geometry": {"coordinates":[4.830005,52.366695],"type":"Point"}
}