{
  "type": "Feature",
  "properties": {
    "iso:country":"NL",
    "sg:address":"Kapitein Horsmanflat 18",
    "sg:city":"Zwijndrecht",
    "sg:orig_category":"Loodgieterswerk, Verwarming And Sanitaire Installaties",
    "sg:phone":"+31 78 619 0961",
    "sg:postcode":"3333 CK",
    "sg:province":"South Holland",
    "wof:name":"Installatietechniek Oosterhout Bv",
    "wof:placetype":"venue"
},
  "geometry": {"coordinates":[4.635503,51.810394],"type":"Point"}
}