{
  "type": "Feature",
  "properties": {
    "addr:full":"Oude Zeewg 38 Noordwyk Zh Zuid-Holland 2202 CG",
    "addr:housenumber":"38",
    "addr:postcode":"2202 cg",
    "addr:street":"Oude Zeewg",
    "iso:country":"NL",
    "sg:address":"Oude Zeewg 38",
    "sg:city":"Noordwyk Zh",
    "sg:orig_category":"Verbandstoffen - Fabrieken En Groothandel",
    "sg:phone":"+31 71 361 1074",
    "sg:postcode":"2202 CG",
    "sg:province":"Zuid-Holland",
    "wof:name":"Safetycare",
    "wof:placetype":"venue"
},
  "geometry": {"coordinates":[4.43288,52.238972],"type":"Point"}
}