{
  "type": "Feature",
  "properties": {
    "addr:full":"Vyzelmolenln 1 Woerden Utrecht 3447 GX",
    "addr:housenumber":"1",
    "addr:postcode":"3447 gx",
    "addr:street":"Vyzelmolenln",
    "iso:country":"NL",
    "sg:address":"Vyzelmolenln 1",
    "sg:city":"Woerden",
    "sg:orig_category":"Verenigingen En Stichtingen",
    "sg:phone":"+31 348 431 385",
    "sg:postcode":"3447 GX",
    "sg:province":"Utrecht",
    "wof:name":"Wesp, Sticht",
    "wof:placetype":"venue"
},
  "geometry": {"coordinates":[4.891011,52.076271],"type":"Point"}
}