{
  "type": "Feature",
  "properties": {
    "addr:full":"Arenborghoeve 9 Maastricht Limburg 6225 DC",
    "addr:housenumber":"9",
    "addr:postcode":"6225",
    "addr:street":"Arenborghoeve",
    "iso:country":"NL",
    "sg:address":"Arenborghoeve 9",
    "sg:city":"Maastricht",
    "sg:orig_category":"Administratie- En Boekhoudkantoren",
    "sg:phone":"+31 43 363 5031",
    "sg:postcode":"6225 DC",
    "sg:province":"Limburg",
    "wof:name":"Janssen-Lamkin",
    "wof:placetype":"venue"
},
  "geometry": {"coordinates":[5.728508,50.861229],"type":"Point"}
}