{
  "type": "Feature",
  "properties": {
    "addr:full":"Rijnstraat 2 Ijmuiden North Holland 1972 VG",
    "addr:housenumber":"2",
    "addr:postcode":"1972 vg",
    "addr:street":"Rijnstraat",
    "iso:country":"NL",
    "sg:address":"Rijnstraat 2",
    "sg:city":"Ijmuiden",
    "sg:orig_category":"Wasserettes And Stomerijen",
    "sg:phone":"+31 255 533 534",
    "sg:postcode":"1972 VG",
    "sg:province":"North Holland",
    "wof:name":"Wonenplus",
    "wof:placetype":"venue"
},
  "geometry": {"coordinates":[4.6099319458,52.4560012817],"type":"Point"}
}