{
  "type": "Feature",
  "properties": {
    "iso:country":"NL",
    "sg:address":"Joubertstraat 7",
    "sg:city":"Rotterdam",
    "sg:classifiers":[
        {
            "category":"Education",
            "subcategory":"Preschool",
            "type":"Public Place"
        }
    ],
    "sg:phone":"+31 10 484 1651",
    "sg:postcode":"3072 XS",
    "sg:province":"South Holland",
    "sg:tags":[
        "kleuteronderwijs",
        "basis-"
    ],
    "wof:name":"Basisschool Nelson Mandela",
    "wof:placetype":"venue"
},
  "geometry": {"coordinates":[4.498017,51.902481],"type":"Point"}
}