{
  "type": "Feature",
  "properties": {
    "iso:country":"NL",
    "sg:address":"Manderveensewg 50",
    "sg:city":"Manderveen",
    "sg:classifiers":[
        {
            "category":"Retail",
            "subcategory":"Auto Repair",
            "type":"Services"
        }
    ],
    "sg:phone":"+31 546 621 507",
    "sg:postcode":"7664 VV",
    "sg:province":"Overijssel",
    "sg:tags":[
        "garage"
    ],
    "wof:name":"Horst, G P",
    "wof:placetype":"venue"
},
  "geometry": {"coordinates":[6.77798,52.434437],"type":"Point"}
}