{
  "type": "Feature",
  "properties": {
    "addr:full":"Gasselterstr 13 Stadskanaal Groningen 9503 JA",
    "addr:housenumber":"13",
    "addr:postcode":"9503 ja",
    "addr:street":"Gasselterstr",
    "iso:country":"NL",
    "sg:address":"Gasselterstr 13",
    "sg:city":"Stadskanaal",
    "sg:orig_category":"Metaalgroothandel",
    "sg:phone":"+31 599 653 104",
    "sg:postcode":"9503 JA",
    "sg:province":"Groningen",
    "wof:name":"Peter Lok Bv",
    "wof:placetype":"venue"
},
  "geometry": {"coordinates":[6.930064,53.000244],"type":"Point"}
}