{
  "type": "Feature",
  "properties": {
    "addr:full":"Kerkpln 1 Dalfsen NL.08 7721 AC",
    "addr:housenumber":"1;nl.08",
    "addr:postcode":"7721 ac",
    "addr:street":"Kerkpln",
    "iso:country":"NL",
    "sg:address":"Kerkpln 1",
    "sg:city":"Dalfsen",
    "sg:classifiers":[
        {
            "category":"Farming",
            "subcategory":"Fish & Marine Products",
            "type":"Manufacturing & Wholesale Goods"
        }
    ],
    "sg:phone":"+31 529 434 266",
    "sg:postcode":"7721 AC",
    "sg:province":"NL.08",
    "sg:tags":[
        "vi"
    ],
    "wof:name":"Beek, Ter",
    "wof:placetype":"venue"
},
  "geometry": {"coordinates":[6.26187,52.50462],"type":"Point"}
}