{
  "type": "Feature",
  "properties": {
    "iso:country":"NL",
    "sg:address":"Wilhelminaln 45",
    "sg:city":"Bennebroek",
    "sg:orig_category":"Glazenwasserijen",
    "sg:phone":"+31 23 584 6746",
    "sg:postcode":"2121 GL",
    "sg:province":"Noord-Holland",
    "wof:name":"Smit",
    "wof:placetype":"venue"
},
  "geometry": {"coordinates":[4.599748,52.320194],"type":"Point"}
}