{
  "type": "Feature",
  "properties": {
    "addr:full":"Zwanebloem 96 Den Hoorn Zh Zuid-Holland 2635 KJ",
    "addr:housenumber":"96",
    "addr:postcode":"2635 kj",
    "addr:street":"Zwanebloem",
    "iso:country":"NL",
    "sg:address":"Zwanebloem 96",
    "sg:city":"Den Hoorn Zh",
    "sg:orig_category":"Geluidsinstallaties - Verhuur",
    "sg:phone":"+31 15 285 0817",
    "sg:postcode":"2635 KJ",
    "sg:province":"Zuid-Holland",
    "wof:name":"Clc",
    "wof:placetype":"venue"
},
  "geometry": {"coordinates":[4.33191,52.005711],"type":"Point"}
}