{
  "type": "Feature",
  "properties": {
    "addr:full":"Venetiehof 61 Amsterdam North Holland 1019 NB",
    "addr:housenumber":"61",
    "addr:postcode":"1019 nb",
    "addr:street":"Venetiehof",
    "iso:country":"NL",
    "sg:address":"Venetiehof 61",
    "sg:city":"Amsterdam",
    "sg:orig_category":"Medische Installaties En Instrumenten",
    "sg:phone":"+31 20 419 3761",
    "sg:postcode":"1019 NB",
    "sg:province":"North Holland",
    "wof:name":"Novarticulatie Bv",
    "wof:placetype":"venue"
},
  "geometry": {"coordinates":[4.947466,52.377563],"type":"Point"}
}