{
  "type": "Feature",
  "properties": {
    "addr:full":"Havenstraat 5 Doetinchem Gelderland 7005 AG",
    "addr:housenumber":"5",
    "addr:postcode":"7005",
    "addr:street":"Havenstraat;Gelderland",
    "iso:country":"NL",
    "sg:address":"Havenstraat 5",
    "sg:city":"Doetinchem",
    "sg:orig_category":"Diverse Grafische Activiteiten",
    "sg:phone":"+31 314 345 107",
    "sg:postcode":"7005 AG",
    "sg:province":"Gelderland",
    "wof:name":"Leesteken",
    "wof:placetype":"venue"
},
  "geometry": {"coordinates":[6.288392,51.956654],"type":"Point"}
}