{
  "type": "Feature",
  "properties": {
    "iso:country":"NL",
    "sg:address":"Maasstraat 1",
    "sg:city":"Grave",
    "sg:orig_category":"Discountwinkels",
    "sg:phone":"+31 486 473 164",
    "sg:postcode":"5361 GE",
    "sg:province":"Louisiana",
    "wof:name":"De Schuur & De Ruif Grave Bv",
    "wof:placetype":"venue"
},
  "geometry": {"coordinates":[-92.151741,32.929253],"type":"Point"}
}