{
  "type": "Feature",
  "properties": {
    "addr:full":"Redoute 9 Hellevoetsluis Zuid-Holland 3221 LM",
    "addr:housenumber":"9",
    "addr:postcode":"3221 lm",
    "addr:street":"Redoute",
    "iso:country":"NL",
    "sg:address":"Redoute 9",
    "sg:city":"Hellevoetsluis",
    "sg:orig_category":"Verzekeringen",
    "sg:phone":"+31 181 310 382",
    "sg:postcode":"3221 LM",
    "sg:province":"Zuid-Holland",
    "wof:name":"Assurantiekantoor Y.J. Van Doesburg-Jans",
    "wof:placetype":"venue"
},
  "geometry": {"coordinates":[4.124668,51.829506],"type":"Point"}
}