{
  "type": "Feature",
  "properties": {
    "iso:country":"NL",
    "sg:address":"Bossestr 2",
    "sg:city":"Schaijk",
    "sg:orig_category":"Artsen - Huisartsen",
    "sg:phone":"+31 486 462 044",
    "sg:postcode":"5374 HT",
    "sg:province":"Noord-Brabant",
    "wof:name":"Groepspraktijk Schaijk",
    "wof:placetype":"venue"
},
  "geometry": {"coordinates":[5.62891,51.747879],"type":"Point"}
}