{
  "type": "Feature",
  "properties": {
    "addr:full":"Kinkerstraat 356 Amsterdam North Holland 1053 GG",
    "addr:housenumber":"356",
    "addr:postcode":"1053 gg",
    "addr:street":"Kinkerstraat",
    "iso:country":"NL",
    "sg:address":"Kinkerstraat 356",
    "sg:city":"Amsterdam",
    "sg:classifiers":[
        {
            "category":"Retail",
            "subcategory":"Photofinishing",
            "type":"Services"
        }
    ],
    "sg:phone":"+31 20 616 2180",
    "sg:postcode":"1053 GG",
    "sg:province":"North Holland",
    "sg:tags":[
        "foto",
        "film"
    ],
    "wof:name":"Speedy-Foto",
    "wof:placetype":"venue"
},
  "geometry": {"coordinates":[4.861667,52.3647],"type":"Point"}
}