{
  "type": "Feature",
  "properties": {
    "addr:full":"Zuiderwg 72A Wydewormer Noord-Holland 1456 NH",
    "addr:housenumber":"72a",
    "addr:postcode":"1456 nh",
    "addr:street":"Zuiderwg",
    "iso:country":"NL",
    "sg:address":"Zuiderwg 72A",
    "sg:city":"Wydewormer",
    "sg:orig_category":"Hondenscholen",
    "sg:phone":"+31 75 687 8021",
    "sg:postcode":"1456 NH",
    "sg:province":"Noord-Holland",
    "sg:website":"http://www.alldogs.biz",
    "wof:name":"All Dogs Business",
    "wof:placetype":"venue"
},
  "geometry": {"coordinates":[4.851631,52.47097],"type":"Point"}
}