{
  "type": "Feature",
  "properties": {
    "addr:full":"Postbus 383 Krimpen Ad Ijssel Zuid-Holland 2925 LB",
    "addr:housenumber":"383",
    "addr:postcode":"ijssel;2925 lb",
    "addr:street":"Postbus",
    "iso:country":"NL",
    "sg:address":"Postbus 383",
    "sg:city":"Krimpen Ad Ijssel",
    "sg:orig_category":"Film-, Tv- And Videoproductie",
    "sg:phone":"+31 180 551 737",
    "sg:postcode":"2925 LB",
    "sg:province":"Zuid-Holland",
    "wof:name":"Interoffice Turnkey Websolutions Vof",
    "wof:placetype":"venue"
},
  "geometry": {"coordinates":[4.6247,51.91724],"type":"Point"}
}