{
  "type": "Feature",
  "properties": {
    "addr:full":"Middelwaard 18 Zoetermeer Zuid-Holland 2716 CW",
    "addr:housenumber":"18",
    "addr:postcode":"2716 cw",
    "addr:street":"Middelwaard",
    "iso:country":"NL",
    "sg:address":"Middelwaard 18",
    "sg:city":"Zoetermeer",
    "sg:orig_category":"Huishoudapparatuur, Televisies And Radio'S",
    "sg:phone":"+31 79 329 0625",
    "sg:postcode":"2716 CW",
    "sg:province":"Zuid-Holland",
    "wof:name":"Expert Meerzicht",
    "wof:placetype":"venue"
},
  "geometry": {"coordinates":[4.46921,52.056129],"type":"Point"}
}