{
  "type": "Feature",
  "properties": {
    "iso:country":"NL",
    "sg:address":"Traay 93",
    "sg:city":"Driebergen Rysenb",
    "sg:orig_category":"Zoetwaren - Winkels",
    "sg:phone":"+31 343 532 274",
    "sg:postcode":"3971 GD",
    "sg:province":"Utrecht",
    "wof:name":"Chacolet",
    "wof:placetype":"venue"
},
  "geometry": {"coordinates":[5.286849,52.053635],"type":"Point"}
}