{
  "type": "Feature",
  "properties": {
    "iso:country":"NL",
    "sg:address":"De Huufkes 110",
    "sg:city":"Nuenen",
    "sg:orig_category":"Metaalwerken",
    "sg:phone":"+31 40 283 8385",
    "sg:postcode":"5674 TM",
    "sg:province":"Noord-Brabant",
    "wof:name":"N E Benelux Bv",
    "wof:placetype":"venue"
},
  "geometry": {"coordinates":[5.558413,51.447357],"type":"Point"}
}