{
  "type": "Feature",
  "properties": {
    "addr:full":"Van Aylvaweg 16 Witmarsum Friesland 8748 CE",
    "addr:housenumber":"16",
    "addr:postcode":"8748 ce",
    "addr:street":"Van Aylvaweg",
    "iso:country":"NL",
    "sg:address":"Van Aylvaweg 16",
    "sg:city":"Witmarsum",
    "sg:orig_category":"Architecten",
    "sg:phone":"+31 517 532 175",
    "sg:postcode":"8748 CE",
    "sg:province":"Friesland",
    "wof:name":"Stokje Architektenburo Bna",
    "wof:placetype":"venue"
},
  "geometry": {"coordinates":[5.464023,53.101418],"type":"Point"}
}