{
  "type": "Feature",
  "properties": {
    "iso:country":"NL",
    "sg:address":"Kanaalwg 90E",
    "sg:city":"Utrecht",
    "sg:orig_category":"Journalisten Freelance",
    "sg:phone":"+31 6 53862036",
    "sg:postcode":"3533 HG",
    "sg:province":"Utrecht",
    "sg:website":"http://www.tekstenfoto.nl",
    "wof:name":"Tekst & Foto",
    "wof:placetype":"venue"
},
  "geometry": {"coordinates":[5.09396,52.087128],"type":"Point"}
}