{
  "type": "Feature",
  "properties": {
    "addr:full":"Zuiderstr 174A Delft South Holland 2611 SJ",
    "addr:housenumber":"174a",
    "addr:postcode":"2611",
    "iso:country":"NL",
    "sg:address":"Zuiderstr 174A",
    "sg:city":"Delft",
    "sg:orig_category":"Banken",
    "sg:phone":"+31 15 215 2000",
    "sg:postcode":"2611 SJ",
    "sg:province":"South Holland",
    "wof:name":"Fortis",
    "wof:placetype":"venue"
},
  "geometry": {"coordinates":[4.363664,52.00919],"type":"Point"}
}