{
  "type": "Feature",
  "properties": {
    "addr:full":"Reiderwolderpolder 2B Woldendorp Groningen 9946 TJ",
    "addr:housenumber":"2b",
    "addr:postcode":"9946 tj",
    "addr:street":"Reiderwolderpolder",
    "iso:country":"NL",
    "sg:address":"Reiderwolderpolder 2B",
    "sg:city":"Woldendorp",
    "sg:orig_category":"Papier - Fabrieken En Groothandel",
    "sg:phone":"+31 596 601 219",
    "sg:postcode":"9946 TJ",
    "sg:province":"Groningen",
    "sg:website":"http://www.mewexpaper.nl",
    "wof:name":"Mewex Paper Bv",
    "wof:placetype":"venue"
},
  "geometry": {"coordinates":[7.058712,53.255955],"type":"Point"}
}