{
  "type": "Feature",
  "properties": {
    "addr:full":"Kotkampwg 142 Enschede Overijssel 7531 AT",
    "addr:housenumber":"142",
    "addr:postcode":"7531",
    "iso:country":"NL",
    "sg:address":"Kotkampwg 142",
    "sg:city":"Enschede",
    "sg:orig_category":"Administratie- En Boekhoudkantoren",
    "sg:phone":"+31 53 433 1365",
    "sg:postcode":"7531 AT",
    "sg:province":"Overijssel",
    "wof:name":"Aalbersberg Fin Adv/Boekhoudbur",
    "wof:placetype":"venue"
},
  "geometry": {"coordinates":[6.913877,52.23307],"type":"Point"}
}