{
  "type": "Feature",
  "properties": {
    "addr:full":"Pompsterweg 14 Middelstum Groningen 9991 TJ",
    "addr:housenumber":"14",
    "addr:postcode":"9991 tj",
    "addr:street":"Pompsterweg",
    "iso:country":"NL",
    "sg:address":"Pompsterweg 14",
    "sg:city":"Middelstum",
    "sg:orig_category":"Begrafenisondernemers",
    "sg:phone":"+31 595 552 444",
    "sg:postcode":"9991 TJ",
    "sg:province":"Groningen",
    "wof:name":"Uitvaartverzorging Robbe Bv",
    "wof:placetype":"venue"
},
  "geometry": {"coordinates":[6.64458,53.344803],"type":"Point"}
}