{
  "type": "Feature",
  "properties": {
    "iso:country":"NL",
    "sg:address":"Stationspln 10",
    "sg:city":"Roermond",
    "sg:orig_category":"Hypotheken",
    "sg:phone":"+31 475 333 669",
    "sg:postcode":"6041 GN",
    "sg:province":"Limburg",
    "sg:website":"http://www.roermond.hypotheekshop.nl/1600",
    "wof:name":"Hypotheekshop, De",
    "wof:placetype":"venue"
},
  "geometry": {"coordinates":[5.992718,51.192848],"type":"Point"}
}