{
  "type": "Feature",
  "properties": {
    "iso:country":"NL",
    "sg:address":"Voorerf 25",
    "sg:city":"Breda",
    "sg:orig_category":"Grafische Bedrijven",
    "sg:phone":"+31 76 541 9015",
    "sg:postcode":"4824 GM",
    "sg:province":"Noord-Brabant",
    "wof:name":"Idemdito",
    "wof:placetype":"venue"
},
  "geometry": {"coordinates":[4.752275,51.613815],"type":"Point"}
}