{
  "type": "Feature",
  "properties": {
    "addr:full":"Oostelijke Achterweg 50 Middelharnis South Holland 3241 CM",
    "addr:housenumber":"50",
    "addr:postcode":"3241 cm",
    "addr:street":"Oostelijke Achterweg",
    "iso:country":"NL",
    "sg:address":"Oostelijke Achterweg 50",
    "sg:city":"Middelharnis",
    "sg:orig_category":"Meubelreparatie And -Restauratie",
    "sg:phone":"+31 187 483 817",
    "sg:postcode":"3241 CM",
    "sg:province":"South Holland",
    "wof:name":"Woningstoffeerderij Van Welsenis",
    "wof:placetype":"venue"
},
  "geometry": {"coordinates":[4.167078,51.758236],"type":"Point"}
}