{
  "type": "Feature",
  "properties": {
    "addr:full":"Rembrandtstr 3 Oud Beyerland South Holland 3262 HN",
    "addr:housenumber":"3",
    "addr:postcode":"3262 hn",
    "addr:street":"Rembrandtstr;Oud Beyerland",
    "iso:country":"NL",
    "sg:address":"Rembrandtstr 3",
    "sg:city":"Oud Beyerland",
    "sg:orig_category":"Fitnesscentra",
    "sg:phone":"+31 186 622 600",
    "sg:postcode":"3262 HN",
    "sg:province":"South Holland",
    "sg:website":"http://www.fitness-world.nl",
    "wof:name":"Fitness World Oud Beyerland",
    "wof:placetype":"venue"
},
  "geometry": {"coordinates":[4.413322,51.81538],"type":"Point"}
}