{
  "type": "Feature",
  "properties": {
    "addr:full":"Brugakker 3664 Zeist Utrecht 3704 LR",
    "addr:housenumber":"3664",
    "addr:postcode":"3704 lr",
    "addr:street":"Brugakker",
    "iso:country":"NL",
    "sg:address":"Brugakker 3664",
    "sg:city":"Zeist",
    "sg:orig_category":"Adviesbureaus Bedrijfsorganisatie",
    "sg:phone":"+31 30 699 1385",
    "sg:postcode":"3704 LR",
    "sg:province":"Utrecht",
    "wof:name":"Arrow",
    "wof:placetype":"venue"
},
  "geometry": {"coordinates":[5.215272,52.081139],"type":"Point"}
}