{
  "type": "Feature",
  "properties": {
    "addr:full":"Sportlaan 1 Boskoop Zuid-Holland 2771 RW",
    "addr:housenumber":"1",
    "addr:postcode":"2771 rw",
    "addr:street":"Sportlaan",
    "iso:country":"NL",
    "sg:address":"Sportlaan 1",
    "sg:city":"Boskoop",
    "sg:orig_category":"Fitnesscentra",
    "sg:phone":"+31 172 211 710",
    "sg:postcode":"2771 RW",
    "sg:province":"Zuid-Holland",
    "wof:name":"Sporting Club Midden Boskoop",
    "wof:placetype":"venue"
},
  "geometry": {"coordinates":[4.632128,52.074818],"type":"Point"}
}