{
  "type": "Feature",
  "properties": {
    "addr:full":"Gr J V Stolbergln 795 Leidschendam Zuid-Holland 2263 BD",
    "addr:housenumber":"795",
    "addr:postcode":"2263 bd",
    "addr:street":"Gr J V Stolbergln",
    "iso:country":"NL",
    "sg:address":"Gr J V Stolbergln 795",
    "sg:city":"Leidschendam",
    "sg:orig_category":"Beregeningsinstallaties",
    "sg:phone":"+31 6 22404557",
    "sg:postcode":"2263 BD",
    "sg:province":"Zuid-Holland",
    "sg:website":"http://bblvankinsmontage.nl",
    "wof:name":"Bbl Van Kins Montage",
    "wof:placetype":"venue"
},
  "geometry": {"coordinates":[4.41042,52.10218],"type":"Point"}
}