{
  "type": "Feature",
  "properties": {
    "iso:country":"NL",
    "sg:address":"Saffierhorst 362",
    "sg:city":"'S Gravenhage",
    "sg:orig_category":"Tandartsen",
    "sg:phone":"+31 70 385 8382",
    "sg:postcode":"2592 GR",
    "sg:province":"Zuid-Holland",
    "wof:name":"J.G. Draisma",
    "wof:placetype":"venue"
},
  "geometry": {"coordinates":[4.35897,52.096561],"type":"Point"}
}