{
  "type": "Feature",
  "properties": {
    "iso:country":"NL",
    "sg:address":"Geuzenkd 49",
    "sg:city":"Amsterdam",
    "sg:classifiers":[
        {
            "category":"Manufacturing",
            "subcategory":"Rubber & Plastics",
            "type":"Manufacturing & Wholesale Goods"
        }
    ],
    "sg:phone":"+31 20 612 3819",
    "sg:postcode":"1056 KM",
    "sg:province":"North Holland",
    "sg:tags":[
        "plexiglas"
    ],
    "wof:name":"Cambridge",
    "wof:placetype":"venue"
},
  "geometry": {"coordinates":[4.85478,52.373699],"type":"Point"}
}