{
  "type": "Feature",
  "properties": {
    "addr:full":"Koekoeksbloem 2 Zeeland North Brabant 5411 GW",
    "addr:housenumber":"2",
    "addr:postcode":"5411 gw",
    "addr:street":"Koekoeksbloem",
    "iso:country":"NL",
    "sg:address":"Koekoeksbloem 2",
    "sg:city":"Zeeland",
    "sg:orig_category":"Verhuur Gereedschapsmachines And Gereedschappen",
    "sg:phone":"+31 486 452 572",
    "sg:postcode":"5411 GW",
    "sg:province":"North Brabant",
    "wof:name":"Verstraten Verhuur- En Attractiebedrijf",
    "wof:placetype":"venue"
},
  "geometry": {"coordinates":[5.684381,51.697945],"type":"Point"}
}