{
  "type": "Feature",
  "properties": {
    "iso:country":"NL",
    "sg:address":"Prometheusstr 13",
    "sg:city":"Rotterdam",
    "sg:orig_category":"Bodemonderzoek",
    "sg:phone":"+31 10 214 1600",
    "sg:postcode":"3054 WD",
    "sg:province":"Zuid-Holland",
    "wof:name":"A1 Consult Bv",
    "wof:placetype":"venue"
},
  "geometry": {"coordinates":[4.488836,51.965981],"type":"Point"}
}