{
  "type": "Feature",
  "properties": {
    "addr:full":"Europalaan 101 Utrecht Utrecht 3526 KR",
    "addr:housenumber":"101",
    "addr:postcode":"3526 kr",
    "addr:street":"Europalaan",
    "iso:country":"NL",
    "sg:address":"Europalaan 101",
    "sg:city":"Utrecht",
    "sg:orig_category":"Verhuur Kantoorapparatuur",
    "sg:phone":"+31 30 282 0888",
    "sg:postcode":"3526 KR",
    "sg:province":"Utrecht",
    "wof:name":"Leasetec Benelux",
    "wof:placetype":"venue"
},
  "geometry": {"coordinates":[5.106131,52.061329],"type":"Point"}
}