{
  "type": "Feature",
  "properties": {
    "addr:full":"Ing Van Stuivenbergweg 45 Winssen Gelderland 6645 AB",
    "addr:housenumber":"45",
    "addr:postcode":"6645 ab",
    "addr:street":"Van Stuivenbergweg;Gelderland",
    "iso:country":"NL",
    "sg:address":"Ing Van Stuivenbergweg 45",
    "sg:city":"Winssen",
    "sg:orig_category":"Boekhouders",
    "sg:phone":"+31 487 521 484",
    "sg:postcode":"6645 AB",
    "sg:province":"Gelderland",
    "wof:name":"Adm. Kantoor W. Verwey",
    "wof:placetype":"venue"
},
  "geometry": {"coordinates":[5.711407,51.880627],"type":"Point"}
}