{
  "type": "Feature",
  "properties": {
    "addr:full":"Kwartelln 6 S Gravenhage South Holland 2566 DW",
    "addr:housenumber":"6",
    "addr:postcode":"2566 dw",
    "addr:street":"Kwartelln;S Gravenhage",
    "iso:country":"NL",
    "sg:address":"Kwartelln 6",
    "sg:city":"S Gravenhage",
    "sg:orig_category":"Logopedisten",
    "sg:phone":"+31 70 325 1209",
    "sg:postcode":"2566 DW",
    "sg:province":"South Holland",
    "wof:name":"Baarsma-Van Der Smissen, M C A M",
    "wof:placetype":"venue"
},
  "geometry": {"coordinates":[4.25553,52.079128],"type":"Point"}
}