{
  "type": "Feature",
  "properties": {
    "addr:full":"V Reedestr 11 Heerhugowaard Noord-Holland 1701 EL",
    "addr:housenumber":"11;1701",
    "addr:postcode":"el",
    "iso:country":"NL",
    "sg:address":"V Reedestr 11",
    "sg:city":"Heerhugowaard",
    "sg:orig_category":"Glasdecoratie",
    "sg:phone":"+31 72 571 3079",
    "sg:postcode":"1701 EL",
    "sg:province":"Noord-Holland",
    "wof:name":"D?glas",
    "wof:placetype":"venue"
},
  "geometry": {"coordinates":[4.827522,52.665195],"type":"Point"}
}