{
  "type": "Feature",
  "properties": {
    "addr:full":"Nunspeterwg 47-49 Elspeet Gelderland 8075 AA",
    "addr:housenumber":"47-49",
    "addr:postcode":"8075 aa",
    "addr:street":"Gelderland",
    "iso:country":"NL",
    "sg:address":"Nunspeterwg 47-49",
    "sg:city":"Elspeet",
    "sg:orig_category":"Kappers",
    "sg:phone":"+31 577 491 088",
    "sg:postcode":"8075 AA",
    "sg:province":"Gelderland",
    "wof:name":"Eddy",
    "wof:placetype":"venue"
},
  "geometry": {"coordinates":[5.7848081589,52.296459198],"type":"Point"}
}