{
  "type": "Feature",
  "properties": {
    "addr:full":"Koppelstraat 4 Roggel Limburg 6088 EP",
    "addr:housenumber":"4",
    "addr:postcode":"6088 ep",
    "addr:street":"Koppelstraat",
    "iso:country":"NL",
    "sg:address":"Koppelstraat 4",
    "sg:city":"Roggel",
    "sg:orig_category":"Boekhandels",
    "sg:phone":"+31 475 491 314",
    "sg:postcode":"6088 EP",
    "sg:province":"Limburg",
    "wof:name":"Berger Kantoorboekhandel Simone",
    "wof:placetype":"venue"
},
  "geometry": {"coordinates":[5.925913,51.264397],"type":"Point"}
}