{
  "type": "Feature",
  "properties": {
    "addr:full":"Abeelwg 378 Rotterdam South Holland 3053 PH",
    "addr:housenumber":"378",
    "addr:postcode":"3053",
    "iso:country":"NL",
    "sg:address":"Abeelwg 378",
    "sg:city":"Rotterdam",
    "sg:orig_category":"Graveerbedrijven",
    "sg:phone":"+31 10 418 8352",
    "sg:postcode":"3053 PH",
    "sg:province":"South Holland",
    "wof:name":"Car Team Ned",
    "wof:placetype":"venue"
},
  "geometry": {"coordinates":[4.47535,51.963459],"type":"Point"}
}