{
  "type": "Feature",
  "properties": {
    "addr:full":"Zilvermosstraat 38 Almere NL. 1314 SR",
    "addr:housenumber":"38;1314",
    "addr:postcode":"sr",
    "addr:street":"Zilvermosstraat;Nl.",
    "iso:country":"NL",
    "sg:address":"Zilvermosstraat 38",
    "sg:city":"Almere",
    "sg:orig_category":"Verzekeringen",
    "sg:phone":"+31 36 533 3955",
    "sg:postcode":"1314 SR",
    "sg:province":"NL.",
    "wof:name":"Tom Van Der Wal Verzekeringen",
    "wof:placetype":"venue"
},
  "geometry": {"coordinates":[5.211575,52.383705],"type":"Point"}
}