{
  "type": "Feature",
  "properties": {
    "iso:country":"NL",
    "sg:address":"Zuukerend 9",
    "sg:city":"Epe",
    "sg:classifiers":[
        {
            "category":"Education",
            "subcategory":"Preschool",
            "type":"Public Place"
        }
    ],
    "sg:phone":"+31 578 620 608",
    "sg:postcode":"8161 RJ",
    "sg:province":"Gelderland",
    "sg:tags":[
        "kleuteronderwijs",
        "basis-"
    ],
    "wof:name":"Duimelot",
    "wof:placetype":"venue"
},
  "geometry": {"coordinates":[6.011558,52.332973],"type":"Point"}
}