{
  "type": "Feature",
  "properties": {
    "iso:country":"NL",
    "sg:address":"Eiberplnts 45",
    "sg:city":"Groot Ammers",
    "sg:orig_category":"Fotoreportages",
    "sg:phone":"+31 184 662 274",
    "sg:postcode":"2964 CX",
    "sg:province":"Zuid-Holland",
    "wof:name":"Fv",
    "wof:placetype":"venue"
},
  "geometry": {"coordinates":[4.819843,51.92593],"type":"Point"}
}