{
  "type": "Feature",
  "properties": {
    "addr:full":"Eikelhofweg 7A Olst NL.08 8121 CV",
    "addr:housenumber":"7a;nl.08",
    "addr:postcode":"8121 cv",
    "addr:street":"Eikelhofweg",
    "iso:country":"NL",
    "sg:address":"Eikelhofweg 7A",
    "sg:city":"Olst",
    "sg:orig_category":"Bloemen And Planten",
    "sg:phone":"+31 570 561 873",
    "sg:postcode":"8121 CV",
    "sg:province":"NL.08",
    "wof:name":"A.J. Overmars",
    "wof:placetype":"venue"
},
  "geometry": {"coordinates":[6.129277,52.327023],"type":"Point"}
}