{
  "type": "Feature",
  "properties": {
    "addr:full":"Baken 14 Krimpen Aan De Lek Zuid-Holland 2931 RP",
    "addr:housenumber":"14",
    "addr:postcode":"aan;lek;2931 rp",
    "addr:street":"Baken",
    "iso:country":"NL",
    "sg:address":"Baken 14",
    "sg:city":"Krimpen Aan De Lek",
    "sg:orig_category":"Wegenbouw",
    "sg:phone":"+31 180 524 661",
    "sg:postcode":"2931 RP",
    "sg:province":"Zuid-Holland",
    "wof:name":"Infra-Service Bv",
    "wof:placetype":"venue"
},
  "geometry": {"coordinates":[4.6348829269,51.8984947205],"type":"Point"}
}