{
  "type": "Feature",
  "properties": {
    "addr:full":"Kolkemonde 37 Nieuwegein Utrecht 3434 KX",
    "addr:housenumber":"37",
    "addr:postcode":"3434 kx",
    "addr:street":"Kolkemonde",
    "iso:country":"NL",
    "sg:address":"Kolkemonde 37",
    "sg:city":"Nieuwegein",
    "sg:orig_category":"Adviesbureaus Financieel",
    "sg:phone":"+31 30 601 9433",
    "sg:postcode":"3434 KX",
    "sg:province":"Utrecht",
    "wof:name":"Finad",
    "wof:placetype":"venue"
},
  "geometry": {"coordinates":[5.08298,52.003937],"type":"Point"}
}