{
  "type": "Feature",
  "properties": {
    "addr:full":"Glashorst 24 Scherpenzeel Gld Gelderland 3925 BS",
    "addr:housenumber":"24",
    "addr:postcode":"3925 bs",
    "addr:street":"Glashorst;Gld Gelderland",
    "iso:country":"NL",
    "sg:address":"Glashorst 24",
    "sg:city":"Scherpenzeel Gld",
    "sg:classifiers":[
        {
            "category":"Education",
            "subcategory":"Preschool",
            "type":"Public Place"
        }
    ],
    "sg:phone":"+31 33 277 2277",
    "sg:postcode":"3925 BS",
    "sg:province":"Gelderland",
    "sg:tags":[
        "kleuteronderwijs",
        "basis-"
    ],
    "wof:name":"Cbs De Glashorst",
    "wof:placetype":"venue"
},
  "geometry": {"coordinates":[5.481135,52.08028],"type":"Point"}
}