{
  "type": "Feature",
  "properties": {
    "addr:full":"Weddehoenln 21 Goor Overijssel 7471 MK",
    "addr:housenumber":"21",
    "addr:postcode":"7471",
    "addr:street":"Weddehoenln",
    "iso:country":"NL",
    "sg:address":"Weddehoenln 21",
    "sg:city":"Goor",
    "sg:orig_category":"Verzekeringen - Verzekeringskantoren",
    "sg:phone":"+31 547 275 814",
    "sg:postcode":"7471 MK",
    "sg:province":"Overijssel",
    "wof:name":"Kamstra",
    "wof:placetype":"venue"
},
  "geometry": {"coordinates":[6.585793,52.229465],"type":"Point"}
}