{
  "type": "Feature",
  "properties": {
    "addr:full":"Lunenburg 12 Veenendaal Utrecht 3904 JN",
    "addr:housenumber":"12",
    "addr:postcode":"3904 jn",
    "addr:street":"Lunenburg",
    "iso:country":"NL",
    "sg:address":"Lunenburg 12",
    "sg:city":"Veenendaal",
    "sg:orig_category":"Modevakscholen",
    "sg:phone":"+31 318 517 833",
    "sg:postcode":"3904 JN",
    "sg:province":"Utrecht",
    "wof:name":"Weerthof-Van De Kraats, G Van De",
    "wof:placetype":"venue"
},
  "geometry": {"coordinates":[5.541876,52.011604],"type":"Point"}
}