{
  "type": "Feature",
  "properties": {
    "addr:full":"Hoorn 33 Ede Gld Gelderland 6713 KR",
    "addr:housenumber":"33",
    "addr:postcode":"6713 kr",
    "addr:street":"Hoorn;Gld Gelderland",
    "iso:country":"NL",
    "sg:address":"Hoorn 33",
    "sg:city":"Ede Gld",
    "sg:orig_category":"Lasbedrijven",
    "sg:phone":"+31 318 636 139",
    "sg:postcode":"6713 KR",
    "sg:province":"Gelderland",
    "wof:name":"Vukman, B",
    "wof:placetype":"venue"
},
  "geometry": {"coordinates":[5.65173,52.034096],"type":"Point"}
}