{
  "type": "Feature",
  "properties": {
    "addr:full":"Sarphatipk 55 Amsterdam Noord-Holland 1073 CS",
    "addr:housenumber":"55",
    "addr:postcode":"1073 cs",
    "addr:street":"Sarphatipk",
    "iso:country":"NL",
    "sg:address":"Sarphatipk 55",
    "sg:city":"Amsterdam",
    "sg:orig_category":"Adviesbureaus Bedrijfsorganisatie",
    "sg:phone":"+31 20 673 8066",
    "sg:postcode":"1073 CS",
    "sg:province":"Noord-Holland",
    "wof:name":"Bwing",
    "wof:placetype":"venue"
},
  "geometry": {"coordinates":[4.896056,52.355175],"type":"Point"}
}