{
  "type": "Feature",
  "properties": {
    "addr:full":"Kelders 35 Leeuwarden Friesland 8911 JD",
    "addr:housenumber":"35",
    "addr:postcode":"8911 jd",
    "addr:street":"Kelders",
    "iso:country":"NL",
    "sg:address":"Kelders 35",
    "sg:city":"Leeuwarden",
    "sg:orig_category":"Schoenen - Reparaties",
    "sg:phone":"+31 58 212 5482",
    "sg:postcode":"8911 JD",
    "sg:province":"Friesland",
    "wof:name":"Kor Venema",
    "wof:placetype":"venue"
},
  "geometry": {"coordinates":[5.798643,53.202114],"type":"Point"}
}