{
  "type": "Feature",
  "properties": {
    "iso:country":"NL",
    "sg:address":"Siemensstr 3",
    "sg:city":"Hoogeveen",
    "sg:orig_category":"Koffie-Automaten",
    "sg:phone":"+31 800 0226800",
    "sg:postcode":"7903 AX",
    "sg:province":"Drenthe",
    "sg:website":"http://www.jede.com",
    "wof:name":"Jede Hoogeveen",
    "wof:placetype":"venue"
},
  "geometry": {"coordinates":[6.503298,52.733227],"type":"Point"}
}