{
  "type": "Feature",
  "properties": {
    "addr:full":"Warder 65 Warder North Holland 1473 PD",
    "addr:housenumber":"65",
    "addr:postcode":"1473 pd",
    "addr:street":"Warder",
    "iso:country":"NL",
    "sg:address":"Warder 65",
    "sg:city":"Warder",
    "sg:classifiers":[
        {
            "category":"Retail",
            "subcategory":"Photofinishing",
            "type":"Services"
        }
    ],
    "sg:phone":"+31 299 402 036",
    "sg:postcode":"1473 PD",
    "sg:province":"North Holland",
    "sg:tags":[
        "foto",
        "film"
    ],
    "wof:name":"E. De Zoete Bv",
    "wof:placetype":"venue"
},
  "geometry": {"coordinates":[5.020468,52.567101],"type":"Point"}
}