{
  "type": "Feature",
  "properties": {
    "addr:full":"Postbus 64 Vleuten Utrecht 3450 AB",
    "addr:housenumber":"64",
    "addr:postcode":"3450 ab",
    "addr:street":"Postbus",
    "iso:country":"NL",
    "sg:address":"Postbus 64",
    "sg:city":"Vleuten",
    "sg:orig_category":"Verloskundigen",
    "sg:phone":"+31 30 677 4979",
    "sg:postcode":"3450 AB",
    "sg:province":"Utrecht",
    "wof:name":"Verloskundigen Praktijk Vleuten De Meern Harmelen",
    "wof:placetype":"venue"
},
  "geometry": {"coordinates":[5.01061,52.106831],"type":"Point"}
}