{
  "type": "Feature",
  "properties": {
    "addr:full":"Kamperfoelie 47 Naaldwyk South Holland 2671 NJ",
    "addr:housenumber":"47",
    "addr:postcode":"2671 nj",
    "addr:street":"Kamperfoelie",
    "iso:country":"NL",
    "sg:address":"Kamperfoelie 47",
    "sg:city":"Naaldwyk",
    "sg:orig_category":"Loopbaanbegeleiding",
    "sg:phone":"+31 174 629 896",
    "sg:postcode":"2671 NJ",
    "sg:province":"South Holland",
    "wof:name":"Lansbergen",
    "wof:placetype":"venue"
},
  "geometry": {"coordinates":[4.197044,51.990433],"type":"Point"}
}