{
  "type": "Feature",
  "properties": {
    "iso:country":"NL",
    "sg:address":"Schiedamsew 56",
    "sg:city":"Vlaardingen",
    "sg:orig_category":"Artsen - Huisartsen",
    "sg:phone":"+31 10 434 2374",
    "sg:postcode":"3134 BN",
    "sg:province":"Zuid-Holland",
    "wof:name":"Spreeuw, A F M",
    "wof:placetype":"venue"
},
  "geometry": {"coordinates":[4.369352,51.906212],"type":"Point"}
}