{
  "type": "Feature",
  "properties": {
    "addr:full":"Luttekestr 42 Zwolle Overijssel 8011 LS",
    "addr:housenumber":"42",
    "addr:postcode":"8011 ls",
    "addr:street":"Luttekestr",
    "iso:country":"NL",
    "sg:address":"Luttekestr 42",
    "sg:city":"Zwolle",
    "sg:orig_category":"Lijstenmakerijen",
    "sg:phone":"+31 38 421 1195",
    "sg:postcode":"8011 LS",
    "sg:province":"Overijssel",
    "wof:name":"Lijst-In/Galeria",
    "wof:placetype":"venue"
},
  "geometry": {"coordinates":[6.090832,52.511337],"type":"Point"}
}