{
  "type": "Feature",
  "properties": {
    "addr:full":"Landstrekenln 40 S Hertogenbosch Noord-Brabant 5235 LA",
    "addr:housenumber":"40",
    "addr:postcode":"5235 la",
    "addr:street":"Landstrekenln;S",
    "iso:country":"NL",
    "sg:address":"Landstrekenln 40",
    "sg:city":"S Hertogenbosch",
    "sg:orig_category":"Schilders",
    "sg:phone":"+31 73 641 3815",
    "sg:postcode":"5235 LA",
    "sg:province":"Noord-Brabant",
    "wof:name":"Boxtel, Van",
    "wof:placetype":"venue"
},
  "geometry": {"coordinates":[5.303697,51.727654],"type":"Point"}
}