{
  "type": "Feature",
  "properties": {
    "addr:full":"Waaldijk 5 Opijnen Gelderland 4184 EK",
    "addr:housenumber":"5",
    "addr:postcode":"4184 ek",
    "addr:street":"Waaldijk;Gelderland",
    "iso:country":"NL",
    "sg:address":"Waaldijk 5",
    "sg:city":"Opijnen",
    "sg:orig_category":"Wegen And Sportterreinen",
    "sg:phone":"+31 418 657 380",
    "sg:postcode":"4184 EK",
    "sg:province":"Gelderland",
    "wof:name":"E.M.W. Wegenbouw Bv",
    "wof:placetype":"venue"
},
  "geometry": {"coordinates":[5.2946767807,51.8269424438],"type":"Point"}
}