{
  "type": "Feature",
  "properties": {
    "addr:full":"Fazantstraat 23 Maassluis South Holland 3145 CA",
    "addr:housenumber":"23",
    "addr:postcode":"3145 ca",
    "addr:street":"Fazantstraat",
    "iso:country":"NL",
    "sg:address":"Fazantstraat 23",
    "sg:city":"Maassluis",
    "sg:orig_category":"Onderhoud And Reparatie Kantoorapparatuur",
    "sg:phone":"+31 10 591 3316",
    "sg:postcode":"3145 CA",
    "sg:province":"South Holland",
    "wof:name":"Aviation And Industrial Supplies Int Bv",
    "wof:placetype":"venue"
},
  "geometry": {"coordinates":[4.23287,51.931973],"type":"Point"}
}