{
  "type": "Feature",
  "properties": {
    "addr:full":"Stationsplein 1 Gouda Zuid-Holland 2801 AK",
    "addr:housenumber":"1",
    "addr:postcode":"2801 ak",
    "addr:street":"Stationsplein",
    "iso:country":"NL",
    "sg:address":"Stationsplein 1",
    "sg:city":"Gouda",
    "sg:orig_category":"Hypotheken And Hypotheekbanken",
    "sg:phone":"+31 182 514 258",
    "sg:postcode":"2801 AK",
    "sg:province":"Zuid-Holland",
    "wof:name":"De Hypotheker Gouda",
    "wof:placetype":"venue"
},
  "geometry": {"coordinates":[4.706689,52.016659],"type":"Point"}
}