{
  "type": "Feature",
  "properties": {
    "addr:full":"Engestr 12 Deventer NL.08 7411 LD",
    "addr:housenumber":"12;nl.08",
    "addr:postcode":"7411 ld",
    "addr:street":"Engestr",
    "iso:country":"NL",
    "sg:address":"Engestr 12",
    "sg:city":"Deventer",
    "sg:orig_category":"Herenkleding",
    "sg:phone":"+31 570 612 076",
    "sg:postcode":"7411 LD",
    "sg:province":"NL.08",
    "wof:name":"Hekkers",
    "wof:placetype":"venue"
},
  "geometry": {"coordinates":[6.156093,52.253716],"type":"Point"}
}