{
  "type": "Feature",
  "properties": {
    "addr:full":"Zuidlandstraat 111 Terneuzen Zeeland 4532 CK",
    "addr:housenumber":"111",
    "addr:postcode":"4532 ck",
    "addr:street":"Zuidlandstraat",
    "iso:country":"NL",
    "sg:address":"Zuidlandstraat 111",
    "sg:city":"Terneuzen",
    "sg:orig_category":"Zalenexploitatie",
    "sg:phone":"+31 115 694 900",
    "sg:postcode":"4532 CK",
    "sg:province":"Zeeland",
    "wof:name":"Zuidlandtheater",
    "wof:placetype":"venue"
},
  "geometry": {"coordinates":[3.840456,51.328918],"type":"Point"}
}