{
  "type": "Feature",
  "properties": {
    "addr:full":"Potgieterstraat 73 Vlaardingen Zuid-Holland 3131 GT",
    "addr:housenumber":"73",
    "addr:postcode":"3131 gt",
    "addr:street":"Potgieterstraat",
    "iso:country":"NL",
    "sg:address":"Potgieterstraat 73",
    "sg:city":"Vlaardingen",
    "sg:classifiers":[
        {
            "category":"Fast Food",
            "type":"Food & Drink"
        }
    ],
    "sg:phone":"+31 10 434 9995",
    "sg:postcode":"3131 GT",
    "sg:province":"Zuid-Holland",
    "sg:tags":[
        "afhaal",
        "restaurant"
    ],
    "wof:name":"Haringhandel W. Prins",
    "wof:placetype":"venue"
},
  "geometry": {"coordinates":[4.338996,51.913342],"type":"Point"}
}