{
  "type": "Feature",
  "properties": {
    "iso:country":"NL",
    "sg:address":"Spaarndamseweg 380/Fl8",
    "sg:city":"Haarlem",
    "sg:orig_category":"Diverse Grafische Activiteiten",
    "sg:phone":"+31 23 526 8335",
    "sg:postcode":"2022 EA",
    "sg:province":"North Holland",
    "wof:name":"Design Studio Sensation",
    "wof:placetype":"venue"
},
  "geometry": {"coordinates":[4.65061,52.402458],"type":"Point"}
}