{
  "type": "Feature",
  "properties": {
    "addr:full":"Achter De Broeren 10 Zwolle Overijssel 8011 VA",
    "addr:housenumber":"10",
    "addr:postcode":"8011",
    "addr:street":"Achter De Broeren",
    "iso:country":"NL",
    "sg:address":"Achter De Broeren 10",
    "sg:city":"Zwolle",
    "sg:orig_category":"Zoetwaren - Winkels",
    "sg:phone":"+31 38 423 1294",
    "sg:postcode":"8011 VA",
    "sg:province":"Overijssel",
    "wof:name":"Suikeroom",
    "wof:placetype":"venue"
},
  "geometry": {"coordinates":[6.095616,52.513519],"type":"Point"}
}