{
  "type": "Feature",
  "properties": {
    "addr:full":"Coolsngl 18 Rotterdam Zuid-Holland 3011 AD",
    "addr:housenumber":"18",
    "addr:postcode":"3011 ad",
    "addr:street":"Coolsngl",
    "iso:country":"NL",
    "sg:address":"Coolsngl 18",
    "sg:city":"Rotterdam",
    "sg:orig_category":"Kantoorbenodigdheden",
    "sg:phone":"+31 10 411 1850",
    "sg:postcode":"3011 AD",
    "sg:province":"Zuid-Holland",
    "wof:name":"Tim Office Innovation Bv",
    "wof:placetype":"venue"
},
  "geometry": {"coordinates":[4.4784550667,51.9228363037],"type":"Point"}
}