{
  "type": "Feature",
  "properties": {
    "addr:full":"Elegaststr 22 Alkmaar Noord-Holland 1813 LA",
    "addr:housenumber":"22",
    "addr:postcode":"1813 la",
    "addr:street":"Elegaststr",
    "iso:country":"NL",
    "sg:address":"Elegaststr 22",
    "sg:city":"Alkmaar",
    "sg:orig_category":"Webdesign Bureaus",
    "sg:phone":"+31 72 547 0734",
    "sg:postcode":"1813 LA",
    "sg:province":"Noord-Holland",
    "sg:website":"http://www.2men.nl",
    "wof:name":"2Men",
    "wof:placetype":"venue"
},
  "geometry": {"coordinates":[4.7530179024,52.6175956726],"type":"Point"}
}