{
  "type": "Feature",
  "properties": {
    "addr:full":"Hoofdwg 2030 Buitenkaag Noord-Holland 2158 MC",
    "addr:housenumber":"2158",
    "addr:postcode":"2030 buitenkaag;mc",
    "iso:country":"NL",
    "sg:address":"Hoofdwg 2030",
    "sg:city":"Buitenkaag",
    "sg:orig_category":"Verf En Lak - Fabrieken En Groothandel",
    "sg:phone":"+31 252 544 994",
    "sg:postcode":"2158 MC",
    "sg:province":"Noord-Holland",
    "wof:name":"Muko",
    "wof:placetype":"venue"
},
  "geometry": {"coordinates":[4.55999,52.220959],"type":"Point"}
}