{
  "type": "Feature",
  "properties": {
    "addr:full":"Brederodestraat 158 Zandvoort Noord-Holland 2042 BM",
    "addr:housenumber":"158",
    "addr:postcode":"zandvoort;2042 bm",
    "addr:street":"Brederodestraat",
    "iso:country":"NL",
    "sg:address":"Brederodestraat 158",
    "sg:city":"Zandvoort",
    "sg:orig_category":"Juridische Dienstverlening",
    "sg:phone":"+31 23 571 8115",
    "sg:postcode":"2042 BM",
    "sg:province":"Noord-Holland",
    "wof:name":"Mr M J E J Coenraad",
    "wof:placetype":"venue"
},
  "geometry": {"coordinates":[4.52403,52.36797],"type":"Point"}
}