{
  "type": "Feature",
  "properties": {
    "addr:full":"Wilhelminapark 32 Meppel Drenthe 7941 GN",
    "addr:housenumber":"32",
    "addr:postcode":"7941 gn",
    "addr:street":"Wilhelminapark",
    "iso:country":"NL",
    "sg:address":"Wilhelminapark 32",
    "sg:city":"Meppel",
    "sg:orig_category":"Diverse Bedrijfsinstallaties Gh",
    "sg:phone":"+31 522 263 242",
    "sg:postcode":"7941 GN",
    "sg:province":"Drenthe",
    "wof:name":"Gerard Industrial Services",
    "wof:placetype":"venue"
},
  "geometry": {"coordinates":[6.196295,52.699615],"type":"Point"}
}