{
  "type": "Feature",
  "properties": {
    "addr:full":"Bakkerstr 62-2 Arnhem Gelderland 6811 EK",
    "addr:housenumber":"62-2",
    "addr:postcode":"6811 ek",
    "iso:country":"NL",
    "sg:address":"Bakkerstr 62-2",
    "sg:city":"Arnhem",
    "sg:orig_category":"Kasregisters",
    "sg:phone":"+31 26 389 2708",
    "sg:postcode":"6811 EK",
    "sg:province":"Gelderland",
    "wof:name":"Doosjen",
    "wof:placetype":"venue"
},
  "geometry": {"coordinates":[5.907949,51.980328],"type":"Point"}
}