{
  "type": "Feature",
  "properties": {
    "addr:full":"Dorpsstraat 190 Zevenhuizen Zh South Holland 2761 AJ",
    "addr:housenumber":"190;zh",
    "addr:postcode":"2761 aj",
    "addr:street":"Dorpsstraat",
    "iso:country":"NL",
    "sg:address":"Dorpsstraat 190",
    "sg:city":"Zevenhuizen Zh",
    "sg:orig_category":"Banken And Kredietinstellingen",
    "sg:phone":"+31 180 637 383",
    "sg:postcode":"2761 AJ",
    "sg:province":"South Holland",
    "wof:name":"Rabobank",
    "wof:placetype":"venue"
},
  "geometry": {"coordinates":[4.580717,52.013035],"type":"Point"}
}