{
  "type": "Feature",
  "properties": {
    "iso:country":"NL",
    "sg:address":"Tongelreep 45",
    "sg:city":"Veldhoven",
    "sg:orig_category":"Afslankinstituten",
    "sg:phone":"+31 40 254 8367",
    "sg:postcode":"5504 MS",
    "sg:province":"Noord-Brabant",
    "wof:name":"In Vorm",
    "wof:placetype":"venue"
},
  "geometry": {"coordinates":[5.39181,51.400684],"type":"Point"}
}