{
  "type": "Feature",
  "properties": {
    "addr:full":"Maasdijk 166A Maasdijk South Holland 2676 LC",
    "addr:housenumber":"166a",
    "addr:postcode":"2676 lc",
    "addr:street":"Maasdijk",
    "iso:country":"NL",
    "sg:address":"Maasdijk 166A",
    "sg:city":"Maasdijk",
    "sg:orig_category":"Land- En Tuinbouw - Loonbedrijven",
    "sg:phone":"+31 174 512 700",
    "sg:postcode":"2676 LC",
    "sg:province":"South Holland",
    "wof:name":"Jong, J De",
    "wof:placetype":"venue"
},
  "geometry": {"coordinates":[4.225564,51.954178],"type":"Point"}
}