{
  "type": "Feature",
  "properties": {
    "addr:full":"Tesselschadestraat 19 Beek Ubbergen Gelderland 6573 BW",
    "addr:housenumber":"19",
    "addr:postcode":"6573 bw",
    "addr:street":"Tesselschadestraat",
    "iso:country":"NL",
    "sg:address":"Tesselschadestraat 19",
    "sg:city":"Beek Ubbergen",
    "sg:orig_category":"Bedrijfs- And Managementsconsultants",
    "sg:phone":"+31 24 684 1058",
    "sg:postcode":"6573 BW",
    "sg:province":"Gelderland",
    "wof:name":"J.H.M. Van Oerle",
    "wof:placetype":"venue"
},
  "geometry": {"coordinates":[5.923447,51.831768],"type":"Point"}
}