{
  "type": "Feature",
  "properties": {
    "addr:full":"Kokerstr 49 Wormer Noord-Holland 1531 DX",
    "addr:housenumber":"49",
    "addr:postcode":"1531 dx",
    "addr:street":"Kokerstr",
    "iso:country":"NL",
    "sg:address":"Kokerstr 49",
    "sg:city":"Wormer",
    "sg:orig_category":"Goudsmeden En Zilversmeden",
    "sg:phone":"+31 75 642 1178",
    "sg:postcode":"1531 DX",
    "sg:province":"Noord-Holland",
    "wof:name":"Driek Hartman",
    "wof:placetype":"venue"
},
  "geometry": {"coordinates":[4.813968,52.496471],"type":"Point"}
}