{
  "type": "Feature",
  "properties": {
    "addr:full":"Nassaukade 31 Amsterdam North Holland 1052 CK",
    "addr:housenumber":"31",
    "addr:postcode":"1052 ck",
    "addr:street":"Nassaukade",
    "iso:country":"NL",
    "sg:address":"Nassaukade 31",
    "sg:city":"Amsterdam",
    "sg:orig_category":"Loodgieterswerk, Verwarming And Sanitaire Installaties",
    "sg:phone":"+31 20 684 3987",
    "sg:postcode":"1052 CK",
    "sg:province":"North Holland",
    "wof:name":"G. Abrahams",
    "wof:placetype":"venue"
},
  "geometry": {"coordinates":[4.880414,52.383255],"type":"Point"}
}