{
  "type": "Feature",
  "properties": {
    "iso:country":"NL",
    "sg:address":"De Hemmen 91",
    "sg:city":"Drachten",
    "sg:orig_category":"Fietsen - Fabrieken En Groothandel",
    "sg:phone":"+31 512 518 461",
    "sg:postcode":"9206 AG",
    "sg:province":"Friesland",
    "wof:name":"Wsb Hi-Tech",
    "wof:placetype":"venue"
},
  "geometry": {"coordinates":[6.066668,53.112167],"type":"Point"}
}