{
  "type": "Feature",
  "properties": {
    "addr:full":"1E Kruisdiep Wz 95 Nieuw Weerdinge Provincie Drenthe 7831 CC",
    "addr:housenumber":"95;7831",
    "addr:postcode":"cc",
    "addr:street":"1E Kruisdiep Wz;Nieuw Weerdinge Provincie Drenthe",
    "iso:country":"NL",
    "sg:address":"1E Kruisdiep Wz 95",
    "sg:city":"Nieuw Weerdinge",
    "sg:classifiers":[
        {
            "category":"Retail",
            "subcategory":"Auto Repair",
            "type":"Services"
        }
    ],
    "sg:phone":"+31 591 521 466",
    "sg:postcode":"7831 CC",
    "sg:province":"Provincie Drenthe",
    "sg:tags":[
        "garage"
    ],
    "sg:website":"http://www.tjeerdsma.org",
    "wof:name":"Tjeerdsma, H",
    "wof:placetype":"venue"
},
  "geometry": {"coordinates":[6.991602,52.854076],"type":"Point"}
}