{
  "type": "Feature",
  "properties": {
    "addr:full":"Postbus 6302 Melick Limburg 6074 ZG",
    "addr:housenumber":"6302",
    "addr:postcode":"6074 zg",
    "addr:street":"Postbus",
    "iso:country":"NL",
    "sg:address":"Postbus 6302",
    "sg:city":"Melick",
    "sg:orig_category":"Artiesten/Gezelschappen",
    "sg:phone":"+31 475 329 257",
    "sg:postcode":"6074 ZG",
    "sg:province":"Limburg",
    "wof:name":"Tiggers Vof",
    "wof:placetype":"venue"
},
  "geometry": {"coordinates":[8.18495,46.834366],"type":"Point"}
}