{
  "type": "Feature",
  "properties": {
    "addr:full":"Pieterstraat 7 Geleen Limburg 6166 AN",
    "addr:housenumber":"7",
    "addr:postcode":"6166 an",
    "addr:street":"Pieterstraat",
    "iso:country":"NL",
    "sg:address":"Pieterstraat 7",
    "sg:city":"Geleen",
    "sg:orig_category":"Slagerijen",
    "sg:phone":"+31 46 474 3716",
    "sg:postcode":"6166 AN",
    "sg:province":"Limburg",
    "wof:name":"Slagerij Jan Salden Bv",
    "wof:placetype":"venue"
},
  "geometry": {"coordinates":[5.841659,50.970509],"type":"Point"}
}