{
  "type": "Feature",
  "properties": {
    "iso:country":"NL",
    "sg:address":"Grotestr 145",
    "sg:city":"Ede Gld",
    "sg:orig_category":"Bloemen En Planten",
    "sg:phone":"+31 318 653 367",
    "sg:postcode":"6711 AL",
    "sg:province":"Gelderland",
    "wof:name":"Roel",
    "wof:placetype":"venue"
},
  "geometry": {"coordinates":[5.670333,52.049004],"type":"Point"}
}