{
  "type": "Feature",
  "properties": {
    "addr:full":"Grotestr 145 Ede Gld Gelderland 6711 AL",
    "addr:housenumber":"145;6711",
    "addr:postcode":"al",
    "addr:street":"Gld Gelderland",
    "iso:country":"NL",
    "sg:address":"Grotestr 145",
    "sg:city":"Ede Gld",
    "sg:orig_category":"Bloemen En Planten",
    "sg:phone":"+31 318 653 367",
    "sg:postcode":"6711 AL",
    "sg:province":"Gelderland",
    "wof:name":"Roel",
    "wof:placetype":"venue"
},
  "geometry": {"coordinates":[5.670333,52.049004],"type":"Point"}
}