{
  "type": "Feature",
  "properties": {
    "iso:country":"NL",
    "sg:address":"Parallelwg 57",
    "sg:city":"Bergen Op Zoom",
    "sg:orig_category":"Honden- En Kattentrimsalons",
    "sg:phone":"+31 164 245 144",
    "sg:postcode":"4621 JR",
    "sg:province":"North Brabant",
    "wof:name":"Sylvia",
    "wof:placetype":"venue"
},
  "geometry": {"coordinates":[4.296824,51.493729],"type":"Point"}
}