{
  "type": "Feature",
  "properties": {
    "addr:full":"Tilburgsewg 136 Goirle Noord-Brabant 5051 AK",
    "addr:housenumber":"136",
    "addr:postcode":"goirle;5051 ak",
    "iso:country":"NL",
    "sg:address":"Tilburgsewg 136",
    "sg:city":"Goirle",
    "sg:orig_category":"Adviesbureaus Bedrijfsorganisatie",
    "sg:phone":"+31 13 530 0560",
    "sg:postcode":"5051 AK",
    "sg:province":"Noord-Brabant",
    "wof:name":"Wegdam",
    "wof:placetype":"venue"
},
  "geometry": {"coordinates":[5.063508,51.526733],"type":"Point"}
}