{
  "type": "Feature",
  "properties": {
    "addr:full":"J V Galenstr 90 Zwyndrecht Zuid-Holland 3333 TK",
    "addr:housenumber":"90",
    "addr:postcode":"3333 tk",
    "addr:street":"J;Galenstr",
    "iso:country":"NL",
    "sg:address":"J V Galenstr 90",
    "sg:city":"Zwyndrecht",
    "sg:orig_category":"Koeriersdiensten",
    "sg:phone":"+31 6 53853753",
    "sg:postcode":"3333 TK",
    "sg:province":"Zuid-Holland",
    "wof:name":"Vree, De",
    "wof:placetype":"venue"
},
  "geometry": {"coordinates":[4.63394,51.81358],"type":"Point"}
}