{
  "type": "Feature",
  "properties": {
    "addr:full":"Schoolstr 6 Beuningen Gld Gelderland 6641 DC",
    "addr:housenumber":"6",
    "addr:postcode":"6641",
    "addr:street":"Schoolstr",
    "iso:country":"NL",
    "sg:address":"Schoolstr 6",
    "sg:city":"Beuningen Gld",
    "sg:orig_category":"Zalenverhuur",
    "sg:phone":"+31 24 677 1703",
    "sg:postcode":"6641 DC",
    "sg:province":"Gelderland",
    "wof:name":"L?ghe Polder, De",
    "wof:placetype":"venue"
},
  "geometry": {"coordinates":[5.77211,51.861916],"type":"Point"}
}