{
  "type": "Feature",
  "properties": {
    "iso:country":"NL",
    "sg:address":"Bernhardstraat 5",
    "sg:city":"Cuijk",
    "sg:orig_category":"Overheidsdiensten",
    "sg:phone":"+31 485 318 413",
    "sg:postcode":"5431 TW",
    "sg:province":"Noord-Brabant",
    "wof:name":"Den Oeiep",
    "wof:placetype":"venue"
},
  "geometry": {"coordinates":[5.8757967949,51.7307052612],"type":"Point"}
}