{
  "type": "Feature",
  "properties": {
    "addr:full":"Aardster 219 Alphen A/D Rijn South Holland 2403 RP",
    "addr:housenumber":"219",
    "addr:postcode":"2403 rp",
    "addr:street":"Aardster",
    "iso:country":"NL",
    "sg:address":"Aardster 219",
    "sg:city":"Alphen A/D Rijn",
    "sg:orig_category":"Goederenvervoer Over De Weg",
    "sg:phone":"+31 172 444 820",
    "sg:postcode":"2403 RP",
    "sg:province":"South Holland",
    "wof:name":"Transportbedrijf J.G. Van Rijn",
    "wof:placetype":"venue"
},
  "geometry": {"coordinates":[4.678647,52.149986],"type":"Point"}
}