{
  "type": "Feature",
  "properties": {
    "iso:country":"NL",
    "sg:address":"Kerklaan 7",
    "sg:city":"Erica",
    "sg:orig_category":"Loodgieterswerk, Verwarming And Sanitaire Installaties",
    "sg:phone":"+31 591 303 020",
    "sg:postcode":"7887 AT",
    "sg:province":"Drenthe",
    "wof:name":"J.H. Keuter",
    "wof:placetype":"venue"
},
  "geometry": {"coordinates":[6.928205,52.716022],"type":"Point"}
}