{
  "type": "Feature",
  "properties": {
    "addr:full":"Grondmolen 61 Papendrecht Zuid-Holland 3352 CC",
    "addr:housenumber":"61",
    "addr:postcode":"3352 cc",
    "addr:street":"Grondmolen",
    "iso:country":"NL",
    "sg:address":"Grondmolen 61",
    "sg:city":"Papendrecht",
    "sg:orig_category":"Binnenhuisarchitecten",
    "sg:phone":"+31 78 641 4101",
    "sg:postcode":"3352 CC",
    "sg:province":"Zuid-Holland",
    "wof:name":"Meander Interieurs",
    "wof:placetype":"venue"
},
  "geometry": {"coordinates":[4.691657,51.843449],"type":"Point"}
}