{
  "type": "Feature",
  "properties": {
    "addr:full":"Keulsebaan 10 Neerkant North Brabant 5758 AB",
    "addr:housenumber":"10",
    "addr:postcode":"5758 ab",
    "addr:street":"Keulsebaan",
    "iso:country":"NL",
    "sg:address":"Keulsebaan 10",
    "sg:city":"Neerkant",
    "sg:orig_category":"Kappers",
    "sg:phone":"+31 77 466 2987",
    "sg:postcode":"5758 AB",
    "sg:province":"North Brabant",
    "wof:name":"Monique",
    "wof:placetype":"venue"
},
  "geometry": {"coordinates":[5.865366,51.365639],"type":"Point"}
}