{
  "type": "Feature",
  "properties": {
    "iso:country":"NL",
    "sg:address":"Kervelhof 35",
    "sg:city":"Rotterdam",
    "sg:orig_category":"Verhuur Audiovisuele Apparatuur",
    "sg:phone":"+31 10 438 5134",
    "sg:postcode":"3193 JG",
    "sg:province":"Zuid-Holland",
    "wof:name":"Niko",
    "wof:placetype":"venue"
},
  "geometry": {"coordinates":[4.348202,51.862621],"type":"Point"}
}