{
  "type": "Feature",
  "properties": {
    "addr:full":"Terpstraat 9 Wieringerwerf Noord-Holland 1771 AC",
    "addr:housenumber":"9",
    "addr:postcode":"1771 ac",
    "addr:street":"Terpstraat",
    "iso:country":"NL",
    "sg:address":"Terpstraat 9",
    "sg:city":"Wieringerwerf",
    "sg:orig_category":"Discountwinkels",
    "sg:phone":"+31 227 601 700",
    "sg:postcode":"1771 AC",
    "sg:province":"Noord-Holland",
    "wof:name":"Passepartout Vonder Mode En Textiel",
    "wof:placetype":"venue"
},
  "geometry": {"coordinates":[5.023198,52.851479],"type":"Point"}
}