{
  "type": "Feature",
  "properties": {
    "addr:full":"De Killick 24 Dronten Flevoland 8251 DA",
    "addr:housenumber":"24;8251",
    "addr:postcode":"da",
    "addr:street":"De Killick;Flevoland",
    "iso:country":"NL",
    "sg:address":"De Killick 24",
    "sg:city":"Dronten",
    "sg:orig_category":"Fotostudio'S And Fotografen",
    "sg:phone":"+31 321 317 513",
    "sg:postcode":"8251 DA",
    "sg:province":"Flevoland",
    "wof:name":"Fotografie Harry Werkman",
    "wof:placetype":"venue"
},
  "geometry": {"coordinates":[5.727163,52.516384],"type":"Point"}
}