{
  "type": "Feature",
  "properties": {
    "addr:full":"Kerkstr 52 Lage Zwaluwe Noord-Brabant 4926 CX",
    "addr:housenumber":"52",
    "addr:postcode":"zwaluwe;4926 cx",
    "addr:street":"Kerkstr",
    "iso:country":"NL",
    "sg:address":"Kerkstr 52",
    "sg:city":"Lage Zwaluwe",
    "sg:orig_category":"Centrale Verwarming - Installatie En Onderhoud",
    "sg:phone":"+31 6 53928070",
    "sg:postcode":"4926 CX",
    "sg:province":"Noord-Brabant",
    "sg:website":"http://www.aargo.nl",
    "wof:name":"Aargo",
    "wof:placetype":"venue"
},
  "geometry": {"coordinates":[4.702698,51.711296],"type":"Point"}
}