{
  "type": "Feature",
  "properties": {
    "iso:country":"NL",
    "sg:address":"V V Goghpln 60",
    "sg:city":"Almelo",
    "sg:classifiers":[
        {
            "category":"Food & Beverages",
            "subcategory":"Bakery",
            "type":"Retail Goods"
        }
    ],
    "sg:phone":"+31 546 819 344",
    "sg:postcode":"7606 HR",
    "sg:province":"Overijssel",
    "sg:tags":[
        "brood",
        "en",
        "banket"
    ],
    "wof:name":"Braaksma",
    "wof:placetype":"venue"
},
  "geometry": {"coordinates":[6.664543,52.354954],"type":"Point"}
}