{
  "type": "Feature",
  "properties": {
    "addr:full":"Raadhuisplein 9 Berlicum Nb Noord-Brabant 5258 BJ",
    "addr:housenumber":"9",
    "addr:postcode":"5258 bj",
    "addr:street":"Raadhuisplein",
    "iso:country":"NL",
    "sg:address":"Raadhuisplein 9",
    "sg:city":"Berlicum Nb",
    "sg:orig_category":"Advocaten And Juridische Adviseurs",
    "sg:phone":"+31 73 503 4543",
    "sg:postcode":"5258 BJ",
    "sg:province":"Noord-Brabant",
    "wof:name":"Advocatenkantoor Giebels & De Kok",
    "wof:placetype":"venue"
},
  "geometry": {"coordinates":[5.386211,51.684658],"type":"Point"}
}