{
  "type": "Feature",
  "properties": {
    "iso:country":"NL",
    "sg:address":"Leropperweg 2",
    "sg:city":"Roermond",
    "sg:orig_category":"Bloemen And Planten",
    "sg:phone":"+31 475 334 828",
    "sg:postcode":"6041 PB",
    "sg:province":"Limburg",
    "wof:name":"Boomkwekerij En Tuincentrum Roermond Zui",
    "wof:placetype":"venue"
},
  "geometry": {"coordinates":[5.979532,51.175827],"type":"Point"}
}