{
  "type": "Feature",
  "properties": {
    "iso:country":"NL",
    "sg:address":"Beegderweg 8",
    "sg:city":"Horn",
    "sg:orig_category":"Autokeuringen",
    "sg:phone":"+31 475 582 777",
    "sg:postcode":"6085 AN",
    "sg:province":"Limburg",
    "wof:name":"Folimex Trading Bv",
    "wof:placetype":"venue"
},
  "geometry": {"coordinates":[-103.439728,42.765663],"type":"Point"}
}