{
  "type": "Feature",
  "properties": {
    "addr:full":"Weeskinderendk 13 Dordrecht South Holland 3314 CM",
    "addr:housenumber":"13",
    "addr:postcode":"3314 cm",
    "addr:street":"Weeskinderendk",
    "iso:country":"NL",
    "sg:address":"Weeskinderendk 13",
    "sg:city":"Dordrecht",
    "sg:orig_category":"Autowasserettes",
    "sg:phone":"+31 78 648 9700",
    "sg:postcode":"3314 CM",
    "sg:province":"South Holland",
    "wof:name":"Autowas Dordrecht",
    "wof:placetype":"venue"
},
  "geometry": {"coordinates":[4.652523,51.808575],"type":"Point"}
}