{
  "type": "Feature",
  "properties": {
    "addr:full":"Anna Reynvaanstraat 7 Deventer Overijssel 7421 LW",
    "addr:housenumber":"7",
    "addr:postcode":"7421 lw",
    "addr:street":"Anna Reynvaanstraat",
    "iso:country":"NL",
    "sg:address":"Anna Reynvaanstraat 7",
    "sg:city":"Deventer",
    "sg:orig_category":"Makelaars In Onroerend Goed",
    "sg:phone":"+31 570 657 270",
    "sg:postcode":"7421 LW",
    "sg:province":"Overijssel",
    "wof:name":"H.J. Ten Kate",
    "wof:placetype":"venue"
},
  "geometry": {"coordinates":[6.228779,52.241192],"type":"Point"}
}