{
  "type": "Feature",
  "properties": {
    "addr:full":"Goorkesdk 7 Helmond North Brabant 5703 HX",
    "addr:housenumber":"7",
    "addr:postcode":"5703 hx",
    "addr:street":"Goorkesdk",
    "iso:country":"NL",
    "sg:address":"Goorkesdk 7",
    "sg:city":"Helmond",
    "sg:orig_category":"Verenigingen En Stichtingen",
    "sg:phone":"+31 492 537 329",
    "sg:postcode":"5703 HX",
    "sg:province":"North Brabant",
    "wof:name":"Oranje Zwart Helmond",
    "wof:placetype":"venue"
},
  "geometry": {"coordinates":[5.676198,51.484409],"type":"Point"}
}