{
  "type": "Feature",
  "properties": {
    "iso:country":"NL",
    "sg:address":"Lentestr 20",
    "sg:city":"Scherpenisse",
    "sg:orig_category":"Grafmonumenten",
    "sg:phone":"+31 166 662 222",
    "sg:postcode":"4694 CS",
    "sg:province":"Zeeland",
    "wof:name":"Vermeer",
    "wof:placetype":"venue"
},
  "geometry": {"coordinates":[4.103732,51.547039],"type":"Point"}
}