{
  "type": "Feature",
  "properties": {
    "addr:full":"Klompenmakerstraat 17 Velserbroek Noord-Holland 1991 JJ",
    "addr:housenumber":"17",
    "addr:postcode":"1991 jj",
    "addr:street":"Klompenmakerstraat",
    "iso:country":"NL",
    "sg:address":"Klompenmakerstraat 17",
    "sg:city":"Velserbroek",
    "sg:orig_category":"Elektronische Bedrijfsinstallaties",
    "sg:phone":"+31 23 538 5150",
    "sg:postcode":"1991 JJ",
    "sg:province":"Noord-Holland",
    "wof:name":"Vario Lift Bv",
    "wof:placetype":"venue"
},
  "geometry": {"coordinates":[4.650063,52.432728],"type":"Point"}
}