{
  "type": "Feature",
  "properties": {
    "iso:country":"NL",
    "sg:address":"Vd Boschstr 2A",
    "sg:city":"Utrecht",
    "sg:orig_category":"Fotoreportages",
    "sg:phone":"+31 30 296 7386",
    "sg:postcode":"3531 GL",
    "sg:province":"Utrecht",
    "wof:name":"Thiel, M Van",
    "wof:placetype":"venue"
},
  "geometry": {"coordinates":[5.097833,52.089817],"type":"Point"}
}