{
  "type": "Feature",
  "properties": {
    "iso:country":"NL",
    "sg:address":"Oostdijk 4",
    "sg:city":"Noordbeemster",
    "sg:orig_category":"Fruitteelt",
    "sg:phone":"+31 299 403 874",
    "sg:postcode":"1463 PP",
    "sg:province":"Noord-Holland",
    "wof:name":"Firma W. En H. Van Rooijen",
    "wof:placetype":"venue"
},
  "geometry": {"coordinates":[4.991627,52.571186],"type":"Point"}
}