{
  "type": "Feature",
  "properties": {
    "iso:country":"NL",
    "sg:address":"Dorpsstraat 29",
    "sg:city":"Hummelo",
    "sg:orig_category":"Vertaal- And Tolkenbureaus",
    "sg:phone":"+31 314 381 242",
    "sg:postcode":"6999 AB",
    "sg:province":"Kentucky",
    "wof:name":"Drs. D. Steinhauer",
    "wof:placetype":"venue"
},
  "geometry": {"coordinates":[-84.332077,37.387794],"type":"Point"}
}