{
  "type": "Feature",
  "properties": {
    "addr:full":"Dorpswg 123 Schellinkhout Noord-Holland 1697 KH",
    "addr:housenumber":"123",
    "addr:postcode":"1697 kh",
    "addr:street":"Schellinkhout",
    "iso:country":"NL",
    "sg:address":"Dorpswg 123",
    "sg:city":"Schellinkhout",
    "sg:classifiers":[
        {
            "category":"Sports & Exercise",
            "subcategory":"Stables",
            "type":"Entertainment"
        }
    ],
    "sg:phone":"+31 229 501 705",
    "sg:postcode":"1697 KH",
    "sg:province":"Noord-Holland",
    "sg:tags":[
        "maneges"
    ],
    "wof:name":"Vis",
    "wof:placetype":"venue"
},
  "geometry": {"coordinates":[5.124105,52.632534],"type":"Point"}
}