{
  "type": "Feature",
  "properties": {
    "addr:full":"Van Riedevliet 90 Barendrecht Zuid-Holland 2992 TM",
    "addr:housenumber":"90",
    "addr:postcode":"2992 tm",
    "addr:street":"Van Riedevliet",
    "iso:country":"NL",
    "sg:address":"Van Riedevliet 90",
    "sg:city":"Barendrecht",
    "sg:orig_category":"Verzekeringen",
    "sg:phone":"+31 180 613 959",
    "sg:postcode":"2992 TM",
    "sg:province":"Zuid-Holland",
    "wof:name":"Verzekeringskantoor F.M.M. Heruer",
    "wof:placetype":"venue"
},
  "geometry": {"coordinates":[4.534865,51.846844],"type":"Point"}
}