{
  "type": "Feature",
  "properties": {
    "iso:country":"NL",
    "sg:address":"Lindeln 1",
    "sg:city":"Kessel Lb",
    "sg:orig_category":"Verhuur",
    "sg:phone":"+31 77 462 3013",
    "sg:postcode":"5995 NL",
    "sg:province":"Limburg",
    "wof:name":"Jelra",
    "wof:placetype":"venue"
},
  "geometry": {"coordinates":[6.04894,51.291866],"type":"Point"}
}