{
  "type": "Feature",
  "properties": {
    "iso:country":"NL",
    "sg:address":"G Schalckenhage 26",
    "sg:city":"Nieuwegein",
    "sg:orig_category":"Administratie- En Boekhoudkantoren",
    "sg:phone":"+31 30 600 0601",
    "sg:postcode":"3437 NP",
    "sg:province":"Utrecht",
    "sg:website":"http://www.hovko.com",
    "wof:name":"Hovko",
    "wof:placetype":"venue"
},
  "geometry": {"coordinates":[5.070945,52.051521],"type":"Point"}
}