{
  "type": "Feature",
  "properties": {
    "addr:full":"Arnhemseweg 70 Leusden Utrecht 3832 GN",
    "addr:housenumber":"70",
    "addr:postcode":"3832 gn",
    "addr:street":"Arnhemseweg",
    "iso:country":"NL",
    "sg:address":"Arnhemseweg 70",
    "sg:city":"Leusden",
    "sg:orig_category":"Verlichting And Huishoudartikelen",
    "sg:phone":"+31 33 494 0487",
    "sg:postcode":"3832 GN",
    "sg:province":"Utrecht",
    "wof:name":"Majojac",
    "wof:placetype":"venue"
},
  "geometry": {"coordinates":[5.405956,52.112034],"type":"Point"}
}