{
  "type": "Feature",
  "properties": {
    "iso:country":"NL",
    "sg:address":"Camminghalaan 15",
    "sg:city":"Bunnik",
    "sg:orig_category":"Bedrijfs- And Managementsconsultants",
    "sg:phone":"+31 30 656 4483",
    "sg:postcode":"3981 GD",
    "sg:province":"Utrecht",
    "wof:name":"Buro Support Bunnik Bv",
    "wof:placetype":"venue"
},
  "geometry": {"coordinates":[5.196452,52.068531],"type":"Point"}
}