{
  "type": "Feature",
  "properties": {
    "addr:full":"Rietgansstr 9 Putten Gelderland 3882 JD",
    "addr:housenumber":"9",
    "addr:postcode":"3882 jd",
    "addr:street":"Rietgansstr;Gelderland",
    "iso:country":"NL",
    "sg:address":"Rietgansstr 9",
    "sg:city":"Putten",
    "sg:orig_category":"Vetsmelterijen",
    "sg:phone":"+31 341 360 110",
    "sg:postcode":"3882 JD",
    "sg:province":"Gelderland",
    "wof:name":"Eerste Ermelose Vethandel, De",
    "wof:placetype":"venue"
},
  "geometry": {"coordinates":[5.586696,52.259972],"type":"Point"}
}