{
  "type": "Feature",
  "properties": {
    "iso:country":"NL",
    "sg:address":"Ruysdaelkade 97",
    "sg:city":"Amsterdam",
    "sg:orig_category":"Autokeuringen",
    "sg:phone":"+31 20 673 2853",
    "sg:postcode":"1072 AM",
    "sg:province":"North Holland",
    "wof:name":"Merel Mooij Bv",
    "wof:placetype":"venue"
},
  "geometry": {"coordinates":[4.88718,52.355553],"type":"Point"}
}