{
  "type": "Feature",
  "properties": {
    "iso:country":"NL",
    "sg:address":"Hoogewaard 163-165",
    "sg:city":"Koudekerk Ad Ryn",
    "sg:orig_category":"Kampeerauto'S",
    "sg:phone":"+31 71 341 5680",
    "sg:postcode":"2396 AP",
    "sg:province":"Zuid-Holland",
    "wof:name":"Vogelzang, Kampeer Autobedrijf",
    "wof:placetype":"venue"
},
  "geometry": {"coordinates":[4.6125030518,52.1301460266],"type":"Point"}
}