{
  "type": "Feature",
  "properties": {
    "iso:country":"NL",
    "sg:address":"Tramstr 2",
    "sg:city":"S Gravenhage",
    "sg:orig_category":"Opticiens",
    "sg:phone":"+31 70 397 9383",
    "sg:postcode":"2551 TV",
    "sg:province":"Zuid-Holland",
    "wof:name":"Meer, J Van Der",
    "wof:placetype":"venue"
},
  "geometry": {"coordinates":[4.2377500534,52.0586013794],"type":"Point"}
}