{
  "type": "Feature",
  "properties": {
    "addr:full":"Kraanvogellaan 52 'S Hertogenbosch Noord-Brabant 5221 GB",
    "addr:housenumber":"52",
    "addr:postcode":"5221 gb",
    "addr:street":"Kraanvogellaan;' S",
    "iso:country":"NL",
    "sg:address":"Kraanvogellaan 52",
    "sg:city":"'S Hertogenbosch",
    "sg:orig_category":"Werving And Selectie Van Vast Personeel",
    "sg:phone":"+31 73 631 2923",
    "sg:postcode":"5221 GB",
    "sg:province":"Noord-Brabant",
    "wof:name":"Centro",
    "wof:placetype":"venue"
},
  "geometry": {"coordinates":[5.2620210648,51.7204666138],"type":"Point"}
}