{
  "type": "Feature",
  "properties": {
    "iso:country":"NL",
    "sg:address":"Echternachlaan 350",
    "sg:city":"Eindhoven",
    "sg:orig_category":"Musea And Historische Gebouwen",
    "sg:phone":"+31 40 242 8587",
    "sg:postcode":"5625 JG",
    "sg:province":"Noord-Brabant",
    "wof:name":"Gerda Meijer",
    "wof:placetype":"venue"
},
  "geometry": {"coordinates":[5.476517,51.4757],"type":"Point"}
}