{
  "type": "Feature",
  "properties": {
    "addr:full":"Raadhuisstr 31 Moerkapelle Zuid-Holland 2751 AT",
    "addr:housenumber":"31",
    "addr:postcode":"2751",
    "addr:street":"Raadhuisstr",
    "iso:country":"NL",
    "sg:address":"Raadhuisstr 31",
    "sg:city":"Moerkapelle",
    "sg:orig_category":"Keuken- Groot-Installaties",
    "sg:phone":"+31 79 593 6474",
    "sg:postcode":"2751 AT",
    "sg:province":"Zuid-Holland",
    "wof:name":"Wit, Andr\u00fa De",
    "wof:placetype":"venue"
},
  "geometry": {"coordinates":[4.578299,52.045059],"type":"Point"}
}