{
  "type": "Feature",
  "properties": {
    "addr:full":"Wylpstr 2 Stiens Provincie Friesland 9051 AX",
    "addr:housenumber":"2",
    "addr:postcode":"9051 ax",
    "addr:street":"Wylpstr;Provincie Friesland",
    "iso:country":"NL",
    "sg:address":"Wylpstr 2",
    "sg:city":"Stiens",
    "sg:orig_category":"Banken",
    "sg:phone":"+31 58 257 4411",
    "sg:postcode":"9051 AX",
    "sg:province":"Provincie Friesland",
    "wof:name":"Regio Bank",
    "wof:placetype":"venue"
},
  "geometry": {"coordinates":[5.758139,53.260426],"type":"Point"}
}