{
  "type": "Feature",
  "properties": {
    "iso:country":"NL",
    "sg:address":"Voorbancken 17",
    "sg:city":"Vinkeveen",
    "sg:orig_category":"Verlichtingsartikelen - Fabrieken",
    "sg:phone":"+31 297 262 093",
    "sg:postcode":"3645 GV",
    "sg:province":"Utrecht",
    "wof:name":"Toplicht",
    "wof:placetype":"venue"
},
  "geometry": {"coordinates":[4.920375,52.2038],"type":"Point"}
}