{
  "type": "Feature",
  "properties": {
    "addr:full":"Carnissewg 100 Barendrecht South Holland 2993 AE",
    "addr:housenumber":"100",
    "addr:postcode":"2993 ae",
    "iso:country":"NL",
    "sg:address":"Carnissewg 100",
    "sg:city":"Barendrecht",
    "sg:orig_category":"Verenigingen En Stichtingen",
    "sg:phone":"+31 180 613 068",
    "sg:postcode":"2993 AE",
    "sg:province":"South Holland",
    "sg:website":"http://home.planet.nl/~noote027",
    "wof:name":"Carnisselande - Portland",
    "wof:placetype":"venue"
},
  "geometry": {"coordinates":[4.51022,51.85535],"type":"Point"}
}