{
  "type": "Feature",
  "properties": {
    "addr:full":"C Parkerstr 90 Almere Flevoland 1311 PJ",
    "addr:housenumber":"90",
    "addr:postcode":"1311 pj",
    "addr:street":"Flevoland",
    "iso:country":"NL",
    "sg:address":"C Parkerstr 90",
    "sg:city":"Almere",
    "sg:orig_category":"Adviesbureaus Bedrijfsorganisatie",
    "sg:phone":"+31 36 536 4524",
    "sg:postcode":"1311 PJ",
    "sg:province":"Flevoland",
    "wof:name":"Corona",
    "wof:placetype":"venue"
},
  "geometry": {"coordinates":[5.180971,52.366367],"type":"Point"}
}