{
  "type": "Feature",
  "properties": {
    "iso:country":"NL",
    "sg:address":"A J Ernststr 199",
    "sg:city":"Amsterdam",
    "sg:orig_category":"Notarissen En Notariskantoren",
    "sg:phone":"+31 20 540 8000",
    "sg:postcode":"1083 GV",
    "sg:province":"Noord-Holland",
    "wof:name":"Voorneman Geenen",
    "wof:placetype":"venue"
},
  "geometry": {"coordinates":[4.88921,52.33028],"type":"Point"}
}