{
  "type": "Feature",
  "properties": {
    "iso:country":"NL",
    "sg:address":"Hollanderdk 31",
    "sg:city":"Leeuwarden",
    "sg:orig_category":"Verenigingen En Stichtingen",
    "sg:phone":"+31 58 212 0617",
    "sg:postcode":"8932 GK",
    "sg:province":"Provincie Friesland",
    "wof:name":"Vrijwilligerssteunpunt",
    "wof:placetype":"venue"
},
  "geometry": {"coordinates":[5.794545,53.195824],"type":"Point"}
}