{
  "type": "Feature",
  "properties": {
    "addr:full":"Ploegwg 7 S Hertogenbosch Noord-Brabant 5232 BR",
    "addr:housenumber":"7",
    "addr:postcode":"5232 br",
    "addr:street":"Ploegwg",
    "iso:country":"NL",
    "sg:address":"Ploegwg 7",
    "sg:city":"S Hertogenbosch",
    "sg:orig_category":"Lederwaren - Fabrieken En Groothandel",
    "sg:phone":"+31 73 641 4400",
    "sg:postcode":"5232 BR",
    "sg:province":"Noord-Brabant",
    "wof:name":"Doomernik, J",
    "wof:placetype":"venue"
},
  "geometry": {"coordinates":[5.331674,51.709953],"type":"Point"}
}