{
  "type": "Feature",
  "properties": {
    "addr:full":"Hoofdstraat 16 Noordwijk Zh Zuid-Holland 2202 GD",
    "addr:housenumber":"16",
    "addr:postcode":"2202 gd",
    "addr:street":"Hoofdstraat",
    "iso:country":"NL",
    "sg:address":"Hoofdstraat 16",
    "sg:city":"Noordwijk Zh",
    "sg:orig_category":"Herenmodezaken",
    "sg:phone":"+31 71 361 5532",
    "sg:postcode":"2202 GD",
    "sg:province":"Zuid-Holland",
    "wof:name":"Gidion Fashion",
    "wof:placetype":"venue"
},
  "geometry": {"coordinates":[4.434635,52.242973],"type":"Point"}
}