{
  "type": "Feature",
  "properties": {
    "iso:country":"NL",
    "sg:address":"Pasnagelshof 1",
    "sg:city":"Ammerzoden",
    "sg:orig_category":"Verenigingen En Stichtingen",
    "sg:phone":"+31 73 594 9295",
    "sg:postcode":"5324 DG",
    "sg:province":"Gelderland",
    "wof:name":"Sfom",
    "wof:placetype":"venue"
},
  "geometry": {"coordinates":[5.22439,51.747311],"type":"Point"}
}