{
  "type": "Feature",
  "properties": {
    "addr:full":"Zwanebloembocht 105 Velserbroek Noord-Holland 1991 GG",
    "addr:housenumber":"105",
    "addr:postcode":"1991 gg",
    "addr:street":"Zwanebloembocht",
    "iso:country":"NL",
    "sg:address":"Zwanebloembocht 105",
    "sg:city":"Velserbroek",
    "sg:orig_category":"Kappers",
    "sg:phone":"+31 23 538 6833",
    "sg:postcode":"1991 GG",
    "sg:province":"Noord-Holland",
    "wof:name":"Caroll'S Coiffures",
    "wof:placetype":"venue"
},
  "geometry": {"coordinates":[4.6561818123,52.4341163635],"type":"Point"}
}