{
  "type": "Feature",
  "properties": {
    "addr:full":"Gerbera 21 Dirksland Zuid-Holland 3247 DR",
    "addr:housenumber":"21",
    "addr:postcode":"3247 dr",
    "addr:street":"Gerbera",
    "iso:country":"NL",
    "sg:address":"Gerbera 21",
    "sg:city":"Dirksland",
    "sg:orig_category":"Autorijscholen",
    "sg:phone":"+31 187 603 944",
    "sg:postcode":"3247 DR",
    "sg:province":"Zuid-Holland",
    "wof:name":"Bevelander, Ria",
    "wof:placetype":"venue"
},
  "geometry": {"coordinates":[4.106581,51.744774],"type":"Point"}
}