{
  "type": "Feature",
  "properties": {
    "iso:country":"NL",
    "sg:address":"Boschstr 51",
    "sg:city":"Zaltbommel",
    "sg:orig_category":"Adviesbureaus Bedrijfsorganisatie",
    "sg:phone":"+31 418 517 859",
    "sg:postcode":"5301 AB",
    "sg:province":"Gelderland",
    "wof:name":"T\u00eat\u00ea \u00c0 T\u00eat\u00ea, Bureau",
    "wof:placetype":"venue"
},
  "geometry": {"coordinates":[5.249207,51.812431],"type":"Point"}
}