{
  "type": "Feature",
  "properties": {
    "iso:country":"NL",
    "sg:address":"Vriezenveensewg 39",
    "sg:city":"Geesteren Ov",
    "sg:orig_category":"Dierenvoeder - Fabrieken",
    "sg:phone":"+31 546 631 136",
    "sg:postcode":"7678 VA",
    "sg:province":"NL.08",
    "wof:name":"Oude Elberink Bv",
    "wof:placetype":"venue"
},
  "geometry": {"coordinates":[6.72897,52.420609],"type":"Point"}
}