{
  "type": "Feature",
  "properties": {
    "addr:full":"Roggestraat 2 Den Ham Ov Overijssel 7683 AH",
    "addr:housenumber":"2",
    "addr:postcode":"ov;7683 ah",
    "addr:street":"Roggestraat",
    "iso:country":"NL",
    "sg:address":"Roggestraat 2",
    "sg:city":"Den Ham Ov",
    "sg:orig_category":"Kappers",
    "sg:phone":"+31 546 673 111",
    "sg:postcode":"7683 AH",
    "sg:province":"Overijssel",
    "wof:name":"Haarmode Bosscher",
    "wof:placetype":"venue"
},
  "geometry": {"coordinates":[6.496243,52.4649238586],"type":"Point"}
}