{
  "type": "Feature",
  "properties": {
    "addr:full":"Jongbloedlaan 23 Soesterberg Utrecht 3769 BP",
    "addr:housenumber":"23",
    "addr:postcode":"3769 bp",
    "addr:street":"Jongbloedlaan",
    "iso:country":"NL",
    "sg:address":"Jongbloedlaan 23",
    "sg:city":"Soesterberg",
    "sg:orig_category":"Boekhouders",
    "sg:phone":"+31 346 352 419",
    "sg:postcode":"3769 BP",
    "sg:province":"Utrecht",
    "wof:name":"A.W.P. De Groot",
    "wof:placetype":"venue"
},
  "geometry": {"coordinates":[5.278788,52.119911],"type":"Point"}
}