{
  "type": "Feature",
  "properties": {
    "addr:full":"Osebos 1 Gulpen Limburg 6271 PP",
    "addr:housenumber":"1",
    "addr:postcode":"6271 pp",
    "addr:street":"Osebos",
    "iso:country":"NL",
    "sg:address":"Osebos 1",
    "sg:city":"Gulpen",
    "sg:orig_category":"Kampeerterreinen",
    "sg:phone":"+31 43 450 1611",
    "sg:postcode":"6271 PP",
    "sg:province":"Limburg",
    "wof:name":"Camping Osebos",
    "wof:placetype":"venue"
},
  "geometry": {"coordinates":[5.8708109856,50.8073005676],"type":"Point"}
}