{
  "type": "Feature",
  "properties": {
    "addr:full":"Kwakscheweg 3 Oud Beijerland Zuid-Holland 3261 LG",
    "addr:housenumber":"3",
    "addr:postcode":"3261 lg",
    "addr:street":"Kwakscheweg;Oud Beijerland",
    "iso:country":"NL",
    "sg:address":"Kwakscheweg 3",
    "sg:city":"Oud Beijerland",
    "sg:classifiers":[
        {
            "category":"Food & Beverages",
            "subcategory":"Fruits & Vegetables",
            "type":"Retail Goods"
        }
    ],
    "sg:phone":"+31 186 613 390",
    "sg:postcode":"3261 LG",
    "sg:province":"Zuid-Holland",
    "sg:tags":[
        "groenten"
    ],
    "wof:name":"M. Schrijvershof En Zonen",
    "wof:placetype":"venue"
},
  "geometry": {"coordinates":[4.418745,51.811527],"type":"Point"}
}