{
  "type": "Feature",
  "properties": {
    "addr:full":"Nieuwe Markt 9 Raalte NL.08 8102 CG",
    "addr:housenumber":"9;nl.08",
    "addr:postcode":"8102 cg",
    "addr:street":"Nieuwe Markt",
    "iso:country":"NL",
    "sg:address":"Nieuwe Markt 9",
    "sg:city":"Raalte",
    "sg:orig_category":"Feestartikelen",
    "sg:phone":"+31 572 354 345",
    "sg:postcode":"8102 CG",
    "sg:province":"NL.08",
    "wof:name":"Carnaval Albers-Raalte",
    "wof:placetype":"venue"
},
  "geometry": {"coordinates":[6.278286,52.388596],"type":"Point"}
}