{
  "type": "Feature",
  "properties": {
    "iso:country":"NL",
    "sg:address":"Oudebrugsteeg 30",
    "sg:city":"Amsterdam",
    "sg:classifiers":[
        {
            "category":"Fast Food",
            "type":"Food & Drink"
        }
    ],
    "sg:phone":"+31 20 627 0217",
    "sg:postcode":"1012 JP",
    "sg:province":"North Holland",
    "sg:tags":[
        "afhaal",
        "restaurant"
    ],
    "wof:name":"Grillroom Ilanit",
    "wof:placetype":"venue"
},
  "geometry": {"coordinates":[4.895963,52.376087],"type":"Point"}
}