{
  "type": "Feature",
  "properties": {
    "addr:full":"Erasmusln 6 Amstelveen Noord-Holland 1185 BH",
    "addr:housenumber":"6",
    "addr:postcode":"1185 bh",
    "addr:street":"Erasmusln",
    "iso:country":"NL",
    "sg:address":"Erasmusln 6",
    "sg:city":"Amstelveen",
    "sg:orig_category":"Adviesbureaus Bedrijfsorganisatie",
    "sg:phone":"+31 20 681 5991",
    "sg:postcode":"1185 BH",
    "sg:province":"Noord-Holland",
    "wof:name":"Elshout, Van Den",
    "wof:placetype":"venue"
},
  "geometry": {"coordinates":[4.862982,52.296871],"type":"Point"}
}