{
  "type": "Feature",
  "properties": {
    "iso:country":"NL",
    "sg:address":"Bostonwg 11",
    "sg:city":"Almere",
    "sg:orig_category":"Keukens",
    "sg:phone":"+31 36 532 3336",
    "sg:postcode":"1334 KN",
    "sg:province":"NL.",
    "sg:website":"http://www.bruynzeel.nl",
    "wof:name":"Bruynzeel",
    "wof:placetype":"venue"
},
  "geometry": {"coordinates":[5.274673,52.394508],"type":"Point"}
}