{
  "type": "Feature",
  "properties": {
    "addr:full":"Bostonwg 11 Almere NL. 1334 KN",
    "addr:housenumber":"11",
    "addr:postcode":"1334 kn",
    "addr:street":"Bostonwg;Nl.",
    "iso:country":"NL",
    "sg:address":"Bostonwg 11",
    "sg:city":"Almere",
    "sg:orig_category":"Keukens",
    "sg:phone":"+31 36 532 3336",
    "sg:postcode":"1334 KN",
    "sg:province":"NL.",
    "sg:website":"http://www.bruynzeel.nl",
    "wof:name":"Bruynzeel",
    "wof:placetype":"venue"
},
  "geometry": {"coordinates":[5.274673,52.394508],"type":"Point"}
}