{
  "type": "Feature",
  "properties": {
    "addr:full":"Patrimoniumstraat 7 Aalten Gelderland 7121 CG",
    "addr:housenumber":"7",
    "addr:postcode":"7121 cg",
    "addr:street":"Patrimoniumstraat;Gelderland",
    "iso:country":"NL",
    "sg:address":"Patrimoniumstraat 7",
    "sg:city":"Aalten",
    "sg:orig_category":"Partycatering And -Organisatie",
    "sg:phone":"+31 543 476 112",
    "sg:postcode":"7121 CG",
    "sg:province":"Gelderland",
    "wof:name":"Rusink Catering",
    "wof:placetype":"venue"
},
  "geometry": {"coordinates":[6.587018,51.928432],"type":"Point"}
}