{
  "type": "Feature",
  "properties": {
    "addr:full":"Nieuwstr 143 Spykenisse Zuid-Holland 3201 EE",
    "addr:housenumber":"143",
    "addr:postcode":"3201 ee",
    "addr:street":"Spykenisse",
    "iso:country":"NL",
    "sg:address":"Nieuwstr 143",
    "sg:city":"Spykenisse",
    "sg:orig_category":"Schoenen",
    "sg:phone":"+31 181 627 577",
    "sg:postcode":"3201 EE",
    "sg:province":"Zuid-Holland",
    "sg:website":"http://www.massa-schoen-mode.nl",
    "wof:name":"Massa",
    "wof:placetype":"venue"
},
  "geometry": {"coordinates":[4.325045,51.849525],"type":"Point"}
}