{
  "type": "Feature",
  "properties": {
    "addr:full":"Kr Steenwg 4 Helmond Noord-Brabant 5707 CC",
    "addr:housenumber":"4",
    "addr:postcode":"5707 cc",
    "addr:street":"Steenwg",
    "iso:country":"NL",
    "sg:address":"Kr Steenwg 4",
    "sg:city":"Helmond",
    "sg:orig_category":"Makelaars En Adviseurs Onroerende Goederen",
    "sg:phone":"+31 492 525 552",
    "sg:postcode":"5707 CC",
    "sg:province":"Noord-Brabant",
    "wof:name":"Santvoort & Van Santvoort Bv, Van",
    "wof:placetype":"venue"
},
  "geometry": {"coordinates":[5.651139,51.479134],"type":"Point"}
}