{
  "type": "Feature",
  "properties": {
    "addr:full":"Taag 77 S Gravenhage South Holland 2491 CS",
    "addr:housenumber":"77",
    "addr:postcode":"2491 cs",
    "addr:street":"Taag;S Gravenhage",
    "iso:country":"NL",
    "sg:address":"Taag 77",
    "sg:city":"S Gravenhage",
    "sg:orig_category":"Wegenbouw",
    "sg:phone":"+31 70 317 7977",
    "sg:postcode":"2491 CS",
    "sg:province":"South Holland",
    "wof:name":"Gleijm Bv, W",
    "wof:placetype":"venue"
},
  "geometry": {"coordinates":[4.3838200569,52.0652885437],"type":"Point"}
}