{
  "type": "Feature",
  "properties": {
    "addr:full":"Vriezenveensewg 1 Almelo Overijssel 7602 AA",
    "addr:housenumber":"1",
    "addr:postcode":"7602 aa",
    "addr:street":"Vriezenveensewg",
    "iso:country":"NL",
    "sg:address":"Vriezenveensewg 1",
    "sg:city":"Almelo",
    "sg:orig_category":"Ziekenhuizen, Sanatoria, Verpleeghuizen",
    "sg:phone":"+31 546 486 666",
    "sg:postcode":"7602 AA",
    "sg:province":"Overijssel",
    "wof:name":"Eugeria",
    "wof:placetype":"venue"
},
  "geometry": {"coordinates":[6.668735,52.365002],"type":"Point"}
}