{
  "type": "Feature",
  "properties": {
    "addr:full":"Wilhelminastraat 65 Lekkerkerk Zuid-Holland 2941 CA",
    "addr:housenumber":"65",
    "addr:postcode":"2941 ca",
    "addr:street":"Wilhelminastraat",
    "iso:country":"NL",
    "sg:address":"Wilhelminastraat 65",
    "sg:city":"Lekkerkerk",
    "sg:orig_category":"Voeding, Dranken And Tabak Gh",
    "sg:phone":"+31 180 663 788",
    "sg:postcode":"2941 CA",
    "sg:province":"Zuid-Holland",
    "wof:name":"M&M Action Sports",
    "wof:placetype":"venue"
},
  "geometry": {"coordinates":[4.688533,51.899616],"type":"Point"}
}