{
  "type": "Feature",
  "properties": {
    "addr:full":"Wanroyseweg 15 Mill Noord-Brabant 5451 GX",
    "addr:housenumber":"15",
    "addr:postcode":"5451 gx",
    "addr:street":"Wanroyseweg",
    "iso:country":"NL",
    "sg:address":"Wanroyseweg 15",
    "sg:city":"Mill",
    "sg:orig_category":"Verzekeringen",
    "sg:phone":"+31 485 451 877",
    "sg:postcode":"5451 GX",
    "sg:province":"Noord-Brabant",
    "wof:name":"Ass Ktr H Hermanussen",
    "wof:placetype":"venue"
},
  "geometry": {"coordinates":[-77.762939,41.90403],"type":"Point"}
}