{
  "type": "Feature",
  "properties": {
    "iso:country":"NL",
    "sg:address":"Geelgietersdreef 24",
    "sg:city":"Maastricht",
    "sg:orig_category":"Bloemen And Planten",
    "sg:phone":"+31 43 343 5309",
    "sg:postcode":"6216 RE",
    "sg:province":"Limburg",
    "wof:name":"Bloemen- En Plantenhandel 'T Pleintje",
    "wof:placetype":"venue"
},
  "geometry": {"coordinates":[5.66246,50.845654],"type":"Point"}
}