{
  "type": "Feature",
  "properties": {
    "addr:full":"Veerwg 10 Blitterswyck Limburg 5863 AR",
    "addr:housenumber":"10",
    "addr:postcode":"5863",
    "addr:street":"Veerwg;Limburg",
    "iso:country":"NL",
    "sg:address":"Veerwg 10",
    "sg:city":"Blitterswyck",
    "sg:orig_category":"Voetbalverenigingen",
    "sg:phone":"+31 478 532 077",
    "sg:postcode":"5863 AR",
    "sg:province":"Limburg",
    "wof:name":"Bvv 27",
    "wof:placetype":"venue"
},
  "geometry": {"coordinates":[6.124655,51.525127],"type":"Point"}
}