{
  "type": "Feature",
  "properties": {
    "addr:full":"Meeuwenstr 16 Ospel Limburg 6035 GA",
    "addr:housenumber":"16",
    "addr:postcode":"6035 ga",
    "addr:street":"Meeuwenstr",
    "iso:country":"NL",
    "sg:address":"Meeuwenstr 16",
    "sg:city":"Ospel",
    "sg:orig_category":"Voetbalverenigingen",
    "sg:phone":"+31 495 625 911",
    "sg:postcode":"6035 GA",
    "sg:province":"Limburg",
    "wof:name":"Br\u00f6kske, 'T",
    "wof:placetype":"venue"
},
  "geometry": {"coordinates":[-86.165451,34.620892],"type":"Point"}
}