{
  "type": "Feature",
  "properties": {
    "iso:country":"NL",
    "sg:address":"Kuilkant 141",
    "sg:city":"Barendrecht",
    "sg:orig_category":"Webdesign Bureaus",
    "sg:phone":"+31 180 699 378",
    "sg:postcode":"2993 DV",
    "sg:province":"Zuid-Holland",
    "sg:website":"http://www.favro.nl",
    "wof:name":"Favro Services",
    "wof:placetype":"venue"
},
  "geometry": {"coordinates":[4.50710392,51.8456878662],"type":"Point"}
}