{
  "type": "Feature",
  "properties": {
    "addr:full":"Tractiewg 32 Utrecht Utrecht 3534 AP",
    "addr:housenumber":"32",
    "addr:postcode":"3534 ap",
    "addr:street":"Tractiewg",
    "iso:country":"NL",
    "sg:address":"Tractiewg 32",
    "sg:city":"Utrecht",
    "sg:orig_category":"Oud Metaal",
    "sg:phone":"+31 30 243 0845",
    "sg:postcode":"3534 AP",
    "sg:province":"Utrecht",
    "wof:name":"Gerritsen Van Der Hoop, F A P",
    "wof:placetype":"venue"
},
  "geometry": {"coordinates":[5.0797457695,52.1060943604],"type":"Point"}
}