{
  "type": "Feature",
  "properties": {
    "addr:full":"Vierde Broekdijk 43 Aalten Gelderland 7122 JD",
    "addr:housenumber":"43",
    "addr:postcode":"7122 jd",
    "addr:street":"Vierde Broekdijk;Gelderland",
    "iso:country":"NL",
    "sg:address":"Vierde Broekdijk 43",
    "sg:city":"Aalten",
    "sg:orig_category":"Fotostudio'S And Fotografen",
    "sg:phone":"+31 543 479 082",
    "sg:postcode":"7122 JD",
    "sg:province":"Gelderland",
    "wof:name":"Alex Vreeman Fotograaf",
    "wof:placetype":"venue"
},
  "geometry": {"coordinates":[6.567833,51.909023],"type":"Point"}
}