{
  "type": "Feature",
  "properties": {
    "addr:full":"Loobeekwg 6 Holthees North Brabant 5824 AE",
    "addr:housenumber":"6",
    "addr:postcode":"5824 ae",
    "addr:street":"Loobeekwg",
    "iso:country":"NL",
    "sg:address":"Loobeekwg 6",
    "sg:city":"Holthees",
    "sg:orig_category":"Kunststoffen- Verwerkende Industrie",
    "sg:phone":"+31 478 636 719",
    "sg:postcode":"5824 AE",
    "sg:province":"North Brabant",
    "wof:name":"Lobo Bv",
    "wof:placetype":"venue"
},
  "geometry": {"coordinates":[6.002535,51.570065],"type":"Point"}
}