{
  "type": "Feature",
  "properties": {
    "iso:country":"NL",
    "sg:address":"Koningswg 2",
    "sg:city":"Soest",
    "sg:orig_category":"Verzekeringen - Verzekeringskantoren",
    "sg:phone":"+31 35 601 2821",
    "sg:postcode":"3762 EC",
    "sg:province":"Utrecht",
    "wof:name":"Bottelberghs",
    "wof:placetype":"venue"
},
  "geometry": {"coordinates":[5.278011,52.174187],"type":"Point"}
}