{
  "type": "Feature",
  "properties": {
    "addr:full":"De Huufkes 112 Nuenen Noord-Brabant 5674 TM",
    "addr:housenumber":"112",
    "addr:postcode":"5674 tm",
    "addr:street":"De Huufkes",
    "iso:country":"NL",
    "sg:address":"De Huufkes 112",
    "sg:city":"Nuenen",
    "sg:orig_category":"Plafonds",
    "sg:phone":"+31 40 283 1905",
    "sg:postcode":"5674 TM",
    "sg:province":"Noord-Brabant",
    "wof:name":"Asn Bv",
    "wof:placetype":"venue"
},
  "geometry": {"coordinates":[5.558539,51.447285],"type":"Point"}
}