{
  "type": "Feature",
  "properties": {
    "iso:country":"NL",
    "sg:address":"Beekstraat 5",
    "sg:city":"Haelen",
    "sg:orig_category":"Kappers",
    "sg:phone":"+31 475 591 585",
    "sg:postcode":"6081 AT",
    "sg:province":"Limburg",
    "wof:name":"Herenkapsalon Van Hinsberg",
    "wof:placetype":"venue"
},
  "geometry": {"coordinates":[5.9567909241,51.2342224121],"type":"Point"}
}