{
  "type": "Feature",
  "properties": {
    "iso:country":"NL",
    "sg:address":"Hoevenbocht 14",
    "sg:city":"Reusel",
    "sg:orig_category":"Montagebedrijven",
    "sg:phone":"+31 497 644 086",
    "sg:postcode":"5541 RX",
    "sg:province":"Noord-Brabant",
    "wof:name":"Hoevenbocht Vof",
    "wof:placetype":"venue"
},
  "geometry": {"coordinates":[5.175968,51.363621],"type":"Point"}
}