{
  "type": "Feature",
  "properties": {
    "addr:full":"Bergweg 22 Ommen Overijssel 7731 AD",
    "addr:housenumber":"22",
    "addr:postcode":"7731 ad",
    "addr:street":"Bergweg",
    "iso:country":"NL",
    "sg:address":"Bergweg 22",
    "sg:city":"Ommen",
    "sg:orig_category":"Pluimveehouderijen",
    "sg:phone":"+31 529 451 995",
    "sg:postcode":"7731 AD",
    "sg:province":"Overijssel",
    "wof:name":"H. Stokvisch",
    "wof:placetype":"venue"
},
  "geometry": {"coordinates":[6.425784,52.500256],"type":"Point"}
}