{
  "type": "Feature",
  "properties": {
    "iso:country":"NL",
    "sg:address":"Dinteldal 6",
    "sg:city":"Capelle Ad Yssel",
    "sg:orig_category":"Scheepvaartinspectie",
    "sg:phone":"+31 10 450 6557",
    "sg:postcode":"2904 CC",
    "sg:province":"Zuid-Holland",
    "wof:name":"Msi",
    "wof:placetype":"venue"
},
  "geometry": {"coordinates":[4.607312,51.936558],"type":"Point"}
}