{
  "type": "Feature",
  "properties": {
    "addr:full":"Nieuwe Langendijk 4A Delft South Holland 2611 VK",
    "addr:housenumber":"4a",
    "addr:postcode":"2611 vk",
    "addr:street":"Nieuwe Langendijk",
    "iso:country":"NL",
    "sg:address":"Nieuwe Langendijk 4A",
    "sg:city":"Delft",
    "sg:orig_category":"Wasserettes And Stomerijen",
    "sg:phone":"+31 15 214 5439",
    "sg:postcode":"2611 VK",
    "sg:province":"South Holland",
    "wof:name":"Wasserette Stomerij Rein-Tex",
    "wof:placetype":"venue"
},
  "geometry": {"coordinates":[4.3623080254,52.0126914978],"type":"Point"}
}