{
  "type": "Feature",
  "properties": {
    "addr:full":"Wethouder Gerbertstraat 55 Enschede NL.08 7543 AV",
    "addr:housenumber":"55;7543",
    "addr:street":"Wethouder Gerbertstraat;Av",
    "iso:country":"NL",
    "sg:address":"Wethouder Gerbertstraat 55",
    "sg:city":"Enschede",
    "sg:classifiers":[
        {
            "category":"Fast Food",
            "type":"Food & Drink"
        }
    ],
    "sg:phone":"+31 53 477 1836",
    "sg:postcode":"7543 AV",
    "sg:province":"NL.08",
    "sg:tags":[
        "afhaal",
        "restaurant"
    ],
    "wof:name":"Cafetaria De Lanteern",
    "wof:placetype":"venue"
},
  "geometry": {"coordinates":[6.879082,52.205395],"type":"Point"}
}