{
  "type": "Feature",
  "properties": {
    "addr:full":"Christinastraat 41 Oosterbeek Gelderland 6862 GK",
    "addr:housenumber":"41",
    "addr:postcode":"6862 gk",
    "addr:street":"Christinastraat;Gelderland",
    "iso:country":"NL",
    "sg:address":"Christinastraat 41",
    "sg:city":"Oosterbeek",
    "sg:orig_category":"Boekhouders",
    "sg:phone":"+31 26 333 5721",
    "sg:postcode":"6862 GK",
    "sg:province":"Gelderland",
    "wof:name":"Administratiekantoor Gijsbers Van Wijk",
    "wof:placetype":"venue"
},
  "geometry": {"coordinates":[5.847324,51.982571],"type":"Point"}
}