{
  "type": "Feature",
  "properties": {
    "iso:country":"NL",
    "sg:address":"Overtoom 316",
    "sg:city":"Amsterdam",
    "sg:orig_category":"Webdesign Bureaus",
    "sg:phone":"+31 20 776 3210",
    "sg:postcode":"1054 JD",
    "sg:province":"Noord-Holland",
    "wof:name":"Wicket",
    "wof:placetype":"venue"
},
  "geometry": {"coordinates":[4.8683981895,52.3611793518],"type":"Point"}
}