{
  "type": "Feature",
  "properties": {
    "iso:country":"NL",
    "sg:address":"Helftheuvelpassage 354",
    "sg:city":"'S Hertogenbosch",
    "sg:orig_category":"Verlichting And Huishoudartikelen",
    "sg:phone":"+31 73 621 0022",
    "sg:postcode":"5224 AR",
    "sg:province":"North Brabant",
    "wof:name":"Kadoshop Galanterie Nancy",
    "wof:placetype":"venue"
},
  "geometry": {"coordinates":[5.266699,51.694824],"type":"Point"}
}