{
  "type": "Feature",
  "properties": {
    "iso:country":"NL",
    "sg:address":"Langestraat 107",
    "sg:city":"Genemuiden",
    "sg:orig_category":"Visspeciaalzaken",
    "sg:phone":"+31 38 385 4104",
    "sg:postcode":"8281 AH",
    "sg:province":"Overijssel",
    "wof:name":"Vishandel G. Post En Zoon",
    "wof:placetype":"venue"
},
  "geometry": {"coordinates":[6.040939,52.621365],"type":"Point"}
}