{
  "type": "Feature",
  "properties": {
    "addr:full":"Maastrichterln 10 Vaals Limburg 6291 ES",
    "addr:housenumber":"10",
    "addr:postcode":"6291 es",
    "addr:street":"Maastrichterln",
    "iso:country":"NL",
    "sg:address":"Maastrichterln 10",
    "sg:city":"Vaals",
    "sg:classifiers":[
        {
            "category":"Food & Beverages",
            "subcategory":"Bakery",
            "type":"Retail Goods"
        }
    ],
    "sg:phone":"+31 43 306 2075",
    "sg:postcode":"6291 ES",
    "sg:province":"Limburg",
    "sg:tags":[
        "brood",
        "en",
        "banket"
    ],
    "wof:name":"Kickartz",
    "wof:placetype":"venue"
},
  "geometry": {"coordinates":[6.02236,50.771633],"type":"Point"}
}