{
  "type": "Feature",
  "properties": {
    "addr:full":"Beumeesweg 162 Alteveer Gn Groningen 9661 AM",
    "addr:housenumber":"162",
    "addr:postcode":"gn;9661",
    "addr:street":"Beumeesweg",
    "iso:country":"NL",
    "sg:address":"Beumeesweg 162",
    "sg:city":"Alteveer Gn",
    "sg:orig_category":"Autokeuringen",
    "sg:phone":"+31 599 331 642",
    "sg:postcode":"9661 AM",
    "sg:province":"Groningen",
    "wof:name":"Garage Wijnholds",
    "wof:placetype":"venue"
},
  "geometry": {"coordinates":[6.998453,53.052254],"type":"Point"}
}