{
  "type": "Feature",
  "properties": {
    "addr:full":"Jachtln 41 Silvolde Gelderland 7064 EJ",
    "addr:housenumber":"41",
    "addr:postcode":"7064 ej",
    "addr:street":"Jachtln;Gelderland",
    "iso:country":"NL",
    "sg:address":"Jachtln 41",
    "sg:city":"Silvolde",
    "sg:orig_category":"Videoreportages",
    "sg:phone":"+31 315 340 040",
    "sg:postcode":"7064 EJ",
    "sg:province":"Gelderland",
    "sg:website":"http://www.bmrmedia.nl",
    "wof:name":"Bmr",
    "wof:placetype":"venue"
},
  "geometry": {"coordinates":[6.394963,51.893879],"type":"Point"}
}