{
  "type": "Feature",
  "properties": {
    "addr:full":"William Boothlaan 19 Rotterdam South Holland 3012 VH",
    "addr:housenumber":"19",
    "addr:postcode":"3012 vh",
    "addr:street":"William Boothlaan",
    "iso:country":"NL",
    "sg:address":"William Boothlaan 19",
    "sg:city":"Rotterdam",
    "sg:orig_category":"Verzekeringen",
    "sg:phone":"+31 10 412 7589",
    "sg:postcode":"3012 VH",
    "sg:province":"South Holland",
    "wof:name":"J. Chantrel",
    "wof:placetype":"venue"
},
  "geometry": {"coordinates":[4.478896,51.9151],"type":"Point"}
}