{
  "type": "Feature",
  "properties": {
    "addr:full":"Breedweer 16-18 Koog Aan De Zaan Noord-Holland 1541 AC",
    "addr:housenumber":"16-18",
    "addr:postcode":"aan;zaan;1541 ac",
    "addr:street":"Breedweer",
    "iso:country":"NL",
    "sg:address":"Breedweer 16-18",
    "sg:city":"Koog Aan De Zaan",
    "sg:orig_category":"Leesportefeuilles",
    "sg:phone":"+31 75 635 0111",
    "sg:postcode":"1541 AC",
    "sg:province":"Noord-Holland",
    "wof:name":"Leesland Zaanlandia",
    "wof:placetype":"venue"
},
  "geometry": {"coordinates":[4.809529,52.456066],"type":"Point"}
}