{
  "type": "Feature",
  "properties": {
    "addr:full":"Nieuwstad 57 Vorden Gelderland 7251 AG",
    "addr:housenumber":"57",
    "addr:postcode":"7251",
    "addr:street":"Nieuwstad;Gelderland",
    "iso:country":"NL",
    "sg:address":"Nieuwstad 57",
    "sg:city":"Vorden",
    "sg:orig_category":"Meubelmakerijen",
    "sg:phone":"+31 575 553 956",
    "sg:postcode":"7251 AG",
    "sg:province":"Gelderland",
    "wof:name":"Zweverink, J",
    "wof:placetype":"venue"
},
  "geometry": {"coordinates":[6.310474,52.097767],"type":"Point"}
}