{
  "type": "Feature",
  "properties": {
    "iso:country":"NL",
    "sg:address":"Nieuwstad 57",
    "sg:city":"Vorden",
    "sg:orig_category":"Meubelmakerijen",
    "sg:phone":"+31 575 553 956",
    "sg:postcode":"7251 AG",
    "sg:province":"Gelderland",
    "wof:name":"Zweverink, J",
    "wof:placetype":"venue"
},
  "geometry": {"coordinates":[6.310474,52.097767],"type":"Point"}
}