{
  "type": "Feature",
  "properties": {
    "addr:full":"Postbus 8 Egmond Binnen Noord-Holland 1935 ZG",
    "addr:housenumber":"8",
    "addr:postcode":"1935 zg",
    "addr:street":"Postbus;Egmond",
    "iso:country":"NL",
    "sg:address":"Postbus 8",
    "sg:city":"Egmond Binnen",
    "sg:orig_category":"Exploitatie- Maatschappijen",
    "sg:phone":"+31 72 506 5367",
    "sg:postcode":"1935 ZG",
    "sg:province":"Noord-Holland",
    "wof:name":"Schoehuijs Bv",
    "wof:placetype":"venue"
},
  "geometry": {"coordinates":[4.655705,52.596455],"type":"Point"}
}