{
  "type": "Feature",
  "properties": {
    "addr:full":"Benschopperstraat 40 Ijsselstein Ut Utrecht 3401 DH",
    "addr:housenumber":"40",
    "addr:postcode":"3401 dh",
    "addr:street":"Benschopperstraat",
    "iso:country":"NL",
    "sg:address":"Benschopperstraat 40",
    "sg:city":"Ijsselstein Ut",
    "sg:orig_category":"Meubelzaken, Woning- And Keukeninrichting",
    "sg:phone":"+31 30 688 9295",
    "sg:postcode":"3401 DH",
    "sg:province":"Utrecht",
    "wof:name":"Scorpio",
    "wof:placetype":"venue"
},
  "geometry": {"coordinates":[5.043081,52.019157],"type":"Point"}
}