{
  "type": "Feature",
  "properties": {
    "iso:country":"NL",
    "sg:address":"Grt Plaat 43",
    "sg:city":"Zeewolde",
    "sg:orig_category":"Schoonheidsinstituten",
    "sg:phone":"+31 36 522 9070",
    "sg:postcode":"3891 ZA",
    "sg:province":"NL.",
    "wof:name":"Riekje",
    "wof:placetype":"venue"
},
  "geometry": {"coordinates":[5.537072,52.334206],"type":"Point"}
}