{
  "type": "Feature",
  "properties": {
    "addr:full":"Zuidplnts 2 Delft Zuid-Holland 2628 BZ",
    "addr:housenumber":"2",
    "addr:postcode":"2628 bz",
    "addr:street":"Zuidplnts",
    "iso:country":"NL",
    "sg:address":"Zuidplnts 2",
    "sg:city":"Delft",
    "sg:orig_category":"Verhuur",
    "sg:phone":"+31 15 278 5082",
    "sg:postcode":"2628 BZ",
    "sg:province":"Zuid-Holland",
    "wof:name":"Multi Media Services",
    "wof:placetype":"venue"
},
  "geometry": {"coordinates":[4.37537,52.001652],"type":"Point"}
}