{
  "type": "Feature",
  "properties": {
    "addr:full":"Ring 20 Zuidland Zuid-Holland 3214 AT",
    "addr:housenumber":"20",
    "addr:postcode":"3214",
    "addr:street":"Ring",
    "iso:country":"NL",
    "sg:address":"Ring 20",
    "sg:city":"Zuidland",
    "sg:orig_category":"Fietsen En Bromfietsen",
    "sg:phone":"+31 181 451 334",
    "sg:postcode":"3214 AT",
    "sg:province":"Zuid-Holland",
    "wof:name":"Stoof, I",
    "wof:placetype":"venue"
},
  "geometry": {"coordinates":[4.261256,51.822781],"type":"Point"}
}