{
  "type": "Feature",
  "properties": {
    "addr:full":"Rijksstraatweg 7 Sleeuwijk Noord-Brabant 4254 XA",
    "addr:housenumber":"7",
    "addr:postcode":"4254 xa",
    "addr:street":"Rijksstraatweg",
    "iso:country":"NL",
    "sg:address":"Rijksstraatweg 7",
    "sg:city":"Sleeuwijk",
    "sg:orig_category":"Wegen And Sportterreinen",
    "sg:phone":"+31 183 301 905",
    "sg:postcode":"4254 XA",
    "sg:province":"Noord-Brabant",
    "wof:name":"Aannemersbedrijf C.L.P. Van Andel",
    "wof:placetype":"venue"
},
  "geometry": {"coordinates":[4.9599380493,51.8142852783],"type":"Point"}
}