{
  "type": "Feature",
  "properties": {
    "addr:full":"Schutsboom 68 Hilvarenbeek Noord-Brabant 5081 PB",
    "addr:housenumber":"68",
    "addr:postcode":"5081 pb",
    "addr:street":"Schutsboom",
    "iso:country":"NL",
    "sg:address":"Schutsboom 68",
    "sg:city":"Hilvarenbeek",
    "sg:orig_category":"Goederenvervoer Over De Weg",
    "sg:phone":"+31 13 505 3172",
    "sg:postcode":"5081 PB",
    "sg:province":"Noord-Brabant",
    "wof:name":"Jan Vugt Int",
    "wof:placetype":"venue"
},
  "geometry": {"coordinates":[5.138458,51.487076],"type":"Point"}
}