{
  "type": "Feature",
  "properties": {
    "iso:country":"NL",
    "sg:address":"Pater Van Den Elsenlaan 1",
    "sg:city":"Veghel",
    "sg:orig_category":"Glaszetten",
    "sg:phone":"+31 413 367 362",
    "sg:postcode":"5462 GG",
    "sg:province":"North Brabant",
    "wof:name":"Glas In Loodbedrijf Jan Evers",
    "wof:placetype":"venue"
},
  "geometry": {"coordinates":[5.528919,51.617062],"type":"Point"}
}