{
  "type": "Feature",
  "properties": {
    "addr:full":"Vorsselweg 7 Heesch Noord-Brabant 5384 RW",
    "addr:housenumber":"7",
    "addr:postcode":"5384 rw",
    "addr:street":"Vorsselweg",
    "iso:country":"NL",
    "sg:address":"Vorsselweg 7",
    "sg:city":"Heesch",
    "sg:orig_category":"Discountwinkels",
    "sg:phone":"+31 412 451 327",
    "sg:postcode":"5384 RW",
    "sg:province":"Noord-Brabant",
    "wof:name":"A.A.A.M. Neelen- Van Dinther",
    "wof:placetype":"venue"
},
  "geometry": {"coordinates":[5.559617,51.730751],"type":"Point"}
}