{
  "type": "Feature",
  "properties": {
    "iso:country":"NL",
    "sg:address":"Busschopswg 9",
    "sg:city":"Heythuysen",
    "sg:orig_category":"Zalenverhuur",
    "sg:phone":"+31 475 491 139",
    "sg:postcode":"6093 AA",
    "sg:province":"Limburg",
    "wof:name":"Busjop, De",
    "wof:placetype":"venue"
},
  "geometry": {"coordinates":[5.909772,51.244976],"type":"Point"}
}