{
  "type": "Feature",
  "properties": {
    "addr:full":"Deventerstraat 4 Raalte Overijssel 8102 GC",
    "addr:housenumber":"4",
    "addr:postcode":"8102 gc",
    "addr:street":"Deventerstraat",
    "iso:country":"NL",
    "sg:address":"Deventerstraat 4",
    "sg:city":"Raalte",
    "sg:orig_category":"Kappers",
    "sg:phone":"+31 572 358 263",
    "sg:postcode":"8102 GC",
    "sg:province":"Overijssel",
    "wof:name":"Kapsalon Pauline",
    "wof:placetype":"venue"
},
  "geometry": {"coordinates":[6.274887085,52.3837814331],"type":"Point"}
}