{
  "type": "Feature",
  "properties": {
    "iso:country":"NL",
    "sg:address":"Spinozawg 229",
    "sg:city":"Rotterdam",
    "sg:orig_category":"Verenigingen En Stichtingen",
    "sg:phone":"+31 10 419 8711",
    "sg:postcode":"3076 EM",
    "sg:province":"South Holland",
    "wof:name":"Beukhoeve Volkstuinver, De",
    "wof:placetype":"venue"
},
  "geometry": {"coordinates":[4.519592,51.877235],"type":"Point"}
}