{
  "type": "Feature",
  "properties": {
    "iso:country":"NL",
    "sg:address":"Cornelis Tromplaan 21",
    "sg:city":"'S Graveland",
    "sg:orig_category":"Autokeuringen",
    "sg:phone":"+31 35 656 1932",
    "sg:postcode":"1243 LA",
    "sg:province":"Noord-Holland",
    "wof:name":"M.C. V.D. Laan-De Vries",
    "wof:placetype":"venue"
},
  "geometry": {"coordinates":[5.124689,52.225697],"type":"Point"}
}