{
  "type": "Feature",
  "properties": {
    "addr:full":"D Leestr 61 Stampersgat Noord-Brabant 4754 BB",
    "addr:housenumber":"61",
    "addr:postcode":"4754 bb",
    "iso:country":"NL",
    "sg:address":"D Leestr 61",
    "sg:city":"Stampersgat",
    "sg:orig_category":"Bloemen En Planten",
    "sg:phone":"+31 165 512 191",
    "sg:postcode":"4754 BB",
    "sg:province":"Noord-Brabant",
    "wof:name":"Ranonkeltje, 'T",
    "wof:placetype":"venue"
},
  "geometry": {"coordinates":[4.448448,51.61311],"type":"Point"}
}