{
  "type": "Feature",
  "properties": {
    "addr:full":"Bavelselaan 131 Breda North Brabant 4834 TA",
    "addr:housenumber":"131",
    "addr:postcode":"4834 ta",
    "addr:street":"Bavelselaan",
    "iso:country":"NL",
    "sg:address":"Bavelselaan 131",
    "sg:city":"Breda",
    "sg:orig_category":"Aannemers Woningbouw",
    "sg:phone":"+31 76 560 1012",
    "sg:postcode":"4834 TA",
    "sg:province":"North Brabant",
    "wof:name":"Aannemersbedrijf Segeren Bv",
    "wof:placetype":"venue"
},
  "geometry": {"coordinates":[4.795758,51.565121],"type":"Point"}
}