{
  "type": "Feature",
  "properties": {
    "iso:country":"NL",
    "sg:address":"Zilverschoon 28",
    "sg:city":"Duiven",
    "sg:classifiers":[
        {
            "category":"Professional",
            "subcategory":"Accounting & Tax Preparation",
            "type":"Services"
        }
    ],
    "sg:phone":"+31 316 280 855",
    "sg:postcode":"6922 GV",
    "sg:province":"Gelderland",
    "sg:tags":[
        "accountant"
    ],
    "wof:name":"Nass Accountants",
    "wof:placetype":"venue"
},
  "geometry": {"coordinates":[6.015382,51.942314],"type":"Point"}
}