{
  "type": "Feature",
  "properties": {
    "addr:full":"Loosduinsekade 418 Den Haag Zuid-Holland 2571  C",
    "addr:housenumber":"418;2571 c",
    "addr:street":"Loosduinsekade",
    "iso:country":"NL",
    "sg:address":"Loosduinsekade 418",
    "sg:city":"Den Haag",
    "sg:orig_category":"Verhuisdiensten",
    "sg:phone":"+31 70 123 4567",
    "sg:postcode":"2571  C",
    "sg:province":"Zuid-Holland",
    "wof:name":"Visser Vrachttaxi",
    "wof:placetype":"venue"
},
  "geometry": {"coordinates":[4.273408,52.067429],"type":"Point"}
}