{
  "type": "Feature",
  "properties": {
    "iso:country":"NL",
    "sg:address":"Duijvekotstraat 6",
    "sg:city":"Moergestel",
    "sg:orig_category":"Vaste And Vloeibare Brandstoffen",
    "sg:phone":"+31 13 513 4141",
    "sg:postcode":"5066 BP",
    "sg:province":"North Brabant",
    "wof:name":"A.W.M. Westgeest Benzine Oisterwijk Bv",
    "wof:placetype":"venue"
},
  "geometry": {"coordinates":[5.175233,51.542751],"type":"Point"}
}