{
  "type": "Feature",
  "properties": {
    "iso:country":"NL",
    "sg:address":"Eendrachtstr 27",
    "sg:city":"Coevorden",
    "sg:orig_category":"Begrafenisverzorging",
    "sg:phone":"+31 524 512 538",
    "sg:postcode":"7742 VJ",
    "sg:province":"Drenthe",
    "wof:name":"Laatste Eer, De",
    "wof:placetype":"venue"
},
  "geometry": {"coordinates":[6.743318,52.657509],"type":"Point"}
}