{
  "type": "Feature",
  "properties": {
    "addr:full":"Oost Kinderdijk 193 Alblasserdam Zuid-Holland 2953 CL",
    "addr:housenumber":"193",
    "addr:postcode":"2953",
    "addr:street":"Oost Kinderdijk",
    "iso:country":"NL",
    "sg:address":"Oost Kinderdijk 193",
    "sg:city":"Alblasserdam",
    "sg:orig_category":"Bedrijfs- And Managementsconsultants",
    "sg:phone":"+31 78 691 5979",
    "sg:postcode":"2953 CL",
    "sg:province":"Zuid-Holland",
    "wof:name":"Swing, Business Consultancy",
    "wof:placetype":"venue"
},
  "geometry": {"coordinates":[4.642732,51.867908],"type":"Point"}
}