{
  "type": "Feature",
  "properties": {
    "addr:full":"Brandery 5 Leek Groningen 9351 NX",
    "addr:housenumber":"5",
    "addr:postcode":"9351 nx",
    "addr:street":"Brandery",
    "iso:country":"NL",
    "sg:address":"Brandery 5",
    "sg:city":"Leek",
    "sg:orig_category":"Metaaldraaierijen",
    "sg:phone":"+31 594 518 680",
    "sg:postcode":"9351 NX",
    "sg:province":"Groningen",
    "sg:website":"http://www.vcn-leek.nl",
    "wof:name":"Verspanings Centrum Noord Bv",
    "wof:placetype":"venue"
},
  "geometry": {"coordinates":[6.367389,53.154011],"type":"Point"}
}