{
  "type": "Feature",
  "properties": {
    "addr:full":"Piet Heinstraat 19 'S Gravenhage Zuid-Holland 2518 CB",
    "addr:housenumber":"19",
    "addr:postcode":"2518 cb",
    "addr:street":"Piet Heinstraat;' S",
    "iso:country":"NL",
    "sg:address":"Piet Heinstraat 19",
    "sg:city":"'S Gravenhage",
    "sg:orig_category":"Luchtvaart",
    "sg:phone":"+31 70 356 0900",
    "sg:postcode":"2518 CB",
    "sg:province":"Zuid-Holland",
    "wof:name":"Surinam Airways",
    "wof:placetype":"venue"
},
  "geometry": {"coordinates":[4.299729,52.082455],"type":"Point"}
}