{
  "type": "Feature",
  "properties": {
    "addr:full":"Dr. A.F. Philipsweg 47 Assen Drenthe 9403 AD",
    "addr:housenumber":"47",
    "addr:postcode":"9403 ad",
    "addr:street":"Dr. A.F. Philipsweg",
    "iso:country":"NL",
    "sg:address":"Dr. A.F. Philipsweg 47",
    "sg:city":"Assen",
    "sg:orig_category":"Bedrijfsinventaris Gh",
    "sg:phone":"+31 592 376 376",
    "sg:postcode":"9403 AD",
    "sg:province":"Drenthe",
    "wof:name":"Animo Bv",
    "wof:placetype":"venue"
},
  "geometry": {"coordinates":[6.583522,53.001839],"type":"Point"}
}