{
  "type": "Feature",
  "properties": {
    "addr:full":"Oldenzaalsestr 104 Hengelo Ov Overijssel 7557 GA",
    "addr:housenumber":"104",
    "addr:postcode":"7557 ga",
    "addr:street":"Ov",
    "iso:country":"NL",
    "sg:address":"Oldenzaalsestr 104",
    "sg:city":"Hengelo Ov",
    "sg:orig_category":"Haptotherapeuten",
    "sg:phone":"+31 74 242 6726",
    "sg:postcode":"7557 GA",
    "sg:province":"Overijssel",
    "wof:name":"Horst, G J M Ter",
    "wof:placetype":"venue"
},
  "geometry": {"coordinates":[6.799965,52.268799],"type":"Point"}
}