{
  "type": "Feature",
  "properties": {
    "iso:country":"NL",
    "sg:address":"De Ambachten 41A",
    "sg:city":"Zundert",
    "sg:orig_category":"Verlichtingsartikelen - Fabrieken",
    "sg:phone":"+31 76 597 2365",
    "sg:postcode":"4881 XZ",
    "sg:province":"Noord-Brabant",
    "sg:website":"http://www.clairtronics.nl",
    "wof:name":"Clairtronics Bv",
    "wof:placetype":"venue"
},
  "geometry": {"coordinates":[4.646847,51.464764],"type":"Point"}
}