{
  "type": "Feature",
  "properties": {
    "addr:full":"De Stede 23 'S Gravenhage Zuid-Holland 2543 BG",
    "addr:housenumber":"23",
    "addr:postcode":"2543",
    "addr:street":"De Stede;' S",
    "iso:country":"NL",
    "sg:address":"De Stede 23",
    "sg:city":"'S Gravenhage",
    "sg:classifiers":[
        {
            "category":"Retail",
            "subcategory":"Photofinishing",
            "type":"Services"
        }
    ],
    "sg:phone":"+31 70 367 9431",
    "sg:postcode":"2543 BG",
    "sg:province":"Zuid-Holland",
    "sg:tags":[
        "foto",
        "film"
    ],
    "wof:name":"Hafo Foto & Video",
    "wof:placetype":"venue"
},
  "geometry": {"coordinates":[4.259846,52.043476],"type":"Point"}
}