{
  "type": "Feature",
  "properties": {
    "addr:full":"Keienbergwg 109 Amsterdam Zuidoost North Holland 1101 GG",
    "addr:housenumber":"109",
    "addr:postcode":"1101 gg",
    "iso:country":"NL",
    "sg:address":"Keienbergwg 109",
    "sg:city":"Amsterdam Zuidoost",
    "sg:orig_category":"Grafische Bedrijven",
    "sg:phone":"+31 20 342 5425",
    "sg:postcode":"1101 GG",
    "sg:province":"North Holland",
    "wof:name":"Jurriaans Bv",
    "wof:placetype":"venue"
},
  "geometry": {"coordinates":[4.93461,52.306664],"type":"Point"}
}