{
  "type": "Feature",
  "properties": {
    "addr:full":"Veursewg 212 Voorschoten Zuid-Holland 2252 AH",
    "addr:housenumber":"212",
    "addr:postcode":"2252 ah",
    "iso:country":"NL",
    "sg:address":"Veursewg 212",
    "sg:city":"Voorschoten",
    "sg:classifiers":[
        {
            "category":"Retail",
            "subcategory":"Auto Repair",
            "type":"Services"
        }
    ],
    "sg:phone":"+31 71 561 2687",
    "sg:postcode":"2252 AH",
    "sg:province":"Zuid-Holland",
    "sg:tags":[
        "garage"
    ],
    "wof:name":"Heden, S Van Der",
    "wof:placetype":"venue"
},
  "geometry": {"coordinates":[4.433123,52.114323],"type":"Point"}
}