{
  "type": "Feature",
  "properties": {
    "addr:full":"J C Beetsln 139 Hoofddorp North Holland 2131 AK",
    "addr:housenumber":"139",
    "addr:postcode":"2131 ak",
    "addr:street":"J C Beetsln",
    "iso:country":"NL",
    "sg:address":"J C Beetsln 139",
    "sg:city":"Hoofddorp",
    "sg:orig_category":"Onderhoudswerken",
    "sg:phone":"+31 23 562 7745",
    "sg:postcode":"2131 AK",
    "sg:province":"North Holland",
    "wof:name":"Winter, R Y P De",
    "wof:placetype":"venue"
},
  "geometry": {"coordinates":[4.70066,52.322971],"type":"Point"}
}