{
  "type": "Feature",
  "properties": {
    "addr:full":"Mulderskamp 25 Goor Overijssel 7471 PC",
    "addr:housenumber":"25",
    "addr:postcode":"7471 pc",
    "addr:street":"Mulderskamp",
    "iso:country":"NL",
    "sg:address":"Mulderskamp 25",
    "sg:city":"Goor",
    "sg:orig_category":"Keukens",
    "sg:phone":"+31 547 364 016",
    "sg:postcode":"7471 PC",
    "sg:province":"Overijssel",
    "wof:name":"Freriksen",
    "wof:placetype":"venue"
},
  "geometry": {"coordinates":[6.599273,52.231544],"type":"Point"}
}