{
  "type": "Feature",
  "properties": {
    "addr:full":"Postbus 397 Venlo Limburg 5900 AJ",
    "addr:housenumber":"397",
    "addr:postcode":"5900 aj",
    "addr:street":"Postbus",
    "iso:country":"NL",
    "sg:address":"Postbus 397",
    "sg:city":"Venlo",
    "sg:orig_category":"Verzekeringen - Verzekeringskantoren",
    "sg:phone":"+31 77 351 2102",
    "sg:postcode":"5900 AJ",
    "sg:province":"Limburg",
    "wof:name":"Cabooter Bv",
    "wof:placetype":"venue"
},
  "geometry": {"coordinates":[6.17286,51.372421],"type":"Point"}
}