{
  "type": "Feature",
  "properties": {
    "addr:full":"Plesmanstr 62 Veenendaal Utrecht 3905 KZ",
    "addr:housenumber":"62",
    "addr:postcode":"3905",
    "addr:street":"Plesmanstr",
    "iso:country":"NL",
    "sg:address":"Plesmanstr 62",
    "sg:city":"Veenendaal",
    "sg:classifiers":[
        {
            "category":"Wholesale",
            "subcategory":"Meat",
            "type":"Manufacturing & Wholesale Goods"
        }
    ],
    "sg:phone":"+31 318 559 290",
    "sg:postcode":"3905 KZ",
    "sg:province":"Utrecht",
    "sg:tags":[
        "regeltechniek",
        "en",
        "meet-"
    ],
    "sg:website":"http://www.bk-bnl.nl",
    "wof:name":"Bruel & Kjaer Ned",
    "wof:placetype":"venue"
},
  "geometry": {"coordinates":[5.555832,52.039543],"type":"Point"}
}