{
  "type": "Feature",
  "properties": {
    "addr:full":"Zwarte Zee 54 Maassluis Zuid-Holland 3144 DE",
    "addr:housenumber":"54",
    "addr:postcode":"3144 de",
    "addr:street":"Zwarte Zee",
    "iso:country":"NL",
    "sg:address":"Zwarte Zee 54",
    "sg:city":"Maassluis",
    "sg:orig_category":"Diverse Bedrijfsinstallaties Gh",
    "sg:phone":"+31 10 591 5011",
    "sg:postcode":"3144 DE",
    "sg:province":"Zuid-Holland",
    "wof:name":"Van Kessel Luchtbehandeling Bv",
    "wof:placetype":"venue"
},
  "geometry": {"coordinates":[4.24447,51.918861],"type":"Point"}
}