{
  "type": "Feature",
  "properties": {
    "addr:full":"Thorbeckegracht 28 Zwolle Overijssel 8011 VM",
    "addr:housenumber":"28",
    "addr:postcode":"8011 vm",
    "addr:street":"Thorbeckegracht",
    "iso:country":"NL",
    "sg:address":"Thorbeckegracht 28",
    "sg:city":"Zwolle",
    "sg:orig_category":"Meubelzaken, Woning- And Keukeninrichting",
    "sg:phone":"+31 38 422 4704",
    "sg:postcode":"8011 VM",
    "sg:province":"Overijssel",
    "wof:name":"Grenen Meubel Centrum",
    "wof:placetype":"venue"
},
  "geometry": {"coordinates":[6.097209,52.514771],"type":"Point"}
}