{
  "type": "Feature",
  "properties": {
    "iso:country":"NL",
    "sg:address":"Rembrandtgalery 125",
    "sg:city":"Roosendaal",
    "sg:orig_category":"Bloemen En Planten",
    "sg:phone":"+31 165 533 083",
    "sg:postcode":"4703 GX",
    "sg:province":"North Brabant",
    "wof:name":"Hagenaars, Jan",
    "wof:placetype":"venue"
},
  "geometry": {"coordinates":[4.443242,51.535049],"type":"Point"}
}