{
  "type": "Feature",
  "properties": {
    "addr:full":"Handelsweg 5 Meerkerk Zuid-Holland 4231 EZ",
    "addr:housenumber":"5",
    "addr:postcode":"4231 ez",
    "addr:street":"Handelsweg",
    "iso:country":"NL",
    "sg:address":"Handelsweg 5",
    "sg:city":"Meerkerk",
    "sg:orig_category":"Zuivelproducten And Spijsoli?n Gh",
    "sg:phone":"+31 183 353 088",
    "sg:postcode":"4231 EZ",
    "sg:province":"Zuid-Holland",
    "wof:name":"Handelsonderneming Nico Schep Bv",
    "wof:placetype":"venue"
},
  "geometry": {"coordinates":[4.98606,51.908169],"type":"Point"}
}