{
  "type": "Feature",
  "properties": {
    "addr:full":"Westfalenstraat 44 Alkmaar Noord-Holland 1827 AZ",
    "addr:housenumber":"44",
    "addr:postcode":"1827 az",
    "addr:street":"Westfalenstraat",
    "iso:country":"NL",
    "sg:address":"Westfalenstraat 44",
    "sg:city":"Alkmaar",
    "sg:orig_category":"Diverse Grafische Activiteiten",
    "sg:phone":"+31 72 561 9695",
    "sg:postcode":"1827 AZ",
    "sg:province":"Noord-Holland",
    "wof:name":"K & P-Produkties Alkmaar",
    "wof:placetype":"venue"
},
  "geometry": {"coordinates":[4.756796,52.666752],"type":"Point"}
}