{
  "type": "Feature",
  "properties": {
    "addr:full":"Hoogstr 26 Berlicum Nb Noord-Brabant 5258 BD",
    "addr:housenumber":"26",
    "addr:postcode":"5258 bd",
    "addr:street":"Hoogstr",
    "iso:country":"NL",
    "sg:address":"Hoogstr 26",
    "sg:city":"Berlicum Nb",
    "sg:orig_category":"Juridische Adviseurs",
    "sg:phone":"+31 73 503 2543",
    "sg:postcode":"5258 BD",
    "sg:province":"Noord-Brabant",
    "wof:name":"Jurisconsult",
    "wof:placetype":"venue"
},
  "geometry": {"coordinates":[5.389811,51.683235],"type":"Point"}
}