{
  "type": "Feature",
  "properties": {
    "addr:full":"Zwaanstr 44 Amersfoort Utrecht 3816 AR",
    "addr:housenumber":"44",
    "addr:postcode":"3816",
    "addr:street":"Zwaanstr",
    "iso:country":"NL",
    "sg:address":"Zwaanstr 44",
    "sg:city":"Amersfoort",
    "sg:orig_category":"Schilders",
    "sg:phone":"+31 33 475 8989",
    "sg:postcode":"3816 AR",
    "sg:province":"Utrecht",
    "wof:name":"Braak, J M Van Den",
    "wof:placetype":"venue"
},
  "geometry": {"coordinates":[5.396215,52.151688],"type":"Point"}
}