{
  "type": "Feature",
  "properties": {
    "addr:full":"Graswinckelstraat 11 Arnhem Gelderland 6828 TL",
    "addr:housenumber":"11",
    "addr:postcode":"6828 tl",
    "addr:street":"Graswinckelstraat",
    "iso:country":"NL",
    "sg:address":"Graswinckelstraat 11",
    "sg:city":"Arnhem",
    "sg:orig_category":"Kinderopvang Behalve Thuis",
    "sg:phone":"+31 26 442 2949",
    "sg:postcode":"6828 TL",
    "sg:province":"Gelderland",
    "wof:name":"Kinderdagverblijf Kakelbont",
    "wof:placetype":"venue"
},
  "geometry": {"coordinates":[5.932356,51.981346],"type":"Point"}
}