{
  "type": "Feature",
  "properties": {
    "addr:full":"Slotlaan 130 Zeist Utrecht 3701 GR",
    "addr:housenumber":"130",
    "addr:postcode":"3701",
    "addr:street":"Slotlaan",
    "iso:country":"NL",
    "sg:address":"Slotlaan 130",
    "sg:city":"Zeist",
    "sg:orig_category":"Damesmodezaken",
    "sg:phone":"+31 30 692 5734",
    "sg:postcode":"3701 GR",
    "sg:province":"Utrecht",
    "wof:name":"Modehuis H.Slot Zeist Bv",
    "wof:placetype":"venue"
},
  "geometry": {"coordinates":[5.243303,52.084873],"type":"Point"}
}