{
  "type": "Feature",
  "properties": {
    "iso:country":"NL",
    "sg:address":"Wilhelminapln 2",
    "sg:city":"Naaldwyk",
    "sg:orig_category":"Projectontwikkeling",
    "sg:phone":"+31 174 615 544",
    "sg:postcode":"2671 GR",
    "sg:province":"Zuid-Holland",
    "sg:website":"http://www.bouhuisen-groep.nl",
    "wof:name":"Bouhuisen Groep",
    "wof:placetype":"venue"
},
  "geometry": {"coordinates":[4.207659,51.992718],"type":"Point"}
}