{
  "type": "Feature",
  "properties": {
    "iso:country":"NL",
    "sg:address":"Voorstraat 17",
    "sg:city":"Vianen Zh",
    "sg:classifiers":[
        {
            "category":"Retail",
            "subcategory":"Photofinishing",
            "type":"Services"
        }
    ],
    "sg:phone":"+31 347 371 069",
    "sg:postcode":"4132 AM",
    "sg:province":"Utrecht",
    "sg:tags":[
        "foto",
        "film"
    ],
    "wof:name":"Fotodiscounts",
    "wof:placetype":"venue"
},
  "geometry": {"coordinates":[5.091733,51.9953],"type":"Point"}
}