{
  "type": "Feature",
  "properties": {
    "addr:full":"Het Gewat 20 Berlicum Nb Noord-Brabant 5258 KL",
    "addr:housenumber":"20",
    "addr:postcode":"5258 kl",
    "addr:street":"Het Gewat",
    "iso:country":"NL",
    "sg:address":"Het Gewat 20",
    "sg:city":"Berlicum Nb",
    "sg:orig_category":"Bedrijfs- And Managementsconsultants",
    "sg:phone":"+31 73 503 7068",
    "sg:postcode":"5258 KL",
    "sg:province":"Noord-Brabant",
    "wof:name":"Improve Business Consultants Bv",
    "wof:placetype":"venue"
},
  "geometry": {"coordinates":[5.412314,51.664745],"type":"Point"}
}