{
  "type": "Feature",
  "properties": {
    "iso:country":"NL",
    "sg:address":"Voorsteven 19",
    "sg:city":"Wyk By Duurstede",
    "sg:orig_category":"Verenigingen En Stichtingen",
    "sg:phone":"+31 343 597 175",
    "sg:postcode":"3961 TG",
    "sg:province":"Utrecht",
    "wof:name":"Abrona",
    "wof:placetype":"venue"
},
  "geometry": {"coordinates":[5.326046,51.970634],"type":"Point"}
}