{
  "type": "Feature",
  "properties": {
    "addr:full":"Turfsngl 49 Gouda Zuid-Holland 2802 BC",
    "addr:housenumber":"49",
    "addr:postcode":"2802 bc",
    "addr:street":"Turfsngl",
    "iso:country":"NL",
    "sg:address":"Turfsngl 49",
    "sg:city":"Gouda",
    "sg:classifiers":[
        {
            "category":"Personal",
            "subcategory":"Nail Salon",
            "type":"Services"
        }
    ],
    "sg:phone":"+31 182 526 823",
    "sg:postcode":"2802 BC",
    "sg:province":"Zuid-Holland",
    "sg:tags":[
        "pedicure"
    ],
    "wof:name":"Joke Geukes",
    "wof:placetype":"venue"
},
  "geometry": {"coordinates":[4.710715,52.010006],"type":"Point"}
}