{
  "type": "Feature",
  "properties": {
    "addr:full":"Westkade 12 Sas Van Gent Zeeland 4551 BV",
    "addr:housenumber":"12",
    "addr:postcode":"4551 bv",
    "addr:street":"Westkade",
    "iso:country":"NL",
    "sg:address":"Westkade 12",
    "sg:city":"Sas Van Gent",
    "sg:orig_category":"Benzinestations And Brandstoffen",
    "sg:phone":"+31 115 451 529",
    "sg:postcode":"4551 BV",
    "sg:province":"Zeeland",
    "wof:name":"Fina",
    "wof:placetype":"venue"
},
  "geometry": {"coordinates":[3.801477,51.213623],"type":"Point"}
}