{
  "type": "Feature",
  "properties": {
    "addr:full":"Populierweg 3 Watergang Noord-Holland 1454 AR",
    "addr:housenumber":"3",
    "addr:postcode":"1454",
    "addr:street":"Populierweg",
    "iso:country":"NL",
    "sg:address":"Populierweg 3",
    "sg:city":"Watergang",
    "sg:orig_category":"Granen, Zaden And Diervoeders Gh",
    "sg:phone":"+31 20 436 3207",
    "sg:postcode":"1454 AR",
    "sg:province":"Noord-Holland",
    "wof:name":"Plantvit Bv",
    "wof:placetype":"venue"
},
  "geometry": {"coordinates":[4.951602,52.438633],"type":"Point"}
}