{
  "type": "Feature",
  "properties": {
    "iso:country":"NL",
    "sg:address":"Bastenakenstr 18",
    "sg:city":"Amsterdam",
    "sg:orig_category":"Artiesten/Gezelschappen",
    "sg:phone":"+31 20 408 0483",
    "sg:postcode":"1066 JD",
    "sg:province":"North Holland",
    "sg:website":"http://www.mama-entertainment.nl",
    "wof:name":"Mama Entertainment Vof",
    "wof:placetype":"venue"
},
  "geometry": {"coordinates":[4.813174,52.342831],"type":"Point"}
}