{
  "type": "Feature",
  "properties": {
    "addr:full":"Oostzyde 289 Zaandam Noord-Holland 1508 EN",
    "addr:housenumber":"289",
    "addr:postcode":"1508 en",
    "addr:street":"Oostzyde",
    "iso:country":"NL",
    "sg:address":"Oostzyde 289",
    "sg:city":"Zaandam",
    "sg:orig_category":"Parketvloeren",
    "sg:phone":"+31 75 614 6850",
    "sg:postcode":"1508 EN",
    "sg:province":"Noord-Holland",
    "wof:name":"Fir",
    "wof:placetype":"venue"
},
  "geometry": {"coordinates":[4.81295,52.44162],"type":"Point"}
}