{
  "type": "Feature",
  "properties": {
    "addr:full":"Sprongenloet 4 Honselersdyk South Holland 2675 KV",
    "addr:housenumber":"4",
    "addr:postcode":"2675 kv",
    "addr:street":"Sprongenloet",
    "iso:country":"NL",
    "sg:address":"Sprongenloet 4",
    "sg:city":"Honselersdyk",
    "sg:orig_category":"Onderhoudswerken",
    "sg:phone":"+31 6 25342974",
    "sg:postcode":"2675 KV",
    "sg:province":"South Holland",
    "wof:name":"Geron",
    "wof:placetype":"venue"
},
  "geometry": {"coordinates":[4.240834,52.002914],"type":"Point"}
}