{
  "type": "Feature",
  "properties": {
    "iso:country":"NL",
    "sg:address":"Peizerweg 146",
    "sg:city":"Groningen",
    "sg:orig_category":"Wegen And Sportterreinen",
    "sg:phone":"+31 50 520 1111",
    "sg:postcode":"9727 AR",
    "sg:province":"Groningen",
    "wof:name":"Koop Tjuchem Bv",
    "wof:placetype":"venue"
},
  "geometry": {"coordinates":[6.5361819267,53.2073974609],"type":"Point"}
}