{
  "type": "Feature",
  "properties": {
    "iso:country":"NL",
    "sg:address":"Nieuwstraat 17A",
    "sg:city":"Bruinisse",
    "sg:orig_category":"Kappers",
    "sg:phone":"+31 111 482 722",
    "sg:postcode":"4311 AM",
    "sg:province":"Zeeland",
    "wof:name":"Kapsalon 'T Knip-Uus",
    "wof:placetype":"venue"
},
  "geometry": {"coordinates":[4.0942988396,51.6612815857],"type":"Point"}
}