{
  "type": "Feature",
  "properties": {
    "iso:country":"NL",
    "sg:address":"Vecht 116",
    "sg:city":"Nieuwerkerk Yssel",
    "sg:orig_category":"Organisatiebureaus",
    "sg:phone":"+31 180 399 733",
    "sg:postcode":"2911 ES",
    "sg:province":"Zuid-Holland",
    "wof:name":"Proza Vof",
    "wof:placetype":"venue"
},
  "geometry": {"coordinates":[4.6163082123,51.9583587646],"type":"Point"}
}