{
  "type": "Feature",
  "properties": {
    "iso:country":"NL",
    "sg:address":"Capucijnerpln 1C",
    "sg:city":"Budel",
    "sg:orig_category":"Wolartikelen En Breiwol",
    "sg:phone":"+31 495 495 324",
    "sg:postcode":"6021 CA",
    "sg:province":"Noord-Brabant",
    "wof:name":"Phildar",
    "wof:placetype":"venue"
},
  "geometry": {"coordinates":[5.5764517784,51.273311615],"type":"Point"}
}