{
  "type": "Feature",
  "properties": {
    "addr:full":"Rijnhuizenln 27 Utrecht Utrecht 3523 JC",
    "addr:housenumber":"27",
    "addr:postcode":"3523 jc",
    "addr:street":"Rijnhuizenln",
    "iso:country":"NL",
    "sg:address":"Rijnhuizenln 27",
    "sg:city":"Utrecht",
    "sg:orig_category":"Artsen - Huisartsen",
    "sg:phone":"+31 30 288 0292",
    "sg:postcode":"3523 JC",
    "sg:province":"Utrecht",
    "wof:name":"Huisartsenprakt Rijnhuizenlaan",
    "wof:placetype":"venue"
},
  "geometry": {"coordinates":[5.122886,52.067963],"type":"Point"}
}