{
  "type": "Feature",
  "properties": {
    "addr:full":"Vlaardingenstr 6 Almere Flevoland 1324 LC",
    "addr:housenumber":"6",
    "addr:postcode":"1324 lc",
    "addr:street":"Vlaardingenstr;Flevoland",
    "iso:country":"NL",
    "sg:address":"Vlaardingenstr 6",
    "sg:city":"Almere",
    "sg:orig_category":"Autowasserettes",
    "sg:phone":"+31 73 641 5982",
    "sg:postcode":"1324 LC",
    "sg:province":"Flevoland",
    "wof:name":"Blauwe Olifant, De",
    "wof:placetype":"venue"
},
  "geometry": {"coordinates":[5.201644,52.362457],"type":"Point"}
}