{
  "type": "Feature",
  "properties": {
    "iso:country":"NL",
    "sg:address":"Industrieweg 55",
    "sg:city":"Zoetermeer",
    "sg:orig_category":"Verhuur Huishoudartikelen",
    "sg:phone":"+31 79 331 6545",
    "sg:postcode":"2712 LA",
    "sg:province":"Zuid-Holland",
    "wof:name":"Doe Verhuur",
    "wof:placetype":"venue"
},
  "geometry": {"coordinates":[4.511168,52.048008],"type":"Point"}
}