{
  "type": "Feature",
  "properties": {
    "iso:country":"NL",
    "sg:address":"Kloosterstr 15",
    "sg:city":"Duivendrecht",
    "sg:classifiers":[
        {
            "category":"Retail",
            "subcategory":"Auto Repair",
            "type":"Services"
        }
    ],
    "sg:phone":"+31 20 699 1632",
    "sg:postcode":"1115 BJ",
    "sg:province":"Noord-Holland",
    "sg:tags":[
        "garage"
    ],
    "wof:name":"Buys En Hauber, Garage",
    "wof:placetype":"venue"
},
  "geometry": {"coordinates":[4.940942,52.334747],"type":"Point"}
}