{
  "type": "Feature",
  "properties": {
    "addr:full":"Brandstraat 14 Heerde Gelderland 8181 GD",
    "addr:housenumber":"14",
    "addr:postcode":"8181 gd",
    "addr:street":"Brandstraat;Gelderland",
    "iso:country":"NL",
    "sg:address":"Brandstraat 14",
    "sg:city":"Heerde",
    "sg:orig_category":"Goederenvervoer Over De Weg",
    "sg:phone":"+31 578 691 867",
    "sg:postcode":"8181 GD",
    "sg:province":"Gelderland",
    "wof:name":"A.J. Herms",
    "wof:placetype":"venue"
},
  "geometry": {"coordinates":[6.037249,52.384315],"type":"Point"}
}