{
  "type": "Feature",
  "properties": {
    "addr:full":"Ottergeerde 22-28 Raamsdonksveer Noord-Brabant 4941 VM",
    "addr:housenumber":"22-28",
    "addr:postcode":"4941 vm",
    "addr:street":"Ottergeerde",
    "iso:country":"NL",
    "sg:address":"Ottergeerde 22-28",
    "sg:city":"Raamsdonksveer",
    "sg:orig_category":"Plastic Verwerkende Industrie",
    "sg:phone":"+31 162 587 600",
    "sg:postcode":"4941 VM",
    "sg:province":"Noord-Brabant",
    "wof:name":"Lnp Europe Bv",
    "wof:placetype":"venue"
},
  "geometry": {"coordinates":[4.879449,51.707783],"type":"Point"}
}