{
  "type": "Feature",
  "properties": {
    "addr:full":"Boslaan 88A Emmen Drenthe 7823 TS",
    "addr:housenumber":"88a",
    "addr:postcode":"7823 ts",
    "addr:street":"Boslaan",
    "iso:country":"NL",
    "sg:address":"Boslaan 88A",
    "sg:city":"Emmen",
    "sg:orig_category":"Bloemen And Planten",
    "sg:phone":"+31 591 625 912",
    "sg:postcode":"7823 TS",
    "sg:province":"Drenthe",
    "wof:name":"Bloemenschuur De Tobbe",
    "wof:placetype":"venue"
},
  "geometry": {"coordinates":[6.937105,52.799671],"type":"Point"}
}