{
  "type": "Feature",
  "properties": {
    "iso:country":"NL",
    "sg:address":"Oosterhuiswg 3",
    "sg:city":"Makkinga",
    "sg:orig_category":"Verenigingen En Stichtingen",
    "sg:phone":"+31 516 441 315",
    "sg:postcode":"8423 TG",
    "sg:province":"Provincie Friesland",
    "wof:name":"Dorpshuis, Sticht",
    "wof:placetype":"venue"
},
  "geometry": {"coordinates":[6.218904,52.980694],"type":"Point"}
}