{
  "type": "Feature",
  "properties": {
    "addr:full":"Boschdijkdwarsstraat 16 Budel Noord-Brabant 6021 AL",
    "addr:housenumber":"16",
    "addr:postcode":"6021 al",
    "addr:street":"Boschdijkdwarsstraat",
    "iso:country":"NL",
    "sg:address":"Boschdijkdwarsstraat 16",
    "sg:city":"Budel",
    "sg:orig_category":"Pluimveehouderijen",
    "sg:phone":"+31 495 491 579",
    "sg:postcode":"6021 AL",
    "sg:province":"Noord-Brabant",
    "wof:name":"J.J. Vermeulen-Richaerts",
    "wof:placetype":"venue"
},
  "geometry": {"coordinates":[5.59598,51.270943],"type":"Point"}
}