{
  "type": "Feature",
  "properties": {
    "iso:country":"NL",
    "sg:address":"Gladiolenveld 17",
    "sg:city":"Castricum",
    "sg:orig_category":"Adviesbureaus Onderhoudswerken",
    "sg:phone":"+31 251 671 012",
    "sg:postcode":"1901 LR",
    "sg:province":"Noord-Holland",
    "wof:name":"Behrens, Wim",
    "wof:placetype":"venue"
},
  "geometry": {"coordinates":[4.674615,52.560207],"type":"Point"}
}