{
  "type": "Feature",
  "properties": {
    "iso:country":"NL",
    "sg:address":"Strijperstraat 73",
    "sg:city":"Leende",
    "sg:orig_category":"Visspeciaalzaken",
    "sg:phone":"+31 40 206 1357",
    "sg:postcode":"5595 GB",
    "sg:province":"Noord-Brabant",
    "wof:name":"Svr Camping De Zandberg",
    "wof:placetype":"venue"
},
  "geometry": {"coordinates":[-2.23218,54.313919],"type":"Point"}
}