{
  "type": "Feature",
  "properties": {
    "addr:full":"Wulp 5 Ouderkerk Amstel Noord-Holland 1191 TA",
    "addr:housenumber":"5",
    "addr:postcode":"1191 ta",
    "addr:street":"Wulp;Ouderkerk Amstel",
    "iso:country":"NL",
    "sg:address":"Wulp 5",
    "sg:city":"Ouderkerk Amstel",
    "sg:orig_category":"Schoonheidsinstituten",
    "sg:phone":"+31 20 496 7660",
    "sg:postcode":"1191 TA",
    "sg:province":"Noord-Holland",
    "wof:name":"Jacqueline",
    "wof:placetype":"venue"
},
  "geometry": {"coordinates":[4.909408,52.293789],"type":"Point"}
}