{
  "type": "Feature",
  "properties": {
    "addr:full":"Beekstraat 65 Weert Limburg 6001 GH",
    "addr:housenumber":"65",
    "addr:postcode":"6001 gh",
    "addr:street":"Beekstraat",
    "iso:country":"NL",
    "sg:address":"Beekstraat 65",
    "sg:city":"Weert",
    "sg:orig_category":"Biljart- And Snookerzalen",
    "sg:phone":"+31 495 546 627",
    "sg:postcode":"6001 GH",
    "sg:province":"Limburg",
    "wof:name":"Stichting Lunchcafe Weert",
    "wof:placetype":"venue"
},
  "geometry": {"coordinates":[5.705517,51.25597],"type":"Point"}
}