{
  "type": "Feature",
  "properties": {
    "addr:full":"Prijsseweg 16 Culemborg Gelderland 4105 LE",
    "addr:housenumber":"16",
    "addr:postcode":"4105 le",
    "addr:street":"Prijsseweg;Gelderland",
    "iso:country":"NL",
    "sg:address":"Prijsseweg 16",
    "sg:city":"Culemborg",
    "sg:orig_category":"Verhuur Diversen",
    "sg:phone":"+31 345 517 179",
    "sg:postcode":"4105 LE",
    "sg:province":"Gelderland",
    "wof:name":"J G Van Dord",
    "wof:placetype":"venue"
},
  "geometry": {"coordinates":[5.189023,51.950947],"type":"Point"}
}