{
  "type": "Feature",
  "properties": {
    "iso:country":"NL",
    "sg:address":"Westendorpseweg 10",
    "sg:city":"Doetinchem",
    "sg:orig_category":"Landbouwmachines Gh",
    "sg:phone":"+31 314 631 236",
    "sg:postcode":"7004 JD",
    "sg:province":"Gelderland",
    "wof:name":"H.W. Mebelder",
    "wof:placetype":"venue"
},
  "geometry": {"coordinates":[6.410976,51.973724],"type":"Point"}
}