{
  "type": "Feature",
  "properties": {
    "addr:full":"Stapakker 10 Oirschot North Brabant 5688 PR",
    "addr:housenumber":"10",
    "addr:postcode":"5688 pr",
    "addr:street":"Stapakker",
    "iso:country":"NL",
    "sg:address":"Stapakker 10",
    "sg:city":"Oirschot",
    "sg:classifiers":[
        {
            "category":"Personal",
            "subcategory":"Nail Salon",
            "type":"Services"
        }
    ],
    "sg:phone":"+31 499 575 565",
    "sg:postcode":"5688 PR",
    "sg:province":"North Brabant",
    "sg:tags":[
        "pedicure"
    ],
    "wof:name":"Pied, Le",
    "wof:placetype":"venue"
},
  "geometry": {"coordinates":[5.31332,51.509258],"type":"Point"}
}