{
  "type": "Feature",
  "properties": {
    "iso:country":"NL",
    "sg:address":"Wagenwg 1B",
    "sg:city":"Purmerend",
    "sg:orig_category":"Levensmiddelen - Fabrieken En Groothandel",
    "sg:phone":"+31 299 427 482",
    "sg:postcode":"1442 BX",
    "sg:province":"Noord-Holland",
    "wof:name":"Kweker, De",
    "wof:placetype":"venue"
},
  "geometry": {"coordinates":[4.955727,52.508968],"type":"Point"}
}