{
  "type": "Feature",
  "properties": {
    "iso:country":"NL",
    "sg:address":"Merellaan 4",
    "sg:city":"Capelle A/D Ijssel",
    "sg:orig_category":"Onderhoud And Reparatie Kantoorapparatuur",
    "sg:phone":"+31 10 451 1537",
    "sg:postcode":"2902 JG",
    "sg:province":"Zuid-Holland",
    "wof:name":"Vcs",
    "wof:placetype":"venue"
},
  "geometry": {"coordinates":[4.578802,51.929138],"type":"Point"}
}