{
  "type": "Feature",
  "properties": {
    "addr:full":"Merellaan 4 Capelle A/D Ijssel Zuid-Holland 2902 JG",
    "addr:housenumber":"4;a / d",
    "addr:postcode":"2902 jg",
    "addr:street":"Merellaan",
    "iso:country":"NL",
    "sg:address":"Merellaan 4",
    "sg:city":"Capelle A/D Ijssel",
    "sg:orig_category":"Onderhoud And Reparatie Kantoorapparatuur",
    "sg:phone":"+31 10 451 1537",
    "sg:postcode":"2902 JG",
    "sg:province":"Zuid-Holland",
    "wof:name":"Vcs",
    "wof:placetype":"venue"
},
  "geometry": {"coordinates":[4.578802,51.929138],"type":"Point"}
}