{
  "type": "Feature",
  "properties": {
    "addr:full":"J V Stolbergstr 3 Tilburg North Brabant 5038 AM",
    "addr:housenumber":"3",
    "addr:postcode":"5038",
    "addr:street":"J;Stolbergstr",
    "iso:country":"NL",
    "sg:address":"J V Stolbergstr 3",
    "sg:city":"Tilburg",
    "sg:orig_category":"Kousen En Sokken",
    "sg:phone":"+31 13 542 1124",
    "sg:postcode":"5038 AM",
    "sg:province":"North Brabant",
    "wof:name":"Jambelle Tilburg",
    "wof:placetype":"venue"
},
  "geometry": {"coordinates":[5.07758,51.556911],"type":"Point"}
}