{
  "type": "Feature",
  "properties": {
    "addr:full":"Eperwg 2 Nunspeet Gelderland 8071 AX",
    "addr:housenumber":"2",
    "addr:postcode":"8071 ax",
    "addr:street":"Eperwg;Gelderland",
    "iso:country":"NL",
    "sg:address":"Eperwg 2",
    "sg:city":"Nunspeet",
    "sg:orig_category":"Makelaars En Adviseurs Onroerende Goederen",
    "sg:phone":"+31 341 261 911",
    "sg:postcode":"8071 AX",
    "sg:province":"Gelderland",
    "wof:name":"Visscher",
    "wof:placetype":"venue"
},
  "geometry": {"coordinates":[5.788738,52.376396],"type":"Point"}
}