{
  "type": "Feature",
  "properties": {
    "addr:full":"Smidswg 23 Schalkhaar NL.08 7433 BM",
    "addr:housenumber":"23;nl.08",
    "addr:postcode":"7433 bm",
    "addr:street":"Smidswg",
    "iso:country":"NL",
    "sg:address":"Smidswg 23",
    "sg:city":"Schalkhaar",
    "sg:orig_category":"Fietsen En Bromfietsen",
    "sg:phone":"+31 6 51015231",
    "sg:postcode":"7433 BM",
    "sg:province":"NL.08",
    "wof:name":"Goede, De",
    "wof:placetype":"venue"
},
  "geometry": {"coordinates":[6.1925,52.26775],"type":"Point"}
}