{
  "type": "Feature",
  "properties": {
    "iso:country":"NL",
    "sg:address":"Jordaensstraat 9",
    "sg:city":"Ede Gld",
    "sg:orig_category":"Boekhouders",
    "sg:phone":"+31 318 626 067",
    "sg:postcode":"6717 RK",
    "sg:province":"Gelderland",
    "wof:name":"C M Van Den Broek",
    "wof:placetype":"venue"
},
  "geometry": {"coordinates":[5.651819,52.019451],"type":"Point"}
}