{
  "type": "Feature",
  "properties": {
    "addr:full":"Bisschopswetering 23 S Heerenbroek Overijssel 8275 AK",
    "addr:housenumber":"23",
    "addr:postcode":"8275 ak",
    "addr:street":"Bisschopswetering;S Heerenbroek Overijssel",
    "iso:country":"NL",
    "sg:address":"Bisschopswetering 23",
    "sg:city":"S Heerenbroek",
    "sg:orig_category":"Onderhoudswerken",
    "sg:phone":"+31 38 355 6812",
    "sg:postcode":"8275 AK",
    "sg:province":"Overijssel",
    "wof:name":"Zunnenberg",
    "wof:placetype":"venue"
},
  "geometry": {"coordinates":[6.014145,52.5368],"type":"Point"}
}