{
  "type": "Feature",
  "properties": {
    "addr:full":"Kleine Overstraat 36 Deventer Overijssel 7411 JM",
    "addr:housenumber":"36",
    "addr:postcode":"7411 jm",
    "addr:street":"Kleine Overstraat",
    "iso:country":"NL",
    "sg:address":"Kleine Overstraat 36",
    "sg:city":"Deventer",
    "sg:orig_category":"Verlichting And Huishoudartikelen",
    "sg:phone":"+31 570 611 792",
    "sg:postcode":"7411 JM",
    "sg:province":"Overijssel",
    "wof:name":"Geertsema Woninginrichting",
    "wof:placetype":"venue"
},
  "geometry": {"coordinates":[6.158481,52.25201],"type":"Point"}
}