{
  "type": "Feature",
  "properties": {
    "iso:country":"NL",
    "sg:address":"Marnewaard 12",
    "sg:city":"Capelle A/D Ijssel",
    "sg:orig_category":"Verhuur Bouwmachines",
    "sg:phone":"+31 10 284 0810",
    "sg:postcode":"2904 ST",
    "sg:province":"Zuid-Holland",
    "wof:name":"Coenraadts Bv",
    "wof:placetype":"venue"
},
  "geometry": {"coordinates":[4.612825,51.936031],"type":"Point"}
}