{
  "type": "Feature",
  "properties": {
    "addr:full":"Capucijnerpln 14 Budel Noord-Brabant 6021 CB",
    "addr:housenumber":"14",
    "addr:postcode":"6021 cb",
    "addr:street":"Capucijnerpln",
    "iso:country":"NL",
    "sg:address":"Capucijnerpln 14",
    "sg:city":"Budel",
    "sg:orig_category":"Schoenen",
    "sg:phone":"+31 495 491 483",
    "sg:postcode":"6021 CB",
    "sg:province":"Noord-Brabant",
    "wof:name":"Elegance",
    "wof:placetype":"venue"
},
  "geometry": {"coordinates":[5.575181,51.273823],"type":"Point"}
}