{
  "type": "Feature",
  "properties": {
    "addr:full":"V Heylerhoffln 12 Maastricht Limburg 6211 KA",
    "addr:housenumber":"12",
    "addr:postcode":"6211 ka",
    "iso:country":"NL",
    "sg:address":"V Heylerhoffln 12",
    "sg:city":"Maastricht",
    "sg:orig_category":"Vertalers",
    "sg:phone":"+31 43 326 1557",
    "sg:postcode":"6211 KA",
    "sg:province":"Limburg",
    "wof:name":"Bailey, D",
    "wof:placetype":"venue"
},
  "geometry": {"coordinates":[5.68829,50.849831],"type":"Point"}
}