{
  "type": "Feature",
  "properties": {
    "addr:full":"Carstenswyk 1 Elim Provincie Drenthe 7916 TM",
    "addr:housenumber":"1",
    "addr:postcode":"7916 tm",
    "addr:street":"Carstenswyk;Provincie",
    "iso:country":"NL",
    "sg:address":"Carstenswyk 1",
    "sg:city":"Elim",
    "sg:orig_category":"Projectontwikkeling",
    "sg:phone":"+31 528 351 319",
    "sg:postcode":"7916 TM",
    "sg:province":"Provincie Drenthe",
    "sg:website":"http://www.adelaar-ontwikkeling.nl",
    "wof:name":"Reiderland Bv",
    "wof:placetype":"venue"
},
  "geometry": {"coordinates":[6.539142,52.684303],"type":"Point"}
}