{
  "type": "Feature",
  "properties": {
    "addr:full":"St Luciastr 4 Ter Apel Groningen 9561 GC",
    "addr:housenumber":"4",
    "addr:postcode":"9561 gc",
    "addr:street":"Ter",
    "iso:country":"NL",
    "sg:address":"St Luciastr 4",
    "sg:city":"Ter Apel",
    "sg:orig_category":"Kinderopvang",
    "sg:phone":"+31 599 582 417",
    "sg:postcode":"9561 GC",
    "sg:province":"Groningen",
    "sg:website":"http://www.skwe.nl",
    "wof:name":"Kinderopvang Westerwolde, Sticht",
    "wof:placetype":"venue"
},
  "geometry": {"coordinates":[7.051918,52.875851],"type":"Point"}
}