{
  "type": "Feature",
  "properties": {
    "iso:country":"NL",
    "sg:address":"Instr 10",
    "sg:city":"Budel",
    "sg:orig_category":"Geluidsinstallaties - Verhuur",
    "sg:phone":"+31 6 53882740",
    "sg:postcode":"6021 AC",
    "sg:province":"Noord-Brabant",
    "wof:name":"Reflash",
    "wof:placetype":"venue"
},
  "geometry": {"coordinates":[5.582551,51.26651],"type":"Point"}
}