{
  "type": "Feature",
  "properties": {
    "iso:country":"NL",
    "sg:address":"Hogewg 11",
    "sg:city":"Hulst",
    "sg:orig_category":"Glas",
    "sg:phone":"+31 114 311 487",
    "sg:postcode":"4561 RN",
    "sg:province":"Zeeland",
    "wof:name":"Waesberghe, H Van",
    "wof:placetype":"venue"
},
  "geometry": {"coordinates":[4.042647,51.270226],"type":"Point"}
}