{
  "type": "Feature",
  "properties": {
    "addr:full":"V Bodelswingstr 12 Ootmarsum NL.08 7631 JJ",
    "addr:housenumber":"12;nl.08",
    "addr:postcode":"7631 jj",
    "iso:country":"NL",
    "sg:address":"V Bodelswingstr 12",
    "sg:city":"Ootmarsum",
    "sg:orig_category":"Machineonderhoud En -Reparatie",
    "sg:phone":"+31 541 534 514",
    "sg:postcode":"7631 JJ",
    "sg:province":"NL.08",
    "wof:name":"Dijkhuis Cnc Service",
    "wof:placetype":"venue"
},
  "geometry": {"coordinates":[6.89415,52.406929],"type":"Point"}
}