{
  "type": "Feature",
  "properties": {
    "addr:full":"M Stokezyde 266 S Gravenhage Zuid-Holland 2543 GR",
    "addr:housenumber":"266;gravenhage",
    "addr:postcode":"2543",
    "addr:street":"S",
    "iso:country":"NL",
    "sg:address":"M Stokezyde 266",
    "sg:city":"S Gravenhage",
    "sg:orig_category":"Belastingconsulenten/ Belastingadviseurs",
    "sg:phone":"+31 70 321 3244",
    "sg:postcode":"2543 GR",
    "sg:province":"Zuid-Holland",
    "wof:name":"Hartman Bv, C A",
    "wof:placetype":"venue"
},
  "geometry": {"coordinates":[4.26264,52.040501],"type":"Point"}
}