{
  "type": "Feature",
  "properties": {
    "addr:full":"S Lagerlof Erf 163 Dordrecht South Holland 3315 AT",
    "addr:housenumber":"163",
    "addr:postcode":"3315",
    "iso:country":"NL",
    "sg:address":"S Lagerlof Erf 163",
    "sg:city":"Dordrecht",
    "sg:orig_category":"Kinderopvang",
    "sg:phone":"+31 78 616 7551",
    "sg:postcode":"3315 AT",
    "sg:province":"South Holland",
    "sg:website":"http://www.cokd.nl",
    "wof:name":"Polderbende, De",
    "wof:placetype":"venue"
},
  "geometry": {"coordinates":[4.72291,51.799984],"type":"Point"}
}