{
  "type": "Feature",
  "properties": {
    "addr:full":"Tuinderweg 28 Mariahout Noord-Brabant 5738 BL",
    "addr:housenumber":"28",
    "addr:postcode":"5738 bl",
    "addr:street":"Tuinderweg",
    "iso:country":"NL",
    "sg:address":"Tuinderweg 28",
    "sg:city":"Mariahout",
    "sg:orig_category":"Marktonderzoekbureaus",
    "sg:phone":"+31 499 425 625",
    "sg:postcode":"5738 BL",
    "sg:province":"Noord-Brabant",
    "wof:name":"Ahout Business Services",
    "wof:placetype":"venue"
},
  "geometry": {"coordinates":[5.572786,51.542847],"type":"Point"}
}