{
  "type": "Feature",
  "properties": {
    "addr:full":"Berlageweg 80 Groningen Groningen 9731 LK",
    "addr:housenumber":"80",
    "addr:postcode":"9731 lk",
    "addr:street":"Berlageweg",
    "iso:country":"NL",
    "sg:address":"Berlageweg 80",
    "sg:city":"Groningen",
    "sg:orig_category":"Kinderopvang Behalve Thuis",
    "sg:phone":"+31 50 542 3182",
    "sg:postcode":"9731 LK",
    "sg:province":"Groningen",
    "wof:name":"Kinderdagverblijf Dikkertje Dap",
    "wof:placetype":"venue"
},
  "geometry": {"coordinates":[6.577434,53.241871],"type":"Point"}
}