{
  "type": "Feature",
  "properties": {
    "iso:country":"NL",
    "sg:address":"Stuurboord 18",
    "sg:city":"Rozenburg Zh",
    "sg:orig_category":"Diverse Consumentenartikelen Gh",
    "sg:phone":"+31 181 219 383",
    "sg:postcode":"3181 NM",
    "sg:province":"Zuid-Holland",
    "wof:name":"M.C. International Marketing",
    "wof:placetype":"venue"
},
  "geometry": {"coordinates":[4.241514,51.909184],"type":"Point"}
}