{
  "type": "Feature",
  "properties": {
    "addr:full":"Aristotelesln 33 Huizen Noord-Holland 1277 AN",
    "addr:housenumber":"33",
    "addr:postcode":"1277 an",
    "addr:street":"Aristotelesln",
    "iso:country":"NL",
    "sg:address":"Aristotelesln 33",
    "sg:city":"Huizen",
    "sg:orig_category":"Accountants - Administratie- Consulenten En -Kantoren",
    "sg:phone":"+31 35 691 0362",
    "sg:postcode":"1277 AN",
    "sg:province":"Noord-Holland",
    "wof:name":"Nijhof",
    "wof:placetype":"venue"
},
  "geometry": {"coordinates":[5.274717,52.29464],"type":"Point"}
}