{
  "type": "Feature",
  "properties": {
    "addr:full":"O L Vrouwestr 6 Bentelo Overijssel 7497 MA",
    "addr:housenumber":"6",
    "addr:postcode":"7497 ma",
    "addr:street":"O;Vrouwestr",
    "iso:country":"NL",
    "sg:address":"O L Vrouwestr 6",
    "sg:city":"Bentelo",
    "sg:orig_category":"Scholen Voor Basisonderwijs",
    "sg:phone":"+31 547 292 492",
    "sg:postcode":"7497 MA",
    "sg:province":"Overijssel",
    "wof:name":"Onze Lieve Vrouwe",
    "wof:placetype":"venue"
},
  "geometry": {"coordinates":[6.683495,52.225876],"type":"Point"}
}