{
  "type": "Feature",
  "properties": {
    "addr:full":"Oosterstr 12 Warffum Groningen 9989 AD",
    "addr:housenumber":"12",
    "addr:postcode":"9989 ad",
    "addr:street":"Oosterstr",
    "iso:country":"NL",
    "sg:address":"Oosterstr 12",
    "sg:city":"Warffum",
    "sg:orig_category":"Adviesbureaus Bedrijfsorganisatie",
    "sg:phone":"+31 595 422 250",
    "sg:postcode":"9989 AD",
    "sg:province":"Groningen",
    "sg:website":"http://www.gdp-consult.nl",
    "wof:name":"Gdp Consult",
    "wof:placetype":"venue"
},
  "geometry": {"coordinates":[6.56335,53.392284],"type":"Point"}
}