{
  "type": "Feature",
  "properties": {
    "iso:country":"NL",
    "sg:address":"Krugerstr 167",
    "sg:city":"Vaassen",
    "sg:orig_category":"Onderhoudswerken",
    "sg:phone":"+31 578 570 067",
    "sg:postcode":"8172 BJ",
    "sg:province":"Gelderland",
    "wof:name":"Vos",
    "wof:placetype":"venue"
},
  "geometry": {"coordinates":[5.95242,52.283127],"type":"Point"}
}