{
  "type": "Feature",
  "properties": {
    "addr:full":"Kraaiennest 28 Amsterdam Zuidoost Noord-Holland 1104 CB",
    "addr:housenumber":"28",
    "addr:postcode":"zuidoost;1104 cb",
    "addr:street":"Kraaiennest",
    "iso:country":"NL",
    "sg:address":"Kraaiennest 28",
    "sg:city":"Amsterdam Zuidoost",
    "sg:orig_category":"Hout Gh",
    "sg:phone":"+31 20 690 0779",
    "sg:postcode":"1104 CB",
    "sg:province":"Noord-Holland",
    "wof:name":"Hubo",
    "wof:placetype":"venue"
},
  "geometry": {"coordinates":[4.980701,52.317112],"type":"Point"}
}