{
  "type": "Feature",
  "properties": {
    "addr:full":"Kuipersdk 412 Enschede NL.08 7541 WK",
    "addr:housenumber":"412",
    "addr:postcode":"7541",
    "addr:street":"Wk",
    "iso:country":"NL",
    "sg:address":"Kuipersdk 412",
    "sg:city":"Enschede",
    "sg:orig_category":"Makelaars En Adviseurs Onroerende Goederen",
    "sg:phone":"+31 53 431 4747",
    "sg:postcode":"7541 WK",
    "sg:province":"NL.08",
    "wof:name":"Klinker",
    "wof:placetype":"venue"
},
  "geometry": {"coordinates":[6.89463,52.204105],"type":"Point"}
}