{
  "type": "Feature",
  "properties": {
    "addr:full":"Nw Veldenwg 7 Veghel Noord-Brabant 5464 RC",
    "addr:housenumber":"7",
    "addr:postcode":"5464 rc",
    "addr:street":"Veldenwg",
    "iso:country":"NL",
    "sg:address":"Nw Veldenwg 7",
    "sg:city":"Veghel",
    "sg:orig_category":"Betonboringen",
    "sg:phone":"+31 413 317 597",
    "sg:postcode":"5464 RC",
    "sg:province":"Noord-Brabant",
    "wof:name":"Techteam Bv",
    "wof:placetype":"venue"
},
  "geometry": {"coordinates":[5.583385,51.640862],"type":"Point"}
}