{
  "type": "Feature",
  "properties": {
    "addr:full":"Nyverheidsstr 6 Emmen Drenthe 7815 HV",
    "addr:housenumber":"6",
    "addr:postcode":"7815 hv",
    "addr:street":"Nyverheidsstr",
    "iso:country":"NL",
    "sg:address":"Nyverheidsstr 6",
    "sg:city":"Emmen",
    "sg:orig_category":"Schilders",
    "sg:phone":"+31 591 640 080",
    "sg:postcode":"7815 HV",
    "sg:province":"Drenthe",
    "wof:name":"Schilderswacht Bv",
    "wof:placetype":"venue"
},
  "geometry": {"coordinates":[6.899151,52.797745],"type":"Point"}
}