{
  "type": "Feature",
  "properties": {
    "addr:full":"Schaafsebosweg 12 Heijen Limburg 6598 DB",
    "addr:housenumber":"12",
    "addr:postcode":"6598 db",
    "addr:street":"Schaafsebosweg",
    "iso:country":"NL",
    "sg:address":"Schaafsebosweg 12",
    "sg:city":"Heijen",
    "sg:orig_category":"Goederenvervoer Over De Weg",
    "sg:phone":"+31 485 532 466",
    "sg:postcode":"6598 DB",
    "sg:province":"Limburg",
    "wof:name":"A. Koster Transport",
    "wof:placetype":"venue"
},
  "geometry": {"coordinates":[5.998702,51.657803],"type":"Point"}
}