{
  "type": "Feature",
  "properties": {
    "addr:full":"Dr Colynstr 19 Veenendaal Utrecht 3904 EM",
    "addr:housenumber":"19",
    "addr:postcode":"3904 em",
    "iso:country":"NL",
    "sg:address":"Dr Colynstr 19",
    "sg:city":"Veenendaal",
    "sg:orig_category":"Vertalers",
    "sg:phone":"+31 318 528 168",
    "sg:postcode":"3904 EM",
    "sg:province":"Utrecht",
    "sg:website":"http://www.lexitext.nl",
    "wof:name":"Lexitext",
    "wof:placetype":"venue"
},
  "geometry": {"coordinates":[5.541298,52.019005],"type":"Point"}
}