{
  "type": "Feature",
  "properties": {
    "addr:full":"Postbus 1019 Houten Noord-Holland 3990 CA",
    "addr:housenumber":"1019",
    "addr:postcode":"3990 ca",
    "addr:street":"Postbus",
    "iso:country":"NL",
    "sg:address":"Postbus 1019",
    "sg:city":"Houten",
    "sg:orig_category":"Bijouterie?n - Fabrieken En Groothandel",
    "sg:phone":"+31 30 294 6602",
    "sg:postcode":"3990 CA",
    "sg:province":"Noord-Holland",
    "wof:name":"Versteegh Utrecht Bv",
    "wof:placetype":"venue"
},
  "geometry": {"coordinates":[5.169435,52.036541],"type":"Point"}
}