{
  "type": "Feature",
  "properties": {
    "addr:full":"Drentestr 8 Enschede Overijssel 7543 DS",
    "addr:housenumber":"8",
    "addr:postcode":"7543 ds",
    "addr:street":"Drentestr",
    "iso:country":"NL",
    "sg:address":"Drentestr 8",
    "sg:city":"Enschede",
    "sg:classifiers":[
        {
            "category":"Personal",
            "subcategory":"Nail Salon",
            "type":"Services"
        }
    ],
    "sg:phone":"+31 53 477 1139",
    "sg:postcode":"7543 DS",
    "sg:province":"Overijssel",
    "sg:tags":[
        "pedicure"
    ],
    "wof:name":"Elegance Salon",
    "wof:placetype":"venue"
},
  "geometry": {"coordinates":[6.878975,52.20739],"type":"Point"}
}