{
  "type": "Feature",
  "properties": {
    "iso:country":"NL",
    "sg:address":"Postbus 29112",
    "sg:city":"Rotterdam",
    "sg:orig_category":"Zonne-Energie",
    "sg:phone":"+31 10 240 0233",
    "sg:postcode":"3001 GC",
    "sg:province":"South Holland",
    "sg:website":"http://www.ekomation.nl",
    "wof:name":"Ekomation",
    "wof:placetype":"venue"
},
  "geometry": {"coordinates":[4.47075,51.922619],"type":"Point"}
}