{
  "type": "Feature",
  "properties": {
    "addr:full":"Willem Alexanderstraat 17 Asten North Brabant 5721 LX",
    "addr:housenumber":"17",
    "addr:postcode":"5721 lx",
    "addr:street":"Willem Alexanderstraat",
    "iso:country":"NL",
    "sg:address":"Willem Alexanderstraat 17",
    "sg:city":"Asten",
    "sg:orig_category":"Verzekeringen",
    "sg:phone":"+31 493 692 013",
    "sg:postcode":"5721 LX",
    "sg:province":"North Brabant",
    "wof:name":"Asten Assurantien",
    "wof:placetype":"venue"
},
  "geometry": {"coordinates":[5.737692,51.399906],"type":"Point"}
}