{
  "type": "Feature",
  "properties": {
    "iso:country":"NL",
    "sg:address":"Hilversumstr 324",
    "sg:city":"Amsterdam",
    "sg:orig_category":"Accountants - Administratie- Consulenten En -Kantoren",
    "sg:phone":"+31 20 635 2035",
    "sg:postcode":"1024 MB",
    "sg:province":"North Holland",
    "wof:name":"Brouwer & Oudhof",
    "wof:placetype":"venue"
},
  "geometry": {"coordinates":[4.96295,52.390938],"type":"Point"}
}