{
  "type": "Feature",
  "properties": {
    "addr:full":"Platte Ven 12 Noord-Scharwoude North Holland 1723 AB",
    "addr:housenumber":"12",
    "addr:postcode":"1723 ab",
    "addr:street":"Platte Ven",
    "iso:country":"NL",
    "sg:address":"Platte Ven 12",
    "sg:city":"Noord-Scharwoude",
    "sg:classifiers":[
        {
            "category":"Education",
            "subcategory":"Preschool",
            "type":"Public Place"
        }
    ],
    "sg:phone":"+31 226 341 763",
    "sg:postcode":"1723 AB",
    "sg:province":"North Holland",
    "sg:tags":[
        "kleuteronderwijs",
        "basis-"
    ],
    "wof:name":"Christelijke Basisschool De Rank",
    "wof:placetype":"venue"
},
  "geometry": {"coordinates":[4.808736,52.699524],"type":"Point"}
}