{
  "type": "Feature",
  "properties": {
    "iso:country":"NL",
    "sg:address":"Tramstr 18",
    "sg:city":"Groenlo",
    "sg:orig_category":"Schilders",
    "sg:phone":"+31 544 462 999",
    "sg:postcode":"7141 EG",
    "sg:province":"Gelderland",
    "wof:name":"Boome Bv, Te",
    "wof:placetype":"venue"
},
  "geometry": {"coordinates":[6.611413,52.040005],"type":"Point"}
}