{
  "type": "Feature",
  "properties": {
    "addr:full":"Vestestr 18 Leiden Zuid-Holland 2312 SX",
    "addr:housenumber":"18",
    "addr:postcode":"2312 sx",
    "addr:street":"Vestestr",
    "iso:country":"NL",
    "sg:address":"Vestestr 18",
    "sg:city":"Leiden",
    "sg:orig_category":"Cd'S, Grammofoonpl. En Muziekcass.-Maatschapp. En Grooth",
    "sg:phone":"+31 71 512 3599",
    "sg:postcode":"2312 SX",
    "sg:province":"Zuid-Holland",
    "sg:website":"http://www.wolffman.nl",
    "wof:name":"Wolffman",
    "wof:placetype":"venue"
},
  "geometry": {"coordinates":[4.498289,52.156929],"type":"Point"}
}