{
  "type": "Feature",
  "properties": {
    "addr:full":"Bogerdstr 19A Uden Noord-Brabant 5401 ZG",
    "addr:housenumber":"19a",
    "addr:postcode":"5401 zg",
    "addr:street":"Bogerdstr",
    "iso:country":"NL",
    "sg:address":"Bogerdstr 19A",
    "sg:city":"Uden",
    "sg:orig_category":"Verenigingsgebouwen",
    "sg:phone":"+31 413 267 467",
    "sg:postcode":"5401 ZG",
    "sg:province":"Noord-Brabant",
    "wof:name":"Pit, De",
    "wof:placetype":"venue"
},
  "geometry": {"coordinates":[8.54799,47.164558],"type":"Point"}
}