{
  "type": "Feature",
  "properties": {
    "iso:country":"NL",
    "sg:address":"Abersonpln 2",
    "sg:city":"Warnsveld",
    "sg:orig_category":"Adviesbureaus Bedrijfsorganisatie",
    "sg:phone":"+31 575 526 674",
    "sg:postcode":"7231 CP",
    "sg:province":"Gelderland",
    "wof:name":"Atl",
    "wof:placetype":"venue"
},
  "geometry": {"coordinates":[6.230921,52.140888],"type":"Point"}
}