{
  "type": "Feature",
  "properties": {
    "addr:full":"Stationsweg 134 Wezep Gelderland 8091 AG",
    "addr:housenumber":"134",
    "addr:postcode":"8091",
    "addr:street":"Stationsweg",
    "iso:country":"NL",
    "sg:address":"Stationsweg 134",
    "sg:city":"Wezep",
    "sg:classifiers":[
        {
            "category":"Fast Food",
            "type":"Food & Drink"
        }
    ],
    "sg:phone":"+31 38 376 1564",
    "sg:postcode":"8091 AG",
    "sg:province":"Gelderland",
    "sg:tags":[
        "afhaal",
        "restaurant"
    ],
    "wof:name":"Cafetaria Huisman",
    "wof:placetype":"venue"
},
  "geometry": {"coordinates":[6.00375,52.45295],"type":"Point"}
}