{
  "type": "Feature",
  "properties": {
    "addr:full":"W Pyrmontln 22 Baarn Utrecht 3743 DE",
    "addr:housenumber":"22",
    "addr:postcode":"3743 de",
    "addr:street":"W",
    "iso:country":"NL",
    "sg:address":"W Pyrmontln 22",
    "sg:city":"Baarn",
    "sg:orig_category":"Architecten En Architectenbureaus",
    "sg:phone":"+31 35 542 2026",
    "sg:postcode":"3743 DE",
    "sg:province":"Utrecht",
    "wof:name":"Wentink Baarn Bv",
    "wof:placetype":"venue"
},
  "geometry": {"coordinates":[5.270143,52.21357],"type":"Point"}
}