{
  "type": "Feature",
  "properties": {
    "iso:country":"NL",
    "sg:address":"Groenhovenweg 211",
    "sg:city":"Gouda",
    "sg:orig_category":"Vertaalbureaus",
    "sg:phone":"+31 182 572 674",
    "sg:postcode":"2803 DE",
    "sg:province":"Zuid-Holland",
    "wof:name":"Lomas Ned Bv",
    "wof:placetype":"venue"
},
  "geometry": {"coordinates":[4.689898,52.025501],"type":"Point"}
}