{
  "type": "Feature",
  "properties": {
    "iso:country":"NL",
    "sg:address":"Van Duivenvoordestraat 23",
    "sg:city":"Heerhugowaard",
    "sg:orig_category":"Boekhouders",
    "sg:phone":"+31 72 571 4206",
    "sg:postcode":"1701 CA",
    "sg:province":"Noord-Holland",
    "wof:name":"Boekhoudburo J.L. Bos",
    "wof:placetype":"venue"
},
  "geometry": {"coordinates":[4.843143,52.672199],"type":"Point"}
}