{
  "type": "Feature",
  "properties": {
    "addr:full":"Kaweide 10 Milheeze Noord-Brabant 5763 PX",
    "addr:housenumber":"10",
    "addr:postcode":"5763 px",
    "addr:street":"Kaweide",
    "iso:country":"NL",
    "sg:address":"Kaweide 10",
    "sg:city":"Milheeze",
    "sg:orig_category":"Loonbedrijven",
    "sg:phone":"+31 492 342 462",
    "sg:postcode":"5763 PX",
    "sg:province":"Noord-Brabant",
    "wof:name":"Nooijen, J M J M",
    "wof:placetype":"venue"
},
  "geometry": {"coordinates":[5.76877,51.49836],"type":"Point"}
}