{
  "type": "Feature",
  "properties": {
    "addr:full":"Cor Gordijnsingel 3 Leiderdorp Zuid-Holland 2353 GB",
    "addr:housenumber":"3",
    "addr:postcode":"2353 gb",
    "addr:street":"Gordijnsingel",
    "iso:country":"NL",
    "sg:address":"Cor Gordijnsingel 3",
    "sg:city":"Leiderdorp",
    "sg:orig_category":"Bibliotheken And Openbare Archieven",
    "sg:phone":"+31 71 589 0849",
    "sg:postcode":"2353 GB",
    "sg:province":"Zuid-Holland",
    "wof:name":"Openbare Bibliotheek",
    "wof:placetype":"venue"
},
  "geometry": {"coordinates":[4.528994,52.16452],"type":"Point"}
}