{
  "type": "Feature",
  "properties": {
    "addr:full":"Kruisstraat 7 Genemuiden NL.08 8281 BA",
    "addr:housenumber":"7;nl.08",
    "addr:postcode":"8281 ba",
    "addr:street":"Kruisstraat",
    "iso:country":"NL",
    "sg:address":"Kruisstraat 7",
    "sg:city":"Genemuiden",
    "sg:orig_category":"Verzekeringen",
    "sg:phone":"+31 38 385 6868",
    "sg:postcode":"8281 BA",
    "sg:province":"NL.08",
    "wof:name":"Van Keulen Assurantien",
    "wof:placetype":"venue"
},
  "geometry": {"coordinates":[6.039729,52.623772],"type":"Point"}
}