{
  "type": "Feature",
  "properties": {
    "iso:country":"NL",
    "sg:address":"Kruisstraat 7",
    "sg:city":"Genemuiden",
    "sg:orig_category":"Verzekeringen",
    "sg:phone":"+31 38 385 6868",
    "sg:postcode":"8281 BA",
    "sg:province":"NL.08",
    "wof:name":"Van Keulen Assurantien",
    "wof:placetype":"venue"
},
  "geometry": {"coordinates":[6.039729,52.623772],"type":"Point"}
}