{
  "type": "Feature",
  "properties": {
    "addr:full":"Nw Tielsewg 8 Tiel Gelderland 4001 JW",
    "addr:housenumber":"8",
    "addr:postcode":"4001 jw",
    "addr:street":"Tielsewg;Gelderland",
    "iso:country":"NL",
    "sg:address":"Nw Tielsewg 8",
    "sg:city":"Tiel",
    "sg:orig_category":"Orthopedisch Schoeisel",
    "sg:phone":"+31 344 624 435",
    "sg:postcode":"4001 JW",
    "sg:province":"Gelderland",
    "wof:name":"Penders Bv",
    "wof:placetype":"venue"
},
  "geometry": {"coordinates":[5.4306960106,51.8880958557],"type":"Point"}
}