{
  "type": "Feature",
  "properties": {
    "addr:full":"George Westinghousestr 2 Amsterdam Noord-Holland 1097 BA",
    "addr:housenumber":"2",
    "addr:postcode":"1097 ba",
    "iso:country":"NL",
    "sg:address":"George Westinghousestr 2",
    "sg:city":"Amsterdam",
    "sg:orig_category":"Bedrijfs- And Managementsconsultants",
    "sg:phone":"+31 20 665 6262",
    "sg:postcode":"1097 BA",
    "sg:province":"Noord-Holland",
    "wof:name":"Monza Advertising Bv",
    "wof:placetype":"venue"
},
  "geometry": {"coordinates":[4.920901,52.350365],"type":"Point"}
}