{
  "type": "Feature",
  "properties": {
    "iso:country":"NL",
    "sg:address":"Polslandstraat 82",
    "sg:city":"Rotterdam",
    "sg:orig_category":"Verzekeringen",
    "sg:phone":"+31 10 423 2254",
    "sg:postcode":"3081 TR",
    "sg:province":"South Holland",
    "wof:name":"Assurantiekantoor P.A. Piepers",
    "wof:placetype":"venue"
},
  "geometry": {"coordinates":[4.487014,51.892681],"type":"Point"}
}