{
  "type": "Feature",
  "properties": {
    "iso:country":"NL",
    "sg:address":"Noordeindsewg 380E",
    "sg:city":"Berkel En Rodenrys",
    "sg:orig_category":"Autoschade- Herstelbedrijven",
    "sg:phone":"+31 10 511 5037",
    "sg:postcode":"2651 LN",
    "sg:province":"Zuid-Holland",
    "wof:name":"Laurens",
    "wof:placetype":"venue"
},
  "geometry": {"coordinates":[4.482039,52.024315],"type":"Point"}
}