{
  "type": "Feature",
  "properties": {
    "iso:country":"NL",
    "sg:address":"Akerstr 35A",
    "sg:city":"Heerlen",
    "sg:orig_category":"Drukkerijen",
    "sg:phone":"+31 45 571 3389",
    "sg:postcode":"6411 GW",
    "sg:province":"Limburg",
    "wof:name":"Leufkens",
    "wof:placetype":"venue"
},
  "geometry": {"coordinates":[5.981793,50.884995],"type":"Point"}
}