{
  "type": "Feature",
  "properties": {
    "addr:full":"Marne 29 Amstelveen Noord-Holland 1186 PB",
    "addr:housenumber":"29",
    "addr:postcode":"1186 pb",
    "addr:street":"Marne",
    "iso:country":"NL",
    "sg:address":"Marne 29",
    "sg:city":"Amstelveen",
    "sg:orig_category":"Vertalers",
    "sg:phone":"+31 20 615 6625",
    "sg:postcode":"1186 PB",
    "sg:province":"Noord-Holland",
    "wof:name":"Glan, Von",
    "wof:placetype":"venue"
},
  "geometry": {"coordinates":[4.862332,52.2859],"type":"Point"}
}