{
  "type": "Feature",
  "properties": {
    "addr:full":"Kruiswg 616 Hoofddorp North Holland 2132 CH",
    "addr:housenumber":"616",
    "addr:postcode":"2132",
    "iso:country":"NL",
    "sg:address":"Kruiswg 616",
    "sg:city":"Hoofddorp",
    "sg:orig_category":"Verzekeringen - Verzekeringskantoren",
    "sg:phone":"+31 23 561 1017",
    "sg:postcode":"2132 CH",
    "sg:province":"North Holland",
    "sg:website":"http://www.verkuylverzekeringen.nl",
    "wof:name":"Verkuyl Bv",
    "wof:placetype":"venue"
},
  "geometry": {"coordinates":[4.699577,52.301685],"type":"Point"}
}