{
  "type": "Feature",
  "properties": {
    "addr:full":"M Marisstr 49 Dordrecht South Holland 3314 TM",
    "addr:housenumber":"49",
    "addr:postcode":"3314 tm",
    "iso:country":"NL",
    "sg:address":"M Marisstr 49",
    "sg:city":"Dordrecht",
    "sg:orig_category":"Glazenwasserijen",
    "sg:phone":"+31 78 631 3071",
    "sg:postcode":"3314 TM",
    "sg:province":"South Holland",
    "wof:name":"Zillig, R J",
    "wof:placetype":"venue"
},
  "geometry": {"coordinates":[4.658316,51.799091],"type":"Point"}
}