{
  "type": "Feature",
  "properties": {
    "addr:full":"Rivierdk 707 Sliedrecht Zuid-Holland 3361 BT",
    "addr:housenumber":"707",
    "addr:postcode":"3361 bt",
    "iso:country":"NL",
    "sg:address":"Rivierdk 707",
    "sg:city":"Sliedrecht",
    "sg:orig_category":"Babyartikelen",
    "sg:phone":"+31 184 418 802",
    "sg:postcode":"3361 BT",
    "sg:province":"Zuid-Holland",
    "wof:name":"Hartewens",
    "wof:placetype":"venue"
},
  "geometry": {"coordinates":[4.78075,51.817097],"type":"Point"}
}