{
  "type": "Feature",
  "properties": {
    "addr:full":"V Naeltwyckstr 203 Voorburg South Holland 2274 PA",
    "addr:housenumber":"203",
    "addr:postcode":"2274 pa",
    "iso:country":"NL",
    "sg:address":"V Naeltwyckstr 203",
    "sg:city":"Voorburg",
    "sg:orig_category":"Webdesign Bureaus",
    "sg:phone":"+31 6 24217184",
    "sg:postcode":"2274 PA",
    "sg:province":"South Holland",
    "sg:website":"http://www.studio203.nl",
    "wof:name":"Studio 203",
    "wof:placetype":"venue"
},
  "geometry": {"coordinates":[4.3495202065,52.0737915039],"type":"Point"}
}