{
  "type": "Feature",
  "properties": {
    "addr:full":"Pr Mauritsstr 37 Delft Zuid-Holland 2628 SR",
    "addr:housenumber":"37",
    "addr:postcode":"2628 sr",
    "addr:street":"Delft",
    "iso:country":"NL",
    "sg:address":"Pr Mauritsstr 37",
    "sg:city":"Delft",
    "sg:orig_category":"Peuterspeelzalen",
    "sg:phone":"+31 15 262 8060",
    "sg:postcode":"2628 SR",
    "sg:province":"Zuid-Holland",
    "wof:name":"Muizenhuis, Het",
    "wof:placetype":"venue"
},
  "geometry": {"coordinates":[4.373764,52.007736],"type":"Point"}
}