{
  "type": "Feature",
  "properties": {
    "addr:full":"Heideveldwg 42 Heerlen Limburg 6414 XL",
    "addr:housenumber":"42",
    "addr:postcode":"6414 xl",
    "addr:street":"Heideveldwg",
    "iso:country":"NL",
    "sg:address":"Heideveldwg 42",
    "sg:city":"Heerlen",
    "sg:orig_category":"Adviesbureaus Bouwkunde",
    "sg:phone":"+31 45 563 0248",
    "sg:postcode":"6414 XL",
    "sg:province":"Limburg",
    "wof:name":"Cordewener, Adviesbureau L C H",
    "wof:placetype":"venue"
},
  "geometry": {"coordinates":[5.977431,50.913338],"type":"Point"}
}