{
  "type": "Feature",
  "properties": {
    "iso:country":"NL",
    "sg:address":"V Schaffelaarstr 26",
    "sg:city":"Barneveld",
    "sg:orig_category":"Opticiens",
    "sg:phone":"+31 342 414 560",
    "sg:postcode":"3771 BT",
    "sg:province":"Gelderland",
    "wof:name":"Baas",
    "wof:placetype":"venue"
},
  "geometry": {"coordinates":[5.5888428688,52.1412162781],"type":"Point"}
}