{
  "type": "Feature",
  "properties": {
    "iso:country":"NL",
    "sg:address":"Mynsherenln 110D",
    "sg:city":"Rotterdam",
    "sg:orig_category":"Glazenwasserijen",
    "sg:phone":"+31 10 484 7481",
    "sg:postcode":"3081 CH",
    "sg:province":"Zuid-Holland",
    "wof:name":"Westenbrugge, Fred Van",
    "wof:placetype":"venue"
},
  "geometry": {"coordinates":[4.490636,51.89283],"type":"Point"}
}