{
  "type": "Feature",
  "properties": {
    "iso:country":"NL",
    "sg:address":"K Nobelstr 19",
    "sg:city":"Zierikzee",
    "sg:orig_category":"Schilders",
    "sg:phone":"+31 111 415 356",
    "sg:postcode":"4301 HM",
    "sg:province":"Zeeland",
    "wof:name":"Graaf-Stoutjesdijk, De",
    "wof:placetype":"venue"
},
  "geometry": {"coordinates":[3.919557,51.65316],"type":"Point"}
}