{
  "type": "Feature",
  "properties": {
    "addr:full":"Hagelkruisweg 11 Sint Odilienberg Limburg 6077 HA",
    "addr:housenumber":"11",
    "addr:postcode":"6077 ha",
    "addr:street":"Hagelkruisweg;Limburg",
    "iso:country":"NL",
    "sg:address":"Hagelkruisweg 11",
    "sg:city":"Sint Odilienberg",
    "sg:orig_category":"Paramedische Behandelingen",
    "sg:phone":"+31 475 532 797",
    "sg:postcode":"6077 HA",
    "sg:province":"Limburg",
    "wof:name":"M.F.A. Cuijpers-Sanders",
    "wof:placetype":"venue"
},
  "geometry": {"coordinates":[5.996587,51.14402],"type":"Point"}
}