{
  "type": "Feature",
  "properties": {
    "addr:full":"Mariendonkstr 37 Elshout North Brabant 5154 EG",
    "addr:housenumber":"37",
    "addr:postcode":"5154 eg",
    "addr:street":"Mariendonkstr",
    "iso:country":"NL",
    "sg:address":"Mariendonkstr 37",
    "sg:city":"Elshout",
    "sg:orig_category":"Autoschade- Herstelbedrijven",
    "sg:phone":"+31 416 320 602",
    "sg:postcode":"5154 EG",
    "sg:province":"North Brabant",
    "wof:name":"Knippels",
    "wof:placetype":"venue"
},
  "geometry": {"coordinates":[5.152522,51.704906],"type":"Point"}
}