{
  "type": "Feature",
  "properties": {
    "addr:full":"Koningsbergerstraat 9 Utrecht Utrecht 3531 AJ",
    "addr:housenumber":"9",
    "addr:postcode":"3531 aj",
    "addr:street":"Koningsbergerstraat",
    "iso:country":"NL",
    "sg:address":"Koningsbergerstraat 9",
    "sg:city":"Utrecht",
    "sg:orig_category":"Hoger Onderwijs",
    "sg:phone":"+31 30 292 7777",
    "sg:postcode":"3531 AJ",
    "sg:province":"Utrecht",
    "wof:name":"Hogeschool Domstad Kath. Lerarenopl. Basisonderw.",
    "wof:placetype":"venue"
},
  "geometry": {"coordinates":[5.099123,52.08757],"type":"Point"}
}