{
  "type": "Feature",
  "properties": {
    "addr:full":"Dennenln 5 Leimuiden South Holland 2451 XK",
    "addr:housenumber":"5",
    "addr:postcode":"2451 xk",
    "addr:street":"Dennenln",
    "iso:country":"NL",
    "sg:address":"Dennenln 5",
    "sg:city":"Leimuiden",
    "sg:orig_category":"Orgelbouw",
    "sg:phone":"+31 172 507 516",
    "sg:postcode":"2451 XK",
    "sg:province":"South Holland",
    "wof:name":"Kath Klokken En Orgel-Adviesraad",
    "wof:placetype":"venue"
},
  "geometry": {"coordinates":[4.6635551453,52.2235641479],"type":"Point"}
}