{
  "type": "Feature",
  "properties": {
    "iso:country":"NL",
    "sg:address":"Jannewekken 11",
    "sg:city":"Zierikzee",
    "sg:orig_category":"Drukkerijen",
    "sg:phone":"+31 111 453 535",
    "sg:postcode":"4301 HH",
    "sg:province":"Zeeland",
    "sg:website":"http://www.lno.nl",
    "wof:name":"Lno",
    "wof:placetype":"venue"
},
  "geometry": {"coordinates":[3.9213,51.652454],"type":"Point"}
}