{
  "type": "Feature",
  "properties": {
    "iso:country":"NL",
    "sg:address":"Damstr 40Bis",
    "sg:city":"Utrecht",
    "sg:orig_category":"Webdesign Bureaus",
    "sg:phone":"+31 30 296 7800",
    "sg:postcode":"3531 BW",
    "sg:province":"Utrecht",
    "sg:website":"http://www.arabizz.com",
    "wof:name":"Arabizz",
    "wof:placetype":"venue"
},
  "geometry": {"coordinates":[5.103374958,52.0917549133],"type":"Point"}
}