{
  "type": "Feature",
  "properties": {
    "addr:full":"Keizerstr 21 Heerlen Limburg 6411 XJ",
    "addr:housenumber":"21",
    "addr:postcode":"6411 xj",
    "addr:street":"Keizerstr",
    "iso:country":"NL",
    "sg:address":"Keizerstr 21",
    "sg:city":"Heerlen",
    "sg:orig_category":"Beeldende Kunstenaars",
    "sg:phone":"+31 45 571 4546",
    "sg:postcode":"6411 XJ",
    "sg:province":"Limburg",
    "wof:name":"Bour, Hubert",
    "wof:placetype":"venue"
},
  "geometry": {"coordinates":[5.963017,50.891418],"type":"Point"}
}