{
  "type": "Feature",
  "properties": {
    "addr:full":"Lijnbaan 77 Rotterdam South Holland 3012 EM",
    "addr:housenumber":"77",
    "addr:postcode":"3012 em",
    "addr:street":"Lijnbaan",
    "iso:country":"NL",
    "sg:address":"Lijnbaan 77",
    "sg:city":"Rotterdam",
    "sg:orig_category":"Juweliers",
    "sg:phone":"+31 10 411 9445",
    "sg:postcode":"3012 EM",
    "sg:province":"South Holland",
    "wof:name":"Schaap En Citroen",
    "wof:placetype":"venue"
},
  "geometry": {"coordinates":[4.476786,51.920601],"type":"Point"}
}