{
  "type": "Feature",
  "properties": {
    "addr:full":"Vivaldiplnts 100 Utrecht Utrecht 3533 JE",
    "addr:housenumber":"100",
    "addr:postcode":"3533 je",
    "iso:country":"NL",
    "sg:address":"Vivaldiplnts 100",
    "sg:city":"Utrecht",
    "sg:orig_category":"Adviesbureaus Bedrijfsorganisatie",
    "sg:phone":"+31 30 298 4300",
    "sg:postcode":"3533 JE",
    "sg:province":"Utrecht",
    "wof:name":"Ormit Bv",
    "wof:placetype":"venue"
},
  "geometry": {"coordinates":[5.0874,52.088428],"type":"Point"}
}