{
  "type": "Feature",
  "properties": {
    "addr:full":"W Dykstrastr 6 Holwerd Friesland 9151 JK",
    "addr:housenumber":"6",
    "addr:postcode":"9151 jk",
    "addr:street":"W",
    "iso:country":"NL",
    "sg:address":"W Dykstrastr 6",
    "sg:city":"Holwerd",
    "sg:orig_category":"Woninginrichting",
    "sg:phone":"+31 519 561 254",
    "sg:postcode":"9151 JK",
    "sg:province":"Friesland",
    "wof:name":"Bron, Woonservice Winkel",
    "wof:placetype":"venue"
},
  "geometry": {"coordinates":[5.9002709389,53.3687324524],"type":"Point"}
}