{
  "type": "Feature",
  "properties": {
    "iso:country":"NL",
    "sg:address":"Duinkerkenstr 56",
    "sg:city":"Groningen",
    "sg:orig_category":"Machinefabrieken",
    "sg:phone":"+31 50 312 4475",
    "sg:postcode":"9723 BT",
    "sg:province":"Groningen",
    "wof:name":"Zantingh Bv",
    "wof:placetype":"venue"
},
  "geometry": {"coordinates":[6.607959,53.198936],"type":"Point"}
}