{
  "type": "Feature",
  "properties": {
    "addr:full":"Holterbergweide 19 Helmond Noord-Brabant 5709 MN",
    "addr:housenumber":"19",
    "addr:postcode":"5709 mn",
    "addr:street":"Holterbergweide",
    "iso:country":"NL",
    "sg:address":"Holterbergweide 19",
    "sg:city":"Helmond",
    "sg:orig_category":"Verzekeringen",
    "sg:phone":"+31 492 512 659",
    "sg:postcode":"5709 MN",
    "sg:province":"Noord-Brabant",
    "wof:name":"Vof Kusters Assurantien En Hypotheken",
    "wof:placetype":"venue"
},
  "geometry": {"coordinates":[5.687275,51.490318],"type":"Point"}
}