{
  "type": "Feature",
  "properties": {
    "addr:full":"Populierestraat 6 'S Gravenpolder Zeeland 4431 CK",
    "addr:housenumber":"6 '",
    "addr:postcode":"4431 ck",
    "addr:street":"Populierestraat",
    "iso:country":"NL",
    "sg:address":"Populierestraat 6",
    "sg:city":"'S Gravenpolder",
    "sg:orig_category":"Geluidsopnamen",
    "sg:phone":"+31 113 313 105",
    "sg:postcode":"4431 CK",
    "sg:province":"Zeeland",
    "wof:name":"B & A Sound",
    "wof:placetype":"venue"
},
  "geometry": {"coordinates":[3.903438,51.462376],"type":"Point"}
}