{
  "type": "Feature",
  "properties": {
    "addr:full":"Nachtegaallaan 9 Markelo Overijssel 7475 DE",
    "addr:housenumber":"9",
    "addr:postcode":"7475 de",
    "addr:street":"Nachtegaallaan",
    "iso:country":"NL",
    "sg:address":"Nachtegaallaan 9",
    "sg:city":"Markelo",
    "sg:orig_category":"Diverse Grafische Activiteiten",
    "sg:phone":"+31 547 362 841",
    "sg:postcode":"7475 DE",
    "sg:province":"Overijssel",
    "wof:name":"Willem Niessink Illustraties",
    "wof:placetype":"venue"
},
  "geometry": {"coordinates":[6.502008,52.234146],"type":"Point"}
}