{
  "type": "Feature",
  "properties": {
    "addr:full":"Julianastr 23 Hellevoetsluis Zuid-Holland 3223 AC",
    "addr:housenumber":"23",
    "addr:postcode":"3223 ac",
    "addr:street":"Julianastr",
    "iso:country":"NL",
    "sg:address":"Julianastr 23",
    "sg:city":"Hellevoetsluis",
    "sg:orig_category":"Werving En Selectie",
    "sg:phone":"+31 181 337 339",
    "sg:postcode":"3223 AC",
    "sg:province":"Zuid-Holland",
    "wof:name":"Boom, De",
    "wof:placetype":"venue"
},
  "geometry": {"coordinates":[4.140089035,51.8392868042],"type":"Point"}
}