{
  "type": "Feature",
  "properties": {
    "addr:full":"Osdorppln 822 Amsterdam North Holland 1068 TD",
    "addr:housenumber":"822",
    "addr:postcode":"1068 td",
    "iso:country":"NL",
    "sg:address":"Osdorppln 822",
    "sg:city":"Amsterdam",
    "sg:classifiers":[
        {
            "category":"Food & Beverages",
            "subcategory":"Bakery",
            "type":"Retail Goods"
        }
    ],
    "sg:phone":"+31 20 667 2950",
    "sg:postcode":"1068 TD",
    "sg:province":"North Holland",
    "sg:tags":[
        "pizza"
    ],
    "sg:website":"http://www.ildelfinoblu.nl",
    "wof:name":"Il Delfino Blu",
    "wof:placetype":"venue"
},
  "geometry": {"coordinates":[4.806281,52.358665],"type":"Point"}
}