{
  "type": "Feature",
  "properties": {
    "addr:full":"Walstraat 7 Terneuzen Zeeland 4531 ED",
    "addr:housenumber":"7",
    "addr:postcode":"4531 ed",
    "addr:street":"Walstraat",
    "iso:country":"NL",
    "sg:address":"Walstraat 7",
    "sg:city":"Terneuzen",
    "sg:classifiers":[
        {
            "category":"Shopping",
            "subcategory":"Gifts & Souvenirs",
            "type":"Retail Goods"
        }
    ],
    "sg:phone":"+31 115 617 416",
    "sg:postcode":"4531 ED",
    "sg:province":"Zeeland",
    "sg:tags":[
        "geschenken"
    ],
    "wof:name":"Wereldwinkel",
    "wof:placetype":"venue"
},
  "geometry": {"coordinates":[3.827745,51.338799],"type":"Point"}
}