{
  "type": "Feature",
  "properties": {
    "addr:full":"Wateringsestraat 23A 'S Gravenhage Zuid-Holland 2512 PH",
    "addr:housenumber":"23a '",
    "addr:postcode":"2512",
    "addr:street":"Wateringsestraat",
    "iso:country":"NL",
    "sg:address":"Wateringsestraat 23A",
    "sg:city":"'S Gravenhage",
    "sg:orig_category":"Kinderopvang Behalve Thuis",
    "sg:phone":"+31 70 389 6442",
    "sg:postcode":"2512 PH",
    "sg:province":"Zuid-Holland",
    "wof:name":"Alexander Kinderopvang Dak",
    "wof:placetype":"venue"
},
  "geometry": {"coordinates":[4.299098,52.071625],"type":"Point"}
}