{
  "type": "Feature",
  "properties": {
    "addr:full":"Hoogstraat 147 Rotterdam Zuid-Holland 3011 PM",
    "addr:housenumber":"147",
    "addr:postcode":"3011 pm",
    "addr:street":"Hoogstraat",
    "iso:country":"NL",
    "sg:address":"Hoogstraat 147",
    "sg:city":"Rotterdam",
    "sg:classifiers":[
        {
            "category":"Fast Food",
            "type":"Food & Drink"
        }
    ],
    "sg:phone":"+31 10 213 1826",
    "sg:postcode":"3011 PM",
    "sg:province":"Zuid-Holland",
    "sg:tags":[
        "afhaal",
        "restaurant"
    ],
    "wof:name":"Febo",
    "wof:placetype":"venue"
},
  "geometry": {"coordinates":[4.486536,51.921192],"type":"Point"}
}