{
  "type": "Feature",
  "properties": {
    "addr:full":"Spoorlaan 21-E Tilburg Noord-Brabant 5038 CB",
    "addr:housenumber":"21-e",
    "addr:postcode":"5038 cb",
    "addr:street":"Spoorlaan",
    "iso:country":"NL",
    "sg:address":"Spoorlaan 21-E",
    "sg:city":"Tilburg",
    "sg:orig_category":"Woningbouwverenigingen",
    "sg:phone":"+31 13 539 9700",
    "sg:postcode":"5038 CB",
    "sg:province":"Noord-Brabant",
    "wof:name":"Makelaardij Wonen Middenbrabant",
    "wof:placetype":"venue"
},
  "geometry": {"coordinates":[5.0775799751,51.5569114685],"type":"Point"}
}