{
  "type": "Feature",
  "properties": {
    "addr:full":"Westeinde 664 Vriezenveen NL.08 7671 CZ",
    "addr:housenumber":"664;nl.08",
    "addr:postcode":"7671",
    "addr:street":"Westeinde",
    "iso:country":"NL",
    "sg:address":"Westeinde 664",
    "sg:city":"Vriezenveen",
    "sg:orig_category":"Kappers",
    "sg:phone":"+31 546 561 684",
    "sg:postcode":"7671 CZ",
    "sg:province":"NL.08",
    "wof:name":"Kapsalon Zwak",
    "wof:placetype":"venue"
},
  "geometry": {"coordinates":[6.6013908386,52.4036178589],"type":"Point"}
}