{
  "type": "Feature",
  "properties": {
    "iso:country":"NL",
    "sg:address":"Ysselmeerdk 4",
    "sg:city":"Oosthuizen",
    "sg:orig_category":"Metaalbewerking",
    "sg:phone":"+31 299 403 894",
    "sg:postcode":"1474 MX",
    "sg:province":"Noord-Holland",
    "wof:name":"Koole, R",
    "wof:placetype":"venue"
},
  "geometry": {"coordinates":[5.025491,52.580681],"type":"Point"}
}