{
  "type": "Feature",
  "properties": {
    "addr:full":"Kerksngl 6 Ooltgensplaat South Holland 3257 AH",
    "addr:housenumber":"6",
    "addr:postcode":"3257 ah",
    "addr:street":"Kerksngl",
    "iso:country":"NL",
    "sg:address":"Kerksngl 6",
    "sg:city":"Ooltgensplaat",
    "sg:orig_category":"Woninginrichting",
    "sg:phone":"+31 187 631 437",
    "sg:postcode":"3257 AH",
    "sg:province":"South Holland",
    "wof:name":"Drongelen En Zn, Fa J Van",
    "wof:placetype":"venue"
},
  "geometry": {"coordinates":[4.3493847847,51.681678772],"type":"Point"}
}