{
  "type": "Feature",
  "properties": {
    "addr:full":"Laarpk 30 Veghel Noord-Brabant 5467 HL",
    "addr:housenumber":"30",
    "addr:postcode":"5467 hl",
    "addr:street":"Laarpk",
    "iso:country":"NL",
    "sg:address":"Laarpk 30",
    "sg:city":"Veghel",
    "sg:orig_category":"Adviesbureaus Bedrijfsorganisatie",
    "sg:phone":"+31 413 321 755",
    "sg:postcode":"5467 HL",
    "sg:province":"Noord-Brabant",
    "sg:website":"http://www.bascule-vof.nl",
    "wof:name":"Bascule",
    "wof:placetype":"venue"
},
  "geometry": {"coordinates":[5.561324,51.619499],"type":"Point"}
}