{
  "type": "Feature",
  "properties": {
    "iso:country":"NL",
    "sg:address":"Barnewinkel 708",
    "sg:city":"Apeldoorn",
    "sg:orig_category":"Ongediertebestrijding En Ontsmetting",
    "sg:phone":"+31 55 541 5156",
    "sg:postcode":"7326 KD",
    "sg:province":"Gelderland",
    "wof:name":"Pob",
    "wof:placetype":"venue"
},
  "geometry": {"coordinates":[6.01638,52.196468],"type":"Point"}
}