{
  "type": "Feature",
  "properties": {
    "iso:country":"NL",
    "sg:address":"A Jacobsln 50",
    "sg:city":"Purmerend",
    "sg:orig_category":"Verenigingen En Stichtingen",
    "sg:phone":"+31 299 420 654",
    "sg:postcode":"1442 AH",
    "sg:province":"Noord-Holland",
    "wof:name":"Katholieke Bond Van Ouderen",
    "wof:placetype":"venue"
},
  "geometry": {"coordinates":[4.94793,52.507607],"type":"Point"}
}