{
  "type": "Feature",
  "properties": {
    "iso:country":"NL",
    "sg:address":"Boezemstr 368-370",
    "sg:city":"Rotterdam",
    "sg:orig_category":"Meubelstoffering",
    "sg:phone":"+31 10 413 4090",
    "sg:postcode":"3034 EM",
    "sg:province":"South Holland",
    "sg:website":"http://www.vrooyen.nl",
    "wof:name":"Arthur Van Rooijen",
    "wof:placetype":"venue"
},
  "geometry": {"coordinates":[4.4977,51.931114],"type":"Point"}
}