{
  "type": "Feature",
  "properties": {
    "addr:full":"Sint Gerlach 46 Valkenburg Lb Limburg 6301 JD",
    "addr:housenumber":"46",
    "addr:postcode":"lb;6301 jd",
    "addr:street":"Sint Gerlach",
    "iso:country":"NL",
    "sg:address":"Sint Gerlach 46",
    "sg:city":"Valkenburg Lb",
    "sg:orig_category":"Bloemen And Planten",
    "sg:phone":"+31 43 604 0665",
    "sg:postcode":"6301 JD",
    "sg:province":"Limburg",
    "wof:name":"Geuskens En Zn Rozenkwekerij & Tuinplanten",
    "wof:placetype":"venue"
},
  "geometry": {"coordinates":[5.796394,50.872395],"type":"Point"}
}