{
  "type": "Feature",
  "properties": {
    "addr:full":"Bovenstreek 15 Groningen Groningen 9731 DH",
    "addr:housenumber":"15",
    "addr:postcode":"9731 dh",
    "addr:street":"Bovenstreek",
    "iso:country":"NL",
    "sg:address":"Bovenstreek 15",
    "sg:city":"Groningen",
    "sg:orig_category":"Koeriersdiensten",
    "sg:phone":"+31 50 312 1040",
    "sg:postcode":"9731 DH",
    "sg:province":"Groningen",
    "wof:name":"Hb",
    "wof:placetype":"venue"
},
  "geometry": {"coordinates":[6.589615,53.236847],"type":"Point"}
}