{
  "type": "Feature",
  "properties": {
    "iso:country":"NL",
    "sg:address":"Oosteinde 127",
    "sg:city":"Berkhout",
    "sg:orig_category":"Diverse Opleidingen And Onderwijs",
    "sg:phone":"+31 229 551 780",
    "sg:postcode":"1647 AH",
    "sg:province":"North Holland",
    "wof:name":"Atelier Naturel",
    "wof:placetype":"venue"
},
  "geometry": {"coordinates":[5.002791,52.640526],"type":"Point"}
}