{
  "type": "Feature",
  "properties": {
    "addr:full":"Siebengewaldseweg 2 Bergen Lb Limburg 5854 PC",
    "addr:housenumber":"2",
    "addr:postcode":"lb;5854 pc",
    "addr:street":"Siebengewaldseweg",
    "iso:country":"NL",
    "sg:address":"Siebengewaldseweg 2",
    "sg:city":"Bergen Lb",
    "sg:orig_category":"Goederenvervoer Over De Weg",
    "sg:phone":"+31 485 343 228",
    "sg:postcode":"5854 PC",
    "sg:province":"Limburg",
    "wof:name":"G. Urselmann",
    "wof:placetype":"venue"
},
  "geometry": {"coordinates":[-93.129936,36.705662],"type":"Point"}
}