{
  "type": "Feature",
  "properties": {
    "addr:full":"Ten Pol 4 Oude Meer North Holland 1438 AH",
    "addr:housenumber":"4",
    "addr:postcode":"1438 ah",
    "addr:street":"Ten Pol",
    "iso:country":"NL",
    "sg:address":"Ten Pol 4",
    "sg:city":"Oude Meer",
    "sg:orig_category":"Accountants - Administratie- Consulenten En -Kantoren",
    "sg:phone":"+31 20 657 0010",
    "sg:postcode":"1438 AH",
    "sg:province":"North Holland",
    "wof:name":"Oudejans Van Eekeres En Partners Bv",
    "wof:placetype":"venue"
},
  "geometry": {"coordinates":[4.783348,52.290848],"type":"Point"}
}