{
  "type": "Feature",
  "properties": {
    "addr:full":"Dorpsstraat 24 Nieuwveen Zuid-Holland 2441 CH",
    "addr:housenumber":"24",
    "addr:postcode":"2441",
    "addr:street":"Dorpsstraat",
    "iso:country":"NL",
    "sg:address":"Dorpsstraat 24",
    "sg:city":"Nieuwveen",
    "sg:orig_category":"Metaalwerken",
    "sg:phone":"+31 172 538 974",
    "sg:postcode":"2441 CH",
    "sg:province":"Zuid-Holland",
    "wof:name":"Fa Jac. Stouten",
    "wof:placetype":"venue"
},
  "geometry": {"coordinates":[4.757393,52.197983],"type":"Point"}
}