{
  "type": "Feature",
  "properties": {
    "addr:full":"Bezuidenhoutseweg 99 'S Gravenhage Zuid-Holland 2594 AC",
    "addr:housenumber":"99",
    "addr:postcode":"2594 ac",
    "addr:street":"Bezuidenhoutseweg;' S",
    "iso:country":"NL",
    "sg:address":"Bezuidenhoutseweg 99",
    "sg:city":"'S Gravenhage",
    "sg:orig_category":"Werving And Selectie Van Tijdelijk Personeel And Uitzendkantoren",
    "sg:phone":"+31 70 371 5120",
    "sg:postcode":"2594 AC",
    "sg:province":"Zuid-Holland",
    "wof:name":"Quirasse",
    "wof:placetype":"venue"
},
  "geometry": {"coordinates":[4.3292341232,52.0848922729],"type":"Point"}
}