{
  "type": "Feature",
  "properties": {
    "addr:full":"Dr Schaepmanstr 16 Posterholt Limburg 6061 GG",
    "addr:housenumber":"16",
    "addr:postcode":"6061 gg",
    "iso:country":"NL",
    "sg:address":"Dr Schaepmanstr 16",
    "sg:city":"Posterholt",
    "sg:orig_category":"Makelaars En Adviseurs Onroerende Goederen",
    "sg:phone":"+31 475 407 008",
    "sg:postcode":"6061 GG",
    "sg:province":"Limburg",
    "wof:name":"Grensland Inmobilien",
    "wof:placetype":"venue"
},
  "geometry": {"coordinates":[6.02042,51.127651],"type":"Point"}
}