{
  "type": "Feature",
  "properties": {
    "iso:country":"NL",
    "sg:address":"Smeepoortstraat 41",
    "sg:city":"Harderwijk",
    "sg:orig_category":"Kappers",
    "sg:phone":"+31 341 426 441",
    "sg:postcode":"3841 EH",
    "sg:province":"Gelderland",
    "wof:name":"Nicole Figaro",
    "wof:placetype":"venue"
},
  "geometry": {"coordinates":[5.615343,52.348724],"type":"Point"}
}