{
  "type": "Feature",
  "properties": {
    "addr:full":"Laandwstr 13 Baarn Utrecht 3743 BS",
    "addr:housenumber":"13",
    "addr:postcode":"3743 bs",
    "addr:street":"Laandwstr",
    "iso:country":"NL",
    "sg:address":"Laandwstr 13",
    "sg:city":"Baarn",
    "sg:orig_category":"Discotheken",
    "sg:phone":"+31 35 541 8087",
    "sg:postcode":"3743 BS",
    "sg:province":"Utrecht",
    "wof:name":"Jungle, The",
    "wof:placetype":"venue"
},
  "geometry": {"coordinates":[5.284308,52.211781],"type":"Point"}
}