{
  "type": "Feature",
  "properties": {
    "iso:country":"NL",
    "sg:address":"V Ryningenpk 7",
    "sg:city":"Woudenberg",
    "sg:orig_category":"Administratie- En Boekhoudkantoren",
    "sg:phone":"+31 33 286 0517",
    "sg:postcode":"3931 XP",
    "sg:province":"Utrecht",
    "wof:name":"Markant Administratiekantoor",
    "wof:placetype":"venue"
},
  "geometry": {"coordinates":[5.415759,52.08215],"type":"Point"}
}