{
  "type": "Feature",
  "properties": {
    "iso:country":"NL",
    "sg:address":"Kerkstr 168",
    "sg:city":"Amsterdam",
    "sg:orig_category":"Kunsthandel",
    "sg:phone":"+31 20 623 4402",
    "sg:postcode":"1017 GS",
    "sg:province":"Noord-Holland",
    "sg:website":"http://www.astamangala.com",
    "wof:name":"Astamangala",
    "wof:placetype":"venue"
},
  "geometry": {"coordinates":[4.88971,52.363117],"type":"Point"}
}