{
  "type": "Feature",
  "properties": {
    "iso:country":"NL",
    "sg:address":"Jachtwg 1",
    "sg:city":"Hengelo Gld",
    "sg:orig_category":"Video - Faciliteiten En Producties",
    "sg:phone":"+31 575 467 463",
    "sg:postcode":"7255 NS",
    "sg:province":"Gelderland",
    "wof:name":"Sports Video Prod",
    "wof:placetype":"venue"
},
  "geometry": {"coordinates":[6.376395,52.046192],"type":"Point"}
}