{
  "type": "Feature",
  "properties": {
    "addr:full":"A Dubcekstr 13 Rotterdam Zuid-Holland 3065 EJ",
    "addr:housenumber":"13",
    "addr:postcode":"3065 ej",
    "iso:country":"NL",
    "sg:address":"A Dubcekstr 13",
    "sg:city":"Rotterdam",
    "sg:orig_category":"Adviesbureaus Bedrijfsorganisatie",
    "sg:phone":"+31 10 202 2444",
    "sg:postcode":"3065 EJ",
    "sg:province":"Zuid-Holland",
    "wof:name":"Eclips Bv",
    "wof:placetype":"venue"
},
  "geometry": {"coordinates":[4.561472,51.924026],"type":"Point"}
}