{
  "type": "Feature",
  "properties": {
    "addr:full":"Vierambachtsweg 59 Woubrugge South Holland 2481 KS",
    "addr:housenumber":"59",
    "addr:postcode":"2481 ks",
    "addr:street":"Vierambachtsweg",
    "iso:country":"NL",
    "sg:address":"Vierambachtsweg 59",
    "sg:city":"Woubrugge",
    "sg:orig_category":"Pleziervaartuigen And Reparatie",
    "sg:phone":"+31 172 519 172",
    "sg:postcode":"2481 KS",
    "sg:province":"South Holland",
    "wof:name":"Hans Jansen Jachtservice",
    "wof:placetype":"venue"
},
  "geometry": {"coordinates":[4.641553,52.163933],"type":"Point"}
}