{
  "type": "Feature",
  "properties": {
    "addr:full":"Nusterwg 119 Sittard Limburg 6136 KT",
    "addr:housenumber":"119",
    "addr:postcode":"6136 kt",
    "addr:street":"Sittard Limburg",
    "iso:country":"NL",
    "sg:address":"Nusterwg 119",
    "sg:city":"Sittard",
    "sg:orig_category":"Meubelstoffering",
    "sg:phone":"+31 46 451 8461",
    "sg:postcode":"6136 KT",
    "sg:province":"Limburg",
    "wof:name":"Henk Vorstermans",
    "wof:placetype":"venue"
},
  "geometry": {"coordinates":[5.864532,51.020279],"type":"Point"}
}