{
  "type": "Feature",
  "properties": {
    "addr:full":"Hoofdweg 203 Bellingwolde Groningen 9695 AG",
    "addr:housenumber":"203",
    "addr:postcode":"9695",
    "addr:street":"Hoofdweg",
    "iso:country":"NL",
    "sg:address":"Hoofdweg 203",
    "sg:city":"Bellingwolde",
    "sg:orig_category":"Goederenvervoer Over De Weg",
    "sg:phone":"+31 597 531 500",
    "sg:postcode":"9695 AG",
    "sg:province":"Groningen",
    "wof:name":"Firma Bahlmann En Zoon",
    "wof:placetype":"venue"
},
  "geometry": {"coordinates":[7.165544,53.117756],"type":"Point"}
}