{
  "type": "Feature",
  "properties": {
    "addr:full":"Wielewaalstraat 37 Rotterdam Zuid-Holland 3083 KW",
    "addr:housenumber":"37",
    "addr:postcode":"3083 kw",
    "addr:street":"Wielewaalstraat",
    "iso:country":"NL",
    "sg:address":"Wielewaalstraat 37",
    "sg:city":"Rotterdam",
    "sg:orig_category":"Verzekeringen",
    "sg:phone":"+31 10 480 9272",
    "sg:postcode":"3083 KW",
    "sg:province":"Zuid-Holland",
    "wof:name":"J. Sjerp Assurantien",
    "wof:placetype":"venue"
},
  "geometry": {"coordinates":[4.47243,51.885994],"type":"Point"}
}