{
  "type": "Feature",
  "properties": {
    "addr:full":"Heekstr 30 Hoogvliet Rt Zuid-Holland 3192 TE",
    "addr:housenumber":"30",
    "addr:postcode":"rt;3192 te",
    "addr:street":"Heekstr",
    "iso:country":"NL",
    "sg:address":"Heekstr 30",
    "sg:city":"Hoogvliet Rt",
    "sg:orig_category":"Artsen - Huisartsen",
    "sg:phone":"+31 10 416 0205",
    "sg:postcode":"3192 TE",
    "sg:province":"Zuid-Holland",
    "wof:name":"Geest, S Th Van Der",
    "wof:placetype":"venue"
},
  "geometry": {"coordinates":[4.355313,51.859043],"type":"Point"}
}