{
  "type": "Feature",
  "properties": {
    "addr:full":"Kerkstr 100 Hilversum Noord-Holland 1211 CS",
    "addr:housenumber":"100",
    "addr:postcode":"hilversum;1211 cs",
    "iso:country":"NL",
    "sg:address":"Kerkstr 100",
    "sg:city":"Hilversum",
    "sg:orig_category":"Koffie- En Theehuizen",
    "sg:phone":"+31 35 624 7600",
    "sg:postcode":"1211 CS",
    "sg:province":"Noord-Holland",
    "wof:name":"Zijtveld Bv, Van",
    "wof:placetype":"venue"
},
  "geometry": {"coordinates":[5.1695,52.228565],"type":"Point"}
}