{
  "type": "Feature",
  "properties": {
    "addr:full":"Wagenstr 133 S Gravenhage Zuid-Holland 2512 AT",
    "addr:housenumber":"133;gravenhage",
    "addr:postcode":"2512",
    "addr:street":"S",
    "iso:country":"NL",
    "sg:address":"Wagenstr 133",
    "sg:city":"S Gravenhage",
    "sg:orig_category":"Boekhandels",
    "sg:phone":"+31 70 363 4115",
    "sg:postcode":"2512 AT",
    "sg:province":"Zuid-Holland",
    "sg:website":"http://www.stripboekhandel.nl",
    "wof:name":"Haagse Stripshop",
    "wof:placetype":"venue"
},
  "geometry": {"coordinates":[4.30618,52.073212],"type":"Point"}
}