{
  "type": "Feature",
  "properties": {
    "addr:full":"Stationsweg 42 Stedum Groningen 9921 PW",
    "addr:housenumber":"42",
    "addr:postcode":"9921 pw",
    "addr:street":"Stationsweg",
    "iso:country":"NL",
    "sg:address":"Stationsweg 42",
    "sg:city":"Stedum",
    "sg:orig_category":"Fotostudio'S And Fotografen",
    "sg:phone":"+31 596 551 922",
    "sg:postcode":"9921 PW",
    "sg:province":"Groningen",
    "wof:name":"Pitt Fotografie",
    "wof:placetype":"venue"
},
  "geometry": {"coordinates":[6.688604,53.32497],"type":"Point"}
}