{
  "type": "Feature",
  "properties": {
    "addr:full":"St. Canisiussingel 19 Nijmegen Gelderland 6511 TE",
    "addr:housenumber":"19",
    "addr:postcode":"6511 te",
    "addr:street":"Canisiussingel;Gelderland",
    "iso:country":"NL",
    "sg:address":"St. Canisiussingel 19",
    "sg:city":"Nijmegen",
    "sg:classifiers":[
        {
            "category":"Professional",
            "subcategory":"Accounting & Tax Preparation",
            "type":"Services"
        }
    ],
    "sg:phone":"+31 24 382 3456",
    "sg:postcode":"6511 TE",
    "sg:province":"Gelderland",
    "sg:tags":[
        "accountant"
    ],
    "wof:name":"Ernst & Young",
    "wof:placetype":"venue"
},
  "geometry": {"coordinates":[5.870669,51.843487],"type":"Point"}
}