{
  "type": "Feature",
  "properties": {
    "addr:full":"J Asselbergsweg 50 Tilburg Noord-Brabant 5026 RR",
    "addr:housenumber":"50",
    "addr:postcode":"5026 rr",
    "addr:street":"J Asselbergsweg",
    "iso:country":"NL",
    "sg:address":"J Asselbergsweg 50",
    "sg:city":"Tilburg",
    "sg:orig_category":"Werving And Selectie Van Tijdelijk Personeel And Uitzendkantoren",
    "sg:phone":"+31 13 594 2222",
    "sg:postcode":"5026 RR",
    "sg:province":"Noord-Brabant",
    "wof:name":"Start",
    "wof:placetype":"venue"
},
  "geometry": {"coordinates":[5.0560150146,51.5423088074],"type":"Point"}
}