{
  "type": "Feature",
  "properties": {
    "addr:full":"J Steenstr 16 Krimpen Ad Yssel South Holland 2923 CP",
    "addr:housenumber":"16",
    "addr:postcode":"2923 cp",
    "addr:street":"Krimpen;Yssel",
    "iso:country":"NL",
    "sg:address":"J Steenstr 16",
    "sg:city":"Krimpen Ad Yssel",
    "sg:orig_category":"Fietsen En Bromfietsen",
    "sg:phone":"+31 180 551 021",
    "sg:postcode":"2923 CP",
    "sg:province":"South Holland",
    "wof:name":"Rimako",
    "wof:placetype":"venue"
},
  "geometry": {"coordinates":[4.599414,51.910889],"type":"Point"}
}