{
  "type": "Feature",
  "properties": {
    "addr:full":"Strevelswg 107A Rotterdam Zuid-Holland 3073 DW",
    "addr:housenumber":"107a",
    "addr:postcode":"3073 dw",
    "iso:country":"NL",
    "sg:address":"Strevelswg 107A",
    "sg:city":"Rotterdam",
    "sg:orig_category":"Plafonds",
    "sg:phone":"+31 10 480 0883",
    "sg:postcode":"3073 DW",
    "sg:province":"Zuid-Holland",
    "wof:name":"Groenenboom, C",
    "wof:placetype":"venue"
},
  "geometry": {"coordinates":[4.50085,51.889763],"type":"Point"}
}