{
  "type": "Feature",
  "properties": {
    "addr:full":"Sarphatistr 33 Amsterdam Noord-Holland 1018 EV",
    "addr:housenumber":"33",
    "addr:street":"Sarphatistr",
    "iso:country":"NL",
    "sg:address":"Sarphatistr 33",
    "sg:city":"Amsterdam",
    "sg:orig_category":"Adviesbureaus Beroeps- En Schoolkeuze",
    "sg:phone":"+31 20 524 7070",
    "sg:postcode":"1018 EV",
    "sg:province":"Noord-Holland",
    "sg:website":"http://www.iboamsterdam.nl",
    "wof:name":"Ibo Cursus",
    "wof:placetype":"venue"
},
  "geometry": {"coordinates":[4.905618,52.360882],"type":"Point"}
}