{
  "type": "Feature",
  "properties": {
    "addr:full":"Alddk 24 Beetgum Provincie Friesland 9044 MN",
    "addr:housenumber":"24;9044",
    "addr:postcode":"mn",
    "addr:street":"Alddk;Provincie Friesland",
    "iso:country":"NL",
    "sg:address":"Alddk 24",
    "sg:city":"Beetgum",
    "sg:orig_category":"Autoreclame",
    "sg:phone":"+31 58 253 1817",
    "sg:postcode":"9044 MN",
    "sg:province":"Provincie Friesland",
    "sg:website":"http://www.reitsmareclame.nl",
    "wof:name":"Reitsma, Reclame",
    "wof:placetype":"venue"
},
  "geometry": {"coordinates":[5.684958,53.238541],"type":"Point"}
}