{
  "type": "Feature",
  "properties": {
    "addr:full":"W R Fisherstr 13 Wirdum Fr Provincie Friesland 9088 BH",
    "addr:housenumber":"13",
    "addr:postcode":"9088 bh",
    "addr:street":"W;Fisherstr;Friesland",
    "iso:country":"NL",
    "sg:address":"W R Fisherstr 13",
    "sg:city":"Wirdum Fr",
    "sg:orig_category":"Vertaalbureaus",
    "sg:phone":"+31 58 255 1913",
    "sg:postcode":"9088 BH",
    "sg:province":"Provincie Friesland",
    "sg:website":"http://www.ljocht.nl",
    "wof:name":"Ljocht, Vertaalbureau It",
    "wof:placetype":"venue"
},
  "geometry": {"coordinates":[5.804648,53.149754],"type":"Point"}
}