{
  "type": "Feature",
  "properties": {
    "addr:full":"Treslongln 99 S Gravenhage Zuid-Holland 2548 RT",
    "addr:housenumber":"99;gravenhage",
    "addr:postcode":"2548 rt",
    "addr:street":"Treslongln;S",
    "iso:country":"NL",
    "sg:address":"Treslongln 99",
    "sg:city":"S Gravenhage",
    "sg:orig_category":"Kinderopvang",
    "sg:phone":"+31 70 394 2795",
    "sg:postcode":"2548 RT",
    "sg:province":"Zuid-Holland",
    "wof:name":"2 Schuiten",
    "wof:placetype":"venue"
},
  "geometry": {"coordinates":[4.2901,52.029888],"type":"Point"}
}