{
  "type": "Feature",
  "properties": {
    "iso:country":"NL",
    "sg:address":"Casembrootstraat 22",
    "sg:city":"Ijmuiden",
    "sg:classifiers":[
        {
            "category":"Food & Beverages",
            "subcategory":"Fruits & Vegetables",
            "type":"Retail Goods"
        }
    ],
    "sg:phone":"+31 255 530 434",
    "sg:postcode":"1972 CC",
    "sg:province":"Noord-Holland",
    "sg:tags":[
        "groenten"
    ],
    "wof:name":"De Groenhoek",
    "wof:placetype":"venue"
},
  "geometry": {"coordinates":[4.619216,52.462067],"type":"Point"}
}