{
  "type": "Feature",
  "properties": {
    "addr:full":"Rietakker 6 Noord Scharwoude Noord-Holland 1723 BC",
    "addr:housenumber":"6",
    "addr:postcode":"1723 bc",
    "addr:street":"Rietakker",
    "iso:country":"NL",
    "sg:address":"Rietakker 6",
    "sg:city":"Noord Scharwoude",
    "sg:orig_category":"Video - Faciliteiten En Producties",
    "sg:phone":"+31 6 44972350",
    "sg:postcode":"1723 BC",
    "sg:province":"Noord-Holland",
    "sg:website":"http://www.digi-video.nl",
    "wof:name":"Crw Digi Video Productions",
    "wof:placetype":"venue"
},
  "geometry": {"coordinates":[4.80375,52.696629],"type":"Point"}
}