{
  "type": "Feature",
  "properties": {
    "addr:full":"Martin Luther Kingsngl 40 Drachten Friesland 9203 JC",
    "addr:housenumber":"40",
    "addr:postcode":"9203 jc",
    "addr:street":"Martin",
    "iso:country":"NL",
    "sg:address":"Martin Luther Kingsngl 40",
    "sg:city":"Drachten",
    "sg:orig_category":"Metaalwerken",
    "sg:phone":"+31 512 544 481",
    "sg:postcode":"9203 JC",
    "sg:province":"Friesland",
    "wof:name":"Carpet Land",
    "wof:placetype":"venue"
},
  "geometry": {"coordinates":[6.104506,53.096001],"type":"Point"}
}