{
  "type": "Feature",
  "properties": {
    "addr:full":"V Beethovenln 10A Voorschoten South Holland 2253 BE",
    "addr:housenumber":"10a",
    "addr:postcode":"2253",
    "iso:country":"NL",
    "sg:address":"V Beethovenln 10A",
    "sg:city":"Voorschoten",
    "sg:orig_category":"Scholen Voor Basisonderwijs",
    "sg:phone":"+31 71 561 2995",
    "sg:postcode":"2253 BE",
    "sg:province":"South Holland",
    "wof:name":"Fortgensschool",
    "wof:placetype":"venue"
},
  "geometry": {"coordinates":[4.44429,52.124825],"type":"Point"}
}