{
  "type": "Feature",
  "properties": {
    "addr:full":"V Ostadeln 254 Alkmaar Noord-Holland 1816 JG",
    "addr:housenumber":"254",
    "addr:postcode":"1816 jg",
    "iso:country":"NL",
    "sg:address":"V Ostadeln 254",
    "sg:city":"Alkmaar",
    "sg:classifiers":[
        {
            "category":"Food & Beverages",
            "subcategory":"Bakery",
            "type":"Retail Goods"
        }
    ],
    "sg:phone":"+31 72 512 6303",
    "sg:postcode":"1816 JG",
    "sg:province":"Noord-Holland",
    "sg:tags":[
        "pizza"
    ],
    "wof:name":"Buonasera Pizzeria",
    "wof:placetype":"venue"
},
  "geometry": {"coordinates":[4.746258,52.634361],"type":"Point"}
}