{
  "type": "Feature",
  "properties": {
    "iso:country":"NL",
    "sg:address":"Broekerstraat 53",
    "sg:city":"Leende",
    "sg:orig_category":"Verenigingen En Stichtingen",
    "sg:phone":"+31 40 206 1081",
    "sg:postcode":"5595 CV",
    "sg:province":"Noord-Brabant",
    "wof:name":"Levende Aarde, Sticht",
    "wof:placetype":"venue"
},
  "geometry": {"coordinates":[5.558742,51.349964],"type":"Point"}
}