{
  "type": "Feature",
  "properties": {
    "addr:full":"Hoofdstr 183 Driebergen Rysenb Utrecht 3971 KL",
    "addr:housenumber":"183",
    "addr:postcode":"3971 kl",
    "addr:street":"Driebergen Rysenb",
    "iso:country":"NL",
    "sg:address":"Hoofdstr 183",
    "sg:city":"Driebergen Rysenb",
    "sg:orig_category":"Adviesbureaus",
    "sg:phone":"+31 343 511 581",
    "sg:postcode":"3971 KL",
    "sg:province":"Utrecht",
    "wof:name":"Tjarcon Bv",
    "wof:placetype":"venue"
},
  "geometry": {"coordinates":[5.292233,52.049244],"type":"Point"}
}