{
  "type": "Feature",
  "properties": {
    "addr:full":"Gedempte Gr 49 Zaandam North Holland 1506 CB",
    "addr:housenumber":"49",
    "addr:postcode":"1506 cb",
    "addr:street":"Gedempte Gr",
    "iso:country":"NL",
    "sg:address":"Gedempte Gr 49",
    "sg:city":"Zaandam",
    "sg:orig_category":"Warenhuizen",
    "sg:phone":"+31 75 617 0251",
    "sg:postcode":"1506 CB",
    "sg:province":"North Holland",
    "sg:website":"http://www.vroomendreesmann.nl",
    "wof:name":"V & D",
    "wof:placetype":"venue"
},
  "geometry": {"coordinates":[4.8222618103,52.4395637512],"type":"Point"}
}