{
  "type": "Feature",
  "properties": {
    "addr:full":"F V Mierisstr 41 Amsterdam North Holland 1071 RK",
    "addr:housenumber":"41",
    "addr:postcode":"1071 rk",
    "addr:street":"Mierisstr",
    "iso:country":"NL",
    "sg:address":"F V Mierisstr 41",
    "sg:city":"Amsterdam",
    "sg:orig_category":"Video - Faciliteiten En Producties",
    "sg:phone":"+31 20 679 1745",
    "sg:postcode":"1071 RK",
    "sg:province":"North Holland",
    "wof:name":"Royen, Lucas Van",
    "wof:placetype":"venue"
},
  "geometry": {"coordinates":[4.87701,52.355549],"type":"Point"}
}