{
  "type": "Feature",
  "properties": {
    "addr:full":"Gaspeldoorn 14 Rotterdam Zuid-Holland 3068 MK",
    "addr:housenumber":"14",
    "addr:postcode":"3068",
    "addr:street":"Gaspeldoorn",
    "iso:country":"NL",
    "sg:address":"Gaspeldoorn 14",
    "sg:city":"Rotterdam",
    "sg:orig_category":"Bedrijfsinventaris Gh",
    "sg:phone":"+31 10 220 2224",
    "sg:postcode":"3068 MK",
    "sg:province":"Zuid-Holland",
    "wof:name":"Jede Lady Rotterdam",
    "wof:placetype":"venue"
},
  "geometry": {"coordinates":[4.539115,51.957001],"type":"Point"}
}