{
  "type": "Feature",
  "properties": {
    "addr:full":"Floraweg 200 Amsterdam Noord-Holland 1032 ZG",
    "addr:housenumber":"200",
    "addr:postcode":"1032 zg",
    "addr:street":"Floraweg",
    "iso:country":"NL",
    "sg:address":"Floraweg 200",
    "sg:city":"Amsterdam",
    "sg:orig_category":"Woningbouwverenigingen",
    "sg:phone":"+31 20 494 6300",
    "sg:postcode":"1032 ZG",
    "sg:province":"Noord-Holland",
    "wof:name":"Woningbedrijf Amsterdam Vestiging Noord",
    "wof:placetype":"venue"
},
  "geometry": {"coordinates":[4.908575058,52.3999061584],"type":"Point"}
}