{
  "type": "Feature",
  "properties": {
    "iso:country":"NL",
    "sg:address":"Burg Baetenspk 10",
    "sg:city":"Prinsenbeek",
    "sg:orig_category":"Administratie- En Boekhoudkantoren",
    "sg:phone":"+31 76 543 0177",
    "sg:postcode":"4841 JS",
    "sg:province":"North Brabant",
    "wof:name":"Alm",
    "wof:placetype":"venue"
},
  "geometry": {"coordinates":[4.701989,51.59763],"type":"Point"}
}