{
  "type": "Feature",
  "properties": {
    "addr:full":"Kapt Nemostr 21-23 Emmen Provincie Drenthe 7821 AB",
    "addr:housenumber":"21-23",
    "addr:postcode":"7821 ab",
    "addr:street":"Provincie Drenthe",
    "iso:country":"NL",
    "sg:address":"Kapt Nemostr 21-23",
    "sg:city":"Emmen",
    "sg:orig_category":"Verf En Lak - Fabrieken En Groothandel",
    "sg:phone":"+31 591 658 200",
    "sg:postcode":"7821 AB",
    "sg:province":"Provincie Drenthe",
    "wof:name":"Weerd Bv, Gebr Van Der",
    "wof:placetype":"venue"
},
  "geometry": {"coordinates":[6.921912,52.769993],"type":"Point"}
}