{
  "type": "Feature",
  "properties": {
    "addr:full":"Wannerstraat 13 Heerlen Limburg 6413 EV",
    "addr:housenumber":"13",
    "addr:postcode":"6413 ev",
    "addr:street":"Wannerstraat",
    "iso:country":"NL",
    "sg:address":"Wannerstraat 13",
    "sg:city":"Heerlen",
    "sg:orig_category":"Kappers",
    "sg:phone":"+31 45 522 9170",
    "sg:postcode":"6413 EV",
    "sg:province":"Limburg",
    "wof:name":"Kapsalon Korbel",
    "wof:placetype":"venue"
},
  "geometry": {"coordinates":[5.9556188583,50.9156646729],"type":"Point"}
}