{
  "type": "Feature",
  "properties": {
    "iso:country":"NL",
    "sg:address":"P Calandln 17",
    "sg:city":"Amsterdam",
    "sg:orig_category":"Makelaars En Adviseurs Verzekeringen",
    "sg:phone":"+31 20 408 4744",
    "sg:postcode":"1065 KH",
    "sg:province":"Noord-Holland",
    "wof:name":"Mangr\u00e9",
    "wof:placetype":"venue"
},
  "geometry": {"coordinates":[4.829715,52.35622],"type":"Point"}
}