{
  "type": "Feature",
  "properties": {
    "addr:full":"Adelaarstraat 36 Utrecht Utrecht 3514 CG",
    "addr:housenumber":"36",
    "addr:postcode":"3514 cg",
    "addr:street":"Adelaarstraat",
    "iso:country":"NL",
    "sg:address":"Adelaarstraat 36",
    "sg:city":"Utrecht",
    "sg:orig_category":"Wasserettes And Stomerijen",
    "sg:phone":"+31 30 271 4765",
    "sg:postcode":"3514 CG",
    "sg:province":"Utrecht",
    "wof:name":"Stomerij Dolman",
    "wof:placetype":"venue"
},
  "geometry": {"coordinates":[5.1159729958,52.0993766785],"type":"Point"}
}