{
  "type": "Feature",
  "properties": {
    "addr:full":"Nassaukd 387-390 Amsterdam North Holland 1054 AE",
    "addr:housenumber":"387-390",
    "addr:postcode":"1054 ae",
    "iso:country":"NL",
    "sg:address":"Nassaukd 387-390",
    "sg:city":"Amsterdam",
    "sg:classifiers":[
        {
            "category":"Travel",
            "subcategory":"Hotels & Motels",
            "type":"Entertainment"
        }
    ],
    "sg:phone":"+31 20 683 4935",
    "sg:postcode":"1054 AE",
    "sg:province":"North Holland",
    "sg:website":"http://www.westropa.demon.nl",
    "wof:name":"Westropa, Hotel",
    "wof:placetype":"venue"
},
  "geometry": {"coordinates":[4.86857,52.361408],"type":"Point"}
}