{
  "type": "Feature",
  "properties": {
    "addr:full":"Gerbrandyplein 1 Zwijndrecht Zuid-Holland 3332 XA",
    "addr:housenumber":"1",
    "addr:postcode":"3332 xa",
    "addr:street":"Gerbrandyplein",
    "iso:country":"NL",
    "sg:address":"Gerbrandyplein 1",
    "sg:city":"Zwijndrecht",
    "sg:orig_category":"Beautyfarms And Sauna'S",
    "sg:phone":"+31 78 620 9740",
    "sg:postcode":"3332 XA",
    "sg:province":"Zuid-Holland",
    "wof:name":"Ergoline Zwijndrecht",
    "wof:placetype":"venue"
},
  "geometry": {"coordinates":[4.65566,51.821232],"type":"Point"}
}