{
  "type": "Feature",
  "properties": {
    "addr:full":"Appelmarkt 18 Zierikzee Zeeland 4301 CA",
    "addr:housenumber":"18",
    "addr:postcode":"4301 ca",
    "addr:street":"Appelmarkt",
    "iso:country":"NL",
    "sg:address":"Appelmarkt 18",
    "sg:city":"Zierikzee",
    "sg:orig_category":"Sportschoenen - Winkels",
    "sg:phone":"+31 111 450 260",
    "sg:postcode":"4301 CA",
    "sg:province":"Zeeland",
    "sg:website":"http://www.intersport.nl",
    "wof:name":"Intersport Vision",
    "wof:placetype":"venue"
},
  "geometry": {"coordinates":[3.920058,51.649635],"type":"Point"}
}