{
  "type": "Feature",
  "properties": {
    "iso:country":"NL",
    "sg:address":"Ruimtevaartlaan 29",
    "sg:city":"Krommenie",
    "sg:orig_category":"Elektrische Apparatuur Gh",
    "sg:phone":"+31 75 628 6983",
    "sg:postcode":"1562 BA",
    "sg:province":"Noord-Holland",
    "wof:name":"Maron",
    "wof:placetype":"venue"
},
  "geometry": {"coordinates":[4.755999,52.506084],"type":"Point"}
}