{
  "type": "Feature",
  "properties": {
    "addr:full":"Herenlaan 10A Zeist Utrecht 3701 AT",
    "addr:housenumber":"10a",
    "addr:postcode":"3701",
    "addr:street":"Herenlaan",
    "iso:country":"NL",
    "sg:address":"Herenlaan 10A",
    "sg:city":"Zeist",
    "sg:orig_category":"Binnenhuisarchitecten",
    "sg:phone":"+31 30 692 2137",
    "sg:postcode":"3701 AT",
    "sg:province":"Utrecht",
    "wof:name":"O.P. Koch",
    "wof:placetype":"venue"
},
  "geometry": {"coordinates":[5.241661,52.082588],"type":"Point"}
}