{
  "type": "Feature",
  "properties": {
    "iso:country":"NL",
    "sg:address":"Leliestr 50",
    "sg:city":"Deventer",
    "sg:orig_category":"Verhuur",
    "sg:phone":"+31 570 616 909",
    "sg:postcode":"7419 CW",
    "sg:province":"Gelderland",
    "wof:name":"Beeld & Geluid Deventer",
    "wof:placetype":"venue"
},
  "geometry": {"coordinates":[6.140181,52.249195],"type":"Point"}
}