{
  "type": "Feature",
  "properties": {
    "addr:full":"Radboudkwartier 21 Utrecht Utrecht 3511 CC",
    "addr:housenumber":"21",
    "addr:postcode":"3511 cc",
    "addr:street":"Radboudkwartier",
    "iso:country":"NL",
    "sg:address":"Radboudkwartier 21",
    "sg:city":"Utrecht",
    "sg:orig_category":"Schoenen",
    "sg:phone":"+31 30 232 8881",
    "sg:postcode":"3511 CC",
    "sg:province":"Utrecht",
    "sg:website":"http://www.invito.com",
    "wof:name":"Invito",
    "wof:placetype":"venue"
},
  "geometry": {"coordinates":[5.112883,52.090683],"type":"Point"}
}