{
  "type": "Feature",
  "properties": {
    "iso:country":"NL",
    "sg:address":"Patersw Meer Wz 2",
    "sg:city":"Haren Gn",
    "sg:orig_category":"Adviesbureaus Bedrijfsorganisatie",
    "sg:phone":"+31 50 309 0399",
    "sg:postcode":"9752 XH",
    "sg:province":"Groningen",
    "wof:name":"Everards Bv, Wim",
    "wof:placetype":"venue"
},
  "geometry": {"coordinates":[6.58649,53.16354],"type":"Point"}
}