{
  "type": "Feature",
  "properties": {
    "addr:full":"Keizersgr 263 Amsterdam Noord-Holland 1016 EC",
    "addr:housenumber":"263",
    "addr:postcode":"1016 ec",
    "iso:country":"NL",
    "sg:address":"Keizersgr 263",
    "sg:city":"Amsterdam",
    "sg:orig_category":"Fotografie Reclame En Mode",
    "sg:phone":"+31 20 622 4297",
    "sg:postcode":"1016 EC",
    "sg:province":"Noord-Holland",
    "wof:name":"Meer, Dorien Van Der",
    "wof:placetype":"venue"
},
  "geometry": {"coordinates":[4.885292,52.371258],"type":"Point"}
}