{
  "type": "Feature",
  "properties": {
    "addr:full":"Postbus 40 Bemmel Gelderland 6680 AA",
    "addr:housenumber":"40",
    "addr:postcode":"6680 aa",
    "addr:street":"Postbus;Gelderland",
    "iso:country":"NL",
    "sg:address":"Postbus 40",
    "sg:city":"Bemmel",
    "sg:orig_category":"Bloemen En Planten - Groothandel",
    "sg:phone":"+31 26 325 9195",
    "sg:postcode":"6680 AA",
    "sg:province":"Gelderland",
    "wof:name":"Niftrik Bv",
    "wof:placetype":"venue"
},
  "geometry": {"coordinates":[5.89882,51.8941],"type":"Point"}
}