{
  "type": "Feature",
  "properties": {
    "addr:full":"A Bellstr 57 Ymuiden Noord-Holland 1972 RB",
    "addr:housenumber":"57",
    "addr:postcode":"1972 rb",
    "iso:country":"NL",
    "sg:address":"A Bellstr 57",
    "sg:city":"Ymuiden",
    "sg:orig_category":"Drukwerkverspreiding",
    "sg:phone":"+31 255 537 402",
    "sg:postcode":"1972 RB",
    "sg:province":"Noord-Holland",
    "wof:name":"Dijk Distributie & Verspreiding, Van",
    "wof:placetype":"venue"
},
  "geometry": {"coordinates":[4.61762,52.458302],"type":"Point"}
}