{
  "type": "Feature",
  "properties": {
    "addr:full":"Ekkerstr 29A Bergeyk Noord-Brabant 5571 LG",
    "addr:housenumber":"29a",
    "addr:postcode":"5571 lg",
    "addr:street":"Ekkerstr",
    "iso:country":"NL",
    "sg:address":"Ekkerstr 29A",
    "sg:city":"Bergeyk",
    "sg:orig_category":"Loodgieters",
    "sg:phone":"+31 497 571 374",
    "sg:postcode":"5571 LG",
    "sg:province":"Noord-Brabant",
    "wof:name":"Peeters Roijers Bv",
    "wof:placetype":"venue"
},
  "geometry": {"coordinates":[5.346939,51.317181],"type":"Point"}
}