{
  "type": "Feature",
  "properties": {
    "iso:country":"NL",
    "sg:address":"Eikenbosch 26",
    "sg:city":"Berkel-Enschot",
    "sg:orig_category":"Wasserettes And Stomerijen",
    "sg:phone":"+31 13 533 4320",
    "sg:postcode":"5056 GB",
    "sg:province":"North Brabant",
    "wof:name":"Stomerij Eikenbosch",
    "wof:placetype":"venue"
},
  "geometry": {"coordinates":[5.1398029327,51.5848731995],"type":"Point"}
}