{
  "type": "Feature",
  "properties": {
    "addr:full":"Heselbergherweg 66 Arnhem Gelderland 6821 JS",
    "addr:housenumber":"66",
    "addr:postcode":"6821 js",
    "addr:street":"Heselbergherweg",
    "iso:country":"NL",
    "sg:address":"Heselbergherweg 66",
    "sg:city":"Arnhem",
    "sg:orig_category":"Meubelzaken, Woning- And Keukeninrichting",
    "sg:phone":"+31 26 445 4135",
    "sg:postcode":"6821 JS",
    "sg:province":"Gelderland",
    "wof:name":"Ambachtelijk Meubel",
    "wof:placetype":"venue"
},
  "geometry": {"coordinates":[5.917519,51.995235],"type":"Point"}
}