{
  "type": "Feature",
  "properties": {
    "iso:country":"NL",
    "sg:address":"De Pas 90",
    "sg:city":"Arnhem",
    "sg:orig_category":"Vertaalbureaus",
    "sg:phone":"+31 26 327 0748",
    "sg:postcode":"6836 HM",
    "sg:province":"Gelderland",
    "wof:name":"1.2.Communicate",
    "wof:placetype":"venue"
},
  "geometry": {"coordinates":[5.8827,51.942833],"type":"Point"}
}