{
  "type": "Feature",
  "properties": {
    "addr:full":"Oeverstraat 30 Wijk Bij Duurstede Utrecht 3961 AN",
    "addr:housenumber":"30",
    "addr:postcode":"3961 an",
    "addr:street":"Oeverstraat",
    "iso:country":"NL",
    "sg:address":"Oeverstraat 30",
    "sg:city":"Wijk Bij Duurstede",
    "sg:orig_category":"Makelaars In Onroerend Goed",
    "sg:phone":"+31 343 571 254",
    "sg:postcode":"3961 AN",
    "sg:province":"Utrecht",
    "wof:name":"Dikker Makelaardij",
    "wof:placetype":"venue"
},
  "geometry": {"coordinates":[5.348055,51.970955],"type":"Point"}
}