{
  "type": "Feature",
  "properties": {
    "addr:full":"Langstraat 36 Wijhe Overijssel 8131 BC",
    "addr:housenumber":"36",
    "addr:postcode":"8131 bc",
    "addr:street":"Langstraat",
    "iso:country":"NL",
    "sg:address":"Langstraat 36",
    "sg:city":"Wijhe",
    "sg:orig_category":"Verlichting And Huishoudartikelen",
    "sg:phone":"+31 570 521 723",
    "sg:postcode":"8131 BC",
    "sg:province":"Overijssel",
    "wof:name":"Interieurverzorging Overmars",
    "wof:placetype":"venue"
},
  "geometry": {"coordinates":[6.135243,52.388561],"type":"Point"}
}