{
  "type": "Feature",
  "properties": {
    "addr:full":"Kabeljauwallee 35 Doorwerth Gelderland 6865 BL",
    "addr:housenumber":"35",
    "addr:postcode":"6865 bl",
    "addr:street":"Kabeljauwallee;Gelderland",
    "iso:country":"NL",
    "sg:address":"Kabeljauwallee 35",
    "sg:city":"Doorwerth",
    "sg:orig_category":"Exploitatie- Maatschappijen",
    "sg:phone":"+31 317 319 010",
    "sg:postcode":"6865 BL",
    "sg:province":"Gelderland",
    "wof:name":"Leemkuil Bv, De",
    "wof:placetype":"venue"
},
  "geometry": {"coordinates":[5.780831,51.977905],"type":"Point"}
}