{
  "type": "Feature",
  "properties": {
    "addr:full":"Molenstraat 65 Nederhemert Gelderland 5317 JE",
    "addr:housenumber":"65",
    "addr:postcode":"5317 je",
    "addr:street":"Molenstraat;Gelderland",
    "iso:country":"NL",
    "sg:address":"Molenstraat 65",
    "sg:city":"Nederhemert",
    "sg:orig_category":"Bloemen And Planten",
    "sg:phone":"+31 418 551 187",
    "sg:postcode":"5317 JE",
    "sg:province":"Gelderland",
    "wof:name":"Bloembinderij Style",
    "wof:placetype":"venue"
},
  "geometry": {"coordinates":[5.160609,51.763332],"type":"Point"}
}