{
  "type": "Feature",
  "properties": {
    "addr:full":"Latyns Amerikaln 15 Delft South Holland 2622 BA",
    "addr:housenumber":"15",
    "addr:postcode":"2622 ba",
    "iso:country":"NL",
    "sg:address":"Latyns Amerikaln 15",
    "sg:city":"Delft",
    "sg:orig_category":"Kappers",
    "sg:phone":"+31 15 262 6777",
    "sg:postcode":"2622 BA",
    "sg:province":"South Holland",
    "wof:name":"Denise",
    "wof:placetype":"venue"
},
  "geometry": {"coordinates":[4.3518300056,51.9843406677],"type":"Point"}
}