{
  "type": "Feature",
  "properties": {
    "addr:full":"Reigersweg 151 Apeldoorn Gelderland 7331 TN",
    "addr:housenumber":"151",
    "addr:postcode":"7331",
    "addr:street":"Reigersweg;Gelderland",
    "iso:country":"NL",
    "sg:address":"Reigersweg 151",
    "sg:city":"Apeldoorn",
    "sg:orig_category":"Fietshandelaren",
    "sg:phone":"+31 55 533 3797",
    "sg:postcode":"7331 TN",
    "sg:province":"Gelderland",
    "wof:name":"J.W. Modderkolk",
    "wof:placetype":"venue"
},
  "geometry": {"coordinates":[5.974226,52.205353],"type":"Point"}
}