{
  "type": "Feature",
  "properties": {
    "addr:full":"St Odastr 26 Eindhoven Noord-Brabant 5614 AM",
    "addr:housenumber":"26",
    "addr:postcode":"5614",
    "iso:country":"NL",
    "sg:address":"St Odastr 26",
    "sg:city":"Eindhoven",
    "sg:orig_category":"Psychotherapeuten",
    "sg:phone":"+31 40 211 1505",
    "sg:postcode":"5614 AM",
    "sg:province":"Noord-Brabant",
    "wof:name":"Baars, M Van",
    "wof:placetype":"venue"
},
  "geometry": {"coordinates":[5.493057,51.43121],"type":"Point"}
}