{
  "type": "Feature",
  "properties": {
    "addr:full":"Zuidwending 5 Vriescheloo Groningen 9699 PV",
    "addr:housenumber":"5",
    "addr:postcode":"9699 pv",
    "addr:street":"Zuidwending",
    "iso:country":"NL",
    "sg:address":"Zuidwending 5",
    "sg:city":"Vriescheloo",
    "sg:orig_category":"Homeopathie",
    "sg:phone":"+31 597 532 702",
    "sg:postcode":"9699 PV",
    "sg:province":"Groningen",
    "wof:name":"Marry Van Der Zon",
    "wof:placetype":"venue"
},
  "geometry": {"coordinates":[7.135775,53.099022],"type":"Point"}
}