{
  "type": "Feature",
  "properties": {
    "addr:full":"Westfrankelandsestraat 152 Schiedam Zuid-Holland 3117 AZ",
    "addr:housenumber":"152",
    "addr:postcode":"3117 az",
    "addr:street":"Westfrankelandsestraat",
    "iso:country":"NL",
    "sg:address":"Westfrankelandsestraat 152",
    "sg:city":"Schiedam",
    "sg:classifiers":[
        {
            "category":"Education",
            "subcategory":"Preschool",
            "type":"Public Place"
        }
    ],
    "sg:phone":"+31 10 426 1885",
    "sg:postcode":"3117 AZ",
    "sg:province":"Zuid-Holland",
    "sg:tags":[
        "kleuteronderwijs",
        "basis-"
    ],
    "wof:name":"Christelijke Basisschool De Wieken",
    "wof:placetype":"venue"
},
  "geometry": {"coordinates":[4.386619,51.9137],"type":"Point"}
}