{
  "type": "Feature",
  "properties": {
    "addr:full":"Haansbergseweg 30 Rijen Noord-Brabant 5121 LJ",
    "addr:housenumber":"30",
    "addr:postcode":"5121 lj",
    "addr:street":"Haansbergseweg",
    "iso:country":"NL",
    "sg:address":"Haansbergseweg 30",
    "sg:city":"Rijen",
    "sg:orig_category":"Metaalbekleding And -Behandeling",
    "sg:phone":"+31 161 222 802",
    "sg:postcode":"5121 LJ",
    "sg:province":"Noord-Brabant",
    "wof:name":"Verzinkerij Rijen Bv",
    "wof:placetype":"venue"
},
  "geometry": {"coordinates":[4.926522,51.582047],"type":"Point"}
}