{
  "type": "Feature",
  "properties": {
    "iso:country":"NL",
    "sg:address":"Poortse Bos 13",
    "sg:city":"Maarn",
    "sg:orig_category":"Adviesbureaus Bedrijfsorganisatie",
    "sg:phone":"+31 343 442 761",
    "sg:postcode":"3951 BK",
    "sg:province":"Utrecht",
    "wof:name":"Kruft Cons Bv",
    "wof:placetype":"venue"
},
  "geometry": {"coordinates":[5.362337,52.066994],"type":"Point"}
}