{
  "type": "Feature",
  "properties": {
    "addr:full":"Poortse Bos 13 Maarn Utrecht 3951 BK",
    "addr:housenumber":"13",
    "addr:postcode":"3951 bk",
    "addr:street":"Poortse Bos",
    "iso:country":"NL",
    "sg:address":"Poortse Bos 13",
    "sg:city":"Maarn",
    "sg:orig_category":"Adviesbureaus Bedrijfsorganisatie",
    "sg:phone":"+31 343 442 761",
    "sg:postcode":"3951 BK",
    "sg:province":"Utrecht",
    "wof:name":"Kruft Cons Bv",
    "wof:placetype":"venue"
},
  "geometry": {"coordinates":[5.362337,52.066994],"type":"Point"}
}