{
  "type": "Feature",
  "properties": {
    "addr:full":"Hoofdstraat 24 Veenendaal Utrecht 3901 AN",
    "addr:housenumber":"24",
    "addr:postcode":"3901 an",
    "addr:street":"Hoofdstraat",
    "iso:country":"NL",
    "sg:address":"Hoofdstraat 24",
    "sg:city":"Veenendaal",
    "sg:classifiers":[
        {
            "category":"Retail",
            "subcategory":"Photofinishing",
            "type":"Services"
        }
    ],
    "sg:phone":"+31 318 512 689",
    "sg:postcode":"3901 AN",
    "sg:province":"Utrecht",
    "sg:tags":[
        "foto",
        "film"
    ],
    "wof:name":"Combimarkt",
    "wof:placetype":"venue"
},
  "geometry": {"coordinates":[5.555328,52.026119],"type":"Point"}
}