{
  "type": "Feature",
  "properties": {
    "addr:full":"Vreewijkplein 1 Rhenen Utrecht 3911 EH",
    "addr:housenumber":"1",
    "addr:postcode":"3911 eh",
    "addr:street":"Vreewijkplein",
    "iso:country":"NL",
    "sg:address":"Vreewijkplein 1",
    "sg:city":"Rhenen",
    "sg:classifiers":[
        {
            "category":"Fast Food",
            "type":"Food & Drink"
        }
    ],
    "sg:phone":"+31 317 618 322",
    "sg:postcode":"3911 EH",
    "sg:province":"Utrecht",
    "sg:tags":[
        "afhaal",
        "restaurant"
    ],
    "wof:name":"Cafetaria Vreewijk",
    "wof:placetype":"venue"
},
  "geometry": {"coordinates":[5.570335,51.964954],"type":"Point"}
}