{
  "type": "Feature",
  "properties": {
    "iso:country":"NL",
    "sg:address":"Breestr 50",
    "sg:city":"Beverwyk",
    "sg:orig_category":"Huishoudelijke Apparaten En Artikelen",
    "sg:phone":"+31 251 227 377",
    "sg:postcode":"1941 EK",
    "sg:province":"Noord-Holland",
    "wof:name":"Blokker Bv",
    "wof:placetype":"venue"
},
  "geometry": {"coordinates":[4.656203,52.480755],"type":"Point"}
}