{
  "type": "Feature",
  "properties": {
    "addr:full":"Steffenshein 10 Laren Nh North Holland 1251 ZE",
    "addr:housenumber":"10",
    "addr:postcode":"1251 ze",
    "addr:street":"Steffenshein;Nh North",
    "iso:country":"NL",
    "sg:address":"Steffenshein 10",
    "sg:city":"Laren Nh",
    "sg:orig_category":"Kantoor- En Secretariaatsservice",
    "sg:phone":"+31 35 647 8634",
    "sg:postcode":"1251 ZE",
    "sg:province":"North Holland",
    "wof:name":"Together Management Support",
    "wof:placetype":"venue"
},
  "geometry": {"coordinates":[5.2253289223,52.2500572205],"type":"Point"}
}