{
  "type": "Feature",
  "properties": {
    "iso:country":"NL",
    "sg:address":"Steffenshein 10",
    "sg:city":"Laren Nh",
    "sg:orig_category":"Kantoor- En Secretariaatsservice",
    "sg:phone":"+31 35 647 8634",
    "sg:postcode":"1251 ZE",
    "sg:province":"North Holland",
    "wof:name":"Together Management Support",
    "wof:placetype":"venue"
},
  "geometry": {"coordinates":[5.2253289223,52.2500572205],"type":"Point"}
}