{
  "type": "Feature",
  "properties": {
    "addr:full":"Koningin Wilhelminalaan 8 Rijnsburg Zuid-Holland 2231 VV",
    "addr:housenumber":"8",
    "addr:postcode":"2231 vv",
    "addr:street":"Koningin Wilhelminalaan",
    "iso:country":"NL",
    "sg:address":"Koningin Wilhelminalaan 8",
    "sg:city":"Rijnsburg",
    "sg:orig_category":"Bloemen And Planten Gh",
    "sg:phone":"+31 71 402 1098",
    "sg:postcode":"2231 VV",
    "sg:province":"Zuid-Holland",
    "wof:name":"Henk Van Egmond Bv",
    "wof:placetype":"venue"
},
  "geometry": {"coordinates":[4.437339,52.18441],"type":"Point"}
}