{
  "type": "Feature",
  "properties": {
    "iso:country":"NL",
    "sg:address":"Notenborg 18",
    "sg:city":"Maastricht",
    "sg:orig_category":"Bouwmaterialen Gh",
    "sg:phone":"+31 43 367 0010",
    "sg:postcode":"6228 CX",
    "sg:province":"Limburg",
    "wof:name":"Maenen Natuursteen",
    "wof:placetype":"venue"
},
  "geometry": {"coordinates":[5.726126,50.82407],"type":"Point"}
}