{
  "type": "Feature",
  "properties": {
    "iso:country":"NL",
    "sg:address":"Kortvoort 100",
    "sg:city":"Amsterdam Zuidoost",
    "sg:orig_category":"Bejaarden - Verzorgingstehuizen",
    "sg:phone":"+31 20 699 1151",
    "sg:postcode":"1104 NB",
    "sg:province":"Noord-Holland",
    "wof:name":"Henri?tte Roland Holsthuis",
    "wof:placetype":"venue"
},
  "geometry": {"coordinates":[4.970274,52.314812],"type":"Point"}
}