{
  "type": "Feature",
  "properties": {
    "addr:full":"Dommelsedk 1 Westerhoven Noord-Brabant 5563 AA",
    "addr:housenumber":"1",
    "addr:postcode":"5563 aa",
    "addr:street":"Dommelsedk",
    "iso:country":"NL",
    "sg:address":"Dommelsedk 1",
    "sg:city":"Westerhoven",
    "sg:classifiers":[
        {
            "category":"Animal Shelter",
            "type":"Public Place"
        }
    ],
    "sg:phone":"+31 40 201 4154",
    "sg:postcode":"5563 AA",
    "sg:province":"Noord-Brabant",
    "sg:tags":[
        "kennel"
    ],
    "wof:name":"Teckel, De",
    "wof:placetype":"venue"
},
  "geometry": {"coordinates":[5.418489,51.342365],"type":"Point"}
}