{
  "type": "Feature",
  "properties": {
    "addr:full":"Godevaert Montensstraat 27 Breda North Brabant 4811 PD",
    "addr:housenumber":"27",
    "addr:postcode":"4811 pd",
    "addr:street":"Godevaert Montensstraat",
    "iso:country":"NL",
    "sg:address":"Godevaert Montensstraat 27",
    "sg:city":"Breda",
    "sg:orig_category":"Loodgieterswerk, Verwarming And Sanitaire Installaties",
    "sg:phone":"+31 76 572 0810",
    "sg:postcode":"4811 PD",
    "sg:province":"North Brabant",
    "wof:name":"Franken Technisch Onderhoud En Installat",
    "wof:placetype":"venue"
},
  "geometry": {"coordinates":[4.775499,51.581528],"type":"Point"}
}