{
  "type": "Feature",
  "properties": {
    "iso:country":"NL",
    "sg:address":"P/A Rhonepad 20",
    "sg:city":"Assen",
    "sg:orig_category":"Metaalwerken",
    "sg:phone":"+31 592 398 335",
    "sg:postcode":"9406 VD",
    "sg:province":"Drenthe",
    "wof:name":"Alberti Projekten",
    "wof:placetype":"venue"
},
  "geometry": {"coordinates":[6.543786,53.0107],"type":"Point"}
}