{
  "type": "Feature",
  "properties": {
    "addr:full":"Vishalstraat 6 Zoutkamp Groningen 9974 PH",
    "addr:housenumber":"6",
    "addr:postcode":"9974",
    "addr:street":"Vishalstraat",
    "iso:country":"NL",
    "sg:address":"Vishalstraat 6",
    "sg:city":"Zoutkamp",
    "sg:orig_category":"Bibliotheken And Openbare Archieven",
    "sg:phone":"+31 595 402 750",
    "sg:postcode":"9974 PH",
    "sg:province":"Groningen",
    "wof:name":"Openbare Bibliotheek",
    "wof:placetype":"venue"
},
  "geometry": {"coordinates":[6.302887,53.336308],"type":"Point"}
}