{
  "type": "Feature",
  "properties": {
    "iso:country":"NL",
    "sg:address":"Nyverheidswg 57",
    "sg:city":"Woudenberg",
    "sg:orig_category":"Autosleepbedrijven",
    "sg:phone":"+31 33 286 2288",
    "sg:postcode":"3931 CW",
    "sg:province":"Utrecht",
    "wof:name":"Schreuder Bv",
    "wof:placetype":"venue"
},
  "geometry": {"coordinates":[5.430226,52.0812],"type":"Point"}
}