{
  "type": "Feature",
  "properties": {
    "addr:full":"Tiendweg 16 Naaldwijk Zuid-Holland 2671 SB",
    "addr:housenumber":"16",
    "addr:postcode":"2671 sb",
    "addr:street":"Tiendweg",
    "iso:country":"NL",
    "sg:address":"Tiendweg 16",
    "sg:city":"Naaldwijk",
    "sg:orig_category":"Advocaten And Juridische Adviseurs",
    "sg:phone":"+31 174 629 333",
    "sg:postcode":"2671 SB",
    "sg:province":"Zuid-Holland",
    "wof:name":"Advocatenkantoor Everts Bosboom Hiemstra",
    "wof:placetype":"venue"
},
  "geometry": {"coordinates":[4.22079,51.991211],"type":"Point"}
}