{
  "type": "Feature",
  "properties": {
    "iso:country":"NL",
    "sg:address":"Nyverheidstr 14",
    "sg:city":"Edam",
    "sg:orig_category":"Koeltechniek",
    "sg:phone":"+31 299 364 735",
    "sg:postcode":"1135 GE",
    "sg:province":"Noord-Holland",
    "wof:name":"Vema",
    "wof:placetype":"venue"
},
  "geometry": {"coordinates":[5.037062,52.515793],"type":"Point"}
}