{
  "type": "Feature",
  "properties": {
    "addr:full":"C Vosmaerhove 6 Nieuwegein Utrecht 3438 HR",
    "addr:housenumber":"6",
    "addr:postcode":"3438 hr",
    "addr:street":"Vosmaerhove",
    "iso:country":"NL",
    "sg:address":"C Vosmaerhove 6",
    "sg:city":"Nieuwegein",
    "sg:orig_category":"Webdesign Bureaus",
    "sg:phone":"+31 30 603 1744",
    "sg:postcode":"3438 HR",
    "sg:province":"Utrecht",
    "sg:website":"http://www.kalpa.nl",
    "wof:name":"Kalpa",
    "wof:placetype":"venue"
},
  "geometry": {"coordinates":[5.089951992,52.0530471802],"type":"Point"}
}