{
  "type": "Feature",
  "properties": {
    "addr:full":"Singelwg 8 Sauwerd Groningen 9771 BC",
    "addr:housenumber":"8",
    "addr:postcode":"9771 bc",
    "addr:street":"Singelwg",
    "iso:country":"NL",
    "sg:address":"Singelwg 8",
    "sg:city":"Sauwerd",
    "sg:orig_category":"Hoefsmederijen",
    "sg:phone":"+31 50 306 1881",
    "sg:postcode":"9771 BC",
    "sg:province":"Groningen",
    "wof:name":"Wietses, P",
    "wof:placetype":"venue"
},
  "geometry": {"coordinates":[6.526576,53.293221],"type":"Point"}
}