{
  "type": "Feature",
  "properties": {
    "addr:full":"Ringbaan West 211 Tilburg North Brabant 5037 PB",
    "addr:housenumber":"211",
    "addr:postcode":"5037 pb",
    "addr:street":"Ringbaan West",
    "iso:country":"NL",
    "sg:address":"Ringbaan West 211",
    "sg:city":"Tilburg",
    "sg:orig_category":"Huishoudapparatuur, Televisies And Radio'S",
    "sg:phone":"+31 13 467 3787",
    "sg:postcode":"5037 PB",
    "sg:province":"North Brabant",
    "wof:name":"Gvb Geluid",
    "wof:placetype":"venue"
},
  "geometry": {"coordinates":[5.063597,51.555874],"type":"Point"}
}