{
  "type": "Feature",
  "properties": {
    "addr:full":"Minervalaan 44 Rotterdam Zuid-Holland 3054 SL",
    "addr:housenumber":"44",
    "addr:postcode":"3054 sl",
    "addr:street":"Minervalaan",
    "iso:country":"NL",
    "sg:address":"Minervalaan 44",
    "sg:city":"Rotterdam",
    "sg:orig_category":"Paramedische Behandelingen",
    "sg:phone":"+31 10 282 6040",
    "sg:postcode":"3054 SL",
    "sg:province":"Zuid-Holland",
    "wof:name":"Thuiszorg Rotterdam, Onderdeel Thuiszorgcentrum Mi",
    "wof:placetype":"venue"
},
  "geometry": {"coordinates":[4.48968,51.961536],"type":"Point"}
}