{
  "type": "Feature",
  "properties": {
    "addr:full":"Terhoevenderweg 100 Heerlen Limburg 6412 ZJ",
    "addr:housenumber":"100",
    "addr:postcode":"6412 zj",
    "addr:street":"Terhoevenderweg",
    "iso:country":"NL",
    "sg:address":"Terhoevenderweg 100",
    "sg:city":"Heerlen",
    "sg:orig_category":"Autoverhuur",
    "sg:phone":"+31 45 528 0079",
    "sg:postcode":"6412 ZJ",
    "sg:province":"Limburg",
    "wof:name":"Wealer",
    "wof:placetype":"venue"
},
  "geometry": {"coordinates":[5.948628,50.905285],"type":"Point"}
}