{
  "type": "Feature",
  "properties": {
    "addr:full":"Wynstr 241B Dordrecht Zuid-Holland 3311 BV",
    "addr:housenumber":"241b",
    "addr:postcode":"3311 bv",
    "iso:country":"NL",
    "sg:address":"Wynstr 241B",
    "sg:city":"Dordrecht",
    "sg:orig_category":"Adviesbureaus Bouwkunde",
    "sg:phone":"+31 78 613 7420",
    "sg:postcode":"3311 BV",
    "sg:province":"Zuid-Holland",
    "wof:name":"Kamplan Bv",
    "wof:placetype":"venue"
},
  "geometry": {"coordinates":[4.656506,51.811916],"type":"Point"}
}