{
  "type": "Feature",
  "properties": {
    "addr:full":"T Asserln 61 Berkel Enschot Noord-Brabant 5056 VB",
    "addr:housenumber":"61",
    "addr:postcode":"5056 vb",
    "addr:street":"Berkel",
    "iso:country":"NL",
    "sg:address":"T Asserln 61",
    "sg:city":"Berkel Enschot",
    "sg:orig_category":"Artiesten/Gezelschappen",
    "sg:phone":"+31 6 14366636",
    "sg:postcode":"5056 VB",
    "sg:province":"Noord-Brabant",
    "sg:website":"http://www.toonaangevend.com",
    "wof:name":"Toonaangevend",
    "wof:placetype":"venue"
},
  "geometry": {"coordinates":[5.136945,51.57674],"type":"Point"}
}