{
  "type": "Feature",
  "properties": {
    "addr:full":"Ballandstr 17 Dalen Drenthe 7751 CT",
    "addr:housenumber":"17",
    "addr:postcode":"7751 ct",
    "addr:street":"Ballandstr",
    "iso:country":"NL",
    "sg:address":"Ballandstr 17",
    "sg:city":"Dalen",
    "sg:orig_category":"Beeldende Kunstenaars",
    "sg:phone":"+31 524 553 483",
    "sg:postcode":"7751 CT",
    "sg:province":"Drenthe",
    "wof:name":"Verschoor, C A J",
    "wof:placetype":"venue"
},
  "geometry": {"coordinates":[6.751814,52.700214],"type":"Point"}
}