{
  "type": "Feature",
  "properties": {
    "addr:full":"Kerkstr 18A Landgraaf Limburg 6374 HK",
    "addr:housenumber":"18a",
    "addr:postcode":"6374 hk",
    "addr:street":"Kerkstr",
    "iso:country":"NL",
    "sg:address":"Kerkstr 18A",
    "sg:city":"Landgraaf",
    "sg:orig_category":"Zonnebank- En Solariumcentra",
    "sg:phone":"+31 45 532 4260",
    "sg:postcode":"6374 HK",
    "sg:province":"Limburg",
    "wof:name":"Farao",
    "wof:placetype":"venue"
},
  "geometry": {"coordinates":[6.05011,50.917919],"type":"Point"}
}