{
  "type": "Feature",
  "properties": {
    "addr:full":"Brugstraat 2 Breukelen Ut Utrecht 3621 AH",
    "addr:housenumber":"2",
    "addr:postcode":"3621 ah",
    "addr:street":"Brugstraat",
    "iso:country":"NL",
    "sg:address":"Brugstraat 2",
    "sg:city":"Breukelen Ut",
    "sg:classifiers":[
        {
            "category":"Retail",
            "subcategory":"Photofinishing",
            "type":"Services"
        }
    ],
    "sg:phone":"+31 346 261 436",
    "sg:postcode":"3621 AH",
    "sg:province":"Utrecht",
    "sg:tags":[
        "foto",
        "film"
    ],
    "wof:name":"Foto De Graaf",
    "wof:placetype":"venue"
},
  "geometry": {"coordinates":[5.003971,52.171909],"type":"Point"}
}