{
  "type": "Feature",
  "properties": {
    "addr:full":"J A Heywegenln 9 Spykenisse Zuid-Holland 3201 KH",
    "addr:housenumber":"9",
    "addr:postcode":"3201 kh",
    "addr:street":"J A Heywegenln",
    "iso:country":"NL",
    "sg:address":"J A Heywegenln 9",
    "sg:city":"Spykenisse",
    "sg:orig_category":"Bedrijfsopleidingen",
    "sg:phone":"+31 800 0234442",
    "sg:postcode":"3201 KH",
    "sg:province":"Zuid-Holland",
    "sg:website":"http://www.bme.nl",
    "wof:name":"Bme Bv",
    "wof:placetype":"venue"
},
  "geometry": {"coordinates":[4.325045,51.849525],"type":"Point"}
}