{
  "type": "Feature",
  "properties": {
    "iso:country":"NL",
    "sg:address":"V Alphenstr 62",
    "sg:city":"Voorburg",
    "sg:orig_category":"Autoschade- Herstelbedrijven",
    "sg:phone":"+31 70 387 0055",
    "sg:postcode":"2274 NC",
    "sg:province":"South Holland",
    "wof:name":"Oyt",
    "wof:placetype":"venue"
},
  "geometry": {"coordinates":[4.34952,52.073792],"type":"Point"}
}