{
  "type": "Feature",
  "properties": {
    "iso:country":"NL",
    "sg:address":"Prof Aalberseln 2",
    "sg:city":"Voorhout",
    "sg:orig_category":"Artsen - Huisartsen",
    "sg:phone":"+31 252 211 393",
    "sg:postcode":"2215 PK",
    "sg:province":"Zuid-Holland",
    "wof:name":"Boerhaave",
    "wof:placetype":"venue"
},
  "geometry": {"coordinates":[4.484574,52.22142],"type":"Point"}
}