{
  "type": "Feature",
  "properties": {
    "addr:full":"De Wouden 113 Assen Provincie Drenthe 9405 HD",
    "addr:housenumber":"113",
    "addr:postcode":"9405 hd",
    "addr:street":"De Wouden;Provincie Drenthe",
    "iso:country":"NL",
    "sg:address":"De Wouden 113",
    "sg:city":"Assen",
    "sg:orig_category":"Public Relationbureaus",
    "sg:phone":"+31 592 352 905",
    "sg:postcode":"9405 HD",
    "sg:province":"Provincie Drenthe",
    "wof:name":"Willy Bethlehem",
    "wof:placetype":"venue"
},
  "geometry": {"coordinates":[6.529606,52.983685],"type":"Point"}
}