{
  "type": "Feature",
  "properties": {
    "addr:full":"Eindhovenseweg 23 Valkenswaard Noord-Brabant 5554 AA",
    "addr:housenumber":"23",
    "addr:postcode":"5554 aa",
    "addr:street":"Eindhovenseweg",
    "iso:country":"NL",
    "sg:address":"Eindhovenseweg 23",
    "sg:city":"Valkenswaard",
    "sg:orig_category":"Opticiens",
    "sg:phone":"+31 40 201 6998",
    "sg:postcode":"5554 AA",
    "sg:province":"Noord-Brabant",
    "wof:name":"Pearle Opticiens",
    "wof:placetype":"venue"
},
  "geometry": {"coordinates":[5.4593777657,51.3522567749],"type":"Point"}
}