{
  "type": "Feature",
  "properties": {
    "addr:full":"Molenstr 15 Vaassen Gelderland 8171 CE",
    "addr:housenumber":"15",
    "addr:postcode":"8171 ce",
    "addr:street":"Molenstr;Gelderland",
    "iso:country":"NL",
    "sg:address":"Molenstr 15",
    "sg:city":"Vaassen",
    "sg:orig_category":"Verenigingen En Stichtingen",
    "sg:phone":"+31 578 572 715",
    "sg:postcode":"8171 CE",
    "sg:province":"Gelderland",
    "wof:name":"Welzijn Ouderen, Sticht",
    "wof:placetype":"venue"
},
  "geometry": {"coordinates":[5.97054,52.288914],"type":"Point"}
}