{
  "type": "Feature",
  "properties": {
    "addr:full":"Postbus 95 Gaanderen Gelderland 7010 AB",
    "addr:housenumber":"95",
    "addr:postcode":"7010 ab",
    "addr:street":"Postbus;Gelderland",
    "iso:country":"NL",
    "sg:address":"Postbus 95",
    "sg:city":"Gaanderen",
    "sg:orig_category":"Adviesbureaus Bedrijfsveiligheid",
    "sg:phone":"+31 315 324 803",
    "sg:postcode":"7010 AB",
    "sg:province":"Gelderland",
    "wof:name":"Hekman",
    "wof:placetype":"venue"
},
  "geometry": {"coordinates":[6.34412,51.928959],"type":"Point"}
}