{
  "type": "Feature",
  "properties": {
    "addr:full":"Poeyersstr 38 Eindhoven Noord-Brabant 5642 GC",
    "addr:housenumber":"38",
    "addr:postcode":"5642 gc",
    "addr:street":"Poeyersstr",
    "iso:country":"NL",
    "sg:address":"Poeyersstr 38",
    "sg:city":"Eindhoven",
    "sg:orig_category":"Woningstoffeerders",
    "sg:phone":"+31 40 281 2361",
    "sg:postcode":"5642 GC",
    "sg:province":"Noord-Brabant",
    "wof:name":"Nuland, Jos Van",
    "wof:placetype":"venue"
},
  "geometry": {"coordinates":[5.5181097984,51.438419342],"type":"Point"}
}