{
  "type": "Feature",
  "properties": {
    "addr:full":"Brederodeln 26 Papendrecht Zuid-Holland 3353 GG",
    "addr:housenumber":"26",
    "addr:postcode":"3353 gg",
    "addr:street":"Brederodeln",
    "iso:country":"NL",
    "sg:address":"Brederodeln 26",
    "sg:city":"Papendrecht",
    "sg:orig_category":"Opticiens",
    "sg:phone":"+31 78 615 1132",
    "sg:postcode":"3353 GG",
    "sg:province":"Zuid-Holland",
    "sg:website":"http://www.eyewish.nl",
    "wof:name":"Eye Wish Groeneveld",
    "wof:placetype":"venue"
},
  "geometry": {"coordinates":[4.6848688126,51.8262023926],"type":"Point"}
}