{
  "type": "Feature",
  "properties": {
    "addr:full":"Veldmanserve 42 Hellendoorn NL.08 7447 BL",
    "addr:housenumber":"42;nl.08",
    "addr:postcode":"7447 bl",
    "addr:street":"Veldmanserve",
    "iso:country":"NL",
    "sg:address":"Veldmanserve 42",
    "sg:city":"Hellendoorn",
    "sg:orig_category":"Vertalers",
    "sg:phone":"+31 548 656 510",
    "sg:postcode":"7447 BL",
    "sg:province":"NL.08",
    "wof:name":"Avh",
    "wof:placetype":"venue"
},
  "geometry": {"coordinates":[6.448955,52.395958],"type":"Point"}
}