{
  "type": "Feature",
  "properties": {
    "addr:full":"Schakel 70 Loosdrecht North Holland 1231 SZ",
    "addr:housenumber":"70",
    "addr:postcode":"1231 sz",
    "addr:street":"Schakel",
    "iso:country":"NL",
    "sg:address":"Schakel 70",
    "sg:city":"Loosdrecht",
    "sg:orig_category":"Adviesbureaus Elektrotechniek",
    "sg:phone":"+31 35 582 6146",
    "sg:postcode":"1231 SZ",
    "sg:province":"North Holland",
    "wof:name":"Dml",
    "wof:placetype":"venue"
},
  "geometry": {"coordinates":[5.13575,52.196808],"type":"Point"}
}