{
  "type": "Feature",
  "properties": {
    "addr:full":"Veldhovenring 27 Tilburg Noord-Brabant 5041 BA",
    "addr:housenumber":"27",
    "addr:postcode":"5041 ba",
    "addr:street":"Veldhovenring",
    "iso:country":"NL",
    "sg:address":"Veldhovenring 27",
    "sg:city":"Tilburg",
    "sg:orig_category":"Verenigingen En Stichtingen",
    "sg:phone":"+31 13 543 6541",
    "sg:postcode":"5041 BA",
    "sg:province":"Noord-Brabant",
    "wof:name":"Natuurhistorische Ver, Kon Ned",
    "wof:placetype":"venue"
},
  "geometry": {"coordinates":[5.087378,51.567856],"type":"Point"}
}