{
  "type": "Feature",
  "properties": {
    "addr:full":"Zuidlaarderwg 83 Annen South Carolina 9468 AD",
    "addr:housenumber":"83;9468",
    "addr:postcode":"ad",
    "addr:street":"Zuidlaarderwg",
    "iso:country":"NL",
    "sg:address":"Zuidlaarderwg 83",
    "sg:city":"Annen",
    "sg:orig_category":"Warenhuizen",
    "sg:phone":"+31 592 272 380",
    "sg:postcode":"9468 AD",
    "sg:province":"South Carolina",
    "wof:name":"Inloop Warenhuis Bv",
    "wof:placetype":"venue"
},
  "geometry": {"coordinates":[-79.2538146973,33.4712333679],"type":"Point"}
}