{
  "type": "Feature",
  "properties": {
    "addr:full":"Willemsparkwg 138 Amsterdam Noord-Holland 1071 HR",
    "addr:housenumber":"138",
    "addr:postcode":"1071 hr",
    "iso:country":"NL",
    "sg:address":"Willemsparkwg 138",
    "sg:city":"Amsterdam",
    "sg:classifiers":[
        {
            "category":"Travel",
            "subcategory":"Hotels & Motels",
            "type":"Entertainment"
        }
    ],
    "sg:phone":"+31 20 671 4093",
    "sg:postcode":"1071 HR",
    "sg:province":"Noord-Holland",
    "wof:name":"Hotel, L'",
    "wof:placetype":"venue"
},
  "geometry": {"coordinates":[4.871798,52.356468],"type":"Point"}
}