{
  "type": "Feature",
  "properties": {
    "iso:country":"NL",
    "sg:address":"Oudegr 288",
    "sg:city":"Utrecht",
    "sg:orig_category":"Psychotherapeuten",
    "sg:phone":"+31 30 231 9181",
    "sg:postcode":"3511 NW",
    "sg:province":"Utrecht",
    "wof:name":"Psychotherapiepraktijk",
    "wof:placetype":"venue"
},
  "geometry": {"coordinates":[5.115405,52.088932],"type":"Point"}
}