{
  "type": "Feature",
  "properties": {
    "addr:full":"Stationswg O 269 Woudenberg Utrecht 3931 ER",
    "addr:housenumber":"269",
    "addr:postcode":"3931 er",
    "iso:country":"NL",
    "sg:address":"Stationswg O 269",
    "sg:city":"Woudenberg",
    "sg:classifiers":[
        {
            "category":"Retail",
            "subcategory":"Auto Repair",
            "type":"Services"
        }
    ],
    "sg:phone":"+31 33 286 1808",
    "sg:postcode":"3931 ER",
    "sg:province":"Utrecht",
    "sg:tags":[
        "garage"
    ],
    "wof:name":"Veenvliet, A C",
    "wof:placetype":"venue"
},
  "geometry": {"coordinates":[5.452951,52.081017],"type":"Point"}
}