{
  "type": "Feature",
  "properties": {
    "iso:country":"NL",
    "sg:address":"Sint - Josephstraat 31",
    "sg:city":"Bergen Op Zoom",
    "sg:orig_category":"Verzekeringen",
    "sg:phone":"+31 164 252 525",
    "sg:postcode":"4611 MJ",
    "sg:province":"Noord-Brabant",
    "wof:name":"Oz Zorgverzekeringen",
    "wof:placetype":"venue"
},
  "geometry": {"coordinates":[4.291858,51.494396],"type":"Point"}
}