{
  "type": "Feature",
  "properties": {
    "addr:full":"Rijnstraat 559 'S Hertogenbosch Noord-Brabant 5215 EJ",
    "addr:housenumber":"559 ' s",
    "addr:postcode":"5215 ej",
    "addr:street":"Rijnstraat",
    "iso:country":"NL",
    "sg:address":"Rijnstraat 559",
    "sg:city":"'S Hertogenbosch",
    "sg:orig_category":"Kinderopvang Behalve Thuis",
    "sg:phone":"+31 73 612 5282",
    "sg:postcode":"5215 EJ",
    "sg:province":"Noord-Brabant",
    "wof:name":"Peuterspeelzaal Zonnelicht",
    "wof:placetype":"venue"
},
  "geometry": {"coordinates":[5.333958,51.690315],"type":"Point"}
}