{
  "type": "Feature",
  "properties": {
    "addr:full":"Gasthuisstr 17 Kaatsheuvel North Brabant 5171 GC",
    "addr:housenumber":"17",
    "addr:postcode":"5171 gc",
    "addr:street":"Gasthuisstr",
    "iso:country":"NL",
    "sg:address":"Gasthuisstr 17",
    "sg:city":"Kaatsheuvel",
    "sg:orig_category":"Fietsen En Bromfietsen",
    "sg:phone":"+31 416 283 084",
    "sg:postcode":"5171 GC",
    "sg:province":"North Brabant",
    "sg:website":"http://www.ryanpost.nl",
    "wof:name":"Ryan Post Profile",
    "wof:placetype":"venue"
},
  "geometry": {"coordinates":[5.035079,51.659309],"type":"Point"}
}