{
  "type": "Feature",
  "properties": {
    "addr:full":"Utrechtsewg 164 Oosterbeek Gelderland 6862 AT",
    "addr:housenumber":"164",
    "addr:postcode":"6862",
    "addr:street":"Gelderland",
    "iso:country":"NL",
    "sg:address":"Utrechtsewg 164",
    "sg:city":"Oosterbeek",
    "sg:orig_category":"Glas, Porselein En Aardewerk",
    "sg:phone":"+31 26 339 2809",
    "sg:postcode":"6862 AT",
    "sg:province":"Gelderland",
    "sg:website":"http://www.glorieinterieurobjecten.nl",
    "wof:name":"Glorie, De",
    "wof:placetype":"venue"
},
  "geometry": {"coordinates":[5.843331,51.987152],"type":"Point"}
}