{
  "type": "Feature",
  "properties": {
    "addr:full":"Loenensewg 121 Eerbeek Gelderland 6961 CP",
    "addr:housenumber":"121",
    "addr:postcode":"6961 cp",
    "addr:street":"Gelderland",
    "iso:country":"NL",
    "sg:address":"Loenensewg 121",
    "sg:city":"Eerbeek",
    "sg:orig_category":"Administratie- En Boekhoudkantoren",
    "sg:phone":"+31 313 653 320",
    "sg:postcode":"6961 CP",
    "sg:province":"Gelderland",
    "wof:name":"Mensink",
    "wof:placetype":"venue"
},
  "geometry": {"coordinates":[6.05039,52.105732],"type":"Point"}
}