{
  "type": "Feature",
  "properties": {
    "iso:country":"NL",
    "sg:address":"Grensstraat 9",
    "sg:city":"'S Heerenberg",
    "sg:orig_category":"Meubelzaken, Woning- And Keukeninrichting",
    "sg:phone":"+31 314 650 361",
    "sg:postcode":"7041 GZ",
    "sg:province":"Gelderland",
    "wof:name":"Arena International Meubelagenturen Bv",
    "wof:placetype":"venue"
},
  "geometry": {"coordinates":[6.262744,51.869923],"type":"Point"}
}