{
  "type": "Feature",
  "properties": {
    "addr:full":"Ternatestr 15 Haarlem Noord-Holland 2022 BT",
    "addr:housenumber":"15",
    "addr:postcode":"2022 bt",
    "addr:street":"Ternatestr",
    "iso:country":"NL",
    "sg:address":"Ternatestr 15",
    "sg:city":"Haarlem",
    "sg:orig_category":"Directmail",
    "sg:phone":"+31 23 526 9880",
    "sg:postcode":"2022 BT",
    "sg:province":"Noord-Holland",
    "wof:name":"Wal, J Van Der",
    "wof:placetype":"venue"
},
  "geometry": {"coordinates":[4.64677,52.398495],"type":"Point"}
}