{
  "type": "Feature",
  "properties": {
    "addr:full":"O Nassauln 25 Maarheeze Noord-Brabant 6026 BW",
    "addr:housenumber":"25",
    "addr:postcode":"6026 bw",
    "iso:country":"NL",
    "sg:address":"O Nassauln 25",
    "sg:city":"Maarheeze",
    "sg:classifiers":[
        {
            "category":"Professional",
            "subcategory":"Accounting & Tax Preparation",
            "type":"Services"
        }
    ],
    "sg:phone":"+31 495 599 022",
    "sg:postcode":"6026 BW",
    "sg:province":"Noord-Brabant",
    "sg:tags":[
        "accountant",
        "en",
        "-kantoren",
        "register-"
    ],
    "wof:name":"Retera Accountants",
    "wof:placetype":"venue"
},
  "geometry": {"coordinates":[5.615365,51.312126],"type":"Point"}
}