{
  "type": "Feature",
  "properties": {
    "addr:full":"De Tunen 1 Witmarsum Provincie Friesland 8748 EG",
    "addr:housenumber":"1",
    "addr:postcode":"8748 eg",
    "addr:street":"De Tunen;Provincie Friesland",
    "iso:country":"NL",
    "sg:address":"De Tunen 1",
    "sg:city":"Witmarsum",
    "sg:orig_category":"Zonweringen",
    "sg:phone":"+31 517 531 557",
    "sg:postcode":"8748 EG",
    "sg:province":"Provincie Friesland",
    "sg:website":"http://www.nnzi.nl",
    "wof:name":"Nrd Ned Zonwering Ind Bv",
    "wof:placetype":"venue"
},
  "geometry": {"coordinates":[5.473185,53.108173],"type":"Point"}
}