{
  "type": "Feature",
  "properties": {
    "addr:full":"De Vlyt 28A Bedum Groningen 9781 NR",
    "addr:housenumber":"28a",
    "addr:postcode":"9781 nr",
    "addr:street":"Bedum",
    "iso:country":"NL",
    "sg:address":"De Vlyt 28A",
    "sg:city":"Bedum",
    "sg:orig_category":"Tekstschrijversters",
    "sg:phone":"+31 50 301 0787",
    "sg:postcode":"9781 NR",
    "sg:province":"Groningen",
    "wof:name":"Texpert",
    "wof:placetype":"venue"
},
  "geometry": {"coordinates":[6.610038,53.301044],"type":"Point"}
}