{
  "type": "Feature",
  "properties": {
    "addr:full":"Wittenburgergracht 71 Amsterdam Noord-Holland 1018 MX",
    "addr:housenumber":"71",
    "addr:postcode":"1018 mx",
    "addr:street":"Wittenburgergracht",
    "iso:country":"NL",
    "sg:address":"Wittenburgergracht 71",
    "sg:city":"Amsterdam",
    "sg:orig_category":"Binnenhuisarchitecten",
    "sg:phone":"+31 20 622 7452",
    "sg:postcode":"1018 MX",
    "sg:province":"Noord-Holland",
    "wof:name":"A.B. Vonk-Versnel",
    "wof:placetype":"venue"
},
  "geometry": {"coordinates":[4.919019,52.369926],"type":"Point"}
}