{
  "type": "Feature",
  "properties": {
    "addr:full":"Simon De Cockstraat 4 Tilburg Noord-Brabant 5048 AW",
    "addr:housenumber":"4",
    "addr:postcode":"5048 aw",
    "addr:street":"Simon De Cockstraat",
    "iso:country":"NL",
    "sg:address":"Simon De Cockstraat 4",
    "sg:city":"Tilburg",
    "sg:orig_category":"Airconditioning And Ventilatie",
    "sg:phone":"+31 13 463 0730",
    "sg:postcode":"5048 AW",
    "sg:province":"Noord-Brabant",
    "wof:name":"Mzn",
    "wof:placetype":"venue"
},
  "geometry": {"coordinates":[5.051231,51.591331],"type":"Point"}
}