{
  "type": "Feature",
  "properties": {
    "addr:full":"Jan Hamdorfflaan 30 Laren Nh Noord-Holland 1251 NM",
    "addr:housenumber":"30",
    "addr:postcode":"1251",
    "addr:street":"Jan Hamdorfflaan",
    "iso:country":"NL",
    "sg:address":"Jan Hamdorfflaan 30",
    "sg:city":"Laren Nh",
    "sg:orig_category":"Boekhouders",
    "sg:phone":"+31 35 531 0814",
    "sg:postcode":"1251 NM",
    "sg:province":"Noord-Holland",
    "wof:name":"Leidy Van Spanje Administratiekantoor",
    "wof:placetype":"venue"
},
  "geometry": {"coordinates":[5.24236,52.252048],"type":"Point"}
}