{
  "type": "Feature",
  "properties": {
    "addr:full":"Wilhelminaplnts 1 Bussum North Holland 1404 JA",
    "addr:housenumber":"1",
    "addr:postcode":"1404 ja",
    "addr:street":"Wilhelminaplnts",
    "iso:country":"NL",
    "sg:address":"Wilhelminaplnts 1",
    "sg:city":"Bussum",
    "sg:orig_category":"Juweliers",
    "sg:phone":"+31 35 691 4597",
    "sg:postcode":"1404 JA",
    "sg:province":"North Holland",
    "wof:name":"Geerling, Jos",
    "wof:placetype":"venue"
},
  "geometry": {"coordinates":[5.162605,52.276829],"type":"Point"}
}