{
  "type": "Feature",
  "properties": {
    "addr:full":"De Hanekampen 38 Beilen Drenthe 9411 XM",
    "addr:housenumber":"38",
    "addr:postcode":"9411 xm",
    "addr:street":"De Hanekampen",
    "iso:country":"NL",
    "sg:address":"De Hanekampen 38",
    "sg:city":"Beilen",
    "sg:orig_category":"Schilderwerk",
    "sg:phone":"+31 593 540 555",
    "sg:postcode":"9411 XM",
    "sg:province":"Drenthe",
    "wof:name":"Sommer Schilderwerken Bv",
    "wof:placetype":"venue"
},
  "geometry": {"coordinates":[6.516025,52.857738],"type":"Point"}
}