{
  "type": "Feature",
  "properties": {
    "addr:full":"Schotersingel 109 Haarlem North Holland 2023 AA",
    "addr:housenumber":"109",
    "addr:postcode":"2023 aa",
    "addr:street":"Schotersingel",
    "iso:country":"NL",
    "sg:address":"Schotersingel 109",
    "sg:city":"Haarlem",
    "sg:orig_category":"Architecten",
    "sg:phone":"+31 23 526 4476",
    "sg:postcode":"2023 AA",
    "sg:province":"North Holland",
    "wof:name":"Plan Architekten Bv",
    "wof:placetype":"venue"
},
  "geometry": {"coordinates":[4.63278,52.390175],"type":"Point"}
}