{
  "type": "Feature",
  "properties": {
    "addr:full":"Groenewg 3 Bunde Limburg 6241 NW",
    "addr:housenumber":"3",
    "addr:postcode":"6241 nw",
    "addr:street":"Groenewg",
    "iso:country":"NL",
    "sg:address":"Groenewg 3",
    "sg:city":"Bunde",
    "sg:orig_category":"Verbouwingen",
    "sg:phone":"+31 6 21566210",
    "sg:postcode":"6241 NW",
    "sg:province":"Limburg",
    "wof:name":"Gerits",
    "wof:placetype":"venue"
},
  "geometry": {"coordinates":[8.57966,52.196812],"type":"Point"}
}