{
  "type": "Feature",
  "properties": {
    "addr:full":"Westhavenkade 48 Vlaardingen Zuid-Holland 3131 AE",
    "addr:housenumber":"48",
    "addr:postcode":"3131 ae",
    "addr:street":"Westhavenkade",
    "iso:country":"NL",
    "sg:address":"Westhavenkade 48",
    "sg:city":"Vlaardingen",
    "sg:orig_category":"Verlichting And Huishoudartikelen",
    "sg:phone":"+31 10 248 9364",
    "sg:postcode":"3131 AE",
    "sg:province":"Zuid-Holland",
    "wof:name":"Verlichting Interieur Dibo",
    "wof:placetype":"venue"
},
  "geometry": {"coordinates":[4.345017,51.906113],"type":"Point"}
}