{
  "type": "Feature",
  "properties": {
    "addr:full":"Hoefweg 45 Bleiswijk South Holland 2665 CB",
    "addr:housenumber":"45",
    "addr:postcode":"2665 cb",
    "addr:street":"Hoefweg",
    "iso:country":"NL",
    "sg:address":"Hoefweg 45",
    "sg:city":"Bleiswijk",
    "sg:orig_category":"Boekhouders",
    "sg:phone":"+31 10 529 6161",
    "sg:postcode":"2665 CB",
    "sg:province":"South Holland",
    "wof:name":"Joh. Fr. Koene Bleiswijk Adm Dienstverle",
    "wof:placetype":"venue"
},
  "geometry": {"coordinates":[4.532148,52.014481],"type":"Point"}
}