{
  "type": "Feature",
  "properties": {
    "addr:full":"Langestr 172 Klazienaveen Drenthe 7891 GL",
    "addr:housenumber":"172",
    "addr:postcode":"7891 gl",
    "iso:country":"NL",
    "sg:address":"Langestr 172",
    "sg:city":"Klazienaveen",
    "sg:orig_category":"Autorijscholen",
    "sg:phone":"+31 591 312 877",
    "sg:postcode":"7891 GL",
    "sg:province":"Drenthe",
    "wof:name":"Ophof, G",
    "wof:placetype":"venue"
},
  "geometry": {"coordinates":[7.002274,52.724033],"type":"Point"}
}