{
  "type": "Feature",
  "properties": {
    "addr:full":"Laarmanhof 11 Haren Gn Groningen 9751 NT",
    "addr:housenumber":"11",
    "addr:postcode":"9751 nt",
    "addr:street":"Laarmanhof",
    "iso:country":"NL",
    "sg:address":"Laarmanhof 11",
    "sg:city":"Haren Gn",
    "sg:orig_category":"Webdesign Bureaus",
    "sg:phone":"+31 50 534 0067",
    "sg:postcode":"9751 NT",
    "sg:province":"Groningen",
    "sg:website":"http://www.rjswebs.com",
    "wof:name":"Rj",
    "wof:placetype":"venue"
},
  "geometry": {"coordinates":[6.6062541008,53.1784553528],"type":"Point"}
}