{
  "type": "Feature",
  "properties": {
    "iso:country":"NL",
    "sg:address":"Rendementsweg 8",
    "sg:city":"Mijdrecht",
    "sg:orig_category":"Goederenvervoer Over De Weg",
    "sg:phone":"+31 297 281 698",
    "sg:postcode":"3641 SK",
    "sg:province":"Utrecht",
    "wof:name":"Leliveld Transport Bv",
    "wof:placetype":"venue"
},
  "geometry": {"coordinates":[4.884165,52.207298],"type":"Point"}
}