{
  "type": "Feature",
  "properties": {
    "addr:full":"Helmersstr 18 Gouda South Holland 2802 ND",
    "addr:housenumber":"18",
    "addr:postcode":"2802 nd",
    "addr:street":"Helmersstr",
    "iso:country":"NL",
    "sg:address":"Helmersstr 18",
    "sg:city":"Gouda",
    "sg:orig_category":"Leesportefeuilles",
    "sg:phone":"+31 182 511 826",
    "sg:postcode":"2802 ND",
    "sg:province":"South Holland",
    "wof:name":"Zanen, Van",
    "wof:placetype":"venue"
},
  "geometry": {"coordinates":[4.703305,52.004059],"type":"Point"}
}