{
  "type": "Feature",
  "properties": {
    "addr:full":"Punterwg 31 Maastricht Limburg 6222 NW",
    "addr:housenumber":"31",
    "addr:postcode":"6222 nw",
    "addr:street":"Punterwg",
    "iso:country":"NL",
    "sg:address":"Punterwg 31",
    "sg:city":"Maastricht",
    "sg:orig_category":"Koeltechniek",
    "sg:phone":"+31 43 369 0418",
    "sg:postcode":"6222 NW",
    "sg:province":"Limburg",
    "wof:name":"Imtech Maintenance Zuid Bv",
    "wof:placetype":"venue"
},
  "geometry": {"coordinates":[5.711261,50.876923],"type":"Point"}
}