{
  "type": "Feature",
  "properties": {
    "addr:full":"A Toscaninistr 47 Almere Flevoland 1311 KR",
    "addr:housenumber":"47",
    "addr:postcode":"1311 kr",
    "addr:street":"Flevoland",
    "iso:country":"NL",
    "sg:address":"A Toscaninistr 47",
    "sg:city":"Almere",
    "sg:orig_category":"Adviesbureaus Bouwkunde",
    "sg:phone":"+31 36 546 5455",
    "sg:postcode":"1311 KR",
    "sg:province":"Flevoland",
    "wof:name":"Bruijn Vof, R P De",
    "wof:placetype":"venue"
},
  "geometry": {"coordinates":[5.175504,52.370811],"type":"Point"}
}