{
  "type": "Feature",
  "properties": {
    "iso:country":"NL",
    "sg:address":"Hoge Zandschel 21",
    "sg:city":"Sprang-Capelle",
    "sg:orig_category":"Schoenen",
    "sg:phone":"+31 416 311 420",
    "sg:postcode":"5161 RL",
    "sg:province":"Noord-Brabant",
    "wof:name":"Joh. Wervers",
    "wof:placetype":"venue"
},
  "geometry": {"coordinates":[4.988306,51.662754],"type":"Point"}
}