{
  "type": "Feature",
  "properties": {
    "addr:full":"Klapstr 45A Arnhem Gelderland 6842 AC",
    "addr:housenumber":"45a",
    "addr:postcode":"6842 ac",
    "addr:street":"Klapstr",
    "iso:country":"NL",
    "sg:address":"Klapstr 45A",
    "sg:city":"Arnhem",
    "sg:orig_category":"Fietsen En Bromfietsen",
    "sg:phone":"+31 26 383 1832",
    "sg:postcode":"6842 AC",
    "sg:province":"Gelderland",
    "wof:name":"Fiets Totaal Elden",
    "wof:placetype":"venue"
},
  "geometry": {"coordinates":[5.87795,51.960209],"type":"Point"}
}