{
  "type": "Feature",
  "properties": {
    "addr:full":"Heemraadssngl 241 Rotterdam South Holland 3023 CD",
    "addr:housenumber":"241",
    "addr:postcode":"3023 cd",
    "iso:country":"NL",
    "sg:address":"Heemraadssngl 241",
    "sg:city":"Rotterdam",
    "sg:orig_category":"Adviesbureaus Bouwkunde",
    "sg:phone":"+31 10 251 9776",
    "sg:postcode":"3023 CD",
    "sg:province":"South Holland",
    "wof:name":"Bouwfysica",
    "wof:placetype":"venue"
},
  "geometry": {"coordinates":[4.454155,51.915035],"type":"Point"}
}