{
  "type": "Feature",
  "properties": {
    "iso:country":"NL",
    "sg:address":"Ln V Nw O Indie 252",
    "sg:city":"S Gravenhage",
    "sg:orig_category":"Woningbureaus",
    "sg:phone":"+31 70 382 2733",
    "sg:postcode":"2593 CD",
    "sg:province":"South Holland",
    "wof:name":"Roomservice",
    "wof:placetype":"venue"
},
  "geometry": {"coordinates":[4.3426599503,52.0861206055],"type":"Point"}
}