{
  "type": "Feature",
  "properties": {
    "addr:full":"Karpaten 62 Utrecht Utrecht 3524 DE",
    "addr:housenumber":"62",
    "addr:postcode":"3524 de",
    "addr:street":"Karpaten",
    "iso:country":"NL",
    "sg:address":"Karpaten 62",
    "sg:city":"Utrecht",
    "sg:orig_category":"Adviesbureaus Elektronica",
    "sg:phone":"+31 30 267 1017",
    "sg:postcode":"3524 DE",
    "sg:province":"Utrecht",
    "sg:website":"http://www.vanmuiswinkel.nl",
    "wof:name":"Muiswinkel Consultancy, Van",
    "wof:placetype":"venue"
},
  "geometry": {"coordinates":[5.133317,52.066345],"type":"Point"}
}