{
  "type": "Feature",
  "properties": {
    "iso:country":"NL",
    "sg:address":"Paulus Potterlaan 10",
    "sg:city":"Capelle A/D Ijssel",
    "sg:orig_category":"Bedrijfs- And Managementsconsultants",
    "sg:phone":"+31 10 451 4588",
    "sg:postcode":"2902 GP",
    "sg:province":"South Holland",
    "wof:name":"Van Holst & Koppies",
    "wof:placetype":"venue"
},
  "geometry": {"coordinates":[4.581867,51.926193],"type":"Point"}
}