{
  "type": "Feature",
  "properties": {
    "addr:full":"Karel Doormanstraat 273A Rotterdam Zuid-Holland 3012 GH",
    "addr:housenumber":"273a",
    "addr:postcode":"3012 gh",
    "addr:street":"Karel Doormanstraat",
    "iso:country":"NL",
    "sg:address":"Karel Doormanstraat 273A",
    "sg:city":"Rotterdam",
    "sg:orig_category":"Fotografie Reclame En Mode",
    "sg:phone":"+31 6 55186300",
    "sg:postcode":"3012 GH",
    "sg:province":"Zuid-Holland",
    "wof:name":"Robofoto",
    "wof:placetype":"venue"
},
  "geometry": {"coordinates":[4.474899,51.919823],"type":"Point"}
}