{
  "type": "Feature",
  "properties": {
    "iso:country":"NL",
    "sg:address":"Opstalwg 31",
    "sg:city":"Naaldwyk",
    "sg:orig_category":"Onderhoudswerken",
    "sg:phone":"+31 174 627 459",
    "sg:postcode":"2671 LX",
    "sg:province":"Zuid-Holland",
    "wof:name":"Maat Bv, M C",
    "wof:placetype":"venue"
},
  "geometry": {"coordinates":[4.192023,51.995651],"type":"Point"}
}