{
  "type": "Feature",
  "properties": {
    "addr:full":"Zuidhollandsedijk 53 Kaatsheuvel Noord-Brabant 5171 TK",
    "addr:housenumber":"53",
    "addr:postcode":"5171 tk",
    "addr:street":"Zuidhollandsedijk",
    "iso:country":"NL",
    "sg:address":"Zuidhollandsedijk 53",
    "sg:city":"Kaatsheuvel",
    "sg:orig_category":"Paramedische Behandelingen",
    "sg:phone":"+31 416 273 666",
    "sg:postcode":"5171 TK",
    "sg:province":"Noord-Brabant",
    "wof:name":"Verloskundigen Praktijk Bollebuik",
    "wof:placetype":"venue"
},
  "geometry": {"coordinates":[5.01419,51.670654],"type":"Point"}
}