{
  "type": "Feature",
  "properties": {
    "iso:country":"NL",
    "sg:address":"Scheldestr 24",
    "sg:city":"Breda",
    "sg:orig_category":"Beeldende Kunstenaars",
    "sg:phone":"+31 76 520 2873",
    "sg:postcode":"4812 VK",
    "sg:province":"North Brabant",
    "wof:name":"Mutsers, Hans",
    "wof:placetype":"venue"
},
  "geometry": {"coordinates":[4.760731,51.581291],"type":"Point"}
}