{
  "type": "Feature",
  "properties": {
    "addr:full":"St Annaln 3A Maastricht Limburg 6214 AA",
    "addr:housenumber":"3a",
    "addr:postcode":"6214 aa",
    "iso:country":"NL",
    "sg:address":"St Annaln 3A",
    "sg:city":"Maastricht",
    "sg:orig_category":"Biljartzalen",
    "sg:phone":"+31 43 325 8224",
    "sg:postcode":"6214 AA",
    "sg:province":"Limburg",
    "wof:name":"Fantasia",
    "wof:placetype":"venue"
},
  "geometry": {"coordinates":[5.676647,50.849083],"type":"Point"}
}