{
  "type": "Feature",
  "properties": {
    "addr:full":"Hyacinthstr 17 Groningen Groningen 9713 XA",
    "addr:housenumber":"17",
    "addr:postcode":"9713 xa",
    "addr:street":"Hyacinthstr",
    "iso:country":"NL",
    "sg:address":"Hyacinthstr 17",
    "sg:city":"Groningen",
    "sg:orig_category":"Houtdraaierijen",
    "sg:phone":"+31 50 312 1778",
    "sg:postcode":"9713 XA",
    "sg:province":"Groningen",
    "wof:name":"Veenstra",
    "wof:placetype":"venue"
},
  "geometry": {"coordinates":[6.591762,53.22459],"type":"Point"}
}