{
  "type": "Feature",
  "properties": {
    "addr:full":"Holleblok 14 Huizen North Holland 1273 EG",
    "addr:housenumber":"14",
    "addr:postcode":"1273 eg",
    "addr:street":"Holleblok",
    "iso:country":"NL",
    "sg:address":"Holleblok 14",
    "sg:city":"Huizen",
    "sg:classifiers":[
        {
            "category":"Communications",
            "subcategory":"Television Station",
            "type":"Services"
        }
    ],
    "sg:phone":"+31 35 526 0886",
    "sg:postcode":"1273 EG",
    "sg:province":"North Holland",
    "sg:tags":[
        "video",
        "audio",
        "verhuur"
    ],
    "wof:name":"Videoworld",
    "wof:placetype":"venue"
},
  "geometry": {"coordinates":[5.252985,52.302078],"type":"Point"}
}