{
  "type": "Feature",
  "properties": {
    "addr:full":"Huibersakker 56 Zaltbommel Gelderland 5301 WZ",
    "addr:housenumber":"56",
    "addr:postcode":"5301 wz",
    "addr:street":"Huibersakker;Gelderland",
    "iso:country":"NL",
    "sg:address":"Huibersakker 56",
    "sg:city":"Zaltbommel",
    "sg:orig_category":"Poppen En Poppenhuismaterialen",
    "sg:phone":"+31 418 514 156",
    "sg:postcode":"5301 WZ",
    "sg:province":"Gelderland",
    "wof:name":"Little Cupido",
    "wof:placetype":"venue"
},
  "geometry": {"coordinates":[5.237552,51.80402],"type":"Point"}
}