{
  "type": "Feature",
  "properties": {
    "addr:full":"Pryssewg 71 Culemborg Gelderland 4105 LE",
    "addr:housenumber":"71",
    "addr:postcode":"4105 le",
    "addr:street":"Pryssewg;Gelderland",
    "iso:country":"NL",
    "sg:address":"Pryssewg 71",
    "sg:city":"Culemborg",
    "sg:orig_category":"Scholen Voor Basisonderwijs",
    "sg:phone":"+31 345 511 672",
    "sg:postcode":"4105 LE",
    "sg:province":"Gelderland",
    "wof:name":"Anansi",
    "wof:placetype":"venue"
},
  "geometry": {"coordinates":[5.207221,51.94989],"type":"Point"}
}