{
  "type": "Feature",
  "properties": {
    "addr:full":"Molenrak 23 Zeewolde NL. 3891 EK",
    "addr:housenumber":"23",
    "addr:postcode":"3891 ek",
    "addr:street":"Molenrak;Nl.",
    "iso:country":"NL",
    "sg:address":"Molenrak 23",
    "sg:city":"Zeewolde",
    "sg:orig_category":"Journalisten Freelance",
    "sg:phone":"+31 36 522 1403",
    "sg:postcode":"3891 EK",
    "sg:province":"NL.",
    "wof:name":"Vos, R",
    "wof:placetype":"venue"
},
  "geometry": {"coordinates":[5.541646,52.334106],"type":"Point"}
}