{
  "type": "Feature",
  "properties": {
    "addr:full":"Ringweg 18 Heiloo North Holland 1852 CM",
    "addr:housenumber":"18",
    "addr:postcode":"1852 cm",
    "addr:street":"Ringweg",
    "iso:country":"NL",
    "sg:address":"Ringweg 18",
    "sg:city":"Heiloo",
    "sg:orig_category":"Vertaal- And Tolkenbureaus",
    "sg:phone":"+31 72 533 3842",
    "sg:postcode":"1852 CM",
    "sg:province":"North Holland",
    "wof:name":"Vertaalbureau Ulot Bv",
    "wof:placetype":"venue"
},
  "geometry": {"coordinates":[4.697315,52.605137],"type":"Point"}
}