{
  "type": "Feature",
  "properties": {
    "addr:full":"Duboisdomein 50 Maastricht Limburg 6229 GT",
    "addr:housenumber":"50",
    "addr:postcode":"6229 gt",
    "addr:street":"Duboisdomein",
    "iso:country":"NL",
    "sg:address":"Duboisdomein 50",
    "sg:city":"Maastricht",
    "sg:orig_category":"Banken And Kredietinstellingen",
    "sg:phone":"+31 43 367 2273",
    "sg:postcode":"6229 GT",
    "sg:province":"Limburg",
    "wof:name":"Postkantoor",
    "wof:placetype":"venue"
},
  "geometry": {"coordinates":[5.708876,50.839046],"type":"Point"}
}