{
  "type": "Feature",
  "properties": {
    "addr:full":"Pr Irenestr 65 Huizen Noord-Holland 1271 XT",
    "addr:housenumber":"65",
    "addr:postcode":"1271 xt",
    "iso:country":"NL",
    "sg:address":"Pr Irenestr 65",
    "sg:city":"Huizen",
    "sg:orig_category":"Verenigingen En Stichtingen",
    "sg:phone":"+31 35 526 8927",
    "sg:postcode":"1271 XT",
    "sg:province":"Noord-Holland",
    "wof:name":"Active Refugee Care, Sticht",
    "wof:placetype":"venue"
},
  "geometry": {"coordinates":[5.233915,52.305092],"type":"Point"}
}