{
  "type": "Feature",
  "properties": {
    "addr:full":"Middelwg 7 Numansdorp South Holland 3281 KH",
    "addr:housenumber":"7",
    "addr:postcode":"3281 kh",
    "addr:street":"Middelwg",
    "iso:country":"NL",
    "sg:address":"Middelwg 7",
    "sg:city":"Numansdorp",
    "sg:orig_category":"Verloskundigen",
    "sg:phone":"+31 186 651 362",
    "sg:postcode":"3281 KH",
    "sg:province":"South Holland",
    "wof:name":"Duna Lus",
    "wof:placetype":"venue"
},
  "geometry": {"coordinates":[4.440274,51.734707],"type":"Point"}
}