{
  "type": "Feature",
  "properties": {
    "addr:full":"Baanvak 14 Aalsmeer North Holland 1431 LK",
    "addr:housenumber":"14",
    "addr:postcode":"1431 lk",
    "addr:street":"Baanvak",
    "iso:country":"NL",
    "sg:address":"Baanvak 14",
    "sg:city":"Aalsmeer",
    "sg:classifiers":[
        {
            "category":"Professional",
            "subcategory":"Management & Consulting",
            "type":"Services"
        }
    ],
    "sg:phone":"+31 297 340 834",
    "sg:postcode":"1431 LK",
    "sg:province":"North Holland",
    "sg:tags":[
        "relation",
        "adviesbureaus",
        "public"
    ],
    "sg:website":"http://www.e-motion.nl",
    "wof:name":"E-Motion",
    "wof:placetype":"venue"
},
  "geometry": {"coordinates":[4.754435,52.265724],"type":"Point"}
}