{
  "type": "Feature",
  "properties": {
    "addr:full":"Postbus 72 Sliedrecht Zuid-Holland 3360 AB",
    "addr:housenumber":"72",
    "addr:postcode":"3360 ab",
    "addr:street":"Postbus",
    "iso:country":"NL",
    "sg:address":"Postbus 72",
    "sg:city":"Sliedrecht",
    "sg:orig_category":"Verlichting And Huishoudartikelen",
    "sg:phone":"+31 184 410 788",
    "sg:postcode":"3360 AB",
    "sg:province":"Zuid-Holland",
    "wof:name":"Bogerman Serviezen",
    "wof:placetype":"venue"
},
  "geometry": {"coordinates":[4.772605,51.823555],"type":"Point"}
}