{
  "type": "Feature",
  "properties": {
    "iso:country":"NL",
    "sg:address":"Kuipersstr 21",
    "sg:city":"Oeffelt",
    "sg:orig_category":"Koel- En Vriestransporten",
    "sg:phone":"+31 485 362 353",
    "sg:postcode":"5441 XK",
    "sg:province":"Noord-Brabant",
    "wof:name":"Bouwmans",
    "wof:placetype":"venue"
},
  "geometry": {"coordinates":[5.936027,51.700809],"type":"Point"}
}