{
  "type": "Feature",
  "properties": {
    "addr:full":"Raadstede 60 Nieuwegein Utrecht 3431 HA",
    "addr:housenumber":"60",
    "addr:postcode":"3431 ha",
    "addr:street":"Raadstede",
    "iso:country":"NL",
    "sg:address":"Raadstede 60",
    "sg:city":"Nieuwegein",
    "sg:orig_category":"Schoenen",
    "sg:phone":"+31 30 603 5068",
    "sg:postcode":"3431 HA",
    "sg:province":"Utrecht",
    "sg:website":"http://www.kosterschoenmode.nl",
    "wof:name":"Koster Nieuwegein",
    "wof:placetype":"venue"
},
  "geometry": {"coordinates":[5.084519,52.028118],"type":"Point"}
}