{
  "type": "Feature",
  "properties": {
    "addr:full":"Lijnbaansgracht 282Bg Amsterdam Noord-Holland 1017 RM",
    "addr:housenumber":"282bg",
    "addr:postcode":"1017 rm",
    "addr:street":"Lijnbaansgracht",
    "iso:country":"NL",
    "sg:address":"Lijnbaansgracht 282Bg",
    "sg:city":"Amsterdam",
    "sg:orig_category":"Meubelzaken, Woning- And Keukeninrichting",
    "sg:phone":"+31 20 624 9652",
    "sg:postcode":"1017 RM",
    "sg:province":"Noord-Holland",
    "wof:name":"Adam'S House",
    "wof:placetype":"venue"
},
  "geometry": {"coordinates":[4.886721,52.361996],"type":"Point"}
}