{
  "type": "Feature",
  "properties": {
    "addr:full":"L Hortensiusln 40D Naarden North Holland 1412 GX",
    "addr:housenumber":"40d",
    "addr:postcode":"1412 gx",
    "iso:country":"NL",
    "sg:address":"L Hortensiusln 40D",
    "sg:city":"Naarden",
    "sg:orig_category":"Artsen - Huisartsen",
    "sg:phone":"+31 35 694 2282",
    "sg:postcode":"1412 GX",
    "sg:province":"North Holland",
    "wof:name":"Siderakis, K",
    "wof:placetype":"venue"
},
  "geometry": {"coordinates":[5.161698,52.284809],"type":"Point"}
}