{
  "type": "Feature",
  "properties": {
    "addr:full":"Middel Broekwg 26 Honselersdyk Zuid-Holland 2675 KB",
    "addr:housenumber":"26",
    "addr:postcode":"2675 kb",
    "iso:country":"NL",
    "sg:address":"Middel Broekwg 26",
    "sg:city":"Honselersdyk",
    "sg:orig_category":"Bloemen En Planten - Groothandel",
    "sg:phone":"+31 174 620 757",
    "sg:postcode":"2675 KB",
    "sg:province":"Zuid-Holland",
    "wof:name":"Heyl Jr Bv, W K",
    "wof:placetype":"venue"
},
  "geometry": {"coordinates":[4.225792,51.993946],"type":"Point"}
}