{
  "type": "Feature",
  "properties": {
    "iso:country":"NL",
    "sg:address":"Wachthoorn 12",
    "sg:city":"Aalden",
    "sg:orig_category":"Elektronische Bedrijfsinstallaties",
    "sg:phone":"+31 591 372 235",
    "sg:postcode":"7854 TN",
    "sg:province":"Drenthe",
    "wof:name":"Cobatt",
    "wof:placetype":"venue"
},
  "geometry": {"coordinates":[6.713964,52.79435],"type":"Point"}
}