{
  "type": "Feature",
  "properties": {
    "addr:full":"Van Veenweg 156 Heerhugowaard Noord-Holland 1701 HL",
    "addr:housenumber":"156",
    "addr:postcode":"1701 hl",
    "addr:street":"Van Veenweg",
    "iso:country":"NL",
    "sg:address":"Van Veenweg 156",
    "sg:city":"Heerhugowaard",
    "sg:orig_category":"Architecten",
    "sg:phone":"+31 72 571 6795",
    "sg:postcode":"1701 HL",
    "sg:province":"Noord-Holland",
    "wof:name":"C.A.L.M. Schilder- Tuintechnisch Adviesb",
    "wof:placetype":"venue"
},
  "geometry": {"coordinates":[4.865616,52.664997],"type":"Point"}
}