{
  "type": "Feature",
  "properties": {
    "iso:country":"NL",
    "sg:address":"Brink 47",
    "sg:city":"Almere",
    "sg:orig_category":"Bloemen And Planten",
    "sg:phone":"+31 36 531 1508",
    "sg:postcode":"1354 HM",
    "sg:province":"Flevoland",
    "wof:name":"Florado",
    "wof:placetype":"venue"
},
  "geometry": {"coordinates":[5.218622,52.337547],"type":"Point"}
}