{
  "type": "Feature",
  "properties": {
    "addr:full":"Middelpaed 11 Suameer Friesland 9262 SW",
    "addr:housenumber":"11",
    "addr:postcode":"9262 sw",
    "addr:street":"Middelpaed",
    "iso:country":"NL",
    "sg:address":"Middelpaed 11",
    "sg:city":"Suameer",
    "sg:orig_category":"Modevakscholen",
    "sg:phone":"+31 511 521 218",
    "sg:postcode":"9262 SW",
    "sg:province":"Friesland",
    "wof:name":"Ensaid, Modevakschool Suameer",
    "wof:placetype":"venue"
},
  "geometry": {"coordinates":[5.998,53.163738],"type":"Point"}
}