{
  "type": "Feature",
  "properties": {
    "addr:full":"Nieuwstr 36 Barneveld Gelderland 3771 AT",
    "addr:housenumber":"36",
    "addr:postcode":"3771",
    "addr:street":"Nieuwstr;Gelderland",
    "iso:country":"NL",
    "sg:address":"Nieuwstr 36",
    "sg:city":"Barneveld",
    "sg:orig_category":"Fietsen En Bromfietsen",
    "sg:phone":"+31 342 412 988",
    "sg:postcode":"3771 AT",
    "sg:province":"Gelderland",
    "wof:name":"Fraanje, C",
    "wof:placetype":"venue"
},
  "geometry": {"coordinates":[5.588382,52.140564],"type":"Point"}
}