{
  "type": "Feature",
  "properties": {
    "addr:full":"Liesveldweg 6 Ameide Zuid-Holland 4233 HH",
    "addr:housenumber":"6",
    "addr:postcode":"4233 hh",
    "addr:street":"Liesveldweg",
    "iso:country":"NL",
    "sg:address":"Liesveldweg 6",
    "sg:city":"Ameide",
    "sg:orig_category":"Goederenvervoer Over De Weg",
    "sg:phone":"+31 183 601 528",
    "sg:postcode":"4233 HH",
    "sg:province":"Zuid-Holland",
    "wof:name":"Fa Stam En Boef",
    "wof:placetype":"venue"
},
  "geometry": {"coordinates":[4.965141,51.956688],"type":"Point"}
}