{
  "type": "Feature",
  "properties": {
    "addr:full":"V Galenstr 39 Bergeyk Noord-Brabant 5571 BP",
    "addr:housenumber":"39",
    "addr:postcode":"5571 bp",
    "iso:country":"NL",
    "sg:address":"V Galenstr 39",
    "sg:city":"Bergeyk",
    "sg:orig_category":"Waterbouwkundige Werken",
    "sg:phone":"+31 497 573 168",
    "sg:postcode":"5571 BP",
    "sg:province":"Noord-Brabant",
    "wof:name":"Wellesen",
    "wof:placetype":"venue"
},
  "geometry": {"coordinates":[5.3601350784,51.3233261108],"type":"Point"}
}