{
  "type": "Feature",
  "properties": {
    "addr:full":"Leywg 940W S Gravenhage Zuid-Holland 2545 GV",
    "addr:housenumber":"940w s",
    "addr:postcode":"2545 gv",
    "addr:street":"Leywg",
    "iso:country":"NL",
    "sg:address":"Leywg 940W",
    "sg:city":"S Gravenhage",
    "sg:orig_category":"Opticiens",
    "sg:phone":"+31 70 367 5927",
    "sg:postcode":"2545 GV",
    "sg:province":"Zuid-Holland",
    "wof:name":"Huis Rinck, Het",
    "wof:placetype":"venue"
},
  "geometry": {"coordinates":[4.2704901695,52.0509300232],"type":"Point"}
}