{
  "type": "Feature",
  "properties": {
    "addr:full":"Ransdalerstr 43 Ransdaal Limburg 6311 AW",
    "addr:housenumber":"43",
    "addr:postcode":"6311 aw",
    "addr:street":"Ransdalerstr",
    "iso:country":"NL",
    "sg:address":"Ransdalerstr 43",
    "sg:city":"Ransdaal",
    "sg:classifiers":[
        {
            "category":"Retail",
            "subcategory":"Auto Repair",
            "type":"Services"
        }
    ],
    "sg:phone":"+31 43 459 1677",
    "sg:postcode":"6311 AW",
    "sg:province":"Limburg",
    "sg:tags":[
        "garage"
    ],
    "wof:name":"Eussen",
    "wof:placetype":"venue"
},
  "geometry": {"coordinates":[5.89214,50.863674],"type":"Point"}
}