{
  "type": "Feature",
  "properties": {
    "iso:country":"NL",
    "sg:address":"Nieuwe Uitleg 2",
    "sg:city":"Dalfsen",
    "sg:classifiers":[
        {
            "category":"Education",
            "subcategory":"Preschool",
            "type":"Public Place"
        }
    ],
    "sg:phone":"+31 529 431 781",
    "sg:postcode":"7721 BN",
    "sg:province":"NL.08",
    "sg:tags":[
        "kleuteronderwijs",
        "basis-"
    ],
    "wof:name":"Gereformeerde Basisschool De Uitleg",
    "wof:placetype":"venue"
},
  "geometry": {"coordinates":[6.259154,52.503036],"type":"Point"}
}