{
  "type": "Feature",
  "properties": {
    "iso:country":"NL",
    "sg:address":"V V Goghstr 18",
    "sg:city":"Voorthuizen",
    "sg:orig_category":"Adviesbureaus",
    "sg:phone":"+31 342 472 917",
    "sg:postcode":"3781 XN",
    "sg:province":"Gelderland",
    "wof:name":"Groenhorst Bv, De",
    "wof:placetype":"venue"
},
  "geometry": {"coordinates":[5.605344,52.186821],"type":"Point"}
}