{
  "type": "Feature",
  "properties": {
    "iso:country":"NL",
    "sg:address":"Bergwegplnts 10",
    "sg:city":"Rotterdam",
    "sg:orig_category":"Bejaarden - Verzorgingstehuizen",
    "sg:phone":"+31 10 443 6100",
    "sg:postcode":"3037 SK",
    "sg:province":"Zuid-Holland",
    "wof:name":"Humanitas Bergweg",
    "wof:placetype":"venue"
},
  "geometry": {"coordinates":[4.47416,51.937038],"type":"Point"}
}