{
  "type": "Feature",
  "properties": {
    "addr:full":"Gershwinstr 45 Zwyndrecht Zuid-Holland 3335 WJ",
    "addr:housenumber":"45",
    "addr:postcode":"3335 wj",
    "addr:street":"Gershwinstr",
    "iso:country":"NL",
    "sg:address":"Gershwinstr 45",
    "sg:city":"Zwyndrecht",
    "sg:orig_category":"Administratie- En Boekhoudkantoren",
    "sg:phone":"+31 78 610 3239",
    "sg:postcode":"3335 WJ",
    "sg:province":"Zuid-Holland",
    "wof:name":"Middelweerd, P C J",
    "wof:placetype":"venue"
},
  "geometry": {"coordinates":[4.60712,51.827839],"type":"Point"}
}