{
  "type": "Feature",
  "properties": {
    "iso:country":"NL",
    "sg:address":"Oudeschans 25B",
    "sg:city":"Amsterdam",
    "sg:orig_category":"Psychotherapeuten",
    "sg:phone":"+31 20 626 1499",
    "sg:postcode":"1011 KS",
    "sg:province":"Noord-Holland",
    "wof:name":"Hopman, Drs R",
    "wof:placetype":"venue"
},
  "geometry": {"coordinates":[4.90529,52.371124],"type":"Point"}
}