{
  "type": "Feature",
  "properties": {
    "addr:full":"Tjalk 31 Schipluiden Zuid-Holland 2636 DA",
    "addr:housenumber":"31",
    "addr:postcode":"2636 da",
    "addr:street":"Tjalk",
    "iso:country":"NL",
    "sg:address":"Tjalk 31",
    "sg:city":"Schipluiden",
    "sg:orig_category":"Onroerende Goederen",
    "sg:phone":"+31 15 380 9575",
    "sg:postcode":"2636 DA",
    "sg:province":"Zuid-Holland",
    "wof:name":"Verschoor Bv",
    "wof:placetype":"venue"
},
  "geometry": {"coordinates":[4.311932,51.977917],"type":"Point"}
}