{
  "type": "Feature",
  "properties": {
    "addr:full":"Prins Hendrikweg 56 Putten Gelderland 3881 GE",
    "addr:housenumber":"56",
    "addr:postcode":"3881",
    "addr:street":"Prins Hendrikweg;Gelderland",
    "iso:country":"NL",
    "sg:address":"Prins Hendrikweg 56",
    "sg:city":"Putten",
    "sg:classifiers":[
        {
            "category":"Professional",
            "subcategory":"Accounting & Tax Preparation",
            "type":"Services"
        }
    ],
    "sg:phone":"+31 341 351 346",
    "sg:postcode":"3881 GE",
    "sg:province":"Gelderland",
    "sg:tags":[
        "accountant"
    ],
    "wof:name":"Drs. R.J. Vahstal Ra.",
    "wof:placetype":"venue"
},
  "geometry": {"coordinates":[5.616254,52.257633],"type":"Point"}
}