{
  "type": "Feature",
  "properties": {
    "addr:full":"J Catsstr 10 Grypskerke Zeeland 4364 AM",
    "addr:housenumber":"10",
    "addr:postcode":"4364",
    "addr:street":"Grypskerke Zeeland",
    "iso:country":"NL",
    "sg:address":"J Catsstr 10",
    "sg:city":"Grypskerke",
    "sg:orig_category":"Administratie- En Boekhoudkantoren",
    "sg:phone":"+31 118 592 828",
    "sg:postcode":"4364 AM",
    "sg:province":"Zeeland",
    "wof:name":"Beers, Van",
    "wof:placetype":"venue"
},
  "geometry": {"coordinates":[3.573785,51.519073],"type":"Point"}
}