{
  "type": "Feature",
  "properties": {
    "addr:full":"Koning Clovisstraat 16A Maastricht Limburg 6224 GW",
    "addr:housenumber":"16a",
    "addr:postcode":"6224 gw",
    "addr:street":"Koning Clovisstraat",
    "iso:country":"NL",
    "sg:address":"Koning Clovisstraat 16A",
    "sg:city":"Maastricht",
    "sg:orig_category":"Vertaal- And Tolkenbureaus",
    "sg:phone":"+31 43 352 1404",
    "sg:postcode":"6224 GW",
    "sg:province":"Limburg",
    "wof:name":"Vrenay En Koot Vertaalburo",
    "wof:placetype":"venue"
},
  "geometry": {"coordinates":[5.718438,50.851337],"type":"Point"}
}