{
  "type": "Feature",
  "properties": {
    "iso:country":"NL",
    "sg:address":"Kamphuizenlaan 83-2",
    "sg:city":"Arnhem",
    "sg:orig_category":"Vertaal- And Tolkenbureaus",
    "sg:phone":"+31 26 363 6224",
    "sg:postcode":"6825  E",
    "sg:province":"Gelderland",
    "wof:name":"Sneltekst Vertaalburo",
    "wof:placetype":"venue"
},
  "geometry": {"coordinates":[5.968904,51.983727],"type":"Point"}
}