{
  "type": "Feature",
  "properties": {
    "addr:full":"Kamphuizenlaan 83-2 Arnhem Gelderland 6825  E",
    "addr:housenumber":"83-2;6825",
    "addr:street":"Kamphuizenlaan;E",
    "iso:country":"NL",
    "sg:address":"Kamphuizenlaan 83-2",
    "sg:city":"Arnhem",
    "sg:orig_category":"Vertaal- And Tolkenbureaus",
    "sg:phone":"+31 26 363 6224",
    "sg:postcode":"6825  E",
    "sg:province":"Gelderland",
    "wof:name":"Sneltekst Vertaalburo",
    "wof:placetype":"venue"
},
  "geometry": {"coordinates":[5.968904,51.983727],"type":"Point"}
}