{
  "type": "Feature",
  "properties": {
    "addr:full":"Kleine Berg 14 Eindhoven North Brabant 5611 JV",
    "addr:housenumber":"14",
    "addr:postcode":"5611 jv",
    "addr:street":"Kleine Berg",
    "iso:country":"NL",
    "sg:address":"Kleine Berg 14",
    "sg:city":"Eindhoven",
    "sg:orig_category":"Kunst And Kunstenaarsbenodigdheden",
    "sg:phone":"+31 40 244 1381",
    "sg:postcode":"5611 JV",
    "sg:province":"North Brabant",
    "wof:name":"Kunsthandel Beckers Bv",
    "wof:placetype":"venue"
},
  "geometry": {"coordinates":[5.484105,51.434471],"type":"Point"}
}