{
  "type": "Feature",
  "properties": {
    "iso:country":"NL",
    "sg:address":"Stationswg 47",
    "sg:city":"Geertruidenberg",
    "sg:classifiers":[
        {
            "category":"Travel",
            "subcategory":"Hotels & Motels",
            "type":"Entertainment"
        }
    ],
    "sg:phone":"+31 162 522 100",
    "sg:postcode":"4931 BX",
    "sg:province":"Noord-Brabant",
    "sg:website":"http://www.den-engel.nl",
    "wof:name":"Engel, Den",
    "wof:placetype":"venue"
},
  "geometry": {"coordinates":[4.858335,51.701351],"type":"Point"}
}