{
  "type": "Feature",
  "properties": {
    "addr:full":"Rykswg 3 Oosterland Zeeland 4307 LE",
    "addr:housenumber":"3",
    "addr:postcode":"4307 le",
    "addr:street":"Rykswg",
    "iso:country":"NL",
    "sg:address":"Rykswg 3",
    "sg:city":"Oosterland",
    "sg:orig_category":"Foerage",
    "sg:phone":"+31 111 481 482",
    "sg:postcode":"4307 LE",
    "sg:province":"Zeeland",
    "wof:name":"Koppert, H",
    "wof:placetype":"venue"
},
  "geometry": {"coordinates":[4.053316,51.657539],"type":"Point"}
}