{
  "type": "Feature",
  "properties": {
    "iso:country":"NL",
    "sg:address":"Markt 23",
    "sg:city":"Poortvliet",
    "sg:orig_category":"Adviesbureaus Bedrijfsorganisatie",
    "sg:phone":"+31 166 617 001",
    "sg:postcode":"4693 CA",
    "sg:province":"Zeeland",
    "wof:name":"Langenhuizen",
    "wof:placetype":"venue"
},
  "geometry": {"coordinates":[-119.270203,37.271832],"type":"Point"}
}