{
  "type": "Feature",
  "properties": {
    "addr:full":"Koningin Regentesselaan 47 Roermond Limburg 6043 CJ",
    "addr:housenumber":"47",
    "addr:postcode":"6043 cj",
    "addr:street":"Koningin Regentesselaan",
    "iso:country":"NL",
    "sg:address":"Koningin Regentesselaan 47",
    "sg:city":"Roermond",
    "sg:orig_category":"Kappers",
    "sg:phone":"+31 475 315 268",
    "sg:postcode":"6043 CJ",
    "sg:province":"Limburg",
    "wof:name":"Haarmodeteam Verberk",
    "wof:placetype":"venue"
},
  "geometry": {"coordinates":[5.9972529411,51.1904220581],"type":"Point"}
}