{
  "type": "Feature",
  "properties": {
    "iso:country":"NL",
    "sg:address":"Hagelingerwg 65",
    "sg:city":"Santpoort Noord",
    "sg:classifiers":[
        {
            "category":"Food & Beverages",
            "subcategory":"Bakery",
            "type":"Retail Goods"
        }
    ],
    "sg:phone":"+31 23 537 8523",
    "sg:postcode":"2071 CA",
    "sg:province":"Noord-Holland",
    "sg:tags":[
        "brood",
        "en",
        "banket"
    ],
    "wof:name":"Everts",
    "wof:placetype":"venue"
},
  "geometry": {"coordinates":[-121.95871,39.780125],"type":"Point"}
}