{
  "type": "Feature",
  "properties": {
    "addr:full":"Wilgenstraat 11 Oss Noord-Brabant 5342 XH",
    "addr:housenumber":"11",
    "addr:postcode":"5342 xh",
    "addr:street":"Wilgenstraat",
    "iso:country":"NL",
    "sg:address":"Wilgenstraat 11",
    "sg:city":"Oss",
    "sg:orig_category":"Makelaars In Onroerend Goed",
    "sg:phone":"+31 412 646 129",
    "sg:postcode":"5342 XH",
    "sg:province":"Noord-Brabant",
    "wof:name":"Makelaarskantoor Hendriks - Oss",
    "wof:placetype":"venue"
},
  "geometry": {"coordinates":[-91.21601099999999,44.580002],"type":"Point"}
}