{
  "type": "Feature",
  "properties": {
    "addr:full":"Kruisln 196 Amsterdam Noord-Holland 1098 SK",
    "addr:housenumber":"196",
    "addr:street":"1098",
    "iso:country":"NL",
    "sg:address":"Kruisln 196",
    "sg:city":"Amsterdam",
    "sg:orig_category":"Psychotherapeuten",
    "sg:phone":"+31 20 692 3162",
    "sg:postcode":"1098 SK",
    "sg:province":"Noord-Holland",
    "wof:name":"Hofmann-Spies, Drs M",
    "wof:placetype":"venue"
},
  "geometry": {"coordinates":[4.94688,52.349209],"type":"Point"}
}