{
  "type": "Feature",
  "properties": {
    "addr:full":"Munnikendijk 56 Westmaas Zuid-Holland 3273 LE",
    "addr:housenumber":"56",
    "addr:postcode":"3273 le",
    "addr:street":"Munnikendijk",
    "iso:country":"NL",
    "sg:address":"Munnikendijk 56",
    "sg:city":"Westmaas",
    "sg:orig_category":"Schilderwerk",
    "sg:phone":"+31 186 574 466",
    "sg:postcode":"3273 LE",
    "sg:province":"Zuid-Holland",
    "wof:name":"E De Jong",
    "wof:placetype":"venue"
},
  "geometry": {"coordinates":[4.484288,51.782284],"type":"Point"}
}