{
  "type": "Feature",
  "properties": {
    "addr:full":"Koperslagery 39 Barendrecht Zuid-Holland 2993 CD",
    "addr:housenumber":"39",
    "addr:postcode":"2993 cd",
    "addr:street":"Koperslagery",
    "iso:country":"NL",
    "sg:address":"Koperslagery 39",
    "sg:city":"Barendrecht",
    "sg:orig_category":"Administratie- En Boekhoudkantoren",
    "sg:phone":"+31 180 610 403",
    "sg:postcode":"2993 CD",
    "sg:province":"Zuid-Holland",
    "wof:name":"Ensink",
    "wof:placetype":"venue"
},
  "geometry": {"coordinates":[4.483984,51.855656],"type":"Point"}
}