{
  "type": "Feature",
  "properties": {
    "addr:full":"Spoorstr 2 Gouda South Holland 2806 BZ",
    "addr:housenumber":"2",
    "addr:postcode":"2806 bz",
    "addr:street":"Spoorstr",
    "iso:country":"NL",
    "sg:address":"Spoorstr 2",
    "sg:city":"Gouda",
    "sg:orig_category":"Verenigingen En Stichtingen",
    "sg:phone":"+31 182 594 710",
    "sg:postcode":"2806 BZ",
    "sg:province":"South Holland",
    "wof:name":"Ter Vest De Vierstroom",
    "wof:placetype":"venue"
},
  "geometry": {"coordinates":[4.709664,52.015923],"type":"Point"}
}