{
  "type": "Feature",
  "properties": {
    "addr:full":"Sluisjesdk 111 Rotterdam South Holland 3087 AE",
    "addr:housenumber":"111",
    "addr:postcode":"3087 ae",
    "iso:country":"NL",
    "sg:address":"Sluisjesdk 111",
    "sg:city":"Rotterdam",
    "sg:orig_category":"Horecabenodigdheden",
    "sg:phone":"+31 10 495 5454",
    "sg:postcode":"3087 AE",
    "sg:province":"South Holland",
    "wof:name":"Kortlever Bv",
    "wof:placetype":"venue"
},
  "geometry": {"coordinates":[4.450048,51.896873],"type":"Point"}
}