{
  "type": "Feature",
  "properties": {
    "iso:country":"NL",
    "sg:address":"Marktplein 1",
    "sg:city":"Uithoorn",
    "sg:orig_category":"Meubelreparatie And -Restauratie",
    "sg:phone":"+31 297 532 359",
    "sg:postcode":"1421 AC",
    "sg:province":"Utrecht",
    "wof:name":"De Toekomst",
    "wof:placetype":"venue"
},
  "geometry": {"coordinates":[4.832293,52.233006],"type":"Point"}
}