{
  "type": "Feature",
  "properties": {
    "addr:full":"Spoorstr 6 Rosmalen Noord-Brabant 5241 EG",
    "addr:housenumber":"6",
    "addr:postcode":"5241 eg",
    "addr:street":"Spoorstr",
    "iso:country":"NL",
    "sg:address":"Spoorstr 6",
    "sg:city":"Rosmalen",
    "sg:orig_category":"Adviesbureaus Bedrijfsorganisatie",
    "sg:phone":"+31 73 521 1696",
    "sg:postcode":"5241 EG",
    "sg:province":"Noord-Brabant",
    "wof:name":"Claassen Moolenbeek & Partn",
    "wof:placetype":"venue"
},
  "geometry": {"coordinates":[5.36198,51.713081],"type":"Point"}
}