{
  "type": "Feature",
  "properties": {
    "addr:full":"Peppelkd 11 Houten Utrecht 3992 AL",
    "addr:housenumber":"11",
    "addr:postcode":"3992 al",
    "addr:street":"Peppelkd",
    "iso:country":"NL",
    "sg:address":"Peppelkd 11",
    "sg:city":"Houten",
    "sg:orig_category":"Sanitaire Artikelen",
    "sg:phone":"+31 30 637 4156",
    "sg:postcode":"3992 AL",
    "sg:province":"Utrecht",
    "sg:website":"http://www.sanispecial.nl",
    "wof:name":"Sanispecial Bv",
    "wof:placetype":"venue"
},
  "geometry": {"coordinates":[5.169435,52.036541],"type":"Point"}
}