{
  "type": "Feature",
  "properties": {
    "addr:full":"Plompetorengr 4 Utrecht Utrecht 3512 CC",
    "addr:housenumber":"4",
    "addr:postcode":"3512 cc",
    "addr:street":"Plompetorengr",
    "iso:country":"NL",
    "sg:address":"Plompetorengr 4",
    "sg:city":"Utrecht",
    "sg:orig_category":"Beeldende Kunstenaars",
    "sg:phone":"+31 30 231 8582",
    "sg:postcode":"3512 CC",
    "sg:province":"Utrecht",
    "sg:website":"http://www.gua.nl",
    "wof:name":"Grafisch Atelier Utrecht, Sticht",
    "wof:placetype":"venue"
},
  "geometry": {"coordinates":[5.123169,52.09552],"type":"Point"}
}