{
  "type": "Feature",
  "properties": {
    "addr:full":"Nieuwestad 136 Leeuwarden Friesland 8911 DA",
    "addr:housenumber":"136",
    "addr:postcode":"8911 da",
    "addr:street":"Nieuwestad",
    "iso:country":"NL",
    "sg:address":"Nieuwestad 136",
    "sg:city":"Leeuwarden",
    "sg:orig_category":"Schoenen",
    "sg:phone":"+31 58 216 4170",
    "sg:postcode":"8911 DA",
    "sg:province":"Friesland",
    "sg:website":"http://www.dolcis.nl",
    "wof:name":"Dolcis",
    "wof:placetype":"venue"
},
  "geometry": {"coordinates":[5.795096,53.200432],"type":"Point"}
}