{
  "type": "Feature",
  "properties": {
    "addr:full":"De Poort 77 Rilland Zeeland 4411 PB",
    "addr:housenumber":"77",
    "addr:postcode":"4411 pb",
    "addr:street":"De Poort",
    "iso:country":"NL",
    "sg:address":"De Poort 77",
    "sg:city":"Rilland",
    "sg:orig_category":"Lasapparaten En Benodigdheden",
    "sg:phone":"+31 113 551 155",
    "sg:postcode":"4411 PB",
    "sg:province":"Zeeland",
    "wof:name":"Weldas Europe Bv",
    "wof:placetype":"venue"
},
  "geometry": {"coordinates":[4.198657,51.422409],"type":"Point"}
}