{
  "type": "Feature",
  "properties": {
    "addr:full":"Hoge Varenweg 25 Hierden Gelderland 3849 RG",
    "addr:housenumber":"25",
    "addr:postcode":"3849 rg",
    "addr:street":"Hoge Varenweg;Gelderland",
    "iso:country":"NL",
    "sg:address":"Hoge Varenweg 25",
    "sg:city":"Hierden",
    "sg:orig_category":"Zetwerk And Graveren",
    "sg:phone":"+31 341 451 540",
    "sg:postcode":"3849 RG",
    "sg:province":"Gelderland",
    "wof:name":"Vof E-77",
    "wof:placetype":"venue"
},
  "geometry": {"coordinates":[5.683855,52.356346],"type":"Point"}
}