{
  "type": "Feature",
  "properties": {
    "addr:full":"G V Amstelstr 221-223 Hilversum Noord-Holland 1214 BA",
    "addr:postcode":"221-223;1214 ba",
    "addr:street":"V Amstelstr",
    "iso:country":"NL",
    "sg:address":"G V Amstelstr 221-223",
    "sg:city":"Hilversum",
    "sg:orig_category":"Herenkleding",
    "sg:phone":"+31 35 622 9898",
    "sg:postcode":"1214 BA",
    "sg:province":"Noord-Holland",
    "wof:name":"Donald'S Outfit",
    "wof:placetype":"venue"
},
  "geometry": {"coordinates":[5.1695,52.228565],"type":"Point"}
}