{
  "type": "Feature",
  "properties": {
    "iso:country":"NL",
    "sg:address":"Langeweg 14",
    "sg:city":"Bruinisse",
    "sg:orig_category":"Kampeerterreinen",
    "sg:phone":"+31 111 481 585",
    "sg:postcode":"4311 RC",
    "sg:province":"Zeeland",
    "wof:name":"Camping Bru",
    "wof:placetype":"venue"
},
  "geometry": {"coordinates":[4.064057827,51.6365852356],"type":"Point"}
}