{
  "type": "Feature",
  "properties": {
    "addr:full":"Grotestraat 49 Drunen North Brabant 5151 JC",
    "addr:housenumber":"49",
    "addr:postcode":"5151 jc",
    "addr:street":"Grotestraat",
    "iso:country":"NL",
    "sg:address":"Grotestraat 49",
    "sg:city":"Drunen",
    "sg:classifiers":[
        {
            "category":"Communications",
            "subcategory":"Television Station",
            "type":"Services"
        }
    ],
    "sg:phone":"+31 416 380 570",
    "sg:postcode":"5151 JC",
    "sg:province":"North Brabant",
    "sg:tags":[
        "video",
        "audio",
        "verhuur"
    ],
    "wof:name":"Paradise Video Entertainment",
    "wof:placetype":"venue"
},
  "geometry": {"coordinates":[5.124795,51.687351],"type":"Point"}
}