{
  "type": "Feature",
  "properties": {
    "addr:full":"Dode Nieuwstraat 16 'S-Hertogenbosch Noord-Brabant 5211 EK",
    "addr:housenumber":"16",
    "addr:postcode":"5211 ek",
    "addr:street":"Dode Nieuwstraat",
    "iso:country":"NL",
    "sg:address":"Dode Nieuwstraat 16",
    "sg:city":"'S-Hertogenbosch",
    "sg:orig_category":"Organisatiebureaus",
    "sg:phone":"+31 73 613 8700",
    "sg:postcode":"5211 EK",
    "sg:province":"Noord-Brabant",
    "wof:name":"Projectr",
    "wof:placetype":"venue"
},
  "geometry": {"coordinates":[5.3015398979,51.6888885498],"type":"Point"}
}