{
  "type": "Feature",
  "properties": {
    "addr:full":"Nijverheidsweg 8 Sint Oedenrode Noord-Brabant 5492 NK",
    "addr:housenumber":"8;oedenrode",
    "addr:postcode":"5492 nk",
    "addr:street":"Nijverheidsweg",
    "iso:country":"NL",
    "sg:address":"Nijverheidsweg 8",
    "sg:city":"Sint Oedenrode",
    "sg:orig_category":"Verhuur Huishoudartikelen",
    "sg:phone":"+31 413 472 520",
    "sg:postcode":"5492 NK",
    "sg:province":"Noord-Brabant",
    "wof:name":"Vof Party-Verhuur Rooi",
    "wof:placetype":"venue"
},
  "geometry": {"coordinates":[5.479669,51.556358],"type":"Point"}
}