{
  "type": "Feature",
  "properties": {
    "addr:full":"Prins Bisschoplaan 3 Horn Limburg 6085 AW",
    "addr:housenumber":"3",
    "addr:postcode":"6085 aw",
    "addr:street":"Prins Bisschoplaan",
    "iso:country":"NL",
    "sg:address":"Prins Bisschoplaan 3",
    "sg:city":"Horn",
    "sg:orig_category":"Goederenvervoer Over De Weg",
    "sg:phone":"+31 475 582 544",
    "sg:postcode":"6085 AW",
    "sg:province":"Limburg",
    "wof:name":"Opbroek-Teven Har En Jose",
    "wof:placetype":"venue"
},
  "geometry": {"coordinates":[-103.439728,42.765663],"type":"Point"}
}