{
  "type": "Feature",
  "properties": {
    "addr:full":"Tulpstr 155 Oldenzaal Overijssel 7571 AB",
    "addr:housenumber":"155",
    "addr:postcode":"7571 ab",
    "iso:country":"NL",
    "sg:address":"Tulpstr 155",
    "sg:city":"Oldenzaal",
    "sg:orig_category":"Artsen - Huisartsen",
    "sg:phone":"+31 541 522 666",
    "sg:postcode":"7571 AB",
    "sg:province":"Overijssel",
    "sg:website":"HTTP://www.huisartsoldenzaal.nl",
    "wof:name":"Beek, P J Van",
    "wof:placetype":"venue"
},
  "geometry": {"coordinates":[6.925183,52.314217],"type":"Point"}
}