{
  "type": "Feature",
  "properties": {
    "addr:full":"Wilhelminastraat 21 Rijen Noord-Brabant 5121 WR",
    "addr:housenumber":"21",
    "addr:postcode":"5121 wr",
    "addr:street":"Wilhelminastraat",
    "iso:country":"NL",
    "sg:address":"Wilhelminastraat 21",
    "sg:city":"Rijen",
    "sg:orig_category":"Bedrijfs- And Managementsconsultants",
    "sg:phone":"+31 161 231 992",
    "sg:postcode":"5121 WR",
    "sg:province":"Noord-Brabant",
    "wof:name":"Alom",
    "wof:placetype":"venue"
},
  "geometry": {"coordinates":[4.91922,51.586674],"type":"Point"}
}