{
  "type": "Feature",
  "properties": {
    "addr:full":"Vd Does D Willeboissngl 57 'S Hertogenbosch Noord-Brabant 5211 CE",
    "addr:housenumber":"57",
    "addr:postcode":"5211 ce",
    "addr:street":"' S",
    "iso:country":"NL",
    "sg:address":"Vd Does D Willeboissngl 57",
    "sg:city":"'S Hertogenbosch",
    "sg:orig_category":"Fotostudio'S And Fotografen",
    "sg:phone":"+31 73 613 7688",
    "sg:postcode":"5211 CE",
    "sg:province":"Noord-Brabant",
    "wof:name":"J. Lennarts",
    "wof:placetype":"venue"
},
  "geometry": {"coordinates":[5.29302,51.683041],"type":"Point"}
}