{
  "type": "Feature",
  "properties": {
    "addr:full":"F Lisztstr 6 Tilburg Noord-Brabant 5011 RC",
    "addr:housenumber":"6",
    "addr:postcode":"5011 rc",
    "addr:street":"Lisztstr",
    "iso:country":"NL",
    "sg:address":"F Lisztstr 6",
    "sg:city":"Tilburg",
    "sg:orig_category":"Artsen - Huisartsen",
    "sg:phone":"+31 13 455 6829",
    "sg:postcode":"5011 RC",
    "sg:province":"Noord-Brabant",
    "wof:name":"Pauw, C H",
    "wof:placetype":"venue"
},
  "geometry": {"coordinates":[5.082059,51.582287],"type":"Point"}
}