{
  "type": "Feature",
  "properties": {
    "iso:country":"NL",
    "sg:address":"Noordstr 8",
    "sg:city":"Domburg",
    "sg:orig_category":"Makelaars En Adviseurs Onroerende Goederen",
    "sg:phone":"+31 118 584 660",
    "sg:postcode":"4357 AP",
    "sg:province":"Zeeland",
    "sg:website":"http://www.pateer.nl",
    "wof:name":"Arthur Pateer Makelaardij",
    "wof:placetype":"venue"
},
  "geometry": {"coordinates":[3.496964,51.564037],"type":"Point"}
}