{
  "type": "Feature",
  "properties": {
    "addr:full":"Smuldersln 24 Someren North Brabant 5712 PN",
    "addr:housenumber":"24",
    "addr:postcode":"5712 pn",
    "addr:street":"Smuldersln",
    "iso:country":"NL",
    "sg:address":"Smuldersln 24",
    "sg:city":"Someren",
    "sg:orig_category":"Honden- En Kattentrimsalons",
    "sg:phone":"+31 493 490 755",
    "sg:postcode":"5712 PN",
    "sg:province":"North Brabant",
    "wof:name":"Doggy",
    "wof:placetype":"venue"
},
  "geometry": {"coordinates":[5.695338,51.350674],"type":"Point"}
}