{
  "type": "Feature",
  "properties": {
    "addr:full":"Aalsterwg 77E Eindhoven North Brabant 5615 CB",
    "addr:housenumber":"77e",
    "addr:postcode":"5615 cb",
    "addr:street":"Aalsterwg",
    "iso:country":"NL",
    "sg:address":"Aalsterwg 77E",
    "sg:city":"Eindhoven",
    "sg:orig_category":"Piano'S",
    "sg:phone":"+31 40 211 9731",
    "sg:postcode":"5615 CB",
    "sg:province":"North Brabant",
    "wof:name":"Kawai Nederland",
    "wof:placetype":"venue"
},
  "geometry": {"coordinates":[5.486332,51.425709],"type":"Point"}
}