{
  "type": "Feature",
  "properties": {
    "iso:country":"NL",
    "sg:address":"Slochterenln 37",
    "sg:city":"Bussum",
    "sg:orig_category":"Woningbouw- Verenigingen En -Stichtingen",
    "sg:phone":"+31 35 695 4270",
    "sg:postcode":"1405 AL",
    "sg:province":"North Holland",
    "wof:name":"Patio",
    "wof:placetype":"venue"
},
  "geometry": {"coordinates":[5.1548352242,52.2814331055],"type":"Point"}
}