{
  "type": "Feature",
  "properties": {
    "addr:full":"Dijkweg 265 Andijk Noord-Holland 1619 JE",
    "addr:housenumber":"265",
    "addr:postcode":"1619 je",
    "addr:street":"Dijkweg",
    "iso:country":"NL",
    "sg:address":"Dijkweg 265",
    "sg:city":"Andijk",
    "sg:orig_category":"Fitnesscentra",
    "sg:phone":"+31 228 591 353",
    "sg:postcode":"1619 JE",
    "sg:province":"Noord-Holland",
    "wof:name":"Asonia Judovereniging",
    "wof:placetype":"venue"
},
  "geometry": {"coordinates":[5.18707,52.746799],"type":"Point"}
}