{
  "type": "Feature",
  "properties": {
    "addr:full":"Kennedyln 85 Leiden Zuid-Holland 2324 EV",
    "addr:housenumber":"85",
    "addr:postcode":"2324 ev",
    "addr:street":"Kennedyln",
    "iso:country":"NL",
    "sg:address":"Kennedyln 85",
    "sg:city":"Leiden",
    "sg:orig_category":"Voetbalverenigingen",
    "sg:phone":"+31 71 576 4234",
    "sg:postcode":"2324 EV",
    "sg:province":"Zuid-Holland",
    "wof:name":"Ebr Vv",
    "wof:placetype":"venue"
},
  "geometry": {"coordinates":[4.47026,52.144901],"type":"Point"}
}