{
  "type": "Feature",
  "properties": {
    "addr:full":"Postbus 9655 Haarlem Drenthe 2003 LR",
    "addr:housenumber":"9655",
    "addr:postcode":"2003 lr",
    "addr:street":"Postbus",
    "iso:country":"NL",
    "sg:address":"Postbus 9655",
    "sg:city":"Haarlem",
    "sg:orig_category":"Sportverenigingen En Ontspannings- Verenigingen",
    "sg:phone":"+31 23 537 7030",
    "sg:postcode":"2003 LR",
    "sg:province":"Drenthe",
    "wof:name":"Hsv De Kampioen Wielerver",
    "wof:placetype":"venue"
},
  "geometry": {"coordinates":[4.64225,52.380562],"type":"Point"}
}