{
  "type": "Feature",
  "properties": {
    "iso:country":"NL",
    "sg:address":"Plesmanstraat 45",
    "sg:city":"Hoogeveen",
    "sg:orig_category":"Fruit And Groenten Gh",
    "sg:phone":"+31 528 269 362",
    "sg:postcode":"7903 BG",
    "sg:province":"Drenthe",
    "wof:name":"Doldersum Groenten- En Fruitmarkten Bv",
    "wof:placetype":"venue"
},
  "geometry": {"coordinates":[6.519865,52.735062],"type":"Point"}
}