{
  "type": "Feature",
  "properties": {
    "addr:full":"Mechtildisstr 19 Tilburg Noord-Brabant 5021 CM",
    "addr:housenumber":"19",
    "addr:postcode":"5021 cm",
    "addr:street":"Mechtildisstr",
    "iso:country":"NL",
    "sg:address":"Mechtildisstr 19",
    "sg:city":"Tilburg",
    "sg:orig_category":"Adviesbureaus Bedrijfsorganisatie",
    "sg:phone":"+31 13 544 5279",
    "sg:postcode":"5021 CM",
    "sg:province":"Noord-Brabant",
    "wof:name":"Invise",
    "wof:placetype":"venue"
},
  "geometry": {"coordinates":[5.094327,51.549652],"type":"Point"}
}