{
  "type": "Feature",
  "properties": {
    "addr:full":"Pekelderstr 2C Stadskanaal Groningen 9501 LC",
    "addr:housenumber":"2c",
    "addr:postcode":"9501 lc",
    "addr:street":"Pekelderstr",
    "iso:country":"NL",
    "sg:address":"Pekelderstr 2C",
    "sg:city":"Stadskanaal",
    "sg:orig_category":"Kappers",
    "sg:phone":"+31 599 454 576",
    "sg:postcode":"9501 LC",
    "sg:province":"Groningen",
    "wof:name":"Buist, A",
    "wof:placetype":"venue"
},
  "geometry": {"coordinates":[6.908053875,53.0192108154],"type":"Point"}
}