{
  "type": "Feature",
  "properties": {
    "addr:full":"Zuidbrink 13 Westerbork Provincie Drenthe 9431 AP",
    "addr:housenumber":"13",
    "addr:postcode":"9431 ap",
    "addr:street":"Zuidbrink;Provincie Drenthe",
    "iso:country":"NL",
    "sg:address":"Zuidbrink 13",
    "sg:city":"Westerbork",
    "sg:orig_category":"Bibliotheken En Leeszalen Openbare",
    "sg:phone":"+31 593 331 560",
    "sg:postcode":"9431 AP",
    "sg:province":"Provincie Drenthe",
    "wof:name":"Openb Bibliotheek",
    "wof:placetype":"venue"
},
  "geometry": {"coordinates":[6.610342,52.848412],"type":"Point"}
}