{
  "type": "Feature",
  "properties": {
    "addr:full":"Borgerspark 45 Veendam Groningen 9642 LL",
    "addr:housenumber":"45",
    "addr:postcode":"9642 ll",
    "addr:street":"Borgerspark",
    "iso:country":"NL",
    "sg:address":"Borgerspark 45",
    "sg:city":"Veendam",
    "sg:orig_category":"Autokeuringen",
    "sg:phone":"+31 598 625 528",
    "sg:postcode":"9642 LL",
    "sg:province":"Groningen",
    "wof:name":"Ad Trucks",
    "wof:placetype":"venue"
},
  "geometry": {"coordinates":[6.853442,53.099926],"type":"Point"}
}