{
  "type": "Feature",
  "properties": {
    "addr:full":"Ln V Meerdervoort 155 S Gravenhage Zuid-Holland 2517 AX",
    "addr:housenumber":"155;gravenhage",
    "addr:postcode":"2517 ax",
    "addr:street":"Ln;Meerdervoort;S",
    "iso:country":"NL",
    "sg:address":"Ln V Meerdervoort 155",
    "sg:city":"S Gravenhage",
    "sg:classifiers":[
        {
            "category":"Travel",
            "subcategory":"Hotels & Motels",
            "type":"Entertainment"
        }
    ],
    "sg:phone":"+31 70 364 7879",
    "sg:postcode":"2517 AX",
    "sg:province":"Zuid-Holland",
    "wof:name":"Haagsche Suites Bv",
    "wof:placetype":"venue"
},
  "geometry": {"coordinates":[4.28708,52.08667],"type":"Point"}
}