{
  "type": "Feature",
  "properties": {
    "addr:full":"Schapenmeent 1 Almere Flevoland 1357 GA",
    "addr:housenumber":"1",
    "addr:postcode":"1357 ga",
    "addr:street":"Schapenmeent;Flevoland",
    "iso:country":"NL",
    "sg:address":"Schapenmeent 1",
    "sg:city":"Almere",
    "sg:orig_category":"Homeopathie",
    "sg:phone":"+31 35 683 5961",
    "sg:postcode":"1357 GA",
    "sg:province":"Flevoland",
    "wof:name":"Meuwese, P H",
    "wof:placetype":"venue"
},
  "geometry": {"coordinates":[5.234779,52.333054],"type":"Point"}
}