{
  "type": "Feature",
  "properties": {
    "iso:country":"NL",
    "sg:address":"Utrechtsewg 109C",
    "sg:city":"Utrecht",
    "sg:orig_category":"Bloemen En Planten - Veilingen",
    "sg:phone":"+31 30 677 9982",
    "sg:postcode":"3544 NA",
    "sg:province":"Utrecht",
    "wof:name":"Horta Groencentrum",
    "wof:placetype":"venue"
},
  "geometry": {"coordinates":[5.049783,52.098232],"type":"Point"}
}