{
  "type": "Feature",
  "properties": {
    "addr:full":"Zuidwenk 33 Bunschoten Spakenb Utrecht 3751 CB",
    "addr:housenumber":"33",
    "addr:street":"Zuidwenk",
    "iso:country":"NL",
    "sg:address":"Zuidwenk 33",
    "sg:city":"Bunschoten Spakenb",
    "sg:classifiers":[
        {
            "category":"Farming",
            "subcategory":"Fish & Marine Products",
            "type":"Manufacturing & Wholesale Goods"
        }
    ],
    "sg:phone":"+31 33 298 1068",
    "sg:postcode":"3751 CB",
    "sg:province":"Utrecht",
    "sg:tags":[
        "vi"
    ],
    "wof:name":"Muijs & Zn Vof, B",
    "wof:placetype":"venue"
},
  "geometry": {"coordinates":[5.383489,52.249111],"type":"Point"}
}