{
  "type": "Feature",
  "properties": {
    "addr:full":"Vijverweg 9 Zwijndrecht Zuid-Holland 3331 CZ",
    "addr:housenumber":"9",
    "addr:postcode":"3331",
    "addr:street":"Vijverweg",
    "iso:country":"NL",
    "sg:address":"Vijverweg 9",
    "sg:city":"Zwijndrecht",
    "sg:classifiers":[
        {
            "category":"Professional",
            "subcategory":"Accounting & Tax Preparation",
            "type":"Services"
        }
    ],
    "sg:phone":"+31 78 612 5538",
    "sg:postcode":"3331 CZ",
    "sg:province":"Zuid-Holland",
    "sg:tags":[
        "accountant"
    ],
    "wof:name":"Accountantskantoor Van Den Bogaard & Rem",
    "wof:placetype":"venue"
},
  "geometry": {"coordinates":[4.642804,51.81966],"type":"Point"}
}