{
  "type": "Feature",
  "properties": {
    "iso:country":"NL",
    "sg:address":"Utrechtseweg 4",
    "sg:city":"Vleuten",
    "sg:orig_category":"Diverse Bedrijfsinstallaties Gh",
    "sg:phone":"+31 30 677 9211",
    "sg:postcode":"3451 GG",
    "sg:province":"Utrecht",
    "wof:name":"Verder Vleuten Bv",
    "wof:placetype":"venue"
},
  "geometry": {"coordinates":[5.022618,52.101654],"type":"Point"}
}