{
  "type": "Feature",
  "properties": {
    "addr:full":"Rijksweg Zuid 43 Sittard Limburg 6131 AL",
    "addr:housenumber":"43",
    "addr:postcode":"6131 al",
    "addr:street":"Rijksweg Zuid",
    "iso:country":"NL",
    "sg:address":"Rijksweg Zuid 43",
    "sg:city":"Sittard",
    "sg:orig_category":"Architecten En Architectenbureaus",
    "sg:phone":"+31 46 452 2000",
    "sg:postcode":"6131 AL",
    "sg:province":"Limburg",
    "wof:name":"Schinkel-Benning Bv",
    "wof:placetype":"venue"
},
  "geometry": {"coordinates":[5.860929,50.997215],"type":"Point"}
}