{
  "type": "Feature",
  "properties": {
    "addr:full":"G Terlouwstr 2 Rotterdam South Holland 3065 GH",
    "addr:housenumber":"2",
    "addr:postcode":"3065 gh",
    "iso:country":"NL",
    "sg:address":"G Terlouwstr 2",
    "sg:city":"Rotterdam",
    "sg:orig_category":"Onderhoudswerken",
    "sg:phone":"+31 10 447 1059",
    "sg:postcode":"3065 GH",
    "sg:province":"South Holland",
    "wof:name":"Zijffers, R",
    "wof:placetype":"venue"
},
  "geometry": {"coordinates":[4.549893,51.928349],"type":"Point"}
}