{
  "type": "Feature",
  "properties": {
    "addr:full":"E V Wegbergpln 7 Heythuysen Limburg 6093 EX",
    "addr:housenumber":"7",
    "addr:postcode":"6093 ex",
    "addr:street":"Wegbergpln",
    "iso:country":"NL",
    "sg:address":"E V Wegbergpln 7",
    "sg:city":"Heythuysen",
    "sg:orig_category":"Boeken En Tijdschriften",
    "sg:phone":"+31 475 440 115",
    "sg:postcode":"6093 EX",
    "sg:province":"Limburg",
    "wof:name":"Bruna Brugmans",
    "wof:placetype":"venue"
},
  "geometry": {"coordinates":[5.89478,51.249954],"type":"Point"}
}