{
  "type": "Feature",
  "properties": {
    "addr:full":"E De Bruynstr 138 Secr Naarden North Holland 1411 TE",
    "addr:housenumber":"138",
    "addr:postcode":"1411 te",
    "addr:street":"E",
    "iso:country":"NL",
    "sg:address":"E De Bruynstr 138 Secr",
    "sg:city":"Naarden",
    "sg:orig_category":"Verenigingen En Stichtingen",
    "sg:phone":"+31 35 694 2760",
    "sg:postcode":"1411 TE",
    "sg:province":"North Holland",
    "wof:name":"Audiovisuele Kontakten, Ver",
    "wof:placetype":"venue"
},
  "geometry": {"coordinates":[5.161848,52.296371],"type":"Point"}
}