{
  "type": "Feature",
  "properties": {
    "iso:country":"NL",
    "sg:address":"Parelhoenhof 5",
    "sg:city":"Beuningen Gld",
    "sg:orig_category":"Adviesbureaus Elektrotechniek",
    "sg:phone":"+31 24 675 0217",
    "sg:postcode":"6641 DM",
    "sg:province":"Gelderland",
    "wof:name":"Dama Engineering Adviesbureau",
    "wof:placetype":"venue"
},
  "geometry": {"coordinates":[5.767461,51.857674],"type":"Point"}
}