{
  "type": "Feature",
  "properties": {
    "addr:full":"Parklaan 81 Eindhoven Noord-Brabant 5613 BB",
    "addr:housenumber":"81",
    "addr:postcode":"5613 bb",
    "addr:street":"Parklaan",
    "iso:country":"NL",
    "sg:address":"Parklaan 81",
    "sg:city":"Eindhoven",
    "sg:orig_category":"Werving And Selectie Van Tijdelijk Personeel And Uitzendkantoren",
    "sg:phone":"+31 40 235 8855",
    "sg:postcode":"5613 BB",
    "sg:province":"Noord-Brabant",
    "wof:name":"Avalix",
    "wof:placetype":"venue"
},
  "geometry": {"coordinates":[5.4933948517,51.4416809082],"type":"Point"}
}