{
  "type": "Feature",
  "properties": {
    "addr:full":"Badwg 8 Vlieland Provincie Friesland 8899 BV",
    "addr:housenumber":"8",
    "addr:postcode":"8899 bv",
    "addr:street":"Badwg;Friesland",
    "iso:country":"NL",
    "sg:address":"Badwg 8",
    "sg:city":"Vlieland",
    "sg:classifiers":[
        {
            "category":"Sports & Exercise",
            "subcategory":"Stables",
            "type":"Entertainment"
        }
    ],
    "sg:phone":"+31 562 451 962",
    "sg:postcode":"8899 BV",
    "sg:province":"Provincie Friesland",
    "sg:tags":[
        "maneges"
    ],
    "wof:name":"Seeruyter Manege, De",
    "wof:placetype":"venue"
},
  "geometry": {"coordinates":[5.053443,53.303093],"type":"Point"}
}