{
  "type": "Feature",
  "properties": {
    "addr:full":"Planterslaan 26 Leersum Utrecht 3956 VX",
    "addr:housenumber":"26",
    "addr:postcode":"3956 vx",
    "addr:street":"Planterslaan",
    "iso:country":"NL",
    "sg:address":"Planterslaan 26",
    "sg:city":"Leersum",
    "sg:orig_category":"Verpakkingsbedrijven",
    "sg:phone":"+31 343 413 512",
    "sg:postcode":"3956 VX",
    "sg:province":"Utrecht",
    "wof:name":"Vlot, A G",
    "wof:placetype":"venue"
},
  "geometry": {"coordinates":[5.436831,52.012531],"type":"Point"}
}