{
  "type": "Feature",
  "properties": {
    "addr:full":"Postbus 33000 Rotterdam 3005 EA",
    "addr:postcode":"33000;3005 ea",
    "addr:street":"Postbus",
    "iso:country":"NL",
    "sg:address":"Postbus 33000",
    "sg:city":"Rotterdam",
    "sg:orig_category":"Adviesbureaus Bedrijfsorganisatie",
    "sg:phone":"+31 10 418 3849",
    "sg:postcode":"3005 EA",
    "wof:name":"Hezik Bv, W J Van",
    "wof:placetype":"venue"
},
  "geometry": {"coordinates":[4.47075,51.922619],"type":"Point"}
}