{
  "type": "Feature",
  "properties": {
    "addr:full":"Millseweg 1 Beers Nb North Brabant 5437 NB",
    "addr:housenumber":"1",
    "addr:postcode":"5437 nb",
    "addr:street":"Millseweg",
    "iso:country":"NL",
    "sg:address":"Millseweg 1",
    "sg:city":"Beers Nb",
    "sg:orig_category":"Chemische Producten Gh",
    "sg:phone":"+31 485 314 333",
    "sg:postcode":"5437 NB",
    "sg:province":"North Brabant",
    "wof:name":"H.I.J. Van Haren",
    "wof:placetype":"venue"
},
  "geometry": {"coordinates":[5.823117,51.721718],"type":"Point"}
}