{
  "type": "Feature",
  "properties": {
    "addr:full":"Planetenbaan 26  Maarssen 3606 AK",
    "addr:housenumber":"26",
    "addr:postcode":"3606 ak",
    "addr:street":"Planetenbaan",
    "iso:country":"NL",
    "sg:address":"Planetenbaan 26",
    "sg:city":" Maarssen",
    "sg:classifiers":[
        {
            "category":"Professional",
            "subcategory":"Computer Services",
            "type":"Services"
        }
    ],
    "sg:postcode":"3606 AK",
    "sg:tags":[
        "mobile-work-order",
        "mobile-field-workers",
        "mobile-extention",
        "mobile-software-application",
        "mobile-software-solutions",
        "mobility",
        "software-development",
        "mobile-asset-management"
    ],
    "sg:website":"http://www.navara.com",
    "wof:name":"Navara",
    "wof:placetype":"venue"
},
  "geometry": {"coordinates":[5.038078,52.126616],"type":"Point"}
}