{
  "type": "Feature",
  "properties": {
    "iso:country":"NL",
    "sg:address":"Waterloolaan 17",
    "sg:city":"Driehuis Nh",
    "sg:classifiers":[
        {
            "category":"Education",
            "subcategory":"Preschool",
            "type":"Public Place"
        }
    ],
    "sg:phone":"+31 255 511 483",
    "sg:postcode":"1985 EP",
    "sg:province":"North Holland",
    "sg:tags":[
        "kleuteronderwijs",
        "basis-"
    ],
    "wof:name":"Jan Campert",
    "wof:placetype":"venue"
},
  "geometry": {"coordinates":[4.637266,52.449734],"type":"Point"}
}