{
  "type": "Feature",
  "properties": {
    "iso:country":"NL",
    "sg:address":"J Wattstr 24",
    "sg:city":"Leeuwarden",
    "sg:orig_category":"Onderhoudswerken",
    "sg:phone":"+31 58 212 1522",
    "sg:postcode":"8912 AS",
    "sg:province":"Friesland",
    "wof:name":"Ko-Bus",
    "wof:placetype":"venue"
},
  "geometry": {"coordinates":[5.762545,53.191116],"type":"Point"}
}