{
  "type": "Feature",
  "properties": {
    "addr:full":"9E Reit 68 S Hertogenbosch Noord-Brabant 5233 JK",
    "addr:housenumber":"68",
    "addr:postcode":"5233 jk",
    "addr:street":"9E Reit;S Hertogenbosch",
    "iso:country":"NL",
    "sg:address":"9E Reit 68",
    "sg:city":"S Hertogenbosch",
    "sg:orig_category":"Kappers",
    "sg:phone":"+31 73 641 3456",
    "sg:postcode":"5233 JK",
    "sg:province":"Noord-Brabant",
    "wof:name":"Mobistyle",
    "wof:placetype":"venue"
},
  "geometry": {"coordinates":[5.333771,51.715984],"type":"Point"}
}