{
  "type": "Feature",
  "properties": {
    "iso:country":"NL",
    "sg:address":"Vogelshoekschewg 1",
    "sg:city":"Escharen",
    "sg:orig_category":"Beeldende Kunstenaars",
    "sg:phone":"+31 486 420 103",
    "sg:postcode":"5364 NW",
    "sg:province":"North Brabant",
    "sg:website":"http://www.pvandelocht.nl",
    "wof:name":"Peter H Van De Locht",
    "wof:placetype":"venue"
},
  "geometry": {"coordinates":[5.758135,51.725479],"type":"Point"}
}