{
  "type": "Feature",
  "properties": {
    "addr:full":"Spoelstraat 7 Gilze North Brabant 5126 PD",
    "addr:housenumber":"7",
    "addr:postcode":"5126 pd",
    "addr:street":"Spoelstraat",
    "iso:country":"NL",
    "sg:address":"Spoelstraat 7",
    "sg:city":"Gilze",
    "sg:orig_category":"Kampeerterreinen",
    "sg:phone":"+31 161 451 625",
    "sg:postcode":"5126 PD",
    "sg:province":"North Brabant",
    "wof:name":"De Vossenberg",
    "wof:placetype":"venue"
},
  "geometry": {"coordinates":[4.9565181732,51.5463638306],"type":"Point"}
}