{
  "type": "Feature",
  "properties": {
    "addr:full":"Maasstraat 2 Steijl Limburg 5935 AL",
    "addr:housenumber":"2",
    "addr:postcode":"5935 al",
    "addr:street":"Maasstraat",
    "iso:country":"NL",
    "sg:address":"Maasstraat 2",
    "sg:city":"Steijl",
    "sg:orig_category":"Politie",
    "sg:phone":"+31 77 327 2200",
    "sg:postcode":"5935 AL",
    "sg:province":"Limburg",
    "wof:name":"Politie Basiseenheid Tegelen",
    "wof:placetype":"venue"
},
  "geometry": {"coordinates":[6.123025,51.333511],"type":"Point"}
}