{
  "type": "Feature",
  "properties": {
    "iso:country":"NL",
    "sg:address":"Overstr 28B",
    "sg:city":"Amerongen",
    "sg:orig_category":"Verenigingen En Stichtingen",
    "sg:phone":"+31 343 450 459",
    "sg:postcode":"3958 BV",
    "sg:province":"Utrecht",
    "wof:name":"Kunst In Amerongen",
    "wof:placetype":"venue"
},
  "geometry": {"coordinates":[5.457096,51.998726],"type":"Point"}
}