{
  "type": "Feature",
  "properties": {
    "addr:full":"Theems 152 Amstelveen North Holland 1186 KK",
    "addr:housenumber":"152",
    "addr:postcode":"1186 kk",
    "addr:street":"Theems",
    "iso:country":"NL",
    "sg:address":"Theems 152",
    "sg:city":"Amstelveen",
    "sg:orig_category":"Accountants - Administratie- Consulenten En -Kantoren",
    "sg:phone":"+31 20 647 0960",
    "sg:postcode":"1186 KK",
    "sg:province":"North Holland",
    "wof:name":"Visser, T G",
    "wof:placetype":"venue"
},
  "geometry": {"coordinates":[4.864481,52.289413],"type":"Point"}
}