{
  "type": "Feature",
  "properties": {
    "addr:full":"Tolnegenwg 3A Stroe Gelderland 3776 PT",
    "addr:housenumber":"3a",
    "addr:postcode":"3776",
    "addr:street":"Tolnegenwg;Gelderland;Pt",
    "iso:country":"NL",
    "sg:address":"Tolnegenwg 3A",
    "sg:city":"Stroe",
    "sg:orig_category":"Kunststof Ramen",
    "sg:phone":"+31 342 442 760",
    "sg:postcode":"3776 PT",
    "sg:province":"Gelderland",
    "wof:name":"Schimmel",
    "wof:placetype":"venue"
},
  "geometry": {"coordinates":[5.691116,52.188236],"type":"Point"}
}