{
  "type": "Feature",
  "properties": {
    "iso:country":"NL",
    "sg:address":"Smeestr 68",
    "sg:city":"Lochem",
    "sg:orig_category":"Antiquiteiten",
    "sg:phone":"+31 573 252 006",
    "sg:postcode":"7241 AT",
    "sg:province":"Gelderland",
    "wof:name":"Old Style",
    "wof:placetype":"venue"
},
  "geometry": {"coordinates":[6.416396,52.159912],"type":"Point"}
}