{
  "type": "Feature",
  "properties": {
    "addr:full":"Daniel Jos Jittastraat 8 Tilburg Noord-Brabant 5042 MX",
    "addr:housenumber":"8",
    "addr:postcode":"5042 mx",
    "addr:street":"Jittastraat",
    "iso:country":"NL",
    "sg:address":"Daniel Jos Jittastraat 8",
    "sg:city":"Tilburg",
    "sg:orig_category":"Huishoudapparatuur, Televisies And Radio'S",
    "sg:phone":"+31 13 467 0904",
    "sg:postcode":"5042 MX",
    "sg:province":"Noord-Brabant",
    "wof:name":"Van Helfteren Audio Video Electra Bv",
    "wof:placetype":"venue"
},
  "geometry": {"coordinates":[5.053553,51.568901],"type":"Point"}
}