{
  "type": "Feature",
  "properties": {
    "addr:full":"Ysselzoom 75 Capelle Ad Yssel South Holland 2902 LB",
    "addr:housenumber":"75",
    "addr:postcode":"2902 lb",
    "addr:street":"Ysselzoom;Yssel",
    "iso:country":"NL",
    "sg:address":"Ysselzoom 75",
    "sg:city":"Capelle Ad Yssel",
    "sg:orig_category":"Adviesbureaus Marketing",
    "sg:phone":"+31 10 451 0491",
    "sg:postcode":"2902 LB",
    "sg:province":"South Holland",
    "wof:name":"Win Schotting",
    "wof:placetype":"venue"
},
  "geometry": {"coordinates":[4.57697,51.926311],"type":"Point"}
}