{
  "type": "Feature",
  "properties": {
    "addr:full":"Hoofdwg 189 Siddeburen Groningen 9628 CN",
    "addr:housenumber":"189",
    "addr:postcode":"9628 cn",
    "addr:street":"Siddeburen",
    "iso:country":"NL",
    "sg:address":"Hoofdwg 189",
    "sg:city":"Siddeburen",
    "sg:orig_category":"Kappers",
    "sg:phone":"+31 598 431 385",
    "sg:postcode":"9628 CN",
    "sg:province":"Groningen",
    "wof:name":"Gina",
    "wof:placetype":"venue"
},
  "geometry": {"coordinates":[6.8703269958,53.2471237183],"type":"Point"}
}