{
  "type": "Feature",
  "properties": {
    "addr:full":"Jacobusstraat 217 Rotterdam South Holland 3012 JM",
    "addr:housenumber":"217",
    "addr:postcode":"3012 jm",
    "addr:street":"Jacobusstraat",
    "iso:country":"NL",
    "sg:address":"Jacobusstraat 217",
    "sg:city":"Rotterdam",
    "sg:orig_category":"Boekhouders",
    "sg:phone":"+31 10 411 5601",
    "sg:postcode":"3012 JM",
    "sg:province":"South Holland",
    "wof:name":"Finplus",
    "wof:placetype":"venue"
},
  "geometry": {"coordinates":[4.473903,51.917542],"type":"Point"}
}