{
  "type": "Feature",
  "properties": {
    "iso:country":"NL",
    "sg:address":"Brouwerstraat 10",
    "sg:city":"Almere",
    "sg:orig_category":"Medische Apparatuur And Prothesen Fab",
    "sg:phone":"+31 36 534 6191",
    "sg:postcode":"1315 BP",
    "sg:province":"Flevoland",
    "wof:name":"Beter Horen Audire",
    "wof:placetype":"venue"
},
  "geometry": {"coordinates":[5.21998,52.374531],"type":"Point"}
}