{
  "type": "Feature",
  "properties": {
    "iso:country":"NL",
    "sg:address":"Groene Wierde 3",
    "sg:city":"Kloosterburen",
    "sg:orig_category":"Verenigingen En Stichtingen",
    "sg:phone":"+31 595 487 006",
    "sg:postcode":"9977 PT",
    "sg:province":"Groningen",
    "wof:name":"Ntc",
    "wof:placetype":"venue"
},
  "geometry": {"coordinates":[6.377334,53.385727],"type":"Point"}
}