{
  "type": "Feature",
  "properties": {
    "addr:full":"Wijnruit 25 Oosterhout Nb Noord-Brabant 4907 HC",
    "addr:housenumber":"25",
    "addr:postcode":"4907 hc",
    "addr:street":"Wijnruit",
    "iso:country":"NL",
    "sg:address":"Wijnruit 25",
    "sg:city":"Oosterhout Nb",
    "sg:orig_category":"Architecten",
    "sg:phone":"+31 162 454 229",
    "sg:postcode":"4907 HC",
    "sg:province":"Noord-Brabant",
    "wof:name":"Bloemsma Tuinen",
    "wof:placetype":"venue"
},
  "geometry": {"coordinates":[4.880007,51.652725],"type":"Point"}
}