{
  "type": "Feature",
  "properties": {
    "addr:full":"Kerkewyk 25A Veenendaal Utrecht 3901 EB",
    "addr:housenumber":"25a",
    "addr:postcode":"3901 eb",
    "addr:street":"Kerkewyk",
    "iso:country":"NL",
    "sg:address":"Kerkewyk 25A",
    "sg:city":"Veenendaal",
    "sg:orig_category":"Belastingconsulenten/ Belastingadviseurs",
    "sg:phone":"+31 318 500 787",
    "sg:postcode":"3901 EB",
    "sg:province":"Utrecht",
    "wof:name":"Peppel Administratie, Van De",
    "wof:placetype":"venue"
},
  "geometry": {"coordinates":[5.554062,52.024399],"type":"Point"}
}