{
  "type": "Feature",
  "properties": {
    "addr:full":"Gertrudisboulevard 136 Bergen Op Zoom Noord-Brabant 4615 MB",
    "addr:housenumber":"136",
    "addr:postcode":"4615 mb",
    "addr:street":"Gertrudisboulevard",
    "iso:country":"NL",
    "sg:address":"Gertrudisboulevard 136",
    "sg:city":"Bergen Op Zoom",
    "sg:orig_category":"Kantoorartikelen",
    "sg:phone":"+31 164 241 286",
    "sg:postcode":"4615 MB",
    "sg:province":"Noord-Brabant",
    "wof:name":"Harry De Weerd Kantoormachines",
    "wof:placetype":"venue"
},
  "geometry": {"coordinates":[4.2821412086,51.4881401062],"type":"Point"}
}