{
  "type": "Feature",
  "properties": {
    "addr:full":"Veilingstr 1 Enschede Overijssel 7545 LZ",
    "addr:housenumber":"1",
    "addr:postcode":"7545 lz",
    "addr:street":"Veilingstr",
    "iso:country":"NL",
    "sg:address":"Veilingstr 1",
    "sg:city":"Enschede",
    "sg:orig_category":"Verhuur",
    "sg:phone":"+31 53 430 0444",
    "sg:postcode":"7545 LZ",
    "sg:province":"Overijssel",
    "wof:name":"P & R Verhuur",
    "wof:placetype":"venue"
},
  "geometry": {"coordinates":[6.871217,52.217113],"type":"Point"}
}