{
  "type": "Feature",
  "properties": {
    "addr:full":"Scandinavieln 33 Emmeloord Flevoland 8303 GN",
    "addr:housenumber":"33",
    "addr:postcode":"8303 gn",
    "addr:street":"Scandinavieln;Flevoland",
    "iso:country":"NL",
    "sg:address":"Scandinavieln 33",
    "sg:city":"Emmeloord",
    "sg:orig_category":"Biljartzalen",
    "sg:phone":"+31 527 620 294",
    "sg:postcode":"8303 GN",
    "sg:province":"Flevoland",
    "wof:name":"Entree",
    "wof:placetype":"venue"
},
  "geometry": {"coordinates":[5.740807,52.708767],"type":"Point"}
}