{
  "type": "Feature",
  "properties": {
    "addr:full":"Buitenwatersloot 29 Delft Zuid-Holland 2613 TA",
    "addr:housenumber":"29",
    "addr:postcode":"2613 ta",
    "addr:street":"Buitenwatersloot",
    "iso:country":"NL",
    "sg:address":"Buitenwatersloot 29",
    "sg:city":"Delft",
    "sg:orig_category":"Adviesbureaus Bedrijfsorganisatie",
    "sg:phone":"+31 15 214 4327",
    "sg:postcode":"2613 TA",
    "sg:province":"Zuid-Holland",
    "wof:name":"Boulogne, Rogier",
    "wof:placetype":"venue"
},
  "geometry": {"coordinates":[4.354248,52.00843],"type":"Point"}
}