{
  "type": "Feature",
  "properties": {
    "addr:full":"Larenseweg 4 Hilversum Noord-Holland 1221  C",
    "addr:housenumber":"4;1221 c",
    "addr:street":"Larenseweg",
    "iso:country":"NL",
    "sg:address":"Larenseweg 4",
    "sg:city":"Hilversum",
    "sg:orig_category":"Aannemers Woningbouw",
    "sg:phone":"+31 35 646 8456",
    "sg:postcode":"1221  C",
    "sg:province":"Noord-Holland",
    "wof:name":"Schoonmaakbedrijf Tanis",
    "wof:placetype":"venue"
},
  "geometry": {"coordinates":[5.18217,52.227352],"type":"Point"}
}