{
  "type": "Feature",
  "properties": {
    "addr:full":"Heidewg 2 Volendam Noord-Holland 1132 DB",
    "addr:housenumber":"2",
    "addr:postcode":"1132 db",
    "addr:street":"Heidewg",
    "iso:country":"NL",
    "sg:address":"Heidewg 2",
    "sg:city":"Volendam",
    "sg:orig_category":"Verenigingen En Stichtingen",
    "sg:phone":"+31 299 399 290",
    "sg:postcode":"1132 DB",
    "sg:province":"Noord-Holland",
    "wof:name":"Katholiek Onderwijs Volendam, Sticht",
    "wof:placetype":"venue"
},
  "geometry": {"coordinates":[5.056967,52.493298],"type":"Point"}
}