{
  "type": "Feature",
  "properties": {
    "addr:full":"Pelikaanstr 1A Zutphen Gelderland 7201 DR",
    "addr:housenumber":"1a;7201",
    "addr:street":"Pelikaanstr;Gelderland;Dr",
    "iso:country":"NL",
    "sg:address":"Pelikaanstr 1A",
    "sg:city":"Zutphen",
    "sg:classifiers":[
        {
            "category":"Food & Beverages",
            "subcategory":"Bakery",
            "type":"Retail Goods"
        }
    ],
    "sg:phone":"+31 575 518 869",
    "sg:postcode":"7201 DR",
    "sg:province":"Gelderland",
    "sg:tags":[
        "pizza"
    ],
    "wof:name":"Dolce Vita, La",
    "wof:placetype":"venue"
},
  "geometry": {"coordinates":[6.197673,52.139565],"type":"Point"}
}