{
  "type": "Feature",
  "properties": {
    "addr:full":"Middelkampseweg 2 Gameren Gelderland 5311 PC",
    "addr:housenumber":"2",
    "addr:postcode":"5311 pc",
    "addr:street":"Middelkampseweg;Gelderland",
    "iso:country":"NL",
    "sg:address":"Middelkampseweg 2",
    "sg:city":"Gameren",
    "sg:orig_category":"Overheidsdiensten",
    "sg:phone":"+31 418 561 416",
    "sg:postcode":"5311 PC",
    "sg:province":"Gelderland",
    "wof:name":"Dorpshuis Gambora",
    "wof:placetype":"venue"
},
  "geometry": {"coordinates":[5.2098960876,51.797744751],"type":"Point"}
}