{
  "type": "Feature",
  "properties": {
    "addr:full":"Hof 8 Amerongen Utrecht 3958 CH",
    "addr:housenumber":"8",
    "addr:postcode":"3958",
    "addr:street":"Hof",
    "iso:country":"NL",
    "sg:address":"Hof 8",
    "sg:city":"Amerongen",
    "sg:orig_category":"Elektrische Apparatuur Gh",
    "sg:phone":"+31 343 461 104",
    "sg:postcode":"3958 CH",
    "sg:province":"Utrecht",
    "wof:name":"Huibers Elektrotechnische Isolatie Syste",
    "wof:placetype":"venue"
},
  "geometry": {"coordinates":[5.46095,51.998196],"type":"Point"}
}