{
  "type": "Feature",
  "properties": {
    "addr:full":"Achter De Hoven 207 Leeuwarden Friesland 8933 CL",
    "addr:housenumber":"207",
    "addr:postcode":"8933",
    "addr:street":"Achter De Hoven",
    "iso:country":"NL",
    "sg:address":"Achter De Hoven 207",
    "sg:city":"Leeuwarden",
    "sg:orig_category":"Autokeuringen",
    "sg:phone":"+31 58 215 3032",
    "sg:postcode":"8933 CL",
    "sg:province":"Friesland",
    "wof:name":"Garage Van Apeldoorn De Lpg Specialist",
    "wof:placetype":"venue"
},
  "geometry": {"coordinates":[5.809327,53.196274],"type":"Point"}
}