{
  "type": "Feature",
  "properties": {
    "addr:full":"Langestr 9 Amsterdam Noord-Holland 1015 AK",
    "addr:housenumber":"9",
    "addr:postcode":"1015 ak",
    "addr:street":"Langestr",
    "iso:country":"NL",
    "sg:address":"Langestr 9",
    "sg:city":"Amsterdam",
    "sg:orig_category":"Beeldende Kunstenaars",
    "sg:phone":"+31 20 625 5679",
    "sg:postcode":"1015 AK",
    "sg:province":"Noord-Holland",
    "wof:name":"Rem?, J?Rg",
    "wof:placetype":"venue"
},
  "geometry": {"coordinates":[4.892701,52.378635],"type":"Point"}
}