{
  "type": "Feature",
  "properties": {
    "addr:full":"Tichelstraat 37 Amsterdam Noord-Holland 1015 KS",
    "addr:housenumber":"37",
    "addr:postcode":"1015 ks",
    "addr:street":"Tichelstraat",
    "iso:country":"NL",
    "sg:address":"Tichelstraat 37",
    "sg:city":"Amsterdam",
    "sg:orig_category":"Diverse Consumentenartikelen Gh",
    "sg:phone":"+31 20 627 7493",
    "sg:postcode":"1015 KS",
    "sg:province":"Noord-Holland",
    "wof:name":"Jahanka Vof",
    "wof:placetype":"venue"
},
  "geometry": {"coordinates":[4.881183,52.378658],"type":"Point"}
}