{
  "type": "Feature",
  "properties": {
    "addr:full":"Jagersbosstr 22A Rosmalen Noord-Brabant 5241 JT",
    "addr:housenumber":"22a",
    "addr:postcode":"5241 jt",
    "addr:street":"Jagersbosstr",
    "iso:country":"NL",
    "sg:address":"Jagersbosstr 22A",
    "sg:city":"Rosmalen",
    "sg:orig_category":"Juridische Adviseurs",
    "sg:phone":"+31 73 522 0988",
    "sg:postcode":"5241 JT",
    "sg:province":"Noord-Brabant",
    "wof:name":"Heijden, Van Der",
    "wof:placetype":"venue"
},
  "geometry": {"coordinates":[5.355171,51.719509],"type":"Point"}
}