{
  "type": "Feature",
  "properties": {
    "addr:full":"Dorpstraat 4 Simpelveld Limburg 6369 AM",
    "addr:housenumber":"4",
    "addr:postcode":"6369",
    "addr:street":"Dorpstraat",
    "iso:country":"NL",
    "sg:address":"Dorpstraat 4",
    "sg:city":"Simpelveld",
    "sg:classifiers":[
        {
            "category":"Professional",
            "subcategory":"Accounting & Tax Preparation",
            "type":"Services"
        }
    ],
    "sg:phone":"+31 45 568 0255",
    "sg:postcode":"6369 AM",
    "sg:province":"Limburg",
    "sg:tags":[
        "accountant"
    ],
    "wof:name":"Administratie En Verzekeringsservice Avs",
    "wof:placetype":"venue"
},
  "geometry": {"coordinates":[5.982154,50.83474],"type":"Point"}
}