{
  "type": "Feature",
  "properties": {
    "addr:full":"Tjipke Visserweg 2 Bergen Nh Noord-Holland 1862 VD",
    "addr:housenumber":"2",
    "addr:postcode":"1862 vd",
    "addr:street":"Tjipke Visserweg",
    "iso:country":"NL",
    "sg:address":"Tjipke Visserweg 2",
    "sg:city":"Bergen Nh",
    "sg:orig_category":"Huishoudapparatuur, Televisies And Radio'S",
    "sg:phone":"+31 72 589 8409",
    "sg:postcode":"1862 VD",
    "sg:province":"Noord-Holland",
    "wof:name":"Van Dorth Electrospeciaalzaak",
    "wof:placetype":"venue"
},
  "geometry": {"coordinates":[4.714421,52.664516],"type":"Point"}
}