{
  "type": "Feature",
  "properties": {
    "addr:full":"Beethovenlaan 102 Leiden Zuid-Holland 2324 EP",
    "addr:housenumber":"102",
    "addr:postcode":"2324 ep",
    "addr:street":"Beethovenlaan",
    "iso:country":"NL",
    "sg:address":"Beethovenlaan 102",
    "sg:city":"Leiden",
    "sg:orig_category":"Juridische Dienstverlening",
    "sg:phone":"+31 71 531 8860",
    "sg:postcode":"2324 EP",
    "sg:province":"Zuid-Holland",
    "wof:name":"Mr H F G Lemaire",
    "wof:placetype":"venue"
},
  "geometry": {"coordinates":[4.473514,52.140156],"type":"Point"}
}