{
  "type": "Feature",
  "properties": {
    "addr:full":"Jericholaan 20 Eindhoven North Brabant 5625 TH",
    "addr:housenumber":"20",
    "addr:postcode":"5625 th",
    "addr:street":"Jericholaan",
    "iso:country":"NL",
    "sg:address":"Jericholaan 20",
    "sg:city":"Eindhoven",
    "sg:classifiers":[
        {
            "category":"Fast Food",
            "type":"Food & Drink"
        }
    ],
    "sg:phone":"+31 40 211 3100",
    "sg:postcode":"5625 TH",
    "sg:province":"North Brabant",
    "sg:tags":[
        "afhaal",
        "restaurant"
    ],
    "wof:name":"Pico Bello Pizzalijn Bv",
    "wof:placetype":"venue"
},
  "geometry": {"coordinates":[5.48589,51.475437],"type":"Point"}
}