{
  "type": "Feature",
  "properties": {
    "addr:full":"Herestraat 109 Groningen Groningen 9711 LG",
    "addr:housenumber":"109",
    "addr:postcode":"9711 lg",
    "addr:street":"Herestraat",
    "iso:country":"NL",
    "sg:address":"Herestraat 109",
    "sg:city":"Groningen",
    "sg:orig_category":"Reclamebureaus",
    "sg:phone":"+31 50 312 6263",
    "sg:postcode":"9711 LG",
    "sg:province":"Groningen",
    "wof:name":"Van Marle Erkend Bureau Voor Reclame En Publicitei",
    "wof:placetype":"venue"
},
  "geometry": {"coordinates":[6.568897,53.214272],"type":"Point"}
}