{
  "type": "Feature",
  "properties": {
    "iso:country":"NL",
    "sg:address":"Broekhovensewg 130G",
    "sg:city":"Tilburg",
    "sg:orig_category":"Horloges - Groothandel",
    "sg:phone":"+31 13 580 1717",
    "sg:postcode":"5021 LJ",
    "sg:province":"Noord-Brabant",
    "wof:name":"Scafusia",
    "wof:placetype":"venue"
},
  "geometry": {"coordinates":[5.093448,51.545551],"type":"Point"}
}