{
  "type": "Feature",
  "properties": {
    "addr:full":"Delta-Industrieweg 38 Stellendam Zuid-Holland 3251 LX",
    "addr:housenumber":"38",
    "addr:postcode":"3251 lx",
    "addr:street":"Delta-Industrieweg",
    "iso:country":"NL",
    "sg:address":"Delta-Industrieweg 38",
    "sg:city":"Stellendam",
    "sg:orig_category":"Meubelzaken, Woning- And Keukeninrichting",
    "sg:phone":"+31 187 492 300",
    "sg:postcode":"3251 LX",
    "sg:province":"Zuid-Holland",
    "wof:name":"Meubel Expo Stellendam Bv",
    "wof:placetype":"venue"
},
  "geometry": {"coordinates":[4.035734,51.819748],"type":"Point"}
}