{
  "type": "Feature",
  "properties": {
    "addr:full":"Grote Kerkstraat 23 Hoogeveen Drenthe 7902 CE",
    "addr:housenumber":"23",
    "addr:postcode":"7902 ce",
    "addr:street":"Grote Kerkstraat",
    "iso:country":"NL",
    "sg:address":"Grote Kerkstraat 23",
    "sg:city":"Hoogeveen",
    "sg:orig_category":"Bedrijfsinventaris Gh",
    "sg:phone":"+31 528 233 800",
    "sg:postcode":"7902 CE",
    "sg:province":"Drenthe",
    "wof:name":"De Hairshop",
    "wof:placetype":"venue"
},
  "geometry": {"coordinates":[6.478676,52.726315],"type":"Point"}
}