{
  "type": "Feature",
  "properties": {
    "iso:country":"NL",
    "sg:address":"Valkenierslaan 67",
    "sg:city":"Breda",
    "sg:orig_category":"Werving And Selectie Van Tijdelijk Personeel And Uitzendkantoren",
    "sg:phone":"+31 76 565 6720",
    "sg:postcode":"4834 CA",
    "sg:province":"North Brabant",
    "wof:name":"Q-Flex",
    "wof:placetype":"venue"
},
  "geometry": {"coordinates":[4.795732975,51.571849823],"type":"Point"}
}