{
  "type": "Feature",
  "properties": {
    "addr:full":"Varsseveldsewg 30 Lichtenvoorde Gelderland 7131 BJ",
    "addr:housenumber":"30",
    "addr:postcode":"7131 bj",
    "addr:street":"Varsseveldsewg;Gelderland",
    "iso:country":"NL",
    "sg:address":"Varsseveldsewg 30",
    "sg:city":"Lichtenvoorde",
    "sg:classifiers":[
        {
            "category":"Food & Beverages",
            "subcategory":"Bakery",
            "type":"Retail Goods"
        }
    ],
    "sg:phone":"+31 544 371 239",
    "sg:postcode":"7131 BJ",
    "sg:province":"Gelderland",
    "sg:tags":[
        "brood",
        "en",
        "banket"
    ],
    "wof:name":"Oude Wesselink",
    "wof:placetype":"venue"
},
  "geometry": {"coordinates":[6.561215,51.987049],"type":"Point"}
}