{
  "type": "Feature",
  "properties": {
    "iso:country":"NL",
    "sg:address":"Kerkstraat 19",
    "sg:city":"Nuland",
    "sg:classifiers":[
        {
            "category":"Bakery",
            "type":"Food & Drink"
        }
    ],
    "sg:phone":"+31 73 532 2556",
    "sg:postcode":"5392 CA",
    "sg:province":"Noord-Brabant",
    "sg:tags":[
        "brood",
        "banket"
    ],
    "wof:name":"Van Roosmalen Brood En Banket Vof",
    "wof:placetype":"venue"
},
  "geometry": {"coordinates":[5.431825,51.73101],"type":"Point"}
}