{
  "type": "Feature",
  "properties": {
    "addr:full":"Siebengewaldseweg 26 Bergen Lb Limburg 5854 PC",
    "addr:housenumber":"26",
    "addr:postcode":"lb;5854 pc",
    "addr:street":"Siebengewaldseweg",
    "iso:country":"NL",
    "sg:address":"Siebengewaldseweg 26",
    "sg:city":"Bergen Lb",
    "sg:orig_category":"Paramedische Behandelingen",
    "sg:phone":"+31 485 343 090",
    "sg:postcode":"5854 PC",
    "sg:province":"Limburg",
    "wof:name":"M.J.A.G. Geelen-Berends",
    "wof:placetype":"venue"
},
  "geometry": {"coordinates":[-93.129936,36.705662],"type":"Point"}
}