{
  "type": "Feature",
  "properties": {
    "addr:full":"Rensgars 6 Schagen Noord-Holland 1741 BR",
    "addr:housenumber":"6",
    "addr:postcode":"1741 br",
    "addr:street":"Rensgars",
    "iso:country":"NL",
    "sg:address":"Rensgars 6",
    "sg:city":"Schagen",
    "sg:classifiers":[
        {
            "category":"Fast Food",
            "type":"Food & Drink"
        }
    ],
    "sg:phone":"+31 224 214 930",
    "sg:postcode":"1741 BR",
    "sg:province":"Noord-Holland",
    "sg:tags":[
        "afhaal",
        "restaurant"
    ],
    "wof:name":"Ristorante Pizzeria Italiano Donna Rosa",
    "wof:placetype":"venue"
},
  "geometry": {"coordinates":[4.795659,52.786091],"type":"Point"}
}