{
  "type": "Feature",
  "properties": {
    "addr:full":"Zandstraat 16 Alphen Nb North Brabant 5131 AC",
    "addr:housenumber":"16;nb",
    "addr:postcode":"5131 ac",
    "addr:street":"Zandstraat",
    "iso:country":"NL",
    "sg:address":"Zandstraat 16",
    "sg:city":"Alphen Nb",
    "sg:orig_category":"Sportclubs",
    "sg:phone":"+31 13 508 1825",
    "sg:postcode":"5131 AC",
    "sg:province":"North Brabant",
    "wof:name":"Voetbalvereniging Viola",
    "wof:placetype":"venue"
},
  "geometry": {"coordinates":[4.952733,51.487755],"type":"Point"}
}