{
  "type": "Feature",
  "properties": {
    "addr:full":"Westeinde 78 Oud Alblas Zuid-Holland 2969 BP",
    "addr:housenumber":"78",
    "addr:postcode":"2969 bp",
    "addr:street":"Westeinde;Oud Alblas",
    "iso:country":"NL",
    "sg:address":"Westeinde 78",
    "sg:city":"Oud Alblas",
    "sg:orig_category":"Hoefsmederijen",
    "sg:phone":"+31 184 691 499",
    "sg:postcode":"2969 BP",
    "sg:province":"Zuid-Holland",
    "wof:name":"Graaf, A Van De",
    "wof:placetype":"venue"
},
  "geometry": {"coordinates":[4.682467,51.858723],"type":"Point"}
}