{
  "type": "Feature",
  "properties": {
    "addr:full":"Florasingel 1 Bovenkarspel North Holland 1611 GA",
    "addr:housenumber":"1",
    "addr:postcode":"1611 ga",
    "addr:street":"Florasingel",
    "iso:country":"NL",
    "sg:address":"Florasingel 1",
    "sg:city":"Bovenkarspel",
    "sg:orig_category":"Autokeuringen",
    "sg:phone":"+31 228 513 655",
    "sg:postcode":"1611 GA",
    "sg:province":"North Holland",
    "wof:name":"Bp",
    "wof:placetype":"venue"
},
  "geometry": {"coordinates":[5.243141,52.688438],"type":"Point"}
}