{
  "type": "Feature",
  "properties": {
    "addr:full":"Dam 143 Alblasserdam Zuid-Holland 2951 GA",
    "addr:housenumber":"143",
    "addr:postcode":"2951 ga",
    "addr:street":"Dam",
    "iso:country":"NL",
    "sg:address":"Dam 143",
    "sg:city":"Alblasserdam",
    "sg:orig_category":"Verenigingen En Stichtingen",
    "sg:phone":"+31 78 693 0972",
    "sg:postcode":"2951 GA",
    "sg:province":"Zuid-Holland",
    "wof:name":"Vluchtelingenwerk",
    "wof:placetype":"venue"
},
  "geometry": {"coordinates":[4.660269,51.861435],"type":"Point"}
}