{
  "type": "Feature",
  "properties": {
    "addr:full":"Vijzelstraat 28 Amsterdam North Holland 1017 HK",
    "addr:housenumber":"28",
    "addr:postcode":"1017 hk",
    "addr:street":"Vijzelstraat",
    "iso:country":"NL",
    "sg:address":"Vijzelstraat 28",
    "sg:city":"Amsterdam",
    "sg:orig_category":"Fotostudio'S And Fotografen",
    "sg:phone":"+31 20 626 0883",
    "sg:postcode":"1017 HK",
    "sg:province":"North Holland",
    "wof:name":"Maarten Schets",
    "wof:placetype":"venue"
},
  "geometry": {"coordinates":[4.89275,52.365448],"type":"Point"}
}