{
  "type": "Feature",
  "properties": {
    "addr:full":"Binnen Bant Str 1 Amsterdam Missouri 1011 CH",
    "addr:housenumber":"1",
    "addr:postcode":"1011",
    "addr:street":"Binnen Bant Str",
    "iso:country":"NL",
    "sg:address":"Binnen Bant Str 1",
    "sg:city":"Amsterdam",
    "sg:classifiers":[
        {
            "category":"Food & Beverages",
            "subcategory":"Bakery",
            "type":"Retail Goods"
        }
    ],
    "sg:phone":"+31 20 320 6310",
    "sg:postcode":"1011 CH",
    "sg:province":"Missouri",
    "sg:tags":[
        "pizza"
    ],
    "wof:name":"Oscar",
    "wof:placetype":"venue"
},
  "geometry": {"coordinates":[-94.605186,38.381996],"type":"Point"}
}