{
  "type": "Feature",
  "properties": {
    "addr:full":"V Speykstr 12 S Gravenhage Zuid-Holland 2518 GC",
    "addr:housenumber":"12;gravenhage",
    "addr:postcode":"2518 gc",
    "addr:street":"S",
    "iso:country":"NL",
    "sg:address":"V Speykstr 12",
    "sg:city":"S Gravenhage",
    "sg:orig_category":"Schilders",
    "sg:phone":"+31 70 345 2545",
    "sg:postcode":"2518 GC",
    "sg:province":"Zuid-Holland",
    "sg:website":"http://www.brouwer-schilders.nl",
    "wof:name":"Brouwer Schildersbedrijf Bv",
    "wof:placetype":"venue"
},
  "geometry": {"coordinates":[4.29348,52.080318],"type":"Point"}
}