{
  "type": "Feature",
  "properties": {
    "addr:full":"Andorrawg 7 Ritthem Zeeland 4389 PG",
    "addr:housenumber":"7",
    "addr:postcode":"4389 pg",
    "addr:street":"Andorrawg",
    "iso:country":"NL",
    "sg:address":"Andorrawg 7",
    "sg:city":"Ritthem",
    "sg:orig_category":"Baggerwerken",
    "sg:phone":"+31 118 467 715",
    "sg:postcode":"4389 PG",
    "sg:province":"Zeeland",
    "wof:name":"Oord Bv, Van",
    "wof:placetype":"venue"
},
  "geometry": {"coordinates":[3.683265,51.472198],"type":"Point"}
}