{
  "type": "Feature",
  "properties": {
    "iso:country":"NL",
    "sg:address":"Buurmalseplein 1",
    "sg:city":"Tilburg",
    "sg:classifiers":[
        {
            "category":"Fast Food",
            "type":"Food & Drink"
        }
    ],
    "sg:phone":"+31 13 570 2050",
    "sg:postcode":"5043 XL",
    "sg:province":"Noord-Brabant",
    "sg:tags":[
        "afhaal",
        "restaurant"
    ],
    "wof:name":"De Reeshof",
    "wof:placetype":"venue"
},
  "geometry": {"coordinates":[5.018042,51.581757],"type":"Point"}
}