{
  "type": "Feature",
  "properties": {
    "addr:full":"Voltastraat 7 Leeuwarden Friesland 8912 AE",
    "addr:housenumber":"7",
    "addr:postcode":"8912 ae",
    "addr:street":"Voltastraat",
    "iso:country":"NL",
    "sg:address":"Voltastraat 7",
    "sg:city":"Leeuwarden",
    "sg:orig_category":"Drukkerijen And Copyshops",
    "sg:phone":"+31 58 298 7700",
    "sg:postcode":"8912 AE",
    "sg:province":"Friesland",
    "wof:name":"Nederlandse Rotatie Drukkerij Bv",
    "wof:placetype":"venue"
},
  "geometry": {"coordinates":[5.771936,53.19643],"type":"Point"}
}