{
  "type": "Feature",
  "properties": {
    "iso:country":"NL",
    "sg:address":"U T Delfiaweg 5",
    "sg:city":"Groningen",
    "sg:orig_category":"Verhuur Bouwmachines",
    "sg:phone":"+31 50 556 6444",
    "sg:postcode":"9745 EN",
    "sg:province":"Groningen",
    "wof:name":"Ferro Rent",
    "wof:placetype":"venue"
},
  "geometry": {"coordinates":[6.512167,53.215153],"type":"Point"}
}