{
  "type": "Feature",
  "properties": {
    "iso:country":"NL",
    "sg:address":"Nw Gouwe Oz 11B",
    "sg:city":"Gouda",
    "sg:orig_category":"Veilingen En Venduhuizen",
    "sg:phone":"+31 182 572 030",
    "sg:postcode":"2801 SB",
    "sg:province":"Zuid-Holland",
    "sg:website":"http://www.filatelist.com",
    "wof:name":"Boekenland",
    "wof:placetype":"venue"
},
  "geometry": {"coordinates":[4.684009,52.018795],"type":"Point"}
}