{
  "type": "Feature",
  "properties": {
    "iso:country":"NL",
    "sg:address":"Langestraat 152",
    "sg:city":"Klazienaveen",
    "sg:orig_category":"Meubelzaken, Woning- And Keukeninrichting",
    "sg:phone":"+31 591 312 324",
    "sg:postcode":"7891 GK",
    "sg:province":"Provincie Drenthe",
    "wof:name":"Fa. Henk Bruning",
    "wof:placetype":"venue"
},
  "geometry": {"coordinates":[6.997888,52.724129],"type":"Point"}
}