{
  "type": "Feature",
  "properties": {
    "addr:full":"Biezenstr 8 Eede Zld Zeeland 4529 JK",
    "addr:housenumber":"8",
    "addr:postcode":"4529 jk",
    "addr:street":"Biezenstr",
    "iso:country":"NL",
    "sg:address":"Biezenstr 8",
    "sg:city":"Eede Zld",
    "sg:orig_category":"Kunstmest",
    "sg:phone":"+31 117 491 628",
    "sg:postcode":"4529 JK",
    "sg:province":"Zeeland",
    "wof:name":"Cuelenaere",
    "wof:placetype":"venue"
},
  "geometry": {"coordinates":[3.461345,51.243778],"type":"Point"}
}