{
  "type": "Feature",
  "properties": {
    "addr:full":"Veemarktstraat 13 Breda Noord-Brabant 4811 ZB",
    "addr:housenumber":"13",
    "addr:postcode":"4811 zb",
    "addr:street":"Veemarktstraat",
    "iso:country":"NL",
    "sg:address":"Veemarktstraat 13",
    "sg:city":"Breda",
    "sg:orig_category":"Kunst And Kunstenaarsbenodigdheden",
    "sg:phone":"+31 76 522 1309",
    "sg:postcode":"4811 ZB",
    "sg:province":"Noord-Brabant",
    "wof:name":"Lijst-In",
    "wof:placetype":"venue"
},
  "geometry": {"coordinates":[4.777121,51.588303],"type":"Point"}
}