{
  "type": "Feature",
  "properties": {
    "addr:full":"Burgemeester Van Erpstr 57 Berghem Noord-Brabant 5351 AS",
    "addr:housenumber":"57",
    "addr:postcode":"5351 as",
    "addr:street":"Burgemeester Van Erpstr",
    "iso:country":"NL",
    "sg:address":"Burgemeester Van Erpstr 57",
    "sg:city":"Berghem",
    "sg:orig_category":"Autokeuringen",
    "sg:phone":"+31 412 401 133",
    "sg:postcode":"5351 AS",
    "sg:province":"Noord-Brabant",
    "wof:name":"Handelsonderneming Harrie Ruijs Bv",
    "wof:placetype":"venue"
},
  "geometry": {"coordinates":[5.575761,51.775772],"type":"Point"}
}