{
  "type": "Feature",
  "properties": {
    "iso:country":"NL",
    "sg:address":"Kempwg 9",
    "sg:city":"Horst",
    "sg:orig_category":"Lasbedrijven",
    "sg:phone":"+31 77 398 1647",
    "sg:postcode":"5964 ND",
    "sg:province":"Limburg",
    "wof:name":"Sterren, J H M Van Der",
    "wof:placetype":"venue"
},
  "geometry": {"coordinates":[-100.30171199999999,47.467731],"type":"Point"}
}