{
  "type": "Feature",
  "properties": {
    "iso:country":"NL",
    "sg:address":"Lanen 56",
    "sg:city":"Harlingen",
    "sg:orig_category":"Advocaten And Juridische Adviseurs",
    "sg:phone":"+31 517 418 453",
    "sg:postcode":"8861 CE",
    "sg:province":"Friesland",
    "wof:name":"Van Smeden Advocaten Bv",
    "wof:placetype":"venue"
},
  "geometry": {"coordinates":[5.4182019234,53.1738166809],"type":"Point"}
}