{
  "type": "Feature",
  "properties": {
    "addr:full":"Lopikerstr 23 Schoonhoven Zuid-Holland 2871 BT",
    "addr:housenumber":"23",
    "addr:postcode":"2871 bt",
    "addr:street":"Lopikerstr",
    "iso:country":"NL",
    "sg:address":"Lopikerstr 23",
    "sg:city":"Schoonhoven",
    "sg:classifiers":[
        {
            "category":"Shopping",
            "subcategory":"Adult",
            "type":"Retail Goods"
        }
    ],
    "sg:phone":"+31 182 382 284",
    "sg:postcode":"2871 BT",
    "sg:province":"Zuid-Holland",
    "sg:tags":[
        "lingerie",
        "en",
        "tricotage"
    ],
    "wof:name":"Wilco",
    "wof:placetype":"venue"
},
  "geometry": {"coordinates":[4.853119,51.946331],"type":"Point"}
}