{
  "type": "Feature",
  "properties": {
    "iso:country":"NL",
    "sg:address":"Fluitekruid 128",
    "sg:city":"Rotterdam",
    "sg:orig_category":"Glazenwasserijen",
    "sg:phone":"+31 10 420 3288",
    "sg:postcode":"3068 RR",
    "sg:province":"Zuid-Holland",
    "wof:name":"Bol, Fa J T H",
    "wof:placetype":"venue"
},
  "geometry": {"coordinates":[4.555282,51.955742],"type":"Point"}
}