{
  "type": "Feature",
  "properties": {
    "addr:full":"Hertzogstr 152 S Gravenhage Zuid-Holland 2572 XC",
    "addr:housenumber":"152;gravenhage",
    "addr:postcode":"2572 xc",
    "addr:street":"S",
    "iso:country":"NL",
    "sg:address":"Hertzogstr 152",
    "sg:city":"S Gravenhage",
    "sg:orig_category":"Adviesbureaus",
    "sg:phone":"+31 70 365 0023",
    "sg:postcode":"2572 XC",
    "sg:province":"Zuid-Holland",
    "wof:name":"P'Adds",
    "wof:placetype":"venue"
},
  "geometry": {"coordinates":[4.29421,52.06422],"type":"Point"}
}