{
  "type": "Feature",
  "properties": {
    "addr:full":"Lucasbolwerk 2 Utrecht Utrecht 3512 EG",
    "addr:housenumber":"2",
    "addr:postcode":"3512 eg",
    "addr:street":"Lucasbolwerk",
    "iso:country":"NL",
    "sg:address":"Lucasbolwerk 2",
    "sg:city":"Utrecht",
    "sg:orig_category":"Makelaars En Adviseurs Onroerende Goederen",
    "sg:phone":"+31 30 230 4530",
    "sg:postcode":"3512 EG",
    "sg:province":"Utrecht",
    "sg:website":"http://www.kooijmans-vastgoed.com",
    "wof:name":"Kooijmans Int Bv",
    "wof:placetype":"venue"
},
  "geometry": {"coordinates":[5.126296,52.093098],"type":"Point"}
}