{
  "type": "Feature",
  "properties": {
    "iso:country":"NL",
    "sg:address":"Hikkaarderdyk 31B",
    "sg:city":"Jislum",
    "sg:orig_category":"Kampeerterreinen",
    "sg:phone":"+31 519 332 339",
    "sg:postcode":"9177 GA",
    "sg:province":"Provincie Friesland",
    "wof:name":"Camping Zwanenburg",
    "wof:placetype":"venue"
},
  "geometry": {"coordinates":[5.8722519875,53.3062896729],"type":"Point"}
}