{
  "type": "Feature",
  "properties": {
    "iso:country":"NL",
    "sg:address":"Voetboogstr 33",
    "sg:city":"Amsterdam",
    "sg:orig_category":"Cafetaria'S",
    "sg:phone":"+31 20 624 6075",
    "sg:postcode":"1012 XK",
    "sg:province":"Noord-Holland",
    "wof:name":"Vlaamse Friethuis",
    "wof:placetype":"venue"
},
  "geometry": {"coordinates":[4.891091,52.367939],"type":"Point"}
}