{
  "type": "Feature",
  "properties": {
    "addr:full":"Pirolastraat 33 Amsterdam North Holland 1032 XW",
    "addr:housenumber":"33",
    "addr:postcode":"1032 xw",
    "addr:street":"Pirolastraat",
    "iso:country":"NL",
    "sg:address":"Pirolastraat 33",
    "sg:city":"Amsterdam",
    "sg:orig_category":"Beursorganisaties And Standbouw",
    "sg:phone":"+31 20 634 0185",
    "sg:postcode":"1032 XW",
    "sg:province":"North Holland",
    "wof:name":"H.J. Van Dam",
    "wof:placetype":"venue"
},
  "geometry": {"coordinates":[4.914345,52.39883],"type":"Point"}
}