{
  "type": "Feature",
  "properties": {
    "addr:full":"Grotestraat 27 Cuijk Noord-Brabant 5431 DH",
    "addr:housenumber":"27",
    "addr:postcode":"5431 dh",
    "addr:street":"Grotestraat",
    "iso:country":"NL",
    "sg:address":"Grotestraat 27",
    "sg:city":"Cuijk",
    "sg:orig_category":"Schoenen",
    "sg:phone":"+31 485 312 266",
    "sg:postcode":"5431 DH",
    "sg:province":"Noord-Brabant",
    "wof:name":"Ghijsen Schoenen",
    "wof:placetype":"venue"
},
  "geometry": {"coordinates":[5.829904,51.725136],"type":"Point"}
}