{
  "type": "Feature",
  "properties": {
    "iso:country":"NL",
    "sg:address":"Traaswg 5",
    "sg:city":"Markelo",
    "sg:orig_category":"Verzekerings- Maatschappijen",
    "sg:phone":"+31 547 361 910",
    "sg:postcode":"7475 PS",
    "sg:province":"Overijssel",
    "wof:name":"Bakkersbelang, Sticht",
    "wof:placetype":"venue"
},
  "geometry": {"coordinates":[6.474006,52.228596],"type":"Point"}
}