{
  "type": "Feature",
  "properties": {
    "addr:full":"Quarles Van Uffordstraat 93 Noordwijk Zh Zuid-Holland 2202 NE",
    "addr:housenumber":"93;2202",
    "addr:postcode":"ne",
    "addr:street":"Quarles Van Uffordstraat",
    "iso:country":"NL",
    "sg:address":"Quarles Van Uffordstraat 93",
    "sg:city":"Noordwijk Zh",
    "sg:orig_category":"Bedrijfs- And Managementsconsultants",
    "sg:phone":"+31 71 362 2613",
    "sg:postcode":"2202 NE",
    "sg:province":"Zuid-Holland",
    "wof:name":"Astraia Promotions",
    "wof:placetype":"venue"
},
  "geometry": {"coordinates":[4.436016,52.247608],"type":"Point"}
}