{
  "type": "Feature",
  "properties": {
    "addr:full":"Beukenln 1 Reusel Noord-Brabant 5541 VJ",
    "addr:housenumber":"1",
    "addr:postcode":"5541 vj",
    "addr:street":"Beukenln",
    "iso:country":"NL",
    "sg:address":"Beukenln 1",
    "sg:city":"Reusel",
    "sg:orig_category":"Artsen - Huisartsen",
    "sg:phone":"+31 497 641 900",
    "sg:postcode":"5541 VJ",
    "sg:province":"Noord-Brabant",
    "wof:name":"Sanders, W",
    "wof:placetype":"venue"
},
  "geometry": {"coordinates":[5.168723,51.362541],"type":"Point"}
}