{
  "type": "Feature",
  "properties": {
    "addr:full":"Energiewg 4A Den Helder Noord-Holland 1785 AD",
    "addr:housenumber":"4a",
    "addr:postcode":"1785 ad",
    "addr:street":"Energiewg",
    "iso:country":"NL",
    "sg:address":"Energiewg 4A",
    "sg:city":"Den Helder",
    "sg:orig_category":"Jachthavens - Jachtwerven",
    "sg:phone":"+31 223 669 278",
    "sg:postcode":"1785 AD",
    "sg:province":"Noord-Holland",
    "wof:name":"Baan",
    "wof:placetype":"venue"
},
  "geometry": {"coordinates":[4.770396,52.94603],"type":"Point"}
}