{
  "type": "Feature",
  "properties": {
    "addr:full":"Pastoor Van Leeuwenstr 77 Helmond Noord-Brabant 5701 JT",
    "addr:housenumber":"77",
    "addr:postcode":"5701 jt",
    "addr:street":"Pastoor Van Leeuwenstr",
    "iso:country":"NL",
    "sg:address":"Pastoor Van Leeuwenstr 77",
    "sg:city":"Helmond",
    "sg:orig_category":"Fitnesscentra",
    "sg:phone":"+31 492 550 213",
    "sg:postcode":"5701 JT",
    "sg:province":"Noord-Brabant",
    "wof:name":"Fitnesscentrum J.H.M. Van Berlo",
    "wof:placetype":"venue"
},
  "geometry": {"coordinates":[5.665261,51.47847],"type":"Point"}
}