{
  "type": "Feature",
  "properties": {
    "addr:full":"Luzernestr 40 Nieuw Vennep North Holland 2153 GN",
    "addr:housenumber":"40",
    "addr:postcode":"2153 gn",
    "addr:street":"Luzernestr;Nieuw Vennep North",
    "iso:country":"NL",
    "sg:address":"Luzernestr 40",
    "sg:city":"Nieuw Vennep",
    "sg:orig_category":"Levensmiddelen - Fabrieken En Groothandel",
    "sg:phone":"+31 252 687 936",
    "sg:postcode":"2153 GN",
    "sg:province":"North Holland",
    "wof:name":"Showa Boeki Europa Bv",
    "wof:placetype":"venue"
},
  "geometry": {"coordinates":[4.64851,52.263031],"type":"Point"}
}