{
  "type": "Feature",
  "properties": {
    "addr:full":"Sasdk 10 Werkendam Noord-Brabant 4251 AA",
    "addr:housenumber":"10",
    "addr:postcode":"4251 aa",
    "addr:street":"Sasdk",
    "iso:country":"NL",
    "sg:address":"Sasdk 10",
    "sg:city":"Werkendam",
    "sg:orig_category":"Onroerende Goederen",
    "sg:phone":"+31 183 508 666",
    "sg:postcode":"4251 AA",
    "sg:province":"Noord-Brabant",
    "wof:name":"Rijn-Delta Cv",
    "wof:placetype":"venue"
},
  "geometry": {"coordinates":[4.894164,51.815109],"type":"Point"}
}