{
  "type": "Feature",
  "properties": {
    "addr:full":"Keizersgracht 391 Amsterdam Noord-Holland 1016 EJ",
    "addr:housenumber":"391",
    "addr:postcode":"1016 ej",
    "addr:street":"Keizersgracht",
    "iso:country":"NL",
    "sg:address":"Keizersgracht 391",
    "sg:city":"Amsterdam",
    "sg:orig_category":"Bedrijfs- And Managementsconsultants",
    "sg:phone":"+31 20 420 1601",
    "sg:postcode":"1016 EJ",
    "sg:province":"Noord-Holland",
    "wof:name":"Margin Consultancy Bv",
    "wof:placetype":"venue"
},
  "geometry": {"coordinates":[4.884956,52.367912],"type":"Point"}
}