{
  "type": "Feature",
  "properties": {
    "addr:full":"Prins Bernhardstraat 17 Nunspeet Gelderland 8071 LW",
    "addr:housenumber":"17",
    "addr:postcode":"8071 lw",
    "addr:street":"Prins Bernhardstraat;Gelderland",
    "iso:country":"NL",
    "sg:address":"Prins Bernhardstraat 17",
    "sg:city":"Nunspeet",
    "sg:classifiers":[
        {
            "category":"Education",
            "subcategory":"Preschool",
            "type":"Public Place"
        }
    ],
    "sg:phone":"+31 341 258 037",
    "sg:postcode":"8071 LW",
    "sg:province":"Gelderland",
    "sg:tags":[
        "kleuteronderwijs",
        "basis-"
    ],
    "wof:name":"Prot Chr Bambino",
    "wof:placetype":"venue"
},
  "geometry": {"coordinates":[5.77999,52.381542],"type":"Point"}
}