{
  "type": "Feature",
  "properties": {
    "addr:full":"Amstelveensewg 140 Amsterdam Noord-Holland 1075 XM",
    "addr:housenumber":"140",
    "addr:postcode":"1075 xm",
    "iso:country":"NL",
    "sg:address":"Amstelveensewg 140",
    "sg:city":"Amsterdam",
    "sg:orig_category":"Artiesten/Gezelschappen",
    "sg:phone":"+31 20 675 0392",
    "sg:postcode":"1075 XM",
    "sg:province":"Noord-Holland",
    "wof:name":"Paxy Dragon",
    "wof:placetype":"venue"
},
  "geometry": {"coordinates":[4.855503,52.354088],"type":"Point"}
}