{
  "type": "Feature",
  "properties": {
    "addr:full":"Statenjachtstr 4 Amsterdam Noord-Holland 1034 EC",
    "addr:housenumber":"4",
    "addr:postcode":"1034 ec",
    "addr:street":"Statenjachtstr",
    "iso:country":"NL",
    "sg:address":"Statenjachtstr 4",
    "sg:city":"Amsterdam",
    "sg:orig_category":"Koeriersdiensten",
    "sg:phone":"+31 6 24778327",
    "sg:postcode":"1034 EC",
    "sg:province":"Noord-Holland",
    "wof:name":"Baryar",
    "wof:placetype":"venue"
},
  "geometry": {"coordinates":[4.918759,52.40667],"type":"Point"}
}