{
  "type": "Feature",
  "properties": {
    "addr:full":"Rakstr 9B Rotterdam South Holland 3034 RD",
    "addr:housenumber":"9b",
    "addr:postcode":"3034 rd",
    "addr:street":"Rakstr",
    "iso:country":"NL",
    "sg:address":"Rakstr 9B",
    "sg:city":"Rotterdam",
    "sg:orig_category":"Onderhoudswerken",
    "sg:phone":"+31 6 17330534",
    "sg:postcode":"3034 RD",
    "sg:province":"South Holland",
    "wof:name":"Mulderklus",
    "wof:placetype":"venue"
},
  "geometry": {"coordinates":[4.49116,51.935638],"type":"Point"}
}