{
  "type": "Feature",
  "properties": {
    "addr:full":"Bloemgracht 51 Amsterdam Noord-Holland 1016 KD",
    "addr:housenumber":"51",
    "addr:postcode":"1016 kd",
    "addr:street":"Bloemgracht",
    "iso:country":"NL",
    "sg:address":"Bloemgracht 51",
    "sg:city":"Amsterdam",
    "sg:orig_category":"Architecten",
    "sg:phone":"+31 20 622 4568",
    "sg:postcode":"1016 KD",
    "sg:province":"Noord-Holland",
    "wof:name":"Spreeuwenberg Architektenburo Bna",
    "wof:placetype":"venue"
},
  "geometry": {"coordinates":[4.88107,52.373951],"type":"Point"}
}