{
  "type": "Feature",
  "properties": {
    "iso:country":"NL",
    "sg:address":"Notel 49",
    "sg:city":"Oirschot",
    "sg:orig_category":"Overkappingen",
    "sg:phone":"+31 499 461 938",
    "sg:postcode":"5688 NB",
    "sg:province":"North Brabant",
    "sg:website":"http://www.texabri.com",
    "wof:name":"Texabri Benelux",
    "wof:placetype":"venue"
},
  "geometry": {"coordinates":[5.3192710876,51.5140953064],"type":"Point"}
}