{
  "type": "Feature",
  "properties": {
    "addr:full":"Voorstraat 279 Dordrecht Zuid-Holland 3311 EP",
    "addr:housenumber":"279",
    "addr:postcode":"3311 ep",
    "addr:street":"Voorstraat",
    "iso:country":"NL",
    "sg:address":"Voorstraat 279",
    "sg:city":"Dordrecht",
    "sg:orig_category":"Verlichting And Huishoudartikelen",
    "sg:phone":"+31 78 631 7167",
    "sg:postcode":"3311 EP",
    "sg:province":"Zuid-Holland",
    "wof:name":"Carleentje",
    "wof:placetype":"venue"
},
  "geometry": {"coordinates":[4.667999,51.815376],"type":"Point"}
}