{
  "type": "Feature",
  "properties": {
    "addr:full":"Industriewg 15 Ter Apel Groningen 9561 MB",
    "addr:housenumber":"15",
    "addr:postcode":"9561 mb",
    "addr:street":"Industriewg",
    "iso:country":"NL",
    "sg:address":"Industriewg 15",
    "sg:city":"Ter Apel",
    "sg:orig_category":"Keuken- Groot-Installaties",
    "sg:phone":"+31 599 589 999",
    "sg:postcode":"9561 MB",
    "sg:province":"Groningen",
    "sg:website":"http://www.presswoodgrootkeuken.nl",
    "wof:name":"Presswood Bv",
    "wof:placetype":"venue"
},
  "geometry": {"coordinates":[7.05095,52.88805],"type":"Point"}
}