{
  "type": "Feature",
  "properties": {
    "addr:full":"Laanenderweg 38 Alkmaar North Holland 1812 PW",
    "addr:housenumber":"38",
    "addr:postcode":"1812 pw",
    "addr:street":"Laanenderweg",
    "iso:country":"NL",
    "sg:address":"Laanenderweg 38",
    "sg:city":"Alkmaar",
    "sg:orig_category":"Verhuur",
    "sg:phone":"+31 72 540 4020",
    "sg:postcode":"1812 PW",
    "sg:province":"North Holland",
    "wof:name":"Hss Hire Shop",
    "wof:placetype":"venue"
},
  "geometry": {"coordinates":[4.764,52.612225],"type":"Point"}
}