{
  "type": "Feature",
  "properties": {
    "addr:full":"Postbus 1032 Oud Beyerland Noord-Holland 3260 AA",
    "addr:housenumber":"1032",
    "addr:postcode":"3260 aa",
    "addr:street":"Postbus;Oud Beyerland",
    "iso:country":"NL",
    "sg:address":"Postbus 1032",
    "sg:city":"Oud Beyerland",
    "sg:orig_category":"Administratie- En Boekhoudkantoren",
    "sg:phone":"+31 186 621 310",
    "sg:postcode":"3260 AA",
    "sg:province":"Noord-Holland",
    "wof:name":"Boertje Bv",
    "wof:placetype":"venue"
},
  "geometry": {"coordinates":[4.40917,51.82272],"type":"Point"}
}