{
  "type": "Feature",
  "properties": {
    "addr:full":"Bloemengaarde 23A Bergambacht Zuid-Holland 2861 VM",
    "addr:housenumber":"23a",
    "addr:postcode":"2861 vm",
    "addr:street":"Bloemengaarde",
    "iso:country":"NL",
    "sg:address":"Bloemengaarde 23A",
    "sg:city":"Bergambacht",
    "sg:orig_category":"Woningbouw- Verenigingen En -Stichtingen",
    "sg:phone":"+31 182 353 801",
    "sg:postcode":"2861 VM",
    "sg:province":"Zuid-Holland",
    "wof:name":"Bergambacht",
    "wof:placetype":"venue"
},
  "geometry": {"coordinates":[4.7873840332,51.9346580505],"type":"Point"}
}