{
  "type": "Feature",
  "properties": {
    "addr:full":"Laan 41 Nunspeet Gelderland 8071 JH",
    "addr:housenumber":"41",
    "addr:postcode":"8071 jh",
    "addr:street":"Laan;Gelderland",
    "iso:country":"NL",
    "sg:address":"Laan 41",
    "sg:city":"Nunspeet",
    "sg:orig_category":"Artsen - Huisartsen",
    "sg:phone":"+31 341 252 395",
    "sg:postcode":"8071 JH",
    "sg:province":"Gelderland",
    "wof:name":"Geurts, H G M",
    "wof:placetype":"venue"
},
  "geometry": {"coordinates":[5.786487,52.379772],"type":"Point"}
}