{
  "type": "Feature",
  "properties": {
    "addr:full":"Rembrandtwg 25 Noordwyk Zh Zuid-Holland 2202 AT",
    "addr:housenumber":"25",
    "addr:postcode":"2202",
    "addr:street":"Rembrandtwg",
    "iso:country":"NL",
    "sg:address":"Rembrandtwg 25",
    "sg:city":"Noordwyk Zh",
    "sg:orig_category":"Adviesbureaus Bedrijfsorganisatie",
    "sg:phone":"+31 71 361 1022",
    "sg:postcode":"2202 AT",
    "sg:province":"Zuid-Holland",
    "wof:name":"Hyalko Bv",
    "wof:placetype":"venue"
},
  "geometry": {"coordinates":[4.428865,52.237267],"type":"Point"}
}