{
  "type": "Feature",
  "properties": {
    "addr:full":"De Brinio 23 Hellevoetsluis Zuid-Holland 3224 GE",
    "addr:housenumber":"23",
    "addr:postcode":"3224",
    "addr:street":"De Brinio",
    "iso:country":"NL",
    "sg:address":"De Brinio 23",
    "sg:city":"Hellevoetsluis",
    "sg:orig_category":"Verenigingen En Stichtingen",
    "sg:phone":"+31 181 319 912",
    "sg:postcode":"3224 GE",
    "sg:province":"Zuid-Holland",
    "wof:name":"Ebbeheuvel, De",
    "wof:placetype":"venue"
},
  "geometry": {"coordinates":[4.152419,51.825298],"type":"Point"}
}