{
  "type": "Feature",
  "properties": {
    "addr:full":"Voorstad 18 Sittard Limburg 6131 CR",
    "addr:housenumber":"18;6131",
    "addr:postcode":"cr",
    "addr:street":"Voorstad",
    "iso:country":"NL",
    "sg:address":"Voorstad 18",
    "sg:city":"Sittard",
    "sg:classifiers":[
        {
            "category":"Shopping",
            "subcategory":"Gifts & Souvenirs",
            "type":"Retail Goods"
        }
    ],
    "sg:phone":"+31 46 458 4055",
    "sg:postcode":"6131 CR",
    "sg:province":"Limburg",
    "sg:tags":[
        "geschenken"
    ],
    "wof:name":"Kosnix",
    "wof:placetype":"venue"
},
  "geometry": {"coordinates":[5.864106,50.998817],"type":"Point"}
}