{
  "type": "Feature",
  "properties": {
    "addr:full":"Walborg 3 Amsterdam North Holland 1082 AM",
    "addr:housenumber":"3",
    "addr:postcode":"1082",
    "addr:street":"Walborg",
    "iso:country":"NL",
    "sg:address":"Walborg 3",
    "sg:city":"Amsterdam",
    "sg:orig_category":"Onroerende Goederen",
    "sg:phone":"+31 20 644 5528",
    "sg:postcode":"1082 AM",
    "sg:province":"North Holland",
    "wof:name":"Sellmeyer, J B",
    "wof:placetype":"venue"
},
  "geometry": {"coordinates":[4.874306,52.324512],"type":"Point"}
}