{
  "type": "Feature",
  "properties": {
    "iso:country":"NL",
    "sg:address":"Borculosewg 52",
    "sg:city":"Eibergen",
    "sg:orig_category":"Woningbouw- Verenigingen En -Stichtingen",
    "sg:phone":"+31 545 463 400",
    "sg:postcode":"7151 MR",
    "sg:province":"Gelderland",
    "sg:website":"http://www.woonklavier.nl",
    "wof:name":"Woonklavier",
    "wof:placetype":"venue"
},
  "geometry": {"coordinates":[6.6338281631,52.1058120728],"type":"Point"}
}