{
  "type": "Feature",
  "properties": {
    "addr:full":"Tiendwg W 45C Krimpen Aan De Lek Zuid-Holland 2931 LH",
    "addr:housenumber":"45c",
    "addr:postcode":"2931 lh",
    "addr:street":"W",
    "iso:country":"NL",
    "sg:address":"Tiendwg W 45C",
    "sg:city":"Krimpen Aan De Lek",
    "sg:orig_category":"Wormenkwekerijen",
    "sg:phone":"+31 180 522 678",
    "sg:postcode":"2931 LH",
    "sg:province":"Zuid-Holland",
    "wof:name":"Geda",
    "wof:placetype":"venue"
},
  "geometry": {"coordinates":[4.6424331665,51.900352478],"type":"Point"}
}