{
  "type": "Feature",
  "properties": {
    "addr:full":"Postbus 19 Harkstede Groningen 9617 ZG",
    "addr:housenumber":"19",
    "addr:postcode":"9617 zg",
    "addr:street":"Postbus",
    "iso:country":"NL",
    "sg:address":"Postbus 19",
    "sg:city":"Harkstede",
    "sg:orig_category":"Scholen Voor Basisonderwijs",
    "sg:phone":"+31 50 404 1675",
    "sg:postcode":"9617 ZG",
    "sg:province":"Groningen",
    "wof:name":"Driespan Openb, De",
    "wof:placetype":"venue"
},
  "geometry": {"coordinates":[6.69389,53.212566],"type":"Point"}
}