{
  "type": "Feature",
  "properties": {
    "addr:full":"Burgemeester Posweg 8 Brakel Gelderland 5306 GD",
    "addr:housenumber":"8",
    "addr:postcode":"5306 gd",
    "addr:street":"Burgemeester Posweg;Gelderland",
    "iso:country":"NL",
    "sg:address":"Burgemeester Posweg 8",
    "sg:city":"Brakel",
    "sg:orig_category":"Antiekzaken",
    "sg:phone":"+31 418 671 269",
    "sg:postcode":"5306 GD",
    "sg:province":"Gelderland",
    "wof:name":"G.C.L. Vervoorn",
    "wof:placetype":"venue"
},
  "geometry": {"coordinates":[5.098117,51.819969],"type":"Point"}
}