{
  "type": "Feature",
  "properties": {
    "iso:country":"NL",
    "sg:address":"Van Bijnkershoeklaan 10",
    "sg:city":"Utrecht",
    "sg:orig_category":"Overheidsdiensten",
    "sg:phone":"+31 30 294 6384",
    "sg:postcode":"3527 XL",
    "sg:province":"Utrecht",
    "wof:name":"De Paraplu",
    "wof:placetype":"venue"
},
  "geometry": {"coordinates":[5.0965437889,52.0796928406],"type":"Point"}
}