{
  "type": "Feature",
  "properties": {
    "iso:country":"NL",
    "sg:address":"Spoorstr 11",
    "sg:city":"Alkmaar",
    "sg:orig_category":"Onderhoudswerken",
    "sg:phone":"+31 72 512 3280",
    "sg:postcode":"1815 BG",
    "sg:province":"North Holland",
    "wof:name":"Donker Bv",
    "wof:placetype":"venue"
},
  "geometry": {"coordinates":[4.743746,52.635963],"type":"Point"}
}