{
  "type": "Feature",
  "properties": {
    "addr:full":"Middachtenstraat 48 Breda Noord-Brabant 4834 PC",
    "addr:housenumber":"48",
    "addr:postcode":"4834 pc",
    "addr:street":"Middachtenstraat",
    "iso:country":"NL",
    "sg:address":"Middachtenstraat 48",
    "sg:city":"Breda",
    "sg:orig_category":"Diverse Bedrijfsinstallaties Gh",
    "sg:phone":"+31 76 564 9410",
    "sg:postcode":"4834 PC",
    "sg:province":"Noord-Brabant",
    "wof:name":"Stavon Bv",
    "wof:placetype":"venue"
},
  "geometry": {"coordinates":[4.81486,51.571892],"type":"Point"}
}