{
  "type": "Feature",
  "properties": {
    "addr:full":"Noordsngl 52 Swifterbant NL. 8255 AE",
    "addr:housenumber":"52",
    "addr:postcode":"8255 ae",
    "addr:street":"Noordsngl;Nl.",
    "iso:country":"NL",
    "sg:address":"Noordsngl 52",
    "sg:city":"Swifterbant",
    "sg:orig_category":"Banken",
    "sg:phone":"+31 320 292 500",
    "sg:postcode":"8255 AE",
    "sg:province":"NL.",
    "sg:website":"http://www.rabobank.nl",
    "wof:name":"Rabobank",
    "wof:placetype":"venue"
},
  "geometry": {"coordinates":[5.6436190605,52.5717201233],"type":"Point"}
}