{
  "type": "Feature",
  "properties": {
    "iso:country":"NL",
    "sg:address":"Franciscusweg 137",
    "sg:city":"Hilversum",
    "sg:orig_category":"Kappers",
    "sg:phone":"+31 35 624 5490",
    "sg:postcode":"1216 SB",
    "sg:province":"Noord-Holland",
    "wof:name":"Ans Jurna Haarmode",
    "wof:placetype":"venue"
},
  "geometry": {"coordinates":[5.1461381912,52.2150306702],"type":"Point"}
}