{
  "type": "Feature",
  "properties": {
    "addr:full":"Hofwg 11 Spykenisse Zuid-Holland 3208 LE",
    "addr:housenumber":"11",
    "addr:postcode":"3208 le",
    "addr:street":"Hofwg",
    "iso:country":"NL",
    "sg:address":"Hofwg 11",
    "sg:city":"Spykenisse",
    "sg:classifiers":[
        {
            "category":"Food & Beverages",
            "subcategory":"Bakery",
            "type":"Retail Goods"
        }
    ],
    "sg:phone":"+31 181 690 400",
    "sg:postcode":"3208 LE",
    "sg:province":"Zuid-Holland",
    "sg:tags":[
        "brood",
        "en",
        "banket"
    ],
    "wof:name":"Breggen Bakkers, Van Der",
    "wof:placetype":"venue"
},
  "geometry": {"coordinates":[4.3029,51.84264],"type":"Point"}
}