{
  "type": "Feature",
  "properties": {
    "addr:full":"Vinkerstr 74 Kerkrade Limburg 6464 GM",
    "addr:housenumber":"74",
    "addr:postcode":"6464 gm",
    "addr:street":"Vinkerstr",
    "iso:country":"NL",
    "sg:address":"Vinkerstr 74",
    "sg:city":"Kerkrade",
    "sg:orig_category":"Keramiek - Fabrieken En Groothandel",
    "sg:phone":"+31 45 546 3887",
    "sg:postcode":"6464 GM",
    "sg:province":"Limburg",
    "wof:name":"Teka",
    "wof:placetype":"venue"
},
  "geometry": {"coordinates":[6.066865,50.881325],"type":"Point"}
}