{
  "type": "Feature",
  "properties": {
    "addr:full":"Langestr 104 Winschoten Groningen 9671 PN",
    "addr:housenumber":"104",
    "addr:postcode":"9671 pn",
    "addr:street":"Winschoten",
    "iso:country":"NL",
    "sg:address":"Langestr 104",
    "sg:city":"Winschoten",
    "sg:orig_category":"Woningstoffeerders",
    "sg:phone":"+31 597 675 754",
    "sg:postcode":"9671 PN",
    "sg:province":"Groningen",
    "wof:name":"Ballema, R P",
    "wof:placetype":"venue"
},
  "geometry": {"coordinates":[7.0339980125,53.1460533142],"type":"Point"}
}