{
  "type": "Feature",
  "properties": {
    "addr:full":"Hemwg 8 Wydenes Noord-Holland 1608 HL",
    "addr:housenumber":"8",
    "addr:postcode":"1608 hl",
    "addr:street":"Hemwg",
    "iso:country":"NL",
    "sg:address":"Hemwg 8",
    "sg:city":"Wydenes",
    "sg:orig_category":"Pluimveebedrijven En -Handelaren",
    "sg:phone":"+31 229 501 451",
    "sg:postcode":"1608 HL",
    "sg:province":"Noord-Holland",
    "wof:name":"Wydenes Bv",
    "wof:placetype":"venue"
},
  "geometry": {"coordinates":[5.153829,52.654842],"type":"Point"}
}