{
  "type": "Feature",
  "properties": {
    "iso:country":"NL",
    "sg:address":"Industrieweg 12",
    "sg:city":"Zuidbroek",
    "sg:orig_category":"Gebouwenafwerking, Renovaties And Reiniging",
    "sg:phone":"+31 598 453 436",
    "sg:postcode":"9636 DB",
    "sg:province":"Groningen",
    "wof:name":"Straal- En Coatingsbedrijf Sips Bv",
    "wof:placetype":"venue"
},
  "geometry": {"coordinates":[6.879877,53.161846],"type":"Point"}
}