{
  "type": "Feature",
  "properties": {
    "iso:country":"NL",
    "sg:address":"Braamhof 2",
    "sg:city":"Heemskerk",
    "sg:orig_category":"Boekhouders",
    "sg:phone":"+31 251 247 765",
    "sg:postcode":"1964 LP",
    "sg:province":"Noord-Holland",
    "wof:name":"J W Aerts",
    "wof:placetype":"venue"
},
  "geometry": {"coordinates":[4.657284,52.511497],"type":"Point"}
}