{
  "type": "Feature",
  "properties": {
    "addr:full":"Ereprijs 36 Leeuwarden Friesland 8935 JH",
    "addr:housenumber":"36",
    "addr:postcode":"8935 jh",
    "addr:street":"Ereprijs",
    "iso:country":"NL",
    "sg:address":"Ereprijs 36",
    "sg:city":"Leeuwarden",
    "sg:orig_category":"Kappers",
    "sg:phone":"+31 58 288 5508",
    "sg:postcode":"8935 JH",
    "sg:province":"Friesland",
    "wof:name":"Ellen'S Hair Studio",
    "wof:placetype":"venue"
},
  "geometry": {"coordinates":[5.819890976,53.1858329773],"type":"Point"}
}