{
  "type": "Feature",
  "properties": {
    "addr:full":"Wilhelminastr 15 Breda Noord-Brabant 4818 SB",
    "addr:housenumber":"15",
    "addr:postcode":"4818 sb",
    "addr:street":"Wilhelminastr",
    "iso:country":"NL",
    "sg:address":"Wilhelminastr 15",
    "sg:city":"Breda",
    "sg:orig_category":"Juweliers",
    "sg:phone":"+31 76 520 5534",
    "sg:postcode":"4818 SB",
    "sg:province":"Noord-Brabant",
    "wof:name":"Pallador",
    "wof:placetype":"venue"
},
  "geometry": {"coordinates":[4.77799,51.580132],"type":"Point"}
}