{
  "type": "Feature",
  "properties": {
    "iso:country":"NL",
    "sg:address":"Kortestraat 7",
    "sg:city":"Bakel",
    "sg:orig_category":"Fotostudio'S And Fotografen",
    "sg:phone":"+31 492 341 686",
    "sg:postcode":"5761 CX",
    "sg:province":"Noord-Brabant",
    "wof:name":"Fotografie Huup Van Happen",
    "wof:placetype":"venue"
},
  "geometry": {"coordinates":[5.73959,51.50161],"type":"Point"}
}