{
  "type": "Feature",
  "properties": {
    "iso:country":"NL",
    "sg:address":"W Barentszkd 2",
    "sg:city":"Terschelling West",
    "sg:orig_category":"Juridische Adviseurs",
    "sg:phone":"+31 562 443 060",
    "sg:postcode":"8881 BC",
    "sg:province":"Friesland",
    "wof:name":"Gorter",
    "wof:placetype":"venue"
},
  "geometry": {"coordinates":[5.214094,53.360294],"type":"Point"}
}