{
  "type": "Feature",
  "properties": {
    "addr:full":"W Barentszkd 2 Terschelling West Friesland 8881 BC",
    "addr:housenumber":"2",
    "addr:postcode":"8881 bc",
    "addr:street":"W;Terschelling West",
    "iso:country":"NL",
    "sg:address":"W Barentszkd 2",
    "sg:city":"Terschelling West",
    "sg:orig_category":"Juridische Adviseurs",
    "sg:phone":"+31 562 443 060",
    "sg:postcode":"8881 BC",
    "sg:province":"Friesland",
    "wof:name":"Gorter",
    "wof:placetype":"venue"
},
  "geometry": {"coordinates":[5.214094,53.360294],"type":"Point"}
}