{
  "type": "Feature",
  "properties": {
    "addr:full":"Raadhuisstr 16-24 Koog Aan De Zaan Noord-Holland 1541 JC",
    "addr:housenumber":"16-24",
    "addr:postcode":"koog aan;zaan;1541 jc",
    "iso:country":"NL",
    "sg:address":"Raadhuisstr 16-24",
    "sg:city":"Koog Aan De Zaan",
    "sg:classifiers":[
        {
            "category":"Wholesale",
            "subcategory":"Meat",
            "type":"Manufacturing & Wholesale Goods"
        }
    ],
    "sg:phone":"+31 75 616 4775",
    "sg:postcode":"1541 JC",
    "sg:province":"Noord-Holland",
    "sg:tags":[
        "hang-",
        "sluitwerk",
        "en"
    ],
    "wof:name":"Veenstra, Klaas",
    "wof:placetype":"venue"
},
  "geometry": {"coordinates":[4.811042,52.461182],"type":"Point"}
}