{
  "type": "Feature",
  "properties": {
    "addr:full":"Beijerlandselaan 142 Rotterdam South Holland 3074 EP",
    "addr:housenumber":"142",
    "addr:postcode":"3074 ep",
    "addr:street":"Beijerlandselaan",
    "iso:country":"NL",
    "sg:address":"Beijerlandselaan 142",
    "sg:city":"Rotterdam",
    "sg:classifiers":[
        {
            "category":"Food & Beverages",
            "subcategory":"Fruits & Vegetables",
            "type":"Retail Goods"
        }
    ],
    "sg:phone":"+31 10 432 5165",
    "sg:postcode":"3074 EP",
    "sg:province":"South Holland",
    "sg:tags":[
        "groenten"
    ],
    "wof:name":"Groenteboxer",
    "wof:placetype":"venue"
},
  "geometry": {"coordinates":[4.510768,51.895615],"type":"Point"}
}