{
  "type": "Feature",
  "properties": {
    "addr:full":"Skou 20 Joure Friesland 8501 SC",
    "addr:housenumber":"20",
    "addr:postcode":"8501 sc",
    "addr:street":"Skou",
    "iso:country":"NL",
    "sg:address":"Skou 20",
    "sg:city":"Joure",
    "sg:orig_category":"Bedrijfsopleidingen",
    "sg:phone":"+31 513 414 647",
    "sg:postcode":"8501 SC",
    "sg:province":"Friesland",
    "wof:name":"Kenneth Smit",
    "wof:placetype":"venue"
},
  "geometry": {"coordinates":[5.800737,52.972313],"type":"Point"}
}