{
  "type": "Feature",
  "properties": {
    "addr:full":"Eenrumerwg 2 Baflo Groningen 9953 TD",
    "addr:housenumber":"2",
    "addr:postcode":"9953 td",
    "addr:street":"Eenrumerwg",
    "iso:country":"NL",
    "sg:address":"Eenrumerwg 2",
    "sg:city":"Baflo",
    "sg:classifiers":[
        {
            "category":"Retail",
            "subcategory":"Auto Repair",
            "type":"Services"
        }
    ],
    "sg:phone":"+31 595 422 552",
    "sg:postcode":"9953 TD",
    "sg:province":"Groningen",
    "sg:tags":[
        "garage"
    ],
    "wof:name":"Koning",
    "wof:placetype":"venue"
},
  "geometry": {"coordinates":[6.510266,53.363712],"type":"Point"}
}