{
  "type": "Feature",
  "properties": {
    "iso:country":"NL",
    "sg:address":"Eenrumerwg 2",
    "sg:city":"Baflo",
    "sg:classifiers":[
        {
            "category":"Retail",
            "subcategory":"Auto Repair",
            "type":"Services"
        }
    ],
    "sg:phone":"+31 595 422 552",
    "sg:postcode":"9953 TD",
    "sg:province":"Groningen",
    "sg:tags":[
        "garage"
    ],
    "wof:name":"Koning",
    "wof:placetype":"venue"
},
  "geometry": {"coordinates":[6.510266,53.363712],"type":"Point"}
}