{
  "type": "Feature",
  "properties": {
    "addr:full":"Landriteweg 5 Geesteren Ov NL.08 7678 RM",
    "addr:housenumber":"5",
    "addr:postcode":"7678 rm",
    "addr:street":"Landriteweg;Ov",
    "iso:country":"NL",
    "sg:address":"Landriteweg 5",
    "sg:city":"Geesteren Ov",
    "sg:orig_category":"Kantoorartikelen",
    "sg:phone":"+31 546 632 525",
    "sg:postcode":"7678 RM",
    "sg:province":"NL.08",
    "wof:name":"Handelsonderneming De Delmar",
    "wof:placetype":"venue"
},
  "geometry": {"coordinates":[6.7227730751,52.4058570862],"type":"Point"}
}