{
  "type": "Feature",
  "properties": {
    "addr:full":"Piersonware 3 Zwolle Overijssel 8014 PX",
    "addr:housenumber":"3",
    "addr:postcode":"8014 px",
    "addr:street":"Piersonware",
    "iso:country":"NL",
    "sg:address":"Piersonware 3",
    "sg:city":"Zwolle",
    "sg:orig_category":"Fotostudio'S And Fotografen",
    "sg:phone":"+31 38 460 3866",
    "sg:postcode":"8014 PX",
    "sg:province":"Overijssel",
    "wof:name":"Ma Fotografie",
    "wof:placetype":"venue"
},
  "geometry": {"coordinates":[6.111246,52.478966],"type":"Point"}
}