{
  "type": "Feature",
  "properties": {
    "iso:country":"NL",
    "sg:address":"Boulevard Bankert 50",
    "sg:city":"Vlissingen",
    "sg:orig_category":"Werving And Selectie Van Tijdelijk Personeel And Uitzendkantoren",
    "sg:phone":"+31 118 413 010",
    "sg:postcode":"4382 AC",
    "sg:province":"Zeeland",
    "wof:name":"Deinco Bv",
    "wof:placetype":"venue"
},
  "geometry": {"coordinates":[3.5673770905,51.4444084167],"type":"Point"}
}