{
  "type": "Feature",
  "properties": {
    "addr:full":"Voskuilenwg 123 Heerlen Limburg 6416 AJ",
    "addr:housenumber":"123",
    "addr:postcode":"6416 aj",
    "iso:country":"NL",
    "sg:address":"Voskuilenwg 123",
    "sg:city":"Heerlen",
    "sg:orig_category":"Oldtimers",
    "sg:phone":"+31 45 571 4748",
    "sg:postcode":"6416 AJ",
    "sg:province":"Limburg",
    "sg:website":"http://www.autohuubgrouls.nl",
    "wof:name":"Grouls, Autobedrijf Huub",
    "wof:placetype":"venue"
},
  "geometry": {"coordinates":[5.996856,50.888042],"type":"Point"}
}