{
  "type": "Feature",
  "properties": {
    "iso:country":"NL",
    "sg:address":"Leeghwaterpark 6",
    "sg:city":"Purmerend",
    "sg:orig_category":"Paramedische Behandelingen",
    "sg:phone":"+31 299 642 201",
    "sg:postcode":"1445 RA",
    "sg:province":"North Holland",
    "wof:name":"Logopediepraktijk E.J. Van Ijken",
    "wof:placetype":"venue"
},
  "geometry": {"coordinates":[4.974053,52.499683],"type":"Point"}
}