{
  "type": "Feature",
  "properties": {
    "addr:full":"T Bysterveld 8 Helmond North Brabant 5701 GW",
    "addr:housenumber":"8",
    "addr:postcode":"5701 gw",
    "iso:country":"NL",
    "sg:address":"T Bysterveld 8",
    "sg:city":"Helmond",
    "sg:orig_category":"Verzekeringen - Verzekeringskantoren",
    "sg:phone":"+31 492 535 843",
    "sg:postcode":"5701 GW",
    "sg:province":"North Brabant",
    "wof:name":"Meulendijks",
    "wof:placetype":"venue"
},
  "geometry": {"coordinates":[5.674065,51.483315],"type":"Point"}
}