{
  "type": "Feature",
  "properties": {
    "iso:country":"NL",
    "sg:address":"Sake Kromhoutwei 8",
    "sg:city":"Hoornsterzwaag",
    "sg:orig_category":"Fotografische And Optische Artikelen Gh",
    "sg:phone":"+31 516 462 864",
    "sg:postcode":"8412 CG",
    "sg:province":"Friesland",
    "wof:name":"J. Van Alphen",
    "wof:placetype":"venue"
},
  "geometry": {"coordinates":[6.145228,52.994537],"type":"Point"}
}