{
  "type": "Feature",
  "properties": {
    "addr:full":"J Stillerstr 13 Zaandam Noord-Holland 1507 PT",
    "addr:housenumber":"13",
    "addr:postcode":"1507 pt",
    "iso:country":"NL",
    "sg:address":"J Stillerstr 13",
    "sg:city":"Zaandam",
    "sg:orig_category":"Metselwerken",
    "sg:phone":"+31 75 616 7653",
    "sg:postcode":"1507 PT",
    "sg:province":"Noord-Holland",
    "wof:name":"Al & Nachbar Vof",
    "wof:placetype":"venue"
},
  "geometry": {"coordinates":[4.803127,52.443172],"type":"Point"}
}