{
  "type": "Feature",
  "properties": {
    "iso:country":"NL",
    "sg:address":"Haefland 15",
    "sg:city":"Brunssum",
    "sg:classifiers":[
        {
            "category":"Retail",
            "subcategory":"Auto Repair",
            "type":"Services"
        }
    ],
    "sg:phone":"+31 45 527 0270",
    "sg:postcode":"6441 PA",
    "sg:province":"Limburg",
    "sg:tags":[
        "garage"
    ],
    "wof:name":"Bergh, Vakgarage Sjaak V/D",
    "wof:placetype":"venue"
},
  "geometry": {"coordinates":[5.96916,50.957581],"type":"Point"}
}