{
  "type": "Feature",
  "properties": {
    "addr:full":"Rijnbandijk 171 Kesteren Gelderland 4041 AV",
    "addr:housenumber":"171",
    "addr:postcode":"4041 av",
    "addr:street":"Rijnbandijk;Gelderland",
    "iso:country":"NL",
    "sg:address":"Rijnbandijk 171",
    "sg:city":"Kesteren",
    "sg:orig_category":"Fruit And Groenten Gh",
    "sg:phone":"+31 488 481 439",
    "sg:postcode":"4041 AV",
    "sg:province":"Gelderland",
    "wof:name":"De Rijnbanhof",
    "wof:placetype":"venue"
},
  "geometry": {"coordinates":[5.576959,51.936531],"type":"Point"}
}