{
  "type": "Feature",
  "properties": {
    "iso:country":"NL",
    "sg:address":"T Hoogtlaan 16",
    "sg:city":"Noordwijkerhout",
    "sg:orig_category":"Wegen And Sportterreinen",
    "sg:phone":"+31 252 377 133",
    "sg:postcode":"2211 AN",
    "sg:province":"South Holland",
    "wof:name":"C.N.M. Jansen",
    "wof:placetype":"venue"
},
  "geometry": {"coordinates":[4.4912691116,52.2704696655],"type":"Point"}
}