{
  "type": "Feature",
  "properties": {
    "addr:full":"Kerkln 3-5 Nieuwerkerk Yssel South Holland 2911 AA",
    "addr:housenumber":"3-5",
    "addr:postcode":"2911 aa",
    "addr:street":"Kerkln",
    "iso:country":"NL",
    "sg:address":"Kerkln 3-5",
    "sg:city":"Nieuwerkerk Yssel",
    "sg:orig_category":"Parketvloeren",
    "sg:phone":"+31 180 312 255",
    "sg:postcode":"2911 AA",
    "sg:province":"South Holland",
    "wof:name":"Boele Hubo",
    "wof:placetype":"venue"
},
  "geometry": {"coordinates":[4.62252,51.959648],"type":"Point"}
}