{
  "type": "Feature",
  "properties": {
    "addr:full":"Lorentzstr 3 Dordrecht South Holland 3316 AB",
    "addr:housenumber":"3",
    "addr:postcode":"3316 ab",
    "addr:street":"Lorentzstr",
    "iso:country":"NL",
    "sg:address":"Lorentzstr 3",
    "sg:city":"Dordrecht",
    "sg:classifiers":[
        {
            "category":"Retail",
            "subcategory":"Auto Repair",
            "type":"Services"
        }
    ],
    "sg:phone":"+31 78 614 9017",
    "sg:postcode":"3316 AB",
    "sg:province":"South Holland",
    "sg:tags":[
        "garage"
    ],
    "wof:name":"Korpershoek, K M",
    "wof:placetype":"venue"
},
  "geometry": {"coordinates":[4.646953,51.800156],"type":"Point"}
}