{
  "type": "Feature",
  "properties": {
    "addr:full":"Leppingtonstr 12 Linne Limburg 6067 HZ",
    "addr:housenumber":"12",
    "addr:postcode":"6067 hz",
    "addr:street":"Leppingtonstr",
    "iso:country":"NL",
    "sg:address":"Leppingtonstr 12",
    "sg:city":"Linne",
    "sg:orig_category":"Horren",
    "sg:phone":"+31 475 485 013",
    "sg:postcode":"6067 HZ",
    "sg:province":"Limburg",
    "sg:website":"http://www.interhor.nl",
    "wof:name":"Interhor-Horsystemen",
    "wof:placetype":"venue"
},
  "geometry": {"coordinates":[-120.57225,35.571556],"type":"Point"}
}