{
  "type": "Feature",
  "properties": {
    "addr:full":"Huijbergseweg 1 Hoogerheide North Brabant 4631 GC",
    "addr:housenumber":"1",
    "addr:postcode":"4631 gc",
    "addr:street":"Huijbergseweg",
    "iso:country":"NL",
    "sg:address":"Huijbergseweg 1",
    "sg:city":"Hoogerheide",
    "sg:classifiers":[
        {
            "category":"Fast Food",
            "type":"Food & Drink"
        }
    ],
    "sg:phone":"+31 164 660 315",
    "sg:postcode":"4631 GC",
    "sg:province":"North Brabant",
    "sg:tags":[
        "afhaal",
        "restaurant"
    ],
    "wof:name":"Broodjeszaak Het Cafetaria Portret",
    "wof:placetype":"venue"
},
  "geometry": {"coordinates":[4.324905,51.423],"type":"Point"}
}