{
  "type": "Feature",
  "properties": {
    "iso:country":"NL",
    "sg:address":"P P Rubensstr 71",
    "sg:city":"Wolvega",
    "sg:orig_category":"Homeopathie",
    "sg:phone":"+31 561 612 080",
    "sg:postcode":"8471 TE",
    "sg:province":"Provincie Friesland",
    "sg:website":"http://www.chevalcare.nl",
    "wof:name":"Cheval Care For Pets",
    "wof:placetype":"venue"
},
  "geometry": {"coordinates":[5.990704,52.871029],"type":"Point"}
}