{
  "type": "Feature",
  "properties": {
    "addr:full":"Concourslaan 98 Hoofddorp North Holland 2132 DK",
    "addr:housenumber":"98",
    "addr:postcode":"2132 dk",
    "addr:street":"Concourslaan",
    "iso:country":"NL",
    "sg:address":"Concourslaan 98",
    "sg:city":"Hoofddorp",
    "sg:orig_category":"Werving And Selectie Van Tijdelijk Personeel And Uitzendkantoren",
    "sg:phone":"+31 23 555 4848",
    "sg:postcode":"2132 DK",
    "sg:province":"North Holland",
    "wof:name":"Spherion",
    "wof:placetype":"venue"
},
  "geometry": {"coordinates":[4.6940279007,52.3029937744],"type":"Point"}
}