{
  "type": "Feature",
  "properties": {
    "addr:full":"Achterweg 11 Driesum Provincie Friesland 9114 RT",
    "addr:housenumber":"11;9114",
    "addr:postcode":"rt",
    "addr:street":"Achterweg;Provincie Friesland",
    "iso:country":"NL",
    "sg:address":"Achterweg 11",
    "sg:city":"Driesum",
    "sg:orig_category":"Autokeuringen",
    "sg:phone":"+31 511 421 392",
    "sg:postcode":"9114 RT",
    "sg:province":"Provincie Friesland",
    "wof:name":"Handelsonderneming H.J. Van Der Wal",
    "wof:placetype":"venue"
},
  "geometry": {"coordinates":[6.04205,53.298618],"type":"Point"}
}