{
  "type": "Feature",
  "properties": {
    "addr:full":"Campherbeekln 82 Zwolle Overijssel 8024 BZ",
    "addr:housenumber":"82",
    "addr:postcode":"8024 bz",
    "addr:street":"Campherbeekln",
    "iso:country":"NL",
    "sg:address":"Campherbeekln 82",
    "sg:city":"Zwolle",
    "sg:orig_category":"Verenigingsgebouwen",
    "sg:phone":"+31 38 453 7409",
    "sg:postcode":"8024 BZ",
    "sg:province":"Overijssel",
    "wof:name":"Weijenbelt, De",
    "wof:placetype":"venue"
},
  "geometry": {"coordinates":[6.135509,52.522198],"type":"Point"}
}