{
  "type": "Feature",
  "properties": {
    "iso:country":"NL",
    "sg:address":"Piet Kramerplein 5",
    "sg:city":"Leeuwarden",
    "sg:orig_category":"Kappers",
    "sg:phone":"+31 58 267 5804",
    "sg:postcode":"8923 BV",
    "sg:province":"Provincie Friesland",
    "wof:name":"Korrie'S Kapsalon",
    "wof:placetype":"venue"
},
  "geometry": {"coordinates":[5.811415,53.214531],"type":"Point"}
}