{
  "type": "Feature",
  "properties": {
    "addr:full":"Berkenln 2 Zegveld Utrecht 3474 KA",
    "addr:housenumber":"2",
    "addr:postcode":"3474 ka",
    "addr:street":"Berkenln",
    "iso:country":"NL",
    "sg:address":"Berkenln 2",
    "sg:city":"Zegveld",
    "sg:orig_category":"Adviesbureaus Werktuigbouwkunde",
    "sg:phone":"+31 348 690 333",
    "sg:postcode":"3474 KA",
    "sg:province":"Utrecht",
    "sg:website":"http://www.blok-mechanical.nl",
    "wof:name":"Blok",
    "wof:placetype":"venue"
},
  "geometry": {"coordinates":[4.832224,52.115513],"type":"Point"}
}