{
  "type": "Feature",
  "properties": {
    "addr:full":"Maatschapsln 53 Bunnik Utrecht 3981 AW",
    "addr:housenumber":"53",
    "addr:postcode":"3981 aw",
    "addr:street":"Maatschapsln",
    "iso:country":"NL",
    "sg:address":"Maatschapsln 53",
    "sg:city":"Bunnik",
    "sg:orig_category":"Huisbrand- En Industrieolie",
    "sg:phone":"+31 30 656 2757",
    "sg:postcode":"3981 AW",
    "sg:province":"Utrecht",
    "wof:name":"Echtelt, T H G Van",
    "wof:placetype":"venue"
},
  "geometry": {"coordinates":[5.196565,52.064091],"type":"Point"}
}