{
  "type": "Feature",
  "properties": {
    "iso:country":"NL",
    "sg:address":"Herengr 605",
    "sg:city":"Amsterdam",
    "sg:orig_category":"Musea",
    "sg:phone":"+31 20 523 1870",
    "sg:postcode":"1017 CE",
    "sg:province":"North Holland",
    "sg:website":"http://www.netland.nl/~handshak/musea/willet.htm",
    "wof:name":"Willet Holthuysen",
    "wof:placetype":"venue"
},
  "geometry": {"coordinates":[4.898658,52.365589],"type":"Point"}
}