{
  "type": "Feature",
  "properties": {
    "iso:country":"NL",
    "sg:address":"Hoekenes 7",
    "sg:city":"Amsterdam",
    "sg:orig_category":"Meubelen",
    "sg:phone":"+31 20 667 0702",
    "sg:postcode":"1068 ML",
    "sg:province":"Noord-Holland",
    "wof:name":"Woude, Van Der",
    "wof:placetype":"venue"
},
  "geometry": {"coordinates":[4.798369,52.361351],"type":"Point"}
}