{
  "type": "Feature",
  "properties": {
    "iso:country":"NL",
    "sg:address":"Oosterstraat 16",
    "sg:city":"Groningen",
    "sg:orig_category":"Herenmodezaken",
    "sg:phone":"+31 50 314 0261",
    "sg:postcode":"9711 NT",
    "sg:province":"Groningen",
    "wof:name":"Max Mannenmode",
    "wof:placetype":"venue"
},
  "geometry": {"coordinates":[6.569537,53.217869],"type":"Point"}
}