{
  "type": "Feature",
  "properties": {
    "addr:full":"Buys Ballotstraat 4 Heerhugowaard Noord-Holland 1704 SK",
    "addr:housenumber":"4",
    "addr:street":"Buys Ballotstraat;1704",
    "iso:country":"NL",
    "sg:address":"Buys Ballotstraat 4",
    "sg:city":"Heerhugowaard",
    "sg:orig_category":"Bouwmaterialen Gh",
    "sg:phone":"+31 72 571 4350",
    "sg:postcode":"1704 SK",
    "sg:province":"Noord-Holland",
    "wof:name":"Flexim International Bv",
    "wof:placetype":"venue"
},
  "geometry": {"coordinates":[4.83019,52.688053],"type":"Point"}
}