{
  "type": "Feature",
  "properties": {
    "iso:country":"NL",
    "sg:address":"Planetenbaan 14",
    "sg:city":"Maarn",
    "sg:orig_category":"Vertaalbureaus",
    "sg:phone":"+31 343 442 310",
    "sg:postcode":"3951 EJ",
    "sg:province":"Utrecht",
    "wof:name":"Trainital Italiaans, Instituut",
    "wof:placetype":"venue"
},
  "geometry": {"coordinates":[5.382959,52.065388],"type":"Point"}
}