{
  "type": "Feature",
  "properties": {
    "addr:full":"Havenwg 8 Biddinghuizen Flevoland 8256 BH",
    "addr:housenumber":"8",
    "addr:postcode":"8256 bh",
    "addr:street":"Havenwg;Flevoland",
    "iso:country":"NL",
    "sg:address":"Havenwg 8",
    "sg:city":"Biddinghuizen",
    "sg:orig_category":"Autoschade- Herstelbedrijven",
    "sg:phone":"+31 321 330 655",
    "sg:postcode":"8256 BH",
    "sg:province":"Flevoland",
    "wof:name":"Lekkerkerker, Autoschadebedrijf",
    "wof:placetype":"venue"
},
  "geometry": {"coordinates":[5.693445,52.457329],"type":"Point"}
}