{
  "type": "Feature",
  "properties": {
    "addr:full":"Aalsmeerderwg 100A Aalsmeer Noord-Holland 1432 CT",
    "addr:housenumber":"100a",
    "addr:postcode":"1432 ct",
    "iso:country":"NL",
    "sg:address":"Aalsmeerderwg 100A",
    "sg:city":"Aalsmeer",
    "sg:orig_category":"Bloemen En Planten - Groothandel",
    "sg:phone":"+31 297 345 845",
    "sg:postcode":"1432 CT",
    "sg:province":"Noord-Holland",
    "wof:name":"Oriental Plants Bv",
    "wof:placetype":"venue"
},
  "geometry": {"coordinates":[4.779004,52.273911],"type":"Point"}
}