{
  "type": "Feature",
  "properties": {
    "addr:full":"Industriestraat 30 Haaksbergen NL.08 7482 EZ",
    "addr:housenumber":"30;nl.08",
    "addr:postcode":"7482 ez",
    "addr:street":"Industriestraat",
    "iso:country":"NL",
    "sg:address":"Industriestraat 30",
    "sg:city":"Haaksbergen",
    "sg:orig_category":"Kunststofverpakkingen Fab",
    "sg:phone":"+31 53 572 3884",
    "sg:postcode":"7482 EZ",
    "sg:province":"NL.08",
    "wof:name":"Dijkstra Plastics Bv",
    "wof:placetype":"venue"
},
  "geometry": {"coordinates":[6.717114,52.151218],"type":"Point"}
}