{
  "type": "Feature",
  "properties": {
    "addr:full":"Snoekstr 10 Almere Flevoland 1317 JN",
    "addr:housenumber":"10",
    "addr:postcode":"1317 jn",
    "addr:street":"Snoekstr;Flevoland",
    "iso:country":"NL",
    "sg:address":"Snoekstr 10",
    "sg:city":"Almere",
    "sg:orig_category":"Administratie- En Boekhoudkantoren",
    "sg:phone":"+31 36 533 8495",
    "sg:postcode":"1317 JN",
    "sg:province":"Flevoland",
    "wof:name":"Ofia Vof",
    "wof:placetype":"venue"
},
  "geometry": {"coordinates":[5.23613,52.388054],"type":"Point"}
}