{
  "type": "Feature",
  "properties": {
    "iso:country":"NL",
    "sg:address":"Czaar Peterstraat 1",
    "sg:city":"Amsterdam",
    "sg:classifiers":[
        {
            "category":"Fast Food",
            "type":"Food & Drink"
        }
    ],
    "sg:phone":"+31 20 625 1986",
    "sg:postcode":"1018 NW",
    "sg:province":"Noord-Holland",
    "sg:tags":[
        "afhaal",
        "restaurant"
    ],
    "wof:name":"Egyptische Grillroom Iris",
    "wof:placetype":"venue"
},
  "geometry": {"coordinates":[4.925444,52.367653],"type":"Point"}
}