{
  "type": "Feature",
  "properties": {
    "addr:full":"Smidsstr 7-9 Zelhem Gelderland 7021 AB",
    "addr:housenumber":"7-9",
    "addr:postcode":"7021 ab",
    "addr:street":"Smidsstr;Gelderland",
    "iso:country":"NL",
    "sg:address":"Smidsstr 7-9",
    "sg:city":"Zelhem",
    "sg:orig_category":"Meubelen",
    "sg:phone":"+31 314 623 762",
    "sg:postcode":"7021 AB",
    "sg:province":"Gelderland",
    "wof:name":"Gr",
    "wof:placetype":"venue"
},
  "geometry": {"coordinates":[6.348902,52.006489],"type":"Point"}
}