{
  "type": "Feature",
  "properties": {
    "iso:country":"NL",
    "sg:address":"Smidsstr 7-9",
    "sg:city":"Zelhem",
    "sg:orig_category":"Meubelen",
    "sg:phone":"+31 314 623 762",
    "sg:postcode":"7021 AB",
    "sg:province":"Gelderland",
    "wof:name":"Gr",
    "wof:placetype":"venue"
},
  "geometry": {"coordinates":[6.348902,52.006489],"type":"Point"}
}