{
  "type": "Feature",
  "properties": {
    "addr:full":"Bloemenln 29 Rotterdam South Holland 3075 PE",
    "addr:housenumber":"29",
    "addr:postcode":"3075 pe",
    "addr:street":"Bloemenln",
    "iso:country":"NL",
    "sg:address":"Bloemenln 29",
    "sg:city":"Rotterdam",
    "sg:orig_category":"Koeriersdiensten",
    "sg:phone":"+31 10 485 3047",
    "sg:postcode":"3075 PE",
    "sg:province":"South Holland",
    "wof:name":"Teunisse, Marc",
    "wof:placetype":"venue"
},
  "geometry": {"coordinates":[4.50016,51.883469],"type":"Point"}
}