{
  "type": "Feature",
  "properties": {
    "addr:full":"Pelmolenln 12-14 Woerden Utrecht 3447 GW",
    "addr:housenumber":"12-14",
    "addr:postcode":"3447 gw",
    "addr:street":"Woerden",
    "iso:country":"NL",
    "sg:address":"Pelmolenln 12-14",
    "sg:city":"Woerden",
    "sg:orig_category":"Facilitaire Dienstverlening",
    "sg:phone":"+31 348 462 080",
    "sg:postcode":"3447 GW",
    "sg:province":"Utrecht",
    "wof:name":"Prisma Bv",
    "wof:placetype":"venue"
},
  "geometry": {"coordinates":[4.892123,52.077492],"type":"Point"}
}