{
  "type": "Feature",
  "properties": {
    "addr:full":"Lindeln 15 Krommenie Noord-Holland 1561 CJ",
    "addr:housenumber":"15",
    "addr:postcode":"1561 cj",
    "addr:street":"Lindeln",
    "iso:country":"NL",
    "sg:address":"Lindeln 15",
    "sg:city":"Krommenie",
    "sg:orig_category":"Boekbinderijen",
    "sg:phone":"+31 75 628 7466",
    "sg:postcode":"1561 CJ",
    "sg:province":"Noord-Holland",
    "wof:name":"Riet Bv",
    "wof:placetype":"venue"
},
  "geometry": {"coordinates":[4.768958,52.501457],"type":"Point"}
}