{
  "type": "Feature",
  "properties": {
    "addr:full":"Sionstr 31A Rotterdam South Holland 3061 ER",
    "addr:housenumber":"31a",
    "addr:postcode":"3061 er",
    "addr:street":"Sionstr",
    "iso:country":"NL",
    "sg:address":"Sionstr 31A",
    "sg:city":"Rotterdam",
    "sg:orig_category":"Filmstudio'S En -Productie",
    "sg:phone":"+31 6 47810637",
    "sg:postcode":"3061 ER",
    "sg:province":"South Holland",
    "sg:website":"http://www.meneerknoop.nl",
    "wof:name":"Planet Pablo",
    "wof:placetype":"venue"
},
  "geometry": {"coordinates":[4.507478,51.927021],"type":"Point"}
}