{
  "type": "Feature",
  "properties": {
    "addr:full":"Bramenberg 12 Eemnes Utrecht 3755 BZ",
    "addr:housenumber":"12",
    "addr:postcode":"3755 bz",
    "addr:street":"Bramenberg",
    "iso:country":"NL",
    "sg:address":"Bramenberg 12",
    "sg:city":"Eemnes",
    "sg:orig_category":"Metaalbewerking",
    "sg:phone":"+31 35 538 1679",
    "sg:postcode":"3755 BZ",
    "sg:province":"Utrecht",
    "wof:name":"Tas",
    "wof:placetype":"venue"
},
  "geometry": {"coordinates":[5.249071,52.248959],"type":"Point"}
}