{
  "type": "Feature",
  "properties": {
    "addr:full":"Industriestr 12 Noord Scharwoude North Holland 1723 LE",
    "addr:housenumber":"12",
    "addr:postcode":"1723 le",
    "addr:street":"Industriestr",
    "iso:country":"NL",
    "sg:address":"Industriestr 12",
    "sg:city":"Noord Scharwoude",
    "sg:orig_category":"Koel- En Vrieshuizen",
    "sg:phone":"+31 226 312 768",
    "sg:postcode":"1723 LE",
    "sg:province":"North Holland",
    "wof:name":"Henselmans En Zn, Fa C",
    "wof:placetype":"venue"
},
  "geometry": {"coordinates":[4.816685,52.706348],"type":"Point"}
}