{
  "type": "Feature",
  "properties": {
    "addr:full":"Deurningerstr 7 Oldenzaal Overijssel 7571 BA",
    "addr:housenumber":"7",
    "addr:postcode":"7571 ba",
    "addr:street":"Deurningerstr",
    "iso:country":"NL",
    "sg:address":"Deurningerstr 7",
    "sg:city":"Oldenzaal",
    "sg:orig_category":"Schoenen",
    "sg:phone":"+31 541 512 567",
    "sg:postcode":"7571 BA",
    "sg:province":"Overijssel",
    "wof:name":"Hendriks, F",
    "wof:placetype":"venue"
},
  "geometry": {"coordinates":[6.926794,52.31184],"type":"Point"}
}