{
  "type": "Feature",
  "properties": {
    "addr:full":"Europawg 109 Schoonebeek Provincie Drenthe 7761 AB",
    "addr:housenumber":"109",
    "addr:postcode":"7761 ab",
    "addr:street":"Provincie Drenthe",
    "iso:country":"NL",
    "sg:address":"Europawg 109",
    "sg:city":"Schoonebeek",
    "sg:orig_category":"Administratie- En Boekhoudkantoren",
    "sg:phone":"+31 524 532 934",
    "sg:postcode":"7761 AB",
    "sg:province":"Provincie Drenthe",
    "wof:name":"Hanken Vof, F",
    "wof:placetype":"venue"
},
  "geometry": {"coordinates":[6.886324,52.661125],"type":"Point"}
}