{
  "type": "Feature",
  "properties": {
    "addr:full":"Bastenakenstraat 165 Amsterdam Noord-Holland 1066 JC",
    "addr:housenumber":"165",
    "addr:postcode":"1066 jc",
    "addr:street":"Bastenakenstraat",
    "iso:country":"NL",
    "sg:address":"Bastenakenstraat 165",
    "sg:city":"Amsterdam",
    "sg:orig_category":"Plafonds",
    "sg:phone":"+31 20 388 0863",
    "sg:postcode":"1066 JC",
    "sg:province":"Noord-Holland",
    "sg:website":"http://www.vandijkafbouw.nl",
    "wof:name":"Dijk Afbouw, Van",
    "wof:placetype":"venue"
},
  "geometry": {"coordinates":[4.820539,52.345371],"type":"Point"}
}