{
  "type": "Feature",
  "properties": {
    "iso:country":"NL",
    "sg:address":"De Kerkhof 4",
    "sg:city":"'S Hertogenbosch",
    "sg:orig_category":"Bedrijfs- And Managementsconsultants",
    "sg:phone":"+31 73 633 0050",
    "sg:postcode":"5221 AJ",
    "sg:province":"North Brabant",
    "wof:name":"Bottom Line",
    "wof:placetype":"venue"
},
  "geometry": {"coordinates":[5.271801,51.720425],"type":"Point"}
}