{
  "type": "Feature",
  "properties": {
    "addr:full":"Noordeinde 151 Almere Flevoland 1334 AN",
    "addr:housenumber":"151",
    "addr:postcode":"1334 an",
    "addr:street":"Noordeinde;Flevoland",
    "iso:country":"NL",
    "sg:address":"Noordeinde 151",
    "sg:city":"Almere",
    "sg:orig_category":"Boekenuitgeverijen",
    "sg:phone":"+31 36 532 7402",
    "sg:postcode":"1334 AN",
    "sg:province":"Flevoland",
    "wof:name":"De Wegwijzer",
    "wof:placetype":"venue"
},
  "geometry": {"coordinates":[5.277259,52.395088],"type":"Point"}
}