{
  "type": "Feature",
  "properties": {
    "iso:country":"NL",
    "sg:address":"Nobeldwstr 8Bis",
    "sg:city":"Utrecht",
    "sg:orig_category":"Vertaalbureaus",
    "sg:phone":"+31 30 240 0328",
    "sg:postcode":"3512 EX",
    "sg:province":"Utrecht",
    "wof:name":"Valke, Peggy",
    "wof:placetype":"venue"
},
  "geometry": {"coordinates":[5.126233,52.092602],"type":"Point"}
}