{
  "type": "Feature",
  "properties": {
    "addr:full":"K Doormanstr 22 Rotterdam Zuid-Holland 3012 GJ",
    "addr:housenumber":"22",
    "addr:postcode":"3012 gj",
    "addr:street":"Doormanstr",
    "iso:country":"NL",
    "sg:address":"K Doormanstr 22",
    "sg:city":"Rotterdam",
    "sg:orig_category":"Margarine, Olie En Vet - Industrie",
    "sg:phone":"+31 10 414 9200",
    "sg:postcode":"3012 GJ",
    "sg:province":"Zuid-Holland",
    "wof:name":"Adams Bv, W",
    "wof:placetype":"venue"
},
  "geometry": {"coordinates":[4.473726,51.922607],"type":"Point"}
}