{
  "type": "Feature",
  "properties": {
    "addr:full":"Dam 12 Schiedam Zuid-Holland 3111 BD",
    "addr:housenumber":"12",
    "addr:postcode":"3111 bd",
    "addr:street":"Dam",
    "iso:country":"NL",
    "sg:address":"Dam 12",
    "sg:city":"Schiedam",
    "sg:orig_category":"Woningstoffeerders",
    "sg:phone":"+31 10 473 9122",
    "sg:postcode":"3111 BD",
    "sg:province":"Zuid-Holland",
    "wof:name":"Coster, J M",
    "wof:placetype":"venue"
},
  "geometry": {"coordinates":[4.3958468437,51.9178733826],"type":"Point"}
}