{
  "type": "Feature",
  "properties": {
    "addr:full":"T Plein 21 Leusden Utrecht 3831 CR",
    "addr:housenumber":"21",
    "addr:postcode":"3831 cr",
    "addr:street":"T Plein",
    "iso:country":"NL",
    "sg:address":"T Plein 21",
    "sg:city":"Leusden",
    "sg:classifiers":[
        {
            "category":"Bakery",
            "type":"Food & Drink"
        }
    ],
    "sg:phone":"+31 33 495 3294",
    "sg:postcode":"3831 CR",
    "sg:province":"Utrecht",
    "sg:tags":[
        "brood",
        "banket"
    ],
    "wof:name":"Vof Vlaaierie",
    "wof:placetype":"venue"
},
  "geometry": {"coordinates":[5.427555,52.12915],"type":"Point"}
}