{
  "type": "Feature",
  "properties": {
    "addr:full":"Moerwijk 47 Breda North Brabant 4826 HP",
    "addr:housenumber":"47",
    "addr:postcode":"4826 hp",
    "addr:street":"Moerwijk",
    "iso:country":"NL",
    "sg:address":"Moerwijk 47",
    "sg:city":"Breda",
    "sg:orig_category":"Huishoudapparatuur, Televisies And Radio'S",
    "sg:phone":"+31 76 587 3901",
    "sg:postcode":"4826 HP",
    "sg:province":"North Brabant",
    "wof:name":"Electronic Partner Reichardt",
    "wof:placetype":"venue"
},
  "geometry": {"coordinates":[4.789922,51.607903],"type":"Point"}
}