{
  "type": "Feature",
  "properties": {
    "addr:full":"Havenstr 29 Waarde Zeeland 4414 AX",
    "addr:housenumber":"29",
    "addr:postcode":"4414 ax",
    "addr:street":"Havenstr",
    "iso:country":"NL",
    "sg:address":"Havenstr 29",
    "sg:city":"Waarde",
    "sg:orig_category":"Pluimveebedrijven En -Handelaren",
    "sg:phone":"+31 113 501 756",
    "sg:postcode":"4414 AX",
    "sg:province":"Zeeland",
    "wof:name":"Goud, O J",
    "wof:placetype":"venue"
},
  "geometry": {"coordinates":[4.066627,51.416702],"type":"Point"}
}