{
  "type": "Feature",
  "properties": {
    "addr:full":"Louis Couperusstraat 47 Gemert North Brabant 5421 RM",
    "addr:housenumber":"47",
    "addr:postcode":"5421 rm",
    "addr:street":"Louis Couperusstraat",
    "iso:country":"NL",
    "sg:address":"Louis Couperusstraat 47",
    "sg:city":"Gemert",
    "sg:orig_category":"Loodgieterswerk, Verwarming And Sanitaire Installaties",
    "sg:phone":"+31 492 362 205",
    "sg:postcode":"5421 RM",
    "sg:province":"North Brabant",
    "wof:name":"A.H.T.M. Baggermans",
    "wof:placetype":"venue"
},
  "geometry": {"coordinates":[5.684678,51.563099],"type":"Point"}
}