{
  "type": "Feature",
  "properties": {
    "iso:country":"NL",
    "sg:address":"Corellistr 27",
    "sg:city":"Amsterdam",
    "sg:classifiers":[
        {
            "category":"Shopping",
            "subcategory":"Adult",
            "type":"Retail Goods"
        }
    ],
    "sg:phone":"+31 20 671 8535",
    "sg:postcode":"1077 HB",
    "sg:province":"Noord-Holland",
    "sg:tags":[
        "lingerie",
        "en",
        "tricotage"
    ],
    "sg:website":"http://www.donker.org",
    "wof:name":"Palo",
    "wof:placetype":"venue"
},
  "geometry": {"coordinates":[4.87794,52.34967],"type":"Point"}
}