{
  "type": "Feature",
  "properties": {
    "addr:full":"Pimpernelstr 7 Almere NL. 1314 JK",
    "addr:housenumber":"7",
    "addr:postcode":"1314 jk",
    "addr:street":"Pimpernelstr;Nl.",
    "iso:country":"NL",
    "sg:address":"Pimpernelstr 7",
    "sg:city":"Almere",
    "sg:orig_category":"Koeriersdiensten",
    "sg:phone":"+31 36 534 6951",
    "sg:postcode":"1314 JK",
    "sg:province":"NL.",
    "wof:name":"Abc Snelkoeriers",
    "wof:placetype":"venue"
},
  "geometry": {"coordinates":[5.206259,52.378357],"type":"Point"}
}