{
  "type": "Feature",
  "properties": {
    "addr:full":"Disselsjeesdrift 16 Nieuwegein Utrecht 3436 AJ",
    "addr:housenumber":"16",
    "addr:postcode":"3436 aj",
    "addr:street":"Disselsjeesdrift",
    "iso:country":"NL",
    "sg:address":"Disselsjeesdrift 16",
    "sg:city":"Nieuwegein",
    "sg:orig_category":"Metaaldetectors",
    "sg:phone":"+31 30 603 4681",
    "sg:postcode":"3436 AJ",
    "sg:province":"Utrecht",
    "wof:name":"Discoveryshop",
    "wof:placetype":"venue"
},
  "geometry": {"coordinates":[5.071678,52.029125],"type":"Point"}
}