{
  "type": "Feature",
  "properties": {
    "addr:full":"Textielwg 11 Amersfoort Utrecht 3812 RV",
    "addr:housenumber":"11",
    "addr:postcode":"3812 rv",
    "addr:street":"Textielwg",
    "iso:country":"NL",
    "sg:address":"Textielwg 11",
    "sg:city":"Amersfoort",
    "sg:orig_category":"Oud Metaal",
    "sg:phone":"+31 33 463 0577",
    "sg:postcode":"3812 RV",
    "sg:province":"Utrecht",
    "wof:name":"Randeraad-Malestein Recycling",
    "wof:placetype":"venue"
},
  "geometry": {"coordinates":[5.3688220978,52.1650886536],"type":"Point"}
}