{
  "type": "Feature",
  "properties": {
    "addr:full":"Merketon 57 Uden North Brabant 5401 LR",
    "addr:housenumber":"57",
    "addr:postcode":"5401 lr",
    "addr:street":"Merketon",
    "iso:country":"NL",
    "sg:address":"Merketon 57",
    "sg:city":"Uden",
    "sg:orig_category":"Verzekeringen",
    "sg:phone":"+31 413 265 648",
    "sg:postcode":"5401 LR",
    "sg:province":"North Brabant",
    "wof:name":"Assuring Kuipers Bv",
    "wof:placetype":"venue"
},
  "geometry": {"coordinates":[5.603438,51.66798],"type":"Point"}
}