{
  "type": "Feature",
  "properties": {
    "iso:country":"NL",
    "sg:address":"Provincialeweg 47",
    "sg:city":"Westerhoven",
    "sg:orig_category":"Bloemen And Planten",
    "sg:phone":"+31 40 201 2140",
    "sg:postcode":"5563 AG",
    "sg:province":"Noord-Brabant",
    "wof:name":"Vof Het Molenveld",
    "wof:placetype":"venue"
},
  "geometry": {"coordinates":[5.394454,51.329567],"type":"Point"}
}