{
  "type": "Feature",
  "properties": {
    "addr:full":"Beek 6 Merselo Limburg 5815 CS",
    "addr:housenumber":"6",
    "addr:postcode":"5815 cs",
    "addr:street":"Beek",
    "iso:country":"NL",
    "sg:address":"Beek 6",
    "sg:city":"Merselo",
    "sg:orig_category":"Psychologen",
    "sg:phone":"+31 478 546 807",
    "sg:postcode":"5815 CS",
    "sg:province":"Limburg",
    "wof:name":"Zandvliet, Drs P M",
    "wof:placetype":"venue"
},
  "geometry": {"coordinates":[5.942146,51.536858],"type":"Point"}
}