{
  "type": "Feature",
  "properties": {
    "addr:full":"Achtersloot 172 Ysselstein Ut Utrecht 3401 NZ",
    "addr:housenumber":"172",
    "addr:postcode":"3401 nz",
    "addr:street":"Achtersloot",
    "iso:country":"NL",
    "sg:address":"Achtersloot 172",
    "sg:city":"Ysselstein Ut",
    "sg:orig_category":"Loonbedrijven",
    "sg:phone":"+31 30 688 4130",
    "sg:postcode":"3401 NZ",
    "sg:province":"Utrecht",
    "wof:name":"Bruin, G N M De",
    "wof:placetype":"venue"
},
  "geometry": {"coordinates":[5.022525,52.035892],"type":"Point"}
}