{
  "type": "Feature",
  "properties": {
    "iso:country":"NL",
    "sg:address":"Meerstr 35",
    "sg:city":"Bunde",
    "sg:orig_category":"Verhuizingen",
    "sg:phone":"+31 800 2582582",
    "sg:postcode":"6241 ND",
    "sg:province":"Limburg",
    "wof:name":"Evs",
    "wof:placetype":"venue"
},
  "geometry": {"coordinates":[5.724387,50.901501],"type":"Point"}
}