{
  "type": "Feature",
  "properties": {
    "iso:country":"NL",
    "sg:address":"Mgr Zwysenpln 29",
    "sg:city":"Kerkdriel",
    "sg:orig_category":"Behangselpapier En Wandbekleding",
    "sg:phone":"+31 418 632 223",
    "sg:postcode":"5331 BE",
    "sg:province":"Gelderland",
    "wof:name":"Deco Home Poulisse Vof",
    "wof:placetype":"venue"
},
  "geometry": {"coordinates":[5.33669,51.771244],"type":"Point"}
}