{
  "type": "Feature",
  "properties": {
    "addr:full":"Varkensstraat 3 Arnhem Gelderland 6811 GM",
    "addr:housenumber":"3",
    "addr:postcode":"6811 gm",
    "addr:street":"Varkensstraat",
    "iso:country":"NL",
    "sg:address":"Varkensstraat 3",
    "sg:city":"Arnhem",
    "sg:classifiers":[
        {
            "category":"Bars & Pubs",
            "type":"Food & Drink"
        }
    ],
    "sg:phone":"+31 26 443 6252",
    "sg:postcode":"6811 GM",
    "sg:province":"Gelderland",
    "wof:name":"Speak Easy",
    "wof:placetype":"venue"
},
  "geometry": {"coordinates":[5.90413,51.981953],"type":"Point"}
}