{
  "type": "Feature",
  "properties": {
    "addr:full":"Bloemenweg 2 Maastricht Limburg 6221 TV",
    "addr:housenumber":"2",
    "addr:postcode":"6221 tv",
    "addr:street":"Bloemenweg",
    "iso:country":"NL",
    "sg:address":"Bloemenweg 2",
    "sg:city":"Maastricht",
    "sg:orig_category":"Autokeuringen",
    "sg:phone":"+31 43 321 5938",
    "sg:postcode":"6221 TV",
    "sg:province":"Limburg",
    "wof:name":"Don Weerts Auto'S Bv",
    "wof:placetype":"venue"
},
  "geometry": {"coordinates":[5.707276,50.844883],"type":"Point"}
}