{
  "type": "Feature",
  "properties": {
    "addr:full":"Grote Markt 20 Nijmegen Gelderland 6511 KA",
    "addr:housenumber":"20",
    "addr:postcode":"6511 ka",
    "addr:street":"Grote Markt;Gelderland",
    "iso:country":"NL",
    "sg:address":"Grote Markt 20",
    "sg:city":"Nijmegen",
    "sg:orig_category":"Fietshandelaren",
    "sg:phone":"+31 24 322 5359",
    "sg:postcode":"6511 KA",
    "sg:province":"Gelderland",
    "wof:name":"De Bruijn Rijwielhandel",
    "wof:placetype":"venue"
},
  "geometry": {"coordinates":[5.86326,51.847599],"type":"Point"}
}