{
  "type": "Feature",
  "properties": {
    "addr:full":"Wildersekade 25 Bergschenhoek South Holland 2661 AA",
    "addr:housenumber":"25",
    "addr:postcode":"2661 aa",
    "addr:street":"Wildersekade",
    "iso:country":"NL",
    "sg:address":"Wildersekade 25",
    "sg:city":"Bergschenhoek",
    "sg:orig_category":"Bloemen And Planten",
    "sg:phone":"+31 10 511 2642",
    "sg:postcode":"2661 AA",
    "sg:province":"South Holland",
    "wof:name":"C. Vermeer En Zoon",
    "wof:placetype":"venue"
},
  "geometry": {"coordinates":[4.477915,51.976292],"type":"Point"}
}