{
  "type": "Feature",
  "properties": {
    "iso:country":"NL",
    "sg:address":"Wildersekade 25",
    "sg:city":"Bergschenhoek",
    "sg:orig_category":"Bloemen And Planten",
    "sg:phone":"+31 10 511 2642",
    "sg:postcode":"2661 AA",
    "sg:province":"South Holland",
    "wof:name":"C. Vermeer En Zoon",
    "wof:placetype":"venue"
},
  "geometry": {"coordinates":[4.477915,51.976292],"type":"Point"}
}