{
  "type": "Feature",
  "properties": {
    "iso:country":"NL",
    "sg:address":"Kraatsweg 34",
    "sg:city":"Ede Gld",
    "sg:orig_category":"Loodgieterswerk, Verwarming And Sanitaire Installaties",
    "sg:phone":"+31 318 610 127",
    "sg:postcode":"6712 DB",
    "sg:province":"Gelderland",
    "wof:name":"Woningonderhoud P. Stoel",
    "wof:placetype":"venue"
},
  "geometry": {"coordinates":[5.65296,52.047497],"type":"Point"}
}