{
  "type": "Feature",
  "properties": {
    "iso:country":"NL",
    "sg:address":"Evertsenstr 4",
    "sg:city":"Heerlen",
    "sg:orig_category":"Autorijscholen",
    "sg:phone":"+31 45 521 3173",
    "sg:postcode":"6414 RZ",
    "sg:province":"Limburg",
    "wof:name":"Berg, P Van Den",
    "wof:placetype":"venue"
},
  "geometry": {"coordinates":[5.965377,50.930317],"type":"Point"}
}