{
  "type": "Feature",
  "properties": {
    "addr:full":"Velserstr 19B , (Lokatie Deo) Haarlem Noord-Holland 2023 EA",
    "addr:housenumber":"19b;deo",
    "addr:postcode":"2023 ea",
    "addr:street":"Velserstr",
    "iso:country":"NL",
    "sg:address":"Velserstr 19B , (Lokatie Deo)",
    "sg:city":"Haarlem",
    "sg:orig_category":"Orthopedische Artikelen",
    "sg:phone":"+31 23 552 4244",
    "sg:postcode":"2023 EA",
    "sg:province":"Noord-Holland",
    "wof:name":"Deo, Centr",
    "wof:placetype":"venue"
},
  "geometry": {"coordinates":[4.6319351196,52.3924026489],"type":"Point"}
}