{
  "type": "Feature",
  "properties": {
    "addr:full":"Theaterpassage 4 Kerkrade Limburg 6461 DV",
    "addr:housenumber":"4",
    "addr:postcode":"6461 dv",
    "addr:street":"Theaterpassage",
    "iso:country":"NL",
    "sg:address":"Theaterpassage 4",
    "sg:city":"Kerkrade",
    "sg:orig_category":"Verlichting And Huishoudartikelen",
    "sg:phone":"+31 45 567 0197",
    "sg:postcode":"6461 DV",
    "sg:province":"Limburg",
    "wof:name":"Lampenier",
    "wof:placetype":"venue"
},
  "geometry": {"coordinates":[6.062729,50.865479],"type":"Point"}
}