{
  "type": "Feature",
  "properties": {
    "addr:full":"Beekstraat 9 Weert Limburg 6001 GG",
    "addr:housenumber":"9",
    "addr:postcode":"6001 gg",
    "addr:street":"Beekstraat",
    "iso:country":"NL",
    "sg:address":"Beekstraat 9",
    "sg:city":"Weert",
    "sg:orig_category":"Schoenen",
    "sg:phone":"+31 495 545 600",
    "sg:postcode":"6001 GG",
    "sg:province":"Limburg",
    "wof:name":"Claessens Modeschoenen",
    "wof:placetype":"venue"
},
  "geometry": {"coordinates":[5.705723,51.256161],"type":"Point"}
}