{
  "type": "Feature",
  "properties": {
    "addr:full":"Zambiastr 15 Delft Zuid-Holland 2622 DG",
    "addr:housenumber":"15",
    "addr:postcode":"2622 dg",
    "addr:street":"Zambiastr",
    "iso:country":"NL",
    "sg:address":"Zambiastr 15",
    "sg:city":"Delft",
    "sg:orig_category":"Octrooionderzoek- En Exploitatiebureaus",
    "sg:phone":"+31 15 261 7192",
    "sg:postcode":"2622 DG",
    "sg:province":"Zuid-Holland",
    "wof:name":"Gicom",
    "wof:placetype":"venue"
},
  "geometry": {"coordinates":[4.339485,51.982819],"type":"Point"}
}