{
  "type": "Feature",
  "properties": {
    "addr:full":"Amersfoortsewg 11C Doorn Utrecht 3941 EJ",
    "addr:housenumber":"11c",
    "addr:postcode":"3941 ej",
    "addr:street":"Amersfoortsewg",
    "iso:country":"NL",
    "sg:address":"Amersfoortsewg 11C",
    "sg:city":"Doorn",
    "sg:orig_category":"Fotoreportages",
    "sg:phone":"+31 343 592 092",
    "sg:postcode":"3941 EJ",
    "sg:province":"Utrecht",
    "wof:name":"Kesteren, Van",
    "wof:placetype":"venue"
},
  "geometry": {"coordinates":[5.345485,52.033768],"type":"Point"}
}