{
  "type": "Feature",
  "properties": {
    "addr:full":"Stadhouderln 51 Zwolle Overijssel 8016 AB",
    "addr:housenumber":"51",
    "addr:postcode":"8016 ab",
    "addr:street":"Stadhouderln",
    "iso:country":"NL",
    "sg:address":"Stadhouderln 51",
    "sg:city":"Zwolle",
    "sg:orig_category":"Verzekeringen - Verzekeringskantoren",
    "sg:phone":"+31 38 460 7930",
    "sg:postcode":"8016 AB",
    "sg:province":"Overijssel",
    "wof:name":"Gepast Advies",
    "wof:placetype":"venue"
},
  "geometry": {"coordinates":[6.088738,52.512566],"type":"Point"}
}