{
  "type": "Feature",
  "properties": {
    "addr:full":"Rietveen 3 Nieuwerkerk Yssel South Holland 2912 SK",
    "addr:housenumber":"3",
    "addr:street":"Rietveen;2912",
    "iso:country":"NL",
    "sg:address":"Rietveen 3",
    "sg:city":"Nieuwerkerk Yssel",
    "sg:orig_category":"Etalagefiguren En -Materialen",
    "sg:phone":"+31 180 322 046",
    "sg:postcode":"2912 SK",
    "sg:province":"South Holland",
    "wof:name":"Wat Anders",
    "wof:placetype":"venue"
},
  "geometry": {"coordinates":[4.614205,51.964836],"type":"Point"}
}