{
  "type": "Feature",
  "properties": {
    "iso:country":"NL",
    "sg:address":"Dorpsstraat 162",
    "sg:city":"Scherpenzeel Gld",
    "sg:orig_category":"Herenmodezaken",
    "sg:phone":"+31 33 277 1296",
    "sg:postcode":"3925 KG",
    "sg:province":"Utrecht",
    "wof:name":"Struik Mode",
    "wof:placetype":"venue"
},
  "geometry": {"coordinates":[5.490598,52.079327],"type":"Point"}
}