{
  "type": "Feature",
  "properties": {
    "iso:country":"NL",
    "sg:address":"Hofstraat 1",
    "sg:city":"Willemstad Nb",
    "sg:orig_category":"Kinderopvang Behalve Thuis",
    "sg:phone":"+31 168 472 296",
    "sg:postcode":"4797 AC",
    "sg:province":"Noord-Brabant",
    "wof:name":"Kinderdagverblijf De Speeldoos",
    "wof:placetype":"venue"
},
  "geometry": {"coordinates":[4.436343,51.693016],"type":"Point"}
}