{
  "type": "Feature",
  "properties": {
    "iso:country":"NL",
    "sg:address":"Pastoor Pottersplein 12",
    "sg:city":"Breda",
    "sg:orig_category":"Overheidsdiensten",
    "sg:phone":"+31 76 571 0915",
    "sg:postcode":"4815 BC",
    "sg:province":"Noord-Brabant",
    "wof:name":"De Belcrum",
    "wof:placetype":"venue"
},
  "geometry": {"coordinates":[4.7776007652,51.6001358032],"type":"Point"}
}