{
  "type": "Feature",
  "properties": {
    "addr:full":"Pastoor Pottersplein 12 Breda Noord-Brabant 4815 BC",
    "addr:housenumber":"12",
    "addr:postcode":"4815 bc",
    "addr:street":"Pastoor Pottersplein",
    "iso:country":"NL",
    "sg:address":"Pastoor Pottersplein 12",
    "sg:city":"Breda",
    "sg:orig_category":"Overheidsdiensten",
    "sg:phone":"+31 76 571 0915",
    "sg:postcode":"4815 BC",
    "sg:province":"Noord-Brabant",
    "wof:name":"De Belcrum",
    "wof:placetype":"venue"
},
  "geometry": {"coordinates":[4.7776007652,51.6001358032],"type":"Point"}
}