{
  "type": "Feature",
  "properties": {
    "addr:full":"Nye Buorren 2 Woudsend Provincie Friesland 8551 PN",
    "addr:housenumber":"2",
    "addr:postcode":"8551 pn",
    "addr:street":"Nye Buorren;Provincie Friesland",
    "iso:country":"NL",
    "sg:address":"Nye Buorren 2",
    "sg:city":"Woudsend",
    "sg:orig_category":"Verhuizingen",
    "sg:phone":"+31 514 591 362",
    "sg:postcode":"8551 PN",
    "sg:province":"Provincie Friesland",
    "sg:website":"http://www.dejongverhuizingen.nl",
    "wof:name":"Jong Verhuizingen, De",
    "wof:placetype":"venue"
},
  "geometry": {"coordinates":[5.6206,52.948154],"type":"Point"}
}