{
  "type": "Feature",
  "properties": {
    "addr:full":"Burg Niemeijerstr 3 Staphorst NL.08 7951 TD",
    "addr:housenumber":"3;nl.08",
    "addr:postcode":"7951 td",
    "addr:street":"Burg Niemeijerstr",
    "iso:country":"NL",
    "sg:address":"Burg Niemeijerstr 3",
    "sg:city":"Staphorst",
    "sg:orig_category":"Diverse Consumentenartikelen Gh",
    "sg:phone":"+31 522 461 310",
    "sg:postcode":"7951 TD",
    "sg:province":"NL.08",
    "wof:name":"Vof Frans Van Der Veen",
    "wof:placetype":"venue"
},
  "geometry": {"coordinates":[6.227294,52.636726],"type":"Point"}
}