{
  "type": "Feature",
  "properties": {
    "addr:full":"Bellamypk 26 Vlissingen Zeeland 4381 CK",
    "addr:housenumber":"26",
    "addr:postcode":"4381 ck",
    "addr:street":"Bellamypk",
    "iso:country":"NL",
    "sg:address":"Bellamypk 26",
    "sg:city":"Vlissingen",
    "sg:orig_category":"Kappers",
    "sg:phone":"+31 118 417 164",
    "sg:postcode":"4381 CK",
    "sg:province":"Zeeland",
    "wof:name":"Christian",
    "wof:placetype":"venue"
},
  "geometry": {"coordinates":[3.5740830898,51.4418296814],"type":"Point"}
}