{
  "type": "Feature",
  "properties": {
    "iso:country":"NL",
    "sg:address":"Oud Eemnesserweg 23",
    "sg:city":"Eemnes",
    "sg:orig_category":"Bloemen And Planten",
    "sg:phone":"+31 35 538 7711",
    "sg:postcode":"3755 MR",
    "sg:province":"Utrecht",
    "wof:name":"Europatuin Eemnes",
    "wof:placetype":"venue"
},
  "geometry": {"coordinates":[5.242762,52.226875],"type":"Point"}
}