{
  "type": "Feature",
  "properties": {
    "addr:full":"Nieuwstraat 22 Hoorn Nh North Holland 1621 EA",
    "addr:housenumber":"22",
    "addr:postcode":"1621 ea",
    "addr:street":"Nieuwstraat;Nh North",
    "iso:country":"NL",
    "sg:address":"Nieuwstraat 22",
    "sg:city":"Hoorn Nh",
    "sg:orig_category":"Juweliers",
    "sg:phone":"+31 229 214 438",
    "sg:postcode":"1621 EA",
    "sg:province":"North Holland",
    "wof:name":"Siebel Juweliers Bv",
    "wof:placetype":"venue"
},
  "geometry": {"coordinates":[5.060074,52.641388],"type":"Point"}
}