{
  "type": "Feature",
  "properties": {
    "iso:country":"NL",
    "sg:address":"Nootweg 31",
    "sg:city":"Loosdrecht",
    "sg:orig_category":"Banken And Kredietinstellingen",
    "sg:phone":"+31 35 582 1751",
    "sg:postcode":"1231 CP",
    "sg:province":"Noord-Holland",
    "wof:name":"Abn Amro",
    "wof:placetype":"venue"
},
  "geometry": {"coordinates":[5.137331,52.199982],"type":"Point"}
}