{
  "type": "Feature",
  "properties": {
    "addr:full":"Keppelseweg 1 Doetinchem Gelderland 7001 CE",
    "addr:housenumber":"1",
    "addr:postcode":"7001 ce",
    "addr:street":"Keppelseweg;Gelderland",
    "iso:country":"NL",
    "sg:address":"Keppelseweg 1",
    "sg:city":"Doetinchem",
    "sg:orig_category":"Notarissen",
    "sg:phone":"+31 314 372 222",
    "sg:postcode":"7001 CE",
    "sg:province":"Gelderland",
    "wof:name":"Van Weeghel-Dottenberg Notarissen",
    "wof:placetype":"venue"
},
  "geometry": {"coordinates":[6.285639,51.967506],"type":"Point"}
}