{
  "type": "Feature",
  "properties": {
    "addr:full":"Korenmaat 8 Assen Drenthe 9405 TJ",
    "addr:housenumber":"8",
    "addr:postcode":"9405 tj",
    "addr:street":"Korenmaat",
    "iso:country":"NL",
    "sg:address":"Korenmaat 8",
    "sg:city":"Assen",
    "sg:orig_category":"Banden - Fabrieken En Groothandel",
    "sg:phone":"+31 592 333 030",
    "sg:postcode":"9405 TJ",
    "sg:province":"Drenthe",
    "wof:name":"Holland Tyre Bv",
    "wof:placetype":"venue"
},
  "geometry": {"coordinates":[6.558314,52.97221],"type":"Point"}
}