{
  "type": "Feature",
  "properties": {
    "addr:full":"Belcrumweg 5 Breda Noord-Brabant 4815 HA",
    "addr:housenumber":"5",
    "addr:postcode":"4815 ha",
    "addr:street":"Belcrumweg",
    "iso:country":"NL",
    "sg:address":"Belcrumweg 5",
    "sg:city":"Breda",
    "sg:orig_category":"Verhuur Gereedschapsmachines And Gereedschappen",
    "sg:phone":"+31 76 572 1050",
    "sg:postcode":"4815 HA",
    "sg:province":"Noord-Brabant",
    "wof:name":"Boels Verhuur",
    "wof:placetype":"venue"
},
  "geometry": {"coordinates":[4.769248,51.598091],"type":"Point"}
}