{
  "type": "Feature",
  "properties": {
    "iso:country":"NL",
    "sg:address":"Langstraat 56",
    "sg:city":"Wassenaar",
    "sg:orig_category":"Krantenuitgeverijen",
    "sg:phone":"+31 70 511 4000",
    "sg:postcode":"2242 KN",
    "sg:province":"South Holland",
    "wof:name":"Uitg Geco",
    "wof:placetype":"venue"
},
  "geometry": {"coordinates":[4.393668,52.143719],"type":"Point"}
}