{
  "type": "Feature",
  "properties": {
    "addr:full":"Wethouder Van Bremenweg 20 Beesd Gelderland 4153 XH",
    "addr:housenumber":"20",
    "addr:postcode":"4153 xh",
    "addr:street":"Wethouder Van Bremenweg;Gelderland",
    "iso:country":"NL",
    "sg:address":"Wethouder Van Bremenweg 20",
    "sg:city":"Beesd",
    "sg:orig_category":"Metaalafval, Schrootrecycling And Sloperijen",
    "sg:phone":"+31 345 681 812",
    "sg:postcode":"4153 XH",
    "sg:province":"Gelderland",
    "wof:name":"Metaalhandel Gebr. Coenmans Bv",
    "wof:placetype":"venue"
},
  "geometry": {"coordinates":[5.172208,51.916862],"type":"Point"}
}