{
  "type": "Feature",
  "properties": {
    "addr:full":"Geldersestr 76 Geldermalsen Gelderland 4191 BD",
    "addr:housenumber":"76",
    "addr:postcode":"4191 bd",
    "addr:street":"Geldersestr;Gelderland",
    "iso:country":"NL",
    "sg:address":"Geldersestr 76",
    "sg:city":"Geldermalsen",
    "sg:orig_category":"Wasmachines En Wasdrogers",
    "sg:phone":"+31 345 581 948",
    "sg:postcode":"4191 BD",
    "sg:province":"Gelderland",
    "wof:name":"Bruin, De",
    "wof:placetype":"venue"
},
  "geometry": {"coordinates":[5.2931690216,51.8832092285],"type":"Point"}
}