{
  "type": "Feature",
  "properties": {
    "addr:full":"Lorentzkd 166 Haarlem Noord-Holland 2014 CD",
    "addr:housenumber":"166",
    "addr:postcode":"2014 cd",
    "iso:country":"NL",
    "sg:address":"Lorentzkd 166",
    "sg:city":"Haarlem",
    "sg:orig_category":"Adviesbureaus Bedrijfsorganisatie",
    "sg:phone":"+31 23 534 6353",
    "sg:postcode":"2014 CD",
    "sg:province":"Noord-Holland",
    "sg:website":"http://www.horizontwikkeling.nl",
    "wof:name":"Horizont",
    "wof:placetype":"venue"
},
  "geometry": {"coordinates":[4.611114,52.373142],"type":"Point"}
}