{
  "type": "Feature",
  "properties": {
    "addr:full":"Gorecht O 131 Hoogezand Groningen 9603 AE",
    "addr:housenumber":"131",
    "addr:postcode":"9603 ae",
    "iso:country":"NL",
    "sg:address":"Gorecht O 131",
    "sg:city":"Hoogezand",
    "sg:orig_category":"Opticiens",
    "sg:phone":"+31 598 327 190",
    "sg:postcode":"9603 AE",
    "sg:province":"Groningen",
    "sg:website":"http://www.hansanders.nl",
    "wof:name":"Hans Anders",
    "wof:placetype":"venue"
},
  "geometry": {"coordinates":[6.7576260567,53.1555175781],"type":"Point"}
}