{
  "type": "Feature",
  "properties": {
    "addr:full":"Paktuinen 8 Enkhuizen North Holland 1601 GD",
    "addr:housenumber":"8",
    "addr:postcode":"1601 gd",
    "addr:street":"Paktuinen",
    "iso:country":"NL",
    "sg:address":"Paktuinen 8",
    "sg:city":"Enkhuizen",
    "sg:classifiers":[
        {
            "category":"Travel",
            "subcategory":"Hotels & Motels",
            "type":"Entertainment"
        }
    ],
    "sg:phone":"+31 228 312 462",
    "sg:postcode":"1601 GD",
    "sg:province":"North Holland",
    "wof:name":"Du Passage",
    "wof:placetype":"venue"
},
  "geometry": {"coordinates":[5.290497,52.701397],"type":"Point"}
}