{
  "type": "Feature",
  "properties": {
    "iso:country":"NL",
    "sg:address":"Berkhoutln 1",
    "sg:city":"Lisse",
    "sg:orig_category":"Bloemen En Planten",
    "sg:phone":"+31 252 411 609",
    "sg:postcode":"2161 EL",
    "sg:province":"North Holland",
    "wof:name":"Fleurette",
    "wof:placetype":"venue"
},
  "geometry": {"coordinates":[4.552546,52.257221],"type":"Point"}
}