{
  "type": "Feature",
  "properties": {
    "addr:full":"Kaldenkerkerwg 20 Venlo Limburg 5913 AE",
    "addr:housenumber":"20",
    "addr:postcode":"5913 ae",
    "addr:street":"Kaldenkerkerwg",
    "iso:country":"NL",
    "sg:address":"Kaldenkerkerwg 20",
    "sg:city":"Venlo",
    "sg:orig_category":"Politie",
    "sg:phone":"+31 900 8844",
    "sg:postcode":"5913 AE",
    "sg:province":"Limburg",
    "wof:name":"Politie",
    "wof:placetype":"venue"
},
  "geometry": {"coordinates":[6.174318,51.363918],"type":"Point"}
}