{
  "type": "Feature",
  "properties": {
    "addr:full":"Parklaan 40 Rotterdam Zuid-Holland 3016 BC",
    "addr:housenumber":"40",
    "addr:postcode":"3016 bc",
    "addr:street":"Parklaan",
    "iso:country":"NL",
    "sg:address":"Parklaan 40",
    "sg:city":"Rotterdam",
    "sg:orig_category":"Bedrijfs- And Managementsconsultants",
    "sg:phone":"+31 10 436 0364",
    "sg:postcode":"3016 BC",
    "sg:province":"Zuid-Holland",
    "wof:name":"Policy Research Corp",
    "wof:placetype":"venue"
},
  "geometry": {"coordinates":[4.474119,51.906982],"type":"Point"}
}