{
  "type": "Feature",
  "properties": {
    "addr:full":"Herestraat 9 Groningen Groningen 9711 LA",
    "addr:housenumber":"9",
    "addr:postcode":"9711 la",
    "addr:street":"Herestraat",
    "iso:country":"NL",
    "sg:address":"Herestraat 9",
    "sg:city":"Groningen",
    "sg:orig_category":"Medische And Orthopedische Artikelen",
    "sg:phone":"+31 50 318 4135",
    "sg:postcode":"9711 LA",
    "sg:province":"Groningen",
    "wof:name":"Becker Bv",
    "wof:placetype":"venue"
},
  "geometry": {"coordinates":[6.566678,53.217609],"type":"Point"}
}