{
  "type": "Feature",
  "properties": {
    "addr:full":"Twyver 66A Venhuizen Noord-Holland 1606 BW",
    "addr:housenumber":"66a",
    "addr:postcode":"1606 bw",
    "addr:street":"Twyver",
    "iso:country":"NL",
    "sg:address":"Twyver 66A",
    "sg:city":"Venhuizen",
    "sg:orig_category":"Bibliotheken En Leeszalen Openbare",
    "sg:phone":"+31 228 542 326",
    "sg:postcode":"1606 BW",
    "sg:province":"Noord-Holland",
    "wof:name":"Openb Bibliotheek",
    "wof:placetype":"venue"
},
  "geometry": {"coordinates":[5.199493,52.662418],"type":"Point"}
}