{
  "type": "Feature",
  "properties": {
    "addr:full":"Ln D Zeven Linden 161 Delfgauw Zuid-Holland 2645 GV",
    "addr:housenumber":"161",
    "addr:postcode":"2645 gv",
    "addr:street":"Ln D Zeven Linden",
    "iso:country":"NL",
    "sg:address":"Ln D Zeven Linden 161",
    "sg:city":"Delfgauw",
    "sg:orig_category":"Danssportbenodigdheden",
    "sg:phone":"+31 15 285 0893",
    "sg:postcode":"2645 GV",
    "sg:province":"Zuid-Holland",
    "sg:website":"http://www.floorcraft.nl",
    "wof:name":"Floorcraft",
    "wof:placetype":"venue"
},
  "geometry": {"coordinates":[4.390677,52.004456],"type":"Point"}
}