{
  "type": "Feature",
  "properties": {
    "addr:full":"Melanendreef 147 Bergen Op Zoom Noord-Brabant 4614 GK",
    "addr:housenumber":"147",
    "addr:postcode":"4614 gk",
    "addr:street":"Melanendreef",
    "iso:country":"NL",
    "sg:address":"Melanendreef 147",
    "sg:city":"Bergen Op Zoom",
    "sg:orig_category":"Verlichting",
    "sg:phone":"+31 164 266 072",
    "sg:postcode":"4614 GK",
    "sg:province":"Noord-Brabant",
    "wof:name":"Jasper, G",
    "wof:placetype":"venue"
},
  "geometry": {"coordinates":[4.287783,51.509785],"type":"Point"}
}