{
  "type": "Feature",
  "properties": {
    "addr:full":"Aristotelesstr 2 Amersfoort Utrecht 3822 BT",
    "addr:housenumber":"2",
    "addr:postcode":"3822 bt",
    "addr:street":"Aristotelesstr",
    "iso:country":"NL",
    "sg:address":"Aristotelesstr 2",
    "sg:city":"Amersfoort",
    "sg:orig_category":"Kappers",
    "sg:phone":"+31 33 455 2438",
    "sg:postcode":"3822 BT",
    "sg:province":"Utrecht",
    "wof:name":"Fivon Coiffures",
    "wof:placetype":"venue"
},
  "geometry": {"coordinates":[5.4038600922,52.1772270203],"type":"Point"}
}