{
  "type": "Feature",
  "properties": {
    "addr:full":"Kraaienlaan 5 'S Gravenhage Zuid-Holland 2566 RA",
    "addr:housenumber":"5 '",
    "addr:postcode":"2566 ra",
    "addr:street":"Kraaienlaan",
    "iso:country":"NL",
    "sg:address":"Kraaienlaan 5",
    "sg:city":"'S Gravenhage",
    "sg:orig_category":"Juridische Dienstverlening",
    "sg:phone":"+31 70 368 2884",
    "sg:postcode":"2566 RA",
    "sg:province":"Zuid-Holland",
    "wof:name":"Juridisch Adv- & Bemiddelingsbur Frans C",
    "wof:placetype":"venue"
},
  "geometry": {"coordinates":[4.248091,52.076256],"type":"Point"}
}