{
  "type": "Feature",
  "properties": {
    "iso:country":"NL",
    "sg:address":"Grt Staat 44",
    "sg:city":"Maastricht",
    "sg:orig_category":"Homeopathie",
    "sg:phone":"+31 43 325 3908",
    "sg:postcode":"6211 CX",
    "sg:province":"Limburg",
    "sg:website":"http://www.dekruiderij.nl",
    "wof:name":"Kruiderij, De",
    "wof:placetype":"venue"
},
  "geometry": {"coordinates":[5.689912,50.849934],"type":"Point"}
}