{
  "type": "Feature",
  "properties": {
    "iso:country":"NL",
    "sg:address":"Marktstraat 31",
    "sg:city":"Ravenstein",
    "sg:classifiers":[
        {
            "category":"Bakery",
            "type":"Food & Drink"
        }
    ],
    "sg:phone":"+31 486 411 293",
    "sg:postcode":"5371 AC",
    "sg:province":"Noord-Brabant",
    "sg:tags":[
        "brood",
        "banket"
    ],
    "wof:name":"Echte Bakker Willy Van Mook",
    "wof:placetype":"venue"
},
  "geometry": {"coordinates":[5.6524038315,51.7974586487],"type":"Point"}
}