{
  "type": "Feature",
  "properties": {
    "addr:full":"Noordzijde 36 Noordeloos Zuid-Holland 4225 PH",
    "addr:housenumber":"36",
    "addr:postcode":"4225",
    "addr:street":"Noordzijde",
    "iso:country":"NL",
    "sg:address":"Noordzijde 36",
    "sg:city":"Noordeloos",
    "sg:orig_category":"Binnenhuisarchitecten",
    "sg:phone":"+31 183 582 478",
    "sg:postcode":"4225 PH",
    "sg:province":"Zuid-Holland",
    "wof:name":"Cees Oosterom Design Bv",
    "wof:placetype":"venue"
},
  "geometry": {"coordinates":[4.941274,51.903866],"type":"Point"}
}