{
  "type": "Feature",
  "properties": {
    "addr:full":"Spoorln 24 Etten Leur Noord-Brabant 4872 XP",
    "addr:housenumber":"24",
    "addr:postcode":"4872 xp",
    "addr:street":"Spoorln",
    "iso:country":"NL",
    "sg:address":"Spoorln 24",
    "sg:city":"Etten Leur",
    "sg:orig_category":"Glazenwasserijen",
    "sg:phone":"+31 76 501 7368",
    "sg:postcode":"4872 XP",
    "sg:province":"Noord-Brabant",
    "wof:name":"Kruif, De",
    "wof:placetype":"venue"
},
  "geometry": {"coordinates":[4.639522,51.570694],"type":"Point"}
}