{
  "type": "Feature",
  "properties": {
    "addr:full":"Bombaystr 79 Rotterdam Zuid-Holland 3047 BA",
    "addr:housenumber":"79",
    "addr:postcode":"3047 ba",
    "addr:street":"Bombaystr",
    "iso:country":"NL",
    "sg:address":"Bombaystr 79",
    "sg:city":"Rotterdam",
    "sg:orig_category":"Oldtimers",
    "sg:phone":"+31 10 437 2404",
    "sg:postcode":"3047 BA",
    "sg:province":"Zuid-Holland",
    "sg:website":"http://www.xs4all.nl/~robinscc/",
    "wof:name":"Anthony Robins",
    "wof:placetype":"venue"
},
  "geometry": {"coordinates":[4.402012,51.941326],"type":"Point"}
}