{
  "type": "Feature",
  "properties": {
    "iso:country":"NL",
    "sg:address":"Burg Roelenwg 34",
    "sg:city":"Zwolle",
    "sg:orig_category":"Artsen - Manuele Geneeskunde",
    "sg:phone":"+31 341 563 252",
    "sg:postcode":"8021 EW",
    "sg:province":"Overijssel",
    "wof:name":"Zwieten, J A Van",
    "wof:placetype":"venue"
},
  "geometry": {"coordinates":[6.086538,52.51738],"type":"Point"}
}