{
  "type": "Feature",
  "properties": {
    "iso:country":"NL",
    "sg:address":"Postbus 93",
    "sg:city":"Culemborg",
    "sg:orig_category":"Geluidshinderbestrijding",
    "sg:phone":"+31 345 470 170",
    "sg:postcode":"4100 AB",
    "sg:province":"Gelderland",
    "wof:name":"Redubel Geluidsschermen",
    "wof:placetype":"venue"
},
  "geometry": {"coordinates":[5.22148,51.952175],"type":"Point"}
}