{
  "type": "Feature",
  "properties": {
    "addr:full":"Zijde 3 Boskoop South Holland 2771 EJ",
    "addr:housenumber":"3",
    "addr:postcode":"2771 ej",
    "addr:street":"Zijde",
    "iso:country":"NL",
    "sg:address":"Zijde 3",
    "sg:city":"Boskoop",
    "sg:orig_category":"Meubelzaken, Woning- And Keukeninrichting",
    "sg:phone":"+31 172 212 544",
    "sg:postcode":"2771 EJ",
    "sg:province":"South Holland",
    "wof:name":"Morgana Slaapkamers Van Der Linde",
    "wof:placetype":"venue"
},
  "geometry": {"coordinates":[4.658297,52.07444],"type":"Point"}
}