{
  "type": "Feature",
  "properties": {
    "iso:country":"NL",
    "sg:address":"Tussen De Bogen 107",
    "sg:city":"Amsterdam",
    "sg:orig_category":"Architecten",
    "sg:phone":"+31 20 625 0575",
    "sg:postcode":"1013 JB",
    "sg:province":"Noord-Holland",
    "wof:name":"Dolderen Vd Prijt Architecten",
    "wof:placetype":"venue"
},
  "geometry": {"coordinates":[4.885193,52.385044],"type":"Point"}
}