{
  "type": "Feature",
  "properties": {
    "addr:full":"V Loostr 68 S Gravenhage Zuid-Holland 2582 XE",
    "addr:housenumber":"68;gravenhage",
    "addr:postcode":"2582 xe",
    "addr:street":"S",
    "iso:country":"NL",
    "sg:address":"V Loostr 68",
    "sg:city":"S Gravenhage",
    "sg:orig_category":"Fotoreportages",
    "sg:phone":"+31 6 22213470",
    "sg:postcode":"2582 XE",
    "sg:province":"Zuid-Holland",
    "wof:name":"Allfo",
    "wof:placetype":"venue"
},
  "geometry": {"coordinates":[4.27852,52.092411],"type":"Point"}
}