{
  "type": "Feature",
  "properties": {
    "addr:full":"Waye 1A Neer Limburg 6086 NP",
    "addr:housenumber":"1a",
    "addr:postcode":"6086 np",
    "addr:street":"Waye",
    "iso:country":"NL",
    "sg:address":"Waye 1A",
    "sg:city":"Neer",
    "sg:orig_category":"Sportverenigingen En Ontspannings- Verenigingen",
    "sg:phone":"+31 475 594 195",
    "sg:postcode":"6086 NP",
    "sg:province":"Limburg",
    "wof:name":"Bussen-Schutten, Schietver",
    "wof:placetype":"venue"
},
  "geometry": {"coordinates":[6.002925,51.266392],"type":"Point"}
}