{
  "type": "Feature",
  "properties": {
    "addr:full":"Aalscholver 13 Muiderberg Noord-Holland 1399 KP",
    "addr:housenumber":"13;1399",
    "addr:postcode":"kp",
    "addr:street":"Aalscholver",
    "iso:country":"NL",
    "sg:address":"Aalscholver 13",
    "sg:city":"Muiderberg",
    "sg:orig_category":"Babyartikelen",
    "sg:phone":"+31 294 261 606",
    "sg:postcode":"1399 KP",
    "sg:province":"Noord-Holland",
    "wof:name":"Koeka",
    "wof:placetype":"venue"
},
  "geometry": {"coordinates":[5.124628,52.324284],"type":"Point"}
}