{
  "type": "Feature",
  "properties": {
    "addr:full":"Jan Bronnerstraat 101 'S Gravenhage South Holland 2552 WX",
    "addr:housenumber":"101 '",
    "addr:postcode":"2552 wx",
    "addr:street":"Jan Bronnerstraat",
    "iso:country":"NL",
    "sg:address":"Jan Bronnerstraat 101",
    "sg:city":"'S Gravenhage",
    "sg:orig_category":"Alternatieve Geneeskunde",
    "sg:phone":"+31 70 391 2361",
    "sg:postcode":"2552 WX",
    "sg:province":"South Holland",
    "wof:name":"Hstc Oosterman Bv",
    "wof:placetype":"venue"
},
  "geometry": {"coordinates":[4.249347,52.055931],"type":"Point"}
}