{
  "type": "Feature",
  "properties": {
    "addr:full":"T Stegeslag 26 Zevenaar Gelderland 6903 XV",
    "addr:housenumber":"26",
    "addr:postcode":"6903 xv",
    "addr:street":"T Stegeslag",
    "iso:country":"NL",
    "sg:address":"T Stegeslag 26",
    "sg:city":"Zevenaar",
    "sg:orig_category":"Kinderkleding",
    "sg:phone":"+31 316 331 627",
    "sg:postcode":"6903 XV",
    "sg:province":"Gelderland",
    "wof:name":"Klein-Duimpje",
    "wof:placetype":"venue"
},
  "geometry": {"coordinates":[6.062736,51.940479],"type":"Point"}
}