{
  "type": "Feature",
  "properties": {
    "addr:full":"Keersluisweg 11 Almere Flevoland 1332 EE",
    "addr:housenumber":"11",
    "addr:postcode":"1332 ee",
    "addr:street":"Keersluisweg;Flevoland",
    "iso:country":"NL",
    "sg:address":"Keersluisweg 11",
    "sg:city":"Almere",
    "sg:orig_category":"Koffie, Thee And Specerijen Gh",
    "sg:phone":"+31 36 537 2480",
    "sg:postcode":"1332 EE",
    "sg:province":"Flevoland",
    "wof:name":"Blok Bv",
    "wof:placetype":"venue"
},
  "geometry": {"coordinates":[5.248012,52.409794],"type":"Point"}
}