{
  "type": "Feature",
  "properties": {
    "addr:full":"Felliniln 151 Almere NL. 1325 TW",
    "addr:housenumber":"151",
    "addr:postcode":"1325 tw",
    "addr:street":"Nl.",
    "iso:country":"NL",
    "sg:address":"Felliniln 151",
    "sg:city":"Almere",
    "sg:orig_category":"Webdesign Bureaus",
    "sg:phone":"+31 6 28750656",
    "sg:postcode":"1325 TW",
    "sg:province":"NL.",
    "sg:website":"http://www.benjaminwebdesign.nl",
    "wof:name":"Benjamin",
    "wof:placetype":"venue"
},
  "geometry": {"coordinates":[5.2425642014,52.3573722839],"type":"Point"}
}