{
  "type": "Feature",
  "properties": {
    "addr:full":"Lilienthalplein 3 Stadskanaal Groningen 9501 XP",
    "addr:housenumber":"3",
    "addr:postcode":"9501 xp",
    "addr:street":"Lilienthalplein",
    "iso:country":"NL",
    "sg:address":"Lilienthalplein 3",
    "sg:city":"Stadskanaal",
    "sg:orig_category":"Notarissen",
    "sg:phone":"+31 599 612 016",
    "sg:postcode":"9501 XP",
    "sg:province":"Groningen",
    "wof:name":"Notariskantoor Dijkstra & Jansen",
    "wof:placetype":"venue"
},
  "geometry": {"coordinates":[6.952677,52.988819],"type":"Point"}
}