{
  "type": "Feature",
  "properties": {
    "addr:full":"Slieperstr 6 Beltrum Gelderland 7156 ML",
    "addr:housenumber":"6",
    "addr:postcode":"7156 ml",
    "addr:street":"Slieperstr;Gelderland",
    "iso:country":"NL",
    "sg:address":"Slieperstr 6",
    "sg:city":"Beltrum",
    "sg:orig_category":"Verenigingsgebouwen",
    "sg:phone":"+31 544 481 707",
    "sg:postcode":"7156 ML",
    "sg:province":"Gelderland",
    "wof:name":"Dorpshuis",
    "wof:placetype":"venue"
},
  "geometry": {"coordinates":[6.565014,52.067207],"type":"Point"}
}