{
  "type": "Feature",
  "properties": {
    "addr:full":"Bieremaln 15 S Gravenhage 2497 AW",
    "addr:housenumber":"15",
    "addr:postcode":"2497 aw",
    "addr:street":"Bieremaln;S Gravenhage",
    "iso:country":"NL",
    "sg:address":"Bieremaln 15",
    "sg:city":"S Gravenhage",
    "sg:orig_category":"Administratie- En Boekhoudkantoren",
    "sg:phone":"+31 70 369 9210",
    "sg:postcode":"2497 AW",
    "sg:website":"http://www.atil.nl",
    "wof:name":"Atil Bv",
    "wof:placetype":"venue"
},
  "geometry": {"coordinates":[4.36602,52.035912],"type":"Point"}
}