{
  "type": "Feature",
  "properties": {
    "addr:full":"Ryswyksewg 492 S Gravenhage South Holland 2516 HS",
    "addr:housenumber":"492",
    "addr:postcode":"2516 hs",
    "addr:street":"S Gravenhage",
    "iso:country":"NL",
    "sg:address":"Ryswyksewg 492",
    "sg:city":"S Gravenhage",
    "sg:orig_category":"Beeldende Kunstenaars",
    "sg:phone":"+31 70 399 9518",
    "sg:postcode":"2516 HS",
    "sg:province":"South Holland",
    "wof:name":"Simeoni, C",
    "wof:placetype":"venue"
},
  "geometry": {"coordinates":[4.33931,52.06786],"type":"Point"}
}