{
  "type": "Feature",
  "properties": {
    "addr:full":"Grachtwg 37 Lisse Zuid-Holland 2161 HL",
    "addr:housenumber":"37",
    "addr:postcode":"2161 hl",
    "addr:street":"Grachtwg",
    "iso:country":"NL",
    "sg:address":"Grachtwg 37",
    "sg:city":"Lisse",
    "sg:orig_category":"Schoenen",
    "sg:phone":"+31 252 414 112",
    "sg:postcode":"2161 HL",
    "sg:province":"Zuid-Holland",
    "wof:name":"Hogervorst",
    "wof:placetype":"venue"
},
  "geometry": {"coordinates":[4.555946,52.25938],"type":"Point"}
}