{
  "type": "Feature",
  "properties": {
    "iso:country":"NL",
    "sg:address":"Paterswoldsewg 16/1",
    "sg:city":"Groningen",
    "sg:orig_category":"Kappers",
    "sg:phone":"+31 50 313 0126",
    "sg:postcode":"9726 BC",
    "sg:province":"Groningen",
    "wof:name":"Onnes",
    "wof:placetype":"venue"
},
  "geometry": {"coordinates":[6.555713,53.212791],"type":"Point"}
}