{
  "type": "Feature",
  "properties": {
    "iso:country":"NL",
    "sg:address":"Esther De Boer V Rijkln 22",
    "sg:city":"Bussum",
    "sg:classifiers":[
        {
            "category":"Education",
            "subcategory":"Preschool",
            "type":"Public Place"
        }
    ],
    "sg:phone":"+31 35 693 8308",
    "sg:postcode":"1403 GD",
    "sg:province":"Noord-Holland",
    "sg:tags":[
        "kleuteronderwijs",
        "basis-"
    ],
    "wof:name":"Peuterhof Windekind",
    "wof:placetype":"venue"
},
  "geometry": {"coordinates":[5.1865592003,52.2670593262],"type":"Point"}
}