{
  "type": "Feature",
  "properties": {
    "addr:full":"Hoge Molenwerf 1 Ouderkerk A/D Ijssel South Holland 2935 CB",
    "addr:housenumber":"1;a / d",
    "addr:postcode":"2935 cb",
    "addr:street":"Hoge Molenwerf;Ijssel South",
    "iso:country":"NL",
    "sg:address":"Hoge Molenwerf 1",
    "sg:city":"Ouderkerk A/D Ijssel",
    "sg:classifiers":[
        {
            "category":"Education",
            "subcategory":"Preschool",
            "type":"Public Place"
        }
    ],
    "sg:phone":"+31 180 681 992",
    "sg:postcode":"2935 CB",
    "sg:province":"South Holland",
    "sg:tags":[
        "kleuteronderwijs",
        "basis-"
    ],
    "wof:name":"Koningin Julianaschool Christelijke School V Basis",
    "wof:placetype":"venue"
},
  "geometry": {"coordinates":[4.639876,51.965851],"type":"Point"}
}