{
  "type": "Feature",
  "properties": {
    "addr:full":"Damstraat 2 Dordrecht Zuid-Holland 3319 BD",
    "addr:housenumber":"2",
    "addr:postcode":"3319 bd",
    "addr:street":"Damstraat",
    "iso:country":"NL",
    "sg:address":"Damstraat 2",
    "sg:city":"Dordrecht",
    "sg:classifiers":[
        {
            "category":"Bakery",
            "type":"Food & Drink"
        }
    ],
    "sg:phone":"+31 78 616 2157",
    "sg:postcode":"3319 BD",
    "sg:province":"Zuid-Holland",
    "sg:tags":[
        "brood",
        "banket"
    ],
    "wof:name":"Echte Bakker Korteweg",
    "wof:placetype":"venue"
},
  "geometry": {"coordinates":[4.704196,51.794685],"type":"Point"}
}