{
  "type": "Feature",
  "properties": {
    "addr:full":"De Zandberg 4 Kaatsheuvel Noord-Brabant 5171 RE",
    "addr:housenumber":"4",
    "addr:postcode":"5171 re",
    "addr:street":"De Zandberg",
    "iso:country":"NL",
    "sg:address":"De Zandberg 4",
    "sg:city":"Kaatsheuvel",
    "sg:orig_category":"Verenigingen En Stichtingen",
    "sg:phone":"+31 416 337 617",
    "sg:postcode":"5171 RE",
    "sg:province":"Noord-Brabant",
    "wof:name":"Bekkersgroep, Mgr",
    "wof:placetype":"venue"
},
  "geometry": {"coordinates":[5.070005,51.668186],"type":"Point"}
}