{
  "type": "Feature",
  "properties": {
    "addr:full":"Bothniakd 20 Sneek Friesland 8601 BL",
    "addr:housenumber":"20",
    "addr:postcode":"8601 bl",
    "addr:street":"Bothniakd",
    "iso:country":"NL",
    "sg:address":"Bothniakd 20",
    "sg:city":"Sneek",
    "sg:orig_category":"Artsen - Huisartsen",
    "sg:phone":"+31 515 433 493",
    "sg:postcode":"8601 BL",
    "sg:province":"Friesland",
    "wof:name":"Toot",
    "wof:placetype":"venue"
},
  "geometry": {"coordinates":[5.66197,53.033459],"type":"Point"}
}