{
  "type": "Feature",
  "properties": {
    "addr:full":"De Huesmolen 39 Hoorn Nh Noord-Holland 1625 HZ",
    "addr:housenumber":"39",
    "addr:postcode":"1625 hz",
    "addr:street":"De Huesmolen",
    "iso:country":"NL",
    "sg:address":"De Huesmolen 39",
    "sg:city":"Hoorn Nh",
    "sg:orig_category":"Werving And Selectie Van Tijdelijk Personeel And Uitzendkantoren",
    "sg:phone":"+31 229 273 539",
    "sg:postcode":"1625 HZ",
    "sg:province":"Noord-Holland",
    "wof:name":"West",
    "wof:placetype":"venue"
},
  "geometry": {"coordinates":[5.0560760498,52.6579093933],"type":"Point"}
}