{
  "type": "Feature",
  "properties": {
    "addr:full":"M Hobbemastr 140 Almere Flevoland 1318 PG",
    "addr:housenumber":"140",
    "addr:postcode":"1318",
    "addr:street":"Flevoland;Pg",
    "iso:country":"NL",
    "sg:address":"M Hobbemastr 140",
    "sg:city":"Almere",
    "sg:orig_category":"Fotoreportages",
    "sg:phone":"+31 36 533 8315",
    "sg:postcode":"1318 PG",
    "sg:province":"Flevoland",
    "wof:name":"Admiraal",
    "wof:placetype":"venue"
},
  "geometry": {"coordinates":[5.257019,52.382763],"type":"Point"}
}