{
  "type": "Feature",
  "properties": {
    "iso:country":"NL",
    "sg:address":"Annie M G Schmidtplein 2",
    "sg:city":"Maasland",
    "sg:classifiers":[
        {
            "category":"Education",
            "subcategory":"Preschool",
            "type":"Public Place"
        }
    ],
    "sg:phone":"+31 10 592 6617",
    "sg:postcode":"3155 VZ",
    "sg:province":"Zuid-Holland",
    "sg:tags":[
        "kleuteronderwijs",
        "basis-"
    ],
    "wof:name":"Harlekijn",
    "wof:placetype":"venue"
},
  "geometry": {"coordinates":[4.269559,51.934505],"type":"Point"}
}