{
  "type": "Feature",
  "properties": {
    "addr:full":"Woldreef 3 Oss Noord-Brabant 5345 XX",
    "addr:housenumber":"3",
    "addr:postcode":"5345 xx",
    "addr:street":"Woldreef",
    "iso:country":"NL",
    "sg:address":"Woldreef 3",
    "sg:city":"Oss",
    "sg:orig_category":"Werving And Selectie Van Vast Personeel",
    "sg:phone":"+31 412 639 482",
    "sg:postcode":"5345 XX",
    "sg:province":"Noord-Brabant",
    "wof:name":"De Vries Werving En Selectie Vof",
    "wof:placetype":"venue"
},
  "geometry": {"coordinates":[-77.2352142334,38.3125991821],"type":"Point"}
}