{
  "type": "Feature",
  "properties": {
    "iso:country":"NL",
    "sg:address":"Jan Bernardusstraat 24 H.L.",
    "sg:city":"Amsterdam",
    "sg:classifiers":[
        {
            "category":"Recreation",
            "subcategory":"Amusement Park",
            "type":"Entertainment"
        }
    ],
    "sg:phone":"+31 20 694 0898",
    "sg:postcode":"1091 TT",
    "sg:province":"Noord-Holland",
    "wof:name":"Eventief Evenementen Organisatie",
    "wof:placetype":"venue"
},
  "geometry": {"coordinates":[4.91306,52.35487],"type":"Point"}
}