{
  "type": "Feature",
  "properties": {
    "addr:full":"Fluitenkruid 6 S Hertogenbosch Noord-Brabant 5236 TL",
    "addr:housenumber":"6",
    "addr:postcode":"5236 tl",
    "addr:street":"Fluitenkruid",
    "iso:country":"NL",
    "sg:address":"Fluitenkruid 6",
    "sg:city":"S Hertogenbosch",
    "sg:orig_category":"Kinderopvang",
    "sg:phone":"+31 73 611 1370",
    "sg:postcode":"5236 TL",
    "sg:province":"Noord-Brabant",
    "wof:name":"Sterrenwacht, De",
    "wof:placetype":"venue"
},
  "geometry": {"coordinates":[5.329496,51.73291],"type":"Point"}
}