{
  "type": "Feature",
  "properties": {
    "iso:country":"NL",
    "sg:address":"Draijerswijk 13",
    "sg:city":"Oude Pekela",
    "sg:orig_category":"Goederenvervoer Over De Weg",
    "sg:phone":"+31 597 618 319",
    "sg:postcode":"9665 NH",
    "sg:province":"Groningen",
    "wof:name":"P. Broesder",
    "wof:placetype":"venue"
},
  "geometry": {"coordinates":[7.007344,53.100922],"type":"Point"}
}