{
  "type": "Feature",
  "properties": {
    "addr:full":"Abberdaan 206 Amsterdam Noord-Holland 1046 AB",
    "addr:housenumber":"206",
    "addr:postcode":"1046 ab",
    "addr:street":"Abberdaan",
    "iso:country":"NL",
    "sg:address":"Abberdaan 206",
    "sg:city":"Amsterdam",
    "sg:orig_category":"Kopieerapparaten",
    "sg:phone":"+31 20 614 8688",
    "sg:postcode":"1046 AB",
    "sg:province":"Noord-Holland",
    "sg:website":"http://www.canoncenter.nl",
    "wof:name":"Canon Center Pds Bv",
    "wof:placetype":"venue"
},
  "geometry": {"coordinates":[4.785508,52.39201],"type":"Point"}
}