{
  "type": "Feature",
  "properties": {
    "addr:full":"Vondellaan 74 Arnhem Gelderland 6824 NG",
    "addr:housenumber":"74",
    "addr:postcode":"6824 ng",
    "addr:street":"Vondellaan",
    "iso:country":"NL",
    "sg:address":"Vondellaan 74",
    "sg:city":"Arnhem",
    "sg:orig_category":"Overheidsdiensten",
    "sg:phone":"+31 26 361 3862",
    "sg:postcode":"6824 NG",
    "sg:province":"Gelderland",
    "wof:name":"Udi-Handbal",
    "wof:placetype":"venue"
},
  "geometry": {"coordinates":[5.9434709549,51.9978675842],"type":"Point"}
}