{
  "type": "Feature",
  "properties": {
    "iso:country":"NL",
    "sg:address":"Handelsweg 38",
    "sg:city":"Rijssen",
    "sg:orig_category":"Meubelzaken, Woning- And Keukeninrichting",
    "sg:phone":"+31 548 540 992",
    "sg:postcode":"7461 JK",
    "sg:province":"NL.08",
    "wof:name":"Hafo Meubelen Bv",
    "wof:placetype":"venue"
},
  "geometry": {"coordinates":[6.513703,52.32093],"type":"Point"}
}