{
  "type": "Feature",
  "properties": {
    "addr:full":"Handelsweg 38 Rijssen NL.08 7461 JK",
    "addr:housenumber":"38;nl.08",
    "addr:postcode":"7461 jk",
    "addr:street":"Handelsweg",
    "iso:country":"NL",
    "sg:address":"Handelsweg 38",
    "sg:city":"Rijssen",
    "sg:orig_category":"Meubelzaken, Woning- And Keukeninrichting",
    "sg:phone":"+31 548 540 992",
    "sg:postcode":"7461 JK",
    "sg:province":"NL.08",
    "wof:name":"Hafo Meubelen Bv",
    "wof:placetype":"venue"
},
  "geometry": {"coordinates":[6.513703,52.32093],"type":"Point"}
}