{
  "type": "Feature",
  "properties": {
    "addr:full":"Lansinkesweg 4 Hengelo Ov NL.08 7553 AE",
    "addr:housenumber":"4",
    "addr:postcode":"7553 ae",
    "addr:street":"Lansinkesweg;Ov",
    "iso:country":"NL",
    "sg:address":"Lansinkesweg 4",
    "sg:city":"Hengelo Ov",
    "sg:orig_category":"Onderhoud And Reparatie Kantoorapparatuur",
    "sg:phone":"+31 74 255 5770",
    "sg:postcode":"7553 AE",
    "sg:province":"NL.08",
    "wof:name":"Rti",
    "wof:placetype":"venue"
},
  "geometry": {"coordinates":[6.787897,52.261509],"type":"Point"}
}