{
  "type": "Feature",
  "properties": {
    "addr:full":"Oudekerkspln 8 Amsterdam Noord-Holland 1012 GZ",
    "addr:housenumber":"8",
    "addr:postcode":"1012 gz",
    "addr:street":"Oudekerkspln",
    "iso:country":"NL",
    "sg:address":"Oudekerkspln 8",
    "sg:city":"Amsterdam",
    "sg:orig_category":"Kinderopvang",
    "sg:phone":"+31 20 638 6575",
    "sg:postcode":"1012 GZ",
    "sg:province":"Noord-Holland",
    "wof:name":"Prinses Juliana",
    "wof:placetype":"venue"
},
  "geometry": {"coordinates":[4.898762,52.374714],"type":"Point"}
}