{
  "type": "Feature",
  "properties": {
    "addr:full":"Hoofdwg 248 Nyeholtpade Friesland 8475 CE",
    "addr:housenumber":"248",
    "addr:postcode":"8475 ce",
    "addr:street":"Nyeholtpade Friesland",
    "iso:country":"NL",
    "sg:address":"Hoofdwg 248",
    "sg:city":"Nyeholtpade",
    "sg:orig_category":"Adviesbureaus Bedrijfsorganisatie",
    "sg:phone":"+31 561 688 507",
    "sg:postcode":"8475 CE",
    "sg:province":"Friesland",
    "wof:name":"Burie",
    "wof:placetype":"venue"
},
  "geometry": {"coordinates":[6.07883,52.911011],"type":"Point"}
}