{
  "type": "Feature",
  "properties": {
    "addr:full":"Zomerdykstr 5Hs Amsterdam Noord-Holland 1079 WX",
    "addr:housenumber":"5hs",
    "addr:postcode":"1079 wx",
    "addr:street":"Zomerdykstr",
    "iso:country":"NL",
    "sg:address":"Zomerdykstr 5Hs",
    "sg:city":"Amsterdam",
    "sg:orig_category":"Acupunctuur",
    "sg:phone":"+31 20 642 4513",
    "sg:postcode":"1079 WX",
    "sg:province":"Noord-Holland",
    "wof:name":"Hoogenstrijd, W",
    "wof:placetype":"venue"
},
  "geometry": {"coordinates":[4.904505,52.342281],"type":"Point"}
}