{
  "type": "Feature",
  "properties": {
    "addr:full":"Willemstraat 50 Utrecht Utrecht 3511 RK",
    "addr:housenumber":"50",
    "addr:postcode":"3511 rk",
    "addr:street":"Willemstraat",
    "iso:country":"NL",
    "sg:address":"Willemstraat 50",
    "sg:city":"Utrecht",
    "sg:orig_category":"Meubelreparatie And -Restauratie",
    "sg:phone":"+31 30 231 1345",
    "sg:postcode":"3511 RK",
    "sg:province":"Utrecht",
    "wof:name":"Pemba",
    "wof:placetype":"venue"
},
  "geometry": {"coordinates":[5.113045,52.094563],"type":"Point"}
}