{
  "type": "Feature",
  "properties": {
    "addr:full":"Duivendrechtsekd 46 Amsterdam North Holland 1096 AH",
    "addr:housenumber":"46",
    "addr:postcode":"1096 ah",
    "addr:street":"Duivendrechtsekd",
    "iso:country":"NL",
    "sg:address":"Duivendrechtsekd 46",
    "sg:city":"Amsterdam",
    "sg:orig_category":"Fotoarchieven",
    "sg:phone":"+31 20 712 3950",
    "sg:postcode":"1096 AH",
    "sg:province":"North Holland",
    "sg:website":"http://www.studioeu.com",
    "wof:name":"Studio Eu",
    "wof:placetype":"venue"
},
  "geometry": {"coordinates":[4.930386,52.33865],"type":"Point"}
}