{
  "type": "Feature",
  "properties": {
    "addr:full":"Weerdskampweg 12 'S Hertogenbosch Noord-Brabant 5222 BA",
    "addr:housenumber":"12",
    "addr:postcode":"5222 ba",
    "addr:street":"Weerdskampweg;' S",
    "iso:country":"NL",
    "sg:address":"Weerdskampweg 12",
    "sg:city":"'S Hertogenbosch",
    "sg:orig_category":"Drukkerijen And Copyshops",
    "sg:phone":"+31 73 623 0666",
    "sg:postcode":"5222 BA",
    "sg:province":"Noord-Brabant",
    "wof:name":"Grafimedia Den Bosch",
    "wof:placetype":"venue"
},
  "geometry": {"coordinates":[5.269248,51.702415],"type":"Point"}
}