{
  "type": "Feature",
  "properties": {
    "addr:full":"De Overmaat 54 Arnhem Gelderland 6831 AJ",
    "addr:housenumber":"54",
    "addr:postcode":"6831 aj",
    "addr:street":"De Overmaat",
    "iso:country":"NL",
    "sg:address":"De Overmaat 54",
    "sg:city":"Arnhem",
    "sg:orig_category":"Grondwerken",
    "sg:phone":"+31 26 323 1231",
    "sg:postcode":"6831 AJ",
    "sg:province":"Gelderland",
    "wof:name":"Komen Bv",
    "wof:placetype":"venue"
},
  "geometry": {"coordinates":[5.883911,51.953072],"type":"Point"}
}