{
  "type": "Feature",
  "properties": {
    "addr:full":"Michelangelostraat 18 Rotterdam Zuid-Holland 3066 NM",
    "addr:housenumber":"18",
    "addr:postcode":"3066",
    "addr:street":"Michelangelostraat",
    "iso:country":"NL",
    "sg:address":"Michelangelostraat 18",
    "sg:city":"Rotterdam",
    "sg:orig_category":"Bedrijfs- And Managementsconsultants",
    "sg:phone":"+31 10 455 5527",
    "sg:postcode":"3066 NM",
    "sg:province":"Zuid-Holland",
    "wof:name":"Ave Organisatie- En Personeeladvies",
    "wof:placetype":"venue"
},
  "geometry": {"coordinates":[4.551701,51.939346],"type":"Point"}
}