{
  "type": "Feature",
  "properties": {
    "addr:full":"Manensheide 31 Klimmen Limburg 6343 CP",
    "addr:housenumber":"31",
    "addr:postcode":"6343 cp",
    "addr:street":"Manensheide",
    "iso:country":"NL",
    "sg:address":"Manensheide 31",
    "sg:city":"Klimmen",
    "sg:orig_category":"Adviesbureaus Bouwkunde",
    "sg:phone":"+31 43 459 1922",
    "sg:postcode":"6343 CP",
    "sg:province":"Limburg",
    "wof:name":"Bbm Bouwadviesburo Morshinkhof",
    "wof:placetype":"venue"
},
  "geometry": {"coordinates":[5.885637,50.871117],"type":"Point"}
}