{
  "type": "Feature",
  "properties": {
    "iso:country":"NL",
    "sg:address":"Heerewg 346",
    "sg:city":"Lisse",
    "sg:orig_category":"Ballonnen - Fabrieken En Groothandel",
    "sg:phone":"+31 252 424 283",
    "sg:postcode":"2161 CC",
    "sg:province":"South Holland",
    "sg:website":"http://www.balloonworld.nl",
    "wof:name":"Balloonworld",
    "wof:placetype":"venue"
},
  "geometry": {"coordinates":[4.546158,52.248981],"type":"Point"}
}