{
  "type": "Feature",
  "properties": {
    "iso:country":"NL",
    "sg:address":"Mathenesserdk 403",
    "sg:city":"Rotterdam",
    "sg:classifiers":[
        {
            "category":"Retail",
            "subcategory":"Auto Repair",
            "type":"Services"
        }
    ],
    "sg:phone":"+31 10 476 3795",
    "sg:postcode":"3026 GG",
    "sg:province":"Zuid-Holland",
    "sg:tags":[
        "garage"
    ],
    "wof:name":"Auto Serv Mathenesserdijk Bv",
    "wof:placetype":"venue"
},
  "geometry": {"coordinates":[4.445464,51.912727],"type":"Point"}
}