{
  "type": "Feature",
  "properties": {
    "iso:country":"NL",
    "sg:address":"Weg Achter De Es 1",
    "sg:city":"Uffelte",
    "sg:orig_category":"Antiekzaken",
    "sg:phone":"+31 521 351 222",
    "sg:postcode":"7975 PZ",
    "sg:province":"Drenthe",
    "wof:name":"R. Timmer Jr.",
    "wof:placetype":"venue"
},
  "geometry": {"coordinates":[6.290995,52.798161],"type":"Point"}
}