{
  "type": "Feature",
  "properties": {
    "iso:country":"NL",
    "sg:address":"Gasthuisstr 158",
    "sg:city":"Tegelen",
    "sg:orig_category":"Administratie- En Boekhoudkantoren",
    "sg:phone":"+31 77 326 0030",
    "sg:postcode":"5931 NW",
    "sg:province":"Limburg",
    "wof:name":"Admicon Vof",
    "wof:placetype":"venue"
},
  "geometry": {"coordinates":[6.139344,51.338902],"type":"Point"}
}