{
  "type": "Feature",
  "properties": {
    "addr:full":"Werkhovenseweg 19 Werkhoven Utrecht 3960 BE",
    "addr:housenumber":"19",
    "addr:postcode":"3960",
    "addr:street":"Werkhovenseweg",
    "iso:country":"NL",
    "sg:address":"Werkhovenseweg 19",
    "sg:city":"Werkhoven",
    "sg:orig_category":"Verhuur Audiovisuele Apparatuur",
    "sg:phone":"+31 343 551 470",
    "sg:postcode":"3960 BE",
    "sg:province":"Utrecht",
    "wof:name":"Go Produkties",
    "wof:placetype":"venue"
},
  "geometry": {"coordinates":[5.594419,51.140568],"type":"Point"}
}