{
  "type": "Feature",
  "properties": {
    "addr:full":"Plesmanstr 56 Veenendaal Utrecht 3905 KZ",
    "addr:housenumber":"56",
    "addr:postcode":"3905",
    "addr:street":"Plesmanstr",
    "iso:country":"NL",
    "sg:address":"Plesmanstr 56",
    "sg:city":"Veenendaal",
    "sg:orig_category":"Energiebesparing",
    "sg:phone":"+31 318 525 522",
    "sg:postcode":"3905 KZ",
    "sg:province":"Utrecht",
    "sg:website":"http://www.intechno.nl",
    "wof:name":"Intechno Bv",
    "wof:placetype":"venue"
},
  "geometry": {"coordinates":[5.554769,52.039608],"type":"Point"}
}