{
  "type": "Feature",
  "properties": {
    "addr:full":"Burg V Nispenstr 23 Beek En Donk Noord-Brabant 5741 GN",
    "addr:housenumber":"23",
    "addr:postcode":"5741 gn",
    "addr:street":"Burg V Nispenstr",
    "iso:country":"NL",
    "sg:address":"Burg V Nispenstr 23",
    "sg:city":"Beek En Donk",
    "sg:classifiers":[
        {
            "category":"Personal",
            "subcategory":"Nail Salon",
            "type":"Services"
        }
    ],
    "sg:phone":"+31 492 462 140",
    "sg:postcode":"5741 GN",
    "sg:province":"Noord-Brabant",
    "sg:tags":[
        "pedicure"
    ],
    "wof:name":"Zutven, J Van",
    "wof:placetype":"venue"
},
  "geometry": {"coordinates":[5.63467,51.529236],"type":"Point"}
}