{
  "type": "Feature",
  "properties": {
    "addr:full":"Molenstr 48 Bruinisse Zeeland 4311 ED",
    "addr:housenumber":"48",
    "addr:postcode":"4311 ed",
    "addr:street":"Molenstr",
    "iso:country":"NL",
    "sg:address":"Molenstr 48",
    "sg:city":"Bruinisse",
    "sg:orig_category":"Bloemen En Planten",
    "sg:phone":"+31 111 481 555",
    "sg:postcode":"4311 ED",
    "sg:province":"Zeeland",
    "wof:name":"Magnolia",
    "wof:placetype":"venue"
},
  "geometry": {"coordinates":[4.092342,51.6609],"type":"Point"}
}