{
  "type": "Feature",
  "properties": {
    "iso:country":"NL",
    "sg:address":"Chrysantstraat 165",
    "sg:city":"Nieuw Buinen",
    "sg:orig_category":"Hypotheken And Hypotheekbanken",
    "sg:phone":"+31 599 650 229",
    "sg:postcode":"9521 ES",
    "sg:province":"Drenthe",
    "wof:name":"Hypotheekadviesburo Galdermans",
    "wof:placetype":"venue"
},
  "geometry": {"coordinates":[6.948893,52.974937],"type":"Point"}
}