{
  "type": "Feature",
  "properties": {
    "iso:country":"NL",
    "sg:address":"Ploegstraat 10",
    "sg:city":"Someren",
    "sg:orig_category":"Goederenvervoer Over De Weg",
    "sg:phone":"+31 493 494 760",
    "sg:postcode":"5712 GH",
    "sg:province":"North Brabant",
    "wof:name":"H. Van Zoggel",
    "wof:placetype":"venue"
},
  "geometry": {"coordinates":[5.69842,51.351479],"type":"Point"}
}