{
  "type": "Feature",
  "properties": {
    "addr:full":"Catharijnelaan 26 Lisse Zuid-Holland 2161 CK",
    "addr:housenumber":"26",
    "addr:postcode":"2161 ck",
    "addr:street":"Catharijnelaan",
    "iso:country":"NL",
    "sg:address":"Catharijnelaan 26",
    "sg:city":"Lisse",
    "sg:orig_category":"Goederenvervoer Over De Weg",
    "sg:phone":"+31 252 219 030",
    "sg:postcode":"2161 CK",
    "sg:province":"Zuid-Holland",
    "wof:name":"C.N. Mens Transport Bv",
    "wof:placetype":"venue"
},
  "geometry": {"coordinates":[4.536349,52.24474],"type":"Point"}
}