{
  "type": "Feature",
  "properties": {
    "addr:full":"De Morinel 25 Dronten NL. 8251 HT",
    "addr:housenumber":"25",
    "addr:postcode":"8251 ht",
    "addr:street":"De Morinel;Nl.",
    "iso:country":"NL",
    "sg:address":"De Morinel 25",
    "sg:city":"Dronten",
    "sg:orig_category":"Onroerende Goederen",
    "sg:phone":"+31 321 336 680",
    "sg:postcode":"8251 HT",
    "sg:province":"NL.",
    "wof:name":"Timmerman Beheer Bv, A G",
    "wof:placetype":"venue"
},
  "geometry": {"coordinates":[5.725767,52.53196],"type":"Point"}
}