{
  "type": "Feature",
  "properties": {
    "addr:full":"Van Dissellaan 3 Bladel Noord-Brabant 5531 BP",
    "addr:housenumber":"3",
    "addr:postcode":"5531 bp",
    "addr:street":"Van Dissellaan",
    "iso:country":"NL",
    "sg:address":"Van Dissellaan 3",
    "sg:city":"Bladel",
    "sg:orig_category":"Paramedische Behandelingen",
    "sg:phone":"+31 497 381 984",
    "sg:postcode":"5531 BP",
    "sg:province":"Noord-Brabant",
    "wof:name":"Logopedist M.M. Buiter",
    "wof:placetype":"venue"
},
  "geometry": {"coordinates":[5.214625,51.368092],"type":"Point"}
}