{
  "type": "Feature",
  "properties": {
    "addr:full":"Citer 39 Soest Utrecht 3766 ZK",
    "addr:housenumber":"39",
    "addr:postcode":"3766",
    "addr:street":"Citer",
    "iso:country":"NL",
    "sg:address":"Citer 39",
    "sg:city":"Soest",
    "sg:orig_category":"Beeldende Kunstenaars",
    "sg:phone":"+31 35 601 1109",
    "sg:postcode":"3766 ZK",
    "sg:province":"Utrecht",
    "wof:name":"Ittersum, N Van",
    "wof:placetype":"venue"
},
  "geometry": {"coordinates":[5.277911,52.172276],"type":"Point"}
}