{
  "type": "Feature",
  "properties": {
    "addr:full":"De Kempenaerstraat 71 Oegstgeest Zuid-Holland 2341 GJ",
    "addr:housenumber":"71",
    "addr:postcode":"2341 gj",
    "addr:street":"De Kempenaerstraat",
    "iso:country":"NL",
    "sg:address":"De Kempenaerstraat 71",
    "sg:city":"Oegstgeest",
    "sg:orig_category":"Binnenhuisarchitecten",
    "sg:phone":"+31 71 517 4972",
    "sg:postcode":"2341 GJ",
    "sg:province":"Zuid-Holland",
    "wof:name":"At Home Interiors",
    "wof:placetype":"venue"
},
  "geometry": {"coordinates":[4.471667,52.177711],"type":"Point"}
}