{
  "type": "Feature",
  "properties": {
    "addr:full":"Hoge Hondstraat 204 Deventer Overijssel 7415 GH",
    "addr:housenumber":"204",
    "addr:postcode":"7415 gh",
    "addr:street":"Hoge Hondstraat",
    "iso:country":"NL",
    "sg:address":"Hoge Hondstraat 204",
    "sg:city":"Deventer",
    "sg:orig_category":"Drukkerijen And Copyshops",
    "sg:phone":"+31 570 631 309",
    "sg:postcode":"7415 GH",
    "sg:province":"Overijssel",
    "wof:name":"Stadsdrukkerij Deventer",
    "wof:placetype":"venue"
},
  "geometry": {"coordinates":[6.169435,52.265404],"type":"Point"}
}