{
  "type": "Feature",
  "properties": {
    "addr:full":"Tulpstr 17 Waarland North Holland 1738 CA",
    "addr:housenumber":"17",
    "addr:postcode":"1738 ca",
    "addr:street":"Tulpstr",
    "iso:country":"NL",
    "sg:address":"Tulpstr 17",
    "sg:city":"Waarland",
    "sg:orig_category":"Facilitaire Dienstverlening",
    "sg:phone":"+31 226 421 315",
    "sg:postcode":"1738 CA",
    "sg:province":"North Holland",
    "wof:name":"Bruin",
    "wof:placetype":"venue"
},
  "geometry": {"coordinates":[4.830201,52.725342],"type":"Point"}
}