{
  "type": "Feature",
  "properties": {
    "addr:full":"Iepenstraat 1-2 Almere Flevoland 1326 DB",
    "addr:housenumber":"1-2",
    "addr:postcode":"1326 db",
    "addr:street":"Iepenstraat;Flevoland",
    "iso:country":"NL",
    "sg:address":"Iepenstraat 1-2",
    "sg:city":"Almere",
    "sg:classifiers":[
        {
            "category":"Education",
            "subcategory":"Preschool",
            "type":"Public Place"
        }
    ],
    "sg:phone":"+31 36 537 9821",
    "sg:postcode":"1326 DB",
    "sg:province":"Flevoland",
    "sg:tags":[
        "kleuteronderwijs",
        "basis-"
    ],
    "wof:name":"De Hasselbraam",
    "wof:placetype":"venue"
},
  "geometry": {"coordinates":[5.248548,52.373932],"type":"Point"}
}