{
  "type": "Feature",
  "properties": {
    "addr:full":"Flevoland 24 Beverwyk NL. 1948 RH",
    "addr:housenumber":"24",
    "addr:postcode":"1948 rh",
    "addr:street":"Flevoland;Nl.",
    "iso:country":"NL",
    "sg:address":"Flevoland 24",
    "sg:city":"Beverwyk",
    "sg:orig_category":"Plaatwerk",
    "sg:phone":"+31 251 239 411",
    "sg:postcode":"1948 RH",
    "sg:province":"NL.",
    "wof:name":"Murgia",
    "wof:placetype":"venue"
},
  "geometry": {"coordinates":[5.48971,52.431648],"type":"Point"}
}