{
  "type": "Feature",
  "properties": {
    "iso:country":"NL",
    "sg:address":"Vughterstraat 162",
    "sg:city":"'S Hertogenbosch",
    "sg:orig_category":"Kunst And Kunstenaarsbenodigdheden",
    "sg:phone":"+31 73 613 3536",
    "sg:postcode":"5211 GN",
    "sg:province":"Noord-Brabant",
    "wof:name":"Kunsthandel Hendrik De Laat",
    "wof:placetype":"venue"
},
  "geometry": {"coordinates":[5.29797,51.685913],"type":"Point"}
}