{
  "type": "Feature",
  "properties": {
    "addr:full":"Buitengaats 7 Enkhuizen Noord-Holland 1602 HX",
    "addr:housenumber":"7",
    "addr:postcode":"1602 hx",
    "addr:street":"Buitengaats",
    "iso:country":"NL",
    "sg:address":"Buitengaats 7",
    "sg:city":"Enkhuizen",
    "sg:orig_category":"Vertalers",
    "sg:phone":"+31 228 321 640",
    "sg:postcode":"1602 HX",
    "sg:province":"Noord-Holland",
    "wof:name":"Lengua Viva",
    "wof:placetype":"venue"
},
  "geometry": {"coordinates":[5.27444,52.718296],"type":"Point"}
}