{
  "type": "Feature",
  "properties": {
    "addr:full":"Duurstedelaan 24 Utrecht Utrecht 3525 AR",
    "addr:housenumber":"24",
    "addr:postcode":"3525",
    "addr:street":"Duurstedelaan",
    "iso:country":"NL",
    "sg:address":"Duurstedelaan 24",
    "sg:city":"Utrecht",
    "sg:classifiers":[
        {
            "category":"Education",
            "subcategory":"Preschool",
            "type":"Public Place"
        }
    ],
    "sg:phone":"+31 30 288 0642",
    "sg:postcode":"3525 AR",
    "sg:province":"Utrecht",
    "sg:tags":[
        "kleuteronderwijs",
        "basis-"
    ],
    "wof:name":"Ariensschool",
    "wof:placetype":"venue"
},
  "geometry": {"coordinates":[5.11963,52.0634],"type":"Point"}
}