{
  "type": "Feature",
  "properties": {
    "addr:full":"Molenstr 185 Helmond Noord-Brabant 5701 KD",
    "addr:housenumber":"185",
    "addr:postcode":"5701 kd",
    "addr:street":"Molenstr",
    "iso:country":"NL",
    "sg:address":"Molenstr 185",
    "sg:city":"Helmond",
    "sg:orig_category":"Fietsen En Bromfietsen",
    "sg:phone":"+31 492 522 739",
    "sg:postcode":"5701 KD",
    "sg:province":"Noord-Brabant",
    "sg:website":"http://www.ronaldbreeman.nl",
    "wof:name":"Profile",
    "wof:placetype":"venue"
},
  "geometry": {"coordinates":[5.661862,51.478493],"type":"Point"}
}