{
  "type": "Feature",
  "properties": {
    "addr:full":"Somerenseweg 12 Heeze Noord-Brabant 5591 JW",
    "addr:housenumber":"12",
    "addr:postcode":"5591 jw",
    "addr:street":"Somerenseweg",
    "iso:country":"NL",
    "sg:address":"Somerenseweg 12",
    "sg:city":"Heeze",
    "sg:orig_category":"Goederenvervoer Over De Weg",
    "sg:phone":"+31 40 226 1214",
    "sg:postcode":"5591 JW",
    "sg:province":"Noord-Brabant",
    "wof:name":"Scheepers Vervoersbedrijf Bv",
    "wof:placetype":"venue"
},
  "geometry": {"coordinates":[5.586492,51.372807],"type":"Point"}
}