{
  "type": "Feature",
  "properties": {
    "addr:full":"Van Dijkhuizenstraat 13 Nijkerkerveen Gelderland 3864 DS",
    "addr:housenumber":"13",
    "addr:postcode":"3864 ds",
    "addr:street":"Van Dijkhuizenstraat;Gelderland",
    "iso:country":"NL",
    "sg:address":"Van Dijkhuizenstraat 13",
    "sg:city":"Nijkerkerveen",
    "sg:orig_category":"Meubelzaken, Woning- And Keukeninrichting",
    "sg:phone":"+31 33 257 1953",
    "sg:postcode":"3864 DS",
    "sg:province":"Gelderland",
    "wof:name":"Select Wonen Van Den Brandhof",
    "wof:placetype":"venue"
},
  "geometry": {"coordinates":[5.468189,52.199001],"type":"Point"}
}