{
  "type": "Feature",
  "properties": {
    "addr:full":"J Mennenstr 27 Roggel Limburg 6088 HX",
    "addr:housenumber":"27",
    "addr:postcode":"6088 hx",
    "iso:country":"NL",
    "sg:address":"J Mennenstr 27",
    "sg:city":"Roggel",
    "sg:orig_category":"Keukens",
    "sg:phone":"+31 475 491 471",
    "sg:postcode":"6088 HX",
    "sg:province":"Limburg",
    "wof:name":"Seuren, M T M",
    "wof:placetype":"venue"
},
  "geometry": {"coordinates":[5.931132,51.261719],"type":"Point"}
}