{
  "type": "Feature",
  "properties": {
    "iso:country":"NL",
    "sg:address":"Violierstr 20",
    "sg:city":"Beuningen Gld",
    "sg:orig_category":"Loodgieters",
    "sg:phone":"+31 24 677 7163",
    "sg:postcode":"6641 BB",
    "sg:province":"Gelderland",
    "wof:name":"Waloga",
    "wof:placetype":"venue"
},
  "geometry": {"coordinates":[5.776052,51.861713],"type":"Point"}
}