{
  "type": "Feature",
  "properties": {
    "addr:full":"Sportstr 36 Roermond Limburg 6042 KE",
    "addr:housenumber":"36",
    "addr:postcode":"6042 ke",
    "addr:street":"Sportstr",
    "iso:country":"NL",
    "sg:address":"Sportstr 36",
    "sg:city":"Roermond",
    "sg:orig_category":"Goudsmeden En Zilversmeden",
    "sg:phone":"+31 475 321 299",
    "sg:postcode":"6042 KE",
    "sg:province":"Limburg",
    "wof:name":"Mooren, C",
    "wof:placetype":"venue"
},
  "geometry": {"coordinates":[6.015057,51.196007],"type":"Point"}
}