{
  "type": "Feature",
  "properties": {
    "addr:full":"Burgemeester Meesstraat 28 Leerdam Zuid-Holland 4141 EJ",
    "addr:housenumber":"28",
    "addr:postcode":"4141 ej",
    "addr:street":"Burgemeester Meesstraat",
    "iso:country":"NL",
    "sg:address":"Burgemeester Meesstraat 28",
    "sg:city":"Leerdam",
    "sg:orig_category":"Verzekeringen",
    "sg:phone":"+31 345 612 635",
    "sg:postcode":"4141 EJ",
    "sg:province":"Zuid-Holland",
    "wof:name":"M. Van Meeuwen, Adm Verzekering-Financie",
    "wof:placetype":"venue"
},
  "geometry": {"coordinates":[5.099482,51.891338],"type":"Point"}
}