{
  "type": "Feature",
  "properties": {
    "addr:full":"Kaaistr 46 St Willebrord Noord-Brabant 4711 HS",
    "addr:housenumber":"46",
    "addr:postcode":"4711 hs",
    "addr:street":"Kaaistr",
    "iso:country":"NL",
    "sg:address":"Kaaistr 46",
    "sg:city":"St Willebrord",
    "sg:classifiers":[
        {
            "category":"Retail",
            "subcategory":"Auto Repair",
            "type":"Services"
        }
    ],
    "sg:phone":"+31 165 382 973",
    "sg:postcode":"4711 HS",
    "sg:province":"Noord-Brabant",
    "sg:tags":[
        "garage"
    ],
    "wof:name":"Westerink",
    "wof:placetype":"venue"
},
  "geometry": {"coordinates":[4.580679,51.547291],"type":"Point"}
}