{
  "type": "Feature",
  "properties": {
    "addr:full":"Amnesty Intern Wg 25 Dordrecht Zuid-Holland 3318 AZ",
    "addr:housenumber":"25",
    "addr:postcode":"3318 az",
    "addr:street":"Amnesty;Wg",
    "iso:country":"NL",
    "sg:address":"Amnesty Intern Wg 25",
    "sg:city":"Dordrecht",
    "sg:orig_category":"Verlichtingsartikelen - Groothandel",
    "sg:phone":"+31 78 617 2748",
    "sg:postcode":"3318 AZ",
    "sg:province":"Zuid-Holland",
    "wof:name":"Luxo Ned Bv",
    "wof:placetype":"venue"
},
  "geometry": {"coordinates":[4.676251,51.792057],"type":"Point"}
}