{
  "type": "Feature",
  "properties": {
    "addr:full":"Noordergracht 60 Enkhuizen Noord-Holland 1601 PH",
    "addr:housenumber":"60",
    "addr:postcode":"1601",
    "addr:street":"Noordergracht",
    "iso:country":"NL",
    "sg:address":"Noordergracht 60",
    "sg:city":"Enkhuizen",
    "sg:orig_category":"Krantenuitgeverijen",
    "sg:phone":"+31 228 320 327",
    "sg:postcode":"1601 PH",
    "sg:province":"Noord-Holland",
    "wof:name":"Poolster Boekproducties",
    "wof:placetype":"venue"
},
  "geometry": {"coordinates":[5.28551,52.707279],"type":"Point"}
}