{
  "type": "Feature",
  "properties": {
    "iso:country":"NL",
    "sg:address":"Singel 456",
    "sg:city":"Amsterdam",
    "sg:classifiers":[
        {
            "category":"Wholesale",
            "subcategory":"Meat",
            "type":"Manufacturing & Wholesale Goods"
        }
    ],
    "sg:phone":"+31 20 311 3646",
    "sg:postcode":"1017 AW",
    "sg:province":"North Holland",
    "sg:tags":[
        "hang-",
        "sluitwerk",
        "en"
    ],
    "sg:website":"http://www.weijntjes.nl",
    "wof:name":"Weijntjes Bv, W F",
    "wof:placetype":"venue"
},
  "geometry": {"coordinates":[4.888774,52.367474],"type":"Point"}
}