{
  "type": "Feature",
  "properties": {
    "iso:country":"NL",
    "sg:address":"Weipoortsewg 29B",
    "sg:city":"Zoeterwoude",
    "sg:orig_category":"Kaas",
    "sg:phone":"+31 71 580 3245",
    "sg:postcode":"2381 NC",
    "sg:province":"South Holland",
    "wof:name":"Captein Kaasboerderij",
    "wof:placetype":"venue"
},
  "geometry": {"coordinates":[4.5263972282,52.1220664978],"type":"Point"}
}