{
  "type": "Feature",
  "properties": {
    "addr:full":"Raamwg 19 S Gravenhage Zuid-Holland 2596 HL",
    "addr:housenumber":"19;gravenhage",
    "addr:postcode":"2596 hl",
    "addr:street":"Raamwg;S",
    "iso:country":"NL",
    "sg:address":"Raamwg 19",
    "sg:city":"S Gravenhage",
    "sg:orig_category":"Adviesbureaus",
    "sg:phone":"+31 70 427 5454",
    "sg:postcode":"2596 HL",
    "sg:province":"Zuid-Holland",
    "wof:name":"Recreatie, Sticht",
    "wof:placetype":"venue"
},
  "geometry": {"coordinates":[4.31846,52.093311],"type":"Point"}
}