{
  "type": "Feature",
  "properties": {
    "addr:full":"Verdistraat 34 Haaksbergen Overijssel 7482 TM",
    "addr:housenumber":"34",
    "addr:postcode":"7482 tm",
    "addr:street":"Verdistraat",
    "iso:country":"NL",
    "sg:address":"Verdistraat 34",
    "sg:city":"Haaksbergen",
    "sg:orig_category":"Binnenhuisarchitecten",
    "sg:phone":"+31 53 572 7731",
    "sg:postcode":"7482 TM",
    "sg:province":"Overijssel",
    "wof:name":"Resink Interieurcoordinatie",
    "wof:placetype":"venue"
},
  "geometry": {"coordinates":[6.747636,52.166264],"type":"Point"}
}