{
  "type": "Feature",
  "properties": {
    "addr:full":"Prins Bernhardlaan 10 Veenendaal Utrecht 3901 CC",
    "addr:housenumber":"10",
    "addr:postcode":"3901 cc",
    "addr:street":"Prins Bernhardlaan",
    "iso:country":"NL",
    "sg:address":"Prins Bernhardlaan 10",
    "sg:city":"Veenendaal",
    "sg:orig_category":"Kledingzaken",
    "sg:phone":"+31 318 553 212",
    "sg:postcode":"3901 CC",
    "sg:province":"Utrecht",
    "wof:name":"Leerfashion Veenendaal",
    "wof:placetype":"venue"
},
  "geometry": {"coordinates":[5.559857,52.028877],"type":"Point"}
}