{
  "type": "Feature",
  "properties": {
    "addr:full":"Omroepweg 11 Almere NL. 1324 KT",
    "addr:housenumber":"11",
    "addr:postcode":"1324 kt",
    "addr:street":"Omroepweg;Nl.",
    "iso:country":"NL",
    "sg:address":"Omroepweg 11",
    "sg:city":"Almere",
    "sg:orig_category":"Farmaceutische Industrie En Groothandel",
    "sg:phone":"+31 36 539 7411",
    "sg:postcode":"1324 KT",
    "sg:province":"NL.",
    "wof:name":"Interpharm Bv",
    "wof:placetype":"venue"
},
  "geometry": {"coordinates":[5.193106,52.356415],"type":"Point"}
}