{
  "type": "Feature",
  "properties": {
    "addr:full":"Rubenslaan 65 Utrecht Utrecht 3582 JC",
    "addr:housenumber":"65",
    "addr:postcode":"3582 jc",
    "addr:street":"Rubenslaan",
    "iso:country":"NL",
    "sg:address":"Rubenslaan 65",
    "sg:city":"Utrecht",
    "sg:orig_category":"Bloemen And Planten",
    "sg:phone":"+31 30 254 1754",
    "sg:postcode":"3582 JC",
    "sg:province":"Utrecht",
    "wof:name":"Henk`S Bloemen En Planten",
    "wof:placetype":"venue"
},
  "geometry": {"coordinates":[5.135788,52.079247],"type":"Point"}
}