{
  "type": "Feature",
  "properties": {
    "iso:country":"NL",
    "sg:address":"Van Ostadestraat 15",
    "sg:city":"Amsterdam",
    "sg:orig_category":"Loodgieterswerk, Verwarming And Sanitaire Installaties",
    "sg:phone":"+31 20 662 5027",
    "sg:postcode":"1072 SL",
    "sg:province":"Noord-Holland",
    "wof:name":"J.F. Teters & Zoon",
    "wof:placetype":"venue"
},
  "geometry": {"coordinates":[4.887555,52.351742],"type":"Point"}
}