{
  "type": "Feature",
  "properties": {
    "addr:full":"Rembrandtln 2 Veenendaal Utrecht 3904 ZK",
    "addr:housenumber":"2",
    "addr:postcode":"3904",
    "addr:street":"Rembrandtln",
    "iso:country":"NL",
    "sg:address":"Rembrandtln 2",
    "sg:city":"Veenendaal",
    "sg:orig_category":"Scholen Voor Algemeen Voortgezet Onderwijs",
    "sg:phone":"+31 318 509 900",
    "sg:postcode":"3904 ZK",
    "sg:province":"Utrecht",
    "sg:website":"http://www.rembrandt-college.nl",
    "wof:name":"Rembrandt College",
    "wof:placetype":"venue"
},
  "geometry": {"coordinates":[5.54211,52.023071],"type":"Point"}
}