{
  "type": "Feature",
  "properties": {
    "addr:full":"Wallerstr 125 Nykerk Gld Gelderland 3862 CN",
    "addr:housenumber":"125",
    "addr:postcode":"3862 cn",
    "addr:street":"Nykerk Gld Gelderland",
    "iso:country":"NL",
    "sg:address":"Wallerstr 125",
    "sg:city":"Nykerk Gld",
    "sg:orig_category":"Elektrotechnische Installatiebureaus",
    "sg:phone":"+31 33 245 2202",
    "sg:postcode":"3862 CN",
    "sg:province":"Gelderland",
    "wof:name":"Poltech",
    "wof:placetype":"venue"
},
  "geometry": {"coordinates":[5.4988307953,52.2265930176],"type":"Point"}
}