{
  "type": "Feature",
  "properties": {
    "addr:full":"Bergbosweg 17 Budel Noord-Brabant 6021 SB",
    "addr:housenumber":"17",
    "addr:postcode":"6021 sb",
    "addr:street":"Bergbosweg",
    "iso:country":"NL",
    "sg:address":"Bergbosweg 17",
    "sg:city":"Budel",
    "sg:classifiers":[
        {
            "category":"Food & Beverages",
            "subcategory":"Fruits & Vegetables",
            "type":"Retail Goods"
        }
    ],
    "sg:phone":"+31 495 493 629",
    "sg:postcode":"6021 SB",
    "sg:province":"Noord-Brabant",
    "sg:tags":[
        "groenten"
    ],
    "wof:name":"J.J. Janssen-Van Asten",
    "wof:placetype":"venue"
},
  "geometry": {"coordinates":[5.538409,51.281445],"type":"Point"}
}