{
  "type": "Feature",
  "properties": {
    "addr:full":"Hoofdstr 65 Meppel Drenthe 7941 AC",
    "addr:housenumber":"65",
    "addr:postcode":"7941 ac",
    "addr:street":"Hoofdstr",
    "iso:country":"NL",
    "sg:address":"Hoofdstr 65",
    "sg:city":"Meppel",
    "sg:orig_category":"Juweliers",
    "sg:phone":"+31 522 253 875",
    "sg:postcode":"7941 AC",
    "sg:province":"Drenthe",
    "wof:name":"Werf, H Van Der",
    "wof:placetype":"venue"
},
  "geometry": {"coordinates":[6.196295,52.699615],"type":"Point"}
}