{
  "type": "Feature",
  "properties": {
    "addr:full":"Rengerswg 5 Oenkerk Friesland 9062 EA",
    "addr:housenumber":"5",
    "addr:postcode":"9062 ea",
    "addr:street":"Rengerswg",
    "iso:country":"NL",
    "sg:address":"Rengerswg 5",
    "sg:city":"Oenkerk",
    "sg:orig_category":"Bloemen En Planten",
    "sg:phone":"+31 58 256 1925",
    "sg:postcode":"9062 EA",
    "sg:province":"Friesland",
    "wof:name":"Mantel, L P",
    "wof:placetype":"venue"
},
  "geometry": {"coordinates":[5.896455,53.248604],"type":"Point"}
}