{
  "type": "Feature",
  "properties": {
    "addr:full":"Rietheuvel 12 Werkendam North Brabant 4251 DN",
    "addr:housenumber":"12",
    "addr:postcode":"4251 dn",
    "addr:street":"Rietheuvel",
    "iso:country":"NL",
    "sg:address":"Rietheuvel 12",
    "sg:city":"Werkendam",
    "sg:orig_category":"Accountants - Administratie- Consulenten En -Kantoren",
    "sg:phone":"+31 183 503 460",
    "sg:postcode":"4251 DN",
    "sg:province":"North Brabant",
    "wof:name":"Fiege",
    "wof:placetype":"venue"
},
  "geometry": {"coordinates":[4.895317,51.808372],"type":"Point"}
}