{
  "type": "Feature",
  "properties": {
    "addr:full":"Adriaen Van Ostadestraat 9 Enschede NL.08 7545 DR",
    "addr:housenumber":"9;7545",
    "addr:street":"Adriaen Van Ostadestraat;Dr",
    "iso:country":"NL",
    "sg:address":"Adriaen Van Ostadestraat 9",
    "sg:city":"Enschede",
    "sg:orig_category":"Verhuur Audiovisuele Apparatuur",
    "sg:phone":"+31 53 430 6469",
    "sg:postcode":"7545 DR",
    "sg:province":"NL.08",
    "wof:name":"A En A Music",
    "wof:placetype":"venue"
},
  "geometry": {"coordinates":[6.859979,52.209663],"type":"Point"}
}