{
  "type": "Feature",
  "properties": {
    "addr:full":"Eikenlaan 16 Waalre Noord-Brabant 5581 HA",
    "addr:housenumber":"16",
    "addr:postcode":"5581 ha",
    "addr:street":"Eikenlaan",
    "iso:country":"NL",
    "sg:address":"Eikenlaan 16",
    "sg:city":"Waalre",
    "sg:orig_category":"Marktonderzoekbureaus",
    "sg:phone":"+31 40 221 4773",
    "sg:postcode":"5581 HA",
    "sg:province":"Noord-Brabant",
    "wof:name":"B.S.M.C.",
    "wof:placetype":"venue"
},
  "geometry": {"coordinates":[5.450814,51.38633],"type":"Point"}
}