{
  "type": "Feature",
  "properties": {
    "addr:full":"Groedehof 3 Tilburg North Brabant 5043 NC",
    "addr:housenumber":"3",
    "addr:postcode":"5043 nc",
    "addr:street":"Groedehof",
    "iso:country":"NL",
    "sg:address":"Groedehof 3",
    "sg:city":"Tilburg",
    "sg:orig_category":"Juridische Dienstverlening",
    "sg:phone":"+31 13 571 7390",
    "sg:postcode":"5043 NC",
    "sg:province":"North Brabant",
    "wof:name":"Pj Support Tilburg",
    "wof:placetype":"venue"
},
  "geometry": {"coordinates":[5.010407,51.582695],"type":"Point"}
}