{
  "type": "Feature",
  "properties": {
    "addr:full":"Morelgaarde 2 Nieuwegein Utrecht 3436 GE",
    "addr:housenumber":"2",
    "addr:postcode":"3436",
    "addr:street":"Morelgaarde",
    "iso:country":"NL",
    "sg:address":"Morelgaarde 2",
    "sg:city":"Nieuwegein",
    "sg:orig_category":"Vertaalbureaus",
    "sg:phone":"+31 30 604 0578",
    "sg:postcode":"3436 GE",
    "sg:province":"Utrecht",
    "sg:website":"http://www.giannakos.nl",
    "wof:name":"Giannakos Vertaalburo Grieks",
    "wof:placetype":"venue"
},
  "geometry": {"coordinates":[5.072478,52.033104],"type":"Point"}
}