{
  "type": "Feature",
  "properties": {
    "iso:country":"NL",
    "sg:address":"Galileistr 17",
    "sg:city":"S Gravenhage",
    "sg:orig_category":"Psychotherapeuten",
    "sg:phone":"+31 70 356 2569",
    "sg:postcode":"2561 SX",
    "sg:province":"Zuid-Holland",
    "wof:name":"Dijkshoorn, K",
    "wof:placetype":"venue"
},
  "geometry": {"coordinates":[4.27581,52.074532],"type":"Point"}
}