{
  "type": "Feature",
  "properties": {
    "addr:full":"Beneden Oosterd 160 Veendam Groningen 9645 LJ",
    "addr:housenumber":"160",
    "addr:postcode":"9645 lj",
    "addr:street":"Beneden Oosterd",
    "iso:country":"NL",
    "sg:address":"Beneden Oosterd 160",
    "sg:city":"Veendam",
    "sg:orig_category":"Levensmiddelen - Fabrieken En Groothandel",
    "sg:phone":"+31 598 614 246",
    "sg:postcode":"9645 LJ",
    "sg:province":"Groningen",
    "wof:name":"Boer, De",
    "wof:placetype":"venue"
},
  "geometry": {"coordinates":[6.889048,53.112278],"type":"Point"}
}