{
  "type": "Feature",
  "properties": {
    "iso:country":"NL",
    "sg:address":"Nijverdalsestraat 104",
    "sg:city":"Wierden",
    "sg:orig_category":"Boekhouders",
    "sg:phone":"+31 546 572 036",
    "sg:postcode":"7642 LG",
    "sg:province":"Overijssel",
    "wof:name":"Adcam Administraties",
    "wof:placetype":"venue"
},
  "geometry": {"coordinates":[6.564678,52.359562],"type":"Point"}
}