{
  "type": "Feature",
  "properties": {
    "addr:full":"Burgemeester De Zeeuwstr 4 Numansdorp Zuid-Holland 3281 AJ",
    "addr:housenumber":"4",
    "addr:postcode":"3281 aj",
    "addr:street":"Burgemeester De Zeeuwstr",
    "iso:country":"NL",
    "sg:address":"Burgemeester De Zeeuwstr 4",
    "sg:city":"Numansdorp",
    "sg:classifiers":[
        {
            "category":"Fast Food",
            "type":"Food & Drink"
        }
    ],
    "sg:phone":"+31 186 651 987",
    "sg:postcode":"3281 AJ",
    "sg:province":"Zuid-Holland",
    "sg:tags":[
        "afhaal",
        "restaurant"
    ],
    "wof:name":"Vof Cafetaria 'T Pandje",
    "wof:placetype":"venue"
},
  "geometry": {"coordinates":[4.438316,51.728989],"type":"Point"}
}