{
  "type": "Feature",
  "properties": {
    "addr:full":"Torenstr 43A Serooskerke Walch Zeeland 4353 AB",
    "addr:housenumber":"43a",
    "addr:postcode":"4353 ab",
    "addr:street":"Torenstr;Walch",
    "iso:country":"NL",
    "sg:address":"Torenstr 43A",
    "sg:city":"Serooskerke Walch",
    "sg:orig_category":"Banken",
    "sg:phone":"+31 118 593 159",
    "sg:postcode":"4353 AB",
    "sg:province":"Zeeland",
    "wof:name":"Regio Bank",
    "wof:placetype":"venue"
},
  "geometry": {"coordinates":[3.592655,51.549183],"type":"Point"}
}