{
  "type": "Feature",
  "properties": {
    "iso:country":"NL",
    "sg:address":"Roomburgerwg 3A",
    "sg:city":"Leiden",
    "sg:orig_category":"Levensmiddelen - Fabrieken En Groothandel",
    "sg:phone":"+31 71 541 1620",
    "sg:postcode":"2314 XM",
    "sg:province":"Zuid-Holland",
    "wof:name":"Kaasmerk Bv",
    "wof:placetype":"venue"
},
  "geometry": {"coordinates":[4.514322,52.154373],"type":"Point"}
}