{
  "type": "Feature",
  "properties": {
    "addr:full":"Plantsoenlaan 1 Wierden NL.08 7642 EC",
    "addr:housenumber":"1;nl.08",
    "addr:postcode":"7642 ec",
    "addr:street":"Plantsoenlaan",
    "iso:country":"NL",
    "sg:address":"Plantsoenlaan 1",
    "sg:city":"Wierden",
    "sg:orig_category":"Overheidsdiensten",
    "sg:phone":"+31 546 580 800",
    "sg:postcode":"7642 EC",
    "sg:province":"NL.08",
    "wof:name":"Gemeente Wierden",
    "wof:placetype":"venue"
},
  "geometry": {"coordinates":[6.59308815,52.3555831909],"type":"Point"}
}