{
  "type": "Feature",
  "properties": {
    "addr:full":"Hoffmanswg 12 Vriezenveen NL.08 7671 SM",
    "addr:housenumber":"12;nl.08",
    "addr:postcode":"7671 sm",
    "addr:street":"Hoffmanswg",
    "iso:country":"NL",
    "sg:address":"Hoffmanswg 12",
    "sg:city":"Vriezenveen",
    "sg:orig_category":"Pelsdieren - Fokbedrijven",
    "sg:phone":"+31 546 658 786",
    "sg:postcode":"7671 SM",
    "sg:province":"NL.08",
    "wof:name":"Meijer En Grob",
    "wof:placetype":"venue"
},
  "geometry": {"coordinates":[6.633534,52.437855],"type":"Point"}
}