{
  "type": "Feature",
  "properties": {
    "addr:full":"Kon Wilhelminaln 7 Joure Provincie Friesland 8501 KV",
    "addr:housenumber":"7",
    "addr:postcode":"8501 kv",
    "addr:street":"Kon Wilhelminaln;Provincie Friesland",
    "iso:country":"NL",
    "sg:address":"Kon Wilhelminaln 7",
    "sg:city":"Joure",
    "sg:orig_category":"Keukens",
    "sg:phone":"+31 513 411 051",
    "sg:postcode":"8501 KV",
    "sg:province":"Provincie Friesland",
    "wof:name":"Keukenland Design Bv",
    "wof:placetype":"venue"
},
  "geometry": {"coordinates":[5.806573,52.960739],"type":"Point"}
}