{
  "type": "Feature",
  "properties": {
    "addr:full":"De Rosmolen 40 Westervoort Gelderland 6932 ND",
    "addr:housenumber":"40",
    "addr:postcode":"6932 nd",
    "addr:street":"De Rosmolen;Gelderland",
    "iso:country":"NL",
    "sg:address":"De Rosmolen 40",
    "sg:city":"Westervoort",
    "sg:orig_category":"Sanitaire Artikelen",
    "sg:phone":"+31 26 311 3435",
    "sg:postcode":"6932 ND",
    "sg:province":"Gelderland",
    "wof:name":"Vink",
    "wof:placetype":"venue"
},
  "geometry": {"coordinates":[5.974813,51.943893],"type":"Point"}
}