{
  "type": "Feature",
  "properties": {
    "addr:full":"Landpoortstraat 29 Woudrichem Noord-Brabant 4285 AR",
    "addr:housenumber":"29",
    "addr:postcode":"4285",
    "addr:street":"Landpoortstraat",
    "iso:country":"NL",
    "sg:address":"Landpoortstraat 29",
    "sg:city":"Woudrichem",
    "sg:orig_category":"Maatschappelijk Werk",
    "sg:phone":"+31 183 302 931",
    "sg:postcode":"4285 AR",
    "sg:province":"Noord-Brabant",
    "wof:name":"Bprakt. V. Sociaal Pedagogische Hulp",
    "wof:placetype":"venue"
},
  "geometry": {"coordinates":[5.004702,51.81641],"type":"Point"}
}