{
  "type": "Feature",
  "properties": {
    "addr:full":"A Pauwstr 45 Wassenaar South Holland 2242 LS",
    "addr:housenumber":"45",
    "addr:postcode":"2242 ls",
    "iso:country":"NL",
    "sg:address":"A Pauwstr 45",
    "sg:city":"Wassenaar",
    "sg:orig_category":"Houtgroothandel",
    "sg:phone":"+31 70 511 9307",
    "sg:postcode":"2242 LS",
    "sg:province":"South Holland",
    "sg:website":"http://www.hillegomsehoutgroep.nl",
    "wof:name":"Eerste Wassenaarse Houthdl",
    "wof:placetype":"venue"
},
  "geometry": {"coordinates":[4.400954,52.144711],"type":"Point"}
}