{
  "type": "Feature",
  "properties": {
    "iso:country":"NL",
    "sg:address":"Middenbree 14",
    "sg:city":"Assen",
    "sg:orig_category":"Nagelstudio'S",
    "sg:phone":"+31 592 344 902",
    "sg:postcode":"9403 JM",
    "sg:province":"Drenthe",
    "wof:name":"Studio Artic",
    "wof:placetype":"venue"
},
  "geometry": {"coordinates":[6.580608,53.021164],"type":"Point"}
}