{
  "type": "Feature",
  "properties": {
    "iso:country":"NL",
    "sg:address":"Luiendk 11",
    "sg:city":"Purmerend",
    "sg:orig_category":"Psychosociale Therapeuten",
    "sg:phone":"+31 299 643 330",
    "sg:postcode":"1446 BG",
    "sg:province":"North Holland",
    "wof:name":"Lotte Rijnboutt",
    "wof:placetype":"venue"
},
  "geometry": {"coordinates":[4.985615,52.510044],"type":"Point"}
}