{
  "type": "Feature",
  "properties": {
    "iso:country":"NL",
    "sg:address":"Goudse Rijweg 13D",
    "sg:city":"Rotterdam",
    "sg:orig_category":"Wassalons",
    "sg:phone":"+31 6 18700183",
    "sg:postcode":"3061 DA",
    "sg:province":"South Holland",
    "wof:name":"Waspunt, Het",
    "wof:placetype":"venue"
},
  "geometry": {"coordinates":[4.5007967949,51.928943634],"type":"Point"}
}