{
  "type": "Feature",
  "properties": {
    "addr:full":"Gr Albrechtstr 10 Elshout North Brabant 5154 AH",
    "addr:housenumber":"10",
    "addr:postcode":"5154 ah",
    "iso:country":"NL",
    "sg:address":"Gr Albrechtstr 10",
    "sg:city":"Elshout",
    "sg:classifiers":[
        {
            "category":"Personal",
            "subcategory":"Nail Salon",
            "type":"Services"
        }
    ],
    "sg:phone":"+31 416 374 667",
    "sg:postcode":"5154 AH",
    "sg:province":"North Brabant",
    "sg:tags":[
        "pedicure"
    ],
    "wof:name":"Jonkers-Kievits, I P J C",
    "wof:placetype":"venue"
},
  "geometry": {"coordinates":[5.140089,51.700504],"type":"Point"}
}