{
  "type": "Feature",
  "properties": {
    "addr:full":"Verl Vaart Zz 43 Erica Drenthe 7887 EM",
    "addr:housenumber":"43",
    "addr:postcode":"7887 em",
    "addr:street":"Vaart Zz",
    "iso:country":"NL",
    "sg:address":"Verl Vaart Zz 43",
    "sg:city":"Erica",
    "sg:orig_category":"Administratie- En Boekhoudkantoren",
    "sg:phone":"+31 591 301 776",
    "sg:postcode":"7887 EM",
    "sg:province":"Drenthe",
    "wof:name":"Erica",
    "wof:placetype":"venue"
},
  "geometry": {"coordinates":[8.50811,51.882469],"type":"Point"}
}