{
  "type": "Feature",
  "properties": {
    "addr:full":"Museumlaan 7 Utrecht Utrecht 3581 HK",
    "addr:housenumber":"7",
    "addr:postcode":"3581 hk",
    "addr:street":"Museumlaan",
    "iso:country":"NL",
    "sg:address":"Museumlaan 7",
    "sg:city":"Utrecht",
    "sg:orig_category":"Makelaars In Onroerend Goed",
    "sg:phone":"+31 30 256 8888",
    "sg:postcode":"3581 HK",
    "sg:province":"Utrecht",
    "wof:name":"Dynamis Abc",
    "wof:placetype":"venue"
},
  "geometry": {"coordinates":[5.141094,52.094707],"type":"Point"}
}