{
  "type": "Feature",
  "properties": {
    "addr:full":"Leenderweg 183 Eindhoven Noord-Brabant 5643 AG",
    "addr:housenumber":"183",
    "addr:postcode":"5643",
    "addr:street":"Leenderweg",
    "iso:country":"NL",
    "sg:address":"Leenderweg 183",
    "sg:city":"Eindhoven",
    "sg:orig_category":"Fotostudio'S And Fotografen",
    "sg:phone":"+31 40 212 4767",
    "sg:postcode":"5643 AG",
    "sg:province":"Noord-Brabant",
    "wof:name":"Fotografie N. Van Onna",
    "wof:placetype":"venue"
},
  "geometry": {"coordinates":[5.493332,51.42379],"type":"Point"}
}