{
  "type": "Feature",
  "properties": {
    "addr:full":"Postbus 111 Voorthuizen Gelderland 3780 BC",
    "addr:housenumber":"111",
    "addr:postcode":"3780 bc",
    "addr:street":"Postbus;Gelderland",
    "iso:country":"NL",
    "sg:address":"Postbus 111",
    "sg:city":"Voorthuizen",
    "sg:classifiers":[
        {
            "category":"Wholesale",
            "subcategory":"Meat",
            "type":"Manufacturing & Wholesale Goods"
        }
    ],
    "sg:phone":"+31 342 423 420",
    "sg:postcode":"3780 BC",
    "sg:province":"Gelderland",
    "sg:tags":[
        "regeltechniek",
        "en",
        "meet-"
    ],
    "sg:website":"http://www.merconet.nl",
    "wof:name":"Merconet",
    "wof:placetype":"venue"
},
  "geometry": {"coordinates":[5.60713,52.18708],"type":"Point"}
}