{
  "type": "Feature",
  "properties": {
    "addr:full":"Moleburren 11 Workum Friesland 8711 JA",
    "addr:housenumber":"11",
    "addr:postcode":"8711 ja",
    "addr:street":"Moleburren",
    "iso:country":"NL",
    "sg:address":"Moleburren 11",
    "sg:city":"Workum",
    "sg:orig_category":"Watersportartikelen",
    "sg:phone":"+31 515 541 653",
    "sg:postcode":"8711 JA",
    "sg:province":"Friesland",
    "wof:name":"Liefde, De",
    "wof:placetype":"venue"
},
  "geometry": {"coordinates":[5.4549160004,52.9823112488],"type":"Point"}
}