{
  "type": "Feature",
  "properties": {
    "addr:full":"Fruiteniersstraat 45 Zwijndrecht Zuid-Holland 3334 KA",
    "addr:housenumber":"45",
    "addr:postcode":"3334 ka",
    "addr:street":"Fruiteniersstraat",
    "iso:country":"NL",
    "sg:address":"Fruiteniersstraat 45",
    "sg:city":"Zwijndrecht",
    "sg:orig_category":"Boekhouders",
    "sg:phone":"+31 78 610 5623",
    "sg:postcode":"3334 KA",
    "sg:province":"Zuid-Holland",
    "wof:name":"Backspace Consultancy Bv",
    "wof:placetype":"venue"
},
  "geometry": {"coordinates":[4.59391,51.812649],"type":"Point"}
}