{
  "type": "Feature",
  "properties": {
    "iso:country":"NL",
    "sg:address":"Noordervaart 99",
    "sg:city":"Stompetoren",
    "sg:orig_category":"Overheidsdiensten",
    "sg:phone":"+31 72 503 7320",
    "sg:postcode":"1841 GB",
    "sg:province":"England",
    "wof:name":"Gemeente Schermer",
    "wof:placetype":"venue"
},
  "geometry": {"coordinates":[-2.2321801186,54.3139190674],"type":"Point"}
}