{
  "type": "Feature",
  "properties": {
    "addr:full":"Stikker 9 Asten North Brabant 5721 VD",
    "addr:housenumber":"9",
    "addr:postcode":"5721 vd",
    "addr:street":"Stikker",
    "iso:country":"NL",
    "sg:address":"Stikker 9",
    "sg:city":"Asten",
    "sg:orig_category":"Papierwaren - Fabrieken En Groothandel",
    "sg:phone":"+31 493 696 964",
    "sg:postcode":"5721 VD",
    "sg:province":"North Brabant",
    "sg:website":"http://www.verhaak.nl",
    "wof:name":"Verhaak Bv",
    "wof:placetype":"venue"
},
  "geometry": {"coordinates":[5.753762,51.415546],"type":"Point"}
}