{
  "type": "Feature",
  "properties": {
    "addr:full":"N Parallelwg 1 Wierden Overijssel 7641 AW",
    "addr:housenumber":"1",
    "addr:postcode":"7641 aw",
    "addr:street":"N Parallelwg",
    "iso:country":"NL",
    "sg:address":"N Parallelwg 1",
    "sg:city":"Wierden",
    "sg:orig_category":"Oud Metaal",
    "sg:phone":"+31 546 578 280",
    "sg:postcode":"7641 AW",
    "sg:province":"Overijssel",
    "wof:name":"Meijer",
    "wof:placetype":"venue"
},
  "geometry": {"coordinates":[6.5908908844,52.3618392944],"type":"Point"}
}