{
  "type": "Feature",
  "properties": {
    "addr:full":"Emslandweg 4 Ommen Overijssel 7731 RP",
    "addr:housenumber":"4",
    "addr:postcode":"7731 rp",
    "addr:street":"Emslandweg",
    "iso:country":"NL",
    "sg:address":"Emslandweg 4",
    "sg:city":"Ommen",
    "sg:orig_category":"Pluimveehouderijen",
    "sg:phone":"+31 529 452 141",
    "sg:postcode":"7731 RP",
    "sg:province":"Overijssel",
    "wof:name":"Landb Pluimveebdr Gebr G J En Joh Kamphuis",
    "wof:placetype":"venue"
},
  "geometry": {"coordinates":[6.400618,52.536289],"type":"Point"}
}