{
  "type": "Feature",
  "properties": {
    "iso:country":"NL",
    "sg:address":"Overijsselhaven 63",
    "sg:city":"Nieuwegein",
    "sg:orig_category":"Elektrische Apparatuur Gh",
    "sg:phone":"+31 30 606 6300",
    "sg:postcode":"3433 PH",
    "sg:province":"Utrecht",
    "wof:name":"Leuze Electronic Bv",
    "wof:placetype":"venue"
},
  "geometry": {"coordinates":[5.105385,52.021015],"type":"Point"}
}