{
  "type": "Feature",
  "properties": {
    "addr:full":"Kaldenkerkerwg 4 Venlo Limburg 5913 AD",
    "addr:housenumber":"4",
    "addr:postcode":"5913 ad",
    "addr:street":"Kaldenkerkerwg",
    "iso:country":"NL",
    "sg:address":"Kaldenkerkerwg 4",
    "sg:city":"Venlo",
    "sg:orig_category":"Verzekeringen - Verzekeringskantoren",
    "sg:phone":"+31 77 354 4444",
    "sg:postcode":"5913 AD",
    "sg:province":"Limburg",
    "wof:name":"Steegh Assurantien Bv",
    "wof:placetype":"venue"
},
  "geometry": {"coordinates":[6.17356,51.364441],"type":"Point"}
}