{
  "type": "Feature",
  "properties": {
    "iso:country":"NL",
    "sg:address":"V Reenenpk 39A",
    "sg:city":"Nykerk Gld",
    "sg:orig_category":"Luchtbehandelings- Apparaten",
    "sg:phone":"+31 33 245 3983",
    "sg:postcode":"3862 CB",
    "sg:province":"Gelderland",
    "sg:website":"http://www.healthy-life.nl",
    "wof:name":"Hl Luchttechniek",
    "wof:placetype":"venue"
},
  "geometry": {"coordinates":[5.51415,52.21376],"type":"Point"}
}