{
  "type": "Feature",
  "properties": {
    "addr:full":"Luit 14 Rotterdam South Holland 3068 LR",
    "addr:housenumber":"14",
    "addr:postcode":"3068 lr",
    "addr:street":"Luit",
    "iso:country":"NL",
    "sg:address":"Luit 14",
    "sg:city":"Rotterdam",
    "sg:orig_category":"Parfum And Cosmetica Gh",
    "sg:phone":"+31 10 455 3183",
    "sg:postcode":"3068 LR",
    "sg:province":"South Holland",
    "wof:name":"Vocra (P De Vos-Cramer)",
    "wof:placetype":"venue"
},
  "geometry": {"coordinates":[4.564268,51.964874],"type":"Point"}
}