{
  "type": "Feature",
  "properties": {
    "iso:country":"NL",
    "sg:address":"Schiedamsedijk 2",
    "sg:city":"Vlaardingen",
    "sg:orig_category":"Partycatering And -Organisatie",
    "sg:phone":"+31 10 460 4100",
    "sg:postcode":"3134 KK",
    "sg:province":"Zuid-Holland",
    "wof:name":"Multicater",
    "wof:placetype":"venue"
},
  "geometry": {"coordinates":[4.362962,51.909363],"type":"Point"}
}