{
  "type": "Feature",
  "properties": {
    "addr:full":"Eemskan Nz 70 Groningen Groningen 9713 AB",
    "addr:housenumber":"70",
    "addr:postcode":"9713 ab",
    "addr:street":"Nz",
    "iso:country":"NL",
    "sg:address":"Eemskan Nz 70",
    "sg:city":"Groningen",
    "sg:orig_category":"Sportverenigingen En Ontspannings- Verenigingen",
    "sg:phone":"+31 50 314 1728",
    "sg:postcode":"9713 AB",
    "sg:province":"Groningen",
    "wof:name":"Groninger Motorbootclub",
    "wof:placetype":"venue"
},
  "geometry": {"coordinates":[6.58386,53.218544],"type":"Point"}
}