{
  "type": "Feature",
  "properties": {
    "iso:country":"NL",
    "sg:address":"J Postmesstr 12",
    "sg:city":"Maastricht",
    "sg:orig_category":"Beeldende Kunstenaars",
    "sg:phone":"+31 43 343 1389",
    "sg:postcode":"6217 NK",
    "sg:province":"Limburg",
    "wof:name":"Jonas, J H H",
    "wof:placetype":"venue"
},
  "geometry": {"coordinates":[5.67234,50.857342],"type":"Point"}
}