{
  "type": "Feature",
  "properties": {
    "addr:full":"Lobbekenstorenstraat 3 Zevenbergen Noord-Brabant 4761 DV",
    "addr:housenumber":"3",
    "addr:postcode":"4761 dv",
    "addr:street":"Lobbekenstorenstraat",
    "iso:country":"NL",
    "sg:address":"Lobbekenstorenstraat 3",
    "sg:city":"Zevenbergen",
    "sg:orig_category":"Fietshandelaren",
    "sg:phone":"+31 168 323 966",
    "sg:postcode":"4761 DV",
    "sg:province":"Noord-Brabant",
    "wof:name":"Peter V/D Kieboom Tweewielers",
    "wof:placetype":"venue"
},
  "geometry": {"coordinates":[4.605096,51.645985],"type":"Point"}
}