{
  "type": "Feature",
  "properties": {
    "addr:full":"Langestr 131A Klazienaveen Drenthe 7891 GH",
    "addr:housenumber":"131a",
    "addr:postcode":"7891 gh",
    "iso:country":"NL",
    "sg:address":"Langestr 131A",
    "sg:city":"Klazienaveen",
    "sg:orig_category":"Kappers",
    "sg:phone":"+31 591 312 584",
    "sg:postcode":"7891 GH",
    "sg:province":"Drenthe",
    "wof:name":"Chris Boerland Haarmode",
    "wof:placetype":"venue"
},
  "geometry": {"coordinates":[6.9935002327,52.7243652344],"type":"Point"}
}