{
  "type": "Feature",
  "properties": {
    "addr:full":"Dykeindenwg 7B Waspik Noord-Brabant 5165 NS",
    "addr:housenumber":"7b",
    "addr:postcode":"5165 ns",
    "addr:street":"Dykeindenwg",
    "iso:country":"NL",
    "sg:address":"Dykeindenwg 7B",
    "sg:city":"Waspik",
    "sg:orig_category":"Metaalbewerking",
    "sg:phone":"+31 416 319 844",
    "sg:postcode":"5165 NS",
    "sg:province":"Noord-Brabant",
    "wof:name":"Alphen, Van",
    "wof:placetype":"venue"
},
  "geometry": {"coordinates":[4.941908,51.696362],"type":"Point"}
}