{
  "type": "Feature",
  "properties": {
    "iso:country":"NL",
    "sg:address":"Molenstr 14",
    "sg:city":"Lochem",
    "sg:orig_category":"Pottenbakkerijen",
    "sg:phone":"+31 573 257 171",
    "sg:postcode":"7241 AE",
    "sg:province":"Gelderland",
    "wof:name":"Egbert Boonstra, Potterie",
    "wof:placetype":"venue"
},
  "geometry": {"coordinates":[6.417068,52.161751],"type":"Point"}
}