{
  "type": "Feature",
  "properties": {
    "addr:full":"Treubstraat 14 Voorschoten Zuid-Holland 2251 BV",
    "addr:housenumber":"14",
    "addr:postcode":"2251 bv",
    "addr:street":"Treubstraat",
    "iso:country":"NL",
    "sg:address":"Treubstraat 14",
    "sg:city":"Voorschoten",
    "sg:orig_category":"Verlichting And Huishoudartikelen",
    "sg:phone":"+31 71 561 4410",
    "sg:postcode":"2251 BV",
    "sg:province":"Zuid-Holland",
    "wof:name":"Glashandel Van Aken",
    "wof:placetype":"venue"
},
  "geometry": {"coordinates":[4.447294,52.125652],"type":"Point"}
}