{
  "type": "Feature",
  "properties": {
    "iso:country":"NL",
    "sg:address":"Ursulineweg 14",
    "sg:city":"Leusden",
    "sg:orig_category":"Bloemen And Planten",
    "sg:phone":"+31 33 434 7878",
    "sg:postcode":"3833 AA",
    "sg:province":"Utrecht",
    "wof:name":"Eurofleur Leusden Bv",
    "wof:placetype":"venue"
},
  "geometry": {"coordinates":[5.411299,52.141747],"type":"Point"}
}