{
  "type": "Feature",
  "properties": {
    "addr:full":"Zwaanshals 233B Rotterdam Zuid-Holland 3036 KP",
    "addr:housenumber":"233b",
    "addr:postcode":"3036 kp",
    "addr:street":"Zwaanshals",
    "iso:country":"NL",
    "sg:address":"Zwaanshals 233B",
    "sg:city":"Rotterdam",
    "sg:orig_category":"Loonbedrijven",
    "sg:phone":"+31 10 467 9481",
    "sg:postcode":"3036 KP",
    "sg:province":"Zuid-Holland",
    "wof:name":"Osi",
    "wof:placetype":"venue"
},
  "geometry": {"coordinates":[4.486205,51.93425],"type":"Point"}
}