{
  "type": "Feature",
  "properties": {
    "addr:full":"H Bosmansstr 39 Amsterdam Noord-Holland 1077 XG",
    "addr:housenumber":"39",
    "addr:postcode":"1077 xg",
    "iso:country":"NL",
    "sg:address":"H Bosmansstr 39",
    "sg:city":"Amsterdam",
    "sg:orig_category":"Organisatiebureaus",
    "sg:phone":"+31 20 675 7539",
    "sg:postcode":"1077 XG",
    "sg:province":"Noord-Holland",
    "wof:name":"Greve Van Hoorn",
    "wof:placetype":"venue"
},
  "geometry": {"coordinates":[4.8707890511,52.3423805237],"type":"Point"}
}