{
  "type": "Feature",
  "properties": {
    "iso:country":"NL",
    "sg:address":"Geerdijk 7",
    "sg:city":"Den Ham Ov",
    "sg:orig_category":"Bloemen And Planten",
    "sg:phone":"+31 546 671 960",
    "sg:postcode":"7683 SN",
    "sg:province":"NL.08",
    "wof:name":"De Kleine Kweker",
    "wof:placetype":"venue"
},
  "geometry": {"coordinates":[6.496274,52.462387],"type":"Point"}
}