{
  "type": "Feature",
  "properties": {
    "addr:full":"Olympiakade 52 Amsterdam Noord-Holland 1076 XX",
    "addr:housenumber":"52",
    "addr:postcode":"1076 xx",
    "addr:street":"Olympiakade",
    "iso:country":"NL",
    "sg:address":"Olympiakade 52",
    "sg:city":"Amsterdam",
    "sg:orig_category":"Kappers",
    "sg:phone":"+31 20 679 5373",
    "sg:postcode":"1076 XX",
    "sg:province":"Noord-Holland",
    "wof:name":"Kapsalon Majolina",
    "wof:placetype":"venue"
},
  "geometry": {"coordinates":[4.8588848114,52.3472137451],"type":"Point"}
}