{
  "type": "Feature",
  "properties": {
    "addr:full":"N Odyckstr 65 S Gravenhage Zuid-Holland 2596 AG",
    "addr:housenumber":"65;gravenhage",
    "addr:postcode":"2596",
    "addr:street":"S",
    "iso:country":"NL",
    "sg:address":"N Odyckstr 65",
    "sg:city":"S Gravenhage",
    "sg:orig_category":"Bibliotheken Weten- Schappelijke",
    "sg:phone":"+31 70 324 6596",
    "sg:postcode":"2596 AG",
    "sg:province":"Zuid-Holland",
    "wof:name":"Theosofische Ver Ned",
    "wof:placetype":"venue"
},
  "geometry": {"coordinates":[4.31846,52.093311],"type":"Point"}
}