{
  "type": "Feature",
  "properties": {
    "iso:country":"NL",
    "sg:address":"Nieuwehaven 225",
    "sg:city":"Gouda",
    "sg:orig_category":"Dumpgoederen",
    "sg:phone":"+31 182 528 097",
    "sg:postcode":"2801 CX",
    "sg:province":"Zuid-Holland",
    "wof:name":"Dumptoko",
    "wof:placetype":"venue"
},
  "geometry": {"coordinates":[4.704932,52.011765],"type":"Point"}
}