{
  "type": "Feature",
  "properties": {
    "iso:country":"NL",
    "sg:address":"Goudenregenstr 62",
    "sg:city":"Den Helder",
    "sg:orig_category":"Projectontwikkeling",
    "sg:phone":"+31 6 27333740",
    "sg:postcode":"1783 EN",
    "sg:province":"Noord-Holland",
    "wof:name":"Bob",
    "wof:placetype":"venue"
},
  "geometry": {"coordinates":[4.736121,52.9454],"type":"Point"}
}