{
  "type": "Feature",
  "properties": {
    "addr:full":"Veldzichtwg 10 Ermelo Gelderland 3851 SH",
    "addr:housenumber":"10;3851",
    "addr:postcode":"sh",
    "addr:street":"Veldzichtwg;Gelderland",
    "iso:country":"NL",
    "sg:address":"Veldzichtwg 10",
    "sg:city":"Ermelo",
    "sg:orig_category":"Elektronica - Ontwikkeling En Groothandel",
    "sg:phone":"+31 341 493 366",
    "sg:postcode":"3851 SH",
    "sg:province":"Gelderland",
    "wof:name":"Promidel Vof",
    "wof:placetype":"venue"
},
  "geometry": {"coordinates":[5.620742,52.320667],"type":"Point"}
}