{
  "type": "Feature",
  "properties": {
    "addr:full":"Piet Heinstraat 105 'S Gravenhage Zuid-Holland 2518 CE",
    "addr:housenumber":"105 '",
    "addr:postcode":"2518 ce",
    "addr:street":"Piet Heinstraat",
    "iso:country":"NL",
    "sg:address":"Piet Heinstraat 105",
    "sg:city":"'S Gravenhage",
    "sg:orig_category":"Kappers",
    "sg:phone":"+31 70 345 9187",
    "sg:postcode":"2518 CE",
    "sg:province":"Zuid-Holland",
    "wof:name":"Il Mondo",
    "wof:placetype":"venue"
},
  "geometry": {"coordinates":[4.2973251343,52.0814437866],"type":"Point"}
}