{
  "type": "Feature",
  "properties": {
    "addr:full":"Brinklaan 114 Bussum North Holland 1404 GT",
    "addr:housenumber":"114",
    "addr:postcode":"1404 gt",
    "addr:street":"Brinklaan",
    "iso:country":"NL",
    "sg:address":"Brinklaan 114",
    "sg:city":"Bussum",
    "sg:orig_category":"Binnenhuisarchitecten",
    "sg:phone":"+31 35 691 3479",
    "sg:postcode":"1404 GT",
    "sg:province":"North Holland",
    "wof:name":"Lookman Interieurs",
    "wof:placetype":"venue"
},
  "geometry": {"coordinates":[5.162625,52.272118],"type":"Point"}
}