{
  "type": "Feature",
  "properties": {
    "addr:full":"Zusterstr 29 Middelburg Zeeland 4331 KG",
    "addr:housenumber":"29",
    "addr:postcode":"4331 kg",
    "addr:street":"Zusterstr",
    "iso:country":"NL",
    "sg:address":"Zusterstr 29",
    "sg:city":"Middelburg",
    "sg:orig_category":"Kappers",
    "sg:phone":"+31 118 614 142",
    "sg:postcode":"4331 KG",
    "sg:province":"Zeeland",
    "sg:website":"http://www.cosmo.nl/",
    "wof:name":"Cosmo",
    "wof:placetype":"venue"
},
  "geometry": {"coordinates":[3.6124200821,51.4973907471],"type":"Point"}
}