{
  "type": "Feature",
  "properties": {
    "addr:full":"Nieuweweg 85 Veenendaal Utrecht 3905 LH",
    "addr:housenumber":"85",
    "addr:postcode":"3905 lh",
    "addr:street":"Nieuweweg",
    "iso:country":"NL",
    "sg:address":"Nieuweweg 85",
    "sg:city":"Veenendaal",
    "sg:orig_category":"Metaalwerken",
    "sg:phone":"+31 318 517 565",
    "sg:postcode":"3905 LH",
    "sg:province":"Utrecht",
    "wof:name":"Leppers Zonwering",
    "wof:placetype":"venue"
},
  "geometry": {"coordinates":[5.553142,52.033447],"type":"Point"}
}