{
  "type": "Feature",
  "properties": {
    "addr:full":"Grotestr 278 Drunen Noord-Brabant 5151 BS",
    "addr:housenumber":"278",
    "addr:postcode":"5151 bs",
    "iso:country":"NL",
    "sg:address":"Grotestr 278",
    "sg:city":"Drunen",
    "sg:orig_category":"Woninginrichting",
    "sg:phone":"+31 416 378 469",
    "sg:postcode":"5151 BS",
    "sg:province":"Noord-Brabant",
    "wof:name":"Michiels",
    "wof:placetype":"venue"
},
  "geometry": {"coordinates":[5.1452541351,51.6867599487],"type":"Point"}
}