{
  "type": "Feature",
  "properties": {
    "iso:country":"NL",
    "sg:address":"Echternachln 596",
    "sg:city":"Eindhoven",
    "sg:orig_category":"Verlichtingsartikelen - Groothandel",
    "sg:phone":"+31 40 248 9903",
    "sg:postcode":"5625 KJ",
    "sg:province":"Noord-Brabant",
    "wof:name":"Deta-Licht",
    "wof:placetype":"venue"
},
  "geometry": {"coordinates":[5.472049,51.475906],"type":"Point"}
}