{
  "type": "Feature",
  "properties": {
    "addr:full":"J Ramaerstr 15-3H Amsterdam Noord-Holland 1065 GB",
    "addr:housenumber":"15-3h",
    "addr:postcode":"1065 gb",
    "iso:country":"NL",
    "sg:address":"J Ramaerstr 15-3H",
    "sg:city":"Amsterdam",
    "sg:orig_category":"Vertalers",
    "sg:phone":"+31 20 615 0485",
    "sg:postcode":"1065 GB",
    "sg:province":"Noord-Holland",
    "wof:name":"Alf\u00f6ldy, M",
    "wof:placetype":"venue"
},
  "geometry": {"coordinates":[4.824972,52.356522],"type":"Point"}
}