{
  "type": "Feature",
  "properties": {
    "addr:full":"Argusvlinder 298 Breda Noord-Brabant 4814 SW",
    "addr:housenumber":"298",
    "addr:postcode":"4814 sw",
    "addr:street":"Argusvlinder",
    "iso:country":"NL",
    "sg:address":"Argusvlinder 298",
    "sg:city":"Breda",
    "sg:orig_category":"Bejaarden - Verzorgingstehuizen",
    "sg:phone":"+31 76 531 8700",
    "sg:postcode":"4814 SW",
    "sg:province":"Noord-Brabant",
    "wof:name":"Westerwiek, De",
    "wof:placetype":"venue"
},
  "geometry": {"coordinates":[4.74559,51.585918],"type":"Point"}
}