{
  "type": "Feature",
  "properties": {
    "addr:full":"Petersburg 19 Nigtevecht Utrecht 1393 PS",
    "addr:housenumber":"19",
    "addr:postcode":"1393 ps",
    "addr:street":"Petersburg",
    "iso:country":"NL",
    "sg:address":"Petersburg 19",
    "sg:city":"Nigtevecht",
    "sg:orig_category":"Administratie- En Boekhoudkantoren",
    "sg:phone":"+31 294 252 578",
    "sg:postcode":"1393 PS",
    "sg:province":"Utrecht",
    "wof:name":"Hartog, A",
    "wof:placetype":"venue"
},
  "geometry": {"coordinates":[5.030092,52.276016],"type":"Point"}
}