{
  "type": "Feature",
  "properties": {
    "iso:country":"NL",
    "sg:address":"M Heinenwg 15",
    "sg:city":"S Gravenhage",
    "sg:orig_category":"Verenigingen En Stichtingen",
    "sg:phone":"+31 70 366 8650",
    "sg:postcode":"2533 SX",
    "sg:province":"Zuid-Holland",
    "wof:name":"Kleindierenteelt, Sticht Haagse",
    "wof:placetype":"venue"
},
  "geometry": {"coordinates":[4.28581,52.05286],"type":"Point"}
}