{
  "type": "Feature",
  "properties": {
    "addr:full":"Heiligeweg 8 Amsterdam North Holland 1012 XR",
    "addr:housenumber":"8",
    "addr:postcode":"1012 xr",
    "addr:street":"Heiligeweg",
    "iso:country":"NL",
    "sg:address":"Heiligeweg 8",
    "sg:city":"Amsterdam",
    "sg:orig_category":"Opticiens",
    "sg:phone":"+31 20 623 3295",
    "sg:postcode":"1012 XR",
    "sg:province":"North Holland",
    "wof:name":"York Optiek Bv",
    "wof:placetype":"venue"
},
  "geometry": {"coordinates":[4.8914279938,52.3679351807],"type":"Point"}
}