{
  "type": "Feature",
  "properties": {
    "addr:full":"Gravin Louisesingel 1 Nieuwegein Utrecht 3434 DH",
    "addr:housenumber":"1",
    "addr:postcode":"3434 dh",
    "addr:street":"Gravin Louisesingel",
    "iso:country":"NL",
    "sg:address":"Gravin Louisesingel 1",
    "sg:city":"Nieuwegein",
    "sg:orig_category":"Boekhouders",
    "sg:phone":"+31 30 606 0417",
    "sg:postcode":"3434 DH",
    "sg:province":"Utrecht",
    "wof:name":"Administratiekantoor Verzuu",
    "wof:placetype":"venue"
},
  "geometry": {"coordinates":[5.095282,52.015503],"type":"Point"}
}