{
  "type": "Feature",
  "properties": {
    "addr:full":"Htg V Brabantpln 17 Eindhoven Noord-Brabant 5611 PE",
    "addr:housenumber":"17",
    "addr:postcode":"5611 pe",
    "addr:street":"Brabantpln",
    "iso:country":"NL",
    "sg:address":"Htg V Brabantpln 17",
    "sg:city":"Eindhoven",
    "sg:orig_category":"Artsen - Manuele Geneeskunde",
    "sg:phone":"+31 40 211 6380",
    "sg:postcode":"5611 PE",
    "sg:province":"Noord-Brabant",
    "wof:name":"Polikliniek Manuele Geneeskunde",
    "wof:placetype":"venue"
},
  "geometry": {"coordinates":[5.484105,51.434471],"type":"Point"}
}