{
  "type": "Feature",
  "properties": {
    "addr:full":"Mascagnihof 633 Tilburg North Brabant 5049 BW",
    "addr:housenumber":"633",
    "addr:postcode":"5049 bw",
    "addr:street":"Mascagnihof",
    "iso:country":"NL",
    "sg:address":"Mascagnihof 633",
    "sg:city":"Tilburg",
    "sg:orig_category":"Autorijscholen",
    "sg:phone":"+31 13 456 4011",
    "sg:postcode":"5049 BW",
    "sg:province":"North Brabant",
    "sg:website":"http://www.rijwijs.nl",
    "wof:name":"Marchand Autorijschool",
    "wof:placetype":"venue"
},
  "geometry": {"coordinates":[5.070284,51.58728],"type":"Point"}
}