{
  "type": "Feature",
  "properties": {
    "addr:full":"Kagerdreef 14 Sassenheim Zuid-Holland 2172 HK",
    "addr:housenumber":"14",
    "addr:postcode":"2172 hk",
    "addr:street":"Kagerdreef",
    "iso:country":"NL",
    "sg:address":"Kagerdreef 14",
    "sg:city":"Sassenheim",
    "sg:orig_category":"Beautyfarms And Sauna'S",
    "sg:phone":"+31 252 231 087",
    "sg:postcode":"2172 HK",
    "sg:province":"Zuid-Holland",
    "wof:name":"M Brouwer-Van Maastricht",
    "wof:placetype":"venue"
},
  "geometry": {"coordinates":[4.529222,52.219624],"type":"Point"}
}