{
  "type": "Feature",
  "properties": {
    "addr:full":"Gravin Adelalaan 2 Renkum Gelderland 6871 TX",
    "addr:housenumber":"2",
    "addr:postcode":"6871",
    "addr:street":"Adelalaan;Gelderland",
    "iso:country":"NL",
    "sg:address":"Gravin Adelalaan 2",
    "sg:city":"Renkum",
    "sg:orig_category":"Verzekeringen",
    "sg:phone":"+31 317 315 929",
    "sg:postcode":"6871 TX",
    "sg:province":"Gelderland",
    "wof:name":"Staat Assurantien",
    "wof:placetype":"venue"
},
  "geometry": {"coordinates":[5.73741,51.983349],"type":"Point"}
}