{
  "type": "Feature",
  "properties": {
    "addr:full":"Kleiwg 80 Rotterdam South Holland 3051 GV",
    "addr:housenumber":"80",
    "addr:postcode":"3051 gv",
    "addr:street":"Kleiwg",
    "iso:country":"NL",
    "sg:address":"Kleiwg 80",
    "sg:city":"Rotterdam",
    "sg:orig_category":"Onroerende Goederen",
    "sg:phone":"+31 10 422 3045",
    "sg:postcode":"3051 GV",
    "sg:province":"South Holland",
    "wof:name":"Pitlo & Van Schelven",
    "wof:placetype":"venue"
},
  "geometry": {"coordinates":[4.478382,51.945248],"type":"Point"}
}