{
  "type": "Feature",
  "properties": {
    "addr:full":"Cuyleborg 176 Maastricht Limburg 6228 BP",
    "addr:housenumber":"176",
    "addr:postcode":"6228 bp",
    "addr:street":"Cuyleborg",
    "iso:country":"NL",
    "sg:address":"Cuyleborg 176",
    "sg:city":"Maastricht",
    "sg:orig_category":"Geluidsopnamen",
    "sg:phone":"+31 43 361 8310",
    "sg:postcode":"6228 BP",
    "sg:province":"Limburg",
    "wof:name":"Southbound Dance Music",
    "wof:placetype":"venue"
},
  "geometry": {"coordinates":[5.726586,50.825584],"type":"Point"}
}