{
  "type": "Feature",
  "properties": {
    "iso:country":"NL",
    "sg:address":"Postbus 2171",
    "sg:city":"Arnhem",
    "sg:orig_category":"Meubelstoffering",
    "sg:phone":"+31 26 443 5931",
    "sg:postcode":"6802 CD",
    "sg:province":"Zuid-Holland",
    "wof:name":"Jos De Waal",
    "wof:placetype":"venue"
},
  "geometry": {"coordinates":[5.9124,51.979729],"type":"Point"}
}