{
  "type": "Feature",
  "properties": {
    "iso:country":"NL",
    "sg:address":"Verl Walstr 1",
    "sg:city":"Arnemuiden",
    "sg:orig_category":"Kunststof Ramen",
    "sg:phone":"+31 118 602 935",
    "sg:postcode":"4341 CS",
    "sg:province":"Zeeland",
    "wof:name":"Poortvliet, F P",
    "wof:placetype":"venue"
},
  "geometry": {"coordinates":[3.67512,51.499878],"type":"Point"}
}