{
  "type": "Feature",
  "properties": {
    "iso:country":"NL",
    "sg:address":"Morgenrood 1",
    "sg:city":"Tuitjenhorn",
    "sg:orig_category":"Makelaars En Adviseurs Onroerende Goederen",
    "sg:phone":"+31 226 394 139",
    "sg:postcode":"1747 EC",
    "sg:province":"Noord-Holland",
    "wof:name":"Waard, De",
    "wof:placetype":"venue"
},
  "geometry": {"coordinates":[4.754814,52.732624],"type":"Point"}
}