{
  "type": "Feature",
  "properties": {
    "addr:full":"Jan Lievenslaan 15 Hazerswoude Dorp South Holland 2391 GW",
    "addr:housenumber":"15",
    "addr:postcode":"2391 gw",
    "addr:street":"Jan Lievenslaan;Dorp",
    "iso:country":"NL",
    "sg:address":"Jan Lievenslaan 15",
    "sg:city":"Hazerswoude Dorp",
    "sg:orig_category":"Kappers",
    "sg:phone":"+31 172 589 449",
    "sg:postcode":"2391 GW",
    "sg:province":"South Holland",
    "wof:name":"Ingrid",
    "wof:placetype":"venue"
},
  "geometry": {"coordinates":[4.5788321495,52.0957107544],"type":"Point"}
}