{
  "type": "Feature",
  "properties": {
    "addr:full":"Achterbente 7 Dalen Provincie Drenthe 7751 SK",
    "addr:housenumber":"7;7751",
    "addr:street":"Achterbente;Provincie Drenthe",
    "iso:country":"NL",
    "sg:address":"Achterbente 7",
    "sg:city":"Dalen",
    "sg:classifiers":[
        {
            "category":"Retail",
            "subcategory":"Storage",
            "type":"Services"
        }
    ],
    "sg:phone":"+31 524 552 285",
    "sg:postcode":"7751 SK",
    "sg:province":"Provincie Drenthe",
    "sg:tags":[
        "opslag",
        "bewaring"
    ],
    "wof:name":"Overslagbedrijf H. Pat Bv",
    "wof:placetype":"venue"
},
  "geometry": {"coordinates":[6.7494711876,52.6890144348],"type":"Point"}
}