{
  "type": "Feature",
  "properties": {
    "iso:country":"NL",
    "sg:address":"Martin Luther Kinglaan 123",
    "sg:city":"Hellevoetsluis",
    "sg:orig_category":"Goederenvervoer Over De Weg",
    "sg:phone":"+31 181 324 388",
    "sg:postcode":"3223 GG",
    "sg:province":"Zuid-Holland",
    "wof:name":"H.J. Leenderts Nationaal & Internat.Tran",
    "wof:placetype":"venue"
},
  "geometry": {"coordinates":[4.146159,51.840488],"type":"Point"}
}