{
  "type": "Feature",
  "properties": {
    "addr:full":"Woudrichemstr 87 Arnhem Gelderland 6844 GH",
    "addr:housenumber":"87",
    "addr:postcode":"6844 gh",
    "addr:street":"Woudrichemstr",
    "iso:country":"NL",
    "sg:address":"Woudrichemstr 87",
    "sg:city":"Arnhem",
    "sg:orig_category":"Optische Instrumenten",
    "sg:phone":"+31 26 381 4152",
    "sg:postcode":"6844 GH",
    "sg:province":"Gelderland",
    "wof:name":"Opin",
    "wof:placetype":"venue"
},
  "geometry": {"coordinates":[5.8595972061,51.9495201111],"type":"Point"}
}