{
  "type": "Feature",
  "properties": {
    "addr:full":"Walstr 2 Kraggenburg NL. 8317 AP",
    "addr:housenumber":"2",
    "addr:postcode":"8317 ap",
    "addr:street":"Walstr;Nl.",
    "iso:country":"NL",
    "sg:address":"Walstr 2",
    "sg:city":"Kraggenburg",
    "sg:orig_category":"Land- En Tuinbouw - Mechanisatie",
    "sg:phone":"+31 527 252 310",
    "sg:postcode":"8317 AP",
    "sg:province":"NL.",
    "wof:name":"Weevers Kraggenburg Vof",
    "wof:placetype":"venue"
},
  "geometry": {"coordinates":[5.898563,52.66333],"type":"Point"}
}