{
  "type": "Feature",
  "properties": {
    "addr:full":"Sem Dresdenlaan 45 Hoofddorp Noord-Holland 2132 KR",
    "addr:housenumber":"45",
    "addr:postcode":"2132 kr",
    "addr:street":"Sem Dresdenlaan",
    "iso:country":"NL",
    "sg:address":"Sem Dresdenlaan 45",
    "sg:city":"Hoofddorp",
    "sg:orig_category":"Artsen And Specialisten",
    "sg:phone":"+31 23 563 4345",
    "sg:postcode":"2132 KR",
    "sg:province":"Noord-Holland",
    "wof:name":"J. Dekker",
    "wof:placetype":"venue"
},
  "geometry": {"coordinates":[4.704651,52.308281],"type":"Point"}
}