{
  "type": "Feature",
  "properties": {
    "addr:full":"Jan Van Goijenstraat 15 Papendrecht Zuid-Holland 3351 JM",
    "addr:housenumber":"15",
    "addr:postcode":"3351 jm",
    "addr:street":"Jan Van Goijenstraat",
    "iso:country":"NL",
    "sg:address":"Jan Van Goijenstraat 15",
    "sg:city":"Papendrecht",
    "sg:orig_category":"Huishoudapparatuur, Televisies And Radio'S",
    "sg:phone":"+31 78 615 5906",
    "sg:postcode":"3351 JM",
    "sg:province":"Zuid-Holland",
    "wof:name":"Van Dijk Huistechniek",
    "wof:placetype":"venue"
},
  "geometry": {"coordinates":[4.685773,51.836746],"type":"Point"}
}