{
  "type": "Feature",
  "properties": {
    "addr:full":"Kon Emmakd 82 S Gravenhage Zuid-Holland 2518 RM",
    "addr:housenumber":"82;gravenhage",
    "addr:postcode":"2518 rm",
    "addr:street":"Kon;S",
    "iso:country":"NL",
    "sg:address":"Kon Emmakd 82",
    "sg:city":"S Gravenhage",
    "sg:orig_category":"Jachthavens - Jachtwerven",
    "sg:phone":"+31 70 360 7256",
    "sg:postcode":"2518 RM",
    "sg:province":"Zuid-Holland",
    "wof:name":"Mobile Yachtservice Holl",
    "wof:placetype":"venue"
},
  "geometry": {"coordinates":[4.29348,52.080318],"type":"Point"}
}