{
  "type": "Feature",
  "properties": {
    "iso:country":"NL",
    "sg:address":"Meerpolder 1",
    "sg:city":"Zoetermeer",
    "sg:orig_category":"Verhuur Bouwmachines",
    "sg:phone":"+31 79 351 8490",
    "sg:postcode":"2717 PA",
    "sg:province":"Zuid-Holland",
    "wof:name":"J. Glijnis Loon- En Verhuurbedrijf Bv",
    "wof:placetype":"venue"
},
  "geometry": {"coordinates":[4.45673,52.077126],"type":"Point"}
}