{
  "type": "Feature",
  "properties": {
    "addr:full":"V Swaanswyckstr 36 Moerkapelle South Holland 2751 XL",
    "addr:housenumber":"36",
    "addr:postcode":"2751 xl",
    "iso:country":"NL",
    "sg:address":"V Swaanswyckstr 36",
    "sg:city":"Moerkapelle",
    "sg:orig_category":"Video - Faciliteiten En Producties",
    "sg:phone":"+31 79 593 6901",
    "sg:postcode":"2751 XL",
    "sg:province":"South Holland",
    "sg:website":"http://www.cuevision.nl",
    "wof:name":"Cue Vision",
    "wof:placetype":"venue"
},
  "geometry": {"coordinates":[4.57578,52.044224],"type":"Point"}
}