{
  "type": "Feature",
  "properties": {
    "addr:full":"V Baerlestr 110 Amsterdam North Holland 1071 BC",
    "addr:housenumber":"110",
    "addr:postcode":"1071 bc",
    "iso:country":"NL",
    "sg:address":"V Baerlestr 110",
    "sg:city":"Amsterdam",
    "sg:orig_category":"Binnenhuisarchitectuur",
    "sg:phone":"+31 20 679 1461",
    "sg:postcode":"1071 BC",
    "sg:province":"North Holland",
    "wof:name":"Hillen Bv",
    "wof:placetype":"venue"
},
  "geometry": {"coordinates":[4.87701,52.355549],"type":"Point"}
}