{
  "type": "Feature",
  "properties": {
    "addr:full":"Stationsstr 43 Deurne Noord-Brabant 5751 HB",
    "addr:housenumber":"43",
    "addr:postcode":"5751 hb",
    "addr:street":"Stationsstr",
    "iso:country":"NL",
    "sg:address":"Stationsstr 43",
    "sg:city":"Deurne",
    "sg:orig_category":"Zoetwaren - Winkels",
    "sg:phone":"+31 493 310 627",
    "sg:postcode":"5751 HB",
    "sg:province":"Noord-Brabant",
    "wof:name":"Drop-Inn",
    "wof:placetype":"venue"
},
  "geometry": {"coordinates":[5.791769,51.461491],"type":"Point"}
}