{
  "type": "Feature",
  "properties": {
    "iso:country":"NL",
    "sg:address":"Bosscheweg 61A",
    "sg:city":"Drunen",
    "sg:classifiers":[
        {
            "category":"Food & Beverages",
            "subcategory":"Fruits & Vegetables",
            "type":"Retail Goods"
        }
    ],
    "sg:phone":"+31 416 320 930",
    "sg:postcode":"5151 BB",
    "sg:province":"Noord-Brabant",
    "sg:tags":[
        "groenten"
    ],
    "wof:name":"A.H.M. Smetsers",
    "wof:placetype":"venue"
},
  "geometry": {"coordinates":[5.15421,51.68742],"type":"Point"}
}