{
  "type": "Feature",
  "properties": {
    "iso:country":"NL",
    "sg:address":"Oudlandsestr 88",
    "sg:city":"Steenbergen Nb",
    "sg:orig_category":"Juridische Adviseurs",
    "sg:phone":"+31 167 540 099",
    "sg:postcode":"4651 ME",
    "sg:province":"North Brabant",
    "wof:name":"Meulblok",
    "wof:placetype":"venue"
},
  "geometry": {"coordinates":[4.314915,51.576107],"type":"Point"}
}