{
  "type": "Feature",
  "properties": {
    "iso:country":"NL",
    "sg:address":"Industriewg 3U",
    "sg:city":"Vught",
    "sg:classifiers":[
        {
            "category":"Retail",
            "subcategory":"Auto Repair",
            "type":"Services"
        }
    ],
    "sg:phone":"+31 73 656 4411",
    "sg:postcode":"5262 GJ",
    "sg:province":"Noord-Brabant",
    "sg:tags":[
        "garage"
    ],
    "wof:name":"Vaessen, W",
    "wof:placetype":"venue"
},
  "geometry": {"coordinates":[5.291997,51.646824],"type":"Point"}
}