{
  "type": "Feature",
  "properties": {
    "addr:full":"Van Oosterwijk Bruynstr 3 'S Gravenhage South Holland 2523 XS",
    "addr:housenumber":"3 '",
    "addr:postcode":"2523 xs",
    "addr:street":"Van Oosterwijk Bruynstr",
    "iso:country":"NL",
    "sg:address":"Van Oosterwijk Bruynstr 3",
    "sg:city":"'S Gravenhage",
    "sg:orig_category":"Loodgieterswerk, Verwarming And Sanitaire Installaties",
    "sg:phone":"+31 70 393 3131",
    "sg:postcode":"2523 XS",
    "sg:province":"South Holland",
    "wof:name":"Loodgietersbedrijf H. Koestal",
    "wof:placetype":"venue"
},
  "geometry": {"coordinates":[4.3134,52.056808],"type":"Point"}
}