{
  "type": "Feature",
  "properties": {
    "addr:full":"Libel 29 Alblasserdam Zuid-Holland 2954 BC",
    "addr:housenumber":"29",
    "addr:postcode":"2954 bc",
    "addr:street":"Libel",
    "iso:country":"NL",
    "sg:address":"Libel 29",
    "sg:city":"Alblasserdam",
    "sg:orig_category":"Goederenvervoer Over De Weg",
    "sg:phone":"+31 78 691 5363",
    "sg:postcode":"2954 BC",
    "sg:province":"Zuid-Holland",
    "wof:name":"Transportbedrijf P. Monster",
    "wof:placetype":"venue"
},
  "geometry": {"coordinates":[4.656246,51.871902],"type":"Point"}
}