{
  "type": "Feature",
  "properties": {
    "addr:full":"Bruggen 36 Rosmalen Noord-Brabant 5243 RB",
    "addr:housenumber":"36",
    "addr:postcode":"5243 rb",
    "addr:street":"Bruggen",
    "iso:country":"NL",
    "sg:address":"Bruggen 36",
    "sg:city":"Rosmalen",
    "sg:orig_category":"Architecten",
    "sg:phone":"+31 73 521 3850",
    "sg:postcode":"5243 RB",
    "sg:province":"Noord-Brabant",
    "wof:name":"Architectenburo Gruben Bv",
    "wof:placetype":"venue"
},
  "geometry": {"coordinates":[5.37284,51.724182],"type":"Point"}
}