{
  "type": "Feature",
  "properties": {
    "addr:full":"D Slothouwerstr 27 Doetinchem Gelderland 7009 JS",
    "addr:housenumber":"27",
    "addr:postcode":"7009 js",
    "addr:street":"Gelderland",
    "iso:country":"NL",
    "sg:address":"D Slothouwerstr 27",
    "sg:city":"Doetinchem",
    "sg:orig_category":"Bloemen En Planten",
    "sg:phone":"+31 314 324 750",
    "sg:postcode":"7009 JS",
    "sg:province":"Gelderland",
    "wof:name":"Oase, De",
    "wof:placetype":"venue"
},
  "geometry": {"coordinates":[6.297371,51.976494],"type":"Point"}
}