{
  "type": "Feature",
  "properties": {
    "addr:full":"Meiveld 86 Veldhoven North Brabant 5501 KD",
    "addr:housenumber":"86",
    "addr:postcode":"5501 kd",
    "addr:street":"Meiveld",
    "iso:country":"NL",
    "sg:address":"Meiveld 86",
    "sg:city":"Veldhoven",
    "sg:classifiers":[
        {
            "category":"Food & Beverages",
            "subcategory":"Fruits & Vegetables",
            "type":"Retail Goods"
        }
    ],
    "sg:phone":"+31 40 254 0474",
    "sg:postcode":"5501 KD",
    "sg:province":"North Brabant",
    "sg:tags":[
        "groenten"
    ],
    "wof:name":"B. Van Gerwen Groente En Fruit",
    "wof:placetype":"venue"
},
  "geometry": {"coordinates":[5.406731,51.420143],"type":"Point"}
}