{
  "type": "Feature",
  "properties": {
    "iso:country":"NL",
    "sg:address":"Stationswg 6",
    "sg:city":"Barendrecht",
    "sg:orig_category":"Adviesbureaus Werktuigbouwkunde",
    "sg:phone":"+31 180 617 945",
    "sg:postcode":"2991 RN",
    "sg:province":"Zuid-Holland",
    "wof:name":"Alc",
    "wof:placetype":"venue"
},
  "geometry": {"coordinates":[4.54064,51.853176],"type":"Point"}
}