{
  "type": "Feature",
  "properties": {
    "addr:full":"Dunantstr 1B Tilburg Noord-Brabant 5017 KC",
    "addr:housenumber":"1b",
    "addr:postcode":"5017 kc",
    "addr:street":"Dunantstr",
    "iso:country":"NL",
    "sg:address":"Dunantstr 1B",
    "sg:city":"Tilburg",
    "sg:orig_category":"Administratie- En Boekhoudkantoren",
    "sg:phone":"+31 13 580 2000",
    "sg:postcode":"5017 KC",
    "sg:province":"Noord-Brabant",
    "wof:name":"Informa Administratie Adviesburo",
    "wof:placetype":"venue"
},
  "geometry": {"coordinates":[5.09578,51.557388],"type":"Point"}
}