{
  "type": "Feature",
  "properties": {
    "addr:full":"Provincialeweg 66 Veldhoven Noord-Brabant 5503 HH",
    "addr:housenumber":"66",
    "addr:postcode":"5503 hh",
    "addr:street":"Provincialeweg",
    "iso:country":"NL",
    "sg:address":"Provincialeweg 66",
    "sg:city":"Veldhoven",
    "sg:classifiers":[
        {
            "category":"Professional",
            "subcategory":"Accounting & Tax Preparation",
            "type":"Services"
        }
    ],
    "sg:phone":"+31 40 230 0530",
    "sg:postcode":"5503 HH",
    "sg:province":"Noord-Brabant",
    "sg:tags":[
        "accountant"
    ],
    "wof:name":"Peek Accountants & Belastingadviseurs",
    "wof:placetype":"venue"
},
  "geometry": {"coordinates":[5.416477,51.413277],"type":"Point"}
}