{
  "type": "Feature",
  "properties": {
    "addr:full":"Molenkrite 169 Sneek Friesland 8608 WD",
    "addr:housenumber":"169",
    "addr:postcode":"8608 wd",
    "addr:street":"Molenkrite",
    "iso:country":"NL",
    "sg:address":"Molenkrite 169",
    "sg:city":"Sneek",
    "sg:classifiers":[
        {
            "category":"Education",
            "subcategory":"Preschool",
            "type":"Public Place"
        }
    ],
    "sg:phone":"+31 515 411 213",
    "sg:postcode":"8608 WD",
    "sg:province":"Friesland",
    "sg:tags":[
        "kleuteronderwijs",
        "basis-"
    ],
    "wof:name":"Openbare Basisschool De Wyken",
    "wof:placetype":"venue"
},
  "geometry": {"coordinates":[5.649106,53.0214],"type":"Point"}
}