{
  "type": "Feature",
  "properties": {
    "iso:country":"NL",
    "sg:address":"Neptunusweg 30",
    "sg:city":"Leeuwarden",
    "sg:orig_category":"Verlichting And Huishoudartikelen",
    "sg:phone":"+31 58 288 2922",
    "sg:postcode":"8938 AA",
    "sg:province":"Friesland",
    "wof:name":"Bruins Visscher Licht Bv",
    "wof:placetype":"venue"
},
  "geometry": {"coordinates":[5.836873,53.19677],"type":"Point"}
}