{
  "type": "Feature",
  "properties": {
    "addr:full":"Oranje Nassaulaan 13 Vrouwenpolder Zeeland 4354 BG",
    "addr:housenumber":"13",
    "addr:postcode":"4354",
    "addr:street":"Oranje Nassaulaan",
    "iso:country":"NL",
    "sg:address":"Oranje Nassaulaan 13",
    "sg:city":"Vrouwenpolder",
    "sg:orig_category":"Kappers",
    "sg:phone":"+31 118 591 030",
    "sg:postcode":"4354 BG",
    "sg:province":"Zeeland",
    "wof:name":"G.H. Wolswijk",
    "wof:placetype":"venue"
},
  "geometry": {"coordinates":[3.6124699116,51.5762176514],"type":"Point"}
}