{
  "type": "Feature",
  "properties": {
    "addr:full":"Zaaimansakker 13 Dedemsvaart Overijssel 7701 ZJ",
    "addr:housenumber":"13",
    "addr:postcode":"7701 zj",
    "addr:street":"Zaaimansakker",
    "iso:country":"NL",
    "sg:address":"Zaaimansakker 13",
    "sg:city":"Dedemsvaart",
    "sg:orig_category":"Adviesbureaus Bedrijfsorganisatie",
    "sg:phone":"+31 523 617 097",
    "sg:postcode":"7701 ZJ",
    "sg:province":"Overijssel",
    "wof:name":"Kip, J",
    "wof:placetype":"venue"
},
  "geometry": {"coordinates":[6.461989,52.593903],"type":"Point"}
}