{
  "type": "Feature",
  "properties": {
    "iso:country":"NL",
    "sg:address":"Midstr 33",
    "sg:city":"Joure",
    "sg:orig_category":"Opticiens",
    "sg:phone":"+31 513 412 887",
    "sg:postcode":"8501 AD",
    "sg:province":"Provincie Friesland",
    "wof:name":"Huis Van Slooten, Het",
    "wof:placetype":"venue"
},
  "geometry": {"coordinates":[5.7934660912,52.9687805176],"type":"Point"}
}