{
  "type": "Feature",
  "properties": {
    "addr:full":"Spoorstr 68 Ruurlo Gelderland 7261 AG",
    "addr:housenumber":"68",
    "addr:postcode":"7261",
    "addr:street":"Spoorstr;Gelderland",
    "iso:country":"NL",
    "sg:address":"Spoorstr 68",
    "sg:city":"Ruurlo",
    "sg:orig_category":"Koel- En Vriestransporten",
    "sg:phone":"+31 573 451 749",
    "sg:postcode":"7261 AG",
    "sg:province":"Gelderland",
    "wof:name":"Donkelaar Bv, Van",
    "wof:placetype":"venue"
},
  "geometry": {"coordinates":[6.46108,52.077759],"type":"Point"}
}