{
  "type": "Feature",
  "properties": {
    "iso:country":"NL",
    "sg:address":"Deventerstr 232A",
    "sg:city":"Apeldoorn",
    "sg:orig_category":"Bloemen En Planten - Decoratie",
    "sg:phone":"+31 55 367 0373",
    "sg:postcode":"7321 DB",
    "sg:province":"Gelderland",
    "wof:name":"Julian Knol",
    "wof:placetype":"venue"
},
  "geometry": {"coordinates":[5.98915,52.214828],"type":"Point"}
}