{
  "type": "Feature",
  "properties": {
    "addr:full":"Reimersbeek 2 Amsterdam Noord-Holland 1082 AG",
    "addr:housenumber":"2",
    "addr:postcode":"1082",
    "addr:street":"Reimersbeek",
    "iso:country":"NL",
    "sg:address":"Reimersbeek 2",
    "sg:city":"Amsterdam",
    "sg:classifiers":[
        {
            "category":"Professional",
            "subcategory":"Accounting & Tax Preparation",
            "type":"Services"
        }
    ],
    "sg:phone":"+31 20 661 0234",
    "sg:postcode":"1082 AG",
    "sg:province":"Noord-Holland",
    "sg:tags":[
        "accountant",
        "en",
        "-kantoren",
        "register-"
    ],
    "wof:name":"Arenthals En Partners",
    "wof:placetype":"venue"
},
  "geometry": {"coordinates":[4.877665,52.324131],"type":"Point"}
}