{
  "type": "Feature",
  "properties": {
    "iso:country":"NL",
    "sg:address":"Burg V Nispenstr 31",
    "sg:city":"Laren Nh",
    "sg:orig_category":"Kinderopvang",
    "sg:phone":"+31 35 538 8886",
    "sg:postcode":"1251 KG",
    "sg:province":"Noord-Holland",
    "wof:name":"Pro-Kids",
    "wof:placetype":"venue"
},
  "geometry": {"coordinates":[5.22387,52.256741],"type":"Point"}
}