{
  "type": "Feature",
  "properties": {
    "addr:full":"Amsterdamsestrwg 57 Naarden Noord-Holland 1411 AX",
    "addr:housenumber":"57",
    "addr:postcode":"1411 ax",
    "addr:street":"Amsterdamsestrwg",
    "iso:country":"NL",
    "sg:address":"Amsterdamsestrwg 57",
    "sg:city":"Naarden",
    "sg:classifiers":[
        {
            "category":"Sports & Exercise",
            "subcategory":"Stables",
            "type":"Entertainment"
        }
    ],
    "sg:phone":"+31 35 694 5406",
    "sg:postcode":"1411 AX",
    "sg:province":"Noord-Holland",
    "sg:tags":[
        "maneges"
    ],
    "wof:name":"Pronk",
    "wof:placetype":"venue"
},
  "geometry": {"coordinates":[5.132325,52.307926],"type":"Point"}
}