{
  "type": "Feature",
  "properties": {
    "addr:full":"Kepplerstraat 58 Zaandam North Holland 1501 XM",
    "addr:housenumber":"58",
    "addr:postcode":"1501 xm",
    "addr:street":"Kepplerstraat",
    "iso:country":"NL",
    "sg:address":"Kepplerstraat 58",
    "sg:city":"Zaandam",
    "sg:orig_category":"Kappers",
    "sg:phone":"+31 75 631 3184",
    "sg:postcode":"1501 XM",
    "sg:province":"North Holland",
    "wof:name":"Blitsers Kinderkapsalon",
    "wof:placetype":"venue"
},
  "geometry": {"coordinates":[4.8358111382,52.4383430481],"type":"Point"}
}