{
  "type": "Feature",
  "properties": {
    "addr:full":"Jacob Van Rijsoordstraat 5 Rhoon Zuid-Holland 3161 XC",
    "addr:housenumber":"5",
    "addr:postcode":"3161 xc",
    "addr:street":"Jacob Van Rijsoordstraat",
    "iso:country":"NL",
    "sg:address":"Jacob Van Rijsoordstraat 5",
    "sg:city":"Rhoon",
    "sg:orig_category":"Bedrijfs- And Managementsconsultants",
    "sg:phone":"+31 10 501 4476",
    "sg:postcode":"3161 XC",
    "sg:province":"Zuid-Holland",
    "wof:name":"Polder Safety And Consultancy Vof",
    "wof:placetype":"venue"
},
  "geometry": {"coordinates":[4.418965,51.854725],"type":"Point"}
}