{
  "type": "Feature",
  "properties": {
    "addr:full":"De Ronge 2 Heiloo Noord-Holland 1852 XA",
    "addr:housenumber":"2",
    "addr:postcode":"1852 xa",
    "addr:street":"De Ronge",
    "iso:country":"NL",
    "sg:address":"De Ronge 2",
    "sg:city":"Heiloo",
    "sg:orig_category":"Kasregisters",
    "sg:phone":"+31 72 533 3025",
    "sg:postcode":"1852 XA",
    "sg:province":"Noord-Holland",
    "wof:name":"Abbo & Zn, J J",
    "wof:placetype":"venue"
},
  "geometry": {"coordinates":[4.682919,52.600475],"type":"Point"}
}