{
  "type": "Feature",
  "properties": {
    "addr:full":"Pastorietuin 7 Harkstede Groningen 9617 ED",
    "addr:housenumber":"7",
    "addr:postcode":"9617 ed",
    "addr:street":"Pastorietuin",
    "iso:country":"NL",
    "sg:address":"Pastorietuin 7",
    "sg:city":"Harkstede",
    "sg:orig_category":"Adviesbureaus Bedrijfsorganisatie",
    "sg:phone":"+31 50 404 1929",
    "sg:postcode":"9617 ED",
    "sg:province":"Groningen",
    "wof:name":"Pbb",
    "wof:placetype":"venue"
},
  "geometry": {"coordinates":[6.69389,53.212566],"type":"Point"}
}