{
  "type": "Feature",
  "properties": {
    "iso:country":"NL",
    "sg:address":"Wassenaarstraat 61",
    "sg:city":"Bergen Op Zoom",
    "sg:orig_category":"Juridische Dienstverlening",
    "sg:phone":"+31 164 250 250",
    "sg:postcode":"4611 BT",
    "sg:province":"Noord-Brabant",
    "wof:name":"Buro Voor Rechtshulp",
    "wof:placetype":"venue"
},
  "geometry": {"coordinates":[4.291674,51.492931],"type":"Point"}
}