{
  "type": "Feature",
  "properties": {
    "iso:country":"NL",
    "sg:address":"Handelsterrein 28",
    "sg:city":"Oude-Tonge",
    "sg:orig_category":"Kampeerterreinen",
    "sg:phone":"+31 187 641 550",
    "sg:postcode":"3255 LD",
    "sg:province":"South Holland",
    "wof:name":"Camping Oude Tonge",
    "wof:placetype":"venue"
},
  "geometry": {"coordinates":[4.213944912,51.6912002563],"type":"Point"}
}