{
  "type": "Feature",
  "properties": {
    "addr:full":"Twikkelstr 45 Breda Noord-Brabant 4834 LL",
    "addr:housenumber":"45",
    "addr:postcode":"4834 ll",
    "addr:street":"Twikkelstr",
    "iso:country":"NL",
    "sg:address":"Twikkelstr 45",
    "sg:city":"Breda",
    "sg:orig_category":"Wijnkoperijen En -Groothandel",
    "sg:phone":"+31 76 543 0036",
    "sg:postcode":"4834 LL",
    "sg:province":"Noord-Brabant",
    "wof:name":"Persistance, La",
    "wof:placetype":"venue"
},
  "geometry": {"coordinates":[4.8097438812,51.5716171265],"type":"Point"}
}