{
  "type": "Feature",
  "properties": {
    "iso:country":"NL",
    "sg:address":"Adamshofstraat 24",
    "sg:city":"Rotterdam",
    "sg:orig_category":"Watersport-, Sport- And Kampeerbenodigdheden Verhuur",
    "sg:phone":"+31 10 413 9171",
    "sg:postcode":"3061 ZE",
    "sg:province":"South Holland",
    "wof:name":"Aphrodite Sailing",
    "wof:placetype":"venue"
},
  "geometry": {"coordinates":[4.5117211342,51.9261817932],"type":"Point"}
}