{
  "type": "Feature",
  "properties": {
    "addr:full":"Kantenbeemd 28 Breda Noord-Brabant 4824 NB",
    "addr:housenumber":"28",
    "addr:postcode":"4824 nb",
    "addr:street":"Kantenbeemd",
    "iso:country":"NL",
    "sg:address":"Kantenbeemd 28",
    "sg:city":"Breda",
    "sg:orig_category":"Modevakscholen",
    "sg:phone":"+31 76 543 9761",
    "sg:postcode":"4824 NB",
    "sg:province":"Noord-Brabant",
    "wof:name":"D-Kid-Original",
    "wof:placetype":"venue"
},
  "geometry": {"coordinates":[4.741321,51.605408],"type":"Point"}
}