{
  "type": "Feature",
  "properties": {
    "iso:country":"NL",
    "sg:address":"Kanaaldk N 175",
    "sg:city":"Eindhoven",
    "sg:orig_category":"Betonmortel",
    "sg:phone":"+31 40 281 1711",
    "sg:postcode":"5642 JB",
    "sg:province":"Noord-Brabant",
    "wof:name":"Betonmortelcentrale Eindhoven Bv",
    "wof:placetype":"venue"
},
  "geometry": {"coordinates":[5.522946,51.433388],"type":"Point"}
}