{
  "type": "Feature",
  "properties": {
    "addr:full":"Lijnbaan 132 Rotterdam Zuid-Holland 3012 ER",
    "addr:housenumber":"132",
    "addr:postcode":"3012 er",
    "addr:street":"Lijnbaan",
    "iso:country":"NL",
    "sg:address":"Lijnbaan 132",
    "sg:city":"Rotterdam",
    "sg:orig_category":"Damesmodezaken",
    "sg:phone":"+31 10 414 0650",
    "sg:postcode":"3012 ER",
    "sg:province":"Zuid-Holland",
    "wof:name":"Boetiek Lipstick",
    "wof:placetype":"venue"
},
  "geometry": {"coordinates":[4.478168,51.918919],"type":"Point"}
}