{
  "type": "Feature",
  "properties": {
    "iso:country":"NL",
    "sg:address":"A Cuypstr 2B",
    "sg:city":"Arnhem",
    "sg:orig_category":"Haptotherapeuten",
    "sg:phone":"+31 26 445 7982",
    "sg:postcode":"6814 LD",
    "sg:province":"Gelderland",
    "wof:name":"Leeuwe, M E L Van",
    "wof:placetype":"venue"
},
  "geometry": {"coordinates":[5.889676,51.994461],"type":"Point"}
}