{
  "type": "Feature",
  "properties": {
    "addr:full":"Dorpsweg 121 Schellinkhout Noord-Holland 1697 KH",
    "addr:housenumber":"121",
    "addr:postcode":"1697 kh",
    "addr:street":"Dorpsweg",
    "iso:country":"NL",
    "sg:address":"Dorpsweg 121",
    "sg:city":"Schellinkhout",
    "sg:orig_category":"Huishoudelijk Textiel Fab",
    "sg:phone":"+31 229 503 169",
    "sg:postcode":"1697 KH",
    "sg:province":"Noord-Holland",
    "wof:name":"Dons Farm Nrd-H",
    "wof:placetype":"venue"
},
  "geometry": {"coordinates":[5.123824,52.632721],"type":"Point"}
}