{
  "type": "Feature",
  "properties": {
    "addr:full":"Dorpsstr 72C De Wyk Drenthe 7957 AW",
    "addr:housenumber":"72c",
    "addr:postcode":"7957 aw",
    "addr:street":"Dorpsstr;De Wyk",
    "iso:country":"NL",
    "sg:address":"Dorpsstr 72C",
    "sg:city":"De Wyk",
    "sg:orig_category":"Kappers",
    "sg:phone":"+31 522 442 784",
    "sg:postcode":"7957 AW",
    "sg:province":"Drenthe",
    "wof:name":"Trendline",
    "wof:placetype":"venue"
},
  "geometry": {"coordinates":[6.286781,52.672256],"type":"Point"}
}