{
  "type": "Feature",
  "properties": {
    "addr:full":"Kolstraat 17 Herwijnen Gelderland 4171 CX",
    "addr:housenumber":"17",
    "addr:postcode":"4171 cx",
    "addr:street":"Kolstraat;Gelderland",
    "iso:country":"NL",
    "sg:address":"Kolstraat 17",
    "sg:city":"Herwijnen",
    "sg:orig_category":"Kunst And Kunstenaarsbenodigdheden",
    "sg:phone":"+31 418 582 066",
    "sg:postcode":"4171 CX",
    "sg:province":"Gelderland",
    "wof:name":"Lijstenmakerij Van Horssen",
    "wof:placetype":"venue"
},
  "geometry": {"coordinates":[5.131147,51.826473],"type":"Point"}
}