{
  "type": "Feature",
  "properties": {
    "addr:full":"Doorndistel 22 Klazienaveen Drenthe 7891 WT",
    "addr:housenumber":"22",
    "addr:postcode":"7891 wt",
    "addr:street":"Doorndistel",
    "iso:country":"NL",
    "sg:address":"Doorndistel 22",
    "sg:city":"Klazienaveen",
    "sg:orig_category":"Betonwerken",
    "sg:phone":"+31 591 317 371",
    "sg:postcode":"7891 WT",
    "sg:province":"Drenthe",
    "wof:name":"Schwieters, P J",
    "wof:placetype":"venue"
},
  "geometry": {"coordinates":[6.97713,52.732437],"type":"Point"}
}