{
  "type": "Feature",
  "properties": {
    "iso:country":"NL",
    "sg:address":"Doorndistel 22",
    "sg:city":"Klazienaveen",
    "sg:orig_category":"Betonwerken",
    "sg:phone":"+31 591 317 371",
    "sg:postcode":"7891 WT",
    "sg:province":"Drenthe",
    "wof:name":"Schwieters, P J",
    "wof:placetype":"venue"
},
  "geometry": {"coordinates":[6.97713,52.732437],"type":"Point"}
}