{
  "type": "Feature",
  "properties": {
    "addr:full":"Edisonstraat 137 Heerlen Limburg 6412 TS",
    "addr:housenumber":"137",
    "addr:postcode":"6412 ts",
    "addr:street":"Edisonstraat",
    "iso:country":"NL",
    "sg:address":"Edisonstraat 137",
    "sg:city":"Heerlen",
    "sg:orig_category":"Boekhouders",
    "sg:phone":"+31 45 572 2995",
    "sg:postcode":"6412 TS",
    "sg:province":"Limburg",
    "wof:name":"Administratiekantoor M Rijpkema",
    "wof:placetype":"venue"
},
  "geometry": {"coordinates":[5.973352,50.899799],"type":"Point"}
}