{
  "type": "Feature",
  "properties": {
    "addr:full":"Gassedonkln 14 S Hertogenbosch Noord-Brabant 5223 XT",
    "addr:housenumber":"14",
    "addr:postcode":"5223 xt",
    "addr:street":"Gassedonkln;S",
    "iso:country":"NL",
    "sg:address":"Gassedonkln 14",
    "sg:city":"S Hertogenbosch",
    "sg:orig_category":"Schilders",
    "sg:phone":"+31 73 622 0069",
    "sg:postcode":"5223 XT",
    "sg:province":"Noord-Brabant",
    "wof:name":"Daibenle",
    "wof:placetype":"venue"
},
  "geometry": {"coordinates":[5.28148,51.687405],"type":"Point"}
}