{
  "type": "Feature",
  "properties": {
    "iso:country":"NL",
    "sg:address":"Rulstraat 20",
    "sg:city":"Oosterhout Nb",
    "sg:orig_category":"Kappers",
    "sg:phone":"+31 162 425 660",
    "sg:postcode":"4901 LN",
    "sg:province":"Noord-Brabant",
    "wof:name":"Coiffure Helmut Fleischacker",
    "wof:placetype":"venue"
},
  "geometry": {"coordinates":[4.8562870026,51.6454162598],"type":"Point"}
}