{
  "type": "Feature",
  "properties": {
    "addr:full":"Plein 1953 29 Rotterdam South Holland 3086 ED",
    "addr:housenumber":"29",
    "addr:postcode":"3086 ed",
    "addr:street":"Plein 1953",
    "iso:country":"NL",
    "sg:address":"Plein 1953 29",
    "sg:city":"Rotterdam",
    "sg:orig_category":"Kappers",
    "sg:phone":"+31 10 480 2655",
    "sg:postcode":"3086 ED",
    "sg:province":"South Holland",
    "wof:name":"Marvelous",
    "wof:placetype":"venue"
},
  "geometry": {"coordinates":[4.468032,51.87447],"type":"Point"}
}