{
  "type": "Feature",
  "properties": {
    "addr:full":"Kapittellaan 99 Maastricht Limburg 6229 TT",
    "addr:housenumber":"99",
    "addr:postcode":"6229 tt",
    "addr:street":"Kapittellaan",
    "iso:country":"NL",
    "sg:address":"Kapittellaan 99",
    "sg:city":"Maastricht",
    "sg:orig_category":"Parfum And Cosmetica Gh",
    "sg:phone":"+31 43 361 3982",
    "sg:postcode":"6229 TT",
    "sg:province":"Limburg",
    "wof:name":"Humblet Cosmetics",
    "wof:placetype":"venue"
},
  "geometry": {"coordinates":[5.708541,50.828659],"type":"Point"}
}