{
  "type": "Feature",
  "properties": {
    "addr:full":"Kruisstraat 41 Stein Lb Limburg 6171 GC",
    "addr:housenumber":"41",
    "addr:postcode":"lb;6171 gc",
    "addr:street":"Kruisstraat",
    "iso:country":"NL",
    "sg:address":"Kruisstraat 41",
    "sg:city":"Stein Lb",
    "sg:orig_category":"Opticiens",
    "sg:phone":"+31 46 433 5062",
    "sg:postcode":"6171 GC",
    "sg:province":"Limburg",
    "wof:name":"Peter Vossen Brillen Contactlenzen",
    "wof:placetype":"venue"
},
  "geometry": {"coordinates":[5.7598209381,50.9691734314],"type":"Point"}
}