{
  "type": "Feature",
  "properties": {
    "iso:country":"NL",
    "sg:address":"Hanendorperweg 310",
    "sg:city":"Emst",
    "sg:orig_category":"Kampeerterreinen",
    "sg:phone":"+31 578 661 306",
    "sg:postcode":"8166 JJ",
    "sg:province":"Gelderland",
    "wof:name":"De Bonte Vlucht",
    "wof:placetype":"venue"
},
  "geometry": {"coordinates":[5.9178352356,52.311958313],"type":"Point"}
}