{
  "type": "Feature",
  "properties": {
    "addr:full":"Steenstraat 80 Arnhem Gelderland 6828 CN",
    "addr:housenumber":"80",
    "addr:postcode":"6828 cn",
    "addr:street":"Steenstraat",
    "iso:country":"NL",
    "sg:address":"Steenstraat 80",
    "sg:city":"Arnhem",
    "sg:classifiers":[
        {
            "category":"Food & Beverages",
            "subcategory":"Fruits & Vegetables",
            "type":"Retail Goods"
        }
    ],
    "sg:phone":"+31 26 442 2703",
    "sg:postcode":"6828 CN",
    "sg:province":"Gelderland",
    "sg:tags":[
        "groenten"
    ],
    "wof:name":"Vof Derkzen",
    "wof:placetype":"venue"
},
  "geometry": {"coordinates":[5.919143,51.98423],"type":"Point"}
}