{
  "type": "Feature",
  "properties": {
    "addr:full":"Terheydensewg 122 Breda North Brabant 4816 AB",
    "addr:housenumber":"122",
    "addr:postcode":"4816 ab",
    "iso:country":"NL",
    "sg:address":"Terheydensewg 122",
    "sg:city":"Breda",
    "sg:orig_category":"Houtgroothandel Hardhout",
    "sg:phone":"+31 76 587 3650",
    "sg:postcode":"4816 AB",
    "sg:province":"North Brabant",
    "wof:name":"Cantrijn Bv",
    "wof:placetype":"venue"
},
  "geometry": {"coordinates":[4.77845,51.601395],"type":"Point"}
}