{
  "type": "Feature",
  "properties": {
    "addr:full":"Beukenln 8D Reusel Noord-Brabant 5541 VL",
    "addr:housenumber":"8d",
    "addr:postcode":"5541 vl",
    "iso:country":"NL",
    "sg:address":"Beukenln 8D",
    "sg:city":"Reusel",
    "sg:orig_category":"Horeca-Inrichtingen En -Uitrustingen",
    "sg:phone":"+31 497 641 393",
    "sg:postcode":"5541 VL",
    "sg:province":"Noord-Brabant",
    "wof:name":"Laureijs Machinehandel Bv",
    "wof:placetype":"venue"
},
  "geometry": {"coordinates":[5.168901,51.362892],"type":"Point"}
}