{
  "type": "Feature",
  "properties": {
    "iso:country":"NL",
    "sg:address":"Haringbuiswg 31",
    "sg:city":"Vlaardingen",
    "sg:orig_category":"Artsen - Huisartsen",
    "sg:phone":"+31 10 434 0403",
    "sg:postcode":"3133 KP",
    "sg:province":"Zuid-Holland",
    "wof:name":"Huisartsendienst",
    "wof:placetype":"venue"
},
  "geometry": {"coordinates":[4.311704,51.898514],"type":"Point"}
}