{
  "type": "Feature",
  "properties": {
    "addr:full":"Waterstr 23 Beneden Leeuwen Gelderland 6658 AA",
    "addr:housenumber":"23",
    "addr:postcode":"6658 aa",
    "addr:street":"Waterstr",
    "iso:country":"NL",
    "sg:address":"Waterstr 23",
    "sg:city":"Beneden Leeuwen",
    "sg:orig_category":"Meubelen - Fabrieken En Groothandel",
    "sg:phone":"+31 487 594 657",
    "sg:postcode":"6658 AA",
    "sg:province":"Gelderland",
    "wof:name":"Os, Van",
    "wof:placetype":"venue"
},
  "geometry": {"coordinates":[5.53422,51.88657],"type":"Point"}
}