{
  "type": "Feature",
  "properties": {
    "addr:full":"Kernweg 41 Hoorn Nh North Holland 1627 LH",
    "addr:housenumber":"41",
    "addr:postcode":"1627 lh",
    "addr:street":"Kernweg;Nh North",
    "iso:country":"NL",
    "sg:address":"Kernweg 41",
    "sg:city":"Hoorn Nh",
    "sg:orig_category":"Verhuur Bouwmachines",
    "sg:phone":"+31 229 210 617",
    "sg:postcode":"1627 LH",
    "sg:province":"North Holland",
    "wof:name":"Aannemingsbedrijf Snijder Bv",
    "wof:placetype":"venue"
},
  "geometry": {"coordinates":[5.101719,52.636189],"type":"Point"}
}