{
  "type": "Feature",
  "properties": {
    "addr:full":"Wagnerlaan 7 Waalre Noord-Brabant 5583 ZE",
    "addr:housenumber":"7",
    "addr:postcode":"5583 ze",
    "addr:street":"Wagnerlaan",
    "iso:country":"NL",
    "sg:address":"Wagnerlaan 7",
    "sg:city":"Waalre",
    "sg:orig_category":"Schoenen",
    "sg:phone":"+31 40 246 4089",
    "sg:postcode":"5583 ZE",
    "sg:province":"Noord-Brabant",
    "wof:name":"Andre Eliens Bv",
    "wof:placetype":"venue"
},
  "geometry": {"coordinates":[5.491425,51.392738],"type":"Point"}
}