{
  "type": "Feature",
  "properties": {
    "addr:full":"Groot Hertoginnelaan 92 'S Gravenhage Zuid-Holland 2517 EK",
    "addr:housenumber":"92",
    "addr:postcode":"2517 ek",
    "addr:street":"Groot Hertoginnelaan;' S",
    "iso:country":"NL",
    "sg:address":"Groot Hertoginnelaan 92",
    "sg:city":"'S Gravenhage",
    "sg:orig_category":"Grafologen, Handlezers And Helderzienden",
    "sg:phone":"+31 70 362 5889",
    "sg:postcode":"2517 EK",
    "sg:province":"Zuid-Holland",
    "wof:name":"Ciska En Raymond",
    "wof:placetype":"venue"
},
  "geometry": {"coordinates":[4.281959,52.084503],"type":"Point"}
}