{
  "type": "Feature",
  "properties": {
    "addr:full":"Burgemeester Falkenaweg 58 Heerenveen Friesland 8442 LE",
    "addr:housenumber":"58",
    "addr:postcode":"8442 le",
    "addr:street":"Burgemeester Falkenaweg",
    "iso:country":"NL",
    "sg:address":"Burgemeester Falkenaweg 58",
    "sg:city":"Heerenveen",
    "sg:orig_category":"Schilderwerk",
    "sg:phone":"+31 513 620 262",
    "sg:postcode":"8442 LE",
    "sg:province":"Friesland",
    "wof:name":"Wits Friesland Groningen",
    "wof:placetype":"venue"
},
  "geometry": {"coordinates":[5.929475,52.954365],"type":"Point"}
}