{
  "type": "Feature",
  "properties": {
    "iso:country":"NL",
    "sg:address":"Verbindingswg 14",
    "sg:city":"Wagenborgen",
    "sg:orig_category":"Oud Metaal",
    "sg:phone":"+31 596 542 041",
    "sg:postcode":"9945 SK",
    "sg:province":"Groningen",
    "wof:name":"Timmer, H",
    "wof:placetype":"venue"
},
  "geometry": {"coordinates":[6.9303607941,53.2508926392],"type":"Point"}
}