{
  "type": "Feature",
  "properties": {
    "addr:full":"Drostenstr 1 Sleen Provincie Drenthe 7841 BM",
    "addr:housenumber":"1",
    "addr:postcode":"7841 bm",
    "addr:street":"Drostenstr;Provincie Drenthe",
    "iso:country":"NL",
    "sg:address":"Drostenstr 1",
    "sg:city":"Sleen",
    "sg:orig_category":"Bejaarden - Verzorgingstehuizen",
    "sg:phone":"+31 591 361 816",
    "sg:postcode":"7841 BM",
    "sg:province":"Provincie Drenthe",
    "wof:name":"Schoel, De",
    "wof:placetype":"venue"
},
  "geometry": {"coordinates":[6.800883,52.772274],"type":"Point"}
}