{
  "type": "Feature",
  "properties": {
    "iso:country":"NL",
    "sg:address":"Visserstr 18",
    "sg:city":"Wormer",
    "sg:orig_category":"Scheepssleep- En Duwvaart",
    "sg:phone":"+31 75 642 1512",
    "sg:postcode":"1531 CS",
    "sg:province":"Noord-Holland",
    "wof:name":"Calypso Vof",
    "wof:placetype":"venue"
},
  "geometry": {"coordinates":[4.8103652,52.4959030151],"type":"Point"}
}