{
  "type": "Feature",
  "properties": {
    "iso:country":"NL",
    "sg:address":"Nachtegaalstr 66",
    "sg:city":"Utrecht",
    "sg:orig_category":"Autoverzekeringen",
    "sg:phone":"+31 30 236 9585",
    "sg:postcode":"3581 AM",
    "sg:province":"Utrecht",
    "wof:name":"Raad Op Maat Bv",
    "wof:placetype":"venue"
},
  "geometry": {"coordinates":[5.131603,52.091763],"type":"Point"}
}