{
  "type": "Feature",
  "properties": {
    "addr:full":"Schrans 61 Leeuwarden Provincie Friesland 8932 NB",
    "addr:housenumber":"61",
    "addr:postcode":"8932 nb",
    "addr:street":"Schrans;Provincie Friesland",
    "iso:country":"NL",
    "sg:address":"Schrans 61",
    "sg:city":"Leeuwarden",
    "sg:orig_category":"Opticiens",
    "sg:phone":"+31 58 288 7900",
    "sg:postcode":"8932 NB",
    "sg:province":"Provincie Friesland",
    "wof:name":"De Hoop Brillen",
    "wof:placetype":"venue"
},
  "geometry": {"coordinates":[5.7987551689,53.1956520081],"type":"Point"}
}