{
  "type": "Feature",
  "properties": {
    "addr:full":"Noordewierweg 35 Amersfoort Utrecht 3812 DB",
    "addr:housenumber":"35",
    "addr:postcode":"3812 db",
    "addr:street":"Noordewierweg",
    "iso:country":"NL",
    "sg:address":"Noordewierweg 35",
    "sg:city":"Amersfoort",
    "sg:orig_category":"Kappers",
    "sg:phone":"+31 33 463 3383",
    "sg:postcode":"3812 DB",
    "sg:province":"Utrecht",
    "wof:name":"Bon Rademaker Haarmode",
    "wof:placetype":"venue"
},
  "geometry": {"coordinates":[5.3704199791,52.1592178345],"type":"Point"}
}