{
  "type": "Feature",
  "properties": {
    "addr:full":"Lekdk 223 Nieuw Lekkerland Zuid-Holland 2957 CH",
    "addr:housenumber":"223",
    "addr:postcode":"2957",
    "addr:street":"Nieuw Lekkerland",
    "iso:country":"NL",
    "sg:address":"Lekdk 223",
    "sg:city":"Nieuw Lekkerland",
    "sg:orig_category":"Kinderkleding",
    "sg:phone":"+31 184 683 094",
    "sg:postcode":"2957 CH",
    "sg:province":"Zuid-Holland",
    "wof:name":"Harlekijn, De",
    "wof:placetype":"venue"
},
  "geometry": {"coordinates":[4.685244,51.890862],"type":"Point"}
}