{
  "type": "Feature",
  "properties": {
    "addr:full":"Groenhoeveln 49 Oegstgeest South Holland 2343 BR",
    "addr:housenumber":"49",
    "addr:postcode":"2343 br",
    "addr:street":"Groenhoeveln",
    "iso:country":"NL",
    "sg:address":"Groenhoeveln 49",
    "sg:city":"Oegstgeest",
    "sg:orig_category":"Bloemen En Planten - Groothandel",
    "sg:phone":"+31 71 402 4277",
    "sg:postcode":"2343 BR",
    "sg:province":"South Holland",
    "wof:name":"Aanhane Bv, Gebr",
    "wof:placetype":"venue"
},
  "geometry": {"coordinates":[4.466041,52.190845],"type":"Point"}
}