{
  "type": "Feature",
  "properties": {
    "addr:full":"Dillenburgstr 3 Aalten Gelderland 7121 DE",
    "addr:housenumber":"3",
    "addr:postcode":"7121 de",
    "addr:street":"Dillenburgstr;Gelderland",
    "iso:country":"NL",
    "sg:address":"Dillenburgstr 3",
    "sg:city":"Aalten",
    "sg:orig_category":"Offsetdrukkerijen",
    "sg:phone":"+31 543 473 031",
    "sg:postcode":"7121 DE",
    "sg:province":"Gelderland",
    "sg:website":"http://www.kempers.nl0",
    "wof:name":"Kempers Bv",
    "wof:placetype":"venue"
},
  "geometry": {"coordinates":[6.58745,51.927341],"type":"Point"}
}