{
  "type": "Feature",
  "properties": {
    "addr:full":"Roda J C Ring 99A Kerkrade Limburg 6466 NH",
    "addr:housenumber":"99a",
    "addr:postcode":"6466 nh",
    "addr:street":"C Ring",
    "iso:country":"NL",
    "sg:address":"Roda J C Ring 99A",
    "sg:city":"Kerkrade",
    "sg:orig_category":"Accountants - Administratie- Consulenten En -Kantoren",
    "sg:phone":"+31 45 571 8565",
    "sg:postcode":"6466 NH",
    "sg:province":"Limburg",
    "wof:name":"Ackermann",
    "wof:placetype":"venue"
},
  "geometry": {"coordinates":[6.004356,50.857059],"type":"Point"}
}