{
  "type": "Feature",
  "properties": {
    "addr:full":"Wilgenhof 316 Papendrecht Zuid-Holland 3355 PD",
    "addr:housenumber":"316",
    "addr:postcode":"3355 pd",
    "addr:street":"Wilgenhof",
    "iso:country":"NL",
    "sg:address":"Wilgenhof 316",
    "sg:city":"Papendrecht",
    "sg:orig_category":"Scheepssleep- En Duwvaart",
    "sg:phone":"+31 78 641 1266",
    "sg:postcode":"3355 PD",
    "sg:province":"Zuid-Holland",
    "wof:name":"Cried Vof",
    "wof:placetype":"venue"
},
  "geometry": {"coordinates":[4.7046070099,51.8336410522],"type":"Point"}
}