{
  "type": "Feature",
  "properties": {
    "iso:country":"NL",
    "sg:address":"Van Cruiningenweg 7",
    "sg:city":"Heenvliet",
    "sg:orig_category":"Huisdierenfokkers",
    "sg:phone":"+31 181 664 041",
    "sg:postcode":"3218 BB",
    "sg:province":"South Holland",
    "wof:name":"Baskerville",
    "wof:placetype":"venue"
},
  "geometry": {"coordinates":[4.243842,51.86618],"type":"Point"}
}