{
  "type": "Feature",
  "properties": {
    "addr:full":"Vinkenln 10 Bilthoven Utrecht 3722 AJ",
    "addr:housenumber":"10",
    "addr:postcode":"3722 aj",
    "addr:street":"Vinkenln",
    "iso:country":"NL",
    "sg:address":"Vinkenln 10",
    "sg:city":"Bilthoven",
    "sg:orig_category":"Sanitaire Artikelen",
    "sg:phone":"+31 30 228 7470",
    "sg:postcode":"3722 AJ",
    "sg:province":"Utrecht",
    "wof:name":"Rossum En Sterk, Van",
    "wof:placetype":"venue"
},
  "geometry": {"coordinates":[5.205587,52.128887],"type":"Point"}
}