{
  "type": "Feature",
  "properties": {
    "iso:country":"NL",
    "sg:address":"Witte De Withstraat 10",
    "sg:city":"Amsterdam",
    "sg:classifiers":[
        {
            "category":"Fast Food",
            "type":"Food & Drink"
        }
    ],
    "sg:phone":"+31 20 683 8236",
    "sg:postcode":"1057 XV",
    "sg:province":"Noord-Holland",
    "sg:tags":[
        "afhaal",
        "restaurant"
    ],
    "wof:name":"Snackbar Witte De With",
    "wof:placetype":"venue"
},
  "geometry": {"coordinates":[4.85966,52.365234],"type":"Point"}
}