{
  "type": "Feature",
  "properties": {
    "iso:country":"NL",
    "sg:address":"Kon Julianastr 32",
    "sg:city":"Waarder",
    "sg:orig_category":"Directmail",
    "sg:phone":"+31 348 501 060",
    "sg:postcode":"3466 LH",
    "sg:province":"South Holland",
    "wof:name":"Tiny",
    "wof:placetype":"venue"
},
  "geometry": {"coordinates":[4.822681,52.059574],"type":"Point"}
}