{
  "type": "Feature",
  "properties": {
    "iso:country":"NL",
    "sg:address":"Crispynhof 1",
    "sg:city":"Dongen",
    "sg:orig_category":"Administratie- En Boekhoudkantoren",
    "sg:phone":"+31 162 323 041",
    "sg:postcode":"5101 BL",
    "sg:province":"Noord-Brabant",
    "wof:name":"Jacobs",
    "wof:placetype":"venue"
},
  "geometry": {"coordinates":[7.82245,47.45105],"type":"Point"}
}