{
  "type": "Feature",
  "properties": {
    "addr:full":"Klinkenberg 75 Meerssen Limburg 6231 BB",
    "addr:housenumber":"75",
    "addr:postcode":"6231 bb",
    "addr:street":"Klinkenberg",
    "iso:country":"NL",
    "sg:address":"Klinkenberg 75",
    "sg:city":"Meerssen",
    "sg:orig_category":"Kappers",
    "sg:phone":"+31 43 364 1339",
    "sg:postcode":"6231 BB",
    "sg:province":"Limburg",
    "wof:name":"Basje",
    "wof:placetype":"venue"
},
  "geometry": {"coordinates":[5.7361478806,50.8768043518],"type":"Point"}
}