{
  "type": "Feature",
  "properties": {
    "iso:country":"NL",
    "sg:address":"Stadhouderswg 14",
    "sg:city":"St Annaparochie",
    "sg:orig_category":"Muziekinstrumenten En Bladmuziek",
    "sg:phone":"+31 518 402 739",
    "sg:postcode":"9076 AC",
    "sg:province":"Provincie Friesland",
    "wof:name":"Pasma",
    "wof:placetype":"venue"
},
  "geometry": {"coordinates":[5.657104,53.2775],"type":"Point"}
}