{
  "type": "Feature",
  "properties": {
    "iso:country":"NL",
    "sg:address":"Molenstr 54",
    "sg:city":"Beuningen Gld",
    "sg:orig_category":"Verenigingen En Stichtingen",
    "sg:phone":"+31 24 677 4160",
    "sg:postcode":"6641 BK",
    "sg:province":"Gelderland",
    "sg:website":"http://www.sscwbeuningen.nl",
    "wof:name":"Soc Cult Werk, Sticht",
    "wof:placetype":"venue"
},
  "geometry": {"coordinates":[5.776451,51.860855],"type":"Point"}
}