{
  "type": "Feature",
  "properties": {
    "addr:full":"Schubertlaan 10 Vlijmen Noord-Brabant 5251 HJ",
    "addr:housenumber":"10",
    "addr:postcode":"5251 hj",
    "addr:street":"Schubertlaan",
    "iso:country":"NL",
    "sg:address":"Schubertlaan 10",
    "sg:city":"Vlijmen",
    "sg:orig_category":"Diverse Consumentenartikelen Gh",
    "sg:phone":"+31 73 511 2068",
    "sg:postcode":"5251 HJ",
    "sg:province":"Noord-Brabant",
    "wof:name":"Polle Vof",
    "wof:placetype":"venue"
},
  "geometry": {"coordinates":[5.217671,51.701473],"type":"Point"}
}