{
  "type": "Feature",
  "properties": {
    "addr:full":"Gouwestraat 21 Boskoop Zuid-Holland 2771 CG",
    "addr:housenumber":"21",
    "addr:postcode":"2771 cg",
    "addr:street":"Gouwestraat",
    "iso:country":"NL",
    "sg:address":"Gouwestraat 21",
    "sg:city":"Boskoop",
    "sg:orig_category":"Kappers",
    "sg:phone":"+31 172 212 506",
    "sg:postcode":"2771 CG",
    "sg:province":"Zuid-Holland",
    "wof:name":"Kapsalon Groenendijk",
    "wof:placetype":"venue"
},
  "geometry": {"coordinates":[4.6622061729,52.0739479065],"type":"Point"}
}