{
  "type": "Feature",
  "properties": {
    "addr:full":"Goorsestraat 5 'S Heerenberg Gelderland 7041 GA",
    "addr:housenumber":"5 ' s",
    "addr:postcode":"7041 ga",
    "addr:street":"Goorsestraat;Heerenberg Gelderland",
    "iso:country":"NL",
    "sg:address":"Goorsestraat 5",
    "sg:city":"'S Heerenberg",
    "sg:classifiers":[
        {
            "category":"Shopping",
            "subcategory":"Clothing, Apparel, & Fashions",
            "type":"Retail Goods"
        }
    ],
    "sg:phone":"+31 314 667 156",
    "sg:postcode":"7041 GA",
    "sg:province":"Gelderland",
    "sg:tags":[
        "ondergoed",
        "lingerie"
    ],
    "wof:name":"Sassa Moden Bv",
    "wof:placetype":"venue"
},
  "geometry": {"coordinates":[6.2598,51.874081],"type":"Point"}
}