{
  "type": "Feature",
  "properties": {
    "iso:country":"NL",
    "sg:address":"Goorsestraat 5",
    "sg:city":"'S Heerenberg",
    "sg:classifiers":[
        {
            "category":"Shopping",
            "subcategory":"Clothing, Apparel, & Fashions",
            "type":"Retail Goods"
        }
    ],
    "sg:phone":"+31 314 667 156",
    "sg:postcode":"7041 GA",
    "sg:province":"Gelderland",
    "sg:tags":[
        "ondergoed",
        "lingerie"
    ],
    "wof:name":"Sassa Moden Bv",
    "wof:placetype":"venue"
},
  "geometry": {"coordinates":[6.2598,51.874081],"type":"Point"}
}