{
  "type": "Feature",
  "properties": {
    "addr:full":"Kerkpln 9 Maasland South Holland 3155 AM",
    "addr:housenumber":"9",
    "addr:postcode":"3155",
    "addr:street":"Kerkpln",
    "iso:country":"NL",
    "sg:address":"Kerkpln 9",
    "sg:city":"Maasland",
    "sg:orig_category":"Notarissen En Notariskantoren",
    "sg:phone":"+31 10 592 0111",
    "sg:postcode":"3155 AM",
    "sg:province":"South Holland",
    "wof:name":"Geldens, Mr A A P M",
    "wof:placetype":"venue"
},
  "geometry": {"coordinates":[4.272318,51.936535],"type":"Point"}
}