{
  "type": "Feature",
  "properties": {
    "addr:full":"Lorentzplein 14 Haarlem North Holland 2012 HG",
    "addr:housenumber":"14",
    "addr:postcode":"2012 hg",
    "addr:street":"Lorentzplein",
    "iso:country":"NL",
    "sg:address":"Lorentzplein 14",
    "sg:city":"Haarlem",
    "sg:orig_category":"Boekhouders",
    "sg:phone":"+31 23 531 1119",
    "sg:postcode":"2012 HG",
    "sg:province":"North Holland",
    "wof:name":"Buro Zaken",
    "wof:placetype":"venue"
},
  "geometry": {"coordinates":[4.628105,52.375046],"type":"Point"}
}