{
  "type": "Feature",
  "properties": {
    "addr:full":"Oude Bennekomseweg 12 Ede Gld Gelderland 6717 LL",
    "addr:housenumber":"12",
    "addr:postcode":"6717 ll",
    "addr:street":"Oude Bennekomseweg;Gld Gelderland",
    "iso:country":"NL",
    "sg:address":"Oude Bennekomseweg 12",
    "sg:city":"Ede Gld",
    "sg:orig_category":"Geluidsopnamen",
    "sg:phone":"+31 318 690 738",
    "sg:postcode":"6717 LL",
    "sg:province":"Gelderland",
    "wof:name":"Jodi Studio'S",
    "wof:placetype":"venue"
},
  "geometry": {"coordinates":[5.671344,52.02615],"type":"Point"}
}