{
  "type": "Feature",
  "properties": {
    "addr:full":"Niers 6 Deurne Noord-Brabant 5751 TS",
    "addr:housenumber":"6",
    "addr:postcode":"5751 ts",
    "addr:street":"Niers",
    "iso:country":"NL",
    "sg:address":"Niers 6",
    "sg:city":"Deurne",
    "sg:orig_category":"Kantoorapparatuur Gh",
    "sg:phone":"+31 493 313 572",
    "sg:postcode":"5751 TS",
    "sg:province":"Noord-Brabant",
    "wof:name":"Heyblom Project",
    "wof:placetype":"venue"
},
  "geometry": {"coordinates":[5.8037791252,51.4596824646],"type":"Point"}
}