{
  "type": "Feature",
  "properties": {
    "addr:full":"De Schoren 31 Malden Gelderland 6581 DL",
    "addr:housenumber":"31",
    "addr:postcode":"6581 dl",
    "addr:street":"De Schoren;Gelderland",
    "iso:country":"NL",
    "sg:address":"De Schoren 31",
    "sg:city":"Malden",
    "sg:orig_category":"Diverse Grafische Activiteiten",
    "sg:phone":"+31 24 358 1930",
    "sg:postcode":"6581 DL",
    "sg:province":"Gelderland",
    "wof:name":"Adriaensen Design",
    "wof:placetype":"venue"
},
  "geometry": {"coordinates":[5.853363,51.788277],"type":"Point"}
}