{
  "type": "Feature",
  "properties": {
    "addr:full":"Aar 67 Rotterdam Zuid-Holland 3068 HA",
    "addr:housenumber":"67",
    "addr:postcode":"3068 ha",
    "addr:street":"Aar",
    "iso:country":"NL",
    "sg:address":"Aar 67",
    "sg:city":"Rotterdam",
    "sg:orig_category":"Tekstschrijversters",
    "sg:phone":"+31 10 421 8928",
    "sg:postcode":"3068 HA",
    "sg:province":"Zuid-Holland",
    "wof:name":"Lydia",
    "wof:placetype":"venue"
},
  "geometry": {"coordinates":[4.569553,51.963493],"type":"Point"}
}