{
  "type": "Feature",
  "properties": {
    "addr:full":"Nieuwkoopsewg 13 Aarlanderveen Zuid-Holland 2445 NB",
    "addr:housenumber":"13",
    "addr:postcode":"2445 nb",
    "addr:street":"Nieuwkoopsewg",
    "iso:country":"NL",
    "sg:address":"Nieuwkoopsewg 13",
    "sg:city":"Aarlanderveen",
    "sg:orig_category":"Onderhoudswerken",
    "sg:phone":"+31 6 51364915",
    "sg:postcode":"2445 NB",
    "sg:province":"Zuid-Holland",
    "wof:name":"Kuijf, A",
    "wof:placetype":"venue"
},
  "geometry": {"coordinates":[4.729421,52.141529],"type":"Point"}
}