{
  "type": "Feature",
  "properties": {
    "addr:full":"Purperreigerstr 2 S Gravenhage 2492 TD",
    "addr:housenumber":"2",
    "addr:postcode":"2492 td",
    "addr:street":"Purperreigerstr;S Gravenhage",
    "iso:country":"NL",
    "sg:address":"Purperreigerstr 2",
    "sg:city":"S Gravenhage",
    "sg:orig_category":"Natuursteen",
    "sg:phone":"+31 70 444 7133",
    "sg:postcode":"2492 TD",
    "wof:name":"Ptc",
    "wof:placetype":"venue"
},
  "geometry": {"coordinates":[4.40783,52.067459],"type":"Point"}
}