{
  "type": "Feature",
  "properties": {
    "addr:full":"Schoolstraat 2 Rijswijk Zh South Holland 2282 RD",
    "addr:housenumber":"2",
    "addr:postcode":"2282 rd",
    "addr:street":"Schoolstraat",
    "iso:country":"NL",
    "sg:address":"Schoolstraat 2",
    "sg:city":"Rijswijk Zh",
    "sg:orig_category":"Kappers",
    "sg:phone":"+31 70 399 4062",
    "sg:postcode":"2282 RD",
    "sg:province":"South Holland",
    "wof:name":"Haarmode Independence",
    "wof:placetype":"venue"
},
  "geometry": {"coordinates":[4.3322601318,52.0555763245],"type":"Point"}
}