{
  "type": "Feature",
  "properties": {
    "addr:full":"Papendalln 50 Arnhem Gelderland 6816 VD",
    "addr:housenumber":"50",
    "addr:postcode":"6816 vd",
    "addr:street":"Papendalln",
    "iso:country":"NL",
    "sg:address":"Papendalln 50",
    "sg:city":"Arnhem",
    "sg:orig_category":"Verenigingen En Stichtingen",
    "sg:phone":"+31 26 483 3800",
    "sg:postcode":"6816 VD",
    "sg:province":"Gelderland",
    "sg:website":"http://www.nisb.nl",
    "wof:name":"Nisb",
    "wof:placetype":"venue"
},
  "geometry": {"coordinates":[5.817949,52.011318],"type":"Point"}
}