{
  "type": "Feature",
  "properties": {
    "addr:full":"Baliendk 46 Breda Noord-Brabant 4816 GE",
    "addr:housenumber":"46",
    "addr:postcode":"4816",
    "addr:street":"Baliendk",
    "iso:country":"NL",
    "sg:address":"Baliendk 46",
    "sg:city":"Breda",
    "sg:orig_category":"Drukkerijen",
    "sg:phone":"+31 76 571 3833",
    "sg:postcode":"4816 GE",
    "sg:province":"Noord-Brabant",
    "wof:name":"Drukwerkservice Baliendijk Bv",
    "wof:placetype":"venue"
},
  "geometry": {"coordinates":[4.794405,51.598755],"type":"Point"}
}