{
  "type": "Feature",
  "properties": {
    "addr:full":"Nijverheidsweg 20 Druten Gelderland 6651 KS",
    "addr:housenumber":"20",
    "addr:postcode":"6651 ks",
    "addr:street":"Nijverheidsweg",
    "iso:country":"NL",
    "sg:address":"Nijverheidsweg 20",
    "sg:city":"Druten",
    "sg:orig_category":"Touringcars",
    "sg:phone":"+31 487 515 151",
    "sg:postcode":"6651 KS",
    "sg:province":"Gelderland",
    "sg:website":"http://www.schiks.nl",
    "wof:name":"Schiks Bv",
    "wof:placetype":"venue"
},
  "geometry": {"coordinates":[5.576815,51.885876],"type":"Point"}
}