{
  "type": "Feature",
  "properties": {
    "iso:country":"NL",
    "sg:address":"Croydonplein 406",
    "sg:city":"Arnhem",
    "sg:orig_category":"Kappers",
    "sg:phone":"+31 26 323 6166",
    "sg:postcode":"6831 LN",
    "sg:province":"Gelderland",
    "wof:name":"Coiffure Pour Vous",
    "wof:placetype":"venue"
},
  "geometry": {"coordinates":[5.8943610191,51.9583091736],"type":"Point"}
}