{
  "type": "Feature",
  "properties": {
    "addr:full":"Hoogeind 56 Driebruggen Zuid-Holland 3465 HD",
    "addr:housenumber":"56",
    "addr:postcode":"3465 hd",
    "addr:street":"Hoogeind",
    "iso:country":"NL",
    "sg:address":"Hoogeind 56",
    "sg:city":"Driebruggen",
    "sg:orig_category":"Landbouwmachines Gh",
    "sg:phone":"+31 348 502 487",
    "sg:postcode":"3465 HD",
    "sg:province":"Zuid-Holland",
    "wof:name":"Landbouwmechanisatie Bedrijf Verburg",
    "wof:placetype":"venue"
},
  "geometry": {"coordinates":[4.800201,52.030704],"type":"Point"}
}