{
  "type": "Feature",
  "properties": {
    "addr:full":"Markt 1 Delden Overijssel 7491 AT",
    "addr:housenumber":"1",
    "addr:postcode":"7491",
    "addr:street":"Markt",
    "iso:country":"NL",
    "sg:address":"Markt 1",
    "sg:city":"Delden",
    "sg:orig_category":"Bloemen And Planten",
    "sg:phone":"+31 74 376 3871",
    "sg:postcode":"7491 AT",
    "sg:province":"Overijssel",
    "wof:name":"Bloembinderij Anton Visch",
    "wof:placetype":"venue"
},
  "geometry": {"coordinates":[6.711995,52.263115],"type":"Point"}
}