{
  "type": "Feature",
  "properties": {
    "addr:full":"Stationswg 1 Venhuizen Noord-Holland 1606 XN",
    "addr:housenumber":"1",
    "addr:postcode":"1606 xn",
    "addr:street":"Stationswg",
    "iso:country":"NL",
    "sg:address":"Stationswg 1",
    "sg:city":"Venhuizen",
    "sg:orig_category":"Wijnkoperijen En -Groothandel",
    "sg:phone":"+31 228 542 773",
    "sg:postcode":"1606 XN",
    "sg:province":"Noord-Holland",
    "wof:name":"Veldman",
    "wof:placetype":"venue"
},
  "geometry": {"coordinates":[5.2157897949,52.6689224243],"type":"Point"}
}