{
  "type": "Feature",
  "properties": {
    "iso:country":"NL",
    "sg:address":"O Nassaustr 21",
    "sg:city":"Voorburg",
    "sg:orig_category":"Wasserijen",
    "sg:phone":"+31 70 386 6556",
    "sg:postcode":"2271 SJ",
    "sg:province":"Zuid-Holland",
    "wof:name":"Lochem, P F B Van",
    "wof:placetype":"venue"
},
  "geometry": {"coordinates":[4.3716578484,52.0737075806],"type":"Point"}
}