{
  "type": "Feature",
  "properties": {
    "addr:full":"Damrak 1 Amsterdam Noord-Holland 1012 LG",
    "addr:housenumber":"1",
    "addr:postcode":"1012 lg",
    "addr:street":"Damrak",
    "iso:country":"NL",
    "sg:address":"Damrak 1",
    "sg:city":"Amsterdam",
    "sg:classifiers":[
        {
            "category":"Shopping",
            "subcategory":"Gifts & Souvenirs",
            "type":"Retail Goods"
        }
    ],
    "sg:phone":"+31 20 625 5735",
    "sg:postcode":"1012 LG",
    "sg:province":"Noord-Holland",
    "sg:tags":[
        "geschenken"
    ],
    "wof:name":"Souvenirshop La Vitrine",
    "wof:placetype":"venue"
},
  "geometry": {"coordinates":[4.898075,52.377163],"type":"Point"}
}