{
  "type": "Feature",
  "properties": {
    "iso:country":"NL",
    "sg:address":"Kruisweg 953",
    "sg:city":"Hoofddorp",
    "sg:orig_category":"Zuivelproducten",
    "sg:phone":"+31 23 565 4263",
    "sg:postcode":"2132 CD",
    "sg:province":"Noord-Holland",
    "wof:name":"J. Oud",
    "wof:placetype":"venue"
},
  "geometry": {"coordinates":[4.698472,52.302773],"type":"Point"}
}