{
  "type": "Feature",
  "properties": {
    "iso:country":"NL",
    "sg:address":"Molenstraat 48",
    "sg:city":"Bunschoten Spakenburg",
    "sg:orig_category":"Verzekeringen",
    "sg:phone":"+31 33 298 1591",
    "sg:postcode":"3752 CJ",
    "sg:province":"Utrecht",
    "wof:name":"Assurantiekantoor Hartog",
    "wof:placetype":"venue"
},
  "geometry": {"coordinates":[5.375801,52.247517],"type":"Point"}
}