{
  "type": "Feature",
  "properties": {
    "addr:full":"H Duyfhuysstr 7 Utrecht Utrecht 3553 VT",
    "addr:housenumber":"7",
    "addr:postcode":"3553",
    "iso:country":"NL",
    "sg:address":"H Duyfhuysstr 7",
    "sg:city":"Utrecht",
    "sg:orig_category":"Acupunctuur",
    "sg:phone":"+31 30 243 6551",
    "sg:postcode":"3553 VT",
    "sg:province":"Utrecht",
    "wof:name":"Leeuwen, L I Van",
    "wof:placetype":"venue"
},
  "geometry": {"coordinates":[5.08441,52.109322],"type":"Point"}
}