{
  "type": "Feature",
  "properties": {
    "addr:full":"Bellesteynlaan 89 Wassenaar South Holland 2241 WH",
    "addr:housenumber":"89",
    "addr:postcode":"2241 wh",
    "addr:street":"Bellesteynlaan",
    "iso:country":"NL",
    "sg:address":"Bellesteynlaan 89",
    "sg:city":"Wassenaar",
    "sg:orig_category":"Fotostudio'S And Fotografen",
    "sg:phone":"+31 70 511 9870",
    "sg:postcode":"2241 WH",
    "sg:province":"South Holland",
    "wof:name":"E.J. Kenens",
    "wof:placetype":"venue"
},
  "geometry": {"coordinates":[4.412151,52.149757],"type":"Point"}
}