{
  "type": "Feature",
  "properties": {
    "addr:full":"Rozenstr 144 Amsterdam Noord-Holland 1016 NZ",
    "addr:housenumber":"144",
    "addr:postcode":"1016 nz",
    "iso:country":"NL",
    "sg:address":"Rozenstr 144",
    "sg:city":"Amsterdam",
    "sg:orig_category":"Modeontwerpen",
    "sg:phone":"+31 20 622 5066",
    "sg:postcode":"1016 NZ",
    "sg:province":"Noord-Holland",
    "wof:name":"Teja, Studio",
    "wof:placetype":"venue"
},
  "geometry": {"coordinates":[4.879125,52.372429],"type":"Point"}
}