{
  "type": "Feature",
  "properties": {
    "addr:full":"V Hogendorpwg 12B Alblasserdam Zuid-Holland 2953 AS",
    "addr:housenumber":"12b",
    "addr:postcode":"2953 as",
    "addr:street":"Hogendorpwg",
    "iso:country":"NL",
    "sg:address":"V Hogendorpwg 12B",
    "sg:city":"Alblasserdam",
    "sg:orig_category":"Fietsen En Bromfietsen",
    "sg:phone":"+31 78 691 7914",
    "sg:postcode":"2953 AS",
    "sg:province":"Zuid-Holland",
    "wof:name":"Dieren, Van",
    "wof:placetype":"venue"
},
  "geometry": {"coordinates":[4.658851,51.861031],"type":"Point"}
}