{
  "type": "Feature",
  "properties": {
    "addr:full":"Oranjestraat 23 Elst Ut Utrecht 3921 BA",
    "addr:housenumber":"23",
    "addr:postcode":"ut;3921 ba",
    "addr:street":"Oranjestraat",
    "iso:country":"NL",
    "sg:address":"Oranjestraat 23",
    "sg:city":"Elst Ut",
    "sg:orig_category":"Paramedische Behandelingen",
    "sg:phone":"+31 318 471 314",
    "sg:postcode":"3921 BA",
    "sg:province":"Utrecht",
    "wof:name":"Cmd Zuid-Oost Utrecht",
    "wof:placetype":"venue"
},
  "geometry": {"coordinates":[5.500685,51.984528],"type":"Point"}
}