{
  "type": "Feature",
  "properties": {
    "addr:full":"Eggewg 52 Koekange Drenthe 7958 PM",
    "addr:housenumber":"52",
    "addr:postcode":"7958 pm",
    "addr:street":"Eggewg",
    "iso:country":"NL",
    "sg:address":"Eggewg 52",
    "sg:city":"Koekange",
    "sg:orig_category":"Beeldende Kunstenaars",
    "sg:phone":"+31 522 451 753",
    "sg:postcode":"7958 PM",
    "sg:province":"Drenthe",
    "wof:name":"Windemuller, S",
    "wof:placetype":"venue"
},
  "geometry": {"coordinates":[6.325615,52.694237],"type":"Point"}
}