{
  "type": "Feature",
  "properties": {
    "addr:full":"Havenpark 28 Zierikzee Zeeland 4301 CD",
    "addr:housenumber":"28",
    "addr:postcode":"4301 cd",
    "addr:street":"Havenpark",
    "iso:country":"NL",
    "sg:address":"Havenpark 28",
    "sg:city":"Zierikzee",
    "sg:orig_category":"Meubelzaken, Woning- And Keukeninrichting",
    "sg:phone":"+31 111 413 727",
    "sg:postcode":"4301 CD",
    "sg:province":"Zeeland",
    "wof:name":"T Lange Uus Bv",
    "wof:placetype":"venue"
},
  "geometry": {"coordinates":[3.922078,51.649044],"type":"Point"}
}