{
  "type": "Feature",
  "properties": {
    "iso:country":"NL",
    "sg:address":"Schoolstraat 3",
    "sg:city":"Burdaard",
    "sg:orig_category":"Artiesten",
    "sg:phone":"+31 519 332 404",
    "sg:postcode":"9111 HG",
    "sg:province":"Friesland",
    "wof:name":"Nynke Runia",
    "wof:placetype":"venue"
},
  "geometry": {"coordinates":[5.876918,53.294834],"type":"Point"}
}