{
  "type": "Feature",
  "properties": {
    "iso:country":"NL",
    "sg:address":"Constantijnstraat 111",
    "sg:city":"Vroomshoop",
    "sg:orig_category":"Chemische Producten Gh",
    "sg:phone":"+31 546 646 454",
    "sg:postcode":"7681 WE",
    "sg:province":"Overijssel",
    "wof:name":"I A D Vroomshoop",
    "wof:placetype":"venue"
},
  "geometry": {"coordinates":[6.561114,52.454319],"type":"Point"}
}