{
  "type": "Feature",
  "properties": {
    "addr:full":"Laan Op Zuid 45 Rotterdam South Holland 3072 DB",
    "addr:housenumber":"45",
    "addr:postcode":"3072 db",
    "addr:street":"Laan Op Zuid",
    "iso:country":"NL",
    "sg:address":"Laan Op Zuid 45",
    "sg:city":"Rotterdam",
    "sg:orig_category":"Overheidsdiensten",
    "sg:phone":"+31 10 290 5050",
    "sg:postcode":"3072 DB",
    "sg:province":"South Holland",
    "wof:name":"Belastingdienst Ondernemingen Rotterdam 2",
    "wof:placetype":"venue"
},
  "geometry": {"coordinates":[4.4946708679,51.9073486328],"type":"Point"}
}