{
  "type": "Feature",
  "properties": {
    "addr:full":"Achter De Kamp 2 Amersfoort Utrecht 3811 JG",
    "addr:housenumber":"2",
    "addr:postcode":"3811 jg",
    "addr:street":"Achter De Kamp",
    "iso:country":"NL",
    "sg:address":"Achter De Kamp 2",
    "sg:city":"Amersfoort",
    "sg:orig_category":"Galeries",
    "sg:phone":"+31 33 472 2424",
    "sg:postcode":"3811 JG",
    "sg:province":"Utrecht",
    "wof:name":"Kei",
    "wof:placetype":"venue"
},
  "geometry": {"coordinates":[5.394186,52.157028],"type":"Point"}
}