{
  "type": "Feature",
  "properties": {
    "iso:country":"NL",
    "sg:address":"Hammarskjoldln 16",
    "sg:city":"Middelburg",
    "sg:orig_category":"Adviesbureaus Bedrijfsorganisatie",
    "sg:phone":"+31 118 625 901",
    "sg:postcode":"4334 EN",
    "sg:province":"Zeeland",
    "wof:name":"Implementations Services Bv",
    "wof:placetype":"venue"
},
  "geometry": {"coordinates":[3.592208,51.502346],"type":"Point"}
}