{
  "type": "Feature",
  "properties": {
    "addr:full":"Marconiwg 7 Gorinchem Zuid-Holland 4207 HH",
    "addr:housenumber":"7",
    "addr:postcode":"4207 hh",
    "addr:street":"Marconiwg",
    "iso:country":"NL",
    "sg:address":"Marconiwg 7",
    "sg:city":"Gorinchem",
    "sg:orig_category":"Autoschade- Herstelbedrijven",
    "sg:phone":"+31 6 53156650",
    "sg:postcode":"4207 HH",
    "sg:province":"Zuid-Holland",
    "wof:name":"Janson Bv",
    "wof:placetype":"venue"
},
  "geometry": {"coordinates":[4.996698,51.840679],"type":"Point"}
}