{
  "type": "Feature",
  "properties": {
    "addr:full":"Koningsweg 34 'S Hertogenbosch Noord-Brabant 5211 BL",
    "addr:housenumber":"34",
    "addr:postcode":"5211 bl",
    "addr:street":"Koningsweg;' S",
    "iso:country":"NL",
    "sg:address":"Koningsweg 34",
    "sg:city":"'S Hertogenbosch",
    "sg:orig_category":"Schilderwerk",
    "sg:phone":"+31 73 614 0149",
    "sg:postcode":"5211 BL",
    "sg:province":"Noord-Brabant",
    "wof:name":"Harry Damen Decoratieschilder",
    "wof:placetype":"venue"
},
  "geometry": {"coordinates":[5.294293,51.686325],"type":"Point"}
}