{
  "type": "Feature",
  "properties": {
    "addr:full":"Bosdreef 7 Bergeyk Noord-Brabant 5571 AG",
    "addr:housenumber":"7",
    "addr:postcode":"5571",
    "addr:street":"Bosdreef",
    "iso:country":"NL",
    "sg:address":"Bosdreef 7",
    "sg:city":"Bergeyk",
    "sg:orig_category":"Adviesbureaus Bedrijfsorganisatie",
    "sg:phone":"+31 497 550 140",
    "sg:postcode":"5571 AG",
    "sg:province":"Noord-Brabant",
    "wof:name":"Kic",
    "wof:placetype":"venue"
},
  "geometry": {"coordinates":[5.350656,51.326927],"type":"Point"}
}