{
  "type": "Feature",
  "properties": {
    "addr:full":"Kerkln 10E Ermelo Gelderland 3851 JV",
    "addr:housenumber":"10e",
    "addr:postcode":"3851 jv",
    "addr:street":"Kerkln;Gelderland",
    "iso:country":"NL",
    "sg:address":"Kerkln 10E",
    "sg:city":"Ermelo",
    "sg:orig_category":"Administratie- En Boekhoudkantoren",
    "sg:phone":"+31 341 552 844",
    "sg:postcode":"3851 JV",
    "sg:province":"Gelderland",
    "sg:website":"http://www.adminbos.nl",
    "wof:name":"Bos",
    "wof:placetype":"venue"
},
  "geometry": {"coordinates":[5.63146,52.297852],"type":"Point"}
}