{
  "type": "Feature",
  "properties": {
    "addr:full":"Marnixstr 195F Amsterdam North Holland 1015 VR",
    "addr:housenumber":"195f",
    "addr:postcode":"1015 vr",
    "addr:street":"Marnixstr",
    "iso:country":"NL",
    "sg:address":"Marnixstr 195F",
    "sg:city":"Amsterdam",
    "sg:orig_category":"Onderhoudswerken",
    "sg:phone":"+31 20 638 1696",
    "sg:postcode":"1015 VR",
    "sg:province":"North Holland",
    "wof:name":"Ito",
    "wof:placetype":"venue"
},
  "geometry": {"coordinates":[4.879721,52.378971],"type":"Point"}
}