{
  "type": "Feature",
  "properties": {
    "addr:full":"Gulden Huis 48 Oss Virginia 5346 SR",
    "addr:housenumber":"48",
    "addr:postcode":"5346 sr",
    "addr:street":"Gulden Huis",
    "iso:country":"NL",
    "sg:address":"Gulden Huis 48",
    "sg:city":"Oss",
    "sg:orig_category":"Meubelzaken, Woning- And Keukeninrichting",
    "sg:phone":"+31 412 637 192",
    "sg:postcode":"5346 SR",
    "sg:province":"Virginia",
    "wof:name":"A. Smits",
    "wof:placetype":"venue"
},
  "geometry": {"coordinates":[-77.235214,38.312599],"type":"Point"}
}