{
  "type": "Feature",
  "properties": {
    "addr:full":"Pampuspad 45 Emmeloord Flevoland 8304 DR",
    "addr:housenumber":"45",
    "addr:postcode":"8304 dr",
    "addr:street":"Pampuspad;Flevoland",
    "iso:country":"NL",
    "sg:address":"Pampuspad 45",
    "sg:city":"Emmeloord",
    "sg:orig_category":"Scholen Voor Basisonderwijs",
    "sg:phone":"+31 527 616 674",
    "sg:postcode":"8304 DR",
    "sg:province":"Flevoland",
    "wof:name":"Daltonschool Windkracht 10 Openb",
    "wof:placetype":"venue"
},
  "geometry": {"coordinates":[5.762101,52.704071],"type":"Point"}
}