{
  "type": "Feature",
  "properties": {
    "addr:full":"Dampadsteeg 4 Zaandam North Holland 1506 SJ",
    "addr:housenumber":"4",
    "addr:postcode":"1506",
    "addr:street":"Dampadsteeg",
    "iso:country":"NL",
    "sg:address":"Dampadsteeg 4",
    "sg:city":"Zaandam",
    "sg:orig_category":"Artiestenbureaus",
    "sg:phone":"+31 75 670 0971",
    "sg:postcode":"1506 SJ",
    "sg:province":"North Holland",
    "wof:name":"Matje Artists Agency",
    "wof:placetype":"venue"
},
  "geometry": {"coordinates":[4.82084,52.43911],"type":"Point"}
}