{
  "type": "Feature",
  "properties": {
    "iso:country":"NL",
    "sg:address":"Bavelseln 1",
    "sg:city":"Breda",
    "sg:orig_category":"Makelaars En Adviseurs Onroerende Goederen",
    "sg:phone":"+31 76 565 6750",
    "sg:postcode":"4835 GP",
    "sg:province":"Noord-Brabant",
    "sg:website":"http://www.vancaulil.nl",
    "wof:name":"Caulil, Makelaars Van",
    "wof:placetype":"venue"
},
  "geometry": {"coordinates":[4.78509,51.569248],"type":"Point"}
}