{
  "type": "Feature",
  "properties": {
    "iso:country":"NL",
    "sg:address":"Dorpsstr 18B",
    "sg:city":"Aalst Gld",
    "sg:orig_category":"Woninginrichting",
    "sg:phone":"+31 418 677 303",
    "sg:postcode":"5308 KC",
    "sg:province":"Gelderland",
    "wof:name":"Tendance, La",
    "wof:placetype":"venue"
},
  "geometry": {"coordinates":[5.1245942116,51.7826385498],"type":"Point"}
}