{
  "type": "Feature",
  "properties": {
    "addr:full":"Glanswit 12 Zoetermeer Zuid-Holland 2718 AD",
    "addr:housenumber":"12",
    "addr:postcode":"2718 ad",
    "addr:street":"Glanswit",
    "iso:country":"NL",
    "sg:address":"Glanswit 12",
    "sg:city":"Zoetermeer",
    "sg:orig_category":"Adviesbureaus",
    "sg:phone":"+31 79 361 1768",
    "sg:postcode":"2718 AD",
    "sg:province":"Zuid-Holland",
    "wof:name":"Martcon",
    "wof:placetype":"venue"
},
  "geometry": {"coordinates":[4.488646,52.044109],"type":"Point"}
}