{
  "type": "Feature",
  "properties": {
    "addr:full":"S V Capelwg 99 Noorden Zuid-Holland 2431 AD",
    "addr:housenumber":"99",
    "addr:postcode":"2431 ad",
    "addr:street":"Capelwg",
    "iso:country":"NL",
    "sg:address":"S V Capelwg 99",
    "sg:city":"Noorden",
    "sg:orig_category":"Kunststof Ramen",
    "sg:phone":"+31 172 408 464",
    "sg:postcode":"2431 AD",
    "sg:province":"Zuid-Holland",
    "wof:name":"Wahle Aannemingsbedrijf",
    "wof:placetype":"venue"
},
  "geometry": {"coordinates":[-120.36385300000001,39.320374],"type":"Point"}
}