{
  "type": "Feature",
  "properties": {
    "addr:full":"Berlicumsewg 10 Rosmalen North Brabant 5248 NT",
    "addr:housenumber":"10",
    "addr:postcode":"5248 nt",
    "addr:street":"Berlicumsewg",
    "iso:country":"NL",
    "sg:address":"Berlicumsewg 10",
    "sg:city":"Rosmalen",
    "sg:orig_category":"Projectontwikkeling",
    "sg:phone":"+31 73 523 1030",
    "sg:postcode":"5248 NT",
    "sg:province":"North Brabant",
    "wof:name":"Meijon Bv",
    "wof:placetype":"venue"
},
  "geometry": {"coordinates":[5.367471,51.698406],"type":"Point"}
}