{
  "type": "Feature",
  "properties": {
    "addr:full":"Lageweg 39 Katwijk Zh South Holland 2222 AG",
    "addr:housenumber":"39",
    "addr:postcode":"zh;2222",
    "addr:street":"Lageweg",
    "iso:country":"NL",
    "sg:address":"Lageweg 39",
    "sg:city":"Katwijk Zh",
    "sg:orig_category":"Kantoorapparatuur Gh",
    "sg:phone":"+31 71 406 0400",
    "sg:postcode":"2222 AG",
    "sg:province":"South Holland",
    "wof:name":"Bv Bura",
    "wof:placetype":"venue"
},
  "geometry": {"coordinates":[4.4369778633,52.2024726868],"type":"Point"}
}