{
  "type": "Feature",
  "properties": {
    "addr:full":"Grevelingen 14 Zwijndrecht Zuid-Holland 3332 VA",
    "addr:housenumber":"14",
    "addr:postcode":"3332",
    "addr:street":"Grevelingen",
    "iso:country":"NL",
    "sg:address":"Grevelingen 14",
    "sg:city":"Zwijndrecht",
    "sg:orig_category":"Landbouwmachines Gh",
    "sg:phone":"+31 78 612 4001",
    "sg:postcode":"3332 VA",
    "sg:province":"Zuid-Holland",
    "wof:name":"Elmeco",
    "wof:placetype":"venue"
},
  "geometry": {"coordinates":[4.66578,51.822304],"type":"Point"}
}