{
  "type": "Feature",
  "properties": {
    "addr:full":"De Lairessestr 152 Amsterdam North Holland 1075 HL",
    "addr:housenumber":"152",
    "addr:postcode":"1075 hl",
    "iso:country":"NL",
    "sg:address":"De Lairessestr 152",
    "sg:city":"Amsterdam",
    "sg:orig_category":"Verzekeringen - Verzekeringskantoren",
    "sg:phone":"+31 20 662 1624",
    "sg:postcode":"1075 HL",
    "sg:province":"North Holland",
    "wof:name":"Spier & Zeegers",
    "wof:placetype":"venue"
},
  "geometry": {"coordinates":[4.867721,52.352657],"type":"Point"}
}