{
  "type": "Feature",
  "properties": {
    "iso:country":"NL",
    "sg:address":"Oostergouw 1",
    "sg:city":"Zwaag",
    "sg:orig_category":"Benzinestations And Brandstoffen",
    "sg:phone":"+31 229 273 504",
    "sg:postcode":"1689 AH",
    "sg:province":"Noord-Holland",
    "wof:name":"Grootveld Tankstation Zwaag",
    "wof:placetype":"venue"
},
  "geometry": {"coordinates":[5.060298,52.671837],"type":"Point"}
}