{
  "type": "Feature",
  "properties": {
    "addr:full":"Ten Darperwg 84 Wapse Provincie Drenthe 7983 KN",
    "addr:housenumber":"84",
    "addr:postcode":"7983 kn",
    "addr:street":"Ten;Provincie Drenthe",
    "iso:country":"NL",
    "sg:address":"Ten Darperwg 84",
    "sg:city":"Wapse",
    "sg:orig_category":"Verf En Lak - Fabrieken En Groothandel",
    "sg:phone":"+31 521 551 314",
    "sg:postcode":"7983 KN",
    "sg:province":"Provincie Drenthe",
    "wof:name":"Muco",
    "wof:placetype":"venue"
},
  "geometry": {"coordinates":[6.270742,52.859058],"type":"Point"}
}