{
  "type": "Feature",
  "properties": {
    "addr:full":"Schuilingsoord 8 198 Rotterdam Zuid-Holland 3079 NG",
    "addr:housenumber":"8 198",
    "addr:postcode":"3079 ng",
    "addr:street":"Schuilingsoord",
    "iso:country":"NL",
    "sg:address":"Schuilingsoord 8 198",
    "sg:city":"Rotterdam",
    "sg:orig_category":"Bejaarden - Verzorgingstehuizen",
    "sg:phone":"+31 10 482 0526",
    "sg:postcode":"3079 NG",
    "sg:province":"Zuid-Holland",
    "wof:name":"Schuilburgh",
    "wof:placetype":"venue"
},
  "geometry": {"coordinates":[4.549188,51.884129],"type":"Point"}
}