{
  "type": "Feature",
  "properties": {
    "addr:full":"Frits De Zwerverlaan 7 Hardenberg NL.08 7771 CV",
    "addr:housenumber":"7;nl.08",
    "addr:postcode":"7771 cv",
    "addr:street":"Frits De Zwerverlaan",
    "iso:country":"NL",
    "sg:address":"Frits De Zwerverlaan 7",
    "sg:city":"Hardenberg",
    "sg:classifiers":[
        {
            "category":"Education",
            "subcategory":"Preschool",
            "type":"Public Place"
        }
    ],
    "sg:phone":"+31 523 270 855",
    "sg:postcode":"7771 CV",
    "sg:province":"NL.08",
    "sg:tags":[
        "kleuteronderwijs",
        "basis-"
    ],
    "wof:name":"Gereformeerde Basisschool Ds. G. Doekes",
    "wof:placetype":"venue"
},
  "geometry": {"coordinates":[6.601504,52.56675],"type":"Point"}
}