{
  "type": "Feature",
  "properties": {
    "addr:full":"J J Viottastr 52 Amsterdam Noord-Holland 1071 JT",
    "addr:housenumber":"52",
    "addr:postcode":"1071 jt",
    "iso:country":"NL",
    "sg:address":"J J Viottastr 52",
    "sg:city":"Amsterdam",
    "sg:orig_category":"Adviesbureaus Bedrijfsorganisatie",
    "sg:phone":"+31 20 575 0750",
    "sg:postcode":"1071 JT",
    "sg:province":"Noord-Holland",
    "wof:name":"Gitp Int Bv",
    "wof:placetype":"venue"
},
  "geometry": {"coordinates":[4.8706,52.35276],"type":"Point"}
}