{
  "type": "Feature",
  "properties": {
    "addr:full":"Gorinchemsestr 60B Meerkerk Zuid-Holland 4231 BJ",
    "addr:housenumber":"60b",
    "addr:postcode":"4231 bj",
    "addr:street":"Gorinchemsestr",
    "iso:country":"NL",
    "sg:address":"Gorinchemsestr 60B",
    "sg:city":"Meerkerk",
    "sg:orig_category":"Hijswerktuigen",
    "sg:phone":"+31 183 353 843",
    "sg:postcode":"4231 BJ",
    "sg:province":"Zuid-Holland",
    "sg:website":"http://www.hijsmiddelen.nl",
    "wof:name":"Hijsmiddelen.Nl Bv",
    "wof:placetype":"venue"
},
  "geometry": {"coordinates":[4.998188,51.918465],"type":"Point"}
}