{
  "type": "Feature",
  "properties": {
    "addr:full":"Klompenmakerij 27 Barendrecht Zuid-Holland 2993 AJ",
    "addr:housenumber":"27",
    "addr:postcode":"2993 aj",
    "addr:street":"Klompenmakerij",
    "iso:country":"NL",
    "sg:address":"Klompenmakerij 27",
    "sg:city":"Barendrecht",
    "sg:orig_category":"Kinderopvang Behalve Thuis",
    "sg:phone":"+31 180 615 490",
    "sg:postcode":"2993 AJ",
    "sg:province":"Zuid-Holland",
    "wof:name":"K.D.V. De Kindertjesboom",
    "wof:placetype":"venue"
},
  "geometry": {"coordinates":[4.482806,51.856853],"type":"Point"}
}