{
  "type": "Feature",
  "properties": {
    "addr:full":"De Maas 25 Best Texas 5684 PL",
    "addr:housenumber":"25",
    "addr:postcode":"5684 pl",
    "addr:street":"De Maas",
    "iso:country":"NL",
    "sg:address":"De Maas 25",
    "sg:city":"Best",
    "sg:orig_category":"Bedrijfsmechanisatie En -Automatisering",
    "sg:phone":"+31 499 336 565",
    "sg:postcode":"5684 PL",
    "sg:province":"Texas",
    "sg:website":"http://www.a2-networks.nl",
    "wof:name":"A2 Networks Bv",
    "wof:placetype":"venue"
},
  "geometry": {"coordinates":[-101.618134,31.224251],"type":"Point"}
}