{
  "type": "Feature",
  "properties": {
    "iso:country":"NL",
    "sg:address":"Barlheze 43",
    "sg:city":"Zutphen",
    "sg:orig_category":"Zoetwaren - Fabrieken En Groothandel",
    "sg:phone":"+31 575 547 008",
    "sg:postcode":"7201 JV",
    "sg:province":"Gelderland",
    "wof:name":"Don Q Choc",
    "wof:placetype":"venue"
},
  "geometry": {"coordinates":[6.193387,52.142838],"type":"Point"}
}