{
  "type": "Feature",
  "properties": {
    "addr:full":"Barlheze 43 Zutphen Gelderland 7201 JV",
    "addr:housenumber":"43",
    "addr:postcode":"7201 jv",
    "addr:street":"Barlheze;Gelderland",
    "iso:country":"NL",
    "sg:address":"Barlheze 43",
    "sg:city":"Zutphen",
    "sg:orig_category":"Zoetwaren - Fabrieken En Groothandel",
    "sg:phone":"+31 575 547 008",
    "sg:postcode":"7201 JV",
    "sg:province":"Gelderland",
    "wof:name":"Don Q Choc",
    "wof:placetype":"venue"
},
  "geometry": {"coordinates":[6.193387,52.142838],"type":"Point"}
}