{
  "type": "Feature",
  "properties": {
    "addr:full":"Nieuwstad 14 Zutphen Gelderland 7201 NP",
    "addr:housenumber":"14",
    "addr:postcode":"7201 np",
    "addr:street":"Nieuwstad;Gelderland",
    "iso:country":"NL",
    "sg:address":"Nieuwstad 14",
    "sg:city":"Zutphen",
    "sg:orig_category":"Bloemen And Planten",
    "sg:phone":"+31 575 519 192",
    "sg:postcode":"7201 NP",
    "sg:province":"Gelderland",
    "wof:name":"Bloemtiek Sandra",
    "wof:placetype":"venue"
},
  "geometry": {"coordinates":[6.196757,52.143436],"type":"Point"}
}