{
  "type": "Feature",
  "properties": {
    "addr:full":"Hoogstr 8 S Gravenhage Zuid-Holland 2513 AR",
    "addr:housenumber":"8 s",
    "addr:postcode":"2513",
    "addr:street":"Hoogstr",
    "iso:country":"NL",
    "sg:address":"Hoogstr 8",
    "sg:city":"S Gravenhage",
    "sg:orig_category":"Herenkleding",
    "sg:phone":"+31 70 360 2755",
    "sg:postcode":"2513 AR",
    "sg:province":"Zuid-Holland",
    "wof:name":"Exclusive Brands",
    "wof:placetype":"venue"
},
  "geometry": {"coordinates":[4.30339,52.078442],"type":"Point"}
}