{
  "type": "Feature",
  "properties": {
    "addr:full":"Dorpsstraat 4 Hellevoetsluis Zuid-Holland 3223 BG",
    "addr:housenumber":"4",
    "addr:postcode":"3223",
    "addr:street":"Dorpsstraat",
    "iso:country":"NL",
    "sg:address":"Dorpsstraat 4",
    "sg:city":"Hellevoetsluis",
    "sg:orig_category":"Kappers",
    "sg:phone":"+31 181 324 238",
    "sg:postcode":"3223 BG",
    "sg:province":"Zuid-Holland",
    "wof:name":"Kapsalon Haar",
    "wof:placetype":"venue"
},
  "geometry": {"coordinates":[4.1454410553,51.8505744934],"type":"Point"}
}