{
  "type": "Feature",
  "properties": {
    "addr:full":"Rynsburgerwg 3 Leiden Zuid-Holland 2334 BA",
    "addr:housenumber":"3",
    "addr:postcode":"2334 ba",
    "addr:street":"Rynsburgerwg",
    "iso:country":"NL",
    "sg:address":"Rynsburgerwg 3",
    "sg:city":"Leiden",
    "sg:orig_category":"Verenigingen En Stichtingen",
    "sg:phone":"+31 71 515 6555",
    "sg:postcode":"2334 BA",
    "sg:province":"Zuid-Holland",
    "wof:name":"Canon Foundation In Europe",
    "wof:placetype":"venue"
},
  "geometry": {"coordinates":[4.482393,52.167706],"type":"Point"}
}