{
  "type": "Feature",
  "properties": {
    "addr:full":"Palestrinastr 3 Boxtel Noord-Brabant 5283 HT",
    "addr:housenumber":"3",
    "addr:postcode":"5283 ht",
    "addr:street":"Palestrinastr",
    "iso:country":"NL",
    "sg:address":"Palestrinastr 3",
    "sg:city":"Boxtel",
    "sg:orig_category":"Fotoreportages",
    "sg:phone":"+31 411 677 712",
    "sg:postcode":"5283 HT",
    "sg:province":"Noord-Brabant",
    "sg:website":"http://www.coverack.nl",
    "wof:name":"Marten Coverack",
    "wof:placetype":"venue"
},
  "geometry": {"coordinates":[5.343859,51.587826],"type":"Point"}
}