{
  "type": "Feature",
  "properties": {
    "addr:full":"L Ansinghstr 80 Amsterdam Noord-Holland 1072 RD",
    "addr:housenumber":"80",
    "addr:postcode":"1072 rd",
    "iso:country":"NL",
    "sg:address":"L Ansinghstr 80",
    "sg:city":"Amsterdam",
    "sg:orig_category":"Mensendieck - Oefentherapeuten",
    "sg:phone":"+31 20 664 9322",
    "sg:postcode":"1072 RD",
    "sg:province":"Noord-Holland",
    "sg:website":"http://www.ergomotion.nl",
    "wof:name":"Oude Rai De Pijp",
    "wof:placetype":"venue"
},
  "geometry": {"coordinates":[4.89323,52.349766],"type":"Point"}
}