{
  "type": "Feature",
  "properties": {
    "iso:country":"NL",
    "sg:address":"Ramshoorn 11",
    "sg:city":"Breda",
    "sg:orig_category":"Wegenbouw - Materialen",
    "sg:phone":"+31 76 542 1200",
    "sg:postcode":"4824 AG",
    "sg:province":"North Brabant",
    "wof:name":"Veluvine Bv",
    "wof:placetype":"venue"
},
  "geometry": {"coordinates":[4.7558321953,51.6122131348],"type":"Point"}
}