{
  "type": "Feature",
  "properties": {
    "addr:full":"Ramshoorn 11 Breda North Brabant 4824 AG",
    "addr:housenumber":"11",
    "addr:postcode":"4824",
    "addr:street":"Ramshoorn",
    "iso:country":"NL",
    "sg:address":"Ramshoorn 11",
    "sg:city":"Breda",
    "sg:orig_category":"Wegenbouw - Materialen",
    "sg:phone":"+31 76 542 1200",
    "sg:postcode":"4824 AG",
    "sg:province":"North Brabant",
    "wof:name":"Veluvine Bv",
    "wof:placetype":"venue"
},
  "geometry": {"coordinates":[4.7558321953,51.6122131348],"type":"Point"}
}