{
  "type": "Feature",
  "properties": {
    "addr:full":"Anjerstr 44 Goor NL.08 7471 JL",
    "addr:housenumber":"44;nl.08",
    "addr:postcode":"7471 jl",
    "addr:street":"Anjerstr",
    "iso:country":"NL",
    "sg:address":"Anjerstr 44",
    "sg:city":"Goor",
    "sg:orig_category":"Scholen Voor Basisonderwijs",
    "sg:phone":"+31 547 272 090",
    "sg:postcode":"7471 JL",
    "sg:province":"NL.08",
    "wof:name":"Constantijn Prot Chr, Pr",
    "wof:placetype":"venue"
},
  "geometry": {"coordinates":[6.589845,52.23143],"type":"Point"}
}