{
  "type": "Feature",
  "properties": {
    "addr:full":"Bontwerkerstr 2 Breda Noord-Brabant 4813 LL",
    "addr:housenumber":"2",
    "addr:postcode":"4813 ll",
    "addr:street":"Bontwerkerstr",
    "iso:country":"NL",
    "sg:address":"Bontwerkerstr 2",
    "sg:city":"Breda",
    "sg:orig_category":"Verenigingen En Stichtingen",
    "sg:phone":"+31 76 520 3735",
    "sg:postcode":"4813 LL",
    "sg:province":"Noord-Brabant",
    "wof:name":"Amarant, Sticht",
    "wof:placetype":"venue"
},
  "geometry": {"coordinates":[4.733229,51.573997],"type":"Point"}
}