{
  "type": "Feature",
  "properties": {
    "addr:full":"Ettenseweg 55 Ulft Gelderland 7071 AB",
    "addr:housenumber":"55",
    "addr:postcode":"7071 ab",
    "addr:street":"Ettenseweg;Gelderland",
    "iso:country":"NL",
    "sg:address":"Ettenseweg 55",
    "sg:city":"Ulft",
    "sg:orig_category":"Autokeuringen",
    "sg:phone":"+31 315 630 701",
    "sg:postcode":"7071 AB",
    "sg:province":"Gelderland",
    "wof:name":"Vof Kempers",
    "wof:placetype":"venue"
},
  "geometry": {"coordinates":[6.369982,51.902786],"type":"Point"}
}