{
  "type": "Feature",
  "properties": {
    "addr:full":"Iepln 35 Waddinxveen Zuid-Holland 2742 ZG",
    "addr:housenumber":"35",
    "addr:postcode":"2742 zg",
    "addr:street":"Iepln",
    "iso:country":"NL",
    "sg:address":"Iepln 35",
    "sg:city":"Waddinxveen",
    "sg:orig_category":"Verzekeringen - Verzekeringskantoren",
    "sg:phone":"+31 182 610 011",
    "sg:postcode":"2742 ZG",
    "sg:province":"Zuid-Holland",
    "wof:name":"Bruijstens Bv",
    "wof:placetype":"venue"
},
  "geometry": {"coordinates":[4.643792,52.044022],"type":"Point"}
}