{
  "type": "Feature",
  "properties": {
    "iso:country":"NL",
    "sg:address":"Dokweg 14",
    "sg:city":"Lelystad",
    "sg:orig_category":"Pleziervaartuigen And Reparatie",
    "sg:phone":"+31 320 261 444",
    "sg:postcode":"8243 PT",
    "sg:province":"Flevoland",
    "wof:name":"Rego Watersport Bv",
    "wof:placetype":"venue"
},
  "geometry": {"coordinates":[5.435298,52.497517],"type":"Point"}
}