{
  "type": "Feature",
  "properties": {
    "iso:country":"NL",
    "sg:address":"Groenewg 23",
    "sg:city":"Rotterdam",
    "sg:orig_category":"Boeken En Tijdschriften",
    "sg:phone":"+31 6 24894787",
    "sg:postcode":"3059 LC",
    "sg:province":"South Holland",
    "wof:name":"Himalaya",
    "wof:placetype":"venue"
},
  "geometry": {"coordinates":[4.596887,51.98428],"type":"Point"}
}