{
  "type": "Feature",
  "properties": {
    "addr:full":"Hanedoes 3 Oude Niedorp Noord-Holland 1734 NC",
    "addr:housenumber":"3",
    "addr:postcode":"1734 nc",
    "addr:street":"Hanedoes",
    "iso:country":"NL",
    "sg:address":"Hanedoes 3",
    "sg:city":"Oude Niedorp",
    "sg:orig_category":"Adviesbureaus Bedrijfsorganisatie",
    "sg:phone":"+31 226 413 608",
    "sg:postcode":"1734 NC",
    "sg:province":"Noord-Holland",
    "wof:name":"Bruinzeel",
    "wof:placetype":"venue"
},
  "geometry": {"coordinates":[4.895451,52.709797],"type":"Point"}
}