{
  "type": "Feature",
  "properties": {
    "iso:country":"NL",
    "sg:address":"Nyverheidsstr 4",
    "sg:city":"Kerkdriel",
    "sg:classifiers":[
        {
            "category":"Bus Charters",
            "type":"Transportation"
        }
    ],
    "sg:phone":"+31 418 633 674",
    "sg:postcode":"5331 PT",
    "sg:province":"Gelderland",
    "sg:tags":[
        "caravan"
    ],
    "wof:name":"Schutskooi, De",
    "wof:placetype":"venue"
},
  "geometry": {"coordinates":[5.325565,51.772701],"type":"Point"}
}