{
  "type": "Feature",
  "properties": {
    "addr:full":"Hooigracht 44 Leiden Zuid-Holland 2312 KV",
    "addr:housenumber":"44",
    "addr:postcode":"2312 kv",
    "addr:street":"Hooigracht",
    "iso:country":"NL",
    "sg:address":"Hooigracht 44",
    "sg:city":"Leiden",
    "sg:orig_category":"Muziekinstrumenten",
    "sg:phone":"+31 71 513 3445",
    "sg:postcode":"2312 KV",
    "sg:province":"Zuid-Holland",
    "wof:name":"Muziek Servaas-Strijk",
    "wof:placetype":"venue"
},
  "geometry": {"coordinates":[4.495605,52.158234],"type":"Point"}
}