{
  "type": "Feature",
  "properties": {
    "addr:full":"Vd Dussenstr 7 Rotterdam Zuid-Holland 3039 TA",
    "addr:housenumber":"7",
    "addr:postcode":"3039 ta",
    "iso:country":"NL",
    "sg:address":"Vd Dussenstr 7",
    "sg:city":"Rotterdam",
    "sg:orig_category":"Kunstenaars- Benodigdheden",
    "sg:phone":"+31 10 465 4528",
    "sg:postcode":"3039 TA",
    "sg:province":"Zuid-Holland",
    "sg:website":"http://www.xzillion.net",
    "wof:name":"Xzillion International Bv",
    "wof:placetype":"venue"
},
  "geometry": {"coordinates":[4.456505,51.931187],"type":"Point"}
}