{
  "type": "Feature",
  "properties": {
    "addr:full":"Lichtboei 16 Amstelveen Noord-Holland 1186 DE",
    "addr:housenumber":"16;1186",
    "addr:postcode":"de",
    "addr:street":"Lichtboei",
    "iso:country":"NL",
    "sg:address":"Lichtboei 16",
    "sg:city":"Amstelveen",
    "sg:orig_category":"Verzekeringen",
    "sg:phone":"+31 20 647 2745",
    "sg:postcode":"1186 DE",
    "sg:province":"Noord-Holland",
    "wof:name":"P. Van Der Mast Verzekeringen",
    "wof:placetype":"venue"
},
  "geometry": {"coordinates":[4.868049,52.275612],"type":"Point"}
}