{
  "type": "Feature",
  "properties": {
    "addr:full":"Doornenburg 54 Barneveld Gelderland 3772 ZP",
    "addr:housenumber":"54",
    "addr:postcode":"3772 zp",
    "addr:street":"Doornenburg;Gelderland",
    "iso:country":"NL",
    "sg:address":"Doornenburg 54",
    "sg:city":"Barneveld",
    "sg:orig_category":"Boekhouders",
    "sg:phone":"+31 342 400 580",
    "sg:postcode":"3772 ZP",
    "sg:province":"Gelderland",
    "wof:name":"Ad Point",
    "wof:placetype":"venue"
},
  "geometry": {"coordinates":[5.579508,52.130051],"type":"Point"}
}