{
  "type": "Feature",
  "properties": {
    "iso:country":"NL",
    "sg:address":"Melleveld 22",
    "sg:city":"Wouw",
    "sg:orig_category":"Voetbalverenigingen",
    "sg:phone":"+31 165 302 293",
    "sg:postcode":"4724 EL",
    "sg:province":"North Brabant",
    "wof:name":"Cluzona'74",
    "wof:placetype":"venue"
},
  "geometry": {"coordinates":[4.391889,51.521042],"type":"Point"}
}