{
  "type": "Feature",
  "properties": {
    "addr:full":"Robijnring 15 Eindhoven North Brabant 5629 GH",
    "addr:housenumber":"15",
    "addr:postcode":"5629 gh",
    "addr:street":"Robijnring",
    "iso:country":"NL",
    "sg:address":"Robijnring 15",
    "sg:city":"Eindhoven",
    "sg:orig_category":"Boekhouders",
    "sg:phone":"+31 40 290 3052",
    "sg:postcode":"5629 GH",
    "sg:province":"North Brabant",
    "wof:name":"P.J.A. Aarts",
    "wof:placetype":"venue"
},
  "geometry": {"coordinates":[5.459722,51.48558],"type":"Point"}
}