{
  "type": "Feature",
  "properties": {
    "addr:full":"Industrieweg 18 Zierikzee Zeeland 4301 RS",
    "addr:housenumber":"18",
    "addr:postcode":"4301 rs",
    "addr:street":"Industrieweg",
    "iso:country":"NL",
    "sg:address":"Industrieweg 18",
    "sg:city":"Zierikzee",
    "sg:orig_category":"Wegen And Sportterreinen",
    "sg:phone":"+31 111 450 184",
    "sg:postcode":"4301 RS",
    "sg:province":"Zeeland",
    "wof:name":"Aannemingsmaatschappij Van Gelder Bv",
    "wof:placetype":"venue"
},
  "geometry": {"coordinates":[3.9194509983,51.6440162659],"type":"Point"}
}