{
  "type": "Feature",
  "properties": {
    "iso:country":"NL",
    "sg:address":"Vaartweg 71",
    "sg:city":"Lelystad",
    "sg:orig_category":"Metaalwerken",
    "sg:phone":"+31 320 262 071",
    "sg:postcode":"8243 PD",
    "sg:province":"Flevoland",
    "wof:name":"Fa Van De Burgwal",
    "wof:placetype":"venue"
},
  "geometry": {"coordinates":[5.439716,52.499454],"type":"Point"}
}