{
  "type": "Feature",
  "properties": {
    "iso:country":"NL",
    "sg:address":"Groenlosewg 44",
    "sg:city":"Eibergen",
    "sg:classifiers":[
        {
            "category":"Sports & Exercise",
            "subcategory":"Stables",
            "type":"Entertainment"
        }
    ],
    "sg:phone":"+31 545 471 554",
    "sg:postcode":"7151 HG",
    "sg:province":"Gelderland",
    "sg:tags":[
        "maneges"
    ],
    "wof:name":"Nijhuis",
    "wof:placetype":"venue"
},
  "geometry": {"coordinates":[6.633609,52.071331],"type":"Point"}
}