{
  "type": "Feature",
  "properties": {
    "addr:full":"V Schagenstr 24 Elshout Noord-Brabant 5154 PG",
    "addr:housenumber":"24",
    "addr:postcode":"5154 pg",
    "addr:street":"Elshout",
    "iso:country":"NL",
    "sg:address":"V Schagenstr 24",
    "sg:city":"Elshout",
    "sg:orig_category":"Bliksembeveiliging",
    "sg:phone":"+31 416 370 067",
    "sg:postcode":"5154 PG",
    "sg:province":"Noord-Brabant",
    "wof:name":"Betonindustrie",
    "wof:placetype":"venue"
},
  "geometry": {"coordinates":[5.144005,51.702637],"type":"Point"}
}