{
  "type": "Feature",
  "properties": {
    "addr:full":"Dorpstraat 3 Groessen Gelderland 6923 AA",
    "addr:housenumber":"3",
    "addr:postcode":"6923 aa",
    "addr:street":"Dorpstraat;Gelderland",
    "iso:country":"NL",
    "sg:address":"Dorpstraat 3",
    "sg:city":"Groessen",
    "sg:orig_category":"Autokeuringen",
    "sg:phone":"+31 316 342 600",
    "sg:postcode":"6923 AA",
    "sg:province":"Gelderland",
    "wof:name":"P. Palm & Zn. Vof",
    "wof:placetype":"venue"
},
  "geometry": {"coordinates":[6.030208,51.93161],"type":"Point"}
}