{
  "type": "Feature",
  "properties": {
    "addr:full":"A Vd Neerstr 12 Enschede NL.08 7545 DE",
    "addr:housenumber":"12;7545",
    "addr:street":"A;De",
    "iso:country":"NL",
    "sg:address":"A Vd Neerstr 12",
    "sg:city":"Enschede",
    "sg:orig_category":"Verenigingen En Stichtingen",
    "sg:phone":"+31 53 432 4514",
    "sg:postcode":"7545 DE",
    "sg:province":"NL.08",
    "wof:name":"55+, Sticht",
    "wof:placetype":"venue"
},
  "geometry": {"coordinates":[6.861121,52.207935],"type":"Point"}
}