{
  "type": "Feature",
  "properties": {
    "addr:full":"Obrechtstr 10 Dordrecht South Holland 3314 EL",
    "addr:housenumber":"10",
    "addr:postcode":"3314 el",
    "addr:street":"Obrechtstr",
    "iso:country":"NL",
    "sg:address":"Obrechtstr 10",
    "sg:city":"Dordrecht",
    "sg:orig_category":"Verzekeringen - Verzekeringskantoren",
    "sg:phone":"+31 78 614 8707",
    "sg:postcode":"3314 EL",
    "sg:province":"South Holland",
    "wof:name":"Kelder, W W",
    "wof:placetype":"venue"
},
  "geometry": {"coordinates":[4.656643,51.80336],"type":"Point"}
}