{
  "type": "Feature",
  "properties": {
    "addr:full":"Bazuinstraat 64 Purmerend Noord-Holland 1443 JG",
    "addr:housenumber":"64",
    "addr:postcode":"1443 jg",
    "addr:street":"Bazuinstraat",
    "iso:country":"NL",
    "sg:address":"Bazuinstraat 64",
    "sg:city":"Purmerend",
    "sg:orig_category":"Schoonheidssalons",
    "sg:phone":"+31 299 426 284",
    "sg:postcode":"1443 JG",
    "sg:province":"Noord-Holland",
    "wof:name":"Salon Papillon Trijnie Versluis",
    "wof:placetype":"venue"
},
  "geometry": {"coordinates":[4.973207,52.50853],"type":"Point"}
}