{
  "type": "Feature",
  "properties": {
    "addr:full":"Rooseveltln 61 Delft South Holland 2625 GM",
    "addr:housenumber":"61",
    "addr:postcode":"2625 gm",
    "addr:street":"Rooseveltln",
    "iso:country":"NL",
    "sg:address":"Rooseveltln 61",
    "sg:city":"Delft",
    "sg:orig_category":"Boekbinderijen",
    "sg:phone":"+31 15 256 2606",
    "sg:postcode":"2625 GM",
    "sg:province":"South Holland",
    "wof:name":"Ambachtelijke Boeckbinderij",
    "wof:placetype":"venue"
},
  "geometry": {"coordinates":[4.349189,51.989666],"type":"Point"}
}