{
  "type": "Feature",
  "properties": {
    "addr:full":"Markeweg 30 Noord Sleen Provincie Drenthe 7846 AH",
    "addr:housenumber":"30",
    "addr:postcode":"7846 ah",
    "addr:street":"Markeweg;Drenthe",
    "iso:country":"NL",
    "sg:address":"Markeweg 30",
    "sg:city":"Noord Sleen",
    "sg:orig_category":"Granen, Zaden And Diervoeders Gh",
    "sg:phone":"+31 591 362 360",
    "sg:postcode":"7846 AH",
    "sg:province":"Provincie Drenthe",
    "wof:name":"Schepers Fourage- En Kunstmesthandel",
    "wof:placetype":"venue"
},
  "geometry": {"coordinates":[6.803175,52.787708],"type":"Point"}
}