{
  "type": "Feature",
  "properties": {
    "addr:full":"Kruisstr 24 Tegelen Limburg 5931 RB",
    "addr:housenumber":"24",
    "addr:postcode":"5931 rb",
    "addr:street":"Kruisstr",
    "iso:country":"NL",
    "sg:address":"Kruisstr 24",
    "sg:city":"Tegelen",
    "sg:orig_category":"Autorijscholen",
    "sg:phone":"+31 77 373 1027",
    "sg:postcode":"5931 RB",
    "sg:province":"Limburg",
    "wof:name":"Wilbers, H J",
    "wof:placetype":"venue"
},
  "geometry": {"coordinates":[6.132336,51.336971],"type":"Point"}
}