{
  "type": "Feature",
  "properties": {
    "iso:country":"NL",
    "sg:address":"Rielant 59",
    "sg:city":"Monnickendam",
    "sg:orig_category":"Adviesbureaus Bedrijfsorganisatie",
    "sg:phone":"+31 299 654 171",
    "sg:postcode":"1141 RE",
    "sg:province":"North Holland",
    "wof:name":"Holthuis",
    "wof:placetype":"venue"
},
  "geometry": {"coordinates":[5.037259,52.447308],"type":"Point"}
}