{
  "type": "Feature",
  "properties": {
    "addr:full":"Rozenstr 43 Colynsplaat Zeeland 4486 CE",
    "addr:housenumber":"43",
    "addr:postcode":"4486 ce",
    "addr:street":"Rozenstr;Zeeland",
    "iso:country":"NL",
    "sg:address":"Rozenstr 43",
    "sg:city":"Colynsplaat",
    "sg:orig_category":"Woningbouw- Verenigingen En -Stichtingen",
    "sg:phone":"+31 113 695 020",
    "sg:postcode":"4486 CE",
    "sg:province":"Zeeland",
    "wof:name":"Woonzorg Nederland",
    "wof:placetype":"venue"
},
  "geometry": {"coordinates":[3.8510649204,51.5962677002],"type":"Point"}
}