{
  "type": "Feature",
  "properties": {
    "iso:country":"NL",
    "sg:address":"Bennebroekerdk 46B",
    "sg:city":"Zwaanshoek",
    "sg:orig_category":"Grafisch Ontwerpers",
    "sg:phone":"+31 23 584 7948",
    "sg:postcode":"2136 LV",
    "sg:province":"Noord-Holland",
    "wof:name":"Vjoew Design",
    "wof:placetype":"venue"
},
  "geometry": {"coordinates":[24.533529,57.091541],"type":"Point"}
}