{
  "type": "Feature",
  "properties": {
    "addr:full":"Engelberterwg 13 Groningen Groningen 9723 EH",
    "addr:housenumber":"13",
    "addr:postcode":"9723 eh",
    "addr:street":"Engelberterwg",
    "iso:country":"NL",
    "sg:address":"Engelberterwg 13",
    "sg:city":"Groningen",
    "sg:orig_category":"Bedrijfsopleidingen",
    "sg:phone":"+31 50 541 4015",
    "sg:postcode":"9723 EH",
    "sg:province":"Groningen",
    "wof:name":"Hebel & Von Hebel Bv, Von",
    "wof:placetype":"venue"
},
  "geometry": {"coordinates":[6.641564,53.213581],"type":"Point"}
}