{
  "type": "Feature",
  "properties": {
    "addr:full":"V Boemelln 31 S Hertogenbosch Noord-Brabant 5237 KA",
    "addr:housenumber":"31",
    "addr:postcode":"5237 ka",
    "addr:street":"S",
    "iso:country":"NL",
    "sg:address":"V Boemelln 31",
    "sg:city":"S Hertogenbosch",
    "sg:orig_category":"Adviesbureaus Bedrijfsorganisatie",
    "sg:phone":"+31 73 644 4560",
    "sg:postcode":"5237 KA",
    "sg:province":"Noord-Brabant",
    "wof:name":"Irwin De Jong, Mr",
    "wof:placetype":"venue"
},
  "geometry": {"coordinates":[5.2886,51.730911],"type":"Point"}
}