{
  "type": "Feature",
  "properties": {
    "addr:full":"Wildforstlaan 28 Epe Gelderland 8162 ER",
    "addr:housenumber":"28",
    "addr:postcode":"8162 er",
    "addr:street":"Wildforstlaan;Gelderland",
    "iso:country":"NL",
    "sg:address":"Wildforstlaan 28",
    "sg:city":"Epe",
    "sg:orig_category":"Bloemen And Planten",
    "sg:phone":"+31 578 613 986",
    "sg:postcode":"8162 ER",
    "sg:province":"Gelderland",
    "wof:name":"Witteveen`S Bloemen",
    "wof:placetype":"venue"
},
  "geometry": {"coordinates":[5.981945,52.351509],"type":"Point"}
}