{
  "type": "Feature",
  "properties": {
    "iso:country":"NL",
    "sg:address":"Wildforstlaan 28",
    "sg:city":"Epe",
    "sg:orig_category":"Bloemen And Planten",
    "sg:phone":"+31 578 613 986",
    "sg:postcode":"8162 ER",
    "sg:province":"Gelderland",
    "wof:name":"Witteveen`S Bloemen",
    "wof:placetype":"venue"
},
  "geometry": {"coordinates":[5.981945,52.351509],"type":"Point"}
}