{
  "type": "Feature",
  "properties": {
    "iso:country":"NL",
    "sg:address":"Monseigneur Vranckenpln 5",
    "sg:city":"Maastricht",
    "sg:classifiers":[
        {
            "category":"Fast Food",
            "type":"Food & Drink"
        }
    ],
    "sg:phone":"+31 43 361 0001",
    "sg:postcode":"6213 HL",
    "sg:province":"Limburg",
    "sg:tags":[
        "afhaal",
        "restaurant"
    ],
    "wof:name":"Friture-Snackbar De Smickel",
    "wof:placetype":"venue"
},
  "geometry": {"coordinates":[5.654151,50.834435],"type":"Point"}
}