{
  "type": "Feature",
  "properties": {
    "addr:full":"Oofthegge 6 Maastricht Limburg 6225 KD",
    "addr:housenumber":"6",
    "addr:postcode":"6225 kd",
    "addr:street":"Oofthegge",
    "iso:country":"NL",
    "sg:address":"Oofthegge 6",
    "sg:city":"Maastricht",
    "sg:orig_category":"Oud Metaal",
    "sg:phone":"+31 43 362 2439",
    "sg:postcode":"6225 KD",
    "sg:province":"Limburg",
    "wof:name":"Franssen, J K A",
    "wof:placetype":"venue"
},
  "geometry": {"coordinates":[5.7380948067,50.8606681824],"type":"Point"}
}