{
  "type": "Feature",
  "properties": {
    "iso:country":"NL",
    "sg:address":"Unoln 100A",
    "sg:city":"Heerlen",
    "sg:orig_category":"Autoschade- Herstelbedrijven",
    "sg:phone":"+31 45 523 1050",
    "sg:postcode":"6413 CT",
    "sg:province":"Limburg",
    "wof:name":"Kan, Roy Van",
    "wof:placetype":"venue"
},
  "geometry": {"coordinates":[5.98098,50.885506],"type":"Point"}
}