{
  "type": "Feature",
  "properties": {
    "iso:country":"NL",
    "sg:address":"Thorbeckeplein 14",
    "sg:city":"Alphen Aan Den Rijn",
    "sg:orig_category":"Werving And Selectie Van Tijdelijk Personeel And Uitzendkantoren",
    "sg:phone":"+31 172 428 480",
    "sg:postcode":"2406 CG",
    "sg:province":"Zuid-Holland",
    "wof:name":"Randstad Transportdiensten",
    "wof:placetype":"venue"
},
  "geometry": {"coordinates":[4.6645469666,52.1311683655],"type":"Point"}
}