{
  "type": "Feature",
  "properties": {
    "addr:full":"Oude Asserstr 30B Vries Drenthe 9481 BL",
    "addr:housenumber":"30b",
    "addr:postcode":"9481 bl",
    "addr:street":"Oude Asserstr",
    "iso:country":"NL",
    "sg:address":"Oude Asserstr 30B",
    "sg:city":"Vries",
    "sg:orig_category":"Hypotheken",
    "sg:phone":"+31 592 543 868",
    "sg:postcode":"9481 BL",
    "sg:province":"Drenthe",
    "wof:name":"Hypotheekgids, De",
    "wof:placetype":"venue"
},
  "geometry": {"coordinates":[-85.944946,42.811916],"type":"Point"}
}