{
  "type": "Feature",
  "properties": {
    "addr:full":"Wilhelminastr 184 Amsterdam North Holland 1054 WT",
    "addr:housenumber":"184",
    "addr:postcode":"1054 wt",
    "addr:street":"Wilhelminastr",
    "iso:country":"NL",
    "sg:address":"Wilhelminastr 184",
    "sg:city":"Amsterdam",
    "sg:orig_category":"Fotoreportages",
    "sg:phone":"+31 20 618 4972",
    "sg:postcode":"1054 WT",
    "sg:province":"North Holland",
    "wof:name":"Steenmeijer, J W",
    "wof:placetype":"venue"
},
  "geometry": {"coordinates":[4.859367,52.360752],"type":"Point"}
}