{
  "type": "Feature",
  "properties": {
    "addr:full":"Europaweg 118 Nieuw Schoonebeek Provincie Drenthe 7766 AP",
    "addr:housenumber":"118",
    "addr:postcode":"7766 ap",
    "addr:street":"Europaweg;Nieuw Schoonebeek Provincie Drenthe",
    "iso:country":"NL",
    "sg:address":"Europaweg 118",
    "sg:city":"Nieuw Schoonebeek",
    "sg:orig_category":"Autorijscholen",
    "sg:phone":"+31 524 542 392",
    "sg:postcode":"7766 AP",
    "sg:province":"Provincie Drenthe",
    "wof:name":"Schulte",
    "wof:placetype":"venue"
},
  "geometry": {"coordinates":[6.983725,52.646973],"type":"Point"}
}