{
  "type": "Feature",
  "properties": {
    "addr:full":"De Waarden 387 Zutphen Gelderland 7206 GX",
    "addr:housenumber":"387",
    "addr:postcode":"7206 gx",
    "addr:street":"De Waarden;Gelderland",
    "iso:country":"NL",
    "sg:address":"De Waarden 387",
    "sg:city":"Zutphen",
    "sg:orig_category":"Adviesbureaus Personeel",
    "sg:phone":"+31 575 574 271",
    "sg:postcode":"7206 GX",
    "sg:province":"Gelderland",
    "wof:name":"Netwerk Feiken",
    "wof:placetype":"venue"
},
  "geometry": {"coordinates":[6.193575,52.127621],"type":"Point"}
}