{
  "type": "Feature",
  "properties": {
    "addr:full":"Oranjehof 27 Leerdam Zuid-Holland 4141 GC",
    "addr:housenumber":"27",
    "addr:postcode":"4141 gc",
    "addr:street":"Oranjehof",
    "iso:country":"NL",
    "sg:address":"Oranjehof 27",
    "sg:city":"Leerdam",
    "sg:orig_category":"Bejaarden - Verzorgingstehuizen",
    "sg:phone":"+31 345 613 841",
    "sg:postcode":"4141 GC",
    "sg:province":"Zuid-Holland",
    "wof:name":"Emmahuis, Kon",
    "wof:placetype":"venue"
},
  "geometry": {"coordinates":[5.104852,51.891544],"type":"Point"}
}