{
  "type": "Feature",
  "properties": {
    "addr:full":"H Heyermansstr 89 Terneuzen Zeeland 4532 GK",
    "addr:housenumber":"89",
    "addr:postcode":"4532 gk",
    "iso:country":"NL",
    "sg:address":"H Heyermansstr 89",
    "sg:city":"Terneuzen",
    "sg:orig_category":"Vertaalbureaus",
    "sg:phone":"+31 115 648 186",
    "sg:postcode":"4532 GK",
    "sg:province":"Zeeland",
    "wof:name":"Avetaal",
    "wof:placetype":"venue"
},
  "geometry": {"coordinates":[3.827559,51.338146],"type":"Point"}
}