{
  "type": "Feature",
  "properties": {
    "addr:full":"De Meren 3 Oudenbosch North Brabant 4731 WB",
    "addr:housenumber":"3",
    "addr:postcode":"4731 wb",
    "addr:street":"De Meren",
    "iso:country":"NL",
    "sg:address":"De Meren 3",
    "sg:city":"Oudenbosch",
    "sg:orig_category":"Kunststoffen - Fabrieken En Groothandel",
    "sg:phone":"+31 165 315 644",
    "sg:postcode":"4731 WB",
    "sg:province":"North Brabant",
    "wof:name":"Brand",
    "wof:placetype":"venue"
},
  "geometry": {"coordinates":[4.53264,51.582024],"type":"Point"}
}