{
  "type": "Feature",
  "properties": {
    "addr:full":"Dinxperlosestraatweg 60 Aalten Gelderland 7122 AH",
    "addr:housenumber":"60",
    "addr:postcode":"7122 ah",
    "addr:street":"Dinxperlosestraatweg;Gelderland",
    "iso:country":"NL",
    "sg:address":"Dinxperlosestraatweg 60",
    "sg:city":"Aalten",
    "sg:orig_category":"Zuivelproducten And Spijsoli?n Gh",
    "sg:phone":"+31 543 476 251",
    "sg:postcode":"7122 AH",
    "sg:province":"Gelderland",
    "wof:name":"Prinzen Machines Bv",
    "wof:placetype":"venue"
},
  "geometry": {"coordinates":[6.576233,51.915066],"type":"Point"}
}