{
  "type": "Feature",
  "properties": {
    "addr:full":"Gerberaln 49 Naaldwyk Zuid-Holland 2671 KB",
    "addr:housenumber":"49",
    "addr:postcode":"2671 kb",
    "addr:street":"Gerberaln",
    "iso:country":"NL",
    "sg:address":"Gerberaln 49",
    "sg:city":"Naaldwyk",
    "sg:orig_category":"Wasmachines En Wasdrogers - Onderhoud En Reparatie",
    "sg:phone":"+31 174 629 496",
    "sg:postcode":"2671 KB",
    "sg:province":"Zuid-Holland",
    "wof:name":"Bos, J Van Den",
    "wof:placetype":"venue"
},
  "geometry": {"coordinates":[4.2052488327,51.9913978577],"type":"Point"}
}