{
  "type": "Feature",
  "properties": {
    "addr:full":"Twellosewg 12 Deventer Overijssel 7419 BJ",
    "addr:housenumber":"12",
    "addr:postcode":"7419 bj",
    "addr:street":"Twellosewg",
    "iso:country":"NL",
    "sg:address":"Twellosewg 12",
    "sg:city":"Deventer",
    "sg:orig_category":"Psychologen",
    "sg:phone":"+31 570 644 309",
    "sg:postcode":"7419 BJ",
    "sg:province":"Overijssel",
    "sg:website":"http://www.spreekuurpsycholoog.nl",
    "wof:name":"Suijkerbuijk, Mw Drs I",
    "wof:placetype":"venue"
},
  "geometry": {"coordinates":[6.145165,52.247433],"type":"Point"}
}