{
  "type": "Feature",
  "properties": {
    "addr:full":"Jacobijnerstr 8 Groningen Groningen 9712 HZ",
    "addr:housenumber":"8",
    "addr:postcode":"9712 hz",
    "addr:street":"Jacobijnerstr",
    "iso:country":"NL",
    "sg:address":"Jacobijnerstr 8",
    "sg:city":"Groningen",
    "sg:orig_category":"Fietsen En Bromfietsen",
    "sg:phone":"+31 50 313 8959",
    "sg:postcode":"9712 HZ",
    "sg:province":"Groningen",
    "wof:name":"Oostindier, Jan",
    "wof:placetype":"venue"
},
  "geometry": {"coordinates":[6.567169,53.220482],"type":"Point"}
}