{
  "type": "Feature",
  "properties": {
    "addr:full":"Hoofdstraat 213 Hoogeveen Provincie Drenthe 7902 EH",
    "addr:housenumber":"213",
    "addr:postcode":"7902 eh",
    "addr:street":"Hoofdstraat;Provincie",
    "iso:country":"NL",
    "sg:address":"Hoofdstraat 213",
    "sg:city":"Hoogeveen",
    "sg:orig_category":"Schoenen",
    "sg:phone":"+31 528 233 862",
    "sg:postcode":"7902 EH",
    "sg:province":"Provincie Drenthe",
    "wof:name":"Helder Schoenen",
    "wof:placetype":"venue"
},
  "geometry": {"coordinates":[6.478068,52.7215],"type":"Point"}
}