{
  "type": "Feature",
  "properties": {
    "addr:full":"Prinsengr 489 Amsterdam Noord-Holland 1016 HP",
    "addr:housenumber":"489",
    "addr:postcode":"1016 hp",
    "iso:country":"NL",
    "sg:address":"Prinsengr 489",
    "sg:city":"Amsterdam",
    "sg:orig_category":"Kappers",
    "sg:phone":"+31 20 420 6412",
    "sg:postcode":"1016 HP",
    "sg:province":"Noord-Holland",
    "wof:name":"Shampoo Planet",
    "wof:placetype":"venue"
},
  "geometry": {"coordinates":[4.883151,52.369385],"type":"Point"}
}