{
  "type": "Feature",
  "properties": {
    "addr:full":"Rijksweg 164 Dorst North Brabant 4849 BS",
    "addr:housenumber":"164",
    "addr:postcode":"4849 bs",
    "addr:street":"Rijksweg",
    "iso:country":"NL",
    "sg:address":"Rijksweg 164",
    "sg:city":"Dorst",
    "sg:orig_category":"Bloemen And Planten",
    "sg:phone":"+31 161 411 210",
    "sg:postcode":"4849 BS",
    "sg:province":"North Brabant",
    "wof:name":"J. Kerremans",
    "wof:placetype":"venue"
},
  "geometry": {"coordinates":[4.863985,51.588364],"type":"Point"}
}