{
  "type": "Feature",
  "properties": {
    "addr:full":"De Hg Hofstr 6 Oosterhout Gld Gelderland 6678 AH",
    "addr:housenumber":"6",
    "addr:postcode":"6678 ah",
    "addr:street":"De;Hofstr;Gld Gelderland",
    "iso:country":"NL",
    "sg:address":"De Hg Hofstr 6",
    "sg:city":"Oosterhout Gld",
    "sg:classifiers":[
        {
            "category":"Personal",
            "subcategory":"Nail Salon",
            "type":"Services"
        }
    ],
    "sg:phone":"+31 481 481 954",
    "sg:postcode":"6678 AH",
    "sg:province":"Gelderland",
    "sg:tags":[
        "pedicure"
    ],
    "wof:name":"Giesen",
    "wof:placetype":"venue"
},
  "geometry": {"coordinates":[5.828742,51.883209],"type":"Point"}
}