{
  "type": "Feature",
  "properties": {
    "addr:full":"Troelstrastraat 30 Culemborg Gelderland 4102 EV",
    "addr:housenumber":"30",
    "addr:postcode":"4102 ev",
    "addr:street":"Troelstrastraat;Gelderland",
    "iso:country":"NL",
    "sg:address":"Troelstrastraat 30",
    "sg:city":"Culemborg",
    "sg:orig_category":"Goederenvervoer Over De Weg",
    "sg:phone":"+31 345 510 490",
    "sg:postcode":"4102 EV",
    "sg:province":"Gelderland",
    "wof:name":"J.C. Van Maanen",
    "wof:placetype":"venue"
},
  "geometry": {"coordinates":[5.240041,51.950859],"type":"Point"}
}