{
  "type": "Feature",
  "properties": {
    "iso:country":"NL",
    "sg:address":"Mercurius 9",
    "sg:city":"Oosterhout Nb",
    "sg:orig_category":"Boekhouders",
    "sg:phone":"+31 162 433 021",
    "sg:postcode":"4907 CD",
    "sg:province":"North Brabant",
    "wof:name":"Administratiekantoor Boudewijns",
    "wof:placetype":"venue"
},
  "geometry": {"coordinates":[4.863872,51.654709],"type":"Point"}
}