{
  "type": "Feature",
  "properties": {
    "addr:full":"Chrysantenstraat 45 Aalsmeer North Holland 1431 BM",
    "addr:housenumber":"45",
    "addr:postcode":"1431 bm",
    "addr:street":"Chrysantenstraat",
    "iso:country":"NL",
    "sg:address":"Chrysantenstraat 45",
    "sg:city":"Aalsmeer",
    "sg:classifiers":[
        {
            "category":"Fast Food",
            "type":"Food & Drink"
        }
    ],
    "sg:phone":"+31 297 324 789",
    "sg:postcode":"1431 BM",
    "sg:province":"North Holland",
    "sg:tags":[
        "afhaal",
        "restaurant"
    ],
    "wof:name":"Lunchroom Pannekoekenhuis Marcon",
    "wof:placetype":"venue"
},
  "geometry": {"coordinates":[4.751055,52.269749],"type":"Point"}
}