{
  "type": "Feature",
  "properties": {
    "addr:full":"Develwg 18 Zwyndrecht South Holland 3333 LA",
    "addr:housenumber":"18",
    "addr:postcode":"3333 la",
    "addr:street":"Develwg",
    "iso:country":"NL",
    "sg:address":"Develwg 18",
    "sg:city":"Zwyndrecht",
    "sg:orig_category":"Adviesbureaus Bedrijfsorganisatie",
    "sg:phone":"+31 78 619 8466",
    "sg:postcode":"3333 LA",
    "sg:province":"South Holland",
    "sg:website":"http://www.pkn.nl",
    "wof:name":"Interim-En Projektmanagement Bv",
    "wof:placetype":"venue"
},
  "geometry": {"coordinates":[4.623998,51.811451],"type":"Point"}
}