{
  "type": "Feature",
  "properties": {
    "addr:full":"Kuppersweg 29 Haarlem North Holland 2031 EA",
    "addr:housenumber":"29",
    "addr:postcode":"2031 ea",
    "addr:street":"Kuppersweg",
    "iso:country":"NL",
    "sg:address":"Kuppersweg 29",
    "sg:city":"Haarlem",
    "sg:orig_category":"Verhuisdiensten",
    "sg:phone":"+31 23 542 3110",
    "sg:postcode":"2031 EA",
    "sg:province":"North Holland",
    "sg:website":"http://www.move4u.com",
    "wof:name":"Move 4 U !",
    "wof:placetype":"venue"
},
  "geometry": {"coordinates":[4.654096,52.39241],"type":"Point"}
}