{
  "type": "Feature",
  "properties": {
    "addr:full":"Oudkerkhof 8 Utrecht Utrecht 3512 GK",
    "addr:housenumber":"8",
    "addr:postcode":"3512 gk",
    "addr:street":"Oudkerkhof",
    "iso:country":"NL",
    "sg:address":"Oudkerkhof 8",
    "sg:city":"Utrecht",
    "sg:orig_category":"Mode-Artikelen Dames En Heren",
    "sg:phone":"+31 30 296 0683",
    "sg:postcode":"3512 GK",
    "sg:province":"Utrecht",
    "wof:name":"Players Collections",
    "wof:placetype":"venue"
},
  "geometry": {"coordinates":[5.120708,52.091827],"type":"Point"}
}