{
  "type": "Feature",
  "properties": {
    "addr:full":"Karolingerswg 122 Wyk By Duurstede Utrecht 3962 AL",
    "addr:housenumber":"122",
    "addr:postcode":"3962 al",
    "addr:street":"Wyk By Duurstede",
    "iso:country":"NL",
    "sg:address":"Karolingerswg 122",
    "sg:city":"Wyk By Duurstede",
    "sg:orig_category":"Verhuizingen",
    "sg:phone":"+31 343 461 211",
    "sg:postcode":"3962 AL",
    "sg:province":"Utrecht",
    "sg:website":"http://www.marbafun.nl",
    "wof:name":"Marbafun",
    "wof:placetype":"venue"
},
  "geometry": {"coordinates":[5.33492,51.976559],"type":"Point"}
}