{
  "type": "Feature",
  "properties": {
    "addr:full":"Van Bruhezedal 28 Valkenswaard North Brabant 5551 EW",
    "addr:housenumber":"28",
    "addr:postcode":"5551 ew",
    "addr:street":"Van Bruhezedal",
    "iso:country":"NL",
    "sg:address":"Van Bruhezedal 28",
    "sg:city":"Valkenswaard",
    "sg:orig_category":"Banken And Kredietinstellingen",
    "sg:phone":"+31 40 207 1200",
    "sg:postcode":"5551 EW",
    "sg:province":"North Brabant",
    "wof:name":"Rabobank",
    "wof:placetype":"venue"
},
  "geometry": {"coordinates":[5.431054,51.355946],"type":"Point"}
}