{
  "type": "Feature",
  "properties": {
    "addr:full":"Meeuwerdensestr 2 Herveld Gelderland 6674 MB",
    "addr:housenumber":"2",
    "addr:postcode":"6674 mb",
    "addr:street":"Meeuwerdensestr;Gelderland",
    "iso:country":"NL",
    "sg:address":"Meeuwerdensestr 2",
    "sg:city":"Herveld",
    "sg:orig_category":"Directmail",
    "sg:phone":"+31 488 470 625",
    "sg:postcode":"6674 MB",
    "sg:province":"Gelderland",
    "sg:website":"http://www.zcard.com",
    "wof:name":"Z-Card Benelux",
    "wof:placetype":"venue"
},
  "geometry": {"coordinates":[5.741242,51.921242],"type":"Point"}
}