{
  "type": "Feature",
  "properties": {
    "addr:full":"Vierlingsbeekseweg 17 Overloon Noord-Brabant 5825 AS",
    "addr:housenumber":"17",
    "addr:postcode":"5825 as",
    "addr:street":"Vierlingsbeekseweg",
    "iso:country":"NL",
    "sg:address":"Vierlingsbeekseweg 17",
    "sg:city":"Overloon",
    "sg:orig_category":"Huishoudapparatuur, Televisies And Radio'S",
    "sg:phone":"+31 478 641 683",
    "sg:postcode":"5825 AS",
    "sg:province":"Noord-Brabant",
    "wof:name":"M. Peeters",
    "wof:placetype":"venue"
},
  "geometry": {"coordinates":[5.95036,51.572182],"type":"Point"}
}