{
  "type": "Feature",
  "properties": {
    "addr:full":"Noordstr 80 Tilburg Noord-Brabant 5038 EK",
    "addr:housenumber":"80",
    "addr:postcode":"5038 ek",
    "addr:street":"Noordstr",
    "iso:country":"NL",
    "sg:address":"Noordstr 80",
    "sg:city":"Tilburg",
    "sg:orig_category":"Verenigingen En Stichtingen",
    "sg:phone":"+31 13 532 1436",
    "sg:postcode":"5038 EK",
    "sg:province":"Noord-Brabant",
    "sg:website":"http://www.paletweb.nl",
    "wof:name":"Palet Midden-Brabant",
    "wof:placetype":"venue"
},
  "geometry": {"coordinates":[5.07758,51.556911],"type":"Point"}
}