{
  "type": "Feature",
  "properties": {
    "addr:full":"Navoln 12 Stadskanaal Groningen 9501 VJ",
    "addr:housenumber":"12",
    "addr:postcode":"9501 vj",
    "addr:street":"Navoln",
    "iso:country":"NL",
    "sg:address":"Navoln 12",
    "sg:city":"Stadskanaal",
    "sg:orig_category":"Bloemen En Planten",
    "sg:phone":"+31 599 610 030",
    "sg:postcode":"9501 VJ",
    "sg:province":"Groningen",
    "wof:name":"Alders",
    "wof:placetype":"venue"
},
  "geometry": {"coordinates":[6.959475,52.984375],"type":"Point"}
}