{
  "type": "Feature",
  "properties": {
    "addr:full":"St Jorisstr 65 Amersfoort Utrecht 3811 DH",
    "addr:housenumber":"65",
    "addr:postcode":"3811 dh",
    "iso:country":"NL",
    "sg:address":"St Jorisstr 65",
    "sg:city":"Amersfoort",
    "sg:orig_category":"Huishoudelijke Apparaten En Artikelen",
    "sg:phone":"+31 33 445 0785",
    "sg:postcode":"3811 DH",
    "sg:province":"Utrecht",
    "wof:name":"Blokker Bv",
    "wof:placetype":"venue"
},
  "geometry": {"coordinates":[5.38458,52.154724],"type":"Point"}
}