{
  "type": "Feature",
  "properties": {
    "addr:full":"Gawege 10 Waarde Zeeland 4414 NB",
    "addr:housenumber":"10",
    "addr:postcode":"4414 nb",
    "addr:street":"Gawege",
    "iso:country":"NL",
    "sg:address":"Gawege 10",
    "sg:city":"Waarde",
    "sg:orig_category":"Fruit And Groenten Gh",
    "sg:phone":"+31 113 501 658",
    "sg:postcode":"4414 NB",
    "sg:province":"Zeeland",
    "wof:name":"Franje Agrarische Produkten Bv",
    "wof:placetype":"venue"
},
  "geometry": {"coordinates":[4.104119,51.418941],"type":"Point"}
}