{
  "type": "Feature",
  "properties": {
    "addr:full":"Zydesngl 26 Leidschendam South Holland 2261 CA",
    "addr:housenumber":"26",
    "addr:postcode":"2261 ca",
    "addr:street":"Zydesngl",
    "iso:country":"NL",
    "sg:address":"Zydesngl 26",
    "sg:city":"Leidschendam",
    "sg:orig_category":"Verenigingen En Stichtingen",
    "sg:phone":"+31 70 327 5258",
    "sg:postcode":"2261 CA",
    "sg:province":"South Holland",
    "sg:website":"http://www.fietsersbond.nl",
    "wof:name":"Fietsersbond",
    "wof:placetype":"venue"
},
  "geometry": {"coordinates":[4.38851,52.096661],"type":"Point"}
}