{
  "type": "Feature",
  "properties": {
    "iso:country":"NL",
    "sg:address":"Wilhelminastr 154 1Hg",
    "sg:city":"Amsterdam",
    "sg:orig_category":"Video - Faciliteiten En Producties",
    "sg:phone":"+31 20 612 2607",
    "sg:postcode":"1054 WS",
    "sg:province":"North Holland",
    "sg:website":"http://www.grandvideo.nl",
    "wof:name":"Grandvideo",
    "wof:placetype":"venue"
},
  "geometry": {"coordinates":[4.860522,52.361073],"type":"Point"}
}