{
  "type": "Feature",
  "properties": {
    "addr:full":"Willemstr 24 Arnhem Gelderland 6822 CT",
    "addr:housenumber":"24",
    "addr:postcode":"6822 ct",
    "addr:street":"Willemstr",
    "iso:country":"NL",
    "sg:address":"Willemstr 24",
    "sg:city":"Arnhem",
    "sg:orig_category":"Oud Metaal",
    "sg:phone":"+31 26 442 4330",
    "sg:postcode":"6822 CT",
    "sg:province":"Gelderland",
    "wof:name":"Kruijer Fa",
    "wof:placetype":"venue"
},
  "geometry": {"coordinates":[5.9212999344,51.9866638184],"type":"Point"}
}