{
  "type": "Feature",
  "properties": {
    "addr:full":"Molendk 32 Oud Beyerland Zuid-Holland 3262 AK",
    "addr:housenumber":"32",
    "addr:postcode":"3262 ak",
    "addr:street":"Molendk;Oud Beyerland",
    "iso:country":"NL",
    "sg:address":"Molendk 32",
    "sg:city":"Oud Beyerland",
    "sg:orig_category":"Opticiens",
    "sg:phone":"+31 186 616 494",
    "sg:postcode":"3262 AK",
    "sg:province":"Zuid-Holland",
    "wof:name":"Roukens",
    "wof:placetype":"venue"
},
  "geometry": {"coordinates":[4.4097690582,51.8270568848],"type":"Point"}
}