{
  "type": "Feature",
  "properties": {
    "addr:full":"Crooswyksesngl 33 Rotterdam Zuid-Holland 3034 CJ",
    "addr:housenumber":"33",
    "addr:postcode":"3034 cj",
    "addr:street":"Crooswyksesngl",
    "iso:country":"NL",
    "sg:address":"Crooswyksesngl 33",
    "sg:city":"Rotterdam",
    "sg:orig_category":"Nachtclubs",
    "sg:phone":"+31 10 433 4342",
    "sg:postcode":"3034 CJ",
    "sg:province":"Zuid-Holland",
    "sg:website":"http://www.yabyum.nl",
    "wof:name":"Yab Yum",
    "wof:placetype":"venue"
},
  "geometry": {"coordinates":[4.49123,51.93848],"type":"Point"}
}