{
  "type": "Feature",
  "properties": {
    "addr:full":"Van Der Capellenstraat 59 Zwolle NL.08 8014 VV",
    "addr:housenumber":"59",
    "addr:postcode":"8014 vv",
    "addr:street":"Van Der Capellenstraat",
    "iso:country":"NL",
    "sg:address":"Van Der Capellenstraat 59",
    "sg:city":"Zwolle",
    "sg:orig_category":"Kappers",
    "sg:phone":"+31 38 466 0390",
    "sg:postcode":"8014 VV",
    "sg:province":"NL.08",
    "wof:name":"Hans Kalf Intercoiffure",
    "wof:placetype":"venue"
},
  "geometry": {"coordinates":[6.1135869026,52.4836959839],"type":"Point"}
}