{
  "type": "Feature",
  "properties": {
    "addr:full":"Fatimastraat 56 Breda Noord-Brabant 4835 BD",
    "addr:housenumber":"56",
    "addr:postcode":"4835 bd",
    "addr:street":"Fatimastraat",
    "iso:country":"NL",
    "sg:address":"Fatimastraat 56",
    "sg:city":"Breda",
    "sg:orig_category":"Koeriersdiensten",
    "sg:phone":"+31 76 564 0340",
    "sg:postcode":"4835 BD",
    "sg:province":"Noord-Brabant",
    "wof:name":"Hg Couriers",
    "wof:placetype":"venue"
},
  "geometry": {"coordinates":[4.791716,51.574268],"type":"Point"}
}