{
  "type": "Feature",
  "properties": {
    "addr:full":"Linnaeusstraat 78 Amsterdam North Holland 1092 CN",
    "addr:housenumber":"78",
    "addr:postcode":"1092 cn",
    "addr:street":"Linnaeusstraat",
    "iso:country":"NL",
    "sg:address":"Linnaeusstraat 78",
    "sg:city":"Amsterdam",
    "sg:classifiers":[
        {
            "category":"Retail",
            "subcategory":"Photofinishing",
            "type":"Services"
        }
    ],
    "sg:phone":"+31 20 694 2863",
    "sg:postcode":"1092 CN",
    "sg:province":"North Holland",
    "sg:tags":[
        "foto",
        "film"
    ],
    "wof:name":"Foto Solleveld Timmer",
    "wof:placetype":"venue"
},
  "geometry": {"coordinates":[4.92751,52.356392],"type":"Point"}
}