{
  "type": "Feature",
  "properties": {
    "addr:full":"St Bonifaciusln 17 Eindhoven North Brabant 5643 NA",
    "addr:housenumber":"17",
    "addr:postcode":"5643 na",
    "iso:country":"NL",
    "sg:address":"St Bonifaciusln 17",
    "sg:city":"Eindhoven",
    "sg:orig_category":"Bloemen En Planten - Decoratie",
    "sg:phone":"+31 40 294 0124",
    "sg:postcode":"5643 NA",
    "sg:province":"North Brabant",
    "wof:name":"Alexandra",
    "wof:placetype":"venue"
},
  "geometry": {"coordinates":[5.502,51.425301],"type":"Point"}
}