{
  "type": "Feature",
  "properties": {
    "addr:full":"Bruistensngl 132 S Hertogenbosch Noord-Brabant 5232 AC",
    "addr:housenumber":"132",
    "addr:postcode":"5232 ac",
    "addr:street":"S Hertogenbosch",
    "iso:country":"NL",
    "sg:address":"Bruistensngl 132",
    "sg:city":"S Hertogenbosch",
    "sg:classifiers":[
        {
            "category":"Professional",
            "subcategory":"Accounting & Tax Preparation",
            "type":"Services"
        }
    ],
    "sg:phone":"+31 73 640 8336",
    "sg:postcode":"5232 AC",
    "sg:province":"Noord-Brabant",
    "sg:tags":[
        "accountant",
        "en",
        "-kantoren",
        "register-"
    ],
    "wof:name":"Fsv",
    "wof:placetype":"venue"
},
  "geometry": {"coordinates":[5.319015,51.701176],"type":"Point"}
}