{
  "type": "Feature",
  "properties": {
    "iso:country":"NL",
    "sg:address":"Sarphatipk 97",
    "sg:city":"Amsterdam",
    "sg:orig_category":"Verloskundigen",
    "sg:phone":"+31 20 671 0650",
    "sg:postcode":"1073 CV",
    "sg:province":"North Holland",
    "wof:name":"Astrid Limburg, Prakt",
    "wof:placetype":"venue"
},
  "geometry": {"coordinates":[4.897605,52.355526],"type":"Point"}
}