{
  "type": "Feature",
  "properties": {
    "addr:full":"Sarphatipk 97 Amsterdam North Holland 1073 CV",
    "addr:housenumber":"97",
    "addr:postcode":"1073 cv",
    "addr:street":"Sarphatipk",
    "iso:country":"NL",
    "sg:address":"Sarphatipk 97",
    "sg:city":"Amsterdam",
    "sg:orig_category":"Verloskundigen",
    "sg:phone":"+31 20 671 0650",
    "sg:postcode":"1073 CV",
    "sg:province":"North Holland",
    "wof:name":"Astrid Limburg, Prakt",
    "wof:placetype":"venue"
},
  "geometry": {"coordinates":[4.897605,52.355526],"type":"Point"}
}