{
  "type": "Feature",
  "properties": {
    "addr:full":"Dorpsstraat 84 Mierlo North Brabant 5731 JK",
    "addr:housenumber":"84",
    "addr:postcode":"5731 jk",
    "addr:street":"Dorpsstraat",
    "iso:country":"NL",
    "sg:address":"Dorpsstraat 84",
    "sg:city":"Mierlo",
    "sg:orig_category":"Boekhouders",
    "sg:phone":"+31 492 430 105",
    "sg:postcode":"5731 JK",
    "sg:province":"North Brabant",
    "wof:name":"Jan De Vries Administratiekantoor",
    "wof:placetype":"venue"
},
  "geometry": {"coordinates":[5.619782,51.4436],"type":"Point"}
}