{
  "type": "Feature",
  "properties": {
    "addr:full":"Dorpsstraat 81 Ilpendam Noord-Holland 1452 PJ",
    "addr:housenumber":"81",
    "addr:postcode":"1452 pj",
    "addr:street":"Dorpsstraat",
    "iso:country":"NL",
    "sg:address":"Dorpsstraat 81",
    "sg:city":"Ilpendam",
    "sg:orig_category":"Goederenvervoer Over De Weg",
    "sg:phone":"+31 20 436 9000",
    "sg:postcode":"1452 PJ",
    "sg:province":"Noord-Holland",
    "wof:name":"C.H. Dekker & Zonen Expediteurs Bv",
    "wof:placetype":"venue"
},
  "geometry": {"coordinates":[4.951504,52.459003],"type":"Point"}
}