{
  "type": "Feature",
  "properties": {
    "addr:full":"Griftdijk 29 Woudenberg Utrecht 3931 MC",
    "addr:housenumber":"29",
    "addr:postcode":"3931 mc",
    "addr:street":"Griftdijk",
    "iso:country":"NL",
    "sg:address":"Griftdijk 29",
    "sg:city":"Woudenberg",
    "sg:orig_category":"Bloemen And Planten",
    "sg:phone":"+31 33 286 1476",
    "sg:postcode":"3931 MC",
    "sg:province":"Utrecht",
    "wof:name":"Plantenkwekerij En Tuincentrum Eldorado",
    "wof:placetype":"venue"
},
  "geometry": {"coordinates":[5.398791,52.088058],"type":"Point"}
}