{
  "type": "Feature",
  "properties": {
    "addr:full":"Takenhofplein 2 Nijmegen Gelderland 6538 SZ",
    "addr:housenumber":"2",
    "addr:postcode":"6538 sz",
    "addr:street":"Takenhofplein;Gelderland",
    "iso:country":"NL",
    "sg:address":"Takenhofplein 2",
    "sg:city":"Nijmegen",
    "sg:orig_category":"Werving And Selectie Van Tijdelijk Personeel And Uitzendkantoren",
    "sg:phone":"+31 24 343 5444",
    "sg:postcode":"6538 SZ",
    "sg:province":"Gelderland",
    "wof:name":"Spn Uitzendburo Bv",
    "wof:placetype":"venue"
},
  "geometry": {"coordinates":[5.7912669182,51.8245697021],"type":"Point"}
}