{
  "type": "Feature",
  "properties": {
    "addr:full":"Berkstr 39 T Harde Gelderland 8084 HP",
    "addr:housenumber":"39",
    "addr:postcode":"8084 hp",
    "addr:street":"Berkstr",
    "iso:country":"NL",
    "sg:address":"Berkstr 39",
    "sg:city":"T Harde",
    "sg:classifiers":[
        {
            "category":"Personal",
            "subcategory":"Nail Salon",
            "type":"Services"
        }
    ],
    "sg:phone":"+31 525 653 301",
    "sg:postcode":"8084 HP",
    "sg:province":"Gelderland",
    "sg:tags":[
        "pedicure"
    ],
    "wof:name":"Linde, C Van Der",
    "wof:placetype":"venue"
},
  "geometry": {"coordinates":[5.88555,52.417961],"type":"Point"}
}