{
  "type": "Feature",
  "properties": {
    "iso:country":"NL",
    "sg:address":"Zijpendaalseweg 6",
    "sg:city":"Arnhem",
    "sg:orig_category":"Werving And Selectie Van Vast Personeel",
    "sg:phone":"+31 26 351 8220",
    "sg:postcode":"6814 CK",
    "sg:province":"Gelderland",
    "wof:name":"Centerpoint Adviesgroep Bv",
    "wof:placetype":"venue"
},
  "geometry": {"coordinates":[5.904820919,51.9854736328],"type":"Point"}
}