{
  "type": "Feature",
  "properties": {
    "addr:full":"Prikkewei 57 Ny Beets Friesland 9245 HW",
    "addr:housenumber":"57",
    "addr:postcode":"beets;9245 hw",
    "addr:street":"Prikkewei",
    "iso:country":"NL",
    "sg:address":"Prikkewei 57",
    "sg:city":"Ny Beets",
    "sg:orig_category":"Kinderkleding",
    "sg:phone":"+31 512 461 868",
    "sg:postcode":"9245 HW",
    "sg:province":"Friesland",
    "wof:name":"Bolderkar, De",
    "wof:placetype":"venue"
},
  "geometry": {"coordinates":[6.004204,53.06982],"type":"Point"}
}