{
  "type": "Feature",
  "properties": {
    "addr:full":"Meerenakkerweg 14 Eindhoven Noord-Brabant 5652 AV",
    "addr:housenumber":"14",
    "addr:postcode":"5652 av",
    "addr:street":"Meerenakkerweg",
    "iso:country":"NL",
    "sg:address":"Meerenakkerweg 14",
    "sg:city":"Eindhoven",
    "sg:orig_category":"Partycatering And -Organisatie",
    "sg:phone":"+31 40 256 3536",
    "sg:postcode":"5652 AV",
    "sg:province":"Noord-Brabant",
    "wof:name":"Ecs Catering",
    "wof:placetype":"venue"
},
  "geometry": {"coordinates":[5.43625,51.428448],"type":"Point"}
}