{
  "type": "Feature",
  "properties": {
    "addr:full":"Pascalwg 19 Spykenisse Zuid-Holland 3208 KL",
    "addr:housenumber":"19",
    "addr:postcode":"3208 kl",
    "addr:street":"Pascalwg",
    "iso:country":"NL",
    "sg:address":"Pascalwg 19",
    "sg:city":"Spykenisse",
    "sg:orig_category":"Autoruiten",
    "sg:phone":"+31 181 698 001",
    "sg:postcode":"3208 KL",
    "sg:province":"Zuid-Holland",
    "sg:website":"http://www.carglass.nl",
    "wof:name":"Carglass",
    "wof:placetype":"venue"
},
  "geometry": {"coordinates":[4.3029,51.84264],"type":"Point"}
}