{
  "type": "Feature",
  "properties": {
    "iso:country":"NL",
    "sg:address":"Van Woustraat 20",
    "sg:city":"Amsterdam",
    "sg:classifiers":[
        {
            "category":"Fast Food",
            "type":"Food & Drink"
        }
    ],
    "sg:phone":"+31 20 662 3701",
    "sg:postcode":"1073 LL",
    "sg:province":"Noord-Holland",
    "sg:tags":[
        "afhaal",
        "restaurant"
    ],
    "wof:name":"Broodje Popov Bv",
    "wof:placetype":"venue"
},
  "geometry": {"coordinates":[4.89953,52.356804],"type":"Point"}
}