{
  "type": "Feature",
  "properties": {
    "addr:full":"Meidoorn 18 Dokkum Friesland 9103 SH",
    "addr:housenumber":"18",
    "addr:postcode":"9103 sh",
    "addr:street":"Meidoorn",
    "iso:country":"NL",
    "sg:address":"Meidoorn 18",
    "sg:city":"Dokkum",
    "sg:orig_category":"Begrafenisverzorging",
    "sg:phone":"+31 519 297 280",
    "sg:postcode":"9103 SH",
    "sg:province":"Friesland",
    "wof:name":"Zeilinga, M",
    "wof:placetype":"venue"
},
  "geometry": {"coordinates":[6.006666,53.314075],"type":"Point"}
}