{
  "type": "Feature",
  "properties": {
    "addr:full":"Chrysantenstr 20 Amsterdam Noord-Holland 1031 HT",
    "addr:housenumber":"20",
    "addr:postcode":"1031 ht",
    "addr:street":"Chrysantenstr",
    "iso:country":"NL",
    "sg:address":"Chrysantenstr 20",
    "sg:city":"Amsterdam",
    "sg:classifiers":[
        {
            "category":"Retail",
            "subcategory":"Auto Repair",
            "type":"Services"
        }
    ],
    "sg:phone":"+31 20 334 1899",
    "sg:postcode":"1031 HT",
    "sg:province":"Noord-Holland",
    "sg:tags":[
        "garage"
    ],
    "sg:website":"http://www.garagestouten.nl",
    "wof:name":"Stouten Garage Classic",
    "wof:placetype":"venue"
},
  "geometry": {"coordinates":[4.905184,52.391659],"type":"Point"}
}