{
  "type": "Feature",
  "properties": {
    "addr:full":"Laak 8 Putten Gelderland 3881 MK",
    "addr:housenumber":"8",
    "addr:postcode":"3881",
    "addr:street":"Laak;Gelderland",
    "iso:country":"NL",
    "sg:address":"Laak 8",
    "sg:city":"Putten",
    "sg:orig_category":"Werving En Selectie",
    "sg:phone":"+31 341 360 306",
    "sg:postcode":"3881 MK",
    "sg:province":"Gelderland",
    "sg:website":"http://www.bva-ms.nl",
    "wof:name":"Bva",
    "wof:placetype":"venue"
},
  "geometry": {"coordinates":[5.6234750748,52.2748718262],"type":"Point"}
}