{
  "type": "Feature",
  "properties": {
    "addr:full":"Vuurse Dreef 184 Hollandsche Rading Utrecht 3739 KW",
    "addr:housenumber":"184",
    "addr:postcode":"3739 kw",
    "addr:street":"Vuurse Dreef",
    "iso:country":"NL",
    "sg:address":"Vuurse Dreef 184",
    "sg:city":"Hollandsche Rading",
    "sg:orig_category":"Bedrijfsopleidingen",
    "sg:phone":"+31 35 577 2911",
    "sg:postcode":"3739 KW",
    "sg:province":"Utrecht",
    "sg:website":"http://www.coachcompany.nl",
    "wof:name":"Coach Company",
    "wof:placetype":"venue"
},
  "geometry": {"coordinates":[5.203474,52.183197],"type":"Point"}
}