{
  "type": "Feature",
  "properties": {
    "iso:country":"NL",
    "sg:address":"Coornhertdreef 7",
    "sg:city":"Leiderdorp",
    "sg:orig_category":"Nagelstudio'S",
    "sg:phone":"+31 71 541 5806",
    "sg:postcode":"2353 CC",
    "sg:province":"Zuid-Holland",
    "wof:name":"Karin, Supernailservice",
    "wof:placetype":"venue"
},
  "geometry": {"coordinates":[4.537866,52.164501],"type":"Point"}
}