{
  "type": "Feature",
  "properties": {
    "addr:full":"Groenedk 9 Dordrecht South Holland 3311 DB",
    "addr:housenumber":"9",
    "addr:postcode":"3311 db",
    "addr:street":"Groenedk",
    "iso:country":"NL",
    "sg:address":"Groenedk 9",
    "sg:city":"Dordrecht",
    "sg:orig_category":"Autorijscholen",
    "sg:phone":"+31 78 631 9890",
    "sg:postcode":"3311 DB",
    "sg:province":"South Holland",
    "wof:name":"George Autorijschool",
    "wof:placetype":"venue"
},
  "geometry": {"coordinates":[4.680472,51.81422],"type":"Point"}
}