{
  "type": "Feature",
  "properties": {
    "iso:country":"NL",
    "sg:address":"Oordtstraat 12",
    "sg:city":"Beerzerveld",
    "sg:orig_category":"Verzekeringen",
    "sg:phone":"+31 523 251 914",
    "sg:postcode":"7685 PB",
    "sg:province":"Overijssel",
    "wof:name":"Uitvaartver De Laatste Eer Beerzerveld E",
    "wof:placetype":"venue"
},
  "geometry": {"coordinates":[6.574733,52.493969],"type":"Point"}
}