{
  "type": "Feature",
  "properties": {
    "iso:country":"NL",
    "sg:address":"Heenwg 66",
    "sg:city":"S Gravenzande",
    "sg:orig_category":"Bloemen En Planten - Groothandel",
    "sg:phone":"+31 174 412 280",
    "sg:postcode":"2691 LE",
    "sg:province":"Zuid-Holland",
    "wof:name":"Dijk, R Van",
    "wof:placetype":"venue"
},
  "geometry": {"coordinates":[4.182491,51.982525],"type":"Point"}
}