{
  "type": "Feature",
  "properties": {
    "addr:full":"Koninginnestraat 1 Westdorpe Zeeland 4554 CJ",
    "addr:housenumber":"1",
    "addr:postcode":"4554 cj",
    "addr:street":"Koninginnestraat",
    "iso:country":"NL",
    "sg:address":"Koninginnestraat 1",
    "sg:city":"Westdorpe",
    "sg:orig_category":"Verzekeringen",
    "sg:phone":"+31 115 453 821",
    "sg:postcode":"4554 CJ",
    "sg:province":"Zeeland",
    "wof:name":"Verhoosel Assurantien",
    "wof:placetype":"venue"
},
  "geometry": {"coordinates":[3.82961,51.233009],"type":"Point"}
}