{
  "type": "Feature",
  "properties": {
    "addr:full":"Burg De Withstr 15A De Bilt Utrecht 3732 EH",
    "addr:housenumber":"15a",
    "addr:postcode":"3732 eh",
    "iso:country":"NL",
    "sg:address":"Burg De Withstr 15A",
    "sg:city":"De Bilt",
    "sg:orig_category":"Kinderopvang",
    "sg:phone":"+31 30 220 2350",
    "sg:postcode":"3732 EH",
    "sg:province":"Utrecht",
    "wof:name":"Gastouderbureau",
    "wof:placetype":"venue"
},
  "geometry": {"coordinates":[5.182805,52.104637],"type":"Point"}
}