{
  "type": "Feature",
  "properties": {
    "addr:full":"Javastraat 14 'S Gravenhage Zuid-Holland 2585 AN",
    "addr:housenumber":"14",
    "addr:postcode":"2585 an",
    "addr:street":"Javastraat;' S",
    "iso:country":"NL",
    "sg:address":"Javastraat 14",
    "sg:city":"'S Gravenhage",
    "sg:orig_category":"Marktonderzoekbureaus",
    "sg:phone":"+31 70 365 8300",
    "sg:postcode":"2585 AN",
    "sg:province":"Zuid-Holland",
    "wof:name":"Marketing Executive Center Mec",
    "wof:placetype":"venue"
},
  "geometry": {"coordinates":[4.302656,52.087742],"type":"Point"}
}