{
  "type": "Feature",
  "properties": {
    "addr:full":"Leliendaal 17 Schiedam Zuid-Holland 3111 KN",
    "addr:housenumber":"17",
    "addr:postcode":"3111 kn",
    "addr:street":"Leliendaal",
    "iso:country":"NL",
    "sg:address":"Leliendaal 17",
    "sg:city":"Schiedam",
    "sg:orig_category":"Autorijscholen",
    "sg:phone":"+31 6 53501658",
    "sg:postcode":"3111 KN",
    "sg:province":"Zuid-Holland",
    "wof:name":"Reyhan Autorijschool",
    "wof:placetype":"venue"
},
  "geometry": {"coordinates":[4.399211,51.915737],"type":"Point"}
}