{
  "type": "Feature",
  "properties": {
    "addr:full":"Aardster 167 Alphen Aan Den Ryn Zuid-Holland 2403 RN",
    "addr:housenumber":"167",
    "addr:postcode":"2403 rn",
    "addr:street":"Aardster;Aan Den Ryn",
    "iso:country":"NL",
    "sg:address":"Aardster 167",
    "sg:city":"Alphen Aan Den Ryn",
    "sg:orig_category":"Grafisch Ontwerpers",
    "sg:phone":"+31 172 442 317",
    "sg:postcode":"2403 RN",
    "sg:province":"Zuid-Holland",
    "wof:name":"Schwithal",
    "wof:placetype":"venue"
},
  "geometry": {"coordinates":[4.678049,52.150059],"type":"Point"}
}