{
  "type": "Feature",
  "properties": {
    "addr:full":"Noorsestraat 10 Kaatsheuvel North Brabant 5171 PP",
    "addr:housenumber":"10",
    "addr:postcode":"5171 pp",
    "addr:street":"Noorsestraat",
    "iso:country":"NL",
    "sg:address":"Noorsestraat 10",
    "sg:city":"Kaatsheuvel",
    "sg:orig_category":"Autokeuringen",
    "sg:phone":"+31 416 280 744",
    "sg:postcode":"5171 PP",
    "sg:province":"North Brabant",
    "wof:name":"Vincent Leijtens Autobedrijf",
    "wof:placetype":"venue"
},
  "geometry": {"coordinates":[5.033175,51.659588],"type":"Point"}
}