{
  "type": "Feature",
  "properties": {
    "addr:full":"Spoorlaan 191 Tilburg North Brabant 5038 CB",
    "addr:housenumber":"191",
    "addr:postcode":"5038 cb",
    "addr:street":"Spoorlaan",
    "iso:country":"NL",
    "sg:address":"Spoorlaan 191",
    "sg:city":"Tilburg",
    "sg:orig_category":"Hypotheken And Hypotheekbanken",
    "sg:phone":"+31 13 544 5888",
    "sg:postcode":"5038 CB",
    "sg:province":"North Brabant",
    "wof:name":"Hypotheek Visie Tilburg",
    "wof:placetype":"venue"
},
  "geometry": {"coordinates":[5.077684,51.56041],"type":"Point"}
}