{
  "type": "Feature",
  "properties": {
    "addr:full":"Burgemeester Prinssenln 1 Raamsdonksveer Noord-Brabant 4941 AJ",
    "addr:housenumber":"1",
    "addr:postcode":"4941 aj",
    "addr:street":"Burgemeester Prinssenln",
    "iso:country":"NL",
    "sg:address":"Burgemeester Prinssenln 1",
    "sg:city":"Raamsdonksveer",
    "sg:orig_category":"Autokeuringen",
    "sg:phone":"+31 162 517 889",
    "sg:postcode":"4941 AJ",
    "sg:province":"Noord-Brabant",
    "wof:name":"Vof Autobedrijf W. Bocxe",
    "wof:placetype":"venue"
},
  "geometry": {"coordinates":[4.882279,51.693943],"type":"Point"}
}