{
  "type": "Feature",
  "properties": {
    "addr:full":"Gentiaan 21 Boskoop Zuid-Holland 2771 SL",
    "addr:housenumber":"21",
    "addr:postcode":"2771 sl",
    "addr:street":"Gentiaan",
    "iso:country":"NL",
    "sg:address":"Gentiaan 21",
    "sg:city":"Boskoop",
    "sg:orig_category":"Boekhouders",
    "sg:phone":"+31 172 212 096",
    "sg:postcode":"2771 SL",
    "sg:province":"Zuid-Holland",
    "wof:name":"Buro Oudijk",
    "wof:placetype":"venue"
},
  "geometry": {"coordinates":[4.641171,52.071274],"type":"Point"}
}