{
  "type": "Feature",
  "properties": {
    "addr:full":"2E J V Campenstr 138 Amsterdam Noord-Holland 1073 XZ",
    "addr:housenumber":"138",
    "addr:postcode":"1073 xz",
    "addr:street":"2E J V Campenstr",
    "iso:country":"NL",
    "sg:address":"2E J V Campenstr 138",
    "sg:city":"Amsterdam",
    "sg:orig_category":"Evenementenverzorging",
    "sg:phone":"+31 20 471 4358",
    "sg:postcode":"1073 XZ",
    "sg:province":"Noord-Holland",
    "sg:website":"http://www.culturecoalition.nl",
    "wof:name":"Culture Coalition, Sticht",
    "wof:placetype":"venue"
},
  "geometry": {"coordinates":[4.896075,52.35693],"type":"Point"}
}