{
  "type": "Feature",
  "properties": {
    "addr:full":"B Goodmanstr 2 Zaandyk Noord-Holland 1544 LR",
    "addr:housenumber":"2",
    "addr:postcode":"1544 lr",
    "addr:street":"Zaandyk Noord-Holland",
    "iso:country":"NL",
    "sg:address":"B Goodmanstr 2",
    "sg:city":"Zaandyk",
    "sg:orig_category":"Autorijscholen",
    "sg:phone":"+31 75 621 4514",
    "sg:postcode":"1544 LR",
    "sg:province":"Noord-Holland",
    "sg:website":"http://www.arisbakker.nl",
    "wof:name":"Aris Bakker",
    "wof:placetype":"venue"
},
  "geometry": {"coordinates":[4.812078,52.475719],"type":"Point"}
}