{
  "type": "Feature",
  "properties": {
    "addr:full":"Marcusestr 30 Arnhem Gelderland 6836 JB",
    "addr:housenumber":"30",
    "addr:postcode":"6836 jb",
    "addr:street":"Marcusestr",
    "iso:country":"NL",
    "sg:address":"Marcusestr 30",
    "sg:city":"Arnhem",
    "sg:orig_category":"Adviesbureaus Bedrijfsorganisatie",
    "sg:phone":"+31 26 327 3700",
    "sg:postcode":"6836 JB",
    "sg:province":"Gelderland",
    "wof:name":"Movement",
    "wof:placetype":"venue"
},
  "geometry": {"coordinates":[5.892947,51.944675],"type":"Point"}
}