{
  "type": "Feature",
  "properties": {
    "iso:country":"NL",
    "sg:address":"Postbus 2021",
    "sg:city":"Barendrecht",
    "sg:orig_category":"Binnenhuisarchitectuur",
    "sg:phone":"+31 6 28597282",
    "sg:postcode":"2990 DA",
    "sg:province":"Noord-Holland",
    "wof:name":"Bruijn-Coufreur, Monique De",
    "wof:placetype":"venue"
},
  "geometry": {"coordinates":[4.54064,51.853176],"type":"Point"}
}