{
  "type": "Feature",
  "properties": {
    "addr:full":"G V Ledenberchstr 50-56 Amsterdam Noord-Holland 1052 VJ",
    "addr:housenumber":"50-56",
    "addr:postcode":"1052 vj",
    "addr:street":"V Ledenberchstr",
    "iso:country":"NL",
    "sg:address":"G V Ledenberchstr 50-56",
    "sg:city":"Amsterdam",
    "sg:orig_category":"Sanitaire Artikelen",
    "sg:phone":"+31 20 686 0266",
    "sg:postcode":"1052 VJ",
    "sg:province":"Noord-Holland",
    "sg:website":"http://www.ravo.net",
    "wof:name":"Ravo",
    "wof:placetype":"venue"
},
  "geometry": {"coordinates":[4.87379,52.377899],"type":"Point"}
}