{
  "type": "Feature",
  "properties": {
    "addr:full":"Visserstr 12 Breda Noord-Brabant 4811 WJ",
    "addr:housenumber":"12",
    "addr:postcode":"4811 wj",
    "addr:street":"Visserstr",
    "iso:country":"NL",
    "sg:address":"Visserstr 12",
    "sg:city":"Breda",
    "sg:orig_category":"Zalenverhuur",
    "sg:phone":"+31 76 520 5796",
    "sg:postcode":"4811 WJ",
    "sg:province":"Noord-Brabant",
    "wof:name":"Miller Time, Caf?",
    "wof:placetype":"venue"
},
  "geometry": {"coordinates":[4.773351,51.588604],"type":"Point"}
}