{
  "type": "Feature",
  "properties": {
    "addr:full":"Neuzendk 7A Zelhem Gelderland 7021 LS",
    "addr:housenumber":"7a",
    "addr:postcode":"7021 ls",
    "addr:street":"Neuzendk;Gelderland",
    "iso:country":"NL",
    "sg:address":"Neuzendk 7A",
    "sg:city":"Zelhem",
    "sg:orig_category":"Schilders",
    "sg:phone":"+31 314 641 950",
    "sg:postcode":"7021 LS",
    "sg:province":"Gelderland",
    "wof:name":"Abc-Bessels",
    "wof:placetype":"venue"
},
  "geometry": {"coordinates":[6.293043,52.011692],"type":"Point"}
}