{
  "type": "Feature",
  "properties": {
    "addr:full":"Mozartln 2-4 Waddinxveen Zuid-Holland 2742 BN",
    "addr:housenumber":"2-4",
    "addr:postcode":"2742 bn",
    "addr:street":"Mozartln",
    "iso:country":"NL",
    "sg:address":"Mozartln 2-4",
    "sg:city":"Waddinxveen",
    "sg:orig_category":"Artsen - Huisartsen",
    "sg:phone":"+31 182 612 676",
    "sg:postcode":"2742 BN",
    "sg:province":"Zuid-Holland",
    "wof:name":"Siemons En W A Van Heel, G",
    "wof:placetype":"venue"
},
  "geometry": {"coordinates":[4.65507,52.044601],"type":"Point"}
}