{
  "type": "Feature",
  "properties": {
    "addr:full":"Emmastraat 12 Amsterdam Noord-Holland 1075 HT",
    "addr:housenumber":"12",
    "addr:postcode":"1075 ht",
    "addr:street":"Emmastraat",
    "iso:country":"NL",
    "sg:address":"Emmastraat 12",
    "sg:city":"Amsterdam",
    "sg:orig_category":"Verzekeringen",
    "sg:phone":"+31 20 679 7633",
    "sg:postcode":"1075 HT",
    "sg:province":"Noord-Holland",
    "wof:name":"Spier Consultancy Bv",
    "wof:placetype":"venue"
},
  "geometry": {"coordinates":[4.868933,52.353977],"type":"Point"}
}