{
  "type": "Feature",
  "properties": {
    "addr:full":"Vogelshemwg 9 Gasselternyveen Drenthe 9514 BT",
    "addr:housenumber":"9",
    "addr:postcode":"9514 bt",
    "addr:street":"Vogelshemwg",
    "iso:country":"NL",
    "sg:address":"Vogelshemwg 9",
    "sg:city":"Gasselternyveen",
    "sg:orig_category":"Waterbouwkundige Werken",
    "sg:phone":"+31 599 512 402",
    "sg:postcode":"9514 BT",
    "sg:province":"Drenthe",
    "wof:name":"Luis, Ltc",
    "wof:placetype":"venue"
},
  "geometry": {"coordinates":[6.8379130363,52.9870681763],"type":"Point"}
}