{
  "type": "Feature",
  "properties": {
    "addr:full":"Dukdalf 3 Joure Friesland 8502 CB",
    "addr:housenumber":"3",
    "addr:postcode":"8502 cb",
    "addr:street":"Dukdalf",
    "iso:country":"NL",
    "sg:address":"Dukdalf 3",
    "sg:city":"Joure",
    "sg:orig_category":"Goudsmeden En Zilversmeden",
    "sg:phone":"+31 513 419 885",
    "sg:postcode":"8502 CB",
    "sg:province":"Friesland",
    "wof:name":"Brouwer, M",
    "wof:placetype":"venue"
},
  "geometry": {"coordinates":[5.811035,52.969803],"type":"Point"}
}