{
  "type": "Feature",
  "properties": {
    "iso:country":"NL",
    "sg:address":"Samsonwg 110",
    "sg:city":"Wormerveer",
    "sg:orig_category":"Koeriersdiensten",
    "sg:phone":"+31 75 628 9744",
    "sg:postcode":"1521 RM",
    "sg:province":"Noord-Holland",
    "wof:name":"Fds",
    "wof:placetype":"venue"
},
  "geometry": {"coordinates":[4.784197,52.51075],"type":"Point"}
}