{
  "type": "Feature",
  "properties": {
    "iso:country":"NL",
    "sg:address":"Schuppert 2",
    "sg:city":"Barchem",
    "sg:orig_category":"Verhuur Bouwmachines",
    "sg:phone":"+31 573 441 626",
    "sg:postcode":"7244 NH",
    "sg:province":"Gelderland",
    "wof:name":"W. Platerink",
    "wof:placetype":"venue"
},
  "geometry": {"coordinates":[-71.632828,44.001301],"type":"Point"}
}