{
  "type": "Feature",
  "properties": {
    "addr:full":"Neptunusstr 18 Hardenberg Overijssel 7771 EX",
    "addr:housenumber":"18",
    "addr:postcode":"7771 ex",
    "addr:street":"Neptunusstr",
    "iso:country":"NL",
    "sg:address":"Neptunusstr 18",
    "sg:city":"Hardenberg",
    "sg:orig_category":"Verenigingen En Stichtingen",
    "sg:phone":"+31 523 682 008",
    "sg:postcode":"7771 EX",
    "sg:province":"Overijssel",
    "wof:name":"Kynologen Club Hardenberg Eo",
    "wof:placetype":"venue"
},
  "geometry": {"coordinates":[6.607115,52.562939],"type":"Point"}
}