{
  "type": "Feature",
  "properties": {
    "addr:full":"Heistraat 32 Helmond Noord-Brabant 5701 HP",
    "addr:housenumber":"32",
    "addr:postcode":"5701 hp",
    "addr:street":"Heistraat",
    "iso:country":"NL",
    "sg:address":"Heistraat 32",
    "sg:city":"Helmond",
    "sg:orig_category":"Meubelzaken, Woning- And Keukeninrichting",
    "sg:phone":"+31 492 533 551",
    "sg:postcode":"5701 HP",
    "sg:province":"Noord-Brabant",
    "wof:name":"Woninginrichting G. Watervoort Bv",
    "wof:placetype":"venue"
},
  "geometry": {"coordinates":[5.664363,51.483768],"type":"Point"}
}