{
  "type": "Feature",
  "properties": {
    "addr:full":"Hagerhofweg 7 Venlo Limburg 5912 PN",
    "addr:housenumber":"7",
    "addr:postcode":"5912 pn",
    "addr:street":"Hagerhofweg",
    "iso:country":"NL",
    "sg:address":"Hagerhofweg 7",
    "sg:city":"Venlo",
    "sg:orig_category":"Verhuur Bouwmachines",
    "sg:phone":"+31 77 354 1188",
    "sg:postcode":"5912 PN",
    "sg:province":"Limburg",
    "wof:name":"Boels Verhuur",
    "wof:placetype":"venue"
},
  "geometry": {"coordinates":[6.162944,51.356152],"type":"Point"}
}