{
  "type": "Feature",
  "properties": {
    "addr:full":"Kerspelln 84 Emmen Drenthe 7824 JK",
    "addr:housenumber":"84",
    "addr:postcode":"7824 jk",
    "addr:street":"Kerspelln",
    "iso:country":"NL",
    "sg:address":"Kerspelln 84",
    "sg:city":"Emmen",
    "sg:orig_category":"Parketvloeren",
    "sg:phone":"+31 591 620 870",
    "sg:postcode":"7824 JK",
    "sg:province":"Drenthe",
    "wof:name":"Parketman",
    "wof:placetype":"venue"
},
  "geometry": {"coordinates":[6.92951,52.7799],"type":"Point"}
}