{
  "type": "Feature",
  "properties": {
    "addr:full":"Rijksweg 83 Nieuwendijk Nb Noord-Brabant 4255 GH",
    "addr:housenumber":"83",
    "addr:postcode":"4255 gh",
    "addr:street":"Rijksweg",
    "iso:country":"NL",
    "sg:address":"Rijksweg 83",
    "sg:city":"Nieuwendijk Nb",
    "sg:orig_category":"Granen, Zaden And Diervoeders Gh",
    "sg:phone":"+31 183 401 497",
    "sg:postcode":"4255 GH",
    "sg:province":"Noord-Brabant",
    "wof:name":"Schouten Graanhandel Cv",
    "wof:placetype":"venue"
},
  "geometry": {"coordinates":[4.92366,51.768997],"type":"Point"}
}