{
  "type": "Feature",
  "properties": {
    "iso:country":"NL",
    "sg:address":"Floresstraat 3",
    "sg:city":"Zwolle",
    "sg:orig_category":"Diverse Grafische Activiteiten",
    "sg:phone":"+31 38 453 1818",
    "sg:postcode":"8022 AD",
    "sg:province":"Overijssel",
    "wof:name":"Boekbinderij De Ruiter Bv",
    "wof:placetype":"venue"
},
  "geometry": {"coordinates":[6.112261,52.519104],"type":"Point"}
}