{
  "type": "Feature",
  "properties": {
    "iso:country":"NL",
    "sg:address":"Gulickstr 17",
    "sg:city":"Tegelen",
    "sg:orig_category":"Administratie- En Boekhoudkantoren",
    "sg:phone":"+31 77 373 6564",
    "sg:postcode":"5931 LA",
    "sg:province":"Limburg",
    "sg:website":"http://www.unitedpartners.nl",
    "wof:name":"Control Consultants",
    "wof:placetype":"venue"
},
  "geometry": {"coordinates":[6.146728,51.344517],"type":"Point"}
}