{
  "type": "Feature",
  "properties": {
    "addr:full":"Roggestr 12 Doesburg Gelderland 6981 BK",
    "addr:housenumber":"12",
    "addr:postcode":"6981 bk",
    "addr:street":"Roggestr;Gelderland",
    "iso:country":"NL",
    "sg:address":"Roggestr 12",
    "sg:city":"Doesburg",
    "sg:orig_category":"Goudsmeden En Zilversmeden",
    "sg:phone":"+31 313 484 771",
    "sg:postcode":"6981 BK",
    "sg:province":"Gelderland",
    "wof:name":"Blok, C M",
    "wof:placetype":"venue"
},
  "geometry": {"coordinates":[6.132968,52.01487],"type":"Point"}
}