{
  "type": "Feature",
  "properties": {
    "addr:full":"Bentinckplein 6 Rotterdam South Holland 3039 KL",
    "addr:housenumber":"6",
    "addr:postcode":"3039 kl",
    "addr:street":"Bentinckplein",
    "iso:country":"NL",
    "sg:address":"Bentinckplein 6",
    "sg:city":"Rotterdam",
    "sg:classifiers":[
        {
            "category":"Fast Food",
            "type":"Food & Drink"
        }
    ],
    "sg:phone":"+31 10 466 5393",
    "sg:postcode":"3039 KL",
    "sg:province":"South Holland",
    "sg:tags":[
        "afhaal",
        "restaurant"
    ],
    "wof:name":"Afhaalcentrum Nieuw Shanghai",
    "wof:placetype":"venue"
},
  "geometry": {"coordinates":[4.461308,51.926414],"type":"Point"}
}