{
  "type": "Feature",
  "properties": {
    "addr:full":"Marshallln 47 Hellevoetsluis Zuid-Holland 3223 TJ",
    "addr:housenumber":"47",
    "addr:postcode":"3223 tj",
    "addr:street":"Marshallln",
    "iso:country":"NL",
    "sg:address":"Marshallln 47",
    "sg:city":"Hellevoetsluis",
    "sg:orig_category":"Homeopathie",
    "sg:phone":"+31 181 317 730",
    "sg:postcode":"3223 TJ",
    "sg:province":"Zuid-Holland",
    "wof:name":"Klaij, B",
    "wof:placetype":"venue"
},
  "geometry": {"coordinates":[4.14703,51.830406],"type":"Point"}
}