{
  "type": "Feature",
  "properties": {
    "addr:full":"Herengr 400 Amsterdam Noord-Holland 1017 BX",
    "addr:housenumber":"400",
    "addr:postcode":"1017 bx",
    "iso:country":"NL",
    "sg:address":"Herengr 400",
    "sg:city":"Amsterdam",
    "sg:orig_category":"Kantoor- En Secretariaatsservice",
    "sg:phone":"+31 20 421 1110",
    "sg:postcode":"1017 BX",
    "sg:province":"Noord-Holland",
    "wof:name":"Italian Business Support",
    "wof:placetype":"venue"
},
  "geometry": {"coordinates":[4.8868670464,52.3671607971],"type":"Point"}
}