{
  "type": "Feature",
  "properties": {
    "addr:full":"Martin Ovenwg 3 Utrecht Utrecht 3555 HZ",
    "addr:housenumber":"3",
    "addr:postcode":"3555 hz",
    "addr:street":"Ovenwg",
    "iso:country":"NL",
    "sg:address":"Martin Ovenwg 3",
    "sg:city":"Utrecht",
    "sg:orig_category":"Fotografie Reclame En Mode",
    "sg:phone":"+31 30 244 8070",
    "sg:postcode":"3555 HZ",
    "sg:province":"Utrecht",
    "sg:website":"http://www.fotostudiotonspekschoor.nl",
    "wof:name":"Spekschoor, Ton",
    "wof:placetype":"venue"
},
  "geometry": {"coordinates":[5.078491,52.110958],"type":"Point"}
}