{
  "type": "Feature",
  "properties": {
    "addr:full":"Windmolen 71 Wateringen Zuid-Holland 2291 KR",
    "addr:housenumber":"71",
    "addr:postcode":"2291 kr",
    "addr:street":"Windmolen",
    "iso:country":"NL",
    "sg:address":"Windmolen 71",
    "sg:city":"Wateringen",
    "sg:orig_category":"Administratie- En Boekhoudkantoren",
    "sg:phone":"+31 174 296 895",
    "sg:postcode":"2291 KR",
    "sg:province":"Zuid-Holland",
    "wof:name":"Henskens",
    "wof:placetype":"venue"
},
  "geometry": {"coordinates":[4.272411,52.020432],"type":"Point"}
}