{
  "type": "Feature",
  "properties": {
    "addr:full":"Statenweg 23 Emmen Drenthe 7824 CS",
    "addr:housenumber":"23",
    "addr:postcode":"7824 cs",
    "addr:street":"Statenweg",
    "iso:country":"NL",
    "sg:address":"Statenweg 23",
    "sg:city":"Emmen",
    "sg:orig_category":"Banken And Kredietinstellingen",
    "sg:phone":"+31 591 680 680",
    "sg:postcode":"7824 CS",
    "sg:province":"Drenthe",
    "wof:name":"Rabobank",
    "wof:placetype":"venue"
},
  "geometry": {"coordinates":[6.921279,52.779465],"type":"Point"}
}