{
  "type": "Feature",
  "properties": {
    "addr:full":"Keurmeesterstraat 15 Ridderkerk Zuid-Holland 2984 BA",
    "addr:housenumber":"15",
    "addr:postcode":"2984 ba",
    "addr:street":"Keurmeesterstraat",
    "iso:country":"NL",
    "sg:address":"Keurmeesterstraat 15",
    "sg:city":"Ridderkerk",
    "sg:orig_category":"Metaalbekleding And -Behandeling",
    "sg:phone":"+31 180 481 777",
    "sg:postcode":"2984 BA",
    "sg:province":"Zuid-Holland",
    "wof:name":"Spuit- En Restauratiebedrijf Marconi Vof",
    "wof:placetype":"venue"
},
  "geometry": {"coordinates":[4.62033,51.876732],"type":"Point"}
}