{
  "type": "Feature",
  "properties": {
    "addr:full":"Lindestraat 32 Oudelande Zeeland 4436 AJ",
    "addr:housenumber":"32",
    "addr:postcode":"4436 aj",
    "addr:street":"Lindestraat",
    "iso:country":"NL",
    "sg:address":"Lindestraat 32",
    "sg:city":"Oudelande",
    "sg:orig_category":"Binnenhuisarchitecten",
    "sg:phone":"+31 113 548 245",
    "sg:postcode":"4436 AJ",
    "sg:province":"Zeeland",
    "wof:name":"B. V.D. Hoven",
    "wof:placetype":"venue"
},
  "geometry": {"coordinates":[3.854908,51.408722],"type":"Point"}
}