{
  "type": "Feature",
  "properties": {
    "addr:full":"Daalseweg 205 Nijmegen Gelderland 6521 GH",
    "addr:housenumber":"205",
    "addr:postcode":"6521 gh",
    "addr:street":"Daalseweg;Gelderland",
    "iso:country":"NL",
    "sg:address":"Daalseweg 205",
    "sg:city":"Nijmegen",
    "sg:orig_category":"Fietshandelaren",
    "sg:phone":"+31 24 322 5495",
    "sg:postcode":"6521 GH",
    "sg:province":"Gelderland",
    "wof:name":"Sloos Tweewielers",
    "wof:placetype":"venue"
},
  "geometry": {"coordinates":[5.873004,51.840069],"type":"Point"}
}