{
  "type": "Feature",
  "properties": {
    "iso:country":"NL",
    "sg:address":"Koraalrood 40",
    "sg:city":"Zoetermeer",
    "sg:orig_category":"Kinderopvang Behalve Thuis",
    "sg:phone":"+31 79 361 7572",
    "sg:postcode":"2718 SC",
    "sg:province":"South Holland",
    "wof:name":"Kinderdagverblijf Roodkapje",
    "wof:placetype":"venue"
},
  "geometry": {"coordinates":[4.503158,52.040707],"type":"Point"}
}