{
  "type": "Feature",
  "properties": {
    "iso:country":"NL",
    "sg:address":"Postbus 75597",
    "sg:city":"Amsterdam",
    "sg:orig_category":"Bedrijfsopleidingen",
    "sg:phone":"+31 20 662 7474",
    "sg:postcode":"1070 AN",
    "sg:province":"Overijssel",
    "sg:website":"http://www.peoplesbusiness.nl",
    "wof:name":"People'S Business",
    "wof:placetype":"venue"
},
  "geometry": {"coordinates":[4.89205,52.37355],"type":"Point"}
}