{
  "type": "Feature",
  "properties": {
    "addr:full":"Marconilaan 11 Weert Limburg 6003 DD",
    "addr:housenumber":"11",
    "addr:postcode":"6003 dd",
    "addr:street":"Marconilaan",
    "iso:country":"NL",
    "sg:address":"Marconilaan 11",
    "sg:city":"Weert",
    "sg:orig_category":"Bouwnijverheidsmachines Gh",
    "sg:phone":"+31 495 546 240",
    "sg:postcode":"6003 DD",
    "sg:province":"Limburg",
    "wof:name":"Bo-Rent",
    "wof:placetype":"venue"
},
  "geometry": {"coordinates":[5.729763,51.272472],"type":"Point"}
}