{
  "type": "Feature",
  "properties": {
    "addr:full":"Kerkpln 3 Haren Nb Noord-Brabant 5368 AM",
    "addr:housenumber":"3",
    "addr:postcode":"5368",
    "addr:street":"Kerkpln",
    "iso:country":"NL",
    "sg:address":"Kerkpln 3",
    "sg:city":"Haren Nb",
    "sg:orig_category":"Verenigingsgebouwen",
    "sg:phone":"+31 412 462 666",
    "sg:postcode":"5368 AM",
    "sg:province":"Noord-Brabant",
    "wof:name":"Gemeenschapshuis Haren",
    "wof:placetype":"venue"
},
  "geometry": {"coordinates":[5.584929,51.798622],"type":"Point"}
}