{
  "type": "Feature",
  "properties": {
    "iso:country":"NL",
    "sg:address":"Kerkpln 3",
    "sg:city":"Haren Nb",
    "sg:orig_category":"Verenigingsgebouwen",
    "sg:phone":"+31 412 462 666",
    "sg:postcode":"5368 AM",
    "sg:province":"Noord-Brabant",
    "wof:name":"Gemeenschapshuis Haren",
    "wof:placetype":"venue"
},
  "geometry": {"coordinates":[5.584929,51.798622],"type":"Point"}
}