{
  "type": "Feature",
  "properties": {
    "addr:full":"Impuls 139 Purmerend North Holland 1446 WE",
    "addr:housenumber":"139",
    "addr:postcode":"1446 we",
    "addr:street":"Impuls",
    "iso:country":"NL",
    "sg:address":"Impuls 139",
    "sg:city":"Purmerend",
    "sg:orig_category":"Timmerwerk Van Hout And Kunststof",
    "sg:phone":"+31 299 645 722",
    "sg:postcode":"1446 WE",
    "sg:province":"North Holland",
    "wof:name":"Fakkeldij Groep",
    "wof:placetype":"venue"
},
  "geometry": {"coordinates":[5.00657,52.511162],"type":"Point"}
}