{
  "type": "Feature",
  "properties": {
    "addr:full":"Wijngracht 64 Kerkrade Limburg 6461 AL",
    "addr:housenumber":"64",
    "addr:postcode":"6461 al",
    "addr:street":"Wijngracht",
    "iso:country":"NL",
    "sg:address":"Wijngracht 64",
    "sg:city":"Kerkrade",
    "sg:orig_category":"Politie",
    "sg:phone":"+31 45 400 2000",
    "sg:postcode":"6461 AL",
    "sg:province":"Limburg",
    "wof:name":"Politie Limburg Zuid District Kerkrade",
    "wof:placetype":"venue"
},
  "geometry": {"coordinates":[6.060406,50.866882],"type":"Point"}
}