{
  "type": "Feature",
  "properties": {
    "addr:full":"Stationsplein 23 Eindhoven Noord-Brabant 5611 AC",
    "addr:housenumber":"23",
    "addr:postcode":"5611 ac",
    "addr:street":"Stationsplein",
    "iso:country":"NL",
    "sg:address":"Stationsplein 23",
    "sg:city":"Eindhoven",
    "sg:orig_category":"Kappers",
    "sg:phone":"+31 40 243 0822",
    "sg:postcode":"5611 AC",
    "sg:province":"Noord-Brabant",
    "wof:name":"Stationskapsalon Eindhoven",
    "wof:placetype":"venue"
},
  "geometry": {"coordinates":[5.484105,51.434471],"type":"Point"}
}