{
  "type": "Feature",
  "properties": {
    "addr:full":"Scholtenstraat 23 Schiedam South Holland 3125 BM",
    "addr:housenumber":"23",
    "addr:postcode":"3125 bm",
    "addr:street":"Scholtenstraat",
    "iso:country":"NL",
    "sg:address":"Scholtenstraat 23",
    "sg:city":"Schiedam",
    "sg:orig_category":"Diverse Consumentenartikelen Gh",
    "sg:phone":"+31 10 415 8787",
    "sg:postcode":"3125 BM",
    "sg:province":"South Holland",
    "wof:name":"Adnico Bv",
    "wof:placetype":"venue"
},
  "geometry": {"coordinates":[4.40349,51.93058],"type":"Point"}
}