{
  "type": "Feature",
  "properties": {
    "iso:country":"NL",
    "sg:address":"Pater Chevalierstraat 6",
    "sg:city":"Sittard",
    "sg:orig_category":"Begrafenisondernemers",
    "sg:phone":"+31 46 451 3572",
    "sg:postcode":"6136 AT",
    "sg:province":"Limburg",
    "wof:name":"Begrafenis-En Crematieverzorging",
    "wof:placetype":"venue"
},
  "geometry": {"coordinates":[5.864726,51.007149],"type":"Point"}
}