{
  "type": "Feature",
  "properties": {
    "iso:country":"NL",
    "sg:address":"Van Musschenbroekstraat 178",
    "sg:city":"'S Gravenhage",
    "sg:classifiers":[
        {
            "category":"Food & Beverages",
            "subcategory":"Fruits & Vegetables",
            "type":"Retail Goods"
        }
    ],
    "sg:phone":"+31 70 399 1466",
    "sg:postcode":"2522 AW",
    "sg:province":"Zuid-Holland",
    "sg:tags":[
        "groenten"
    ],
    "wof:name":"Prijskraker",
    "wof:placetype":"venue"
},
  "geometry": {"coordinates":[4.328486,52.061291],"type":"Point"}
}