{
  "type": "Feature",
  "properties": {
    "addr:full":"Hoofdstr 297 Schiedam Zuid-Holland 3114 GE",
    "addr:housenumber":"297",
    "addr:postcode":"3114",
    "iso:country":"NL",
    "sg:address":"Hoofdstr 297",
    "sg:city":"Schiedam",
    "sg:orig_category":"Postzegels",
    "sg:phone":"+31 10 426 8121",
    "sg:postcode":"3114 GE",
    "sg:province":"Zuid-Holland",
    "wof:name":"Java",
    "wof:placetype":"venue"
},
  "geometry": {"coordinates":[4.406861,51.908073],"type":"Point"}
}