{
  "type": "Feature",
  "properties": {
    "addr:full":"S E Wendelaar Bongastr 1 Dokkum Friesland 9103 PP",
    "addr:housenumber":"1",
    "addr:postcode":"9103 pp",
    "addr:street":"Bongastr",
    "iso:country":"NL",
    "sg:address":"S E Wendelaar Bongastr 1",
    "sg:city":"Dokkum",
    "sg:orig_category":"Loodgieterswerk, Verwarming And Sanitaire Installaties",
    "sg:phone":"+31 519 220 689",
    "sg:postcode":"9103 PP",
    "sg:province":"Friesland",
    "wof:name":"C. Visser",
    "wof:placetype":"venue"
},
  "geometry": {"coordinates":[6.0101,53.319485],"type":"Point"}
}