{
  "type": "Feature",
  "properties": {
    "iso:country":"NL",
    "sg:address":"Boerhaaveln 22",
    "sg:city":"Zoetermeer",
    "sg:orig_category":"Parfumerie - Groothandel",
    "sg:phone":"+31 79 329 3220",
    "sg:postcode":"2713 HX",
    "sg:province":"Zuid-Holland",
    "wof:name":"Chanel",
    "wof:placetype":"venue"
},
  "geometry": {"coordinates":[4.488925,52.06308],"type":"Point"}
}