{
  "type": "Feature",
  "properties": {
    "addr:full":"Schelpenkd 49 Leiden Zuid-Holland 2313 ZX",
    "addr:housenumber":"49",
    "addr:postcode":"2313 zx",
    "addr:street":"Schelpenkd",
    "iso:country":"NL",
    "sg:address":"Schelpenkd 49",
    "sg:city":"Leiden",
    "sg:orig_category":"Adviesbureaus Bedrijfsorganisatie",
    "sg:phone":"+31 71 512 1372",
    "sg:postcode":"2313 ZX",
    "sg:province":"Zuid-Holland",
    "wof:name":"Bree",
    "wof:placetype":"venue"
},
  "geometry": {"coordinates":[4.484731,52.151054],"type":"Point"}
}