{
  "type": "Feature",
  "properties": {
    "iso:country":"NL",
    "sg:address":"Fellenoordstr 72",
    "sg:city":"Breda",
    "sg:orig_category":"Adviesbureaus Bedrijfsorganisatie",
    "sg:phone":"+31 76 522 8463",
    "sg:postcode":"4811 TJ",
    "sg:province":"Noord-Brabant",
    "wof:name":"Associatie Voor Org & Manageme",
    "wof:placetype":"venue"
},
  "geometry": {"coordinates":[4.767551,51.585072],"type":"Point"}
}