{
  "type": "Feature",
  "properties": {
    "addr:full":"Rooseveltstr 35 Oudenbosch Noord-Brabant 4731 KG",
    "addr:housenumber":"35",
    "addr:postcode":"4731 kg",
    "addr:street":"Rooseveltstr",
    "iso:country":"NL",
    "sg:address":"Rooseveltstr 35",
    "sg:city":"Oudenbosch",
    "sg:orig_category":"Danssportbenodigdheden",
    "sg:phone":"+31 165 321 843",
    "sg:postcode":"4731 KG",
    "sg:province":"Noord-Brabant",
    "wof:name":"Dancefashion",
    "wof:placetype":"venue"
},
  "geometry": {"coordinates":[4.526705,51.591965],"type":"Point"}
}