{
  "type": "Feature",
  "properties": {
    "addr:full":"Zevenhuizerstr 39 Hoogland Utrecht 3828 BB",
    "addr:housenumber":"39",
    "addr:postcode":"3828 bb",
    "addr:street":"Zevenhuizerstr",
    "iso:country":"NL",
    "sg:address":"Zevenhuizerstr 39",
    "sg:city":"Hoogland",
    "sg:orig_category":"Onroerende Goederen",
    "sg:phone":"+31 33 480 4444",
    "sg:postcode":"3828 BB",
    "sg:province":"Utrecht",
    "wof:name":"Norden Bv, Yvonne Van",
    "wof:placetype":"venue"
},
  "geometry": {"coordinates":[5.373689,52.183956],"type":"Point"}
}