{
  "type": "Feature",
  "properties": {
    "iso:country":"NL",
    "sg:address":"J V Riebeeckstr 14",
    "sg:city":"Best",
    "sg:orig_category":"Grondwerken",
    "sg:phone":"+31 499 379 911",
    "sg:postcode":"5684 EJ",
    "sg:province":"Texas",
    "wof:name":"Schepens Bv Grond- En Sloopwerk, B",
    "wof:placetype":"venue"
},
  "geometry": {"coordinates":[-101.618134,31.224251],"type":"Point"}
}