{
  "type": "Feature",
  "properties": {
    "addr:full":"G Schalckenstr 47 Made California 4921 CP",
    "addr:housenumber":"47",
    "addr:postcode":"4921 cp",
    "iso:country":"NL",
    "sg:address":"G Schalckenstr 47",
    "sg:city":"Made",
    "sg:orig_category":"Onderhoudswerken",
    "sg:phone":"+31 162 687 112",
    "sg:postcode":"4921 CP",
    "sg:province":"California",
    "wof:name":"Made",
    "wof:placetype":"venue"
},
  "geometry": {"coordinates":[-120.06399500000001,36.962055],"type":"Point"}
}