{
  "type": "Feature",
  "properties": {
    "iso:country":"NL",
    "sg:address":"S Gravenweg 340",
    "sg:city":"Nieuwerkerk Ad Ijssel",
    "sg:orig_category":"Wegen And Sportterreinen",
    "sg:phone":"+31 180 314 333",
    "sg:postcode":"2911 BK",
    "sg:province":"Zuid-Holland",
    "wof:name":"Aannemingsmaatschappij G. Van Herk Tzn Bv",
    "wof:placetype":"venue"
},
  "geometry": {"coordinates":[4.6273927689,51.96692276],"type":"Point"}
}