{
  "type": "Feature",
  "properties": {
    "iso:country":"NL",
    "sg:address":"Uilenweg 11",
    "sg:city":"Lelystad",
    "sg:orig_category":"Kampeerterreinen",
    "sg:phone":"+31 320 253 693",
    "sg:postcode":"8245 AB",
    "sg:province":"Flevoland",
    "wof:name":"Camping 'T Oppertje",
    "wof:placetype":"venue"
},
  "geometry": {"coordinates":[5.4164891243,52.485786438],"type":"Point"}
}