{
  "type": "Feature",
  "properties": {
    "addr:full":"Julianastr 53 Stramproy Limburg 6039 AH",
    "addr:housenumber":"53",
    "addr:postcode":"6039 ah",
    "addr:street":"Julianastr",
    "iso:country":"NL",
    "sg:address":"Julianastr 53",
    "sg:city":"Stramproy",
    "sg:orig_category":"Fitnesscentra",
    "sg:phone":"+31 495 562 023",
    "sg:postcode":"6039 AH",
    "sg:province":"Limburg",
    "wof:name":"Fit-Inn",
    "wof:placetype":"venue"
},
  "geometry": {"coordinates":[5.72146,51.196388],"type":"Point"}
}