{
  "type": "Feature",
  "properties": {
    "addr:full":"Genemuidenstraat 18 Tilburg Noord-Brabant 5043 LT",
    "addr:housenumber":"18",
    "addr:postcode":"5043 lt",
    "addr:street":"Genemuidenstraat",
    "iso:country":"NL",
    "sg:address":"Genemuidenstraat 18",
    "sg:city":"Tilburg",
    "sg:orig_category":"Glaszetten",
    "sg:phone":"+31 13 570 2029",
    "sg:postcode":"5043 LT",
    "sg:province":"Noord-Brabant",
    "wof:name":"Van Pelt Glas Atelier",
    "wof:placetype":"venue"
},
  "geometry": {"coordinates":[5.009921,51.578583],"type":"Point"}
}