{
  "type": "Feature",
  "properties": {
    "iso:country":"NL",
    "sg:address":"Burg Patynln 184",
    "sg:city":"Zeist",
    "sg:orig_category":"Adviesbureaus Bedrijfsorganisatie",
    "sg:phone":"+31 30 695 0055",
    "sg:postcode":"3705 CL",
    "sg:province":"Utrecht",
    "wof:name":"Vollenhoven, Drs Ing F J E Van",
    "wof:placetype":"venue"
},
  "geometry": {"coordinates":[5.24387,52.08548],"type":"Point"}
}