{
  "type": "Feature",
  "properties": {
    "addr:full":"Roelantdreef 20 Utrecht Utrecht 3562 KB",
    "addr:housenumber":"20",
    "addr:postcode":"3562 kb",
    "addr:street":"Roelantdreef",
    "iso:country":"NL",
    "sg:address":"Roelantdreef 20",
    "sg:city":"Utrecht",
    "sg:orig_category":"Huishoudelijke Apparaten En Artikelen",
    "sg:phone":"+31 30 261 0013",
    "sg:postcode":"3562 KB",
    "sg:province":"Utrecht",
    "sg:website":"http://www.blokker.nl",
    "wof:name":"Blokker Bv",
    "wof:placetype":"venue"
},
  "geometry": {"coordinates":[5.112318,52.113598],"type":"Point"}
}