{
  "type": "Feature",
  "properties": {
    "iso:country":"NL",
    "sg:address":"Huetingstraat 9",
    "sg:city":"Katwijk Zh",
    "sg:orig_category":"Goederenvervoer Over De Weg",
    "sg:phone":"+31 71 402 3011",
    "sg:postcode":"2223 BM",
    "sg:province":"South Holland",
    "wof:name":"Transportbedrijf A.W. Kruger",
    "wof:placetype":"venue"
},
  "geometry": {"coordinates":[4.422908,52.192993],"type":"Point"}
}