{
  "type": "Feature",
  "properties": {
    "addr:full":"Moliereln 168 Venlo Limburg 5924 AN",
    "addr:housenumber":"168",
    "addr:postcode":"5924 an",
    "iso:country":"NL",
    "sg:address":"Moliereln 168",
    "sg:city":"Venlo",
    "sg:orig_category":"Evenementenverzorging",
    "sg:phone":"+31 77 382 3462",
    "sg:postcode":"5924 AN",
    "sg:province":"Limburg",
    "wof:name":"Coupe Int",
    "wof:placetype":"venue"
},
  "geometry": {"coordinates":[6.13,51.366501],"type":"Point"}
}