{
  "type": "Feature",
  "properties": {
    "iso:country":"NL",
    "sg:address":"Het Zool 44",
    "sg:city":"Leeuwarden",
    "sg:orig_category":"Adviesbureaus Bouwkunde",
    "sg:phone":"+31 58 288 2944",
    "sg:postcode":"8939 BM",
    "sg:province":"Provincie Friesland",
    "wof:name":"Veldtman",
    "wof:placetype":"venue"
},
  "geometry": {"coordinates":[5.828966,53.181606],"type":"Point"}
}