{
  "type": "Feature",
  "properties": {
    "addr:full":"Zuiderbuurt 47 Drachten Friesland 9203 CT",
    "addr:housenumber":"47",
    "addr:postcode":"9203 ct",
    "addr:street":"Zuiderbuurt",
    "iso:country":"NL",
    "sg:address":"Zuiderbuurt 47",
    "sg:city":"Drachten",
    "sg:orig_category":"Huishoudapparatuur, Televisies And Radio'S",
    "sg:phone":"+31 512 526 000",
    "sg:postcode":"9203 CT",
    "sg:province":"Friesland",
    "wof:name":"S & F Scheer & Foppen",
    "wof:placetype":"venue"
},
  "geometry": {"coordinates":[6.098558,53.104809],"type":"Point"}
}