{
  "type": "Feature",
  "properties": {
    "addr:full":"Soendastraat 12 'S Gravenhage Zuid-Holland 2585 VD",
    "addr:housenumber":"12",
    "addr:postcode":"2585 vd",
    "addr:street":"Soendastraat;' S",
    "iso:country":"NL",
    "sg:address":"Soendastraat 12",
    "sg:city":"'S Gravenhage",
    "sg:orig_category":"Artiesten",
    "sg:phone":"+31 70 350 5095",
    "sg:postcode":"2585 VD",
    "sg:province":"Zuid-Holland",
    "wof:name":"W Van Roon-Telders",
    "wof:placetype":"venue"
},
  "geometry": {"coordinates":[4.303711,52.091526],"type":"Point"}
}