{
  "type": "Feature",
  "properties": {
    "addr:full":"V Speykstr 143B Rotterdam South Holland 3014 VJ",
    "addr:housenumber":"143b",
    "addr:postcode":"3014 vj",
    "iso:country":"NL",
    "sg:address":"V Speykstr 143B",
    "sg:city":"Rotterdam",
    "sg:orig_category":"Muziekinstrumenten En Bladmuziek",
    "sg:phone":"+31 10 436 5364",
    "sg:postcode":"3014 VJ",
    "sg:province":"South Holland",
    "wof:name":"Accordeonpaleis, 'T",
    "wof:placetype":"venue"
},
  "geometry": {"coordinates":[4.478455,51.922836],"type":"Point"}
}