{
  "type": "Feature",
  "properties": {
    "addr:full":"Delflandplein 18 Amsterdam North Holland 1062 HR",
    "addr:housenumber":"18",
    "addr:postcode":"1062 hr",
    "addr:street":"Delflandplein",
    "iso:country":"NL",
    "sg:address":"Delflandplein 18",
    "sg:city":"Amsterdam",
    "sg:classifiers":[
        {
            "category":"Communications",
            "subcategory":"Television Station",
            "type":"Services"
        }
    ],
    "sg:phone":"+31 20 617 7506",
    "sg:postcode":"1062 HR",
    "sg:province":"North Holland",
    "sg:tags":[
        "video",
        "audio",
        "verhuur"
    ],
    "wof:name":"De Filmfreak The Pink Panther",
    "wof:placetype":"venue"
},
  "geometry": {"coordinates":[4.840338,52.349815],"type":"Point"}
}