{
  "type": "Feature",
  "properties": {
    "addr:full":"Tiendwg W 28 Lekkerkerk Zuid-Holland 2941 ER",
    "addr:postcode":"2941 er",
    "addr:street":"W 28",
    "iso:country":"NL",
    "sg:address":"Tiendwg W 28",
    "sg:city":"Lekkerkerk",
    "sg:orig_category":"Melktransporten",
    "sg:phone":"+31 180 662 365",
    "sg:postcode":"2941 ER",
    "sg:province":"Zuid-Holland",
    "wof:name":"Jager En Overvoorde, Fa De",
    "wof:placetype":"venue"
},
  "geometry": {"coordinates":[4.663155,51.901234],"type":"Point"}
}