{
  "type": "Feature",
  "properties": {
    "addr:full":"Voltaweg 1 Vlissingen Zeeland 4382 NG",
    "addr:housenumber":"1",
    "addr:postcode":"4382 ng",
    "addr:street":"Voltaweg",
    "iso:country":"NL",
    "sg:address":"Voltaweg 1",
    "sg:city":"Vlissingen",
    "sg:orig_category":"Autokeuringen",
    "sg:phone":"+31 118 465 939",
    "sg:postcode":"4382 NG",
    "sg:province":"Zeeland",
    "wof:name":"K Huiszoon Handelsonderneming",
    "wof:placetype":"venue"
},
  "geometry": {"coordinates":[3.590408,51.452168],"type":"Point"}
}