{
  "type": "Feature",
  "properties": {
    "addr:full":"Hei Grindelwg 82 Heerlen Limburg 6414 BT",
    "addr:housenumber":"82",
    "addr:postcode":"6414 bt",
    "iso:country":"NL",
    "sg:address":"Hei Grindelwg 82",
    "sg:city":"Heerlen",
    "sg:orig_category":"Peuterspeelzalen",
    "sg:phone":"+31 45 523 0394",
    "sg:postcode":"6414 BT",
    "sg:province":"Limburg",
    "wof:name":"Belhameltjes, De",
    "wof:placetype":"venue"
},
  "geometry": {"coordinates":[5.971151,50.912834],"type":"Point"}
}