{
  "type": "Feature",
  "properties": {
    "iso:country":"NL",
    "sg:address":"Bergwg 147",
    "sg:city":"Rotterdam",
    "sg:orig_category":"Autorijscholen",
    "sg:phone":"+31 10 466 1398",
    "sg:postcode":"3037 EG",
    "sg:province":"Zuid-Holland",
    "wof:name":"Bastinck",
    "wof:placetype":"venue"
},
  "geometry": {"coordinates":[4.469808,51.934444],"type":"Point"}
}