{
  "type": "Feature",
  "properties": {
    "iso:country":"NL",
    "sg:address":"Nijverheidslaan 34",
    "sg:city":"Weesp",
    "sg:orig_category":"Diverse Bedrijfsinstallaties Gh",
    "sg:phone":"+31 294 413 451",
    "sg:postcode":"1382 LJ",
    "sg:province":"North Holland",
    "wof:name":"Wanson Bv",
    "wof:placetype":"venue"
},
  "geometry": {"coordinates":[5.053107,52.311306],"type":"Point"}
}