{
  "type": "Feature",
  "properties": {
    "addr:full":"Nijverheidslaan 34 Weesp North Holland 1382 LJ",
    "addr:housenumber":"34",
    "addr:postcode":"1382 lj",
    "addr:street":"Nijverheidslaan",
    "iso:country":"NL",
    "sg:address":"Nijverheidslaan 34",
    "sg:city":"Weesp",
    "sg:orig_category":"Diverse Bedrijfsinstallaties Gh",
    "sg:phone":"+31 294 413 451",
    "sg:postcode":"1382 LJ",
    "sg:province":"North Holland",
    "wof:name":"Wanson Bv",
    "wof:placetype":"venue"
},
  "geometry": {"coordinates":[5.053107,52.311306],"type":"Point"}
}