{
  "type": "Feature",
  "properties": {
    "addr:full":"Stationsweg 164 Hillegom Zuid-Holland 2182 BE",
    "addr:housenumber":"164",
    "addr:postcode":"2182",
    "addr:street":"Stationsweg",
    "iso:country":"NL",
    "sg:address":"Stationsweg 164",
    "sg:city":"Hillegom",
    "sg:orig_category":"Verzekeringen",
    "sg:phone":"+31 252 516 127",
    "sg:postcode":"2182 BE",
    "sg:province":"Zuid-Holland",
    "wof:name":"Ass Kant J F Van Trigt",
    "wof:placetype":"venue"
},
  "geometry": {"coordinates":[4.572767,52.301418],"type":"Point"}
}