{
  "type": "Feature",
  "properties": {
    "addr:full":"Pomonaweg 44 Loppersum Groningen 9919 HW",
    "addr:housenumber":"44",
    "addr:postcode":"9919 hw",
    "addr:street":"Pomonaweg",
    "iso:country":"NL",
    "sg:address":"Pomonaweg 44",
    "sg:city":"Loppersum",
    "sg:classifiers":[
        {
            "category":"Education",
            "subcategory":"Preschool",
            "type":"Public Place"
        }
    ],
    "sg:phone":"+31 596 572 616",
    "sg:postcode":"9919 HW",
    "sg:province":"Groningen",
    "sg:tags":[
        "kleuteronderwijs",
        "basis-"
    ],
    "wof:name":"Openbare Basisschool Prinses Beatrix",
    "wof:placetype":"venue"
},
  "geometry": {"coordinates":[6.74058,53.333035],"type":"Point"}
}