{
  "type": "Feature",
  "properties": {
    "addr:full":"Dellewg 13 Stedum Groningen 9921 TG",
    "addr:housenumber":"13",
    "addr:postcode":"9921 tg",
    "addr:street":"Dellewg",
    "iso:country":"NL",
    "sg:address":"Dellewg 13",
    "sg:city":"Stedum",
    "sg:orig_category":"Adviesbureaus Bedrijfsorganisatie",
    "sg:phone":"+31 596 551 733",
    "sg:postcode":"9921 TG",
    "sg:province":"Groningen",
    "wof:name":"Nieboer, Drs E L G",
    "wof:placetype":"venue"
},
  "geometry": {"coordinates":[6.680211,53.333755],"type":"Point"}
}