{
  "type": "Feature",
  "properties": {
    "addr:full":"Mastwijkerdijk 128 Montfoort Utrecht 3417 BT",
    "addr:housenumber":"128",
    "addr:postcode":"3417 bt",
    "addr:street":"Mastwijkerdijk",
    "iso:country":"NL",
    "sg:address":"Mastwijkerdijk 128",
    "sg:city":"Montfoort",
    "sg:orig_category":"Metaalafval, Schrootrecycling And Sloperijen",
    "sg:phone":"+31 348 471 779",
    "sg:postcode":"3417 BT",
    "sg:province":"Utrecht",
    "wof:name":"Autodemontagebedrijf Wilco Bv",
    "wof:placetype":"venue"
},
  "geometry": {"coordinates":[4.96398,52.056873],"type":"Point"}
}