{
  "type": "Feature",
  "properties": {
    "addr:full":"Oosterdijk 63 Sneek Provincie Friesland 8601 BR",
    "addr:housenumber":"63;8601",
    "addr:postcode":"br",
    "addr:street":"Oosterdijk;Provincie Friesland",
    "iso:country":"NL",
    "sg:address":"Oosterdijk 63",
    "sg:city":"Sneek",
    "sg:orig_category":"Verlichting And Huishoudartikelen",
    "sg:phone":"+31 515 431 949",
    "sg:postcode":"8601 BR",
    "sg:province":"Provincie Friesland",
    "wof:name":"Marskramer Bv",
    "wof:placetype":"venue"
},
  "geometry": {"coordinates":[5.66197,53.033459],"type":"Point"}
}