{
  "type": "Feature",
  "properties": {
    "addr:full":"Markt 5 Kerkrade Limburg 6461 EB",
    "addr:housenumber":"5",
    "addr:postcode":"6461 eb",
    "addr:street":"Markt",
    "iso:country":"NL",
    "sg:address":"Markt 5",
    "sg:city":"Kerkrade",
    "sg:orig_category":"Kaas",
    "sg:phone":"+31 45 545 4760",
    "sg:postcode":"6461 EB",
    "sg:province":"Limburg",
    "wof:name":"Kaasshop, De",
    "wof:placetype":"venue"
},
  "geometry": {"coordinates":[6.0630431175,50.8656463623],"type":"Point"}
}