{
  "type": "Feature",
  "properties": {
    "addr:full":"Verspronckwg 48 Haarlem Noord-Holland 2023 BM",
    "addr:housenumber":"48",
    "addr:postcode":"2023 bm",
    "addr:street":"Verspronckwg",
    "iso:country":"NL",
    "sg:address":"Verspronckwg 48",
    "sg:city":"Haarlem",
    "sg:orig_category":"Psychologen",
    "sg:phone":"+31 23 527 1529",
    "sg:postcode":"2023 BM",
    "sg:province":"Noord-Holland",
    "wof:name":"Bolt, H",
    "wof:placetype":"venue"
},
  "geometry": {"coordinates":[4.628229,52.389885],"type":"Point"}
}