{
  "type": "Feature",
  "properties": {
    "addr:full":"Strawinskyweg 37 Veenendaal Utrecht 3906 BA",
    "addr:housenumber":"37",
    "addr:postcode":"3906 ba",
    "addr:street":"Strawinskyweg",
    "iso:country":"NL",
    "sg:address":"Strawinskyweg 37",
    "sg:city":"Veenendaal",
    "sg:orig_category":"Paramedische Behandelingen",
    "sg:phone":"+31 318 511 174",
    "sg:postcode":"3906 BA",
    "sg:province":"Utrecht",
    "wof:name":"E. Schriemer",
    "wof:placetype":"venue"
},
  "geometry": {"coordinates":[5.535681,52.034588],"type":"Point"}
}