{
  "type": "Feature",
  "properties": {
    "iso:country":"NL",
    "sg:address":"Jacob Gillesstraat 6",
    "sg:city":"'S Gravenhage",
    "sg:orig_category":"Medische Apparatuur And Prothesen Fab",
    "sg:phone":"+31 70 352 1226",
    "sg:postcode":"2582 XZ",
    "sg:province":"Zuid-Holland",
    "wof:name":"Dental Line",
    "wof:placetype":"venue"
},
  "geometry": {"coordinates":[4.275117,52.087563],"type":"Point"}
}