{
  "type": "Feature",
  "properties": {
    "iso:country":"NL",
    "sg:address":"Tolbergcentrum 144",
    "sg:city":"Roosendaal",
    "sg:orig_category":"Banken",
    "sg:phone":"+31 165 596 000",
    "sg:postcode":"4708 HK",
    "sg:province":"Noord-Brabant",
    "sg:website":"http://www.rabobank.nl",
    "wof:name":"Rabobank",
    "wof:placetype":"venue"
},
  "geometry": {"coordinates":[4.439147,51.513432],"type":"Point"}
}