{
  "type": "Feature",
  "properties": {
    "addr:full":"Lindenhorst 28 Ede Gld Gelderland 6714 JW",
    "addr:housenumber":"28",
    "addr:postcode":"6714 jw",
    "addr:street":"Lindenhorst;Gld Gelderland",
    "iso:country":"NL",
    "sg:address":"Lindenhorst 28",
    "sg:city":"Ede Gld",
    "sg:orig_category":"Bloemen En Planten - Decoratie",
    "sg:phone":"+31 318 633 900",
    "sg:postcode":"6714 JW",
    "sg:province":"Gelderland",
    "wof:name":"Lindenhorst, De",
    "wof:placetype":"venue"
},
  "geometry": {"coordinates":[5.643462,52.046764],"type":"Point"}
}