{
  "type": "Feature",
  "properties": {
    "addr:full":"Industriewg 4B Heusden Gem Heusd Noord-Brabant 5256 PN",
    "addr:housenumber":"4b",
    "addr:postcode":"heusd;5256 pn",
    "addr:street":"Industriewg",
    "iso:country":"NL",
    "sg:address":"Industriewg 4B",
    "sg:city":"Heusden Gem Heusd",
    "sg:orig_category":"Natuursteen",
    "sg:phone":"+31 416 665 020",
    "sg:postcode":"5256 PN",
    "sg:province":"Noord-Brabant",
    "wof:name":"Petrumus",
    "wof:placetype":"venue"
},
  "geometry": {"coordinates":[5.13727,51.733074],"type":"Point"}
}