{
  "type": "Feature",
  "properties": {
    "addr:full":"By De Leywei 85 Hoornsterzwaag Friesland 8412 SJ",
    "addr:housenumber":"85",
    "addr:postcode":"8412",
    "iso:country":"NL",
    "sg:address":"By De Leywei 85",
    "sg:city":"Hoornsterzwaag",
    "sg:classifiers":[
        {
            "category":"Wholesale",
            "subcategory":"Motor Vehicles",
            "type":"Manufacturing & Wholesale Goods"
        }
    ],
    "sg:phone":"+31 516 462 150",
    "sg:postcode":"8412 SJ",
    "sg:province":"Friesland",
    "sg:tags":[
        "scooter",
        "en"
    ],
    "wof:name":"Haan, De",
    "wof:placetype":"venue"
},
  "geometry": {"coordinates":[6.156955,53.015709],"type":"Point"}
}