{
  "type": "Feature",
  "properties": {
    "addr:full":"Wouwsestraat 23 Bergen Op Zoom Noord-Brabant 4611 PK",
    "addr:housenumber":"23",
    "addr:postcode":"4611 pk",
    "addr:street":"Wouwsestraat",
    "iso:country":"NL",
    "sg:address":"Wouwsestraat 23",
    "sg:city":"Bergen Op Zoom",
    "sg:orig_category":"Baby- And Kinderkleding",
    "sg:phone":"+31 164 211 339",
    "sg:postcode":"4611 PK",
    "sg:province":"Noord-Brabant",
    "wof:name":"We Men",
    "wof:placetype":"venue"
},
  "geometry": {"coordinates":[4.29192,51.495369],"type":"Point"}
}