{
  "type": "Feature",
  "properties": {
    "addr:full":"Componistenln 96 Gouda Zuid-Holland 2807 HD",
    "addr:housenumber":"96",
    "addr:postcode":"2807 hd",
    "addr:street":"Componistenln",
    "iso:country":"NL",
    "sg:address":"Componistenln 96",
    "sg:city":"Gouda",
    "sg:orig_category":"Fotoreportages",
    "sg:phone":"+31 182 518 864",
    "sg:postcode":"2807 HD",
    "sg:province":"Zuid-Holland",
    "sg:website":"http://www.sandrazeilstra.nl",
    "wof:name":"Sandra Zeilstra",
    "wof:placetype":"venue"
},
  "geometry": {"coordinates":[4.747911,52.013008],"type":"Point"}
}