{
  "type": "Feature",
  "properties": {
    "addr:full":"Laat 1 Alkmaar North Holland 1811 EA",
    "addr:housenumber":"1",
    "addr:postcode":"1811 ea",
    "addr:street":"Laat",
    "iso:country":"NL",
    "sg:address":"Laat 1",
    "sg:city":"Alkmaar",
    "sg:orig_category":"Parketvloeren",
    "sg:phone":"+31 72 511 2115",
    "sg:postcode":"1811 EA",
    "sg:province":"North Holland",
    "wof:name":"Multi Vloer Alkmaar",
    "wof:placetype":"venue"
},
  "geometry": {"coordinates":[4.752502,52.62838],"type":"Point"}
}