{
  "type": "Feature",
  "properties": {
    "addr:full":"Hooge Akker 22 Vessem Noord-Brabant 5512 BV",
    "addr:housenumber":"22",
    "addr:postcode":"5512 bv",
    "addr:street":"Hooge Akker",
    "iso:country":"NL",
    "sg:address":"Hooge Akker 22",
    "sg:city":"Vessem",
    "sg:orig_category":"Boekhouders",
    "sg:phone":"+31 497 594 020",
    "sg:postcode":"5512 BV",
    "sg:province":"Noord-Brabant",
    "wof:name":"Administratiekantoor Schoofs-De Vries",
    "wof:placetype":"venue"
},
  "geometry": {"coordinates":[8.54226,54.568062],"type":"Point"}
}