{
  "type": "Feature",
  "properties": {
    "addr:full":"Speulmanwg 5A Beusichem North Dakota 4112 ND",
    "addr:housenumber":"5a",
    "addr:postcode":"4112 nd",
    "addr:street":"Speulmanwg",
    "iso:country":"NL",
    "sg:address":"Speulmanwg 5A",
    "sg:city":"Beusichem",
    "sg:orig_category":"Projectinrichting",
    "sg:phone":"+31 345 501 803",
    "sg:postcode":"4112 ND",
    "sg:province":"North Dakota",
    "wof:name":"Sch\u00fcrgers Collection",
    "wof:placetype":"venue"
},
  "geometry": {"coordinates":[-100.30171199999999,47.467731],"type":"Point"}
}