{
  "type": "Feature",
  "properties": {
    "addr:full":"Birkstr 146 Soest Utrecht 3768 HP",
    "addr:housenumber":"146",
    "addr:postcode":"3768 hp",
    "addr:street":"Soest",
    "iso:country":"NL",
    "sg:address":"Birkstr 146",
    "sg:city":"Soest",
    "sg:orig_category":"Honden- En Kattentrimsalons",
    "sg:phone":"+31 33 461 2074",
    "sg:postcode":"3768 HP",
    "sg:province":"Utrecht",
    "wof:name":"Toonen, Harriet",
    "wof:placetype":"venue"
},
  "geometry": {"coordinates":[5.34181,52.16748],"type":"Point"}
}