{
  "type": "Feature",
  "properties": {
    "addr:full":"Hazelaarstr 5 St Willebrord North Brabant 4711 RE",
    "addr:housenumber":"5",
    "addr:postcode":"4711 re",
    "addr:street":"Hazelaarstr;St",
    "iso:country":"NL",
    "sg:address":"Hazelaarstr 5",
    "sg:city":"St Willebrord",
    "sg:orig_category":"Betonijzervlechten",
    "sg:phone":"+31 165 384 205",
    "sg:postcode":"4711 RE",
    "sg:province":"North Brabant",
    "wof:name":"Wijnings",
    "wof:placetype":"venue"
},
  "geometry": {"coordinates":[4.579712,51.547073],"type":"Point"}
}