{
  "type": "Feature",
  "properties": {
    "addr:full":"Luchthavenwg 6E Den Helder North Holland 1786 PP",
    "addr:housenumber":"6e",
    "addr:postcode":"1786 pp",
    "addr:street":"Luchthavenwg",
    "iso:country":"NL",
    "sg:address":"Luchthavenwg 6E",
    "sg:city":"Den Helder",
    "sg:orig_category":"Accountants - Administratie- Consulenten En -Kantoren",
    "sg:phone":"+31 223 522 550",
    "sg:postcode":"1786 PP",
    "sg:province":"North Holland",
    "wof:name":"Ltb Bv",
    "wof:placetype":"venue"
},
  "geometry": {"coordinates":[4.785284,52.921085],"type":"Point"}
}