{
  "type": "Feature",
  "properties": {
    "addr:full":"Aquamarynstr 106 Hengelo Ov Overijssel 7554 NT",
    "addr:housenumber":"106",
    "addr:postcode":"7554 nt",
    "addr:street":"Ov",
    "iso:country":"NL",
    "sg:address":"Aquamarynstr 106",
    "sg:city":"Hengelo Ov",
    "sg:orig_category":"Verfspuitinstallaties",
    "sg:phone":"+31 74 256 9569",
    "sg:postcode":"7554 NT",
    "sg:province":"Overijssel",
    "wof:name":"Braker, Toon",
    "wof:placetype":"venue"
},
  "geometry": {"coordinates":[6.76553,52.238659],"type":"Point"}
}