{
  "type": "Feature",
  "properties": {
    "addr:full":"Oude Delft 197 Delft Zuid-Holland 2611 HD",
    "addr:housenumber":"197",
    "addr:postcode":"2611 hd",
    "addr:street":"Oude Delft",
    "iso:country":"NL",
    "sg:address":"Oude Delft 197",
    "sg:city":"Delft",
    "sg:orig_category":"Advocaten And Juridische Adviseurs",
    "sg:phone":"+31 15 213 6241",
    "sg:postcode":"2611 HD",
    "sg:province":"Zuid-Holland",
    "wof:name":"Advocatenkantoor Mr. C. Vidor",
    "wof:placetype":"venue"
},
  "geometry": {"coordinates":[4.354481,52.013157],"type":"Point"}
}