{
  "type": "Feature",
  "properties": {
    "iso:country":"NL",
    "sg:address":"Zuiderparkln 265",
    "sg:city":"S Gravenhage",
    "sg:classifiers":[
        {
            "category":"Food & Beverages",
            "subcategory":"Bakery",
            "type":"Retail Goods"
        }
    ],
    "sg:phone":"+31 70 365 8109",
    "sg:postcode":"2574 GA",
    "sg:province":"Zuid-Holland",
    "sg:tags":[
        "brood",
        "en",
        "banket"
    ],
    "wof:name":"Kempen, C J Van",
    "wof:placetype":"venue"
},
  "geometry": {"coordinates":[4.277523,52.064205],"type":"Point"}
}