{
  "type": "Feature",
  "properties": {
    "addr:full":"Oosteinderweg 44 Wognum Noord-Holland 1687 AD",
    "addr:housenumber":"44",
    "addr:postcode":"1687 ad",
    "addr:street":"Oosteinderweg",
    "iso:country":"NL",
    "sg:address":"Oosteinderweg 44",
    "sg:city":"Wognum",
    "sg:orig_category":"Glaszetten",
    "sg:phone":"+31 229 572 073",
    "sg:postcode":"1687 AD",
    "sg:province":"Noord-Holland",
    "wof:name":"De Glazenier",
    "wof:placetype":"venue"
},
  "geometry": {"coordinates":[5.040012,52.683182],"type":"Point"}
}