{
  "type": "Feature",
  "properties": {
    "addr:full":"Vroegeling 11 Nijverdal Overijssel 7443 MC",
    "addr:housenumber":"11",
    "addr:postcode":"7443 mc",
    "addr:street":"Vroegeling",
    "iso:country":"NL",
    "sg:address":"Vroegeling 11",
    "sg:city":"Nijverdal",
    "sg:orig_category":"Schoonheidssalons",
    "sg:phone":"+31 548 618 099",
    "sg:postcode":"7443 MC",
    "sg:province":"Overijssel",
    "wof:name":"Schoonheidssalon Ankie Stevens",
    "wof:placetype":"venue"
},
  "geometry": {"coordinates":[6.48463,52.38131],"type":"Point"}
}