{
  "type": "Feature",
  "properties": {
    "addr:full":"Zuiderzeestrwg 328 Oldebroek Gelderland 8096 CL",
    "addr:housenumber":"328",
    "addr:postcode":"8096",
    "addr:street":"Gelderland",
    "iso:country":"NL",
    "sg:address":"Zuiderzeestrwg 328",
    "sg:city":"Oldebroek",
    "sg:orig_category":"Fietsen En Bromfietsen",
    "sg:phone":"+31 525 631 351",
    "sg:postcode":"8096 CL",
    "sg:province":"Gelderland",
    "wof:name":"Zoombelt, J P F",
    "wof:placetype":"venue"
},
  "geometry": {"coordinates":[5.8934,52.445419],"type":"Point"}
}