{
  "type": "Feature",
  "properties": {
    "addr:full":"Anker 7 Hellevoetsluis Zuid-Holland 3224 PA",
    "addr:housenumber":"7",
    "addr:postcode":"3224 pa",
    "addr:street":"Anker",
    "iso:country":"NL",
    "sg:address":"Anker 7",
    "sg:city":"Hellevoetsluis",
    "sg:orig_category":"Beautyfarms And Sauna'S",
    "sg:phone":"+31 181 320 789",
    "sg:postcode":"3224 PA",
    "sg:province":"Zuid-Holland",
    "wof:name":"Zonnestudio Joni",
    "wof:placetype":"venue"
},
  "geometry": {"coordinates":[4.156075,51.82481],"type":"Point"}
}