{
  "type": "Feature",
  "properties": {
    "addr:full":"Postbus 9 Boxmeer North Brabant 5830 AA",
    "addr:housenumber":"9",
    "addr:postcode":"5830 aa",
    "addr:street":"Postbus",
    "iso:country":"NL",
    "sg:address":"Postbus 9",
    "sg:city":"Boxmeer",
    "sg:orig_category":"Vertaalbureaus",
    "sg:phone":"+31 485 588 600",
    "sg:postcode":"5830 AA",
    "sg:province":"North Brabant",
    "wof:name":"Stork Tps",
    "wof:placetype":"venue"
},
  "geometry": {"coordinates":[5.950357,51.646206],"type":"Point"}
}