{
  "type": "Feature",
  "properties": {
    "addr:full":"Arena Boulev 83 Amsterdam Zuidoost North Holland 1101 DM",
    "addr:housenumber":"83",
    "addr:postcode":"1101 dm",
    "addr:street":"Boulev",
    "iso:country":"NL",
    "sg:address":"Arena Boulev 83",
    "sg:city":"Amsterdam Zuidoost",
    "sg:orig_category":"Kantoor- En Secretariaatsservice",
    "sg:phone":"+31 20 652 0520",
    "sg:postcode":"1101 DM",
    "sg:province":"North Holland",
    "sg:website":"http://www.d-office.nl",
    "wof:name":"D-Office Amsterdam Bv",
    "wof:placetype":"venue"
},
  "geometry": {"coordinates":[4.942715168,52.3128204346],"type":"Point"}
}