{
  "type": "Feature",
  "properties": {
    "addr:full":"Klazienaveensestraat 109 Nieuw Dordrecht Provincie Drenthe 7885 BC",
    "addr:housenumber":"109",
    "addr:postcode":"7885 bc",
    "addr:street":"Klazienaveensestraat;Nieuw Dordrecht Provincie Drenthe",
    "iso:country":"NL",
    "sg:address":"Klazienaveensestraat 109",
    "sg:city":"Nieuw Dordrecht",
    "sg:orig_category":"Granen, Zaden And Diervoeders Gh",
    "sg:phone":"+31 591 624 104",
    "sg:postcode":"7885 BC",
    "sg:province":"Provincie Drenthe",
    "wof:name":"G. Teuben",
    "wof:placetype":"venue"
},
  "geometry": {"coordinates":[6.964436,52.758419],"type":"Point"}
}