{
  "type": "Feature",
  "properties": {
    "iso:country":"NL",
    "sg:address":"Oude Haven 16",
    "sg:city":"Zierikzee",
    "sg:orig_category":"Makelaars En Adviseurs Verzekeringen",
    "sg:phone":"+31 111 416 888",
    "sg:postcode":"4301 CK",
    "sg:province":"Zeeland",
    "sg:website":"http://www.driewerf.com",
    "wof:name":"Driewerf",
    "wof:placetype":"venue"
},
  "geometry": {"coordinates":[3.924244,51.647991],"type":"Point"}
}