{
  "type": "Feature",
  "properties": {
    "addr:full":"Achtse Loop 36 Eindhoven Noord-Brabant 5626 BW",
    "addr:housenumber":"36",
    "addr:postcode":"5626 bw",
    "addr:street":"Achtse Loop",
    "iso:country":"NL",
    "sg:address":"Achtse Loop 36",
    "sg:city":"Eindhoven",
    "sg:classifiers":[
        {
            "category":"Personal",
            "subcategory":"Nail Salon",
            "type":"Services"
        }
    ],
    "sg:phone":"+31 40 262 3443",
    "sg:postcode":"5626 BW",
    "sg:province":"Noord-Brabant",
    "sg:tags":[
        "pedicure"
    ],
    "wof:name":"Thea, Salon",
    "wof:placetype":"venue"
},
  "geometry": {"coordinates":[5.4287371635,51.4775886536],"type":"Point"}
}