{
  "type": "Feature",
  "properties": {
    "iso:country":"NL",
    "sg:address":"Prins Hendrikkade 133",
    "sg:city":"Rotterdam",
    "sg:orig_category":"Fotostudio'S And Fotografen",
    "sg:phone":"+31 10 411 9335",
    "sg:postcode":"3071 KM",
    "sg:province":"Zuid-Holland",
    "wof:name":"Fairview Images",
    "wof:placetype":"venue"
},
  "geometry": {"coordinates":[4.492134,51.910934],"type":"Point"}
}