{
  "type": "Feature",
  "properties": {
    "addr:full":"De Bongerd 22 Molenhoek Lb Limburg 6584 DH",
    "addr:housenumber":"22",
    "addr:postcode":"lb;6584 dh",
    "addr:street":"De Bongerd",
    "iso:country":"NL",
    "sg:address":"De Bongerd 22",
    "sg:city":"Molenhoek Lb",
    "sg:orig_category":"Meubelzaken, Woning- And Keukeninrichting",
    "sg:phone":"+31 24 358 4982",
    "sg:postcode":"6584 DH",
    "sg:province":"Limburg",
    "wof:name":"T.T.A.",
    "wof:placetype":"venue"
},
  "geometry": {"coordinates":[5.878416,51.774151],"type":"Point"}
}