{
  "type": "Feature",
  "properties": {
    "addr:full":"Groenstr 2 Raamsdonksveer North Brabant 4941 HB",
    "addr:housenumber":"2",
    "addr:postcode":"4941 hb",
    "addr:street":"Groenstr",
    "iso:country":"NL",
    "sg:address":"Groenstr 2",
    "sg:city":"Raamsdonksveer",
    "sg:orig_category":"Prijs- En Codeerapparatuur",
    "sg:phone":"+31 162 521 637",
    "sg:postcode":"4941 HB",
    "sg:province":"North Brabant",
    "wof:name":"Etla",
    "wof:placetype":"venue"
},
  "geometry": {"coordinates":[4.869177,51.692986],"type":"Point"}
}