{
  "type": "Feature",
  "properties": {
    "iso:country":"NL",
    "sg:address":"Jan Valsterweg 30",
    "sg:city":"Dordrecht",
    "sg:orig_category":"Chemische Producten Gh",
    "sg:phone":"+31 78 630 5860",
    "sg:postcode":"3315 LG",
    "sg:province":"South Holland",
    "wof:name":"Gcm Systems Bv",
    "wof:placetype":"venue"
},
  "geometry": {"coordinates":[4.703024,51.804066],"type":"Point"}
}