{
  "type": "Feature",
  "properties": {
    "iso:country":"NL",
    "sg:address":"Boompjes 390",
    "sg:city":"Rotterdam",
    "sg:orig_category":"Projectontwikkeling",
    "sg:phone":"+31 10 413 8590",
    "sg:postcode":"3011 XZ",
    "sg:province":"Zuid-Holland",
    "sg:website":"http://www.sunergy.nl",
    "wof:name":"Sunergy",
    "wof:placetype":"venue"
},
  "geometry": {"coordinates":[4.48668,51.914246],"type":"Point"}
}