{
  "type": "Feature",
  "properties": {
    "addr:full":"Boomstr 161 Tilburg North Brabant 5038 GR",
    "addr:housenumber":"161",
    "addr:postcode":"5038",
    "iso:country":"NL",
    "sg:address":"Boomstr 161",
    "sg:city":"Tilburg",
    "sg:orig_category":"Horecabenodigdheden",
    "sg:phone":"+31 13 469 1010",
    "sg:postcode":"5038 GR",
    "sg:province":"North Brabant",
    "wof:name":"Interfastfood, Tilburg Bv",
    "wof:placetype":"venue"
},
  "geometry": {"coordinates":[5.071247,51.559093],"type":"Point"}
}