{
  "type": "Feature",
  "properties": {
    "addr:full":"Wijngaard 99 Lelystad NL. 8212 CG",
    "addr:housenumber":"99",
    "addr:postcode":"8212 cg",
    "addr:street":"Wijngaard;Nl.",
    "iso:country":"NL",
    "sg:address":"Wijngaard 99",
    "sg:city":"Lelystad",
    "sg:orig_category":"Film-, Tv- And Videoproductie",
    "sg:phone":"+31 320 244 057",
    "sg:postcode":"8212 CG",
    "sg:province":"NL.",
    "wof:name":"Ko Lamboo Produkties",
    "wof:placetype":"venue"
},
  "geometry": {"coordinates":[5.507983,52.516521],"type":"Point"}
}