{
  "type": "Feature",
  "properties": {
    "addr:full":"Plevierstraat 24 Velp Gld Gelderland 6883 CH",
    "addr:housenumber":"24",
    "addr:postcode":"6883",
    "addr:street":"Plevierstraat;Gld Gelderland",
    "iso:country":"NL",
    "sg:address":"Plevierstraat 24",
    "sg:city":"Velp Gld",
    "sg:orig_category":"Public Relationbureaus",
    "sg:phone":"+31 26 363 0417",
    "sg:postcode":"6883 CH",
    "sg:province":"Gelderland",
    "wof:name":"H.P. Westerbeek",
    "wof:placetype":"venue"
},
  "geometry": {"coordinates":[5.983658,51.986809],"type":"Point"}
}