{
  "type": "Feature",
  "properties": {
    "iso:country":"NL",
    "sg:address":"Heiligeweg 43",
    "sg:city":"Krommenie",
    "sg:classifiers":[
        {
            "category":"Communications",
            "subcategory":"Television Station",
            "type":"Services"
        }
    ],
    "sg:phone":"+31 75 621 4837",
    "sg:postcode":"1561 DE",
    "sg:province":"North Holland",
    "sg:tags":[
        "video",
        "audio",
        "verhuur"
    ],
    "wof:name":"De Gouden Beer",
    "wof:placetype":"venue"
},
  "geometry": {"coordinates":[4.765038,52.500935],"type":"Point"}
}