{
  "type": "Feature",
  "properties": {
    "addr:full":"Maliesngl 18 Utrecht Utrecht 3581 BE",
    "addr:housenumber":"18",
    "addr:postcode":"3581",
    "addr:street":"Maliesngl",
    "iso:country":"NL",
    "sg:address":"Maliesngl 18",
    "sg:city":"Utrecht",
    "sg:orig_category":"Makelaars En Adviseurs Onroerende Goederen",
    "sg:phone":"+31 30 231 3035",
    "sg:postcode":"3581 BE",
    "sg:province":"Utrecht",
    "sg:website":"http://www.waltmann.nl",
    "wof:name":"Waltmann & Co",
    "wof:placetype":"venue"
},
  "geometry": {"coordinates":[-73.996292,40.613091],"type":"Point"}
}