{
  "type": "Feature",
  "properties": {
    "addr:full":"Grotestraat 57 A Tegelen Limburg 5931 CT",
    "addr:housenumber":"57 a",
    "addr:postcode":"5931 ct",
    "addr:street":"Grotestraat",
    "iso:country":"NL",
    "sg:address":"Grotestraat 57 A",
    "sg:city":"Tegelen",
    "sg:classifiers":[
        {
            "category":"Fast Food",
            "type":"Food & Drink"
        }
    ],
    "sg:phone":"+31 77 373 3168",
    "sg:postcode":"5931 CT",
    "sg:province":"Limburg",
    "sg:tags":[
        "afhaal",
        "restaurant"
    ],
    "wof:name":"Kervan",
    "wof:placetype":"venue"
},
  "geometry": {"coordinates":[6.135896,51.342167],"type":"Point"}
}