{
  "type": "Feature",
  "properties": {
    "iso:country":"NL",
    "sg:address":"Amstelveensewg 70",
    "sg:city":"Amsterdam",
    "sg:orig_category":"Verenigingen En Stichtingen",
    "sg:phone":"+31 20 618 8758",
    "sg:postcode":"1075 XJ",
    "sg:province":"North Holland",
    "wof:name":"Int Hemp Ass",
    "wof:placetype":"venue"
},
  "geometry": {"coordinates":[4.854863,52.35537],"type":"Point"}
}