{
  "type": "Feature",
  "properties": {
    "addr:full":"Lindtsedijk 88 Zwijndrecht South Holland 3336 LE",
    "addr:housenumber":"88",
    "addr:postcode":"3336 le",
    "addr:street":"Lindtsedijk",
    "iso:country":"NL",
    "sg:address":"Lindtsedijk 88",
    "sg:city":"Zwijndrecht",
    "sg:orig_category":"Onderhoud And Reparatie Kantoorapparatuur",
    "sg:phone":"+31 78 629 2500",
    "sg:postcode":"3336 LE",
    "sg:province":"South Holland",
    "wof:name":"Simac Services Bv",
    "wof:placetype":"venue"
},
  "geometry": {"coordinates":[4.60807,51.811932],"type":"Point"}
}