{
  "type": "Feature",
  "properties": {
    "addr:full":"Leonard Springerlaan 39 Groningen Groningen 9727 KB",
    "addr:housenumber":"39",
    "addr:postcode":"9727 kb",
    "addr:street":"Leonard Springerlaan",
    "iso:country":"NL",
    "sg:address":"Leonard Springerlaan 39",
    "sg:city":"Groningen",
    "sg:orig_category":"Werving And Selectie Van Vast Personeel",
    "sg:phone":"+31 50 314 1070",
    "sg:postcode":"9727 KB",
    "sg:province":"Groningen",
    "wof:name":"Euromatch Bv",
    "wof:placetype":"venue"
},
  "geometry": {"coordinates":[6.553896904,53.2029342651],"type":"Point"}
}