{
  "type": "Feature",
  "properties": {
    "iso:country":"NL",
    "sg:address":"Enkweg 6",
    "sg:city":"Wijhe",
    "sg:orig_category":"Verhuisdiensten",
    "sg:phone":"+31 570 521 666",
    "sg:postcode":"8131 VH",
    "sg:province":"NL.08",
    "wof:name":"Op- En Overslagbedrijf Tielbeke Bv",
    "wof:placetype":"venue"
},
  "geometry": {"coordinates":[6.134183,52.383484],"type":"Point"}
}