{
  "type": "Feature",
  "properties": {
    "iso:country":"NL",
    "sg:address":"De Haere 32",
    "sg:city":"Wenum Wiesel",
    "sg:orig_category":"Autokeuringen",
    "sg:phone":"+31 55 312 1557",
    "sg:postcode":"7345 EL",
    "sg:province":"Gelderland",
    "wof:name":"J. Wolters",
    "wof:placetype":"venue"
},
  "geometry": {"coordinates":[5.963562,52.254066],"type":"Point"}
}