{
  "type": "Feature",
  "properties": {
    "addr:full":"H V Veldekestr 39 Heerlen Limburg 6416 TK",
    "addr:housenumber":"39",
    "addr:postcode":"6416 tk",
    "addr:street":"H;Veldekestr",
    "iso:country":"NL",
    "sg:address":"H V Veldekestr 39",
    "sg:city":"Heerlen",
    "sg:orig_category":"Verenigingen En Stichtingen",
    "sg:phone":"+31 45 541 6571",
    "sg:postcode":"6416 TK",
    "sg:province":"Limburg",
    "wof:name":"Wapenbroeders, Bond Van",
    "wof:placetype":"venue"
},
  "geometry": {"coordinates":[5.98098,50.885506],"type":"Point"}
}