{
  "type": "Feature",
  "properties": {
    "addr:full":"Hildebrandstr 135 S Gravenhage Zuid-Holland 2524 VG",
    "addr:housenumber":"135;gravenhage",
    "addr:postcode":"2524 vg",
    "addr:street":"S",
    "iso:country":"NL",
    "sg:address":"Hildebrandstr 135",
    "sg:city":"S Gravenhage",
    "sg:orig_category":"Meubelen",
    "sg:phone":"+31 70 394 0870",
    "sg:postcode":"2524 VG",
    "sg:province":"Zuid-Holland",
    "wof:name":"Hildebrand",
    "wof:placetype":"venue"
},
  "geometry": {"coordinates":[4.31538,52.052422],"type":"Point"}
}