{
  "type": "Feature",
  "properties": {
    "addr:full":"Van Weerden Poelmanweg 1 Rotterdam South Holland 3088 EA",
    "addr:housenumber":"1",
    "addr:postcode":"3088 ea",
    "addr:street":"Van Weerden Poelmanweg",
    "iso:country":"NL",
    "sg:address":"Van Weerden Poelmanweg 1",
    "sg:city":"Rotterdam",
    "sg:orig_category":"Goederenvervoer Over De Weg",
    "sg:phone":"+31 10 495 0570",
    "sg:postcode":"3088 EA",
    "sg:province":"South Holland",
    "wof:name":"Nabek Rotterdam",
    "wof:placetype":"venue"
},
  "geometry": {"coordinates":[4.443532,51.875214],"type":"Point"}
}