{
  "type": "Feature",
  "properties": {
    "addr:full":"Vondellaan 95 Arnhem Gelderland 6824 NC",
    "addr:housenumber":"95",
    "addr:postcode":"6824 nc",
    "addr:street":"Vondellaan",
    "iso:country":"NL",
    "sg:address":"Vondellaan 95",
    "sg:city":"Arnhem",
    "sg:orig_category":"Autokeuringen",
    "sg:phone":"+31 26 361 4713",
    "sg:postcode":"6824 NC",
    "sg:province":"Gelderland",
    "wof:name":"Vrijhoef-Wegen Bv",
    "wof:placetype":"venue"
},
  "geometry": {"coordinates":[5.945611,51.996323],"type":"Point"}
}