{
  "type": "Feature",
  "properties": {
    "iso:country":"NL",
    "sg:address":"Nieuwstraat 45",
    "sg:city":"Deventer",
    "sg:orig_category":"Werving And Selectie Van Tijdelijk Personeel And Uitzendkantoren",
    "sg:phone":"+31 570 615 005",
    "sg:postcode":"7411 LH",
    "sg:province":"Overijssel",
    "wof:name":"Manpower Uitzendorganisatie Bv",
    "wof:placetype":"venue"
},
  "geometry": {"coordinates":[6.1598992348,52.251033783],"type":"Point"}
}