{
  "type": "Feature",
  "properties": {
    "iso:country":"NL",
    "sg:address":"Dorpsstraat 71",
    "sg:city":"De Koog",
    "sg:classifiers":[
        {
            "category":"Fast Food",
            "type":"Food & Drink"
        }
    ],
    "sg:phone":"+31 222 317 142",
    "sg:postcode":"1796 CA",
    "sg:province":"Noord-Holland",
    "sg:tags":[
        "afhaal",
        "restaurant"
    ],
    "wof:name":"Hatim Pizzeria",
    "wof:placetype":"venue"
},
  "geometry": {"coordinates":[4.762611,53.098621],"type":"Point"}
}