{
  "type": "Feature",
  "properties": {
    "addr:full":"Mathildelaan 25 Eindhoven North Brabant 5611 BD",
    "addr:housenumber":"25",
    "addr:postcode":"5611 bd",
    "addr:street":"Mathildelaan",
    "iso:country":"NL",
    "sg:address":"Mathildelaan 25",
    "sg:city":"Eindhoven",
    "sg:orig_category":"Medische Apparatuur And Prothesen Fab",
    "sg:phone":"+31 40 244 8633",
    "sg:postcode":"5611 BD",
    "sg:province":"North Brabant",
    "wof:name":"Rebadent Ttl",
    "wof:placetype":"venue"
},
  "geometry": {"coordinates":[5.470742,51.441212],"type":"Point"}
}