{
  "type": "Feature",
  "properties": {
    "addr:full":"De Vergulde Pauw 2 Amersfoort Utrecht 3824 CP",
    "addr:housenumber":"2",
    "addr:postcode":"3824 cp",
    "addr:street":"De Vergulde Pauw",
    "iso:country":"NL",
    "sg:address":"De Vergulde Pauw 2",
    "sg:city":"Amersfoort",
    "sg:orig_category":"Glaszetten",
    "sg:phone":"+31 33 456 7173",
    "sg:postcode":"3824 CP",
    "sg:province":"Utrecht",
    "wof:name":"Wolters Glas Service",
    "wof:placetype":"venue"
},
  "geometry": {"coordinates":[5.379436,52.197189],"type":"Point"}
}