{
  "type": "Feature",
  "properties": {
    "addr:full":"Archipelweg 40-44 Leeuwarden Friesland 8924 AC",
    "addr:housenumber":"40-44",
    "addr:postcode":"8924 ac",
    "addr:street":"Archipelweg",
    "iso:country":"NL",
    "sg:address":"Archipelweg 40-44",
    "sg:city":"Leeuwarden",
    "sg:orig_category":"Fietshandelaren",
    "sg:phone":"+31 58 266 0070",
    "sg:postcode":"8924 AC",
    "sg:province":"Friesland",
    "wof:name":"Meindert Fietsplus",
    "wof:placetype":"venue"
},
  "geometry": {"coordinates":[5.818776,53.203369],"type":"Point"}
}