{
  "type": "Feature",
  "properties": {
    "addr:full":"Raadhuisstraat 74 Rucphen North Brabant 4715 CE",
    "addr:housenumber":"74",
    "addr:postcode":"4715 ce",
    "addr:street":"Raadhuisstraat",
    "iso:country":"NL",
    "sg:address":"Raadhuisstraat 74",
    "sg:city":"Rucphen",
    "sg:orig_category":"Meubelzaken, Woning- And Keukeninrichting",
    "sg:phone":"+31 165 341 464",
    "sg:postcode":"4715 CE",
    "sg:province":"North Brabant",
    "wof:name":"Regtop Interieurs Vof",
    "wof:placetype":"venue"
},
  "geometry": {"coordinates":[4.562745,51.532402],"type":"Point"}
}