{
  "type": "Feature",
  "properties": {
    "addr:full":"Wildenborch 73 Leidschendam Zuid-Holland 2261 XK",
    "addr:housenumber":"73",
    "addr:postcode":"2261 xk",
    "addr:street":"Wildenborch",
    "iso:country":"NL",
    "sg:address":"Wildenborch 73",
    "sg:city":"Leidschendam",
    "sg:orig_category":"Schoonheidsinstituten",
    "sg:phone":"+31 70 327 8124",
    "sg:postcode":"2261 XK",
    "sg:province":"Zuid-Holland",
    "wof:name":"Jansen, Tonny",
    "wof:placetype":"venue"
},
  "geometry": {"coordinates":[4.40041,52.101944],"type":"Point"}
}