{
  "type": "Feature",
  "properties": {
    "addr:full":"Manderveensewg 63 Manderveen Overijssel 7664 VS",
    "addr:housenumber":"63",
    "addr:postcode":"7664 vs",
    "addr:street":"Manderveensewg",
    "iso:country":"NL",
    "sg:address":"Manderveensewg 63",
    "sg:city":"Manderveen",
    "sg:orig_category":"Sportverenigingen En Ontspannings- Verenigingen",
    "sg:phone":"+31 541 680 867",
    "sg:postcode":"7664 VS",
    "sg:province":"Overijssel",
    "wof:name":"Manderveen Vv",
    "wof:placetype":"venue"
},
  "geometry": {"coordinates":[6.779976,52.442825],"type":"Point"}
}