{
  "type": "Feature",
  "properties": {
    "addr:full":"Waarderwg 56 Haarlem Noord-Holland 2031 BP",
    "addr:housenumber":"56",
    "addr:postcode":"2031 bp",
    "addr:street":"Waarderwg",
    "iso:country":"NL",
    "sg:address":"Waarderwg 56",
    "sg:city":"Haarlem",
    "sg:orig_category":"Grafisch Ontwerpers",
    "sg:phone":"+31 23 551 6289",
    "sg:postcode":"2031 BP",
    "sg:province":"Noord-Holland",
    "wof:name":"Kostermans",
    "wof:placetype":"venue"
},
  "geometry": {"coordinates":[4.661475,52.397541],"type":"Point"}
}