{
  "type": "Feature",
  "properties": {
    "addr:full":"Kerkpad 8 Haskerhorne Friesland 8506 BA",
    "addr:housenumber":"8",
    "addr:postcode":"8506 ba",
    "addr:street":"Kerkpad",
    "iso:country":"NL",
    "sg:address":"Kerkpad 8",
    "sg:city":"Haskerhorne",
    "sg:orig_category":"Goederenvervoer Over De Weg",
    "sg:phone":"+31 513 412 579",
    "sg:postcode":"8506 BA",
    "sg:province":"Friesland",
    "wof:name":"A.S. Locht",
    "wof:placetype":"venue"
},
  "geometry": {"coordinates":[5.827912,52.952827],"type":"Point"}
}