{
  "type": "Feature",
  "properties": {
    "iso:country":"NL",
    "sg:address":"Kooiwg 15",
    "sg:city":"Giethoorn",
    "sg:orig_category":"Onderhoudswerken",
    "sg:phone":"+31 521 371 519",
    "sg:postcode":"8355 VD",
    "sg:province":"Overijssel",
    "wof:name":"Lok, Bart",
    "wof:placetype":"venue"
},
  "geometry": {"coordinates":[6.023929,52.74638],"type":"Point"}
}