{
  "type": "Feature",
  "properties": {
    "iso:country":"NL",
    "sg:address":"Richard Sturenberghlaan 68",
    "sg:city":"Voorburg",
    "sg:orig_category":"Loodgieterswerk, Verwarming And Sanitaire Installaties",
    "sg:phone":"+31 70 386 8869",
    "sg:postcode":"2273 GZ",
    "sg:province":"South Holland",
    "wof:name":"J.J.M. Schokker",
    "wof:placetype":"venue"
},
  "geometry": {"coordinates":[4.36223,52.082142],"type":"Point"}
}