{
  "type": "Feature",
  "properties": {
    "addr:full":"Hoefslag 61 Nijkerk Gld Gelderland 3862 KA",
    "addr:housenumber":"61",
    "addr:postcode":"3862 ka",
    "addr:street":"Hoefslag;Gld Gelderland",
    "iso:country":"NL",
    "sg:address":"Hoefslag 61",
    "sg:city":"Nijkerk Gld",
    "sg:orig_category":"Banken And Kredietinstellingen",
    "sg:phone":"+31 33 247 5475",
    "sg:postcode":"3862 KA",
    "sg:province":"Gelderland",
    "wof:name":"Rabobank",
    "wof:placetype":"venue"
},
  "geometry": {"coordinates":[5.491164,52.214836],"type":"Point"}
}