{
  "type": "Feature",
  "properties": {
    "addr:full":"Oosterbracht 40 Emmen Drenthe 7821 CG",
    "addr:housenumber":"40",
    "addr:postcode":"7821 cg",
    "addr:street":"Oosterbracht",
    "iso:country":"NL",
    "sg:address":"Oosterbracht 40",
    "sg:city":"Emmen",
    "sg:orig_category":"Banden",
    "sg:phone":"+31 591 613 938",
    "sg:postcode":"7821 CG",
    "sg:province":"Drenthe",
    "sg:website":"http://www.euromaster.com",
    "wof:name":"Euromaster",
    "wof:placetype":"venue"
},
  "geometry": {"coordinates":[6.90091,52.768124],"type":"Point"}
}