{
  "type": "Feature",
  "properties": {
    "addr:full":"Pieternelweg 3 Noordwijk Zh Zuid-Holland 2202 CR",
    "addr:housenumber":"3;2202",
    "addr:postcode":"cr",
    "addr:street":"Pieternelweg",
    "iso:country":"NL",
    "sg:address":"Pieternelweg 3",
    "sg:city":"Noordwijk Zh",
    "sg:orig_category":"Organisaties And Verenigingen",
    "sg:phone":"+31 71 364 7007",
    "sg:postcode":"2202 CR",
    "sg:province":"Zuid-Holland",
    "wof:name":"Stichting Tegen Zinloos Geweld",
    "wof:placetype":"venue"
},
  "geometry": {"coordinates":[4.4351391792,52.2417984009],"type":"Point"}
}