{
  "type": "Feature",
  "properties": {
    "addr:full":"Hippolytusbuurt 14 Delft Zuid-Holland 2611 HN",
    "addr:housenumber":"14",
    "addr:postcode":"2611 hn",
    "addr:street":"Hippolytusbuurt",
    "iso:country":"NL",
    "sg:address":"Hippolytusbuurt 14",
    "sg:city":"Delft",
    "sg:orig_category":"Postkantoren",
    "sg:phone":"+31 15 212 4511",
    "sg:postcode":"2611 HN",
    "sg:province":"Zuid-Holland",
    "sg:website":"http://www.postkantoor.nl",
    "wof:name":"Postkantoor",
    "wof:placetype":"venue"
},
  "geometry": {"coordinates":[4.357349,52.012264],"type":"Point"}
}