{
  "type": "Feature",
  "properties": {
    "iso:country":"NL",
    "sg:address":"Molenstraat 24",
    "sg:city":"Steenwijk",
    "sg:orig_category":"Overheidsdiensten",
    "sg:phone":"+31 521 514 986",
    "sg:postcode":"8331 HR",
    "sg:province":"NL.08",
    "wof:name":"De Beitel",
    "wof:placetype":"venue"
},
  "geometry": {"coordinates":[6.1177921295,52.7861747742],"type":"Point"}
}