{
  "type": "Feature",
  "properties": {
    "addr:full":"Cannenburg 81 Hoofddorp Noord-Holland 2135 CE",
    "addr:housenumber":"81",
    "addr:postcode":"2135 ce",
    "addr:street":"Cannenburg",
    "iso:country":"NL",
    "sg:address":"Cannenburg 81",
    "sg:city":"Hoofddorp",
    "sg:orig_category":"Wegen And Sportterreinen",
    "sg:phone":"+31 23 563 4281",
    "sg:postcode":"2135 CE",
    "sg:province":"Noord-Holland",
    "wof:name":"A.W. Van Alphen",
    "wof:placetype":"venue"
},
  "geometry": {"coordinates":[4.6590099335,52.308216095],"type":"Point"}
}