{
  "type": "Feature",
  "properties": {
    "iso:country":"NL",
    "sg:address":"Nicolaas Maesstraat 124",
    "sg:city":"Amsterdam",
    "sg:classifiers":[
        {
            "category":"Education",
            "subcategory":"Preschool",
            "type":"Public Place"
        }
    ],
    "sg:phone":"+31 20 617 6967",
    "sg:postcode":"1071 RH",
    "sg:province":"Noord-Holland",
    "sg:tags":[
        "kleuteronderwijs",
        "basis-"
    ],
    "wof:name":"Nicolaas Maesschool",
    "wof:placetype":"venue"
},
  "geometry": {"coordinates":[4.876197,52.353828],"type":"Point"}
}