{
  "type": "Feature",
  "properties": {
    "addr:full":"Watermanstr 64 Apeldoorn Gelderland 7324 AK",
    "addr:housenumber":"64",
    "addr:postcode":"7324 ak",
    "addr:street":"Watermanstr;Gelderland",
    "iso:country":"NL",
    "sg:address":"Watermanstr 64",
    "sg:city":"Apeldoorn",
    "sg:orig_category":"Dierenvoeder - Fabrieken",
    "sg:phone":"+31 55 360 1179",
    "sg:postcode":"7324 AK",
    "sg:province":"Gelderland",
    "wof:name":"Lohmann",
    "wof:placetype":"venue"
},
  "geometry": {"coordinates":[5.98446,52.240921],"type":"Point"}
}