{
  "type": "Feature",
  "properties": {
    "iso:country":"NL",
    "sg:address":"Kruisstraat 7",
    "sg:city":"Assen",
    "sg:orig_category":"Kantoorapparatuur Gh",
    "sg:phone":"+31 592 312 934",
    "sg:postcode":"9401 JJ",
    "sg:province":"Drenthe",
    "wof:name":"Hummelen Bv",
    "wof:placetype":"venue"
},
  "geometry": {"coordinates":[6.5617461205,52.9944152832],"type":"Point"}
}