{
  "type": "Feature",
  "properties": {
    "addr:full":"Stationsstr 38 Zaandam Noord-Holland 1506 DH",
    "addr:housenumber":"38",
    "addr:postcode":"1506 dh",
    "addr:street":"Stationsstr",
    "iso:country":"NL",
    "sg:address":"Stationsstr 38",
    "sg:city":"Zaandam",
    "sg:orig_category":"Natuur- En Milieuorganisaties",
    "sg:phone":"+31 75 635 3580",
    "sg:postcode":"1506 DH",
    "sg:province":"Noord-Holland",
    "sg:website":"http://www.antenna.nl/kmz",
    "wof:name":"Kontakt Milieubeheer Zaanstreek",
    "wof:placetype":"venue"
},
  "geometry": {"coordinates":[4.819902,52.441185],"type":"Point"}
}