{
  "type": "Feature",
  "properties": {
    "iso:country":"NL",
    "sg:address":"Nieuwstraat 43",
    "sg:city":"Medemblik",
    "sg:orig_category":"Voeding, Dranken And Tabak Gh",
    "sg:phone":"+31 227 541 674",
    "sg:postcode":"1671 BB",
    "sg:province":"North Holland",
    "wof:name":"Grozo",
    "wof:placetype":"venue"
},
  "geometry": {"coordinates":[5.106913,52.77235],"type":"Point"}
}