{
  "type": "Feature",
  "properties": {
    "addr:full":"Nieuwstraat 67 Leerdam South Holland 4141 CB",
    "addr:housenumber":"67",
    "addr:postcode":"4141 cb",
    "addr:street":"Nieuwstraat",
    "iso:country":"NL",
    "sg:address":"Nieuwstraat 67",
    "sg:city":"Leerdam",
    "sg:orig_category":"Werving And Selectie Van Tijdelijk Personeel And Uitzendkantoren",
    "sg:phone":"+31 345 631 717",
    "sg:postcode":"4141 CB",
    "sg:province":"South Holland",
    "wof:name":"Adecco",
    "wof:placetype":"venue"
},
  "geometry": {"coordinates":[5.0921230316,51.8914146423],"type":"Point"}
}