{
  "type": "Feature",
  "properties": {
    "addr:full":"Nieuwstr 2/B Oosterhout Nb Noord-Brabant 4901 JH",
    "addr:housenumber":"2 / b",
    "addr:postcode":"4901 jh",
    "addr:street":"Nieuwstr",
    "iso:country":"NL",
    "sg:address":"Nieuwstr 2/B",
    "sg:city":"Oosterhout Nb",
    "sg:orig_category":"Kinderkleding",
    "sg:phone":"+31 162 421 127",
    "sg:postcode":"4901 JH",
    "sg:province":"Noord-Brabant",
    "wof:name":"Deugniet",
    "wof:placetype":"venue"
},
  "geometry": {"coordinates":[4.858891,51.64397],"type":"Point"}
}