{
  "type": "Feature",
  "properties": {
    "addr:full":"G Stresemannstr 29 Diemen Noord-Holland 1111 KL",
    "addr:housenumber":"29",
    "addr:postcode":"1111 kl",
    "iso:country":"NL",
    "sg:address":"G Stresemannstr 29",
    "sg:city":"Diemen",
    "sg:orig_category":"Agenturen En Commissiehandel",
    "sg:phone":"+31 20 600 3775",
    "sg:postcode":"1111 KL",
    "sg:province":"Noord-Holland",
    "wof:name":"Swidde, N",
    "wof:placetype":"venue"
},
  "geometry": {"coordinates":[4.962126,52.343987],"type":"Point"}
}