{
  "type": "Feature",
  "properties": {
    "iso:country":"NL",
    "sg:address":"Kruiswg 1081",
    "sg:city":"Hoofddorp",
    "sg:orig_category":"Levensmiddelen - Fabrieken En Groothandel",
    "sg:phone":"+31 23 555 3485",
    "sg:postcode":"2131 CT",
    "sg:province":"North Holland",
    "wof:name":"Global Bv",
    "wof:placetype":"venue"
},
  "geometry": {"coordinates":[4.688391,52.308254],"type":"Point"}
}