{
  "type": "Feature",
  "properties": {
    "addr:full":"Verliefd Ln 3A Helmond North Brabant 5707 LG",
    "addr:housenumber":"3a",
    "addr:postcode":"5707 lg",
    "addr:street":"Verliefd Ln",
    "iso:country":"NL",
    "sg:address":"Verliefd Ln 3A",
    "sg:city":"Helmond",
    "sg:orig_category":"Golfbanen",
    "sg:phone":"+31 492 475 807",
    "sg:postcode":"5707 LG",
    "sg:province":"North Brabant",
    "wof:name":"Dimpel, D'N",
    "wof:placetype":"venue"
},
  "geometry": {"coordinates":[5.646785,51.495293],"type":"Point"}
}