{
  "type": "Feature",
  "properties": {
    "iso:country":"NL",
    "sg:address":"Graafschedk 46",
    "sg:city":"Escharen",
    "sg:orig_category":"Administratie- En Boekhoudkantoren",
    "sg:phone":"+31 486 420 832",
    "sg:postcode":"5364 PS",
    "sg:province":"Noord-Brabant",
    "wof:name":"Cruysen",
    "wof:placetype":"venue"
},
  "geometry": {"coordinates":[5.747564,51.74226],"type":"Point"}
}