{
  "type": "Feature",
  "properties": {
    "addr:full":"C Franckstr 1A Almelo Overijssel 7604 JE",
    "addr:housenumber":"1a",
    "addr:postcode":"7604 je",
    "iso:country":"NL",
    "sg:address":"C Franckstr 1A",
    "sg:city":"Almelo",
    "sg:orig_category":"Bedrijfsopleidingen",
    "sg:phone":"+31 546 535 555",
    "sg:postcode":"7604 JE",
    "sg:province":"Overijssel",
    "sg:website":"HTTP://www.stodt.nl",
    "wof:name":"Stodt",
    "wof:placetype":"venue"
},
  "geometry": {"coordinates":[6.642692,52.362286],"type":"Point"}
}