{
  "type": "Feature",
  "properties": {
    "iso:country":"NL",
    "sg:address":"Singel 59A",
    "sg:city":"Woerden",
    "sg:orig_category":"Ventilatiesystemen",
    "sg:phone":"+31 348 432 932",
    "sg:postcode":"3442 AM",
    "sg:province":"Utrecht",
    "wof:name":"Mooij Agro Bv",
    "wof:placetype":"venue"
},
  "geometry": {"coordinates":[4.884179,52.082619],"type":"Point"}
}