{
  "type": "Feature",
  "properties": {
    "iso:country":"NL",
    "sg:address":"Commandeurstraat 56",
    "sg:city":"Mechelen",
    "sg:classifiers":[
        {
            "category":"Fast Food",
            "type":"Food & Drink"
        }
    ],
    "sg:phone":"+31 43 455 2578",
    "sg:postcode":"6281 AN",
    "sg:province":"Limburg",
    "sg:tags":[
        "afhaal",
        "restaurant"
    ],
    "wof:name":"Vof Chin. Ind. Spec. Rest. De Chinese Muur",
    "wof:placetype":"venue"
},
  "geometry": {"coordinates":[5.926507,50.793381],"type":"Point"}
}