{
  "type": "Feature",
  "properties": {
    "addr:full":"Pr Bernhardstr 8 Fynaart Noord-Brabant 4793 CT",
    "addr:housenumber":"8",
    "addr:postcode":"4793 ct",
    "addr:street":"Fynaart",
    "iso:country":"NL",
    "sg:address":"Pr Bernhardstr 8",
    "sg:city":"Fynaart",
    "sg:orig_category":"Glazenwasserijen",
    "sg:phone":"+31 168 464 718",
    "sg:postcode":"4793 CT",
    "sg:province":"Noord-Brabant",
    "wof:name":"Kanters, J",
    "wof:placetype":"venue"
},
  "geometry": {"coordinates":[4.494492,51.660118],"type":"Point"}
}