{
  "type": "Feature",
  "properties": {
    "addr:full":"Koninginneln 9 Oegstgeest Zuid-Holland 2341 EW",
    "addr:housenumber":"9",
    "addr:postcode":"2341 ew",
    "addr:street":"Koninginneln",
    "iso:country":"NL",
    "sg:address":"Koninginneln 9",
    "sg:city":"Oegstgeest",
    "sg:classifiers":[
        {
            "category":"Professional",
            "subcategory":"Management & Consulting",
            "type":"Services"
        }
    ],
    "sg:phone":"+31 71 519 0633",
    "sg:postcode":"2341 EW",
    "sg:province":"Zuid-Holland",
    "sg:tags":[
        "relation",
        "adviesbureaus",
        "public"
    ],
    "wof:name":"Wolff",
    "wof:placetype":"venue"
},
  "geometry": {"coordinates":[4.468865,52.178314],"type":"Point"}
}