{
  "type": "Feature",
  "properties": {
    "addr:full":"Snydersstr 7 Lelystad Flevoland 8223 AA",
    "addr:housenumber":"7",
    "addr:postcode":"8223 aa",
    "addr:street":"Snydersstr;Flevoland",
    "iso:country":"NL",
    "sg:address":"Snydersstr 7",
    "sg:city":"Lelystad",
    "sg:orig_category":"Fotozaken",
    "sg:phone":"+31 320 222 106",
    "sg:postcode":"8223 AA",
    "sg:province":"Flevoland",
    "wof:name":"Foto Quelle",
    "wof:placetype":"venue"
},
  "geometry": {"coordinates":[5.483487,52.519413],"type":"Point"}
}