{
  "type": "Feature",
  "properties": {
    "addr:full":"Koninginneln 53 Apeldoorn Gelderland 7315 BM",
    "addr:housenumber":"53",
    "addr:postcode":"7315 bm",
    "addr:street":"Koninginneln;Gelderland",
    "iso:country":"NL",
    "sg:address":"Koninginneln 53",
    "sg:city":"Apeldoorn",
    "sg:orig_category":"Schilders",
    "sg:phone":"+31 55 521 2172",
    "sg:postcode":"7315 BM",
    "sg:province":"Gelderland",
    "wof:name":"Bergmeester Deco Home, Schildersbedrijf",
    "wof:placetype":"venue"
},
  "geometry": {"coordinates":[5.956255,52.224407],"type":"Point"}
}