{
  "type": "Feature",
  "properties": {
    "addr:full":"Vaassenstr 38 S Gravenhage South Holland 2573 WT",
    "addr:housenumber":"38",
    "addr:postcode":"2573 wt",
    "addr:street":"Vaassenstr;S Gravenhage",
    "iso:country":"NL",
    "sg:address":"Vaassenstr 38",
    "sg:city":"S Gravenhage",
    "sg:orig_category":"Onderhoudswerken",
    "sg:phone":"+31 6 15221749",
    "sg:postcode":"2573 WT",
    "sg:province":"South Holland",
    "wof:name":"Pragt, Eddy",
    "wof:placetype":"venue"
},
  "geometry": {"coordinates":[4.2844,52.064911],"type":"Point"}
}