{
  "type": "Feature",
  "properties": {
    "addr:full":"Industriewg 37B Soest Utrecht 3762 EH",
    "addr:housenumber":"37b",
    "addr:postcode":"3762 eh",
    "addr:street":"Industriewg",
    "iso:country":"NL",
    "sg:address":"Industriewg 37B",
    "sg:city":"Soest",
    "sg:orig_category":"Filters - Fabrieken En Groothandel",
    "sg:phone":"+31 35 694 6533",
    "sg:postcode":"3762 EH",
    "sg:province":"Utrecht",
    "sg:website":"http://www.hydrofil.nl",
    "wof:name":"Hydrofil",
    "wof:placetype":"venue"
},
  "geometry": {"coordinates":[5.278878,52.176445],"type":"Point"}
}