{
  "type": "Feature",
  "properties": {
    "addr:full":"Lievevrouwestraat 34 Bergen Op Zoom Noord-Brabant 4611 JL",
    "addr:housenumber":"34",
    "addr:postcode":"4611 jl",
    "addr:street":"Lievevrouwestraat",
    "iso:country":"NL",
    "sg:address":"Lievevrouwestraat 34",
    "sg:city":"Bergen Op Zoom",
    "sg:orig_category":"Kappers",
    "sg:phone":"+31 164 243 290",
    "sg:postcode":"4611 JL",
    "sg:province":"Noord-Brabant",
    "wof:name":"Taylor'S Hairshop",
    "wof:placetype":"venue"
},
  "geometry": {"coordinates":[4.283228,51.495293],"type":"Point"}
}