{
  "type": "Feature",
  "properties": {
    "iso:country":"NL",
    "sg:address":"Weteringschans 24",
    "sg:city":"Amsterdam Centrum",
    "sg:orig_category":"Binnenvaart",
    "sg:phone":"+31 20 626 5574",
    "sg:postcode":"1017 SG",
    "sg:province":"Noord-Holland",
    "wof:name":"Canal Bike Party & Incentive Organisers",
    "wof:placetype":"venue"
},
  "geometry": {"coordinates":[4.886177,52.361206],"type":"Point"}
}