{
  "type": "Feature",
  "properties": {
    "addr:full":"Asfaltstraat 25 Lelystad Flevoland 8211 AC",
    "addr:housenumber":"25",
    "addr:postcode":"8211 ac",
    "addr:street":"Asfaltstraat;Flevoland",
    "iso:country":"NL",
    "sg:address":"Asfaltstraat 25",
    "sg:city":"Lelystad",
    "sg:orig_category":"Wegen And Sportterreinen",
    "sg:phone":"+31 320 226 613",
    "sg:postcode":"8211 AC",
    "sg:province":"Flevoland",
    "wof:name":"L. Timmer Lelystad Bv",
    "wof:placetype":"venue"
},
  "geometry": {"coordinates":[5.524503231,52.5332756042],"type":"Point"}
}