{
  "type": "Feature",
  "properties": {
    "addr:full":"Koudhoornsewg 17 Garderen Gelderland 3886 PJ",
    "addr:housenumber":"17",
    "addr:postcode":"3886 pj",
    "addr:street":"Koudhoornsewg;Gelderland",
    "iso:country":"NL",
    "sg:address":"Koudhoornsewg 17",
    "sg:city":"Garderen",
    "sg:orig_category":"Adviesbureaus Bedrijfsorganisatie",
    "sg:phone":"+31 577 462 273",
    "sg:postcode":"3886 PJ",
    "sg:province":"Gelderland",
    "wof:name":"Crucedis Bv",
    "wof:placetype":"venue"
},
  "geometry": {"coordinates":[5.6988,52.233101],"type":"Point"}
}