{
  "type": "Feature",
  "properties": {
    "addr:full":"Amsteldk 21B Anna Paulowna Noord-Holland 1761 JP",
    "addr:housenumber":"21b",
    "addr:postcode":"1761 jp",
    "addr:street":"Amsteldk",
    "iso:country":"NL",
    "sg:address":"Amsteldk 21B",
    "sg:city":"Anna Paulowna",
    "sg:orig_category":"Bodemsanering",
    "sg:phone":"+31 223 537 333",
    "sg:postcode":"1761 JP",
    "sg:province":"Noord-Holland",
    "wof:name":"Biograp",
    "wof:placetype":"venue"
},
  "geometry": {"coordinates":[4.884774,52.879242],"type":"Point"}
}