{
  "type": "Feature",
  "properties": {
    "iso:country":"NL",
    "sg:address":"Amsteldk 21B",
    "sg:city":"Anna Paulowna",
    "sg:orig_category":"Bodemsanering",
    "sg:phone":"+31 223 537 333",
    "sg:postcode":"1761 JP",
    "sg:province":"Noord-Holland",
    "wof:name":"Biograp",
    "wof:placetype":"venue"
},
  "geometry": {"coordinates":[4.884774,52.879242],"type":"Point"}
}