{
  "type": "Feature",
  "properties": {
    "addr:full":"Nachtegaalstraat 46 Utrecht Utrecht 3581 AK",
    "addr:housenumber":"46",
    "addr:postcode":"3581 ak",
    "addr:street":"Nachtegaalstraat",
    "iso:country":"NL",
    "sg:address":"Nachtegaalstraat 46",
    "sg:city":"Utrecht",
    "sg:classifiers":[
        {
            "category":"Retail",
            "subcategory":"Photofinishing",
            "type":"Services"
        }
    ],
    "sg:phone":"+31 30 231 1097",
    "sg:postcode":"3581 AK",
    "sg:province":"Utrecht",
    "sg:tags":[
        "foto",
        "film"
    ],
    "wof:name":"Foto Abstede",
    "wof:placetype":"venue"
},
  "geometry": {"coordinates":[5.130638,52.092201],"type":"Point"}
}