{
  "type": "Feature",
  "properties": {
    "addr:full":"Stationswg 100 Herkenbosch Limburg 6075 CD",
    "addr:housenumber":"100",
    "addr:postcode":"6075 cd",
    "iso:country":"NL",
    "sg:address":"Stationswg 100",
    "sg:city":"Herkenbosch",
    "sg:orig_category":"Golfbanen",
    "sg:phone":"+31 475 529 529",
    "sg:postcode":"6075 CD",
    "sg:province":"Limburg",
    "wof:name":"Burggolf Herkenbosch Bv",
    "wof:placetype":"venue"
},
  "geometry": {"coordinates":[6.06053,51.170471],"type":"Point"}
}