{
  "type": "Feature",
  "properties": {
    "addr:full":"Mosveld 74 Amsterdam Noord-Holland 1032 GG",
    "addr:housenumber":"74",
    "addr:postcode":"1032 gg",
    "addr:street":"Mosveld",
    "iso:country":"NL",
    "sg:address":"Mosveld 74",
    "sg:city":"Amsterdam",
    "sg:classifiers":[
        {
            "category":"Fast Food",
            "type":"Food & Drink"
        }
    ],
    "sg:phone":"+31 20 637 2522",
    "sg:postcode":"1032 GG",
    "sg:province":"Noord-Holland",
    "sg:tags":[
        "afhaal",
        "restaurant"
    ],
    "wof:name":"Pizzeria San Remo",
    "wof:placetype":"venue"
},
  "geometry": {"coordinates":[4.91402,52.391865],"type":"Point"}
}