{
  "type": "Feature",
  "properties": {
    "addr:full":"Krommestraat 12 Amersfoort Utrecht 3811 CC",
    "addr:housenumber":"12",
    "addr:postcode":"3811 cc",
    "addr:street":"Krommestraat",
    "iso:country":"NL",
    "sg:address":"Krommestraat 12",
    "sg:city":"Amersfoort",
    "sg:orig_category":"Opticiens",
    "sg:phone":"+31 33 461 5989",
    "sg:postcode":"3811 CC",
    "sg:province":"Utrecht",
    "wof:name":"Fashion Optiek",
    "wof:placetype":"venue"
},
  "geometry": {"coordinates":[5.388988018,52.1558074951],"type":"Point"}
}