{
  "type": "Feature",
  "properties": {
    "addr:full":"Zandpad 10 Middelharnis South Holland 3241 GX",
    "addr:housenumber":"10",
    "addr:postcode":"3241 gx",
    "addr:street":"Zandpad",
    "iso:country":"NL",
    "sg:address":"Zandpad 10",
    "sg:city":"Middelharnis",
    "sg:orig_category":"Kappers",
    "sg:phone":"+31 187 486 006",
    "sg:postcode":"3241 GX",
    "sg:province":"South Holland",
    "wof:name":"Papillot",
    "wof:placetype":"venue"
},
  "geometry": {"coordinates":[4.159351,51.760612],"type":"Point"}
}