{
  "type": "Feature",
  "properties": {
    "iso:country":"NL",
    "sg:address":"Scholtenstraat 3",
    "sg:city":"Schiedam",
    "sg:orig_category":"Schilderwerk",
    "sg:phone":"+31 10 437 6502",
    "sg:postcode":"3125 BM",
    "sg:province":"Zuid-Holland",
    "wof:name":"Van Velzen Schilders",
    "wof:placetype":"venue"
},
  "geometry": {"coordinates":[4.404843,51.930702],"type":"Point"}
}