{
  "type": "Feature",
  "properties": {
    "addr:full":"Meedhuizerwg 28B Meedhuizen Groningen 9937 PA",
    "addr:housenumber":"28b",
    "addr:postcode":"9937 pa",
    "addr:street":"Meedhuizerwg",
    "iso:country":"NL",
    "sg:address":"Meedhuizerwg 28B",
    "sg:city":"Meedhuizen",
    "sg:orig_category":"Sportverenigingen En Ontspannings- Verenigingen",
    "sg:phone":"+31 596 533 542",
    "sg:postcode":"9937 PA",
    "sg:province":"Groningen",
    "wof:name":"Daft Crowd",
    "wof:placetype":"venue"
},
  "geometry": {"coordinates":[6.910636,53.291615],"type":"Point"}
}