{
  "type": "Feature",
  "properties": {
    "addr:full":"Wilhelminaln 9 Hengelo Gld Gelderland 7255 DC",
    "addr:housenumber":"9",
    "addr:postcode":"7255",
    "addr:street":"Wilhelminaln",
    "iso:country":"NL",
    "sg:address":"Wilhelminaln 9",
    "sg:city":"Hengelo Gld",
    "sg:orig_category":"Accountants - Administratie- Consulenten En -Kantoren",
    "sg:phone":"+31 575 462 216",
    "sg:postcode":"7255 DC",
    "sg:province":"Gelderland",
    "wof:name":"Greef, B J De",
    "wof:placetype":"venue"
},
  "geometry": {"coordinates":[6.310447,52.05249],"type":"Point"}
}