{
  "type": "Feature",
  "properties": {
    "iso:country":"NL",
    "sg:address":"Leidsevaart 36",
    "sg:city":"Vogelenzang",
    "sg:orig_category":"Open Haarden",
    "sg:phone":"+31 23 584 7475",
    "sg:postcode":"2114 AD",
    "sg:province":"Noord-Holland",
    "sg:website":"http://www.schouwspel.nl",
    "wof:name":"Schouwspel",
    "wof:placetype":"venue"
},
  "geometry": {"coordinates":[4.588094,52.324448],"type":"Point"}
}