{
  "type": "Feature",
  "properties": {
    "addr:full":"Eindsepad 20 Den Hout Nb Noord-Brabant 4911 AR",
    "addr:housenumber":"20",
    "addr:postcode":"4911",
    "addr:street":"Eindsepad",
    "iso:country":"NL",
    "sg:address":"Eindsepad 20",
    "sg:city":"Den Hout Nb",
    "sg:orig_category":"Goederenvervoer Over De Weg",
    "sg:phone":"+31 162 422 755",
    "sg:postcode":"4911 AR",
    "sg:province":"Noord-Brabant",
    "wof:name":"Firma Gebr. Caron Bv",
    "wof:placetype":"venue"
},
  "geometry": {"coordinates":[4.802427,51.657574],"type":"Point"}
}