{
  "type": "Feature",
  "properties": {
    "iso:country":"NL",
    "sg:address":"Dokter Desainlaan 13",
    "sg:city":"Oisterwijk",
    "sg:orig_category":"Paramedische Behandelingen",
    "sg:phone":"+31 13 528 5599",
    "sg:postcode":"5062 EK",
    "sg:province":"Noord-Brabant",
    "wof:name":"E.J.E.B. Van Bergeijk- Diepens",
    "wof:placetype":"venue"
},
  "geometry": {"coordinates":[5.198308,51.576851],"type":"Point"}
}