{
  "type": "Feature",
  "properties": {
    "addr:full":"J Bloemhof 130 Hoorn Nh Noord-Holland 1628 VR",
    "addr:housenumber":"130",
    "addr:postcode":"1628 vr",
    "addr:street":"Bloemhof",
    "iso:country":"NL",
    "sg:address":"J Bloemhof 130",
    "sg:city":"Hoorn Nh",
    "sg:orig_category":"Geluidsopnamestudio'S",
    "sg:phone":"+31 6 53922161",
    "sg:postcode":"1628 VR",
    "sg:province":"Noord-Holland",
    "wof:name":"4 Always",
    "wof:placetype":"venue"
},
  "geometry": {"coordinates":[5.05207,52.642399],"type":"Point"}
}