{
  "type": "Feature",
  "properties": {
    "addr:full":"De Dintel 26 Best Texas 5684 PS",
    "addr:housenumber":"26",
    "addr:postcode":"5684 ps",
    "addr:street":"De Dintel",
    "iso:country":"NL",
    "sg:address":"De Dintel 26",
    "sg:city":"Best",
    "sg:orig_category":"Elektronica - Ontwikkeling En Groothandel",
    "sg:phone":"+31 499 335 700",
    "sg:postcode":"5684 PS",
    "sg:province":"Texas",
    "sg:website":"http://www.kestronics.nl",
    "wof:name":"Kestronics Bv",
    "wof:placetype":"venue"
},
  "geometry": {"coordinates":[-101.618134,31.224251],"type":"Point"}
}