{
  "type": "Feature",
  "properties": {
    "iso:country":"NL",
    "sg:address":"J G Staringhln 18",
    "sg:city":"Gouderak",
    "sg:classifiers":[
        {
            "category":"Food & Beverages",
            "subcategory":"Fruits & Vegetables",
            "type":"Retail Goods"
        }
    ],
    "sg:phone":"+31 182 372 440",
    "sg:postcode":"2831 XC",
    "sg:province":"Zuid-Holland",
    "sg:tags":[
        "en",
        "groenten"
    ],
    "wof:name":"Kok En Zn, Fa J",
    "wof:placetype":"venue"
},
  "geometry": {"coordinates":[4.675,51.9856],"type":"Point"}
}