{
  "type": "Feature",
  "properties": {
    "addr:full":"J Mulderstr 29 Vaassen Gelderland 8171 CC",
    "addr:housenumber":"29",
    "addr:postcode":"8171 cc",
    "addr:street":"Gelderland",
    "iso:country":"NL",
    "sg:address":"J Mulderstr 29",
    "sg:city":"Vaassen",
    "sg:orig_category":"Artsen - Huisartsen",
    "sg:phone":"+31 578 571 230",
    "sg:postcode":"8171 CC",
    "sg:province":"Gelderland",
    "wof:name":"Groot - Weis, Praktijk De",
    "wof:placetype":"venue"
},
  "geometry": {"coordinates":[5.97061,52.288658],"type":"Point"}
}