{
  "type": "Feature",
  "properties": {
    "addr:full":"Zilkerbinnenwg 58 De Zilk South Holland 2191 AD",
    "addr:housenumber":"58",
    "addr:postcode":"2191 ad",
    "addr:street":"Zilkerbinnenwg",
    "iso:country":"NL",
    "sg:address":"Zilkerbinnenwg 58",
    "sg:city":"De Zilk",
    "sg:orig_category":"Bloembollen - Groothandel",
    "sg:phone":"+31 252 515 821",
    "sg:postcode":"2191 AD",
    "sg:province":"South Holland",
    "wof:name":"Ruigrok & Zonen, C J",
    "wof:placetype":"venue"
},
  "geometry": {"coordinates":[4.540561,52.29591],"type":"Point"}
}