{
  "type": "Feature",
  "properties": {
    "addr:full":"Kerkstr 10 Oldenzaal Overijssel 7571 EE",
    "addr:housenumber":"10",
    "addr:postcode":"7571 ee",
    "addr:street":"Kerkstr",
    "iso:country":"NL",
    "sg:address":"Kerkstr 10",
    "sg:city":"Oldenzaal",
    "sg:orig_category":"Kappers",
    "sg:phone":"+31 541 536 178",
    "sg:postcode":"7571 EE",
    "sg:province":"Overijssel",
    "wof:name":"Boyd'S Up To Date",
    "wof:placetype":"venue"
},
  "geometry": {"coordinates":[6.928976059,52.3129959106],"type":"Point"}
}