{
  "type": "Feature",
  "properties": {
    "addr:full":"Overtoom 78 Westzaan Noord-Holland 1551 PB",
    "addr:housenumber":"78",
    "addr:postcode":"1551 pb",
    "addr:street":"Overtoom",
    "iso:country":"NL",
    "sg:address":"Overtoom 78",
    "sg:city":"Westzaan",
    "sg:orig_category":"Goudsmeden En Zilversmeden",
    "sg:phone":"+31 75 616 1865",
    "sg:postcode":"1551 PB",
    "sg:province":"Noord-Holland",
    "wof:name":"Bert Slaman Goud En Zilversmederij",
    "wof:placetype":"venue"
},
  "geometry": {"coordinates":[4.782279,52.430691],"type":"Point"}
}