{
  "type": "Feature",
  "properties": {
    "addr:full":"Hoge Weerd 201 Maastricht Limburg 6229 AM",
    "addr:housenumber":"201",
    "addr:postcode":"6229",
    "addr:street":"Hoge Weerd",
    "iso:country":"NL",
    "sg:address":"Hoge Weerd 201",
    "sg:city":"Maastricht",
    "sg:orig_category":"Autokeuringen",
    "sg:phone":"+31 43 361 2616",
    "sg:postcode":"6229 AM",
    "sg:province":"Limburg",
    "wof:name":"Shell",
    "wof:placetype":"venue"
},
  "geometry": {"coordinates":[5.702524,50.82877],"type":"Point"}
}