{
  "type": "Feature",
  "properties": {
    "iso:country":"NL",
    "sg:address":"Tuindorpstraat 25",
    "sg:city":"Hengelo Ov",
    "sg:orig_category":"Kantoorapparatuur Gh",
    "sg:phone":"+31 74 242 4025",
    "sg:postcode":"7551 AW",
    "sg:province":"Overijssel",
    "wof:name":"Tsc Technische Service Copiers",
    "wof:placetype":"venue"
},
  "geometry": {"coordinates":[6.7851958275,52.2651519775],"type":"Point"}
}