{
  "type": "Feature",
  "properties": {
    "addr:full":"Dorp 131 Benschop Utrecht 3405 BC",
    "addr:housenumber":"131",
    "addr:postcode":"3405 bc",
    "addr:street":"Dorp",
    "iso:country":"NL",
    "sg:address":"Dorp 131",
    "sg:city":"Benschop",
    "sg:orig_category":"Fietshandelaren",
    "sg:phone":"+31 348 451 827",
    "sg:postcode":"3405 BC",
    "sg:province":"Utrecht",
    "wof:name":"H A Cooiman",
    "wof:placetype":"venue"
},
  "geometry": {"coordinates":[4.983536,52.009289],"type":"Point"}
}