{
  "type": "Feature",
  "properties": {
    "addr:full":"Schandelerstraat 80 Heerlen Limburg 6412 XR",
    "addr:housenumber":"80",
    "addr:postcode":"6412 xr",
    "addr:street":"Schandelerstraat",
    "iso:country":"NL",
    "sg:address":"Schandelerstraat 80",
    "sg:city":"Heerlen",
    "sg:orig_category":"Drukkerijen And Copyshops",
    "sg:phone":"+31 45 570 8105",
    "sg:postcode":"6412 XR",
    "sg:province":"Limburg",
    "wof:name":"System Integrated Engineering & Service Bv",
    "wof:placetype":"venue"
},
  "geometry": {"coordinates":[5.981785,50.895439],"type":"Point"}
}