{
  "type": "Feature",
  "properties": {
    "addr:full":"Schoolwg 23 Groesbeek Gelderland 6562 GD",
    "addr:housenumber":"23",
    "addr:postcode":"6562 gd",
    "addr:street":"Schoolwg;Gelderland",
    "iso:country":"NL",
    "sg:address":"Schoolwg 23",
    "sg:city":"Groesbeek",
    "sg:orig_category":"Scholen Voor Basisonderwijs",
    "sg:phone":"+31 24 397 8777",
    "sg:postcode":"6562 GD",
    "sg:province":"Gelderland",
    "wof:name":"Basisschool Breedeweg Rk",
    "wof:placetype":"venue"
},
  "geometry": {"coordinates":[5.939646,51.756809],"type":"Point"}
}