{
  "type": "Feature",
  "properties": {
    "iso:country":"NL",
    "sg:address":"S Gravelandsewg 10",
    "sg:city":"Hilversum",
    "sg:orig_category":"Grafisch Ontwerpers",
    "sg:phone":"+31 35 623 4479",
    "sg:postcode":"1211 BR",
    "sg:province":"Noord-Holland",
    "wof:name":"Timmo Polak",
    "wof:placetype":"venue"
},
  "geometry": {"coordinates":[5.1721,52.225254],"type":"Point"}
}