{
  "type": "Feature",
  "properties": {
    "addr:full":"Stedenbaan 10 Rijen Noord-Brabant 5121 DP",
    "addr:housenumber":"10",
    "addr:postcode":"5121 dp",
    "addr:street":"Stedenbaan",
    "iso:country":"NL",
    "sg:address":"Stedenbaan 10",
    "sg:city":"Rijen",
    "sg:orig_category":"Autoreparatie And Auto-Onderhoud",
    "sg:phone":"+31 161 230 081",
    "sg:postcode":"5121 DP",
    "sg:province":"Noord-Brabant",
    "wof:name":"Bedrijfswagen En Industrieel Spuiterij Cabanier Bv",
    "wof:placetype":"venue"
},
  "geometry": {"coordinates":[4.93341,51.577389],"type":"Point"}
}