{
  "type": "Feature",
  "properties": {
    "addr:full":"Lintveldebrink 22 Enschede NL.08 7544 KA",
    "addr:housenumber":"22",
    "addr:postcode":"7544 ka",
    "addr:street":"Lintveldebrink",
    "iso:country":"NL",
    "sg:address":"Lintveldebrink 22",
    "sg:city":"Enschede",
    "sg:orig_category":"Zuivelproducten And Spijsoli?n Gh",
    "sg:phone":"+31 53 476 3007",
    "sg:postcode":"7544 KA",
    "sg:province":"NL.08",
    "wof:name":"W.J. Schellings",
    "wof:placetype":"venue"
},
  "geometry": {"coordinates":[6.882047,52.189697],"type":"Point"}
}