{
  "type": "Feature",
  "properties": {
    "addr:full":"Weytackers 64 Emmen Provincie Drenthe 7824 PD",
    "addr:housenumber":"64",
    "addr:postcode":"7824 pd",
    "addr:street":"Weytackers;Provincie Drenthe",
    "iso:country":"NL",
    "sg:address":"Weytackers 64",
    "sg:city":"Emmen",
    "sg:orig_category":"Loonbedrijven",
    "sg:phone":"+31 591 301 096",
    "sg:postcode":"7824 PD",
    "sg:province":"Provincie Drenthe",
    "wof:name":"Prima-Job",
    "wof:placetype":"venue"
},
  "geometry": {"coordinates":[6.942188,52.781738],"type":"Point"}
}