{
  "type": "Feature",
  "properties": {
    "addr:full":"Steenbakkersstr 33 Krimpen Ad Yssel Zuid-Holland 2922 XK",
    "addr:housenumber":"33",
    "addr:postcode":"2922 xk",
    "addr:street":"Steenbakkersstr",
    "iso:country":"NL",
    "sg:address":"Steenbakkersstr 33",
    "sg:city":"Krimpen Ad Yssel",
    "sg:orig_category":"Adviesbureaus Economie",
    "sg:phone":"+31 180 551 240",
    "sg:postcode":"2922 XK",
    "sg:province":"Zuid-Holland",
    "wof:name":"Jocabo",
    "wof:placetype":"venue"
},
  "geometry": {"coordinates":[4.583851,51.915955],"type":"Point"}
}