{
  "type": "Feature",
  "properties": {
    "addr:full":"Kaapsepln 31 S Gravenhage South Holland 2572 ND",
    "addr:housenumber":"31",
    "addr:postcode":"2572 nd",
    "addr:street":"Kaapsepln;S Gravenhage",
    "iso:country":"NL",
    "sg:address":"Kaapsepln 31",
    "sg:city":"S Gravenhage",
    "sg:orig_category":"Verzekeringen - Verzekeringskantoren",
    "sg:phone":"+31 70 380 4226",
    "sg:postcode":"2572 ND",
    "sg:province":"South Holland",
    "wof:name":"Yapici",
    "wof:placetype":"venue"
},
  "geometry": {"coordinates":[4.29421,52.06422],"type":"Point"}
}