{
  "type": "Feature",
  "properties": {
    "iso:country":"NL",
    "sg:address":"Keizerfazant 15",
    "sg:city":"Heerhugowaard",
    "sg:orig_category":"Juridische Adviseurs",
    "sg:phone":"+31 72 572 8777",
    "sg:postcode":"1704 WL",
    "sg:province":"Noord-Holland",
    "wof:name":"Eecen-Bokhorst, W M",
    "wof:placetype":"venue"
},
  "geometry": {"coordinates":[4.809193,52.653259],"type":"Point"}
}