{
  "type": "Feature",
  "properties": {
    "addr:full":"Tilanusstr 30 Naaldwyk Zuid-Holland 2672 BL",
    "addr:housenumber":"30",
    "addr:postcode":"2672 bl",
    "addr:street":"Tilanusstr",
    "iso:country":"NL",
    "sg:address":"Tilanusstr 30",
    "sg:city":"Naaldwyk",
    "sg:orig_category":"Golfbanen",
    "sg:phone":"+31 174 440 037",
    "sg:postcode":"2672 BL",
    "sg:province":"Zuid-Holland",
    "sg:website":"http://www.nedergolf.nl",
    "wof:name":"Nedergolf",
    "wof:placetype":"venue"
},
  "geometry": {"coordinates":[4.21544,51.998032],"type":"Point"}
}