{
  "type": "Feature",
  "properties": {
    "addr:full":"Schoolstraat 6A Bathmen Overijssel 7437 AE",
    "addr:housenumber":"6a",
    "addr:postcode":"7437 ae",
    "addr:street":"Schoolstraat",
    "iso:country":"NL",
    "sg:address":"Schoolstraat 6A",
    "sg:city":"Bathmen",
    "sg:orig_category":"Overheidsdiensten",
    "sg:phone":"+31 570 542 420",
    "sg:postcode":"7437 AE",
    "sg:province":"Overijssel",
    "wof:name":"Braakhekke / Bv Tot Expl Van Hcr Boode",
    "wof:placetype":"venue"
},
  "geometry": {"coordinates":[6.2863669395,52.2496757507],"type":"Point"}
}