{
  "type": "Feature",
  "properties": {
    "addr:full":"Verdronkenoord 29 Alkmaar Noord-Holland 1811 BB",
    "addr:housenumber":"29",
    "addr:postcode":"1811 bb",
    "addr:street":"Verdronkenoord",
    "iso:country":"NL",
    "sg:address":"Verdronkenoord 29",
    "sg:city":"Alkmaar",
    "sg:orig_category":"Handelsbemiddeling Textiel And Lederwaren",
    "sg:phone":"+31 72 520 0750",
    "sg:postcode":"1811 BB",
    "sg:province":"Noord-Holland",
    "wof:name":"Jordan Textiles Bv",
    "wof:placetype":"venue"
},
  "geometry": {"coordinates":[4.753628,52.628422],"type":"Point"}
}