{
  "type": "Feature",
  "properties": {
    "iso:country":"NL",
    "sg:address":"Romerostr 117",
    "sg:city":"Utrecht",
    "sg:orig_category":"Adviesbureaus Bouwkunde",
    "sg:phone":"+31 30 276 2000",
    "sg:postcode":"3573 AE",
    "sg:province":"Utrecht",
    "wof:name":"Bouwmeester",
    "wof:placetype":"venue"
},
  "geometry": {"coordinates":[5.15159,52.108509],"type":"Point"}
}