{
  "type": "Feature",
  "properties": {
    "addr:full":"Industrieweg 12 Groesbeek Gelderland 6562 AR",
    "addr:housenumber":"12",
    "addr:postcode":"6562",
    "addr:street":"Industrieweg;Gelderland",
    "iso:country":"NL",
    "sg:address":"Industrieweg 12",
    "sg:city":"Groesbeek",
    "sg:orig_category":"Autokeuringen",
    "sg:phone":"+31 24 397 3213",
    "sg:postcode":"6562 AR",
    "sg:province":"Gelderland",
    "wof:name":"Garage De Horst",
    "wof:placetype":"venue"
},
  "geometry": {"coordinates":[5.942704,51.776669],"type":"Point"}
}