{
  "type": "Feature",
  "properties": {
    "addr:full":"Mgr Poelsstr 1 Berkel Enschot North Brabant 5056 ET",
    "addr:housenumber":"1",
    "addr:postcode":"5056 et",
    "addr:street":"Poelsstr;Enschot",
    "iso:country":"NL",
    "sg:address":"Mgr Poelsstr 1",
    "sg:city":"Berkel Enschot",
    "sg:orig_category":"Meubelstoffen",
    "sg:phone":"+31 13 533 2897",
    "sg:postcode":"5056 ET",
    "sg:province":"North Brabant",
    "wof:name":"Marcant Staalboek",
    "wof:placetype":"venue"
},
  "geometry": {"coordinates":[5.134846,51.582569],"type":"Point"}
}