{
  "type": "Feature",
  "properties": {
    "addr:full":"De Hucht 2 Heiloo Noord-Holland 1851 ZC",
    "addr:housenumber":"2",
    "addr:postcode":"1851 zc",
    "addr:street":"De Hucht",
    "iso:country":"NL",
    "sg:address":"De Hucht 2",
    "sg:city":"Heiloo",
    "sg:classifiers":[
        {
            "category":"Education",
            "subcategory":"Preschool",
            "type":"Public Place"
        }
    ],
    "sg:phone":"+31 72 533 9935",
    "sg:postcode":"1851 ZC",
    "sg:province":"Noord-Holland",
    "sg:tags":[
        "kleuteronderwijs",
        "basis-"
    ],
    "wof:name":"Openbare Basisschool Meander",
    "wof:placetype":"venue"
},
  "geometry": {"coordinates":[4.711987,52.58939],"type":"Point"}
}