{
  "type": "Feature",
  "properties": {
    "addr:full":"Hoofdstr 37C Krimpen Aan De Lek Zuid-Holland 2931 CE",
    "addr:housenumber":"37c",
    "addr:postcode":"2931 ce",
    "addr:street":"Hoofdstr",
    "iso:country":"NL",
    "sg:address":"Hoofdstr 37C",
    "sg:city":"Krimpen Aan De Lek",
    "sg:orig_category":"Kappers",
    "sg:phone":"+31 180 518 179",
    "sg:postcode":"2931 CE",
    "sg:province":"Zuid-Holland",
    "wof:name":"Haar-Idee",
    "wof:placetype":"venue"
},
  "geometry": {"coordinates":[4.6285071373,51.8933143616],"type":"Point"}
}