{
  "type": "Feature",
  "properties": {
    "addr:full":"Kievitstraat 21 Sint Willebrord Noord-Brabant 4711 KH",
    "addr:housenumber":"21",
    "addr:postcode":"4711 kh",
    "addr:street":"Kievitstraat",
    "iso:country":"NL",
    "sg:address":"Kievitstraat 21",
    "sg:city":"Sint Willebrord",
    "sg:classifiers":[
        {
            "category":"Fast Food",
            "type":"Food & Drink"
        }
    ],
    "sg:phone":"+31 165 384 413",
    "sg:postcode":"4711 KH",
    "sg:province":"Noord-Brabant",
    "sg:tags":[
        "afhaal",
        "restaurant"
    ],
    "wof:name":"Eethuis En Snackbar Bellevue",
    "wof:placetype":"venue"
},
  "geometry": {"coordinates":[4.591566,51.547859],"type":"Point"}
}