{
  "type": "Feature",
  "properties": {
    "addr:full":"Spuiboulevard 91 Dordrecht South Holland 3311 GN",
    "addr:housenumber":"91",
    "addr:postcode":"3311 gn",
    "addr:street":"Spuiboulevard",
    "iso:country":"NL",
    "sg:address":"Spuiboulevard 91",
    "sg:city":"Dordrecht",
    "sg:orig_category":"Makelaars In Onroerend Goed",
    "sg:phone":"+31 78 639 0220",
    "sg:postcode":"3311 GN",
    "sg:province":"South Holland",
    "wof:name":"Koophuis Dordrecht",
    "wof:placetype":"venue"
},
  "geometry": {"coordinates":[4.666685,51.811584],"type":"Point"}
}