{
  "type": "Feature",
  "properties": {
    "addr:full":"Reguliersdwstr 53 Amsterdam North Holland 1017 BK",
    "addr:housenumber":"53",
    "addr:postcode":"1017 bk",
    "addr:street":"Reguliersdwstr",
    "iso:country":"NL",
    "sg:address":"Reguliersdwstr 53",
    "sg:city":"Amsterdam",
    "sg:orig_category":"Koffie- En Theehuizen",
    "sg:phone":"+31 20 420 2406",
    "sg:postcode":"1017 BK",
    "sg:province":"North Holland",
    "wof:name":"Gary'S Muffins",
    "wof:placetype":"venue"
},
  "geometry": {"coordinates":[4.89136,52.36639],"type":"Point"}
}