{
  "type": "Feature",
  "properties": {
    "iso:country":"NL",
    "sg:address":"Kerkstr 68B",
    "sg:city":"Amsterdam",
    "sg:orig_category":"Kantoor- En Secretariaatsservice",
    "sg:phone":"+31 20 638 1255",
    "sg:postcode":"1017 GN",
    "sg:province":"North Holland",
    "wof:name":"Nota Bene Bv",
    "wof:placetype":"venue"
},
  "geometry": {"coordinates":[4.886138916,52.3647727966],"type":"Point"}
}