{
  "type": "Feature",
  "properties": {
    "iso:country":"NL",
    "sg:address":"Eursingerkerkwg 4",
    "sg:city":"Havelte",
    "sg:orig_category":"Scholen Voor Basisonderwijs",
    "sg:phone":"+31 521 341 772",
    "sg:postcode":"7971 BS",
    "sg:province":"Provincie Drenthe",
    "wof:name":"Bosrank, De",
    "wof:placetype":"venue"
},
  "geometry": {"coordinates":[6.23963,52.772453],"type":"Point"}
}