{
  "type": "Feature",
  "properties": {
    "addr:full":"Aelbert Cuyplaan 23 Hendrik Ido Ambacht South Holland 3343 DA",
    "addr:housenumber":"23",
    "addr:postcode":"3343 da",
    "addr:street":"Aelbert Cuyplaan",
    "iso:country":"NL",
    "sg:address":"Aelbert Cuyplaan 23",
    "sg:city":"Hendrik Ido Ambacht",
    "sg:orig_category":"Boekhouders",
    "sg:phone":"+31 78 681 8170",
    "sg:postcode":"3343 DA",
    "sg:province":"South Holland",
    "wof:name":"Kooreman Administratie- & Belastingadviezen",
    "wof:placetype":"venue"
},
  "geometry": {"coordinates":[4.641905,51.840305],"type":"Point"}
}