{
  "type": "Feature",
  "properties": {
    "addr:full":"Caledoniastr 1-01 Tilburg North Brabant 5047 TZ",
    "addr:housenumber":"1-01",
    "addr:postcode":"5047 tz",
    "iso:country":"NL",
    "sg:address":"Caledoniastr 1-01",
    "sg:city":"Tilburg",
    "sg:orig_category":"Autopoetsbedrijven",
    "sg:phone":"+31 13 535 5023",
    "sg:postcode":"5047 TZ",
    "sg:province":"North Brabant",
    "wof:name":"Perfect, Autopoetsbedrijf",
    "wof:placetype":"venue"
},
  "geometry": {"coordinates":[5.03402,51.583729],"type":"Point"}
}