{
  "type": "Feature",
  "properties": {
    "addr:full":"Bogardeind 39 Geldrop Noord-Brabant 5664 EA",
    "addr:housenumber":"39",
    "addr:postcode":"5664 ea",
    "addr:street":"Bogardeind",
    "iso:country":"NL",
    "sg:address":"Bogardeind 39",
    "sg:city":"Geldrop",
    "sg:orig_category":"Kappers",
    "sg:phone":"+31 40 280 2080",
    "sg:postcode":"5664 EA",
    "sg:province":"Noord-Brabant",
    "wof:name":"Barber Shop, The",
    "wof:placetype":"venue"
},
  "geometry": {"coordinates":[5.559114933,51.4193344116],"type":"Point"}
}