{
  "type": "Feature",
  "properties": {
    "addr:full":"De Joncheerelaan 11 Hellendoorn NL.08 7441 HA",
    "addr:housenumber":"11;nl.08",
    "addr:postcode":"7441 ha",
    "addr:street":"De Joncheerelaan",
    "iso:country":"NL",
    "sg:address":"De Joncheerelaan 11",
    "sg:city":"Hellendoorn",
    "sg:classifiers":[
        {
            "category":"Shopping",
            "subcategory":"Clothing, Apparel, & Fashions",
            "type":"Retail Goods"
        }
    ],
    "sg:phone":"+31 548 613 030",
    "sg:postcode":"7441 HA",
    "sg:province":"NL.08",
    "sg:tags":[
        "ondergoed",
        "lingerie"
    ],
    "wof:name":"Steggink Naaimachines",
    "wof:placetype":"venue"
},
  "geometry": {"coordinates":[6.453469,52.367352],"type":"Point"}
}