{
  "type": "Feature",
  "properties": {
    "iso:country":"NL",
    "sg:address":"Middenwg 4",
    "sg:city":"Zegveld",
    "sg:orig_category":"Bloemen En Planten",
    "sg:phone":"+31 348 691 626",
    "sg:postcode":"3474 KC",
    "sg:province":"Utrecht",
    "wof:name":"Yvonne",
    "wof:placetype":"venue"
},
  "geometry": {"coordinates":[4.83658,52.115448],"type":"Point"}
}