{
  "type": "Feature",
  "properties": {
    "addr:full":"Marshallweg 5 Veghel Noord-Brabant 5466 AH",
    "addr:housenumber":"5",
    "addr:postcode":"5466 ah",
    "addr:street":"Marshallweg",
    "iso:country":"NL",
    "sg:address":"Marshallweg 5",
    "sg:city":"Veghel",
    "sg:orig_category":"Wegen And Sportterreinen",
    "sg:phone":"+31 413 317 600",
    "sg:postcode":"5466 AH",
    "sg:province":"Noord-Brabant",
    "wof:name":"Combinatie Maasroute Vof",
    "wof:placetype":"venue"
},
  "geometry": {"coordinates":[5.5118060112,51.6068115234],"type":"Point"}
}