{
  "type": "Feature",
  "properties": {
    "addr:full":"Eusebiuspln 30 Arnhem Gelderland 6811 HE",
    "addr:housenumber":"30",
    "addr:postcode":"6811 he",
    "addr:street":"Eusebiuspln",
    "iso:country":"NL",
    "sg:address":"Eusebiuspln 30",
    "sg:city":"Arnhem",
    "sg:orig_category":"Vakorganisaties",
    "sg:phone":"+31 26 443 3438",
    "sg:postcode":"6811 HE",
    "sg:province":"Gelderland",
    "sg:website":"http://www.vhpakzonobel.nl",
    "wof:name":"Vhp Akzo Nobel",
    "wof:placetype":"venue"
},
  "geometry": {"coordinates":[5.908839,51.97678],"type":"Point"}
}