{
  "type": "Feature",
  "properties": {
    "addr:full":"Parkweg 5 Maarssen Utrecht 3603 AA",
    "addr:housenumber":"5",
    "addr:postcode":"3603 aa",
    "addr:street":"Parkweg",
    "iso:country":"NL",
    "sg:address":"Parkweg 5",
    "sg:city":"Maarssen",
    "sg:orig_category":"Beursorganisaties And Standbouw",
    "sg:phone":"+31 346 565 751",
    "sg:postcode":"3603 AA",
    "sg:province":"Utrecht",
    "wof:name":"Jan Slager Standbouw",
    "wof:placetype":"venue"
},
  "geometry": {"coordinates":[5.041154,52.140148],"type":"Point"}
}