{
  "type": "Feature",
  "properties": {
    "addr:full":"Markt 27 S Hertogenbosch Noord-Brabant 5211 JV",
    "addr:housenumber":"27",
    "addr:postcode":"5211 jv",
    "addr:street":"Markt;S",
    "iso:country":"NL",
    "sg:address":"Markt 27",
    "sg:city":"S Hertogenbosch",
    "sg:orig_category":"Herenkleding",
    "sg:phone":"+31 73 614 1610",
    "sg:postcode":"5211 JV",
    "sg:province":"Noord-Brabant",
    "wof:name":"Setpoint",
    "wof:placetype":"venue"
},
  "geometry": {"coordinates":[5.304473,51.689026],"type":"Point"}
}