{
  "type": "Feature",
  "properties": {
    "iso:country":"NL",
    "sg:address":"Pr Irenestr 2",
    "sg:city":"Ridderkerk",
    "sg:orig_category":"Artsen - Huisartsen",
    "sg:phone":"+31 180 412 298",
    "sg:postcode":"2983 HX",
    "sg:province":"Zuid-Holland",
    "wof:name":"Caljouw En J P Caljouw-Vos, R D",
    "wof:placetype":"venue"
},
  "geometry": {"coordinates":[4.606982,51.881741],"type":"Point"}
}