{
  "type": "Feature",
  "properties": {
    "addr:full":"Zuidend 33 Sneek Friesland 8601 EL",
    "addr:housenumber":"33;8601",
    "addr:postcode":"el",
    "addr:street":"Zuidend",
    "iso:country":"NL",
    "sg:address":"Zuidend 33",
    "sg:city":"Sneek",
    "sg:orig_category":"Meubelzaken, Woning- And Keukeninrichting",
    "sg:phone":"+31 515 430 695",
    "sg:postcode":"8601 EL",
    "sg:province":"Friesland",
    "wof:name":"De Woonmarkt",
    "wof:placetype":"venue"
},
  "geometry": {"coordinates":[5.658953,53.029728],"type":"Point"}
}