{
  "type": "Feature",
  "properties": {
    "addr:full":"Traay 76 Driebergen-Rijsenburg Utrecht 3971 GR",
    "addr:housenumber":"76",
    "addr:postcode":"3971",
    "addr:street":"Traay",
    "iso:country":"NL",
    "sg:address":"Traay 76",
    "sg:city":"Driebergen-Rijsenburg",
    "sg:orig_category":"Fruit And Groenten Gh",
    "sg:phone":"+31 343 533 555",
    "sg:postcode":"3971 GR",
    "sg:province":"Utrecht",
    "wof:name":"Zeeuwse De Aardappelhal",
    "wof:placetype":"venue"
},
  "geometry": {"coordinates":[5.287676,52.05378],"type":"Point"}
}