{
  "type": "Feature",
  "properties": {
    "addr:full":"Belgradostr 2 Ysselstein Ut Utrecht 3404 VH",
    "addr:housenumber":"2",
    "addr:postcode":"3404 vh",
    "addr:street":"Belgradostr",
    "iso:country":"NL",
    "sg:address":"Belgradostr 2",
    "sg:city":"Ysselstein Ut",
    "sg:orig_category":"Montagebedrijven",
    "sg:phone":"+31 30 687 8641",
    "sg:postcode":"3404 VH",
    "sg:province":"Utrecht",
    "wof:name":"Middelkoop & Hidding",
    "wof:placetype":"venue"
},
  "geometry": {"coordinates":[5.040315,52.012222],"type":"Point"}
}