{
  "type": "Feature",
  "properties": {
    "iso:country":"NL",
    "sg:address":"Oudendijk 188",
    "sg:city":"Dordrecht",
    "sg:orig_category":"Landbouwmachines Gh",
    "sg:phone":"+31 78 616 0548",
    "sg:postcode":"3319 LE",
    "sg:province":"Zuid-Holland",
    "wof:name":"M Langendoen Bv",
    "wof:placetype":"venue"
},
  "geometry": {"coordinates":[4.719129,51.793098],"type":"Point"}
}