{
  "type": "Feature",
  "properties": {
    "addr:full":"Einthovenln 4 Doetinchem Gelderland 7002 HG",
    "addr:housenumber":"4",
    "addr:postcode":"7002 hg",
    "addr:street":"Einthovenln;Gelderland",
    "iso:country":"NL",
    "sg:address":"Einthovenln 4",
    "sg:city":"Doetinchem",
    "sg:orig_category":"Fotoreportages",
    "sg:phone":"+31 314 344 848",
    "sg:postcode":"7002 HG",
    "sg:province":"Gelderland",
    "sg:website":"http://www.amitbar.com",
    "wof:name":"Amit Bar",
    "wof:placetype":"venue"
},
  "geometry": {"coordinates":[6.318369,51.973099],"type":"Point"}
}