{
  "type": "Feature",
  "properties": {
    "addr:full":"Anthony Fokkerweg 61 Amsterdam Noord-Holland 1059 CP",
    "addr:housenumber":"61",
    "addr:postcode":"1059 cp",
    "addr:street":"Anthony Fokkerweg",
    "iso:country":"NL",
    "sg:address":"Anthony Fokkerweg 61",
    "sg:city":"Amsterdam",
    "sg:orig_category":"Diverse Grafische Activiteiten",
    "sg:phone":"+31 20 614 2335",
    "sg:postcode":"1059 CP",
    "sg:province":"Noord-Holland",
    "wof:name":"L & L Retouche Bv",
    "wof:placetype":"venue"
},
  "geometry": {"coordinates":[4.842267,52.341396],"type":"Point"}
}