{
  "type": "Feature",
  "properties": {
    "addr:full":"Meidoornlaan 88 Nieuwe Pekela Groningen 9663 EG",
    "addr:housenumber":"88",
    "addr:postcode":"9663 eg",
    "addr:street":"Meidoornlaan",
    "iso:country":"NL",
    "sg:address":"Meidoornlaan 88",
    "sg:city":"Nieuwe Pekela",
    "sg:orig_category":"Overheidsdiensten",
    "sg:phone":"+31 597 645 678",
    "sg:postcode":"9663 EG",
    "sg:province":"Groningen",
    "wof:name":"Ontmoetingscentrum De Kiepe",
    "wof:placetype":"venue"
},
  "geometry": {"coordinates":[6.966173172,53.0794639587],"type":"Point"}
}