{
  "type": "Feature",
  "properties": {
    "iso:country":"NL",
    "sg:address":"Kinineln 1",
    "sg:city":"S Graveland",
    "sg:orig_category":"Sportverenigingen En Ontspannings- Verenigingen",
    "sg:phone":"+31 35 656 0506",
    "sg:postcode":"1243 LD",
    "sg:province":"North Holland",
    "wof:name":"S-Graveland Voetbalver",
    "wof:placetype":"venue"
},
  "geometry": {"coordinates":[5.123305,52.224094],"type":"Point"}
}