{
  "type": "Feature",
  "properties": {
    "addr:full":"Lambertusstraat 19 Brunssum Limburg 6444 XA",
    "addr:housenumber":"19",
    "addr:postcode":"6444 xa",
    "addr:street":"Lambertusstraat",
    "iso:country":"NL",
    "sg:address":"Lambertusstraat 19",
    "sg:city":"Brunssum",
    "sg:orig_category":"Technische Studies And Onderzoek",
    "sg:phone":"+31 45 527 3000",
    "sg:postcode":"6444 XA",
    "sg:province":"Limburg",
    "wof:name":"Vof Procon Instrumentatie Techniek",
    "wof:placetype":"venue"
},
  "geometry": {"coordinates":[5.952813,50.937935],"type":"Point"}
}