{
  "type": "Feature",
  "properties": {
    "addr:full":"Chinaln 85 Delft Zuid-Holland 2622 JS",
    "addr:housenumber":"85",
    "addr:postcode":"2622 js",
    "addr:street":"Chinaln",
    "iso:country":"NL",
    "sg:address":"Chinaln 85",
    "sg:city":"Delft",
    "sg:orig_category":"Organisatiebureaus",
    "sg:phone":"+31 6 51369534",
    "sg:postcode":"2622 JS",
    "sg:province":"Zuid-Holland",
    "wof:name":"Braak Consultancy Bv, Ter",
    "wof:placetype":"venue"
},
  "geometry": {"coordinates":[4.3380069733,51.9790267944],"type":"Point"}
}