{
  "type": "Feature",
  "properties": {
    "iso:country":"NL",
    "sg:address":"Loevestein 2",
    "sg:city":"S Hertogenbosch",
    "sg:orig_category":"Bloemen En Planten",
    "sg:phone":"+31 73 642 7318",
    "sg:postcode":"5235 GC",
    "sg:province":"Noord-Brabant",
    "wof:name":"Biermans",
    "wof:placetype":"venue"
},
  "geometry": {"coordinates":[5.307772,51.722591],"type":"Point"}
}