{
  "type": "Feature",
  "properties": {
    "addr:full":"Schilkkade 1B Ter Aar Zuid-Holland 2461 LB",
    "addr:housenumber":"1b",
    "addr:postcode":"aar;2461 lb",
    "addr:street":"Schilkkade",
    "iso:country":"NL",
    "sg:address":"Schilkkade 1B",
    "sg:city":"Ter Aar",
    "sg:orig_category":"Metaalbekleding And -Behandeling",
    "sg:phone":"+31 172 604 705",
    "sg:postcode":"2461 LB",
    "sg:province":"Zuid-Holland",
    "wof:name":"R. Berk",
    "wof:placetype":"venue"
},
  "geometry": {"coordinates":[4.733204,52.181362],"type":"Point"}
}