{
  "type": "Feature",
  "properties": {
    "addr:full":"Willemsweg 43 Nijmegen Gelderland 6531 DB",
    "addr:housenumber":"43",
    "addr:postcode":"6531 db",
    "addr:street":"Willemsweg;Gelderland",
    "iso:country":"NL",
    "sg:address":"Willemsweg 43",
    "sg:city":"Nijmegen",
    "sg:orig_category":"Fietshandelaren",
    "sg:phone":"+31 24 355 8854",
    "sg:postcode":"6531 DB",
    "sg:province":"Gelderland",
    "wof:name":"Rijwielhandel Willemse",
    "wof:placetype":"venue"
},
  "geometry": {"coordinates":[5.849784,51.836708],"type":"Point"}
}