{
  "type": "Feature",
  "properties": {
    "addr:full":"Van Vrijberghestraat 18 Driebergen-Rijsenburg Utrecht 3972 EN",
    "addr:housenumber":"18",
    "addr:postcode":"3972 en",
    "addr:street":"Van Vrijberghestraat",
    "iso:country":"NL",
    "sg:address":"Van Vrijberghestraat 18",
    "sg:city":"Driebergen-Rijsenburg",
    "sg:orig_category":"Loodgieterswerk, Verwarming And Sanitaire Installaties",
    "sg:phone":"+31 343 521 559",
    "sg:postcode":"3972 EN",
    "sg:province":"Utrecht",
    "wof:name":"Techni Call",
    "wof:placetype":"venue"
},
  "geometry": {"coordinates":[5.274502,52.054749],"type":"Point"}
}