{
  "type": "Feature",
  "properties": {
    "addr:full":"Berkenln 11 Maarn Utrecht 3951 XW",
    "addr:housenumber":"11",
    "addr:postcode":"3951 xw",
    "addr:street":"Berkenln",
    "iso:country":"NL",
    "sg:address":"Berkenln 11",
    "sg:city":"Maarn",
    "sg:classifiers":[
        {
            "category":"Professional",
            "subcategory":"Management & Consulting",
            "type":"Services"
        }
    ],
    "sg:phone":"+31 343 441 743",
    "sg:postcode":"3951 XW",
    "sg:province":"Utrecht",
    "sg:tags":[
        "relation",
        "adviesbureaus",
        "public"
    ],
    "wof:name":"Borgsteijn & Partn Vof",
    "wof:placetype":"venue"
},
  "geometry": {"coordinates":[5.369307,52.062035],"type":"Point"}
}