{
  "type": "Feature",
  "properties": {
    "addr:full":"Dr M L Kingsngl 1 Drachten Friesland 9203 JC",
    "addr:housenumber":"1",
    "addr:postcode":"9203 jc",
    "iso:country":"NL",
    "sg:address":"Dr M L Kingsngl 1",
    "sg:city":"Drachten",
    "sg:orig_category":"Orthopedische Artikelen",
    "sg:phone":"+31 512 584 999",
    "sg:postcode":"9203 JC",
    "sg:province":"Friesland",
    "sg:website":"http://www.orthin.nl",
    "wof:name":"Orthin Bv",
    "wof:placetype":"venue"
},
  "geometry": {"coordinates":[6.0985651016,53.1028709412],"type":"Point"}
}