{
  "type": "Feature",
  "properties": {
    "addr:full":"Ceintuurbaan 210 Rotterdam South Holland 3051 KD",
    "addr:housenumber":"210",
    "addr:postcode":"3051 kd",
    "addr:street":"Ceintuurbaan",
    "iso:country":"NL",
    "sg:address":"Ceintuurbaan 210",
    "sg:city":"Rotterdam",
    "sg:orig_category":"Bouwmaterialen Gh",
    "sg:phone":"+31 10 418 8166",
    "sg:postcode":"3051 KD",
    "sg:province":"South Holland",
    "wof:name":"Bouwcenter Fels & Burgers",
    "wof:placetype":"venue"
},
  "geometry": {"coordinates":[4.470198,51.941002],"type":"Point"}
}