{
  "type": "Feature",
  "properties": {
    "addr:full":"Vredeman De Vriesstraat 85 Tilburg Noord-Brabant 5041 GR",
    "addr:housenumber":"85",
    "addr:postcode":"5041",
    "addr:street":"Vredeman De Vriesstraat",
    "iso:country":"NL",
    "sg:address":"Vredeman De Vriesstraat 85",
    "sg:city":"Tilburg",
    "sg:classifiers":[
        {
            "category":"Food & Beverages",
            "subcategory":"Fruits & Vegetables",
            "type":"Retail Goods"
        }
    ],
    "sg:phone":"+31 13 543 5744",
    "sg:postcode":"5041 GR",
    "sg:province":"Noord-Brabant",
    "sg:tags":[
        "groenten"
    ],
    "wof:name":"Ton En Rene Timmermans Groente & Fruit Versspecial",
    "wof:placetype":"venue"
},
  "geometry": {"coordinates":[5.073396,51.564117],"type":"Point"}
}