{
  "type": "Feature",
  "properties": {
    "addr:full":"Schoolstr 39 Moergestel North Brabant 5066 ED",
    "addr:housenumber":"39",
    "addr:postcode":"5066 ed",
    "addr:street":"Schoolstr",
    "iso:country":"NL",
    "sg:address":"Schoolstr 39",
    "sg:city":"Moergestel",
    "sg:orig_category":"Logopedisten",
    "sg:phone":"+31 13 513 6042",
    "sg:postcode":"5066 ED",
    "sg:province":"North Brabant",
    "wof:name":"Gils-Van Zelst, L Van",
    "wof:placetype":"venue"
},
  "geometry": {"coordinates":[5.181395,51.540588],"type":"Point"}
}