{
  "type": "Feature",
  "properties": {
    "addr:full":"Oosteinde 3 Schermerhorn Noord-Holland 1636 XR",
    "addr:housenumber":"3",
    "addr:postcode":"1636 xr",
    "addr:street":"Oosteinde",
    "iso:country":"NL",
    "sg:address":"Oosteinde 3",
    "sg:city":"Schermerhorn",
    "sg:orig_category":"Verzekeringen",
    "sg:phone":"+31 72 502 1375",
    "sg:postcode":"1636 XR",
    "sg:province":"Noord-Holland",
    "wof:name":"Assurantiekantoor J Bakker",
    "wof:placetype":"venue"
},
  "geometry": {"coordinates":[4.889759,52.600864],"type":"Point"}
}