{
  "type": "Feature",
  "properties": {
    "addr:full":"Venus 100 Heerenveen Provincie Friesland 8448 GW",
    "addr:housenumber":"100",
    "addr:postcode":"8448 gw",
    "addr:street":"Venus;Provincie Friesland",
    "iso:country":"NL",
    "sg:address":"Venus 100",
    "sg:city":"Heerenveen",
    "sg:orig_category":"Werving And Selectie Van Tijdelijk Personeel And Uitzendkantoren",
    "sg:phone":"+31 513 619 393",
    "sg:postcode":"8448 GW",
    "sg:province":"Provincie Friesland",
    "wof:name":"Capac",
    "wof:placetype":"venue"
},
  "geometry": {"coordinates":[5.9366412163,52.9726333618],"type":"Point"}
}