{
  "type": "Feature",
  "properties": {
    "addr:full":"Postbus 108 Aerdenhout Noord-Holland 2110 AC",
    "addr:housenumber":"108",
    "addr:postcode":"2110 ac",
    "addr:street":"Postbus",
    "iso:country":"NL",
    "sg:address":"Postbus 108",
    "sg:city":"Aerdenhout",
    "sg:orig_category":"Pruiken",
    "sg:phone":"+31 23 531 1567",
    "sg:postcode":"2110 AC",
    "sg:province":"Noord-Holland",
    "sg:website":"http://www.tophaarwerkersgilde.nl",
    "wof:name":"Top Haarwerkers Gilde Ned, Ver",
    "wof:placetype":"venue"
},
  "geometry": {"coordinates":[4.59305,52.366798],"type":"Point"}
}