{
  "type": "Feature",
  "properties": {
    "addr:full":"J Dutilhwg 203 Rotterdam Zuid-Holland 3065 KA",
    "addr:housenumber":"203",
    "addr:postcode":"3065 ka",
    "iso:country":"NL",
    "sg:address":"J Dutilhwg 203",
    "sg:city":"Rotterdam",
    "sg:orig_category":"Schoonheidsinstituten",
    "sg:phone":"+31 10 235 5600",
    "sg:postcode":"3065 KA",
    "sg:province":"Zuid-Holland",
    "wof:name":"Sigma",
    "wof:placetype":"venue"
},
  "geometry": {"coordinates":[4.559398,51.929966],"type":"Point"}
}