{
  "type": "Feature",
  "properties": {
    "addr:full":"Veerstr 6 Woensdrecht Noord-Brabant 4634 VZ",
    "addr:housenumber":"6",
    "addr:postcode":"4634 vz",
    "addr:street":"Veerstr",
    "iso:country":"NL",
    "sg:address":"Veerstr 6",
    "sg:city":"Woensdrecht",
    "sg:orig_category":"Kappers",
    "sg:phone":"+31 6 51533384",
    "sg:postcode":"4634 VZ",
    "sg:province":"Noord-Brabant",
    "wof:name":"Diana Hair Home Service",
    "wof:placetype":"venue"
},
  "geometry": {"coordinates":[4.3081660271,51.4277038574],"type":"Point"}
}