{
  "type": "Feature",
  "properties": {
    "addr:full":"Spyksedk 12 Gorinchem South Holland 4207 GN",
    "addr:housenumber":"12",
    "addr:postcode":"4207 gn",
    "addr:street":"Spyksedk",
    "iso:country":"NL",
    "sg:address":"Spyksedk 12",
    "sg:city":"Gorinchem",
    "sg:orig_category":"Autoruiten",
    "sg:phone":"+31 183 666 612",
    "sg:postcode":"4207 GN",
    "sg:province":"South Holland",
    "sg:website":"http://www.carglass.nl",
    "wof:name":"Carglass",
    "wof:placetype":"venue"
},
  "geometry": {"coordinates":[4.979852,51.833721],"type":"Point"}
}