{
  "type": "Feature",
  "properties": {
    "addr:full":"Heugemerweg 2 A Maastricht Limburg 6221 GJ",
    "addr:housenumber":"2 a",
    "addr:postcode":"6221 gj",
    "addr:street":"Heugemerweg",
    "iso:country":"NL",
    "sg:address":"Heugemerweg 2 A",
    "sg:city":"Maastricht",
    "sg:orig_category":"Werving And Selectie Van Vast Personeel",
    "sg:phone":"+31 43 326 1818",
    "sg:postcode":"6221 GJ",
    "sg:province":"Limburg",
    "wof:name":"Orion Engineering",
    "wof:placetype":"venue"
},
  "geometry": {"coordinates":[5.7052659988,50.8470726013],"type":"Point"}
}