{
  "type": "Feature",
  "properties": {
    "addr:full":"Kweekweg 24 Epe Gelderland 8161 PG",
    "addr:housenumber":"24",
    "addr:postcode":"8161",
    "addr:street":"Kweekweg;Gelderland;Pg",
    "iso:country":"NL",
    "sg:address":"Kweekweg 24",
    "sg:city":"Epe",
    "sg:orig_category":"Pompen And Compressoren Fab",
    "sg:phone":"+31 578 613 180",
    "sg:postcode":"8161 PG",
    "sg:province":"Gelderland",
    "wof:name":"Rijva Bv",
    "wof:placetype":"venue"
},
  "geometry": {"coordinates":[5.994042,52.345051],"type":"Point"}
}