{
  "type": "Feature",
  "properties": {
    "addr:full":"V Bergenstr 39 S Gravenhage South Holland 2583 CS",
    "addr:housenumber":"39",
    "addr:postcode":"2583 cs",
    "addr:street":"S Gravenhage",
    "iso:country":"NL",
    "sg:address":"V Bergenstr 39",
    "sg:city":"S Gravenhage",
    "sg:orig_category":"Bloemen En Planten",
    "sg:phone":"+31 70 355 9468",
    "sg:postcode":"2583 CS",
    "sg:province":"South Holland",
    "wof:name":"Westfleur, Fa",
    "wof:placetype":"venue"
},
  "geometry": {"coordinates":[4.25526,52.09124],"type":"Point"}
}