{
  "type": "Feature",
  "properties": {
    "iso:country":"NL",
    "sg:address":"Stormezandeweg 5",
    "sg:city":"Wemeldinge",
    "sg:orig_category":"Schilderwerk",
    "sg:phone":"+31 113 622 788",
    "sg:postcode":"4424 EZ",
    "sg:province":"Zeeland",
    "wof:name":"Firma Vermeij-Ooms",
    "wof:placetype":"venue"
},
  "geometry": {"coordinates":[3.997886,51.519672],"type":"Point"}
}