{
  "type": "Feature",
  "properties": {
    "addr:full":"Dorpsstraat 8 Ruurlo Gelderland 7261 AW",
    "addr:housenumber":"8",
    "addr:postcode":"7261 aw",
    "addr:street":"Dorpsstraat;Gelderland",
    "iso:country":"NL",
    "sg:address":"Dorpsstraat 8",
    "sg:city":"Ruurlo",
    "sg:orig_category":"Kappers",
    "sg:phone":"+31 573 451 552",
    "sg:postcode":"7261 AW",
    "sg:province":"Gelderland",
    "wof:name":"Swift Hairfashion",
    "wof:placetype":"venue"
},
  "geometry": {"coordinates":[6.449277,52.08527],"type":"Point"}
}