{
  "type": "Feature",
  "properties": {
    "addr:full":"Prins Karelstraat 75 Helmond North Brabant 5701 VK",
    "addr:housenumber":"75",
    "addr:postcode":"5701 vk",
    "addr:street":"Prins Karelstraat",
    "iso:country":"NL",
    "sg:address":"Prins Karelstraat 75",
    "sg:city":"Helmond",
    "sg:orig_category":"Bloemen And Planten",
    "sg:phone":"+31 492 527 931",
    "sg:postcode":"5701 VK",
    "sg:province":"North Brabant",
    "wof:name":"Bloemenboetiek Sylvia",
    "wof:placetype":"venue"
},
  "geometry": {"coordinates":[5.671847,51.479855],"type":"Point"}
}