{
  "type": "Feature",
  "properties": {
    "addr:full":"Westzyde 47 Zaandam Noord-Holland 1506 EB",
    "addr:housenumber":"47",
    "addr:postcode":"1506 eb",
    "addr:street":"Westzyde",
    "iso:country":"NL",
    "sg:address":"Westzyde 47",
    "sg:city":"Zaandam",
    "sg:orig_category":"Warenhuizen",
    "sg:phone":"+31 75 612 5514",
    "sg:postcode":"1506 EB",
    "sg:province":"Noord-Holland",
    "wof:name":"Action",
    "wof:placetype":"venue"
},
  "geometry": {"coordinates":[4.8089251518,52.4494400024],"type":"Point"}
}