{
  "type": "Feature",
  "properties": {
    "addr:full":"Postbus 43 Sassenheim Zuid-Holland 2170 AA",
    "addr:housenumber":"43",
    "addr:postcode":"2170 aa",
    "addr:street":"Postbus",
    "iso:country":"NL",
    "sg:address":"Postbus 43",
    "sg:city":"Sassenheim",
    "sg:orig_category":"Grafisch Ontwerpers",
    "sg:phone":"+31 252 220 045",
    "sg:postcode":"2170 AA",
    "sg:province":"Zuid-Holland",
    "wof:name":"Typisch Grafisch",
    "wof:placetype":"venue"
},
  "geometry": {"coordinates":[4.52109,52.226662],"type":"Point"}
}