{
  "type": "Feature",
  "properties": {
    "iso:country":"NL",
    "sg:address":"Enkele Ring 43",
    "sg:city":"Sommelsdijk",
    "sg:orig_category":"Fruit And Groenten Gh",
    "sg:phone":"+31 187 486 852",
    "sg:postcode":"3245 AH",
    "sg:province":"South Holland",
    "wof:name":"P. Lodder",
    "wof:placetype":"venue"
},
  "geometry": {"coordinates":[4.150862,51.75845],"type":"Point"}
}