{
  "type": "Feature",
  "properties": {
    "addr:full":"Amaliastr 3-5 S Gravenhage South Holland 2514 JC",
    "addr:housenumber":"3-5",
    "addr:postcode":"2514 jc",
    "addr:street":"Amaliastr;S Gravenhage",
    "iso:country":"NL",
    "sg:address":"Amaliastr 3-5",
    "sg:city":"S Gravenhage",
    "sg:orig_category":"Administratie- En Boekhoudkantoren",
    "sg:phone":"+31 70 346 9396",
    "sg:postcode":"2514 JC",
    "sg:province":"South Holland",
    "wof:name":"Polderman",
    "wof:placetype":"venue"
},
  "geometry": {"coordinates":[4.30935,52.084148],"type":"Point"}
}