{
  "type": "Feature",
  "properties": {
    "iso:country":"NL",
    "sg:address":"Amaliastr 3-5",
    "sg:city":"S Gravenhage",
    "sg:orig_category":"Administratie- En Boekhoudkantoren",
    "sg:phone":"+31 70 346 9396",
    "sg:postcode":"2514 JC",
    "sg:province":"South Holland",
    "wof:name":"Polderman",
    "wof:placetype":"venue"
},
  "geometry": {"coordinates":[4.30935,52.084148],"type":"Point"}
}