{
  "type": "Feature",
  "properties": {
    "addr:full":"Smidsweg 28 'S Gravendeel South Holland 3295 BV",
    "addr:housenumber":"28",
    "addr:postcode":"3295 bv",
    "addr:street":"Smidsweg;' S Gravendeel",
    "iso:country":"NL",
    "sg:address":"Smidsweg 28",
    "sg:city":"'S Gravendeel",
    "sg:orig_category":"Fruit And Groenten Gh",
    "sg:phone":"+31 78 673 1461",
    "sg:postcode":"3295 BV",
    "sg:province":"South Holland",
    "wof:name":"P. Koomans",
    "wof:placetype":"venue"
},
  "geometry": {"coordinates":[4.614648,51.780792],"type":"Point"}
}