{
  "type": "Feature",
  "properties": {
    "addr:full":"Dukaat 10 Deurne North Brabant 5751 PW",
    "addr:housenumber":"10",
    "addr:postcode":"5751 pw",
    "addr:street":"Dukaat",
    "iso:country":"NL",
    "sg:address":"Dukaat 10",
    "sg:city":"Deurne",
    "sg:orig_category":"Kunststoffen - Fabrieken En Groothandel",
    "sg:phone":"+31 493 322 068",
    "sg:postcode":"5751 PW",
    "sg:province":"North Brabant",
    "wof:name":"Verpas",
    "wof:placetype":"venue"
},
  "geometry": {"coordinates":[5.775838,51.464298],"type":"Point"}
}