{
  "type": "Feature",
  "properties": {
    "addr:full":"Toulonseln 137 Dordrecht South Holland 3311 LT",
    "addr:housenumber":"137",
    "addr:postcode":"3311 lt",
    "iso:country":"NL",
    "sg:address":"Toulonseln 137",
    "sg:city":"Dordrecht",
    "sg:orig_category":"Artsen - Huisartsen",
    "sg:phone":"+31 78 613 7400",
    "sg:postcode":"3311 LT",
    "sg:province":"South Holland",
    "wof:name":"Sijthoff En M Ten Sijthoff-Lemson, I G Ten",
    "wof:placetype":"venue"
},
  "geometry": {"coordinates":[4.67415,51.80764],"type":"Point"}
}