{
  "type": "Feature",
  "properties": {
    "addr:full":"Spoorstraat 14 'S Gravenpolder Zeeland 4431 NK",
    "addr:housenumber":"14",
    "addr:postcode":"4431 nk",
    "addr:street":"Spoorstraat;' S Gravenpolder Zeeland",
    "iso:country":"NL",
    "sg:address":"Spoorstraat 14",
    "sg:city":"'S Gravenpolder",
    "sg:orig_category":"Kantoorartikelen",
    "sg:phone":"+31 113 311 324",
    "sg:postcode":"4431 NK",
    "sg:province":"Zeeland",
    "wof:name":"Werma Office International Bv",
    "wof:placetype":"venue"
},
  "geometry": {"coordinates":[3.8827769756,51.4490242004],"type":"Point"}
}