{
  "type": "Feature",
  "properties": {
    "addr:full":"Burg Honykstr 34 Venhuizen Noord-Holland 1606 XM",
    "addr:housenumber":"34",
    "addr:postcode":"1606 xm",
    "addr:street":"Burg",
    "iso:country":"NL",
    "sg:address":"Burg Honykstr 34",
    "sg:city":"Venhuizen",
    "sg:orig_category":"Geluidsinstallaties - Verhuur",
    "sg:phone":"+31 228 544 003",
    "sg:postcode":"1606 XM",
    "sg:province":"Noord-Holland",
    "wof:name":"What About Bob",
    "wof:placetype":"venue"
},
  "geometry": {"coordinates":[5.199493,52.662418],"type":"Point"}
}