{
  "type": "Feature",
  "properties": {
    "addr:full":"Nobelstraat 1 'S Gravenhage Zuid-Holland 2513 BC",
    "addr:housenumber":"1 '",
    "addr:postcode":"2513 bc",
    "addr:street":"Nobelstraat",
    "iso:country":"NL",
    "sg:address":"Nobelstraat 1",
    "sg:city":"'S Gravenhage",
    "sg:orig_category":"Schoenen",
    "sg:phone":"+31 70 361 5845",
    "sg:postcode":"2513 BC",
    "sg:province":"Zuid-Holland",
    "wof:name":"Niconico Bv",
    "wof:placetype":"venue"
},
  "geometry": {"coordinates":[4.307243,52.078876],"type":"Point"}
}