{
  "type": "Feature",
  "properties": {
    "addr:full":"Zuidsngl 30 Leiden Zuid-Holland 2312 SC",
    "addr:housenumber":"30",
    "addr:postcode":"2312 sc",
    "addr:street":"Zuidsngl",
    "iso:country":"NL",
    "sg:address":"Zuidsngl 30",
    "sg:city":"Leiden",
    "sg:orig_category":"Luchtfotografie",
    "sg:phone":"+31 71 514 9606",
    "sg:postcode":"2312 SC",
    "sg:province":"Zuid-Holland",
    "wof:name":"Picture Partn",
    "wof:placetype":"venue"
},
  "geometry": {"coordinates":[4.49463,52.154572],"type":"Point"}
}