{
  "type": "Feature",
  "properties": {
    "addr:full":"Overtoom 85 Amsterdam Noord-Holland 1054 HC",
    "addr:housenumber":"85",
    "addr:postcode":"1054 hc",
    "addr:street":"Overtoom",
    "iso:country":"NL",
    "sg:address":"Overtoom 85",
    "sg:city":"Amsterdam",
    "sg:orig_category":"Kunst And Kunstenaarsbenodigdheden",
    "sg:phone":"+31 20 616 3103",
    "sg:postcode":"1054 HC",
    "sg:province":"Noord-Holland",
    "wof:name":"Lijsten Atelier W. Van Poelgeest Bv",
    "wof:placetype":"venue"
},
  "geometry": {"coordinates":[4.875343,52.362652],"type":"Point"}
}