{
  "type": "Feature",
  "properties": {
    "addr:full":"Europaboulevard 160 Alkmaar Noord-Holland 1825 SH",
    "addr:housenumber":"160",
    "addr:postcode":"1825 sh",
    "addr:street":"Europaboulevard",
    "iso:country":"NL",
    "sg:address":"Europaboulevard 160",
    "sg:city":"Alkmaar",
    "sg:classifiers":[
        {
            "category":"Retail",
            "subcategory":"Photofinishing",
            "type":"Services"
        }
    ],
    "sg:phone":"+31 72 561 9523",
    "sg:postcode":"1825 SH",
    "sg:province":"Noord-Holland",
    "sg:tags":[
        "foto",
        "film"
    ],
    "wof:name":"Drogisterij P.J. Veul",
    "wof:placetype":"venue"
},
  "geometry": {"coordinates":[4.756921,52.65461],"type":"Point"}
}