{
  "type": "Feature",
  "properties": {
    "addr:full":"Kerkbuurt 38 Westzaan North Holland 1551 AE",
    "addr:housenumber":"38",
    "addr:postcode":"1551 ae",
    "addr:street":"Kerkbuurt",
    "iso:country":"NL",
    "sg:address":"Kerkbuurt 38",
    "sg:city":"Westzaan",
    "sg:orig_category":"Banken And Kredietinstellingen",
    "sg:phone":"+31 75 628 1110",
    "sg:postcode":"1551 AE",
    "sg:province":"North Holland",
    "wof:name":"Postkantoor",
    "wof:placetype":"venue"
},
  "geometry": {"coordinates":[4.772209,52.463924],"type":"Point"}
}