{
  "type": "Feature",
  "properties": {
    "iso:country":"NL",
    "sg:address":"Kerkbuurt 38",
    "sg:city":"Westzaan",
    "sg:orig_category":"Banken And Kredietinstellingen",
    "sg:phone":"+31 75 628 1110",
    "sg:postcode":"1551 AE",
    "sg:province":"North Holland",
    "wof:name":"Postkantoor",
    "wof:placetype":"venue"
},
  "geometry": {"coordinates":[4.772209,52.463924],"type":"Point"}
}