{
  "type": "Feature",
  "properties": {
    "iso:country":"NL",
    "sg:address":"Scheepmakersstr 1",
    "sg:city":"S Gravenhage",
    "sg:orig_category":"Verenigingen En Stichtingen",
    "sg:phone":"+31 70 383 7676",
    "sg:postcode":"2515 VA",
    "sg:province":"South Holland",
    "wof:name":"Inner Warrior, Sticht",
    "wof:placetype":"venue"
},
  "geometry": {"coordinates":[4.31741,52.083988],"type":"Point"}
}