{
  "type": "Feature",
  "properties": {
    "addr:full":"Emmaln 11 Apeldoorn Gelderland 7316 EC",
    "addr:housenumber":"11",
    "addr:postcode":"7316 ec",
    "addr:street":"Emmaln;Gelderland",
    "iso:country":"NL",
    "sg:address":"Emmaln 11",
    "sg:city":"Apeldoorn",
    "sg:orig_category":"Adviesbureaus Bedrijfsorganisatie",
    "sg:phone":"+31 55 576 0136",
    "sg:postcode":"7316 EC",
    "sg:province":"Gelderland",
    "wof:name":"Sietsma Mgt Bv",
    "wof:placetype":"venue"
},
  "geometry": {"coordinates":[5.958022,52.223022],"type":"Point"}
}