{
  "type": "Feature",
  "properties": {
    "iso:country":"NL",
    "sg:address":"De Veluwse Snees 9",
    "sg:city":"Dronten",
    "sg:orig_category":"Kappers",
    "sg:phone":"+31 321 381 654",
    "sg:postcode":"8252 KV",
    "sg:province":"NL.",
    "wof:name":"Swanborn, Studio Angeline",
    "wof:placetype":"venue"
},
  "geometry": {"coordinates":[5.691901,52.519035],"type":"Point"}
}