{
  "type": "Feature",
  "properties": {
    "iso:country":"NL",
    "sg:address":"Ceresstraat 17",
    "sg:city":"Assen",
    "sg:orig_category":"Diverse Bedrijfsinstallaties Gh",
    "sg:phone":"+31 592 351 190",
    "sg:postcode":"9401 DP",
    "sg:province":"Drenthe",
    "wof:name":"Tds Special Products Bv",
    "wof:placetype":"venue"
},
  "geometry": {"coordinates":[6.56018,52.996929],"type":"Point"}
}