{
  "type": "Feature",
  "properties": {
    "addr:full":"Raadhuisplein 1 Tubbergen NL.08 7651 CV",
    "addr:housenumber":"1;nl.08",
    "addr:postcode":"7651 cv",
    "addr:street":"Raadhuisplein",
    "iso:country":"NL",
    "sg:address":"Raadhuisplein 1",
    "sg:city":"Tubbergen",
    "sg:orig_category":"Overheidsdiensten",
    "sg:phone":"+31 546 628 000",
    "sg:postcode":"7651 CV",
    "sg:province":"NL.08",
    "wof:name":"Gemeente Tubbergen",
    "wof:placetype":"venue"
},
  "geometry": {"coordinates":[6.7811160088,52.4080467224],"type":"Point"}
}