{
  "type": "Feature",
  "properties": {
    "addr:full":"Schaarbroekerwg 2 Roermond Limburg 6042 EJ",
    "addr:housenumber":"2",
    "addr:postcode":"6042 ej",
    "addr:street":"Schaarbroekerwg",
    "iso:country":"NL",
    "sg:address":"Schaarbroekerwg 2",
    "sg:city":"Roermond",
    "sg:orig_category":"Waterschappen",
    "sg:phone":"+31 475 347 773",
    "sg:postcode":"6042 EJ",
    "sg:province":"Limburg",
    "wof:name":"Rijkswaterstaat Viascoop 73",
    "wof:placetype":"venue"
},
  "geometry": {"coordinates":[6.0175461769,51.2118911743],"type":"Point"}
}