{
  "type": "Feature",
  "properties": {
    "addr:full":"Lylantse Baan 2 Capelle A/D Ijssel Zuid-Holland 2908 LG",
    "addr:housenumber":"2;a / d",
    "addr:postcode":"2908 lg",
    "addr:street":"Lylantse Baan",
    "iso:country":"NL",
    "sg:address":"Lylantse Baan 2",
    "sg:city":"Capelle A/D Ijssel",
    "sg:orig_category":"Metaalwerken",
    "sg:phone":"+31 10 451 6695",
    "sg:postcode":"2908 LG",
    "sg:province":"Zuid-Holland",
    "wof:name":"Carpetland Bv",
    "wof:placetype":"venue"
},
  "geometry": {"coordinates":[4.564409,51.95332],"type":"Point"}
}