{
  "type": "Feature",
  "properties": {
    "addr:full":"Nieuwstraat 21 Sint Michielsgestel North Brabant 5271 AB",
    "addr:housenumber":"21;michielsgestel",
    "addr:postcode":"5271 ab",
    "addr:street":"Nieuwstraat",
    "iso:country":"NL",
    "sg:address":"Nieuwstraat 21",
    "sg:city":"Sint Michielsgestel",
    "sg:orig_category":"Banken And Kredietinstellingen",
    "sg:phone":"+31 73 551 4392",
    "sg:postcode":"5271 AB",
    "sg:province":"North Brabant",
    "wof:name":"Abn Amro",
    "wof:placetype":"venue"
},
  "geometry": {"coordinates":[5.351919,51.640057],"type":"Point"}
}