{
  "type": "Feature",
  "properties": {
    "addr:full":"Meeuwerderwg 59 Groningen Groningen 9724 EN",
    "addr:housenumber":"59",
    "addr:postcode":"9724 en",
    "addr:street":"Meeuwerderwg",
    "iso:country":"NL",
    "sg:address":"Meeuwerderwg 59",
    "sg:city":"Groningen",
    "sg:orig_category":"Fotografie Reclame En Mode",
    "sg:phone":"+31 50 312 8687",
    "sg:postcode":"9724 EN",
    "sg:province":"Groningen",
    "sg:website":"http://www.groningen.demon.nl",
    "wof:name":"Andy Fox",
    "wof:placetype":"venue"
},
  "geometry": {"coordinates":[6.578435,53.212318],"type":"Point"}
}