{
  "type": "Feature",
  "properties": {
    "iso:country":"NL",
    "sg:address":"Anthonetta Kuijlstraat 67-69",
    "sg:city":"Rotterdam",
    "sg:orig_category":"Autoreparatie And Auto-Onderhoud",
    "sg:phone":"+31 10 286 0047",
    "sg:postcode":"3066  G",
    "sg:province":"Zuid-Holland",
    "wof:name":"Banden Service Prinsenland",
    "wof:placetype":"venue"
},
  "geometry": {"coordinates":[4.539629,51.931435],"type":"Point"}
}