{
  "type": "Feature",
  "properties": {
    "addr:full":"Liesveldweg 36 Ameide South Holland 4233 HH",
    "addr:housenumber":"36",
    "addr:postcode":"4233 hh",
    "addr:street":"Liesveldweg",
    "iso:country":"NL",
    "sg:address":"Liesveldweg 36",
    "sg:city":"Ameide",
    "sg:orig_category":"Boekhouders",
    "sg:phone":"+31 183 601 611",
    "sg:postcode":"4233 HH",
    "sg:province":"South Holland",
    "wof:name":"J.H. Peeters Administratiekantoor",
    "wof:placetype":"venue"
},
  "geometry": {"coordinates":[4.965439,51.955246],"type":"Point"}
}