{
  "type": "Feature",
  "properties": {
    "iso:country":"NL",
    "sg:address":"W Vd Zaandreef 5",
    "sg:city":"Voorschoten",
    "sg:orig_category":"Marketingbureaus",
    "sg:phone":"+31 71 531 4079",
    "sg:postcode":"2253 VE",
    "sg:province":"South Holland",
    "wof:name":"Oak Lake Management Bv",
    "wof:placetype":"venue"
},
  "geometry": {"coordinates":[4.463452,52.14172],"type":"Point"}
}