{
  "type": "Feature",
  "properties": {
    "iso:country":"NL",
    "sg:address":"Oostersingel 37",
    "sg:city":"Culemborg",
    "sg:orig_category":"Huizensloop And Bouwrijp Maken",
    "sg:phone":"+31 345 521 255",
    "sg:postcode":"4101 GH",
    "sg:province":"Gelderland",
    "wof:name":"Handelsonderneming Peterse Bv",
    "wof:placetype":"venue"
},
  "geometry": {"coordinates":[5.230624,51.954018],"type":"Point"}
}