{
  "type": "Feature",
  "properties": {
    "addr:full":"Oostersingel 37 Culemborg Gelderland 4101 GH",
    "addr:housenumber":"37",
    "addr:postcode":"4101 gh",
    "addr:street":"Oostersingel;Gelderland",
    "iso:country":"NL",
    "sg:address":"Oostersingel 37",
    "sg:city":"Culemborg",
    "sg:orig_category":"Huizensloop And Bouwrijp Maken",
    "sg:phone":"+31 345 521 255",
    "sg:postcode":"4101 GH",
    "sg:province":"Gelderland",
    "wof:name":"Handelsonderneming Peterse Bv",
    "wof:placetype":"venue"
},
  "geometry": {"coordinates":[5.230624,51.954018],"type":"Point"}
}