{
  "type": "Feature",
  "properties": {
    "addr:full":"C De Bourbonln 18B Amersfoort Utrecht 3818 DJ",
    "addr:housenumber":"18b",
    "addr:postcode":"3818 dj",
    "addr:street":"C",
    "iso:country":"NL",
    "sg:address":"C De Bourbonln 18B",
    "sg:city":"Amersfoort",
    "sg:orig_category":"Beeldende Kunstenaars",
    "sg:phone":"+31 33 463 1315",
    "sg:postcode":"3818 DJ",
    "sg:province":"Utrecht",
    "wof:name":"Ottink, F M",
    "wof:placetype":"venue"
},
  "geometry": {"coordinates":[5.386085,52.152325],"type":"Point"}
}