{
  "type": "Feature",
  "properties": {
    "addr:full":"Postbus 30315 S Gravenhage Zuid-Holland 2500 GH",
    "addr:housenumber":"30315;gravenhage",
    "addr:postcode":"2500 gh",
    "addr:street":"Postbus;S",
    "iso:country":"NL",
    "sg:address":"Postbus 30315",
    "sg:city":"S Gravenhage",
    "sg:orig_category":"Verenigingen En Stichtingen",
    "sg:phone":"+31 70 361 1420",
    "sg:postcode":"2500 GH",
    "sg:province":"Zuid-Holland",
    "wof:name":"Ned Ver Voor Rechtspraak",
    "wof:placetype":"venue"
},
  "geometry": {"coordinates":[4.31741,52.083988],"type":"Point"}
}