{
  "type": "Feature",
  "properties": {
    "addr:full":"Kr Spieringwg 311 Vyfhuizen Noord-Holland 2141 BS",
    "addr:housenumber":"311;2141",
    "addr:postcode":"bs",
    "addr:street":"Vyfhuizen Noord-Holland",
    "iso:country":"NL",
    "sg:address":"Kr Spieringwg 311",
    "sg:city":"Vyfhuizen",
    "sg:classifiers":[
        {
            "category":"Wholesale",
            "subcategory":"Motor Vehicles",
            "type":"Manufacturing & Wholesale Goods"
        }
    ],
    "sg:phone":"+31 23 558 1775",
    "sg:postcode":"2141 BS",
    "sg:province":"Noord-Holland",
    "sg:tags":[
        "scooter",
        "en"
    ],
    "wof:name":"Cross-Shop",
    "wof:placetype":"venue"
},
  "geometry": {"coordinates":[4.679655,52.352299],"type":"Point"}
}