{
  "type": "Feature",
  "properties": {
    "addr:full":"Dwarsvaartwg 9 Oosterstreek Provincie Friesland 8388 MH",
    "addr:housenumber":"9",
    "addr:postcode":"8388 mh",
    "addr:street":"Dwarsvaartwg;Provincie Friesland",
    "iso:country":"NL",
    "sg:address":"Dwarsvaartwg 9",
    "sg:city":"Oosterstreek",
    "sg:orig_category":"Meubelmakerijen",
    "sg:phone":"+31 561 433 271",
    "sg:postcode":"8388 MH",
    "sg:province":"Provincie Friesland",
    "wof:name":"Deijns Meubelmakerij",
    "wof:placetype":"venue"
},
  "geometry": {"coordinates":[6.156495,52.888496],"type":"Point"}
}