{
  "type": "Feature",
  "properties": {
    "addr:full":"W De Rykeln 16 Castricum North Holland 1901 TT",
    "addr:housenumber":"16",
    "addr:postcode":"1901 tt",
    "addr:street":"W De Rykeln",
    "iso:country":"NL",
    "sg:address":"W De Rykeln 16",
    "sg:city":"Castricum",
    "sg:orig_category":"Modevakscholen",
    "sg:phone":"+31 251 655 063",
    "sg:postcode":"1901 TT",
    "sg:province":"North Holland",
    "wof:name":"Rijkhoff",
    "wof:placetype":"venue"
},
  "geometry": {"coordinates":[4.663725,52.546844],"type":"Point"}
}