{
  "type": "Feature",
  "properties": {
    "addr:full":"Genraydelwg 9 Venlo Limburg 5916 NZ",
    "addr:housenumber":"9",
    "addr:postcode":"5916 nz",
    "addr:street":"Genraydelwg",
    "iso:country":"NL",
    "sg:address":"Genraydelwg 9",
    "sg:city":"Venlo",
    "sg:orig_category":"Makelaars En Adviseurs Onroerende Goederen",
    "sg:phone":"+31 77 352 3546",
    "sg:postcode":"5916 NZ",
    "sg:province":"Limburg",
    "sg:website":"http://www.vbo.nl",
    "wof:name":"Rijn Vastgoed, Van",
    "wof:placetype":"venue"
},
  "geometry": {"coordinates":[6.206139,51.37978],"type":"Point"}
}