{
  "type": "Feature",
  "properties": {
    "addr:full":"H De Vriesln 17 Gouda Zuid-Holland 2803 JJ",
    "addr:housenumber":"17",
    "addr:postcode":"2803 jj",
    "iso:country":"NL",
    "sg:address":"H De Vriesln 17",
    "sg:city":"Gouda",
    "sg:orig_category":"Glazenwasserijen",
    "sg:phone":"+31 182 530 295",
    "sg:postcode":"2803 JJ",
    "sg:province":"Zuid-Holland",
    "wof:name":"Eerste Goudse",
    "wof:placetype":"venue"
},
  "geometry": {"coordinates":[4.710715,52.010006],"type":"Point"}
}