{
  "type": "Feature",
  "properties": {
    "addr:full":"Zeesluiswg 55 S Gravenhage Zuid-Holland 2583 DP",
    "addr:housenumber":"55;gravenhage",
    "addr:postcode":"2583 dp",
    "addr:street":"Zeesluiswg;S",
    "iso:country":"NL",
    "sg:address":"Zeesluiswg 55",
    "sg:city":"S Gravenhage",
    "sg:orig_category":"Fitnesscentra",
    "sg:phone":"+31 70 355 7045",
    "sg:postcode":"2583 DP",
    "sg:province":"Zuid-Holland",
    "sg:website":"http://www.bodybasics.nl",
    "wof:name":"Body Basics Health Clubs",
    "wof:placetype":"venue"
},
  "geometry": {"coordinates":[4.25526,52.09124],"type":"Point"}
}