{
  "type": "Feature",
  "properties": {
    "addr:full":"De Sikkel 11 Dronten NL. 8253 CS",
    "addr:housenumber":"11",
    "addr:postcode":"8253 cs",
    "addr:street":"De Sikkel;Nl.",
    "iso:country":"NL",
    "sg:address":"De Sikkel 11",
    "sg:city":"Dronten",
    "sg:orig_category":"Autorijscholen",
    "sg:phone":"+31 321 380 225",
    "sg:postcode":"8253 CS",
    "sg:province":"NL.",
    "wof:name":"Adrie Van Baal",
    "wof:placetype":"venue"
},
  "geometry": {"coordinates":[5.701847,52.527073],"type":"Point"}
}