{
  "type": "Feature",
  "properties": {
    "addr:full":"Midden Polderwg 17 Streefkerk Zuid-Holland 2959 LB",
    "addr:housenumber":"17",
    "addr:postcode":"2959 lb",
    "addr:street":"Midden Polderwg",
    "iso:country":"NL",
    "sg:address":"Midden Polderwg 17",
    "sg:city":"Streefkerk",
    "sg:orig_category":"Loonbedrijven",
    "sg:phone":"+31 6 53855213",
    "sg:postcode":"2959 LB",
    "sg:province":"Zuid-Holland",
    "wof:name":"Boer, A J",
    "wof:placetype":"venue"
},
  "geometry": {"coordinates":[4.802215,51.908325],"type":"Point"}
}