{
  "type": "Feature",
  "properties": {
    "addr:full":"Europapln 1 Kerkrade Limburg 6461 AJ",
    "addr:housenumber":"1",
    "addr:postcode":"6461 aj",
    "addr:street":"Europapln",
    "iso:country":"NL",
    "sg:address":"Europapln 1",
    "sg:city":"Kerkrade",
    "sg:orig_category":"Zalenverhuur",
    "sg:phone":"+31 45 567 9230",
    "sg:postcode":"6461 AJ",
    "sg:province":"Limburg",
    "wof:name":"Rodahal",
    "wof:placetype":"venue"
},
  "geometry": {"coordinates":[6.063066,50.86784],"type":"Point"}
}