{
  "type": "Feature",
  "properties": {
    "addr:full":"Noordersluisweg 2 Lelystad NL. 8243 PR",
    "addr:housenumber":"2",
    "addr:postcode":"8243 pr",
    "addr:street":"Noordersluisweg;Nl.",
    "iso:country":"NL",
    "sg:address":"Noordersluisweg 2",
    "sg:city":"Lelystad",
    "sg:orig_category":"Loodgieterswerk, Verwarming And Sanitaire Installaties",
    "sg:phone":"+31 320 222 599",
    "sg:postcode":"8243 PR",
    "sg:province":"NL.",
    "wof:name":"Technisch Installatiebureau Verkaart Bv",
    "wof:placetype":"venue"
},
  "geometry": {"coordinates":[5.442877,52.505863],"type":"Point"}
}