{
  "type": "Feature",
  "properties": {
    "addr:full":"Postwg 79 Lunteren Gelderland 6741 BB",
    "addr:housenumber":"79",
    "addr:postcode":"6741 bb",
    "addr:street":"Postwg;Gelderland",
    "iso:country":"NL",
    "sg:address":"Postwg 79",
    "sg:city":"Lunteren",
    "sg:orig_category":"Adviesbureaus Bedrijfsorganisatie",
    "sg:phone":"+31 318 485 616",
    "sg:postcode":"6741 BB",
    "sg:province":"Gelderland",
    "wof:name":"Pbs",
    "wof:placetype":"venue"
},
  "geometry": {"coordinates":[5.612093,52.085239],"type":"Point"}
}