{
  "type": "Feature",
  "properties": {
    "addr:full":"Hoofdwg 57 Rilland Zeeland 4411 AP",
    "addr:housenumber":"57",
    "addr:postcode":"4411 ap",
    "addr:street":"Hoofdwg",
    "iso:country":"NL",
    "sg:address":"Hoofdwg 57",
    "sg:city":"Rilland",
    "sg:orig_category":"Banken",
    "sg:phone":"+31 113 239 000",
    "sg:postcode":"4411 AP",
    "sg:province":"Zeeland",
    "sg:website":"http://www.rabobank.nl",
    "wof:name":"Rabobank",
    "wof:placetype":"venue"
},
  "geometry": {"coordinates":[4.17991,51.416954],"type":"Point"}
}