{
  "type": "Feature",
  "properties": {
    "addr:full":"Bultswg 136 Enschede NL.08 7532 XJ",
    "addr:housenumber":"136",
    "addr:postcode":"7532 xj",
    "iso:country":"NL",
    "sg:address":"Bultswg 136",
    "sg:city":"Enschede",
    "sg:orig_category":"Fotojournalisten Freelance",
    "sg:phone":"+31 53 461 5173",
    "sg:postcode":"7532 XJ",
    "sg:province":"NL.08",
    "wof:name":"Willigen, R Van",
    "wof:placetype":"venue"
},
  "geometry": {"coordinates":[6.967488,52.22068],"type":"Point"}
}