{
  "type": "Feature",
  "properties": {
    "addr:full":"Dorpsstr 114 Renswoude Utrecht 3927 BG",
    "addr:housenumber":"114",
    "addr:postcode":"3927",
    "iso:country":"NL",
    "sg:address":"Dorpsstr 114",
    "sg:city":"Renswoude",
    "sg:classifiers":[
        {
            "category":"Retail",
            "subcategory":"Auto Repair",
            "type":"Services"
        }
    ],
    "sg:phone":"+31 318 571 719",
    "sg:postcode":"3927 BG",
    "sg:province":"Utrecht",
    "sg:tags":[
        "garage"
    ],
    "sg:website":"HTTP://www.vanburken.nl",
    "wof:name":"Burken, Van",
    "wof:placetype":"venue"
},
  "geometry": {"coordinates":[5.538955,52.074409],"type":"Point"}
}