{
  "type": "Feature",
  "properties": {
    "addr:full":"Dorpsplein 20 Riel North Brabant 5133 AM",
    "addr:housenumber":"20",
    "addr:postcode":"5133",
    "addr:street":"Dorpsplein",
    "iso:country":"NL",
    "sg:address":"Dorpsplein 20",
    "sg:city":"Riel",
    "sg:orig_category":"Overheidsdiensten",
    "sg:phone":"+31 13 518 1401",
    "sg:postcode":"5133 AM",
    "sg:province":"North Brabant",
    "wof:name":"De Leybron",
    "wof:placetype":"venue"
},
  "geometry": {"coordinates":[5.0240969658,51.5232048035],"type":"Point"}
}