{
  "type": "Feature",
  "properties": {
    "addr:full":"Everjachtstraat 55 Tilburg North Brabant 5042 WG",
    "addr:housenumber":"55",
    "addr:postcode":"5042 wg",
    "addr:street":"Everjachtstraat",
    "iso:country":"NL",
    "sg:address":"Everjachtstraat 55",
    "sg:city":"Tilburg",
    "sg:classifiers":[
        {
            "category":"Fast Food",
            "type":"Food & Drink"
        }
    ],
    "sg:phone":"+31 13 467 3681",
    "sg:postcode":"5042 WG",
    "sg:province":"North Brabant",
    "sg:tags":[
        "afhaal",
        "restaurant"
    ],
    "wof:name":"Ijs- En Eetsalon Tra 'T Zand",
    "wof:placetype":"venue"
},
  "geometry": {"coordinates":[5.047121,51.573021],"type":"Point"}
}