{
  "type": "Feature",
  "properties": {
    "addr:full":"Sint Barbarastraat 122 Heerlen Limburg 6415 RZ",
    "addr:housenumber":"122",
    "addr:postcode":"6415 rz",
    "addr:street":"Sint Barbarastraat",
    "iso:country":"NL",
    "sg:address":"Sint Barbarastraat 122",
    "sg:city":"Heerlen",
    "sg:orig_category":"Kappers",
    "sg:phone":"+31 45 572 0290",
    "sg:postcode":"6415 RZ",
    "sg:province":"Limburg",
    "wof:name":"Kapsalon Pakbiers",
    "wof:placetype":"venue"
},
  "geometry": {"coordinates":[5.9860129356,50.9019622803],"type":"Point"}
}