{
  "type": "Feature",
  "properties": {
    "addr:full":"Amsterdamsestraatweg 138 Utrecht Utrecht 3513 AM",
    "addr:housenumber":"138",
    "addr:postcode":"3513",
    "addr:street":"Amsterdamsestraatweg",
    "iso:country":"NL",
    "sg:address":"Amsterdamsestraatweg 138",
    "sg:city":"Utrecht",
    "sg:classifiers":[
        {
            "category":"Fast Food",
            "type":"Food & Drink"
        }
    ],
    "sg:phone":"+31 30 231 2648",
    "sg:postcode":"3513 AM",
    "sg:province":"Utrecht",
    "sg:tags":[
        "afhaal",
        "restaurant"
    ],
    "wof:name":"Efes Afhaalcentrum Vof",
    "wof:placetype":"venue"
},
  "geometry": {"coordinates":[5.105296,52.097534],"type":"Point"}
}