{
  "type": "Feature",
  "properties": {
    "iso:country":"NL",
    "sg:address":"De Twynder 67",
    "sg:city":"Veldhoven",
    "sg:orig_category":"Adviesbureaus Bedrijfsorganisatie",
    "sg:phone":"+31 6 55728955",
    "sg:postcode":"5506 AM",
    "sg:province":"Noord-Brabant",
    "wof:name":"Kalmijn Vof, J W",
    "wof:placetype":"venue"
},
  "geometry": {"coordinates":[5.383093,51.418587],"type":"Point"}
}