{
  "type": "Feature",
  "properties": {
    "iso:country":"NL",
    "sg:address":"Langevliet 34",
    "sg:city":"Den Helder",
    "sg:orig_category":"Landbouwmachines Gh",
    "sg:phone":"+31 223 641 261",
    "sg:postcode":"1788 BD",
    "sg:province":"Noord-Holland",
    "wof:name":"G Van Mullum",
    "wof:placetype":"venue"
},
  "geometry": {"coordinates":[4.752041,52.900845],"type":"Point"}
}