{
  "type": "Feature",
  "properties": {
    "addr:full":"Rietschans 67 Leiderdorp South Holland 2352 BB",
    "addr:housenumber":"67",
    "addr:postcode":"2352 bb",
    "addr:street":"Rietschans",
    "iso:country":"NL",
    "sg:address":"Rietschans 67",
    "sg:city":"Leiderdorp",
    "sg:orig_category":"Kantoor- En Bedrijfsmeubelen",
    "sg:phone":"+31 71 541 3414",
    "sg:postcode":"2352 BB",
    "sg:province":"South Holland",
    "wof:name":"Cieba Bv",
    "wof:placetype":"venue"
},
  "geometry": {"coordinates":[4.5194587708,52.1677131653],"type":"Point"}
}