{
  "type": "Feature",
  "properties": {
    "iso:country":"NL",
    "sg:address":"Willem De Zwijgerlaan 85",
    "sg:city":"Zevenaar",
    "sg:orig_category":"Fotostudio'S And Fotografen",
    "sg:phone":"+31 316 330 248",
    "sg:postcode":"6904  C",
    "sg:province":"Gelderland",
    "wof:name":"Bas Photo & Design",
    "wof:placetype":"venue"
},
  "geometry": {"coordinates":[6.063222,51.929657],"type":"Point"}
}