{
  "type": "Feature",
  "properties": {
    "addr:full":"Gastelsewg 7A Rucphen North Brabant 4715 AA",
    "addr:housenumber":"7a",
    "addr:postcode":"4715 aa",
    "addr:street":"Gastelsewg",
    "iso:country":"NL",
    "sg:address":"Gastelsewg 7A",
    "sg:city":"Rucphen",
    "sg:orig_category":"Verenigingen En Stichtingen",
    "sg:phone":"+31 165 342 758",
    "sg:postcode":"4715 AA",
    "sg:province":"North Brabant",
    "wof:name":"Zon & Leven",
    "wof:placetype":"venue"
},
  "geometry": {"coordinates":[4.548759,51.533665],"type":"Point"}
}