{
  "type": "Feature",
  "properties": {
    "addr:full":"Lindehof 1 Amstenrade Limburg 6436 BA",
    "addr:housenumber":"1",
    "addr:postcode":"6436 ba",
    "addr:street":"Lindehof",
    "iso:country":"NL",
    "sg:address":"Lindehof 1",
    "sg:city":"Amstenrade",
    "sg:orig_category":"Artiesten/Gezelschappen",
    "sg:phone":"+31 46 442 1847",
    "sg:postcode":"6436 BA",
    "sg:province":"Limburg",
    "wof:name":"Joe Hames Soultones",
    "wof:placetype":"venue"
},
  "geometry": {"coordinates":[5.923462,50.939232],"type":"Point"}
}