{
  "type": "Feature",
  "properties": {
    "iso:country":"NL",
    "sg:address":"Nieuwstr 36",
    "sg:city":"Leiden",
    "sg:orig_category":"Organisatiebureaus",
    "sg:phone":"+31 71 566 1661",
    "sg:postcode":"2312 KC",
    "sg:province":"Zuid-Holland",
    "wof:name":"Live House, The",
    "wof:placetype":"venue"
},
  "geometry": {"coordinates":[4.4948449135,52.1571998596],"type":"Point"}
}