{
  "type": "Feature",
  "properties": {
    "iso:country":"NL",
    "sg:address":"Tjalk 1508",
    "sg:city":"Lelystad",
    "sg:orig_category":"Zonweringen",
    "sg:phone":"+31 320 218 191",
    "sg:postcode":"8232 LK",
    "sg:province":"Flevoland",
    "wof:name":"Ewijk, Van",
    "wof:placetype":"venue"
},
  "geometry": {"coordinates":[5.471694,52.501183],"type":"Point"}
}