{
  "type": "Feature",
  "properties": {
    "addr:full":"S Heer Boeyenstr 1-3 Dordrecht South Holland 3311 BN",
    "addr:housenumber":"1-3",
    "addr:postcode":"3311 bn",
    "addr:street":"S;Boeyenstr",
    "iso:country":"NL",
    "sg:address":"S Heer Boeyenstr 1-3",
    "sg:city":"Dordrecht",
    "sg:orig_category":"Postzegels",
    "sg:phone":"+31 78 613 6438",
    "sg:postcode":"3311 BN",
    "sg:province":"South Holland",
    "wof:name":"Dordtse Kil",
    "wof:placetype":"venue"
},
  "geometry": {"coordinates":[4.667921,51.816452],"type":"Point"}
}