{
  "type": "Feature",
  "properties": {
    "addr:full":"Bernadottestraat 165 Hoofddorp North Holland 2131 SV",
    "addr:housenumber":"165",
    "addr:postcode":"2131 sv",
    "addr:street":"Bernadottestraat",
    "iso:country":"NL",
    "sg:address":"Bernadottestraat 165",
    "sg:city":"Hoofddorp",
    "sg:orig_category":"Bloemen And Planten",
    "sg:phone":"+31 23 561 2100",
    "sg:postcode":"2131 SV",
    "sg:province":"North Holland",
    "wof:name":"Bloemsierkunst Paxiflora",
    "wof:placetype":"venue"
},
  "geometry": {"coordinates":[4.677026,52.303448],"type":"Point"}
}