{
  "type": "Feature",
  "properties": {
    "addr:full":"Spuistr 245 Amsterdam Noord-Holland 1012 VP",
    "addr:housenumber":"245",
    "addr:postcode":"1012 vp",
    "iso:country":"NL",
    "sg:address":"Spuistr 245",
    "sg:city":"Amsterdam",
    "sg:orig_category":"Bedrijfsopleidingen",
    "sg:phone":"+31 20 638 2163",
    "sg:postcode":"1012 VP",
    "sg:province":"Noord-Holland",
    "wof:name":"Phoenix",
    "wof:placetype":"venue"
},
  "geometry": {"coordinates":[4.889394,52.370823],"type":"Point"}
}