{
  "type": "Feature",
  "properties": {
    "addr:full":"Langewijk 132 Dedemsvaart NL.08 7701 AJ",
    "addr:housenumber":"132;nl.08",
    "addr:postcode":"7701 aj",
    "addr:street":"Langewijk",
    "iso:country":"NL",
    "sg:address":"Langewijk 132",
    "sg:city":"Dedemsvaart",
    "sg:orig_category":"Visspeciaalzaken",
    "sg:phone":"+31 523 613 210",
    "sg:postcode":"7701 AJ",
    "sg:province":"NL.08",
    "wof:name":"H Kosse",
    "wof:placetype":"venue"
},
  "geometry": {"coordinates":[6.453911,52.605015],"type":"Point"}
}