{
  "type": "Feature",
  "properties": {
    "iso:country":"NL",
    "sg:address":"Binnenwg 15",
    "sg:city":"Buren Fr",
    "sg:orig_category":"Verenigingsgebouwen",
    "sg:phone":"+31 519 543 127",
    "sg:postcode":"9164 JA",
    "sg:province":"Provincie Friesland",
    "wof:name":"Dorpshuis 'T Wantij",
    "wof:placetype":"venue"
},
  "geometry": {"coordinates":[5.79798,53.447689],"type":"Point"}
}