{
  "type": "Feature",
  "properties": {
    "addr:full":"Zonnebaan 45A Utrecht Utrecht 3542 EB",
    "addr:housenumber":"45a",
    "addr:postcode":"3542 eb",
    "addr:street":"Zonnebaan",
    "iso:country":"NL",
    "sg:address":"Zonnebaan 45A",
    "sg:city":"Utrecht",
    "sg:orig_category":"Onroerende Goederen",
    "sg:phone":"+31 30 248 2268",
    "sg:postcode":"3542 EB",
    "sg:province":"Utrecht",
    "sg:website":"http://www.webtower.nl",
    "wof:name":"Webtower Bv",
    "wof:placetype":"venue"
},
  "geometry": {"coordinates":[5.03843,52.118439],"type":"Point"}
}