{
  "type": "Feature",
  "properties": {
    "addr:full":"Violenstr 49 Groningen Groningen 9712 RG",
    "addr:housenumber":"49",
    "addr:postcode":"9712 rg",
    "addr:street":"Violenstr",
    "iso:country":"NL",
    "sg:address":"Violenstr 49",
    "sg:city":"Groningen",
    "sg:orig_category":"Onderhoudswerken",
    "sg:phone":"+31 6 51870901",
    "sg:postcode":"9712 RG",
    "sg:province":"Groningen",
    "wof:name":"D & B Groningen",
    "wof:placetype":"venue"
},
  "geometry": {"coordinates":[6.559481,53.224155],"type":"Point"}
}