{
  "type": "Feature",
  "properties": {
    "iso:country":"NL",
    "sg:address":"Middenwg 2",
    "sg:city":"Hoogerheide",
    "sg:classifiers":[
        {
            "category":"Retail",
            "subcategory":"Auto Repair",
            "type":"Services"
        }
    ],
    "sg:phone":"+31 164 613 000",
    "sg:postcode":"4631 ST",
    "sg:province":"Noord-Brabant",
    "sg:tags":[
        "garage"
    ],
    "wof:name":"Visman",
    "wof:placetype":"venue"
},
  "geometry": {"coordinates":[4.347444,51.427563],"type":"Point"}
}