{
  "type": "Feature",
  "properties": {
    "addr:full":"Grasweg 63 Amsterdam Noord-Holland 1031 HX",
    "addr:housenumber":"63",
    "addr:postcode":"1031 hx",
    "addr:street":"Grasweg",
    "iso:country":"NL",
    "sg:address":"Grasweg 63",
    "sg:city":"Amsterdam",
    "sg:orig_category":"Reclamebureaus",
    "sg:phone":"+31 20 494 2030",
    "sg:postcode":"1031 HX",
    "sg:province":"Noord-Holland",
    "wof:name":"Vaz Dias Advertising Bv",
    "wof:placetype":"venue"
},
  "geometry": {"coordinates":[4.898258,52.39296],"type":"Point"}
}