{
  "type": "Feature",
  "properties": {
    "addr:full":"De Genestetln 1 Roosendaal Noord-Brabant 4707 KW",
    "addr:housenumber":"1",
    "addr:postcode":"4707 kw",
    "iso:country":"NL",
    "sg:address":"De Genestetln 1",
    "sg:city":"Roosendaal",
    "sg:orig_category":"Verpakkingsbedrijven",
    "sg:phone":"+31 165 558 073",
    "sg:postcode":"4707 KW",
    "sg:province":"Noord-Brabant",
    "wof:name":"Waropack Vof",
    "wof:placetype":"venue"
},
  "geometry": {"coordinates":[4.462019,51.515091],"type":"Point"}
}