{
  "type": "Feature",
  "properties": {
    "addr:full":"Neerhem 2 Valkenburg Lb Limburg 6301 CH",
    "addr:housenumber":"2",
    "addr:postcode":"lb;6301",
    "addr:street":"Neerhem",
    "iso:country":"NL",
    "sg:address":"Neerhem 2",
    "sg:city":"Valkenburg Lb",
    "sg:classifiers":[
        {
            "category":"Travel",
            "subcategory":"Hotels & Motels",
            "type":"Entertainment"
        }
    ],
    "sg:phone":"+31 43 601 2992",
    "sg:postcode":"6301 CH",
    "sg:province":"Limburg",
    "wof:name":"De La Ruine",
    "wof:placetype":"venue"
},
  "geometry": {"coordinates":[-93.129936,36.705662],"type":"Point"}
}