{
  "type": "Feature",
  "properties": {
    "iso:country":"NL",
    "sg:address":"Willem Weysingel 5",
    "sg:city":"Pernis Rt",
    "sg:orig_category":"Loodgieterswerk, Verwarming And Sanitaire Installaties",
    "sg:phone":"+31 10 438 4871",
    "sg:postcode":"3195 BT",
    "sg:province":"Zuid-Holland",
    "wof:name":"A. Koller",
    "wof:placetype":"venue"
},
  "geometry": {"coordinates":[4.385773,51.887516],"type":"Point"}
}