{
  "type": "Feature",
  "properties": {
    "addr:full":"Gaasterland 32 Zoetermeer South Holland 2716 BN",
    "addr:housenumber":"32",
    "addr:postcode":"2716 bn",
    "addr:street":"Gaasterland",
    "iso:country":"NL",
    "sg:address":"Gaasterland 32",
    "sg:city":"Zoetermeer",
    "sg:orig_category":"On- Offshore",
    "sg:phone":"+31 79 320 0283",
    "sg:postcode":"2716 BN",
    "sg:province":"South Holland",
    "wof:name":"Total Maritime Supp Int Bv",
    "wof:placetype":"venue"
},
  "geometry": {"coordinates":[4.46054,52.051357],"type":"Point"}
}