{
  "type": "Feature",
  "properties": {
    "addr:full":"Kloekhorststraat 29 Assen Drenthe 9401 BB",
    "addr:housenumber":"29",
    "addr:postcode":"9401 bb",
    "addr:street":"Kloekhorststraat",
    "iso:country":"NL",
    "sg:address":"Kloekhorststraat 29",
    "sg:city":"Assen",
    "sg:orig_category":"Werving And Selectie Van Vast Personeel",
    "sg:phone":"+31 592 360 911",
    "sg:postcode":"9401 BB",
    "sg:province":"Drenthe",
    "wof:name":"Arbeidsvoorz Noord Nederland Arbeidsbureau Assen",
    "wof:placetype":"venue"
},
  "geometry": {"coordinates":[6.565489769,52.9976081848],"type":"Point"}
}