{
  "type": "Feature",
  "properties": {
    "addr:full":"Nedereindsewg 520 Nieuwegein Utrecht 3437 PS",
    "addr:housenumber":"520",
    "addr:postcode":"3437 ps",
    "iso:country":"NL",
    "sg:address":"Nedereindsewg 520",
    "sg:city":"Nieuwegein",
    "sg:orig_category":"Adviesbureaus Bedrijfsorganisatie",
    "sg:phone":"+31 30 687 1611",
    "sg:postcode":"3437 PS",
    "sg:province":"Utrecht",
    "wof:name":"Vliet Bv, Jos Van",
    "wof:placetype":"venue"
},
  "geometry": {"coordinates":[5.06283,52.041302],"type":"Point"}
}