{
  "type": "Feature",
  "properties": {
    "addr:full":"Kinkerstraat 241 Amsterdam North Holland 1053 EP",
    "addr:housenumber":"241",
    "addr:postcode":"1053 ep",
    "addr:street":"Kinkerstraat",
    "iso:country":"NL",
    "sg:address":"Kinkerstraat 241",
    "sg:city":"Amsterdam",
    "sg:orig_category":"Discountwinkels",
    "sg:phone":"+31 20 412 0350",
    "sg:postcode":"1053 EP",
    "sg:province":"North Holland",
    "wof:name":"Zeeman Textielsupers",
    "wof:placetype":"venue"
},
  "geometry": {"coordinates":[4.8649230003,52.3652000427],"type":"Point"}
}