{
  "type": "Feature",
  "properties": {
    "addr:full":"Stephensonweg 6 Gorinchem South Holland 4207 HB",
    "addr:housenumber":"6",
    "addr:postcode":"4207 hb",
    "addr:street":"Stephensonweg",
    "iso:country":"NL",
    "sg:address":"Stephensonweg 6",
    "sg:city":"Gorinchem",
    "sg:orig_category":"Werving And Selectie Van Tijdelijk Personeel And Uitzendkantoren",
    "sg:phone":"+31 183 697 333",
    "sg:postcode":"4207 HB",
    "sg:province":"South Holland",
    "wof:name":"Pro-At Bv.",
    "wof:placetype":"venue"
},
  "geometry": {"coordinates":[5.001180172,51.8422813416],"type":"Point"}
}