{
  "type": "Feature",
  "properties": {
    "addr:full":"Eerste Hambaken 29 'S Hertogenbosch Noord-Brabant 5231 RA",
    "addr:housenumber":"29",
    "addr:postcode":"5231 ra",
    "addr:street":"Eerste Hambaken;' S",
    "iso:country":"NL",
    "sg:address":"Eerste Hambaken 29",
    "sg:city":"'S Hertogenbosch",
    "sg:orig_category":"Drukkerijen And Copyshops",
    "sg:phone":"+31 73 642 8616",
    "sg:postcode":"5231 RA",
    "sg:province":"Noord-Brabant",
    "wof:name":"Susan Gloudemans Drukwerkservice",
    "wof:placetype":"venue"
},
  "geometry": {"coordinates":[5.308792,51.713093],"type":"Point"}
}