{
  "type": "Feature",
  "properties": {
    "iso:country":"NL",
    "sg:address":"Herengracht 386",
    "sg:city":"1016",
    "sg:classifiers":[
        {
            "category":"Banks & Credit Unions",
            "subcategory":"Bank",
            "type":"Services"
        }
    ],
    "sg:phone":"+31 20 520 7333",
    "sg:postcode":"AMST ER",
    "sg:province":"Noord-Holland",
    "wof:name":"Dg Bank",
    "wof:placetype":"venue"
},
  "geometry": {"coordinates":[4.886144,52.36792],"type":"Point"}
}