{
  "type": "Feature",
  "properties": {
    "addr:full":"Herengracht 386 1016 Noord-Holland AMST ER",
    "addr:housenumber":"386",
    "addr:postcode":"1016",
    "addr:street":"Herengracht",
    "iso:country":"NL",
    "sg:address":"Herengracht 386",
    "sg:city":"1016",
    "sg:classifiers":[
        {
            "category":"Banks & Credit Unions",
            "subcategory":"Bank",
            "type":"Services"
        }
    ],
    "sg:phone":"+31 20 520 7333",
    "sg:postcode":"AMST ER",
    "sg:province":"Noord-Holland",
    "wof:name":"Dg Bank",
    "wof:placetype":"venue"
},
  "geometry": {"coordinates":[4.886144,52.36792],"type":"Point"}
}