{
  "type": "Feature",
  "properties": {
    "addr:full":"Parallelweg 8 Geldrop Noord-Brabant 5664 AC",
    "addr:housenumber":"8",
    "addr:postcode":"5664 ac",
    "addr:street":"Parallelweg",
    "iso:country":"NL",
    "sg:address":"Parallelweg 8",
    "sg:city":"Geldrop",
    "sg:classifiers":[
        {
            "category":"Education",
            "subcategory":"Preschool",
            "type":"Public Place"
        }
    ],
    "sg:phone":"+31 40 286 2464",
    "sg:postcode":"5664 AC",
    "sg:province":"Noord-Brabant",
    "sg:tags":[
        "kleuteronderwijs",
        "basis-"
    ],
    "wof:name":"Burg Van Der Putschool Sbo",
    "wof:placetype":"venue"
},
  "geometry": {"coordinates":[5.553249,51.418667],"type":"Point"}
}