{
  "type": "Feature",
  "properties": {
    "addr:full":"De Factory 8D Zwaag Noord-Holland 1689 AL",
    "addr:housenumber":"8d",
    "addr:postcode":"1689 al",
    "addr:street":"De Factory",
    "iso:country":"NL",
    "sg:address":"De Factory 8D",
    "sg:city":"Zwaag",
    "sg:classifiers":[
        {
            "category":"Retail",
            "subcategory":"Auto Repair",
            "type":"Services"
        }
    ],
    "sg:phone":"+31 229 277 070",
    "sg:postcode":"1689 AL",
    "sg:province":"Noord-Holland",
    "sg:tags":[
        "garage"
    ],
    "wof:name":"Keverpits West-Friesland",
    "wof:placetype":"venue"
},
  "geometry": {"coordinates":[5.064757,52.667145],"type":"Point"}
}