{
  "type": "Feature",
  "properties": {
    "addr:full":"Industriewg 1 Harmelen Utrecht 3481 MD",
    "addr:housenumber":"1",
    "addr:postcode":"3481",
    "addr:street":"Industriewg",
    "iso:country":"NL",
    "sg:address":"Industriewg 1",
    "sg:city":"Harmelen",
    "sg:orig_category":"Touringcars",
    "sg:phone":"+31 348 441 800",
    "sg:postcode":"3481 MD",
    "sg:province":"Utrecht",
    "sg:website":"http://www.theomiddelweerd.nl",
    "wof:name":"Middelweerd, Theo",
    "wof:placetype":"venue"
},
  "geometry": {"coordinates":[4.945509,52.099789],"type":"Point"}
}