{
  "type": "Feature",
  "properties": {
    "iso:country":"NL",
    "sg:address":"Vrijenbanselaan 2",
    "sg:city":"Delft",
    "sg:orig_category":"Kappers",
    "sg:phone":"+31 15 214 1330",
    "sg:postcode":"2612 CM",
    "sg:province":"Zuid-Holland",
    "wof:name":"Maatwerk Haarmode",
    "wof:placetype":"venue"
},
  "geometry": {"coordinates":[4.352605,52.022247],"type":"Point"}
}