{
  "type": "Feature",
  "properties": {
    "addr:full":"Kransakker 12 Berkel Enschot North Brabant 5056 LZ",
    "addr:housenumber":"12",
    "addr:postcode":"5056 lz",
    "addr:street":"Kransakker;Enschot",
    "iso:country":"NL",
    "sg:address":"Kransakker 12",
    "sg:city":"Berkel Enschot",
    "sg:classifiers":[
        {
            "category":"Education",
            "subcategory":"School",
            "type":"Public Place"
        }
    ],
    "sg:phone":"+31 13 581 1292",
    "sg:postcode":"5056 LZ",
    "sg:province":"North Brabant",
    "sg:tags":[
        "studiebegeleiding",
        "en",
        "school-"
    ],
    "sg:website":"http://www.rtpraktijk.nl",
    "wof:name":"Maan",
    "wof:placetype":"venue"
},
  "geometry": {"coordinates":[5.148807,51.592915],"type":"Point"}
}