{
  "type": "Feature",
  "properties": {
    "addr:full":"De Ruyterstraat 49 Rijssen Overijssel 7461 GH",
    "addr:housenumber":"49",
    "addr:postcode":"7461 gh",
    "addr:street":"De Ruyterstraat",
    "iso:country":"NL",
    "sg:address":"De Ruyterstraat 49",
    "sg:city":"Rijssen",
    "sg:orig_category":"Loodgieterswerk, Verwarming And Sanitaire Installaties",
    "sg:phone":"+31 548 519 303",
    "sg:postcode":"7461 GH",
    "sg:province":"Overijssel",
    "wof:name":"A.H. Labobar",
    "wof:placetype":"venue"
},
  "geometry": {"coordinates":[6.533518,52.303726],"type":"Point"}
}