{
  "type": "Feature",
  "properties": {
    "addr:full":"Litauensestr 2 Zutphen Gelderland 7202 CN",
    "addr:housenumber":"2",
    "addr:postcode":"7202 cn",
    "addr:street":"Litauensestr;Gelderland",
    "iso:country":"NL",
    "sg:address":"Litauensestr 2",
    "sg:city":"Zutphen",
    "sg:orig_category":"Horecabenodigdheden",
    "sg:phone":"+31 575 516 461",
    "sg:postcode":"7202 CN",
    "sg:province":"Gelderland",
    "wof:name":"Combigro Leuvenink Bv",
    "wof:placetype":"venue"
},
  "geometry": {"coordinates":[6.197428,52.156239],"type":"Point"}
}