{
  "type": "Feature",
  "properties": {
    "addr:full":"Fokko Kortlanglaan 192 Ermelo Gelderland 3851 SJ",
    "addr:housenumber":"192",
    "addr:postcode":"3851",
    "addr:street":"Fokko Kortlanglaan;Gelderland",
    "iso:country":"NL",
    "sg:address":"Fokko Kortlanglaan 192",
    "sg:city":"Ermelo",
    "sg:orig_category":"Mobiele Service Aan Motorvoertuigen",
    "sg:phone":"+31 341 419 528",
    "sg:postcode":"3851 SJ",
    "sg:province":"Gelderland",
    "wof:name":"Bergingsbedrijf Delta",
    "wof:placetype":"venue"
},
  "geometry": {"coordinates":[5.617623,52.324265],"type":"Point"}
}