{
  "type": "Feature",
  "properties": {
    "addr:full":"Koekoeklaan 5 Grubbenvorst Limburg 5971 CP",
    "addr:housenumber":"5",
    "addr:postcode":"5971 cp",
    "addr:street":"Koekoeklaan",
    "iso:country":"NL",
    "sg:address":"Koekoeklaan 5",
    "sg:city":"Grubbenvorst",
    "sg:orig_category":"Vertaal- And Tolkenbureaus",
    "sg:phone":"+31 77 366 3073",
    "sg:postcode":"5971 CP",
    "sg:province":"Limburg",
    "wof:name":"Drs. W.H.J.M. Kurris",
    "wof:placetype":"venue"
},
  "geometry": {"coordinates":[6.146198,51.416203],"type":"Point"}
}