{
  "type": "Feature",
  "properties": {
    "addr:full":"J Bertsstr 6 Diemen Distrito Federal 1111 AR",
    "addr:housenumber":"6",
    "addr:postcode":"1111",
    "iso:country":"NL",
    "sg:address":"J Bertsstr 6",
    "sg:city":"Diemen",
    "sg:orig_category":"Open Haarden",
    "sg:phone":"+31 6 55877636",
    "sg:postcode":"1111 AR",
    "sg:province":"Distrito Federal",
    "wof:name":"Colijn, B",
    "wof:placetype":"venue"
},
  "geometry": {"coordinates":[-58.4011917114,-34.5973815918],"type":"Point"}
}