{
  "type": "Feature",
  "properties": {
    "addr:full":"Postbus 77 Honselersdyk Zuid-Holland 2675 ZH",
    "addr:housenumber":"77",
    "addr:postcode":"2675 zh",
    "addr:street":"Postbus",
    "iso:country":"NL",
    "sg:address":"Postbus 77",
    "sg:city":"Honselersdyk",
    "sg:orig_category":"Journalisten Freelance",
    "sg:phone":"+31 174 626 586",
    "sg:postcode":"2675 ZH",
    "sg:province":"Zuid-Holland",
    "wof:name":"Westland Pers",
    "wof:placetype":"venue"
},
  "geometry": {"coordinates":[4.22951,52.008755],"type":"Point"}
}