{
  "type": "Feature",
  "properties": {
    "addr:full":"Prins Hendrikstraat 32 Den Haag Zuid-Holland 2518 HT",
    "addr:housenumber":"32",
    "addr:postcode":"2518 ht",
    "addr:street":"Prins Hendrikstraat",
    "iso:country":"NL",
    "sg:address":"Prins Hendrikstraat 32",
    "sg:city":"Den Haag",
    "sg:classifiers":[
        {
            "category":"Fast Food",
            "type":"Food & Drink"
        }
    ],
    "sg:phone":"+31 70 360 6772",
    "sg:postcode":"2518 HT",
    "sg:province":"Zuid-Holland",
    "sg:tags":[
        "afhaal",
        "restaurant"
    ],
    "wof:name":"Snackbar Snoopy",
    "wof:placetype":"venue"
},
  "geometry": {"coordinates":[4.294056,52.0821],"type":"Point"}
}