{
  "type": "Feature",
  "properties": {
    "addr:full":"Hommelstraat 78 Arnhem Gelderland 6828 AL",
    "addr:housenumber":"78",
    "addr:postcode":"6828 al",
    "addr:street":"Hommelstraat",
    "iso:country":"NL",
    "sg:address":"Hommelstraat 78",
    "sg:city":"Arnhem",
    "sg:orig_category":"Fruit And Groenten Gh",
    "sg:phone":"+31 26 445 7310",
    "sg:postcode":"6828 AL",
    "sg:province":"Gelderland",
    "wof:name":"Sara",
    "wof:placetype":"venue"
},
  "geometry": {"coordinates":[5.914357,51.985752],"type":"Point"}
}