{
  "type": "Feature",
  "properties": {
    "addr:full":"Havendk 24A Tilburg Noord-Brabant 5017 AM",
    "addr:housenumber":"24a",
    "addr:postcode":"5017",
    "addr:street":"Havendk",
    "iso:country":"NL",
    "sg:address":"Havendk 24A",
    "sg:city":"Tilburg",
    "sg:orig_category":"Fotografie Reclame En Mode",
    "sg:phone":"+31 13 581 2369",
    "sg:postcode":"5017 AM",
    "sg:province":"Noord-Brabant",
    "wof:name":"Swinkels & Van 'T Hoff",
    "wof:placetype":"venue"
},
  "geometry": {"coordinates":[5.102762,51.55328],"type":"Point"}
}