{
  "type": "Feature",
  "properties": {
    "addr:full":"Dkn Maesln 10 Prinsenbeek Noord-Brabant 4841 VS",
    "addr:housenumber":"10",
    "addr:postcode":"4841 vs",
    "iso:country":"NL",
    "sg:address":"Dkn Maesln 10",
    "sg:city":"Prinsenbeek",
    "sg:orig_category":"Onderhoudswerken",
    "sg:phone":"+31 76 543 9915",
    "sg:postcode":"4841 VS",
    "sg:province":"Noord-Brabant",
    "wof:name":"Raaff, Klus- En Onderhoudsbedr De",
    "wof:placetype":"venue"
},
  "geometry": {"coordinates":[4.714282,51.598518],"type":"Point"}
}