{
  "type": "Feature",
  "properties": {
    "addr:full":"Apolloln 109 Amsterdam North Holland 1077 AN",
    "addr:housenumber":"109",
    "addr:postcode":"1077 an",
    "iso:country":"NL",
    "sg:address":"Apolloln 109",
    "sg:city":"Amsterdam",
    "sg:orig_category":"Verzekeringen - Verzekeringskantoren",
    "sg:phone":"+31 20 679 1344",
    "sg:postcode":"1077 AN",
    "sg:province":"North Holland",
    "wof:name":"Brusse",
    "wof:placetype":"venue"
},
  "geometry": {"coordinates":[4.87585,52.345482],"type":"Point"}
}