{
  "type": "Feature",
  "properties": {
    "iso:country":"NL",
    "sg:address":"Calvariestraat 35C",
    "sg:city":"Maastricht",
    "sg:orig_category":"Film-, Tv- And Videoproductie",
    "sg:phone":"+31 43 325 2517",
    "sg:postcode":"6211 NH",
    "sg:province":"Limburg",
    "wof:name":"Lvw Multi-Media Service",
    "wof:placetype":"venue"
},
  "geometry": {"coordinates":[5.67952,50.847031],"type":"Point"}
}