{
  "type": "Feature",
  "properties": {
    "addr:full":"Purmerpln 21 Amsterdam Noord-Holland 1023 BC",
    "addr:housenumber":"21",
    "addr:postcode":"1023 bc",
    "addr:street":"Purmerpln",
    "iso:country":"NL",
    "sg:address":"Purmerpln 21",
    "sg:city":"Amsterdam",
    "sg:orig_category":"Handenarbeid",
    "sg:phone":"+31 20 632 0738",
    "sg:postcode":"1023 BC",
    "sg:province":"Noord-Holland",
    "wof:name":"Wissewasjes",
    "wof:placetype":"venue"
},
  "geometry": {"coordinates":[4.944653,52.391323],"type":"Point"}
}