{
  "type": "Feature",
  "properties": {
    "addr:full":"Anna Paulownastraat 103 Den Haag Zuid-Holland 2518 BC",
    "addr:housenumber":"103",
    "addr:postcode":"2518 bc",
    "addr:street":"Anna Paulownastraat",
    "iso:country":"NL",
    "sg:address":"Anna Paulownastraat 103",
    "sg:city":"Den Haag",
    "sg:orig_category":"Advocaten And Juridische Adviseurs",
    "sg:phone":"+31 70 427 3215",
    "sg:postcode":"2518 BC",
    "sg:province":"Zuid-Holland",
    "wof:name":"Mesdag Advocaten",
    "wof:placetype":"venue"
},
  "geometry": {"coordinates":[4.29852,52.086029],"type":"Point"}
}