{
  "type": "Feature",
  "properties": {
    "iso:country":"NL",
    "sg:address":"Industriestraat 187",
    "sg:city":"Hengelo Ov",
    "sg:orig_category":"Bloemen And Planten",
    "sg:phone":"+31 74 291 1145",
    "sg:postcode":"7553 CN",
    "sg:province":"Overijssel",
    "wof:name":"La Bella Fleur",
    "wof:placetype":"venue"
},
  "geometry": {"coordinates":[6.779284,52.253517],"type":"Point"}
}