{
  "type": "Feature",
  "properties": {
    "addr:full":"Wilhelmina Van Haeftendr 7 Vianen Zh South Holland 4133 JB",
    "addr:housenumber":"7",
    "addr:postcode":"zh;4133 jb",
    "addr:street":"Wilhelmina Van Haeftendr",
    "iso:country":"NL",
    "sg:address":"Wilhelmina Van Haeftendr 7",
    "sg:city":"Vianen Zh",
    "sg:orig_category":"Film-, Tv- And Videoproductie",
    "sg:phone":"+31 347 322 611",
    "sg:postcode":"4133 JB",
    "sg:province":"South Holland",
    "wof:name":"E.J. Support",
    "wof:placetype":"venue"
},
  "geometry": {"coordinates":[5.071338,51.986649],"type":"Point"}
}