{
  "type": "Feature",
  "properties": {
    "addr:full":"Statenweg 90A Rotterdam Zuid-Holland 3039 JJ",
    "addr:housenumber":"90a",
    "addr:postcode":"3039 jj",
    "addr:street":"Statenweg",
    "iso:country":"NL",
    "sg:address":"Statenweg 90A",
    "sg:city":"Rotterdam",
    "sg:orig_category":"Artsen And Specialisten",
    "sg:phone":"+31 10 466 4920",
    "sg:postcode":"3039 JJ",
    "sg:province":"Zuid-Holland",
    "wof:name":"A.J.W. Beek En L.C.C. De Lange",
    "wof:placetype":"venue"
},
  "geometry": {"coordinates":[4.458272,51.931339],"type":"Point"}
}