{
  "type": "Feature",
  "properties": {
    "addr:full":"Swaardvenstraat 75 Tilburg North Brabant 5048 AV",
    "addr:housenumber":"75",
    "addr:postcode":"5048 av",
    "addr:street":"Swaardvenstraat",
    "iso:country":"NL",
    "sg:address":"Swaardvenstraat 75",
    "sg:city":"Tilburg",
    "sg:orig_category":"Boekhouders",
    "sg:phone":"+31 13 543 6597",
    "sg:postcode":"5048 AV",
    "sg:province":"North Brabant",
    "wof:name":"Stichting Gasthuis",
    "wof:placetype":"venue"
},
  "geometry": {"coordinates":[5.043468,51.584457],"type":"Point"}
}