{
  "type": "Feature",
  "properties": {
    "addr:full":"Lorentzkd 344 Haarlem Noord-Holland 2014 CJ",
    "addr:housenumber":"344",
    "addr:postcode":"2014 cj",
    "iso:country":"NL",
    "sg:address":"Lorentzkd 344",
    "sg:city":"Haarlem",
    "sg:orig_category":"Marketingbureaus",
    "sg:phone":"+31 23 524 5336",
    "sg:postcode":"2014 CJ",
    "sg:province":"Noord-Holland",
    "wof:name":"All Round",
    "wof:placetype":"venue"
},
  "geometry": {"coordinates":[4.612563,52.377117],"type":"Point"}
}