{
  "type": "Feature",
  "properties": {
    "iso:country":"NL",
    "sg:address":"Straatwg 30A",
    "sg:city":"Maarssen",
    "sg:orig_category":"Verzekeringen - Verzekeringskantoren",
    "sg:phone":"+31 346 569 696",
    "sg:postcode":"3604 BB",
    "sg:province":"Utrecht",
    "sg:website":"http://www.lange-jacht.nl",
    "wof:name":"Lange Jacht Bv",
    "wof:placetype":"venue"
},
  "geometry": {"coordinates":[5.047911,52.131584],"type":"Point"}
}