{
  "type": "Feature",
  "properties": {
    "addr:full":"Langs De Werf 1 Amstelveen Noord-Holland 1185 XT",
    "addr:housenumber":"1",
    "addr:postcode":"1185 xt",
    "addr:street":"Langs De Werf",
    "iso:country":"NL",
    "sg:address":"Langs De Werf 1",
    "sg:city":"Amstelveen",
    "sg:orig_category":"Huishoudapparatuur, Televisies And Radio'S",
    "sg:phone":"+31 20 645 4554",
    "sg:postcode":"1185 XT",
    "sg:province":"Noord-Holland",
    "wof:name":"Buram Electro Bv",
    "wof:placetype":"venue"
},
  "geometry": {"coordinates":[4.837978,52.280678],"type":"Point"}
}