{
  "type": "Feature",
  "properties": {
    "addr:full":"De Barones 43 Breda Noord-Brabant 4811 XZ",
    "addr:housenumber":"43",
    "addr:postcode":"4811 xz",
    "addr:street":"De Barones",
    "iso:country":"NL",
    "sg:address":"De Barones 43",
    "sg:city":"Breda",
    "sg:orig_category":"Juweliers",
    "sg:phone":"+31 76 513 8787",
    "sg:postcode":"4811 XZ",
    "sg:province":"Noord-Brabant",
    "wof:name":"Edelsmid Paul Van Den Hout",
    "wof:placetype":"venue"
},
  "geometry": {"coordinates":[4.775233,51.58717],"type":"Point"}
}