{
  "type": "Feature",
  "properties": {
    "addr:full":"Sluiswegje 10 Jubbega Friesland 8411 XM",
    "addr:housenumber":"10",
    "addr:postcode":"8411 xm",
    "addr:street":"Sluiswegje",
    "iso:country":"NL",
    "sg:address":"Sluiswegje 10",
    "sg:city":"Jubbega",
    "sg:orig_category":"Koeriersdiensten",
    "sg:phone":"+31 516 462 973",
    "sg:postcode":"8411 XM",
    "sg:province":"Friesland",
    "wof:name":"Rapieko Koeriersdiensten",
    "wof:placetype":"venue"
},
  "geometry": {"coordinates":[6.12317,53.00523],"type":"Point"}
}