{
  "type": "Feature",
  "properties": {
    "addr:full":"Westermarkt 127 Tilburg Noord-Brabant 5042 SZ",
    "addr:housenumber":"127",
    "addr:postcode":"5042 sz",
    "addr:street":"Westermarkt",
    "iso:country":"NL",
    "sg:address":"Westermarkt 127",
    "sg:city":"Tilburg",
    "sg:orig_category":"Behangselpapier En Wandbekleding",
    "sg:phone":"+31 13 463 5924",
    "sg:postcode":"5042 SZ",
    "sg:province":"Noord-Brabant",
    "wof:name":"Jongh, A De",
    "wof:placetype":"venue"
},
  "geometry": {"coordinates":[5.052832,51.569214],"type":"Point"}
}