{
  "type": "Feature",
  "properties": {
    "addr:full":"Wielkamp 5 Zaltbommel Gelderland 5301 DB",
    "addr:housenumber":"5",
    "addr:postcode":"5301 db",
    "addr:street":"Wielkamp;Gelderland",
    "iso:country":"NL",
    "sg:address":"Wielkamp 5",
    "sg:city":"Zaltbommel",
    "sg:orig_category":"Advocaten En Advocatenkantoren",
    "sg:phone":"+31 418 540 400",
    "sg:postcode":"5301 DB",
    "sg:province":"Gelderland",
    "wof:name":"Maatje",
    "wof:placetype":"venue"
},
  "geometry": {"coordinates":[5.242408,51.800262],"type":"Point"}
}