{
  "type": "Feature",
  "properties": {
    "iso:country":"NL",
    "sg:address":"Westduinweg 12",
    "sg:city":"'S Gravenhage",
    "sg:orig_category":"Kappers",
    "sg:phone":"+31 70 354 9927",
    "sg:postcode":"2583 EG",
    "sg:province":"Zuid-Holland",
    "wof:name":"Quartel Coiffures",
    "wof:placetype":"venue"
},
  "geometry": {"coordinates":[4.265562,52.092239],"type":"Point"}
}