{
  "type": "Feature",
  "properties": {
    "addr:full":"Wilhelminastr 10 Velp Gld Gelderland 6881 LJ",
    "addr:housenumber":"10;lj",
    "addr:postcode":"6881",
    "addr:street":"Wilhelminastr;Gld Gelderland",
    "iso:country":"NL",
    "sg:address":"Wilhelminastr 10",
    "sg:city":"Velp Gld",
    "sg:classifiers":[
        {
            "category":"Personal",
            "subcategory":"Nail Salon",
            "type":"Services"
        }
    ],
    "sg:phone":"+31 26 364 3688",
    "sg:postcode":"6881 LJ",
    "sg:province":"Gelderland",
    "sg:tags":[
        "pedicure"
    ],
    "wof:name":"Voet-Fit",
    "wof:placetype":"venue"
},
  "geometry": {"coordinates":[5.96883,51.99646],"type":"Point"}
}