{
  "type": "Feature",
  "properties": {
    "iso:country":"NL",
    "sg:address":"R V Lennepstr 16",
    "sg:city":"Heerlen",
    "sg:orig_category":"Fotopersbureaus",
    "sg:phone":"+31 45 571 8702",
    "sg:postcode":"6419 BL",
    "sg:province":"Limburg",
    "wof:name":"Bq Bas Quaedvlieg, Foto",
    "wof:placetype":"venue"
},
  "geometry": {"coordinates":[5.9661,50.875561],"type":"Point"}
}