{
  "type": "Feature",
  "properties": {
    "addr:full":"Geeststr 4 Heerhugowaard Noord-Holland 1705 DZ",
    "addr:housenumber":"4",
    "addr:postcode":"1705 dz",
    "addr:street":"Geeststr",
    "iso:country":"NL",
    "sg:address":"Geeststr 4",
    "sg:city":"Heerhugowaard",
    "sg:orig_category":"Administratie- En Boekhoudkantoren",
    "sg:phone":"+31 72 574 2949",
    "sg:postcode":"1705 DZ",
    "sg:province":"Noord-Holland",
    "wof:name":"Moraal, P R",
    "wof:placetype":"venue"
},
  "geometry": {"coordinates":[4.83099,52.648197],"type":"Point"}
}