{
  "type": "Feature",
  "properties": {
    "addr:full":"Heicop 29 Kockengen Utrecht 3628 AD",
    "addr:housenumber":"29",
    "addr:postcode":"3628 ad",
    "addr:street":"Heicop",
    "iso:country":"NL",
    "sg:address":"Heicop 29",
    "sg:city":"Kockengen",
    "sg:orig_category":"Heiwerken En Funderingstechniek",
    "sg:phone":"+31 346 241 289",
    "sg:postcode":"3628 AD",
    "sg:province":"Utrecht",
    "wof:name":"Eijk Bv, J R Van",
    "wof:placetype":"venue"
},
  "geometry": {"coordinates":[4.946538,52.149555],"type":"Point"}
}