{
  "type": "Feature",
  "properties": {
    "iso:country":"NL",
    "sg:address":"Callistoln 2",
    "sg:city":"Dordrecht",
    "sg:orig_category":"Woningbouw- Verenigingen En -Stichtingen",
    "sg:phone":"+31 78 654 8888",
    "sg:postcode":"3318 JA",
    "sg:province":"Zuid-Holland",
    "sg:website":"http://www.progrez.nl",
    "wof:name":"Progrez",
    "wof:placetype":"venue"
},
  "geometry": {"coordinates":[4.671710968,51.7858428955],"type":"Point"}
}