{
  "type": "Feature",
  "properties": {
    "iso:country":"NL",
    "sg:address":"Westeinde 10",
    "sg:city":"Oosthuizen",
    "sg:orig_category":"Poppen En Poppenhuismaterialen",
    "sg:phone":"+31 299 402 044",
    "sg:postcode":"1474 HA",
    "sg:province":"Noord-Holland",
    "sg:website":"http://www.stolp.nl",
    "wof:name":"Stolp Poppenhuizen, De",
    "wof:placetype":"venue"
},
  "geometry": {"coordinates":[4.99894,52.574059],"type":"Point"}
}