{
  "type": "Feature",
  "properties": {
    "addr:full":"Stationswg 13A Castricum Noord-Holland 1901 AA",
    "addr:housenumber":"13a",
    "addr:postcode":"1901 aa",
    "addr:street":"Stationswg",
    "iso:country":"NL",
    "sg:address":"Stationswg 13A",
    "sg:city":"Castricum",
    "sg:orig_category":"Touringcars",
    "sg:phone":"+31 900 9999990",
    "sg:postcode":"1901 AA",
    "sg:province":"Noord-Holland",
    "sg:website":"http://www.touringcarboekingscentrale.nl",
    "wof:name":"Touringcar Boekingscentrale",
    "wof:placetype":"venue"
},
  "geometry": {"coordinates":[4.65927,52.545811],"type":"Point"}
}