{
  "type": "Feature",
  "properties": {
    "addr:full":"Zuiderzeestraatweg West 124 Doornspijk Gelderland 8085 AJ",
    "addr:housenumber":"124",
    "addr:postcode":"8085 aj",
    "addr:street":"Zuiderzeestraatweg West;Gelderland",
    "iso:country":"NL",
    "sg:address":"Zuiderzeestraatweg West 124",
    "sg:city":"Doornspijk",
    "sg:orig_category":"Huishoudapparatuur, Televisies And Radio'S",
    "sg:phone":"+31 525 661 355",
    "sg:postcode":"8085 AJ",
    "sg:province":"Gelderland",
    "wof:name":"E. Van Zeeburg Hifi, T.V., Video Vof",
    "wof:placetype":"venue"
},
  "geometry": {"coordinates":[5.807605,52.407887],"type":"Point"}
}