{
  "type": "Feature",
  "properties": {
    "addr:full":"Plevierenln 21 Vinkeveen Utrecht 3645 GN",
    "addr:housenumber":"21",
    "addr:postcode":"3645 gn",
    "addr:street":"Plevierenln",
    "iso:country":"NL",
    "sg:address":"Plevierenln 21",
    "sg:city":"Vinkeveen",
    "sg:orig_category":"Postkantoren",
    "sg:phone":"+31 297 261 340",
    "sg:postcode":"3645 GN",
    "sg:province":"Utrecht",
    "sg:website":"http://www.postkantoor.nl",
    "wof:name":"Postkantoor",
    "wof:placetype":"venue"
},
  "geometry": {"coordinates":[4.925997,52.214397],"type":"Point"}
}