{
  "type": "Feature",
  "properties": {
    "addr:full":"V Woustr 46 Amsterdam Noord-Holland 1073 LM",
    "addr:housenumber":"46",
    "addr:postcode":"1073 lm",
    "iso:country":"NL",
    "sg:address":"V Woustr 46",
    "sg:city":"Amsterdam",
    "sg:orig_category":"Schoenen",
    "sg:phone":"+31 20 470 9795",
    "sg:postcode":"1073 LM",
    "sg:province":"Noord-Holland",
    "wof:name":"Betsy Palmer",
    "wof:placetype":"venue"
},
  "geometry": {"coordinates":[4.8984,52.353001],"type":"Point"}
}