{
  "type": "Feature",
  "properties": {
    "addr:full":"Satellietbaan 17 Hillegom North Holland 2181 MG",
    "addr:housenumber":"17",
    "addr:postcode":"2181 mg",
    "addr:street":"Satellietbaan",
    "iso:country":"NL",
    "sg:address":"Satellietbaan 17",
    "sg:city":"Hillegom",
    "sg:orig_category":"Verpakkingsmachines",
    "sg:phone":"+31 252 531 030",
    "sg:postcode":"2181 MG",
    "sg:province":"North Holland",
    "sg:website":"HTTP://www.mundipak.nl",
    "wof:name":"Mundipak Bv",
    "wof:placetype":"venue"
},
  "geometry": {"coordinates":[4.585558,52.301949],"type":"Point"}
}