{
  "type": "Feature",
  "properties": {
    "iso:country":"NL",
    "sg:address":"Teunisbloemplein 60",
    "sg:city":"'S Gravenhage",
    "sg:orig_category":"Fotografische And Optische Artikelen Gh",
    "sg:phone":"+31 70 368 8111",
    "sg:postcode":"2555 AB",
    "sg:province":"Zuid-Holland",
    "wof:name":"Fa Rehako",
    "wof:placetype":"venue"
},
  "geometry": {"coordinates":[4.227212,52.062675],"type":"Point"}
}