{
  "type": "Feature",
  "properties": {
    "iso:country":"NL",
    "sg:address":"Componistenlaan 141",
    "sg:city":"Gouda",
    "sg:orig_category":"Boekhouders",
    "sg:phone":"+31 182 526 633",
    "sg:postcode":"2807 HG",
    "sg:province":"Zuid-Holland",
    "wof:name":"C.N.M. Van Deursen",
    "wof:placetype":"venue"
},
  "geometry": {"coordinates":[4.749407,52.012444],"type":"Point"}
}