{
  "type": "Feature",
  "properties": {
    "addr:full":"Tarweakker 23 Arnemuiden Zeeland 4341 MD",
    "addr:housenumber":"23",
    "addr:postcode":"4341",
    "addr:street":"Tarweakker",
    "iso:country":"NL",
    "sg:address":"Tarweakker 23",
    "sg:city":"Arnemuiden",
    "sg:orig_category":"Begrafenisverzorging",
    "sg:phone":"+31 118 602 500",
    "sg:postcode":"4341 MD",
    "sg:province":"Zeeland",
    "wof:name":"Vader, Begrafenisverzorging C W",
    "wof:placetype":"venue"
},
  "geometry": {"coordinates":[3.671006,51.504162],"type":"Point"}
}