{
  "type": "Feature",
  "properties": {
    "addr:full":"Grote Gracht 18 Maastricht Limburg 6211 SW",
    "addr:housenumber":"18",
    "addr:postcode":"6211 sw",
    "addr:street":"Grote Gracht",
    "iso:country":"NL",
    "sg:address":"Grote Gracht 18",
    "sg:city":"Maastricht",
    "sg:orig_category":"Gespecialiseerde Voeding",
    "sg:phone":"+31 43 325 1355",
    "sg:postcode":"6211 SW",
    "sg:province":"Limburg",
    "wof:name":"G. Thiessen Wijnkoopers Sedert 1740 Bv",
    "wof:placetype":"venue"
},
  "geometry": {"coordinates":[5.68898,50.851044],"type":"Point"}
}