{
  "type": "Feature",
  "properties": {
    "addr:full":"Apollowg 10-12 Leeuwarden Provincie Friesland 8938 AT",
    "addr:housenumber":"10-12",
    "addr:postcode":"8938",
    "addr:street":"Provincie Friesland",
    "iso:country":"NL",
    "sg:address":"Apollowg 10-12",
    "sg:city":"Leeuwarden",
    "sg:orig_category":"Verf En Lak - Fabrieken En Groothandel",
    "sg:phone":"+31 58 288 7700",
    "sg:postcode":"8938 AT",
    "sg:province":"Provincie Friesland",
    "wof:name":"Zijlstra & Co Bv",
    "wof:placetype":"venue"
},
  "geometry": {"coordinates":[5.851193,53.199131],"type":"Point"}
}