{
  "type": "Feature",
  "properties": {
    "addr:full":"Amstelveensewg 579 Amsterdam Noord-Holland 1081 JC",
    "addr:housenumber":"579",
    "addr:postcode":"1081 jc",
    "iso:country":"NL",
    "sg:address":"Amstelveensewg 579",
    "sg:city":"Amsterdam",
    "sg:orig_category":"Beeldende Kunstenaars",
    "sg:phone":"+31 20 642 3382",
    "sg:postcode":"1081 JC",
    "sg:province":"Noord-Holland",
    "wof:name":"Tollenaar-Molhuysen, F",
    "wof:placetype":"venue"
},
  "geometry": {"coordinates":[4.857379,52.334179],"type":"Point"}
}