{
  "type": "Feature",
  "properties": {
    "iso:country":"NL",
    "sg:address":"Ring 36",
    "sg:city":"Simonshaven",
    "sg:orig_category":"Agenturen En Commissiehandel",
    "sg:phone":"+31 181 451 301",
    "sg:postcode":"3212 LS",
    "sg:province":"Zuid-Holland",
    "wof:name":"Versim Bv",
    "wof:placetype":"venue"
},
  "geometry": {"coordinates":[4.290851,51.822407],"type":"Point"}
}