{
  "type": "Feature",
  "properties": {
    "addr:full":"Haarl Houttuinen 17 Amsterdam Noord-Holland 1013 GL",
    "addr:housenumber":"17",
    "addr:postcode":"1013 gl",
    "addr:street":"Houttuinen",
    "iso:country":"NL",
    "sg:address":"Haarl Houttuinen 17",
    "sg:city":"Amsterdam",
    "sg:orig_category":"Autorijscholen",
    "sg:phone":"+31 20 638 2052",
    "sg:postcode":"1013 GL",
    "sg:province":"Noord-Holland",
    "wof:name":"Slotermeer",
    "wof:placetype":"venue"
},
  "geometry": {"coordinates":[4.892221,52.380554],"type":"Point"}
}