{
  "type": "Feature",
  "properties": {
    "addr:full":"Eikenln 5A Bennekom Gelderland 6721 DM",
    "addr:housenumber":"5a",
    "addr:postcode":"6721 dm",
    "addr:street":"Eikenln;Gelderland",
    "iso:country":"NL",
    "sg:address":"Eikenln 5A",
    "sg:city":"Bennekom",
    "sg:orig_category":"Bewakingsdiensten",
    "sg:phone":"+31 318 413 160",
    "sg:postcode":"6721 DM",
    "sg:province":"Gelderland",
    "sg:website":"http://www.dssbeveiliging.nl",
    "wof:name":"Dogs Bv",
    "wof:placetype":"venue"
},
  "geometry": {"coordinates":[5.680824,52.003418],"type":"Point"}
}