{
  "type": "Feature",
  "properties": {
    "iso:country":"NL",
    "sg:address":"Parlevinker 23",
    "sg:city":"Nieuw Vennep",
    "sg:classifiers":[
        {
            "category":"Personal",
            "subcategory":"Nail Salon",
            "type":"Services"
        }
    ],
    "sg:phone":"+31 252 689 569",
    "sg:postcode":"2152 LC",
    "sg:province":"North Holland",
    "sg:tags":[
        "pedicure"
    ],
    "wof:name":"Olofsen, A",
    "wof:placetype":"venue"
},
  "geometry": {"coordinates":[4.641349,52.270809],"type":"Point"}
}