{
  "type": "Feature",
  "properties": {
    "addr:full":"Langenakker 40 Mierlo North Brabant 5731 JT",
    "addr:housenumber":"40",
    "addr:postcode":"5731 jt",
    "addr:street":"Langenakker",
    "iso:country":"NL",
    "sg:address":"Langenakker 40",
    "sg:city":"Mierlo",
    "sg:orig_category":"Schilderwerk",
    "sg:phone":"+31 492 661 999",
    "sg:postcode":"5731 JT",
    "sg:province":"North Brabant",
    "wof:name":"J.L.M. Veldwijk-Poppelier",
    "wof:placetype":"venue"
},
  "geometry": {"coordinates":[5.613422,51.440681],"type":"Point"}
}