{
  "type": "Feature",
  "properties": {
    "iso:country":"NL",
    "sg:address":"De Vriesplein 8",
    "sg:city":"Purmerend",
    "sg:orig_category":"Zuivelproducten",
    "sg:phone":"+31 299 425 486",
    "sg:postcode":"1442 CG",
    "sg:province":"Noord-Holland",
    "wof:name":"Vomar Kaasboer/Poelier",
    "wof:placetype":"venue"
},
  "geometry": {"coordinates":[4.960112,52.513016],"type":"Point"}
}