{
  "type": "Feature",
  "properties": {
    "iso:country":"NL",
    "sg:address":"Dorpsweg 109",
    "sg:city":"Schellinkhout",
    "sg:classifiers":[
        {
            "category":"Education",
            "subcategory":"Preschool",
            "type":"Public Place"
        }
    ],
    "sg:phone":"+31 229 501 460",
    "sg:postcode":"1697 KG",
    "sg:province":"Noord-Holland",
    "sg:tags":[
        "kleuteronderwijs",
        "basis-"
    ],
    "wof:name":"Jan Luijkenschool",
    "wof:placetype":"venue"
},
  "geometry": {"coordinates":[5.122597,52.633965],"type":"Point"}
}