{
  "type": "Feature",
  "properties": {
    "iso:country":"NL",
    "sg:address":"Rijksstraatweg 7",
    "sg:city":"Dordrecht",
    "sg:orig_category":"Levensmiddelen - Fabrieken En Groothandel",
    "sg:phone":"+31 78 653 4244",
    "sg:postcode":"3316 EE",
    "sg:province":"South Holland",
    "wof:name":"Wholesale Bv, Paul",
    "wof:placetype":"venue"
},
  "geometry": {"coordinates":[4.644695,51.783684],"type":"Point"}
}