{
  "type": "Feature",
  "properties": {
    "addr:full":"Dodingawei 28 Engwierum Provincie Friesland 9132 EA",
    "addr:housenumber":"28",
    "addr:postcode":"9132 ea",
    "addr:street":"Dodingawei;Provincie Friesland",
    "iso:country":"NL",
    "sg:address":"Dodingawei 28",
    "sg:city":"Engwierum",
    "sg:orig_category":"Autokeuringen",
    "sg:phone":"+31 511 408 391",
    "sg:postcode":"9132 EA",
    "sg:province":"Provincie Friesland",
    "wof:name":"Wiersma T.",
    "wof:placetype":"venue"
},
  "geometry": {"coordinates":[6.136076,53.321198],"type":"Point"}
}