{
  "type": "Feature",
  "properties": {
    "addr:full":"Mariastr 13 Aarle Rixtel Noord-Brabant 5735 EW",
    "addr:housenumber":"13",
    "addr:postcode":"5735 ew",
    "addr:street":"Mariastr",
    "iso:country":"NL",
    "sg:address":"Mariastr 13",
    "sg:city":"Aarle Rixtel",
    "sg:orig_category":"Administratie- En Boekhoudkantoren",
    "sg:phone":"+31 492 386 033",
    "sg:postcode":"5735 EW",
    "sg:province":"Noord-Brabant",
    "wof:name":"Kops",
    "wof:placetype":"venue"
},
  "geometry": {"coordinates":[5.642565,51.50803],"type":"Point"}
}