{
  "type": "Feature",
  "properties": {
    "iso:country":"NL",
    "sg:address":"Baanwg 9",
    "sg:city":"Rotterdam",
    "sg:orig_category":"Verzekeringen - Verzekeringskantoren",
    "sg:phone":"+31 10 415 5466",
    "sg:postcode":"3042 AB",
    "sg:province":"Zuid-Holland",
    "wof:name":"Krastman & Zn, G J",
    "wof:placetype":"venue"
},
  "geometry": {"coordinates":[4.427515,51.93494],"type":"Point"}
}