{
  "type": "Feature",
  "properties": {
    "iso:country":"NL",
    "sg:address":"Kerkln 11",
    "sg:city":"Amstelhoek",
    "sg:orig_category":"Bestratingen",
    "sg:phone":"+31 297 563 081",
    "sg:postcode":"1427 AA",
    "sg:province":"Utrecht",
    "wof:name":"Kempen Bv, J A G Van",
    "wof:placetype":"venue"
},
  "geometry": {"coordinates":[4.835238,52.229973],"type":"Point"}
}