{
  "type": "Feature",
  "properties": {
    "addr:full":"Leenderwg 54 Valkenswaard North Brabant 5555 CE",
    "addr:housenumber":"54",
    "addr:postcode":"5555 ce",
    "addr:street":"Leenderwg",
    "iso:country":"NL",
    "sg:address":"Leenderwg 54",
    "sg:city":"Valkenswaard",
    "sg:orig_category":"Honden- En Kattentrimsalons",
    "sg:phone":"+31 40 201 0304",
    "sg:postcode":"5555 CE",
    "sg:province":"North Brabant",
    "wof:name":"Kiki",
    "wof:placetype":"venue"
},
  "geometry": {"coordinates":[5.465737,51.351906],"type":"Point"}
}