{
  "type": "Feature",
  "properties": {
    "addr:full":"Heemraadssngl 257A Rotterdam Zuid-Holland 3023 CE",
    "addr:housenumber":"257a",
    "addr:postcode":"3023 ce",
    "iso:country":"NL",
    "sg:address":"Heemraadssngl 257A",
    "sg:city":"Rotterdam",
    "sg:orig_category":"Modeontwerpen",
    "sg:phone":"+31 10 476 8830",
    "sg:postcode":"3023 CE",
    "sg:province":"Zuid-Holland",
    "wof:name":"Weijer, Studio De",
    "wof:placetype":"venue"
},
  "geometry": {"coordinates":[4.454266,51.914104],"type":"Point"}
}