{
  "type": "Feature",
  "properties": {
    "addr:full":"Anemoonstr 56 Hoogeveen Provincie Drenthe 7906 PG",
    "addr:housenumber":"56",
    "addr:postcode":"7906",
    "addr:street":"Anemoonstr;Provincie;Pg",
    "iso:country":"NL",
    "sg:address":"Anemoonstr 56",
    "sg:city":"Hoogeveen",
    "sg:orig_category":"Tegelwerken",
    "sg:phone":"+31 528 269 228",
    "sg:postcode":"7906 PG",
    "sg:province":"Provincie Drenthe",
    "wof:name":"Hoogeveen Tegelzetbedrijf",
    "wof:placetype":"venue"
},
  "geometry": {"coordinates":[6.489276,52.715813],"type":"Point"}
}