{
  "type": "Feature",
  "properties": {
    "addr:full":"V Randwyckln 4-4A Amersfoort Utrecht 3814 AL",
    "addr:housenumber":"4-4a",
    "addr:postcode":"3814 al",
    "iso:country":"NL",
    "sg:address":"V Randwyckln 4-4A",
    "sg:city":"Amersfoort",
    "sg:classifiers":[
        {
            "category":"Food & Beverages",
            "subcategory":"Bakery",
            "type":"Retail Goods"
        }
    ],
    "sg:phone":"+31 33 475 4094",
    "sg:postcode":"3814 AL",
    "sg:province":"Utrecht",
    "sg:tags":[
        "pizza"
    ],
    "wof:name":"New York Pizza",
    "wof:placetype":"venue"
},
  "geometry": {"coordinates":[5.386085,52.152325],"type":"Point"}
}