{
  "type": "Feature",
  "properties": {
    "addr:full":"Hooiland 117 Wierden NL.08 7641 HZ",
    "addr:housenumber":"117;nl.08",
    "addr:postcode":"7641 hz",
    "addr:street":"Hooiland",
    "iso:country":"NL",
    "sg:address":"Hooiland 117",
    "sg:city":"Wierden",
    "sg:orig_category":"Fitnesscentra",
    "sg:phone":"+31 546 574 644",
    "sg:postcode":"7641 HZ",
    "sg:province":"NL.08",
    "wof:name":"T'Ai-Chi & Wu-Shu",
    "wof:placetype":"venue"
},
  "geometry": {"coordinates":[6.597175,52.367744],"type":"Point"}
}