{
  "type": "Feature",
  "properties": {
    "iso:country":"NL",
    "sg:address":"Peperstr 38",
    "sg:city":"Purmerend",
    "sg:orig_category":"Herenkleding",
    "sg:phone":"+31 299 423 971",
    "sg:postcode":"1441 BJ",
    "sg:province":"Noord-Holland",
    "wof:name":"Deitmers",
    "wof:placetype":"venue"
},
  "geometry": {"coordinates":[4.946044,52.510185],"type":"Point"}
}