{
  "type": "Feature",
  "properties": {
    "addr:full":"Nw Nonnendaalsewg 11 Nymegen Gelderland 6542 PA",
    "addr:housenumber":"11",
    "addr:postcode":"6542",
    "addr:street":"Nymegen Gelderland",
    "iso:country":"NL",
    "sg:address":"Nw Nonnendaalsewg 11",
    "sg:city":"Nymegen",
    "sg:orig_category":"Homeopathie",
    "sg:phone":"+31 24 377 2394",
    "sg:postcode":"6542 PA",
    "sg:province":"Gelderland",
    "wof:name":"Albers Paul",
    "wof:placetype":"venue"
},
  "geometry": {"coordinates":[-77.604507,40.99464],"type":"Point"}
}