{
  "type": "Feature",
  "properties": {
    "addr:full":"Arkendonk 27 Oosterhout Nb North Brabant 4907 XT",
    "addr:housenumber":"27;nb",
    "addr:postcode":"4907 xt",
    "addr:street":"Arkendonk",
    "iso:country":"NL",
    "sg:address":"Arkendonk 27",
    "sg:city":"Oosterhout Nb",
    "sg:orig_category":"Bloemen And Planten",
    "sg:phone":"+31 162 458 997",
    "sg:postcode":"4907 XT",
    "sg:province":"North Brabant",
    "wof:name":"Bloemsierkunst 'T Blommeke",
    "wof:placetype":"venue"
},
  "geometry": {"coordinates":[4.863355,51.65778],"type":"Point"}
}