{
  "type": "Feature",
  "properties": {
    "addr:full":"Lievensbergstraat 1 Almere NL. 1333 ZR",
    "addr:housenumber":"1;1333",
    "addr:street":"Lievensbergstraat;Nl.",
    "iso:country":"NL",
    "sg:address":"Lievensbergstraat 1",
    "sg:city":"Almere",
    "sg:orig_category":"Grafologen, Handlezers And Helderzienden",
    "sg:phone":"+31 36 537 0917",
    "sg:postcode":"1333 ZR",
    "sg:province":"NL.",
    "wof:name":"Algemeen Schriftkundig Bureau",
    "wof:placetype":"venue"
},
  "geometry": {"coordinates":[5.265028,52.386307],"type":"Point"}
}