{
  "type": "Feature",
  "properties": {
    "addr:full":"Dorpsstraat 63 Lexmond Zuid-Holland 4128 BW",
    "addr:housenumber":"63",
    "addr:postcode":"4128 bw",
    "addr:street":"Dorpsstraat",
    "iso:country":"NL",
    "sg:address":"Dorpsstraat 63",
    "sg:city":"Lexmond",
    "sg:classifiers":[
        {
            "category":"Food & Beverages",
            "subcategory":"Fruits & Vegetables",
            "type":"Retail Goods"
        }
    ],
    "sg:phone":"+31 347 320 185",
    "sg:postcode":"4128 BW",
    "sg:province":"Zuid-Holland",
    "sg:tags":[
        "groenten"
    ],
    "wof:name":"Alewijn Versluis",
    "wof:placetype":"venue"
},
  "geometry": {"coordinates":[5.036376,51.963268],"type":"Point"}
}