{
  "type": "Feature",
  "properties": {
    "addr:full":"Voorwg 161 Zoetermeer Zuid-Holland 2716 NJ",
    "addr:housenumber":"161",
    "addr:postcode":"2716 nj",
    "iso:country":"NL",
    "sg:address":"Voorwg 161",
    "sg:city":"Zoetermeer",
    "sg:orig_category":"Watersportartikelen",
    "sg:phone":"+31 79 351 7018",
    "sg:postcode":"2716 NJ",
    "sg:province":"Zuid-Holland",
    "wof:name":"Zelst Watersport Bv, Van",
    "wof:placetype":"venue"
},
  "geometry": {"coordinates":[4.4447598457,52.0688285828],"type":"Point"}
}