{
  "type": "Feature",
  "properties": {
    "iso:country":"NL",
    "sg:address":"Eerste Van Swindenstraat 83",
    "sg:city":"Amsterdam",
    "sg:orig_category":"Baby- And Kinderkleding",
    "sg:phone":"+31 20 668 3809",
    "sg:postcode":"1093 EX",
    "sg:province":"North Holland",
    "wof:name":"Rossy Fashion",
    "wof:placetype":"venue"
},
  "geometry": {"coordinates":[4.924916,52.362263],"type":"Point"}
}