{
  "type": "Feature",
  "properties": {
    "addr:full":"Kastanjeln 4 Assen Drenthe 9401 LR",
    "addr:housenumber":"4",
    "addr:postcode":"9401 lr",
    "addr:street":"Kastanjeln",
    "iso:country":"NL",
    "sg:address":"Kastanjeln 4",
    "sg:city":"Assen",
    "sg:orig_category":"Makelaars En Adviseurs Onroerende Goederen",
    "sg:phone":"+31 592 302 735",
    "sg:postcode":"9401 LR",
    "sg:province":"Drenthe",
    "wof:name":"White House, The",
    "wof:placetype":"venue"
},
  "geometry": {"coordinates":[6.564167,52.987152],"type":"Point"}
}