{
  "type": "Feature",
  "properties": {
    "addr:full":"Ruitenweg 39 Froombosch Groningen 9619 PL",
    "addr:housenumber":"39",
    "addr:postcode":"9619 pl",
    "addr:street":"Ruitenweg",
    "iso:country":"NL",
    "sg:address":"Ruitenweg 39",
    "sg:city":"Froombosch",
    "sg:orig_category":"Overheidsdiensten",
    "sg:phone":"+31 598 397 066",
    "sg:postcode":"9619 PL",
    "sg:province":"Groningen",
    "wof:name":"Ruitenvelder",
    "wof:placetype":"venue"
},
  "geometry": {"coordinates":[6.7762231827,53.1954956055],"type":"Point"}
}