{
  "type": "Feature",
  "properties": {
    "iso:country":"NL",
    "sg:address":"Vissershavenweg 62",
    "sg:city":"Scheveningen",
    "sg:orig_category":"Diverse Grafische Activiteiten",
    "sg:phone":"+31 70 351 4482",
    "sg:postcode":"2583 DL",
    "sg:province":"Zuid-Holland",
    "wof:name":"Zizo Creatie En Litho",
    "wof:placetype":"venue"
},
  "geometry": {"coordinates":[4.268131,52.101955],"type":"Point"}
}