{
  "type": "Feature",
  "properties": {
    "iso:country":"NL",
    "sg:address":"Landstr 47",
    "sg:city":"Vlaardingen",
    "sg:orig_category":"Beeldende Kunstenaars",
    "sg:phone":"+31 10 434 7691",
    "sg:postcode":"3131 CE",
    "sg:province":"Zuid-Holland",
    "wof:name":"Esch, J A Van",
    "wof:placetype":"venue"
},
  "geometry": {"coordinates":[4.344042,51.906975],"type":"Point"}
}