{
  "type": "Feature",
  "properties": {
    "addr:full":"Koopmansstr 9 Ryswyk Zh Zuid-Holland 2288 BC",
    "addr:housenumber":"9",
    "addr:postcode":"2288 bc",
    "addr:street":"Koopmansstr",
    "iso:country":"NL",
    "sg:address":"Koopmansstr 9",
    "sg:city":"Ryswyk Zh",
    "sg:orig_category":"Kamers Van Koophandel",
    "sg:phone":"+31 70 303 0965",
    "sg:postcode":"2288 BC",
    "sg:province":"Zuid-Holland",
    "wof:name":"Euro Caribbean",
    "wof:placetype":"venue"
},
  "geometry": {"coordinates":[4.3243598938,52.0372505188],"type":"Point"}
}