{
  "type": "Feature",
  "properties": {
    "addr:full":"Postbus 1074 Sliedrecht Noord-Holland 3360 BB",
    "addr:housenumber":"1074",
    "addr:postcode":"3360 bb",
    "addr:street":"Postbus",
    "iso:country":"NL",
    "sg:address":"Postbus 1074",
    "sg:city":"Sliedrecht",
    "sg:orig_category":"Verfspuitinstallaties",
    "sg:phone":"+31 184 613 772",
    "sg:postcode":"3360 BB",
    "sg:province":"Noord-Holland",
    "wof:name":"Raadgeving, Van",
    "wof:placetype":"venue"
},
  "geometry": {"coordinates":[4.772605,51.823555],"type":"Point"}
}