{
  "type": "Feature",
  "properties": {
    "addr:full":"Zwettestr 17 Leeuwarden Friesland 8912 AH",
    "addr:housenumber":"17",
    "addr:postcode":"8912 ah",
    "addr:street":"Zwettestr",
    "iso:country":"NL",
    "sg:address":"Zwettestr 17",
    "sg:city":"Leeuwarden",
    "sg:orig_category":"Koeriersdiensten",
    "sg:phone":"+31 58 216 8622",
    "sg:postcode":"8912 AH",
    "sg:province":"Friesland",
    "wof:name":"Wds",
    "wof:placetype":"venue"
},
  "geometry": {"coordinates":[5.769671,53.194897],"type":"Point"}
}