{
  "type": "Feature",
  "properties": {
    "addr:full":"Gjaltema 24 Grou Idaho 9001 NB",
    "addr:housenumber":"24",
    "addr:postcode":"9001 nb",
    "addr:street":"Gjaltema",
    "iso:country":"NL",
    "sg:address":"Gjaltema 24",
    "sg:city":"Grou",
    "sg:orig_category":"Verhuur Audiovisuele Apparatuur",
    "sg:phone":"+31 566 624 194",
    "sg:postcode":"9001 NB",
    "sg:province":"Idaho",
    "wof:name":"Multisound",
    "wof:placetype":"venue"
},
  "geometry": {"coordinates":[-113.611923,43.688873],"type":"Point"}
}