{
  "type": "Feature",
  "properties": {
    "addr:full":"Hermelynhof 27 Zeewolde Flevoland 3892 VE",
    "addr:housenumber":"27",
    "addr:postcode":"3892",
    "addr:street":"Hermelynhof;Flevoland;Ve",
    "iso:country":"NL",
    "sg:address":"Hermelynhof 27",
    "sg:city":"Zeewolde",
    "sg:orig_category":"Peuterspeelzalen",
    "sg:phone":"+31 36 522 4160",
    "sg:postcode":"3892 VE",
    "sg:province":"Flevoland",
    "wof:name":"Zeewolde, Sticht",
    "wof:placetype":"venue"
},
  "geometry": {"coordinates":[5.538097,52.321709],"type":"Point"}
}