{
  "type": "Feature",
  "properties": {
    "iso:country":"NL",
    "sg:address":"Dorpsstraat 127",
    "sg:city":"Lunteren",
    "sg:orig_category":"Visspeciaalzaken",
    "sg:phone":"+31 318 484 523",
    "sg:postcode":"6741 AE",
    "sg:province":"Gelderland",
    "wof:name":"De Lunterse Beek",
    "wof:placetype":"venue"
},
  "geometry": {"coordinates":[5.619508,52.085835],"type":"Point"}
}