{
  "type": "Feature",
  "properties": {
    "addr:full":"D Aumeriestr 9 S Gravenhage Zuid-Holland 2586 XL",
    "addr:housenumber":"9;gravenhage",
    "addr:postcode":"2586 xl",
    "addr:street":"S",
    "iso:country":"NL",
    "sg:address":"D Aumeriestr 9",
    "sg:city":"S Gravenhage",
    "sg:orig_category":"Sportverenigingen En Ontspannings- Verenigingen",
    "sg:phone":"+31 70 350 2503",
    "sg:postcode":"2586 XL",
    "sg:province":"Zuid-Holland",
    "wof:name":"Sml Badmintonver",
    "wof:placetype":"venue"
},
  "geometry": {"coordinates":[4.277215,52.10672],"type":"Point"}
}