{
  "type": "Feature",
  "properties": {
    "addr:full":"Vlambloem 75 Rotterdam Zuid-Holland 3068 JG",
    "addr:housenumber":"75",
    "addr:postcode":"3068 jg",
    "addr:street":"Vlambloem",
    "iso:country":"NL",
    "sg:address":"Vlambloem 75",
    "sg:city":"Rotterdam",
    "sg:classifiers":[
        {
            "category":"Food & Beverages",
            "subcategory":"Bakery",
            "type":"Retail Goods"
        }
    ],
    "sg:phone":"+31 800 0222282",
    "sg:postcode":"3068 JG",
    "sg:province":"Zuid-Holland",
    "sg:tags":[
        "pizza"
    ],
    "wof:name":"Al Capone'S",
    "wof:placetype":"venue"
},
  "geometry": {"coordinates":[4.530037,51.9548],"type":"Point"}
}