{
  "type": "Feature",
  "properties": {
    "addr:full":"Hamsestr 61 Opheusden Gelderland 4043 LG",
    "addr:housenumber":"61",
    "addr:postcode":"4043 lg",
    "addr:street":"Hamsestr;Gelderland",
    "iso:country":"NL",
    "sg:address":"Hamsestr 61",
    "sg:city":"Opheusden",
    "sg:orig_category":"Tuinontwerp En -Advies",
    "sg:phone":"+31 488 443 018",
    "sg:postcode":"4043 LG",
    "sg:province":"Gelderland",
    "wof:name":"Prunella",
    "wof:placetype":"venue"
},
  "geometry": {"coordinates":[5.620222,51.931942],"type":"Point"}
}