{
  "type": "Feature",
  "properties": {
    "addr:full":"Herenstr 10 Naaldwyk Zuid-Holland 2671 JA",
    "addr:housenumber":"10",
    "addr:postcode":"2671 ja",
    "addr:street":"Herenstr",
    "iso:country":"NL",
    "sg:address":"Herenstr 10",
    "sg:city":"Naaldwyk",
    "sg:orig_category":"Bloemen En Planten",
    "sg:phone":"+31 174 620 232",
    "sg:postcode":"2671 JA",
    "sg:province":"Zuid-Holland",
    "wof:name":"Alleblas",
    "wof:placetype":"venue"
},
  "geometry": {"coordinates":[4.206742,51.993355],"type":"Point"}
}