{
  "type": "Feature",
  "properties": {
    "addr:full":"Gestelsestr 88 Eindhoven Noord-Brabant 5615 LH",
    "addr:housenumber":"88",
    "addr:postcode":"5615 lh",
    "addr:street":"Gestelsestr",
    "iso:country":"NL",
    "sg:address":"Gestelsestr 88",
    "sg:city":"Eindhoven",
    "sg:orig_category":"Kappers",
    "sg:phone":"+31 40 252 0112",
    "sg:postcode":"5615 LH",
    "sg:province":"Noord-Brabant",
    "wof:name":"Jacqueline Coiffure",
    "wof:placetype":"venue"
},
  "geometry": {"coordinates":[5.4713702202,51.4301300049],"type":"Point"}
}