{
  "type": "Feature",
  "properties": {
    "addr:full":"Populierenlaan 51 Uitgeest Noord-Holland 1911 BK",
    "addr:housenumber":"51",
    "addr:postcode":"1911 bk",
    "addr:street":"Populierenlaan",
    "iso:country":"NL",
    "sg:address":"Populierenlaan 51",
    "sg:city":"Uitgeest",
    "sg:orig_category":"Metaalwerken",
    "sg:phone":"+31 251 320 553",
    "sg:postcode":"1911 BK",
    "sg:province":"Noord-Holland",
    "wof:name":"Suntrend Holding Bv",
    "wof:placetype":"venue"
},
  "geometry": {"coordinates":[4.71861,52.529644],"type":"Point"}
}