{
  "type": "Feature",
  "properties": {
    "addr:full":"Albert Cuypstraat 55 Amsterdam North Holland 1072 CM",
    "addr:housenumber":"55",
    "addr:postcode":"1072 cm",
    "addr:street":"Albert Cuypstraat",
    "iso:country":"NL",
    "sg:address":"Albert Cuypstraat 55",
    "sg:city":"Amsterdam",
    "sg:orig_category":"Wasserettes And Stomerijen",
    "sg:phone":"+31 20 662 3256",
    "sg:postcode":"1072 CM",
    "sg:province":"North Holland",
    "wof:name":"Chemische Wassery A Westmaas",
    "wof:placetype":"venue"
},
  "geometry": {"coordinates":[4.8890337944,52.3548431396],"type":"Point"}
}