{
  "type": "Feature",
  "properties": {
    "addr:full":"Sumatrastr 199 Amsterdam North Holland 1094 NA",
    "addr:housenumber":"199",
    "addr:postcode":"1094 na",
    "iso:country":"NL",
    "sg:address":"Sumatrastr 199",
    "sg:city":"Amsterdam",
    "sg:orig_category":"Koeriersdiensten",
    "sg:phone":"+31 20 774 0399",
    "sg:postcode":"1094 NA",
    "sg:province":"North Holland",
    "wof:name":"Hakan",
    "wof:placetype":"venue"
},
  "geometry": {"coordinates":[4.93968,52.359009],"type":"Point"}
}