{
  "type": "Feature",
  "properties": {
    "addr:full":"Groenhof 136 Amstelveen Noord-Holland 1186 EX",
    "addr:housenumber":"136",
    "addr:postcode":"1186 ex",
    "addr:street":"Groenhof",
    "iso:country":"NL",
    "sg:address":"Groenhof 136",
    "sg:city":"Amstelveen",
    "sg:orig_category":"Postkantoren",
    "sg:phone":"+31 20 641 6193",
    "sg:postcode":"1186 EX",
    "sg:province":"Noord-Holland",
    "sg:website":"http://www.postkantoor.nl",
    "wof:name":"Postkantoor",
    "wof:placetype":"venue"
},
  "geometry": {"coordinates":[4.869942,52.289494],"type":"Point"}
}