{
  "type": "Feature",
  "properties": {
    "addr:full":"Bontekoelaan 9 Utrecht Utrecht 3526 RA",
    "addr:housenumber":"9",
    "addr:postcode":"3526 ra",
    "addr:street":"Bontekoelaan",
    "iso:country":"NL",
    "sg:address":"Bontekoelaan 9",
    "sg:city":"Utrecht",
    "sg:classifiers":[
        {
            "category":"Education",
            "subcategory":"Preschool",
            "type":"Public Place"
        }
    ],
    "sg:phone":"+31 30 288 0857",
    "sg:postcode":"3526 RA",
    "sg:province":"Utrecht",
    "sg:tags":[
        "kleuteronderwijs",
        "basis-"
    ],
    "wof:name":"Da Costabasisschool Kanaleneiland",
    "wof:placetype":"venue"
},
  "geometry": {"coordinates":[5.094334,52.066692],"type":"Point"}
}