{
  "type": "Feature",
  "properties": {
    "addr:full":"Dorpsstr 30 Bergharen Gelderland 6617 AD",
    "addr:housenumber":"30",
    "addr:postcode":"6617 ad",
    "addr:street":"Dorpsstr;Gelderland",
    "iso:country":"NL",
    "sg:address":"Dorpsstr 30",
    "sg:city":"Bergharen",
    "sg:orig_category":"Verenigingen En Stichtingen",
    "sg:phone":"+31 487 531 611",
    "sg:postcode":"6617 AD",
    "sg:province":"Gelderland",
    "wof:name":"Buitencentr Bergharen",
    "wof:placetype":"venue"
},
  "geometry": {"coordinates":[5.664419,51.850227],"type":"Point"}
}