{
  "type": "Feature",
  "properties": {
    "addr:full":"Marswg 53 Zwolle Overijssel 8013 PE",
    "addr:housenumber":"53",
    "addr:postcode":"8013 pe",
    "addr:street":"Marswg",
    "iso:country":"NL",
    "sg:address":"Marswg 53",
    "sg:city":"Zwolle",
    "sg:orig_category":"Verf En Lak - Fabrieken En Groothandel",
    "sg:phone":"+31 38 465 7020",
    "sg:postcode":"8013 PE",
    "sg:province":"Overijssel",
    "wof:name":"Habeco Bv",
    "wof:placetype":"venue"
},
  "geometry": {"coordinates":[6.127478,52.4907],"type":"Point"}
}