{
  "type": "Feature",
  "properties": {
    "addr:full":"Lupinetuin 19 Leiden Zuid-Holland 2317 MX",
    "addr:housenumber":"19",
    "addr:postcode":"2317 mx",
    "addr:street":"Lupinetuin",
    "iso:country":"NL",
    "sg:address":"Lupinetuin 19",
    "sg:city":"Leiden",
    "sg:orig_category":"Maatschappelijk Werk",
    "sg:phone":"+31 71 522 4672",
    "sg:postcode":"2317 MX",
    "sg:province":"Zuid-Holland",
    "wof:name":"M Van Den Eijnden",
    "wof:placetype":"venue"
},
  "geometry": {"coordinates":[4.50106,52.176514],"type":"Point"}
}