{
  "type": "Feature",
  "properties": {
    "addr:full":"Mercuriusstr 105 Sassenheim Zuid-Holland 2172 CC",
    "addr:housenumber":"105",
    "addr:postcode":"sassenheim;2172 cc",
    "iso:country":"NL",
    "sg:address":"Mercuriusstr 105",
    "sg:city":"Sassenheim",
    "sg:orig_category":"Autorijscholen",
    "sg:phone":"+31 252 211 592",
    "sg:postcode":"2172 CC",
    "sg:province":"Zuid-Holland",
    "wof:name":"Sassenheimse, De 1E",
    "wof:placetype":"venue"
},
  "geometry": {"coordinates":[4.528738,52.221825],"type":"Point"}
}