{
  "type": "Feature",
  "properties": {
    "iso:country":"NL",
    "sg:address":"Gasinjetstr 2",
    "sg:city":"Purmerend",
    "sg:orig_category":"Autorijscholen",
    "sg:phone":"+31 299 431 133",
    "sg:postcode":"1442 WN",
    "sg:province":"North Holland",
    "wof:name":"Bork, Ter",
    "wof:placetype":"venue"
},
  "geometry": {"coordinates":[4.961913,52.513809],"type":"Point"}
}