{
  "type": "Feature",
  "properties": {
    "iso:country":"NL",
    "sg:address":"Bosscherwg 181",
    "sg:city":"Maastricht",
    "sg:classifiers":[
        {
            "category":"Retail",
            "subcategory":"Auto Repair",
            "type":"Services"
        }
    ],
    "sg:phone":"+31 43 325 5935",
    "sg:postcode":"6219 AA",
    "sg:province":"Limburg",
    "sg:tags":[
        "garage"
    ],
    "wof:name":"Berg, Van De",
    "wof:placetype":"venue"
},
  "geometry": {"coordinates":[5.688564,50.861839],"type":"Point"}
}