{
  "type": "Feature",
  "properties": {
    "addr:full":"Haarsterweg 27 Marum Groningen 9363 VB",
    "addr:housenumber":"27",
    "addr:postcode":"9363 vb",
    "addr:street":"Haarsterweg",
    "iso:country":"NL",
    "sg:address":"Haarsterweg 27",
    "sg:city":"Marum",
    "sg:orig_category":"Metaalbekleding And -Behandeling",
    "sg:phone":"+31 594 642 670",
    "sg:postcode":"9363 VB",
    "sg:province":"Groningen",
    "wof:name":"Fa Oosting",
    "wof:placetype":"venue"
},
  "geometry": {"coordinates":[6.22696,53.132343],"type":"Point"}
}