{
  "type": "Feature",
  "properties": {
    "addr:full":"Vergierdewg 205-209 Haarlem North Holland 2026 ZD",
    "addr:housenumber":"205-209",
    "addr:postcode":"2026 zd",
    "iso:country":"NL",
    "sg:address":"Vergierdewg 205-209",
    "sg:city":"Haarlem",
    "sg:classifiers":[
        {
            "category":"Wholesale",
            "subcategory":"Motor Vehicles",
            "type":"Manufacturing & Wholesale Goods"
        }
    ],
    "sg:phone":"+31 23 537 1263",
    "sg:postcode":"2026 ZD",
    "sg:province":"North Holland",
    "sg:tags":[
        "scooter",
        "en"
    ],
    "wof:name":"Jansen Tweewielers",
    "wof:placetype":"venue"
},
  "geometry": {"coordinates":[4.654909,52.418343],"type":"Point"}
}