{
  "type": "Feature",
  "properties": {
    "addr:full":"Balistraat 1 Zwijndrecht South Holland 3333 AB",
    "addr:housenumber":"1",
    "addr:postcode":"3333 ab",
    "addr:street":"Balistraat",
    "iso:country":"NL",
    "sg:address":"Balistraat 1",
    "sg:city":"Zwijndrecht",
    "sg:classifiers":[
        {
            "category":"Education",
            "subcategory":"Preschool",
            "type":"Public Place"
        }
    ],
    "sg:phone":"+31 78 612 8951",
    "sg:postcode":"3333 AB",
    "sg:province":"South Holland",
    "sg:tags":[
        "kleuteronderwijs",
        "basis-"
    ],
    "wof:name":"Openbare Basisschool De Dolfijn",
    "wof:placetype":"venue"
},
  "geometry": {"coordinates":[4.635253,51.811592],"type":"Point"}
}