{
  "type": "Feature",
  "properties": {
    "addr:full":"Westersngl 29 Rotterdam Zuid-Holland 3014 GR",
    "addr:housenumber":"29",
    "addr:postcode":"3014",
    "addr:street":"Westersngl",
    "iso:country":"NL",
    "sg:address":"Westersngl 29",
    "sg:city":"Rotterdam",
    "sg:orig_category":"Haarwerken",
    "sg:phone":"+31 10 436 2237",
    "sg:postcode":"3014 GR",
    "sg:province":"Zuid-Holland",
    "wof:name":"Pelatti",
    "wof:placetype":"venue"
},
  "geometry": {"coordinates":[4.478455,51.922836],"type":"Point"}
}