{
  "type": "Feature",
  "properties": {
    "addr:full":"Spectrumsingel 175 Zoetermeer South Holland 2718 JR",
    "addr:housenumber":"175",
    "addr:postcode":"2718 jr",
    "addr:street":"Spectrumsingel",
    "iso:country":"NL",
    "sg:address":"Spectrumsingel 175",
    "sg:city":"Zoetermeer",
    "sg:orig_category":"Diverse Grafische Activiteiten",
    "sg:phone":"+31 79 361 4788",
    "sg:postcode":"2718 JR",
    "sg:province":"South Holland",
    "wof:name":"Ben Kooloos Grafische Vormgeving",
    "wof:placetype":"venue"
},
  "geometry": {"coordinates":[4.491658,52.035492],"type":"Point"}
}