{
  "type": "Feature",
  "properties": {
    "addr:full":"Groenstr 139/377 Tilburg Noord-Brabant 5021 LL",
    "addr:housenumber":"139 / 377",
    "addr:postcode":"5021 ll",
    "iso:country":"NL",
    "sg:address":"Groenstr 139/377",
    "sg:city":"Tilburg",
    "sg:orig_category":"Koeriersdiensten",
    "sg:phone":"+31 13 535 1559",
    "sg:postcode":"5021 LL",
    "sg:province":"Noord-Brabant",
    "wof:name":"Allround Express",
    "wof:placetype":"venue"
},
  "geometry": {"coordinates":[5.16142,51.62265],"type":"Point"}
}