{
  "type": "Feature",
  "properties": {
    "addr:full":"Ginnekenstr 38 Breda Noord-Brabant 4811 JH",
    "addr:housenumber":"38",
    "addr:postcode":"4811 jh",
    "addr:street":"Ginnekenstr",
    "iso:country":"NL",
    "sg:address":"Ginnekenstr 38",
    "sg:city":"Breda",
    "sg:orig_category":"Warenhuizen",
    "sg:phone":"+31 76 522 5252",
    "sg:postcode":"4811 JH",
    "sg:province":"Noord-Brabant",
    "wof:name":"Hema",
    "wof:placetype":"venue"
},
  "geometry": {"coordinates":[4.7765498161,51.5850143433],"type":"Point"}
}