{
  "type": "Feature",
  "properties": {
    "addr:full":"Veelakker 33 Eindhoven North Brabant 5625 WJ",
    "addr:housenumber":"33",
    "addr:postcode":"5625 wj",
    "addr:street":"Veelakker",
    "iso:country":"NL",
    "sg:address":"Veelakker 33",
    "sg:city":"Eindhoven",
    "sg:orig_category":"Loodgieterswerk, Verwarming And Sanitaire Installaties",
    "sg:phone":"+31 40 242 1084",
    "sg:postcode":"5625 WJ",
    "sg:province":"North Brabant",
    "wof:name":"Dielissen",
    "wof:placetype":"venue"
},
  "geometry": {"coordinates":[5.482939,51.470238],"type":"Point"}
}