{
  "type": "Feature",
  "properties": {
    "addr:full":"Aalsmeerwg 30 Amsterdam Noord-Holland 1059 AK",
    "addr:housenumber":"30",
    "addr:postcode":"1059 ak",
    "addr:street":"Aalsmeerwg",
    "iso:country":"NL",
    "sg:address":"Aalsmeerwg 30",
    "sg:city":"Amsterdam",
    "sg:orig_category":"Kappers",
    "sg:phone":"+31 20 617 6176",
    "sg:postcode":"1059 AK",
    "sg:province":"Noord-Holland",
    "sg:website":"http://www.dekapper.nl",
    "wof:name":"Kapper, De",
    "wof:placetype":"venue"
},
  "geometry": {"coordinates":[4.8491940498,52.3500328064],"type":"Point"}
}