{
  "type": "Feature",
  "properties": {
    "addr:full":"Zuiderzeestraatweg 525 Wezep Gelderland 8091 CN",
    "addr:housenumber":"525",
    "addr:postcode":"8091 cn",
    "addr:street":"Zuiderzeestraatweg",
    "iso:country":"NL",
    "sg:address":"Zuiderzeestraatweg 525",
    "sg:city":"Wezep",
    "sg:orig_category":"Kappers",
    "sg:phone":"+31 38 375 9505",
    "sg:postcode":"8091 CN",
    "sg:province":"Gelderland",
    "wof:name":"R Kalf",
    "wof:placetype":"venue"
},
  "geometry": {"coordinates":[5.997447,52.464912],"type":"Point"}
}