{
  "type": "Feature",
  "properties": {
    "addr:full":"Korenbree 8 Borculo Gelderland 7271 LH",
    "addr:housenumber":"8",
    "addr:postcode":"7271 lh",
    "addr:street":"Korenbree;Gelderland",
    "iso:country":"NL",
    "sg:address":"Korenbree 8",
    "sg:city":"Borculo",
    "sg:orig_category":"Oud Metaal",
    "sg:phone":"+31 545 273 672",
    "sg:postcode":"7271 LH",
    "sg:province":"Gelderland",
    "wof:name":"Soldaat, H",
    "wof:placetype":"venue"
},
  "geometry": {"coordinates":[6.5331478119,52.1244010925],"type":"Point"}
}