{
  "type": "Feature",
  "properties": {
    "addr:full":"Maasdk 273B Wyk En Aalburg Noord-Brabant 4261 AL",
    "addr:housenumber":"273b",
    "addr:postcode":"4261 al",
    "addr:street":"Wyk En",
    "iso:country":"NL",
    "sg:address":"Maasdk 273B",
    "sg:city":"Wyk En Aalburg",
    "sg:orig_category":"Bloemen En Planten - Groothandel",
    "sg:phone":"+31 416 693 889",
    "sg:postcode":"4261 AL",
    "sg:province":"Noord-Brabant",
    "wof:name":"Holland Export Plants",
    "wof:placetype":"venue"
},
  "geometry": {"coordinates":[5.116467,51.775803],"type":"Point"}
}