{
  "type": "Feature",
  "properties": {
    "addr:full":"Rynstr 62 Enschede Overijssel 7523 GH",
    "addr:housenumber":"62",
    "addr:postcode":"7523 gh",
    "addr:street":"Rynstr",
    "iso:country":"NL",
    "sg:address":"Rynstr 62",
    "sg:city":"Enschede",
    "sg:orig_category":"Juweliers",
    "sg:phone":"+31 53 435 6859",
    "sg:postcode":"7523 GH",
    "sg:province":"Overijssel",
    "wof:name":"Anneveld, P",
    "wof:placetype":"venue"
},
  "geometry": {"coordinates":[6.89691,52.235901],"type":"Point"}
}