{
  "type": "Feature",
  "properties": {
    "addr:full":"Kuiperbergwg 28 Amsterdam Zuidoost Noord-Holland 1101 AG",
    "addr:housenumber":"28",
    "addr:postcode":"zuidoost;1101",
    "addr:street":"Kuiperbergwg",
    "iso:country":"NL",
    "sg:address":"Kuiperbergwg 28",
    "sg:city":"Amsterdam Zuidoost",
    "sg:orig_category":"Koeriersdiensten",
    "sg:phone":"+31 20 688 8898",
    "sg:postcode":"1101 AG",
    "sg:province":"Noord-Holland",
    "wof:name":"City Net Bv",
    "wof:placetype":"venue"
},
  "geometry": {"coordinates":[4.938881,52.30138],"type":"Point"}
}