{
  "type": "Feature",
  "properties": {
    "addr:full":"Gladiolenveld 27 Castricum North Holland 1901 LR",
    "addr:housenumber":"27",
    "addr:postcode":"1901 lr",
    "addr:street":"Gladiolenveld",
    "iso:country":"NL",
    "sg:address":"Gladiolenveld 27",
    "sg:city":"Castricum",
    "sg:orig_category":"Fotoreportages",
    "sg:phone":"+31 251 659 017",
    "sg:postcode":"1901 LR",
    "sg:province":"North Holland",
    "wof:name":"Ferrie Blom Vakfotografie-Photodesign",
    "wof:placetype":"venue"
},
  "geometry": {"coordinates":[4.675235,52.560322],"type":"Point"}
}