{
  "type": "Feature",
  "properties": {
    "iso:country":"NL",
    "sg:address":"Angstelkade 4",
    "sg:city":"Nieuwersluis",
    "sg:classifiers":[
        {
            "category":"Retail",
            "subcategory":"Photofinishing",
            "type":"Services"
        }
    ],
    "sg:phone":"+31 294 233 503",
    "sg:postcode":"3631 NA",
    "sg:province":"Utrecht",
    "sg:tags":[
        "foto",
        "film"
    ],
    "wof:name":"Fotografie Jaap De Jong",
    "wof:placetype":"venue"
},
  "geometry": {"coordinates":[4.991817,52.204414],"type":"Point"}
}