{
  "type": "Feature",
  "properties": {
    "addr:full":"Blaaksedk O 27 Heinenoord South Holland 3274 LA",
    "addr:housenumber":"27",
    "addr:postcode":"3274 la",
    "iso:country":"NL",
    "sg:address":"Blaaksedk O 27",
    "sg:city":"Heinenoord",
    "sg:orig_category":"Verhuur",
    "sg:phone":"+31 186 603 233",
    "sg:postcode":"3274 LA",
    "sg:province":"South Holland",
    "wof:name":"Thomas",
    "wof:placetype":"venue"
},
  "geometry": {"coordinates":[4.515663,51.812084],"type":"Point"}
}