{
  "type": "Feature",
  "properties": {
    "iso:country":"NL",
    "sg:address":"Polsbroek 85",
    "sg:city":"Zutphen",
    "sg:orig_category":"Horecabenodigdheden",
    "sg:phone":"+31 575 544 384",
    "sg:postcode":"7201 BX",
    "sg:province":"Gelderland",
    "wof:name":"Koelewijn & Zoon",
    "wof:placetype":"venue"
},
  "geometry": {"coordinates":[6.201539,52.138268],"type":"Point"}
}