{
  "type": "Feature",
  "properties": {
    "addr:full":"Slochterwaard 151 Alkmaar Noord-Holland 1824 KT",
    "addr:housenumber":"151",
    "addr:postcode":"1824 kt",
    "addr:street":"Slochterwaard",
    "iso:country":"NL",
    "sg:address":"Slochterwaard 151",
    "sg:city":"Alkmaar",
    "sg:orig_category":"Kunstgebitten",
    "sg:phone":"+31 72 561 6066",
    "sg:postcode":"1824 KT",
    "sg:province":"Noord-Holland",
    "wof:name":"Kieft, P",
    "wof:placetype":"venue"
},
  "geometry": {"coordinates":[4.762292,52.645313],"type":"Point"}
}