{
  "type": "Feature",
  "properties": {
    "addr:full":"Kinkerstraat 39 Amsterdam Noord-Holland 1053 DD",
    "addr:housenumber":"39",
    "addr:postcode":"1053 dd",
    "addr:street":"Kinkerstraat",
    "iso:country":"NL",
    "sg:address":"Kinkerstraat 39",
    "sg:city":"Amsterdam",
    "sg:orig_category":"Boekhandels",
    "sg:phone":"+31 20 683 6191",
    "sg:postcode":"1053 DD",
    "sg:province":"Noord-Holland",
    "wof:name":"British General Stores",
    "wof:placetype":"venue"
},
  "geometry": {"coordinates":[4.874421,52.367718],"type":"Point"}
}