{
  "type": "Feature",
  "properties": {
    "iso:country":"NL",
    "sg:address":"Boswg 5",
    "sg:city":"Apeldoorn",
    "sg:orig_category":"Scholen Voor Basisonderwijs",
    "sg:phone":"+31 55 521 9527",
    "sg:postcode":"7314 AL",
    "sg:province":"Gelderland",
    "wof:name":"Heuvellaan Openb",
    "wof:placetype":"venue"
},
  "geometry": {"coordinates":[5.949819,52.223698],"type":"Point"}
}