{
  "type": "Feature",
  "properties": {
    "iso:country":"NL",
    "sg:address":"Gelderlandpln 36",
    "sg:city":"Amsterdam",
    "sg:classifiers":[
        {
            "category":"Farming",
            "subcategory":"Fish & Marine Products",
            "type":"Manufacturing & Wholesale Goods"
        }
    ],
    "sg:phone":"+31 20 642 7651",
    "sg:postcode":"1082 LB",
    "sg:province":"North Holland",
    "sg:tags":[
        "vi"
    ],
    "wof:name":"Kroon Volendammer Vishandel",
    "wof:placetype":"venue"
},
  "geometry": {"coordinates":[4.876353,52.331482],"type":"Point"}
}