{
  "type": "Feature",
  "properties": {
    "addr:full":"Griend 16 Diemen Noord-Holland 1112 LD",
    "addr:housenumber":"16",
    "addr:postcode":"1112 ld",
    "addr:street":"Griend",
    "iso:country":"NL",
    "sg:address":"Griend 16",
    "sg:city":"Diemen",
    "sg:orig_category":"Autorijscholen",
    "sg:phone":"+31 6 54678741",
    "sg:postcode":"1112 LD",
    "sg:province":"Noord-Holland",
    "wof:name":"Best, C J De",
    "wof:placetype":"venue"
},
  "geometry": {"coordinates":[4.947035,52.3293],"type":"Point"}
}