{
  "type": "Feature",
  "properties": {
    "addr:full":"Nijverheidsstraat 15 Hardenberg Overijssel 7772 TP",
    "addr:housenumber":"15",
    "addr:postcode":"7772 tp",
    "addr:street":"Nijverheidsstraat",
    "iso:country":"NL",
    "sg:address":"Nijverheidsstraat 15",
    "sg:city":"Hardenberg",
    "sg:orig_category":"Bouwmaterialen Gh",
    "sg:phone":"+31 523 266 200",
    "sg:postcode":"7772 TP",
    "sg:province":"Overijssel",
    "wof:name":"Cuperus Steenhouwerij- Natuursteenhandel",
    "wof:placetype":"venue"
},
  "geometry": {"coordinates":[6.632569,52.561539],"type":"Point"}
}