{
  "type": "Feature",
  "properties": {
    "iso:country":"NL",
    "sg:address":"L Slagen 34",
    "sg:city":"Breda",
    "sg:orig_category":"Afslankinstituten",
    "sg:phone":"+31 76 541 4358",
    "sg:postcode":"4823 LJ",
    "sg:province":"Noord-Brabant",
    "sg:website":"http://www.polystore.nl",
    "wof:name":"Healthy Food International",
    "wof:placetype":"venue"
},
  "geometry": {"coordinates":[4.733877,51.625141],"type":"Point"}
}