{
  "type": "Feature",
  "properties": {
    "addr:full":"De Klencke 34 Roden Drenthe 9301 SZ",
    "addr:housenumber":"34",
    "addr:postcode":"9301 sz",
    "addr:street":"De Klencke",
    "iso:country":"NL",
    "sg:address":"De Klencke 34",
    "sg:city":"Roden",
    "sg:orig_category":"Adviesbureaus Personeel",
    "sg:phone":"+31 50 501 7269",
    "sg:postcode":"9301 SZ",
    "sg:province":"Drenthe",
    "wof:name":"Bosconsult",
    "wof:placetype":"venue"
},
  "geometry": {"coordinates":[6.406668,53.138885],"type":"Point"}
}