{
  "type": "Feature",
  "properties": {
    "iso:country":"NL",
    "sg:address":"De Klencke 34",
    "sg:city":"Roden",
    "sg:orig_category":"Adviesbureaus Personeel",
    "sg:phone":"+31 50 501 7269",
    "sg:postcode":"9301 SZ",
    "sg:province":"Drenthe",
    "wof:name":"Bosconsult",
    "wof:placetype":"venue"
},
  "geometry": {"coordinates":[6.406668,53.138885],"type":"Point"}
}