{
  "type": "Feature",
  "properties": {
    "addr:full":"Zandwierde 44 Almere Flevoland 1353 CE",
    "addr:housenumber":"44",
    "addr:postcode":"1353 ce",
    "addr:street":"Zandwierde;Flevoland",
    "iso:country":"NL",
    "sg:address":"Zandwierde 44",
    "sg:city":"Almere",
    "sg:orig_category":"Onderhoudswerken",
    "sg:phone":"+31 36 531 8535",
    "sg:postcode":"1353 CE",
    "sg:province":"Flevoland",
    "wof:name":"Faro",
    "wof:placetype":"venue"
},
  "geometry": {"coordinates":[5.211692,52.334927],"type":"Point"}
}