{
  "type": "Feature",
  "properties": {
    "iso:country":"NL",
    "sg:address":"Grasbroekerwg",
    "sg:city":"Heerlen",
    "sg:orig_category":"Meubelstoffering",
    "sg:phone":"+31 45 521 3975",
    "sg:postcode":"6412 BC",
    "sg:province":"Limburg",
    "wof:name":"Rinia, Meubelstoffering",
    "wof:placetype":"venue"
},
  "geometry": {"coordinates":[5.973195,50.897781],"type":"Point"}
}