{
  "type": "Feature",
  "properties": {
    "addr:full":"Reguliersln 23 Alkmaar Noord-Holland 1815 KA",
    "addr:housenumber":"23",
    "addr:postcode":"1815 ka",
    "addr:street":"Reguliersln",
    "iso:country":"NL",
    "sg:address":"Reguliersln 23",
    "sg:city":"Alkmaar",
    "sg:orig_category":"Verzekeringen - Verzekeringskantoren",
    "sg:phone":"+31 72 512 5530",
    "sg:postcode":"1815 KA",
    "sg:province":"Noord-Holland",
    "wof:name":"Vethaak, J",
    "wof:placetype":"venue"
},
  "geometry": {"coordinates":[4.728877,52.620289],"type":"Point"}
}