{
  "type": "Feature",
  "properties": {
    "addr:full":"John F Kennedylaan 3 Eindhoven Noord-Brabant 5612 AB",
    "addr:housenumber":"3",
    "addr:postcode":"5612 ab",
    "addr:street":"John F Kennedylaan",
    "iso:country":"NL",
    "sg:address":"John F Kennedylaan 3",
    "sg:city":"Eindhoven",
    "sg:orig_category":"Werving And Selectie Van Tijdelijk Personeel And Uitzendkantoren",
    "sg:phone":"+31 40 244 0284",
    "sg:postcode":"5612 AB",
    "sg:province":"Noord-Brabant",
    "wof:name":"Bbb",
    "wof:placetype":"venue"
},
  "geometry": {"coordinates":[5.4813961983,51.4458885193],"type":"Point"}
}