{
  "type": "Feature",
  "properties": {
    "addr:full":"Agneshof 24 Nuth Limburg 6361 BN",
    "addr:housenumber":"24",
    "addr:postcode":"6361 bn",
    "addr:street":"Agneshof",
    "iso:country":"NL",
    "sg:address":"Agneshof 24",
    "sg:city":"Nuth",
    "sg:orig_category":"Hypnotherapeuten",
    "sg:phone":"+31 45 524 4016",
    "sg:postcode":"6361 BN",
    "sg:province":"Limburg",
    "wof:name":"Hypnotherapie",
    "wof:placetype":"venue"
},
  "geometry": {"coordinates":[5.885999,50.918785],"type":"Point"}
}