{
  "type": "Feature",
  "properties": {
    "addr:full":"Vierwindenstraat 225 Amsterdam Noord-Holland 1013 CW",
    "addr:housenumber":"225",
    "addr:postcode":"1013 cw",
    "addr:street":"Vierwindenstraat",
    "iso:country":"NL",
    "sg:address":"Vierwindenstraat 225",
    "sg:city":"Amsterdam",
    "sg:orig_category":"Adviesbureaus",
    "sg:phone":"+31 20 882 0607",
    "sg:postcode":"1013 CW",
    "sg:province":"Noord-Holland",
    "sg:website":"http://www.onoff.nl",
    "wof:name":"On-Off Consultancy",
    "wof:placetype":"venue"
},
  "geometry": {"coordinates":[4.886586,52.387489],"type":"Point"}
}