{
  "type": "Feature",
  "properties": {
    "addr:full":"Galeiwg 1 Werkendam Noord-Brabant 4251 MZ",
    "addr:housenumber":"1",
    "addr:postcode":"4251 mz",
    "addr:street":"Galeiwg",
    "iso:country":"NL",
    "sg:address":"Galeiwg 1",
    "sg:city":"Werkendam",
    "sg:orig_category":"Grondwerken",
    "sg:phone":"+31 183 504 190",
    "sg:postcode":"4251 MZ",
    "sg:province":"Noord-Brabant",
    "wof:name":"Broek, A Van Den",
    "wof:placetype":"venue"
},
  "geometry": {"coordinates":[4.830619,51.777233],"type":"Point"}
}