{
  "type": "Feature",
  "properties": {
    "addr:full":"Wyldpaed O 23A Twyzelerheide Provincie Friesland 9287 VM",
    "addr:housenumber":"23a twyzelerheide",
    "addr:postcode":"9287 vm",
    "addr:street":"Wyldpaed O;Provincie Friesland",
    "iso:country":"NL",
    "sg:address":"Wyldpaed O 23A",
    "sg:city":"Twyzelerheide",
    "sg:orig_category":"Metaalbewerking",
    "sg:phone":"+31 511 443 360",
    "sg:postcode":"9287 VM",
    "sg:province":"Provincie Friesland",
    "wof:name":"Weg, Van Der",
    "wof:placetype":"venue"
},
  "geometry": {"coordinates":[6.067803,53.243458],"type":"Point"}
}