{
  "type": "Feature",
  "properties": {
    "addr:full":"Poeldonkwg 5 S Hertogenbosch Noord-Brabant 5216 JX",
    "addr:housenumber":"5",
    "addr:postcode":"5216 jx",
    "addr:street":"Poeldonkwg",
    "iso:country":"NL",
    "sg:address":"Poeldonkwg 5",
    "sg:city":"S Hertogenbosch",
    "sg:orig_category":"Elektronica - Ontwikkeling En Groothandel",
    "sg:phone":"+31 73 612 5852",
    "sg:postcode":"5216 JX",
    "sg:province":"Noord-Brabant",
    "sg:website":"http://www.tme-elec.com",
    "wof:name":"Trade Mark Bv",
    "wof:placetype":"venue"
},
  "geometry": {"coordinates":[5.332923,51.685555],"type":"Point"}
}