{
  "type": "Feature",
  "properties": {
    "addr:full":"Van Speijkstraat 38 Haaksbergen NL.08 7482 BN",
    "addr:housenumber":"38;nl.08",
    "addr:postcode":"7482 bn",
    "addr:street":"Van Speijkstraat",
    "iso:country":"NL",
    "sg:address":"Van Speijkstraat 38",
    "sg:city":"Haaksbergen",
    "sg:orig_category":"Autokeuringen",
    "sg:phone":"+31 53 572 3548",
    "sg:postcode":"7482 BN",
    "sg:province":"NL.08",
    "wof:name":"M.J. Nijkamp",
    "wof:placetype":"venue"
},
  "geometry": {"coordinates":[6.739143,52.160965],"type":"Point"}
}