{
  "type": "Feature",
  "properties": {
    "addr:full":"Monstersestraat 150 'S Gravenhage Zuid-Holland 2512 PD",
    "addr:housenumber":"150 '",
    "addr:postcode":"2512 pd",
    "addr:street":"Monstersestraat",
    "iso:country":"NL",
    "sg:address":"Monstersestraat 150",
    "sg:city":"'S Gravenhage",
    "sg:orig_category":"Huizensloop And Bouwrijp Maken",
    "sg:phone":"+31 70 380 2801",
    "sg:postcode":"2512 PD",
    "sg:province":"Zuid-Holland",
    "wof:name":"Vof Tuinbouwloonbedr Meta",
    "wof:placetype":"venue"
},
  "geometry": {"coordinates":[4.294103,52.070244],"type":"Point"}
}