{
  "type": "Feature",
  "properties": {
    "iso:country":"NL",
    "sg:address":"Bedrijvenweg 24",
    "sg:city":"Sint Michielsgestel",
    "sg:classifiers":[
        {
            "category":"Food & Beverages",
            "subcategory":"Fruits & Vegetables",
            "type":"Retail Goods"
        }
    ],
    "sg:phone":"+31 73 551 6226",
    "sg:postcode":"5272 PB",
    "sg:province":"Noord-Brabant",
    "sg:tags":[
        "groenten"
    ],
    "wof:name":"M.H.J.W. Lenaerts",
    "wof:placetype":"venue"
},
  "geometry": {"coordinates":[5.363396,51.647808],"type":"Point"}
}