{
  "type": "Feature",
  "properties": {
    "addr:full":"Kerkstr 4 Noordwyk Zh South Holland 2201 KM",
    "addr:housenumber":"4;zh",
    "addr:street":"Kerkstr;2201 Km",
    "iso:country":"NL",
    "sg:address":"Kerkstr 4",
    "sg:city":"Noordwyk Zh",
    "sg:orig_category":"Beeldende Kunstenaars",
    "sg:phone":"+31 71 361 9557",
    "sg:postcode":"2201 KM",
    "sg:province":"South Holland",
    "wof:name":"Jil'S Art Janine Lamers",
    "wof:placetype":"venue"
},
  "geometry": {"coordinates":[4.447213,52.234173],"type":"Point"}
}