{
  "type": "Feature",
  "properties": {
    "addr:full":"Dorpsstr 159 Zuid Beyerland Zuid-Holland 3284 AE",
    "addr:housenumber":"159;beyerland",
    "addr:postcode":"3284 ae",
    "iso:country":"NL",
    "sg:address":"Dorpsstr 159",
    "sg:city":"Zuid Beyerland",
    "sg:orig_category":"Psychotherapeuten",
    "sg:phone":"+31 186 669 155",
    "sg:postcode":"3284 AE",
    "sg:province":"Zuid-Holland",
    "wof:name":"Relatie En Gezinstherapie, Prakt Voor Indiv",
    "wof:placetype":"venue"
},
  "geometry": {"coordinates":[4.368483,51.749577],"type":"Point"}
}