{
  "type": "Feature",
  "properties": {
    "addr:full":"Luttekestr 13 Zwolle NL.08 8011 LN",
    "addr:housenumber":"13",
    "addr:postcode":"8011 ln",
    "addr:street":"Luttekestr",
    "iso:country":"NL",
    "sg:address":"Luttekestr 13",
    "sg:city":"Zwolle",
    "sg:orig_category":"Fietsen En Bromfietsen",
    "sg:phone":"+31 38 421 7378",
    "sg:postcode":"8011 LN",
    "sg:province":"NL.08",
    "sg:website":"http://www.tweewielerspecialistscholten.nl",
    "wof:name":"Scholten, Tweewielerspecialist",
    "wof:placetype":"venue"
},
  "geometry": {"coordinates":[6.091127,52.511246],"type":"Point"}
}