{
  "type": "Feature",
  "properties": {
    "iso:country":"NL",
    "sg:address":"Asterlo 83",
    "sg:city":"Rotterdam",
    "sg:orig_category":"Diverse Bedrijfsinstallaties Gh",
    "sg:phone":"+31 10 480 1518",
    "sg:postcode":"3085 AE",
    "sg:province":"Zuid-Holland",
    "wof:name":"Hw Hydro-Paint Int.",
    "wof:placetype":"venue"
},
  "geometry": {"coordinates":[4.482804,51.874306],"type":"Point"}
}