{
  "type": "Feature",
  "properties": {
    "addr:full":"Ten Katestr 4 Amsterdam Noord-Holland 1053 CE",
    "addr:housenumber":"4",
    "addr:postcode":"1053 ce",
    "addr:street":"Ten Katestr",
    "iso:country":"NL",
    "sg:address":"Ten Katestr 4",
    "sg:city":"Amsterdam",
    "sg:orig_category":"Gordijnen",
    "sg:phone":"+31 20 683 4855",
    "sg:postcode":"1053 CE",
    "sg:province":"Noord-Holland",
    "wof:name":"Vitragemarkt",
    "wof:placetype":"venue"
},
  "geometry": {"coordinates":[4.866004,52.367859],"type":"Point"}
}