{
  "type": "Feature",
  "properties": {
    "addr:full":"Postbus 19290 Utrecht Utrecht 3501 DG",
    "addr:postcode":"19290;3501 dg",
    "addr:street":"Postbus",
    "iso:country":"NL",
    "sg:address":"Postbus 19290",
    "sg:city":"Utrecht",
    "sg:orig_category":"Verenigingen En Stichtingen",
    "sg:phone":"+31 30 234 3222",
    "sg:postcode":"3501 DG",
    "sg:province":"Utrecht",
    "wof:name":"Arbitrage Voor De Bouwbedrijven In Ned, Raad Van",
    "wof:placetype":"venue"
},
  "geometry": {"coordinates":[5.12289,52.091],"type":"Point"}
}