{
  "type": "Feature",
  "properties": {
    "addr:full":"Wattstr 26H Zoetermeer Zuid-Holland 2723 RC",
    "addr:postcode":"2723 rc",
    "iso:country":"NL",
    "sg:address":"Wattstr 26H",
    "sg:city":"Zoetermeer",
    "sg:classifiers":[
        {
            "category":"Food & Beverages",
            "subcategory":"Bakery",
            "type":"Retail Goods"
        }
    ],
    "sg:phone":"+31 79 342 2339",
    "sg:postcode":"2723 RC",
    "sg:province":"Zuid-Holland",
    "sg:tags":[
        "pizza"
    ],
    "wof:name":"Venezia Pizzeria",
    "wof:placetype":"venue"
},
  "geometry": {"coordinates":[4.524946,52.059574],"type":"Point"}
}