{
  "type": "Feature",
  "properties": {
    "iso:country":"NL",
    "sg:address":"Vaartstraat 44",
    "sg:city":"Amsterdam",
    "sg:orig_category":"Boekhouders",
    "sg:phone":"+31 20 672 2393",
    "sg:postcode":"1075 RR",
    "sg:province":"North Holland",
    "wof:name":"Strega",
    "wof:placetype":"venue"
},
  "geometry": {"coordinates":[4.854951,52.350491],"type":"Point"}
}