{
  "type": "Feature",
  "properties": {
    "addr:full":"Vaartstraat 44 Amsterdam North Holland 1075 RR",
    "addr:housenumber":"44",
    "addr:postcode":"1075 rr",
    "addr:street":"Vaartstraat",
    "iso:country":"NL",
    "sg:address":"Vaartstraat 44",
    "sg:city":"Amsterdam",
    "sg:orig_category":"Boekhouders",
    "sg:phone":"+31 20 672 2393",
    "sg:postcode":"1075 RR",
    "sg:province":"North Holland",
    "wof:name":"Strega",
    "wof:placetype":"venue"
},
  "geometry": {"coordinates":[4.854951,52.350491],"type":"Point"}
}