{
  "type": "Feature",
  "properties": {
    "addr:full":"Laarderwg 19 Bussum Noord-Holland 1402 BB",
    "addr:housenumber":"19",
    "addr:postcode":"1402 bb",
    "addr:street":"Laarderwg",
    "iso:country":"NL",
    "sg:address":"Laarderwg 19",
    "sg:city":"Bussum",
    "sg:orig_category":"Gordijnenateliers",
    "sg:phone":"+31 35 693 2489",
    "sg:postcode":"1402 BB",
    "sg:province":"Noord-Holland",
    "wof:name":"Calis, Diny",
    "wof:placetype":"venue"
},
  "geometry": {"coordinates":[5.166056,52.270985],"type":"Point"}
}