{
  "type": "Feature",
  "properties": {
    "addr:full":"Burg Jansenpln 44 Hengelo Ov NL.08 7551 ED",
    "addr:housenumber":"44",
    "addr:postcode":"7551 ed",
    "addr:street":"Burg;Ov",
    "iso:country":"NL",
    "sg:address":"Burg Jansenpln 44",
    "sg:city":"Hengelo Ov",
    "sg:orig_category":"Makelaars En Adviseurs Onroerende Goederen",
    "sg:phone":"+31 74 250 6566",
    "sg:postcode":"7551 ED",
    "sg:province":"NL.08",
    "wof:name":"Hag, Ten",
    "wof:placetype":"venue"
},
  "geometry": {"coordinates":[6.789712,52.266361],"type":"Point"}
}