{
  "type": "Feature",
  "properties": {
    "addr:full":"Rechtstr 65A Maastricht Limburg 6221 EH",
    "addr:housenumber":"65a",
    "addr:postcode":"6221 eh",
    "addr:street":"Rechtstr",
    "iso:country":"NL",
    "sg:address":"Rechtstr 65A",
    "sg:city":"Maastricht",
    "sg:orig_category":"Parketvloeren",
    "sg:phone":"+31 43 325 2228",
    "sg:postcode":"6221 EH",
    "sg:province":"Limburg",
    "sg:website":"http://www.hetvloerencentrum.nl",
    "wof:name":"Argus Vloerencentrum",
    "wof:placetype":"venue"
},
  "geometry": {"coordinates":[5.698426,50.848305],"type":"Point"}
}