{
  "type": "Feature",
  "properties": {
    "addr:full":"Herculesstr 71 Amsterdam Noord-Holland 1076 SE",
    "addr:housenumber":"71",
    "addr:postcode":"1076 se",
    "addr:street":"Herculesstr",
    "iso:country":"NL",
    "sg:address":"Herculesstr 71",
    "sg:city":"Amsterdam",
    "sg:orig_category":"Journalisten Freelance",
    "sg:phone":"+31 20 616 6354",
    "sg:postcode":"1076 SE",
    "sg:province":"Noord-Holland",
    "sg:website":"http://www.slinkz.nl",
    "wof:name":"Slinkz",
    "wof:placetype":"venue"
},
  "geometry": {"coordinates":[4.862602,52.347458],"type":"Point"}
}