{
  "type": "Feature",
  "properties": {
    "iso:country":"NL",
    "sg:address":"Molenstr 20",
    "sg:city":"Ossendrecht",
    "sg:orig_category":"Verf En Lak",
    "sg:phone":"+31 164 672 409",
    "sg:postcode":"4641 BD",
    "sg:province":"Noord-Brabant",
    "wof:name":"Burgt-De Noier Vof, Van Der",
    "wof:placetype":"venue"
},
  "geometry": {"coordinates":[4.332245,51.392883],"type":"Point"}
}