{
  "type": "Feature",
  "properties": {
    "addr:full":"Eygelshovergr 64 Kerkrade Limburg 6464 GB",
    "addr:housenumber":"64",
    "addr:postcode":"6464 gb",
    "addr:street":"Eygelshovergr",
    "iso:country":"NL",
    "sg:address":"Eygelshovergr 64",
    "sg:city":"Kerkrade",
    "sg:classifiers":[
        {
            "category":"Retail",
            "subcategory":"Auto Repair",
            "type":"Services"
        }
    ],
    "sg:phone":"+31 45 546 0500",
    "sg:postcode":"6464 GB",
    "sg:province":"Limburg",
    "sg:tags":[
        "garage"
    ],
    "sg:website":"http://www.janssen.peugeot.nl",
    "wof:name":"Janssen Bv, Autobedrijf",
    "wof:placetype":"venue"
},
  "geometry": {"coordinates":[6.061353,50.885128],"type":"Point"}
}