{
  "type": "Feature",
  "properties": {
    "iso:country":"NL",
    "sg:address":"De Molen 8",
    "sg:city":"Houten",
    "sg:orig_category":"Vertaal- And Tolkenbureaus",
    "sg:phone":"+31 30 635 5135",
    "sg:postcode":"3994 DB",
    "sg:province":"Utrecht",
    "wof:name":"Comtech Houten Bv",
    "wof:placetype":"venue"
},
  "geometry": {"coordinates":[5.176062,52.028053],"type":"Point"}
}