{
  "type": "Feature",
  "properties": {
    "addr:full":"Noorwal 101 S Gravenhage South Holland 2513 EA",
    "addr:housenumber":"101",
    "addr:postcode":"2513 ea",
    "addr:street":"Noorwal;S Gravenhage",
    "iso:country":"NL",
    "sg:address":"Noorwal 101",
    "sg:city":"S Gravenhage",
    "sg:orig_category":"Woningbouw- Verenigingen En -Stichtingen",
    "sg:phone":"+31 70 361 0610",
    "sg:postcode":"2513 EA",
    "sg:province":"South Holland",
    "wof:name":"Vestia Den Haag Zo",
    "wof:placetype":"venue"
},
  "geometry": {"coordinates":[4.3033900261,52.0784416199],"type":"Point"}
}