{
  "type": "Feature",
  "properties": {
    "iso:country":"NL",
    "sg:address":"Fortunawg 70",
    "sg:city":"Schiedam",
    "sg:orig_category":"Verlichtingsartikelen - Groothandel",
    "sg:phone":"+31 10 473 8400",
    "sg:postcode":"3113 AN",
    "sg:province":"South Holland",
    "wof:name":"Lohuis Bv",
    "wof:placetype":"venue"
},
  "geometry": {"coordinates":[4.41025,51.90398],"type":"Point"}
}