{
  "type": "Feature",
  "properties": {
    "addr:full":"Fortunawg 70 Schiedam South Holland 3113 AN",
    "addr:housenumber":"70",
    "addr:postcode":"3113 an",
    "addr:street":"Fortunawg",
    "iso:country":"NL",
    "sg:address":"Fortunawg 70",
    "sg:city":"Schiedam",
    "sg:orig_category":"Verlichtingsartikelen - Groothandel",
    "sg:phone":"+31 10 473 8400",
    "sg:postcode":"3113 AN",
    "sg:province":"South Holland",
    "wof:name":"Lohuis Bv",
    "wof:placetype":"venue"
},
  "geometry": {"coordinates":[4.41025,51.90398],"type":"Point"}
}