{
  "type": "Feature",
  "properties": {
    "iso:country":"NL",
    "sg:address":"Sluiswachtershoev 610",
    "sg:city":"Apeldoorn",
    "sg:orig_category":"Bloemen En Planten - Groothandel",
    "sg:phone":"+31 55 533 6936",
    "sg:postcode":"7326 ZH",
    "sg:province":"Gelderland",
    "wof:name":"Racap",
    "wof:placetype":"venue"
},
  "geometry": {"coordinates":[6.011798,52.187614],"type":"Point"}
}