{
  "type": "Feature",
  "properties": {
    "addr:full":"Duizeldonksestr 24 Helmond North Brabant 5705 CA",
    "addr:housenumber":"24",
    "addr:postcode":"5705 ca",
    "addr:street":"Duizeldonksestr",
    "iso:country":"NL",
    "sg:address":"Duizeldonksestr 24",
    "sg:city":"Helmond",
    "sg:orig_category":"Koeltechniek",
    "sg:phone":"+31 492 555 222",
    "sg:postcode":"5705 CA",
    "sg:province":"North Brabant",
    "sg:website":"http://www.vekahkoudetechniek.nl",
    "wof:name":"Vekah Koudetechniek",
    "wof:placetype":"venue"
},
  "geometry": {"coordinates":[5.684943,51.470478],"type":"Point"}
}