{
  "type": "Feature",
  "properties": {
    "addr:full":"A Toscaninistr 19 Almere NL. 1311 LR",
    "addr:housenumber":"19",
    "addr:postcode":"1311 lr",
    "addr:street":"Nl.",
    "iso:country":"NL",
    "sg:address":"A Toscaninistr 19",
    "sg:city":"Almere",
    "sg:orig_category":"Adviesbureaus Bouwkunde",
    "sg:phone":"+31 36 546 8439",
    "sg:postcode":"1311 LR",
    "sg:province":"NL.",
    "wof:name":"Ves Civil",
    "wof:placetype":"venue"
},
  "geometry": {"coordinates":[5.176152,52.372013],"type":"Point"}
}