{
  "type": "Feature",
  "properties": {
    "addr:full":"Dres 8 Sybekarspel Noord-Holland 1655 KL",
    "addr:housenumber":"8",
    "addr:postcode":"1655 kl",
    "addr:street":"Dres",
    "iso:country":"NL",
    "sg:address":"Dres 8",
    "sg:city":"Sybekarspel",
    "sg:orig_category":"Bedrijfsopleidingen",
    "sg:phone":"+31 229 591 662",
    "sg:postcode":"1655 KL",
    "sg:province":"Noord-Holland",
    "wof:name":"Maret",
    "wof:placetype":"venue"
},
  "geometry": {"coordinates":[5.009022,52.704193],"type":"Point"}
}