{
  "type": "Feature",
  "properties": {
    "iso:country":"NL",
    "sg:address":"Koningin Julianastraat 6",
    "sg:city":"Mook",
    "sg:orig_category":"Goederenvervoer Over De Weg",
    "sg:phone":"+31 24 696 1717",
    "sg:postcode":"6585 XR",
    "sg:province":"Limburg",
    "wof:name":"Transportbedrijf Vos-Mook",
    "wof:placetype":"venue"
},
  "geometry": {"coordinates":[5.88342,51.751141],"type":"Point"}
}