{
  "type": "Feature",
  "properties": {
    "iso:country":"NL",
    "sg:address":"Toneelln 1",
    "sg:city":"Zoetermeer",
    "sg:orig_category":"Ziekenhuizen, Sanatoria, Verpleeghuizen",
    "sg:phone":"+31 79 346 2626",
    "sg:postcode":"2725 NA",
    "sg:province":"Zuid-Holland",
    "sg:website":"http://www.langeland.nl",
    "wof:name":"Lange Land Ziekenhuis, 'T",
    "wof:placetype":"venue"
},
  "geometry": {"coordinates":[4.49972,52.069134],"type":"Point"}
}