{
  "type": "Feature",
  "properties": {
    "addr:full":"Mgr. Nolenslaan 792 Schiedam South Holland 3119 EW",
    "addr:housenumber":"792",
    "addr:postcode":"3119 ew",
    "addr:street":"Mgr. Nolenslaan",
    "iso:country":"NL",
    "sg:address":"Mgr. Nolenslaan 792",
    "sg:city":"Schiedam",
    "sg:orig_category":"Diverse Consumentenartikelen Gh",
    "sg:phone":"+31 10 273 0448",
    "sg:postcode":"3119 EW",
    "sg:province":"South Holland",
    "wof:name":"Agm International Company Operation",
    "wof:placetype":"venue"
},
  "geometry": {"coordinates":[4.387212,51.9203],"type":"Point"}
}