{
  "type": "Feature",
  "properties": {
    "addr:full":"Markt 10C Kerkrade Limburg 6461 EB",
    "addr:housenumber":"10c",
    "addr:postcode":"6461 eb",
    "addr:street":"Markt",
    "iso:country":"NL",
    "sg:address":"Markt 10C",
    "sg:city":"Kerkrade",
    "sg:orig_category":"Autorijscholen",
    "sg:phone":"+31 45 535 3692",
    "sg:postcode":"6461 EB",
    "sg:province":"Limburg",
    "wof:name":"Gielis, Frank",
    "wof:placetype":"venue"
},
  "geometry": {"coordinates":[6.06315,50.865562],"type":"Point"}
}