{
  "type": "Feature",
  "properties": {
    "addr:full":"Lahrstr 5 Sittard Limburg 6137 AD",
    "addr:housenumber":"5",
    "addr:postcode":"6137 ad",
    "addr:street":"Lahrstr",
    "iso:country":"NL",
    "sg:address":"Lahrstr 5",
    "sg:city":"Sittard",
    "sg:classifiers":[
        {
            "category":"Autos & Motor Vehicles",
            "subcategory":"Automobile Sales",
            "type":"Retail Goods"
        }
    ],
    "sg:phone":"+31 46 442 2601",
    "sg:postcode":"6137 AD",
    "sg:province":"Limburg",
    "sg:tags":[
        "caravan",
        "stalling",
        "-"
    ],
    "wof:name":"Rosa, St",
    "wof:placetype":"venue"
},
  "geometry": {"coordinates":[5.87807,50.995399],"type":"Point"}
}