{
  "type": "Feature",
  "properties": {
    "addr:full":"Overtoom 15 Castricum Noord-Holland 1901 EW",
    "addr:housenumber":"15",
    "addr:postcode":"1901 ew",
    "addr:street":"Overtoom",
    "iso:country":"NL",
    "sg:address":"Overtoom 15",
    "sg:city":"Castricum",
    "sg:orig_category":"Verenigingsgebouwen",
    "sg:phone":"+31 251 653 202",
    "sg:postcode":"1901 EW",
    "sg:province":"Noord-Holland",
    "wof:name":"Kern, De",
    "wof:placetype":"venue"
},
  "geometry": {"coordinates":[4.6624240875,52.5465431213],"type":"Point"}
}