{
  "type": "Feature",
  "properties": {
    "addr:full":"Kasteelln 21 Waalwyk Noord-Brabant 5141 BM",
    "addr:housenumber":"21",
    "addr:postcode":"5141 bm",
    "addr:street":"Kasteelln",
    "iso:country":"NL",
    "sg:address":"Kasteelln 21",
    "sg:city":"Waalwyk",
    "sg:orig_category":"Antiquiteiten - Restauratie",
    "sg:phone":"+31 416 334 550",
    "sg:postcode":"5141 BM",
    "sg:province":"Noord-Brabant",
    "wof:name":"Dijk, Van",
    "wof:placetype":"venue"
},
  "geometry": {"coordinates":[5.062876,51.689789],"type":"Point"}
}