{
  "type": "Feature",
  "properties": {
    "addr:full":"Kl Beer 18A Alblasserdam South Holland 2952 AS",
    "addr:housenumber":"18a",
    "addr:postcode":"2952 as",
    "iso:country":"NL",
    "sg:address":"Kl Beer 18A",
    "sg:city":"Alblasserdam",
    "sg:orig_category":"Ventilatiesystemen",
    "sg:phone":"+31 78 692 0620",
    "sg:postcode":"2952 AS",
    "sg:province":"South Holland",
    "sg:website":"http://www.flaktwoods.com",
    "wof:name":"Fl\u00e4kt Elve Nv",
    "wof:placetype":"venue"
},
  "geometry": {"coordinates":[4.658851,51.861031],"type":"Point"}
}