{
  "type": "Feature",
  "properties": {
    "addr:full":"De Beente 82A Maastricht Limburg 6229 AV",
    "addr:housenumber":"82a",
    "addr:postcode":"6229 av",
    "addr:street":"De Beente",
    "iso:country":"NL",
    "sg:address":"De Beente 82A",
    "sg:city":"Maastricht",
    "sg:orig_category":"Banken",
    "sg:phone":"+31 43 409 7100",
    "sg:postcode":"6229 AV",
    "sg:province":"Limburg",
    "sg:website":"http://www.rabobank.nl",
    "wof:name":"Rabobank",
    "wof:placetype":"venue"
},
  "geometry": {"coordinates":[5.703955,50.831543],"type":"Point"}
}