{
  "type": "Feature",
  "properties": {
    "addr:full":"Touwlaan 25 Ijsselstein Ut Utrecht 3401 CA",
    "addr:housenumber":"25",
    "addr:postcode":"3401 ca",
    "addr:street":"Touwlaan",
    "iso:country":"NL",
    "sg:address":"Touwlaan 25",
    "sg:city":"Ijsselstein Ut",
    "sg:orig_category":"Paramedische Behandelingen",
    "sg:phone":"+31 30 687 0708",
    "sg:postcode":"3401 CA",
    "sg:province":"Utrecht",
    "wof:name":"Podotherapeut C.H.J. Kivits",
    "wof:placetype":"venue"
},
  "geometry": {"coordinates":[5.043315,52.022369],"type":"Point"}
}