{
  "type": "Feature",
  "properties": {
    "addr:full":"Galjoen 24 Veenendaal Utrecht 3904 SG",
    "addr:housenumber":"24",
    "addr:postcode":"3904 sg",
    "addr:street":"Galjoen",
    "iso:country":"NL",
    "sg:address":"Galjoen 24",
    "sg:city":"Veenendaal",
    "sg:orig_category":"Parketvloeren",
    "sg:phone":"+31 342 475 283",
    "sg:postcode":"3904 SG",
    "sg:province":"Utrecht",
    "sg:website":"http://www.dijkstraparket.nl",
    "wof:name":"Dijkstra Parket",
    "wof:placetype":"venue"
},
  "geometry": {"coordinates":[5.533742,52.02681],"type":"Point"}
}