{
  "type": "Feature",
  "properties": {
    "iso:country":"NL",
    "sg:address":"Pierhoekseweg 1",
    "sg:city":"Sint Maartensdijk",
    "sg:orig_category":"Hoefdierhouderijen",
    "sg:phone":"+31 166 692 638",
    "sg:postcode":"4695 PE",
    "sg:province":"Zeeland",
    "wof:name":"El Gezirah Arabians",
    "wof:placetype":"venue"
},
  "geometry": {"coordinates":[4.049436,51.56081],"type":"Point"}
}