{
  "type": "Feature",
  "properties": {
    "iso:country":"NL",
    "sg:address":"Emmastraat 5",
    "sg:city":"Epe",
    "sg:orig_category":"Banken And Kredietinstellingen",
    "sg:phone":"+31 578 676 711",
    "sg:postcode":"8162 BA",
    "sg:province":"Gelderland",
    "wof:name":"Sns Bank",
    "wof:placetype":"venue"
},
  "geometry": {"coordinates":[5.982496,52.346928],"type":"Point"}
}