{
  "type": "Feature",
  "properties": {
    "addr:full":"Oude Polderstraat 3 Hansweert Zeeland 4417 AW",
    "addr:housenumber":"3",
    "addr:postcode":"4417 aw",
    "addr:street":"Oude Polderstraat",
    "iso:country":"NL",
    "sg:address":"Oude Polderstraat 3",
    "sg:city":"Hansweert",
    "sg:orig_category":"Goederenvervoer Over De Weg",
    "sg:phone":"+31 113 381 529",
    "sg:postcode":"4417 AW",
    "sg:province":"Zeeland",
    "wof:name":"M.J. Openeer Transportbedrijf Bv",
    "wof:placetype":"venue"
},
  "geometry": {"coordinates":[4.003563,51.446552],"type":"Point"}
}