{
  "type": "Feature",
  "properties": {
    "addr:full":"T Zylstrastr 22 Franeker Friesland 8802 TK",
    "addr:housenumber":"22",
    "addr:postcode":"8802 tk",
    "iso:country":"NL",
    "sg:address":"T Zylstrastr 22",
    "sg:city":"Franeker",
    "sg:orig_category":"Glazenwasserijen",
    "sg:phone":"+31 517 397 819",
    "sg:postcode":"8802 TK",
    "sg:province":"Friesland",
    "wof:name":"Franeker",
    "wof:placetype":"venue"
},
  "geometry": {"coordinates":[5.53092,53.191036],"type":"Point"}
}