{
  "type": "Feature",
  "properties": {
    "iso:country":"NL",
    "sg:address":"Hammerstraat 2",
    "sg:city":"Vroomshoop",
    "sg:orig_category":"Fotostudio'S And Fotografen",
    "sg:phone":"+31 546 644 007",
    "sg:postcode":"7681 DC",
    "sg:province":"NL.08",
    "wof:name":"Fotostudio Margreeth",
    "wof:placetype":"venue"
},
  "geometry": {"coordinates":[6.571916,52.461361],"type":"Point"}
}