{
  "type": "Feature",
  "properties": {
    "addr:full":"Mr. Beerninkplantsoen 72 Rijswijk Zh Zuid-Holland 2286 ML",
    "addr:housenumber":"72",
    "addr:postcode":"zh;2286 ml",
    "iso:country":"NL",
    "sg:address":"Mr. Beerninkplantsoen 72",
    "sg:city":"Rijswijk Zh",
    "sg:classifiers":[
        {
            "category":"Fast Food",
            "type":"Food & Drink"
        }
    ],
    "sg:phone":"+31 70 396 2696",
    "sg:postcode":"2286 ML",
    "sg:province":"Zuid-Holland",
    "sg:tags":[
        "afhaal",
        "restaurant"
    ],
    "wof:name":"Henk Patat",
    "wof:placetype":"venue"
},
  "geometry": {"coordinates":[4.315804,52.023663],"type":"Point"}
}