{
  "type": "Feature",
  "properties": {
    "addr:full":"Ryksstrwg 42 Nieuwersluis Utrecht 3631 AD",
    "addr:housenumber":"42",
    "addr:postcode":"3631 ad",
    "addr:street":"Ryksstrwg",
    "iso:country":"NL",
    "sg:address":"Ryksstrwg 42",
    "sg:city":"Nieuwersluis",
    "sg:orig_category":"Werving En Selectie",
    "sg:phone":"+31 294 231 502",
    "sg:postcode":"3631 AD",
    "sg:province":"Utrecht",
    "sg:website":"http://www.hettybos.nl",
    "wof:name":"Bos, Hetty",
    "wof:placetype":"venue"
},
  "geometry": {"coordinates":[5.0065598488,52.1958351135],"type":"Point"}
}