{
  "type": "Feature",
  "properties": {
    "addr:full":"Bergse Dorpsstraat 82 Rotterdam Zuid-Holland 3054 GG",
    "addr:housenumber":"82",
    "addr:postcode":"3054 gg",
    "addr:street":"Bergse Dorpsstraat",
    "iso:country":"NL",
    "sg:address":"Bergse Dorpsstraat 82",
    "sg:city":"Rotterdam",
    "sg:classifiers":[
        {
            "category":"Fast Food",
            "type":"Food & Drink"
        }
    ],
    "sg:phone":"+31 10 418 7078",
    "sg:postcode":"3054 GG",
    "sg:province":"Zuid-Holland",
    "sg:tags":[
        "afhaal",
        "restaurant"
    ],
    "wof:name":"Snackbar Ijspaleis",
    "wof:placetype":"venue"
},
  "geometry": {"coordinates":[4.494179,51.957054],"type":"Point"}
}