{
  "type": "Feature",
  "properties": {
    "addr:full":"Balsemienstr 12 Gouda South Holland 2803 JD",
    "addr:housenumber":"12",
    "addr:postcode":"2803 jd",
    "addr:street":"Balsemienstr",
    "iso:country":"NL",
    "sg:address":"Balsemienstr 12",
    "sg:city":"Gouda",
    "sg:orig_category":"Autorijscholen",
    "sg:phone":"+31 182 528 091",
    "sg:postcode":"2803 JD",
    "sg:province":"South Holland",
    "wof:name":"Sahin Ler",
    "wof:placetype":"venue"
},
  "geometry": {"coordinates":[4.691071,52.031479],"type":"Point"}
}