{
  "type": "Feature",
  "properties": {
    "addr:full":"Goldbergsngl 3 Leek Groningen 9351 CK",
    "addr:housenumber":"3",
    "addr:postcode":"9351 ck",
    "addr:street":"Goldbergsngl",
    "iso:country":"NL",
    "sg:address":"Goldbergsngl 3",
    "sg:city":"Leek",
    "sg:orig_category":"Administratie- En Boekhoudkantoren",
    "sg:phone":"+31 594 517 239",
    "sg:postcode":"9351 CK",
    "sg:province":"Groningen",
    "wof:name":"Admicom",
    "wof:placetype":"venue"
},
  "geometry": {"coordinates":[6.392695,53.162521],"type":"Point"}
}