{
  "type": "Feature",
  "properties": {
    "iso:country":"NL",
    "sg:address":"Veerhaven 7",
    "sg:city":"Rotterdam",
    "sg:orig_category":"Adviesbureaus Economie",
    "sg:phone":"+31 10 436 7947",
    "sg:postcode":"3016 CJ",
    "sg:province":"Zuid-Holland",
    "wof:name":"Ovohus Bv",
    "wof:placetype":"venue"
},
  "geometry": {"coordinates":[4.477865,51.907478],"type":"Point"}
}