{
  "type": "Feature",
  "properties": {
    "addr:full":"Postbus 154 Assen Drenthe 9400 AD",
    "addr:housenumber":"154",
    "addr:postcode":"9400 ad",
    "addr:street":"Postbus",
    "iso:country":"NL",
    "sg:address":"Postbus 154",
    "sg:city":"Assen",
    "sg:orig_category":"Adviesbureaus Bedrijfsorganisatie",
    "sg:phone":"+31 592 302 202",
    "sg:postcode":"9400 AD",
    "sg:province":"Drenthe",
    "sg:website":"http://www.benb-advies.nl",
    "wof:name":"B&B Organisatie Adviesbureau",
    "wof:placetype":"venue"
},
  "geometry": {"coordinates":[6.559506,52.994041],"type":"Point"}
}