{
  "type": "Feature",
  "properties": {
    "iso:country":"NL",
    "sg:address":"Prins Hendriklaan 32",
    "sg:city":"Utrecht",
    "sg:orig_category":"Werving And Selectie Van Tijdelijk Personeel And Uitzendkantoren",
    "sg:phone":"+31 30 251 3393",
    "sg:postcode":"3583 EN",
    "sg:province":"Utrecht",
    "wof:name":"Sedes",
    "wof:placetype":"venue"
},
  "geometry": {"coordinates":[5.1440057755,52.0864715576],"type":"Point"}
}