{
  "type": "Feature",
  "properties": {
    "addr:full":"Bremstr 153 Den Helder North Holland 1783 JD",
    "addr:housenumber":"153",
    "addr:postcode":"1783 jd",
    "iso:country":"NL",
    "sg:address":"Bremstr 153",
    "sg:city":"Den Helder",
    "sg:orig_category":"Verzekeringen - Verzekeringskantoren",
    "sg:phone":"+31 223 618 777",
    "sg:postcode":"1783 JD",
    "sg:province":"North Holland",
    "wof:name":"Kraak, J",
    "wof:placetype":"venue"
},
  "geometry": {"coordinates":[4.730431,52.941113],"type":"Point"}
}