{
  "type": "Feature",
  "properties": {
    "iso:country":"NL",
    "sg:address":"Mgr Savelbergstr 1",
    "sg:city":"Schinnen",
    "sg:orig_category":"Artiesten/Gezelschappen",
    "sg:phone":"+31 46 443 1960",
    "sg:postcode":"6365 BC",
    "sg:province":"Limburg",
    "wof:name":"Knarren, Piet",
    "wof:placetype":"venue"
},
  "geometry": {"coordinates":[5.888541,50.943497],"type":"Point"}
}