{
  "type": "Feature",
  "properties": {
    "iso:country":"NL",
    "sg:address":"Lucasbolwerk 6",
    "sg:city":"Utrecht",
    "sg:classifiers":[
        {
            "category":"Professional",
            "subcategory":"Management & Consulting",
            "type":"Services"
        }
    ],
    "sg:phone":"+31 30 242 7990",
    "sg:postcode":"3512 EG",
    "sg:province":"Utrecht",
    "sg:tags":[
        "relation",
        "adviesbureaus",
        "public"
    ],
    "sg:website":"http://www.paapstvandam.nl",
    "wof:name":"Paapstvandam",
    "wof:placetype":"venue"
},
  "geometry": {"coordinates":[5.126148,52.093311],"type":"Point"}
}