{
  "type": "Feature",
  "properties": {
    "iso:country":"NL",
    "sg:address":"Veerhaven",
    "sg:city":"Kats",
    "sg:orig_category":"Kunststoffen- Verwerkende Industrie",
    "sg:phone":"+31 113 600 270",
    "sg:postcode":"4485 PL",
    "sg:province":"Zeeland",
    "wof:name":"Rest Nautic Bv, Van Der",
    "wof:placetype":"venue"
},
  "geometry": {"coordinates":[3.887685,51.573685],"type":"Point"}
}