{
  "type": "Feature",
  "properties": {
    "addr:full":"Dissel 50 Nuland Noord-Brabant 5391 CM",
    "addr:housenumber":"50",
    "addr:postcode":"5391 cm",
    "addr:street":"Dissel",
    "iso:country":"NL",
    "sg:address":"Dissel 50",
    "sg:city":"Nuland",
    "sg:orig_category":"Accountants - Administratie- Consulenten En -Kantoren",
    "sg:phone":"+31 73 532 0405",
    "sg:postcode":"5391 CM",
    "sg:province":"Noord-Brabant",
    "wof:name":"Pro",
    "wof:placetype":"venue"
},
  "geometry": {"coordinates":[5.43759,51.722969],"type":"Point"}
}