{
  "type": "Feature",
  "properties": {
    "iso:country":"NL",
    "sg:address":"Philipsstraat 20",
    "sg:city":"Zoetermeer",
    "sg:orig_category":"Fruit And Groenten Gh",
    "sg:phone":"+31 79 331 4750",
    "sg:postcode":"2722 NA",
    "sg:province":"Zuid-Holland",
    "wof:name":"Cornelis Zwaan'S Exporthandel Bv",
    "wof:placetype":"venue"
},
  "geometry": {"coordinates":[4.511795,52.050587],"type":"Point"}
}