{
  "type": "Feature",
  "properties": {
    "iso:country":"NL",
    "sg:address":"Pomonaplein 52",
    "sg:city":"'S Gravenhage",
    "sg:orig_category":"Boekhouders",
    "sg:phone":"+31 70 368 4093",
    "sg:postcode":"2564 XS",
    "sg:province":"South Holland",
    "wof:name":"Duivesteijn Administratie- En Belastingadvieskanto",
    "wof:placetype":"venue"
},
  "geometry": {"coordinates":[4.259765,52.069237],"type":"Point"}
}