{
  "type": "Feature",
  "properties": {
    "addr:full":"Oudestraat 144 Kampen Overijssel 8261 CX",
    "addr:housenumber":"144",
    "addr:postcode":"8261 cx",
    "addr:street":"Oudestraat",
    "iso:country":"NL",
    "sg:address":"Oudestraat 144",
    "sg:city":"Kampen",
    "sg:orig_category":"Damesmodezaken",
    "sg:phone":"+31 38 332 7840",
    "sg:postcode":"8261 CX",
    "sg:province":"Overijssel",
    "wof:name":"Nastro Damesmode",
    "wof:placetype":"venue"
},
  "geometry": {"coordinates":[5.916102,52.559078],"type":"Point"}
}