{
  "type": "Feature",
  "properties": {
    "addr:full":"Dorpsstr 20 Renkum Gelderland 6871 AL",
    "addr:housenumber":"20",
    "addr:postcode":"6871",
    "addr:street":"Dorpsstr;Gelderland",
    "iso:country":"NL",
    "sg:address":"Dorpsstr 20",
    "sg:city":"Renkum",
    "sg:orig_category":"Administratie- En Boekhoudkantoren",
    "sg:phone":"+31 317 415 216",
    "sg:postcode":"6871 AL",
    "sg:province":"Gelderland",
    "wof:name":"Auwi Bv",
    "wof:placetype":"venue"
},
  "geometry": {"coordinates":[5.728227,51.971859],"type":"Point"}
}