{
  "type": "Feature",
  "properties": {
    "addr:full":"Oenenburgwg 314 Nunspeet Gelderland 8072 GT",
    "addr:housenumber":"314",
    "addr:postcode":"8072 gt",
    "addr:street":"Gelderland",
    "iso:country":"NL",
    "sg:address":"Oenenburgwg 314",
    "sg:city":"Nunspeet",
    "sg:orig_category":"Podotherapeuten",
    "sg:phone":"+31 341 254 792",
    "sg:postcode":"8072 GT",
    "sg:province":"Gelderland",
    "wof:name":"Schubert, C C M Van",
    "wof:placetype":"venue"
},
  "geometry": {"coordinates":[5.796102,52.388798],"type":"Point"}
}