{
  "type": "Feature",
  "properties": {
    "addr:full":"Zandbergenln 55 Amersfoort Utrecht 3817 GT",
    "addr:housenumber":"55",
    "addr:postcode":"3817 gt",
    "addr:street":"Zandbergenln",
    "iso:country":"NL",
    "sg:address":"Zandbergenln 55",
    "sg:city":"Amersfoort",
    "sg:orig_category":"Adviesbureaus Bedrijfsorganisatie",
    "sg:phone":"+31 33 472 7739",
    "sg:postcode":"3817 GT",
    "sg:province":"Utrecht",
    "wof:name":"Hessing Cons Ict, H",
    "wof:placetype":"venue"
},
  "geometry": {"coordinates":[5.391071,52.140545],"type":"Point"}
}