{
  "type": "Feature",
  "properties": {
    "addr:full":"Italielaan 147 Haarlem Noord-Holland 2034 BZ",
    "addr:housenumber":"147",
    "addr:postcode":"2034 bz",
    "addr:street":"Italielaan",
    "iso:country":"NL",
    "sg:address":"Italielaan 147",
    "sg:city":"Haarlem",
    "sg:classifiers":[
        {
            "category":"Food & Beverages",
            "subcategory":"Fruits & Vegetables",
            "type":"Retail Goods"
        }
    ],
    "sg:phone":"+31 23 533 6936",
    "sg:postcode":"2034 BZ",
    "sg:province":"Noord-Holland",
    "sg:tags":[
        "groenten"
    ],
    "wof:name":"Karaman",
    "wof:placetype":"venue"
},
  "geometry": {"coordinates":[4.648932,52.361622],"type":"Point"}
}