{
  "type": "Feature",
  "properties": {
    "addr:full":"Gentiaanstraat 4 Dedemsvaart Overijssel 7701 ES",
    "addr:housenumber":"4",
    "addr:postcode":"7701 es",
    "addr:street":"Gentiaanstraat",
    "iso:country":"NL",
    "sg:address":"Gentiaanstraat 4",
    "sg:city":"Dedemsvaart",
    "sg:orig_category":"Politie",
    "sg:phone":"+31 900 8844",
    "sg:postcode":"7701 ES",
    "sg:province":"Overijssel",
    "wof:name":"Politie Ijsselland Vechtdal Steunpunt Avereest",
    "wof:placetype":"venue"
},
  "geometry": {"coordinates":[6.459415,52.603127],"type":"Point"}
}