{
  "type": "Feature",
  "properties": {
    "addr:full":"Nieuwe Passage 37 Schiedam South Holland 3111 EG",
    "addr:housenumber":"37",
    "addr:postcode":"3111 eg",
    "addr:street":"Nieuwe Passage",
    "iso:country":"NL",
    "sg:address":"Nieuwe Passage 37",
    "sg:city":"Schiedam",
    "sg:classifiers":[
        {
            "category":"Shopping",
            "subcategory":"Clothing, Apparel, & Fashions",
            "type":"Retail Goods"
        }
    ],
    "sg:phone":"+31 10 426 7150",
    "sg:postcode":"3111 EG",
    "sg:province":"South Holland",
    "sg:tags":[
        "ondergoed",
        "lingerie"
    ],
    "wof:name":"Livera",
    "wof:placetype":"venue"
},
  "geometry": {"coordinates":[4.39816,51.918472],"type":"Point"}
}