{
  "type": "Feature",
  "properties": {
    "addr:full":"Utrechtsestraat 20 Ijsselstein Ut Utrecht 3401 CV",
    "addr:housenumber":"20",
    "addr:postcode":"3401 cv",
    "addr:street":"Utrechtsestraat",
    "iso:country":"NL",
    "sg:address":"Utrechtsestraat 20",
    "sg:city":"Ijsselstein Ut",
    "sg:orig_category":"Meubelzaken, Woning- And Keukeninrichting",
    "sg:phone":"+31 30 687 0321",
    "sg:postcode":"3401 CV",
    "sg:province":"Utrecht",
    "wof:name":"City Bed",
    "wof:placetype":"venue"
},
  "geometry": {"coordinates":[5.045081,52.020557],"type":"Point"}
}