{
  "type": "Feature",
  "properties": {
    "iso:country":"NL",
    "sg:address":"Bilderdijkstraat 177",
    "sg:city":"Amsterdam",
    "sg:orig_category":"Werving And Selectie Van Tijdelijk Personeel And Uitzendkantoren",
    "sg:phone":"+31 20 676 9699",
    "sg:postcode":"1053 KR",
    "sg:province":"Noord-Holland",
    "wof:name":"Primajob Uitzendbureau Bv",
    "wof:placetype":"venue"
},
  "geometry": {"coordinates":[4.8724942207,52.3670082092],"type":"Point"}
}