{
  "type": "Feature",
  "properties": {
    "addr:full":"Hendrikstraat 55 Dordrecht South Holland 3314 ZM",
    "addr:housenumber":"55",
    "addr:postcode":"3314 zm",
    "addr:street":"Hendrikstraat",
    "iso:country":"NL",
    "sg:address":"Hendrikstraat 55",
    "sg:city":"Dordrecht",
    "sg:orig_category":"Boekhouders",
    "sg:phone":"+31 78 614 2442",
    "sg:postcode":"3314 ZM",
    "sg:province":"South Holland",
    "wof:name":"W. Sneep",
    "wof:placetype":"venue"
},
  "geometry": {"coordinates":[4.675131,51.804142],"type":"Point"}
}