{
  "type": "Feature",
  "properties": {
    "addr:full":"Krugerplein 4 Amsterdam Noord-Holland 1091 KX",
    "addr:housenumber":"4",
    "addr:postcode":"1091 kx",
    "addr:street":"Krugerplein",
    "iso:country":"NL",
    "sg:address":"Krugerplein 4",
    "sg:city":"Amsterdam",
    "sg:orig_category":"Gespecialiseerde Voeding",
    "sg:phone":"+31 20 663 9301",
    "sg:postcode":"1091 KX",
    "sg:province":"Noord-Holland",
    "wof:name":"Tropisch Huis Chris",
    "wof:placetype":"venue"
},
  "geometry": {"coordinates":[4.919898,52.354443],"type":"Point"}
}