{
  "type": "Feature",
  "properties": {
    "addr:full":"Verlaatseweg 10 Steenwijk Overijssel 8331 PC",
    "addr:housenumber":"10",
    "addr:postcode":"8331 pc",
    "addr:street":"Verlaatseweg",
    "iso:country":"NL",
    "sg:address":"Verlaatseweg 10",
    "sg:city":"Steenwijk",
    "sg:classifiers":[
        {
            "category":"Education",
            "subcategory":"Preschool",
            "type":"Public Place"
        }
    ],
    "sg:phone":"+31 521 512 750",
    "sg:postcode":"8331 PC",
    "sg:province":"Overijssel",
    "sg:tags":[
        "kleuteronderwijs",
        "basis-"
    ],
    "wof:name":"Burgemeester Voetelinkschool Basisschool Voor So",
    "wof:placetype":"venue"
},
  "geometry": {"coordinates":[6.109698,52.784679],"type":"Point"}
}