{
  "type": "Feature",
  "properties": {
    "addr:full":"Promenadepln 107 Zoetermeer South Holland 2711 AB",
    "addr:housenumber":"107",
    "addr:postcode":"2711 ab",
    "iso:country":"NL",
    "sg:address":"Promenadepln 107",
    "sg:city":"Zoetermeer",
    "sg:orig_category":"Webdesign Bureaus",
    "sg:phone":"+31 6 24187798",
    "sg:postcode":"2711 AB",
    "sg:province":"South Holland",
    "sg:website":"http://www.woonstad.com",
    "wof:name":"Adnet",
    "wof:placetype":"venue"
},
  "geometry": {"coordinates":[4.489428997,52.0612373352],"type":"Point"}
}