{
  "type": "Feature",
  "properties": {
    "iso:country":"NL",
    "sg:address":"Sigarenmaker 1",
    "sg:city":"Eersel",
    "sg:orig_category":"Algemene Werktuigbouw",
    "sg:phone":"+31 497 518 735",
    "sg:postcode":"5521 DJ",
    "sg:province":"North Brabant",
    "wof:name":"Van Woerkum Lasindustrie",
    "wof:placetype":"venue"
},
  "geometry": {"coordinates":[5.31779,51.368343],"type":"Point"}
}