{
  "type": "Feature",
  "properties": {
    "addr:full":"V V Goghstr 44 Terneuzen Zeeland 4532 GR",
    "addr:housenumber":"44",
    "addr:postcode":"4532",
    "addr:street":"Goghstr",
    "iso:country":"NL",
    "sg:address":"V V Goghstr 44",
    "sg:city":"Terneuzen",
    "sg:orig_category":"Fotoreportages",
    "sg:phone":"+31 115 695 386",
    "sg:postcode":"4532 GR",
    "sg:province":"Zeeland",
    "sg:website":"http://www.fotograficus.nl",
    "wof:name":"Fermont, Fotograficus",
    "wof:placetype":"venue"
},
  "geometry": {"coordinates":[3.827559,51.338146],"type":"Point"}
}