{
  "type": "Feature",
  "properties": {
    "addr:full":"Nw Koekoekstr 86 Utrecht Utrecht 3514 EH",
    "addr:housenumber":"86",
    "addr:postcode":"3514 eh",
    "iso:country":"NL",
    "sg:address":"Nw Koekoekstr 86",
    "sg:city":"Utrecht",
    "sg:orig_category":"Adviesbureaus Bedrijfsorganisatie",
    "sg:phone":"+31 30 271 5217",
    "sg:postcode":"3514 EH",
    "sg:province":"Utrecht",
    "wof:name":"Simonscope",
    "wof:placetype":"venue"
},
  "geometry": {"coordinates":[5.120882,52.099674],"type":"Point"}
}