{
  "type": "Feature",
  "properties": {
    "addr:full":"Postbus 393 Zaandam Noord-Holland 1500 EJ",
    "addr:housenumber":"393",
    "addr:postcode":"1500 ej",
    "addr:street":"Postbus",
    "iso:country":"NL",
    "sg:address":"Postbus 393",
    "sg:city":"Zaandam",
    "sg:orig_category":"Timmerwerken",
    "sg:phone":"+31 6 53793822",
    "sg:postcode":"1500 EJ",
    "sg:province":"Noord-Holland",
    "wof:name":"Statim",
    "wof:placetype":"venue"
},
  "geometry": {"coordinates":[4.81295,52.44162],"type":"Point"}
}