{
  "type": "Feature",
  "properties": {
    "addr:full":"Burghardt Vd Berghstr 155 Nijmegen Gelderland 6512 DK",
    "addr:housenumber":"155",
    "addr:postcode":"6512 dk",
    "addr:street":"Gelderland",
    "iso:country":"NL",
    "sg:address":"Burghardt Vd Berghstr 155",
    "sg:city":"Nijmegen",
    "sg:orig_category":"Touringcars",
    "sg:phone":"+31 24 360 9791",
    "sg:postcode":"6512 DK",
    "sg:province":"Gelderland",
    "wof:name":"Kimada",
    "wof:placetype":"venue"
},
  "geometry": {"coordinates":[5.854823,51.839458],"type":"Point"}
}