{
  "type": "Feature",
  "properties": {
    "addr:full":"A V Spangensngl 33 Rotterdam Zuid-Holland 3054 CV",
    "addr:housenumber":"33",
    "addr:postcode":"3054 cv",
    "addr:street":"A;Spangensngl",
    "iso:country":"NL",
    "sg:address":"A V Spangensngl 33",
    "sg:city":"Rotterdam",
    "sg:orig_category":"Adviesbureaus Bedrijfsorganisatie",
    "sg:phone":"+31 10 422 1175",
    "sg:postcode":"3054 CV",
    "sg:province":"Zuid-Holland",
    "wof:name":"Brouwer, George",
    "wof:placetype":"venue"
},
  "geometry": {"coordinates":[4.49284,51.957539],"type":"Point"}
}