{
  "type": "Feature",
  "properties": {
    "addr:full":"Gedempte Nieuwesloot 47 Alkmaar Noord-Holland 1811 KP",
    "addr:housenumber":"47",
    "addr:postcode":"1811 kp",
    "addr:street":"Gedempte Nieuwesloot",
    "iso:country":"NL",
    "sg:address":"Gedempte Nieuwesloot 47",
    "sg:city":"Alkmaar",
    "sg:classifiers":[
        {
            "category":"Food & Beverages",
            "subcategory":"Fruits & Vegetables",
            "type":"Retail Goods"
        }
    ],
    "sg:phone":"+31 72 511 3735",
    "sg:postcode":"1811 KP",
    "sg:province":"Noord-Holland",
    "sg:tags":[
        "groenten"
    ],
    "wof:name":"Klaver Sip En Groen Paul",
    "wof:placetype":"venue"
},
  "geometry": {"coordinates":[4.749214,52.632195],"type":"Point"}
}