{
  "type": "Feature",
  "properties": {
    "addr:full":"Rubensstr 41 Voorthuizen Gelderland 3781 VK",
    "addr:housenumber":"41",
    "addr:postcode":"3781 vk",
    "addr:street":"Rubensstr;Gelderland",
    "iso:country":"NL",
    "sg:address":"Rubensstr 41",
    "sg:city":"Voorthuizen",
    "sg:orig_category":"Pluimveebedrijven En -Handelaren",
    "sg:phone":"+31 342 476 329",
    "sg:postcode":"3781 VK",
    "sg:province":"Gelderland",
    "wof:name":"Geurts, D W",
    "wof:placetype":"venue"
},
  "geometry": {"coordinates":[5.606951,52.19178],"type":"Point"}
}