{
  "type": "Feature",
  "properties": {
    "iso:country":"NL",
    "sg:address":"Lorentzkade 204",
    "sg:city":"Haarlem",
    "sg:orig_category":"Meubels And Huishoudapparatuur Gh",
    "sg:phone":"+31 23 524 9383",
    "sg:postcode":"2014 CE",
    "sg:province":"North Holland",
    "wof:name":"Jericos Global",
    "wof:placetype":"venue"
},
  "geometry": {"coordinates":[4.611409,52.374428],"type":"Point"}
}