{
  "type": "Feature",
  "properties": {
    "addr:full":"Industrieweg 9B Assendelft North Holland 1566 JN",
    "addr:housenumber":"9b",
    "addr:postcode":"1566 jn",
    "addr:street":"Industrieweg",
    "iso:country":"NL",
    "sg:address":"Industrieweg 9B",
    "sg:city":"Assendelft",
    "sg:orig_category":"Goederenvervoer Over De Weg",
    "sg:phone":"+31 75 628 9460",
    "sg:postcode":"1566 JN",
    "sg:province":"North Holland",
    "wof:name":"Betjes Transport Bv",
    "wof:placetype":"venue"
},
  "geometry": {"coordinates":[4.766358,52.48941],"type":"Point"}
}