{
  "type": "Feature",
  "properties": {
    "addr:full":"W Pyrmontstraat 6 Maasdijk Zuid-Holland 2676 AR",
    "addr:housenumber":"6",
    "addr:postcode":"2676",
    "addr:street":"W Pyrmontstraat",
    "iso:country":"NL",
    "sg:address":"W Pyrmontstraat 6",
    "sg:city":"Maasdijk",
    "sg:orig_category":"Damesmodezaken",
    "sg:phone":"+31 174 516 105",
    "sg:postcode":"2676 AR",
    "sg:province":"Zuid-Holland",
    "wof:name":"Boetiek Adyla",
    "wof:placetype":"venue"
},
  "geometry": {"coordinates":[4.215215,51.960949],"type":"Point"}
}