{
  "type": "Feature",
  "properties": {
    "addr:full":"Burchtstr 45 Bunde Limburg 6241 CR",
    "addr:housenumber":"45",
    "addr:postcode":"6241 cr",
    "addr:street":"Burchtstr",
    "iso:country":"NL",
    "sg:address":"Burchtstr 45",
    "sg:city":"Bunde",
    "sg:orig_category":"Autorijscholen",
    "sg:phone":"+31 43 364 7412",
    "sg:postcode":"6241 CR",
    "sg:province":"Limburg",
    "wof:name":"Jacobs, J",
    "wof:placetype":"venue"
},
  "geometry": {"coordinates":[5.730171,50.898846],"type":"Point"}
}