{
  "type": "Feature",
  "properties": {
    "addr:full":"Schildersstr 12 Diepenveen NL.08 7431 EC",
    "addr:housenumber":"12;nl.08",
    "addr:postcode":"7431 ec",
    "addr:street":"Schildersstr",
    "iso:country":"NL",
    "sg:address":"Schildersstr 12",
    "sg:city":"Diepenveen",
    "sg:orig_category":"Fotoreportages",
    "sg:phone":"+31 570 592 182",
    "sg:postcode":"7431 EC",
    "sg:province":"NL.08",
    "wof:name":"Kiers, B",
    "wof:placetype":"venue"
},
  "geometry": {"coordinates":[6.144039,52.291485],"type":"Point"}
}