{
  "type": "Feature",
  "properties": {
    "iso:country":"NL",
    "sg:address":"Oosthavenzyde 1",
    "sg:city":"Puttershoek",
    "sg:orig_category":"Koffie- En Theehuizen",
    "sg:phone":"+31 78 676 1453",
    "sg:postcode":"3297 LD",
    "sg:province":"Zuid-Holland",
    "wof:name":"Veerhuis, 'T",
    "wof:placetype":"venue"
},
  "geometry": {"coordinates":[4.577058,51.807133],"type":"Point"}
}