{
  "type": "Feature",
  "properties": {
    "iso:country":"NL",
    "sg:address":"Albert Cuijpstraat 9",
    "sg:city":"Hengelo Ov",
    "sg:orig_category":"Boekhouders",
    "sg:phone":"+31 74 242 3537",
    "sg:postcode":"7556 GD",
    "sg:province":"Overijssel",
    "wof:name":"W A Leurink",
    "wof:placetype":"venue"
},
  "geometry": {"coordinates":[6.786298,52.27351],"type":"Point"}
}