{
  "type": "Feature",
  "properties": {
    "iso:country":"NL",
    "sg:address":"Tongelresestraat 35",
    "sg:city":"Eindhoven",
    "sg:orig_category":"Fietshandelaren",
    "sg:phone":"+31 40 245 2588",
    "sg:postcode":"5613 DA",
    "sg:province":"Noord-Brabant",
    "wof:name":"Rijwielhandel Van De Wijgert",
    "wof:placetype":"venue"
},
  "geometry": {"coordinates":[5.492799,51.438419],"type":"Point"}
}