{
  "type": "Feature",
  "properties": {
    "addr:full":"Bankastr 10 Dordrecht Zuid-Holland 3312 GD",
    "addr:housenumber":"10",
    "addr:postcode":"3312 gd",
    "addr:street":"Bankastr",
    "iso:country":"NL",
    "sg:address":"Bankastr 10",
    "sg:city":"Dordrecht",
    "sg:orig_category":"Verenigingsgebouwen",
    "sg:phone":"+31 78 613 2607",
    "sg:postcode":"3312 GD",
    "sg:province":"Zuid-Holland",
    "wof:name":"Driesprong, De",
    "wof:placetype":"venue"
},
  "geometry": {"coordinates":[4.683441,51.81036],"type":"Point"}
}