{
  "type": "Feature",
  "properties": {
    "addr:full":"Bornsestraat 3 Hengelo Ov Overijssel 7556 BA",
    "addr:housenumber":"3",
    "addr:postcode":"7556 ba",
    "addr:street":"Bornsestraat;Ov",
    "iso:country":"NL",
    "sg:address":"Bornsestraat 3",
    "sg:city":"Hengelo Ov",
    "sg:orig_category":"Diverse Grafische Activiteiten",
    "sg:phone":"+31 74 255 6230",
    "sg:postcode":"7556 BA",
    "sg:province":"Overijssel",
    "wof:name":"Ahrend Repro",
    "wof:placetype":"venue"
},
  "geometry": {"coordinates":[6.791496,52.267818],"type":"Point"}
}