{
  "type": "Feature",
  "properties": {
    "addr:full":"Postbus 123 Schoonhoven Zuid-Holland 2870 AC",
    "addr:housenumber":"123",
    "addr:postcode":"2870 ac",
    "addr:street":"Postbus",
    "iso:country":"NL",
    "sg:address":"Postbus 123",
    "sg:city":"Schoonhoven",
    "sg:orig_category":"Verzekeringen - Verzekeringskantoren",
    "sg:phone":"+31 182 320 635",
    "sg:postcode":"2870 AC",
    "sg:province":"Zuid-Holland",
    "wof:name":"Team Bv",
    "wof:placetype":"venue"
},
  "geometry": {"coordinates":[4.85103,51.946453],"type":"Point"}
}