{
  "type": "Feature",
  "properties": {
    "addr:full":"Van Hardenbroekplein 8 Driebergen-Rijsenburg Utrecht 3971 BK",
    "addr:housenumber":"8",
    "addr:postcode":"3971 bk",
    "addr:street":"Van Hardenbroekplein",
    "iso:country":"NL",
    "sg:address":"Van Hardenbroekplein 8",
    "sg:city":"Driebergen-Rijsenburg",
    "sg:orig_category":"Bedrijfs- And Managementsconsultants",
    "sg:phone":"+31 343 531 409",
    "sg:postcode":"3971 BK",
    "sg:province":"Utrecht",
    "wof:name":"Schut Bv",
    "wof:placetype":"venue"
},
  "geometry": {"coordinates":[5.291346,52.058998],"type":"Point"}
}