{
  "type": "Feature",
  "properties": {
    "addr:full":"Witte Paal 37 Schagen Noord-Holland 1742 NL",
    "addr:housenumber":"37",
    "addr:postcode":"1742 nl",
    "addr:street":"Witte Paal",
    "iso:country":"NL",
    "sg:address":"Witte Paal 37",
    "sg:city":"Schagen",
    "sg:orig_category":"Verlichtingsartikelen - Groothandel",
    "sg:phone":"+31 224 290 979",
    "sg:postcode":"1742 NL",
    "sg:province":"Noord-Holland",
    "wof:name":"Hartog, Den",
    "wof:placetype":"venue"
},
  "geometry": {"coordinates":[4.809598,52.774055],"type":"Point"}
}