{
  "type": "Feature",
  "properties": {
    "addr:full":"Bieberglaan 60 Breda North Brabant 4834 ML",
    "addr:housenumber":"60",
    "addr:postcode":"4834 ml",
    "addr:street":"Bieberglaan",
    "iso:country":"NL",
    "sg:address":"Bieberglaan 60",
    "sg:city":"Breda",
    "sg:orig_category":"Vertaal- And Tolkenbureaus",
    "sg:phone":"+31 76 565 3748",
    "sg:postcode":"4834 ML",
    "sg:province":"North Brabant",
    "wof:name":"G. Keizer",
    "wof:placetype":"venue"
},
  "geometry": {"coordinates":[4.788428,51.557888],"type":"Point"}
}