{
  "type": "Feature",
  "properties": {
    "addr:full":"Rijssenseweg 3 Holten Overijssel 7451 RC",
    "addr:housenumber":"3",
    "addr:postcode":"7451 rc",
    "addr:street":"Rijssenseweg",
    "iso:country":"NL",
    "sg:address":"Rijssenseweg 3",
    "sg:city":"Holten",
    "sg:orig_category":"Houtverwerking",
    "sg:phone":"+31 548 362 071",
    "sg:postcode":"7451 RC",
    "sg:province":"Overijssel",
    "wof:name":"J.A. Wansink",
    "wof:placetype":"venue"
},
  "geometry": {"coordinates":[6.43597,52.283451],"type":"Point"}
}