{
  "type": "Feature",
  "properties": {
    "addr:full":"Swarte Wyk 32 Drachtstercompagnie Friesland 9222 LW",
    "addr:housenumber":"32",
    "addr:postcode":"9222 lw",
    "addr:street":"Swarte Wyk",
    "iso:country":"NL",
    "sg:address":"Swarte Wyk 32",
    "sg:city":"Drachtstercompagnie",
    "sg:orig_category":"Diverse Consumentenartikelen Gh",
    "sg:phone":"+31 512 341 077",
    "sg:postcode":"9222 LW",
    "sg:province":"Friesland",
    "wof:name":"P. Bosma",
    "wof:placetype":"venue"
},
  "geometry": {"coordinates":[6.142026,53.136372],"type":"Point"}
}