{
  "type": "Feature",
  "properties": {
    "addr:full":"Poldermolen 2 Papendrecht Zuid-Holland 3352 TH",
    "addr:housenumber":"2",
    "addr:postcode":"3352 th",
    "addr:street":"Poldermolen",
    "iso:country":"NL",
    "sg:address":"Poldermolen 2",
    "sg:city":"Papendrecht",
    "sg:orig_category":"Woningbouwverenigingen",
    "sg:phone":"+31 78 644 2222",
    "sg:postcode":"3352 TH",
    "sg:province":"Zuid-Holland",
    "wof:name":"Woningstichting Papendrecht",
    "wof:placetype":"venue"
},
  "geometry": {"coordinates":[4.6900429726,51.8371124268],"type":"Point"}
}