{
  "type": "Feature",
  "properties": {
    "addr:full":"Dorrewold 11 Gorssel Gelderland 7213 TG",
    "addr:housenumber":"11",
    "addr:postcode":"7213 tg",
    "addr:street":"Dorrewold;Gelderland",
    "iso:country":"NL",
    "sg:address":"Dorrewold 11",
    "sg:city":"Gorssel",
    "sg:classifiers":[
        {
            "category":"Personal",
            "subcategory":"Nail Salon",
            "type":"Services"
        }
    ],
    "sg:phone":"+31 575 494 926",
    "sg:postcode":"7213 TG",
    "sg:province":"Gelderland",
    "sg:tags":[
        "pedicure"
    ],
    "wof:name":"Nijhof, Marieke",
    "wof:placetype":"venue"
},
  "geometry": {"coordinates":[6.203957,52.208546],"type":"Point"}
}