{
  "type": "Feature",
  "properties": {
    "addr:full":"Julianastraat 10 Dedemsvaart Overijssel 7701 GL",
    "addr:housenumber":"10",
    "addr:postcode":"7701 gl",
    "addr:street":"Julianastraat",
    "iso:country":"NL",
    "sg:address":"Julianastraat 10",
    "sg:city":"Dedemsvaart",
    "sg:orig_category":"Juweliers",
    "sg:phone":"+31 523 612 596",
    "sg:postcode":"7701 GL",
    "sg:province":"Overijssel",
    "wof:name":"Juwelier P. Brinkhuis",
    "wof:placetype":"venue"
},
  "geometry": {"coordinates":[6.458029,52.600391],"type":"Point"}
}