{
  "type": "Feature",
  "properties": {
    "addr:full":"Kanaalstraat 2 Leiden South Holland 2313 NR",
    "addr:housenumber":"2",
    "addr:postcode":"2313 nr",
    "addr:street":"Kanaalstraat",
    "iso:country":"NL",
    "sg:address":"Kanaalstraat 2",
    "sg:city":"Leiden",
    "sg:orig_category":"Wegen And Sportterreinen",
    "sg:phone":"+31 71 512 3777",
    "sg:postcode":"2313 NR",
    "sg:province":"South Holland",
    "wof:name":"W. Blansjaar",
    "wof:placetype":"venue"
},
  "geometry": {"coordinates":[4.5115008354,52.1548271179],"type":"Point"}
}