{
  "type": "Feature",
  "properties": {
    "addr:full":"Zuivelstr 5 Baarlo Lb Limburg 5991 AN",
    "addr:housenumber":"5",
    "addr:postcode":"lb;5991 an",
    "addr:street":"Zuivelstr",
    "iso:country":"NL",
    "sg:address":"Zuivelstr 5",
    "sg:city":"Baarlo Lb",
    "sg:orig_category":"Bejaarden - Verzorgingstehuizen",
    "sg:phone":"+31 77 477 2700",
    "sg:postcode":"5991 AN",
    "sg:province":"Limburg",
    "sg:website":"http://www.zorggroep-noord-limburg.nl",
    "wof:name":"Baarlo",
    "wof:placetype":"venue"
},
  "geometry": {"coordinates":[6.093768,51.332508],"type":"Point"}
}