{
  "type": "Feature",
  "properties": {
    "iso:country":"NL",
    "sg:address":"Pastoor Geenenstraat 38",
    "sg:city":"Baarlo Lb",
    "sg:classifiers":[
        {
            "category":"Education",
            "subcategory":"Preschool",
            "type":"Public Place"
        }
    ],
    "sg:phone":"+31 77 477 8225",
    "sg:postcode":"5991 BJ",
    "sg:province":"Limburg",
    "sg:tags":[
        "kleuteronderwijs",
        "basis-"
    ],
    "wof:name":"Basisschool 'T Kempke",
    "wof:placetype":"venue"
},
  "geometry": {"coordinates":[6.088565,51.32877],"type":"Point"}
}