{
  "type": "Feature",
  "properties": {
    "addr:full":"Ijsselsteen 1 Wijk Bij Duurstede Utrecht 3961 GA",
    "addr:housenumber":"1",
    "addr:postcode":"3961 ga",
    "addr:street":"Ijsselsteen",
    "iso:country":"NL",
    "sg:address":"Ijsselsteen 1",
    "sg:city":"Wijk Bij Duurstede",
    "sg:orig_category":"Diverse Grafische Activiteiten",
    "sg:phone":"+31 343 578 525",
    "sg:postcode":"3961 GA",
    "sg:province":"Utrecht",
    "wof:name":"Shiva Visual Design",
    "wof:placetype":"venue"
},
  "geometry": {"coordinates":[5.327192,51.976376],"type":"Point"}
}