{
  "type": "Feature",
  "properties": {
    "iso:country":"NL",
    "sg:address":"Mt Ondinaweg 24",
    "sg:city":"Amsterdam",
    "sg:orig_category":"Metaalbekleding And -Behandeling",
    "sg:phone":"+31 20 631 5807",
    "sg:postcode":"1033 RG",
    "sg:province":"Noord-Holland",
    "wof:name":"R.G. Prein",
    "wof:placetype":"venue"
},
  "geometry": {"coordinates":[4.89262,52.401516],"type":"Point"}
}