{
  "type": "Feature",
  "properties": {
    "iso:country":"NL",
    "sg:address":"Dillenburgln 2A",
    "sg:city":"Soest",
    "sg:orig_category":"Kinderkleding",
    "sg:phone":"+31 35 602 9206",
    "sg:postcode":"3761 JA",
    "sg:province":"Utrecht",
    "wof:name":"Beau & Belle",
    "wof:placetype":"venue"
},
  "geometry": {"coordinates":[5.295351,52.185947],"type":"Point"}
}