{
  "type": "Feature",
  "properties": {
    "addr:full":"Dorpsstraat 78-80 Oegstgeest Zuid-Holland 2343 BB",
    "addr:housenumber":"78-80",
    "addr:postcode":"2343 bb",
    "addr:street":"Dorpsstraat",
    "iso:country":"NL",
    "sg:address":"Dorpsstraat 78-80",
    "sg:city":"Oegstgeest",
    "sg:orig_category":"Glaszetten",
    "sg:phone":"+31 71 519 0248",
    "sg:postcode":"2343 BB",
    "sg:province":"Zuid-Holland",
    "wof:name":"Atelier De L Art Glas In Lood",
    "wof:placetype":"venue"
},
  "geometry": {"coordinates":[4.467745,52.191116],"type":"Point"}
}