{
  "type": "Feature",
  "properties": {
    "iso:country":"NL",
    "sg:address":"Ekkersrijt 1201",
    "sg:city":"Son",
    "sg:orig_category":"Kantoorapparatuur Gh",
    "sg:phone":"+31 499 477 075",
    "sg:postcode":"5692 AG",
    "sg:province":"Texas",
    "wof:name":"Civo Bv",
    "wof:placetype":"venue"
},
  "geometry": {"coordinates":[-101.93762207029999,35.1896209717],"type":"Point"}
}