{
  "type": "Feature",
  "properties": {
    "addr:full":"G Borgesiusstraat 8 Zaandijk North Holland 1544 RN",
    "addr:housenumber":"8",
    "addr:postcode":"1544 rn",
    "addr:street":"Borgesiusstraat",
    "iso:country":"NL",
    "sg:address":"G Borgesiusstraat 8",
    "sg:city":"Zaandijk",
    "sg:orig_category":"Boekhouders",
    "sg:phone":"+31 75 771 3567",
    "sg:postcode":"1544 RN",
    "sg:province":"North Holland",
    "wof:name":"R. Koopman",
    "wof:placetype":"venue"
},
  "geometry": {"coordinates":[4.810993,52.473385],"type":"Point"}
}