{
  "type": "Feature",
  "properties": {
    "addr:full":"Bergerslag 2 Staphorst NL.08 7951 DS",
    "addr:housenumber":"2;nl.08",
    "addr:postcode":"7951 ds",
    "addr:street":"Bergerslag",
    "iso:country":"NL",
    "sg:address":"Bergerslag 2",
    "sg:city":"Staphorst",
    "sg:classifiers":[
        {
            "category":"Retail",
            "subcategory":"Photofinishing",
            "type":"Services"
        }
    ],
    "sg:phone":"+31 522 463 563",
    "sg:postcode":"7951 DS",
    "sg:province":"NL.08",
    "sg:tags":[
        "foto",
        "film"
    ],
    "wof:name":"Vof Foto Schuurman",
    "wof:placetype":"venue"
},
  "geometry": {"coordinates":[6.208768,52.64579],"type":"Point"}
}