{
  "type": "Feature",
  "properties": {
    "iso:country":"NL",
    "sg:address":"Bergerslag 2",
    "sg:city":"Staphorst",
    "sg:classifiers":[
        {
            "category":"Retail",
            "subcategory":"Photofinishing",
            "type":"Services"
        }
    ],
    "sg:phone":"+31 522 463 563",
    "sg:postcode":"7951 DS",
    "sg:province":"NL.08",
    "sg:tags":[
        "foto",
        "film"
    ],
    "wof:name":"Vof Foto Schuurman",
    "wof:placetype":"venue"
},
  "geometry": {"coordinates":[6.208768,52.64579],"type":"Point"}
}