{
  "type": "Feature",
  "properties": {
    "addr:full":"Waalstr 58 Amsterdam North Holland 1078 BX",
    "addr:housenumber":"58",
    "addr:postcode":"1078 bx",
    "addr:street":"Waalstr",
    "iso:country":"NL",
    "sg:address":"Waalstr 58",
    "sg:city":"Amsterdam",
    "sg:orig_category":"Woningbureaus",
    "sg:phone":"+31 20 672 1840",
    "sg:postcode":"1078 BX",
    "sg:province":"North Holland",
    "sg:website":"http://www.apartmentservices.nl",
    "wof:name":"A1 Apartment Services",
    "wof:placetype":"venue"
},
  "geometry": {"coordinates":[4.9004049301,52.3447418213],"type":"Point"}
}