{
  "type": "Feature",
  "properties": {
    "iso:country":"NL",
    "sg:address":"Drievogelstraat 136",
    "sg:city":"Kerkrade",
    "sg:orig_category":"Goederenvervoer Over De Weg",
    "sg:phone":"+31 45 541 4647",
    "sg:postcode":"6466 GR",
    "sg:province":"Limburg",
    "wof:name":"Internationaal Transportbedr L. Van Loo Bv",
    "wof:placetype":"venue"
},
  "geometry": {"coordinates":[6.015432,50.85281],"type":"Point"}
}