{
  "type": "Feature",
  "properties": {
    "addr:full":"Gerrit Van Der Veenstr 112 Amsterdam North Holland 1077 EN",
    "addr:housenumber":"112",
    "addr:postcode":"1077 en",
    "addr:street":"Gerrit Van Der Veenstr",
    "iso:country":"NL",
    "sg:address":"Gerrit Van Der Veenstr 112",
    "sg:city":"Amsterdam",
    "sg:orig_category":"Public Relationbureaus",
    "sg:phone":"+31 20 662 5021",
    "sg:postcode":"1077 EN",
    "sg:province":"North Holland",
    "wof:name":"Tez Management Consulting Bv",
    "wof:placetype":"venue"
},
  "geometry": {"coordinates":[4.871273,52.34893],"type":"Point"}
}