{
  "type": "Feature",
  "properties": {
    "addr:full":"Burg Ryndersln 20 Amstelveen Noord-Holland 1185 MC",
    "addr:housenumber":"20",
    "addr:postcode":"1185 mc",
    "addr:street":"Burg",
    "iso:country":"NL",
    "sg:address":"Burg Ryndersln 20",
    "sg:city":"Amstelveen",
    "sg:orig_category":"Architecten En Architectenbureaus",
    "sg:phone":"+31 20 656 7108",
    "sg:postcode":"1185 MC",
    "sg:province":"Noord-Holland",
    "wof:name":"Schalk Bv, Marcel Van Der",
    "wof:placetype":"venue"
},
  "geometry": {"coordinates":[4.862868,52.29929],"type":"Point"}
}