{
  "type": "Feature",
  "properties": {
    "addr:full":"Ommerenveldsewg 29 Ommeren Gelderland 4032 NA",
    "addr:housenumber":"29",
    "addr:postcode":"4032 na",
    "addr:street":"Ommerenveldsewg;Gelderland",
    "iso:country":"NL",
    "sg:address":"Ommerenveldsewg 29",
    "sg:city":"Ommeren",
    "sg:classifiers":[
        {
            "category":"Retail",
            "subcategory":"Storage",
            "type":"Services"
        }
    ],
    "sg:phone":"+31 344 601 702",
    "sg:postcode":"4032 NA",
    "sg:province":"Gelderland",
    "sg:tags":[
        "op-",
        "en",
        "overslagbedrijven"
    ],
    "wof:name":"Stroom Bv, Bas Van Der",
    "wof:placetype":"venue"
},
  "geometry": {"coordinates":[5.48355,51.934986],"type":"Point"}
}