{
  "type": "Feature",
  "properties": {
    "iso:country":"NL",
    "sg:address":"Lupinehof 13",
    "sg:city":"Rotterdam",
    "sg:orig_category":"Verbandstoffen - Fabrieken En Groothandel",
    "sg:phone":"+31 10 418 5136",
    "sg:postcode":"3053 HT",
    "sg:province":"Zuid-Holland",
    "wof:name":"Medikit Care Bv",
    "wof:placetype":"venue"
},
  "geometry": {"coordinates":[4.46724,51.961582],"type":"Point"}
}