{
  "type": "Feature",
  "properties": {
    "addr:full":"Antoniusstraat 3 Tilburg North Brabant 5038 DK",
    "addr:housenumber":"3",
    "addr:postcode":"5038 dk",
    "addr:street":"Antoniusstraat",
    "iso:country":"NL",
    "sg:address":"Antoniusstraat 3",
    "sg:city":"Tilburg",
    "sg:orig_category":"Kinderopvang",
    "sg:phone":"+31 13 571 4114",
    "sg:postcode":"5038 DK",
    "sg:province":"North Brabant",
    "wof:name":"Bert En Ernie",
    "wof:placetype":"venue"
},
  "geometry": {"coordinates":[5.084222,51.558743],"type":"Point"}
}