{
  "type": "Feature",
  "properties": {
    "addr:full":"Grote Spuistraat 10 Dordrecht Zuid-Holland 3311 GE",
    "addr:housenumber":"10",
    "addr:postcode":"3311",
    "addr:street":"Grote Spuistraat",
    "iso:country":"NL",
    "sg:address":"Grote Spuistraat 10",
    "sg:city":"Dordrecht",
    "sg:orig_category":"Zuivelproducten",
    "sg:phone":"+31 78 614 0360",
    "sg:postcode":"3311 GE",
    "sg:province":"Zuid-Holland",
    "wof:name":"Zuivelhandel P.F. Ottevanger Vof",
    "wof:placetype":"venue"
},
  "geometry": {"coordinates":[4.664,51.813202],"type":"Point"}
}