{
  "type": "Feature",
  "properties": {
    "addr:full":"Zwartewg 105 Enschede Overijssel 7532 XL",
    "addr:housenumber":"105",
    "addr:postcode":"7532 xl",
    "iso:country":"NL",
    "sg:address":"Zwartewg 105",
    "sg:city":"Enschede",
    "sg:orig_category":"Ventilatiesystemen",
    "sg:phone":"+31 53 461 1419",
    "sg:postcode":"7532 XL",
    "sg:province":"Overijssel",
    "sg:website":"http://www.kleinsmit.nl",
    "wof:name":"Kleinsmit Bv",
    "wof:placetype":"venue"
},
  "geometry": {"coordinates":[6.964809,52.218861],"type":"Point"}
}