{
  "type": "Feature",
  "properties": {
    "addr:full":"Lambertusstraat 3A Etten-Leur North Brabant 4872 XA",
    "addr:housenumber":"3a",
    "addr:postcode":"4872 xa",
    "addr:street":"Lambertusstraat",
    "iso:country":"NL",
    "sg:address":"Lambertusstraat 3A",
    "sg:city":"Etten-Leur",
    "sg:orig_category":"Kinderopvang Behalve Thuis",
    "sg:phone":"+31 76 503 7353",
    "sg:postcode":"4872 XA",
    "sg:province":"North Brabant",
    "wof:name":"Dagcentrum Liesbos",
    "wof:placetype":"venue"
},
  "geometry": {"coordinates":[4.635919,51.57246],"type":"Point"}
}