{
  "type": "Feature",
  "properties": {
    "addr:full":"Deweverstr 14 Nuth Limburg 6361 BX",
    "addr:housenumber":"14",
    "addr:postcode":"6361 bx",
    "addr:street":"Deweverstr",
    "iso:country":"NL",
    "sg:address":"Deweverstr 14",
    "sg:city":"Nuth",
    "sg:orig_category":"Tegelwerken",
    "sg:phone":"+31 45 524 1257",
    "sg:postcode":"6361 BX",
    "sg:province":"Limburg",
    "wof:name":"Pascal Van De Wetering",
    "wof:placetype":"venue"
},
  "geometry": {"coordinates":[5.88709,50.918404],"type":"Point"}
}