{
  "type": "Feature",
  "properties": {
    "addr:full":"Verzetsstryderspk 10 Apeldoorn Gelderland 7316 CM",
    "addr:housenumber":"10",
    "addr:postcode":"7316 cm",
    "addr:street":"Verzetsstryderspk;Gelderland",
    "iso:country":"NL",
    "sg:address":"Verzetsstryderspk 10",
    "sg:city":"Apeldoorn",
    "sg:orig_category":"Evenementenverzorging",
    "sg:phone":"+31 55 526 8887",
    "sg:postcode":"7316 CM",
    "sg:province":"Gelderland",
    "wof:name":"Amazing Events Bv",
    "wof:placetype":"venue"
},
  "geometry": {"coordinates":[5.967202,52.223095],"type":"Point"}
}