{
  "type": "Feature",
  "properties": {
    "iso:country":"NL",
    "sg:address":"Kerkstraat 109",
    "sg:city":"Alblasserdam",
    "sg:orig_category":"Boekhouders",
    "sg:phone":"+31 78 691 5450",
    "sg:postcode":"2951 GH",
    "sg:province":"Zuid-Holland",
    "wof:name":"B. Herwig Adm En Assurantie Bemiddeling",
    "wof:placetype":"venue"
},
  "geometry": {"coordinates":[4.664621,51.861095],"type":"Point"}
}