{
  "type": "Feature",
  "properties": {
    "addr:full":"Marktpln 1 Oud Beyerland South Holland 3261 BZ",
    "addr:housenumber":"1",
    "addr:postcode":"3261 bz",
    "addr:street":"Marktpln;Oud Beyerland",
    "iso:country":"NL",
    "sg:address":"Marktpln 1",
    "sg:city":"Oud Beyerland",
    "sg:orig_category":"Bloemen En Planten",
    "sg:phone":"+31 186 621 821",
    "sg:postcode":"3261 BZ",
    "sg:province":"South Holland",
    "wof:name":"Bloemenreus, De",
    "wof:placetype":"venue"
},
  "geometry": {"coordinates":[4.413165,51.82663],"type":"Point"}
}