{
  "type": "Feature",
  "properties": {
    "addr:full":"Kerkstr 11 Oss Noord-Brabant 5341 BK",
    "addr:housenumber":"11",
    "addr:postcode":"5341 bk",
    "addr:street":"Kerkstr",
    "iso:country":"NL",
    "sg:address":"Kerkstr 11",
    "sg:city":"Oss",
    "sg:orig_category":"Verlichting",
    "sg:phone":"+31 412 647 701",
    "sg:postcode":"5341 BK",
    "sg:province":"Noord-Brabant",
    "wof:name":"Louw Van De Zanden Bv, De",
    "wof:placetype":"venue"
},
  "geometry": {"coordinates":[-91.21601099999999,44.580002],"type":"Point"}
}