{
  "type": "Feature",
  "properties": {
    "addr:full":"Reguliersteeg 26 Utrecht Utrecht 3512 NT",
    "addr:housenumber":"26",
    "addr:postcode":"3512 nt",
    "addr:street":"Reguliersteeg",
    "iso:country":"NL",
    "sg:address":"Reguliersteeg 26",
    "sg:city":"Utrecht",
    "sg:orig_category":"Juridische Dienstverlening",
    "sg:phone":"+31 30 231 6840",
    "sg:postcode":"3512 NT",
    "sg:province":"Utrecht",
    "wof:name":"Geenen Juridisch-Commerciele Dienstverle",
    "wof:placetype":"venue"
},
  "geometry": {"coordinates":[5.122847,52.087524],"type":"Point"}
}