{
  "type": "Feature",
  "properties": {
    "addr:full":"Gronsvelderwg . Maastricht Limburg 6229 VN",
    "addr:postcode":"6229 vn",
    "addr:street":"Gronsvelderwg",
    "iso:country":"NL",
    "sg:address":"Gronsvelderwg .",
    "sg:city":"Maastricht",
    "sg:orig_category":"Sportverenigingen En Ontspannings- Verenigingen",
    "sg:phone":"+31 43 361 6164",
    "sg:postcode":"6229 VN",
    "sg:province":"Limburg",
    "wof:name":"Heugem Ltv Tennisver",
    "wof:placetype":"venue"
},
  "geometry": {"coordinates":[5.711061,50.825806],"type":"Point"}
}