{
  "type": "Feature",
  "properties": {
    "addr:full":"Postbus 548 Schiedam Zuid-Holland 3100 AM",
    "addr:housenumber":"548",
    "addr:postcode":"3100",
    "addr:street":"Postbus",
    "iso:country":"NL",
    "sg:address":"Postbus 548",
    "sg:city":"Schiedam",
    "sg:orig_category":"Gasapparaten En -Artikelen - Fabrieken En Groothandel",
    "sg:phone":"+31 10 246 0495",
    "sg:postcode":"3100 AM",
    "sg:province":"Zuid-Holland",
    "wof:name":"Joc",
    "wof:placetype":"venue"
},
  "geometry": {"coordinates":[4.39816,51.918449],"type":"Point"}
}