{
  "type": "Feature",
  "properties": {
    "addr:full":"D M Viscontiln 125 De Meern Utrecht 3453 ST",
    "addr:housenumber":"125",
    "addr:postcode":"3453 st",
    "iso:country":"NL",
    "sg:address":"D M Viscontiln 125",
    "sg:city":"De Meern",
    "sg:orig_category":"Administratie- En Boekhoudkantoren",
    "sg:phone":"+31 30 662 1626",
    "sg:postcode":"3453 ST",
    "sg:province":"Utrecht",
    "wof:name":"Pastoors",
    "wof:placetype":"venue"
},
  "geometry": {"coordinates":[5.0138,52.081131],"type":"Point"}
}