{
  "type": "Feature",
  "properties": {
    "iso:country":"NL",
    "sg:address":"Roosmarijnhof 26",
    "sg:city":"Duivendrecht",
    "sg:orig_category":"Schilderwerk",
    "sg:phone":"+31 20 699 3218",
    "sg:postcode":"1115 DW",
    "sg:province":"Noord-Holland",
    "wof:name":"R.L. Thomas",
    "wof:placetype":"venue"
},
  "geometry": {"coordinates":[4.935765,52.328777],"type":"Point"}
}