{
  "type": "Feature",
  "properties": {
    "addr:full":"Lagedijk 12 Enter Overijssel 7468 EZ",
    "addr:housenumber":"12",
    "addr:postcode":"7468 ez",
    "addr:street":"Lagedijk",
    "iso:country":"NL",
    "sg:address":"Lagedijk 12",
    "sg:city":"Enter",
    "sg:orig_category":"Juridische Dienstverlening",
    "sg:phone":"+31 547 383 810",
    "sg:postcode":"7468 EZ",
    "sg:province":"Overijssel",
    "wof:name":"Van Der Kraats Adviesbureau",
    "wof:placetype":"venue"
},
  "geometry": {"coordinates":[-76.841904,40.463078],"type":"Point"}
}