{
  "type": "Feature",
  "properties": {
    "addr:full":"Reewg O 27 Dordrecht Zuid-Holland 3312 CK",
    "addr:housenumber":"27",
    "addr:postcode":"3312 ck",
    "iso:country":"NL",
    "sg:address":"Reewg O 27",
    "sg:city":"Dordrecht",
    "sg:classifiers":[
        {
            "category":"Food & Beverages",
            "subcategory":"Bakery",
            "type":"Retail Goods"
        }
    ],
    "sg:phone":"+31 78 613 4702",
    "sg:postcode":"3312 CK",
    "sg:province":"Zuid-Holland",
    "sg:tags":[
        "brood",
        "en",
        "banket"
    ],
    "wof:name":"Breggen Vof, Van Der",
    "wof:placetype":"venue"
},
  "geometry": {"coordinates":[4.656506,51.811916],"type":"Point"}
}