{
  "type": "Feature",
  "properties": {
    "addr:full":"Spanjaardstraat 68 Middelburg Zeeland 4331 ES",
    "addr:housenumber":"68",
    "addr:postcode":"4331 es",
    "addr:street":"Spanjaardstraat",
    "iso:country":"NL",
    "sg:address":"Spanjaardstraat 68",
    "sg:city":"Middelburg",
    "sg:orig_category":"Boekenuitgeverijen",
    "sg:phone":"+31 118 615 217",
    "sg:postcode":"4331 ES",
    "sg:province":"Zeeland",
    "wof:name":"Uitgeverij Reclad",
    "wof:placetype":"venue"
},
  "geometry": {"coordinates":[3.617744,51.501938],"type":"Point"}
}