{
  "type": "Feature",
  "properties": {
    "addr:full":"Dorpsstr 81 St Willebrord Noord-Brabant 4711 NE",
    "addr:housenumber":"81",
    "addr:postcode":"4711 ne",
    "addr:street":"Dorpsstr",
    "iso:country":"NL",
    "sg:address":"Dorpsstr 81",
    "sg:city":"St Willebrord",
    "sg:orig_category":"Kantoormachines",
    "sg:phone":"+31 165 383 102",
    "sg:postcode":"4711 NE",
    "sg:province":"Noord-Brabant",
    "wof:name":"Difra",
    "wof:placetype":"venue"
},
  "geometry": {"coordinates":[4.5912971497,51.5484924316],"type":"Point"}
}