{
  "type": "Feature",
  "properties": {
    "addr:full":"B Boschsngl 14 Numansdorp Zuid-Holland 3281 SK",
    "addr:housenumber":"14",
    "addr:street":"3281",
    "iso:country":"NL",
    "sg:address":"B Boschsngl 14",
    "sg:city":"Numansdorp",
    "sg:orig_category":"Woninginrichting",
    "sg:phone":"+31 6 51400742",
    "sg:postcode":"3281 SK",
    "sg:province":"Zuid-Holland",
    "wof:name":"Chabo",
    "wof:placetype":"venue"
},
  "geometry": {"coordinates":[4.4383449554,51.7313690186],"type":"Point"}
}