{
  "type": "Feature",
  "properties": {
    "iso:country":"NL",
    "sg:address":"Goudsmidsstr 18",
    "sg:city":"Hoorn Nh",
    "sg:orig_category":"Schilders",
    "sg:phone":"+31 229 218 726",
    "sg:postcode":"1624 VL",
    "sg:province":"Noord-Holland",
    "wof:name":"Veen, R Van Der",
    "wof:placetype":"venue"
},
  "geometry": {"coordinates":[5.062074,52.651127],"type":"Point"}
}