{
  "type": "Feature",
  "properties": {
    "addr:full":"Snydersstr 16 Lelystad NL. 8224 AA",
    "addr:housenumber":"16",
    "addr:postcode":"8224 aa",
    "addr:street":"Snydersstr;Nl.",
    "iso:country":"NL",
    "sg:address":"Snydersstr 16",
    "sg:city":"Lelystad",
    "sg:orig_category":"Boeken En Tijdschriften - Groothandel",
    "sg:phone":"+31 320 243 663",
    "sg:postcode":"8224 AA",
    "sg:province":"NL.",
    "wof:name":"Fakkel, De",
    "wof:placetype":"venue"
},
  "geometry": {"coordinates":[5.483567,52.519222],"type":"Point"}
}