{
  "type": "Feature",
  "properties": {
    "addr:full":"St Willibrordstr 18 Oosterhout Nb Noord-Brabant 4902 XS",
    "addr:housenumber":"18",
    "addr:postcode":"4902 xs",
    "iso:country":"NL",
    "sg:address":"St Willibrordstr 18",
    "sg:city":"Oosterhout Nb",
    "sg:classifiers":[
        {
            "category":"Personal",
            "subcategory":"Nail Salon",
            "type":"Services"
        }
    ],
    "sg:phone":"+31 162 451 719",
    "sg:postcode":"4902 XS",
    "sg:province":"Noord-Brabant",
    "sg:tags":[
        "pedicure"
    ],
    "wof:name":"Poppelaars-Van Den Noort, P C F M",
    "wof:placetype":"venue"
},
  "geometry": {"coordinates":[4.860627,51.633907],"type":"Point"}
}