{
  "type": "Feature",
  "properties": {
    "addr:full":"Ilpensteinstraat 7 Nijmegen Gelderland 6535 KK",
    "addr:housenumber":"7",
    "addr:postcode":"6535 kk",
    "addr:street":"Ilpensteinstraat;Gelderland",
    "iso:country":"NL",
    "sg:address":"Ilpensteinstraat 7",
    "sg:city":"Nijmegen",
    "sg:orig_category":"Marktonderzoekbureaus",
    "sg:phone":"+31 24 350 2716",
    "sg:postcode":"6535 KK",
    "sg:province":"Gelderland",
    "wof:name":"Drs. A.J.W. Geelen",
    "wof:placetype":"venue"
},
  "geometry": {"coordinates":[5.822126,51.805332],"type":"Point"}
}