{
  "type": "Feature",
  "properties": {
    "addr:full":"Westmolendijk 99 Ridderkerk Zuid-Holland 2985 XK",
    "addr:housenumber":"99",
    "addr:postcode":"2985 xk",
    "addr:street":"Westmolendijk",
    "iso:country":"NL",
    "sg:address":"Westmolendijk 99",
    "sg:city":"Ridderkerk",
    "sg:orig_category":"Diensten Voor Huisdieren",
    "sg:phone":"+31 180 425 588",
    "sg:postcode":"2985 XK",
    "sg:province":"Zuid-Holland",
    "wof:name":"Vogelvereniging Witroka",
    "wof:placetype":"venue"
},
  "geometry": {"coordinates":[4.606864,51.868469],"type":"Point"}
}