{
  "type": "Feature",
  "properties": {
    "addr:full":"Botterstr 22 Huizen North Holland 1271 XM",
    "addr:housenumber":"22",
    "addr:postcode":"1271 xm",
    "addr:street":"Botterstr",
    "iso:country":"NL",
    "sg:address":"Botterstr 22",
    "sg:city":"Huizen",
    "sg:orig_category":"Schilders",
    "sg:phone":"+31 35 524 0016",
    "sg:postcode":"1271 XM",
    "sg:province":"North Holland",
    "wof:name":"Uyl, Den",
    "wof:placetype":"venue"
},
  "geometry": {"coordinates":[5.231503,52.30275],"type":"Point"}
}