{
  "type": "Feature",
  "properties": {
    "addr:full":"Dreef 18 Zutphen Gelderland 7202 AG",
    "addr:housenumber":"18",
    "addr:postcode":"7202",
    "addr:street":"Dreef;Gelderland",
    "iso:country":"NL",
    "sg:address":"Dreef 18",
    "sg:city":"Zutphen",
    "sg:orig_category":"Autokeuringen",
    "sg:phone":"+31 575 540 141",
    "sg:postcode":"7202 AG",
    "sg:province":"Gelderland",
    "wof:name":"Kose En Kal",
    "wof:placetype":"venue"
},
  "geometry": {"coordinates":[6.193082,52.147606],"type":"Point"}
}