{
  "type": "Feature",
  "properties": {
    "addr:full":"Stadtvliedt 26 Dordrecht Zuid-Holland 3319 WH",
    "addr:housenumber":"26",
    "addr:postcode":"3319 wh",
    "addr:street":"Stadtvliedt",
    "iso:country":"NL",
    "sg:address":"Stadtvliedt 26",
    "sg:city":"Dordrecht",
    "sg:orig_category":"Fotostudio'S And Fotografen",
    "sg:phone":"+31 78 621 2772",
    "sg:postcode":"3319 WH",
    "sg:province":"Zuid-Holland",
    "wof:name":"Bas Maris",
    "wof:placetype":"venue"
},
  "geometry": {"coordinates":[4.697444,51.800285],"type":"Point"}
}