{
  "type": "Feature",
  "properties": {
    "addr:full":"Mathijsenlaan 5 Eindhoven Noord-Brabant 5644 JH",
    "addr:housenumber":"5",
    "addr:postcode":"5644 jh",
    "addr:street":"Mathijsenlaan",
    "iso:country":"NL",
    "sg:address":"Mathijsenlaan 5",
    "sg:city":"Eindhoven",
    "sg:orig_category":"Diverse Grafische Activiteiten",
    "sg:phone":"+31 40 211 7817",
    "sg:postcode":"5644 JH",
    "sg:province":"Noord-Brabant",
    "wof:name":"Divinus",
    "wof:placetype":"venue"
},
  "geometry": {"coordinates":[5.490061,51.415565],"type":"Point"}
}