{
  "type": "Feature",
  "properties": {
    "iso:country":"NL",
    "sg:address":"Zwaanshals 249B",
    "sg:city":"Rotterdam",
    "sg:orig_category":"Boekhandels",
    "sg:phone":"+31 10 465 5275",
    "sg:postcode":"3035 KE",
    "sg:province":"South Holland",
    "sg:website":"http://www.beyzaboekhandel.nl",
    "wof:name":"Beyza",
    "wof:placetype":"venue"
},
  "geometry": {"coordinates":[4.48607,51.933472],"type":"Point"}
}