{
  "type": "Feature",
  "properties": {
    "iso:country":"NL",
    "sg:address":"Oudemansstraat 2",
    "sg:city":"Zaandam",
    "sg:orig_category":"Kappers",
    "sg:phone":"+31 75 616 6498",
    "sg:postcode":"1504 KN",
    "sg:province":"North Holland",
    "wof:name":"Johnn Cops Hair",
    "wof:placetype":"venue"
},
  "geometry": {"coordinates":[4.8516750336,52.4401893616],"type":"Point"}
}