{
  "type": "Feature",
  "properties": {
    "addr:full":"Scheveningseslag 15 'S Gravenhage Zuid-Holland 2586 CJ",
    "addr:housenumber":"15",
    "addr:postcode":"2586 cj",
    "addr:street":"Scheveningseslag;' S",
    "iso:country":"NL",
    "sg:address":"Scheveningseslag 15",
    "sg:city":"'S Gravenhage",
    "sg:orig_category":"Verzekeringen",
    "sg:phone":"+31 70 351 4432",
    "sg:postcode":"2586 CJ",
    "sg:province":"Zuid-Holland",
    "wof:name":"Van Der Linden Linders Assurantie Bv",
    "wof:placetype":"venue"
},
  "geometry": {"coordinates":[4.277573,52.110935],"type":"Point"}
}