{
  "type": "Feature",
  "properties": {
    "iso:country":"NL",
    "sg:address":"Golf V Biskaje 4A-25",
    "sg:city":"Woerden",
    "sg:orig_category":"Warmtetechniek",
    "sg:phone":"+31 348 460 013",
    "sg:postcode":"3446 CP",
    "sg:province":"Utrecht",
    "wof:name":"Heatpoint Bv",
    "wof:placetype":"venue"
},
  "geometry": {"coordinates":[4.905189991,52.0819282532],"type":"Point"}
}