{
  "type": "Feature",
  "properties": {
    "addr:full":"Pruimenln 4 S Gravenzande Zuid-Holland 2691 JR",
    "addr:housenumber":"4;gravenzande;2691",
    "addr:postcode":"jr",
    "addr:street":"Pruimenln;S",
    "iso:country":"NL",
    "sg:address":"Pruimenln 4",
    "sg:city":"S Gravenzande",
    "sg:classifiers":[
        {
            "category":"Food & Beverages",
            "subcategory":"Fruits & Vegetables",
            "type":"Retail Goods"
        }
    ],
    "sg:phone":"+31 174 244 779",
    "sg:postcode":"2691 JR",
    "sg:province":"Zuid-Holland",
    "sg:tags":[
        "en",
        "groenten"
    ],
    "wof:name":"Zwinkels Cv, Johan",
    "wof:placetype":"venue"
},
  "geometry": {"coordinates":[4.171925,52.015282],"type":"Point"}
}