{
  "type": "Feature",
  "properties": {
    "iso:country":"NL",
    "sg:address":"Lievenshof 47",
    "sg:city":"Alkmaar",
    "sg:orig_category":"Plafonds",
    "sg:phone":"+31 72 515 2452",
    "sg:postcode":"1816 KJ",
    "sg:province":"Noord-Holland",
    "wof:name":"Ribo",
    "wof:placetype":"venue"
},
  "geometry": {"coordinates":[4.728247,52.6311],"type":"Point"}
}