{
  "type": "Feature",
  "properties": {
    "addr:full":"Hemmensestraat 3 Randwijk Gelderland 6668 LC",
    "addr:housenumber":"3",
    "addr:postcode":"6668 lc",
    "addr:street":"Hemmensestraat;Gelderland",
    "iso:country":"NL",
    "sg:address":"Hemmensestraat 3",
    "sg:city":"Randwijk",
    "sg:classifiers":[
        {
            "category":"Food & Beverages",
            "subcategory":"Fruits & Vegetables",
            "type":"Retail Goods"
        }
    ],
    "sg:phone":"+31 488 491 474",
    "sg:postcode":"6668 LC",
    "sg:province":"Gelderland",
    "sg:tags":[
        "groenten"
    ],
    "wof:name":"Groente- En Fruithandel G.W. Timmer",
    "wof:placetype":"venue"
},
  "geometry": {"coordinates":[5.691152,51.949211],"type":"Point"}
}