{
  "type": "Feature",
  "properties": {
    "iso:country":"NL",
    "sg:address":"Zwartewg 98",
    "sg:city":"Aalsmeer",
    "sg:orig_category":"Gehandicapteninformatie",
    "sg:phone":"+31 297 323 811",
    "sg:postcode":"1431 VM",
    "sg:province":"North Holland",
    "sg:website":"http://www.heliomare.nl",
    "wof:name":"Aktiviteitencentr Aalsmeer",
    "wof:placetype":"venue"
},
  "geometry": {"coordinates":[4.769117,52.260475],"type":"Point"}
}