{
  "type": "Feature",
  "properties": {
    "addr:full":"Ambachtstr 9A Meerkerk Zuid-Holland 4231 DP",
    "addr:housenumber":"9a",
    "addr:postcode":"4231 dp",
    "addr:street":"Ambachtstr",
    "iso:country":"NL",
    "sg:address":"Ambachtstr 9A",
    "sg:city":"Meerkerk",
    "sg:classifiers":[
        {
            "category":"Retail",
            "subcategory":"Auto Repair",
            "type":"Services"
        }
    ],
    "sg:phone":"+31 183 352 427",
    "sg:postcode":"4231 DP",
    "sg:province":"Zuid-Holland",
    "sg:tags":[
        "garage"
    ],
    "sg:website":"http://www.degrootautoservice.nl",
    "wof:name":"Groot, De",
    "wof:placetype":"venue"
},
  "geometry": {"coordinates":[4.989373,51.914913],"type":"Point"}
}