{
  "type": "Feature",
  "properties": {
    "addr:full":"Holtackers 12 Emmen Drenthe 7824 LB",
    "addr:housenumber":"12",
    "addr:postcode":"7824 lb",
    "addr:street":"Holtackers",
    "iso:country":"NL",
    "sg:address":"Holtackers 12",
    "sg:city":"Emmen",
    "sg:orig_category":"Goederenvervoer Over De Weg",
    "sg:phone":"+31 591 624 191",
    "sg:postcode":"7824 LB",
    "sg:province":"Drenthe",
    "wof:name":"Fa. H. Oost Transportbedrijf",
    "wof:placetype":"venue"
},
  "geometry": {"coordinates":[6.939905,52.784508],"type":"Point"}
}