{
  "type": "Feature",
  "properties": {
    "addr:full":"Essenstraat 19 Haarlem Noord-Holland 2011 DW",
    "addr:housenumber":"19",
    "addr:postcode":"2011 dw",
    "addr:street":"Essenstraat",
    "iso:country":"NL",
    "sg:address":"Essenstraat 19",
    "sg:city":"Haarlem",
    "sg:orig_category":"Werving And Selectie Van Vast Personeel",
    "sg:phone":"+31 23 532 7121",
    "sg:postcode":"2011 DW",
    "sg:province":"Noord-Holland",
    "wof:name":"Peter Van Borssum Waalkes",
    "wof:placetype":"venue"
},
  "geometry": {"coordinates":[4.637773037,52.3770561218],"type":"Point"}
}