{
  "type": "Feature",
  "properties": {
    "addr:full":"Amsterdamsestraatweg 661 Utrecht Utrecht 3555 HB",
    "addr:housenumber":"661",
    "addr:postcode":"3555 hb",
    "addr:street":"Amsterdamsestraatweg",
    "iso:country":"NL",
    "sg:address":"Amsterdamsestraatweg 661",
    "sg:city":"Utrecht",
    "sg:orig_category":"Meubelzaken, Woning- And Keukeninrichting",
    "sg:phone":"+31 30 244 4263",
    "sg:postcode":"3555 HB",
    "sg:province":"Utrecht",
    "wof:name":"Meubelen De Jager",
    "wof:placetype":"venue"
},
  "geometry": {"coordinates":[5.081363,52.111637],"type":"Point"}
}