{
  "type": "Feature",
  "properties": {
    "addr:full":"Scherpenzeelseweg 84 Goor NL.08 7471 GS",
    "addr:housenumber":"84;nl.08",
    "addr:postcode":"7471 gs",
    "addr:street":"Scherpenzeelseweg",
    "iso:country":"NL",
    "sg:address":"Scherpenzeelseweg 84",
    "sg:city":"Goor",
    "sg:orig_category":"Grafologen, Handlezers And Helderzienden",
    "sg:phone":"+31 547 271 887",
    "sg:postcode":"7471 GS",
    "sg:province":"NL.08",
    "wof:name":"Yvonne Van Ek",
    "wof:placetype":"venue"
},
  "geometry": {"coordinates":[6.570769,52.241127],"type":"Point"}
}