{
  "type": "Feature",
  "properties": {
    "iso:country":"NL",
    "sg:address":"Hogeschoorweg 238",
    "sg:city":"Venlo",
    "sg:orig_category":"Medische Apparatuur And Prothesen Fab",
    "sg:phone":"+31 77 352 4673",
    "sg:postcode":"5914 CZ",
    "sg:province":"Limburg",
    "wof:name":"Dentalis Tandtechnisch Laboratorium",
    "wof:placetype":"venue"
},
  "geometry": {"coordinates":[6.169642,51.381214],"type":"Point"}
}