{
  "type": "Feature",
  "properties": {
    "addr:full":"Valkenierspln 1 Breda Noord-Brabant 4835 RA",
    "addr:housenumber":"1",
    "addr:postcode":"4835 ra",
    "addr:street":"Valkenierspln",
    "iso:country":"NL",
    "sg:address":"Valkenierspln 1",
    "sg:city":"Breda",
    "sg:orig_category":"Kaas",
    "sg:phone":"+31 76 565 0433",
    "sg:postcode":"4835 RA",
    "sg:province":"Noord-Brabant",
    "wof:name":"Thijs Hoff",
    "wof:placetype":"venue"
},
  "geometry": {"coordinates":[4.7912621498,51.5702095032],"type":"Point"}
}