{
  "type": "Feature",
  "properties": {
    "iso:country":"NL",
    "sg:address":"Northgodreef 39",
    "sg:city":"Noordwijk Zh",
    "sg:orig_category":"Bedrijfs- And Managementsconsultants",
    "sg:phone":"+31 71 361 7889",
    "sg:postcode":"2202 XZ",
    "sg:province":"South Holland",
    "wof:name":"C. Vermaas",
    "wof:placetype":"venue"
},
  "geometry": {"coordinates":[4.441166,52.252083],"type":"Point"}
}