{
  "type": "Feature",
  "properties": {
    "addr:full":"Raadhuisstraat 64 Hulsberg Limburg 6336 VM",
    "addr:housenumber":"64",
    "addr:postcode":"6336 vm",
    "addr:street":"Raadhuisstraat",
    "iso:country":"NL",
    "sg:address":"Raadhuisstraat 64",
    "sg:city":"Hulsberg",
    "sg:classifiers":[
        {
            "category":"Travel",
            "subcategory":"Hotels & Motels",
            "type":"Entertainment"
        }
    ],
    "sg:phone":"+31 45 405 2620",
    "sg:postcode":"6336 VM",
    "sg:province":"Limburg",
    "wof:name":"Pension Datura",
    "wof:placetype":"venue"
},
  "geometry": {"coordinates":[5.856201,50.885723],"type":"Point"}
}