{
  "type": "Feature",
  "properties": {
    "addr:full":"Biss Lindanussngl 41 Roermond Limburg 6041 LV",
    "addr:housenumber":"41",
    "addr:postcode":"6041",
    "iso:country":"NL",
    "sg:address":"Biss Lindanussngl 41",
    "sg:city":"Roermond",
    "sg:orig_category":"Peuterspeelzalen",
    "sg:phone":"+31 475 336 600",
    "sg:postcode":"6041 LV",
    "sg:province":"Limburg",
    "wof:name":"\u00d6pke D\u00f6pke",
    "wof:placetype":"venue"
},
  "geometry": {"coordinates":[5.983628,51.189865],"type":"Point"}
}