{
  "type": "Feature",
  "properties": {
    "iso:country":"NL",
    "sg:address":"Verlaat 25",
    "sg:city":"Enkhuizen",
    "sg:orig_category":"Diverse Consumentenartikelen Gh",
    "sg:phone":"+31 228 322 571",
    "sg:postcode":"1601 JW",
    "sg:province":"Noord-Holland",
    "wof:name":"Poseidon Merchant Venturer",
    "wof:placetype":"venue"
},
  "geometry": {"coordinates":[5.292814,52.705257],"type":"Point"}
}