{
  "type": "Feature",
  "properties": {
    "iso:country":"NL",
    "sg:address":"Boschplaat 35",
    "sg:city":"Amstelveen",
    "sg:orig_category":"Glazenwasserijen",
    "sg:phone":"+31 20 445 2580",
    "sg:postcode":"1187 KV",
    "sg:province":"Noord-Holland",
    "wof:name":"Sabico",
    "wof:placetype":"venue"
},
  "geometry": {"coordinates":[4.821063,52.283234],"type":"Point"}
}