{
  "type": "Feature",
  "properties": {
    "iso:country":"NL",
    "sg:address":"Sauterneslaan 6",
    "sg:city":"Maastricht",
    "sg:classifiers":[
        {
            "category":"Bakery",
            "type":"Food & Drink"
        }
    ],
    "sg:phone":"+31 43 344 0028",
    "sg:postcode":"6213 EN",
    "sg:province":"Limburg",
    "sg:tags":[
        "brood",
        "banket"
    ],
    "wof:name":"J P J Bastiaens",
    "wof:placetype":"venue"
},
  "geometry": {"coordinates":[5.666804,50.839973],"type":"Point"}
}