{
  "type": "Feature",
  "properties": {
    "addr:full":"Oudwykerdwstr 98 Utrecht Utrecht 3581 LH",
    "addr:housenumber":"98",
    "addr:postcode":"3581 lh",
    "addr:street":"Oudwykerdwstr",
    "iso:country":"NL",
    "sg:address":"Oudwykerdwstr 98",
    "sg:city":"Utrecht",
    "sg:classifiers":[
        {
            "category":"Food & Beverages",
            "subcategory":"Bakery",
            "type":"Retail Goods"
        }
    ],
    "sg:phone":"+31 30 251 9875",
    "sg:postcode":"3581 LH",
    "sg:province":"Utrecht",
    "sg:tags":[
        "pizza"
    ],
    "wof:name":"Selena",
    "wof:placetype":"venue"
},
  "geometry": {"coordinates":[5.13426,52.087372],"type":"Point"}
}