{
  "type": "Feature",
  "properties": {
    "addr:full":"V Ittersumstr 132 Zwolle Overijssel 8012 TN",
    "addr:housenumber":"132",
    "addr:postcode":"8012",
    "iso:country":"NL",
    "sg:address":"V Ittersumstr 132",
    "sg:city":"Zwolle",
    "sg:orig_category":"Bedrijfsopleidingen",
    "sg:phone":"+31 38 421 2607",
    "sg:postcode":"8012 TN",
    "sg:province":"Overijssel",
    "wof:name":"Goos, Piet",
    "wof:placetype":"venue"
},
  "geometry": {"coordinates":[6.088738,52.512566],"type":"Point"}
}