{
  "type": "Feature",
  "properties": {
    "iso:country":"NL",
    "sg:address":"Zwanenkamp 379",
    "sg:city":"Maarssen",
    "sg:orig_category":"Artsen - Huisartsen",
    "sg:phone":"+31 346 573 434",
    "sg:postcode":"3607 SL",
    "sg:province":"Utrecht",
    "wof:name":"Stegeman, B",
    "wof:placetype":"venue"
},
  "geometry": {"coordinates":[5.012589,52.142288],"type":"Point"}
}