{
  "type": "Feature",
  "properties": {
    "iso:country":"NL",
    "sg:address":"Capelsewg 120",
    "sg:city":"Capelle Ad Yssel",
    "sg:orig_category":"Verenigingen En Stichtingen",
    "sg:phone":"+31 10 451 8915",
    "sg:postcode":"2907 XC",
    "sg:province":"Zuid-Holland",
    "wof:name":"Eendracht Maakt Macht, Muziekver",
    "wof:placetype":"venue"
},
  "geometry": {"coordinates":[4.575716,51.941345],"type":"Point"}
}