{
  "type": "Feature",
  "properties": {
    "addr:full":"Closenberg Bastion 11 Velserbroek S\u00e3o Paulo 1991 SP",
    "addr:housenumber":"11",
    "addr:postcode":"sp",
    "addr:street":"Closenberg Bastion",
    "iso:country":"NL",
    "sg:address":"Closenberg Bastion 11",
    "sg:city":"Velserbroek",
    "sg:orig_category":"Public Relationbureaus",
    "sg:phone":"+31 23 549 3366",
    "sg:postcode":"1991 SP",
    "sg:province":"S\u00e3o Paulo",
    "wof:name":"Communicatieadvies Rommelse",
    "wof:placetype":"venue"
},
  "geometry": {"coordinates":[-48.635078,-22.5149],"type":"Point"}
}