{
  "type": "Feature",
  "properties": {
    "addr:full":"De Greide 93 Eindhoven Noord-Brabant 5622 NG",
    "addr:housenumber":"93",
    "addr:postcode":"5622 ng",
    "addr:street":"De Greide",
    "iso:country":"NL",
    "sg:address":"De Greide 93",
    "sg:city":"Eindhoven",
    "sg:orig_category":"Hulpverlening Sociaal",
    "sg:phone":"+31 40 296 2760",
    "sg:postcode":"5622 NG",
    "sg:province":"Noord-Brabant",
    "wof:name":"Maatschappelijk Werk Woensel-Zuid",
    "wof:placetype":"venue"
},
  "geometry": {"coordinates":[5.470367,51.456436],"type":"Point"}
}