{
  "type": "Feature",
  "properties": {
    "addr:full":"Almeloplein 70 'S Gravenhage Zuid-Holland 2533 AD",
    "addr:housenumber":"70",
    "addr:postcode":"2533 ad",
    "addr:street":"Almeloplein;' S",
    "iso:country":"NL",
    "sg:address":"Almeloplein 70",
    "sg:city":"'S Gravenhage",
    "sg:classifiers":[
        {
            "category":"Food & Beverages",
            "subcategory":"Fruits & Vegetables",
            "type":"Retail Goods"
        }
    ],
    "sg:phone":"+31 70 366 2314",
    "sg:postcode":"2533 AD",
    "sg:province":"Zuid-Holland",
    "sg:tags":[
        "groenten"
    ],
    "wof:name":"Dijkstra Groente - En Fruit",
    "wof:placetype":"venue"
},
  "geometry": {"coordinates":[4.275029,52.055546],"type":"Point"}
}