{
  "type": "Feature",
  "properties": {
    "addr:full":"Hoofdstr 175A Herveld Gelderland 6674 BC",
    "addr:housenumber":"175a",
    "addr:postcode":"6674 bc",
    "addr:street":"Gelderland",
    "iso:country":"NL",
    "sg:address":"Hoofdstr 175A",
    "sg:city":"Herveld",
    "sg:orig_category":"Kappers",
    "sg:phone":"+31 488 420 644",
    "sg:postcode":"6674 BC",
    "sg:province":"Gelderland",
    "wof:name":"Jose",
    "wof:placetype":"venue"
},
  "geometry": {"coordinates":[5.7475600243,51.9133529663],"type":"Point"}
}