{
  "type": "Feature",
  "properties": {
    "addr:full":"Kamperfoelie 14 Tiel Gelderland 4007 TL",
    "addr:housenumber":"14",
    "addr:postcode":"4007 tl",
    "addr:street":"Kamperfoelie;Gelderland",
    "iso:country":"NL",
    "sg:address":"Kamperfoelie 14",
    "sg:city":"Tiel",
    "sg:orig_category":"Bloemen En Planten",
    "sg:phone":"+31 344 632 324",
    "sg:postcode":"4007 TL",
    "sg:province":"Gelderland",
    "wof:name":"Florado Passewaay",
    "wof:placetype":"venue"
},
  "geometry": {"coordinates":[5.40027,51.870491],"type":"Point"}
}