{
  "type": "Feature",
  "properties": {
    "addr:full":"Oosterengwg 34 Hilversum Noord-Holland 1221 JV",
    "addr:housenumber":"34",
    "addr:postcode":"1221 jv",
    "addr:street":"Oosterengwg",
    "iso:country":"NL",
    "sg:address":"Oosterengwg 34",
    "sg:city":"Hilversum",
    "sg:orig_category":"Verf En Lak - Fabrieken En Groothandel",
    "sg:phone":"+31 35 624 7910",
    "sg:postcode":"1221 JV",
    "sg:province":"Noord-Holland",
    "sg:website":"http://www.bouwmancoatings.nl",
    "wof:name":"Bouwman Coatings Bv",
    "wof:placetype":"venue"
},
  "geometry": {"coordinates":[5.194022,52.220943],"type":"Point"}
}