{
  "type": "Feature",
  "properties": {
    "iso:country":"NL",
    "sg:address":"Scheepersstraat 54",
    "sg:city":"'S-Gravenhage",
    "sg:orig_category":"Hulpverlening Sociaal",
    "sg:phone":"+31 70 302 8005",
    "sg:postcode":"2572 AL",
    "sg:province":"Zuid-Holland",
    "wof:name":"Kans, De",
    "wof:placetype":"venue"
},
  "geometry": {"coordinates":[4.292751,52.067146],"type":"Point"}
}