{
  "type": "Feature",
  "properties": {
    "addr:full":"Dubbelsteynln O 228 Dordrecht Zuid-Holland 3319 EH",
    "addr:housenumber":"228",
    "addr:postcode":"3319 eh",
    "iso:country":"NL",
    "sg:address":"Dubbelsteynln O 228",
    "sg:city":"Dordrecht",
    "sg:orig_category":"Voetbalverenigingen",
    "sg:phone":"+31 78 621 3699",
    "sg:postcode":"3319 EH",
    "sg:province":"Zuid-Holland",
    "wof:name":"Dubbeldam",
    "wof:placetype":"venue"
},
  "geometry": {"coordinates":[4.708347,51.793907],"type":"Point"}
}