{
  "type": "Feature",
  "properties": {
    "iso:country":"NL",
    "sg:address":"Duizend Roeden 23",
    "sg:city":"Veenendaal",
    "sg:orig_category":"Autorijscholen",
    "sg:phone":"+31 318 523 310",
    "sg:postcode":"3901 KA",
    "sg:province":"Utrecht",
    "wof:name":"Ravo",
    "wof:placetype":"venue"
},
  "geometry": {"coordinates":[5.560047,52.018944],"type":"Point"}
}