{
  "type": "Feature",
  "properties": {
    "iso:country":"NL",
    "sg:address":"Van Eesterensingel 150",
    "sg:city":"Alblasserdam",
    "sg:orig_category":"Goederenvervoer Over De Weg",
    "sg:phone":"+31 78 691 8380",
    "sg:postcode":"2951 VS",
    "sg:province":"Zuid-Holland",
    "wof:name":"W. De Vreugd Transport",
    "wof:placetype":"venue"
},
  "geometry": {"coordinates":[4.660755,51.864288],"type":"Point"}
}