{
  "type": "Feature",
  "properties": {
    "addr:full":"Peppelweg 160-162 Rotterdam Zuid-Holland 3053 GW",
    "addr:housenumber":"160-162",
    "addr:postcode":"3053 gw",
    "addr:street":"Peppelweg",
    "iso:country":"NL",
    "sg:address":"Peppelweg 160-162",
    "sg:city":"Rotterdam",
    "sg:orig_category":"Metaalafval, Schrootrecycling And Sloperijen",
    "sg:phone":"+31 10 418 9822",
    "sg:postcode":"3053 GW",
    "sg:province":"Zuid-Holland",
    "wof:name":"Ijzerhandel P Van Wijk",
    "wof:placetype":"venue"
},
  "geometry": {"coordinates":[4.468246,51.96059],"type":"Point"}
}