{
  "type": "Feature",
  "properties": {
    "addr:full":"Postbus 2251 Emmen Provincie Drenthe 7801 CG",
    "addr:housenumber":"2251",
    "addr:postcode":"7801 cg",
    "addr:street":"Postbus;Provincie Drenthe",
    "iso:country":"NL",
    "sg:address":"Postbus 2251",
    "sg:city":"Emmen",
    "sg:orig_category":"Opvangtehuizen",
    "sg:phone":"+31 591 648 342",
    "sg:postcode":"7801 CG",
    "sg:province":"Provincie Drenthe",
    "wof:name":"Blijf Van M'N Lijf",
    "wof:placetype":"venue"
},
  "geometry": {"coordinates":[6.8997101784,52.7959594727],"type":"Point"}
}