{
  "type": "Feature",
  "properties": {
    "addr:full":"H.J.Nederhorststraat 1 Gouda South Holland 2801 SC",
    "addr:housenumber":"1",
    "addr:postcode":"2801 sc",
    "addr:street":"H.J.Nederhorststraat",
    "iso:country":"NL",
    "sg:address":"H.J.Nederhorststraat 1",
    "sg:city":"Gouda",
    "sg:orig_category":"Wegen And Sportterreinen",
    "sg:phone":"+31 182 590 600",
    "sg:postcode":"2801 SC",
    "sg:province":"South Holland",
    "wof:name":"Hbg Civiel Bv",
    "wof:placetype":"venue"
},
  "geometry": {"coordinates":[4.6948618889,52.016040802],"type":"Point"}
}