{
  "type": "Feature",
  "properties": {
    "addr:full":"Waterkant 41 Ens Flevoland 8307 AB",
    "addr:housenumber":"41",
    "addr:postcode":"8307 ab",
    "addr:street":"Waterkant;Flevoland",
    "iso:country":"NL",
    "sg:address":"Waterkant 41",
    "sg:city":"Ens",
    "sg:orig_category":"Fruit And Groenten Gh",
    "sg:phone":"+31 527 251 651",
    "sg:postcode":"8307 AB",
    "sg:province":"Flevoland",
    "wof:name":"H. Lambregtse",
    "wof:placetype":"venue"
},
  "geometry": {"coordinates":[5.821975,52.638042],"type":"Point"}
}