{
  "type": "Feature",
  "properties": {
    "addr:full":"Delta-Industrieweg 8 Stellendam Zuid-Holland 3251 LX",
    "addr:housenumber":"8",
    "addr:postcode":"3251 lx",
    "addr:street":"Delta-Industrieweg",
    "iso:country":"NL",
    "sg:address":"Delta-Industrieweg 8",
    "sg:city":"Stellendam",
    "sg:orig_category":"Algemene Werktuigbouw",
    "sg:phone":"+31 187 492 222",
    "sg:postcode":"3251 LX",
    "sg:province":"Zuid-Holland",
    "wof:name":"Van Toledo Staalbouw Bv",
    "wof:placetype":"venue"
},
  "geometry": {"coordinates":[4.029773,51.805542],"type":"Point"}
}