{
  "type": "Feature",
  "properties": {
    "addr:full":"Haringweg 1 Ottoland Zuid-Holland 2975 LB",
    "addr:housenumber":"1",
    "addr:postcode":"2975 lb",
    "addr:street":"Haringweg",
    "iso:country":"NL",
    "sg:address":"Haringweg 1",
    "sg:city":"Ottoland",
    "sg:orig_category":"Bloemen And Planten",
    "sg:phone":"+31 184 641 867",
    "sg:postcode":"2975 LB",
    "sg:province":"Zuid-Holland",
    "wof:name":"Jungheim Boomkwekerijen Ottoland",
    "wof:placetype":"venue"
},
  "geometry": {"coordinates":[4.844435,51.891743],"type":"Point"}
}