{
  "type": "Feature",
  "properties": {
    "addr:full":"J Steenstr 9 Woerden Utrecht 3443 GP",
    "addr:housenumber":"9",
    "addr:postcode":"3443 gp",
    "addr:street":"Woerden",
    "iso:country":"NL",
    "sg:address":"J Steenstr 9",
    "sg:city":"Woerden",
    "sg:orig_category":"Administratie- En Boekhoudkantoren",
    "sg:phone":"+31 348 411 122",
    "sg:postcode":"3443 GP",
    "sg:province":"Utrecht",
    "wof:name":"Bocxe",
    "wof:placetype":"venue"
},
  "geometry": {"coordinates":[4.878266,52.091648],"type":"Point"}
}