{
  "type": "Feature",
  "properties": {
    "iso:country":"NL",
    "sg:address":"Aardappeleterssteegje 2",
    "sg:city":"Nuenen",
    "sg:orig_category":"Verzekeringen",
    "sg:phone":"+31 40 283 2197",
    "sg:postcode":"5671 CV",
    "sg:province":"North Brabant",
    "wof:name":"Buro Van Liempd Nuenen",
    "wof:placetype":"venue"
},
  "geometry": {"coordinates":[5.551851,51.475697],"type":"Point"}
}