{
  "type": "Feature",
  "properties": {
    "addr:full":"Steenarend 28 Nieuwegein Utrecht 3435 GW",
    "addr:housenumber":"28",
    "addr:postcode":"3435 gw",
    "addr:street":"Steenarend",
    "iso:country":"NL",
    "sg:address":"Steenarend 28",
    "sg:city":"Nieuwegein",
    "sg:orig_category":"Adviesbureaus Bouwkosten",
    "sg:phone":"+31 30 605 4593",
    "sg:postcode":"3435 GW",
    "sg:province":"Utrecht",
    "wof:name":"Oort, Van",
    "wof:placetype":"venue"
},
  "geometry": {"coordinates":[5.067559,52.020992],"type":"Point"}
}