{
  "type": "Feature",
  "properties": {
    "addr:full":"Gruttostr 9 Rotterdam South Holland 3083 KZ",
    "addr:housenumber":"9",
    "addr:postcode":"3083 kz",
    "addr:street":"Gruttostr",
    "iso:country":"NL",
    "sg:address":"Gruttostr 9",
    "sg:city":"Rotterdam",
    "sg:orig_category":"Verenigingen En Stichtingen",
    "sg:phone":"+31 10 410 2569",
    "sg:postcode":"3083 KZ",
    "sg:province":"South Holland",
    "wof:name":"Tref",
    "wof:placetype":"venue"
},
  "geometry": {"coordinates":[4.474687,51.888321],"type":"Point"}
}