{
  "type": "Feature",
  "properties": {
    "addr:full":"Banckertln 149 Hilversum Noord-Holland 1215 PZ",
    "addr:housenumber":"149",
    "addr:postcode":"hilversum;1215 pz",
    "iso:country":"NL",
    "sg:address":"Banckertln 149",
    "sg:city":"Hilversum",
    "sg:orig_category":"Tekstschrijversters",
    "sg:phone":"+31 35 772 1385",
    "sg:postcode":"1215 PZ",
    "sg:province":"Noord-Holland",
    "wof:name":"Tekst & Stuff",
    "wof:placetype":"venue"
},
  "geometry": {"coordinates":[5.1695,52.228565],"type":"Point"}
}