{
  "type": "Feature",
  "properties": {
    "addr:full":"Kerkstraat 104 Goor Overijssel 7471 AN",
    "addr:housenumber":"104",
    "addr:postcode":"7471 an",
    "addr:street":"Kerkstraat",
    "iso:country":"NL",
    "sg:address":"Kerkstraat 104",
    "sg:city":"Goor",
    "sg:orig_category":"Loodgieterswerk, Verwarming And Sanitaire Installaties",
    "sg:phone":"+31 547 276 284",
    "sg:postcode":"7471 AN",
    "sg:province":"Overijssel",
    "wof:name":"Matel Bouw",
    "wof:placetype":"venue"
},
  "geometry": {"coordinates":[6.575412,52.23391],"type":"Point"}
}