{
  "type": "Feature",
  "properties": {
    "addr:full":"Dr H Noodtstr 87 Doetinchem Gelderland 7001 DV",
    "addr:housenumber":"87",
    "addr:postcode":"7001",
    "addr:street":"Dr;Gelderland",
    "iso:country":"NL",
    "sg:address":"Dr H Noodtstr 87",
    "sg:city":"Doetinchem",
    "sg:orig_category":"Piano'S",
    "sg:phone":"+31 314 344 647",
    "sg:postcode":"7001 DV",
    "sg:province":"Gelderland",
    "sg:website":"http://www.vriese.nl",
    "wof:name":"Vriese, Muziekhuis",
    "wof:placetype":"venue"
},
  "geometry": {"coordinates":[6.296271,51.966396],"type":"Point"}
}