{
  "type": "Feature",
  "properties": {
    "addr:full":"Kuipersdk 13 Enkhuizen Noord-Holland 1601 CL",
    "addr:housenumber":"13",
    "addr:postcode":"1601",
    "addr:street":"Kuipersdk",
    "iso:country":"NL",
    "sg:address":"Kuipersdk 13",
    "sg:city":"Enkhuizen",
    "sg:orig_category":"Keuringsdiensten",
    "sg:phone":"+31 228 319 966",
    "sg:postcode":"1601 CL",
    "sg:province":"Noord-Holland",
    "wof:name":"Register Holland",
    "wof:placetype":"venue"
},
  "geometry": {"coordinates":[5.282253,52.700584],"type":"Point"}
}