{
  "type": "Feature",
  "properties": {
    "addr:full":"Ysbaanpad 66F Amsterdam Noord-Holland 1076 CW",
    "addr:housenumber":"66f",
    "addr:postcode":"1076 cw",
    "addr:street":"Ysbaanpad",
    "iso:country":"NL",
    "sg:address":"Ysbaanpad 66F",
    "sg:city":"Amsterdam",
    "sg:orig_category":"Adviesbureaus Bedrijfsorganisatie",
    "sg:phone":"+31 20 671 7477",
    "sg:postcode":"1076 CW",
    "sg:province":"Noord-Holland",
    "wof:name":"Miedema & Van Der Schoot",
    "wof:placetype":"venue"
},
  "geometry": {"coordinates":[4.849135,52.342155],"type":"Point"}
}