{
  "type": "Feature",
  "properties": {
    "iso:country":"NL",
    "sg:address":"Lord B Powellwg 1",
    "sg:city":"Voorschoten",
    "sg:classifiers":[
        {
            "category":"Food & Beverages",
            "subcategory":"Bakery",
            "type":"Retail Goods"
        }
    ],
    "sg:phone":"+31 71 561 0804",
    "sg:postcode":"2251 VC",
    "sg:province":"Zuid-Holland",
    "sg:tags":[
        "pizza"
    ],
    "wof:name":"Sicilia Pizzeria La",
    "wof:placetype":"venue"
},
  "geometry": {"coordinates":[4.453766,52.12682],"type":"Point"}
}