{
  "type": "Feature",
  "properties": {
    "addr:full":"Lente 4 De Meern Utrecht 3454 KR",
    "addr:housenumber":"4",
    "addr:postcode":"3454 kr",
    "addr:street":"Lente",
    "iso:country":"NL",
    "sg:address":"Lente 4",
    "sg:city":"De Meern",
    "sg:orig_category":"Honden- En Kattentrimsalons",
    "sg:phone":"+31 30 666 6602",
    "sg:postcode":"3454 KR",
    "sg:province":"Utrecht",
    "wof:name":"Stangenberger, Saskia",
    "wof:placetype":"venue"
},
  "geometry": {"coordinates":[5.036036,52.086563],"type":"Point"}
}