{
  "type": "Feature",
  "properties": {
    "addr:full":"Hoofdstraat 31 Terborg Gelderland 7061 CG",
    "addr:housenumber":"31",
    "addr:postcode":"7061 cg",
    "addr:street":"Hoofdstraat;Gelderland",
    "iso:country":"NL",
    "sg:address":"Hoofdstraat 31",
    "sg:city":"Terborg",
    "sg:orig_category":"Bloemen And Planten",
    "sg:phone":"+31 315 329 512",
    "sg:postcode":"7061 CG",
    "sg:province":"Gelderland",
    "wof:name":"Vof Bloemsierkunst Terry Hecker",
    "wof:placetype":"venue"
},
  "geometry": {"coordinates":[6.35991,51.919456],"type":"Point"}
}