{
  "type": "Feature",
  "properties": {
    "addr:full":"Stuyvesantstr 89Zw Haarlem Noord-Holland 2023 KM",
    "addr:housenumber":"89zw",
    "addr:postcode":"2023 km",
    "addr:street":"Stuyvesantstr",
    "iso:country":"NL",
    "sg:address":"Stuyvesantstr 89Zw",
    "sg:city":"Haarlem",
    "sg:orig_category":"Ademhalingstherapeuten",
    "sg:phone":"+31 23 526 0500",
    "sg:postcode":"2023 KM",
    "sg:province":"Noord-Holland",
    "wof:name":"Dirk Van Duijn",
    "wof:placetype":"venue"
},
  "geometry": {"coordinates":[4.630262,52.400818],"type":"Point"}
}