{
  "type": "Feature",
  "properties": {
    "addr:full":"Garyp 5 Grypskerke Zeeland 4364 AD",
    "addr:housenumber":"5",
    "addr:postcode":"4364 ad",
    "addr:street":"Garyp;Zeeland",
    "iso:country":"NL",
    "sg:address":"Garyp 5",
    "sg:city":"Grypskerke",
    "sg:orig_category":"Bloemen En Planten - Groothandel",
    "sg:phone":"+31 118 591 139",
    "sg:postcode":"4364 AD",
    "sg:province":"Zeeland",
    "wof:name":"As Bloemen Bv, Van",
    "wof:placetype":"venue"
},
  "geometry": {"coordinates":[3.573785,51.519073],"type":"Point"}
}