{
  "type": "Feature",
  "properties": {
    "addr:full":"Schiewg 1 Delft South Holland 2627 AN",
    "addr:housenumber":"1",
    "addr:postcode":"2627 an",
    "addr:street":"Schiewg",
    "iso:country":"NL",
    "sg:address":"Schiewg 1",
    "sg:city":"Delft",
    "sg:orig_category":"Keukens",
    "sg:phone":"+31 15 257 3434",
    "sg:postcode":"2627 AN",
    "sg:province":"South Holland",
    "wof:name":"Hans Verkerk",
    "wof:placetype":"venue"
},
  "geometry": {"coordinates":[4.363798,52.000519],"type":"Point"}
}