{
  "type": "Feature",
  "properties": {
    "addr:full":"Pr Mauritsln 82 S Gravenhage Zuid-Holland 2582 LV",
    "addr:housenumber":"82;gravenhage",
    "addr:postcode":"2582",
    "addr:street":"S",
    "iso:country":"NL",
    "sg:address":"Pr Mauritsln 82",
    "sg:city":"S Gravenhage",
    "sg:orig_category":"Administratie- En Boekhoudkantoren",
    "sg:phone":"+31 70 306 0649",
    "sg:postcode":"2582 LV",
    "sg:province":"Zuid-Holland",
    "sg:website":"http://www.mennema-vdgraaf.nl",
    "wof:name":"Mennema & Van De Graaf",
    "wof:placetype":"venue"
},
  "geometry": {"coordinates":[4.27852,52.092411],"type":"Point"}
}