{
  "type": "Feature",
  "properties": {
    "addr:full":"Industrieweg 85 Mijdrecht Utrecht 3641 RK",
    "addr:housenumber":"85",
    "addr:postcode":"3641 rk",
    "addr:street":"Industrieweg",
    "iso:country":"NL",
    "sg:address":"Industrieweg 85",
    "sg:city":"Mijdrecht",
    "sg:orig_category":"Goederenvervoer Over De Weg",
    "sg:phone":"+31 297 272 007",
    "sg:postcode":"3641 RK",
    "sg:province":"Utrecht",
    "wof:name":"Van Der Marel Transport",
    "wof:placetype":"venue"
},
  "geometry": {"coordinates":[4.88261,52.206692],"type":"Point"}
}