{
  "type": "Feature",
  "properties": {
    "addr:full":"Polanen 14 Rysbergen Noord-Brabant 4891 ZW",
    "addr:housenumber":"14",
    "addr:postcode":"4891 zw",
    "addr:street":"Polanen",
    "iso:country":"NL",
    "sg:address":"Polanen 14",
    "sg:city":"Rysbergen",
    "sg:orig_category":"Adviesbureaus Financieel",
    "sg:phone":"+31 76 596 2335",
    "sg:postcode":"4891 ZW",
    "sg:province":"Noord-Brabant",
    "wof:name":"Riel, Van",
    "wof:placetype":"venue"
},
  "geometry": {"coordinates":[4.697005,51.520031],"type":"Point"}
}