{
  "type": "Feature",
  "properties": {
    "addr:full":"Joost Van Vondelstraat 3 Heerlen Limburg 6416 AN",
    "addr:housenumber":"3",
    "addr:postcode":"6416 an",
    "addr:street":"Joost Van Vondelstraat",
    "iso:country":"NL",
    "sg:address":"Joost Van Vondelstraat 3",
    "sg:city":"Heerlen",
    "sg:orig_category":"Bloemen And Planten",
    "sg:phone":"+31 45 571 2362",
    "sg:postcode":"6416 AN",
    "sg:province":"Limburg",
    "wof:name":"Bloemsierkunst Ritzen",
    "wof:placetype":"venue"
},
  "geometry": {"coordinates":[5.995495,50.884842],"type":"Point"}
}