{
  "type": "Feature",
  "properties": {
    "addr:full":"Kievitln 63 Schagen North Holland 1742 AC",
    "addr:housenumber":"63",
    "addr:postcode":"1742 ac",
    "addr:street":"Kievitln",
    "iso:country":"NL",
    "sg:address":"Kievitln 63",
    "sg:city":"Schagen",
    "sg:orig_category":"Scholen Voor Basisonderwijs",
    "sg:phone":"+31 224 212 083",
    "sg:postcode":"1742 AC",
    "sg:province":"North Holland",
    "wof:name":"Nico Tinbergen Openb",
    "wof:placetype":"venue"
},
  "geometry": {"coordinates":[4.795030117,52.7848396301],"type":"Point"}
}