{
  "type": "Feature",
  "properties": {
    "addr:full":"Gareelmakersdreef 3 Tholen Zeeland 4691 LR",
    "addr:housenumber":"3",
    "addr:postcode":"4691 lr",
    "addr:street":"Gareelmakersdreef",
    "iso:country":"NL",
    "sg:address":"Gareelmakersdreef 3",
    "sg:city":"Tholen",
    "sg:orig_category":"Boomverzorging",
    "sg:phone":"+31 166 606 502",
    "sg:postcode":"4691 LR",
    "sg:province":"Zeeland",
    "wof:name":"Remco",
    "wof:placetype":"venue"
},
  "geometry": {"coordinates":[4.21266,51.527172],"type":"Point"}
}