{
  "type": "Feature",
  "properties": {
    "addr:full":"Windmolen 16 Almelo Overijssel 7609 NN",
    "addr:housenumber":"16",
    "addr:postcode":"7609 nn",
    "addr:street":"Windmolen",
    "iso:country":"NL",
    "sg:address":"Windmolen 16",
    "sg:city":"Almelo",
    "sg:orig_category":"Kunststoffen - Fabrieken En Groothandel",
    "sg:phone":"+31 546 824 151",
    "sg:postcode":"7609 NN",
    "sg:province":"Overijssel",
    "wof:name":"Bruhamij Bv",
    "wof:placetype":"venue"
},
  "geometry": {"coordinates":[6.652849,52.337299],"type":"Point"}
}