{
  "type": "Feature",
  "properties": {
    "iso:country":"NL",
    "sg:address":"Snekertrekwg 23",
    "sg:city":"Leeuwarden",
    "sg:orig_category":"Warenhuizen",
    "sg:phone":"+31 58 212 0211",
    "sg:postcode":"8912 AA",
    "sg:province":"Friesland",
    "wof:name":"Maxis Cv",
    "wof:placetype":"venue"
},
  "geometry": {"coordinates":[5.7858748436,53.1968765259],"type":"Point"}
}