{
  "type": "Feature",
  "properties": {
    "iso:country":"NL",
    "sg:address":"Gasthuispln 5",
    "sg:city":"Zandvoort",
    "sg:orig_category":"Bioscopen",
    "sg:phone":"+31 23 571 8686",
    "sg:postcode":"2042 JM",
    "sg:province":"Noord-Holland",
    "sg:website":"http://www.circuszandvoort.nl",
    "wof:name":"Circus Zandvoort",
    "wof:placetype":"venue"
},
  "geometry": {"coordinates":[4.52824,52.372494],"type":"Point"}
}