{
  "type": "Feature",
  "properties": {
    "addr:full":"Oude Watering 259 Rotterdam Zuid-Holland 3077 RG",
    "addr:housenumber":"259",
    "addr:postcode":"3077 rg",
    "addr:street":"Oude Watering",
    "iso:country":"NL",
    "sg:address":"Oude Watering 259",
    "sg:city":"Rotterdam",
    "sg:orig_category":"Zuivelproducten",
    "sg:phone":"+31 10 483 3956",
    "sg:postcode":"3077 RG",
    "sg:province":"Zuid-Holland",
    "wof:name":"Waayer De Kaasboer Bv",
    "wof:placetype":"venue"
},
  "geometry": {"coordinates":[4.568894,51.892498],"type":"Point"}
}