{
  "type": "Feature",
  "properties": {
    "iso:country":"NL",
    "sg:address":"Valendries 20",
    "sg:city":"Boxmeer",
    "sg:orig_category":"Autokeuringen",
    "sg:phone":"+31 485 578 435",
    "sg:postcode":"5831 DV",
    "sg:province":"North Brabant",
    "wof:name":"Hoffmans Auto'S",
    "wof:placetype":"venue"
},
  "geometry": {"coordinates":[5.947888,51.638161],"type":"Point"}
}