{
  "type": "Feature",
  "properties": {
    "addr:full":"Raadhuisstraat 1 Roosendaal North Brabant 4701 PK",
    "addr:housenumber":"1",
    "addr:postcode":"4701 pk",
    "addr:street":"Raadhuisstraat",
    "iso:country":"NL",
    "sg:address":"Raadhuisstraat 1",
    "sg:city":"Roosendaal",
    "sg:orig_category":"Banken And Kredietinstellingen",
    "sg:phone":"+31 165 523 630",
    "sg:postcode":"4701 PK",
    "sg:province":"North Brabant",
    "wof:name":"Sns Bank Brabant",
    "wof:placetype":"venue"
},
  "geometry": {"coordinates":[4.456591,51.533192],"type":"Point"}
}