{
  "type": "Feature",
  "properties": {
    "addr:full":"Rademakerstr 27 Soesterberg Utrecht 3769 BB",
    "addr:housenumber":"27",
    "addr:postcode":"3769 bb",
    "addr:street":"Rademakerstr",
    "iso:country":"NL",
    "sg:address":"Rademakerstr 27",
    "sg:city":"Soesterberg",
    "sg:orig_category":"Horloges En Klokken Fournituren - Fabr. En Grooth",
    "sg:phone":"+31 346 350 208",
    "sg:postcode":"3769 BB",
    "sg:province":"Utrecht",
    "wof:name":"Ds Bv",
    "wof:placetype":"venue"
},
  "geometry": {"coordinates":[5.283349,52.120434],"type":"Point"}
}