{
  "type": "Feature",
  "properties": {
    "addr:full":"Ootmarsumsestraat 59 Almelo Overijssel 7607 AZ",
    "addr:housenumber":"59",
    "addr:postcode":"7607 az",
    "addr:street":"Ootmarsumsestraat",
    "iso:country":"NL",
    "sg:address":"Ootmarsumsestraat 59",
    "sg:city":"Almelo",
    "sg:orig_category":"Bedrijfsinventaris Gh",
    "sg:phone":"+31 546 814 834",
    "sg:postcode":"7607 AZ",
    "sg:province":"Overijssel",
    "wof:name":"Wessels Papiergroothandel",
    "wof:placetype":"venue"
},
  "geometry": {"coordinates":[6.66836,52.361752],"type":"Point"}
}