{
  "type": "Feature",
  "properties": {
    "addr:full":"Vechtstr 46 Zwolle Overijssel 8021 AX",
    "addr:housenumber":"46",
    "addr:postcode":"8021 ax",
    "addr:street":"Vechtstr",
    "iso:country":"NL",
    "sg:address":"Vechtstr 46",
    "sg:city":"Zwolle",
    "sg:orig_category":"Kappers",
    "sg:phone":"+31 38 453 5786",
    "sg:postcode":"8021 AX",
    "sg:province":"Overijssel",
    "wof:name":"Kijk In De Vegt, Rob",
    "wof:placetype":"venue"
},
  "geometry": {"coordinates":[6.1060547829,52.5154571533],"type":"Point"}
}