{
  "type": "Feature",
  "properties": {
    "addr:full":"Breegraven 80 Warnsveld Gelderland 7231 JH",
    "addr:housenumber":"80",
    "addr:postcode":"7231 jh",
    "addr:street":"Breegraven;Gelderland",
    "iso:country":"NL",
    "sg:address":"Breegraven 80",
    "sg:city":"Warnsveld",
    "sg:orig_category":"Juridische Adviseurs",
    "sg:phone":"+31 575 530 206",
    "sg:postcode":"7231 JH",
    "sg:province":"Gelderland",
    "wof:name":"Bureau Achterhoek",
    "wof:placetype":"venue"
},
  "geometry": {"coordinates":[6.225082,52.138817],"type":"Point"}
}