{
  "type": "Feature",
  "properties": {
    "addr:full":"Zeeltstr 1 Utrecht Utrecht 3525 TC",
    "addr:housenumber":"1",
    "addr:postcode":"3525 tc",
    "addr:street":"Zeeltstr",
    "iso:country":"NL",
    "sg:address":"Zeeltstr 1",
    "sg:city":"Utrecht",
    "sg:orig_category":"Adviesbureaus Bedrijfsorganisatie",
    "sg:phone":"+31 30 280 2990",
    "sg:postcode":"3525 TC",
    "sg:province":"Utrecht",
    "wof:name":"Regt, De",
    "wof:placetype":"venue"
},
  "geometry": {"coordinates":[5.115012,52.064857],"type":"Point"}
}