{
  "type": "Feature",
  "properties": {
    "iso:country":"NL",
    "sg:address":"Dorpspln 13",
    "sg:city":"Westervoort",
    "sg:orig_category":"Cafetaria'S",
    "sg:phone":"+31 26 311 5517",
    "sg:postcode":"6931 CZ",
    "sg:province":"Gelderland",
    "wof:name":"Olympia",
    "wof:placetype":"venue"
},
  "geometry": {"coordinates":[5.966967,51.961876],"type":"Point"}
}