{
  "type": "Feature",
  "properties": {
    "addr:full":"Molenstr 34 Tiel Gelderland 4001 CB",
    "addr:housenumber":"34",
    "addr:postcode":"4001 cb",
    "addr:street":"Molenstr;Gelderland",
    "iso:country":"NL",
    "sg:address":"Molenstr 34",
    "sg:city":"Tiel",
    "sg:orig_category":"Begrafenisverzorging",
    "sg:phone":"+31 344 613 691",
    "sg:postcode":"4001 CB",
    "sg:province":"Gelderland",
    "wof:name":"Haan & Zoon, H K Den",
    "wof:placetype":"venue"
},
  "geometry": {"coordinates":[5.430696,51.888096],"type":"Point"}
}