{
  "type": "Feature",
  "properties": {
    "addr:full":"Basicweg 14 Amersfoort Utrecht 3821 BR",
    "addr:housenumber":"14",
    "addr:postcode":"3821 br",
    "addr:street":"Basicweg",
    "iso:country":"NL",
    "sg:address":"Basicweg 14",
    "sg:city":"Amersfoort",
    "sg:orig_category":"Juridische Dienstverlening",
    "sg:phone":"+31 33 453 0405",
    "sg:postcode":"3821 BR",
    "sg:province":"Utrecht",
    "wof:name":"Business And Law",
    "wof:placetype":"venue"
},
  "geometry": {"coordinates":[5.422059,52.17374],"type":"Point"}
}