{
  "type": "Feature",
  "properties": {
    "addr:full":"Lagedykerwg 22 Schagen North Holland 1742 NB",
    "addr:housenumber":"22",
    "addr:postcode":"1742 nb",
    "addr:street":"Lagedykerwg",
    "iso:country":"NL",
    "sg:address":"Lagedykerwg 22",
    "sg:city":"Schagen",
    "sg:classifiers":[
        {
            "category":"Home & Garden",
            "subcategory":"Hardware",
            "type":"Retail Goods"
        }
    ],
    "sg:phone":"+31 224 299 174",
    "sg:postcode":"1742 NB",
    "sg:province":"North Holland",
    "sg:tags":[
        "machine",
        "-",
        "metaalbewerking"
    ],
    "wof:name":"Roja Vof",
    "wof:placetype":"venue"
},
  "geometry": {"coordinates":[4.79503,52.78484],"type":"Point"}
}