{
  "type": "Feature",
  "properties": {
    "iso:country":"NL",
    "sg:address":"Postbus 76529",
    "sg:city":"Amsterdam",
    "sg:orig_category":"Evenementenverzorging",
    "sg:phone":"+31 20 470 0738",
    "sg:postcode":"1070 HC",
    "sg:province":"Noord-Holland",
    "wof:name":"Amsterdam Only",
    "wof:placetype":"venue"
},
  "geometry": {"coordinates":[4.89205,52.37355],"type":"Point"}
}