{
  "type": "Feature",
  "properties": {
    "addr:full":"Bilderdykstr 96 Lekkerkerk Zuid-Holland 2941 GH",
    "addr:housenumber":"96",
    "addr:postcode":"2941 gh",
    "addr:street":"Bilderdykstr",
    "iso:country":"NL",
    "sg:address":"Bilderdykstr 96",
    "sg:city":"Lekkerkerk",
    "sg:orig_category":"Kunststof Ramen",
    "sg:phone":"+31 180 662 287",
    "sg:postcode":"2941 GH",
    "sg:province":"Zuid-Holland",
    "wof:name":"Eerland, J C",
    "wof:placetype":"venue"
},
  "geometry": {"coordinates":[4.678503,51.898174],"type":"Point"}
}