{
  "type": "Feature",
  "properties": {
    "iso:country":"NL",
    "sg:address":"Hinkelenoord 14",
    "sg:city":"Bergen Op Zoom",
    "sg:classifiers":[
        {
            "category":"Education",
            "subcategory":"Preschool",
            "type":"Public Place"
        }
    ],
    "sg:phone":"+31 164 234 555",
    "sg:postcode":"4617 NC",
    "sg:province":"North Brabant",
    "sg:tags":[
        "kleuteronderwijs",
        "basis-"
    ],
    "wof:name":"Openbare Basisschool De Kreek",
    "wof:placetype":"venue"
},
  "geometry": {"coordinates":[4.279086,51.475491],"type":"Point"}
}