{
  "type": "Feature",
  "properties": {
    "addr:full":"De Akker 31 Vlijmen North Brabant 5251 AB",
    "addr:housenumber":"31",
    "addr:postcode":"5251 ab",
    "addr:street":"De Akker",
    "iso:country":"NL",
    "sg:address":"De Akker 31",
    "sg:city":"Vlijmen",
    "sg:orig_category":"Kappers",
    "sg:phone":"+31 73 511 3273",
    "sg:postcode":"5251 AB",
    "sg:province":"North Brabant",
    "wof:name":"Bertine",
    "wof:placetype":"venue"
},
  "geometry": {"coordinates":[5.2200241089,51.6947174072],"type":"Point"}
}