{
  "type": "Feature",
  "properties": {
    "addr:full":"Rykswg N 16A Sittard Limburg 6131 CL",
    "addr:housenumber":"16a",
    "addr:postcode":"6131",
    "addr:street":"N",
    "iso:country":"NL",
    "sg:address":"Rykswg N 16A",
    "sg:city":"Sittard",
    "sg:orig_category":"Kappersbenodigdheden",
    "sg:phone":"+31 46 451 3095",
    "sg:postcode":"6131 CL",
    "sg:province":"Limburg",
    "wof:name":"Hair Centre",
    "wof:placetype":"venue"
},
  "geometry": {"coordinates":[5.864265,50.999729],"type":"Point"}
}