{
  "type": "Feature",
  "properties": {
    "addr:full":"Nyverheidswg 54 Stolwyk Zuid-Holland 2821 AZ",
    "addr:housenumber":"54",
    "addr:postcode":"2821 az",
    "addr:street":"Nyverheidswg",
    "iso:country":"NL",
    "sg:address":"Nyverheidswg 54",
    "sg:city":"Stolwyk",
    "sg:orig_category":"Heiwerken En Funderingstechniek",
    "sg:phone":"+31 182 341 522",
    "sg:postcode":"2821 AZ",
    "sg:province":"Zuid-Holland",
    "wof:name":"Jcb Bouw",
    "wof:placetype":"venue"
},
  "geometry": {"coordinates":[-111.93034400000001,34.168091],"type":"Point"}
}