{
  "type": "Feature",
  "properties": {
    "addr:full":"Kalverdk 73 Leeuwarden Friesland 8924 JJ",
    "addr:housenumber":"73",
    "addr:postcode":"8924 jj",
    "addr:street":"Kalverdk",
    "iso:country":"NL",
    "sg:address":"Kalverdk 73",
    "sg:city":"Leeuwarden",
    "sg:orig_category":"Schietbanen",
    "sg:phone":"+31 58 266 1100",
    "sg:postcode":"8924 JJ",
    "sg:province":"Friesland",
    "wof:name":"Indoor Schietb, Sticht",
    "wof:placetype":"venue"
},
  "geometry": {"coordinates":[5.8279,53.211418],"type":"Point"}
}