{
  "type": "Feature",
  "properties": {
    "addr:full":"Spaarnwouderstr 41A Haarlem Noord-Holland 2011 AB",
    "addr:housenumber":"41a",
    "addr:postcode":"2011 ab",
    "addr:street":"Spaarnwouderstr",
    "iso:country":"NL",
    "sg:address":"Spaarnwouderstr 41A",
    "sg:city":"Haarlem",
    "sg:orig_category":"Vaten - Fabrieken En Groothandel",
    "sg:phone":"+31 23 535 7496",
    "sg:postcode":"2011 AB",
    "sg:province":"Noord-Holland",
    "wof:name":"Goedhart En Zn Bv, S",
    "wof:placetype":"venue"
},
  "geometry": {"coordinates":[4.643548,52.380032],"type":"Point"}
}