{
  "type": "Feature",
  "properties": {
    "iso:country":"NL",
    "sg:address":"Heerlensewg 22",
    "sg:city":"Landgraaf",
    "sg:orig_category":"Administratie- En Boekhoudkantoren",
    "sg:phone":"+31 45 532 0342",
    "sg:postcode":"6371 HS",
    "sg:province":"Limburg",
    "wof:name":"Gaillard",
    "wof:placetype":"venue"
},
  "geometry": {"coordinates":[6.01518,50.899078],"type":"Point"}
}