{
  "type": "Feature",
  "properties": {
    "addr:full":"Ryksstrwg 121 Loenen Ad Vecht Utrecht 3632 AB",
    "addr:housenumber":"121",
    "addr:postcode":"3632 ab",
    "addr:street":"Vecht",
    "iso:country":"NL",
    "sg:address":"Ryksstrwg 121",
    "sg:city":"Loenen Ad Vecht",
    "sg:orig_category":"Boeken En Tijdschriften",
    "sg:phone":"+31 294 231 828",
    "sg:postcode":"3632 AB",
    "sg:province":"Utrecht",
    "wof:name":"Koopman, D J",
    "wof:placetype":"venue"
},
  "geometry": {"coordinates":[5.021896,52.209732],"type":"Point"}
}