{
  "type": "Feature",
  "properties": {
    "addr:full":"Postbus 19 Schalkhaar Overijssel 7433 ZG",
    "addr:housenumber":"19",
    "addr:postcode":"7433 zg",
    "addr:street":"Postbus",
    "iso:country":"NL",
    "sg:address":"Postbus 19",
    "sg:city":"Schalkhaar",
    "sg:orig_category":"Verenigingen En Stichtingen",
    "sg:phone":"+31 570 635 281",
    "sg:postcode":"7433 ZG",
    "sg:province":"Overijssel",
    "wof:name":"Ouderen Werk Deventer, Sticht",
    "wof:placetype":"venue"
},
  "geometry": {"coordinates":[6.193855,52.2687],"type":"Point"}
}