{
  "type": "Feature",
  "properties": {
    "addr:full":"Vroenhoutstraat 10 Oosterhout Nb North Brabant 4901 ZN",
    "addr:housenumber":"10;nb",
    "addr:postcode":"4901 zn",
    "addr:street":"Vroenhoutstraat",
    "iso:country":"NL",
    "sg:address":"Vroenhoutstraat 10",
    "sg:city":"Oosterhout Nb",
    "sg:orig_category":"Autokeuringen",
    "sg:phone":"+31 162 455 019",
    "sg:postcode":"4901 ZN",
    "sg:province":"North Brabant",
    "wof:name":"Ripzaad Auto'S",
    "wof:placetype":"venue"
},
  "geometry": {"coordinates":[4.871588,51.643902],"type":"Point"}
}