{
  "type": "Feature",
  "properties": {
    "iso:country":"NL",
    "sg:address":"Vondellaan 55",
    "sg:city":"Utrecht",
    "sg:orig_category":"Huishoudapparatuur, Televisies And Radio'S",
    "sg:phone":"+31 30 293 0989",
    "sg:postcode":"3521 GC",
    "sg:province":"Utrecht",
    "wof:name":"De Scheer & Foppen Bv",
    "wof:placetype":"venue"
},
  "geometry": {"coordinates":[5.115304,52.078316],"type":"Point"}
}