{
  "type": "Feature",
  "properties": {
    "iso:country":"NL",
    "sg:address":"De Posten 135",
    "sg:city":"Enschede",
    "sg:orig_category":"Bejaardeninstellingen And Serviceflats",
    "sg:phone":"+31 53 475 3753",
    "sg:postcode":"7544 LR",
    "sg:province":"NL.08",
    "wof:name":"Verzorgingshuis De Posten",
    "wof:placetype":"venue"
},
  "geometry": {"coordinates":[6.882962,52.18692],"type":"Point"}
}