{
  "type": "Feature",
  "properties": {
    "addr:full":"Kalenbergerwg 18B Luttelgeest Flevoland 8315 PG",
    "addr:housenumber":"18b",
    "addr:postcode":"8315",
    "addr:street":"Kalenbergerwg;Flevoland;Pg",
    "iso:country":"NL",
    "sg:address":"Kalenbergerwg 18B",
    "sg:city":"Luttelgeest",
    "sg:orig_category":"Koeriersdiensten",
    "sg:phone":"+31 527 202 942",
    "sg:postcode":"8315 PG",
    "sg:province":"Flevoland",
    "wof:name":"Bergsma, L",
    "wof:placetype":"venue"
},
  "geometry": {"coordinates":[5.895012,52.746185],"type":"Point"}
}