{
  "type": "Feature",
  "properties": {
    "addr:full":"Willemsbos 162 Hoofddorp Noord-Holland 2134 EH",
    "addr:housenumber":"162",
    "addr:postcode":"2134 eh",
    "addr:street":"Willemsbos",
    "iso:country":"NL",
    "sg:address":"Willemsbos 162",
    "sg:city":"Hoofddorp",
    "sg:orig_category":"Webdesign Bureaus",
    "sg:phone":"+31 23 535 7147",
    "sg:postcode":"2134 EH",
    "sg:province":"Noord-Holland",
    "wof:name":"Isok",
    "wof:placetype":"venue"
},
  "geometry": {"coordinates":[4.6520471573,52.313457489],"type":"Point"}
}