{
  "type": "Feature",
  "properties": {
    "iso:country":"NL",
    "sg:address":"Herfstakker 10",
    "sg:city":"Spykenisse",
    "sg:orig_category":"Fietsen En Bromfietsen Stalling",
    "sg:phone":"+31 181 648 236",
    "sg:postcode":"3206 TA",
    "sg:province":"Zuid-Holland",
    "wof:name":"Omij, Sticht",
    "wof:placetype":"venue"
},
  "geometry": {"coordinates":[4.32515,51.829128],"type":"Point"}
}