{
  "type": "Feature",
  "properties": {
    "addr:full":"De Genestetlaan 9A Bussum North Holland 1401 EH",
    "addr:housenumber":"9a",
    "addr:postcode":"1401 eh",
    "addr:street":"De Genestetlaan",
    "iso:country":"NL",
    "sg:address":"De Genestetlaan 9A",
    "sg:city":"Bussum",
    "sg:orig_category":"Etaleurs And Showroominrichters",
    "sg:phone":"+31 6 53707236",
    "sg:postcode":"1401 EH",
    "sg:province":"North Holland",
    "wof:name":"Carolien Huisers Etalage Verzorging",
    "wof:placetype":"venue"
},
  "geometry": {"coordinates":[5.165046,52.277264],"type":"Point"}
}