{
  "type": "Feature",
  "properties": {
    "iso:country":"NL",
    "sg:address":"Gangboord 9",
    "sg:city":"Raamsdonksveer",
    "sg:orig_category":"Administratie- En Boekhoudkantoren",
    "sg:phone":"+31 162 521 598",
    "sg:postcode":"4941 RE",
    "sg:province":"Noord-Brabant",
    "wof:name":"Dirk Zwang",
    "wof:placetype":"venue"
},
  "geometry": {"coordinates":[4.872991,51.696762],"type":"Point"}
}