{
  "type": "Feature",
  "properties": {
    "addr:full":"Scheveningseweg 2 'S Gravenhage Zuid-Holland 2517 KT",
    "addr:housenumber":"2 '",
    "addr:postcode":"2517 kt",
    "addr:street":"Scheveningseweg",
    "iso:country":"NL",
    "sg:address":"Scheveningseweg 2",
    "sg:city":"'S Gravenhage",
    "sg:orig_category":"Public Relationbureaus",
    "sg:phone":"+31 70 313 1313",
    "sg:postcode":"2517 KT",
    "sg:province":"Zuid-Holland",
    "wof:name":"Tomeij & Partners",
    "wof:placetype":"venue"
},
  "geometry": {"coordinates":[4.300213,52.086891],"type":"Point"}
}