{
  "type": "Feature",
  "properties": {
    "addr:full":"Zylstr 43 Haarlem Noord-Holland 2011 TK",
    "addr:housenumber":"43",
    "addr:postcode":"2011 tk",
    "addr:street":"Zylstr",
    "iso:country":"NL",
    "sg:address":"Zylstr 43",
    "sg:city":"Haarlem",
    "sg:orig_category":"Koffiebranderijen",
    "sg:phone":"+31 23 542 5302",
    "sg:postcode":"2011 TK",
    "sg:province":"Noord-Holland",
    "wof:name":"Kale Jonker, De",
    "wof:placetype":"venue"
},
  "geometry": {"coordinates":[4.642253,52.380562],"type":"Point"}
}