{
  "type": "Feature",
  "properties": {
    "addr:full":"Langeweg 1 Slootdorp Noord-Holland 1774 AJ",
    "addr:housenumber":"1",
    "addr:postcode":"1774 aj",
    "addr:street":"Langeweg",
    "iso:country":"NL",
    "sg:address":"Langeweg 1",
    "sg:city":"Slootdorp",
    "sg:classifiers":[
        {
            "category":"Education",
            "subcategory":"Preschool",
            "type":"Public Place"
        }
    ],
    "sg:phone":"+31 227 581 711",
    "sg:postcode":"1774 AJ",
    "sg:province":"Noord-Holland",
    "sg:tags":[
        "kleuteronderwijs",
        "basis-"
    ],
    "wof:name":"De Zaaier",
    "wof:placetype":"venue"
},
  "geometry": {"coordinates":[4.974229,52.844398],"type":"Point"}
}