{
  "type": "Feature",
  "properties": {
    "addr:full":"Gietersstraat 23 Amsterdam Noord-Holland 1015 HB",
    "addr:housenumber":"23",
    "addr:postcode":"1015 hb",
    "addr:street":"Gietersstraat",
    "iso:country":"NL",
    "sg:address":"Gietersstraat 23",
    "sg:city":"Amsterdam",
    "sg:orig_category":"Binnenhuisarchitecten",
    "sg:phone":"+31 20 523 0052",
    "sg:postcode":"1015 HB",
    "sg:province":"Noord-Holland",
    "wof:name":"Merkx + Girod Bv",
    "wof:placetype":"venue"
},
  "geometry": {"coordinates":[4.880519,52.378628],"type":"Point"}
}