{
  "type": "Feature",
  "properties": {
    "addr:full":"Heemskerklaan 25 Baarn Utrecht 3742 AK",
    "addr:housenumber":"25",
    "addr:postcode":"3742 ak",
    "addr:street":"Heemskerklaan",
    "iso:country":"NL",
    "sg:address":"Heemskerklaan 25",
    "sg:city":"Baarn",
    "sg:orig_category":"Antiekzaken",
    "sg:phone":"+31 35 542 5647",
    "sg:postcode":"3742 AK",
    "sg:province":"Utrecht",
    "wof:name":"Cooperatie Palm Court Galleries Ua",
    "wof:placetype":"venue"
},
  "geometry": {"coordinates":[5.299097,52.209282],"type":"Point"}
}