{
  "type": "Feature",
  "properties": {
    "iso:country":"NL",
    "sg:address":"Generaal Foulkesweg 50",
    "sg:city":"Wageningen",
    "sg:orig_category":"Begrafenisondernemers",
    "sg:phone":"+31 317 414 945",
    "sg:postcode":"6703 BT",
    "sg:province":"Gelderland",
    "wof:name":"Uitvaartverzorging Fa. J. Mijnhart",
    "wof:placetype":"venue"
},
  "geometry": {"coordinates":[5.673571,51.966873],"type":"Point"}
}