{
  "type": "Feature",
  "properties": {
    "iso:country":"NL",
    "sg:address":"Dorpsplein 67",
    "sg:city":"Zuidzande",
    "sg:orig_category":"Huishoudapparatuur, Televisies And Radio'S",
    "sg:phone":"+31 117 452 222",
    "sg:postcode":"4505 AR",
    "sg:province":"Zeeland",
    "wof:name":"Expert Bakker Bv",
    "wof:placetype":"venue"
},
  "geometry": {"coordinates":[3.45033,51.341228],"type":"Point"}
}