{
  "type": "Feature",
  "properties": {
    "addr:full":"Bovendorpsstr 29 Zeddam Gelderland 7038 EC",
    "addr:housenumber":"29",
    "addr:postcode":"7038 ec",
    "addr:street":"Bovendorpsstr;Gelderland",
    "iso:country":"NL",
    "sg:address":"Bovendorpsstr 29",
    "sg:city":"Zeddam",
    "sg:orig_category":"Video - Faciliteiten En Producties",
    "sg:phone":"+31 314 651 838",
    "sg:postcode":"7038 EC",
    "sg:province":"Gelderland",
    "sg:website":"http://www.wellingvideo.com",
    "wof:name":"Welling",
    "wof:placetype":"venue"
},
  "geometry": {"coordinates":[6.253158,51.902428],"type":"Point"}
}