{
  "type": "Feature",
  "properties": {
    "addr:full":"De M V Streefk Ln 27 Vlissingen Zeeland 4384 KK",
    "addr:housenumber":"27",
    "addr:postcode":"4384 kk",
    "addr:street":"De M V Streefk Ln",
    "iso:country":"NL",
    "sg:address":"De M V Streefk Ln 27",
    "sg:city":"Vlissingen",
    "sg:orig_category":"Artiesten/Gezelschappen",
    "sg:phone":"+31 118 467 542",
    "sg:postcode":"4384 KK",
    "sg:province":"Zeeland",
    "wof:name":"Dramakize Meespeeltheater",
    "wof:placetype":"venue"
},
  "geometry": {"coordinates":[3.57262,51.442684],"type":"Point"}
}