{
  "type": "Feature",
  "properties": {
    "addr:full":"O Industriewg 13-19 Franeker Friesland 8801 JW",
    "addr:housenumber":"13-19",
    "addr:postcode":"franeker;8801 jw",
    "iso:country":"NL",
    "sg:address":"O Industriewg 13-19",
    "sg:city":"Franeker",
    "sg:classifiers":[
        {
            "category":"Retail",
            "subcategory":"Storage",
            "type":"Services"
        }
    ],
    "sg:phone":"+31 517 396 494",
    "sg:postcode":"8801 JW",
    "sg:province":"Friesland",
    "sg:tags":[
        "op-",
        "en",
        "overslagbedrijven"
    ],
    "wof:name":"Metselaar Franeker Bv",
    "wof:placetype":"venue"
},
  "geometry": {"coordinates":[5.540495,53.181923],"type":"Point"}
}