{
  "type": "Feature",
  "properties": {
    "addr:full":"Ludgerstr 1 Deventer Overijssel 7415 DV",
    "addr:housenumber":"1",
    "addr:postcode":"7415 dv",
    "addr:street":"Ludgerstr",
    "iso:country":"NL",
    "sg:address":"Ludgerstr 1",
    "sg:city":"Deventer",
    "sg:orig_category":"Scholen Voor Algemeen Voortgezet Onderwijs",
    "sg:phone":"+31 570 503 466",
    "sg:postcode":"7415 DV",
    "sg:province":"Overijssel",
    "wof:name":"Etty Hillesum",
    "wof:placetype":"venue"
},
  "geometry": {"coordinates":[6.159073,52.269566],"type":"Point"}
}