{
  "type": "Feature",
  "properties": {
    "addr:full":"Timmermannswg 82 Ysselsteyn Lb Limburg 5813 AP",
    "addr:housenumber":"82",
    "addr:postcode":"lb;5813 ap",
    "addr:street":"Timmermannswg",
    "iso:country":"NL",
    "sg:address":"Timmermannswg 82",
    "sg:city":"Ysselsteyn Lb",
    "sg:orig_category":"Energiebedrijven",
    "sg:phone":"+31 493 529 422",
    "sg:postcode":"5813 AP",
    "sg:province":"Limburg",
    "wof:name":"Ideco",
    "wof:placetype":"venue"
},
  "geometry": {"coordinates":[5.889595,51.467724],"type":"Point"}
}