{
  "type": "Feature",
  "properties": {
    "addr:full":"Catharina Van Clevepark 30 Amstelveen Noord-Holland 1181 AT",
    "addr:housenumber":"30",
    "addr:postcode":"1181",
    "addr:street":"Catharina Van Clevepark",
    "iso:country":"NL",
    "sg:address":"Catharina Van Clevepark 30",
    "sg:city":"Amstelveen",
    "sg:orig_category":"Schoonheidssalons",
    "sg:phone":"+31 20 645 3264",
    "sg:postcode":"1181 AT",
    "sg:province":"Noord-Holland",
    "wof:name":"B D Reiziger-Maasdamme",
    "wof:placetype":"venue"
},
  "geometry": {"coordinates":[4.864146,52.320011],"type":"Point"}
}