{
  "type": "Feature",
  "properties": {
    "addr:full":"V Disselln 24B Bladel Noord-Brabant 5531 BR",
    "addr:housenumber":"24b",
    "addr:postcode":"5531 br",
    "addr:street":"V Disselln",
    "iso:country":"NL",
    "sg:address":"V Disselln 24B",
    "sg:city":"Bladel",
    "sg:orig_category":"Bloemen En Planten",
    "sg:phone":"+31 497 382 213",
    "sg:postcode":"5531 BR",
    "sg:province":"Noord-Brabant",
    "wof:name":"Clemens Vof",
    "wof:placetype":"venue"
},
  "geometry": {"coordinates":[5.21485,51.366089],"type":"Point"}
}