{
  "type": "Feature",
  "properties": {
    "addr:full":"Nw Walden 66 Nederhorst D Berg California 1394 PC",
    "addr:housenumber":"66",
    "addr:postcode":"1394 pc",
    "addr:street":"Nw Walden;Nederhorst D Berg",
    "iso:country":"NL",
    "sg:address":"Nw Walden 66",
    "sg:city":"Nederhorst D Berg",
    "sg:orig_category":"Metaalbewerking",
    "sg:phone":"+31 294 257 855",
    "sg:postcode":"1394 PC",
    "sg:province":"California",
    "wof:name":"Boeijen, Van",
    "wof:placetype":"venue"
},
  "geometry": {"coordinates":[-121.624138,39.182121],"type":"Point"}
}