{
  "type": "Feature",
  "properties": {
    "addr:full":"Willemsparkweg 153 Amsterdam Noord-Holland 1071 GX",
    "addr:housenumber":"153",
    "addr:postcode":"1071 gx",
    "addr:street":"Willemsparkweg",
    "iso:country":"NL",
    "sg:address":"Willemsparkweg 153",
    "sg:city":"Amsterdam",
    "sg:orig_category":"Fotostudio'S And Fotografen",
    "sg:phone":"+31 20 671 9764",
    "sg:postcode":"1071 GX",
    "sg:province":"Noord-Holland",
    "wof:name":"T. Dobber",
    "wof:placetype":"venue"
},
  "geometry": {"coordinates":[4.871596,52.356125],"type":"Point"}
}