{
  "type": "Feature",
  "properties": {
    "addr:full":"Vliegveldwg 337 Enschede Overijssel 7524 PT",
    "addr:housenumber":"337",
    "addr:postcode":"7524 pt",
    "iso:country":"NL",
    "sg:address":"Vliegveldwg 337",
    "sg:city":"Enschede",
    "sg:orig_category":"Luchtvrachtexpediteurs",
    "sg:phone":"+31 53 433 6367",
    "sg:postcode":"7524 PT",
    "sg:province":"Overijssel",
    "sg:website":"HTTP://www.merzario.nl",
    "wof:name":"Merzario",
    "wof:placetype":"venue"
},
  "geometry": {"coordinates":[6.895092,52.263275],"type":"Point"}
}