{
  "type": "Feature",
  "properties": {
    "addr:full":"De Paad 10 Well Lb Limburg 5855 AV",
    "addr:housenumber":"10",
    "addr:postcode":"lb;5855 av",
    "addr:street":"De Paad",
    "iso:country":"NL",
    "sg:address":"De Paad 10",
    "sg:city":"Well Lb",
    "sg:orig_category":"Bloemen And Planten Gh",
    "sg:phone":"+31 478 501 900",
    "sg:postcode":"5855 AV",
    "sg:province":"Limburg",
    "wof:name":"J.J. Koek Bv",
    "wof:placetype":"venue"
},
  "geometry": {"coordinates":[-93.129936,36.705662],"type":"Point"}
}