{
  "type": "Feature",
  "properties": {
    "addr:full":"Stationswg 63 S Gravenhage South Holland 2515 BJ",
    "addr:housenumber":"63",
    "addr:postcode":"2515 bj",
    "addr:street":"Stationswg;S Gravenhage",
    "iso:country":"NL",
    "sg:address":"Stationswg 63",
    "sg:city":"S Gravenhage",
    "sg:orig_category":"Postkantoren",
    "sg:phone":"+31 70 388 3885",
    "sg:postcode":"2515 BJ",
    "sg:province":"South Holland",
    "sg:website":"http://www.postkantoor.nl",
    "wof:name":"Postkantoor",
    "wof:placetype":"venue"
},
  "geometry": {"coordinates":[4.31741,52.083988],"type":"Point"}
}