{
  "type": "Feature",
  "properties": {
    "addr:full":"Speedwellstraat 330 Rotterdam South Holland 3029 BL",
    "addr:housenumber":"330",
    "addr:postcode":"3029 bl",
    "addr:street":"Speedwellstraat",
    "iso:country":"NL",
    "sg:address":"Speedwellstraat 330",
    "sg:city":"Rotterdam",
    "sg:orig_category":"Fotostudio'S And Fotografen",
    "sg:phone":"+31 10 476 4512",
    "sg:postcode":"3029 BL",
    "sg:province":"South Holland",
    "wof:name":"Fotobureau Ben Wind",
    "wof:placetype":"venue"
},
  "geometry": {"coordinates":[4.438669,51.904499],"type":"Point"}
}