{
  "type": "Feature",
  "properties": {
    "iso:country":"NL",
    "sg:address":"Speedwellstraat 330",
    "sg:city":"Rotterdam",
    "sg:orig_category":"Fotostudio'S And Fotografen",
    "sg:phone":"+31 10 476 4512",
    "sg:postcode":"3029 BL",
    "sg:province":"South Holland",
    "wof:name":"Fotobureau Ben Wind",
    "wof:placetype":"venue"
},
  "geometry": {"coordinates":[4.438669,51.904499],"type":"Point"}
}