{
  "type": "Feature",
  "properties": {
    "addr:full":"Mercuriuswg 25 Brummen Gelderland 6971 GV",
    "addr:housenumber":"25",
    "addr:postcode":"6971 gv",
    "addr:street":"Mercuriuswg;Gelderland",
    "iso:country":"NL",
    "sg:address":"Mercuriuswg 25",
    "sg:city":"Brummen",
    "sg:orig_category":"Verhuizingen",
    "sg:phone":"+31 575 561 917",
    "sg:postcode":"6971 GV",
    "sg:province":"Gelderland",
    "wof:name":"Hertgers Sms Verhuizingen",
    "wof:placetype":"venue"
},
  "geometry": {"coordinates":[6.153822,52.104664],"type":"Point"}
}