{
  "type": "Feature",
  "properties": {
    "addr:full":"L Armstrongln 11 Leiden South Holland 2324 LJ",
    "addr:housenumber":"11",
    "addr:postcode":"2324 lj",
    "iso:country":"NL",
    "sg:address":"L Armstrongln 11",
    "sg:city":"Leiden",
    "sg:orig_category":"Schoonheidsinstituten",
    "sg:phone":"+31 71 576 0035",
    "sg:postcode":"2324 LJ",
    "sg:province":"South Holland",
    "wof:name":"Face To Face",
    "wof:placetype":"venue"
},
  "geometry": {"coordinates":[4.466785,52.15123],"type":"Point"}
}