{
  "type": "Feature",
  "properties": {
    "iso:country":"NL",
    "sg:address":"Watersnip 9",
    "sg:city":"Emmen",
    "sg:orig_category":"Woningstoffeerders",
    "sg:phone":"+31 6 10282221",
    "sg:postcode":"7827 KJ",
    "sg:province":"Drenthe",
    "wof:name":"Zondag",
    "wof:placetype":"venue"
},
  "geometry": {"coordinates":[6.881881237,52.7405853271],"type":"Point"}
}