{
  "type": "Feature",
  "properties": {
    "iso:country":"NL",
    "sg:address":"Oud Schutt Kan Oz 109",
    "sg:city":"Roswinkel",
    "sg:orig_category":"Homeopathie",
    "sg:phone":"+31 591 317 955",
    "sg:postcode":"7895 TC",
    "sg:province":"Provincie Drenthe",
    "wof:name":"Just Nature",
    "wof:placetype":"venue"
},
  "geometry": {"coordinates":[7.038415,52.837872],"type":"Point"}
}