{
  "type": "Feature",
  "properties": {
    "addr:full":"Meidoornln 36 Renswoude Utrecht 3927 AD",
    "addr:housenumber":"36",
    "addr:postcode":"3927 ad",
    "addr:street":"Meidoornln",
    "iso:country":"NL",
    "sg:address":"Meidoornln 36",
    "sg:city":"Renswoude",
    "sg:orig_category":"Kappers",
    "sg:phone":"+31 318 574 950",
    "sg:postcode":"3927 AD",
    "sg:province":"Utrecht",
    "wof:name":"Jeanet",
    "wof:placetype":"venue"
},
  "geometry": {"coordinates":[5.5402097702,52.0765113831],"type":"Point"}
}