{
  "type": "Feature",
  "properties": {
    "iso:country":"NL",
    "sg:address":"Straatweg 137",
    "sg:city":"Breukelen Ut",
    "sg:orig_category":"Glaszetten",
    "sg:phone":"+31 346 261 959",
    "sg:postcode":"3621 BK",
    "sg:province":"Utrecht",
    "wof:name":"C. Vervat & Zn Vof",
    "wof:placetype":"venue"
},
  "geometry": {"coordinates":[5.002415,52.176949],"type":"Point"}
}