{
  "type": "Feature",
  "properties": {
    "addr:full":"Lymbeekstr 236 Eindhoven Noord-Brabant 5612 NJ",
    "addr:housenumber":"236",
    "addr:postcode":"5612 nj",
    "iso:country":"NL",
    "sg:address":"Lymbeekstr 236",
    "sg:city":"Eindhoven",
    "sg:orig_category":"Fotoreportages",
    "sg:phone":"+31 40 246 2633",
    "sg:postcode":"5612 NJ",
    "sg:province":"Noord-Brabant",
    "sg:website":"http://www.blighted.nl",
    "wof:name":"Blighted",
    "wof:placetype":"venue"
},
  "geometry": {"coordinates":[5.467749,51.446285],"type":"Point"}
}