{
  "type": "Feature",
  "properties": {
    "addr:full":"Weverstraat 7 Zevenaar Gelderland 6901 AM",
    "addr:housenumber":"7",
    "addr:postcode":"6901",
    "addr:street":"Weverstraat",
    "iso:country":"NL",
    "sg:address":"Weverstraat 7",
    "sg:city":"Zevenaar",
    "sg:orig_category":"Kappers",
    "sg:phone":"+31 316 333 303",
    "sg:postcode":"6901 AM",
    "sg:province":"Gelderland",
    "wof:name":"Salon Peter",
    "wof:placetype":"venue"
},
  "geometry": {"coordinates":[6.076596,51.927174],"type":"Point"}
}