{
  "type": "Feature",
  "properties": {
    "iso:country":"NL",
    "sg:address":"Zilverweg 12",
    "sg:city":"Heerenveen",
    "sg:orig_category":"Goederenvervoer Over De Weg",
    "sg:phone":"+31 513 633 737",
    "sg:postcode":"8445 PE",
    "sg:province":"Friesland",
    "wof:name":"Koeriersdienst H. Van Den Berg",
    "wof:placetype":"venue"
},
  "geometry": {"coordinates":[5.93846,52.933235],"type":"Point"}
}