{
  "type": "Feature",
  "properties": {
    "addr:full":"Postbus 182 Alphen Aan Den Ryn 2400 AD",
    "addr:housenumber":"182",
    "addr:postcode":"2400 ad",
    "addr:street":"Postbus;Aan Den Ryn",
    "iso:country":"NL",
    "sg:address":"Postbus 182",
    "sg:city":"Alphen Aan Den Ryn",
    "sg:orig_category":"Kinderopvang",
    "sg:phone":"+31 172 479 590",
    "sg:postcode":"2400 AD",
    "sg:website":"http://www.konnekt.nl",
    "wof:name":"Konnekt Kinderopvang Bv",
    "wof:placetype":"venue"
},
  "geometry": {"coordinates":[4.68895,52.131088],"type":"Point"}
}