{
  "type": "Feature",
  "properties": {
    "addr:full":"Harreveldseweg 12 Zieuwent Gelderland 7136 KB",
    "addr:housenumber":"12",
    "addr:postcode":"7136 kb",
    "addr:street":"Harreveldseweg;Gelderland",
    "iso:country":"NL",
    "sg:address":"Harreveldseweg 12",
    "sg:city":"Zieuwent",
    "sg:orig_category":"Kappers",
    "sg:phone":"+31 544 352 391",
    "sg:postcode":"7136 KB",
    "sg:province":"Gelderland",
    "wof:name":"Kapsalon Jeannette",
    "wof:placetype":"venue"
},
  "geometry": {"coordinates":[6.5163059235,52.0024414062],"type":"Point"}
}