{
  "type": "Feature",
  "properties": {
    "addr:full":"Van Den Boetzelaerlaan 28 Langerak Zh South Holland 2967 XC",
    "addr:housenumber":"28;zh",
    "addr:postcode":"2967 xc",
    "addr:street":"Van Den Boetzelaerlaan",
    "iso:country":"NL",
    "sg:address":"Van Den Boetzelaerlaan 28",
    "sg:city":"Langerak Zh",
    "sg:orig_category":"Goederenvervoer Over De Weg",
    "sg:phone":"+31 184 602 392",
    "sg:postcode":"2967 XC",
    "sg:province":"South Holland",
    "wof:name":"K. Maat Transport",
    "wof:placetype":"venue"
},
  "geometry": {"coordinates":[4.878268,51.931644],"type":"Point"}
}