{
  "type": "Feature",
  "properties": {
    "iso:country":"NL",
    "sg:address":"Fazantenkamp 41",
    "sg:city":"Maarssen",
    "sg:orig_category":"Architecten",
    "sg:phone":"+31 346 574 684",
    "sg:postcode":"3607 CB",
    "sg:province":"Utrecht",
    "wof:name":"Brouwer",
    "wof:placetype":"venue"
},
  "geometry": {"coordinates":[5.020848,52.132462],"type":"Point"}
}