{
  "type": "Feature",
  "properties": {
    "addr:full":"Rijsbergseweg 466 Breda Noord-Brabant 4838 EG",
    "addr:housenumber":"466",
    "addr:postcode":"4838 eg",
    "addr:street":"Rijsbergseweg",
    "iso:country":"NL",
    "sg:address":"Rijsbergseweg 466",
    "sg:city":"Breda",
    "sg:orig_category":"Metaalafval, Schrootrecycling And Sloperijen",
    "sg:phone":"+31 76 514 0388",
    "sg:postcode":"4838 EG",
    "sg:province":"Noord-Brabant",
    "wof:name":"Autosloopbedrijf De Toekomst",
    "wof:placetype":"venue"
},
  "geometry": {"coordinates":[4.727707,51.5509],"type":"Point"}
}