{
  "type": "Feature",
  "properties": {
    "addr:full":"Theerestr 21 St Michielsgestel Noord-Brabant 5271 GB",
    "addr:housenumber":"21",
    "addr:postcode":"5271 gb",
    "addr:street":"Theerestr",
    "iso:country":"NL",
    "sg:address":"Theerestr 21",
    "sg:city":"St Michielsgestel",
    "sg:orig_category":"Verzekeringen - Verzekeringskantoren",
    "sg:phone":"+31 73 551 6323",
    "sg:postcode":"5271 GB",
    "sg:province":"Noord-Brabant",
    "sg:website":"http://www.vanroosmalenvof.nl",
    "wof:name":"Roosmalen Vof, Van",
    "wof:placetype":"venue"
},
  "geometry": {"coordinates":[5.345889,51.639503],"type":"Point"}
}