{
  "type": "Feature",
  "properties": {
    "addr:full":"Korteling 16 Midwoud Noord-Holland 1679 VH",
    "addr:housenumber":"16",
    "addr:postcode":"1679 vh",
    "addr:street":"Korteling",
    "iso:country":"NL",
    "sg:address":"Korteling 16",
    "sg:city":"Midwoud",
    "sg:classifiers":[
        {
            "category":"Food & Beverages",
            "subcategory":"Bakery",
            "type":"Retail Goods"
        }
    ],
    "sg:phone":"+31 229 202 598",
    "sg:postcode":"1679 VH",
    "sg:province":"Noord-Holland",
    "sg:tags":[
        "brood",
        "en",
        "banket"
    ],
    "wof:name":"Kool",
    "wof:placetype":"venue"
},
  "geometry": {"coordinates":[5.075268,52.719494],"type":"Point"}
}