{
  "type": "Feature",
  "properties": {
    "iso:country":"NL",
    "sg:address":"De Streep 16",
    "sg:city":"Assendelft",
    "sg:orig_category":"Vertaalbureaus",
    "sg:phone":"+31 75 687 5625",
    "sg:postcode":"1566 GR",
    "sg:province":"North Holland",
    "wof:name":"Crealyse",
    "wof:placetype":"venue"
},
  "geometry": {"coordinates":[4.745114,52.470177],"type":"Point"}
}