{
  "type": "Feature",
  "properties": {
    "addr:full":"Jagtlustkade 20 Sassenheim Zuid-Holland 2171 AG",
    "addr:housenumber":"20",
    "addr:postcode":"2171",
    "addr:street":"Jagtlustkade",
    "iso:country":"NL",
    "sg:address":"Jagtlustkade 20",
    "sg:city":"Sassenheim",
    "sg:orig_category":"Loodgieterswerk, Verwarming And Sanitaire Installaties",
    "sg:phone":"+31 252 212 428",
    "sg:postcode":"2171 AG",
    "sg:province":"Zuid-Holland",
    "wof:name":"J. Van Den Burg Bv",
    "wof:placetype":"venue"
},
  "geometry": {"coordinates":[4.508603,52.216373],"type":"Point"}
}