{
  "type": "Feature",
  "properties": {
    "addr:full":"Kleine Veenkade 49 'S Gravenhage South Holland 2518 PK",
    "addr:housenumber":"49",
    "addr:postcode":"2518 pk",
    "addr:street":"Kleine Veenkade;' S Gravenhage",
    "iso:country":"NL",
    "sg:address":"Kleine Veenkade 49",
    "sg:city":"'S Gravenhage",
    "sg:orig_category":"Fotostudio'S And Fotografen",
    "sg:phone":"+31 70 364 8213",
    "sg:postcode":"2518 PK",
    "sg:province":"South Holland",
    "wof:name":"Photography Opus",
    "wof:placetype":"venue"
},
  "geometry": {"coordinates":[4.292043,52.07618],"type":"Point"}
}