{
  "type": "Feature",
  "properties": {
    "addr:full":"Laan V Nieuw-Oost-Indie 118 'S Gravenhage South Holland 2593 BZ",
    "addr:housenumber":"118 '",
    "addr:postcode":"2593 bz",
    "addr:street":"Laan V Nieuw-Oost-Indie",
    "iso:country":"NL",
    "sg:address":"Laan V Nieuw-Oost-Indie 118",
    "sg:city":"'S Gravenhage",
    "sg:orig_category":"Fruit And Groenten Gh",
    "sg:phone":"+31 70 383 7170",
    "sg:postcode":"2593 BZ",
    "sg:province":"South Holland",
    "wof:name":"Van Der Meer, F.W.C.",
    "wof:placetype":"venue"
},
  "geometry": {"coordinates":[4.338921,52.084961],"type":"Point"}
}