{
  "type": "Feature",
  "properties": {
    "addr:full":"Fransestraat 77A Nijmegen Gelderland 6524 HX",
    "addr:housenumber":"77a",
    "addr:postcode":"6524 hx",
    "addr:street":"Fransestraat;Gelderland",
    "iso:country":"NL",
    "sg:address":"Fransestraat 77A",
    "sg:city":"Nijmegen",
    "sg:orig_category":"Bloemen And Planten",
    "sg:phone":"+31 24 322 1778",
    "sg:postcode":"6524 HX",
    "sg:province":"Gelderland",
    "wof:name":"Firma Ensink Bloemsierkunst Lady Paula",
    "wof:placetype":"venue"
},
  "geometry": {"coordinates":[5.8605971336,51.8380622864],"type":"Point"}
}