{
  "type": "Feature",
  "properties": {
    "addr:full":"Koartebaen 19 Uitwellingerga Friesland 8624 TD",
    "addr:housenumber":"19",
    "addr:postcode":"8624 td",
    "addr:street":"Koartebaen",
    "iso:country":"NL",
    "sg:address":"Koartebaen 19",
    "sg:city":"Uitwellingerga",
    "sg:orig_category":"Elektrische Apparatuur Gh",
    "sg:phone":"+31 515 559 944",
    "sg:postcode":"8624 TD",
    "sg:province":"Friesland",
    "wof:name":"Metessco Bv",
    "wof:placetype":"venue"
},
  "geometry": {"coordinates":[5.712241,53.005054],"type":"Point"}
}