{
  "type": "Feature",
  "properties": {
    "addr:full":"Thijssestraat 417 'S Gravenhage Zuid-Holland 2521 ZJ",
    "addr:housenumber":"417 '",
    "addr:postcode":"2521 zj",
    "addr:street":"Thijssestraat",
    "iso:country":"NL",
    "sg:address":"Thijssestraat 417",
    "sg:city":"'S Gravenhage",
    "sg:orig_category":"Technische Studies And Onderzoek",
    "sg:phone":"+31 70 399 9181",
    "sg:postcode":"2521 ZJ",
    "sg:province":"Zuid-Holland",
    "wof:name":"Tma Technisch Management & Adviesbureau",
    "wof:placetype":"venue"
},
  "geometry": {"coordinates":[4.319338,52.062035],"type":"Point"}
}