{
  "type": "Feature",
  "properties": {
    "addr:full":"Coronelstr 6 Amsterdam Noord-Holland 1063 EP",
    "addr:housenumber":"6",
    "addr:postcode":"1063 ep",
    "addr:street":"Coronelstr",
    "iso:country":"NL",
    "sg:address":"Coronelstr 6",
    "sg:city":"Amsterdam",
    "sg:orig_category":"Antiquariaten",
    "sg:phone":"+31 20 611 8818",
    "sg:postcode":"1063 EP",
    "sg:province":"Noord-Holland",
    "wof:name":"Wesselman, P J M",
    "wof:placetype":"venue"
},
  "geometry": {"coordinates":[4.831588,52.384132],"type":"Point"}
}