{
  "type": "Feature",
  "properties": {
    "addr:full":"Tongelresestr 274 Eindhoven Noord-Brabant 5613 DV",
    "addr:housenumber":"274",
    "addr:postcode":"5613 dv",
    "iso:country":"NL",
    "sg:address":"Tongelresestr 274",
    "sg:city":"Eindhoven",
    "sg:classifiers":[
        {
            "category":"Food & Beverages",
            "subcategory":"Fruits & Vegetables",
            "type":"Retail Goods"
        }
    ],
    "sg:phone":"+31 40 243 9228",
    "sg:postcode":"5613 DV",
    "sg:province":"Noord-Brabant",
    "sg:tags":[
        "en",
        "groenten"
    ],
    "wof:name":"Verhallen, T H",
    "wof:placetype":"venue"
},
  "geometry": {"coordinates":[5.502782,51.441792],"type":"Point"}
}