{
  "type": "Feature",
  "properties": {
    "addr:full":"Poldermolen 33 Bergschenhoek Zuid-Holland 2661 LB",
    "addr:housenumber":"33",
    "addr:postcode":"2661 lb",
    "addr:street":"Poldermolen",
    "iso:country":"NL",
    "sg:address":"Poldermolen 33",
    "sg:city":"Bergschenhoek",
    "sg:orig_category":"Advocaten And Juridische Adviseurs",
    "sg:phone":"+31 10 529 0614",
    "sg:postcode":"2661 LB",
    "sg:province":"Zuid-Holland",
    "wof:name":"Advocatenkantoor Konijnenburg-De Heer",
    "wof:placetype":"venue"
},
  "geometry": {"coordinates":[4.501786,51.99065],"type":"Point"}
}