{
  "type": "Feature",
  "properties": {
    "addr:full":"Hastelwg 91 Eindhoven North Brabant 5616 HK",
    "addr:housenumber":"91",
    "addr:postcode":"5616 hk",
    "addr:street":"Hastelwg",
    "iso:country":"NL",
    "sg:address":"Hastelwg 91",
    "sg:city":"Eindhoven",
    "sg:orig_category":"Drukkerijen",
    "sg:phone":"+31 40 257 3777",
    "sg:postcode":"5616 HK",
    "sg:province":"North Brabant",
    "sg:website":"http://www.prepart.nl",
    "wof:name":"Prepart Digital Printing",
    "wof:placetype":"venue"
},
  "geometry": {"coordinates":[5.453302,51.436382],"type":"Point"}
}