{
  "type": "Feature",
  "properties": {
    "iso:country":"NL",
    "sg:address":"Ln V Westmolen 87",
    "sg:city":"Mynsheerenland",
    "sg:orig_category":"Verzekeringen - Verzekeringskantoren",
    "sg:phone":"+31 186 603 885",
    "sg:postcode":"3271 BJ",
    "sg:province":"South Holland",
    "wof:name":"Mekes, M",
    "wof:placetype":"venue"
},
  "geometry": {"coordinates":[4.492185,51.797523],"type":"Point"}
}