{
  "type": "Feature",
  "properties": {
    "addr:full":"Vondelln 164 Papendrecht Zuid-Holland 3351 HG",
    "addr:housenumber":"164",
    "addr:postcode":"papendrecht;3351 hg",
    "iso:country":"NL",
    "sg:address":"Vondelln 164",
    "sg:city":"Papendrecht",
    "sg:orig_category":"Autoschade- Herstelbedrijven",
    "sg:phone":"+31 78 615 0611",
    "sg:postcode":"3351 HG",
    "sg:province":"Zuid-Holland",
    "wof:name":"Auto Van Wijngaarden Bv",
    "wof:placetype":"venue"
},
  "geometry": {"coordinates":[4.686203,51.830353],"type":"Point"}
}