{
  "type": "Feature",
  "properties": {
    "addr:full":"Utrechtsewg 95 Zeist Utrecht 3702 AA",
    "addr:housenumber":"95",
    "addr:postcode":"3702 aa",
    "addr:street":"Utrechtsewg",
    "iso:country":"NL",
    "sg:address":"Utrechtsewg 95",
    "sg:city":"Zeist",
    "sg:orig_category":"Onroerende Goederen",
    "sg:phone":"+31 30 691 4500",
    "sg:postcode":"3702 AA",
    "sg:province":"Utrecht",
    "wof:name":"Probo Holl Bv",
    "wof:placetype":"venue"
},
  "geometry": {"coordinates":[5.232069,52.08646],"type":"Point"}
}