{
  "type": "Feature",
  "properties": {
    "addr:full":"Gravenkasteel 1 Gastel North Brabant 6028 RK",
    "addr:housenumber":"1",
    "addr:postcode":"6028 rk",
    "addr:street":"Gravenkasteel",
    "iso:country":"NL",
    "sg:address":"Gravenkasteel 1",
    "sg:city":"Gastel",
    "sg:orig_category":"Krantenuitgeverijen",
    "sg:phone":"+31 495 430 930",
    "sg:postcode":"6028 RK",
    "sg:province":"North Brabant",
    "wof:name":"Automedia",
    "wof:placetype":"venue"
},
  "geometry": {"coordinates":[5.557014,51.285973],"type":"Point"}
}