{
  "type": "Feature",
  "properties": {
    "iso:country":"NL",
    "sg:address":"Piet Mondriaanstraat 3",
    "sg:city":"Deurne",
    "sg:orig_category":"Watersport-, Sport- And Kampeerbenodigdheden Verhuur",
    "sg:phone":"+31 493 321 132",
    "sg:postcode":"5753 DJ",
    "sg:province":"North Brabant",
    "wof:name":"Aventura Plus Yachtcharters",
    "wof:placetype":"venue"
},
  "geometry": {"coordinates":[5.7984762192,51.4490814209],"type":"Point"}
}