{
  "type": "Feature",
  "properties": {
    "addr:full":"De Eglantier 308 Apeldoorn Gelderland 7329 DJ",
    "addr:housenumber":"308",
    "addr:postcode":"7329 dj",
    "addr:street":"De Eglantier;Gelderland",
    "iso:country":"NL",
    "sg:address":"De Eglantier 308",
    "sg:city":"Apeldoorn",
    "sg:orig_category":"Fotostudio'S And Fotografen",
    "sg:phone":"+31 55 542 5200",
    "sg:postcode":"7329 DJ",
    "sg:province":"Gelderland",
    "wof:name":"Foto F.G.M. Kuipers Cv",
    "wof:placetype":"venue"
},
  "geometry": {"coordinates":[6.004235,52.195683],"type":"Point"}
}