{
  "type": "Feature",
  "properties": {
    "addr:full":"Lageweg 31 Zuidlaren Provincie Drenthe 9472 TD",
    "addr:housenumber":"31",
    "addr:postcode":"9472 td",
    "addr:street":"Lageweg;Provincie Drenthe",
    "iso:country":"NL",
    "sg:address":"Lageweg 31",
    "sg:city":"Zuidlaren",
    "sg:orig_category":"Beautyfarms And Sauna'S",
    "sg:phone":"+31 50 409 3769",
    "sg:postcode":"9472 TD",
    "sg:province":"Provincie Drenthe",
    "wof:name":"P. Lubberts",
    "wof:placetype":"venue"
},
  "geometry": {"coordinates":[6.701295,53.081024],"type":"Point"}
}