{
  "type": "Feature",
  "properties": {
    "addr:full":"Boompjesstraat 35 Strijen Zuid-Holland 3291 AA",
    "addr:housenumber":"35",
    "addr:postcode":"3291 aa",
    "addr:street":"Boompjesstraat",
    "iso:country":"NL",
    "sg:address":"Boompjesstraat 35",
    "sg:city":"Strijen",
    "sg:orig_category":"Fietshandelaren",
    "sg:phone":"+31 78 674 4124",
    "sg:postcode":"3291 AA",
    "sg:province":"Zuid-Holland",
    "wof:name":"Turbo Tweewielers",
    "wof:placetype":"venue"
},
  "geometry": {"coordinates":[4.551909,51.742104],"type":"Point"}
}