{
  "type": "Feature",
  "properties": {
    "iso:country":"NL",
    "sg:address":"Oenenburgwg 11",
    "sg:city":"Nunspeet",
    "sg:orig_category":"Vetsmelterijen",
    "sg:phone":"+31 341 251 250",
    "sg:postcode":"8072 GG",
    "sg:province":"Gelderland",
    "wof:name":"Wijk En Olthuis, Fa Van",
    "wof:placetype":"venue"
},
  "geometry": {"coordinates":[5.801563,52.37981],"type":"Point"}
}