{
  "type": "Feature",
  "properties": {
    "iso:country":"NL",
    "sg:address":"Geesterduin 4",
    "sg:city":"Castricum",
    "sg:orig_category":"Medische And Orthopedische Artikelen",
    "sg:phone":"+31 251 653 623",
    "sg:postcode":"1902 EK",
    "sg:province":"Noord-Holland",
    "wof:name":"Toornend Orthopedic Services",
    "wof:placetype":"venue"
},
  "geometry": {"coordinates":[4.675012,52.550385],"type":"Point"}
}