{
  "type": "Feature",
  "properties": {
    "addr:full":"De Opslach 3B Heerenveen Friesland 8448 GV",
    "addr:housenumber":"3b",
    "addr:postcode":"8448 gv",
    "addr:street":"De Opslach",
    "iso:country":"NL",
    "sg:address":"De Opslach 3B",
    "sg:city":"Heerenveen",
    "sg:orig_category":"Gassen Industrieel En Medisch",
    "sg:phone":"+31 513 620 136",
    "sg:postcode":"8448 GV",
    "sg:province":"Friesland",
    "wof:name":"Gascentrum Heerenveen Bv",
    "wof:placetype":"venue"
},
  "geometry": {"coordinates":[5.933538,52.962055],"type":"Point"}
}