{
  "type": "Feature",
  "properties": {
    "iso:country":"NL",
    "sg:address":"Onze Lieve Vrouwestraat 15",
    "sg:city":"Zegge",
    "sg:orig_category":"Goederenvervoer Over De Weg",
    "sg:phone":"+31 165 540 724",
    "sg:postcode":"4735 SL",
    "sg:province":"North Brabant",
    "wof:name":"Vof A. Van Overveld Transport",
    "wof:placetype":"venue"
},
  "geometry": {"coordinates":[4.51218,51.547112],"type":"Point"}
}