{
  "type": "Feature",
  "properties": {
    "iso:country":"NL",
    "sg:address":"Postbus 101",
    "sg:city":"Kesteren",
    "sg:orig_category":"Kinderopvang",
    "sg:phone":"+31 488 483 494",
    "sg:postcode":"4040 DC",
    "sg:province":"Gelderland",
    "wof:name":"Kinderopvang Kesteren, Sticht",
    "wof:placetype":"venue"
},
  "geometry": {"coordinates":[-77.01458700000001,38.8937],"type":"Point"}
}