{
  "type": "Feature",
  "properties": {
    "addr:full":"C V Bruggenhove 13 Zoetermeer Zuid-Holland 2717 XT",
    "addr:housenumber":"13",
    "addr:postcode":"2717 xt",
    "addr:street":"V Bruggenhove",
    "iso:country":"NL",
    "sg:address":"C V Bruggenhove 13",
    "sg:city":"Zoetermeer",
    "sg:orig_category":"Vertaalbureaus",
    "sg:phone":"+31 79 352 2939",
    "sg:postcode":"2717 XT",
    "sg:province":"Zuid-Holland",
    "wof:name":"Espalmia",
    "wof:placetype":"venue"
},
  "geometry": {"coordinates":[4.488925,52.06308],"type":"Point"}
}