{
  "type": "Feature",
  "properties": {
    "addr:full":"Parkzicht 21 Waarde Zeeland 4414 AE",
    "addr:housenumber":"21",
    "addr:postcode":"4414 ae",
    "addr:street":"Parkzicht",
    "iso:country":"NL",
    "sg:address":"Parkzicht 21",
    "sg:city":"Waarde",
    "sg:orig_category":"Kappers",
    "sg:phone":"+31 113 501 995",
    "sg:postcode":"4414 AE",
    "sg:province":"Zeeland",
    "wof:name":"Kapsalon Anja",
    "wof:placetype":"venue"
},
  "geometry": {"coordinates":[4.066172123,51.4197235107],"type":"Point"}
}