{
  "type": "Feature",
  "properties": {
    "addr:full":"Govert Flinckstraat 22 Zaandam Noord-Holland 1506 LM",
    "addr:housenumber":"22",
    "addr:postcode":"1506 lm",
    "addr:street":"Govert Flinckstraat",
    "iso:country":"NL",
    "sg:address":"Govert Flinckstraat 22",
    "sg:city":"Zaandam",
    "sg:orig_category":"Kantoorartikelen",
    "sg:phone":"+31 75 631 3856",
    "sg:postcode":"1506 LM",
    "sg:province":"Noord-Holland",
    "wof:name":"L. Thissen",
    "wof:placetype":"venue"
},
  "geometry": {"coordinates":[4.8125758171,52.4522171021],"type":"Point"}
}