{
  "type": "Feature",
  "properties": {
    "addr:full":"Vinkestraat 10 Hengevelde Overijssel 7496 AS",
    "addr:housenumber":"10",
    "addr:postcode":"7496 as",
    "addr:street":"Vinkestraat",
    "iso:country":"NL",
    "sg:address":"Vinkestraat 10",
    "sg:city":"Hengevelde",
    "sg:orig_category":"Goederenvervoer Over De Weg",
    "sg:phone":"+31 547 333 350",
    "sg:postcode":"7496 AS",
    "sg:province":"Overijssel",
    "wof:name":"H.J. Wibbelink",
    "wof:placetype":"venue"
},
  "geometry": {"coordinates":[6.632207,52.199009],"type":"Point"}
}