{
  "type": "Feature",
  "properties": {
    "iso:country":"NL",
    "sg:address":"Sint Jansgildestraat 35",
    "sg:city":"Beek Gem Bergh",
    "sg:orig_category":"Schilderwerk",
    "sg:phone":"+31 316 531 265",
    "sg:postcode":"7037 CB",
    "sg:province":"Gelderland",
    "wof:name":"Span Schilderwerken Bv",
    "wof:placetype":"venue"
},
  "geometry": {"coordinates":[6.193075,51.912247],"type":"Point"}
}