{
  "type": "Feature",
  "properties": {
    "addr:full":"V Brammendreef 33 Utrecht Utrecht 3561 XD",
    "addr:housenumber":"33",
    "addr:postcode":"3561 xd",
    "addr:street":"Brammendreef",
    "iso:country":"NL",
    "sg:address":"V Brammendreef 33",
    "sg:city":"Utrecht",
    "sg:orig_category":"Vertaalbureaus",
    "sg:phone":"+31 30 266 2977",
    "sg:postcode":"3561 XD",
    "sg:province":"Utrecht",
    "sg:website":"http://home.wxs.nl/tidea.kuijk",
    "wof:name":"Virtuoos",
    "wof:placetype":"venue"
},
  "geometry": {"coordinates":[5.12395,52.11272],"type":"Point"}
}