{
  "type": "Feature",
  "properties": {
    "addr:full":"Kuiperpln 9 Ede Gld Gelderland 6713 AX",
    "addr:housenumber":"9",
    "addr:postcode":"6713 ax",
    "addr:street":"Kuiperpln;Gld Gelderland",
    "iso:country":"NL",
    "sg:address":"Kuiperpln 9",
    "sg:city":"Ede Gld",
    "sg:orig_category":"Biljartzalen",
    "sg:phone":"+31 318 615 715",
    "sg:postcode":"6713 AX",
    "sg:province":"Gelderland",
    "wof:name":"Biljart En Snookercentrum Ede",
    "wof:placetype":"venue"
},
  "geometry": {"coordinates":[5.668675,52.045357],"type":"Point"}
}