{
  "type": "Feature",
  "properties": {
    "addr:full":"H W Mesdagstr 6 Apeldoorn Gelderland 7312 LP",
    "addr:housenumber":"6",
    "addr:postcode":"7312 lp",
    "addr:street":"H W Mesdagstr;Gelderland",
    "iso:country":"NL",
    "sg:address":"H W Mesdagstr 6",
    "sg:city":"Apeldoorn",
    "sg:orig_category":"Duikers",
    "sg:phone":"+31 55 541 6312",
    "sg:postcode":"7312 LP",
    "sg:province":"Gelderland",
    "wof:name":"Sterckel",
    "wof:placetype":"venue"
},
  "geometry": {"coordinates":[5.941839,52.200764],"type":"Point"}
}