{
  "type": "Feature",
  "properties": {
    "addr:full":"Tienhovenseweg 43 Everdingen Utrecht 4121 KT",
    "addr:housenumber":"43",
    "addr:postcode":"4121 kt",
    "addr:street":"Tienhovenseweg",
    "iso:country":"NL",
    "sg:address":"Tienhovenseweg 43",
    "sg:city":"Everdingen",
    "sg:orig_category":"Autokeuringen",
    "sg:phone":"+31 347 351 865",
    "sg:postcode":"4121 KT",
    "sg:province":"Utrecht",
    "wof:name":"A.M. Bouwman",
    "wof:placetype":"venue"
},
  "geometry": {"coordinates":[5.13912,51.961582],"type":"Point"}
}