{
  "type": "Feature",
  "properties": {
    "addr:full":"Kazernestr 88D S Gravenhage Zuid-Holland 2514 CW",
    "addr:housenumber":"88d;gravenhage",
    "addr:postcode":"2514 cw",
    "addr:street":"Kazernestr;S",
    "iso:country":"NL",
    "sg:address":"Kazernestr 88D",
    "sg:city":"S Gravenhage",
    "sg:orig_category":"Goudsmeden En Zilversmeden",
    "sg:phone":"+31 70 345 7879",
    "sg:postcode":"2514 CW",
    "sg:province":"Zuid-Holland",
    "wof:name":"Atelierdeneuve",
    "wof:placetype":"venue"
},
  "geometry": {"coordinates":[4.30935,52.084148],"type":"Point"}
}