{
  "type": "Feature",
  "properties": {
    "addr:full":"Dorpsstraat 37 Breskens Zeeland 4511 EB",
    "addr:housenumber":"37",
    "addr:postcode":"4511 eb",
    "addr:street":"Dorpsstraat",
    "iso:country":"NL",
    "sg:address":"Dorpsstraat 37",
    "sg:city":"Breskens",
    "sg:classifiers":[
        {
            "category":"Bakery",
            "type":"Food & Drink"
        }
    ],
    "sg:phone":"+31 117 381 746",
    "sg:postcode":"4511 EB",
    "sg:province":"Zeeland",
    "sg:tags":[
        "brood",
        "banket"
    ],
    "wof:name":"J.H. Maas",
    "wof:placetype":"venue"
},
  "geometry": {"coordinates":[3.556103,51.395428],"type":"Point"}
}