{
  "type": "Feature",
  "properties": {
    "addr:full":"Rhodenstr 4 Rhoon Zuid-Holland 3161 BG",
    "addr:housenumber":"4",
    "addr:postcode":"3161",
    "addr:street":"Rhodenstr",
    "iso:country":"NL",
    "sg:address":"Rhodenstr 4",
    "sg:city":"Rhoon",
    "sg:orig_category":"Wijnkoperijen En -Groothandel",
    "sg:phone":"+31 10 501 6929",
    "sg:postcode":"3161 BG",
    "sg:province":"Zuid-Holland",
    "wof:name":"Prins, L A H",
    "wof:placetype":"venue"
},
  "geometry": {"coordinates":[-108.6639175415,39.1203308105],"type":"Point"}
}