{
  "type": "Feature",
  "properties": {
    "addr:full":"Grt Markt 36-38 Bergen Op Zoom Noord-Brabant 4611 NT",
    "addr:postcode":"36-38;4611 nt",
    "addr:street":"Markt",
    "iso:country":"NL",
    "sg:address":"Grt Markt 36-38",
    "sg:city":"Bergen Op Zoom",
    "sg:classifiers":[
        {
            "category":"Travel",
            "subcategory":"Hotels & Motels",
            "type":"Entertainment"
        }
    ],
    "sg:phone":"+31 164 252 050",
    "sg:postcode":"4611 NT",
    "sg:province":"Noord-Brabant",
    "wof:name":"Mercure, Hotel De Draak",
    "wof:placetype":"venue"
},
  "geometry": {"coordinates":[4.281987,51.495953],"type":"Point"}
}