{
  "type": "Feature",
  "properties": {
    "addr:full":"Graafsewg 194B S Hertogenbosch Noord-Brabant 5213 AP",
    "addr:housenumber":"194b",
    "addr:postcode":"5213 ap",
    "addr:street":"S Hertogenbosch",
    "iso:country":"NL",
    "sg:address":"Graafsewg 194B",
    "sg:city":"S Hertogenbosch",
    "sg:orig_category":"Beeldende Kunstenaars",
    "sg:phone":"+31 73 612 5045",
    "sg:postcode":"5213 AP",
    "sg:province":"Noord-Brabant",
    "wof:name":"Visualize Dreams",
    "wof:placetype":"venue"
},
  "geometry": {"coordinates":[5.325045,51.696583],"type":"Point"}
}