{
  "type": "Feature",
  "properties": {
    "addr:full":"Zuiderpark 1 Groningen Groningen 9724 AD",
    "addr:housenumber":"1",
    "addr:postcode":"9724 ad",
    "addr:street":"Zuiderpark",
    "iso:country":"NL",
    "sg:address":"Zuiderpark 1",
    "sg:city":"Groningen",
    "sg:orig_category":"Hypotheken And Hypotheekbanken",
    "sg:phone":"+31 50 311 4582",
    "sg:postcode":"9724 AD",
    "sg:province":"Groningen",
    "wof:name":"Fgh Bank Nv",
    "wof:placetype":"venue"
},
  "geometry": {"coordinates":[6.570914,53.212223],"type":"Point"}
}