{
  "type": "Feature",
  "properties": {
    "addr:full":"W A Scholtenstr 32 Assen Drenthe 9403 AK",
    "addr:housenumber":"32",
    "addr:postcode":"9403 ak",
    "addr:street":"W A Scholtenstr",
    "iso:country":"NL",
    "sg:address":"W A Scholtenstr 32",
    "sg:city":"Assen",
    "sg:orig_category":"Verf En Lak - Fabrieken En Groothandel",
    "sg:phone":"+31 592 344 233",
    "sg:postcode":"9403 AK",
    "sg:province":"Drenthe",
    "wof:name":"Olijslager Bv",
    "wof:placetype":"venue"
},
  "geometry": {"coordinates":[6.574544,53.007889],"type":"Point"}
}