{
  "type": "Feature",
  "properties": {
    "addr:full":"Langestr 68 Winschoten Groningen 9671 PJ",
    "addr:housenumber":"68",
    "addr:postcode":"9671 pj",
    "addr:street":"Langestr",
    "iso:country":"NL",
    "sg:address":"Langestr 68",
    "sg:city":"Winschoten",
    "sg:orig_category":"Opticiens",
    "sg:phone":"+31 597 412 366",
    "sg:postcode":"9671 PJ",
    "sg:province":"Groningen",
    "wof:name":"Koning Optiek",
    "wof:placetype":"venue"
},
  "geometry": {"coordinates":[7.0351071358,53.1450691223],"type":"Point"}
}