{
  "type": "Feature",
  "properties": {
    "addr:full":"Maliebaan 64 Utrecht Utrecht 3581 CT",
    "addr:housenumber":"64",
    "addr:postcode":"3581 ct",
    "addr:street":"Maliebaan",
    "iso:country":"NL",
    "sg:address":"Maliebaan 64",
    "sg:city":"Utrecht",
    "sg:orig_category":"Adviesbureaus Bedrijfsorganisatie",
    "sg:phone":"+31 30 236 9485",
    "sg:postcode":"3581 CT",
    "sg:province":"Utrecht",
    "wof:name":"Meijer",
    "wof:placetype":"venue"
},
  "geometry": {"coordinates":[5.134926,52.092781],"type":"Point"}
}