{
  "type": "Feature",
  "properties": {
    "addr:full":"P V Eyckheem 85 Hillegom North Holland 2182 ZV",
    "addr:housenumber":"85",
    "addr:postcode":"2182 zv",
    "addr:street":"Eyckheem",
    "iso:country":"NL",
    "sg:address":"P V Eyckheem 85",
    "sg:city":"Hillegom",
    "sg:orig_category":"Organisatiebureaus",
    "sg:phone":"+31 252 525 012",
    "sg:postcode":"2182 ZV",
    "sg:province":"North Holland",
    "wof:name":"Bob",
    "wof:placetype":"venue"
},
  "geometry": {"coordinates":[4.5786027908,52.2909927368],"type":"Point"}
}