{
  "type": "Feature",
  "properties": {
    "addr:full":"Handelswg 15 Vlissingen Zeeland 4387 PC",
    "addr:housenumber":"15",
    "addr:postcode":"4387 pc",
    "addr:street":"Handelswg",
    "iso:country":"NL",
    "sg:address":"Handelswg 15",
    "sg:city":"Vlissingen",
    "sg:orig_category":"Elektrotechnische Installatiebureaus",
    "sg:phone":"+31 118 490 800",
    "sg:postcode":"4387 PC",
    "sg:province":"Zeeland",
    "wof:name":"Pwe",
    "wof:placetype":"venue"
},
  "geometry": {"coordinates":[3.59161,51.471512],"type":"Point"}
}