{
  "type": "Feature",
  "properties": {
    "addr:full":"Noorddammerweg 95 Amstelveen Noord-Holland 1187 ZS",
    "addr:housenumber":"95",
    "addr:postcode":"1187 zs",
    "addr:street":"Noorddammerweg",
    "iso:country":"NL",
    "sg:address":"Noorddammerweg 95",
    "sg:city":"Amstelveen",
    "sg:orig_category":"Bloemen And Planten",
    "sg:phone":"+31 20 426 4300",
    "sg:postcode":"1187 ZS",
    "sg:province":"Noord-Holland",
    "wof:name":"Edelcactus Bv",
    "wof:placetype":"venue"
},
  "geometry": {"coordinates":[4.812091,52.263988],"type":"Point"}
}