{
  "type": "Feature",
  "properties": {
    "addr:full":"Damstraat 7 Amsterdam Noord-Holland 1012  J",
    "addr:housenumber":"7;1012 j",
    "addr:street":"Damstraat",
    "iso:country":"NL",
    "sg:address":"Damstraat 7",
    "sg:city":"Amsterdam",
    "sg:orig_category":"Kunst And Kunstenaarsbenodigdheden",
    "sg:phone":"+31 20 624 0724",
    "sg:postcode":"1012  J",
    "sg:province":"Noord-Holland",
    "wof:name":"D. Eberhardt Aziatische Kunst Bv",
    "wof:placetype":"venue"
},
  "geometry": {"coordinates":[4.894474,52.372452],"type":"Point"}
}