{
  "type": "Feature",
  "properties": {
    "addr:full":"Burgveldwg 23 Meerlo Limburg 5864 AJ",
    "addr:housenumber":"23",
    "addr:postcode":"5864 aj",
    "addr:street":"Burgveldwg",
    "iso:country":"NL",
    "sg:address":"Burgveldwg 23",
    "sg:city":"Meerlo",
    "sg:orig_category":"Geluidsinstallaties - Verhuur",
    "sg:phone":"+31 478 691 320",
    "sg:postcode":"5864 AJ",
    "sg:province":"Limburg",
    "wof:name":"Lipzig, Geluidsinstallatieverhuur",
    "wof:placetype":"venue"
},
  "geometry": {"coordinates":[6.082634,51.513298],"type":"Point"}
}