{
  "type": "Feature",
  "properties": {
    "addr:full":"Hoofdstraat 154 Kaatsheuvel Noord-Brabant 5171 DH",
    "addr:housenumber":"154",
    "addr:postcode":"5171 dh",
    "addr:street":"Hoofdstraat",
    "iso:country":"NL",
    "sg:address":"Hoofdstraat 154",
    "sg:city":"Kaatsheuvel",
    "sg:orig_category":"Autokeuringen",
    "sg:phone":"+31 416 273 802",
    "sg:postcode":"5171 DH",
    "sg:province":"Noord-Brabant",
    "wof:name":"Garage Ronald Kuis",
    "wof:placetype":"venue"
},
  "geometry": {"coordinates":[5.025237,51.661976],"type":"Point"}
}