{
  "type": "Feature",
  "properties": {
    "iso:country":"NL",
    "sg:address":"Hoofdstraat 154",
    "sg:city":"Kaatsheuvel",
    "sg:orig_category":"Autokeuringen",
    "sg:phone":"+31 416 273 802",
    "sg:postcode":"5171 DH",
    "sg:province":"Noord-Brabant",
    "wof:name":"Garage Ronald Kuis",
    "wof:placetype":"venue"
},
  "geometry": {"coordinates":[5.025237,51.661976],"type":"Point"}
}