{
  "type": "Feature",
  "properties": {
    "iso:country":"NL",
    "sg:address":"Robijndk 215",
    "sg:city":"Roosendaal",
    "sg:orig_category":"Begrafenisverzorging",
    "sg:phone":"+31 165 542 928",
    "sg:postcode":"4706 MG",
    "sg:province":"Noord-Brabant",
    "sg:website":"http://www.dela.nl",
    "wof:name":"Dela",
    "wof:placetype":"venue"
},
  "geometry": {"coordinates":[4.4874,51.5187],"type":"Point"}
}