{
  "type": "Feature",
  "properties": {
    "addr:full":"Breedeplaats 1 Franeker Friesland 8801 LZ",
    "addr:housenumber":"1",
    "addr:postcode":"8801 lz",
    "addr:street":"Breedeplaats",
    "iso:country":"NL",
    "sg:address":"Breedeplaats 1",
    "sg:city":"Franeker",
    "sg:orig_category":"Projectontwikkeling",
    "sg:phone":"+31 517 390 012",
    "sg:postcode":"8801 LZ",
    "sg:province":"Friesland",
    "wof:name":"Projectbureau Nw Friesland",
    "wof:placetype":"venue"
},
  "geometry": {"coordinates":[5.544042,53.186085],"type":"Point"}
}