{
  "type": "Feature",
  "properties": {
    "iso:country":"NL",
    "sg:address":"Leggelostr 63",
    "sg:city":"S Gravenhage",
    "sg:orig_category":"Verenigingen En Stichtingen",
    "sg:phone":"+31 70 367 0339",
    "sg:postcode":"2541 HR",
    "sg:province":"South Holland",
    "wof:name":"Haag Wonen, Huurdersvereniging",
    "wof:placetype":"venue"
},
  "geometry": {"coordinates":[4.28115,52.04451],"type":"Point"}
}