{
  "type": "Feature",
  "properties": {
    "addr:full":"Burg Fockstr 56 Amsterdam North Holland 1063 CV",
    "addr:housenumber":"56",
    "addr:postcode":"1063 cv",
    "addr:street":"Burg",
    "iso:country":"NL",
    "sg:address":"Burg Fockstr 56",
    "sg:city":"Amsterdam",
    "sg:orig_category":"Kappers",
    "sg:phone":"+31 20 613 1231",
    "sg:postcode":"1063 CV",
    "sg:province":"North Holland",
    "wof:name":"Bakker, H",
    "wof:placetype":"venue"
},
  "geometry": {"coordinates":[4.8327488899,52.38048172],"type":"Point"}
}