{
  "type": "Feature",
  "properties": {
    "addr:full":"Dorpsstraat 198 Zoetermeer South Holland 2712 AR",
    "addr:housenumber":"198",
    "addr:postcode":"2712",
    "addr:street":"Dorpsstraat",
    "iso:country":"NL",
    "sg:address":"Dorpsstraat 198",
    "sg:city":"Zoetermeer",
    "sg:classifiers":[
        {
            "category":"Retail",
            "subcategory":"Photofinishing",
            "type":"Services"
        }
    ],
    "sg:phone":"+31 79 316 9106",
    "sg:postcode":"2712 AR",
    "sg:province":"South Holland",
    "sg:tags":[
        "foto",
        "film"
    ],
    "wof:name":"Super Photo Snelservice",
    "wof:placetype":"venue"
},
  "geometry": {"coordinates":[4.501577,52.054192],"type":"Point"}
}