{
  "type": "Feature",
  "properties": {
    "addr:full":"De Gildekamp 1024 Nijmegen Gelderland 6545 KB",
    "addr:housenumber":"1024",
    "addr:postcode":"6545 kb",
    "addr:street":"De Gildekamp;Gelderland",
    "iso:country":"NL",
    "sg:address":"De Gildekamp 1024",
    "sg:city":"Nijmegen",
    "sg:classifiers":[
        {
            "category":"Professional",
            "subcategory":"Accounting & Tax Preparation",
            "type":"Services"
        }
    ],
    "sg:phone":"+31 24 378 9995",
    "sg:postcode":"6545 KB",
    "sg:province":"Gelderland",
    "sg:tags":[
        "accountant"
    ],
    "wof:name":"Accountantskantoor A.J.F.M. Schmeddes",
    "wof:placetype":"venue"
},
  "geometry": {"coordinates":[5.79837,51.831802],"type":"Point"}
}