{
  "type": "Feature",
  "properties": {
    "addr:full":"Geldereschwg 1 Winterswyk Meddo Gelderland 7104 AM",
    "addr:housenumber":"1",
    "addr:postcode":"7104",
    "addr:street":"Geldereschwg;Gelderland",
    "iso:country":"NL",
    "sg:address":"Geldereschwg 1",
    "sg:city":"Winterswyk Meddo",
    "sg:classifiers":[
        {
            "category":"Food & Beverages",
            "subcategory":"Bakery",
            "type":"Retail Goods"
        }
    ],
    "sg:phone":"+31 543 569 777",
    "sg:postcode":"7104 AM",
    "sg:province":"Gelderland",
    "sg:tags":[
        "brood",
        "en",
        "banket"
    ],
    "wof:name":"Weme, Ter",
    "wof:placetype":"venue"
},
  "geometry": {"coordinates":[6.708769,52.01368],"type":"Point"}
}