{
  "type": "Feature",
  "properties": {
    "addr:full":"F.A. Molijnlaan 28 Nunspeet Gelderland 8071 AG",
    "addr:housenumber":"28",
    "addr:postcode":"8071",
    "addr:street":"F.A. Molijnlaan;Gelderland",
    "iso:country":"NL",
    "sg:address":"F.A. Molijnlaan 28",
    "sg:city":"Nunspeet",
    "sg:orig_category":"Makelaars In Onroerend Goed",
    "sg:phone":"+31 341 252 363",
    "sg:postcode":"8071 AG",
    "sg:province":"Gelderland",
    "wof:name":"A. Van De Loosdrecht En Co. Bv",
    "wof:placetype":"venue"
},
  "geometry": {"coordinates":[5.787565,52.371716],"type":"Point"}
}