{
  "type": "Feature",
  "properties": {
    "iso:country":"NL",
    "sg:address":"Terminalwg 41",
    "sg:city":"Amersfoort",
    "sg:orig_category":"Machineonderhoud En -Reparatie",
    "sg:phone":"+31 33 456 7722",
    "sg:postcode":"3821 AJ",
    "sg:province":"Utrecht",
    "sg:website":"http://www.ising.nl",
    "wof:name":"Ising Services Bv",
    "wof:placetype":"venue"
},
  "geometry": {"coordinates":[5.420571,52.177406],"type":"Point"}
}