{
  "type": "Feature",
  "properties": {
    "addr:full":"Randwyksngl 6 Malden Gelderland 6581 CE",
    "addr:housenumber":"6",
    "addr:postcode":"6581 ce",
    "addr:street":"Randwyksngl;Gelderland",
    "iso:country":"NL",
    "sg:address":"Randwyksngl 6",
    "sg:city":"Malden",
    "sg:orig_category":"Administratie- En Boekhoudkantoren",
    "sg:phone":"+31 24 358 2213",
    "sg:postcode":"6581 CE",
    "sg:province":"Gelderland",
    "wof:name":"Bisseling, H G J",
    "wof:placetype":"venue"
},
  "geometry": {"coordinates":[5.852469,51.781147],"type":"Point"}
}