{
  "type": "Feature",
  "properties": {
    "iso:country":"NL",
    "sg:address":"Zilverpk 61",
    "sg:city":"S Hertogenbosch",
    "sg:orig_category":"Kasregisters",
    "sg:phone":"+31 73 642 0144",
    "sg:postcode":"5237 HS",
    "sg:province":"North Brabant",
    "sg:website":"http://www.chevaliers.nl",
    "wof:name":"Chevaliers",
    "wof:placetype":"venue"
},
  "geometry": {"coordinates":[5.294691,51.729046],"type":"Point"}
}