{
  "type": "Feature",
  "properties": {
    "addr:full":"Willemsvaart 1-504 Zwolle Overijssel 8019 AA",
    "addr:housenumber":"1-504",
    "addr:postcode":"8019 aa",
    "addr:street":"Willemsvaart",
    "iso:country":"NL",
    "sg:address":"Willemsvaart 1-504",
    "sg:city":"Zwolle",
    "sg:classifiers":[
        {
            "category":"Utilities",
            "subcategory":"Cable",
            "type":"Services"
        }
    ],
    "sg:phone":"+31 6 53713353",
    "sg:postcode":"8019 AA",
    "sg:province":"Overijssel",
    "sg:tags":[
        "masseur",
        "en",
        "heilgymnasten"
    ],
    "wof:name":"Stoel Massages, De",
    "wof:placetype":"venue"
},
  "geometry": {"coordinates":[6.082162,52.507298],"type":"Point"}
}