{
  "type": "Feature",
  "properties": {
    "addr:full":"J Steenstr 59 Woerden Utrecht 3443 GS",
    "addr:housenumber":"59",
    "addr:postcode":"3443 gs",
    "addr:street":"Woerden",
    "iso:country":"NL",
    "sg:address":"J Steenstr 59",
    "sg:city":"Woerden",
    "sg:orig_category":"Acupunctuur",
    "sg:phone":"+31 348 419 824",
    "sg:postcode":"3443 GS",
    "sg:province":"Utrecht",
    "wof:name":"Woen, W M",
    "wof:placetype":"venue"
},
  "geometry": {"coordinates":[4.872776,52.090302],"type":"Point"}
}