{
  "type": "Feature",
  "properties": {
    "addr:full":"Hogerlustlaan 38 Ouderkerk A/D Amstel North Holland 1191 CN",
    "addr:housenumber":"38;a / d",
    "addr:postcode":"1191 cn",
    "addr:street":"Hogerlustlaan;Amstel North",
    "iso:country":"NL",
    "sg:address":"Hogerlustlaan 38",
    "sg:city":"Ouderkerk A/D Amstel",
    "sg:orig_category":"Marktonderzoekbureaus",
    "sg:phone":"+31 20 496 4925",
    "sg:postcode":"1191 CN",
    "sg:province":"North Holland",
    "wof:name":"S. Mink",
    "wof:placetype":"venue"
},
  "geometry": {"coordinates":[4.910185,52.297966],"type":"Point"}
}