{
  "type": "Feature",
  "properties": {
    "addr:full":"G V Prinstererstr 67 Vlaardingen Zuid-Holland 3131 GE",
    "addr:housenumber":"67",
    "addr:postcode":"3131",
    "addr:street":"V Prinstererstr",
    "iso:country":"NL",
    "sg:address":"G V Prinstererstr 67",
    "sg:city":"Vlaardingen",
    "sg:orig_category":"Verenigingen En Stichtingen",
    "sg:phone":"+31 10 435 0380",
    "sg:postcode":"3131 GE",
    "sg:province":"Zuid-Holland",
    "wof:name":"Vrijwilligers Vakature Bank",
    "wof:placetype":"venue"
},
  "geometry": {"coordinates":[4.340359,51.910442],"type":"Point"}
}