{
  "type": "Feature",
  "properties": {
    "addr:full":"Kerkstraat 19 Berkel En Rodenrijs Zuid-Holland 2651 CD",
    "addr:housenumber":"19",
    "addr:postcode":"2651 cd",
    "addr:street":"Kerkstraat",
    "iso:country":"NL",
    "sg:address":"Kerkstraat 19",
    "sg:city":"Berkel En Rodenrijs",
    "sg:orig_category":"Hypotheken And Hypotheekbanken",
    "sg:phone":"+31 10 519 0722",
    "sg:postcode":"2651 CD",
    "sg:province":"Zuid-Holland",
    "wof:name":"Holland Hypotheek Groep",
    "wof:placetype":"venue"
},
  "geometry": {"coordinates":[4.477296,51.99374],"type":"Point"}
}