{
  "type": "Feature",
  "properties": {
    "addr:full":"Nw Uilenburgerstr 116 Amsterdam Noord-Holland 1011 LX",
    "addr:housenumber":"116",
    "addr:postcode":"1011 lx",
    "iso:country":"NL",
    "sg:address":"Nw Uilenburgerstr 116",
    "sg:city":"Amsterdam",
    "sg:orig_category":"Discotheken",
    "sg:phone":"+31 20 624 9566",
    "sg:postcode":"1011 LX",
    "sg:province":"Noord-Holland",
    "wof:name":"Caribbean",
    "wof:placetype":"venue"
},
  "geometry": {"coordinates":[4.903155,52.369846],"type":"Point"}
}