{
  "type": "Feature",
  "properties": {
    "addr:full":"Badhuisstraat 218 'S Gravenhage South Holland 2584 HN",
    "addr:housenumber":"218 '",
    "addr:postcode":"2584 hn",
    "addr:street":"Badhuisstraat",
    "iso:country":"NL",
    "sg:address":"Badhuisstraat 218",
    "sg:city":"'S Gravenhage",
    "sg:orig_category":"Medische Apparatuur And Prothesen Fab",
    "sg:phone":"+31 70 354 8448",
    "sg:postcode":"2584 HN",
    "sg:province":"South Holland",
    "wof:name":"Alg Tandprothetisch Lab Taubman",
    "wof:placetype":"venue"
},
  "geometry": {"coordinates":[4.279347,52.103466],"type":"Point"}
}