{
  "type": "Feature",
  "properties": {
    "iso:country":"NL",
    "sg:address":"Hoofdstr 77",
    "sg:city":"Kaatsheuvel",
    "sg:orig_category":"Huishoudelijke Apparaten En Artikelen",
    "sg:phone":"+31 416 540 347",
    "sg:postcode":"5171 DK",
    "sg:province":"Noord-Brabant",
    "wof:name":"Blokker Bv",
    "wof:placetype":"venue"
},
  "geometry": {"coordinates":[5.033193,51.661606],"type":"Point"}
}