{
  "type": "Feature",
  "properties": {
    "addr:full":"Vrye Nesse 140 Bodegraven Zuid-Holland 2411 GS",
    "addr:housenumber":"140",
    "addr:postcode":"2411 gs",
    "addr:street":"Nesse",
    "iso:country":"NL",
    "sg:address":"Vrye Nesse 140",
    "sg:city":"Bodegraven",
    "sg:orig_category":"Kappers",
    "sg:phone":"+31 172 610 860",
    "sg:postcode":"2411 GS",
    "sg:province":"Zuid-Holland",
    "wof:name":"Trendline, Kapsalon",
    "wof:placetype":"venue"
},
  "geometry": {"coordinates":[4.746799,52.079189],"type":"Point"}
}