{
  "type": "Feature",
  "properties": {
    "addr:full":"Sportterreinstraat 78 Wildervank Groningen 9648 CD",
    "addr:housenumber":"78",
    "addr:postcode":"9648 cd",
    "addr:street":"Sportterreinstraat",
    "iso:country":"NL",
    "sg:address":"Sportterreinstraat 78",
    "sg:city":"Wildervank",
    "sg:orig_category":"Bloemen And Planten",
    "sg:phone":"+31 598 617 232",
    "sg:postcode":"9648 CD",
    "sg:province":"Groningen",
    "wof:name":"Gerard'S Bloemenkas",
    "wof:placetype":"venue"
},
  "geometry": {"coordinates":[6.868103,53.090191],"type":"Point"}
}