{
  "type": "Feature",
  "properties": {
    "addr:full":"De Middend 50 Bovenkarspel Noord-Holland 1611 KT",
    "addr:housenumber":"50",
    "addr:postcode":"1611 kt",
    "addr:street":"De Middend",
    "iso:country":"NL",
    "sg:address":"De Middend 50",
    "sg:city":"Bovenkarspel",
    "sg:orig_category":"Kappers",
    "sg:phone":"+31 228 514 540",
    "sg:postcode":"1611 KT",
    "sg:province":"Noord-Holland",
    "wof:name":"Swart, H",
    "wof:placetype":"venue"
},
  "geometry": {"coordinates":[5.234896,52.69595],"type":"Point"}
}