{
  "type": "Feature",
  "properties": {
    "iso:country":"NL",
    "sg:address":"Erve Hams 1",
    "sg:city":"Oldenzaal",
    "sg:orig_category":"Scholen Voor Basisonderwijs",
    "sg:phone":"+31 541 533 131",
    "sg:postcode":"7577 NK",
    "sg:province":"Overijssel",
    "wof:name":"Bongerd, De",
    "wof:placetype":"venue"
},
  "geometry": {"coordinates":[6.908818,52.322254],"type":"Point"}
}