{
  "type": "Feature",
  "properties": {
    "addr:full":"Postbus 225 Leiderdorp Zuid-Holland 2350 AE",
    "addr:housenumber":"225",
    "addr:postcode":"2350 ae",
    "addr:street":"Postbus",
    "iso:country":"NL",
    "sg:address":"Postbus 225",
    "sg:city":"Leiderdorp",
    "sg:orig_category":"Postorderbedrijven",
    "sg:phone":"+31 71 589 9899",
    "sg:postcode":"2350 AE",
    "sg:province":"Zuid-Holland",
    "sg:website":"http://www.extase-erotiek.nl",
    "wof:name":"Extase Erotiek",
    "wof:placetype":"venue"
},
  "geometry": {"coordinates":[4.534218,52.156174],"type":"Point"}
}