{
  "type": "Feature",
  "properties": {
    "addr:full":"Sprinterplaats 90 Vlaardingen Zuid-Holland 3134 TB",
    "addr:housenumber":"90",
    "addr:postcode":"3134 tb",
    "addr:street":"Sprinterplaats",
    "iso:country":"NL",
    "sg:address":"Sprinterplaats 90",
    "sg:city":"Vlaardingen",
    "sg:orig_category":"Verzekeringen",
    "sg:phone":"+31 10 435 8734",
    "sg:postcode":"3134 TB",
    "sg:province":"Zuid-Holland",
    "wof:name":"P & S Assurantien Bv",
    "wof:placetype":"venue"
},
  "geometry": {"coordinates":[4.351366,51.905472],"type":"Point"}
}