{
  "type": "Feature",
  "properties": {
    "addr:full":"Ginnekenweg 161 Breda Noord-Brabant 4818 JD",
    "addr:housenumber":"161",
    "addr:postcode":"4818 jd",
    "addr:street":"Ginnekenweg",
    "iso:country":"NL",
    "sg:address":"Ginnekenweg 161",
    "sg:city":"Breda",
    "sg:orig_category":"Makelaars In Onroerend Goed",
    "sg:phone":"+31 76 522 6090",
    "sg:postcode":"4818 JD",
    "sg:province":"Noord-Brabant",
    "wof:name":"De Boer Storimans & Partners Bv",
    "wof:placetype":"venue"
},
  "geometry": {"coordinates":[4.783434,51.573887],"type":"Point"}
}