{
  "type": "Feature",
  "properties": {
    "addr:full":"Platielstr 20 Maastricht Limburg 6211 GV",
    "addr:housenumber":"20",
    "addr:postcode":"6211 gv",
    "addr:street":"Platielstr",
    "iso:country":"NL",
    "sg:address":"Platielstr 20",
    "sg:city":"Maastricht",
    "sg:orig_category":"Juweliers",
    "sg:phone":"+31 43 358 1155",
    "sg:postcode":"6211 GV",
    "sg:province":"Limburg",
    "wof:name":"Burger Juwelier",
    "wof:placetype":"venue"
},
  "geometry": {"coordinates":[5.689378,50.848969],"type":"Point"}
}