{
  "type": "Feature",
  "properties": {
    "iso:country":"NL",
    "sg:address":"Rijn En Schiekade 135",
    "sg:city":"Leiden",
    "sg:orig_category":"Airconditioning And Ventilatie",
    "sg:phone":"+31 71 512 6586",
    "sg:postcode":"2311 AW",
    "sg:province":"Zuid-Holland",
    "wof:name":"Auto Airconditiong B.P. Haan",
    "wof:placetype":"venue"
},
  "geometry": {"coordinates":[4.482884,52.150677],"type":"Point"}
}