{
  "type": "Feature",
  "properties": {
    "addr:full":"Moerstraatsewg 84 Moerstraten Noord-Brabant 4727 SP",
    "addr:housenumber":"84",
    "addr:postcode":"4727 sp",
    "addr:street":"Moerstraatsewg",
    "iso:country":"NL",
    "sg:address":"Moerstraatsewg 84",
    "sg:city":"Moerstraten",
    "sg:orig_category":"Paardenhandelaren",
    "sg:phone":"+31 165 300 063",
    "sg:postcode":"4727 SP",
    "sg:province":"Noord-Brabant",
    "wof:name":"Verbunt",
    "wof:placetype":"venue"
},
  "geometry": {"coordinates":[4.34259,51.541107],"type":"Point"}
}