{
  "type": "Feature",
  "properties": {
    "iso:country":"NL",
    "sg:address":"Willem Ii Laan 38",
    "sg:city":"Landgraaf",
    "sg:orig_category":"Verzekeringen",
    "sg:phone":"+31 45 531 2199",
    "sg:postcode":"6371 JC",
    "sg:province":"Limburg",
    "wof:name":"Assurantiekantoor Janssens-Schiffers",
    "wof:placetype":"venue"
},
  "geometry": {"coordinates":[6.010752,50.902046],"type":"Point"}
}