{
  "type": "Feature",
  "properties": {
    "addr:full":"Willem Ii Laan 38 Landgraaf Limburg 6371 JC",
    "addr:housenumber":"38",
    "addr:postcode":"6371 jc",
    "addr:street":"Willem Ii Laan",
    "iso:country":"NL",
    "sg:address":"Willem Ii Laan 38",
    "sg:city":"Landgraaf",
    "sg:orig_category":"Verzekeringen",
    "sg:phone":"+31 45 531 2199",
    "sg:postcode":"6371 JC",
    "sg:province":"Limburg",
    "wof:name":"Assurantiekantoor Janssens-Schiffers",
    "wof:placetype":"venue"
},
  "geometry": {"coordinates":[6.010752,50.902046],"type":"Point"}
}