{
  "type": "Feature",
  "properties": {
    "iso:country":"NL",
    "sg:address":"Bosstraat 20",
    "sg:city":"Winschoten",
    "sg:orig_category":"Kappers",
    "sg:phone":"+31 597 431 132",
    "sg:postcode":"9671 GG",
    "sg:province":"Groningen",
    "wof:name":"Knipperij De Krul",
    "wof:placetype":"venue"
},
  "geometry": {"coordinates":[7.035362,53.14352],"type":"Point"}
}