{
  "type": "Feature",
  "properties": {
    "addr:full":"Bosstraat 20 Winschoten Groningen 9671 GG",
    "addr:housenumber":"20",
    "addr:postcode":"9671 gg",
    "addr:street":"Bosstraat",
    "iso:country":"NL",
    "sg:address":"Bosstraat 20",
    "sg:city":"Winschoten",
    "sg:orig_category":"Kappers",
    "sg:phone":"+31 597 431 132",
    "sg:postcode":"9671 GG",
    "sg:province":"Groningen",
    "wof:name":"Knipperij De Krul",
    "wof:placetype":"venue"
},
  "geometry": {"coordinates":[7.035362,53.14352],"type":"Point"}
}