{
  "type": "Feature",
  "properties": {
    "addr:full":"Markt 9 Panningen Limburg 5981 AM",
    "addr:housenumber":"9",
    "addr:postcode":"5981",
    "addr:street":"Markt",
    "iso:country":"NL",
    "sg:address":"Markt 9",
    "sg:city":"Panningen",
    "sg:orig_category":"Opticiens",
    "sg:phone":"+31 77 307 1071",
    "sg:postcode":"5981 AM",
    "sg:province":"Limburg",
    "wof:name":"Maaren, Carl Van",
    "wof:placetype":"venue"
},
  "geometry": {"coordinates":[5.9804430008,51.3288726807],"type":"Point"}
}