{
  "type": "Feature",
  "properties": {
    "addr:full":"Rietgors 10 Nieuwegein Utrecht 3435 CB",
    "addr:housenumber":"10",
    "addr:postcode":"3435 cb",
    "addr:street":"Rietgors",
    "iso:country":"NL",
    "sg:address":"Rietgors 10",
    "sg:city":"Nieuwegein",
    "sg:orig_category":"Verenigingen En Stichtingen",
    "sg:phone":"+31 30 604 0798",
    "sg:postcode":"3435 CB",
    "sg:province":"Utrecht",
    "wof:name":"Ned Ver Van Tandartsen",
    "wof:placetype":"venue"
},
  "geometry": {"coordinates":[5.078748,52.027206],"type":"Point"}
}