{
  "type": "Feature",
  "properties": {
    "addr:full":"Handelsweg 3 Joure Friesland 8501 XJ",
    "addr:housenumber":"3",
    "addr:postcode":"8501 xj",
    "addr:street":"Handelsweg",
    "iso:country":"NL",
    "sg:address":"Handelsweg 3",
    "sg:city":"Joure",
    "sg:orig_category":"Autokeuringen",
    "sg:phone":"+31 513 419 911",
    "sg:postcode":"8501 XJ",
    "sg:province":"Friesland",
    "wof:name":"Piet Rood Autoschade",
    "wof:placetype":"venue"
},
  "geometry": {"coordinates":[5.820774,52.964455],"type":"Point"}
}