{
  "type": "Feature",
  "properties": {
    "addr:full":"Oosterwykln 16 Kaatsheuvel North Brabant 5171 HD",
    "addr:housenumber":"16",
    "addr:postcode":"5171 hd",
    "addr:street":"Oosterwykln",
    "iso:country":"NL",
    "sg:address":"Oosterwykln 16",
    "sg:city":"Kaatsheuvel",
    "sg:orig_category":"Scholen Voor Basisonderwijs",
    "sg:phone":"+31 416 273 997",
    "sg:postcode":"5171 HD",
    "sg:province":"North Brabant",
    "wof:name":"Hil Rk, De",
    "wof:placetype":"venue"
},
  "geometry": {"coordinates":[5.030028,51.654339],"type":"Point"}
}