{
  "type": "Feature",
  "properties": {
    "addr:full":"Hofkamp 23 Geleen Limburg 6161 DC",
    "addr:housenumber":"23",
    "addr:postcode":"6161",
    "addr:street":"Hofkamp",
    "iso:country":"NL",
    "sg:address":"Hofkamp 23",
    "sg:city":"Geleen",
    "sg:orig_category":"Autopoetsbedrijven",
    "sg:phone":"+31 46 474 0059",
    "sg:postcode":"6161 DC",
    "sg:province":"Limburg",
    "wof:name":"Abc",
    "wof:placetype":"venue"
},
  "geometry": {"coordinates":[5.814123,50.959778],"type":"Point"}
}