{
  "type": "Feature",
  "properties": {
    "iso:country":"NL",
    "sg:address":"Dintelwg 89",
    "sg:city":"Europoort Rt",
    "sg:orig_category":"Pompen - Verhuur",
    "sg:phone":"+31 181 261 407",
    "sg:postcode":"3198 LB",
    "sg:province":"Zuid-Holland",
    "sg:website":"http://www.lttholland.com",
    "wof:name":"Ltt Bv",
    "wof:placetype":"venue"
},
  "geometry": {"coordinates":[4.125642,51.938187],"type":"Point"}
}