{
  "type": "Feature",
  "properties": {
    "iso:country":"NL",
    "sg:address":"Zutphensestrwg 21A",
    "sg:city":"Spankeren",
    "sg:orig_category":"Meubelen",
    "sg:phone":"+31 313 412 153",
    "sg:postcode":"6956 AA",
    "sg:province":"Gelderland",
    "wof:name":"Trendhouse",
    "wof:placetype":"venue"
},
  "geometry": {"coordinates":[-84.245392,39.856728],"type":"Point"}
}