{
  "type": "Feature",
  "properties": {
    "addr:full":"Bosstraat 5 Valkenburg Lb Limburg 6301 HM",
    "addr:housenumber":"5",
    "addr:postcode":"lb;6301 hm",
    "addr:street":"Bosstraat",
    "iso:country":"NL",
    "sg:address":"Bosstraat 5",
    "sg:city":"Valkenburg Lb",
    "sg:classifiers":[
        {
            "category":"Education",
            "subcategory":"Preschool",
            "type":"Public Place"
        }
    ],
    "sg:phone":"+31 43 601 5166",
    "sg:postcode":"6301 HM",
    "sg:province":"Limburg",
    "sg:tags":[
        "kleuteronderwijs",
        "basis-"
    ],
    "wof:name":"Peuterspeelzaal Mik Mak",
    "wof:placetype":"venue"
},
  "geometry": {"coordinates":[5.823164,50.871635],"type":"Point"}
}