{
  "type": "Feature",
  "properties": {
    "addr:full":"2E J V Campenstr 144-148 Amsterdam Noord-Holland 1073 XZ",
    "addr:housenumber":"144-148",
    "addr:postcode":"1073 xz",
    "addr:street":"2E J V Campenstr",
    "iso:country":"NL",
    "sg:address":"2E J V Campenstr 144-148",
    "sg:city":"Amsterdam",
    "sg:classifiers":[
        {
            "category":"Retail",
            "subcategory":"Auto Repair",
            "type":"Services"
        }
    ],
    "sg:phone":"+31 20 679 1924",
    "sg:postcode":"1073 XZ",
    "sg:province":"Noord-Holland",
    "sg:tags":[
        "garage"
    ],
    "sg:website":"http://www.westergarage.nl",
    "wof:name":"Westergarage",
    "wof:placetype":"venue"
},
  "geometry": {"coordinates":[4.896336,52.356915],"type":"Point"}
}