{
  "type": "Feature",
  "properties": {
    "addr:full":"Westb Binnenwg 68C Tienhoven Ut Utrecht 3612 AJ",
    "addr:housenumber":"68c",
    "addr:postcode":"3612 aj",
    "iso:country":"NL",
    "sg:address":"Westb Binnenwg 68C",
    "sg:city":"Tienhoven Ut",
    "sg:orig_category":"Meubelen",
    "sg:phone":"+31 346 282 909",
    "sg:postcode":"3612 AJ",
    "sg:province":"Utrecht",
    "wof:name":"Steen En Tafel",
    "wof:placetype":"venue"
},
  "geometry": {"coordinates":[5.08764,52.161224],"type":"Point"}
}