{
  "type": "Feature",
  "properties": {
    "addr:full":"V Baerlestr 10 Hs Amsterdam Noord-Holland 1071 AW",
    "addr:housenumber":"10 hs",
    "addr:postcode":"1071 aw",
    "iso:country":"NL",
    "sg:address":"V Baerlestr 10 Hs",
    "sg:city":"Amsterdam",
    "sg:orig_category":"Kappers",
    "sg:phone":"+31 20 618 1600",
    "sg:postcode":"1071 AW",
    "sg:province":"Noord-Holland",
    "wof:name":"Lorenzo Fuente Coiffures",
    "wof:placetype":"venue"
},
  "geometry": {"coordinates":[4.87701,52.355549],"type":"Point"}
}