{
  "type": "Feature",
  "properties": {
    "iso:country":"NL",
    "sg:address":"Lijnbaan 13",
    "sg:city":"Vianen Zh",
    "sg:orig_category":"Werving And Selectie Van Tijdelijk Personeel And Uitzendkantoren",
    "sg:phone":"+31 347 326 222",
    "sg:postcode":"4132 CB",
    "sg:province":"Utrecht",
    "wof:name":"Randstad",
    "wof:placetype":"venue"
},
  "geometry": {"coordinates":[5.0950517654,51.9915428162],"type":"Point"}
}