{
  "type": "Feature",
  "properties": {
    "iso:country":"NL",
    "sg:address":"Jasparstr 36",
    "sg:city":"Geleen",
    "sg:orig_category":"Keuken- Inbouwapparatuur",
    "sg:phone":"+31 46 475 1242",
    "sg:postcode":"6164 HX",
    "sg:province":"Limburg",
    "wof:name":"Apparatenservice",
    "wof:placetype":"venue"
},
  "geometry": {"coordinates":[5.835999,50.958549],"type":"Point"}
}