{
  "type": "Feature",
  "properties": {
    "addr:full":"Industriewg 8B Alphen Aan Den Ryn Zuid-Holland 2404 BZ",
    "addr:housenumber":"8b",
    "addr:postcode":"2404 bz",
    "addr:street":"Industriewg;Aan Den Ryn",
    "iso:country":"NL",
    "sg:address":"Industriewg 8B",
    "sg:city":"Alphen Aan Den Ryn",
    "sg:orig_category":"Geluidsinstallaties",
    "sg:phone":"+31 172 441 498",
    "sg:postcode":"2404 BZ",
    "sg:province":"Zuid-Holland",
    "sg:website":"http://www.overdevest-audio.nl",
    "wof:name":"Overdevest Audio Bv",
    "wof:placetype":"venue"
},
  "geometry": {"coordinates":[4.642894,52.135849],"type":"Point"}
}