{
  "type": "Feature",
  "properties": {
    "iso:country":"NL",
    "sg:address":"De Woerd .",
    "sg:city":"Driebergen Rysenb",
    "sg:orig_category":"Sportverenigingen En Ontspannings- Verenigingen",
    "sg:phone":"+31 343 517 923",
    "sg:postcode":"3972 KD",
    "sg:province":"Utrecht",
    "wof:name":"Dalto, Korfbalver",
    "wof:placetype":"venue"
},
  "geometry": {"coordinates":[5.26028,52.055725],"type":"Point"}
}