{
  "type": "Feature",
  "properties": {
    "addr:full":"Valthermussel 4 Tweede Valthermond Drenthe 7877 TA",
    "addr:housenumber":"4",
    "addr:postcode":"7877 ta",
    "addr:street":"Valthermussel;Tweede Valthermond",
    "iso:country":"NL",
    "sg:address":"Valthermussel 4",
    "sg:city":"Tweede Valthermond",
    "sg:orig_category":"Honden- En Kattentrimsalons",
    "sg:phone":"+31 599 416 131",
    "sg:postcode":"7877 TA",
    "sg:province":"Drenthe",
    "wof:name":"Sas",
    "wof:placetype":"venue"
},
  "geometry": {"coordinates":[7.019358,52.906029],"type":"Point"}
}