{
  "type": "Feature",
  "properties": {
    "iso:country":"NL",
    "sg:address":"Raadhuisstr 14",
    "sg:city":"Heerhugowaard",
    "sg:orig_category":"Hypotheken",
    "sg:phone":"+31 72 571 8187",
    "sg:postcode":"1701 EK",
    "sg:province":"Noord-Holland",
    "wof:name":"Hypotheeknet",
    "wof:placetype":"venue"
},
  "geometry": {"coordinates":[4.844902,52.669781],"type":"Point"}
}