{
  "type": "Feature",
  "properties": {
    "addr:full":"Hoofdstr 73 De Lier Zuid-Holland 2678 CG",
    "addr:housenumber":"73",
    "addr:postcode":"2678 cg",
    "addr:street":"Hoofdstr",
    "iso:country":"NL",
    "sg:address":"Hoofdstr 73",
    "sg:city":"De Lier",
    "sg:orig_category":"Fietsen En Bromfietsen",
    "sg:phone":"+31 174 511 144",
    "sg:postcode":"2678 CG",
    "sg:province":"Zuid-Holland",
    "wof:name":"Vijverberg Fietsen",
    "wof:placetype":"venue"
},
  "geometry": {"coordinates":[4.249659,51.974819],"type":"Point"}
}