{
  "type": "Feature",
  "properties": {
    "addr:full":"Engelenburg 37 Haarlem Noord-Holland 2036 RB",
    "addr:housenumber":"37",
    "addr:postcode":"2036 rb",
    "addr:street":"Engelenburg",
    "iso:country":"NL",
    "sg:address":"Engelenburg 37",
    "sg:city":"Haarlem",
    "sg:orig_category":"Huizensloop And Bouwrijp Maken",
    "sg:phone":"+31 23 535 1902",
    "sg:postcode":"2036 RB",
    "sg:province":"Noord-Holland",
    "wof:name":"Hercules",
    "wof:placetype":"venue"
},
  "geometry": {"coordinates":[4.652802,52.352489],"type":"Point"}
}