{
  "type": "Feature",
  "properties": {
    "addr:full":"Oliemolenwg 4A Meppel Drenthe 7944 HX",
    "addr:housenumber":"4a",
    "addr:postcode":"7944 hx",
    "addr:street":"Oliemolenwg",
    "iso:country":"NL",
    "sg:address":"Oliemolenwg 4A",
    "sg:city":"Meppel",
    "sg:orig_category":"Zuivel - Fabrieken",
    "sg:phone":"+31 522 238 138",
    "sg:postcode":"7944 HX",
    "sg:province":"Drenthe",
    "sg:website":"http://www.kievit.com",
    "wof:name":"Kievit",
    "wof:placetype":"venue"
},
  "geometry": {"coordinates":[6.171489,52.69215],"type":"Point"}
}