{
  "type": "Feature",
  "properties": {
    "iso:country":"NL",
    "sg:address":"Eindhovenseweg 264",
    "sg:city":"Valkenswaard",
    "sg:orig_category":"Overheidsdiensten",
    "sg:phone":"+31 40 204 0929",
    "sg:postcode":"5553 AA",
    "sg:province":"Noord-Brabant",
    "wof:name":"Brabanconne Culinaire Gilde",
    "wof:placetype":"venue"
},
  "geometry": {"coordinates":[5.4654798508,51.3670387268],"type":"Point"}
}