{
  "type": "Feature",
  "properties": {
    "addr:full":"Maire Hofstedelaan 56 Maarssen Utrecht 3601 BS",
    "addr:housenumber":"56",
    "addr:postcode":"3601 bs",
    "addr:street":"Maire Hofstedelaan",
    "iso:country":"NL",
    "sg:address":"Maire Hofstedelaan 56",
    "sg:city":"Maarssen",
    "sg:orig_category":"Metalen And Ertsen Gh",
    "sg:phone":"+31 346 563 216",
    "sg:postcode":"3601 BS",
    "sg:province":"Utrecht",
    "wof:name":"Ccm-Sail Plan",
    "wof:placetype":"venue"
},
  "geometry": {"coordinates":[5.052965,52.142712],"type":"Point"}
}