{
  "type": "Feature",
  "properties": {
    "addr:full":"Columbusweg 33 Venlo Limburg 5928 LA",
    "addr:housenumber":"33",
    "addr:postcode":"5928 la",
    "addr:street":"Columbusweg",
    "iso:country":"NL",
    "sg:address":"Columbusweg 33",
    "sg:city":"Venlo",
    "sg:orig_category":"Kantoorartikelen",
    "sg:phone":"+31 77 323 8888",
    "sg:postcode":"5928 LA",
    "sg:province":"Limburg",
    "wof:name":"Viking Direct",
    "wof:placetype":"venue"
},
  "geometry": {"coordinates":[6.0888972282,51.397769928],"type":"Point"}
}