{
  "type": "Feature",
  "properties": {
    "addr:full":"De Oude Werf 1 Heiloo North Holland 1851 PW",
    "addr:housenumber":"1",
    "addr:postcode":"1851 pw",
    "addr:street":"De Oude Werf",
    "iso:country":"NL",
    "sg:address":"De Oude Werf 1",
    "sg:city":"Heiloo",
    "sg:orig_category":"Autokeuringen",
    "sg:phone":"+31 72 533 8543",
    "sg:postcode":"1851 PW",
    "sg:province":"North Holland",
    "wof:name":"Van Der Steen Autobedrijf Bv",
    "wof:placetype":"venue"
},
  "geometry": {"coordinates":[4.719499,52.593182],"type":"Point"}
}