{
  "type": "Feature",
  "properties": {
    "iso:country":"NL",
    "sg:address":"Van Beresteynstraat 97",
    "sg:city":"Delft",
    "sg:orig_category":"Diverse Grafische Activiteiten",
    "sg:phone":"+31 15 213 8763",
    "sg:postcode":"2614 EB",
    "sg:province":"South Holland",
    "wof:name":"Chroma Grafisch Ontwerp",
    "wof:placetype":"venue"
},
  "geometry": {"coordinates":[4.338392,52.012196],"type":"Point"}
}