{
  "type": "Feature",
  "properties": {
    "iso:country":"NL",
    "sg:address":"De Lind 28",
    "sg:city":"Oisterwyk",
    "sg:orig_category":"Zoetwaren - Fabrieken En Groothandel",
    "sg:phone":"+31 13 523 3300",
    "sg:postcode":"5061 HW",
    "sg:province":"North Brabant",
    "wof:name":"Nedan Bv",
    "wof:placetype":"venue"
},
  "geometry": {"coordinates":[5.197082,51.580692],"type":"Point"}
}