{
  "type": "Feature",
  "properties": {
    "addr:full":"Van Heemskerckstraat 33 Amsterdam Noord-Holland 1013 NV",
    "addr:housenumber":"33",
    "addr:postcode":"1013 nv",
    "addr:street":"Van Heemskerckstraat",
    "iso:country":"NL",
    "sg:address":"Van Heemskerckstraat 33",
    "sg:city":"Amsterdam",
    "sg:classifiers":[
        {
            "category":"Fast Food",
            "type":"Food & Drink"
        }
    ],
    "sg:phone":"+31 20 623 9360",
    "sg:postcode":"1013 NV",
    "sg:province":"Noord-Holland",
    "sg:tags":[
        "afhaal",
        "restaurant"
    ],
    "wof:name":"Lucky Snacks",
    "wof:placetype":"venue"
},
  "geometry": {"coordinates":[4.885712,52.389095],"type":"Point"}
}