{
  "type": "Feature",
  "properties": {
    "iso:country":"NL",
    "sg:address":"Punter 4953",
    "sg:city":"Lelystad",
    "sg:orig_category":"Beveiliging",
    "sg:phone":"+31 320 227 237",
    "sg:postcode":"8242 GP",
    "sg:province":"Flevoland",
    "wof:name":"Vdc",
    "wof:placetype":"venue"
},
  "geometry": {"coordinates":[5.445723,52.519283],"type":"Point"}
}