{
  "type": "Feature",
  "properties": {
    "addr:full":"Brandstr 22 Sittard Limburg 6131 CT",
    "addr:housenumber":"22",
    "addr:postcode":"6131 ct",
    "addr:street":"Brandstr",
    "iso:country":"NL",
    "sg:address":"Brandstr 22",
    "sg:city":"Sittard",
    "sg:orig_category":"Kinderkleding",
    "sg:phone":"+31 46 452 4851",
    "sg:postcode":"6131 CT",
    "sg:province":"Limburg",
    "wof:name":"Reipke, 'T",
    "wof:placetype":"venue"
},
  "geometry": {"coordinates":[5.86573,50.998444],"type":"Point"}
}