{
  "type": "Feature",
  "properties": {
    "addr:full":"N Koninginnewal 2 Helmond Noord-Brabant 5701 NK",
    "addr:housenumber":"2",
    "addr:postcode":"5701 nk",
    "addr:street":"N Koninginnewal",
    "iso:country":"NL",
    "sg:address":"N Koninginnewal 2",
    "sg:city":"Helmond",
    "sg:orig_category":"Behangselpapier En Wandbekleding",
    "sg:phone":"+31 492 541 234",
    "sg:postcode":"5701 NK",
    "sg:province":"Noord-Brabant",
    "wof:name":"Beer, De",
    "wof:placetype":"venue"
},
  "geometry": {"coordinates":[5.657458,51.477131],"type":"Point"}
}