{
  "type": "Feature",
  "properties": {
    "addr:full":"Krachtenveld 22 Zeewolde Flevoland 3893 CD",
    "addr:housenumber":"22",
    "addr:postcode":"3893 cd",
    "addr:street":"Krachtenveld;Flevoland",
    "iso:country":"NL",
    "sg:address":"Krachtenveld 22",
    "sg:city":"Zeewolde",
    "sg:orig_category":"Horecabenodigdheden",
    "sg:phone":"+31 36 522 4867",
    "sg:postcode":"3893 CD",
    "sg:province":"Flevoland",
    "sg:website":"http://www.multitec.nl",
    "wof:name":"Multitec",
    "wof:placetype":"venue"
},
  "geometry": {"coordinates":[5.52516,52.330986],"type":"Point"}
}