{
  "type": "Feature",
  "properties": {
    "addr:full":"Citadel 3 Vyfhuizen North Holland 2141 MC",
    "addr:housenumber":"3;2141",
    "addr:postcode":"mc",
    "addr:street":"Citadel;North",
    "iso:country":"NL",
    "sg:address":"Citadel 3",
    "sg:city":"Vyfhuizen",
    "sg:orig_category":"Bedrijfsopleidingen",
    "sg:phone":"+31 23 558 3121",
    "sg:postcode":"2141 MC",
    "sg:province":"North Holland",
    "wof:name":"Nimwork",
    "wof:placetype":"venue"
},
  "geometry": {"coordinates":[4.675952,52.344128],"type":"Point"}
}