{
  "type": "Feature",
  "properties": {
    "addr:full":"Zuiderzeestrwg O 82 Elburg Gelderland 8081 LE",
    "addr:housenumber":"82",
    "addr:postcode":"8081 le",
    "addr:street":"Gelderland",
    "iso:country":"NL",
    "sg:address":"Zuiderzeestrwg O 82",
    "sg:city":"Elburg",
    "sg:orig_category":"Onroerende Goederen",
    "sg:phone":"+31 525 681 645",
    "sg:postcode":"8081 LE",
    "sg:province":"Gelderland",
    "wof:name":"Linde Bv, D Van Der",
    "wof:placetype":"venue"
},
  "geometry": {"coordinates":[5.835945,52.442108],"type":"Point"}
}