{
  "type": "Feature",
  "properties": {
    "addr:full":"Amaliastein 130 Vianen Ut Utrecht 4133 HD",
    "addr:housenumber":"130",
    "addr:postcode":"4133 hd",
    "addr:street":"Amaliastein",
    "iso:country":"NL",
    "sg:address":"Amaliastein 130",
    "sg:city":"Vianen Ut",
    "sg:orig_category":"Adviesbureaus Bedrijfsorganisatie",
    "sg:phone":"+31 347 328 346",
    "sg:postcode":"4133 HD",
    "sg:province":"Utrecht",
    "sg:website":"http://www.inwilution.com",
    "wof:name":"Inwilution Bv",
    "wof:placetype":"venue"
},
  "geometry": {"coordinates":[5.072726,51.988228],"type":"Point"}
}