{
  "type": "Feature",
  "properties": {
    "iso:country":"NL",
    "sg:address":"Pastoriestraat 149",
    "sg:city":"Eindhoven",
    "sg:orig_category":"Kantoor- And Schoolbenodigdheden Gh",
    "sg:phone":"+31 40 246 4660",
    "sg:postcode":"5612 EK",
    "sg:province":"North Brabant",
    "wof:name":"Proost En Brandt Bv",
    "wof:placetype":"venue"
},
  "geometry": {"coordinates":[5.4725470543,51.4525413513],"type":"Point"}
}