{
  "type": "Feature",
  "properties": {
    "addr:full":"Lopikerwg O 87A Lopik Utrecht 3411 JD",
    "addr:housenumber":"87a",
    "addr:postcode":"3411 jd",
    "addr:street":"O",
    "iso:country":"NL",
    "sg:address":"Lopikerwg O 87A",
    "sg:city":"Lopik",
    "sg:orig_category":"Loonbedrijven",
    "sg:phone":"+31 348 553 267",
    "sg:postcode":"3411 JD",
    "sg:province":"Utrecht",
    "wof:name":"Kers, T",
    "wof:placetype":"venue"
},
  "geometry": {"coordinates":[4.992014,51.984058],"type":"Point"}
}