{
  "type": "Feature",
  "properties": {
    "addr:full":"Walstr 59 Deventer Overijssel 7411 GK",
    "addr:housenumber":"59",
    "addr:postcode":"7411 gk",
    "addr:street":"Walstr",
    "iso:country":"NL",
    "sg:address":"Walstr 59",
    "sg:city":"Deventer",
    "sg:orig_category":"Huishoudelijke Apparaten En Artikelen",
    "sg:phone":"+31 570 615 019",
    "sg:postcode":"7411 GK",
    "sg:province":"Overijssel",
    "wof:name":"Teklewa Bv",
    "wof:placetype":"venue"
},
  "geometry": {"coordinates":[6.161883,52.253578],"type":"Point"}
}