{
  "type": "Feature",
  "properties": {
    "addr:full":"Nijverheidslaan 1 Weesp Noord-Holland 1382 LE",
    "addr:housenumber":"1",
    "addr:postcode":"1382 le",
    "addr:street":"Nijverheidslaan",
    "iso:country":"NL",
    "sg:address":"Nijverheidslaan 1",
    "sg:city":"Weesp",
    "sg:orig_category":"Farmaceutische Producten Gh",
    "sg:phone":"+31 294 433 038",
    "sg:postcode":"1382 LE",
    "sg:province":"Noord-Holland",
    "wof:name":"This Gas Analysis Systems",
    "wof:placetype":"venue"
},
  "geometry": {"coordinates":[5.048101,52.312096],"type":"Point"}
}