{
  "type": "Feature",
  "properties": {
    "iso:country":"NL",
    "sg:address":"Watermanwg 227",
    "sg:city":"Rotterdam",
    "sg:orig_category":"Meubelen",
    "sg:phone":"+31 10 220 3107",
    "sg:postcode":"3067 GA",
    "sg:province":"Zuid-Holland",
    "wof:name":"Domino Bv",
    "wof:placetype":"venue"
},
  "geometry": {"coordinates":[4.558687,51.951221],"type":"Point"}
}