{
  "type": "Feature",
  "properties": {
    "addr:full":"S Groeneweg Erf 109 Dordrecht Zuid-Holland 3315 XC",
    "addr:housenumber":"109",
    "addr:postcode":"3315 xc",
    "addr:street":"S Groeneweg Erf",
    "iso:country":"NL",
    "sg:address":"S Groeneweg Erf 109",
    "sg:city":"Dordrecht",
    "sg:orig_category":"Sanitaire Artikelen - Installatie En Onderhoud",
    "sg:phone":"+31 78 616 7373",
    "sg:postcode":"3315 XC",
    "sg:province":"Zuid-Holland",
    "wof:name":"Bellex, Badkamerspecialist",
    "wof:placetype":"venue"
},
  "geometry": {"coordinates":[4.717215,51.801311],"type":"Point"}
}